{
  "type": "Feature",
  "properties": {
    "iso:country":"ES",
    "sg:address":"Calle de Portugal, 39",
    "sg:city":"Fuenlabrada",
    "sg:orig_category":"Ense\u00d1anza Secundaria: Colegios Y Escuelas Privadas",
    "sg:phone":"+34 916 08 34 19",
    "sg:postcode":"28943",
    "sg:province":"Madrid",
    "wof:name":"Kepler Centro De Estudios S.l.",
    "wof:placetype":"venue"
},
  "geometry": {"coordinates":[-3.8095231056,40.2845077515],"type":"Point"}
}