{
  "type": "Feature",
  "properties": {
    "addr:full":"Calle de Quero, 47 Madrid Madrid 28024",
    "addr:housenumber":"47",
    "addr:postcode":"madrid;28024",
    "addr:street":"Calle De Quero",
    "iso:country":"ES",
    "sg:address":"Calle de Quero, 47",
    "sg:city":"Madrid",
    "sg:orig_category":"Ropa Para Se\u00d1oras (al Por Menor)",
    "sg:phone":"+34 917 17 10 03",
    "sg:postcode":"28024",
    "sg:province":"Madrid",
    "wof:name":"Garcia Jimenez Manuel",
    "wof:placetype":"venue"
},
  "geometry": {"coordinates":[-3.7610321045,40.3907585144],"type":"Point"}
}