{
  "type": "Feature",
  "properties": {
    "iso:country":"ES",
    "sg:address":"A Camba, 11",
    "sg:city":"Camba",
    "sg:orig_category":"Cerrajer\u00cda, Ferrallista",
    "sg:phone":"+34 986 64 14 13",
    "sg:postcode":"36865",
    "sg:province":"Pontevedra",
    "wof:name":"Cerrajeria Bargiela S.l",
    "wof:placetype":"venue"
},
  "geometry": {"coordinates":[-8.5024337769,42.1738243103],"type":"Point"}
}