{
  "type": "Feature",
  "properties": {
    "iso:country":"ES",
    "sg:address":"Calle de Marques De Valdegama, 35",
    "sg:city":"Villafranca De Los Barros",
    "sg:orig_category":"Contenedores (mercanc\u00cdas)",
    "sg:phone":"+34 924 52 46 61",
    "sg:postcode":"06220",
    "sg:province":"Badajoz",
    "wof:name":"Arenas Garcia Jose",
    "wof:placetype":"venue"
},
  "geometry": {"coordinates":[-6.3435025215,38.559299469],"type":"Point"}
}