{
  "type": "Feature",
  "properties": {
    "iso:country":"ES",
    "sg:address":"Av Principal, 3",
    "sg:city":"Picassent",
    "sg:orig_category":"Piscinas, Accesorios, Suministros (fabricaci\u00d3n, Al Por Mayor)",
    "sg:phone":"+34 961 24 08 66",
    "sg:postcode":"46220",
    "sg:province":"Valencia",
    "wof:name":"Material Actual S.l.",
    "wof:placetype":"venue"
},
  "geometry": {"coordinates":[-0.4595290124,39.3631401062],"type":"Point"}
}