{
  "type": "Feature",
  "properties": {
    "iso:country":"ES",
    "sg:address":"Calle de Santeren, 51",
    "sg:city":"Alhama Murcia",
    "sg:orig_category":"Molduras, Junquillos, Listones Y Molduras Perforadas",
    "sg:phone":"+34 968 63 13 85",
    "sg:postcode":"30840",
    "sg:province":"Murcia",
    "wof:name":"Garcia Bernal Isidro",
    "wof:placetype":"venue"
},
  "geometry": {"coordinates":[-1.428550005,37.8555145264],"type":"Point"}
}