{
  "type": "Feature",
  "properties": {
    "addr:full":"Calle de Bekolarra, 2 Vitoria-gasteiz \u00c1lava 01010",
    "addr:housenumber":"2",
    "addr:postcode":"01010",
    "addr:street":"Calle De Bekolarra",
    "iso:country":"ES",
    "sg:address":"Calle de Bekolarra, 2",
    "sg:city":"Vitoria-gasteiz",
    "sg:orig_category":"Transporte En General",
    "sg:phone":"+34 945 21 32 52",
    "sg:postcode":"01010",
    "sg:province":"\u00c1lava",
    "wof:name":"Herrera Del Rio Fermin",
    "wof:placetype":"venue"
},
  "geometry": {"coordinates":[-2.715195179,42.8573684692],"type":"Point"}
}