{
  "type": "Feature",
  "properties": {
    "addr:full":"Rua Covadonga, 1 Vigo Pontevedra 36208",
    "addr:housenumber":"1",
    "addr:postcode":"36208",
    "addr:street":"Rua Covadonga",
    "iso:country":"ES",
    "sg:address":"Rua Covadonga, 1",
    "sg:city":"Vigo",
    "sg:orig_category":"Supermercados Y Hipermercados",
    "sg:phone":"+34 986 24 42 46",
    "sg:postcode":"36208",
    "sg:province":"Pontevedra",
    "wof:name":"Distribuciones Froiz S.a.",
    "wof:placetype":"venue"
},
  "geometry": {"coordinates":[-8.752076149,42.2250976562],"type":"Point"}
}