{
  "type": "Feature",
  "properties": {
    "addr:full":"Urb Zenia Golf, S/n La Zenia Alicante 03189",
    "addr:housenumber":"/ n",
    "addr:postcode":"03189",
    "addr:street":"La Zenia",
    "iso:country":"ES",
    "sg:address":"Urb Zenia Golf, S/n",
    "sg:city":"La Zenia",
    "sg:orig_category":"Cl\u00cdnicas Dentales",
    "sg:phone":"+34 966 73 00 58",
    "sg:postcode":"03189",
    "sg:province":"Alicante",
    "wof:name":"Zahnarztpraxis-dr.nagel S.l.",
    "wof:placetype":"venue"
},
  "geometry": {"coordinates":[-0.7286275029,37.9253616333],"type":"Point"}
}