{
  "type": "Feature",
  "properties": {
    "iso:country":"ES",
    "sg:address":"Carrer de Santuari, 94",
    "sg:city":"Barcelona",
    "sg:orig_category":"Obras Y Organismos Sociales",
    "sg:phone":"+34 933 58 49 46",
    "sg:postcode":"08032",
    "sg:province":"Barcelona",
    "wof:name":"Mercedarias De La Caridad Hermanas Provincia De Zumarraga Curia Provincial",
    "wof:placetype":"venue"
},
  "geometry": {"coordinates":[2.1562380791,41.4196739197],"type":"Point"}
}