{
  "type": "Feature",
  "properties": {
    "addr:full":"Rua Coru\u00d1a (de La), 9 Monforte De Lemos Lugo 27400",
    "addr:postcode":"27400",
    "addr:street":"Rua Corun\u0303A De La 9",
    "iso:country":"ES",
    "sg:address":"Rua Coru\u00d1a (de La), 9",
    "sg:city":"Monforte De Lemos",
    "sg:orig_category":"Alimentaci\u00d3n General (al Por Menor)",
    "sg:phone":"+34 982 40 06 86",
    "sg:postcode":"27400",
    "sg:province":"Lugo",
    "wof:name":"Macia Gonzalez Luis",
    "wof:placetype":"venue"
},
  "geometry": {"coordinates":[-7.5103130341,42.5210800171],"type":"Point"}
}