{
  "type": "Feature",
  "properties": {
    "addr:full":"La Granda, S/n Granda Asturias 33439",
    "addr:housenumber":"s / n",
    "addr:postcode":"33439",
    "iso:country":"ES",
    "sg:address":"La Granda, S/n",
    "sg:city":"Granda",
    "sg:classifiers":[
        {
            "category":"Manufacturing",
            "subcategory":"Metals",
            "type":"Manufacturing & Wholesale Goods"
        }
    ],
    "sg:phone":"+34 985 57 54 12",
    "sg:postcode":"33439",
    "sg:province":"Asturias",
    "sg:tags":[
        "en",
        "fundiciones"
    ],
    "wof:name":"Talleres Sufer S. L.",
    "wof:placetype":"venue"
},
  "geometry": {"coordinates":[-5.8164548874,43.5645713806],"type":"Point"}
}