{
  "type": "Feature",
  "properties": {
    "addr:full":"Calle de Camelia, 66 Zaragoza Zaragoza 50012",
    "addr:housenumber":"66",
    "addr:postcode":"50012",
    "addr:street":"Calle De Camelia",
    "iso:country":"ES",
    "sg:address":"Calle de Camelia, 66",
    "sg:city":"Zaragoza",
    "sg:orig_category":"Art\u00cdculos Funerarios (al Por Menor)",
    "sg:phone":"+34 976 33 72 97",
    "sg:postcode":"50012",
    "sg:province":"Zaragoza",
    "wof:name":"Najucem S.a.",
    "wof:placetype":"venue"
},
  "geometry": {"coordinates":[-0.9245936275,41.6408233643],"type":"Point"}
}