{
  "type": "Feature",
  "properties": {
    "iso:country":"ES",
    "sg:address":"Avda Dinamarca, 17",
    "sg:city":"Sevilla",
    "sg:orig_category":"Cer\u00c1micas: Material Y Suministros",
    "sg:phone":"+34 954 61 30 64",
    "sg:postcode":"41012",
    "sg:province":"Sevilla",
    "wof:name":"Medtronic S.a.",
    "wof:placetype":"venue"
},
  "geometry": {"coordinates":[-5.9836740494,37.3459091187],"type":"Point"}
}