{
  "type": "Feature",
  "properties": {
    "iso:country":"ES",
    "sg:address":"Avda Virgen De Fatima (de), 15",
    "sg:city":"Cordoba",
    "sg:orig_category":"Frutas, Legumbres Frescas Y Tempranas (al Por Menor)",
    "sg:phone":"+34 957 25 03 08",
    "sg:postcode":"14014",
    "sg:province":"C\u00f3rdoba",
    "wof:name":"Mengual Hornero Juan Antonio",
    "wof:placetype":"venue"
},
  "geometry": {"coordinates":[-4.7581281662,37.8981170654],"type":"Point"}
}