{
  "type": "Feature",
  "properties": {
    "addr:full":"Plaz Mancha (de La), 15 Puertollano Ciudad Real 13500",
    "addr:postcode":"13500",
    "iso:country":"ES",
    "sg:address":"Plaz Mancha (de La), 15",
    "sg:city":"Puertollano",
    "sg:orig_category":"Autob\u00das (explotaci\u00d3n Y Servicios De)",
    "sg:phone":"+34 926 43 00 90",
    "sg:postcode":"13500",
    "sg:province":"Ciudad Real",
    "wof:name":"Autobuses Urbanos E Interurbanos De Puertollano S. L.",
    "wof:placetype":"venue"
},
  "geometry": {"coordinates":[-4.1104474068,38.6952438354],"type":"Point"}
}