{
  "type": "Feature",
  "properties": {
    "addr:full":"Avda Lopez De Mena, 12 San Pedro Alcantara M\u00e1laga 29670",
    "addr:housenumber":"12",
    "addr:postcode":"29670",
    "addr:street":"Avda Lopez De Mena",
    "iso:country":"ES",
    "sg:address":"Avda Lopez De Mena, 12",
    "sg:city":"San Pedro Alcantara",
    "sg:orig_category":"Fabricaci\u00d3n, Distribuci\u00d3n De Discos, V\u00cddeodiscos Y Musicassettes",
    "sg:phone":"+34 952 78 37 08",
    "sg:postcode":"29670",
    "sg:province":"M\u00e1laga",
    "wof:name":"Cosane S.l",
    "wof:placetype":"venue"
},
  "geometry": {"coordinates":[-4.9877858162,36.4841270447],"type":"Point"}
}