{
  "type": "Feature",
  "properties": {
    "addr:full":"Calle de Real Abajo, S/n Vallelado Segovia 40213",
    "addr:housenumber":"s",
    "addr:postcode":"40213",
    "addr:street":"Calle De;Abajo;/ N Vallelado Segovia",
    "iso:country":"ES",
    "sg:address":"Calle de Real Abajo, S/n",
    "sg:city":"Vallelado",
    "sg:orig_category":"Muebles Y Accesorios Para Cocinas Y Cuartos De Ba\u00d1o (al Por Menor)",
    "sg:phone":"+34 921 15 01 17",
    "sg:postcode":"40213",
    "sg:province":"Segovia",
    "wof:name":"Cuellar Gonzalez Antonio",
    "wof:placetype":"venue"
},
  "geometry": {"coordinates":[-4.433262825,41.401725769],"type":"Point"}
}