{
  "type": "Feature",
  "properties": {
    "iso:country":"ES",
    "sg:address":"Calle de Fabiola De Mora, 23",
    "sg:city":"Socuellamos",
    "sg:orig_category":"Telas Y Sedas (al Por Menor)",
    "sg:phone":"+34 926 53 22 71",
    "sg:postcode":"13630",
    "sg:province":"Ciudad Real",
    "wof:name":"Leon Perona Manuel",
    "wof:placetype":"venue"
},
  "geometry": {"coordinates":[-2.7943139076,39.2868041992],"type":"Point"}
}