{
  "type": "Feature",
  "properties": {
    "addr:full":"Carrer de Hondures, 27 Barcelona Barcelona 08027",
    "addr:housenumber":"27",
    "addr:postcode":"08027",
    "addr:street":"Carrer De Hondures",
    "iso:country":"ES",
    "sg:address":"Carrer de Hondures, 27",
    "sg:city":"Barcelona",
    "sg:orig_category":"Administradores De Bienes Y Delegados De Comunidades De Propietarios",
    "sg:phone":"+34 933 52 47 49",
    "sg:postcode":"08027",
    "sg:province":"Barcelona",
    "wof:name":"Esteban Egusquiza Salvador",
    "wof:placetype":"venue"
},
  "geometry": {"coordinates":[2.1901938915,41.4194641113],"type":"Point"}
}