{
  "type": "Feature",
  "properties": {
    "addr:full":"Playa Algeciras, 1 Bonanza Madrid 28669",
    "addr:housenumber":"1",
    "addr:postcode":"28669",
    "addr:street":"Algeciras",
    "iso:country":"ES",
    "sg:address":"Playa Algeciras, 1",
    "sg:city":"Bonanza",
    "sg:orig_category":"Empresarios Y Productoras De Espect\u00c1culos",
    "sg:phone":"+34 916 33 19 62",
    "sg:postcode":"28669",
    "sg:province":"Madrid",
    "wof:name":"Mafalda",
    "wof:placetype":"venue"
},
  "geometry": {"coordinates":[-3.8848030567,40.4467582703],"type":"Point"}
}