{
  "type": "Feature",
  "properties": {
    "iso:country":"ES",
    "sg:address":"Calle de Oloron Santa Maria, 2",
    "sg:city":"Jaca",
    "sg:orig_category":"Alimentaci\u00d3n General (al Por Menor)",
    "sg:phone":"+34 974 35 67 32",
    "sg:postcode":"22700",
    "sg:province":"Huesca",
    "wof:name":"7 Alimentacion 7 S.a.",
    "wof:placetype":"venue"
},
  "geometry": {"coordinates":[-0.548276,42.57415],"type":"Point"}
}