{
  "type": "Feature",
  "properties": {
    "addr:full":"Ptda Ratils, 1 Ratils Castell\u00f3n 12200",
    "addr:housenumber":"1",
    "addr:postcode":"12200",
    "addr:street":"Ptda Ratils;Castello\u0301N",
    "iso:country":"ES",
    "sg:address":"Ptda Ratils, 1",
    "sg:city":"Ratils",
    "sg:orig_category":"Bebidas",
    "sg:phone":"+34 964 60 11 85",
    "sg:postcode":"12200",
    "sg:province":"Castell\u00f3n",
    "wof:name":"Francisco Jose Gonzalez Castello Y Otro C.b.",
    "wof:placetype":"venue"
},
  "geometry": {"coordinates":[-0.2620640099,39.9651794434],"type":"Point"}
}