{
  "type": "Feature",
  "properties": {
    "addr:full":"Calle de Argos, 23 Madrid Madrid 28037",
    "addr:housenumber":"23",
    "addr:postcode":"madrid;28037",
    "addr:street":"Calle De Argos",
    "iso:country":"ES",
    "sg:address":"Calle de Argos, 23",
    "sg:city":"Madrid",
    "sg:orig_category":"Inversiones",
    "sg:phone":"+34 913 27 29 72",
    "sg:postcode":"28037",
    "sg:province":"Madrid",
    "wof:name":"Opins Inversiones S.l.",
    "wof:placetype":"venue"
},
  "geometry": {"coordinates":[-3.6336216927,40.43724823],"type":"Point"}
}