{
  "type": "Feature",
  "properties": {
    "iso:country":"ES",
    "sg:address":"Avda Espa\u00d1a (de), 18",
    "sg:city":"Alcobendas",
    "sg:orig_category":"Administradores De Bienes Y Delegados De Comunidades De Propietarios",
    "sg:phone":"+34 916 54 40 10",
    "sg:postcode":"28100",
    "sg:province":"Madrid",
    "wof:name":"Glr Asesores De Empresas S.l.",
    "wof:placetype":"venue"
},
  "geometry": {"coordinates":[-3.6426739693,40.5457458496],"type":"Point"}
}