{
  "type": "Feature",
  "properties": {
    "addr:full":"Av. Cruz, 3 Museros Valencia 46136",
    "addr:housenumber":"3",
    "addr:postcode":"46136",
    "addr:street":"Av. Cruz",
    "iso:country":"ES",
    "sg:address":"Av. Cruz, 3",
    "sg:city":"Museros",
    "sg:orig_category":"Peluqueros: De Se\u00d1oras",
    "sg:phone":"+34 961 44 00 96",
    "sg:postcode":"46136",
    "sg:province":"Valencia",
    "wof:name":"Costa Garcia Amparo",
    "wof:placetype":"venue"
},
  "geometry": {"coordinates":[-0.3390020132,39.5615348816],"type":"Point"}
}