{
  "type": "Feature",
  "properties": {
    "addr:full":"Ctra. Logro\u00f1o, Km. 0291,2 Mallen Zaragoza 50550",
    "addr:postcode":"50550",
    "addr:street":"Ctra. Logron\u0303O Km. 0291,2",
    "iso:country":"ES",
    "sg:address":"Ctra. Logro\u00f1o, Km. 0291,2",
    "sg:city":"Mallen",
    "sg:orig_category":"Distribuci\u00d3n De Petr\u00d3leo Y Derivados",
    "sg:phone":"+34 976 85 03 76",
    "sg:postcode":"50550",
    "sg:province":"Zaragoza",
    "wof:name":"Serviaragon S.a.",
    "wof:placetype":"venue"
},
  "geometry": {"coordinates":[-1.4205390215,41.9020500183],"type":"Point"}
}