{
  "type": "Feature",
  "properties": {
    "addr:full":"Calle de Pilar (el), 19 Santa Cruz De Tenerife Santa Cruz De Tenerife 38002",
    "addr:housenumber":"19",
    "addr:postcode":"38002",
    "addr:street":"Calle De Pilar El",
    "iso:country":"ES",
    "sg:address":"Calle de Pilar (el), 19",
    "sg:city":"Santa Cruz De Tenerife",
    "sg:orig_category":"Abogados",
    "sg:phone":"+34 922 28 60 36",
    "sg:postcode":"38002",
    "sg:province":"Santa Cruz De Tenerife",
    "wof:name":"Montoya Ezquerra Francisco Jose",
    "wof:placetype":"venue"
},
  "geometry": {"coordinates":[-16.2520122528,28.4697246552],"type":"Point"}
}