{
  "type": "Feature",
  "properties": {
    "iso:country":"ES",
    "sg:address":"Calle de Doramas, 42",
    "sg:city":"Galdar",
    "sg:orig_category":"M\u00c9dicos: Pediatr\u00cda. Enfermedades De Los Ni\u00d1os",
    "sg:phone":"+34 928 55 29 30",
    "sg:postcode":"35460",
    "sg:province":"Las Palmas",
    "wof:name":"Ramos Diaz Antonio",
    "wof:placetype":"venue"
},
  "geometry": {"coordinates":[-15.6534719467,28.1469898224],"type":"Point"}
}