{
  "type": "Feature",
  "properties": {
    "addr:full":"Av Juan Gil - Albert, 11 Alcoi Alicante 03804",
    "addr:housenumber":"11",
    "addr:postcode":"03804",
    "addr:street":"Av Juan Gil Albert",
    "iso:country":"ES",
    "sg:address":"Av Juan Gil - Albert, 11",
    "sg:city":"Alcoi",
    "sg:orig_category":"Inmobiliaria (agencias)",
    "sg:phone":"+34 966 52 36 79",
    "sg:postcode":"03804",
    "sg:province":"Alicante",
    "wof:name":"Motilla Canto Paulino",
    "wof:placetype":"venue"
},
  "geometry": {"coordinates":[-0.4728690088,38.7060585022],"type":"Point"}
}