{
  "type": "Feature",
  "properties": {
    "addr:full":"Avda Alberto Alcocer, 3 Madrid Madrid 28036",
    "addr:housenumber":"3",
    "addr:postcode":"28036",
    "addr:street":"Alberto Alcocer",
    "iso:country":"ES",
    "sg:address":"Avda Alberto Alcocer, 3",
    "sg:city":"Madrid",
    "sg:orig_category":"Estancos",
    "sg:phone":"+34 913 59 10 42",
    "sg:postcode":"28036",
    "sg:province":"Madrid",
    "wof:name":"Valle-inclan Lapido Ramon",
    "wof:placetype":"venue"
},
  "geometry": {"coordinates":[-3.6889369488,40.4590759277],"type":"Point"}
}