{
  "type": "Feature",
  "properties": {
    "iso:country":"ES",
    "sg:address":"Calle de Nu\u00d1ez De Balboa, 10",
    "sg:city":"Zamora",
    "sg:orig_category":"Ropa Para Se\u00d1oras Y Caballeros (al Por Menor)",
    "sg:phone":"+34 980 52 02 53",
    "sg:postcode":"49019",
    "sg:province":"Zamora",
    "wof:name":"Ballesteros Rodriguez Paloma",
    "wof:placetype":"venue"
},
  "geometry": {"coordinates":[-5.7341079712,41.5105056763],"type":"Point"}
}