{
  "type": "Feature",
  "properties": {
    "addr:full":"Carrer de Aribau, 114 Barcelona Barcelona 08036",
    "addr:housenumber":"114",
    "addr:postcode":"08036",
    "addr:street":"Carrer De Aribau",
    "iso:country":"ES",
    "sg:address":"Carrer de Aribau, 114",
    "sg:city":"Barcelona",
    "sg:orig_category":"Peluqueros: De Se\u00d1oras",
    "sg:phone":"+34 934 53 33 09",
    "sg:postcode":"08036",
    "sg:province":"Barcelona",
    "wof:name":"Canonigo Hermo Esperanza",
    "wof:placetype":"venue"
},
  "geometry": {"coordinates":[2.1561830044,41.3909645081],"type":"Point"}
}