{
  "type": "Feature",
  "properties": {
    "addr:full":"Calle de Rua Antigua, 5 Salamanca Salamanca 37002",
    "addr:housenumber":"5",
    "addr:postcode":"37002",
    "addr:street":"Calle De Rua Antigua",
    "iso:country":"ES",
    "sg:address":"Calle de Rua Antigua, 5",
    "sg:city":"Salamanca",
    "sg:orig_category":"Artes Gr\u00c1ficas, Artes Pl\u00c1sticas (curso)",
    "sg:phone":"+34 923 21 86 67",
    "sg:postcode":"37002",
    "sg:province":"Salamanca",
    "wof:name":"Martin Ortiz Jose Maria",
    "wof:placetype":"venue"
},
  "geometry": {"coordinates":[-5.6660227776,40.9625892639],"type":"Point"}
}