{
  "type": "Feature",
  "properties": {
    "iso:country":"ES",
    "sg:address":"Avda Retamas (las), 47",
    "sg:city":"Alcorcon",
    "sg:orig_category":"Postigos, Persianas Y Celos\u00cdas",
    "sg:phone":"+34 916 43 88 74",
    "sg:postcode":"28922",
    "sg:province":"Madrid",
    "wof:name":"Gonzalez Gonzalez Carmen",
    "wof:placetype":"venue"
},
  "geometry": {"coordinates":[-3.8298609257,40.3376083374],"type":"Point"}
}