{
  "type": "Feature",
  "properties": {
    "iso:country":"ES",
    "sg:address":"Calle de Escalante, 12",
    "sg:city":"Valencia",
    "sg:orig_category":"Fabricaci\u00d3n, Reparaci\u00d3n Y Mantenimiento De Construcciones Navales Y Fluviales",
    "sg:phone":"+34 963 67 66 61",
    "sg:postcode":"46011",
    "sg:province":"Valencia",
    "wof:name":"Compa\u00d1ia Radio Aerea Maritima Espa\u00d1ola S.a.",
    "wof:placetype":"venue"
},
  "geometry": {"coordinates":[-0.3317280114,39.461894989],"type":"Point"}
}