{
  "type": "Feature",
  "properties": {
    "addr:full":"Calle de Vazquez Lopez, 16 Huelva Huelva 21001",
    "addr:housenumber":"16",
    "addr:postcode":"21001",
    "addr:street":"Calle De Vazquez Lopez",
    "iso:country":"ES",
    "sg:address":"Calle de Vazquez Lopez, 16",
    "sg:city":"Huelva",
    "sg:orig_category":"Contables",
    "sg:phone":"+34 959 26 38 60",
    "sg:postcode":"21001",
    "sg:province":"Huelva",
    "wof:name":"Ramos Marquez Maria Teresa",
    "wof:placetype":"venue"
},
  "geometry": {"coordinates":[-6.9519538879,37.255607605],"type":"Point"}
}