{
  "type": "Feature",
  "properties": {
    "addr:full":"Calle de Fueros (los), 6 Caparroso Navarra 31380",
    "addr:housenumber":"6",
    "addr:postcode":"31380",
    "addr:street":"Calle De Fueros Los",
    "iso:country":"ES",
    "sg:address":"Calle de Fueros (los), 6",
    "sg:city":"Caparroso",
    "sg:orig_category":"Centros De Educaci\u00d3n Especial",
    "sg:phone":"+34 948 73 01 09",
    "sg:postcode":"31380",
    "sg:province":"Navarra",
    "wof:name":"Colegio Publico Nuestra Se\u00f1ora Virgen Del Soto",
    "wof:placetype":"venue"
},
  "geometry": {"coordinates":[-1.6500500441,42.3419418335],"type":"Point"}
}