{
  "type": "Feature",
  "properties": {
    "addr:full":"Calle de Newton, 1 Grela La Coru\u00f1a 15008",
    "addr:housenumber":"1",
    "addr:postcode":"15008",
    "addr:street":"Calle De Newton;La Corun\u0303A",
    "iso:country":"ES",
    "sg:address":"Calle de Newton, 1",
    "sg:city":"Grela",
    "sg:orig_category":"Agentes, Concesionarios Y Sucursales De Veh\u00cdculos",
    "sg:phone":"+34 981 16 00 99",
    "sg:postcode":"15008",
    "sg:province":"La Coru\u00f1a",
    "wof:name":"Breogan Motor S.l.",
    "wof:placetype":"venue"
},
  "geometry": {"coordinates":[-8.4512443542,43.3434753418],"type":"Point"}
}