{
  "type": "Feature",
  "properties": {
    "addr:full":"Calle de Marco Aurelio, 7 Torreciega Murcia 30392",
    "addr:housenumber":"7",
    "addr:postcode":"30392",
    "addr:street":"Calle De Marco Aurelio",
    "iso:country":"ES",
    "sg:address":"Calle de Marco Aurelio, 7",
    "sg:city":"Torreciega",
    "sg:orig_category":"Montaje (empresas De)",
    "sg:phone":"+34 968 52 21 12",
    "sg:postcode":"30392",
    "sg:province":"Murcia",
    "wof:name":"Cegelec S.a.",
    "wof:placetype":"venue"
},
  "geometry": {"coordinates":[-0.967738986,37.6146888733],"type":"Point"}
}