{
  "type": "Feature",
  "properties": {
    "addr:full":"Pg Saladar, 77 Denia Alicante 03700",
    "addr:housenumber":"77",
    "addr:postcode":"03700",
    "addr:street":"Pg Saladar",
    "iso:country":"ES",
    "sg:address":"Pg Saladar, 77",
    "sg:city":"Denia",
    "sg:orig_category":"Centros De Coordinaci\u00d3n",
    "sg:phone":"+34 965 78 50 61",
    "sg:postcode":"03700",
    "sg:province":"Alicante",
    "wof:name":"Tecnicos Asociados Consulting S.l.",
    "wof:placetype":"venue"
},
  "geometry": {"coordinates":[0.1099950001,38.8391685486],"type":"Point"}
}