{
  "type": "Feature",
  "properties": {
    "addr:full":"Calle de Poeta Carmelo Calvo, 14 Alacant Alicante 03004",
    "addr:housenumber":"14",
    "addr:postcode":"03004",
    "addr:street":"Calle De Poeta Carmelo Calvo",
    "iso:country":"ES",
    "sg:address":"Calle de Poeta Carmelo Calvo, 14",
    "sg:city":"Alacant",
    "sg:orig_category":"Venta, Colocaci\u00d3n, Reparaci\u00d3n De Parabrisas, Techos Descapotables",
    "sg:phone":"+34 965 21 44 36",
    "sg:postcode":"03004",
    "sg:province":"Alicante",
    "sg:website":"www.guardianexpress.es",
    "wof:name":"Guardian Glass Express S.l.",
    "wof:placetype":"venue"
},
  "geometry": {"coordinates":[-0.4876529872,38.3509216309],"type":"Point"}
}