{
  "type": "Feature",
  "properties": {
    "addr:full":"Carrer de Can Ceferi, 40 Carrer De Dalt -pineda -pla De L'alzina Barcelona 08184",
    "addr:housenumber":"40",
    "addr:postcode":"08184",
    "addr:street":"Carrer De Can Ceferi;Carrer De Dalt Pineda Pla De L'Alzina Barcelona",
    "iso:country":"ES",
    "sg:address":"Carrer de Can Ceferi, 40",
    "sg:city":"Carrer De Dalt -pineda -pla De L'alzina",
    "sg:orig_category":"Mec\u00c1nico Del Autom\u00d3vil",
    "sg:phone":"+34 938 64 93 89",
    "sg:postcode":"08184",
    "sg:province":"Barcelona",
    "wof:name":"Auto Esteve S.l.",
    "wof:placetype":"venue"
},
  "geometry": {"coordinates":[2.1761360168,41.5975990295],"type":"Point"}
}