{
  "type": "Feature",
  "properties": {
    "iso:country":"ES",
    "sg:address":"Avda Constitucion, 224",
    "sg:city":"Villena",
    "sg:orig_category":"Electricidad, Electr\u00d3nica: Suministros (al Por Menor)",
    "sg:phone":"+34 965 34 86 26",
    "sg:postcode":"03400",
    "sg:province":"Alicante",
    "sg:website":"www.delytel.com",
    "wof:name":"Delytel Electronica S.l.",
    "wof:placetype":"venue"
},
  "geometry": {"coordinates":[-0.8699910045,38.6455001831],"type":"Point"}
}