{
  "type": "Feature",
  "properties": {
    "addr:full":"Carrer de Sagunt, 55 Barcelona Barcelona 08014",
    "addr:housenumber":"55",
    "addr:postcode":"08014",
    "addr:street":"Carrer De Sagunt",
    "iso:country":"ES",
    "sg:address":"Carrer de Sagunt, 55",
    "sg:city":"Barcelona",
    "sg:orig_category":"Poller\u00cda Y Caza (al Por Menor)",
    "sg:phone":"+34 933 32 26 91",
    "sg:postcode":"08014",
    "sg:province":"Barcelona",
    "wof:name":"Vallverdu Pujol Magdalena",
    "wof:placetype":"venue"
},
  "geometry": {"coordinates":[2.1345698833,41.3714027405],"type":"Point"}
}