{
  "type": "Feature",
  "properties": {
    "addr:full":"Calle de Circunvalacion, Km. 0004,0 Casas De Fernando Alonso Cuenca 16610",
    "addr:postcode":"16610",
    "addr:street":"Calle De Circunvalacion Km. 0004,0",
    "iso:country":"ES",
    "sg:address":"Calle de Circunvalacion, Km. 0004,0",
    "sg:city":"Casas De Fernando Alonso",
    "sg:orig_category":"Trabajos De Soldaduras",
    "sg:phone":"+34 969 38 35 02",
    "sg:postcode":"16610",
    "sg:province":"Cuenca",
    "wof:name":"Martinez Ortega Jose Manuel",
    "wof:placetype":"venue"
},
  "geometry": {"coordinates":[-2.321495533,39.34740448],"type":"Point"}
}