{
  "type": "Feature",
  "properties": {
    "iso:country":"ES",
    "sg:address":"Carrer de Amadeu Torner, 74",
    "sg:city":"Hospitalet Llobregat",
    "sg:orig_category":"Ense\u00d1anza, Formaci\u00d3n Profesional: Aprendizaje",
    "sg:phone":"+34 934 31 75 89",
    "sg:postcode":"08902",
    "sg:province":"Barcelona",
    "sg:website":"www.cteep.com",
    "wof:name":"Centro Tecnico Europeo De Ense\u00f1anzas Profesionales S.l.",
    "wof:placetype":"venue"
},
  "geometry": {"coordinates":[2.1222760677,41.3625411987],"type":"Point"}
}