{
  "type": "Feature",
  "properties": {
    "addr:full":"Calle de Fermin Lasuen, 7 Vitoria-gasteiz \u00c1lava 01013",
    "addr:housenumber":"7",
    "addr:postcode":"01013",
    "addr:street":"Calle De Fermin Lasuen",
    "iso:country":"ES",
    "sg:address":"Calle de Fermin Lasuen, 7",
    "sg:city":"Vitoria-gasteiz",
    "sg:orig_category":"Bazares, Art\u00cdculos De Limpieza Y De Cocina (al Por Menor)",
    "sg:phone":"+34 945 26 14 69",
    "sg:postcode":"01013",
    "sg:province":"\u00c1lava",
    "wof:name":"Hundred-gazteiz S.l.",
    "wof:placetype":"venue"
},
  "geometry": {"coordinates":[-2.6700251102,42.8555488586],"type":"Point"}
}