{
  "type": "Feature",
  "properties": {
    "iso:country":"ES",
    "sg:address":"Calle de Chile, 1",
    "sg:city":"Coslada",
    "sg:orig_category":"Producci\u00d3n, Distribuci\u00d3n De Electricidad",
    "sg:phone":"+34 916 74 01 29",
    "sg:postcode":"28820",
    "sg:province":"Madrid",
    "wof:name":"Generadores Electricos Bravo S.l",
    "wof:placetype":"venue"
},
  "geometry": {"coordinates":[-3.5553975105,40.4249382019],"type":"Point"}
}