{
  "type": "Feature",
  "properties": {
    "iso:country":"ES",
    "sg:address":"Rua Severo Ochoa, 5",
    "sg:city":"Vigo",
    "sg:orig_category":"Agencias Y Asesores De Publicidad",
    "sg:phone":"+34 986 23 68 97",
    "sg:postcode":"36202",
    "sg:province":"Pontevedra",
    "wof:name":"Europea De Porta Documentos Y Publicidad S.l",
    "wof:placetype":"venue"
},
  "geometry": {"coordinates":[-8.7339096069,42.228767395],"type":"Point"}
}