{
  "type": "Feature",
  "properties": {
    "addr:full":"Calle de Olivar, 47 Madrid Madrid 28012",
    "addr:housenumber":"47",
    "addr:postcode":"madrid;28012",
    "addr:street":"Calle De Olivar",
    "iso:country":"ES",
    "sg:address":"Calle de Olivar, 47",
    "sg:city":"Madrid",
    "sg:orig_category":"\u00d3ptica: Instrumentos (fabricaci\u00d3n)",
    "sg:phone":"+34 915 28 04 07",
    "sg:postcode":"28012",
    "sg:province":"Madrid",
    "wof:name":"Carazo Minguez Carlos",
    "wof:placetype":"venue"
},
  "geometry": {"coordinates":[-3.7012159824,40.409236908],"type":"Point"}
}