{
  "type": "Feature",
  "properties": {
    "iso:country":"ES",
    "sg:address":"Calle de Ramiro I, 2",
    "sg:city":"Oviedo",
    "sg:orig_category":"Cajas De Ahorro",
    "sg:phone":"+34 985 23 06 01",
    "sg:postcode":"33012",
    "sg:province":"Asturias",
    "wof:name":"Caja De Ahorros De Asturias",
    "wof:placetype":"venue"
},
  "geometry": {"coordinates":[-5.8603811264,43.3645629883],"type":"Point"}
}