{
  "type": "Feature",
  "properties": {
    "addr:full":"Calle de San Esteban, S/n Pedrajas S. Esteban Valladolid 47430",
    "addr:housenumber":"s / n",
    "addr:postcode":"47430",
    "addr:street":"Calle De San;Pedrajas S. Esteban Valladolid",
    "iso:country":"ES",
    "sg:address":"Calle de San Esteban, S/n",
    "sg:city":"Pedrajas S. Esteban",
    "sg:orig_category":"Pescader\u00cdas (al Por Menor)",
    "sg:phone":"+34 983 62 58 79",
    "sg:postcode":"47430",
    "sg:province":"Valladolid",
    "wof:name":"Arranz Arranz Cesareo",
    "wof:placetype":"venue"
},
  "geometry": {"coordinates":[-4.5838260651,41.3414306641],"type":"Point"}
}