{
  "type": "Feature",
  "properties": {
    "iso:country":"ES",
    "sg:address":"Avda Boliches De Los, 93",
    "sg:city":"Fuengirola",
    "sg:orig_category":"Cl\u00cdnicas M\u00c9dicas",
    "sg:phone":"+34 952 46 00 40",
    "sg:postcode":"29640",
    "sg:province":"M\u00e1laga",
    "wof:name":"Naesgaard  Jens",
    "wof:placetype":"venue"
},
  "geometry": {"coordinates":[-4.6330537796,36.5426368713],"type":"Point"}
}