{
  "type": "Feature",
  "properties": {
    "addr:full":"Seara, 26 Masma Lugo 27749",
    "addr:housenumber":"26",
    "addr:postcode":"27749",
    "addr:street":"Seara",
    "iso:country":"ES",
    "sg:address":"Seara, 26",
    "sg:city":"Masma",
    "sg:orig_category":"Explotaci\u00d3n De Bosques",
    "sg:phone":"+34 982 51 94 24",
    "sg:postcode":"27749",
    "sg:province":"Lugo",
    "wof:name":"Maderas Masma S.l.",
    "wof:placetype":"venue"
},
  "geometry": {"coordinates":[-7.3447489738,43.47082901],"type":"Point"}
}