{
  "type": "Feature",
  "properties": {
    "addr:full":"Calle de Garcia Lorca, 16 Olula Rio Almer\u00eda 04860",
    "addr:housenumber":"16",
    "addr:postcode":"04860",
    "addr:street":"Calle De Garcia Lorca;Almeri\u0301A",
    "iso:country":"ES",
    "sg:address":"Calle de Garcia Lorca, 16",
    "sg:city":"Olula Rio",
    "sg:orig_category":"Art\u00cdculos Funerarios (al Por Menor)",
    "sg:phone":"+34 950 44 21 22",
    "sg:postcode":"04860",
    "sg:province":"Almer\u00eda",
    "wof:name":"Garcia Reche Jose",
    "wof:placetype":"venue"
},
  "geometry": {"coordinates":[-2.2962779999,37.3541145325],"type":"Point"}
}