{
  "type": "Feature",
  "properties": {
    "iso:country":"ES",
    "sg:address":"Calle de Veinte De Febrero, 11",
    "sg:city":"Valladolid",
    "sg:orig_category":"Inmobiliaria (agencias)",
    "sg:phone":"+34 983 33 59 77",
    "sg:postcode":"47001",
    "sg:province":"Valladolid",
    "wof:name":"Ansorena De Bienes S.a.",
    "wof:placetype":"venue"
},
  "geometry": {"coordinates":[-4.7323856354,41.6502113342],"type":"Point"}
}