{
  "type": "Feature",
  "properties": {
    "addr:full":"Calle de Republica Argentina, 15 Badajoz Badajoz 06005",
    "addr:housenumber":"15",
    "addr:postcode":"06005",
    "addr:street":"Calle De Republica Argentina",
    "iso:country":"ES",
    "sg:address":"Calle de Republica Argentina, 15",
    "sg:city":"Badajoz",
    "sg:orig_category":"M\u00c9dicos: Estomatolog\u00cda",
    "sg:phone":"+34 924 26 08 88",
    "sg:postcode":"06005",
    "sg:province":"Badajoz",
    "wof:name":"Leopoldo Rodado Fernando",
    "wof:placetype":"venue"
},
  "geometry": {"coordinates":[-6.9791412354,38.8738594055],"type":"Point"}
}