{
  "type": "Feature",
  "properties": {
    "addr:full":"Garcia Ximenez, 5 Iru\u00f1a Navarra 31002",
    "addr:housenumber":"5",
    "addr:postcode":"31002",
    "addr:street":"Garcia Ximenez",
    "iso:country":"ES",
    "sg:address":"Garcia Ximenez, 5",
    "sg:city":"Iru\u00f1a",
    "sg:orig_category":"Herboristas (al Por Menor)",
    "sg:phone":"+34 948 22 41 80",
    "sg:postcode":"31002",
    "sg:province":"Navarra",
    "wof:name":"Torres Torres Maria Asuncion",
    "wof:placetype":"venue"
},
  "geometry": {"coordinates":[-1.6443710327,42.8134384155],"type":"Point"}
}