{
  "type": "Feature",
  "properties": {
    "addr:full":"Plaz Sagrado Corazon, 2 Valdealgorfa Teruel 44594",
    "addr:housenumber":"2",
    "addr:postcode":"44594",
    "addr:street":"Corazon",
    "iso:country":"ES",
    "sg:address":"Plaz Sagrado Corazon, 2",
    "sg:city":"Valdealgorfa",
    "sg:orig_category":"Molduras, Junquillos, Listones Y Molduras Perforadas",
    "sg:phone":"+34 978 85 70 06",
    "sg:postcode":"44594",
    "sg:province":"Teruel",
    "wof:name":"Merino Herrero Moises",
    "wof:placetype":"venue"
},
  "geometry": {"coordinates":[-0.0346239991,40.9885292053],"type":"Point"}
}