{
  "type": "Feature",
  "properties": {
    "addr:full":"Carr Pintor Calbo, 2 Mao Islas Baleares 07703",
    "addr:housenumber":"2",
    "addr:postcode":"07703",
    "addr:street":"Carr Pintor Calbo",
    "iso:country":"ES",
    "sg:address":"Carr Pintor Calbo, 2",
    "sg:city":"Mao",
    "sg:orig_category":"Librer\u00cdas",
    "sg:phone":"+34 971 36 79 13",
    "sg:postcode":"07703",
    "sg:province":"Islas Baleares",
    "wof:name":"Riudavets Carreras Cristina",
    "wof:placetype":"venue"
},
  "geometry": {"coordinates":[4.2582402229,39.8856925964],"type":"Point"}
}