{
  "type": "Feature",
  "properties": {
    "addr:full":"Astintze Kalea, 4 Derio Vizcaya 48160",
    "addr:housenumber":"4",
    "addr:postcode":"48160",
    "addr:street":"Astintze Kalea",
    "iso:country":"ES",
    "sg:address":"Astintze Kalea, 4",
    "sg:city":"Derio",
    "sg:orig_category":"Panader\u00cdas, Panader\u00cdas",
    "sg:phone":"+34 944 54 36 89",
    "sg:postcode":"48160",
    "sg:province":"Vizcaya",
    "wof:name":"Panrico S.l.u.",
    "wof:placetype":"venue"
},
  "geometry": {"coordinates":[-2.8869380951,43.2908973694],"type":"Point"}
}