{
  "type": "Feature",
  "properties": {
    "iso:country":"ES",
    "sg:address":"C/ Antonio Sansano Franco, 24",
    "sg:city":"Elche",
    "sg:orig_category":"\u00d3ptica: Instrumentos (fabricaci\u00d3n)",
    "sg:phone":"+34 966 63 11 57",
    "sg:postcode":"03204",
    "sg:province":"Alicante",
    "wof:name":"Vicente Climent Pedro Jose",
    "wof:placetype":"venue"
},
  "geometry": {"coordinates":[-0.7052249908,38.2569580078],"type":"Point"}
}