{
  "type": "Feature",
  "properties": {
    "iso:country":"ES",
    "sg:address":"Av Conqueridor, 17",
    "sg:city":"Ciutadella Menorca",
    "sg:orig_category":"Zapatos (al Por Menor)",
    "sg:phone":"+34 971 38 51 13",
    "sg:postcode":"07760",
    "sg:province":"Islas Baleares",
    "wof:name":"Fincas Alfa Menorca, S.l.",
    "wof:placetype":"venue"
},
  "geometry": {"coordinates":[3.8411369324,40.0016593933],"type":"Point"}
}