{
  "type": "Feature",
  "properties": {
    "addr:full":"Carr Corbella, (de La), 126 Carlet Valencia 46240",
    "addr:housenumber":"126",
    "addr:postcode":"46240",
    "addr:street":"Carr Corbella De La",
    "iso:country":"ES",
    "sg:address":"Carr Corbella, (de La), 126",
    "sg:city":"Carlet",
    "sg:orig_category":"Freidur\u00cdas: Equipos Y Suministros",
    "sg:phone":"+34 962 53 03 63",
    "sg:postcode":"46240",
    "sg:province":"Valencia",
    "wof:name":"Rey Martinez Salvador",
    "wof:placetype":"venue"
},
  "geometry": {"coordinates":[-0.5206720233,39.2221794128],"type":"Point"}
}