{
  "type": "Feature",
  "properties": {
    "addr:full":"Avda Doctor Vilardell, S/n Castejon Monegros Huesca 22222",
    "addr:housenumber":"s / n",
    "addr:postcode":"22222",
    "addr:street":"Avda Doctor Vilardell",
    "iso:country":"ES",
    "sg:address":"Avda Doctor Vilardell, S/n",
    "sg:city":"Castejon Monegros",
    "sg:orig_category":"Maquinaria Para Industrias Diversas",
    "sg:phone":"+34 976 17 27 40",
    "sg:postcode":"22222",
    "sg:province":"Huesca",
    "wof:name":"Guallar Buil Fernando",
    "wof:placetype":"venue"
},
  "geometry": {"coordinates":[-0.233969301,41.6150588989],"type":"Point"}
}