{
  "type": "Feature",
  "properties": {
    "addr:full":"Via Julia, 57 Barcelona Barcelona 08042",
    "addr:housenumber":"57",
    "addr:postcode":"08042",
    "addr:street":"Via Julia",
    "iso:country":"ES",
    "sg:address":"Via Julia, 57",
    "sg:city":"Barcelona",
    "sg:orig_category":"Fabricaci\u00d3n, Importaci\u00d3n, Venta De Material De Telefon\u00cda, Peritelefon\u00cda",
    "sg:phone":"+34 932 76 29 64",
    "sg:postcode":"08042",
    "sg:province":"Barcelona",
    "wof:name":"Servitel Consulting S.l.",
    "wof:placetype":"venue"
},
  "geometry": {"coordinates":[2.1764059067,41.4407501221],"type":"Point"}
}