{
  "type": "Feature",
  "properties": {
    "addr:full":"Calle de Sagunto, 8 Almeria Almer\u00eda 04004",
    "addr:housenumber":"8",
    "addr:postcode":"04004",
    "addr:street":"Calle De Sagunto",
    "iso:country":"ES",
    "sg:address":"Calle de Sagunto, 8",
    "sg:city":"Almeria",
    "sg:classifiers":[
        {
            "category":"Personal",
            "subcategory":"Barber",
            "type":"Services"
        }
    ],
    "sg:phone":"+34 950 27 28 84",
    "sg:postcode":"04004",
    "sg:province":"Almer\u00eda",
    "sg:tags":[
        "caballeros",
        "de",
        "peluqueros"
    ],
    "wof:name":"Martin Romera Juan Francisco",
    "wof:placetype":"venue"
},
  "geometry": {"coordinates":[-2.4596629143,36.8345184326],"type":"Point"}
}