{
  "type": "Feature",
  "properties": {
    "iso:country":"ES",
    "sg:address":"Carrer de Marques De Santillana, 13",
    "sg:city":"Barcelona",
    "sg:orig_category":"Pintura, Barniz, Productos Asimilables (fabricaci\u00d3n, Al Por Mayor)",
    "sg:phone":"+34 932 74 06 16",
    "sg:postcode":"08030",
    "sg:province":"Barcelona",
    "wof:name":"Materis Paints Espana S.l.",
    "wof:placetype":"venue"
},
  "geometry": {"coordinates":[2.1890480518,41.4290428162],"type":"Point"}
}