{
  "type": "Feature",
  "properties": {
    "iso:country":"ES",
    "sg:address":"Calle de Corona De Aragon, 43",
    "sg:city":"Zaragoza",
    "sg:orig_category":"Muebles, Minoristas",
    "sg:phone":"+34 976 30 68 91",
    "sg:postcode":"50009",
    "sg:province":"Zaragoza",
    "wof:name":"Pe\u00f1a Pons Fernando",
    "wof:placetype":"venue"
},
  "geometry": {"coordinates":[-0.8987393975,41.6444549561],"type":"Point"}
}