{
  "type": "Feature",
  "properties": {
    "addr:full":"Calle de Nuevo Mundo, 8 Mazagon Huelva 21130",
    "addr:housenumber":"8",
    "addr:postcode":"21130",
    "addr:street":"Calle De Nuevo Mundo",
    "iso:country":"ES",
    "sg:address":"Calle de Nuevo Mundo, 8",
    "sg:city":"Mazagon",
    "sg:orig_category":"Empresas De Limpieza",
    "sg:phone":"+34 959 37 68 13",
    "sg:postcode":"21130",
    "sg:province":"Huelva",
    "wof:name":"Mantenimiento Y Limpieza Supermade S.l.",
    "wof:placetype":"venue"
},
  "geometry": {"coordinates":[-6.8279538155,37.1366615295],"type":"Point"}
}