{
  "type": "Feature",
  "properties": {
    "addr:full":"Plaz San Pedro, 1 Torredonjimeno Ja\u00e9n 23650",
    "addr:housenumber":"1",
    "addr:postcode":"23650",
    "addr:street":"Plaz San Pedro",
    "iso:country":"ES",
    "sg:address":"Plaz San Pedro, 1",
    "sg:city":"Torredonjimeno",
    "sg:orig_category":"Iglesia Cat\u00d3lica",
    "sg:phone":"+34 953 34 42 24",
    "sg:postcode":"23650",
    "sg:province":"Ja\u00e9n",
    "wof:name":"Parroquia De San Pedro",
    "wof:placetype":"venue"
},
  "geometry": {"coordinates":[-3.9562489986,37.7677383423],"type":"Point"}
}