{
  "type": "Feature",
  "properties": {
    "iso:country":"ES",
    "sg:address":"Carr Rutlla, 105",
    "sg:city":"Girona",
    "sg:orig_category":"Aparcamientos (infraestructuras, Accesorios)",
    "sg:phone":"+34 972 20 47 57",
    "sg:postcode":"17003",
    "sg:province":"Girona",
    "wof:name":"Fernandez Gich Maria",
    "wof:placetype":"venue"
},
  "geometry": {"coordinates":[2.8221459389,41.973487854],"type":"Point"}
}