{
  "type": "Feature",
  "properties": {
    "iso:country":"ES",
    "sg:address":"Pl Iglesia, 2",
    "sg:city":"Castalla",
    "sg:orig_category":"Iglesia Cat\u00d3lica",
    "sg:phone":"+34 965 56 05 19",
    "sg:postcode":"03420",
    "sg:province":"Alicante",
    "wof:name":"Parroquia Maria Asunta",
    "wof:placetype":"venue"
},
  "geometry": {"coordinates":[-0.6706849933,38.5966110229],"type":"Point"}
}