{
  "type": "Feature",
  "properties": {
    "addr:full":"Cmno Hormigueras, 169 Madrid Madrid 28031",
    "addr:housenumber":"169",
    "addr:postcode":"28031",
    "addr:street":"Cmno Hormigueras",
    "iso:country":"ES",
    "sg:address":"Cmno Hormigueras, 169",
    "sg:city":"Madrid",
    "sg:orig_category":"Sindicatos De Trabajadores",
    "sg:phone":"+34 913 31 63 93",
    "sg:postcode":"28031",
    "sg:province":"Madrid",
    "wof:name":"Sindicato Libre De Correos Telecomunicac",
    "wof:placetype":"venue"
},
  "geometry": {"coordinates":[-3.6347789764,40.3770599365],"type":"Point"}
}