{
  "type": "Feature",
  "properties": {
    "addr:full":"Calle de Universidad De Texas, 4 Almeria Almer\u00eda 04005",
    "addr:housenumber":"4",
    "addr:postcode":"04005",
    "addr:street":"Calle De Universidad De Texas",
    "iso:country":"ES",
    "sg:address":"Calle de Universidad De Texas, 4",
    "sg:city":"Almeria",
    "sg:orig_category":"Artes Gr\u00c1ficas, Artes Pl\u00c1sticas: Material Y Suministros (al Por Menor)",
    "sg:phone":"+34 950 22 18 21",
    "sg:postcode":"04005",
    "sg:province":"Almer\u00eda",
    "wof:name":"Martinez Elvira Presentacion",
    "wof:placetype":"venue"
},
  "geometry": {"coordinates":[-2.4540219307,36.8413658142],"type":"Point"}
}