{
  "type": "Feature",
  "properties": {
    "addr:full":"Avda Pablo Gargallo, 110 Zaragoza Zaragoza 50003",
    "addr:housenumber":"110",
    "addr:postcode":"50003",
    "addr:street":"Avda Pablo Gargallo",
    "iso:country":"ES",
    "sg:address":"Avda Pablo Gargallo, 110",
    "sg:city":"Zaragoza",
    "sg:orig_category":"Agencias Y Agentes Comerciales, Representantes",
    "sg:phone":"+34 976 43 64 39",
    "sg:postcode":"50003",
    "sg:province":"Zaragoza",
    "wof:name":"Baquer Villa Esther",
    "wof:placetype":"venue"
},
  "geometry": {"coordinates":[-0.9029809833,41.6618232727],"type":"Point"}
}