{
  "type": "Feature",
  "properties": {
    "iso:country":"ES",
    "sg:address":"Pase Julia (la), 1",
    "sg:city":"Palencia",
    "sg:orig_category":"Parques De Atracciones Y Centros De Esparcimiento",
    "sg:phone":"+34 979 16 01 78",
    "sg:postcode":"34002",
    "sg:province":"Palencia",
    "wof:name":"Gonzalez Ramos Vanessa",
    "wof:placetype":"venue"
},
  "geometry": {"coordinates":[-4.5286130905,42.0026664734],"type":"Point"}
}