{
  "type": "Feature",
  "properties": {
    "iso:country":"ES",
    "sg:address":"Calle de Doctor Cornago, 14",
    "sg:city":"Pozuelo De Alarcon",
    "sg:orig_category":"Perfumer\u00cda, Art\u00cdculos De Ba\u00d1o (fabricaci\u00d3n, Al Por Mayor)",
    "sg:phone":"+34 913 52 98 98",
    "sg:postcode":"28223",
    "sg:province":"Madrid",
    "wof:name":"Alvarez Sanchez-rubio Felicisimo",
    "wof:placetype":"venue"
},
  "geometry": {"coordinates":[-3.8135530949,40.4365386963],"type":"Point"}
}