{
  "type": "Feature",
  "properties": {
    "addr:full":"Calle de Martinez Monta\u00d1ez, 38 Argana Baja Las Palmas 35500",
    "addr:housenumber":"38",
    "addr:postcode":"35500",
    "addr:street":"Calle De Martinez Montan\u0303Ez",
    "iso:country":"ES",
    "sg:address":"Calle de Martinez Monta\u00d1ez, 38",
    "sg:city":"Argana Baja",
    "sg:orig_category":"Venta, Instalaci\u00d3n De Sistemas De Alarmas Y Vigilancia",
    "sg:phone":"+34 928 81 77 91",
    "sg:postcode":"35500",
    "sg:province":"Las Palmas",
    "wof:name":"Seguridad Integral Canaria S.a.",
    "wof:placetype":"venue"
},
  "geometry": {"coordinates":[-13.5490036011,28.9582099915],"type":"Point"}
}