{
  "type": "Feature",
  "properties": {
    "addr:full":"Calle de Bailen, 9 Alcorcon Madrid 28921",
    "addr:housenumber":"9",
    "addr:postcode":"28921",
    "addr:street":"Calle De Bailen",
    "iso:country":"ES",
    "sg:address":"Calle de Bailen, 9",
    "sg:city":"Alcorcon",
    "sg:orig_category":"Agencias De Viajes",
    "sg:phone":"+34 916 12 15 33",
    "sg:postcode":"28921",
    "sg:province":"Madrid",
    "sg:website":"www.plantour.es",
    "wof:name":"Viajes Beduin S.l.",
    "wof:placetype":"venue"
},
  "geometry": {"coordinates":[-3.8312339783,40.3492240906],"type":"Point"}
}