{
  "type": "Feature",
  "properties": {
    "addr:full":"Uno-los Olmos, S/n Olimar Valencia 46370",
    "addr:housenumber":"s / n",
    "addr:postcode":"46370",
    "addr:street":"Olmos",
    "iso:country":"ES",
    "sg:address":"Uno-los Olmos, S/n",
    "sg:city":"Olimar",
    "sg:orig_category":"Aguas (distribuci\u00d3n, Servicios)",
    "sg:phone":"+34 961 80 50 45",
    "sg:postcode":"46370",
    "sg:province":"Valencia",
    "wof:name":"Suministros Y Servicios Olimar S.l.",
    "wof:placetype":"venue"
},
  "geometry": {"coordinates":[-0.7179690003,39.4728012085],"type":"Point"}
}