{
  "type": "Feature",
  "properties": {
    "addr:full":"Focanos, 1 Focanos La Coru\u00f1a 15175",
    "addr:housenumber":"1",
    "addr:postcode":"15175",
    "addr:street":"Focanos;La Corun\u0303A",
    "iso:country":"ES",
    "sg:address":"Focanos, 1",
    "sg:city":"Focanos",
    "sg:orig_category":"Arquitectos",
    "sg:phone":"+34 981 67 02 09",
    "sg:postcode":"15175",
    "sg:province":"La Coru\u00f1a",
    "wof:name":"Ruiz Jainaga Jose Luis",
    "wof:placetype":"venue"
},
  "geometry": {"coordinates":[-8.3558893204,43.2278442383],"type":"Point"}
}