{
  "type": "Feature",
  "properties": {
    "iso:country":"ES",
    "sg:address":"Cllo Campo Volantin, 23",
    "sg:city":"Bilbao",
    "sg:orig_category":"Barbacoas Y Accesorios",
    "sg:phone":"+34 944 46 12 23",
    "sg:postcode":"48007",
    "sg:province":"Vizcaya",
    "wof:name":"Parrillas De Campo Volantin, S.l.",
    "wof:placetype":"venue"
},
  "geometry": {"coordinates":[-2.9274148941,43.2670860291],"type":"Point"}
}