{
  "type": "Feature",
  "properties": {
    "addr:full":"Carrer de Polonia, 18 Barcelona Barcelona 08024",
    "addr:housenumber":"18",
    "addr:postcode":"08024",
    "addr:street":"Carrer De Polonia",
    "iso:country":"ES",
    "sg:address":"Carrer de Polonia, 18",
    "sg:city":"Barcelona",
    "sg:orig_category":"Organizaciones Internacionales",
    "sg:phone":"+34 932 13 07 94",
    "sg:postcode":"08024",
    "sg:province":"Barcelona",
    "sg:website":"www.ntafrica.org",
    "wof:name":"Noves Tecnologies Per A Leafrica",
    "wof:placetype":"venue"
},
  "geometry": {"coordinates":[2.1646909714,41.4151992798],"type":"Point"}
}