{
  "type": "Feature",
  "properties": {
    "addr:full":"Carr San Francisco, 49 Aldaia Valencia 46960",
    "addr:housenumber":"49",
    "addr:postcode":"46960",
    "addr:street":"Carr San Francisco",
    "iso:country":"ES",
    "sg:address":"Carr San Francisco, 49",
    "sg:city":"Aldaia",
    "sg:orig_category":"Asesor\u00cda Fiscal Y Jur\u00cddica",
    "sg:phone":"+34 961 50 97 27",
    "sg:postcode":"46960",
    "sg:province":"Valencia",
    "wof:name":"Gestofice S.l.",
    "wof:placetype":"venue"
},
  "geometry": {"coordinates":[-0.460878998,39.4649238586],"type":"Point"}
}