{
  "type": "Feature",
  "properties": {
    "iso:country":"ES",
    "sg:address":"Calle de Belisana, 26",
    "sg:city":"Madrid",
    "sg:orig_category":"Comunidades Religiosas",
    "sg:phone":"+34 913 88 10 76",
    "sg:postcode":"28043",
    "sg:province":"Madrid",
    "wof:name":"Hermanas Pasionistas De San Pablo De La Cruz",
    "wof:placetype":"venue"
},
  "geometry": {"coordinates":[-3.6531960964,40.4585494995],"type":"Point"}
}