{
  "type": "Feature",
  "properties": {
    "addr:full":"Carrer de Flors De Maig, 11 Barcelona Barcelona 08041",
    "addr:housenumber":"11",
    "addr:postcode":"08041",
    "addr:street":"Carrer De Flors De Maig",
    "iso:country":"ES",
    "sg:address":"Carrer de Flors De Maig, 11",
    "sg:city":"Barcelona",
    "sg:orig_category":"Promotores Constructores",
    "sg:phone":"+34 934 56 26 28",
    "sg:postcode":"08041",
    "sg:province":"Barcelona",
    "wof:name":"Construcciones Mayoso S.l.",
    "wof:placetype":"venue"
},
  "geometry": {"coordinates":[2.175260067,41.417930603],"type":"Point"}
}