{
  "type": "Feature",
  "properties": {
    "iso:country":"ES",
    "sg:address":"Calle de Barrio Nuevo, 26",
    "sg:city":"Bigastro",
    "sg:orig_category":"Empresarios",
    "sg:phone":"+34 965 35 02 38",
    "sg:postcode":"03380",
    "sg:province":"Alicante",
    "wof:name":"Alcaina Fuentes Antonio",
    "wof:placetype":"venue"
},
  "geometry": {"coordinates":[-0.8999310732,38.0621528625],"type":"Point"}
}