{
  "type": "Feature",
  "properties": {
    "addr:full":"Calle de Teresa Gil, 18 Valladolid Valladolid 47002",
    "addr:housenumber":"18",
    "addr:postcode":"47002",
    "addr:street":"Calle De Teresa Gil",
    "iso:country":"ES",
    "sg:address":"Calle de Teresa Gil, 18",
    "sg:city":"Valladolid",
    "sg:orig_category":"Abogados",
    "sg:phone":"+34 983 21 01 45",
    "sg:postcode":"47002",
    "sg:province":"Valladolid",
    "wof:name":"Pi\u00f1eyroa De La Fuente Jose Carlos",
    "wof:placetype":"venue"
},
  "geometry": {"coordinates":[-4.7256436348,41.6504364014],"type":"Point"}
}