{
  "type": "Feature",
  "properties": {
    "addr:full":"Calle de Ruidiaz, 5 Iniesta Cuenca 16235",
    "addr:housenumber":"5",
    "addr:postcode":"16235",
    "addr:street":"Calle De Ruidiaz",
    "iso:country":"ES",
    "sg:address":"Calle de Ruidiaz, 5",
    "sg:city":"Iniesta",
    "sg:orig_category":"Ropa Y Art\u00cdculos Pre",
    "sg:phone":"+34 967 49 08 44",
    "sg:postcode":"16235",
    "sg:province":"Cuenca",
    "wof:name":"Monica Dulce Bebe S.l.",
    "wof:placetype":"venue"
},
  "geometry": {"coordinates":[-1.7445240021,39.4410591125],"type":"Point"}
}