{
  "type": "Feature",
  "properties": {
    "iso:country":"ES",
    "sg:address":"Calle de Soledades, 3",
    "sg:city":"Sevilla",
    "sg:orig_category":"Guarder\u00cdas",
    "sg:phone":"+34 954 40 85 45",
    "sg:postcode":"41020",
    "sg:province":"Sevilla",
    "wof:name":"Sanz Ruiz Esther",
    "wof:placetype":"venue"
},
  "geometry": {"coordinates":[-5.9252672195,37.3985557556],"type":"Point"}
}