{
  "type": "Feature",
  "properties": {
    "addr:full":"Calle de Pe\u00d1as Del Chache, 4 Arrecife Las Palmas 35500",
    "addr:housenumber":"4",
    "addr:postcode":"35500",
    "addr:street":"Calle De Pen\u0303As Del Chache",
    "iso:country":"ES",
    "sg:address":"Calle de Pe\u00d1as Del Chache, 4",
    "sg:city":"Arrecife",
    "sg:orig_category":"Bazares, Art\u00cdculos De Limpieza Y De Cocina (al Por Menor)",
    "sg:phone":"+34 928 80 58 20",
    "sg:postcode":"35500",
    "sg:province":"Las Palmas",
    "wof:name":"Fei Tian Scp",
    "wof:placetype":"venue"
},
  "geometry": {"coordinates":[-13.5565690994,28.9595088959],"type":"Point"}
}