{
  "type": "Feature",
  "properties": {
    "iso:country":"ES",
    "sg:address":"Calle de Circunvalacion, 2",
    "sg:city":"Torrejon Ardoz",
    "sg:orig_category":"Zapatos (al Por Menor)",
    "sg:phone":"+34 916 77 32 12",
    "sg:postcode":"28850",
    "sg:province":"Madrid",
    "wof:name":"Gordo Venturo Eugenio",
    "wof:placetype":"venue"
},
  "geometry": {"coordinates":[-3.4591083527,40.4517784119],"type":"Point"}
}