{
  "type": "Feature",
  "properties": {
    "addr:full":"Calle de Venezuela, 14 Tablero Las Palmas 35100",
    "addr:housenumber":"14",
    "addr:postcode":"35100",
    "addr:street":"Calle De Venezuela;Las",
    "iso:country":"ES",
    "sg:address":"Calle de Venezuela, 14",
    "sg:city":"Tablero",
    "sg:orig_category":"Molduras, Junquillos, Listones Y Molduras Perforadas",
    "sg:phone":"+34 928 14 24 54",
    "sg:postcode":"35100",
    "sg:province":"Las Palmas",
    "wof:name":"Garcia Rodriguez Marcial",
    "wof:placetype":"venue"
},
  "geometry": {"coordinates":[-15.4397096634,28.1302204132],"type":"Point"}
}