{
  "type": "Feature",
  "properties": {
    "iso:country":"ES",
    "sg:address":"Calle de Valois, 47",
    "sg:city":"Puerto Cruz",
    "sg:orig_category":"Transportes Urbanos Y Regionales Para Personas",
    "sg:phone":"+34 922 37 33 98",
    "sg:postcode":"38400",
    "sg:province":"Santa Cruz De Tenerife",
    "wof:name":"Yurena Trans S.l.",
    "wof:placetype":"venue"
},
  "geometry": {"coordinates":[-16.5442295074,28.415430069],"type":"Point"}
}