{
  "type": "Feature",
  "properties": {
    "iso:country":"ES",
    "sg:address":"La Cruz, S/n",
    "sg:city":"Colmenar",
    "sg:orig_category":"Ba\u00d1os Y Duchas P\u00dablicos",
    "sg:phone":"+34 952 73 09 31",
    "sg:postcode":"29170",
    "sg:province":"M\u00e1laga",
    "wof:name":"Ayuntamiento De Colmenar Piscina Publica Municipal",
    "wof:placetype":"venue"
},
  "geometry": {"coordinates":[-4.259390831,36.9947433472],"type":"Point"}
}