{
  "type": "Feature",
  "properties": {
    "addr:full":"Calle de Jose Ortega Y Gasset, 29 Madrid Madrid 28006",
    "addr:housenumber":"29",
    "addr:postcode":"madrid;28006",
    "addr:street":"Calle De Jose Ortega Y Gasset",
    "iso:country":"ES",
    "sg:address":"Calle de Jose Ortega Y Gasset, 29",
    "sg:city":"Madrid",
    "sg:orig_category":"Inmobiliaria (agencias)",
    "sg:phone":"+34 915 75 44 16",
    "sg:postcode":"28006",
    "sg:province":"Madrid",
    "wof:name":"Vivienda Y Oficinas S. A.",
    "wof:placetype":"venue"
},
  "geometry": {"coordinates":[-3.6830377579,40.4303016663],"type":"Point"}
}