{
  "type": "Feature",
  "properties": {
    "addr:full":"Ctra Torron (do), 13 Brues Ourense 32521",
    "addr:housenumber":"13",
    "addr:postcode":"32521",
    "addr:street":"Ctra Torron Do",
    "iso:country":"ES",
    "sg:address":"Ctra Torron (do), 13",
    "sg:city":"Brues",
    "sg:orig_category":"Electricidad (montaje, Ensamblaje De Componentes)",
    "sg:phone":"+34 988 28 53 61",
    "sg:postcode":"32521",
    "sg:province":"Ourense",
    "wof:name":"Garcia Cerdeira Antonio",
    "wof:placetype":"venue"
},
  "geometry": {"coordinates":[-8.1390380859,42.4515800476],"type":"Point"}
}