{
  "type": "Feature",
  "properties": {
    "iso:country":"ES",
    "sg:address":"Calle de Cruz Del Estudiante, 11",
    "sg:city":"Puente-genil",
    "sg:orig_category":"Panader\u00cdas, Panader\u00cdas",
    "sg:phone":"+34 957 60 66 26",
    "sg:postcode":"14500",
    "sg:province":"C\u00f3rdoba",
    "wof:name":"Distribuidora Alimentaria Ruiz Santos Sl",
    "wof:placetype":"venue"
},
  "geometry": {"coordinates":[-4.7701091766,37.3894615173],"type":"Point"}
}