{
  "type": "Feature",
  "properties": {
    "addr:full":"Ctra. Pedro Mu\u00f1oz, 5 Mota Cuervo Cuenca 16630",
    "addr:housenumber":"5",
    "addr:postcode":"16630",
    "addr:street":"Ctra. Pedro Mun\u0303Oz",
    "iso:country":"ES",
    "sg:address":"Ctra. Pedro Mu\u00f1oz, 5",
    "sg:city":"Mota Cuervo",
    "sg:orig_category":"Reposter\u00cdas",
    "sg:phone":"+34 967 18 00 33",
    "sg:postcode":"16630",
    "sg:province":"Cuenca",
    "wof:name":"Zarco Morales Jose Luis",
    "wof:placetype":"venue"
},
  "geometry": {"coordinates":[-2.8738629818,39.4972991943],"type":"Point"}
}