{
  "type": "Feature",
  "properties": {
    "addr:full":"Avda Primero De Mayo, 33 Palmas De Gran Canaria Las Palmas 35002",
    "addr:postcode":"35002",
    "addr:street":"Avda Primero De Mayo 33",
    "iso:country":"ES",
    "sg:address":"Avda Primero De Mayo, 33",
    "sg:city":"Palmas De Gran Canaria",
    "sg:orig_category":"Agentes Generales De Seguros",
    "sg:phone":"+34 928 36 17 17",
    "sg:postcode":"35002",
    "sg:province":"Las Palmas",
    "wof:name":"Pirez Janariz Victor Jose Juan",
    "wof:placetype":"venue"
},
  "geometry": {"coordinates":[-15.419916153,28.1054515839],"type":"Point"}
}