{
  "type": "Feature",
  "properties": {
    "addr:full":"Carr Ausias March, D', 18 Casco Urbano Valencia 46760",
    "addr:housenumber":"18",
    "addr:postcode":"46760",
    "addr:street":"Carr Ausias March D '",
    "iso:country":"ES",
    "sg:address":"Carr Ausias March, D', 18",
    "sg:city":"Casco Urbano",
    "sg:orig_category":"Panader\u00cdas, Panader\u00cdas",
    "sg:phone":"+34 962 82 30 10",
    "sg:postcode":"46760",
    "sg:province":"Valencia",
    "wof:name":"Martinez Reig Jose",
    "wof:placetype":"venue"
},
  "geometry": {"coordinates":[-0.3758000135,39.4568138123],"type":"Point"}
}