{
  "type": "Feature",
  "properties": {
    "addr:full":"Avda Nuestra Se\u00d1ora De Estibaliz, 5 Vitoria-gasteiz \u00c1lava 01003",
    "addr:housenumber":"5",
    "addr:postcode":"01003",
    "addr:street":"Avda Nuestra Sen\u0303Ora;Estibaliz",
    "iso:country":"ES",
    "sg:address":"Avda Nuestra Se\u00d1ora De Estibaliz, 5",
    "sg:city":"Vitoria-gasteiz",
    "sg:orig_category":"Confecci\u00d3n De Trajes Para Se\u00d1oras",
    "sg:phone":"+34 945 27 92 95",
    "sg:postcode":"01003",
    "sg:province":"\u00c1lava",
    "wof:name":"Albeniz Gonzalez De Durana Jorge Luis",
    "wof:placetype":"venue"
},
  "geometry": {"coordinates":[-2.6637926102,42.844909668],"type":"Point"}
}