{
  "type": "Feature",
  "properties": {
    "addr:full":"Plaz Lavadero, 4 Montefrio Granada 18270",
    "addr:housenumber":"4",
    "addr:postcode":"18270",
    "addr:street":"Lavadero",
    "iso:country":"ES",
    "sg:address":"Plaz Lavadero, 4",
    "sg:city":"Montefrio",
    "sg:orig_category":"Negocio De Materiales De Construcci\u00d3n",
    "sg:phone":"+34 958 33 62 39",
    "sg:postcode":"18270",
    "sg:province":"Granada",
    "wof:name":"Pedregosa Avila Cristobal",
    "wof:placetype":"venue"
},
  "geometry": {"coordinates":[-4.0050649643,37.3236503601],"type":"Point"}
}