{
  "type": "Feature",
  "properties": {
    "addr:full":"Calle de Faisanes, 4 Aranjuez Madrid 28300",
    "addr:housenumber":"4",
    "addr:postcode":"28300",
    "addr:street":"Calle De Faisanes",
    "iso:country":"ES",
    "sg:address":"Calle de Faisanes, 4",
    "sg:city":"Aranjuez",
    "sg:orig_category":"Pintura Industrial (trabajos De)",
    "sg:phone":"+34 918 91 74 94",
    "sg:postcode":"28300",
    "sg:province":"Madrid",
    "wof:name":"Hermanos Beltran C.b.",
    "wof:placetype":"venue"
},
  "geometry": {"coordinates":[-3.6133029461,40.0269737244],"type":"Point"}
}