{
  "type": "Feature",
  "properties": {
    "addr:full":"Cra San Agustin, 13 Loja Granada 18300",
    "addr:housenumber":"13 loja",
    "addr:postcode":"18300",
    "addr:street":"Agustin",
    "iso:country":"ES",
    "sg:address":"Cra San Agustin, 13",
    "sg:city":"Loja",
    "sg:orig_category":"Cl\u00cdnicas Dentales",
    "sg:phone":"+34 958 32 27 59",
    "sg:postcode":"18300",
    "sg:province":"Granada",
    "wof:name":"Oca\u00f1a Rey Miguel Angel",
    "wof:placetype":"venue"
},
  "geometry": {"coordinates":[-4.1490159035,37.1667251587],"type":"Point"}
}