{
  "type": "Feature",
  "properties": {
    "addr:full":"Calle de Elizagibela, 7 Doneztebe Navarra 31740",
    "addr:housenumber":"7",
    "addr:postcode":"31740",
    "addr:street":"Calle De Elizagibela;Navarra",
    "iso:country":"ES",
    "sg:address":"Calle de Elizagibela, 7",
    "sg:city":"Doneztebe",
    "sg:orig_category":"Tintes (fabricaci\u00d3n, Al Por Mayor)",
    "sg:phone":"+34 948 45 05 21",
    "sg:postcode":"31740",
    "sg:province":"Navarra",
    "wof:name":"Tellechea Tellechea Jaione",
    "wof:placetype":"venue"
},
  "geometry": {"coordinates":[-1.6693099737,43.1327362061],"type":"Point"}
}