{
  "type": "Feature",
  "properties": {
    "addr:full":"Avda Ciudad Real, 72 Abenojar Ciudad Real 13180",
    "addr:housenumber":"72",
    "addr:postcode":"13180",
    "addr:street":"Avda Ciudad Real",
    "iso:country":"ES",
    "sg:address":"Avda Ciudad Real, 72",
    "sg:city":"Abenojar",
    "sg:orig_category":"Aceites Y Grasas Alimentarias (fabricaci\u00d3n, Al Por Mayor)",
    "sg:phone":"+34 926 83 50 77",
    "sg:postcode":"13180",
    "sg:province":"Ciudad Real",
    "wof:name":"Cooperativa Agricola Nuestra Se\u00f1ora De La Encarnacion",
    "wof:placetype":"venue"
},
  "geometry": {"coordinates":[-4.3524260521,38.8767585754],"type":"Point"}
}