{
  "type": "Feature",
  "properties": {
    "addr:full":"Av Catalunya, 100 Casc Antic Barcelona 08150",
    "addr:housenumber":"100",
    "addr:postcode":"08150",
    "addr:street":"Av Catalunya",
    "iso:country":"ES",
    "sg:address":"Av Catalunya, 100",
    "sg:city":"Casc Antic",
    "sg:orig_category":"Pescader\u00cdas (al Por Menor)",
    "sg:phone":"+34 935 62 36 45",
    "sg:postcode":"08150",
    "sg:province":"Barcelona",
    "wof:name":"Hierro Criado Eliso",
    "wof:placetype":"venue"
},
  "geometry": {"coordinates":[2.1699187756,41.3879165649],"type":"Point"}
}