{
  "type": "Feature",
  "properties": {
    "iso:country":"ES",
    "sg:address":"Poli Casa Grande, 85",
    "sg:city":"Torrevieja",
    "sg:orig_category":"Empresas De Carpinter\u00cda Met\u00c1lica",
    "sg:phone":"+34 966 70 42 52",
    "sg:postcode":"03180",
    "sg:province":"Alicante",
    "wof:name":"Carpinteria Metalica Torremar S.l.",
    "wof:placetype":"venue"
},
  "geometry": {"coordinates":[-0.6536790133,38.0173606873],"type":"Point"}
}