{
  "type": "Feature",
  "properties": {
    "addr:full":"Avda Santa Maria, 36 Meliana Valencia 46133",
    "addr:housenumber":"36",
    "addr:postcode":"46133",
    "addr:street":"Avda Santa Maria",
    "iso:country":"ES",
    "sg:address":"Avda Santa Maria, 36",
    "sg:city":"Meliana",
    "sg:orig_category":"\u00d3ptica: Instrumentos (fabricaci\u00d3n)",
    "sg:phone":"+34 961 49 18 04",
    "sg:postcode":"46133",
    "sg:province":"Valencia",
    "wof:name":"Furio Ayllon Jose Julian",
    "wof:placetype":"venue"
},
  "geometry": {"coordinates":[-0.3515869975,39.5301780701],"type":"Point"}
}