{
  "type": "Feature",
  "properties": {
    "addr:full":"Carrer de Cobalt, 2 Barcelona Barcelona 08038",
    "addr:housenumber":"2",
    "addr:postcode":"08038",
    "addr:street":"Carrer De Cobalt",
    "iso:country":"ES",
    "sg:address":"Carrer de Cobalt, 2",
    "sg:city":"Barcelona",
    "sg:orig_category":"Fabricaci\u00d3n De Tapices Y Moquetas Para Suelos Y Paredes",
    "sg:phone":"+34 932 23 24 09",
    "sg:postcode":"08038",
    "sg:province":"Barcelona",
    "wof:name":"Irc",
    "wof:placetype":"venue"
},
  "geometry": {"coordinates":[2.1403529644,41.3531723022],"type":"Point"}
}