{
  "type": "Feature",
  "properties": {
    "iso:country":"ES",
    "sg:address":"Calle de Berrocal, 16",
    "sg:city":"Madrid",
    "sg:orig_category":"Inmobiliaria (agencias)",
    "sg:phone":"+34 917 96 14 55",
    "sg:postcode":"28021",
    "sg:province":"Madrid",
    "wof:name":"Integral Coin S.l.",
    "wof:placetype":"venue"
},
  "geometry": {"coordinates":[-3.6774358749,40.3472290039],"type":"Point"}
}