{
  "type": "Feature",
  "properties": {
    "addr:full":"Paseo Astondo Ibiltokia, 2 Gorliz Vizcaya 48630",
    "addr:housenumber":"2",
    "addr:postcode":"48630",
    "addr:street":"Paseo Astondo Ibiltokia",
    "iso:country":"ES",
    "sg:address":"Paseo Astondo Ibiltokia, 2",
    "sg:city":"Gorliz",
    "sg:orig_category":"Hospitales",
    "sg:phone":"+34 944 00 66 00",
    "sg:postcode":"48630",
    "sg:province":"Vizcaya",
    "wof:name":"Osakidetza",
    "wof:placetype":"venue"
},
  "geometry": {"coordinates":[-2.9446489811,43.4165840149],"type":"Point"}
}