{
  "type": "Feature",
  "properties": {
    "iso:country":"ES",
    "sg:address":"Carrer de Pau Claris, 94",
    "sg:city":"Barcelona",
    "sg:orig_category":"Agencias Y Agentes Comerciales, Representantes",
    "sg:phone":"+34 933 42 41 73",
    "sg:postcode":"08010",
    "sg:province":"Barcelona",
    "wof:name":"Van Meel  Christianus",
    "wof:placetype":"venue"
},
  "geometry": {"coordinates":[2.1704740524,41.3903846741],"type":"Point"}
}