{
  "type": "Feature",
  "properties": {
    "iso:country":"ES",
    "sg:address":"Carrer de Pontons, 2",
    "sg:city":"Barcelona",
    "sg:orig_category":"Molduras, Junquillos, Listones Y Molduras Perforadas",
    "sg:phone":"+34 933 57 44 28",
    "sg:postcode":"08031",
    "sg:province":"Barcelona",
    "wof:name":"Perez Rodriguez Benito",
    "wof:placetype":"venue"
},
  "geometry": {"coordinates":[2.1728670597,41.4265098572],"type":"Point"}
}