{
  "type": "Feature",
  "properties": {
    "addr:full":"Calle de Mar Caspio, 18 Madrid Madrid 28033",
    "addr:housenumber":"18",
    "addr:postcode":"madrid;28033",
    "addr:street":"Calle De Mar Caspio",
    "iso:country":"ES",
    "sg:address":"Calle de Mar Caspio, 18",
    "sg:city":"Madrid",
    "sg:orig_category":"Aparatos, Material Y Suministros Para Laboratorios",
    "sg:phone":"+34 913 81 56 37",
    "sg:postcode":"28033",
    "sg:province":"Madrid",
    "wof:name":"Microbeam S. A.",
    "wof:placetype":"venue"
},
  "geometry": {"coordinates":[-3.643073082,40.4730911255],"type":"Point"}
}