{
  "type": "Feature",
  "properties": {
    "iso:country":"ES",
    "sg:address":"Calle de Pelayo, 12",
    "sg:city":"Zamora",
    "sg:orig_category":"Asesor\u00cda Fiscal Y Jur\u00cddica",
    "sg:phone":"+34 980 53 29 50",
    "sg:postcode":"49014",
    "sg:province":"Zamora",
    "wof:name":"Alvarez Serrano Enrique",
    "wof:placetype":"venue"
},
  "geometry": {"coordinates":[-5.7431030273,41.5065689087],"type":"Point"}
}