{
  "type": "Feature",
  "properties": {
    "addr:full":"Partida Mas Nauvi, 42 Riudoms Tarragona 43330",
    "addr:housenumber":"42",
    "addr:postcode":"43330",
    "addr:street":"Partida Mas Nauvi",
    "iso:country":"ES",
    "sg:address":"Partida Mas Nauvi, 42",
    "sg:city":"Riudoms",
    "sg:orig_category":"Promotores Constructores",
    "sg:phone":"+34 977 76 87 12",
    "sg:postcode":"43330",
    "sg:province":"Tarragona",
    "sg:website":"www.canalsdelmarenostrum.net",
    "wof:name":"Canals Del Mare Nostrum S.l.",
    "wof:placetype":"venue"
},
  "geometry": {"coordinates":[1.0541909933,41.1382713318],"type":"Point"}
}