{
  "type": "Feature",
  "properties": {
    "addr:full":"Pontevea, 10 Pontevea La Coru\u00f1a 15883",
    "addr:housenumber":"10",
    "addr:postcode":"15883",
    "addr:street":"Pontevea;La Corun\u0303A",
    "iso:country":"ES",
    "sg:address":"Pontevea, 10",
    "sg:city":"Pontevea",
    "sg:orig_category":"Audiovisuales (producci\u00d3n, Edici\u00d3n, Realizaci\u00d3n)",
    "sg:phone":"+34 981 80 96 65",
    "sg:postcode":"15883",
    "sg:province":"La Coru\u00f1a",
    "wof:name":"Puente Bermudez Fermin",
    "wof:placetype":"venue"
},
  "geometry": {"coordinates":[-8.5444011688,42.8382263184],"type":"Point"}
}