{
  "type": "Feature",
  "properties": {
    "addr:full":"Calle de Comandante Caballero, 4 Oviedo Asturias 33005",
    "addr:housenumber":"4",
    "addr:postcode":"33005",
    "addr:street":"Calle De Comandante Caballero",
    "iso:country":"ES",
    "sg:address":"Calle de Comandante Caballero, 4",
    "sg:city":"Oviedo",
    "sg:orig_category":"Abogados",
    "sg:phone":"+34 985 25 94 74",
    "sg:postcode":"33005",
    "sg:province":"Asturias",
    "wof:name":"Lara Alba Juan Carlos",
    "wof:placetype":"venue"
},
  "geometry": {"coordinates":[-5.8560562134,43.3601875305],"type":"Point"}
}