{
  "type": "Feature",
  "properties": {
    "iso:country":"ES",
    "sg:address":"Calle de Flores, S/n",
    "sg:city":"Arboleas",
    "sg:orig_category":"Hoteles",
    "sg:phone":"+34 950 43 81 47",
    "sg:postcode":"04660",
    "sg:province":"Almer\u00eda",
    "wof:name":"Lopez Lopez Angel",
    "wof:placetype":"venue"
},
  "geometry": {"coordinates":[-2.073823452,37.351348877],"type":"Point"}
}