{
  "type": "Feature",
  "properties": {
    "iso:country":"ES",
    "sg:address":"Carrer de Barcelona, 8",
    "sg:city":"Sant Sadurni D'anoia",
    "sg:orig_category":"Supermercados Y Hipermercados",
    "sg:phone":"+34 938 18 31 76",
    "sg:postcode":"08770",
    "sg:province":"Barcelona",
    "wof:name":"Bon Preu S.a.",
    "wof:placetype":"venue"
},
  "geometry": {"coordinates":[1.775799036,41.6818504333],"type":"Point"}
}