{
  "type": "Feature",
  "properties": {
    "addr:full":"Av Abat Marcet, 358 Terrassa Barcelona 08225",
    "addr:housenumber":"358",
    "addr:postcode":"08225",
    "addr:street":"Av Abat Marcet",
    "iso:country":"ES",
    "sg:address":"Av Abat Marcet, 358",
    "sg:city":"Terrassa",
    "sg:orig_category":"Estancos",
    "sg:phone":"+34 937 88 69 94",
    "sg:postcode":"08225",
    "sg:province":"Barcelona",
    "wof:name":"Gimenez Moreno Antonio",
    "wof:placetype":"venue"
},
  "geometry": {"coordinates":[2.0034222603,41.574180603],"type":"Point"}
}