{
  "type": "Feature",
  "properties": {
    "addr:full":"Calle de Carril San Diego, 70 Sanlucar De Barrameda C\u00e1diz 11540",
    "addr:housenumber":"70",
    "addr:postcode":"11540",
    "addr:street":"Calle De Carril;Diego;Ca\u0301Diz",
    "iso:country":"ES",
    "sg:address":"Calle de Carril San Diego, 70",
    "sg:city":"Sanlucar De Barrameda",
    "sg:classifiers":[
        {
            "category":"Utilities",
            "subcategory":"Natural Gas",
            "type":"Services"
        }
    ],
    "sg:phone":"+34 956 38 13 49",
    "sg:postcode":"11540",
    "sg:province":"C\u00e1diz",
    "wof:name":"C.l.p. Envirogas S.l.",
    "wof:placetype":"venue"
},
  "geometry": {"coordinates":[-6.3517518044,36.7803688049],"type":"Point"}
}