{
  "type": "Feature",
  "properties": {
    "iso:country":"ES",
    "sg:address":"Vall Del Pi, S/n",
    "sg:city":"Portellada",
    "sg:orig_category":"Producci\u00d3n, Venta De Productos De Agricultura Biol\u00d3gica",
    "sg:phone":"+34 978 76 90 40",
    "sg:postcode":"44589",
    "sg:province":"Teruel",
    "wof:name":"Guardia Micolau S.cv.",
    "wof:placetype":"venue"
},
  "geometry": {"coordinates":[-1.1069096327,40.3441085815],"type":"Point"}
}