{
  "type": "Feature",
  "properties": {
    "addr:full":"Trueno, 44 Leganes Madrid 28918",
    "addr:housenumber":"44",
    "addr:postcode":"28918",
    "addr:street":"Trueno",
    "iso:country":"ES",
    "sg:address":"Trueno, 44",
    "sg:city":"Leganes",
    "sg:orig_category":"M\u00c1quinas Textiles, Accesorios Y Suministros (fabricaci\u00d3n)",
    "sg:phone":"+34 916 42 54 88",
    "sg:postcode":"28918",
    "sg:province":"Madrid",
    "wof:name":"Ibermark Textil S.a.",
    "wof:placetype":"venue"
},
  "geometry": {"coordinates":[-3.7967169285,40.3472862244],"type":"Point"}
}