{
  "type": "Feature",
  "properties": {
    "addr:full":"Calle de Civicos, 1 Rambla C\u00f3rdoba 14540",
    "addr:housenumber":"1",
    "addr:postcode":"14540",
    "addr:street":"Calle De Civicos;Rambla Co\u0301Rdoba",
    "iso:country":"ES",
    "sg:address":"Calle de Civicos, 1",
    "sg:city":"Rambla",
    "sg:orig_category":"Alfarer\u00cda",
    "sg:phone":"+34 957 68 44 76",
    "sg:postcode":"14540",
    "sg:province":"C\u00f3rdoba",
    "wof:name":"Urbano Casas Rafael",
    "wof:placetype":"venue"
},
  "geometry": {"coordinates":[-4.7437491417,37.6060218811],"type":"Point"}
}