{
  "type": "Feature",
  "properties": {
    "iso:country":"ES",
    "sg:address":"Trva Bisbe Torres, De, 30",
    "sg:city":"S. Antoni Portmany",
    "sg:orig_category":"Deportes Diversos",
    "sg:phone":"+34 971 34 79 03",
    "sg:postcode":"07820",
    "sg:province":"Islas Baleares",
    "wof:name":"Delegacion De Petanca Ibiza Y Formentera",
    "wof:placetype":"venue"
},
  "geometry": {"coordinates":[1.5188339949,39.1094055176],"type":"Point"}
}