{
  "type": "Feature",
  "properties": {
    "iso:country":"ES",
    "sg:address":"Calle de Fontanares, 55",
    "sg:city":"Valencia",
    "sg:orig_category":"Cajas De Ahorro",
    "sg:phone":"+34 963 77 44 63",
    "sg:postcode":"46014",
    "sg:province":"Valencia",
    "wof:name":"Caixa Popular Cooperativa De Credito Valenciana",
    "wof:placetype":"venue"
},
  "geometry": {"coordinates":[-0.39487499,39.4605522156],"type":"Point"}
}