{
  "type": "Feature",
  "properties": {
    "iso:country":"ES",
    "sg:address":"Calle de San Miguel, 8",
    "sg:city":"Najera",
    "sg:orig_category":"Electricidad: Instaladores",
    "sg:phone":"+34 941 36 34 25",
    "sg:postcode":"26300",
    "sg:province":"La Rioja",
    "wof:name":"Maria Pilar Ojeda Garcia Comunidad De Bienes",
    "wof:placetype":"venue"
},
  "geometry": {"coordinates":[-2.7350859642,42.4178771973],"type":"Point"}
}