{
  "type": "Feature",
  "properties": {
    "iso:country":"ES",
    "sg:address":"Calle de Granada, 18",
    "sg:city":"Estepona",
    "sg:orig_category":"Importaci\u00d3n, Exportaci\u00d3n Y Comercios De Productos Textiles",
    "sg:phone":"+34 952 80 62 79",
    "sg:postcode":"29680",
    "sg:province":"M\u00e1laga",
    "wof:name":"Decomoda S.l.",
    "wof:placetype":"venue"
},
  "geometry": {"coordinates":[-5.1469769478,36.4282951355],"type":"Point"}
}