{
  "type": "Feature",
  "properties": {
    "addr:full":"Pase Martin J.iraola Etorbidea, 2 San Blas Guip\u00f9zcoa 20400",
    "addr:housenumber":"2",
    "addr:postcode":"20400",
    "addr:street":"J.Iraola Etorbidea",
    "iso:country":"ES",
    "sg:address":"Pase Martin J.iraola Etorbidea, 2",
    "sg:city":"San Blas",
    "sg:orig_category":"Ense\u00d1anza Variada",
    "sg:phone":"+34 943 67 24 48",
    "sg:postcode":"20400",
    "sg:province":"Guip\u00f9zcoa",
    "wof:name":"Academia Pausoka Cb",
    "wof:placetype":"venue"
},
  "geometry": {"coordinates":[-2.0789339542,43.1339912415],"type":"Point"}
}