{
  "type": "Feature",
  "properties": {
    "addr:full":"Calle de San Herculano, 12 Madrid Madrid 28022",
    "addr:housenumber":"12",
    "addr:postcode":"madrid;28022",
    "addr:street":"Calle De San Herculano",
    "iso:country":"ES",
    "sg:address":"Calle de San Herculano, 12",
    "sg:city":"Madrid",
    "sg:orig_category":"Bisuteros (fabricaci\u00d3n, Al Por Mayor)",
    "sg:phone":"+34 917 41 96 64",
    "sg:postcode":"28022",
    "sg:province":"Madrid",
    "wof:name":"Merino Cardaba Gabriel",
    "wof:placetype":"venue"
},
  "geometry": {"coordinates":[-3.6100649834,40.4412269592],"type":"Point"}
}