{
  "type": "Feature",
  "properties": {
    "addr:full":"C/ Velarde, 17 Elche Alicante 03203",
    "addr:housenumber":"17",
    "addr:postcode":"03203",
    "addr:street":"C / Velarde",
    "iso:country":"ES",
    "sg:address":"C/ Velarde, 17",
    "sg:city":"Elche",
    "sg:orig_category":"Restaurantes",
    "sg:phone":"+34 966 61 46 94",
    "sg:postcode":"03203",
    "sg:province":"Alicante",
    "wof:name":"Le Bouquet Vins I Delicatessens S.l.",
    "wof:placetype":"venue"
},
  "geometry": {"coordinates":[-0.6940730214,38.2658653259],"type":"Point"}
}