{
  "type": "Feature",
  "properties": {
    "addr:full":"Ctra Montilla, Km. 0001,5 Rambla C\u00f3rdoba 14540",
    "addr:postcode":"14540",
    "addr:street":"Ctra Montilla Km. 0001,5 Rambla Co\u0301Rdoba",
    "iso:country":"ES",
    "sg:address":"Ctra Montilla, Km. 0001,5",
    "sg:city":"Rambla",
    "sg:orig_category":"Cer\u00c1mica Art\u00cdstica Y Decorativa",
    "sg:phone":"+34 957 68 42 10",
    "sg:postcode":"14540",
    "sg:province":"C\u00f3rdoba",
    "wof:name":"Decosuna Ceramicas S.l.",
    "wof:placetype":"venue"
},
  "geometry": {"coordinates":[-4.7416338921,37.6080932617],"type":"Point"}
}