{
  "type": "Feature",
  "properties": {
    "addr:full":"Ctra Brazatortas, Km. 0153,0 Puertollano Ciudad Real 13500",
    "addr:postcode":"13500",
    "addr:street":"Ctra Brazatortas Km. 0153,0",
    "iso:country":"ES",
    "sg:address":"Ctra Brazatortas, Km. 0153,0",
    "sg:city":"Puertollano",
    "sg:orig_category":"Explosivos",
    "sg:phone":"+34 926 41 07 15",
    "sg:postcode":"13500",
    "sg:province":"Ciudad Real",
    "wof:name":"Maxamcorp S.a.u.",
    "wof:placetype":"venue"
},
  "geometry": {"coordinates":[-4.1869544983,38.7080039978],"type":"Point"}
}