{
  "type": "Feature",
  "properties": {
    "iso:country":"ES",
    "sg:address":"Avda Gasteiz, 78",
    "sg:city":"Vitoria-gasteiz",
    "sg:orig_category":"Doctores En Medicina",
    "sg:phone":"+34 945 24 82 50",
    "sg:postcode":"01012",
    "sg:province":"\u00c1lava",
    "wof:name":"Consultorio Medico Permanente, Sc",
    "wof:placetype":"venue"
},
  "geometry": {"coordinates":[-2.6798689365,42.8529472351],"type":"Point"}
}