{
  "type": "Feature",
  "properties": {
    "iso:country":"ES",
    "sg:address":"Calle de Milan, 26",
    "sg:city":"Madrid",
    "sg:orig_category":"Comercio, Reparaci\u00d3n De Motocicletas, Bicicletas Y Piezas Sueltas",
    "sg:phone":"+34 913 88 45 50",
    "sg:postcode":"28043",
    "sg:province":"Madrid",
    "wof:name":"Hospital Motor S.l.",
    "wof:placetype":"venue"
},
  "geometry": {"coordinates":[-3.6474719048,40.4545669556],"type":"Point"}
}