{
  "type": "Feature",
  "properties": {
    "addr:full":"Poligon Industrial Pla Del Riu, S/n S. Vicen\u00e7 Castellet Barcelona 08295",
    "addr:postcode":"08295",
    "addr:street":"Industrial;S / N S. Vicenc\u0327;Barcelona",
    "iso:country":"ES",
    "sg:address":"Poligon Industrial Pla Del Riu, S/n",
    "sg:city":"S. Vicen\u00e7 Castellet",
    "sg:orig_category":"Fabricaci\u00d3n De Taburetes, Sillas Y Sillones",
    "sg:phone":"+34 938 33 10 72",
    "sg:postcode":"08295",
    "sg:province":"Barcelona",
    "wof:name":"Muebles Tapizados Alpe S.l.",
    "wof:placetype":"venue"
},
  "geometry": {"coordinates":[1.8631989956,41.6670608521],"type":"Point"}
}