{
  "type": "Feature",
  "properties": {
    "iso:country":"ES",
    "sg:address":"Calle de Mejico, 43",
    "sg:city":"Albacete",
    "sg:orig_category":"Promotores Constructores",
    "sg:phone":"+34 967 50 82 00",
    "sg:postcode":"02006",
    "sg:province":"Albacete",
    "wof:name":"Martinez De La Rosa Amparo",
    "wof:placetype":"venue"
},
  "geometry": {"coordinates":[-1.8705044985,38.9832878113],"type":"Point"}
}