{
  "type": "Feature",
  "properties": {
    "addr:full":"Pla\u00c7 Martirs, 2 Cervera Lleida 25200",
    "addr:housenumber":"2",
    "addr:postcode":"25200",
    "addr:street":"Martirs",
    "iso:country":"ES",
    "sg:address":"Pla\u00c7 Martirs, 2",
    "sg:city":"Cervera",
    "sg:orig_category":"Peluquer\u00cdas, Peluquer\u00cda Mixta",
    "sg:phone":"+34 973 53 33 77",
    "sg:postcode":"25200",
    "sg:province":"Lleida",
    "wof:name":"Blancart Infante Dolores",
    "wof:placetype":"venue"
},
  "geometry": {"coordinates":[1.2735830545,41.6697807312],"type":"Point"}
}