{
  "type": "Feature",
  "properties": {
    "addr:full":"Psaj Rodo, 1 Badalona Barcelona 08917",
    "addr:housenumber":"1",
    "addr:postcode":"08917",
    "iso:country":"ES",
    "sg:address":"Psaj Rodo, 1",
    "sg:city":"Badalona",
    "sg:orig_category":"Veh\u00cdculos De Ocasi\u00d3n",
    "sg:phone":"+34 933 87 43 55",
    "sg:postcode":"08917",
    "sg:province":"Barcelona",
    "wof:name":"Recycle Car S.l.",
    "wof:placetype":"venue"
},
  "geometry": {"coordinates":[2.2450649738,41.4503440857],"type":"Point"}
}