{
  "type": "Feature",
  "properties": {
    "iso:country":"ES",
    "sg:address":"Cdad Jardin, 47",
    "sg:city":"Torrox",
    "sg:orig_category":"Suministros Y Materiales Industriales",
    "sg:phone":"+34 952 53 83 61",
    "sg:postcode":"29770",
    "sg:province":"M\u00e1laga",
    "wof:name":"Suministros Mavi S.l.",
    "wof:placetype":"venue"
},
  "geometry": {"coordinates":[-3.9506690502,36.7658500671],"type":"Point"}
}