{
  "type": "Feature",
  "properties": {
    "iso:country":"ES",
    "sg:address":"Avda Jose Mesa Y Lopez, 19",
    "sg:city":"Palmas De Gran Canaria",
    "sg:orig_category":"Peluquer\u00cdas, Peluquer\u00cda Mixta",
    "sg:phone":"+34 928 24 85 20",
    "sg:postcode":"35006",
    "sg:province":"Las Palmas",
    "wof:name":"Valeron Garcia Pilar",
    "wof:placetype":"venue"
},
  "geometry": {"coordinates":[-15.4325962067,28.1344566345],"type":"Point"}
}