{
  "type": "Feature",
  "properties": {
    "iso:country":"ES",
    "sg:address":"Barr Atxukarro, 9",
    "sg:city":"Arrigorriaga",
    "sg:orig_category":"Muebles Y Accesorios Para Cocinas Y Cuartos De Ba\u00d1o (al Por Menor)",
    "sg:phone":"+34 946 71 40 94",
    "sg:postcode":"48480",
    "sg:province":"Vizcaya",
    "wof:name":"Montaje Mobiliario Moderno S.l. M3",
    "wof:placetype":"venue"
},
  "geometry": {"coordinates":[-2.8878386021,43.2075195312],"type":"Point"}
}