{
  "type": "Feature",
  "properties": {
    "iso:country":"ES",
    "sg:address":"Plaz Madrid, S/n",
    "sg:city":"Almu\u00f1ecar",
    "sg:orig_category":"M\u00c9dicos: Estomatolog\u00cda",
    "sg:phone":"+34 958 88 14 14",
    "sg:postcode":"18690",
    "sg:province":"Granada",
    "wof:name":"Rodriguez Calpe Francisco Javier",
    "wof:placetype":"venue"
},
  "geometry": {"coordinates":[-3.6884241104,36.7321243286],"type":"Point"}
}