{
  "type": "Feature",
  "properties": {
    "iso:country":"ES",
    "sg:address":"Calle de Vicente Clavel, 10",
    "sg:city":"Valencia",
    "sg:orig_category":"Fabricaci\u00d3n, Distribuci\u00d3n De Material Para La Climatizaci\u00d3n, Aireaci\u00d3n Y Ventilaci\u00d3n",
    "sg:phone":"+34 963 80 13 20",
    "sg:postcode":"46014",
    "sg:province":"Valencia",
    "wof:name":"Area De Ventilacion S.l.",
    "wof:placetype":"venue"
},
  "geometry": {"coordinates":[-0.3968788981,39.461265564],"type":"Point"}
}