{
  "type": "Feature",
  "properties": {
    "addr:full":"Rua Rollo, 34 Betanzos La Coru\u00f1a 15300",
    "addr:housenumber":"34",
    "addr:postcode":"15300",
    "addr:street":"Rua Rollo;La",
    "iso:country":"ES",
    "sg:address":"Rua Rollo, 34",
    "sg:city":"Betanzos",
    "sg:orig_category":"Acero: Productos Sider\u00dargicos Y Transformados (fabricaci\u00d3n, Negocio)",
    "sg:phone":"+34 981 77 41 59",
    "sg:postcode":"15300",
    "sg:province":"La Coru\u00f1a",
    "wof:name":"Galival Y Steel S.l.",
    "wof:placetype":"venue"
},
  "geometry": {"coordinates":[-8.210729599,43.2771377563],"type":"Point"}
}