{
  "type": "Feature",
  "properties": {
    "addr:full":"Plaz Paz, De La, 8 Haro La Rioja 26200",
    "addr:housenumber":"8",
    "addr:postcode":"26200",
    "addr:street":"Plaz",
    "iso:country":"ES",
    "sg:address":"Plaz Paz, De La, 8",
    "sg:city":"Haro",
    "sg:orig_category":"Caf\u00c9s, Bares, Cervecer\u00cdas",
    "sg:phone":"+34 941 31 00 21",
    "sg:postcode":"26200",
    "sg:province":"La Rioja",
    "wof:name":"Gallo Orodea Julio",
    "wof:placetype":"venue"
},
  "geometry": {"coordinates":[-2.8502631187,42.5774803162],"type":"Point"}
}