{
  "type": "Feature",
  "properties": {
    "iso:country":"ES",
    "sg:address":"Carr Manuel Simo Marin, 21",
    "sg:city":"Ontinyent",
    "sg:orig_category":"Heladeros",
    "sg:phone":"+34 962 38 30 60",
    "sg:postcode":"46870",
    "sg:province":"Valencia",
    "wof:name":"Carrion Canto Mauricio",
    "wof:placetype":"venue"
},
  "geometry": {"coordinates":[-0.6042019725,38.8213920593],"type":"Point"}
}