{
  "type": "Feature",
  "properties": {
    "addr:full":"Pur\u00edsima, 4 Segorbe Castell\u00f3n 12400",
    "addr:housenumber":"4",
    "addr:postcode":"12400",
    "addr:street":"Puri\u0301Sima",
    "iso:country":"ES",
    "sg:address":"Pur\u00edsima, 4",
    "sg:city":"Segorbe",
    "sg:orig_category":"Promotores Constructores",
    "sg:phone":"+34 964 71 10 73",
    "sg:postcode":"12400",
    "sg:province":"Castell\u00f3n",
    "wof:name":"Bolumar Martin Juan Antonio",
    "wof:placetype":"venue"
},
  "geometry": {"coordinates":[-0.4856519997,39.8529243469],"type":"Point"}
}