{
  "type": "Feature",
  "properties": {
    "addr:full":"Ctra. Andratx, 35 Peguera Islas Baleares 07160",
    "addr:housenumber":"35",
    "addr:postcode":"07160",
    "addr:street":"Ctra. Andratx",
    "iso:country":"ES",
    "sg:address":"Ctra. Andratx, 35",
    "sg:city":"Peguera",
    "sg:orig_category":"Art\u00cdculos De Regalo (al Por Menor)",
    "sg:phone":"+34 971 68 62 07",
    "sg:postcode":"07160",
    "sg:province":"Islas Baleares",
    "wof:name":"Juanes Carrobles Isaac",
    "wof:placetype":"venue"
},
  "geometry": {"coordinates":[2.4631509781,39.5322647095],"type":"Point"}
}