{
  "type": "Feature",
  "properties": {
    "iso:country":"ES",
    "sg:address":"Carr Ramir Medir, 3",
    "sg:city":"Palafrugell",
    "sg:orig_category":"Plomeros",
    "sg:phone":"+34 972 30 09 81",
    "sg:postcode":"17200",
    "sg:province":"Girona",
    "wof:name":"Instalacions Baixcat S.l.",
    "wof:placetype":"venue"
},
  "geometry": {"coordinates":[3.1597599983,41.9181594849],"type":"Point"}
}