{
  "type": "Feature",
  "properties": {
    "iso:country":"ES",
    "sg:address":"Carrer de Finestrelles, 23",
    "sg:city":"Esplugues Llobregat",
    "sg:orig_category":"Arquitectos",
    "sg:phone":"+34 933 71 97 55",
    "sg:postcode":"08950",
    "sg:province":"Barcelona",
    "wof:name":"O\u00f1a Martinez Jose",
    "wof:placetype":"venue"
},
  "geometry": {"coordinates":[2.1003301144,41.384929657],"type":"Point"}
}