{
  "type": "Feature",
  "properties": {
    "addr:full":"Avda Dos De Mayo (del), 79 Mostoles Madrid 28934",
    "addr:housenumber":"79",
    "addr:postcode":"28934",
    "addr:street":"Avda Dos De Mayo Del",
    "iso:country":"ES",
    "sg:address":"Avda Dos De Mayo (del), 79",
    "sg:city":"Mostoles",
    "sg:orig_category":"Empresas De Carpinter\u00cda De Madera",
    "sg:phone":"+34 916 45 98 25",
    "sg:postcode":"28934",
    "sg:province":"Madrid",
    "wof:name":"Arpublock S.l.",
    "wof:placetype":"venue"
},
  "geometry": {"coordinates":[-3.8773229122,40.3185081482],"type":"Point"}
}