{
  "type": "Feature",
  "properties": {
    "iso:country":"ES",
    "sg:address":"Calle de Canalejas, 28",
    "sg:city":"Herradura",
    "sg:orig_category":"Comercio, Reparaci\u00d3n De Motocicletas, Bicicletas Y Piezas Sueltas",
    "sg:phone":"+34 958 82 76 68",
    "sg:postcode":"18697",
    "sg:province":"Granada",
    "wof:name":"Guerrero Fernandez Manuel Angel",
    "wof:placetype":"venue"
},
  "geometry": {"coordinates":[-3.73843503,36.7335510254],"type":"Point"}
}