{
  "type": "Feature",
  "properties": {
    "addr:full":"Calle de Duquesa Villahermosa, 139 Zaragoza Zaragoza 50009",
    "addr:housenumber":"139",
    "addr:postcode":"50009",
    "addr:street":"Calle De Duquesa Villahermosa",
    "iso:country":"ES",
    "sg:address":"Calle de Duquesa Villahermosa, 139",
    "sg:city":"Zaragoza",
    "sg:orig_category":"Inform\u00c1tica (estudios, Servicios, Asesor\u00cda, Formaci\u00d3n)",
    "sg:phone":"+34 976 75 44 00",
    "sg:postcode":"50009",
    "sg:province":"Zaragoza",
    "sg:website":"www.zaragozavirtual.com",
    "wof:name":"Seinteco S.l.",
    "wof:placetype":"venue"
},
  "geometry": {"coordinates":[-0.9126830101,41.6446647644],"type":"Point"}
}