{
  "type": "Feature",
  "properties": {
    "iso:country":"ES",
    "sg:address":"Calle de Constitucion (de La), 9",
    "sg:city":"Navalcarnero",
    "sg:orig_category":"Perfumer\u00cda (al Por Menor)",
    "sg:phone":"+34 918 11 01 25",
    "sg:postcode":"28600",
    "sg:province":"Madrid",
    "wof:name":"Gutierrez Pe\u00f1a Jose Luis",
    "wof:placetype":"venue"
},
  "geometry": {"coordinates":[-4.0028858185,40.288520813],"type":"Point"}
}