{
  "type": "Feature",
  "properties": {
    "addr:full":"Calle de Emilio Ferrari, 65 Madrid Madrid 28017",
    "addr:housenumber":"65",
    "addr:postcode":"madrid;28017",
    "addr:street":"Calle De Emilio Ferrari",
    "iso:country":"ES",
    "sg:address":"Calle de Emilio Ferrari, 65",
    "sg:city":"Madrid",
    "sg:orig_category":"Farmacias",
    "sg:phone":"+34 913 67 16 89",
    "sg:postcode":"28017",
    "sg:province":"Madrid",
    "wof:name":"Linde Garcia Juan",
    "wof:placetype":"venue"
},
  "geometry": {"coordinates":[-3.6410596371,40.4311027527],"type":"Point"}
}