{
  "type": "Feature",
  "properties": {
    "iso:country":"ES",
    "sg:address":"Calle de Tres Tazas, 8",
    "sg:city":"Avila",
    "sg:orig_category":"Peluqueros: De Se\u00d1oras",
    "sg:phone":"+34 920 25 15 06",
    "sg:postcode":"05001",
    "sg:province":"\u00c1vila",
    "wof:name":"Gimenez Gimenez Marta",
    "wof:placetype":"venue"
},
  "geometry": {"coordinates":[-4.7025680542,40.6575279236],"type":"Point"}
}