{
  "type": "Feature",
  "properties": {
    "addr:full":"Calle de Dionisio Guardiola, 47 Albacete Albacete 02003",
    "addr:housenumber":"47",
    "addr:postcode":"02003",
    "addr:street":"Calle De Dionisio Guardiola",
    "iso:country":"ES",
    "sg:address":"Calle de Dionisio Guardiola, 47",
    "sg:city":"Albacete",
    "sg:orig_category":"Ropa Para Ni\u00d1os (al Por Menor)",
    "sg:phone":"+34 967 50 00 36",
    "sg:postcode":"02003",
    "sg:province":"Albacete",
    "wof:name":"Madrona Tarraga Maria Del Carmen",
    "wof:placetype":"venue"
},
  "geometry": {"coordinates":[-1.8594082594,38.992855072],"type":"Point"}
}