{
  "type": "Feature",
  "properties": {
    "addr:full":"Carrer de Casanova, 94 Barcelona Barcelona 08011",
    "addr:housenumber":"94",
    "addr:postcode":"08011",
    "addr:street":"Carrer De Casanova",
    "iso:country":"ES",
    "sg:address":"Carrer de Casanova, 94",
    "sg:city":"Barcelona",
    "sg:orig_category":"Molduras, Junquillos, Listones Y Molduras Perforadas",
    "sg:phone":"+34 934 51 37 49",
    "sg:postcode":"08011",
    "sg:province":"Barcelona",
    "wof:name":"Fer Boca 2000 S.l.",
    "wof:placetype":"venue"
},
  "geometry": {"coordinates":[2.1569540501,41.3869667053],"type":"Point"}
}