{
  "type": "Feature",
  "properties": {
    "iso:country":"ES",
    "sg:address":"Pase General Davila, 64",
    "sg:city":"Santander",
    "sg:orig_category":"Servicios De Higiene Y Peluquer\u00cda Para Perros Y Gatos",
    "sg:phone":"+34 942 31 81 36",
    "sg:postcode":"39006",
    "sg:province":"Cantabria",
    "wof:name":"Duncan S.cv.",
    "wof:placetype":"venue"
},
  "geometry": {"coordinates":[-3.7994480133,43.4683609009],"type":"Point"}
}