{
  "type": "Feature",
  "properties": {
    "addr:full":"Joan Carles I, 12 Batea Tarragona 43786",
    "addr:housenumber":"12",
    "addr:postcode":"43786",
    "addr:street":"Joan;I",
    "iso:country":"ES",
    "sg:address":"Joan Carles I, 12",
    "sg:city":"Batea",
    "sg:orig_category":"Estudios, Instalaci\u00d3n De Climatizaci\u00d3n",
    "sg:phone":"+34 977 43 02 65",
    "sg:postcode":"43786",
    "sg:province":"Tarragona",
    "wof:name":"Rams Ferrer Jose",
    "wof:placetype":"venue"
},
  "geometry": {"coordinates":[0.3124260008,41.0930900574],"type":"Point"}
}