{
  "type": "Feature",
  "properties": {
    "iso:country":"ES",
    "sg:address":"Rbla Catalunya (de), 6",
    "sg:city":"Vila-seca",
    "sg:orig_category":"Droguer\u00cdas (al Por Menor)",
    "sg:phone":"+34 977 39 16 19",
    "sg:postcode":"43480",
    "sg:province":"Tarragona",
    "wof:name":"Rodriguez Fernandez Miguel",
    "wof:placetype":"venue"
},
  "geometry": {"coordinates":[1.1479899883,41.109790802],"type":"Point"}
}