{
  "type": "Feature",
  "properties": {
    "addr:full":"Calle de General Diaz Porlier, 37 Madrid Madrid 28001",
    "addr:housenumber":"37",
    "addr:postcode":"madrid;28001",
    "addr:street":"Calle De General Diaz Porlier",
    "iso:country":"ES",
    "sg:address":"Calle de General Diaz Porlier, 37",
    "sg:city":"Madrid",
    "sg:orig_category":"Filatelia",
    "sg:phone":"+34 914 02 50 99",
    "sg:postcode":"28001",
    "sg:province":"Madrid",
    "wof:name":"Pizarro Valencia Jose Antonio",
    "wof:placetype":"venue"
},
  "geometry": {"coordinates":[-3.6771349907,40.4281425476],"type":"Point"}
}