{
  "type": "Feature",
  "properties": {
    "addr:full":"Carrer de Bruguera, 200 Calella Barcelona 08370",
    "addr:housenumber":"200",
    "addr:postcode":"08370",
    "addr:street":"Carrer De Bruguera",
    "iso:country":"ES",
    "sg:address":"Carrer de Bruguera, 200",
    "sg:city":"Calella",
    "sg:orig_category":"Institutos De Belleza",
    "sg:phone":"+34 937 69 09 26",
    "sg:postcode":"08370",
    "sg:province":"Barcelona",
    "wof:name":"Vila Dalmau Antonia",
    "wof:placetype":"venue"
},
  "geometry": {"coordinates":[2.6650059223,41.6162986755],"type":"Point"}
}