{
  "type": "Feature",
  "properties": {
    "addr:full":"Avda Novelda, 60 Alacant Alicante 03010",
    "addr:housenumber":"60",
    "addr:postcode":"03010",
    "addr:street":"Avda Novelda",
    "iso:country":"ES",
    "sg:address":"Avda Novelda, 60",
    "sg:city":"Alacant",
    "sg:orig_category":"Perfumer\u00cda Y Cosm\u00c9tica (fabricaci\u00d3n, Al Por Mayor)",
    "sg:phone":"+34 965 17 58 11",
    "sg:postcode":"03010",
    "sg:province":"Alicante",
    "sg:website":"www.lendan.com",
    "wof:name":"Cosmetica Tecnica S.a.",
    "wof:placetype":"venue"
},
  "geometry": {"coordinates":[-0.4937460124,38.3633384705],"type":"Point"}
}