{
  "type": "Feature",
  "properties": {
    "iso:country":"ES",
    "sg:address":"Calle de Fuente, 24",
    "sg:city":"Toledo",
    "sg:orig_category":"Asistencia Social",
    "sg:phone":"+34 925 22 95 17",
    "sg:postcode":"45006",
    "sg:province":"Toledo",
    "wof:name":"Fundacion Fislem",
    "wof:placetype":"venue"
},
  "geometry": {"coordinates":[-4.0087532997,39.8612251282],"type":"Point"}
}