{
  "type": "Feature",
  "properties": {
    "addr:full":"Ctra Nal 340, Km. 1091,0 Camarles Tarragona 43894",
    "addr:postcode":"43894",
    "addr:street":"Ctra Nal 340 Km. 1091,0",
    "iso:country":"ES",
    "sg:address":"Ctra Nal 340, Km. 1091,0",
    "sg:city":"Camarles",
    "sg:orig_category":"Construcciones Met\u00c1licas",
    "sg:phone":"+34 977 47 10 49",
    "sg:postcode":"43894",
    "sg:province":"Tarragona",
    "sg:website":"www.nutecomes.com",
    "wof:name":"Nuevas Tecnologias Comes S.a.",
    "wof:placetype":"venue"
},
  "geometry": {"coordinates":[0.6723750234,40.7711791992],"type":"Point"}
}