{
  "type": "Feature",
  "properties": {
    "addr:full":"G. Via A. C. Palma, 74 Palma Rio C\u00f3rdoba 14700",
    "addr:housenumber":"74",
    "addr:postcode":"14700",
    "addr:street":"Via A. C. Palma;Rio Co\u0301Rdoba",
    "iso:country":"ES",
    "sg:address":"G. Via A. C. Palma, 74",
    "sg:city":"Palma Rio",
    "sg:orig_category":"Mec\u00c1nico Del Autom\u00d3vil",
    "sg:phone":"+34 957 64 56 43",
    "sg:postcode":"14700",
    "sg:province":"C\u00f3rdoba",
    "wof:name":"Leon Trassierra Juan Luis",
    "wof:placetype":"venue"
},
  "geometry": {"coordinates":[-5.2795991898,37.7004241943],"type":"Point"}
}