{
  "type": "Feature",
  "properties": {
    "addr:full":"Plaz Arriola, 1 Malaga M\u00e1laga 29005",
    "addr:housenumber":"1",
    "addr:postcode":"29005",
    "addr:street":"Plaz Arriola;Ma\u0301Laga",
    "iso:country":"ES",
    "sg:address":"Plaz Arriola, 1",
    "sg:city":"Malaga",
    "sg:orig_category":"Electrodom\u00c9sticos (al Por Menor)",
    "sg:phone":"+34 952 22 58 95",
    "sg:postcode":"29005",
    "sg:province":"M\u00e1laga",
    "sg:website":"www.vivas.net.com",
    "wof:name":"Coypasa S.a.",
    "wof:placetype":"venue"
},
  "geometry": {"coordinates":[-4.4249510765,36.7191352844],"type":"Point"}
}