{
  "type": "Feature",
  "properties": {
    "iso:country":"ES",
    "sg:address":"Avda Castilla-la Mancha, 40",
    "sg:city":"Villafranca De Los Caballeros",
    "sg:orig_category":"Empresas De Carpinter\u00cda De Madera",
    "sg:phone":"+34 926 57 80 06",
    "sg:postcode":"45730",
    "sg:province":"Toledo",
    "wof:name":"Tejera Bernaldo Teresa",
    "wof:placetype":"venue"
},
  "geometry": {"coordinates":[-3.3555309772,39.4266166687],"type":"Point"}
}