{
  "type": "Feature",
  "properties": {
    "iso:country":"ES",
    "sg:address":"Carrer de Pau (la), 33",
    "sg:city":"Manlleu",
    "sg:orig_category":"Venta, Instalaci\u00d3n De Calefacci\u00d3n",
    "sg:phone":"+34 938 51 25 09",
    "sg:postcode":"08560",
    "sg:province":"Barcelona",
    "wof:name":"Calefaccions Unio S.l.",
    "wof:placetype":"venue"
},
  "geometry": {"coordinates":[2.2804028988,42.0037002563],"type":"Point"}
}