{
  "type": "Feature",
  "properties": {
    "addr:full":"Carr Joan Regla, 1 Girona Girona 17003",
    "addr:housenumber":"1",
    "addr:postcode":"17003",
    "addr:street":"Carr Joan Regla",
    "iso:country":"ES",
    "sg:address":"Carr Joan Regla, 1",
    "sg:city":"Girona",
    "sg:orig_category":"Deportes Y Programas De Aventura",
    "sg:phone":"+34 872 08 10 92",
    "sg:postcode":"17003",
    "sg:province":"Girona",
    "wof:name":"El Mon De L'esport S.l.",
    "wof:placetype":"venue"
},
  "geometry": {"coordinates":[2.8200170994,41.971824646],"type":"Point"}
}