{
  "type": "Feature",
  "properties": {
    "addr:full":"Rua Benito Vicetto, Km. 0584,2 Vilanova La Coru\u00f1a 15176",
    "addr:postcode":"15176",
    "addr:street":"Rua Benito Vicetto Km. 0584,2 Vilanova La Corun\u0303A",
    "iso:country":"ES",
    "sg:address":"Rua Benito Vicetto, Km. 0584,2",
    "sg:city":"Vilanova",
    "sg:orig_category":"Venta, Instalaci\u00d3n, Mantenimiento De Chimeneas De Interior Y Accesorios",
    "sg:phone":"+34 981 66 46 60",
    "sg:postcode":"15176",
    "sg:province":"La Coru\u00f1a",
    "wof:name":"Chimenea Center S.l.",
    "wof:placetype":"venue"
},
  "geometry": {"coordinates":[-8.3265943527,43.3246536255],"type":"Point"}
}