{
  "type": "Feature",
  "properties": {
    "iso:country":"ES",
    "sg:address":"Carrer de Providencia, 73",
    "sg:city":"Barcelona",
    "sg:orig_category":"Sales (al Por Mayor)",
    "sg:phone":"+34 932 19 23 15",
    "sg:postcode":"08024",
    "sg:province":"Barcelona",
    "wof:name":"Compte Coll Marta",
    "wof:placetype":"venue"
},
  "geometry": {"coordinates":[2.1589579582,41.4080505371],"type":"Point"}
}