{
  "type": "Feature",
  "properties": {
    "iso:country":"ES",
    "sg:address":"Pda Castell, S/n",
    "sg:city":"Figueres",
    "sg:orig_category":"Museos",
    "sg:phone":"+34 972 50 60 94",
    "sg:postcode":"17600",
    "sg:province":"Girona",
    "wof:name":"Fundacio Les Fortaleses Catalanes",
    "wof:placetype":"venue"
},
  "geometry": {"coordinates":[2.9570000172,42.2692260742],"type":"Point"}
}