{
  "type": "Feature",
  "properties": {
    "addr:full":"Ctra Zaragoza, S/n Alca\u00f1iz Teruel 44600",
    "addr:postcode":"44600",
    "addr:street":"Ctra Zaragoza S / N",
    "iso:country":"ES",
    "sg:address":"Ctra Zaragoza, S/n",
    "sg:city":"Alca\u00f1iz",
    "sg:orig_category":"Frutas Y Legumbres Frescas (al Por Mayor)",
    "sg:phone":"+34 978 83 23 09",
    "sg:postcode":"44600",
    "sg:province":"Teruel",
    "wof:name":"Romero Soler Emilio",
    "wof:placetype":"venue"
},
  "geometry": {"coordinates":[-0.1437969953,41.0519523621],"type":"Point"}
}