{
  "type": "Feature",
  "properties": {
    "addr:full":"Calle de Gobernador, 3 Madrid Madrid 28014",
    "addr:housenumber":"3",
    "addr:postcode":"28014",
    "addr:street":"Calle De Gobernador",
    "iso:country":"ES",
    "sg:address":"Calle de Gobernador, 3",
    "sg:city":"Madrid",
    "sg:orig_category":"Diarios, Revistas Y Boletines (distribuidores)",
    "sg:phone":"+34 914 29 37 74",
    "sg:postcode":"28014",
    "sg:province":"Madrid",
    "sg:website":"www.nodo50.org/worldwatch",
    "wof:name":"Santamarta Florez Jose",
    "wof:placetype":"venue"
},
  "geometry": {"coordinates":[-3.6964309216,40.4117889404],"type":"Point"}
}