{
  "type": "Feature",
  "properties": {
    "addr:full":"Calle de Sol, 1 Ledesma Salamanca 37100",
    "addr:housenumber":"1",
    "addr:postcode":"37100",
    "addr:street":"Calle De Sol",
    "iso:country":"ES",
    "sg:address":"Calle de Sol, 1",
    "sg:city":"Ledesma",
    "sg:orig_category":"Electricidad: Instaladores",
    "sg:phone":"+34 923 57 05 76",
    "sg:postcode":"37100",
    "sg:province":"Salamanca",
    "wof:name":"Electricidad Emilux S.l.",
    "wof:placetype":"venue"
},
  "geometry": {"coordinates":[-6.000497818,41.0904846191],"type":"Point"}
}