{
  "type": "Feature",
  "properties": {
    "addr:full":"Calle de Santos Justo Y Pastor, 30 Valencia Valencia 46021",
    "addr:housenumber":"30",
    "addr:postcode":"46021",
    "addr:street":"Calle De Santos Justo Y Pastor",
    "iso:country":"ES",
    "sg:address":"Calle de Santos Justo Y Pastor, 30",
    "sg:city":"Valencia",
    "sg:orig_category":"Minerales (al Por Mayor)",
    "sg:phone":"+34 963 60 42 76",
    "sg:postcode":"46021",
    "sg:province":"Valencia",
    "wof:name":"Del Barrio Lazaro Pedro Antonio Jeremias",
    "wof:placetype":"venue"
},
  "geometry": {"coordinates":[-0.3517830074,39.4705810547],"type":"Point"}
}