{
  "type": "Feature",
  "properties": {
    "addr:full":"Ctra Denia, 24 Oliva Valencia 46780",
    "addr:housenumber":"24",
    "addr:postcode":"46780",
    "addr:street":"Ctra Denia",
    "iso:country":"ES",
    "sg:address":"Ctra Denia, 24",
    "sg:city":"Oliva",
    "sg:orig_category":"Suministros Y Materiales Industriales",
    "sg:phone":"+34 962 85 11 60",
    "sg:postcode":"46780",
    "sg:province":"Valencia",
    "wof:name":"Suministres Tecnics S. L.",
    "wof:placetype":"venue"
},
  "geometry": {"coordinates":[-0.1179220006,38.9189491272],"type":"Point"}
}