{
  "type": "Feature",
  "properties": {
    "iso:country":"ES",
    "sg:address":"Carr Major, 21",
    "sg:city":"Felanitx",
    "sg:orig_category":"Art\u00cdculos Funerarios (al Por Menor)",
    "sg:phone":"+34 971 55 65 60",
    "sg:postcode":"07200",
    "sg:province":"Islas Baleares",
    "wof:name":"Pompas Funebres De Manacor S.a.",
    "wof:placetype":"venue"
},
  "geometry": {"coordinates":[3.1497650146,39.4694290161],"type":"Point"}
}