{
  "type": "Feature",
  "properties": {
    "iso:country":"ES",
    "sg:address":"La Loma, S/n",
    "sg:city":"Sotopalacios",
    "sg:orig_category":"M\u00c1rmoles, Granitos Y Piedras Naturales",
    "sg:phone":"+34 947 44 12 00",
    "sg:postcode":"09140",
    "sg:province":"Burgos",
    "wof:name":"Hormigones Marcos S.a.",
    "wof:placetype":"venue"
},
  "geometry": {"coordinates":[-3.6831541061,42.4509162903],"type":"Point"}
}