{
  "type": "Feature",
  "properties": {
    "addr:full":"Calle de Escultor Garcia Mas, 3 Valencia Valencia 46015",
    "addr:housenumber":"3",
    "addr:postcode":"46015",
    "addr:street":"Calle De Escultor Garcia Mas",
    "iso:country":"ES",
    "sg:address":"Calle de Escultor Garcia Mas, 3",
    "sg:city":"Valencia",
    "sg:orig_category":"Asesor\u00cda Fiscal Y Jur\u00cddica",
    "sg:phone":"+34 963 40 65 50",
    "sg:postcode":"46015",
    "sg:province":"Valencia",
    "wof:name":"Ribera Y Alfaro Servicios Administrativos Enpresariales Sl",
    "wof:placetype":"venue"
},
  "geometry": {"coordinates":[-0.3981400132,39.4855918884],"type":"Point"}
}