{
  "type": "Feature",
  "properties": {
    "addr:full":"Calle de Navas De Tolosa, 1 Carolina Ja\u00e9n 23200",
    "addr:housenumber":"1",
    "addr:postcode":"23200",
    "addr:street":"Calle De Navas De Tolosa;Carolina Jae\u0301N",
    "iso:country":"ES",
    "sg:address":"Calle de Navas De Tolosa, 1",
    "sg:city":"Carolina",
    "sg:orig_category":"Panader\u00cdas, Panader\u00cdas",
    "sg:phone":"+34 953 66 05 14",
    "sg:postcode":"23200",
    "sg:province":"Ja\u00e9n",
    "wof:name":"Lopez Martos Emilio",
    "wof:placetype":"venue"
},
  "geometry": {"coordinates":[-3.6135649681,38.2753753662],"type":"Point"}
}