{
  "type": "Feature",
  "properties": {
    "addr:full":"Calle de Corregidor Juan Francisco De Lujan, 45 Madrid Madrid 28030",
    "addr:housenumber":"45",
    "addr:postcode":"madrid;28030",
    "addr:street":"Calle De Corregidor Juan Francisco De Lujan",
    "iso:country":"ES",
    "sg:address":"Calle de Corregidor Juan Francisco De Lujan, 45",
    "sg:city":"Madrid",
    "sg:orig_category":"Asociaciones, Organismos Culturales Y Socioeducativos",
    "sg:phone":"+34 913 28 05 10",
    "sg:postcode":"28030",
    "sg:province":"Madrid",
    "wof:name":"Asociacion Exploradores De Madrid S.cv.",
    "wof:placetype":"venue"
},
  "geometry": {"coordinates":[-3.6474690437,40.4027633667],"type":"Point"}
}