{
  "type": "Feature",
  "properties": {
    "iso:country":"ES",
    "sg:address":"Estacion, S/n",
    "sg:city":"Novelda",
    "sg:orig_category":"Importaci\u00d3n",
    "sg:phone":"+34 965 60 09 89",
    "sg:postcode":"03660",
    "sg:province":"Alicante",
    "wof:name":"Pastor Perez Francisco",
    "wof:placetype":"venue"
},
  "geometry": {"coordinates":[-0.7638189793,38.3825035095],"type":"Point"}
}