{
  "type": "Feature",
  "properties": {
    "iso:country":"ES",
    "sg:address":"Plaz San Pablo, 6",
    "sg:city":"Palencia",
    "sg:orig_category":"Molduras, Junquillos, Listones Y Molduras Perforadas",
    "sg:phone":"+34 979 74 38 08",
    "sg:postcode":"34005",
    "sg:province":"Palencia",
    "wof:name":"Garcia Cuesta Celestino",
    "wof:placetype":"venue"
},
  "geometry": {"coordinates":[-4.5373458862,42.0139770508],"type":"Point"}
}