{
  "type": "Feature",
  "properties": {
    "addr:full":"Calle de Alfareria, 11 Yecla Murcia 30510",
    "addr:housenumber":"11",
    "addr:postcode":"30510",
    "addr:street":"Calle De Alfareria",
    "iso:country":"ES",
    "sg:address":"Calle de Alfareria, 11",
    "sg:city":"Yecla",
    "sg:orig_category":"Peluqueros: De Se\u00d1oras",
    "sg:phone":"+34 968 79 55 54",
    "sg:postcode":"30510",
    "sg:province":"Murcia",
    "wof:name":"Mu\u00f1oz Soriano Antonio",
    "wof:placetype":"venue"
},
  "geometry": {"coordinates":[-1.1160546541,38.6151618958],"type":"Point"}
}