{
  "type": "Feature",
  "properties": {
    "iso:country":"ES",
    "sg:address":"Calle de Parvillas Altas, 7",
    "sg:city":"Madrid",
    "sg:orig_category":"Zapatos (al Por Menor)",
    "sg:phone":"+34 917 98 86 95",
    "sg:postcode":"28021",
    "sg:province":"Madrid",
    "wof:name":"Calzados Andrea Ruiz S.l.",
    "wof:placetype":"venue"
},
  "geometry": {"coordinates":[-3.7075800896,40.3446998596],"type":"Point"}
}