{
  "type": "Feature",
  "properties": {
    "iso:country":"ES",
    "sg:address":"Calle de Ave Maria, 42",
    "sg:city":"Torredonjimeno",
    "sg:orig_category":"Institutos De Belleza",
    "sg:phone":"+34 953 34 40 05",
    "sg:postcode":"23650",
    "sg:province":"Ja\u00e9n",
    "wof:name":"Moncaraz S.l.",
    "wof:placetype":"venue"
},
  "geometry": {"coordinates":[-3.952760458,37.7612075806],"type":"Point"}
}