{
  "type": "Feature",
  "properties": {
    "addr:full":"Avda Andalucia, 30 Palmones C\u00e1diz 11379",
    "addr:housenumber":"30",
    "addr:postcode":"11379",
    "addr:street":"Avda Andalucia;Ca\u0301Diz",
    "iso:country":"ES",
    "sg:address":"Avda Andalucia, 30",
    "sg:city":"Palmones",
    "sg:orig_category":"Farmacias",
    "sg:phone":"+34 956 67 75 60",
    "sg:postcode":"11379",
    "sg:province":"C\u00e1diz",
    "wof:name":"Martinez Pe\u00f1a Macarena",
    "wof:placetype":"venue"
},
  "geometry": {"coordinates":[-5.435988903,36.1755409241],"type":"Point"}
}