{
  "type": "Feature",
  "properties": {
    "iso:country":"ES",
    "sg:address":"Avda Canteras (de Las), 39",
    "sg:city":"Valmor-rompecubas",
    "sg:orig_category":"Muebles",
    "sg:phone":"+34 918 09 25 31",
    "sg:postcode":"28340",
    "sg:province":"Madrid",
    "wof:name":"Frio Cantalapiedra S.l",
    "wof:placetype":"venue"
},
  "geometry": {"coordinates":[-3.6677899361,40.1646308899],"type":"Point"}
}