{
  "type": "Feature",
  "properties": {
    "addr:full":"Carrer de Barceloneta, 3 Llagostera Girona 17240",
    "addr:housenumber":"3",
    "addr:postcode":"17240",
    "addr:street":"Carrer De Barceloneta",
    "iso:country":"ES",
    "sg:address":"Carrer de Barceloneta, 3",
    "sg:city":"Llagostera",
    "sg:orig_category":"Juegos Y Juguetes (al Por Menor)",
    "sg:phone":"+34 972 83 03 13",
    "sg:postcode":"17240",
    "sg:province":"Girona",
    "wof:name":"Aubo Ferrer Miguel",
    "wof:placetype":"venue"
},
  "geometry": {"coordinates":[2.8956880569,41.8264274597],"type":"Point"}
}