{
  "type": "Feature",
  "properties": {
    "iso:country":"ES",
    "sg:address":"Calle de Colon, 16",
    "sg:city":"Burriana",
    "sg:orig_category":"Imprenta",
    "sg:phone":"+34 964 51 14 11",
    "sg:postcode":"12530",
    "sg:province":"Castell\u00f3n",
    "wof:name":"Graficas Juancho S.l.",
    "wof:placetype":"venue"
},
  "geometry": {"coordinates":[-0.0831741989,39.8883056641],"type":"Point"}
}