{
  "type": "Feature",
  "properties": {
    "iso:country":"ES",
    "sg:address":"Calle de Plaza (de La), 28",
    "sg:city":"Chiclana De La Frontera",
    "sg:orig_category":"Abogados",
    "sg:phone":"+34 956 40 64 15",
    "sg:postcode":"11130",
    "sg:province":"C\u00e1diz",
    "wof:name":"Monzon Moreno Jose Maria",
    "wof:placetype":"venue"
},
  "geometry": {"coordinates":[-6.1479291916,36.4214515686],"type":"Point"}
}