{
  "type": "Feature",
  "properties": {
    "addr:full":"Cmno Vecinal El Fondillo, 82 Tafira Baja Las Palmas 35017",
    "addr:housenumber":"82",
    "addr:postcode":"35017",
    "addr:street":"Cmno Vecinal El Fondillo",
    "iso:country":"ES",
    "sg:address":"Cmno Vecinal El Fondillo, 82",
    "sg:city":"Tafira Baja",
    "sg:orig_category":"Alimentaci\u00d3n General (al Por Menor)",
    "sg:phone":"+34 928 35 10 14",
    "sg:postcode":"35017",
    "sg:province":"Las Palmas",
    "wof:name":"Santana Infante Dolores",
    "wof:placetype":"venue"
},
  "geometry": {"coordinates":[-15.4646606445,28.054693222],"type":"Point"}
}