{
  "type": "Feature",
  "properties": {
    "iso:country":"ES",
    "sg:address":"Peroxa, S/n",
    "sg:city":"Peroxa",
    "sg:orig_category":"Arenas, Guijarros Y Granulados",
    "sg:phone":"+34 986 53 03 70",
    "sg:postcode":"36658",
    "sg:province":"Pontevedra",
    "wof:name":"Aridos Da Peroxa S.l.",
    "wof:placetype":"venue"
},
  "geometry": {"coordinates":[-8.6480531693,42.4336204529],"type":"Point"}
}