{
  "type": "Feature",
  "properties": {
    "iso:country":"ES",
    "sg:address":"Calle de San Marcos, 88",
    "sg:city":"Talavera Reina",
    "sg:orig_category":"Carnicer\u00cdas, Carnicer\u00cdas",
    "sg:phone":"+34 925 80 27 95",
    "sg:postcode":"45600",
    "sg:province":"Toledo",
    "wof:name":"Santos Jimenez Maria Isabel",
    "wof:placetype":"venue"
},
  "geometry": {"coordinates":[-4.8553671837,39.9512710571],"type":"Point"}
}