{
  "type": "Feature",
  "properties": {
    "iso:country":"ES",
    "sg:address":"Calle de Catalu\u00d1a, 21",
    "sg:city":"Castellon",
    "sg:orig_category":"Farmacias",
    "sg:phone":"+34 964 21 06 15",
    "sg:postcode":"12004",
    "sg:province":"Castell\u00f3n",
    "wof:name":"Aragones Llop Maria Gracia",
    "wof:placetype":"venue"
},
  "geometry": {"coordinates":[-0.0422486998,39.9887771606],"type":"Point"}
}