{
  "type": "Feature",
  "properties": {
    "iso:country":"ES",
    "sg:address":"Calle de Fi\u00d1ana, 27",
    "sg:city":"Caniles",
    "sg:orig_category":"Reposter\u00cdas",
    "sg:phone":"+34 958 71 00 47",
    "sg:postcode":"18810",
    "sg:province":"Granada",
    "wof:name":"Panaderia Pasteleria Juan Lucas S.l.",
    "wof:placetype":"venue"
},
  "geometry": {"coordinates":[-2.7256979942,37.4359321594],"type":"Point"}
}