{
  "type": "Feature",
  "properties": {
    "addr:full":"Calle de Ribera, 8 Valencia Valencia 46002",
    "addr:housenumber":"8",
    "addr:postcode":"46002",
    "addr:street":"Calle De Ribera",
    "iso:country":"ES",
    "sg:address":"Calle de Ribera, 8",
    "sg:city":"Valencia",
    "sg:orig_category":"Ludotecas",
    "sg:phone":"+34 963 94 03 11",
    "sg:postcode":"46002",
    "sg:province":"Valencia",
    "wof:name":"Adjub 40 S.l.",
    "wof:placetype":"venue"
},
  "geometry": {"coordinates":[-0.375821799,39.4686317444],"type":"Point"}
}