{
  "type": "Feature",
  "properties": {
    "iso:country":"ES",
    "sg:address":"Av E Tierno Galvan, S/n",
    "sg:city":"Espinardo",
    "sg:orig_category":"Comercio, Reparaci\u00d3n De Motocicletas, Bicicletas Y Piezas Sueltas",
    "sg:phone":"+34 968 83 06 36",
    "sg:postcode":"30100",
    "sg:province":"Murcia",
    "wof:name":"Albaladejo Sierra Manuel",
    "wof:placetype":"venue"
},
  "geometry": {"coordinates":[-1.1503430605,38.0141448975],"type":"Point"}
}