{
  "type": "Feature",
  "properties": {
    "addr:full":"Calle de San Antonio, 1 Gijon Asturias 33201",
    "addr:housenumber":"1",
    "addr:postcode":"33201",
    "addr:street":"Calle De San Antonio",
    "iso:country":"ES",
    "sg:address":"Calle de San Antonio, 1",
    "sg:city":"Gijon",
    "sg:orig_category":"Fabricaci\u00d3n De Sobres, Bolsas Y Fundas",
    "sg:phone":"+34 985 35 86 81",
    "sg:postcode":"33201",
    "sg:province":"Asturias",
    "wof:name":"Vilo Sainz S.l.",
    "wof:placetype":"venue"
},
  "geometry": {"coordinates":[-5.6625900269,43.5438613892],"type":"Point"}
}