{
  "type": "Feature",
  "properties": {
    "addr:full":"La Solana, 22 Argamasilla Alba Ciudad Real 13710",
    "addr:housenumber":"22",
    "addr:postcode":"alba;13710",
    "addr:street":"Solana",
    "iso:country":"ES",
    "sg:address":"La Solana, 22",
    "sg:city":"Argamasilla Alba",
    "sg:orig_category":"Pensiones Familiares",
    "sg:phone":"+34 926 52 12 25",
    "sg:postcode":"13710",
    "sg:province":"Ciudad Real",
    "wof:name":"Aparicio Lagreca Manuela",
    "wof:placetype":"venue"
},
  "geometry": {"coordinates":[-3.092559576,39.1274185181],"type":"Point"}
}