{
  "type": "Feature",
  "properties": {
    "iso:country":"ES",
    "sg:address":"Avda Descubrimientos (los), S/n",
    "sg:city":"Mairena Aljarafe",
    "sg:classifiers":[
        {
            "category":"Autos & Motor Vehicles",
            "subcategory":"Automobile Sales",
            "type":"Retail Goods"
        }
    ],
    "sg:phone":"+34 954 18 38 21",
    "sg:postcode":"41927",
    "sg:province":"Sevilla",
    "wof:name":"Autoescuela Ciudad Expo S.l",
    "wof:placetype":"venue"
},
  "geometry": {"coordinates":[-6.0502114296,37.3501434326],"type":"Point"}
}