{
  "type": "Feature",
  "properties": {
    "addr:full":"Rua Oriente, 6 Ca\u00f1iza Pontevedra 36880",
    "addr:housenumber":"6",
    "addr:postcode":"36880",
    "addr:street":"Rua Oriente",
    "iso:country":"ES",
    "sg:address":"Rua Oriente, 6",
    "sg:city":"Ca\u00f1iza",
    "sg:orig_category":"Bisuter\u00cda, Joyer\u00cda, Relojer\u00cda (al Por Menor)",
    "sg:phone":"+34 986 65 23 81",
    "sg:postcode":"36880",
    "sg:province":"Pontevedra",
    "wof:name":"Casa Y Algodon Mi Casa S.l.",
    "wof:placetype":"venue"
},
  "geometry": {"coordinates":[-8.2728424072,42.2127952576],"type":"Point"}
}