{
  "type": "Feature",
  "properties": {
    "iso:country":"ES",
    "sg:address":"Carrer de Sagristans, 9",
    "sg:city":"Barcelona",
    "sg:classifiers":[
        {
            "category":"Personal",
            "subcategory":"Barber",
            "type":"Services"
        }
    ],
    "sg:phone":"+34 933 17 53 33",
    "sg:postcode":"08002",
    "sg:province":"Barcelona",
    "sg:tags":[
        "caballeros",
        "de",
        "peluqueros"
    ],
    "wof:name":"Barroso Rodriguez Jose Luis",
    "wof:placetype":"venue"
},
  "geometry": {"coordinates":[2.1752450466,41.3852348328],"type":"Point"}
}