{
  "type": "Feature",
  "properties": {
    "addr:full":"Avda Costa, 67 Gijon Asturias 33202",
    "addr:housenumber":"67",
    "addr:postcode":"33202",
    "addr:street":"Avda Costa",
    "iso:country":"ES",
    "sg:address":"Avda Costa, 67",
    "sg:city":"Gijon",
    "sg:orig_category":"Art\u00cdculos De Regalo (al Por Menor)",
    "sg:phone":"+34 985 33 05 43",
    "sg:postcode":"33202",
    "sg:province":"Asturias",
    "wof:name":"Garcia Sanchez Felix",
    "wof:placetype":"venue"
},
  "geometry": {"coordinates":[-5.6562700272,43.5376243591],"type":"Point"}
}