{
  "type": "Feature",
  "properties": {
    "iso:country":"ES",
    "sg:address":"Pase San Gregorio, 43",
    "sg:city":"Puertollano",
    "sg:orig_category":"Ingenier\u00cda, Centros De Estudios (diversos)",
    "sg:phone":"+34 926 42 79 51",
    "sg:postcode":"13500",
    "sg:province":"Ciudad Real",
    "wof:name":"Previcon S.l.",
    "wof:placetype":"venue"
},
  "geometry": {"coordinates":[-4.1043257713,38.6891403198],"type":"Point"}
}