{
  "type": "Feature",
  "properties": {
    "iso:country":"ES",
    "sg:address":"Plaz Andalucia, 4",
    "sg:city":"Palma Rio",
    "sg:orig_category":"Ense\u00d1anza: Profesiones Art\u00cdsticas",
    "sg:phone":"+34 957 64 39 63",
    "sg:postcode":"14700",
    "sg:province":"C\u00f3rdoba",
    "wof:name":"Rueda Rincon Antonio",
    "wof:placetype":"venue"
},
  "geometry": {"coordinates":[-5.2795991898,37.7004241943],"type":"Point"}
}