{
  "type": "Feature",
  "properties": {
    "addr:full":"Calle de Navas De Tolosa, 10 Jaen Ja\u00e9n 23001",
    "addr:housenumber":"10;jae\u0301n",
    "addr:postcode":"23001",
    "addr:street":"Calle De Navas De Tolosa",
    "iso:country":"ES",
    "sg:address":"Calle de Navas De Tolosa, 10",
    "sg:city":"Jaen",
    "sg:orig_category":"Cl\u00cdnicas Dentales",
    "sg:phone":"+34 953 22 52 39",
    "sg:postcode":"23001",
    "sg:province":"Ja\u00e9n",
    "wof:name":"Liebana Cano Rafael",
    "wof:placetype":"venue"
},
  "geometry": {"coordinates":[-3.7873420715,37.7700271606],"type":"Point"}
}