{
  "type": "Feature",
  "properties": {
    "addr:full":"Calle de Alonso Barba, 8 Alcala Henares Madrid 28806",
    "addr:housenumber":"8",
    "addr:postcode":"28806",
    "addr:street":"Calle De Alonso Barba",
    "iso:country":"ES",
    "sg:address":"Calle de Alonso Barba, 8",
    "sg:city":"Alcala Henares",
    "sg:orig_category":"Fabricaci\u00d3n, Venta De Cuadros, Accesorios Para Enmarcar",
    "sg:phone":"+34 918 80 89 65",
    "sg:postcode":"28806",
    "sg:province":"Madrid",
    "wof:name":"Molduras Especiales S. A.",
    "wof:placetype":"venue"
},
  "geometry": {"coordinates":[-3.4033513069,40.4916114807],"type":"Point"}
}