{
  "type": "Feature",
  "properties": {
    "iso:country":"ES",
    "sg:address":"Carrer de Pont Del Treball, 5",
    "sg:city":"Barcelona",
    "sg:orig_category":"Reposter\u00cdas",
    "sg:phone":"+34 932 78 31 07",
    "sg:postcode":"08020",
    "sg:province":"Barcelona",
    "wof:name":"Gomez Acosta Consuelo",
    "wof:placetype":"venue"
},
  "geometry": {"coordinates":[2.1982429028,41.421672821],"type":"Point"}
}