{
  "type": "Feature",
  "properties": {
    "iso:country":"ES",
    "sg:address":"C/ Goya, 4",
    "sg:city":"Ferreries",
    "sg:orig_category":"Empresas De Carpinter\u00cda De Madera",
    "sg:phone":"+34 971 37 40 80",
    "sg:postcode":"07750",
    "sg:province":"Islas Baleares",
    "wof:name":"Precarma S.l.",
    "wof:placetype":"venue"
},
  "geometry": {"coordinates":[4.0114431381,39.9855690002],"type":"Point"}
}