{
  "type": "Feature",
  "properties": {
    "addr:full":"Calle de San Blas, 6 Parla Madrid 28980",
    "addr:housenumber":"6",
    "addr:postcode":"28980",
    "addr:street":"Calle De San Blas",
    "iso:country":"ES",
    "sg:address":"Calle de San Blas, 6",
    "sg:city":"Parla",
    "sg:orig_category":"Centros De Coordinaci\u00d3n",
    "sg:phone":"+34 916 05 69 74",
    "sg:postcode":"28980",
    "sg:province":"Madrid",
    "wof:name":"Gestoria Administrativa Gonzalez Martinez Sl",
    "wof:placetype":"venue"
},
  "geometry": {"coordinates":[-3.7710399628,40.2405128479],"type":"Point"}
}