{
  "type": "Feature",
  "properties": {
    "iso:country":"ES",
    "sg:address":"Calle de Vi\u00d1as, S/n",
    "sg:city":"Trabazos",
    "sg:orig_category":"Art\u00cdculos De Aluminio",
    "sg:phone":"+34 980 68 10 07",
    "sg:postcode":"49516",
    "sg:province":"Zamora",
    "wof:name":"Mendez Casado Emilio",
    "wof:placetype":"venue"
},
  "geometry": {"coordinates":[-6.4900012016,41.7475967407],"type":"Point"}
}