{
  "type": "Feature",
  "properties": {
    "iso:country":"ES",
    "sg:address":"Parque Tecnologico, 12",
    "sg:city":"Pinseque",
    "sg:orig_category":"Confecci\u00d3n De Trajes Para Se\u00d1oras",
    "sg:phone":"+34 976 65 68 58",
    "sg:postcode":"50298",
    "sg:province":"Zaragoza",
    "wof:name":"Belotex Sll",
    "wof:placetype":"venue"
},
  "geometry": {"coordinates":[-1.0983140469,41.7387619019],"type":"Point"}
}