{
  "type": "Feature",
  "properties": {
    "addr:full":"Calle de Castilla, 21 Cadrete Zaragoza 50420",
    "addr:housenumber":"21",
    "addr:postcode":"50420",
    "addr:street":"Calle De Castilla",
    "iso:country":"ES",
    "sg:address":"Calle de Castilla, 21",
    "sg:city":"Cadrete",
    "sg:orig_category":"Panader\u00cdas, Pasteler\u00cdas, Boller\u00cda Industriale (fabricaci\u00d3n, Al Por Mayor)",
    "sg:phone":"+34 976 12 52 09",
    "sg:postcode":"50420",
    "sg:province":"Zaragoza",
    "wof:name":"Ra & Mi S.cv.",
    "wof:placetype":"venue"
},
  "geometry": {"coordinates":[-0.9648069143,41.5641288757],"type":"Point"}
}