{
  "type": "Feature",
  "properties": {
    "iso:country":"ES",
    "sg:address":"Calle de Rojo Hermogenes, 2",
    "sg:city":"Bilbao",
    "sg:orig_category":"Poller\u00cda Y Caza (al Por Menor)",
    "sg:phone":"+34 944 99 34 29",
    "sg:postcode":"48013",
    "sg:province":"Vizcaya",
    "wof:name":"Gutierrez Vaquero Anastasio",
    "wof:placetype":"venue"
},
  "geometry": {"coordinates":[-2.9732511044,43.2775268555],"type":"Point"}
}