{
  "type": "Feature",
  "properties": {
    "addr:full":"Calle de Solar, S/n Gijon Asturias 33213",
    "addr:housenumber":"s / n",
    "addr:postcode":"33213",
    "addr:street":"Calle De Solar",
    "iso:country":"ES",
    "sg:address":"Calle de Solar, S/n",
    "sg:city":"Gijon",
    "sg:orig_category":"Ferreter\u00cda (diversos)",
    "sg:phone":"+34 985 32 36 86",
    "sg:postcode":"33213",
    "sg:province":"Asturias",
    "wof:name":"Rodriguez Molano Cristina",
    "wof:placetype":"venue"
},
  "geometry": {"coordinates":[-5.7072591782,43.5364456177],"type":"Point"}
}