{
  "type": "Feature",
  "properties": {
    "addr:full":"Calle de Veracruz, 16 Puebla Almoradiel Toledo 45840",
    "addr:housenumber":"16",
    "addr:postcode":"45840",
    "addr:street":"Calle De Veracruz;Almoradiel",
    "iso:country":"ES",
    "sg:address":"Calle de Veracruz, 16",
    "sg:city":"Puebla Almoradiel",
    "sg:orig_category":"Farmacias",
    "sg:phone":"+34 925 17 87 29",
    "sg:postcode":"45840",
    "sg:province":"Toledo",
    "wof:name":"Ortiz Medina Luis Farmacia",
    "wof:placetype":"venue"
},
  "geometry": {"coordinates":[-3.1181190014,39.5993232727],"type":"Point"}
}