{
  "type": "Feature",
  "properties": {
    "addr:full":"Calle de Abel Anton, 7 Rute C\u00f3rdoba 14960",
    "addr:housenumber":"7",
    "addr:postcode":"14960",
    "addr:street":"Calle De Abel Anton;Co\u0301Rdoba",
    "iso:country":"ES",
    "sg:address":"Calle de Abel Anton, 7",
    "sg:city":"Rute",
    "sg:orig_category":"Abogados",
    "sg:phone":"+34 957 53 91 29",
    "sg:postcode":"14960",
    "sg:province":"C\u00f3rdoba",
    "wof:name":"Perez Mur Esther",
    "wof:placetype":"venue"
},
  "geometry": {"coordinates":[-4.372238636,37.3239097595],"type":"Point"}
}