{
  "type": "Feature",
  "properties": {
    "addr:full":"Calle de Pinzon, 10 Malaga M\u00e1laga 29001",
    "addr:housenumber":"10",
    "addr:postcode":"29001",
    "addr:street":"Calle De Pinzon;Ma\u0301Laga",
    "iso:country":"ES",
    "sg:address":"Calle de Pinzon, 10",
    "sg:city":"Malaga",
    "sg:orig_category":"Electrodom\u00c9sticos (fabricaci\u00d3n, Al Por Mayor)",
    "sg:phone":"+34 952 06 04 74",
    "sg:postcode":"29001",
    "sg:province":"M\u00e1laga",
    "wof:name":"T-systems Itc Services Espa\u00d1a S.a.",
    "wof:placetype":"venue"
},
  "geometry": {"coordinates":[-4.423927784,36.7149009705],"type":"Point"}
}