{
  "type": "Feature",
  "properties": {
    "iso:country":"ES",
    "sg:address":"Calle de Villena, 13",
    "sg:city":"Banyeres Mariola",
    "sg:orig_category":"Reposter\u00cdas",
    "sg:phone":"+34 965 56 70 86",
    "sg:postcode":"03450",
    "sg:province":"Alicante",
    "wof:name":"Gisbert Aznar Beatriz",
    "wof:placetype":"venue"
},
  "geometry": {"coordinates":[-0.6607499719,38.7176513672],"type":"Point"}
}