{
  "type": "Feature",
  "properties": {
    "iso:country":"ES",
    "sg:address":"Praz Pazo De Pati\u00d1o (do), 5",
    "sg:city":"Sanxenxo",
    "sg:orig_category":"Doctores En Medicina",
    "sg:phone":"+34 986 69 05 51",
    "sg:postcode":"36960",
    "sg:province":"Pontevedra",
    "wof:name":"Magdalena Mouri\u00f1o Luis",
    "wof:placetype":"venue"
},
  "geometry": {"coordinates":[-8.8059329987,42.4004325867],"type":"Point"}
}