{
  "type": "Feature",
  "properties": {
    "iso:country":"ES",
    "sg:address":"Calle de Burgos, 3",
    "sg:city":"San Juan De Aznalfarache",
    "sg:orig_category":"Ropa De Hogar (al Por Menor)",
    "sg:phone":"+34 954 76 70 01",
    "sg:postcode":"41920",
    "sg:province":"Sevilla",
    "wof:name":"Albalalejo Letran Manuela",
    "wof:placetype":"venue"
},
  "geometry": {"coordinates":[-6.0361013412,37.357334137],"type":"Point"}
}