{
  "type": "Feature",
  "properties": {
    "iso:country":"ES",
    "sg:address":"Calle de Labasture, 4",
    "sg:city":"Plentzia",
    "sg:orig_category":"Urbanistas",
    "sg:phone":"+34 946 77 30 50",
    "sg:postcode":"48620",
    "sg:province":"Vizcaya",
    "wof:name":"Massalleras Vidal Isabel",
    "wof:placetype":"venue"
},
  "geometry": {"coordinates":[-2.9498488903,43.4055747986],"type":"Point"}
}