{
  "type": "Feature",
  "properties": {
    "addr:full":"Rond Alarcos, 36 Ciudad Real Ciudad Real 13002",
    "addr:housenumber":"36",
    "addr:postcode":"13002",
    "addr:street":"Rond Alarcos",
    "iso:country":"ES",
    "sg:address":"Rond Alarcos, 36",
    "sg:city":"Ciudad Real",
    "sg:orig_category":"Promotores Constructores",
    "sg:phone":"+34 926 21 56 25",
    "sg:postcode":"13002",
    "sg:province":"Ciudad Real",
    "wof:name":"Jesus Talavera Yebenes S.a.",
    "wof:placetype":"venue"
},
  "geometry": {"coordinates":[-3.9341979027,38.9871101379],"type":"Point"}
}