{
  "type": "Feature",
  "properties": {
    "iso:country":"ES",
    "sg:address":"Carr Progres, S/n",
    "sg:city":"Santa Margalida",
    "sg:orig_category":"Centros De Educaci\u00d3n Especial",
    "sg:phone":"+34 971 52 32 94",
    "sg:postcode":"07450",
    "sg:province":"Islas Baleares",
    "wof:name":"Escuela Nacional Graduada Mixta",
    "wof:placetype":"venue"
},
  "geometry": {"coordinates":[3.1024870872,39.7049102783],"type":"Point"}
}