{
  "type": "Feature",
  "properties": {
    "iso:country":"ES",
    "sg:address":"Calle de La Rioja, 7",
    "sg:city":"Madrid",
    "sg:orig_category":"Montaje (empresas De)",
    "sg:phone":"+34 917 42 43 41",
    "sg:postcode":"28042",
    "sg:province":"Madrid",
    "wof:name":"Gamarra Avila Oscar",
    "wof:placetype":"venue"
},
  "geometry": {"coordinates":[-3.5898020267,40.4566192627],"type":"Point"}
}