{
  "type": "Feature",
  "properties": {
    "addr:full":"Fco Bergamin, 15 Iru\u00f1a Navarra 31003",
    "addr:housenumber":"15",
    "addr:postcode":"31003",
    "addr:street":"Fco Bergamin",
    "iso:country":"ES",
    "sg:address":"Fco Bergamin, 15",
    "sg:city":"Iru\u00f1a",
    "sg:orig_category":"Abogados",
    "sg:phone":"+34 948 15 00 52",
    "sg:postcode":"31003",
    "sg:province":"Navarra",
    "wof:name":"Larumbe Zazu Jesus Maria",
    "wof:placetype":"venue"
},
  "geometry": {"coordinates":[-1.6414630413,42.8112335205],"type":"Point"}
}