{
  "type": "Feature",
  "properties": {
    "addr:full":"Calle de Eduardo Requenas, 12 Madrid Madrid 28053",
    "addr:housenumber":"12",
    "addr:postcode":"madrid;28053",
    "addr:street":"Calle De Eduardo Requenas",
    "iso:country":"ES",
    "sg:address":"Calle de Eduardo Requenas, 12",
    "sg:city":"Madrid",
    "sg:orig_category":"Imprenta",
    "sg:phone":"+34 914 77 52 02",
    "sg:postcode":"28053",
    "sg:province":"Madrid",
    "wof:name":"Artes Graficas Ruiz S.l.",
    "wof:placetype":"venue"
},
  "geometry": {"coordinates":[-3.6656684875,40.3905448914],"type":"Point"}
}