{
  "type": "Feature",
  "properties": {
    "iso:country":"ES",
    "sg:address":"Avda Sorolla De, 23",
    "sg:city":"Torremolinos",
    "sg:orig_category":"Asilos De Ancianos. Centros Privados",
    "sg:phone":"+34 952 38 37 06",
    "sg:postcode":"29620",
    "sg:province":"M\u00e1laga",
    "wof:name":"Geriatria Malacitana S.l.",
    "wof:placetype":"venue"
},
  "geometry": {"coordinates":[-4.5040578842,36.6262359619],"type":"Point"}
}