{
  "type": "Feature",
  "properties": {
    "iso:country":"ES",
    "sg:address":"Calle de Francos, 42",
    "sg:city":"Sevilla",
    "sg:orig_category":"Lencer\u00cda Femenina, Corseter\u00cda, Trajes De Ba\u00d1o (al Por Menor)",
    "sg:phone":"+34 954 50 20 33",
    "sg:postcode":"41004",
    "sg:province":"Sevilla",
    "wof:name":"Los Caminos De Peyre S.l.",
    "wof:placetype":"venue"
},
  "geometry": {"coordinates":[-5.9926438332,37.3882484436],"type":"Point"}
}