{
  "type": "Feature",
  "properties": {
    "iso:country":"ES",
    "sg:address":"Avda Dos De Mayo (del), 67",
    "sg:city":"Mostoles",
    "sg:orig_category":"Juegos Y Juguetes (al Por Menor)",
    "sg:phone":"+34 916 17 03 78",
    "sg:postcode":"28934",
    "sg:province":"Madrid",
    "wof:name":"Jugueteria El Capricho S.l.",
    "wof:placetype":"venue"
},
  "geometry": {"coordinates":[-3.8740739822,40.3194007874],"type":"Point"}
}