{
  "type": "Feature",
  "properties": {
    "iso:country":"ES",
    "sg:address":"Calle de Almendros, Los, 11",
    "sg:city":"Calpe",
    "sg:orig_category":"Reposter\u00cdas",
    "sg:phone":"+34 965 83 03 81",
    "sg:postcode":"03710",
    "sg:province":"Alicante",
    "wof:name":"Mas Crespo Marisol",
    "wof:placetype":"venue"
},
  "geometry": {"coordinates":[0.0464835986,38.6447296143],"type":"Point"}
}