{
  "type": "Feature",
  "properties": {
    "addr:full":"Avda Leganes, 27 Alcorcon Madrid 28924",
    "addr:housenumber":"27",
    "addr:postcode":"28924",
    "addr:street":"Avda Leganes",
    "iso:country":"ES",
    "sg:address":"Avda Leganes, 27",
    "sg:city":"Alcorcon",
    "sg:orig_category":"Centros Empresariales",
    "sg:phone":"+34 916 19 63 71",
    "sg:postcode":"28924",
    "sg:province":"Madrid",
    "wof:name":"Sertec, Proyectos Y Desarrollos S.l.",
    "wof:placetype":"venue"
},
  "geometry": {"coordinates":[-3.8150439262,40.3464813232],"type":"Point"}
}