{
  "type": "Feature",
  "properties": {
    "addr:full":"Pla\u00c7 Frederic Rahola, 9 Cadaques Girona 17488",
    "addr:housenumber":"9",
    "addr:postcode":"17488",
    "addr:street":"Cadaques Girona",
    "iso:country":"ES",
    "sg:address":"Pla\u00c7 Frederic Rahola, 9",
    "sg:city":"Cadaques",
    "sg:orig_category":"Farmacias",
    "sg:phone":"+34 972 25 87 51",
    "sg:postcode":"17488",
    "sg:province":"Girona",
    "wof:name":"Moradell Llobet Eva",
    "wof:placetype":"venue"
},
  "geometry": {"coordinates":[3.2778389454,42.288974762],"type":"Point"}
}