{
  "type": "Feature",
  "properties": {
    "iso:country":"ES",
    "sg:address":"Carrer de Pedro Cano, 33",
    "sg:city":"Mutxamel",
    "sg:orig_category":"Empresarios",
    "sg:phone":"+34 965 95 35 79",
    "sg:postcode":"03110",
    "sg:province":"Alicante",
    "wof:name":"Verdu Anton Jose Ramon",
    "wof:placetype":"venue"
},
  "geometry": {"coordinates":[-0.4429610074,38.4170227051],"type":"Point"}
}