{
  "type": "Feature",
  "properties": {
    "addr:full":"Carrer de Font Vella, 90 Terrassa Barcelona 08221",
    "addr:housenumber":"90",
    "addr:postcode":"08221",
    "addr:street":"Carrer De;Vella",
    "iso:country":"ES",
    "sg:address":"Carrer de Font Vella, 90",
    "sg:city":"Terrassa",
    "sg:orig_category":"Art\u00cdculos De Decoraci\u00d3n",
    "sg:phone":"+34 937 86 17 22",
    "sg:postcode":"08221",
    "sg:province":"Barcelona",
    "wof:name":"Montse Interior S.l",
    "wof:placetype":"venue"
},
  "geometry": {"coordinates":[2.0144240856,41.5630836487],"type":"Point"}
}