{
  "type": "Feature",
  "properties": {
    "iso:country":"ES",
    "sg:address":"Calle de Coca, 4",
    "sg:city":"Madrid",
    "sg:orig_category":"Farmacias",
    "sg:phone":"+34 914 64 75 98",
    "sg:postcode":"28047",
    "sg:province":"Madrid",
    "wof:name":"Ortiz Garcia Pilar",
    "wof:placetype":"venue"
},
  "geometry": {"coordinates":[-3.7490100861,40.4033584595],"type":"Point"}
}