{
  "type": "Feature",
  "properties": {
    "iso:country":"ES",
    "sg:address":"Avda America, 9",
    "sg:city":"Estrada",
    "sg:orig_category":"Electrodom\u00c9sticos (al Por Menor)",
    "sg:phone":"+34 986 57 09 12",
    "sg:postcode":"36680",
    "sg:province":"Pontevedra",
    "wof:name":"Electrodomesticos Baladron S.l",
    "wof:placetype":"venue"
},
  "geometry": {"coordinates":[-8.4950885773,42.6885604858],"type":"Point"}
}