{
  "type": "Feature",
  "properties": {
    "iso:country":"ES",
    "sg:address":"Calle de Alheli, 11",
    "sg:city":"Sevilla",
    "sg:orig_category":"Reposter\u00cdas",
    "sg:phone":"+34 954 35 79 14",
    "sg:postcode":"41008",
    "sg:province":"Sevilla",
    "wof:name":"Copacial S.a.",
    "wof:placetype":"venue"
},
  "geometry": {"coordinates":[-5.9792332649,37.4039115906],"type":"Point"}
}