{
  "type": "Feature",
  "properties": {
    "addr:full":"Calle de Pardo Bazan, 9 Salamanca Salamanca 37004",
    "addr:housenumber":"9",
    "addr:postcode":"37004",
    "addr:street":"Calle De Pardo Bazan",
    "iso:country":"ES",
    "sg:address":"Calle de Pardo Bazan, 9",
    "sg:city":"Salamanca",
    "sg:orig_category":"Promotores Constructores",
    "sg:phone":"+34 923 12 48 91",
    "sg:postcode":"37004",
    "sg:province":"Salamanca",
    "wof:name":"Comunidad De Propietarios C/ Pardo Bazan N\u00ba 9",
    "wof:placetype":"venue"
},
  "geometry": {"coordinates":[-5.6543321609,40.9724464417],"type":"Point"}
}