{
  "type": "Feature",
  "properties": {
    "iso:country":"ES",
    "sg:address":"Calle de Barreras (las), S/n",
    "sg:city":"Villaverde Abadia",
    "sg:orig_category":"Chapister\u00cda",
    "sg:phone":"+34 987 54 47 43",
    "sg:postcode":"24390",
    "sg:province":"Le\u00f3n",
    "wof:name":"Pacios Rodriguez Enrique",
    "wof:placetype":"venue"
},
  "geometry": {"coordinates":[-6.7131643295,42.5243301392],"type":"Point"}
}