{
  "type": "Feature",
  "properties": {
    "iso:country":"ES",
    "sg:address":"Calle de Maria Mediadora, S/n",
    "sg:city":"Cedeira",
    "sg:orig_category":"Encuadernaci\u00d3n E Impresi\u00d3n De Folletos",
    "sg:phone":"+34 981 48 04 23",
    "sg:postcode":"15350",
    "sg:province":"La Coru\u00f1a",
    "wof:name":"Bouzamayor Lorenzo Mercedes",
    "wof:placetype":"venue"
},
  "geometry": {"coordinates":[-8.0532236099,43.6614112854],"type":"Point"}
}