{
  "type": "Feature",
  "properties": {
    "addr:full":"Calle de Ancha, 49 Huetor-tajar Granada 18360",
    "addr:housenumber":"49",
    "addr:postcode":"18360",
    "addr:street":"Calle De Ancha",
    "iso:country":"ES",
    "sg:address":"Calle de Ancha, 49",
    "sg:city":"Huetor-tajar",
    "sg:orig_category":"\u00d3pticos Optometristas (al Por Menor)",
    "sg:phone":"+34 958 33 28 06",
    "sg:postcode":"18360",
    "sg:province":"Granada",
    "wof:name":"Centro Optico Jimenez Garofano S.l.",
    "wof:placetype":"venue"
},
  "geometry": {"coordinates":[-4.0476894379,37.1978340149],"type":"Point"}
}