{
  "type": "Feature",
  "properties": {
    "iso:country":"ES",
    "sg:address":"Avda Numancia, S/n",
    "sg:city":"Calahorra",
    "sg:orig_category":"Internados & Ense\u00d1anza Privada",
    "sg:phone":"+34 941 13 29 01",
    "sg:postcode":"26500",
    "sg:province":"La Rioja",
    "wof:name":"Hijas De La Caridad",
    "wof:placetype":"venue"
},
  "geometry": {"coordinates":[-1.9746290445,42.3027801514],"type":"Point"}
}