{
  "type": "Feature",
  "properties": {
    "addr:full":"Carrer de Corro, 1 Granollers Barcelona 08401",
    "addr:housenumber":"1",
    "addr:postcode":"08401",
    "addr:street":"Carrer De Corro",
    "iso:country":"ES",
    "sg:address":"Carrer de Corro, 1",
    "sg:city":"Granollers",
    "sg:orig_category":"Florister\u00cdas",
    "sg:phone":"+34 938 70 47 47",
    "sg:postcode":"08401",
    "sg:province":"Barcelona",
    "wof:name":"Soldevila Estrada Roser",
    "wof:placetype":"venue"
},
  "geometry": {"coordinates":[2.2877850533,41.6092567444],"type":"Point"}
}