{
  "type": "Feature",
  "properties": {
    "addr:full":"Calle de Santa Ana, 76 Gineta Albacete 02110",
    "addr:housenumber":"76",
    "addr:postcode":"02110",
    "addr:street":"Calle De Santa Ana",
    "iso:country":"ES",
    "sg:address":"Calle de Santa Ana, 76",
    "sg:city":"Gineta",
    "sg:orig_category":"Muebles, Minoristas",
    "sg:phone":"+34 967 27 50 13",
    "sg:postcode":"02110",
    "sg:province":"Albacete",
    "wof:name":"Mobiliario Hosteleria Gaivall S.l.",
    "wof:placetype":"venue"
},
  "geometry": {"coordinates":[-2.0002090931,39.1132087708],"type":"Point"}
}