{
  "type": "Feature",
  "properties": {
    "addr:full":"Landeta Hiribidea, 25 Azpeitia Guip\u00f9zcoa 20730",
    "addr:housenumber":"25",
    "addr:postcode":"20730",
    "addr:street":"Landeta Hiribidea;Guipu\u0300Zcoa",
    "iso:country":"ES",
    "sg:address":"Landeta Hiribidea, 25",
    "sg:city":"Azpeitia",
    "sg:orig_category":"Electricidad: Instaladores",
    "sg:phone":"+34 943 81 68 58",
    "sg:postcode":"20730",
    "sg:province":"Guip\u00f9zcoa",
    "wof:name":"Ipintza S.a.",
    "wof:placetype":"venue"
},
  "geometry": {"coordinates":[-2.2539129257,43.1761398315],"type":"Point"}
}