{
  "type": "Feature",
  "properties": {
    "addr:full":"El Horno, 4 Cabo Blanco Santa Cruz De Tenerife 38626",
    "addr:housenumber":"4",
    "addr:postcode":"38626",
    "addr:street":"El Horno;Cabo Blanco",
    "iso:country":"ES",
    "sg:address":"El Horno, 4",
    "sg:city":"Cabo Blanco",
    "sg:orig_category":"Establecimientos De Cura, Prevenci\u00d3n Y Readaptaci\u00d3n",
    "sg:phone":"+34 922 72 16 64",
    "sg:postcode":"38626",
    "sg:province":"Santa Cruz De Tenerife",
    "wof:name":"Asociacion Vivir",
    "wof:placetype":"venue"
},
  "geometry": {"coordinates":[-16.6682376862,28.0703868866],"type":"Point"}
}