{
  "type": "Feature",
  "properties": {
    "iso:country":"ES",
    "sg:address":"Cra Piera, 4",
    "sg:city":"Martorell",
    "sg:orig_category":"Comercio De Piezas De Recambio Y De Accesorios De Veh\u00cdculos, Veh\u00cdculos Industriales",
    "sg:phone":"+34 937 74 07 02",
    "sg:postcode":"08760",
    "sg:province":"Barcelona",
    "wof:name":"Recanvis Martorell S.l.",
    "wof:placetype":"venue"
},
  "geometry": {"coordinates":[1.9231990576,41.4786148071],"type":"Point"}
}