{
  "type": "Feature",
  "properties": {
    "iso:country":"ES",
    "sg:address":"Rua Cardenal Rodrigo De Castro, 12",
    "sg:city":"Monforte De Lemos",
    "sg:orig_category":"Alimentaci\u00d3n General (al Por Menor)",
    "sg:phone":"+34 982 40 12 99",
    "sg:postcode":"27420",
    "sg:province":"Lugo",
    "wof:name":"Rodriguez Rodriguez Pablo",
    "wof:placetype":"venue"
},
  "geometry": {"coordinates":[-7.5264849663,42.496887207],"type":"Point"}
}