{
  "type": "Feature",
  "properties": {
    "iso:country":"ES",
    "sg:address":"Carrer de Vila Joiosa, 52",
    "sg:city":"Barcelona",
    "sg:orig_category":"Asesor\u00cda Fiscal Y Jur\u00cddica",
    "sg:phone":"+34 932 21 36 28",
    "sg:postcode":"08003",
    "sg:province":"Barcelona",
    "wof:name":"Artlegis S C P",
    "wof:placetype":"venue"
},
  "geometry": {"coordinates":[2.1911513805,41.3782539368],"type":"Point"}
}