{
  "type": "Feature",
  "properties": {
    "addr:full":"Calle de Europa, 3 Valladolid Valladolid 47009",
    "addr:housenumber":"3",
    "addr:postcode":"47009",
    "addr:street":"Calle De Europa",
    "iso:country":"ES",
    "sg:address":"Calle de Europa, 3",
    "sg:city":"Valladolid",
    "sg:orig_category":"Ense\u00d1anza Variada",
    "sg:phone":"+34 983 33 72 16",
    "sg:postcode":"47009",
    "sg:province":"Valladolid",
    "wof:name":"Gonzalez Fernandez Maria Azucena",
    "wof:placetype":"venue"
},
  "geometry": {"coordinates":[-4.7383475304,41.6628456116],"type":"Point"}
}