{
  "type": "Feature",
  "properties": {
    "addr:full":"Calle de Francisco Mari\u00d1o, 12 Coru\u00d1a La Coru\u00f1a 15004",
    "addr:housenumber":"12",
    "addr:postcode":"15004",
    "addr:street":"Calle De Francisco Marin\u0303O;La Corun\u0303A",
    "iso:country":"ES",
    "sg:address":"Calle de Francisco Mari\u00d1o, 12",
    "sg:city":"Coru\u00d1a",
    "sg:orig_category":"Ingeniero",
    "sg:phone":"+34 981 22 58 04",
    "sg:postcode":"15004",
    "sg:province":"La Coru\u00f1a",
    "wof:name":"Naranjo Arenas Diego",
    "wof:placetype":"venue"
},
  "geometry": {"coordinates":[-8.4080944061,43.366645813],"type":"Point"}
}