{
  "type": "Feature",
  "properties": {
    "iso:country":"ES",
    "sg:address":"Plaz Ubrique (de), 1",
    "sg:city":"Jerez De La Frontera",
    "sg:orig_category":"Farmacias",
    "sg:phone":"+34 956 30 49 62",
    "sg:postcode":"11405",
    "sg:province":"C\u00e1diz",
    "wof:name":"Beser Ruiz Julia",
    "wof:placetype":"venue"
},
  "geometry": {"coordinates":[-6.1058111191,36.6971511841],"type":"Point"}
}