{
  "type": "Feature",
  "properties": {
    "iso:country":"ES",
    "sg:address":"Calle de Valderrodrigo, 8",
    "sg:city":"Madrid",
    "sg:orig_category":"Asesor\u00cda Fiscal Y Jur\u00cddica",
    "sg:phone":"+34 913 16 15 11",
    "sg:postcode":"28035",
    "sg:province":"Madrid",
    "wof:name":"Afisla Consultoria De Empresas S.l.",
    "wof:placetype":"venue"
},
  "geometry": {"coordinates":[-3.7222619057,40.4695663452],"type":"Point"}
}