{
  "type": "Feature",
  "properties": {
    "iso:country":"ES",
    "sg:address":"Calle de Bonaire, 30",
    "sg:city":"Valencia",
    "sg:orig_category":"Instalaci\u00d3n De Vestuarios",
    "sg:phone":"+34 963 52 67 64",
    "sg:postcode":"46003",
    "sg:province":"Valencia",
    "wof:name":"Serrano Lopez Cristobal",
    "wof:placetype":"venue"
},
  "geometry": {"coordinates":[-0.3718389869,39.4718399048],"type":"Point"}
}