{
  "type": "Feature",
  "properties": {
    "iso:country":"ES",
    "sg:address":"Carrer de Balmes, 63",
    "sg:city":"Barcelona",
    "sg:orig_category":"Agencias Y Asesores De Publicidad",
    "sg:phone":"+34 933 23 60 56",
    "sg:postcode":"08007",
    "sg:province":"Barcelona",
    "wof:name":"Molins Nubiola Miguel",
    "wof:placetype":"venue"
},
  "geometry": {"coordinates":[2.1615629196,41.3899230957],"type":"Point"}
}