{
  "type": "Feature",
  "properties": {
    "iso:country":"ES",
    "sg:address":"Calle de Rio Molinar, 7",
    "sg:city":"Andosilla",
    "sg:orig_category":"Peluqueros: De Se\u00d1oras",
    "sg:phone":"+34 948 69 02 00",
    "sg:postcode":"31261",
    "sg:province":"Navarra",
    "wof:name":"Mayor Monasterio Ines",
    "wof:placetype":"venue"
},
  "geometry": {"coordinates":[-1.9500989914,42.371257782],"type":"Point"}
}