{
  "type": "Feature",
  "properties": {
    "addr:full":"Cmno Alivio, 8 Seijo Pontevedra 36740",
    "addr:housenumber":"8",
    "addr:postcode":"36740",
    "addr:street":"Cmno Alivio",
    "iso:country":"ES",
    "sg:address":"Cmno Alivio, 8",
    "sg:city":"Seijo",
    "sg:orig_category":"Inmobiliaria (agencias)",
    "sg:phone":"+34 986 62 26 07",
    "sg:postcode":"36740",
    "sg:province":"Pontevedra",
    "wof:name":"Inmobiliaria Barrantina S.l.",
    "wof:placetype":"venue"
},
  "geometry": {"coordinates":[-8.731048584,41.9869499207],"type":"Point"}
}