{
  "type": "Feature",
  "properties": {
    "iso:country":"ES",
    "sg:address":"Calle de Fuego (del), 48",
    "sg:city":"Alcobendas",
    "sg:orig_category":"Molduras, Junquillos, Listones Y Molduras Perforadas",
    "sg:phone":"+34 916 51 67 12",
    "sg:postcode":"28100",
    "sg:province":"Madrid",
    "wof:name":"Martin Martin Juan Manuel",
    "wof:placetype":"venue"
},
  "geometry": {"coordinates":[-3.6352078915,40.5452613831],"type":"Point"}
}