{
  "type": "Feature",
  "properties": {
    "addr:full":"Avda Prensa (la), 3 Sevilla Sevilla 41007",
    "addr:housenumber":"3",
    "addr:postcode":"41007",
    "addr:street":"Avda Prensa La",
    "iso:country":"ES",
    "sg:address":"Avda Prensa (la), 3",
    "sg:city":"Sevilla",
    "sg:orig_category":"Fabricaci\u00d3n De Bibliotecas Y Estanter\u00cdas",
    "sg:phone":"+34 954 52 06 00",
    "sg:postcode":"41007",
    "sg:province":"Sevilla",
    "wof:name":"Mecalux Servis",
    "wof:placetype":"venue"
},
  "geometry": {"coordinates":[-5.956264019,37.3898506165],"type":"Point"}
}