{
  "type": "Feature",
  "properties": {
    "addr:full":"Calle de Fuentespina, 21 Madrid Madrid 28031",
    "addr:housenumber":"21",
    "addr:postcode":"madrid;28031",
    "addr:street":"Calle De Fuentespina",
    "iso:country":"ES",
    "sg:address":"Calle de Fuentespina, 21",
    "sg:city":"Madrid",
    "sg:orig_category":"Peluqueros: De Se\u00d1oras",
    "sg:phone":"+34 913 32 64 46",
    "sg:postcode":"28031",
    "sg:province":"Madrid",
    "wof:name":"Amo Mancebo Miguel Angel Del",
    "wof:placetype":"venue"
},
  "geometry": {"coordinates":[-3.6054685116,40.3797492981],"type":"Point"}
}