{
  "type": "Feature",
  "properties": {
    "iso:country":"ES",
    "sg:address":"Rua Vilalba (de), 8",
    "sg:city":"Ribadeo",
    "sg:orig_category":"Art\u00cdculos De Decoraci\u00d3n",
    "sg:phone":"+34 982 13 09 00",
    "sg:postcode":"27700",
    "sg:province":"Lugo",
    "wof:name":"Lopez Covian Jose Luis",
    "wof:placetype":"venue"
},
  "geometry": {"coordinates":[-7.0450868607,43.5364990234],"type":"Point"}
}