{
  "type": "Feature",
  "properties": {
    "iso:country":"ES",
    "sg:address":"Ctra Guadarrama (de), 51",
    "sg:city":"San Lorenzo De El Escorial",
    "sg:orig_category":"Farmacias",
    "sg:phone":"+34 918 90 08 00",
    "sg:postcode":"28200",
    "sg:province":"Madrid",
    "wof:name":"Gonzalez Moreno Claudia",
    "wof:placetype":"venue"
},
  "geometry": {"coordinates":[-4.1277518272,40.6005096436],"type":"Point"}
}