{
  "type": "Feature",
  "properties": {
    "addr:full":"Barr Baular (el), S/n Mimetiz Vizcaya 48860",
    "addr:postcode":"48860",
    "addr:street":"El S / N",
    "iso:country":"ES",
    "sg:address":"Barr Baular (el), S/n",
    "sg:city":"Mimetiz",
    "sg:orig_category":"Cajas De Ahorro",
    "sg:phone":"+34 946 39 10 65",
    "sg:postcode":"48860",
    "sg:province":"Vizcaya",
    "wof:name":"Caja Laboral Popular",
    "wof:placetype":"venue"
},
  "geometry": {"coordinates":[-3.1296989918,43.2133483887],"type":"Point"}
}