{
  "type": "Feature",
  "properties": {
    "iso:country":"ES",
    "sg:address":"Calle de Rios Rosas, 30",
    "sg:city":"Madrid",
    "sg:orig_category":"M\u00c9dicos: Psiquiatr\u00cda",
    "sg:phone":"+34 914 42 81 05",
    "sg:postcode":"28003",
    "sg:province":"Madrid",
    "wof:name":"Mu\u00f1oz Soler Alberto",
    "wof:placetype":"venue"
},
  "geometry": {"coordinates":[-3.6988039017,40.4417304993],"type":"Point"}
}