{
  "type": "Feature",
  "properties": {
    "iso:country":"ES",
    "sg:address":"Calle de La Rua, 57",
    "sg:city":"Villalon Campos",
    "sg:orig_category":"Cajas Para Embalar",
    "sg:phone":"+34 983 74 01 02",
    "sg:postcode":"47600",
    "sg:province":"Valladolid",
    "wof:name":"Caja Rural Del Duero",
    "wof:placetype":"venue"
},
  "geometry": {"coordinates":[-5.0358819962,42.0978012085],"type":"Point"}
}