{
  "type": "Feature",
  "properties": {
    "addr:full":"Carr Gregal, 29 Godella Valencia 46110",
    "addr:housenumber":"29",
    "addr:postcode":"46110",
    "addr:street":"Carr Gregal",
    "iso:country":"ES",
    "sg:address":"Carr Gregal, 29",
    "sg:city":"Godella",
    "sg:orig_category":"Ingeniero",
    "sg:phone":"+34 963 63 79 94",
    "sg:postcode":"46110",
    "sg:province":"Valencia",
    "wof:name":"Ortiz Descalzo Adolfo",
    "wof:placetype":"venue"
},
  "geometry": {"coordinates":[-0.4154840112,39.5255889893],"type":"Point"}
}