{
  "type": "Feature",
  "properties": {
    "addr:full":"Carrer de Viladrosa, 114 Barcelona Barcelona 08042",
    "addr:housenumber":"114",
    "addr:postcode":"08042",
    "addr:street":"Carrer De Viladrosa",
    "iso:country":"ES",
    "sg:address":"Carrer de Viladrosa, 114",
    "sg:city":"Barcelona",
    "sg:orig_category":"Poller\u00cda Y Caza (al Por Menor)",
    "sg:phone":"+34 933 53 34 20",
    "sg:postcode":"08042",
    "sg:province":"Barcelona",
    "wof:name":"Huevos Margim S.l.",
    "wof:placetype":"venue"
},
  "geometry": {"coordinates":[2.1773838997,41.4440574646],"type":"Point"}
}