{
  "type": "Feature",
  "properties": {
    "iso:country":"ES",
    "sg:address":"Calle de Canalejas, 38",
    "sg:city":"Balos I",
    "sg:orig_category":"Confiter\u00cdas, Chocolater\u00cdas (al Por Menor)",
    "sg:phone":"+34 928 79 52 79",
    "sg:postcode":"35110",
    "sg:province":"Las Palmas",
    "wof:name":"Reigosa Bordon Victor",
    "wof:placetype":"venue"
},
  "geometry": {"coordinates":[-15.4300060272,28.1248226166],"type":"Point"}
}