{
  "type": "Feature",
  "properties": {
    "addr:full":"Calle de Fernando Guanarteme, 109 Palmas De Gran Canaria Las Palmas 35010",
    "addr:housenumber":"109",
    "addr:postcode":"35010",
    "addr:street":"Calle De Fernando Guanarteme",
    "iso:country":"ES",
    "sg:address":"Calle de Fernando Guanarteme, 109",
    "sg:city":"Palmas De Gran Canaria",
    "sg:orig_category":"Abogados",
    "sg:phone":"+34 928 26 95 51",
    "sg:postcode":"35010",
    "sg:province":"Las Palmas",
    "wof:name":"Cobo Machin Luis Jorge",
    "wof:placetype":"venue"
},
  "geometry": {"coordinates":[-15.4387302399,28.1340370178],"type":"Point"}
}