{
  "type": "Feature",
  "properties": {
    "addr:full":"Cmno Aljube, 14 Tobarra Albacete 02500",
    "addr:housenumber":"14",
    "addr:postcode":"02500",
    "addr:street":"Cmno Aljube",
    "iso:country":"ES",
    "sg:address":"Cmno Aljube, 14",
    "sg:city":"Tobarra",
    "sg:orig_category":"Armaduras De Hormig\u00d3n",
    "sg:phone":"+34 967 32 87 20",
    "sg:postcode":"02500",
    "sg:province":"Albacete",
    "wof:name":"Estructuras Coy S.l.",
    "wof:placetype":"venue"
},
  "geometry": {"coordinates":[-1.6946289539,38.5935401917],"type":"Point"}
}