{
  "type": "Feature",
  "properties": {
    "addr:full":"Av Meridiana, 180 Barcelona Barcelona 08026",
    "addr:housenumber":"180",
    "addr:postcode":"08026",
    "addr:street":"Meridiana",
    "iso:country":"ES",
    "sg:address":"Av Meridiana, 180",
    "sg:city":"Barcelona",
    "sg:orig_category":"M\u00c9dicos: Estomatolog\u00cda",
    "sg:phone":"+34 934 08 51 07",
    "sg:postcode":"08026",
    "sg:province":"Barcelona",
    "wof:name":"Paris Cenzano Jordi",
    "wof:placetype":"venue"
},
  "geometry": {"coordinates":[2.1870319843,41.4121017456],"type":"Point"}
}