{
  "type": "Feature",
  "properties": {
    "addr:full":"Carr Hannover, 27 Mao Islas Baleares 07703",
    "addr:housenumber":"27",
    "addr:postcode":"07703",
    "addr:street":"Carr Hannover",
    "iso:country":"ES",
    "sg:address":"Carr Hannover, 27",
    "sg:city":"Mao",
    "sg:orig_category":"Zapater\u00cdas",
    "sg:phone":"+34 971 36 35 09",
    "sg:postcode":"07703",
    "sg:province":"Islas Baleares",
    "wof:name":"Cardona Marques Lorenzo",
    "wof:placetype":"venue"
},
  "geometry": {"coordinates":[4.265625,39.8903694153],"type":"Point"}
}