{
  "type": "Feature",
  "properties": {
    "addr:full":"Urb Huerta Del Retortillo, 2 Chiclana De La Frontera C\u00e1diz 11130",
    "addr:housenumber":"2",
    "addr:postcode":"11130",
    "addr:street":"Urb;Del Retortillo",
    "iso:country":"ES",
    "sg:address":"Urb Huerta Del Retortillo, 2",
    "sg:city":"Chiclana De La Frontera",
    "sg:orig_category":"Agencias Y Agentes Comerciales, Representantes",
    "sg:phone":"+34 956 40 40 60",
    "sg:postcode":"11130",
    "sg:province":"C\u00e1diz",
    "wof:name":"Reyes Morales Miguel",
    "wof:placetype":"venue"
},
  "geometry": {"coordinates":[-6.1447038651,36.4212188721],"type":"Point"}
}