{
  "type": "Feature",
  "properties": {
    "addr:full":"Calle de Encrucijada, 35 Maracena Granada 18200",
    "addr:housenumber":"35",
    "addr:postcode":"18200",
    "addr:street":"Calle De Encrucijada",
    "iso:country":"ES",
    "sg:address":"Calle de Encrucijada, 35",
    "sg:city":"Maracena",
    "sg:orig_category":"Peluquer\u00cdas, Peluquer\u00cda Mixta",
    "sg:phone":"+34 958 41 24 61",
    "sg:postcode":"18200",
    "sg:province":"Granada",
    "wof:name":"Rodriguez Parejo Patricia",
    "wof:placetype":"venue"
},
  "geometry": {"coordinates":[-3.635915041,37.2061195374],"type":"Point"}
}