{
  "type": "Feature",
  "properties": {
    "addr:full":"Calle de Reyes Catolicos, 24 Moguer Huelva 21800",
    "addr:housenumber":"24",
    "addr:postcode":"21800",
    "addr:street":"Calle De Reyes Catolicos",
    "iso:country":"ES",
    "sg:address":"Calle de Reyes Catolicos, 24",
    "sg:city":"Moguer",
    "sg:orig_category":"Cajas De Ahorro",
    "sg:phone":"+34 959 37 34 02",
    "sg:postcode":"21800",
    "sg:province":"Huelva",
    "sg:website":"www.caja-granada.es",
    "wof:name":"Cajagranada",
    "wof:placetype":"venue"
},
  "geometry": {"coordinates":[-6.8371911049,37.2749404907],"type":"Point"}
}