{
  "type": "Feature",
  "properties": {
    "iso:country":"ES",
    "sg:address":"Avda Blas Infante, 5",
    "sg:city":"Arroyo De La Miel-benalmadena Costa",
    "sg:orig_category":"Cajas De Ahorro",
    "sg:phone":"+34 952 57 63 96",
    "sg:postcode":"29631",
    "sg:province":"M\u00e1laga",
    "wof:name":"Caja De Ahorros De Valencia Castellon Y Alicante",
    "wof:placetype":"venue"
},
  "geometry": {"coordinates":[-4.5351271629,36.5988807678],"type":"Point"}
}