{
  "type": "Feature",
  "properties": {
    "iso:country":"ES",
    "sg:address":"Avda Suel Urb Ajolin, 69",
    "sg:city":"Fuengirola",
    "sg:orig_category":"Restaurantes",
    "sg:phone":"+34 952 47 85 82",
    "sg:postcode":"29640",
    "sg:province":"M\u00e1laga",
    "wof:name":"Catering Pereas Rojas S.l",
    "wof:placetype":"venue"
},
  "geometry": {"coordinates":[-4.6330537796,36.5426368713],"type":"Point"}
}