{
  "type": "Feature",
  "properties": {
    "addr:full":"Calle de Ollerias, 4 Andujar Ja\u00e9n 23740",
    "addr:housenumber":"4",
    "addr:postcode":"23740",
    "addr:street":"Calle De Ollerias",
    "iso:country":"ES",
    "sg:address":"Calle de Ollerias, 4",
    "sg:city":"Andujar",
    "sg:orig_category":"Relojer\u00cda (al Por Menor, Reparaci\u00d3n)",
    "sg:phone":"+34 953 50 07 70",
    "sg:postcode":"23740",
    "sg:province":"Ja\u00e9n",
    "wof:name":"Ruiz Fonta Francisco",
    "wof:placetype":"venue"
},
  "geometry": {"coordinates":[-4.0523438454,38.0376586914],"type":"Point"}
}