{
  "type": "Feature",
  "properties": {
    "iso:country":"ES",
    "sg:address":"Estd Vigo, 16",
    "sg:city":"Redondela",
    "sg:orig_category":"Servicios Gsm",
    "sg:phone":"+34 986 40 81 09",
    "sg:postcode":"36800",
    "sg:province":"Pontevedra",
    "wof:name":"Comunicaciones Dacu\u00f1a Y Perez S.l.",
    "wof:placetype":"venue"
},
  "geometry": {"coordinates":[-8.6090641022,42.2820243835],"type":"Point"}
}