{
  "type": "Feature",
  "properties": {
    "addr:full":"Avda Aragon (de), 35 Teruel Teruel 44002",
    "addr:housenumber":"35",
    "addr:postcode":"44002",
    "addr:street":"Avda Aragon De",
    "iso:country":"ES",
    "sg:address":"Avda Aragon (de), 35",
    "sg:city":"Teruel",
    "sg:orig_category":"Supermercados Y Hipermercados",
    "sg:phone":"+34 978 61 13 25",
    "sg:postcode":"44002",
    "sg:province":"Teruel",
    "sg:website":"www.mercadona.es",
    "wof:name":"Mercadona S.a.",
    "wof:placetype":"venue"
},
  "geometry": {"coordinates":[-1.1057989597,40.3313484192],"type":"Point"}
}