{
  "type": "Feature",
  "properties": {
    "addr:full":"Avda Zumalakarregi, 51 Llodio \u00c1lava 01400",
    "addr:housenumber":"51",
    "addr:postcode":"01400",
    "addr:street":"Avda Zumalakarregi",
    "iso:country":"ES",
    "sg:address":"Avda Zumalakarregi, 51",
    "sg:city":"Llodio",
    "sg:orig_category":"Agencias De Viajes",
    "sg:phone":"+34 946 72 65 45",
    "sg:postcode":"01400",
    "sg:province":"\u00c1lava",
    "sg:website":"www.halconviajes.com",
    "wof:name":"Viajes Halcon S.a.",
    "wof:placetype":"venue"
},
  "geometry": {"coordinates":[-2.9650139809,43.1406707764],"type":"Point"}
}