{
  "type": "Feature",
  "properties": {
    "iso:country":"ES",
    "sg:address":"Las Marinas, 1",
    "sg:city":"Roquetas Mar",
    "sg:orig_category":"Molduras, Junquillos, Listones Y Molduras Perforadas",
    "sg:phone":"+34 950 32 03 39",
    "sg:postcode":"04740",
    "sg:province":"Almer\u00eda",
    "wof:name":"Lopez Pomares Trinidad",
    "wof:placetype":"venue"
},
  "geometry": {"coordinates":[-2.6318869591,36.7311515808],"type":"Point"}
}