{
  "type": "Feature",
  "properties": {
    "addr:full":"Calle de Camino Pinares Llanos, 9 Villaviciosa Odon Madrid 28670",
    "addr:housenumber":"9",
    "addr:postcode":"28670",
    "addr:street":"Calle De Camino Pinares Llanos;Odon",
    "iso:country":"ES",
    "sg:address":"Calle de Camino Pinares Llanos, 9",
    "sg:city":"Villaviciosa Odon",
    "sg:orig_category":"Electrodom\u00c9sticos (fabricaci\u00d3n, Al Por Mayor)",
    "sg:phone":"+34 916 16 60 21",
    "sg:postcode":"28670",
    "sg:province":"Madrid",
    "sg:website":"www.dometic.es",
    "wof:name":"Dometic S.l.",
    "wof:placetype":"venue"
},
  "geometry": {"coordinates":[-3.7003455162,40.4166908264],"type":"Point"}
}