{
  "type": "Feature",
  "properties": {
    "iso:country":"ES",
    "sg:address":"Calle de Alderete, 2",
    "sg:city":"Malaga",
    "sg:orig_category":"Droguer\u00cdas (al Por Menor)",
    "sg:phone":"+34 952 25 20 50",
    "sg:postcode":"29013",
    "sg:province":"M\u00e1laga",
    "wof:name":"Sanchez Vazquez Jose",
    "wof:placetype":"venue"
},
  "geometry": {"coordinates":[-4.4229307175,36.7272262573],"type":"Point"}
}