{
  "type": "Feature",
  "properties": {
    "addr:full":"Calle de Orixe, 48 Bilbao Vizcaya 48015",
    "addr:housenumber":"48",
    "addr:postcode":"48015",
    "addr:street":"Calle De Orixe",
    "iso:country":"ES",
    "sg:address":"Calle de Orixe, 48",
    "sg:city":"Bilbao",
    "sg:orig_category":"Farmacias",
    "sg:phone":"+34 944 02 76 31",
    "sg:postcode":"48015",
    "sg:province":"Vizcaya",
    "wof:name":"Juan Antonio Uriarte Goiricelaya",
    "wof:placetype":"venue"
},
  "geometry": {"coordinates":[-2.9602639675,43.2832565308],"type":"Point"}
}