{
  "type": "Feature",
  "properties": {
    "iso:country":"ES",
    "sg:address":"Calle de Postigo Bajo, 43",
    "sg:city":"Oviedo",
    "sg:orig_category":"Peluqueros: De Se\u00d1oras",
    "sg:phone":"+34 985 21 75 73",
    "sg:postcode":"33009",
    "sg:province":"Asturias",
    "wof:name":"Gonzalez Campomanes Guillermina",
    "wof:placetype":"venue"
},
  "geometry": {"coordinates":[-5.8395118713,43.362739563],"type":"Point"}
}