{
  "type": "Feature",
  "properties": {
    "addr:full":"Crri Gamarra, 9 Malaga M\u00e1laga 29010",
    "addr:housenumber":"9",
    "addr:postcode":"29010",
    "addr:street":"Gamarra;Ma\u0301Laga",
    "iso:country":"ES",
    "sg:address":"Crri Gamarra, 9",
    "sg:city":"Malaga",
    "sg:orig_category":"Comisarios",
    "sg:phone":"+34 952 30 07 84",
    "sg:postcode":"29010",
    "sg:province":"M\u00e1laga",
    "wof:name":"Aguinaleo Narvaez Fernando",
    "wof:placetype":"venue"
},
  "geometry": {"coordinates":[-4.5108861923,36.7505378723],"type":"Point"}
}