{
  "type": "Feature",
  "properties": {
    "iso:country":"ES",
    "sg:address":"Calle de Principe De Vergara, 257",
    "sg:city":"Madrid",
    "sg:orig_category":"Farmacias",
    "sg:phone":"+34 914 57 32 29",
    "sg:postcode":"28016",
    "sg:province":"Madrid",
    "wof:name":"Maga\u00f1a Carasa Fernando",
    "wof:placetype":"venue"
},
  "geometry": {"coordinates":[-3.6772561073,40.4563293457],"type":"Point"}
}