{
  "type": "Feature",
  "properties": {
    "addr:full":"Pase Canalejas, 21 Santander Cantabria 39004",
    "addr:housenumber":"21",
    "addr:postcode":"39004",
    "addr:street":"Canalejas",
    "iso:country":"ES",
    "sg:address":"Pase Canalejas, 21",
    "sg:city":"Santander",
    "sg:orig_category":"Extinci\u00d3n De Incendios: Material Y Suministros (fabricaci\u00d3n, Al Por Mayor)",
    "sg:phone":"+34 942 31 29 16",
    "sg:postcode":"39004",
    "sg:province":"Cantabria",
    "wof:name":"Extintores Cosmos S.l.",
    "wof:placetype":"venue"
},
  "geometry": {"coordinates":[-3.7928309441,43.4648323059],"type":"Point"}
}