{
  "type": "Feature",
  "properties": {
    "addr:full":"Ctra. Majadahonda, Km. 0001,8 Pozuelo Madrid 28223",
    "addr:postcode":"28223",
    "addr:street":"Ctra. Majadahonda Km. 0001,8",
    "iso:country":"ES",
    "sg:address":"Ctra. Majadahonda, Km. 0001,8",
    "sg:city":"Pozuelo",
    "sg:orig_category":"Restaurantes De Empresas Y Colectivos",
    "sg:phone":"+34 913 52 64 83",
    "sg:postcode":"28223",
    "sg:province":"Madrid",
    "wof:name":"Aramark S.l.",
    "wof:placetype":"venue"
},
  "geometry": {"coordinates":[-3.8271524906,40.4335632324],"type":"Point"}
}