{
  "type": "Feature",
  "properties": {
    "addr:full":"Calle de San Juan, 32 Malaga M\u00e1laga 29005",
    "addr:housenumber":"32",
    "addr:postcode":"29005",
    "addr:street":"Calle De San Juan;Ma\u0301Laga",
    "iso:country":"ES",
    "sg:address":"Calle de San Juan, 32",
    "sg:city":"Malaga",
    "sg:orig_category":"Perfumer\u00cda Y Cosm\u00c9tica (fabricaci\u00d3n, Al Por Mayor)",
    "sg:phone":"+34 952 22 95 81",
    "sg:postcode":"29005",
    "sg:province":"M\u00e1laga",
    "sg:website":"www.avon.es",
    "wof:name":"Avon Cosmetics S.a.",
    "wof:placetype":"venue"
},
  "geometry": {"coordinates":[-4.4235701561,36.7198410034],"type":"Point"}
}