{
  "type": "Feature",
  "properties": {
    "addr:full":"Avda Sagunto (de), 8 Teruel Teruel 44002",
    "addr:housenumber":"8",
    "addr:postcode":"44002",
    "addr:street":"Avda Sagunto De",
    "iso:country":"ES",
    "sg:address":"Avda Sagunto (de), 8",
    "sg:city":"Teruel",
    "sg:orig_category":"Fabricaci\u00d3n De Art\u00cdculos Para Papeler\u00cdas",
    "sg:phone":"+34 978 61 00 22",
    "sg:postcode":"44002",
    "sg:province":"Teruel",
    "wof:name":"Hernandez Sorando Maria Jose",
    "wof:placetype":"venue"
},
  "geometry": {"coordinates":[-1.1050209999,40.3365859985],"type":"Point"}
}