{
  "type": "Feature",
  "properties": {
    "iso:country":"ES",
    "sg:address":"Carr Guifre, 107",
    "sg:city":"Badalona",
    "sg:orig_category":"Cl\u00cdnicas Dentales",
    "sg:phone":"+34 933 83 49 42",
    "sg:postcode":"08912",
    "sg:province":"Barcelona",
    "wof:name":"Basso Pibernat Jorge",
    "wof:placetype":"venue"
},
  "geometry": {"coordinates":[2.243874073,41.4454650879],"type":"Point"}
}