{
  "type": "Feature",
  "properties": {
    "addr:full":"Avgd Catalunya, 10 Almafra Alicante 03610",
    "addr:housenumber":"10",
    "addr:postcode":"03610",
    "addr:street":"Almafra Alicante",
    "iso:country":"ES",
    "sg:address":"Avgd Catalunya, 10",
    "sg:city":"Almafra",
    "sg:orig_category":"Venta, Instalaci\u00d3n, Mantenimiento De Chimeneas De Interior Y Accesorios",
    "sg:phone":"+34 965 37 09 68",
    "sg:postcode":"03610",
    "sg:province":"Alicante",
    "wof:name":"Tabarnero Asuncion Hilario",
    "wof:placetype":"venue"
},
  "geometry": {"coordinates":[-0.7731289864,38.4793281555],"type":"Point"}
}