{
  "type": "Feature",
  "properties": {
    "iso:country":"ES",
    "sg:address":"Calle de Alameda, 22",
    "sg:city":"Illescas",
    "sg:orig_category":"Ropa Y Art\u00cdculos Pre",
    "sg:phone":"+34 925 51 20 69",
    "sg:postcode":"45200",
    "sg:province":"Toledo",
    "wof:name":"Garcia Aguirre Concepcion",
    "wof:placetype":"venue"
},
  "geometry": {"coordinates":[-3.8391604424,40.1160202026],"type":"Point"}
}