{
  "type": "Feature",
  "properties": {
    "addr:full":"Trva Plantas (de Las), 6 Algete Madrid 28110",
    "addr:housenumber":"6",
    "addr:postcode":"28110",
    "addr:street":"Trva Plantas De Las",
    "iso:country":"ES",
    "sg:address":"Trva Plantas (de Las), 6",
    "sg:city":"Algete",
    "sg:orig_category":"Mec\u00c1nica Y Herramientas De Precisi\u00d3n",
    "sg:phone":"+34 916 28 22 90",
    "sg:postcode":"28110",
    "sg:province":"Madrid",
    "wof:name":"Sociedad De Instrumentacion De Elementos Primarios S.l.",
    "wof:placetype":"venue"
},
  "geometry": {"coordinates":[-3.4994180202,40.5932273865],"type":"Point"}
}