{
  "type": "Feature",
  "properties": {
    "iso:country":"ES",
    "sg:address":"Carrer de Esteve Terradas, 43",
    "sg:city":"Manresa",
    "sg:orig_category":"Empresas De Carpinter\u00cda",
    "sg:phone":"+34 938 77 09 98",
    "sg:postcode":"08243",
    "sg:province":"Barcelona",
    "wof:name":"Aluminios San Salvador S.l.",
    "wof:placetype":"venue"
},
  "geometry": {"coordinates":[1.8482103348,41.7133903503],"type":"Point"}
}