{
  "type": "Feature",
  "properties": {
    "iso:country":"ES",
    "sg:address":"Avda Montecillo, 1",
    "sg:city":"Aranda Duero",
    "sg:orig_category":"Calderer\u00cda",
    "sg:phone":"+34 947 51 50 49",
    "sg:postcode":"09400",
    "sg:province":"Burgos",
    "wof:name":"Revinox Sll",
    "wof:placetype":"venue"
},
  "geometry": {"coordinates":[-3.7049489021,41.6720809937],"type":"Point"}
}