{
  "type": "Feature",
  "properties": {
    "iso:country":"ES",
    "sg:address":"Trva Naval (la), 6",
    "sg:city":"Reinosa",
    "sg:orig_category":"Carnicer\u00cdas, Carnicer\u00cdas",
    "sg:phone":"+34 942 75 37 19",
    "sg:postcode":"39200",
    "sg:province":"Cantabria",
    "wof:name":"Fuente Merino Carlos",
    "wof:placetype":"venue"
},
  "geometry": {"coordinates":[-4.1362051964,42.9986495972],"type":"Point"}
}