{
  "type": "Feature",
  "properties": {
    "iso:country":"ES",
    "sg:address":"Rua Republica De El Salvador (da), 10",
    "sg:city":"Santiago De Compostela",
    "sg:orig_category":"Servicios Gsm",
    "sg:phone":"+34 981 57 08 33",
    "sg:postcode":"15701",
    "sg:province":"A Coru\u00f1a",
    "wof:name":"Voz Datos Imagen Comunicaciones S.l.",
    "wof:placetype":"venue"
},
  "geometry": {"coordinates":[-8.5460176468,42.8745994568],"type":"Point"}
}