{
  "type": "Feature",
  "properties": {
    "addr:full":"Calle de Doctor Jose Ricarte, 65 San Bartolome Alicante 03314",
    "addr:housenumber":"65",
    "addr:postcode":"03314",
    "addr:street":"Calle De Doctor Jose Ricarte",
    "iso:country":"ES",
    "sg:address":"Calle de Doctor Jose Ricarte, 65",
    "sg:city":"San Bartolome",
    "sg:orig_category":"Sociedades, Compa\u00d1\u00cdas Aseguradoras",
    "sg:phone":"+34 966 77 60 44",
    "sg:postcode":"03314",
    "sg:province":"Alicante",
    "wof:name":"Martinez Tovar Asuncion",
    "wof:placetype":"venue"
},
  "geometry": {"coordinates":[-0.8609601855,38.0937194824],"type":"Point"}
}