{
  "type": "Feature",
  "properties": {
    "addr:full":"Ctra San Javier, Km. 0010,7 Beniajan Murcia 30570",
    "addr:postcode":"30570",
    "addr:street":"Ctra San Javier Km. 0010,7",
    "iso:country":"ES",
    "sg:address":"Ctra San Javier, Km. 0010,7",
    "sg:city":"Beniajan",
    "sg:orig_category":"Fabricaci\u00d3n Y Comercio De M\u00c1quinas",
    "sg:phone":"+34 968 82 43 30",
    "sg:postcode":"30570",
    "sg:province":"Murcia",
    "wof:name":"Joaquin Meseguer Vicente Y Otros S.l.",
    "wof:placetype":"venue"
},
  "geometry": {"coordinates":[-1.0651390553,37.9766197205],"type":"Point"}
}