{
  "type": "Feature",
  "properties": {
    "iso:country":"ES",
    "sg:address":"Calle de Joaquin Arroyo, 9",
    "sg:city":"Madrid",
    "sg:orig_category":"Asesor\u00cdas Y Estudios Financieros",
    "sg:phone":"+34 913 02 55 86",
    "sg:postcode":"28033",
    "sg:province":"Madrid",
    "wof:name":"Diez Pazos Pablo",
    "wof:placetype":"venue"
},
  "geometry": {"coordinates":[-3.6641581059,40.4684410095],"type":"Point"}
}