{
  "type": "Feature",
  "properties": {
    "iso:country":"ES",
    "sg:address":"Avda Nuestra Se\u00d1ora Del Pilar, 13",
    "sg:city":"Binefar",
    "sg:orig_category":"Supermercados Y Hipermercados",
    "sg:phone":"+34 974 43 02 75",
    "sg:postcode":"22500",
    "sg:province":"Huesca",
    "wof:name":"Pacita Complex S.l.",
    "wof:placetype":"venue"
},
  "geometry": {"coordinates":[0.2921670079,41.8518104553],"type":"Point"}
}