{
  "type": "Feature",
  "properties": {
    "iso:country":"ES",
    "sg:address":"Calle de Antonio Concha, 2",
    "sg:city":"Navalmoral Mata",
    "sg:orig_category":"Art\u00cdculos De Regalo (al Por Menor)",
    "sg:phone":"+34 927 53 30 01",
    "sg:postcode":"10300",
    "sg:province":"C\u00e1ceres",
    "wof:name":"Gonzalez Encina Maria Purificacion",
    "wof:placetype":"venue"
},
  "geometry": {"coordinates":[-5.5346736908,39.8902397156],"type":"Point"}
}