{
  "type": "Feature",
  "properties": {
    "iso:country":"ES",
    "sg:address":"Carrer de Pujades, 63",
    "sg:city":"Barcelona",
    "sg:orig_category":"Arquitectos",
    "sg:phone":"+34 934 85 54 94",
    "sg:postcode":"08005",
    "sg:province":"Barcelona",
    "wof:name":"Pep Bonet&associats",
    "wof:placetype":"venue"
},
  "geometry": {"coordinates":[2.1934859753,41.3964195251],"type":"Point"}
}