{
  "type": "Feature",
  "properties": {
    "addr:full":"Carrer de Sant Gabriel, 57 Arenys Mar Barcelona 08350",
    "addr:housenumber":"57",
    "addr:postcode":"08350",
    "addr:street":"Carrer De Sant Gabriel",
    "iso:country":"ES",
    "sg:address":"Carrer de Sant Gabriel, 57",
    "sg:city":"Arenys Mar",
    "sg:orig_category":"Confecci\u00d3n De Ropa Interior",
    "sg:phone":"+34 937 92 36 36",
    "sg:postcode":"08350",
    "sg:province":"Barcelona",
    "wof:name":"Maldonado Herrera Carmen",
    "wof:placetype":"venue"
},
  "geometry": {"coordinates":[2.548361063,41.5822410583],"type":"Point"}
}