{
  "type": "Feature",
  "properties": {
    "iso:country":"ES",
    "sg:address":"Avda Alonso Martin, 3",
    "sg:city":"Don Benito",
    "sg:orig_category":"Enfermeras: Consultas, Atenci\u00d3n A Domicilio",
    "sg:phone":"+34 924 80 48 04",
    "sg:postcode":"06400",
    "sg:province":"Badajoz",
    "wof:name":"Moya Rino Antonio",
    "wof:placetype":"venue"
},
  "geometry": {"coordinates":[-5.862842083,38.9613113403],"type":"Point"}
}