{
  "type": "Feature",
  "properties": {
    "iso:country":"ES",
    "sg:address":"Calle de Fuencarral, 137",
    "sg:city":"Madrid",
    "sg:orig_category":"Talleres: Ropa A Medida",
    "sg:phone":"+34 914 48 25 99",
    "sg:postcode":"28010",
    "sg:province":"Madrid",
    "wof:name":"Molina Lopez Ticiano",
    "wof:placetype":"venue"
},
  "geometry": {"coordinates":[-3.7038149834,40.4321899414],"type":"Point"}
}