{
  "type": "Feature",
  "properties": {
    "iso:country":"ES",
    "sg:address":"Rosalia De Castro, 24",
    "sg:city":"Padron",
    "sg:orig_category":"Bazares, Art\u00cdculos De Limpieza Y De Cocina (al Por Menor)",
    "sg:phone":"+34 981 81 21 70",
    "sg:postcode":"15900",
    "sg:province":"La Coru\u00f1a",
    "wof:name":"Cajaraville Cardama Purificacion Laura",
    "wof:placetype":"venue"
},
  "geometry": {"coordinates":[-8.6601362228,42.7393722534],"type":"Point"}
}