{
  "type": "Feature",
  "properties": {
    "iso:country":"ES",
    "sg:address":"Av Roma (de), 5",
    "sg:city":"Tarragona",
    "sg:orig_category":"Asesor\u00cda De Formaci\u00d3n Y Gesti\u00d3n De Personal",
    "sg:phone":"+34 977 24 55 27",
    "sg:postcode":"43005",
    "sg:province":"Tarragona",
    "wof:name":"Huguet Alsina Jose",
    "wof:placetype":"venue"
},
  "geometry": {"coordinates":[1.2432899475,41.118938446],"type":"Point"}
}