{
  "type": "Feature",
  "properties": {
    "iso:country":"ES",
    "sg:address":"Carrer de Cigne, 13",
    "sg:city":"Palma",
    "sg:orig_category":"Cristaler\u00cdas",
    "sg:phone":"+34 971 46 30 35",
    "sg:postcode":"07006",
    "sg:province":"Islas Baleares",
    "wof:name":"Luis Cuesta Gaitan",
    "wof:placetype":"venue"
},
  "geometry": {"coordinates":[2.6618030071,39.5661659241],"type":"Point"}
}