{
  "type": "Feature",
  "properties": {
    "iso:country":"ES",
    "sg:address":"Rua Juan De Austria, 6",
    "sg:city":"Ferrol",
    "sg:orig_category":"Peluqueros: De Se\u00d1oras",
    "sg:phone":"+34 981 37 16 40",
    "sg:postcode":"15406",
    "sg:province":"La Coru\u00f1a",
    "wof:name":"Fraga Polo Maria Luz",
    "wof:placetype":"venue"
},
  "geometry": {"coordinates":[-8.2065286636,43.4860305786],"type":"Point"}
}