{
  "type": "Feature",
  "properties": {
    "addr:full":"Calle de General Pardi\u00d1as, 28 Madrid Madrid 28001",
    "addr:housenumber":"28",
    "addr:postcode":"madrid;28001",
    "addr:street":"Calle De General Pardin\u0303As",
    "iso:country":"ES",
    "sg:address":"Calle de General Pardi\u00d1as, 28",
    "sg:city":"Madrid",
    "sg:orig_category":"Fabricaci\u00d3n De Muebles",
    "sg:phone":"+34 914 31 12 14",
    "sg:postcode":"28001",
    "sg:province":"Madrid",
    "wof:name":"Jimenez Charro Maria Del Carmen",
    "wof:placetype":"venue"
},
  "geometry": {"coordinates":[-3.6785600185,40.4259719849],"type":"Point"}
}