{
  "type": "Feature",
  "properties": {
    "addr:full":"Carrer de Francoli, 28 Barcelona Barcelona 08006",
    "addr:housenumber":"28",
    "addr:postcode":"08006",
    "addr:street":"Carrer De Francoli",
    "iso:country":"ES",
    "sg:address":"Carrer de Francoli, 28",
    "sg:city":"Barcelona",
    "sg:orig_category":"Peluquer\u00cdas, Peluquer\u00cda Mixta",
    "sg:phone":"+34 932 17 69 67",
    "sg:postcode":"08006",
    "sg:province":"Barcelona",
    "wof:name":"Martin Martin Pilar",
    "wof:placetype":"venue"
},
  "geometry": {"coordinates":[2.1471779346,41.4043121338],"type":"Point"}
}