{
  "type": "Feature",
  "properties": {
    "iso:country":"ES",
    "sg:address":"Carrer de Jordi Camp, 113",
    "sg:city":"Granollers",
    "sg:orig_category":"Agentes, Concesionarios Y Sucursales De Veh\u00cdculos",
    "sg:phone":"+34 938 61 69 99",
    "sg:postcode":"08403",
    "sg:province":"Barcelona",
    "sg:website":"www.vilavila.redsaab.com",
    "wof:name":"Comercial Vila Vila S. A.",
    "wof:placetype":"venue"
},
  "geometry": {"coordinates":[2.2769498825,41.6016693115],"type":"Point"}
}