{
  "type": "Feature",
  "properties": {
    "addr:full":"Calle de Caballero, 4 Carmen Murcia 30002",
    "addr:housenumber":"4",
    "addr:postcode":"30002",
    "addr:street":"Calle De Caballero",
    "iso:country":"ES",
    "sg:address":"Calle de Caballero, 4",
    "sg:city":"Carmen",
    "sg:orig_category":"Electricidad: Instaladores",
    "sg:phone":"+34 968 25 32 11",
    "sg:postcode":"30002",
    "sg:province":"Murcia",
    "wof:name":"Anzora Instalaciones Electricas S.l.",
    "wof:placetype":"venue"
},
  "geometry": {"coordinates":[-1.1298867464,37.9834747314],"type":"Point"}
}