{
  "type": "Feature",
  "properties": {
    "iso:country":"ES",
    "sg:address":"Plaz Marques De Salamanca, 11",
    "sg:city":"Madrid",
    "sg:orig_category":"Asesor\u00cda Sobre Comunicaci\u00d3n De Empresas",
    "sg:phone":"+34 915 76 50 25",
    "sg:postcode":"28006",
    "sg:province":"Madrid",
    "wof:name":"Aguirregomezcorta Semprun Fernando",
    "wof:placetype":"venue"
},
  "geometry": {"coordinates":[-3.6795992851,40.4297332764],"type":"Point"}
}