{
  "type": "Feature",
  "properties": {
    "iso:country":"ES",
    "sg:address":"Calle de Leopoldo Romeo, 22",
    "sg:city":"Zaragoza",
    "sg:orig_category":"Muebles Y Accesorios Para Cocinas Y Cuartos De Ba\u00d1o (al Por Menor)",
    "sg:phone":"+34 976 59 94 00",
    "sg:postcode":"50002",
    "sg:province":"Zaragoza",
    "sg:website":"www.latiendadejuan.com",
    "wof:name":"Mundo Singular S.l.",
    "wof:placetype":"venue"
},
  "geometry": {"coordinates":[-0.8639889956,41.6468200684],"type":"Point"}
}