{
  "type": "Feature",
  "properties": {
    "iso:country":"ES",
    "sg:address":"Calle de Ortega Y Mu\u00d1oz, 32",
    "sg:city":"Almendralejo",
    "sg:orig_category":"Internados & Ense\u00d1anza Privada",
    "sg:phone":"+34 924 66 16 89",
    "sg:postcode":"06200",
    "sg:province":"Badajoz",
    "wof:name":"Agrupacion De Servicios Santa Ana S.l.",
    "wof:placetype":"venue"
},
  "geometry": {"coordinates":[-6.3944048882,38.6767539978],"type":"Point"}
}