{
  "type": "Feature",
  "properties": {
    "addr:full":"Rua Paz, 10 Vigo Pontevedra 36202",
    "addr:housenumber":"10",
    "addr:postcode":"36202",
    "addr:street":"Rua Paz",
    "iso:country":"ES",
    "sg:address":"Rua Paz, 10",
    "sg:city":"Vigo",
    "sg:orig_category":"Periodistas Profesionales",
    "sg:phone":"+34 986 29 51 77",
    "sg:postcode":"36202",
    "sg:province":"Pontevedra",
    "wof:name":"Ramos Fernandez Luis Fernando",
    "wof:placetype":"venue"
},
  "geometry": {"coordinates":[-8.7344923019,42.2279930115],"type":"Point"}
}