{
  "type": "Feature",
  "properties": {
    "iso:country":"ES",
    "sg:address":"Calle de Nerbioi, 3",
    "sg:city":"Bilbao",
    "sg:orig_category":"Locales Y Clases De Danza",
    "sg:phone":"+34 944 23 02 99",
    "sg:postcode":"48001",
    "sg:province":"Vizcaya",
    "sg:website":"www.bilbaobaila.com",
    "wof:name":"Ines Uriarte-i\u00f1igo Fidalgo C.b.",
    "wof:placetype":"venue"
},
  "geometry": {"coordinates":[-2.9461190701,43.2686500549],"type":"Point"}
}