{
  "type": "Feature",
  "properties": {
    "iso:country":"ES",
    "sg:address":"Cno. Sarratella, S/n",
    "sg:city":"Poblados Maritimos",
    "sg:orig_category":"Aguas (distribuci\u00d3n, Servicios)",
    "sg:phone":"+34 964 58 62 17",
    "sg:postcode":"12530",
    "sg:province":"Castell\u00f3n",
    "wof:name":"Sociedad De Fomento Agricola Castellonense S.a.",
    "wof:placetype":"venue"
},
  "geometry": {"coordinates":[-0.0852660015,39.8894195557],"type":"Point"}
}