{
  "type": "Feature",
  "properties": {
    "addr:full":"Ctra Malaga (de), 90 Granada Granada 18015",
    "addr:housenumber":"90",
    "addr:postcode":"18015",
    "addr:street":"Ctra Malaga De",
    "iso:country":"ES",
    "sg:address":"Ctra Malaga (de), 90",
    "sg:city":"Granada",
    "sg:orig_category":"Mercer\u00cda, Lencer\u00cda (al Por Menor)",
    "sg:phone":"+34 958 27 45 30",
    "sg:postcode":"18015",
    "sg:province":"Granada",
    "wof:name":"Rodriguez Lopez Maria Del Carmen",
    "wof:placetype":"venue"
},
  "geometry": {"coordinates":[-3.6263709068,37.1894989014],"type":"Point"}
}