{
  "type": "Feature",
  "properties": {
    "addr:full":"Calle de Ventura Rodriguez, 6 Oviedo Asturias 33004",
    "addr:housenumber":"6",
    "addr:postcode":"33004",
    "addr:street":"Calle De Ventura Rodriguez",
    "iso:country":"ES",
    "sg:address":"Calle de Ventura Rodriguez, 6",
    "sg:city":"Oviedo",
    "sg:orig_category":"Art\u00cdculos De Decoraci\u00d3n",
    "sg:phone":"+34 985 23 11 83",
    "sg:postcode":"33004",
    "sg:province":"Asturias",
    "wof:name":"Rodriguez Fanjul Eva",
    "wof:placetype":"venue"
},
  "geometry": {"coordinates":[-5.8540468216,43.3640937805],"type":"Point"}
}