{
  "type": "Feature",
  "properties": {
    "addr:full":"Calle de Jose Pereyra Galviaty, 76 Arrecife Las Palmas 35500",
    "addr:housenumber":"76",
    "addr:postcode":"35500",
    "addr:street":"Calle De Jose;Galviaty",
    "iso:country":"ES",
    "sg:address":"Calle de Jose Pereyra Galviaty, 76",
    "sg:city":"Arrecife",
    "sg:orig_category":"Alimentaci\u00d3n General (al Por Menor)",
    "sg:phone":"+34 928 81 14 52",
    "sg:postcode":"35500",
    "sg:province":"Las Palmas",
    "wof:name":"Gonzalez Diaz Rafael",
    "wof:placetype":"venue"
},
  "geometry": {"coordinates":[-13.5553092957,28.9704265594],"type":"Point"}
}