{
  "type": "Feature",
  "properties": {
    "iso:country":"ES",
    "sg:address":"Calle de Jose Pereyra Galviaty, 76",
    "sg:city":"Arrecife",
    "sg:orig_category":"Alimentaci\u00d3n General (al Por Menor)",
    "sg:phone":"+34 928 81 14 52",
    "sg:postcode":"35500",
    "sg:province":"Las Palmas",
    "wof:name":"Gonzalez Diaz Rafael",
    "wof:placetype":"venue"
},
  "geometry": {"coordinates":[-13.5553092957,28.9704265594],"type":"Point"}
}