{
  "type": "Feature",
  "properties": {
    "addr:full":"Rua X, 2 Lalin Pontevedra 36500",
    "addr:postcode":"36500",
    "iso:country":"ES",
    "sg:address":"Rua X, 2",
    "sg:city":"Lalin",
    "sg:orig_category":"Cl\u00cdnicas Dentales",
    "sg:phone":"+34 986 78 21 43",
    "sg:postcode":"36500",
    "sg:province":"Pontevedra",
    "wof:name":"Clinident Lalin S.l.l",
    "wof:placetype":"venue"
},
  "geometry": {"coordinates":[-8.1118192673,42.660736084],"type":"Point"}
}