{
  "type": "Feature",
  "properties": {
    "iso:country":"ES",
    "sg:address":"C/ Santa Marcel.lina, S/n",
    "sg:city":"Cerdanyola Valles",
    "sg:orig_category":"Supermercados Y Hipermercados",
    "sg:phone":"+34 935 94 00 68",
    "sg:postcode":"08290",
    "sg:province":"Barcelona",
    "wof:name":"Bon-preu S.a.",
    "wof:placetype":"venue"
},
  "geometry": {"coordinates":[2.1372699738,41.4915390015],"type":"Point"}
}