{
  "type": "Feature",
  "properties": {
    "addr:full":"Calle de Nueva, 4 Toledo Toledo 45001",
    "addr:housenumber":"4",
    "addr:postcode":"45001",
    "addr:street":"Calle De Nueva",
    "iso:country":"ES",
    "sg:address":"Calle de Nueva, 4",
    "sg:city":"Toledo",
    "sg:orig_category":"Asesor\u00cdas Y Estudios Financieros",
    "sg:phone":"+34 925 25 25 39",
    "sg:postcode":"45001",
    "sg:province":"Toledo",
    "wof:name":"Fernandez Jaime Alejandro",
    "wof:placetype":"venue"
},
  "geometry": {"coordinates":[-4.0223112106,39.8594665527],"type":"Point"}
}