{
  "type": "Feature",
  "properties": {
    "iso:country":"ES",
    "sg:address":"Grande, 2",
    "sg:city":"Tronceda",
    "sg:orig_category":"Farmacias",
    "sg:phone":"+34 988 20 31 50",
    "sg:postcode":"32766",
    "sg:province":"Ourense",
    "wof:name":"Gonzalez Movilla Claudio Jose",
    "wof:placetype":"venue"
},
  "geometry": {"coordinates":[-7.3470921516,42.384059906],"type":"Point"}
}