{
  "type": "Feature",
  "properties": {
    "addr:full":"Partida La Cenia, S/n Riudoms Tarragona 43330",
    "addr:housenumber":"s / n",
    "addr:postcode":"43330",
    "addr:street":"Partida La Cenia",
    "iso:country":"ES",
    "sg:address":"Partida La Cenia, S/n",
    "sg:city":"Riudoms",
    "sg:orig_category":"Fabricaci\u00d3n De Moldes Y Modelos",
    "sg:phone":"+34 977 85 06 92",
    "sg:postcode":"43330",
    "sg:province":"Tarragona",
    "wof:name":"Matricerias Montblanc S.a.",
    "wof:placetype":"venue"
},
  "geometry": {"coordinates":[1.0541909933,41.1382713318],"type":"Point"}
}