{
  "type": "Feature",
  "properties": {
    "addr:full":"Avda Vi\u00d1alta, 13 Palencia Palencia 34005",
    "addr:housenumber":"13",
    "addr:postcode":"34005",
    "addr:street":"Avda Vin\u0303Alta",
    "iso:country":"ES",
    "sg:address":"Avda Vi\u00d1alta, 13",
    "sg:city":"Palencia",
    "sg:orig_category":"Zapater\u00cdas",
    "sg:phone":"+34 979 70 10 08",
    "sg:postcode":"34005",
    "sg:province":"Palencia",
    "wof:name":"Medrano Ortiz Nuria",
    "wof:placetype":"venue"
},
  "geometry": {"coordinates":[-4.5420379639,42.0076713562],"type":"Point"}
}