{
  "type": "Feature",
  "properties": {
    "addr:full":"Covadonga, 62 Infiesto Asturias 33530",
    "addr:housenumber":"62",
    "addr:postcode":"33530",
    "addr:street":"Covadonga",
    "iso:country":"ES",
    "sg:address":"Covadonga, 62",
    "sg:city":"Infiesto",
    "sg:orig_category":"Electrodom\u00c9sticos (al Por Menor)",
    "sg:phone":"+34 985 71 05 49",
    "sg:postcode":"33530",
    "sg:province":"Asturias",
    "wof:name":"Espina Llano Jose Manuel",
    "wof:placetype":"venue"
},
  "geometry": {"coordinates":[-5.3648190498,43.3494110107],"type":"Point"}
}