{
  "type": "Feature",
  "properties": {
    "iso:country":"ES",
    "sg:address":"Avda Principe De Espa\u00d1a, 26",
    "sg:city":"Alovera",
    "sg:orig_category":"Contenedores (mercanc\u00cdas)",
    "sg:phone":"+34 949 27 02 74",
    "sg:postcode":"19208",
    "sg:province":"Guadalajara",
    "wof:name":"Garcia Gil Jesus",
    "wof:placetype":"venue"
},
  "geometry": {"coordinates":[-3.2441461086,40.5952606201],"type":"Point"}
}