{
  "type": "Feature",
  "properties": {
    "addr:full":"Avda Talgo, 204 Madrid Madrid 28023",
    "addr:housenumber":"204",
    "addr:postcode":"28023",
    "addr:street":"Avda Talgo",
    "iso:country":"ES",
    "sg:address":"Avda Talgo, 204",
    "sg:city":"Madrid",
    "sg:orig_category":"Peluquer\u00cdas, Peluquer\u00cda Mixta",
    "sg:phone":"+34 913 57 12 70",
    "sg:postcode":"28023",
    "sg:province":"Madrid",
    "sg:website":"www.marcoaldany.com",
    "wof:name":"Fernandez Cu\u00d1a Vanesa",
    "wof:placetype":"venue"
},
  "geometry": {"coordinates":[-3.783798933,40.4475746155],"type":"Point"}
}