{
  "type": "Feature",
  "properties": {
    "iso:country":"ES",
    "sg:address":"Carrer de Alegria, 27",
    "sg:city":"Hospitalet Llobregat",
    "sg:orig_category":"Tapicer\u00cdas",
    "sg:phone":"+34 934 40 78 33",
    "sg:postcode":"08905",
    "sg:province":"Barcelona",
    "wof:name":"Vera Castilla Francesc",
    "wof:placetype":"venue"
},
  "geometry": {"coordinates":[2.1137039661,41.3700065613],"type":"Point"}
}