{
  "type": "Feature",
  "properties": {
    "addr:full":"Avda Industria (de La), 62 Humanes De Madrid Madrid 28970",
    "addr:housenumber":"62",
    "addr:postcode":"28970",
    "addr:street":"Avda Industria De La",
    "iso:country":"ES",
    "sg:address":"Avda Industria (de La), 62",
    "sg:city":"Humanes De Madrid",
    "sg:orig_category":"Muebles, Minoristas",
    "sg:phone":"+34 916 97 24 11",
    "sg:postcode":"28970",
    "sg:province":"Madrid",
    "wof:name":"Muebles Salinero S.a.",
    "wof:placetype":"venue"
},
  "geometry": {"coordinates":[-3.8392159939,40.2654380798],"type":"Point"}
}