{
  "type": "Feature",
  "properties": {
    "addr:full":"Carrer de Carretera De Barcelona, 49 S. Andreu Barca Barcelona 08740",
    "addr:housenumber":"49",
    "addr:postcode":"08740",
    "addr:street":"Carrer De Carretera De Barcelona;S. Andreu;Barcelona",
    "iso:country":"ES",
    "sg:address":"Carrer de Carretera De Barcelona, 49",
    "sg:city":"S. Andreu Barca",
    "sg:orig_category":"Empresas De Carpinter\u00cda De Madera",
    "sg:phone":"+34 936 53 19 15",
    "sg:postcode":"08740",
    "sg:province":"Barcelona",
    "wof:name":"Estor Martinez Pedro",
    "wof:placetype":"venue"
},
  "geometry": {"coordinates":[1.973369956,41.4486236572],"type":"Point"}
}