{
  "type": "Feature",
  "properties": {
    "iso:country":"ES",
    "sg:address":"Moreo, 1",
    "sg:city":"Moreo",
    "sg:orig_category":"Empresas De Carpinter\u00cda Met\u00c1lica",
    "sg:phone":"+34 985 98 54 98",
    "sg:postcode":"33199",
    "sg:province":"Asturias",
    "wof:name":"Alcala Carpinteria Metalica S.l.",
    "wof:placetype":"venue"
},
  "geometry": {"coordinates":[-5.9832577705,43.2504386902],"type":"Point"}
}