{
  "type": "Feature",
  "properties": {
    "iso:country":"ES",
    "sg:address":"Calle de Cristobal Colon, 5",
    "sg:city":"Pozoblanco",
    "sg:orig_category":"Asesor\u00cda Sobre Comunicaci\u00d3n De Empresas",
    "sg:phone":"+34 957 77 02 09",
    "sg:postcode":"14400",
    "sg:province":"C\u00f3rdoba",
    "wof:name":"Roberto Fuertes Y Juan Alfonso Garcia S.l.",
    "wof:placetype":"venue"
},
  "geometry": {"coordinates":[-4.8514027596,38.3831176758],"type":"Point"}
}