{
  "type": "Feature",
  "properties": {
    "addr:full":"Avda Extremadura, 155 Santa Marta Badajoz 06150",
    "addr:housenumber":"155",
    "addr:postcode":"06150",
    "addr:street":"Avda Extremadura",
    "iso:country":"ES",
    "sg:address":"Avda Extremadura, 155",
    "sg:city":"Santa Marta",
    "sg:orig_category":"Chapister\u00cda",
    "sg:phone":"+34 924 68 13 17",
    "sg:postcode":"06150",
    "sg:province":"Badajoz",
    "wof:name":"Romero Corrales Justo",
    "wof:placetype":"venue"
},
  "geometry": {"coordinates":[-6.6212978363,38.6202507019],"type":"Point"}
}