{
  "type": "Feature",
  "properties": {
    "addr:full":"Carrer de Barcelona, 25 Granollers Barcelona 08401",
    "addr:housenumber":"25",
    "addr:postcode":"08401",
    "addr:street":"Carrer De Barcelona",
    "iso:country":"ES",
    "sg:address":"Carrer de Barcelona, 25",
    "sg:city":"Granollers",
    "sg:orig_category":"Juegos Y Juguetes (al Por Menor)",
    "sg:phone":"+34 938 70 90 09",
    "sg:postcode":"08401",
    "sg:province":"Barcelona",
    "wof:name":"Marti Galimany Rosina",
    "wof:placetype":"venue"
},
  "geometry": {"coordinates":[2.287142992,41.6070098877],"type":"Point"}
}