{
  "type": "Feature",
  "properties": {
    "addr:full":"Rbla Egara, 311 Terrassa Barcelona 08224",
    "addr:housenumber":"311",
    "addr:postcode":"08224",
    "addr:street":"Rbla Egara",
    "iso:country":"ES",
    "sg:address":"Rbla Egara, 311",
    "sg:city":"Terrassa",
    "sg:orig_category":"Sociedades, Compa\u00d1\u00cdas Aseguradoras",
    "sg:phone":"+34 937 33 66 90",
    "sg:postcode":"08224",
    "sg:province":"Barcelona",
    "wof:name":"La Previsora Bilbaina Compaa De Seguros S.a.",
    "wof:placetype":"venue"
},
  "geometry": {"coordinates":[2.0056340694,41.5672111511],"type":"Point"}
}