{
  "type": "Feature",
  "properties": {
    "addr:full":"Carr Tramuntana, S/n Badalona Barcelona 08915",
    "addr:postcode":"08915",
    "addr:street":"Carr Tramuntana S / N",
    "iso:country":"ES",
    "sg:address":"Carr Tramuntana, S/n",
    "sg:city":"Badalona",
    "sg:orig_category":"Promotores Constructores",
    "sg:phone":"+34 934 65 23 82",
    "sg:postcode":"08915",
    "sg:province":"Barcelona",
    "wof:name":"Comunidad De Propietarios Plaza De Sant Carlos De Nicaragua 4",
    "wof:placetype":"venue"
},
  "geometry": {"coordinates":[2.2501969337,41.4638252258],"type":"Point"}
}