{
  "type": "Feature",
  "properties": {
    "iso:country":"ES",
    "sg:address":"Calle de Urdaneta, 20",
    "sg:city":"Donostia-san Sebastian",
    "sg:orig_category":"Institutos De Belleza",
    "sg:phone":"+34 943 47 12 25",
    "sg:postcode":"20006",
    "sg:province":"Guip\u00f9zcoa",
    "wof:name":"Eizaguirre Uranga Lourdes",
    "wof:placetype":"venue"
},
  "geometry": {"coordinates":[-1.9826569557,43.31590271],"type":"Point"}
}