{
  "type": "Feature",
  "properties": {
    "addr:full":"Av Albudor, 13 Silla Valencia 46460",
    "addr:housenumber":"13",
    "addr:postcode":"46460",
    "addr:street":"Av Albudor",
    "iso:country":"ES",
    "sg:address":"Av Albudor, 13",
    "sg:city":"Silla",
    "sg:orig_category":"Negocio De Materiales De Construcci\u00d3n",
    "sg:phone":"+34 961 20 04 74",
    "sg:postcode":"46460",
    "sg:province":"Valencia",
    "wof:name":"Palau E Hijos S.l.",
    "wof:placetype":"venue"
},
  "geometry": {"coordinates":[-0.41593799,39.3520202637],"type":"Point"}
}