{
  "type": "Feature",
  "properties": {
    "iso:country":"ES",
    "sg:address":"Calle de Amapolas, 8",
    "sg:city":"Madrid",
    "sg:orig_category":"Abogados",
    "sg:phone":"+34 915 34 88 66",
    "sg:postcode":"28003",
    "sg:province":"Madrid",
    "wof:name":"Pastor Lopez Rafael Mariano",
    "wof:placetype":"venue"
},
  "geometry": {"coordinates":[-3.7161118984,40.4437408447],"type":"Point"}
}