{
  "type": "Feature",
  "properties": {
    "addr:full":"Bimbial-valdeflores, 13 Viveiro Lugo 27850",
    "addr:housenumber":"13",
    "addr:postcode":"27850",
    "addr:street":"Bimbial-Valdeflores",
    "iso:country":"ES",
    "sg:address":"Bimbial-valdeflores, 13",
    "sg:city":"Viveiro",
    "sg:orig_category":"Caf\u00c9s, Bares, Cervecer\u00cdas",
    "sg:phone":"+34 982 55 02 56",
    "sg:postcode":"27850",
    "sg:province":"Lugo",
    "wof:name":"Galtelcom",
    "wof:placetype":"venue"
},
  "geometry": {"coordinates":[-7.5959348679,43.6629714966],"type":"Point"}
}