{
  "type": "Feature",
  "properties": {
    "addr:full":"Carrer de Andres Segovia, 2 Palma Islas Baleares 07004",
    "addr:housenumber":"2",
    "addr:postcode":"07004",
    "addr:street":"Carrer De Andres Segovia",
    "iso:country":"ES",
    "sg:address":"Carrer de Andres Segovia, 2",
    "sg:city":"Palma",
    "sg:orig_category":"Suministros Para Hoteles",
    "sg:phone":"+34 971 29 54 58",
    "sg:postcode":"07004",
    "sg:province":"Islas Baleares",
    "wof:name":"Barcelona M. Frau S.a.",
    "wof:placetype":"venue"
},
  "geometry": {"coordinates":[2.6645710468,39.5841445923],"type":"Point"}
}