{
  "type": "Feature",
  "properties": {
    "iso:country":"ES",
    "sg:address":"Carrer de Doctor Josep Castells, 32",
    "sg:city":"S. Boi Llobregat",
    "sg:orig_category":"Fabricaci\u00d3n De Moldes Y Modelos",
    "sg:phone":"+34 936 30 53 64",
    "sg:postcode":"08830",
    "sg:province":"Barcelona",
    "wof:name":"Plasticos Del Baix Llobregat S.l.",
    "wof:placetype":"venue"
},
  "geometry": {"coordinates":[2.034733057,41.3272666931],"type":"Point"}
}