{
  "type": "Feature",
  "properties": {
    "iso:country":"ES",
    "sg:address":"Carr Francesc Ciurana, 8",
    "sg:city":"Girona",
    "sg:orig_category":"Electrodom\u00c9sticos (fabricaci\u00d3n, Al Por Mayor)",
    "sg:phone":"+34 972 21 32 00",
    "sg:postcode":"17002",
    "sg:province":"Girona",
    "sg:website":"www.expert.es",
    "wof:name":"Unec S.a.",
    "wof:placetype":"venue"
},
  "geometry": {"coordinates":[2.8187320232,41.9773254395],"type":"Point"}
}