{
  "type": "Feature",
  "properties": {
    "iso:country":"ES",
    "sg:address":"Carrer de Comte D'urgell, 169",
    "sg:city":"Barcelona",
    "sg:orig_category":"Cueros Y Pieles (al Por Mayor)",
    "sg:phone":"+34 934 53 78 12",
    "sg:postcode":"08036",
    "sg:province":"Barcelona",
    "wof:name":"Benetfurs S.a.",
    "wof:placetype":"venue"
},
  "geometry": {"coordinates":[2.1507000923,41.3880577087],"type":"Point"}
}