{
  "type": "Feature",
  "properties": {
    "iso:country":"ES",
    "sg:address":"C/ Victor Catala, 47",
    "sg:city":"Cerdanyola Valles",
    "sg:orig_category":"Autob\u00das (explotaci\u00d3n Y Servicios De)",
    "sg:phone":"+34 936 92 14 82",
    "sg:postcode":"08290",
    "sg:province":"Barcelona",
    "wof:name":"Carbonell Troses Jaime",
    "wof:placetype":"venue"
},
  "geometry": {"coordinates":[2.1312720776,41.4794960022],"type":"Point"}
}