{
  "type": "Feature",
  "properties": {
    "iso:country":"ES",
    "sg:address":"Calle de San Pedro, 19",
    "sg:city":"Albocasser",
    "sg:orig_category":"Cerrajer\u00cda, Ferrallista",
    "sg:phone":"+34 964 42 81 04",
    "sg:postcode":"12140",
    "sg:province":"Castell\u00f3n",
    "wof:name":"Boix Prades Hector",
    "wof:placetype":"venue"
},
  "geometry": {"coordinates":[0.0257799998,40.3567008972],"type":"Point"}
}