{
  "type": "Feature",
  "properties": {
    "addr:full":"Pase Florida, 35 Madrid Madrid 28008",
    "addr:housenumber":"35",
    "addr:postcode":"madrid;28008",
    "addr:street":"Florida",
    "iso:country":"ES",
    "sg:address":"Pase Florida, 35",
    "sg:city":"Madrid",
    "sg:orig_category":"Caf\u00c9s, Bares, Cervecer\u00cdas",
    "sg:phone":"+34 915 42 34 61",
    "sg:postcode":"28008",
    "sg:province":"Madrid",
    "wof:name":"Horno San Antonio S.l.",
    "wof:placetype":"venue"
},
  "geometry": {"coordinates":[-3.7231318951,40.422744751],"type":"Point"}
}