{
  "type": "Feature",
  "properties": {
    "addr:full":"Calle de Mangada, 18 Moraleja Enmedio Madrid 28950",
    "addr:housenumber":"18",
    "addr:postcode":"28950",
    "addr:street":"Calle De Mangada",
    "iso:country":"ES",
    "sg:address":"Calle de Mangada, 18",
    "sg:city":"Moraleja Enmedio",
    "sg:orig_category":"Empresas De Carpinter\u00cda De Madera",
    "sg:phone":"+34 916 09 32 17",
    "sg:postcode":"28950",
    "sg:province":"Madrid",
    "wof:name":"Leoncio Corrales Lopez S.l.",
    "wof:placetype":"venue"
},
  "geometry": {"coordinates":[-3.8495590687,40.2661209106],"type":"Point"}
}