{
  "type": "Feature",
  "properties": {
    "iso:country":"ES",
    "sg:address":"Calle de Juan De Lanuza, 14",
    "sg:city":"Caspe",
    "sg:orig_category":"Limpieza Con Chorro De Arena Y Con Granalla, Pulido",
    "sg:phone":"+34 976 63 22 49",
    "sg:postcode":"50700",
    "sg:province":"Zaragoza",
    "wof:name":"Fort Hernandez Fernando",
    "wof:placetype":"venue"
},
  "geometry": {"coordinates":[-0.0457389988,41.2339515686],"type":"Point"}
}