{
  "type": "Feature",
  "properties": {
    "addr:full":"Calle de Orobal, S/n Camella Santa Cruz De Tenerife 38627",
    "addr:housenumber":"s / n",
    "addr:postcode":"38627",
    "addr:street":"Calle De Orobal",
    "iso:country":"ES",
    "sg:address":"Calle de Orobal, S/n",
    "sg:city":"Camella",
    "sg:orig_category":"Restaurantes",
    "sg:phone":"+34 922 72 04 86",
    "sg:postcode":"38627",
    "sg:province":"Santa Cruz De Tenerife",
    "wof:name":"Velazquez Padilla Jose Manuel",
    "wof:placetype":"venue"
},
  "geometry": {"coordinates":[-16.681842804,28.0780220032],"type":"Point"}
}