{
  "type": "Feature",
  "properties": {
    "addr:full":"Carrer de Almassora, 9 Barcelona Barcelona 08033",
    "addr:housenumber":"9",
    "addr:postcode":"08033",
    "addr:street":"Carrer De Almassora",
    "iso:country":"ES",
    "sg:address":"Carrer de Almassora, 9",
    "sg:city":"Barcelona",
    "sg:orig_category":"Bricolaje, Herramientas (al Por Menor)",
    "sg:phone":"+34 933 46 83 57",
    "sg:postcode":"08033",
    "sg:province":"Barcelona",
    "wof:name":"Jimenez Priego Carlos",
    "wof:placetype":"venue"
},
  "geometry": {"coordinates":[2.1895749569,41.4515075684],"type":"Point"}
}