{
  "type": "Feature",
  "properties": {
    "iso:country":"ES",
    "sg:address":"Carr Manuel Fdez Marquez, 30",
    "sg:city":"Badalona",
    "sg:orig_category":"Albergues",
    "sg:phone":"+34 932 07 79 10",
    "sg:postcode":"08918",
    "sg:province":"Barcelona",
    "wof:name":"Comercial Framan S.a",
    "wof:placetype":"venue"
},
  "geometry": {"coordinates":[2.2336530685,41.4305114746],"type":"Point"}
}