{
  "type": "Feature",
  "properties": {
    "iso:country":"ES",
    "sg:address":"Calle de Virgen De La Antigua, 11",
    "sg:city":"Sevilla",
    "sg:orig_category":"Arquitectos",
    "sg:phone":"+34 954 45 19 05",
    "sg:postcode":"41011",
    "sg:province":"Sevilla",
    "wof:name":"Canterla Gonzalez Emiliano",
    "wof:placetype":"venue"
},
  "geometry": {"coordinates":[-6.0002708435,37.3728713989],"type":"Point"}
}