{
  "type": "Feature",
  "properties": {
    "addr:full":"Calle de Ramon Y Cajal, 31 Castellon Castell\u00f3n 12005",
    "addr:housenumber":"31",
    "addr:postcode":"12005",
    "addr:street":"Calle De Ramon Y Cajal",
    "iso:country":"ES",
    "sg:address":"Calle de Ramon Y Cajal, 31",
    "sg:city":"Castellon",
    "sg:orig_category":"Papeler\u00cdas, Librer\u00cdas",
    "sg:phone":"+34 964 24 47 75",
    "sg:postcode":"12005",
    "sg:province":"Castell\u00f3n",
    "wof:name":"Guzman Marti Maria Salome",
    "wof:placetype":"venue"
},
  "geometry": {"coordinates":[-0.0297400001,39.9624290466],"type":"Point"}
}