{
  "type": "Feature",
  "properties": {
    "iso:country":"ES",
    "sg:address":"Rua Fonti\u00d1as De Abaixo, 106",
    "sg:city":"Fonti\u00d1as",
    "sg:orig_category":"Reciclaje, Desguace De Veh\u00cdculos",
    "sg:phone":"+34 986 37 59 52",
    "sg:postcode":"36215",
    "sg:province":"Pontevedra",
    "wof:name":"Marquez Silva Hermindo",
    "wof:placetype":"venue"
},
  "geometry": {"coordinates":[-8.663274765,42.2263412476],"type":"Point"}
}