{
  "type": "Feature",
  "properties": {
    "addr:full":"Calle de Cervantes, 11 Balazote Albacete 02320",
    "addr:housenumber":"11",
    "addr:postcode":"02320",
    "addr:street":"Calle De Cervantes",
    "iso:country":"ES",
    "sg:address":"Calle de Cervantes, 11",
    "sg:city":"Balazote",
    "sg:orig_category":"Ingeniero",
    "sg:phone":"+34 967 36 00 07",
    "sg:postcode":"02320",
    "sg:province":"Albacete",
    "wof:name":"Cebrian Haro David",
    "wof:placetype":"venue"
},
  "geometry": {"coordinates":[-2.1518278122,38.8852729797],"type":"Point"}
}