{
  "type": "Feature",
  "properties": {
    "addr:full":"Calle de Santa Maria, 10 Errenteria Guip\u00f9zcoa 20100",
    "addr:housenumber":"10",
    "addr:postcode":"20100",
    "addr:street":"Calle De Santa Maria;Guipu\u0300Zcoa",
    "iso:country":"ES",
    "sg:address":"Calle de Santa Maria, 10",
    "sg:city":"Errenteria",
    "sg:orig_category":"Platos Preparados Refrigerados (fabricaci\u00d3n, Al Por Mayor)",
    "sg:phone":"+34 943 52 63 94",
    "sg:postcode":"20100",
    "sg:province":"Guip\u00f9zcoa",
    "sg:website":"www.cornelioetxea.com",
    "wof:name":"Iribarren Elizondo Cornelio",
    "wof:placetype":"venue"
},
  "geometry": {"coordinates":[-1.8991080523,43.3129501343],"type":"Point"}
}