{
  "type": "Feature",
  "properties": {
    "addr:full":"Calle de Puerto, 33 Huelva Huelva 21001",
    "addr:housenumber":"33",
    "addr:postcode":"21001",
    "addr:street":"Calle De Puerto",
    "iso:country":"ES",
    "sg:address":"Calle de Puerto, 33",
    "sg:city":"Huelva",
    "sg:orig_category":"M\u00c9dicos: Medicina General",
    "sg:phone":"+34 959 26 37 32",
    "sg:postcode":"21001",
    "sg:province":"Huelva",
    "wof:name":"Gomez Reyes Jose Luis",
    "wof:placetype":"venue"
},
  "geometry": {"coordinates":[-6.9531698227,37.2585372925],"type":"Point"}
}