{
  "type": "Feature",
  "properties": {
    "addr:full":"Calle de Tomasos, Dels, 17 Valencia Valencia 46006",
    "addr:housenumber":"17",
    "addr:postcode":"46006",
    "addr:street":"Calle De Tomasos Dels",
    "iso:country":"ES",
    "sg:address":"Calle de Tomasos, Dels, 17",
    "sg:city":"Valencia",
    "sg:orig_category":"Asociaciones, Organismos Culturales Y Socioeducativos",
    "sg:phone":"+34 963 33 93 68",
    "sg:postcode":"46006",
    "sg:province":"Valencia",
    "wof:name":"Asociacion Cultural L'avan\u00e7 Informacion",
    "wof:placetype":"venue"
},
  "geometry": {"coordinates":[-0.3718118072,39.4617042542],"type":"Point"}
}