{
  "type": "Feature",
  "properties": {
    "iso:country":"ES",
    "sg:address":"Calle de Virgen Del Valle, 40",
    "sg:city":"Sevilla",
    "sg:orig_category":"Arquitectos",
    "sg:phone":"+34 954 27 22 32",
    "sg:postcode":"41011",
    "sg:province":"Sevilla",
    "wof:name":"Morales Hevia Francisco",
    "wof:placetype":"venue"
},
  "geometry": {"coordinates":[-5.9982509613,37.3758506775],"type":"Point"}
}