{
  "type": "Feature",
  "properties": {
    "addr:full":"Calle de Seis De Junio, 24 Valdepe\u00f1as Ciudad Real 13300",
    "addr:housenumber":"24",
    "addr:postcode":"13300",
    "addr:street":"Calle De Seis De Junio",
    "iso:country":"ES",
    "sg:address":"Calle de Seis De Junio, 24",
    "sg:city":"Valdepe\u00f1as",
    "sg:orig_category":"Gafas (fabricaci\u00d3n)",
    "sg:phone":"+34 926 34 81 06",
    "sg:postcode":"13300",
    "sg:province":"Ciudad Real",
    "wof:name":"Audio Seleccion S.l.",
    "wof:placetype":"venue"
},
  "geometry": {"coordinates":[-3.3870549202,38.7631492615],"type":"Point"}
}