{
  "type": "Feature",
  "properties": {
    "iso:country":"ES",
    "sg:address":"Calle de Colegio, 9",
    "sg:city":"Valdemoro",
    "sg:orig_category":"Inmobiliaria (agencias)",
    "sg:phone":"+34 918 95 30 68",
    "sg:postcode":"28340",
    "sg:province":"Madrid",
    "wof:name":"Gestion Inmobiliaria Seguros Bruma S.c.p",
    "wof:placetype":"venue"
},
  "geometry": {"coordinates":[-3.6778790951,40.1911087036],"type":"Point"}
}