{
  "type": "Feature",
  "properties": {
    "iso:country":"ES",
    "sg:address":"Calle de Martin Machio, 27",
    "sg:city":"Madrid",
    "sg:orig_category":"Psic\u00d3logos",
    "sg:phone":"+34 914 13 56 80",
    "sg:postcode":"28002",
    "sg:province":"Madrid",
    "wof:name":"Moreno Bargue\u00f1o David",
    "wof:placetype":"venue"
},
  "geometry": {"coordinates":[-3.662759304,40.4469413757],"type":"Point"}
}