{
  "type": "Feature",
  "properties": {
    "iso:country":"ES",
    "sg:address":"Rua Lopez Mora, 21",
    "sg:city":"Vigo",
    "sg:orig_category":"Edici\u00d3n De Diarios, Revistas, Boletines",
    "sg:phone":"+34 986 29 59 42",
    "sg:postcode":"36211",
    "sg:province":"Pontevedra",
    "wof:name":"Asociacion Provincial De Vendedores Profesionales De Prensa De Pontevedra",
    "wof:placetype":"venue"
},
  "geometry": {"coordinates":[-8.7314453125,42.2266654968],"type":"Point"}
}