{
  "type": "Feature",
  "properties": {
    "addr:full":"Carr Moll, 4 Alcudia Islas Baleares 07400",
    "addr:housenumber":"4",
    "addr:postcode":"07400",
    "addr:street":"Carr Moll",
    "iso:country":"ES",
    "sg:address":"Carr Moll, 4",
    "sg:city":"Alcudia",
    "sg:orig_category":"Estancos",
    "sg:phone":"+34 971 54 51 88",
    "sg:postcode":"07400",
    "sg:province":"Islas Baleares",
    "wof:name":"Garcias Ferrer Catalina",
    "wof:placetype":"venue"
},
  "geometry": {"coordinates":[3.1233251095,39.8516159058],"type":"Point"}
}