{
  "type": "Feature",
  "properties": {
    "addr:full":"Calle de Iglesia, 1 Malpartida Caceres C\u00e1ceres 10910",
    "addr:housenumber":"1",
    "addr:postcode":"10910",
    "addr:street":"Calle De Iglesia;Ca\u0301Ceres",
    "iso:country":"ES",
    "sg:address":"Calle de Iglesia, 1",
    "sg:city":"Malpartida Caceres",
    "sg:orig_category":"Cajas De Ahorro",
    "sg:phone":"+34 927 27 50 35",
    "sg:postcode":"10910",
    "sg:province":"C\u00e1ceres",
    "sg:website":"www.cajaextremadura.es",
    "wof:name":"Caja De Ahorros Y Monte De Piedad De Extremadura",
    "wof:placetype":"venue"
},
  "geometry": {"coordinates":[-6.5062050819,39.4456367493],"type":"Point"}
}