{
  "type": "Feature",
  "properties": {
    "addr:full":"Calle de Doctor Julian Martin Renedo, 18 Tudela Duero Valladolid 47320",
    "addr:housenumber":"18;duero",
    "addr:postcode":"47320",
    "addr:street":"Calle De Doctor Julian Martin Renedo",
    "iso:country":"ES",
    "sg:address":"Calle de Doctor Julian Martin Renedo, 18",
    "sg:city":"Tudela Duero",
    "sg:orig_category":"Inform\u00c1tica (estudios, Servicios, Asesor\u00cda, Formaci\u00d3n)",
    "sg:phone":"+34 983 52 03 50",
    "sg:postcode":"47320",
    "sg:province":"Valladolid",
    "wof:name":"Merlinmedia S.l.",
    "wof:placetype":"venue"
},
  "geometry": {"coordinates":[-4.5813293457,41.5854225159],"type":"Point"}
}