{
  "type": "Feature",
  "properties": {
    "iso:country":"ES",
    "sg:address":"Calle de Valentin Arevalo Ayllon, 35",
    "sg:city":"Matapozuelos",
    "sg:orig_category":"Iglesia Cat\u00d3lica",
    "sg:phone":"+34 983 83 28 99",
    "sg:postcode":"47230",
    "sg:province":"Valladolid",
    "wof:name":"Parroquia Santa Maria Magdalena",
    "wof:placetype":"venue"
},
  "geometry": {"coordinates":[-4.7907981873,41.4126281738],"type":"Point"}
}