{
  "type": "Feature",
  "properties": {
    "iso:country":"ES",
    "sg:address":"Calle de San Luis, 1",
    "sg:city":"Gijon",
    "sg:orig_category":"Centros Empresariales",
    "sg:phone":"+34 985 13 43 25",
    "sg:postcode":"33205",
    "sg:province":"Asturias",
    "wof:name":"Fernandez Gayol Rosendo",
    "wof:placetype":"venue"
},
  "geometry": {"coordinates":[-5.6558690071,43.537399292],"type":"Point"}
}