{
  "type": "Feature",
  "properties": {
    "iso:country":"ES",
    "sg:address":"La Pe\u00f1a-somado, S/n",
    "sg:city":"Muros Nalon",
    "sg:orig_category":"Empresas De Pintura Y Revestimientos",
    "sg:phone":"+34 985 58 30 48",
    "sg:postcode":"33139",
    "sg:province":"Asturias",
    "wof:name":"Garcia Gonzalez Avelino Salvador",
    "wof:placetype":"venue"
},
  "geometry": {"coordinates":[-6.1192741394,43.5345611572],"type":"Point"}
}