{
  "type": "Feature",
  "properties": {
    "addr:full":"Calle de General Rodrigo, 6 Madrid Madrid 28003",
    "addr:housenumber":"6",
    "addr:postcode":"28003",
    "addr:street":"Calle De General Rodrigo",
    "iso:country":"ES",
    "sg:address":"Calle de General Rodrigo, 6",
    "sg:city":"Madrid",
    "sg:orig_category":"Centros Empresariales",
    "sg:phone":"+34 915 54 70 45",
    "sg:postcode":"28003",
    "sg:province":"Madrid",
    "sg:website":"www.aice.es",
    "wof:name":"Asociacion De Industrias De La Carne De Espa\u00f1a",
    "wof:placetype":"venue"
},
  "geometry": {"coordinates":[-3.7141489983,40.4435653687],"type":"Point"}
}