{
  "type": "Feature",
  "properties": {
    "addr:full":"Ctra Almatriche De, 59 Almatriche Alto Las Palmas 35018",
    "addr:housenumber":"59",
    "addr:postcode":"35018",
    "addr:street":"Ctra Almatriche De",
    "iso:country":"ES",
    "sg:address":"Ctra Almatriche De, 59",
    "sg:city":"Almatriche Alto",
    "sg:orig_category":"Fabricaci\u00d3n De Quesos",
    "sg:phone":"+34 928 67 49 73",
    "sg:postcode":"35018",
    "sg:province":"Las Palmas",
    "wof:name":"Quesos Guia S.l.",
    "wof:placetype":"venue"
},
  "geometry": {"coordinates":[-15.4607486725,28.0851097107],"type":"Point"}
}