{
  "type": "Feature",
  "properties": {
    "addr:full":"Calle de Rossinyol, Del, 10 Nuestra Se\u00e7ora De Jesus Islas Baleares 07819",
    "addr:housenumber":"10",
    "addr:postcode":"07819",
    "addr:street":"Calle De Rossinyol Del;Islas Baleares",
    "iso:country":"ES",
    "sg:address":"Calle de Rossinyol, Del, 10",
    "sg:city":"Nuestra Se\u00e7ora De Jesus",
    "sg:orig_category":"Chapister\u00cda",
    "sg:phone":"+34 971 19 22 65",
    "sg:postcode":"07819",
    "sg:province":"Islas Baleares",
    "wof:name":"Taller Riera S.cv.",
    "wof:placetype":"venue"
},
  "geometry": {"coordinates":[1.444257021,38.934135437],"type":"Point"}
}