{
  "type": "Feature",
  "properties": {
    "iso:country":"ES",
    "sg:address":"Calle de Serrano, 230",
    "sg:city":"Madrid",
    "sg:orig_category":"Peluqueros: De Se\u00d1oras",
    "sg:phone":"+34 915 64 65 87",
    "sg:postcode":"28016",
    "sg:province":"Madrid",
    "wof:name":"Valiente Porras Mario",
    "wof:placetype":"venue"
},
  "geometry": {"coordinates":[-3.6790332794,40.4539260864],"type":"Point"}
}