{
  "type": "Feature",
  "properties": {
    "addr:full":"Agustin Arrojo Mu\u00f1oz, S/n Hervas C\u00e1ceres 10700",
    "addr:postcode":"10700",
    "addr:street":"Agustin;Mun\u0303Oz S / N;Ca\u0301Ceres",
    "iso:country":"ES",
    "sg:address":"Agustin Arrojo Mu\u00f1oz, S/n",
    "sg:city":"Hervas",
    "sg:orig_category":"Art\u00cdculos Funerarios (al Por Menor)",
    "sg:phone":"+34 927 47 34 49",
    "sg:postcode":"10700",
    "sg:province":"C\u00e1ceres",
    "wof:name":"Moraza Garcia Noelia",
    "wof:placetype":"venue"
},
  "geometry": {"coordinates":[-5.8647398949,40.2702217102],"type":"Point"}
}