{
  "type": "Feature",
  "properties": {
    "addr:full":"Av. Monte Alina, 66 Montealina Madrid 28223",
    "addr:housenumber":"66",
    "addr:postcode":"28223",
    "addr:street":"Av. Monte Alina",
    "iso:country":"ES",
    "sg:address":"Av. Monte Alina, 66",
    "sg:city":"Montealina",
    "sg:orig_category":"Asesor\u00cda Sobre Comunicaci\u00d3n De Empresas",
    "sg:phone":"+34 913 51 28 51",
    "sg:postcode":"28223",
    "sg:province":"Madrid",
    "wof:name":"New Business Oportunities S.l.",
    "wof:placetype":"venue"
},
  "geometry": {"coordinates":[-3.8478479385,40.4348335266],"type":"Point"}
}