{
  "type": "Feature",
  "properties": {
    "iso:country":"ES",
    "sg:address":"Calle de Daute, S/n",
    "sg:city":"Sue\u00e7o Azul",
    "sg:orig_category":"Administradores De Bienes Y Delegados De Comunidades De Propietarios",
    "sg:phone":"+34 922 74 11 31",
    "sg:postcode":"38678",
    "sg:province":"Santa Cruz De Tenerife",
    "wof:name":"Wimpen Leisure Management S.a.",
    "wof:placetype":"venue"
},
  "geometry": {"coordinates":[-16.7804145813,28.1329898834],"type":"Point"}
}