{
  "type": "Feature",
  "properties": {
    "addr:full":"Rua Juan Xxiii, S/n Ourense Ourense 32003",
    "addr:housenumber":"s",
    "addr:postcode":"32003",
    "addr:street":"Rua Juan Xxiii;/ N",
    "iso:country":"ES",
    "sg:address":"Rua Juan Xxiii, S/n",
    "sg:city":"Ourense",
    "sg:orig_category":"Aparcamientos (infraestructuras, Accesorios)",
    "sg:phone":"+34 988 37 47 00",
    "sg:postcode":"32003",
    "sg:province":"Ourense",
    "wof:name":"Parking Juan Xxiii S.a.",
    "wof:placetype":"venue"
},
  "geometry": {"coordinates":[-7.8660039902,42.3403053284],"type":"Point"}
}