{
  "type": "Feature",
  "properties": {
    "iso:country":"ES",
    "sg:address":"E. Rollo, S/n",
    "sg:city":"Garrovillas De Alconetar",
    "sg:orig_category":"Mec\u00c1nico Del Autom\u00d3vil",
    "sg:phone":"+34 927 30 90 11",
    "sg:postcode":"10940",
    "sg:province":"C\u00e1ceres",
    "wof:name":"Talleres Mecanicos Santiago Santiago S.l.",
    "wof:placetype":"venue"
},
  "geometry": {"coordinates":[-6.5544137955,39.7060317993],"type":"Point"}
}