{
  "type": "Feature",
  "properties": {
    "iso:country":"ES",
    "sg:address":"Avda Arboledas (de Las), 24",
    "sg:city":"Valdemoro",
    "sg:orig_category":"Fabricaci\u00d3n De Moldes Y Modelos",
    "sg:phone":"+34 918 95 64 46",
    "sg:postcode":"28340",
    "sg:province":"Madrid",
    "wof:name":"Diaz-mayordomo S.l.",
    "wof:placetype":"venue"
},
  "geometry": {"coordinates":[-3.6721899509,40.2038040161],"type":"Point"}
}