{
  "type": "Feature",
  "properties": {
    "iso:country":"ES",
    "sg:address":"Av Tarragona, 3",
    "sg:city":"Tarrega",
    "sg:orig_category":"Pizzer\u00cdas",
    "sg:phone":"+34 973 31 31 34",
    "sg:postcode":"25300",
    "sg:province":"Lleida",
    "wof:name":"Bori Folguera Jesus",
    "wof:placetype":"venue"
},
  "geometry": {"coordinates":[1.140444994,41.6408157349],"type":"Point"}
}