{
  "type": "Feature",
  "properties": {
    "addr:full":"Calle de Garcia Margallo, General, 20 Melilla Melilla 52002",
    "addr:housenumber":"20",
    "addr:postcode":"52002",
    "addr:street":"Calle De Garcia;General",
    "iso:country":"ES",
    "sg:address":"Calle de Garcia Margallo, General, 20",
    "sg:city":"Melilla",
    "sg:orig_category":"Moquetas, Alfombras (al Por Menor)",
    "sg:phone":"+34 952 68 57 84",
    "sg:postcode":"52002",
    "sg:province":"Melilla",
    "wof:name":"Abdelkader  Al Lal",
    "wof:placetype":"venue"
},
  "geometry": {"coordinates":[-2.946317,35.301273],"type":"Point"}
}