{
  "type": "Feature",
  "properties": {
    "iso:country":"ES",
    "sg:address":"Calle de Azorin, 4",
    "sg:city":"Almeria",
    "sg:orig_category":"Centros Empresariales",
    "sg:phone":"+34 950 22 84 73",
    "sg:postcode":"04005",
    "sg:province":"Almer\u00eda",
    "wof:name":"Montajes De Electricidad Moya S.l.",
    "wof:placetype":"venue"
},
  "geometry": {"coordinates":[-2.4575390816,36.8390922546],"type":"Point"}
}