{
  "type": "Feature",
  "properties": {
    "addr:full":"Calle de Santa Ana, 40 Paiporta Valencia 46200",
    "addr:housenumber":"40",
    "addr:postcode":"46200",
    "addr:street":"Calle De Santa Ana",
    "iso:country":"ES",
    "sg:address":"Calle de Santa Ana, 40",
    "sg:city":"Paiporta",
    "sg:orig_category":"Promotores Constructores",
    "sg:phone":"+34 963 97 12 00",
    "sg:postcode":"46200",
    "sg:province":"Valencia",
    "wof:name":"Amt D'obres Y Serveis S.l.",
    "wof:placetype":"venue"
},
  "geometry": {"coordinates":[-0.4202198088,39.4253959656],"type":"Point"}
}