{
  "type": "Feature",
  "properties": {
    "addr:full":"C/ Jorge Juan, 23 Elche Alicante 03201",
    "addr:housenumber":"23",
    "addr:postcode":"03201",
    "addr:street":"C / Jorge Juan",
    "iso:country":"ES",
    "sg:address":"C/ Jorge Juan, 23",
    "sg:city":"Elche",
    "sg:orig_category":"Confecci\u00d3n (fabricaci\u00d3n, Al Por Mayor)",
    "sg:phone":"+34 965 43 22 71",
    "sg:postcode":"03201",
    "sg:province":"Alicante",
    "wof:name":"Martinez Aviles Josefa",
    "wof:placetype":"venue"
},
  "geometry": {"coordinates":[-0.7047709823,38.2667999268],"type":"Point"}
}