{
  "type": "Feature",
  "properties": {
    "addr:full":"Ctra Aldan, 84 Santa Marta Pontevedra 36940",
    "addr:housenumber":"84",
    "addr:postcode":"36940",
    "addr:street":"Ctra Aldan",
    "iso:country":"ES",
    "sg:address":"Ctra Aldan, 84",
    "sg:city":"Santa Marta",
    "sg:orig_category":"Organizaciones Profesionales",
    "sg:phone":"+34 986 30 02 67",
    "sg:postcode":"36940",
    "sg:province":"Pontevedra",
    "wof:name":"Fernandez Gonzalez Eugenio",
    "wof:placetype":"venue"
},
  "geometry": {"coordinates":[-8.8184690475,42.2742500305],"type":"Point"}
}