{
  "type": "Feature",
  "properties": {
    "iso:country":"ES",
    "sg:address":"Carr Major, 25",
    "sg:city":"Picassent",
    "sg:orig_category":"Hormig\u00d3n (m\u00c1quinas E Instalaci\u00d3n)",
    "sg:phone":"+34 961 23 13 15",
    "sg:postcode":"46220",
    "sg:province":"Valencia",
    "wof:name":"Hormigones Senia S.l.",
    "wof:placetype":"venue"
},
  "geometry": {"coordinates":[-0.459461987,39.3625602722],"type":"Point"}
}