{
  "type": "Feature",
  "properties": {
    "addr:full":"Pl Castanyers, 1 Sabadell Barcelona 08207",
    "addr:housenumber":"1",
    "addr:postcode":"08207",
    "addr:street":"Pl Castanyers",
    "iso:country":"ES",
    "sg:address":"Pl Castanyers, 1",
    "sg:city":"Sabadell",
    "sg:orig_category":"Cajas De Ahorro",
    "sg:phone":"+34 937 16 52 33",
    "sg:postcode":"08207",
    "sg:province":"Barcelona",
    "wof:name":"Caixa D'estalvis Sabadell",
    "wof:placetype":"venue"
},
  "geometry": {"coordinates":[2.0874040127,41.5761299133],"type":"Point"}
}