{
  "type": "Feature",
  "properties": {
    "iso:country":"ES",
    "sg:address":"Carr Migdia, 24",
    "sg:city":"Girona",
    "sg:orig_category":"Ropa Para Se\u00d1oras Y Caballeros (al Por Menor)",
    "sg:phone":"+34 972 22 84 86",
    "sg:postcode":"17002",
    "sg:province":"Girona",
    "wof:name":"Martinez Calls Alba",
    "wof:placetype":"venue"
},
  "geometry": {"coordinates":[2.8206090927,41.9765930176],"type":"Point"}
}