{
  "type": "Feature",
  "properties": {
    "addr:full":"Carrer de Pare F Molina, 32 Palma Islas Baleares 07003",
    "addr:housenumber":"32",
    "addr:postcode":"07003",
    "addr:street":"Carrer De Pare F Molina",
    "iso:country":"ES",
    "sg:address":"Carrer de Pare F Molina, 32",
    "sg:city":"Palma",
    "sg:orig_category":"Institutos De Belleza",
    "sg:phone":"+34 971 73 31 77",
    "sg:postcode":"07003",
    "sg:province":"Islas Baleares",
    "wof:name":"Martorell Genovart Francisca",
    "wof:placetype":"venue"
},
  "geometry": {"coordinates":[2.6474070549,39.5827445984],"type":"Point"}
}