{
  "type": "Feature",
  "properties": {
    "iso:country":"ES",
    "sg:address":"Plaz Cascorro, 13",
    "sg:city":"Madrid",
    "sg:orig_category":"Fabricaci\u00d3n, Importaci\u00d3n De L\u00c1mparas Y Bombillas",
    "sg:phone":"+34 913 65 24 51",
    "sg:postcode":"28005",
    "sg:province":"Madrid",
    "wof:name":"Cepero Anastasia Y Perez Garaulet Ana Maria S.c.",
    "wof:placetype":"venue"
},
  "geometry": {"coordinates":[-3.7074871063,40.4101791382],"type":"Point"}
}