{
  "type": "Feature",
  "properties": {
    "iso:country":"ES",
    "sg:address":"Carrer de Llull, 133",
    "sg:city":"Barcelona",
    "sg:orig_category":"Suministros Para Hoteles",
    "sg:phone":"+34 933 00 48 00",
    "sg:postcode":"08005",
    "sg:province":"Barcelona",
    "sg:website":"www.oyv.es",
    "wof:name":"Oms Y Vi\u00f1as S.r.c.",
    "wof:placetype":"venue"
},
  "geometry": {"coordinates":[2.1986029148,41.3985366821],"type":"Point"}
}