{
  "type": "Feature",
  "properties": {
    "addr:full":"Cril Parra(la Cueva), 42 Monteagudo Murcia 30160",
    "addr:housenumber":"42",
    "addr:postcode":"30160",
    "addr:street":"Cueva",
    "iso:country":"ES",
    "sg:address":"Cril Parra(la Cueva), 42",
    "sg:city":"Monteagudo",
    "sg:orig_category":"Maquinaria Para Industrias Diversas",
    "sg:phone":"+34 968 85 27 31",
    "sg:postcode":"30160",
    "sg:province":"Murcia",
    "wof:name":"Martinez Gomez Jose",
    "wof:placetype":"venue"
},
  "geometry": {"coordinates":[-1.0960119963,38.0188484192],"type":"Point"}
}