{
  "type": "Feature",
  "properties": {
    "addr:full":"Carrer de Tossa, S/n Llagostera Girona 17240",
    "addr:housenumber":"s / n",
    "addr:postcode":"17240",
    "addr:street":"Carrer De Tossa",
    "iso:country":"ES",
    "sg:address":"Carrer de Tossa, S/n",
    "sg:city":"Llagostera",
    "sg:orig_category":"Mec\u00c1nico Del Autom\u00d3vil",
    "sg:phone":"+34 972 83 09 07",
    "sg:postcode":"17240",
    "sg:province":"Girona",
    "wof:name":"Ramon Gurnes S.l.",
    "wof:placetype":"venue"
},
  "geometry": {"coordinates":[2.8879349232,41.8238487244],"type":"Point"}
}