{
  "type": "Feature",
  "properties": {
    "iso:country":"ES",
    "sg:address":"O Sisto, S/n",
    "sg:city":"Sisto",
    "sg:orig_category":"M\u00c9dicos: Estomatolog\u00cda",
    "sg:phone":"+34 981 80 76 45",
    "sg:postcode":"15883",
    "sg:province":"La Coru\u00f1a",
    "wof:name":"Bernardez Dominguez Juan Jose",
    "wof:placetype":"venue"
},
  "geometry": {"coordinates":[-8.5444011688,42.8382263184],"type":"Point"}
}