{
  "type": "Feature",
  "properties": {
    "addr:full":"Calle de Santo Tome, S/n Rollan Salamanca 37447",
    "addr:housenumber":"s",
    "addr:postcode":"37447",
    "addr:street":"Calle De Santo Tome;/ N",
    "iso:country":"ES",
    "sg:address":"Calle de Santo Tome, S/n",
    "sg:city":"Rollan",
    "sg:orig_category":"Cerrajer\u00cda, Ferrallista",
    "sg:phone":"+34 923 31 30 16",
    "sg:postcode":"37447",
    "sg:province":"Salamanca",
    "wof:name":"Talleres Rodrisan S.l.",
    "wof:placetype":"venue"
},
  "geometry": {"coordinates":[-5.9159116745,40.9616012573],"type":"Point"}
}