{
  "type": "Feature",
  "properties": {
    "addr:full":"Carrer de Josep Anselm Clave, 31 S. Just Desvern Barcelona 08960",
    "addr:housenumber":"31",
    "addr:postcode":"08960",
    "addr:street":"Carrer De Josep Anselm Clave",
    "iso:country":"ES",
    "sg:address":"Carrer de Josep Anselm Clave, 31",
    "sg:city":"S. Just Desvern",
    "sg:orig_category":"Inform\u00c1tica (estudios, Servicios, Asesor\u00cda, Formaci\u00d3n)",
    "sg:phone":"+34 934 70 51 12",
    "sg:postcode":"08960",
    "sg:province":"Barcelona",
    "wof:name":"Tic Informatica S.c.p",
    "wof:placetype":"venue"
},
  "geometry": {"coordinates":[2.074600935,41.3841590881],"type":"Point"}
}