{
  "type": "Feature",
  "properties": {
    "iso:country":"ES",
    "sg:address":"Carrer de Camps I Fabres, 10",
    "sg:city":"Barcelona",
    "sg:orig_category":"Fabricaci\u00d3n De Sobres, Bolsas Y Fundas",
    "sg:phone":"+34 932 37 54 75",
    "sg:postcode":"08006",
    "sg:province":"Barcelona",
    "sg:website":"www.bitlobarcelona.com",
    "wof:name":"Beatriz Furest S.l.",
    "wof:placetype":"venue"
},
  "geometry": {"coordinates":[2.1495521069,41.4039726257],"type":"Point"}
}