{
  "type": "Feature",
  "properties": {
    "addr:full":"Calle de Linaje, 1 Malaga M\u00e1laga 29001",
    "addr:housenumber":"1",
    "addr:postcode":"29001",
    "addr:street":"Calle De Linaje;Ma\u0301Laga",
    "iso:country":"ES",
    "sg:address":"Calle de Linaje, 1",
    "sg:city":"Malaga",
    "sg:orig_category":"Doctores En Medicina",
    "sg:phone":"+34 952 22 66 57",
    "sg:postcode":"29001",
    "sg:province":"M\u00e1laga",
    "wof:name":"Lopez Gonzalez Angel Luis",
    "wof:placetype":"venue"
},
  "geometry": {"coordinates":[-4.4252099991,36.7157249451],"type":"Point"}
}