{
  "type": "Feature",
  "properties": {
    "iso:country":"ES",
    "sg:address":"Avda America (de), S/n",
    "sg:city":"Cordoba",
    "sg:orig_category":"Alquiler De Veh\u00cdculos: Turismos Y Utilitarios",
    "sg:phone":"+34 957 40 23 96",
    "sg:postcode":"14008",
    "sg:province":"C\u00f3rdoba",
    "sg:website":"www.europcar.es",
    "wof:name":"Europcar Ib. S.a",
    "wof:placetype":"venue"
},
  "geometry": {"coordinates":[-4.783823967,37.8902015686],"type":"Point"}
}