{
  "type": "Feature",
  "properties": {
    "addr:full":"Avda Pais Valencia, 5 San Vicente Del Raspeig-sant Vicent Del Raspeig Alicante 03690",
    "addr:housenumber":"5",
    "addr:postcode":"03690",
    "addr:street":"Avda Pais Valencia",
    "iso:country":"ES",
    "sg:address":"Avda Pais Valencia, 5",
    "sg:city":"San Vicente Del Raspeig-sant Vicent Del Raspeig",
    "sg:orig_category":"Promotores Constructores",
    "sg:phone":"+34 965 66 21 68",
    "sg:postcode":"03690",
    "sg:province":"Alicante",
    "wof:name":"Adimed Xxi S.l.",
    "wof:placetype":"venue"
},
  "geometry": {"coordinates":[-0.5230718851,38.3921775818],"type":"Point"}
}