{
  "type": "Feature",
  "properties": {
    "iso:country":"ES",
    "sg:address":"Avda Perez Galdos, 52",
    "sg:city":"Logro\u00f1o",
    "sg:orig_category":"Dorados, Plater\u00cda (orfebrer\u00cda)",
    "sg:phone":"+34 941 22 34 25",
    "sg:postcode":"26002",
    "sg:province":"La Rioja",
    "wof:name":"Lopez-lavalillo Manclares Maria Pilar",
    "wof:placetype":"venue"
},
  "geometry": {"coordinates":[-2.452755928,42.4625091553],"type":"Point"}
}