{
  "type": "Feature",
  "properties": {
    "addr:full":"Carrer de Rei Marti L'huma, 9 Olot Girona 17800",
    "addr:housenumber":"9",
    "addr:postcode":"17800",
    "addr:street":"Carrer De Rei Marti L'Huma",
    "iso:country":"ES",
    "sg:address":"Carrer de Rei Marti L'huma, 9",
    "sg:city":"Olot",
    "sg:orig_category":"Servicios De Telecomunicaciones",
    "sg:phone":"+34 972 27 29 57",
    "sg:postcode":"17800",
    "sg:province":"Girona",
    "wof:name":"Souleymane  Coulidaly",
    "wof:placetype":"venue"
},
  "geometry": {"coordinates":[2.4970159531,42.1879081726],"type":"Point"}
}