{
  "type": "Feature",
  "properties": {
    "addr:full":"Calle de Sagunto, 7 Castellon Castell\u00f3n 12006",
    "addr:housenumber":"7",
    "addr:postcode":"12006",
    "addr:street":"Calle De Sagunto;Castello\u0301N",
    "iso:country":"ES",
    "sg:address":"Calle de Sagunto, 7",
    "sg:city":"Castellon",
    "sg:orig_category":"Ropa Para Se\u00d1oras Y Caballeros (al Por Menor)",
    "sg:phone":"+34 964 25 53 63",
    "sg:postcode":"12006",
    "sg:province":"Castell\u00f3n",
    "wof:name":"Garcia Alarcon Amada",
    "wof:placetype":"venue"
},
  "geometry": {"coordinates":[-0.1292939931,40.0168533325],"type":"Point"}
}