{
  "type": "Feature",
  "properties": {
    "addr:full":"Carr Santiago Rossinyol, 29 Almenar Lleida 25126",
    "addr:housenumber":"29",
    "addr:postcode":"25126",
    "addr:street":"Carr Santiago Rossinyol",
    "iso:country":"ES",
    "sg:address":"Carr Santiago Rossinyol, 29",
    "sg:city":"Almenar",
    "sg:orig_category":"Carnicer\u00cdas, Carnicer\u00cdas",
    "sg:phone":"+34 973 77 10 65",
    "sg:postcode":"25126",
    "sg:province":"Lleida",
    "wof:name":"La Carnisseria S.c.p.",
    "wof:placetype":"venue"
},
  "geometry": {"coordinates":[0.5701000094,41.7965431213],"type":"Point"}
}