{
  "type": "Feature",
  "properties": {
    "iso:country":"ES",
    "sg:address":"Carrer de Manlleu, 34",
    "sg:city":"Vic",
    "sg:orig_category":"Molduras, Junquillos, Listones Y Molduras Perforadas",
    "sg:phone":"+34 938 89 37 26",
    "sg:postcode":"08500",
    "sg:province":"Barcelona",
    "wof:name":"Lal  Harwinder",
    "wof:placetype":"venue"
},
  "geometry": {"coordinates":[2.255603075,41.9324150085],"type":"Point"}
}