{
  "type": "Feature",
  "properties": {
    "addr:full":"Pl Vila De Madrid, 5 Barcelona Barcelona 08002",
    "addr:housenumber":"5",
    "addr:postcode":"08002",
    "addr:street":"Pl Vila De Madrid",
    "iso:country":"ES",
    "sg:address":"Pl Vila De Madrid, 5",
    "sg:city":"Barcelona",
    "sg:orig_category":"Asesor\u00cda Sobre Comunicaci\u00d3n De Empresas",
    "sg:phone":"+34 934 12 77 10",
    "sg:postcode":"08002",
    "sg:province":"Barcelona",
    "sg:website":"www.balancenet.info/web/index.php",
    "wof:name":"Centre Recursos De Iniciatives I Autocupacio S.l.",
    "wof:placetype":"venue"
},
  "geometry": {"coordinates":[2.1724460125,41.3840522766],"type":"Point"}
}