{
  "type": "Feature",
  "properties": {
    "addr:full":"Calle de Heroes De Baler, 1 Fuengirola M\u00e1laga 29640",
    "addr:postcode":"29640",
    "addr:street":"Calle De Heroes De Baler;Ma\u0301Laga",
    "iso:country":"ES",
    "sg:address":"Calle de Heroes De Baler, 1",
    "sg:city":"Fuengirola",
    "sg:orig_category":"Procuradores",
    "sg:phone":"+34 952 47 05 92",
    "sg:postcode":"29640",
    "sg:province":"M\u00e1laga",
    "wof:name":"Garcia Bermudez Matias",
    "wof:placetype":"venue"
},
  "geometry": {"coordinates":[-4.626595974,36.5325164795],"type":"Point"}
}