{
  "type": "Feature",
  "properties": {
    "addr:full":"Pg Can Taio, 73 Florida Barcelona 08130",
    "addr:housenumber":"73",
    "addr:postcode":"08130",
    "addr:street":"Pg Can Taio",
    "iso:country":"ES",
    "sg:address":"Pg Can Taio, 73",
    "sg:city":"Florida",
    "sg:orig_category":"Promotores Constructores",
    "sg:phone":"+34 935 60 68 19",
    "sg:postcode":"08130",
    "sg:province":"Barcelona",
    "wof:name":"Tenencia De Solares S. L.",
    "wof:placetype":"venue"
},
  "geometry": {"coordinates":[2.1802799702,41.5371818542],"type":"Point"}
}