{
  "type": "Feature",
  "properties": {
    "iso:country":"ES",
    "sg:address":"Carr Montcaire, 5",
    "sg:city":"Pont D'inca",
    "sg:orig_category":"Remolques, Carretillas De Mano Para Operaciones Portuarias",
    "sg:phone":"+34 971 60 89 91",
    "sg:postcode":"07009",
    "sg:province":"Islas Baleares",
    "wof:name":"Plataformas Aereas Mallorca S.l.",
    "wof:placetype":"venue"
},
  "geometry": {"coordinates":[2.9091899395,39.7197418213],"type":"Point"}
}