{
  "type": "Feature",
  "properties": {
    "iso:country":"ES",
    "sg:address":"Carrer de Sant Francesc, 46",
    "sg:city":"Sitges",
    "sg:orig_category":"Hoteles",
    "sg:phone":"+34 938 94 06 12",
    "sg:postcode":"08870",
    "sg:province":"Barcelona",
    "wof:name":"Amell S. L.",
    "wof:placetype":"venue"
},
  "geometry": {"coordinates":[1.8081227541,41.237663269],"type":"Point"}
}