{
  "type": "Feature",
  "properties": {
    "addr:full":"Calle de Luis De Gongora, 4 Madrid Madrid 28004",
    "addr:housenumber":"4",
    "addr:postcode":"28004",
    "addr:street":"Calle De Luis De Gongora",
    "iso:country":"ES",
    "sg:address":"Calle de Luis De Gongora, 4",
    "sg:city":"Madrid",
    "sg:orig_category":"Motocicletas (agentes, Concesionarios)",
    "sg:phone":"+34 915 21 71 75",
    "sg:postcode":"28004",
    "sg:province":"Madrid",
    "wof:name":"Lopez Bueno Maria Paz",
    "wof:placetype":"venue"
},
  "geometry": {"coordinates":[-3.6966838837,40.4230461121],"type":"Point"}
}