{
  "type": "Feature",
  "properties": {
    "iso:country":"ES",
    "sg:address":"Carrer de La Rambla, 66",
    "sg:city":"Barcelona",
    "sg:orig_category":"Art\u00cdculos De Regalo (al Por Menor)",
    "sg:phone":"+34 933 17 76 53",
    "sg:postcode":"08002",
    "sg:province":"Barcelona",
    "wof:name":"Harjani  Ishwarlal",
    "wof:placetype":"venue"
},
  "geometry": {"coordinates":[2.1740651131,41.380657196],"type":"Point"}
}