{
  "type": "Feature",
  "properties": {
    "addr:full":"Avda Miramar, 4 S. Vicente Barquera Cantabria 39540",
    "addr:housenumber":"4",
    "addr:postcode":"39540",
    "addr:street":"Avda Miramar;S. Vicente",
    "iso:country":"ES",
    "sg:address":"Avda Miramar, 4",
    "sg:city":"S. Vicente Barquera",
    "sg:orig_category":"Fabricaci\u00d3n, Reparaci\u00d3n Y Mantenimiento De Construcciones Navales Y Fluviales",
    "sg:phone":"+34 942 71 02 55",
    "sg:postcode":"39540",
    "sg:province":"Cantabria",
    "wof:name":"Bada Bada Serafin",
    "wof:placetype":"venue"
},
  "geometry": {"coordinates":[-4.398639679,43.3832168579],"type":"Point"}
}