{
  "type": "Feature",
  "properties": {
    "iso:country":"ES",
    "sg:address":"Calle de Morgan, 2",
    "sg:city":"Bilbao",
    "sg:orig_category":"Material Y Accesorios Para Soldaduras",
    "sg:phone":"+34 944 75 45 81",
    "sg:postcode":"48014",
    "sg:province":"Vizcaya",
    "wof:name":"Soldadura Bohler Utp Espa\u00f1a S.a.",
    "wof:placetype":"venue"
},
  "geometry": {"coordinates":[-2.9540739059,43.2685661316],"type":"Point"}
}