{
  "type": "Feature",
  "properties": {
    "addr:full":"Calle de Doctor Vigueras, 6 Puerta De Segura Ja\u00e9n 23360",
    "addr:housenumber":"6",
    "addr:postcode":"23360",
    "addr:street":"Calle De Doctor Vigueras;Jae\u0301N",
    "iso:country":"ES",
    "sg:address":"Calle de Doctor Vigueras, 6",
    "sg:city":"Puerta De Segura",
    "sg:orig_category":"Conservas De Legumbres (fabricaci\u00d3n, Al Por Mayor)",
    "sg:phone":"+34 953 48 62 06",
    "sg:postcode":"23360",
    "sg:province":"Ja\u00e9n",
    "wof:name":"Aceitunas El Yelmo S.l.",
    "wof:placetype":"venue"
},
  "geometry": {"coordinates":[-2.7340741158,38.3479270935],"type":"Point"}
}