{
  "type": "Feature",
  "properties": {
    "addr:full":"Calle de Profesor Francisco Cruz, 10 S.juan Las Palmas 35200",
    "addr:housenumber":"10",
    "addr:postcode":"35200",
    "addr:street":"Calle De Profesor Francisco Cruz;Las Palmas",
    "iso:country":"ES",
    "sg:address":"Calle de Profesor Francisco Cruz, 10",
    "sg:city":"S.juan",
    "sg:orig_category":"Panader\u00cdas, Panader\u00cdas",
    "sg:phone":"+34 928 69 90 53",
    "sg:postcode":"35200",
    "sg:province":"Las Palmas",
    "wof:name":"Socorro Tejera Carmen",
    "wof:placetype":"venue"
},
  "geometry": {"coordinates":[-15.5215034485,28.1200065613],"type":"Point"}
}