{
  "type": "Feature",
  "properties": {
    "addr:full":"Martires Auzoa, S/n Arrieta-mendi Guip\u00f9zcoa 20720",
    "addr:housenumber":"s / n",
    "addr:postcode":"20720",
    "addr:street":"Martires Auzoa;Guipu\u0300Zcoa",
    "iso:country":"ES",
    "sg:address":"Martires Auzoa, S/n",
    "sg:city":"Arrieta-mendi",
    "sg:orig_category":"Molduras, Junquillos, Listones Y Molduras Perforadas",
    "sg:phone":"+34 943 85 33 36",
    "sg:postcode":"20720",
    "sg:province":"Guip\u00f9zcoa",
    "wof:name":"Arrizabalaga Zubizarreta Manuel",
    "wof:placetype":"venue"
},
  "geometry": {"coordinates":[-2.3134639263,43.1762886047],"type":"Point"}
}