{
  "type": "Feature",
  "properties": {
    "iso:country":"ES",
    "sg:address":"Calle de Magistral Delgado, 4",
    "sg:city":"Zamora",
    "sg:orig_category":"Fabricaci\u00d3n De Acumuladores Y De Pilas El\u00c9ctricas",
    "sg:phone":"+34 980 51 65 04",
    "sg:postcode":"49031",
    "sg:province":"Zamora",
    "wof:name":"Carnero Felipe Ramon Manuel",
    "wof:placetype":"venue"
},
  "geometry": {"coordinates":[-5.7509450912,41.5048828125],"type":"Point"}
}