{
  "type": "Feature",
  "properties": {
    "iso:country":"ES",
    "sg:address":"Plaz Fuente, 15",
    "sg:city":"Salamanca",
    "sg:orig_category":"Supermercados Y Hipermercados",
    "sg:phone":"+34 923 26 11 14",
    "sg:postcode":"37002",
    "sg:province":"Salamanca",
    "wof:name":"Grupo El Arbol Distribucion Y Supermercados S.a. Unipersonal",
    "wof:placetype":"venue"
},
  "geometry": {"coordinates":[-5.6667218208,40.9674987793],"type":"Point"}
}