{
  "type": "Feature",
  "properties": {
    "iso:country":"ES",
    "sg:address":"Calle de Reyes Catolicos, 33",
    "sg:city":"Palmas De Gran Canaria",
    "sg:orig_category":"M\u00c9dicos: Otorrinolaringolog\u00cda",
    "sg:phone":"+34 928 33 00 99",
    "sg:postcode":"35001",
    "sg:province":"Las Palmas",
    "wof:name":"Martinez Herrero Jesus",
    "wof:placetype":"venue"
},
  "geometry": {"coordinates":[-15.4140672684,28.0990772247],"type":"Point"}
}