{
  "type": "Feature",
  "properties": {
    "iso:country":"ES",
    "sg:address":"Calle de Aguila, 8",
    "sg:city":"Albacete",
    "sg:orig_category":"Empresas De Pintura Y Revestimientos",
    "sg:phone":"+34 967 50 32 46",
    "sg:postcode":"02006",
    "sg:province":"Albacete",
    "wof:name":"Cebrian Arteseros Juan Sebastian",
    "wof:placetype":"venue"
},
  "geometry": {"coordinates":[-1.8739032745,38.9972419739],"type":"Point"}
}