{
  "type": "Feature",
  "properties": {
    "iso:country":"ES",
    "sg:address":"Calle de Infanta Beatriz, 17",
    "sg:city":"Sanlucar De Barrameda",
    "sg:orig_category":"Sociedades, Compa\u00d1\u00cdas Aseguradoras",
    "sg:phone":"+34 956 38 55 60",
    "sg:postcode":"11540",
    "sg:province":"C\u00e1diz",
    "sg:website":"www.mapfre.es",
    "wof:name":"Mapfre Servicios De Informatica S.a.",
    "wof:placetype":"venue"
},
  "geometry": {"coordinates":[-6.354033947,36.781627655],"type":"Point"}
}