{
  "type": "Feature",
  "properties": {
    "addr:full":"Calle de Oviedo, 12 Humanes De Madrid Madrid 28970",
    "addr:housenumber":"12",
    "addr:postcode":"28970",
    "addr:street":"Calle De Oviedo",
    "iso:country":"ES",
    "sg:address":"Calle de Oviedo, 12",
    "sg:city":"Humanes De Madrid",
    "sg:orig_category":"Chapister\u00cda",
    "sg:phone":"+34 916 00 08 50",
    "sg:postcode":"28970",
    "sg:province":"Madrid",
    "wof:name":"Talleres Joviauto S.l.",
    "wof:placetype":"venue"
},
  "geometry": {"coordinates":[-3.8246970177,40.2716674805],"type":"Point"}
}