{
  "type": "Feature",
  "properties": {
    "addr:full":"Avda Pirineos, S/n Barbastro Huesca 22300",
    "addr:housenumber":"s / n",
    "addr:postcode":"22300",
    "addr:street":"Avda Pirineos",
    "iso:country":"ES",
    "sg:address":"Avda Pirineos, S/n",
    "sg:city":"Barbastro",
    "sg:orig_category":"Ebanister\u00cda",
    "sg:phone":"+34 974 31 00 49",
    "sg:postcode":"22300",
    "sg:province":"Huesca",
    "wof:name":"Malo Solana Manuel",
    "wof:placetype":"venue"
},
  "geometry": {"coordinates":[0.136164993,42.0437812805],"type":"Point"}
}