{
  "type": "Feature",
  "properties": {
    "addr:full":"Calle de Iglesia, 3 Dilar Granada 18152",
    "addr:housenumber":"3",
    "addr:postcode":"18152",
    "addr:street":"Calle De Iglesia",
    "iso:country":"ES",
    "sg:address":"Calle de Iglesia, 3",
    "sg:city":"Dilar",
    "sg:orig_category":"Iglesia Cat\u00d3lica",
    "sg:phone":"+34 958 59 60 07",
    "sg:postcode":"18152",
    "sg:province":"Granada",
    "wof:name":"Parroquia De La Inmaculada Concepcion",
    "wof:placetype":"venue"
},
  "geometry": {"coordinates":[-3.6015539169,37.0747375488],"type":"Point"}
}