{
  "type": "Feature",
  "properties": {
    "iso:country":"ES",
    "sg:address":"Calle de San Isidro, 16",
    "sg:city":"Vencillon",
    "sg:orig_category":"Centros Empresariales",
    "sg:phone":"+34 974 43 42 45",
    "sg:postcode":"22549",
    "sg:province":"Huesca",
    "wof:name":"Comunidad Regantes De Vencillon",
    "wof:placetype":"venue"
},
  "geometry": {"coordinates":[0.3247889876,41.704536438],"type":"Point"}
}