{
  "type": "Feature",
  "properties": {
    "addr:full":"Calle de Doctor Espina, 24 Madrid Madrid 28019",
    "addr:housenumber":"24",
    "addr:postcode":"madrid;28019",
    "addr:street":"Calle De Doctor Espina",
    "iso:country":"ES",
    "sg:address":"Calle de Doctor Espina, 24",
    "sg:city":"Madrid",
    "sg:orig_category":"Panader\u00cdas, Panader\u00cdas",
    "sg:phone":"+34 914 71 94 91",
    "sg:postcode":"28019",
    "sg:province":"Madrid",
    "wof:name":"Pasteleria El Soto S.l.",
    "wof:placetype":"venue"
},
  "geometry": {"coordinates":[-3.7280857563,40.3890571594],"type":"Point"}
}