{
  "type": "Feature",
  "properties": {
    "addr:full":"Calle de Don Juan De Austria, 33 Malaga M\u00e1laga 29009",
    "addr:housenumber":"33",
    "addr:postcode":"29009",
    "addr:street":"Calle De Don Juan De Austria;Ma\u0301Laga",
    "iso:country":"ES",
    "sg:address":"Calle de Don Juan De Austria, 33",
    "sg:city":"Malaga",
    "sg:orig_category":"Estancos",
    "sg:phone":"+34 952 39 72 91",
    "sg:postcode":"29009",
    "sg:province":"M\u00e1laga",
    "wof:name":"Diaz Molina Trinidad",
    "wof:placetype":"venue"
},
  "geometry": {"coordinates":[-4.4289360046,36.7256965637],"type":"Point"}
}