{
  "type": "Feature",
  "properties": {
    "iso:country":"ES",
    "sg:address":"Calle de Maria De Molina, 5",
    "sg:city":"Valladolid",
    "sg:orig_category":"Molduras, Junquillos, Listones Y Molduras Perforadas",
    "sg:phone":"+34 983 34 38 37",
    "sg:postcode":"47001",
    "sg:province":"Valladolid",
    "wof:name":"Intercoma Xxi S.l.",
    "wof:placetype":"venue"
},
  "geometry": {"coordinates":[-4.7302360535,41.6497421265],"type":"Point"}
}