{
  "type": "Feature",
  "properties": {
    "addr:full":"Calle de San Fermin, 28 Torrent Valencia 46900",
    "addr:housenumber":"28",
    "addr:postcode":"46900",
    "addr:street":"Calle De San Fermin;Valencia",
    "iso:country":"ES",
    "sg:address":"Calle de San Fermin, 28",
    "sg:city":"Torrent",
    "sg:orig_category":"Fabricaci\u00d3n De Jabones, Detergentes Y Lej\u00cdas",
    "sg:phone":"+34 961 55 01 84",
    "sg:postcode":"46900",
    "sg:province":"Valencia",
    "wof:name":"Alejandro Moncholi Vicente",
    "wof:placetype":"venue"
},
  "geometry": {"coordinates":[-0.4726040959,39.4342765808],"type":"Point"}
}