{
  "type": "Feature",
  "properties": {
    "addr:full":"Carrer de Retama, 20 Viladecans Barcelona 08840",
    "addr:housenumber":"20",
    "addr:postcode":"08840",
    "addr:street":"Carrer De Retama",
    "iso:country":"ES",
    "sg:address":"Carrer de Retama, 20",
    "sg:city":"Viladecans",
    "sg:orig_category":"Mec\u00c1nico Del Autom\u00d3vil",
    "sg:phone":"+34 936 59 05 08",
    "sg:postcode":"08840",
    "sg:province":"Barcelona",
    "wof:name":"Autoracing 92 S.l.",
    "wof:placetype":"venue"
},
  "geometry": {"coordinates":[2.0097310543,41.3228378296],"type":"Point"}
}