{
  "type": "Feature",
  "properties": {
    "addr:full":"Calle de Musico Cabanilles, 40 Valencia Valencia 46017",
    "addr:housenumber":"40",
    "addr:postcode":"46017",
    "addr:street":"Calle De Musico Cabanilles",
    "iso:country":"ES",
    "sg:address":"Calle de Musico Cabanilles, 40",
    "sg:city":"Valencia",
    "sg:orig_category":"Fabricaci\u00d3n De Su\u00c9ters Y Chalecos De Punto",
    "sg:phone":"+34 963 78 21 73",
    "sg:postcode":"46017",
    "sg:province":"Valencia",
    "wof:name":"Crespo Martin Juana",
    "wof:placetype":"venue"
},
  "geometry": {"coordinates":[-0.3911789954,39.445148468],"type":"Point"}
}