{
  "type": "Feature",
  "properties": {
    "iso:country":"ES",
    "sg:address":"Calle de Fajardo, 24",
    "sg:city":"Haria",
    "sg:orig_category":"Ense\u00d1anza: Idiomas",
    "sg:phone":"+34 928 83 51 35",
    "sg:postcode":"35520",
    "sg:province":"Las Palmas",
    "wof:name":"Beaker  Jaquelin",
    "wof:placetype":"venue"
},
  "geometry": {"coordinates":[-13.4984197617,29.1485557556],"type":"Point"}
}