{
  "type": "Feature",
  "properties": {
    "iso:country":"ES",
    "sg:address":"Avda Juventudes Musicales, 13",
    "sg:city":"Sevilla",
    "sg:orig_category":"Farmacias",
    "sg:phone":"+34 954 38 44 00",
    "sg:postcode":"41009",
    "sg:province":"Sevilla",
    "wof:name":"Farmacia El Alamillo C.b.",
    "wof:placetype":"venue"
},
  "geometry": {"coordinates":[-5.984336853,37.4135780334],"type":"Point"}
}