{
  "type": "Feature",
  "properties": {
    "iso:country":"ES",
    "sg:address":"Calle de Rojas Zorrilla, 3",
    "sg:city":"Alcala Henares",
    "sg:orig_category":"Inmobiliaria (agencias)",
    "sg:phone":"+34 918 79 72 72",
    "sg:postcode":"28805",
    "sg:province":"Madrid",
    "wof:name":"Gestion Integral Inmobiliaria Villacasa S.l.",
    "wof:placetype":"venue"
},
  "geometry": {"coordinates":[-3.3599669933,40.4891662598],"type":"Point"}
}