{
  "type": "Feature",
  "properties": {
    "iso:country":"ES",
    "sg:address":"Finca Valverde, S/n",
    "sg:city":"Santiba\u00f1ez Alto",
    "sg:orig_category":"Conservas De Legumbres (fabricaci\u00d3n, Al Por Mayor)",
    "sg:phone":"+34 927 44 11 32",
    "sg:postcode":"10859",
    "sg:province":"C\u00e1ceres",
    "wof:name":"Pizarro Bonilla Felix",
    "wof:placetype":"venue"
},
  "geometry": {"coordinates":[-6.5466189384,40.1860351562],"type":"Point"}
}