{
  "type": "Feature",
  "properties": {
    "iso:country":"ES",
    "sg:address":"Calle de Julian Gayarre, 6",
    "sg:city":"Sestao",
    "sg:orig_category":"Producci\u00d3n, Distribuci\u00d3n De Electricidad",
    "sg:phone":"+34 944 95 22 76",
    "sg:postcode":"48910",
    "sg:province":"Vizcaya",
    "wof:name":"Alberto San Mames Perez",
    "wof:placetype":"venue"
},
  "geometry": {"coordinates":[-3.0003643036,43.3089828491],"type":"Point"}
}