{
  "type": "Feature",
  "properties": {
    "iso:country":"ES",
    "sg:address":"Pase Jesuitas, 87",
    "sg:city":"Madrid",
    "sg:orig_category":"Bisuteros (fabricaci\u00d3n, Al Por Mayor)",
    "sg:phone":"+34 914 70 24 13",
    "sg:postcode":"28011",
    "sg:province":"Madrid",
    "wof:name":"Talleres Olcina E Hijos S.l.",
    "wof:placetype":"venue"
},
  "geometry": {"coordinates":[-3.7352690697,40.4065322876],"type":"Point"}
}