{
  "type": "Feature",
  "properties": {
    "addr:full":"Pg Zona Franca, 200 Barcelona Barcelona 08038",
    "addr:housenumber":"200",
    "addr:postcode":"08038",
    "addr:street":"Pg Zona Franca",
    "iso:country":"ES",
    "sg:address":"Pg Zona Franca, 200",
    "sg:city":"Barcelona",
    "sg:orig_category":"Ropa Para Se\u00d1oras Y Caballeros (al Por Menor)",
    "sg:phone":"+34 933 32 30 46",
    "sg:postcode":"08038",
    "sg:province":"Barcelona",
    "wof:name":"Martin Garcia Eduardo",
    "wof:placetype":"venue"
},
  "geometry": {"coordinates":[2.1384749413,41.361366272],"type":"Point"}
}