{
  "type": "Feature",
  "properties": {
    "iso:country":"ES",
    "sg:address":"Carr Dinamarca, 9",
    "sg:city":"Igualada",
    "sg:orig_category":"Papel (al Por Mayor)",
    "sg:phone":"+34 938 05 39 50",
    "sg:postcode":"08700",
    "sg:province":"Barcelona",
    "wof:name":"Iberica De Papel S.a.",
    "wof:placetype":"venue"
},
  "geometry": {"coordinates":[1.6295650005,41.5981407166],"type":"Point"}
}