{
  "type": "Feature",
  "properties": {
    "addr:full":"Carrer de Lepant, 258 Barcelona Barcelona 08013",
    "addr:housenumber":"258",
    "addr:postcode":"08013",
    "addr:street":"Carrer De Lepant",
    "iso:country":"ES",
    "sg:address":"Carrer de Lepant, 258",
    "sg:city":"Barcelona",
    "sg:orig_category":"Suministros Y Materiales Industriales",
    "sg:phone":"+34 932 45 38 06",
    "sg:postcode":"08013",
    "sg:province":"Barcelona",
    "wof:name":"Suministros Del Decoletaje Map S.a.",
    "wof:placetype":"venue"
},
  "geometry": {"coordinates":[2.1780838966,41.4035797119],"type":"Point"}
}