{
  "type": "Feature",
  "properties": {
    "addr:full":"Calle de Doctor Eduardo Arroyo, 7 Jaen Ja\u00e9n 23003",
    "addr:housenumber":"7;jae\u0301n",
    "addr:postcode":"23003",
    "addr:street":"Calle De Doctor Eduardo Arroyo",
    "iso:country":"ES",
    "sg:address":"Calle de Doctor Eduardo Arroyo, 7",
    "sg:city":"Jaen",
    "sg:orig_category":"Asociaciones Y Clubs Deportivos",
    "sg:phone":"+34 953 24 14 44",
    "sg:postcode":"23003",
    "sg:province":"Ja\u00e9n",
    "wof:name":"La Boutique Del Trofeo C.b.",
    "wof:placetype":"venue"
},
  "geometry": {"coordinates":[-3.790766716,37.7679443359],"type":"Point"}
}