{
  "type": "Feature",
  "properties": {
    "iso:country":"ES",
    "sg:address":"Calle de Korreo Kalea, 23",
    "sg:city":"Tolosa",
    "sg:orig_category":"Caf\u00c9s (al Por Menor)",
    "sg:phone":"+34 943 67 18 19",
    "sg:postcode":"20400",
    "sg:province":"Guip\u00f9zcoa",
    "wof:name":"Maria Pilar Urkia Aranzasti (kafetxea Egia)",
    "wof:placetype":"venue"
},
  "geometry": {"coordinates":[-2.0725851059,43.1383628845],"type":"Point"}
}