{
  "type": "Feature",
  "properties": {
    "addr:full":"Santo, S/n Jumilla Murcia 30520",
    "addr:housenumber":"s / n",
    "addr:postcode":"30520",
    "addr:street":"Santo",
    "iso:country":"ES",
    "sg:address":"Santo, S/n",
    "sg:city":"Jumilla",
    "sg:orig_category":"Mec\u00c1nico Del Autom\u00d3vil",
    "sg:phone":"+34 968 78 00 92",
    "sg:postcode":"30520",
    "sg:province":"Murcia",
    "wof:name":"Taller Mecanico Jimar C.b.",
    "wof:placetype":"venue"
},
  "geometry": {"coordinates":[-1.317407012,38.4277191162],"type":"Point"}
}