{
  "type": "Feature",
  "properties": {
    "addr:full":"Rua Regueiro, 12 Vilaboa La Coru\u00f1a 15174",
    "addr:housenumber":"12",
    "addr:postcode":"15174",
    "addr:street":"Rua Regueiro;La Corun\u0303A",
    "iso:country":"ES",
    "sg:address":"Rua Regueiro, 12",
    "sg:city":"Vilaboa",
    "sg:orig_category":"Molduras, Junquillos, Listones Y Molduras Perforadas",
    "sg:phone":"+34 981 66 22 16",
    "sg:postcode":"15174",
    "sg:province":"La Coru\u00f1a",
    "wof:name":"Longueira Varela Manuela",
    "wof:placetype":"venue"
},
  "geometry": {"coordinates":[-8.3879089355,43.3130111694],"type":"Point"}
}