{
  "type": "Feature",
  "properties": {
    "addr:full":"Calle de Santa Gema, 4 Alcorcon Madrid 28921",
    "addr:housenumber":"4",
    "addr:postcode":"28921",
    "addr:street":"Calle De Santa Gema",
    "iso:country":"ES",
    "sg:address":"Calle de Santa Gema, 4",
    "sg:city":"Alcorcon",
    "sg:orig_category":"Lencer\u00cda Femenina, Corseter\u00cda, Trajes De Ba\u00d1o (al Por Menor)",
    "sg:phone":"+34 916 43 09 29",
    "sg:postcode":"28921",
    "sg:province":"Madrid",
    "wof:name":"Quecuti Fernandez Miguel",
    "wof:placetype":"venue"
},
  "geometry": {"coordinates":[-3.8269371986,40.344997406],"type":"Point"}
}