{
  "type": "Feature",
  "properties": {
    "iso:country":"ES",
    "sg:address":"Calle de Fuentespina, 6",
    "sg:city":"Madrid",
    "sg:orig_category":"Bares, Piano",
    "sg:phone":"+34 913 32 85 59",
    "sg:postcode":"28031",
    "sg:province":"Madrid",
    "wof:name":"Francisco Martin Abad S.a.",
    "wof:placetype":"venue"
},
  "geometry": {"coordinates":[-3.6044859886,40.3802604675],"type":"Point"}
}