{
  "type": "Feature",
  "properties": {
    "iso:country":"ES",
    "sg:address":"Barr Monte La Torre, 64",
    "sg:city":"Monte",
    "sg:orig_category":"Aceites Y Grasas Alimentarias (fabricaci\u00d3n, Al Por Mayor)",
    "sg:phone":"+34 942 32 31 55",
    "sg:postcode":"39012",
    "sg:province":"Cantabria",
    "sg:website":"www.ybarra.es",
    "wof:name":"Hijos De Ybarra S. A.",
    "wof:placetype":"venue"
},
  "geometry": {"coordinates":[-3.8604888916,43.4665527344],"type":"Point"}
}