{
  "type": "Feature",
  "properties": {
    "iso:country":"ES",
    "sg:address":"Polig. Pocomaco, S/n",
    "sg:city":"A Coru\u00f1a",
    "sg:orig_category":"Electricidad: Material Y Suministros De Instalaci\u00d3n (fabricaci\u00d3n)",
    "sg:phone":"+34 981 13 76 75",
    "sg:postcode":"15190",
    "sg:province":"La Coru\u00f1a",
    "sg:website":"www.acv-world.com",
    "wof:name":"Acv Espa\u00d1a S.a.",
    "wof:placetype":"venue"
},
  "geometry": {"coordinates":[-8.4335021973,43.3301010132],"type":"Point"}
}