{
  "type": "Feature",
  "properties": {
    "addr:full":"Zinkunegi Kalea, 4 Zarautz Guip\u00f9zcoa 20800",
    "addr:housenumber":"4",
    "addr:postcode":"20800",
    "addr:street":"Zinkunegi Kalea;Guipu\u0300Zcoa",
    "iso:country":"ES",
    "sg:address":"Zinkunegi Kalea, 4",
    "sg:city":"Zarautz",
    "sg:orig_category":"Empresas De Pintura Y Revestimientos",
    "sg:phone":"+34 943 83 44 45",
    "sg:postcode":"20800",
    "sg:province":"Guip\u00f9zcoa",
    "wof:name":"Romero Benitez Pedro",
    "wof:placetype":"venue"
},
  "geometry": {"coordinates":[-2.1625680923,43.285900116],"type":"Point"}
}