{
  "type": "Feature",
  "properties": {
    "iso:country":"ES",
    "sg:address":"Calle de Ferraz, 67",
    "sg:city":"Madrid",
    "sg:orig_category":"Arquitectos",
    "sg:phone":"+34 915 44 06 85",
    "sg:postcode":"28008",
    "sg:province":"Madrid",
    "wof:name":"Martin Alcantarilla Maria Del Carmen",
    "wof:placetype":"venue"
},
  "geometry": {"coordinates":[-3.7225909233,40.4313621521],"type":"Point"}
}