{
  "type": "Feature",
  "properties": {
    "iso:country":"ES",
    "sg:address":"Calle de Urbieta, 68",
    "sg:city":"Donostia-san Sebastian",
    "sg:orig_category":"Abogados",
    "sg:phone":"+34 943 45 08 28",
    "sg:postcode":"20006",
    "sg:province":"Guip\u00f9zcoa",
    "wof:name":"Aguirre Franco Pedro",
    "wof:placetype":"venue"
},
  "geometry": {"coordinates":[-1.9803843498,43.3135070801],"type":"Point"}
}