{
  "type": "Feature",
  "properties": {
    "iso:country":"ES",
    "sg:address":"Calle de Iglesia, 35",
    "sg:city":"Lepe",
    "sg:orig_category":"Partidos Pol\u00cdticos",
    "sg:phone":"+34 959 38 24 88",
    "sg:postcode":"21440",
    "sg:province":"Huelva",
    "wof:name":"Partido Socialista Obrero Espa\u00f1ol",
    "wof:placetype":"venue"
},
  "geometry": {"coordinates":[-7.2052588463,37.25390625],"type":"Point"}
}