{
  "type": "Feature",
  "properties": {
    "iso:country":"ES",
    "sg:address":"Carrer de Sant Lluis, 4",
    "sg:city":"Deltebre",
    "sg:orig_category":"Contenedores (mercanc\u00cdas)",
    "sg:phone":"+34 977 48 93 36",
    "sg:postcode":"43580",
    "sg:province":"Tarragona",
    "wof:name":"Zaragoza Vidal Ramon",
    "wof:placetype":"venue"
},
  "geometry": {"coordinates":[0.720344007,40.7166976929],"type":"Point"}
}