{
  "type": "Feature",
  "properties": {
    "addr:full":"Alicante-cartagena, Km. 0003,0 Torrevieja Alicante 03180",
    "addr:postcode":"03180",
    "addr:street":"Alicante-Cartagena Km. 0003,0",
    "iso:country":"ES",
    "sg:address":"Alicante-cartagena, Km. 0003,0",
    "sg:city":"Torrevieja",
    "sg:orig_category":"Polideportivos",
    "sg:phone":"+34 965 71 37 01",
    "sg:postcode":"03180",
    "sg:province":"Alicante",
    "wof:name":"Ayuntamiento De Torrevieja",
    "wof:placetype":"venue"
},
  "geometry": {"coordinates":[-0.6536790133,38.0173606873],"type":"Point"}
}