{
  "type": "Feature",
  "properties": {
    "addr:full":"Calle de Presbitero Blas Marrero, 5 Santa Brigida Las Palmas 35300",
    "addr:housenumber":"5",
    "addr:postcode":"35300",
    "addr:street":"Calle De Presbitero Blas Marrero",
    "iso:country":"ES",
    "sg:address":"Calle de Presbitero Blas Marrero, 5",
    "sg:city":"Santa Brigida",
    "sg:orig_category":"Transportes Por V\u00cdas Navegables",
    "sg:phone":"+34 928 64 12 29",
    "sg:postcode":"35300",
    "sg:province":"Las Palmas",
    "wof:name":"Rodriguez Moreno Pedro Adrian",
    "wof:placetype":"venue"
},
  "geometry": {"coordinates":[-15.4991188049,28.0347061157],"type":"Point"}
}