{
  "type": "Feature",
  "properties": {
    "iso:country":"ES",
    "sg:address":"Rond Buenavista, S/n",
    "sg:city":"Toledo",
    "sg:orig_category":"Lencer\u00cda Femenina, Corseter\u00cda, Trajes De Ba\u00d1o (al Por Menor)",
    "sg:phone":"+34 925 21 64 26",
    "sg:postcode":"45005",
    "sg:province":"Toledo",
    "wof:name":"Sanchez Garcia Juan",
    "wof:placetype":"venue"
},
  "geometry": {"coordinates":[-4.0396938324,39.874370575],"type":"Point"}
}