{
  "type": "Feature",
  "properties": {
    "addr:full":"Avda Paz (la), 49 Sevilla Sevilla 41013",
    "addr:housenumber":"49",
    "addr:postcode":"41013",
    "addr:street":"Avda Paz La",
    "iso:country":"ES",
    "sg:address":"Avda Paz (la), 49",
    "sg:city":"Sevilla",
    "sg:orig_category":"Promotores Constructores",
    "sg:phone":"+34 954 29 63 18",
    "sg:postcode":"41013",
    "sg:province":"Sevilla",
    "wof:name":"C.i.s. Melchor S.l.",
    "wof:placetype":"venue"
},
  "geometry": {"coordinates":[-5.9709267616,37.3714523315],"type":"Point"}
}