{
  "type": "Feature",
  "properties": {
    "addr:full":"La Fanderia, 1 Barakaldo Vizcaya 48901",
    "addr:housenumber":"1",
    "addr:postcode":"48901",
    "addr:street":"Fanderia",
    "iso:country":"ES",
    "sg:address":"La Fanderia, 1",
    "sg:city":"Barakaldo",
    "sg:orig_category":"Producci\u00d3n, Distribuci\u00d3n De Electricidad",
    "sg:phone":"+34 944 04 73 23",
    "sg:postcode":"48901",
    "sg:province":"Vizcaya",
    "wof:name":"Energia Y Gestion Ase, S.l.",
    "wof:placetype":"venue"
},
  "geometry": {"coordinates":[-2.9858388901,43.2973098755],"type":"Point"}
}