{
  "type": "Feature",
  "properties": {
    "iso:country":"ES",
    "sg:address":"Monte Nieves, 6",
    "sg:city":"Galapagar",
    "sg:orig_category":"Servidores Y Editores De Bases De Datos",
    "sg:phone":"+34 918 59 41 18",
    "sg:postcode":"28250",
    "sg:province":"Madrid",
    "wof:name":"Computer Contact S.l.",
    "wof:placetype":"venue"
},
  "geometry": {"coordinates":[-3.958575964,40.5820007324],"type":"Point"}
}