{
  "type": "Feature",
  "properties": {
    "addr:full":"Carr Numancia, 2 Quart Poblet Valencia 46930",
    "addr:housenumber":"2",
    "addr:postcode":"46930",
    "addr:street":"Carr Numancia;Poblet",
    "iso:country":"ES",
    "sg:address":"Carr Numancia, 2",
    "sg:city":"Quart Poblet",
    "sg:orig_category":"Florister\u00cdas",
    "sg:phone":"+34 961 54 77 80",
    "sg:postcode":"46930",
    "sg:province":"Valencia",
    "wof:name":"Rubio Marin Felisa",
    "wof:placetype":"venue"
},
  "geometry": {"coordinates":[-0.4419890046,39.482711792],"type":"Point"}
}