{
  "type": "Feature",
  "properties": {
    "iso:country":"ES",
    "sg:address":"Carr Santa Anna, 47",
    "sg:city":"Estartit",
    "sg:orig_category":"Ropa Y Accesorios",
    "sg:phone":"+34 972 75 06 76",
    "sg:postcode":"17258",
    "sg:province":"Girona",
    "wof:name":"Dalmau Burgues Josefa",
    "wof:placetype":"venue"
},
  "geometry": {"coordinates":[3.1995449066,42.053730011],"type":"Point"}
}