{
  "type": "Feature",
  "properties": {
    "iso:country":"ES",
    "sg:address":"C/ Major, 7",
    "sg:city":"Alaior",
    "sg:orig_category":"Farmacias",
    "sg:phone":"+34 971 37 14 96",
    "sg:postcode":"07730",
    "sg:province":"Islas Baleares",
    "wof:name":"Pedro Y Miguel Lucas Castell C.b.",
    "wof:placetype":"venue"
},
  "geometry": {"coordinates":[4.1396307945,39.9341583252],"type":"Point"}
}