{
  "type": "Feature",
  "properties": {
    "addr:full":"Csta Olivar (del), 1 Pozuelo De Alarcon Madrid 28223",
    "addr:postcode":"28223",
    "iso:country":"ES",
    "sg:address":"Csta Olivar (del), 1",
    "sg:city":"Pozuelo De Alarcon",
    "sg:classifiers":[
        {
            "category":"Professional",
            "subcategory":"Management & Consulting",
            "type":"Services"
        }
    ],
    "sg:phone":"+34 913 51 28 56",
    "sg:postcode":"28223",
    "sg:province":"Madrid",
    "sg:tags":[
        "asesor\u00cda",
        "en",
        "marketing"
    ],
    "sg:website":"www.grupotmh.com",
    "wof:name":"The Marketing House S.l.",
    "wof:placetype":"venue"
},
  "geometry": {"coordinates":[-3.8147089481,40.43491745],"type":"Point"}
}