{
  "type": "Feature",
  "properties": {
    "addr:full":"Carrer de Cultura, 18 Hospitalet Llobregat Barcelona 08902",
    "addr:housenumber":"18",
    "addr:postcode":"08902",
    "addr:street":"Carrer De Cultura",
    "iso:country":"ES",
    "sg:address":"Carrer de Cultura, 18",
    "sg:city":"Hospitalet Llobregat",
    "sg:orig_category":"Fabricaci\u00d3n De Moldes Y Modelos",
    "sg:phone":"+34 933 31 58 62",
    "sg:postcode":"08902",
    "sg:province":"Barcelona",
    "wof:name":"Rubbermat S.l.",
    "wof:placetype":"venue"
},
  "geometry": {"coordinates":[2.1195878983,41.3664741516],"type":"Point"}
}