{
  "type": "Feature",
  "properties": {
    "iso:country":"ES",
    "sg:address":"Avda General Lopez Dominguez, 7",
    "sg:city":"Marbella",
    "sg:orig_category":"Electricidad: Instaladores",
    "sg:phone":"+34 952 77 32 50",
    "sg:postcode":"29600",
    "sg:province":"M\u00e1laga",
    "wof:name":"Electrodecor S.l.",
    "wof:placetype":"venue"
},
  "geometry": {"coordinates":[-4.8757982254,36.5113601685],"type":"Point"}
}