{
  "type": "Feature",
  "properties": {
    "iso:country":"ES",
    "sg:address":"Avda Ricardo Soriano, 36",
    "sg:city":"Marbella",
    "sg:orig_category":"Formaci\u00d3n Continuada (variada)",
    "sg:phone":"+34 952 77 48 87",
    "sg:postcode":"29600",
    "sg:province":"M\u00e1laga",
    "wof:name":"Ternero Roman Salvador",
    "wof:placetype":"venue"
},
  "geometry": {"coordinates":[-4.8912148476,36.5105857849],"type":"Point"}
}