{
  "type": "Feature",
  "properties": {
    "addr:full":"Portua, 26 Getaria Guip\u00f9zcoa 20808",
    "addr:housenumber":"26",
    "addr:postcode":"20808",
    "addr:street":"Portua;Guipu\u0300Zcoa",
    "iso:country":"ES",
    "sg:address":"Portua, 26",
    "sg:city":"Getaria",
    "sg:orig_category":"Pr\u00c1ctica De Vela, Navegaci\u00d3n Y Deportes N\u00c1uticos Y Acu\u00c1ticos",
    "sg:phone":"+34 943 58 09 59",
    "sg:postcode":"20808",
    "sg:province":"Guip\u00f9zcoa",
    "wof:name":"Euskadiko Kirol Portua S.a",
    "wof:placetype":"venue"
},
  "geometry": {"coordinates":[-2.2049660683,43.3031158447],"type":"Point"}
}