{
  "type": "Feature",
  "properties": {
    "addr:full":"Plaz Espa\u00d1a (de), 6 Conil De La Frontera C\u00e1diz 11140",
    "addr:postcode":"11140",
    "addr:street":"Plaz",
    "iso:country":"ES",
    "sg:address":"Plaz Espa\u00d1a (de), 6",
    "sg:city":"Conil De La Frontera",
    "sg:orig_category":"Molduras, Junquillos, Listones Y Molduras Perforadas",
    "sg:phone":"+34 956 44 10 53",
    "sg:postcode":"11140",
    "sg:province":"C\u00e1diz",
    "wof:name":"Ramos Medina Manuel",
    "wof:placetype":"venue"
},
  "geometry": {"coordinates":[-6.0880570412,36.2754936218],"type":"Point"}
}