{
  "type": "Feature",
  "properties": {
    "addr:full":"Av Diagonal, 410 Barcelona Barcelona 08037",
    "addr:housenumber":"410",
    "addr:postcode":"08037",
    "addr:street":"Av Diagonal",
    "iso:country":"ES",
    "sg:address":"Av Diagonal, 410",
    "sg:city":"Barcelona",
    "sg:orig_category":"Cl\u00cdnicas M\u00c9dicas",
    "sg:phone":"+34 932 08 08 10",
    "sg:postcode":"08037",
    "sg:province":"Barcelona",
    "wof:name":"Clinicum Seguros S.a.",
    "wof:placetype":"venue"
},
  "geometry": {"coordinates":[2.1652190685,41.3982582092],"type":"Point"}
}