{
  "type": "Feature",
  "properties": {
    "iso:country":"ES",
    "sg:address":"Calle de Obispo Rabadan, 46",
    "sg:city":"Palmas De Gran Canaria",
    "sg:orig_category":"Promotores Constructores",
    "sg:phone":"+34 928 36 48 04",
    "sg:postcode":"35003",
    "sg:province":"Las Palmas",
    "wof:name":"Lufepi S.l.",
    "wof:placetype":"venue"
},
  "geometry": {"coordinates":[-15.4210767746,28.1117172241],"type":"Point"}
}