{
  "type": "Feature",
  "properties": {
    "iso:country":"ES",
    "sg:address":"Sealo, 5",
    "sg:city":"Lampon",
    "sg:orig_category":"Estudios Y Construcci\u00d3n De Acuarios Y Viveros",
    "sg:phone":"+34 981 84 67 10",
    "sg:postcode":"15992",
    "sg:province":"La Coru\u00f1a",
    "wof:name":"Dean Sampedro Manuel",
    "wof:placetype":"venue"
},
  "geometry": {"coordinates":[-8.9047136307,42.6364364624],"type":"Point"}
}