{
  "type": "Feature",
  "properties": {
    "addr:full":"Urb Villas Blancas, 10 Salteras Sevilla 41909",
    "addr:housenumber":"10",
    "addr:postcode":"41909",
    "addr:street":"Urb Villas Blancas",
    "iso:country":"ES",
    "sg:address":"Urb Villas Blancas, 10",
    "sg:city":"Salteras",
    "sg:orig_category":"Empresas De Labores Complejas De Carga Y Descarga, Montaje Con Elevadores",
    "sg:phone":"+34 955 70 83 74",
    "sg:postcode":"41909",
    "sg:province":"Sevilla",
    "wof:name":"Cenital S.c.",
    "wof:placetype":"venue"
},
  "geometry": {"coordinates":[-6.1071691513,37.4179992676],"type":"Point"}
}