{
  "type": "Feature",
  "properties": {
    "iso:country":"ES",
    "sg:address":"Calle de Tetuan, 7",
    "sg:city":"Sevilla",
    "sg:orig_category":"Estilistas Y Estudios De Estilo De Corte Y Confecci\u00d3n",
    "sg:phone":"+34 954 21 34 21",
    "sg:postcode":"41001",
    "sg:province":"Sevilla",
    "wof:name":"Gonzalez Rodriguez Tomas",
    "wof:placetype":"venue"
},
  "geometry": {"coordinates":[-5.9951190948,37.3900794983],"type":"Point"}
}