{
  "type": "Feature",
  "properties": {
    "addr:full":"Calle de Padilla, 26 Madrid Madrid 28006",
    "addr:housenumber":"26",
    "addr:postcode":"madrid;28006",
    "addr:street":"Calle De Padilla",
    "iso:country":"ES",
    "sg:address":"Calle de Padilla, 26",
    "sg:city":"Madrid",
    "sg:orig_category":"Promotores Constructores",
    "sg:phone":"+34 915 75 80 19",
    "sg:postcode":"28006",
    "sg:province":"Madrid",
    "wof:name":"Arcxigu S.l.",
    "wof:placetype":"venue"
},
  "geometry": {"coordinates":[-3.683110714,40.43151474],"type":"Point"}
}