{
  "type": "Feature",
  "properties": {
    "addr:full":"Avda Paseo De Almeria, 14 Almeria Almer\u00eda 04001",
    "addr:housenumber":"14",
    "addr:postcode":"04001",
    "addr:street":"Avda Paseo De Almeria",
    "iso:country":"ES",
    "sg:address":"Avda Paseo De Almeria, 14",
    "sg:city":"Almeria",
    "sg:orig_category":"M\u00c9dicos: Oftalmolog\u00cda",
    "sg:phone":"+34 950 23 01 52",
    "sg:postcode":"04001",
    "sg:province":"Almer\u00eda",
    "wof:name":"Juarez Arraez Arsenio",
    "wof:placetype":"venue"
},
  "geometry": {"coordinates":[-2.4608390331,36.8422698975],"type":"Point"}
}