{
  "type": "Feature",
  "properties": {
    "iso:country":"ES",
    "sg:address":"Calle de Tiendas Las, 15",
    "sg:city":"Ronda",
    "sg:orig_category":"Abogados",
    "sg:phone":"+34 952 87 07 52",
    "sg:postcode":"29400",
    "sg:province":"M\u00e1laga",
    "wof:name":"Herrera Raquejo Jose",
    "wof:placetype":"venue"
},
  "geometry": {"coordinates":[-5.1644592285,36.74243927],"type":"Point"}
}