{
  "type": "Feature",
  "properties": {
    "addr:full":"Calle de Virgen Del Campo, 6 Covaleda Soria 42157",
    "addr:housenumber":"6",
    "addr:postcode":"42157",
    "addr:street":"Calle De Virgen Del Campo",
    "iso:country":"ES",
    "sg:address":"Calle de Virgen Del Campo, 6",
    "sg:city":"Covaleda",
    "sg:orig_category":"Peluquer\u00cdas, Peluquer\u00cda Mixta",
    "sg:phone":"+34 975 37 01 44",
    "sg:postcode":"42157",
    "sg:province":"Soria",
    "wof:name":"Herrero Garcia Blanca",
    "wof:placetype":"venue"
},
  "geometry": {"coordinates":[-2.8812439442,41.9344558716],"type":"Point"}
}