{
  "type": "Feature",
  "properties": {
    "iso:country":"ES",
    "sg:address":"Pg Germanies (de Les), 77",
    "sg:city":"Gandia",
    "sg:orig_category":"Droguer\u00cdas (al Por Menor)",
    "sg:phone":"+34 962 87 77 58",
    "sg:postcode":"46700",
    "sg:province":"Valencia",
    "wof:name":"Gregori Morillo Salvador",
    "wof:placetype":"venue"
},
  "geometry": {"coordinates":[-0.1909929961,38.966709137],"type":"Point"}
}