{
  "type": "Feature",
  "properties": {
    "iso:country":"ES",
    "sg:address":"Avda Logro\u00d1o, 118",
    "sg:city":"Madrid",
    "sg:orig_category":"Perfumer\u00cda (al Por Menor)",
    "sg:phone":"+34 913 29 31 70",
    "sg:postcode":"28042",
    "sg:province":"Madrid",
    "wof:name":"Guijarro Garcia Pilar",
    "wof:placetype":"venue"
},
  "geometry": {"coordinates":[-3.5815315247,40.4714393616],"type":"Point"}
}