{
  "type": "Feature",
  "properties": {
    "iso:country":"ES",
    "sg:address":"Pg Joan Borbo Comte Barcelo, 12",
    "sg:city":"Barcelona",
    "sg:orig_category":"Molduras, Junquillos, Listones Y Molduras Perforadas",
    "sg:phone":"+34 932 21 28 58",
    "sg:postcode":"08003",
    "sg:province":"Barcelona",
    "wof:name":"Grupo Mart & Mart Rerstauracion S.l.",
    "wof:placetype":"venue"
},
  "geometry": {"coordinates":[2.1872448921,41.3797111511],"type":"Point"}
}