{
  "type": "Feature",
  "properties": {
    "iso:country":"ES",
    "sg:address":"Calle de Foso (del), 122",
    "sg:city":"Aranjuez",
    "sg:orig_category":"Empresas De Vigilancia, Guardia Y Protecci\u00d3n",
    "sg:phone":"+34 918 75 40 05",
    "sg:postcode":"28300",
    "sg:province":"Madrid",
    "wof:name":"Real Sitio Gestion Patrimonial S.l.",
    "wof:placetype":"venue"
},
  "geometry": {"coordinates":[-3.5986309052,40.0299491882],"type":"Point"}
}