{
  "type": "Feature",
  "properties": {
    "addr:full":"Calle de Pedralba, 170 Benaguasil Valencia 46180",
    "addr:housenumber":"170",
    "addr:postcode":"46180",
    "addr:street":"Calle De Pedralba",
    "iso:country":"ES",
    "sg:address":"Calle de Pedralba, 170",
    "sg:city":"Benaguasil",
    "sg:orig_category":"Empresas De Carpinter\u00cda",
    "sg:phone":"+34 962 73 75 17",
    "sg:postcode":"46180",
    "sg:province":"Valencia",
    "wof:name":"Lopez Falomir Salvador",
    "wof:placetype":"venue"
},
  "geometry": {"coordinates":[-0.5898923278,39.5959129333],"type":"Point"}
}