{
  "type": "Feature",
  "properties": {
    "addr:full":"Carr Roca Llisa, Sa, 26 Portol Islas Baleares 07141",
    "addr:housenumber":"26",
    "addr:postcode":"07141",
    "addr:street":"Carr Roca Llisa Sa;Islas",
    "iso:country":"ES",
    "sg:address":"Carr Roca Llisa, Sa, 26",
    "sg:city":"Portol",
    "sg:orig_category":"Alfarer\u00cda",
    "sg:phone":"+34 971 60 27 04",
    "sg:postcode":"07141",
    "sg:province":"Islas Baleares",
    "wof:name":"Serra Amengual Jose",
    "wof:placetype":"venue"
},
  "geometry": {"coordinates":[2.741590023,39.6156005859],"type":"Point"}
}