{
  "type": "Feature",
  "properties": {
    "addr:full":"Carrer de Anoia, 9 S. Andreu Barca Barcelona 08740",
    "addr:housenumber":"9",
    "addr:postcode":"08740",
    "addr:street":"Carrer De Anoia;S. Andreu;Barcelona",
    "iso:country":"ES",
    "sg:address":"Carrer de Anoia, 9",
    "sg:city":"S. Andreu Barca",
    "sg:orig_category":"Agencias Y Asesores De Publicidad",
    "sg:phone":"+34 936 53 32 78",
    "sg:postcode":"08740",
    "sg:province":"Barcelona",
    "wof:name":"Cabello Rodriguez Francisco",
    "wof:placetype":"venue"
},
  "geometry": {"coordinates":[1.9679349661,41.4509544373],"type":"Point"}
}