{
  "type": "Feature",
  "properties": {
    "iso:country":"ES",
    "sg:address":"Calle de Castelar, 12",
    "sg:city":"Almeria",
    "sg:orig_category":"Zapater\u00cdas",
    "sg:phone":"+34 950 23 48 85",
    "sg:postcode":"04001",
    "sg:province":"Almer\u00eda",
    "wof:name":"Calzados Miguel C.b.",
    "wof:placetype":"venue"
},
  "geometry": {"coordinates":[-2.4647169113,36.8402481079],"type":"Point"}
}