{
  "type": "Feature",
  "properties": {
    "iso:country":"ES",
    "sg:address":"Ctra Lorca (de), 9",
    "sg:city":"Pinilla",
    "sg:orig_category":"Producci\u00d3n, Comercio De Cereales",
    "sg:phone":"+34 968 70 41 22",
    "sg:postcode":"30410",
    "sg:province":"Murcia",
    "wof:name":"Cereales Arias S.l.",
    "wof:placetype":"venue"
},
  "geometry": {"coordinates":[-1.9453239441,38.0200157166],"type":"Point"}
}