{
  "type": "Feature",
  "properties": {
    "iso:country":"ES",
    "sg:address":"Ctra Torrelles, 44",
    "sg:city":"Sant Vicen\u00c7 Dels Horts",
    "sg:orig_category":"Juguetes Y Juegos (al Por Mayor)",
    "sg:phone":"+34 936 56 71 70",
    "sg:postcode":"08620",
    "sg:province":"Barcelona",
    "sg:website":"www.barradopeluches.com",
    "wof:name":"Barrado Import-export S.l.",
    "wof:placetype":"venue"
},
  "geometry": {"coordinates":[1.9929020405,41.3786888123],"type":"Point"}
}