{
  "type": "Feature",
  "properties": {
    "iso:country":"ES",
    "sg:address":"Calle de Pintor Aparicio, 38",
    "sg:city":"Alacant",
    "sg:orig_category":"Ense\u00d1anza Variada",
    "sg:phone":"+34 965 12 13 61",
    "sg:postcode":"03003",
    "sg:province":"Alicante",
    "sg:website":"www.escriturasnotariales.com",
    "wof:name":"Centro De Formacion De Empleados De Notaria S L",
    "wof:placetype":"venue"
},
  "geometry": {"coordinates":[-0.4921979904,38.3428649902],"type":"Point"}
}