{
  "type": "Feature",
  "properties": {
    "iso:country":"ES",
    "sg:address":"Muelle, S/n",
    "sg:city":"Burela",
    "sg:classifiers":[
        {
            "category":"Manufacturing",
            "subcategory":"Building Materials",
            "type":"Manufacturing & Wholesale Goods"
        }
    ],
    "sg:phone":"+34 982 58 04 12",
    "sg:postcode":"27880",
    "sg:province":"Lugo",
    "sg:tags":[
        "cemento",
        "y",
        "de",
        "fabricaci\u00d3n",
        "cal"
    ],
    "wof:name":"Tudela Veguin S.a.",
    "wof:placetype":"venue"
},
  "geometry": {"coordinates":[-7.3604969978,43.658657074],"type":"Point"}
}