{
  "type": "Feature",
  "properties": {
    "addr:full":"C/ Pont De Sant Jordi, 1 Alcoi Alicante 03803",
    "addr:housenumber":"1",
    "addr:postcode":"03803",
    "addr:street":"C / Pont De Sant Jordi",
    "iso:country":"ES",
    "sg:address":"C/ Pont De Sant Jordi, 1",
    "sg:city":"Alcoi",
    "sg:orig_category":"Hoteles",
    "sg:phone":"+34 965 33 09 00",
    "sg:postcode":"03803",
    "sg:province":"Alicante",
    "wof:name":"Reconquista Hotel S.l.",
    "wof:placetype":"venue"
},
  "geometry": {"coordinates":[-0.4732739925,38.6984100342],"type":"Point"}
}