{
  "type": "Feature",
  "properties": {
    "addr:full":"Calle de Ascao, 31 Madrid Madrid 28017",
    "addr:housenumber":"31",
    "addr:postcode":"madrid;28017",
    "addr:street":"Calle De Ascao",
    "iso:country":"ES",
    "sg:address":"Calle de Ascao, 31",
    "sg:city":"Madrid",
    "sg:orig_category":"Frutas, Legumbres Frescas Y Tempranas (al Por Menor)",
    "sg:phone":"+34 914 07 24 82",
    "sg:postcode":"28017",
    "sg:province":"Madrid",
    "wof:name":"Autoservicio De La Fruta S.r.l.",
    "wof:placetype":"venue"
},
  "geometry": {"coordinates":[-3.6407105923,40.430305481],"type":"Point"}
}