{
  "type": "Feature",
  "properties": {
    "iso:country":"ES",
    "sg:address":"Naranjo, 25",
    "sg:city":"Pontevedra",
    "sg:orig_category":"Peluqueros: De Se\u00d1oras",
    "sg:phone":"+34 986 85 53 84",
    "sg:postcode":"36002",
    "sg:province":"Pontevedra",
    "wof:name":"Fernandez Taboada Rosa",
    "wof:placetype":"venue"
},
  "geometry": {"coordinates":[-8.6431245804,42.4322128296],"type":"Point"}
}