{
  "type": "Feature",
  "properties": {
    "iso:country":"ES",
    "sg:address":"Calle de Fotografos Darblade, 13",
    "sg:city":"Torrevieja",
    "sg:orig_category":"M\u00c9dicos: Estomatolog\u00cda",
    "sg:phone":"+34 965 71 15 36",
    "sg:postcode":"03180",
    "sg:province":"Alicante",
    "wof:name":"Chapapria Moreno Jose Julian",
    "wof:placetype":"venue"
},
  "geometry": {"coordinates":[-0.6536790133,38.0173606873],"type":"Point"}
}