{
  "type": "Feature",
  "properties": {
    "addr:full":"Pla\u00c7 Maestro Palau, 17 Moncada Valencia 46113",
    "addr:housenumber":"17",
    "addr:postcode":"46113",
    "addr:street":"Maestro Palau",
    "iso:country":"ES",
    "sg:address":"Pla\u00c7 Maestro Palau, 17",
    "sg:city":"Moncada",
    "sg:orig_category":"Asesor\u00cda Sobre Comunicaci\u00d3n De Empresas",
    "sg:phone":"+34 961 30 10 51",
    "sg:postcode":"46113",
    "sg:province":"Valencia",
    "wof:name":"Promocion Economica De Moncada S.a.",
    "wof:placetype":"venue"
},
  "geometry": {"coordinates":[-0.3919990063,39.5453605652],"type":"Point"}
}