{
  "type": "Feature",
  "properties": {
    "iso:country":"ES",
    "sg:address":"Calle de Ferrocarril (del), 33",
    "sg:city":"Coslada",
    "sg:orig_category":"Fabricaci\u00d3n De Juguetes Autom\u00c1ticos",
    "sg:phone":"+34 916 69 44 68",
    "sg:postcode":"28820",
    "sg:province":"Madrid",
    "wof:name":"Super Pik S.l.",
    "wof:placetype":"venue"
},
  "geometry": {"coordinates":[-3.5342590809,40.4431419373],"type":"Point"}
}