{
  "type": "Feature",
  "properties": {
    "addr:full":"Avda Industria (de La), 10 Fuenlabrada Madrid 28947",
    "addr:housenumber":"10",
    "addr:postcode":"28947",
    "addr:street":"Avda Industria De La",
    "iso:country":"ES",
    "sg:address":"Avda Industria (de La), 10",
    "sg:city":"Fuenlabrada",
    "sg:orig_category":"Mec\u00c1nico Del Autom\u00d3vil",
    "sg:phone":"+34 916 65 48 80",
    "sg:postcode":"28947",
    "sg:province":"Madrid",
    "wof:name":"Industrias Auxiliares Cimar S.a.",
    "wof:placetype":"venue"
},
  "geometry": {"coordinates":[-3.7609770298,40.2705574036],"type":"Point"}
}