{
  "type": "Feature",
  "properties": {
    "iso:country":"ES",
    "sg:address":"Carrer de D Bilbao, 15",
    "sg:city":"Ametlla Mar",
    "sg:orig_category":"Maquinaria Para Industrias Diversas",
    "sg:phone":"+34 977 45 62 06",
    "sg:postcode":"43860",
    "sg:province":"Tarragona",
    "wof:name":"Gil Balfego Vicente",
    "wof:placetype":"venue"
},
  "geometry": {"coordinates":[0.7992730141,40.8853607178],"type":"Point"}
}