{
  "type": "Feature",
  "properties": {
    "iso:country":"ES",
    "sg:address":"Avda Region Murciana, 128",
    "sg:city":"Carril De La Enera",
    "sg:orig_category":"Pintura, Barniz, Productos Asimilables (fabricaci\u00d3n, Al Por Mayor)",
    "sg:phone":"+34 968 34 43 10",
    "sg:postcode":"30011",
    "sg:province":"Murcia",
    "wof:name":"Pinturas Piresa S.l.",
    "wof:placetype":"venue"
},
  "geometry": {"coordinates":[-1.100391984,37.9817810059],"type":"Point"}
}