{
  "type": "Feature",
  "properties": {
    "iso:country":"ES",
    "sg:address":"J Romero De Torres, 31",
    "sg:city":"Deltebre",
    "sg:classifiers":[
        {
            "category":"Retail",
            "subcategory":"Event Space",
            "type":"Services"
        }
    ],
    "sg:phone":"+34 977 48 10 50",
    "sg:postcode":"43580",
    "sg:province":"Tarragona",
    "sg:tags":[
        "planchas",
        "surf",
        "alquiler",
        "de",
        "vela",
        "kayak",
        "barcos",
        "canoes",
        "y"
    ],
    "sg:website":"www.pescaebro.com",
    "wof:name":"Navarro Callau Enrique",
    "wof:placetype":"venue"
},
  "geometry": {"coordinates":[0.7014930248,40.7214126587],"type":"Point"}
}