{
  "type": "Feature",
  "properties": {
    "addr:full":"Ctra Villaverde A Vallecas, 1 Madrid Madrid 28...",
    "addr:housenumber":"1;28 ...",
    "addr:street":"Ctra Villaverde A Vallecas;Madrid",
    "iso:country":"ES",
    "sg:address":"Ctra Villaverde A Vallecas, 1",
    "sg:city":"Madrid",
    "sg:orig_category":"Contenedores (mercanc\u00cdas)",
    "sg:phone":"+34 913 48 96 00",
    "sg:postcode":"28...",
    "sg:province":"Madrid",
    "wof:name":"Chronoexpres S.a.",
    "wof:placetype":"venue"
},
  "geometry": {"coordinates":[-3.6283049583,40.3785057068],"type":"Point"}
}