{
  "type": "Feature",
  "properties": {
    "addr:full":"Calle de Real, 48 Carrion Calatrava Ciudad Real 13150",
    "addr:housenumber":"48",
    "addr:postcode":"13150",
    "addr:street":"Calle De Real",
    "iso:country":"ES",
    "sg:address":"Calle de Real, 48",
    "sg:city":"Carrion Calatrava",
    "sg:orig_category":"Electricidad, Electr\u00d3nica: Material Y Suministros (al Por Mayor)",
    "sg:phone":"+34 926 81 41 88",
    "sg:postcode":"13150",
    "sg:province":"Ciudad Real",
    "wof:name":"Sei Ciudad Real S.l.",
    "wof:placetype":"venue"
},
  "geometry": {"coordinates":[-3.8223459721,39.0155029297],"type":"Point"}
}