{
  "type": "Feature",
  "properties": {
    "addr:full":"Calle de Soldados (los), 5 Palencia Palencia 34001",
    "addr:postcode":"34001",
    "addr:street":"Calle De Soldados Los",
    "iso:country":"ES",
    "sg:address":"Calle de Soldados (los), 5",
    "sg:city":"Palencia",
    "sg:orig_category":"Tintorer\u00cdas, Limpieza En Seco",
    "sg:phone":"+34 979 74 46 17",
    "sg:postcode":"34001",
    "sg:province":"Palencia",
    "sg:website":"www.paginasamarillas.es",
    "wof:name":"Lozano Perez Luis Javier",
    "wof:placetype":"venue"
},
  "geometry": {"coordinates":[-4.5331549644,42.0126495361],"type":"Point"}
}