{
  "type": "Feature",
  "properties": {
    "addr:full":"Avda Paz (de La), 27 Burgos Burgos 09004",
    "addr:housenumber":"27",
    "addr:postcode":"09004",
    "addr:street":"Avda Paz De La",
    "iso:country":"ES",
    "sg:address":"Avda Paz (de La), 27",
    "sg:city":"Burgos",
    "sg:orig_category":"Cl\u00cdnicas Dentales",
    "sg:phone":"+34 947 24 47 77",
    "sg:postcode":"09004",
    "sg:province":"Burgos",
    "wof:name":"Centro Dental Virgen Del Manzano",
    "wof:placetype":"venue"
},
  "geometry": {"coordinates":[-3.6909658909,42.3455352783],"type":"Point"}
}