{
  "type": "Feature",
  "properties": {
    "iso:country":"ES",
    "sg:address":"Calle de Gutenberg, S/n",
    "sg:city":"Malaga",
    "sg:orig_category":"M\u00c9dicos: Ginecolog\u00cda Y Obstetricia",
    "sg:phone":"+34 952 60 13 86",
    "sg:postcode":"29016",
    "sg:province":"M\u00e1laga",
    "sg:website":"www.centrogutenberg.com",
    "wof:name":"Azumendi Perez Alejandro",
    "wof:placetype":"venue"
},
  "geometry": {"coordinates":[-4.4055290222,36.7212562561],"type":"Point"}
}