{
  "type": "Feature",
  "properties": {
    "addr:full":"Calle de Autonomia, 55 Bilbao Vizcaya 48012",
    "addr:housenumber":"55",
    "addr:postcode":"48012",
    "addr:street":"Calle De Autonomia",
    "iso:country":"ES",
    "sg:address":"Calle de Autonomia, 55",
    "sg:city":"Bilbao",
    "sg:orig_category":"Zapatos (al Por Menor)",
    "sg:phone":"+34 944 27 07 37",
    "sg:postcode":"48012",
    "sg:province":"Vizcaya",
    "wof:name":"Zubiri Otazua Osane",
    "wof:placetype":"venue"
},
  "geometry": {"coordinates":[-2.9459490776,43.2577705383],"type":"Point"}
}