{
  "type": "Feature",
  "properties": {
    "addr:full":"Calle de Comandante Diaz Trayter, 120 Pto. Rosario Las Palmas 35600",
    "addr:housenumber":"120",
    "addr:postcode":"35600",
    "addr:street":"Calle De Comandante Diaz Trayter;Pto. Rosario Las",
    "iso:country":"ES",
    "sg:address":"Calle de Comandante Diaz Trayter, 120",
    "sg:city":"Pto. Rosario",
    "sg:orig_category":"Fabricaci\u00d3n De Muebles",
    "sg:phone":"+34 928 85 08 39",
    "sg:postcode":"35600",
    "sg:province":"Las Palmas",
    "wof:name":"Muebles Gonzalez Gordillo S. L.",
    "wof:placetype":"venue"
},
  "geometry": {"coordinates":[-13.8488988876,28.502368927],"type":"Point"}
}