{
  "type": "Feature",
  "properties": {
    "iso:country":"ES",
    "sg:address":"Av Doctor Francesc Massana, 18",
    "sg:city":"Martorell",
    "sg:orig_category":"Alimentaci\u00d3n General (al Por Menor)",
    "sg:phone":"+34 937 75 48 07",
    "sg:postcode":"08760",
    "sg:province":"Barcelona",
    "wof:name":"Tobella Hernan Carlos",
    "wof:placetype":"venue"
},
  "geometry": {"coordinates":[1.918135047,41.4783172607],"type":"Point"}
}