{
  "type": "Feature",
  "properties": {
    "addr:full":"Calle de San Antonio De Padua, 1 Cordoba C\u00f3rdoba 14001",
    "addr:housenumber":"1",
    "addr:postcode":"14001",
    "addr:street":"Calle De San Antonio;Padua;Co\u0301Rdoba",
    "iso:country":"ES",
    "sg:address":"Calle de San Antonio De Padua, 1",
    "sg:city":"Cordoba",
    "sg:orig_category":"M\u00c9dicos: Medicina General Orientada A La Homeopat\u00cda",
    "sg:phone":"+34 957 41 08 74",
    "sg:postcode":"14001",
    "sg:province":"C\u00f3rdoba",
    "wof:name":"Cardador Moreno Tomas",
    "wof:placetype":"venue"
},
  "geometry": {"coordinates":[-4.7717170715,37.8924446106],"type":"Point"}
}