{
  "type": "Feature",
  "properties": {
    "addr:full":"Calle de Santa Ursula Calle, 19 Murcia Murcia 30002",
    "addr:postcode":"30002",
    "addr:street":"Calle De;Calle 19",
    "iso:country":"ES",
    "sg:address":"Calle de Santa Ursula Calle, 19",
    "sg:city":"Murcia",
    "sg:orig_category":"Administradores De Bienes Y Delegados De Comunidades De Propietarios",
    "sg:phone":"+34 968 34 11 10",
    "sg:postcode":"30002",
    "sg:province":"Murcia",
    "sg:website":"www.ag-asesores.com",
    "wof:name":"Ag Asesores Y Gestion De Fincas S.l",
    "wof:placetype":"venue"
},
  "geometry": {"coordinates":[-1.131704092,37.9770088196],"type":"Point"}
}