{
  "type": "Feature",
  "properties": {
    "addr:full":"Carrer de Lepant, 415 Barcelona Barcelona 08025",
    "addr:housenumber":"415",
    "addr:postcode":"08025",
    "addr:street":"Carrer De Lepant",
    "iso:country":"ES",
    "sg:address":"Carrer de Lepant, 415",
    "sg:city":"Barcelona",
    "sg:orig_category":"Cr\u00cda De Animales",
    "sg:phone":"+34 934 56 81 55",
    "sg:postcode":"08025",
    "sg:province":"Barcelona",
    "wof:name":"Bonamusa Sanjaume Maria Carmen",
    "wof:placetype":"venue"
},
  "geometry": {"coordinates":[2.1666851044,41.411907196],"type":"Point"}
}