{
  "type": "Feature",
  "properties": {
    "iso:country":"ES",
    "sg:address":"Carrer de Guillem Tell, 21",
    "sg:city":"Barcelona",
    "sg:orig_category":"Negocio De Madera",
    "sg:phone":"+34 932 17 51 96",
    "sg:postcode":"08006",
    "sg:province":"Barcelona",
    "wof:name":"Chinebro S.l.",
    "wof:placetype":"venue"
},
  "geometry": {"coordinates":[2.1489760876,41.4025726318],"type":"Point"}
}