{
  "type": "Feature",
  "properties": {
    "addr:full":"Calle de Doctor Jaime Marcos, 3 Sevilla Sevilla 41009",
    "addr:housenumber":"3",
    "addr:postcode":"41009",
    "addr:street":"Calle De Doctor Jaime Marcos",
    "iso:country":"ES",
    "sg:address":"Calle de Doctor Jaime Marcos, 3",
    "sg:city":"Sevilla",
    "sg:classifiers":[
        {
            "category":"Personal",
            "subcategory":"Barber",
            "type":"Services"
        }
    ],
    "sg:phone":"+34 954 37 62 56",
    "sg:postcode":"41009",
    "sg:province":"Sevilla",
    "sg:tags":[
        "caballeros",
        "de",
        "peluqueros"
    ],
    "wof:name":"Castillo Santa Antonio",
    "wof:placetype":"venue"
},
  "geometry": {"coordinates":[-5.9837217331,37.4096298218],"type":"Point"}
}