{
  "type": "Feature",
  "properties": {
    "addr:full":"Carrer de Sant Sever, 1 Barcelona Barcelona 08002",
    "addr:housenumber":"1",
    "addr:postcode":"08002",
    "addr:street":"Carrer De Sant Sever",
    "iso:country":"ES",
    "sg:address":"Carrer de Sant Sever, 1",
    "sg:city":"Barcelona",
    "sg:orig_category":"Ropa Para Se\u00d1oras (al Por Menor)",
    "sg:phone":"+34 933 18 81 77",
    "sg:postcode":"08002",
    "sg:province":"Barcelona",
    "wof:name":"Recherche Anatomies Fondamentalement Artistiques S.l.",
    "wof:placetype":"venue"
},
  "geometry": {"coordinates":[2.1751630306,41.3830032349],"type":"Point"}
}