{
  "type": "Feature",
  "properties": {
    "iso:country":"ES",
    "sg:address":"Rua San Isidro Labrador, 5",
    "sg:city":"Lugo",
    "sg:orig_category":"Venta, Colocaci\u00d3n, Reparaci\u00d3n De Parabrisas, Techos Descapotables",
    "sg:phone":"+34 982 20 16 42",
    "sg:postcode":"27003",
    "sg:province":"Lugo",
    "wof:name":"Auto Arte S.a.",
    "wof:placetype":"venue"
},
  "geometry": {"coordinates":[-7.5672502518,43.0240783691],"type":"Point"}
}