{
  "type": "Feature",
  "properties": {
    "addr:full":"Carrer de Alt De Gironella, 14 Barcelona Barcelona 08017",
    "addr:housenumber":"14",
    "addr:postcode":"08017",
    "addr:street":"Carrer De Alt De Gironella",
    "iso:country":"ES",
    "sg:address":"Carrer de Alt De Gironella, 14",
    "sg:city":"Barcelona",
    "sg:orig_category":"Artesan\u00cda",
    "sg:phone":"+34 932 03 27 79",
    "sg:postcode":"08017",
    "sg:province":"Barcelona",
    "wof:name":"Ferrot Productes I Produccions S.l.",
    "wof:placetype":"venue"
},
  "geometry": {"coordinates":[2.1303648949,41.3947944641],"type":"Point"}
}