{
  "type": "Feature",
  "properties": {
    "addr:full":"Pg Gran Passeig Ronda, 42 Lleida Lleida 25003",
    "addr:housenumber":"42",
    "addr:postcode":"25003",
    "addr:street":"Pg Gran Passeig Ronda",
    "iso:country":"ES",
    "sg:address":"Pg Gran Passeig Ronda, 42",
    "sg:city":"Lleida",
    "sg:orig_category":"Cajas De Ahorro",
    "sg:phone":"+34 973 26 16 09",
    "sg:postcode":"25003",
    "sg:province":"Lleida",
    "sg:website":"www.caixatarragona.es",
    "wof:name":"Caixa D'estalvis De Tarragona",
    "wof:placetype":"venue"
},
  "geometry": {"coordinates":[0.6135479808,41.6137809753],"type":"Point"}
}