{
  "type": "Feature",
  "properties": {
    "addr:full":"Calle de Alonso Barba, 26 Lepe Huelva 21440",
    "addr:housenumber":"26",
    "addr:postcode":"21440",
    "addr:street":"Calle De Alonso Barba",
    "iso:country":"ES",
    "sg:address":"Calle de Alonso Barba, 26",
    "sg:city":"Lepe",
    "sg:orig_category":"M\u00c9dicos: Estomatolog\u00cda",
    "sg:phone":"+34 959 38 34 40",
    "sg:postcode":"21440",
    "sg:province":"Huelva",
    "wof:name":"Quintana Manrique Raquel",
    "wof:placetype":"venue"
},
  "geometry": {"coordinates":[-7.2052278519,37.2547149658],"type":"Point"}
}