{
  "type": "Feature",
  "properties": {
    "iso:country":"ES",
    "sg:address":"Calle de Luis Doreste Silva, 16",
    "sg:city":"Palmas De Gran Canaria",
    "sg:orig_category":"Refiner\u00cdas De Petr\u00d3leo",
    "sg:phone":"+34 928 24 41 45",
    "sg:postcode":"35004",
    "sg:province":"Las Palmas",
    "wof:name":"Asociacion De Concesionarios De Combustibles",
    "wof:placetype":"venue"
},
  "geometry": {"coordinates":[-15.4202280045,28.1149368286],"type":"Point"}
}