{
  "type": "Feature",
  "properties": {
    "iso:country":"ES",
    "sg:address":"Avda Papa Luna, 37",
    "sg:city":"Pe\u00f1iscola",
    "sg:orig_category":"Inmobiliaria (agencias)",
    "sg:phone":"+34 964 46 75 45",
    "sg:postcode":"12598",
    "sg:province":"Castell\u00f3n",
    "wof:name":"Construcciones Y Gestion Inmobiliaria Tomas Castello S.l.",
    "wof:placetype":"venue"
},
  "geometry": {"coordinates":[0.4056699872,40.3735542297],"type":"Point"}
}