{
  "type": "Feature",
  "properties": {
    "iso:country":"ES",
    "sg:address":"Avda Extremadura, 86",
    "sg:city":"Losar Vera",
    "sg:orig_category":"Material Y Herramientas Agr\u00cdcolas",
    "sg:phone":"+34 927 57 08 46",
    "sg:postcode":"10460",
    "sg:province":"C\u00e1ceres",
    "wof:name":"Moeferpa S.l.",
    "wof:placetype":"venue"
},
  "geometry": {"coordinates":[-5.6094250679,40.1218147278],"type":"Point"}
}