{
  "type": "Feature",
  "properties": {
    "iso:country":"ES",
    "sg:address":"Calle de Foglietti, 2",
    "sg:city":"Alacant",
    "sg:orig_category":"Empresas De Limpieza",
    "sg:phone":"+34 965 12 60 69",
    "sg:postcode":"03007",
    "sg:province":"Alicante",
    "wof:name":"Espina Alvarez Eduardo",
    "wof:placetype":"venue"
},
  "geometry": {"coordinates":[-0.4944100082,38.3411102295],"type":"Point"}
}