{
  "type": "Feature",
  "properties": {
    "addr:full":"Calle de Doctor Pi\u00d1uela, 2 Salamanca Salamanca 37002",
    "addr:housenumber":"2",
    "addr:postcode":"37002",
    "addr:street":"Calle De Doctor Pin\u0303Uela",
    "iso:country":"ES",
    "sg:address":"Calle de Doctor Pi\u00d1uela, 2",
    "sg:city":"Salamanca",
    "sg:orig_category":"Institutos De Belleza",
    "sg:phone":"+34 923 26 40 00",
    "sg:postcode":"37002",
    "sg:province":"Salamanca",
    "wof:name":"Alonso Regalado Maria Josefa",
    "wof:placetype":"venue"
},
  "geometry": {"coordinates":[-5.6633358002,40.965675354],"type":"Point"}
}