{
  "type": "Feature",
  "properties": {
    "iso:country":"ES",
    "sg:address":"Calle de General Emilio Villaescusa, 20",
    "sg:city":"Tarancon",
    "sg:orig_category":"Ingenier\u00cda, Centros De Estudios (diversos)",
    "sg:phone":"+34 969 32 13 25",
    "sg:postcode":"16400",
    "sg:province":"Cuenca",
    "wof:name":"Abad Rius Jose Maria",
    "wof:placetype":"venue"
},
  "geometry": {"coordinates":[-3.010858,40.007301],"type":"Point"}
}