{
  "type": "Feature",
  "properties": {
    "addr:full":"Carrer de Bailen, 71 Barcelona Barcelona 08009",
    "addr:housenumber":"71",
    "addr:postcode":"08009",
    "addr:street":"Carrer De Bailen",
    "iso:country":"ES",
    "sg:address":"Carrer de Bailen, 71",
    "sg:city":"Barcelona",
    "sg:orig_category":"Inmobiliaria (agencias)",
    "sg:phone":"+34 932 44 82 10",
    "sg:postcode":"08009",
    "sg:province":"Barcelona",
    "wof:name":"Tralmer S.l.",
    "wof:placetype":"venue"
},
  "geometry": {"coordinates":[2.1720840931,41.395614624],"type":"Point"}
}