{
  "type": "Feature",
  "properties": {
    "iso:country":"ES",
    "sg:address":"Avda Torneo, 51",
    "sg:city":"Sevilla",
    "sg:orig_category":"Marmolistas Funerarios",
    "sg:phone":"+34 954 90 50 02",
    "sg:postcode":"41002",
    "sg:province":"Sevilla",
    "wof:name":"Funeraria Los Angeles S.l.",
    "wof:placetype":"venue"
},
  "geometry": {"coordinates":[-5.995513916,37.4035873413],"type":"Point"}
}