{
  "type": "Feature",
  "properties": {
    "iso:country":"ES",
    "sg:address":"Carrer de Sant Placid, 9",
    "sg:city":"Granollers",
    "sg:orig_category":"Fabricaci\u00d3n, Venta, Instalaci\u00d3n De R\u00d3tulos, De R\u00d3tulos Luminosos",
    "sg:phone":"+34 938 49 62 17",
    "sg:postcode":"08401",
    "sg:province":"Barcelona",
    "wof:name":"Martinez Lopez Fernando",
    "wof:placetype":"venue"
},
  "geometry": {"coordinates":[2.2905709743,41.6188087463],"type":"Point"}
}