{
  "type": "Feature",
  "properties": {
    "iso:country":"ES",
    "sg:address":"Calle de Velazquez, 2",
    "sg:city":"Rota",
    "sg:orig_category":"Arquitectos",
    "sg:phone":"+34 956 84 17 10",
    "sg:postcode":"11520",
    "sg:province":"C\u00e1diz",
    "wof:name":"Garcia Delgado Mercedes",
    "wof:placetype":"venue"
},
  "geometry": {"coordinates":[-6.3642640114,36.6258811951],"type":"Point"}
}