{
  "type": "Feature",
  "properties": {
    "addr:full":"Calle de Arguelles, 26 Linares Ja\u00e9n 23700",
    "addr:housenumber":"26",
    "addr:postcode":"23700",
    "addr:street":"Calle De Arguelles;Jae\u0301N",
    "iso:country":"ES",
    "sg:address":"Calle de Arguelles, 26",
    "sg:city":"Linares",
    "sg:orig_category":"Ingeniero",
    "sg:phone":"+34 953 69 56 57",
    "sg:postcode":"23700",
    "sg:province":"Ja\u00e9n",
    "sg:website":"www.alvarezvillarrubia.org",
    "wof:name":"Alvarez Villarrubia S.l.",
    "wof:placetype":"venue"
},
  "geometry": {"coordinates":[-3.6322622299,38.0972290039],"type":"Point"}
}