{
  "type": "Feature",
  "properties": {
    "iso:country":"ES",
    "sg:address":"Calle de Industrial Hernisa Ii, 2",
    "sg:city":"Poligono Sta M. De Benquerencia",
    "sg:orig_category":"Asesor\u00cda Sobre Comunicaci\u00d3n De Empresas",
    "sg:phone":"+34 925 23 23 99",
    "sg:postcode":"45007",
    "sg:province":"Toledo",
    "wof:name":"Proyectos Asesoria Y Servicios S.a.",
    "wof:placetype":"venue"
},
  "geometry": {"coordinates":[-3.9533588886,39.8694267273],"type":"Point"}
}