{
  "type": "Feature",
  "properties": {
    "iso:country":"ES",
    "sg:address":"L. Bravo, 10",
    "sg:city":"Villalonquejar",
    "sg:orig_category":"Productores Recolectores, Venta Directa De Vinos",
    "sg:phone":"+34 947 29 82 17",
    "sg:postcode":"09001",
    "sg:province":"Burgos",
    "wof:name":"Bodegas Y Distribuciones Hermanos Ayuso Martin C.b.",
    "wof:placetype":"venue"
},
  "geometry": {"coordinates":[-3.7272269726,42.3730201721],"type":"Point"}
}