{
  "type": "Feature",
  "properties": {
    "iso:country":"ES",
    "sg:address":"Poli Industrial C/e, 18",
    "sg:city":"Rozas De Madrid",
    "sg:orig_category":"Importaci\u00d3n",
    "sg:phone":"+34 916 36 37 92",
    "sg:postcode":"28230",
    "sg:province":"Madrid",
    "wof:name":"Semarang Europe, S.l.",
    "wof:placetype":"venue"
},
  "geometry": {"coordinates":[-3.8913800716,40.5247497559],"type":"Point"}
}