{
  "type": "Feature",
  "properties": {
    "addr:full":"Ceballos, S/n Balsicas Murcia 30591",
    "addr:postcode":"30591",
    "addr:street":"Ceballos S / N Balsicas",
    "iso:country":"ES",
    "sg:address":"Ceballos, S/n",
    "sg:city":"Balsicas",
    "sg:orig_category":"Sales (al Por Mayor)",
    "sg:phone":"+34 968 58 01 16",
    "sg:postcode":"30591",
    "sg:province":"Murcia",
    "wof:name":"Copifor S.l.",
    "wof:placetype":"venue"
},
  "geometry": {"coordinates":[-0.9609609842,37.8191490173],"type":"Point"}
}