{
  "type": "Feature",
  "properties": {
    "iso:country":"ES",
    "sg:address":"Calle de Pelota, 6",
    "sg:city":"Palmas De Gran Canaria",
    "sg:orig_category":"Laboratorios Y Trabajos De Fotograf\u00cda, V\u00cddeo Y Cine",
    "sg:phone":"+34 928 31 51 84",
    "sg:postcode":"35001",
    "sg:province":"Las Palmas",
    "wof:name":"Herrera Melian Ruben Carmelo",
    "wof:placetype":"venue"
},
  "geometry": {"coordinates":[-15.4138393402,28.1022720337],"type":"Point"}
}