{
  "type": "Feature",
  "properties": {
    "iso:country":"ES",
    "sg:address":"Calle de Jaialai, 6",
    "sg:city":"Donostia-san Sebastian",
    "sg:orig_category":"Cultos Diversos",
    "sg:phone":"+34 943 29 17 14",
    "sg:postcode":"20012",
    "sg:province":"Guip\u00f9zcoa",
    "wof:name":"Testigos Cristianos De Jehova",
    "wof:placetype":"venue"
},
  "geometry": {"coordinates":[-1.9681220055,43.3209037781],"type":"Point"}
}