{
  "type": "Feature",
  "properties": {
    "addr:full":"Calle de Montero Rios, 78 Alacant Alicante 03012",
    "addr:housenumber":"78",
    "addr:postcode":"03012",
    "addr:street":"Calle De Montero Rios",
    "iso:country":"ES",
    "sg:address":"Calle de Montero Rios, 78",
    "sg:city":"Alacant",
    "sg:orig_category":"Fabricaci\u00d3n De Juguetes Autom\u00c1ticos",
    "sg:phone":"+34 965 24 50 72",
    "sg:postcode":"03012",
    "sg:province":"Alicante",
    "wof:name":"Automaticos Velazquez S. L.",
    "wof:placetype":"venue"
},
  "geometry": {"coordinates":[-0.4818229973,38.361164093],"type":"Point"}
}