{
  "type": "Feature",
  "properties": {
    "iso:country":"ES",
    "sg:address":"Calle de Pilar De Zaragoza, 106",
    "sg:city":"Madrid",
    "sg:orig_category":"Ropa Y Accesorios",
    "sg:phone":"+34 917 13 06 82",
    "sg:postcode":"28028",
    "sg:province":"Madrid",
    "sg:website":"www.trantraimpex.com",
    "wof:name":"Tantra Impex S.l.",
    "wof:placetype":"venue"
},
  "geometry": {"coordinates":[-3.6745390892,40.4384307861],"type":"Point"}
}