{
  "type": "Feature",
  "properties": {
    "iso:country":"ES",
    "sg:address":"Calle de Navas De Tolosa, 4",
    "sg:city":"Jaen",
    "sg:orig_category":"Confecci\u00d3n De Trajes Para Se\u00d1oras",
    "sg:phone":"+34 953 26 69 37",
    "sg:postcode":"23001",
    "sg:province":"Ja\u00e9n",
    "wof:name":"Serda S.l.",
    "wof:placetype":"venue"
},
  "geometry": {"coordinates":[-3.7871940136,37.7693328857],"type":"Point"}
}