{
  "type": "Feature",
  "properties": {
    "addr:full":"Calle de Maria Jordan, 1 Valencia Valencia 46018",
    "addr:housenumber":"1",
    "addr:postcode":"46018",
    "addr:street":"Calle De Maria Jordan",
    "iso:country":"ES",
    "sg:address":"Calle de Maria Jordan, 1",
    "sg:city":"Valencia",
    "sg:orig_category":"Cine: Pel\u00cdculas Educativas, Industriales Y Publicitarias (producci\u00d3n)",
    "sg:phone":"+34 963 57 77 61",
    "sg:postcode":"46018",
    "sg:province":"Valencia",
    "wof:name":"Repartos Publicitarios Navalcan S.l.",
    "wof:placetype":"venue"
},
  "geometry": {"coordinates":[-0.3919729888,39.4614448547],"type":"Point"}
}