{
  "type": "Feature",
  "properties": {
    "addr:full":"Federico Gcia Lorca, 2 Torredonjimeno Ja\u00e9n 23650",
    "addr:housenumber":"2",
    "addr:postcode":"23650",
    "addr:street":"Federico;Lorca",
    "iso:country":"ES",
    "sg:address":"Federico Gcia Lorca, 2",
    "sg:city":"Torredonjimeno",
    "sg:orig_category":"Ropa Para Se\u00d1oras (al Por Menor)",
    "sg:phone":"+34 953 34 15 59",
    "sg:postcode":"23650",
    "sg:province":"Ja\u00e9n",
    "wof:name":"Castellano Martinez Abelardo",
    "wof:placetype":"venue"
},
  "geometry": {"coordinates":[-3.9562489986,37.7677383423],"type":"Point"}
}