{
  "type": "Feature",
  "properties": {
    "addr:full":"Pl. Conquistadores, S/n Balboa Badajoz 06195",
    "addr:housenumber":"s / n",
    "addr:postcode":"06195",
    "addr:street":"Pl. Conquistadores",
    "iso:country":"ES",
    "sg:address":"Pl. Conquistadores, S/n",
    "sg:city":"Balboa",
    "sg:orig_category":"Ense\u00d1anza, Formaci\u00d3n Profesional: Aprendizaje",
    "sg:phone":"+34 924 44 90 00",
    "sg:postcode":"06195",
    "sg:province":"Badajoz",
    "wof:name":"Ayuntamiento De Badajoz",
    "wof:placetype":"venue"
},
  "geometry": {"coordinates":[-6.8169865608,38.9052391052],"type":"Point"}
}