{
  "type": "Feature",
  "properties": {
    "addr:full":"Av Barceloneta, 66 Sils Girona 17410",
    "addr:housenumber":"66",
    "addr:postcode":"17410",
    "addr:street":"Av Barceloneta",
    "iso:country":"ES",
    "sg:address":"Av Barceloneta, 66",
    "sg:city":"Sils",
    "sg:orig_category":"Arquitectos",
    "sg:phone":"+34 972 85 33 84",
    "sg:postcode":"17410",
    "sg:province":"Girona",
    "wof:name":"Pomar Marin Angel Manuel",
    "wof:placetype":"venue"
},
  "geometry": {"coordinates":[2.7421340942,41.814907074],"type":"Point"}
}