{
  "type": "Feature",
  "properties": {
    "addr:full":"Pl Dalt Vila, 15 Manlleu Barcelona 08560",
    "addr:housenumber":"15",
    "addr:postcode":"08560",
    "addr:street":"Pl Dalt Vila",
    "iso:country":"ES",
    "sg:address":"Pl Dalt Vila, 15",
    "sg:city":"Manlleu",
    "sg:orig_category":"Arquitectos",
    "sg:phone":"+34 938 50 70 00",
    "sg:postcode":"08560",
    "sg:province":"Barcelona",
    "wof:name":"Reches Martinez Jose",
    "wof:placetype":"venue"
},
  "geometry": {"coordinates":[2.2836499214,42.0012588501],"type":"Point"}
}