{
  "type": "Feature",
  "properties": {
    "addr:full":"Pase Urgoiti, 12 Arrigorriaga Vizcaya 48480",
    "addr:housenumber":"12",
    "addr:postcode":"48480",
    "addr:street":"Urgoiti",
    "iso:country":"ES",
    "sg:address":"Pase Urgoiti, 12",
    "sg:city":"Arrigorriaga",
    "sg:orig_category":"Centros Empresariales",
    "sg:phone":"+34 946 71 24 50",
    "sg:postcode":"48480",
    "sg:province":"Vizcaya",
    "wof:name":"Aguirre Merino S.l.",
    "wof:placetype":"venue"
},
  "geometry": {"coordinates":[-2.8881111145,43.2088775635],"type":"Point"}
}