{
  "type": "Feature",
  "properties": {
    "addr:full":"Carrer de Bori I Fontesta, 13 Barcelona Barcelona 08021",
    "addr:housenumber":"13",
    "addr:postcode":"08021",
    "addr:street":"Carrer De Bori I Fontesta",
    "iso:country":"ES",
    "sg:address":"Carrer de Bori I Fontesta, 13",
    "sg:city":"Barcelona",
    "sg:orig_category":"Construcciones Navales Y Fluviales",
    "sg:phone":"+34 932 09 48 19",
    "sg:postcode":"08021",
    "sg:province":"Barcelona",
    "wof:name":"Mitjans Caballeria Maria Rosa",
    "wof:placetype":"venue"
},
  "geometry": {"coordinates":[2.1405549049,41.3934135437],"type":"Point"}
}