{
  "type": "Feature",
  "properties": {
    "iso:country":"ES",
    "sg:address":"Calle de Constancia, 45",
    "sg:city":"Madrid",
    "sg:orig_category":"Fotocopias, Reprograf\u00cda",
    "sg:phone":"+34 915 10 26 72",
    "sg:postcode":"28002",
    "sg:province":"Madrid",
    "wof:name":"Ema Copias Reprografia S.l.",
    "wof:placetype":"venue"
},
  "geometry": {"coordinates":[-3.6717703342,40.4432220459],"type":"Point"}
}