{
  "type": "Feature",
  "properties": {
    "iso:country":"ES",
    "sg:address":"Carr Constitucio (la), 2",
    "sg:city":"Petrer",
    "sg:orig_category":"Oficinas De Estudios De Dise\u00d1o Industrial",
    "sg:phone":"+34 966 95 53 97",
    "sg:postcode":"03610",
    "sg:province":"Alicante",
    "sg:website":"www.queridamilagros.com",
    "wof:name":"Querida Milagros S.l.",
    "wof:placetype":"venue"
},
  "geometry": {"coordinates":[-0.7731289864,38.4793281555],"type":"Point"}
}