{
  "type": "Feature",
  "properties": {
    "addr:full":"Ctra Hurchillo, 1 Orihuela Alicante 03300",
    "addr:housenumber":"1",
    "addr:postcode":"03300",
    "addr:street":"Ctra Hurchillo",
    "iso:country":"ES",
    "sg:address":"Ctra Hurchillo, 1",
    "sg:city":"Orihuela",
    "sg:orig_category":"Muebles",
    "sg:phone":"+34 965 30 64 41",
    "sg:postcode":"03300",
    "sg:province":"Alicante",
    "wof:name":"Perfilmobel S. L.",
    "wof:placetype":"venue"
},
  "geometry": {"coordinates":[-0.9377909899,38.0720252991],"type":"Point"}
}