{
  "type": "Feature",
  "properties": {
    "iso:country":"ES",
    "sg:address":"Calle de Club, 2",
    "sg:city":"Getxo",
    "sg:orig_category":"Supermercados Y Hipermercados",
    "sg:phone":"+34 944 63 58 79",
    "sg:postcode":"48930",
    "sg:province":"Vizcaya",
    "wof:name":"Ultramarinos Julian Sl",
    "wof:placetype":"venue"
},
  "geometry": {"coordinates":[-3.0124490261,43.3270721436],"type":"Point"}
}