{
  "type": "Feature",
  "properties": {
    "addr:full":"Calle de Pio Xii, 47 Santiago El Mayor Murcia 30012",
    "addr:housenumber":"47",
    "addr:postcode":"30012",
    "addr:street":"Calle De Pio Xii",
    "iso:country":"ES",
    "sg:address":"Calle de Pio Xii, 47",
    "sg:city":"Santiago El Mayor",
    "sg:orig_category":"Empresas De Vigilancia, Guardia Y Protecci\u00d3n",
    "sg:phone":"+34 968 34 47 70",
    "sg:postcode":"30012",
    "sg:province":"Murcia",
    "wof:name":"Pyc Seguridad C Atalunya S.a.",
    "wof:placetype":"venue"
},
  "geometry": {"coordinates":[-1.1213320494,37.9693984985],"type":"Point"}
}