{
  "type": "Feature",
  "properties": {
    "addr:full":"Calle de Padre Feijoo, 2 Coru\u00d1a La Coru\u00f1a 15004",
    "addr:housenumber":"2",
    "addr:postcode":"15004",
    "addr:street":"Calle De Padre Feijoo;La Corun\u0303A",
    "iso:country":"ES",
    "sg:address":"Calle de Padre Feijoo, 2",
    "sg:city":"Coru\u00d1a",
    "sg:orig_category":"Platos Preparados Refrigerados (fabricaci\u00d3n, Al Por Mayor)",
    "sg:phone":"+34 981 21 04 60",
    "sg:postcode":"15004",
    "sg:province":"La Coru\u00f1a",
    "wof:name":"Maese Pablos S.l.",
    "wof:placetype":"venue"
},
  "geometry": {"coordinates":[-8.4116697311,43.3660888672],"type":"Point"}
}