{
  "type": "Feature",
  "properties": {
    "iso:country":"ES",
    "sg:address":"Rua General Franco, 21",
    "sg:city":"Lalin",
    "sg:orig_category":"Bazares, Art\u00cdculos De Limpieza Y De Cocina (al Por Menor)",
    "sg:phone":"+34 986 78 00 34",
    "sg:postcode":"36500",
    "sg:province":"Pontevedra",
    "wof:name":"Fernandez Lamazares Victorino",
    "wof:placetype":"venue"
},
  "geometry": {"coordinates":[-8.1120891571,42.6614303589],"type":"Point"}
}