{
  "type": "Feature",
  "properties": {
    "iso:country":"ES",
    "sg:address":"Calle de Real, 2",
    "sg:city":"Rozas De Madrid",
    "sg:orig_category":"Artes Gr\u00c1ficas, Artes Pl\u00c1sticas (curso)",
    "sg:phone":"+34 916 30 66 35",
    "sg:postcode":"28230",
    "sg:province":"Madrid",
    "wof:name":"Instrumentacion Fisico Medica",
    "wof:placetype":"venue"
},
  "geometry": {"coordinates":[-3.8743700981,40.4926605225],"type":"Point"}
}