{
  "type": "Feature",
  "properties": {
    "iso:country":"ES",
    "sg:address":"Calle de Paz, 4",
    "sg:city":"Guijuelo",
    "sg:orig_category":"Mec\u00c1nico Del Autom\u00d3vil",
    "sg:phone":"+34 923 58 09 70",
    "sg:postcode":"37770",
    "sg:province":"Salamanca",
    "wof:name":"Garcia Sequeira Ignacio",
    "wof:placetype":"venue"
},
  "geometry": {"coordinates":[-5.6728258133,40.5576896667],"type":"Point"}
}