{
  "type": "Feature",
  "properties": {
    "iso:country":"ES",
    "sg:address":"Ctra Madrid-irun, Km. 0236,0",
    "sg:city":"Burgos",
    "sg:orig_category":"Parques De Atracciones Y Centros De Esparcimiento",
    "sg:phone":"+34 947 27 32 92",
    "sg:postcode":"09100",
    "sg:province":"Burgos",
    "wof:name":"Abaco Amusement S.l.",
    "wof:placetype":"venue"
},
  "geometry": {"coordinates":[-3.615836,42.367085],"type":"Point"}
}