{
  "type": "Feature",
  "properties": {
    "iso:country":"ES",
    "sg:address":"Calle de Cortes De La Frontera, 35",
    "sg:city":"Malaga",
    "sg:orig_category":"Centros Empresariales",
    "sg:phone":"+34 952 03 81 06",
    "sg:postcode":"29006",
    "sg:province":"M\u00e1laga",
    "sg:website":"www.hecagregu.com",
    "wof:name":"Hecagregu S.coop.andaluza",
    "wof:placetype":"venue"
},
  "geometry": {"coordinates":[-4.4660115242,36.7029647827],"type":"Point"}
}