{
  "type": "Feature",
  "properties": {
    "iso:country":"ES",
    "sg:address":"Calle de Coso, 6",
    "sg:city":"Ejea De Los Caballeros",
    "sg:orig_category":"Confecci\u00d3n De Trajes Para Se\u00d1oras",
    "sg:phone":"+34 976 66 43 76",
    "sg:postcode":"50600",
    "sg:province":"Zaragoza",
    "wof:name":"Lopez Bona Rosa Maria",
    "wof:placetype":"venue"
},
  "geometry": {"coordinates":[-1.1404460669,42.1268081665],"type":"Point"}
}