{
  "type": "Feature",
  "properties": {
    "iso:country":"ES",
    "sg:address":"Calle de Angeles Bohorquez, S/n",
    "sg:city":"Ubrique",
    "sg:orig_category":"Marroquiner\u00cda (confecci\u00d3n)",
    "sg:phone":"+34 956 46 37 01",
    "sg:postcode":"11600",
    "sg:province":"C\u00e1diz",
    "wof:name":"Garcia Galindo Vicente",
    "wof:placetype":"venue"
},
  "geometry": {"coordinates":[-5.4470744133,36.676197052],"type":"Point"}
}