{
  "type": "Feature",
  "properties": {
    "iso:country":"ES",
    "sg:address":"Carrer de Josep Calvet, 34",
    "sg:city":"Mataro",
    "sg:orig_category":"Ropa Para Se\u00d1oras Y Caballeros (al Por Menor)",
    "sg:phone":"+34 937 98 14 35",
    "sg:postcode":"08302",
    "sg:province":"Barcelona",
    "wof:name":"Look And Design Society S.l.",
    "wof:placetype":"venue"
},
  "geometry": {"coordinates":[2.4252960682,41.5293960571],"type":"Point"}
}