{
  "type": "Feature",
  "properties": {
    "iso:country":"ES",
    "sg:address":"Calle de Virgen De Regla, 22",
    "sg:city":"Sevilla",
    "sg:orig_category":"Alimentaci\u00d3n General (al Por Menor)",
    "sg:phone":"+34 954 28 25 58",
    "sg:postcode":"41011",
    "sg:province":"Sevilla",
    "wof:name":"Goncas S.cv.",
    "wof:placetype":"venue"
},
  "geometry": {"coordinates":[-5.9989981651,37.3775672913],"type":"Point"}
}