{
  "type": "Feature",
  "properties": {
    "iso:country":"ES",
    "sg:address":"Calle de Sangarcia, 5",
    "sg:city":"Madrid",
    "sg:orig_category":"Cervecer\u00cdas",
    "sg:phone":"+34 913 65 74 04",
    "sg:postcode":"28005",
    "sg:province":"Madrid",
    "wof:name":"Garcia Rodriguez Celso",
    "wof:placetype":"venue"
},
  "geometry": {"coordinates":[-3.7188000679,40.4050369263],"type":"Point"}
}