{
  "type": "Feature",
  "properties": {
    "addr:full":"Calle de Anselmo J Benitez, 6 Santa Cruz De Tenerife Santa Cruz De Tenerife 38004",
    "addr:housenumber":"6",
    "addr:postcode":"38004",
    "addr:street":"Calle De Anselmo J Benitez",
    "iso:country":"ES",
    "sg:address":"Calle de Anselmo J Benitez, 6",
    "sg:city":"Santa Cruz De Tenerife",
    "sg:orig_category":"M\u00c9dicos: Cirug\u00cda Ortop\u00c9dica Y Traumatolog\u00cda",
    "sg:phone":"+34 922 28 12 53",
    "sg:postcode":"38004",
    "sg:province":"Santa Cruz De Tenerife",
    "wof:name":"Rodriguez Hernandez Antonio",
    "wof:placetype":"venue"
},
  "geometry": {"coordinates":[-16.2596187592,28.4682788849],"type":"Point"}
}