{
  "type": "Feature",
  "properties": {
    "addr:full":"Calle de Rio Guadalcazin, 22 San Javier Murcia 30730",
    "addr:housenumber":"22",
    "addr:postcode":"30730",
    "addr:street":"Calle De Rio Guadalcazin",
    "iso:country":"ES",
    "sg:address":"Calle de Rio Guadalcazin, 22",
    "sg:city":"San Javier",
    "sg:orig_category":"Centros Empresariales",
    "sg:phone":"+34 968 19 32 55",
    "sg:postcode":"30730",
    "sg:province":"Murcia",
    "wof:name":"Vitava Fruit Sl",
    "wof:placetype":"venue"
},
  "geometry": {"coordinates":[-0.8214758039,37.8027000427],"type":"Point"}
}