{
  "type": "Feature",
  "properties": {
    "iso:country":"ES",
    "sg:address":"Calle de Jardin, 5",
    "sg:city":"Aguadulce",
    "sg:orig_category":"Relojer\u00cda Industrial",
    "sg:phone":"+34 950 34 85 48",
    "sg:postcode":"04720",
    "sg:province":"Almer\u00eda",
    "wof:name":"Martinez Soldan Francisco Javier",
    "wof:placetype":"venue"
},
  "geometry": {"coordinates":[-2.5756349564,36.8140983582],"type":"Point"}
}