{
  "type": "Feature",
  "properties": {
    "iso:country":"ES",
    "sg:address":"Calle de Antonio Ramos Carratala, S/n",
    "sg:city":"S. Pedro Pinatar",
    "sg:classifiers":[
        {
            "category":"Personal",
            "subcategory":"Barber",
            "type":"Services"
        }
    ],
    "sg:phone":"+34 968 18 10 38",
    "sg:postcode":"30740",
    "sg:province":"Murcia",
    "sg:tags":[
        "caballeros",
        "de",
        "peluqueros"
    ],
    "wof:name":"Fructuoso Henarejos Jose Antonio",
    "wof:placetype":"venue"
},
  "geometry": {"coordinates":[-0.7937263846,37.8354988098],"type":"Point"}
}