{
  "type": "Feature",
  "properties": {
    "iso:country":"ES",
    "sg:address":"Furs, 5",
    "sg:city":"Quatretonda",
    "sg:orig_category":"Pescader\u00cdas (al Por Menor)",
    "sg:phone":"+34 962 26 45 42",
    "sg:postcode":"46837",
    "sg:province":"Valencia",
    "wof:name":"Benavent Vidal Rafael",
    "wof:placetype":"venue"
},
  "geometry": {"coordinates":[-0.4006139934,38.9446525574],"type":"Point"}
}