{
  "type": "Feature",
  "properties": {
    "iso:country":"ES",
    "sg:address":"Calle de Alfonso Xiii, 19",
    "sg:city":"Parla",
    "sg:orig_category":"Centros De Educaci\u00d3n Especial",
    "sg:phone":"+34 916 05 76 88",
    "sg:postcode":"28980",
    "sg:province":"Madrid",
    "wof:name":"Comunidad Autonoma Madrid-escuela Infantil Los Abetos",
    "wof:placetype":"venue"
},
  "geometry": {"coordinates":[-3.7634079456,40.2336959839],"type":"Point"}
}