{
  "type": "Feature",
  "properties": {
    "addr:full":"Ctra Aldaya, 4 Alaquas Valencia 46970",
    "addr:housenumber":"4",
    "addr:postcode":"46970",
    "addr:street":"Ctra Aldaya",
    "iso:country":"ES",
    "sg:address":"Ctra Aldaya, 4",
    "sg:city":"Alaquas",
    "sg:orig_category":"Institutos De Belleza",
    "sg:phone":"+34 961 51 52 66",
    "sg:postcode":"46970",
    "sg:province":"Valencia",
    "wof:name":"Farma-sano S.l.",
    "wof:placetype":"venue"
},
  "geometry": {"coordinates":[-0.4631820023,39.4579429626],"type":"Point"}
}