{
  "type": "Feature",
  "properties": {
    "addr:full":"Granjas, S/n Vallmanya Lleida 25287",
    "addr:housenumber":"s",
    "addr:postcode":"25287",
    "addr:street":"Granjas;/ N Vallmanya",
    "iso:country":"ES",
    "sg:address":"Granjas, S/n",
    "sg:city":"Vallmanya",
    "sg:orig_category":"Cooperativas Agr\u00cdcolas",
    "sg:phone":"+34 973 47 31 35",
    "sg:postcode":"25287",
    "sg:province":"Lleida",
    "wof:name":"Sociedad Agraria De Transformacion 9682",
    "wof:placetype":"venue"
},
  "geometry": {"coordinates":[1.541105032,41.827419281],"type":"Point"}
}