{
  "type": "Feature",
  "properties": {
    "iso:country":"ES",
    "sg:address":"Calle de Redon, 8",
    "sg:city":"San Jose",
    "sg:orig_category":"Supermercados Y Hipermercados",
    "sg:phone":"+34 968 44 40 41",
    "sg:postcode":"30800",
    "sg:province":"Murcia",
    "wof:name":"Bayly S.l.",
    "wof:placetype":"venue"
},
  "geometry": {"coordinates":[-1.6905640364,37.680557251],"type":"Point"}
}