{
  "type": "Feature",
  "properties": {
    "iso:country":"ES",
    "sg:address":"Pl Font (de La), 9",
    "sg:city":"Tarragona",
    "sg:orig_category":"Molduras, Junquillos, Listones Y Molduras Perforadas",
    "sg:phone":"+34 977 23 22 27",
    "sg:postcode":"43003",
    "sg:province":"Tarragona",
    "wof:name":"Ezhou  Chao",
    "wof:placetype":"venue"
},
  "geometry": {"coordinates":[1.254551053,41.1171340942],"type":"Point"}
}