{
  "type": "Feature",
  "properties": {
    "addr:full":"Avda Vera, 2 Plasencia C\u00e1ceres 10600",
    "addr:housenumber":"2",
    "addr:postcode":"10600",
    "addr:street":"Avda Vera;Ca\u0301Ceres",
    "iso:country":"ES",
    "sg:address":"Avda Vera, 2",
    "sg:city":"Plasencia",
    "sg:orig_category":"Bazares, Art\u00cdculos De Limpieza Y De Cocina (al Por Menor)",
    "sg:phone":"+34 927 41 13 20",
    "sg:postcode":"10600",
    "sg:province":"C\u00e1ceres",
    "wof:name":"Rodriguez Vazquez Manuela",
    "wof:placetype":"venue"
},
  "geometry": {"coordinates":[-6.0854549408,40.0309257507],"type":"Point"}
}