{
  "type": "Feature",
  "properties": {
    "iso:country":"ES",
    "sg:address":"Avda Lasalle, 179",
    "sg:city":"Salamanca",
    "sg:orig_category":"Transportes De Animales Vivos",
    "sg:phone":"+34 923 19 26 87",
    "sg:postcode":"37008",
    "sg:province":"Salamanca",
    "wof:name":"Transportes Campo S. L.",
    "wof:placetype":"venue"
},
  "geometry": {"coordinates":[-5.6892580986,40.9546432495],"type":"Point"}
}