{
  "type": "Feature",
  "properties": {
    "addr:full":"Pg Pere Iii, 15 Manresa Barcelona 08242",
    "addr:housenumber":"15",
    "addr:postcode":"08242",
    "addr:street":"Pg Pere Iii",
    "iso:country":"ES",
    "sg:address":"Pg Pere Iii, 15",
    "sg:city":"Manresa",
    "sg:orig_category":"Zapatos (al Por Menor)",
    "sg:phone":"+34 938 72 37 23",
    "sg:postcode":"08242",
    "sg:province":"Barcelona",
    "wof:name":"Noet Jou Carmen",
    "wof:placetype":"venue"
},
  "geometry": {"coordinates":[1.8233790398,41.7259254456],"type":"Point"}
}