{
  "type": "Feature",
  "properties": {
    "iso:country":"ES",
    "sg:address":"Calle de Reina, 1",
    "sg:city":"Valladolid",
    "sg:orig_category":"Asociaciones, Organismos Culturales Y Socioeducativos",
    "sg:phone":"+34 983 35 28 41",
    "sg:postcode":"47001",
    "sg:province":"Valladolid",
    "sg:website":"www.avacap.org",
    "wof:name":"Asociacion De Cazadores Y Pescadores De Valladolid",
    "wof:placetype":"venue"
},
  "geometry": {"coordinates":[-4.7294282913,41.6517066956],"type":"Point"}
}