{
  "type": "Feature",
  "properties": {
    "iso:country":"ES",
    "sg:address":"Carrer de Bado, 1",
    "sg:city":"S. Just Desvern",
    "sg:orig_category":"Institutos De Belleza",
    "sg:phone":"+34 934 73 97 69",
    "sg:postcode":"08960",
    "sg:province":"Barcelona",
    "wof:name":"Morte Medero Nuria",
    "wof:placetype":"venue"
},
  "geometry": {"coordinates":[2.0756299496,41.3849983215],"type":"Point"}
}