{
  "type": "Feature",
  "properties": {
    "addr:full":"Pase Berabera De, 79 Donostia-san Sebastian Guip\u00f9zcoa 20009",
    "addr:housenumber":"79",
    "addr:postcode":"20009",
    "addr:street":"Berabera",
    "iso:country":"ES",
    "sg:address":"Pase Berabera De, 79",
    "sg:city":"Donostia-san Sebastian",
    "sg:orig_category":"Doctores En Medicina",
    "sg:phone":"+34 943 21 37 20",
    "sg:postcode":"20009",
    "sg:province":"Guip\u00f9zcoa",
    "wof:name":"Grijalba Iturri Marino",
    "wof:placetype":"venue"
},
  "geometry": {"coordinates":[-1.9970860481,43.3038291931],"type":"Point"}
}