{
  "type": "Feature",
  "properties": {
    "iso:country":"ES",
    "sg:address":"Plaz Ramon Y Cajal, 9",
    "sg:city":"Beniel",
    "sg:orig_category":"Cajas De Ahorro",
    "sg:phone":"+34 968 60 60 50",
    "sg:postcode":"30130",
    "sg:province":"Murcia",
    "wof:name":"Caja De Ahorros Del Mediterraneo",
    "wof:placetype":"venue"
},
  "geometry": {"coordinates":[-1.0015610456,38.046661377],"type":"Point"}
}