{
  "type": "Feature",
  "properties": {
    "addr:full":"Avgd Valencia, 19 Lleida Lleida 25001",
    "addr:housenumber":"19",
    "addr:postcode":"25001",
    "addr:street":"Valencia",
    "iso:country":"ES",
    "sg:address":"Avgd Valencia, 19",
    "sg:city":"Lleida",
    "sg:orig_category":"Ropa Y Art\u00cdculos Pre",
    "sg:phone":"+34 973 21 32 50",
    "sg:postcode":"25001",
    "sg:province":"Lleida",
    "wof:name":"Galiano Gimenez Elena",
    "wof:placetype":"venue"
},
  "geometry": {"coordinates":[0.6286560297,41.6119766235],"type":"Point"}
}