{
  "type": "Feature",
  "properties": {
    "addr:full":"Calle de Ramon Gorge, 20 Elda Alicante 03600",
    "addr:housenumber":"20",
    "addr:postcode":"03600",
    "addr:street":"Calle De Ramon Gorge",
    "iso:country":"ES",
    "sg:address":"Calle de Ramon Gorge, 20",
    "sg:city":"Elda",
    "sg:orig_category":"Deportes Y Programas De Aventura",
    "sg:phone":"+34 965 38 63 34",
    "sg:postcode":"03600",
    "sg:province":"Alicante",
    "wof:name":"Lopez Ibaez Estefania",
    "wof:placetype":"venue"
},
  "geometry": {"coordinates":[-0.7927209735,38.4764785767],"type":"Point"}
}