{
  "type": "Feature",
  "properties": {
    "addr:full":"Carrer de Marques De Campo, 23 Denia Alicante 03700",
    "addr:housenumber":"23",
    "addr:postcode":"03700",
    "addr:street":"Carrer De Marques De Campo",
    "iso:country":"ES",
    "sg:address":"Carrer de Marques De Campo, 23",
    "sg:city":"Denia",
    "sg:orig_category":"Maquinaria Para Industrias Diversas",
    "sg:phone":"+34 965 78 83 16",
    "sg:postcode":"03700",
    "sg:province":"Alicante",
    "wof:name":"S.r.m. S.l.",
    "wof:placetype":"venue"
},
  "geometry": {"coordinates":[0.1082059965,38.840133667],"type":"Point"}
}