{
  "type": "Feature",
  "properties": {
    "iso:country":"ES",
    "sg:address":"Ed Isla Park(marina D'or), 2",
    "sg:city":"Oropesa Mar",
    "sg:orig_category":"Inmobiliaria (agencias)",
    "sg:phone":"+34 964 31 30 66",
    "sg:postcode":"12594",
    "sg:province":"Castell\u00f3n",
    "wof:name":"Plaza Inmobiliaria 2000 S.l.",
    "wof:placetype":"venue"
},
  "geometry": {"coordinates":[-0.0456800014,39.9851417542],"type":"Point"}
}