{
  "type": "Feature",
  "properties": {
    "iso:country":"ES",
    "sg:address":"Avda Cuarta Avenida, 21",
    "sg:city":"Zaragoza",
    "sg:orig_category":"Molduras, Junquillos, Listones Y Molduras Perforadas",
    "sg:phone":"+34 976 37 50 65",
    "sg:postcode":"50007",
    "sg:province":"Zaragoza",
    "wof:name":"Alcon Dieguez Monserrat",
    "wof:placetype":"venue"
},
  "geometry": {"coordinates":[-0.8765984774,41.62474823],"type":"Point"}
}