{
  "type": "Feature",
  "properties": {
    "iso:country":"ES",
    "sg:address":"Avgd Constitucion, 5",
    "sg:city":"Betera",
    "sg:orig_category":"Droguer\u00cdas (al Por Menor)",
    "sg:phone":"+34 961 69 06 27",
    "sg:postcode":"46117",
    "sg:province":"Valencia",
    "wof:name":"Martinez Iba\u00f1ez Maria Del Carmen",
    "wof:placetype":"venue"
},
  "geometry": {"coordinates":[-0.4551190138,39.5893669128],"type":"Point"}
}