{
  "type": "Feature",
  "properties": {
    "iso:country":"ES",
    "sg:address":"Nafar Kalea, 21",
    "sg:city":"Hernani",
    "sg:orig_category":"Asociaciones Y Clubs Deportivos",
    "sg:phone":"+34 943 33 37 24",
    "sg:postcode":"20120",
    "sg:province":"Guip\u00f9zcoa",
    "wof:name":"Koldo Alkorta Tomasena",
    "wof:placetype":"venue"
},
  "geometry": {"coordinates":[-1.9765080214,43.2666664124],"type":"Point"}
}