{
  "type": "Feature",
  "properties": {
    "addr:full":"Carrer de Boters (dels), 7 Vendrell Tarragona 43700",
    "addr:housenumber":"7",
    "addr:postcode":"43700",
    "addr:street":"Carrer De Boters Dels",
    "iso:country":"ES",
    "sg:address":"Carrer de Boters (dels), 7",
    "sg:city":"Vendrell",
    "sg:orig_category":"Maquinaria Para Industrias Diversas",
    "sg:phone":"+34 977 66 86 86",
    "sg:postcode":"43700",
    "sg:province":"Tarragona",
    "wof:name":"Margalef S. A.",
    "wof:placetype":"venue"
},
  "geometry": {"coordinates":[1.5298030376,41.23229599],"type":"Point"}
}