{
  "type": "Feature",
  "properties": {
    "addr:full":"Calle de Carril (del), 5 Morata De Taju\u00e7a Madrid 28530",
    "addr:housenumber":"5",
    "addr:postcode":"28530",
    "addr:street":"Calle De Carril Del",
    "iso:country":"ES",
    "sg:address":"Calle de Carril (del), 5",
    "sg:city":"Morata De Taju\u00e7a",
    "sg:orig_category":"Formaci\u00d3n Continuada (variada)",
    "sg:phone":"+34 918 73 12 38",
    "sg:postcode":"28530",
    "sg:province":"Madrid",
    "wof:name":"Area De Asesoramiento Laboral S.l.",
    "wof:placetype":"venue"
},
  "geometry": {"coordinates":[-3.7003455162,40.4166908264],"type":"Point"}
}