{
  "type": "Feature",
  "properties": {
    "addr:full":"Cra Capuchinos, 76 Malaga M\u00e1laga 29013",
    "addr:housenumber":"76",
    "addr:postcode":"29013",
    "addr:street":"Capuchinos;Ma\u0301Laga",
    "iso:country":"ES",
    "sg:address":"Cra Capuchinos, 76",
    "sg:city":"Malaga",
    "sg:orig_category":"Carnicer\u00cdas, Carnicer\u00cdas",
    "sg:phone":"+34 952 26 62 36",
    "sg:postcode":"29013",
    "sg:province":"M\u00e1laga",
    "wof:name":"Roman Guerrero Remedios",
    "wof:placetype":"venue"
},
  "geometry": {"coordinates":[-4.4171690941,36.7320671082],"type":"Point"}
}