{
  "type": "Feature",
  "properties": {
    "addr:full":"Calle de San Mateo, 8 Madrid Madrid 28004",
    "addr:housenumber":"8",
    "addr:postcode":"madrid;28004",
    "addr:street":"Calle De San Mateo",
    "iso:country":"ES",
    "sg:address":"Calle de San Mateo, 8",
    "sg:city":"Madrid",
    "sg:orig_category":"Procuradores",
    "sg:phone":"+34 915 21 77 49",
    "sg:postcode":"28004",
    "sg:province":"Madrid",
    "wof:name":"Gonzalez De Propios Rafael Antonio",
    "wof:placetype":"venue"
},
  "geometry": {"coordinates":[-3.6999158859,40.425201416],"type":"Point"}
}