{
  "type": "Feature",
  "properties": {
    "addr:full":"Avda Yecla (de), 44 Jumilla Murcia 30520",
    "addr:housenumber":"44",
    "addr:postcode":"30520",
    "addr:street":"Avda Yecla De",
    "iso:country":"ES",
    "sg:address":"Avda Yecla (de), 44",
    "sg:city":"Jumilla",
    "sg:orig_category":"Comercio De Piezas De Recambio Y De Accesorios De Veh\u00cdculos, Veh\u00cdculos Industriales",
    "sg:phone":"+34 968 78 24 23",
    "sg:postcode":"30520",
    "sg:province":"Murcia",
    "wof:name":"Repuestos Jumilla S.l.",
    "wof:placetype":"venue"
},
  "geometry": {"coordinates":[-1.3216899633,38.4801063538],"type":"Point"}
}