{
  "type": "Feature",
  "properties": {
    "iso:country":"ES",
    "sg:address":"Calle de Alberto Barbera, 9",
    "sg:city":"S. Miguel Salinas",
    "sg:classifiers":[
        {
            "category":"Autos & Motor Vehicles",
            "subcategory":"Automobile Sales",
            "type":"Retail Goods"
        }
    ],
    "sg:phone":"+34 966 72 30 67",
    "sg:postcode":"03193",
    "sg:province":"Alicante",
    "wof:name":"Pastor Gisbert Luis German",
    "wof:placetype":"venue"
},
  "geometry": {"coordinates":[-0.7909141183,37.9806480408],"type":"Point"}
}