{
  "type": "Feature",
  "properties": {
    "iso:country":"ES",
    "sg:address":"Calle de Claudio Moyano, 24",
    "sg:city":"Fuentelape\u00f1a",
    "sg:orig_category":"Asilos De Ancianos. Centros Privados",
    "sg:phone":"+34 980 60 52 80",
    "sg:postcode":"49410",
    "sg:province":"Zamora",
    "wof:name":"La Nueva C B",
    "wof:placetype":"venue"
},
  "geometry": {"coordinates":[-5.3849577904,41.2521324158],"type":"Point"}
}