{
  "type": "Feature",
  "properties": {
    "addr:full":"Avda Hontoria, S/n Hontoria Segovia 40195",
    "addr:housenumber":"s / n",
    "addr:postcode":"40195",
    "addr:street":"Avda Hontoria",
    "iso:country":"ES",
    "sg:address":"Avda Hontoria, S/n",
    "sg:city":"Hontoria",
    "sg:orig_category":"Agentes, Concesionarios Y Sucursales De Veh\u00cdculos",
    "sg:phone":"+34 921 43 86 65",
    "sg:postcode":"40195",
    "sg:province":"Segovia",
    "wof:name":"Segovia Automocion S. A.",
    "wof:placetype":"venue"
},
  "geometry": {"coordinates":[-4.108754158,40.9075737],"type":"Point"}
}