{
  "type": "Feature",
  "properties": {
    "addr:full":"Ctra Tembleque, Km. 0105,8 Villaca\u00f1as Toledo 45860",
    "addr:postcode":"45860",
    "addr:street":"Ctra Tembleque Km. 0105,8",
    "iso:country":"ES",
    "sg:address":"Ctra Tembleque, Km. 0105,8",
    "sg:city":"Villaca\u00f1as",
    "sg:orig_category":"Mec\u00c1nico Del Autom\u00d3vil",
    "sg:phone":"+34 925 20 13 68",
    "sg:postcode":"45860",
    "sg:province":"Toledo",
    "wof:name":"Talleres Climamotor S.l.",
    "wof:placetype":"venue"
},
  "geometry": {"coordinates":[-3.3500781059,39.6169471741],"type":"Point"}
}