{
  "type": "Feature",
  "properties": {
    "addr:full":"Calle de Real De Pinos Puente, 133 Pinos-puente Granada 18240",
    "addr:housenumber":"133",
    "addr:postcode":"18240",
    "addr:street":"Calle De Real De Pinos Puente",
    "iso:country":"ES",
    "sg:address":"Calle de Real De Pinos Puente, 133",
    "sg:city":"Pinos-puente",
    "sg:orig_category":"Agentes Generales De Seguros",
    "sg:phone":"+34 958 45 26 88",
    "sg:postcode":"18240",
    "sg:province":"Granada",
    "wof:name":"Higarmes Seguros S.l.",
    "wof:placetype":"venue"
},
  "geometry": {"coordinates":[-3.7521839142,37.2517814636],"type":"Point"}
}