{
  "type": "Feature",
  "properties": {
    "iso:country":"ES",
    "sg:address":"Calle de Santa Catalina, 34",
    "sg:city":"Coru\u00d1a",
    "sg:orig_category":"Asesor\u00cda Sobre Comunicaci\u00d3n De Empresas",
    "sg:phone":"+34 981 22 84 72",
    "sg:postcode":"15003",
    "sg:province":"La Coru\u00f1a",
    "wof:name":"Durlines S.l.",
    "wof:placetype":"venue"
},
  "geometry": {"coordinates":[-8.4044370651,43.36876297],"type":"Point"}
}