{
  "type": "Feature",
  "properties": {
    "iso:country":"ES",
    "sg:address":"Plaz Abastos, S/n",
    "sg:city":"Carbonero El Mayor",
    "sg:orig_category":"Cr\u00cda De Animales",
    "sg:phone":"+34 921 56 00 19",
    "sg:postcode":"40270",
    "sg:province":"Segovia",
    "wof:name":"Pascual Pascual Ignacio",
    "wof:placetype":"venue"
},
  "geometry": {"coordinates":[-4.2648239136,41.1222839355],"type":"Point"}
}