{
  "type": "Feature",
  "properties": {
    "iso:country":"ES",
    "sg:address":"Carrer de Comtat D'osona, 9",
    "sg:city":"Vic",
    "sg:orig_category":"Guarder\u00cdas",
    "sg:phone":"+34 938 89 19 32",
    "sg:postcode":"08500",
    "sg:province":"Barcelona",
    "wof:name":"Associacio Per La Promocio D'escoles Bressol El Ralet S.cv.",
    "wof:placetype":"venue"
},
  "geometry": {"coordinates":[2.2611958981,41.9341163635],"type":"Point"}
}