{
  "type": "Feature",
  "properties": {
    "addr:full":"Av Jaume Iii, 21 Palma Islas Baleares 07012",
    "addr:housenumber":"21",
    "addr:postcode":"07012",
    "addr:street":"Av Jaume Iii",
    "iso:country":"ES",
    "sg:address":"Av Jaume Iii, 21",
    "sg:city":"Palma",
    "sg:orig_category":"Cueros Y Pieles (al Por Mayor)",
    "sg:phone":"+34 971 71 51 39",
    "sg:postcode":"07012",
    "sg:province":"Islas Baleares",
    "wof:name":"Ramis Obrador Francisco",
    "wof:placetype":"venue"
},
  "geometry": {"coordinates":[2.6433150768,39.5723114014],"type":"Point"}
}