{
  "type": "Feature",
  "properties": {
    "iso:country":"ES",
    "sg:address":"Calle de Manuel Villalobos, 19",
    "sg:city":"Sevilla",
    "sg:orig_category":"Arquitectos",
    "sg:phone":"+34 954 36 72 78",
    "sg:postcode":"41009",
    "sg:province":"Sevilla",
    "wof:name":"Cercha 99 S.l.",
    "wof:placetype":"venue"
},
  "geometry": {"coordinates":[-5.9815878868,37.4044151306],"type":"Point"}
}