{
  "type": "Feature",
  "properties": {
    "iso:country":"ES",
    "sg:address":"Paraje Palomarejo, S/n",
    "sg:city":"Ani\u00f1on",
    "sg:orig_category":"Contenedores Para Dep\u00d3sito De Sustancias Peligrosas (fabricaci\u00d3n, Al Por Mayor)",
    "sg:phone":"+34 976 89 94 28",
    "sg:postcode":"50313",
    "sg:province":"Zaragoza",
    "wof:name":"Mapro Aragon S.l.l.",
    "wof:placetype":"venue"
},
  "geometry": {"coordinates":[-1.7076189518,41.4440383911],"type":"Point"}
}