{
  "type": "Feature",
  "properties": {
    "addr:full":"Carrer de Garcilaso, 154 Barcelona Barcelona 08027",
    "addr:housenumber":"154",
    "addr:postcode":"08027",
    "addr:street":"Carrer De Garcilaso",
    "iso:country":"ES",
    "sg:address":"Carrer de Garcilaso, 154",
    "sg:city":"Barcelona",
    "sg:orig_category":"Ropa Para Se\u00d1oras Y Caballeros (al Por Menor)",
    "sg:phone":"+34 934 08 27 09",
    "sg:postcode":"08027",
    "sg:province":"Barcelona",
    "wof:name":"Ye  Haiping",
    "wof:placetype":"venue"
},
  "geometry": {"coordinates":[2.1818044186,41.4233894348],"type":"Point"}
}