{
  "type": "Feature",
  "properties": {
    "iso:country":"ES",
    "sg:address":"Calle de Alhondiga, 27",
    "sg:city":"Granada",
    "sg:orig_category":"Ense\u00d1anza: Social, Param\u00c9dica",
    "sg:phone":"+34 958 25 14 68",
    "sg:postcode":"18001",
    "sg:province":"Granada",
    "wof:name":"Instituto De Estudios Sexologicos Al-andalus",
    "wof:placetype":"venue"
},
  "geometry": {"coordinates":[-3.6012825966,37.1748428345],"type":"Point"}
}