{
  "type": "Feature",
  "properties": {
    "iso:country":"ES",
    "sg:address":"Avda Carrascal (del), 6",
    "sg:city":"Jerez De La Frontera",
    "sg:orig_category":"Abogados",
    "sg:phone":"+34 956 18 04 49",
    "sg:postcode":"11407",
    "sg:province":"C\u00e1diz",
    "wof:name":"Rivas Mendez Maria Isabel",
    "wof:placetype":"venue"
},
  "geometry": {"coordinates":[-6.1350388527,36.7027206421],"type":"Point"}
}