{
  "type": "Feature",
  "properties": {
    "addr:full":"Plg. Industrial Ii, 2 Manzanares Ciudad Real 13200",
    "addr:postcode":"13200",
    "iso:country":"ES",
    "sg:address":"Plg. Industrial Ii, 2",
    "sg:city":"Manzanares",
    "sg:orig_category":"Jardiner\u00cdas, Vegetales, Art\u00cdculos De Jardiner\u00cda (al Por Menor)",
    "sg:phone":"+34 926 61 45 18",
    "sg:postcode":"13200",
    "sg:province":"Ciudad Real",
    "wof:name":"Orchis Garden S.l",
    "wof:placetype":"venue"
},
  "geometry": {"coordinates":[-3.3646690845,39.0051193237],"type":"Point"}
}