{
  "type": "Feature",
  "properties": {
    "addr:full":"Calle de Rio Ebro, S/n Cuarte Huerva Zaragoza 50410",
    "addr:housenumber":"s / n",
    "addr:postcode":"50410",
    "addr:street":"Calle De Rio Ebro",
    "iso:country":"ES",
    "sg:address":"Calle de Rio Ebro, S/n",
    "sg:city":"Cuarte Huerva",
    "sg:orig_category":"Cajas De Ahorro",
    "sg:phone":"+34 976 50 33 97",
    "sg:postcode":"50410",
    "sg:province":"Zaragoza",
    "sg:website":"www.cajarural.com",
    "wof:name":"Caja Rural Aragonesa Y De Los Pirineos",
    "wof:placetype":"venue"
},
  "geometry": {"coordinates":[-0.932092011,41.5992774963],"type":"Point"}
}