{
  "type": "Feature",
  "properties": {
    "iso:country":"ES",
    "sg:address":"Rua Blanco Porto, 3",
    "sg:city":"Pontevedra",
    "sg:classifiers":[
        {
            "category":"Autos & Motor Vehicles",
            "subcategory":"Automobile Sales",
            "type":"Retail Goods"
        }
    ],
    "sg:phone":"+34 986 84 51 91",
    "sg:postcode":"36001",
    "sg:province":"Pontevedra",
    "wof:name":"Autoescuela Pontevedra S.l.",
    "wof:placetype":"venue"
},
  "geometry": {"coordinates":[-8.6387023926,42.429473877],"type":"Point"}
}