{
  "type": "Feature",
  "properties": {
    "iso:country":"ES",
    "sg:address":"Cmno Salamanca, S/n",
    "sg:city":"Cabrerizos",
    "sg:orig_category":"Empresas De Carpinter\u00cda De Madera",
    "sg:phone":"+34 923 20 99 00",
    "sg:postcode":"37193",
    "sg:province":"Salamanca",
    "wof:name":"Puertas Y Ventanas S.a.",
    "wof:placetype":"venue"
},
  "geometry": {"coordinates":[-5.6128239632,40.9775695801],"type":"Point"}
}