{
  "type": "Feature",
  "properties": {
    "addr:full":"Avda Madre Maria Aznar, 24 Almeria Almer\u00eda 04009",
    "addr:housenumber":"24",
    "addr:postcode":"04009",
    "addr:street":"Avda Madre Maria Aznar",
    "iso:country":"ES",
    "sg:address":"Avda Madre Maria Aznar, 24",
    "sg:city":"Almeria",
    "sg:orig_category":"Cajas Para Embalar",
    "sg:phone":"+34 950 62 40 97",
    "sg:postcode":"04009",
    "sg:province":"Almer\u00eda",
    "wof:name":"Cajamar",
    "wof:placetype":"venue"
},
  "geometry": {"coordinates":[-2.4399290085,36.8544616699],"type":"Point"}
}