{
  "type": "Feature",
  "properties": {
    "addr:full":"Pol Ind La Barrena, S/n Tudela Navarra 31500",
    "addr:housenumber":"s",
    "addr:postcode":"31500",
    "addr:street":"Barrena;/ N",
    "iso:country":"ES",
    "sg:address":"Pol Ind La Barrena, S/n",
    "sg:city":"Tudela",
    "sg:orig_category":"Distribuci\u00d3n De Petr\u00d3leo Y Derivados",
    "sg:phone":"+34 948 84 86 00",
    "sg:postcode":"31500",
    "sg:province":"Navarra",
    "wof:name":"Servitrack S.a.",
    "wof:placetype":"venue"
},
  "geometry": {"coordinates":[-1.60295403,42.0619239807],"type":"Point"}
}