{
  "type": "Feature",
  "properties": {
    "addr:full":"Calle de Armeras (las), 14 Roldan Murcia 30709",
    "addr:housenumber":"14",
    "addr:postcode":"30709",
    "addr:street":"Calle De Armeras Las",
    "iso:country":"ES",
    "sg:address":"Calle de Armeras (las), 14",
    "sg:city":"Roldan",
    "sg:orig_category":"Producci\u00d3n De Abonos Y De Fertilizantes",
    "sg:phone":"+34 968 58 92 27",
    "sg:postcode":"30709",
    "sg:province":"Murcia",
    "wof:name":"Saura Roca Jose",
    "wof:placetype":"venue"
},
  "geometry": {"coordinates":[-1.0039789677,37.8001060486],"type":"Point"}
}