{
  "type": "Feature",
  "properties": {
    "iso:country":"ES",
    "sg:address":"Calle de Barcelona, 7",
    "sg:city":"Alacant",
    "sg:orig_category":"Inmobiliaria (agencias)",
    "sg:phone":"+34 965 21 87 53",
    "sg:postcode":"03013",
    "sg:province":"Alicante",
    "wof:name":"Crese Inversiones S.l.",
    "wof:placetype":"venue"
},
  "geometry": {"coordinates":[-0.4781042039,38.3545265198],"type":"Point"}
}