{
  "type": "Feature",
  "properties": {
    "iso:country":"ES",
    "sg:address":"Calle de Eugenia Astur, 11",
    "sg:city":"Tineo",
    "sg:orig_category":"Supermercados Y Hipermercados",
    "sg:phone":"+34 985 80 00 89",
    "sg:postcode":"33870",
    "sg:province":"Asturias",
    "wof:name":"Comercial Eugenia Astur S.l.",
    "wof:placetype":"venue"
},
  "geometry": {"coordinates":[-6.4139637947,43.3348197937],"type":"Point"}
}