{
  "type": "Feature",
  "properties": {
    "iso:country":"ES",
    "sg:address":"Calle de Doctor Severo Ochoa Del, 27",
    "sg:city":"Aviles",
    "sg:orig_category":"Electricidad: Instaladores",
    "sg:phone":"+34 985 52 25 16",
    "sg:postcode":"33401",
    "sg:province":"Asturias",
    "wof:name":"Instalaciones Electricas Msa Sl",
    "wof:placetype":"venue"
},
  "geometry": {"coordinates":[-5.9295811653,43.5552177429],"type":"Point"}
}