{
  "type": "Feature",
  "properties": {
    "iso:country":"ES",
    "sg:address":"Calle de Santiago Cuende, 8",
    "sg:city":"Madrid",
    "sg:orig_category":"Confecci\u00d3n De Trajes Para Se\u00d1oras",
    "sg:phone":"+34 915 25 40 17",
    "sg:postcode":"28025",
    "sg:province":"Madrid",
    "wof:name":"Manufacturas Manual S.l.",
    "wof:placetype":"venue"
},
  "geometry": {"coordinates":[-3.7312610149,40.3831863403],"type":"Point"}
}