{
  "type": "Feature",
  "properties": {
    "iso:country":"ES",
    "sg:address":"Rbla Badal, 65",
    "sg:city":"Barcelona",
    "sg:orig_category":"Promotores Constructores",
    "sg:phone":"+34 934 32 97 60",
    "sg:postcode":"08014",
    "sg:province":"Barcelona",
    "wof:name":"Bcn Inversiones 98 S.l.",
    "wof:placetype":"venue"
},
  "geometry": {"coordinates":[2.1327910423,41.3683433533],"type":"Point"}
}