{
  "type": "Feature",
  "properties": {
    "addr:full":"Carrer de Valencia, 213 Barcelona Barcelona 08007",
    "addr:housenumber":"213",
    "addr:postcode":"08007",
    "addr:street":"Carrer De Valencia",
    "iso:country":"ES",
    "sg:address":"Carrer de Valencia, 213",
    "sg:city":"Barcelona",
    "sg:orig_category":"Fabricaci\u00d3n De Mobiliario De Oficina",
    "sg:phone":"+34 934 51 70 77",
    "sg:postcode":"08007",
    "sg:province":"Barcelona",
    "sg:website":"www.esteliberica.com",
    "wof:name":"Kayso Mobiliario S.l.",
    "wof:placetype":"venue"
},
  "geometry": {"coordinates":[2.1600968838,41.3904342651],"type":"Point"}
}