{
  "type": "Feature",
  "properties": {
    "iso:country":"ES",
    "sg:address":"Calle de Eras De San Francisco, 20",
    "sg:city":"Torrijos",
    "sg:orig_category":"Persianas Interiores, Exteriores",
    "sg:phone":"+34 925 76 04 16",
    "sg:postcode":"45500",
    "sg:province":"Toledo",
    "wof:name":"Arevalillo Garcia Roman",
    "wof:placetype":"venue"
},
  "geometry": {"coordinates":[-4.283205986,39.9799842834],"type":"Point"}
}