{
  "type": "Feature",
  "properties": {
    "addr:full":"Mercavalencia, S/n Valencia Valencia 46013",
    "addr:housenumber":"/ n",
    "addr:postcode":"46013",
    "addr:street":"Mercavalencia S",
    "iso:country":"ES",
    "sg:address":"Mercavalencia, S/n",
    "sg:city":"Valencia",
    "sg:orig_category":"Almacenes Frigor\u00cdficos",
    "sg:phone":"+34 963 67 93 68",
    "sg:postcode":"46013",
    "sg:province":"Valencia",
    "wof:name":"Sociedad Agraria De Transformacion 42 Los Gonzalez",
    "wof:placetype":"venue"
},
  "geometry": {"coordinates":[-0.3769130111,39.4687919617],"type":"Point"}
}