{
  "type": "Feature",
  "properties": {
    "iso:country":"ES",
    "sg:address":"Calle de Ronda De Andujar, 7",
    "sg:city":"Cordoba",
    "sg:orig_category":"Material Y Accesorios Para Bisuter\u00cda Y Joyer\u00cda",
    "sg:phone":"+34 957 48 11 68",
    "sg:postcode":"14002",
    "sg:province":"C\u00f3rdoba",
    "wof:name":"Rivero Rivero S. A.",
    "wof:placetype":"venue"
},
  "geometry": {"coordinates":[-4.7684440613,37.8865737915],"type":"Point"}
}