{
  "type": "Feature",
  "properties": {
    "addr:full":"Calle de Calderon, 46 Santa Fe Granada 18320",
    "addr:housenumber":"46",
    "addr:postcode":"18320",
    "addr:street":"Calle De Calderon",
    "iso:country":"ES",
    "sg:address":"Calle de Calderon, 46",
    "sg:city":"Santa Fe",
    "sg:orig_category":"Estancos",
    "sg:phone":"+34 958 51 00 08",
    "sg:postcode":"18320",
    "sg:province":"Granada",
    "wof:name":"Freire Fernandez Jesus",
    "wof:placetype":"venue"
},
  "geometry": {"coordinates":[-3.7165031433,37.1909713745],"type":"Point"}
}