{
  "type": "Feature",
  "properties": {
    "iso:country":"ES",
    "sg:address":"Calle de Poligono Margaritas, Las, S/n",
    "sg:city":"Melilla",
    "sg:orig_category":"Muebles, Minoristas",
    "sg:phone":"+34 952 67 73 73",
    "sg:postcode":"52006",
    "sg:province":"Melilla",
    "wof:name":"Martinez Armengol Julio Jose",
    "wof:placetype":"venue"
},
  "geometry": {"coordinates":[-2.9361999035,35.2828216553],"type":"Point"}
}