{
  "type": "Feature",
  "properties": {
    "addr:full":"Calle de San Rafael, 8 Monte Vedat Valencia 46901",
    "addr:housenumber":"8",
    "addr:postcode":"46901",
    "addr:street":"Calle De San Rafael;Vedat",
    "iso:country":"ES",
    "sg:address":"Calle de San Rafael, 8",
    "sg:city":"Monte Vedat",
    "sg:orig_category":"Maquinaria Para Industrias Diversas",
    "sg:phone":"+34 961 55 50 13",
    "sg:postcode":"46901",
    "sg:province":"Valencia",
    "wof:name":"Iberpress Maquinaria Slu",
    "wof:placetype":"venue"
},
  "geometry": {"coordinates":[-0.4884090126,39.4261741638],"type":"Point"}
}