{
  "type": "Feature",
  "properties": {
    "iso:country":"ES",
    "sg:address":"Avgd Riola, 1",
    "sg:city":"Sueca",
    "sg:orig_category":"Asociaciones Humanitarias, De Cooperaci\u00d3n, De Acci\u00d3n Social",
    "sg:phone":"+34 962 13 70 34",
    "sg:postcode":"46410",
    "sg:province":"Valencia",
    "wof:name":"Reto A La Esperanza Asociacion",
    "wof:placetype":"venue"
},
  "geometry": {"coordinates":[-0.3076440096,39.2027435303],"type":"Point"}
}