{
  "type": "Feature",
  "properties": {
    "addr:full":"Avda Reyes Catolicos, 4 Baza Granada 18800",
    "addr:housenumber":"4",
    "addr:postcode":"18800",
    "addr:street":"Avda Reyes Catolicos",
    "iso:country":"ES",
    "sg:address":"Avda Reyes Catolicos, 4",
    "sg:city":"Baza",
    "sg:orig_category":"Inmobiliaria (agencias)",
    "sg:phone":"+34 958 70 34 20",
    "sg:postcode":"18800",
    "sg:province":"Granada",
    "wof:name":"Inmobiliaria Dama De Baza S.l.",
    "wof:placetype":"venue"
},
  "geometry": {"coordinates":[-2.7746129036,37.4924697876],"type":"Point"}
}