{
  "type": "Feature",
  "properties": {
    "iso:country":"ES",
    "sg:address":"Avda Buenos Aires, 6",
    "sg:city":"Lalin",
    "sg:orig_category":"Zapatos (al Por Menor)",
    "sg:phone":"+34 986 78 00 46",
    "sg:postcode":"36500",
    "sg:province":"Pontevedra",
    "wof:name":"Taboada Lorenzo Amadeo",
    "wof:placetype":"venue"
},
  "geometry": {"coordinates":[-8.1121387482,42.6544914246],"type":"Point"}
}