{
  "type": "Feature",
  "properties": {
    "addr:full":"Calle de Juan Ramon Jimenez (de), 6 Alcobendas Madrid 28100",
    "addr:postcode":"28100",
    "addr:street":"Calle De Juan Ramon Jimenez De 6",
    "iso:country":"ES",
    "sg:address":"Calle de Juan Ramon Jimenez (de), 6",
    "sg:city":"Alcobendas",
    "sg:orig_category":"Deportes Y Ocio: Art\u00cdculos Y Ropas (al Por Menor Y Accesorios)",
    "sg:phone":"+34 916 61 76 07",
    "sg:postcode":"28100",
    "sg:province":"Madrid",
    "sg:website":"www.fitnessonline.es",
    "wof:name":"Thomas Jr Distribuciones S.l.",
    "wof:placetype":"venue"
},
  "geometry": {"coordinates":[-3.6581702232,40.5463752747],"type":"Point"}
}