{
  "type": "Feature",
  "properties": {
    "iso:country":"ES",
    "sg:address":"Carrer de Francesc Bastos (de), 18",
    "sg:city":"Tarragona",
    "sg:orig_category":"Peluquer\u00cdas, Peluquer\u00cda Mixta",
    "sg:phone":"+34 977 24 12 53",
    "sg:postcode":"43005",
    "sg:province":"Tarragona",
    "wof:name":"Estilistes Catalunya S.l.",
    "wof:placetype":"venue"
},
  "geometry": {"coordinates":[1.242264986,41.1146202087],"type":"Point"}
}