{
  "type": "Feature",
  "properties": {
    "iso:country":"ES",
    "sg:address":"El Rodenal, S/n",
    "sg:city":"Sotos",
    "sg:orig_category":"Albergues",
    "sg:phone":"+34 969 28 80 83",
    "sg:postcode":"16143",
    "sg:province":"Cuenca",
    "wof:name":"Ayuntamiento De Sotos",
    "wof:placetype":"venue"
},
  "geometry": {"coordinates":[-2.1596713066,40.196521759],"type":"Point"}
}