{
  "type": "Feature",
  "properties": {
    "iso:country":"ES",
    "sg:address":"Plaz Mercado, 12",
    "sg:city":"Salamanca",
    "sg:orig_category":"Telas Y Sedas (al Por Menor)",
    "sg:phone":"+34 923 21 26 11",
    "sg:postcode":"37001",
    "sg:province":"Salamanca",
    "wof:name":"Herederos De Maria Fernandez C.b.",
    "wof:placetype":"venue"
},
  "geometry": {"coordinates":[-5.6630659103,40.9643440247],"type":"Point"}
}