{
  "type": "Feature",
  "properties": {
    "addr:full":"Calle de Rosario, 9 Villamartin C\u00e1diz 11650",
    "addr:housenumber":"9",
    "addr:postcode":"11650",
    "addr:street":"Calle De Rosario;Ca\u0301Diz",
    "iso:country":"ES",
    "sg:address":"Calle de Rosario, 9",
    "sg:city":"Villamartin",
    "sg:orig_category":"Servicio De Salud",
    "sg:phone":"+34 956 73 09 11",
    "sg:postcode":"11650",
    "sg:province":"C\u00e1diz",
    "wof:name":"Marquez Bocanegra Jose",
    "wof:placetype":"venue"
},
  "geometry": {"coordinates":[-5.6391038895,36.8587188721],"type":"Point"}
}