{
  "type": "Feature",
  "properties": {
    "addr:full":"Plaz Ducal, 1 Marchena Sevilla 41620",
    "addr:housenumber":"1",
    "addr:postcode":"41620",
    "addr:street":"Ducal",
    "iso:country":"ES",
    "sg:address":"Plaz Ducal, 1",
    "sg:city":"Marchena",
    "sg:orig_category":"Ense\u00d1anza, Formaci\u00d3n Profesional: Aprendizaje",
    "sg:phone":"+34 954 84 35 61",
    "sg:postcode":"41620",
    "sg:province":"Sevilla",
    "wof:name":"Organismo Provincial De Asistencia Economica Y Fiscal",
    "wof:placetype":"venue"
},
  "geometry": {"coordinates":[-5.4159288406,37.3331260681],"type":"Point"}
}