{
  "type": "Feature",
  "properties": {
    "addr:full":"Calle de Mesaola, S/n Candelaria Santa Cruz De Tenerife 38530",
    "addr:housenumber":"s",
    "addr:postcode":"38530",
    "addr:street":"Calle De Mesaola;/ N",
    "iso:country":"ES",
    "sg:address":"Calle de Mesaola, S/n",
    "sg:city":"Candelaria",
    "sg:orig_category":"Centros Empresariales",
    "sg:phone":"+34 922 95 60 11",
    "sg:postcode":"38530",
    "sg:province":"Santa Cruz De Tenerife",
    "wof:name":"Rodriguez Hernandez Francisco Javier",
    "wof:placetype":"venue"
},
  "geometry": {"coordinates":[-16.3717498779,28.3555545807],"type":"Point"}
}