{
  "type": "Feature",
  "properties": {
    "iso:country":"ES",
    "sg:address":"Carrer de Antoni Roig (d'), 63",
    "sg:city":"Torredembarra",
    "sg:orig_category":"Ciencias Ocultas",
    "sg:phone":"+34 977 64 20 87",
    "sg:postcode":"43830",
    "sg:province":"Tarragona",
    "wof:name":"Carrera Viu Ramon",
    "wof:placetype":"venue"
},
  "geometry": {"coordinates":[1.3995740414,41.1441497803],"type":"Point"}
}