{
  "type": "Feature",
  "properties": {
    "addr:full":"Calle de Margarita, 6 Morales Vino Zamora 49190",
    "addr:housenumber":"6",
    "addr:postcode":"49190",
    "addr:street":"Calle De Margarita;Zamora",
    "iso:country":"ES",
    "sg:address":"Calle de Margarita, 6",
    "sg:city":"Morales Vino",
    "sg:orig_category":"Psic\u00d3logos",
    "sg:phone":"+34 980 57 42 22",
    "sg:postcode":"49190",
    "sg:province":"Zamora",
    "wof:name":"Agyserza S.l.l.",
    "wof:placetype":"venue"
},
  "geometry": {"coordinates":[-5.7373766899,41.4409637451],"type":"Point"}
}