{
  "type": "Feature",
  "properties": {
    "iso:country":"ES",
    "sg:address":"Calle de Juan Bautista De Toledo, 8",
    "sg:city":"Madrid",
    "sg:orig_category":"Tapicer\u00cdas",
    "sg:phone":"+34 915 61 01 14",
    "sg:postcode":"28002",
    "sg:province":"Madrid",
    "wof:name":"Nieto Avila Juan Carlos",
    "wof:placetype":"venue"
},
  "geometry": {"coordinates":[-3.6738390923,40.4433670044],"type":"Point"}
}