{
  "type": "Feature",
  "properties": {
    "addr:full":"Pe\u00f1a Salon, 39 Lugo Asturias 33192",
    "addr:housenumber":"39",
    "addr:postcode":"33192",
    "iso:country":"ES",
    "sg:address":"Pe\u00f1a Salon, 39",
    "sg:city":"Lugo",
    "sg:orig_category":"Congelados: Productos Alimentarios (al Por Menor)",
    "sg:phone":"+34 985 26 74 92",
    "sg:postcode":"33192",
    "sg:province":"Asturias",
    "wof:name":"Distribucion Y Logistica Asturiana S.l.",
    "wof:placetype":"venue"
},
  "geometry": {"coordinates":[-5.7745718956,43.4596939087],"type":"Point"}
}