{
  "type": "Feature",
  "properties": {
    "addr:full":"Calle de Angel Ganivet, 1 Granada Granada 18009",
    "addr:housenumber":"1",
    "addr:postcode":"18009",
    "addr:street":"Calle De Angel Ganivet",
    "iso:country":"ES",
    "sg:address":"Calle de Angel Ganivet, 1",
    "sg:city":"Granada",
    "sg:orig_category":"Abogados",
    "sg:phone":"+34 958 22 82 59",
    "sg:postcode":"18009",
    "sg:province":"Granada",
    "wof:name":"Nicasio Angulo Jimenez Y Otros C.b.",
    "wof:placetype":"venue"
},
  "geometry": {"coordinates":[-3.5994153023,37.1734809875],"type":"Point"}
}