{
  "type": "Feature",
  "properties": {
    "iso:country":"ES",
    "sg:address":"Avda Happag Lloyd, S/n",
    "sg:city":"Urbanizacion Ca\u00e7ada Del Rio",
    "sg:orig_category":"Art\u00cdculos De Regalo (al Por Menor)",
    "sg:phone":"+34 928 54 71 83",
    "sg:postcode":"35627",
    "sg:province":"Las Palmas",
    "wof:name":"Asnani  Vijay",
    "wof:placetype":"venue"
},
  "geometry": {"coordinates":[-15.4300060272,28.1248226166],"type":"Point"}
}