{
  "type": "Feature",
  "properties": {
    "addr:full":"Pol Ind Pollenca, Km. 0054,1 Pollen\u00e7a Islas Baleares 07460",
    "addr:postcode":"07460",
    "addr:street":"Pollenca Km. 0054,1",
    "iso:country":"ES",
    "sg:address":"Pol Ind Pollenca, Km. 0054,1",
    "sg:city":"Pollen\u00e7a",
    "sg:orig_category":"Distribuci\u00d3n De Petr\u00d3leo Y Derivados",
    "sg:phone":"+34 971 53 20 11",
    "sg:postcode":"07460",
    "sg:province":"Islas Baleares",
    "wof:name":"Pescados Oliver S.l.",
    "wof:placetype":"venue"
},
  "geometry": {"coordinates":[3.0190351009,39.8781204224],"type":"Point"}
}