{
  "type": "Feature",
  "properties": {
    "addr:full":"Carr Vall-llobera, 33 Caldes Malavella Girona 17455",
    "addr:housenumber":"33",
    "addr:postcode":"17455",
    "addr:street":"Carr Vall-Llobera",
    "iso:country":"ES",
    "sg:address":"Carr Vall-llobera, 33",
    "sg:city":"Caldes Malavella",
    "sg:orig_category":"Negocio De Materiales De Construcci\u00d3n",
    "sg:phone":"+34 972 47 01 82",
    "sg:postcode":"17455",
    "sg:province":"Girona",
    "wof:name":"Materials Tauler S.l.",
    "wof:placetype":"venue"
},
  "geometry": {"coordinates":[2.8018240929,41.8385505676],"type":"Point"}
}