{
  "type": "Feature",
  "properties": {
    "addr:full":"Avgd Bufala, 20 Badalona Barcelona 08915",
    "addr:housenumber":"20",
    "addr:postcode":"08915",
    "addr:street":"Bufala",
    "iso:country":"ES",
    "sg:address":"Avgd Bufala, 20",
    "sg:city":"Badalona",
    "sg:orig_category":"Sociedades, Compa\u00d1\u00cdas Aseguradoras",
    "sg:phone":"+34 933 97 27 12",
    "sg:postcode":"08915",
    "sg:province":"Barcelona",
    "wof:name":"Mapfre Servicios De Informatica",
    "wof:placetype":"venue"
},
  "geometry": {"coordinates":[2.2414391041,41.4580230713],"type":"Point"}
}