{
  "type": "Feature",
  "properties": {
    "addr:full":"Calle de Arriba, 1 Lucena Puerto Huelva 21820",
    "addr:housenumber":"1",
    "addr:postcode":"21820",
    "addr:street":"Calle De Arriba;Puerto",
    "iso:country":"ES",
    "sg:address":"Calle de Arriba, 1",
    "sg:city":"Lucena Puerto",
    "sg:orig_category":"Asesor\u00cda De Formaci\u00d3n Y Gesti\u00d3n De Personal",
    "sg:phone":"+34 959 36 00 15",
    "sg:postcode":"21820",
    "sg:province":"Huelva",
    "wof:name":"Staff De Asesoramientos S.l.",
    "wof:placetype":"venue"
},
  "geometry": {"coordinates":[-6.7299733162,37.3036804199],"type":"Point"}
}