{
  "type": "Feature",
  "properties": {
    "addr:full":"Avda Pirineos (de Los), 7 Huesca Huesca 22004",
    "addr:housenumber":"7",
    "addr:postcode":"22004",
    "addr:street":"Avda Pirineos De Los",
    "iso:country":"ES",
    "sg:address":"Avda Pirineos (de Los), 7",
    "sg:city":"Huesca",
    "sg:orig_category":"Cajas De Ahorro",
    "sg:phone":"+34 974 23 85 00",
    "sg:postcode":"22004",
    "sg:province":"Huesca",
    "wof:name":"Caixa D'estalvis Del Penedes",
    "wof:placetype":"venue"
},
  "geometry": {"coordinates":[-0.4164899886,42.1418190002],"type":"Point"}
}