{
  "type": "Feature",
  "properties": {
    "addr:full":"Av Catalunya, 26 Bellpuig Lleida 25250",
    "addr:housenumber":"26",
    "addr:postcode":"25250",
    "addr:street":"Av Catalunya",
    "iso:country":"ES",
    "sg:address":"Av Catalunya, 26",
    "sg:city":"Bellpuig",
    "sg:orig_category":"Pescader\u00cdas (al Por Menor)",
    "sg:phone":"+34 973 32 04 36",
    "sg:postcode":"25250",
    "sg:province":"Lleida",
    "wof:name":"Berenguer Aritzeta Lourdes",
    "wof:placetype":"venue"
},
  "geometry": {"coordinates":[1.0113259554,41.6279716492],"type":"Point"}
}