{
  "type": "Feature",
  "properties": {
    "addr:full":"Calle de Villoria, 18 Veguellina Orbigo Le\u00f3n 24350",
    "addr:housenumber":"18",
    "addr:postcode":"24350",
    "addr:street":"Calle De Villoria;Leo\u0301N",
    "iso:country":"ES",
    "sg:address":"Calle de Villoria, 18",
    "sg:city":"Veguellina Orbigo",
    "sg:orig_category":"Cerrajer\u00cda, Ferrallista",
    "sg:phone":"+34 987 37 42 82",
    "sg:postcode":"24350",
    "sg:province":"Le\u00f3n",
    "wof:name":"Llanos Moran Antonio",
    "wof:placetype":"venue"
},
  "geometry": {"coordinates":[-5.8845500946,42.4307174683],"type":"Point"}
}