{
  "type": "Feature",
  "properties": {
    "iso:country":"ES",
    "sg:address":"Rua Circunvalacion D. Aurelio, 17",
    "sg:city":"Cuntis",
    "sg:orig_category":"Distribuci\u00d3n De Petr\u00d3leo Y Derivados",
    "sg:phone":"+34 986 54 81 54",
    "sg:postcode":"36670",
    "sg:province":"Pontevedra",
    "wof:name":"Ameijeiras Silva Manuel Pedro",
    "wof:placetype":"venue"
},
  "geometry": {"coordinates":[-8.5623168945,42.6330070496],"type":"Point"}
}