{
  "type": "Feature",
  "properties": {
    "addr:full":"Carrer de Antoni Gaudi, 64 S. Boi Llobregat Barcelona 08830",
    "addr:housenumber":"64",
    "addr:postcode":"08830",
    "addr:street":"Carrer De Antoni Gaudi",
    "iso:country":"ES",
    "sg:address":"Carrer de Antoni Gaudi, 64",
    "sg:city":"S. Boi Llobregat",
    "sg:orig_category":"Promotores Constructores",
    "sg:phone":"+34 936 54 15 60",
    "sg:postcode":"08830",
    "sg:province":"Barcelona",
    "sg:website":"www.gestiongaudi.com",
    "wof:name":"Ybansol S.l.",
    "wof:placetype":"venue"
},
  "geometry": {"coordinates":[2.0292270184,41.3487358093],"type":"Point"}
}