{
  "type": "Feature",
  "properties": {
    "addr:full":"Calle de Florian Rey, 18 Zaragoza Zaragoza 50002",
    "addr:housenumber":"18",
    "addr:postcode":"50002",
    "addr:street":"Calle De Florian Rey",
    "iso:country":"ES",
    "sg:address":"Calle de Florian Rey, 18",
    "sg:city":"Zaragoza",
    "sg:orig_category":"Fabricaci\u00d3n De Sobres, Bolsas Y Fundas",
    "sg:phone":"+34 976 39 69 48",
    "sg:postcode":"50002",
    "sg:province":"Zaragoza",
    "wof:name":"Pastor Aunes Pascual Matias",
    "wof:placetype":"venue"
},
  "geometry": {"coordinates":[-0.8631539941,41.6496009827],"type":"Point"}
}