{
  "type": "Feature",
  "properties": {
    "addr:full":"Avda Soto Mayor, 5 Trubia Asturias 33100",
    "addr:housenumber":"5",
    "addr:postcode":"33100",
    "addr:street":"Avda Soto Mayor;Asturias",
    "iso:country":"ES",
    "sg:address":"Avda Soto Mayor, 5",
    "sg:city":"Trubia",
    "sg:orig_category":"Bancos",
    "sg:phone":"+34 985 78 40 08",
    "sg:postcode":"33100",
    "sg:province":"Asturias",
    "wof:name":"Banc Sabadell S.a.",
    "wof:placetype":"venue"
},
  "geometry": {"coordinates":[-5.9715838432,43.3449516296],"type":"Point"}
}