{
  "type": "Feature",
  "properties": {
    "addr:full":"Plaz San Felipe Neri, 6 Valencia Valencia 46021",
    "addr:housenumber":"6",
    "addr:postcode":"46021",
    "addr:street":"Plaz San Felipe Neri",
    "iso:country":"ES",
    "sg:address":"Plaz San Felipe Neri, 6",
    "sg:city":"Valencia",
    "sg:orig_category":"Empresarios",
    "sg:phone":"+34 963 69 89 47",
    "sg:postcode":"46021",
    "sg:province":"Valencia",
    "wof:name":"Decoraciones Algiros S.l.",
    "wof:placetype":"venue"
},
  "geometry": {"coordinates":[-0.3537429869,39.4697380066],"type":"Point"}
}