{
  "type": "Feature",
  "properties": {
    "iso:country":"ES",
    "sg:address":"Carrer de Bruc, 7",
    "sg:city":"Barcelona",
    "sg:orig_category":"Abogados",
    "sg:phone":"+34 933 10 03 61",
    "sg:postcode":"08010",
    "sg:province":"Barcelona",
    "wof:name":"Rodriguez Fernandez Ramon",
    "wof:placetype":"venue"
},
  "geometry": {"coordinates":[2.175538063,41.3896026611],"type":"Point"}
}