{
  "type": "Feature",
  "properties": {
    "iso:country":"ES",
    "sg:address":"Carrer de Moratin, 16",
    "sg:city":"Barcelona",
    "sg:orig_category":"Material Y Suministros Para Fotocopiadoras, Reprograf\u00cda",
    "sg:phone":"+34 933 57 72 29",
    "sg:postcode":"08032",
    "sg:province":"Barcelona",
    "wof:name":"Contact Graf S. A.",
    "wof:placetype":"venue"
},
  "geometry": {"coordinates":[2.153578043,41.4252471924],"type":"Point"}
}