{
  "type": "Feature",
  "properties": {
    "iso:country":"ES",
    "sg:address":"Calle de Estacion, 6",
    "sg:city":"Mora",
    "sg:orig_category":"Cerrajer\u00cda, Ferrallista",
    "sg:phone":"+34 925 34 14 84",
    "sg:postcode":"45400",
    "sg:province":"Toledo",
    "wof:name":"Martin Mora C.b.",
    "wof:placetype":"venue"
},
  "geometry": {"coordinates":[-3.7788009644,39.6833496094],"type":"Point"}
}