{
  "type": "Feature",
  "properties": {
    "addr:full":"Rua Casta\u00d1al (do), S/n Pontevedra Pontevedra 36004",
    "addr:housenumber":"s / n",
    "addr:postcode":"36004",
    "addr:street":"Rua Castan\u0303Al",
    "iso:country":"ES",
    "sg:address":"Rua Casta\u00d1al (do), S/n",
    "sg:city":"Pontevedra",
    "sg:orig_category":"Imprenta",
    "sg:phone":"+34 986 84 14 04",
    "sg:postcode":"36004",
    "sg:province":"Pontevedra",
    "wof:name":"Lorenzo Macias Santiago",
    "wof:placetype":"venue"
},
  "geometry": {"coordinates":[-8.629278183,42.4292831421],"type":"Point"}
}