{
  "type": "Feature",
  "properties": {
    "addr:full":"Pol Ind Los Llanos, 2 Torre Campo Ja\u00e9n 23640",
    "addr:housenumber":"2",
    "addr:postcode":"23640",
    "addr:street":"Llanos;Jae\u0301N",
    "iso:country":"ES",
    "sg:address":"Pol Ind Los Llanos, 2",
    "sg:city":"Torre Campo",
    "sg:orig_category":"Organizaci\u00d3n De Actos, Seminarios Y Congresos",
    "sg:phone":"+34 953 56 85 77",
    "sg:postcode":"23640",
    "sg:province":"Ja\u00e9n",
    "wof:name":"Eliche Cano Felix",
    "wof:placetype":"venue"
},
  "geometry": {"coordinates":[-3.7906870842,37.7650947571],"type":"Point"}
}