{
  "type": "Feature",
  "properties": {
    "addr:full":"Calle de Toneleros, 5 Sevilla Sevilla 41001",
    "addr:housenumber":"5",
    "addr:postcode":"41001",
    "addr:street":"Calle De Toneleros",
    "iso:country":"ES",
    "sg:address":"Calle de Toneleros, 5",
    "sg:city":"Sevilla",
    "sg:orig_category":"Arquitectos",
    "sg:phone":"+34 954 56 16 30",
    "sg:postcode":"41001",
    "sg:province":"Sevilla",
    "wof:name":"Pe\u00f1a Martin Jorge",
    "wof:placetype":"venue"
},
  "geometry": {"coordinates":[-5.9963898659,37.3860244751],"type":"Point"}
}