{
  "type": "Feature",
  "properties": {
    "iso:country":"ES",
    "sg:address":"Cust Morana La, 7",
    "sg:city":"Zamora",
    "sg:orig_category":"Librer\u00cdas",
    "sg:phone":"+34 980 52 58 60",
    "sg:postcode":"49025",
    "sg:province":"Zamora",
    "wof:name":"Martin Calvo Melchor",
    "wof:placetype":"venue"
},
  "geometry": {"coordinates":[-5.7457342148,41.5033302307],"type":"Point"}
}