{
  "type": "Feature",
  "properties": {
    "iso:country":"ES",
    "sg:address":"Calle de Trinitarios, 25",
    "sg:city":"Toledo",
    "sg:orig_category":"Electrodom\u00c9sticos (al Por Menor)",
    "sg:phone":"+34 925 21 27 05",
    "sg:postcode":"45003",
    "sg:province":"Toledo",
    "wof:name":"Corvitel S. A.",
    "wof:placetype":"venue"
},
  "geometry": {"coordinates":[-4.0228819847,39.8658409119],"type":"Point"}
}