{
  "type": "Feature",
  "properties": {
    "iso:country":"ES",
    "sg:address":"Carrer de Riera De Tena, 44",
    "sg:city":"Barcelona",
    "sg:orig_category":"Guarder\u00cdas",
    "sg:phone":"+34 934 31 99 43",
    "sg:postcode":"08014",
    "sg:province":"Barcelona",
    "wof:name":"Maria T. Nadal S.l.",
    "wof:placetype":"venue"
},
  "geometry": {"coordinates":[2.1337399483,41.3720283508],"type":"Point"}
}