{
  "type": "Feature",
  "properties": {
    "addr:full":"Rua Alejandro Cerecedo, 17 Vilagarcia Pontevedra 36600",
    "addr:housenumber":"17",
    "addr:postcode":"36600",
    "addr:street":"Rua Alejandro Cerecedo",
    "iso:country":"ES",
    "sg:address":"Rua Alejandro Cerecedo, 17",
    "sg:city":"Vilagarcia",
    "sg:orig_category":"Ropa Para Se\u00d1oras (al Por Menor)",
    "sg:phone":"+34 986 50 72 41",
    "sg:postcode":"36600",
    "sg:province":"Pontevedra",
    "wof:name":"Gabela Muller S.l.",
    "wof:placetype":"venue"
},
  "geometry": {"coordinates":[-8.7668190002,42.593460083],"type":"Point"}
}