{
  "type": "Feature",
  "properties": {
    "iso:country":"ES",
    "sg:address":"Avda Juan Sebastian Elcano, 45",
    "sg:city":"Badajoz",
    "sg:orig_category":"Asesor\u00cda Fiscal Y Jur\u00cddica",
    "sg:phone":"+34 924 20 05 43",
    "sg:postcode":"06003",
    "sg:province":"Badajoz",
    "wof:name":"Jose Santiago Lavado Rubio Y Asociados Sl",
    "wof:placetype":"venue"
},
  "geometry": {"coordinates":[-6.9671239853,38.8705711365],"type":"Point"}
}