{
  "type": "Feature",
  "properties": {
    "iso:country":"ES",
    "sg:address":"Pla\u00c7 Baix (de), 1",
    "sg:city":"Petrer",
    "sg:orig_category":"Ense\u00d1anza, Formaci\u00d3n Profesional: Aprendizaje",
    "sg:phone":"+34 965 37 79 61",
    "sg:postcode":"03610",
    "sg:province":"Alicante",
    "wof:name":"Ayuntamiento De Petrer",
    "wof:placetype":"venue"
},
  "geometry": {"coordinates":[-0.7731289864,38.4793281555],"type":"Point"}
}