{
  "type": "Feature",
  "properties": {
    "addr:full":"Avda Virgen De Las Angustias, 2 Cuenca Cuenca 16003",
    "addr:housenumber":"2",
    "addr:postcode":"16003",
    "addr:street":"Avda Virgen De Las Angustias",
    "iso:country":"ES",
    "sg:address":"Avda Virgen De Las Angustias, 2",
    "sg:city":"Cuenca",
    "sg:orig_category":"Alimentaci\u00d3n General (al Por Menor)",
    "sg:phone":"+34 969 22 17 14",
    "sg:postcode":"16003",
    "sg:province":"Cuenca",
    "wof:name":"Mora Campos Francisco",
    "wof:placetype":"venue"
},
  "geometry": {"coordinates":[-2.1381249428,40.0651512146],"type":"Point"}
}