{
  "type": "Feature",
  "properties": {
    "iso:country":"ES",
    "sg:address":"Calle de Herbes, 1",
    "sg:city":"Castellon De La Plana",
    "sg:orig_category":"Comercio De Piezas De Recambio Y De Accesorios De Veh\u00cdculos, Veh\u00cdculos Industriales",
    "sg:phone":"+34 964 25 04 88",
    "sg:postcode":"12006",
    "sg:province":"Castell\u00f3n",
    "wof:name":"Auto Kit 4 Por 4 S.l.",
    "wof:placetype":"venue"
},
  "geometry": {"coordinates":[-0.0584390014,39.9714584351],"type":"Point"}
}