{
  "type": "Feature",
  "properties": {
    "iso:country":"ES",
    "sg:address":"Calle de Santa Eulalia, 37",
    "sg:city":"Merida",
    "sg:orig_category":"Hielo Artificial (fabricaci\u00d3n, Distribuci\u00d3n)",
    "sg:phone":"+34 924 31 13 54",
    "sg:postcode":"06800",
    "sg:province":"Badajoz",
    "wof:name":"Amoros E Hijos S.l.",
    "wof:placetype":"venue"
},
  "geometry": {"coordinates":[-6.343735218,38.9174728394],"type":"Point"}
}