{
  "type": "Feature",
  "properties": {
    "iso:country":"ES",
    "sg:address":"Rua Santiago Del Estero (de), 8",
    "sg:city":"Santiago De Compostela",
    "sg:orig_category":"Cl\u00cdnicas Dentales",
    "sg:phone":"+34 981 59 88 49",
    "sg:postcode":"15706",
    "sg:province":"La Coru\u00f1a",
    "wof:name":"Basanta Matos Ricardo",
    "wof:placetype":"venue"
},
  "geometry": {"coordinates":[-8.550784111,42.8745346069],"type":"Point"}
}