{
  "type": "Feature",
  "properties": {
    "iso:country":"ES",
    "sg:address":"Plaz Universidad, 7",
    "sg:city":"Valladolid",
    "sg:orig_category":"Molduras, Junquillos, Listones Y Molduras Perforadas",
    "sg:phone":"+34 983 30 00 20",
    "sg:postcode":"47002",
    "sg:province":"Valladolid",
    "wof:name":"Alfayete Alvarez Roberto",
    "wof:placetype":"venue"
},
  "geometry": {"coordinates":[-4.7221574783,41.6526412964],"type":"Point"}
}