{
  "type": "Feature",
  "properties": {
    "iso:country":"ES",
    "sg:address":"Cig\u00fce\u00f1a, 18",
    "sg:city":"Pareton",
    "sg:orig_category":"Centros Empresariales",
    "sg:phone":"+34 968 48 43 71",
    "sg:postcode":"30858",
    "sg:province":"Murcia",
    "wof:name":"Dilley  Anne Denise",
    "wof:placetype":"venue"
},
  "geometry": {"coordinates":[-1.4035190344,37.7123222351],"type":"Point"}
}