{
  "type": "Feature",
  "properties": {
    "iso:country":"ES",
    "sg:address":"Av Jaume I, 87",
    "sg:city":"Mollet Valles",
    "sg:orig_category":"Ropa Para Se\u00d1oras Y Caballeros (al Por Menor)",
    "sg:phone":"+34 935 93 32 43",
    "sg:postcode":"08100",
    "sg:province":"Barcelona",
    "wof:name":"Garcia Ribas Ana Maria",
    "wof:placetype":"venue"
},
  "geometry": {"coordinates":[2.2135355473,41.5405578613],"type":"Point"}
}