{
  "type": "Feature",
  "properties": {
    "iso:country":"ES",
    "sg:address":"Calle de Mayor, 43",
    "sg:city":"Caravaca Cruz",
    "sg:orig_category":"Arte, Cultura, Edici\u00d3n",
    "sg:phone":"+34 968 70 83 84",
    "sg:postcode":"30400",
    "sg:province":"Murcia",
    "wof:name":"Pe\u00f1a Taurina Caravaque\u00f1a",
    "wof:placetype":"venue"
},
  "geometry": {"coordinates":[-1.8611090183,38.1068000793],"type":"Point"}
}