{
  "type": "Feature",
  "properties": {
    "iso:country":"ES",
    "sg:address":"Calle de Lorenzo Abru\u00d1edo, 20",
    "sg:city":"Oviedo",
    "sg:orig_category":"Perfumer\u00cda Y Cosm\u00c9tica (fabricaci\u00d3n, Al Por Mayor)",
    "sg:phone":"+34 985 11 34 21",
    "sg:postcode":"33012",
    "sg:province":"Asturias",
    "wof:name":"Loromi S.l",
    "wof:placetype":"venue"
},
  "geometry": {"coordinates":[-5.8556032181,43.3700256348],"type":"Point"}
}