{
  "type": "Feature",
  "properties": {
    "addr:full":"Calle de Mayor, 36 Puente Tocinos Murcia 30006",
    "addr:housenumber":"36",
    "addr:postcode":"30006",
    "addr:street":"Calle De Mayor",
    "iso:country":"ES",
    "sg:address":"Calle de Mayor, 36",
    "sg:city":"Puente Tocinos",
    "sg:orig_category":"Muebles, Minoristas",
    "sg:phone":"+34 968 24 19 27",
    "sg:postcode":"30006",
    "sg:province":"Murcia",
    "wof:name":"Antolinos Ortiz Mariano",
    "wof:placetype":"venue"
},
  "geometry": {"coordinates":[-1.105568409,37.9923439026],"type":"Point"}
}