{
  "type": "Feature",
  "properties": {
    "addr:full":"Calle de Zurbaran, 2 Alhama Murcia Murcia 30840",
    "addr:housenumber":"2",
    "addr:postcode":"30840",
    "addr:street":"Calle De Zurbaran",
    "iso:country":"ES",
    "sg:address":"Calle de Zurbaran, 2",
    "sg:city":"Alhama Murcia",
    "sg:orig_category":"Centros De Educaci\u00d3n Especial",
    "sg:phone":"+34 968 63 03 32",
    "sg:postcode":"30840",
    "sg:province":"Murcia",
    "wof:name":"Colegio Publico Principe De Espa\u00f1a",
    "wof:placetype":"venue"
},
  "geometry": {"coordinates":[-1.4241490364,37.8507995605],"type":"Point"}
}