{
  "type": "Feature",
  "properties": {
    "iso:country":"ES",
    "sg:address":"Calle de Dieciocho De Julio, S/n",
    "sg:city":"Talayuelas",
    "sg:orig_category":"Productores Recolectores, Venta Directa De Vinos",
    "sg:phone":"+34 969 36 31 60",
    "sg:postcode":"16320",
    "sg:province":"Cuenca",
    "wof:name":"Cooperativa Del Campo San Antonio De Padua",
    "wof:placetype":"venue"
},
  "geometry": {"coordinates":[-1.2837857008,39.8478393555],"type":"Point"}
}