{
  "type": "Feature",
  "properties": {
    "iso:country":"ES",
    "sg:address":"Carrer de Sant Xavier, 30",
    "sg:city":"Vendrell",
    "sg:orig_category":"Fabricaci\u00d3n De Pastas Alimentarias",
    "sg:phone":"+34 977 66 85 02",
    "sg:postcode":"43700",
    "sg:province":"Tarragona",
    "wof:name":"Comercial Gallo S.a.",
    "wof:placetype":"venue"
},
  "geometry": {"coordinates":[1.5301560163,41.2177810669],"type":"Point"}
}