{
  "type": "Feature",
  "properties": {
    "addr:full":"Carrer de Pinar Del Rio, 14 Barcelona Barcelona 08027",
    "addr:housenumber":"14",
    "addr:postcode":"08027",
    "addr:street":"Carrer De Pinar Del Rio",
    "iso:country":"ES",
    "sg:address":"Carrer de Pinar Del Rio, 14",
    "sg:city":"Barcelona",
    "sg:orig_category":"Empresarios",
    "sg:phone":"+34 934 08 21 95",
    "sg:postcode":"08027",
    "sg:province":"Barcelona",
    "wof:name":"Noesa S.l.",
    "wof:placetype":"venue"
},
  "geometry": {"coordinates":[2.1830410957,41.4223747253],"type":"Point"}
}