{
  "type": "Feature",
  "properties": {
    "addr:full":"Carrer de Girona, 19 Masnou Barcelona 08320",
    "addr:housenumber":"19",
    "addr:postcode":"08320",
    "addr:street":"Carrer De Girona",
    "iso:country":"ES",
    "sg:address":"Carrer de Girona, 19",
    "sg:city":"Masnou",
    "sg:orig_category":"Albergues",
    "sg:phone":"+34 935 55 41 32",
    "sg:postcode":"08320",
    "sg:province":"Barcelona",
    "wof:name":"Renter Comes Elena",
    "wof:placetype":"venue"
},
  "geometry": {"coordinates":[2.3245689869,41.4857139587],"type":"Point"}
}