{
  "type": "Feature",
  "properties": {
    "addr:full":"Carrer de Emporda, 5 Cornella Llobregat Barcelona 08940",
    "addr:housenumber":"5",
    "addr:postcode":"08940",
    "addr:street":"Carrer De Emporda",
    "iso:country":"ES",
    "sg:address":"Carrer de Emporda, 5",
    "sg:city":"Cornella Llobregat",
    "sg:orig_category":"M\u00c9dicos: Estomatolog\u00cda",
    "sg:phone":"+34 933 75 58 20",
    "sg:postcode":"08940",
    "sg:province":"Barcelona",
    "wof:name":"Gallegos Vazquez Francisco",
    "wof:placetype":"venue"
},
  "geometry": {"coordinates":[2.0798881054,41.3588485718],"type":"Point"}
}