{
  "type": "Feature",
  "properties": {
    "addr:full":"Carr Sant Pau, 3 Figueres Girona 17600",
    "addr:housenumber":"3",
    "addr:postcode":"17600",
    "addr:street":"Carr Sant Pau",
    "iso:country":"ES",
    "sg:address":"Carr Sant Pau, 3",
    "sg:city":"Figueres",
    "sg:orig_category":"Agencias De Viajes",
    "sg:phone":"+34 972 51 37 10",
    "sg:postcode":"17600",
    "sg:province":"Girona",
    "wof:name":"Melendez Ferron S.l",
    "wof:placetype":"venue"
},
  "geometry": {"coordinates":[2.9581100941,42.2656898499],"type":"Point"}
}