{
  "type": "Feature",
  "properties": {
    "addr:full":"Cra. Roca, Km. 0003,2 Cardedeu Barcelona 08440",
    "addr:postcode":"08440",
    "addr:street":"Km. 0003,2",
    "iso:country":"ES",
    "sg:address":"Cra. Roca, Km. 0003,2",
    "sg:city":"Cardedeu",
    "sg:orig_category":"Art\u00cdculos De Limpieza Y De Cocina (fabricaci\u00d3n, Al Por Mayor)",
    "sg:phone":"+34 938 45 48 88",
    "sg:postcode":"08440",
    "sg:province":"Barcelona",
    "wof:name":"Gomau S.l.",
    "wof:placetype":"venue"
},
  "geometry": {"coordinates":[2.3589351177,41.6370544434],"type":"Point"}
}