{
  "type": "Feature",
  "properties": {
    "addr:full":"Pl Fra Bernadi, 3 Manlleu Barcelona 08560",
    "addr:housenumber":"3",
    "addr:postcode":"08560",
    "addr:street":"Pl Fra Bernadi",
    "iso:country":"ES",
    "sg:address":"Pl Fra Bernadi, 3",
    "sg:city":"Manlleu",
    "sg:orig_category":"Carnicer\u00cdas, Carnicer\u00cdas",
    "sg:phone":"+34 938 51 39 85",
    "sg:postcode":"08560",
    "sg:province":"Barcelona",
    "wof:name":"Camps Graells Francesc",
    "wof:placetype":"venue"
},
  "geometry": {"coordinates":[2.2836999893,42.0003395081],"type":"Point"}
}