{
  "type": "Feature",
  "properties": {
    "iso:country":"ES",
    "sg:address":"Carrer de Benicarlo, 39",
    "sg:city":"Sant Vicen\u00c7 Dels Horts",
    "sg:orig_category":"Centros De Educaci\u00d3n Especial",
    "sg:phone":"+34 936 56 04 15",
    "sg:postcode":"08620",
    "sg:province":"Barcelona",
    "wof:name":"Ceip Mare De Deu Del Rocio",
    "wof:placetype":"venue"
},
  "geometry": {"coordinates":[2.0012729168,41.3989906311],"type":"Point"}
}