{
  "type": "Feature",
  "properties": {
    "addr:full":"Calle de Embajadores, 42 Valladolid Valladolid 47013",
    "addr:housenumber":"42",
    "addr:postcode":"47013",
    "addr:street":"Calle De Embajadores",
    "iso:country":"ES",
    "sg:address":"Calle de Embajadores, 42",
    "sg:city":"Valladolid",
    "sg:orig_category":"Cl\u00cdnicas Dentales",
    "sg:phone":"+34 983 23 86 91",
    "sg:postcode":"47013",
    "sg:province":"Valladolid",
    "wof:name":"Prestaciones Odontologicas Olid S.l.",
    "wof:placetype":"venue"
},
  "geometry": {"coordinates":[-4.7222728729,41.6365318298],"type":"Point"}
}