{
  "type": "Feature",
  "properties": {
    "addr:full":"Plaz Espa\u00d1a, 10 Brea De Aragon Zaragoza 50246",
    "addr:housenumber":"10",
    "addr:postcode":"50246",
    "addr:street":"Plaz Espan\u0303A",
    "iso:country":"ES",
    "sg:address":"Plaz Espa\u00d1a, 10",
    "sg:city":"Brea De Aragon",
    "sg:orig_category":"Farmacias",
    "sg:phone":"+34 976 82 42 02",
    "sg:postcode":"50246",
    "sg:province":"Zaragoza",
    "wof:name":"Perez Bellido Pablo Miguel",
    "wof:placetype":"venue"
},
  "geometry": {"coordinates":[-1.5998699665,41.5209693909],"type":"Point"}
}