{
  "type": "Feature",
  "properties": {
    "addr:full":"Pase Limonar, 14 Malaga M\u00e1laga 29016",
    "addr:housenumber":"14",
    "addr:postcode":"29016",
    "addr:street":"Limonar;Ma\u0301Laga",
    "iso:country":"ES",
    "sg:address":"Pase Limonar, 14",
    "sg:city":"Malaga",
    "sg:orig_category":"T\u00c9cnicos Veterinarios",
    "sg:phone":"+34 952 22 98 37",
    "sg:postcode":"29016",
    "sg:province":"M\u00e1laga",
    "wof:name":"Diez Lopez Belen",
    "wof:placetype":"venue"
},
  "geometry": {"coordinates":[-4.4015259743,36.7268218994],"type":"Point"}
}