{
  "type": "Feature",
  "properties": {
    "iso:country":"ES",
    "sg:address":"Los Rebites, 37",
    "sg:city":"Huetor-vega",
    "sg:orig_category":"Empresas De Desmonte",
    "sg:phone":"+34 958 50 21 20",
    "sg:postcode":"18198",
    "sg:province":"Granada",
    "wof:name":"Li\u00f1an Alvarez Jose",
    "wof:placetype":"venue"
},
  "geometry": {"coordinates":[-3.5724890232,37.1506309509],"type":"Point"}
}