{
  "type": "Feature",
  "properties": {
    "addr:full":"Calle de Dondovilla, 1 Huerta Rey Burgos 09430",
    "addr:housenumber":"1",
    "addr:postcode":"09430",
    "addr:street":"Calle De Dondovilla;Rey",
    "iso:country":"ES",
    "sg:address":"Calle de Dondovilla, 1",
    "sg:city":"Huerta Rey",
    "sg:orig_category":"Carnicer\u00cdas, Carnicer\u00cdas",
    "sg:phone":"+34 947 38 82 30",
    "sg:postcode":"09430",
    "sg:province":"Burgos",
    "wof:name":"Tello Guerrero Jesus",
    "wof:placetype":"venue"
},
  "geometry": {"coordinates":[-3.3471460342,41.8399009705],"type":"Point"}
}