{
  "type": "Feature",
  "properties": {
    "iso:country":"ES",
    "sg:address":"Calle de Ciudad Real, 63",
    "sg:city":"Almansa",
    "sg:orig_category":"Productos Qu\u00cdmicos (fabricaci\u00d3n, Al Por Mayor)",
    "sg:phone":"+34 967 34 03 46",
    "sg:postcode":"02640",
    "sg:province":"Albacete",
    "wof:name":"Eurobuho Quimica S.a,",
    "wof:placetype":"venue"
},
  "geometry": {"coordinates":[-1.0869214535,38.8589477539],"type":"Point"}
}