{
  "type": "Feature",
  "properties": {
    "iso:country":"ES",
    "sg:address":"Lauro, 5",
    "sg:city":"Alhaurin Torre",
    "sg:orig_category":"Abogados",
    "sg:phone":"+34 952 41 11 26",
    "sg:postcode":"29130",
    "sg:province":"M\u00e1laga",
    "wof:name":"Contreras Baquero Francisco",
    "wof:placetype":"venue"
},
  "geometry": {"coordinates":[-4.5667190552,36.6618614197],"type":"Point"}
}