{
  "type": "Feature",
  "properties": {
    "addr:full":"Calle de Mercurio, 22 Zaragoza Zaragoza 50012",
    "addr:housenumber":"22",
    "addr:postcode":"50012",
    "addr:street":"Calle De Mercurio",
    "iso:country":"ES",
    "sg:address":"Calle de Mercurio, 22",
    "sg:city":"Zaragoza",
    "sg:orig_category":"Agencias Y Agentes Comerciales, Representantes",
    "sg:phone":"+34 976 75 70 00",
    "sg:postcode":"50012",
    "sg:province":"Zaragoza",
    "wof:name":"Comunidad De Propietarios Calle Mercurio",
    "wof:placetype":"venue"
},
  "geometry": {"coordinates":[-0.9344969988,41.6376838684],"type":"Point"}
}