{
  "type": "Feature",
  "properties": {
    "addr:full":"Antzizar Auzoa, S/n Antzizar Guip\u00f9zcoa 20200",
    "addr:housenumber":"s / n",
    "addr:postcode":"20200",
    "addr:street":"Antzizar Auzoa;Antzizar Guipu\u0300Zcoa",
    "iso:country":"ES",
    "sg:address":"Antzizar Auzoa, S/n",
    "sg:city":"Antzizar",
    "sg:classifiers":[
        {
            "category":"Manufacturing",
            "subcategory":"Metals",
            "type":"Manufacturing & Wholesale Goods"
        }
    ],
    "sg:phone":"+34 943 88 66 51",
    "sg:postcode":"20200",
    "sg:province":"Guip\u00f9zcoa",
    "sg:tags":[
        "en",
        "fundiciones"
    ],
    "wof:name":"Fundiciones Del Estanda S.a.",
    "wof:placetype":"venue"
},
  "geometry": {"coordinates":[-2.1944589615,43.0469207764],"type":"Point"}
}