{
  "type": "Feature",
  "properties": {
    "iso:country":"ES",
    "sg:address":"Plaz Federico Garcia Lorca, S/n",
    "sg:city":"Macastre",
    "sg:orig_category":"Empresarios",
    "sg:phone":"+34 962 51 64 03",
    "sg:postcode":"46368",
    "sg:province":"Valencia",
    "wof:name":"Romero Gonzalez Miguel",
    "wof:placetype":"venue"
},
  "geometry": {"coordinates":[-0.7855439782,39.3848381042],"type":"Point"}
}