{
  "type": "Feature",
  "properties": {
    "addr:full":"Calle de Orense, 83 Madrid Madrid 28020",
    "addr:housenumber":"83",
    "addr:postcode":"madrid;28020",
    "addr:street":"Calle De Orense",
    "iso:country":"ES",
    "sg:address":"Calle de Orense, 83",
    "sg:city":"Madrid",
    "sg:orig_category":"Molduras, Junquillos, Listones Y Molduras Perforadas",
    "sg:phone":"+34 915 79 45 51",
    "sg:postcode":"28020",
    "sg:province":"Madrid",
    "wof:name":"Mu\u00f1oz Cerezo Antonio",
    "wof:placetype":"venue"
},
  "geometry": {"coordinates":[-3.6942379475,40.4601135254],"type":"Point"}
}