{
  "type": "Feature",
  "properties": {
    "addr:full":"Donostia Ibilbidea, 46 Astigarraga Guip\u00f9zcoa 20115",
    "addr:housenumber":"46",
    "addr:postcode":"20115",
    "addr:street":"Donostia Ibilbidea;Guipu\u0300Zcoa",
    "iso:country":"ES",
    "sg:address":"Donostia Ibilbidea, 46",
    "sg:city":"Astigarraga",
    "sg:orig_category":"Aperitivos (fabricaci\u00d3n Y Al Por Mayor)",
    "sg:phone":"+34 943 55 75 61",
    "sg:postcode":"20115",
    "sg:province":"Guip\u00f9zcoa",
    "wof:name":"Comercial Onyi S.l.",
    "wof:placetype":"venue"
},
  "geometry": {"coordinates":[-1.9509609938,43.2831993103],"type":"Point"}
}