{
  "type": "Feature",
  "properties": {
    "addr:full":"Trav Corts, 100 Barcelona Barcelona 08028",
    "addr:housenumber":"100",
    "addr:postcode":"08028",
    "addr:street":"Trav Corts",
    "iso:country":"ES",
    "sg:address":"Trav Corts, 100",
    "sg:city":"Barcelona",
    "sg:orig_category":"Ingenier\u00cda, Centros De Estudios (diversos)",
    "sg:phone":"+34 933 30 12 72",
    "sg:postcode":"08028",
    "sg:province":"Barcelona",
    "wof:name":"Carulla Mas Jose",
    "wof:placetype":"venue"
},
  "geometry": {"coordinates":[2.1244580746,41.3797798157],"type":"Point"}
}