{
  "type": "Feature",
  "properties": {
    "iso:country":"ES",
    "sg:address":"Calle de Miguel Morlan, 52",
    "sg:city":"Villanueva Alcardete",
    "sg:orig_category":"Bordado, Marcado A Medida",
    "sg:phone":"+34 925 16 61 04",
    "sg:postcode":"45810",
    "sg:province":"Toledo",
    "wof:name":"Gallego Mota S.l.",
    "wof:placetype":"venue"
},
  "geometry": {"coordinates":[-3.0124690533,39.6725502014],"type":"Point"}
}