{
  "type": "Feature",
  "properties": {
    "iso:country":"ES",
    "sg:address":"Barr Meaka (izq. Carr. Ibarla), 5",
    "sg:city":"Irun",
    "sg:orig_category":"Revestimientos Diversos",
    "sg:phone":"+34 943 62 23 05",
    "sg:postcode":"20305",
    "sg:province":"Guip\u00f9zcoa",
    "wof:name":"Lanchas Rios Marcelino",
    "wof:placetype":"venue"
},
  "geometry": {"coordinates":[-1.7637690306,43.3425445557],"type":"Point"}
}