{
  "type": "Feature",
  "properties": {
    "addr:full":"Rbla Catalunya, 45 Barcelona Barcelona 08007",
    "addr:housenumber":"45",
    "addr:postcode":"08007",
    "addr:street":"Rbla Catalunya",
    "iso:country":"ES",
    "sg:address":"Rbla Catalunya, 45",
    "sg:city":"Barcelona",
    "sg:orig_category":"Institutos De Belleza",
    "sg:phone":"+34 934 87 39 07",
    "sg:postcode":"08007",
    "sg:province":"Barcelona",
    "sg:website":"www.depilgroup.com",
    "wof:name":"Depil Group",
    "wof:placetype":"venue"
},
  "geometry": {"coordinates":[2.1642069817,41.3902206421],"type":"Point"}
}