{
  "type": "Feature",
  "properties": {
    "iso:country":"ES",
    "sg:address":"Carrer de Trafalgar, 55",
    "sg:city":"Barcelona",
    "sg:orig_category":"Ropa Y Accesorios",
    "sg:phone":"+34 933 10 02 70",
    "sg:postcode":"08010",
    "sg:province":"Barcelona",
    "wof:name":"Only-woman S.c.p",
    "wof:placetype":"venue"
},
  "geometry": {"coordinates":[2.1789059639,41.3907966614],"type":"Point"}
}