{
  "type": "Feature",
  "properties": {
    "addr:full":"Urb Calypso, 34 Mijas Costa M\u00e1laga 29649",
    "addr:housenumber":"34",
    "addr:postcode":"29649",
    "addr:street":"Urb Calypso",
    "iso:country":"ES",
    "sg:address":"Urb Calypso, 34",
    "sg:city":"Mijas Costa",
    "sg:orig_category":"Laboratorios Y Trabajos De Fotograf\u00cda, V\u00cddeo Y Cine",
    "sg:phone":"+34 952 93 11 36",
    "sg:postcode":"29649",
    "sg:province":"M\u00e1laga",
    "wof:name":"Garrido Maldonado Diego",
    "wof:placetype":"venue"
},
  "geometry": {"coordinates":[-4.6411604881,36.5099143982],"type":"Point"}
}