{
  "type": "Feature",
  "properties": {
    "addr:full":"Carretera De Solana, S/n Aceuchal Badajoz 06207",
    "addr:housenumber":"s / n",
    "addr:postcode":"06207",
    "addr:street":"Carretera De Solana",
    "iso:country":"ES",
    "sg:address":"Carretera De Solana, S/n",
    "sg:city":"Aceuchal",
    "sg:orig_category":"Mec\u00c1nico Del Autom\u00d3vil",
    "sg:phone":"+34 924 68 05 02",
    "sg:postcode":"06207",
    "sg:province":"Badajoz",
    "wof:name":"Lazaro Y Corchuelo S.l.",
    "wof:placetype":"venue"
},
  "geometry": {"coordinates":[-6.4929289818,38.6492881775],"type":"Point"}
}