{
  "type": "Feature",
  "properties": {
    "iso:country":"ES",
    "sg:address":"Calle de San Juan, 5",
    "sg:city":"Ba\u00e7os De Rio Tobia",
    "sg:orig_category":"Carnicer\u00cdas, Carnicer\u00cdas",
    "sg:phone":"+34 941 37 40 43",
    "sg:postcode":"26320",
    "sg:province":"La Rioja",
    "wof:name":"Zangroniz Azofra Octavio",
    "wof:placetype":"venue"
},
  "geometry": {"coordinates":[-2.7597768307,42.3354263306],"type":"Point"}
}