{
  "type": "Feature",
  "properties": {
    "iso:country":"ES",
    "sg:address":"Calle de Francisco Aritio, 162",
    "sg:city":"Guadalajara",
    "sg:orig_category":"Deportes Diversos",
    "sg:phone":"+34 949 20 09 38",
    "sg:postcode":"19004",
    "sg:province":"Guadalajara",
    "sg:website":"www.curveseurope.com",
    "wof:name":"Curves International Of Spain S.a.",
    "wof:placetype":"venue"
},
  "geometry": {"coordinates":[-3.1992549896,40.6235923767],"type":"Point"}
}