{
  "type": "Feature",
  "properties": {
    "addr:full":"Calle de Triana, 104 Palmas De Gran Canaria Las Palmas 35002",
    "addr:housenumber":"104",
    "addr:postcode":"35002",
    "addr:street":"Calle De Triana",
    "iso:country":"ES",
    "sg:address":"Calle de Triana, 104",
    "sg:city":"Palmas De Gran Canaria",
    "sg:orig_category":"Abogados",
    "sg:phone":"+34 928 37 21 77",
    "sg:postcode":"35002",
    "sg:province":"Las Palmas",
    "wof:name":"Risue\u00f1o Y Ortiz S.l",
    "wof:placetype":"venue"
},
  "geometry": {"coordinates":[-15.4165687561,28.1069107056],"type":"Point"}
}