{
  "type": "Feature",
  "properties": {
    "iso:country":"ES",
    "sg:address":"Calle de Cinca, 25",
    "sg:city":"Madrid",
    "sg:orig_category":"Peritos En C\u00c1lculo Inmobiliario, Industrial Y De Fondos De Comercio",
    "sg:phone":"+34 915 61 94 73",
    "sg:postcode":"28002",
    "sg:province":"Madrid",
    "wof:name":"Abogart & Gubardi S.l.",
    "wof:placetype":"venue"
},
  "geometry": {"coordinates":[-3.679239,40.449032],"type":"Point"}
}