{
  "type": "Feature",
  "properties": {
    "iso:country":"ES",
    "sg:address":"Carrer de Mendez Nu\u00d1ez (de), 2",
    "sg:city":"S. Carles Rapita",
    "sg:orig_category":"Empresas De Pintura Y Revestimientos",
    "sg:phone":"+34 977 74 19 20",
    "sg:postcode":"43540",
    "sg:province":"Tarragona",
    "wof:name":"Castella Menero Luis",
    "wof:placetype":"venue"
},
  "geometry": {"coordinates":[0.5937460065,40.6211051941],"type":"Point"}
}