{
  "type": "Feature",
  "properties": {
    "iso:country":"ES",
    "sg:address":"Carrer de Sant Antoni Maria Claret, 155",
    "sg:city":"Barcelona",
    "sg:orig_category":"Alquiler De V\u00cddeo",
    "sg:phone":"+34 934 36 17 00",
    "sg:postcode":"08025",
    "sg:province":"Barcelona",
    "wof:name":"Cifuespedes S.l.",
    "wof:placetype":"venue"
},
  "geometry": {"coordinates":[2.1737749577,41.4109802246],"type":"Point"}
}