{
  "type": "Feature",
  "properties": {
    "iso:country":"ES",
    "sg:address":"Cno. El Cerradico, 4",
    "sg:city":"Cadrete",
    "sg:orig_category":"Dorados, Plater\u00cda (orfebrer\u00cda)",
    "sg:phone":"+34 976 12 64 98",
    "sg:postcode":"50420",
    "sg:province":"Zaragoza",
    "wof:name":"Mu\u00f1oz Urieta Juana",
    "wof:placetype":"venue"
},
  "geometry": {"coordinates":[-0.9601830244,41.5556411743],"type":"Point"}
}