{
  "type": "Feature",
  "properties": {
    "iso:country":"ES",
    "sg:address":"Carrer de Nou, 46",
    "sg:city":"Sant Vicen\u00c7 Dels Horts",
    "sg:orig_category":"M\u00c1rmoles, Granitos Y Piedras Naturales",
    "sg:phone":"+34 936 76 89 31",
    "sg:postcode":"08620",
    "sg:province":"Barcelona",
    "wof:name":"Lumacri S.l.",
    "wof:placetype":"venue"
},
  "geometry": {"coordinates":[2.0116109848,41.3919868469],"type":"Point"}
}