{
  "type": "Feature",
  "properties": {
    "iso:country":"ES",
    "sg:address":"Calle de Concejal Lorenzo Llaneras, 7",
    "sg:city":"Alacant",
    "sg:orig_category":"Asociaciones Y Clubs Deportivos",
    "sg:phone":"+34 965 92 14 49",
    "sg:postcode":"03005",
    "sg:province":"Alicante",
    "wof:name":"Sport Tono S.l.",
    "wof:placetype":"venue"
},
  "geometry": {"coordinates":[-0.5005733967,38.3488616943],"type":"Point"}
}