{
  "type": "Feature",
  "properties": {
    "addr:full":"Calle de Luchana, 28 Madrid Madrid 28010",
    "addr:housenumber":"28",
    "addr:postcode":"madrid;28010",
    "addr:street":"Calle De Luchana",
    "iso:country":"ES",
    "sg:address":"Calle de Luchana, 28",
    "sg:city":"Madrid",
    "sg:orig_category":"Procuradores",
    "sg:phone":"+34 914 48 29 34",
    "sg:postcode":"28010",
    "sg:province":"Madrid",
    "wof:name":"Haro Martinez Maria Dolores De",
    "wof:placetype":"venue"
},
  "geometry": {"coordinates":[-3.6990559101,40.431224823],"type":"Point"}
}