{
  "type": "Feature",
  "properties": {
    "addr:full":"Avda Santa Isabel, 9 Zaragoza Zaragoza 50016",
    "addr:housenumber":"9",
    "addr:postcode":"50016",
    "addr:street":"Avda Santa Isabel",
    "iso:country":"ES",
    "sg:address":"Avda Santa Isabel, 9",
    "sg:city":"Zaragoza",
    "sg:orig_category":"Plomeros",
    "sg:phone":"+34 976 57 40 08",
    "sg:postcode":"50016",
    "sg:province":"Zaragoza",
    "wof:name":"Talleres Mecanicos Tamex S.l.",
    "wof:placetype":"venue"
},
  "geometry": {"coordinates":[-0.8396900296,41.6703338623],"type":"Point"}
}