{
  "type": "Feature",
  "properties": {
    "iso:country":"ES",
    "sg:address":"Ctra Plasencia, 23",
    "sg:city":"Madrigal Vera",
    "sg:orig_category":"Mec\u00c1nico Del Autom\u00d3vil",
    "sg:phone":"+34 927 56 54 02",
    "sg:postcode":"10480",
    "sg:province":"C\u00e1ceres",
    "wof:name":"Romero Lopez Miguel Angel",
    "wof:placetype":"venue"
},
  "geometry": {"coordinates":[-5.3685188293,40.1458702087],"type":"Point"}
}