{
  "type": "Feature",
  "properties": {
    "addr:full":"Zapateros(p I Tres Hermanas), 9 Aspe Alicante 03680",
    "addr:housenumber":"9",
    "addr:postcode":"03680",
    "addr:street":"P;Tres Hermanas",
    "iso:country":"ES",
    "sg:address":"Zapateros(p I Tres Hermanas), 9",
    "sg:city":"Aspe",
    "sg:orig_category":"M\u00c1rmoles, Granitos Y Piedras Naturales",
    "sg:phone":"+34 965 49 29 29",
    "sg:postcode":"03680",
    "sg:province":"Alicante",
    "wof:name":"Marmoles Elx S.l.",
    "wof:placetype":"venue"
},
  "geometry": {"coordinates":[-0.758638978,38.3245010376],"type":"Point"}
}