{
  "type": "Feature",
  "properties": {
    "iso:country":"ES",
    "sg:address":"Avda Tecnica (de La), 15",
    "sg:city":"Partija-santa Monica",
    "sg:orig_category":"Tubos Met\u00c1licos",
    "sg:phone":"+34 913 01 27 35",
    "sg:postcode":"28529",
    "sg:province":"Madrid",
    "wof:name":"Imtech Mavisa S.a.",
    "wof:placetype":"venue"
},
  "geometry": {"coordinates":[-3.5102670193,40.314289093],"type":"Point"}
}