{
  "type": "Feature",
  "properties": {
    "addr:full":"Carrer de Josep Anselm Clave, 25 Barcelona Barcelona 08002",
    "addr:housenumber":"25",
    "addr:postcode":"08002",
    "addr:street":"Carrer De Josep Anselm Clave",
    "iso:country":"ES",
    "sg:address":"Carrer de Josep Anselm Clave, 25",
    "sg:city":"Barcelona",
    "sg:orig_category":"Asociaciones, Organismos Culturales Y Socioeducativos",
    "sg:phone":"+34 934 12 13 27",
    "sg:postcode":"08002",
    "sg:province":"Barcelona",
    "wof:name":"Fundacio Josep Comaposada",
    "wof:placetype":"venue"
},
  "geometry": {"coordinates":[2.1781740189,41.3778495789],"type":"Point"}
}