{
  "type": "Feature",
  "properties": {
    "addr:full":"Rua Benito Vicetto, 14 Ourense Ourense 32004",
    "addr:housenumber":"14",
    "addr:postcode":"32004",
    "addr:street":"Rua Benito Vicetto",
    "iso:country":"ES",
    "sg:address":"Rua Benito Vicetto, 14",
    "sg:city":"Ourense",
    "sg:orig_category":"Ense\u00d1anza Variada",
    "sg:phone":"+34 988 24 63 90",
    "sg:postcode":"32004",
    "sg:province":"Ourense",
    "wof:name":"Orensana Educativa S.c.",
    "wof:placetype":"venue"
},
  "geometry": {"coordinates":[-7.8556118011,42.3438491821],"type":"Point"}
}