{
  "type": "Feature",
  "properties": {
    "iso:country":"ES",
    "sg:address":"Carrer de Nou, 17",
    "sg:city":"Torello",
    "sg:orig_category":"Producci\u00d3n, Comercio De Cereales",
    "sg:phone":"+34 938 59 05 48",
    "sg:postcode":"08570",
    "sg:province":"Barcelona",
    "wof:name":"Teixido Maideu Jose",
    "wof:placetype":"venue"
},
  "geometry": {"coordinates":[2.2643330097,42.0460128784],"type":"Point"}
}