{
  "type": "Feature",
  "properties": {
    "addr:full":"Calle de San Roque, 98 Azadinos Le\u00f3n 24121",
    "addr:housenumber":"98",
    "addr:postcode":"24121",
    "addr:street":"Calle De San Roque;Leo\u0301N",
    "iso:country":"ES",
    "sg:address":"Calle de San Roque, 98",
    "sg:city":"Azadinos",
    "sg:orig_category":"Cerrajer\u00cda, Ferrallista",
    "sg:phone":"+34 987 28 06 81",
    "sg:postcode":"24121",
    "sg:province":"Le\u00f3n",
    "wof:name":"Juarez De La Mano Jose Luis",
    "wof:placetype":"venue"
},
  "geometry": {"coordinates":[-5.6149291992,42.6403999329],"type":"Point"}
}