{
  "type": "Feature",
  "properties": {
    "iso:country":"ES",
    "sg:address":"Calle de Rioja, 13",
    "sg:city":"Sevilla",
    "sg:orig_category":"Ropa Para Se\u00d1oras (al Por Menor)",
    "sg:phone":"+34 954 22 67 40",
    "sg:postcode":"41001",
    "sg:province":"Sevilla",
    "wof:name":"A.a. Gallardo S.c.",
    "wof:placetype":"venue"
},
  "geometry": {"coordinates":[-5.995648,37.391033],"type":"Point"}
}