{
  "type": "Feature",
  "properties": {
    "addr:full":"Ctra Osor, S/n Angles Girona 17160",
    "addr:housenumber":"s / n",
    "addr:postcode":"17160",
    "addr:street":"Ctra Osor",
    "iso:country":"ES",
    "sg:address":"Ctra Osor, S/n",
    "sg:city":"Angles",
    "sg:orig_category":"Peluquer\u00cdas, Peluquer\u00cda Mixta",
    "sg:phone":"+34 972 42 24 17",
    "sg:postcode":"17160",
    "sg:province":"Girona",
    "wof:name":"Rabionet Planella Marta",
    "wof:placetype":"venue"
},
  "geometry": {"coordinates":[2.630726099,41.9564170837],"type":"Point"}
}