{
  "type": "Feature",
  "properties": {
    "iso:country":"ES",
    "sg:address":"Carrer de Gran De Sant Andreu, 180",
    "sg:city":"Barcelona",
    "sg:orig_category":"Decoradores",
    "sg:phone":"+34 933 11 43 06",
    "sg:postcode":"08030",
    "sg:province":"Barcelona",
    "wof:name":"Saura Lluch Vicenta",
    "wof:placetype":"venue"
},
  "geometry": {"coordinates":[2.1894979477,41.4329147339],"type":"Point"}
}