{
  "type": "Feature",
  "properties": {
    "addr:full":"Galicia, 15 Ribeira-santa Uxia La Coru\u00f1a 15960",
    "addr:housenumber":"15",
    "addr:postcode":"15960",
    "addr:street":"Galicia;Uxia;Corun\u0303A",
    "iso:country":"ES",
    "sg:address":"Galicia, 15",
    "sg:city":"Ribeira-santa Uxia",
    "sg:orig_category":"Peleter\u00cdas",
    "sg:phone":"+34 981 87 44 17",
    "sg:postcode":"15960",
    "sg:province":"La Coru\u00f1a",
    "wof:name":"Ante Piel Napa S.l.",
    "wof:placetype":"venue"
},
  "geometry": {"coordinates":[-8.9920902252,42.557636261],"type":"Point"}
}