{
  "type": "Feature",
  "properties": {
    "iso:country":"ES",
    "sg:address":"Avda Angeles (los), 4",
    "sg:city":"Loja",
    "sg:orig_category":"Bisuter\u00cda, Joyer\u00cda, Relojer\u00cda (al Por Menor)",
    "sg:phone":"+34 958 32 40 74",
    "sg:postcode":"18300",
    "sg:province":"Granada",
    "wof:name":"Ortiz Castilla Elisa Maria",
    "wof:placetype":"venue"
},
  "geometry": {"coordinates":[-4.1470651627,37.1658554077],"type":"Point"}
}