{
  "type": "Feature",
  "properties": {
    "iso:country":"ES",
    "sg:address":"Pase Constitucion (la), 8",
    "sg:city":"Zaragoza",
    "sg:orig_category":"M\u00c9dicos: Cirug\u00cda Pl\u00c1stica, Reconstructiva Y Est\u00c9tica",
    "sg:phone":"+34 976 21 85 00",
    "sg:postcode":"50008",
    "sg:province":"Zaragoza",
    "sg:website":"www.clinicaboston.com",
    "wof:name":"Laboratorios Syntra S.l.",
    "wof:placetype":"venue"
},
  "geometry": {"coordinates":[-0.883318007,41.6477050781],"type":"Point"}
}