{
  "type": "Feature",
  "properties": {
    "iso:country":"ES",
    "sg:address":"Avda Reina Mercedes, 5",
    "sg:city":"Sevilla",
    "sg:orig_category":"Caf\u00c9s, Bares, Cervecer\u00cdas",
    "sg:phone":"+34 954 62 35 92",
    "sg:postcode":"41012",
    "sg:province":"Sevilla",
    "wof:name":"Pascual Hispanomex S.l.",
    "wof:placetype":"venue"
},
  "geometry": {"coordinates":[-5.9858870506,37.3630599976],"type":"Point"}
}