{
  "type": "Feature",
  "properties": {
    "addr:full":"Carr Major, 34 Seu D'urgell Lleida 25700",
    "addr:housenumber":"34",
    "addr:postcode":"25700",
    "addr:street":"Carr Major",
    "iso:country":"ES",
    "sg:address":"Carr Major, 34",
    "sg:city":"Seu D'urgell",
    "sg:orig_category":"Farmacias",
    "sg:phone":"+34 973 35 01 20",
    "sg:postcode":"25700",
    "sg:province":"Lleida",
    "wof:name":"Cepero Calvete Jorge",
    "wof:placetype":"venue"
},
  "geometry": {"coordinates":[0.6256679893,41.6142463684],"type":"Point"}
}