{
  "type": "Feature",
  "properties": {
    "iso:country":"ES",
    "sg:address":"Calle de Campanario, S/n",
    "sg:city":"Puebla Montalban",
    "sg:orig_category":"Promotores Constructores",
    "sg:phone":"+34 925 75 10 86",
    "sg:postcode":"45516",
    "sg:province":"Toledo",
    "wof:name":"Construcciones Carmeli S.l.",
    "wof:placetype":"venue"
},
  "geometry": {"coordinates":[-4.3643260002,39.8641014099],"type":"Point"}
}