{
  "type": "Feature",
  "properties": {
    "addr:full":"Alvarez Quintero, 6 Castilleja Cuesta Sevilla 41950",
    "addr:housenumber":"6",
    "addr:postcode":"41950",
    "addr:street":"Quintero;Cuesta Sevilla",
    "iso:country":"ES",
    "sg:address":"Alvarez Quintero, 6",
    "sg:city":"Castilleja Cuesta",
    "sg:orig_category":"Carnicer\u00cdas, Carnicer\u00cdas",
    "sg:phone":"+34 954 16 04 56",
    "sg:postcode":"41950",
    "sg:province":"Sevilla",
    "wof:name":"Reyes De Los Reyes Jose De Los",
    "wof:placetype":"venue"
},
  "geometry": {"coordinates":[-6.0558128357,37.3850898743],"type":"Point"}
}