{
  "type": "Feature",
  "properties": {
    "iso:country":"ES",
    "sg:address":"Rbla Catalunya, 68",
    "sg:city":"Barcelona",
    "sg:orig_category":"Costureras",
    "sg:phone":"+34 934 87 26 27",
    "sg:postcode":"08007",
    "sg:province":"Barcelona",
    "wof:name":"Fragoso Torres Heliodora",
    "wof:placetype":"venue"
},
  "geometry": {"coordinates":[2.1629300117,41.3917732239],"type":"Point"}
}