{
  "type": "Feature",
  "properties": {
    "iso:country":"ES",
    "sg:address":"Calle de Ventura Rodriguez, 7",
    "sg:city":"Madrid",
    "sg:orig_category":"Agencias De Viajes",
    "sg:phone":"+34 915 47 97 40",
    "sg:postcode":"28008",
    "sg:province":"Madrid",
    "wof:name":"Representaciones New Air S.l.",
    "wof:placetype":"venue"
},
  "geometry": {"coordinates":[-3.713668108,40.425239563],"type":"Point"}
}