{
  "type": "Feature",
  "properties": {
    "iso:country":"ES",
    "sg:address":"Ctra. Jerez-arcos, Km. 0008,0",
    "sg:city":"Jerez",
    "sg:orig_category":"Cr\u00cda De Animales",
    "sg:phone":"+34 956 23 75 39",
    "sg:postcode":"11406",
    "sg:province":"C\u00e1diz",
    "wof:name":"Hermanos Castronieves S. A.",
    "wof:placetype":"venue"
},
  "geometry": {"coordinates":[-5.9091687202,36.730255127],"type":"Point"}
}