{
  "type": "Feature",
  "properties": {
    "iso:country":"ES",
    "sg:address":"Calle de Virgen De Las Cruces, 16",
    "sg:city":"Saceruela",
    "sg:orig_category":"Forjas Y Altos Hornos",
    "sg:phone":"+34 926 77 90 49",
    "sg:postcode":"13414",
    "sg:province":"Ciudad Real",
    "wof:name":"Gonzalez Cabezas Benjamin",
    "wof:placetype":"venue"
},
  "geometry": {"coordinates":[-4.6109991074,38.9446678162],"type":"Point"}
}