{
  "type": "Feature",
  "properties": {
    "addr:full":"Calle de Toro, 24 Salamanca Salamanca 37002",
    "addr:housenumber":"24",
    "addr:postcode":"37002",
    "addr:street":"Calle De Toro",
    "iso:country":"ES",
    "sg:address":"Calle de Toro, 24",
    "sg:city":"Salamanca",
    "sg:orig_category":"Promotores Constructores",
    "sg:phone":"+34 923 26 83 70",
    "sg:postcode":"37002",
    "sg:province":"Salamanca",
    "wof:name":"Promotora De Casas S. A.",
    "wof:placetype":"venue"
},
  "geometry": {"coordinates":[-5.6626091003,40.9663658142],"type":"Point"}
}