{
  "type": "Feature",
  "properties": {
    "iso:country":"ES",
    "sg:address":"Praz Gremio Dos Mareantes (do), 3",
    "sg:city":"Pontevedra",
    "sg:orig_category":"Sindicatos Y Colegios Profesionales",
    "sg:phone":"+34 986 84 70 01",
    "sg:postcode":"36002",
    "sg:province":"Pontevedra",
    "wof:name":"Gremio De Mareantes",
    "wof:placetype":"venue"
},
  "geometry": {"coordinates":[-8.6531801224,42.4290657043],"type":"Point"}
}