{
  "type": "Feature",
  "properties": {
    "iso:country":"ES",
    "sg:address":"Carrer de Josep Miret, 31",
    "sg:city":"Barcelona",
    "sg:orig_category":"Tapicer\u00cdas",
    "sg:phone":"+34 933 14 73 13",
    "sg:postcode":"08020",
    "sg:province":"Barcelona",
    "wof:name":"Blanco Cepeda Pedro",
    "wof:placetype":"venue"
},
  "geometry": {"coordinates":[2.1988909245,41.4229660034],"type":"Point"}
}