{
  "type": "Feature",
  "properties": {
    "addr:full":"Calle de Jose, 2 Madrid Madrid 28029",
    "addr:housenumber":"2",
    "addr:postcode":"28029",
    "addr:street":"Calle De Jose",
    "iso:country":"ES",
    "sg:address":"Calle de Jose, 2",
    "sg:city":"Madrid",
    "sg:orig_category":"Inmobiliaria (agencias)",
    "sg:phone":"+34 913 14 68 95",
    "sg:postcode":"28029",
    "sg:province":"Madrid",
    "wof:name":"Gonzalez Rodriguez Modesto",
    "wof:placetype":"venue"
},
  "geometry": {"coordinates":[-3.6959860325,40.467540741],"type":"Point"}
}