{
  "type": "Feature",
  "properties": {
    "iso:country":"ES",
    "sg:address":"Carrer de Planes (les), 2",
    "sg:city":"S. Pere Ribes",
    "sg:orig_category":"Papeler\u00cdas, Librer\u00cdas",
    "sg:phone":"+34 938 96 02 51",
    "sg:postcode":"08810",
    "sg:province":"Barcelona",
    "wof:name":"Gabalda Pascual Pilar",
    "wof:placetype":"venue"
},
  "geometry": {"coordinates":[1.7711980343,41.2623329163],"type":"Point"}
}