{
  "type": "Feature",
  "properties": {
    "iso:country":"ES",
    "sg:address":"Av Madrid, 191",
    "sg:city":"Barcelona",
    "sg:orig_category":"Promotores Constructores",
    "sg:phone":"+34 934 90 19 20",
    "sg:postcode":"08014",
    "sg:province":"Barcelona",
    "wof:name":"Promociones Cortort S.l.",
    "wof:placetype":"venue"
},
  "geometry": {"coordinates":[2.1336989403,41.3813018799],"type":"Point"}
}