{
  "type": "Feature",
  "properties": {
    "addr:full":"Pase Florida, 17 Madrid Madrid 28008",
    "addr:housenumber":"17",
    "addr:postcode":"madrid;28008",
    "addr:street":"Florida",
    "iso:country":"ES",
    "sg:address":"Pase Florida, 17",
    "sg:city":"Madrid",
    "sg:orig_category":"Ropa Para Se\u00d1oras (al Por Menor)",
    "sg:phone":"+34 915 47 49 15",
    "sg:postcode":"28008",
    "sg:province":"Madrid",
    "wof:name":"Cila S. A.",
    "wof:placetype":"venue"
},
  "geometry": {"coordinates":[-3.7214000225,40.4213485718],"type":"Point"}
}