{
  "type": "Feature",
  "properties": {
    "iso:country":"ES",
    "sg:address":"Calle de Arcipreste De Hita, 8",
    "sg:city":"Madrid",
    "sg:orig_category":"Panader\u00cdas, Panader\u00cdas",
    "sg:phone":"+34 915 44 05 50",
    "sg:postcode":"28015",
    "sg:province":"Madrid",
    "wof:name":"Rutraver S.l.",
    "wof:placetype":"venue"
},
  "geometry": {"coordinates":[-3.7178533077,40.4339866638],"type":"Point"}
}