{
  "type": "Feature",
  "properties": {
    "addr:full":"Rua Matias Lopez, 150 Sarria Lugo 27600",
    "addr:housenumber":"150",
    "addr:postcode":"27600",
    "addr:street":"Rua Matias Lopez",
    "iso:country":"ES",
    "sg:address":"Rua Matias Lopez, 150",
    "sg:city":"Sarria",
    "sg:orig_category":"Muebles Y Accesorios Para Cocinas Y Cuartos De Ba\u00d1o (al Por Menor)",
    "sg:phone":"+34 982 53 36 51",
    "sg:postcode":"27600",
    "sg:province":"Lugo",
    "wof:name":"Poy Lopez Francisco",
    "wof:placetype":"venue"
},
  "geometry": {"coordinates":[-7.4142518044,42.7818336487],"type":"Point"}
}