{
  "type": "Feature",
  "properties": {
    "iso:country":"ES",
    "sg:address":"Carrer de Consell De Cent, 71",
    "sg:city":"Barcelona",
    "sg:orig_category":"Veh\u00cdculos De Ocasi\u00d3n",
    "sg:phone":"+34 934 24 10 15",
    "sg:postcode":"08015",
    "sg:province":"Barcelona",
    "wof:name":"Gonzalez Casals Guillermo",
    "wof:placetype":"venue"
},
  "geometry": {"coordinates":[2.1494588852,41.3790626526],"type":"Point"}
}