{
  "type": "Feature",
  "properties": {
    "iso:country":"ES",
    "sg:address":"Calle de 31 De Agosto, 30",
    "sg:city":"Donostia-san Sebastian",
    "sg:orig_category":"Asociaciones, Organismos Culturales Y Socioeducativos",
    "sg:phone":"+34 943 42 90 25",
    "sg:postcode":"20003",
    "sg:province":"Guip\u00f9zcoa",
    "wof:name":"Euskal Herriko Bertsozale Elkartea",
    "wof:placetype":"venue"
},
  "geometry": {"coordinates":[-1.9853698015,43.3241081238],"type":"Point"}
}