{
  "type": "Feature",
  "properties": {
    "addr:full":"Calle de Tomas Miller, 77 Palmas De Gran Canaria Las Palmas 35007",
    "addr:housenumber":"77",
    "addr:postcode":"35007",
    "addr:street":"Calle De Tomas Miller",
    "iso:country":"ES",
    "sg:address":"Calle de Tomas Miller, 77",
    "sg:city":"Palmas De Gran Canaria",
    "sg:orig_category":"Peluqueros: De Se\u00d1oras",
    "sg:phone":"+34 928 26 14 80",
    "sg:postcode":"35007",
    "sg:province":"Las Palmas",
    "wof:name":"Ramos Pelayo Jesus",
    "wof:placetype":"venue"
},
  "geometry": {"coordinates":[-15.433836937,28.1411170959],"type":"Point"}
}