{
  "type": "Feature",
  "properties": {
    "addr:full":"Vilar-vilalonga, 21 Vilar Pontevedra 36990",
    "addr:housenumber":"21",
    "addr:postcode":"36990",
    "addr:street":"Vilar-Vilalonga",
    "iso:country":"ES",
    "sg:address":"Vilar-vilalonga, 21",
    "sg:city":"Vilar",
    "sg:orig_category":"Confecci\u00d3n (fabricaci\u00d3n, Al Por Mayor)",
    "sg:phone":"+34 986 74 30 42",
    "sg:postcode":"36990",
    "sg:province":"Pontevedra",
    "wof:name":"Guimil Calvo Julian",
    "wof:placetype":"venue"
},
  "geometry": {"coordinates":[-8.8619022369,42.4462432861],"type":"Point"}
}