{
  "type": "Feature",
  "properties": {
    "iso:country":"ES",
    "sg:address":"Barr Poligono De Granda, 6",
    "sg:city":"Granda",
    "sg:orig_category":"Limpieza Industrial",
    "sg:phone":"+34 985 98 50 97",
    "sg:postcode":"33199",
    "sg:province":"Asturias",
    "wof:name":"Lavanderia Asturias S.l.",
    "wof:placetype":"venue"
},
  "geometry": {"coordinates":[-5.7986898422,43.3584632874],"type":"Point"}
}