{
  "type": "Feature",
  "properties": {
    "addr:full":"Calle de Miguel De Unamuno, 1 Fuenlabrada Madrid 28944",
    "addr:housenumber":"1",
    "addr:postcode":"28944",
    "addr:street":"Calle De Miguel De Unamuno",
    "iso:country":"ES",
    "sg:address":"Calle de Miguel De Unamuno, 1",
    "sg:city":"Fuenlabrada",
    "sg:orig_category":"Tatuajes",
    "sg:phone":"+34 914 92 01 15",
    "sg:postcode":"28944",
    "sg:province":"Madrid",
    "wof:name":"Hot Ink Tattoo S.l.",
    "wof:placetype":"venue"
},
  "geometry": {"coordinates":[-3.7918219566,40.2840003967],"type":"Point"}
}