{
  "type": "Feature",
  "properties": {
    "addr:full":"Calle de Santa Teresa, 7 Barco De Avila \u00c1vila 05600",
    "addr:housenumber":"7",
    "addr:postcode":"05600",
    "addr:street":"Calle De Santa Teresa;A\u0301Vila",
    "iso:country":"ES",
    "sg:address":"Calle de Santa Teresa, 7",
    "sg:city":"Barco De Avila",
    "sg:orig_category":"Quincaller\u00cda (al Por Menor)",
    "sg:phone":"+34 920 34 11 63",
    "sg:postcode":"05600",
    "sg:province":"\u00c1vila",
    "wof:name":"Herrero Lopez Julian",
    "wof:placetype":"venue"
},
  "geometry": {"coordinates":[-5.5234308243,40.3575668335],"type":"Point"}
}