{
  "type": "Feature",
  "properties": {
    "iso:country":"ES",
    "sg:address":"Plaz Pepe Castilla, 1",
    "sg:city":"Rambla",
    "sg:orig_category":"Ingeniero",
    "sg:phone":"+34 957 68 23 27",
    "sg:postcode":"14540",
    "sg:province":"C\u00f3rdoba",
    "wof:name":"Torres Rodriguez Baldomero",
    "wof:placetype":"venue"
},
  "geometry": {"coordinates":[-4.7412290573,37.6074066162],"type":"Point"}
}