{
  "type": "Feature",
  "properties": {
    "addr:full":"Avda Torneo, 35 Sevilla Sevilla 41002",
    "addr:housenumber":"35",
    "addr:postcode":"41002",
    "addr:street":"Avda Torneo",
    "iso:country":"ES",
    "sg:address":"Avda Torneo, 35",
    "sg:city":"Sevilla",
    "sg:orig_category":"Arquitectos",
    "sg:phone":"+34 954 37 22 25",
    "sg:postcode":"41002",
    "sg:province":"Sevilla",
    "wof:name":"Flores Llama Manuel",
    "wof:placetype":"venue"
},
  "geometry": {"coordinates":[-5.9996490479,37.3992385864],"type":"Point"}
}