{
  "type": "Feature",
  "properties": {
    "iso:country":"ES",
    "sg:address":"Rua Rosalia De Castro, 3",
    "sg:city":"Vilamean",
    "sg:orig_category":"Peluquer\u00cdas, Peluquer\u00cda Mixta",
    "sg:phone":"+34 986 38 02 13",
    "sg:postcode":"36350",
    "sg:province":"Pontevedra",
    "wof:name":"Gonzalez Alvarez Josefina",
    "wof:placetype":"venue"
},
  "geometry": {"coordinates":[-8.8070688248,42.138710022],"type":"Point"}
}