{
  "type": "Feature",
  "properties": {
    "iso:country":"ES",
    "sg:address":"Carrer de Fontanella, 10",
    "sg:city":"Barcelona",
    "sg:orig_category":"Agencias De Modelos",
    "sg:phone":"+34 933 42 62 65",
    "sg:postcode":"08010",
    "sg:province":"Barcelona",
    "sg:website":"www.bcnhostess.com",
    "wof:name":"Barcelona Hostess S.l.",
    "wof:placetype":"venue"
},
  "geometry": {"coordinates":[2.1721789837,41.3875617981],"type":"Point"}
}