{
  "type": "Feature",
  "properties": {
    "iso:country":"ES",
    "sg:address":"Calle de Mirador, S/n",
    "sg:city":"Mirador",
    "sg:orig_category":"Electricidad: Instaladores",
    "sg:phone":"+34 918 17 81 31",
    "sg:postcode":"45930",
    "sg:province":"Toledo",
    "wof:name":"Lopes Bonafi Pascal",
    "wof:placetype":"venue"
},
  "geometry": {"coordinates":[-4.1866569519,40.2358818054],"type":"Point"}
}