{
  "type": "Feature",
  "properties": {
    "addr:full":"Pl Carles Iii (de), 54 S. Carles Rapita Tarragona 43540",
    "addr:housenumber":"54",
    "addr:postcode":"43540",
    "addr:street":"Pl Carles Iii De;S. Carles Rapita",
    "iso:country":"ES",
    "sg:address":"Pl Carles Iii (de), 54",
    "sg:city":"S. Carles Rapita",
    "sg:orig_category":"Art\u00cdculos De Regalo (al Por Menor)",
    "sg:phone":"+34 977 74 07 97",
    "sg:postcode":"43540",
    "sg:province":"Tarragona",
    "wof:name":"Risa Aliau Margarita",
    "wof:placetype":"venue"
},
  "geometry": {"coordinates":[0.5935080051,40.620929718],"type":"Point"}
}