{
  "type": "Feature",
  "properties": {
    "iso:country":"ES",
    "sg:address":"Rua Curro, S/n",
    "sg:city":"Noia",
    "sg:orig_category":"Edici\u00d3n De Diarios, Revistas, Boletines",
    "sg:phone":"+34 981 82 50 10",
    "sg:postcode":"15200",
    "sg:province":"La Coru\u00f1a",
    "wof:name":"Editorial Compostela S.a.",
    "wof:placetype":"venue"
},
  "geometry": {"coordinates":[-8.8870296478,42.7827339172],"type":"Point"}
}