{
  "type": "Feature",
  "properties": {
    "iso:country":"ES",
    "sg:address":"Calle de Jose Maria Martorell, 4",
    "sg:city":"Cordoba",
    "sg:orig_category":"Farmacias",
    "sg:phone":"+34 957 45 00 74",
    "sg:postcode":"14005",
    "sg:province":"C\u00f3rdoba",
    "wof:name":"Die Martinez Federico",
    "wof:placetype":"venue"
},
  "geometry": {"coordinates":[-4.7988128662,37.8802185059],"type":"Point"}
}