{
  "type": "Feature",
  "properties": {
    "iso:country":"ES",
    "sg:address":"Calle de Comandante Fontanes, 71",
    "sg:city":"Madrid",
    "sg:orig_category":"Mec\u00c1nico Del Autom\u00d3vil",
    "sg:phone":"+34 914 71 99 78",
    "sg:postcode":"28019",
    "sg:province":"Madrid",
    "wof:name":"Peinado Alvarez Juan",
    "wof:placetype":"venue"
},
  "geometry": {"coordinates":[-3.7264204025,40.3948440552],"type":"Point"}
}