{
  "type": "Feature",
  "properties": {
    "iso:country":"ES",
    "sg:address":"Calle de Juan Valera, 9",
    "sg:city":"Oviedo",
    "sg:orig_category":"Inmobiliaria (agencias)",
    "sg:phone":"+34 985 29 49 53",
    "sg:postcode":"33012",
    "sg:province":"Asturias",
    "wof:name":"Construcciones Y Servicios Somiedo",
    "wof:placetype":"venue"
},
  "geometry": {"coordinates":[-5.8507761955,43.3728599548],"type":"Point"}
}