{
  "type": "Feature",
  "properties": {
    "iso:country":"ES",
    "sg:address":"Calle de Manso, 2",
    "sg:city":"Gijon",
    "sg:orig_category":"Hoteles",
    "sg:phone":"+34 985 36 71 11",
    "sg:postcode":"33203",
    "sg:province":"Asturias",
    "wof:name":"Turismo E Inversiones Del Norte S.l.",
    "wof:placetype":"venue"
},
  "geometry": {"coordinates":[-5.6466388702,43.5387611389],"type":"Point"}
}