{
  "type": "Feature",
  "properties": {
    "addr:full":"Pol Ind La Rosa, 21 Chauchina Granada 18330",
    "addr:housenumber":"21",
    "addr:postcode":"18330",
    "addr:street":"Rosa",
    "iso:country":"ES",
    "sg:address":"Pol Ind La Rosa, 21",
    "sg:city":"Chauchina",
    "sg:orig_category":"Empresas De Carpinter\u00cda",
    "sg:phone":"+34 958 44 73 61",
    "sg:postcode":"18330",
    "sg:province":"Granada",
    "wof:name":"Lopez Moya Aluminios S.l.l.",
    "wof:placetype":"venue"
},
  "geometry": {"coordinates":[-3.7719919682,37.2014541626],"type":"Point"}
}