{
  "type": "Feature",
  "properties": {
    "addr:full":"Carrer de Andreu Roig, D'en, 1 Cala D'or Islas Baleares 07660",
    "addr:housenumber":"1",
    "addr:postcode":"07660",
    "addr:street":"Carrer De Andreu Roig D'En",
    "iso:country":"ES",
    "sg:address":"Carrer de Andreu Roig, D'en, 1",
    "sg:city":"Cala D'or",
    "sg:orig_category":"Electricidad, Electr\u00d3nica: Material Y Suministros (al Por Mayor)",
    "sg:phone":"+34 971 65 80 60",
    "sg:postcode":"07660",
    "sg:province":"Islas Baleares",
    "wof:name":"Recreativos Sur Mallorca S.l.",
    "wof:placetype":"venue"
},
  "geometry": {"coordinates":[2.9117100239,39.6136398315],"type":"Point"}
}