{
  "type": "Feature",
  "properties": {
    "iso:country":"ES",
    "sg:address":"Ctra Madrid-coru\u00d1a, Km. 0182,0",
    "sg:city":"Tordesillas",
    "sg:orig_category":"Cooperativas Agr\u00cdcolas",
    "sg:phone":"+34 983 79 65 36",
    "sg:postcode":"47100",
    "sg:province":"Valladolid",
    "wof:name":"Cooperativa Tera-esla-orbigo",
    "wof:placetype":"venue"
},
  "geometry": {"coordinates":[-5.000743866,41.497543335],"type":"Point"}
}