{
  "type": "Feature",
  "properties": {
    "iso:country":"ES",
    "sg:address":"Rua Canovas Del Castillo, S/n",
    "sg:city":"Vigo",
    "sg:orig_category":"Controles De Edificaci\u00d3n (construcci\u00d3n, Seguridad)",
    "sg:phone":"+34 986 22 37 39",
    "sg:postcode":"36202",
    "sg:province":"Pontevedra",
    "sg:website":"www.gocsa.es",
    "wof:name":"Goc S.a.",
    "wof:placetype":"venue"
},
  "geometry": {"coordinates":[-8.7271146774,42.2400436401],"type":"Point"}
}