{
  "type": "Feature",
  "properties": {
    "addr:full":"Avda General Franco, S/n Pedrajas S. Esteban Valladolid 47430",
    "addr:housenumber":"s / n",
    "addr:postcode":"47430",
    "addr:street":"Avda General Franco;Pedrajas S. Esteban Valladolid",
    "iso:country":"ES",
    "sg:address":"Avda General Franco, S/n",
    "sg:city":"Pedrajas S. Esteban",
    "sg:orig_category":"Negocio De Materiales De Construcci\u00d3n",
    "sg:phone":"+34 983 60 54 79",
    "sg:postcode":"47430",
    "sg:province":"Valladolid",
    "wof:name":"Derco Pavimentos Y Terrazos S.l.",
    "wof:placetype":"venue"
},
  "geometry": {"coordinates":[-4.5796442032,41.3413314819],"type":"Point"}
}