{
  "type": "Feature",
  "properties": {
    "addr:full":"Trav De Gracia, 319 Barcelona Barcelona 08025",
    "addr:housenumber":"319",
    "addr:postcode":"08025",
    "addr:street":"Trav De Gracia",
    "iso:country":"ES",
    "sg:address":"Trav De Gracia, 319",
    "sg:city":"Barcelona",
    "sg:orig_category":"Peluqueros: De Se\u00d1oras",
    "sg:phone":"+34 934 58 99 97",
    "sg:postcode":"08025",
    "sg:province":"Barcelona",
    "wof:name":"Bayot De Haro Pilar",
    "wof:placetype":"venue"
},
  "geometry": {"coordinates":[2.1660790443,41.4065856934],"type":"Point"}
}