{
  "type": "Feature",
  "properties": {
    "addr:full":"Calle de San Juan De Letran, 5 Granada Granada 18012",
    "addr:housenumber":"5",
    "addr:postcode":"18012",
    "addr:street":"Calle De San",
    "iso:country":"ES",
    "sg:address":"Calle de San Juan De Letran, 5",
    "sg:city":"Granada",
    "sg:orig_category":"M\u00c9dicos: Endocrinolog\u00cda Y Metabolismo",
    "sg:phone":"+34 958 29 25 20",
    "sg:postcode":"18012",
    "sg:province":"Granada",
    "wof:name":"Gonzalez Jimenez Amalia",
    "wof:placetype":"venue"
},
  "geometry": {"coordinates":[-3.6073830128,37.1860847473],"type":"Point"}
}