{
  "type": "Feature",
  "properties": {
    "addr:full":"Ctra Nacional 340, S/n Hoya Murcia 30816",
    "addr:housenumber":"s / n",
    "addr:postcode":"30816",
    "addr:street":"Ctra Nacional 340",
    "iso:country":"ES",
    "sg:address":"Ctra Nacional 340, S/n",
    "sg:city":"Hoya",
    "sg:orig_category":"Electricidad Veh\u00cdculo",
    "sg:phone":"+34 968 48 17 61",
    "sg:postcode":"30816",
    "sg:province":"Murcia",
    "wof:name":"Del Vas Mendez Miguel",
    "wof:placetype":"venue"
},
  "geometry": {"coordinates":[-1.5710790157,37.7104187012],"type":"Point"}
}