{
  "type": "Feature",
  "properties": {
    "iso:country":"ES",
    "sg:address":"Calle de Hospital, 42",
    "sg:city":"Nava Rey",
    "sg:orig_category":"Sociedades, Compa\u00d1\u00cdas Aseguradoras",
    "sg:phone":"+34 983 85 03 01",
    "sg:postcode":"47500",
    "sg:province":"Valladolid",
    "wof:name":"Castre\u00f1o Martin Maria Inmaculada",
    "wof:placetype":"venue"
},
  "geometry": {"coordinates":[-5.082657814,41.3284378052],"type":"Point"}
}