{
  "type": "Feature",
  "properties": {
    "addr:full":"Avda Mediterraneo (del), 1 Rincon Victoria M\u00e1laga 29730",
    "addr:housenumber":"1",
    "addr:postcode":"29730",
    "addr:street":"Avda Mediterraneo Del;Ma\u0301Laga",
    "iso:country":"ES",
    "sg:address":"Avda Mediterraneo (del), 1",
    "sg:city":"Rincon Victoria",
    "sg:orig_category":"Arreglo, Reparaci\u00d3n, Piezas Sueltas De Televisi\u00d3n, V\u00cddeo, Hi",
    "sg:phone":"+34 952 40 36 07",
    "sg:postcode":"29730",
    "sg:province":"M\u00e1laga",
    "wof:name":"Garcia Torres Carlos",
    "wof:placetype":"venue"
},
  "geometry": {"coordinates":[-4.2868151665,36.7152824402],"type":"Point"}
}