{
  "type": "Feature",
  "properties": {
    "iso:country":"ES",
    "sg:address":"Calle de Mayor, 10",
    "sg:city":"Biar",
    "sg:orig_category":"Carnicer\u00cdas, Carnicer\u00cdas",
    "sg:phone":"+34 965 81 01 58",
    "sg:postcode":"03410",
    "sg:province":"Alicante",
    "wof:name":"Sanchis Camarasa Tomas",
    "wof:placetype":"venue"
},
  "geometry": {"coordinates":[-0.7653989792,38.6297798157],"type":"Point"}
}