{
  "type": "Feature",
  "properties": {
    "iso:country":"ES",
    "sg:address":"Ptge Celler, S/n",
    "sg:city":"S. Cugat Valles",
    "sg:orig_category":"Asesor\u00cda Fiscal Y Jur\u00cddica",
    "sg:phone":"+34 936 75 19 54",
    "sg:postcode":"08172",
    "sg:province":"Barcelona",
    "wof:name":"Associacio De Propietaris De Sant Cugat Del Valles",
    "wof:placetype":"venue"
},
  "geometry": {"coordinates":[2.0851552486,41.471321106],"type":"Point"}
}