{
  "type": "Feature",
  "properties": {
    "iso:country":"ES",
    "sg:address":"Calle de General Oraa, 61",
    "sg:city":"Madrid",
    "sg:orig_category":"Ropa Para Ni\u00d1os (al Por Menor)",
    "sg:phone":"+34 915 62 00 20",
    "sg:postcode":"28006",
    "sg:province":"Madrid",
    "wof:name":"Martin Alafont Cristina",
    "wof:placetype":"venue"
},
  "geometry": {"coordinates":[-3.6776614189,40.4358711243],"type":"Point"}
}