{
  "type": "Feature",
  "properties": {
    "addr:full":"Carr Don Pere De Gomar, 10 Agramunt Lleida 25310",
    "addr:housenumber":"10",
    "addr:postcode":"25310",
    "addr:street":"Carr Don Pere De Gomar",
    "iso:country":"ES",
    "sg:address":"Carr Don Pere De Gomar, 10",
    "sg:city":"Agramunt",
    "sg:orig_category":"Asociaciones Y Clubs Deportivos",
    "sg:phone":"+34 973 39 22 95",
    "sg:postcode":"25310",
    "sg:province":"Lleida",
    "wof:name":"Saladrigues Fernandez Maria Antonia",
    "wof:placetype":"venue"
},
  "geometry": {"coordinates":[1.0938349962,41.7863693237],"type":"Point"}
}