{
  "type": "Feature",
  "properties": {
    "addr:full":"Carr Wagner, 62 Badalona Barcelona 08917",
    "addr:housenumber":"62",
    "addr:postcode":"08917",
    "addr:street":"Carr Wagner",
    "iso:country":"ES",
    "sg:address":"Carr Wagner, 62",
    "sg:city":"Badalona",
    "sg:orig_category":"Supermercados Y Hipermercados",
    "sg:phone":"+34 934 60 78 25",
    "sg:postcode":"08917",
    "sg:province":"Barcelona",
    "wof:name":"Del Rio S.l.",
    "wof:placetype":"venue"
},
  "geometry": {"coordinates":[2.2222540379,41.4521789551],"type":"Point"}
}