{
  "type": "Feature",
  "properties": {
    "addr:full":"Avda Isabel Manoja, 17 Torremolinos M\u00e1laga 29620",
    "addr:housenumber":"17",
    "addr:postcode":"29620",
    "addr:street":"Avda Isabel Manoja;Ma\u0301Laga",
    "iso:country":"ES",
    "sg:address":"Avda Isabel Manoja, 17",
    "sg:city":"Torremolinos",
    "sg:classifiers":[
        {
            "category":"Autos & Motor Vehicles",
            "subcategory":"Automobile Sales",
            "type":"Retail Goods"
        }
    ],
    "sg:phone":"+34 952 38 09 73",
    "sg:postcode":"29620",
    "sg:province":"M\u00e1laga",
    "wof:name":"Bueno Sanchez Jose",
    "wof:placetype":"venue"
},
  "geometry": {"coordinates":[-4.501912117,36.6236572266],"type":"Point"}
}