{
  "type": "Feature",
  "properties": {
    "addr:full":"Calle de Santo Domingo De Guzman, 11 Valladolid Valladolid 47003",
    "addr:housenumber":"11",
    "addr:postcode":"47003",
    "addr:street":"Calle De Santo;Guzman",
    "iso:country":"ES",
    "sg:address":"Calle de Santo Domingo De Guzman, 11",
    "sg:city":"Valladolid",
    "sg:orig_category":"Arquitectos",
    "sg:phone":"+34 983 35 17 96",
    "sg:postcode":"47003",
    "sg:province":"Valladolid",
    "wof:name":"Lanao Eizaguirre Jose",
    "wof:placetype":"venue"
},
  "geometry": {"coordinates":[-4.7300372124,41.6561508179],"type":"Point"}
}