{
  "type": "Feature",
  "properties": {
    "iso:country":"ES",
    "sg:address":"Calle de Juan Bautista Topete, 7",
    "sg:city":"Guadalajara",
    "sg:orig_category":"Ingeniero",
    "sg:phone":"+34 949 22 88 55",
    "sg:postcode":"19001",
    "sg:province":"Guadalajara",
    "wof:name":"Enzibre S.l.",
    "wof:placetype":"venue"
},
  "geometry": {"coordinates":[-3.1645009518,40.6320457458],"type":"Point"}
}