{
  "type": "Feature",
  "properties": {
    "addr:full":"Avda Villarrasa, 26 Rociana Condado Huelva 21720",
    "addr:housenumber":"26",
    "addr:postcode":"21720",
    "addr:street":"Avda Villarrasa",
    "iso:country":"ES",
    "sg:address":"Avda Villarrasa, 26",
    "sg:city":"Rociana Condado",
    "sg:orig_category":"Ropa Para Se\u00d1oras Y Caballeros (al Por Menor)",
    "sg:phone":"+34 959 41 68 47",
    "sg:postcode":"21720",
    "sg:province":"Huelva",
    "wof:name":"La Cadena Suarez S.l.",
    "wof:placetype":"venue"
},
  "geometry": {"coordinates":[-6.59852314,37.3103752136],"type":"Point"}
}