{
  "type": "Feature",
  "properties": {
    "addr:full":"Carrer de Comer\u00c7, 15 Hospitalet Llobregat Barcelona 08902",
    "addr:housenumber":"15",
    "addr:postcode":"08902",
    "addr:street":"Carrer De Comerc\u0327",
    "iso:country":"ES",
    "sg:address":"Carrer de Comer\u00c7, 15",
    "sg:city":"Hospitalet Llobregat",
    "sg:orig_category":"Agentes, Concesionarios Y Sucursales De Veh\u00cdculos",
    "sg:phone":"+34 932 96 76 73",
    "sg:postcode":"08902",
    "sg:province":"Barcelona",
    "wof:name":"Multicars Pintura Y Chapa S.l.",
    "wof:placetype":"venue"
},
  "geometry": {"coordinates":[2.1261560917,41.3660850525],"type":"Point"}
}