{
  "type": "Feature",
  "properties": {
    "iso:country":"ES",
    "sg:address":"C/ Juan Espuche, 32",
    "sg:city":"Elche",
    "sg:orig_category":"Muebles, Minoristas",
    "sg:phone":"+34 965 45 94 86",
    "sg:postcode":"03202",
    "sg:province":"Alicante",
    "wof:name":"Porcel Trave Jose",
    "wof:placetype":"venue"
},
  "geometry": {"coordinates":[-0.6831809878,38.2710418701],"type":"Point"}
}