{
  "type": "Feature",
  "properties": {
    "addr:full":"Calle de Carmen Montoya, 1 Madrid Madrid 28029",
    "addr:housenumber":"1",
    "addr:postcode":"28029",
    "addr:street":"Calle De Carmen Montoya",
    "iso:country":"ES",
    "sg:address":"Calle de Carmen Montoya, 1",
    "sg:city":"Madrid",
    "sg:orig_category":"Pod\u00d3logos: Pedicuros",
    "sg:phone":"+34 917 33 81 56",
    "sg:postcode":"28029",
    "sg:province":"Madrid",
    "wof:name":"Fernandez Martinez Andres",
    "wof:placetype":"venue"
},
  "geometry": {"coordinates":[-3.6991801262,40.4694023132],"type":"Point"}
}