{
  "type": "Feature",
  "properties": {
    "addr:full":"Calle de Vitoria, 140 Burgos Burgos 09007",
    "addr:housenumber":"140",
    "addr:postcode":"09007",
    "addr:street":"Calle De Vitoria",
    "iso:country":"ES",
    "sg:address":"Calle de Vitoria, 140",
    "sg:city":"Burgos",
    "sg:orig_category":"Arquitectos",
    "sg:phone":"+34 947 22 17 71",
    "sg:postcode":"09007",
    "sg:province":"Burgos",
    "wof:name":"Estudio A3 Arquitectos S.c.",
    "wof:placetype":"venue"
},
  "geometry": {"coordinates":[-3.6764729023,42.3490562439],"type":"Point"}
}