{
  "type": "Feature",
  "properties": {
    "iso:country":"ES",
    "sg:address":"Calle de Epifanio Campo Nu\u00d1ez, S/n",
    "sg:city":"Laracha",
    "sg:orig_category":"T\u00c9cnicos Veterinarios",
    "sg:phone":"+34 981 60 56 56",
    "sg:postcode":"15145",
    "sg:province":"La Coru\u00f1a",
    "wof:name":"Martinez Blasco Antonio Andres",
    "wof:placetype":"venue"
},
  "geometry": {"coordinates":[-8.5869235992,43.2477798462],"type":"Point"}
}