{
  "type": "Feature",
  "properties": {
    "addr:full":"Carrer de Marquesa De La Roca (de La), 15 Tortosa Tarragona 43500",
    "addr:postcode":"43500",
    "addr:street":"Carrer De Marquesa De La",
    "iso:country":"ES",
    "sg:address":"Carrer de Marquesa De La Roca (de La), 15",
    "sg:city":"Tortosa",
    "sg:orig_category":"Ebanistas Y Talladores De Muebles Y Objetos De Arte",
    "sg:phone":"+34 977 50 09 97",
    "sg:postcode":"43500",
    "sg:province":"Tarragona",
    "wof:name":"Ginovart Montserrat Joaquin",
    "wof:placetype":"venue"
},
  "geometry": {"coordinates":[0.5167869925,40.8114738464],"type":"Point"}
}