{
  "type": "Feature",
  "properties": {
    "addr:full":"Avda Andalucia, 57 Velez-rubio Almer\u00eda 04820",
    "addr:housenumber":"57",
    "addr:postcode":"04820",
    "addr:street":"Avda Andalucia;Almeri\u0301A",
    "iso:country":"ES",
    "sg:address":"Avda Andalucia, 57",
    "sg:city":"Velez-rubio",
    "sg:orig_category":"Electrodom\u00c9sticos (al Por Menor)",
    "sg:phone":"+34 950 41 04 40",
    "sg:postcode":"04820",
    "sg:province":"Almer\u00eda",
    "sg:website":"www.losvelez.com",
    "wof:name":"Mecap S.coop.andaluza",
    "wof:placetype":"venue"
},
  "geometry": {"coordinates":[-2.0760750771,37.6472740173],"type":"Point"}
}