{
  "type": "Feature",
  "properties": {
    "addr:full":"Calle de Serena, 1 Leganes Madrid 28915",
    "addr:housenumber":"1",
    "addr:postcode":"28915",
    "addr:street":"Calle De Serena",
    "iso:country":"ES",
    "sg:address":"Calle de Serena, 1",
    "sg:city":"Leganes",
    "sg:classifiers":[
        {
            "category":"Personal",
            "subcategory":"Barber",
            "type":"Services"
        }
    ],
    "sg:phone":"+34 916 80 43 45",
    "sg:postcode":"28915",
    "sg:province":"Madrid",
    "sg:tags":[
        "caballeros",
        "de",
        "peluqueros"
    ],
    "wof:name":"Garcia Garcia Eugenio",
    "wof:placetype":"venue"
},
  "geometry": {"coordinates":[-3.7556180954,40.3317527771],"type":"Point"}
}