{
  "type": "Feature",
  "properties": {
    "addr:full":"Huerta, 29 El Viso Alcor Sevilla 41520",
    "addr:housenumber":"29",
    "addr:postcode":"41520",
    "addr:street":"Huerta",
    "iso:country":"ES",
    "sg:address":"Huerta, 29",
    "sg:city":"El Viso Alcor",
    "sg:orig_category":"Tapicer\u00cdas",
    "sg:phone":"+34 955 94 67 07",
    "sg:postcode":"41520",
    "sg:province":"Sevilla",
    "wof:name":"Zamorano Galvez Francisco Javier",
    "wof:placetype":"venue"
},
  "geometry": {"coordinates":[-5.7302889824,37.3845672607],"type":"Point"}
}