{
  "type": "Feature",
  "properties": {
    "iso:country":"ES",
    "sg:address":"Calle de Bordadoras, 6",
    "sg:city":"Sevilla",
    "sg:orig_category":"Frutas, Legumbres Frescas Y Tempranas (al Por Menor)",
    "sg:phone":"+34 954 95 23 45",
    "sg:postcode":"41008",
    "sg:province":"Sevilla",
    "wof:name":"Marquez Barrios Antonio",
    "wof:placetype":"venue"
},
  "geometry": {"coordinates":[-5.9674139023,37.4207267761],"type":"Point"}
}