{
  "type": "Feature",
  "properties": {
    "addr:full":"Plaz Rafael De Riego, 1 Langreo Asturias 33900",
    "addr:housenumber":"1",
    "addr:postcode":"33900",
    "iso:country":"ES",
    "sg:address":"Plaz Rafael De Riego, 1",
    "sg:city":"Langreo",
    "sg:orig_category":"\u00d3ptica: Instrumentos (fabricaci\u00d3n)",
    "sg:phone":"+34 985 67 30 63",
    "sg:postcode":"33900",
    "sg:province":"Asturias",
    "wof:name":"General Optica S.a.",
    "wof:placetype":"venue"
},
  "geometry": {"coordinates":[-5.6692090034,43.2883987427],"type":"Point"}
}