{
  "type": "Feature",
  "properties": {
    "addr:full":"Carrer de Alos, 14 Hospitalet Llobregat Barcelona 08901",
    "addr:housenumber":"14",
    "addr:postcode":"08901",
    "addr:street":"Carrer De Alos",
    "iso:country":"ES",
    "sg:address":"Carrer de Alos, 14",
    "sg:city":"Hospitalet Llobregat",
    "sg:orig_category":"Art\u00cdculos De Madera (fabricaci\u00d3n Y Al Por Mayor)",
    "sg:phone":"+34 933 37 36 64",
    "sg:postcode":"08901",
    "sg:province":"Barcelona",
    "wof:name":"Martinez Febrero Antonio",
    "wof:placetype":"venue"
},
  "geometry": {"coordinates":[2.1176528931,41.3672485352],"type":"Point"}
}