{
  "type": "Feature",
  "properties": {
    "addr:full":"Carrer de Major (sant Celoni), 107 S. Celoni Barcelona 08470",
    "addr:housenumber":"107",
    "addr:postcode":"08470",
    "addr:street":"Carrer De Major Sant Celoni;S. Celoni Barcelona",
    "iso:country":"ES",
    "sg:address":"Carrer de Major (sant Celoni), 107",
    "sg:city":"S. Celoni",
    "sg:orig_category":"Carnicer\u00cdas, Carnicer\u00cdas",
    "sg:phone":"+34 938 67 00 70",
    "sg:postcode":"08470",
    "sg:province":"Barcelona",
    "wof:name":"Pons Cornella Antonio",
    "wof:placetype":"venue"
},
  "geometry": {"coordinates":[2.4910759926,41.6898155212],"type":"Point"}
}