{
  "type": "Feature",
  "properties": {
    "iso:country":"ES",
    "sg:address":"Plaza Del Mercado, S/n",
    "sg:city":"Hellin",
    "sg:orig_category":"Poller\u00cda Y Caza (al Por Menor)",
    "sg:phone":"+34 967 30 44 69",
    "sg:postcode":"02400",
    "sg:province":"Albacete",
    "wof:name":"Hermanos Castillo Alvarado S.l.",
    "wof:placetype":"venue"
},
  "geometry": {"coordinates":[-1.7001819611,38.5132293701],"type":"Point"}
}