{
  "type": "Feature",
  "properties": {
    "iso:country":"ES",
    "sg:address":"Calle de Amnistia, 5",
    "sg:city":"Madrid",
    "sg:orig_category":"Empresarios",
    "sg:phone":"+34 915 41 75 73",
    "sg:postcode":"28013",
    "sg:province":"Madrid",
    "wof:name":"Fundacion De Iniciativas Y Locales",
    "wof:placetype":"venue"
},
  "geometry": {"coordinates":[-3.710619688,40.4172172546],"type":"Point"}
}