{
  "type": "Feature",
  "properties": {
    "addr:full":"Calle de Principe De Vergara, 133 Madrid Madrid 28002",
    "addr:housenumber":"133",
    "addr:postcode":"28002",
    "addr:street":"Calle De Principe De Vergara",
    "iso:country":"ES",
    "sg:address":"Calle de Principe De Vergara, 133",
    "sg:city":"Madrid",
    "sg:orig_category":"Agentes, Concesionarios Y Sucursales De Veh\u00cdculos",
    "sg:phone":"+34 915 64 50 58",
    "sg:postcode":"28002",
    "sg:province":"Madrid",
    "wof:name":"Herranz Concesionarios S.a.",
    "wof:placetype":"venue"
},
  "geometry": {"coordinates":[-3.6786110401,40.4439086914],"type":"Point"}
}