{
  "type": "Feature",
  "properties": {
    "iso:country":"ES",
    "sg:address":"Avda Cantabria (de), 5",
    "sg:city":"Cueto",
    "sg:orig_category":"Arquitectos",
    "sg:phone":"+34 942 39 04 28",
    "sg:postcode":"39012",
    "sg:province":"Cantabria",
    "wof:name":"Alvarez Del Palacio Jose Ramon",
    "wof:placetype":"venue"
},
  "geometry": {"coordinates":[-3.7923424244,43.4784088135],"type":"Point"}
}