{
  "type": "Feature",
  "properties": {
    "addr:full":"Calle de Brazato, 7 Zaragoza Zaragoza 50012",
    "addr:housenumber":"7",
    "addr:postcode":"50012",
    "addr:street":"Calle De Brazato",
    "iso:country":"ES",
    "sg:address":"Calle de Brazato, 7",
    "sg:city":"Zaragoza",
    "sg:orig_category":"Inform\u00c1tica, Ofim\u00c1tica (estudios, Asesor\u00cda, Ingenier\u00cda, Formaci\u00d3n)",
    "sg:phone":"+34 976 56 13 24",
    "sg:postcode":"50012",
    "sg:province":"Zaragoza",
    "wof:name":"Synstar Computer Service S.l.",
    "wof:placetype":"venue"
},
  "geometry": {"coordinates":[-0.9118559957,41.6271591187],"type":"Point"}
}