{
  "type": "Feature",
  "properties": {
    "iso:country":"ES",
    "sg:address":"Avda Nuestra Se\u00d1ora De Fatima, 77",
    "sg:city":"Madrid",
    "sg:orig_category":"Ingenier\u00cda, Centros De Estudios (industria)",
    "sg:phone":"+34 914 66 70 98",
    "sg:postcode":"28047",
    "sg:province":"Madrid",
    "wof:name":"Mu\u00f1oz Sanchez Maria",
    "wof:placetype":"venue"
},
  "geometry": {"coordinates":[-3.7487139702,40.3790206909],"type":"Point"}
}