{
  "type": "Feature",
  "properties": {
    "addr:full":"Avda Cruz Roja (la), 64 Sevilla Sevilla 41008",
    "addr:housenumber":"64",
    "addr:postcode":"41008",
    "addr:street":"Avda Cruz Roja La",
    "iso:country":"ES",
    "sg:address":"Avda Cruz Roja (la), 64",
    "sg:city":"Sevilla",
    "sg:orig_category":"Ebanister\u00cda",
    "sg:phone":"+34 954 35 64 92",
    "sg:postcode":"41008",
    "sg:province":"Sevilla",
    "wof:name":"Labrador Rodriguez Francisco Javier",
    "wof:placetype":"venue"
},
  "geometry": {"coordinates":[-5.9814090729,37.4025688171],"type":"Point"}
}