{
  "type": "Feature",
  "properties": {
    "iso:country":"ES",
    "sg:address":"Julian Etxeberria Kalea, 8",
    "sg:city":"Eibar",
    "sg:orig_category":"Dietistas",
    "sg:phone":"+34 943 20 01 93",
    "sg:postcode":"20600",
    "sg:province":"Guip\u00f9zcoa",
    "wof:name":"Dietetica Mikaitz, Rosa Monge Llorente",
    "wof:placetype":"venue"
},
  "geometry": {"coordinates":[-2.4699909687,43.1857757568],"type":"Point"}
}