{
  "type": "Feature",
  "properties": {
    "iso:country":"ES",
    "sg:address":"Ctra. S. Pablo, Km. 0001,3",
    "sg:city":"Menasalbas",
    "sg:orig_category":"Art\u00cdculos De Madera (fabricaci\u00d3n Y Al Por Mayor)",
    "sg:phone":"+34 925 40 73 50",
    "sg:postcode":"45128",
    "sg:province":"Toledo",
    "wof:name":"Ruesmobel Brn S.l.",
    "wof:placetype":"venue"
},
  "geometry": {"coordinates":[-4.2844028473,39.636806488],"type":"Point"}
}