{
  "type": "Feature",
  "properties": {
    "addr:full":"Avda Dr Villa Diaz, 1 Carmona Sevilla 41410",
    "addr:housenumber":"1",
    "addr:postcode":"41410",
    "addr:street":"Avda Dr Villa Diaz",
    "iso:country":"ES",
    "sg:address":"Avda Dr Villa Diaz, 1",
    "sg:city":"Carmona",
    "sg:orig_category":"Zapatos (al Por Menor)",
    "sg:phone":"+34 954 14 04 07",
    "sg:postcode":"41410",
    "sg:province":"Sevilla",
    "wof:name":"Perez Garcia Fermin",
    "wof:placetype":"venue"
},
  "geometry": {"coordinates":[-5.6433792114,37.4708709717],"type":"Point"}
}