{
  "type": "Feature",
  "properties": {
    "iso:country":"ES",
    "sg:address":"C/ Dusai, D'en, 28",
    "sg:city":"Porreres",
    "sg:orig_category":"Frutas Y Legumbres Frescas (al Por Mayor)",
    "sg:phone":"+34 971 16 83 11",
    "sg:postcode":"07260",
    "sg:province":"Islas Baleares",
    "wof:name":"Barcelo Bennassar Guillem",
    "wof:placetype":"venue"
},
  "geometry": {"coordinates":[3.025851965,39.5108146667],"type":"Point"}
}