{
  "type": "Feature",
  "properties": {
    "addr:full":"Carrer de Roger De Flor, 49 Barcelona Barcelona 08013",
    "addr:housenumber":"49",
    "addr:postcode":"08013",
    "addr:street":"Carrer De Roger De Flor",
    "iso:country":"ES",
    "sg:address":"Carrer de Roger De Flor, 49",
    "sg:city":"Barcelona",
    "sg:orig_category":"Alumbrados",
    "sg:phone":"+34 932 32 27 11",
    "sg:postcode":"08013",
    "sg:province":"Barcelona",
    "wof:name":"Sli Sylvania S.a.",
    "wof:placetype":"venue"
},
  "geometry": {"coordinates":[2.1804339886,41.3927078247],"type":"Point"}
}