{
  "type": "Feature",
  "properties": {
    "addr:full":"Plaz Buen Pastor Del, 11 Donostia-san Sebastian Guip\u00f9zcoa 20005",
    "addr:housenumber":"11",
    "addr:postcode":"20005",
    "addr:street":"Plaz Buen Pastor Del",
    "iso:country":"ES",
    "sg:address":"Plaz Buen Pastor Del, 11",
    "sg:city":"Donostia-san Sebastian",
    "sg:classifiers":[
        {
            "category":"Personal",
            "subcategory":"Barber",
            "type":"Services"
        }
    ],
    "sg:phone":"+34 943 46 54 24",
    "sg:postcode":"20005",
    "sg:province":"Guip\u00f9zcoa",
    "sg:tags":[
        "caballeros",
        "de",
        "peluqueros"
    ],
    "wof:name":"Pedro Jose Colas Ramon Y Otro Cdad",
    "wof:placetype":"venue"
},
  "geometry": {"coordinates":[-1.981063962,43.3168907166],"type":"Point"}
}