{
  "type": "Feature",
  "properties": {
    "iso:country":"ES",
    "sg:address":"Rua Ria Do Ferrol, 1",
    "sg:city":"Arteixo",
    "sg:orig_category":"Maquinaria Para Industrias Diversas",
    "sg:phone":"+34 981 63 32 14",
    "sg:postcode":"15142",
    "sg:province":"La Coru\u00f1a",
    "sg:website":"www.combursa.com",
    "wof:name":"Grupo Combursa S.l.",
    "wof:placetype":"venue"
},
  "geometry": {"coordinates":[-8.5077791214,43.3045387268],"type":"Point"}
}