{
  "type": "Feature",
  "properties": {
    "iso:country":"ES",
    "sg:address":"Calle de Bandera (la), 14",
    "sg:city":"Villalis De La Valduerna",
    "sg:orig_category":"Centros De Educaci\u00d3n Especial",
    "sg:phone":"+34 987 65 01 56",
    "sg:postcode":"24766",
    "sg:province":"Le\u00f3n",
    "wof:name":"Colegio Rural Agrupado De Destriana",
    "wof:placetype":"venue"
},
  "geometry": {"coordinates":[-5.8963990211,42.300655365],"type":"Point"}
}