{
  "type": "Feature",
  "properties": {
    "addr:full":"Calle de Piedra, 1 Higuera Real Badajoz 06350",
    "addr:housenumber":"1",
    "addr:postcode":"06350",
    "addr:street":"Calle De Piedra",
    "iso:country":"ES",
    "sg:address":"Calle de Piedra, 1",
    "sg:city":"Higuera Real",
    "sg:orig_category":"T\u00c9cnicos Veterinarios",
    "sg:phone":"+34 924 72 34 54",
    "sg:postcode":"06350",
    "sg:province":"Badajoz",
    "wof:name":"Rodriguez-armijo Chardonnet Francisco Javier",
    "wof:placetype":"venue"
},
  "geometry": {"coordinates":[-6.688794136,38.1426353455],"type":"Point"}
}