{
  "type": "Feature",
  "properties": {
    "iso:country":"ES",
    "sg:address":"Avda Cadiz (de), 86",
    "sg:city":"Cordoba",
    "sg:orig_category":"Mec\u00c1nico Del Autom\u00d3vil",
    "sg:phone":"+34 957 29 79 02",
    "sg:postcode":"14013",
    "sg:province":"C\u00f3rdoba",
    "wof:name":"Tallerauto S.l.",
    "wof:placetype":"venue"
},
  "geometry": {"coordinates":[-4.7835001945,37.8640975952],"type":"Point"}
}