{
  "type": "Feature",
  "properties": {
    "addr:full":"Calle de Colon, 12 Tui Pontevedra 36700",
    "addr:housenumber":"12",
    "addr:postcode":"36700",
    "addr:street":"Calle De Colon",
    "iso:country":"ES",
    "sg:address":"Calle de Colon, 12",
    "sg:city":"Tui",
    "sg:orig_category":"Comercio, Reparaci\u00d3n De Motocicletas, Bicicletas Y Piezas Sueltas",
    "sg:phone":"+34 986 60 15 71",
    "sg:postcode":"36700",
    "sg:province":"Pontevedra",
    "wof:name":"Rodriguez Romero Francisco",
    "wof:placetype":"venue"
},
  "geometry": {"coordinates":[-8.6486606598,42.0503349304],"type":"Point"}
}