{
  "type": "Feature",
  "properties": {
    "iso:country":"ES",
    "sg:address":"Calle de Principe De Asturias, 6",
    "sg:city":"Elda",
    "sg:orig_category":"Mutuas De Seguros",
    "sg:phone":"+34 966 98 22 32",
    "sg:postcode":"03600",
    "sg:province":"Alicante",
    "wof:name":"Vidal Aguado Luis Manuel",
    "wof:placetype":"venue"
},
  "geometry": {"coordinates":[-0.7903839946,38.4765014648],"type":"Point"}
}