{
  "type": "Feature",
  "properties": {
    "addr:full":"Cra Sant Pere De Ribes, S/n Sitges Barcelona 08870",
    "addr:housenumber":"s / n",
    "addr:postcode":"08870",
    "addr:street":"Ribes",
    "iso:country":"ES",
    "sg:address":"Cra Sant Pere De Ribes, S/n",
    "sg:city":"Sitges",
    "sg:classifiers":[
        {
            "category":"Taxi",
            "type":"Transportation"
        }
    ],
    "sg:phone":"+34 938 94 07 85",
    "sg:postcode":"08870",
    "sg:province":"Barcelona",
    "wof:name":"Mascaraque Huerta Eulalio",
    "wof:placetype":"venue"
},
  "geometry": {"coordinates":[1.8054499626,41.2342414856],"type":"Point"}
}