{
  "type": "Feature",
  "properties": {
    "iso:country":"ES",
    "sg:address":"Avda Andalucia, 6",
    "sg:city":"Albu\u00f1ol",
    "sg:orig_category":"Cervecer\u00cdas",
    "sg:phone":"+34 958 82 67 12",
    "sg:postcode":"18700",
    "sg:province":"Granada",
    "wof:name":"Eurotel-sur S.l.",
    "wof:placetype":"venue"
},
  "geometry": {"coordinates":[-3.2005589008,36.7910614014],"type":"Point"}
}