{
  "type": "Feature",
  "properties": {
    "addr:full":"Calle de San Juan, 6 Sanlucar De Barrameda C\u00e1diz 11540",
    "addr:housenumber":"6",
    "addr:postcode":"11540",
    "addr:street":"Calle De San Juan;Ca\u0301Diz",
    "iso:country":"ES",
    "sg:address":"Calle de San Juan, 6",
    "sg:city":"Sanlucar De Barrameda",
    "sg:orig_category":"Cajas Para Embalar",
    "sg:phone":"+34 956 36 12 46",
    "sg:postcode":"11540",
    "sg:province":"C\u00e1diz",
    "wof:name":"Caja Rural Del Sur Sociedad Cooperativa",
    "wof:placetype":"venue"
},
  "geometry": {"coordinates":[-6.3542909622,36.7785682678],"type":"Point"}
}