{
  "type": "Feature",
  "properties": {
    "addr:full":"El Calvario, 15 Los Llanos Aridane Santa Cruz De Tenerife 38760",
    "addr:housenumber":"15",
    "addr:postcode":"38760",
    "addr:street":"El Calvario",
    "iso:country":"ES",
    "sg:address":"El Calvario, 15",
    "sg:city":"Los Llanos Aridane",
    "sg:orig_category":"Peluquer\u00cdas, Peluquer\u00cda Mixta",
    "sg:phone":"+34 922 46 16 09",
    "sg:postcode":"38760",
    "sg:province":"Santa Cruz De Tenerife",
    "wof:name":"Toledo Vi\u00f1a Antonia Maria",
    "wof:placetype":"venue"
},
  "geometry": {"coordinates":[-17.9082660675,28.6586437225],"type":"Point"}
}