{
  "type": "Feature",
  "properties": {
    "addr:full":"Calle de Rodriguez Marin, 22 Ecija Sevilla 41400",
    "addr:housenumber":"22",
    "addr:postcode":"41400",
    "addr:street":"Calle De Rodriguez Marin",
    "iso:country":"ES",
    "sg:address":"Calle de Rodriguez Marin, 22",
    "sg:city":"Ecija",
    "sg:orig_category":"Alimentaci\u00d3n General (al Por Menor)",
    "sg:phone":"+34 954 83 23 22",
    "sg:postcode":"41400",
    "sg:province":"Sevilla",
    "wof:name":"Rosa Bonilla Francisco",
    "wof:placetype":"venue"
},
  "geometry": {"coordinates":[-5.0832648277,37.5389709473],"type":"Point"}
}