{
  "type": "Feature",
  "properties": {
    "addr:full":"Pl. Candelaria, S/n Sevilla Sevilla 41006",
    "addr:housenumber":"s / n",
    "addr:postcode":"41006",
    "addr:street":"Candelaria",
    "iso:country":"ES",
    "sg:address":"Pl. Candelaria, S/n",
    "sg:city":"Sevilla",
    "sg:orig_category":"Iglesia Cat\u00d3lica",
    "sg:phone":"+34 954 63 50 91",
    "sg:postcode":"41006",
    "sg:province":"Sevilla",
    "wof:name":"Parroquia De Nuestra Se\u00f1ora De Candelaria",
    "wof:placetype":"venue"
},
  "geometry": {"coordinates":[-5.9538841248,37.3821411133],"type":"Point"}
}