{
  "type": "Feature",
  "properties": {
    "iso:country":"ES",
    "sg:address":"Calle de Gamazo, 11",
    "sg:city":"Valladolid",
    "sg:orig_category":"Registro De Empresas",
    "sg:phone":"+34 983 20 79 22",
    "sg:postcode":"47004",
    "sg:province":"Valladolid",
    "wof:name":"Perez Ruiz Esther",
    "wof:placetype":"venue"
},
  "geometry": {"coordinates":[-4.7260699272,41.6466903687],"type":"Point"}
}