{
  "type": "Feature",
  "properties": {
    "addr:full":"Calle de Ibiza, 18 Madrid Madrid 28009",
    "addr:housenumber":"18",
    "addr:postcode":"madrid;28009",
    "addr:street":"Calle De Ibiza",
    "iso:country":"ES",
    "sg:address":"Calle de Ibiza, 18",
    "sg:city":"Madrid",
    "sg:orig_category":"Peluqueros: De Se\u00d1oras",
    "sg:phone":"+34 914 09 65 88",
    "sg:postcode":"28009",
    "sg:province":"Madrid",
    "wof:name":"Padilla Olivares Juana",
    "wof:placetype":"venue"
},
  "geometry": {"coordinates":[-3.6764099598,40.4180984497],"type":"Point"}
}