{
  "type": "Feature",
  "properties": {
    "addr:full":"Calle de Don Juan De Austria, 12 Malaga M\u00e1laga 29009",
    "addr:housenumber":"12",
    "addr:postcode":"29009",
    "addr:street":"Calle De Don Juan De Austria;Ma\u0301Laga",
    "iso:country":"ES",
    "sg:address":"Calle de Don Juan De Austria, 12",
    "sg:city":"Malaga",
    "sg:orig_category":"Equipo De Refrigeraci\u00d3n Industrial",
    "sg:phone":"+34 952 30 56 50",
    "sg:postcode":"29009",
    "sg:province":"M\u00e1laga",
    "sg:website":"www.garnacho.com",
    "wof:name":"Frio Industrial Garnacho S. A.",
    "wof:placetype":"venue"
},
  "geometry": {"coordinates":[-4.4288282394,36.7245445251],"type":"Point"}
}