{
  "type": "Feature",
  "properties": {
    "addr:full":"Carr Bonifaci Viii, 1 Lleida Lleida 25005",
    "addr:housenumber":"1",
    "addr:postcode":"25005",
    "addr:street":"Carr Bonifaci Viii",
    "iso:country":"ES",
    "sg:address":"Carr Bonifaci Viii, 1",
    "sg:city":"Lleida",
    "sg:orig_category":"Fabricaci\u00d3n, Venta, Instalaci\u00d3n De R\u00d3tulos, De R\u00d3tulos Luminosos",
    "sg:phone":"+34 973 22 52 82",
    "sg:postcode":"25005",
    "sg:province":"Lleida",
    "wof:name":"Toni Falcon Retols Sl",
    "wof:placetype":"venue"
},
  "geometry": {"coordinates":[0.6267700195,41.6261177063],"type":"Point"}
}