{
  "type": "Feature",
  "properties": {
    "addr:full":"Calle de Ruiz De Alarcon, 27 Madrid Madrid 28014",
    "addr:housenumber":"27",
    "addr:postcode":"madrid;28014",
    "addr:street":"Calle De Ruiz De Alarcon",
    "iso:country":"ES",
    "sg:address":"Calle de Ruiz De Alarcon, 27",
    "sg:city":"Madrid",
    "sg:orig_category":"Centros Empresariales",
    "sg:phone":"+34 914 29 44 69",
    "sg:postcode":"28014",
    "sg:province":"Madrid",
    "wof:name":"Ana Chiclana Sl",
    "wof:placetype":"venue"
},
  "geometry": {"coordinates":[-3.6914303303,40.4129562378],"type":"Point"}
}