{
  "type": "Feature",
  "properties": {
    "iso:country":"ES",
    "sg:address":"Avda Constitucion, 27",
    "sg:city":"Alcazar S. Juan",
    "sg:orig_category":"Aud\u00cdfonos",
    "sg:phone":"+34 926 55 22 82",
    "sg:postcode":"13600",
    "sg:province":"Ciudad Real",
    "wof:name":"Audiologia Alcazar S.l.",
    "wof:placetype":"venue"
},
  "geometry": {"coordinates":[-3.2190089226,39.392906189],"type":"Point"}
}