{
  "type": "Feature",
  "properties": {
    "iso:country":"ES",
    "sg:address":"Calle de Barranco, 13",
    "sg:city":"Guaro",
    "sg:orig_category":"Bazares, Art\u00cdculos De Limpieza Y De Cocina (al Por Menor)",
    "sg:phone":"+34 952 45 79 53",
    "sg:postcode":"29108",
    "sg:province":"M\u00e1laga",
    "wof:name":"Carretero Gonzalez Catalina",
    "wof:placetype":"venue"
},
  "geometry": {"coordinates":[-4.8324379921,36.6560897827],"type":"Point"}
}