{
  "type": "Feature",
  "properties": {
    "iso:country":"ES",
    "sg:address":"Carr Damia Estela I Molinet, 6",
    "sg:city":"Girona",
    "sg:orig_category":"Contenedores (mercanc\u00cdas)",
    "sg:phone":"+34 972 22 52 92",
    "sg:postcode":"17007",
    "sg:province":"Girona",
    "wof:name":"Contenidors Girona S.l",
    "wof:placetype":"venue"
},
  "geometry": {"coordinates":[2.8157529831,41.9917755127],"type":"Point"}
}