{
  "type": "Feature",
  "properties": {
    "addr:full":"Luga Rabita (la), S/n Rabita Ja\u00e9n 23684",
    "addr:postcode":"23684",
    "addr:street":"La S / N",
    "iso:country":"ES",
    "sg:address":"Luga Rabita (la), S/n",
    "sg:city":"Rabita",
    "sg:orig_category":"Producci\u00d3n, Venta De Productos De Agricultura Biol\u00d3gica",
    "sg:phone":"+34 953 12 13 49",
    "sg:postcode":"23684",
    "sg:province":"Ja\u00e9n",
    "wof:name":"Fernandez Saro Carmen",
    "wof:placetype":"venue"
},
  "geometry": {"coordinates":[-4.0506858826,37.4916191101],"type":"Point"}
}