{
  "type": "Feature",
  "properties": {
    "iso:country":"ES",
    "sg:address":"Calle de Gasset Y Artime, 29",
    "sg:city":"Alacant",
    "sg:orig_category":"Organizaciones Profesionales",
    "sg:phone":"+34 965 14 06 79",
    "sg:postcode":"03012",
    "sg:province":"Alicante",
    "wof:name":"De La Cruz Almaraz Milagros",
    "wof:placetype":"venue"
},
  "geometry": {"coordinates":[-0.4791870117,38.3572845459],"type":"Point"}
}