{
  "type": "Feature",
  "properties": {
    "iso:country":"ES",
    "sg:address":"Buenavista De Arriba, 64",
    "sg:city":"Bre\u00f1a Alta",
    "sg:orig_category":"Empresas De Portes Y Mensajer\u00cda",
    "sg:phone":"+34 922 42 91 62",
    "sg:postcode":"38713",
    "sg:province":"Santa Cruz De Tenerife",
    "wof:name":"Cargopack Expres S.l.",
    "wof:placetype":"venue"
},
  "geometry": {"coordinates":[-17.7823314667,28.670255661],"type":"Point"}
}