{
  "type": "Feature",
  "properties": {
    "iso:country":"ES",
    "sg:address":"Cami Assagador De Santa Llucia, 29",
    "sg:city":"Montgo",
    "sg:orig_category":"Promotores Constructores",
    "sg:phone":"+34 966 42 45 49",
    "sg:postcode":"03700",
    "sg:province":"Alicante",
    "wof:name":"Bausanierung Jahn S.l.",
    "wof:placetype":"venue"
},
  "geometry": {"coordinates":[0.1143869981,38.8226852417],"type":"Point"}
}