{
  "type": "Feature",
  "properties": {
    "addr:full":"Calle de Mayor, 77 Cari\u00f1ena Zaragoza 50400",
    "addr:housenumber":"77",
    "addr:postcode":"50400",
    "addr:street":"Calle De Mayor",
    "iso:country":"ES",
    "sg:address":"Calle de Mayor, 77",
    "sg:city":"Cari\u00f1ena",
    "sg:orig_category":"Reposter\u00cdas",
    "sg:phone":"+34 976 62 07 72",
    "sg:postcode":"50400",
    "sg:province":"Zaragoza",
    "wof:name":"Gonzalvo Berne Alejandro",
    "wof:placetype":"venue"
},
  "geometry": {"coordinates":[-1.2242779732,41.3396224976],"type":"Point"}
}