{
  "type": "Feature",
  "properties": {
    "addr:full":"C/ Juan Sansano Ibarra, 19 Elche Alicante 03205",
    "addr:housenumber":"19",
    "addr:postcode":"03205",
    "addr:street":"C / Juan Sansano Ibarra",
    "iso:country":"ES",
    "sg:address":"C/ Juan Sansano Ibarra, 19",
    "sg:city":"Elche",
    "sg:orig_category":"Peluqueros: De Se\u00d1oras",
    "sg:phone":"+34 965 46 45 16",
    "sg:postcode":"03205",
    "sg:province":"Alicante",
    "wof:name":"Marin Mora Juan",
    "wof:placetype":"venue"
},
  "geometry": {"coordinates":[-0.71489501,38.2704124451],"type":"Point"}
}