{
  "type": "Feature",
  "properties": {
    "iso:country":"ES",
    "sg:address":"Calle de Alfonso Viii, 4",
    "sg:city":"Carolina",
    "sg:classifiers":[
        {
            "category":"Personal",
            "subcategory":"Barber",
            "type":"Services"
        }
    ],
    "sg:phone":"+34 953 68 18 01",
    "sg:postcode":"23200",
    "sg:province":"Ja\u00e9n",
    "sg:tags":[
        "caballeros",
        "de",
        "peluqueros"
    ],
    "wof:name":"Osorio Albanchez Francisco",
    "wof:placetype":"venue"
},
  "geometry": {"coordinates":[-3.5870280266,38.2852516174],"type":"Point"}
}