{
  "type": "Feature",
  "properties": {
    "iso:country":"ES",
    "sg:address":"Rua Casti\u00d1eiras, 1",
    "sg:city":"Sarria",
    "sg:orig_category":"Supermercados Y Hipermercados",
    "sg:phone":"+34 982 53 22 52",
    "sg:postcode":"27600",
    "sg:province":"Lugo",
    "wof:name":"Nu\u00f1ez Lopez Enrique",
    "wof:placetype":"venue"
},
  "geometry": {"coordinates":[-7.4176149368,42.7803688049],"type":"Point"}
}