{
  "type": "Feature",
  "properties": {
    "iso:country":"ES",
    "sg:address":"Calle de Ibiza, 60",
    "sg:city":"Madrid",
    "sg:orig_category":"Asesor\u00cda Sobre Comunicaci\u00d3n De Empresas",
    "sg:phone":"+34 915 04 12 70",
    "sg:postcode":"28009",
    "sg:province":"Madrid",
    "wof:name":"Costero Lopez Ismael",
    "wof:placetype":"venue"
},
  "geometry": {"coordinates":[-3.6713469028,40.417881012],"type":"Point"}
}