{
  "type": "Feature",
  "properties": {
    "addr:full":"Calle de Clavel (del), 20 Linea De La Concepcion C\u00e1diz 11300",
    "addr:housenumber":"20",
    "addr:postcode":"11300",
    "addr:street":"Calle De Clavel Del;Ca\u0301Diz",
    "iso:country":"ES",
    "sg:address":"Calle de Clavel (del), 20",
    "sg:city":"Linea De La Concepcion",
    "sg:orig_category":"Artes Gr\u00c1ficas, Artes Pl\u00c1sticas (curso)",
    "sg:phone":"+34 956 76 16 42",
    "sg:postcode":"11300",
    "sg:province":"C\u00e1diz",
    "wof:name":"Ciatelo Fernandez Manuel",
    "wof:placetype":"venue"
},
  "geometry": {"coordinates":[-5.3478250504,36.1628646851],"type":"Point"}
}