{
  "type": "Feature",
  "properties": {
    "iso:country":"ES",
    "sg:address":"Carrer de Antonio Machado, 11",
    "sg:city":"Barcelona",
    "sg:classifiers":[
        {
            "category":"Personal",
            "subcategory":"Barber",
            "type":"Services"
        }
    ],
    "sg:phone":"+34 934 28 63 85",
    "sg:postcode":"08042",
    "sg:province":"Barcelona",
    "sg:tags":[
        "caballeros",
        "de",
        "peluqueros"
    ],
    "wof:name":"Serrano Pe\u00f1a Juan Ramon",
    "wof:placetype":"venue"
},
  "geometry": {"coordinates":[2.1639170647,41.4420509338],"type":"Point"}
}