{
  "type": "Feature",
  "properties": {
    "iso:country":"ES",
    "sg:address":"Calle de Pedro De Vera, 36",
    "sg:city":"Palmas De Gran Canaria",
    "sg:orig_category":"Ense\u00d1anza, Formaci\u00d3n Profesional: Aprendizaje",
    "sg:phone":"+34 928 38 24 72",
    "sg:postcode":"35003",
    "sg:province":"Las Palmas",
    "wof:name":"Mancomunidad Interinsular De Cabildos",
    "wof:placetype":"venue"
},
  "geometry": {"coordinates":[-15.4191513062,28.1106052399],"type":"Point"}
}