{
  "type": "Feature",
  "properties": {
    "addr:full":"Carrer de Pau, 26 Manresa Barcelona 08243",
    "addr:housenumber":"26",
    "addr:postcode":"08243",
    "addr:street":"Carrer De Pau",
    "iso:country":"ES",
    "sg:address":"Carrer de Pau, 26",
    "sg:city":"Manresa",
    "sg:orig_category":"Carnicer\u00cdas, Carnicer\u00cdas",
    "sg:phone":"+34 938 73 99 15",
    "sg:postcode":"08243",
    "sg:province":"Barcelona",
    "wof:name":"Bricolectric Manresa S.l.",
    "wof:placetype":"venue"
},
  "geometry": {"coordinates":[1.8335399628,41.7372932434],"type":"Point"}
}