{
  "type": "Feature",
  "properties": {
    "addr:full":"Avgd Barcelona, 38 Oliana Lleida 25790",
    "addr:housenumber":"38",
    "addr:postcode":"25790",
    "iso:country":"ES",
    "sg:address":"Avgd Barcelona, 38",
    "sg:city":"Oliana",
    "sg:orig_category":"Bares, Piano",
    "sg:phone":"+34 973 47 06 24",
    "sg:postcode":"25790",
    "sg:province":"Lleida",
    "wof:name":"Hernandez Villar Jose Manuel",
    "wof:placetype":"venue"
},
  "geometry": {"coordinates":[1.3126679659,42.0656051636],"type":"Point"}
}