{
  "type": "Feature",
  "properties": {
    "iso:country":"ES",
    "sg:address":"Calle de Puerta De Murcia, 5",
    "sg:city":"Cartagena",
    "sg:orig_category":"Trajes Y Adornos De Boda (confecci\u00d3n, Al Por Menor)",
    "sg:phone":"+34 968 50 15 73",
    "sg:postcode":"30201",
    "sg:province":"Murcia",
    "wof:name":"Comercial Ferrer S.l.",
    "wof:placetype":"venue"
},
  "geometry": {"coordinates":[-0.9869830012,37.6021957397],"type":"Point"}
}