{
  "type": "Feature",
  "properties": {
    "iso:country":"ES",
    "sg:address":"Plaz Parejas (de), 11",
    "sg:city":"Aranjuez",
    "sg:orig_category":"Hospitales",
    "sg:phone":"+34 918 75 42 01",
    "sg:postcode":"28300",
    "sg:province":"Madrid",
    "wof:name":"Auna Telecomunicaciones S.a.u.",
    "wof:placetype":"venue"
},
  "geometry": {"coordinates":[-3.6073770523,40.0354156494],"type":"Point"}
}