{
  "type": "Feature",
  "properties": {
    "addr:full":"Calle de Camara La, 52 Aviles Asturias 33401",
    "addr:housenumber":"52",
    "addr:postcode":"33401",
    "addr:street":"Calle De Camara La",
    "iso:country":"ES",
    "sg:address":"Calle de Camara La, 52",
    "sg:city":"Aviles",
    "sg:orig_category":"M\u00c9dicos: Cardiolog\u00cda Y Afecciones Cardiovasculares",
    "sg:phone":"+34 985 56 69 82",
    "sg:postcode":"33401",
    "sg:province":"Asturias",
    "wof:name":"Casares Garcia Gerardo",
    "wof:placetype":"venue"
},
  "geometry": {"coordinates":[-5.9254670143,43.5602760315],"type":"Point"}
}