{
  "type": "Feature",
  "properties": {
    "iso:country":"ES",
    "sg:address":"Calle de Cuenca, 3",
    "sg:city":"Parla",
    "sg:orig_category":"Ropa Para Caballeros (al Por Menor)",
    "sg:phone":"+34 916 98 06 25",
    "sg:postcode":"28980",
    "sg:province":"Madrid",
    "wof:name":"Jose Luis Y Fernando Garcia Sancho Cdad",
    "wof:placetype":"venue"
},
  "geometry": {"coordinates":[-3.7653665543,40.2401008606],"type":"Point"}
}