{
  "type": "Feature",
  "properties": {
    "iso:country":"ES",
    "sg:address":"Calle de Maestro Aguilar, 21",
    "sg:city":"Valencia",
    "sg:orig_category":"Electrodom\u00c9sticos (al Por Menor)",
    "sg:phone":"+34 963 33 01 90",
    "sg:postcode":"46006",
    "sg:province":"Valencia",
    "sg:website":"www.microhogar.com",
    "wof:name":"Dise\u00d1o Y Decoracion Naturhogar S.l",
    "wof:placetype":"venue"
},
  "geometry": {"coordinates":[-0.3694880009,39.4605178833],"type":"Point"}
}