{
  "type": "Feature",
  "properties": {
    "iso:country":"ES",
    "sg:address":"Calle de Hernan Cortes, 9",
    "sg:city":"Elda",
    "sg:orig_category":"Venta, Instalaci\u00d3n De Calefacci\u00d3n",
    "sg:phone":"+34 965 38 47 41",
    "sg:postcode":"03600",
    "sg:province":"Alicante",
    "wof:name":"Servicios De Instalacion Y Mantenimiento De Gas Frio Y Calor S.l.",
    "wof:placetype":"venue"
},
  "geometry": {"coordinates":[-0.791212976,38.4733505249],"type":"Point"}
}