{
  "type": "Feature",
  "properties": {
    "iso:country":"ES",
    "sg:address":"Carr Colon, 107",
    "sg:city":"Burjassot",
    "sg:orig_category":"Formaci\u00d3n Continuada (variada)",
    "sg:phone":"+34 963 64 24 34",
    "sg:postcode":"46100",
    "sg:province":"Valencia",
    "wof:name":"Burgos Montaner Bego\u00f1a Maria",
    "wof:placetype":"venue"
},
  "geometry": {"coordinates":[-0.414842993,39.5126686096],"type":"Point"}
}