{
  "type": "Feature",
  "properties": {
    "iso:country":"ES",
    "sg:address":"Mera, S/n",
    "sg:city":"Mera",
    "sg:orig_category":"Sindicatos De Trabajadores",
    "sg:phone":"+34 986 59 20 38",
    "sg:postcode":"36540",
    "sg:province":"Pontevedra",
    "wof:name":"Consorcio De Bomberos Comarcas Del Deza Y Tabeiros Montes",
    "wof:placetype":"venue"
},
  "geometry": {"coordinates":[-8.2418241501,42.6958084106],"type":"Point"}
}