{
  "type": "Feature",
  "properties": {
    "iso:country":"ES",
    "sg:address":"Calle de Ribera, 18",
    "sg:city":"Valencia",
    "sg:orig_category":"Abogados",
    "sg:phone":"+34 963 10 69 03",
    "sg:postcode":"46002",
    "sg:province":"Valencia",
    "wof:name":"Tantum Consultores S.l.",
    "wof:placetype":"venue"
},
  "geometry": {"coordinates":[-0.3759632111,39.4674720764],"type":"Point"}
}