{
  "type": "Feature",
  "properties": {
    "addr:full":"Avgd Concordia, 7 Aldaia Valencia 46960",
    "addr:housenumber":"7",
    "addr:postcode":"46960",
    "addr:street":"Concordia",
    "iso:country":"ES",
    "sg:address":"Avgd Concordia, 7",
    "sg:city":"Aldaia",
    "sg:orig_category":"Complementos De Vestir (al Por Menor)",
    "sg:phone":"+34 961 50 08 68",
    "sg:postcode":"46960",
    "sg:province":"Valencia",
    "wof:name":"Lorente Clavijo Evelia",
    "wof:placetype":"venue"
},
  "geometry": {"coordinates":[-0.460878998,39.4649238586],"type":"Point"}
}