{
  "type": "Feature",
  "properties": {
    "addr:full":"Calle de Vicente Blasco Iba\u00d1ez, 9 Elda Alicante 03600",
    "addr:housenumber":"9",
    "addr:postcode":"03600",
    "addr:street":"Calle De Vicente Blasco Iban\u0303Ez",
    "iso:country":"ES",
    "sg:address":"Calle de Vicente Blasco Iba\u00d1ez, 9",
    "sg:city":"Elda",
    "sg:orig_category":"Decoraci\u00d3n: Instalaci\u00d3n Y Talleres",
    "sg:phone":"+34 965 38 26 39",
    "sg:postcode":"03600",
    "sg:province":"Alicante",
    "wof:name":"Decoraciones Josema S.l.",
    "wof:placetype":"venue"
},
  "geometry": {"coordinates":[-0.7875109911,38.4793548584],"type":"Point"}
}