{
  "type": "Feature",
  "properties": {
    "addr:full":"Gregorio Ameztoy Kalea, 3 Irura Guip\u00f9zcoa 20271",
    "addr:housenumber":"3",
    "addr:postcode":"20271",
    "addr:street":"Gregorio Ameztoy Kalea;Guipu\u0300Zcoa",
    "iso:country":"ES",
    "sg:address":"Gregorio Ameztoy Kalea, 3",
    "sg:city":"Irura",
    "sg:orig_category":"Supermercados Y Hipermercados",
    "sg:phone":"+34 943 69 64 17",
    "sg:postcode":"20271",
    "sg:province":"Guip\u00f9zcoa",
    "wof:name":"Eaghavian  Ali Reza",
    "wof:placetype":"venue"
},
  "geometry": {"coordinates":[-2.0695099831,43.1665115356],"type":"Point"}
}