{
  "type": "Feature",
  "properties": {
    "iso:country":"ES",
    "sg:address":"Avda Castilla La Mancha, 30",
    "sg:city":"Toledo",
    "sg:orig_category":"Asesor\u00cda Sobre Comunicaci\u00d3n De Empresas",
    "sg:phone":"+34 925 25 22 75",
    "sg:postcode":"45003",
    "sg:province":"Toledo",
    "wof:name":"Caba\u00f1as Rodriguez Angel Luis",
    "wof:placetype":"venue"
},
  "geometry": {"coordinates":[-4.0196199417,39.8705368042],"type":"Point"}
}