{
  "type": "Feature",
  "properties": {
    "iso:country":"ES",
    "sg:address":"Pla\u00c7 Artrutx, 8",
    "sg:city":"Ciutadella Menorca",
    "sg:orig_category":"Loter\u00cda Y T\u00d3mbola",
    "sg:phone":"+34 971 38 30 82",
    "sg:postcode":"07760",
    "sg:province":"Islas Baleares",
    "wof:name":"Pons Pons Juana",
    "wof:placetype":"venue"
},
  "geometry": {"coordinates":[3.8416149616,40.0027542114],"type":"Point"}
}