{
  "type": "Feature",
  "properties": {
    "iso:country":"ES",
    "sg:address":"Avda Pilar (del), 3",
    "sg:city":"Calahorra",
    "sg:orig_category":"Promotores Constructores",
    "sg:phone":"+34 941 14 65 92",
    "sg:postcode":"26500",
    "sg:province":"La Rioja",
    "wof:name":"Aransa Europa S.l.",
    "wof:placetype":"venue"
},
  "geometry": {"coordinates":[-1.9654257298,42.304813385],"type":"Point"}
}