{
  "type": "Feature",
  "properties": {
    "iso:country":"ES",
    "sg:address":"Calle de Serrano, 17",
    "sg:city":"S. Pedro Pinatar",
    "sg:orig_category":"Postigos, Persianas Y Celos\u00cdas",
    "sg:phone":"+34 968 18 22 61",
    "sg:postcode":"30740",
    "sg:province":"Murcia",
    "wof:name":"Andres Escudero Maria Dolores",
    "wof:placetype":"venue"
},
  "geometry": {"coordinates":[-0.7913560867,37.833190918],"type":"Point"}
}