{
  "type": "Feature",
  "properties": {
    "iso:country":"ES",
    "sg:address":"Calle de Aries, 7",
    "sg:city":"Alacant",
    "sg:orig_category":"Procuradores",
    "sg:phone":"+34 965 11 47 21",
    "sg:postcode":"03007",
    "sg:province":"Alicante",
    "wof:name":"Lopez Pastor Eva Maria",
    "wof:placetype":"venue"
},
  "geometry": {"coordinates":[-0.5087761283,38.3438148499],"type":"Point"}
}