{
  "type": "Feature",
  "properties": {
    "addr:full":"Rua Maior, 8 Verin Ourense 32600",
    "addr:housenumber":"8",
    "addr:postcode":"32600",
    "addr:street":"Rua Maior",
    "iso:country":"ES",
    "sg:address":"Rua Maior, 8",
    "sg:city":"Verin",
    "sg:orig_category":"Fabricaci\u00d3n, Venta De Cuadros, Accesorios Para Enmarcar",
    "sg:phone":"+34 988 41 30 45",
    "sg:postcode":"32600",
    "sg:province":"Ourense",
    "wof:name":"Gonzalez Tarrio Antonio",
    "wof:placetype":"venue"
},
  "geometry": {"coordinates":[-7.4381890297,41.9412536621],"type":"Point"}
}