{
  "type": "Feature",
  "properties": {
    "iso:country":"ES",
    "sg:address":"Calle de Alonso Alvarado, 43",
    "sg:city":"Palmas De Gran Canaria",
    "sg:orig_category":"Asesor\u00cda De Formaci\u00d3n Y Gesti\u00d3n De Personal",
    "sg:phone":"+34 928 37 18 51",
    "sg:postcode":"35003",
    "sg:province":"Las Palmas",
    "wof:name":"Santana Armas Antonia",
    "wof:placetype":"venue"
},
  "geometry": {"coordinates":[-15.4181890488,28.1114902496],"type":"Point"}
}