{
  "type": "Feature",
  "properties": {
    "addr:full":"Rua Colon, 27 Vigo Pontevedra 36201",
    "addr:housenumber":"27",
    "addr:postcode":"36201",
    "addr:street":"Rua Colon",
    "iso:country":"ES",
    "sg:address":"Rua Colon, 27",
    "sg:city":"Vigo",
    "sg:orig_category":"Cajas De Ahorro",
    "sg:phone":"+34 986 44 34 71",
    "sg:postcode":"36201",
    "sg:province":"Pontevedra",
    "wof:name":"Caixa D'estalvis De Catalunya",
    "wof:placetype":"venue"
},
  "geometry": {"coordinates":[-8.7200269699,42.2365913391],"type":"Point"}
}