{
  "type": "Feature",
  "properties": {
    "addr:full":"Calle de Elizalde, 21 Sarria \u00c1lava 01139",
    "addr:housenumber":"21",
    "addr:postcode":"01139",
    "addr:street":"Calle De Elizalde",
    "iso:country":"ES",
    "sg:address":"Calle de Elizalde, 21",
    "sg:city":"Sarria",
    "sg:orig_category":"Restaurantes",
    "sg:phone":"+34 945 43 02 12",
    "sg:postcode":"01139",
    "sg:province":"\u00c1lava",
    "wof:name":"Uriarte Ircio Miguel Angel",
    "wof:placetype":"venue"
},
  "geometry": {"coordinates":[-2.8245079517,42.9668655396],"type":"Point"}
}