{
  "type": "Feature",
  "properties": {
    "iso:country":"ES",
    "sg:address":"Calle de Rio Seijo, 1",
    "sg:city":"Cari\u00f1o",
    "sg:orig_category":"Molduras, Junquillos, Listones Y Molduras Perforadas",
    "sg:phone":"+34 981 40 59 52",
    "sg:postcode":"15360",
    "sg:province":"La Coru\u00f1a",
    "wof:name":"Rodriguez Ya\u00f1ez Elias",
    "wof:placetype":"venue"
},
  "geometry": {"coordinates":[-7.873652935,43.738193512],"type":"Point"}
}