{
  "type": "Feature",
  "properties": {
    "addr:full":"Calle de Sepulveda, 3 Madrid Madrid 28011",
    "addr:housenumber":"3",
    "addr:postcode":"28011",
    "addr:street":"Calle De Sepulveda",
    "iso:country":"ES",
    "sg:address":"Calle de Sepulveda, 3",
    "sg:city":"Madrid",
    "sg:orig_category":"Centros De Coordinaci\u00d3n",
    "sg:phone":"+34 914 79 29 14",
    "sg:postcode":"28011",
    "sg:province":"Madrid",
    "wof:name":"2000 Elyotros S.l.",
    "wof:placetype":"venue"
},
  "geometry": {"coordinates":[-3.741192,40.404362],"type":"Point"}
}