{
  "type": "Feature",
  "properties": {
    "iso:country":"ES",
    "sg:address":"Rbla Pompeu Fabra, 103",
    "sg:city":"Gava",
    "sg:orig_category":"Ropa De Trabajo Y Profesionales (fabricaci\u00d3n, Al Por Mayor)",
    "sg:phone":"+34 936 38 29 17",
    "sg:postcode":"08850",
    "sg:province":"Barcelona",
    "wof:name":"Diegomoda S.l",
    "wof:placetype":"venue"
},
  "geometry": {"coordinates":[1.9997340441,41.3104324341],"type":"Point"}
}