{
  "type": "Feature",
  "properties": {
    "addr:full":"Calle de Panchito Hernandez, 10 Arucas Las Palmas 35400",
    "addr:housenumber":"10",
    "addr:postcode":"35400",
    "addr:street":"Calle De Panchito Hernandez",
    "iso:country":"ES",
    "sg:address":"Calle de Panchito Hernandez, 10",
    "sg:city":"Arucas",
    "sg:orig_category":"Asesor\u00cda De Formaci\u00d3n Y Gesti\u00d3n De Personal",
    "sg:phone":"+34 928 60 25 32",
    "sg:postcode":"35400",
    "sg:province":"Las Palmas",
    "wof:name":"Rodriguez Marrero Antonia Maria",
    "wof:placetype":"venue"
},
  "geometry": {"coordinates":[-15.5256662369,28.1186523438],"type":"Point"}
}