{
  "type": "Feature",
  "properties": {
    "addr:full":"Plata, S/n Quilo\u00f1o Asturias 33459",
    "addr:postcode":"33459",
    "addr:street":"Plata S / N Quilon\u0303O Asturias",
    "iso:country":"ES",
    "sg:address":"Plata, S/n",
    "sg:city":"Quilo\u00f1o",
    "sg:orig_category":"Discapacitados",
    "sg:phone":"+34 985 53 27 33",
    "sg:postcode":"33459",
    "sg:province":"Asturias",
    "wof:name":"Principado De Asturias",
    "wof:placetype":"venue"
},
  "geometry": {"coordinates":[-6.0285987854,43.551486969],"type":"Point"}
}