{
  "type": "Feature",
  "properties": {
    "iso:country":"ES",
    "sg:address":"Moll Catalunya, S/n",
    "sg:city":"Barcelona",
    "sg:orig_category":"Navegaci\u00d3n (equipos Fluviales)",
    "sg:phone":"+34 933 17 80 45",
    "sg:postcode":"08039",
    "sg:province":"Barcelona",
    "wof:name":"Naviera Pinillos S.a.",
    "wof:placetype":"venue"
},
  "geometry": {"coordinates":[2.1629400253,41.3915786743],"type":"Point"}
}