{
  "type": "Feature",
  "properties": {
    "iso:country":"ES",
    "sg:address":"Altamira Auzoa, 5",
    "sg:city":"Azkoitia",
    "sg:orig_category":"Grabados Y Decoraci\u00d3n De Metales",
    "sg:phone":"+34 943 85 70 27",
    "sg:postcode":"20720",
    "sg:province":"Guip\u00f9zcoa",
    "wof:name":"Galda Beitia S.l.",
    "wof:placetype":"venue"
},
  "geometry": {"coordinates":[-2.309098959,43.172668457],"type":"Point"}
}