{
  "type": "Feature",
  "properties": {
    "addr:full":"Calle de Arriotxe, 8 San Vicente De Barakaldo Vizcaya 48903",
    "addr:housenumber":"8",
    "addr:postcode":"48903",
    "addr:street":"Calle De Arriotxe",
    "iso:country":"ES",
    "sg:address":"Calle de Arriotxe, 8",
    "sg:city":"San Vicente De Barakaldo",
    "sg:orig_category":"Vinos Y Licores (venta Al Por Menor)",
    "sg:phone":"+34 944 99 29 81",
    "sg:postcode":"48903",
    "sg:province":"Vizcaya",
    "wof:name":"Arrinda Garate Maria Begona",
    "wof:placetype":"venue"
},
  "geometry": {"coordinates":[-2.9793112278,43.2901306152],"type":"Point"}
}