{
  "type": "Feature",
  "properties": {
    "iso:country":"ES",
    "sg:address":"Carrer de Joan Massanet I Mo, 3",
    "sg:city":"Palma",
    "sg:orig_category":"M\u00c9dicos: Evaluaci\u00d3n Y Tratamiento Del Dolor",
    "sg:phone":"+34 971 20 52 31",
    "sg:postcode":"07010",
    "sg:province":"Islas Baleares",
    "wof:name":"Mustafa  Murad",
    "wof:placetype":"venue"
},
  "geometry": {"coordinates":[2.6486001015,39.5836257935],"type":"Point"}
}