{
  "type": "Feature",
  "properties": {
    "addr:full":"Calle de Toledillo, 7 Villacarrillo Ja\u00e9n 23300",
    "addr:housenumber":"7",
    "addr:postcode":"23300",
    "addr:street":"Calle De Toledillo;Jae\u0301N",
    "iso:country":"ES",
    "sg:address":"Calle de Toledillo, 7",
    "sg:city":"Villacarrillo",
    "sg:orig_category":"Ropa Para Se\u00d1oras Y Caballeros (al Por Menor)",
    "sg:phone":"+34 953 44 22 56",
    "sg:postcode":"23300",
    "sg:province":"Ja\u00e9n",
    "wof:name":"Carrillo Aranda Miguel Angel",
    "wof:placetype":"venue"
},
  "geometry": {"coordinates":[-3.0829210281,38.1152687073],"type":"Point"}
}