{
  "type": "Feature",
  "properties": {
    "addr:full":"Avda Murcia, 79 Ramos Murcia 30589",
    "addr:housenumber":"79",
    "addr:postcode":"30589",
    "addr:street":"Avda Murcia",
    "iso:country":"ES",
    "sg:address":"Avda Murcia, 79",
    "sg:city":"Ramos",
    "sg:orig_category":"Charcuter\u00cdas (al Por Mayor)",
    "sg:phone":"+34 968 82 32 65",
    "sg:postcode":"30589",
    "sg:province":"Murcia",
    "wof:name":"Industrias Carnicas Arce S.l.",
    "wof:placetype":"venue"
},
  "geometry": {"coordinates":[-1.0354950428,37.9929695129],"type":"Point"}
}