{
  "type": "Feature",
  "properties": {
    "iso:country":"ES",
    "sg:address":"Calle de Doctor Fernando Primo De Rivera, 7",
    "sg:city":"Madrid",
    "sg:orig_category":"\u00d3ptica: Instrumentos (fabricaci\u00d3n)",
    "sg:phone":"+34 914 78 85 05",
    "sg:postcode":"28053",
    "sg:province":"Madrid",
    "wof:name":"Optica Numancia",
    "wof:placetype":"venue"
},
  "geometry": {"coordinates":[-3.6656067371,40.3959388733],"type":"Point"}
}