{
  "type": "Feature",
  "properties": {
    "iso:country":"ES",
    "sg:address":"Carrer de Corsega, 239",
    "sg:city":"Barcelona",
    "sg:orig_category":"Asesor\u00cda Fiscal Y Jur\u00cddica",
    "sg:phone":"+34 934 10 95 55",
    "sg:postcode":"08036",
    "sg:province":"Barcelona",
    "wof:name":"Vila Gimenez Juan",
    "wof:placetype":"venue"
},
  "geometry": {"coordinates":[2.1535670757,41.3923797607],"type":"Point"}
}