{
  "type": "Feature",
  "properties": {
    "iso:country":"ES",
    "sg:address":"Calle de Enmedio, 40",
    "sg:city":"Torrejon Ardoz",
    "sg:orig_category":"Fabricaci\u00d3n, Venta De Cuadros, Accesorios Para Enmarcar",
    "sg:phone":"+34 916 77 26 40",
    "sg:postcode":"28850",
    "sg:province":"Madrid",
    "wof:name":"Robles Hernandez Rosario",
    "wof:placetype":"venue"
},
  "geometry": {"coordinates":[-3.4790840149,40.456111908],"type":"Point"}
}