{
  "type": "Feature",
  "properties": {
    "iso:country":"ES",
    "sg:address":"Avda Principes De Espa\u00d1a, 6",
    "sg:city":"Medano",
    "sg:orig_category":"Peluquer\u00cdas, Peluquer\u00cda Mixta",
    "sg:phone":"+34 922 17 85 57",
    "sg:postcode":"38612",
    "sg:province":"Santa Cruz De Tenerife",
    "wof:name":"Lopez Leon Rocio",
    "wof:placetype":"venue"
},
  "geometry": {"coordinates":[-16.5385055542,28.0454692841],"type":"Point"}
}