{
  "type": "Feature",
  "properties": {
    "addr:full":"Baltar, 62 Baltar Pontevedra 36979",
    "addr:housenumber":"62",
    "addr:postcode":"36979",
    "addr:street":"Baltar",
    "iso:country":"ES",
    "sg:address":"Baltar, 62",
    "sg:city":"Baltar",
    "sg:orig_category":"Inform\u00c1tica, Ofim\u00c1tica (estudios, Asesor\u00cda, Ingenier\u00cda, Formaci\u00d3n)",
    "sg:phone":"+34 986 72 08 78",
    "sg:postcode":"36979",
    "sg:province":"Pontevedra",
    "wof:name":"Lema Deza Maria Del Carmen",
    "wof:placetype":"venue"
},
  "geometry": {"coordinates":[-8.8151941299,42.4157600403],"type":"Point"}
}