{
  "type": "Feature",
  "properties": {
    "iso:country":"ES",
    "sg:address":"Carrer de Sant Pere Mes Baix, 36",
    "sg:city":"Barcelona",
    "sg:orig_category":"Panader\u00cdas, Panader\u00cdas",
    "sg:phone":"+34 933 19 00 99",
    "sg:postcode":"08003",
    "sg:province":"Barcelona",
    "wof:name":"Sanahuja Recasens Juan",
    "wof:placetype":"venue"
},
  "geometry": {"coordinates":[2.1777040958,41.3872528076],"type":"Point"}
}