{
  "type": "Feature",
  "properties": {
    "addr:full":"Avda San Miguel, S/n San Miguel De Meruelo Cantabria 39192",
    "addr:housenumber":"s / n",
    "addr:postcode":"39192",
    "addr:street":"Avda San Miguel",
    "iso:country":"ES",
    "sg:address":"Avda San Miguel, S/n",
    "sg:city":"San Miguel De Meruelo",
    "sg:orig_category":"Supermercados Y Hipermercados",
    "sg:phone":"+34 942 63 72 58",
    "sg:postcode":"39192",
    "sg:province":"Cantabria",
    "wof:name":"Villar Melero Maria Angeles",
    "wof:placetype":"venue"
},
  "geometry": {"coordinates":[-3.5727388859,43.4541931152],"type":"Point"}
}