{
  "type": "Feature",
  "properties": {
    "addr:full":"Calle de Sorolla, 11 Pilas Sevilla 41840",
    "addr:housenumber":"11",
    "addr:postcode":"41840",
    "addr:street":"Calle De Sorolla",
    "iso:country":"ES",
    "sg:address":"Calle de Sorolla, 11",
    "sg:city":"Pilas",
    "sg:orig_category":"Chapister\u00cda",
    "sg:phone":"+34 955 75 22 56",
    "sg:postcode":"41840",
    "sg:province":"Sevilla",
    "wof:name":"Colimar Chapa Y Pintura S.l.",
    "wof:placetype":"venue"
},
  "geometry": {"coordinates":[-6.2953782082,37.3001480103],"type":"Point"}
}