{
  "type": "Feature",
  "properties": {
    "addr:full":"Carr Corbella, (de La), 29 Carlet Valencia 46240",
    "addr:housenumber":"29",
    "addr:postcode":"46240",
    "addr:street":"Carr Corbella De La",
    "iso:country":"ES",
    "sg:address":"Carr Corbella, (de La), 29",
    "sg:city":"Carlet",
    "sg:orig_category":"Inform\u00c1tica: Material Y Suministros",
    "sg:phone":"+34 962 53 30 40",
    "sg:postcode":"46240",
    "sg:province":"Valencia",
    "wof:name":"Computadores Y Serveis Valencians S.l.",
    "wof:placetype":"venue"
},
  "geometry": {"coordinates":[-0.522834003,39.2264289856],"type":"Point"}
}