{
  "type": "Feature",
  "properties": {
    "addr:full":"Calle de Arroyo De San Lorenzo, 19 Cordoba C\u00f3rdoba 14002",
    "addr:housenumber":"19",
    "addr:postcode":"14002",
    "addr:street":"Calle De Arroyo De San Lorenzo;Co\u0301Rdoba",
    "iso:country":"ES",
    "sg:address":"Calle de Arroyo De San Lorenzo, 19",
    "sg:city":"Cordoba",
    "sg:orig_category":"Bazares, Art\u00cdculos De Limpieza Y De Cocina (al Por Menor)",
    "sg:phone":"+34 957 48 38 45",
    "sg:postcode":"14002",
    "sg:province":"C\u00f3rdoba",
    "wof:name":"Bazar San Lorenzo S.c.",
    "wof:placetype":"venue"
},
  "geometry": {"coordinates":[-4.7687768936,37.8873062134],"type":"Point"}
}