{
  "type": "Feature",
  "properties": {
    "iso:country":"ES",
    "sg:address":"Calle de Clemente Jordan, 83",
    "sg:city":"Puente De Arucas",
    "sg:orig_category":"Asesor\u00cda Sobre Comunicaci\u00d3n De Empresas",
    "sg:phone":"+34 928 63 35 37",
    "sg:postcode":"35400",
    "sg:province":"Las Palmas",
    "wof:name":"Proassa",
    "wof:placetype":"venue"
},
  "geometry": {"coordinates":[-15.5134210587,28.1121387482],"type":"Point"}
}