{
  "type": "Feature",
  "properties": {
    "iso:country":"ES",
    "sg:address":"Ctra Canillas, 53",
    "sg:city":"Madrid",
    "sg:orig_category":"Suministros Para Hoteles",
    "sg:phone":"+34 917 59 71 48",
    "sg:postcode":"28043",
    "sg:province":"Madrid",
    "wof:name":"Albie S.a.",
    "wof:placetype":"venue"
},
  "geometry": {"coordinates":[-3.6441745758,40.4642105103],"type":"Point"}
}