{
  "type": "Feature",
  "properties": {
    "addr:full":"Carrer de Sant Domenec, 1 Pego Alicante 03780",
    "addr:housenumber":"1",
    "addr:postcode":"03780",
    "addr:street":"Carrer De Sant Domenec",
    "iso:country":"ES",
    "sg:address":"Carrer de Sant Domenec, 1",
    "sg:city":"Pego",
    "sg:orig_category":"Iglesia Cat\u00d3lica",
    "sg:phone":"+34 965 57 03 67",
    "sg:postcode":"03780",
    "sg:province":"Alicante",
    "wof:name":"Parroquia De Nuestra Se\u00f1ora De La Asuncion",
    "wof:placetype":"venue"
},
  "geometry": {"coordinates":[-0.1178769991,38.8419723511],"type":"Point"}
}