{
  "type": "Feature",
  "properties": {
    "iso:country":"ES",
    "sg:address":"Calle de Cervantes, 17",
    "sg:city":"Albal",
    "sg:orig_category":"Semiller\u00cdas",
    "sg:phone":"+34 961 26 02 51",
    "sg:postcode":"46470",
    "sg:province":"Valencia",
    "wof:name":"Ricart Vila Miguel",
    "wof:placetype":"venue"
},
  "geometry": {"coordinates":[-0.4170235097,39.396522522],"type":"Point"}
}