{
  "type": "Feature",
  "properties": {
    "addr:full":"Avda Malvarrosa, 2 Valencia Valencia 46011",
    "addr:housenumber":"2",
    "addr:postcode":"46011",
    "addr:street":"Avda Malvarrosa",
    "iso:country":"ES",
    "sg:address":"Avda Malvarrosa, 2",
    "sg:city":"Valencia",
    "sg:orig_category":"Centros De Educaci\u00d3n Especial",
    "sg:phone":"+34 963 72 30 43",
    "sg:postcode":"46011",
    "sg:province":"Valencia",
    "wof:name":"Generalitat Valenciana",
    "wof:placetype":"venue"
},
  "geometry": {"coordinates":[-0.327493012,39.475227356],"type":"Point"}
}