{
  "type": "Feature",
  "properties": {
    "iso:country":"ES",
    "sg:address":"Fermin Calbeton Kalea, 23",
    "sg:city":"Eibar",
    "sg:orig_category":"Plomeros",
    "sg:phone":"+34 943 12 07 91",
    "sg:postcode":"20600",
    "sg:province":"Guip\u00f9zcoa",
    "wof:name":"Leonardo Azpiri S.a.",
    "wof:placetype":"venue"
},
  "geometry": {"coordinates":[-2.4704298973,43.1852684021],"type":"Point"}
}