{
  "type": "Feature",
  "properties": {
    "iso:country":"ES",
    "sg:address":"Urreta Bailara, 11",
    "sg:city":"Albiztur",
    "sg:orig_category":"Maquinaria Para Industrias Diversas",
    "sg:phone":"+34 943 69 40 55",
    "sg:postcode":"20495",
    "sg:province":"Guip\u00f9zcoa",
    "wof:name":"Bestebat S.l.",
    "wof:placetype":"venue"
},
  "geometry": {"coordinates":[-2.0976140499,43.0998916626],"type":"Point"}
}