{
  "type": "Feature",
  "properties": {
    "iso:country":"ES",
    "sg:address":"Calle de Alfareros, 23",
    "sg:city":"Burgos",
    "sg:orig_category":"Empresas De Pintura Y Revestimientos",
    "sg:phone":"+34 947 26 89 51",
    "sg:postcode":"09001",
    "sg:province":"Burgos",
    "wof:name":"Santana Serna Jesus",
    "wof:placetype":"venue"
},
  "geometry": {"coordinates":[-3.7020990849,42.3310966492],"type":"Point"}
}