{
  "type": "Feature",
  "properties": {
    "iso:country":"ES",
    "sg:address":"Carrer de Cesar (del), 2",
    "sg:city":"Salou",
    "sg:orig_category":"Inmobiliaria (agencias)",
    "sg:phone":"+34 977 35 30 33",
    "sg:postcode":"43840",
    "sg:province":"Tarragona",
    "wof:name":"Gay De Antonio Laura",
    "wof:placetype":"venue"
},
  "geometry": {"coordinates":[1.1349600554,41.0786018372],"type":"Point"}
}