{
  "type": "Feature",
  "properties": {
    "addr:full":"Carrer de Ample De La Merce, 15 Palma Islas Baleares 07002",
    "addr:housenumber":"15",
    "addr:postcode":"07002",
    "addr:street":"Carrer De Ample De La Merce",
    "iso:country":"ES",
    "sg:address":"Carrer de Ample De La Merce, 15",
    "sg:city":"Palma",
    "sg:orig_category":"Tintorer\u00cdas, Limpieza En Seco",
    "sg:phone":"+34 971 71 55 85",
    "sg:postcode":"07002",
    "sg:province":"Islas Baleares",
    "wof:name":"Bibiloni Guijarro Miguel",
    "wof:placetype":"venue"
},
  "geometry": {"coordinates":[2.654599905,39.5719985962],"type":"Point"}
}