{
  "type": "Feature",
  "properties": {
    "iso:country":"ES",
    "sg:address":"Afueras, S/n",
    "sg:city":"Berzocana",
    "sg:orig_category":"Agricultores, Agricultores",
    "sg:phone":"+34 927 19 50 18",
    "sg:postcode":"10129",
    "sg:province":"C\u00e1ceres",
    "wof:name":"Salinas Lucas Jose Manuel",
    "wof:placetype":"venue"
},
  "geometry": {"coordinates":[-5.4616341591,39.4363441467],"type":"Point"}
}