{
  "type": "Feature",
  "properties": {
    "addr:full":"Carr Xunta De Montes, S/n Betera Valencia 46117",
    "addr:housenumber":"s",
    "addr:postcode":"46117",
    "addr:street":"Carr Xunta De Montes;/ N",
    "iso:country":"ES",
    "sg:address":"Carr Xunta De Montes, S/n",
    "sg:city":"Betera",
    "sg:orig_category":"Promotores Constructores",
    "sg:phone":"+34 961 69 06 08",
    "sg:postcode":"46117",
    "sg:province":"Valencia",
    "wof:name":"Vp Rodrigo S.l",
    "wof:placetype":"venue"
},
  "geometry": {"coordinates":[-0.4639225006,39.5889701843],"type":"Point"}
}