{
  "type": "Feature",
  "properties": {
    "iso:country":"ES",
    "sg:address":"Avda Coll, 1",
    "sg:city":"Arrecife",
    "sg:orig_category":"Inform\u00c1tica (estudios, Servicios, Asesor\u00cda, Formaci\u00d3n)",
    "sg:phone":"+34 928 81 71 60",
    "sg:postcode":"35500",
    "sg:province":"Las Palmas",
    "wof:name":"Informatica Lanzarote S. L.",
    "wof:placetype":"venue"
},
  "geometry": {"coordinates":[-13.5481643677,28.958568573],"type":"Point"}
}