{
  "type": "Feature",
  "properties": {
    "addr:full":"Calle de Aguamarga, 6 Puerto Valencia 46520",
    "addr:housenumber":"6",
    "addr:postcode":"46520",
    "addr:street":"Calle De Aguamarga",
    "iso:country":"ES",
    "sg:address":"Calle de Aguamarga, 6",
    "sg:city":"Puerto",
    "sg:orig_category":"Pr\u00c9stamos Personales E Hipotecarios",
    "sg:phone":"+34 962 67 31 10",
    "sg:postcode":"46520",
    "sg:province":"Valencia",
    "wof:name":"Colegio Nacional De Registradores De La",
    "wof:placetype":"venue"
},
  "geometry": {"coordinates":[-0.2266263068,39.6684417725],"type":"Point"}
}