{
  "type": "Feature",
  "properties": {
    "addr:full":"Calle de Ca\u00d1averal, 24 Madrid Madrid 28029",
    "addr:housenumber":"24",
    "addr:postcode":"madrid;28029",
    "addr:street":"Calle De Can\u0303Averal",
    "iso:country":"ES",
    "sg:address":"Calle de Ca\u00d1averal, 24",
    "sg:city":"Madrid",
    "sg:orig_category":"Farmacias",
    "sg:phone":"+34 913 15 20 35",
    "sg:postcode":"28029",
    "sg:province":"Madrid",
    "wof:name":"Pe\u00f1a Hernando Maria Reyes",
    "wof:placetype":"venue"
},
  "geometry": {"coordinates":[-3.6941740513,40.4673690796],"type":"Point"}
}