{
  "type": "Feature",
  "properties": {
    "iso:country":"ES",
    "sg:address":"Calle de Asensi, 29",
    "sg:city":"Castellon",
    "sg:orig_category":"Abogados",
    "sg:phone":"+34 964 26 00 52",
    "sg:postcode":"12002",
    "sg:province":"Castell\u00f3n",
    "wof:name":"Monferrer Y Marin Bufete De Abogados Sociedad Civil",
    "wof:placetype":"venue"
},
  "geometry": {"coordinates":[-0.0358934999,39.9825325012],"type":"Point"}
}