{
  "type": "Feature",
  "properties": {
    "iso:country":"ES",
    "sg:address":"Calle de Mayor, 65",
    "sg:city":"Pozoblanco",
    "sg:orig_category":"Asesor\u00cda Sobre Comunicaci\u00d3n De Empresas",
    "sg:phone":"+34 957 77 26 55",
    "sg:postcode":"14400",
    "sg:province":"C\u00f3rdoba",
    "wof:name":"Asevap Asesores Y Consultores S.l.",
    "wof:placetype":"venue"
},
  "geometry": {"coordinates":[-4.8497657776,38.3808822632],"type":"Point"}
}