{
  "type": "Feature",
  "properties": {
    "addr:full":"Calle de Candelaria De Leon, 10 Palmas De Gran Canaria Las Palmas 35016",
    "addr:postcode":"35016",
    "addr:street":"Calle De Candelaria De Leon 10",
    "iso:country":"ES",
    "sg:address":"Calle de Candelaria De Leon, 10",
    "sg:city":"Palmas De Gran Canaria",
    "sg:orig_category":"Escultores, Estatuarios E Imagineros",
    "sg:phone":"+34 928 31 66 71",
    "sg:postcode":"35016",
    "sg:province":"Las Palmas",
    "wof:name":"Vargas Jorge Santiago",
    "wof:placetype":"venue"
},
  "geometry": {"coordinates":[-15.4190616608,28.0700187683],"type":"Point"}
}