{
  "type": "Feature",
  "properties": {
    "addr:full":"Ctra Badajoz, S/n Jerez De Los Caballeros Badajoz 06380",
    "addr:housenumber":"s / n",
    "addr:postcode":"06380",
    "addr:street":"Ctra Badajoz",
    "iso:country":"ES",
    "sg:address":"Ctra Badajoz, S/n",
    "sg:city":"Jerez De Los Caballeros",
    "sg:orig_category":"M\u00c1rmoles, Granitos Y Piedras Naturales",
    "sg:phone":"+34 924 73 08 10",
    "sg:postcode":"06380",
    "sg:province":"Badajoz",
    "wof:name":"Benito Araujo S.a.",
    "wof:placetype":"venue"
},
  "geometry": {"coordinates":[-6.7708539963,38.3287010193],"type":"Point"}
}