{
  "type": "Feature",
  "properties": {
    "iso:country":"ES",
    "sg:address":"Av Tarragona, 136",
    "sg:city":"Vilafranca Penedes",
    "sg:orig_category":"Cer\u00c1micas: Material Y Suministros",
    "sg:phone":"+34 938 90 61 10",
    "sg:postcode":"08720",
    "sg:province":"Barcelona",
    "wof:name":"Mediterranea De Inversiones Givisa S.l.",
    "wof:placetype":"venue"
},
  "geometry": {"coordinates":[1.675080657,41.3283042908],"type":"Point"}
}