{
  "type": "Feature",
  "properties": {
    "addr:full":"Calle de Garcia Alix, 13 Almeria Almer\u00eda 04001",
    "addr:housenumber":"13",
    "addr:postcode":"04001",
    "addr:street":"Calle De Garcia Alix",
    "iso:country":"ES",
    "sg:address":"Calle de Garcia Alix, 13",
    "sg:city":"Almeria",
    "sg:orig_category":"Centros M\u00c9dicos Y Sociales, Dispensarios",
    "sg:phone":"+34 950 26 79 77",
    "sg:postcode":"04001",
    "sg:province":"Almer\u00eda",
    "wof:name":"Urrutia Y Montero S.l.",
    "wof:placetype":"venue"
},
  "geometry": {"coordinates":[-2.4616649151,36.8392105103],"type":"Point"}
}