{
  "type": "Feature",
  "properties": {
    "iso:country":"ES",
    "sg:address":"Carrer de Can Parera (de), 22",
    "sg:city":"Montornes Centre",
    "sg:orig_category":"Partidos Pol\u00cdticos",
    "sg:phone":"+34 935 72 06 25",
    "sg:postcode":"08170",
    "sg:province":"Barcelona",
    "wof:name":"Partit Socialista Unificat De Catalunya",
    "wof:placetype":"venue"
},
  "geometry": {"coordinates":[2.2678620815,41.545249939],"type":"Point"}
}