{
  "type": "Feature",
  "properties": {
    "iso:country":"ES",
    "sg:address":"Rond Torrassa, 11",
    "sg:city":"Hospitalet Llobregat",
    "sg:orig_category":"Electricidad: Equipos Industriales, Componentes (fabricaci\u00d3n)",
    "sg:phone":"+34 934 22 98 10",
    "sg:postcode":"08903",
    "sg:province":"Barcelona",
    "wof:name":"Marques Garcia Miguel",
    "wof:placetype":"venue"
},
  "geometry": {"coordinates":[2.1291260719,41.3702735901],"type":"Point"}
}