{
  "type": "Feature",
  "properties": {
    "addr:full":"Avgd Alameda Jaume I, 15 Xativa Valencia 46800",
    "addr:housenumber":"15",
    "addr:postcode":"46800",
    "addr:street":"Alameda Jaume I",
    "iso:country":"ES",
    "sg:address":"Avgd Alameda Jaume I, 15",
    "sg:city":"Xativa",
    "sg:orig_category":"Asesor\u00cda Fiscal Y Jur\u00cddica",
    "sg:phone":"+34 962 28 35 45",
    "sg:postcode":"46800",
    "sg:province":"Valencia",
    "wof:name":"Richart Perez Jose",
    "wof:placetype":"venue"
},
  "geometry": {"coordinates":[-0.5237929821,38.9893226624],"type":"Point"}
}