{
  "type": "Feature",
  "properties": {
    "addr:full":"Carr Valencia, 4 Silla Valencia 46460",
    "addr:housenumber":"4",
    "addr:postcode":"46460",
    "addr:street":"Carr Valencia",
    "iso:country":"ES",
    "sg:address":"Carr Valencia, 4",
    "sg:city":"Silla",
    "sg:orig_category":"Cajas De Ahorro",
    "sg:phone":"+34 961 20 01 14",
    "sg:postcode":"46460",
    "sg:province":"Valencia",
    "wof:name":"Caja De Ahorros De Valencia Castellon Y Alicante",
    "wof:placetype":"venue"
},
  "geometry": {"coordinates":[-0.4105620086,39.3661308289],"type":"Point"}
}