{
  "type": "Feature",
  "properties": {
    "addr:full":"Trinkete Plaza, 2 Tolosa Guip\u00f9zcoa 20400",
    "addr:housenumber":"2",
    "addr:postcode":"20400",
    "addr:street":"Trinkete Plaza;Guipu\u0300Zcoa",
    "iso:country":"ES",
    "sg:address":"Trinkete Plaza, 2",
    "sg:city":"Tolosa",
    "sg:orig_category":"Sindicatos De Trabajadores",
    "sg:phone":"+34 943 01 42 82",
    "sg:postcode":"20400",
    "sg:province":"Guip\u00f9zcoa",
    "wof:name":"Enba, Euskal Nekazarien Batasuna Sindikatua",
    "wof:placetype":"venue"
},
  "geometry": {"coordinates":[-2.0789339542,43.1339912415],"type":"Point"}
}