{
  "type": "Feature",
  "properties": {
    "iso:country":"ES",
    "sg:address":"Av Masnou, 31",
    "sg:city":"Hospitalet Llobregat",
    "sg:orig_category":"Zapatos (al Por Menor)",
    "sg:phone":"+34 934 37 63 46",
    "sg:postcode":"08905",
    "sg:province":"Barcelona",
    "wof:name":"Mu\u00f1oz Serrano Maria Manuela",
    "wof:placetype":"venue"
},
  "geometry": {"coordinates":[2.1068739891,41.3700942993],"type":"Point"}
}