{
  "type": "Feature",
  "properties": {
    "addr:full":"Alam Revilla Gregorio De La, 41 Bilbao Vizcaya 48010",
    "addr:postcode":"48010",
    "addr:street":"Alam Revilla",
    "iso:country":"ES",
    "sg:address":"Alam Revilla Gregorio De La, 41",
    "sg:city":"Bilbao",
    "sg:orig_category":"Limpieza Con Chorro De Arena Y Con Granalla, Pulido",
    "sg:phone":"+34 944 43 22 04",
    "sg:postcode":"48010",
    "sg:province":"Vizcaya",
    "wof:name":"Usategui Guillerma Itziar",
    "wof:placetype":"venue"
},
  "geometry": {"coordinates":[-2.9413108826,43.2582740784],"type":"Point"}
}