{
  "type": "Feature",
  "properties": {
    "addr:full":"Calle de Huertas, 10 Riopar Albacete 02450",
    "addr:housenumber":"10",
    "addr:postcode":"02450",
    "addr:street":"Calle De Huertas",
    "iso:country":"ES",
    "sg:address":"Calle de Huertas, 10",
    "sg:city":"Riopar",
    "sg:orig_category":"Carnicer\u00cdas, Carnicer\u00cdas",
    "sg:phone":"+34 967 43 50 50",
    "sg:postcode":"02450",
    "sg:province":"Albacete",
    "wof:name":"Valdelvira Sanchez Valentina",
    "wof:placetype":"venue"
},
  "geometry": {"coordinates":[-2.4202458858,38.4999046326],"type":"Point"}
}