{
  "type": "Feature",
  "properties": {
    "iso:country":"ES",
    "sg:address":"Ctra Alcala-utrera, S/n",
    "sg:city":"Alcala Guadaira",
    "sg:orig_category":"Producci\u00d3n, Venta De Productos De Agricultura Biol\u00d3gica",
    "sg:phone":"+34 955 99 01 75",
    "sg:postcode":"41500",
    "sg:province":"Sevilla",
    "wof:name":"Majada Alta S. A.",
    "wof:placetype":"venue"
},
  "geometry": {"coordinates":[-5.8398590088,37.3383140564],"type":"Point"}
}