{
  "type": "Feature",
  "properties": {
    "iso:country":"ES",
    "sg:address":"Rua Marina (a), 6",
    "sg:city":"Grove",
    "sg:orig_category":"Art\u00cdculos De Regalo (al Por Menor)",
    "sg:phone":"+34 986 73 25 50",
    "sg:postcode":"36980",
    "sg:province":"Pontevedra",
    "wof:name":"A Marina Grove C.b.",
    "wof:placetype":"venue"
},
  "geometry": {"coordinates":[-8.8630771637,42.4954948425],"type":"Point"}
}