{
  "type": "Feature",
  "properties": {
    "addr:full":"Halcon, 5 Molino Hoz Madrid 28230",
    "addr:housenumber":"5",
    "addr:postcode":"28230",
    "addr:street":"Halcon",
    "iso:country":"ES",
    "sg:address":"Halcon, 5",
    "sg:city":"Molino Hoz",
    "sg:orig_category":"Inform\u00c1tica (estudios, Servicios, Asesor\u00cda, Formaci\u00d3n)",
    "sg:phone":"+34 916 30 61 85",
    "sg:postcode":"28230",
    "sg:province":"Madrid",
    "wof:name":"Atayo S.a.",
    "wof:placetype":"venue"
},
  "geometry": {"coordinates":[-3.9375779629,40.5368118286],"type":"Point"}
}