{
  "type": "Feature",
  "properties": {
    "addr:full":"Calle de Jesus De La Humildad, 14 Higuera Real Badajoz 06350",
    "addr:housenumber":"14",
    "addr:postcode":"06350",
    "addr:street":"Calle De Jesus De La Humildad",
    "iso:country":"ES",
    "sg:address":"Calle de Jesus De La Humildad, 14",
    "sg:city":"Higuera Real",
    "sg:orig_category":"Cajas De Ahorro",
    "sg:phone":"+34 924 72 32 33",
    "sg:postcode":"06350",
    "sg:province":"Badajoz",
    "wof:name":"Caja De Badajoz",
    "wof:placetype":"venue"
},
  "geometry": {"coordinates":[-6.6878638268,38.1427993774],"type":"Point"}
}