{
  "type": "Feature",
  "properties": {
    "addr:full":"Calle de Teodosio, 66 Sevilla Sevilla 41002",
    "addr:housenumber":"66",
    "addr:postcode":"41002",
    "addr:street":"Calle De Teodosio",
    "iso:country":"ES",
    "sg:address":"Calle de Teodosio, 66",
    "sg:city":"Sevilla",
    "sg:orig_category":"Abogados",
    "sg:phone":"+34 954 90 98 43",
    "sg:postcode":"41002",
    "sg:province":"Sevilla",
    "wof:name":"Sanchez Maisanaba Carmen",
    "wof:placetype":"venue"
},
  "geometry": {"coordinates":[-5.997387886,37.3978767395],"type":"Point"}
}