{
  "type": "Feature",
  "properties": {
    "iso:country":"ES",
    "sg:address":"Carrer de Sant Sever, 6",
    "sg:city":"Barcelona",
    "sg:orig_category":"Obras Y Organismos Sociales",
    "sg:phone":"+34 933 17 80 61",
    "sg:postcode":"08002",
    "sg:province":"Barcelona",
    "wof:name":"Fundacio Privada Adfisret",
    "wof:placetype":"venue"
},
  "geometry": {"coordinates":[2.1753430367,41.3830184937],"type":"Point"}
}