{
  "type": "Feature",
  "properties": {
    "iso:country":"ES",
    "sg:address":"Carrer de Cinc, 5",
    "sg:city":"Bonavista",
    "sg:orig_category":"Reposter\u00cdas",
    "sg:phone":"+34 977 55 04 91",
    "sg:postcode":"43100",
    "sg:province":"Tarragona",
    "wof:name":"Ferrandiz Sal Jose",
    "wof:placetype":"venue"
},
  "geometry": {"coordinates":[1.1936869621,41.1176948547],"type":"Point"}
}