{
  "type": "Feature",
  "properties": {
    "iso:country":"ES",
    "sg:address":"Ctra Coru\u00d1a, 7",
    "sg:city":"San Cidre",
    "sg:orig_category":"Bazares, Art\u00cdculos De Limpieza Y De Cocina (al Por Menor)",
    "sg:phone":"+34 981 79 43 75",
    "sg:postcode":"15165",
    "sg:province":"La Coru\u00f1a",
    "sg:website":"www.garimpo.es",
    "wof:name":"Garimpo Artesania Internacional S.l.",
    "wof:placetype":"venue"
},
  "geometry": {"coordinates":[-8.3959693909,43.3714904785],"type":"Point"}
}