{
  "type": "Feature",
  "properties": {
    "iso:country":"ES",
    "sg:address":"Abenda\u00d1o Auzoa, S/n",
    "sg:city":"Elkano",
    "sg:orig_category":"Albergues",
    "sg:phone":"+34 943 13 34 70",
    "sg:postcode":"20800",
    "sg:province":"Guip\u00f9zcoa",
    "wof:name":"Himalaya K2 S.l.",
    "wof:placetype":"venue"
},
  "geometry": {"coordinates":[-2.1776471138,43.2848129272],"type":"Point"}
}