{
  "type": "Feature",
  "properties": {
    "addr:full":"Calle de Luis Doreste Silva, 9 S.juan Las Palmas 35200",
    "addr:housenumber":"9",
    "addr:postcode":"35200",
    "addr:street":"Calle De Luis Doreste Silva;Las Palmas",
    "iso:country":"ES",
    "sg:address":"Calle de Luis Doreste Silva, 9",
    "sg:city":"S.juan",
    "sg:orig_category":"Flores Y Plantas Naturales (al Por Mayor)",
    "sg:phone":"+34 928 69 61 05",
    "sg:postcode":"35200",
    "sg:province":"Las Palmas",
    "wof:name":"Amador Morales Manuel",
    "wof:placetype":"venue"
},
  "geometry": {"coordinates":[-15.4300060272,28.1248226166],"type":"Point"}
}