{
  "type": "Feature",
  "properties": {
    "addr:full":"Barrio La Cotera, 70 Villanueva Pe\u00f1a Cantabria 39509",
    "addr:housenumber":"70",
    "addr:postcode":"39509",
    "addr:street":"Barrio La Cotera",
    "iso:country":"ES",
    "sg:address":"Barrio La Cotera, 70",
    "sg:city":"Villanueva Pe\u00f1a",
    "sg:orig_category":"Sanatorios M\u00c9dico",
    "sg:phone":"+34 942 70 86 14",
    "sg:postcode":"39509",
    "sg:province":"Cantabria",
    "wof:name":"Ayuntamiento De Mazcuerras",
    "wof:placetype":"venue"
},
  "geometry": {"coordinates":[-4.2100739479,43.2973518372],"type":"Point"}
}