{
  "type": "Feature",
  "properties": {
    "iso:country":"ES",
    "sg:address":"Ctra Valladolid, 5",
    "sg:city":"Lastrilla",
    "sg:orig_category":"Lavado, Limpieza De Veh\u00cdculos",
    "sg:phone":"+34 921 43 03 80",
    "sg:postcode":"40196",
    "sg:province":"Segovia",
    "wof:name":"Sociedad Agraria De Transformacion-incoporc",
    "wof:placetype":"venue"
},
  "geometry": {"coordinates":[-4.1034941673,40.9690361023],"type":"Point"}
}