{
  "type": "Feature",
  "properties": {
    "addr:full":"Avda Tenerife (de), 4 Playa Del Ingles Las Palmas 35100",
    "addr:housenumber":"4",
    "addr:postcode":"35100",
    "addr:street":"Avda Tenerife De",
    "iso:country":"ES",
    "sg:address":"Avda Tenerife (de), 4",
    "sg:city":"Playa Del Ingles",
    "sg:orig_category":"Alquiler De Veh\u00cdculos: Turismos Y Utilitarios",
    "sg:phone":"+34 928 77 27 01",
    "sg:postcode":"35100",
    "sg:province":"Las Palmas",
    "wof:name":"Ara\u00f1a Sanchez Benito",
    "wof:placetype":"venue"
},
  "geometry": {"coordinates":[-15.5682020187,27.7618350983],"type":"Point"}
}