{
  "type": "Feature",
  "properties": {
    "addr:full":"Calle de Sagunto, 142 Valencia Valencia 46009",
    "addr:housenumber":"142",
    "addr:postcode":"46009",
    "addr:street":"Calle De Sagunto",
    "iso:country":"ES",
    "sg:address":"Calle de Sagunto, 142",
    "sg:city":"Valencia",
    "sg:orig_category":"Muebles",
    "sg:phone":"+34 963 65 46 68",
    "sg:postcode":"46009",
    "sg:province":"Valencia",
    "wof:name":"Perez Garcia Fernando",
    "wof:placetype":"venue"
},
  "geometry": {"coordinates":[-0.3752498031,39.4880027771],"type":"Point"}
}