{
  "type": "Feature",
  "properties": {
    "iso:country":"ES",
    "sg:address":"Calle de Agricultura, 6",
    "sg:city":"Ubeda",
    "sg:orig_category":"Comercio De Piezas De Recambio Y De Accesorios De Veh\u00cdculos, Veh\u00cdculos Industriales",
    "sg:phone":"+34 953 75 33 01",
    "sg:postcode":"23400",
    "sg:province":"Ja\u00e9n",
    "wof:name":"Ruiz Orcera Juan",
    "wof:placetype":"venue"
},
  "geometry": {"coordinates":[-3.3662445545,38.0265007019],"type":"Point"}
}