{
  "type": "Feature",
  "properties": {
    "iso:country":"ES",
    "sg:address":"Carrer de Rossello, 148",
    "sg:city":"Barcelona",
    "sg:orig_category":"Doctores En Medicina",
    "sg:phone":"+34 933 23 31 99",
    "sg:postcode":"08036",
    "sg:province":"Barcelona",
    "wof:name":"Mercadal Piera Magdalena",
    "wof:placetype":"venue"
},
  "geometry": {"coordinates":[2.1544311047,41.3909301758],"type":"Point"}
}