{
  "type": "Feature",
  "properties": {
    "iso:country":"ES",
    "sg:address":"Carr Sant Domingo, 4",
    "sg:city":"Pollen\u00e7a",
    "sg:orig_category":"Asilos De Ancianos. Centros Privados",
    "sg:phone":"+34 971 53 07 38",
    "sg:postcode":"07460",
    "sg:province":"Islas Baleares",
    "wof:name":"Residencia Social Santo Domingo De Pollenca",
    "wof:placetype":"venue"
},
  "geometry": {"coordinates":[3.0059130192,39.8700141907],"type":"Point"}
}