{
  "type": "Feature",
  "properties": {
    "iso:country":"ES",
    "sg:address":"Calle de Orden, S/n",
    "sg:city":"Ferez",
    "sg:orig_category":"Cajas De Ahorro",
    "sg:phone":"+34 967 42 01 52",
    "sg:postcode":"02436",
    "sg:province":"Albacete",
    "wof:name":"Caja De Ahorros De Castilla La Mancha",
    "wof:placetype":"venue"
},
  "geometry": {"coordinates":[-2.0103070736,38.3556404114],"type":"Point"}
}