{
  "type": "Feature",
  "properties": {
    "addr:full":"Carrer de Josep Cuxart, 21 Cornella Llobregat Barcelona 08940",
    "addr:housenumber":"21",
    "addr:postcode":"08940",
    "addr:street":"Carrer De Josep Cuxart",
    "iso:country":"ES",
    "sg:address":"Carrer de Josep Cuxart, 21",
    "sg:city":"Cornella Llobregat",
    "sg:orig_category":"Empresas De Carpinter\u00cda De Madera",
    "sg:phone":"+34 933 77 48 08",
    "sg:postcode":"08940",
    "sg:province":"Barcelona",
    "wof:name":"Perona Garcia Juan Ramon",
    "wof:placetype":"venue"
},
  "geometry": {"coordinates":[2.072988987,41.3556938171],"type":"Point"}
}