{
  "type": "Feature",
  "properties": {
    "addr:full":"Av. Fisterra, 32 Laracha La Coru\u00f1a 15145",
    "addr:housenumber":"32",
    "addr:postcode":"15145",
    "addr:street":"Av. Fisterra;La Corun\u0303A",
    "iso:country":"ES",
    "sg:address":"Av. Fisterra, 32",
    "sg:city":"Laracha",
    "sg:orig_category":"Cl\u00cdnicas M\u00c9dicas",
    "sg:phone":"+34 981 60 58 74",
    "sg:postcode":"15145",
    "sg:province":"La Coru\u00f1a",
    "wof:name":"Castro Romero Benito",
    "wof:placetype":"venue"
},
  "geometry": {"coordinates":[-8.5799293518,43.247959137],"type":"Point"}
}