{
  "type": "Feature",
  "properties": {
    "addr:full":"Av Granvia, 90 Hospitalet Llobregat Barcelona 08902",
    "addr:housenumber":"90",
    "addr:postcode":"08902",
    "addr:street":"Av Granvia",
    "iso:country":"ES",
    "sg:address":"Av Granvia, 90",
    "sg:city":"Hospitalet Llobregat",
    "sg:orig_category":"Veh\u00cdculos De Ocasi\u00d3n",
    "sg:phone":"+34 932 64 09 64",
    "sg:postcode":"08902",
    "sg:province":"Barcelona",
    "wof:name":"Motor Llansa S.l.",
    "wof:placetype":"venue"
},
  "geometry": {"coordinates":[2.1212100983,41.3543395996],"type":"Point"}
}