{
  "type": "Feature",
  "properties": {
    "addr:full":"Av Tomas Vill Cortes, 3 Palma Islas Baleares 07009",
    "addr:housenumber":"3",
    "addr:postcode":"07009",
    "addr:street":"Av Tomas Vill Cortes",
    "iso:country":"ES",
    "sg:address":"Av Tomas Vill Cortes, 3",
    "sg:city":"Palma",
    "sg:orig_category":"Cajas De Ahorro",
    "sg:phone":"+34 971 76 12 78",
    "sg:postcode":"07009",
    "sg:province":"Islas Baleares",
    "wof:name":"Caixa D'estalvis I Pensions De Barcelona",
    "wof:placetype":"venue"
},
  "geometry": {"coordinates":[2.6776249409,39.6072845459],"type":"Point"}
}