{
  "type": "Feature",
  "properties": {
    "iso:country":"ES",
    "sg:address":"Av Maresme (del), 493",
    "sg:city":"Mataro",
    "sg:orig_category":"Centros Empresariales",
    "sg:phone":"+34 937 90 21 48",
    "sg:postcode":"08301",
    "sg:province":"Barcelona",
    "wof:name":"Pasto Cid Oscar",
    "wof:placetype":"venue"
},
  "geometry": {"coordinates":[2.455313921,41.5404396057],"type":"Point"}
}