{
  "type": "Feature",
  "properties": {
    "addr:full":"Avda Poeta Julian Andugar, 82 Santomera Murcia 30140",
    "addr:housenumber":"82",
    "addr:postcode":"30140",
    "addr:street":"Avda Poeta Julian Andugar",
    "iso:country":"ES",
    "sg:address":"Avda Poeta Julian Andugar, 82",
    "sg:city":"Santomera",
    "sg:orig_category":"Centros De Coordinaci\u00d3n",
    "sg:phone":"+34 968 86 45 32",
    "sg:postcode":"30140",
    "sg:province":"Murcia",
    "wof:name":"Trado Asociados De Santomera S.l.l.",
    "wof:placetype":"venue"
},
  "geometry": {"coordinates":[-1.0538890362,38.0634002686],"type":"Point"}
}