{
  "type": "Feature",
  "properties": {
    "iso:country":"ES",
    "sg:address":"Calle de General Franco, 8",
    "sg:city":"Pueblo",
    "sg:orig_category":"Iglesia Cat\u00d3lica",
    "sg:phone":"+34 922 49 00 04",
    "sg:postcode":"38780",
    "sg:province":"Santa Cruz De Tenerife",
    "wof:name":"Parroquia Nuestra Se\u00f1ora De Candelaria",
    "wof:placetype":"venue"
},
  "geometry": {"coordinates":[-17.9484500885,28.7017993927],"type":"Point"}
}