{
  "type": "Feature",
  "properties": {
    "iso:country":"ES",
    "sg:address":"Calle de San Sebastian, 4",
    "sg:city":"Fernan Nu\u00e7ez",
    "sg:orig_category":"Lencer\u00cda Femenina, Corseter\u00cda, Trajes De Ba\u00d1o (al Por Menor)",
    "sg:phone":"+34 957 37 31 92",
    "sg:postcode":"14520",
    "sg:province":"C\u00f3rdoba",
    "wof:name":"Sotelo Toledano Alfonso Edmundo",
    "wof:placetype":"venue"
},
  "geometry": {"coordinates":[-4.7247362137,37.6700363159],"type":"Point"}
}