{
  "type": "Feature",
  "properties": {
    "addr:full":"Calle de Eusebio Moran, 1 Madrid Madrid 28019",
    "addr:housenumber":"1",
    "addr:postcode":"28019",
    "addr:street":"Calle De Eusebio Moran",
    "iso:country":"ES",
    "sg:address":"Calle de Eusebio Moran, 1",
    "sg:city":"Madrid",
    "sg:orig_category":"Material Y Suministros Para Peluquer\u00cda",
    "sg:phone":"+34 915 69 19 82",
    "sg:postcode":"28019",
    "sg:province":"Madrid",
    "wof:name":"Cerra Del Castillo Fernando",
    "wof:placetype":"venue"
},
  "geometry": {"coordinates":[-3.7209489346,40.3896141052],"type":"Point"}
}