{
  "type": "Feature",
  "properties": {
    "addr:full":"Calle de Rambla, 53 Yecla Murcia 30510",
    "addr:housenumber":"53",
    "addr:postcode":"30510",
    "addr:street":"Calle De Rambla",
    "iso:country":"ES",
    "sg:address":"Calle de Rambla, 53",
    "sg:city":"Yecla",
    "sg:orig_category":"Radiocomunicaciones, Telefon\u00cda M\u00d3vil, Radiomensajer\u00cda: Servicios, Comercializaci\u00d3n",
    "sg:phone":"+34 902 30 99 03",
    "sg:postcode":"30510",
    "sg:province":"Murcia",
    "wof:name":"Grupo Gestion Transporte Internacio-nal",
    "wof:placetype":"venue"
},
  "geometry": {"coordinates":[-1.1087470055,38.6160774231],"type":"Point"}
}