{
  "type": "Feature",
  "properties": {
    "addr:full":"Calle de Tiendas, 2 Orce Granada 18858",
    "addr:housenumber":"2",
    "addr:postcode":"18858",
    "addr:street":"Calle De Tiendas",
    "iso:country":"ES",
    "sg:address":"Calle de Tiendas, 2",
    "sg:city":"Orce",
    "sg:orig_category":"Electrodom\u00c9sticos (al Por Menor)",
    "sg:phone":"+34 958 74 60 52",
    "sg:postcode":"18858",
    "sg:province":"Granada",
    "wof:name":"Gallardo Arjona Miguel",
    "wof:placetype":"venue"
},
  "geometry": {"coordinates":[-2.4794039726,37.7216835022],"type":"Point"}
}