{
  "type": "Feature",
  "properties": {
    "addr:full":"Calle de Jesus Otero, S/n Santillana Cantabria 39330",
    "addr:housenumber":"s / n",
    "addr:postcode":"39330",
    "addr:street":"Calle De Jesus Otero",
    "iso:country":"ES",
    "sg:address":"Calle de Jesus Otero, S/n",
    "sg:city":"Santillana",
    "sg:orig_category":"Molduras, Junquillos, Listones Y Molduras Perforadas",
    "sg:phone":"+34 942 84 03 57",
    "sg:postcode":"39330",
    "sg:province":"Cantabria",
    "wof:name":"Casa Cossio S. Cv.",
    "wof:placetype":"venue"
},
  "geometry": {"coordinates":[-4.1085891724,43.3888092041],"type":"Point"}
}