{
  "type": "Feature",
  "properties": {
    "addr:full":"Calle de Reyes Los, 10 S. Roque C\u00e1diz 11360",
    "addr:housenumber":"10",
    "addr:postcode":"11360",
    "addr:street":"Calle De Reyes Los;Roque Ca\u0301Diz",
    "iso:country":"ES",
    "sg:address":"Calle de Reyes Los, 10",
    "sg:city":"S. Roque",
    "sg:orig_category":"Alimentaci\u00d3n General (al Por Menor)",
    "sg:phone":"+34 956 78 15 37",
    "sg:postcode":"11360",
    "sg:province":"C\u00e1diz",
    "wof:name":"Gavira Gomez Manuel",
    "wof:placetype":"venue"
},
  "geometry": {"coordinates":[-5.3897438049,36.209690094],"type":"Point"}
}