{
  "type": "Feature",
  "properties": {
    "iso:country":"ES",
    "sg:address":"Pl Francesc Macia, 5",
    "sg:city":"Barcelona",
    "sg:orig_category":"Asesor\u00cdas Y Estudios Financieros",
    "sg:phone":"+34 932 41 80 08",
    "sg:postcode":"08021",
    "sg:province":"Barcelona",
    "sg:website":"www.closa.com",
    "wof:name":"Closa Corporate Finance Advisors S.a.",
    "wof:placetype":"venue"
},
  "geometry": {"coordinates":[2.1443281174,41.3931922913],"type":"Point"}
}