{
  "type": "Feature",
  "properties": {
    "iso:country":"ES",
    "sg:address":"Av Barcelona, 7",
    "sg:city":"Tarrega",
    "sg:orig_category":"Electromec\u00c1nica",
    "sg:phone":"+34 973 50 14 40",
    "sg:postcode":"25300",
    "sg:province":"Lleida",
    "wof:name":"Bobinatges J.pujal S.l.",
    "wof:placetype":"venue"
},
  "geometry": {"coordinates":[1.1458059549,41.6518630981],"type":"Point"}
}