{
  "type": "Feature",
  "properties": {
    "iso:country":"ES",
    "sg:address":"Calle de Val, 2",
    "sg:city":"Valladolid",
    "sg:orig_category":"Complementos De Vestir (al Por Menor)",
    "sg:phone":"+34 983 35 11 32",
    "sg:postcode":"47003",
    "sg:province":"Valladolid",
    "wof:name":"Buey Perez Lucia",
    "wof:placetype":"venue"
},
  "geometry": {"coordinates":[-4.7274398804,41.652961731],"type":"Point"}
}