{
  "type": "Feature",
  "properties": {
    "addr:full":"Calle de Adelfa, 16 Humanes De Madrid Madrid 28970",
    "addr:housenumber":"16",
    "addr:postcode":"28970",
    "addr:street":"Calle De Adelfa",
    "iso:country":"ES",
    "sg:address":"Calle de Adelfa, 16",
    "sg:city":"Humanes De Madrid",
    "sg:orig_category":"Estudios, Instalaci\u00d3n De Climatizaci\u00d3n",
    "sg:phone":"+34 916 97 60 01",
    "sg:postcode":"28970",
    "sg:province":"Madrid",
    "wof:name":"Euroclima Madrid S.l.",
    "wof:placetype":"venue"
},
  "geometry": {"coordinates":[-3.8378095627,40.2682533264],"type":"Point"}
}