{
  "type": "Feature",
  "properties": {
    "addr:full":"Carrer de Francesc De Borja Moll, S/n Mataro Barcelona 08304",
    "addr:housenumber":"s",
    "addr:postcode":"08304",
    "addr:street":"Carrer De Francesc De Borja Moll;/ N Mataro Barcelona",
    "iso:country":"ES",
    "sg:address":"Carrer de Francesc De Borja Moll, S/n",
    "sg:city":"Mataro",
    "sg:orig_category":"Peluquer\u00cdas",
    "sg:phone":"+34 937 98 57 26",
    "sg:postcode":"08304",
    "sg:province":"Barcelona",
    "wof:name":"Martinez Navarrete Pepita",
    "wof:placetype":"venue"
},
  "geometry": {"coordinates":[2.4414899349,41.5536956787],"type":"Point"}
}