{
  "type": "Feature",
  "properties": {
    "iso:country":"ES",
    "sg:address":"Luga Conchas (as), S/n",
    "sg:city":"Conchas",
    "sg:orig_category":"Supermercados Y Hipermercados",
    "sg:phone":"+34 988 44 82 10",
    "sg:postcode":"32897",
    "sg:province":"Ourense",
    "wof:name":"Veloso Rodriguez Dolores",
    "wof:placetype":"venue"
},
  "geometry": {"coordinates":[-7.9401597977,41.967754364],"type":"Point"}
}