{
  "type": "Feature",
  "properties": {
    "addr:full":"Calle de Valencia, 16 Monzon Huesca 22400",
    "addr:housenumber":"16",
    "addr:postcode":"22400",
    "addr:street":"Calle De Valencia",
    "iso:country":"ES",
    "sg:address":"Calle de Valencia, 16",
    "sg:city":"Monzon",
    "sg:orig_category":"Ense\u00d1anza Variada",
    "sg:phone":"+34 974 40 18 87",
    "sg:postcode":"22400",
    "sg:province":"Huesca",
    "wof:name":"Garicano Cebrian Esteban",
    "wof:placetype":"venue"
},
  "geometry": {"coordinates":[0.1935900003,41.9146614075],"type":"Point"}
}