{
  "type": "Feature",
  "properties": {
    "iso:country":"ES",
    "sg:address":"Avgd Catalunya, S/n",
    "sg:city":"Poal",
    "sg:orig_category":"Maquinaria Para Industrias Diversas",
    "sg:phone":"+34 973 56 50 88",
    "sg:postcode":"25143",
    "sg:province":"Lleida",
    "sg:website":"www.talleresmoreno.com",
    "wof:name":"Taller Joan I Pere Moreno S.l.",
    "wof:placetype":"venue"
},
  "geometry": {"coordinates":[0.856850028,41.6762161255],"type":"Point"}
}