{
  "type": "Feature",
  "properties": {
    "addr:full":"Calle de San Martin, 1 Salvatierra O Agurain \u00c1lava 01200",
    "addr:housenumber":"1",
    "addr:postcode":"01200",
    "addr:street":"Calle De San Martin;A\u0301Lava",
    "iso:country":"ES",
    "sg:address":"Calle de San Martin, 1",
    "sg:city":"Salvatierra O Agurain",
    "sg:classifiers":[
        {
            "category":"Taxi",
            "type":"Transportation"
        }
    ],
    "sg:phone":"+34 945 30 00 57",
    "sg:postcode":"01200",
    "sg:province":"\u00c1lava",
    "wof:name":"Elizondo Gomez De Segura Felix",
    "wof:placetype":"venue"
},
  "geometry": {"coordinates":[-2.3926889896,42.845790863],"type":"Point"}
}