{
  "type": "Feature",
  "properties": {
    "addr:full":"Calle de Gran Via De San Marcos, 19 Le\u00f3n Le\u00f3n 24002",
    "addr:housenumber":"19",
    "addr:postcode":"24002",
    "addr:street":"Calle De Gran Via De San Marcos;Leo\u0301N",
    "iso:country":"ES",
    "sg:address":"Calle de Gran Via De San Marcos, 19",
    "sg:city":"Le\u00f3n",
    "sg:orig_category":"Arquitectos",
    "sg:phone":"+34 987 87 64 44",
    "sg:postcode":"24002",
    "sg:province":"Le\u00f3n",
    "sg:website":"www.paginasamarillas.es",
    "wof:name":"Geijo Garcia Rogelio",
    "wof:placetype":"venue"
},
  "geometry": {"coordinates":[-5.5763063431,42.5996131897],"type":"Point"}
}