{
  "type": "Feature",
  "properties": {
    "addr:full":"Calle de Fernan Gonzalez, 51 Madrid Madrid 28009",
    "addr:housenumber":"51",
    "addr:postcode":"madrid;28009",
    "addr:street":"Calle De Fernan Gonzalez",
    "iso:country":"ES",
    "sg:address":"Calle de Fernan Gonzalez, 51",
    "sg:city":"Madrid",
    "sg:orig_category":"Mercer\u00cda, Lencer\u00cda (al Por Menor)",
    "sg:phone":"+34 915 74 18 27",
    "sg:postcode":"28009",
    "sg:province":"Madrid",
    "wof:name":"Hernando Gutierrez Maria Almudena",
    "wof:placetype":"venue"
},
  "geometry": {"coordinates":[-3.6745271683,40.4194755554],"type":"Point"}
}