{
  "type": "Feature",
  "properties": {
    "iso:country":"ES",
    "sg:address":"Calle de Valladolid, 1",
    "sg:city":"Espinar",
    "sg:orig_category":"Discapacitados",
    "sg:phone":"+34 921 18 10 82",
    "sg:postcode":"40400",
    "sg:province":"Segovia",
    "wof:name":"Asociacion De Discapacitados Para La Integracion",
    "wof:placetype":"venue"
},
  "geometry": {"coordinates":[-4.2462072372,40.7187767029],"type":"Point"}
}