{
  "type": "Feature",
  "properties": {
    "iso:country":"ES",
    "sg:address":"Calle de Juan De Mena, S/n",
    "sg:city":"Dos Hermanas",
    "sg:orig_category":"Estudios, Instalaci\u00d3n De Climatizaci\u00d3n",
    "sg:phone":"+34 955 66 24 24",
    "sg:postcode":"41700",
    "sg:province":"Sevilla",
    "wof:name":"Electroviso S.l.",
    "wof:placetype":"venue"
},
  "geometry": {"coordinates":[-5.9344091415,37.2816467285],"type":"Point"}
}