{
  "type": "Feature",
  "properties": {
    "addr:full":"Carrer de Elisabets, 5 Barcelona Barcelona 08001",
    "addr:housenumber":"5",
    "addr:postcode":"08001",
    "addr:street":"Carrer De Elisabets",
    "iso:country":"ES",
    "sg:address":"Carrer de Elisabets, 5",
    "sg:city":"Barcelona",
    "sg:orig_category":"Marroquiner\u00cda (confecci\u00d3n)",
    "sg:phone":"+34 933 01 33 98",
    "sg:postcode":"08001",
    "sg:province":"Barcelona",
    "wof:name":"Nydem C.b.",
    "wof:placetype":"venue"
},
  "geometry": {"coordinates":[2.1689538956,41.3834915161],"type":"Point"}
}