{
  "type": "Feature",
  "properties": {
    "addr:full":"Rua Luis Calvo, 19 Carballo La Coru\u00f1a 15100",
    "addr:housenumber":"19",
    "addr:postcode":"15100",
    "addr:street":"Rua Luis Calvo;La Corun\u0303A",
    "iso:country":"ES",
    "sg:address":"Rua Luis Calvo, 19",
    "sg:city":"Carballo",
    "sg:orig_category":"Negocio De Madera",
    "sg:phone":"+34 981 75 56 99",
    "sg:postcode":"15100",
    "sg:province":"La Coru\u00f1a",
    "wof:name":"Carpinteria Fuentes E Iglesias S.l.",
    "wof:placetype":"venue"
},
  "geometry": {"coordinates":[-8.6935043335,43.2123985291],"type":"Point"}
}