{
  "type": "Feature",
  "properties": {
    "iso:country":"ES",
    "sg:address":"Carr Del Dos De Maig, 170",
    "sg:city":"Ontinyent",
    "sg:orig_category":"Agentes Generales De Seguros",
    "sg:phone":"+34 962 91 20 32",
    "sg:postcode":"46870",
    "sg:province":"Valencia",
    "wof:name":"Sanchez Martinez Jose Vicente",
    "wof:placetype":"venue"
},
  "geometry": {"coordinates":[-0.6048769951,38.8187141418],"type":"Point"}
}