{
  "type": "Feature",
  "properties": {
    "addr:full":"Calle de Primo De Rivera, 19 Andratx Islas Baleares 07150",
    "addr:housenumber":"19",
    "addr:postcode":"07150",
    "addr:street":"Calle De Primo De Rivera",
    "iso:country":"ES",
    "sg:address":"Calle de Primo De Rivera, 19",
    "sg:city":"Andratx",
    "sg:orig_category":"Ense\u00d1anza Variada",
    "sg:phone":"+34 971 23 58 77",
    "sg:postcode":"07150",
    "sg:province":"Islas Baleares",
    "wof:name":"Gamiga S. L.",
    "wof:placetype":"venue"
},
  "geometry": {"coordinates":[2.4207260609,39.5757026672],"type":"Point"}
}