{
  "type": "Feature",
  "properties": {
    "iso:country":"ES",
    "sg:address":"Rua Eduardo Vincenti, 35",
    "sg:city":"Bueu",
    "sg:orig_category":"Asesor\u00cda Sobre Comunicaci\u00d3n De Empresas",
    "sg:phone":"+34 986 32 44 21",
    "sg:postcode":"36930",
    "sg:province":"Pontevedra",
    "wof:name":"Gesdegal S.l.",
    "wof:placetype":"venue"
},
  "geometry": {"coordinates":[-8.7845888138,42.3271217346],"type":"Point"}
}