{
  "type": "Feature",
  "properties": {
    "iso:country":"ES",
    "sg:address":"Avda Gonzalez Besada, 19",
    "sg:city":"Vilanova Arousa",
    "sg:orig_category":"Molduras, Junquillos, Listones Y Molduras Perforadas",
    "sg:phone":"+34 986 55 52 28",
    "sg:postcode":"36620",
    "sg:province":"Pontevedra",
    "wof:name":"Telerenta S.l",
    "wof:placetype":"venue"
},
  "geometry": {"coordinates":[-8.8280010223,42.5617828369],"type":"Point"}
}