{
  "type": "Feature",
  "properties": {
    "addr:full":"Calle de Corpus Christi, S/n S. Andres Rabanedo Le\u00f3n 24010",
    "addr:housenumber":"s",
    "addr:postcode":"24010",
    "addr:street":"Calle De Corpus Christi;/ N S. Andres Rabanedo Leo\u0301N",
    "iso:country":"ES",
    "sg:address":"Calle de Corpus Christi, S/n",
    "sg:city":"S. Andres Rabanedo",
    "sg:orig_category":"Servicios De Telecomunicaciones",
    "sg:phone":"+34 987 84 67 13",
    "sg:postcode":"24010",
    "sg:province":"Le\u00f3n",
    "wof:name":"Sociedad Operadora Para Las Telecomunicaciones Castilla-leon S.a.",
    "wof:placetype":"venue"
},
  "geometry": {"coordinates":[-5.5716600418,42.5981292725],"type":"Point"}
}