{
  "type": "Feature",
  "properties": {
    "addr:full":"Calle de Oiartzun, 5 Errenteria Guip\u00f9zcoa 20100",
    "addr:housenumber":"5",
    "addr:postcode":"20100",
    "addr:street":"Calle De Oiartzun;Guipu\u0300Zcoa",
    "iso:country":"ES",
    "sg:address":"Calle de Oiartzun, 5",
    "sg:city":"Errenteria",
    "sg:orig_category":"Confecci\u00d3n (fabricaci\u00d3n, Al Por Mayor)",
    "sg:phone":"+34 943 52 19 90",
    "sg:postcode":"20100",
    "sg:province":"Guip\u00f9zcoa",
    "wof:name":"Espina Ibarburu Antonio",
    "wof:placetype":"venue"
},
  "geometry": {"coordinates":[-1.9024380445,43.3158531189],"type":"Point"}
}