{
  "type": "Feature",
  "properties": {
    "addr:full":"Pase San Vicente, 12 Salamanca Salamanca 37007",
    "addr:housenumber":"12",
    "addr:postcode":"37007",
    "addr:street":"San Vicente",
    "iso:country":"ES",
    "sg:address":"Pase San Vicente, 12",
    "sg:city":"Salamanca",
    "sg:orig_category":"Colchones (fabricaci\u00d3n, Al Por Mayor, Al Por Menor)",
    "sg:phone":"+34 923 26 30 96",
    "sg:postcode":"37007",
    "sg:province":"Salamanca",
    "wof:name":"Pi\u00f1uela Garcia Angel",
    "wof:placetype":"venue"
},
  "geometry": {"coordinates":[-5.6729779243,40.963180542],"type":"Point"}
}