{
  "type": "Feature",
  "properties": {
    "iso:country":"ES",
    "sg:address":"Camino Carra\u00f1on, S/n",
    "sg:city":"Vera De Moncayo",
    "sg:orig_category":"Ense\u00d1ante, Direcci\u00d3n",
    "sg:phone":"+34 976 64 90 61",
    "sg:postcode":"50580",
    "sg:province":"Zaragoza",
    "wof:name":"Dueso Crespo Jesus",
    "wof:placetype":"venue"
},
  "geometry": {"coordinates":[-1.687024951,41.8245544434],"type":"Point"}
}