{
  "type": "Feature",
  "properties": {
    "addr:full":"Martina Maiz Kalea, 3 Beasain Guip\u00f9zcoa 20200",
    "addr:housenumber":"3",
    "addr:postcode":"20200",
    "addr:street":"Martina Maiz Kalea;Guipu\u0300Zcoa",
    "iso:country":"ES",
    "sg:address":"Martina Maiz Kalea, 3",
    "sg:city":"Beasain",
    "sg:orig_category":"Promotores Constructores",
    "sg:phone":"+34 943 88 02 48",
    "sg:postcode":"20200",
    "sg:province":"Guip\u00f9zcoa",
    "wof:name":"Promotora Del Goyerri S.a.",
    "wof:placetype":"venue"
},
  "geometry": {"coordinates":[-2.1949329376,43.0474891663],"type":"Point"}
}