{
  "type": "Feature",
  "properties": {
    "iso:country":"ES",
    "sg:address":"Calle de Santa Isabel, S/n",
    "sg:city":"Alcazares",
    "sg:orig_category":"Alimentaci\u00d3n General (al Por Menor)",
    "sg:phone":"+34 968 57 54 45",
    "sg:postcode":"30710",
    "sg:province":"Murcia",
    "wof:name":"Noguera Sanchez Antonio",
    "wof:placetype":"venue"
},
  "geometry": {"coordinates":[-0.8501666188,37.7392959595],"type":"Point"}
}