{
  "type": "Feature",
  "properties": {
    "iso:country":"ES",
    "sg:address":"Calle de San Jacinto, 37",
    "sg:city":"Sevilla",
    "sg:orig_category":"Reposter\u00cdas",
    "sg:phone":"+34 954 33 46 87",
    "sg:postcode":"41010",
    "sg:province":"Sevilla",
    "wof:name":"Hartillo Diaz Manuel",
    "wof:placetype":"venue"
},
  "geometry": {"coordinates":[-6.0046491623,37.3839607239],"type":"Point"}
}