{
  "type": "Feature",
  "properties": {
    "addr:full":"Calle de Moneda, 13 Burgos Burgos 09003",
    "addr:housenumber":"13",
    "addr:postcode":"09003",
    "addr:street":"Calle De Moneda",
    "iso:country":"ES",
    "sg:address":"Calle de Moneda, 13",
    "sg:city":"Burgos",
    "sg:orig_category":"Agencias De Viajes",
    "sg:phone":"+34 947 20 29 49",
    "sg:postcode":"09003",
    "sg:province":"Burgos",
    "wof:name":"Maria Carmen Roca Cantos Y Otro S.cv.",
    "wof:placetype":"venue"
},
  "geometry": {"coordinates":[-3.7003099918,42.3422431946],"type":"Point"}
}