{
  "type": "Feature",
  "properties": {
    "iso:country":"ES",
    "sg:address":"Ctra Barcelona, S/n",
    "sg:city":"Viladecans",
    "sg:orig_category":"Frutas, Legumbres Frescas Y Tempranas (al Por Menor)",
    "sg:phone":"+34 936 37 53 48",
    "sg:postcode":"08840",
    "sg:province":"Barcelona",
    "sg:website":"www.frutasandres.com",
    "wof:name":"Frutas Andres S.a.",
    "wof:placetype":"venue"
},
  "geometry": {"coordinates":[2.0282700062,41.3215942383],"type":"Point"}
}