{
  "type": "Feature",
  "properties": {
    "addr:full":"Carrer de Santa Caterina, 6 S. Adria Besos Barcelona 08930",
    "addr:housenumber":"6",
    "addr:postcode":"08930",
    "addr:street":"Carrer De Santa Caterina;Barcelona",
    "iso:country":"ES",
    "sg:address":"Carrer de Santa Caterina, 6",
    "sg:city":"S. Adria Besos",
    "sg:orig_category":"Agencias Y Agentes Comerciales, Representantes",
    "sg:phone":"+34 933 81 95 02",
    "sg:postcode":"08930",
    "sg:province":"Barcelona",
    "wof:name":"Galea Alonso Fernando",
    "wof:placetype":"venue"
},
  "geometry": {"coordinates":[2.2202460766,41.4311141968],"type":"Point"}
}