{
  "type": "Feature",
  "properties": {
    "iso:country":"ES",
    "sg:address":"Calle de Gonzalo De Cordoba, 2",
    "sg:city":"Madrid",
    "sg:orig_category":"Ingenier\u00cda, Centros De Estudios (diversos)",
    "sg:phone":"+34 915 93 11 55",
    "sg:postcode":"28010",
    "sg:province":"Madrid",
    "wof:name":"Ute Ebb Publicaciones Tecnicas",
    "wof:placetype":"venue"
},
  "geometry": {"coordinates":[-3.7033810616,40.4320373535],"type":"Point"}
}