{
  "type": "Feature",
  "properties": {
    "iso:country":"ES",
    "sg:address":"Carrer de Gabriel Miro, 37",
    "sg:city":"Pedreguer",
    "sg:orig_category":"Empresas De Carpinter\u00cda Met\u00c1lica",
    "sg:phone":"+34 965 76 02 91",
    "sg:postcode":"03750",
    "sg:province":"Alicante",
    "wof:name":"Costa Ribes Jose Vicente",
    "wof:placetype":"venue"
},
  "geometry": {"coordinates":[0.0321540013,38.7967071533],"type":"Point"}
}