{
  "type": "Feature",
  "properties": {
    "iso:country":"ES",
    "sg:address":"Avda Doctor Salvador Caballero Garcia, 67",
    "sg:city":"Puerto Lumbreras",
    "sg:orig_category":"Flores Y Plantas Naturales (al Por Mayor)",
    "sg:phone":"+34 968 40 28 83",
    "sg:postcode":"30890",
    "sg:province":"Murcia",
    "wof:name":"Cristina Flor S.l.",
    "wof:placetype":"venue"
},
  "geometry": {"coordinates":[-1.8153710365,37.5637664795],"type":"Point"}
}