{
  "type": "Feature",
  "properties": {
    "addr:full":"Carr Santiago Rusi\u00d1ol, 14 Badalona Barcelona 08911",
    "addr:housenumber":"14",
    "addr:postcode":"08911",
    "addr:street":"Carr Santiago Rusin\u0303Ol",
    "iso:country":"ES",
    "sg:address":"Carr Santiago Rusi\u00d1ol, 14",
    "sg:city":"Badalona",
    "sg:classifiers":[
        {
            "category":"Government",
            "subcategory":"Post Office",
            "type":"Public Place"
        }
    ],
    "sg:phone":"+34 933 89 52 48",
    "sg:postcode":"08911",
    "sg:province":"Barcelona",
    "sg:tags":[
        "de",
        "yoga",
        "clases"
    ],
    "wof:name":"Bernaus Sancho Francisco Javier",
    "wof:placetype":"venue"
},
  "geometry": {"coordinates":[2.2526750565,41.4515762329],"type":"Point"}
}