{
  "type": "Feature",
  "properties": {
    "iso:country":"ES",
    "sg:address":"Pg Maritim, 344",
    "sg:city":"Castelldefels",
    "sg:orig_category":"Restaurantes: Restauraci\u00d3n R\u00c1pida Y Autoservicio",
    "sg:phone":"+34 936 64 48 58",
    "sg:postcode":"08860",
    "sg:province":"Barcelona",
    "wof:name":"Diferent Castelldefels S.l.",
    "wof:placetype":"venue"
},
  "geometry": {"coordinates":[1.9544149637,41.2653503418],"type":"Point"}
}