{
  "type": "Feature",
  "properties": {
    "addr:full":"Calle de Casas De Campos, 3 Malaga M\u00e1laga 29001",
    "addr:housenumber":"3",
    "addr:postcode":"29001",
    "addr:street":"Calle De Casas;Campos;Ma\u0301Laga",
    "iso:country":"ES",
    "sg:address":"Calle de Casas De Campos, 3",
    "sg:city":"Malaga",
    "sg:orig_category":"Agentes Generales De Seguros",
    "sg:phone":"+34 952 22 21 78",
    "sg:postcode":"29001",
    "sg:province":"M\u00e1laga",
    "wof:name":"Ojeda Cervi\u00f1o Jose Ramon",
    "wof:placetype":"venue"
},
  "geometry": {"coordinates":[-4.4218554497,36.7164535522],"type":"Point"}
}