{
  "type": "Feature",
  "properties": {
    "iso:country":"ES",
    "sg:address":"Calle de Reyes Benitez, 19",
    "sg:city":"Moron Frontera",
    "sg:orig_category":"Reposter\u00cdas",
    "sg:phone":"+34 955 85 18 48",
    "sg:postcode":"41530",
    "sg:province":"Sevilla",
    "wof:name":"Panificadora Macias S.a.",
    "wof:placetype":"venue"
},
  "geometry": {"coordinates":[-5.4532389641,37.1173820496],"type":"Point"}
}