{
  "type": "Feature",
  "properties": {
    "addr:full":"Carrer de Doctor Calsina, 376 Terrassa Barcelona 08226",
    "addr:housenumber":"376",
    "addr:postcode":"08226",
    "addr:street":"Carrer De Doctor Calsina",
    "iso:country":"ES",
    "sg:address":"Carrer de Doctor Calsina, 376",
    "sg:city":"Terrassa",
    "sg:orig_category":"Platos Preparados Refrigerados (fabricaci\u00d3n, Al Por Mayor)",
    "sg:phone":"+34 937 35 76 99",
    "sg:postcode":"08226",
    "sg:province":"Barcelona",
    "wof:name":"Rosticeria Forte S.c.p",
    "wof:placetype":"venue"
},
  "geometry": {"coordinates":[2.0225939751,41.5774078369],"type":"Point"}
}