{
  "type": "Feature",
  "properties": {
    "addr:full":"Calle de Salvador De Madariaga, 2 Badajoz Badajoz 06011",
    "addr:housenumber":"2",
    "addr:postcode":"06011",
    "addr:street":"Calle De Salvador De Madariaga",
    "iso:country":"ES",
    "sg:address":"Calle de Salvador De Madariaga, 2",
    "sg:city":"Badajoz",
    "sg:orig_category":"Ingenier\u00cda, Centros De Estudios (diversos)",
    "sg:phone":"+34 924 24 80 45",
    "sg:postcode":"06011",
    "sg:province":"Badajoz",
    "wof:name":"Ingenieria Y Control Consultores S.l.",
    "wof:placetype":"venue"
},
  "geometry": {"coordinates":[-6.9845180511,38.8646659851],"type":"Point"}
}