{
  "type": "Feature",
  "properties": {
    "addr:full":"Calle de San Martin, 10 Eg\u00fces Navarra 31486",
    "addr:housenumber":"10",
    "addr:postcode":"31486",
    "addr:street":"Calle De San Martin",
    "iso:country":"ES",
    "sg:address":"Calle de San Martin, 10",
    "sg:city":"Eg\u00fces",
    "sg:classifiers":[
        {
            "category":"Communications",
            "type":"Services"
        }
    ],
    "sg:phone":"+34 948 33 32 65",
    "sg:postcode":"31486",
    "sg:province":"Navarra",
    "sg:tags":[
        "televisiones",
        "y",
        "radio"
    ],
    "wof:name":"Uniprex-onda Cero",
    "wof:placetype":"venue"
},
  "geometry": {"coordinates":[-1.5223180056,42.8062400818],"type":"Point"}
}