{
  "type": "Feature",
  "properties": {
    "iso:country":"ES",
    "sg:address":"Rua Carme, 11",
    "sg:city":"Ferrol",
    "sg:orig_category":"Cueros Y Pieles (al Por Mayor)",
    "sg:phone":"+34 981 35 44 68",
    "sg:postcode":"15402",
    "sg:province":"La Coru\u00f1a",
    "wof:name":"Ricoy Barciela Luz Maria",
    "wof:placetype":"venue"
},
  "geometry": {"coordinates":[-8.2305488586,43.4841194153],"type":"Point"}
}