{
  "type": "Feature",
  "properties": {
    "iso:country":"ES",
    "sg:address":"Barr San Xurxo, 7",
    "sg:city":"Centulle",
    "sg:orig_category":"Molduras, Junquillos, Listones Y Molduras Perforadas",
    "sg:phone":"+34 982 44 12 53",
    "sg:postcode":"27518",
    "sg:province":"Lugo",
    "wof:name":"Otero Dieguez Araceli",
    "wof:placetype":"venue"
},
  "geometry": {"coordinates":[-7.8486537933,42.6254386902],"type":"Point"}
}