{
  "type": "Feature",
  "properties": {
    "addr:full":"Calle de Dato, 7 Zaragoza Zaragoza 50005",
    "addr:housenumber":"7",
    "addr:postcode":"50005",
    "addr:street":"Calle De Dato",
    "iso:country":"ES",
    "sg:address":"Calle de Dato, 7",
    "sg:city":"Zaragoza",
    "sg:orig_category":"Alimentaci\u00d3n General (al Por Menor)",
    "sg:phone":"+34 976 23 55 21",
    "sg:postcode":"50005",
    "sg:province":"Zaragoza",
    "wof:name":"Ca\u00f1ada Garcia Antonio",
    "wof:placetype":"venue"
},
  "geometry": {"coordinates":[-0.8903471828,41.6458892822],"type":"Point"}
}