{
  "type": "Feature",
  "properties": {
    "addr:full":"Calle de Jacinto Benavente, S/n Vitoria-gasteiz \u00c1lava 01003",
    "addr:housenumber":"s / n",
    "addr:postcode":"01003",
    "addr:street":"Calle De Jacinto Benavente",
    "iso:country":"ES",
    "sg:address":"Calle de Jacinto Benavente, S/n",
    "sg:city":"Vitoria-gasteiz",
    "sg:orig_category":"Mec\u00c1nico Del Autom\u00d3vil",
    "sg:phone":"+34 945 28 88 10",
    "sg:postcode":"01003",
    "sg:province":"\u00c1lava",
    "wof:name":"Salgado Iglesias Jose",
    "wof:placetype":"venue"
},
  "geometry": {"coordinates":[-2.6583089828,42.8419494629],"type":"Point"}
}