{
  "type": "Feature",
  "properties": {
    "addr:full":"Carr Salvador Ferrer C. Maura, 25 Girona Girona 17003",
    "addr:housenumber":"25",
    "addr:postcode":"17003",
    "addr:street":"Carr Salvador Ferrer C. Maura",
    "iso:country":"ES",
    "sg:address":"Carr Salvador Ferrer C. Maura, 25",
    "sg:city":"Girona",
    "sg:orig_category":"Dise\u00d1o Industrial",
    "sg:phone":"+34 972 21 98 68",
    "sg:postcode":"17003",
    "sg:province":"Girona",
    "wof:name":"Vila-oliveres C.b",
    "wof:placetype":"venue"
},
  "geometry": {"coordinates":[2.8316919804,41.9649124146],"type":"Point"}
}