{
  "type": "Feature",
  "properties": {
    "iso:country":"ES",
    "sg:address":"Carrer de Paris, 46",
    "sg:city":"Barcelona",
    "sg:orig_category":"M\u00c9dicos: Dermatolog\u00cda Y Venereolog\u00cda",
    "sg:phone":"+34 934 39 18 53",
    "sg:postcode":"08029",
    "sg:province":"Barcelona",
    "wof:name":"Armengol Egea Pere",
    "wof:placetype":"venue"
},
  "geometry": {"coordinates":[2.1434051991,41.3862342834],"type":"Point"}
}