{
  "type": "Feature",
  "properties": {
    "iso:country":"ES",
    "sg:address":"Calle de Coso, 100",
    "sg:city":"Zaragoza",
    "sg:orig_category":"Asesor\u00cda Sobre Comunicaci\u00d3n De Empresas",
    "sg:phone":"+34 976 21 08 33",
    "sg:postcode":"50001",
    "sg:province":"Zaragoza",
    "sg:website":"www.rsc.es",
    "wof:name":"Redes Sistemas Y Comunicaciones S.l.",
    "wof:placetype":"venue"
},
  "geometry": {"coordinates":[-0.8770911098,41.6509399414],"type":"Point"}
}