{
  "type": "Feature",
  "properties": {
    "iso:country":"ES",
    "sg:address":"Plaz Gipuzkoa De, 2",
    "sg:city":"Donostia-san Sebastian",
    "sg:orig_category":"Ense\u00d1anza: Idiomas",
    "sg:phone":"+34 943 42 51 57",
    "sg:postcode":"20004",
    "sg:province":"Guip\u00f9zcoa",
    "sg:website":"www.tandemsansebastian.com",
    "wof:name":"Centro De Idiomas Donostia S.l.",
    "wof:placetype":"venue"
},
  "geometry": {"coordinates":[-1.9826589823,43.3213424683],"type":"Point"}
}