{
  "type": "Feature",
  "properties": {
    "iso:country":"ES",
    "sg:address":"Avda Carlota Alessandri, 127",
    "sg:city":"Torremolinos",
    "sg:orig_category":"Promotores Constructores",
    "sg:phone":"+34 952 05 60 87",
    "sg:postcode":"29620",
    "sg:province":"M\u00e1laga",
    "wof:name":"Ute Albergue Torremolinos",
    "wof:placetype":"venue"
},
  "geometry": {"coordinates":[-4.5135002136,36.6029281616],"type":"Point"}
}