{
  "type": "Feature",
  "properties": {
    "addr:full":"Barr Teyeres Les, Km. 0003,0 Langreo Asturias 33900",
    "addr:postcode":"33900",
    "addr:street":"Les Km. 0003,0",
    "iso:country":"ES",
    "sg:address":"Barr Teyeres Les, Km. 0003,0",
    "sg:city":"Langreo",
    "sg:orig_category":"Serrer\u00cdas De Madera",
    "sg:phone":"+34 985 67 87 09",
    "sg:postcode":"33900",
    "sg:province":"Asturias",
    "wof:name":"Paletizadora Asturiana S.l.",
    "wof:placetype":"venue"
},
  "geometry": {"coordinates":[-5.6692090034,43.2883987427],"type":"Point"}
}