{
  "type": "Feature",
  "properties": {
    "iso:country":"ES",
    "sg:address":"Avda Porvenir (del), 42",
    "sg:city":"Estepa",
    "sg:orig_category":"Material Y Herramientas Agr\u00cdcolas",
    "sg:phone":"+34 954 82 08 30",
    "sg:postcode":"41560",
    "sg:province":"Sevilla",
    "wof:name":"Talleres Agricolas San Miguel S.l.",
    "wof:placetype":"venue"
},
  "geometry": {"coordinates":[-4.873319149,37.2927398682],"type":"Point"}
}