{
  "type": "Feature",
  "properties": {
    "iso:country":"ES",
    "sg:address":"Calle de Chantada, 43",
    "sg:city":"Madrid",
    "sg:orig_category":"Molduras, Junquillos, Listones Y Molduras Perforadas",
    "sg:phone":"+34 913 86 27 06",
    "sg:postcode":"28035",
    "sg:province":"Madrid",
    "wof:name":"Garcia Gonzalez Serafin",
    "wof:placetype":"venue"
},
  "geometry": {"coordinates":[-3.7161245346,40.4732131958],"type":"Point"}
}