{
  "type": "Feature",
  "properties": {
    "addr:full":"Avda America, 52 Madrid Madrid 28028",
    "addr:housenumber":"52",
    "addr:postcode":"madrid;28028",
    "addr:street":"Avda America",
    "iso:country":"ES",
    "sg:address":"Avda America, 52",
    "sg:city":"Madrid",
    "sg:orig_category":"Cl\u00cdnicas Dentales",
    "sg:phone":"+34 913 56 74 20",
    "sg:postcode":"28028",
    "sg:province":"Madrid",
    "wof:name":"Dentconfor S.l.",
    "wof:placetype":"venue"
},
  "geometry": {"coordinates":[-3.6649560928,40.4423408508],"type":"Point"}
}