{
  "type": "Feature",
  "properties": {
    "iso:country":"ES",
    "sg:address":"Calle de Fontan, 15",
    "sg:city":"Oviedo",
    "sg:orig_category":"Loter\u00cda Y T\u00d3mbola",
    "sg:phone":"+34 985 21 77 56",
    "sg:postcode":"33009",
    "sg:province":"Asturias",
    "wof:name":"Llavona Uribelarrea Maria Lila",
    "wof:placetype":"venue"
},
  "geometry": {"coordinates":[-5.8460121155,43.35987854],"type":"Point"}
}