{
  "type": "Feature",
  "properties": {
    "iso:country":"ES",
    "sg:address":"Calle de Doctor Don Luis Bilbao Libano, 11",
    "sg:city":"Elexalde",
    "sg:orig_category":"Venta, Colocaci\u00d3n, Reparaci\u00d3n De Radiadores Para Veh\u00cdculos",
    "sg:phone":"+34 944 63 40 07",
    "sg:postcode":"48940",
    "sg:province":"Vizcaya",
    "wof:name":"Valeo Services Espa\u00f1a S.a.",
    "wof:placetype":"venue"
},
  "geometry": {"coordinates":[-2.9857969284,43.3233451843],"type":"Point"}
}