{
  "type": "Feature",
  "properties": {
    "iso:country":"ES",
    "sg:address":"Avda De Rosalia De Castro, 2",
    "sg:city":"Ponteareas",
    "sg:orig_category":"Arquitectos",
    "sg:phone":"+34 986 64 26 90",
    "sg:postcode":"36860",
    "sg:province":"Pontevedra",
    "wof:name":"Pe\u00f1a Alvarez Guillermo",
    "wof:placetype":"venue"
},
  "geometry": {"coordinates":[-8.5163888931,42.1783599854],"type":"Point"}
}