{
  "type": "Feature",
  "properties": {
    "iso:country":"ES",
    "sg:address":"Calle de Parque De Do\u00d1ana, 63",
    "sg:city":"Vaguadas",
    "sg:orig_category":"Ingenier\u00cda, Centros De Estudios (diversos)",
    "sg:phone":"+34 924 26 14 27",
    "sg:postcode":"06010",
    "sg:province":"Badajoz",
    "wof:name":"Due\u00f1as Gomez Andres",
    "wof:placetype":"venue"
},
  "geometry": {"coordinates":[-6.9776391983,38.8408203125],"type":"Point"}
}