{
  "type": "Feature",
  "properties": {
    "iso:country":"ES",
    "sg:address":"Calle de Rodriguez Sanchez, 9",
    "sg:city":"Cordoba",
    "sg:orig_category":"M\u00c9dicos: Psiquiatr\u00cda",
    "sg:phone":"+34 957 48 52 12",
    "sg:postcode":"14003",
    "sg:province":"C\u00f3rdoba",
    "wof:name":"Mata Cala Francisco Ignacio",
    "wof:placetype":"venue"
},
  "geometry": {"coordinates":[-4.7804760933,37.8831138611],"type":"Point"}
}