{
  "type": "Feature",
  "properties": {
    "addr:full":"Carr Mar, S/n Castello D'empuries Girona 17486",
    "addr:postcode":"17486",
    "addr:street":"Carr Mar S / N;D'Empuries",
    "iso:country":"ES",
    "sg:address":"Carr Mar, S/n",
    "sg:city":"Castello D'empuries",
    "sg:orig_category":"Empresas De Carpinter\u00cda",
    "sg:phone":"+34 972 15 61 63",
    "sg:postcode":"17486",
    "sg:province":"Girona",
    "wof:name":"Gironell Puig Pere",
    "wof:placetype":"venue"
},
  "geometry": {"coordinates":[3.1170799732,42.139251709],"type":"Point"}
}