{
  "type": "Feature",
  "properties": {
    "iso:country":"ES",
    "sg:address":"Avda Antibioticos, 104",
    "sg:city":"Armunia",
    "sg:orig_category":"Distribuci\u00d3n De Petr\u00d3leo Y Derivados",
    "sg:phone":"+34 987 25 07 09",
    "sg:postcode":"24009",
    "sg:province":"Le\u00f3n",
    "wof:name":"Agip Espa\u00d1a S.a.",
    "wof:placetype":"venue"
},
  "geometry": {"coordinates":[-5.5837569237,42.5806884766],"type":"Point"}
}