{
  "type": "Feature",
  "properties": {
    "addr:full":"Calle de Leon, 2 Valladolid Valladolid 47003",
    "addr:housenumber":"2",
    "addr:postcode":"47003",
    "addr:street":"Calle De Leon",
    "iso:country":"ES",
    "sg:address":"Calle de Leon, 2",
    "sg:city":"Valladolid",
    "sg:orig_category":"Arquitectos",
    "sg:phone":"+34 983 37 13 83",
    "sg:postcode":"47003",
    "sg:province":"Valladolid",
    "wof:name":"Arquidimop 93 S.l.",
    "wof:placetype":"venue"
},
  "geometry": {"coordinates":[-4.7269291878,41.6553459167],"type":"Point"}
}