{
  "type": "Feature",
  "properties": {
    "addr:full":"Pase Mikeletegi De, 12 Donostia-san Sebastian Guip\u00f9zcoa 20009",
    "addr:housenumber":"12",
    "addr:postcode":"20009",
    "iso:country":"ES",
    "sg:address":"Pase Mikeletegi De, 12",
    "sg:city":"Donostia-san Sebastian",
    "sg:orig_category":"Asilos De Ancianos. Centros Privados",
    "sg:phone":"+34 943 30 93 10",
    "sg:postcode":"20009",
    "sg:province":"Guip\u00f9zcoa",
    "wof:name":"Sanitas Residencial Pais Vasco S.a.",
    "wof:placetype":"venue"
},
  "geometry": {"coordinates":[-1.9794000387,43.3173789978],"type":"Point"}
}