{
  "type": "Feature",
  "properties": {
    "iso:country":"ES",
    "sg:address":"Calle de Trinidad, 14",
    "sg:city":"Toledo",
    "sg:orig_category":"Artesan\u00cda",
    "sg:phone":"+34 925 21 13 38",
    "sg:postcode":"45002",
    "sg:province":"Toledo",
    "wof:name":"Diaz Fernandez Fernando",
    "wof:placetype":"venue"
},
  "geometry": {"coordinates":[-4.0258488655,39.8572425842],"type":"Point"}
}