{
  "type": "Feature",
  "properties": {
    "addr:full":"Chapitela-txapitela Kalea, 13 Iru\u00f1a Navarra 31001",
    "addr:housenumber":"13",
    "addr:postcode":"31001",
    "addr:street":"Chapitela-Txapitela Kalea",
    "iso:country":"ES",
    "sg:address":"Chapitela-txapitela Kalea, 13",
    "sg:city":"Iru\u00f1a",
    "sg:orig_category":"Ropa Para Se\u00d1oras (al Por Menor)",
    "sg:phone":"+34 948 22 35 86",
    "sg:postcode":"31001",
    "sg:province":"Navarra",
    "wof:name":"Carrera Rabago Jorge",
    "wof:placetype":"venue"
},
  "geometry": {"coordinates":[-1.6429009438,42.8179702759],"type":"Point"}
}