{
  "type": "Feature",
  "properties": {
    "iso:country":"ES",
    "sg:address":"Calle de Paraiso, 11",
    "sg:city":"Valladolid",
    "sg:orig_category":"Carros Elevadores, Carros De Operaciones Portuarias",
    "sg:phone":"+34 983 25 49 63",
    "sg:postcode":"47003",
    "sg:province":"Valladolid",
    "wof:name":"Carretillas Mayor S.a.",
    "wof:placetype":"venue"
},
  "geometry": {"coordinates":[-4.720012188,41.6546592712],"type":"Point"}
}