{
  "type": "Feature",
  "properties": {
    "iso:country":"ES",
    "sg:address":"Carr Sant Antoni, 2",
    "sg:city":"Palamos",
    "sg:classifiers":[
        {
            "category":"Arts & Performance",
            "subcategory":"Art Gallery",
            "type":"Entertainment"
        }
    ],
    "sg:phone":"+34 972 31 73 28",
    "sg:postcode":"17230",
    "sg:province":"Girona",
    "sg:tags":[
        "arte",
        "de",
        "galer\u00cdas"
    ],
    "wof:name":"Payet Corominas Carme",
    "wof:placetype":"venue"
},
  "geometry": {"coordinates":[3.1288781166,41.8493423462],"type":"Point"}
}