{
  "type": "Feature",
  "properties": {
    "addr:full":"Pase Pilar Coloma, 23 Las Villas Castell\u00f3n 12560",
    "addr:housenumber":"23",
    "addr:postcode":"12560",
    "addr:street":"Coloma;Castello\u0301N",
    "iso:country":"ES",
    "sg:address":"Pase Pilar Coloma, 23",
    "sg:city":"Las Villas",
    "sg:orig_category":"Fabricaci\u00d3n, Reparaci\u00d3n Y Mantenimiento De Construcciones Navales Y Fluviales",
    "sg:phone":"+34 964 30 20 93",
    "sg:postcode":"12560",
    "sg:province":"Castell\u00f3n",
    "sg:website":"www.locotractor.com",
    "wof:name":"Importadora Y Distribuidora De Maquinaria Industrial Zephir S.l.",
    "wof:placetype":"venue"
},
  "geometry": {"coordinates":[0.0590550005,40.0523414612],"type":"Point"}
}