{
  "type": "Feature",
  "properties": {
    "iso:country":"ES",
    "sg:address":"Calle de Cid, 8",
    "sg:city":"Castromonte",
    "sg:orig_category":"Agricultores, Agricultores",
    "sg:phone":"+34 983 56 66 58",
    "sg:postcode":"47641",
    "sg:province":"Valladolid",
    "wof:name":"Martin Romo Diego",
    "wof:placetype":"venue"
},
  "geometry": {"coordinates":[-5.0412917137,41.7731285095],"type":"Point"}
}