{
  "type": "Feature",
  "properties": {
    "iso:country":"ES",
    "sg:address":"Rua Garcia Olloqui, 3",
    "sg:city":"Vigo",
    "sg:orig_category":"Agencias De Aduana",
    "sg:phone":"+34 986 22 10 67",
    "sg:postcode":"36201",
    "sg:province":"Pontevedra",
    "wof:name":"Jesus De Labra Y Hermanos S. R. C.",
    "wof:placetype":"venue"
},
  "geometry": {"coordinates":[-8.7242441177,42.2396430969],"type":"Point"}
}