{
  "type": "Feature",
  "properties": {
    "addr:full":"Calle de Leon Y Castillo, 89 Palmas De Gran Canaria Las Palmas 35004",
    "addr:postcode":"35004",
    "addr:street":"Calle De Leon Y Castillo 89",
    "iso:country":"ES",
    "sg:address":"Calle de Leon Y Castillo, 89",
    "sg:city":"Palmas De Gran Canaria",
    "sg:orig_category":"Centros Empresariales",
    "sg:phone":"+34 928 23 35 06",
    "sg:postcode":"35004",
    "sg:province":"Las Palmas",
    "wof:name":"Federacion Provincial De Empresarios De Madera Y Corcho",
    "wof:placetype":"venue"
},
  "geometry": {"coordinates":[-15.4204502106,28.114397049],"type":"Point"}
}