{
  "type": "Feature",
  "properties": {
    "addr:full":"Calle de Tetuan, 5 Sevilla Sevilla 41001",
    "addr:housenumber":"5",
    "addr:postcode":"41001",
    "addr:street":"Calle De Tetuan",
    "iso:country":"ES",
    "sg:address":"Calle de Tetuan, 5",
    "sg:city":"Sevilla",
    "sg:orig_category":"Abogados",
    "sg:phone":"+34 954 22 95 12",
    "sg:postcode":"41001",
    "sg:province":"Sevilla",
    "wof:name":"Anadaluza Tecnica De Seguros S.l.",
    "wof:placetype":"venue"
},
  "geometry": {"coordinates":[-5.9950051308,37.3894729614],"type":"Point"}
}