{
  "type": "Feature",
  "properties": {
    "addr:full":"Plaz Espa\u00d1a, 1 Morera Badajoz 06176",
    "addr:housenumber":"1",
    "addr:postcode":"06176",
    "addr:street":"Plaz Espan\u0303A",
    "iso:country":"ES",
    "sg:address":"Plaz Espa\u00d1a, 1",
    "sg:city":"Morera",
    "sg:orig_category":"Administraciones Regionales, Departamentales Y Locales",
    "sg:phone":"+34 924 69 61 36",
    "sg:postcode":"06176",
    "sg:province":"Badajoz",
    "wof:name":"Ayuntamiento De La Morera",
    "wof:placetype":"venue"
},
  "geometry": {"coordinates":[-6.6228318214,38.5267791748],"type":"Point"}
}