{
  "type": "Feature",
  "properties": {
    "addr:full":"Calle de Jose De Cadalso, 62 Madrid Madrid 28044",
    "addr:housenumber":"62",
    "addr:postcode":"madrid;28044",
    "addr:street":"Calle De Jose De Cadalso",
    "iso:country":"ES",
    "sg:address":"Calle de Jose De Cadalso, 62",
    "sg:city":"Madrid",
    "sg:orig_category":"Supermercados Y Hipermercados",
    "sg:phone":"+34 917 10 63 53",
    "sg:postcode":"28044",
    "sg:province":"Madrid",
    "wof:name":"Distribuidora Internacional De Alimentacion S.a.",
    "wof:placetype":"venue"
},
  "geometry": {"coordinates":[-3.768239975,40.3760032654],"type":"Point"}
}