{
  "type": "Feature",
  "properties": {
    "iso:country":"ES",
    "sg:address":"Avda Rafael Cabrera, 1",
    "sg:city":"Palmas De Gran Canaria",
    "sg:orig_category":"Asesor\u00cda De Formaci\u00d3n Y Gesti\u00d3n De Personal",
    "sg:phone":"+34 928 36 60 55",
    "sg:postcode":"35002",
    "sg:province":"Las Palmas",
    "wof:name":"Artiles Santana Francisco",
    "wof:placetype":"venue"
},
  "geometry": {"coordinates":[-15.4143600464,28.1051502228],"type":"Point"}
}