{
  "type": "Feature",
  "properties": {
    "iso:country":"ES",
    "sg:address":"Peirao, S/n",
    "sg:city":"Ribeira-santa Uxia",
    "sg:orig_category":"Distribuci\u00d3n De Petr\u00d3leo Y Derivados",
    "sg:phone":"+34 981 87 87 76",
    "sg:postcode":"15960",
    "sg:province":"La Coru\u00f1a",
    "wof:name":"Fuel Galicia S.l.",
    "wof:placetype":"venue"
},
  "geometry": {"coordinates":[-8.9892187119,42.553653717],"type":"Point"}
}