{
  "type": "Feature",
  "properties": {
    "iso:country":"ES",
    "sg:address":"Avda Padre Garcia Tejero, 43",
    "sg:city":"Sevilla",
    "sg:orig_category":"Agencias Y Agentes Comerciales, Representantes",
    "sg:phone":"+34 954 62 28 47",
    "sg:postcode":"41012",
    "sg:province":"Sevilla",
    "wof:name":"Garcia Arjona Francisco",
    "wof:placetype":"venue"
},
  "geometry": {"coordinates":[-5.9884338379,37.3549423218],"type":"Point"}
}