{
  "type": "Feature",
  "properties": {
    "addr:full":"Carrer de Salut, 81 Sabadell Barcelona 08202",
    "addr:housenumber":"81",
    "addr:postcode":"08202",
    "addr:street":"Carrer De Salut",
    "iso:country":"ES",
    "sg:address":"Carrer de Salut, 81",
    "sg:city":"Sabadell",
    "sg:orig_category":"Pescader\u00cdas (al Por Menor)",
    "sg:phone":"+34 937 27 53 33",
    "sg:postcode":"08202",
    "sg:province":"Barcelona",
    "wof:name":"Querol Simon Francisco",
    "wof:placetype":"venue"
},
  "geometry": {"coordinates":[2.1104049683,41.5510139465],"type":"Point"}
}