{
  "type": "Feature",
  "properties": {
    "addr:full":"Avda America, 37 Madrid Madrid 28002",
    "addr:housenumber":"37",
    "addr:postcode":"madrid;28002",
    "addr:street":"Avda America",
    "iso:country":"ES",
    "sg:address":"Avda America, 37",
    "sg:city":"Madrid",
    "sg:orig_category":"Arquitectos",
    "sg:phone":"+34 914 16 42 10",
    "sg:postcode":"28002",
    "sg:province":"Madrid",
    "wof:name":"Urgoiti Soriano Nicolas",
    "wof:placetype":"venue"
},
  "geometry": {"coordinates":[-3.6725790501,40.4393997192],"type":"Point"}
}