{
  "type": "Feature",
  "properties": {
    "addr:full":"Rua Concello, 3 Cabanas La Coru\u00f1a 15621",
    "addr:housenumber":"3",
    "addr:postcode":"15621",
    "addr:street":"Rua Concello;La Corun\u0303A",
    "iso:country":"ES",
    "sg:address":"Rua Concello, 3",
    "sg:city":"Cabanas",
    "sg:orig_category":"Administraciones Regionales, Departamentales Y Locales",
    "sg:phone":"+34 981 43 10 07",
    "sg:postcode":"15621",
    "sg:province":"La Coru\u00f1a",
    "wof:name":"Ayuntamiento De Cabanas",
    "wof:placetype":"venue"
},
  "geometry": {"coordinates":[-8.1625156403,43.4736061096],"type":"Point"}
}