{
  "type": "Feature",
  "properties": {
    "addr:full":"Ctra. Alzira-valencia, S/n Almussafes Valencia 46440",
    "addr:housenumber":"s / n",
    "addr:postcode":"46440",
    "addr:street":"Ctra. Alzira-Valencia",
    "iso:country":"ES",
    "sg:address":"Ctra. Alzira-valencia, S/n",
    "sg:city":"Almussafes",
    "sg:orig_category":"Poller\u00cda Y Caza (al Por Menor)",
    "sg:phone":"+34 961 78 20 98",
    "sg:postcode":"46440",
    "sg:province":"Valencia",
    "wof:name":"Perera Climent Arturo",
    "wof:placetype":"venue"
},
  "geometry": {"coordinates":[-0.4112789929,39.2958984375],"type":"Point"}
}