{
  "type": "Feature",
  "properties": {
    "addr:full":"Avda Pasajes San Pedro, 51 Donostia-san Sebastian Guip\u00f9zcoa 20017",
    "addr:housenumber":"51",
    "addr:postcode":"20017",
    "addr:street":"Avda Pasajes San Pedro",
    "iso:country":"ES",
    "sg:address":"Avda Pasajes San Pedro, 51",
    "sg:city":"Donostia-san Sebastian",
    "sg:orig_category":"Fotograf\u00cda Y Cine: Aparatos, Pel\u00cdculas Y Accesorios (al Por Menor)",
    "sg:phone":"+34 943 39 60 72",
    "sg:postcode":"20017",
    "sg:province":"Guip\u00f9zcoa",
    "wof:name":"Cabrera Dominguez Andres",
    "wof:placetype":"venue"
},
  "geometry": {"coordinates":[-1.9794000387,43.3173789978],"type":"Point"}
}