{
  "type": "Feature",
  "properties": {
    "addr:full":"Rond Nelle, 16 Coru\u00d1a La Coru\u00f1a 15005",
    "addr:housenumber":"16",
    "addr:postcode":"15005",
    "addr:street":"Rond Nelle;La Corun\u0303A",
    "iso:country":"ES",
    "sg:address":"Rond Nelle, 16",
    "sg:city":"Coru\u00d1a",
    "sg:orig_category":"Procuradores",
    "sg:phone":"+34 981 24 50 14",
    "sg:postcode":"15005",
    "sg:province":"La Coru\u00f1a",
    "wof:name":"Reyes Paz Alejandro",
    "wof:placetype":"venue"
},
  "geometry": {"coordinates":[-8.4108200073,43.3608703613],"type":"Point"}
}