{
  "type": "Feature",
  "properties": {
    "addr:full":"Calle de Hockey, 24 Sevilla Sevilla 41020",
    "addr:housenumber":"24",
    "addr:postcode":"41020",
    "addr:street":"Calle De Hockey",
    "iso:country":"ES",
    "sg:address":"Calle de Hockey, 24",
    "sg:city":"Sevilla",
    "sg:orig_category":"Farmacias",
    "sg:phone":"+34 954 40 81 67",
    "sg:postcode":"41020",
    "sg:province":"Sevilla",
    "wof:name":"Sanchez Varilla Josefa",
    "wof:placetype":"venue"
},
  "geometry": {"coordinates":[-5.916364193,37.3894958496],"type":"Point"}
}