{
  "type": "Feature",
  "properties": {
    "iso:country":"ES",
    "sg:address":"San Fermin, 18",
    "sg:city":"Iru\u00f1a",
    "sg:orig_category":"Iglesia Cat\u00d3lica",
    "sg:phone":"+34 948 23 97 39",
    "sg:postcode":"31003",
    "sg:province":"Navarra",
    "wof:name":"Parroquia San Miguel",
    "wof:placetype":"venue"
},
  "geometry": {"coordinates":[-1.6399879456,42.8117408752],"type":"Point"}
}