{
  "type": "Feature",
  "properties": {
    "iso:country":"ES",
    "sg:address":"Carr Sant Roc, S/n",
    "sg:city":"Mao",
    "sg:orig_category":"Asociaciones Humanitarias, De Cooperaci\u00d3n, De Acci\u00d3n Social",
    "sg:phone":"+34 971 35 20 95",
    "sg:postcode":"07701",
    "sg:province":"Islas Baleares",
    "wof:name":"Asociacion De Familiares De Enfermos De Alzheimer",
    "wof:placetype":"venue"
},
  "geometry": {"coordinates":[4.2687525749,39.8887672424],"type":"Point"}
}