{
  "type": "Feature",
  "properties": {
    "addr:full":"Carrer de Ciutat D'asuncion, 30 Barcelona Barcelona 08030",
    "addr:housenumber":"30",
    "addr:postcode":"08030",
    "addr:street":"Carrer De Ciutat D'Asuncion",
    "iso:country":"ES",
    "sg:address":"Carrer de Ciutat D'asuncion, 30",
    "sg:city":"Barcelona",
    "sg:orig_category":"Transporte En General",
    "sg:phone":"+34 933 46 04 43",
    "sg:postcode":"08030",
    "sg:province":"Barcelona",
    "wof:name":"New Cina Import S.l.",
    "wof:placetype":"venue"
},
  "geometry": {"coordinates":[2.2003257275,41.4396400452],"type":"Point"}
}