{
  "type": "Feature",
  "properties": {
    "addr:full":"Avda Reina Victoria, 32 Madrid Madrid 28003",
    "addr:housenumber":"32",
    "addr:postcode":"madrid;28003",
    "addr:street":"Avda Reina Victoria",
    "iso:country":"ES",
    "sg:address":"Avda Reina Victoria, 32",
    "sg:city":"Madrid",
    "sg:orig_category":"Cajas De Ahorro",
    "sg:phone":"+34 915 34 11 75",
    "sg:postcode":"28003",
    "sg:province":"Madrid",
    "sg:website":"www.caixacatalunya.es",
    "wof:name":"Caixa D'estalvis De Catalunya",
    "wof:placetype":"venue"
},
  "geometry": {"coordinates":[-3.7103600502,40.4469871521],"type":"Point"}
}