{
  "type": "Feature",
  "properties": {
    "iso:country":"ES",
    "sg:address":"Gazta\u00d1adui Kalea, 21",
    "sg:city":"Eskoriatza",
    "sg:orig_category":"Ropa Para Ni\u00d1os (al Por Menor)",
    "sg:phone":"+34 943 71 53 87",
    "sg:postcode":"20540",
    "sg:province":"Guip\u00f9zcoa",
    "wof:name":"Josune Zubia Atxaga Y Otra , C.b",
    "wof:placetype":"venue"
},
  "geometry": {"coordinates":[-2.526072979,43.0183639526],"type":"Point"}
}