{
  "type": "Feature",
  "properties": {
    "iso:country":"ES",
    "sg:address":"Av Mistral, 45",
    "sg:city":"Barcelona",
    "sg:orig_category":"Psic\u00d3logos",
    "sg:phone":"+34 934 23 42 29",
    "sg:postcode":"08015",
    "sg:province":"Barcelona",
    "wof:name":"Castell Esteller Ana",
    "wof:placetype":"venue"
},
  "geometry": {"coordinates":[2.15634799,41.3763237],"type":"Point"}
}