{
  "type": "Feature",
  "properties": {
    "addr:full":"Carrer de Maria Aguilo, 38 Barcelona Barcelona 08005",
    "addr:housenumber":"38",
    "addr:postcode":"08005",
    "addr:street":"Carrer De Maria Aguilo",
    "iso:country":"ES",
    "sg:address":"Carrer de Maria Aguilo, 38",
    "sg:city":"Barcelona",
    "sg:orig_category":"Electricidad: Instaladores",
    "sg:phone":"+34 933 00 63 89",
    "sg:postcode":"08005",
    "sg:province":"Barcelona",
    "wof:name":"Ubach S.a.",
    "wof:placetype":"venue"
},
  "geometry": {"coordinates":[2.2005550861,41.4028205872],"type":"Point"}
}