{
  "type": "Feature",
  "properties": {
    "addr:full":"Calle de Alfredo Marquerie, 3 Madrid Madrid 28034",
    "addr:housenumber":"3",
    "addr:postcode":"28034",
    "addr:street":"Calle De Alfredo Marquerie",
    "iso:country":"ES",
    "sg:address":"Calle de Alfredo Marquerie, 3",
    "sg:city":"Madrid",
    "sg:orig_category":"Asesor\u00cda Sobre Comunicaci\u00d3n De Empresas",
    "sg:phone":"+34 917 30 81 26",
    "sg:postcode":"28034",
    "sg:province":"Madrid",
    "wof:name":"Arauber Consultores S.l.",
    "wof:placetype":"venue"
},
  "geometry": {"coordinates":[-3.6966228485,40.4865188599],"type":"Point"}
}