{
  "type": "Feature",
  "properties": {
    "addr:full":"Calle de Antolin Lopez Pelaez, 33 Ponferrada Le\u00f3n 24400",
    "addr:housenumber":"33",
    "addr:postcode":"24400",
    "addr:street":"Calle De Antolin Lopez Pelaez",
    "iso:country":"ES",
    "sg:address":"Calle de Antolin Lopez Pelaez, 33",
    "sg:city":"Ponferrada",
    "sg:orig_category":"Ropa Para Se\u00d1oras Y Caballeros (al Por Menor)",
    "sg:phone":"+34 987 42 47 86",
    "sg:postcode":"24400",
    "sg:province":"Le\u00f3n",
    "wof:name":"Gezan S.l.",
    "wof:placetype":"venue"
},
  "geometry": {"coordinates":[-6.6014437675,42.5469589233],"type":"Point"}
}