{
  "type": "Feature",
  "properties": {
    "iso:country":"ES",
    "sg:address":"Plaz Calvo Sotelo, S/n",
    "sg:city":"Fuentes Nava",
    "sg:orig_category":"Administraciones Regionales, Departamentales Y Locales",
    "sg:phone":"+34 979 84 20 49",
    "sg:postcode":"34337",
    "sg:province":"Palencia",
    "wof:name":"Ayuntamiento",
    "wof:placetype":"venue"
},
  "geometry": {"coordinates":[-4.7827353477,42.0830993652],"type":"Point"}
}