{
  "type": "Feature",
  "properties": {
    "addr:full":"Calle de General Vara De Rey, 83 Logro\u00f1o La Rioja 26006",
    "addr:housenumber":"83",
    "addr:postcode":"26006",
    "addr:street":"Calle De General Vara De Rey;Rioja",
    "iso:country":"ES",
    "sg:address":"Calle de General Vara De Rey, 83",
    "sg:city":"Logro\u00f1o",
    "sg:orig_category":"M\u00c9dicos: Medicina General Orientada A La Acupuntura",
    "sg:phone":"+34 941 22 53 75",
    "sg:postcode":"26006",
    "sg:province":"La Rioja",
    "wof:name":"Cerdeira Alonso Juan Ramon",
    "wof:placetype":"venue"
},
  "geometry": {"coordinates":[-2.4473700523,42.4562644958],"type":"Point"}
}