{
  "type": "Feature",
  "properties": {
    "iso:country":"ES",
    "sg:address":"Praz Maior, 13",
    "sg:city":"Lugo",
    "sg:orig_category":"Estancos",
    "sg:phone":"+34 982 22 81 03",
    "sg:postcode":"27001",
    "sg:province":"Lugo",
    "wof:name":"Goy Palombi Luz",
    "wof:placetype":"venue"
},
  "geometry": {"coordinates":[-7.5569701195,43.0100097656],"type":"Point"}
}