{
  "type": "Feature",
  "properties": {
    "addr:full":"Calle de Casas De Abajo, S/n Valle S. Lorenzo Santa Cruz De Tenerife 38626",
    "addr:housenumber":"s",
    "addr:postcode":"38626",
    "addr:street":"Calle De Casas;Abajo;/ N Valle S. Lorenzo",
    "iso:country":"ES",
    "sg:address":"Calle de Casas De Abajo, S/n",
    "sg:city":"Valle S. Lorenzo",
    "sg:orig_category":"Congelados: Productos Alimentarios (al Por Menor)",
    "sg:phone":"+34 922 76 51 94",
    "sg:postcode":"38626",
    "sg:province":"Santa Cruz De Tenerife",
    "wof:name":"Cabrera Hernandez Miguelina",
    "wof:placetype":"venue"
},
  "geometry": {"coordinates":[-16.6544456482,28.0871887207],"type":"Point"}
}