{
  "type": "Feature",
  "properties": {
    "addr:full":"C/ Lluis Braille, 13 Alcoi Alicante 03802",
    "addr:housenumber":"13",
    "addr:postcode":"03802",
    "addr:street":"C / Lluis Braille",
    "iso:country":"ES",
    "sg:address":"C/ Lluis Braille, 13",
    "sg:city":"Alcoi",
    "sg:orig_category":"Reposter\u00cdas",
    "sg:phone":"+34 966 52 32 06",
    "sg:postcode":"03802",
    "sg:province":"Alicante",
    "wof:name":"Jose Antonio Cortes Cerda S.l.",
    "wof:placetype":"venue"
},
  "geometry": {"coordinates":[-0.4860819876,38.6975288391],"type":"Point"}
}