{
  "type": "Feature",
  "properties": {
    "iso:country":"ES",
    "sg:address":"Carrer de Dante Alighieri, 1",
    "sg:city":"Barcelona",
    "sg:orig_category":"Lencer\u00cda Femenina, Corseter\u00cda, Trajes De Ba\u00d1o (al Por Menor)",
    "sg:phone":"+34 934 29 86 57",
    "sg:postcode":"08032",
    "sg:province":"Barcelona",
    "wof:name":"Lanzas Lopez Dolores",
    "wof:placetype":"venue"
},
  "geometry": {"coordinates":[2.1623659134,41.4290275574],"type":"Point"}
}