{
  "type": "Feature",
  "properties": {
    "addr:full":"Carrer de Notari Rull, 15 Reus Tarragona 43205",
    "addr:housenumber":"15",
    "addr:postcode":"43205",
    "addr:street":"Carrer De Notari Rull",
    "iso:country":"ES",
    "sg:address":"Carrer de Notari Rull, 15",
    "sg:city":"Reus",
    "sg:orig_category":"Molduras, Junquillos, Listones Y Molduras Perforadas",
    "sg:phone":"+34 977 75 00 38",
    "sg:postcode":"43205",
    "sg:province":"Tarragona",
    "wof:name":"Morales Espinosa Dolores",
    "wof:placetype":"venue"
},
  "geometry": {"coordinates":[1.1175580025,41.1381874084],"type":"Point"}
}