{
  "type": "Feature",
  "properties": {
    "iso:country":"ES",
    "sg:address":"Calle de Alcalde Sainz De Baranda, 53",
    "sg:city":"Madrid",
    "sg:orig_category":"Bazares, Art\u00cdculos De Limpieza Y De Cocina (al Por Menor)",
    "sg:phone":"+34 914 09 47 91",
    "sg:postcode":"28009",
    "sg:province":"Madrid",
    "wof:name":"Kepeng  Xu",
    "wof:placetype":"venue"
},
  "geometry": {"coordinates":[-3.6711719036,40.4167251587],"type":"Point"}
}