{
  "type": "Feature",
  "properties": {
    "addr:full":"Calle de Buen Juez, 25 Piedrahita \u00c1vila 05500",
    "addr:housenumber":"25",
    "addr:postcode":"05500",
    "addr:street":"Calle De Buen Juez",
    "iso:country":"ES",
    "sg:address":"Calle de Buen Juez, 25",
    "sg:city":"Piedrahita",
    "sg:orig_category":"Carnicer\u00cdas, Carnicer\u00cdas",
    "sg:phone":"+34 920 36 00 70",
    "sg:postcode":"05500",
    "sg:province":"\u00c1vila",
    "wof:name":"Carniceria El Valle C.b.",
    "wof:placetype":"venue"
},
  "geometry": {"coordinates":[-5.3269701004,40.4655303955],"type":"Point"}
}