{
  "type": "Feature",
  "properties": {
    "addr:full":"Plaz San Pedro, 1 Alcantarilla Murcia 30820",
    "addr:housenumber":"1",
    "addr:postcode":"30820",
    "addr:street":"Plaz San Pedro",
    "iso:country":"ES",
    "sg:address":"Plaz San Pedro, 1",
    "sg:city":"Alcantarilla",
    "sg:orig_category":"Iglesia Cat\u00d3lica",
    "sg:phone":"+34 968 89 29 29",
    "sg:postcode":"30820",
    "sg:province":"Murcia",
    "wof:name":"Obispado De Cartagena",
    "wof:placetype":"venue"
},
  "geometry": {"coordinates":[-1.2115750313,37.96717453],"type":"Point"}
}