{
  "type": "Feature",
  "properties": {
    "addr:full":"Calle de Mayor, 38 Munera Albacete 02612",
    "addr:housenumber":"38",
    "addr:postcode":"02612",
    "addr:street":"Calle De Mayor",
    "iso:country":"ES",
    "sg:address":"Calle de Mayor, 38",
    "sg:city":"Munera",
    "sg:orig_category":"Distribuci\u00d3n De Petr\u00d3leo Y Derivados",
    "sg:phone":"+34 967 37 30 88",
    "sg:postcode":"02612",
    "sg:province":"Albacete",
    "wof:name":"Consum Sociedad Cooperativa Limitada",
    "wof:placetype":"venue"
},
  "geometry": {"coordinates":[-2.4799349308,39.0402183533],"type":"Point"}
}