{
  "type": "Feature",
  "properties": {
    "iso:country":"ES",
    "sg:address":"Cra Santa Creu De Calafell, 9",
    "sg:city":"Gava",
    "sg:orig_category":"Molduras, Junquillos, Listones Y Molduras Perforadas",
    "sg:phone":"+34 936 62 00 32",
    "sg:postcode":"08850",
    "sg:province":"Barcelona",
    "wof:name":"Valero Mellado Juan",
    "wof:placetype":"venue"
},
  "geometry": {"coordinates":[2.0112679005,41.3061141968],"type":"Point"}
}