{
  "type": "Feature",
  "properties": {
    "addr:full":"General-bidenagusia, 7 Elexalde Vizcaya 48620",
    "addr:housenumber":"7",
    "addr:postcode":"48620",
    "addr:street":"General-Bidenagusia",
    "iso:country":"ES",
    "sg:address":"General-bidenagusia, 7",
    "sg:city":"Elexalde",
    "sg:orig_category":"Asilos De Ancianos. Centros Privados",
    "sg:phone":"+34 946 77 44 77",
    "sg:postcode":"48620",
    "sg:province":"Vizcaya",
    "wof:name":"Inmobiliaria Barrika-barri S.a.",
    "wof:placetype":"venue"
},
  "geometry": {"coordinates":[-2.9458739758,43.4066467285],"type":"Point"}
}