{
  "type": "Feature",
  "properties": {
    "iso:country":"ES",
    "sg:address":"Ptda Riquer Alt, 23",
    "sg:city":"Alcoi",
    "sg:orig_category":"Bordado, Marcado A Medida",
    "sg:phone":"+34 965 52 08 04",
    "sg:postcode":"03800",
    "sg:province":"Alicante",
    "wof:name":"Bordados Alcoy S.l.",
    "wof:placetype":"venue"
},
  "geometry": {"coordinates":[-0.4732739925,38.6984100342],"type":"Point"}
}