{
  "type": "Feature",
  "properties": {
    "addr:full":"Calle de Virgen De La Soledad, 49 Nules Castell\u00f3n 12520",
    "addr:housenumber":"49",
    "addr:postcode":"12520",
    "addr:street":"Calle De Virgen De La Soledad",
    "iso:country":"ES",
    "sg:address":"Calle de Virgen De La Soledad, 49",
    "sg:city":"Nules",
    "sg:orig_category":"Fabricaci\u00d3n, Importaci\u00d3n De L\u00c1mparas Y Bombillas",
    "sg:phone":"+34 964 67 14 17",
    "sg:postcode":"12520",
    "sg:province":"Castell\u00f3n",
    "wof:name":"Herrero Espinosa Jose",
    "wof:placetype":"venue"
},
  "geometry": {"coordinates":[-0.1542440057,39.852596283],"type":"Point"}
}