{
  "type": "Feature",
  "properties": {
    "iso:country":"ES",
    "sg:address":"Calle de Suecia, 87",
    "sg:city":"Madrid",
    "sg:orig_category":"Inform\u00c1tica: Material Y Suministros",
    "sg:phone":"+34 913 06 95 62",
    "sg:postcode":"28022",
    "sg:province":"Madrid",
    "wof:name":"Desarrollo E Investigacion Informatica Pronet S.l.",
    "wof:placetype":"venue"
},
  "geometry": {"coordinates":[-3.6060268879,40.4327926636],"type":"Point"}
}