{
  "type": "Feature",
  "properties": {
    "addr:full":"Pg Colom, 2 Barcelona Barcelona 08002",
    "addr:housenumber":"2",
    "addr:postcode":"08002",
    "addr:street":"Pg Colom",
    "iso:country":"ES",
    "sg:address":"Pg Colom, 2",
    "sg:city":"Barcelona",
    "sg:orig_category":"Ense\u00d1anza: Profesiones Art\u00cdsticas",
    "sg:phone":"+34 932 68 01 87",
    "sg:postcode":"08002",
    "sg:province":"Barcelona",
    "wof:name":"Black And Blanc Fotografia S.l",
    "wof:placetype":"venue"
},
  "geometry": {"coordinates":[2.1815540791,41.3809432983],"type":"Point"}
}