{
  "type": "Feature",
  "properties": {
    "iso:country":"ES",
    "sg:address":"Rua Padre Seixas, 32",
    "sg:city":"Vigo",
    "sg:orig_category":"Impuestos, Tesoro P\u00dablico",
    "sg:phone":"+34 986 21 04 52",
    "sg:postcode":"36209",
    "sg:province":"Pontevedra",
    "wof:name":"Felipe Alvarez Y Eliseo Cicero C.b.",
    "wof:placetype":"venue"
},
  "geometry": {"coordinates":[-8.7498207092,42.2117271423],"type":"Point"}
}