{
  "type": "Feature",
  "properties": {
    "addr:full":"Calle de San Ignacio, 3 Bu\u00f1uel Navarra 31540",
    "addr:housenumber":"3",
    "addr:postcode":"31540",
    "addr:street":"Calle De San Ignacio",
    "iso:country":"ES",
    "sg:address":"Calle de San Ignacio, 3",
    "sg:city":"Bu\u00f1uel",
    "sg:orig_category":"Molduras, Junquillos, Listones Y Molduras Perforadas",
    "sg:phone":"+34 948 83 35 99",
    "sg:postcode":"31540",
    "sg:province":"Navarra",
    "wof:name":"Rincon Del Torero",
    "wof:placetype":"venue"
},
  "geometry": {"coordinates":[-1.4457969666,41.97996521],"type":"Point"}
}