{
  "type": "Feature",
  "properties": {
    "addr:full":"Calle de Sevilla, 22 Huercal-overa Almer\u00eda 04600",
    "addr:housenumber":"22",
    "addr:postcode":"04600",
    "addr:street":"Calle De Sevilla;Almeri\u0301A",
    "iso:country":"ES",
    "sg:address":"Calle de Sevilla, 22",
    "sg:city":"Huercal-overa",
    "sg:orig_category":"Cristaler\u00cdas",
    "sg:phone":"+34 950 47 05 77",
    "sg:postcode":"04600",
    "sg:province":"Almer\u00eda",
    "wof:name":"Rodriguez Alonso Maria",
    "wof:placetype":"venue"
},
  "geometry": {"coordinates":[-1.9480019808,37.3935317993],"type":"Point"}
}