{
  "type": "Feature",
  "properties": {
    "iso:country":"ES",
    "sg:address":"Calle de Pino (del), 4",
    "sg:city":"Jerez De La Frontera",
    "sg:orig_category":"Fabricaci\u00d3n, Venta De Cuadros, Accesorios Para Enmarcar",
    "sg:phone":"+34 956 34 94 69",
    "sg:postcode":"11408",
    "sg:province":"C\u00e1diz",
    "wof:name":"Perez Roman Josefa",
    "wof:placetype":"venue"
},
  "geometry": {"coordinates":[-6.148419857,36.6837005615],"type":"Point"}
}