{
  "type": "Feature",
  "properties": {
    "addr:full":"Calle de Bolivia, 3 Madrid Madrid 28016",
    "addr:housenumber":"3",
    "addr:postcode":"28016",
    "addr:street":"Calle De Bolivia",
    "iso:country":"ES",
    "sg:address":"Calle de Bolivia, 3",
    "sg:city":"Madrid",
    "sg:orig_category":"Ropa Para Se\u00d1oras (al Por Menor)",
    "sg:phone":"+34 914 57 60 34",
    "sg:postcode":"28016",
    "sg:province":"Madrid",
    "wof:name":"Del Agua Ca\u00f1on Susana",
    "wof:placetype":"venue"
},
  "geometry": {"coordinates":[-3.6780967712,40.4561653137],"type":"Point"}
}