{
  "type": "Feature",
  "properties": {
    "addr:full":"Calle de Magdalena, 2 Solana De Los Barros Badajoz 06209",
    "addr:housenumber":"2",
    "addr:postcode":"06209",
    "addr:street":"Calle De Magdalena;Barros",
    "iso:country":"ES",
    "sg:address":"Calle de Magdalena, 2",
    "sg:city":"Solana De Los Barros",
    "sg:orig_category":"Cajas De Ahorro",
    "sg:phone":"+34 924 68 30 36",
    "sg:postcode":"06209",
    "sg:province":"Badajoz",
    "sg:website":"www.cajabadajoz.es",
    "wof:name":"Caja De Badajoz",
    "wof:placetype":"venue"
},
  "geometry": {"coordinates":[-6.5377440453,38.7259292603],"type":"Point"}
}