{
  "type": "Feature",
  "properties": {
    "iso:country":"ES",
    "sg:address":"Calle de Maestra Do\u00d1a Dolores Cansino, 8",
    "sg:city":"Alhaurin El Grande",
    "sg:classifiers":[
        {
            "category":"Taxi",
            "type":"Transportation"
        }
    ],
    "sg:phone":"+34 952 49 00 66",
    "sg:postcode":"29120",
    "sg:province":"M\u00e1laga",
    "wof:name":"Gomez Garcia Sebastian",
    "wof:placetype":"venue"
},
  "geometry": {"coordinates":[-4.6911292076,36.6420783997],"type":"Point"}
}