{
  "type": "Feature",
  "properties": {
    "iso:country":"ES",
    "sg:address":"Calle de Pablo Morillo, 4",
    "sg:city":"Zamora",
    "sg:orig_category":"Abogados",
    "sg:phone":"+34 980 67 06 71",
    "sg:postcode":"49013",
    "sg:province":"Zamora",
    "wof:name":"Martin Anero Norberto",
    "wof:placetype":"venue"
},
  "geometry": {"coordinates":[-5.7416291237,41.5077323914],"type":"Point"}
}