{
  "type": "Feature",
  "properties": {
    "iso:country":"ES",
    "sg:address":"Carrer de Patronat, 13",
    "sg:city":"Castellter\u00e7ol",
    "sg:orig_category":"Bosques (trabajos, Asesor\u00cda, Gesti\u00d3n)",
    "sg:phone":"+34 938 66 82 92",
    "sg:postcode":"08183",
    "sg:province":"Barcelona",
    "wof:name":"Plans Capdevila Angel",
    "wof:placetype":"venue"
},
  "geometry": {"coordinates":[2.1173300743,41.7466239929],"type":"Point"}
}