{
  "type": "Feature",
  "properties": {
    "iso:country":"ES",
    "sg:address":"Carr Sant Sebastia, 38",
    "sg:city":"Alcarras",
    "sg:orig_category":"Maquinaria Para Industrias Diversas",
    "sg:phone":"+34 973 79 05 43",
    "sg:postcode":"25180",
    "sg:province":"Lleida",
    "wof:name":"Josep Antoni Mongai I Tort Y Javier Mongai Batlle",
    "wof:placetype":"venue"
},
  "geometry": {"coordinates":[0.5227050185,41.5665092468],"type":"Point"}
}