{
  "type": "Feature",
  "properties": {
    "addr:full":"Castillo Villena, 48 Escalona Toledo 45910",
    "addr:housenumber":"48",
    "addr:postcode":"45910",
    "addr:street":"Villena",
    "iso:country":"ES",
    "sg:address":"Castillo Villena, 48",
    "sg:city":"Escalona",
    "sg:orig_category":"Molduras, Junquillos, Listones Y Molduras Perforadas",
    "sg:phone":"+34 925 78 31 94",
    "sg:postcode":"45910",
    "sg:province":"Toledo",
    "wof:name":"Simon Sanchez Gines",
    "wof:placetype":"venue"
},
  "geometry": {"coordinates":[-4.4065790176,40.1327781677],"type":"Point"}
}