{
  "type": "Feature",
  "properties": {
    "addr:full":"Ctra Zaragoza Pol La Laguna, 115 Alca\u00f1iz Teruel 44600",
    "addr:housenumber":"115",
    "addr:postcode":"44600",
    "addr:street":"Ctra Zaragoza Pol La Laguna",
    "iso:country":"ES",
    "sg:address":"Ctra Zaragoza Pol La Laguna, 115",
    "sg:city":"Alca\u00f1iz",
    "sg:orig_category":"Pintura Y Barniz (al Por Menor)",
    "sg:phone":"+34 978 83 20 00",
    "sg:postcode":"44600",
    "sg:province":"Teruel",
    "wof:name":"Ferpi S.l.",
    "wof:placetype":"venue"
},
  "geometry": {"coordinates":[-0.1331740022,41.0522842407],"type":"Point"}
}