{
  "type": "Feature",
  "properties": {
    "iso:country":"ES",
    "sg:address":"Carrer de Gratallops (de), 24",
    "sg:city":"Reus",
    "sg:orig_category":"Alumbrados",
    "sg:phone":"+34 977 33 13 33",
    "sg:postcode":"43206",
    "sg:province":"Tarragona",
    "wof:name":"Reus Lights S.l.",
    "wof:placetype":"venue"
},
  "geometry": {"coordinates":[1.0778180361,41.1561431885],"type":"Point"}
}