{
  "type": "Feature",
  "properties": {
    "iso:country":"ES",
    "sg:address":"Carrer de Miquel Granell, 21",
    "sg:city":"Amposta",
    "sg:orig_category":"Carnicer\u00cdas, Carnicer\u00cdas",
    "sg:phone":"+34 977 70 19 02",
    "sg:postcode":"43870",
    "sg:province":"Tarragona",
    "wof:name":"Dolz Valles Miguel",
    "wof:placetype":"venue"
},
  "geometry": {"coordinates":[0.5789960027,40.710144043],"type":"Point"}
}