{
  "type": "Feature",
  "properties": {
    "addr:full":"Calle de Santa Rosa De Lima, 10 Suerte Las Palmas 35018",
    "addr:housenumber":"10",
    "addr:postcode":"35018",
    "addr:street":"Calle De Santa Rosa De Lima",
    "iso:country":"ES",
    "sg:address":"Calle de Santa Rosa De Lima, 10",
    "sg:city":"Suerte",
    "sg:orig_category":"Empresas De Carpinter\u00cda Met\u00c1lica",
    "sg:phone":"+34 928 67 14 29",
    "sg:postcode":"35018",
    "sg:province":"Las Palmas",
    "wof:name":"Garcia Falcon Pedro",
    "wof:placetype":"venue"
},
  "geometry": {"coordinates":[-15.4817991257,28.0959300995],"type":"Point"}
}