{
  "type": "Feature",
  "properties": {
    "addr:full":"Carr Seu D'urgell, 1 Badalona Barcelona 08911",
    "addr:housenumber":"1",
    "addr:postcode":"08911",
    "addr:street":"Carr Seu D'Urgell",
    "iso:country":"ES",
    "sg:address":"Carr Seu D'urgell, 1",
    "sg:city":"Badalona",
    "sg:orig_category":"Empresarios",
    "sg:phone":"+34 934 64 09 72",
    "sg:postcode":"08911",
    "sg:province":"Barcelona",
    "wof:name":"Jove Llar S.l.",
    "wof:placetype":"venue"
},
  "geometry": {"coordinates":[2.2518024445,41.4536209106],"type":"Point"}
}