{
  "type": "Feature",
  "properties": {
    "addr:full":"Calle de Tiendas (de Las), 28 Almeria Almer\u00eda 04003",
    "addr:housenumber":"28",
    "addr:postcode":"04003",
    "addr:street":"Calle De Tiendas;Las",
    "iso:country":"ES",
    "sg:address":"Calle de Tiendas (de Las), 28",
    "sg:city":"Almeria",
    "sg:orig_category":"Confecci\u00d3n De Trajes Para Se\u00d1oras",
    "sg:phone":"+34 950 23 52 03",
    "sg:postcode":"04003",
    "sg:province":"Almer\u00eda",
    "wof:name":"Linares Navarro Manuel",
    "wof:placetype":"venue"
},
  "geometry": {"coordinates":[-2.4660909176,36.8407707214],"type":"Point"}
}