{
  "type": "Feature",
  "properties": {
    "addr:full":"Calle de Alonso Pesquera, 1 Valladolid Valladolid 47002",
    "addr:housenumber":"1",
    "addr:postcode":"47002",
    "addr:street":"Calle De Alonso Pesquera",
    "iso:country":"ES",
    "sg:address":"Calle de Alonso Pesquera, 1",
    "sg:city":"Valladolid",
    "sg:orig_category":"Productores Recolectores, Venta Directa De Vinos",
    "sg:phone":"+34 983 29 89 49",
    "sg:postcode":"47002",
    "sg:province":"Valladolid",
    "sg:website":"www.pilcar.com",
    "wof:name":"Bodegas Y Vi\u00f1edos Pilcar S.l.",
    "wof:placetype":"venue"
},
  "geometry": {"coordinates":[-4.7208018303,41.6506195068],"type":"Point"}
}