{
  "type": "Feature",
  "properties": {
    "iso:country":"ES",
    "sg:address":"C/ Jaume Ii, 1",
    "sg:city":"Manacor",
    "sg:orig_category":"Equitaci\u00d3n: Guarnicioner\u00cda, Equipo (al Por Menor)",
    "sg:phone":"+34 971 84 51 03",
    "sg:postcode":"07500",
    "sg:province":"Islas Baleares",
    "wof:name":"C.b.guarnicioneria Marti",
    "wof:placetype":"venue"
},
  "geometry": {"coordinates":[3.227793932,39.5640945435],"type":"Point"}
}