{
  "type": "Feature",
  "properties": {
    "iso:country":"ES",
    "sg:address":"Carr Jaume Mas I Noguera, 23",
    "sg:city":"Sant Joan",
    "sg:orig_category":"Forjas Y Altos Hornos",
    "sg:phone":"+34 971 52 65 11",
    "sg:postcode":"07240",
    "sg:province":"Islas Baleares",
    "wof:name":"Serralleria Batxa Cb",
    "wof:placetype":"venue"
},
  "geometry": {"coordinates":[3.0388898849,39.5969161987],"type":"Point"}
}