{
  "type": "Feature",
  "properties": {
    "addr:full":"Calle de San Juan, 1 Corella Navarra 31591",
    "addr:housenumber":"1",
    "addr:postcode":"31591",
    "addr:street":"Calle De San Juan",
    "iso:country":"ES",
    "sg:address":"Calle de San Juan, 1",
    "sg:city":"Corella",
    "sg:orig_category":"Promotores Constructores",
    "sg:phone":"+34 948 78 13 33",
    "sg:postcode":"31591",
    "sg:province":"Navarra",
    "wof:name":"Construcciones Forpe S. L.",
    "wof:placetype":"venue"
},
  "geometry": {"coordinates":[-1.7851289511,42.1136665344],"type":"Point"}
}