{
  "type": "Feature",
  "properties": {
    "addr:full":"Calle de Rodrigo De Triana, 37 Sevilla Sevilla 41010",
    "addr:housenumber":"37",
    "addr:postcode":"41010",
    "addr:street":"Calle De Rodrigo De Triana",
    "iso:country":"ES",
    "sg:address":"Calle de Rodrigo De Triana, 37",
    "sg:city":"Sevilla",
    "sg:orig_category":"Molduras, Junquillos, Listones Y Molduras Perforadas",
    "sg:phone":"+34 954 33 21 37",
    "sg:postcode":"41010",
    "sg:province":"Sevilla",
    "wof:name":"Santiago Del Pino Emilio",
    "wof:placetype":"venue"
},
  "geometry": {"coordinates":[-6.0027737617,37.3834533691],"type":"Point"}
}