{
  "type": "Feature",
  "properties": {
    "addr:full":"Carrer de Llobateras, 20 Rubi Barcelona 08191",
    "addr:housenumber":"20",
    "addr:postcode":"08191",
    "addr:street":"Carrer De Llobateras",
    "iso:country":"ES",
    "sg:address":"Carrer de Llobateras, 20",
    "sg:city":"Rubi",
    "sg:orig_category":"Molduras, Junquillos, Listones Y Molduras Perforadas",
    "sg:phone":"+34 935 88 74 28",
    "sg:postcode":"08191",
    "sg:province":"Barcelona",
    "wof:name":"Llamas De La Osa Luis",
    "wof:placetype":"venue"
},
  "geometry": {"coordinates":[2.0308320522,41.4890861511],"type":"Point"}
}