{
  "type": "Feature",
  "properties": {
    "iso:country":"ES",
    "sg:address":"Avda Ciudad De Barcelona, 132",
    "sg:city":"Madrid",
    "sg:orig_category":"Promotores Constructores",
    "sg:phone":"+34 914 34 83 88",
    "sg:postcode":"28007",
    "sg:province":"Madrid",
    "wof:name":"Sociedad Agrupadora S.l.",
    "wof:placetype":"venue"
},
  "geometry": {"coordinates":[-3.6811439991,40.4042358398],"type":"Point"}
}