{
  "type": "Feature",
  "properties": {
    "iso:country":"ES",
    "sg:address":"Calle de Miguel Servet, 16",
    "sg:city":"Sestao",
    "sg:orig_category":"Talleres: Ropa A Medida",
    "sg:phone":"+34 944 96 55 98",
    "sg:postcode":"48910",
    "sg:province":"Vizcaya",
    "wof:name":"Martinez Fernandez Ivan",
    "wof:placetype":"venue"
},
  "geometry": {"coordinates":[-2.9996962547,43.3090553284],"type":"Point"}
}