{
  "type": "Feature",
  "properties": {
    "addr:full":"Av Lloren\u00c7 Puig Tomas, 54 Viladecans Barcelona 08840",
    "addr:housenumber":"54",
    "addr:postcode":"08840",
    "addr:street":"Av Llorenc\u0327 Puig Tomas",
    "iso:country":"ES",
    "sg:address":"Av Lloren\u00c7 Puig Tomas, 54",
    "sg:city":"Viladecans",
    "sg:orig_category":"Promotores Constructores",
    "sg:phone":"+34 936 37 76 50",
    "sg:postcode":"08840",
    "sg:province":"Barcelona",
    "wof:name":"Rehabilitaciones Manus",
    "wof:placetype":"venue"
},
  "geometry": {"coordinates":[2.0148069859,41.3248214722],"type":"Point"}
}