{
  "type": "Feature",
  "properties": {
    "addr:full":"Pl Colom, 1 Castelldefels Barcelona 08860",
    "addr:housenumber":"1",
    "addr:postcode":"08860",
    "addr:street":"Pl Colom",
    "iso:country":"ES",
    "sg:address":"Pl Colom, 1",
    "sg:city":"Castelldefels",
    "sg:orig_category":"Peluquer\u00cdas, Peluquer\u00cda Mixta",
    "sg:phone":"+34 936 36 28 86",
    "sg:postcode":"08860",
    "sg:province":"Barcelona",
    "wof:name":"Silva Gijon Montserrat",
    "wof:placetype":"venue"
},
  "geometry": {"coordinates":[1.9848669767,41.2846069336],"type":"Point"}
}