{
  "type": "Feature",
  "properties": {
    "addr:full":"C/ Eivissa, 3 Manacor Islas Baleares 07500",
    "addr:housenumber":"3",
    "addr:postcode":"07500",
    "addr:street":"C / Eivissa",
    "iso:country":"ES",
    "sg:address":"C/ Eivissa, 3",
    "sg:city":"Manacor",
    "sg:orig_category":"Empresas De Carpinter\u00cda De Madera",
    "sg:phone":"+34 971 55 28 40",
    "sg:postcode":"07500",
    "sg:province":"Islas Baleares",
    "wof:name":"Marti Estelrich Antonio",
    "wof:placetype":"venue"
},
  "geometry": {"coordinates":[3.2072970867,39.5636711121],"type":"Point"}
}