{
  "type": "Feature",
  "properties": {
    "iso:country":"ES",
    "sg:address":"Calle de Tortola (de La), 16",
    "sg:city":"Puerto De Santa Maria",
    "sg:orig_category":"Agencias Y Agentes Comerciales, Representantes",
    "sg:phone":"+34 956 85 02 12",
    "sg:postcode":"11500",
    "sg:province":"C\u00e1diz",
    "wof:name":"Quintero Curiel Ramon",
    "wof:placetype":"venue"
},
  "geometry": {"coordinates":[-6.2370800972,36.5917854309],"type":"Point"}
}