{
  "type": "Feature",
  "properties": {
    "addr:full":"Calle de Castilla, 5 Zaragoza Zaragoza 50009",
    "addr:housenumber":"5",
    "addr:postcode":"50009",
    "addr:street":"Calle De Castilla",
    "iso:country":"ES",
    "sg:address":"Calle de Castilla, 5",
    "sg:city":"Zaragoza",
    "sg:orig_category":"Ingeniero",
    "sg:phone":"+34 976 75 84 43",
    "sg:postcode":"50009",
    "sg:province":"Zaragoza",
    "sg:website":"www.ergoauditores.com",
    "wof:name":"Ergo Auditores S.%",
    "wof:placetype":"venue"
},
  "geometry": {"coordinates":[-0.9111939073,41.6429100037],"type":"Point"}
}