{
  "type": "Feature",
  "properties": {
    "iso:country":"ES",
    "sg:address":"Avda Gines Campos, S/n",
    "sg:city":"Alhama Murcia",
    "sg:orig_category":"Negocio De Materiales De Construcci\u00d3n",
    "sg:phone":"+34 968 63 09 69",
    "sg:postcode":"30840",
    "sg:province":"Murcia",
    "sg:website":"www.visanfer.com",
    "wof:name":"Visanfer S. A.",
    "wof:placetype":"venue"
},
  "geometry": {"coordinates":[-1.4144289494,37.8527183533],"type":"Point"}
}