{
  "type": "Feature",
  "properties": {
    "iso:country":"ES",
    "sg:address":"B Poligono, S/n",
    "sg:city":"Soria",
    "sg:orig_category":"Empresas De Carpinter\u00cda De Madera",
    "sg:phone":"+34 975 22 68 59",
    "sg:postcode":"42005",
    "sg:province":"Soria",
    "wof:name":"Soriano Hernandez Juan",
    "wof:placetype":"venue"
},
  "geometry": {"coordinates":[-2.4691669941,41.7646598816],"type":"Point"}
}