{
  "type": "Feature",
  "properties": {
    "iso:country":"ES",
    "sg:address":"Carrer de Avila, 140",
    "sg:city":"Barcelona",
    "sg:orig_category":"Electricidad: Instaladores",
    "sg:phone":"+34 933 00 59 66",
    "sg:postcode":"08018",
    "sg:province":"Barcelona",
    "wof:name":"Lopez Sanchez Agustin",
    "wof:placetype":"venue"
},
  "geometry": {"coordinates":[2.1892669201,41.4001274109],"type":"Point"}
}