{
  "type": "Feature",
  "properties": {
    "addr:full":"Calle de Mozart, 7 Madrid Madrid 28008",
    "addr:housenumber":"7",
    "addr:postcode":"madrid;28008",
    "addr:street":"Calle De Mozart",
    "iso:country":"ES",
    "sg:address":"Calle de Mozart, 7",
    "sg:city":"Madrid",
    "sg:orig_category":"M\u00c9dicos: Estomatolog\u00cda",
    "sg:phone":"+34 915 48 50 18",
    "sg:postcode":"28008",
    "sg:province":"Madrid",
    "wof:name":"Conde Giardini Claudio",
    "wof:placetype":"venue"
},
  "geometry": {"coordinates":[-3.7221169472,40.4228782654],"type":"Point"}
}