{
  "type": "Feature",
  "properties": {
    "iso:country":"ES",
    "sg:address":"Pase Castellana, 59",
    "sg:city":"Madrid",
    "sg:orig_category":"Administradores De Bienes Y Delegados De Comunidades De Propietarios",
    "sg:phone":"+34 914 41 19 00",
    "sg:postcode":"28046",
    "sg:province":"Madrid",
    "wof:name":"Albaida De Las Monjas Sl",
    "wof:placetype":"venue"
},
  "geometry": {"coordinates":[-3.691493988,40.4390907288],"type":"Point"}
}