{
  "type": "Feature",
  "properties": {
    "addr:full":"Calle de Carlos Iii, 26 Arrecife Las Palmas 35500",
    "addr:housenumber":"26",
    "addr:postcode":"35500",
    "addr:street":"Calle De Carlos Iii",
    "iso:country":"ES",
    "sg:address":"Calle de Carlos Iii, 26",
    "sg:city":"Arrecife",
    "sg:orig_category":"Iglesia Cat\u00d3lica",
    "sg:phone":"+34 928 80 18 01",
    "sg:postcode":"35500",
    "sg:province":"Las Palmas",
    "wof:name":"Parroquia San Jose Obrero",
    "wof:placetype":"venue"
},
  "geometry": {"coordinates":[-13.5561103821,28.9683380127],"type":"Point"}
}