{
  "type": "Feature",
  "properties": {
    "addr:full":"Calle de Doctor Ros, 19 Alzira Valencia 46600",
    "addr:housenumber":"19",
    "addr:postcode":"46600",
    "addr:street":"Calle De Doctor Ros",
    "iso:country":"ES",
    "sg:address":"Calle de Doctor Ros, 19",
    "sg:city":"Alzira",
    "sg:orig_category":"Iglesia Cat\u00d3lica",
    "sg:phone":"+34 962 41 02 22",
    "sg:postcode":"46600",
    "sg:province":"Valencia",
    "wof:name":"Parroquia Santa Catalina",
    "wof:placetype":"venue"
},
  "geometry": {"coordinates":[-0.4395250082,39.1513710022],"type":"Point"}
}