{
  "type": "Feature",
  "properties": {
    "iso:country":"ES",
    "sg:address":"Av Alcalde Palau, 29",
    "sg:city":"Amposta",
    "sg:orig_category":"Molduras, Junquillos, Listones Y Molduras Perforadas",
    "sg:phone":"+34 977 70 00 14",
    "sg:postcode":"43870",
    "sg:province":"Tarragona",
    "wof:name":"Estelle Marti Alfredo Pedro",
    "wof:placetype":"venue"
},
  "geometry": {"coordinates":[0.5800189972,40.7134170532],"type":"Point"}
}