{
  "type": "Feature",
  "properties": {
    "addr:full":"Calle de Bielorrusia, 9 Malaga M\u00e1laga 29196",
    "addr:housenumber":"9",
    "addr:postcode":"29196",
    "addr:street":"Calle De Bielorrusia;Ma\u0301Laga",
    "iso:country":"ES",
    "sg:address":"Calle de Bielorrusia, 9",
    "sg:city":"Malaga",
    "sg:orig_category":"Agencias Y Asesores De Publicidad",
    "sg:phone":"+34 952 17 24 48",
    "sg:postcode":"29196",
    "sg:province":"M\u00e1laga",
    "sg:website":"www.mmmdigital.com",
    "wof:name":"Homepublic S.l.",
    "wof:placetype":"venue"
},
  "geometry": {"coordinates":[-4.5149121284,36.6967582703],"type":"Point"}
}