{
  "type": "Feature",
  "properties": {
    "addr:full":"Ctra Alcoi (d'), 16 Callosa D'en Sarria Alicante 03510",
    "addr:housenumber":"16",
    "addr:postcode":"03510",
    "addr:street":"Ctra Alcoi D '",
    "iso:country":"ES",
    "sg:address":"Ctra Alcoi (d'), 16",
    "sg:city":"Callosa D'en Sarria",
    "sg:orig_category":"Electricidad: Instaladores",
    "sg:phone":"+34 965 88 05 88",
    "sg:postcode":"03510",
    "sg:province":"Alicante",
    "wof:name":"Berenguer Benimeli Alfonso",
    "wof:placetype":"venue"
},
  "geometry": {"coordinates":[-0.1226157993,38.6500358582],"type":"Point"}
}