{
  "type": "Feature",
  "properties": {
    "addr:full":"Calle de Caceres, 28 Alcorcon Madrid 28921",
    "addr:housenumber":"28",
    "addr:postcode":"28921",
    "addr:street":"Calle De Caceres",
    "iso:country":"ES",
    "sg:address":"Calle de Caceres, 28",
    "sg:city":"Alcorcon",
    "sg:orig_category":"Institutos De Belleza",
    "sg:phone":"+34 916 44 08 68",
    "sg:postcode":"28921",
    "sg:province":"Madrid",
    "wof:name":"Solglamour C.b",
    "wof:placetype":"venue"
},
  "geometry": {"coordinates":[-3.8330101967,40.3472518921],"type":"Point"}
}