{
  "type": "Feature",
  "properties": {
    "iso:country":"ES",
    "sg:address":"Ctra Pego (de), S/n",
    "sg:city":"Oliva",
    "sg:orig_category":"Servicio De Salud",
    "sg:phone":"+34 962 85 05 88",
    "sg:postcode":"46780",
    "sg:province":"Valencia",
    "wof:name":"Suministros Gonzalez E Hijos S.l.",
    "wof:placetype":"venue"
},
  "geometry": {"coordinates":[-0.1148689985,38.9150695801],"type":"Point"}
}