{
  "type": "Feature",
  "properties": {
    "iso:country":"ES",
    "sg:address":"Compositor Gijon, S/n",
    "sg:city":"Belmez Moraleda",
    "sg:orig_category":"Bares, Piano",
    "sg:phone":"+34 953 39 42 50",
    "sg:postcode":"23568",
    "sg:province":"Ja\u00e9n",
    "wof:name":"Robles Ma\u00f1as Antonio",
    "wof:placetype":"venue"
},
  "geometry": {"coordinates":[-3.3803629875,37.7233734131],"type":"Point"}
}