{
  "type": "Feature",
  "properties": {
    "addr:full":"Avda Regne De Valencia, 94 Valencia Valencia 46006",
    "addr:housenumber":"94",
    "addr:postcode":"46006",
    "addr:street":"Avda Regne De Valencia",
    "iso:country":"ES",
    "sg:address":"Avda Regne De Valencia, 94",
    "sg:city":"Valencia",
    "sg:orig_category":"Arquitectos",
    "sg:phone":"+34 963 95 02 52",
    "sg:postcode":"46006",
    "sg:province":"Valencia",
    "wof:name":"Leyva Sanchez Manuel Antonio De",
    "wof:placetype":"venue"
},
  "geometry": {"coordinates":[-0.3613669872,39.4621047974],"type":"Point"}
}