{
  "type": "Feature",
  "properties": {
    "iso:country":"ES",
    "sg:address":"Calle de Princesa, 31",
    "sg:city":"Madrid",
    "sg:orig_category":"Inmobiliaria (agencias)",
    "sg:phone":"+34 915 41 06 05",
    "sg:postcode":"28008",
    "sg:province":"Madrid",
    "wof:name":"Comercial Princesa S. A.",
    "wof:placetype":"venue"
},
  "geometry": {"coordinates":[-3.7143640518,40.4278678894],"type":"Point"}
}