{
  "type": "Feature",
  "properties": {
    "iso:country":"ES",
    "sg:address":"Carrer de Francisco De Vitoria, 15",
    "sg:city":"Terrassa",
    "sg:orig_category":"Lencer\u00cda Femenina, Corseter\u00cda, Trajes De Ba\u00d1o (al Por Menor)",
    "sg:phone":"+34 937 89 36 80",
    "sg:postcode":"08225",
    "sg:province":"Barcelona",
    "wof:name":"Ferran Arenas Maria Angeles",
    "wof:placetype":"venue"
},
  "geometry": {"coordinates":[2.0024330616,41.5702476501],"type":"Point"}
}