{
  "type": "Feature",
  "properties": {
    "iso:country":"ES",
    "sg:address":"Carrer de Cervantes, 67",
    "sg:city":"Alcanar",
    "sg:orig_category":"Frutas Y Legumbres Frescas (al Por Mayor)",
    "sg:phone":"+34 977 73 01 99",
    "sg:postcode":"43530",
    "sg:province":"Tarragona",
    "wof:name":"J.subirats S.a.",
    "wof:placetype":"venue"
},
  "geometry": {"coordinates":[0.4774090052,40.5433006287],"type":"Point"}
}