{
  "type": "Feature",
  "properties": {
    "addr:full":"Bard Federico Garcia Lorca, 6 Sevilla Sevilla 41006",
    "addr:housenumber":"6",
    "addr:postcode":"41006",
    "addr:street":"Federico Garcia Lorca",
    "iso:country":"ES",
    "sg:address":"Bard Federico Garcia Lorca, 6",
    "sg:city":"Sevilla",
    "sg:orig_category":"Venta, Instalaci\u00d3n, Reparaci\u00d3n De Antenas Para Televisi\u00d3n",
    "sg:phone":"+34 954 92 38 41",
    "sg:postcode":"41006",
    "sg:province":"Sevilla",
    "wof:name":"Romero Lopez Manuel",
    "wof:placetype":"venue"
},
  "geometry": {"coordinates":[-5.945081234,37.375087738],"type":"Point"}
}