{
  "type": "Feature",
  "properties": {
    "addr:full":"Proyectos (p I Pelagatos), S/n Chiclana C\u00e1diz 11130",
    "addr:postcode":"11130",
    "addr:street":"Pelagatos S / N",
    "iso:country":"ES",
    "sg:address":"Proyectos (p I Pelagatos), S/n",
    "sg:city":"Chiclana",
    "sg:orig_category":"Negocio De Madera",
    "sg:phone":"+34 956 40 69 23",
    "sg:postcode":"11130",
    "sg:province":"C\u00e1diz",
    "wof:name":"Maderas Diego Gonzalez S.l.l.",
    "wof:placetype":"venue"
},
  "geometry": {"coordinates":[-6.127779007,36.4023704529],"type":"Point"}
}