{
  "type": "Feature",
  "properties": {
    "addr:full":"Carrer de Font (la), 17 Sagra Alicante 03795",
    "addr:housenumber":"17",
    "addr:postcode":"03795",
    "addr:street":"Carrer De Font La",
    "iso:country":"ES",
    "sg:address":"Carrer de Font (la), 17",
    "sg:city":"Sagra",
    "sg:orig_category":"Cooperativas Agr\u00cdcolas",
    "sg:phone":"+34 966 40 44 64",
    "sg:postcode":"03795",
    "sg:province":"Alicante",
    "wof:name":"Cooperativa Agricola De Gandia Coop. V.",
    "wof:placetype":"venue"
},
  "geometry": {"coordinates":[-0.0642110035,38.8118515015],"type":"Point"}
}