{
  "type": "Feature",
  "properties": {
    "iso:country":"ES",
    "sg:address":"Calle de Gobernador Fernandez Jimenez (del), 16",
    "sg:city":"Segovia",
    "sg:orig_category":"Centros De Coordinaci\u00d3n",
    "sg:phone":"+34 921 42 29 00",
    "sg:postcode":"40002",
    "sg:province":"Segovia",
    "wof:name":"Herranz San Frutos Maria Irene",
    "wof:placetype":"venue"
},
  "geometry": {"coordinates":[-4.1188464165,40.9449653625],"type":"Point"}
}