{
  "type": "Feature",
  "properties": {
    "iso:country":"ES",
    "sg:address":"Calle de Capitulaciones, S/n",
    "sg:city":"Torremolinos",
    "sg:orig_category":"Agencias De Viajes",
    "sg:phone":"+34 952 05 25 60",
    "sg:postcode":"29620",
    "sg:province":"M\u00e1laga",
    "sg:website":"www.charminghotels-spain.com",
    "wof:name":"Minotel Espa\u00d1a S.l.",
    "wof:placetype":"venue"
},
  "geometry": {"coordinates":[-4.5133571625,36.6083450317],"type":"Point"}
}