{
  "type": "Feature",
  "properties": {
    "iso:country":"ES",
    "sg:address":"Calle de Velazquez, 43",
    "sg:city":"Madrid",
    "sg:orig_category":"Notarios",
    "sg:phone":"+34 915 75 24 97",
    "sg:postcode":"28001",
    "sg:province":"Madrid",
    "wof:name":"Lopez Duran Juan",
    "wof:placetype":"venue"
},
  "geometry": {"coordinates":[-3.6841650009,40.4268112183],"type":"Point"}
}