{
  "type": "Feature",
  "properties": {
    "iso:country":"ES",
    "sg:address":"Cmno Palomares, Km. 0001,2",
    "sg:city":"Valladolid",
    "sg:orig_category":"Cr\u00cda De Animales",
    "sg:phone":"+34 983 25 08 44",
    "sg:postcode":"47011",
    "sg:province":"Valladolid",
    "wof:name":"Arroyo Sarmentero Victor",
    "wof:placetype":"venue"
},
  "geometry": {"coordinates":[-4.6853618622,41.6699180603],"type":"Point"}
}