{
  "type": "Feature",
  "properties": {
    "addr:full":"Avda Almendros, 20 Benidorm Alicante 03500",
    "addr:housenumber":"20",
    "addr:postcode":"03500",
    "addr:street":"Avda Almendros",
    "iso:country":"ES",
    "sg:address":"Avda Almendros, 20",
    "sg:city":"Benidorm",
    "sg:orig_category":"Ropa Para Se\u00d1oras Y Caballeros (al Por Menor)",
    "sg:phone":"+34 966 80 64 02",
    "sg:postcode":"03500",
    "sg:province":"Alicante",
    "wof:name":"Jardin Galatea 2004",
    "wof:placetype":"venue"
},
  "geometry": {"coordinates":[-0.1743289977,38.5408058167],"type":"Point"}
}