{
  "type": "Feature",
  "properties": {
    "iso:country":"ES",
    "sg:address":"Pl Cuba, 18",
    "sg:city":"Mataro",
    "sg:orig_category":"Agencias Y Asesores De Publicidad",
    "sg:phone":"+34 937 55 48 90",
    "sg:postcode":"08302",
    "sg:province":"Barcelona",
    "wof:name":"Altijusa S.l.",
    "wof:placetype":"venue"
},
  "geometry": {"coordinates":[2.4398522377,41.5377845764],"type":"Point"}
}