{
  "type": "Feature",
  "properties": {
    "addr:full":"Calle de Santa Elena, 26 Javali Viejo Murcia 30831",
    "addr:housenumber":"26",
    "addr:postcode":"30831",
    "addr:street":"Calle De Santa Elena",
    "iso:country":"ES",
    "sg:address":"Calle de Santa Elena, 26",
    "sg:city":"Javali Viejo",
    "sg:orig_category":"Empresas De Pintura Y Revestimientos",
    "sg:phone":"+34 968 80 34 77",
    "sg:postcode":"30831",
    "sg:province":"Murcia",
    "wof:name":"Vazquez Guirao Manuel",
    "wof:placetype":"venue"
},
  "geometry": {"coordinates":[-1.2022490501,37.9885597229],"type":"Point"}
}