{
  "type": "Feature",
  "properties": {
    "addr:full":"Calle de Fundicion (de La), 5 Partija-santa Monica Madrid 28529",
    "addr:housenumber":"5",
    "addr:postcode":"28529",
    "addr:street":"Calle De Fundicion De La",
    "iso:country":"ES",
    "sg:address":"Calle de Fundicion (de La), 5",
    "sg:city":"Partija-santa Monica",
    "sg:orig_category":"Agentes, Concesionarios Y Sucursales De Veh\u00cdculos",
    "sg:phone":"+34 914 99 20 05",
    "sg:postcode":"28529",
    "sg:province":"Madrid",
    "sg:website":"www.mazda-es.com",
    "wof:name":"Autoriente S.l.",
    "wof:placetype":"venue"
},
  "geometry": {"coordinates":[-3.7003455162,40.4166908264],"type":"Point"}
}