{
  "type": "Feature",
  "properties": {
    "iso:country":"ES",
    "sg:address":"Barr Vierna, S/n",
    "sg:city":"S. Bartolome Meruelo",
    "sg:orig_category":"Empresas De Electricidad En General",
    "sg:phone":"+34 942 74 36 97",
    "sg:postcode":"39192",
    "sg:province":"Cantabria",
    "wof:name":"Biomeruelo De Energia",
    "wof:placetype":"venue"
},
  "geometry": {"coordinates":[-3.5916581154,43.4340438843],"type":"Point"}
}