{
  "type": "Feature",
  "properties": {
    "iso:country":"ES",
    "sg:address":"Carrer de Santa Eulalia, 18",
    "sg:city":"Hospitalet Llobregat",
    "sg:orig_category":"Abogados",
    "sg:phone":"+34 933 31 68 94",
    "sg:postcode":"08902",
    "sg:province":"Barcelona",
    "wof:name":"Bosch Nerin Antoni",
    "wof:placetype":"venue"
},
  "geometry": {"coordinates":[2.1302530766,41.3681526184],"type":"Point"}
}