{
  "type": "Feature",
  "properties": {
    "addr:full":"Calle de Imperio, 32 Granada Granada 18007",
    "addr:housenumber":"32",
    "addr:postcode":"18007",
    "addr:street":"Calle De Imperio",
    "iso:country":"ES",
    "sg:address":"Calle de Imperio, 32",
    "sg:city":"Granada",
    "sg:orig_category":"Plomeros",
    "sg:phone":"+34 958 12 79 51",
    "sg:postcode":"18007",
    "sg:province":"Granada",
    "wof:name":"Benitez Torres Antonio",
    "wof:placetype":"venue"
},
  "geometry": {"coordinates":[-3.6035430431,37.1542892456],"type":"Point"}
}