{
  "type": "Feature",
  "properties": {
    "iso:country":"ES",
    "sg:address":"Barr El Puerto, 21",
    "sg:city":"Puerto",
    "sg:orig_category":"Comercio De Minerales, F\u00d3siles Y Conchas",
    "sg:phone":"+34 946 36 50 32",
    "sg:postcode":"48508",
    "sg:province":"Vizcaya",
    "wof:name":"Lazcano Mendiola Santiago",
    "wof:placetype":"venue"
},
  "geometry": {"coordinates":[-3.090914011,43.3470497131],"type":"Point"}
}