{
  "type": "Feature",
  "properties": {
    "addr:full":"Luga Birloque, S/n Coru\u00d1a La Coru\u00f1a 15008",
    "addr:housenumber":"s",
    "addr:postcode":"15008",
    "addr:street":"/ N Corun\u0303A La Corun\u0303A",
    "iso:country":"ES",
    "sg:address":"Luga Birloque, S/n",
    "sg:city":"Coru\u00d1a",
    "sg:orig_category":"Fabricaci\u00d3n, Venta, Instalaci\u00d3n De R\u00d3tulos, De R\u00d3tulos Luminosos",
    "sg:phone":"+34 981 13 04 57",
    "sg:postcode":"15008",
    "sg:province":"La Coru\u00f1a",
    "wof:name":"Arduma S.l.",
    "wof:placetype":"venue"
},
  "geometry": {"coordinates":[-8.4129400253,43.3328208923],"type":"Point"}
}