{
  "type": "Feature",
  "properties": {
    "addr:full":"Calle de Metge Gabriel Flors, 1 Sagunt Valencia 46500",
    "addr:housenumber":"1",
    "addr:postcode":"46500",
    "addr:street":"Calle De Metge Gabriel Flors",
    "iso:country":"ES",
    "sg:address":"Calle de Metge Gabriel Flors, 1",
    "sg:city":"Sagunt",
    "sg:orig_category":"Montaje (empresas De)",
    "sg:phone":"+34 962 66 38 58",
    "sg:postcode":"46500",
    "sg:province":"Valencia",
    "wof:name":"Desmontajes S.l.",
    "wof:placetype":"venue"
},
  "geometry": {"coordinates":[-0.2717100084,39.6777038574],"type":"Point"}
}