{
  "type": "Feature",
  "properties": {
    "addr:full":"Luga Poligono Industrial El Palmar, Km. 0653,0 Poligono Industrial El Palmar C\u00e1diz 11500",
    "addr:postcode":"11500",
    "addr:street":"Poligono Industrial El;0653,0 Poligono Industrial",
    "iso:country":"ES",
    "sg:address":"Luga Poligono Industrial El Palmar, Km. 0653,0",
    "sg:city":"Poligono Industrial El Palmar",
    "sg:orig_category":"Fabricaci\u00d3n, Importaci\u00d3n, Venta De Material De Telefon\u00cda, Peritelefon\u00cda",
    "sg:phone":"+34 956 87 12 85",
    "sg:postcode":"11500",
    "sg:province":"C\u00e1diz",
    "wof:name":"Jecomtel Comunicaciones S.l.",
    "wof:placetype":"venue"
},
  "geometry": {"coordinates":[-6.2059574127,36.6198539734],"type":"Point"}
}