{
  "type": "Feature",
  "properties": {
    "iso:country":"ES",
    "sg:address":"Calle de Escalinata, 11",
    "sg:city":"Madrid",
    "sg:orig_category":"Institutos De Belleza",
    "sg:phone":"+34 915 48 26 23",
    "sg:postcode":"28013",
    "sg:province":"Madrid",
    "wof:name":"Marcos Benavente Maria Del Carmen",
    "wof:placetype":"venue"
},
  "geometry": {"coordinates":[-3.7095980644,40.4175987244],"type":"Point"}
}