{
  "type": "Feature",
  "properties": {
    "iso:country":"ES",
    "sg:address":"Avda Madrid, 19",
    "sg:city":"Palencia",
    "sg:orig_category":"Librer\u00cdas",
    "sg:phone":"+34 979 71 41 23",
    "sg:postcode":"34004",
    "sg:province":"Palencia",
    "wof:name":"Correia Gonzalez Jokin",
    "wof:placetype":"venue"
},
  "geometry": {"coordinates":[-4.5213561058,41.995765686],"type":"Point"}
}