{
  "type": "Feature",
  "properties": {
    "addr:full":"San Fermin, 53 Iru\u00f1a Navarra 31003",
    "addr:housenumber":"53",
    "addr:postcode":"31003",
    "addr:street":"San Fermin",
    "iso:country":"ES",
    "sg:address":"San Fermin, 53",
    "sg:city":"Iru\u00f1a",
    "sg:orig_category":"Art\u00cdculos De Aluminio",
    "sg:phone":"+34 948 15 01 64",
    "sg:postcode":"31003",
    "sg:province":"Navarra",
    "sg:website":"www.iespana.es/arpuvensl",
    "wof:name":"Arpuven Iru\u00f1a S.l.",
    "wof:placetype":"venue"
},
  "geometry": {"coordinates":[-1.6410700083,42.8109588623],"type":"Point"}
}