{
  "type": "Feature",
  "properties": {
    "iso:country":"ES",
    "sg:address":"Calle de Jose Antonio, 7",
    "sg:city":"Entrerrios",
    "sg:orig_category":"Laboratorios Y Trabajos De Fotograf\u00cda, V\u00cddeo Y Cine",
    "sg:phone":"+34 924 83 27 39",
    "sg:postcode":"06710",
    "sg:province":"Badajoz",
    "wof:name":"Gutierrez Millan Justo",
    "wof:placetype":"venue"
},
  "geometry": {"coordinates":[-5.7201590538,38.9956054688],"type":"Point"}
}