{
  "type": "Feature",
  "properties": {
    "addr:full":"Calle de Cabrales, 72 Gijon Asturias 33201",
    "addr:housenumber":"72",
    "addr:postcode":"33201",
    "addr:street":"Calle De Cabrales",
    "iso:country":"ES",
    "sg:address":"Calle de Cabrales, 72",
    "sg:city":"Gijon",
    "sg:orig_category":"Art\u00cdculos De Limpieza Y De Cocina (fabricaci\u00d3n, Al Por Mayor)",
    "sg:phone":"+34 985 17 24 70",
    "sg:postcode":"33201",
    "sg:province":"Asturias",
    "wof:name":"Amc Espa\u00d1a Alfa Metalcraft Corp. S. A.",
    "wof:placetype":"venue"
},
  "geometry": {"coordinates":[-5.6601605415,43.5402488708],"type":"Point"}
}