{
  "type": "Feature",
  "properties": {
    "addr:full":"Calle de San Geroteo, 7 Segovia Segovia 40003",
    "addr:housenumber":"7",
    "addr:postcode":"40003",
    "addr:street":"Calle De San Geroteo",
    "iso:country":"ES",
    "sg:address":"Calle de San Geroteo, 7",
    "sg:city":"Segovia",
    "sg:orig_category":"Arquitectos",
    "sg:phone":"+34 921 46 21 96",
    "sg:postcode":"40003",
    "sg:province":"Segovia",
    "wof:name":"Beloqui Gragera Angel",
    "wof:placetype":"venue"
},
  "geometry": {"coordinates":[-4.1260008812,40.9496421814],"type":"Point"}
}