{
  "type": "Feature",
  "properties": {
    "iso:country":"ES",
    "sg:address":"Ctra Albujon, Km. 0020,0",
    "sg:city":"Beatos",
    "sg:orig_category":"Molduras, Junquillos, Listones Y Molduras Perforadas",
    "sg:phone":"+34 968 13 58 40",
    "sg:postcode":"30367",
    "sg:province":"Murcia",
    "wof:name":"Prefabricados Cabo De Palos S.a.",
    "wof:placetype":"venue"
},
  "geometry": {"coordinates":[-0.9019640088,37.6637687683],"type":"Point"}
}