{
  "type": "Feature",
  "properties": {
    "iso:country":"ES",
    "sg:address":"Calle de San Bartolome, 4",
    "sg:city":"Valverde Leganes",
    "sg:orig_category":"Importaci\u00d3n",
    "sg:phone":"+34 924 49 61 42",
    "sg:postcode":"06130",
    "sg:province":"Badajoz",
    "wof:name":"Excarbri S.l.",
    "wof:placetype":"venue"
},
  "geometry": {"coordinates":[-6.9840731621,38.6700325012],"type":"Point"}
}