{
  "type": "Feature",
  "properties": {
    "iso:country":"ES",
    "sg:address":"Calle de San Ignacio, 2",
    "sg:city":"Villafranca De Los Barros",
    "sg:orig_category":"Internados & Ense\u00d1anza Privada",
    "sg:phone":"+34 924 52 40 01",
    "sg:postcode":"06220",
    "sg:province":"Badajoz",
    "sg:website":"www.sanjosecolegio.org",
    "wof:name":"Colegio De San Jose",
    "wof:placetype":"venue"
},
  "geometry": {"coordinates":[-6.3362298012,38.5643768311],"type":"Point"}
}