{
  "type": "Feature",
  "properties": {
    "iso:country":"ES",
    "sg:address":"Calle de Comandante Cristobal, 3",
    "sg:city":"Sepulveda",
    "sg:orig_category":"Venta, Instalaci\u00d3n De Calefacci\u00d3n",
    "sg:phone":"+34 921 54 00 02",
    "sg:postcode":"40300",
    "sg:province":"Segovia",
    "wof:name":"Palermo Torrego Pedro",
    "wof:placetype":"venue"
},
  "geometry": {"coordinates":[-3.750982523,41.3012809753],"type":"Point"}
}