{
  "type": "Feature",
  "properties": {
    "iso:country":"ES",
    "sg:address":"Pase Pe\u00d1on De La Mata, 5",
    "sg:city":"Cogollos Vega",
    "sg:orig_category":"Molduras, Junquillos, Listones Y Molduras Perforadas",
    "sg:phone":"+34 958 40 93 76",
    "sg:postcode":"18197",
    "sg:province":"Granada",
    "wof:name":"Sanchez Leyva Antonio",
    "wof:placetype":"venue"
},
  "geometry": {"coordinates":[-3.6097240448,37.2210998535],"type":"Point"}
}