{
  "type": "Feature",
  "properties": {
    "iso:country":"ES",
    "sg:address":"Calle de Menendez Pelayo, 1",
    "sg:city":"Molina Segura",
    "sg:orig_category":"Dietistas",
    "sg:phone":"+34 968 64 17 73",
    "sg:postcode":"30500",
    "sg:province":"Murcia",
    "wof:name":"Pastor Valero Rebeca",
    "wof:placetype":"venue"
},
  "geometry": {"coordinates":[-1.2120679617,38.0540847778],"type":"Point"}
}