{
  "type": "Feature",
  "properties": {
    "addr:full":"Plaz Luceros (los), 18 Alacant Alicante 03004",
    "addr:postcode":"03004",
    "addr:street":"Plaz;Los",
    "iso:country":"ES",
    "sg:address":"Plaz Luceros (los), 18",
    "sg:city":"Alacant",
    "sg:orig_category":"M\u00c9dicos: Pediatr\u00cda. Enfermedades De Los Ni\u00d1os",
    "sg:phone":"+34 965 21 89 70",
    "sg:postcode":"03004",
    "sg:province":"Alicante",
    "wof:name":"Sanchez Alvarez Rafael",
    "wof:placetype":"venue"
},
  "geometry": {"coordinates":[-0.4902279973,38.3463058472],"type":"Point"}
}