{
  "type": "Feature",
  "properties": {
    "iso:country":"ES",
    "sg:address":"Avgd Pere Mas I Reus, S/n",
    "sg:city":"Platja D'alcudia",
    "sg:orig_category":"Art\u00cdculos De Regalo (al Por Menor)",
    "sg:phone":"+34 971 89 17 37",
    "sg:postcode":"07408",
    "sg:province":"Islas Baleares",
    "wof:name":"Company Fiol S.c.",
    "wof:placetype":"venue"
},
  "geometry": {"coordinates":[3.1255340576,39.8456192017],"type":"Point"}
}