{
  "type": "Feature",
  "properties": {
    "iso:country":"ES",
    "sg:address":"Avda Adolfo Suarez, 1",
    "sg:city":"Torre-pacheco",
    "sg:orig_category":"Maquinaria Para Industrias Diversas",
    "sg:phone":"+34 968 57 83 47",
    "sg:postcode":"30700",
    "sg:province":"Murcia",
    "wof:name":"Lopez Moreno Luis",
    "wof:placetype":"venue"
},
  "geometry": {"coordinates":[-1.1302490234,37.9829597473],"type":"Point"}
}