{
  "type": "Feature",
  "properties": {
    "iso:country":"ES",
    "sg:address":"Plaz Mayor, 17",
    "sg:city":"Alba Tormes",
    "sg:orig_category":"Par\u00cds",
    "sg:phone":"+34 923 37 04 16",
    "sg:postcode":"37800",
    "sg:province":"Salamanca",
    "wof:name":"Hernandez Martin Maria Jesus",
    "wof:placetype":"venue"
},
  "geometry": {"coordinates":[-5.5114722252,40.8238334656],"type":"Point"}
}