{
  "type": "Feature",
  "properties": {
    "addr:full":"Disseminat, S/n Llerona Barcelona 08520",
    "addr:postcode":"08520",
    "addr:street":"Disseminat S / N",
    "iso:country":"ES",
    "sg:address":"Disseminat, S/n",
    "sg:city":"Llerona",
    "sg:orig_category":"Cooperativas Agr\u00cdcolas",
    "sg:phone":"+34 938 49 53 81",
    "sg:postcode":"08520",
    "sg:province":"Barcelona",
    "wof:name":"Cooperativa Agraria Comarcal Del Valles S.c.c.l.",
    "wof:placetype":"venue"
},
  "geometry": {"coordinates":[2.2992899418,41.6361808777],"type":"Point"}
}