{
  "type": "Feature",
  "properties": {
    "iso:country":"ES",
    "sg:address":"Calle de Pintor Gustavo De Maeztu, 2",
    "sg:city":"Vitoria-gasteiz",
    "sg:orig_category":"Control T\u00c9cnico De Veh\u00cdculos",
    "sg:phone":"+34 945 22 27 12",
    "sg:postcode":"01008",
    "sg:province":"\u00c1lava",
    "wof:name":"Santiago Millan Fernando",
    "wof:placetype":"venue"
},
  "geometry": {"coordinates":[-2.6868970394,42.8498191833],"type":"Point"}
}