{
  "type": "Feature",
  "properties": {
    "iso:country":"ES",
    "sg:address":"Carrer de Riera Major, 2",
    "sg:city":"Vic",
    "sg:orig_category":"Guarder\u00cdas",
    "sg:phone":"+34 938 83 22 63",
    "sg:postcode":"08500",
    "sg:province":"Barcelona",
    "wof:name":"Associacio Guarderia Serra De Sant Ferm",
    "wof:placetype":"venue"
},
  "geometry": {"coordinates":[2.2567665577,41.9136199951],"type":"Point"}
}