{
  "type": "Feature",
  "properties": {
    "addr:full":"Carrer de Reina Victoria, 24 Barcelona Barcelona 08021",
    "addr:housenumber":"24",
    "addr:postcode":"08021",
    "addr:street":"Carrer De Reina Victoria",
    "iso:country":"ES",
    "sg:address":"Carrer de Reina Victoria, 24",
    "sg:city":"Barcelona",
    "sg:orig_category":"Comerciantes Al Por Mayor De Vinos, Licores Y Alcoholes",
    "sg:phone":"+34 932 00 73 34",
    "sg:postcode":"08021",
    "sg:province":"Barcelona",
    "wof:name":"Destilerias Mg S.l.",
    "wof:placetype":"venue"
},
  "geometry": {"coordinates":[2.1371619701,41.3971176147],"type":"Point"}
}