{
  "type": "Feature",
  "properties": {
    "addr:full":"C/ Sant Miquel, 2 Inca Islas Baleares 07300",
    "addr:housenumber":"2",
    "addr:postcode":"07300",
    "addr:street":"C / Sant Miquel",
    "iso:country":"ES",
    "sg:address":"C/ Sant Miquel, 2",
    "sg:city":"Inca",
    "sg:orig_category":"Veh\u00cdculos De Ocasi\u00d3n",
    "sg:phone":"+34 971 88 00 72",
    "sg:postcode":"07300",
    "sg:province":"Islas Baleares",
    "wof:name":"Nou Espai Inmobiliari S.l",
    "wof:placetype":"venue"
},
  "geometry": {"coordinates":[2.9145610332,39.7169113159],"type":"Point"}
}