{
  "type": "Feature",
  "properties": {
    "iso:country":"ES",
    "sg:address":"Avgd Gregorio Molina, 6",
    "sg:city":"Xativa",
    "sg:orig_category":"Procuradores",
    "sg:phone":"+34 962 27 79 29",
    "sg:postcode":"46800",
    "sg:province":"Valencia",
    "wof:name":"Diego Vicedo Maria Jose",
    "wof:placetype":"venue"
},
  "geometry": {"coordinates":[-0.5232629776,38.9911575317],"type":"Point"}
}