{
  "type": "Feature",
  "properties": {
    "addr:full":"Calle de Calvario, S/n Torrechiva Castell\u00f3n 12232",
    "addr:housenumber":"s",
    "addr:postcode":"12232",
    "addr:street":"Calle De Calvario;/ N;Castello\u0301N",
    "iso:country":"ES",
    "sg:address":"Calle de Calvario, S/n",
    "sg:city":"Torrechiva",
    "sg:orig_category":"Asociaciones Humanitarias, De Cooperaci\u00d3n, De Acci\u00d3n Social",
    "sg:phone":"+34 964 61 21 74",
    "sg:postcode":"12232",
    "sg:province":"Castell\u00f3n",
    "wof:name":"Comunidades De Emaus",
    "wof:placetype":"venue"
},
  "geometry": {"coordinates":[-0.4819569886,40.0713195801],"type":"Point"}
}