{
  "type": "Feature",
  "properties": {
    "iso:country":"ES",
    "sg:address":"Cmno Ronda (de), 81",
    "sg:city":"Granada",
    "sg:orig_category":"Ingeniero",
    "sg:phone":"+34 958 25 95 18",
    "sg:postcode":"18004",
    "sg:province":"Granada",
    "wof:name":"Garcia Martinez Joaquin",
    "wof:placetype":"venue"
},
  "geometry": {"coordinates":[-3.6070439816,37.1717376709],"type":"Point"}
}