{
  "type": "Feature",
  "properties": {
    "iso:country":"ES",
    "sg:address":"Padre Alejandro Recio, S/n",
    "sg:city":"Martos",
    "sg:orig_category":"Ense\u00d1anza: Idiomas",
    "sg:phone":"+34 953 70 03 13",
    "sg:postcode":"23600",
    "sg:province":"Ja\u00e9n",
    "wof:name":"English Matters S.l.",
    "wof:placetype":"venue"
},
  "geometry": {"coordinates":[-3.9733240604,37.7187805176],"type":"Point"}
}