{
  "type": "Feature",
  "properties": {
    "addr:full":"Cmno Valderribas, 93 Madrid Madrid 28038",
    "addr:housenumber":"93",
    "addr:postcode":"madrid;28038",
    "addr:street":"Cmno Valderribas",
    "iso:country":"ES",
    "sg:address":"Cmno Valderribas, 93",
    "sg:city":"Madrid",
    "sg:orig_category":"Caf\u00c9s, Bares, Cervecer\u00cdas",
    "sg:phone":"+34 913 28 34 66",
    "sg:postcode":"28038",
    "sg:province":"Madrid",
    "wof:name":"Jimenez Garcia Adelino",
    "wof:placetype":"venue"
},
  "geometry": {"coordinates":[-3.6614029408,40.3992881775],"type":"Point"}
}