{
  "type": "Feature",
  "properties": {
    "iso:country":"ES",
    "sg:address":"Carr Isabel Ii, D', 43",
    "sg:city":"Soller",
    "sg:orig_category":"Art\u00cdculos Funerarios (al Por Menor)",
    "sg:phone":"+34 971 63 31 43",
    "sg:postcode":"07100",
    "sg:province":"Islas Baleares",
    "wof:name":"Lloret Ortega S.l",
    "wof:placetype":"venue"
},
  "geometry": {"coordinates":[2.7137908936,39.764541626],"type":"Point"}
}