{
  "type": "Feature",
  "properties": {
    "iso:country":"ES",
    "sg:address":"Grup Cooperativa San Juan Bautista, 15",
    "sg:city":"Aguilar Campoo",
    "sg:orig_category":"Transportes Por V\u00cdas Navegables",
    "sg:phone":"+34 979 12 55 13",
    "sg:postcode":"34800",
    "sg:province":"Palencia",
    "wof:name":"Transportes Y Logistica Aguilar S.l.",
    "wof:placetype":"venue"
},
  "geometry": {"coordinates":[-4.2607240677,42.795501709],"type":"Point"}
}