{
  "type": "Feature",
  "properties": {
    "iso:country":"ES",
    "sg:address":"Harizti Industrialdea, 1",
    "sg:city":"Ihurre",
    "sg:orig_category":"Supermercados Y Hipermercados",
    "sg:phone":"+34 943 88 03 33",
    "sg:postcode":"20212",
    "sg:province":"Guip\u00f9zcoa",
    "wof:name":"Carrefour Norte S.l.",
    "wof:placetype":"venue"
},
  "geometry": {"coordinates":[-2.2013700008,43.0282554626],"type":"Point"}
}