{
  "type": "Feature",
  "properties": {
    "iso:country":"ES",
    "sg:address":"Pau Claris 138",
    "sg:city":"Barcelona",
    "sg:classifiers":[
        {
            "category":"Professional",
            "subcategory":"Computer Services",
            "type":"Services"
        }
    ],
    "sg:postcode":"08009",
    "sg:tags":[
        "open-source",
        "erp",
        "pos"
    ],
    "sg:website":"http://www.openbravo.com",
    "wof:name":"Openbravo",
    "wof:placetype":"venue"
},
  "geometry": {"coordinates":[2.1660785,41.3935324],"type":"Point"}
}