{
  "type": "Feature",
  "properties": {
    "iso:country":"ES",
    "sg:address":"Carrer de La Rambla, 132",
    "sg:city":"Barcelona",
    "sg:orig_category":"Art\u00cdculos De Regalo (al Por Menor)",
    "sg:phone":"+34 933 17 84 27",
    "sg:postcode":"08002",
    "sg:province":"Barcelona",
    "wof:name":"Su\u00f1ol Kulia Rafael",
    "wof:placetype":"venue"
},
  "geometry": {"coordinates":[2.1710429192,41.384563446],"type":"Point"}
}