{
  "type": "Feature",
  "properties": {
    "addr:full":"Calle de Tomelloso, 14 Ciudad Real Ciudad Real 13005",
    "addr:housenumber":"14",
    "addr:postcode":"13005",
    "addr:street":"Calle De Tomelloso",
    "iso:country":"ES",
    "sg:address":"Calle de Tomelloso, 14",
    "sg:city":"Ciudad Real",
    "sg:orig_category":"Mec\u00c1nico Del Autom\u00d3vil",
    "sg:phone":"+34 926 21 05 64",
    "sg:postcode":"13005",
    "sg:province":"Ciudad Real",
    "wof:name":"Servidiesel Ciudad Real S.l.",
    "wof:placetype":"venue"
},
  "geometry": {"coordinates":[-3.934016943,38.9734611511],"type":"Point"}
}