{
  "type": "Feature",
  "properties": {
    "addr:full":"Ctra Tortosa, Km. 0012,0 Aldea Tarragona 43896",
    "addr:postcode":"43896",
    "addr:street":"Ctra Tortosa Km. 0012,0",
    "iso:country":"ES",
    "sg:address":"Ctra Tortosa, Km. 0012,0",
    "sg:city":"Aldea",
    "sg:orig_category":"Escayola Y Productos De Escayola (fabricaci\u00d3n, Al Por Mayor)",
    "sg:phone":"+34 977 45 03 81",
    "sg:postcode":"43896",
    "sg:province":"Tarragona",
    "wof:name":"Escayolas Bismarch S.l.",
    "wof:placetype":"venue"
},
  "geometry": {"coordinates":[0.6109700203,40.7413139343],"type":"Point"}
}