{
  "type": "Feature",
  "properties": {
    "iso:country":"ES",
    "sg:address":"Calle de Vega, 29",
    "sg:city":"Chiclana De La Frontera",
    "sg:orig_category":"\u00d3ptica: Instrumentos (fabricaci\u00d3n)",
    "sg:phone":"+34 956 40 19 18",
    "sg:postcode":"11130",
    "sg:province":"C\u00e1diz",
    "wof:name":"Perez Gonzalez Ramon",
    "wof:placetype":"venue"
},
  "geometry": {"coordinates":[-6.1490302086,36.4198036194],"type":"Point"}
}