{
  "type": "Feature",
  "properties": {
    "iso:country":"ES",
    "sg:address":"Avda Orihuela-torremendo, S/n",
    "sg:city":"Torremendo",
    "sg:orig_category":"Iglesia Cat\u00d3lica",
    "sg:phone":"+34 965 36 80 59",
    "sg:postcode":"03313",
    "sg:province":"Alicante",
    "wof:name":"Parroquia De Nuestra Se\u00f1ora De Monserrate",
    "wof:placetype":"venue"
},
  "geometry": {"coordinates":[-0.9217389822,38.0595855713],"type":"Point"}
}