{
  "type": "Feature",
  "properties": {
    "iso:country":"ES",
    "sg:address":"Rbla Sant Esteve (de), 25",
    "sg:city":"Ripollet",
    "sg:orig_category":"Agencias De Viajes",
    "sg:phone":"+34 935 91 03 91",
    "sg:postcode":"08291",
    "sg:province":"Barcelona",
    "wof:name":"Pich Brothers Sl",
    "wof:placetype":"venue"
},
  "geometry": {"coordinates":[2.1572859287,41.5002250671],"type":"Point"}
}