{
  "type": "Feature",
  "properties": {
    "addr:full":"Av Manuel Girona, 16 Castelldefels Barcelona 08860",
    "addr:housenumber":"16",
    "addr:postcode":"08860",
    "addr:street":"Av Manuel Girona",
    "iso:country":"ES",
    "sg:address":"Av Manuel Girona, 16",
    "sg:city":"Castelldefels",
    "sg:orig_category":"Institutos De Belleza",
    "sg:phone":"+34 936 36 09 17",
    "sg:postcode":"08860",
    "sg:province":"Barcelona",
    "wof:name":"Sol Castelldefels S.l.",
    "wof:placetype":"venue"
},
  "geometry": {"coordinates":[1.9832830429,41.2851448059],"type":"Point"}
}