{
  "type": "Feature",
  "properties": {
    "addr:full":"Calle de Abrucena, 90 Almeria Almer\u00eda 04007",
    "addr:housenumber":"90",
    "addr:postcode":"04007",
    "addr:street":"Calle De Abrucena",
    "iso:country":"ES",
    "sg:address":"Calle de Abrucena, 90",
    "sg:city":"Almeria",
    "sg:orig_category":"Confecci\u00d3n (fabricaci\u00d3n, Al Por Mayor)",
    "sg:phone":"+34 950 27 56 44",
    "sg:postcode":"04007",
    "sg:province":"Almer\u00eda",
    "wof:name":"Martinez Ortiz Isabel",
    "wof:placetype":"venue"
},
  "geometry": {"coordinates":[-2.4471774101,36.8276023865],"type":"Point"}
}