{
  "type": "Feature",
  "properties": {
    "addr:full":"Calle de Colon, 32 Castellon Castell\u00f3n 12001",
    "addr:housenumber":"32",
    "addr:postcode":"12001",
    "addr:street":"Calle De Colon",
    "iso:country":"ES",
    "sg:address":"Calle de Colon, 32",
    "sg:city":"Castellon",
    "sg:orig_category":"Trajes Y Adornos De Boda (confecci\u00d3n, Al Por Menor)",
    "sg:phone":"+34 964 22 31 13",
    "sg:postcode":"12001",
    "sg:province":"Castell\u00f3n",
    "wof:name":"Victor Blasco S.l.",
    "wof:placetype":"venue"
},
  "geometry": {"coordinates":[-0.0379149988,39.9867591858],"type":"Point"}
}