{
  "type": "Feature",
  "properties": {
    "addr:full":"Ptda Santa, S/n Alcora Castell\u00f3n 12110",
    "addr:housenumber":"s / n",
    "addr:postcode":"12110",
    "addr:street":"Ptda Santa;Alcora Castello\u0301N",
    "iso:country":"ES",
    "sg:address":"Ptda Santa, S/n",
    "sg:city":"Alcora",
    "sg:orig_category":"Empresas De Desmonte",
    "sg:phone":"+34 964 38 63 61",
    "sg:postcode":"12110",
    "sg:province":"Castell\u00f3n",
    "wof:name":"Jose Granell S.l.",
    "wof:placetype":"venue"
},
  "geometry": {"coordinates":[-0.2178789973,40.0734786987],"type":"Point"}
}