{
  "type": "Feature",
  "properties": {
    "iso:country":"ES",
    "sg:address":"Carr Germans Perello, 21",
    "sg:city":"Alaro",
    "sg:orig_category":"Tiendas De Grano, Frutas Y Legumbres Secas (al Por Menor)",
    "sg:phone":"+34 971 51 01 97",
    "sg:postcode":"07340",
    "sg:province":"Islas Baleares",
    "wof:name":"Rossello Borras Arnaldo",
    "wof:placetype":"venue"
},
  "geometry": {"coordinates":[2.7917249203,39.7054519653],"type":"Point"}
}