{
  "type": "Feature",
  "properties": {
    "iso:country":"ES",
    "sg:address":"Carrer de Batan, 13",
    "sg:city":"Reus",
    "sg:orig_category":"Cl\u00cdnicas Dentales",
    "sg:phone":"+34 977 77 09 08",
    "sg:postcode":"43204",
    "sg:province":"Tarragona",
    "wof:name":"Gabinet De Serveis Dentals S.c.",
    "wof:placetype":"venue"
},
  "geometry": {"coordinates":[1.1109880209,41.1528129578],"type":"Point"}
}