{
  "type": "Feature",
  "properties": {
    "addr:full":"Calle de Oca, 86 Madrid Madrid 28025",
    "addr:housenumber":"86",
    "addr:postcode":"madrid;28025",
    "addr:street":"Calle De Oca",
    "iso:country":"ES",
    "sg:address":"Calle de Oca, 86",
    "sg:city":"Madrid",
    "sg:orig_category":"Material Y Suministros Para Peluquer\u00cda",
    "sg:phone":"+34 914 65 33 11",
    "sg:postcode":"28025",
    "sg:province":"Madrid",
    "wof:name":"Mu\u00d1umel Gordillo Maria Del Carmen",
    "wof:placetype":"venue"
},
  "geometry": {"coordinates":[-3.7416408062,40.388458252],"type":"Point"}
}