{
  "type": "Feature",
  "properties": {
    "iso:country":"ES",
    "sg:address":"Carr Doctor Zamenhof, 43",
    "sg:city":"Vilanova I La Geltru",
    "sg:orig_category":"Asesor\u00cda Fiscal Y Jur\u00cddica",
    "sg:phone":"+34 938 15 53 44",
    "sg:postcode":"08800",
    "sg:province":"Barcelona",
    "wof:name":"A.i.a. Assessors S.c.p.",
    "wof:placetype":"venue"
},
  "geometry": {"coordinates":[1.710614562,41.2219772339],"type":"Point"}
}