{
  "type": "Feature",
  "properties": {
    "addr:full":"Calle de Virgen De Los Remedios, 3 Aguilafuente Segovia 40340",
    "addr:housenumber":"3",
    "addr:postcode":"40340",
    "addr:street":"Calle De Virgen De Los Remedios",
    "iso:country":"ES",
    "sg:address":"Calle de Virgen De Los Remedios, 3",
    "sg:city":"Aguilafuente",
    "sg:orig_category":"Electricidad: Instaladores",
    "sg:phone":"+34 921 57 23 11",
    "sg:postcode":"40340",
    "sg:province":"Segovia",
    "wof:name":"Herrero Herranz Carlos",
    "wof:placetype":"venue"
},
  "geometry": {"coordinates":[-4.1186189651,41.2269477844],"type":"Point"}
}