{
  "type": "Feature",
  "properties": {
    "iso:country":"ES",
    "sg:address":"Calle de Olimpo, 50",
    "sg:city":"Madrid",
    "sg:orig_category":"Centros Empresariales",
    "sg:phone":"+34 913 88 72 68",
    "sg:postcode":"28043",
    "sg:province":"Madrid",
    "wof:name":"Internacional De Tecnologia Y Sistemas S.a",
    "wof:placetype":"venue"
},
  "geometry": {"coordinates":[-3.646625042,40.4557991028],"type":"Point"}
}