{
  "type": "Feature",
  "properties": {
    "addr:full":"Ctra Almeria - Torrenueva, Km. 0003,4 Torrenueva Granada 18720",
    "addr:postcode":"18720",
    "addr:street":"Ctra Almeria Torrenueva Km. 0003,4",
    "iso:country":"ES",
    "sg:address":"Ctra Almeria - Torrenueva, Km. 0003,4",
    "sg:city":"Torrenueva",
    "sg:orig_category":"Producci\u00d3n De Abonos Y De Fertilizantes",
    "sg:phone":"+34 958 65 51 78",
    "sg:postcode":"18720",
    "sg:province":"Granada",
    "wof:name":"Urquieta Pizarro Arturo",
    "wof:placetype":"venue"
},
  "geometry": {"coordinates":[-3.4922590256,36.7082748413],"type":"Point"}
}