{
  "type": "Feature",
  "properties": {
    "iso:country":"ES",
    "sg:address":"Calle de Clemente Velasco, 43",
    "sg:city":"Ciudad Rodrigo",
    "sg:orig_category":"Alimentaci\u00d3n General (al Por Mayor)",
    "sg:phone":"+34 923 46 13 52",
    "sg:postcode":"37500",
    "sg:province":"Salamanca",
    "wof:name":"Robledo Jimenez S.a.l.",
    "wof:placetype":"venue"
},
  "geometry": {"coordinates":[-6.5374231339,40.5904426575],"type":"Point"}
}