{
  "type": "Feature",
  "properties": {
    "addr:full":"Avda Clara Campoamor, 12 Camas Sevilla 41900",
    "addr:housenumber":"12",
    "addr:postcode":"41900",
    "addr:street":"Avda Clara Campoamor",
    "iso:country":"ES",
    "sg:address":"Avda Clara Campoamor, 12",
    "sg:city":"Camas",
    "sg:orig_category":"Promotores Constructores",
    "sg:phone":"+34 954 39 34 15",
    "sg:postcode":"41900",
    "sg:province":"Sevilla",
    "wof:name":"Comunidad De Propietarios Clara Campoamor 12",
    "wof:placetype":"venue"
},
  "geometry": {"coordinates":[-6.0344491005,37.4007263184],"type":"Point"}
}