{
  "type": "Feature",
  "properties": {
    "addr:full":"Rua Galicia, 53 Guarda Pontevedra 36780",
    "addr:housenumber":"53",
    "addr:postcode":"36780",
    "addr:street":"Rua Galicia",
    "iso:country":"ES",
    "sg:address":"Rua Galicia, 53",
    "sg:city":"Guarda",
    "sg:orig_category":"Frutas Y Legumbres Frescas (al Por Mayor)",
    "sg:phone":"+34 986 61 02 09",
    "sg:postcode":"36780",
    "sg:province":"Pontevedra",
    "wof:name":"Frutas Nieves S. L.",
    "wof:placetype":"venue"
},
  "geometry": {"coordinates":[-8.869389534,41.9026184082],"type":"Point"}
}