{
  "type": "Feature",
  "properties": {
    "addr:full":"Zona Campdora, 2 Campdora Girona 17461",
    "addr:housenumber":"2",
    "addr:postcode":"17461",
    "addr:street":"Campdora",
    "iso:country":"ES",
    "sg:address":"Zona Campdora, 2",
    "sg:city":"Campdora",
    "sg:orig_category":"Electrolisis, Depurado Del Aluminio Y De Aleaciones",
    "sg:phone":"+34 972 21 53 34",
    "sg:postcode":"17461",
    "sg:province":"Girona",
    "wof:name":"General Galvanica Gironina S.l.",
    "wof:placetype":"venue"
},
  "geometry": {"coordinates":[2.8442840576,42.0145835876],"type":"Point"}
}