{
  "type": "Feature",
  "properties": {
    "addr:full":"Carrer de Castelao, 5 Hospitalet Llobregat Barcelona 08902",
    "addr:housenumber":"5",
    "addr:postcode":"08902",
    "addr:street":"Carrer De Castelao",
    "iso:country":"ES",
    "sg:address":"Carrer de Castelao, 5",
    "sg:city":"Hospitalet Llobregat",
    "sg:orig_category":"Mec\u00c1nico Del Autom\u00d3vil",
    "sg:phone":"+34 933 31 49 95",
    "sg:postcode":"08902",
    "sg:province":"Barcelona",
    "wof:name":"Kand S.a.",
    "wof:placetype":"venue"
},
  "geometry": {"coordinates":[2.1231460571,41.366153717],"type":"Point"}
}