{
  "type": "Feature",
  "properties": {
    "addr:full":"Calle de Marcelo Usera, 55 Madrid Madrid 28026",
    "addr:housenumber":"55",
    "addr:postcode":"madrid;28026",
    "addr:street":"Calle De Marcelo Usera",
    "iso:country":"ES",
    "sg:address":"Calle de Marcelo Usera, 55",
    "sg:city":"Madrid",
    "sg:orig_category":"Ropa Para Se\u00d1oras (al Por Menor)",
    "sg:phone":"+34 914 76 31 70",
    "sg:postcode":"28026",
    "sg:province":"Madrid",
    "wof:name":"Olalde Gonzalez Concepcion",
    "wof:placetype":"venue"
},
  "geometry": {"coordinates":[-3.704087019,40.3859519958],"type":"Point"}
}