{
  "type": "Feature",
  "properties": {
    "addr:full":"Calle de Gines, 3 Sevilla Sevilla 41016",
    "addr:housenumber":"3",
    "addr:postcode":"41016",
    "addr:street":"Calle De Gines",
    "iso:country":"ES",
    "sg:address":"Calle de Gines, 3",
    "sg:city":"Sevilla",
    "sg:orig_category":"Transportes Por V\u00cdas Navegables",
    "sg:phone":"+34 954 51 25 02",
    "sg:postcode":"41016",
    "sg:province":"Sevilla",
    "wof:name":"Bayo Perez Antonio",
    "wof:placetype":"venue"
},
  "geometry": {"coordinates":[-5.9110798836,37.3846969604],"type":"Point"}
}