{
  "type": "Feature",
  "properties": {
    "addr:full":"Ctra Est. F. Oroso-ordes, 3 Sigueiro La Coru\u00f1a 15888",
    "addr:housenumber":"3",
    "addr:postcode":"15888",
    "addr:street":"Ctra Est. F. Oroso-Ordes;La Corun\u0303A",
    "iso:country":"ES",
    "sg:address":"Ctra Est. F. Oroso-ordes, 3",
    "sg:city":"Sigueiro",
    "sg:orig_category":"Empresas De Impermeabilizaci\u00d3n",
    "sg:phone":"+34 981 69 19 98",
    "sg:postcode":"15888",
    "sg:province":"La Coru\u00f1a",
    "wof:name":"Pereiro Vazquez Enrique",
    "wof:placetype":"venue"
},
  "geometry": {"coordinates":[-8.4441986084,42.966709137],"type":"Point"}
}