{
  "type": "Feature",
  "properties": {
    "iso:country":"ES",
    "sg:address":"Rio, S/n",
    "sg:city":"Vilamarin",
    "sg:orig_category":"Serrer\u00cdas De Madera",
    "sg:phone":"+34 988 28 60 40",
    "sg:postcode":"32101",
    "sg:province":"Ourense",
    "wof:name":"Maderas Cacharolos S.a.",
    "wof:placetype":"venue"
},
  "geometry": {"coordinates":[-7.8816328049,42.4782485962],"type":"Point"}
}