{
  "type": "Feature",
  "properties": {
    "addr:full":"Calle de Santa Engracia, 2 Madrid Madrid 28010",
    "addr:housenumber":"2",
    "addr:postcode":"28010",
    "addr:street":"Calle De Santa Engracia",
    "iso:country":"ES",
    "sg:address":"Calle de Santa Engracia, 2",
    "sg:city":"Madrid",
    "sg:classifiers":[
        {
            "category":"Autos & Motor Vehicles",
            "subcategory":"Automobile Sales",
            "type":"Retail Goods"
        }
    ],
    "sg:phone":"+34 913 08 40 51",
    "sg:postcode":"28010",
    "sg:province":"Madrid",
    "wof:name":"Autoescuela Rafael Alvarez S.l.",
    "wof:placetype":"venue"
},
  "geometry": {"coordinates":[-3.6958804131,40.4283752441],"type":"Point"}
}