{
  "type": "Feature",
  "properties": {
    "addr:full":"Calle de Zubieta, 11 Donostia-san Sebastian Guip\u00f9zcoa 20007",
    "addr:housenumber":"11",
    "addr:postcode":"20007",
    "addr:street":"Calle De Zubieta",
    "iso:country":"ES",
    "sg:address":"Calle de Zubieta, 11",
    "sg:city":"Donostia-san Sebastian",
    "sg:orig_category":"M\u00c9dicos: Oftalmolog\u00cda",
    "sg:phone":"+34 943 44 46 79",
    "sg:postcode":"20007",
    "sg:province":"Guip\u00f9zcoa",
    "wof:name":"Loiola Lohizune S.l.",
    "wof:placetype":"venue"
},
  "geometry": {"coordinates":[-1.9866579771,43.3160057068],"type":"Point"}
}