{
  "type": "Feature",
  "properties": {
    "addr:full":"Avda Miguel Rodriguez Bautista, 46 Santa Uxia De Ribeira La Coru\u00f1a 15960",
    "addr:housenumber":"46",
    "addr:postcode":"15960",
    "addr:street":"Avda Miguel Rodriguez Bautista;Corun\u0303A",
    "iso:country":"ES",
    "sg:address":"Avda Miguel Rodriguez Bautista, 46",
    "sg:city":"Santa Uxia De Ribeira",
    "sg:orig_category":"Peluquer\u00cdas, Peluquer\u00cda Mixta",
    "sg:phone":"+34 981 87 05 70",
    "sg:postcode":"15960",
    "sg:province":"La Coru\u00f1a",
    "wof:name":"Gonzalez Garcia Maria Encarnacion",
    "wof:placetype":"venue"
},
  "geometry": {"coordinates":[-8.9944419861,42.5584106445],"type":"Point"}
}