{
  "type": "Feature",
  "properties": {
    "iso:country":"ES",
    "sg:address":"Calle de Castilla, 6",
    "sg:city":"Madrid",
    "sg:orig_category":"Radiocomunicaciones, Telefon\u00cda M\u00d3vil, Radiomensajer\u00cda: Servicios, Comercializaci\u00d3n",
    "sg:phone":"+34 914 50 13 29",
    "sg:postcode":"28039",
    "sg:province":"Madrid",
    "wof:name":"Telecomunicaciones Majo",
    "wof:placetype":"venue"
},
  "geometry": {"coordinates":[-3.7034225464,40.4529037476],"type":"Point"}
}