{
  "type": "Feature",
  "properties": {
    "iso:country":"ES",
    "sg:address":"Calle de Archiduque Alberto, 4",
    "sg:city":"Madrid",
    "sg:orig_category":"Enfermeras: Consultas, Atenci\u00d3n A Domicilio",
    "sg:phone":"+34 917 50 19 59",
    "sg:postcode":"28050",
    "sg:province":"Madrid",
    "wof:name":"Garcia Rey Rocio",
    "wof:placetype":"venue"
},
  "geometry": {"coordinates":[-3.6540014744,40.4930610657],"type":"Point"}
}