{
  "type": "Feature",
  "properties": {
    "iso:country":"ES",
    "sg:address":"Calle de Aragon, 2",
    "sg:city":"Corrales",
    "sg:orig_category":"Mercer\u00cda, Lencer\u00cda (al Por Menor)",
    "sg:phone":"+34 942 84 20 40",
    "sg:postcode":"39400",
    "sg:province":"Cantabria",
    "wof:name":"Gonzalez Perez Mercedes",
    "wof:placetype":"venue"
},
  "geometry": {"coordinates":[-4.0698013306,43.2590751648],"type":"Point"}
}