{
  "type": "Feature",
  "properties": {
    "addr:full":"Cami Ribamar, 15 Ribamar Castell\u00f3n 12579",
    "addr:housenumber":"15",
    "addr:postcode":"12579",
    "addr:street":"Ribamar",
    "iso:country":"ES",
    "sg:address":"Cami Ribamar, 15",
    "sg:city":"Ribamar",
    "sg:orig_category":"Art\u00cdculos De Regalo (al Por Menor)",
    "sg:phone":"+34 964 41 44 63",
    "sg:postcode":"12579",
    "sg:province":"Castell\u00f3n",
    "wof:name":"El Rocio Alcocebre S.l.",
    "wof:placetype":"venue"
},
  "geometry": {"coordinates":[0.2712750137,40.2442741394],"type":"Point"}
}