{
  "type": "Feature",
  "properties": {
    "iso:country":"ES",
    "sg:address":"Calle de Cristo, 43",
    "sg:city":"Roda",
    "sg:orig_category":"Textil",
    "sg:phone":"+34 967 54 86 16",
    "sg:postcode":"02630",
    "sg:province":"Albacete",
    "wof:name":"Aaltair Maintenance Services S.l.",
    "wof:placetype":"venue"
},
  "geometry": {"coordinates":[-2.160145,39.204746],"type":"Point"}
}