{
  "type": "Feature",
  "properties": {
    "addr:full":"Cami Fondo, S/n Corbera Valencia 46612",
    "addr:housenumber":"s / n",
    "addr:postcode":"46612",
    "addr:street":"Fondo",
    "iso:country":"ES",
    "sg:address":"Cami Fondo, S/n",
    "sg:city":"Corbera",
    "sg:orig_category":"Colchones (fabricaci\u00d3n, Al Por Mayor, Al Por Menor)",
    "sg:phone":"+34 962 97 82 66",
    "sg:postcode":"46612",
    "sg:province":"Valencia",
    "wof:name":"Roca Vercher Rosa Maria",
    "wof:placetype":"venue"
},
  "geometry": {"coordinates":[-0.3565639853,39.1604309082],"type":"Point"}
}