{
  "type": "Feature",
  "properties": {
    "iso:country":"ES",
    "sg:address":"Crt. G. Sevilla, Km. 0648,0",
    "sg:city":"Almendralejo",
    "sg:orig_category":"Mec\u00c1nico Del Autom\u00d3vil",
    "sg:phone":"+34 924 67 09 51",
    "sg:postcode":"06200",
    "sg:province":"Badajoz",
    "wof:name":"Zambrano Bermejo Luis",
    "wof:placetype":"venue"
},
  "geometry": {"coordinates":[-6.4017014503,38.6856002808],"type":"Point"}
}