{
  "type": "Feature",
  "properties": {
    "addr:full":"Calle de Canario, 25 Fuenlabrada Madrid 28946",
    "addr:housenumber":"25",
    "addr:postcode":"28946",
    "addr:street":"Calle De Canario",
    "iso:country":"ES",
    "sg:address":"Calle de Canario, 25",
    "sg:city":"Fuenlabrada",
    "sg:orig_category":"Perfumer\u00cda Y Cosm\u00c9tica (fabricaci\u00d3n, Al Por Mayor)",
    "sg:phone":"+34 916 42 24 83",
    "sg:postcode":"28946",
    "sg:province":"Madrid",
    "wof:name":"Labopack S.l.",
    "wof:placetype":"venue"
},
  "geometry": {"coordinates":[-3.7636938095,40.2639465332],"type":"Point"}
}