{
  "type": "Feature",
  "properties": {
    "addr:full":"Avda Andalucia, 5 Mairena Alcor Sevilla 41510",
    "addr:housenumber":"5",
    "addr:postcode":"41510",
    "addr:street":"Avda Andalucia",
    "iso:country":"ES",
    "sg:address":"Avda Andalucia, 5",
    "sg:city":"Mairena Alcor",
    "sg:orig_category":"Ropa Para Se\u00d1oras (al Por Menor)",
    "sg:phone":"+34 955 74 45 43",
    "sg:postcode":"41510",
    "sg:province":"Sevilla",
    "wof:name":"Sanchez Martin Maider",
    "wof:placetype":"venue"
},
  "geometry": {"coordinates":[-5.7516222,37.3743476868],"type":"Point"}
}