{
  "type": "Feature",
  "properties": {
    "addr:full":"Avda Marife De Triana, S/n Torremolinos M\u00e1laga 29620",
    "addr:housenumber":"s / n",
    "addr:postcode":"29620",
    "addr:street":"Avda Marife;Triana;Ma\u0301Laga",
    "iso:country":"ES",
    "sg:address":"Avda Marife De Triana, S/n",
    "sg:city":"Torremolinos",
    "sg:orig_category":"Asesor\u00cda Fiscal Y Jur\u00cddica",
    "sg:phone":"+34 952 05 13 71",
    "sg:postcode":"29620",
    "sg:province":"M\u00e1laga",
    "wof:name":"Albendiz Le\u00f1a Manuel",
    "wof:placetype":"venue"
},
  "geometry": {"coordinates":[-4.4899983406,36.6365890503],"type":"Point"}
}