{
  "type": "Feature",
  "properties": {
    "iso:country":"ES",
    "sg:address":"Ctra. Madrid-coru\u00f1a, S/n",
    "sg:city":"Labajos",
    "sg:orig_category":"Distribuci\u00d3n De Petr\u00d3leo Y Derivados",
    "sg:phone":"+34 921 19 05 03",
    "sg:postcode":"40146",
    "sg:province":"Segovia",
    "sg:website":"www.cepsa.es",
    "wof:name":"Estacion De Servicio Crajma S.l.",
    "wof:placetype":"venue"
},
  "geometry": {"coordinates":[-4.518404007,40.843296051],"type":"Point"}
}