{
  "type": "Feature",
  "properties": {
    "iso:country":"ES",
    "sg:address":"Calle de Romero Civantos, 5",
    "sg:city":"Motril",
    "sg:orig_category":"Art\u00cdculos Funerarios (al Por Menor)",
    "sg:phone":"+34 958 60 26 69",
    "sg:postcode":"18600",
    "sg:province":"Granada",
    "wof:name":"Zumaquero Y Martinez S.l.",
    "wof:placetype":"venue"
},
  "geometry": {"coordinates":[-3.5201935768,36.7448310852],"type":"Point"}
}