{
  "type": "Feature",
  "properties": {
    "iso:country":"ES",
    "sg:address":"Calle de Teseo, 76",
    "sg:city":"Madrid",
    "sg:orig_category":"Tapicer\u00cdas",
    "sg:phone":"+34 913 20 80 32",
    "sg:postcode":"28027",
    "sg:province":"Madrid",
    "wof:name":"Brabante Restauracion Textil S.l.",
    "wof:placetype":"venue"
},
  "geometry": {"coordinates":[-3.6360239983,40.4458580017],"type":"Point"}
}