{
  "type": "Feature",
  "properties": {
    "iso:country":"ES",
    "sg:address":"Plaz Doctor Mara\u00d1on, 3",
    "sg:city":"Valladolid",
    "sg:orig_category":"Asociaciones, Organismos Culturales Y Socioeducativos",
    "sg:phone":"+34 983 26 87 20",
    "sg:postcode":"47011",
    "sg:province":"Valladolid",
    "wof:name":"Centro Recreativo Doctor Mara\u00f1on",
    "wof:placetype":"venue"
},
  "geometry": {"coordinates":[-4.7157540321,41.6581687927],"type":"Point"}
}