{
  "type": "Feature",
  "properties": {
    "addr:full":"Poli Paz (la), 17 Teruel Teruel 44195",
    "addr:postcode":"44195",
    "iso:country":"ES",
    "sg:address":"Poli Paz (la), 17",
    "sg:city":"Teruel",
    "sg:orig_category":"Transporte En General",
    "sg:phone":"+34 978 60 19 68",
    "sg:postcode":"44195",
    "sg:province":"Teruel",
    "sg:website":"www.logista.es",
    "wof:name":"Hidalgo Martin Jose Ignacio",
    "wof:placetype":"venue"
},
  "geometry": {"coordinates":[-1.1755470037,40.358417511],"type":"Point"}
}