{
  "type": "Feature",
  "properties": {
    "addr:full":"Ma\u00f1ueta, 6 Iru\u00f1a Navarra 31001",
    "addr:housenumber":"6",
    "addr:postcode":"31001",
    "addr:street":"Man\u0303Ueta",
    "iso:country":"ES",
    "sg:address":"Ma\u00f1ueta, 6",
    "sg:city":"Iru\u00f1a",
    "sg:orig_category":"Congelados: Productos Alimentarios (fabricaci\u00d3n, Al Por Mayor)",
    "sg:phone":"+34 948 22 41 18",
    "sg:postcode":"31001",
    "sg:province":"Navarra",
    "wof:name":"Martinez De Quel S. L.",
    "wof:placetype":"venue"
},
  "geometry": {"coordinates":[-1.643048048,42.8189811707],"type":"Point"}
}