{
  "type": "Feature",
  "properties": {
    "addr:full":"Carr Sant Andreu, 29 Mao Islas Baleares 07702",
    "addr:housenumber":"29",
    "addr:postcode":"07702",
    "addr:street":"Carr Sant Andreu",
    "iso:country":"ES",
    "sg:address":"Carr Sant Andreu, 29",
    "sg:city":"Mao",
    "sg:orig_category":"Centros P\u00dablicos De Formaci\u00d3n Profesional Y T\u00c9cnica",
    "sg:phone":"+34 971 35 39 77",
    "sg:postcode":"07702",
    "sg:province":"Islas Baleares",
    "wof:name":"Federacion Balear De Futbol",
    "wof:placetype":"venue"
},
  "geometry": {"coordinates":[4.2690558434,39.8839874268],"type":"Point"}
}