{
  "type": "Feature",
  "properties": {
    "iso:country":"ES",
    "sg:address":"Calle de Mostoles, 131",
    "sg:city":"Sabatera",
    "sg:orig_category":"Asesor\u00cda Fiscal Y Jur\u00cddica",
    "sg:phone":"+34 966 49 10 09",
    "sg:postcode":"03725",
    "sg:province":"Alicante",
    "wof:name":"H.r. Services Moraira S.l.",
    "wof:placetype":"venue"
},
  "geometry": {"coordinates":[0.1042950004,38.7289505005],"type":"Point"}
}