{
  "type": "Feature",
  "properties": {
    "addr:full":"Avda Cinta De La, 58 Huelva Huelva 21005",
    "addr:housenumber":"58",
    "addr:postcode":"21005",
    "addr:street":"Avda Cinta De La",
    "iso:country":"ES",
    "sg:address":"Avda Cinta De La, 58",
    "sg:city":"Huelva",
    "sg:orig_category":"Producci\u00d3n, Distribuci\u00d3n De Electricidad",
    "sg:phone":"+34 959 15 86 81",
    "sg:postcode":"21005",
    "sg:province":"Huelva",
    "wof:name":"Raimundo Zarza Rafael",
    "wof:placetype":"venue"
},
  "geometry": {"coordinates":[-6.9408860207,37.2775001526],"type":"Point"}
}