{
  "type": "Feature",
  "properties": {
    "iso:country":"ES",
    "sg:address":"Avda Burjasot, 18",
    "sg:city":"Valencia",
    "sg:orig_category":"Librer\u00cdas",
    "sg:phone":"+34 963 48 30 14",
    "sg:postcode":"46009",
    "sg:province":"Valencia",
    "wof:name":"Piquer Correa Isabel",
    "wof:placetype":"venue"
},
  "geometry": {"coordinates":[-0.3825869858,39.4834136963],"type":"Point"}
}