{
  "type": "Feature",
  "properties": {
    "addr:full":"Avgd Dr Pasteur, 12 Igualada Barcelona 08700",
    "addr:housenumber":"12",
    "addr:postcode":"08700",
    "iso:country":"ES",
    "sg:address":"Avgd Dr Pasteur, 12",
    "sg:city":"Igualada",
    "sg:orig_category":"Supermercados Y Hipermercados",
    "sg:phone":"+34 938 04 34 55",
    "sg:postcode":"08700",
    "sg:province":"Barcelona",
    "sg:website":"www.capraboacasa.com",
    "wof:name":"Caprabo S A",
    "wof:placetype":"venue"
},
  "geometry": {"coordinates":[1.613073945,41.5870742798],"type":"Point"}
}