{
  "type": "Feature",
  "properties": {
    "addr:full":"Carr Antoni Maura, 6 Pobla Islas Baleares 07420",
    "addr:housenumber":"6",
    "addr:postcode":"07420",
    "addr:street":"Carr Antoni Maura;Baleares",
    "iso:country":"ES",
    "sg:address":"Carr Antoni Maura, 6",
    "sg:city":"Pobla",
    "sg:orig_category":"Museos",
    "sg:phone":"+34 971 54 23 89",
    "sg:postcode":"07420",
    "sg:province":"Islas Baleares",
    "wof:name":"Ajuntament De Sa Pobla",
    "wof:placetype":"venue"
},
  "geometry": {"coordinates":[3.0563673973,39.7346801758],"type":"Point"}
}