{
  "type": "Feature",
  "properties": {
    "iso:country":"ES",
    "sg:address":"Calle de Virgen De La Novena, 9",
    "sg:city":"Madrid",
    "sg:orig_category":"Caf\u00c9s, Bares, Cervecer\u00cdas",
    "sg:phone":"+34 914 04 30 54",
    "sg:postcode":"28027",
    "sg:province":"Madrid",
    "wof:name":"Gonzalez Iglesias Pedro",
    "wof:placetype":"venue"
},
  "geometry": {"coordinates":[-3.6495919228,40.4402427673],"type":"Point"}
}