{
  "type": "Feature",
  "properties": {
    "iso:country":"ES",
    "sg:address":"Plaz Pintor Amalio Garcia Del Moral, 5",
    "sg:city":"Sevilla",
    "sg:orig_category":"Agentes Generales De Seguros",
    "sg:phone":"+34 954 63 13 52",
    "sg:postcode":"41005",
    "sg:province":"Sevilla",
    "sg:website":"www.sevillacomercio.com/codest",
    "wof:name":"Asesores Reunidos Codest S.l.",
    "wof:placetype":"venue"
},
  "geometry": {"coordinates":[-5.9647536278,37.3793106079],"type":"Point"}
}