{
  "type": "Feature",
  "properties": {
    "addr:full":"Calle de Carretera, Km. 0002,2 Jimenez Jamuz Le\u00f3n 24767",
    "addr:postcode":"24767",
    "addr:street":"Calle De Carretera Km. 0002,2 Jimenez Jamuz Leo\u0301N",
    "iso:country":"ES",
    "sg:address":"Calle de Carretera, Km. 0002,2",
    "sg:city":"Jimenez Jamuz",
    "sg:orig_category":"Alfarer\u00cda",
    "sg:phone":"+34 987 66 45 24",
    "sg:postcode":"24767",
    "sg:province":"Le\u00f3n",
    "wof:name":"Penin Del Canto Valentin",
    "wof:placetype":"venue"
},
  "geometry": {"coordinates":[-5.9328532219,42.2659416199],"type":"Point"}
}