{
  "type": "Feature",
  "properties": {
    "addr:full":"Av Jaume I, 114 Mollet Valles Barcelona 08100",
    "addr:housenumber":"114",
    "addr:postcode":"08100",
    "addr:street":"Av Jaume I",
    "iso:country":"ES",
    "sg:address":"Av Jaume I, 114",
    "sg:city":"Mollet Valles",
    "sg:orig_category":"Arquitectos",
    "sg:phone":"+34 935 70 27 74",
    "sg:postcode":"08100",
    "sg:province":"Barcelona",
    "wof:name":"Mutge Barcelo Vicente",
    "wof:placetype":"venue"
},
  "geometry": {"coordinates":[2.2144720554,41.5414848328],"type":"Point"}
}