{
  "type": "Feature",
  "properties": {
    "addr:full":"Ctra Madrid Irun, S/n Lerma Burgos 09340",
    "addr:housenumber":"s / n",
    "addr:postcode":"09340",
    "addr:street":"Ctra Madrid",
    "iso:country":"ES",
    "sg:address":"Ctra Madrid Irun, S/n",
    "sg:city":"Lerma",
    "sg:classifiers":[
        {
            "category":"Manufacturing",
            "subcategory":"Building Materials",
            "type":"Manufacturing & Wholesale Goods"
        }
    ],
    "sg:phone":"+34 947 17 01 20",
    "sg:postcode":"09340",
    "sg:province":"Burgos",
    "sg:tags":[
        "cemento",
        "y",
        "de",
        "fabricaci\u00d3n",
        "cal"
    ],
    "wof:name":"Vibrados Lerma S.l.",
    "wof:placetype":"venue"
},
  "geometry": {"coordinates":[-3.7559909821,42.0358695984],"type":"Point"}
}