{
  "type": "Feature",
  "properties": {
    "addr:full":"Calle de Concepcion Arenal, 7 Gijon Asturias 33202",
    "addr:housenumber":"7",
    "addr:postcode":"33202",
    "addr:street":"Calle De Concepcion Arenal",
    "iso:country":"ES",
    "sg:address":"Calle de Concepcion Arenal, 7",
    "sg:city":"Gijon",
    "sg:orig_category":"Molduras, Junquillos, Listones Y Molduras Perforadas",
    "sg:phone":"+34 985 35 36 26",
    "sg:postcode":"33202",
    "sg:province":"Asturias",
    "wof:name":"Sistelcom-telemensaje S.a.",
    "wof:placetype":"venue"
},
  "geometry": {"coordinates":[-5.6588578224,43.5388641357],"type":"Point"}
}