{
  "type": "Feature",
  "properties": {
    "iso:country":"ES",
    "sg:address":"Carr Orient, 1",
    "sg:city":"Palamos",
    "sg:orig_category":"Carnicer\u00cdas, Carnicer\u00cdas",
    "sg:phone":"+34 972 31 60 23",
    "sg:postcode":"17230",
    "sg:province":"Girona",
    "wof:name":"Forroy Marques Ramon",
    "wof:placetype":"venue"
},
  "geometry": {"coordinates":[3.1272559166,41.8477668762],"type":"Point"}
}