{
  "type": "Feature",
  "properties": {
    "addr:full":"Calle de San Juan De Ortega, 10 Madrid Madrid 28050",
    "addr:housenumber":"10",
    "addr:postcode":"madrid;28050",
    "addr:street":"Calle De San Juan De Ortega",
    "iso:country":"ES",
    "sg:address":"Calle de San Juan De Ortega, 10",
    "sg:city":"Madrid",
    "sg:orig_category":"Inform\u00c1tica (estudios, Servicios, Asesor\u00cda, Formaci\u00d3n)",
    "sg:phone":"+34 917 50 67 68",
    "sg:postcode":"28050",
    "sg:province":"Madrid",
    "wof:name":"Easy To Do S.l.",
    "wof:placetype":"venue"
},
  "geometry": {"coordinates":[-3.6717278957,40.5022163391],"type":"Point"}
}