{
  "type": "Feature",
  "properties": {
    "iso:country":"ES",
    "sg:address":"Carr Beat Miro, 5",
    "sg:city":"Sant Joan De Les Abadesses",
    "sg:orig_category":"Reposter\u00cdas",
    "sg:phone":"+34 972 72 00 79",
    "sg:postcode":"17860",
    "sg:province":"Girona",
    "wof:name":"Jorda Rovira Juan",
    "wof:placetype":"venue"
},
  "geometry": {"coordinates":[2.2856869698,42.2337684631],"type":"Point"}
}