{
  "type": "Feature",
  "properties": {
    "iso:country":"ES",
    "sg:address":"Los Marmoles, 3",
    "sg:city":"Lucena",
    "sg:orig_category":"M\u00c9dicos: Ginecolog\u00cda M\u00c9dica, Obstetricia",
    "sg:phone":"+34 957 51 47 88",
    "sg:postcode":"14900",
    "sg:province":"C\u00f3rdoba",
    "wof:name":"Auxilabor Del Sur S.l.",
    "wof:placetype":"venue"
},
  "geometry": {"coordinates":[-4.4835753441,37.4197540283],"type":"Point"}
}