{
  "type": "Feature",
  "properties": {
    "addr:full":"Calle de Espa\u00d1a, 15 Fuengirola M\u00e1laga 29640",
    "addr:housenumber":"15",
    "addr:postcode":"29640",
    "addr:street":"Calle De Espan\u0303A;Ma\u0301Laga",
    "iso:country":"ES",
    "sg:address":"Calle de Espa\u00d1a, 15",
    "sg:city":"Fuengirola",
    "sg:orig_category":"Ropa Para Se\u00d1oras (al Por Menor)",
    "sg:phone":"+34 952 58 59 01",
    "sg:postcode":"29640",
    "sg:province":"M\u00e1laga",
    "wof:name":"Modas Zarpa S.a.",
    "wof:placetype":"venue"
},
  "geometry": {"coordinates":[-4.6226148605,36.5377197266],"type":"Point"}
}