{
  "type": "Feature",
  "properties": {
    "addr:full":"Rond General Mitre, 185 Barcelona Barcelona 08023",
    "addr:housenumber":"185",
    "addr:postcode":"08023",
    "addr:street":"Mitre",
    "iso:country":"ES",
    "sg:address":"Rond General Mitre, 185",
    "sg:city":"Barcelona",
    "sg:orig_category":"Promotores Constructores",
    "sg:phone":"+34 932 11 72 61",
    "sg:postcode":"08023",
    "sg:province":"Barcelona",
    "wof:name":"Construccions I Reformes Putget 1 S.l.",
    "wof:placetype":"venue"
},
  "geometry": {"coordinates":[2.1415998936,41.4047698975],"type":"Point"}
}