{
  "type": "Feature",
  "properties": {
    "addr:full":"Carrer de Ermenegild Goula, 3 Cornella Llobregat Barcelona 08940",
    "addr:housenumber":"3",
    "addr:postcode":"08940",
    "addr:street":"Carrer De Ermenegild Goula",
    "iso:country":"ES",
    "sg:address":"Carrer de Ermenegild Goula, 3",
    "sg:city":"Cornella Llobregat",
    "sg:orig_category":"Asociaciones, Organismos Culturales Y Socioeducativos",
    "sg:phone":"+34 933 76 53 54",
    "sg:postcode":"08940",
    "sg:province":"Barcelona",
    "wof:name":"Associacio Per A La Defensa De La Gent Gran",
    "wof:placetype":"venue"
},
  "geometry": {"coordinates":[2.076390028,41.3598175049],"type":"Point"}
}