{
  "type": "Feature",
  "properties": {
    "addr:full":"Carrer de L'harmonia, 2 Barcelona Barcelona 08035",
    "addr:housenumber":"2",
    "addr:postcode":"08035",
    "addr:street":"Carrer De L'Harmonia",
    "iso:country":"ES",
    "sg:address":"Carrer de L'harmonia, 2",
    "sg:city":"Barcelona",
    "sg:orig_category":"Publicidad (soportes Y Gesti\u00d3n)",
    "sg:phone":"+34 934 28 12 39",
    "sg:postcode":"08035",
    "sg:province":"Barcelona",
    "wof:name":"Henche Juan Gonzalo",
    "wof:placetype":"venue"
},
  "geometry": {"coordinates":[2.1440823078,41.4343757629],"type":"Point"}
}