{
  "type": "Feature",
  "properties": {
    "iso:country":"ES",
    "sg:address":"Pg Viaducte (el), 24",
    "sg:city":"Alcoi",
    "sg:orig_category":"Farmacias",
    "sg:phone":"+34 965 54 71 83",
    "sg:postcode":"03801",
    "sg:province":"Alicante",
    "wof:name":"Farmacia Del Viaducto C.b.",
    "wof:placetype":"venue"
},
  "geometry": {"coordinates":[-0.4679769874,38.6974983215],"type":"Point"}
}