{
  "type": "Feature",
  "properties": {
    "addr:full":"Calle de Mayor, 52 Alcantarilla Murcia 30820",
    "addr:housenumber":"52",
    "addr:postcode":"30820",
    "addr:street":"Calle De Mayor",
    "iso:country":"ES",
    "sg:address":"Calle de Mayor, 52",
    "sg:city":"Alcantarilla",
    "sg:orig_category":"Alquiler De V\u00cddeo",
    "sg:phone":"+34 968 89 29 30",
    "sg:postcode":"30820",
    "sg:province":"Murcia",
    "wof:name":"Pedro Burruezo S.l.",
    "wof:placetype":"venue"
},
  "geometry": {"coordinates":[-1.2149709463,37.9691810608],"type":"Point"}
}