{
  "type": "Feature",
  "properties": {
    "addr:full":"Calle de Salamero, 8 Graus Huesca 22430",
    "addr:housenumber":"8",
    "addr:postcode":"22430",
    "addr:street":"Calle De Salamero",
    "iso:country":"ES",
    "sg:address":"Calle de Salamero, 8",
    "sg:city":"Graus",
    "sg:orig_category":"Molduras, Junquillos, Listones Y Molduras Perforadas",
    "sg:phone":"+34 974 54 00 37",
    "sg:postcode":"22430",
    "sg:province":"Huesca",
    "wof:name":"Octavio Sin Mir Y Otros Cdad.",
    "wof:placetype":"venue"
},
  "geometry": {"coordinates":[0.3382329941,42.1914825439],"type":"Point"}
}