{
  "type": "Feature",
  "properties": {
    "addr:full":"Luga Tetir, 16 Tetir Las Palmas 35613",
    "addr:housenumber":"16",
    "addr:postcode":"35613",
    "addr:street":"Tetir;Las Palmas",
    "iso:country":"ES",
    "sg:address":"Luga Tetir, 16",
    "sg:city":"Tetir",
    "sg:orig_category":"Fabricaci\u00d3n De Harinas, S\u00c9molas, Productos De Elaboraci\u00d3n Del Grano",
    "sg:phone":"+34 928 86 51 45",
    "sg:postcode":"35613",
    "sg:province":"Las Palmas",
    "wof:name":"Fuerte Tetir S.l.",
    "wof:placetype":"venue"
},
  "geometry": {"coordinates":[-13.9335594177,28.532661438],"type":"Point"}
}