{
  "type": "Feature",
  "properties": {
    "iso:country":"ES",
    "sg:address":"Calle de Asuncion, 42",
    "sg:city":"Sevilla",
    "sg:orig_category":"M\u00c9dicos: Oftalmolog\u00cda",
    "sg:phone":"+34 954 27 33 33",
    "sg:postcode":"41011",
    "sg:province":"Sevilla",
    "wof:name":"Fallaha Valdayo Nizar Oscar",
    "wof:placetype":"venue"
},
  "geometry": {"coordinates":[-5.9976215363,37.3763389587],"type":"Point"}
}