{
  "type": "Feature",
  "properties": {
    "addr:full":"Avda Aragon, Km. 0302,0 Montalban Teruel 44700",
    "addr:postcode":"44700",
    "addr:street":"Avda Aragon Km. 0302,0",
    "iso:country":"ES",
    "sg:address":"Avda Aragon, Km. 0302,0",
    "sg:city":"Montalban",
    "sg:orig_category":"Mec\u00c1nico Del Autom\u00d3vil",
    "sg:phone":"+34 978 75 01 33",
    "sg:postcode":"44700",
    "sg:province":"Teruel",
    "wof:name":"Talleres Sanchez Boix S.l.",
    "wof:placetype":"venue"
},
  "geometry": {"coordinates":[-0.8111619949,40.8320922852],"type":"Point"}
}