{
  "type": "Feature",
  "properties": {
    "iso:country":"ES",
    "sg:address":"Calle de Colon, 41",
    "sg:city":"Alzira",
    "sg:orig_category":"Promotores Constructores",
    "sg:phone":"+34 962 41 87 58",
    "sg:postcode":"46600",
    "sg:province":"Valencia",
    "wof:name":"Garcia Ca\u00f1uelo Construcciones S.l.",
    "wof:placetype":"venue"
},
  "geometry": {"coordinates":[-0.4377357066,39.1476325989],"type":"Point"}
}