{
  "type": "Feature",
  "properties": {
    "iso:country":"ES",
    "sg:address":"Calle de Maestro Emilio Vi\u00d1es, 3",
    "sg:city":"Villaviciosa Cordoba",
    "sg:orig_category":"Reposter\u00cdas",
    "sg:phone":"+34 957 36 01 66",
    "sg:postcode":"14300",
    "sg:province":"C\u00f3rdoba",
    "wof:name":"Cantero Delgado Manuel",
    "wof:placetype":"venue"
},
  "geometry": {"coordinates":[-5.0147662163,38.0773353577],"type":"Point"}
}