{
  "type": "Feature",
  "properties": {
    "addr:full":"Alfareria, 28 Guillena Sevilla 41210",
    "addr:housenumber":"28",
    "addr:postcode":"41210",
    "addr:street":"Alfareria",
    "iso:country":"ES",
    "sg:address":"Alfareria, 28",
    "sg:city":"Guillena",
    "sg:orig_category":"Desinfecci\u00d3n, Desinsectaci\u00d3n, Desratizaci\u00d3n",
    "sg:phone":"+34 954 41 84 77",
    "sg:postcode":"41210",
    "sg:province":"Sevilla",
    "wof:name":"Procoam S.a.c.",
    "wof:placetype":"venue"
},
  "geometry": {"coordinates":[-6.0553040504,37.5477600098],"type":"Point"}
}