{
  "type": "Feature",
  "properties": {
    "iso:country":"ES",
    "sg:address":"Carrer de Sant Miquel, 53",
    "sg:city":"Barcelona",
    "sg:orig_category":"Agencias Y Agentes Comerciales, Representantes",
    "sg:phone":"+34 932 21 83 12",
    "sg:postcode":"08003",
    "sg:province":"Barcelona",
    "wof:name":"Deteca S.l.",
    "wof:placetype":"venue"
},
  "geometry": {"coordinates":[2.1887209415,41.3791770935],"type":"Point"}
}