{
  "type": "Feature",
  "properties": {
    "addr:full":"Calle de Rio Rodano - Aldea Moret, S/n Caceres C\u00e1ceres 10005",
    "addr:housenumber":"s / n",
    "addr:postcode":"10005",
    "addr:street":"Calle De Rio Rodano;Moret;Ca\u0301Ceres",
    "iso:country":"ES",
    "sg:address":"Calle de Rio Rodano - Aldea Moret, S/n",
    "sg:city":"Caceres",
    "sg:orig_category":"Iglesia Cat\u00d3lica",
    "sg:phone":"+34 927 23 34 29",
    "sg:postcode":"10005",
    "sg:province":"C\u00e1ceres",
    "wof:name":"Parroquia De San Eugenio",
    "wof:placetype":"venue"
},
  "geometry": {"coordinates":[-6.5341739655,39.4675254822],"type":"Point"}
}