{
  "type": "Feature",
  "properties": {
    "iso:country":"ES",
    "sg:address":"Cami Trinidad, La, S/n",
    "sg:city":"San Juan",
    "sg:orig_category":"Arquitectos",
    "sg:phone":"+34 971 38 39 72",
    "sg:postcode":"07760",
    "sg:province":"Islas Baleares",
    "wof:name":"Gonzalez Pladellorens Antonio",
    "wof:placetype":"venue"
},
  "geometry": {"coordinates":[3.8382499218,39.9930915833],"type":"Point"}
}