{
  "type": "Feature",
  "properties": {
    "iso:country":"ES",
    "sg:address":"Avda Portugal, 114",
    "sg:city":"Salamanca",
    "sg:orig_category":"Asociaciones Y Clubs Deportivos",
    "sg:phone":"+34 923 23 04 25",
    "sg:postcode":"37005",
    "sg:province":"Salamanca",
    "wof:name":"Calderon Cinco S.l.",
    "wof:placetype":"venue"
},
  "geometry": {"coordinates":[-5.6623930931,40.9724578857],"type":"Point"}
}