{
  "type": "Feature",
  "properties": {
    "addr:full":"Carrer de Murcia, 26 S. Boi Llobregat Barcelona 08830",
    "addr:housenumber":"26",
    "addr:postcode":"08830",
    "addr:street":"Carrer De Murcia",
    "iso:country":"ES",
    "sg:address":"Carrer de Murcia, 26",
    "sg:city":"S. Boi Llobregat",
    "sg:orig_category":"Fabricaci\u00d3n De Moldes Y Modelos",
    "sg:phone":"+34 936 30 61 38",
    "sg:postcode":"08830",
    "sg:province":"Barcelona",
    "wof:name":"Cronomol S.l.",
    "wof:placetype":"venue"
},
  "geometry": {"coordinates":[2.0449779034,41.3480606079],"type":"Point"}
}