{
  "type": "Feature",
  "properties": {
    "iso:country":"ES",
    "sg:address":"Avda Coru\u00d1a (da), 165",
    "sg:city":"Lugo",
    "sg:orig_category":"Asociaciones Y Clubs Deportivos",
    "sg:phone":"+34 982 21 11 58",
    "sg:postcode":"27003",
    "sg:province":"Lugo",
    "wof:name":"Bujan Casas Abelardo Pastor",
    "wof:placetype":"venue"
},
  "geometry": {"coordinates":[-7.5626401901,43.0196495056],"type":"Point"}
}