{
  "type": "Feature",
  "properties": {
    "iso:country":"ES",
    "sg:address":"Calle de San Francisco, 36",
    "sg:city":"Aranda Duero",
    "sg:orig_category":"Muebles Y Accesorios Para Cocinas Y Cuartos De Ba\u00d1o (al Por Menor)",
    "sg:phone":"+34 947 51 33 29",
    "sg:postcode":"09400",
    "sg:province":"Burgos",
    "wof:name":"Gonzalez Benito Luis Carlos",
    "wof:placetype":"venue"
},
  "geometry": {"coordinates":[-3.6857941151,41.6738052368],"type":"Point"}
}