{
  "type": "Feature",
  "properties": {
    "addr:full":"Calle de Enrique Nieto, 6 Melilla Melilla 52002",
    "addr:housenumber":"6",
    "addr:postcode":"52002",
    "addr:street":"Calle De Enrique Nieto",
    "iso:country":"ES",
    "sg:address":"Calle de Enrique Nieto, 6",
    "sg:city":"Melilla",
    "sg:orig_category":"Asociaciones, Organismos Culturales Y Socioeducativos",
    "sg:phone":"+34 952 68 36 52",
    "sg:postcode":"52002",
    "sg:province":"Melilla",
    "wof:name":"Asociacion Islamica Badr",
    "wof:placetype":"venue"
},
  "geometry": {"coordinates":[-2.9482674599,35.2999191284],"type":"Point"}
}