{
  "type": "Feature",
  "properties": {
    "iso:country":"ES",
    "sg:address":"Calle de Mayor, 21",
    "sg:city":"Albacete",
    "sg:orig_category":"Pod\u00d3logos: Pedicuros",
    "sg:phone":"+34 967 21 20 10",
    "sg:postcode":"02002",
    "sg:province":"Albacete",
    "wof:name":"Gil Garcia Gloria",
    "wof:placetype":"venue"
},
  "geometry": {"coordinates":[-1.8539279699,38.9930992126],"type":"Point"}
}