{
  "type": "Feature",
  "properties": {
    "iso:country":"ES",
    "sg:address":"Calle de Fragata, 1",
    "sg:city":"Palmones",
    "sg:orig_category":"Ingenier\u00cda, Centros De Estudios (diversos)",
    "sg:phone":"+34 956 67 71 59",
    "sg:postcode":"11379",
    "sg:province":"C\u00e1diz",
    "wof:name":"Canuto Largo S.a.",
    "wof:placetype":"venue"
},
  "geometry": {"coordinates":[-5.4427189827,36.1786231995],"type":"Point"}
}