{
  "type": "Feature",
  "properties": {
    "addr:full":"Avda Europa, 12 Pozuelo De Alarcon Madrid 28224",
    "addr:housenumber":"12",
    "addr:postcode":"28224",
    "addr:street":"Avda Europa",
    "iso:country":"ES",
    "sg:address":"Avda Europa, 12",
    "sg:city":"Pozuelo De Alarcon",
    "sg:orig_category":"Centros Empresariales",
    "sg:phone":"+34 913 52 86 62",
    "sg:postcode":"28224",
    "sg:province":"Madrid",
    "wof:name":"Sanchez Consultores S.l.",
    "wof:placetype":"venue"
},
  "geometry": {"coordinates":[-3.7969949245,40.4361038208],"type":"Point"}
}