{
  "type": "Feature",
  "properties": {
    "addr:full":"Plaz Sagasta, 7 Elda Alicante 03600",
    "addr:housenumber":"7",
    "addr:postcode":"03600",
    "addr:street":"Plaz Sagasta",
    "iso:country":"ES",
    "sg:address":"Plaz Sagasta, 7",
    "sg:city":"Elda",
    "sg:orig_category":"Cl\u00cdnicas Dentales",
    "sg:phone":"+34 965 39 29 52",
    "sg:postcode":"03600",
    "sg:province":"Alicante",
    "wof:name":"Garrido Santo Francisco",
    "wof:placetype":"venue"
},
  "geometry": {"coordinates":[-0.7961040139,38.475315094],"type":"Point"}
}