{
  "type": "Feature",
  "properties": {
    "addr:full":"Neptuno Galerias, 25 Platja Aro Girona 17250",
    "addr:housenumber":"25",
    "addr:postcode":"17250",
    "addr:street":"Galerias",
    "iso:country":"ES",
    "sg:address":"Neptuno Galerias, 25",
    "sg:city":"Platja Aro",
    "sg:orig_category":"Bisuter\u00cda, Joyer\u00cda, Relojer\u00cda (al Por Menor)",
    "sg:phone":"+34 972 81 60 93",
    "sg:postcode":"17250",
    "sg:province":"Girona",
    "wof:name":"Linea De Or S.l.",
    "wof:placetype":"venue"
},
  "geometry": {"coordinates":[3.0639550686,41.8142547607],"type":"Point"}
}