{
  "type": "Feature",
  "properties": {
    "iso:country":"ES",
    "sg:address":"Carrer de Lluis Pascual Roca, 18",
    "sg:city":"S. Boi Llobregat",
    "sg:orig_category":"Lencer\u00cda Femenina, Corseter\u00cda, Trajes De Ba\u00d1o (al Por Menor)",
    "sg:phone":"+34 936 52 17 36",
    "sg:postcode":"08830",
    "sg:province":"Barcelona",
    "wof:name":"Fernandez Nieto Josefa",
    "wof:placetype":"venue"
},
  "geometry": {"coordinates":[2.0381379128,41.3442802429],"type":"Point"}
}