{
  "type": "Feature",
  "properties": {
    "addr:full":"Rua Daniel Castelao, 17 Con Pontevedra 36950",
    "addr:housenumber":"17",
    "addr:postcode":"36950",
    "addr:street":"Rua Daniel Castelao;Pontevedra",
    "iso:country":"ES",
    "sg:address":"Rua Daniel Castelao, 17",
    "sg:city":"Con",
    "sg:orig_category":"Comercio, Reparaci\u00d3n De Motocicletas, Bicicletas Y Piezas Sueltas",
    "sg:phone":"+34 986 31 03 37",
    "sg:postcode":"36950",
    "sg:province":"Pontevedra",
    "wof:name":"Motos Antonio S.l.",
    "wof:placetype":"venue"
},
  "geometry": {"coordinates":[-8.738442421,42.2772254944],"type":"Point"}
}