{
  "type": "Feature",
  "properties": {
    "iso:country":"ES",
    "sg:address":"Avda Madrid (de), 10",
    "sg:city":"Coslada",
    "sg:orig_category":"Servidores Y Editores De Bases De Datos",
    "sg:phone":"+34 916 60 13 05",
    "sg:postcode":"28820",
    "sg:province":"Madrid",
    "wof:name":"Lozano Y Certuche Comunicaciones S.l.",
    "wof:placetype":"venue"
},
  "geometry": {"coordinates":[-3.5417239666,40.4220504761],"type":"Point"}
}