{
  "type": "Feature",
  "properties": {
    "addr:full":"Plaz Molinos (los), 8 Ponferrada Le\u00f3n 24400",
    "addr:postcode":"24400",
    "addr:street":"Los",
    "iso:country":"ES",
    "sg:address":"Plaz Molinos (los), 8",
    "sg:city":"Ponferrada",
    "sg:orig_category":"Fotocopias, Reprograf\u00cda",
    "sg:phone":"+34 987 40 41 65",
    "sg:postcode":"24400",
    "sg:province":"Le\u00f3n",
    "sg:website":"www.paginasamarillas.es",
    "wof:name":"Gonzalez Cerecedo Sergio",
    "wof:placetype":"venue"
},
  "geometry": {"coordinates":[-6.585185051,42.5406036377],"type":"Point"}
}