{
  "type": "Feature",
  "properties": {
    "iso:country":"ES",
    "sg:address":"Pl Tint, 3",
    "sg:city":"Terrassa",
    "sg:orig_category":"Tintes (fabricaci\u00d3n, Al Por Mayor)",
    "sg:phone":"+34 937 80 79 28",
    "sg:postcode":"08224",
    "sg:province":"Barcelona",
    "wof:name":"Manau Trullas Jordi",
    "wof:placetype":"venue"
},
  "geometry": {"coordinates":[2.0050120354,41.5656318665],"type":"Point"}
}