{
  "type": "Feature",
  "properties": {
    "iso:country":"ES",
    "sg:address":"Calle de Virgen De La Muela, 9",
    "sg:city":"Corral Almaguer",
    "sg:orig_category":"Reposter\u00cdas",
    "sg:phone":"+34 925 19 08 14",
    "sg:postcode":"45880",
    "sg:province":"Toledo",
    "wof:name":"Garcia Lajara S.l.",
    "wof:placetype":"venue"
},
  "geometry": {"coordinates":[-3.1651539803,39.7596817017],"type":"Point"}
}