{
  "type": "Feature",
  "properties": {
    "iso:country":"ES",
    "sg:address":"Calle de Sambara, 4",
    "sg:city":"Madrid",
    "sg:orig_category":"Reparaci\u00d3n Y Restauraci\u00d3n De Objetos Diversos",
    "sg:phone":"+34 914 04 89 65",
    "sg:postcode":"28027",
    "sg:province":"Madrid",
    "wof:name":"Restauracion De Tomo Y Lomo",
    "wof:placetype":"venue"
},
  "geometry": {"coordinates":[-3.6551520824,40.4337272644],"type":"Point"}
}