{
  "type": "Feature",
  "properties": {
    "iso:country":"ES",
    "sg:address":"De Baix, 96",
    "sg:city":"S. Gregori",
    "sg:orig_category":"Infograf\u00cda",
    "sg:phone":"+34 972 42 90 04",
    "sg:postcode":"17150",
    "sg:province":"Girona",
    "wof:name":"Caballe Llobet Josep",
    "wof:placetype":"venue"
},
  "geometry": {"coordinates":[2.7546210289,41.9899787903],"type":"Point"}
}