{
  "type": "Feature",
  "properties": {
    "iso:country":"ES",
    "sg:address":"Rua Salmon, 4",
    "sg:city":"Lugo",
    "sg:orig_category":"Peluqueros: De Se\u00d1oras",
    "sg:phone":"+34 982 24 04 65",
    "sg:postcode":"27003",
    "sg:province":"Lugo",
    "wof:name":"Capon Fernandez Jose Eugenio",
    "wof:placetype":"venue"
},
  "geometry": {"coordinates":[-7.5577311516,43.0175743103],"type":"Point"}
}