{
  "type": "Feature",
  "properties": {
    "iso:country":"ES",
    "sg:address":"Calle de Jacinto Verdaguer, 47",
    "sg:city":"Alacant",
    "sg:orig_category":"Venta, Instalaci\u00d3n De Calefacci\u00d3n",
    "sg:phone":"+34 965 12 72 18",
    "sg:postcode":"03009",
    "sg:province":"Alicante",
    "sg:website":"www.tvstecnicalor.com",
    "wof:name":"Terol Y Von Schiller C.v.",
    "wof:placetype":"venue"
},
  "geometry": {"coordinates":[-0.5069569945,38.367023468],"type":"Point"}
}