{
  "type": "Feature",
  "properties": {
    "addr:full":"Calle de Adriano, 33 Sevilla Sevilla 41001",
    "addr:housenumber":"33",
    "addr:postcode":"41001",
    "addr:street":"Calle De Adriano",
    "iso:country":"ES",
    "sg:address":"Calle de Adriano, 33",
    "sg:city":"Sevilla",
    "sg:orig_category":"Agricultores, Agricultores",
    "sg:phone":"+34 954 22 85 36",
    "sg:postcode":"41001",
    "sg:province":"Sevilla",
    "wof:name":"Asociacion Nacional De Ganaderia De Lidia",
    "wof:placetype":"venue"
},
  "geometry": {"coordinates":[-5.9990296364,37.3866539001],"type":"Point"}
}