{
  "type": "Feature",
  "properties": {
    "addr:full":"Calle de Dolores De La Rocha, 43 Palmas De Gran Canaria Las Palmas 35001",
    "addr:housenumber":"43",
    "addr:postcode":"35001",
    "addr:street":"Calle De Dolores De La Rocha",
    "iso:country":"ES",
    "sg:address":"Calle de Dolores De La Rocha, 43",
    "sg:city":"Palmas De Gran Canaria",
    "sg:orig_category":"Abogados",
    "sg:phone":"+34 928 32 08 00",
    "sg:postcode":"35001",
    "sg:province":"Las Palmas",
    "wof:name":"Royo Simon Pino",
    "wof:placetype":"venue"
},
  "geometry": {"coordinates":[-15.4134025574,28.0969638824],"type":"Point"}
}