{
  "type": "Feature",
  "properties": {
    "addr:full":"Calle de Rubi, 3 Almeria Almer\u00eda 04006",
    "addr:housenumber":"3",
    "addr:postcode":"04006",
    "addr:street":"Calle De Rubi",
    "iso:country":"ES",
    "sg:address":"Calle de Rubi, 3",
    "sg:city":"Almeria",
    "sg:orig_category":"Servicios Diversos",
    "sg:phone":"+34 950 22 11 95",
    "sg:postcode":"04006",
    "sg:province":"Almer\u00eda",
    "sg:website":"www.unipost.es",
    "wof:name":"Unipost S.a.",
    "wof:placetype":"venue"
},
  "geometry": {"coordinates":[-2.4387300014,36.8421592712],"type":"Point"}
}