{
  "type": "Feature",
  "properties": {
    "addr:full":"Calle de Pintor Varela, S/n Torrelavega Cantabria 39300",
    "addr:housenumber":"s / n",
    "addr:postcode":"39300",
    "addr:street":"Calle De Pintor Varela",
    "iso:country":"ES",
    "sg:address":"Calle de Pintor Varela, S/n",
    "sg:city":"Torrelavega",
    "sg:orig_category":"Polideportivos",
    "sg:phone":"+34 942 80 56 33",
    "sg:postcode":"39300",
    "sg:province":"Cantabria",
    "wof:name":"Instituto Municipal De Deportes",
    "wof:placetype":"venue"
},
  "geometry": {"coordinates":[-4.0437989235,43.3534889221],"type":"Point"}
}