{
  "type": "Feature",
  "properties": {
    "addr:full":"Ctra Cobre (al), 335 Algeciras C\u00e1diz 11206",
    "addr:housenumber":"335;ca\u0301diz",
    "addr:postcode":"11206",
    "addr:street":"Ctra Cobre Al",
    "iso:country":"ES",
    "sg:address":"Ctra Cobre (al), 335",
    "sg:city":"Algeciras",
    "sg:orig_category":"Plomeros",
    "sg:phone":"+34 956 60 28 97",
    "sg:postcode":"11206",
    "sg:province":"C\u00e1diz",
    "wof:name":"Fontaneria Y Construcciones Campo De Gibraltar S.l.",
    "wof:placetype":"venue"
},
  "geometry": {"coordinates":[-5.4689455032,36.1155090332],"type":"Point"}
}