{
  "type": "Feature",
  "properties": {
    "addr:full":"Calle de Rio Henares, 21 Arroyomolinos Madrid 28939",
    "addr:housenumber":"21",
    "addr:postcode":"28939",
    "addr:street":"Calle De Rio Henares",
    "iso:country":"ES",
    "sg:address":"Calle de Rio Henares, 21",
    "sg:city":"Arroyomolinos",
    "sg:orig_category":"Material Y Suministros Para Fotocopiadoras, Reprograf\u00cda",
    "sg:phone":"+34 916 89 90 96",
    "sg:postcode":"28939",
    "sg:province":"Madrid",
    "wof:name":"Sidicoim S.l.",
    "wof:placetype":"venue"
},
  "geometry": {"coordinates":[-3.919508934,40.2774505615],"type":"Point"}
}