{
  "type": "Feature",
  "properties": {
    "addr:full":"Calle de Principe De Vergara, 67 Madrid Madrid 28006",
    "addr:housenumber":"67",
    "addr:postcode":"madrid;28006",
    "addr:street":"Calle De Principe De Vergara",
    "iso:country":"ES",
    "sg:address":"Calle de Principe De Vergara, 67",
    "sg:city":"Madrid",
    "sg:orig_category":"Laboratorios Y Trabajos De Fotograf\u00cda, V\u00cddeo Y Cine",
    "sg:phone":"+34 914 11 43 17",
    "sg:postcode":"28006",
    "sg:province":"Madrid",
    "wof:name":"Wu  Dongfang",
    "wof:placetype":"venue"
},
  "geometry": {"coordinates":[-3.6795599461,40.4342308044],"type":"Point"}
}