{
  "type": "Feature",
  "properties": {
    "addr:full":"Pla\u00c7 Major, 9 Solsona Lleida 25280",
    "addr:postcode":"25280",
    "iso:country":"ES",
    "sg:address":"Pla\u00c7 Major, 9",
    "sg:city":"Solsona",
    "sg:orig_category":"Ingenier\u00cda, Centros De Estudios (diversos)",
    "sg:phone":"+34 973 48 12 31",
    "sg:postcode":"25280",
    "sg:province":"Lleida",
    "wof:name":"Joan Garriga Enginyer Agronom S.l.",
    "wof:placetype":"venue"
},
  "geometry": {"coordinates":[1.5177006721,41.9936256409],"type":"Point"}
}