{
  "type": "Feature",
  "properties": {
    "iso:country":"ES",
    "sg:address":"Avda Veinticinco De Julio, 49",
    "sg:city":"Santa Cruz De Tenerife",
    "sg:orig_category":"Transporte En General",
    "sg:phone":"+34 922 27 26 81",
    "sg:postcode":"38004",
    "sg:province":"Santa Cruz De Tenerife",
    "wof:name":"Perazza De La Vega Estela",
    "wof:placetype":"venue"
},
  "geometry": {"coordinates":[-16.2564601898,28.4795894623],"type":"Point"}
}