{
  "type": "Feature",
  "properties": {
    "addr:full":"Avda Veinticinco De Julio, 49 Santa Cruz De Tenerife Santa Cruz De Tenerife 38004",
    "addr:housenumber":"49",
    "addr:postcode":"38004",
    "addr:street":"Avda Veinticinco De Julio",
    "iso:country":"ES",
    "sg:address":"Avda Veinticinco De Julio, 49",
    "sg:city":"Santa Cruz De Tenerife",
    "sg:orig_category":"Transporte En General",
    "sg:phone":"+34 922 27 26 81",
    "sg:postcode":"38004",
    "sg:province":"Santa Cruz De Tenerife",
    "wof:name":"Perazza De La Vega Estela",
    "wof:placetype":"venue"
},
  "geometry": {"coordinates":[-16.2564601898,28.4795894623],"type":"Point"}
}