{
  "type": "Feature",
  "properties": {
    "iso:country":"ES",
    "sg:address":"Carr Mare De Deu Del Pilar, 6",
    "sg:city":"Quart Poblet",
    "sg:orig_category":"M\u00c9dicos: Endocrinolog\u00cda Y Metabolismo",
    "sg:phone":"+34 961 52 55 32",
    "sg:postcode":"46930",
    "sg:province":"Valencia",
    "wof:name":"Sanchez Ruiz Monica",
    "wof:placetype":"venue"
},
  "geometry": {"coordinates":[-0.4424630105,39.4832496643],"type":"Point"}
}