{
  "type": "Feature",
  "properties": {
    "addr:full":"Calle de Carmen, 22 Villaviciosa Asturias 33300",
    "addr:housenumber":"22",
    "addr:postcode":"33300",
    "addr:street":"Calle De Carmen",
    "iso:country":"ES",
    "sg:address":"Calle de Carmen, 22",
    "sg:city":"Villaviciosa",
    "sg:orig_category":"Telas Y Sedas (al Por Menor)",
    "sg:phone":"+34 985 89 21 14",
    "sg:postcode":"33300",
    "sg:province":"Asturias",
    "wof:name":"Lozano Fernandez Maria Eugenia",
    "wof:placetype":"venue"
},
  "geometry": {"coordinates":[-5.4360361099,43.4793510437],"type":"Point"}
}