{
  "type": "Feature",
  "properties": {
    "addr:full":"Aginaga Auzoa, 38 Aginaga Guip\u00f9zcoa 20170",
    "addr:housenumber":"38",
    "addr:postcode":"20170",
    "addr:street":"Aginaga Auzoa;Guipu\u0300Zcoa",
    "iso:country":"ES",
    "sg:address":"Aginaga Auzoa, 38",
    "sg:city":"Aginaga",
    "sg:orig_category":"Distribuci\u00d3n De Petr\u00d3leo Y Derivados",
    "sg:phone":"+34 943 37 66 38",
    "sg:postcode":"20170",
    "sg:province":"Guip\u00f9zcoa",
    "wof:name":"Guregas Carburantes S.l.",
    "wof:placetype":"venue"
},
  "geometry": {"coordinates":[-2.0740373135,43.2733612061],"type":"Point"}
}