{
  "type": "Feature",
  "properties": {
    "addr:full":"Rbla Rambla Nova, 114 Tarragona Tarragona 43001",
    "addr:housenumber":"114",
    "addr:postcode":"43001",
    "addr:street":"Rambla Nova",
    "iso:country":"ES",
    "sg:address":"Rbla Rambla Nova, 114",
    "sg:city":"Tarragona",
    "sg:orig_category":"Financiaci\u00d3n Y Cr\u00c9ditos",
    "sg:phone":"+34 977 23 27 11",
    "sg:postcode":"43001",
    "sg:province":"Tarragona",
    "wof:name":"Bt Espa\u00d1a Compa\u00d1ia De Servicios Globales De Telecomunicaciones S.a.u.",
    "wof:placetype":"venue"
},
  "geometry": {"coordinates":[1.2541049719,41.1169281006],"type":"Point"}
}