{
  "type": "Feature",
  "properties": {
    "iso:country":"ES",
    "sg:address":"Calle de San Felix, 25",
    "sg:city":"Castellon",
    "sg:orig_category":"\u00d3ptica: Instrumentos (fabricaci\u00d3n)",
    "sg:phone":"+34 964 25 04 90",
    "sg:postcode":"12004",
    "sg:province":"Castell\u00f3n",
    "wof:name":"Centro Optico Elipe C.b.",
    "wof:placetype":"venue"
},
  "geometry": {"coordinates":[-0.0368690006,39.9892997742],"type":"Point"}
}