{
  "type": "Feature",
  "properties": {
    "iso:country":"ES",
    "sg:address":"Avda Andalucia, 52",
    "sg:city":"S. Bartolome Torre",
    "sg:orig_category":"Alimentaci\u00d3n General (al Por Menor)",
    "sg:phone":"+34 959 38 79 10",
    "sg:postcode":"21510",
    "sg:province":"Huelva",
    "wof:name":"Super Jamon La Antilla S.l.",
    "wof:placetype":"venue"
},
  "geometry": {"coordinates":[-7.103058815,37.4461784363],"type":"Point"}
}