{
  "type": "Feature",
  "properties": {
    "iso:country":"ES",
    "sg:address":"Carrer de Zurbaran, 7",
    "sg:city":"Ondara",
    "sg:orig_category":"Maquinaria Para Industrias Diversas",
    "sg:phone":"+34 965 76 65 10",
    "sg:postcode":"03760",
    "sg:province":"Alicante",
    "wof:name":"Ginestar Bao Juan Francisco",
    "wof:placetype":"venue"
},
  "geometry": {"coordinates":[0.0156369992,38.8277893066],"type":"Point"}
}