{
  "type": "Feature",
  "properties": {
    "iso:country":"ES",
    "sg:address":"Calle de Conquistador Benito De Ba\u00d1os, 8",
    "sg:city":"Cordoba",
    "sg:orig_category":"Pescader\u00cdas (al Por Menor)",
    "sg:phone":"+34 957 43 78 10",
    "sg:postcode":"14007",
    "sg:province":"C\u00f3rdoba",
    "wof:name":"Lopez Mu\u00f1oz Jose",
    "wof:placetype":"venue"
},
  "geometry": {"coordinates":[-4.759314537,37.8918418884],"type":"Point"}
}