{
  "type": "Feature",
  "properties": {
    "iso:country":"ES",
    "sg:address":"Calle de Alfonso Martinez Conde, S/n",
    "sg:city":"Madrid",
    "sg:orig_category":"Librer\u00cdas",
    "sg:phone":"+34 915 65 18 44",
    "sg:postcode":"28025",
    "sg:province":"Madrid",
    "wof:name":"Ruiz Zarco Jose Angel",
    "wof:placetype":"venue"
},
  "geometry": {"coordinates":[-3.7297039032,40.3808135986],"type":"Point"}
}