{
  "type": "Feature",
  "properties": {
    "addr:full":"Irurtzun, 26 Lezo Guip\u00f9zcoa 20100",
    "addr:housenumber":"26",
    "addr:postcode":"20100",
    "addr:street":"Irurtzun;Guipu\u0300Zcoa",
    "iso:country":"ES",
    "sg:address":"Irurtzun, 26",
    "sg:city":"Lezo",
    "sg:orig_category":"Maquinaria Para Industrias Diversas",
    "sg:phone":"+34 943 52 98 97",
    "sg:postcode":"20100",
    "sg:province":"Guip\u00f9zcoa",
    "wof:name":"Kemex S.a.",
    "wof:placetype":"venue"
},
  "geometry": {"coordinates":[-1.8798120022,43.3265151978],"type":"Point"}
}