{
  "type": "Feature",
  "properties": {
    "addr:full":"Lug. Campo De Aviacion, S/n Coreses Zamora 49530",
    "addr:postcode":"49530",
    "addr:street":"S / N",
    "iso:country":"ES",
    "sg:address":"Lug. Campo De Aviacion, S/n",
    "sg:city":"Coreses",
    "sg:orig_category":"Fabricaci\u00d3n De Productos L\u00c1cteos Y Derivados",
    "sg:phone":"+34 980 50 00 90",
    "sg:postcode":"49530",
    "sg:province":"Zamora",
    "wof:name":"Lacteas San Roque S.a.",
    "wof:placetype":"venue"
},
  "geometry": {"coordinates":[-5.6206488609,41.5490608215],"type":"Point"}
}