{
  "type": "Feature",
  "properties": {
    "addr:full":"Avgd Jaume I, 45 Benifaio Valencia 46450",
    "addr:housenumber":"45",
    "addr:postcode":"46450",
    "iso:country":"ES",
    "sg:address":"Avgd Jaume I, 45",
    "sg:city":"Benifaio",
    "sg:orig_category":"Ferreter\u00cda (diversos)",
    "sg:phone":"+34 961 78 03 79",
    "sg:postcode":"46450",
    "sg:province":"Valencia",
    "wof:name":"Chatarras Rubio Beltran S.l.",
    "wof:placetype":"venue"
},
  "geometry": {"coordinates":[-0.4229789972,39.2867202759],"type":"Point"}
}