{
  "type": "Feature",
  "properties": {
    "iso:country":"ES",
    "sg:address":"Carrer de Frederic Soler, 67",
    "sg:city":"Cornella Llobregat",
    "sg:orig_category":"Agencias Y Agentes Comerciales, Representantes",
    "sg:phone":"+34 934 71 12 08",
    "sg:postcode":"08940",
    "sg:province":"Barcelona",
    "wof:name":"Martos Perez Antonio Jose",
    "wof:placetype":"venue"
},
  "geometry": {"coordinates":[2.0772769451,41.3634338379],"type":"Point"}
}