{
  "type": "Feature",
  "properties": {
    "addr:full":"Calle de Pintor Zuloaga, 23 Granada Granada 18005",
    "addr:housenumber":"23",
    "addr:postcode":"18005",
    "addr:street":"Calle De Pintor Zuloaga",
    "iso:country":"ES",
    "sg:address":"Calle de Pintor Zuloaga, 23",
    "sg:city":"Granada",
    "sg:orig_category":"Quincaller\u00cda (al Por Menor)",
    "sg:phone":"+34 958 25 35 62",
    "sg:postcode":"18005",
    "sg:province":"Granada",
    "wof:name":"Crespo Lopez Maria Lourdes",
    "wof:placetype":"venue"
},
  "geometry": {"coordinates":[-3.6022338867,37.1681404114],"type":"Point"}
}