{
  "type": "Feature",
  "properties": {
    "iso:country":"ES",
    "sg:address":"Calle de Primero De Mayo, 1",
    "sg:city":"Paiporta",
    "sg:orig_category":"Relojer\u00cda (al Por Menor, Reparaci\u00d3n)",
    "sg:phone":"+34 963 97 11 83",
    "sg:postcode":"46200",
    "sg:province":"Valencia",
    "wof:name":"Ma\u00f1as Jorge Vicenta",
    "wof:placetype":"venue"
},
  "geometry": {"coordinates":[-0.4187299907,39.4286727905],"type":"Point"}
}