{
  "type": "Feature",
  "properties": {
    "iso:country":"ES",
    "sg:address":"Calle de Francisco Cano, 26",
    "sg:city":"Fuengirola",
    "sg:orig_category":"Bebidas",
    "sg:phone":"+34 952 19 92 24",
    "sg:postcode":"29640",
    "sg:province":"M\u00e1laga",
    "wof:name":"Conejo Vega Cristobal",
    "wof:placetype":"venue"
},
  "geometry": {"coordinates":[-4.6139521599,36.5530700684],"type":"Point"}
}