{
  "type": "Feature",
  "properties": {
    "addr:full":"Calle de Toledo, 8 Sonseca Toledo 45100",
    "addr:housenumber":"8",
    "addr:postcode":"45100",
    "addr:street":"Calle De Toledo",
    "iso:country":"ES",
    "sg:address":"Calle de Toledo, 8",
    "sg:city":"Sonseca",
    "sg:orig_category":"Fisioterapia",
    "sg:phone":"+34 925 38 15 62",
    "sg:postcode":"45100",
    "sg:province":"Toledo",
    "wof:name":"Centro De Fisioterapia Y Salud S.l.l.",
    "wof:placetype":"venue"
},
  "geometry": {"coordinates":[-3.9745979309,39.6769104004],"type":"Point"}
}