{
  "type": "Feature",
  "properties": {
    "addr:full":"Calle de Sierra De Guadarrama, 12 Arganda Madrid 28500",
    "addr:housenumber":"12",
    "addr:postcode":"28500",
    "addr:street":"Calle De Sierra De Guadarrama",
    "iso:country":"ES",
    "sg:address":"Calle de Sierra De Guadarrama, 12",
    "sg:city":"Arganda",
    "sg:orig_category":"Negocio De Metales No Ferrosos",
    "sg:phone":"+34 918 71 95 01",
    "sg:postcode":"28500",
    "sg:province":"Madrid",
    "wof:name":"Orium Packet S.a.",
    "wof:placetype":"venue"
},
  "geometry": {"coordinates":[-3.4762830734,40.3072242737],"type":"Point"}
}