{
  "type": "Feature",
  "properties": {
    "addr:full":"Carrer de Carreras I Candi, 29 Barcelona Barcelona 08028",
    "addr:housenumber":"29",
    "addr:postcode":"08028",
    "addr:street":"Carrer De Carreras I Candi",
    "iso:country":"ES",
    "sg:address":"Carrer de Carreras I Candi, 29",
    "sg:city":"Barcelona",
    "sg:orig_category":"Fabricaci\u00d3n De Moldes Y Modelos",
    "sg:phone":"+34 934 22 41 71",
    "sg:postcode":"08028",
    "sg:province":"Barcelona",
    "wof:name":"Antonio Guiu S.l.",
    "wof:placetype":"venue"
},
  "geometry": {"coordinates":[2.1269817352,41.3741226196],"type":"Point"}
}