{
  "type": "Feature",
  "properties": {
    "iso:country":"ES",
    "sg:address":"Calle de Juan Sebastian Elcano, 18",
    "sg:city":"Corralejo",
    "sg:orig_category":"Tintorer\u00cdas, Limpieza En Seco",
    "sg:phone":"+34 928 53 74 69",
    "sg:postcode":"35660",
    "sg:province":"Las Palmas",
    "wof:name":"Vidal Elijo Maria Jose",
    "wof:placetype":"venue"
},
  "geometry": {"coordinates":[-13.8699398041,28.737745285],"type":"Point"}
}