{
  "type": "Feature",
  "properties": {
    "addr:full":"Cm\u00d1o Cataboi, 38 Freixeiro Pontevedra 36210",
    "addr:housenumber":"38",
    "addr:postcode":"36210",
    "addr:street":"Cataboi",
    "iso:country":"ES",
    "sg:address":"Cm\u00d1o Cataboi, 38",
    "sg:city":"Freixeiro",
    "sg:orig_category":"Electrodom\u00c9sticos (al Por Menor)",
    "sg:phone":"+34 986 23 66 80",
    "sg:postcode":"36210",
    "sg:province":"Pontevedra",
    "wof:name":"Pazo Alvarez Carlos",
    "wof:placetype":"venue"
},
  "geometry": {"coordinates":[-8.6428003311,42.4304618835],"type":"Point"}
}