{
  "type": "Feature",
  "properties": {
    "addr:full":"Calle de Romeu Palazuelos, 4 Alacant Alicante 03013",
    "addr:housenumber":"4",
    "addr:postcode":"03013",
    "addr:street":"Calle De Romeu Palazuelos",
    "iso:country":"ES",
    "sg:address":"Calle de Romeu Palazuelos, 4",
    "sg:city":"Alacant",
    "sg:orig_category":"Locales Y Clases De Danza",
    "sg:phone":"+34 965 21 49 61",
    "sg:postcode":"03013",
    "sg:province":"Alicante",
    "wof:name":"Vales Del Manzano Nydia",
    "wof:placetype":"venue"
},
  "geometry": {"coordinates":[-0.476195991,38.356678009],"type":"Point"}
}