{
  "type": "Feature",
  "properties": {
    "addr:full":"Calle de Lago Titicaca, 17 Madrid Madrid 28032",
    "addr:housenumber":"17",
    "addr:postcode":"madrid;28032",
    "addr:street":"Calle De Lago Titicaca",
    "iso:country":"ES",
    "sg:address":"Calle de Lago Titicaca, 17",
    "sg:city":"Madrid",
    "sg:orig_category":"M\u00c1quinas De Coser Y De Hacer Punto (al Por Mayor)",
    "sg:phone":"+34 917 76 04 14",
    "sg:postcode":"28032",
    "sg:province":"Madrid",
    "wof:name":"Investex S.a.",
    "wof:placetype":"venue"
},
  "geometry": {"coordinates":[-3.6082389355,40.402130127],"type":"Point"}
}