{
  "type": "Feature",
  "properties": {
    "iso:country":"ES",
    "sg:address":"Olabide, 8",
    "sg:city":"Moreaga",
    "sg:orig_category":"Peluqueros: De Se\u00d1oras",
    "sg:phone":"+34 946 76 62 11",
    "sg:postcode":"48600",
    "sg:province":"Vizcaya",
    "wof:name":"Beovipel S.l.",
    "wof:placetype":"venue"
},
  "geometry": {"coordinates":[-2.9684538841,43.3793640137],"type":"Point"}
}