{
  "type": "Feature",
  "properties": {
    "addr:full":"Avda Balaidos, 48 Vigo Pontevedra 36210",
    "addr:housenumber":"48",
    "addr:postcode":"36210",
    "addr:street":"Avda Balaidos",
    "iso:country":"ES",
    "sg:address":"Avda Balaidos, 48",
    "sg:city":"Vigo",
    "sg:orig_category":"Ropa Para Se\u00d1oras (al Por Menor)",
    "sg:phone":"+34 986 24 33 96",
    "sg:postcode":"36210",
    "sg:province":"Pontevedra",
    "wof:name":"Rocha Maia Lucia Maria",
    "wof:placetype":"venue"
},
  "geometry": {"coordinates":[-8.7357006073,42.212978363],"type":"Point"}
}