{
  "type": "Feature",
  "properties": {
    "addr:full":"Urru\u00d1a Plaza, 1 Bera Navarra 31780",
    "addr:postcode":"31780",
    "addr:street":"1",
    "iso:country":"ES",
    "sg:address":"Urru\u00d1a Plaza, 1",
    "sg:city":"Bera",
    "sg:orig_category":"Estancos",
    "sg:phone":"+34 948 63 16 37",
    "sg:postcode":"31780",
    "sg:province":"Navarra",
    "wof:name":"Artieda Goya Juana Maria",
    "wof:placetype":"venue"
},
  "geometry": {"coordinates":[-1.687785387,43.2750740051],"type":"Point"}
}