{
  "type": "Feature",
  "properties": {
    "addr:full":"Carretera De Cordoba A Almeria, Km. 0236,0 Hueneja Granada 18512",
    "addr:housenumber":"a",
    "addr:postcode":"18512",
    "addr:street":"Carretera De Cordoba;Almeria Km. 0236,0",
    "iso:country":"ES",
    "sg:address":"Carretera De Cordoba A Almeria, Km. 0236,0",
    "sg:city":"Hueneja",
    "sg:orig_category":"Distribuci\u00d3n De Petr\u00d3leo Y Derivados",
    "sg:phone":"+34 958 68 30 81",
    "sg:postcode":"18512",
    "sg:province":"Granada",
    "wof:name":"Gasoleos Hueneja S.l.",
    "wof:placetype":"venue"
},
  "geometry": {"coordinates":[-3.0600171089,37.1826705933],"type":"Point"}
}