{
  "type": "Feature",
  "properties": {
    "iso:country":"ES",
    "sg:address":"Joan Fuster, S/n",
    "sg:city":"Algemesi",
    "sg:orig_category":"Ense\u00d1anza, Formaci\u00d3n Profesional: Aprendizaje",
    "sg:phone":"+34 962 42 40 21",
    "sg:postcode":"46680",
    "sg:province":"Valencia",
    "wof:name":"Ajuntament D'algemesi",
    "wof:placetype":"venue"
},
  "geometry": {"coordinates":[-0.4236750901,39.1954460144],"type":"Point"}
}