{
  "type": "Feature",
  "properties": {
    "addr:full":"Calle de Victor Andres Belaunde, 54 Madrid Madrid 28016",
    "addr:housenumber":"54",
    "addr:postcode":"madrid;28016",
    "addr:street":"Calle De Victor Andres Belaunde",
    "iso:country":"ES",
    "sg:address":"Calle de Victor Andres Belaunde, 54",
    "sg:city":"Madrid",
    "sg:orig_category":"Arreglo, Reparaci\u00d3n, Piezas Sueltas De Televisi\u00d3n, V\u00cddeo, Hi",
    "sg:phone":"+34 914 57 97 99",
    "sg:postcode":"28016",
    "sg:province":"Madrid",
    "wof:name":"Perez-tome Torres Gonzalo",
    "wof:placetype":"venue"
},
  "geometry": {"coordinates":[-3.680519104,40.4585914612],"type":"Point"}
}