{
  "type": "Feature",
  "properties": {
    "iso:country":"ES",
    "sg:address":"Calle de Recoletas, 4",
    "sg:city":"Tafalla",
    "sg:orig_category":"Mercer\u00cda, Lencer\u00cda (al Por Menor)",
    "sg:phone":"+34 948 70 05 30",
    "sg:postcode":"31300",
    "sg:province":"Navarra",
    "wof:name":"Iriso Sagardoy Juan",
    "wof:placetype":"venue"
},
  "geometry": {"coordinates":[-1.6755119562,42.5264625549],"type":"Point"}
}