{
  "type": "Feature",
  "properties": {
    "addr:full":"Calle de Eras, 65 Villaviciosa Odon Madrid 28670",
    "addr:housenumber":"65",
    "addr:postcode":"28670",
    "addr:street":"Calle De Eras;Odon",
    "iso:country":"ES",
    "sg:address":"Calle de Eras, 65",
    "sg:city":"Villaviciosa Odon",
    "sg:orig_category":"\u00d3ptica: Instrumentos (fabricaci\u00d3n)",
    "sg:phone":"+34 916 65 76 90",
    "sg:postcode":"28670",
    "sg:province":"Madrid",
    "wof:name":"Vision 65 S.l.",
    "wof:placetype":"venue"
},
  "geometry": {"coordinates":[-3.9001760483,40.3566551208],"type":"Point"}
}