{
  "type": "Feature",
  "properties": {
    "addr:full":"Carrer de Montseny, 43 Barcelona Barcelona 08012",
    "addr:housenumber":"43",
    "addr:postcode":"08012",
    "addr:street":"Carrer De Montseny",
    "iso:country":"ES",
    "sg:address":"Carrer de Montseny, 43",
    "sg:city":"Barcelona",
    "sg:orig_category":"Alimentaci\u00d3n General (al Por Menor)",
    "sg:phone":"+34 932 18 85 60",
    "sg:postcode":"08012",
    "sg:province":"Barcelona",
    "wof:name":"Singh Chauhan Vivek",
    "wof:placetype":"venue"
},
  "geometry": {"coordinates":[2.1555819511,41.4026031494],"type":"Point"}
}