{
  "type": "Feature",
  "properties": {
    "addr:full":"Calle de Queseras, 1 Morro Jable Las Palmas 35625",
    "addr:housenumber":"1",
    "addr:postcode":"35625",
    "addr:street":"Calle De Queseras",
    "iso:country":"ES",
    "sg:address":"Calle de Queseras, 1",
    "sg:city":"Morro Jable",
    "sg:orig_category":"Equipo De Refrigeraci\u00d3n Industrial",
    "sg:phone":"+34 928 54 20 65",
    "sg:postcode":"35625",
    "sg:province":"Las Palmas",
    "wof:name":"Qsr Systems 1 S.l.",
    "wof:placetype":"venue"
},
  "geometry": {"coordinates":[-14.3538293839,28.0525226593],"type":"Point"}
}