{
  "type": "Feature",
  "properties": {
    "iso:country":"ES",
    "sg:address":"Miguel De Cervantes, 14",
    "sg:city":"Zaragoza",
    "sg:orig_category":"Papeler\u00cdas, Librer\u00cdas",
    "sg:phone":"+34 976 21 99 50",
    "sg:postcode":"50006",
    "sg:province":"Zaragoza",
    "wof:name":"Marco Tremp Santiago",
    "wof:placetype":"venue"
},
  "geometry": {"coordinates":[-0.887526989,41.6441688538],"type":"Point"}
}