{
  "type": "Feature",
  "properties": {
    "addr:full":"Calle de Olaburu, 17 Aita San Migel Vizcaya 48215",
    "addr:housenumber":"17",
    "addr:postcode":"48215",
    "addr:street":"Calle De Olaburu;San",
    "iso:country":"ES",
    "sg:address":"Calle de Olaburu, 17",
    "sg:city":"Aita San Migel",
    "sg:orig_category":"Centros De Educaci\u00d3n Especial",
    "sg:phone":"+34 946 81 09 37",
    "sg:postcode":"48215",
    "sg:province":"Vizcaya",
    "wof:name":"Gobierno Vasco",
    "wof:placetype":"venue"
},
  "geometry": {"coordinates":[-2.631608963,43.1760597229],"type":"Point"}
}