{
  "type": "Feature",
  "properties": {
    "iso:country":"ES",
    "sg:address":"Calle de General Chamorro Martinez, 3",
    "sg:city":"Sevilla",
    "sg:orig_category":"Zapatos (al Por Menor)",
    "sg:phone":"+34 954 43 54 27",
    "sg:postcode":"41008",
    "sg:province":"Sevilla",
    "wof:name":"Valero Verdugo Maria Teresa",
    "wof:placetype":"venue"
},
  "geometry": {"coordinates":[-5.9714078903,37.4071884155],"type":"Point"}
}