{
  "type": "Feature",
  "properties": {
    "iso:country":"ES",
    "sg:address":"Calle de San Bernardo, 3",
    "sg:city":"Villarrobledo",
    "sg:orig_category":"Juegos Y Juguetes (al Por Menor)",
    "sg:phone":"+34 967 14 31 86",
    "sg:postcode":"02600",
    "sg:province":"Albacete",
    "wof:name":"Garcia Calero Guillermina",
    "wof:placetype":"venue"
},
  "geometry": {"coordinates":[-2.6050169468,39.2649612427],"type":"Point"}
}