{
  "type": "Feature",
  "properties": {
    "addr:full":"Avda Colon, 2 Logro\u00f1o La Rioja 26003",
    "addr:housenumber":"2",
    "addr:postcode":"26003",
    "addr:street":"Avda Colon;Rioja",
    "iso:country":"ES",
    "sg:address":"Avda Colon, 2",
    "sg:city":"Logro\u00f1o",
    "sg:orig_category":"Complementos De Vestir (al Por Menor)",
    "sg:phone":"+34 941 24 83 84",
    "sg:postcode":"26003",
    "sg:province":"La Rioja",
    "wof:name":"Sanchez Hernandez Francisco",
    "wof:placetype":"venue"
},
  "geometry": {"coordinates":[-2.4390819073,42.4650154114],"type":"Point"}
}