{
  "type": "Feature",
  "properties": {
    "iso:country":"ES",
    "sg:address":"Barr Dueso (el), S/n",
    "sg:city":"Liencres",
    "sg:orig_category":"Psicoterapeutas",
    "sg:phone":"+34 942 57 84 34",
    "sg:postcode":"39120",
    "sg:province":"Cantabria",
    "wof:name":"Inocencio Biangel Roberto De",
    "wof:placetype":"venue"
},
  "geometry": {"coordinates":[-3.9318180084,43.4603996277],"type":"Point"}
}