{
  "type": "Feature",
  "properties": {
    "addr:full":"Calle de Herreria, 2 Madrid Madrid 28037",
    "addr:housenumber":"2",
    "addr:postcode":"28037",
    "addr:street":"Calle De Herreria",
    "iso:country":"ES",
    "sg:address":"Calle de Herreria, 2",
    "sg:city":"Madrid",
    "sg:orig_category":"Peluqueros: De Se\u00d1oras",
    "sg:phone":"+34 913 13 17 30",
    "sg:postcode":"28037",
    "sg:province":"Madrid",
    "wof:name":"Guisado Espinosa Francisca",
    "wof:placetype":"venue"
},
  "geometry": {"coordinates":[-3.6241750717,40.425617218],"type":"Point"}
}