{
  "type": "Feature",
  "properties": {
    "addr:full":"Calle de Santo Domingo De Guzman, 6 Villarrobledo Albacete 02600",
    "addr:housenumber":"6",
    "addr:postcode":"02600",
    "addr:street":"Calle De Santo;Guzman",
    "iso:country":"ES",
    "sg:address":"Calle de Santo Domingo De Guzman, 6",
    "sg:city":"Villarrobledo",
    "sg:orig_category":"Farmacias",
    "sg:phone":"+34 967 14 53 04",
    "sg:postcode":"02600",
    "sg:province":"Albacete",
    "wof:name":"Tolosa Garcia Enriqueta",
    "wof:placetype":"venue"
},
  "geometry": {"coordinates":[-2.5963160992,39.2728652954],"type":"Point"}
}