{
  "type": "Feature",
  "properties": {
    "iso:country":"ES",
    "sg:address":"Calle de Segura, S/n",
    "sg:city":"Pto. Rosario",
    "sg:orig_category":"Veh\u00cdculos De Ocasi\u00d3n",
    "sg:phone":"+34 928 53 12 06",
    "sg:postcode":"35600",
    "sg:province":"Las Palmas",
    "wof:name":"Motor Eleccion Fuerteventura S.l.",
    "wof:placetype":"venue"
},
  "geometry": {"coordinates":[-13.8644189835,28.4925403595],"type":"Point"}
}