{
  "type": "Feature",
  "properties": {
    "iso:country":"ES",
    "sg:address":"Calle de Mayor, 62",
    "sg:city":"Moratalla",
    "sg:orig_category":"Relojer\u00cda (al Por Menor, Reparaci\u00d3n)",
    "sg:phone":"+34 968 73 02 19",
    "sg:postcode":"30440",
    "sg:province":"Murcia",
    "wof:name":"Lopez Guerrero Salvador",
    "wof:placetype":"venue"
},
  "geometry": {"coordinates":[-2.2773861885,38.031162262],"type":"Point"}
}