{
  "type": "Feature",
  "properties": {
    "addr:full":"Calle de Antero Garcia, 5 Iscar Valladolid 47420",
    "addr:housenumber":"5",
    "addr:postcode":"47420",
    "addr:street":"Calle De Antero Garcia",
    "iso:country":"ES",
    "sg:address":"Calle de Antero Garcia, 5",
    "sg:city":"Iscar",
    "sg:orig_category":"Molduras, Junquillos, Listones Y Molduras Perforadas",
    "sg:phone":"+34 983 61 13 08",
    "sg:postcode":"47420",
    "sg:province":"Valladolid",
    "wof:name":"Rodriguez Sanz Jose Antonio",
    "wof:placetype":"venue"
},
  "geometry": {"coordinates":[-4.5315027237,41.3422584534],"type":"Point"}
}