{
  "type": "Feature",
  "properties": {
    "addr:full":"Calle de Madrid, 10 Santa Pola Alicante 03130",
    "addr:housenumber":"10",
    "addr:postcode":"03130",
    "addr:street":"Calle De Madrid",
    "iso:country":"ES",
    "sg:address":"Calle de Madrid, 10",
    "sg:city":"Santa Pola",
    "sg:orig_category":"Farmacias",
    "sg:phone":"+34 965 41 70 58",
    "sg:postcode":"03130",
    "sg:province":"Alicante",
    "wof:name":"Calatayud Calpena Maria Del Carmen",
    "wof:placetype":"venue"
},
  "geometry": {"coordinates":[-0.5563089848,38.1976890564],"type":"Point"}
}