{
  "type": "Feature",
  "properties": {
    "addr:full":"Calle de Columela, 2 Madrid Madrid 28001",
    "addr:housenumber":"2",
    "addr:postcode":"28001",
    "addr:street":"Calle De Columela",
    "iso:country":"ES",
    "sg:address":"Calle de Columela, 2",
    "sg:city":"Madrid",
    "sg:orig_category":"Inmobiliaria (agencias)",
    "sg:phone":"+34 915 75 04 57",
    "sg:postcode":"28001",
    "sg:province":"Madrid",
    "wof:name":"Area Urbana Gestion Inmobiliaria S.l.",
    "wof:placetype":"venue"
},
  "geometry": {"coordinates":[-3.6883687973,40.4211807251],"type":"Point"}
}