{
  "type": "Feature",
  "properties": {
    "addr:full":"Calle de Isla De La Palma, 61 Urbanizacion Valle Grande Toledo 45224",
    "addr:housenumber":"61",
    "addr:postcode":"45224",
    "addr:street":"Calle De Isla De La Palma;Valle",
    "iso:country":"ES",
    "sg:address":"Calle de Isla De La Palma, 61",
    "sg:city":"Urbanizacion Valle Grande",
    "sg:orig_category":"Herboristas (al Por Menor)",
    "sg:phone":"+34 918 01 31 28",
    "sg:postcode":"45224",
    "sg:province":"Toledo",
    "wof:name":"Celar Y Al Alba S.l.",
    "wof:placetype":"venue"
},
  "geometry": {"coordinates":[-3.6424319744,40.1095466614],"type":"Point"}
}