{
  "type": "Feature",
  "properties": {
    "iso:country":"ES",
    "sg:address":"Rua Felipe Dopico Bouzamayor, 8",
    "sg:city":"Ferrol",
    "sg:orig_category":"Mec\u00c1nico Del Autom\u00d3vil",
    "sg:phone":"+34 981 32 52 00",
    "sg:postcode":"15405",
    "sg:province":"A Coru\u00f1a",
    "wof:name":"Talleres Mecanicos Fernando Manso S.l.",
    "wof:placetype":"venue"
},
  "geometry": {"coordinates":[-8.2437515259,43.5037994385],"type":"Point"}
}