{
  "type": "Feature",
  "properties": {
    "iso:country":"ES",
    "sg:address":"Rond General Mitre, 9",
    "sg:city":"Barcelona",
    "sg:classifiers":[
        {
            "category":"Manufacturing",
            "subcategory":"Building Materials",
            "type":"Manufacturing & Wholesale Goods"
        }
    ],
    "sg:phone":"+34 932 80 11 43",
    "sg:postcode":"08017",
    "sg:province":"Barcelona",
    "sg:tags":[
        "cemento",
        "y",
        "de",
        "fabricaci\u00d3n",
        "cal"
    ],
    "wof:name":"Ingenieria De Cimentaciones S. A.",
    "wof:placetype":"venue"
},
  "geometry": {"coordinates":[2.1307768822,41.3931236267],"type":"Point"}
}