{
  "type": "Feature",
  "properties": {
    "addr:full":"Avda Juventud (de La), 12 Avila \u00c1vila 05003",
    "addr:housenumber":"12",
    "addr:postcode":"05003",
    "addr:street":"Avda Juventud De La;A\u0301Vila",
    "iso:country":"ES",
    "sg:address":"Avda Juventud (de La), 12",
    "sg:city":"Avila",
    "sg:orig_category":"Muebles Y Accesorios Para Cocinas Y Cuartos De Ba\u00d1o (al Por Menor)",
    "sg:phone":"+34 920 22 12 82",
    "sg:postcode":"05003",
    "sg:province":"\u00c1vila",
    "wof:name":"Diaz Descalzo Julio",
    "wof:placetype":"venue"
},
  "geometry": {"coordinates":[-4.68516922,40.6469535828],"type":"Point"}
}