{
  "type": "Feature",
  "properties": {
    "iso:country":"ES",
    "sg:address":"Calle de Garcia Morato, 21",
    "sg:city":"Alacant",
    "sg:orig_category":"Importaci\u00d3n",
    "sg:phone":"+34 965 21 33 65",
    "sg:postcode":"03004",
    "sg:province":"Alicante",
    "wof:name":"Inversiones Pelsul S.l.",
    "wof:placetype":"venue"
},
  "geometry": {"coordinates":[-0.4873859882,38.3486747742],"type":"Point"}
}