{
  "type": "Feature",
  "properties": {
    "iso:country":"ES",
    "sg:address":"Calle de Bollullos Del Condado, 25",
    "sg:city":"Huelva",
    "sg:orig_category":"Cerrajer\u00cda, Ferrallista",
    "sg:phone":"+34 959 24 39 02",
    "sg:postcode":"21002",
    "sg:province":"Huelva",
    "wof:name":"Bermejo Suarez Manuel",
    "wof:placetype":"venue"
},
  "geometry": {"coordinates":[-6.9585652351,37.2627182007],"type":"Point"}
}