{
  "type": "Feature",
  "properties": {
    "addr:full":"Carrer de Pont, 23 Poligono Barcelona 08213",
    "addr:housenumber":"23 poligono",
    "addr:postcode":"08213",
    "addr:street":"Carrer De Pont;Barcelona",
    "iso:country":"ES",
    "sg:address":"Carrer de Pont, 23",
    "sg:city":"Poligono",
    "sg:classifiers":[
        {
            "category":"Personal",
            "subcategory":"Barber",
            "type":"Services"
        }
    ],
    "sg:phone":"+34 937 13 07 63",
    "sg:postcode":"08213",
    "sg:province":"Barcelona",
    "sg:tags":[
        "caballeros",
        "de",
        "peluqueros"
    ],
    "wof:name":"Ilari Castellvell Carlos",
    "wof:placetype":"venue"
},
  "geometry": {"coordinates":[2.1570799351,41.5535011292],"type":"Point"}
}