{
  "type": "Feature",
  "properties": {
    "iso:country":"ES",
    "sg:address":"Cllo Marina, De La, S/n",
    "sg:city":"Melilla",
    "sg:orig_category":"Perreras, Pensiones Para Perros, Gatos Y Otros Animales",
    "sg:phone":"+34 952 11 60 12",
    "sg:postcode":"52005",
    "sg:province":"Melilla",
    "wof:name":"Vallejo Lopez Francisca",
    "wof:placetype":"venue"
},
  "geometry": {"coordinates":[-2.9556701183,35.2835693359],"type":"Point"}
}