{
  "type": "Feature",
  "properties": {
    "iso:country":"ES",
    "sg:address":"Urb. Pto. Jandia, 94",
    "sg:city":"Morro Jable",
    "sg:orig_category":"Peleter\u00cdas",
    "sg:phone":"+34 928 54 00 12",
    "sg:postcode":"35625",
    "sg:province":"Las Palmas",
    "wof:name":"Musra S.l.",
    "wof:placetype":"venue"
},
  "geometry": {"coordinates":[-14.3222913742,28.0607738495],"type":"Point"}
}