{
  "type": "Feature",
  "properties": {
    "addr:full":"Carrer de Castillejos, 250 Barcelona Barcelona 08013",
    "addr:housenumber":"250",
    "addr:postcode":"08013",
    "addr:street":"Carrer De Castillejos",
    "iso:country":"ES",
    "sg:address":"Carrer de Castillejos, 250",
    "sg:city":"Barcelona",
    "sg:orig_category":"Agencias De Viajes",
    "sg:phone":"+34 932 65 06 56",
    "sg:postcode":"08013",
    "sg:province":"Barcelona",
    "sg:website":"www.vinpertour.ucave.es",
    "wof:name":"Vinper Tour S.l.",
    "wof:placetype":"venue"
},
  "geometry": {"coordinates":[2.1793899536,41.4058685303],"type":"Point"}
}