{
  "type": "Feature",
  "properties": {
    "iso:country":"ES",
    "sg:address":"Scho Mayor, 8",
    "sg:city":"Iru\u00f1a",
    "sg:orig_category":"Zapatos (al Por Menor)",
    "sg:phone":"+34 948 22 39 12",
    "sg:postcode":"31002",
    "sg:province":"Navarra",
    "wof:name":"Calzados De Ni\u00f1o Juli S.l.",
    "wof:placetype":"venue"
},
  "geometry": {"coordinates":[-1.6434799433,42.8130912781],"type":"Point"}
}