{
  "type": "Feature",
  "properties": {
    "iso:country":"ES",
    "sg:address":"Avda Paskual Abaroa Etorbidea, 18",
    "sg:city":"Lekeitio",
    "sg:orig_category":"Notarios",
    "sg:phone":"+34 946 84 03 04",
    "sg:postcode":"48280",
    "sg:province":"Vizcaya",
    "wof:name":"Francisco Javier Gonzalez Lopez - Notaria",
    "wof:placetype":"venue"
},
  "geometry": {"coordinates":[-2.5054121017,43.3635406494],"type":"Point"}
}