{
  "type": "Feature",
  "properties": {
    "iso:country":"ES",
    "sg:address":"Campredo, 16",
    "sg:city":"L'aldea",
    "sg:orig_category":"Servicios De Telecomunicaciones",
    "sg:phone":"+34 977 45 00 65",
    "sg:postcode":"43896",
    "sg:province":"Tarragona",
    "wof:name":"Comunitel Global S.a.",
    "wof:placetype":"venue"
},
  "geometry": {"coordinates":[0.6271950006,40.7501411438],"type":"Point"}
}