{
  "type": "Feature",
  "properties": {
    "addr:full":"Carr Baro De Maials, 95 Lleida Lleida 25005",
    "addr:housenumber":"95",
    "addr:postcode":"25005",
    "addr:street":"Carr Baro De Maials",
    "iso:country":"ES",
    "sg:address":"Carr Baro De Maials, 95",
    "sg:city":"Lleida",
    "sg:orig_category":"Fabricaci\u00d3n, Instalaci\u00d3n De Armarios",
    "sg:phone":"+34 973 24 16 30",
    "sg:postcode":"25005",
    "sg:province":"Lleida",
    "wof:name":"B A S Armaris Sl",
    "wof:placetype":"venue"
},
  "geometry": {"coordinates":[0.6285799742,41.6275405884],"type":"Point"}
}