{
  "type": "Feature",
  "properties": {
    "iso:country":"ES",
    "sg:address":"Plaz San Vicente, S/n",
    "sg:city":"Bilbao",
    "sg:orig_category":"Aeropuertos Y Servicios Aeroportuarios",
    "sg:phone":"+34 944 23 12 48",
    "sg:postcode":"48001",
    "sg:province":"Vizcaya",
    "wof:name":"Aviareps Espa\u00d1a S.l.",
    "wof:placetype":"venue"
},
  "geometry": {"coordinates":[-2.9280788898,43.2639045715],"type":"Point"}
}