{
  "type": "Feature",
  "properties": {
    "addr:full":"Calle de Cruces, 16 Fuensalida Toledo 45510",
    "addr:housenumber":"16",
    "addr:postcode":"45510",
    "addr:street":"Calle De Cruces",
    "iso:country":"ES",
    "sg:address":"Calle de Cruces, 16",
    "sg:city":"Fuensalida",
    "sg:orig_category":"Bisuter\u00cda, Joyer\u00cda, Relojer\u00cda (al Por Menor)",
    "sg:phone":"+34 925 78 48 05",
    "sg:postcode":"45510",
    "sg:province":"Toledo",
    "wof:name":"Garben Joyeros C.b",
    "wof:placetype":"venue"
},
  "geometry": {"coordinates":[-4.2109885216,40.0518035889],"type":"Point"}
}