{
  "type": "Feature",
  "properties": {
    "iso:country":"ES",
    "sg:address":"Calle de Bermingham, 37",
    "sg:city":"Donostia-san Sebastian",
    "sg:orig_category":"Relojer\u00cda (al Por Menor, Reparaci\u00d3n)",
    "sg:phone":"+34 943 28 66 38",
    "sg:postcode":"20001",
    "sg:province":"Guip\u00f9zcoa",
    "wof:name":"Choperena Legasa Maria Jesus",
    "wof:placetype":"venue"
},
  "geometry": {"coordinates":[-1.9704589844,43.3231010437],"type":"Point"}
}