{
  "type": "Feature",
  "properties": {
    "iso:country":"ES",
    "sg:address":"Calle de Mayor, 127",
    "sg:city":"Union",
    "sg:orig_category":"Quincaller\u00cda (al Por Menor)",
    "sg:phone":"+34 968 56 04 37",
    "sg:postcode":"30360",
    "sg:province":"Murcia",
    "wof:name":"Ba\u00f1os Gutierrez Jose",
    "wof:placetype":"venue"
},
  "geometry": {"coordinates":[-0.8743360043,37.6176185608],"type":"Point"}
}