{
  "type": "Feature",
  "properties": {
    "addr:full":"Avda Domingo Bueno, 132 Pontenova Pontevedra 36400",
    "addr:housenumber":"132",
    "addr:postcode":"36400",
    "addr:street":"Avda Domingo Bueno",
    "iso:country":"ES",
    "sg:address":"Avda Domingo Bueno, 132",
    "sg:city":"Pontenova",
    "sg:orig_category":"Electricidad: Equipos Industriales, Componentes (fabricaci\u00d3n)",
    "sg:phone":"+34 986 33 60 50",
    "sg:postcode":"36400",
    "sg:province":"Pontevedra",
    "wof:name":"Electroguia S.l.",
    "wof:placetype":"venue"
},
  "geometry": {"coordinates":[-8.6179990768,42.1610298157],"type":"Point"}
}