{
  "type": "Feature",
  "properties": {
    "iso:country":"ES",
    "sg:address":"Avd Poeta M. Reina, 96",
    "sg:city":"Puente-genil",
    "sg:orig_category":"Bazares, Art\u00cdculos De Limpieza Y De Cocina (al Por Menor)",
    "sg:phone":"+34 957 60 43 96",
    "sg:postcode":"14500",
    "sg:province":"C\u00f3rdoba",
    "wof:name":"Cosano Rojas Jose",
    "wof:placetype":"venue"
},
  "geometry": {"coordinates":[-4.764316082,37.3927268982],"type":"Point"}
}