{
  "type": "Feature",
  "properties": {
    "addr:full":"Calle de Costa, 9 Bilbao Vizcaya 48010",
    "addr:housenumber":"9",
    "addr:postcode":"48010",
    "addr:street":"Calle De Costa",
    "iso:country":"ES",
    "sg:address":"Calle de Costa, 9",
    "sg:city":"Bilbao",
    "sg:orig_category":"Cine (distribuci\u00d3n)",
    "sg:phone":"+34 944 10 07 13",
    "sg:postcode":"48010",
    "sg:province":"Vizcaya",
    "wof:name":"Distribuciones Cinematograficas J.m.a.s.l.",
    "wof:placetype":"venue"
},
  "geometry": {"coordinates":[-2.9343349934,43.2582817078],"type":"Point"}
}