{
  "type": "Feature",
  "properties": {
    "iso:country":"ES",
    "sg:address":"Calle de Santa Cruz De Ardoi Kalea, 41",
    "sg:city":"Zizur Mayor",
    "sg:orig_category":"Perfumer\u00cda (al Por Menor)",
    "sg:phone":"+34 948 18 28 80",
    "sg:postcode":"31180",
    "sg:province":"Navarra",
    "wof:name":"Fernandez Beaumont Lourdes",
    "wof:placetype":"venue"
},
  "geometry": {"coordinates":[-1.6927540302,42.7928657532],"type":"Point"}
}