{
  "type": "Feature",
  "properties": {
    "addr:full":"Calle de Pintor Velazquez (del), 10 Alcobendas Madrid 28100",
    "addr:postcode":"28100",
    "addr:street":"Calle De Pintor Velazquez Del;Alcobendas",
    "iso:country":"ES",
    "sg:address":"Calle de Pintor Velazquez (del), 10",
    "sg:city":"Alcobendas",
    "sg:orig_category":"Prot\u00c9sicos Dentales",
    "sg:phone":"+34 916 61 95 23",
    "sg:postcode":"28100",
    "sg:province":"Madrid",
    "wof:name":"Tono Dental S.l.",
    "wof:placetype":"venue"
},
  "geometry": {"coordinates":[-3.6406805515,40.5385093689],"type":"Point"}
}