{
  "type": "Feature",
  "properties": {
    "iso:country":"ES",
    "sg:address":"Calle de Virgen De La Consolacion, 2",
    "sg:city":"Granada",
    "sg:orig_category":"Armas Y Municiones (fabricaci\u00d3n, Al Por Mayor)",
    "sg:phone":"+34 958 28 63 76",
    "sg:postcode":"18015",
    "sg:province":"Granada",
    "wof:name":"Armeria Ferreteria Garrido C.b.",
    "wof:placetype":"venue"
},
  "geometry": {"coordinates":[-3.6261487007,37.1935119629],"type":"Point"}
}