{
  "type": "Feature",
  "properties": {
    "addr:full":"Avgd Blasco Iba\u00d1ez, 33 Paterna Valencia 46980",
    "addr:housenumber":"33",
    "addr:postcode":"46980",
    "addr:street":"Iban\u0303Ez",
    "iso:country":"ES",
    "sg:address":"Avgd Blasco Iba\u00d1ez, 33",
    "sg:city":"Paterna",
    "sg:orig_category":"Mec\u00c1nico Del Autom\u00d3vil",
    "sg:phone":"+34 961 37 07 83",
    "sg:postcode":"46980",
    "sg:province":"Valencia",
    "wof:name":"Automotriz Andreu Hnos S.a.",
    "wof:placetype":"venue"
},
  "geometry": {"coordinates":[-0.4405986071,39.5020637512],"type":"Point"}
}