{
  "type": "Feature",
  "properties": {
    "iso:country":"ES",
    "sg:address":"Cmno Vita, 14",
    "sg:city":"Crespos",
    "sg:orig_category":"Material Y Herramientas Agr\u00cdcolas",
    "sg:phone":"+34 920 24 40 19",
    "sg:postcode":"05300",
    "sg:province":"\u00c1vila",
    "wof:name":"Maquinaria Agricola Cruz S.l.",
    "wof:placetype":"venue"
},
  "geometry": {"coordinates":[-4.9710350037,40.8741416931],"type":"Point"}
}