{
  "type": "Feature",
  "properties": {
    "iso:country":"ES",
    "sg:address":"Calle de Conde Don Ramon, 15",
    "sg:city":"Salamanca",
    "sg:orig_category":"Agencias Y Agentes Comerciales, Representantes",
    "sg:phone":"+34 923 22 07 87",
    "sg:postcode":"37004",
    "sg:province":"Salamanca",
    "wof:name":"Rodriguez Turrion Jose Manuel",
    "wof:placetype":"venue"
},
  "geometry": {"coordinates":[-5.6558427811,40.973033905],"type":"Point"}
}