{
  "type": "Feature",
  "properties": {
    "addr:full":"Calle de Villamonte, 13 Algorta Vizcaya 48991",
    "addr:housenumber":"13",
    "addr:postcode":"48991",
    "addr:street":"Calle De Villamonte",
    "iso:country":"ES",
    "sg:address":"Calle de Villamonte, 13",
    "sg:city":"Algorta",
    "sg:orig_category":"Deportes Y Programas De Aventura",
    "sg:phone":"+34 944 30 05 18",
    "sg:postcode":"48991",
    "sg:province":"Vizcaya",
    "wof:name":"Lejonagoitia Orueta Jose Luis",
    "wof:placetype":"venue"
},
  "geometry": {"coordinates":[-3.007152319,43.3504714966],"type":"Point"}
}