{
  "type": "Feature",
  "properties": {
    "iso:country":"ES",
    "sg:address":"Casetas, S/n",
    "sg:city":"Casetas",
    "sg:orig_category":"Electricidad Veh\u00cdculo",
    "sg:phone":"+34 986 75 54 95",
    "sg:postcode":"36559",
    "sg:province":"Pontevedra",
    "wof:name":"Forcarei Motor S.l.",
    "wof:placetype":"venue"
},
  "geometry": {"coordinates":[-8.6428003311,42.4304618835],"type":"Point"}
}