{
  "type": "Feature",
  "properties": {
    "addr:full":"Avda Zugatzarte, 3 Arenas -areeta Vizcaya 48930",
    "addr:housenumber":"3;areeta",
    "addr:postcode":"48930",
    "addr:street":"Avda Zugatzarte",
    "iso:country":"ES",
    "sg:address":"Avda Zugatzarte, 3",
    "sg:city":"Arenas -areeta",
    "sg:orig_category":"Asesor\u00cda Sobre Comunicaci\u00d3n De Empresas",
    "sg:phone":"+34 944 80 06 24",
    "sg:postcode":"48930",
    "sg:province":"Vizcaya",
    "wof:name":"Hispania Service S.l.",
    "wof:placetype":"venue"
},
  "geometry": {"coordinates":[-2.6983869076,43.2204284668],"type":"Point"}
}