{
  "type": "Feature",
  "properties": {
    "iso:country":"ES",
    "sg:address":"Pase Rio Del, 6",
    "sg:city":"Puerto Sotogrande",
    "sg:orig_category":"Inmobiliaria (agencias)",
    "sg:phone":"+34 956 61 03 83",
    "sg:postcode":"11310",
    "sg:province":"C\u00e1diz",
    "wof:name":"Crosoer  Susane Caroline",
    "wof:placetype":"venue"
},
  "geometry": {"coordinates":[-5.2829370499,36.2767448425],"type":"Point"}
}