{
  "type": "Feature",
  "properties": {
    "addr:full":"Calle de Atenea, 2 Mairena Aljarafe Sevilla 41927",
    "addr:housenumber":"2",
    "addr:postcode":"41927",
    "addr:street":"Calle De Atenea",
    "iso:country":"ES",
    "sg:address":"Calle de Atenea, 2",
    "sg:city":"Mairena Aljarafe",
    "sg:orig_category":"Molduras, Junquillos, Listones Y Molduras Perforadas",
    "sg:phone":"+34 954 18 43 46",
    "sg:postcode":"41927",
    "sg:province":"Sevilla",
    "wof:name":"Eurosur De Cervecerias S.l.",
    "wof:placetype":"venue"
},
  "geometry": {"coordinates":[-6.0460309982,37.3526802063],"type":"Point"}
}