{
  "type": "Feature",
  "properties": {
    "iso:country":"ES",
    "sg:address":"Calle de Olivo, 12",
    "sg:city":"Puebla Alfinden",
    "sg:orig_category":"Mec\u00c1nico Del Autom\u00d3vil",
    "sg:phone":"+34 976 10 88 55",
    "sg:postcode":"50171",
    "sg:province":"Zaragoza",
    "wof:name":"Pertusa Felipe Jacinto",
    "wof:placetype":"venue"
},
  "geometry": {"coordinates":[-0.7617740035,41.639465332],"type":"Point"}
}