{
  "type": "Feature",
  "properties": {
    "iso:country":"ES",
    "sg:address":"Calle de Luis De Morales, 20",
    "sg:city":"Sevilla",
    "sg:orig_category":"Ropa Para Ni\u00d1os (al Por Menor)",
    "sg:phone":"+34 954 54 05 07",
    "sg:postcode":"41018",
    "sg:province":"Sevilla",
    "sg:website":"www.neckandneck.com",
    "wof:name":"Neck Child S.a.",
    "wof:placetype":"venue"
},
  "geometry": {"coordinates":[-5.9725461006,37.3867874146],"type":"Point"}
}