{
  "type": "Feature",
  "properties": {
    "addr:full":"Calle de San Francisco, 4 Quintanar Orden Toledo 45800",
    "addr:housenumber":"4",
    "addr:postcode":"45800",
    "addr:street":"Calle De San Francisco",
    "iso:country":"ES",
    "sg:address":"Calle de San Francisco, 4",
    "sg:city":"Quintanar Orden",
    "sg:orig_category":"Cristaler\u00cdas",
    "sg:phone":"+34 925 18 04 51",
    "sg:postcode":"45800",
    "sg:province":"Toledo",
    "wof:name":"Moreno Sanchez De La Blanca Julian",
    "wof:placetype":"venue"
},
  "geometry": {"coordinates":[-3.0414350033,39.5916900635],"type":"Point"}
}