{
  "type": "Feature",
  "properties": {
    "iso:country":"ES",
    "sg:address":"Dr D Antonio Estaca, 5",
    "sg:city":"Espinardo",
    "sg:orig_category":"Iglesia Cat\u00d3lica",
    "sg:phone":"+34 968 83 05 76",
    "sg:postcode":"30100",
    "sg:province":"Murcia",
    "wof:name":"Obispado De Cartagena",
    "wof:placetype":"venue"
},
  "geometry": {"coordinates":[-1.1508959532,38.0083770752],"type":"Point"}
}