{
  "type": "Feature",
  "properties": {
    "iso:country":"ES",
    "sg:address":"Carrer de Proven\u00c7a, 126",
    "sg:city":"Barcelona",
    "sg:orig_category":"Asesor\u00cda De Formaci\u00d3n Y Gesti\u00d3n De Personal",
    "sg:phone":"+34 934 10 05 65",
    "sg:postcode":"08029",
    "sg:province":"Barcelona",
    "wof:name":"Robles Lopez Emilio",
    "wof:placetype":"venue"
},
  "geometry": {"coordinates":[2.1502630711,41.3860969543],"type":"Point"}
}