{
  "type": "Feature",
  "properties": {
    "addr:full":"Calle de Almansa, 19 Madrid Madrid 28039",
    "addr:housenumber":"19",
    "addr:postcode":"madrid;28039",
    "addr:street":"Calle De Almansa",
    "iso:country":"ES",
    "sg:address":"Calle de Almansa, 19",
    "sg:city":"Madrid",
    "sg:orig_category":"Peluquer\u00cdas, Peluquer\u00cda Mixta",
    "sg:phone":"+34 915 33 19 27",
    "sg:postcode":"28039",
    "sg:province":"Madrid",
    "wof:name":"Malecom Peluqueros S.l.",
    "wof:placetype":"venue"
},
  "geometry": {"coordinates":[-3.705411911,40.4487495422],"type":"Point"}
}