{
  "type": "Feature",
  "properties": {
    "iso:country":"ES",
    "sg:address":"Carrer de Gabriel Manalt, 23",
    "sg:city":"Martorell",
    "sg:orig_category":"Arquitectos",
    "sg:phone":"+34 937 75 30 25",
    "sg:postcode":"08760",
    "sg:province":"Barcelona",
    "wof:name":"Estudi D'arquitectura Tecnica Serafi Alvaro S.l.",
    "wof:placetype":"venue"
},
  "geometry": {"coordinates":[1.9131230116,41.4869117737],"type":"Point"}
}