{
  "type": "Feature",
  "properties": {
    "iso:country":"ES",
    "sg:address":"Barrera, 5",
    "sg:city":"Ourense",
    "sg:orig_category":"Fabricaci\u00d3n De Peines Y De Accesorios De Peluquer\u00cda",
    "sg:phone":"+34 988 22 18 49",
    "sg:postcode":"32005",
    "sg:province":"Ourense",
    "wof:name":"Torres Gonzalez Alfonso",
    "wof:placetype":"venue"
},
  "geometry": {"coordinates":[-7.8519001007,42.3053703308],"type":"Point"}
}