{
  "type": "Feature",
  "properties": {
    "iso:country":"ES",
    "sg:address":"Rua Sol (do), 17",
    "sg:city":"Marin",
    "sg:orig_category":"Art\u00cdculos De Regalo (al Por Menor)",
    "sg:phone":"+34 986 89 13 51",
    "sg:postcode":"36900",
    "sg:province":"Pontevedra",
    "wof:name":"Duende C.b.",
    "wof:placetype":"venue"
},
  "geometry": {"coordinates":[-8.6881885529,42.391746521],"type":"Point"}
}