{
  "type": "Feature",
  "properties": {
    "addr:full":"Pol Ind Los Cerros, S/n Ubeda Ja\u00e9n 23400",
    "addr:housenumber":"s / n",
    "addr:postcode":"23400",
    "addr:street":"Cerros;Ubeda Jae\u0301N",
    "iso:country":"ES",
    "sg:address":"Pol Ind Los Cerros, S/n",
    "sg:city":"Ubeda",
    "sg:orig_category":"Insecticidas, Fumigaci\u00d3n",
    "sg:phone":"+34 953 75 60 25",
    "sg:postcode":"23400",
    "sg:province":"Ja\u00e9n",
    "sg:website":"www.lugosa.net",
    "wof:name":"Luis Gonzalez E Hijos S.a.",
    "wof:placetype":"venue"
},
  "geometry": {"coordinates":[-3.3713839054,38.0111618042],"type":"Point"}
}