{
  "type": "Feature",
  "properties": {
    "addr:full":"Avda Doctor Ramon Y Cajal, 11 Alacant Alicante 03003",
    "addr:housenumber":"11",
    "addr:postcode":"03003",
    "addr:street":"Avda Doctor Ramon Y Cajal",
    "iso:country":"ES",
    "sg:address":"Avda Doctor Ramon Y Cajal, 11",
    "sg:city":"Alacant",
    "sg:orig_category":"Empresas De Vigilancia, Guardia Y Protecci\u00d3n",
    "sg:phone":"+34 965 92 02 07",
    "sg:postcode":"03003",
    "sg:province":"Alicante",
    "sg:website":"www.provinen.es",
    "wof:name":"Provinen Seguridad S.a.",
    "wof:placetype":"venue"
},
  "geometry": {"coordinates":[-0.4888069928,38.3396072388],"type":"Point"}
}