{
  "type": "Feature",
  "properties": {
    "iso:country":"ES",
    "sg:address":"Avda Sinforiano Madro\u00d1ero, 20",
    "sg:city":"Badajoz",
    "sg:orig_category":"Asesor\u00cda Sobre Comunicaci\u00d3n De Empresas",
    "sg:phone":"+34 924 22 32 84",
    "sg:postcode":"06011",
    "sg:province":"Badajoz",
    "wof:name":"Gae Asesoramientos Tributarios S.l.",
    "wof:placetype":"venue"
},
  "geometry": {"coordinates":[-6.9869852066,38.8680877686],"type":"Point"}
}