{
  "type": "Feature",
  "properties": {
    "addr:full":"Calle de Chile, 21 Torres Cotillas Murcia 30565",
    "addr:housenumber":"21",
    "addr:postcode":"30565",
    "addr:street":"Calle De Chile",
    "iso:country":"ES",
    "sg:address":"Calle de Chile, 21",
    "sg:city":"Torres Cotillas",
    "sg:orig_category":"Comercio, Reparaci\u00d3n De Motocicletas, Bicicletas Y Piezas Sueltas",
    "sg:phone":"+34 968 62 82 82",
    "sg:postcode":"30565",
    "sg:province":"Murcia",
    "wof:name":"Beltran Vicente Antonio",
    "wof:placetype":"venue"
},
  "geometry": {"coordinates":[-1.2459189892,38.0301246643],"type":"Point"}
}