{
  "type": "Feature",
  "properties": {
    "iso:country":"ES",
    "sg:address":"Hiribarren Kalea, 36",
    "sg:city":"Lazkao",
    "sg:orig_category":"Alquiler De Gr\u00daas",
    "sg:phone":"+34 943 88 88 02",
    "sg:postcode":"20210",
    "sg:province":"Guip\u00f9zcoa",
    "wof:name":"Pinternal S. A.",
    "wof:placetype":"venue"
},
  "geometry": {"coordinates":[-2.1877839565,43.0363769531],"type":"Point"}
}