{
  "type": "Feature",
  "properties": {
    "addr:full":"Avda Benigno Rivera, 54 Lugo Lugo 27003",
    "addr:housenumber":"54",
    "addr:postcode":"27003",
    "addr:street":"Avda Benigno Rivera",
    "iso:country":"ES",
    "sg:address":"Avda Benigno Rivera, 54",
    "sg:city":"Lugo",
    "sg:orig_category":"Agentes, Concesionarios Y Sucursales De Veh\u00cdculos",
    "sg:phone":"+34 982 20 92 14",
    "sg:postcode":"27003",
    "sg:province":"Lugo",
    "wof:name":"Autodome S.l.",
    "wof:placetype":"venue"
},
  "geometry": {"coordinates":[-7.5706329346,43.0423660278],"type":"Point"}
}