{
  "type": "Feature",
  "properties": {
    "addr:full":"Calle de Antonio Machado (de), 52 San Fernando De Henares Madrid 28830",
    "addr:housenumber":"52",
    "addr:postcode":"28830",
    "addr:street":"Calle De Antonio Machado De",
    "iso:country":"ES",
    "sg:address":"Calle de Antonio Machado (de), 52",
    "sg:city":"San Fernando De Henares",
    "sg:orig_category":"Electricidad: Instaladores",
    "sg:phone":"+34 916 69 26 35",
    "sg:postcode":"28830",
    "sg:province":"Madrid",
    "wof:name":"Afp Electrogrupo S.l.l.",
    "wof:placetype":"venue"
},
  "geometry": {"coordinates":[-3.5356009007,40.4236869812],"type":"Point"}
}