{
  "type": "Feature",
  "properties": {
    "addr:full":"Calle de San Ramon Nonato, 2 Madrid Madrid 28046",
    "addr:housenumber":"2",
    "addr:postcode":"28046",
    "addr:street":"Calle De San;Nonato",
    "iso:country":"ES",
    "sg:address":"Calle de San Ramon Nonato, 2",
    "sg:city":"Madrid",
    "sg:orig_category":"Aparcamientos (infraestructuras, Accesorios)",
    "sg:phone":"+34 917 33 73 94",
    "sg:postcode":"28046",
    "sg:province":"Madrid",
    "wof:name":"Talleres Aparcamientos Y Garages S. A.",
    "wof:placetype":"venue"
},
  "geometry": {"coordinates":[-3.6875679493,40.4696578979],"type":"Point"}
}