{
  "type": "Feature",
  "properties": {
    "addr:full":"Disseminats, Km. 0329,5 S. Vicen\u00e7 Horts Barcelona 08620",
    "addr:postcode":"08620",
    "addr:street":"Disseminats Km. 0329,5 S. Vicenc\u0327 Horts Barcelona",
    "iso:country":"ES",
    "sg:address":"Disseminats, Km. 0329,5",
    "sg:city":"S. Vicen\u00e7 Horts",
    "sg:classifiers":[
        {
            "category":"Home & Garden",
            "subcategory":"Household Appliances",
            "type":"Retail Goods"
        }
    ],
    "sg:phone":"+34 936 56 75 70",
    "sg:postcode":"08620",
    "sg:province":"Barcelona",
    "sg:tags":[
        "bodega",
        "de",
        "vino",
        "acondicionamiento"
    ],
    "wof:name":"Codorniu S.a.",
    "wof:placetype":"venue"
},
  "geometry": {"coordinates":[2.0100400448,41.3932189941],"type":"Point"}
}