{
  "type": "Feature",
  "properties": {
    "addr:full":"Ctra Valencia-albacete, Km. 0221,2 Benifaio Valencia 46450",
    "addr:postcode":"46450",
    "addr:street":"Ctra Valencia-Albacete Km. 0221,2",
    "iso:country":"ES",
    "sg:address":"Ctra Valencia-albacete, Km. 0221,2",
    "sg:city":"Benifaio",
    "sg:orig_category":"Material Y Suministros Para Horticultura, Arboricultura",
    "sg:phone":"+34 961 78 17 00",
    "sg:postcode":"46450",
    "sg:province":"Valencia",
    "wof:name":"Horticultura Lorente S.l.",
    "wof:placetype":"venue"
},
  "geometry": {"coordinates":[-0.4229789972,39.2867202759],"type":"Point"}
}