{
  "type": "Feature",
  "properties": {
    "iso:country":"ES",
    "sg:address":"Carrer de Balmes, 319",
    "sg:city":"Barcelona",
    "sg:orig_category":"M\u00c9dicos: Pediatr\u00cda. Enfermedades De Los Ni\u00d1os",
    "sg:phone":"+34 934 18 24 92",
    "sg:postcode":"08006",
    "sg:province":"Barcelona",
    "wof:name":"C.m.a.p. S.l.",
    "wof:placetype":"venue"
},
  "geometry": {"coordinates":[2.1441380978,41.4027862549],"type":"Point"}
}