{
  "type": "Feature",
  "properties": {
    "addr:full":"Rua Trapero Pardo, 35 Lugo Lugo 27004",
    "addr:housenumber":"35",
    "addr:postcode":"27004",
    "addr:street":"Rua Trapero Pardo",
    "iso:country":"ES",
    "sg:address":"Rua Trapero Pardo, 35",
    "sg:city":"Lugo",
    "sg:orig_category":"Carnicer\u00cdas, Carnicer\u00cdas",
    "sg:phone":"+34 982 21 12 91",
    "sg:postcode":"27004",
    "sg:province":"Lugo",
    "wof:name":"Ares Gomez Francisco",
    "wof:placetype":"venue"
},
  "geometry": {"coordinates":[-7.5729894638,43.0107383728],"type":"Point"}
}