{
  "type": "Feature",
  "properties": {
    "addr:full":"Calle de Cimadevila, S/n Boiro La Coru\u00f1a 15930",
    "addr:housenumber":"s / n",
    "addr:postcode":"15930",
    "addr:street":"Calle De Cimadevila;La Corun\u0303A",
    "iso:country":"ES",
    "sg:address":"Calle de Cimadevila, S/n",
    "sg:city":"Boiro",
    "sg:orig_category":"Distribuci\u00d3n De Petr\u00d3leo Y Derivados",
    "sg:phone":"+34 981 84 44 99",
    "sg:postcode":"15930",
    "sg:province":"La Coru\u00f1a",
    "wof:name":"Loureda Dominguez Jose",
    "wof:placetype":"venue"
},
  "geometry": {"coordinates":[-8.8747062683,42.6569137573],"type":"Point"}
}