{
  "type": "Feature",
  "properties": {
    "addr:full":"Calle de Doctor Braulio Busto, S/n Candas Asturias 33430",
    "addr:housenumber":"s / n",
    "addr:postcode":"33430",
    "addr:street":"Calle De Doctor Braulio Busto",
    "iso:country":"ES",
    "sg:address":"Calle de Doctor Braulio Busto, S/n",
    "sg:city":"Candas",
    "sg:orig_category":"Caf\u00c9s, Bares, Cervecer\u00cdas",
    "sg:phone":"+34 985 87 19 77",
    "sg:postcode":"33430",
    "sg:province":"Asturias",
    "wof:name":"Vega Busto Manuel",
    "wof:placetype":"venue"
},
  "geometry": {"coordinates":[-5.7651190758,43.5895767212],"type":"Point"}
}