{
  "type": "Feature",
  "properties": {
    "iso:country":"ES",
    "sg:address":"El Curtijo, S/n",
    "sg:city":"Villarramiel",
    "sg:orig_category":"Granos Y Semillas (producci\u00d3n, Al Por Mayor)",
    "sg:phone":"+34 979 83 74 74",
    "sg:postcode":"34140",
    "sg:province":"Palencia",
    "wof:name":"Semillas Villarramiel S.l.",
    "wof:placetype":"venue"
},
  "geometry": {"coordinates":[-4.915391922,42.0444831848],"type":"Point"}
}