{
  "type": "Feature",
  "properties": {
    "iso:country":"ES",
    "sg:address":"Calle de Joaquin Costa, 33",
    "sg:city":"Valencia",
    "sg:orig_category":"Arquitectos",
    "sg:phone":"+34 963 95 03 68",
    "sg:postcode":"46005",
    "sg:province":"Valencia",
    "wof:name":"Albert Roca Jose Jorge",
    "wof:placetype":"venue"
},
  "geometry": {"coordinates":[-0.3665294945,39.4652404785],"type":"Point"}
}