{
  "type": "Feature",
  "properties": {
    "addr:full":"Major, 2 Bossost Lleida 25550",
    "addr:housenumber":"2",
    "addr:postcode":"25550",
    "addr:street":"Major",
    "iso:country":"ES",
    "sg:address":"Major, 2",
    "sg:city":"Bossost",
    "sg:orig_category":"Supermercados Y Hipermercados",
    "sg:phone":"+34 973 64 83 32",
    "sg:postcode":"25550",
    "sg:province":"Lleida",
    "wof:name":"Euromercat Pablo S.l.",
    "wof:placetype":"venue"
},
  "geometry": {"coordinates":[0.6923300028,42.7854309082],"type":"Point"}
}