{
  "type": "Feature",
  "properties": {
    "addr:full":"Calle de San Jose, 41 Coru\u00d1a La Coru\u00f1a 15008",
    "addr:housenumber":"41",
    "addr:postcode":"15008",
    "addr:street":"Calle De San;Corun\u0303A La Corun\u0303A",
    "iso:country":"ES",
    "sg:address":"Calle de San Jose, 41",
    "sg:city":"Coru\u00d1a",
    "sg:orig_category":"Promotores Constructores",
    "sg:phone":"+34 981 26 48 63",
    "sg:postcode":"15008",
    "sg:province":"La Coru\u00f1a",
    "wof:name":"Isle\u00f1a De Revestimiento S.l.",
    "wof:placetype":"venue"
},
  "geometry": {"coordinates":[-8.4512443542,43.3434753418],"type":"Point"}
}