{
  "type": "Feature",
  "properties": {
    "iso:country":"ES",
    "sg:address":"Plaz Casilla, 4",
    "sg:city":"Bilbao",
    "sg:orig_category":"Molduras, Junquillos, Listones Y Molduras Perforadas",
    "sg:phone":"+34 944 21 64 64",
    "sg:postcode":"48012",
    "sg:province":"Vizcaya",
    "wof:name":"Lopez Ruiz Rafael",
    "wof:placetype":"venue"
},
  "geometry": {"coordinates":[-2.942884922,43.2564125061],"type":"Point"}
}