{
  "type": "Feature",
  "properties": {
    "iso:country":"ES",
    "sg:address":"Pueblo Sur, 9",
    "sg:city":"Cortijillos",
    "sg:orig_category":"Distribuci\u00d3n De Petr\u00d3leo Y Derivados",
    "sg:phone":"+34 956 67 77 45",
    "sg:postcode":"11379",
    "sg:province":"C\u00e1diz",
    "wof:name":"Jose Antonio Rodriguez E Hijos",
    "wof:placetype":"venue"
},
  "geometry": {"coordinates":[-5.4428992271,36.1843261719],"type":"Point"}
}