{
  "type": "Feature",
  "properties": {
    "addr:full":"Clavellina, S/n Alcala Guadaira Sevilla 41500",
    "addr:postcode":"41500",
    "addr:street":"Clavellina S / N",
    "iso:country":"ES",
    "sg:address":"Clavellina, S/n",
    "sg:city":"Alcala Guadaira",
    "sg:orig_category":"Cerrajer\u00cda, Ferrallista",
    "sg:phone":"+34 955 63 12 72",
    "sg:postcode":"41500",
    "sg:province":"Sevilla",
    "wof:name":"Lopez Recacha Juan Jose",
    "wof:placetype":"venue"
},
  "geometry": {"coordinates":[-5.8744840622,37.3833465576],"type":"Point"}
}