{
  "type": "Feature",
  "properties": {
    "iso:country":"ES",
    "sg:address":"Calle de Poeta Federico Garcia Lorca, 42",
    "sg:city":"Fernan Nu\u00e7ez",
    "sg:orig_category":"Sindicatos De Trabajadores",
    "sg:phone":"+34 957 37 30 65",
    "sg:postcode":"14520",
    "sg:province":"C\u00f3rdoba",
    "wof:name":"Confederacion Nacional Del Trabajo",
    "wof:placetype":"venue"
},
  "geometry": {"coordinates":[-4.7272591591,37.6696510315],"type":"Point"}
}