{
  "type": "Feature",
  "properties": {
    "addr:full":"Psaj Canalizacion, 3 Madrid Madrid 28026",
    "addr:housenumber":"3",
    "addr:postcode":"28026",
    "addr:street":"Canalizacion",
    "iso:country":"ES",
    "sg:address":"Psaj Canalizacion, 3",
    "sg:city":"Madrid",
    "sg:orig_category":"Maquinaria Para Industrias Diversas",
    "sg:phone":"+34 917 92 09 41",
    "sg:postcode":"28026",
    "sg:province":"Madrid",
    "wof:name":"Tecno Izquierdo S.l.",
    "wof:placetype":"venue"
},
  "geometry": {"coordinates":[-3.6991560459,40.3887863159],"type":"Point"}
}