{
  "type": "Feature",
  "properties": {
    "iso:country":"ES",
    "sg:address":"Calle de Mayor, 2",
    "sg:city":"Madrid",
    "sg:orig_category":"Panader\u00cdas, Panader\u00cdas",
    "sg:phone":"+34 915 21 12 01",
    "sg:postcode":"28013",
    "sg:province":"Madrid",
    "wof:name":"La Mallorquina S. L.",
    "wof:placetype":"venue"
},
  "geometry": {"coordinates":[-3.7047424316,40.4165534973],"type":"Point"}
}