{
  "type": "Feature",
  "properties": {
    "iso:country":"ES",
    "sg:address":"Disem Eras Cerrao, S/n",
    "sg:city":"Paradas",
    "sg:orig_category":"Poli\u00c9ster",
    "sg:phone":"+34 955 84 43 01",
    "sg:postcode":"41610",
    "sg:province":"Sevilla",
    "wof:name":"Poliester Paradas S.l.",
    "wof:placetype":"venue"
},
  "geometry": {"coordinates":[-5.4962830544,37.290561676],"type":"Point"}
}