{
  "type": "Feature",
  "properties": {
    "addr:full":"Ctra. Valladolid, Km. 0160,0 Golmayo Soria 42190",
    "addr:postcode":"42190",
    "addr:street":"Ctra. Valladolid Km. 0160,0",
    "iso:country":"ES",
    "sg:address":"Ctra. Valladolid, Km. 0160,0",
    "sg:city":"Golmayo",
    "sg:orig_category":"Promotores Constructores",
    "sg:phone":"+34 975 22 57 15",
    "sg:postcode":"42190",
    "sg:province":"Soria",
    "wof:name":"Se\u00d1alizaciones Villar S.a.",
    "wof:placetype":"venue"
},
  "geometry": {"coordinates":[-2.5235359669,41.765663147],"type":"Point"}
}