{
  "type": "Feature",
  "properties": {
    "iso:country":"ES",
    "sg:address":"Av Raval Del Carme, 78",
    "sg:city":"Tarrega",
    "sg:orig_category":"Comercio De Piezas De Recambio Y De Accesorios De Veh\u00cdculos, Veh\u00cdculos Industriales",
    "sg:phone":"+34 973 31 07 90",
    "sg:postcode":"25300",
    "sg:province":"Lleida",
    "wof:name":"Garatge Mundial Sl",
    "wof:placetype":"venue"
},
  "geometry": {"coordinates":[1.1415140629,41.6490097046],"type":"Point"}
}