{
  "type": "Feature",
  "properties": {
    "iso:country":"ES",
    "sg:address":"Calle de Margarita Nelken, 6",
    "sg:city":"Badajoz",
    "sg:orig_category":"Institutos De Belleza",
    "sg:phone":"+34 924 22 26 01",
    "sg:postcode":"06005",
    "sg:province":"Badajoz",
    "wof:name":"Alcaide Reyes Antonia",
    "wof:placetype":"venue"
},
  "geometry": {"coordinates":[-6.9757137299,38.8741073608],"type":"Point"}
}