{
  "type": "Feature",
  "properties": {
    "addr:full":"Calle de Fernandez De Los Rios, 88 Madrid Madrid 28015",
    "addr:housenumber":"88",
    "addr:postcode":"madrid;28015",
    "addr:street":"Calle De Fernandez De Los Rios",
    "iso:country":"ES",
    "sg:address":"Calle de Fernandez De Los Rios, 88",
    "sg:city":"Madrid",
    "sg:orig_category":"Ense\u00d1anza Variada",
    "sg:phone":"+34 914 55 02 09",
    "sg:postcode":"28015",
    "sg:province":"Madrid",
    "wof:name":"Deroyes S.l.",
    "wof:placetype":"venue"
},
  "geometry": {"coordinates":[-3.7149009705,40.4355125427],"type":"Point"}
}