{
  "type": "Feature",
  "properties": {
    "addr:full":"Mercado Municipal, S/n Tavernes Valldigna Valencia 46760",
    "addr:housenumber":"s / n",
    "addr:postcode":"46760",
    "iso:country":"ES",
    "sg:address":"Mercado Municipal, S/n",
    "sg:city":"Tavernes Valldigna",
    "sg:orig_category":"Pescader\u00cdas (al Por Menor)",
    "sg:phone":"+34 962 82 34 20",
    "sg:postcode":"46760",
    "sg:province":"Valencia",
    "wof:name":"Boronat Pose Enrique",
    "wof:placetype":"venue"
},
  "geometry": {"coordinates":[-0.2594090104,39.0749702454],"type":"Point"}
}