{
  "type": "Feature",
  "properties": {
    "addr:full":"Calle de Jose Maria Pereda, 25 Torrelavega Cantabria 39300",
    "addr:housenumber":"25",
    "addr:postcode":"39300",
    "addr:street":"Calle De Jose Maria Pereda",
    "iso:country":"ES",
    "sg:address":"Calle de Jose Maria Pereda, 25",
    "sg:city":"Torrelavega",
    "sg:orig_category":"\u00d3ptica: Instrumentos (fabricaci\u00d3n)",
    "sg:phone":"+34 942 88 17 06",
    "sg:postcode":"39300",
    "sg:province":"Cantabria",
    "wof:name":"Optica Y Relojeria Manuz S.c.",
    "wof:placetype":"venue"
},
  "geometry": {"coordinates":[-4.0498189926,43.3503799438],"type":"Point"}
}