{
  "type": "Feature",
  "properties": {
    "addr:full":"Pla\u00c7 Esplanada, De S', 54 Mao Islas Baleares 07702",
    "addr:postcode":"07702",
    "addr:street":"Islas",
    "iso:country":"ES",
    "sg:address":"Pla\u00c7 Esplanada, De S', 54",
    "sg:city":"Mao",
    "sg:orig_category":"Reposter\u00cdas",
    "sg:phone":"+34 971 36 93 84",
    "sg:postcode":"07702",
    "sg:province":"Islas Baleares",
    "wof:name":"Panaderia Pons S. A.",
    "wof:placetype":"venue"
},
  "geometry": {"coordinates":[4.2599329948,39.8884811401],"type":"Point"}
}