{
  "type": "Feature",
  "properties": {
    "iso:country":"ES",
    "sg:address":"Polig Ind Cruz Chiquita, 10",
    "sg:city":"Alcala Rio",
    "sg:orig_category":"Hormig\u00d3n Listo Para Usar",
    "sg:phone":"+34 955 65 14 91",
    "sg:postcode":"41200",
    "sg:province":"Sevilla",
    "wof:name":"Barosev Sca",
    "wof:placetype":"venue"
},
  "geometry": {"coordinates":[-5.9833860397,37.521987915],"type":"Point"}
}