{
  "type": "Feature",
  "properties": {
    "iso:country":"ES",
    "sg:address":"Calle de Costa Brava, 15",
    "sg:city":"Madrid",
    "sg:orig_category":"Agencias De Prensa E Informaci\u00d3n",
    "sg:phone":"+34 917 34 43 95",
    "sg:postcode":"28034",
    "sg:province":"Madrid",
    "wof:name":"Iniciativas De Prensa Y Comunicacion S.l.",
    "wof:placetype":"venue"
},
  "geometry": {"coordinates":[-3.701649189,40.495136261],"type":"Point"}
}