{
  "type": "Feature",
  "properties": {
    "addr:full":"Cmno Batan, S/n Caspe Zaragoza 50700",
    "addr:housenumber":"s / n",
    "addr:postcode":"50700",
    "addr:street":"Cmno Batan",
    "iso:country":"ES",
    "sg:address":"Cmno Batan, S/n",
    "sg:city":"Caspe",
    "sg:orig_category":"Frutas Y Legumbres Frescas (al Por Mayor)",
    "sg:phone":"+34 976 63 33 45",
    "sg:postcode":"50700",
    "sg:province":"Zaragoza",
    "wof:name":"Joaquin Fortu\u00f1o S.l.",
    "wof:placetype":"venue"
},
  "geometry": {"coordinates":[-0.0493320003,41.2337379456],"type":"Point"}
}