{
  "type": "Feature",
  "properties": {
    "addr:full":"Carr Adan Dielh, 15 Pollen\u00e7a Islas Baleares 07460",
    "addr:housenumber":"15",
    "addr:postcode":"07460",
    "addr:street":"Carr Adan Dielh;Islas",
    "iso:country":"ES",
    "sg:address":"Carr Adan Dielh, 15",
    "sg:city":"Pollen\u00e7a",
    "sg:orig_category":"Transportes Por Carretera: Lotes Completos, Mercanc\u00cdas Diversas",
    "sg:phone":"+34 971 53 09 88",
    "sg:postcode":"07460",
    "sg:province":"Islas Baleares",
    "wof:name":"Cortes Cifre Maria",
    "wof:placetype":"venue"
},
  "geometry": {"coordinates":[3.018807888,39.8799705505],"type":"Point"}
}