{
  "type": "Feature",
  "properties": {
    "iso:country":"ES",
    "sg:address":"Pg Valldaura, 15",
    "sg:city":"Barcelona",
    "sg:orig_category":"Chapister\u00cda",
    "sg:phone":"+34 934 28 26 99",
    "sg:postcode":"08031",
    "sg:province":"Barcelona",
    "wof:name":"Talleres Plancha Y Pintura V.s. S.l.",
    "wof:placetype":"venue"
},
  "geometry": {"coordinates":[2.1551599503,41.4373092651],"type":"Point"}
}