{
  "type": "Feature",
  "properties": {
    "iso:country":"ES",
    "sg:address":"Av. Platja D'aro, 28",
    "sg:city":"Castell D'aro",
    "sg:orig_category":"Material Y Suministros Para Fabricar Y Transformar El Papel Y El Cart\u00d3n",
    "sg:phone":"+34 972 82 62 43",
    "sg:postcode":"17249",
    "sg:province":"Girona",
    "sg:website":"www.claren-quimcodis.com",
    "wof:name":"Claren Ibercuting S.l",
    "wof:placetype":"venue"
},
  "geometry": {"coordinates":[2.8271551132,41.988822937],"type":"Point"}
}