{
  "type": "Feature",
  "properties": {
    "iso:country":"ES",
    "sg:address":"Rua Suarez Vence (de), 40",
    "sg:city":"Santa Comba",
    "sg:orig_category":"Arquitectos",
    "sg:phone":"+34 981 88 13 22",
    "sg:postcode":"15840",
    "sg:province":"La Coru\u00f1a",
    "wof:name":"Garcia Gerpe Ana Maria",
    "wof:placetype":"venue"
},
  "geometry": {"coordinates":[-8.8089466095,43.0320091248],"type":"Point"}
}