{
  "type": "Feature",
  "properties": {
    "iso:country":"ES",
    "sg:address":"Calle de Jacinto Aguirre, 5",
    "sg:city":"Talavera Reina",
    "sg:orig_category":"Bisuter\u00cda, Joyer\u00cda, Relojer\u00cda (al Por Menor)",
    "sg:phone":"+34 925 82 81 16",
    "sg:postcode":"45600",
    "sg:province":"Toledo",
    "wof:name":"Gonzalez Alonso Crispin",
    "wof:placetype":"venue"
},
  "geometry": {"coordinates":[-4.8220868111,39.9627838135],"type":"Point"}
}