{
  "type": "Feature",
  "properties": {
    "iso:country":"ES",
    "sg:address":"Calle de Torrene, 10",
    "sg:city":"Algorta",
    "sg:orig_category":"Televisi\u00d3n, V\u00cddeo: Aparatos Y Accesorios (venta)",
    "sg:phone":"+34 944 60 87 49",
    "sg:postcode":"48991",
    "sg:province":"Vizcaya",
    "sg:website":"www.supersonido.es",
    "wof:name":"Supersonido S.l.",
    "wof:placetype":"venue"
},
  "geometry": {"coordinates":[-3.0105381012,43.3506889343],"type":"Point"}
}