{
  "type": "Feature",
  "properties": {
    "iso:country":"ES",
    "sg:address":"Calle de Juanelo, 24",
    "sg:city":"Madrid",
    "sg:orig_category":"Ropa Para Se\u00d1oras (al Por Menor)",
    "sg:phone":"+34 913 69 19 93",
    "sg:postcode":"28012",
    "sg:province":"Madrid",
    "wof:name":"Sabahan  M Jamil",
    "wof:placetype":"venue"
},
  "geometry": {"coordinates":[-3.706815958,40.411239624],"type":"Point"}
}