{
  "type": "Feature",
  "properties": {
    "iso:country":"ES",
    "sg:address":"Calle de Lezeaga, 2",
    "sg:city":"Bilbao",
    "sg:orig_category":"Molduras, Junquillos, Listones Y Molduras Perforadas",
    "sg:phone":"+34 944 27 68 59",
    "sg:postcode":"48002",
    "sg:province":"Vizcaya",
    "wof:name":"Perales Alvarez Argimiro Jose",
    "wof:placetype":"venue"
},
  "geometry": {"coordinates":[-2.9568853378,43.258228302],"type":"Point"}
}