{
  "type": "Feature",
  "properties": {
    "iso:country":"ES",
    "sg:address":"Carrer de Sant Bartomeu, 54",
    "sg:city":"Campello",
    "sg:orig_category":"Cl\u00cdnicas M\u00c9dicas",
    "sg:phone":"+34 965 63 29 29",
    "sg:postcode":"03560",
    "sg:province":"Alicante",
    "wof:name":"Bueno Garcia Mario",
    "wof:placetype":"venue"
},
  "geometry": {"coordinates":[-0.3910990059,38.4251785278],"type":"Point"}
}