{
  "type": "Feature",
  "properties": {
    "iso:country":"ES",
    "sg:address":"Parc Forestal Budellera, 16",
    "sg:city":"Barcelona",
    "sg:orig_category":"Alimentaci\u00d3n General (al Por Menor)",
    "sg:phone":"+34 934 06 93 47",
    "sg:postcode":"08017",
    "sg:province":"Barcelona",
    "wof:name":"Coronel Suarez Mariano",
    "wof:placetype":"venue"
},
  "geometry": {"coordinates":[2.1115341187,41.4177284241],"type":"Point"}
}