{
  "type": "Feature",
  "properties": {
    "addr:full":"Avda Alcalde Jose Ramirez Bethencourt, 21 Palmas De Gran Canaria Las Palmas 35004",
    "addr:postcode":"35004",
    "addr:street":"Avda Alcalde Jose Ramirez Bethencourt 21",
    "iso:country":"ES",
    "sg:address":"Avda Alcalde Jose Ramirez Bethencourt, 21",
    "sg:city":"Palmas De Gran Canaria",
    "sg:orig_category":"Ingenier\u00cda, Centros De Estudios (industria)",
    "sg:phone":"+34 928 23 14 95",
    "sg:postcode":"35004",
    "sg:province":"Las Palmas",
    "wof:name":"Garcia Cuyas Antonio",
    "wof:placetype":"venue"
},
  "geometry": {"coordinates":[-15.425286293,28.1224155426],"type":"Point"}
}