{
  "type": "Feature",
  "properties": {
    "addr:full":"Calle de San Roque, 6 Sevilla Sevilla 41001",
    "addr:housenumber":"6",
    "addr:postcode":"41001",
    "addr:street":"Calle De San Roque",
    "iso:country":"ES",
    "sg:address":"Calle de San Roque, 6",
    "sg:city":"Sevilla",
    "sg:orig_category":"Guarder\u00cdas",
    "sg:phone":"+34 954 21 05 95",
    "sg:postcode":"41001",
    "sg:province":"Sevilla",
    "wof:name":"Loamar Trade S.l.",
    "wof:placetype":"venue"
},
  "geometry": {"coordinates":[-5.9984111786,37.3912849426],"type":"Point"}
}