{
  "type": "Feature",
  "properties": {
    "addr:full":"Avda Italia, 19 Sevilla Sevilla 41012",
    "addr:housenumber":"19",
    "addr:postcode":"41012",
    "addr:street":"Avda Italia",
    "iso:country":"ES",
    "sg:address":"Avda Italia, 19",
    "sg:city":"Sevilla",
    "sg:orig_category":"Abogados",
    "sg:phone":"+34 954 23 82 05",
    "sg:postcode":"41012",
    "sg:province":"Sevilla",
    "wof:name":"Moeckel Gil Emilio",
    "wof:placetype":"venue"
},
  "geometry": {"coordinates":[-5.9792737961,37.3513145447],"type":"Point"}
}