{
  "type": "Feature",
  "properties": {
    "iso:country":"ES",
    "sg:address":"Capuchinos, 5",
    "sg:city":"Sta. Marta Tormes",
    "sg:orig_category":"\u00d3ptica: Instrumentos (fabricaci\u00d3n)",
    "sg:phone":"+34 923 13 35 11",
    "sg:postcode":"37900",
    "sg:province":"Salamanca",
    "sg:website":"www.visionlab.es",
    "wof:name":"Visionlab",
    "wof:placetype":"venue"
},
  "geometry": {"coordinates":[-5.6505227089,40.9495544434],"type":"Point"}
}