{
  "type": "Feature",
  "properties": {
    "addr:full":"Carrer de Valldonzella, 51 Barcelona Barcelona 08001",
    "addr:housenumber":"51",
    "addr:postcode":"08001",
    "addr:street":"Carrer De Valldonzella",
    "iso:country":"ES",
    "sg:address":"Carrer de Valldonzella, 51",
    "sg:city":"Barcelona",
    "sg:orig_category":"Empresas De Carpinter\u00cda De Madera",
    "sg:phone":"+34 933 18 50 80",
    "sg:postcode":"08001",
    "sg:province":"Barcelona",
    "wof:name":"Ramon Martinez Carlos",
    "wof:placetype":"venue"
},
  "geometry": {"coordinates":[2.1641030312,41.3824920654],"type":"Point"}
}