{
  "type": "Feature",
  "properties": {
    "iso:country":"ES",
    "sg:address":"Calle de San Bartolome, 2",
    "sg:city":"Antequera",
    "sg:orig_category":"Mec\u00c1nico Del Autom\u00d3vil",
    "sg:phone":"+34 952 84 21 13",
    "sg:postcode":"29200",
    "sg:province":"M\u00e1laga",
    "wof:name":"Ruiz Moreno Jose",
    "wof:placetype":"venue"
},
  "geometry": {"coordinates":[-4.5632472038,37.0197525024],"type":"Point"}
}