{
  "type": "Feature",
  "properties": {
    "addr:full":"Plaz Espa\u00d1a, 12 Muel Zaragoza 50450",
    "addr:housenumber":"12",
    "addr:postcode":"50450",
    "addr:street":"Plaz Espan\u0303A",
    "iso:country":"ES",
    "sg:address":"Plaz Espa\u00d1a, 12",
    "sg:city":"Muel",
    "sg:orig_category":"Cooperativas Agr\u00cdcolas",
    "sg:phone":"+34 976 14 00 25",
    "sg:postcode":"50450",
    "sg:province":"Zaragoza",
    "wof:name":"Centro Recreativo San Cristobal",
    "wof:placetype":"venue"
},
  "geometry": {"coordinates":[-1.0870109797,41.467464447],"type":"Point"}
}