{
  "type": "Feature",
  "properties": {
    "iso:country":"ES",
    "sg:address":"Calle de Leon Gil De Palacio, 5",
    "sg:city":"Madrid",
    "sg:orig_category":"Oficinas Y Gesti\u00d3n De Inmuebles",
    "sg:phone":"+34 915 01 95 34",
    "sg:postcode":"28007",
    "sg:province":"Madrid",
    "wof:name":"Villauriz Plaza Emilio",
    "wof:placetype":"venue"
},
  "geometry": {"coordinates":[-3.6786370277,40.4029464722],"type":"Point"}
}