{
  "type": "Feature",
  "properties": {
    "addr:full":"Avda Primero De Julio, 81 Valdepe\u00f1as Ciudad Real 13300",
    "addr:housenumber":"81",
    "addr:postcode":"13300",
    "addr:street":"Avda Primero De Julio",
    "iso:country":"ES",
    "sg:address":"Avda Primero De Julio, 81",
    "sg:city":"Valdepe\u00f1as",
    "sg:orig_category":"Caf\u00c9s, Bares, Cervecer\u00cdas",
    "sg:phone":"+34 926 32 20 53",
    "sg:postcode":"13300",
    "sg:province":"Ciudad Real",
    "wof:name":"Vallez Quintana Angel",
    "wof:placetype":"venue"
},
  "geometry": {"coordinates":[-3.3937571049,38.7550964355],"type":"Point"}
}