{
  "type": "Feature",
  "properties": {
    "iso:country":"ES",
    "sg:address":"Moli, 4",
    "sg:city":"Arties",
    "sg:orig_category":"Centros De Educaci\u00d3n Especial",
    "sg:phone":"+34 973 64 15 01",
    "sg:postcode":"25599",
    "sg:province":"Lleida",
    "wof:name":"Ajuntament De Naut Aran",
    "wof:placetype":"venue"
},
  "geometry": {"coordinates":[0.8728759885,42.6987991333],"type":"Point"}
}