{
  "type": "Feature",
  "properties": {
    "iso:country":"ES",
    "sg:address":"Calle de Milagrosa (la)(corralejo), 11",
    "sg:city":"Corralejo",
    "sg:orig_category":"Florister\u00cdas",
    "sg:phone":"+34 928 86 62 57",
    "sg:postcode":"35660",
    "sg:province":"Las Palmas",
    "wof:name":"Jimenez Quintana Jose Del Pino",
    "wof:placetype":"venue"
},
  "geometry": {"coordinates":[-13.8687734604,28.7382335663],"type":"Point"}
}