{
  "type": "Feature",
  "properties": {
    "iso:country":"ES",
    "sg:address":"Calle de Garcia De La Parra, 8",
    "sg:city":"Madrid",
    "sg:orig_category":"Guarder\u00cdas",
    "sg:phone":"+34 913 07 93 30",
    "sg:postcode":"28023",
    "sg:province":"Madrid",
    "wof:name":"Domingo Gonzalez Esther",
    "wof:placetype":"venue"
},
  "geometry": {"coordinates":[-3.7798841,40.4599685669],"type":"Point"}
}