{
  "type": "Feature",
  "properties": {
    "iso:country":"ES",
    "sg:address":"Del Ficus, 1",
    "sg:city":"Fuengirola",
    "sg:orig_category":"Supermercados Y Hipermercados",
    "sg:phone":"+34 952 46 67 62",
    "sg:postcode":"29640",
    "sg:province":"M\u00e1laga",
    "wof:name":"Canales Blanco S.a.",
    "wof:placetype":"venue"
},
  "geometry": {"coordinates":[-4.6076641083,36.5633239746],"type":"Point"}
}