{
  "type": "Feature",
  "properties": {
    "addr:full":"Plaz Merced De La, S/n Ronda M\u00e1laga 29400",
    "addr:postcode":"29400",
    "addr:street":"Plaz;La S / N Ronda Ma\u0301Laga",
    "iso:country":"ES",
    "sg:address":"Plaz Merced De La, S/n",
    "sg:city":"Ronda",
    "sg:orig_category":"Comunidades Religiosas",
    "sg:phone":"+34 952 87 29 65",
    "sg:postcode":"29400",
    "sg:province":"M\u00e1laga",
    "wof:name":"Carmelitas Descalzas Del Corazon Eucaristico",
    "wof:placetype":"venue"
},
  "geometry": {"coordinates":[-5.1662788391,36.7417945862],"type":"Point"}
}