{
  "type": "Feature",
  "properties": {
    "addr:full":"Ctra. Madrid, 3 Arcahueja Le\u00f3n 24227",
    "addr:housenumber":"3",
    "addr:postcode":"24227",
    "addr:street":"Ctra. Madrid",
    "iso:country":"ES",
    "sg:address":"Ctra. Madrid, 3",
    "sg:city":"Arcahueja",
    "sg:orig_category":"Estancos",
    "sg:phone":"+34 987 20 65 27",
    "sg:postcode":"24227",
    "sg:province":"Le\u00f3n",
    "wof:name":"Villanueva Gonzalez Hortensia",
    "wof:placetype":"venue"
},
  "geometry": {"coordinates":[-5.5140891075,42.5692138672],"type":"Point"}
}