{
  "type": "Feature",
  "properties": {
    "iso:country":"ES",
    "sg:address":"Rond Don Garcia, 20",
    "sg:city":"Salda\u00f1a",
    "sg:orig_category":"Ense\u00d1anza: Comercio, Gesti\u00d3n, Inform\u00c1tica",
    "sg:phone":"+34 979 89 21 05",
    "sg:postcode":"34100",
    "sg:province":"Palencia",
    "wof:name":"Gonzalez Martinez Jesus",
    "wof:placetype":"venue"
},
  "geometry": {"coordinates":[-4.7406888008,42.5192832947],"type":"Point"}
}