{
  "type": "Feature",
  "properties": {
    "addr:full":"Calle de Fernando El Catolico, 56 Pina De Ebro Zaragoza 50750",
    "addr:housenumber":"56",
    "addr:postcode":"50750",
    "addr:street":"Calle De Fernando El Catolico",
    "iso:country":"ES",
    "sg:address":"Calle de Fernando El Catolico, 56",
    "sg:city":"Pina De Ebro",
    "sg:orig_category":"Distribuci\u00d3n De Petr\u00d3leo Y Derivados",
    "sg:phone":"+34 976 16 64 73",
    "sg:postcode":"50750",
    "sg:province":"Zaragoza",
    "wof:name":"Servicios Del Octanaje S.l.",
    "wof:placetype":"venue"
},
  "geometry": {"coordinates":[-0.5235570073,41.4899406433],"type":"Point"}
}