{
  "type": "Feature",
  "properties": {
    "addr:full":"Pg Canal, 31 S. Joan Despi Barcelona 08970",
    "addr:housenumber":"31",
    "addr:postcode":"08970",
    "addr:street":"Pg Canal;S. Joan Despi",
    "iso:country":"ES",
    "sg:address":"Pg Canal, 31",
    "sg:city":"S. Joan Despi",
    "sg:orig_category":"Talleres: Ropa A Medida",
    "sg:phone":"+34 934 77 19 81",
    "sg:postcode":"08970",
    "sg:province":"Barcelona",
    "wof:name":"Centro Alar S.l.",
    "wof:placetype":"venue"
},
  "geometry": {"coordinates":[2.0581378937,41.3689804077],"type":"Point"}
}