{
  "type": "Feature",
  "properties": {
    "addr:full":"Calle de Martires De Teruel, 2 Teruel Teruel 44002",
    "addr:housenumber":"2",
    "addr:postcode":"44002",
    "addr:street":"Calle De Martires De Teruel",
    "iso:country":"ES",
    "sg:address":"Calle de Martires De Teruel, 2",
    "sg:city":"Teruel",
    "sg:orig_category":"Carnicer\u00cdas, Carnicer\u00cdas",
    "sg:phone":"+34 978 60 52 11",
    "sg:postcode":"44002",
    "sg:province":"Teruel",
    "wof:name":"Garzaran De Las Pe\u00f1as Antonia",
    "wof:placetype":"venue"
},
  "geometry": {"coordinates":[-1.1065239906,40.3362503052],"type":"Point"}
}