{
  "type": "Feature",
  "properties": {
    "addr:full":"Pg Estacio, 35 Balaguer Lleida 25600",
    "addr:housenumber":"35",
    "addr:postcode":"25600",
    "addr:street":"Pg Estacio",
    "iso:country":"ES",
    "sg:address":"Pg Estacio, 35",
    "sg:city":"Balaguer",
    "sg:orig_category":"Reposter\u00cdas",
    "sg:phone":"+34 973 44 70 19",
    "sg:postcode":"25600",
    "sg:province":"Lleida",
    "wof:name":"Industrias Alimenticiasde Balaguer S.l.",
    "wof:placetype":"venue"
},
  "geometry": {"coordinates":[0.810765028,41.7890052795],"type":"Point"}
}