{
  "type": "Feature",
  "properties": {
    "iso:country":"ES",
    "sg:address":"Av Corts Catalanes, 3",
    "sg:city":"S. Adria Besos",
    "sg:orig_category":"Poller\u00cda Y Caza (al Por Menor)",
    "sg:phone":"+34 933 81 25 98",
    "sg:postcode":"08930",
    "sg:province":"Barcelona",
    "wof:name":"Garcia Marques Mercedes",
    "wof:placetype":"venue"
},
  "geometry": {"coordinates":[2.2116599083,41.4223899841],"type":"Point"}
}