{
  "type": "Feature",
  "properties": {
    "addr:full":"Plaz Tamayo, 3 Moratalla Murcia 30440",
    "addr:housenumber":"3",
    "addr:postcode":"30440",
    "addr:street":"Tamayo",
    "iso:country":"ES",
    "sg:address":"Plaz Tamayo, 3",
    "sg:city":"Moratalla",
    "sg:orig_category":"Ense\u00d1anza: Profesiones Art\u00cdsticas",
    "sg:phone":"+34 968 72 40 28",
    "sg:postcode":"30440",
    "sg:province":"Murcia",
    "wof:name":"Iba\u00f1ez Martinez Dolores",
    "wof:placetype":"venue"
},
  "geometry": {"coordinates":[-1.8925449848,38.1884880066],"type":"Point"}
}