{
  "type": "Feature",
  "properties": {
    "addr:full":"Calle de Ardemans, 12 Madrid Madrid 28028",
    "addr:housenumber":"12",
    "addr:postcode":"madrid;28028",
    "addr:street":"Calle De Ardemans",
    "iso:country":"ES",
    "sg:address":"Calle de Ardemans, 12",
    "sg:city":"Madrid",
    "sg:orig_category":"Bancos",
    "sg:phone":"+34 917 24 26 50",
    "sg:postcode":"28028",
    "sg:province":"Madrid",
    "sg:website":"www.bancogui.com",
    "wof:name":"Banco Guipuzcoano S.a.",
    "wof:placetype":"venue"
},
  "geometry": {"coordinates":[-3.6712739468,40.4334640503],"type":"Point"}
}