{
  "type": "Feature",
  "properties": {
    "iso:country":"ES",
    "sg:address":"Calle de Nueva, 11",
    "sg:city":"Yepes",
    "sg:orig_category":"Promotores Constructores",
    "sg:phone":"+34 925 15 45 83",
    "sg:postcode":"45313",
    "sg:province":"Toledo",
    "wof:name":"Proyepes S.l",
    "wof:placetype":"venue"
},
  "geometry": {"coordinates":[-3.6287469864,39.9000473022],"type":"Point"}
}