{
  "type": "Feature",
  "properties": {
    "addr:full":"Carrer de Mossen Jacint Verdaguer, 165 S. Boi Llobregat Barcelona 08830",
    "addr:housenumber":"165",
    "addr:postcode":"08830",
    "addr:street":"Carrer De Mossen Jacint Verdaguer;S.",
    "iso:country":"ES",
    "sg:address":"Carrer de Mossen Jacint Verdaguer, 165",
    "sg:city":"S. Boi Llobregat",
    "sg:orig_category":"Muebles",
    "sg:phone":"+34 936 30 26 08",
    "sg:postcode":"08830",
    "sg:province":"Barcelona",
    "wof:name":"Brillma S.l.",
    "wof:placetype":"venue"
},
  "geometry": {"coordinates":[2.0439319611,41.338142395],"type":"Point"}
}