{
  "type": "Feature",
  "properties": {
    "iso:country":"ES",
    "sg:address":"Calle de Maudes, 15",
    "sg:city":"Madrid",
    "sg:orig_category":"Promotores Constructores",
    "sg:phone":"+34 915 54 79 15",
    "sg:postcode":"28003",
    "sg:province":"Madrid",
    "sg:website":"www.mundodependencia.com",
    "wof:name":"Castrillo Jv Asociados S.l.",
    "wof:placetype":"venue"
},
  "geometry": {"coordinates":[-3.702147007,40.4454956055],"type":"Point"}
}