{
  "type": "Feature",
  "properties": {
    "iso:country":"ES",
    "sg:address":"Rond Francesc Camprodon, 3",
    "sg:city":"Vic",
    "sg:orig_category":"Papeler\u00cdas, Librer\u00cdas",
    "sg:phone":"+34 938 89 23 45",
    "sg:postcode":"08500",
    "sg:province":"Barcelona",
    "wof:name":"Ronda S.c.p.",
    "wof:placetype":"venue"
},
  "geometry": {"coordinates":[2.2566919327,41.9342880249],"type":"Point"}
}