{
  "type": "Feature",
  "properties": {
    "iso:country":"ES",
    "sg:address":"Calle de Guadiana, S/n",
    "sg:city":"Bosque",
    "sg:classifiers":[
        {
            "category":"Sports & Exercise",
            "subcategory":"Golf",
            "type":"Entertainment"
        }
    ],
    "sg:phone":"+34 916 16 73 93",
    "sg:postcode":"28670",
    "sg:province":"Madrid",
    "sg:tags":[
        "y",
        "de",
        "campos",
        "clases"
    ],
    "wof:name":"Club De Golf Lomas-bosque S.a",
    "wof:placetype":"venue"
},
  "geometry": {"coordinates":[-3.9330289364,40.3831787109],"type":"Point"}
}