{
  "type": "Feature",
  "properties": {
    "iso:country":"ES",
    "sg:address":"Ctra Granada (de), 12",
    "sg:city":"Alhama Granada",
    "sg:orig_category":"Molduras, Junquillos, Listones Y Molduras Perforadas",
    "sg:phone":"+34 958 36 07 72",
    "sg:postcode":"18120",
    "sg:province":"Granada",
    "wof:name":"Raya Olmos Jose",
    "wof:placetype":"venue"
},
  "geometry": {"coordinates":[-3.9902770519,37.0042686462],"type":"Point"}
}