{
  "type": "Feature",
  "properties": {
    "iso:country":"ES",
    "sg:address":"Calle de Cervantes, 54",
    "sg:city":"Montoro",
    "sg:orig_category":"Agencias De Viajes",
    "sg:phone":"+34 957 16 00 47",
    "sg:postcode":"14600",
    "sg:province":"C\u00f3rdoba",
    "wof:name":"Formatur C.b.",
    "wof:placetype":"venue"
},
  "geometry": {"coordinates":[-4.3828010559,38.0175628662],"type":"Point"}
}