{
  "type": "Feature",
  "properties": {
    "addr:full":"Las Lomas, S/n Valdelafuente Le\u00f3n 24227",
    "addr:housenumber":"s",
    "addr:postcode":"24227",
    "addr:street":"Las Lomas;/ N Valdelafuente Leo\u0301N",
    "iso:country":"ES",
    "sg:address":"Las Lomas, S/n",
    "sg:city":"Valdelafuente",
    "sg:orig_category":"Carb\u00d3n, Carb\u00d3n De Madera (al Por Mayor)",
    "sg:phone":"+34 987 20 47 69",
    "sg:postcode":"24227",
    "sg:province":"Le\u00f3n",
    "wof:name":"Monta\u00f1es Fernandez Fernando Jose",
    "wof:placetype":"venue"
},
  "geometry": {"coordinates":[-5.5330891609,42.5957946777],"type":"Point"}
}