{
  "type": "Feature",
  "properties": {
    "iso:country":"ES",
    "sg:address":"Calle de Sorgintxulo, 9",
    "sg:city":"Errenteria",
    "sg:orig_category":"Estancos",
    "sg:phone":"+34 943 51 40 74",
    "sg:postcode":"20100",
    "sg:province":"Guip\u00f9zcoa",
    "wof:name":"Sanchez Malka Beatriz",
    "wof:placetype":"venue"
},
  "geometry": {"coordinates":[-1.9099400043,43.3165893555],"type":"Point"}
}