{
  "type": "Feature",
  "properties": {
    "iso:country":"ES",
    "sg:address":"Carrer de Albacete, 2",
    "sg:city":"Sant Vicen\u00c7 Dels Horts",
    "sg:orig_category":"Cl\u00cdnicas Psiqui\u00c1tricas",
    "sg:phone":"+34 936 56 80 02",
    "sg:postcode":"08620",
    "sg:province":"Barcelona",
    "wof:name":"Arpa Residencias S.l",
    "wof:placetype":"venue"
},
  "geometry": {"coordinates":[2.0003435612,41.3999214172],"type":"Point"}
}