{
  "type": "Feature",
  "properties": {
    "iso:country":"ES",
    "sg:address":"Calle de Principe, S/n",
    "sg:city":"Casas Benitez",
    "sg:orig_category":"Productores Recolectores, Venta Directa De Vinos",
    "sg:phone":"+34 969 38 20 92",
    "sg:postcode":"16707",
    "sg:province":"Cuenca",
    "wof:name":"Mostos Y Vinos Batanejo S.l.",
    "wof:placetype":"venue"
},
  "geometry": {"coordinates":[-2.1234560013,39.3626060486],"type":"Point"}
}