{
  "type": "Feature",
  "properties": {
    "iso:country":"ES",
    "sg:address":"Carr Pere Seras Isern, 1",
    "sg:city":"Figueres",
    "sg:orig_category":"Centros Empresariales",
    "sg:phone":"+34 972 50 08 15",
    "sg:postcode":"17600",
    "sg:province":"Girona",
    "wof:name":"Reguera Bigas Oscar",
    "wof:placetype":"venue"
},
  "geometry": {"coordinates":[2.9603409767,42.2701416016],"type":"Point"}
}