{
  "type": "Feature",
  "properties": {
    "addr:full":"Calle de Peso (el), 18 Lucena C\u00f3rdoba 14900",
    "addr:housenumber":"18",
    "addr:postcode":"14900",
    "addr:street":"Calle De Peso El",
    "iso:country":"ES",
    "sg:address":"Calle de Peso (el), 18",
    "sg:city":"Lucena",
    "sg:orig_category":"Pizzer\u00cdas",
    "sg:phone":"+34 957 50 04 25",
    "sg:postcode":"14900",
    "sg:province":"C\u00f3rdoba",
    "wof:name":"Rest Pizzeria Via Veneto C.b.",
    "wof:placetype":"venue"
},
  "geometry": {"coordinates":[-4.487238884,37.4089546204],"type":"Point"}
}