{
  "type": "Feature",
  "properties": {
    "iso:country":"ES",
    "sg:address":"Oeste, 6",
    "sg:city":"Benifaio",
    "sg:orig_category":"Muebles Y Accesorios Para Cocinas Y Cuartos De Ba\u00d1o (al Por Menor)",
    "sg:phone":"+34 961 79 50 90",
    "sg:postcode":"46450",
    "sg:province":"Valencia",
    "wof:name":"Mobiliario Rugim S.l.",
    "wof:placetype":"venue"
},
  "geometry": {"coordinates":[-0.4229789972,39.2867202759],"type":"Point"}
}