{
  "type": "Feature",
  "properties": {
    "iso:country":"ES",
    "sg:address":"Avda Castilla, 11",
    "sg:city":"Pedrafita Do Cebreiro",
    "sg:orig_category":"Confecci\u00d3n De Zapatos",
    "sg:phone":"+34 982 36 71 43",
    "sg:postcode":"27670",
    "sg:province":"Lugo",
    "wof:name":"Suarez Valcarcel Francisco",
    "wof:placetype":"venue"
},
  "geometry": {"coordinates":[-7.0194368362,42.7259979248],"type":"Point"}
}