{
  "type": "Feature",
  "properties": {
    "addr:full":"Ronda Del Canillo, S/n Montilla C\u00f3rdoba 14550",
    "addr:housenumber":"s / n",
    "addr:postcode":"14550",
    "addr:street":"Ronda Del Canillo;Co\u0301Rdoba",
    "iso:country":"ES",
    "sg:address":"Ronda Del Canillo, S/n",
    "sg:city":"Montilla",
    "sg:orig_category":"Electricidad Veh\u00cdculo",
    "sg:phone":"+34 957 65 21 21",
    "sg:postcode":"14550",
    "sg:province":"C\u00f3rdoba",
    "wof:name":"Villegas Torres Antonio",
    "wof:placetype":"venue"
},
  "geometry": {"coordinates":[-4.6404690742,37.5799942017],"type":"Point"}
}