{
  "type": "Feature",
  "properties": {
    "iso:country":"ES",
    "sg:address":"Avda Burgos, 28",
    "sg:city":"Briviesca",
    "sg:orig_category":"Venta, Instalaci\u00d3n De Calefacci\u00d3n",
    "sg:phone":"+34 947 59 07 01",
    "sg:postcode":"09240",
    "sg:province":"Burgos",
    "sg:website":"www.vbimagen.es/rayco/",
    "wof:name":"Industrias Rayco S. A.",
    "wof:placetype":"venue"
},
  "geometry": {"coordinates":[-3.3186230659,42.5593414307],"type":"Point"}
}