{
  "type": "Feature",
  "properties": {
    "iso:country":"ES",
    "sg:address":"Carrer de Sant Joan, 6",
    "sg:city":"S. Celoni",
    "sg:orig_category":"Restaurantes",
    "sg:phone":"+34 938 67 28 51",
    "sg:postcode":"08470",
    "sg:province":"Barcelona",
    "wof:name":"El Raco De Can Fabes S. L.",
    "wof:placetype":"venue"
},
  "geometry": {"coordinates":[2.4934999943,41.6903800964],"type":"Point"}
}