{
  "type": "Feature",
  "properties": {
    "addr:full":"Rua A Arxentina, 1 Ponteareas Pontevedra 36860",
    "addr:housenumber":"a;1",
    "addr:postcode":"36860",
    "addr:street":"Rua;Arxentina",
    "iso:country":"ES",
    "sg:address":"Rua A Arxentina, 1",
    "sg:city":"Ponteareas",
    "sg:orig_category":"Alimentaci\u00d3n General (al Por Menor)",
    "sg:phone":"+34 986 64 01 40",
    "sg:postcode":"36860",
    "sg:province":"Pontevedra",
    "wof:name":"Bargiela Ucha Maria Elena De Las Mercedes",
    "wof:placetype":"venue"
},
  "geometry": {"coordinates":[-8.5163888931,42.1783599854],"type":"Point"}
}