{
  "type": "Feature",
  "properties": {
    "iso:country":"ES",
    "sg:address":"C/ Pintor Vayreda, 18",
    "sg:city":"Cerdanyola Valles",
    "sg:orig_category":"Multimedia: Servicios En L\u00cdnea, Acceso En L\u00cdnea, Cd",
    "sg:phone":"+34 935 86 35 53",
    "sg:postcode":"08290",
    "sg:province":"Barcelona",
    "sg:website":"www.afondelvalles.com",
    "wof:name":"Ediciones Mancomunidad S.l",
    "wof:placetype":"venue"
},
  "geometry": {"coordinates":[2.1481130123,41.4902648926],"type":"Point"}
}