{
  "type": "Feature",
  "properties": {
    "iso:country":"ES",
    "sg:address":"Avgd Del Comte De Torrefiel, 2",
    "sg:city":"Ontinyent",
    "sg:orig_category":"Centros P\u00dablicos De Formaci\u00d3n Profesional Y T\u00c9cnica",
    "sg:phone":"+34 962 38 79 07",
    "sg:postcode":"46870",
    "sg:province":"Valencia",
    "wof:name":"Colegiode Abogados De Valencia",
    "wof:placetype":"venue"
},
  "geometry": {"coordinates":[-0.6100850105,38.8204040527],"type":"Point"}
}