{
  "type": "Feature",
  "properties": {
    "addr:full":"Carrer de Bobiles, 66 Hospitalet Llobregat Barcelona 08905",
    "addr:housenumber":"66",
    "addr:postcode":"08905",
    "addr:street":"Carrer De Bobiles",
    "iso:country":"ES",
    "sg:address":"Carrer de Bobiles, 66",
    "sg:city":"Hospitalet Llobregat",
    "sg:orig_category":"Cajas De Ahorro",
    "sg:phone":"+34 933 33 63 47",
    "sg:postcode":"08905",
    "sg:province":"Barcelona",
    "wof:name":"Caixa D'estalvis Del Penedes",
    "wof:placetype":"venue"
},
  "geometry": {"coordinates":[2.1114630699,41.3712768555],"type":"Point"}
}