{
  "type": "Feature",
  "properties": {
    "iso:country":"ES",
    "sg:address":"Almazaricas, S/n",
    "sg:city":"Tabernas",
    "sg:orig_category":"Electrodom\u00c9sticos (al Por Menor)",
    "sg:phone":"+34 950 36 50 54",
    "sg:postcode":"04200",
    "sg:province":"Almer\u00eda",
    "wof:name":"Alonso Ruiz Juan",
    "wof:placetype":"venue"
},
  "geometry": {"coordinates":[-2.3616201878,37.0809898376],"type":"Point"}
}