{
  "type": "Feature",
  "properties": {
    "iso:country":"ES",
    "sg:address":"Calle de Molinos De Viento, 1",
    "sg:city":"Manzanares",
    "sg:orig_category":"Sindicatos De Trabajadores",
    "sg:phone":"+34 926 61 46 66",
    "sg:postcode":"13200",
    "sg:province":"Ciudad Real",
    "wof:name":"Federacion De Servicios Publicos De Ugt",
    "wof:placetype":"venue"
},
  "geometry": {"coordinates":[-3.3669269085,38.9941596985],"type":"Point"}
}