{
  "type": "Feature",
  "properties": {
    "addr:full":"Calle de Real, 34 Valdepe\u00e7as De Jaen Ja\u00e9n 23150",
    "addr:housenumber":"34",
    "addr:postcode":"23150",
    "addr:street":"Calle De Real",
    "iso:country":"ES",
    "sg:address":"Calle de Real, 34",
    "sg:city":"Valdepe\u00e7as De Jaen",
    "sg:orig_category":"Farmacias",
    "sg:phone":"+34 953 31 00 12",
    "sg:postcode":"23150",
    "sg:province":"Ja\u00e9n",
    "wof:name":"Martinez Luna Jose Maria",
    "wof:placetype":"venue"
},
  "geometry": {"coordinates":[-3.8176519871,37.5908584595],"type":"Point"}
}