{
  "type": "Feature",
  "properties": {
    "addr:full":"Pg Doctor Moragas, 251 Barbera Valles Barcelona 08210",
    "addr:housenumber":"251",
    "addr:postcode":"08210",
    "addr:street":"Pg Doctor Moragas",
    "iso:country":"ES",
    "sg:address":"Pg Doctor Moragas, 251",
    "sg:city":"Barbera Valles",
    "sg:classifiers":[
        {
            "category":"Utilities",
            "subcategory":"Natural Gas",
            "type":"Services"
        }
    ],
    "sg:phone":"+34 937 19 37 90",
    "sg:postcode":"08210",
    "sg:province":"Barcelona",
    "wof:name":"Lonix Invest S.l.",
    "wof:placetype":"venue"
},
  "geometry": {"coordinates":[2.1271760464,41.5150566101],"type":"Point"}
}