{
  "type": "Feature",
  "properties": {
    "iso:country":"ES",
    "sg:address":"Av Flora Cadena, Km. 0049,0",
    "sg:city":"Rialp",
    "sg:orig_category":"Piedra Natural",
    "sg:phone":"+34 973 62 04 09",
    "sg:postcode":"25594",
    "sg:province":"Lleida",
    "wof:name":"Pedra Del Pallars S.l",
    "wof:placetype":"venue"
},
  "geometry": {"coordinates":[1.1353470087,42.4446487427],"type":"Point"}
}