{
  "type": "Feature",
  "properties": {
    "iso:country":"ES",
    "sg:address":"Calle de Juan Rejon, 105",
    "sg:city":"Palmas De Gran Canaria",
    "sg:orig_category":"Papeler\u00cdas, Librer\u00cdas",
    "sg:phone":"+34 928 46 61 25",
    "sg:postcode":"35008",
    "sg:province":"Las Palmas",
    "wof:name":"San Gines Araujo Jose Carlos",
    "wof:placetype":"venue"
},
  "geometry": {"coordinates":[-15.423365593,28.1497516632],"type":"Point"}
}