{
  "type": "Feature",
  "properties": {
    "addr:full":"Rivera, 10 Algaba Sevilla 41980",
    "addr:housenumber":"10",
    "addr:postcode":"41980",
    "addr:street":"Rivera",
    "iso:country":"ES",
    "sg:address":"Rivera, 10",
    "sg:city":"Algaba",
    "sg:orig_category":"Frutas, Legumbres Frescas Y Tempranas (al Por Menor)",
    "sg:phone":"+34 954 11 81 57",
    "sg:postcode":"41980",
    "sg:province":"Sevilla",
    "wof:name":"Luna Herrera Miguel",
    "wof:placetype":"venue"
},
  "geometry": {"coordinates":[-6.0096278191,37.4678115845],"type":"Point"}
}