{
  "type": "Feature",
  "properties": {
    "addr:full":"Calle de Canuto Hevia, 26 Pola De Lena Asturias 33630",
    "addr:housenumber":"26",
    "addr:postcode":"33630",
    "addr:street":"Calle De Canuto Hevia",
    "iso:country":"ES",
    "sg:address":"Calle de Canuto Hevia, 26",
    "sg:city":"Pola De Lena",
    "sg:orig_category":"Asesor\u00cda Fiscal Y Jur\u00cddica",
    "sg:phone":"+34 985 49 11 90",
    "sg:postcode":"33630",
    "sg:province":"Asturias",
    "wof:name":"Gonzalez Escalada Arturo",
    "wof:placetype":"venue"
},
  "geometry": {"coordinates":[-5.8303666115,43.1563415527],"type":"Point"}
}