{
  "type": "Feature",
  "properties": {
    "iso:country":"ES",
    "sg:address":"Plaz Placido Fernandez Viagas, 4",
    "sg:city":"Jerez De La Frontera",
    "sg:orig_category":"Papeler\u00cdas, Librer\u00cdas",
    "sg:phone":"+34 956 14 03 10",
    "sg:postcode":"11408",
    "sg:province":"C\u00e1diz",
    "wof:name":"Pedrosa Zambrano Maria Angeles",
    "wof:placetype":"venue"
},
  "geometry": {"coordinates":[-6.1281089783,36.6701622009],"type":"Point"}
}