{
  "type": "Feature",
  "properties": {
    "iso:country":"ES",
    "sg:address":"Calle de Alpes (los), 6",
    "sg:city":"Alcorcon",
    "sg:classifiers":[
        {
            "category":"Autos & Motor Vehicles",
            "subcategory":"Automobile Sales",
            "type":"Retail Goods"
        }
    ],
    "sg:phone":"+34 916 44 03 50",
    "sg:postcode":"28922",
    "sg:province":"Madrid",
    "wof:name":"Garcia Jimenez Evaristo",
    "wof:placetype":"venue"
},
  "geometry": {"coordinates":[-3.8343882561,40.3465118408],"type":"Point"}
}