{
  "type": "Feature",
  "properties": {
    "iso:country":"ES",
    "sg:address":"Plaz Calvo Sotelo, 7",
    "sg:city":"Paredes Nava",
    "sg:orig_category":"Carnicer\u00cdas, Carnicer\u00cdas",
    "sg:phone":"+34 979 83 01 83",
    "sg:postcode":"34300",
    "sg:province":"Palencia",
    "wof:name":"Infante Gonzalez Juan",
    "wof:placetype":"venue"
},
  "geometry": {"coordinates":[-4.6880588531,42.1550292969],"type":"Point"}
}