{
  "type": "Feature",
  "properties": {
    "addr:full":"Avda. Finisterre, 273 A Coru\u00f1a La Coru\u00f1a 15008",
    "addr:housenumber":"273 a",
    "addr:postcode":"15008",
    "addr:street":"Avda. Finisterre;Corun\u0303A La Corun\u0303A",
    "iso:country":"ES",
    "sg:address":"Avda. Finisterre, 273",
    "sg:city":"A Coru\u00f1a",
    "sg:orig_category":"Muebles, Minoristas",
    "sg:phone":"+34 981 27 77 92",
    "sg:postcode":"15008",
    "sg:province":"La Coru\u00f1a",
    "wof:name":"Muebles Juvenil S.a.",
    "wof:placetype":"venue"
},
  "geometry": {"coordinates":[-8.4246196747,43.3567047119],"type":"Point"}
}