{
  "type": "Feature",
  "properties": {
    "addr:full":"Avda Tudela, 3 Ablitas Navarra 31523",
    "addr:housenumber":"3",
    "addr:postcode":"31523",
    "addr:street":"Avda Tudela",
    "iso:country":"ES",
    "sg:address":"Avda Tudela, 3",
    "sg:city":"Ablitas",
    "sg:orig_category":"Molduras, Junquillos, Listones Y Molduras Perforadas",
    "sg:phone":"+34 948 81 35 99",
    "sg:postcode":"31523",
    "sg:province":"Navarra",
    "wof:name":"Andres Santos Domingo",
    "wof:placetype":"venue"
},
  "geometry": {"coordinates":[-1.6398428679,41.9737434387],"type":"Point"}
}