{
  "type": "Feature",
  "properties": {
    "iso:country":"ES",
    "sg:address":"Avda Constitucion, 182",
    "sg:city":"Cistierna",
    "sg:orig_category":"Empresas De Carpinter\u00cda",
    "sg:phone":"+34 987 70 20 43",
    "sg:postcode":"24800",
    "sg:province":"Le\u00f3n",
    "wof:name":"Diez Fernandez Oscar",
    "wof:placetype":"venue"
},
  "geometry": {"coordinates":[-5.1291089058,42.8054008484],"type":"Point"}
}