{
  "type": "Feature",
  "properties": {
    "iso:country":"ES",
    "sg:address":"Urb Angustias (las), S/n",
    "sg:city":"Alcala Guadaira",
    "sg:orig_category":"Carnicer\u00cdas, Carnicer\u00cdas",
    "sg:phone":"+34 955 61 51 44",
    "sg:postcode":"41500",
    "sg:province":"Sevilla",
    "wof:name":"Sevillano Vera Manuel",
    "wof:placetype":"venue"
},
  "geometry": {"coordinates":[-5.8398590088,37.3383140564],"type":"Point"}
}