{
  "type": "Feature",
  "properties": {
    "iso:country":"ES",
    "sg:address":"Carrer de Vidrieria, 15",
    "sg:city":"Barcelona",
    "sg:orig_category":"Caf\u00c9s, Bares, Cervecer\u00cdas",
    "sg:phone":"+34 933 19 11 37",
    "sg:postcode":"08003",
    "sg:province":"Barcelona",
    "wof:name":"Diaz Aragones Alejandro",
    "wof:placetype":"venue"
},
  "geometry": {"coordinates":[2.1832239628,41.3840255737],"type":"Point"}
}