{
  "type": "Feature",
  "properties": {
    "iso:country":"ES",
    "sg:address":"Calle de Illescas, 32",
    "sg:city":"Madrid",
    "sg:orig_category":"Inform\u00c1tica: Soportes De Informaci\u00d3n, Suministros & Accesorios",
    "sg:phone":"+34 915 09 90 39",
    "sg:postcode":"28024",
    "sg:province":"Madrid",
    "wof:name":"Beep Aluche S.l",
    "wof:placetype":"venue"
},
  "geometry": {"coordinates":[-3.763628006,40.3962936401],"type":"Point"}
}