{
  "type": "Feature",
  "properties": {
    "addr:full":"Avda Gregorio Prieto, 7 Malaga M\u00e1laga 29010",
    "addr:housenumber":"7",
    "addr:postcode":"29010",
    "addr:street":"Avda Gregorio Prieto;Ma\u0301Laga",
    "iso:country":"ES",
    "sg:address":"Avda Gregorio Prieto, 7",
    "sg:city":"Malaga",
    "sg:orig_category":"Farmacias",
    "sg:phone":"+34 952 06 81 26",
    "sg:postcode":"29010",
    "sg:province":"M\u00e1laga",
    "wof:name":"Romero Rubio Fernando",
    "wof:placetype":"venue"
},
  "geometry": {"coordinates":[-4.4635019302,36.7171897888],"type":"Point"}
}