{
  "type": "Feature",
  "properties": {
    "addr:full":"Calle de Gobernador, 29 Castellon Castell\u00f3n 12003",
    "addr:housenumber":"29",
    "addr:postcode":"12003",
    "addr:street":"Calle De Gobernador",
    "iso:country":"ES",
    "sg:address":"Calle de Gobernador, 29",
    "sg:city":"Castellon",
    "sg:orig_category":"Inmobiliaria (agencias)",
    "sg:phone":"+34 964 22 01 10",
    "sg:postcode":"12003",
    "sg:province":"Castell\u00f3n",
    "sg:website":"www.navicasa.com",
    "wof:name":"Navica S.a.",
    "wof:placetype":"venue"
},
  "geometry": {"coordinates":[-0.0077,39.9838409424],"type":"Point"}
}