{
  "type": "Feature",
  "properties": {
    "addr:full":"Carrer de Segle Xx, 62 Barcelona Barcelona 08032",
    "addr:housenumber":"62",
    "addr:postcode":"08032",
    "addr:street":"Carrer De Segle Xx",
    "iso:country":"ES",
    "sg:address":"Carrer de Segle Xx, 62",
    "sg:city":"Barcelona",
    "sg:orig_category":"Transportes Por V\u00cdas Navegables",
    "sg:phone":"+34 934 35 71 27",
    "sg:postcode":"08032",
    "sg:province":"Barcelona",
    "wof:name":"Logistica Bellido S.l.",
    "wof:placetype":"venue"
},
  "geometry": {"coordinates":[2.174323082,41.4242172241],"type":"Point"}
}