{
  "type": "Feature",
  "properties": {
    "addr:full":"Calle de Cendeja, 31 San Juan De Muskiz Vizcaya 48550",
    "addr:housenumber":"31",
    "addr:postcode":"48550",
    "addr:street":"Calle De Cendeja",
    "iso:country":"ES",
    "sg:address":"Calle de Cendeja, 31",
    "sg:city":"San Juan De Muskiz",
    "sg:orig_category":"T\u00c9cnicos Veterinarios",
    "sg:phone":"+34 946 70 70 15",
    "sg:postcode":"48550",
    "sg:province":"Vizcaya",
    "wof:name":"Lopez Tudanca Jorge",
    "wof:placetype":"venue"
},
  "geometry": {"coordinates":[-3.1174213886,43.3218345642],"type":"Point"}
}