{
  "type": "Feature",
  "properties": {
    "iso:country":"ES",
    "sg:address":"Calle de Torres Miranda, 4",
    "sg:city":"Madrid",
    "sg:orig_category":"Carnicer\u00cdas, Carnicer\u00cdas",
    "sg:phone":"+34 914 74 70 82",
    "sg:postcode":"28045",
    "sg:province":"Madrid",
    "wof:name":"Paredero Debora Jose Maria",
    "wof:placetype":"venue"
},
  "geometry": {"coordinates":[-3.6984579563,40.3981437683],"type":"Point"}
}