{
  "type": "Feature",
  "properties": {
    "iso:country":"ES",
    "sg:address":"Barr Altamira, 36",
    "sg:city":"Bilbao",
    "sg:orig_category":"Contenedores (mercanc\u00cdas)",
    "sg:phone":"+34 944 27 56 02",
    "sg:postcode":"48002",
    "sg:province":"Vizcaya",
    "wof:name":"Rodriguez Fernandez Aurora",
    "wof:placetype":"venue"
},
  "geometry": {"coordinates":[-2.9626610279,43.2617111206],"type":"Point"}
}