{
  "type": "Feature",
  "properties": {
    "iso:country":"ES",
    "sg:address":"Calle de Periferica, 84",
    "sg:city":"Navas Del Marques",
    "sg:orig_category":"Fabricaci\u00d3n De Muebles",
    "sg:phone":"+34 918 97 01 63",
    "sg:postcode":"05230",
    "sg:province":"\u00c1vila",
    "wof:name":"Angel Sastre Dozarat S.l.",
    "wof:placetype":"venue"
},
  "geometry": {"coordinates":[-4.3314809799,40.5971183777],"type":"Point"}
}