{
  "type": "Feature",
  "properties": {
    "addr:full":"Carr Sagunt, 30 Palafrugell Girona 17200",
    "addr:housenumber":"30",
    "addr:postcode":"17200",
    "addr:street":"Carr Sagunt",
    "iso:country":"ES",
    "sg:address":"Carr Sagunt, 30",
    "sg:city":"Palafrugell",
    "sg:orig_category":"Farmacias",
    "sg:phone":"+34 972 30 00 00",
    "sg:postcode":"17200",
    "sg:province":"Girona",
    "wof:name":"Medir Huerta Luis",
    "wof:placetype":"venue"
},
  "geometry": {"coordinates":[3.1697480679,41.9159851074],"type":"Point"}
}