{
  "type": "Feature",
  "properties": {
    "addr:full":"Calle de Chile, 18 Alcala Henares Madrid 28806",
    "addr:housenumber":"18",
    "addr:postcode":"28806",
    "addr:street":"Calle De Chile",
    "iso:country":"ES",
    "sg:address":"Calle de Chile, 18",
    "sg:city":"Alcala Henares",
    "sg:orig_category":"Metales (labores, Pulido)",
    "sg:phone":"+34 918 80 33 11",
    "sg:postcode":"28806",
    "sg:province":"Madrid",
    "wof:name":"Hierros Y Aceros De Santander S.a.",
    "wof:placetype":"venue"
},
  "geometry": {"coordinates":[-3.3976330757,40.5041122437],"type":"Point"}
}