{
  "type": "Feature",
  "properties": {
    "iso:country":"ES",
    "sg:address":"Avda Valladolid, 43",
    "sg:city":"Tudela Duero",
    "sg:orig_category":"Complementos De Vestir (al Por Menor)",
    "sg:phone":"+34 983 52 10 18",
    "sg:postcode":"47320",
    "sg:province":"Valladolid",
    "wof:name":"Juste Blanco Laura",
    "wof:placetype":"venue"
},
  "geometry": {"coordinates":[-4.454182148,41.507068634],"type":"Point"}
}