{
  "type": "Feature",
  "properties": {
    "addr:full":"Nucleo Residencial La Paz, S/n Linares Ja\u00e9n 23700",
    "addr:housenumber":"s / n",
    "addr:postcode":"23700",
    "addr:street":"Nucleo Residencial La Paz;Jae\u0301N",
    "iso:country":"ES",
    "sg:address":"Nucleo Residencial La Paz, S/n",
    "sg:city":"Linares",
    "sg:orig_category":"Supermercados Y Hipermercados",
    "sg:phone":"+34 953 69 54 62",
    "sg:postcode":"23700",
    "sg:province":"Ja\u00e9n",
    "wof:name":"Perez Garcia Victoriano",
    "wof:placetype":"venue"
},
  "geometry": {"coordinates":[-3.6356039047,38.093914032],"type":"Point"}
}