{
  "type": "Feature",
  "properties": {
    "addr:full":"Calle de Don Pedro, 2 Villarrobledo Albacete 02600",
    "addr:housenumber":"2",
    "addr:postcode":"02600",
    "addr:street":"Calle De Don Pedro",
    "iso:country":"ES",
    "sg:address":"Calle de Don Pedro, 2",
    "sg:city":"Villarrobledo",
    "sg:orig_category":"Carnicer\u00cdas, Carnicer\u00cdas",
    "sg:phone":"+34 967 14 35 23",
    "sg:postcode":"02600",
    "sg:province":"Albacete",
    "wof:name":"Clemente Collado Juan Alfonso",
    "wof:placetype":"venue"
},
  "geometry": {"coordinates":[-2.6040225029,39.2672348022],"type":"Point"}
}