{
  "type": "Feature",
  "properties": {
    "iso:country":"ES",
    "sg:address":"Calle de Juan Xxiii, 30",
    "sg:city":"Arganda",
    "sg:orig_category":"Empresarios",
    "sg:phone":"+34 918 71 21 05",
    "sg:postcode":"28500",
    "sg:province":"Madrid",
    "wof:name":"Fernandez Duran Jose",
    "wof:placetype":"venue"
},
  "geometry": {"coordinates":[-3.4387309551,40.2986412048],"type":"Point"}
}