{
  "type": "Feature",
  "properties": {
    "iso:country":"ES",
    "sg:address":"Calle de Jose Isbert, 17",
    "sg:city":"Albacete",
    "sg:orig_category":"Administradores De Bienes Y Delegados De Comunidades De Propietarios",
    "sg:phone":"+34 967 21 34 35",
    "sg:postcode":"02001",
    "sg:province":"Albacete",
    "wof:name":"Afinur Administracion De Fincas S.l.",
    "wof:placetype":"venue"
},
  "geometry": {"coordinates":[-1.8467626572,38.9963111877],"type":"Point"}
}