{
  "type": "Feature",
  "properties": {
    "addr:full":"Calle de Dos De Mayo, 15 Calahorra La Rioja 26500",
    "addr:housenumber":"15",
    "addr:postcode":"26500",
    "addr:street":"Calle De Dos;Mayo",
    "iso:country":"ES",
    "sg:address":"Calle de Dos De Mayo, 15",
    "sg:city":"Calahorra",
    "sg:orig_category":"Asistencia Social",
    "sg:phone":"+34 941 14 58 73",
    "sg:postcode":"26500",
    "sg:province":"La Rioja",
    "wof:name":"Servicio De Atencion A Mayores En La Rioja S.l.",
    "wof:placetype":"venue"
},
  "geometry": {"coordinates":[-1.9620640278,42.3058395386],"type":"Point"}
}