{
  "type": "Feature",
  "properties": {
    "addr:full":"Calle de Rollo, 34 Torre Don Miguel C\u00e1ceres 10864",
    "addr:housenumber":"34",
    "addr:postcode":"10864",
    "addr:street":"Calle De Rollo;Don;Ca\u0301Ceres",
    "iso:country":"ES",
    "sg:address":"Calle de Rollo, 34",
    "sg:city":"Torre Don Miguel",
    "sg:orig_category":"Semiller\u00cdas",
    "sg:phone":"+34 927 44 14 97",
    "sg:postcode":"10864",
    "sg:province":"C\u00e1ceres",
    "wof:name":"Prieto Otero Luis",
    "wof:placetype":"venue"
},
  "geometry": {"coordinates":[-6.3720030785,39.4745063782],"type":"Point"}
}