{
  "type": "Feature",
  "properties": {
    "addr:full":"Avda Espa\u00d1a, 1 Corrales Cantabria 39400",
    "addr:housenumber":"1",
    "addr:postcode":"39400",
    "addr:street":"Avda Espan\u0303A",
    "iso:country":"ES",
    "sg:address":"Avda Espa\u00d1a, 1",
    "sg:city":"Corrales",
    "sg:orig_category":"Ropa Para Se\u00d1oras Y Caballeros (al Por Menor)",
    "sg:phone":"+34 942 83 42 81",
    "sg:postcode":"39400",
    "sg:province":"Cantabria",
    "wof:name":"Myscom-mysnet S.l.",
    "wof:placetype":"venue"
},
  "geometry": {"coordinates":[-4.0688462257,43.2586631775],"type":"Point"}
}