{
  "type": "Feature",
  "properties": {
    "addr:full":"Cra. Nal. Dos-cents Quaranta, S/n Montblanc Tarragona 43400",
    "addr:housenumber":"s / n",
    "addr:postcode":"43400",
    "iso:country":"ES",
    "sg:address":"Cra. Nal. Dos-cents Quaranta, S/n",
    "sg:city":"Montblanc",
    "sg:orig_category":"Paletas",
    "sg:phone":"+34 977 86 13 84",
    "sg:postcode":"43400",
    "sg:province":"Tarragona",
    "wof:name":"Palets Montblanc,s.l.",
    "wof:placetype":"venue"
},
  "geometry": {"coordinates":[1.1643300056,41.3753395081],"type":"Point"}
}