{
  "type": "Feature",
  "properties": {
    "addr:full":"Calle de Martinez De Medina, 3 Sevilla Sevilla 41018",
    "addr:housenumber":"3",
    "addr:postcode":"41018",
    "addr:street":"Calle De Martinez De Medina",
    "iso:country":"ES",
    "sg:address":"Calle de Martinez De Medina, 3",
    "sg:city":"Sevilla",
    "sg:orig_category":"Cl\u00cdnicas M\u00c9dicas",
    "sg:phone":"+34 954 53 02 34",
    "sg:postcode":"41018",
    "sg:province":"Sevilla",
    "wof:name":"Ruiz De Gopegui Fernandez Jose Luis",
    "wof:placetype":"venue"
},
  "geometry": {"coordinates":[-5.972946167,37.3851585388],"type":"Point"}
}