{
  "type": "Feature",
  "properties": {
    "iso:country":"ES",
    "sg:address":"Po. Del Mar, 46",
    "sg:city":"Palmanova",
    "sg:orig_category":"Bancos",
    "sg:phone":"+34 971 68 10 70",
    "sg:postcode":"07181",
    "sg:province":"Islas Baleares",
    "wof:name":"Banco De Credito Balear",
    "wof:placetype":"venue"
},
  "geometry": {"coordinates":[2.5361430645,39.5199127197],"type":"Point"}
}