{
  "type": "Feature",
  "properties": {
    "iso:country":"ES",
    "sg:address":"Plaz Concepcion, 1",
    "sg:city":"Montellano",
    "sg:orig_category":"Organismos De Reclutamiento",
    "sg:phone":"+34 955 83 14 86",
    "sg:postcode":"41770",
    "sg:province":"Sevilla",
    "wof:name":"Preving Consulting Sur S.l.",
    "wof:placetype":"venue"
},
  "geometry": {"coordinates":[-5.5709638596,36.9954147339],"type":"Point"}
}