{
  "type": "Feature",
  "properties": {
    "iso:country":"ES",
    "sg:address":"Plaz San Pablo, 5",
    "sg:city":"Palencia",
    "sg:orig_category":"Bazares, Art\u00cdculos De Limpieza Y De Cocina (al Por Menor)",
    "sg:phone":"+34 979 74 79 66",
    "sg:postcode":"34005",
    "sg:province":"Palencia",
    "wof:name":"Gadget Shop S.l.",
    "wof:placetype":"venue"
},
  "geometry": {"coordinates":[-4.5362024307,42.0140113831],"type":"Point"}
}