{
  "type": "Feature",
  "properties": {
    "iso:country":"ES",
    "sg:address":"Cami Sant Jordi, 2",
    "sg:city":"Portol",
    "sg:orig_category":"Electricidad: Instaladores",
    "sg:phone":"+34 971 60 24 91",
    "sg:postcode":"07141",
    "sg:province":"Islas Baleares",
    "wof:name":"Martin Serra Vich S C P",
    "wof:placetype":"venue"
},
  "geometry": {"coordinates":[2.7445349693,39.6195487976],"type":"Point"}
}