{
  "type": "Feature",
  "properties": {
    "addr:full":"Calle de Luis De Sotomayor, 3 Melilla Melilla 52004",
    "addr:housenumber":"3",
    "addr:postcode":"52004",
    "addr:street":"Calle De Luis De Sotomayor",
    "iso:country":"ES",
    "sg:address":"Calle de Luis De Sotomayor, 3",
    "sg:city":"Melilla",
    "sg:orig_category":"Abogados",
    "sg:phone":"+34 952 68 30 04",
    "sg:postcode":"52004",
    "sg:province":"Melilla",
    "wof:name":"Aragon Mendoza Jose Luis",
    "wof:placetype":"venue"
},
  "geometry": {"coordinates":[-2.9426689148,35.2919235229],"type":"Point"}
}