{
  "type": "Feature",
  "properties": {
    "addr:full":"Calle de Ramon Y Cajal, 34 Coru\u00d1a La Coru\u00f1a 15006",
    "addr:housenumber":"34",
    "addr:postcode":"15006",
    "addr:street":"Calle De Ramon Y Cajal;Corun\u0303A",
    "iso:country":"ES",
    "sg:address":"Calle de Ramon Y Cajal, 34",
    "sg:city":"Coru\u00d1a",
    "sg:orig_category":"Bancos",
    "sg:phone":"+34 981 13 26 02",
    "sg:postcode":"15006",
    "sg:province":"La Coru\u00f1a",
    "wof:name":"Banc Sabadell S.a.",
    "wof:placetype":"venue"
},
  "geometry": {"coordinates":[-8.4032535553,43.3549842834],"type":"Point"}
}