{
  "type": "Feature",
  "properties": {
    "addr:full":"Karmelo Labaka Kalea, 14 Hernani Guip\u00f9zcoa 20120",
    "addr:housenumber":"14",
    "addr:postcode":"20120",
    "addr:street":"Karmelo Labaka Kalea;Guipu\u0300Zcoa",
    "iso:country":"ES",
    "sg:address":"Karmelo Labaka Kalea, 14",
    "sg:city":"Hernani",
    "sg:orig_category":"Mec\u00c1nico Del Autom\u00d3vil",
    "sg:phone":"+34 943 55 46 92",
    "sg:postcode":"20120",
    "sg:province":"Guip\u00f9zcoa",
    "wof:name":"Gutierrez Gutierrez Unai",
    "wof:placetype":"venue"
},
  "geometry": {"coordinates":[-1.9741330147,43.2697067261],"type":"Point"}
}