{
  "type": "Feature",
  "properties": {
    "iso:country":"ES",
    "sg:address":"Avda Ramon Y Cajal, 109",
    "sg:city":"Madrid",
    "sg:orig_category":"Carnicer\u00cdas, Carnicer\u00cdas",
    "sg:phone":"+34 914 15 10 43",
    "sg:postcode":"28043",
    "sg:province":"Madrid",
    "wof:name":"Carnicas Santiago S.l.",
    "wof:placetype":"venue"
},
  "geometry": {"coordinates":[-3.6642858982,40.4529647827],"type":"Point"}
}