{
  "type": "Feature",
  "properties": {
    "addr:full":"Carrer de Josep Irla I Bosch, 5 Barcelona Barcelona 08034",
    "addr:housenumber":"5",
    "addr:postcode":"08034",
    "addr:street":"Carrer De Josep Irla I Bosch",
    "iso:country":"ES",
    "sg:address":"Carrer de Josep Irla I Bosch, 5",
    "sg:city":"Barcelona",
    "sg:orig_category":"Inform\u00c1tica (estudios, Servicios, Asesor\u00cda, Formaci\u00d3n)",
    "sg:phone":"+34 932 05 27 27",
    "sg:postcode":"08034",
    "sg:province":"Barcelona",
    "wof:name":"Gestio Organitzacio Comunicacio S.a.",
    "wof:placetype":"venue"
},
  "geometry": {"coordinates":[2.1300799847,41.3910484314],"type":"Point"}
}