{
  "type": "Feature",
  "properties": {
    "iso:country":"ES",
    "sg:address":"Calle de San Juan De Dios, 1",
    "sg:city":"Vitigudino",
    "sg:orig_category":"Negocio De Materiales De Construcci\u00d3n",
    "sg:phone":"+34 923 50 00 49",
    "sg:postcode":"37210",
    "sg:province":"Salamanca",
    "wof:name":"Riosmat S.l.",
    "wof:placetype":"venue"
},
  "geometry": {"coordinates":[-6.4357447624,41.0087013245],"type":"Point"}
}