{
  "type": "Feature",
  "properties": {
    "iso:country":"ES",
    "sg:address":"Carr Sant Joan De Mata, 10",
    "sg:city":"Lleida",
    "sg:orig_category":"Trabajos De Fotocomposici\u00d3n",
    "sg:phone":"+34 973 20 55 81",
    "sg:postcode":"25001",
    "sg:province":"Lleida",
    "wof:name":"Grafic Nou Lleida S.l.",
    "wof:placetype":"venue"
},
  "geometry": {"coordinates":[0.6292840242,41.6107902527],"type":"Point"}
}