{
  "type": "Feature",
  "properties": {
    "iso:country":"ES",
    "sg:address":"Calle de Leon Y Castillo, 85",
    "sg:city":"Pto. Rosario",
    "sg:orig_category":"Higiene, Belleza: Art\u00cdculos (al Por Menor)",
    "sg:phone":"+34 928 85 91 17",
    "sg:postcode":"35600",
    "sg:province":"Las Palmas",
    "sg:website":"www.nectarcosmetics.com",
    "wof:name":"Bullon Abon Consuelo",
    "wof:placetype":"venue"
},
  "geometry": {"coordinates":[-13.8685083389,28.5013332367],"type":"Point"}
}