{
  "type": "Feature",
  "properties": {
    "iso:country":"ES",
    "sg:address":"Calle de Carnero, 19",
    "sg:city":"Madrid",
    "sg:orig_category":"Comisarios",
    "sg:phone":"+34 913 65 24 53",
    "sg:postcode":"28005",
    "sg:province":"Madrid",
    "wof:name":"Romo Aguado Mariano",
    "wof:placetype":"venue"
},
  "geometry": {"coordinates":[-3.7095394135,40.4081687927],"type":"Point"}
}