{
  "type": "Feature",
  "properties": {
    "iso:country":"ES",
    "sg:address":"C/ Areny, S/n",
    "sg:city":"Celra",
    "sg:orig_category":"Piscinas, Accesorios, Suministros (fabricaci\u00d3n, Al Por Mayor)",
    "sg:phone":"+34 972 49 42 08",
    "sg:postcode":"17460",
    "sg:province":"Girona",
    "wof:name":"Astral Pool Espa\u00d1a S.a.u.",
    "wof:placetype":"venue"
},
  "geometry": {"coordinates":[2.8783788681,42.0325279236],"type":"Point"}
}