{
  "type": "Feature",
  "properties": {
    "addr:full":"Av Montserrat, 2 Cellera Ter Girona 17165",
    "addr:housenumber":"2",
    "addr:postcode":"17165",
    "addr:street":"Av Montserrat;Cellera Ter",
    "iso:country":"ES",
    "sg:address":"Av Montserrat, 2",
    "sg:city":"Cellera Ter",
    "sg:orig_category":"Muebles Y Accesorios Para Cocinas Y Cuartos De Ba\u00d1o (al Por Menor)",
    "sg:phone":"+34 972 42 37 59",
    "sg:postcode":"17165",
    "sg:province":"Girona",
    "wof:name":"Rodriguez Nu\u00f1ez Maria Isabel",
    "wof:placetype":"venue"
},
  "geometry": {"coordinates":[2.6211791039,41.9696998596],"type":"Point"}
}