{
  "type": "Feature",
  "properties": {
    "addr:full":"Av Progreso(b Progreso), 2 Murcia Murcia 30012",
    "addr:housenumber":"2",
    "addr:postcode":"30012",
    "addr:street":"Av Progreso B Progreso",
    "iso:country":"ES",
    "sg:address":"Av Progreso(b Progreso), 2",
    "sg:city":"Murcia",
    "sg:orig_category":"Electrodom\u00c9sticos (al Por Menor)",
    "sg:phone":"+34 968 25 06 50",
    "sg:postcode":"30012",
    "sg:province":"Murcia",
    "wof:name":"Electroprogreso S.l.",
    "wof:placetype":"venue"
},
  "geometry": {"coordinates":[-1.1214929819,37.9685630798],"type":"Point"}
}