{
  "type": "Feature",
  "properties": {
    "iso:country":"ES",
    "sg:address":"Calle de Profesor Macedonio Jimenez, 22",
    "sg:city":"Albacete",
    "sg:orig_category":"Servicio De Salud",
    "sg:phone":"+34 967 55 00 31",
    "sg:postcode":"02006",
    "sg:province":"Albacete",
    "sg:website":"www.saloni.com",
    "wof:name":"Baycoba S.l.",
    "wof:placetype":"venue"
},
  "geometry": {"coordinates":[-1.8664009571,38.9859390259],"type":"Point"}
}