{
  "type": "Feature",
  "properties": {
    "iso:country":"ES",
    "sg:address":"Avda Independencia, 2",
    "sg:city":"Le\u00f3n",
    "sg:orig_category":"Sociedades Y Organismos Burs\u00c1tiles",
    "sg:phone":"+34 987 20 93 00",
    "sg:postcode":"24001",
    "sg:province":"Le\u00f3n",
    "wof:name":"Renta 4 Sociedad De Valores De Bolsa",
    "wof:placetype":"venue"
},
  "geometry": {"coordinates":[-5.5722618103,42.5975227356],"type":"Point"}
}