{
  "type": "Feature",
  "properties": {
    "addr:full":"Calle de Secundino Alonso, 38 Pto. Rosario Las Palmas 35600",
    "addr:housenumber":"38",
    "addr:postcode":"35600",
    "addr:street":"Calle De Secundino Alonso;Pto. Rosario Las",
    "iso:country":"ES",
    "sg:address":"Calle de Secundino Alonso, 38",
    "sg:city":"Pto. Rosario",
    "sg:orig_category":"Inmobiliaria (agencias)",
    "sg:phone":"+34 928 53 34 40",
    "sg:postcode":"35600",
    "sg:province":"Las Palmas",
    "wof:name":"Inmobiliaria Precedo S.l.",
    "wof:placetype":"venue"
},
  "geometry": {"coordinates":[-13.8624210358,28.4969902039],"type":"Point"}
}