{
  "type": "Feature",
  "properties": {
    "iso:country":"ES",
    "sg:address":"Carr Nou, 8",
    "sg:city":"Artesa Lleida",
    "sg:orig_category":"Mec\u00c1nico Del Autom\u00d3vil",
    "sg:phone":"+34 973 16 72 09",
    "sg:postcode":"25150",
    "sg:province":"Lleida",
    "wof:name":"Gallart Oriol Ramon",
    "wof:placetype":"venue"
},
  "geometry": {"coordinates":[0.7057800293,41.5531044006],"type":"Point"}
}