{
  "type": "Feature",
  "properties": {
    "addr:full":"Plaz Angel Del Alcazar, 1 Ayllon Segovia 40520",
    "addr:housenumber":"1",
    "addr:postcode":"40520",
    "addr:street":"Ayllon Segovia",
    "iso:country":"ES",
    "sg:address":"Plaz Angel Del Alcazar, 1",
    "sg:city":"Ayllon",
    "sg:orig_category":"Carnicer\u00cdas, Carnicer\u00cdas",
    "sg:phone":"+34 921 55 31 30",
    "sg:postcode":"40520",
    "sg:province":"Segovia",
    "wof:name":"Olivares Sanz Felix",
    "wof:placetype":"venue"
},
  "geometry": {"coordinates":[-3.3770949841,41.4184875488],"type":"Point"}
}