{
  "type": "Feature",
  "properties": {
    "iso:country":"ES",
    "sg:address":"Ctra Sev-mal-gr (pi Hda Dolores), S/n",
    "sg:city":"Alcala Guadaira",
    "sg:orig_category":"Iluminaci\u00d3n Industrial, Alumbrado P\u00dablico: Material (fabricaci\u00d3n, Importaci\u00d3n)",
    "sg:phone":"+34 955 63 03 93",
    "sg:postcode":"41500",
    "sg:province":"Sevilla",
    "wof:name":"Cofarol Sevilla S.l.",
    "wof:placetype":"venue"
},
  "geometry": {"coordinates":[-5.8398590088,37.3383140564],"type":"Point"}
}