{
  "type": "Feature",
  "properties": {
    "addr:full":"Calle de Virgen Del Carmen, 10 Donostia-san Sebastian Guip\u00f9zcoa 20012",
    "addr:housenumber":"10",
    "addr:postcode":"20012",
    "addr:street":"Calle De Virgen Del Carmen",
    "iso:country":"ES",
    "sg:address":"Calle de Virgen Del Carmen, 10",
    "sg:city":"Donostia-san Sebastian",
    "sg:orig_category":"Bisuter\u00cda, Joyer\u00cda, Relojer\u00cda (al Por Menor)",
    "sg:phone":"+34 943 28 20 49",
    "sg:postcode":"20012",
    "sg:province":"Guip\u00f9zcoa",
    "wof:name":"Joyeria Relojeria Fuertes Mielaur,s.l.",
    "wof:placetype":"venue"
},
  "geometry": {"coordinates":[-1.9714989662,43.3165664673],"type":"Point"}
}