{
  "type": "Feature",
  "properties": {
    "addr:full":"Ctra Madrid, 72 Santa Marta De Tormes Salamanca 37900",
    "addr:housenumber":"72",
    "addr:postcode":"37900",
    "addr:street":"Ctra Madrid",
    "iso:country":"ES",
    "sg:address":"Ctra Madrid, 72",
    "sg:city":"Santa Marta De Tormes",
    "sg:orig_category":"Agencias Y Agentes Comerciales, Representantes",
    "sg:phone":"+34 923 13 05 23",
    "sg:postcode":"37900",
    "sg:province":"Salamanca",
    "wof:name":"Martin Garcia Carlos Jose",
    "wof:placetype":"venue"
},
  "geometry": {"coordinates":[-5.6278190613,40.9499282837],"type":"Point"}
}