{
  "type": "Feature",
  "properties": {
    "addr:full":"Av. Carlos Iii El Noble, 67 Iru\u00f1a Navarra 31004",
    "addr:housenumber":"67",
    "addr:postcode":"31004",
    "addr:street":"Av. Carlos Iii El Noble",
    "iso:country":"ES",
    "sg:address":"Av. Carlos Iii El Noble, 67",
    "sg:city":"Iru\u00f1a",
    "sg:orig_category":"Moda",
    "sg:phone":"+34 948 15 03 65",
    "sg:postcode":"31004",
    "sg:province":"Navarra",
    "sg:website":"www.prenatal.es",
    "wof:name":"Prenatal S.a.",
    "wof:placetype":"venue"
},
  "geometry": {"coordinates":[-1.6359659433,42.8104553223],"type":"Point"}
}