{
  "type": "Feature",
  "properties": {
    "addr:full":"Plaz Mayor, 8 Almodovar Campo Ciudad Real 13580",
    "addr:housenumber":"8",
    "addr:postcode":"13580",
    "addr:street":"Plaz Mayor;Campo",
    "iso:country":"ES",
    "sg:address":"Plaz Mayor, 8",
    "sg:city":"Almodovar Campo",
    "sg:orig_category":"Ropa De Hogar (al Por Menor)",
    "sg:phone":"+34 926 48 38 22",
    "sg:postcode":"13580",
    "sg:province":"Ciudad Real",
    "wof:name":"El Bastidor C.b.",
    "wof:placetype":"venue"
},
  "geometry": {"coordinates":[-4.1820688248,38.7115097046],"type":"Point"}
}