{
  "type": "Feature",
  "properties": {
    "iso:country":"ES",
    "sg:address":"Cra. De Montbrio, 8",
    "sg:city":"Montbrio Del Camp",
    "sg:orig_category":"Empresas De Carpinter\u00cda De Madera",
    "sg:phone":"+34 977 82 63 49",
    "sg:postcode":"43340",
    "sg:province":"Tarragona",
    "wof:name":"Llao Ferrer Antonio",
    "wof:placetype":"venue"
},
  "geometry": {"coordinates":[1.0044150352,41.1210594177],"type":"Point"}
}