{
  "type": "Feature",
  "properties": {
    "iso:country":"ES",
    "sg:address":"Calle de Nervion, 10",
    "sg:classifiers":[
        {
            "category":"Autos & Motor Vehicles",
            "subcategory":"Automobile Sales",
            "type":"Retail Goods"
        }
    ],
    "sg:phone":"+34 946 72 27 53",
    "sg:postcode":"01400",
    "sg:province":"\u00c1lava",
    "wof:name":"Auto Escuela Latatu Sl",
    "wof:placetype":"venue"
},
  "geometry": {"coordinates":[-2.9647090435,43.1417808533],"type":"Point"}
}