{
  "type": "Feature",
  "properties": {
    "addr:full":"Ptda Boixadors, 144 Basses D'alpicat Lleida 25191",
    "addr:housenumber":"144",
    "addr:postcode":"25191",
    "addr:street":"Ptda Boixadors",
    "iso:country":"ES",
    "sg:address":"Ptda Boixadors, 144",
    "sg:city":"Basses D'alpicat",
    "sg:orig_category":"Pe\u00d1as Y Asociaciones Varias",
    "sg:phone":"+34 973 24 83 37",
    "sg:postcode":"25191",
    "sg:province":"Lleida",
    "wof:name":"Rubiera Alonso Miguel Angel",
    "wof:placetype":"venue"
},
  "geometry": {"coordinates":[0.5885509849,41.6478729248],"type":"Point"}
}