{
  "type": "Feature",
  "properties": {
    "addr:full":"Calle de Auditor Francisco Bohorquez, 4 Ubrique C\u00e1diz 11600",
    "addr:housenumber":"4",
    "addr:postcode":"11600",
    "addr:street":"Calle De Auditor Francisco Bohorquez;Ca\u0301Diz",
    "iso:country":"ES",
    "sg:address":"Calle de Auditor Francisco Bohorquez, 4",
    "sg:city":"Ubrique",
    "sg:orig_category":"Asilos De Ancianos. Centros Privados",
    "sg:phone":"+34 956 46 00 95",
    "sg:postcode":"11600",
    "sg:province":"C\u00e1diz",
    "wof:name":"Asilo Nuestra Se\u00f1ora De Los Remedios",
    "wof:placetype":"venue"
},
  "geometry": {"coordinates":[-5.4432229996,36.6785469055],"type":"Point"}
}