{
  "type": "Feature",
  "properties": {
    "addr:full":"Calle de Santa Cecilia, 4 Aviles Asturias 33403",
    "addr:housenumber":"4",
    "addr:postcode":"33403",
    "addr:street":"Calle De Santa Cecilia",
    "iso:country":"ES",
    "sg:address":"Calle de Santa Cecilia, 4",
    "sg:city":"Aviles",
    "sg:orig_category":"Molduras, Junquillos, Listones Y Molduras Perforadas",
    "sg:phone":"+34 985 57 37 54",
    "sg:postcode":"33403",
    "sg:province":"Asturias",
    "wof:name":"Chamorro Santamarta Jesus",
    "wof:placetype":"venue"
},
  "geometry": {"coordinates":[-5.9063549042,43.5460510254],"type":"Point"}
}