{
  "type": "Feature",
  "properties": {
    "iso:country":"ES",
    "sg:address":"Calle de Lezama, 18",
    "sg:city":"Madrid",
    "sg:orig_category":"M\u00c1quinas De Escribir, M\u00c1quinas De Oficina (al Por Menor, Reparaci\u00d3n)",
    "sg:phone":"+34 913 58 09 78",
    "sg:postcode":"28034",
    "sg:province":"Madrid",
    "wof:name":"Bam Sistems S.a.",
    "wof:placetype":"venue"
},
  "geometry": {"coordinates":[-3.6912600994,40.4905014038],"type":"Point"}
}