{
  "type": "Feature",
  "properties": {
    "addr:full":"Calle de Mendizabal, 176 Almansa Albacete 02640",
    "addr:housenumber":"176",
    "addr:postcode":"02640",
    "addr:street":"Calle De Mendizabal",
    "iso:country":"ES",
    "sg:address":"Calle de Mendizabal, 176",
    "sg:city":"Almansa",
    "sg:orig_category":"Deportes N\u00c1uticos, Acu\u00c1ticos Y Subacu\u00c1ticos: Art\u00cdculos Y Equipo (al Por Menor)",
    "sg:phone":"+34 967 31 12 71",
    "sg:postcode":"02640",
    "sg:province":"Albacete",
    "wof:name":"Montaje Nautico, S.l.",
    "wof:placetype":"venue"
},
  "geometry": {"coordinates":[-1.1077489853,38.8709602356],"type":"Point"}
}