{
  "type": "Feature",
  "properties": {
    "iso:country":"ES",
    "sg:address":"Rua Rio Xallas, 47",
    "sg:city":"Carballo",
    "sg:orig_category":"Empresas De Carpinter\u00cda Met\u00c1lica",
    "sg:phone":"+34 981 70 03 94",
    "sg:postcode":"15100",
    "sg:province":"La Coru\u00f1a",
    "wof:name":"Lema Martinez Alfredo",
    "wof:placetype":"venue"
},
  "geometry": {"coordinates":[-8.6929187775,43.2084541321],"type":"Point"}
}