{
  "type": "Feature",
  "properties": {
    "iso:country":"ES",
    "sg:address":"Calle de Antonio Zamora, 53",
    "sg:city":"Madrid",
    "sg:orig_category":"Art\u00cdculos De Regalo (al Por Menor)",
    "sg:phone":"+34 914 79 96 91",
    "sg:postcode":"28011",
    "sg:province":"Madrid",
    "wof:name":"Franco Rubio Marco",
    "wof:placetype":"venue"
},
  "geometry": {"coordinates":[-3.7309026718,40.4123764038],"type":"Point"}
}