{
  "type": "Feature",
  "properties": {
    "iso:country":"ES",
    "sg:address":"Calle de Jose Ramos, 42",
    "sg:city":"San Pedro Alcantara",
    "sg:orig_category":"Fabricaci\u00d3n, Distribuci\u00d3n De Material Para La Climatizaci\u00d3n, Aireaci\u00d3n Y Ventilaci\u00d3n",
    "sg:phone":"+34 952 78 88 89",
    "sg:postcode":"29670",
    "sg:province":"M\u00e1laga",
    "wof:name":"Mateos Diez Del Valle Virgilio",
    "wof:placetype":"venue"
},
  "geometry": {"coordinates":[-4.9890599251,36.4885368347],"type":"Point"}
}