{
  "type": "Feature",
  "properties": {
    "iso:country":"ES",
    "sg:address":"Calle de Buenas, 1",
    "sg:city":"Carpio",
    "sg:orig_category":"Alimentaci\u00d3n General (al Por Menor)",
    "sg:phone":"+34 957 18 03 63",
    "sg:postcode":"14620",
    "sg:province":"C\u00f3rdoba",
    "wof:name":"Romero Rodriguez Juan",
    "wof:placetype":"venue"
},
  "geometry": {"coordinates":[-4.4979076385,37.9400367737],"type":"Point"}
}