{
  "type": "Feature",
  "properties": {
    "iso:country":"ES",
    "sg:address":"Carr Jaume Balmes, 5",
    "sg:city":"Balaguer",
    "sg:orig_category":"Productores Recolectores, Venta Directa De Vinos",
    "sg:phone":"+34 973 44 62 84",
    "sg:postcode":"25600",
    "sg:province":"Lleida",
    "wof:name":"Bodegas Garces S.a.",
    "wof:placetype":"venue"
},
  "geometry": {"coordinates":[0.8095129728,41.7943077087],"type":"Point"}
}