{
  "type": "Feature",
  "properties": {
    "addr:full":"Pl Fra Bernadi, 15 Manlleu Barcelona 08560",
    "addr:housenumber":"15",
    "addr:postcode":"08560",
    "addr:street":"Pl Fra Bernadi",
    "iso:country":"ES",
    "sg:address":"Pl Fra Bernadi, 15",
    "sg:city":"Manlleu",
    "sg:orig_category":"Caf\u00c9s, Bares, Cervecer\u00cdas",
    "sg:phone":"+34 938 51 44 53",
    "sg:postcode":"08560",
    "sg:province":"Barcelona",
    "wof:name":"Gomez Caro Manuel",
    "wof:placetype":"venue"
},
  "geometry": {"coordinates":[2.2840180397,41.9995002747],"type":"Point"}
}