{
  "type": "Feature",
  "properties": {
    "addr:full":"Plaz Bartolome Esteban, 1 Calamocha Teruel 44200",
    "addr:housenumber":"1",
    "addr:postcode":"44200",
    "addr:street":"Bartolome Esteban",
    "iso:country":"ES",
    "sg:address":"Plaz Bartolome Esteban, 1",
    "sg:city":"Calamocha",
    "sg:orig_category":"Asesor\u00cda Fiscal Y Jur\u00cddica",
    "sg:phone":"+34 978 73 01 97",
    "sg:postcode":"44200",
    "sg:province":"Teruel",
    "wof:name":"Contabilidades Jiloca S.l.",
    "wof:placetype":"venue"
},
  "geometry": {"coordinates":[-1.2977429628,40.9201889038],"type":"Point"}
}