{
  "type": "Feature",
  "properties": {
    "addr:full":"Carrer de Verge Del Pilar, 20 Sant Feliu Llobregat Barcelona 08980",
    "addr:housenumber":"20",
    "addr:postcode":"08980",
    "addr:street":"Carrer De Verge Del Pilar",
    "iso:country":"ES",
    "sg:address":"Carrer de Verge Del Pilar, 20",
    "sg:city":"Sant Feliu Llobregat",
    "sg:orig_category":"Transportes Por Carretera: Lotes Completos, Mercanc\u00cdas Diversas",
    "sg:phone":"+34 936 66 43 43",
    "sg:postcode":"08980",
    "sg:province":"Barcelona",
    "wof:name":"Alimentacion Dorado Barcelona 2002 S.l",
    "wof:placetype":"venue"
},
  "geometry": {"coordinates":[2.0532593727,41.3831481934],"type":"Point"}
}