{
  "type": "Feature",
  "properties": {
    "iso:country":"ES",
    "sg:address":"Plaz Isabel Ii, 3",
    "sg:city":"Madrid",
    "sg:orig_category":"Bisuter\u00cda, Joyer\u00cda, Relojer\u00cda (al Por Menor)",
    "sg:phone":"+34 902 30 30 63",
    "sg:postcode":"28013",
    "sg:province":"Madrid",
    "sg:website":"www.roselinjoyeros.com",
    "wof:name":"Roselin S.l.",
    "wof:placetype":"venue"
},
  "geometry": {"coordinates":[-3.7092089653,40.417842865],"type":"Point"}
}