{
  "type": "Feature",
  "properties": {
    "iso:country":"ES",
    "sg:address":"Calle de Llamica, S/n",
    "sg:city":"Ceadea",
    "sg:orig_category":"Aparatos E Instalaci\u00d3n De Regad\u00cdos",
    "sg:phone":"+34 980 68 45 06",
    "sg:postcode":"49512",
    "sg:province":"Zamora",
    "wof:name":"Fernandez Fernandez Jesus",
    "wof:placetype":"venue"
},
  "geometry": {"coordinates":[-6.2542147636,41.6833763123],"type":"Point"}
}