{
  "type": "Feature",
  "properties": {
    "iso:country":"ES",
    "sg:address":"Rua Orfas (das), 34",
    "sg:city":"Santiago De Compostela",
    "sg:orig_category":"Telas Y Sedas (al Por Menor)",
    "sg:phone":"+34 981 58 59 15",
    "sg:postcode":"15703",
    "sg:province":"A Coru\u00f1a",
    "wof:name":"Somoza Bustelo Catalina",
    "wof:placetype":"venue"
},
  "geometry": {"coordinates":[-8.5443334579,42.8771972656],"type":"Point"}
}