{
  "type": "Feature",
  "properties": {
    "addr:full":"Carrer de Roger De Lluria, 95 Barcelona Barcelona 08009",
    "addr:housenumber":"95",
    "addr:postcode":"08009",
    "addr:street":"Carrer De Roger De Lluria",
    "iso:country":"ES",
    "sg:address":"Carrer de Roger De Lluria, 95",
    "sg:city":"Barcelona",
    "sg:orig_category":"Abogados",
    "sg:phone":"+34 932 16 05 05",
    "sg:postcode":"08009",
    "sg:province":"Barcelona",
    "wof:name":"Abia & Rodriguez De Medina Abogados Asociados S.c.p.",
    "wof:placetype":"venue"
},
  "geometry": {"coordinates":[2.16572,41.395473],"type":"Point"}
}