{
  "type": "Feature",
  "properties": {
    "iso:country":"ES",
    "sg:address":"Avda Reina Sofia, 54",
    "sg:city":"Gibraleon",
    "sg:orig_category":"Colocaci\u00d3n, Mantenimiento De Canalizaciones",
    "sg:phone":"+34 959 30 07 91",
    "sg:postcode":"21500",
    "sg:province":"Huelva",
    "wof:name":"Construcciones Y Reparaciones Jersur S.l.",
    "wof:placetype":"venue"
},
  "geometry": {"coordinates":[-6.9609689713,37.3767204285],"type":"Point"}
}