{
  "type": "Feature",
  "properties": {
    "addr:full":"Calle de Huertos Familiares, 48 Puente-genil C\u00f3rdoba 14500",
    "addr:housenumber":"48",
    "addr:postcode":"14500",
    "addr:street":"Calle De Huertos Familiares;Co\u0301Rdoba",
    "iso:country":"ES",
    "sg:address":"Calle de Huertos Familiares, 48",
    "sg:city":"Puente-genil",
    "sg:orig_category":"Mec\u00c1nico Del Autom\u00d3vil",
    "sg:phone":"+34 957 60 71 53",
    "sg:postcode":"14500",
    "sg:province":"C\u00f3rdoba",
    "wof:name":"Mecanica Anzur S.l.",
    "wof:placetype":"venue"
},
  "geometry": {"coordinates":[-4.7485108376,37.3973770142],"type":"Point"}
}