{
  "type": "Feature",
  "properties": {
    "iso:country":"ES",
    "sg:address":"Carrer de Calders, 212",
    "sg:city":"Sabadell",
    "sg:orig_category":"Carnicer\u00cdas, Carnicer\u00cdas",
    "sg:phone":"+34 937 10 02 81",
    "sg:postcode":"08203",
    "sg:province":"Barcelona",
    "wof:name":"Ortiz Gonzalez Arsenio",
    "wof:placetype":"venue"
},
  "geometry": {"coordinates":[2.1191139221,41.5358352661],"type":"Point"}
}