{
  "type": "Feature",
  "properties": {
    "iso:country":"ES",
    "sg:address":"Calle de Agost, 52",
    "sg:city":"San Vicente Del Raspeig-sant Vicent Del Raspeig",
    "sg:orig_category":"Agencias De Viajes",
    "sg:phone":"+34 965 66 21 40",
    "sg:postcode":"03690",
    "sg:province":"Alicante",
    "wof:name":"Sigma Tours S.l.",
    "wof:placetype":"venue"
},
  "geometry": {"coordinates":[-0.5215929747,38.4005393982],"type":"Point"}
}