{
  "type": "Feature",
  "properties": {
    "addr:full":"Real Almadraba, 6 Barbate Franco C\u00e1diz 11160",
    "addr:housenumber":"6",
    "addr:postcode":"11160",
    "addr:street":"Almadraba",
    "iso:country":"ES",
    "sg:address":"Real Almadraba, 6",
    "sg:city":"Barbate Franco",
    "sg:orig_category":"Asociaciones, Organismos Culturales Y Socioeducativos",
    "sg:phone":"+34 956 43 30 06",
    "sg:postcode":"11160",
    "sg:province":"C\u00e1diz",
    "wof:name":"Eurotel-sur S.l.",
    "wof:placetype":"venue"
},
  "geometry": {"coordinates":[-5.9249129295,36.186920166],"type":"Point"}
}