{
  "type": "Feature",
  "properties": {
    "addr:full":"Carrer de Dr. Fleming, 9 Poblenou Barcelona 08397",
    "addr:housenumber":"9",
    "addr:postcode":"08397",
    "addr:street":"Carrer De Dr. Fleming",
    "iso:country":"ES",
    "sg:address":"Carrer de Dr. Fleming, 9",
    "sg:city":"Poblenou",
    "sg:orig_category":"Cl\u00cdnicas Dentales",
    "sg:phone":"+34 937 69 58 56",
    "sg:postcode":"08397",
    "sg:province":"Barcelona",
    "wof:name":"Clinica Dental Maresma S.l.",
    "wof:placetype":"venue"
},
  "geometry": {"coordinates":[2.6721498966,41.6176986694],"type":"Point"}
}