{
  "type": "Feature",
  "properties": {
    "iso:country":"ES",
    "sg:address":"Av Constitucio, 274",
    "sg:city":"Castelldefels",
    "sg:orig_category":"Restaurantes",
    "sg:phone":"+34 936 64 05 22",
    "sg:postcode":"08860",
    "sg:province":"Barcelona",
    "wof:name":"J Janpe S.c.p.",
    "wof:placetype":"venue"
},
  "geometry": {"coordinates":[1.9715869427,41.2730712891],"type":"Point"}
}