{
  "type": "Feature",
  "properties": {
    "addr:full":"Ptge Uralita, 9 Cerdanyola Valles Barcelona 08290",
    "addr:housenumber":"9",
    "addr:postcode":"08290",
    "addr:street":"Ptge Uralita;Valles Barcelona",
    "iso:country":"ES",
    "sg:address":"Ptge Uralita, 9",
    "sg:city":"Cerdanyola Valles",
    "sg:orig_category":"Empresas De Limpieza",
    "sg:phone":"+34 935 92 17 23",
    "sg:postcode":"08290",
    "sg:province":"Barcelona",
    "wof:name":"Jet Limp S.l.",
    "wof:placetype":"venue"
},
  "geometry": {"coordinates":[2.1470150948,41.4924812317],"type":"Point"}
}