{
  "type": "Feature",
  "properties": {
    "iso:country":"ES",
    "sg:address":"Av Primavera, 72",
    "sg:city":"Cerdanyola Valles",
    "sg:orig_category":"Reposter\u00cdas",
    "sg:phone":"+34 936 92 18 09",
    "sg:postcode":"08290",
    "sg:province":"Barcelona",
    "wof:name":"Abran Martin Gema",
    "wof:placetype":"venue"
},
  "geometry": {"coordinates":[2.139306,41.487217],"type":"Point"}
}