{
  "type": "Feature",
  "properties": {
    "iso:country":"ES",
    "sg:address":"Plaz Vargas, 4",
    "sg:city":"Jerez De La Frontera",
    "sg:orig_category":"Comisarios",
    "sg:phone":"+34 956 34 16 05",
    "sg:postcode":"11403",
    "sg:province":"C\u00e1diz",
    "wof:name":"Llamas Pescada Jose Luis",
    "wof:placetype":"venue"
},
  "geometry": {"coordinates":[-6.1348838806,36.6909637451],"type":"Point"}
}