{
  "type": "Feature",
  "properties": {
    "iso:country":"ES",
    "sg:address":"Calle de Burgos, 38",
    "sg:city":"Santander",
    "sg:orig_category":"Promotores Constructores",
    "sg:phone":"+34 942 37 56 46",
    "sg:postcode":"39008",
    "sg:province":"Cantabria",
    "wof:name":"Construnorte S.c.",
    "wof:placetype":"venue"
},
  "geometry": {"coordinates":[-3.8173298836,43.461025238],"type":"Point"}
}