{
  "type": "Feature",
  "properties": {
    "iso:country":"ES",
    "sg:address":"Avda Malaga (de), 37",
    "sg:city":"Montilla",
    "sg:orig_category":"Mec\u00c1nico Del Autom\u00d3vil",
    "sg:phone":"+34 957 65 37 77",
    "sg:postcode":"14550",
    "sg:province":"C\u00f3rdoba",
    "wof:name":"Felix Urbano Jimenez Y Otro Cdad.",
    "wof:placetype":"venue"
},
  "geometry": {"coordinates":[-4.6495089531,37.5756912231],"type":"Point"}
}