{
  "type": "Feature",
  "properties": {
    "iso:country":"ES",
    "sg:address":"Pase San Antonio, 101",
    "sg:city":"Palmas De Gran Canaria",
    "sg:orig_category":"Almacenes Frigor\u00cdficos",
    "sg:phone":"+34 928 37 08 89",
    "sg:postcode":"35012",
    "sg:province":"Las Palmas",
    "wof:name":"Gutierrez Saavedra Carmelo",
    "wof:placetype":"venue"
},
  "geometry": {"coordinates":[-15.4376401901,28.1102199554],"type":"Point"}
}