{
  "type": "Feature",
  "properties": {
    "iso:country":"ES",
    "sg:address":"Avda Santiago, 6",
    "sg:city":"Vitoria-gasteiz",
    "sg:classifiers":[
        {
            "category":"Taxi",
            "type":"Transportation"
        }
    ],
    "sg:phone":"+34 945 25 05 18",
    "sg:postcode":"01003",
    "sg:province":"\u00c1lava",
    "wof:name":"Larra Moreno Adolfo",
    "wof:placetype":"venue"
},
  "geometry": {"coordinates":[-2.6646559238,42.8471221924],"type":"Point"}
}