{
  "type": "Feature",
  "properties": {
    "addr:full":"Carrer de Santa Joaquima Vedruna, 12 Cambrils Tarragona 43850",
    "addr:housenumber":"12",
    "addr:postcode":"43850",
    "addr:street":"Carrer De Santa Joaquima Vedruna",
    "iso:country":"ES",
    "sg:address":"Carrer de Santa Joaquima Vedruna, 12",
    "sg:city":"Cambrils",
    "sg:orig_category":"Productores Recolectores, Venta Directa De Vinos",
    "sg:phone":"+34 977 79 36 56",
    "sg:postcode":"43850",
    "sg:province":"Tarragona",
    "wof:name":"Milan Gonzalez Jose",
    "wof:placetype":"venue"
},
  "geometry": {"coordinates":[1.0545250177,41.0710678101],"type":"Point"}
}