{
  "type": "Feature",
  "properties": {
    "addr:full":"Rbla Salvador Sama, 3 Vilanova I La Geltru Barcelona 08800",
    "addr:housenumber":"3",
    "addr:postcode":"08800",
    "addr:street":"Rbla Salvador Sama",
    "iso:country":"ES",
    "sg:address":"Rbla Salvador Sama, 3",
    "sg:city":"Vilanova I La Geltru",
    "sg:orig_category":"Cajas De Ahorro",
    "sg:phone":"+34 938 93 64 24",
    "sg:postcode":"08800",
    "sg:province":"Barcelona",
    "sg:website":"www.cajagranada.es",
    "wof:name":"Cajagranada",
    "wof:placetype":"venue"
},
  "geometry": {"coordinates":[1.7219020128,41.2245864868],"type":"Point"}
}