{
  "type": "Feature",
  "properties": {
    "addr:full":"Calle de Mariano Sanjuan, 29 Santisteban Puerto Ja\u00e9n 23250",
    "addr:housenumber":"29",
    "addr:postcode":"23250",
    "addr:street":"Calle De Mariano Sanjuan;Jae\u0301N",
    "iso:country":"ES",
    "sg:address":"Calle de Mariano Sanjuan, 29",
    "sg:city":"Santisteban Puerto",
    "sg:orig_category":"Cr\u00cda De Animales",
    "sg:phone":"+34 953 40 21 79",
    "sg:postcode":"23250",
    "sg:province":"Ja\u00e9n",
    "wof:name":"Arcos Olid Juan",
    "wof:placetype":"venue"
},
  "geometry": {"coordinates":[-3.203738451,38.2519264221],"type":"Point"}
}