{
  "type": "Feature",
  "properties": {
    "addr:full":"Calle de Virgen Del Pilar, 31 Ubeda Ja\u00e9n 23400",
    "addr:housenumber":"31",
    "addr:postcode":"23400",
    "addr:street":"Calle De Virgen Del Pilar;Jae\u0301N",
    "iso:country":"ES",
    "sg:address":"Calle de Virgen Del Pilar, 31",
    "sg:city":"Ubeda",
    "sg:orig_category":"Inform\u00c1tica, Ofim\u00c1tica (estudios, Asesor\u00cda, Ingenier\u00cda, Formaci\u00d3n)",
    "sg:phone":"+34 953 75 73 23",
    "sg:postcode":"23400",
    "sg:province":"Ja\u00e9n",
    "wof:name":"Alvarez Jurado Pedro",
    "wof:placetype":"venue"
},
  "geometry": {"coordinates":[-3.3729827404,38.0170326233],"type":"Point"}
}