{
  "type": "Feature",
  "properties": {
    "addr:full":"Calle de Eugenia De Montijo, 108 Madrid Madrid 28044",
    "addr:housenumber":"108",
    "addr:postcode":"28044",
    "addr:street":"Calle De Eugenia De Montijo",
    "iso:country":"ES",
    "sg:address":"Calle de Eugenia De Montijo, 108",
    "sg:city":"Madrid",
    "sg:orig_category":"Zapatos (al Por Menor)",
    "sg:phone":"+34 915 08 78 44",
    "sg:postcode":"28044",
    "sg:province":"Madrid",
    "wof:name":"Liu  Changnian",
    "wof:placetype":"venue"
},
  "geometry": {"coordinates":[-3.7510764599,40.3743515015],"type":"Point"}
}