{
  "type": "Feature",
  "properties": {
    "addr:full":"Calle de Valladolid, 2 Vitoria-gasteiz \u00c1lava 01002",
    "addr:housenumber":"2",
    "addr:postcode":"01002",
    "addr:street":"Calle De Valladolid",
    "iso:country":"ES",
    "sg:address":"Calle de Valladolid, 2",
    "sg:city":"Vitoria-gasteiz",
    "sg:orig_category":"Poller\u00cda Y Caza (al Por Menor)",
    "sg:phone":"+34 945 25 72 22",
    "sg:postcode":"01002",
    "sg:province":"\u00c1lava",
    "wof:name":"Torre Orive Maria Teresa",
    "wof:placetype":"venue"
},
  "geometry": {"coordinates":[-2.6636090279,42.8530006409],"type":"Point"}
}