{
  "type": "Feature",
  "properties": {
    "addr:full":"Carrer de Enric Granados, 48 Barcelona Barcelona 08008",
    "addr:housenumber":"48",
    "addr:postcode":"08008",
    "addr:street":"Carrer De Enric Granados",
    "iso:country":"ES",
    "sg:address":"Carrer de Enric Granados, 48",
    "sg:city":"Barcelona",
    "sg:orig_category":"Electrodom\u00c9sticos (al Por Menor)",
    "sg:phone":"+34 934 51 84 62",
    "sg:postcode":"08008",
    "sg:province":"Barcelona",
    "wof:name":"Cocoy Group Pares Musicales S.l.",
    "wof:placetype":"venue"
},
  "geometry": {"coordinates":[2.1580820084,41.3912391663],"type":"Point"}
}