{
  "type": "Feature",
  "properties": {
    "iso:country":"ES",
    "sg:address":"Calle de San Francisco, 3",
    "sg:city":"Madridejos",
    "sg:orig_category":"Bisuter\u00cda, Joyer\u00cda, Relojer\u00cda (al Por Menor)",
    "sg:phone":"+34 925 46 12 34",
    "sg:postcode":"45710",
    "sg:province":"Toledo",
    "wof:name":"Lopez Sanchez Francisca",
    "wof:placetype":"venue"
},
  "geometry": {"coordinates":[-3.5349349976,39.4667396545],"type":"Point"}
}