{
  "type": "Feature",
  "properties": {
    "addr:full":"Avda Europa, 124 Mojonera Almer\u00eda 04745",
    "addr:housenumber":"124",
    "addr:postcode":"04745",
    "addr:street":"Avda Europa",
    "iso:country":"ES",
    "sg:address":"Avda Europa, 124",
    "sg:city":"Mojonera",
    "sg:orig_category":"Librer\u00cdas",
    "sg:phone":"+34 950 33 15 89",
    "sg:postcode":"04745",
    "sg:province":"Almer\u00eda",
    "wof:name":"Diaz Dominguez Maria Del Mar",
    "wof:placetype":"venue"
},
  "geometry": {"coordinates":[-2.6815390587,36.7550506592],"type":"Point"}
}