{
  "type": "Feature",
  "properties": {
    "addr:full":"Calle de San Sebastian De La Gomera, 79 Fraile Santa Cruz De Tenerife 38640",
    "addr:housenumber":"79",
    "addr:postcode":"38640",
    "addr:street":"Calle De;Gomera",
    "iso:country":"ES",
    "sg:address":"Calle de San Sebastian De La Gomera, 79",
    "sg:city":"Fraile",
    "sg:orig_category":"Asociaciones Y Clubs Deportivos",
    "sg:phone":"+34 922 73 21 29",
    "sg:postcode":"38640",
    "sg:province":"Santa Cruz De Tenerife",
    "wof:name":"Mt Sport Tenerife S.l.",
    "wof:placetype":"venue"
},
  "geometry": {"coordinates":[-16.682012558,28.0987625122],"type":"Point"}
}