{
  "type": "Feature",
  "properties": {
    "addr:full":"Calle de Pedro Sarmiento De Gamboa, 3 Alcala Henares Madrid 28805",
    "addr:housenumber":"3",
    "addr:postcode":"28805",
    "addr:street":"Calle De Pedro Sarmiento De Gamboa",
    "iso:country":"ES",
    "sg:address":"Calle de Pedro Sarmiento De Gamboa, 3",
    "sg:city":"Alcala Henares",
    "sg:orig_category":"Iglesias Evang\u00c9licas",
    "sg:phone":"+34 918 80 35 41",
    "sg:postcode":"28805",
    "sg:province":"Madrid",
    "wof:name":"Iglesia Bautista El Faro",
    "wof:placetype":"venue"
},
  "geometry": {"coordinates":[-3.360560894,40.4899101257],"type":"Point"}
}