{
  "type": "Feature",
  "properties": {
    "iso:country":"ES",
    "sg:address":"Plaz Bombardera, 14",
    "sg:city":"Teruel",
    "sg:orig_category":"M\u00c1rmoles, Granitos Y Piedras Naturales",
    "sg:phone":"+34 978 60 16 46",
    "sg:postcode":"44001",
    "sg:province":"Teruel",
    "wof:name":"Ortiz Guillen Jose",
    "wof:placetype":"venue"
},
  "geometry": {"coordinates":[-1.1060190201,40.3448181152],"type":"Point"}
}