{
  "type": "Feature",
  "properties": {
    "addr:full":"Calle de Ronda De Capuchinos, 3 Sevilla Sevilla 41009",
    "addr:housenumber":"3",
    "addr:postcode":"41009",
    "addr:street":"Calle De Ronda De Capuchinos",
    "iso:country":"ES",
    "sg:address":"Calle de Ronda De Capuchinos, 3",
    "sg:city":"Sevilla",
    "sg:orig_category":"Panader\u00cdas, Panader\u00cdas",
    "sg:phone":"+34 954 36 14 08",
    "sg:postcode":"41009",
    "sg:province":"Sevilla",
    "wof:name":"Erasaji S.l.",
    "wof:placetype":"venue"
},
  "geometry": {"coordinates":[-5.9839129448,37.3999137878],"type":"Point"}
}