{
  "type": "Feature",
  "properties": {
    "addr:full":"Calle de Jose Pikaza Kalea, 1 Amurrio \u00c1lava 01470",
    "addr:housenumber":"1",
    "addr:postcode":"01470",
    "addr:street":"Calle De Jose Pikaza Kalea",
    "iso:country":"ES",
    "sg:address":"Calle de Jose Pikaza Kalea, 1",
    "sg:city":"Amurrio",
    "sg:orig_category":"Arquitectos",
    "sg:phone":"+34 945 89 04 43",
    "sg:postcode":"01470",
    "sg:province":"\u00c1lava",
    "wof:name":"Iturrate Vea-murguia, Pedro- Arquitecto",
    "wof:placetype":"venue"
},
  "geometry": {"coordinates":[-3.0040090084,43.0523834229],"type":"Point"}
}