{
  "type": "Feature",
  "properties": {
    "iso:country":"ES",
    "sg:address":"Avda Rioja De (la), 83",
    "sg:city":"Rincon Soto",
    "sg:orig_category":"Centros De Educaci\u00d3n Especial",
    "sg:phone":"+34 941 16 02 28",
    "sg:postcode":"26550",
    "sg:province":"La Rioja",
    "wof:name":"Colegio Publico Eduardo Gonzalez Gallarza",
    "wof:placetype":"venue"
},
  "geometry": {"coordinates":[-1.8486180305,42.2304801941],"type":"Point"}
}