{
  "type": "Feature",
  "properties": {
    "iso:country":"ES",
    "sg:address":"Carrer de Lepant, 48",
    "sg:city":"S. Boi Llobregat",
    "sg:orig_category":"Estudios, Instalaci\u00d3n De Climatizaci\u00d3n",
    "sg:phone":"+34 936 52 06 22",
    "sg:postcode":"08830",
    "sg:province":"Barcelona",
    "wof:name":"Conductos Llobregat S.l.",
    "wof:placetype":"venue"
},
  "geometry": {"coordinates":[2.0264220238,41.3497924805],"type":"Point"}
}