{
  "type": "Feature",
  "properties": {
    "iso:country":"ES",
    "sg:address":"Federico Soto, 6",
    "sg:city":"Iru\u00f1a",
    "sg:orig_category":"Florister\u00cdas",
    "sg:phone":"+34 948 13 25 44",
    "sg:postcode":"31015",
    "sg:province":"Navarra",
    "sg:website":"www.ezpeldiartefloral.com",
    "wof:name":"Floristeria Ezpeldi Loradenda",
    "wof:placetype":"venue"
},
  "geometry": {"coordinates":[-1.6316679716,42.8266372681],"type":"Point"}
}