{
  "type": "Feature",
  "properties": {
    "iso:country":"ES",
    "sg:address":"Calle de Concilio (del), 18",
    "sg:city":"Alcobendas",
    "sg:classifiers":[
        {
            "category":"Personal",
            "subcategory":"Barber",
            "type":"Services"
        }
    ],
    "sg:phone":"+34 916 53 11 61",
    "sg:postcode":"28100",
    "sg:province":"Madrid",
    "sg:tags":[
        "caballeros",
        "de",
        "peluqueros"
    ],
    "wof:name":"Moreno Hernandez Ricardo",
    "wof:placetype":"venue"
},
  "geometry": {"coordinates":[-3.6374976635,40.5436706543],"type":"Point"}
}