{
  "type": "Feature",
  "properties": {
    "iso:country":"ES",
    "sg:address":"Rua Jesus Soria, 1",
    "sg:city":"Ourense",
    "sg:orig_category":"Molduras, Junquillos, Listones Y Molduras Perforadas",
    "sg:phone":"+34 988 23 08 17",
    "sg:postcode":"32002",
    "sg:province":"Ourense",
    "wof:name":"Gonzalez Martinez Leonardo",
    "wof:placetype":"venue"
},
  "geometry": {"coordinates":[-7.8695578575,42.3397064209],"type":"Point"}
}