{
  "type": "Feature",
  "properties": {
    "iso:country":"ES",
    "sg:address":"C/ Sant Jaume, 95",
    "sg:city":"Ripollet",
    "sg:orig_category":"Mec\u00c1nico Del Autom\u00d3vil",
    "sg:phone":"+34 936 91 60 55",
    "sg:postcode":"08291",
    "sg:province":"Barcelona",
    "wof:name":"Blas Iba\u00f1ez Antonio",
    "wof:placetype":"venue"
},
  "geometry": {"coordinates":[2.1581029892,41.4984054565],"type":"Point"}
}