{
  "type": "Feature",
  "properties": {
    "iso:country":"ES",
    "sg:address":"Avda Cervantes, 43",
    "sg:city":"Arizgoiti",
    "sg:orig_category":"Cobro De Pr\u00c9stamos",
    "sg:phone":"+34 944 49 48 15",
    "sg:postcode":"48970",
    "sg:province":"Vizcaya",
    "wof:name":"Asociacion Educativa Berriztu",
    "wof:placetype":"venue"
},
  "geometry": {"coordinates":[-2.8811762333,43.2426109314],"type":"Point"}
}