{
  "type": "Feature",
  "properties": {
    "addr:full":"Carrer de Hondures, 66 Barcelona Barcelona 08027",
    "addr:housenumber":"66",
    "addr:postcode":"08027",
    "addr:street":"Carrer De Hondures",
    "iso:country":"ES",
    "sg:address":"Carrer de Hondures, 66",
    "sg:city":"Barcelona",
    "sg:orig_category":"Empresas De Pintura Y Revestimientos",
    "sg:phone":"+34 933 49 23 93",
    "sg:postcode":"08027",
    "sg:province":"Barcelona",
    "wof:name":"Gimenez Castro Pedro",
    "wof:placetype":"venue"
},
  "geometry": {"coordinates":[2.1879889965,41.4214401245],"type":"Point"}
}