{
  "type": "Feature",
  "properties": {
    "iso:country":"ES",
    "sg:address":"Calle de Empedrada, 69",
    "sg:city":"Montalban De Cordoba",
    "sg:orig_category":"Panader\u00cdas, Panader\u00cdas",
    "sg:phone":"+34 957 31 00 17",
    "sg:postcode":"14548",
    "sg:province":"C\u00f3rdoba",
    "wof:name":"Lopez Maestre Antonio",
    "wof:placetype":"venue"
},
  "geometry": {"coordinates":[-4.748606205,37.5820655823],"type":"Point"}
}