{
  "type": "Feature",
  "properties": {
    "addr:full":"Calle de Leon Xiii, 34 Sevilla Sevilla 41009",
    "addr:housenumber":"34",
    "addr:postcode":"41009",
    "addr:street":"Calle De Leon Xiii",
    "iso:country":"ES",
    "sg:address":"Calle de Leon Xiii, 34",
    "sg:city":"Sevilla",
    "sg:orig_category":"Cajas De Ahorro",
    "sg:phone":"+34 954 35 68 50",
    "sg:postcode":"41009",
    "sg:province":"Sevilla",
    "sg:website":"www.cajasanfernando.es",
    "wof:name":"Caja San Fernando De Sevilla Y Jerez",
    "wof:placetype":"venue"
},
  "geometry": {"coordinates":[-5.9833650589,37.4022674561],"type":"Point"}
}