{
  "type": "Feature",
  "properties": {
    "iso:country":"ES",
    "sg:address":"Carrer de Baix Sant Pere, S/n",
    "sg:city":"Mas Rampinyo",
    "sg:orig_category":"Tapicer\u00cdas",
    "sg:phone":"+34 935 64 05 91",
    "sg:postcode":"08110",
    "sg:province":"Barcelona",
    "wof:name":"Rodriguez Guisado Manuel",
    "wof:placetype":"venue"
},
  "geometry": {"coordinates":[2.1834449768,41.4945259094],"type":"Point"}
}