{
  "type": "Feature",
  "properties": {
    "iso:country":"ES",
    "sg:address":"Embalse, S/n",
    "sg:city":"Els Guiamets",
    "sg:orig_category":"Aguas (distribuci\u00d3n, Servicios)",
    "sg:phone":"+34 977 41 31 19",
    "sg:postcode":"43777",
    "sg:province":"Tarragona",
    "wof:name":"Comunitat De Regants Del Bail Priorat Panta De Guillamets",
    "wof:placetype":"venue"
},
  "geometry": {"coordinates":[0.7506399751,41.10181427],"type":"Point"}
}