{
  "type": "Feature",
  "properties": {
    "iso:country":"ES",
    "sg:address":"Calle de Platino, 11",
    "sg:city":"Cordoba",
    "sg:orig_category":"Bisuter\u00cda, Joyer\u00cda, Relojer\u00cda (al Por Menor)",
    "sg:phone":"+34 957 43 38 66",
    "sg:postcode":"14014",
    "sg:province":"C\u00f3rdoba",
    "wof:name":"Rodriguez Galiot Joyeros S.l.",
    "wof:placetype":"venue"
},
  "geometry": {"coordinates":[-4.7502188683,37.8890266418],"type":"Point"}
}