{
  "type": "Feature",
  "properties": {
    "iso:country":"ES",
    "sg:address":"Calle de Costa Valencia, 6",
    "sg:city":"Almafra",
    "sg:orig_category":"Suministros Y Materiales Industriales",
    "sg:phone":"+34 966 95 18 21",
    "sg:postcode":"03610",
    "sg:province":"Alicante",
    "wof:name":"Jose Mejias Suministros Industriales S.l.",
    "wof:placetype":"venue"
},
  "geometry": {"coordinates":[-0.8258302212,38.5351257324],"type":"Point"}
}