{
  "type": "Feature",
  "properties": {
    "iso:country":"ES",
    "sg:address":"Calle de Escolta Real, 47",
    "sg:city":"Donostia-san Sebastian",
    "sg:orig_category":"Confiter\u00cdas, Chocolater\u00cdas (al Por Menor)",
    "sg:phone":"+34 943 31 12 12",
    "sg:postcode":"20008",
    "sg:province":"Guip\u00f9zcoa",
    "wof:name":"Leyre Amaya Esnoz",
    "wof:placetype":"venue"
},
  "geometry": {"coordinates":[-2.0001070499,43.3117866516],"type":"Point"}
}