{
  "type": "Feature",
  "properties": {
    "iso:country":"ES",
    "sg:address":"Calle de Alfonso Vi, 8",
    "sg:city":"Le\u00f3n",
    "sg:orig_category":"Asociaciones Y Clubs Deportivos",
    "sg:phone":"+34 987 23 62 59",
    "sg:postcode":"24007",
    "sg:province":"Le\u00f3n",
    "wof:name":"Gimnasio El Calabozo S.l.",
    "wof:placetype":"venue"
},
  "geometry": {"coordinates":[-5.5676012039,42.6067237854],"type":"Point"}
}