{
  "type": "Feature",
  "properties": {
    "addr:full":"Des Velar, 10 Santanyi Islas Baleares 07650",
    "addr:housenumber":"10",
    "addr:postcode":"07650",
    "addr:street":"Santanyi Islas",
    "iso:country":"ES",
    "sg:address":"Des Velar, 10",
    "sg:city":"Santanyi",
    "sg:orig_category":"Doctores En Medicina",
    "sg:phone":"+34 971 16 34 06",
    "sg:postcode":"07650",
    "sg:province":"Islas Baleares",
    "wof:name":"Borella Pinget Francisco",
    "wof:placetype":"venue"
},
  "geometry": {"coordinates":[3.1236929893,39.3562545776],"type":"Point"}
}