{
  "type": "Feature",
  "properties": {
    "addr:full":"Calle de Estacion, 43 Miranda Ebro Burgos 09200",
    "addr:housenumber":"43",
    "addr:postcode":"09200",
    "addr:street":"Calle De Estacion",
    "iso:country":"ES",
    "sg:address":"Calle de Estacion, 43",
    "sg:city":"Miranda Ebro",
    "sg:orig_category":"Telas Y Sedas (al Por Menor)",
    "sg:phone":"+34 947 31 14 26",
    "sg:postcode":"09200",
    "sg:province":"Burgos",
    "wof:name":"Boveda Ca\u00f1o Maria Angeles",
    "wof:placetype":"venue"
},
  "geometry": {"coordinates":[-2.9424879551,42.6888847351],"type":"Point"}
}