{
  "type": "Feature",
  "properties": {
    "addr:full":"Calle de Pio Baroja, 1 Madrid Madrid 28009",
    "addr:housenumber":"1",
    "addr:postcode":"28009",
    "addr:street":"Calle De Pio Baroja",
    "iso:country":"ES",
    "sg:address":"Calle de Pio Baroja, 1",
    "sg:city":"Madrid",
    "sg:orig_category":"Complementos De Vestir (al Por Menor)",
    "sg:phone":"+34 915 04 65 85",
    "sg:postcode":"28009",
    "sg:province":"Madrid",
    "wof:name":"Rodriguez Jimenez Maria Eugenia",
    "wof:placetype":"venue"
},
  "geometry": {"coordinates":[-3.674710989,40.4158592224],"type":"Point"}
}