{
  "type": "Feature",
  "properties": {
    "iso:country":"ES",
    "sg:address":"Carrer de Escoles, 3",
    "sg:city":"Altafulla",
    "sg:orig_category":"Fabricaci\u00d3n, Venta De Productos Base Farmac\u00c9uticos",
    "sg:phone":"+34 977 65 04 97",
    "sg:postcode":"43893",
    "sg:province":"Tarragona",
    "wof:name":"Domingo Navarro Susana",
    "wof:placetype":"venue"
},
  "geometry": {"coordinates":[1.3739299774,41.1407318115],"type":"Point"}
}