{
  "type": "Feature",
  "properties": {
    "iso:country":"ES",
    "sg:address":"Carrer de Catalunya, 33",
    "sg:city":"Roca Valles",
    "sg:orig_category":"Cajas De Ahorro",
    "sg:phone":"+34 938 42 44 66",
    "sg:postcode":"08430",
    "sg:province":"Barcelona",
    "wof:name":"Caixa D'estalvis Sabadell",
    "wof:placetype":"venue"
},
  "geometry": {"coordinates":[2.3770260811,41.6025276184],"type":"Point"}
}