{
  "type": "Feature",
  "properties": {
    "iso:country":"ES",
    "sg:address":"Carrer de Jaume Perich, 3",
    "sg:city":"S. Cugat Valles",
    "sg:orig_category":"Venta, Localizaci\u00d3n, Reparaci\u00d3n De Material E Instrumental M\u00c9dico",
    "sg:phone":"+34 935 83 61 88",
    "sg:postcode":"08173",
    "sg:province":"Barcelona",
    "wof:name":"Wl Gore Y Asociados S.l.",
    "wof:placetype":"venue"
},
  "geometry": {"coordinates":[2.0689029694,41.4731178284],"type":"Point"}
}