{
  "type": "Feature",
  "properties": {
    "addr:full":"Calle de Delicias, 10 Fuenlabrada Madrid 28945",
    "addr:housenumber":"10",
    "addr:postcode":"28945",
    "addr:street":"Calle De Delicias",
    "iso:country":"ES",
    "sg:address":"Calle de Delicias, 10",
    "sg:city":"Fuenlabrada",
    "sg:orig_category":"Molduras, Junquillos, Listones Y Molduras Perforadas",
    "sg:phone":"+34 916 06 52 07",
    "sg:postcode":"28945",
    "sg:province":"Madrid",
    "wof:name":"Carretero Esperon Joaquin",
    "wof:placetype":"venue"
},
  "geometry": {"coordinates":[-3.7974727154,40.2840766907],"type":"Point"}
}