{
  "type": "Feature",
  "properties": {
    "addr:full":"Calle de Ignacio Monturiol, 2 Albacete Albacete 02005",
    "addr:housenumber":"2",
    "addr:postcode":"02005",
    "addr:street":"Calle De Ignacio Monturiol",
    "iso:country":"ES",
    "sg:address":"Calle de Ignacio Monturiol, 2",
    "sg:city":"Albacete",
    "sg:orig_category":"Ingeniero",
    "sg:phone":"+34 967 52 09 78",
    "sg:postcode":"02005",
    "sg:province":"Albacete",
    "wof:name":"Alfaro Serrano Faustino Enrique",
    "wof:placetype":"venue"
},
  "geometry": {"coordinates":[-1.8583650589,39.0018310547],"type":"Point"}
}