{
  "type": "Feature",
  "properties": {
    "iso:country":"ES",
    "sg:address":"Calle de Jose Arcones Gil, 70",
    "sg:city":"Madrid",
    "sg:orig_category":"Farmacias",
    "sg:phone":"+34 914 08 20 75",
    "sg:postcode":"28017",
    "sg:province":"Madrid",
    "wof:name":"Garcia Lopez-gasco Carmen",
    "wof:placetype":"venue"
},
  "geometry": {"coordinates":[-3.6360709667,40.4309768677],"type":"Point"}
}