{
  "type": "Feature",
  "properties": {
    "addr:full":"Carrer de Antoni Gaudi, 14 Reus Tarragona 43202",
    "addr:housenumber":"14",
    "addr:postcode":"43202",
    "addr:street":"Carrer De Antoni Gaudi",
    "iso:country":"ES",
    "sg:address":"Carrer de Antoni Gaudi, 14",
    "sg:city":"Reus",
    "sg:orig_category":"Venta, Localizaci\u00d3n, Reparaci\u00d3n De Material E Instrumental M\u00c9dico",
    "sg:phone":"+34 977 32 16 11",
    "sg:postcode":"43202",
    "sg:province":"Tarragona",
    "wof:name":"Medilab S. A.",
    "wof:placetype":"venue"
},
  "geometry": {"coordinates":[1.1049640179,41.1594161987],"type":"Point"}
}