{
  "type": "Feature",
  "properties": {
    "iso:country":"ES",
    "sg:address":"Calle de Albatros (de), 12",
    "sg:city":"Pinto",
    "sg:orig_category":"Tapones Y Art\u00cdculos De Corcho",
    "sg:phone":"+34 916 92 76 75",
    "sg:postcode":"28320",
    "sg:province":"Madrid",
    "wof:name":"Armacel Iberia S.l.soc.unip.",
    "wof:placetype":"venue"
},
  "geometry": {"coordinates":[-3.7091403008,40.2486343384],"type":"Point"}
}