{
  "type": "Feature",
  "properties": {
    "addr:full":"Avda Ferrol (del), 29 Viveiro Lugo 27850",
    "addr:housenumber":"29",
    "addr:postcode":"27850",
    "addr:street":"Avda Ferrol Del",
    "iso:country":"ES",
    "sg:address":"Avda Ferrol (del), 29",
    "sg:city":"Viveiro",
    "sg:orig_category":"Artes Gr\u00c1ficas, Artes Pl\u00c1sticas: Material Y Suministros (al Por Menor)",
    "sg:phone":"+34 982 55 00 61",
    "sg:postcode":"27850",
    "sg:province":"Lugo",
    "wof:name":"Fernandez-noriega Fernandez Daniel",
    "wof:placetype":"venue"
},
  "geometry": {"coordinates":[-7.5988898277,43.6568832397],"type":"Point"}
}