{
  "type": "Feature",
  "properties": {
    "addr:full":"Rua Montiron, 78 Lugo Lugo 27002",
    "addr:housenumber":"78",
    "addr:postcode":"27002",
    "addr:street":"Rua Montiron",
    "iso:country":"ES",
    "sg:address":"Rua Montiron, 78",
    "sg:city":"Lugo",
    "sg:orig_category":"Albergues",
    "sg:phone":"+34 982 25 50 89",
    "sg:postcode":"27002",
    "sg:province":"Lugo",
    "wof:name":"Diaz Barreira Manuel",
    "wof:placetype":"venue"
},
  "geometry": {"coordinates":[-7.5450129509,43.0012054443],"type":"Point"}
}