{
  "type": "Feature",
  "properties": {
    "iso:country":"ES",
    "sg:address":"Ctra. Badajoz-caceres, Km. 0079,5",
    "sg:city":"Gevora Caudillo",
    "sg:orig_category":"Empresas De Carpinter\u00cda Met\u00c1lica",
    "sg:phone":"+34 924 43 03 22",
    "sg:postcode":"06180",
    "sg:province":"Badajoz",
    "wof:name":"Martin Aguilar Manuel",
    "wof:placetype":"venue"
},
  "geometry": {"coordinates":[-6.9463391304,38.9193687439],"type":"Point"}
}