{
  "type": "Feature",
  "properties": {
    "iso:country":"ES",
    "sg:address":"Plaz Mayor, 11",
    "sg:city":"Guadalajara",
    "sg:orig_category":"Oficinas Y Gesti\u00d3n De Inmuebles",
    "sg:phone":"+34 949 24 86 68",
    "sg:postcode":"19001",
    "sg:province":"Guadalajara",
    "wof:name":"Ediaz Gestion S.l.",
    "wof:placetype":"venue"
},
  "geometry": {"coordinates":[-3.1663689613,40.6332855225],"type":"Point"}
}