{
  "type": "Feature",
  "properties": {
    "iso:country":"ES",
    "sg:address":"Carrer de Almogavers, 52",
    "sg:city":"Barcelona",
    "sg:orig_category":"Audiovisuales, Tv, Hi",
    "sg:phone":"+34 934 85 38 95",
    "sg:postcode":"08018",
    "sg:province":"Barcelona",
    "wof:name":"Saiz Fabregas Manel",
    "wof:placetype":"venue"
},
  "geometry": {"coordinates":[2.1853129864,41.3934020996],"type":"Point"}
}