{
  "type": "Feature",
  "properties": {
    "addr:full":"Calle de Pablo Remacha, 15 Zaragoza Zaragoza 50008",
    "addr:housenumber":"15",
    "addr:postcode":"50008",
    "addr:street":"Calle De Pablo Remacha",
    "iso:country":"ES",
    "sg:address":"Calle de Pablo Remacha, 15",
    "sg:city":"Zaragoza",
    "sg:orig_category":"Molduras, Junquillos, Listones Y Molduras Perforadas",
    "sg:phone":"+34 976 49 31 13",
    "sg:postcode":"50008",
    "sg:province":"Zaragoza",
    "wof:name":"Cotaina Tenias Marcelo Oscar",
    "wof:placetype":"venue"
},
  "geometry": {"coordinates":[-0.8724309802,41.6385650635],"type":"Point"}
}