{
  "type": "Feature",
  "properties": {
    "addr:full":"Calle de Pio Xii, 13 Vitoria-gasteiz \u00c1lava 01004",
    "addr:housenumber":"13",
    "addr:postcode":"01004",
    "addr:street":"Calle De Pio Xii",
    "iso:country":"ES",
    "sg:address":"Calle de Pio Xii, 13",
    "sg:city":"Vitoria-gasteiz",
    "sg:orig_category":"Estudios Y Construcci\u00d3n De Acuarios Y Viveros",
    "sg:phone":"+34 945 25 45 66",
    "sg:postcode":"01004",
    "sg:province":"\u00c1lava",
    "wof:name":"Viveros De Mariscos La Escollera, S.l.",
    "wof:placetype":"venue"
},
  "geometry": {"coordinates":[-2.6656327248,42.8446540833],"type":"Point"}
}