{
  "type": "Feature",
  "properties": {
    "addr:full":"Av Pau, 41 S. Celoni Barcelona 08470",
    "addr:housenumber":"41",
    "addr:postcode":"08470",
    "addr:street":"Av Pau;S. Celoni Barcelona",
    "iso:country":"ES",
    "sg:address":"Av Pau, 41",
    "sg:city":"S. Celoni",
    "sg:orig_category":"Molduras, Junquillos, Listones Y Molduras Perforadas",
    "sg:phone":"+34 938 67 24 25",
    "sg:postcode":"08470",
    "sg:province":"Barcelona",
    "wof:name":"Sanchez Cobos Rafael",
    "wof:placetype":"venue"
},
  "geometry": {"coordinates":[2.4844141006,41.6852302551],"type":"Point"}
}