{
  "type": "Feature",
  "properties": {
    "iso:country":"ES",
    "sg:address":"Calle de San Isidro, 4",
    "sg:city":"Tauste",
    "sg:orig_category":"Cristaler\u00cdas",
    "sg:phone":"+34 976 85 47 50",
    "sg:postcode":"50660",
    "sg:province":"Zaragoza",
    "wof:name":"Usan Sierra Miguel-angel",
    "wof:placetype":"venue"
},
  "geometry": {"coordinates":[-1.2523909807,41.9188957214],"type":"Point"}
}