{
  "type": "Feature",
  "properties": {
    "addr:full":"Calle de Luis Oliver, 9 Marbella M\u00e1laga 29600",
    "addr:housenumber":"9",
    "addr:postcode":"29600",
    "addr:street":"Calle De Luis Oliver;Ma\u0301Laga",
    "iso:country":"ES",
    "sg:address":"Calle de Luis Oliver, 9",
    "sg:city":"Marbella",
    "sg:orig_category":"Inversiones",
    "sg:phone":"+34 952 77 01 57",
    "sg:postcode":"29600",
    "sg:province":"M\u00e1laga",
    "wof:name":"Inversiones Caimo S.l.",
    "wof:placetype":"venue"
},
  "geometry": {"coordinates":[-4.8885250092,36.5091667175],"type":"Point"}
}