{
  "type": "Feature",
  "properties": {
    "addr:full":"Calle de Almazareros, S/n Sevilla Sevilla 41008",
    "addr:housenumber":"s / n",
    "addr:postcode":"41008",
    "addr:street":"Calle De Almazareros",
    "iso:country":"ES",
    "sg:address":"Calle de Almazareros, S/n",
    "sg:city":"Sevilla",
    "sg:orig_category":"Frutas, Legumbres Frescas Y Tempranas (al Por Menor)",
    "sg:phone":"+34 954 96 07 95",
    "sg:postcode":"41008",
    "sg:province":"Sevilla",
    "wof:name":"Garcia Marquez Javier",
    "wof:placetype":"venue"
},
  "geometry": {"coordinates":[-5.9614167213,37.4230155945],"type":"Point"}
}