{
  "type": "Feature",
  "properties": {
    "iso:country":"ES",
    "sg:address":"Los Naranjos, 5",
    "sg:city":"Madrigal Vera",
    "sg:orig_category":"Farmacias",
    "sg:phone":"+34 927 56 50 87",
    "sg:postcode":"10480",
    "sg:province":"C\u00e1ceres",
    "wof:name":"Morcuende Vadillo Rosa Maria",
    "wof:placetype":"venue"
},
  "geometry": {"coordinates":[-5.3673648834,40.1477355957],"type":"Point"}
}