{
  "type": "Feature",
  "properties": {
    "iso:country":"ES",
    "sg:address":"Calle de Sanchez De Motos, 37",
    "sg:city":"Cella",
    "sg:orig_category":"Transporte En General",
    "sg:phone":"+34 978 65 01 69",
    "sg:postcode":"44370",
    "sg:province":"Teruel",
    "wof:name":"Cooperativa De Consumo Santa Rosina",
    "wof:placetype":"venue"
},
  "geometry": {"coordinates":[-1.2848930359,40.4534339905],"type":"Point"}
}