{
  "type": "Feature",
  "properties": {
    "iso:country":"ES",
    "sg:address":"Avda Virgen De La Pe\u00d1a, 2",
    "sg:city":"Mijas",
    "sg:orig_category":"Bares, Piano",
    "sg:phone":"+34 952 48 62 22",
    "sg:postcode":"29650",
    "sg:province":"M\u00e1laga",
    "wof:name":"Nu\u00f1ez Mota Antonio",
    "wof:placetype":"venue"
},
  "geometry": {"coordinates":[-4.6368789673,36.5964202881],"type":"Point"}
}