{
  "type": "Feature",
  "properties": {
    "iso:country":"ES",
    "sg:address":"Calle de Pelicano, 26",
    "sg:city":"Madrid",
    "sg:orig_category":"Iglesias Evang\u00c9licas",
    "sg:phone":"+34 915 25 17 30",
    "sg:postcode":"28025",
    "sg:province":"Madrid",
    "wof:name":"Iglesia Evangelica Del Nazareno",
    "wof:placetype":"venue"
},
  "geometry": {"coordinates":[-3.7282850742,40.3837547302],"type":"Point"}
}