{
  "type": "Feature",
  "properties": {
    "addr:full":"Carr Tarongeta, 4 S. Jordi Desvalls Girona 17464",
    "addr:housenumber":"4",
    "addr:postcode":"17464",
    "addr:street":"Carr Tarongeta;Jordi",
    "iso:country":"ES",
    "sg:address":"Carr Tarongeta, 4",
    "sg:city":"S. Jordi Desvalls",
    "sg:orig_category":"Producci\u00d3n, Comercio De Cereales",
    "sg:phone":"+34 972 79 80 24",
    "sg:postcode":"17464",
    "sg:province":"Girona",
    "wof:name":"Barcelo Pascual Narciso",
    "wof:placetype":"venue"
},
  "geometry": {"coordinates":[2.9092900753,42.067199707],"type":"Point"}
}