{
  "type": "Feature",
  "properties": {
    "addr:full":"Calle de Juan Ibargutxi, 5 Arizgoiti Vizcaya 48970",
    "addr:housenumber":"5",
    "addr:postcode":"48970",
    "addr:street":"Calle De Juan Ibargutxi",
    "iso:country":"ES",
    "sg:address":"Calle de Juan Ibargutxi, 5",
    "sg:city":"Arizgoiti",
    "sg:orig_category":"Agencias Y Agentes Comerciales, Representantes",
    "sg:phone":"+34 944 49 03 75",
    "sg:postcode":"48970",
    "sg:province":"Vizcaya",
    "wof:name":"Bragado Arribas Jose Fernando",
    "wof:placetype":"venue"
},
  "geometry": {"coordinates":[-2.8911468983,43.2366142273],"type":"Point"}
}