{
  "type": "Feature",
  "properties": {
    "addr:full":"Calle de Virgen Del Carmen, 24 Donostia-san Sebastian Guip\u00f9zcoa 20012",
    "addr:housenumber":"24",
    "addr:postcode":"20012",
    "addr:street":"Calle De Virgen Del Carmen",
    "iso:country":"ES",
    "sg:address":"Calle de Virgen Del Carmen, 24",
    "sg:city":"Donostia-san Sebastian",
    "sg:orig_category":"Pod\u00d3logos: Pedicuros",
    "sg:phone":"+34 943 28 75 20",
    "sg:postcode":"20012",
    "sg:province":"Guip\u00f9zcoa",
    "wof:name":"Tenes Iturri, S.l.",
    "wof:placetype":"venue"
},
  "geometry": {"coordinates":[-1.9695179462,43.3173980713],"type":"Point"}
}