{
  "type": "Feature",
  "properties": {
    "iso:country":"ES",
    "sg:address":"Luga Forte, S/n",
    "sg:city":"Forte",
    "sg:orig_category":"Asesor\u00cda Fiscal Y Jur\u00cddica",
    "sg:phone":"+34 981 81 75 20",
    "sg:postcode":"15881",
    "sg:province":"La Coru\u00f1a",
    "wof:name":"Asesoria Boqueixon S.l.",
    "wof:placetype":"venue"
},
  "geometry": {"coordinates":[-8.4771060944,42.9314994812],"type":"Point"}
}