{
  "type": "Feature",
  "properties": {
    "addr:full":"Veinticinco De Abril, 15 Moncada Valencia 46113",
    "addr:housenumber":"15",
    "addr:postcode":"46113",
    "addr:street":"Veinticinco;Abril",
    "iso:country":"ES",
    "sg:address":"Veinticinco De Abril, 15",
    "sg:city":"Moncada",
    "sg:orig_category":"Tintes (fabricaci\u00d3n, Al Por Mayor)",
    "sg:phone":"+34 961 30 11 69",
    "sg:postcode":"46113",
    "sg:province":"Valencia",
    "wof:name":"Chirivella Rausell Leonardo Adolfo",
    "wof:placetype":"venue"
},
  "geometry": {"coordinates":[-0.3962120116,39.5446510315],"type":"Point"}
}