{
  "type": "Feature",
  "properties": {
    "addr:full":"Pase Conde De Sepulveda (del), 29 Segovia Segovia 40006",
    "addr:housenumber":"29",
    "addr:postcode":"40006",
    "addr:street":"Conde;Sepulveda Del",
    "iso:country":"ES",
    "sg:address":"Pase Conde De Sepulveda (del), 29",
    "sg:city":"Segovia",
    "sg:orig_category":"Comercio De Ganado",
    "sg:phone":"+34 921 43 29 69",
    "sg:postcode":"40006",
    "sg:province":"Segovia",
    "wof:name":"Gregorio Perez Merinero S.l.",
    "wof:placetype":"venue"
},
  "geometry": {"coordinates":[-4.1163339615,40.9404678345],"type":"Point"}
}