{
  "type": "Feature",
  "properties": {
    "iso:country":"ES",
    "sg:address":"Carr Del Riu, 6",
    "sg:city":"Barruera",
    "sg:orig_category":"Centros De Educaci\u00d3n Especial",
    "sg:phone":"+34 973 69 41 42",
    "sg:postcode":"25527",
    "sg:province":"Lleida",
    "wof:name":"Ajuntament De La Vall De Boi",
    "wof:placetype":"venue"
},
  "geometry": {"coordinates":[0.7985954285,42.5032157898],"type":"Point"}
}