{
  "type": "Feature",
  "properties": {
    "addr:full":"Crri Torre Leales, 47 Dolores Murcia 30011",
    "addr:housenumber":"47",
    "addr:postcode":"30011",
    "addr:street":"Leales",
    "iso:country":"ES",
    "sg:address":"Crri Torre Leales, 47",
    "sg:city":"Dolores",
    "sg:orig_category":"Molduras, Junquillos, Listones Y Molduras Perforadas",
    "sg:phone":"+34 968 87 40 05",
    "sg:postcode":"30011",
    "sg:province":"Murcia",
    "wof:name":"Industria De Gofres Murcia",
    "wof:placetype":"venue"
},
  "geometry": {"coordinates":[-1.1055790186,37.9783668518],"type":"Point"}
}