{
  "type": "Feature",
  "properties": {
    "iso:country":"ES",
    "sg:address":"Avda. Burgos, S/n",
    "sg:city":"Campamento",
    "sg:orig_category":"Almacenes Frigor\u00cdficos",
    "sg:phone":"+34 956 69 89 17",
    "sg:postcode":"11314",
    "sg:province":"C\u00e1diz",
    "wof:name":"Almadraba Cabo Plata S.a.",
    "wof:placetype":"venue"
},
  "geometry": {"coordinates":[-5.3679871559,36.1745223999],"type":"Point"}
}