{
  "type": "Feature",
  "properties": {
    "iso:country":"ES",
    "sg:address":"Ctra Barcelona, 66",
    "sg:city":"Viladecans",
    "sg:orig_category":"Lavado, Limpieza De Veh\u00cdculos",
    "sg:phone":"+34 936 59 02 24",
    "sg:postcode":"08840",
    "sg:province":"Barcelona",
    "sg:website":"www.laundry-car.com",
    "wof:name":"Gonzalez Garcia Antonio",
    "wof:placetype":"venue"
},
  "geometry": {"coordinates":[2.0254869461,41.3195533752],"type":"Point"}
}