{
  "type": "Feature",
  "properties": {
    "iso:country":"ES",
    "sg:address":"Rbla Sant Andreu (de), 2",
    "sg:city":"Ripollet",
    "sg:orig_category":"Empresas De Vigilancia, Guardia Y Protecci\u00d3n",
    "sg:phone":"+34 936 91 58 01",
    "sg:postcode":"08291",
    "sg:province":"Barcelona",
    "wof:name":"Sistemes De Control Y Proteccio Segurex,s.c.c.l.",
    "wof:placetype":"venue"
},
  "geometry": {"coordinates":[2.1598289013,41.5011253357],"type":"Point"}
}