{
  "type": "Feature",
  "properties": {
    "iso:country":"ES",
    "sg:address":"Av Carmen Amaya, 14",
    "sg:city":"Hospitalet Llobregat",
    "sg:orig_category":"Molduras, Junquillos, Listones Y Molduras Perforadas",
    "sg:phone":"+34 933 36 05 02",
    "sg:postcode":"08902",
    "sg:province":"Barcelona",
    "wof:name":"Allue Ferraz Jose",
    "wof:placetype":"venue"
},
  "geometry": {"coordinates":[2.1173086166,41.3531532288],"type":"Point"}
}