{
  "type": "Feature",
  "properties": {
    "addr:full":"Pla\u00c7 Major, 5 Vajol Girona 17707",
    "addr:housenumber":"5",
    "addr:postcode":"17707",
    "addr:street":"Vajol Girona",
    "iso:country":"ES",
    "sg:address":"Pla\u00c7 Major, 5",
    "sg:city":"Vajol",
    "sg:orig_category":"Obras Y Organismos Sociales",
    "sg:phone":"+34 972 53 51 63",
    "sg:postcode":"17707",
    "sg:province":"Girona",
    "wof:name":"Sociedad De Socorros Mutuos La Camelia",
    "wof:placetype":"venue"
},
  "geometry": {"coordinates":[2.84719491,42.3942718506],"type":"Point"}
}