{
  "type": "Feature",
  "properties": {
    "addr:full":"Calle de Maria Diaz De Haro, 15 Portugalete Vizcaya 48920",
    "addr:housenumber":"15",
    "addr:postcode":"48920",
    "addr:street":"Calle De Maria Diaz De Haro",
    "iso:country":"ES",
    "sg:address":"Calle de Maria Diaz De Haro, 15",
    "sg:city":"Portugalete",
    "sg:orig_category":"Partidos Pol\u00cdticos",
    "sg:phone":"+34 944 72 12 09",
    "sg:postcode":"48920",
    "sg:province":"Vizcaya",
    "wof:name":"Partido Popular",
    "wof:placetype":"venue"
},
  "geometry": {"coordinates":[-3.0201039314,43.3241958618],"type":"Point"}
}