{
  "type": "Feature",
  "properties": {
    "addr:full":"Calle de Urazurrutia, 37 Bilbao Vizcaya 48003",
    "addr:housenumber":"37",
    "addr:postcode":"48003",
    "addr:street":"Calle De Urazurrutia",
    "iso:country":"ES",
    "sg:address":"Calle de Urazurrutia, 37",
    "sg:city":"Bilbao",
    "sg:orig_category":"Alumbrados",
    "sg:phone":"+34 944 15 43 00",
    "sg:postcode":"48003",
    "sg:province":"Vizcaya",
    "wof:name":"P.c.es De Colores S.l.",
    "wof:placetype":"venue"
},
  "geometry": {"coordinates":[-2.9228720665,43.2513427734],"type":"Point"}
}