{
  "type": "Feature",
  "properties": {
    "iso:country":"ES",
    "sg:address":"Carrer de Riera Baste, 22",
    "sg:city":"S. Boi Llobregat",
    "sg:orig_category":"Ingeniero",
    "sg:phone":"+34 936 30 15 82",
    "sg:postcode":"08830",
    "sg:province":"Barcelona",
    "wof:name":"Grupo Comercial De Empresas Telecomunicaciones Hermanas Aranda S.l.",
    "wof:placetype":"venue"
},
  "geometry": {"coordinates":[2.0357999802,41.346321106],"type":"Point"}
}