{
  "type": "Feature",
  "properties": {
    "addr:full":"Cllo Cruceiros (a), 8 Marin Pontevedra 36900",
    "addr:housenumber":"8",
    "addr:postcode":"36900",
    "iso:country":"ES",
    "sg:address":"Cllo Cruceiros (a), 8",
    "sg:city":"Marin",
    "sg:orig_category":"Alimentaci\u00d3n General (al Por Menor)",
    "sg:phone":"+34 986 88 01 00",
    "sg:postcode":"36900",
    "sg:province":"Pontevedra",
    "wof:name":"Area Moreira Josefa",
    "wof:placetype":"venue"
},
  "geometry": {"coordinates":[-8.6910228729,42.3965415955],"type":"Point"}
}