{
  "type": "Feature",
  "properties": {
    "iso:country":"ES",
    "sg:address":"Plaz Pio Xii, 3",
    "sg:city":"Irun",
    "sg:orig_category":"Farmacias",
    "sg:phone":"+34 943 61 56 09",
    "sg:postcode":"20303",
    "sg:province":"Guip\u00f9zcoa",
    "wof:name":"Farmacia Barrio-ormazabal",
    "wof:placetype":"venue"
},
  "geometry": {"coordinates":[-1.796710968,43.3383102417],"type":"Point"}
}