{
  "type": "Feature",
  "properties": {
    "iso:country":"ES",
    "sg:address":"Av Lluis Millet, S/n",
    "sg:city":"Comte De Sert",
    "sg:orig_category":"Arquitectos",
    "sg:phone":"+34 937 72 01 29",
    "sg:postcode":"08755",
    "sg:province":"Barcelona",
    "wof:name":"Canovas Caparros Pedro",
    "wof:placetype":"venue"
},
  "geometry": {"coordinates":[1.9950959682,41.4856796265],"type":"Point"}
}