{
  "type": "Feature",
  "properties": {
    "iso:country":"ES",
    "sg:address":"Calle de Nevada, 9",
    "sg:city":"Granada",
    "sg:orig_category":"Estancos",
    "sg:phone":"+34 958 20 42 26",
    "sg:postcode":"18010",
    "sg:province":"Granada",
    "wof:name":"Carrillo Lorenzo Ricardo",
    "wof:placetype":"venue"
},
  "geometry": {"coordinates":[-3.5909221172,37.1887435913],"type":"Point"}
}