{
  "type": "Feature",
  "properties": {
    "iso:country":"ES",
    "sg:address":"Calle de Colombia, 23",
    "sg:city":"Madrid",
    "sg:orig_category":"Centros De Coordinaci\u00d3n",
    "sg:phone":"+34 913 45 05 24",
    "sg:postcode":"28016",
    "sg:province":"Madrid",
    "wof:name":"Cuarenta Y Diez Gestion S.l.",
    "wof:placetype":"venue"
},
  "geometry": {"coordinates":[-3.6742093563,40.4570503235],"type":"Point"}
}