{
  "type": "Feature",
  "properties": {
    "addr:full":"Carrer de Sant Adria, 126 Barcelona Barcelona 08030",
    "addr:housenumber":"126",
    "addr:postcode":"08030",
    "addr:street":"Carrer De Sant Adria",
    "iso:country":"ES",
    "sg:address":"Carrer de Sant Adria, 126",
    "sg:city":"Barcelona",
    "sg:orig_category":"Peluquer\u00cdas, Peluquer\u00cda Mixta",
    "sg:phone":"+34 933 13 51 80",
    "sg:postcode":"08030",
    "sg:province":"Barcelona",
    "wof:name":"Gatoo Barrionuevo Angel",
    "wof:placetype":"venue"
},
  "geometry": {"coordinates":[2.2035999298,41.4359321594],"type":"Point"}
}