{
  "type": "Feature",
  "properties": {
    "iso:country":"ES",
    "sg:address":"Calle de San Juan De Dios, 31",
    "sg:city":"Granada",
    "sg:orig_category":"Cajas De Ahorro",
    "sg:phone":"+34 958 29 48 85",
    "sg:postcode":"18001",
    "sg:province":"Granada",
    "sg:website":"www.cajagranada.es",
    "wof:name":"Cajagranada",
    "wof:placetype":"venue"
},
  "geometry": {"coordinates":[-3.6027050018,37.1814575195],"type":"Point"}
}