{
  "type": "Feature",
  "properties": {
    "addr:full":"Calle de Zaragoza, 17 Almeria Almer\u00eda 04001",
    "addr:housenumber":"17",
    "addr:postcode":"04001",
    "addr:street":"Calle De Zaragoza",
    "iso:country":"ES",
    "sg:address":"Calle de Zaragoza, 17",
    "sg:city":"Almeria",
    "sg:orig_category":"Mercer\u00cda, Lencer\u00cda (al Por Menor)",
    "sg:phone":"+34 950 26 78 28",
    "sg:postcode":"04001",
    "sg:province":"Almer\u00eda",
    "wof:name":"Cuenca Lopez Gaspar",
    "wof:placetype":"venue"
},
  "geometry": {"coordinates":[-2.4609889984,36.8395767212],"type":"Point"}
}