{
  "type": "Feature",
  "properties": {
    "addr:full":"Calle de Nieremberg, 27 Madrid Madrid 28002",
    "addr:housenumber":"27",
    "addr:postcode":"madrid;28002",
    "addr:street":"Calle De Nieremberg",
    "iso:country":"ES",
    "sg:address":"Calle de Nieremberg, 27",
    "sg:city":"Madrid",
    "sg:orig_category":"Servicio De Salud",
    "sg:phone":"+34 915 19 49 99",
    "sg:postcode":"28002",
    "sg:province":"Madrid",
    "wof:name":"Saneamientos Pradillo S.l.",
    "wof:placetype":"venue"
},
  "geometry": {"coordinates":[-3.6727490425,40.4482154846],"type":"Point"}
}