{
  "type": "Feature",
  "properties": {
    "iso:country":"ES",
    "sg:address":"Calle de Manresa, 1",
    "sg:city":"Santa Catalina",
    "sg:orig_category":"Abogados",
    "sg:phone":"+34 968 22 12 27",
    "sg:postcode":"30004",
    "sg:province":"Murcia",
    "wof:name":"Navarro Valcarcel Jose",
    "wof:placetype":"venue"
},
  "geometry": {"coordinates":[-1.1324510574,37.9869194031],"type":"Point"}
}