{
  "type": "Feature",
  "properties": {
    "addr:full":"Calle de Miami, 27 Tablero Las Palmas 35100",
    "addr:housenumber":"27",
    "addr:postcode":"35100",
    "addr:street":"Calle De Miami;Las",
    "iso:country":"ES",
    "sg:address":"Calle de Miami, 27",
    "sg:city":"Tablero",
    "sg:orig_category":"Peluquer\u00cdas, Peluquer\u00cda Mixta",
    "sg:phone":"+34 928 14 28 73",
    "sg:postcode":"35100",
    "sg:province":"Las Palmas",
    "wof:name":"Gomez Lirola Maria Esther",
    "wof:placetype":"venue"
},
  "geometry": {"coordinates":[-15.6060733795,27.7691936493],"type":"Point"}
}