{
  "type": "Feature",
  "properties": {
    "addr:full":"Pl Catalunya, 10 Ampolla Tarragona 43895",
    "addr:housenumber":"10",
    "addr:postcode":"43895",
    "addr:street":"Pl Catalunya",
    "iso:country":"ES",
    "sg:address":"Pl Catalunya, 10",
    "sg:city":"Ampolla",
    "sg:orig_category":"Distribuci\u00d3n De Petr\u00d3leo Y Derivados",
    "sg:phone":"+34 977 46 00 34",
    "sg:postcode":"43895",
    "sg:province":"Tarragona",
    "sg:website":"www.pcserveis.com",
    "wof:name":"Pescados Y Mariscos Prades S.l.",
    "wof:placetype":"venue"
},
  "geometry": {"coordinates":[0.7101060152,40.8122291565],"type":"Point"}
}