{
  "type": "Feature",
  "properties": {
    "addr:full":"Calle de Puerta Del Osario, 16 Sevilla Sevilla 41003",
    "addr:housenumber":"16",
    "addr:postcode":"41003",
    "addr:street":"Calle De Puerta Del Osario",
    "iso:country":"ES",
    "sg:address":"Calle de Puerta Del Osario, 16",
    "sg:city":"Sevilla",
    "sg:orig_category":"Formaci\u00d3n Continuada (variada)",
    "sg:phone":"+34 954 21 19 57",
    "sg:postcode":"41003",
    "sg:province":"Sevilla",
    "wof:name":"Soto Delgado Francisco",
    "wof:placetype":"venue"
},
  "geometry": {"coordinates":[-5.9849495888,37.3931121826],"type":"Point"}
}