{
  "type": "Feature",
  "properties": {
    "addr:full":"Ctra Cruce, S/n Zalamea Serena Badajoz 06430",
    "addr:housenumber":"s / n",
    "addr:postcode":"06430",
    "addr:street":"Ctra Cruce",
    "iso:country":"ES",
    "sg:address":"Ctra Cruce, S/n",
    "sg:city":"Zalamea Serena",
    "sg:orig_category":"Mec\u00c1nico Del Autom\u00d3vil",
    "sg:phone":"+34 924 77 51 62",
    "sg:postcode":"06430",
    "sg:province":"Badajoz",
    "wof:name":"Centeno Centeno Diego",
    "wof:placetype":"venue"
},
  "geometry": {"coordinates":[-5.6559262276,38.649646759],"type":"Point"}
}