{
  "type": "Feature",
  "properties": {
    "addr:full":"Av Catalunya, 59 Cervera Lleida 25200",
    "addr:housenumber":"59",
    "addr:postcode":"25200",
    "addr:street":"Av Catalunya",
    "iso:country":"ES",
    "sg:address":"Av Catalunya, 59",
    "sg:city":"Cervera",
    "sg:orig_category":"Institutos De Belleza",
    "sg:phone":"+34 973 53 20 42",
    "sg:postcode":"25200",
    "sg:province":"Lleida",
    "wof:name":"Arbos Pomes Laia",
    "wof:placetype":"venue"
},
  "geometry": {"coordinates":[1.270503521,41.6710777283],"type":"Point"}
}