{
  "type": "Feature",
  "properties": {
    "iso:country":"ES",
    "sg:address":"Calle de Verde (la), S/n",
    "sg:city":"Herrera",
    "sg:orig_category":"Explotaci\u00d3n De Canteras",
    "sg:phone":"+34 942 25 46 50",
    "sg:postcode":"39608",
    "sg:province":"Cantabria",
    "wof:name":"Hongomar S. A.",
    "wof:placetype":"venue"
},
  "geometry": {"coordinates":[-3.8830139637,43.4323272705],"type":"Point"}
}