{
  "type": "Feature",
  "properties": {
    "iso:country":"ES",
    "sg:address":"Calle de Nafarroa, 5",
    "sg:city":"San Vicente De Barakaldo",
    "sg:orig_category":"Ropa Para Se\u00d1oras Y Caballeros (al Por Menor)",
    "sg:phone":"+34 944 37 43 03",
    "sg:postcode":"48901",
    "sg:province":"Vizcaya",
    "wof:name":"Milagros Sainz Castresana Y Otro Cdad",
    "wof:placetype":"venue"
},
  "geometry": {"coordinates":[-2.9878919125,43.2966651917],"type":"Point"}
}