{
  "type": "Feature",
  "properties": {
    "addr:full":"Calle de Cid Campeador, 39 Alfafar Valencia 46910",
    "addr:housenumber":"39",
    "addr:postcode":"46910",
    "addr:street":"Calle De Cid Campeador",
    "iso:country":"ES",
    "sg:address":"Calle de Cid Campeador, 39",
    "sg:city":"Alfafar",
    "sg:orig_category":"Arquitectos",
    "sg:phone":"+34 963 75 73 85",
    "sg:postcode":"46910",
    "sg:province":"Valencia",
    "wof:name":"Garcia Duran Nestor",
    "wof:placetype":"venue"
},
  "geometry": {"coordinates":[-0.3884293139,39.4190368652],"type":"Point"}
}