{
  "type": "Feature",
  "properties": {
    "iso:country":"ES",
    "sg:address":"Avgd Pere Mas I Reus, S/n",
    "sg:city":"Platja D'alcudia",
    "sg:orig_category":"Organismos De Turismo",
    "sg:phone":"+34 971 89 09 70",
    "sg:postcode":"07408",
    "sg:province":"Islas Baleares",
    "wof:name":"Puerto Bello S.l.",
    "wof:placetype":"venue"
},
  "geometry": {"coordinates":[3.1255340576,39.8456192017],"type":"Point"}
}