{
  "type": "Feature",
  "properties": {
    "addr:full":"Av Santa Eularia Des Riu, S/n Eivissa Islas Baleares 07800",
    "addr:housenumber":"/ n",
    "addr:postcode":"07800",
    "addr:street":"Av Santa Eularia;Riu S",
    "iso:country":"ES",
    "sg:address":"Av Santa Eularia Des Riu, S/n",
    "sg:city":"Eivissa",
    "sg:orig_category":"Agencias De Viajes",
    "sg:phone":"+34 971 31 07 11",
    "sg:postcode":"07800",
    "sg:province":"Islas Baleares",
    "wof:name":"Servicios Y Concesiones Maritimas Ibicencas S.a.",
    "wof:placetype":"venue"
},
  "geometry": {"coordinates":[1.4346599579,38.9107551575],"type":"Point"}
}