{
  "type": "Feature",
  "properties": {
    "addr:full":"Calle de Olivo, 18 Cortegana Huelva 21230",
    "addr:housenumber":"18",
    "addr:postcode":"21230",
    "addr:street":"Calle De Olivo",
    "iso:country":"ES",
    "sg:address":"Calle de Olivo, 18",
    "sg:city":"Cortegana",
    "sg:orig_category":"Empresas De Carpinter\u00cda Met\u00c1lica",
    "sg:phone":"+34 959 13 11 66",
    "sg:postcode":"21230",
    "sg:province":"Huelva",
    "wof:name":"Romasan De Cortegana S.l.",
    "wof:placetype":"venue"
},
  "geometry": {"coordinates":[-6.8211488724,37.9153709412],"type":"Point"}
}