{
  "type": "Feature",
  "properties": {
    "iso:country":"ES",
    "sg:address":"Av Diagonal, 605",
    "sg:city":"Barcelona",
    "sg:orig_category":"Inform\u00c1tica Equipo Y Programas (al Por Mayor)",
    "sg:phone":"+34 933 63 68 50",
    "sg:postcode":"08028",
    "sg:province":"Barcelona",
    "sg:website":"www.bmc.com",
    "wof:name":"B.m.c. Software S.a.",
    "wof:placetype":"venue"
},
  "geometry": {"coordinates":[2.1295518875,41.3885307312],"type":"Point"}
}