{
  "type": "Feature",
  "properties": {
    "iso:country":"ES",
    "sg:address":"Pol. Ind. Sesrovires, 3",
    "sg:city":"S. Esteve Sesrovires",
    "sg:orig_category":"Fabricaci\u00d3n De Jabones, Detergentes Y Lej\u00cdas",
    "sg:phone":"+34 937 71 33 13",
    "sg:postcode":"08635",
    "sg:province":"Barcelona",
    "wof:name":"Vilaro Quimics S.l.",
    "wof:placetype":"venue"
},
  "geometry": {"coordinates":[1.8731199503,41.4965515137],"type":"Point"}
}