{
  "type": "Feature",
  "properties": {
    "iso:country":"ES",
    "sg:address":"Plaz Mayor, S/n",
    "sg:city":"Villoldo",
    "sg:orig_category":"Iglesia Cat\u00d3lica",
    "sg:phone":"+34 979 82 70 13",
    "sg:postcode":"34131",
    "sg:province":"Palencia",
    "wof:name":"Parroquia De San Esteban",
    "wof:placetype":"venue"
},
  "geometry": {"coordinates":[-4.6216640472,42.2484664917],"type":"Point"}
}