{
  "type": "Feature",
  "properties": {
    "iso:country":"ES",
    "sg:address":"Calle de Andalucia, 61",
    "sg:city":"Arroyo De La Miel-benalmadena Costa",
    "sg:orig_category":"Tintorer\u00cdas, Limpieza En Seco",
    "sg:phone":"+34 952 44 60 77",
    "sg:postcode":"29631",
    "sg:province":"M\u00e1laga",
    "wof:name":"Lavanderia Rios S.cv.",
    "wof:placetype":"venue"
},
  "geometry": {"coordinates":[-4.5332050323,36.5979232788],"type":"Point"}
}