{
  "type": "Feature",
  "properties": {
    "iso:country":"ES",
    "sg:address":"Carrer de Galileu, 268",
    "sg:city":"Barcelona",
    "sg:orig_category":"Estancos",
    "sg:phone":"+34 934 90 91 17",
    "sg:postcode":"08028",
    "sg:province":"Barcelona",
    "wof:name":"Perello Olivella Maria Dolores",
    "wof:placetype":"venue"
},
  "geometry": {"coordinates":[2.1326329708,41.3833274841],"type":"Point"}
}