{
  "type": "Feature",
  "properties": {
    "iso:country":"ES",
    "sg:address":"Calle de Caridad, 6",
    "sg:city":"Gijon",
    "sg:orig_category":"Internados & Ense\u00d1anza Privada",
    "sg:phone":"+34 985 36 13 29",
    "sg:postcode":"33202",
    "sg:province":"Asturias",
    "wof:name":"Colegio De San Vicente De Paul",
    "wof:placetype":"venue"
},
  "geometry": {"coordinates":[-5.6550388336,43.5402603149],"type":"Point"}
}