{
  "type": "Feature",
  "properties": {
    "iso:country":"ES",
    "sg:address":"Carrer de Mar (la), 28",
    "sg:city":"Altea",
    "sg:orig_category":"Peluquer\u00cdas, Peluquer\u00cda Mixta",
    "sg:phone":"+34 965 84 35 58",
    "sg:postcode":"03590",
    "sg:province":"Alicante",
    "wof:name":"Trujillo Felipe Miguel",
    "wof:placetype":"venue"
},
  "geometry": {"coordinates":[-0.048613999,38.5991859436],"type":"Point"}
}