{
  "type": "Feature",
  "properties": {
    "iso:country":"ES",
    "sg:address":"Calle de Humera, 52",
    "sg:city":"Madrid",
    "sg:orig_category":"Inmobiliaria (agencias)",
    "sg:phone":"+34 913 07 85 51",
    "sg:postcode":"28023",
    "sg:province":"Madrid",
    "wof:name":"Umera 52 S.l.",
    "wof:placetype":"venue"
},
  "geometry": {"coordinates":[-3.7822024822,40.44972229],"type":"Point"}
}