{
  "type": "Feature",
  "properties": {
    "addr:full":"Cmno Campo (del), S/n Argamasilla Alba Ciudad Real 13710",
    "addr:housenumber":"/ n",
    "addr:postcode":"alba;13710",
    "addr:street":"Cmno Campo Del S",
    "iso:country":"ES",
    "sg:address":"Cmno Campo (del), S/n",
    "sg:city":"Argamasilla Alba",
    "sg:orig_category":"Asociaciones Humanitarias, De Cooperaci\u00d3n, De Acci\u00d3n Social",
    "sg:phone":"+34 926 52 35 30",
    "sg:postcode":"13710",
    "sg:province":"Ciudad Real",
    "wof:name":"Asociacion Pro-minusvalidos",
    "wof:placetype":"venue"
},
  "geometry": {"coordinates":[-3.0827875137,39.1325492859],"type":"Point"}
}