{
  "type": "Feature",
  "properties": {
    "addr:full":"Carrer de Sao Paulo, 18 Barcelona Barcelona 08030",
    "addr:housenumber":"18",
    "addr:postcode":"08030",
    "addr:street":"Carrer De Sao Paulo",
    "iso:country":"ES",
    "sg:address":"Carrer de Sao Paulo, 18",
    "sg:city":"Barcelona",
    "sg:orig_category":"Agencias Y Agentes Comerciales, Representantes",
    "sg:phone":"+34 933 11 25 05",
    "sg:postcode":"08030",
    "sg:province":"Barcelona",
    "wof:name":"Girona Carmona David",
    "wof:placetype":"venue"
},
  "geometry": {"coordinates":[2.1964700222,41.4388084412],"type":"Point"}
}