{
  "type": "Feature",
  "properties": {
    "iso:country":"ES",
    "sg:address":"Rua Espido, 76",
    "sg:city":"Verin",
    "sg:orig_category":"Reposter\u00cdas",
    "sg:phone":"+34 988 41 47 69",
    "sg:postcode":"32600",
    "sg:province":"Ourense",
    "wof:name":"Claro Cervi\u00f1o Manuel",
    "wof:placetype":"venue"
},
  "geometry": {"coordinates":[-7.4335660934,41.9396095276],"type":"Point"}
}