{
  "type": "Feature",
  "properties": {
    "iso:country":"ES",
    "sg:address":"Cmno Rejal (del), S/n",
    "sg:city":"Valdilecha",
    "sg:orig_category":"Fabrica De Charcuter\u00cda",
    "sg:phone":"+34 918 73 80 65",
    "sg:postcode":"28511",
    "sg:province":"Madrid",
    "sg:website":"www.etbsa.com",
    "wof:name":"Enrique Torres Brea S.a.",
    "wof:placetype":"venue"
},
  "geometry": {"coordinates":[-3.2986159325,40.2986564636],"type":"Point"}
}