{
  "type": "Feature",
  "properties": {
    "addr:full":"Calle de Cordoba, 1 Lanjaron Granada 18420",
    "addr:housenumber":"1",
    "addr:postcode":"18420",
    "addr:street":"Calle De Cordoba",
    "iso:country":"ES",
    "sg:address":"Calle de Cordoba, 1",
    "sg:city":"Lanjaron",
    "sg:orig_category":"Bibliotecas, Mediatecas",
    "sg:phone":"+34 958 77 22 16",
    "sg:postcode":"18420",
    "sg:province":"Granada",
    "wof:name":"Ayuntamiento De Lanjaron",
    "wof:placetype":"venue"
},
  "geometry": {"coordinates":[-3.4827489853,36.9184799194],"type":"Point"}
}