{
  "type": "Feature",
  "properties": {
    "iso:country":"ES",
    "sg:address":"Plaz Constitucion (la), 12",
    "sg:city":"Villa De Teguise",
    "sg:orig_category":"Artesan\u00cda",
    "sg:phone":"+34 928 84 51 06",
    "sg:postcode":"35530",
    "sg:province":"Las Palmas",
    "wof:name":"Robayna Robayna Maria Dolores",
    "wof:placetype":"venue"
},
  "geometry": {"coordinates":[-13.5599966049,29.0592193604],"type":"Point"}
}