{
  "type": "Feature",
  "properties": {
    "addr:full":"Calle de Camilo Martinon Navarro, 89 Zardo Las Palmas 35018",
    "addr:housenumber":"89",
    "addr:postcode":"35018",
    "addr:street":"Calle De Camilo Martinon Navarro;Palmas",
    "iso:country":"ES",
    "sg:address":"Calle de Camilo Martinon Navarro, 89",
    "sg:city":"Zardo",
    "sg:orig_category":"Agencias Y Agentes Comerciales, Representantes",
    "sg:phone":"+34 928 37 80 10",
    "sg:postcode":"35018",
    "sg:province":"Las Palmas",
    "wof:name":"Abba Armas Adolfo Javier",
    "wof:placetype":"venue"
},
  "geometry": {"coordinates":[-15.430006,28.124823],"type":"Point"}
}