{
  "type": "Feature",
  "properties": {
    "iso:country":"ES",
    "sg:address":"Calle de Bordadores (los), 31",
    "sg:city":"Le\u00f3n",
    "sg:orig_category":"Postigos, Persianas Y Celos\u00cdas",
    "sg:phone":"+34 987 26 15 96",
    "sg:postcode":"24006",
    "sg:province":"Le\u00f3n",
    "wof:name":"Rodriguez Cordero Manuel",
    "wof:placetype":"venue"
},
  "geometry": {"coordinates":[-5.5613470078,42.5925445557],"type":"Point"}
}