{
  "type": "Feature",
  "properties": {
    "addr:full":"Calle de Guillem De Castro, 134 Valencia Valencia 46003",
    "addr:housenumber":"134",
    "addr:postcode":"46003",
    "addr:street":"Calle De Guillem De Castro",
    "iso:country":"ES",
    "sg:address":"Calle de Guillem De Castro, 134",
    "sg:city":"Valencia",
    "sg:orig_category":"Comercio, Reparaci\u00d3n De Motocicletas, Bicicletas Y Piezas Sueltas",
    "sg:phone":"+34 963 91 20 33",
    "sg:postcode":"46003",
    "sg:province":"Valencia",
    "wof:name":"Carmona Montoya Jose Luis",
    "wof:placetype":"venue"
},
  "geometry": {"coordinates":[-0.3805640042,39.4812393188],"type":"Point"}
}