{
  "type": "Feature",
  "properties": {
    "addr:full":"Carrer de Ramon Llull, 9 Prat Llobregat Barcelona 08820",
    "addr:housenumber":"9",
    "addr:postcode":"08820",
    "addr:street":"Carrer De Ramon Llull;Llobregat",
    "iso:country":"ES",
    "sg:address":"Carrer de Ramon Llull, 9",
    "sg:city":"Prat Llobregat",
    "sg:orig_category":"Bisuter\u00cda, Joyer\u00cda, Relojer\u00cda (al Por Menor)",
    "sg:phone":"+34 934 78 71 71",
    "sg:postcode":"08820",
    "sg:province":"Barcelona",
    "wof:name":"Hera Joyeria Y Relojeria Sl",
    "wof:placetype":"venue"
},
  "geometry": {"coordinates":[2.090321064,41.3236808777],"type":"Point"}
}