{
  "type": "Feature",
  "properties": {
    "addr:full":"Calle de Consistorio, S/n Gumiel Mercado Burgos 09440",
    "addr:housenumber":"s / n",
    "addr:postcode":"09440",
    "addr:street":"Calle De Consistorio",
    "iso:country":"ES",
    "sg:address":"Calle de Consistorio, S/n",
    "sg:city":"Gumiel Mercado",
    "sg:classifiers":[
        {
            "category":"Taxi",
            "type":"Transportation"
        }
    ],
    "sg:phone":"+34 947 54 50 49",
    "sg:postcode":"09440",
    "sg:province":"Burgos",
    "wof:name":"Herrero Sierra Tomas",
    "wof:placetype":"venue"
},
  "geometry": {"coordinates":[-3.6997311115,42.3408737183],"type":"Point"}
}