{
  "type": "Feature",
  "properties": {
    "iso:country":"ES",
    "sg:address":"Calle de Ladrillos, 17",
    "sg:city":"Llerena",
    "sg:orig_category":"M\u00c9dicos: Otorrinolaringolog\u00cda",
    "sg:phone":"+34 924 87 24 54",
    "sg:postcode":"06900",
    "sg:province":"Badajoz",
    "wof:name":"Balderrama Caballero David Hugo",
    "wof:placetype":"venue"
},
  "geometry": {"coordinates":[-6.0199546814,38.2343597412],"type":"Point"}
}