{
  "type": "Feature",
  "properties": {
    "iso:country":"ES",
    "sg:address":"Calle de Guzman El Bueno, 9",
    "sg:city":"Madrid",
    "sg:orig_category":"Abogados",
    "sg:phone":"+34 915 49 32 22",
    "sg:postcode":"28015",
    "sg:province":"Madrid",
    "wof:name":"Fernandez Garcia Juan Jose",
    "wof:placetype":"venue"
},
  "geometry": {"coordinates":[-3.7135155201,40.4311447144],"type":"Point"}
}