{
  "type": "Feature",
  "properties": {
    "addr:full":"Avda Pamplona, S/n Tafalla Navarra 31300",
    "addr:housenumber":"s / n",
    "addr:postcode":"31300",
    "addr:street":"Avda Pamplona",
    "iso:country":"ES",
    "sg:address":"Avda Pamplona, S/n",
    "sg:city":"Tafalla",
    "sg:orig_category":"Venta, Instalaci\u00d3n De Calefacci\u00d3n",
    "sg:phone":"+34 948 70 27 66",
    "sg:postcode":"31300",
    "sg:province":"Navarra",
    "wof:name":"Figasca S.l.",
    "wof:placetype":"venue"
},
  "geometry": {"coordinates":[-1.6711490154,42.5334968567],"type":"Point"}
}