{
  "type": "Feature",
  "properties": {
    "addr:full":"Carrer de Garrotxa (la), 25 Vendrell Tarragona 43700",
    "addr:housenumber":"25",
    "addr:postcode":"43700",
    "addr:street":"Carrer De Garrotxa La",
    "iso:country":"ES",
    "sg:address":"Carrer de Garrotxa (la), 25",
    "sg:city":"Vendrell",
    "sg:orig_category":"Transportes Por V\u00cdas Navegables",
    "sg:phone":"+34 977 66 16 30",
    "sg:postcode":"43700",
    "sg:province":"Tarragona",
    "wof:name":"Gallardo Sanchez Jose",
    "wof:placetype":"venue"
},
  "geometry": {"coordinates":[1.5249170065,41.2183685303],"type":"Point"}
}