{
  "type": "Feature",
  "properties": {
    "addr:full":"Avda Pio Xii, 20 Talavera Reina Toledo 45600",
    "addr:housenumber":"20",
    "addr:postcode":"45600",
    "addr:street":"Avda Pio Xii",
    "iso:country":"ES",
    "sg:address":"Avda Pio Xii, 20",
    "sg:city":"Talavera Reina",
    "sg:orig_category":"Ense\u00d1anza: Profesiones Art\u00cdsticas",
    "sg:phone":"+34 925 81 10 06",
    "sg:postcode":"45600",
    "sg:province":"Toledo",
    "wof:name":"Cerro Escobar Miguel Angel Del",
    "wof:placetype":"venue"
},
  "geometry": {"coordinates":[-4.827545166,39.9645347595],"type":"Point"}
}