{
  "type": "Feature",
  "properties": {
    "iso:country":"ES",
    "sg:address":"Calle de Bilbao, 25",
    "sg:city":"San Sebastian De Los Reyes",
    "sg:orig_category":"Molduras, Junquillos, Listones Y Molduras Perforadas",
    "sg:phone":"+34 916 52 13 93",
    "sg:postcode":"28700",
    "sg:province":"Madrid",
    "wof:name":"Casimiro Navacerrada S.a.",
    "wof:placetype":"venue"
},
  "geometry": {"coordinates":[-3.6245529652,40.550113678],"type":"Point"}
}