{
  "type": "Feature",
  "properties": {
    "iso:country":"ES",
    "sg:address":"Calle de Manuel Iradier, 26",
    "sg:city":"Vitoria-gasteiz",
    "sg:orig_category":"Fabricaci\u00d3n De Ventanas",
    "sg:phone":"+34 945 13 94 18",
    "sg:postcode":"01005",
    "sg:province":"\u00c1lava",
    "sg:website":"www.deimaconstrucciones.com",
    "wof:name":"Blanco Olivares Silvia",
    "wof:placetype":"venue"
},
  "geometry": {"coordinates":[-2.6721138954,42.8420639038],"type":"Point"}
}