{
  "type": "Feature",
  "properties": {
    "addr:full":"Pase Arco De Ladrillo, 7 Valladolid Valladolid 47007",
    "addr:housenumber":"7",
    "addr:postcode":"47007",
    "addr:street":"Ladrillo",
    "iso:country":"ES",
    "sg:address":"Pase Arco De Ladrillo, 7",
    "sg:city":"Valladolid",
    "sg:orig_category":"Asesor\u00cda, Estudio Y Control Medioambiental",
    "sg:phone":"+34 983 27 61 66",
    "sg:postcode":"47007",
    "sg:province":"Valladolid",
    "wof:name":"Sicma Consultora Y Formacion S.l.",
    "wof:placetype":"venue"
},
  "geometry": {"coordinates":[-4.7311830521,41.6422729492],"type":"Point"}
}