{
  "type": "Feature",
  "properties": {
    "iso:country":"ES",
    "sg:address":"Calle de Pio Baroja, 11",
    "sg:city":"Valladolid",
    "sg:orig_category":"Delegados, Agentes De Tr\u00c1nsito, Auxiliares De Transporte Internacional",
    "sg:phone":"+34 983 24 82 17",
    "sg:postcode":"47008",
    "sg:province":"Valladolid",
    "wof:name":"Ega\u00f1a Gomez Aranzazu",
    "wof:placetype":"venue"
},
  "geometry": {"coordinates":[-4.7539629936,41.6120948792],"type":"Point"}
}