{
  "type": "Feature",
  "properties": {
    "iso:country":"ES",
    "sg:address":"Calle de Isabel La Catolica, 26",
    "sg:city":"Alcala Real",
    "sg:orig_category":"Maquinaria Para Industrias Diversas",
    "sg:phone":"+34 953 58 05 72",
    "sg:postcode":"23680",
    "sg:province":"Ja\u00e9n",
    "wof:name":"Marchal Arias Juan Antonio",
    "wof:placetype":"venue"
},
  "geometry": {"coordinates":[-3.9249780178,37.4598808289],"type":"Point"}
}