{
  "type": "Feature",
  "properties": {
    "addr:full":"Calle de Alcotanes (de), 27 Pinto Madrid 28320",
    "addr:housenumber":"27",
    "addr:postcode":"28320",
    "addr:street":"Calle De Alcotanes De",
    "iso:country":"ES",
    "sg:address":"Calle de Alcotanes (de), 27",
    "sg:city":"Pinto",
    "sg:orig_category":"Comercio De Hierro",
    "sg:phone":"+34 916 92 85 12",
    "sg:postcode":"28320",
    "sg:province":"Madrid",
    "sg:website":"www.maypersl.com",
    "wof:name":"Materiales Y Perforados S.l.",
    "wof:placetype":"venue"
},
  "geometry": {"coordinates":[-3.7116324902,40.2510719299],"type":"Point"}
}