{
  "type": "Feature",
  "properties": {
    "iso:country":"ES",
    "sg:address":"Ctra Riells, Km. 0001,5",
    "sg:city":"Breda",
    "sg:orig_category":"Fabrica De Cer\u00c1micas",
    "sg:phone":"+34 972 87 04 33",
    "sg:postcode":"17400",
    "sg:province":"Girona",
    "wof:name":"Ceramiques La Pe\u00e7a",
    "wof:placetype":"venue"
},
  "geometry": {"coordinates":[2.5548899174,41.7563591003],"type":"Point"}
}