{
  "type": "Feature",
  "properties": {
    "addr:full":"Carr Pont Major, 75 Girona Girona 17007",
    "addr:housenumber":"75",
    "addr:postcode":"17007",
    "addr:street":"Carr Pont Major",
    "iso:country":"ES",
    "sg:address":"Carr Pont Major, 75",
    "sg:city":"Girona",
    "sg:orig_category":"Iglesia Cat\u00d3lica",
    "sg:phone":"+34 972 21 90 16",
    "sg:postcode":"17007",
    "sg:province":"Girona",
    "wof:name":"Bisbat De Girona",
    "wof:placetype":"venue"
},
  "geometry": {"coordinates":[2.8254549503,42.0123634338],"type":"Point"}
}