{
  "type": "Feature",
  "properties": {
    "iso:country":"ES",
    "sg:address":"Avgd Colon, 40",
    "sg:city":"Alcasser",
    "sg:orig_category":"Sociedades, Compa\u00d1\u00cdas Aseguradoras",
    "sg:phone":"+34 961 24 04 82",
    "sg:postcode":"46290",
    "sg:province":"Valencia",
    "wof:name":"Correduria De Seguros Frances Y Cab S.l.",
    "wof:placetype":"venue"
},
  "geometry": {"coordinates":[-0.443836987,39.3657035828],"type":"Point"}
}