{
  "type": "Feature",
  "properties": {
    "iso:country":"ES",
    "sg:address":"Calle de Carril Del Conde, 106",
    "sg:city":"Madrid",
    "sg:orig_category":"Caf\u00c9s, Bares, Cervecer\u00cdas",
    "sg:phone":"+34 917 59 45 38",
    "sg:postcode":"28043",
    "sg:province":"Madrid",
    "wof:name":"Alonso Mu\u00f1oz Jesus",
    "wof:placetype":"venue"
},
  "geometry": {"coordinates":[-3.6530482769,40.4629936218],"type":"Point"}
}