{
  "type": "Feature",
  "properties": {
    "iso:country":"ES",
    "sg:address":"Plaz Espa\u00d1a, 15",
    "sg:city":"Casarrubios Monte",
    "sg:orig_category":"Molduras, Junquillos, Listones Y Molduras Perforadas",
    "sg:phone":"+34 918 17 21 29",
    "sg:postcode":"45950",
    "sg:province":"Toledo",
    "wof:name":"Sanchez Prieto Julio",
    "wof:placetype":"venue"
},
  "geometry": {"coordinates":[-4.0399508476,40.1880645752],"type":"Point"}
}