{
  "type": "Feature",
  "properties": {
    "iso:country":"ES",
    "sg:address":"Calle de Velazquez, 5",
    "sg:city":"Segovia",
    "sg:orig_category":"Mec\u00c1nico Del Autom\u00d3vil",
    "sg:phone":"+34 921 42 98 13",
    "sg:postcode":"40002",
    "sg:province":"Segovia",
    "wof:name":"Monedero Sastre Teodoro",
    "wof:placetype":"venue"
},
  "geometry": {"coordinates":[-4.115858078,40.940284729],"type":"Point"}
}