{
  "type": "Feature",
  "properties": {
    "iso:country":"ES",
    "sg:address":"Carr Joan Alcover, Escriptor, 57",
    "sg:city":"Alaro",
    "sg:orig_category":"Empresas De Carpinter\u00cda De Madera",
    "sg:phone":"+34 971 51 03 48",
    "sg:postcode":"07340",
    "sg:province":"Islas Baleares",
    "wof:name":"Fusteria Isern S.l.",
    "wof:placetype":"venue"
},
  "geometry": {"coordinates":[2.7967810631,39.7019004822],"type":"Point"}
}