{
  "type": "Feature",
  "properties": {
    "iso:country":"ES",
    "sg:address":"Aero-club, S/n",
    "sg:city":"Fuentemilanos",
    "sg:orig_category":"Industrias Aeron\u00c1uticas Y Espaciales",
    "sg:phone":"+34 921 12 00 92",
    "sg:postcode":"40153",
    "sg:province":"Segovia",
    "wof:name":"Aeronautica Del Guadarrama S.a.",
    "wof:placetype":"venue"
},
  "geometry": {"coordinates":[-4.2289366722,40.876663208],"type":"Point"}
}