{
  "type": "Feature",
  "properties": {
    "addr:full":"Pase Tomas Morales, 140 Palmas De Gran Canaria Las Palmas 35004",
    "addr:housenumber":"140",
    "addr:postcode":"35004",
    "addr:street":"Tomas Morales",
    "iso:country":"ES",
    "sg:address":"Pase Tomas Morales, 140",
    "sg:city":"Palmas De Gran Canaria",
    "sg:orig_category":"Apicultura",
    "sg:phone":"+34 928 24 09 54",
    "sg:postcode":"35004",
    "sg:province":"Las Palmas",
    "wof:name":"Vilardaga Gonzalez Oscar",
    "wof:placetype":"venue"
},
  "geometry": {"coordinates":[-15.4275131226,28.1186351776],"type":"Point"}
}