{
  "type": "Feature",
  "properties": {
    "iso:country":"ES",
    "sg:address":"Rond Santa Maria, 279",
    "sg:city":"Barbera Valles",
    "sg:orig_category":"Panader\u00cdas, Panader\u00cdas",
    "sg:phone":"+34 937 18 74 51",
    "sg:postcode":"08210",
    "sg:province":"Barcelona",
    "wof:name":"Pozo Soldado Juan Francisco",
    "wof:placetype":"venue"
},
  "geometry": {"coordinates":[2.1271760464,41.5150566101],"type":"Point"}
}