{
  "type": "Feature",
  "properties": {
    "addr:full":"Ctra. Roquetas De Mar, 68 S. Agustin Almer\u00eda 04700",
    "addr:housenumber":"68",
    "addr:postcode":"04700",
    "addr:street":"Ctra. Roquetas De Mar;S. Agustin Almeri\u0301A",
    "iso:country":"ES",
    "sg:address":"Ctra. Roquetas De Mar, 68",
    "sg:city":"S. Agustin",
    "sg:orig_category":"Frutas Y Legumbres Frescas (al Por Mayor)",
    "sg:phone":"+34 950 53 62 24",
    "sg:postcode":"04700",
    "sg:province":"Almer\u00eda",
    "wof:name":"Sat Costa De Almeria",
    "wof:placetype":"venue"
},
  "geometry": {"coordinates":[-2.8176040649,36.7727012634],"type":"Point"}
}