{
  "type": "Feature",
  "properties": {
    "iso:country":"ES",
    "sg:address":"Calle de Trento, 8",
    "sg:city":"Alacant",
    "sg:orig_category":"Lecher\u00cdas",
    "sg:phone":"+34 965 17 02 50",
    "sg:postcode":"03011",
    "sg:province":"Alicante",
    "wof:name":"Parmalat S.a.",
    "wof:placetype":"venue"
},
  "geometry": {"coordinates":[-0.4987899959,38.3777122498],"type":"Point"}
}