{
  "type": "Feature",
  "properties": {
    "iso:country":"ES",
    "sg:address":"Carrer de Cesar, 10",
    "sg:city":"Can Pastilla",
    "sg:orig_category":"Molduras, Junquillos, Listones Y Molduras Perforadas",
    "sg:phone":"+34 971 26 37 01",
    "sg:postcode":"07610",
    "sg:province":"Islas Baleares",
    "wof:name":"Rebollero Nieto Juan",
    "wof:placetype":"venue"
},
  "geometry": {"coordinates":[2.7174329758,39.535118103],"type":"Point"}
}