{
  "type": "Feature",
  "properties": {
    "iso:country":"ES",
    "sg:address":"Avda Constitucion (la), 37",
    "sg:city":"Pizarra",
    "sg:orig_category":"Electrodom\u00c9sticos (al Por Menor)",
    "sg:phone":"+34 952 48 43 71",
    "sg:postcode":"29560",
    "sg:province":"M\u00e1laga",
    "wof:name":"Electrodomesticos Chira S.l.",
    "wof:placetype":"venue"
},
  "geometry": {"coordinates":[-4.7090549469,36.7646446228],"type":"Point"}
}