{
  "type": "Feature",
  "properties": {
    "addr:full":"Avda Vigo, 158 Ferrol La Coru\u00f1a 15403",
    "addr:housenumber":"158",
    "addr:postcode":"15403",
    "addr:street":"Avda Vigo;La Corun\u0303A",
    "iso:country":"ES",
    "sg:address":"Avda Vigo, 158",
    "sg:city":"Ferrol",
    "sg:orig_category":"Reposter\u00cdas",
    "sg:phone":"+34 981 32 73 92",
    "sg:postcode":"15403",
    "sg:province":"La Coru\u00f1a",
    "wof:name":"Panaderia Santa Rita S.l.",
    "wof:placetype":"venue"
},
  "geometry": {"coordinates":[-8.2262935638,43.4850158691],"type":"Point"}
}