{
  "type": "Feature",
  "properties": {
    "addr:full":"Avda Bierzo (el), Km. 0000,5 Dehesas Le\u00f3n 24390",
    "addr:housenumber":"leo\u0301n",
    "addr:postcode":"24390",
    "addr:street":"Avda Bierzo El Km. 0000,5 Dehesas",
    "iso:country":"ES",
    "sg:address":"Avda Bierzo (el), Km. 0000,5",
    "sg:city":"Dehesas",
    "sg:orig_category":"Arenas, Guijarros Y Granulados",
    "sg:phone":"+34 987 41 34 40",
    "sg:postcode":"24390",
    "sg:province":"Le\u00f3n",
    "wof:name":"Nuevos Metodos De Organizacion S.a.",
    "wof:placetype":"venue"
},
  "geometry": {"coordinates":[-6.6797690392,42.5274391174],"type":"Point"}
}