{
  "type": "Feature",
  "properties": {
    "iso:country":"ES",
    "sg:address":"Carrer de Denia, 5",
    "sg:city":"Mutxamel",
    "sg:orig_category":"Empresarios Y Productoras De Espect\u00c1culos",
    "sg:phone":"+34 965 95 55 94",
    "sg:postcode":"03110",
    "sg:province":"Alicante",
    "wof:name":"Anima't 2003 S.l",
    "wof:placetype":"venue"
},
  "geometry": {"coordinates":[-0.4482038915,38.4209136963],"type":"Point"}
}