{
  "type": "Feature",
  "properties": {
    "addr:full":"Calle de Triste Condesa, 8 Arenas San Pedro \u00c1vila 05400",
    "addr:housenumber":"8",
    "addr:postcode":"05400",
    "addr:street":"Calle De Triste Condesa;A\u0301Vila",
    "iso:country":"ES",
    "sg:address":"Calle de Triste Condesa, 8",
    "sg:city":"Arenas San Pedro",
    "sg:orig_category":"Asesor\u00cda Sobre Comunicaci\u00d3n De Empresas",
    "sg:phone":"+34 920 37 60 20",
    "sg:postcode":"05400",
    "sg:province":"\u00c1vila",
    "wof:name":"Blanco Recio Jesus",
    "wof:placetype":"venue"
},
  "geometry": {"coordinates":[-5.0897769928,40.2096328735],"type":"Point"}
}