{
  "type": "Feature",
  "properties": {
    "iso:country":"ES",
    "sg:address":"Calle de Maria Teresa Saenz De Heredia, 46",
    "sg:city":"Madrid",
    "sg:orig_category":"Supermercados Y Hipermercados",
    "sg:phone":"+34 914 04 28 42",
    "sg:postcode":"28017",
    "sg:province":"Madrid",
    "wof:name":"Todymas S. A.",
    "wof:placetype":"venue"
},
  "geometry": {"coordinates":[-3.6507120132,40.4256591797],"type":"Point"}
}