{
  "type": "Feature",
  "properties": {
    "iso:country":"ES",
    "sg:address":"Calle de Puerta De Aguilar, 41",
    "sg:city":"Montilla",
    "sg:orig_category":"Animales (al Por Menor)",
    "sg:phone":"+34 957 65 09 98",
    "sg:postcode":"14550",
    "sg:province":"C\u00f3rdoba",
    "wof:name":"Ruz Arrabal Manoli",
    "wof:placetype":"venue"
},
  "geometry": {"coordinates":[-4.6410508156,37.5852546692],"type":"Point"}
}