{
  "type": "Feature",
  "properties": {
    "iso:country":"ES",
    "sg:address":"Calle de Ejercito Espa\u00d1ol, 30",
    "sg:city":"Candeleda",
    "sg:orig_category":"M\u00c9dicos: Naturistas",
    "sg:phone":"+34 920 38 03 93",
    "sg:postcode":"05480",
    "sg:province":"\u00c1vila",
    "wof:name":"Sanchez Guzman Concepcion",
    "wof:placetype":"venue"
},
  "geometry": {"coordinates":[-5.2427887917,40.1571578979],"type":"Point"}
}