{
  "type": "Feature",
  "properties": {
    "addr:full":"Calle de Serrano, 33 Madrid Madrid 28001",
    "addr:housenumber":"33",
    "addr:postcode":"madrid;28001",
    "addr:street":"Calle De Serrano",
    "iso:country":"ES",
    "sg:address":"Calle de Serrano, 33",
    "sg:city":"Madrid",
    "sg:orig_category":"Ropa Para Se\u00d1oras (al Por Menor)",
    "sg:phone":"+34 915 76 86 99",
    "sg:postcode":"28001",
    "sg:province":"Madrid",
    "sg:website":"www.simorra.com",
    "wof:name":"Simorra Tiendas S.a.",
    "wof:placetype":"venue"
},
  "geometry": {"coordinates":[-3.6875910759,40.4276542664],"type":"Point"}
}