{
  "type": "Feature",
  "properties": {
    "iso:country":"ES",
    "sg:address":"Calle de Real, 77",
    "sg:city":"Villasinta Torio",
    "sg:orig_category":"Almacenes Frigor\u00cdficos",
    "sg:phone":"+34 987 28 72 00",
    "sg:postcode":"24193",
    "sg:province":"Le\u00f3n",
    "wof:name":"Puente Hermanos S.l.",
    "wof:placetype":"venue"
},
  "geometry": {"coordinates":[-5.5629849434,42.6257247925],"type":"Point"}
}