{
  "type": "Feature",
  "properties": {
    "iso:country":"ES",
    "sg:address":"Calle de Ceuta, 15",
    "sg:city":"San Sebastian De Los Reyes",
    "sg:orig_category":"Electricidad Veh\u00cdculo",
    "sg:phone":"+34 916 63 96 18",
    "sg:postcode":"28700",
    "sg:province":"Madrid",
    "wof:name":"Garcia Gomez Gregorio",
    "wof:placetype":"venue"
},
  "geometry": {"coordinates":[-3.6257879734,40.5577888489],"type":"Point"}
}