{
  "type": "Feature",
  "properties": {
    "iso:country":"ES",
    "sg:address":"Calle de Rio Polendos, S/n",
    "sg:city":"Caba\u00e7as De Polendos",
    "sg:orig_category":"Fabrica, Negocio De Vidrieras, Productos Vidriados Y Espejos",
    "sg:phone":"+34 921 49 64 56",
    "sg:postcode":"40392",
    "sg:province":"Segovia",
    "wof:name":"Mateo Manso Maria Eustolia",
    "wof:placetype":"venue"
},
  "geometry": {"coordinates":[-4.1110491753,41.0675163269],"type":"Point"}
}