{
  "type": "Feature",
  "properties": {
    "addr:full":"Carrer de Nanses, 1 Can Pastilla Islas Baleares 07610",
    "addr:housenumber":"1",
    "addr:postcode":"07610",
    "addr:street":"Carrer De Nanses",
    "iso:country":"ES",
    "sg:address":"Carrer de Nanses, 1",
    "sg:city":"Can Pastilla",
    "sg:orig_category":"Molduras, Junquillos, Listones Y Molduras Perforadas",
    "sg:phone":"+34 971 49 07 03",
    "sg:postcode":"07610",
    "sg:province":"Islas Baleares",
    "wof:name":"Redondo Tobarias Juan",
    "wof:placetype":"venue"
},
  "geometry": {"coordinates":[2.7122409344,39.5352859497],"type":"Point"}
}