{
  "type": "Feature",
  "properties": {
    "addr:full":"Calle de Mar (la), 43 Colindres Cantabria 39750",
    "addr:housenumber":"43",
    "addr:postcode":"39750",
    "addr:street":"Calle De Mar La",
    "iso:country":"ES",
    "sg:address":"Calle de Mar (la), 43",
    "sg:city":"Colindres",
    "sg:orig_category":"Caf\u00c9s, Bares, Cervecer\u00cdas",
    "sg:phone":"+34 942 65 01 70",
    "sg:postcode":"39750",
    "sg:province":"Cantabria",
    "wof:name":"Alonso Ortiz Ana Maria",
    "wof:placetype":"venue"
},
  "geometry": {"coordinates":[-3.4604268074,43.3935890198],"type":"Point"}
}