{
  "type": "Feature",
  "properties": {
    "addr:full":"Avda Hermanos Noain, 2 Ansoain Navarra 31013",
    "addr:housenumber":"2",
    "addr:postcode":"31013",
    "addr:street":"Avda Hermanos Noain",
    "iso:country":"ES",
    "sg:address":"Avda Hermanos Noain, 2",
    "sg:city":"Ansoain",
    "sg:orig_category":"Cajas De Ahorro",
    "sg:phone":"+34 948 14 12 99",
    "sg:postcode":"31013",
    "sg:province":"Navarra",
    "wof:name":"Caixa D'estalvis I Pensions De Barcelona",
    "wof:placetype":"venue"
},
  "geometry": {"coordinates":[-1.6404349804,42.8332252502],"type":"Point"}
}