{
  "type": "Feature",
  "properties": {
    "iso:country":"ES",
    "sg:address":"Carrer de Sant Pere, 21",
    "sg:city":"Crevillent",
    "sg:orig_category":"Mec\u00c1nico Del Autom\u00d3vil",
    "sg:phone":"+34 965 40 16 14",
    "sg:postcode":"03330",
    "sg:province":"Alicante",
    "wof:name":"Lledo Merino Miguel",
    "wof:placetype":"venue"
},
  "geometry": {"coordinates":[-0.804840982,38.247177124],"type":"Point"}
}