{
  "type": "Feature",
  "properties": {
    "iso:country":"ES",
    "sg:address":"Carrer de Gomis, 82",
    "sg:city":"Barcelona",
    "sg:orig_category":"Farmacias",
    "sg:phone":"+34 934 17 08 10",
    "sg:postcode":"08023",
    "sg:province":"Barcelona",
    "wof:name":"Bas Serra Teresa",
    "wof:placetype":"venue"
},
  "geometry": {"coordinates":[2.1397778988,41.4137115479],"type":"Point"}
}