{
  "type": "Feature",
  "properties": {
    "iso:country":"ES",
    "sg:address":"Calle de Tomas Breton, 21",
    "sg:city":"Zaragoza",
    "sg:orig_category":"Molduras, Junquillos, Listones Y Molduras Perforadas",
    "sg:phone":"+34 976 56 50 04",
    "sg:postcode":"50005",
    "sg:province":"Zaragoza",
    "wof:name":"Mil Cuatrocientos Noventa Y Dos S.cv.",
    "wof:placetype":"venue"
},
  "geometry": {"coordinates":[-0.8956999779,41.6443557739],"type":"Point"}
}