{
  "type": "Feature",
  "properties": {
    "addr:full":"Send Jose Pablo Ulibarri, 6 Vitoria-gasteiz \u00c1lava 01002",
    "addr:housenumber":"6",
    "addr:postcode":"01002",
    "addr:street":"Send Jose Pablo Ulibarri",
    "iso:country":"ES",
    "sg:address":"Send Jose Pablo Ulibarri, 6",
    "sg:city":"Vitoria-gasteiz",
    "sg:orig_category":"Peluquer\u00cdas, Peluquer\u00cda Mixta",
    "sg:phone":"+34 945 25 87 71",
    "sg:postcode":"01002",
    "sg:province":"\u00c1lava",
    "wof:name":"Oihana Gomez Martinez De Marigorta",
    "wof:placetype":"venue"
},
  "geometry": {"coordinates":[-2.662416935,42.8537063599],"type":"Point"}
}