{
  "type": "Feature",
  "properties": {
    "addr:full":"Carrer de Arx Lluis Salvador, 74 Palma Islas Baleares 07004",
    "addr:housenumber":"74",
    "addr:postcode":"07004",
    "addr:street":"Carrer De Arx Lluis Salvador",
    "iso:country":"ES",
    "sg:address":"Carrer de Arx Lluis Salvador, 74",
    "sg:city":"Palma",
    "sg:orig_category":"Agencias De Viajes",
    "sg:phone":"+34 971 75 65 92",
    "sg:postcode":"07004",
    "sg:province":"Islas Baleares",
    "wof:name":"Viajes Canals S.a.",
    "wof:placetype":"venue"
},
  "geometry": {"coordinates":[2.6564869881,39.5828971863],"type":"Point"}
}