{
  "type": "Feature",
  "properties": {
    "addr:full":"Carr Pare Espuig, 14 Villarreal Castell\u00f3n 12540",
    "addr:housenumber":"14",
    "addr:postcode":"12540",
    "addr:street":"Carr Pare Espuig",
    "iso:country":"ES",
    "sg:address":"Carr Pare Espuig, 14",
    "sg:city":"Villarreal",
    "sg:orig_category":"Agencias Y Agentes Comerciales, Representantes",
    "sg:phone":"+34 964 52 50 27",
    "sg:postcode":"12540",
    "sg:province":"Castell\u00f3n",
    "wof:name":"Batalla Torres Juan Vicente",
    "wof:placetype":"venue"
},
  "geometry": {"coordinates":[-0.0952939987,39.9453048706],"type":"Point"}
}