{
  "type": "Feature",
  "properties": {
    "iso:country":"ES",
    "sg:address":"Carrer de Roger De Lluria, 86",
    "sg:city":"Barcelona",
    "sg:orig_category":"Abogados",
    "sg:phone":"+34 934 57 86 70",
    "sg:postcode":"08009",
    "sg:province":"Barcelona",
    "wof:name":"Cordoba Roda Juan",
    "wof:placetype":"venue"
},
  "geometry": {"coordinates":[2.166162014,41.395362854],"type":"Point"}
}