{
  "type": "Feature",
  "properties": {
    "iso:country":"ES",
    "sg:address":"Avda Llanos De Nava, S/n",
    "sg:city":"Navatejera",
    "sg:orig_category":"Caf\u00c9s, Bares, Cervecer\u00cdas",
    "sg:phone":"+34 987 28 51 20",
    "sg:postcode":"24008",
    "sg:province":"Le\u00f3n",
    "wof:name":"Ordas Pardo Angel",
    "wof:placetype":"venue"
},
  "geometry": {"coordinates":[-5.5550928116,42.6448745728],"type":"Point"}
}