{
  "type": "Feature",
  "properties": {
    "addr:full":"Carrer de Pujades, 228 Barcelona Barcelona 08005",
    "addr:housenumber":"228",
    "addr:postcode":"08005",
    "addr:street":"Carrer De Pujades",
    "iso:country":"ES",
    "sg:address":"Carrer de Pujades, 228",
    "sg:city":"Barcelona",
    "sg:orig_category":"Cajas De Ahorro",
    "sg:phone":"+34 934 85 00 36",
    "sg:postcode":"08005",
    "sg:province":"Barcelona",
    "sg:website":"www.caixagirona.es",
    "wof:name":"Caixa De Girona",
    "wof:placetype":"venue"
},
  "geometry": {"coordinates":[2.203109026,41.4033737183],"type":"Point"}
}