{
  "type": "Feature",
  "properties": {
    "addr:full":"Avda Condes De San Isidro, 2 Fuengirola M\u00e1laga 29640",
    "addr:housenumber":"2",
    "addr:postcode":"29640",
    "addr:street":"Avda Condes De San Isidro;Ma\u0301Laga",
    "iso:country":"ES",
    "sg:address":"Avda Condes De San Isidro, 2",
    "sg:city":"Fuengirola",
    "sg:orig_category":"Bisuter\u00cda, Joyer\u00cda, Relojer\u00cda (al Por Menor)",
    "sg:phone":"+34 952 46 45 76",
    "sg:postcode":"29640",
    "sg:province":"M\u00e1laga",
    "wof:name":"Roca Fortes Antonio",
    "wof:placetype":"venue"
},
  "geometry": {"coordinates":[-4.6269459724,36.5331535339],"type":"Point"}
}