{
  "type": "Feature",
  "properties": {
    "addr:full":"Arkaute, S/n Arcaute \u00c1lava 01192",
    "addr:housenumber":"/ n",
    "addr:postcode":"01192",
    "addr:street":"Arkaute S;Arcaute A\u0301Lava",
    "iso:country":"ES",
    "sg:address":"Arkaute, S/n",
    "sg:city":"Arcaute",
    "sg:orig_category":"Inform\u00c1tica (estudios, Servicios, Asesor\u00cda, Formaci\u00d3n)",
    "sg:phone":"+34 945 27 70 12",
    "sg:postcode":"01192",
    "sg:province":"\u00c1lava",
    "wof:name":"Ikt S.a.",
    "wof:placetype":"venue"
},
  "geometry": {"coordinates":[-2.6345989704,42.8502388],"type":"Point"}
}