{
  "type": "Feature",
  "properties": {
    "iso:country":"ES",
    "sg:address":"Carrer de Ricart, 15",
    "sg:city":"S. Adria Besos",
    "sg:orig_category":"Radiocomunicaciones, Telefon\u00cda M\u00d3vil, Radiomensajer\u00cda: Servicios, Comercializaci\u00d3n",
    "sg:phone":"+34 933 81 92 50",
    "sg:postcode":"08930",
    "sg:province":"Barcelona",
    "sg:website":"www.telefoniapymes.com",
    "wof:name":"Telefonia Pymes S.l.",
    "wof:placetype":"venue"
},
  "geometry": {"coordinates":[2.2153689861,41.4305000305],"type":"Point"}
}