{
  "type": "Feature",
  "properties": {
    "iso:country":"ES",
    "sg:address":"Carrer de Josep Carner, 11",
    "sg:city":"Granollers",
    "sg:orig_category":"Delegados, Agentes De Tr\u00c1nsito, Auxiliares De Transporte Internacional",
    "sg:phone":"+34 938 61 32 05",
    "sg:postcode":"08402",
    "sg:province":"Barcelona",
    "wof:name":"Cruz Sanchez Alberto",
    "wof:placetype":"venue"
},
  "geometry": {"coordinates":[2.2944350243,41.6076507568],"type":"Point"}
}