{
  "type": "Feature",
  "properties": {
    "iso:country":"ES",
    "sg:address":"Calle de Enrique De Las Morenas, 17",
    "sg:city":"Cabra",
    "sg:orig_category":"Reposter\u00cdas",
    "sg:phone":"+34 957 52 08 02",
    "sg:postcode":"14940",
    "sg:province":"C\u00f3rdoba",
    "wof:name":"Gonzalez Lara Manuel",
    "wof:placetype":"venue"
},
  "geometry": {"coordinates":[-4.4409022331,37.4717826843],"type":"Point"}
}