{
  "type": "Feature",
  "properties": {
    "addr:full":"Calle de Andres Mellado, 25 Madrid Madrid 28015",
    "addr:housenumber":"25",
    "addr:postcode":"madrid;28015",
    "addr:street":"Calle De Andres Mellado",
    "iso:country":"ES",
    "sg:address":"Calle de Andres Mellado, 25",
    "sg:city":"Madrid",
    "sg:orig_category":"Perfumer\u00cda (al Por Menor)",
    "sg:phone":"+34 915 43 31 38",
    "sg:postcode":"28015",
    "sg:province":"Madrid",
    "sg:website":"www.bodybell.com",
    "wof:name":"Iberica De Drogueria Y Perfumeria S.a.",
    "wof:placetype":"venue"
},
  "geometry": {"coordinates":[-3.7145204544,40.4327926636],"type":"Point"}
}