{
  "type": "Feature",
  "properties": {
    "addr:full":"Carrer de Xerric, 29 S. Cugat Valles Barcelona 08172",
    "addr:housenumber":"29",
    "addr:postcode":"08172",
    "addr:street":"Carrer De Xerric;S. Cugat Valles Barcelona",
    "iso:country":"ES",
    "sg:address":"Carrer de Xerric, 29",
    "sg:city":"S. Cugat Valles",
    "sg:orig_category":"\u00d3ptica: Instrumentos (fabricaci\u00d3n)",
    "sg:phone":"+34 935 89 61 61",
    "sg:postcode":"08172",
    "sg:province":"Barcelona",
    "wof:name":"Centre Optics",
    "wof:placetype":"venue"
},
  "geometry": {"coordinates":[2.0842399597,41.4679336548],"type":"Point"}
}