{
  "type": "Feature",
  "properties": {
    "addr:full":"Avda Sicilia, 30 Parquelagos Madrid 28420",
    "addr:housenumber":"30",
    "addr:postcode":"28420",
    "addr:street":"Avda Sicilia",
    "iso:country":"ES",
    "sg:address":"Avda Sicilia, 30",
    "sg:city":"Parquelagos",
    "sg:orig_category":"Aceites Y Grasas Alimentarias (fabricaci\u00d3n, Al Por Mayor)",
    "sg:phone":"+34 918 59 36 14",
    "sg:postcode":"28420",
    "sg:province":"Madrid",
    "wof:name":"El Soto De Ojeda S.l.",
    "wof:placetype":"venue"
},
  "geometry": {"coordinates":[-3.9661340714,40.598449707],"type":"Point"}
}