{
  "type": "Feature",
  "properties": {
    "iso:country":"ES",
    "sg:address":"Carrer de Sant Pere, 43",
    "sg:city":"Gava",
    "sg:orig_category":"Pescader\u00cdas (al Por Menor)",
    "sg:phone":"+34 936 38 32 65",
    "sg:postcode":"08850",
    "sg:province":"Barcelona",
    "wof:name":"Cruz Pavon Montserrat",
    "wof:placetype":"venue"
},
  "geometry": {"coordinates":[2.0032401085,41.3042831421],"type":"Point"}
}