{
  "type": "Feature",
  "properties": {
    "iso:country":"ES",
    "sg:address":"Calle de Antigona, 2",
    "sg:city":"Malaga",
    "sg:orig_category":"Caf\u00c9s, Bares, Cervecer\u00cdas",
    "sg:phone":"+34 952 10 91 28",
    "sg:postcode":"29010",
    "sg:province":"M\u00e1laga",
    "wof:name":"Cuellar Ortega Angel",
    "wof:placetype":"venue"
},
  "geometry": {"coordinates":[-4.4773640633,36.7196540833],"type":"Point"}
}