{
  "type": "Feature",
  "properties": {
    "addr:full":"Carrer de Agustina D'arago, 83 Amposta Tarragona 43870",
    "addr:housenumber":"83",
    "addr:postcode":"43870",
    "addr:street":"Carrer De Agustina D'Arago",
    "iso:country":"ES",
    "sg:address":"Carrer de Agustina D'arago, 83",
    "sg:city":"Amposta",
    "sg:orig_category":"Explotaci\u00d3n De Canteras",
    "sg:phone":"+34 977 70 05 72",
    "sg:postcode":"43870",
    "sg:province":"Tarragona",
    "wof:name":"Canteras Simo S.a.",
    "wof:placetype":"venue"
},
  "geometry": {"coordinates":[0.5754520297,40.7143516541],"type":"Point"}
}