{
  "type": "Feature",
  "properties": {
    "addr:full":"Urdaneta Kalea, 27 Ordizia Guip\u00f9zcoa 20240",
    "addr:housenumber":"27",
    "addr:postcode":"20240",
    "addr:street":"Urdaneta Kalea;Guipu\u0300Zcoa",
    "iso:country":"ES",
    "sg:address":"Urdaneta Kalea, 27",
    "sg:city":"Ordizia",
    "sg:orig_category":"Ropa Para Se\u00d1oras (al Por Menor)",
    "sg:phone":"+34 943 88 62 03",
    "sg:postcode":"20240",
    "sg:province":"Guip\u00f9zcoa",
    "wof:name":"Bego\u00f1a Cabezudo Uharte",
    "wof:placetype":"venue"
},
  "geometry": {"coordinates":[-2.1818759441,43.0536193848],"type":"Point"}
}