{
  "type": "Feature",
  "properties": {
    "addr:full":"Calle de Angustias, 21 Moguer Huelva 21800",
    "addr:housenumber":"21",
    "addr:postcode":"21800",
    "addr:street":"Calle De Angustias",
    "iso:country":"ES",
    "sg:address":"Calle de Angustias, 21",
    "sg:city":"Moguer",
    "sg:orig_category":"Carnicer\u00cdas, Carnicer\u00cdas",
    "sg:phone":"+34 959 37 10 26",
    "sg:postcode":"21800",
    "sg:province":"Huelva",
    "wof:name":"Diego Ponce Dionisio",
    "wof:placetype":"venue"
},
  "geometry": {"coordinates":[-6.8384485245,37.2719078064],"type":"Point"}
}