{
  "type": "Feature",
  "properties": {
    "addr:full":"Carrer de Nou De La Rambla, 25 Barcelona Barcelona 08001",
    "addr:housenumber":"25",
    "addr:postcode":"08001",
    "addr:street":"Carrer De Nou De La Rambla",
    "iso:country":"ES",
    "sg:address":"Carrer de Nou De La Rambla, 25",
    "sg:city":"Barcelona",
    "sg:orig_category":"Inform\u00c1tica: Consultores",
    "sg:phone":"+34 933 18 06 16",
    "sg:postcode":"08001",
    "sg:province":"Barcelona",
    "wof:name":"Vazquez Varela Carmen",
    "wof:placetype":"venue"
},
  "geometry": {"coordinates":[2.1733250618,41.3780975342],"type":"Point"}
}