{
  "type": "Feature",
  "properties": {
    "addr:full":"Carrer de Onze De Setembre (l'), 39 Corro D'avall Barcelona 08520",
    "addr:housenumber":"39",
    "addr:postcode":"08520",
    "addr:street":"Carrer De Onze De Setembre L ';D'Avall Barcelona",
    "iso:country":"ES",
    "sg:address":"Carrer de Onze De Setembre (l'), 39",
    "sg:city":"Corro D'avall",
    "sg:orig_category":"Centros Empresariales",
    "sg:phone":"+34 938 40 32 53",
    "sg:postcode":"08520",
    "sg:province":"Barcelona",
    "wof:name":"Riera Peicasat Rosa",
    "wof:placetype":"venue"
},
  "geometry": {"coordinates":[2.1453080177,41.3764686584],"type":"Point"}
}