{
  "type": "Feature",
  "properties": {
    "addr:full":"Calle de Avicena, 31 Alcala Guadaira Sevilla 41500",
    "addr:housenumber":"31",
    "addr:postcode":"41500",
    "addr:street":"Calle De Avicena",
    "iso:country":"ES",
    "sg:address":"Calle de Avicena, 31",
    "sg:city":"Alcala Guadaira",
    "sg:orig_category":"Ense\u00d1anza Variada",
    "sg:phone":"+34 955 68 07 86",
    "sg:postcode":"41500",
    "sg:province":"Sevilla",
    "wof:name":"Centro De Formacion Antaya S.l",
    "wof:placetype":"venue"
},
  "geometry": {"coordinates":[-5.8506813049,37.3371086121],"type":"Point"}
}