{
  "type": "Feature",
  "properties": {
    "addr:full":"Calle de Mayor, 11 Villabona Guip\u00f9zcoa 20150",
    "addr:housenumber":"11",
    "addr:postcode":"20150",
    "addr:street":"Calle De Mayor;Guipu\u0300Zcoa",
    "iso:country":"ES",
    "sg:address":"Calle de Mayor, 11",
    "sg:city":"Villabona",
    "sg:orig_category":"Transporte En General",
    "sg:phone":"+34 943 69 18 22",
    "sg:postcode":"20150",
    "sg:province":"Guip\u00f9zcoa",
    "wof:name":"Maite Ortiz Garcia",
    "wof:placetype":"venue"
},
  "geometry": {"coordinates":[-2.0486390591,43.2030830383],"type":"Point"}
}