{
  "type": "Feature",
  "properties": {
    "addr:full":"Calle de Bartolome Torres Naharro, 3 Merida Badajoz 06800",
    "addr:housenumber":"3",
    "addr:postcode":"06800",
    "addr:street":"Calle De Bartolome Torres Naharro",
    "iso:country":"ES",
    "sg:address":"Calle de Bartolome Torres Naharro, 3",
    "sg:city":"Merida",
    "sg:orig_category":"Promotores Constructores",
    "sg:phone":"+34 924 37 40 79",
    "sg:postcode":"06800",
    "sg:province":"Badajoz",
    "wof:name":"Kantrila S.l.",
    "wof:placetype":"venue"
},
  "geometry": {"coordinates":[-6.3376741409,38.9097061157],"type":"Point"}
}