{
  "type": "Feature",
  "properties": {
    "addr:full":"Calle de Gregorio Ortiz, 26 Madrid Madrid 28021",
    "addr:housenumber":"26",
    "addr:postcode":"madrid;28021",
    "addr:street":"Calle De Gregorio Ortiz",
    "iso:country":"ES",
    "sg:address":"Calle de Gregorio Ortiz, 26",
    "sg:city":"Madrid",
    "sg:orig_category":"Fabricaci\u00d3n De Peines Y De Accesorios De Peluquer\u00cda",
    "sg:phone":"+34 917 96 00 37",
    "sg:postcode":"28021",
    "sg:province":"Madrid",
    "wof:name":"Agudo Mendez Maria Carmen",
    "wof:placetype":"venue"
},
  "geometry": {"coordinates":[-3.7091128826,40.3444442749],"type":"Point"}
}