{
  "type": "Feature",
  "properties": {
    "addr:full":"Calle de San Lorenzo, 4 Huesca Huesca 22002",
    "addr:housenumber":"4",
    "addr:postcode":"22002",
    "addr:street":"Calle De San Lorenzo",
    "iso:country":"ES",
    "sg:address":"Calle de San Lorenzo, 4",
    "sg:city":"Huesca",
    "sg:orig_category":"Florister\u00cdas",
    "sg:phone":"+34 974 24 33 43",
    "sg:postcode":"22002",
    "sg:province":"Huesca",
    "wof:name":"Pardo Lancina Sonia",
    "wof:placetype":"venue"
},
  "geometry": {"coordinates":[-0.406423986,42.1365127563],"type":"Point"}
}