{
  "type": "Feature",
  "properties": {
    "iso:country":"ES",
    "sg:address":"Pase Espa\u00d1a (de), 24",
    "sg:city":"Jaen",
    "sg:orig_category":"Asesor\u00cda, Estudio Y Control Medioambiental",
    "sg:phone":"+34 953 22 18 22",
    "sg:postcode":"23008",
    "sg:province":"Ja\u00e9n",
    "wof:name":"Consultoria En Caridad Medio Ambiente Y Prevencion Sl",
    "wof:placetype":"venue"
},
  "geometry": {"coordinates":[-3.7906870842,37.7650947571],"type":"Point"}
}