{
  "type": "Feature",
  "properties": {
    "iso:country":"ES",
    "sg:address":"Calle de Castillo De Aledo, S/n",
    "sg:city":"Altorreal",
    "sg:orig_category":"Promotores Constructores",
    "sg:phone":"+34 968 60 45 61",
    "sg:postcode":"30500",
    "sg:province":"Murcia",
    "wof:name":"Constructora San Jose S.a.",
    "wof:placetype":"venue"
},
  "geometry": {"coordinates":[-1.1625410318,38.0750656128],"type":"Point"}
}