{
  "type": "Feature",
  "properties": {
    "addr:full":"Calle de Benavente, 2 Candeleda \u00c1vila 05480",
    "addr:housenumber":"2",
    "addr:postcode":"05480",
    "addr:street":"Calle De Benavente",
    "iso:country":"ES",
    "sg:address":"Calle de Benavente, 2",
    "sg:city":"Candeleda",
    "sg:orig_category":"Institutos De Belleza",
    "sg:phone":"+34 920 38 21 89",
    "sg:postcode":"05480",
    "sg:province":"\u00c1vila",
    "wof:name":"Jimenez Gonzalez Maria Cruz",
    "wof:placetype":"venue"
},
  "geometry": {"coordinates":[-5.240249157,40.1574821472],"type":"Point"}
}