{
  "type": "Feature",
  "properties": {
    "addr:full":"Calle de Loiola, 4 Donostia-san Sebastian Guip\u00f9zcoa 20005",
    "addr:housenumber":"4",
    "addr:postcode":"20005",
    "addr:street":"Calle De Loiola",
    "iso:country":"ES",
    "sg:address":"Calle de Loiola, 4",
    "sg:city":"Donostia-san Sebastian",
    "sg:orig_category":"Bisuter\u00cda, Joyer\u00cda, Relojer\u00cda (al Por Menor)",
    "sg:phone":"+34 943 42 89 53",
    "sg:postcode":"20005",
    "sg:province":"Guip\u00f9zcoa",
    "wof:name":"Olazabal Dendariarena Marta",
    "wof:placetype":"venue"
},
  "geometry": {"coordinates":[-1.9832539558,43.3187789917],"type":"Point"}
}