{
  "type": "Feature",
  "properties": {
    "addr:full":"Calle de Elbarren, 42 Leitza Navarra 31880",
    "addr:housenumber":"42",
    "addr:postcode":"31880",
    "addr:street":"Calle De Elbarren",
    "iso:country":"ES",
    "sg:address":"Calle de Elbarren, 42",
    "sg:city":"Leitza",
    "sg:orig_category":"Restaurantes",
    "sg:phone":"+34 948 51 00 52",
    "sg:postcode":"31880",
    "sg:province":"Navarra",
    "wof:name":"Zabaleta Bernarda Y Iparaguirre Javier S.cv",
    "wof:placetype":"venue"
},
  "geometry": {"coordinates":[-1.9146380424,43.0811347961],"type":"Point"}
}