{
  "type": "Feature",
  "properties": {
    "iso:country":"ES",
    "sg:address":"Ctra Mojonera, 116",
    "sg:city":"Norias De Daza",
    "sg:orig_category":"Bisuter\u00cda, Joyer\u00cda, Relojer\u00cda (al Por Menor)",
    "sg:phone":"+34 950 58 78 63",
    "sg:postcode":"04716",
    "sg:province":"Almer\u00eda",
    "wof:name":"Artes Rubio Ramon",
    "wof:placetype":"venue"
},
  "geometry": {"coordinates":[-2.7526004314,36.7587928772],"type":"Point"}
}