{
  "type": "Feature",
  "properties": {
    "iso:country":"ES",
    "sg:address":"Calle de Campo (del), 1",
    "sg:city":"Segovia",
    "sg:classifiers":[
        {
            "category":"Autos & Motor Vehicles",
            "subcategory":"Automobile Sales",
            "type":"Retail Goods"
        }
    ],
    "sg:phone":"+34 921 44 02 08",
    "sg:postcode":"40004",
    "sg:province":"Segovia",
    "wof:name":"Rojo De Frutos Jesus",
    "wof:placetype":"venue"
},
  "geometry": {"coordinates":[-4.1081604958,40.9467582703],"type":"Point"}
}