{
  "type": "Feature",
  "properties": {
    "iso:country":"ES",
    "sg:address":"Carrer de Corsega, 466",
    "sg:city":"Barcelona",
    "sg:orig_category":"M\u00c9dicos: Estomatolog\u00cda",
    "sg:phone":"+34 932 07 00 94",
    "sg:postcode":"08025",
    "sg:province":"Barcelona",
    "wof:name":"Geuna Mariani Cecilia",
    "wof:placetype":"venue"
},
  "geometry": {"coordinates":[2.1682770252,41.4031562805],"type":"Point"}
}