{
  "type": "Feature",
  "properties": {
    "addr:full":"Ctra. Madrid-irun, S/n Burgos Burgos 09001",
    "addr:housenumber":"s / n",
    "addr:postcode":"09001",
    "addr:street":"Ctra. Madrid-Irun",
    "iso:country":"ES",
    "sg:address":"Ctra. Madrid-irun, S/n",
    "sg:city":"Burgos",
    "sg:orig_category":"Ebanister\u00cda",
    "sg:phone":"+34 947 27 95 59",
    "sg:postcode":"09001",
    "sg:province":"Burgos",
    "wof:name":"Aranda Blanco Juan Carlos",
    "wof:placetype":"venue"
},
  "geometry": {"coordinates":[-3.7017037868,42.3211631775],"type":"Point"}
}