{
  "type": "Feature",
  "properties": {
    "addr:full":"Calle de Ricardo Del Arco, 3 Zaragoza Zaragoza 50015",
    "addr:housenumber":"3",
    "addr:postcode":"50015",
    "addr:street":"Calle De Ricardo Del Arco",
    "iso:country":"ES",
    "sg:address":"Calle de Ricardo Del Arco, 3",
    "sg:city":"Zaragoza",
    "sg:orig_category":"Peluquer\u00cdas, Peluquer\u00cda Mixta",
    "sg:phone":"+34 976 52 01 67",
    "sg:postcode":"50015",
    "sg:province":"Zaragoza",
    "wof:name":"Francisco Quintana Peluqueros S.l.",
    "wof:placetype":"venue"
},
  "geometry": {"coordinates":[-0.8761680126,41.659538269],"type":"Point"}
}