{
  "type": "Feature",
  "properties": {
    "addr:full":"Calle de Reina, 6 Valencia Valencia 46011",
    "addr:housenumber":"6",
    "addr:postcode":"46011",
    "addr:street":"Calle De Reina",
    "iso:country":"ES",
    "sg:address":"Calle de Reina, 6",
    "sg:city":"Valencia",
    "sg:orig_category":"Agencias De Aduana",
    "sg:phone":"+34 963 67 58 04",
    "sg:postcode":"46011",
    "sg:province":"Valencia",
    "wof:name":"Estellez Valencia S. A.",
    "wof:placetype":"venue"
},
  "geometry": {"coordinates":[-0.3292180002,39.4638710022],"type":"Point"}
}