{
  "type": "Feature",
  "properties": {
    "addr:full":"Calle de Carreras Bajas, 5 Caravaca Cruz Murcia 30400",
    "addr:housenumber":"5",
    "addr:postcode":"30400",
    "addr:street":"Calle De Carreras Bajas",
    "iso:country":"ES",
    "sg:address":"Calle de Carreras Bajas, 5",
    "sg:city":"Caravaca Cruz",
    "sg:orig_category":"Reposter\u00cdas",
    "sg:phone":"+34 968 70 78 67",
    "sg:postcode":"30400",
    "sg:province":"Murcia",
    "wof:name":"Panaderia El Gamba S.l.",
    "wof:placetype":"venue"
},
  "geometry": {"coordinates":[-1.8634773493,38.1081809998],"type":"Point"}
}