{
  "type": "Feature",
  "properties": {
    "iso:country":"ES",
    "sg:address":"Calle de Jose Manuel De Villena, 18",
    "sg:city":"Salamanca",
    "sg:orig_category":"Agencias De Viajes",
    "sg:phone":"+34 923 60 40 00",
    "sg:postcode":"37006",
    "sg:province":"Salamanca",
    "sg:website":"www.swimtravel.com",
    "wof:name":"Occidente Express S.l.",
    "wof:placetype":"venue"
},
  "geometry": {"coordinates":[-5.6646289825,40.9725379944],"type":"Point"}
}