{
  "type": "Feature",
  "properties": {
    "iso:country":"ES",
    "sg:address":"Avda General Mola (del), 90",
    "sg:city":"Santa Cruz De Tenerife",
    "sg:orig_category":"Centros M\u00c9dicos Y Sociales, Dispensarios",
    "sg:phone":"+34 922 21 11 33",
    "sg:postcode":"38007",
    "sg:province":"Santa Cruz De Tenerife",
    "wof:name":"Consultorio Medico Centro De Atencion Primaria Y Especializada S.l.",
    "wof:placetype":"venue"
},
  "geometry": {"coordinates":[-16.2668437958,28.4663257599],"type":"Point"}
}