{
  "type": "Feature",
  "properties": {
    "iso:country":"ES",
    "sg:address":"Iberre Edificio 12, 6",
    "sg:city":"Sondika",
    "sg:orig_category":"Transporte En General",
    "sg:phone":"+34 944 53 82 70",
    "sg:postcode":"48150",
    "sg:province":"Vizcaya",
    "sg:website":"www.almacenajesondika.com",
    "wof:name":"Almacenaje Y Distribucion Sondika",
    "wof:placetype":"venue"
},
  "geometry": {"coordinates":[-2.9325785637,43.2871627808],"type":"Point"}
}