{
  "type": "Feature",
  "properties": {
    "iso:country":"ES",
    "sg:address":"Avda Espa\u00d1a (de), S/n",
    "sg:city":"Ubrique",
    "sg:classifiers":[
        {
            "category":"Taxi",
            "type":"Transportation"
        }
    ],
    "sg:phone":"+34 956 46 00 55",
    "sg:postcode":"11600",
    "sg:province":"C\u00e1diz",
    "wof:name":"Agrupacion Local De Autonomos Del Taxi",
    "wof:placetype":"venue"
},
  "geometry": {"coordinates":[-5.4471139908,36.6747932434],"type":"Point"}
}