{
  "type": "Feature",
  "properties": {
    "addr:full":"Nueva-kale Berria, 6 Irurtzun Navarra 31860",
    "addr:housenumber":"6",
    "addr:postcode":"31860",
    "addr:street":"Berria",
    "iso:country":"ES",
    "sg:address":"Nueva-kale Berria, 6",
    "sg:city":"Irurtzun",
    "sg:classifiers":[
        {
            "category":"Autos & Motor Vehicles",
            "subcategory":"Automobile Sales",
            "type":"Retail Goods"
        }
    ],
    "sg:phone":"+34 948 60 06 21",
    "sg:postcode":"31860",
    "sg:province":"Navarra",
    "wof:name":"Machain Eugui Juan Miguel",
    "wof:placetype":"venue"
},
  "geometry": {"coordinates":[-1.8282489777,42.9185066223],"type":"Point"}
}