{
  "type": "Feature",
  "properties": {
    "addr:full":"Calle de Jazmin, 1 Motril Granada 18600",
    "addr:housenumber":"1",
    "addr:postcode":"18600",
    "addr:street":"Calle De Jazmin",
    "iso:country":"ES",
    "sg:address":"Calle de Jazmin, 1",
    "sg:city":"Motril",
    "sg:orig_category":"Centros Empresariales",
    "sg:phone":"+34 958 83 32 45",
    "sg:postcode":"18600",
    "sg:province":"Granada",
    "wof:name":"Aecost",
    "wof:placetype":"venue"
},
  "geometry": {"coordinates":[-3.5216095448,36.7459182739],"type":"Point"}
}