{
  "type": "Feature",
  "properties": {
    "addr:full":"Carrer de Santa Eulalia, 79 Hospitalet Llobregat Barcelona 08902",
    "addr:housenumber":"79",
    "addr:postcode":"08902",
    "addr:street":"Carrer De Santa Eulalia",
    "iso:country":"ES",
    "sg:address":"Carrer de Santa Eulalia, 79",
    "sg:city":"Hospitalet Llobregat",
    "sg:orig_category":"Cajas Para Embalar",
    "sg:phone":"+34 933 31 52 12",
    "sg:postcode":"08902",
    "sg:province":"Barcelona",
    "sg:website":"www.cajamar.es",
    "wof:name":"Cajamar",
    "wof:placetype":"venue"
},
  "geometry": {"coordinates":[2.1271660328,41.3670387268],"type":"Point"}
}