{
  "type": "Feature",
  "properties": {
    "addr:full":"Calle de Maestro Jose Alonso Barrio, 34 Bembibre Le\u00f3n 24300",
    "addr:housenumber":"34",
    "addr:postcode":"24300",
    "addr:street":"Calle De Maestro Jose Alonso Barrio;Leo\u0301N",
    "iso:country":"ES",
    "sg:address":"Calle de Maestro Jose Alonso Barrio, 34",
    "sg:city":"Bembibre",
    "sg:orig_category":"Reposter\u00cdas",
    "sg:phone":"+34 987 51 09 25",
    "sg:postcode":"24300",
    "sg:province":"Le\u00f3n",
    "wof:name":"Panaderia Martin Majan C.b.",
    "wof:placetype":"venue"
},
  "geometry": {"coordinates":[-6.4176287651,42.6184692383],"type":"Point"}
}