{
  "type": "Feature",
  "properties": {
    "iso:country":"ES",
    "sg:address":"Avda Aguirre Lehendakari, 85",
    "sg:city":"Bilbao",
    "sg:orig_category":"Caf\u00c9s, Bares, Cervecer\u00cdas",
    "sg:phone":"+34 944 47 90 49",
    "sg:postcode":"48015",
    "sg:province":"Vizcaya",
    "wof:name":"Amaia Lazkano Fernandez (bar Garlas)",
    "wof:placetype":"venue"
},
  "geometry": {"coordinates":[-2.9603738785,43.2761383057],"type":"Point"}
}