{
  "type": "Feature",
  "properties": {
    "addr:full":"Calle de Arane, 12 Bilbao Vizcaya 48012",
    "addr:housenumber":"12",
    "addr:postcode":"48012",
    "addr:street":"Calle De Arane",
    "iso:country":"ES",
    "sg:address":"Calle de Arane, 12",
    "sg:city":"Bilbao",
    "sg:orig_category":"Asesor\u00cda Fiscal Y Jur\u00cddica",
    "sg:phone":"+34 944 21 27 85",
    "sg:postcode":"48012",
    "sg:province":"Vizcaya",
    "wof:name":"Maria Bego\u00f1a Casas Sanchez Y Otros Cdad",
    "wof:placetype":"venue"
},
  "geometry": {"coordinates":[-2.9372081757,43.2501869202],"type":"Point"}
}