{
  "type": "Feature",
  "properties": {
    "iso:country":"ES",
    "sg:address":"Calle de Camarena, 121",
    "sg:city":"Madrid",
    "sg:orig_category":"Herboristas (al Por Menor)",
    "sg:phone":"+34 917 17 41 56",
    "sg:postcode":"28047",
    "sg:province":"Madrid",
    "wof:name":"Herpacu S.l.",
    "wof:placetype":"venue"
},
  "geometry": {"coordinates":[-3.7556602955,40.390789032],"type":"Point"}
}