{
  "type": "Feature",
  "properties": {
    "iso:country":"ES",
    "sg:address":"Calle de Fortuny, 24",
    "sg:city":"Alacant",
    "sg:orig_category":"Fabricaci\u00d3n De Material Y Sistemas De Se\u00d1alizaci\u00d3n De Carreteras, Urbanos Y De Obras",
    "sg:phone":"+34 965 17 08 87",
    "sg:postcode":"03009",
    "sg:province":"Alicante",
    "sg:website":"www.grupoetra.com",
    "wof:name":"Electronic Traffic S.a.",
    "wof:placetype":"venue"
},
  "geometry": {"coordinates":[-0.5039569736,38.3748245239],"type":"Point"}
}