{
  "type": "Feature",
  "properties": {
    "addr:full":"Calle de Sope\u00d1a, 43 Arguedas Navarra 31513",
    "addr:housenumber":"43",
    "addr:postcode":"31513",
    "addr:street":"Calle De Sopen\u0303A",
    "iso:country":"ES",
    "sg:address":"Calle de Sope\u00d1a, 43",
    "sg:city":"Arguedas",
    "sg:orig_category":"Agencias Y Agentes Comerciales, Representantes",
    "sg:phone":"+34 948 83 04 92",
    "sg:postcode":"31513",
    "sg:province":"Navarra",
    "wof:name":"Arriazu Marton S.l.",
    "wof:placetype":"venue"
},
  "geometry": {"coordinates":[-1.6054269075,42.1818084717],"type":"Point"}
}