{
  "type": "Feature",
  "properties": {
    "addr:full":"Ctra. Montijo, Km. 0002,0 Merida Badajoz 06800",
    "addr:postcode":"06800",
    "addr:street":"Ctra. Montijo Km. 0002,0",
    "iso:country":"ES",
    "sg:address":"Ctra. Montijo, Km. 0002,0",
    "sg:city":"Merida",
    "sg:orig_category":"Agencias Y Asesores De Publicidad",
    "sg:phone":"+34 924 30 06 62",
    "sg:postcode":"06800",
    "sg:province":"Badajoz",
    "wof:name":"Marketing Directo Publiex S.a.",
    "wof:placetype":"venue"
},
  "geometry": {"coordinates":[-6.3464841843,38.916053772],"type":"Point"}
}