{
  "type": "Feature",
  "properties": {
    "iso:country":"ES",
    "sg:address":"Calle de Baja, 16",
    "sg:city":"Nava",
    "sg:orig_category":"Ropa Para Se\u00d1oras Y Caballeros (al Por Menor)",
    "sg:phone":"+34 985 71 73 51",
    "sg:postcode":"33520",
    "sg:province":"Asturias",
    "wof:name":"La Farandula C.b.",
    "wof:placetype":"venue"
},
  "geometry": {"coordinates":[-5.5075230598,43.3581695557],"type":"Point"}
}