{
  "type": "Feature",
  "properties": {
    "addr:full":"Carrer de Josep Comas I Sola, 19 Manresa Barcelona 08243",
    "addr:housenumber":"19",
    "addr:postcode":"08243",
    "addr:street":"Carrer De Josep Comas I Sola",
    "iso:country":"ES",
    "sg:address":"Carrer de Josep Comas I Sola, 19",
    "sg:city":"Manresa",
    "sg:orig_category":"Delegados, Agentes De Tr\u00c1nsito, Auxiliares De Transporte Internacional",
    "sg:phone":"+34 938 77 23 22",
    "sg:postcode":"08243",
    "sg:province":"Barcelona",
    "wof:name":"Brunet Oliva S.l.",
    "wof:placetype":"venue"
},
  "geometry": {"coordinates":[1.8481860161,41.7118606567],"type":"Point"}
}