{
  "type": "Feature",
  "properties": {
    "iso:country":"ES",
    "sg:address":"Calle de Lopez De Hoyos, 153",
    "sg:city":"Madrid",
    "sg:orig_category":"Organizaciones Internacionales",
    "sg:phone":"+34 915 19 16 64",
    "sg:postcode":"28002",
    "sg:province":"Madrid",
    "sg:website":"www.lasbuenasintenciones.com",
    "wof:name":"Las Buenas Intenciones S.l.",
    "wof:placetype":"venue"
},
  "geometry": {"coordinates":[-3.6681940556,40.4483451843],"type":"Point"}
}