{
  "type": "Feature",
  "properties": {
    "addr:full":"Calle de Moral, 7 Adrada Piron Segovia 40192",
    "addr:housenumber":"7",
    "addr:postcode":"40192",
    "addr:street":"Calle De Moral",
    "iso:country":"ES",
    "sg:address":"Calle de Moral, 7",
    "sg:city":"Adrada Piron",
    "sg:orig_category":"Empresas De Desmonte",
    "sg:phone":"+34 921 40 40 29",
    "sg:postcode":"40192",
    "sg:province":"Segovia",
    "wof:name":"Escavaciones Pecharroman S.l.",
    "wof:placetype":"venue"
},
  "geometry": {"coordinates":[-4.0526518822,41.0524215698],"type":"Point"}
}