{
  "type": "Feature",
  "properties": {
    "addr:full":"Torreiro, S/n Torreiro Pontevedra 36460",
    "addr:housenumber":"s / n",
    "addr:postcode":"36460",
    "addr:street":"Torreiro",
    "iso:country":"ES",
    "sg:address":"Torreiro, S/n",
    "sg:city":"Torreiro",
    "sg:orig_category":"Pescader\u00cdas (al Por Menor)",
    "sg:phone":"+34 986 62 90 51",
    "sg:postcode":"36460",
    "sg:province":"Pontevedra",
    "wof:name":"Maemi\u00f1o S. L.",
    "wof:placetype":"venue"
},
  "geometry": {"coordinates":[-8.5616960526,42.057220459],"type":"Point"}
}