{
  "type": "Feature",
  "properties": {
    "addr:full":"Calle de Fraternidad, 23 Tias Las Palmas 35572",
    "addr:housenumber":"23",
    "addr:postcode":"35572",
    "addr:street":"Calle De Fraternidad",
    "iso:country":"ES",
    "sg:address":"Calle de Fraternidad, 23",
    "sg:city":"Tias",
    "sg:orig_category":"T\u00c9cnicos Veterinarios",
    "sg:phone":"+34 928 83 39 90",
    "sg:postcode":"35572",
    "sg:province":"Las Palmas",
    "wof:name":"Azcorra Salo\u00f1a Amelia Margarita",
    "wof:placetype":"venue"
},
  "geometry": {"coordinates":[-13.6546611786,28.9535884857],"type":"Point"}
}