{
  "type": "Feature",
  "properties": {
    "addr:full":"Av De La Constitucio, 64 Castalla Alicante 03420",
    "addr:housenumber":"64",
    "addr:postcode":"03420",
    "addr:street":"Av De La Constitucio",
    "iso:country":"ES",
    "sg:address":"Av De La Constitucio, 64",
    "sg:city":"Castalla",
    "sg:orig_category":"Asistencia Social",
    "sg:phone":"+34 965 56 10 00",
    "sg:postcode":"03420",
    "sg:province":"Alicante",
    "wof:name":"Ayuntamiento De Castalla",
    "wof:placetype":"venue"
},
  "geometry": {"coordinates":[-0.6707282066,38.5918617249],"type":"Point"}
}