{
  "type": "Feature",
  "properties": {
    "addr:full":"Avda Malvarrosa, 16 Valencia Valencia 46011",
    "addr:housenumber":"16",
    "addr:postcode":"46011",
    "addr:street":"Avda Malvarrosa",
    "iso:country":"ES",
    "sg:address":"Avda Malvarrosa, 16",
    "sg:city":"Valencia",
    "sg:orig_category":"Frutas, Legumbres Frescas Y Tempranas (al Por Menor)",
    "sg:phone":"+34 963 55 70 21",
    "sg:postcode":"46011",
    "sg:province":"Valencia",
    "wof:name":"Rio Dominguez Luis Del",
    "wof:placetype":"venue"
},
  "geometry": {"coordinates":[-0.3278639913,39.4772796631],"type":"Point"}
}