{
  "type": "Feature",
  "properties": {
    "addr:full":"Calle de Granada, 157 Puebla Del Rio Sevilla 41130",
    "addr:housenumber":"157",
    "addr:postcode":"41130",
    "addr:street":"Calle De Granada",
    "iso:country":"ES",
    "sg:address":"Calle de Granada, 157",
    "sg:city":"Puebla Del Rio",
    "sg:orig_category":"Maquinaria Para Industrias Diversas",
    "sg:phone":"+34 955 95 03 68",
    "sg:postcode":"41130",
    "sg:province":"Sevilla",
    "wof:name":"Clardy S.l.",
    "wof:placetype":"venue"
},
  "geometry": {"coordinates":[-6.0686588287,37.2622909546],"type":"Point"}
}