{
  "type": "Feature",
  "properties": {
    "addr:full":"Trueno, 62 Leganes Madrid 28918",
    "addr:housenumber":"62",
    "addr:postcode":"28918",
    "addr:street":"Trueno",
    "iso:country":"ES",
    "sg:address":"Trueno, 62",
    "sg:city":"Leganes",
    "sg:orig_category":"Fabricaci\u00d3n De Bibliotecas Y Estanter\u00cdas",
    "sg:phone":"+34 916 11 24 41",
    "sg:postcode":"28918",
    "sg:province":"Madrid",
    "sg:website":"www.decorequip.com",
    "wof:name":"Megaequip",
    "wof:placetype":"venue"
},
  "geometry": {"coordinates":[-3.7953839302,40.3483085632],"type":"Point"}
}