{
  "type": "Feature",
  "properties": {
    "iso:country":"ES",
    "sg:address":"Calle de Rosario, 27",
    "sg:city":"Teruel",
    "sg:orig_category":"Calefacci\u00d3n Central: Material (fabricaci\u00d3n, Al Por Mayor)",
    "sg:phone":"+34 978 60 40 50",
    "sg:postcode":"44003",
    "sg:province":"Teruel",
    "wof:name":"Garcia Redondo Eladio",
    "wof:placetype":"venue"
},
  "geometry": {"coordinates":[-1.1041560173,40.3409767151],"type":"Point"}
}