{
  "type": "Feature",
  "properties": {
    "addr:full":"Calle de Pintor Astorza Y Triay, 20 Alacant Alicante 03015",
    "addr:housenumber":"20",
    "addr:postcode":"03015",
    "addr:street":"Calle De Pintor Astorza Y Triay",
    "iso:country":"ES",
    "sg:address":"Calle de Pintor Astorza Y Triay, 20",
    "sg:city":"Alacant",
    "sg:orig_category":"Molduras, Junquillos, Listones Y Molduras Perforadas",
    "sg:phone":"+34 965 26 34 85",
    "sg:postcode":"03015",
    "sg:province":"Alicante",
    "wof:name":"Fernandez Alvarez Baltasar",
    "wof:placetype":"venue"
},
  "geometry": {"coordinates":[-0.4753470123,38.3707504272],"type":"Point"}
}