{
  "type": "Feature",
  "properties": {
    "addr:full":"Calle de Conde De Torrefiel, 26 Valencia Valencia 46019",
    "addr:housenumber":"26",
    "addr:postcode":"46019",
    "addr:street":"Calle De Conde De Torrefiel",
    "iso:country":"ES",
    "sg:address":"Calle de Conde De Torrefiel, 26",
    "sg:city":"Valencia",
    "sg:orig_category":"Peluqueros: De Se\u00d1oras",
    "sg:phone":"+34 963 65 43 30",
    "sg:postcode":"46019",
    "sg:province":"Valencia",
    "wof:name":"Ferrer Gimenez Salvador",
    "wof:placetype":"venue"
},
  "geometry": {"coordinates":[-0.3761047125,39.4931983948],"type":"Point"}
}