{
  "type": "Feature",
  "properties": {
    "iso:country":"ES",
    "sg:address":"Calle de General Vives, 1",
    "sg:city":"Palmas De Gran Canaria",
    "sg:orig_category":"Asesor\u00cda De Formaci\u00d3n Y Gesti\u00d3n De Personal",
    "sg:phone":"+34 928 23 42 47",
    "sg:postcode":"35006",
    "sg:province":"Las Palmas",
    "wof:name":"Bolaos Betancor Clodovaldo",
    "wof:placetype":"venue"
},
  "geometry": {"coordinates":[-15.4312610626,28.1341362],"type":"Point"}
}