{
  "type": "Feature",
  "properties": {
    "addr:full":"Avda Malaga Oloroso, 43 Malaga M\u00e1laga 29014",
    "addr:housenumber":"43",
    "addr:postcode":"29014",
    "addr:street":"Avda Malaga Oloroso;Ma\u0301Laga",
    "iso:country":"ES",
    "sg:address":"Avda Malaga Oloroso, 43",
    "sg:city":"Malaga",
    "sg:orig_category":"Reposter\u00cdas",
    "sg:phone":"+34 952 65 24 77",
    "sg:postcode":"29014",
    "sg:province":"M\u00e1laga",
    "wof:name":"Rute Martin Antonio Jesus",
    "wof:placetype":"venue"
},
  "geometry": {"coordinates":[-4.4141569138,36.7453460693],"type":"Point"}
}