{
  "type": "Feature",
  "properties": {
    "addr:full":"Calle de Ingleses, 27 Santovenia Pisuerga Valladolid 47155",
    "addr:housenumber":"27",
    "addr:postcode":"47155",
    "addr:street":"Calle De Ingleses",
    "iso:country":"ES",
    "sg:address":"Calle de Ingleses, 27",
    "sg:city":"Santovenia Pisuerga",
    "sg:orig_category":"Construcciones Met\u00c1licas",
    "sg:phone":"+34 983 26 33 77",
    "sg:postcode":"47155",
    "sg:province":"Valladolid",
    "wof:name":"Gonzalez Mielgo S.l.",
    "wof:placetype":"venue"
},
  "geometry": {"coordinates":[-4.680398941,41.6904716492],"type":"Point"}
}