{
  "type": "Feature",
  "properties": {
    "addr:full":"Arra Gudi\u00d1os, 81 Rianxo La Coru\u00f1a 15920",
    "addr:housenumber":"81",
    "addr:postcode":"15920",
    "addr:street":"Gudin\u0303Os;La Corun\u0303A",
    "iso:country":"ES",
    "sg:address":"Arra Gudi\u00d1os, 81",
    "sg:city":"Rianxo",
    "sg:orig_category":"Construcciones Navales Y Fluviales",
    "sg:phone":"+34 981 86 04 80",
    "sg:postcode":"15920",
    "sg:province":"La Coru\u00f1a",
    "wof:name":"Losada Fachado Jose",
    "wof:placetype":"venue"
},
  "geometry": {"coordinates":[-8.814538002,42.6515731812],"type":"Point"}
}