{
  "type": "Feature",
  "properties": {
    "addr:full":"Carrer de Domenech I Montaner, 6 Rubi Barcelona 08191",
    "addr:housenumber":"6",
    "addr:postcode":"08191",
    "addr:street":"Carrer De Domenech I Montaner",
    "iso:country":"ES",
    "sg:address":"Carrer de Domenech I Montaner, 6",
    "sg:city":"Rubi",
    "sg:orig_category":"Fabricaci\u00d3n De Moldes Y Modelos",
    "sg:phone":"+34 936 97 91 00",
    "sg:postcode":"08191",
    "sg:province":"Barcelona",
    "wof:name":"Plasterlink Invest S.l.",
    "wof:placetype":"venue"
},
  "geometry": {"coordinates":[2.0316240788,41.4919128418],"type":"Point"}
}