{
  "type": "Feature",
  "properties": {
    "addr:full":"Avda La Sierrezuela, 76 Mijas Costa M\u00e1laga 29649",
    "addr:housenumber":"76",
    "addr:postcode":"29649",
    "addr:street":"Avda La Sierrezuela",
    "iso:country":"ES",
    "sg:address":"Avda La Sierrezuela, 76",
    "sg:city":"Mijas Costa",
    "sg:orig_category":"Agencias Y Agentes Comerciales, Representantes",
    "sg:phone":"+34 952 59 26 84",
    "sg:postcode":"29649",
    "sg:province":"M\u00e1laga",
    "wof:name":"Pacual Export S.l.",
    "wof:placetype":"venue"
},
  "geometry": {"coordinates":[-4.6310629845,36.5238952637],"type":"Point"}
}