{
  "type": "Feature",
  "properties": {
    "addr:full":"Calle de Bidezabal, 9 Getxo Vizcaya 48990",
    "addr:housenumber":"9",
    "addr:postcode":"48990",
    "addr:street":"Calle De Bidezabal",
    "iso:country":"ES",
    "sg:address":"Calle de Bidezabal, 9",
    "sg:city":"Getxo",
    "sg:orig_category":"Carnicer\u00cdas, Carnicer\u00cdas",
    "sg:phone":"+34 944 30 02 04",
    "sg:postcode":"48990",
    "sg:province":"Vizcaya",
    "wof:name":"Alfredo Portero Gonzalez",
    "wof:placetype":"venue"
},
  "geometry": {"coordinates":[-3.0109665394,43.3572998047],"type":"Point"}
}