{
  "type": "Feature",
  "properties": {
    "iso:country":"ES",
    "sg:address":"Calle de Maria De Molina, 40",
    "sg:city":"Madrid",
    "sg:orig_category":"Promotores Constructores",
    "sg:phone":"+34 917 45 14 10",
    "sg:postcode":"28006",
    "sg:province":"Madrid",
    "wof:name":"Geinsol",
    "wof:placetype":"venue"
},
  "geometry": {"coordinates":[-3.6827969551,40.4375038147],"type":"Point"}
}