{
  "type": "Feature",
  "properties": {
    "iso:country":"ES",
    "sg:address":"Calle de Virgen, 2",
    "sg:city":"Do\u00e7a Mencia",
    "sg:orig_category":"Serigraf\u00cda (material Y Suministros)",
    "sg:phone":"+34 957 67 66 53",
    "sg:postcode":"14860",
    "sg:province":"C\u00f3rdoba",
    "wof:name":"Graficas Flora S.l.",
    "wof:placetype":"venue"
},
  "geometry": {"coordinates":[-4.3589568138,37.5554466248],"type":"Point"}
}