{
  "type": "Feature",
  "properties": {
    "addr:full":"Calle de Micer Masco, 35 Valencia Valencia 46010",
    "addr:housenumber":"35",
    "addr:postcode":"46010",
    "addr:street":"Calle De Micer Masco",
    "iso:country":"ES",
    "sg:address":"Calle de Micer Masco, 35",
    "sg:city":"Valencia",
    "sg:orig_category":"Agencias Y Agentes Comerciales, Representantes",
    "sg:phone":"+34 963 60 73 80",
    "sg:postcode":"46010",
    "sg:province":"Valencia",
    "wof:name":"Vidal Alemany Francisco",
    "wof:placetype":"venue"
},
  "geometry": {"coordinates":[-0.3601480126,39.4749031067],"type":"Point"}
}