{
  "type": "Feature",
  "properties": {
    "addr:full":"Calle de Izelaieta, 23 Ermua Vizcaya 48260",
    "addr:housenumber":"23",
    "addr:postcode":"48260",
    "addr:street":"Calle De Izelaieta",
    "iso:country":"ES",
    "sg:address":"Calle de Izelaieta, 23",
    "sg:city":"Ermua",
    "sg:orig_category":"Asistencia Social",
    "sg:phone":"+34 943 17 70 55",
    "sg:postcode":"48260",
    "sg:province":"Vizcaya",
    "wof:name":"Urgatzi S.l.",
    "wof:placetype":"venue"
},
  "geometry": {"coordinates":[-2.4993638992,43.1844482422],"type":"Point"}
}