{
  "type": "Feature",
  "properties": {
    "addr:full":"Ctra Madrid-cadiz, S/n Cuervo Sevilla 41749",
    "addr:housenumber":"/ n",
    "addr:postcode":"41749",
    "addr:street":"Ctra Madrid-Cadiz S",
    "iso:country":"ES",
    "sg:address":"Ctra Madrid-cadiz, S/n",
    "sg:city":"Cuervo",
    "sg:orig_category":"Producci\u00d3n, Comercio De Cereales",
    "sg:phone":"+34 955 97 90 67",
    "sg:postcode":"41749",
    "sg:province":"Sevilla",
    "wof:name":"Comercial Antonio Gracia S.l.",
    "wof:placetype":"venue"
},
  "geometry": {"coordinates":[-6.039809227,36.8541641235],"type":"Point"}
}