{
  "type": "Feature",
  "properties": {
    "iso:country":"ES",
    "sg:address":"Avda Tomillar (del), 41",
    "sg:city":"Pe\u00d1ascales",
    "sg:orig_category":"Librer\u00cdas",
    "sg:phone":"+34 918 59 92 67",
    "sg:postcode":"28250",
    "sg:province":"Madrid",
    "wof:name":"Tarazona Lopez Jorge",
    "wof:placetype":"venue"
},
  "geometry": {"coordinates":[-3.8938570023,40.5762863159],"type":"Point"}
}