{
  "type": "Feature",
  "properties": {
    "addr:full":"Calle de Alta, 32 Alcala Selva Teruel 44432",
    "addr:housenumber":"32",
    "addr:postcode":"44432",
    "addr:street":"Calle De Alta",
    "iso:country":"ES",
    "sg:address":"Calle de Alta, 32",
    "sg:city":"Alcala Selva",
    "sg:orig_category":"Cajas De Ahorro",
    "sg:phone":"+34 978 80 10 29",
    "sg:postcode":"44432",
    "sg:province":"Teruel",
    "wof:name":"Caja De Ahorros Y Monte De Piedad De Zaragoza Aragon Y Rioja",
    "wof:placetype":"venue"
},
  "geometry": {"coordinates":[-0.7182809711,40.371471405],"type":"Point"}
}