{
  "type": "Feature",
  "properties": {
    "iso:country":"ES",
    "sg:address":"Pase San Gregorio, S/n",
    "sg:city":"Puertollano",
    "sg:orig_category":"Centros De Educaci\u00d3n Especial",
    "sg:phone":"+34 926 42 63 66",
    "sg:postcode":"13500",
    "sg:province":"Ciudad Real",
    "wof:name":"Ceip Giner De Los Rios",
    "wof:placetype":"venue"
},
  "geometry": {"coordinates":[-4.1027088165,38.6894798279],"type":"Point"}
}