{
  "type": "Feature",
  "properties": {
    "addr:full":"Monasterio De La Oliva, 60 Iru\u00f1a Navarra 31011",
    "addr:housenumber":"60",
    "addr:postcode":"31011",
    "addr:street":"La Oliva",
    "iso:country":"ES",
    "sg:address":"Monasterio De La Oliva, 60",
    "sg:city":"Iru\u00f1a",
    "sg:orig_category":"Peluqueros: De Se\u00d1oras",
    "sg:phone":"+34 948 17 16 66",
    "sg:postcode":"31011",
    "sg:province":"Navarra",
    "wof:name":"Zarranz Marcilla Lucia",
    "wof:placetype":"venue"
},
  "geometry": {"coordinates":[-1.6628665924,42.8149681091],"type":"Point"}
}