{
  "type": "Feature",
  "properties": {
    "iso:country":"ES",
    "sg:address":"Calle de Maria De Guzman, 18",
    "sg:city":"Madrid",
    "sg:orig_category":"Carnicer\u00cdas, Carnicer\u00cdas",
    "sg:phone":"+34 915 54 02 70",
    "sg:postcode":"28003",
    "sg:province":"Madrid",
    "wof:name":"Herranz De Diego Moises",
    "wof:placetype":"venue"
},
  "geometry": {"coordinates":[-3.7029759884,40.4442100525],"type":"Point"}
}