{
  "type": "Feature",
  "properties": {
    "iso:country":"ES",
    "sg:address":"Pl. Espanya, 4",
    "sg:city":"Benirredra",
    "sg:orig_category":"Iglesia Cat\u00d3lica",
    "sg:phone":"+34 962 86 02 44",
    "sg:postcode":"46700",
    "sg:province":"Valencia",
    "wof:name":"Parroquia San Lorenzo",
    "wof:placetype":"venue"
},
  "geometry": {"coordinates":[-0.1925130039,38.9618148804],"type":"Point"}
}