{
  "type": "Feature",
  "properties": {
    "addr:full":"Calle de Ramon Gonzalez, 10 Ribadeo Lugo 27700",
    "addr:housenumber":"10",
    "addr:postcode":"27700",
    "addr:street":"Calle De Ramon Gonzalez",
    "iso:country":"ES",
    "sg:address":"Calle de Ramon Gonzalez, 10",
    "sg:city":"Ribadeo",
    "sg:orig_category":"Farmacias",
    "sg:phone":"+34 982 12 80 07",
    "sg:postcode":"27700",
    "sg:province":"Lugo",
    "wof:name":"Iglesias Nu\u00f1ez Montserrat",
    "wof:placetype":"venue"
},
  "geometry": {"coordinates":[-7.043405056,43.5369644165],"type":"Point"}
}