{
  "type": "Feature",
  "properties": {
    "addr:full":"Plaz Charco, 16 Montoro C\u00f3rdoba 14600",
    "addr:housenumber":"16",
    "addr:postcode":"14600",
    "addr:street":"Plaz Charco;Co\u0301Rdoba",
    "iso:country":"ES",
    "sg:address":"Plaz Charco, 16",
    "sg:city":"Montoro",
    "sg:orig_category":"Electrodom\u00c9sticos (al Por Menor)",
    "sg:phone":"+34 957 16 01 82",
    "sg:postcode":"14600",
    "sg:province":"C\u00f3rdoba",
    "wof:name":"Alba Frenegal Manuel",
    "wof:placetype":"venue"
},
  "geometry": {"coordinates":[-4.3565130234,38.1094436646],"type":"Point"}
}