{
  "type": "Feature",
  "properties": {
    "addr:full":"Calle de Conrado Blanco, 12 Ba\u00d1eza Le\u00f3n 24750",
    "addr:housenumber":"12",
    "addr:postcode":"24750",
    "addr:street":"Calle De Conrado Blanco;Leo\u0301N",
    "iso:country":"ES",
    "sg:address":"Calle de Conrado Blanco, 12",
    "sg:city":"Ba\u00d1eza",
    "sg:orig_category":"M\u00c9dicos: Estomatolog\u00cda",
    "sg:phone":"+34 987 64 43 73",
    "sg:postcode":"24750",
    "sg:province":"Le\u00f3n",
    "wof:name":"Ruiz Gonzalez Francisco Jose",
    "wof:placetype":"venue"
},
  "geometry": {"coordinates":[-5.5717520714,42.5998764038],"type":"Point"}
}