{
  "type": "Feature",
  "properties": {
    "iso:country":"ES",
    "sg:address":"Calle de Horno De Abad, 13",
    "sg:city":"Granada",
    "sg:orig_category":"Ropa Y Accesorios",
    "sg:phone":"+34 958 52 00 67",
    "sg:postcode":"18002",
    "sg:province":"Granada",
    "wof:name":"Sanchez Medina Estrella Luz",
    "wof:placetype":"venue"
},
  "geometry": {"coordinates":[-3.603718996,37.1765899658],"type":"Point"}
}