{
  "type": "Feature",
  "properties": {
    "addr:full":"Calle de Arrabal, 87 Don Benito Badajoz 06400",
    "addr:housenumber":"87",
    "addr:postcode":"06400",
    "addr:street":"Calle De Arrabal",
    "iso:country":"ES",
    "sg:address":"Calle de Arrabal, 87",
    "sg:city":"Don Benito",
    "sg:orig_category":"Molduras, Junquillos, Listones Y Molduras Perforadas",
    "sg:phone":"+34 924 80 49 33",
    "sg:postcode":"06400",
    "sg:province":"Badajoz",
    "wof:name":"Mora Velarde Alejandro",
    "wof:placetype":"venue"
},
  "geometry": {"coordinates":[-5.8658685684,38.9535064697],"type":"Point"}
}