{
  "type": "Feature",
  "properties": {
    "addr:full":"C/ Moli D'en Ginestar, 34 Ripollet Barcelona 08291",
    "addr:housenumber":"34",
    "addr:postcode":"08291",
    "addr:street":"C / Moli D'En Ginestar",
    "iso:country":"ES",
    "sg:address":"C/ Moli D'en Ginestar, 34",
    "sg:city":"Ripollet",
    "sg:orig_category":"Protecci\u00d3n Contra Incendios: Material, Instalaci\u00d3n, Mantenimiento",
    "sg:phone":"+34 935 92 24 03",
    "sg:postcode":"08291",
    "sg:province":"Barcelona",
    "sg:website":"www.sicogravi.com",
    "wof:name":"Sicogravi S.l.",
    "wof:placetype":"venue"
},
  "geometry": {"coordinates":[2.1535930634,41.4941864014],"type":"Point"}
}