{
  "type": "Feature",
  "properties": {
    "iso:country":"ES",
    "sg:address":"Carr Nou Cases, 89",
    "sg:city":"Badalona",
    "sg:orig_category":"Promotores Constructores",
    "sg:phone":"+34 933 95 63 72",
    "sg:postcode":"08917",
    "sg:province":"Barcelona",
    "wof:name":"Jimenez Perez Manuel",
    "wof:placetype":"venue"
},
  "geometry": {"coordinates":[2.2388699055,41.4605102539],"type":"Point"}
}