{
  "type": "Feature",
  "properties": {
    "iso:country":"ES",
    "sg:address":"Calle de Simon De Anda, 1",
    "sg:city":"Vitoria-gasteiz",
    "sg:orig_category":"Ropa Para Se\u00d1oras (al Por Menor)",
    "sg:phone":"+34 945 22 49 60",
    "sg:postcode":"01012",
    "sg:province":"\u00c1lava",
    "wof:name":"Vesga Saez Cristina",
    "wof:placetype":"venue"
},
  "geometry": {"coordinates":[-2.6759080887,42.8547439575],"type":"Point"}
}