{
  "type": "Feature",
  "properties": {
    "iso:country":"ES",
    "sg:address":"Avgd Arquitecte Antoni Gilabert, 1",
    "sg:city":"Pedreguer",
    "sg:orig_category":"Molduras, Junquillos, Listones Y Molduras Perforadas",
    "sg:phone":"+34 965 76 05 80",
    "sg:postcode":"03750",
    "sg:province":"Alicante",
    "wof:name":"Palacios Santos Pascual",
    "wof:placetype":"venue"
},
  "geometry": {"coordinates":[0.037349999,38.7942886353],"type":"Point"}
}