{
  "type": "Feature",
  "properties": {
    "addr:full":"Pol Ind Son Llaut, S/n Sta. Maria Cami Islas Baleares 07320",
    "addr:housenumber":"s / n",
    "addr:postcode":"07320",
    "addr:street":"Islas",
    "iso:country":"ES",
    "sg:address":"Pol Ind Son Llaut, S/n",
    "sg:city":"Sta. Maria Cami",
    "sg:orig_category":"Productos Qu\u00cdmicos (fabricaci\u00d3n, Al Por Mayor)",
    "sg:phone":"+34 971 43 17 59",
    "sg:postcode":"07320",
    "sg:province":"Islas Baleares",
    "wof:name":"Cobi Balear S.l.",
    "wof:placetype":"venue"
},
  "geometry": {"coordinates":[2.77760005,39.6388893127],"type":"Point"}
}