{
  "type": "Feature",
  "properties": {
    "iso:country":"ES",
    "sg:address":"Calle de Venegas, 13",
    "sg:city":"Palmas De Gran Canaria",
    "sg:orig_category":"Psic\u00d3logos",
    "sg:phone":"+34 928 43 20 98",
    "sg:postcode":"35003",
    "sg:province":"Las Palmas",
    "sg:website":"www.ecologia-humana.com",
    "wof:name":"Almeida Falcon Juana Teresa",
    "wof:placetype":"venue"
},
  "geometry": {"coordinates":[-15.4172325134,28.1104812622],"type":"Point"}
}