{
  "type": "Feature",
  "properties": {
    "addr:full":"Calle de Santa Teresa, 5 Aracena Huelva 21200",
    "addr:housenumber":"5",
    "addr:postcode":"21200",
    "addr:street":"Calle De Santa Teresa",
    "iso:country":"ES",
    "sg:address":"Calle de Santa Teresa, 5",
    "sg:city":"Aracena",
    "sg:orig_category":"M\u00c9dicos: Estomatolog\u00cda",
    "sg:phone":"+34 959 12 75 62",
    "sg:postcode":"21200",
    "sg:province":"Huelva",
    "wof:name":"Marquez Rodriguez Joaquin",
    "wof:placetype":"venue"
},
  "geometry": {"coordinates":[-6.5626940727,37.8933105469],"type":"Point"}
}