{
  "type": "Feature",
  "properties": {
    "iso:country":"ES",
    "sg:address":"Czad Martianez, 14",
    "sg:city":"Botanico",
    "sg:orig_category":"Bisuter\u00cda, Joyer\u00cda, Relojer\u00cda (al Por Menor)",
    "sg:phone":"+34 922 37 01 58",
    "sg:postcode":"38400",
    "sg:province":"Santa Cruz De Tenerife",
    "wof:name":"Menendez Segovia Rafael",
    "wof:placetype":"venue"
},
  "geometry": {"coordinates":[-16.5473842621,28.4141807556],"type":"Point"}
}