{
  "type": "Feature",
  "properties": {
    "addr:full":"Av Princep D'asturies, 3 Barcelona Barcelona 08012",
    "addr:housenumber":"3",
    "addr:postcode":"08012",
    "addr:street":"Av Princep D'Asturies",
    "iso:country":"ES",
    "sg:address":"Av Princep D'asturies, 3",
    "sg:city":"Barcelona",
    "sg:orig_category":"Molduras, Junquillos, Listones Y Molduras Perforadas",
    "sg:phone":"+34 932 18 64 39",
    "sg:postcode":"08012",
    "sg:province":"Barcelona",
    "wof:name":"Alvarez Torres Gabino",
    "wof:placetype":"venue"
},
  "geometry": {"coordinates":[2.1511428356,41.4014472961],"type":"Point"}
}