{
  "type": "Feature",
  "properties": {
    "addr:full":"Carr Duc De Calabria, 1 Xativa Valencia 46800",
    "addr:housenumber":"1",
    "addr:postcode":"46800",
    "addr:street":"Carr Duc De Calabria",
    "iso:country":"ES",
    "sg:address":"Carr Duc De Calabria, 1",
    "sg:city":"Xativa",
    "sg:orig_category":"Ferreter\u00cda (diversos)",
    "sg:phone":"+34 962 28 33 35",
    "sg:postcode":"46800",
    "sg:province":"Valencia",
    "sg:website":"www.forencin.com",
    "wof:name":"Forecin,calculos De Ingenieria Para La E",
    "wof:placetype":"venue"
},
  "geometry": {"coordinates":[-0.5296379924,38.9888954163],"type":"Point"}
}