{
  "type": "Feature",
  "properties": {
    "addr:full":"Ibai-tarte Kalea, S/n Elgoibar Guip\u00f9zcoa 20870",
    "addr:housenumber":"s / n",
    "addr:postcode":"20870",
    "addr:street":"Ibai-Tarte Kalea;Guipu\u0300Zcoa",
    "iso:country":"ES",
    "sg:address":"Ibai-tarte Kalea, S/n",
    "sg:city":"Elgoibar",
    "sg:orig_category":"Maquinaria Para Industrias Diversas",
    "sg:phone":"+34 943 74 38 24",
    "sg:postcode":"20870",
    "sg:province":"Guip\u00f9zcoa",
    "wof:name":"Alki Haizea S.a.",
    "wof:placetype":"venue"
},
  "geometry": {"coordinates":[-2.4089910984,43.2230644226],"type":"Point"}
}