{
  "type": "Feature",
  "properties": {
    "iso:country":"ES",
    "sg:address":"Calle de Santa Ana, 2",
    "sg:city":"Villaviciosa Odon",
    "sg:orig_category":"Asociaciones Humanitarias, De Cooperaci\u00d3n, De Acci\u00d3n Social",
    "sg:phone":"+34 916 65 71 94",
    "sg:postcode":"28670",
    "sg:province":"Madrid",
    "wof:name":"Asociacion Espa\u00f1ola Contra El Cancer",
    "wof:placetype":"venue"
},
  "geometry": {"coordinates":[-3.9002103806,40.3574638367],"type":"Point"}
}