{
  "type": "Feature",
  "properties": {
    "iso:country":"ES",
    "sg:address":"Carrer de Enric Prat De La Riba, 1",
    "sg:city":"Vic",
    "sg:orig_category":"Cajas De Ahorro",
    "sg:phone":"+34 938 85 34 90",
    "sg:postcode":"08500",
    "sg:province":"Barcelona",
    "wof:name":"Caixa D'estalvis I Pensions De Barcelona",
    "wof:placetype":"venue"
},
  "geometry": {"coordinates":[2.2522809505,41.9203224182],"type":"Point"}
}