{
  "type": "Feature",
  "properties": {
    "addr:full":"Calle de Torre Del Mar, 12 Malaga M\u00e1laga 29004",
    "addr:housenumber":"12",
    "addr:postcode":"29004",
    "addr:street":"Calle De Torre Del Mar;Ma\u0301Laga",
    "iso:country":"ES",
    "sg:address":"Calle de Torre Del Mar, 12",
    "sg:city":"Malaga",
    "sg:classifiers":[
        {
            "category":"Professional",
            "subcategory":"Management & Consulting",
            "type":"Services"
        }
    ],
    "sg:phone":"+34 952 17 35 79",
    "sg:postcode":"29004",
    "sg:province":"M\u00e1laga",
    "sg:tags":[
        "asesor\u00cda",
        "en",
        "marketing"
    ],
    "wof:name":"Nopin Alavesa S.a",
    "wof:placetype":"venue"
},
  "geometry": {"coordinates":[-4.474984169,36.6674613953],"type":"Point"}
}