{
  "type": "Feature",
  "properties": {
    "addr:full":"Calle de Londres, 1 Caceres C\u00e1ceres 10005",
    "addr:housenumber":"1",
    "addr:postcode":"10005",
    "addr:street":"Calle De Londres;Ca\u0301Ceres",
    "iso:country":"ES",
    "sg:address":"Calle de Londres, 1",
    "sg:city":"Caceres",
    "sg:orig_category":"Zapatos (al Por Menor)",
    "sg:phone":"+34 927 62 93 95",
    "sg:postcode":"10005",
    "sg:province":"C\u00e1ceres",
    "wof:name":"Zapaterias",
    "wof:placetype":"venue"
},
  "geometry": {"coordinates":[-6.3887991905,39.4685592651],"type":"Point"}
}