{
  "type": "Feature",
  "properties": {
    "iso:country":"ES",
    "sg:address":"Magdalena, S/n",
    "sg:city":"Iru\u00f1a",
    "sg:orig_category":"Negocio De Madera",
    "sg:phone":"+34 948 12 99 68",
    "sg:postcode":"31015",
    "sg:province":"Navarra",
    "wof:name":"Maderas Urederra S.l.",
    "wof:placetype":"venue"
},
  "geometry": {"coordinates":[-1.6333640814,42.8255958557],"type":"Point"}
}