{
  "type": "Feature",
  "properties": {
    "addr:full":"Carr De Jesus Vilar, 38 S. Rafael Rio Castell\u00f3n 12510",
    "addr:housenumber":"38",
    "addr:postcode":"12510",
    "addr:street":"Carr De Jesus Vilar;Rafael Rio Castello\u0301N",
    "iso:country":"ES",
    "sg:address":"Carr De Jesus Vilar, 38",
    "sg:city":"S. Rafael Rio",
    "sg:orig_category":"Agentes Generales De Seguros",
    "sg:phone":"+34 977 57 54 37",
    "sg:postcode":"12510",
    "sg:province":"Castell\u00f3n",
    "wof:name":"Castell Ferre Maria Victoria",
    "wof:placetype":"venue"
},
  "geometry": {"coordinates":[0.3464699984,40.6063156128],"type":"Point"}
}