{
  "type": "Feature",
  "properties": {
    "addr:full":"Calle de Fuentepelayo, 2 Navalmanzano Segovia 40280",
    "addr:housenumber":"2",
    "addr:postcode":"40280",
    "addr:street":"Calle De Fuentepelayo",
    "iso:country":"ES",
    "sg:address":"Calle de Fuentepelayo, 2",
    "sg:city":"Navalmanzano",
    "sg:orig_category":"Bancos",
    "sg:phone":"+34 921 57 52 32",
    "sg:postcode":"40280",
    "sg:province":"Segovia",
    "wof:name":"Banco Espa\u00f1ol De Credito S.a.",
    "wof:placetype":"venue"
},
  "geometry": {"coordinates":[-4.2549500465,41.2148094177],"type":"Point"}
}