{
  "type": "Feature",
  "properties": {
    "addr:full":"Calle de Francisco Bastarreche, 17 Marin Pontevedra 36900",
    "addr:housenumber":"17",
    "addr:postcode":"36900",
    "addr:street":"Calle De Francisco Bastarreche",
    "iso:country":"ES",
    "sg:address":"Calle de Francisco Bastarreche, 17",
    "sg:city":"Marin",
    "sg:orig_category":"Asociaciones Y Clubs Deportivos",
    "sg:phone":"+34 986 88 26 37",
    "sg:postcode":"36900",
    "sg:province":"Pontevedra",
    "wof:name":"Vega Villaverde Maria Del Carmen De La",
    "wof:placetype":"venue"
},
  "geometry": {"coordinates":[-8.6881885529,42.391746521],"type":"Point"}
}