{
  "type": "Feature",
  "properties": {
    "addr:full":"Crril. Palmeras, 32 Aljucer Murcia 30152",
    "addr:housenumber":"32",
    "addr:postcode":"30152",
    "addr:street":"Palmeras",
    "iso:country":"ES",
    "sg:address":"Crril. Palmeras, 32",
    "sg:city":"Aljucer",
    "sg:orig_category":"Alimentaci\u00d3n General (al Por Menor)",
    "sg:phone":"+34 968 25 23 89",
    "sg:postcode":"30152",
    "sg:province":"Murcia",
    "wof:name":"Zaragoza Fenol Antonio",
    "wof:placetype":"venue"
},
  "geometry": {"coordinates":[-1.1487027407,37.9530715942],"type":"Point"}
}