{
  "type": "Feature",
  "properties": {
    "iso:country":"ES",
    "sg:address":"Ctra General, 68",
    "sg:city":"Tagle",
    "sg:orig_category":"Transportes Por V\u00cdas Navegables",
    "sg:phone":"+34 942 84 45 13",
    "sg:postcode":"39360",
    "sg:province":"Cantabria",
    "wof:name":"Transportes Ramon Y Jose Luis Gutierrez S.l.",
    "wof:placetype":"venue"
},
  "geometry": {"coordinates":[-4.0774188042,43.4217681885],"type":"Point"}
}