{
  "type": "Feature",
  "properties": {
    "iso:country":"ES",
    "sg:address":"Calle de Maria Auxiliadora, 50",
    "sg:city":"Monzon",
    "sg:orig_category":"Agricultura: Abastecimiento Y Cosechado (negocio)",
    "sg:phone":"+34 974 40 19 20",
    "sg:postcode":"22400",
    "sg:province":"Huesca",
    "wof:name":"Hermanos Jimenez Laborda,s.l.",
    "wof:placetype":"venue"
},
  "geometry": {"coordinates":[0.1868070066,41.91456604],"type":"Point"}
}