{
  "type": "Feature",
  "properties": {
    "addr:full":"Avda Jose Martinez Gonzalez, 36 Elda Alicante 03600",
    "addr:housenumber":"36",
    "addr:postcode":"03600",
    "addr:street":"Avda Jose Martinez Gonzalez",
    "iso:country":"ES",
    "sg:address":"Avda Jose Martinez Gonzalez, 36",
    "sg:city":"Elda",
    "sg:orig_category":"Caf\u00c9s, Bares, Cervecer\u00cdas",
    "sg:phone":"+34 966 98 01 33",
    "sg:postcode":"03600",
    "sg:province":"Alicante",
    "wof:name":"Rada Business S.l.",
    "wof:placetype":"venue"
},
  "geometry": {"coordinates":[-0.7878230214,38.4768791199],"type":"Point"}
}