{
  "type": "Feature",
  "properties": {
    "addr:full":"Calle de Tirso De Molina, 33 Valladolid Valladolid 47010",
    "addr:housenumber":"33",
    "addr:postcode":"47010",
    "addr:street":"Calle De Tirso De Molina",
    "iso:country":"ES",
    "sg:address":"Calle de Tirso De Molina, 33",
    "sg:city":"Valladolid",
    "sg:orig_category":"Abogados",
    "sg:phone":"+34 983 26 19 08",
    "sg:postcode":"47010",
    "sg:province":"Valladolid",
    "wof:name":"Tarilonte Santos Julia",
    "wof:placetype":"venue"
},
  "geometry": {"coordinates":[-4.7261757851,41.6610336304],"type":"Point"}
}