{
  "type": "Feature",
  "properties": {
    "iso:country":"ES",
    "sg:address":"Carrer de Rutlla (la), 18",
    "sg:city":"Terrassa",
    "sg:orig_category":"Electrodom\u00c9sticos (al Por Menor)",
    "sg:phone":"+34 937 88 18 82",
    "sg:postcode":"08221",
    "sg:province":"Barcelona",
    "wof:name":"Electrodomestics L'autentic Miro S.l.",
    "wof:placetype":"venue"
},
  "geometry": {"coordinates":[2.0117800236,41.5612297058],"type":"Point"}
}