{
  "type": "Feature",
  "properties": {
    "iso:country":"ES",
    "sg:address":"Cristobal Colon, 18",
    "sg:city":"Campillo Salvatierra",
    "sg:orig_category":"Limpieza Industrial",
    "sg:phone":"+34 923 58 09 55",
    "sg:postcode":"37778",
    "sg:province":"Salamanca",
    "wof:name":"Lavanderia Industrial Maite S.l.",
    "wof:placetype":"venue"
},
  "geometry": {"coordinates":[-5.6777892113,40.5702209473],"type":"Point"}
}