{
  "type": "Feature",
  "properties": {
    "addr:full":"Carr Mariana Pineda, 90 Burjassot Valencia 46100",
    "addr:housenumber":"90",
    "addr:postcode":"46100",
    "addr:street":"Carr Mariana Pineda",
    "iso:country":"ES",
    "sg:address":"Carr Mariana Pineda, 90",
    "sg:city":"Burjassot",
    "sg:orig_category":"Sociedades, Compa\u00d1\u00cdas Aseguradoras",
    "sg:phone":"+34 963 63 00 58",
    "sg:postcode":"46100",
    "sg:province":"Valencia",
    "sg:website":"www.santalucia.es",
    "wof:name":"Santa Lucia S.a.",
    "wof:placetype":"venue"
},
  "geometry": {"coordinates":[-0.4105490148,39.5093688965],"type":"Point"}
}