{
  "type": "Feature",
  "properties": {
    "iso:country":"ES",
    "sg:address":"Calle de Cardenal Benlloch, 48",
    "sg:city":"Mislata",
    "sg:orig_category":"Farmacias",
    "sg:phone":"+34 963 79 08 98",
    "sg:postcode":"46920",
    "sg:province":"Valencia",
    "wof:name":"F.zamora Y Zamora C.b.",
    "wof:placetype":"venue"
},
  "geometry": {"coordinates":[-0.4182111025,39.4729042053],"type":"Point"}
}