{
  "type": "Feature",
  "properties": {
    "iso:country":"ES",
    "sg:address":"Calle de Inmaculada Concepcion, 36",
    "sg:city":"Madrid",
    "sg:orig_category":"Estancos",
    "sg:phone":"+34 915 60 10 31",
    "sg:postcode":"28019",
    "sg:province":"Madrid",
    "wof:name":"Rivera Gomez Maria Rosa",
    "wof:placetype":"venue"
},
  "geometry": {"coordinates":[-3.7123959064,40.3926734924],"type":"Point"}
}