{
  "type": "Feature",
  "properties": {
    "iso:country":"ES",
    "sg:address":"Calle de Pablo Iglesias, S/n",
    "sg:city":"Medina-sidonia",
    "sg:orig_category":"Agencias Y Agentes Comerciales, Representantes",
    "sg:phone":"+34 956 41 06 16",
    "sg:postcode":"11170",
    "sg:province":"C\u00e1diz",
    "wof:name":"Compa\u00f1ia Hidalgo Andrey Y De La Cruz S.l.",
    "wof:placetype":"venue"
},
  "geometry": {"coordinates":[-5.9270777702,36.4547691345],"type":"Point"}
}