{
  "type": "Feature",
  "properties": {
    "iso:country":"ES",
    "sg:address":"Calle de Enrique Jardiel Poncela, 6",
    "sg:city":"Zaragoza",
    "sg:orig_category":"Aparatos, Sistemas De Tele",
    "sg:phone":"+34 976 46 66 24",
    "sg:postcode":"50015",
    "sg:province":"Zaragoza",
    "wof:name":"Alarmas Y Tecnicas De Seguridad S.l.l.",
    "wof:placetype":"venue"
},
  "geometry": {"coordinates":[-0.8879367113,41.6701011658],"type":"Point"}
}