{
  "type": "Feature",
  "properties": {
    "addr:full":"Carrer de Major De Sarria, 174 Barcelona Barcelona 08017",
    "addr:housenumber":"174",
    "addr:postcode":"08017",
    "addr:street":"Carrer De Major De Sarria",
    "iso:country":"ES",
    "sg:address":"Carrer de Major De Sarria, 174",
    "sg:city":"Barcelona",
    "sg:orig_category":"Laboratorios Y Cl\u00cdnicas Veterinarias",
    "sg:phone":"+34 932 80 13 52",
    "sg:postcode":"08017",
    "sg:province":"Barcelona",
    "wof:name":"Centre Veterinari Delphis S.l.",
    "wof:placetype":"venue"
},
  "geometry": {"coordinates":[2.1199970245,41.4018707275],"type":"Point"}
}