{
  "type": "Feature",
  "properties": {
    "iso:country":"ES",
    "sg:address":"Estacio Ferrocarril, S/n",
    "sg:city":"Tarragona",
    "sg:orig_category":"Bazares, Art\u00cdculos De Limpieza Y De Cocina (al Por Menor)",
    "sg:phone":"+34 977 23 53 51",
    "sg:postcode":"43004",
    "sg:province":"Tarragona",
    "wof:name":"Areas S.a.",
    "wof:placetype":"venue"
},
  "geometry": {"coordinates":[1.2349683046,41.104598999],"type":"Point"}
}