{
  "type": "Feature",
  "properties": {
    "addr:full":"Urb Cala Dorada, 22 Torrevieja Alicante 03180",
    "addr:housenumber":"22",
    "addr:postcode":"03180",
    "addr:street":"Urb Cala Dorada",
    "iso:country":"ES",
    "sg:address":"Urb Cala Dorada, 22",
    "sg:city":"Torrevieja",
    "sg:orig_category":"Fabricaci\u00d3n De Muebles",
    "sg:phone":"+34 966 70 65 85",
    "sg:postcode":"03180",
    "sg:province":"Alicante",
    "wof:name":"Viojelindo S.l.",
    "wof:placetype":"venue"
},
  "geometry": {"coordinates":[-0.6536790133,38.0173606873],"type":"Point"}
}