{
  "type": "Feature",
  "properties": {
    "iso:country":"ES",
    "sg:address":"Pla\u00c7 Escoles, 1",
    "sg:city":"Escala",
    "sg:orig_category":"Oficinas De Turismo, Asociaciones De Iniciativa",
    "sg:phone":"+34 972 77 06 03",
    "sg:postcode":"17130",
    "sg:province":"Girona",
    "sg:website":"www.lescala.org",
    "wof:name":"Patronat Municipal De Turisme De L'escala",
    "wof:placetype":"venue"
},
  "geometry": {"coordinates":[3.1321649551,42.1229934692],"type":"Point"}
}