{
  "type": "Feature",
  "properties": {
    "addr:full":"Pl Reial, 11 Barcelona Barcelona 08002",
    "addr:housenumber":"11",
    "addr:postcode":"08002",
    "addr:street":"Pl Reial",
    "iso:country":"ES",
    "sg:address":"Pl Reial, 11",
    "sg:city":"Barcelona",
    "sg:orig_category":"Caf\u00c9s, Bares, Cervecer\u00cdas",
    "sg:phone":"+34 932 70 10 62",
    "sg:postcode":"08002",
    "sg:province":"Barcelona",
    "wof:name":"Hotel Roma Kane Room S.l.",
    "wof:placetype":"venue"
},
  "geometry": {"coordinates":[2.1751220226,41.3805656433],"type":"Point"}
}