{
  "type": "Feature",
  "properties": {
    "iso:country":"ES",
    "sg:address":"Cami Ullastrell, 300",
    "sg:city":"Rubi",
    "sg:orig_category":"Contenedores (mercanc\u00cdas)",
    "sg:phone":"+34 935 87 07 20",
    "sg:postcode":"08191",
    "sg:province":"Barcelona",
    "wof:name":"Llorens Gruls Angel Enrique",
    "wof:placetype":"venue"
},
  "geometry": {"coordinates":[2.0117950439,41.497543335],"type":"Point"}
}