{
  "type": "Feature",
  "properties": {
    "addr:full":"Vrins, 1 Vrins La Coru\u00f1a 15897",
    "addr:housenumber":"1",
    "addr:postcode":"15897",
    "addr:street":"Vrins;La Corun\u0303A",
    "iso:country":"ES",
    "sg:address":"Vrins, 1",
    "sg:city":"Vrins",
    "sg:orig_category":"Forjas Y Altos Hornos",
    "sg:phone":"+34 981 57 40 10",
    "sg:postcode":"15897",
    "sg:province":"La Coru\u00f1a",
    "wof:name":"Bali\u00f1as Rey Jose",
    "wof:placetype":"venue"
},
  "geometry": {"coordinates":[-8.3959693909,43.3714904785],"type":"Point"}
}