{
  "type": "Feature",
  "properties": {
    "iso:country":"ES",
    "sg:address":"Calle de Europa, S/n",
    "sg:city":"Fuengirola",
    "sg:orig_category":"Alquiler De Veh\u00cdculos: Turismos Y Utilitarios",
    "sg:phone":"+34 952 47 51 78",
    "sg:postcode":"29640",
    "sg:province":"M\u00e1laga",
    "wof:name":"Autos Martin S. A.",
    "wof:placetype":"venue"
},
  "geometry": {"coordinates":[-4.6248140335,36.5326309204],"type":"Point"}
}