{
  "type": "Feature",
  "properties": {
    "iso:country":"ES",
    "sg:address":"Carr Doctor Sanchis Bergon, 9",
    "sg:city":"Eliana",
    "sg:orig_category":"Centros Empresariales",
    "sg:phone":"+34 962 74 15 72",
    "sg:postcode":"46183",
    "sg:province":"Valencia",
    "wof:name":"Explotaciones Y Mecanizados Olmo Sl",
    "wof:placetype":"venue"
},
  "geometry": {"coordinates":[-0.5156729817,39.5547180176],"type":"Point"}
}