{
  "type": "Feature",
  "properties": {
    "iso:country":"ES",
    "sg:address":"Calle de Antonio Martin Lopez, 10",
    "sg:city":"San Fernando",
    "sg:orig_category":"Alquiler De V\u00cddeo",
    "sg:phone":"+34 928 76 78 27",
    "sg:postcode":"35100",
    "sg:province":"Las Palmas",
    "wof:name":"Delgado Trujillo Ana Maria",
    "wof:placetype":"venue"
},
  "geometry": {"coordinates":[-15.5837392807,28.090631485],"type":"Point"}
}