{
  "type": "Feature",
  "properties": {
    "iso:country":"ES",
    "sg:address":"Avda Galicia, S/n",
    "sg:city":"Fuentes Nuevas",
    "sg:orig_category":"Ense\u00d1anza, Formaci\u00d3n Profesional: Aprendizaje",
    "sg:phone":"+34 987 45 53 80",
    "sg:postcode":"24411",
    "sg:province":"Le\u00f3n",
    "wof:name":"Ayuntamiento De Ponferrada",
    "wof:placetype":"venue"
},
  "geometry": {"coordinates":[-6.6428170204,42.5680885315],"type":"Point"}
}