{
  "type": "Feature",
  "properties": {
    "addr:full":"Pintor Jesus Gzlez Torre, 1 Ronda M\u00e1laga 29400",
    "addr:postcode":"29400",
    "addr:street":"Pintor;Ronda Ma\u0301Laga",
    "iso:country":"ES",
    "sg:address":"Pintor Jesus Gzlez Torre, 1",
    "sg:city":"Ronda",
    "sg:orig_category":"M\u00c9dicos: Otorrinolaringolog\u00cda",
    "sg:phone":"+34 952 87 84 64",
    "sg:postcode":"29400",
    "sg:province":"M\u00e1laga",
    "wof:name":"Luengos Matilla Cesar",
    "wof:placetype":"venue"
},
  "geometry": {"coordinates":[-5.0806918144,36.7813644409],"type":"Point"}
}