{
  "type": "Feature",
  "properties": {
    "addr:full":"Avda Danzantes De Huesca (los), 20 Huesca Huesca 22005",
    "addr:housenumber":"20",
    "addr:postcode":"22005",
    "addr:street":"Avda Danzantes De Huesca Los",
    "iso:country":"ES",
    "sg:address":"Avda Danzantes De Huesca (los), 20",
    "sg:city":"Huesca",
    "sg:orig_category":"Promotores Constructores",
    "sg:phone":"+34 974 24 39 83",
    "sg:postcode":"22005",
    "sg:province":"Huesca",
    "wof:name":"Angel Aso Construcciones S.l.",
    "wof:placetype":"venue"
},
  "geometry": {"coordinates":[-0.4004383981,42.1366386414],"type":"Point"}
}