{
  "type": "Feature",
  "properties": {
    "addr:full":"Calle de Divino Jesus, 8 Olivares De Jucar Cuenca 16760",
    "addr:housenumber":"8",
    "addr:postcode":"16760",
    "addr:street":"Calle De Divino Jesus",
    "iso:country":"ES",
    "sg:address":"Calle de Divino Jesus, 8",
    "sg:city":"Olivares De Jucar",
    "sg:classifiers":[
        {
            "category":"Autos & Motor Vehicles",
            "subcategory":"Automobile Sales",
            "type":"Retail Goods"
        }
    ],
    "sg:phone":"+34 969 29 44 58",
    "sg:postcode":"16760",
    "sg:province":"Cuenca",
    "wof:name":"Rubio De La Fuente Jaime",
    "wof:placetype":"venue"
},
  "geometry": {"coordinates":[-2.3563446999,39.7602806091],"type":"Point"}
}