{
  "type": "Feature",
  "properties": {
    "addr:full":"Calle de Santillana Del Mar (de), 4 Boadilla Del Monte Madrid 28660",
    "addr:postcode":"28660",
    "addr:street":"Calle De Santillana",
    "iso:country":"ES",
    "sg:address":"Calle de Santillana Del Mar (de), 4",
    "sg:city":"Boadilla Del Monte",
    "sg:orig_category":"Fabrica De Cer\u00c1micas",
    "sg:phone":"+34 916 32 08 08",
    "sg:postcode":"28660",
    "sg:province":"Madrid",
    "wof:name":"Faba Hanchon Jose",
    "wof:placetype":"venue"
},
  "geometry": {"coordinates":[-3.8814890385,40.4015045166],"type":"Point"}
}