{
  "type": "Feature",
  "properties": {
    "addr:full":"Calle de Alfonso Xi, 21 Algeciras C\u00e1diz 11201",
    "addr:housenumber":"21;ca\u0301diz",
    "addr:postcode":"11201",
    "addr:street":"Calle De Alfonso Xi",
    "iso:country":"ES",
    "sg:address":"Calle de Alfonso Xi, 21",
    "sg:city":"Algeciras",
    "sg:orig_category":"Agencias De Viajes",
    "sg:phone":"+34 956 65 20 30",
    "sg:postcode":"11201",
    "sg:province":"C\u00e1diz",
    "sg:website":"www.marsans.es",
    "wof:name":"Viajes Marsans S.a.",
    "wof:placetype":"venue"
},
  "geometry": {"coordinates":[-5.4472928047,36.1315689087],"type":"Point"}
}