{
  "type": "Feature",
  "properties": {
    "iso:country":"ES",
    "sg:address":"Cmno Telefonica (de La), Km. 0001,4",
    "sg:city":"Torrejon Calzada",
    "sg:orig_category":"Jardiner\u00cdas, Vegetales, Art\u00cdculos De Jardiner\u00cda (al Por Menor)",
    "sg:phone":"+34 918 10 60 76",
    "sg:postcode":"28991",
    "sg:province":"Madrid",
    "wof:name":"Jardines Gardi S.l.",
    "wof:placetype":"venue"
},
  "geometry": {"coordinates":[-3.8016889095,40.2015762329],"type":"Point"}
}