{
  "type": "Feature",
  "properties": {
    "addr:full":"Calle de Perez Casas, 1 San Jose Murcia 30800",
    "addr:housenumber":"1",
    "addr:postcode":"30800",
    "addr:street":"Calle De Perez Casas",
    "iso:country":"ES",
    "sg:address":"Calle de Perez Casas, 1",
    "sg:city":"San Jose",
    "sg:classifiers":[
        {
            "category":"Autos & Motor Vehicles",
            "subcategory":"Automobile Sales",
            "type":"Retail Goods"
        }
    ],
    "sg:phone":"+34 968 46 99 20",
    "sg:postcode":"30800",
    "sg:province":"Murcia",
    "wof:name":"Sanchez Morales Juan",
    "wof:placetype":"venue"
},
  "geometry": {"coordinates":[-1.6905640364,37.680557251],"type":"Point"}
}