{
  "type": "Feature",
  "properties": {
    "addr:full":"Calle de Iglesia, 3 Valderrodrigo Salamanca 37219",
    "addr:housenumber":"3",
    "addr:postcode":"37219",
    "addr:street":"Calle De Iglesia",
    "iso:country":"ES",
    "sg:address":"Calle de Iglesia, 3",
    "sg:city":"Valderrodrigo",
    "sg:orig_category":"Centros De Educaci\u00d3n Especial",
    "sg:phone":"+34 923 51 06 08",
    "sg:postcode":"37219",
    "sg:province":"Salamanca",
    "wof:name":"Ayuntamiento De Valderrodrigo",
    "wof:placetype":"venue"
},
  "geometry": {"coordinates":[-6.5081233978,41.0637779236],"type":"Point"}
}