{
  "type": "Feature",
  "properties": {
    "iso:country":"ES",
    "sg:address":"Pla\u00c7 Claustre Del Carme, S/n",
    "sg:city":"Mao",
    "sg:orig_category":"Mercer\u00cda, Lencer\u00cda (al Por Menor)",
    "sg:phone":"+34 971 35 03 36",
    "sg:postcode":"07701",
    "sg:province":"Islas Baleares",
    "wof:name":"Merceria Sapla\u00e7a S.l.",
    "wof:placetype":"venue"
},
  "geometry": {"coordinates":[4.2659897804,39.8886184692],"type":"Point"}
}