{
  "type": "Feature",
  "properties": {
    "addr:full":"Calle de Entretorres, S/n Talavera Reina Toledo 45600",
    "addr:housenumber":"s / n",
    "addr:postcode":"45600",
    "addr:street":"Calle De Entretorres",
    "iso:country":"ES",
    "sg:address":"Calle de Entretorres, S/n",
    "sg:city":"Talavera Reina",
    "sg:orig_category":"Sociedades, Compa\u00d1\u00cdas Aseguradoras",
    "sg:phone":"+34 925 72 14 57",
    "sg:postcode":"45600",
    "sg:province":"Toledo",
    "wof:name":"Mapfre Servicios De Informatica S.a.",
    "wof:placetype":"venue"
},
  "geometry": {"coordinates":[-4.8360118866,39.9569816589],"type":"Point"}
}