{
  "type": "Feature",
  "properties": {
    "iso:country":"ES",
    "sg:address":"Pase Castellana, 167",
    "sg:city":"Madrid",
    "sg:orig_category":"Instalaci\u00d3n, Reparaci\u00d3n De Ascensores Y Montacargas",
    "sg:phone":"+34 915 79 27 00",
    "sg:postcode":"28046",
    "sg:province":"Madrid",
    "sg:website":"www.orona.es",
    "wof:name":"Orona Scl",
    "wof:placetype":"venue"
},
  "geometry": {"coordinates":[-3.6903541088,40.4618148804],"type":"Point"}
}