{
  "type": "Feature",
  "properties": {
    "iso:country":"ES",
    "sg:address":"Calle de Carlos Trivi\u00d1o Moreno, 9",
    "sg:city":"Malaga",
    "sg:orig_category":"Asesor\u00cda Sobre Comunicaci\u00d3n De Empresas",
    "sg:phone":"+34 952 35 74 62",
    "sg:postcode":"29003",
    "sg:province":"M\u00e1laga",
    "wof:name":"Gomez De Los Rios Asesores S.l.",
    "wof:placetype":"venue"
},
  "geometry": {"coordinates":[-4.4438347816,36.700302124],"type":"Point"}
}