{
  "type": "Feature",
  "properties": {
    "addr:full":"Avda Elizatxo, 23 Irun Guip\u00f9zcoa 20303",
    "addr:housenumber":"23",
    "addr:postcode":"20303",
    "addr:street":"Avda Elizatxo;Guipu\u0300Zcoa",
    "iso:country":"ES",
    "sg:address":"Avda Elizatxo, 23",
    "sg:city":"Irun",
    "sg:orig_category":"Asesor\u00cda De Formaci\u00d3n Y Gesti\u00d3n De Personal",
    "sg:phone":"+34 943 62 04 23",
    "sg:postcode":"20303",
    "sg:province":"Guip\u00f9zcoa",
    "wof:name":"Gefepro S.l.",
    "wof:placetype":"venue"
},
  "geometry": {"coordinates":[-1.7990181446,43.3353004456],"type":"Point"}
}