{
  "type": "Feature",
  "properties": {
    "iso:country":"ES",
    "sg:address":"Pg Estacio, 10",
    "sg:city":"Balaguer",
    "sg:orig_category":"Centros M\u00c9dicos Y Sociales, Dispensarios",
    "sg:phone":"+34 973 44 81 13",
    "sg:postcode":"25600",
    "sg:province":"Lleida",
    "wof:name":"Montserrat Pifarre Torres Medical Sport Consulting C.b.",
    "wof:placetype":"venue"
},
  "geometry": {"coordinates":[0.8089619875,41.7892074585],"type":"Point"}
}