{
  "type": "Feature",
  "properties": {
    "addr:full":"C/ Madrid, De, 1 S. Antoni Portmany Islas Baleares 07820",
    "addr:postcode":"07820",
    "addr:street":"C / Madrid De 1 S. Antoni Portmany",
    "iso:country":"ES",
    "sg:address":"C/ Madrid, De, 1",
    "sg:city":"S. Antoni Portmany",
    "sg:orig_category":"Complementos De Vestir (al Por Menor)",
    "sg:phone":"+34 971 34 59 16",
    "sg:postcode":"07820",
    "sg:province":"Islas Baleares",
    "wof:name":"Alcon Merino Luisa",
    "wof:placetype":"venue"
},
  "geometry": {"coordinates":[1.2791874409,38.9717292786],"type":"Point"}
}