{
  "type": "Feature",
  "properties": {
    "addr:full":"Carrer de Valencia, 141 Barcelona Barcelona 08011",
    "addr:housenumber":"141",
    "addr:postcode":"08011",
    "addr:street":"Carrer De Valencia",
    "iso:country":"ES",
    "sg:address":"Carrer de Valencia, 141",
    "sg:city":"Barcelona",
    "sg:orig_category":"Filatelia",
    "sg:phone":"+34 933 23 33 82",
    "sg:postcode":"08011",
    "sg:province":"Barcelona",
    "sg:website":"www.notafiliacari.com",
    "wof:name":"Notafilia Cari S.c.p.",
    "wof:placetype":"venue"
},
  "geometry": {"coordinates":[2.1558279991,41.3872566223],"type":"Point"}
}