{
  "type": "Feature",
  "properties": {
    "addr:full":"Pol Ind Las Yeguas, 13 Sanlucar Mayor Sevilla 41800",
    "addr:housenumber":"13",
    "addr:postcode":"41800",
    "addr:street":"Yeguas",
    "iso:country":"ES",
    "sg:address":"Pol Ind Las Yeguas, 13",
    "sg:city":"Sanlucar Mayor",
    "sg:orig_category":"Electricidad: Instaladores",
    "sg:phone":"+34 955 70 35 95",
    "sg:postcode":"41800",
    "sg:province":"Sevilla",
    "wof:name":"Hegisan Electricidad Y Mantenimento S.l.",
    "wof:placetype":"venue"
},
  "geometry": {"coordinates":[-6.1956338882,37.3855361938],"type":"Point"}
}