{
  "type": "Feature",
  "properties": {
    "addr:full":"Calle de Pedro Icaza Aguirre, 17 Santurtzi Vizcaya 48980",
    "addr:housenumber":"17",
    "addr:postcode":"48980",
    "addr:street":"Calle De Pedro Icaza Aguirre",
    "iso:country":"ES",
    "sg:address":"Calle de Pedro Icaza Aguirre, 17",
    "sg:city":"Santurtzi",
    "sg:orig_category":"Alimentaci\u00d3n General (al Por Menor)",
    "sg:phone":"+34 944 83 43 03",
    "sg:postcode":"48980",
    "sg:province":"Vizcaya",
    "wof:name":"Distribuciones Txema",
    "wof:placetype":"venue"
},
  "geometry": {"coordinates":[-3.0294349194,43.3262252808],"type":"Point"}
}