{
  "type": "Feature",
  "properties": {
    "iso:country":"ES",
    "sg:address":"Ctra. Fregeneda, 20",
    "sg:city":"Villaseco Gamitos",
    "sg:orig_category":"Cerrajer\u00cda, Ferrallista",
    "sg:phone":"+34 923 14 04 21",
    "sg:postcode":"37114",
    "sg:province":"Salamanca",
    "wof:name":"Hernandez Garcia Salustiano",
    "wof:placetype":"venue"
},
  "geometry": {"coordinates":[-6.1104512215,41.0353851318],"type":"Point"}
}