{
  "type": "Feature",
  "properties": {
    "addr:full":"Calle de Mallabarrena, S/n Mallabia Vizcaya 48269",
    "addr:housenumber":"s / n",
    "addr:postcode":"48269",
    "addr:street":"Calle De Mallabarrena",
    "iso:country":"ES",
    "sg:address":"Calle de Mallabarrena, S/n",
    "sg:city":"Mallabia",
    "sg:orig_category":"Rectificaci\u00d3n, Mecanizado, Fresado",
    "sg:phone":"+34 943 17 03 10",
    "sg:postcode":"48269",
    "sg:province":"Vizcaya",
    "sg:website":"www.talleresmalla.com",
    "wof:name":"Talleres Malla S. L.",
    "wof:placetype":"venue"
},
  "geometry": {"coordinates":[-2.5305562019,43.1853523254],"type":"Point"}
}