{
  "type": "Feature",
  "properties": {
    "addr:full":"Calle de Salvador Lluch, 10 Valencia Valencia 46006",
    "addr:housenumber":"10",
    "addr:postcode":"46006",
    "addr:street":"Calle De Salvador Lluch",
    "iso:country":"ES",
    "sg:address":"Calle de Salvador Lluch, 10",
    "sg:city":"Valencia",
    "sg:orig_category":"Mec\u00c1nico Del Autom\u00d3vil",
    "sg:phone":"+34 963 73 93 52",
    "sg:postcode":"46006",
    "sg:province":"Valencia",
    "wof:name":"Sanchis Olmeda Alberto",
    "wof:placetype":"venue"
},
  "geometry": {"coordinates":[-0.3681760132,39.4583702087],"type":"Point"}
}