{
  "type": "Feature",
  "properties": {
    "addr:full":"Carrer de Pais Valencia, 2 Cala Alicante 03509",
    "addr:housenumber":"2",
    "addr:postcode":"03509",
    "addr:street":"Carrer De Pais Valencia",
    "iso:country":"ES",
    "sg:address":"Carrer de Pais Valencia, 2",
    "sg:city":"Cala",
    "sg:orig_category":"Ropa De Hogar (al Por Menor)",
    "sg:phone":"+34 965 86 17 94",
    "sg:postcode":"03509",
    "sg:province":"Alicante",
    "sg:website":"www.zarahome.com",
    "wof:name":"Zara Home Espa\u00d1a S.a.",
    "wof:placetype":"venue"
},
  "geometry": {"coordinates":[-0.1818955988,38.5348205566],"type":"Point"}
}