{
  "type": "Feature",
  "properties": {
    "iso:country":"ES",
    "sg:address":"Calle de Torre (la), 3",
    "sg:city":"Le\u00f3n",
    "sg:orig_category":"Aparcamientos (infraestructuras, Accesorios)",
    "sg:phone":"+34 987 24 80 08",
    "sg:postcode":"24002",
    "sg:province":"Le\u00f3n",
    "wof:name":"Gutierrez Gonzalez-fierro Jesus",
    "wof:placetype":"venue"
},
  "geometry": {"coordinates":[-5.5716609955,42.5981369019],"type":"Point"}
}