{
  "type": "Feature",
  "properties": {
    "iso:country":"ES",
    "sg:address":"Plaz Maria Agustina, 5",
    "sg:city":"Castellon",
    "sg:orig_category":"Ense\u00d1anza, Formaci\u00d3n Profesional: Aprendizaje",
    "sg:phone":"+34 964 35 86 88",
    "sg:postcode":"12...",
    "sg:province":"Castell\u00f3n",
    "sg:website":"www.comunitatvalenciana.com",
    "wof:name":"Generalitat Valenciana",
    "wof:placetype":"venue"
},
  "geometry": {"coordinates":[-0.0360242017,39.9860687256],"type":"Point"}
}