{
  "type": "Feature",
  "properties": {
    "iso:country":"ES",
    "sg:address":"Pase Canalejas, 66",
    "sg:city":"Santander",
    "sg:orig_category":"Alimentaci\u00d3n General (al Por Menor)",
    "sg:phone":"+34 942 27 01 70",
    "sg:postcode":"39004",
    "sg:province":"Cantabria",
    "wof:name":"Cantabria En Su Mesa S.l.",
    "wof:placetype":"venue"
},
  "geometry": {"coordinates":[-3.7883589268,43.46534729],"type":"Point"}
}