{
  "type": "Feature",
  "properties": {
    "addr:full":"Urb Villas Golf, 8 Illescas Toledo 45200",
    "addr:postcode":"45200",
    "addr:street":"Urb",
    "iso:country":"ES",
    "sg:address":"Urb Villas Golf, 8",
    "sg:city":"Illescas",
    "sg:orig_category":"Chapister\u00cda",
    "sg:phone":"+34 925 51 33 57",
    "sg:postcode":"45200",
    "sg:province":"Toledo",
    "wof:name":"Eurocor S. A.",
    "wof:placetype":"venue"
},
  "geometry": {"coordinates":[-3.8458640575,40.1230163574],"type":"Point"}
}