{
  "type": "Feature",
  "properties": {
    "addr:full":"Calle de Iglesia, 30 Villacastin Segovia 40150",
    "addr:housenumber":"30",
    "addr:postcode":"40150",
    "addr:street":"Calle De Iglesia",
    "iso:country":"ES",
    "sg:address":"Calle de Iglesia, 30",
    "sg:city":"Villacastin",
    "sg:orig_category":"Electrodom\u00c9sticos (fabricaci\u00d3n, Al Por Mayor)",
    "sg:phone":"+34 921 19 82 88",
    "sg:postcode":"40150",
    "sg:province":"Segovia",
    "wof:name":"Sanz Sanz Santiago",
    "wof:placetype":"venue"
},
  "geometry": {"coordinates":[-4.4111652374,40.7803115845],"type":"Point"}
}