{
  "type": "Feature",
  "properties": {
    "iso:country":"ES",
    "sg:address":"Calle de Virgen De La Almudena, 6",
    "sg:city":"Benidorm",
    "sg:orig_category":"Asesor\u00cda Para La Organizaci\u00d3n Y Gesti\u00d3n Del Transporte",
    "sg:phone":"+34 966 80 84 00",
    "sg:postcode":"03500",
    "sg:province":"Alicante",
    "sg:website":"www.nacex.es",
    "wof:name":"Calpexpress Sl",
    "wof:placetype":"venue"
},
  "geometry": {"coordinates":[-0.1334580034,38.5440597534],"type":"Point"}
}