{
  "type": "Feature",
  "properties": {
    "addr:full":"Pg Maritim, 95 Santa Margarida-salatar Girona 17480",
    "addr:housenumber":"95",
    "addr:postcode":"17480",
    "addr:street":"Pg Maritim",
    "iso:country":"ES",
    "sg:address":"Pg Maritim, 95",
    "sg:city":"Santa Margarida-salatar",
    "sg:orig_category":"Molduras, Junquillos, Listones Y Molduras Perforadas",
    "sg:phone":"+34 972 15 25 68",
    "sg:postcode":"17480",
    "sg:province":"Girona",
    "wof:name":"Nova Cuina 1.999 S.l.",
    "wof:placetype":"venue"
},
  "geometry": {"coordinates":[3.1509261131,42.2604904175],"type":"Point"}
}