{
  "type": "Feature",
  "properties": {
    "iso:country":"ES",
    "sg:address":"Calle de Alcala, 342",
    "sg:city":"Madrid",
    "sg:orig_category":"Ropa Para Ni\u00d1os (al Por Menor)",
    "sg:phone":"+34 913 67 53 68",
    "sg:postcode":"28027",
    "sg:province":"Madrid",
    "wof:name":"Tebaran Equity S.l.",
    "wof:placetype":"venue"
},
  "geometry": {"coordinates":[-3.6451458931,40.4343681335],"type":"Point"}
}