{
  "type": "Feature",
  "properties": {
    "iso:country":"ES",
    "sg:address":"Carrer de Canigo, 41",
    "sg:city":"S. Feliu Guixols",
    "sg:orig_category":"Ense\u00d1anza, Formaci\u00d3n Profesional: Aprendizaje",
    "sg:phone":"+34 972 82 16 46",
    "sg:postcode":"17220",
    "sg:province":"Girona",
    "wof:name":"Centre De Telecomunicaciones De Catalunya",
    "wof:placetype":"venue"
},
  "geometry": {"coordinates":[3.0247399807,41.7939834595],"type":"Point"}
}