{
  "type": "Feature",
  "properties": {
    "addr:full":"Rua Navas, 11 Navas Pontevedra 36391",
    "addr:housenumber":"11",
    "addr:postcode":"36391",
    "addr:street":"Rua Navas",
    "iso:country":"ES",
    "sg:address":"Rua Navas, 11",
    "sg:city":"Navas",
    "sg:orig_category":"Empresarios",
    "sg:phone":"+34 986 36 55 58",
    "sg:postcode":"36391",
    "sg:province":"Pontevedra",
    "wof:name":"Fundacion Menela",
    "wof:placetype":"venue"
},
  "geometry": {"coordinates":[-8.8210258484,42.1536941528],"type":"Point"}
}