{
  "type": "Feature",
  "properties": {
    "iso:country":"ES",
    "sg:address":"Disseminat, S/n",
    "sg:city":"Perafita",
    "sg:orig_category":"Cr\u00cda De Cerdos",
    "sg:phone":"+34 938 53 01 53",
    "sg:postcode":"08589",
    "sg:province":"Barcelona",
    "wof:name":"Sociedad Agraria De Transformacion N 578",
    "wof:placetype":"venue"
},
  "geometry": {"coordinates":[-97.78224945069999,45.7040786743],"type":"Point"}
}