{
  "type": "Feature",
  "properties": {
    "iso:country":"ES",
    "sg:address":"A Igrexa, 204",
    "sg:city":"Mos",
    "sg:orig_category":"Gas: Botellas Y Contenedores",
    "sg:phone":"+34 986 33 23 72",
    "sg:postcode":"36416",
    "sg:province":"Pontevedra",
    "wof:name":"Uniprosa De Vigo S. L.",
    "wof:placetype":"venue"
},
  "geometry": {"coordinates":[-8.6403799057,42.1906967163],"type":"Point"}
}