{
  "type": "Feature",
  "properties": {
    "addr:full":"Calle de Relator Gonzalez, 2 Hervas C\u00e1ceres 10700",
    "addr:housenumber":"2",
    "addr:postcode":"10700",
    "addr:street":"Calle De Relator Gonzalez;Ca\u0301Ceres",
    "iso:country":"ES",
    "sg:address":"Calle de Relator Gonzalez, 2",
    "sg:city":"Hervas",
    "sg:orig_category":"Electrodom\u00c9sticos (al Por Menor)",
    "sg:phone":"+34 927 48 16 27",
    "sg:postcode":"10700",
    "sg:province":"C\u00e1ceres",
    "wof:name":"Gomez Santos Pedro",
    "wof:placetype":"venue"
},
  "geometry": {"coordinates":[-5.8577799797,40.2741775513],"type":"Point"}
}