{
  "type": "Feature",
  "properties": {
    "iso:country":"ES",
    "sg:address":"Av Gatassa, 73",
    "sg:city":"Mataro",
    "sg:orig_category":"\u00d3ptica: Instrumentos (fabricaci\u00d3n)",
    "sg:phone":"+34 937 99 40 61",
    "sg:postcode":"08303",
    "sg:province":"Barcelona",
    "wof:name":"Ximenes I Fills S. A.",
    "wof:placetype":"venue"
},
  "geometry": {"coordinates":[2.4276218414,41.5378341675],"type":"Point"}
}