{
  "type": "Feature",
  "properties": {
    "addr:full":"Carrer de Comedies, 31 Sabadell Barcelona 08202",
    "addr:housenumber":"31",
    "addr:postcode":"08202",
    "addr:street":"Carrer De Comedies",
    "iso:country":"ES",
    "sg:address":"Carrer de Comedies, 31",
    "sg:city":"Sabadell",
    "sg:orig_category":"Tapicer\u00cdas",
    "sg:phone":"+34 937 25 67 48",
    "sg:postcode":"08202",
    "sg:province":"Barcelona",
    "wof:name":"Molina Valls Jose",
    "wof:placetype":"venue"
},
  "geometry": {"coordinates":[2.1100480556,41.5494499207],"type":"Point"}
}