{
  "type": "Feature",
  "properties": {
    "iso:country":"ES",
    "sg:address":"C/ Vicent Andres Estelles, 30",
    "sg:city":"Elche",
    "sg:orig_category":"Art\u00cdculos De Regalo (al Por Menor)",
    "sg:phone":"+34 965 42 61 94",
    "sg:postcode":"03202",
    "sg:province":"Alicante",
    "wof:name":"Regalos Andrea S.c.",
    "wof:placetype":"venue"
},
  "geometry": {"coordinates":[-0.6804019809,38.2726402283],"type":"Point"}
}