{
  "type": "Feature",
  "properties": {
    "iso:country":"ES",
    "sg:address":"Carrer de Pere Grau, 9",
    "sg:city":"Masnou",
    "sg:orig_category":"Administradores De Bienes Y Delegados De Comunidades De Propietarios",
    "sg:phone":"+34 935 55 65 06",
    "sg:postcode":"08320",
    "sg:province":"Barcelona",
    "wof:name":"Gabinet Ocata S.l.",
    "wof:placetype":"venue"
},
  "geometry": {"coordinates":[2.3240940571,41.4811401367],"type":"Point"}
}