{
  "type": "Feature",
  "properties": {
    "addr:full":"Avda Alfredo Nobel, 121 Torrevieja Alicante 03180",
    "addr:housenumber":"121",
    "addr:postcode":"03180",
    "addr:street":"Avda Alfredo Nobel",
    "iso:country":"ES",
    "sg:address":"Avda Alfredo Nobel, 121",
    "sg:city":"Torrevieja",
    "sg:orig_category":"Asesor\u00cda Sobre Comunicaci\u00d3n De Empresas",
    "sg:phone":"+34 965 70 67 99",
    "sg:postcode":"03180",
    "sg:province":"Alicante",
    "wof:name":"Norsk Servicesenter S.l.",
    "wof:placetype":"venue"
},
  "geometry": {"coordinates":[-0.6536790133,38.0173606873],"type":"Point"}
}