{
  "type": "Feature",
  "properties": {
    "addr:full":"Av Pau Casals, 31 S. Quirze Valles Barcelona 08192",
    "addr:housenumber":"31",
    "addr:postcode":"08192",
    "addr:street":"Av Pau Casals",
    "iso:country":"ES",
    "sg:address":"Av Pau Casals, 31",
    "sg:city":"S. Quirze Valles",
    "sg:orig_category":"Alquiler De V\u00cddeo",
    "sg:phone":"+34 937 21 10 27",
    "sg:postcode":"08192",
    "sg:province":"Barcelona",
    "wof:name":"Aguilar Melgarejo Antonio",
    "wof:placetype":"venue"
},
  "geometry": {"coordinates":[2.082808733,41.5323829651],"type":"Point"}
}