{
  "type": "Feature",
  "properties": {
    "addr:full":"Calle de Teruel, 10 Ejea De Los Caballeros Zaragoza 50600",
    "addr:housenumber":"10",
    "addr:postcode":"50600",
    "addr:street":"Calle De Teruel",
    "iso:country":"ES",
    "sg:address":"Calle de Teruel, 10",
    "sg:city":"Ejea De Los Caballeros",
    "sg:orig_category":"Agricultores, Agricultores",
    "sg:phone":"+34 976 66 07 09",
    "sg:postcode":"50600",
    "sg:province":"Zaragoza",
    "wof:name":"Herposa Explotacion Agropecuaria",
    "wof:placetype":"venue"
},
  "geometry": {"coordinates":[-1.1395219564,42.1239547729],"type":"Point"}
}