{
  "type": "Feature",
  "properties": {
    "addr:full":"Barr Hazas, S/n Hazas Cantabria 39776",
    "addr:housenumber":"s / n",
    "addr:postcode":"39776",
    "addr:street":"Hazas",
    "iso:country":"ES",
    "sg:address":"Barr Hazas, S/n",
    "sg:city":"Hazas",
    "sg:orig_category":"Empresarios",
    "sg:phone":"+34 942 64 30 24",
    "sg:postcode":"39776",
    "sg:province":"Cantabria",
    "wof:name":"Dehesa Fernandez Feliciano",
    "wof:placetype":"venue"
},
  "geometry": {"coordinates":[-3.3817749023,43.393321991],"type":"Point"}
}