{
  "type": "Feature",
  "properties": {
    "iso:country":"ES",
    "sg:address":"Calle de Bidebarrieta, 1",
    "sg:city":"Bilbao",
    "sg:orig_category":"Psic\u00d3logos",
    "sg:phone":"+34 944 15 25 98",
    "sg:postcode":"48005",
    "sg:province":"Vizcaya",
    "wof:name":"Aitor Urieta Guijarro",
    "wof:placetype":"venue"
},
  "geometry": {"coordinates":[-2.9245612621,43.2591094971],"type":"Point"}
}