{
  "type": "Feature",
  "properties": {
    "addr:full":"Trva Avenida De La Reguera, S/n Langreo Asturias 33930",
    "addr:housenumber":"s / n",
    "addr:postcode":"33930",
    "addr:street":"Avenida De La Reguera",
    "iso:country":"ES",
    "sg:address":"Trva Avenida De La Reguera, S/n",
    "sg:city":"Langreo",
    "sg:orig_category":"Refiner\u00cdas De Petr\u00d3leo",
    "sg:phone":"+34 985 69 74 51",
    "sg:postcode":"33930",
    "sg:province":"Asturias",
    "sg:website":"www.cepsa.es",
    "wof:name":"Cedipsa Compa\u00d1ia Espa\u00d1ola Distribuidora De Petroleos S.a.",
    "wof:placetype":"venue"
},
  "geometry": {"coordinates":[-5.7070870399,43.3195877075],"type":"Point"}
}