{
  "type": "Feature",
  "properties": {
    "addr:full":"Carrer de Salvador Juncadella, 26 Manlleu Barcelona 08560",
    "addr:housenumber":"26",
    "addr:postcode":"08560",
    "addr:street":"Carrer De Salvador Juncadella",
    "iso:country":"ES",
    "sg:address":"Carrer de Salvador Juncadella, 26",
    "sg:city":"Manlleu",
    "sg:orig_category":"Fabricaci\u00d3n De Sobres, Bolsas Y Fundas",
    "sg:phone":"+34 938 50 74 95",
    "sg:postcode":"08560",
    "sg:province":"Barcelona",
    "sg:website":"www.capsart.btlmk.net",
    "wof:name":"Cap\u00e7'art S.l.",
    "wof:placetype":"venue"
},
  "geometry": {"coordinates":[2.2919659615,42.0067176819],"type":"Point"}
}