{
  "type": "Feature",
  "properties": {
    "iso:country":"ES",
    "sg:address":"Pl Joaquim Bau (de), 4",
    "sg:city":"Tortosa",
    "sg:orig_category":"Reposter\u00cdas",
    "sg:phone":"+34 977 50 29 28",
    "sg:postcode":"43500",
    "sg:province":"Tarragona",
    "wof:name":"Cugat Costa Juan",
    "wof:placetype":"venue"
},
  "geometry": {"coordinates":[0.5161370039,40.8137016296],"type":"Point"}
}