{
  "type": "Feature",
  "properties": {
    "addr:full":"Avda Pintor Portela, 4 Cartagena Murcia 30203",
    "addr:housenumber":"4",
    "addr:postcode":"30203",
    "addr:street":"Avda Pintor Portela",
    "iso:country":"ES",
    "sg:address":"Avda Pintor Portela, 4",
    "sg:city":"Cartagena",
    "sg:orig_category":"Institutos De Belleza",
    "sg:phone":"+34 968 52 92 73",
    "sg:postcode":"30203",
    "sg:province":"Murcia",
    "wof:name":"Gallego Ca\u00f1avate Mercedes",
    "wof:placetype":"venue"
},
  "geometry": {"coordinates":[-0.9747419953,37.6061973572],"type":"Point"}
}