{
  "type": "Feature",
  "properties": {
    "addr:full":"Calle de Constitucion (de La), 89 Alcobendas Madrid 28100",
    "addr:housenumber":"89",
    "addr:postcode":"28100",
    "addr:street":"Calle De Constitucion De La",
    "iso:country":"ES",
    "sg:address":"Calle de Constitucion (de La), 89",
    "sg:city":"Alcobendas",
    "sg:orig_category":"Material Y Suministros Para Perforaciones, Sondeos",
    "sg:phone":"+34 916 52 21 54",
    "sg:postcode":"28100",
    "sg:province":"Madrid",
    "wof:name":"Excavaciones Y Derribos Lopez S.l.",
    "wof:placetype":"venue"
},
  "geometry": {"coordinates":[-3.6410083771,40.5446014404],"type":"Point"}
}