{
  "type": "Feature",
  "properties": {
    "addr:full":"Carrer de Ausias Marc, 71 Barcelona Barcelona 08013",
    "addr:housenumber":"71",
    "addr:postcode":"08013",
    "addr:street":"Carrer De Ausias Marc",
    "iso:country":"ES",
    "sg:address":"Carrer de Ausias Marc, 71",
    "sg:city":"Barcelona",
    "sg:orig_category":"Abogados",
    "sg:phone":"+34 932 31 49 00",
    "sg:postcode":"08013",
    "sg:province":"Barcelona",
    "wof:name":"Perez Seuma Neus",
    "wof:placetype":"venue"
},
  "geometry": {"coordinates":[2.179090023,41.393951416],"type":"Point"}
}