{
  "type": "Feature",
  "properties": {
    "addr:full":"Carrer de Gran De Sant Andreu, 50 Barcelona Barcelona 08030",
    "addr:housenumber":"50",
    "addr:postcode":"08030",
    "addr:street":"Carrer De Gran De Sant Andreu",
    "iso:country":"ES",
    "sg:address":"Carrer de Gran De Sant Andreu, 50",
    "sg:city":"Barcelona",
    "sg:orig_category":"Asociaciones Y Clubs Deportivos",
    "sg:phone":"+34 933 11 03 04",
    "sg:postcode":"08030",
    "sg:province":"Barcelona",
    "wof:name":"Gimnasio Deportivo San Andres S.a.",
    "wof:placetype":"venue"
},
  "geometry": {"coordinates":[2.1903500557,41.429233551],"type":"Point"}
}