{
  "type": "Feature",
  "properties": {
    "addr:full":"Calle de Industria (de La), 7 Jerez De La Frontera C\u00e1diz 11407",
    "addr:housenumber":"7",
    "addr:postcode":"11407",
    "addr:street":"Calle De Industria De La",
    "iso:country":"ES",
    "sg:address":"Calle de Industria (de La), 7",
    "sg:city":"Jerez De La Frontera",
    "sg:orig_category":"Vinos (agentes)",
    "sg:phone":"+34 956 30 73 34",
    "sg:postcode":"11407",
    "sg:province":"C\u00e1diz",
    "sg:website":"www.dat-tripodi.de",
    "wof:name":"Datripodi Import Sl.",
    "wof:placetype":"venue"
},
  "geometry": {"coordinates":[-6.116964817,36.7092208862],"type":"Point"}
}