{
  "type": "Feature",
  "properties": {
    "addr:full":"Siderurgia(pol. Bankunion Ii), 3 Gijon Asturias 33211",
    "addr:housenumber":"3",
    "addr:postcode":"33211",
    "addr:street":"Pol.;Ii",
    "iso:country":"ES",
    "sg:address":"Siderurgia(pol. Bankunion Ii), 3",
    "sg:city":"Gijon",
    "sg:orig_category":"Acero: Productos Sider\u00dargicos Y Transformados (fabricaci\u00d3n, Negocio)",
    "sg:phone":"+34 985 32 12 12",
    "sg:postcode":"33211",
    "sg:province":"Asturias",
    "wof:name":"Metalnet S.l.",
    "wof:placetype":"venue"
},
  "geometry": {"coordinates":[-5.7107639313,43.5276756287],"type":"Point"}
}