{
  "type": "Feature",
  "properties": {
    "addr:full":"Rua Real, 164 Ferrol La Coru\u00f1a 15402",
    "addr:housenumber":"164",
    "addr:postcode":"15402",
    "addr:street":"Rua Real;La Corun\u0303A",
    "iso:country":"ES",
    "sg:address":"Rua Real, 164",
    "sg:city":"Ferrol",
    "sg:orig_category":"Farmacias",
    "sg:phone":"+34 981 35 15 64",
    "sg:postcode":"15402",
    "sg:province":"La Coru\u00f1a",
    "wof:name":"Sanchez Y Sande C.b.",
    "wof:placetype":"venue"
},
  "geometry": {"coordinates":[-8.2386188507,43.4817314148],"type":"Point"}
}