{
  "type": "Feature",
  "properties": {
    "iso:country":"ES",
    "sg:address":"Pg Delicies(les), 15",
    "sg:city":"Bellvis",
    "sg:orig_category":"Electricidad: Instaladores",
    "sg:phone":"+34 973 56 52 14",
    "sg:postcode":"25142",
    "sg:province":"Lleida",
    "wof:name":"Torrent Lopez Juan",
    "wof:placetype":"venue"
},
  "geometry": {"coordinates":[0.8152300119,41.6714897156],"type":"Point"}
}