{
  "type": "Feature",
  "properties": {
    "addr:full":"Calle de Gerona, 8 San Sebastian De Los Reyes Madrid 28700",
    "addr:housenumber":"8",
    "addr:postcode":"28700",
    "addr:street":"Calle De Gerona",
    "iso:country":"ES",
    "sg:address":"Calle de Gerona, 8",
    "sg:city":"San Sebastian De Los Reyes",
    "sg:orig_category":"Artes Gr\u00c1ficas, Artes Pl\u00c1sticas (curso)",
    "sg:phone":"+34 916 52 72 80",
    "sg:postcode":"28700",
    "sg:province":"Madrid",
    "wof:name":"Regidor Sanz Victorio",
    "wof:placetype":"venue"
},
  "geometry": {"coordinates":[-3.6363363266,40.5513381958],"type":"Point"}
}