{
  "type": "Feature",
  "properties": {
    "iso:country":"ES",
    "sg:address":"Calle de Soria, 1",
    "sg:city":"Burgos",
    "sg:orig_category":"Abogados",
    "sg:phone":"+34 947 21 80 95",
    "sg:postcode":"09004",
    "sg:province":"Burgos",
    "wof:name":"Garcia De Viedma Serrano Enrique Y Otro S.c.",
    "wof:placetype":"venue"
},
  "geometry": {"coordinates":[-3.6898341179,42.3458328247],"type":"Point"}
}