{
  "type": "Feature",
  "properties": {
    "addr:full":"Calle de Marceliano Santa Maria, 8 Madrid Madrid 28036",
    "addr:housenumber":"8",
    "addr:postcode":"madrid;28036",
    "addr:street":"Calle De Marceliano Santa Maria",
    "iso:country":"ES",
    "sg:address":"Calle de Marceliano Santa Maria, 8",
    "sg:city":"Madrid",
    "sg:orig_category":"Agencias De Viajes",
    "sg:phone":"+34 915 62 07 40",
    "sg:postcode":"28036",
    "sg:province":"Madrid",
    "wof:name":"Set Viajes Madrid S.l.",
    "wof:placetype":"venue"
},
  "geometry": {"coordinates":[-3.68821311,40.4512252808],"type":"Point"}
}