{
  "type": "Feature",
  "properties": {
    "addr:full":"Plaz Espa\u00d1a (de), 13 Alhondiga Guadalajara 19132",
    "addr:postcode":"19132",
    "addr:street":"Plaz",
    "iso:country":"ES",
    "sg:address":"Plaz Espa\u00d1a (de), 13",
    "sg:city":"Alhondiga",
    "sg:orig_category":"Farmacias",
    "sg:phone":"+34 949 28 40 52",
    "sg:postcode":"19132",
    "sg:province":"Guadalajara",
    "wof:name":"Martinez Sanchez Maria Jose",
    "wof:placetype":"venue"
},
  "geometry": {"coordinates":[-2.819865942,40.5266151428],"type":"Point"}
}