{
  "type": "Feature",
  "properties": {
    "iso:country":"ES",
    "sg:address":"Calle de Rey Juan Carlos, 13",
    "sg:city":"Villanueva De Los Infantes",
    "sg:orig_category":"Mercer\u00cda, Lencer\u00cda (al Por Menor)",
    "sg:phone":"+34 926 36 00 37",
    "sg:postcode":"13320",
    "sg:province":"Ciudad Real",
    "wof:name":"Hurtado Garcia Primitivo",
    "wof:placetype":"venue"
},
  "geometry": {"coordinates":[-3.0137300491,38.7371902466],"type":"Point"}
}