{
  "type": "Feature",
  "properties": {
    "addr:full":"Ctra. Estella, S/n Abarzuza Navarra 31178",
    "addr:housenumber":"s",
    "addr:postcode":"31178",
    "addr:street":"Ctra. Estella;/ N Abarzuza Navarra",
    "iso:country":"ES",
    "sg:address":"Ctra. Estella, S/n",
    "sg:city":"Abarzuza",
    "sg:orig_category":"Maquinaria Para Industrias Diversas",
    "sg:phone":"+34 948 52 01 56",
    "sg:postcode":"31178",
    "sg:province":"Navarra",
    "wof:name":"Andueza Izcue Miguel",
    "wof:placetype":"venue"
},
  "geometry": {"coordinates":[-2.0211446285,42.716999054],"type":"Point"}
}