{
  "type": "Feature",
  "properties": {
    "iso:country":"ES",
    "sg:address":"Calle de Longares, 2",
    "sg:city":"Madrid",
    "sg:orig_category":"Caf\u00c9s, Bares, Cervecer\u00cdas",
    "sg:phone":"+34 913 06 53 53",
    "sg:postcode":"28022",
    "sg:province":"Madrid",
    "wof:name":"De Gracia Lillo Juan Carlos",
    "wof:placetype":"venue"
},
  "geometry": {"coordinates":[-3.6099369526,40.432674408],"type":"Point"}
}