{
  "type": "Feature",
  "properties": {
    "iso:country":"ES",
    "sg:address":"Psaj Loarre, 1",
    "sg:city":"Monzon",
    "sg:orig_category":"Fotograf\u00cda Y Cine: Aparatos, Pel\u00cdculas Y Accesorios (al Por Menor)",
    "sg:phone":"+34 974 40 09 25",
    "sg:postcode":"22400",
    "sg:province":"Huesca",
    "wof:name":"Puig Guivernau Juan",
    "wof:placetype":"venue"
},
  "geometry": {"coordinates":[0.1920070052,41.9124641418],"type":"Point"}
}