{
  "type": "Feature",
  "properties": {
    "addr:full":"Ctra. Cap De Barberia, 1916 S. Francesc Formentera Islas Baleares 07860",
    "addr:housenumber":"1916",
    "addr:postcode":"07860",
    "addr:street":"Ctra. Cap De Barberia;S. Francesc",
    "iso:country":"ES",
    "sg:address":"Ctra. Cap De Barberia, 1916",
    "sg:city":"S. Francesc Formentera",
    "sg:orig_category":"Promotores Constructores",
    "sg:phone":"+34 971 32 25 48",
    "sg:postcode":"07860",
    "sg:province":"Islas Baleares",
    "wof:name":"Construcciones Agustin Moya Ortiz S.l.",
    "wof:placetype":"venue"
},
  "geometry": {"coordinates":[1.4254900217,38.6987304688],"type":"Point"}
}