{
  "type": "Feature",
  "properties": {
    "iso:country":"ES",
    "sg:address":"Calle de Manuel Luna, 1",
    "sg:city":"Madrid",
    "sg:orig_category":"Producci\u00d3n, Venta De Productos De Agricultura Biol\u00d3gica",
    "sg:phone":"+34 915 70 92 60",
    "sg:postcode":"28020",
    "sg:province":"Madrid",
    "wof:name":"Alvarez Redondo-marin Mariam",
    "wof:placetype":"venue"
},
  "geometry": {"coordinates":[-3.7024834156,40.455039978],"type":"Point"}
}