{
  "type": "Feature",
  "properties": {
    "addr:full":"Carr Sant Esteve, 3 Mao Islas Baleares 07703",
    "addr:housenumber":"3",
    "addr:postcode":"07703",
    "addr:street":"Carr Sant Esteve",
    "iso:country":"ES",
    "sg:address":"Carr Sant Esteve, 3",
    "sg:city":"Mao",
    "sg:orig_category":"Asesor\u00cda Sobre Comunicaci\u00d3n De Empresas",
    "sg:phone":"+34 971 35 40 86",
    "sg:postcode":"07703",
    "sg:province":"Islas Baleares",
    "sg:website":"www.ccriera.com",
    "wof:name":"Centro Contable Riera S.l.",
    "wof:placetype":"venue"
},
  "geometry": {"coordinates":[4.2564001083,39.8884010315],"type":"Point"}
}