{
  "type": "Feature",
  "properties": {
    "addr:full":"Calle de Campomanes, 6 Oviedo Asturias 33008",
    "addr:housenumber":"6",
    "addr:postcode":"33008",
    "addr:street":"Calle De Campomanes",
    "iso:country":"ES",
    "sg:address":"Calle de Campomanes, 6",
    "sg:city":"Oviedo",
    "sg:orig_category":"Centros Empresariales",
    "sg:phone":"+34 985 21 10 19",
    "sg:postcode":"33008",
    "sg:province":"Asturias",
    "wof:name":"Milenia Asturias S.l",
    "wof:placetype":"venue"
},
  "geometry": {"coordinates":[-5.8463215828,43.3583145142],"type":"Point"}
}