{
  "type": "Feature",
  "properties": {
    "iso:country":"ES",
    "sg:address":"Avda Esla (el), 2",
    "sg:city":"Santa Maria Del Paramo",
    "sg:orig_category":"Electrodom\u00c9sticos (al Por Menor)",
    "sg:phone":"+34 987 35 17 18",
    "sg:postcode":"24240",
    "sg:province":"Le\u00f3n",
    "wof:name":"Dominguez Franco Clemente",
    "wof:placetype":"venue"
},
  "geometry": {"coordinates":[-5.7478938103,42.3557701111],"type":"Point"}
}