{
  "type": "Feature",
  "properties": {
    "addr:full":"Avgd De L'alt Urgell, 112 Oliana Lleida 25790",
    "addr:housenumber":"112",
    "addr:postcode":"25790",
    "iso:country":"ES",
    "sg:address":"Avgd De L'alt Urgell, 112",
    "sg:city":"Oliana",
    "sg:orig_category":"Mec\u00c1nico Del Autom\u00d3vil",
    "sg:phone":"+34 973 47 00 68",
    "sg:postcode":"25790",
    "sg:province":"Lleida",
    "wof:name":"Braut Aynes Amadeo",
    "wof:placetype":"venue"
},
  "geometry": {"coordinates":[1.3131630421,42.068271637],"type":"Point"}
}