{
  "type": "Feature",
  "properties": {
    "addr:full":"C/ Roger De Lluria, 5 Alcoi Alicante 03801",
    "addr:housenumber":"5",
    "addr:postcode":"03801",
    "addr:street":"C / Roger De Lluria",
    "iso:country":"ES",
    "sg:address":"C/ Roger De Lluria, 5",
    "sg:city":"Alcoi",
    "sg:orig_category":"Farmacias",
    "sg:phone":"+34 965 54 06 84",
    "sg:postcode":"03801",
    "sg:province":"Alicante",
    "wof:name":"Corcoles Ferrandiz Maria Edelmira",
    "wof:placetype":"venue"
},
  "geometry": {"coordinates":[-0.4753729999,38.6961402893],"type":"Point"}
}