{
  "type": "Feature",
  "properties": {
    "addr:full":"Calle de Dieciocho De Julio, 10 Colunga Asturias 33320",
    "addr:housenumber":"10",
    "addr:postcode":"33320",
    "addr:street":"Calle De Dieciocho De Julio",
    "iso:country":"ES",
    "sg:address":"Calle de Dieciocho De Julio, 10",
    "sg:city":"Colunga",
    "sg:orig_category":"Bancos",
    "sg:phone":"+34 985 85 60 04",
    "sg:postcode":"33320",
    "sg:province":"Asturias",
    "wof:name":"Banco Espa\u00f1ol De Credito S.a.",
    "wof:placetype":"venue"
},
  "geometry": {"coordinates":[-5.2751731873,43.485458374],"type":"Point"}
}