{
  "type": "Feature",
  "properties": {
    "iso:country":"ES",
    "sg:address":"Calle de San Antonio Maria Claret, 19",
    "sg:city":"Zaragoza",
    "sg:orig_category":"Estilistas Y Estudios De Estilo De Corte Y Confecci\u00d3n",
    "sg:phone":"+34 976 35 55 33",
    "sg:postcode":"50005",
    "sg:province":"Zaragoza",
    "wof:name":"Tomas Yago Miguel Angel",
    "wof:placetype":"venue"
},
  "geometry": {"coordinates":[-0.8946070075,41.6455001831],"type":"Point"}
}