{
  "type": "Feature",
  "properties": {
    "iso:country":"ES",
    "sg:address":"Calle de Francisco De Ari\u00d1o, 1",
    "sg:city":"Sevilla",
    "sg:orig_category":"Cl\u00cdnicas Dentales",
    "sg:phone":"+34 954 53 89 81",
    "sg:postcode":"41008",
    "sg:province":"Sevilla",
    "wof:name":"Protesico Nervion S.l.",
    "wof:placetype":"venue"
},
  "geometry": {"coordinates":[-5.9804258347,37.4007415771],"type":"Point"}
}