{
  "type": "Feature",
  "properties": {
    "addr:full":"Ctra. Palomares, S/n Bejar Salamanca 37700",
    "addr:postcode":"37700",
    "addr:street":"Ctra. Palomares S / N Bejar",
    "iso:country":"ES",
    "sg:address":"Ctra. Palomares, S/n",
    "sg:city":"Bejar",
    "sg:orig_category":"Asociaciones Humanitarias, De Cooperaci\u00d3n, De Acci\u00d3n Social",
    "sg:phone":"+34 923 41 11 13",
    "sg:postcode":"37700",
    "sg:province":"Salamanca",
    "wof:name":"Asprodes",
    "wof:placetype":"venue"
},
  "geometry": {"coordinates":[-5.7390537262,40.3912773132],"type":"Point"}
}