{
  "type": "Feature",
  "properties": {
    "iso:country":"ES",
    "sg:address":"Av Constitucio, 36",
    "sg:city":"Castelldefels",
    "sg:orig_category":"Traductores",
    "sg:phone":"+34 936 36 04 52",
    "sg:postcode":"08860",
    "sg:province":"Barcelona",
    "wof:name":"Homolka  Ilona",
    "wof:placetype":"venue"
},
  "geometry": {"coordinates":[1.9874559641,41.28673172],"type":"Point"}
}