{
  "type": "Feature",
  "properties": {
    "iso:country":"ES",
    "sg:address":"Plaz Escritor Ramon Solis, 17",
    "sg:city":"Cadiz",
    "sg:orig_category":"Frutas, Legumbres Frescas Y Tempranas (al Por Menor)",
    "sg:phone":"+34 956 27 80 66",
    "sg:postcode":"11008",
    "sg:province":"C\u00e1diz",
    "wof:name":"Pe\u00f1a Jimenez Francisco",
    "wof:placetype":"venue"
},
  "geometry": {"coordinates":[-6.2850317955,36.5175857544],"type":"Point"}
}