{
  "type": "Feature",
  "properties": {
    "iso:country":"ES",
    "sg:address":"Calle de Sevilla, 72",
    "sg:city":"Campillo",
    "sg:orig_category":"Estancos",
    "sg:phone":"+34 959 58 82 87",
    "sg:postcode":"21650",
    "sg:province":"Huelva",
    "wof:name":"Marin Dominguez Ildefonso",
    "wof:placetype":"venue"
},
  "geometry": {"coordinates":[-6.6259088516,37.6936645508],"type":"Point"}
}