{
  "type": "Feature",
  "properties": {
    "addr:full":"Avda Alcoy, 11 Alacant Alicante 03004",
    "addr:housenumber":"11",
    "addr:postcode":"03004",
    "addr:street":"Avda Alcoy",
    "iso:country":"ES",
    "sg:address":"Avda Alcoy, 11",
    "sg:city":"Alacant",
    "sg:orig_category":"Laboratorios Y Trabajos De Fotograf\u00cda, V\u00cddeo Y Cine",
    "sg:phone":"+34 965 25 02 47",
    "sg:postcode":"03004",
    "sg:province":"Alicante",
    "wof:name":"Superfoto Giner S.l",
    "wof:placetype":"venue"
},
  "geometry": {"coordinates":[-0.4860689938,38.3529014587],"type":"Point"}
}