{
  "type": "Feature",
  "properties": {
    "addr:full":"Santiago Compostela, S/n Roquetas Mar Almer\u00eda 04740",
    "addr:housenumber":"s / n",
    "addr:postcode":"04740",
    "iso:country":"ES",
    "sg:address":"Santiago Compostela, S/n",
    "sg:city":"Roquetas Mar",
    "sg:orig_category":"Agentes, Concesionarios Y Sucursales De Veh\u00cdculos",
    "sg:phone":"+34 950 32 70 13",
    "sg:postcode":"04740",
    "sg:province":"Almer\u00eda",
    "wof:name":"Almerialva S.l.",
    "wof:placetype":"venue"
},
  "geometry": {"coordinates":[-2.4679217339,36.8401641846],"type":"Point"}
}