{
  "type": "Feature",
  "properties": {
    "addr:full":"Calle de Alameda, 16 Vegadeo Asturias 33770",
    "addr:housenumber":"16",
    "addr:postcode":"33770",
    "addr:street":"Calle De Alameda",
    "iso:country":"ES",
    "sg:address":"Calle de Alameda, 16",
    "sg:city":"Vegadeo",
    "sg:orig_category":"Relojer\u00cda (al Por Menor, Reparaci\u00d3n)",
    "sg:phone":"+34 985 63 48 91",
    "sg:postcode":"33770",
    "sg:province":"Asturias",
    "wof:name":"Lago Mediante Angel Ramon",
    "wof:placetype":"venue"
},
  "geometry": {"coordinates":[-7.0516366959,43.4642562866],"type":"Point"}
}