{
  "type": "Feature",
  "properties": {
    "addr:full":"Calle de Zaldoko, 8 Gorraitz-artzibar Navarra 31620",
    "addr:housenumber":"8",
    "addr:postcode":"31620",
    "addr:street":"Calle De Zaldoko",
    "iso:country":"ES",
    "sg:address":"Calle de Zaldoko, 8",
    "sg:city":"Gorraitz-artzibar",
    "sg:orig_category":"Chapister\u00cda",
    "sg:phone":"+34 948 33 74 81",
    "sg:postcode":"31620",
    "sg:province":"Navarra",
    "wof:name":"Bueno Pe\u00f1a Jose",
    "wof:placetype":"venue"
},
  "geometry": {"coordinates":[-1.5902739763,42.83177948],"type":"Point"}
}