{
  "type": "Feature",
  "properties": {
    "iso:country":"ES",
    "sg:address":"Pase Sancha, 5",
    "sg:city":"Malaga",
    "sg:orig_category":"Peluqueros: De Se\u00d1oras",
    "sg:phone":"+34 952 22 74 85",
    "sg:postcode":"29016",
    "sg:province":"M\u00e1laga",
    "wof:name":"Sanchez Gonzalez Fernando",
    "wof:placetype":"venue"
},
  "geometry": {"coordinates":[-4.4019989967,36.7226066589],"type":"Point"}
}