{
  "type": "Feature",
  "properties": {
    "iso:country":"ES",
    "sg:address":"Calle de Tramontana, 20",
    "sg:city":"Cortijo Del Aire",
    "sg:orig_category":"Abogados",
    "sg:phone":"+34 958 53 73 05",
    "sg:postcode":"18220",
    "sg:province":"Granada",
    "wof:name":"Orozco Pardo Miguel",
    "wof:placetype":"venue"
},
  "geometry": {"coordinates":[-3.6505188942,37.2535934448],"type":"Point"}
}