{
  "type": "Feature",
  "properties": {
    "iso:country":"ES",
    "sg:address":"Calle de General Jauregi, 8",
    "sg:city":"Donostia-san Sebastian",
    "sg:orig_category":"Locales De Saunas, De Ba\u00d1os",
    "sg:phone":"+34 943 44 61 16",
    "sg:postcode":"20003",
    "sg:province":"Guip\u00f9zcoa",
    "wof:name":"Venconmen S.l",
    "wof:placetype":"venue"
},
  "geometry": {"coordinates":[-1.9825789928,43.3245277405],"type":"Point"}
}