{
  "type": "Feature",
  "properties": {
    "iso:country":"ES",
    "sg:address":"Calle de Cuba, 2",
    "sg:city":"Malaga",
    "sg:orig_category":"Carnicer\u00cdas, Carnicer\u00cdas",
    "sg:phone":"+34 952 25 06 94",
    "sg:postcode":"29013",
    "sg:province":"M\u00e1laga",
    "wof:name":"Del Pino Ruiz Francisco",
    "wof:placetype":"venue"
},
  "geometry": {"coordinates":[-4.4154310226,36.732925415],"type":"Point"}
}