{
  "type": "Feature",
  "properties": {
    "addr:full":"Ptge Amics D'argentona (dels), 24 Cros Barcelona 08310",
    "addr:housenumber":"24",
    "addr:postcode":"08310",
    "addr:street":"Ptge Amics;Dels",
    "iso:country":"ES",
    "sg:address":"Ptge Amics D'argentona (dels), 24",
    "sg:city":"Cros",
    "sg:orig_category":"Telas (al Por Mayor)",
    "sg:phone":"+34 937 98 69 08",
    "sg:postcode":"08310",
    "sg:province":"Barcelona",
    "wof:name":"Cotton Station S.l.",
    "wof:placetype":"venue"
},
  "geometry": {"coordinates":[2.1699187756,41.3879165649],"type":"Point"}
}