{
  "type": "Feature",
  "properties": {
    "iso:country":"ES",
    "sg:address":"Calle de Larga De San Cristobal, 2",
    "sg:city":"Cella",
    "sg:orig_category":"Promotores Constructores",
    "sg:phone":"+34 978 65 30 75",
    "sg:postcode":"44370",
    "sg:province":"Teruel",
    "wof:name":"Pascual Lozano S.l.",
    "wof:placetype":"venue"
},
  "geometry": {"coordinates":[-1.293792963,40.4528961182],"type":"Point"}
}