{
  "type": "Feature",
  "properties": {
    "iso:country":"ES",
    "sg:address":"Calle de Victoriano Rivera, 2",
    "sg:city":"Cordoba",
    "sg:orig_category":"Centros Comerciales Y Grandes Tiendas",
    "sg:phone":"+34 957 47 78 96",
    "sg:postcode":"14002",
    "sg:province":"C\u00f3rdoba",
    "wof:name":"Martinez Saez Maria Del Carmen",
    "wof:placetype":"venue"
},
  "geometry": {"coordinates":[-4.7795162201,37.8851547241],"type":"Point"}
}