{
  "type": "Feature",
  "properties": {
    "iso:country":"ES",
    "sg:address":"Calle de Sanchoenea, 2",
    "sg:city":"Errenteria",
    "sg:orig_category":"Asociaciones, Organismos Culturales Y Socioeducativos",
    "sg:phone":"+34 943 34 01 43",
    "sg:postcode":"20100",
    "sg:province":"Guip\u00f9zcoa",
    "wof:name":"Lau Haizetara Euskaldunon Elkartea",
    "wof:placetype":"venue"
},
  "geometry": {"coordinates":[-1.8991500139,43.3125686646],"type":"Point"}
}