{
  "type": "Feature",
  "properties": {
    "iso:country":"ES",
    "sg:address":"Muel Muelle De Levante, S/n",
    "sg:city":"Cadiz",
    "sg:orig_category":"Distribuci\u00d3n De Petr\u00d3leo Y Derivados",
    "sg:phone":"+34 956 20 55 14",
    "sg:postcode":"11006",
    "sg:province":"C\u00e1diz",
    "wof:name":"Pescados Juan Villar Guimerans S L",
    "wof:placetype":"venue"
},
  "geometry": {"coordinates":[-6.2902388573,36.5298614502],"type":"Point"}
}