{
  "type": "Feature",
  "properties": {
    "addr:full":"Calle de Hilarion Eslava, 10 Madrid Madrid 28015",
    "addr:housenumber":"10",
    "addr:postcode":"madrid;28015",
    "addr:street":"Calle De Hilarion Eslava",
    "iso:country":"ES",
    "sg:address":"Calle de Hilarion Eslava, 10",
    "sg:city":"Madrid",
    "sg:orig_category":"Inmobiliaria (agencias)",
    "sg:phone":"+34 915 22 11 11",
    "sg:postcode":"28015",
    "sg:province":"Madrid",
    "sg:website":"www.hersau.es",
    "wof:name":"Grupo Inmobiliario Hersau S.a.",
    "wof:placetype":"venue"
},
  "geometry": {"coordinates":[-3.7165970802,40.4333152771],"type":"Point"}
}