{
  "type": "Feature",
  "properties": {
    "addr:full":"Carr Del Cami Vell De Xativa, S/n Ontinyent Valencia 46870",
    "addr:housenumber":"s / n",
    "addr:postcode":"46870",
    "addr:street":"Carr Del Cami Vell De Xativa",
    "iso:country":"ES",
    "sg:address":"Carr Del Cami Vell De Xativa, S/n",
    "sg:city":"Ontinyent",
    "sg:orig_category":"Textil",
    "sg:phone":"+34 962 38 04 09",
    "sg:postcode":"46870",
    "sg:province":"Valencia",
    "wof:name":"Textil Mu\u00f1oz S.l.",
    "wof:placetype":"venue"
},
  "geometry": {"coordinates":[-0.6026489735,38.8266448975],"type":"Point"}
}