{
  "type": "Feature",
  "properties": {
    "addr:full":"Carrer de Bruguera, 277 Calella Barcelona 08370",
    "addr:housenumber":"277",
    "addr:postcode":"08370",
    "addr:street":"Carrer De Bruguera",
    "iso:country":"ES",
    "sg:address":"Carrer de Bruguera, 277",
    "sg:city":"Calella",
    "sg:orig_category":"Ense\u00d1anza: Idiomas",
    "sg:phone":"+34 937 66 14 91",
    "sg:postcode":"08370",
    "sg:province":"Barcelona",
    "sg:website":"www.grupo-sil.com",
    "wof:name":"Inlingua-idiomund S.l.",
    "wof:placetype":"venue"
},
  "geometry": {"coordinates":[2.6660490036,41.6169052124],"type":"Point"}
}