{
  "type": "Feature",
  "properties": {
    "iso:country":"ES",
    "sg:address":"Plaz Espa\u00d1a, S/n",
    "sg:city":"Algeciras",
    "sg:orig_category":"Semiller\u00cdas",
    "sg:phone":"+34 956 63 19 86",
    "sg:postcode":"11203",
    "sg:province":"C\u00e1diz",
    "wof:name":"Estrechoflor Hermanos S.l.",
    "wof:placetype":"venue"
},
  "geometry": {"coordinates":[-5.4571428299,36.1311607361],"type":"Point"}
}