{
  "type": "Feature",
  "properties": {
    "addr:full":"Calle de Funikular, 12 Valle Trapaga Vizcaya 48510",
    "addr:housenumber":"12",
    "addr:postcode":"48510",
    "addr:street":"Calle De Funikular;Trapaga",
    "iso:country":"ES",
    "sg:address":"Calle de Funikular, 12",
    "sg:city":"Valle Trapaga",
    "sg:orig_category":"Asociaciones, Organismos Culturales Y Socioeducativos",
    "sg:phone":"+34 944 92 29 13",
    "sg:postcode":"48510",
    "sg:province":"Vizcaya",
    "wof:name":"Ayuntamiento Del Valle De Trapaga Trapagaran",
    "wof:placetype":"venue"
},
  "geometry": {"coordinates":[-3.0379528999,43.3039703369],"type":"Point"}
}