{
  "type": "Feature",
  "properties": {
    "iso:country":"ES",
    "sg:address":"Calle de Jenaro Oraa, 26",
    "sg:city":"Santurtzi",
    "sg:orig_category":"Importaci\u00d3n, Exportaci\u00d3n Y Comercios De Productos Textiles",
    "sg:phone":"+34 944 61 84 24",
    "sg:postcode":"48980",
    "sg:province":"Vizcaya",
    "sg:website":"www.beds.es",
    "wof:name":"C.c. Del Descanso Alaia, S.l.l.",
    "wof:placetype":"venue"
},
  "geometry": {"coordinates":[-3.0312399864,43.3271751404],"type":"Point"}
}