{
  "type": "Feature",
  "properties": {
    "iso:country":"ES",
    "sg:address":"Calle de Alcala (de), 2",
    "sg:city":"Algete",
    "sg:orig_category":"Ense\u00d1anza: Profesiones Art\u00cdsticas",
    "sg:phone":"+34 916 29 11 91",
    "sg:postcode":"28110",
    "sg:province":"Madrid",
    "wof:name":"Sanchez-cabezudo Sanchez Salvador",
    "wof:placetype":"venue"
},
  "geometry": {"coordinates":[-3.4989190102,40.5965042114],"type":"Point"}
}