{
  "type": "Feature",
  "properties": {
    "iso:country":"ES",
    "sg:address":"Pol Ind Cruz Alta, S/n",
    "sg:city":"Castilblanco Arroyos",
    "sg:orig_category":"Equipo De Refrigeraci\u00d3n Industrial",
    "sg:phone":"+34 955 73 46 24",
    "sg:postcode":"41230",
    "sg:province":"Sevilla",
    "wof:name":"Fritecsur S.l.",
    "wof:placetype":"venue"
},
  "geometry": {"coordinates":[-5.9854841232,37.6786766052],"type":"Point"}
}