{
  "type": "Feature",
  "properties": {
    "iso:country":"ES",
    "sg:address":"Rua Mato (do), 40",
    "sg:city":"Xinzo De Limia",
    "sg:orig_category":"Plomeros",
    "sg:phone":"+34 988 46 26 33",
    "sg:postcode":"32630",
    "sg:province":"Ourense",
    "wof:name":"Instalaciones Lolo S.l",
    "wof:placetype":"venue"
},
  "geometry": {"coordinates":[-7.7297339439,42.0608634949],"type":"Point"}
}