{
  "type": "Feature",
  "properties": {
    "iso:country":"ES",
    "sg:address":"Rond Sobradiel, 6",
    "sg:city":"Madrid",
    "sg:orig_category":"Agricultores, Agricultores",
    "sg:phone":"+34 913 00 57 06",
    "sg:postcode":"28043",
    "sg:province":"Madrid",
    "wof:name":"Juliven S. A.",
    "wof:placetype":"venue"
},
  "geometry": {"coordinates":[-3.6447200775,40.4514732361],"type":"Point"}
}