{
  "type": "Feature",
  "properties": {
    "addr:full":"Rua San Pedro De Mezonzo (de), 38 Santiago De Compostela La Coru\u00f1a 15701",
    "addr:housenumber":"38",
    "addr:postcode":"15701",
    "addr:street":"Rua San Pedro De Mezonzo De;Corun\u0303A",
    "iso:country":"ES",
    "sg:address":"Rua San Pedro De Mezonzo (de), 38",
    "sg:city":"Santiago De Compostela",
    "sg:orig_category":"M\u00c9dicos: Otorrinolaringolog\u00cda",
    "sg:phone":"+34 981 59 45 08",
    "sg:postcode":"15701",
    "sg:province":"La Coru\u00f1a",
    "wof:name":"Horna Vereau Edmundo",
    "wof:placetype":"venue"
},
  "geometry": {"coordinates":[-8.5473670959,42.8712043762],"type":"Point"}
}