{
  "type": "Feature",
  "properties": {
    "addr:full":"Pol Ind Riu Clar, 22 Tarragona Tarragona 43006",
    "addr:housenumber":"22",
    "addr:postcode":"43006",
    "iso:country":"ES",
    "sg:address":"Pol Ind Riu Clar, 22",
    "sg:city":"Tarragona",
    "sg:orig_category":"Escayola Y Productos De Escayola (fabricaci\u00d3n, Al Por Mayor)",
    "sg:phone":"+34 977 55 36 64",
    "sg:postcode":"43006",
    "sg:province":"Tarragona",
    "wof:name":"Eurovalls Materiales Para La Construccion S.l.",
    "wof:placetype":"venue"
},
  "geometry": {"coordinates":[1.2209249735,41.1154441833],"type":"Point"}
}