{
  "type": "Feature",
  "properties": {
    "addr:full":"Rua O Mari\u00d1o, 8 Grove Pontevedra 36980",
    "addr:housenumber":"8",
    "addr:postcode":"36980",
    "addr:street":"Rua O Marin\u0303O",
    "iso:country":"ES",
    "sg:address":"Rua O Mari\u00d1o, 8",
    "sg:city":"Grove",
    "sg:orig_category":"Bisuter\u00cda, Joyer\u00cda, Relojer\u00cda (al Por Menor)",
    "sg:phone":"+34 986 73 18 66",
    "sg:postcode":"36980",
    "sg:province":"Pontevedra",
    "wof:name":"Gonzalez Gonzalez Avelina",
    "wof:placetype":"venue"
},
  "geometry": {"coordinates":[-8.8628768921,42.4936904907],"type":"Point"}
}