{
  "type": "Feature",
  "properties": {
    "iso:country":"ES",
    "sg:address":"Calle de Antonio Maura, 9",
    "sg:city":"Solana",
    "sg:orig_category":"Art\u00cdculos De Regalo (al Por Menor)",
    "sg:phone":"+34 926 63 10 74",
    "sg:postcode":"13240",
    "sg:province":"Ciudad Real",
    "wof:name":"Alhambra Martin De Las Mulas Camilo",
    "wof:placetype":"venue"
},
  "geometry": {"coordinates":[-3.2362408638,38.9421234131],"type":"Point"}
}