{
  "type": "Feature",
  "properties": {
    "iso:country":"ES",
    "sg:address":"Calle de Almaden, 2",
    "sg:city":"Guadalmez",
    "sg:orig_category":"Iglesia Cat\u00d3lica",
    "sg:phone":"+34 926 74 20 23",
    "sg:postcode":"13490",
    "sg:province":"Ciudad Real",
    "wof:name":"Parroquia De San Sebastian",
    "wof:placetype":"venue"
},
  "geometry": {"coordinates":[-4.9706420898,38.7271347046],"type":"Point"}
}