{
  "type": "Feature",
  "properties": {
    "iso:country":"ES",
    "sg:address":"Carrer de Industria, 1",
    "sg:city":"Santa Perpetua De Mogoda",
    "sg:orig_category":"Venta, Montaje De Neum\u00c1ticos",
    "sg:phone":"+34 935 60 10 04",
    "sg:postcode":"08130",
    "sg:province":"Barcelona",
    "wof:name":"Pneumatics Santa Perpetua S.l.",
    "wof:placetype":"venue"
},
  "geometry": {"coordinates":[2.1810050011,41.5378303528],"type":"Point"}
}