{
  "type": "Feature",
  "properties": {
    "addr:full":"Calle de Brasil, 6 Rua De Valdeorras Ourense 32350",
    "addr:housenumber":"6",
    "addr:postcode":"32350",
    "addr:street":"Calle De Brasil;Rua De",
    "iso:country":"ES",
    "sg:address":"Calle de Brasil, 6",
    "sg:city":"Rua De Valdeorras",
    "sg:orig_category":"Peluquer\u00cdas, Peluquer\u00cda Mixta",
    "sg:phone":"+34 988 31 04 49",
    "sg:postcode":"32350",
    "sg:province":"Ourense",
    "wof:name":"Gonzalez Gonzalez Alma Maria",
    "wof:placetype":"venue"
},
  "geometry": {"coordinates":[-7.1111702919,42.3964653015],"type":"Point"}
}