{
  "type": "Feature",
  "properties": {
    "iso:country":"ES",
    "sg:address":"Carrer de Ramon Llull, 5",
    "sg:city":"Can Trias Industrial",
    "sg:orig_category":"M\u00c1rmoles, Granitos Y Piedras Naturales",
    "sg:phone":"+34 937 33 34 02",
    "sg:postcode":"08232",
    "sg:province":"Barcelona",
    "wof:name":"Marmoles Hermanos Ros S.l.",
    "wof:placetype":"venue"
},
  "geometry": {"coordinates":[1.9798289537,41.5642089844],"type":"Point"}
}