{
  "type": "Feature",
  "properties": {
    "iso:country":"ES",
    "sg:address":"Pase Recaredo, 1",
    "sg:city":"Toledo",
    "sg:orig_category":"Asesor\u00cda Sobre Comunicaci\u00d3n De Empresas",
    "sg:phone":"+34 925 21 18 12",
    "sg:postcode":"45004",
    "sg:province":"Toledo",
    "sg:website":"www.fedeto.es",
    "wof:name":"Federacion Empresarial Toledana",
    "wof:placetype":"venue"
},
  "geometry": {"coordinates":[-4.0680837631,39.8566055298],"type":"Point"}
}