{
  "type": "Feature",
  "properties": {
    "addr:full":"Avda Paz De (la), 48 Logro\u00f1o La Rioja 26004",
    "addr:housenumber":"48",
    "addr:postcode":"26004",
    "addr:street":"Avda Paz De La;Rioja",
    "iso:country":"ES",
    "sg:address":"Avda Paz De (la), 48",
    "sg:city":"Logro\u00f1o",
    "sg:orig_category":"Peluqueros: De Se\u00d1oras",
    "sg:phone":"+34 941 24 49 07",
    "sg:postcode":"26004",
    "sg:province":"La Rioja",
    "wof:name":"Olmedo Peluqueros S.l.",
    "wof:placetype":"venue"
},
  "geometry": {"coordinates":[-2.4364690781,42.4647216797],"type":"Point"}
}