{
  "type": "Feature",
  "properties": {
    "iso:country":"ES",
    "sg:address":"Calle de Lapa (la), S/n",
    "sg:city":"Playa Blanca",
    "sg:orig_category":"Bancos",
    "sg:phone":"+34 928 51 76 36",
    "sg:postcode":"35580",
    "sg:province":"Las Palmas",
    "wof:name":"Banco Popular Espa\u00f1ol",
    "wof:placetype":"venue"
},
  "geometry": {"coordinates":[-13.8269643784,28.864730835],"type":"Point"}
}