{
  "type": "Feature",
  "properties": {
    "addr:full":"Calle de Panama, 18 Gijon Asturias 33213",
    "addr:housenumber":"18",
    "addr:postcode":"33213",
    "addr:street":"Calle De Panama",
    "iso:country":"ES",
    "sg:address":"Calle de Panama, 18",
    "sg:city":"Gijon",
    "sg:orig_category":"Charcuter\u00cdas (al Por Mayor)",
    "sg:phone":"+34 985 31 25 85",
    "sg:postcode":"33213",
    "sg:province":"Asturias",
    "wof:name":"Gallego De La Varga Maria De Los Angeles",
    "wof:placetype":"venue"
},
  "geometry": {"coordinates":[-5.6961641312,43.5379905701],"type":"Point"}
}