{
  "type": "Feature",
  "properties": {
    "iso:country":"ES",
    "sg:address":"Carrer de Nou De Valldaura, 1",
    "sg:city":"Manresa",
    "sg:orig_category":"Tintes (fabricaci\u00d3n, Al Por Mayor)",
    "sg:phone":"+34 938 72 05 40",
    "sg:postcode":"08241",
    "sg:province":"Barcelona",
    "wof:name":"Estragues Badia Montserrat",
    "wof:placetype":"venue"
},
  "geometry": {"coordinates":[1.819939971,41.7240600586],"type":"Point"}
}