{
  "type": "Feature",
  "properties": {
    "addr:full":"Av Pais Valencia (del), 97 Cocentaina Alicante 03820",
    "addr:postcode":"03820",
    "addr:street":"Av Pais;Del 97",
    "iso:country":"ES",
    "sg:address":"Av Pais Valencia (del), 97",
    "sg:city":"Cocentaina",
    "sg:orig_category":"Agencias De Viajes",
    "sg:phone":"+34 966 54 45 46",
    "sg:postcode":"03820",
    "sg:province":"Alicante",
    "wof:name":"Ruta Jove S.l.",
    "wof:placetype":"venue"
},
  "geometry": {"coordinates":[-0.438917011,38.7403717041],"type":"Point"}
}