{
  "type": "Feature",
  "properties": {
    "addr:full":"Calle de Jerez Baja, 1 Moron Frontera Sevilla 41530",
    "addr:housenumber":"1",
    "addr:postcode":"41530",
    "addr:street":"Calle De Jerez Baja",
    "iso:country":"ES",
    "sg:address":"Calle de Jerez Baja, 1",
    "sg:city":"Moron Frontera",
    "sg:orig_category":"Producci\u00d3n, Venta De Productos De Agricultura Biol\u00d3gica",
    "sg:phone":"+34 955 85 28 96",
    "sg:postcode":"41530",
    "sg:province":"Sevilla",
    "wof:name":"Sierra De Pozo Amargo S.l.",
    "wof:placetype":"venue"
},
  "geometry": {"coordinates":[-5.4564528465,37.1192436218],"type":"Point"}
}