{
  "type": "Feature",
  "properties": {
    "addr:full":"Ctra Quintanadue\u00d1as, S/n Burgos Burgos 09003",
    "addr:housenumber":"s / n",
    "addr:postcode":"09003",
    "addr:street":"Ctra Quintanaduen\u0303As",
    "iso:country":"ES",
    "sg:address":"Ctra Quintanadue\u00d1as, S/n",
    "sg:city":"Burgos",
    "sg:orig_category":"Molduras, Junquillos, Listones Y Molduras Perforadas",
    "sg:phone":"+34 947 20 70 12",
    "sg:postcode":"09003",
    "sg:province":"Burgos",
    "wof:name":"Gutierrez Teran Lorenzo",
    "wof:placetype":"venue"
},
  "geometry": {"coordinates":[-3.7136163712,42.3652534485],"type":"Point"}
}