{
  "type": "Feature",
  "properties": {
    "iso:country":"ES",
    "sg:address":"Avgd Del Cami Nou, 89",
    "sg:city":"Xirivella",
    "sg:orig_category":"Molduras, Junquillos, Listones Y Molduras Perforadas",
    "sg:phone":"+34 963 70 83 91",
    "sg:postcode":"46950",
    "sg:province":"Valencia",
    "wof:name":"Rubio Bigorra Emilia",
    "wof:placetype":"venue"
},
  "geometry": {"coordinates":[-0.4305149913,39.4655647278],"type":"Point"}
}