{
  "type": "Feature",
  "properties": {
    "addr:full":"Calle de Islas Canarias, 126 Valencia Valencia 46023",
    "addr:housenumber":"126",
    "addr:postcode":"46023",
    "addr:street":"Calle De Islas Canarias",
    "iso:country":"ES",
    "sg:address":"Calle de Islas Canarias, 126",
    "sg:city":"Valencia",
    "sg:orig_category":"Cajas De Ahorro",
    "sg:phone":"+34 963 30 51 95",
    "sg:postcode":"46023",
    "sg:province":"Valencia",
    "sg:website":"www.bancaja.es",
    "wof:name":"Caja De Ahorros De Valencia Castellon Y Alicante",
    "wof:placetype":"venue"
},
  "geometry": {"coordinates":[-0.3441590071,39.4626235962],"type":"Point"}
}