{
  "type": "Feature",
  "properties": {
    "addr:full":"Rua Doctor Jose Fari\u00d1a, 2 Betanzos A Coru\u00f1a 15300",
    "addr:housenumber":"2",
    "addr:postcode":"15300",
    "addr:street":"Rua Doctor Jose Farin\u0303A",
    "iso:country":"ES",
    "sg:address":"Rua Doctor Jose Fari\u00d1a, 2",
    "sg:city":"Betanzos",
    "sg:orig_category":"Cl\u00cdnicas Dentales",
    "sg:phone":"+34 981 77 31 08",
    "sg:postcode":"15300",
    "sg:province":"A Coru\u00f1a",
    "wof:name":"Viqueira Amor Maria Del Pilar",
    "wof:placetype":"venue"
},
  "geometry": {"coordinates":[-8.2119092941,43.279914856],"type":"Point"}
}