{
  "type": "Feature",
  "properties": {
    "iso:country":"ES",
    "sg:address":"Av Jaume Recoder, 53",
    "sg:city":"Mataro",
    "sg:orig_category":"Organismos De Turismo",
    "sg:phone":"+34 937 98 55 58",
    "sg:postcode":"08301",
    "sg:province":"Barcelona",
    "wof:name":"Gremio De Hosteleria Y Turismo De Mataro Y El Maresme",
    "wof:placetype":"venue"
},
  "geometry": {"coordinates":[2.4433801174,41.5340576172],"type":"Point"}
}