{
  "type": "Feature",
  "properties": {
    "iso:country":"ES",
    "sg:address":"Calle de Almirante Gazta\u00d1eta, 24",
    "sg:city":"Mutriku",
    "sg:orig_category":"Peluquer\u00cdas",
    "sg:phone":"+34 943 60 42 68",
    "sg:postcode":"20830",
    "sg:province":"Guip\u00f9zcoa",
    "wof:name":"Peluqueria Gotzone",
    "wof:placetype":"venue"
},
  "geometry": {"coordinates":[-2.3894293308,43.3052520752],"type":"Point"}
}