{
  "type": "Feature",
  "properties": {
    "addr:full":"Avda Sevilla, S/n Torreperogil Ja\u00e9n 23320",
    "addr:housenumber":"s",
    "addr:postcode":"23320",
    "addr:street":"Avda Sevilla;/ N;Jae\u0301N",
    "iso:country":"ES",
    "sg:address":"Avda Sevilla, S/n",
    "sg:city":"Torreperogil",
    "sg:orig_category":"Empresas De Carpinter\u00cda Met\u00c1lica",
    "sg:phone":"+34 953 77 71 10",
    "sg:postcode":"23320",
    "sg:province":"Ja\u00e9n",
    "wof:name":"Lara Jurado Juan",
    "wof:placetype":"venue"
},
  "geometry": {"coordinates":[-3.2948451042,38.0358428955],"type":"Point"}
}