{
  "type": "Feature",
  "properties": {
    "iso:country":"ES",
    "sg:address":"Calle de Adriano, 20",
    "sg:city":"Merida",
    "sg:orig_category":"Telas Y Sedas (al Por Menor)",
    "sg:phone":"+34 924 31 74 53",
    "sg:postcode":"06800",
    "sg:province":"Badajoz",
    "wof:name":"Garcia Alventosa S. L.",
    "wof:placetype":"venue"
},
  "geometry": {"coordinates":[-6.349187851,38.9191741943],"type":"Point"}
}