{
  "type": "Feature",
  "properties": {
    "addr:full":"Plaz Ramon Y Cajal (de), 5 Cordoba C\u00f3rdoba 14003",
    "addr:housenumber":"5",
    "addr:postcode":"14003",
    "addr:street":"Ramon Y Cajal De;Co\u0301Rdoba",
    "iso:country":"ES",
    "sg:address":"Plaz Ramon Y Cajal (de), 5",
    "sg:city":"Cordoba",
    "sg:orig_category":"Funcionario",
    "sg:phone":"+34 957 24 99 32",
    "sg:postcode":"14003",
    "sg:province":"C\u00f3rdoba",
    "wof:name":"Colegio Profesional De Agentes Comerciales",
    "wof:placetype":"venue"
},
  "geometry": {"coordinates":[-4.7824110985,37.8832511902],"type":"Point"}
}