{
  "type": "Feature",
  "properties": {
    "iso:country":"ES",
    "sg:address":"Avda Ernesto Sarti, S/n",
    "sg:city":"Torviscas Bajo",
    "sg:classifiers":[
        {
            "category":"Professional",
            "subcategory":"Management & Consulting",
            "type":"Services"
        }
    ],
    "sg:phone":"+34 922 71 77 67",
    "sg:postcode":"38660",
    "sg:province":"Santa Cruz De Tenerife",
    "sg:tags":[
        "asesor\u00cda",
        "en",
        "marketing"
    ],
    "wof:name":"Bogers  Maria",
    "wof:placetype":"venue"
},
  "geometry": {"coordinates":[-16.7311515808,28.0861644745],"type":"Point"}
}