{
  "type": "Feature",
  "properties": {
    "addr:full":"Avda Dos De Mayo (del), 7 Mostoles Madrid 28934",
    "addr:housenumber":"7",
    "addr:postcode":"28934",
    "addr:street":"Avda Dos De Mayo Del",
    "iso:country":"ES",
    "sg:address":"Avda Dos De Mayo (del), 7",
    "sg:city":"Mostoles",
    "sg:orig_category":"Bancos",
    "sg:phone":"+34 916 64 36 66",
    "sg:postcode":"28934",
    "sg:province":"Madrid",
    "wof:name":"Bankinter S.a.",
    "wof:placetype":"venue"
},
  "geometry": {"coordinates":[-3.8669199944,40.3206443787],"type":"Point"}
}