{
  "type": "Feature",
  "properties": {
    "iso:country":"ES",
    "sg:address":"Carrer de Pau Casals, 36",
    "sg:city":"Cambrils",
    "sg:orig_category":"Ropa Para Se\u00d1oras (al Por Menor)",
    "sg:phone":"+34 977 79 18 86",
    "sg:postcode":"43850",
    "sg:province":"Tarragona",
    "wof:name":"Pedrola S. L",
    "wof:placetype":"venue"
},
  "geometry": {"coordinates":[1.0625389814,41.0667457581],"type":"Point"}
}