{
  "type": "Feature",
  "properties": {
    "addr:full":"Calle de Apostol Santiago, 17 Madrid Madrid 28017",
    "addr:housenumber":"17",
    "addr:postcode":"madrid;28017",
    "addr:street":"Calle De Apostol Santiago",
    "iso:country":"ES",
    "sg:address":"Calle de Apostol Santiago, 17",
    "sg:city":"Madrid",
    "sg:orig_category":"Costureras",
    "sg:phone":"+34 914 04 82 65",
    "sg:postcode":"28017",
    "sg:province":"Madrid",
    "wof:name":"Campos Martin Manuela",
    "wof:placetype":"venue"
},
  "geometry": {"coordinates":[-3.6546919346,40.4254302979],"type":"Point"}
}