{
  "type": "Feature",
  "properties": {
    "addr:full":"Calle de Rio Segre, 11 Moron Frontera Sevilla 41530",
    "addr:housenumber":"11",
    "addr:postcode":"41530",
    "addr:street":"Calle De Rio Segre",
    "iso:country":"ES",
    "sg:address":"Calle de Rio Segre, 11",
    "sg:city":"Moron Frontera",
    "sg:orig_category":"Aguas (distribuci\u00d3n, Servicios)",
    "sg:phone":"+34 955 85 47 15",
    "sg:postcode":"41530",
    "sg:province":"Sevilla",
    "wof:name":"Cyclus Id S.l.",
    "wof:placetype":"venue"
},
  "geometry": {"coordinates":[-5.453110218,37.1250572205],"type":"Point"}
}