{
  "type": "Feature",
  "properties": {
    "iso:country":"ES",
    "sg:address":"Calle de Capuchinos, 7",
    "sg:city":"Alcala Real",
    "sg:orig_category":"Peluquer\u00cdas, Peluquer\u00cda Mixta",
    "sg:phone":"+34 953 58 18 92",
    "sg:postcode":"23680",
    "sg:province":"Ja\u00e9n",
    "wof:name":"Fuentes Cano Justo",
    "wof:placetype":"venue"
},
  "geometry": {"coordinates":[-3.9233016968,37.4608726501],"type":"Point"}
}