{
  "type": "Feature",
  "properties": {
    "iso:country":"ES",
    "sg:address":"Pl. Purisima, 4",
    "sg:city":"Betxi",
    "sg:orig_category":"Artes Gr\u00c1ficas, Artes Pl\u00c1sticas (curso)",
    "sg:phone":"+34 964 62 01 82",
    "sg:postcode":"12549",
    "sg:province":"Castell\u00f3n",
    "wof:name":"Guillamon Manuel Dolores",
    "wof:placetype":"venue"
},
  "geometry": {"coordinates":[-0.1986079961,39.9291572571],"type":"Point"}
}