{
  "type": "Feature",
  "properties": {
    "iso:country":"ES",
    "sg:address":"Carrer de Rossello, 419",
    "sg:city":"Barcelona",
    "sg:orig_category":"Radiocomunicaciones, Telefon\u00cda M\u00d3vil, Radiomensajer\u00cda: Servicios, Comercializaci\u00d3n",
    "sg:phone":"+34 934 35 29 60",
    "sg:postcode":"08025",
    "sg:province":"Barcelona",
    "wof:name":"Martinez Alonso Ramon",
    "wof:placetype":"venue"
},
  "geometry": {"coordinates":[2.1722049713,41.4046783447],"type":"Point"}
}