{
  "type": "Feature",
  "properties": {
    "iso:country":"ES",
    "sg:address":"Carrer de Progres, 69",
    "sg:city":"Gava",
    "sg:orig_category":"Electrodom\u00c9sticos (al Por Menor)",
    "sg:phone":"+34 936 38 31 40",
    "sg:postcode":"08850",
    "sg:province":"Barcelona",
    "wof:name":"Reche Y Gilabert S.a.",
    "wof:placetype":"venue"
},
  "geometry": {"coordinates":[2.0115170479,41.2989578247],"type":"Point"}
}