{
  "type": "Feature",
  "properties": {
    "addr:full":"Calle de Pozoblanco, 16 Cordoba C\u00f3rdoba 14013",
    "addr:housenumber":"16",
    "addr:postcode":"14013",
    "addr:street":"Calle De Pozoblanco;Co\u0301Rdoba",
    "iso:country":"ES",
    "sg:address":"Calle de Pozoblanco, 16",
    "sg:city":"Cordoba",
    "sg:orig_category":"Molduras, Junquillos, Listones Y Molduras Perforadas",
    "sg:phone":"+34 957 29 00 47",
    "sg:postcode":"14013",
    "sg:province":"C\u00f3rdoba",
    "wof:name":"Segovia Morilla Rafael",
    "wof:placetype":"venue"
},
  "geometry": {"coordinates":[-4.7778792381,37.8635787964],"type":"Point"}
}