{
  "type": "Feature",
  "properties": {
    "iso:country":"ES",
    "sg:address":"Rbla Volart, 52",
    "sg:city":"Barcelona",
    "sg:orig_category":"Ebanister\u00cda",
    "sg:phone":"+34 934 55 03 54",
    "sg:postcode":"08041",
    "sg:province":"Barcelona",
    "wof:name":"Escabia Marco Jose Luis",
    "wof:placetype":"venue"
},
  "geometry": {"coordinates":[2.1773290634,41.4167633057],"type":"Point"}
}