{
  "type": "Feature",
  "properties": {
    "iso:country":"ES",
    "sg:address":"Calle de Orquidea, 28",
    "sg:city":"Malaga",
    "sg:orig_category":"Panader\u00cdas, Panader\u00cdas",
    "sg:phone":"+34 952 43 25 50",
    "sg:postcode":"29190",
    "sg:province":"M\u00e1laga",
    "wof:name":"Abastecimientos Anuca S.l.",
    "wof:placetype":"venue"
},
  "geometry": {"coordinates":[-4.494375,36.743011],"type":"Point"}
}