{
  "type": "Feature",
  "properties": {
    "addr:full":"Camino De Hijar, S/n Las Gabias Granada 18110",
    "addr:housenumber":"/ n",
    "addr:postcode":"18110",
    "addr:street":"Camino De Hijar S",
    "iso:country":"ES",
    "sg:address":"Camino De Hijar, S/n",
    "sg:city":"Las Gabias",
    "sg:orig_category":"Fabrica De Cer\u00c1micas",
    "sg:phone":"+34 958 58 29 22",
    "sg:postcode":"18110",
    "sg:province":"Granada",
    "wof:name":"Ladrillos Las Nieves Sociedad Limitada Laboral",
    "wof:placetype":"venue"
},
  "geometry": {"coordinates":[-97.78224945069999,45.7040786743],"type":"Point"}
}