{
  "type": "Feature",
  "properties": {
    "iso:country":"ES",
    "sg:address":"Avda Pe\u00d1acorada, S/n",
    "sg:city":"Cistierna",
    "sg:orig_category":"Cer\u00c1micas: Material Y Suministros",
    "sg:phone":"+34 987 70 12 18",
    "sg:postcode":"24800",
    "sg:province":"Le\u00f3n",
    "wof:name":"Schluter Systems S.l.",
    "wof:placetype":"venue"
},
  "geometry": {"coordinates":[-5.1321439743,42.8056297302],"type":"Point"}
}