{
  "type": "Feature",
  "properties": {
    "addr:full":"Luga Hoya Chiquita (la), 44 Lomo Espino Las Palmas 35300",
    "addr:postcode":"35300",
    "addr:street":"Lomo Espino Las",
    "iso:country":"ES",
    "sg:address":"Luga Hoya Chiquita (la), 44",
    "sg:city":"Lomo Espino",
    "sg:orig_category":"Productores Recolectores, Venta Directa De Vinos",
    "sg:phone":"+34 928 64 05 55",
    "sg:postcode":"35300",
    "sg:province":"Las Palmas",
    "wof:name":"Navarro Ojeda Antonio",
    "wof:placetype":"venue"
},
  "geometry": {"coordinates":[-15.4988956451,28.0369472504],"type":"Point"}
}