{
  "type": "Feature",
  "properties": {
    "addr:full":"Calle de Isla De Jamaica, 13 Madrid Madrid 28034",
    "addr:housenumber":"13",
    "addr:postcode":"madrid;28034",
    "addr:street":"Calle De Isla De Jamaica",
    "iso:country":"ES",
    "sg:address":"Calle de Isla De Jamaica, 13",
    "sg:city":"Madrid",
    "sg:orig_category":"Montaje (empresas De)",
    "sg:phone":"+34 917 28 07 21",
    "sg:postcode":"28034",
    "sg:province":"Madrid",
    "wof:name":"Telvent Outsourcing S.a.",
    "wof:placetype":"venue"
},
  "geometry": {"coordinates":[-3.680505991,40.489616394],"type":"Point"}
}