{
  "type": "Feature",
  "properties": {
    "iso:country":"ES",
    "sg:address":"Carrer de Cuba, 7",
    "sg:city":"Mataro",
    "sg:orig_category":"Carnicer\u00cdas, Carnicer\u00cdas",
    "sg:phone":"+34 937 98 15 46",
    "sg:postcode":"08302",
    "sg:province":"Barcelona",
    "wof:name":"Niubo-rodrigo S.cv.",
    "wof:placetype":"venue"
},
  "geometry": {"coordinates":[2.4399991035,41.5378913879],"type":"Point"}
}