{
  "type": "Feature",
  "properties": {
    "addr:full":"Calle de Mayor, 18 Higueruela Albacete 02694",
    "addr:housenumber":"18",
    "addr:postcode":"02694",
    "addr:street":"Calle De Mayor",
    "iso:country":"ES",
    "sg:address":"Calle de Mayor, 18",
    "sg:city":"Higueruela",
    "sg:orig_category":"Cl\u00cdnicas Dentales",
    "sg:phone":"+34 967 28 70 25",
    "sg:postcode":"02694",
    "sg:province":"Albacete",
    "wof:name":"Clinica Dental Santa Quiteria",
    "wof:placetype":"venue"
},
  "geometry": {"coordinates":[-1.4418929815,38.9625701904],"type":"Point"}
}