{
  "type": "Feature",
  "properties": {
    "iso:country":"ES",
    "sg:address":"Pase Habana, 33",
    "sg:city":"Madrid",
    "sg:orig_category":"M\u00c9dicos: Pediatr\u00cda. Enfermedades De Los Ni\u00d1os",
    "sg:phone":"+34 915 64 92 12",
    "sg:postcode":"28036",
    "sg:province":"Madrid",
    "wof:name":"Tolosa Latour Alcala Galiano Manuel",
    "wof:placetype":"venue"
},
  "geometry": {"coordinates":[-3.6854829788,40.4526176453],"type":"Point"}
}