{
  "type": "Feature",
  "properties": {
    "addr:full":"Industrialdea, 31 Anoeta Guip\u00f9zcoa 20270",
    "addr:housenumber":"31",
    "addr:postcode":"20270",
    "addr:street":"Industrialdea;Guipu\u0300Zcoa",
    "iso:country":"ES",
    "sg:address":"Industrialdea, 31",
    "sg:city":"Anoeta",
    "sg:orig_category":"Mec\u00c1nico Del Autom\u00d3vil",
    "sg:phone":"+34 943 65 26 53",
    "sg:postcode":"20270",
    "sg:province":"Guip\u00f9zcoa",
    "wof:name":"Gurutze Autoak S.l.",
    "wof:placetype":"venue"
},
  "geometry": {"coordinates":[-2.069963932,43.1619186401],"type":"Point"}
}