{
  "type": "Feature",
  "properties": {
    "iso:country":"ES",
    "sg:address":"Toro-norte, S/n",
    "sg:city":"Toro",
    "sg:orig_category":"Mec\u00c1nico Del Autom\u00d3vil",
    "sg:phone":"+34 980 69 32 96",
    "sg:postcode":"49800",
    "sg:province":"Zamora",
    "wof:name":"Fortuoso Alonso Jose Antonio",
    "wof:placetype":"venue"
},
  "geometry": {"coordinates":[-5.4181170464,41.5279388428],"type":"Point"}
}