{
  "type": "Feature",
  "properties": {
    "iso:country":"ES",
    "sg:address":"Avda Rufo G Rendueles, 23",
    "sg:city":"Gijon",
    "sg:orig_category":"Institutos De Belleza",
    "sg:phone":"+34 985 19 56 01",
    "sg:postcode":"33203",
    "sg:province":"Asturias",
    "wof:name":"Sol Y Moca S.l.",
    "wof:placetype":"venue"
},
  "geometry": {"coordinates":[-5.645608902,43.5401306152],"type":"Point"}
}