{
  "type": "Feature",
  "properties": {
    "addr:full":"Ctra Villamarchante, 109 Riba-roja Turia Valencia 46190",
    "addr:housenumber":"109",
    "addr:postcode":"46190",
    "addr:street":"Ctra Villamarchante",
    "iso:country":"ES",
    "sg:address":"Ctra Villamarchante, 109",
    "sg:city":"Riba-roja Turia",
    "sg:orig_category":"Ense\u00d1anza, Formaci\u00d3n Profesional: Aprendizaje",
    "sg:phone":"+34 962 77 01 51",
    "sg:postcode":"46190",
    "sg:province":"Valencia",
    "wof:name":"Ayuntamiento De Ribarroja",
    "wof:placetype":"venue"
},
  "geometry": {"coordinates":[-0.5280619264,39.5662536621],"type":"Point"}
}