{
  "type": "Feature",
  "properties": {
    "iso:country":"ES",
    "sg:address":"Calle de Comunidad Valenciana, 12",
    "sg:city":"Almoradi",
    "sg:orig_category":"Caf\u00c9s, Bares, Cervecer\u00cdas",
    "sg:phone":"+34 965 70 00 08",
    "sg:postcode":"03160",
    "sg:province":"Alicante",
    "wof:name":"Forrat Rabasco Antonio",
    "wof:placetype":"venue"
},
  "geometry": {"coordinates":[-0.7895542979,38.1106033325],"type":"Point"}
}