{
  "type": "Feature",
  "properties": {
    "addr:full":"Av Bejar, 230 Terrassa Barcelona 08225",
    "addr:housenumber":"230",
    "addr:postcode":"08225",
    "addr:street":"Av Bejar",
    "iso:country":"ES",
    "sg:address":"Av Bejar, 230",
    "sg:city":"Terrassa",
    "sg:orig_category":"Ropa Para Ni\u00d1os (al Por Menor)",
    "sg:phone":"+34 937 35 80 48",
    "sg:postcode":"08225",
    "sg:province":"Barcelona",
    "wof:name":"Moda Tendre S.l.",
    "wof:placetype":"venue"
},
  "geometry": {"coordinates":[2.0171239376,41.5799484253],"type":"Point"}
}