{
  "type": "Feature",
  "properties": {
    "iso:country":"ES",
    "sg:address":"Carr Major Sant Jaume, 47",
    "sg:city":"Villarreal",
    "sg:orig_category":"Lencer\u00cda Femenina, Corseter\u00cda, Trajes De Ba\u00d1o (al Por Menor)",
    "sg:phone":"+34 964 52 19 51",
    "sg:postcode":"12540",
    "sg:province":"Castell\u00f3n",
    "wof:name":"Cabanes Nebot Bienvenida",
    "wof:placetype":"venue"
},
  "geometry": {"coordinates":[-0.0994480029,39.9385032654],"type":"Point"}
}