{
  "type": "Feature",
  "properties": {
    "iso:country":"ES",
    "sg:address":"Calle de Calzada, S/n",
    "sg:city":"San Pedro Arroyo",
    "sg:orig_category":"Alimentaci\u00d3n General (al Por Menor)",
    "sg:phone":"+34 920 24 03 81",
    "sg:postcode":"05350",
    "sg:province":"\u00c1vila",
    "wof:name":"Oniz Moyano Angel",
    "wof:placetype":"venue"
},
  "geometry": {"coordinates":[-4.8715186119,40.8022994995],"type":"Point"}
}