{
  "type": "Feature",
  "properties": {
    "iso:country":"ES",
    "sg:address":"Plaz Salvador, S/n",
    "sg:city":"Sevilla",
    "sg:orig_category":"Asociaciones, Organismos Culturales Y Socioeducativos",
    "sg:phone":"+34 954 22 40 64",
    "sg:postcode":"41004",
    "sg:province":"Sevilla",
    "wof:name":"Hermandad De Nuestra Se\u00f1ora Del Rocio De Sevilla",
    "wof:placetype":"venue"
},
  "geometry": {"coordinates":[-5.9931540489,37.3903694153],"type":"Point"}
}