{
  "type": "Feature",
  "properties": {
    "iso:country":"ES",
    "sg:address":"Calle de Dos, S/n",
    "sg:city":"Manzanares",
    "sg:orig_category":"Asesor\u00cda Para La Organizaci\u00d3n Y Gesti\u00d3n Del Transporte",
    "sg:phone":"+34 926 62 08 17",
    "sg:postcode":"13200",
    "sg:province":"Ciudad Real",
    "wof:name":"Diaz Garrido S.l.",
    "wof:placetype":"venue"
},
  "geometry": {"coordinates":[-3.3589088917,39.0056533813],"type":"Point"}
}