{
  "type": "Feature",
  "properties": {
    "iso:country":"ES",
    "sg:address":"Carr Sant Blai, 1",
    "sg:city":"Cabanes",
    "sg:orig_category":"Producci\u00d3n De Abonos Y De Fertilizantes",
    "sg:phone":"+34 964 33 21 98",
    "sg:postcode":"12180",
    "sg:province":"Castell\u00f3n",
    "wof:name":"Triumph Hisparom S.l.",
    "wof:placetype":"venue"
},
  "geometry": {"coordinates":[0.0448350012,40.1544303894],"type":"Point"}
}