{
  "type": "Feature",
  "properties": {
    "iso:country":"ES",
    "sg:address":"Calle de Valle Inclan, 53",
    "sg:city":"Molina Segura",
    "sg:orig_category":"Iglesias Cristianas Diversas",
    "sg:phone":"+34 968 64 37 11",
    "sg:postcode":"30500",
    "sg:province":"Murcia",
    "wof:name":"Testigos Cristianos De Jehova",
    "wof:placetype":"venue"
},
  "geometry": {"coordinates":[-1.2021780014,38.0563774109],"type":"Point"}
}