{
  "type": "Feature",
  "properties": {
    "addr:full":"Rua Eduardo Pondal, 3 Monforte De Lemos Lugo 27400",
    "addr:housenumber":"3",
    "addr:postcode":"27400",
    "addr:street":"Rua Eduardo Pondal",
    "iso:country":"ES",
    "sg:address":"Rua Eduardo Pondal, 3",
    "sg:city":"Monforte De Lemos",
    "sg:orig_category":"Carnes De Carnicer\u00cda (al Por Mayor)",
    "sg:phone":"+34 982 40 51 16",
    "sg:postcode":"27400",
    "sg:province":"Lugo",
    "wof:name":"Distribuciones A Pinguela S.c.l.",
    "wof:placetype":"venue"
},
  "geometry": {"coordinates":[-7.5032467842,42.5208473206],"type":"Point"}
}