{
  "type": "Feature",
  "properties": {
    "iso:country":"ES",
    "sg:address":"Luga Cuesta De La Pared, S/n",
    "sg:city":"Pared",
    "sg:orig_category":"Asociaciones, Organismos Culturales Y Socioeducativos",
    "sg:phone":"+34 928 17 40 24",
    "sg:postcode":"35627",
    "sg:province":"Las Palmas",
    "wof:name":"Ayuntamiento De Pajara",
    "wof:placetype":"venue"
},
  "geometry": {"coordinates":[-14.213350296,28.2138404846],"type":"Point"}
}