{
  "type": "Feature",
  "properties": {
    "addr:full":"Calle de Hombre De Palo, 11 Toledo Toledo 45001",
    "addr:housenumber":"11",
    "addr:postcode":"45001",
    "addr:street":"Calle De Hombre De Palo",
    "iso:country":"ES",
    "sg:address":"Calle de Hombre De Palo, 11",
    "sg:city":"Toledo",
    "sg:orig_category":"Confecci\u00d3n De Trajes Para Se\u00d1oras",
    "sg:phone":"+34 925 21 46 30",
    "sg:postcode":"45001",
    "sg:province":"Toledo",
    "wof:name":"Lozano Reyes Antonio",
    "wof:placetype":"venue"
},
  "geometry": {"coordinates":[-4.0237350464,39.8581161499],"type":"Point"}
}