{
  "type": "Feature",
  "properties": {
    "iso:country":"ES",
    "sg:address":"Avda Novelda, 118",
    "sg:city":"Alacant",
    "sg:orig_category":"Venta, Montaje De Neum\u00c1ticos",
    "sg:phone":"+34 965 17 02 41",
    "sg:postcode":"03011",
    "sg:province":"Alicante",
    "wof:name":"Neumaticos Altiplano S.l.",
    "wof:placetype":"venue"
},
  "geometry": {"coordinates":[-0.4984689951,38.373840332],"type":"Point"}
}