{
  "type": "Feature",
  "properties": {
    "iso:country":"ES",
    "sg:address":"Calle de Coli Escalona, Leonardo, 52",
    "sg:city":"Sabi\u00f1anigo",
    "sg:orig_category":"Laboratorios Y Cl\u00cdnicas Veterinarias",
    "sg:phone":"+34 974 48 14 79",
    "sg:postcode":"22600",
    "sg:province":"Huesca",
    "wof:name":"Perez Marcuello Maria Jesus",
    "wof:placetype":"venue"
},
  "geometry": {"coordinates":[-0.3674978912,42.5192298889],"type":"Point"}
}