{
  "type": "Feature",
  "properties": {
    "iso:country":"ES",
    "sg:address":"Plaz Tomas Zumalacarregui, S/n",
    "sg:city":"Alsasua",
    "sg:orig_category":"Poller\u00cda Y Caza (al Por Menor)",
    "sg:phone":"+34 948 46 79 63",
    "sg:postcode":"31800",
    "sg:province":"Navarra",
    "wof:name":"Anguiano Aguado Maria Carmen",
    "wof:placetype":"venue"
},
  "geometry": {"coordinates":[-2.1725392342,42.8938446045],"type":"Point"}
}