{
  "type": "Feature",
  "properties": {
    "iso:country":"ES",
    "sg:address":"Calle de Mayor, S/n",
    "sg:city":"Artazu",
    "sg:orig_category":"Productores Recolectores, Venta Directa De Vinos",
    "sg:phone":"+34 948 38 60 10",
    "sg:postcode":"31109",
    "sg:province":"Navarra",
    "wof:name":"Bodegas Y Vi\u00f1edos Artazu S.a.",
    "wof:placetype":"venue"
},
  "geometry": {"coordinates":[-1.8410029411,42.691242218],"type":"Point"}
}