{
  "type": "Feature",
  "properties": {
    "iso:country":"ES",
    "sg:address":"Pase Maritimo, 25",
    "sg:city":"Torremolinos",
    "sg:orig_category":"Peleter\u00cdas",
    "sg:phone":"+34 952 05 37 87",
    "sg:postcode":"29620",
    "sg:province":"M\u00e1laga",
    "wof:name":"Lakhlisi  Abdeslam",
    "wof:placetype":"venue"
},
  "geometry": {"coordinates":[-4.4943032265,36.623008728],"type":"Point"}
}