{
  "type": "Feature",
  "properties": {
    "addr:full":"Poligono Andori\u00f1as, 22 Las Chafiras Santa Cruz De Tenerife 38639",
    "addr:housenumber":"22",
    "addr:postcode":"38639",
    "addr:street":"Andorin\u0303As",
    "iso:country":"ES",
    "sg:address":"Poligono Andori\u00f1as, 22",
    "sg:city":"Las Chafiras",
    "sg:orig_category":"Bisuter\u00cda, Joyer\u00cda, Relojer\u00cda (al Por Menor)",
    "sg:phone":"+34 922 73 56 40",
    "sg:postcode":"38639",
    "sg:province":"Santa Cruz De Tenerife",
    "wof:name":"Sierra Vereda Antonio",
    "wof:placetype":"venue"
},
  "geometry": {"coordinates":[-16.6115474701,28.0350246429],"type":"Point"}
}