{
  "type": "Feature",
  "properties": {
    "addr:full":"Calle de Arene Pelaio Deuna, S/n Arene-pelaio Deuna Vizcaya 48370",
    "addr:housenumber":"s / n",
    "addr:postcode":"48370",
    "addr:street":"Calle De Arene Pelaio Deuna",
    "iso:country":"ES",
    "sg:address":"Calle de Arene Pelaio Deuna, S/n",
    "sg:city":"Arene-pelaio Deuna",
    "sg:orig_category":"Mec\u00c1nico Del Autom\u00d3vil",
    "sg:phone":"+34 946 88 45 03",
    "sg:postcode":"48370",
    "sg:province":"Vizcaya",
    "wof:name":"Talleres Arene S.l.",
    "wof:placetype":"venue"
},
  "geometry": {"coordinates":[-2.7251009941,43.41929245],"type":"Point"}
}