{
  "type": "Feature",
  "properties": {
    "addr:full":"Afores, S/n Vallcanera Girona 17420",
    "addr:housenumber":"s / n",
    "addr:postcode":"17420",
    "addr:street":"Afores",
    "iso:country":"ES",
    "sg:address":"Afores, S/n",
    "sg:city":"Vallcanera",
    "sg:orig_category":"Fabricaci\u00d3n De Juegos Y Juguetes",
    "sg:phone":"+34 972 16 80 50",
    "sg:postcode":"17420",
    "sg:province":"Girona",
    "wof:name":"Recreatives R.l. Van Beek S.l.",
    "wof:placetype":"venue"
},
  "geometry": {"coordinates":[2.7321300507,41.8180007935],"type":"Point"}
}