{
  "type": "Feature",
  "properties": {
    "iso:country":"ES",
    "sg:address":"Calle de Puerto, 10",
    "sg:city":"S Jose",
    "sg:orig_category":"Molduras, Junquillos, Listones Y Molduras Perforadas",
    "sg:phone":"+34 950 38 04 46",
    "sg:postcode":"04118",
    "sg:province":"Almer\u00eda",
    "wof:name":"Corbi Verdu Luis",
    "wof:placetype":"venue"
},
  "geometry": {"coordinates":[-2.1082139015,36.7618408203],"type":"Point"}
}