{
  "type": "Feature",
  "properties": {
    "addr:full":"Carrer de Deu I Mata, 117 Barcelona Barcelona 08029",
    "addr:housenumber":"117",
    "addr:postcode":"08029",
    "addr:street":"Carrer De Deu I Mata",
    "iso:country":"ES",
    "sg:address":"Carrer de Deu I Mata, 117",
    "sg:city":"Barcelona",
    "sg:orig_category":"Abogados",
    "sg:phone":"+34 933 22 16 48",
    "sg:postcode":"08029",
    "sg:province":"Barcelona",
    "wof:name":"Andreu Batllo Carlos",
    "wof:placetype":"venue"
},
  "geometry": {"coordinates":[2.1381869316,41.3898696899],"type":"Point"}
}