{
  "type": "Feature",
  "properties": {
    "addr:full":"Calle de Gallinero, 35 Pto Real C\u00e1diz 11510",
    "addr:housenumber":"35",
    "addr:postcode":"11510",
    "addr:street":"Calle De Gallinero;Ca\u0301Diz",
    "iso:country":"ES",
    "sg:address":"Calle de Gallinero, 35",
    "sg:city":"Pto Real",
    "sg:orig_category":"Promotores Constructores",
    "sg:phone":"+34 956 83 32 05",
    "sg:postcode":"11510",
    "sg:province":"C\u00e1diz",
    "wof:name":"Construcciones Lavalle Y Moreno S.l.",
    "wof:placetype":"venue"
},
  "geometry": {"coordinates":[-6.2003788948,36.5303382874],"type":"Point"}
}