{
  "type": "Feature",
  "properties": {
    "addr:full":"Calle de Juan Carlo, 45 Palmas De Gran Canaria Las Palmas 35004",
    "addr:housenumber":"45",
    "addr:postcode":"35004",
    "addr:street":"Calle De Juan Carlo",
    "iso:country":"ES",
    "sg:address":"Calle de Juan Carlo, 45",
    "sg:city":"Palmas De Gran Canaria",
    "sg:orig_category":"Importaci\u00d3n",
    "sg:phone":"+34 928 24 02 54",
    "sg:postcode":"35004",
    "sg:province":"Las Palmas",
    "wof:name":"Markoba Trading S.l.",
    "wof:placetype":"venue"
},
  "geometry": {"coordinates":[-15.4270486832,28.1136837006],"type":"Point"}
}