{
  "type": "Feature",
  "properties": {
    "addr:full":"Carrer de Mallorca, 211 Barcelona Barcelona 08008",
    "addr:housenumber":"211",
    "addr:postcode":"08008",
    "addr:street":"Carrer De Mallorca",
    "iso:country":"ES",
    "sg:address":"Carrer de Mallorca, 211",
    "sg:city":"Barcelona",
    "sg:orig_category":"M\u00c9dicos: Dermatolog\u00cda Y Venereolog\u00cda",
    "sg:phone":"+34 934 51 35 41",
    "sg:postcode":"08008",
    "sg:province":"Barcelona",
    "wof:name":"Tribo Boixareu Maria Jose",
    "wof:placetype":"venue"
},
  "geometry": {"coordinates":[2.158479929,41.3907699585],"type":"Point"}
}