{
  "type": "Feature",
  "properties": {
    "iso:country":"ES",
    "sg:address":"Carrer de Arago, 412",
    "sg:city":"Barcelona",
    "sg:orig_category":"Andamiajes Y Escaleras De Mano (fabricaci\u00d3n, Al Por Mayor)",
    "sg:phone":"+34 932 32 12 84",
    "sg:postcode":"08013",
    "sg:province":"Barcelona",
    "wof:name":"Pablo Baldu Dolores",
    "wof:placetype":"venue"
},
  "geometry": {"coordinates":[2.1747119427,41.3993682861],"type":"Point"}
}