{
  "type": "Feature",
  "properties": {
    "iso:country":"ES",
    "sg:address":"Pla\u00c7 Espanya, 13",
    "sg:city":"Inca",
    "sg:orig_category":"Relojer\u00cda (al Por Menor, Reparaci\u00d3n)",
    "sg:phone":"+34 971 50 06 17",
    "sg:postcode":"07300",
    "sg:province":"Islas Baleares",
    "wof:name":"Bonnin Aguilo Gaspar",
    "wof:placetype":"venue"
},
  "geometry": {"coordinates":[2.9208989143,39.7179527283],"type":"Point"}
}