{
  "type": "Feature",
  "properties": {
    "iso:country":"ES",
    "sg:address":"Calle de Navalmoral De La Mata - A, 16",
    "sg:city":"Caceres",
    "sg:orig_category":"Laboratorios Y Trabajos De Fotograf\u00cda, V\u00cddeo Y Cine",
    "sg:phone":"+34 927 23 29 16",
    "sg:postcode":"10005",
    "sg:province":"C\u00e1ceres",
    "wof:name":"Gemaher S.a.",
    "wof:placetype":"venue"
},
  "geometry": {"coordinates":[-6.3879141808,39.4473609924],"type":"Point"}
}