{
  "type": "Feature",
  "properties": {
    "addr:full":"Calle de Lira, 1 Madrid Madrid 28007",
    "addr:housenumber":"1",
    "addr:postcode":"28007",
    "addr:street":"Calle De Lira",
    "iso:country":"ES",
    "sg:address":"Calle de Lira, 1",
    "sg:city":"Madrid",
    "sg:orig_category":"Promotores Constructores",
    "sg:phone":"+34 914 09 48 12",
    "sg:postcode":"28007",
    "sg:province":"Madrid",
    "wof:name":"Construcciones Rio Duero S.l.",
    "wof:placetype":"venue"
},
  "geometry": {"coordinates":[-3.6694180965,40.4085540771],"type":"Point"}
}