{
  "type": "Feature",
  "properties": {
    "iso:country":"ES",
    "sg:address":"Calle de Nicolas Salmeron, 26",
    "sg:city":"Madrid",
    "sg:orig_category":"Plomeros",
    "sg:phone":"+34 913 13 56 97",
    "sg:postcode":"28017",
    "sg:province":"Madrid",
    "wof:name":"Sanchez Ramos Jose",
    "wof:placetype":"venue"
},
  "geometry": {"coordinates":[-3.6263840199,40.4176216125],"type":"Point"}
}