{
  "type": "Feature",
  "properties": {
    "iso:country":"ES",
    "sg:address":"Calle de Convento, 22",
    "sg:city":"Solana",
    "sg:orig_category":"Asesor\u00cda Sobre Comunicaci\u00d3n De Empresas",
    "sg:phone":"+34 926 63 50 70",
    "sg:postcode":"13240",
    "sg:province":"Ciudad Real",
    "wof:name":"Tecman Asesoria S.l.",
    "wof:placetype":"venue"
},
  "geometry": {"coordinates":[-3.2367699146,38.9386825562],"type":"Point"}
}