{
  "type": "Feature",
  "properties": {
    "addr:full":"Avda Andalucia, 43 Albu\u00f1ol Granada 18700",
    "addr:housenumber":"43 albun\u0303ol",
    "addr:postcode":"18700",
    "addr:street":"Avda Andalucia",
    "iso:country":"ES",
    "sg:address":"Avda Andalucia, 43",
    "sg:city":"Albu\u00f1ol",
    "sg:orig_category":"Mec\u00c1nico Del Autom\u00d3vil",
    "sg:phone":"+34 958 82 61 21",
    "sg:postcode":"18700",
    "sg:province":"Granada",
    "wof:name":"Autotaller Y Grua Ramon Garcia E Hijos S.l.",
    "wof:placetype":"venue"
},
  "geometry": {"coordinates":[-3.1734421253,36.7512130737],"type":"Point"}
}