{
  "type": "Feature",
  "properties": {
    "iso:country":"ES",
    "sg:address":"Carrer de Constancia (de La), 49",
    "sg:city":"S. Carles Rapita",
    "sg:orig_category":"Bares, Piano",
    "sg:phone":"+34 977 74 25 65",
    "sg:postcode":"43540",
    "sg:province":"Tarragona",
    "wof:name":"Geballi Baila Angel",
    "wof:placetype":"venue"
},
  "geometry": {"coordinates":[0.5897809863,40.6207466125],"type":"Point"}
}