{
  "type": "Feature",
  "properties": {
    "iso:country":"ES",
    "sg:address":"Calle de Purisima (la), 2",
    "sg:city":"Uroz",
    "sg:orig_category":"Laboratorios De Control Sanitario Y Ambiental",
    "sg:phone":"+34 948 33 81 14",
    "sg:postcode":"31485",
    "sg:province":"Navarra",
    "wof:name":"Martinez Gonzalez Cristian",
    "wof:placetype":"venue"
},
  "geometry": {"coordinates":[-1.5125999451,42.7971801758],"type":"Point"}
}