{
  "type": "Feature",
  "properties": {
    "iso:country":"ES",
    "sg:address":"Calle de Salamanca, 80",
    "sg:city":"Zamora",
    "sg:orig_category":"M\u00c1rmoles, Granitos Y Piedras Naturales",
    "sg:phone":"+34 980 52 71 68",
    "sg:postcode":"49028",
    "sg:province":"Zamora",
    "wof:name":"Ramos Alberca Fernando",
    "wof:placetype":"venue"
},
  "geometry": {"coordinates":[-5.7417287827,41.4942207336],"type":"Point"}
}