{
  "type": "Feature",
  "properties": {
    "addr:full":"Barr Salas, 95 Liencres Cantabria 39120",
    "addr:housenumber":"95",
    "addr:postcode":"39120",
    "addr:street":"Salas",
    "iso:country":"ES",
    "sg:address":"Barr Salas, 95",
    "sg:city":"Liencres",
    "sg:orig_category":"Molduras, Junquillos, Listones Y Molduras Perforadas",
    "sg:phone":"+34 942 57 80 55",
    "sg:postcode":"39120",
    "sg:province":"Cantabria",
    "wof:name":"Fernandez Villanueva Eloy",
    "wof:placetype":"venue"
},
  "geometry": {"coordinates":[-3.9269039631,43.4604797363],"type":"Point"}
}