{
  "type": "Feature",
  "properties": {
    "addr:full":"Pla De Quart, 95 Alaquas Valencia 46970",
    "addr:housenumber":"95",
    "addr:postcode":"46970",
    "addr:street":"Quart",
    "iso:country":"ES",
    "sg:address":"Pla De Quart, 95",
    "sg:city":"Alaquas",
    "sg:orig_category":"Paneles De Madera: Contrachapados, Fibras, Particulados, Estratificados (fabricaci\u00d3n, Venta)",
    "sg:phone":"+34 961 50 23 58",
    "sg:postcode":"46970",
    "sg:province":"Valencia",
    "wof:name":"Industria Del Tablero Game S. A.",
    "wof:placetype":"venue"
},
  "geometry": {"coordinates":[-0.4636380076,39.4573860168],"type":"Point"}
}