{
  "type": "Feature",
  "properties": {
    "iso:country":"ES",
    "sg:address":"Nnal. 435 R, Km. 0014,0",
    "sg:city":"Alconera",
    "sg:classifiers":[
        {
            "category":"Manufacturing",
            "subcategory":"Building Materials",
            "type":"Manufacturing & Wholesale Goods"
        }
    ],
    "sg:phone":"+34 924 57 00 94",
    "sg:postcode":"06393",
    "sg:province":"Badajoz",
    "sg:tags":[
        "cemento",
        "y",
        "de",
        "fabricaci\u00d3n",
        "cal"
    ],
    "wof:name":"A.g.cementos Balboa S.a.",
    "wof:placetype":"venue"
},
  "geometry": {"coordinates":[-6.4609999657,38.38073349],"type":"Point"}
}