{
  "type": "Feature",
  "properties": {
    "iso:country":"ES",
    "sg:address":"Calle de Camino Viejo De Leganes, 88",
    "sg:city":"Madrid",
    "sg:orig_category":"Servicios Gsm",
    "sg:phone":"+34 914 69 46 20",
    "sg:postcode":"28025",
    "sg:province":"Madrid",
    "wof:name":"De Santical S.l.",
    "wof:placetype":"venue"
},
  "geometry": {"coordinates":[-3.7310230732,40.3813209534],"type":"Point"}
}