{
  "type": "Feature",
  "properties": {
    "addr:full":"Calle de Sor Josefa Morales, 21 Carrizal Las Palmas 35240",
    "addr:housenumber":"21",
    "addr:postcode":"35240",
    "addr:street":"Calle De Sor Josefa Morales",
    "iso:country":"ES",
    "sg:address":"Calle de Sor Josefa Morales, 21",
    "sg:city":"Carrizal",
    "sg:orig_category":"Mercer\u00cda, Lencer\u00cda (al Por Menor)",
    "sg:phone":"+34 928 78 13 38",
    "sg:postcode":"35240",
    "sg:province":"Las Palmas",
    "wof:name":"Viera Goes Pino",
    "wof:placetype":"venue"
},
  "geometry": {"coordinates":[-15.4120807648,27.9095497131],"type":"Point"}
}