{
  "type": "Feature",
  "properties": {
    "addr:full":"Calle de Comuneros De Castilla, 3 Zaragoza Zaragoza 50002",
    "addr:housenumber":"3",
    "addr:postcode":"50002",
    "addr:street":"Calle De Comuneros De Castilla",
    "iso:country":"ES",
    "sg:address":"Calle de Comuneros De Castilla, 3",
    "sg:city":"Zaragoza",
    "sg:orig_category":"Alimentaci\u00d3n General (al Por Menor)",
    "sg:phone":"+34 976 39 07 48",
    "sg:postcode":"50002",
    "sg:province":"Zaragoza",
    "wof:name":"Mecina Vellocillo Francisco",
    "wof:placetype":"venue"
},
  "geometry": {"coordinates":[-0.8603640199,41.6505851746],"type":"Point"}
}