{
  "type": "Feature",
  "properties": {
    "addr:full":"Calle de Escuza Jose Maria, 4 Bilbao Vizcaya 48013",
    "addr:housenumber":"4",
    "addr:postcode":"48013",
    "addr:street":"Calle De Escuza Jose Maria",
    "iso:country":"ES",
    "sg:address":"Calle de Escuza Jose Maria, 4",
    "sg:city":"Bilbao",
    "sg:orig_category":"Talleres De Corte Y Confecci\u00d3n",
    "sg:phone":"+34 944 27 69 25",
    "sg:postcode":"48013",
    "sg:province":"Vizcaya",
    "wof:name":"Rodriguez Perez Rosario",
    "wof:placetype":"venue"
},
  "geometry": {"coordinates":[-2.9451711178,43.2622489929],"type":"Point"}
}