{
  "type": "Feature",
  "properties": {
    "iso:country":"ES",
    "sg:address":"Cmno Pi Gros, 8",
    "sg:city":"Castellon De La Plana",
    "sg:orig_category":"Veh\u00cdculos De Ocasi\u00d3n",
    "sg:phone":"+34 964 25 22 45",
    "sg:postcode":"12005",
    "sg:province":"Castell\u00f3n",
    "wof:name":"Franauto Mediterranea S.l.",
    "wof:placetype":"venue"
},
  "geometry": {"coordinates":[-0.057537701,39.9680213928],"type":"Point"}
}