{
  "type": "Feature",
  "properties": {
    "addr:full":"Avda. Cruz, 6 Combarro Pontevedra 36993",
    "addr:housenumber":"6",
    "addr:postcode":"36993",
    "addr:street":"Avda. Cruz",
    "iso:country":"ES",
    "sg:address":"Avda. Cruz, 6",
    "sg:city":"Combarro",
    "sg:orig_category":"Agricultura: Abastecimiento Y Cosechado (negocio)",
    "sg:phone":"+34 986 77 21 21",
    "sg:postcode":"36993",
    "sg:province":"Pontevedra",
    "wof:name":"Perez Pousada Jose Andres",
    "wof:placetype":"venue"
},
  "geometry": {"coordinates":[-8.6917266846,42.4410018921],"type":"Point"}
}