{
  "type": "Feature",
  "properties": {
    "addr:full":"S. Mac Bride, 63 Urb. Valles Parc-can Barcelo Barcelona 08191",
    "addr:postcode":"08191",
    "addr:street":"Urb.;Parc-Can;Barcelona",
    "iso:country":"ES",
    "sg:address":"S. Mac Bride, 63",
    "sg:city":"Urb. Valles Parc-can Barcelo",
    "sg:orig_category":"Electricidad: Instaladores",
    "sg:phone":"+34 935 87 06 79",
    "sg:postcode":"08191",
    "sg:province":"Barcelona",
    "wof:name":"Aeligas S.c.p",
    "wof:placetype":"venue"
},
  "geometry": {"coordinates":[2.1699187756,41.3879165649],"type":"Point"}
}