{
  "type": "Feature",
  "properties": {
    "addr:full":"Avda San Esteban, 2 Etxebarri Vizcaya 48450",
    "addr:housenumber":"2",
    "addr:postcode":"48450",
    "addr:street":"Avda San Esteban",
    "iso:country":"ES",
    "sg:address":"Avda San Esteban, 2",
    "sg:city":"Etxebarri",
    "sg:orig_category":"Mec\u00c1nico Del Autom\u00d3vil",
    "sg:phone":"+34 944 49 19 43",
    "sg:postcode":"48450",
    "sg:province":"Vizcaya",
    "wof:name":"Talleres Inyeccion Echebarri, S.l.",
    "wof:placetype":"venue"
},
  "geometry": {"coordinates":[-2.8919069767,43.245716095],"type":"Point"}
}