{
  "type": "Feature",
  "properties": {
    "iso:country":"ES",
    "sg:address":"Carr Pare Buenaventura, 32",
    "sg:city":"Pu\u00e7ol",
    "sg:orig_category":"Sociedades, Compa\u00d1\u00cdas Aseguradoras",
    "sg:phone":"+34 961 46 46 46",
    "sg:postcode":"46530",
    "sg:province":"Valencia",
    "wof:name":"Perez Almendros Lucas",
    "wof:placetype":"venue"
},
  "geometry": {"coordinates":[-0.3082489967,39.6158294678],"type":"Point"}
}