{
  "type": "Feature",
  "properties": {
    "addr:full":"Carr Lluna, 74 Palafrugell Girona 17200",
    "addr:housenumber":"74",
    "addr:postcode":"17200",
    "addr:street":"Carr Lluna",
    "iso:country":"ES",
    "sg:address":"Carr Lluna, 74",
    "sg:city":"Palafrugell",
    "sg:orig_category":"Inmobiliaria (agencias)",
    "sg:phone":"+34 972 30 07 24",
    "sg:postcode":"17200",
    "sg:province":"Girona",
    "sg:website":"www.areabrava.com",
    "wof:name":"Farrarons Salva Rosa Maria",
    "wof:placetype":"venue"
},
  "geometry": {"coordinates":[3.1676399708,41.9194335938],"type":"Point"}
}