{
  "type": "Feature",
  "properties": {
    "iso:country":"ES",
    "sg:address":"Cami Vell De Selva (27), S/n",
    "sg:city":"Lloseta",
    "sg:orig_category":"F\u00c1bricas De Ladrillo Y Tejas",
    "sg:phone":"+34 971 51 47 01",
    "sg:postcode":"07360",
    "sg:province":"Islas Baleares",
    "wof:name":"Encofrados J.alsina S.a.",
    "wof:placetype":"venue"
},
  "geometry": {"coordinates":[2.8711159229,39.7173461914],"type":"Point"}
}