{
  "type": "Feature",
  "properties": {
    "iso:country":"ES",
    "sg:address":"Avda Generalisimo (del), 14",
    "sg:city":"Boadilla Del Monte",
    "sg:orig_category":"Bancos",
    "sg:phone":"+34 916 33 25 11",
    "sg:postcode":"28660",
    "sg:province":"Madrid",
    "wof:name":"Bt Espa\u00d1a Compa\u00d1ia De Servicios Globales De Telecomunicaciones S.a.u.",
    "wof:placetype":"venue"
},
  "geometry": {"coordinates":[-3.8758120537,40.4058876038],"type":"Point"}
}