{
  "type": "Feature",
  "properties": {
    "iso:country":"ES",
    "sg:address":"Calle de Santiago Apostol, 4",
    "sg:city":"San Vicente De Barakaldo",
    "sg:orig_category":"M\u00c9dicos: Estomatolog\u00cda",
    "sg:phone":"+34 944 85 08 66",
    "sg:postcode":"48902",
    "sg:province":"Vizcaya",
    "wof:name":"Uribasterra Achurra Antonio",
    "wof:placetype":"venue"
},
  "geometry": {"coordinates":[-2.9923419952,43.2923240662],"type":"Point"}
}