{
  "type": "Feature",
  "properties": {
    "iso:country":"ES",
    "sg:address":"Ctra Camp De Mar, S/n",
    "sg:city":"Port D'andratx",
    "sg:orig_category":"Distribuci\u00d3n De Petr\u00d3leo Y Derivados",
    "sg:phone":"+34 971 67 15 09",
    "sg:postcode":"07157",
    "sg:province":"Islas Baleares",
    "wof:name":"Port D'andratx 4g4 S.l.",
    "wof:placetype":"venue"
},
  "geometry": {"coordinates":[2.4215099812,39.5746994019],"type":"Point"}
}