{
  "type": "Feature",
  "properties": {
    "addr:full":"Ctra Villaviciosa (c-5114) (de), Km. 0004,0 Mostoles Madrid 28935",
    "addr:postcode":"c-5114;28935",
    "addr:street":"Ctra Villaviciosa;De Km. 0004,0 Mostoles",
    "iso:country":"ES",
    "sg:address":"Ctra Villaviciosa (c-5114) (de), Km. 0004,0",
    "sg:city":"Mostoles",
    "sg:orig_category":"Fabricaci\u00d3n De Sobres, Bolsas Y Fundas",
    "sg:phone":"+34 916 13 34 17",
    "sg:postcode":"28935",
    "sg:province":"Madrid",
    "wof:name":"S. Maurin S. A.",
    "wof:placetype":"venue"
},
  "geometry": {"coordinates":[-3.9280939102,40.3081817627],"type":"Point"}
}