{
  "type": "Feature",
  "properties": {
    "iso:country":"ES",
    "sg:address":"Avda Baron De Carcer, 42",
    "sg:city":"Valencia",
    "sg:orig_category":"M\u00c9dicos: Neumolog\u00cda",
    "sg:phone":"+34 963 51 83 84",
    "sg:postcode":"46001",
    "sg:province":"Valencia",
    "wof:name":"Lluch Motta Rafael-vicente",
    "wof:placetype":"venue"
},
  "geometry": {"coordinates":[-0.3797689974,39.470287323],"type":"Point"}
}