{
  "type": "Feature",
  "properties": {
    "iso:country":"ES",
    "sg:address":"Avda Canarias, 122",
    "sg:city":"Vecindario",
    "sg:orig_category":"Sociedades, Compa\u00d1\u00cdas Aseguradoras",
    "sg:phone":"+34 928 75 03 31",
    "sg:postcode":"35110",
    "sg:province":"Las Palmas",
    "wof:name":"Correduria De Seguros Torres F.t. S.l.",
    "wof:placetype":"venue"
},
  "geometry": {"coordinates":[-15.4406194687,27.8517799377],"type":"Point"}
}