{
  "type": "Feature",
  "properties": {
    "addr:full":"Calle de Cine, 27 Vila Cruces Pontevedra 36590",
    "addr:housenumber":"27",
    "addr:postcode":"36590",
    "addr:street":"Calle De Cine",
    "iso:country":"ES",
    "sg:address":"Calle de Cine, 27",
    "sg:city":"Vila Cruces",
    "sg:orig_category":"Ropa De Hogar (al Por Menor)",
    "sg:phone":"+34 986 58 23 40",
    "sg:postcode":"36590",
    "sg:province":"Pontevedra",
    "wof:name":"Gonzalez Castro Engracia",
    "wof:placetype":"venue"
},
  "geometry": {"coordinates":[-8.1718549728,42.7930831909],"type":"Point"}
}