{
  "type": "Feature",
  "properties": {
    "iso:country":"ES",
    "sg:address":"Calle de Antonio Lopez, 6",
    "sg:city":"Madrid",
    "sg:orig_category":"Poller\u00cda Y Caza (al Por Menor)",
    "sg:phone":"+34 915 65 21 55",
    "sg:postcode":"28019",
    "sg:province":"Madrid",
    "wof:name":"Redondo Rubio Eugenio",
    "wof:placetype":"venue"
},
  "geometry": {"coordinates":[-3.7141978741,40.3970222473],"type":"Point"}
}