{
  "type": "Feature",
  "properties": {
    "addr:full":"Avda Ramon Y Cajal, 3 Marbella M\u00e1laga 29600",
    "addr:housenumber":"3",
    "addr:postcode":"29600",
    "addr:street":"Avda Ramon Y Cajal;Ma\u0301Laga",
    "iso:country":"ES",
    "sg:address":"Avda Ramon Y Cajal, 3",
    "sg:city":"Marbella",
    "sg:orig_category":"Ropa Para Caballeros (al Por Menor)",
    "sg:phone":"+34 952 86 00 78",
    "sg:postcode":"29600",
    "sg:province":"M\u00e1laga",
    "sg:website":"www.spf.com",
    "wof:name":"Cortefiel S.a.",
    "wof:placetype":"venue"
},
  "geometry": {"coordinates":[-4.8851461411,36.5090408325],"type":"Point"}
}