{
  "type": "Feature",
  "properties": {
    "iso:country":"ES",
    "sg:address":"Pase Berabera De, 18",
    "sg:city":"Donostia-san Sebastian",
    "sg:orig_category":"Impuestos, Tesoro P\u00dablico",
    "sg:phone":"+34 943 31 12 82",
    "sg:postcode":"20009",
    "sg:province":"Guip\u00f9zcoa",
    "wof:name":"Francisco Martin S.c.",
    "wof:placetype":"venue"
},
  "geometry": {"coordinates":[-1.9931880236,43.3008613586],"type":"Point"}
}