{
  "type": "Feature",
  "properties": {
    "addr:full":"Avda Ramon Nieto, 302 Penis Pontevedra 36205",
    "addr:housenumber":"302",
    "addr:postcode":"36205",
    "addr:street":"Avda Ramon Nieto",
    "iso:country":"ES",
    "sg:address":"Avda Ramon Nieto, 302",
    "sg:city":"Penis",
    "sg:orig_category":"Asociaciones, Organismos Culturales Y Socioeducativos",
    "sg:phone":"+34 986 37 96 18",
    "sg:postcode":"36205",
    "sg:province":"Pontevedra",
    "wof:name":"Asociacion Vecinal Cultural Y Deportiva De Lavadores",
    "wof:placetype":"venue"
},
  "geometry": {"coordinates":[-8.6480531693,42.4336204529],"type":"Point"}
}