{
  "type": "Feature",
  "properties": {
    "addr:full":"Avgd Raval, 88 Massamagrell Valencia 46130",
    "addr:housenumber":"88",
    "addr:postcode":"46130",
    "addr:street":"Raval",
    "iso:country":"ES",
    "sg:address":"Avgd Raval, 88",
    "sg:city":"Massamagrell",
    "sg:orig_category":"Frutas Y Legumbres Frescas (al Por Mayor)",
    "sg:phone":"+34 961 44 44 72",
    "sg:postcode":"46130",
    "sg:province":"Valencia",
    "wof:name":"Adelantado Celda Juan Jose",
    "wof:placetype":"venue"
},
  "geometry": {"coordinates":[-0.3329221904,39.5671615601],"type":"Point"}
}