{
  "type": "Feature",
  "properties": {
    "addr:full":"Calle de General Elorza, 75 Oviedo Asturias 33002",
    "addr:housenumber":"75",
    "addr:postcode":"33002",
    "addr:street":"Calle De General Elorza",
    "iso:country":"ES",
    "sg:address":"Calle de General Elorza, 75",
    "sg:city":"Oviedo",
    "sg:orig_category":"Alimentaci\u00d3n General (al Por Menor)",
    "sg:phone":"+34 985 22 79 20",
    "sg:postcode":"33002",
    "sg:province":"Asturias",
    "wof:name":"Santos Da Fonseca Ana",
    "wof:placetype":"venue"
},
  "geometry": {"coordinates":[-5.849178791,43.367023468],"type":"Point"}
}