{
  "type": "Feature",
  "properties": {
    "addr:full":"Carrer de Mallorca, 50 S. Boi Llobregat Barcelona 08830",
    "addr:housenumber":"50",
    "addr:postcode":"08830",
    "addr:street":"Carrer De Mallorca",
    "iso:country":"ES",
    "sg:address":"Carrer de Mallorca, 50",
    "sg:city":"S. Boi Llobregat",
    "sg:orig_category":"M\u00c1quinas De Escribir, M\u00c1quinas De Oficina (al Por Menor, Reparaci\u00d3n)",
    "sg:phone":"+34 936 54 21 50",
    "sg:postcode":"08830",
    "sg:province":"Barcelona",
    "wof:name":"Alvarez Corchero Jose",
    "wof:placetype":"venue"
},
  "geometry": {"coordinates":[2.0405225754,41.3403205872],"type":"Point"}
}