{
  "type": "Feature",
  "properties": {
    "iso:country":"ES",
    "sg:address":"Arroyo De La Parra, S/n",
    "sg:city":"Arroyo Parra",
    "sg:orig_category":"Inmobiliaria (agencias)",
    "sg:phone":"+34 920 28 72 55",
    "sg:postcode":"05278",
    "sg:province":"\u00c1vila",
    "wof:name":"Jose Luis Garcia Lopez S.a.",
    "wof:placetype":"venue"
},
  "geometry": {"coordinates":[-4.700322628,40.6564216614],"type":"Point"}
}