{
  "type": "Feature",
  "properties": {
    "iso:country":"ES",
    "sg:address":"Avda Lisboa (de), 38",
    "sg:city":"Coslada",
    "sg:orig_category":"Molduras, Junquillos, Listones Y Molduras Perforadas",
    "sg:phone":"+34 916 72 18 46",
    "sg:postcode":"28820",
    "sg:province":"Madrid",
    "wof:name":"Berlanga Martinez Pedro",
    "wof:placetype":"venue"
},
  "geometry": {"coordinates":[-3.5443069935,40.4164733887],"type":"Point"}
}