{
  "type": "Feature",
  "properties": {
    "iso:country":"ES",
    "sg:address":"Calle de Matosa, 1",
    "sg:city":"Bajos Y Tagoro",
    "sg:orig_category":"Cerrajer\u00cda, Ferrallista",
    "sg:phone":"+34 922 58 10 49",
    "sg:postcode":"38380",
    "sg:province":"Santa Cruz De Tenerife",
    "wof:name":"Comunidad De Bienes Cruz Mar C.b.",
    "wof:placetype":"venue"
},
  "geometry": {"coordinates":[-16.4766902924,28.4301795959],"type":"Point"}
}