{
  "type": "Feature",
  "properties": {
    "addr:full":"Avda Carlos Iii, 401 Campillo Del Moro Almer\u00eda 04720",
    "addr:housenumber":"401",
    "addr:postcode":"04720",
    "addr:street":"Avda Carlos Iii",
    "iso:country":"ES",
    "sg:address":"Avda Carlos Iii, 401",
    "sg:city":"Campillo Del Moro",
    "sg:orig_category":"Inmobiliaria (agencias)",
    "sg:phone":"+34 950 34 28 11",
    "sg:postcode":"04720",
    "sg:province":"Almer\u00eda",
    "sg:website":"www.alcarazinmobiliaria.com",
    "wof:name":"Alcaraz Ubeda Abelardo",
    "wof:placetype":"venue"
},
  "geometry": {"coordinates":[-2.5784783363,36.8125839233],"type":"Point"}
}