{
  "type": "Feature",
  "properties": {
    "addr:full":"Azagador De La Torre, 44 Sedavi Valencia 46910",
    "addr:housenumber":"44",
    "addr:postcode":"46910",
    "addr:street":"La Torre",
    "iso:country":"ES",
    "sg:address":"Azagador De La Torre, 44",
    "sg:city":"Sedavi",
    "sg:orig_category":"Aislamiento El\u00c9ctrico",
    "sg:phone":"+34 963 96 36 85",
    "sg:postcode":"46910",
    "sg:province":"Valencia",
    "wof:name":"Ivedar S.l.",
    "wof:placetype":"venue"
},
  "geometry": {"coordinates":[-0.3743439913,39.4267196655],"type":"Point"}
}