{
  "type": "Feature",
  "properties": {
    "addr:full":"Calle de Altagracia, 24 Ciudad Real Ciudad Real 13003",
    "addr:housenumber":"24",
    "addr:postcode":"13003",
    "addr:street":"Calle De Altagracia",
    "iso:country":"ES",
    "sg:address":"Calle de Altagracia, 24",
    "sg:city":"Ciudad Real",
    "sg:orig_category":"Asesor\u00cda Sobre Comunicaci\u00d3n De Empresas",
    "sg:phone":"+34 926 22 06 58",
    "sg:postcode":"13003",
    "sg:province":"Ciudad Real",
    "wof:name":"Manuel Antonio Garcia Mu\u00f1oz Gomez Del Pulgar S.l.",
    "wof:placetype":"venue"
},
  "geometry": {"coordinates":[-3.9266221523,38.9908370972],"type":"Point"}
}