{
  "type": "Feature",
  "properties": {
    "addr:full":"Calle de San Jose, 84 San Jose Rinconada Sevilla 41300",
    "addr:postcode":"41300",
    "addr:street":"Calle De San;84",
    "iso:country":"ES",
    "sg:address":"Calle de San Jose, 84",
    "sg:city":"San Jose Rinconada",
    "sg:orig_category":"Hormigonados",
    "sg:phone":"+34 954 79 27 75",
    "sg:postcode":"41300",
    "sg:province":"Sevilla",
    "wof:name":"Arenor S.l.",
    "wof:placetype":"venue"
},
  "geometry": {"coordinates":[-5.9443840981,37.4819297791],"type":"Point"}
}