{
  "type": "Feature",
  "properties": {
    "iso:country":"ES",
    "sg:address":"Calle de Magallanes, 10",
    "sg:city":"Madrid",
    "sg:orig_category":"Fotocopias, Reprograf\u00cda",
    "sg:phone":"+34 914 46 44 81",
    "sg:postcode":"28015",
    "sg:province":"Madrid",
    "wof:name":"San Agustin Badorrey Fidela",
    "wof:placetype":"venue"
},
  "geometry": {"coordinates":[-3.7052979469,40.4330329895],"type":"Point"}
}