{
  "type": "Feature",
  "properties": {
    "iso:country":"ES",
    "sg:address":"Igrexa (figueiro), S/n",
    "sg:city":"Igrexa",
    "sg:orig_category":"Asociaciones, Organismos Culturales Y Socioeducativos",
    "sg:phone":"+34 986 62 03 66",
    "sg:postcode":"36792",
    "sg:province":"Pontevedra",
    "wof:name":"Asociacion Centro Cultural Y Recreativo Figueiro",
    "wof:placetype":"venue"
},
  "geometry": {"coordinates":[-8.6678285599,42.4119529724],"type":"Point"}
}