{
  "type": "Feature",
  "properties": {
    "addr:full":"Carr Figueres, 47 Torroella Montgri Girona 17257",
    "addr:housenumber":"47",
    "addr:postcode":"17257",
    "addr:street":"Carr Figueres",
    "iso:country":"ES",
    "sg:address":"Carr Figueres, 47",
    "sg:city":"Torroella Montgri",
    "sg:orig_category":"Persianas Interiores, Exteriores",
    "sg:phone":"+34 972 75 81 94",
    "sg:postcode":"17257",
    "sg:province":"Girona",
    "wof:name":"Fabregas Roura Joaquin",
    "wof:placetype":"venue"
},
  "geometry": {"coordinates":[3.1277420521,42.042766571],"type":"Point"}
}