{
  "type": "Feature",
  "properties": {
    "addr:full":"Calle de Perpetuo Socorro, 2 Zaragoza Zaragoza 50006",
    "addr:housenumber":"2",
    "addr:postcode":"50006",
    "addr:street":"Calle De Perpetuo Socorro",
    "iso:country":"ES",
    "sg:address":"Calle de Perpetuo Socorro, 2",
    "sg:city":"Zaragoza",
    "sg:classifiers":[
        {
            "category":"Personal",
            "subcategory":"Barber",
            "type":"Services"
        }
    ],
    "sg:phone":"+34 976 38 68 05",
    "sg:postcode":"50006",
    "sg:province":"Zaragoza",
    "sg:tags":[
        "caballeros",
        "de",
        "peluqueros"
    ],
    "wof:name":"Mu\u00d1oz Pinilla Maria Zaida",
    "wof:placetype":"venue"
},
  "geometry": {"coordinates":[-0.8875820041,41.6421432495],"type":"Point"}
}