{
  "type": "Feature",
  "properties": {
    "addr:full":"Carr Ponent, 1 Mont-ras Girona 17253",
    "addr:housenumber":"1",
    "addr:postcode":"17253",
    "addr:street":"Carr Ponent",
    "iso:country":"ES",
    "sg:address":"Carr Ponent, 1",
    "sg:city":"Mont-ras",
    "sg:orig_category":"Limpieza Industrial",
    "sg:phone":"+34 972 30 24 08",
    "sg:postcode":"17253",
    "sg:province":"Girona",
    "wof:name":"Bugaderia Costa Brava S.l.",
    "wof:placetype":"venue"
},
  "geometry": {"coordinates":[3.1464159489,41.9082527161],"type":"Point"}
}