{
  "type": "Feature",
  "properties": {
    "addr:full":"Calle de San Antolin, 3 Tordesillas Valladolid 47100",
    "addr:housenumber":"3",
    "addr:postcode":"47100",
    "addr:street":"Calle De San Antolin",
    "iso:country":"ES",
    "sg:address":"Calle de San Antolin, 3",
    "sg:city":"Tordesillas",
    "sg:orig_category":"Librer\u00cdas",
    "sg:phone":"+34 983 77 06 07",
    "sg:postcode":"47100",
    "sg:province":"Valladolid",
    "wof:name":"Juarez Vegas Petra",
    "wof:placetype":"venue"
},
  "geometry": {"coordinates":[-4.9974460602,41.5128135681],"type":"Point"}
}