{
  "type": "Feature",
  "properties": {
    "iso:country":"ES",
    "sg:address":"Calle de Panaderos, 8",
    "sg:city":"Valladolid",
    "sg:orig_category":"Confiter\u00cdas, Chocolater\u00cdas (al Por Menor)",
    "sg:phone":"+34 983 20 69 25",
    "sg:postcode":"47004",
    "sg:province":"Valladolid",
    "wof:name":"Eschute S.l.",
    "wof:placetype":"venue"
},
  "geometry": {"coordinates":[-4.7239379883,41.6478385925],"type":"Point"}
}