{
  "type": "Feature",
  "properties": {
    "addr:full":"Calle de Lorca, 22 Aguilar De La Frontera C\u00f3rdoba 14920",
    "addr:housenumber":"22",
    "addr:postcode":"14920",
    "addr:street":"Calle De Lorca",
    "iso:country":"ES",
    "sg:address":"Calle de Lorca, 22",
    "sg:city":"Aguilar De La Frontera",
    "sg:orig_category":"Carnicer\u00cdas, Carnicer\u00cdas",
    "sg:phone":"+34 957 66 04 68",
    "sg:postcode":"14920",
    "sg:province":"C\u00f3rdoba",
    "wof:name":"Romero Garcia Diego",
    "wof:placetype":"venue"
},
  "geometry": {"coordinates":[-4.657189846,37.5134658813],"type":"Point"}
}