{
  "type": "Feature",
  "properties": {
    "iso:country":"ES",
    "sg:address":"Afores, S/n",
    "sg:city":"Fonollosa",
    "sg:orig_category":"Alimentaci\u00d3n General (al Por Mayor)",
    "sg:phone":"+34 938 36 91 41",
    "sg:postcode":"08259",
    "sg:province":"Barcelona",
    "wof:name":"Railean  Petru",
    "wof:placetype":"venue"
},
  "geometry": {"coordinates":[1.6672199965,41.7623214722],"type":"Point"}
}