{
  "type": "Feature",
  "properties": {
    "addr:full":"Via Laietana, 41 Barcelona Barcelona 08003",
    "addr:housenumber":"41",
    "addr:postcode":"08003",
    "addr:street":"Via Laietana",
    "iso:country":"ES",
    "sg:address":"Via Laietana, 41",
    "sg:city":"Barcelona",
    "sg:orig_category":"Edici\u00d3n De Diarios, Revistas, Boletines",
    "sg:phone":"+34 933 10 05 47",
    "sg:postcode":"08003",
    "sg:province":"Barcelona",
    "wof:name":"El Roure Societat Cooperativa Limitada De Produccion D'educacions",
    "wof:placetype":"venue"
},
  "geometry": {"coordinates":[2.1754369736,41.3863716125],"type":"Point"}
}