{
  "type": "Feature",
  "properties": {
    "iso:country":"ES",
    "sg:address":"Plaz Mayor, 1",
    "sg:city":"Anchuelo",
    "sg:orig_category":"Administraciones Regionales, Departamentales Y Locales",
    "sg:phone":"+34 918 84 00 76",
    "sg:postcode":"28818",
    "sg:province":"Madrid",
    "wof:name":"Ayuntamiento De Anchuelo",
    "wof:placetype":"venue"
},
  "geometry": {"coordinates":[-3.269233942,40.4655036926],"type":"Point"}
}