{
  "type": "Feature",
  "properties": {
    "iso:country":"ES",
    "sg:address":"Tres Cruces, S/n",
    "sg:city":"Casta\u00f1ar Ibor",
    "sg:orig_category":"Electricidad: Instaladores",
    "sg:phone":"+34 927 55 42 23",
    "sg:postcode":"10340",
    "sg:province":"C\u00e1ceres",
    "wof:name":"Garcia Naharro Julio",
    "wof:placetype":"venue"
},
  "geometry": {"coordinates":[-5.4165887833,39.6288642883],"type":"Point"}
}