{
  "type": "Feature",
  "properties": {
    "iso:country":"ES",
    "sg:address":"Calle de San Patricio, 5",
    "sg:city":"Salamanca",
    "sg:orig_category":"Ense\u00d1anza: Idiomas",
    "sg:phone":"+34 923 28 15 14",
    "sg:postcode":"37002",
    "sg:province":"Salamanca",
    "sg:website":"www.escuelai.com",
    "wof:name":"Escuela Internacional Salamanca S.l.",
    "wof:placetype":"venue"
},
  "geometry": {"coordinates":[-5.6640381813,40.9694366455],"type":"Point"}
}