{
  "type": "Feature",
  "properties": {
    "iso:country":"ES",
    "sg:address":"Calle de Ramiro Molina, 27",
    "sg:city":"Madrid",
    "sg:orig_category":"Tapicer\u00cdas",
    "sg:phone":"+34 915 26 47 74",
    "sg:postcode":"28011",
    "sg:province":"Madrid",
    "wof:name":"Vicente Sanchez Venancio",
    "wof:placetype":"venue"
},
  "geometry": {"coordinates":[-3.7360384464,40.4091796875],"type":"Point"}
}