{
  "type": "Feature",
  "properties": {
    "iso:country":"ES",
    "sg:address":"Calle de Garcia Escamez, 9",
    "sg:city":"Yaiza",
    "sg:orig_category":"Distribuci\u00d3n De Petr\u00d3leo Y Derivados",
    "sg:phone":"+34 928 83 03 18",
    "sg:postcode":"35570",
    "sg:province":"Las Palmas",
    "wof:name":"Petrolanza S.l.",
    "wof:placetype":"venue"
},
  "geometry": {"coordinates":[-13.7630233765,28.954416275],"type":"Point"}
}