{
  "type": "Feature",
  "properties": {
    "addr:full":"Carrer de Maresme, 70 Barcelona Barcelona 08019",
    "addr:housenumber":"70",
    "addr:postcode":"08019",
    "addr:street":"Carrer De Maresme",
    "iso:country":"ES",
    "sg:address":"Carrer de Maresme, 70",
    "sg:city":"Barcelona",
    "sg:orig_category":"Pesca Y Caza: Art\u00cdculos (al Por Menor)",
    "sg:phone":"+34 932 66 35 20",
    "sg:postcode":"08019",
    "sg:province":"Barcelona",
    "wof:name":"Posadas Tellez Placida",
    "wof:placetype":"venue"
},
  "geometry": {"coordinates":[2.2139120102,41.4138259888],"type":"Point"}
}