{
  "type": "Feature",
  "properties": {
    "iso:country":"ES",
    "sg:address":"Calle de Obispo Jaime Perez, 35",
    "sg:city":"Valencia",
    "sg:orig_category":"Fabricaci\u00d3n De Acumuladores Y De Pilas El\u00c9ctricas",
    "sg:phone":"+34 963 73 28 12",
    "sg:postcode":"46006",
    "sg:province":"Valencia",
    "wof:name":"Indalux Iluminacion Tecnica S.l.",
    "wof:placetype":"venue"
},
  "geometry": {"coordinates":[-0.3648079932,39.4573287964],"type":"Point"}
}