{
  "type": "Feature",
  "properties": {
    "addr:full":"Calle de Parroco Camino, 18 Luarca Asturias 33700",
    "addr:housenumber":"18",
    "addr:postcode":"33700",
    "addr:street":"Calle De Parroco Camino",
    "iso:country":"ES",
    "sg:address":"Calle de Parroco Camino, 18",
    "sg:city":"Luarca",
    "sg:orig_category":"Estancos",
    "sg:phone":"+34 985 64 09 29",
    "sg:postcode":"33700",
    "sg:province":"Asturias",
    "wof:name":"Magar Gonzalez Baldomero",
    "wof:placetype":"venue"
},
  "geometry": {"coordinates":[-6.5344181061,43.5446128845],"type":"Point"}
}