{
  "type": "Feature",
  "properties": {
    "iso:country":"ES",
    "sg:address":"Carr Can Barrera, 123",
    "sg:city":"Cabaneta",
    "sg:orig_category":"Caf\u00c9s, Bares, Cervecer\u00cdas",
    "sg:phone":"+34 971 60 47 67",
    "sg:postcode":"07141",
    "sg:province":"Islas Baleares",
    "wof:name":"Lopez Jimenez Jose Manuel",
    "wof:placetype":"venue"
},
  "geometry": {"coordinates":[2.7445349693,39.6195487976],"type":"Point"}
}