{
  "type": "Feature",
  "properties": {
    "addr:full":"Cmno Salabosque, 11 Aljucer Murcia 30152",
    "addr:housenumber":"11",
    "addr:postcode":"30152",
    "addr:street":"Cmno Salabosque",
    "iso:country":"ES",
    "sg:address":"Cmno Salabosque, 11",
    "sg:city":"Aljucer",
    "sg:orig_category":"Empresas De Carpinter\u00cda De Madera",
    "sg:phone":"+34 968 34 49 19",
    "sg:postcode":"30152",
    "sg:province":"Murcia",
    "wof:name":"Jumi Decor S.l.",
    "wof:placetype":"venue"
},
  "geometry": {"coordinates":[-1.1452490091,37.9643058777],"type":"Point"}
}