{
  "type": "Feature",
  "properties": {
    "addr:full":"Calle de Puerta Canseco, 35 Santa Cruz De Tenerife Santa Cruz De Tenerife 38003",
    "addr:housenumber":"35",
    "addr:postcode":"38003",
    "addr:street":"Calle De Puerta Canseco",
    "iso:country":"ES",
    "sg:address":"Calle de Puerta Canseco, 35",
    "sg:city":"Santa Cruz De Tenerife",
    "sg:orig_category":"Arquitectos",
    "sg:phone":"+34 922 28 88 38",
    "sg:postcode":"38003",
    "sg:province":"Santa Cruz De Tenerife",
    "wof:name":"Martin Menis Fernando",
    "wof:placetype":"venue"
},
  "geometry": {"coordinates":[-16.2524986267,28.4663791656],"type":"Point"}
}