{
  "type": "Feature",
  "properties": {
    "iso:country":"ES",
    "sg:address":"Av Jaume I El Conqueridor, 1",
    "sg:city":"Playa Muchavista",
    "sg:orig_category":"Inform\u00c1tica (estudios, Servicios, Asesor\u00cda, Formaci\u00d3n)",
    "sg:phone":"+34 965 10 77 71",
    "sg:postcode":"03560",
    "sg:province":"Alicante",
    "wof:name":"Trymedia Systems S.l.",
    "wof:placetype":"venue"
},
  "geometry": {"coordinates":[-0.4088290036,38.38621521],"type":"Point"}
}