{
  "type": "Feature",
  "properties": {
    "iso:country":"ES",
    "sg:address":"Calle de Nueva (la), S/n",
    "sg:city":"Laguna Negrillos",
    "sg:orig_category":"Carnicer\u00cdas, Carnicer\u00cdas",
    "sg:phone":"+34 987 75 51 73",
    "sg:postcode":"24234",
    "sg:province":"Le\u00f3n",
    "wof:name":"Garcia Prieto Francisco",
    "wof:placetype":"venue"
},
  "geometry": {"coordinates":[-5.660577774,42.237827301],"type":"Point"}
}