{
  "type": "Feature",
  "properties": {
    "addr:full":"Calle de San Antonio, 11 Bujalance C\u00f3rdoba 14650",
    "addr:housenumber":"11",
    "addr:postcode":"14650",
    "addr:street":"Calle De San Antonio",
    "iso:country":"ES",
    "sg:address":"Calle de San Antonio, 11",
    "sg:city":"Bujalance",
    "sg:orig_category":"Confecci\u00d3n (fabricaci\u00d3n, Al Por Mayor)",
    "sg:phone":"+34 957 17 00 58",
    "sg:postcode":"14650",
    "sg:province":"C\u00f3rdoba",
    "wof:name":"Soriano Alcala Jose",
    "wof:placetype":"venue"
},
  "geometry": {"coordinates":[-4.3797860146,37.8960418701],"type":"Point"}
}