{
  "type": "Feature",
  "properties": {
    "addr:full":"Calle de Carcalacueva (de), 33 Cuestas Madrid 28229",
    "addr:housenumber":"33",
    "addr:postcode":"28229",
    "addr:street":"Calle De Carcalacueva De",
    "iso:country":"ES",
    "sg:address":"Calle de Carcalacueva (de), 33",
    "sg:city":"Cuestas",
    "sg:orig_category":"Muebles Y Decoraci\u00d3n De Jardines (fabricaci\u00d3n, Venta)",
    "sg:phone":"+34 918 15 16 56",
    "sg:postcode":"28229",
    "sg:province":"Madrid",
    "wof:name":"Molinos Molinos Herminia",
    "wof:placetype":"venue"
},
  "geometry": {"coordinates":[-3.9819254875,40.5217094421],"type":"Point"}
}