{
  "type": "Feature",
  "properties": {
    "iso:country":"ES",
    "sg:address":"Avda Bele\u00d1a, 16",
    "sg:city":"Guadalajara",
    "sg:orig_category":"Cajas De Ahorro",
    "sg:phone":"+34 949 21 74 81",
    "sg:postcode":"19005",
    "sg:province":"Guadalajara",
    "wof:name":"Caja Provincial De Ahorros De Guadalajara",
    "wof:placetype":"venue"
},
  "geometry": {"coordinates":[-3.1603739262,40.6387367249],"type":"Point"}
}