{
  "type": "Feature",
  "properties": {
    "addr:full":"Calle de Sebastian Recasens, 27 Sevilla Sevilla 41007",
    "addr:housenumber":"27",
    "addr:postcode":"41007",
    "addr:street":"Calle De Sebastian Recasens",
    "iso:country":"ES",
    "sg:address":"Calle de Sebastian Recasens, 27",
    "sg:city":"Sevilla",
    "sg:orig_category":"Tintes (fabricaci\u00d3n, Al Por Mayor)",
    "sg:phone":"+34 954 57 90 88",
    "sg:postcode":"41007",
    "sg:province":"Sevilla",
    "wof:name":"Escorial Moya Javier",
    "wof:placetype":"venue"
},
  "geometry": {"coordinates":[-5.9691781998,37.3906135559],"type":"Point"}
}