{
  "type": "Feature",
  "properties": {
    "iso:country":"ES",
    "sg:address":"Calle de Mendez Nu\u00d1ez, 7",
    "sg:city":"Huelva",
    "sg:orig_category":"M\u00c9dicos: Oftalmolog\u00cda",
    "sg:phone":"+34 959 25 20 18",
    "sg:postcode":"21001",
    "sg:province":"Huelva",
    "wof:name":"Vidarte Rodriguez Damian",
    "wof:placetype":"venue"
},
  "geometry": {"coordinates":[-6.9518618584,37.258026123],"type":"Point"}
}