{
  "type": "Feature",
  "properties": {
    "iso:country":"ES",
    "sg:address":"Carrer de Bailen, 169",
    "sg:city":"Barcelona",
    "sg:orig_category":"Molduras, Junquillos, Listones Y Molduras Perforadas",
    "sg:phone":"+34 932 07 02 40",
    "sg:postcode":"08037",
    "sg:province":"Barcelona",
    "wof:name":"Andreu Fernandez Jose",
    "wof:placetype":"venue"
},
  "geometry": {"coordinates":[2.1655373573,41.4007453918],"type":"Point"}
}