{
  "type": "Feature",
  "properties": {
    "iso:country":"ES",
    "sg:address":"Calle de Simon Bolivar, 52",
    "sg:city":"Santa Cruz De Tenerife",
    "sg:orig_category":"Bisuter\u00cda, Joyer\u00cda, Relojer\u00cda (al Por Menor)",
    "sg:phone":"+34 922 21 45 71",
    "sg:postcode":"38007",
    "sg:province":"Santa Cruz De Tenerife",
    "wof:name":"Montesino Herrera Maria De Los Angeles",
    "wof:placetype":"venue"
},
  "geometry": {"coordinates":[-16.2712631226,28.463262558],"type":"Point"}
}