{
  "type": "Feature",
  "properties": {
    "iso:country":"ES",
    "sg:address":"Carrer de Ponent, 23",
    "sg:city":"Granollers",
    "sg:orig_category":"Peluquer\u00cdas, Peluquer\u00cda Mixta",
    "sg:phone":"+34 938 61 37 42",
    "sg:postcode":"08401",
    "sg:province":"Barcelona",
    "wof:name":"Ca\u00f1adas Cots Concepcion",
    "wof:placetype":"venue"
},
  "geometry": {"coordinates":[2.2858829498,41.610332489],"type":"Point"}
}