{
  "type": "Feature",
  "properties": {
    "addr:full":"Av Constitucio, 80 Castelldefels Barcelona 08860",
    "addr:housenumber":"80",
    "addr:postcode":"08860",
    "addr:street":"Av Constitucio",
    "iso:country":"ES",
    "sg:address":"Av Constitucio, 80",
    "sg:city":"Castelldefels",
    "sg:orig_category":"Inmobiliaria (agencias)",
    "sg:phone":"+34 936 64 61 82",
    "sg:postcode":"08860",
    "sg:province":"Barcelona",
    "sg:website":"www.ficasas.com",
    "wof:name":"Cedos Barcelona S.l.",
    "wof:placetype":"venue"
},
  "geometry": {"coordinates":[1.9808520079,41.2817268372],"type":"Point"}
}