{
  "type": "Feature",
  "properties": {
    "iso:country":"ES",
    "sg:address":"Calle de Benavides, S/n",
    "sg:city":"Matanza De Acentejo",
    "sg:orig_category":"Flores Y Plantas Naturales (al Por Mayor)",
    "sg:phone":"+34 922 57 89 44",
    "sg:postcode":"38370",
    "sg:province":"Santa Cruz De Tenerife",
    "wof:name":"Gonzalez Baez Maria De Los Angeles",
    "wof:placetype":"venue"
},
  "geometry": {"coordinates":[-16.4550514221,28.4498291016],"type":"Point"}
}