{
  "type": "Feature",
  "properties": {
    "addr:full":"Calle de Muralla, 82 Talavera Real Badajoz 06140",
    "addr:housenumber":"82",
    "addr:postcode":"06140",
    "addr:street":"Calle De Muralla",
    "iso:country":"ES",
    "sg:address":"Calle de Muralla, 82",
    "sg:city":"Talavera Real",
    "sg:orig_category":"Venta Al Preg\u00d3n",
    "sg:phone":"+34 924 44 02 05",
    "sg:postcode":"06140",
    "sg:province":"Badajoz",
    "wof:name":"Nu\u00f1ez Gonzalez Mariano",
    "wof:placetype":"venue"
},
  "geometry": {"coordinates":[-6.772559166,38.8789710999],"type":"Point"}
}