{
  "type": "Feature",
  "properties": {
    "iso:country":"ES",
    "sg:address":"Maliciosa, 39",
    "sg:city":"Tres Cantos",
    "sg:orig_category":"Molduras, Junquillos, Listones Y Molduras Perforadas",
    "sg:phone":"+34 918 03 31 51",
    "sg:postcode":"28760",
    "sg:province":"Madrid",
    "wof:name":"Rincon Adrados Francisco Del",
    "wof:placetype":"venue"
},
  "geometry": {"coordinates":[-3.7136108875,40.6102638245],"type":"Point"}
}