{
  "type": "Feature",
  "properties": {
    "iso:country":"ES",
    "sg:address":"Carrer de Aleixar (cami De L'), 48",
    "sg:city":"Reus",
    "sg:orig_category":"Electrodom\u00c9sticos (al Por Menor)",
    "sg:phone":"+34 977 31 31 80",
    "sg:postcode":"43202",
    "sg:province":"Tarragona",
    "wof:name":"Electrodomesticos Idea S.l.",
    "wof:placetype":"venue"
},
  "geometry": {"coordinates":[1.0992380381,41.1569366455],"type":"Point"}
}