{
  "type": "Feature",
  "properties": {
    "addr:full":"Calle de Agustin Deuna, 6 Markina-xemein Vizcaya 48270",
    "addr:housenumber":"6",
    "addr:postcode":"48270",
    "addr:street":"Calle De Agustin Deuna",
    "iso:country":"ES",
    "sg:address":"Calle de Agustin Deuna, 6",
    "sg:city":"Markina-xemein",
    "sg:orig_category":"Asilos De Ancianos. Centros Privados",
    "sg:phone":"+34 946 16 62 21",
    "sg:postcode":"48270",
    "sg:province":"Vizcaya",
    "wof:name":"Gsr S.coop.",
    "wof:placetype":"venue"
},
  "geometry": {"coordinates":[-2.4956243038,43.2655410767],"type":"Point"}
}