{
  "type": "Feature",
  "properties": {
    "iso:country":"ES",
    "sg:address":"Calle de Sebastian Conde, 8",
    "sg:city":"Almonte",
    "sg:orig_category":"Ense\u00d1anza, Formaci\u00d3n Profesional: Aprendizaje",
    "sg:phone":"+34 959 45 15 03",
    "sg:postcode":"21730",
    "sg:province":"Huelva",
    "wof:name":"Ayuntamiento De Almonte",
    "wof:placetype":"venue"
},
  "geometry": {"coordinates":[-6.5166091919,37.2621078491],"type":"Point"}
}