{
  "type": "Feature",
  "properties": {
    "iso:country":"ES",
    "sg:address":"Carr Sant Cap, 30",
    "sg:city":"Vilanova Sal",
    "sg:orig_category":"Asesor\u00cda, Estudio Y Control Medioambiental",
    "sg:phone":"+34 973 45 42 34",
    "sg:postcode":"25612",
    "sg:province":"Lleida",
    "wof:name":"Marcelino Camarasa Miquel",
    "wof:placetype":"venue"
},
  "geometry": {"coordinates":[0.7619799972,41.9095344543],"type":"Point"}
}