{
  "type": "Feature",
  "properties": {
    "addr:full":"Carr Providencia, 129 Badalona Barcelona 08912",
    "addr:housenumber":"129",
    "addr:postcode":"08912",
    "addr:street":"Carr Providencia",
    "iso:country":"ES",
    "sg:address":"Carr Providencia, 129",
    "sg:city":"Badalona",
    "sg:orig_category":"Cerrajer\u00cda, Ferrallista",
    "sg:phone":"+34 933 87 80 91",
    "sg:postcode":"08912",
    "sg:province":"Barcelona",
    "wof:name":"Martinez Costa Rafael",
    "wof:placetype":"venue"
},
  "geometry": {"coordinates":[2.2415750027,41.4440155029],"type":"Point"}
}