{
  "type": "Feature",
  "properties": {
    "iso:country":"ES",
    "sg:address":"Calle de Santa Teresa, 95",
    "sg:city":"Mentrida",
    "sg:orig_category":"Producci\u00d3n, Venta De Productos De Agricultura Biol\u00d3gica",
    "sg:phone":"+34 918 17 70 81",
    "sg:postcode":"45930",
    "sg:province":"Toledo",
    "wof:name":"Lopez Tordesillas Luis",
    "wof:placetype":"venue"
},
  "geometry": {"coordinates":[-4.1951050758,40.2356834412],"type":"Point"}
}