{
  "type": "Feature",
  "properties": {
    "addr:full":"Calle de Anglo-vasco, 2 Vitoria-gasteiz \u00c1lava 01002",
    "addr:housenumber":"2",
    "addr:postcode":"01002",
    "addr:street":"Calle De Anglo-Vasco",
    "iso:country":"ES",
    "sg:address":"Calle de Anglo-vasco, 2",
    "sg:city":"Vitoria-gasteiz",
    "sg:orig_category":"Empresas De Carpinter\u00cda",
    "sg:phone":"+34 945 26 00 59",
    "sg:postcode":"01002",
    "sg:province":"\u00c1lava",
    "wof:name":"Juan Luis Cabrero Alonso",
    "wof:placetype":"venue"
},
  "geometry": {"coordinates":[-2.6656763554,42.8520355225],"type":"Point"}
}