{
  "type": "Feature",
  "properties": {
    "addr:full":"Virgen De Las Mercedes, 15 Mutxamel Alicante 03110",
    "addr:housenumber":"15",
    "addr:postcode":"03110",
    "addr:street":"Virgen;Las Mercedes",
    "iso:country":"ES",
    "sg:address":"Virgen De Las Mercedes, 15",
    "sg:city":"Mutxamel",
    "sg:orig_category":"Cervecer\u00cdas",
    "sg:phone":"+34 965 95 52 33",
    "sg:postcode":"03110",
    "sg:province":"Alicante",
    "wof:name":"Amerpu S.l.",
    "wof:placetype":"venue"
},
  "geometry": {"coordinates":[-0.4432407916,38.4123497009],"type":"Point"}
}