{
  "type": "Feature",
  "properties": {
    "iso:country":"ES",
    "sg:address":"Carr Francisco Vitoria, 23",
    "sg:city":"Sueca",
    "sg:orig_category":"Agencias Y Agentes Comerciales, Representantes",
    "sg:phone":"+34 961 70 16 26",
    "sg:postcode":"46410",
    "sg:province":"Valencia",
    "wof:name":"Biendicho Garcia Juan",
    "wof:placetype":"venue"
},
  "geometry": {"coordinates":[-0.312586993,39.200340271],"type":"Point"}
}