{
  "type": "Feature",
  "properties": {
    "iso:country":"ES",
    "sg:address":"Calle de Navas De Tolosa, 26",
    "sg:city":"Linares",
    "sg:classifiers":[
        {
            "category":"Professional",
            "subcategory":"Research",
            "type":"Services"
        }
    ],
    "sg:phone":"+34 953 60 25 40",
    "sg:postcode":"23700",
    "sg:province":"Ja\u00e9n",
    "sg:tags":[
        "mercado",
        "de",
        "estudios"
    ],
    "wof:name":"Compoired De Andalucia S.l.",
    "wof:placetype":"venue"
},
  "geometry": {"coordinates":[-3.6295690536,38.09400177],"type":"Point"}
}