{
  "type": "Feature",
  "properties": {
    "addr:full":"Carr Arnus, 23 Badalona Barcelona 08911",
    "addr:housenumber":"23",
    "addr:postcode":"08911",
    "addr:street":"Carr Arnus",
    "iso:country":"ES",
    "sg:address":"Carr Arnus, 23",
    "sg:city":"Badalona",
    "sg:orig_category":"Papeler\u00cdas, Librer\u00cdas",
    "sg:phone":"+34 933 89 20 15",
    "sg:postcode":"08911",
    "sg:province":"Barcelona",
    "wof:name":"Martinez Lara Josefa",
    "wof:placetype":"venue"
},
  "geometry": {"coordinates":[2.2468140125,41.4489364624],"type":"Point"}
}