{
  "type": "Feature",
  "properties": {
    "iso:country":"ES",
    "sg:address":"Rua Progreso (do), 89",
    "sg:city":"Ourense",
    "sg:orig_category":"Ropa Para Ni\u00d1os (al Por Menor)",
    "sg:phone":"+34 988 23 00 93",
    "sg:postcode":"32003",
    "sg:province":"Ourense",
    "wof:name":"Rodriguez Alvarez Maria Esther",
    "wof:placetype":"venue"
},
  "geometry": {"coordinates":[-7.8661937714,42.3387184143],"type":"Point"}
}