{
  "type": "Feature",
  "properties": {
    "addr:full":"Calle de Moradas, 36 Valladolid Valladolid 47010",
    "addr:housenumber":"36",
    "addr:postcode":"47010",
    "addr:street":"Calle De Moradas",
    "iso:country":"ES",
    "sg:address":"Calle de Moradas, 36",
    "sg:city":"Valladolid",
    "sg:orig_category":"Comerciantes Al Por Mayor De Vinos, Licores Y Alcoholes",
    "sg:phone":"+34 983 25 24 96",
    "sg:postcode":"47010",
    "sg:province":"Valladolid",
    "wof:name":"Pardo Carlon Felix",
    "wof:placetype":"venue"
},
  "geometry": {"coordinates":[-4.7202749252,41.6623764038],"type":"Point"}
}