{
  "type": "Feature",
  "properties": {
    "iso:country":"ES",
    "sg:address":"Avda Republica Argentina, 2",
    "sg:city":"Sada",
    "sg:orig_category":"Electrodom\u00c9sticos (al Por Menor)",
    "sg:phone":"+34 981 62 02 11",
    "sg:postcode":"15160",
    "sg:province":"A Coru\u00f1a",
    "wof:name":"Sistelcom-telemensaje,s.a.",
    "wof:placetype":"venue"
},
  "geometry": {"coordinates":[-8.2518587112,43.348991394],"type":"Point"}
}