{
  "type": "Feature",
  "properties": {
    "addr:full":"Calle de Pablo Iglesias, 105 Elda Alicante 03600",
    "addr:housenumber":"105",
    "addr:postcode":"03600",
    "addr:street":"Calle De Pablo Iglesias",
    "iso:country":"ES",
    "sg:address":"Calle de Pablo Iglesias, 105",
    "sg:city":"Elda",
    "sg:orig_category":"Reposter\u00cdas",
    "sg:phone":"+34 965 38 17 10",
    "sg:postcode":"03600",
    "sg:province":"Alicante",
    "wof:name":"Panaderia Ortega C.b.",
    "wof:placetype":"venue"
},
  "geometry": {"coordinates":[-0.7941480279,38.4743309021],"type":"Point"}
}