{
  "type": "Feature",
  "properties": {
    "iso:country":"ES",
    "sg:address":"Calle de Embajadores, S/n",
    "sg:city":"Madrid",
    "sg:orig_category":"Semiller\u00cdas",
    "sg:phone":"+34 915 06 48 70",
    "sg:postcode":"28053",
    "sg:province":"Madrid",
    "sg:website":"www.gruporaga.com",
    "wof:name":"Grupo Raga S.a.",
    "wof:placetype":"venue"
},
  "geometry": {"coordinates":[-3.6865539551,40.3827590942],"type":"Point"}
}