{
  "type": "Feature",
  "properties": {
    "addr:full":"Plaz Virgen De La Antigua, 7 Guadalajara Guadalajara 19001",
    "addr:housenumber":"7",
    "addr:postcode":"19001",
    "addr:street":"Plaz Virgen De La Antigua",
    "iso:country":"ES",
    "sg:address":"Plaz Virgen De La Antigua, 7",
    "sg:city":"Guadalajara",
    "sg:orig_category":"Farmacias",
    "sg:phone":"+34 949 21 58 02",
    "sg:postcode":"19001",
    "sg:province":"Guadalajara",
    "wof:name":"Rodrigo Garcia Maria Nuria",
    "wof:placetype":"venue"
},
  "geometry": {"coordinates":[-3.1685209274,40.6324882507],"type":"Point"}
}