{
  "type": "Feature",
  "properties": {
    "iso:country":"ES",
    "sg:address":"Calle de Pinos Alta, 42",
    "sg:city":"Madrid",
    "sg:orig_category":"Caf\u00c9s, Bares, Cervecer\u00cdas",
    "sg:phone":"+34 913 23 13 89",
    "sg:postcode":"28029",
    "sg:province":"Madrid",
    "wof:name":"Hosthermar S.l.",
    "wof:placetype":"venue"
},
  "geometry": {"coordinates":[-3.6972930431,40.4675636292],"type":"Point"}
}