{
  "type": "Feature",
  "properties": {
    "iso:country":"ES",
    "sg:address":"Cost Deia, D'en, 47",
    "sg:city":"Mao",
    "sg:orig_category":"Grafistas",
    "sg:phone":"+34 971 35 67 52",
    "sg:postcode":"07702",
    "sg:province":"Islas Baleares",
    "wof:name":"Diseny I Desenvolupament M.i.a. S.l.",
    "wof:placetype":"venue"
},
  "geometry": {"coordinates":[4.2634820938,39.8879318237],"type":"Point"}
}