{
  "type": "Feature",
  "properties": {
    "iso:country":"ES",
    "sg:address":"Calle de Bolivia, 3",
    "sg:city":"Valladolid",
    "sg:orig_category":"Supermercados Y Hipermercados",
    "sg:phone":"+34 983 47 52 35",
    "sg:postcode":"47014",
    "sg:province":"Valladolid",
    "wof:name":"Gil Rios Pedro",
    "wof:placetype":"venue"
},
  "geometry": {"coordinates":[-4.750140667,41.632610321],"type":"Point"}
}