{
  "type": "Feature",
  "properties": {
    "iso:country":"ES",
    "sg:address":"Carrer de Palau, 13",
    "sg:city":"Alcanar",
    "sg:orig_category":"Peluquer\u00cdas, Peluquer\u00cda Mixta",
    "sg:phone":"+34 977 73 09 36",
    "sg:postcode":"43530",
    "sg:province":"Tarragona",
    "wof:name":"Subirats Reverter Maria Josefa",
    "wof:placetype":"venue"
},
  "geometry": {"coordinates":[0.4808200002,40.5425796509],"type":"Point"}
}