{
  "type": "Feature",
  "properties": {
    "addr:full":"Calle de Madrid, 38 Vitoria-gasteiz \u00c1lava 01002",
    "addr:housenumber":"38",
    "addr:postcode":"01002",
    "addr:street":"Calle De Madrid",
    "iso:country":"ES",
    "sg:address":"Calle de Madrid, 38",
    "sg:city":"Vitoria-gasteiz",
    "sg:orig_category":"Transportes Por V\u00cdas Navegables",
    "sg:phone":"+34 945 25 32 76",
    "sg:postcode":"01002",
    "sg:province":"\u00c1lava",
    "wof:name":"Jose Miguel Morales Leza",
    "wof:placetype":"venue"
},
  "geometry": {"coordinates":[-2.6573989391,42.8549499512],"type":"Point"}
}