{
  "type": "Feature",
  "properties": {
    "addr:full":"Avda Cairo (del), 1 Cordoba C\u00f3rdoba 14014",
    "addr:housenumber":"1",
    "addr:postcode":"14014",
    "addr:street":"Avda Cairo Del;Co\u0301Rdoba",
    "iso:country":"ES",
    "sg:address":"Avda Cairo (del), 1",
    "sg:city":"Cordoba",
    "sg:orig_category":"Mensajer\u00cda Express, Portes Internacionales",
    "sg:phone":"+34 957 26 86 00",
    "sg:postcode":"14014",
    "sg:province":"C\u00f3rdoba",
    "sg:website":"www.mrw.es",
    "wof:name":"Mensajeros Arcos S.l.",
    "wof:placetype":"venue"
},
  "geometry": {"coordinates":[-4.7561888695,37.8924102783],"type":"Point"}
}