{
  "type": "Feature",
  "properties": {
    "addr:full":"Avda Portugal De, 15 Aviles Asturias 33402",
    "addr:housenumber":"15",
    "addr:postcode":"33402",
    "addr:street":"Avda Portugal De",
    "iso:country":"ES",
    "sg:address":"Avda Portugal De, 15",
    "sg:city":"Aviles",
    "sg:orig_category":"Oficinas: Suministros Para (fabricaci\u00d3n, Al Por Mayor)",
    "sg:phone":"+34 985 55 04 11",
    "sg:postcode":"33402",
    "sg:province":"Asturias",
    "wof:name":"Canodigital S.l.",
    "wof:placetype":"venue"
},
  "geometry": {"coordinates":[-5.9276938438,43.5517349243],"type":"Point"}
}