{
  "type": "Feature",
  "properties": {
    "iso:country":"ES",
    "sg:address":"Ctra Beniel, Km. 0001,4",
    "sg:city":"Orihuela",
    "sg:orig_category":"Art\u00cdculos De Madera (fabricaci\u00d3n Y Al Por Mayor)",
    "sg:phone":"+34 966 74 19 00",
    "sg:postcode":"03300",
    "sg:province":"Alicante",
    "wof:name":"Muebles Oriol S.l.",
    "wof:placetype":"venue"
},
  "geometry": {"coordinates":[-0.9519230127,38.0831794739],"type":"Point"}
}