{
  "type": "Feature",
  "properties": {
    "iso:country":"ES",
    "sg:address":"Carr Montjuic, 5",
    "sg:city":"Blanes",
    "sg:orig_category":"Fabricaci\u00d3n, Venta, Instalaci\u00d3n De R\u00d3tulos, De R\u00d3tulos Luminosos",
    "sg:phone":"+34 972 33 13 38",
    "sg:postcode":"17300",
    "sg:province":"Girona",
    "wof:name":"Pinturas Guisado S.l.",
    "wof:placetype":"venue"
},
  "geometry": {"coordinates":[2.7762639523,41.6798744202],"type":"Point"}
}