{
  "type": "Feature",
  "properties": {
    "iso:country":"ES",
    "sg:address":"Ctra Hospitalet, 342",
    "sg:city":"Almeda Mercader",
    "sg:orig_category":"Fabricaci\u00d3n De Moldes Y Modelos",
    "sg:phone":"+34 934 74 00 58",
    "sg:postcode":"08940",
    "sg:province":"Barcelona",
    "wof:name":"Antonio Carrasco Piezas De Norma Para Moldes Y Matrices S.a.",
    "wof:placetype":"venue"
},
  "geometry": {"coordinates":[2.0926597118,41.3582305908],"type":"Point"}
}