{
  "type": "Feature",
  "properties": {
    "addr:full":"Pl Carme, 3 Tarrega Lleida 25300",
    "addr:housenumber":"3",
    "addr:postcode":"25300",
    "addr:street":"Pl Carme",
    "iso:country":"ES",
    "sg:address":"Pl Carme, 3",
    "sg:city":"Tarrega",
    "sg:orig_category":"Caf\u00c9s, Bares, Cervecer\u00cdas",
    "sg:phone":"+34 973 31 00 02",
    "sg:postcode":"25300",
    "sg:province":"Lleida",
    "wof:name":"La Antigua S.c.p.",
    "wof:placetype":"venue"
},
  "geometry": {"coordinates":[1.1394579411,41.6470603943],"type":"Point"}
}