{
  "type": "Feature",
  "properties": {
    "iso:country":"ES",
    "sg:address":"Calle de Joaquin Costa, 9",
    "sg:city":"Zaragoza",
    "sg:orig_category":"Inform\u00c1tica: Consultores",
    "sg:phone":"+34 976 23 53 20",
    "sg:postcode":"50001",
    "sg:province":"Zaragoza",
    "sg:website":"www.insynergy.com",
    "wof:name":"Burillo Serrano Tomas",
    "wof:placetype":"venue"
},
  "geometry": {"coordinates":[-0.8808649778,41.6487846375],"type":"Point"}
}