{
  "type": "Feature",
  "properties": {
    "addr:full":"Calle de General Ricardos, 212 Madrid Madrid 28025",
    "addr:housenumber":"212",
    "addr:postcode":"28025",
    "addr:street":"Calle De General Ricardos",
    "iso:country":"ES",
    "sg:address":"Calle de General Ricardos, 212",
    "sg:city":"Madrid",
    "sg:orig_category":"Ambulancias",
    "sg:phone":"+34 914 62 18 63",
    "sg:postcode":"28025",
    "sg:province":"Madrid",
    "sg:website":"www.ambulanciassamaar.com",
    "wof:name":"Samar Y Servicios Medicos S.l",
    "wof:placetype":"venue"
},
  "geometry": {"coordinates":[-3.7384359837,40.3850288391],"type":"Point"}
}