{
  "type": "Feature",
  "properties": {
    "iso:country":"ES",
    "sg:address":"Carrer de Mare Eterna, 52",
    "sg:city":"Barcelona",
    "sg:orig_category":"Venta De Caravanas, Casas M\u00d3viles, Camping",
    "sg:phone":"+34 933 14 09 27",
    "sg:postcode":"08030",
    "sg:province":"Barcelona",
    "wof:name":"Comunidad De Propietarios De Mare Eterna 52",
    "wof:placetype":"venue"
},
  "geometry": {"coordinates":[2.2026000023,41.4349136353],"type":"Point"}
}