{
  "type": "Feature",
  "properties": {
    "addr:full":"Avda Severo Ochoa, 30 Marbella M\u00e1laga 29600",
    "addr:housenumber":"30",
    "addr:postcode":"29600",
    "addr:street":"Avda Severo Ochoa;Ma\u0301Laga",
    "iso:country":"ES",
    "sg:address":"Avda Severo Ochoa, 30",
    "sg:city":"Marbella",
    "sg:classifiers":[
        {
            "category":"Professional",
            "subcategory":"Management & Consulting",
            "type":"Services"
        }
    ],
    "sg:phone":"+34 952 76 50 31",
    "sg:postcode":"29600",
    "sg:province":"M\u00e1laga",
    "sg:tags":[
        "asesor\u00cda",
        "en",
        "marketing"
    ],
    "wof:name":"Telco Sensors S.l.",
    "wof:placetype":"venue"
},
  "geometry": {"coordinates":[-4.8739619255,36.5092658997],"type":"Point"}
}