{
  "type": "Feature",
  "properties": {
    "addr:full":"Calle de Carquizano, 2 Donostia-san Sebastian Guip\u00f9zcoa 20001",
    "addr:housenumber":"2",
    "addr:postcode":"20001",
    "addr:street":"Calle De Carquizano",
    "iso:country":"ES",
    "sg:address":"Calle de Carquizano, 2",
    "sg:city":"Donostia-san Sebastian",
    "sg:orig_category":"Asociaciones, Organismos Culturales Y Socioeducativos",
    "sg:phone":"+34 943 27 77 98",
    "sg:postcode":"20001",
    "sg:province":"Guip\u00f9zcoa",
    "wof:name":"Donosti Ereski Abesbatza",
    "wof:placetype":"venue"
},
  "geometry": {"coordinates":[-1.972843051,43.3231773376],"type":"Point"}
}