{
  "type": "Feature",
  "properties": {
    "addr:full":"Carrer de Borras, 37 Barcelona Barcelona 08016",
    "addr:housenumber":"37",
    "addr:postcode":"08016",
    "addr:street":"Carrer De Borras",
    "iso:country":"ES",
    "sg:address":"Carrer de Borras, 37",
    "sg:city":"Barcelona",
    "sg:orig_category":"Pintura Y Barniz (al Por Menor)",
    "sg:phone":"+34 933 54 29 93",
    "sg:postcode":"08016",
    "sg:province":"Barcelona",
    "wof:name":"Ruiz Garcia Manuel",
    "wof:placetype":"venue"
},
  "geometry": {"coordinates":[2.1771628857,41.4404411316],"type":"Point"}
}