{
  "type": "Feature",
  "properties": {
    "addr:full":"Ctra Estella, 22 S. Adrian Navarra 31570",
    "addr:housenumber":"22",
    "addr:postcode":"31570",
    "addr:street":"Ctra Estella;S. Adrian Navarra",
    "iso:country":"ES",
    "sg:address":"Ctra Estella, 22",
    "sg:city":"S. Adrian",
    "sg:orig_category":"Venta, Instalaci\u00d3n, Reparaci\u00d3n De Antenas Para Televisi\u00d3n",
    "sg:phone":"+34 948 67 04 99",
    "sg:postcode":"31570",
    "sg:province":"Navarra",
    "wof:name":"Jose Ramon Alvarez S.l.",
    "wof:placetype":"venue"
},
  "geometry": {"coordinates":[-1.9346345663,42.3344116211],"type":"Point"}
}