{
  "type": "Feature",
  "properties": {
    "addr:full":"Calle de Pedro Maria Ric, 8 Zaragoza Zaragoza 50008",
    "addr:housenumber":"8",
    "addr:postcode":"50008",
    "addr:street":"Calle De Pedro Maria Ric",
    "iso:country":"ES",
    "sg:address":"Calle de Pedro Maria Ric, 8",
    "sg:city":"Zaragoza",
    "sg:orig_category":"Agencias Y Agentes Comerciales, Representantes",
    "sg:phone":"+34 976 22 10 23",
    "sg:postcode":"50008",
    "sg:province":"Zaragoza",
    "wof:name":"Fleta Maza Luis Carlos",
    "wof:placetype":"venue"
},
  "geometry": {"coordinates":[-0.8840910196,41.6458358765],"type":"Point"}
}