{
  "type": "Feature",
  "properties": {
    "addr:full":"Rua Igrexa (a), 6 Grove Pontevedra 36980",
    "addr:housenumber":"6",
    "addr:postcode":"36980",
    "addr:street":"Rua Igrexa A",
    "iso:country":"ES",
    "sg:address":"Rua Igrexa (a), 6",
    "sg:city":"Grove",
    "sg:orig_category":"Pompas F\u00danebres, Inhumaciones Y Cremaciones",
    "sg:phone":"+34 986 73 14 28",
    "sg:postcode":"36980",
    "sg:province":"Pontevedra",
    "wof:name":"Maria Luz Mirazo Nu\u00f1ez Y Carmen Mirazo Nu\u00f1ez Cdad",
    "wof:placetype":"venue"
},
  "geometry": {"coordinates":[-8.8686761856,42.4893989563],"type":"Point"}
}