{
  "type": "Feature",
  "properties": {
    "addr:full":"Irunlarrea, 5 Iru\u00f1a Navarra 31008",
    "addr:housenumber":"5",
    "addr:postcode":"31008",
    "addr:street":"Irunlarrea",
    "iso:country":"ES",
    "sg:address":"Irunlarrea, 5",
    "sg:city":"Iru\u00f1a",
    "sg:orig_category":"Lencer\u00cda Femenina, Corseter\u00cda, Trajes De Ba\u00d1o (al Por Menor)",
    "sg:phone":"+34 948 27 76 69",
    "sg:postcode":"31008",
    "sg:province":"Navarra",
    "wof:name":"Martinez Lopez Maria Jesus",
    "wof:placetype":"venue"
},
  "geometry": {"coordinates":[-1.6697340012,42.8072891235],"type":"Point"}
}