{
  "type": "Feature",
  "properties": {
    "iso:country":"ES",
    "sg:address":"Calle de Madrid, 17",
    "sg:city":"Tembleque",
    "sg:orig_category":"Empresas De Pintura Y Revestimientos",
    "sg:phone":"+34 925 14 52 04",
    "sg:postcode":"45780",
    "sg:province":"Toledo",
    "wof:name":"Garcia-cano Carmona Jesus",
    "wof:placetype":"venue"
},
  "geometry": {"coordinates":[-3.5003941059,39.7012557983],"type":"Point"}
}