{
  "type": "Feature",
  "properties": {
    "addr:full":"Carrer de Frederic Mompou, 6 Tarragona Tarragona 43005",
    "addr:housenumber":"6",
    "addr:postcode":"43005",
    "addr:street":"Carrer De Frederic Mompou",
    "iso:country":"ES",
    "sg:address":"Carrer de Frederic Mompou, 6",
    "sg:city":"Tarragona",
    "sg:orig_category":"Servicios De Telecomunicaciones",
    "sg:phone":"+34 977 24 61 33",
    "sg:postcode":"43005",
    "sg:province":"Tarragona",
    "wof:name":"Ericcson Espa\u00d1a S.a.",
    "wof:placetype":"venue"
},
  "geometry": {"coordinates":[1.2416540384,41.1156654358],"type":"Point"}
}