{
  "type": "Feature",
  "properties": {
    "addr:full":"Calle de Progreso, 10 Sonseca Toledo 45100",
    "addr:housenumber":"10",
    "addr:postcode":"45100",
    "addr:street":"Calle De Progreso",
    "iso:country":"ES",
    "sg:address":"Calle de Progreso, 10",
    "sg:city":"Sonseca",
    "sg:orig_category":"Escotaduras, Torneados",
    "sg:phone":"+34 925 38 37 43",
    "sg:postcode":"45100",
    "sg:province":"Toledo",
    "wof:name":"Torres Iglesias Diego",
    "wof:placetype":"venue"
},
  "geometry": {"coordinates":[-3.9823338985,39.6852416992],"type":"Point"}
}