{
  "type": "Feature",
  "properties": {
    "addr:full":"Calle de Claudio Coello, 81 Madrid Madrid 28001",
    "addr:housenumber":"81",
    "addr:postcode":"madrid;28001",
    "addr:street":"Calle De Claudio Coello",
    "iso:country":"ES",
    "sg:address":"Calle de Claudio Coello, 81",
    "sg:city":"Madrid",
    "sg:orig_category":"Complementos De Vestir (al Por Menor)",
    "sg:phone":"+34 914 35 49 03",
    "sg:postcode":"28001",
    "sg:province":"Madrid",
    "wof:name":"Arduan Culatto Lourdes",
    "wof:placetype":"venue"
},
  "geometry": {"coordinates":[-3.6859388351,40.4297599792],"type":"Point"}
}