{
  "type": "Feature",
  "properties": {
    "addr:full":"Cmno Bouza Da Fonte, 5 Bouza Da Fonte Pontevedra 36788",
    "addr:housenumber":"5",
    "addr:postcode":"36788",
    "addr:street":"Cmno Bouza Da Fonte;Da",
    "iso:country":"ES",
    "sg:address":"Cmno Bouza Da Fonte, 5",
    "sg:city":"Bouza Da Fonte",
    "sg:orig_category":"Fabricaci\u00d3n De Tapices Y Moquetas Para Suelos Y Paredes",
    "sg:phone":"+34 986 62 72 15",
    "sg:postcode":"36788",
    "sg:province":"Pontevedra",
    "wof:name":"Manuel Riego Porri\u00f1o S.a.",
    "wof:placetype":"venue"
},
  "geometry": {"coordinates":[-8.8542041779,41.8935165405],"type":"Point"}
}