{
  "type": "Feature",
  "properties": {
    "iso:country":"ES",
    "sg:address":"Calle de Hermanos Machado, 37",
    "sg:city":"Madrid",
    "sg:orig_category":"Comerciantes Al Por Mayor De Vinos, Licores Y Alcoholes",
    "sg:phone":"+34 914 08 37 38",
    "sg:postcode":"28017",
    "sg:province":"Madrid",
    "wof:name":"Mayorga Bascu\u00f1ana Francisco",
    "wof:placetype":"venue"
},
  "geometry": {"coordinates":[-3.6488010883,40.4301300049],"type":"Point"}
}