{
  "type": "Feature",
  "properties": {
    "iso:country":"ES",
    "sg:address":"Carr Polo De Bernabe, 29",
    "sg:city":"Villarreal",
    "sg:orig_category":"Asesor\u00cda Sobre Comunicaci\u00d3n De Empresas",
    "sg:phone":"+34 964 52 76 40",
    "sg:postcode":"12540",
    "sg:province":"Castell\u00f3n",
    "wof:name":"Estudio Dinamico Empresarial Cta.s.coop.v.",
    "wof:placetype":"venue"
},
  "geometry": {"coordinates":[-0.0952939987,39.9453048706],"type":"Point"}
}