{
  "type": "Feature",
  "properties": {
    "iso:country":"ES",
    "sg:address":"Cmno Cendos (de), 15",
    "sg:city":"Avion",
    "sg:orig_category":"Centros De Educaci\u00d3n Especial",
    "sg:phone":"+34 988 48 61 78",
    "sg:postcode":"32435",
    "sg:province":"Ourense",
    "wof:name":"Concello De Avion",
    "wof:placetype":"venue"
},
  "geometry": {"coordinates":[-8.2517595291,42.374420166],"type":"Point"}
}