{
  "type": "Feature",
  "properties": {
    "addr:full":"Cami Merle, 2 Montgo Alicante 03700",
    "addr:housenumber":"2",
    "addr:postcode":"03700",
    "addr:street":"Merle",
    "iso:country":"ES",
    "sg:address":"Cami Merle, 2",
    "sg:city":"Montgo",
    "sg:orig_category":"Inversiones",
    "sg:phone":"+34 966 43 30 41",
    "sg:postcode":"03700",
    "sg:province":"Alicante",
    "wof:name":"Weitzko Inversiones S.l.",
    "wof:placetype":"venue"
},
  "geometry": {"coordinates":[0.1035993993,38.8373260498],"type":"Point"}
}