{
  "type": "Feature",
  "properties": {
    "addr:full":"Rua Progreso, 8 Mondo\u00f1edo Lugo 27740",
    "addr:housenumber":"8",
    "addr:postcode":"27740",
    "addr:street":"Rua Progreso",
    "iso:country":"ES",
    "sg:address":"Rua Progreso, 8",
    "sg:city":"Mondo\u00f1edo",
    "sg:orig_category":"Panader\u00cdas, Panader\u00cdas",
    "sg:phone":"+34 982 52 11 00",
    "sg:postcode":"27740",
    "sg:province":"Lugo",
    "wof:name":"Ares Alvarez Covadonga",
    "wof:placetype":"venue"
},
  "geometry": {"coordinates":[-7.3646025658,43.4296913147],"type":"Point"}
}