{
  "type": "Feature",
  "properties": {
    "addr:full":"Pase Castellana, 92 Madrid Madrid 28046",
    "addr:housenumber":"92",
    "addr:postcode":"madrid;28046",
    "addr:street":"Castellana",
    "iso:country":"ES",
    "sg:address":"Pase Castellana, 92",
    "sg:city":"Madrid",
    "sg:orig_category":"Asesor\u00cda Fiscal Y Jur\u00cddica",
    "sg:phone":"+34 914 11 31 07",
    "sg:postcode":"28046",
    "sg:province":"Madrid",
    "wof:name":"Baker & Mckenzie Abogados Madrid S.l.",
    "wof:placetype":"venue"
},
  "geometry": {"coordinates":[-3.691116333,40.4432411194],"type":"Point"}
}