{
  "type": "Feature",
  "properties": {
    "addr:full":"Ctra. Sevilla, Km. 0048,0 Sta Olalla Cala Huelva 21260",
    "addr:postcode":"21260",
    "addr:street":"Ctra. Sevilla Km. 0048,0 Sta Olalla Cala",
    "iso:country":"ES",
    "sg:address":"Ctra. Sevilla, Km. 0048,0",
    "sg:city":"Sta Olalla Cala",
    "sg:orig_category":"Explotaci\u00d3n De Bosques",
    "sg:phone":"+34 959 50 70 49",
    "sg:postcode":"21260",
    "sg:province":"Huelva",
    "wof:name":"Ludeke Welzel Ernestine",
    "wof:placetype":"venue"
},
  "geometry": {"coordinates":[-6.2301287651,37.9081115723],"type":"Point"}
}