{
  "type": "Feature",
  "properties": {
    "iso:country":"ES",
    "sg:address":"Av. El Orrin, S/n",
    "sg:city":"San Antonio",
    "sg:orig_category":"Cerrajer\u00cda, Ferrallista",
    "sg:phone":"+34 985 71 06 24",
    "sg:postcode":"33539",
    "sg:province":"Asturias",
    "wof:name":"Aladro Gonzalez Jose Manuel",
    "wof:placetype":"venue"
},
  "geometry": {"coordinates":[-5.6046509743,43.506477356],"type":"Point"}
}