{
  "type": "Feature",
  "properties": {
    "addr:full":"Avda Touroperador Finnmatkat, 9 Campo Internacional Las Palmas 35100",
    "addr:housenumber":"9",
    "addr:postcode":"35100",
    "addr:street":"Avda Touroperador Finnmatkat",
    "iso:country":"ES",
    "sg:address":"Avda Touroperador Finnmatkat, 9",
    "sg:city":"Campo Internacional",
    "sg:orig_category":"Abogados",
    "sg:phone":"+34 928 76 38 80",
    "sg:postcode":"35100",
    "sg:province":"Las Palmas",
    "wof:name":"Heymanns  Hans Gunter",
    "wof:placetype":"venue"
},
  "geometry": {"coordinates":[-15.4397096634,28.1302204132],"type":"Point"}
}