{
  "type": "Feature",
  "properties": {
    "addr:full":"Pase Zorrilla, 105 Valladolid Valladolid 47008",
    "addr:housenumber":"105",
    "addr:postcode":"47008",
    "addr:street":"Zorrilla",
    "iso:country":"ES",
    "sg:address":"Pase Zorrilla, 105",
    "sg:city":"Valladolid",
    "sg:orig_category":"Reposter\u00cdas",
    "sg:phone":"+34 983 47 90 09",
    "sg:postcode":"47008",
    "sg:province":"Valladolid",
    "wof:name":"Martinez Ballesteros Maria Del Carmen",
    "wof:placetype":"venue"
},
  "geometry": {"coordinates":[-4.7415690422,41.6295814514],"type":"Point"}
}