{
  "type": "Feature",
  "properties": {
    "addr:full":"Afueras, S/n Sa Pobla Islas Baleares 07420",
    "addr:postcode":"07420",
    "addr:street":"Afueras S / N",
    "iso:country":"ES",
    "sg:address":"Afueras, S/n",
    "sg:city":"Sa Pobla",
    "sg:orig_category":"Colchones (fabricaci\u00d3n, Al Por Mayor, Al Por Menor)",
    "sg:phone":"+34 971 54 40 00",
    "sg:postcode":"07420",
    "sg:province":"Islas Baleares",
    "wof:name":"Amorini Internacional S.l.",
    "wof:placetype":"venue"
},
  "geometry": {"coordinates":[3.0275802612,39.7876853943],"type":"Point"}
}