{
  "type": "Feature",
  "properties": {
    "addr:full":"Avda Autonomia Aragonesa, S/n Calanda Teruel 44570",
    "addr:housenumber":"s",
    "addr:postcode":"44570",
    "addr:street":"Avda Autonomia Aragonesa;/ N",
    "iso:country":"ES",
    "sg:address":"Avda Autonomia Aragonesa, S/n",
    "sg:city":"Calanda",
    "sg:orig_category":"Asesor\u00cda De Formaci\u00d3n Y Gesti\u00d3n De Personal",
    "sg:phone":"+34 978 84 66 75",
    "sg:postcode":"44570",
    "sg:province":"Teruel",
    "wof:name":"Maria Pilar Jubierre S.l.",
    "wof:placetype":"venue"
},
  "geometry": {"coordinates":[-0.2323540002,40.9430961609],"type":"Point"}
}