{
  "type": "Feature",
  "properties": {
    "addr:full":"Calle de Pechuan, 1 Madrid Madrid 28002",
    "addr:housenumber":"1",
    "addr:postcode":"28002",
    "addr:street":"Calle De Pechuan",
    "iso:country":"ES",
    "sg:address":"Calle de Pechuan, 1",
    "sg:city":"Madrid",
    "sg:orig_category":"Conservas De Pescados Y Salazones Mar\u00cdtimos (fabricaci\u00d3n, Al Por Mayor)",
    "sg:phone":"+34 915 61 24 54",
    "sg:postcode":"28002",
    "sg:province":"Madrid",
    "wof:name":"R Cable Y Telecomunicaciones Galicia S.a.",
    "wof:placetype":"venue"
},
  "geometry": {"coordinates":[-3.677587986,40.4442367554],"type":"Point"}
}