{
  "type": "Feature",
  "properties": {
    "addr:full":"Los Campones, 2 Pravia Asturias 33120",
    "addr:housenumber":"2",
    "addr:postcode":"33120",
    "addr:street":"Campones",
    "iso:country":"ES",
    "sg:address":"Los Campones, 2",
    "sg:city":"Pravia",
    "sg:orig_category":"Hormigonados",
    "sg:phone":"+34 985 82 05 88",
    "sg:postcode":"33120",
    "sg:province":"Asturias",
    "wof:name":"Hormigones De Pravia S.l.",
    "wof:placetype":"venue"
},
  "geometry": {"coordinates":[-6.1117367744,43.4881896973],"type":"Point"}
}