{
  "type": "Feature",
  "properties": {
    "iso:country":"ES",
    "sg:address":"Calle de Fernandez De Los Rios, 67",
    "sg:city":"Madrid",
    "sg:orig_category":"Doctores En Medicina",
    "sg:phone":"+34 915 44 32 69",
    "sg:postcode":"28015",
    "sg:province":"Madrid",
    "wof:name":"Garcia Contreras Enrique",
    "wof:placetype":"venue"
},
  "geometry": {"coordinates":[-3.713603735,40.4353179932],"type":"Point"}
}