{
  "type": "Feature",
  "properties": {
    "addr:full":"Calle de Foglietti, 41 Alacant Alicante 03007",
    "addr:housenumber":"41",
    "addr:postcode":"03007",
    "addr:street":"Calle De Foglietti",
    "iso:country":"ES",
    "sg:address":"Calle de Foglietti, 41",
    "sg:city":"Alacant",
    "sg:orig_category":"Abogados",
    "sg:phone":"+34 965 11 20 41",
    "sg:postcode":"03007",
    "sg:province":"Alicante",
    "wof:name":"Frade Sanchez Maria Teresa",
    "wof:placetype":"venue"
},
  "geometry": {"coordinates":[-0.5001024008,38.3406105042],"type":"Point"}
}