{
  "type": "Feature",
  "properties": {
    "iso:country":"ES",
    "sg:address":"Plaz Juan Xxiii, 2",
    "sg:city":"Arrigorriaga",
    "sg:orig_category":"Grafistas",
    "sg:phone":"+34 946 71 32 00",
    "sg:postcode":"48480",
    "sg:province":"Vizcaya",
    "wof:name":"Copisteria Di-da",
    "wof:placetype":"venue"
},
  "geometry": {"coordinates":[-2.8866000175,43.2074356079],"type":"Point"}
}