{
  "type": "Feature",
  "properties": {
    "iso:country":"ES",
    "sg:address":"Calle de Azcona, 33",
    "sg:city":"Madrid",
    "sg:orig_category":"Tiendas De Grano, Frutas Y Legumbres Secas (al Por Menor)",
    "sg:phone":"+34 913 56 60 58",
    "sg:postcode":"28028",
    "sg:province":"Madrid",
    "wof:name":"Bo\u00f1ar S.l.",
    "wof:placetype":"venue"
},
  "geometry": {"coordinates":[-3.6681544781,40.4348983765],"type":"Point"}
}