{
  "type": "Feature",
  "properties": {
    "iso:country":"ES",
    "sg:address":"Calle de Hilarion Eslava, 15",
    "sg:city":"Madrid",
    "sg:orig_category":"Ropa Para Se\u00d1oras (al Por Menor)",
    "sg:phone":"+34 915 43 36 01",
    "sg:postcode":"28015",
    "sg:province":"Madrid",
    "wof:name":"Momoyo S.l.",
    "wof:placetype":"venue"
},
  "geometry": {"coordinates":[-3.7169458866,40.4333992004],"type":"Point"}
}