{
  "type": "Feature",
  "properties": {
    "iso:country":"ES",
    "sg:address":"Calle de Dato Iradier, 20",
    "sg:city":"Alacant",
    "sg:orig_category":"Peluquer\u00cdas, Peluquer\u00cda Mixta",
    "sg:phone":"+34 965 21 22 24",
    "sg:postcode":"03012",
    "sg:province":"Alicante",
    "wof:name":"Guzzardo  Giuseppe",
    "wof:placetype":"venue"
},
  "geometry": {"coordinates":[-0.4795410931,38.3566017151],"type":"Point"}
}