{
  "type": "Feature",
  "properties": {
    "iso:country":"ES",
    "sg:address":"Avda Villarreal, 13",
    "sg:city":"Olivenza",
    "sg:orig_category":"Centros De Educaci\u00d3n Especial",
    "sg:phone":"+34 924 49 25 22",
    "sg:postcode":"06100",
    "sg:province":"Badajoz",
    "wof:name":"Aprosuba 14",
    "wof:placetype":"venue"
},
  "geometry": {"coordinates":[-7.1054272652,38.6837539673],"type":"Point"}
}