{
  "type": "Feature",
  "properties": {
    "addr:full":"Rua Diaz De Rabago, 24 Pobra Do Carami\u00e7al La Coru\u00f1a 15940",
    "addr:housenumber":"24",
    "addr:postcode":"15940",
    "addr:street":"Rua Diaz De Rabago;Corun\u0303A",
    "iso:country":"ES",
    "sg:address":"Rua Diaz De Rabago, 24",
    "sg:city":"Pobra Do Carami\u00e7al",
    "sg:orig_category":"M\u00c9dicos: Pediatr\u00cda. Enfermedades De Los Ni\u00d1os",
    "sg:phone":"+34 981 83 19 54",
    "sg:postcode":"15940",
    "sg:province":"La Coru\u00f1a",
    "wof:name":"Monteagudo Campos Jose Luis",
    "wof:placetype":"venue"
},
  "geometry": {"coordinates":[-8.9376535416,42.6081085205],"type":"Point"}
}