{
  "type": "Feature",
  "properties": {
    "addr:full":"Calle de Camino Del Campillo, 6 Ciudad Real Ciudad Real 13002",
    "addr:housenumber":"6",
    "addr:postcode":"13002",
    "addr:street":"Calle De Camino Del Campillo",
    "iso:country":"ES",
    "sg:address":"Calle de Camino Del Campillo, 6",
    "sg:city":"Ciudad Real",
    "sg:orig_category":"Agencias Y Agentes Comerciales, Representantes",
    "sg:phone":"+34 926 21 73 56",
    "sg:postcode":"13002",
    "sg:province":"Ciudad Real",
    "wof:name":"Fernandez Barahona Francisco Javier",
    "wof:placetype":"venue"
},
  "geometry": {"coordinates":[-3.9377791882,38.985584259],"type":"Point"}
}