{
  "type": "Feature",
  "properties": {
    "iso:country":"ES",
    "sg:address":"Carrer de Pi I Margall, 57",
    "sg:city":"Terrassa",
    "sg:orig_category":"Veh\u00cdculos De Ocasi\u00d3n",
    "sg:phone":"+34 937 80 82 68",
    "sg:postcode":"08224",
    "sg:province":"Barcelona",
    "wof:name":"Gomez Garcia Jorge",
    "wof:placetype":"venue"
},
  "geometry": {"coordinates":[2.0033299923,41.5610542297],"type":"Point"}
}