{
  "type": "Feature",
  "properties": {
    "iso:country":"ES",
    "sg:address":"Carretera De Baza, S/n",
    "sg:city":"Pozo Alcon",
    "sg:orig_category":"Mec\u00c1nico Del Autom\u00d3vil",
    "sg:phone":"+34 953 73 82 24",
    "sg:postcode":"23485",
    "sg:province":"Ja\u00e9n",
    "wof:name":"Docampo Otero Manuel",
    "wof:placetype":"venue"
},
  "geometry": {"coordinates":[-2.9372200966,37.702495575],"type":"Point"}
}