{
  "type": "Feature",
  "properties": {
    "iso:country":"ES",
    "sg:address":"Calle de Nueva Travesia Buenavista, 11",
    "sg:city":"Coru\u00d1a",
    "sg:orig_category":"Agencias Y Agentes Comerciales, Representantes",
    "sg:phone":"+34 981 28 66 47",
    "sg:postcode":"15006",
    "sg:province":"La Coru\u00f1a",
    "wof:name":"Fornis Harguindey Angel Manuel",
    "wof:placetype":"venue"
},
  "geometry": {"coordinates":[-8.3886547089,43.3519973755],"type":"Point"}
}