{
  "type": "Feature",
  "properties": {
    "addr:full":"Calle de Sanchez Pacheco, 39 Madrid Madrid 28002",
    "addr:housenumber":"39",
    "addr:postcode":"madrid;28002",
    "addr:street":"Calle De Sanchez Pacheco",
    "iso:country":"ES",
    "sg:address":"Calle de Sanchez Pacheco, 39",
    "sg:city":"Madrid",
    "sg:orig_category":"Colchones (fabricaci\u00d3n, Al Por Mayor, Al Por Menor)",
    "sg:phone":"+34 914 15 90 19",
    "sg:postcode":"28002",
    "sg:province":"Madrid",
    "wof:name":"Sebastian Sebastian Angel",
    "wof:placetype":"venue"
},
  "geometry": {"coordinates":[-3.6740300655,40.447353363],"type":"Point"}
}