{
  "type": "Feature",
  "properties": {
    "iso:country":"ES",
    "sg:address":"Carrer de Maladeta, 24",
    "sg:city":"Hospitalet Llobregat",
    "sg:orig_category":"Comerciantes Al Por Mayor De Vinos, Licores Y Alcoholes",
    "sg:phone":"+34 934 37 35 77",
    "sg:postcode":"08906",
    "sg:province":"Barcelona",
    "wof:name":"Vins I Licors Monfort S.l.",
    "wof:placetype":"venue"
},
  "geometry": {"coordinates":[2.1007919312,41.3729362488],"type":"Point"}
}