{
  "type": "Feature",
  "properties": {
    "addr:full":"Calle de Feijoo, 7 Madrid Madrid 28010",
    "addr:housenumber":"7",
    "addr:postcode":"madrid;28010",
    "addr:street":"Calle De Feijoo",
    "iso:country":"ES",
    "sg:address":"Calle de Feijoo, 7",
    "sg:city":"Madrid",
    "sg:orig_category":"Agencias De Viajes",
    "sg:phone":"+34 914 47 14 33",
    "sg:postcode":"28010",
    "sg:province":"Madrid",
    "sg:website":"www.taranna.com",
    "wof:name":"Viajes Tembo 2000 S.l.",
    "wof:placetype":"venue"
},
  "geometry": {"coordinates":[-3.7032189369,40.4349784851],"type":"Point"}
}