{
  "type": "Feature",
  "properties": {
    "addr:full":"Calle de Arces, 2 Viana Navarra 31230",
    "addr:housenumber":"2",
    "addr:postcode":"31230",
    "addr:street":"Calle De Arces",
    "iso:country":"ES",
    "sg:address":"Calle de Arces, 2",
    "sg:city":"Viana",
    "sg:orig_category":"Promotores Constructores",
    "sg:phone":"+34 948 64 57 77",
    "sg:postcode":"31230",
    "sg:province":"Navarra",
    "wof:name":"Construcciones Sainz Arpon S.l.",
    "wof:placetype":"venue"
},
  "geometry": {"coordinates":[-2.3746643066,42.5157737732],"type":"Point"}
}