{
  "type": "Feature",
  "properties": {
    "iso:country":"ES",
    "sg:address":"Calle de Doctor Cerrada, 25",
    "sg:city":"Zaragoza",
    "sg:orig_category":"Agencias Y Agentes Comerciales, Representantes",
    "sg:phone":"+34 976 21 73 83",
    "sg:postcode":"50005",
    "sg:province":"Zaragoza",
    "wof:name":"Arrieta Navarro Raquel",
    "wof:placetype":"venue"
},
  "geometry": {"coordinates":[-0.8898484111,41.6463356018],"type":"Point"}
}