{
  "type": "Feature",
  "properties": {
    "iso:country":"ES",
    "sg:address":"Prospes(san Sadurni\u00f1o), S/n",
    "sg:city":"Prospes",
    "sg:orig_category":"Cooperativas Agr\u00cdcolas",
    "sg:phone":"+34 981 49 01 53",
    "sg:postcode":"15560",
    "sg:province":"La Coru\u00f1a",
    "wof:name":"Lopez Fernandez Cesar Antonio",
    "wof:placetype":"venue"
},
  "geometry": {"coordinates":[-8.0724773407,43.5319709778],"type":"Point"}
}