{
  "type": "Feature",
  "properties": {
    "addr:full":"Calle de Sant Lloren\u00c7, 16 Alberic Valencia 46260",
    "addr:housenumber":"16",
    "addr:postcode":"46260",
    "addr:street":"Calle De Sant Llorenc\u0327",
    "iso:country":"ES",
    "sg:address":"Calle de Sant Lloren\u00c7, 16",
    "sg:city":"Alberic",
    "sg:orig_category":"Carnicer\u00cdas, Carnicer\u00cdas",
    "sg:phone":"+34 962 44 14 48",
    "sg:postcode":"46260",
    "sg:province":"Valencia",
    "wof:name":"Fiambres Pavypoll S.l.",
    "wof:placetype":"venue"
},
  "geometry": {"coordinates":[-0.5188750029,39.1167755127],"type":"Point"}
}