{
  "type": "Feature",
  "properties": {
    "addr:full":"Rbla Sant Esteve (de), S/n Ripollet Barcelona 08291",
    "addr:postcode":"08291",
    "addr:street":"Rbla Sant Esteve De S / N",
    "iso:country":"ES",
    "sg:address":"Rbla Sant Esteve (de), S/n",
    "sg:city":"Ripollet",
    "sg:orig_category":"Perfumer\u00cda (al Por Menor)",
    "sg:phone":"+34 936 91 76 53",
    "sg:postcode":"08291",
    "sg:province":"Barcelona",
    "wof:name":"Bouquet Jimenez Julia",
    "wof:placetype":"venue"
},
  "geometry": {"coordinates":[2.1574640274,41.5002098083],"type":"Point"}
}