{
  "type": "Feature",
  "properties": {
    "iso:country":"ES",
    "sg:address":"Calle de Jose Ponte, 6",
    "sg:city":"Perdoma",
    "sg:orig_category":"Empresas De Pintura Y Revestimientos",
    "sg:phone":"+34 922 30 94 67",
    "sg:postcode":"38315",
    "sg:province":"Santa Cruz De Tenerife",
    "wof:name":"Bethencourt Lorenzo Henry",
    "wof:placetype":"venue"
},
  "geometry": {"coordinates":[-16.5055618286,28.3659114838],"type":"Point"}
}