{
  "type": "Feature",
  "properties": {
    "addr:full":"Carrer de Amilcar, 195 Barcelona Barcelona 08032",
    "addr:housenumber":"195",
    "addr:postcode":"08032",
    "addr:street":"Carrer De Amilcar",
    "iso:country":"ES",
    "sg:address":"Carrer de Amilcar, 195",
    "sg:city":"Barcelona",
    "sg:orig_category":"Ingeniero",
    "sg:phone":"+34 934 55 26 76",
    "sg:postcode":"08032",
    "sg:province":"Barcelona",
    "wof:name":"Tecnicas Ferreres S.l.",
    "wof:placetype":"venue"
},
  "geometry": {"coordinates":[2.1729969978,41.4225997925],"type":"Point"}
}