{
  "type": "Feature",
  "properties": {
    "iso:country":"ES",
    "sg:address":"Carrer de Sant Jordi, 3",
    "sg:city":"Mollet Valles",
    "sg:orig_category":"Inmobiliaria (agencias)",
    "sg:phone":"+34 935 70 49 19",
    "sg:postcode":"08100",
    "sg:province":"Barcelona",
    "sg:website":"www.mirmaragi.es.vg",
    "wof:name":"Grupo Mirmar Agi Sl",
    "wof:placetype":"venue"
},
  "geometry": {"coordinates":[2.209239006,41.5380363464],"type":"Point"}
}