{
  "type": "Feature",
  "properties": {
    "addr:full":"Calle de Manfrio, 23 Torredelcampo Ja\u00e9n 23640",
    "addr:housenumber":"23",
    "addr:postcode":"23640",
    "addr:street":"Calle De Manfrio;Jae\u0301N",
    "iso:country":"ES",
    "sg:address":"Calle de Manfrio, 23",
    "sg:city":"Torredelcampo",
    "sg:orig_category":"Empresas De Carpinter\u00cda Met\u00c1lica",
    "sg:phone":"+34 953 56 88 03",
    "sg:postcode":"23640",
    "sg:province":"Ja\u00e9n",
    "wof:name":"Salvador Arroyo Zafra Y Otro Comunidad De Bienes",
    "wof:placetype":"venue"
},
  "geometry": {"coordinates":[-3.8993589878,37.7761001587],"type":"Point"}
}