{
  "type": "Feature",
  "properties": {
    "iso:country":"ES",
    "sg:address":"Pl Montserrat Roig, 10",
    "sg:city":"Mataro",
    "sg:orig_category":"Inform\u00c1tica (estudios, Servicios, Asesor\u00cda, Formaci\u00d3n)",
    "sg:phone":"+34 937 41 52 50",
    "sg:postcode":"08304",
    "sg:province":"Barcelona",
    "wof:name":"Sala Assessor Informatic S.l.",
    "wof:placetype":"venue"
},
  "geometry": {"coordinates":[2.4413220882,41.5540313721],"type":"Point"}
}