{
  "type": "Feature",
  "properties": {
    "iso:country":"ES",
    "sg:address":"Avda Regne De Valencia, 82",
    "sg:city":"Valencia",
    "sg:orig_category":"M\u00c9dicos: Neurolog\u00cda",
    "sg:phone":"+34 963 73 78 68",
    "sg:postcode":"46005",
    "sg:province":"Valencia",
    "wof:name":"Palao Esteve Salvador",
    "wof:placetype":"venue"
},
  "geometry": {"coordinates":[-0.3637430072,39.4626197815],"type":"Point"}
}