{
  "type": "Feature",
  "properties": {
    "iso:country":"ES",
    "sg:address":"Barr Pedriscos (los), 6",
    "sg:city":"Somahoz",
    "sg:orig_category":"Promotores Constructores",
    "sg:phone":"+34 942 84 22 81",
    "sg:postcode":"39400",
    "sg:province":"Cantabria",
    "wof:name":"Obras Y Proyectos Trebol S.l.",
    "wof:placetype":"venue"
},
  "geometry": {"coordinates":[-4.0661587715,43.2497444153],"type":"Point"}
}