{
  "type": "Feature",
  "properties": {
    "iso:country":"ES",
    "sg:address":"Av Primavera, 5",
    "sg:city":"Cerdanyola Valles",
    "sg:orig_category":"M\u00c9dicos: Pediatr\u00cda. Enfermedades De Los Ni\u00d1os",
    "sg:phone":"+34 936 92 26 37",
    "sg:postcode":"08290",
    "sg:province":"Barcelona",
    "wof:name":"Moyano Montoro Cecilio",
    "wof:placetype":"venue"
},
  "geometry": {"coordinates":[2.1468639374,41.4921264648],"type":"Point"}
}