{
  "type": "Feature",
  "properties": {
    "addr:full":"Calle de Budapest, 131 Torreciega Murcia 30391",
    "addr:housenumber":"131",
    "addr:postcode":"30391",
    "addr:street":"Calle De Budapest",
    "iso:country":"ES",
    "sg:address":"Calle de Budapest, 131",
    "sg:city":"Torreciega",
    "sg:orig_category":"Agencias Y Asesores De Publicidad",
    "sg:phone":"+34 968 12 01 96",
    "sg:postcode":"30391",
    "sg:province":"Murcia",
    "sg:website":"www.berbois.com",
    "wof:name":"Berbois S.l.",
    "wof:placetype":"venue"
},
  "geometry": {"coordinates":[-1.0487240553,37.6523857117],"type":"Point"}
}