{
  "type": "Feature",
  "properties": {
    "addr:full":"Av Puig I Cadafalch, 180 Mataro Barcelona 08303",
    "addr:housenumber":"180",
    "addr:postcode":"08303",
    "addr:street":"Av Puig;Cadafalch",
    "iso:country":"ES",
    "sg:address":"Av Puig I Cadafalch, 180",
    "sg:city":"Mataro",
    "sg:orig_category":"Hilaturas, Hilos Y Actividades Relacionadas",
    "sg:phone":"+34 937 57 04 75",
    "sg:postcode":"08303",
    "sg:province":"Barcelona",
    "wof:name":"Carrillo Llauge Fernando",
    "wof:placetype":"venue"
},
  "geometry": {"coordinates":[2.4265899658,41.5404243469],"type":"Point"}
}