{
  "type": "Feature",
  "properties": {
    "iso:country":"ES",
    "sg:address":"Rua Alfonso Senra, 49",
    "sg:city":"Ordes",
    "sg:orig_category":"Ense\u00d1anza Secundaria: Colegios Y Escuelas Privadas",
    "sg:phone":"+34 981 68 08 35",
    "sg:postcode":"15680",
    "sg:province":"La Coru\u00f1a",
    "wof:name":"Sanchez Pampin Cesar",
    "wof:placetype":"venue"
},
  "geometry": {"coordinates":[-8.4068393707,43.0780982971],"type":"Point"}
}