{
  "type": "Feature",
  "properties": {
    "iso:country":"ES",
    "sg:address":"Avda Basagoiti, 57",
    "sg:city":"Algorta",
    "sg:orig_category":"Ropa Para Se\u00d1oras (al Por Menor)",
    "sg:phone":"+34 944 60 94 55",
    "sg:postcode":"48991",
    "sg:province":"Vizcaya",
    "wof:name":"Velarde Oscariz Maria Carmen",
    "wof:placetype":"venue"
},
  "geometry": {"coordinates":[-3.0123140812,43.3494720459],"type":"Point"}
}