{
  "type": "Feature",
  "properties": {
    "addr:full":"C/ Joan Lliteras, 5 Manacor Islas Baleares 07500",
    "addr:housenumber":"5",
    "addr:postcode":"07500",
    "addr:street":"C / Joan Lliteras",
    "iso:country":"ES",
    "sg:address":"C/ Joan Lliteras, 5",
    "sg:city":"Manacor",
    "sg:orig_category":"Asociaciones Y Clubs Deportivos",
    "sg:phone":"+34 971 55 02 18",
    "sg:postcode":"07500",
    "sg:province":"Islas Baleares",
    "wof:name":"Master Tenda D'sports S.l.",
    "wof:placetype":"venue"
},
  "geometry": {"coordinates":[3.2090899944,39.5698127747],"type":"Point"}
}