{
  "type": "Feature",
  "properties": {
    "iso:country":"ES",
    "sg:address":"Finc Casa El Quinto, S/n",
    "sg:city":"Estacion Urda Peleches",
    "sg:orig_category":"Producci\u00d3n, Venta De Productos De Agricultura Biol\u00d3gica",
    "sg:phone":"+34 925 59 40 52",
    "sg:postcode":"45470",
    "sg:province":"Toledo",
    "wof:name":"Explotacion Agricola Ganadera Edmundo Alonso E Hijos S.a.",
    "wof:placetype":"venue"
},
  "geometry": {"coordinates":[-3.8697290421,39.5791702271],"type":"Point"}
}