{
  "type": "Feature",
  "properties": {
    "iso:country":"ES",
    "sg:address":"Calle de Sarria, 26",
    "sg:city":"Madrid",
    "sg:orig_category":"Ebanister\u00cda",
    "sg:phone":"+34 913 73 28 37",
    "sg:postcode":"28029",
    "sg:province":"Madrid",
    "wof:name":"Rodriguez Dominguez Manuel",
    "wof:placetype":"venue"
},
  "geometry": {"coordinates":[-3.714124918,40.4746322632],"type":"Point"}
}