{
  "type": "Feature",
  "properties": {
    "iso:country":"ES",
    "sg:address":"Trav De Gracia, 423",
    "sg:city":"Barcelona",
    "sg:orig_category":"Molduras, Junquillos, Listones Y Molduras Perforadas",
    "sg:phone":"+34 934 36 00 48",
    "sg:postcode":"08025",
    "sg:province":"Barcelona",
    "wof:name":"Sociedad Cafe Villar S.l",
    "wof:placetype":"venue"
},
  "geometry": {"coordinates":[2.1720509529,41.4105377197],"type":"Point"}
}