{
  "type": "Feature",
  "properties": {
    "addr:full":"Calle de Calvario-la Orotava (el), 51 Orotava Santa Cruz De Tenerife 38300",
    "addr:postcode":"38300",
    "addr:street":"Calle De Calvario-La;El;Orotava",
    "iso:country":"ES",
    "sg:address":"Calle de Calvario-la Orotava (el), 51",
    "sg:city":"Orotava",
    "sg:orig_category":"Peluquer\u00cdas, Peluquer\u00cda Mixta",
    "sg:phone":"+34 922 33 09 20",
    "sg:postcode":"38300",
    "sg:province":"Santa Cruz De Tenerife",
    "wof:name":"Hernandez Paez Maria Candelaria",
    "wof:placetype":"venue"
},
  "geometry": {"coordinates":[-16.5208396912,28.3942623138],"type":"Point"}
}