{
  "type": "Feature",
  "properties": {
    "iso:country":"ES",
    "sg:address":"Calle de Alcazar, 2",
    "sg:city":"Valderas",
    "sg:orig_category":"Cristaler\u00cdas",
    "sg:phone":"+34 987 76 24 45",
    "sg:postcode":"24220",
    "sg:province":"Le\u00f3n",
    "wof:name":"Garcia Rodriguez Alberto Antonio",
    "wof:placetype":"venue"
},
  "geometry": {"coordinates":[-5.4462752342,42.0793838501],"type":"Point"}
}