{
  "type": "Feature",
  "properties": {
    "iso:country":"ES",
    "sg:address":"Calle de Reyes Catolicos, 14",
    "sg:city":"Donostia-san Sebastian",
    "sg:orig_category":"Asociaciones Humanitarias, De Cooperaci\u00d3n, De Acci\u00d3n Social",
    "sg:phone":"+34 943 47 36 72",
    "sg:postcode":"20006",
    "sg:province":"Guip\u00f9zcoa",
    "wof:name":"Union De Sordos De Guipuzcoa",
    "wof:placetype":"venue"
},
  "geometry": {"coordinates":[-1.980659008,43.3151397705],"type":"Point"}
}