{
  "type": "Feature",
  "properties": {
    "addr:full":"Cno Sierra, 1 Redovan Alicante 03370",
    "addr:housenumber":"1",
    "addr:postcode":"03370",
    "addr:street":"Cno Sierra;Alicante",
    "iso:country":"ES",
    "sg:address":"Cno Sierra, 1",
    "sg:city":"Redovan",
    "sg:orig_category":"Construcciones Met\u00c1licas",
    "sg:phone":"+34 966 75 53 73",
    "sg:postcode":"03370",
    "sg:province":"Alicante",
    "wof:name":"Metalisteria Redinox S.l.",
    "wof:placetype":"venue"
},
  "geometry": {"coordinates":[-0.9054669738,38.1110725403],"type":"Point"}
}