{
  "type": "Feature",
  "properties": {
    "addr:full":"Poli Poligono Uai-4, 9 Arriandi Vizcaya 48215",
    "addr:housenumber":"9",
    "addr:postcode":"48215",
    "addr:street":"Poligono Uai-4",
    "iso:country":"ES",
    "sg:address":"Poli Poligono Uai-4, 9",
    "sg:city":"Arriandi",
    "sg:orig_category":"Metalurgia: Maquinaria Y Equipos",
    "sg:phone":"+34 946 81 70 51",
    "sg:postcode":"48215",
    "sg:province":"Vizcaya",
    "wof:name":"Doliva Gerhardt Ricardo",
    "wof:placetype":"venue"
},
  "geometry": {"coordinates":[-2.631608963,43.1760597229],"type":"Point"}
}