{
  "type": "Feature",
  "properties": {
    "iso:country":"ES",
    "sg:address":"Avda Pilar, 40",
    "sg:city":"Don Benito",
    "sg:orig_category":"Ingenier\u00cda, Centros De Estudios (diversos)",
    "sg:phone":"+34 924 81 09 25",
    "sg:postcode":"06400",
    "sg:province":"Badajoz",
    "wof:name":"Comercial Ediciones S.m. S.a.",
    "wof:placetype":"venue"
},
  "geometry": {"coordinates":[-5.8733639717,38.9556503296],"type":"Point"}
}