{
  "type": "Feature",
  "properties": {
    "addr:full":"Pl Caserna, S/n Granollers Barcelona 08401",
    "addr:housenumber":"s",
    "addr:postcode":"08401",
    "addr:street":"Pl Caserna;/ N",
    "iso:country":"ES",
    "sg:address":"Pl Caserna, S/n",
    "sg:city":"Granollers",
    "sg:orig_category":"Carnicer\u00cdas, Carnicer\u00cdas",
    "sg:phone":"+34 938 70 24 29",
    "sg:postcode":"08401",
    "sg:province":"Barcelona",
    "wof:name":"Salgado Enriquez Oscar",
    "wof:placetype":"venue"
},
  "geometry": {"coordinates":[2.2860100269,41.6089935303],"type":"Point"}
}