{
  "type": "Feature",
  "properties": {
    "iso:country":"ES",
    "sg:address":"Calle de Angeles (los), 48",
    "sg:city":"Muela",
    "sg:orig_category":"Maquinaria Para Industrias Diversas",
    "sg:phone":"+34 976 14 47 65",
    "sg:postcode":"50196",
    "sg:province":"Zaragoza",
    "wof:name":"Lubeni Energias S.l.",
    "wof:placetype":"venue"
},
  "geometry": {"coordinates":[-1.0772374868,41.6132545471],"type":"Point"}
}