{
  "type": "Feature",
  "properties": {
    "addr:full":"Calle de Rio Cubas, 6 Santander Cantabria 39004",
    "addr:housenumber":"6",
    "addr:postcode":"39004",
    "addr:street":"Calle De Rio Cubas",
    "iso:country":"ES",
    "sg:address":"Calle de Rio Cubas, 6",
    "sg:city":"Santander",
    "sg:orig_category":"Mec\u00c1nico Del Autom\u00d3vil",
    "sg:phone":"+34 942 27 17 81",
    "sg:postcode":"39004",
    "sg:province":"Cantabria",
    "wof:name":"Gutierrez Sanchez Jose",
    "wof:placetype":"venue"
},
  "geometry": {"coordinates":[-3.7898290157,43.465511322],"type":"Point"}
}