{
  "type": "Feature",
  "properties": {
    "addr:full":"Calle de Antonino Vera, 57 Elda Alicante 03600",
    "addr:housenumber":"57",
    "addr:postcode":"03600",
    "addr:street":"Calle De Antonino Vera",
    "iso:country":"ES",
    "sg:address":"Calle de Antonino Vera, 57",
    "sg:city":"Elda",
    "sg:orig_category":"Abogados",
    "sg:phone":"+34 965 39 35 04",
    "sg:postcode":"03600",
    "sg:province":"Alicante",
    "wof:name":"Deltell Sala Roberto Joaquin",
    "wof:placetype":"venue"
},
  "geometry": {"coordinates":[-0.7916070223,38.4766426086],"type":"Point"}
}