{
  "type": "Feature",
  "properties": {
    "addr:full":"Avda Padre Garcia Tejero, 12 Sevilla Sevilla 41012",
    "addr:housenumber":"12",
    "addr:postcode":"41012",
    "addr:street":"Avda Padre;Tejero",
    "iso:country":"ES",
    "sg:address":"Avda Padre Garcia Tejero, 12",
    "sg:city":"Sevilla",
    "sg:orig_category":"Molduras, Junquillos, Listones Y Molduras Perforadas",
    "sg:phone":"+34 954 23 97 93",
    "sg:postcode":"41012",
    "sg:province":"Sevilla",
    "wof:name":"Pavon Suarez Antonio",
    "wof:placetype":"venue"
},
  "geometry": {"coordinates":[-5.9847998619,37.3562355042],"type":"Point"}
}