{
  "type": "Feature",
  "properties": {
    "addr:full":"Calle de Francisco Silvela, 37 Madrid Madrid 28028",
    "addr:housenumber":"37",
    "addr:postcode":"madrid;28028",
    "addr:street":"Calle De Francisco Silvela",
    "iso:country":"ES",
    "sg:address":"Calle de Francisco Silvela, 37",
    "sg:city":"Madrid",
    "sg:orig_category":"Abogados",
    "sg:phone":"+34 914 01 28 36",
    "sg:postcode":"28028",
    "sg:province":"Madrid",
    "wof:name":"Zubizarreta Samperio Jose Maria",
    "wof:placetype":"venue"
},
  "geometry": {"coordinates":[-3.672137022,40.4319419861],"type":"Point"}
}