{
  "type": "Feature",
  "properties": {
    "iso:country":"ES",
    "sg:address":"Calle de Padilla, 2",
    "sg:city":"Gijon",
    "sg:classifiers":[
        {
            "category":"Government",
            "subcategory":"Post Office",
            "type":"Public Place"
        }
    ],
    "sg:phone":"+34 985 35 22 45",
    "sg:postcode":"33205",
    "sg:province":"Asturias",
    "sg:tags":[
        "de",
        "yoga",
        "clases"
    ],
    "sg:website":"www.www.samyama.com",
    "wof:name":"Samyama S.coop.",
    "wof:placetype":"venue"
},
  "geometry": {"coordinates":[-5.6623220444,43.5394477844],"type":"Point"}
}