{
  "type": "Feature",
  "properties": {
    "addr:full":"De La Luna, 18 Fontanar Guadalajara 19290",
    "addr:housenumber":"18",
    "addr:postcode":"19290",
    "addr:street":"Luna",
    "iso:country":"ES",
    "sg:address":"De La Luna, 18",
    "sg:city":"Fontanar",
    "sg:orig_category":"Carnicer\u00cdas, Carnicer\u00cdas",
    "sg:phone":"+34 949 33 15 10",
    "sg:postcode":"19290",
    "sg:province":"Guadalajara",
    "wof:name":"Nuero Beato Maria Luisa",
    "wof:placetype":"venue"
},
  "geometry": {"coordinates":[-3.17344594,40.7214813232],"type":"Point"}
}