{
  "type": "Feature",
  "properties": {
    "addr:full":"Calle de Fortuny, 9 Ogijares Granada 18151",
    "addr:housenumber":"9",
    "addr:postcode":"18151",
    "addr:street":"Calle De Fortuny",
    "iso:country":"ES",
    "sg:address":"Calle de Fortuny, 9",
    "sg:city":"Ogijares",
    "sg:orig_category":"Agencias Y Agentes Comerciales, Representantes",
    "sg:phone":"+34 958 50 75 21",
    "sg:postcode":"18151",
    "sg:province":"Granada",
    "wof:name":"Munuera Lopez De Hierro Francisco",
    "wof:placetype":"venue"
},
  "geometry": {"coordinates":[-3.6068360806,37.114906311],"type":"Point"}
}