{
  "type": "Feature",
  "properties": {
    "addr:full":"Calle de Arrasate, 47 Donostia-san Sebastian Guip\u00f9zcoa 20005",
    "addr:housenumber":"47",
    "addr:postcode":"20005",
    "addr:street":"Calle De Arrasate",
    "iso:country":"ES",
    "sg:address":"Calle de Arrasate, 47",
    "sg:city":"Donostia-san Sebastian",
    "sg:orig_category":"Centros De Coordinaci\u00d3n",
    "sg:phone":"+34 943 42 97 64",
    "sg:postcode":"20005",
    "sg:province":"Guip\u00f9zcoa",
    "wof:name":"Fernandez Iturbe Isaac",
    "wof:placetype":"venue"
},
  "geometry": {"coordinates":[-1.9842021465,43.3172531128],"type":"Point"}
}