{
  "type": "Feature",
  "properties": {
    "addr:full":"Carrer de Aprestadora, 7 Hospitalet Llobregat Barcelona 08902",
    "addr:housenumber":"7",
    "addr:postcode":"08902",
    "addr:street":"Carrer De Aprestadora",
    "iso:country":"ES",
    "sg:address":"Carrer de Aprestadora, 7",
    "sg:city":"Hospitalet Llobregat",
    "sg:orig_category":"Cajas De Ahorro",
    "sg:phone":"+34 933 32 31 49",
    "sg:postcode":"08902",
    "sg:province":"Barcelona",
    "wof:name":"Caixa D'estalvis I Pensions De Barcelona",
    "wof:placetype":"venue"
},
  "geometry": {"coordinates":[2.1306090355,41.3647842407],"type":"Point"}
}