{
  "type": "Feature",
  "properties": {
    "iso:country":"ES",
    "sg:address":"Los Naranjos Urbanizacion, 15",
    "sg:city":"Gojar",
    "sg:orig_category":"Agencias Y Agentes Comerciales, Representantes",
    "sg:phone":"+34 958 50 82 64",
    "sg:postcode":"18150",
    "sg:province":"Granada",
    "wof:name":"Onorato Gutierrez Jose Luis",
    "wof:placetype":"venue"
},
  "geometry": {"coordinates":[-3.6003830433,37.1112709045],"type":"Point"}
}