{
  "type": "Feature",
  "properties": {
    "addr:full":"Sonnenland, S/n Maspalomas Las Palmas 35100",
    "addr:housenumber":"s / n",
    "addr:postcode":"35100",
    "iso:country":"ES",
    "sg:address":"Sonnenland, S/n",
    "sg:city":"Maspalomas",
    "sg:orig_category":"Agencias De Viajes",
    "sg:phone":"+34 928 14 23 85",
    "sg:postcode":"35100",
    "sg:province":"Las Palmas",
    "wof:name":"Barcelo Destination Services S.l.",
    "wof:placetype":"venue"
},
  "geometry": {"coordinates":[-15.5830888748,27.7700748444],"type":"Point"}
}