{
  "type": "Feature",
  "properties": {
    "iso:country":"ES",
    "sg:address":"Trva Ameztia, 1",
    "sg:city":"Doneztebe",
    "sg:orig_category":"Electrodom\u00c9sticos (al Por Menor)",
    "sg:phone":"+34 948 45 09 25",
    "sg:postcode":"31740",
    "sg:province":"Navarra",
    "wof:name":"Miguelena Ariztegui Francisco Javier",
    "wof:placetype":"venue"
},
  "geometry": {"coordinates":[-1.6707600355,43.1309165955],"type":"Point"}
}