{
  "type": "Feature",
  "properties": {
    "iso:country":"ES",
    "sg:address":"Calle de Do\u00d1a Ana, 27",
    "sg:city":"Iniesta",
    "sg:orig_category":"Reposter\u00cdas",
    "sg:phone":"+34 967 49 00 52",
    "sg:postcode":"16235",
    "sg:province":"Cuenca",
    "wof:name":"Larrey Olivares Jose Miguel",
    "wof:placetype":"venue"
},
  "geometry": {"coordinates":[-1.7498055696,39.4453277588],"type":"Point"}
}