{
  "type": "Feature",
  "properties": {
    "addr:full":"Calle de Juan Fortuny, 1 San Pedro Alcantara M\u00e1laga 29670",
    "addr:housenumber":"1",
    "addr:postcode":"29670",
    "addr:street":"Calle De Juan Fortuny",
    "iso:country":"ES",
    "sg:address":"Calle de Juan Fortuny, 1",
    "sg:city":"San Pedro Alcantara",
    "sg:orig_category":"Psic\u00d3logos",
    "sg:phone":"+34 952 78 62 19",
    "sg:postcode":"29670",
    "sg:province":"M\u00e1laga",
    "wof:name":"Rosa  Abelardo Sixto De La",
    "wof:placetype":"venue"
},
  "geometry": {"coordinates":[-4.9873490334,36.4863357544],"type":"Point"}
}