{
  "type": "Feature",
  "properties": {
    "iso:country":"ES",
    "sg:address":"Calle de Barrio Nuevo, 32",
    "sg:city":"Morcillo",
    "sg:orig_category":"Empresarios",
    "sg:phone":"+34 927 67 15 15",
    "sg:postcode":"10811",
    "sg:province":"C\u00e1ceres",
    "wof:name":"Obras Brau S.l",
    "wof:placetype":"venue"
},
  "geometry": {"coordinates":[-6.3985776901,40.0187721252],"type":"Point"}
}