{
  "type": "Feature",
  "properties": {
    "addr:full":"Calle de Fundidores, 17 Getafe Madrid 28906",
    "addr:housenumber":"17",
    "addr:postcode":"28906",
    "addr:street":"Calle De Fundidores",
    "iso:country":"ES",
    "sg:address":"Calle de Fundidores, 17",
    "sg:city":"Getafe",
    "sg:orig_category":"Agencias Y Agentes Comerciales, Representantes",
    "sg:phone":"+34 916 95 10 12",
    "sg:postcode":"28906",
    "sg:province":"Madrid",
    "wof:name":"Sanchez Garcia Domingo",
    "wof:placetype":"venue"
},
  "geometry": {"coordinates":[-3.7049601078,40.3119239807],"type":"Point"}
}