{
  "type": "Feature",
  "properties": {
    "addr:full":"Calle de Calvario, 69 Olvera C\u00e1diz 11690",
    "addr:housenumber":"69",
    "addr:postcode":"11690",
    "addr:street":"Calle De Calvario;Ca\u0301Diz",
    "iso:country":"ES",
    "sg:address":"Calle de Calvario, 69",
    "sg:city":"Olvera",
    "sg:orig_category":"Farmacias",
    "sg:phone":"+34 956 13 08 23",
    "sg:postcode":"11690",
    "sg:province":"C\u00e1diz",
    "wof:name":"Moron Escolar Rafael",
    "wof:placetype":"venue"
},
  "geometry": {"coordinates":[-5.2605137825,36.9350280762],"type":"Point"}
}