{
  "type": "Feature",
  "properties": {
    "iso:country":"ES",
    "sg:address":"Poli Talluntxe / Talluntze Industrialdea, 1",
    "sg:city":"Noain",
    "sg:orig_category":"Empresas De Limpieza",
    "sg:phone":"+34 948 31 85 62",
    "sg:postcode":"31110",
    "sg:province":"Navarra",
    "sg:website":"www.mainorte.com",
    "wof:name":"Mainorte",
    "wof:placetype":"venue"
},
  "geometry": {"coordinates":[-1.6338239908,42.7598800659],"type":"Point"}
}