{
  "type": "Feature",
  "properties": {
    "addr:full":"Avda Boliches De Los, 44 Fuengirola M\u00e1laga 29640",
    "addr:postcode":"29640",
    "addr:street":"Avda Boliches De Los;Ma\u0301Laga",
    "iso:country":"ES",
    "sg:address":"Avda Boliches De Los, 44",
    "sg:city":"Fuengirola",
    "sg:orig_category":"Cajas De Ahorro",
    "sg:phone":"+34 952 66 70 93",
    "sg:postcode":"29640",
    "sg:province":"M\u00e1laga",
    "wof:name":"Caja De Ahorros Del Mediterraneo",
    "wof:placetype":"venue"
},
  "geometry": {"coordinates":[-4.6139922142,36.553981781],"type":"Point"}
}