{
  "type": "Feature",
  "properties": {
    "addr:full":"Carrer de Murillo, 25 Cornella Llobregat Barcelona 08940",
    "addr:housenumber":"25",
    "addr:postcode":"08940",
    "addr:street":"Carrer De Murillo",
    "iso:country":"ES",
    "sg:address":"Carrer de Murillo, 25",
    "sg:city":"Cornella Llobregat",
    "sg:orig_category":"Contenedores (mercanc\u00cdas)",
    "sg:phone":"+34 933 77 03 61",
    "sg:postcode":"08940",
    "sg:province":"Barcelona",
    "wof:name":"Perea Mu\u00f1oz Joaquin",
    "wof:placetype":"venue"
},
  "geometry": {"coordinates":[2.0679419041,41.3551559448],"type":"Point"}
}