{
  "type": "Feature",
  "properties": {
    "addr:full":"Calle de San Juan, 25 Sangonera Seca Murcia 30835",
    "addr:housenumber":"25",
    "addr:postcode":"30835",
    "addr:street":"Calle De San Juan",
    "iso:country":"ES",
    "sg:address":"Calle de San Juan, 25",
    "sg:city":"Sangonera Seca",
    "sg:orig_category":"Farmacias",
    "sg:phone":"+34 968 80 16 21",
    "sg:postcode":"30835",
    "sg:province":"Murcia",
    "wof:name":"Martinez Garcia Maria Josefa",
    "wof:placetype":"venue"
},
  "geometry": {"coordinates":[-1.2281939983,37.9618148804],"type":"Point"}
}