{
  "type": "Feature",
  "properties": {
    "iso:country":"ES",
    "sg:address":"Carrer de Jaume I, 54",
    "sg:city":"S. Celoni",
    "sg:orig_category":"Electrodom\u00c9sticos (al Por Menor)",
    "sg:phone":"+34 938 67 41 67",
    "sg:postcode":"08470",
    "sg:province":"Barcelona",
    "wof:name":"Martin Martin Maria Consuelo",
    "wof:placetype":"venue"
},
  "geometry": {"coordinates":[2.4968349934,41.6928901672],"type":"Point"}
}