{
  "type": "Feature",
  "properties": {
    "addr:full":"Calle de Skal, S/n Torremolinos M\u00e1laga 29620",
    "addr:housenumber":"s / n",
    "addr:postcode":"29620",
    "addr:street":"Calle De Skal;Ma\u0301Laga",
    "iso:country":"ES",
    "sg:address":"Calle de Skal, S/n",
    "sg:city":"Torremolinos",
    "sg:orig_category":"Aparcamientos (infraestructuras, Accesorios)",
    "sg:phone":"+34 952 38 96 50",
    "sg:postcode":"29620",
    "sg:province":"M\u00e1laga",
    "wof:name":"Essadaka S.l.",
    "wof:placetype":"venue"
},
  "geometry": {"coordinates":[-4.4990391731,36.6198577881],"type":"Point"}
}