{
  "type": "Feature",
  "properties": {
    "iso:country":"ES",
    "sg:address":"Pase Quince De Mayo, 17",
    "sg:city":"Madrid",
    "sg:orig_category":"Tiendas De Grano, Frutas Y Legumbres Secas (al Por Menor)",
    "sg:phone":"+34 914 71 89 34",
    "sg:postcode":"28019",
    "sg:province":"Madrid",
    "wof:name":"Salazar Salazar Juan",
    "wof:placetype":"venue"
},
  "geometry": {"coordinates":[-3.719014883,40.3979263306],"type":"Point"}
}