{
  "type": "Feature",
  "properties": {
    "iso:country":"ES",
    "sg:address":"Calle de Nestor De La Torre, 7",
    "sg:city":"Palmas De Gran Canaria",
    "sg:classifiers":[
        {
            "category":"Banks & Credit Unions",
            "subcategory":"Bureau De Change",
            "type":"Services"
        }
    ],
    "sg:phone":"+34 928 24 20 21",
    "sg:postcode":"35006",
    "sg:province":"Las Palmas",
    "sg:tags":[
        "organismos",
        "control"
    ],
    "sg:website":"www.inteinco.es",
    "wof:name":"Inteinco S.a.",
    "wof:placetype":"venue"
},
  "geometry": {"coordinates":[-15.4397087097,28.1302242279],"type":"Point"}
}