{
  "type": "Feature",
  "properties": {
    "addr:full":"Calle de Pablo Rada, 4 Huelva Huelva 21004",
    "addr:housenumber":"4",
    "addr:postcode":"21004",
    "addr:street":"Calle De Pablo Rada",
    "iso:country":"ES",
    "sg:address":"Calle de Pablo Rada, 4",
    "sg:city":"Huelva",
    "sg:orig_category":"Fabricaci\u00d3n, Venta De Cuadros, Accesorios Para Enmarcar",
    "sg:phone":"+34 959 28 11 50",
    "sg:postcode":"21004",
    "sg:province":"Huelva",
    "wof:name":"Pulgarin Gonzalez Maria Antonia",
    "wof:placetype":"venue"
},
  "geometry": {"coordinates":[-6.9488267899,37.2589645386],"type":"Point"}
}