{
  "type": "Feature",
  "properties": {
    "addr:full":"Calle de Carcel (de La), 25 Manzanares Ciudad Real 13200",
    "addr:housenumber":"25",
    "addr:postcode":"13200",
    "addr:street":"Calle De Carcel De La",
    "iso:country":"ES",
    "sg:address":"Calle de Carcel (de La), 25",
    "sg:city":"Manzanares",
    "sg:orig_category":"Aparatos E Instalaci\u00d3n De Regad\u00cdos",
    "sg:phone":"+34 926 61 07 80",
    "sg:postcode":"13200",
    "sg:province":"Ciudad Real",
    "wof:name":"Ramos Garcia-sacristan Pedro",
    "wof:placetype":"venue"
},
  "geometry": {"coordinates":[-3.3742928505,38.9951057434],"type":"Point"}
}