{
  "type": "Feature",
  "properties": {
    "addr:full":"Calle de Camino De Los Sastres, 14 Cordoba C\u00f3rdoba 14004",
    "addr:housenumber":"14",
    "addr:postcode":"14004",
    "addr:street":"Calle De Camino De Los Sastres;Co\u0301Rdoba",
    "iso:country":"ES",
    "sg:address":"Calle de Camino De Los Sastres, 14",
    "sg:city":"Cordoba",
    "sg:orig_category":"Animales (al Por Menor)",
    "sg:phone":"+34 957 23 23 83",
    "sg:postcode":"14004",
    "sg:province":"C\u00f3rdoba",
    "wof:name":"Guerra Martos Fernando",
    "wof:placetype":"venue"
},
  "geometry": {"coordinates":[-4.7887148857,37.8814239502],"type":"Point"}
}