{
  "type": "Feature",
  "properties": {
    "addr:full":"Iglesia, S/n Villamaderne \u00c1lava 01423",
    "addr:housenumber":"s / n",
    "addr:postcode":"01423",
    "addr:street":"A\u0301Lava",
    "iso:country":"ES",
    "sg:address":"Iglesia, S/n",
    "sg:city":"Villamaderne",
    "sg:orig_category":"Producci\u00d3n, Comercio De Cereales",
    "sg:phone":"+34 945 35 10 28",
    "sg:postcode":"01423",
    "sg:province":"\u00c1lava",
    "wof:name":"Cooperativa De Cereales Valdegovia De A\u00f1ana",
    "wof:placetype":"venue"
},
  "geometry": {"coordinates":[-3.045388937,42.7516593933],"type":"Point"}
}