{
  "type": "Feature",
  "properties": {
    "iso:country":"ES",
    "sg:address":"Rond Bellesguard, 26",
    "sg:city":"Sabadell",
    "sg:orig_category":"Fabricaci\u00d3n De Juguetes Autom\u00c1ticos",
    "sg:phone":"+34 937 12 45 18",
    "sg:postcode":"08203",
    "sg:province":"Barcelona",
    "wof:name":"Eyofran",
    "wof:placetype":"venue"
},
  "geometry": {"coordinates":[2.1210899353,41.5358963013],"type":"Point"}
}