{
  "type": "Feature",
  "properties": {
    "addr:full":"G. Garcia Tafalla, 1 Carrascalejo C\u00e1ceres 10331",
    "addr:housenumber":"1",
    "addr:postcode":"10331",
    "addr:street":"Tafalla;Ca\u0301Ceres",
    "iso:country":"ES",
    "sg:address":"G. Garcia Tafalla, 1",
    "sg:city":"Carrascalejo",
    "sg:orig_category":"Iglesia Cat\u00d3lica",
    "sg:phone":"+34 927 55 50 66",
    "sg:postcode":"10331",
    "sg:province":"C\u00e1ceres",
    "wof:name":"Parroquia Nuestra Se\u00f1ora De La Asuncion",
    "wof:placetype":"venue"
},
  "geometry": {"coordinates":[-5.218624115,39.6495742798],"type":"Point"}
}