{
  "type": "Feature",
  "properties": {
    "iso:country":"ES",
    "sg:address":"Avda Pero Mingo (de), 44",
    "sg:city":"Sevilla",
    "sg:orig_category":"Quincaller\u00cda (al Por Menor)",
    "sg:phone":"+34 954 99 99 82",
    "sg:postcode":"41016",
    "sg:province":"Sevilla",
    "wof:name":"Ferreteria Y Armeria Hermanos Gomez S.l.",
    "wof:placetype":"venue"
},
  "geometry": {"coordinates":[-5.9146089554,37.3867454529],"type":"Point"}
}