{
  "type": "Feature",
  "properties": {
    "addr:full":"Pase Sagasta, 74 Zaragoza Zaragoza 50006",
    "addr:housenumber":"74",
    "addr:postcode":"50006",
    "iso:country":"ES",
    "sg:address":"Pase Sagasta, 74",
    "sg:city":"Zaragoza",
    "sg:orig_category":"Asesor\u00cda Sobre Comunicaci\u00d3n De Empresas",
    "sg:phone":"+34 976 37 17 16",
    "sg:postcode":"50006",
    "sg:province":"Zaragoza",
    "wof:name":"Asesoria Ruise\u00f1ores S.l.",
    "wof:placetype":"venue"
},
  "geometry": {"coordinates":[-0.8865686059,41.6397132874],"type":"Point"}
}