{
  "type": "Feature",
  "properties": {
    "addr:full":"Ctra Cordoba-almeria, 18 Huelma Ja\u00e9n 23560",
    "addr:housenumber":"18",
    "addr:postcode":"23560",
    "addr:street":"Ctra Cordoba-Almeria",
    "iso:country":"ES",
    "sg:address":"Ctra Cordoba-almeria, 18",
    "sg:city":"Huelma",
    "sg:orig_category":"Mec\u00c1nico Del Autom\u00d3vil",
    "sg:phone":"+34 953 39 03 41",
    "sg:postcode":"23560",
    "sg:province":"Ja\u00e9n",
    "wof:name":"Garcia Martinez Andres",
    "wof:placetype":"venue"
},
  "geometry": {"coordinates":[-3.4499619007,37.6491203308],"type":"Point"}
}