{
  "type": "Feature",
  "properties": {
    "addr:full":"Calle de Mayor, 26 Albacete Albacete 02002",
    "addr:housenumber":"26",
    "addr:postcode":"02002",
    "addr:street":"Calle De Mayor",
    "iso:country":"ES",
    "sg:address":"Calle de Mayor, 26",
    "sg:city":"Albacete",
    "sg:orig_category":"Pod\u00d3logos: Pedicuros",
    "sg:phone":"+34 967 21 69 51",
    "sg:postcode":"02002",
    "sg:province":"Albacete",
    "wof:name":"Lopez Barcenilla Francisco Manuel",
    "wof:placetype":"venue"
},
  "geometry": {"coordinates":[-1.8538589478,38.9929885864],"type":"Point"}
}