{
  "type": "Feature",
  "properties": {
    "addr:full":"Calle de Lope De Vega, 4 Cehegin Murcia 30430",
    "addr:housenumber":"4",
    "addr:postcode":"30430",
    "addr:street":"Calle De Lope De Vega",
    "iso:country":"ES",
    "sg:address":"Calle de Lope De Vega, 4",
    "sg:city":"Cehegin",
    "sg:orig_category":"Reposter\u00cdas",
    "sg:phone":"+34 968 74 08 14",
    "sg:postcode":"30430",
    "sg:province":"Murcia",
    "wof:name":"Sanchez Abril Francisco",
    "wof:placetype":"venue"
},
  "geometry": {"coordinates":[-1.7955460548,38.0954055786],"type":"Point"}
}