{
  "type": "Feature",
  "properties": {
    "addr:full":"Avda Cantarrana, 29 Covas Lugo 27861",
    "addr:housenumber":"29",
    "addr:postcode":"27861",
    "addr:street":"Avda Cantarrana",
    "iso:country":"ES",
    "sg:address":"Avda Cantarrana, 29",
    "sg:city":"Covas",
    "sg:orig_category":"Inform\u00c1tica, Ofim\u00c1tica (estudios, Asesor\u00cda, Ingenier\u00cda, Formaci\u00d3n)",
    "sg:phone":"+34 982 55 15 38",
    "sg:postcode":"27861",
    "sg:province":"Lugo",
    "wof:name":"Viveiro Informatica S.l.",
    "wof:placetype":"venue"
},
  "geometry": {"coordinates":[-7.603099823,43.6685905457],"type":"Point"}
}