{
  "type": "Feature",
  "properties": {
    "addr:full":"Avda Principes De Espa\u00d1a (de Los), 1 Coslada Madrid 28820",
    "addr:housenumber":"1",
    "addr:postcode":"28820",
    "addr:street":"Avda Principes De Espan\u0303A De Los",
    "iso:country":"ES",
    "sg:address":"Avda Principes De Espa\u00d1a (de Los), 1",
    "sg:city":"Coslada",
    "sg:orig_category":"Caf\u00c9s, Bares, Cervecer\u00cdas",
    "sg:phone":"+34 916 74 17 39",
    "sg:postcode":"28820",
    "sg:province":"Madrid",
    "wof:name":"Rodriguez Fernandez Emilio",
    "wof:placetype":"venue"
},
  "geometry": {"coordinates":[-3.5508890152,40.4268188477],"type":"Point"}
}