{
  "type": "Feature",
  "properties": {
    "iso:country":"ES",
    "sg:address":"Calle de Luis Braille (de), 22",
    "sg:city":"Coslada",
    "sg:orig_category":"Muebles Y Accesorios Para Cocinas Y Cuartos De Ba\u00d1o (al Por Menor)",
    "sg:phone":"+34 916 69 11 56",
    "sg:postcode":"28820",
    "sg:province":"Madrid",
    "wof:name":"Muebles Mugahi S.l.",
    "wof:placetype":"venue"
},
  "geometry": {"coordinates":[-3.5595059395,40.4256286621],"type":"Point"}
}