{
  "type": "Feature",
  "properties": {
    "addr:full":"Calle de Torrelapaja, 8 Sisallete Zaragoza 50420",
    "addr:housenumber":"8",
    "addr:postcode":"50420",
    "addr:street":"Calle De Torrelapaja",
    "iso:country":"ES",
    "sg:address":"Calle de Torrelapaja, 8",
    "sg:city":"Sisallete",
    "sg:orig_category":"Desinfecci\u00d3n, Desinsectaci\u00d3n, Desratizaci\u00d3n",
    "sg:phone":"+34 976 12 65 14",
    "sg:postcode":"50420",
    "sg:province":"Zaragoza",
    "wof:name":"Paules Alvarez Raquel",
    "wof:placetype":"venue"
},
  "geometry": {"coordinates":[-0.9601830244,41.5556411743],"type":"Point"}
}