{
  "type": "Feature",
  "properties": {
    "iso:country":"ES",
    "sg:address":"Avda Barranco (del), S/n",
    "sg:city":"Tablero",
    "sg:orig_category":"Peluquer\u00cdas, Peluquer\u00cda Mixta",
    "sg:phone":"+34 928 14 85 07",
    "sg:postcode":"35100",
    "sg:province":"Las Palmas",
    "wof:name":"Jimenez Rosales Jaime Alberto",
    "wof:placetype":"venue"
},
  "geometry": {"coordinates":[-15.6017599106,27.7717380524],"type":"Point"}
}