{
  "type": "Feature",
  "properties": {
    "addr:full":"Bos, 18 Bos A Coru\u00f1a 15640",
    "addr:housenumber":"18",
    "addr:postcode":"15640",
    "addr:street":"Bos;A Corun\u0303A",
    "iso:country":"ES",
    "sg:address":"Bos, 18",
    "sg:city":"Bos",
    "sg:orig_category":"Semiller\u00cdas",
    "sg:phone":"+34 981 79 51 84",
    "sg:postcode":"15640",
    "sg:province":"A Coru\u00f1a",
    "wof:name":"Silvar Pi\u00f1eiro Miguel Angel",
    "wof:placetype":"venue"
},
  "geometry": {"coordinates":[-8.2682237625,43.2997894287],"type":"Point"}
}