{
  "type": "Feature",
  "properties": {
    "addr:full":"Pg Pla\u00c7a Major, 31 Sabadell Barcelona 08201",
    "addr:housenumber":"31",
    "addr:postcode":"08201",
    "addr:street":"Pg Plac\u0327A Major",
    "iso:country":"ES",
    "sg:address":"Pg Pla\u00c7a Major, 31",
    "sg:city":"Sabadell",
    "sg:orig_category":"Art\u00cdculos De Regalo (al Por Menor)",
    "sg:phone":"+34 937 25 87 15",
    "sg:postcode":"08201",
    "sg:province":"Barcelona",
    "wof:name":"Llamps I Trons",
    "wof:placetype":"venue"
},
  "geometry": {"coordinates":[2.1088807583,41.5475502014],"type":"Point"}
}