{
  "type": "Feature",
  "properties": {
    "addr:full":"Calle de Juan Xxiii, 9 Cristianos Santa Cruz De Tenerife 38650",
    "addr:housenumber":"9",
    "addr:postcode":"38650",
    "addr:street":"Calle De Juan Xxiii",
    "iso:country":"ES",
    "sg:address":"Calle de Juan Xxiii, 9",
    "sg:city":"Cristianos",
    "sg:orig_category":"Ropa Para Se\u00d1oras (al Por Menor)",
    "sg:phone":"+34 922 79 29 37",
    "sg:postcode":"38650",
    "sg:province":"Santa Cruz De Tenerife",
    "wof:name":"Herman  Louis",
    "wof:placetype":"venue"
},
  "geometry": {"coordinates":[-16.7180461884,28.05210495],"type":"Point"}
}