{
  "type": "Feature",
  "properties": {
    "iso:country":"ES",
    "sg:address":"Avda Constitucion, 45",
    "sg:city":"Sangonera La Verde O Ermita Nueva",
    "sg:orig_category":"Promotores Constructores",
    "sg:phone":"+34 968 86 63 40",
    "sg:postcode":"30833",
    "sg:province":"Murcia",
    "wof:name":"Construcciones Pedro Diaz S.l.",
    "wof:placetype":"venue"
},
  "geometry": {"coordinates":[-1.2103899717,37.9288520813],"type":"Point"}
}