{
  "type": "Feature",
  "properties": {
    "iso:country":"ES",
    "sg:address":"Calle de Querol, 9",
    "sg:city":"Madrid",
    "sg:orig_category":"Reposter\u00cdas",
    "sg:phone":"+34 917 66 08 41",
    "sg:postcode":"28033",
    "sg:province":"Madrid",
    "wof:name":"Sanchez Gonzalez Maria Del Pilar",
    "wof:placetype":"venue"
},
  "geometry": {"coordinates":[-3.6638240814,40.4801483154],"type":"Point"}
}