{
  "type": "Feature",
  "properties": {
    "iso:country":"ES",
    "sg:address":"Pase Zorrilla, 83",
    "sg:city":"Valladolid",
    "sg:orig_category":"Muebles",
    "sg:phone":"+34 983 27 65 06",
    "sg:postcode":"47007",
    "sg:province":"Valladolid",
    "wof:name":"Miguel Alvarez Aparicio S.l.",
    "wof:placetype":"venue"
},
  "geometry": {"coordinates":[-4.7395138741,41.6351280212],"type":"Point"}
}