{
  "type": "Feature",
  "properties": {
    "addr:full":"Calle de Manuel De Falla, 6 San Vicente Del Raspeig-sant Vicent Del Raspeig Alicante 03690",
    "addr:housenumber":"6",
    "addr:postcode":"03690",
    "addr:street":"Calle De Manuel De Falla",
    "iso:country":"ES",
    "sg:address":"Calle de Manuel De Falla, 6",
    "sg:city":"San Vicente Del Raspeig-sant Vicent Del Raspeig",
    "sg:orig_category":"Centros Empresariales",
    "sg:phone":"+34 965 66 76 65",
    "sg:postcode":"03690",
    "sg:province":"Alicante",
    "wof:name":"Asociacion Provincial Administradores De Loteria De Alicante",
    "wof:placetype":"venue"
},
  "geometry": {"coordinates":[-0.5233678818,38.3973274231],"type":"Point"}
}