{
  "type": "Feature",
  "properties": {
    "addr:full":"Avda Generalisimo, 99 Meira Lugo 27240",
    "addr:housenumber":"99",
    "addr:postcode":"27240",
    "addr:street":"Avda Generalisimo",
    "iso:country":"ES",
    "sg:address":"Avda Generalisimo, 99",
    "sg:city":"Meira",
    "sg:orig_category":"Reposter\u00cdas",
    "sg:phone":"+34 982 33 01 73",
    "sg:postcode":"27240",
    "sg:province":"Lugo",
    "wof:name":"Panaderia Casta\u00f1al C.b.",
    "wof:placetype":"venue"
},
  "geometry": {"coordinates":[-7.2977280617,43.2135887146],"type":"Point"}
}