{
  "type": "Feature",
  "properties": {
    "addr:full":"Copernic (zona Ind Cami Ral), 18 Gava Barcelona 08850",
    "addr:housenumber":"18",
    "addr:postcode":"08850",
    "addr:street":"Cami Ral",
    "iso:country":"ES",
    "sg:address":"Copernic (zona Ind Cami Ral), 18",
    "sg:city":"Gava",
    "sg:orig_category":"Material Y Equipo Para Conserver\u00cdas Y Confiter\u00cdas",
    "sg:phone":"+34 936 36 35 93",
    "sg:postcode":"08850",
    "sg:province":"Barcelona",
    "sg:website":"www.scanvaegt.com",
    "wof:name":"Scanvaegt Espa\u00d1a S.l.",
    "wof:placetype":"venue"
},
  "geometry": {"coordinates":[1.9916280508,41.283416748],"type":"Point"}
}