{
  "type": "Feature",
  "properties": {
    "iso:country":"ES",
    "sg:address":"Carrer de Casp, 139",
    "sg:city":"Barcelona",
    "sg:orig_category":"Agencias Y Agentes Comerciales, Representantes",
    "sg:phone":"+34 932 31 87 62",
    "sg:postcode":"08013",
    "sg:province":"Barcelona",
    "wof:name":"Vi\u00f1as Berrocal Juan",
    "wof:placetype":"venue"
},
  "geometry": {"coordinates":[2.1812562943,41.3973121643],"type":"Point"}
}