{
  "type": "Feature",
  "properties": {
    "iso:country":"ES",
    "sg:address":"Casa Carreres, S/n",
    "sg:city":"Lliria",
    "sg:orig_category":"Asilos De Ancianos. Centros Privados",
    "sg:phone":"+34 962 78 21 72",
    "sg:postcode":"46160",
    "sg:province":"Valencia",
    "wof:name":"Espacios De Bienestar S.l.",
    "wof:placetype":"venue"
},
  "geometry": {"coordinates":[-0.5862500072,39.6414871216],"type":"Point"}
}