{
  "type": "Feature",
  "properties": {
    "addr:full":"Carrer de Andalusia, 10 Calafell Tarragona 43820",
    "addr:housenumber":"10",
    "addr:postcode":"43820",
    "addr:street":"Carrer De Andalusia",
    "iso:country":"ES",
    "sg:address":"Carrer de Andalusia, 10",
    "sg:city":"Calafell",
    "sg:orig_category":"Empresas De Carpinter\u00cda",
    "sg:phone":"+34 977 69 56 84",
    "sg:postcode":"43820",
    "sg:province":"Tarragona",
    "wof:name":"Aluminis A. Nogales S.l.",
    "wof:placetype":"venue"
},
  "geometry": {"coordinates":[1.5673036575,41.202671051],"type":"Point"}
}