{
  "type": "Feature",
  "properties": {
    "iso:country":"ES",
    "sg:address":"Calle de Merced La, 8",
    "sg:city":"Gijon",
    "sg:orig_category":"Arquitectos",
    "sg:phone":"+34 985 34 66 55",
    "sg:postcode":"33201",
    "sg:province":"Asturias",
    "wof:name":"Bra\u00f1a Diaz Juan",
    "wof:placetype":"venue"
},
  "geometry": {"coordinates":[-5.6622619629,43.5433197021],"type":"Point"}
}