{
  "type": "Feature",
  "properties": {
    "addr:full":"Carr Sequia, 20 Aitona Lleida 25182",
    "addr:housenumber":"20",
    "addr:postcode":"25182",
    "addr:street":"Carr Sequia",
    "iso:country":"ES",
    "sg:address":"Carr Sequia, 20",
    "sg:city":"Aitona",
    "sg:orig_category":"Molduras, Junquillos, Listones Y Molduras Perforadas",
    "sg:phone":"+34 973 79 40 00",
    "sg:postcode":"25182",
    "sg:province":"Lleida",
    "wof:name":"Vila Del Hueso Montserrat",
    "wof:placetype":"venue"
},
  "geometry": {"coordinates":[0.4589020014,41.4938621521],"type":"Point"}
}