{
  "type": "Feature",
  "properties": {
    "addr:full":"Carrer de Miguel De Cervantes (de), 19 Tortosa Tarragona 43500",
    "addr:housenumber":"19",
    "addr:postcode":"43500",
    "addr:street":"Carrer De Miguel De Cervantes De",
    "iso:country":"ES",
    "sg:address":"Carrer de Miguel De Cervantes (de), 19",
    "sg:city":"Tortosa",
    "sg:orig_category":"Pod\u00d3logos: Pedicuros",
    "sg:phone":"+34 977 44 21 84",
    "sg:postcode":"43500",
    "sg:province":"Tarragona",
    "wof:name":"Aixendri Ventura Javier",
    "wof:placetype":"venue"
},
  "geometry": {"coordinates":[0.563609004,40.8360290527],"type":"Point"}
}