{
  "type": "Feature",
  "properties": {
    "iso:country":"ES",
    "sg:address":"Los Rosales, 7",
    "sg:city":"Coria",
    "sg:orig_category":"Chapister\u00cda",
    "sg:phone":"+34 927 50 63 11",
    "sg:postcode":"10800",
    "sg:province":"C\u00e1ceres",
    "wof:name":"Chapa Y Pintura Rusicar S.l.",
    "wof:placetype":"venue"
},
  "geometry": {"coordinates":[-6.5262007713,39.9889335632],"type":"Point"}
}