{
  "type": "Feature",
  "properties": {
    "addr:full":"Carr Bisbe Messeguer, 22 Lleida Lleida 25003",
    "addr:housenumber":"22",
    "addr:postcode":"25003",
    "addr:street":"Carr Bisbe Messeguer",
    "iso:country":"ES",
    "sg:address":"Carr Bisbe Messeguer, 22",
    "sg:city":"Lleida",
    "sg:orig_category":"Muebles Y Accesorios Para Cocinas Y Cuartos De Ba\u00d1o (al Por Menor)",
    "sg:phone":"+34 973 26 34 48",
    "sg:postcode":"25003",
    "sg:province":"Lleida",
    "wof:name":"Decoceramica Coll S.l.",
    "wof:placetype":"venue"
},
  "geometry": {"coordinates":[0.6163510084,41.615272522],"type":"Point"}
}