{
  "type": "Feature",
  "properties": {
    "addr:full":"Pg Gracia, 23 Barcelona Barcelona 08007",
    "addr:housenumber":"23",
    "addr:postcode":"08007",
    "addr:street":"Pg Gracia",
    "iso:country":"ES",
    "sg:address":"Pg Gracia, 23",
    "sg:city":"Barcelona",
    "sg:orig_category":"Ropa Para Se\u00d1oras (al Por Menor)",
    "sg:phone":"+34 934 88 21 81",
    "sg:postcode":"08007",
    "sg:province":"Barcelona",
    "wof:name":"Gracia 23 S.l.",
    "wof:placetype":"venue"
},
  "geometry": {"coordinates":[2.1664910316,41.3904647827],"type":"Point"}
}