{
  "type": "Feature",
  "properties": {
    "addr:full":"Calle de Galera, 21 Coru\u00d1a La Coru\u00f1a 15001",
    "addr:housenumber":"21",
    "addr:postcode":"15001",
    "addr:street":"Calle De Galera;La Corun\u0303A",
    "iso:country":"ES",
    "sg:address":"Calle de Galera, 21",
    "sg:city":"Coru\u00d1a",
    "sg:orig_category":"Material Y Suministros Para Peluquer\u00cda",
    "sg:phone":"+34 981 22 94 97",
    "sg:postcode":"15001",
    "sg:province":"La Coru\u00f1a",
    "wof:name":"Freire Garcia Jose Maria",
    "wof:placetype":"venue"
},
  "geometry": {"coordinates":[-8.3195390701,43.1524581909],"type":"Point"}
}