{
  "type": "Feature",
  "properties": {
    "iso:country":"ES",
    "sg:address":"Av Catalunya, 96",
    "sg:city":"Casc Antic",
    "sg:orig_category":"Administradores De Bienes Y Delegados De Comunidades De Propietarios",
    "sg:phone":"+34 935 62 05 04",
    "sg:postcode":"08150",
    "sg:province":"Barcelona",
    "wof:name":"Administracio I Finques Isern S.l.",
    "wof:placetype":"venue"
},
  "geometry": {"coordinates":[2.1699187756,41.3879165649],"type":"Point"}
}