{
  "type": "Feature",
  "properties": {
    "addr:full":"Rua Ribeiro (do), 1 Ribadavia Ourense 32400",
    "addr:housenumber":"1",
    "addr:postcode":"32400",
    "addr:street":"Rua Ribeiro Do",
    "iso:country":"ES",
    "sg:address":"Rua Ribeiro (do), 1",
    "sg:city":"Ribadavia",
    "sg:orig_category":"Alimentaci\u00d3n General (al Por Menor)",
    "sg:phone":"+34 988 47 08 32",
    "sg:postcode":"32400",
    "sg:province":"Ourense",
    "wof:name":"Mosquera Almui\u00f1a Francisco",
    "wof:placetype":"venue"
},
  "geometry": {"coordinates":[-8.1432886124,42.2903938293],"type":"Point"}
}