{
  "type": "Feature",
  "properties": {
    "addr:full":"Carrer de Bruguera, 38 Calella Barcelona 08370",
    "addr:housenumber":"38",
    "addr:postcode":"08370",
    "addr:street":"Carrer De Bruguera",
    "iso:country":"ES",
    "sg:address":"Carrer de Bruguera, 38",
    "sg:city":"Calella",
    "sg:orig_category":"Fabricaci\u00d3n, Importaci\u00d3n De L\u00c1mparas Y Bombillas",
    "sg:phone":"+34 937 66 06 34",
    "sg:postcode":"08370",
    "sg:province":"Barcelona",
    "wof:name":"Martinez Ruiz Juan Antonio",
    "wof:placetype":"venue"
},
  "geometry": {"coordinates":[2.6595630646,41.6142501831],"type":"Point"}
}