{
  "type": "Feature",
  "properties": {
    "addr:full":"Calle de Cascaleria, 3 Le\u00f3n Le\u00f3n 24003",
    "addr:housenumber":"3",
    "addr:postcode":"24003",
    "addr:street":"Calle De Cascaleria;Leo\u0301N",
    "iso:country":"ES",
    "sg:address":"Calle de Cascaleria, 3",
    "sg:city":"Le\u00f3n",
    "sg:orig_category":"Molduras, Junquillos, Listones Y Molduras Perforadas",
    "sg:phone":"+34 987 26 32 42",
    "sg:postcode":"24003",
    "sg:province":"Le\u00f3n",
    "wof:name":"Delgado Fuentes Jesus Antonio",
    "wof:placetype":"venue"
},
  "geometry": {"coordinates":[-5.5690779686,42.5967330933],"type":"Point"}
}