{
  "type": "Feature",
  "properties": {
    "iso:country":"ES",
    "sg:address":"Plaz Iglesia (la), 2",
    "sg:city":"Cabanillas Campo",
    "sg:orig_category":"Cajas De Ahorro",
    "sg:phone":"+34 949 33 20 61",
    "sg:postcode":"19171",
    "sg:province":"Guadalajara",
    "sg:website":"www.cajaguadalajara.es",
    "wof:name":"Caja De Ahorro Provincial De Guadalajara",
    "wof:placetype":"venue"
},
  "geometry": {"coordinates":[-3.2374420166,40.6377639771],"type":"Point"}
}