{
  "type": "Feature",
  "properties": {
    "iso:country":"ES",
    "sg:address":"Calle de San Agustin, 10",
    "sg:city":"Icod De Los Vinos",
    "sg:orig_category":"Muebles, Minoristas",
    "sg:phone":"+34 922 81 57 10",
    "sg:postcode":"38430",
    "sg:province":"Santa Cruz De Tenerife",
    "sg:website":"www.hcalatayud.com",
    "wof:name":"Muebles Drago S.a.",
    "wof:placetype":"venue"
},
  "geometry": {"coordinates":[-16.7184295654,28.367017746],"type":"Point"}
}