{
  "type": "Feature",
  "properties": {
    "addr:full":"Pl Pomar, S/n Badalona Barcelona 08915",
    "addr:housenumber":"s / n",
    "addr:postcode":"08915",
    "addr:street":"Pl Pomar",
    "iso:country":"ES",
    "sg:address":"Pl Pomar, S/n",
    "sg:city":"Badalona",
    "sg:orig_category":"Iglesia Cat\u00d3lica",
    "sg:phone":"+34 933 95 41 54",
    "sg:postcode":"08915",
    "sg:province":"Barcelona",
    "wof:name":"Parroquia De San Sebastian",
    "wof:placetype":"venue"
},
  "geometry": {"coordinates":[2.2505230904,41.4649658203],"type":"Point"}
}