{
  "type": "Feature",
  "properties": {
    "iso:country":"ES",
    "sg:address":"Calle de Carretera, S/n",
    "sg:city":"Conil De La Frontera",
    "sg:orig_category":"Zapatos (al Por Menor)",
    "sg:phone":"+34 956 44 24 20",
    "sg:postcode":"11140",
    "sg:province":"C\u00e1diz",
    "wof:name":"Bonillo Rosado Ana Victoria",
    "wof:placetype":"venue"
},
  "geometry": {"coordinates":[-6.083313942,36.2816810608],"type":"Point"}
}