{
  "type": "Feature",
  "properties": {
    "iso:country":"ES",
    "sg:address":"Carr Sant Francesc, 81",
    "sg:city":"Picanya",
    "sg:orig_category":"Artes Gr\u00c1ficas, Artes Pl\u00c1sticas (curso)",
    "sg:phone":"+34 961 59 25 44",
    "sg:postcode":"46210",
    "sg:province":"Valencia",
    "wof:name":"Quilez Sierra Juan Emilio",
    "wof:placetype":"venue"
},
  "geometry": {"coordinates":[-0.4369910061,39.4335823059],"type":"Point"}
}