{
  "type": "Feature",
  "properties": {
    "iso:country":"ES",
    "sg:address":"Calle de Velazquez, 9",
    "sg:city":"Nerja",
    "sg:orig_category":"Empresas De Carpinter\u00cda De Madera",
    "sg:phone":"+34 952 52 34 84",
    "sg:postcode":"29780",
    "sg:province":"M\u00e1laga",
    "wof:name":"Anumar S.l.",
    "wof:placetype":"venue"
},
  "geometry": {"coordinates":[-3.8765888214,36.7535400391],"type":"Point"}
}