{
  "type": "Feature",
  "properties": {
    "iso:country":"ES",
    "sg:address":"Calle de Jesus Aprendiz, 21",
    "sg:city":"Madrid",
    "sg:orig_category":"Productos Qu\u00cdmicos (fabricaci\u00d3n, Al Por Mayor)",
    "sg:phone":"+34 914 33 02 06",
    "sg:postcode":"28007",
    "sg:province":"Madrid",
    "wof:name":"Laboratorios Athanor S.l.",
    "wof:placetype":"venue"
},
  "geometry": {"coordinates":[-3.6710190773,40.4094085693],"type":"Point"}
}