{
  "type": "Feature",
  "properties": {
    "iso:country":"ES",
    "sg:address":"Carrer de Rauric, 2",
    "sg:city":"Barcelona",
    "sg:orig_category":"Art\u00cdculos De Regalo (al Por Menor)",
    "sg:phone":"+34 933 02 58 76",
    "sg:postcode":"08002",
    "sg:province":"Barcelona",
    "wof:name":"Galarza De La Cruz Horacio",
    "wof:placetype":"venue"
},
  "geometry": {"coordinates":[2.1745998859,41.3814544678],"type":"Point"}
}