{
  "type": "Feature",
  "properties": {
    "iso:country":"ES",
    "sg:address":"Alam Mazarredo, 15",
    "sg:city":"Bilbao",
    "sg:orig_category":"Centros De Adelgazamiento Y De Est\u00c9tica",
    "sg:phone":"+34 944 23 36 64",
    "sg:postcode":"48001",
    "sg:province":"Vizcaya",
    "wof:name":"Peluqueria Yolanda Aberasturi S.l.",
    "wof:placetype":"venue"
},
  "geometry": {"coordinates":[-2.9293310642,43.2643737793],"type":"Point"}
}