{
  "type": "Feature",
  "properties": {
    "addr:full":"Calle de Jaime Vera, 12 Madrid Madrid 28011",
    "addr:housenumber":"12",
    "addr:postcode":"madrid;28011",
    "addr:street":"Calle De Jaime Vera",
    "iso:country":"ES",
    "sg:address":"Calle de Jaime Vera, 12",
    "sg:city":"Madrid",
    "sg:orig_category":"Molduras, Junquillos, Listones Y Molduras Perforadas",
    "sg:phone":"+34 914 64 30 52",
    "sg:postcode":"28011",
    "sg:province":"Madrid",
    "wof:name":"Sanchidrian Alonso Felix",
    "wof:placetype":"venue"
},
  "geometry": {"coordinates":[-3.7289550304,40.4125556946],"type":"Point"}
}