{
  "type": "Feature",
  "properties": {
    "addr:full":"Calle de Tercia, 38 Malagon Ciudad Real 13420",
    "addr:housenumber":"38",
    "addr:postcode":"13420",
    "addr:street":"Calle De Tercia",
    "iso:country":"ES",
    "sg:address":"Calle de Tercia, 38",
    "sg:city":"Malagon",
    "sg:orig_category":"Ense\u00d1anza Variada",
    "sg:phone":"+34 926 80 16 14",
    "sg:postcode":"13420",
    "sg:province":"Ciudad Real",
    "wof:name":"Valencia Leon Maria Soledad",
    "wof:placetype":"venue"
},
  "geometry": {"coordinates":[-3.8536291122,39.1699790955],"type":"Point"}
}