{
  "type": "Feature",
  "properties": {
    "addr:full":"Carrer de Rossello, 47 S. Boi Llobregat Barcelona 08830",
    "addr:housenumber":"47",
    "addr:postcode":"08830",
    "addr:street":"Carrer De Rossello",
    "iso:country":"ES",
    "sg:address":"Carrer de Rossello, 47",
    "sg:city":"S. Boi Llobregat",
    "sg:orig_category":"Farmacias",
    "sg:phone":"+34 936 52 02 14",
    "sg:postcode":"08830",
    "sg:province":"Barcelona",
    "wof:name":"Prat Borrell Maria Mercedes",
    "wof:placetype":"venue"
},
  "geometry": {"coordinates":[2.0309669971,41.3479003906],"type":"Point"}
}