{
  "type": "Feature",
  "properties": {
    "iso:country":"ES",
    "sg:address":"Calle de Alferez Bayton, 1",
    "sg:city":"Ceuta",
    "sg:orig_category":"Loter\u00cda Y T\u00d3mbola",
    "sg:phone":"+34 956 51 28 14",
    "sg:postcode":"51001",
    "sg:province":"Ceuta",
    "wof:name":"Fernandez Del Villar Jimenez Antonio",
    "wof:placetype":"venue"
},
  "geometry": {"coordinates":[-5.3120069504,35.8881149292],"type":"Point"}
}