{
  "type": "Feature",
  "properties": {
    "iso:country":"ES",
    "sg:address":"La Vinya, 37",
    "sg:city":"Vilafant",
    "sg:orig_category":"Mec\u00c1nico Del Autom\u00d3vil",
    "sg:phone":"+34 972 54 60 68",
    "sg:postcode":"17740",
    "sg:province":"Girona",
    "wof:name":"Serra Juanola Joaquin",
    "wof:placetype":"venue"
},
  "geometry": {"coordinates":[2.9401900768,42.2476806641],"type":"Point"}
}