{
  "type": "Feature",
  "properties": {
    "addr:full":"Carrer de Beat Oriol, 7 Mas Rampinyo Barcelona 08110",
    "addr:housenumber":"7",
    "addr:postcode":"08110",
    "addr:street":"Carrer De;Oriol",
    "iso:country":"ES",
    "sg:address":"Carrer de Beat Oriol, 7",
    "sg:city":"Mas Rampinyo",
    "sg:orig_category":"Aluminio Y Aleaciones (producci\u00d3n, Transformaci\u00d3n, Negocio)",
    "sg:phone":"+34 935 72 42 11",
    "sg:postcode":"08110",
    "sg:province":"Barcelona",
    "wof:name":"Aluminios Fima S.a.",
    "wof:placetype":"venue"
},
  "geometry": {"coordinates":[2.1781036854,41.4914855957],"type":"Point"}
}