{
  "type": "Feature",
  "properties": {
    "addr:full":"Calle de Mostoles, 27 Gijon Asturias 33212",
    "addr:housenumber":"27",
    "addr:postcode":"33212",
    "addr:street":"Calle De Mostoles",
    "iso:country":"ES",
    "sg:address":"Calle de Mostoles, 27",
    "sg:city":"Gijon",
    "sg:orig_category":"Negocio De Enlosados, Soler\u00cdas",
    "sg:phone":"+34 985 30 03 88",
    "sg:postcode":"33212",
    "sg:province":"Asturias",
    "wof:name":"Arena Dise\u00f1o Y Decoracion S.l.",
    "wof:placetype":"venue"
},
  "geometry": {"coordinates":[-5.6843552589,43.5416297913],"type":"Point"}
}