{
  "type": "Feature",
  "properties": {
    "iso:country":"ES",
    "sg:address":"Avda Espa\u00d1a, 18",
    "sg:city":"Albacete",
    "sg:orig_category":"Radiocomunicaciones, Telefon\u00cda M\u00d3vil, Radiomensajer\u00cda: Servicios, Comercializaci\u00d3n",
    "sg:phone":"+34 967 19 00 80",
    "sg:postcode":"02002",
    "sg:province":"Albacete",
    "sg:website":"www.cantenet.com",
    "wof:name":"Cantenet S.l.",
    "wof:placetype":"venue"
},
  "geometry": {"coordinates":[-1.8539030552,38.9843559265],"type":"Point"}
}