{
  "type": "Feature",
  "properties": {
    "iso:country":"ES",
    "sg:address":"Calle de Canalejas, 10",
    "sg:city":"Lucena",
    "sg:orig_category":"Caf\u00c9s, Bares, Cervecer\u00cdas",
    "sg:phone":"+34 957 51 58 87",
    "sg:postcode":"14900",
    "sg:province":"C\u00f3rdoba",
    "wof:name":"Toro Lozano Antonio",
    "wof:placetype":"venue"
},
  "geometry": {"coordinates":[-4.4859118462,37.4094619751],"type":"Point"}
}