{
  "type": "Feature",
  "properties": {
    "iso:country":"ES",
    "sg:address":"Ctra. Segovia, 8",
    "sg:city":"Abades",
    "sg:orig_category":"Cerrajer\u00cda, Ferrallista",
    "sg:phone":"+34 921 49 52 79",
    "sg:postcode":"40141",
    "sg:province":"Segovia",
    "wof:name":"Bravo Garcia Benito",
    "wof:placetype":"venue"
},
  "geometry": {"coordinates":[-4.2673459053,40.9156837463],"type":"Point"}
}