{
  "type": "Feature",
  "properties": {
    "addr:full":"Carrer de Raiguer (del), S/n Montornes Nord Barcelona 08170",
    "addr:postcode":"08170",
    "addr:street":"Carrer De Raiguer Del S / N Montornes Nord Barcelona",
    "iso:country":"ES",
    "sg:address":"Carrer de Raiguer (del), S/n",
    "sg:city":"Montornes Nord",
    "sg:orig_category":"Contenedores (mercanc\u00cdas)",
    "sg:phone":"+34 935 72 17 05",
    "sg:postcode":"08170",
    "sg:province":"Barcelona",
    "wof:name":"Distribuciones Codina S.l.",
    "wof:placetype":"venue"
},
  "geometry": {"coordinates":[2.2627000809,41.5591583252],"type":"Point"}
}