{
  "type": "Feature",
  "properties": {
    "addr:full":"Calle de Duquesa De La Victoria, 34 Logro\u00f1o La Rioja 26003",
    "addr:housenumber":"34",
    "addr:postcode":"26003",
    "addr:street":"Calle De Duquesa De La Victoria;Rioja",
    "iso:country":"ES",
    "sg:address":"Calle de Duquesa De La Victoria, 34",
    "sg:city":"Logro\u00f1o",
    "sg:orig_category":"Electricidad Veh\u00cdculo",
    "sg:phone":"+34 941 23 11 79",
    "sg:postcode":"26003",
    "sg:province":"La Rioja",
    "wof:name":"Saenz Cara Ricardo",
    "wof:placetype":"venue"
},
  "geometry": {"coordinates":[-2.4390892982,42.4647903442],"type":"Point"}
}