{
  "type": "Feature",
  "properties": {
    "addr:full":"Calle de Portal De Arriaga, 11 Vitoria-gasteiz \u00c1lava 01012",
    "addr:housenumber":"11",
    "addr:postcode":"01012",
    "addr:street":"Calle De Portal De Arriaga",
    "iso:country":"ES",
    "sg:address":"Calle de Portal De Arriaga, 11",
    "sg:city":"Vitoria-gasteiz",
    "sg:orig_category":"Peluqueros: De Se\u00d1oras",
    "sg:phone":"+34 945 22 15 32",
    "sg:postcode":"01012",
    "sg:province":"\u00c1lava",
    "wof:name":"Larrauri Fernandez De Leceta Maria Estibaliz",
    "wof:placetype":"venue"
},
  "geometry": {"coordinates":[-2.6733810902,42.853679657],"type":"Point"}
}