{
  "type": "Feature",
  "properties": {
    "iso:country":"ES",
    "sg:address":"Lince, 48",
    "sg:city":"El Rocio",
    "sg:orig_category":"Diarios, Revistas Y Boletines (suscripciones)",
    "sg:phone":"+34 959 44 23 82",
    "sg:postcode":"21750",
    "sg:province":"Huelva",
    "wof:name":"Hache Hache Luike S.l.",
    "wof:placetype":"venue"
},
  "geometry": {"coordinates":[-6.4818649292,37.1365203857],"type":"Point"}
}