{
  "type": "Feature",
  "properties": {
    "iso:country":"ES",
    "sg:address":"Calle de Rosario, 10",
    "sg:city":"Viso Del Alcor",
    "sg:orig_category":"Peluquer\u00cdas, Peluquer\u00cda Mixta",
    "sg:phone":"+34 955 94 58 73",
    "sg:postcode":"41520",
    "sg:province":"Sevilla",
    "wof:name":"Sanchez Borreguero Jesus",
    "wof:placetype":"venue"
},
  "geometry": {"coordinates":[-5.7219572067,37.3870849609],"type":"Point"}
}