{
  "type": "Feature",
  "properties": {
    "iso:country":"ES",
    "sg:address":"Calle de Bolta\u00d1a, 58",
    "sg:city":"Madrid",
    "sg:orig_category":"Frutas, Legumbres Frescas Y Tempranas (al Por Menor)",
    "sg:phone":"+34 913 20 18 81",
    "sg:postcode":"28022",
    "sg:province":"Madrid",
    "wof:name":"Lagunar Bahamonde Miriam",
    "wof:placetype":"venue"
},
  "geometry": {"coordinates":[-3.6123621464,40.4458694458],"type":"Point"}
}