{
  "type": "Feature",
  "properties": {
    "iso:country":"ES",
    "sg:address":"Praj Buenavista, 23",
    "sg:city":"Burgos",
    "sg:orig_category":"Alimentaci\u00d3n General (al Por Mayor)",
    "sg:phone":"+34 947 47 49 97",
    "sg:postcode":"09007",
    "sg:province":"Burgos",
    "wof:name":"Canibur S.l.",
    "wof:placetype":"venue"
},
  "geometry": {"coordinates":[-3.6628870964,42.3535194397],"type":"Point"}
}