{
  "type": "Feature",
  "properties": {
    "iso:country":"ES",
    "sg:address":"Carrer de Torrent Fondo, 7",
    "sg:city":"Viladecans",
    "sg:orig_category":"Aceros Inoxidables",
    "sg:phone":"+34 936 47 23 40",
    "sg:postcode":"08840",
    "sg:province":"Barcelona",
    "wof:name":"Ugitech Iberica S.a.",
    "wof:placetype":"venue"
},
  "geometry": {"coordinates":[2.0272901058,41.3209686279],"type":"Point"}
}