{
  "type": "Feature",
  "properties": {
    "addr:full":"Avda Constitucion, 204 Villena Alicante 03400",
    "addr:housenumber":"204",
    "addr:postcode":"03400",
    "addr:street":"Avda Constitucion",
    "iso:country":"ES",
    "sg:address":"Avda Constitucion, 204",
    "sg:city":"Villena",
    "sg:orig_category":"Comercio, Reparaci\u00d3n De Bicicletas, De Motocicletas, De Accesorios",
    "sg:phone":"+34 965 80 18 83",
    "sg:postcode":"03400",
    "sg:province":"Alicante",
    "wof:name":"Camus Martinez Miguel",
    "wof:placetype":"venue"
},
  "geometry": {"coordinates":[-0.8690119982,38.6429138184],"type":"Point"}
}