{
  "type": "Feature",
  "properties": {
    "iso:country":"ES",
    "sg:address":"Calle de Pinos (los), 6",
    "sg:city":"Mislata",
    "sg:orig_category":"Bisuter\u00cda, Joyer\u00cda, Relojer\u00cda (al Por Menor)",
    "sg:phone":"+34 963 79 49 62",
    "sg:postcode":"46920",
    "sg:province":"Valencia",
    "wof:name":"Valdior S.l.",
    "wof:placetype":"venue"
},
  "geometry": {"coordinates":[-0.4202097058,39.4758834839],"type":"Point"}
}