{
  "type": "Feature",
  "properties": {
    "iso:country":"ES",
    "sg:address":"Camino De Fuente Vaqueros, S/n",
    "sg:city":"Pedro Ruiz",
    "sg:orig_category":"Asilos De Ancianos. Centros Privados",
    "sg:phone":"+34 958 44 71 54",
    "sg:postcode":"18292",
    "sg:province":"Granada",
    "wof:name":"Centro Asistencial Fuente Salinas S.l.",
    "wof:placetype":"venue"
},
  "geometry": {"coordinates":[-3.7519299984,37.2159118652],"type":"Point"}
}