{
  "type": "Feature",
  "properties": {
    "iso:country":"ES",
    "sg:address":"Geltoki Bidea, 9",
    "sg:city":"Zarautz",
    "sg:orig_category":"Molduras, Junquillos, Listones Y Molduras Perforadas",
    "sg:phone":"+34 943 83 28 24",
    "sg:postcode":"20800",
    "sg:province":"Guip\u00f9zcoa",
    "wof:name":"Nu\u00f1ez Hernandez Francisco",
    "wof:placetype":"venue"
},
  "geometry": {"coordinates":[-2.1732580662,43.2845001221],"type":"Point"}
}