{
  "type": "Feature",
  "properties": {
    "addr:full":"Calle de Hermosilla, 74 Madrid Madrid 28001",
    "addr:housenumber":"74",
    "addr:postcode":"madrid;28001",
    "addr:street":"Calle De Hermosilla",
    "iso:country":"ES",
    "sg:address":"Calle de Hermosilla, 74",
    "sg:city":"Madrid",
    "sg:orig_category":"Perfumer\u00cda (al Por Menor)",
    "sg:phone":"+34 914 35 58 93",
    "sg:postcode":"28001",
    "sg:province":"Madrid",
    "sg:website":"www.bodybell.com",
    "wof:name":"Iberica De Drogueria Y Perfumeria S.a.",
    "wof:placetype":"venue"
},
  "geometry": {"coordinates":[-3.678096056,40.4259033203],"type":"Point"}
}