{
  "type": "Feature",
  "properties": {
    "iso:country":"ES",
    "sg:address":"Carr Eduardo Torres (d'), 8",
    "sg:city":"Albaida",
    "sg:orig_category":"Cables Y Hilos El\u00c9ctricos (fabricaci\u00d3n, Al Por Mayor)",
    "sg:phone":"+34 962 90 09 81",
    "sg:postcode":"46860",
    "sg:province":"Valencia",
    "wof:name":"Hijos De Fernando Borderia Martinez S.l.",
    "wof:placetype":"venue"
},
  "geometry": {"coordinates":[-0.5177410245,38.8406524658],"type":"Point"}
}