{
  "type": "Feature",
  "properties": {
    "iso:country":"ES",
    "sg:address":"Calle de Siervas De Jesus, 14",
    "sg:city":"Haro",
    "sg:orig_category":"Comercio, Reparaci\u00d3n De Bicicletas, De Motocicletas, De Accesorios",
    "sg:phone":"+34 941 31 26 38",
    "sg:postcode":"26200",
    "sg:province":"La Rioja",
    "wof:name":"Fernandez Gonzalez Jose Luis",
    "wof:placetype":"venue"
},
  "geometry": {"coordinates":[-2.8440389633,42.5774040222],"type":"Point"}
}