{
  "type": "Feature",
  "properties": {
    "addr:full":"Calle de Toscales, 2 Toscales Santa Cruz De Tenerife 38626",
    "addr:housenumber":"2",
    "addr:postcode":"38626",
    "addr:street":"Calle De Toscales",
    "iso:country":"ES",
    "sg:address":"Calle de Toscales, 2",
    "sg:city":"Toscales",
    "sg:orig_category":"Agencias Y Agentes Comerciales, Representantes",
    "sg:phone":"+34 922 72 13 47",
    "sg:postcode":"38626",
    "sg:province":"Santa Cruz De Tenerife",
    "wof:name":"Harrison  Alan John",
    "wof:placetype":"venue"
},
  "geometry": {"coordinates":[-16.6702098846,28.0729980469],"type":"Point"}
}