{
  "type": "Feature",
  "properties": {
    "addr:full":"Calle de Mayor De Reinoso, 5 Bejar Salamanca 37700",
    "addr:housenumber":"5",
    "addr:postcode":"37700",
    "addr:street":"Calle De Mayor De Reinoso",
    "iso:country":"ES",
    "sg:address":"Calle de Mayor De Reinoso, 5",
    "sg:city":"Bejar",
    "sg:orig_category":"Bisuter\u00cda, Joyer\u00cda, Relojer\u00cda (al Por Menor)",
    "sg:phone":"+34 923 40 03 65",
    "sg:postcode":"37700",
    "sg:province":"Salamanca",
    "wof:name":"Izquierdo Garcia Francisco",
    "wof:placetype":"venue"
},
  "geometry": {"coordinates":[-5.7665991783,40.386390686],"type":"Point"}
}