{
  "type": "Feature",
  "properties": {
    "iso:country":"ES",
    "sg:address":"Avda Constitucion (de La), S/n",
    "sg:city":"Poligono Industrial Monte Boyal",
    "sg:orig_category":"Cerrajer\u00cda, Ferrallista",
    "sg:phone":"+34 918 18 31 44",
    "sg:postcode":"45950",
    "sg:province":"Toledo",
    "sg:website":"www.patente-fac.com",
    "wof:name":"Fac Seguridad S.a.",
    "wof:placetype":"venue"
},
  "geometry": {"coordinates":[-4.0531868935,40.2130241394],"type":"Point"}
}