{
  "type": "Feature",
  "properties": {
    "iso:country":"ES",
    "sg:address":"Barr Castro-pousada, 16",
    "sg:city":"Chantada",
    "sg:orig_category":"Mec\u00c1nico Del Autom\u00d3vil",
    "sg:phone":"+34 982 44 05 28",
    "sg:postcode":"27500",
    "sg:province":"Lugo",
    "wof:name":"Manuel Varela Gonzalez S.l.",
    "wof:placetype":"venue"
},
  "geometry": {"coordinates":[-8.5196342468,42.7190093994],"type":"Point"}
}