{
  "type": "Feature",
  "properties": {
    "addr:full":"Pase Andalucia (de), 51 Espejo C\u00f3rdoba 14830",
    "addr:postcode":"14830",
    "addr:street":"Espejo Co\u0301Rdoba",
    "iso:country":"ES",
    "sg:address":"Pase Andalucia (de), 51",
    "sg:city":"Espejo",
    "sg:orig_category":"Asociaciones, Organismos Culturales Y Socioeducativos",
    "sg:phone":"+34 957 37 61 14",
    "sg:postcode":"14830",
    "sg:province":"C\u00f3rdoba",
    "wof:name":"Asociacion Pe\u00f1a Los Amigos De Espejo",
    "wof:placetype":"venue"
},
  "geometry": {"coordinates":[-4.5521273613,37.668056488],"type":"Point"}
}