{
  "type": "Feature",
  "properties": {
    "iso:country":"ES",
    "sg:address":"Pg Progres, 2",
    "sg:city":"Olesa Montserrat",
    "sg:orig_category":"Agentes Generales De Seguros",
    "sg:phone":"+34 937 78 56 86",
    "sg:postcode":"08640",
    "sg:province":"Barcelona",
    "wof:name":"Creu De Saba S.l.",
    "wof:placetype":"venue"
},
  "geometry": {"coordinates":[1.8942710161,41.543346405],"type":"Point"}
}