{
  "type": "Feature",
  "properties": {
    "iso:country":"ES",
    "sg:address":"Pase San Cristobal, 7",
    "sg:city":"Toledo",
    "sg:orig_category":"M\u00c9dicos: Otorrinolaringolog\u00cda",
    "sg:phone":"+34 925 22 86 39",
    "sg:postcode":"45002",
    "sg:province":"Toledo",
    "wof:name":"Iba\u00f1ez Garcia Dimas",
    "wof:placetype":"venue"
},
  "geometry": {"coordinates":[-4.0269641876,39.8547172546],"type":"Point"}
}