{
  "type": "Feature",
  "properties": {
    "addr:full":"Calle de Athos, 56 Madrid Madrid 28011",
    "addr:housenumber":"56",
    "addr:postcode":"madrid;28011",
    "addr:street":"Calle De Athos",
    "iso:country":"ES",
    "sg:address":"Calle de Athos, 56",
    "sg:city":"Madrid",
    "sg:orig_category":"Elementos Para Suelos Prefabricados",
    "sg:phone":"+34 914 79 41 63",
    "sg:postcode":"28011",
    "sg:province":"Madrid",
    "wof:name":"Lozano Fernandez Ramon",
    "wof:placetype":"venue"
},
  "geometry": {"coordinates":[-3.7320673466,40.4063644409],"type":"Point"}
}