{
  "type": "Feature",
  "properties": {
    "iso:country":"ES",
    "sg:address":"Calle de Julio Garcia Condoy, 36",
    "sg:city":"Zaragoza",
    "sg:orig_category":"Edici\u00d3n De Diarios, Revistas, Boletines",
    "sg:phone":"+34 976 10 60 73",
    "sg:postcode":"50018",
    "sg:province":"Zaragoza",
    "wof:name":"Europea De Derecho S.a.",
    "wof:placetype":"venue"
},
  "geometry": {"coordinates":[-0.8847140074,41.6744918823],"type":"Point"}
}