{
  "type": "Feature",
  "properties": {
    "iso:country":"ES",
    "sg:address":"Calle de Privilegio De La Union, 18",
    "sg:city":"Zaragoza",
    "sg:orig_category":"Empresas De Carpinter\u00cda",
    "sg:phone":"+34 976 42 14 54",
    "sg:postcode":"50013",
    "sg:province":"Zaragoza",
    "wof:name":"Talleres Bimesa S.c.v.",
    "wof:placetype":"venue"
},
  "geometry": {"coordinates":[-0.8720690012,41.6420516968],"type":"Point"}
}