{
  "type": "Feature",
  "properties": {
    "addr:full":"Rua Castelao, 5 Pontevedra Pontevedra 36099",
    "addr:housenumber":"5",
    "addr:postcode":"36099",
    "addr:street":"Rua Castelao",
    "iso:country":"ES",
    "sg:address":"Rua Castelao, 5",
    "sg:city":"Pontevedra",
    "sg:orig_category":"Cl\u00cdnicas M\u00c9dicas",
    "sg:phone":"+34 986 86 54 00",
    "sg:postcode":"36099",
    "sg:province":"Pontevedra",
    "wof:name":"Compa\u00f1ia De Seguros Adeslas S.a.",
    "wof:placetype":"venue"
},
  "geometry": {"coordinates":[-8.6423130035,42.429851532],"type":"Point"}
}