{
  "type": "Feature",
  "properties": {
    "addr:full":"Av Sardana (de La), 1 Borges Blanques Lleida 25400",
    "addr:housenumber":"1",
    "addr:postcode":"25400",
    "addr:street":"Av Sardana De La",
    "iso:country":"ES",
    "sg:address":"Av Sardana (de La), 1",
    "sg:city":"Borges Blanques",
    "sg:orig_category":"Electrodom\u00c9sticos (al Por Menor)",
    "sg:phone":"+34 973 14 34 56",
    "sg:postcode":"25400",
    "sg:province":"Lleida",
    "wof:name":"Xifre Herrera Maria Carme",
    "wof:placetype":"venue"
},
  "geometry": {"coordinates":[0.8681607246,41.5183296204],"type":"Point"}
}