{
  "type": "Feature",
  "properties": {
    "addr:full":"Calle de Genova, 15 Madrid Madrid 28004",
    "addr:housenumber":"15",
    "addr:postcode":"madrid;28004",
    "addr:street":"Calle De Genova",
    "iso:country":"ES",
    "sg:address":"Calle de Genova, 15",
    "sg:city":"Madrid",
    "sg:orig_category":"Notarios",
    "sg:phone":"+34 913 19 06 08",
    "sg:postcode":"28004",
    "sg:province":"Madrid",
    "wof:name":"Gomez Valdivieso Jose Ignacio",
    "wof:placetype":"venue"
},
  "geometry": {"coordinates":[-3.693770647,40.4266700745],"type":"Point"}
}