{
  "type": "Feature",
  "properties": {
    "iso:country":"ES",
    "sg:address":"Pje Embalse Del Viboras, S/n",
    "sg:city":"Las Casillas",
    "sg:orig_category":"Aguas (distribuci\u00d3n, Servicios)",
    "sg:phone":"+34 953 55 82 11",
    "sg:postcode":"23614",
    "sg:province":"Ja\u00e9n",
    "wof:name":"Confederacion Hidrografica Del Guadalquivir",
    "wof:placetype":"venue"
},
  "geometry": {"coordinates":[-3.984746933,37.6445198059],"type":"Point"}
}