{
  "type": "Feature",
  "properties": {
    "iso:country":"ES",
    "sg:address":"Rua Paraguay, 5",
    "sg:city":"Vigo",
    "sg:orig_category":"Herboristas (al Por Menor)",
    "sg:phone":"+34 986 41 99 60",
    "sg:postcode":"36204",
    "sg:province":"Pontevedra",
    "wof:name":"Las Hierbas Salvajes De Vigo S. L.",
    "wof:placetype":"venue"
},
  "geometry": {"coordinates":[-8.7164011002,42.2329788208],"type":"Point"}
}