{
  "type": "Feature",
  "properties": {
    "addr:full":"Ctra Circunvalacion, 2 Martina Le\u00f3n 24400",
    "addr:housenumber":"2",
    "addr:postcode":"24400",
    "addr:street":"Ctra Circunvalacion;Leo\u0301N",
    "iso:country":"ES",
    "sg:address":"Ctra Circunvalacion, 2",
    "sg:city":"Martina",
    "sg:orig_category":"Hormigonados",
    "sg:phone":"+34 987 41 82 21",
    "sg:postcode":"24400",
    "sg:province":"Le\u00f3n",
    "wof:name":"Canteras Industriales Del Bierzo S.a.",
    "wof:placetype":"venue"
},
  "geometry": {"coordinates":[-6.5983390808,42.5483360291],"type":"Point"}
}