{
  "type": "Feature",
  "properties": {
    "addr:full":"Calle de Sauce, 24 Torrejon Ardoz Madrid 28850",
    "addr:housenumber":"24",
    "addr:postcode":"28850",
    "addr:street":"Calle De Sauce",
    "iso:country":"ES",
    "sg:address":"Calle de Sauce, 24",
    "sg:city":"Torrejon Ardoz",
    "sg:orig_category":"Galvanizaci\u00d3n, Esta\u00d1ado, Emplomado",
    "sg:phone":"+34 916 75 25 44",
    "sg:postcode":"28850",
    "sg:province":"Madrid",
    "wof:name":"Brokermet S.l.",
    "wof:placetype":"venue"
},
  "geometry": {"coordinates":[-3.456690073,40.4520683289],"type":"Point"}
}