{
  "type": "Feature",
  "properties": {
    "addr:full":"Avda Doctor Galvez Ginachero, 29 Malaga M\u00e1laga 29009",
    "addr:housenumber":"29",
    "addr:postcode":"29009",
    "addr:street":"Avda Doctor Galvez Ginachero;Ma\u0301Laga",
    "iso:country":"ES",
    "sg:address":"Avda Doctor Galvez Ginachero, 29",
    "sg:city":"Malaga",
    "sg:orig_category":"Asociaciones, Organismos Culturales Y Socioeducativos",
    "sg:phone":"+34 952 39 31 21",
    "sg:postcode":"29009",
    "sg:province":"M\u00e1laga",
    "wof:name":"A.u.g.c.",
    "wof:placetype":"venue"
},
  "geometry": {"coordinates":[-4.4298906326,36.7269363403],"type":"Point"}
}