{
  "type": "Feature",
  "properties": {
    "addr:full":"Ctra. Moralzarzal A Cerceda, Km. 0000,4 Cerceda Madrid 28412",
    "addr:postcode":"28412",
    "addr:street":"Ctra. Moralzarzal A Cerceda Km. 0000,4",
    "iso:country":"ES",
    "sg:address":"Ctra. Moralzarzal A Cerceda, Km. 0000,4",
    "sg:city":"Cerceda",
    "sg:orig_category":"Hormig\u00d3n (m\u00c1quinas E Instalaci\u00d3n)",
    "sg:phone":"+34 918 52 93 11",
    "sg:postcode":"28412",
    "sg:province":"Madrid",
    "wof:name":"Sanz Salgado S.l.",
    "wof:placetype":"venue"
},
  "geometry": {"coordinates":[-3.9373989105,40.699546814],"type":"Point"}
}