{
  "type": "Feature",
  "properties": {
    "iso:country":"ES",
    "sg:address":"Calle de Cirilo Amoros, 59",
    "sg:city":"Valencia",
    "sg:orig_category":"Bancos",
    "sg:phone":"+34 963 52 03 53",
    "sg:postcode":"46004",
    "sg:province":"Valencia",
    "sg:website":"www.bancopopular.es",
    "wof:name":"Banco Popular Espa\u00d1ol S.a.",
    "wof:placetype":"venue"
},
  "geometry": {"coordinates":[-0.3692600131,39.4684181213],"type":"Point"}
}