{
  "type": "Feature",
  "properties": {
    "addr:full":"Cmno Juncal (del), 2 Alcala Henares Madrid 28802",
    "addr:housenumber":"2",
    "addr:postcode":"28802",
    "addr:street":"Cmno Juncal Del",
    "iso:country":"ES",
    "sg:address":"Cmno Juncal (del), 2",
    "sg:city":"Alcala Henares",
    "sg:orig_category":"T\u00c9cnicos Veterinarios",
    "sg:phone":"+34 918 80 65 62",
    "sg:postcode":"28802",
    "sg:province":"Madrid",
    "wof:name":"Ordo\u00f1ez Soblechero Rocio",
    "wof:placetype":"venue"
},
  "geometry": {"coordinates":[-3.3731739521,40.4806480408],"type":"Point"}
}