{
  "type": "Feature",
  "properties": {
    "addr:full":"Avda Alfonso R. Castelao, 69 Calle Pontevedra 36690",
    "addr:housenumber":"69",
    "addr:postcode":"36690",
    "addr:street":"Avda Alfonso R. Castelao;Calle Pontevedra",
    "iso:country":"ES",
    "sg:address":"Avda Alfonso R. Castelao, 69",
    "sg:city":"Calle",
    "sg:orig_category":"Mec\u00c1nico Del Autom\u00d3vil",
    "sg:phone":"+34 986 70 01 61",
    "sg:postcode":"36690",
    "sg:province":"Pontevedra",
    "wof:name":"Crespo Rodriguez Manuel",
    "wof:placetype":"venue"
},
  "geometry": {"coordinates":[-8.6055440903,42.3392410278],"type":"Point"}
}