{
  "type": "Feature",
  "properties": {
    "iso:country":"ES",
    "sg:address":"Carrer de Camelies, 61",
    "sg:city":"Barcelona",
    "sg:orig_category":"Mec\u00c1nico Del Autom\u00d3vil",
    "sg:phone":"+34 932 19 36 81",
    "sg:postcode":"08024",
    "sg:province":"Barcelona",
    "wof:name":"Palo Mesa Jesus",
    "wof:placetype":"venue"
},
  "geometry": {"coordinates":[2.1626269817,41.4131240845],"type":"Point"}
}