{
  "type": "Feature",
  "properties": {
    "iso:country":"ES",
    "sg:address":"Calle de Bonifaz, 9",
    "sg:city":"Santander",
    "sg:orig_category":"Venta, Instalaci\u00d3n De Cocinas",
    "sg:phone":"+34 942 22 51 76",
    "sg:postcode":"39003",
    "sg:province":"Cantabria",
    "wof:name":"Quintanilla Arnaiz Francisco Javier",
    "wof:placetype":"venue"
},
  "geometry": {"coordinates":[-3.7980484962,43.4639282227],"type":"Point"}
}