{
  "type": "Feature",
  "properties": {
    "iso:country":"ES",
    "sg:address":"Blasco Garay, 21",
    "sg:city":"Villalbilla",
    "sg:orig_category":"Montaje (empresas De)",
    "sg:phone":"+34 918 84 60 34",
    "sg:postcode":"28810",
    "sg:province":"Madrid",
    "wof:name":"Decoracion Stands Villalbilla S.s.l.",
    "wof:placetype":"venue"
},
  "geometry": {"coordinates":[-3.3158690929,40.4389038086],"type":"Point"}
}