{
  "type": "Feature",
  "properties": {
    "iso:country":"ES",
    "sg:address":"R. Cajal, 14",
    "sg:city":"Albox",
    "sg:orig_category":"Mec\u00c1nico Del Autom\u00d3vil",
    "sg:phone":"+34 950 43 00 60",
    "sg:postcode":"04800",
    "sg:province":"Almer\u00eda",
    "wof:name":"Liria Lopez Jose",
    "wof:placetype":"venue"
},
  "geometry": {"coordinates":[-2.1489620209,37.388217926],"type":"Point"}
}