{
  "type": "Feature",
  "properties": {
    "iso:country":"ES",
    "sg:address":"Bo. Sierra, S/n",
    "sg:city":"Barreda",
    "sg:orig_category":"Centros De Educaci\u00d3n Especial",
    "sg:phone":"+34 942 88 43 74",
    "sg:postcode":"39300",
    "sg:province":"Cantabria",
    "wof:name":"Colegio Publico Pintor Manuel Lia\u00f1o",
    "wof:placetype":"venue"
},
  "geometry": {"coordinates":[-4.0520391464,43.34897995],"type":"Point"}
}