{
  "type": "Feature",
  "properties": {
    "addr:full":"Pla\u00c7 Josep Roca, S/n Peramola Lleida 25790",
    "addr:housenumber":"s / n",
    "addr:postcode":"25790",
    "iso:country":"ES",
    "sg:address":"Pla\u00c7 Josep Roca, S/n",
    "sg:city":"Peramola",
    "sg:orig_category":"Ense\u00d1anza, Formaci\u00d3n Profesional: Aprendizaje",
    "sg:phone":"+34 973 46 30 04",
    "sg:postcode":"25790",
    "sg:province":"Lleida",
    "wof:name":"Ajuntament De Peramola",
    "wof:placetype":"venue"
},
  "geometry": {"coordinates":[1.267334938,42.0585784912],"type":"Point"}
}