{
  "type": "Feature",
  "properties": {
    "addr:full":"Calle de Ximenez Sandoval, 7 Venta De Ba\u00e7os Palencia 34200",
    "addr:housenumber":"7",
    "addr:postcode":"34200",
    "addr:street":"Calle De Ximenez Sandoval",
    "iso:country":"ES",
    "sg:address":"Calle de Ximenez Sandoval, 7",
    "sg:city":"Venta De Ba\u00e7os",
    "sg:orig_category":"Transporte En General",
    "sg:phone":"+34 979 77 07 27",
    "sg:postcode":"34200",
    "sg:province":"Palencia",
    "wof:name":"Distribuidora Internacional De Alimentacion S.a.",
    "wof:placetype":"venue"
},
  "geometry": {"coordinates":[-4.489068985,41.9193916321],"type":"Point"}
}