{
  "type": "Feature",
  "properties": {
    "iso:country":"ES",
    "sg:address":"Calle de Ezcurdia, 116",
    "sg:city":"Gijon",
    "sg:orig_category":"Tintes (fabricaci\u00d3n, Al Por Mayor)",
    "sg:phone":"+34 985 36 89 27",
    "sg:postcode":"33202",
    "sg:province":"Asturias",
    "wof:name":"Garcia Alvarez Maria Laura",
    "wof:placetype":"venue"
},
  "geometry": {"coordinates":[-5.6503992081,43.5384216309],"type":"Point"}
}