{
  "type": "Feature",
  "properties": {
    "addr:full":"Avda Maritima (coloradas Las), 35 Coloradas Las Palmas 35580",
    "addr:housenumber":"35",
    "addr:postcode":"35580",
    "addr:street":"Avda Maritima Coloradas Las",
    "iso:country":"ES",
    "sg:address":"Avda Maritima (coloradas Las), 35",
    "sg:city":"Coloradas",
    "sg:orig_category":"Ropa Para Se\u00d1oras Y Caballeros (al Por Menor)",
    "sg:phone":"+34 928 34 90 93",
    "sg:postcode":"35580",
    "sg:province":"Las Palmas",
    "wof:name":"Almacenes Ferrer S.a.",
    "wof:placetype":"venue"
},
  "geometry": {"coordinates":[-15.4300060272,28.1248226166],"type":"Point"}
}