{
  "type": "Feature",
  "properties": {
    "addr:full":"Calle de Maria Jordan, 7 Valencia Valencia 46018",
    "addr:housenumber":"7",
    "addr:postcode":"46018",
    "addr:street":"Calle De Maria Jordan",
    "iso:country":"ES",
    "sg:address":"Calle de Maria Jordan, 7",
    "sg:city":"Valencia",
    "sg:orig_category":"Arquitectos",
    "sg:phone":"+34 963 57 21 70",
    "sg:postcode":"46018",
    "sg:province":"Valencia",
    "wof:name":"Albert Alcina Francisco",
    "wof:placetype":"venue"
},
  "geometry": {"coordinates":[-0.3927263916,39.4608879089],"type":"Point"}
}