{
  "type": "Feature",
  "properties": {
    "addr:full":"Avda Primero De Mayo, 13 Valle Trapaga Vizcaya 48510",
    "addr:housenumber":"13",
    "addr:postcode":"48510",
    "addr:street":"Avda Primero De Mayo;Trapaga",
    "iso:country":"ES",
    "sg:address":"Avda Primero De Mayo, 13",
    "sg:city":"Valle Trapaga",
    "sg:orig_category":"Molduras, Junquillos, Listones Y Molduras Perforadas",
    "sg:phone":"+34 944 86 24 32",
    "sg:postcode":"48510",
    "sg:province":"Vizcaya",
    "wof:name":"Herrera Cortes Juan Francisco",
    "wof:placetype":"venue"
},
  "geometry": {"coordinates":[-3.0357449055,43.3035354614],"type":"Point"}
}