{
  "type": "Feature",
  "properties": {
    "addr:full":"Calle de Barcelona, 5 Sant Mateu Castell\u00f3n 12170",
    "addr:housenumber":"5",
    "addr:postcode":"12170",
    "addr:street":"Calle De Barcelona",
    "iso:country":"ES",
    "sg:address":"Calle de Barcelona, 5",
    "sg:city":"Sant Mateu",
    "sg:orig_category":"Quiropr\u00c1cticos",
    "sg:phone":"+34 964 41 67 17",
    "sg:postcode":"12170",
    "sg:province":"Castell\u00f3n",
    "wof:name":"Haral Manuel Pauw",
    "wof:placetype":"venue"
},
  "geometry": {"coordinates":[0.1805641055,40.4658546448],"type":"Point"}
}