{
  "type": "Feature",
  "properties": {
    "iso:country":"ES",
    "sg:address":"Avda Alcalde Miguel Casta\u00d1o, 117",
    "sg:city":"Le\u00f3n",
    "sg:orig_category":"Autob\u00das (explotaci\u00d3n Y Servicios De)",
    "sg:phone":"+34 987 25 25 60",
    "sg:postcode":"24005",
    "sg:province":"Le\u00f3n",
    "wof:name":"Hermanos Vivas Santander S.a.",
    "wof:placetype":"venue"
},
  "geometry": {"coordinates":[-5.5576791763,42.5844268799],"type":"Point"}
}