{
  "type": "Feature",
  "properties": {
    "iso:country":"ES",
    "sg:address":"Calle de Cordoba (de), 32",
    "sg:city":"Colmenar Viejo",
    "sg:orig_category":"Comit\u00c9s De Organizaci\u00d3n De Exposiciones, Ferias, Salones",
    "sg:phone":"+34 918 45 95 89",
    "sg:postcode":"28770",
    "sg:province":"Madrid",
    "sg:website":"www.feriaint-bilbao.es",
    "wof:name":"Bilbao Exhibition Centre S.a.",
    "wof:placetype":"venue"
},
  "geometry": {"coordinates":[-3.7807838917,40.6700553894],"type":"Point"}
}