{
  "type": "Feature",
  "properties": {
    "iso:country":"ES",
    "sg:address":"Calle de Palleter, 6",
    "sg:city":"Xirivella",
    "sg:orig_category":"Caf\u00c9s, Bares, Cervecer\u00cdas",
    "sg:phone":"+34 963 70 80 32",
    "sg:postcode":"46950",
    "sg:province":"Valencia",
    "wof:name":"Romero Mata Emiliano",
    "wof:placetype":"venue"
},
  "geometry": {"coordinates":[-0.4217199981,39.4643783569],"type":"Point"}
}