{
  "type": "Feature",
  "properties": {
    "iso:country":"ES",
    "sg:address":"Carrer de Tajo, 69",
    "sg:city":"Barcelona",
    "sg:orig_category":"Zapatos (al Por Menor)",
    "sg:phone":"+34 934 29 49 82",
    "sg:postcode":"08032",
    "sg:province":"Barcelona",
    "wof:name":"Gomez Lopez Juan",
    "wof:placetype":"venue"
},
  "geometry": {"coordinates":[2.1602649689,41.4295272827],"type":"Point"}
}