{
  "type": "Feature",
  "properties": {
    "addr:full":"Calle de Infantes, 1 Santa Amalia Badajoz 06410",
    "addr:housenumber":"1",
    "addr:postcode":"06410",
    "addr:street":"Calle De Infantes;Santa Amalia",
    "iso:country":"ES",
    "sg:address":"Calle de Infantes, 1",
    "sg:city":"Santa Amalia",
    "sg:orig_category":"Reposter\u00cdas",
    "sg:phone":"+34 924 83 00 72",
    "sg:postcode":"06410",
    "sg:province":"Badajoz",
    "wof:name":"Tena Gallego Manuel",
    "wof:placetype":"venue"
},
  "geometry": {"coordinates":[-6.0138778687,39.0124473572],"type":"Point"}
}