{
  "type": "Feature",
  "properties": {
    "addr:full":"Calle de Montes De Barbanza, 27 Madrid Madrid 28031",
    "addr:housenumber":"27",
    "addr:postcode":"madrid;28031",
    "addr:street":"Calle De Montes De Barbanza",
    "iso:country":"ES",
    "sg:address":"Calle de Montes De Barbanza, 27",
    "sg:city":"Madrid",
    "sg:orig_category":"Papeler\u00cdas: Art\u00cdculos (al Por Mayor)",
    "sg:phone":"+34 913 32 23 66",
    "sg:postcode":"28031",
    "sg:province":"Madrid",
    "sg:website":"www.carlin.es",
    "wof:name":"Tecnologia Del Dise\u00f1o Manufacturado Y Decoracion S.a.",
    "wof:placetype":"venue"
},
  "geometry": {"coordinates":[-3.6196780205,40.376701355],"type":"Point"}
}