{
  "type": "Feature",
  "properties": {
    "iso:country":"ES",
    "sg:address":"Avgd Sanchis Guarner, 10",
    "sg:city":"Picanya",
    "sg:orig_category":"Centros Empresariales",
    "sg:phone":"+34 961 59 04 42",
    "sg:postcode":"46210",
    "sg:province":"Valencia",
    "wof:name":"Montesa Puchau Jorge Miguel",
    "wof:placetype":"venue"
},
  "geometry": {"coordinates":[-0.4336169958,39.435836792],"type":"Point"}
}