{
  "type": "Feature",
  "properties": {
    "addr:full":"Ctra. Silla A Alborache, Km. 0018,4 Picassent Valencia 46220",
    "addr:postcode":"46220",
    "addr:street":"Ctra. Silla A Alborache Km. 0018,4",
    "iso:country":"ES",
    "sg:address":"Ctra. Silla A Alborache, Km. 0018,4",
    "sg:city":"Picassent",
    "sg:orig_category":"Distribuci\u00d3n De Petr\u00d3leo Y Derivados",
    "sg:phone":"+34 961 24 03 73",
    "sg:postcode":"46220",
    "sg:province":"Valencia",
    "wof:name":"Oilinvest Espa\u00f1a S.a.",
    "wof:placetype":"venue"
},
  "geometry": {"coordinates":[-0.4595290124,39.3631401062],"type":"Point"}
}