{
  "type": "Feature",
  "properties": {
    "addr:full":"Calle de Malaga, 2 Campillos M\u00e1laga 29320",
    "addr:housenumber":"2",
    "addr:postcode":"29320",
    "addr:street":"Calle De Malaga",
    "iso:country":"ES",
    "sg:address":"Calle de Malaga, 2",
    "sg:city":"Campillos",
    "sg:orig_category":"Asesor\u00cda Fiscal Y Jur\u00cddica",
    "sg:phone":"+34 952 72 21 05",
    "sg:postcode":"29320",
    "sg:province":"M\u00e1laga",
    "wof:name":"Corral Sanchez Francisco Jesus",
    "wof:placetype":"venue"
},
  "geometry": {"coordinates":[-4.8670592308,37.0477104187],"type":"Point"}
}