{
  "type": "Feature",
  "properties": {
    "addr:full":"Calle de Collado De Cerro Malejo, 8 Madrid Madrid 28035",
    "addr:housenumber":"8",
    "addr:postcode":"madrid;28035",
    "addr:street":"Calle De Collado De Cerro Malejo",
    "iso:country":"ES",
    "sg:address":"Calle de Collado De Cerro Malejo, 8",
    "sg:city":"Madrid",
    "sg:orig_category":"Inform\u00c1tica (estudios, Servicios, Asesor\u00cda, Formaci\u00d3n)",
    "sg:phone":"+34 913 76 34 19",
    "sg:postcode":"28035",
    "sg:province":"Madrid",
    "sg:website":"www.soluinfocom.net",
    "wof:name":"Alves Sequeira Ana Maria",
    "wof:placetype":"venue"
},
  "geometry": {"coordinates":[-3.7184522152,40.4890937805],"type":"Point"}
}