{
  "type": "Feature",
  "properties": {
    "addr:full":"Avda Arroyo De Los Angeles, S/n Malaga M\u00e1laga 29011",
    "addr:housenumber":"s",
    "addr:postcode":"29011",
    "addr:street":"Avda Arroyo De Los;/ N;Ma\u0301Laga",
    "iso:country":"ES",
    "sg:address":"Avda Arroyo De Los Angeles, S/n",
    "sg:city":"Malaga",
    "sg:orig_category":"Asociaciones Humanitarias, De Cooperaci\u00d3n, De Acci\u00d3n Social",
    "sg:phone":"+34 952 30 73 62",
    "sg:postcode":"29011",
    "sg:province":"M\u00e1laga",
    "wof:name":"Asociacion Espa\u00d1ola Contra El Cancer",
    "wof:placetype":"venue"
},
  "geometry": {"coordinates":[-4.4343996048,36.7300109863],"type":"Point"}
}