{
  "type": "Feature",
  "properties": {
    "iso:country":"ES",
    "sg:address":"Avda Andalucia (de), 4",
    "sg:city":"Montilla",
    "sg:orig_category":"Arquitectos",
    "sg:phone":"+34 957 65 14 31",
    "sg:postcode":"14550",
    "sg:province":"C\u00f3rdoba",
    "wof:name":"Ruz Hidalgo Jose",
    "wof:placetype":"venue"
},
  "geometry": {"coordinates":[-4.6422228813,37.584148407],"type":"Point"}
}