{
  "type": "Feature",
  "properties": {
    "addr:full":"Avda Juan Grande De, S/n Malaga M\u00e1laga 29014",
    "addr:postcode":"29014",
    "addr:street":"Avda Juan Grande De S / N;Ma\u0301Laga",
    "iso:country":"ES",
    "sg:address":"Avda Juan Grande De, S/n",
    "sg:city":"Malaga",
    "sg:orig_category":"Agencias Y Agentes Comerciales, Representantes",
    "sg:phone":"+34 952 26 53 14",
    "sg:postcode":"29014",
    "sg:province":"M\u00e1laga",
    "wof:name":"Carnero Arroyo Juan Antonio",
    "wof:placetype":"venue"
},
  "geometry": {"coordinates":[-4.4241552353,36.7566223145],"type":"Point"}
}