{
  "type": "Feature",
  "properties": {
    "addr:full":"Calle de Legion Vii, 4 Le\u00f3n Le\u00f3n 24003",
    "addr:housenumber":"4",
    "addr:postcode":"24003",
    "addr:street":"Calle De Legion Vii;Leo\u0301N",
    "iso:country":"ES",
    "sg:address":"Calle de Legion Vii, 4",
    "sg:city":"Le\u00f3n",
    "sg:orig_category":"M\u00c9dicos: Estomatolog\u00cda",
    "sg:phone":"+34 987 22 74 29",
    "sg:postcode":"24003",
    "sg:province":"Le\u00f3n",
    "sg:website":"www.paginasamarillas.es",
    "wof:name":"Canseco De Las Vallinas Octavio",
    "wof:placetype":"venue"
},
  "geometry": {"coordinates":[-5.5717329979,42.5972824097],"type":"Point"}
}