{
  "type": "Feature",
  "properties": {
    "addr:full":"Calle de Cuenca, 16 Minglanilla Cuenca 16260",
    "addr:housenumber":"16",
    "addr:postcode":"16260",
    "addr:street":"Calle De Cuenca",
    "iso:country":"ES",
    "sg:address":"Calle de Cuenca, 16",
    "sg:city":"Minglanilla",
    "sg:orig_category":"Promotores Constructores",
    "sg:phone":"+34 962 18 72 58",
    "sg:postcode":"16260",
    "sg:province":"Cuenca",
    "wof:name":"Construcciones Arpicon S.l.",
    "wof:placetype":"venue"
},
  "geometry": {"coordinates":[-1.5982160568,39.5364341736],"type":"Point"}
}