{
  "type": "Feature",
  "properties": {
    "addr:full":"Calle de Barranquillo, 2 Cristianos Santa Cruz De Tenerife 38650",
    "addr:housenumber":"2",
    "addr:postcode":"38650",
    "addr:street":"Calle De Barranquillo",
    "iso:country":"ES",
    "sg:address":"Calle de Barranquillo, 2",
    "sg:city":"Cristianos",
    "sg:orig_category":"Centros De Coordinaci\u00d3n",
    "sg:phone":"+34 922 75 32 40",
    "sg:postcode":"38650",
    "sg:province":"Santa Cruz De Tenerife",
    "sg:website":"www.asesoriaclavijo.com",
    "wof:name":"Promogestion Morantes S.l.",
    "wof:placetype":"venue"
},
  "geometry": {"coordinates":[-16.7169818878,28.0523586273],"type":"Point"}
}