{
  "type": "Feature",
  "properties": {
    "iso:country":"ES",
    "sg:address":"Av Gava, 38",
    "sg:city":"Viladecans",
    "sg:orig_category":"Televisi\u00d3n, V\u00cddeo: Aparatos Y Accesorios (venta)",
    "sg:phone":"+34 936 37 57 58",
    "sg:postcode":"08840",
    "sg:province":"Barcelona",
    "wof:name":"Tanaki Espa\u00f1a S.a.",
    "wof:placetype":"venue"
},
  "geometry": {"coordinates":[2.0144400597,41.3114318848],"type":"Point"}
}