{
  "type": "Feature",
  "properties": {
    "addr:full":"Calle de Laguardia, 3 Ba\u00e7os De Ebro \u00c1lava 01307",
    "addr:housenumber":"3",
    "addr:postcode":"01307",
    "addr:street":"Calle De Laguardia",
    "iso:country":"ES",
    "sg:address":"Calle de Laguardia, 3",
    "sg:city":"Ba\u00e7os De Ebro",
    "sg:orig_category":"Centros M\u00c9dicos Y Sociales, Dispensarios",
    "sg:phone":"+34 945 60 90 81",
    "sg:postcode":"01307",
    "sg:province":"\u00c1lava",
    "wof:name":"Ayuntamiento De Ba\u00f1os De Ebro",
    "wof:placetype":"venue"
},
  "geometry": {"coordinates":[-2.6983869076,42.9099998474],"type":"Point"}
}