{
  "type": "Feature",
  "properties": {
    "addr:full":"Casti\u00f1eiro(andoio), 31 Casti\u00f1eiro La Coru\u00f1a 15684",
    "addr:housenumber":"31",
    "addr:postcode":"15684",
    "addr:street":"Andoio;La Corun\u0303A",
    "iso:country":"ES",
    "sg:address":"Casti\u00f1eiro(andoio), 31",
    "sg:city":"Casti\u00f1eiro",
    "sg:orig_category":"Zapatos (al Por Menor)",
    "sg:phone":"+34 981 69 26 75",
    "sg:postcode":"15684",
    "sg:province":"La Coru\u00f1a",
    "wof:name":"Gonzalez Se\u00f1aris Jose Manuel",
    "wof:placetype":"venue"
},
  "geometry": {"coordinates":[-8.5861663818,43.1389961243],"type":"Point"}
}