{
  "type": "Feature",
  "properties": {
    "iso:country":"ES",
    "sg:address":"Calle de Ansar, 46",
    "sg:city":"Madrid",
    "sg:orig_category":"Venta, Instalaci\u00d3n, Reparaci\u00d3n De Antenas Para Televisi\u00d3n",
    "sg:phone":"+34 914 79 02 74",
    "sg:postcode":"28047",
    "sg:province":"Madrid",
    "wof:name":"Lopez De La Fuente Evaristo",
    "wof:placetype":"venue"
},
  "geometry": {"coordinates":[-3.7412695885,40.4039802551],"type":"Point"}
}