{
  "type": "Feature",
  "properties": {
    "addr:full":"Calle de Calvario, 6 Olvera C\u00e1diz 11690",
    "addr:housenumber":"6",
    "addr:postcode":"11690",
    "addr:street":"Calle De Calvario;Ca\u0301Diz",
    "iso:country":"ES",
    "sg:address":"Calle de Calvario, 6",
    "sg:city":"Olvera",
    "sg:orig_category":"Farmacias",
    "sg:phone":"+34 956 13 07 94",
    "sg:postcode":"11690",
    "sg:province":"C\u00e1diz",
    "wof:name":"Cortina Mallol Miguel Angel",
    "wof:placetype":"venue"
},
  "geometry": {"coordinates":[-5.2623009682,36.9353942871],"type":"Point"}
}