{
  "type": "Feature",
  "properties": {
    "iso:country":"ES",
    "sg:address":"Calle de Humanista Furio, 25",
    "sg:city":"Valencia",
    "sg:orig_category":"Desinfecci\u00d3n, Desinsectaci\u00d3n, Desratizaci\u00d3n",
    "sg:phone":"+34 963 55 10 77",
    "sg:postcode":"46022",
    "sg:province":"Valencia",
    "wof:name":"Beltran Cervera Francisco",
    "wof:placetype":"venue"
},
  "geometry": {"coordinates":[-0.3446210027,39.4692115784],"type":"Point"}
}