{
  "type": "Feature",
  "properties": {
    "iso:country":"ES",
    "sg:address":"Calle de Ronda, 11",
    "sg:city":"Pto Real",
    "sg:orig_category":"Asociaciones Y Clubs Deportivos",
    "sg:phone":"+34 956 83 01 75",
    "sg:postcode":"11510",
    "sg:province":"C\u00e1diz",
    "sg:website":"www.javierartero.com",
    "wof:name":"Asociacion Shotokan Karate Espa\u00d1a",
    "wof:placetype":"venue"
},
  "geometry": {"coordinates":[-6.1802425385,36.5253753662],"type":"Point"}
}