{
  "type": "Feature",
  "properties": {
    "addr:full":"Calle de Onice, 1 Salamanca Salamanca 37006",
    "addr:housenumber":"1",
    "addr:postcode":"37006",
    "addr:street":"Calle De Onice",
    "iso:country":"ES",
    "sg:address":"Calle de Onice, 1",
    "sg:city":"Salamanca",
    "sg:orig_category":"Plomeros",
    "sg:phone":"+34 923 25 39 37",
    "sg:postcode":"37006",
    "sg:province":"Salamanca",
    "wof:name":"Amaro Lago Antonio",
    "wof:placetype":"venue"
},
  "geometry": {"coordinates":[-5.6729183197,40.9733161926],"type":"Point"}
}