{
  "type": "Feature",
  "properties": {
    "iso:country":"ES",
    "sg:address":"Minas Cala Ca\u00f1av Ctra, S/n",
    "sg:city":"Cala",
    "sg:orig_category":"Empresas De Electricidad En General",
    "sg:phone":"+34 959 50 71 07",
    "sg:postcode":"21270",
    "sg:province":"Huelva",
    "wof:name":"Electrica Tentudia S. A.",
    "wof:placetype":"venue"
},
  "geometry": {"coordinates":[-6.3188099861,37.9726524353],"type":"Point"}
}