{
  "type": "Feature",
  "properties": {
    "addr:full":"Jose Luis I\u00d1arra Pasealekua, 20 Arrasate Guip\u00f9zcoa 20500",
    "addr:housenumber":"20",
    "addr:postcode":"20500",
    "addr:street":"Jose;In\u0303Arra Pasealekua;Guipu\u0300Zcoa",
    "iso:country":"ES",
    "sg:address":"Jose Luis I\u00d1arra Pasealekua, 20",
    "sg:city":"Arrasate",
    "sg:orig_category":"Empresas De Pintura Y Revestimientos",
    "sg:phone":"+34 943 79 21 72",
    "sg:postcode":"20500",
    "sg:province":"Guip\u00f9zcoa",
    "wof:name":"I\u00f1iguez Pineda Jesus",
    "wof:placetype":"venue"
},
  "geometry": {"coordinates":[-2.4870970249,43.0679626465],"type":"Point"}
}