{
  "type": "Feature",
  "properties": {
    "addr:full":"Carrer de Rafael Casanova, 19 Rubi Barcelona 08191",
    "addr:housenumber":"19",
    "addr:postcode":"08191",
    "addr:street":"Carrer De Rafael Casanova",
    "iso:country":"ES",
    "sg:address":"Carrer de Rafael Casanova, 19",
    "sg:city":"Rubi",
    "sg:orig_category":"Promotores Constructores",
    "sg:phone":"+34 935 88 51 57",
    "sg:postcode":"08191",
    "sg:province":"Barcelona",
    "wof:name":"Renda Rubi S.l.",
    "wof:placetype":"venue"
},
  "geometry": {"coordinates":[2.0314819813,41.4936714172],"type":"Point"}
}