{
  "type": "Feature",
  "properties": {
    "addr:full":"Ctra Tries, Les, 81 Olot Girona 17800",
    "addr:housenumber":"81",
    "addr:postcode":"17800",
    "addr:street":"Ctra Tries Les",
    "iso:country":"ES",
    "sg:address":"Ctra Tries, Les, 81",
    "sg:city":"Olot",
    "sg:orig_category":"Rectificaci\u00d3n, Mecanizado, Fresado",
    "sg:phone":"+34 972 26 65 04",
    "sg:postcode":"17800",
    "sg:province":"Girona",
    "wof:name":"Mecanitzats Padrosa S.l.",
    "wof:placetype":"venue"
},
  "geometry": {"coordinates":[2.5051269531,42.190120697],"type":"Point"}
}