{
  "type": "Feature",
  "properties": {
    "addr:full":"Carrer de Esglesia, 93 Calella Barcelona 08370",
    "addr:housenumber":"93",
    "addr:postcode":"08370",
    "addr:street":"Carrer De Esglesia",
    "iso:country":"ES",
    "sg:address":"Carrer de Esglesia, 93",
    "sg:city":"Calella",
    "sg:classifiers":[
        {
            "category":"Cinema",
            "subcategory":"Movie Theater",
            "type":"Entertainment"
        }
    ],
    "sg:phone":"+34 937 66 23 44",
    "sg:postcode":"08370",
    "sg:province":"Barcelona",
    "sg:tags":[
        "salas",
        "de",
        "cine"
    ],
    "wof:name":"Cidacra 21 S.l.",
    "wof:placetype":"venue"
},
  "geometry": {"coordinates":[2.6604189873,41.6143226624],"type":"Point"}
}