{
  "type": "Feature",
  "properties": {
    "addr:full":"C/ Balmes, 4 Ripollet Barcelona 08291",
    "addr:housenumber":"4",
    "addr:postcode":"08291",
    "addr:street":"C / Balmes",
    "iso:country":"ES",
    "sg:address":"C/ Balmes, 4",
    "sg:city":"Ripollet",
    "sg:orig_category":"Veh\u00cdculos De Ocasi\u00d3n",
    "sg:phone":"+34 936 92 91 02",
    "sg:postcode":"08291",
    "sg:province":"Barcelona",
    "wof:name":"Auto Y Alvez S.l.",
    "wof:placetype":"venue"
},
  "geometry": {"coordinates":[2.1574223042,41.4947433472],"type":"Point"}
}