{
  "type": "Feature",
  "properties": {
    "addr:full":"Ptge Gertrudis Artigas, 2 Sabadell Barcelona 08208",
    "addr:housenumber":"2",
    "addr:postcode":"08208",
    "addr:street":"Ptge Gertrudis Artigas",
    "iso:country":"ES",
    "sg:address":"Ptge Gertrudis Artigas, 2",
    "sg:city":"Sabadell",
    "sg:orig_category":"Agencias Y Agentes Comerciales, Representantes",
    "sg:phone":"+34 937 17 38 85",
    "sg:postcode":"08208",
    "sg:province":"Barcelona",
    "wof:name":"Comunidad De Propietarios Pasaje Gertudris Artigas 2-4",
    "wof:placetype":"venue"
},
  "geometry": {"coordinates":[2.1060600281,41.5596961975],"type":"Point"}
}