{
  "type": "Feature",
  "properties": {
    "iso:country":"ES",
    "sg:address":"Grup San Jose, 6",
    "sg:city":"Castellon",
    "sg:orig_category":"Servidores Y Editores De Bases De Datos",
    "sg:phone":"+34 964 23 01 46",
    "sg:postcode":"12005",
    "sg:province":"Castell\u00f3n",
    "sg:website":"www.simisl.com",
    "wof:name":"Servicios Informacion Impagados S.l.",
    "wof:placetype":"venue"
},
  "geometry": {"coordinates":[-0.0297400001,39.9624290466],"type":"Point"}
}