{
  "type": "Feature",
  "properties": {
    "iso:country":"ES",
    "sg:address":"Plaz Francisco Perojo Cagigas, 2",
    "sg:city":"Solares",
    "sg:orig_category":"Psic\u00d3logos",
    "sg:phone":"+34 942 52 23 24",
    "sg:postcode":"39710",
    "sg:province":"Cantabria",
    "wof:name":"Fontecilla Pellon Pilar",
    "wof:placetype":"venue"
},
  "geometry": {"coordinates":[-3.7379589081,43.3838615417],"type":"Point"}
}