{
  "type": "Feature",
  "properties": {
    "addr:full":"Carrer de Santander, 42 Barcelona Barcelona 08020",
    "addr:housenumber":"42",
    "addr:postcode":"08020",
    "addr:street":"Carrer De Santander",
    "iso:country":"ES",
    "sg:address":"Carrer de Santander, 42",
    "sg:city":"Barcelona",
    "sg:orig_category":"Serigraf\u00cda (material Y Suministros)",
    "sg:phone":"+34 932 78 28 29",
    "sg:postcode":"08020",
    "sg:province":"Barcelona",
    "sg:website":"www.fasdel.com",
    "wof:name":"Fasdel S.l.",
    "wof:placetype":"venue"
},
  "geometry": {"coordinates":[2.2019441128,41.4272117615],"type":"Point"}
}