{
  "type": "Feature",
  "properties": {
    "iso:country":"ES",
    "sg:address":"Calle de Jose Ventura, 25",
    "sg:city":"San Isidro",
    "sg:orig_category":"Entrega Y Recogida (servicios)",
    "sg:phone":"+34 922 39 30 82",
    "sg:postcode":"38611",
    "sg:province":"Santa Cruz De Tenerife",
    "wof:name":"Caller Garcia Maria Del Rosario",
    "wof:placetype":"venue"
},
  "geometry": {"coordinates":[-16.5610141754,28.0794734955],"type":"Point"}
}