{
  "type": "Feature",
  "properties": {
    "addr:full":"Culebras Cno., S/n Renedo Valladolid 47170",
    "addr:postcode":"47170",
    "addr:street":"Cno. S / N",
    "iso:country":"ES",
    "sg:address":"Culebras Cno., S/n",
    "sg:city":"Renedo",
    "sg:orig_category":"Ferreter\u00cda (diversos)",
    "sg:phone":"+34 983 50 81 56",
    "sg:postcode":"47170",
    "sg:province":"Valladolid",
    "wof:name":"Jose Maria Calvo S.l.",
    "wof:placetype":"venue"
},
  "geometry": {"coordinates":[-4.6277241707,41.6534729004],"type":"Point"}
}