{
  "type": "Feature",
  "properties": {
    "addr:full":"Calle de Alferez Verda, 9 Cabanillas Campo Guadalajara 19171",
    "addr:housenumber":"9",
    "addr:postcode":"19171",
    "addr:street":"Calle De Alferez Verda",
    "iso:country":"ES",
    "sg:address":"Calle de Alferez Verda, 9",
    "sg:city":"Cabanillas Campo",
    "sg:orig_category":"Abogados",
    "sg:phone":"+34 949 33 20 74",
    "sg:postcode":"19171",
    "sg:province":"Guadalajara",
    "wof:name":"Dominguez Soria Nuria",
    "wof:placetype":"venue"
},
  "geometry": {"coordinates":[-3.2360672951,40.6386222839],"type":"Point"}
}