{
  "type": "Feature",
  "properties": {
    "addr:full":"Ctra Nacional 430 Km 96, Km. 0307,0 Santa Amalia Badajoz 06410",
    "addr:housenumber":"km",
    "addr:postcode":"06410",
    "addr:street":"Ctra Nacional 430;96 Km. 0307,0 Santa",
    "iso:country":"ES",
    "sg:address":"Ctra Nacional 430 Km 96, Km. 0307,0",
    "sg:city":"Santa Amalia",
    "sg:orig_category":"Producci\u00d3n, Venta De Productos De Agricultura Biol\u00d3gica",
    "sg:phone":"+34 924 14 70 56",
    "sg:postcode":"06410",
    "sg:province":"Badajoz",
    "wof:name":"Bonilla Marcos Guillermo",
    "wof:placetype":"venue"
},
  "geometry": {"coordinates":[-6.0347437859,39.0760536194],"type":"Point"}
}