{
  "type": "Feature",
  "properties": {
    "iso:country":"ES",
    "sg:address":"Calle de Toca, 5",
    "sg:city":"Iscar",
    "sg:orig_category":"Barnizadores",
    "sg:phone":"+34 983 62 03 87",
    "sg:postcode":"47420",
    "sg:province":"Valladolid",
    "wof:name":"Padrones Aldea Julio",
    "wof:placetype":"venue"
},
  "geometry": {"coordinates":[-4.5416607857,41.3569526672],"type":"Point"}
}