{
  "type": "Feature",
  "properties": {
    "addr:full":"Calle de Camilo Jose Cela, 6 Laguna Duero Valladolid 47140",
    "addr:housenumber":"6",
    "addr:postcode":"47140",
    "addr:street":"Calle De Camilo Jose Cela",
    "iso:country":"ES",
    "sg:address":"Calle de Camilo Jose Cela, 6",
    "sg:city":"Laguna Duero",
    "sg:orig_category":"Empresas De Carpinter\u00cda De Madera",
    "sg:phone":"+34 983 54 38 61",
    "sg:postcode":"47140",
    "sg:province":"Valladolid",
    "wof:name":"El Prado Boyal S.a.",
    "wof:placetype":"venue"
},
  "geometry": {"coordinates":[-4.7237248421,41.5807304382],"type":"Point"}
}