{
  "type": "Feature",
  "properties": {
    "addr:full":"Calle de Julian Camarillo, 29 Madrid Madrid 28...",
    "addr:housenumber":"29;28 ...",
    "addr:postcode":"madrid",
    "addr:street":"Calle De Julian Camarillo;Madrid",
    "iso:country":"ES",
    "sg:address":"Calle de Julian Camarillo, 29",
    "sg:city":"Madrid",
    "sg:orig_category":"Servicios De Telecomunicaciones",
    "sg:phone":"+34 917 54 91 00",
    "sg:postcode":"28...",
    "sg:province":"Madrid",
    "wof:name":"Iberbanda S.a.",
    "wof:placetype":"venue"
},
  "geometry": {"coordinates":[-3.6284430027,40.4347724915],"type":"Point"}
}