{
  "type": "Feature",
  "properties": {
    "addr:full":"Calle de Pedro Bilbao, 1 Basauri Vizcaya 48970",
    "addr:housenumber":"1",
    "addr:postcode":"48970",
    "addr:street":"Calle De Pedro Bilbao",
    "iso:country":"ES",
    "sg:address":"Calle de Pedro Bilbao, 1",
    "sg:city":"Basauri",
    "sg:orig_category":"Ense\u00d1anza: Peluquer\u00cda Est\u00c9tica",
    "sg:phone":"+34 944 00 84 77",
    "sg:postcode":"48970",
    "sg:province":"Vizcaya",
    "wof:name":"Arantza Ramirez Ugarte",
    "wof:placetype":"venue"
},
  "geometry": {"coordinates":[-2.8882410526,43.2357139587],"type":"Point"}
}