{
  "type": "Feature",
  "properties": {
    "addr:full":"Calle de Jose Garcia Granda, 11 Madrid Madrid 28038",
    "addr:housenumber":"11",
    "addr:postcode":"madrid;28038",
    "addr:street":"Calle De Jose Garcia Granda",
    "iso:country":"ES",
    "sg:address":"Calle de Jose Garcia Granda, 11",
    "sg:city":"Madrid",
    "sg:orig_category":"Contenedores (mercanc\u00cdas)",
    "sg:phone":"+34 913 03 41 05",
    "sg:postcode":"28038",
    "sg:province":"Madrid",
    "wof:name":"Romera Beltran Tomas",
    "wof:placetype":"venue"
},
  "geometry": {"coordinates":[-3.6504740715,40.3931121826],"type":"Point"}
}