{
  "type": "Feature",
  "properties": {
    "iso:country":"ES",
    "sg:address":"Calle de Torre De Romo, 17",
    "sg:city":"Carmen",
    "sg:orig_category":"Librer\u00cdas",
    "sg:phone":"+34 968 34 11 43",
    "sg:postcode":"30002",
    "sg:province":"Murcia",
    "wof:name":"Maria Milagros Illescas Lucas Y Otra C.b.",
    "wof:placetype":"venue"
},
  "geometry": {"coordinates":[-1.1302499771,37.9829597473],"type":"Point"}
}