{
  "type": "Feature",
  "properties": {
    "iso:country":"ES",
    "sg:address":"Frederic Mompou(pol Ind Sud), 22",
    "sg:city":"Cardedeu",
    "sg:orig_category":"Importaci\u00d3n",
    "sg:phone":"+34 938 44 45 50",
    "sg:postcode":"08440",
    "sg:province":"Barcelona",
    "wof:name":"Persentili Internacional S. L.",
    "wof:placetype":"venue"
},
  "geometry": {"coordinates":[2.3620998859,41.6284103394],"type":"Point"}
}