{
  "type": "Feature",
  "properties": {
    "iso:country":"ES",
    "sg:address":"Ctra. Logro\u00f1o-vigo, Km. 0140,0",
    "sg:city":"Villanueva Arga\u00f1o",
    "sg:orig_category":"Cr\u00cda De Animales",
    "sg:phone":"+34 947 56 09 28",
    "sg:postcode":"09130",
    "sg:province":"Burgos",
    "wof:name":"Desarrollo Ganadero Espa\u00f1ol S. A.",
    "wof:placetype":"venue"
},
  "geometry": {"coordinates":[-3.8345999718,42.3399848938],"type":"Point"}
}