{
  "type": "Feature",
  "properties": {
    "addr:full":"Calle de Amargura (la), S/n Yunta Guadalajara 19361",
    "addr:housenumber":"/ n",
    "addr:postcode":"19361",
    "addr:street":"Calle De Amargura La S",
    "iso:country":"ES",
    "sg:address":"Calle de Amargura (la), S/n",
    "sg:city":"Yunta",
    "sg:orig_category":"Centros De Educaci\u00d3n Especial",
    "sg:phone":"+34 949 83 42 00",
    "sg:postcode":"19361",
    "sg:province":"Guadalajara",
    "wof:name":"Cra El Rincon De Castilla",
    "wof:placetype":"venue"
},
  "geometry": {"coordinates":[-1.6836563349,40.9153213501],"type":"Point"}
}