{
  "type": "Feature",
  "properties": {
    "iso:country":"ES",
    "sg:address":"Carrer de Putget, 16",
    "sg:city":"Barcelona",
    "sg:orig_category":"Agencias Y Agentes Comerciales, Representantes",
    "sg:phone":"+34 932 12 50 30",
    "sg:postcode":"08006",
    "sg:province":"Barcelona",
    "wof:name":"Sahun Ballabriga Jose Manuel",
    "wof:placetype":"venue"
},
  "geometry": {"coordinates":[2.1425030231,41.4045829773],"type":"Point"}
}