{
  "type": "Feature",
  "properties": {
    "addr:full":"Gerezpea Kalea, 8 Jundiz \u00c1lava 01015",
    "addr:housenumber":"8",
    "addr:postcode":"01015",
    "addr:street":"Gerezpea Kalea;A\u0301Lava",
    "iso:country":"ES",
    "sg:address":"Gerezpea Kalea, 8",
    "sg:city":"Jundiz",
    "sg:orig_category":"Contenedores (mercanc\u00cdas)",
    "sg:phone":"+34 945 29 10 36",
    "sg:postcode":"01015",
    "sg:province":"\u00c1lava",
    "wof:name":"Transportes Ibarra S.l.",
    "wof:placetype":"venue"
},
  "geometry": {"coordinates":[-2.7258689404,42.8387718201],"type":"Point"}
}