{
  "type": "Feature",
  "properties": {
    "iso:country":"ES",
    "sg:address":"Ctra. Cuellar, 15",
    "sg:city":"Rapariegos",
    "sg:orig_category":"Fabricaci\u00d3n De Muebles",
    "sg:phone":"+34 920 30 96 40",
    "sg:postcode":"40466",
    "sg:province":"Segovia",
    "wof:name":"Muebles Carretero S.l.",
    "wof:placetype":"venue"
},
  "geometry": {"coordinates":[-4.650633812,41.0934524536],"type":"Point"}
}