{
  "type": "Feature",
  "properties": {
    "iso:country":"ES",
    "sg:address":"Carrer de Bruc, 63",
    "sg:city":"Barcelona",
    "sg:orig_category":"Inmobiliaria (agencias)",
    "sg:phone":"+34 932 15 85 72",
    "sg:postcode":"08009",
    "sg:province":"Barcelona",
    "wof:name":"Almond Valley S.l.",
    "wof:placetype":"venue"
},
  "geometry": {"coordinates":[2.1703224182,41.3937225342],"type":"Point"}
}