{
  "type": "Feature",
  "properties": {
    "iso:country":"ES",
    "sg:address":"Calle de Carretas, 19",
    "sg:city":"Madrid",
    "sg:orig_category":"Bisuter\u00cda, Joyer\u00cda, Relojer\u00cda (al Por Menor)",
    "sg:phone":"+34 915 21 37 62",
    "sg:postcode":"28012",
    "sg:province":"Madrid",
    "wof:name":"Catalan Lopez Luis",
    "wof:placetype":"venue"
},
  "geometry": {"coordinates":[-3.7032198906,40.4157676697],"type":"Point"}
}