{
  "type": "Feature",
  "properties": {
    "iso:country":"ES",
    "sg:address":"Calle de Jose Antonio, S/n",
    "sg:city":"Pacios",
    "sg:orig_category":"Suministros Para Carrocer\u00cdas",
    "sg:phone":"+34 982 54 10 56",
    "sg:postcode":"27611",
    "sg:province":"Lugo",
    "wof:name":"Talleres Cal C.b.",
    "wof:placetype":"venue"
},
  "geometry": {"coordinates":[-7.5682868958,42.7631835938],"type":"Point"}
}