{
  "type": "Feature",
  "properties": {
    "addr:full":"Carrer de Roger De Flor, 296 Barcelona Barcelona 08025",
    "addr:housenumber":"296",
    "addr:postcode":"08025",
    "addr:street":"Carrer De Roger De Flor",
    "iso:country":"ES",
    "sg:address":"Carrer de Roger De Flor, 296",
    "sg:city":"Barcelona",
    "sg:orig_category":"Radiocomunicaciones, Telefon\u00cda M\u00d3vil, Radiomensajer\u00cda: Servicios, Comercializaci\u00d3n",
    "sg:phone":"+34 932 07 15 28",
    "sg:postcode":"08025",
    "sg:province":"Barcelona",
    "wof:name":"Namudesaher S.l.",
    "wof:placetype":"venue"
},
  "geometry": {"coordinates":[2.1661989689,41.4038734436],"type":"Point"}
}