{
  "type": "Feature",
  "properties": {
    "addr:full":"Rua San Xose, 2 Carballo La Coru\u00f1a 15100",
    "addr:housenumber":"2",
    "addr:postcode":"15100",
    "addr:street":"Rua San Xose;La Corun\u0303A",
    "iso:country":"ES",
    "sg:address":"Rua San Xose, 2",
    "sg:city":"Carballo",
    "sg:orig_category":"M\u00c9dicos: Oftalmolog\u00cda",
    "sg:phone":"+34 981 75 60 50",
    "sg:postcode":"15100",
    "sg:province":"La Coru\u00f1a",
    "wof:name":"Rodriguez Sanchez Daniel",
    "wof:placetype":"venue"
},
  "geometry": {"coordinates":[-8.689204216,43.211479187],"type":"Point"}
}