{
  "type": "Feature",
  "properties": {
    "addr:full":"Avda Blas De Otero, 34 Maracena Granada 18200",
    "addr:housenumber":"34",
    "addr:postcode":"18200",
    "addr:street":"Avda Blas De Otero",
    "iso:country":"ES",
    "sg:address":"Avda Blas De Otero, 34",
    "sg:city":"Maracena",
    "sg:orig_category":"Promotores Constructores",
    "sg:phone":"+34 958 42 00 73",
    "sg:postcode":"18200",
    "sg:province":"Granada",
    "wof:name":"Mayfo S.l.",
    "wof:placetype":"venue"
},
  "geometry": {"coordinates":[-3.6332190037,37.2105712891],"type":"Point"}
}