{
  "type": "Feature",
  "properties": {
    "iso:country":"ES",
    "sg:address":"Calle de Becerro De Bengoa, 8",
    "sg:city":"Palencia",
    "sg:orig_category":"Psic\u00d3logos",
    "sg:phone":"+34 979 70 20 91",
    "sg:postcode":"34002",
    "sg:province":"Palencia",
    "wof:name":"Moreno Palenzuela Susana",
    "wof:placetype":"venue"
},
  "geometry": {"coordinates":[-4.5316762924,42.0088768005],"type":"Point"}
}