{
  "type": "Feature",
  "properties": {
    "addr:full":"Calle de San Moises, 39 Madrid Madrid 28018",
    "addr:housenumber":"39",
    "addr:postcode":"madrid;28018",
    "addr:street":"Calle De San Moises",
    "iso:country":"ES",
    "sg:address":"Calle de San Moises, 39",
    "sg:city":"Madrid",
    "sg:orig_category":"Cultos Diversos",
    "sg:phone":"+34 915 07 38 55",
    "sg:postcode":"28018",
    "sg:province":"Madrid",
    "wof:name":"Testigos Cristianos De Jehova",
    "wof:placetype":"venue"
},
  "geometry": {"coordinates":[-3.6656830311,40.3818702698],"type":"Point"}
}