{
  "type": "Feature",
  "properties": {
    "iso:country":"ES",
    "sg:address":"Rua Redondo, 56",
    "sg:city":"Redondo",
    "sg:orig_category":"Distribuci\u00d3n De Petr\u00d3leo Y Derivados",
    "sg:phone":"+34 986 55 60 25",
    "sg:postcode":"36649",
    "sg:province":"Pontevedra",
    "wof:name":"Gasolinera Jers S.l.",
    "wof:placetype":"venue"
},
  "geometry": {"coordinates":[-8.7386341095,42.2920913696],"type":"Point"}
}