{
  "type": "Feature",
  "properties": {
    "addr:full":"Calle de Alloza, 111 Castellon Castell\u00f3n 12001",
    "addr:housenumber":"111",
    "addr:postcode":"12001",
    "addr:street":"Calle De Alloza",
    "iso:country":"ES",
    "sg:address":"Calle de Alloza, 111",
    "sg:city":"Castellon",
    "sg:orig_category":"Art\u00cdculos Funerarios (al Por Menor)",
    "sg:phone":"+34 964 20 55 20",
    "sg:postcode":"12001",
    "sg:province":"Castell\u00f3n",
    "wof:name":"Servicios Funerarios Pellicer S.l.",
    "wof:placetype":"venue"
},
  "geometry": {"coordinates":[-0.0390600003,39.9874191284],"type":"Point"}
}