{
  "type": "Feature",
  "properties": {
    "addr:full":"Calle de Moreno De Mora, 4 Linea De La Concepcion C\u00e1diz 11300",
    "addr:housenumber":"4",
    "addr:postcode":"11300",
    "addr:street":"Calle De Moreno De Mora;Ca\u0301Diz",
    "iso:country":"ES",
    "sg:address":"Calle de Moreno De Mora, 4",
    "sg:city":"Linea De La Concepcion",
    "sg:orig_category":"Venta, Montaje De Neum\u00c1ticos",
    "sg:phone":"+34 956 76 71 48",
    "sg:postcode":"11300",
    "sg:province":"C\u00e1diz",
    "wof:name":"Neumaticos El Junquillo S.l.",
    "wof:placetype":"venue"
},
  "geometry": {"coordinates":[-5.3534398079,36.1618804932],"type":"Point"}
}