{
  "type": "Feature",
  "properties": {
    "iso:country":"ES",
    "sg:address":"Laminacion(pol Ind Ingruinsa), 18",
    "sg:city":"Puerto Sagunto",
    "sg:orig_category":"T\u00c9cnicos Veterinarios",
    "sg:phone":"+34 962 67 44 14",
    "sg:postcode":"46520",
    "sg:province":"Valencia",
    "wof:name":"Global Veterinaria S.l",
    "wof:placetype":"venue"
},
  "geometry": {"coordinates":[-0.2254589945,39.6553993225],"type":"Point"}
}