{
  "type": "Feature",
  "properties": {
    "iso:country":"ES",
    "sg:address":"Calle de Conde Vallellano, 38",
    "sg:city":"Dacon",
    "sg:orig_category":"Carnicer\u00cdas, Carnicer\u00cdas",
    "sg:phone":"+34 988 27 33 75",
    "sg:postcode":"32572",
    "sg:province":"Ourense",
    "wof:name":"Otero Alvarez Manuel",
    "wof:placetype":"venue"
},
  "geometry": {"coordinates":[-8.0499277115,42.4218978882],"type":"Point"}
}