{
  "type": "Feature",
  "properties": {
    "iso:country":"ES",
    "sg:address":"Poligono Mora-garay, S/n",
    "sg:city":"Gijon",
    "sg:orig_category":"Metalurgia",
    "sg:phone":"+34 985 31 40 19",
    "sg:postcode":"33211",
    "sg:province":"Asturias",
    "wof:name":"Caldevilla Huerta Juan Carlos",
    "wof:placetype":"venue"
},
  "geometry": {"coordinates":[-5.6850991249,43.532913208],"type":"Point"}
}