{
  "type": "Feature",
  "properties": {
    "addr:full":"Calle de Pinar De Valsain, S/n Salamanca Salamanca 37008",
    "addr:housenumber":"s / n",
    "addr:postcode":"37008",
    "addr:street":"Calle De Pinar De Valsain",
    "iso:country":"ES",
    "sg:address":"Calle de Pinar De Valsain, S/n",
    "sg:city":"Salamanca",
    "sg:orig_category":"Herramientas Y Suministros Para Plomeros",
    "sg:phone":"+34 923 19 05 59",
    "sg:postcode":"37008",
    "sg:province":"Salamanca",
    "wof:name":"Tuberia Y Valvuleria Salmantina S.l.",
    "wof:placetype":"venue"
},
  "geometry": {"coordinates":[-5.6957888603,40.9548416138],"type":"Point"}
}