{
  "type": "Feature",
  "properties": {
    "iso:country":"ES",
    "sg:address":"Calle de Tejar (el), 13",
    "sg:city":"Orotava",
    "sg:orig_category":"Fabricaci\u00d3n De Art\u00cdculos Y Equipos Deportivos Y De Ocio",
    "sg:phone":"+34 922 33 07 68",
    "sg:postcode":"38300",
    "sg:province":"Santa Cruz De Tenerife",
    "wof:name":"Alrube S.l.",
    "wof:placetype":"venue"
},
  "geometry": {"coordinates":[-16.5204086304,28.3937206268],"type":"Point"}
}