{
  "type": "Feature",
  "properties": {
    "iso:country":"ES",
    "sg:address":"Ctra Campanas-puente La Reina, Km. 0022,0",
    "sg:city":"Obanos",
    "sg:orig_category":"Hormigonados",
    "sg:phone":"+34 948 39 00 03",
    "sg:postcode":"31151",
    "sg:province":"Navarra",
    "wof:name":"Hormigones Puente S.a.",
    "wof:placetype":"venue"
},
  "geometry": {"coordinates":[-1.7903590202,42.6767616272],"type":"Point"}
}