{
  "type": "Feature",
  "properties": {
    "iso:country":"ES",
    "sg:address":"Av Barbera, 27",
    "sg:city":"Sabadell",
    "sg:orig_category":"Agentes, Concesionarios Y Sucursales De Veh\u00cdculos",
    "sg:phone":"+34 937 20 52 81",
    "sg:postcode":"08203",
    "sg:province":"Barcelona",
    "wof:name":"Talleres Santi Enrique S.a.",
    "wof:placetype":"venue"
},
  "geometry": {"coordinates":[2.1129961014,41.5388946533],"type":"Point"}
}