{
  "type": "Feature",
  "properties": {
    "addr:full":"Avda Pio Xii, S/n Motril Granada 18600",
    "addr:housenumber":"s / n",
    "addr:postcode":"18600",
    "addr:street":"Avda Pio Xii",
    "iso:country":"ES",
    "sg:address":"Avda Pio Xii, S/n",
    "sg:city":"Motril",
    "sg:orig_category":"Sindicatos De Trabajadores",
    "sg:phone":"+34 958 82 48 24",
    "sg:postcode":"18600",
    "sg:province":"Granada",
    "wof:name":"Confederacion General Del Trabajo Cgt",
    "wof:placetype":"venue"
},
  "geometry": {"coordinates":[-3.5143449306,36.7461853027],"type":"Point"}
}