{
  "type": "Feature",
  "properties": {
    "addr:full":"Germans Llobet, 9 Gandia Valencia 46700",
    "addr:housenumber":"9",
    "addr:postcode":"46700",
    "addr:street":"Llobet;Valencia",
    "iso:country":"ES",
    "sg:address":"Germans Llobet, 9",
    "sg:city":"Gandia",
    "sg:orig_category":"Prot\u00c9sicos Dentales",
    "sg:phone":"+34 962 86 34 99",
    "sg:postcode":"46700",
    "sg:province":"Valencia",
    "wof:name":"Pelayo Fernandez Jose",
    "wof:placetype":"venue"
},
  "geometry": {"coordinates":[-0.1736280024,38.9775352478],"type":"Point"}
}