{
  "type": "Feature",
  "properties": {
    "addr:full":"Carr Major, 1 Campdevanol Girona 17530",
    "addr:housenumber":"1",
    "addr:postcode":"17530",
    "addr:street":"Carr Major",
    "iso:country":"ES",
    "sg:address":"Carr Major, 1",
    "sg:city":"Campdevanol",
    "sg:orig_category":"Carnicer\u00cdas, Carnicer\u00cdas",
    "sg:phone":"+34 972 73 00 98",
    "sg:postcode":"17530",
    "sg:province":"Girona",
    "wof:name":"Camprubi Basaga\u00f1a Ramon",
    "wof:placetype":"venue"
},
  "geometry": {"coordinates":[2.1704668999,42.2252960205],"type":"Point"}
}