{
  "type": "Feature",
  "properties": {
    "addr:full":"Calle de Ansite, 88 Cruce De Arinaga Las Palmas 35118",
    "addr:housenumber":"88",
    "addr:postcode":"35118",
    "addr:street":"Calle De Ansite;Arinaga",
    "iso:country":"ES",
    "sg:address":"Calle de Ansite, 88",
    "sg:city":"Cruce De Arinaga",
    "sg:orig_category":"Servicios De Telecomunicaciones",
    "sg:phone":"+34 928 18 31 72",
    "sg:postcode":"35118",
    "sg:province":"Las Palmas",
    "wof:name":"Megias Gonzalez Fatima Yobana",
    "wof:placetype":"venue"
},
  "geometry": {"coordinates":[-15.4269752502,27.8772068024],"type":"Point"}
}