{
  "type": "Feature",
  "properties": {
    "addr:full":"Calle de Reyes Catolicos, 5 Vejer De La Frontera C\u00e1diz 11150",
    "addr:housenumber":"5",
    "addr:postcode":"11150",
    "addr:street":"Calle De Reyes Catolicos",
    "iso:country":"ES",
    "sg:address":"Calle de Reyes Catolicos, 5",
    "sg:city":"Vejer De La Frontera",
    "sg:orig_category":"Producci\u00d3n, Venta De Productos De Agricultura Biol\u00d3gica",
    "sg:phone":"+34 956 45 08 97",
    "sg:postcode":"11150",
    "sg:province":"C\u00e1diz",
    "wof:name":"Mu\u00f1oz De Arenillas Ramirez Jose",
    "wof:placetype":"venue"
},
  "geometry": {"coordinates":[-5.9633970261,36.2529945374],"type":"Point"}
}