{
  "type": "Feature",
  "properties": {
    "addr:full":"Pl Major, 4 Santa Maria De Palautordera Barcelona 08460",
    "addr:housenumber":"4",
    "addr:postcode":"08460",
    "addr:street":"Pl Major",
    "iso:country":"ES",
    "sg:address":"Pl Major, 4",
    "sg:city":"Santa Maria De Palautordera",
    "sg:orig_category":"Ropa Para Beb\u00c9s Y Ni\u00d1os (confecci\u00d3n, Al Por Mayor)",
    "sg:phone":"+34 938 48 20 78",
    "sg:postcode":"08460",
    "sg:province":"Barcelona",
    "wof:name":"Sabe Arabia Teresa",
    "wof:placetype":"venue"
},
  "geometry": {"coordinates":[-97.78224945069999,45.7040786743],"type":"Point"}
}