{
  "type": "Feature",
  "properties": {
    "addr:full":"Carrer de Malats, 16 Barcelona Barcelona 08030",
    "addr:housenumber":"16",
    "addr:postcode":"08030",
    "addr:street":"Carrer De Malats",
    "iso:country":"ES",
    "sg:address":"Carrer de Malats, 16",
    "sg:city":"Barcelona",
    "sg:orig_category":"Molduras, Junquillos, Listones Y Molduras Perforadas",
    "sg:phone":"+34 933 11 61 10",
    "sg:postcode":"08030",
    "sg:province":"Barcelona",
    "wof:name":"Remesal Moldon Angel",
    "wof:placetype":"venue"
},
  "geometry": {"coordinates":[2.1904020309,41.4362258911],"type":"Point"}
}