{
  "type": "Feature",
  "properties": {
    "addr:full":"Calle de Santa Lucia, 3 Jerez De La Frontera C\u00e1diz 11408",
    "addr:housenumber":"3",
    "addr:postcode":"11408",
    "addr:street":"Calle De Santa Lucia",
    "iso:country":"ES",
    "sg:address":"Calle de Santa Lucia, 3",
    "sg:city":"Jerez De La Frontera",
    "sg:orig_category":"Quincaller\u00cda (al Por Menor)",
    "sg:phone":"+34 956 18 33 20",
    "sg:postcode":"11408",
    "sg:province":"C\u00e1diz",
    "wof:name":"Oca\u00f1a Madero Magdalena",
    "wof:placetype":"venue"
},
  "geometry": {"coordinates":[-6.1414241791,36.6739845276],"type":"Point"}
}