{
  "type": "Feature",
  "properties": {
    "iso:country":"ES",
    "sg:address":"Carr Bajoli, 73",
    "sg:city":"Poima",
    "sg:orig_category":"Asesor\u00cda Para La Organizaci\u00d3n Y Gesti\u00d3n Del Transporte",
    "sg:phone":"+34 971 36 73 10",
    "sg:postcode":"07714",
    "sg:province":"Islas Baleares",
    "wof:name":"Guillen Menorca S.a.",
    "wof:placetype":"venue"
},
  "geometry": {"coordinates":[2.9117100239,39.6136398315],"type":"Point"}
}