{
  "type": "Feature",
  "properties": {
    "iso:country":"ES",
    "sg:address":"Pla\u00c7 Bisbe Benlloch, 2",
    "sg:city":"Guissona",
    "sg:orig_category":"Caf\u00c9s, Bares, Cervecer\u00cdas",
    "sg:phone":"+34 973 55 22 12",
    "sg:postcode":"25210",
    "sg:province":"Lleida",
    "wof:name":"Bar Centre, Scp",
    "wof:placetype":"venue"
},
  "geometry": {"coordinates":[1.2882540226,41.7848052979],"type":"Point"}
}