{
  "type": "Feature",
  "properties": {
    "addr:full":"Calle de Mayor, 1 Puebla Valverde Teruel 44450",
    "addr:housenumber":"1",
    "addr:postcode":"44450",
    "addr:street":"Calle De Mayor",
    "iso:country":"ES",
    "sg:address":"Calle de Mayor, 1",
    "sg:city":"Puebla Valverde",
    "sg:orig_category":"Cajas De Ahorro",
    "sg:phone":"+34 978 67 01 30",
    "sg:postcode":"44450",
    "sg:province":"Teruel",
    "sg:website":"www.ibercaja.es",
    "wof:name":"Caja De Ahorros Y Monte De Piedad De Zaragoza Aragon Y Rioja",
    "wof:placetype":"venue"
},
  "geometry": {"coordinates":[-0.9285569787,40.2248916626],"type":"Point"}
}