{
  "type": "Feature",
  "properties": {
    "addr:full":"Calle de Rio Taju\u00d1a, 6 Arganda Madrid 28500",
    "addr:housenumber":"6",
    "addr:postcode":"28500",
    "addr:street":"Calle De Rio Tajun\u0303A",
    "iso:country":"ES",
    "sg:address":"Calle de Rio Taju\u00d1a, 6",
    "sg:city":"Arganda",
    "sg:orig_category":"Mec\u00c1nico Del Autom\u00d3vil",
    "sg:phone":"+34 918 71 36 15",
    "sg:postcode":"28500",
    "sg:province":"Madrid",
    "wof:name":"Garcia-mu\u00f1oz Gonzalez De La Aleja Jesus",
    "wof:placetype":"venue"
},
  "geometry": {"coordinates":[-3.4574990273,40.3005828857],"type":"Point"}
}