{
  "type": "Feature",
  "properties": {
    "iso:country":"ES",
    "sg:address":"Calle de Santa Ana, 33",
    "sg:city":"Castuera",
    "sg:orig_category":"Psic\u00d3logos",
    "sg:phone":"+34 924 77 25 42",
    "sg:postcode":"06420",
    "sg:province":"Badajoz",
    "wof:name":"Tena Morillo Felisa De",
    "wof:placetype":"venue"
},
  "geometry": {"coordinates":[-5.5448141098,38.7234802246],"type":"Point"}
}