{
  "type": "Feature",
  "properties": {
    "addr:full":"Calle de San Basilio, 14 Cordoba C\u00f3rdoba 14004",
    "addr:housenumber":"14",
    "addr:postcode":"14004",
    "addr:street":"Calle De San;Co\u0301Rdoba",
    "iso:country":"ES",
    "sg:address":"Calle de San Basilio, 14",
    "sg:city":"Cordoba",
    "sg:orig_category":"Empresas De Carpinter\u00cda Met\u00c1lica",
    "sg:phone":"+34 957 42 19 19",
    "sg:postcode":"14004",
    "sg:province":"C\u00f3rdoba",
    "wof:name":"Gavi\u00f1o Moya Manuel",
    "wof:placetype":"venue"
},
  "geometry": {"coordinates":[-4.783408165,37.8769798279],"type":"Point"}
}