{
  "type": "Feature",
  "properties": {
    "iso:country":"ES",
    "sg:address":"A Mtnez De La Hoz, 12",
    "sg:city":"Mancha Real",
    "sg:orig_category":"Cr\u00cda De Animales",
    "sg:phone":"+34 953 35 44 22",
    "sg:postcode":"23100",
    "sg:province":"Ja\u00e9n",
    "wof:name":"Alcala Rodriguez Antonio Javier",
    "wof:placetype":"venue"
},
  "geometry": {"coordinates":[-3.6116495132,37.8278694153],"type":"Point"}
}