{
  "type": "Feature",
  "properties": {
    "addr:full":"Avgd Alemanya, 20 Villarreal Castell\u00f3n 12540",
    "addr:housenumber":"20",
    "addr:postcode":"12540",
    "addr:street":"Alemanya",
    "iso:country":"ES",
    "sg:address":"Avgd Alemanya, 20",
    "sg:city":"Villarreal",
    "sg:orig_category":"Venta, Montaje De Neum\u00c1ticos",
    "sg:phone":"+34 964 52 00 66",
    "sg:postcode":"12540",
    "sg:province":"Castell\u00f3n",
    "wof:name":"Neumaticos Vila-real S.l.",
    "wof:placetype":"venue"
},
  "geometry": {"coordinates":[-0.0952939987,39.9453048706],"type":"Point"}
}