{
  "type": "Feature",
  "properties": {
    "addr:full":"Calle de Parauta, 32 Malaga M\u00e1laga 29006",
    "addr:housenumber":"32",
    "addr:postcode":"29006",
    "addr:street":"Calle De Parauta;Ma\u0301Laga",
    "iso:country":"ES",
    "sg:address":"Calle de Parauta, 32",
    "sg:city":"Malaga",
    "sg:orig_category":"Confecci\u00d3n (fabricaci\u00d3n, Al Por Mayor)",
    "sg:phone":"+34 952 35 33 50",
    "sg:postcode":"29006",
    "sg:province":"M\u00e1laga",
    "wof:name":"Decoracion Y Modas Kinga's S.l.",
    "wof:placetype":"venue"
},
  "geometry": {"coordinates":[-4.467716217,36.7015037537],"type":"Point"}
}