{
  "type": "Feature",
  "properties": {
    "addr:full":"Via Edison (de), 56 Boisaca La Coru\u00f1a 15890",
    "addr:housenumber":"56",
    "addr:postcode":"15890",
    "addr:street":"Via Edison De;La Corun\u0303A",
    "iso:country":"ES",
    "sg:address":"Via Edison (de), 56",
    "sg:city":"Boisaca",
    "sg:orig_category":"Electricidad: Instalaciones Industriales",
    "sg:phone":"+34 981 58 71 20",
    "sg:postcode":"15890",
    "sg:province":"La Coru\u00f1a",
    "wof:name":"Caneda Electricidad S.l.",
    "wof:placetype":"venue"
},
  "geometry": {"coordinates":[-8.4769210815,42.8835983276],"type":"Point"}
}