{
  "type": "Feature",
  "properties": {
    "addr:full":"Av Esplugues, 103 Barcelona Barcelona 08034",
    "addr:housenumber":"103",
    "addr:postcode":"08034",
    "addr:street":"Av Esplugues",
    "iso:country":"ES",
    "sg:address":"Av Esplugues, 103",
    "sg:city":"Barcelona",
    "sg:orig_category":"Distribuci\u00d3n De Petr\u00d3leo Y Derivados",
    "sg:phone":"+34 932 80 09 93",
    "sg:postcode":"08034",
    "sg:province":"Barcelona",
    "wof:name":"Estacion Servicio Pedralbes S.l.",
    "wof:placetype":"venue"
},
  "geometry": {"coordinates":[2.1054930687,41.3863372803],"type":"Point"}
}