{
  "type": "Feature",
  "properties": {
    "iso:country":"ES",
    "sg:address":"Carr Sant Joan (de), 3",
    "sg:city":"Albaida",
    "sg:orig_category":"Bazares, Art\u00cdculos De Limpieza Y De Cocina (al Por Menor)",
    "sg:phone":"+34 962 90 11 65",
    "sg:postcode":"46860",
    "sg:province":"Valencia",
    "wof:name":"Boronat Tejada Carlos",
    "wof:placetype":"venue"
},
  "geometry": {"coordinates":[-0.5187529922,38.8402938843],"type":"Point"}
}