{
  "type": "Feature",
  "properties": {
    "iso:country":"ES",
    "sg:address":"Calle de Guardia Civil, La, 20",
    "sg:city":"Valencia",
    "sg:orig_category":"Controles De Edificaci\u00d3n (construcci\u00d3n, Seguridad)",
    "sg:phone":"+34 963 39 08 93",
    "sg:postcode":"46020",
    "sg:province":"Valencia",
    "wof:name":"Vatoyma S.l.",
    "wof:placetype":"venue"
},
  "geometry": {"coordinates":[-0.3571299911,39.4815139771],"type":"Point"}
}