{
  "type": "Feature",
  "properties": {
    "iso:country":"ES",
    "sg:address":"Calle de Hermanos Paternina Garcia-cid, 2",
    "sg:city":"Haro",
    "sg:orig_category":"Plomeros",
    "sg:phone":"+34 941 30 32 28",
    "sg:postcode":"26200",
    "sg:province":"La Rioja",
    "wof:name":"Ba\u00f1o Integral S.l.",
    "wof:placetype":"venue"
},
  "geometry": {"coordinates":[-2.8502631187,42.5774803162],"type":"Point"}
}