{
  "type": "Feature",
  "properties": {
    "iso:country":"ES",
    "sg:address":"Carr Sant Ramon (de), S/n",
    "sg:city":"Artesa Lleida",
    "sg:orig_category":"Barnizadores",
    "sg:phone":"+34 973 16 76 63",
    "sg:postcode":"25150",
    "sg:province":"Lleida",
    "wof:name":"Tortosa Lopez Francisco Ricardo",
    "wof:placetype":"venue"
},
  "geometry": {"coordinates":[0.7057800293,41.5531044006],"type":"Point"}
}