{
  "type": "Feature",
  "properties": {
    "iso:country":"ES",
    "sg:address":"Calle de Veintinueve De Diciembre, S/n",
    "sg:city":"Tudela Duero",
    "sg:orig_category":"Peluquer\u00cdas, Peluquer\u00cda Mixta",
    "sg:phone":"+34 983 52 07 45",
    "sg:postcode":"47320",
    "sg:province":"Valladolid",
    "wof:name":"Julio Cachorro Diez Y Otro Cdad",
    "wof:placetype":"venue"
},
  "geometry": {"coordinates":[-4.5873403549,41.5868911743],"type":"Point"}
}