{
  "type": "Feature",
  "properties": {
    "addr:full":"Calle de Forja, 5 Malaga M\u00e1laga 29190",
    "addr:housenumber":"5",
    "addr:postcode":"29190",
    "addr:street":"Calle De Forja;Ma\u0301Laga",
    "iso:country":"ES",
    "sg:address":"Calle de Forja, 5",
    "sg:city":"Malaga",
    "sg:orig_category":"Inform\u00c1tica (estudios, Servicios, Asesor\u00cda, Formaci\u00d3n)",
    "sg:phone":"+34 952 43 90 21",
    "sg:postcode":"29190",
    "sg:province":"M\u00e1laga",
    "wof:name":"Hardware Soluciones Profesionales A Informaticos S.l",
    "wof:placetype":"venue"
},
  "geometry": {"coordinates":[-4.479640007,36.734462738],"type":"Point"}
}