{
  "type": "Feature",
  "properties": {
    "addr:full":"Calle de Malaga, 18 Mairena Aljarafe Sevilla 41927",
    "addr:housenumber":"18",
    "addr:postcode":"41927",
    "addr:street":"Calle De Malaga",
    "iso:country":"ES",
    "sg:address":"Calle de Malaga, 18",
    "sg:city":"Mairena Aljarafe",
    "sg:orig_category":"Mec\u00c1nico Del Autom\u00d3vil",
    "sg:phone":"+34 955 60 94 48",
    "sg:postcode":"41927",
    "sg:province":"Sevilla",
    "wof:name":"Medina Merino S.l.l",
    "wof:placetype":"venue"
},
  "geometry": {"coordinates":[-6.0673241615,37.3445739746],"type":"Point"}
}