{
  "type": "Feature",
  "properties": {
    "addr:full":"Rua Hospital, 31 Cambados Pontevedra 36630",
    "addr:housenumber":"31",
    "addr:postcode":"36630",
    "addr:street":"Rua Hospital",
    "iso:country":"ES",
    "sg:address":"Rua Hospital, 31",
    "sg:city":"Cambados",
    "sg:orig_category":"Plomeros",
    "sg:phone":"+34 986 54 21 86",
    "sg:postcode":"36630",
    "sg:province":"Pontevedra",
    "wof:name":"Calvet Barreiro Amancio",
    "wof:placetype":"venue"
},
  "geometry": {"coordinates":[-8.8154392242,42.5111198425],"type":"Point"}
}