{
  "type": "Feature",
  "properties": {
    "iso:country":"ES",
    "sg:address":"Rua Conde Torrecedeira, 58",
    "sg:city":"Vigo",
    "sg:orig_category":"Agencias De Trabajo Temporal",
    "sg:phone":"+34 986 24 46 74",
    "sg:postcode":"36202",
    "sg:province":"Pontevedra",
    "wof:name":"Laborman Trabajo Temporal Ett S.a.",
    "wof:placetype":"venue"
},
  "geometry": {"coordinates":[-8.7326755524,42.2304382324],"type":"Point"}
}