{
  "type": "Feature",
  "properties": {
    "iso:country":"ES",
    "sg:address":"Avda Estella, 10",
    "sg:city":"Tafalla",
    "sg:orig_category":"Zapater\u00cds Y Cordeler\u00cda",
    "sg:phone":"+34 948 70 18 23",
    "sg:postcode":"31300",
    "sg:province":"Navarra",
    "wof:name":"Lopez Carcar Luis",
    "wof:placetype":"venue"
},
  "geometry": {"coordinates":[-1.6782599688,42.5261116028],"type":"Point"}
}