{
  "type": "Feature",
  "properties": {
    "iso:country":"ES",
    "sg:address":"Carrer de Felip Ii, 275",
    "sg:city":"Barcelona",
    "sg:orig_category":"Material De Ocasi\u00d3n Para Particulares (compra, Reventa)",
    "sg:phone":"+34 933 49 56 50",
    "sg:postcode":"08016",
    "sg:province":"Barcelona",
    "sg:website":"www.cashconverters.com",
    "wof:name":"Segundos Articulos S.a.",
    "wof:placetype":"venue"
},
  "geometry": {"coordinates":[2.1758630276,41.4286842346],"type":"Point"}
}