{
  "type": "Feature",
  "properties": {
    "iso:country":"ES",
    "sg:address":"Calle de Salinas, S/n",
    "sg:city":"Prado Del Rey",
    "sg:orig_category":"Mec\u00c1nico Del Autom\u00d3vil",
    "sg:phone":"+34 956 72 32 03",
    "sg:postcode":"11660",
    "sg:province":"C\u00e1diz",
    "wof:name":"Pacheco Moreno Francisco",
    "wof:placetype":"venue"
},
  "geometry": {"coordinates":[-5.559800148,36.7841873169],"type":"Point"}
}