{
  "type": "Feature",
  "properties": {
    "addr:full":"Pl. Major, 6 Figuerola Orcau Lleida 25655",
    "addr:housenumber":"6",
    "addr:postcode":"25655",
    "addr:street":"Pl. Major",
    "iso:country":"ES",
    "sg:address":"Pl. Major, 6",
    "sg:city":"Figuerola Orcau",
    "sg:orig_category":"Farmacias",
    "sg:phone":"+34 973 66 50 29",
    "sg:postcode":"25655",
    "sg:province":"Lleida",
    "wof:name":"Agusti Garrido Joana",
    "wof:placetype":"venue"
},
  "geometry": {"coordinates":[0.9816882014,42.1631126404],"type":"Point"}
}