{
  "type": "Feature",
  "properties": {
    "addr:full":"Calle de Alhondiga, 9 Baza Granada 18800",
    "addr:housenumber":"9",
    "addr:postcode":"18800",
    "addr:street":"Calle De Alhondiga",
    "iso:country":"ES",
    "sg:address":"Calle de Alhondiga, 9",
    "sg:city":"Baza",
    "sg:orig_category":"Ense\u00d1anza: Profesiones Art\u00cdsticas",
    "sg:phone":"+34 958 71 20 96",
    "sg:postcode":"18800",
    "sg:province":"Granada",
    "wof:name":"Guillen Moreno Jesus",
    "wof:placetype":"venue"
},
  "geometry": {"coordinates":[-2.7745034695,37.4893722534],"type":"Point"}
}