{
  "type": "Feature",
  "properties": {
    "addr:full":"Calle de Ugaldeguren Kalea, S/n Ugaldeguren Vizcaya 48160",
    "addr:housenumber":"s / n",
    "addr:postcode":"48160",
    "addr:street":"Calle De Ugaldeguren Kalea",
    "iso:country":"ES",
    "sg:address":"Calle de Ugaldeguren Kalea, S/n",
    "sg:city":"Ugaldeguren",
    "sg:orig_category":"M\u00c1rmoles, Granitos Y Piedras Naturales",
    "sg:phone":"+34 944 54 38 79",
    "sg:postcode":"48160",
    "sg:province":"Vizcaya",
    "wof:name":"Madariaga Barrueta Gorka",
    "wof:placetype":"venue"
},
  "geometry": {"coordinates":[-2.9316000938,43.2383995056],"type":"Point"}
}