{
  "type": "Feature",
  "properties": {
    "iso:country":"ES",
    "sg:address":"Carr Can Pau Birol, 19",
    "sg:city":"Girona",
    "sg:orig_category":"Imprenta",
    "sg:phone":"+34 972 40 51 02",
    "sg:postcode":"17005",
    "sg:province":"Girona",
    "wof:name":"Nortprint S.a.",
    "wof:placetype":"venue"
},
  "geometry": {"coordinates":[2.8038020134,41.9663162231],"type":"Point"}
}