{
  "type": "Feature",
  "properties": {
    "addr:full":"Cmno Pajarillas (de Las), 17 Mostoles Madrid 28935",
    "addr:housenumber":"17",
    "addr:postcode":"28935",
    "addr:street":"Cmno Pajarillas De Las",
    "iso:country":"ES",
    "sg:address":"Cmno Pajarillas (de Las), 17",
    "sg:city":"Mostoles",
    "sg:orig_category":"Cerrajer\u00cda, Ferrallista",
    "sg:phone":"+34 916 13 96 94",
    "sg:postcode":"28935",
    "sg:province":"Madrid",
    "wof:name":"Cerrajerias Vidal S.a.",
    "wof:placetype":"venue"
},
  "geometry": {"coordinates":[-3.8896429539,40.3367347717],"type":"Point"}
}