{
  "type": "Feature",
  "properties": {
    "addr:full":"Calle de Trinidad, 103 Castellon Castell\u00f3n 12002",
    "addr:housenumber":"103",
    "addr:postcode":"12002",
    "addr:street":"Calle De Trinidad",
    "iso:country":"ES",
    "sg:address":"Calle de Trinidad, 103",
    "sg:city":"Castellon",
    "sg:orig_category":"Carnicer\u00cdas, Carnicer\u00cdas",
    "sg:phone":"+34 964 22 41 57",
    "sg:postcode":"12002",
    "sg:province":"Castell\u00f3n",
    "wof:name":"Esteve Trilles Marcelo",
    "wof:placetype":"venue"
},
  "geometry": {"coordinates":[-0.0417400002,39.9835395813],"type":"Point"}
}