{
  "type": "Feature",
  "properties": {
    "addr:full":"Erguin Kalea, 3 Arrasate Guip\u00f9zcoa 20500",
    "addr:housenumber":"3",
    "addr:postcode":"20500",
    "addr:street":"Erguin Kalea;Guipu\u0300Zcoa",
    "iso:country":"ES",
    "sg:address":"Erguin Kalea, 3",
    "sg:city":"Arrasate",
    "sg:orig_category":"Peluquer\u00cdas, Peluquer\u00cda Mixta",
    "sg:phone":"+34 943 79 72 56",
    "sg:postcode":"20500",
    "sg:province":"Guip\u00f9zcoa",
    "wof:name":"Revuelta Varona , Herminio",
    "wof:placetype":"venue"
},
  "geometry": {"coordinates":[-2.4970140457,43.0635108948],"type":"Point"}
}