{
  "type": "Feature",
  "properties": {
    "addr:full":"Calle de San Juan De Letran, 4 Granada Granada 18012",
    "addr:housenumber":"4",
    "addr:postcode":"18012",
    "addr:street":"Calle De San",
    "iso:country":"ES",
    "sg:address":"Calle de San Juan De Letran, 4",
    "sg:city":"Granada",
    "sg:orig_category":"Peluqueros: De Se\u00d1oras",
    "sg:phone":"+34 958 29 36 49",
    "sg:postcode":"18012",
    "sg:province":"Granada",
    "wof:name":"Martinez Lozano Inmaculada",
    "wof:placetype":"venue"
},
  "geometry": {"coordinates":[-3.6074149609,37.1860389709],"type":"Point"}
}