{
  "type": "Feature",
  "properties": {
    "iso:country":"ES",
    "sg:address":"Avda Cantue\u00d1a (de La), 7",
    "sg:city":"Fuenlabrada",
    "sg:orig_category":"Paletas",
    "sg:phone":"+34 916 42 12 92",
    "sg:postcode":"28947",
    "sg:province":"Madrid",
    "wof:name":"Chep Espa\u00f1a S.a.",
    "wof:placetype":"venue"
},
  "geometry": {"coordinates":[-3.762196064,40.2731208801],"type":"Point"}
}