{
  "type": "Feature",
  "properties": {
    "addr:full":"Calle de Vega, 22 Chiclana De La Frontera C\u00e1diz 11130",
    "addr:housenumber":"22",
    "addr:postcode":"11130",
    "addr:street":"Calle De Vega",
    "iso:country":"ES",
    "sg:address":"Calle de Vega, 22",
    "sg:city":"Chiclana De La Frontera",
    "sg:orig_category":"\u00d3ptica: Instrumentos (fabricaci\u00d3n)",
    "sg:phone":"+34 956 53 28 31",
    "sg:postcode":"11130",
    "sg:province":"C\u00e1diz",
    "wof:name":"Benitez Massa Maria Dolores",
    "wof:placetype":"venue"
},
  "geometry": {"coordinates":[-6.1483688354,36.4204788208],"type":"Point"}
}