{
  "type": "Feature",
  "properties": {
    "addr:full":"Avda Padre Ismael, 42 Aspe Alicante 03680",
    "addr:housenumber":"42",
    "addr:postcode":"03680",
    "addr:street":"Avda Padre Ismael",
    "iso:country":"ES",
    "sg:address":"Avda Padre Ismael, 42",
    "sg:city":"Aspe",
    "sg:orig_category":"Asociaciones De Vecinos, Centros De Juventud",
    "sg:phone":"+34 965 49 27 52",
    "sg:postcode":"03680",
    "sg:province":"Alicante",
    "wof:name":"A.o.d.a.c.",
    "wof:placetype":"venue"
},
  "geometry": {"coordinates":[-0.7643805742,38.3493537903],"type":"Point"}
}