{
  "type": "Feature",
  "properties": {
    "iso:country":"ES",
    "sg:address":"Calle de Gabriel Miro, 22",
    "sg:city":"Torrevieja",
    "sg:orig_category":"Electrodom\u00c9sticos (al Por Menor)",
    "sg:phone":"+34 966 70 59 56",
    "sg:postcode":"03180",
    "sg:province":"Alicante",
    "wof:name":"Vicente Bernabeu Salvador",
    "wof:placetype":"venue"
},
  "geometry": {"coordinates":[-0.6861069798,37.9777641296],"type":"Point"}
}