{
  "type": "Feature",
  "properties": {
    "addr:full":"Plaz Pinazo, S/n Madrid Madrid 28021",
    "addr:housenumber":"s / n",
    "addr:postcode":"28021",
    "addr:street":"Plaz Pinazo",
    "iso:country":"ES",
    "sg:address":"Plaz Pinazo, S/n",
    "sg:city":"Madrid",
    "sg:orig_category":"Fabricaci\u00d3n De Papel Pintado",
    "sg:phone":"+34 917 97 13 03",
    "sg:postcode":"28021",
    "sg:province":"Madrid",
    "wof:name":"Alejandre Serrano Isabel",
    "wof:placetype":"venue"
},
  "geometry": {"coordinates":[-3.6912276745,40.3433532715],"type":"Point"}
}