{
  "type": "Feature",
  "properties": {
    "addr:full":"Calle de Onesimo Redondo, 8 Cantalejo Segovia 40320",
    "addr:housenumber":"8",
    "addr:postcode":"40320",
    "addr:street":"Calle De Onesimo Redondo",
    "iso:country":"ES",
    "sg:address":"Calle de Onesimo Redondo, 8",
    "sg:city":"Cantalejo",
    "sg:orig_category":"Agentes Generales De Seguros",
    "sg:phone":"+34 921 52 04 05",
    "sg:postcode":"40320",
    "sg:province":"Segovia",
    "wof:name":"Sancho Arribas German",
    "wof:placetype":"venue"
},
  "geometry": {"coordinates":[-3.9272971153,41.2595100403],"type":"Point"}
}