{
  "type": "Feature",
  "properties": {
    "addr:full":"Los Rosales, 5 Coria C\u00e1ceres 10800",
    "addr:housenumber":"5",
    "addr:postcode":"10800",
    "addr:street":"Los Rosales;Ca\u0301Ceres",
    "iso:country":"ES",
    "sg:address":"Los Rosales, 5",
    "sg:city":"Coria",
    "sg:orig_category":"M\u00c1rmoles, Granitos Y Piedras Naturales",
    "sg:phone":"+34 927 50 42 43",
    "sg:postcode":"10800",
    "sg:province":"C\u00e1ceres",
    "wof:name":"Marmoles Y Granito Sanchez Rico C.b.",
    "wof:placetype":"venue"
},
  "geometry": {"coordinates":[-6.5262508392,39.9888114929],"type":"Point"}
}