{
  "type": "Feature",
  "properties": {
    "iso:country":"ES",
    "sg:address":"Calle de Pe\u00d1uelas, 7",
    "sg:city":"Madrid",
    "sg:orig_category":"Alimentaci\u00d3n General (al Por Menor)",
    "sg:phone":"+34 915 17 15 75",
    "sg:postcode":"28005",
    "sg:province":"Madrid",
    "wof:name":"Malaga Lopez Gonzalo",
    "wof:placetype":"venue"
},
  "geometry": {"coordinates":[-3.7043609619,40.4039230347],"type":"Point"}
}