{
  "type": "Feature",
  "properties": {
    "iso:country":"ES",
    "sg:address":"Calle de Moreno, 1",
    "sg:city":"Alcantarilla",
    "sg:orig_category":"M\u00c9dicos: Estomatolog\u00cda",
    "sg:phone":"+34 968 80 56 98",
    "sg:postcode":"30820",
    "sg:province":"Murcia",
    "wof:name":"Pons-fuster Olivera Jose Maria",
    "wof:placetype":"venue"
},
  "geometry": {"coordinates":[-1.2106930017,37.9708709717],"type":"Point"}
}