{
  "type": "Feature",
  "properties": {
    "addr:full":"C/ Barcelona, S/n Torre Islas Baleares 07609",
    "addr:housenumber":"/ n",
    "addr:postcode":"07609",
    "addr:street":"C / Barcelona S",
    "iso:country":"ES",
    "sg:address":"C/ Barcelona, S/n",
    "sg:city":"Torre",
    "sg:orig_category":"Venta, Instalaci\u00d3n De Calefacci\u00d3n",
    "sg:phone":"+34 971 74 97 74",
    "sg:postcode":"07609",
    "sg:province":"Islas Baleares",
    "wof:name":"Millan Mendez Javier",
    "wof:placetype":"venue"
},
  "geometry": {"coordinates":[2.7507419586,39.4544181824],"type":"Point"}
}