{
  "type": "Feature",
  "properties": {
    "iso:country":"ES",
    "sg:address":"Plaz Espa\u00d1a, 8",
    "sg:city":"Campillos",
    "sg:orig_category":"Droguer\u00cdas (al Por Menor)",
    "sg:phone":"+34 952 72 31 11",
    "sg:postcode":"29320",
    "sg:province":"M\u00e1laga",
    "wof:name":"Ya\u00f1ez Padilla Francisco",
    "wof:placetype":"venue"
},
  "geometry": {"coordinates":[-4.8728094101,37.047492981],"type":"Point"}
}