{
  "type": "Feature",
  "properties": {
    "addr:full":"Av Francesc Macia, 90 Vilanova I La Geltru Barcelona 08800",
    "addr:housenumber":"90",
    "addr:postcode":"08800",
    "addr:street":"Av Francesc Macia",
    "iso:country":"ES",
    "sg:address":"Av Francesc Macia, 90",
    "sg:city":"Vilanova I La Geltru",
    "sg:orig_category":"Material Y Suministros Para Peluquer\u00cda",
    "sg:phone":"+34 938 14 42 00",
    "sg:postcode":"08800",
    "sg:province":"Barcelona",
    "wof:name":"Distribuciones Generales De Peluqueria Y Belleza S. L.",
    "wof:placetype":"venue"
},
  "geometry": {"coordinates":[1.7195390463,41.2223167419],"type":"Point"}
}