{
  "type": "Feature",
  "properties": {
    "addr:full":"Calle de Bailen, 34 Valencia Valencia 46007",
    "addr:housenumber":"34",
    "addr:postcode":"46007",
    "addr:street":"Calle De Bailen",
    "iso:country":"ES",
    "sg:address":"Calle de Bailen, 34",
    "sg:city":"Valencia",
    "sg:orig_category":"Asociaciones, Organismos Culturales Y Socioeducativos",
    "sg:phone":"+34 963 80 18 77",
    "sg:postcode":"46007",
    "sg:province":"Valencia",
    "wof:name":"Comision Falla Ferroviaria Bailen-jativa",
    "wof:placetype":"venue"
},
  "geometry": {"coordinates":[-0.3785271943,39.4655418396],"type":"Point"}
}