{
  "type": "Feature",
  "properties": {
    "addr:full":"Avda Vena, 1 Burgos Burgos 09005",
    "addr:housenumber":"1",
    "addr:postcode":"09005",
    "addr:street":"Avda Vena",
    "iso:country":"ES",
    "sg:address":"Avda Vena, 1",
    "sg:city":"Burgos",
    "sg:orig_category":"Ingenier\u00cda, Centros De Estudios (diversos)",
    "sg:phone":"+34 947 22 06 30",
    "sg:postcode":"09005",
    "sg:province":"Burgos",
    "wof:name":"Tirado De La Cruz Felix",
    "wof:placetype":"venue"
},
  "geometry": {"coordinates":[-3.6924030781,42.3470001221],"type":"Point"}
}