{
  "type": "Feature",
  "properties": {
    "addr:full":"Calle de Santa Maria, 8 Casarrubios Monte Toledo 45950",
    "addr:housenumber":"8",
    "addr:postcode":"45950",
    "addr:street":"Calle De Santa Maria",
    "iso:country":"ES",
    "sg:address":"Calle de Santa Maria, 8",
    "sg:city":"Casarrubios Monte",
    "sg:orig_category":"Alimentaci\u00d3n General (al Por Menor)",
    "sg:phone":"+34 918 17 26 83",
    "sg:postcode":"45950",
    "sg:province":"Toledo",
    "wof:name":"Cogolludo Barroso Apolinar",
    "wof:placetype":"venue"
},
  "geometry": {"coordinates":[-4.0362100601,40.1847496033],"type":"Point"}
}