{
  "type": "Feature",
  "properties": {
    "iso:country":"ES",
    "sg:address":"Calle de C, 21",
    "sg:city":"Gines",
    "sg:orig_category":"Suministros Para Hoteles",
    "sg:phone":"+34 954 71 35 53",
    "sg:postcode":"41960",
    "sg:province":"Sevilla",
    "sg:website":"www.alvarezromero.com",
    "wof:name":"Alvarez Romero Hosteleria S.l.",
    "wof:placetype":"venue"
},
  "geometry": {"coordinates":[-6.0861701965,37.3813514709],"type":"Point"}
}