{
  "type": "Feature",
  "properties": {
    "iso:country":"ES",
    "sg:address":"Carrer de Quinze, 4",
    "sg:city":"Bonavista",
    "sg:orig_category":"Carnicer\u00cdas, Carnicer\u00cdas",
    "sg:phone":"+34 977 54 11 81",
    "sg:postcode":"43100",
    "sg:province":"Tarragona",
    "wof:name":"Martinez Borrego Salvador",
    "wof:placetype":"venue"
},
  "geometry": {"coordinates":[1.1939630508,41.1213722229],"type":"Point"}
}