{
  "type": "Feature",
  "properties": {
    "iso:country":"ES",
    "sg:address":"Carrer de Navas De Tolosa, 321",
    "sg:city":"Barcelona",
    "sg:orig_category":"Dietistas",
    "sg:phone":"+34 933 52 23 94",
    "sg:postcode":"08026",
    "sg:province":"Barcelona",
    "wof:name":"Gil De Leonardo Maria Isabel",
    "wof:placetype":"venue"
},
  "geometry": {"coordinates":[2.1853790283,41.4163894653],"type":"Point"}
}