{
  "type": "Feature",
  "properties": {
    "iso:country":"ES",
    "sg:address":"Pg Progres, 4",
    "sg:city":"Olesa Montserrat",
    "sg:orig_category":"Ropa Para Se\u00d1oras Y Caballeros (al Por Menor)",
    "sg:phone":"+34 937 75 93 25",
    "sg:postcode":"08640",
    "sg:province":"Barcelona",
    "wof:name":"Asensio Gonzalez Raul",
    "wof:placetype":"venue"
},
  "geometry": {"coordinates":[1.8933434486,41.5408592224],"type":"Point"}
}