{
  "type": "Feature",
  "properties": {
    "addr:full":"Calle de Amanecer, S/n Algeciras C\u00e1diz 11204",
    "addr:housenumber":"s",
    "addr:postcode":"11204",
    "addr:street":"Calle De Amanecer;/ N;Ca\u0301Diz",
    "iso:country":"ES",
    "sg:address":"Calle de Amanecer, S/n",
    "sg:city":"Algeciras",
    "sg:orig_category":"Instalaci\u00d3n, Reparaci\u00d3n De Ascensores Y Montacargas",
    "sg:phone":"+34 956 65 19 19",
    "sg:postcode":"11204",
    "sg:province":"C\u00e1diz",
    "wof:name":"General Elevadores Xxi S.l.",
    "wof:placetype":"venue"
},
  "geometry": {"coordinates":[-5.4573373795,36.1418228149],"type":"Point"}
}