{
  "type": "Feature",
  "properties": {
    "iso:country":"ES",
    "sg:address":"Calle de Arquitecto Ribes, 1",
    "sg:city":"Valencia",
    "sg:orig_category":"Venta, Alquiler Y Mantenimiento De Juegos De Sal\u00d3n O Casinos",
    "sg:phone":"+34 963 79 07 63",
    "sg:postcode":"46014",
    "sg:province":"Valencia",
    "wof:name":"Electronicos Herbon S. L.",
    "wof:placetype":"venue"
},
  "geometry": {"coordinates":[-0.4071569145,39.4717826843],"type":"Point"}
}