{
  "type": "Feature",
  "properties": {
    "iso:country":"ES",
    "sg:address":"Rua Alcalde Domingo Sierra, 17",
    "sg:city":"Conduzo",
    "sg:orig_category":"Inmobiliaria (agencias)",
    "sg:phone":"+34 981 65 15 31",
    "sg:postcode":"15174",
    "sg:province":"La Coru\u00f1a",
    "wof:name":"Marigle Promociones S.l.",
    "wof:placetype":"venue"
},
  "geometry": {"coordinates":[-8.3825464249,43.3157272339],"type":"Point"}
}