{
  "type": "Feature",
  "properties": {
    "addr:full":"Av Generalitat (de La), 101 Tortosa Tarragona 43500",
    "addr:housenumber":"101",
    "addr:postcode":"43500",
    "addr:street":"Av Generalitat De La",
    "iso:country":"ES",
    "sg:address":"Av Generalitat (de La), 101",
    "sg:city":"Tortosa",
    "sg:orig_category":"Persianas Interiores, Exteriores",
    "sg:phone":"+34 977 44 04 06",
    "sg:postcode":"43500",
    "sg:province":"Tarragona",
    "wof:name":"Tendals I Entapissats Francisco Also C.b.",
    "wof:placetype":"venue"
},
  "geometry": {"coordinates":[0.5204600096,40.8076171875],"type":"Point"}
}