{
  "type": "Feature",
  "properties": {
    "iso:country":"ES",
    "sg:address":"Av Prat De La Riba, 21",
    "sg:city":"Tarragona",
    "sg:orig_category":"Ense\u00d1anza: Profesiones Art\u00cdsticas",
    "sg:phone":"+34 977 24 35 05",
    "sg:postcode":"43001",
    "sg:province":"Tarragona",
    "wof:name":"Rodriguez Granell Manel",
    "wof:placetype":"venue"
},
  "geometry": {"coordinates":[1.2468639612,41.1162452698],"type":"Point"}
}