{
  "type": "Feature",
  "properties": {
    "iso:country":"ES",
    "sg:address":"Ctra M-511 (villaviciosa-boadilla), Km. 0011,0",
    "sg:city":"Arco Iris",
    "sg:orig_category":"Maquinaria Para Industrias Diversas",
    "sg:phone":"+34 916 65 79 21",
    "sg:postcode":"28670",
    "sg:province":"Madrid",
    "wof:name":"Delgado Tardon Jesus",
    "wof:placetype":"venue"
},
  "geometry": {"coordinates":[-3.9017140865,40.3512306213],"type":"Point"}
}