{
  "type": "Feature",
  "properties": {
    "iso:country":"ES",
    "sg:address":"Avda Europa, 2",
    "sg:city":"Arriondas",
    "sg:orig_category":"Organismos De Turismo",
    "sg:phone":"+34 985 84 04 90",
    "sg:postcode":"33540",
    "sg:province":"Asturias",
    "wof:name":"Actuwadi S.l.",
    "wof:placetype":"venue"
},
  "geometry": {"coordinates":[-5.1837892532,43.3899154663],"type":"Point"}
}