{
  "type": "Feature",
  "properties": {
    "iso:country":"ES",
    "sg:address":"Calle de San Gil, 11",
    "sg:city":"Le\u00f3n",
    "sg:orig_category":"Frutas Y Legumbres Frescas (al Por Mayor)",
    "sg:phone":"+34 987 25 86 77",
    "sg:postcode":"24006",
    "sg:province":"Le\u00f3n",
    "wof:name":"Representaciones Lobo S.l.",
    "wof:placetype":"venue"
},
  "geometry": {"coordinates":[-5.5633997917,42.5956230164],"type":"Point"}
}