{
  "type": "Feature",
  "properties": {
    "iso:country":"ES",
    "sg:address":"Calle de Numancia, 14",
    "sg:city":"Tauste",
    "sg:orig_category":"Construcciones Prefabricadas Y Desmontables",
    "sg:phone":"+34 976 85 52 36",
    "sg:postcode":"50660",
    "sg:province":"Zaragoza",
    "sg:website":"www.alfonsocipres.com",
    "wof:name":"Alfonso Cipres S.l.",
    "wof:placetype":"venue"
},
  "geometry": {"coordinates":[-1.2554795742,41.924823761],"type":"Point"}
}