{
  "type": "Feature",
  "properties": {
    "addr:full":"Avda Otero Pedrayo, 38 Ourense Ourense 32004",
    "addr:housenumber":"38",
    "addr:postcode":"32004",
    "addr:street":"Avda Otero Pedrayo",
    "iso:country":"ES",
    "sg:address":"Avda Otero Pedrayo, 38",
    "sg:city":"Ourense",
    "sg:orig_category":"Almacenes Para Venta: Muebles Y Varios",
    "sg:phone":"+34 988 23 63 43",
    "sg:postcode":"32004",
    "sg:province":"Ourense",
    "wof:name":"Muebles Feijoo S.l.",
    "wof:placetype":"venue"
},
  "geometry": {"coordinates":[-7.8517551422,42.3424034119],"type":"Point"}
}