{
  "type": "Feature",
  "properties": {
    "addr:full":"Calle de Cid Campeador, 8 Linares Ja\u00e9n 23700",
    "addr:housenumber":"8",
    "addr:postcode":"23700",
    "addr:street":"Calle De Cid Campeador;Jae\u0301N",
    "iso:country":"ES",
    "sg:address":"Calle de Cid Campeador, 8",
    "sg:city":"Linares",
    "sg:orig_category":"Contenedores (mercanc\u00cdas)",
    "sg:phone":"+34 953 69 32 71",
    "sg:postcode":"23700",
    "sg:province":"Ja\u00e9n",
    "wof:name":"Visiedo Garcia Antonio Jose",
    "wof:placetype":"venue"
},
  "geometry": {"coordinates":[-3.6392800808,38.0911750793],"type":"Point"}
}