{
  "type": "Feature",
  "properties": {
    "iso:country":"ES",
    "sg:address":"Carrer de Font, S/n",
    "sg:city":"Can Sant Joan",
    "sg:orig_category":"Guarder\u00cdas",
    "sg:phone":"+34 935 64 60 55",
    "sg:postcode":"08110",
    "sg:province":"Barcelona",
    "wof:name":"Cooperativa De Guarderias De Montcada I Reixac S. C. R. L.",
    "wof:placetype":"venue"
},
  "geometry": {"coordinates":[2.1817800999,41.4892234802],"type":"Point"}
}