{
  "type": "Feature",
  "properties": {
    "iso:country":"ES",
    "sg:address":"Carr Carretera, Sa, 30",
    "sg:city":"Campanet",
    "sg:orig_category":"Bisuter\u00cda, Joyer\u00cda, Relojer\u00cda (al Por Menor)",
    "sg:phone":"+34 971 50 90 55",
    "sg:postcode":"07310",
    "sg:province":"Islas Baleares",
    "wof:name":"Reines Palou Magdalena",
    "wof:placetype":"venue"
},
  "geometry": {"coordinates":[2.9658000469,39.7748908997],"type":"Point"}
}