{
  "type": "Feature",
  "properties": {
    "addr:full":"Calle de Resurreccion M. De Azkue, 1 Arizgoiti Vizcaya 48970",
    "addr:housenumber":"1",
    "addr:postcode":"48970",
    "addr:street":"Calle De Resurreccion M. De Azkue",
    "iso:country":"ES",
    "sg:address":"Calle de Resurreccion M. De Azkue, 1",
    "sg:city":"Arizgoiti",
    "sg:orig_category":"Mec\u00c1nico Del Autom\u00d3vil",
    "sg:phone":"+34 944 26 14 09",
    "sg:postcode":"48970",
    "sg:province":"Vizcaya",
    "wof:name":"Gomez Mahave Felipe",
    "wof:placetype":"venue"
},
  "geometry": {"coordinates":[-2.8841369152,43.2364692688],"type":"Point"}
}