{
  "type": "Feature",
  "properties": {
    "addr:full":"Avda Parque (del), 56 Lucena C\u00f3rdoba 14900",
    "addr:housenumber":"56",
    "addr:postcode":"14900",
    "addr:street":"Avda Parque Del",
    "iso:country":"ES",
    "sg:address":"Avda Parque (del), 56",
    "sg:city":"Lucena",
    "sg:orig_category":"Art\u00cdculos De Decoraci\u00d3n",
    "sg:phone":"+34 957 51 63 94",
    "sg:postcode":"14900",
    "sg:province":"C\u00f3rdoba",
    "wof:name":"Decoraciones Ramirez Dorado S.l.l.",
    "wof:placetype":"venue"
},
  "geometry": {"coordinates":[-4.4922389984,37.4099388123],"type":"Point"}
}