{
  "type": "Feature",
  "properties": {
    "iso:country":"ES",
    "sg:address":"Rua Capitan Eloy, 19",
    "sg:city":"Ourense",
    "sg:orig_category":"Laboratorios Y Trabajos De Fotograf\u00cda, V\u00cddeo Y Cine",
    "sg:phone":"+34 988 23 30 24",
    "sg:postcode":"32003",
    "sg:province":"Ourense",
    "wof:name":"Fernandez Riego Luis",
    "wof:placetype":"venue"
},
  "geometry": {"coordinates":[-7.8639669418,42.3394165039],"type":"Point"}
}