{
  "type": "Feature",
  "properties": {
    "addr:full":"Calle de San Antonio, 26 Calzada Calatrava Ciudad Real 13370",
    "addr:housenumber":"26",
    "addr:postcode":"13370",
    "addr:street":"Calle De San Antonio",
    "iso:country":"ES",
    "sg:address":"Calle de San Antonio, 26",
    "sg:city":"Calzada Calatrava",
    "sg:orig_category":"Panader\u00cdas, Panader\u00cdas",
    "sg:phone":"+34 926 87 54 72",
    "sg:postcode":"13370",
    "sg:province":"Ciudad Real",
    "wof:name":"Alarcon Torres Tomasa",
    "wof:placetype":"venue"
},
  "geometry": {"coordinates":[-3.7717974186,38.7016563416],"type":"Point"}
}