{
  "type": "Feature",
  "properties": {
    "iso:country":"ES",
    "sg:address":"Pda Bixquert, 12",
    "sg:city":"Xativa",
    "sg:orig_category":"Supermercados Y Hipermercados",
    "sg:phone":"+34 962 27 57 16",
    "sg:postcode":"46800",
    "sg:province":"Valencia",
    "wof:name":"Simo Mu\u00f1oz Emilio",
    "wof:placetype":"venue"
},
  "geometry": {"coordinates":[-0.5200830102,38.9934272766],"type":"Point"}
}