{
  "type": "Feature",
  "properties": {
    "iso:country":"ES",
    "sg:address":"Carrer de Baix Penedes, 8",
    "sg:city":"Calafell",
    "sg:orig_category":"Promotores Constructores",
    "sg:phone":"+34 977 69 31 94",
    "sg:postcode":"43820",
    "sg:province":"Tarragona",
    "wof:name":"Urbaser S.a.",
    "wof:placetype":"venue"
},
  "geometry": {"coordinates":[1.5665880442,41.2004203796],"type":"Point"}
}