{
  "type": "Feature",
  "properties": {
    "addr:full":"Calle de Cueva Santa, 11 Cheste Valencia 46380",
    "addr:housenumber":"11",
    "addr:postcode":"46380",
    "addr:street":"Calle De Cueva Santa",
    "iso:country":"ES",
    "sg:address":"Calle de Cueva Santa, 11",
    "sg:city":"Cheste",
    "sg:orig_category":"Contenedores (mercanc\u00cdas)",
    "sg:phone":"+34 962 51 16 68",
    "sg:postcode":"46380",
    "sg:province":"Valencia",
    "wof:name":"Excavaciones Morgan S.l.",
    "wof:placetype":"venue"
},
  "geometry": {"coordinates":[-0.687943995,39.4912490845],"type":"Point"}
}