{
  "type": "Feature",
  "properties": {
    "iso:country":"ES",
    "sg:address":"Rbla Principal, 23",
    "sg:city":"Vilanova I La Geltru",
    "sg:orig_category":"Telas Y Sedas (al Por Menor)",
    "sg:phone":"+34 938 93 02 18",
    "sg:postcode":"08800",
    "sg:province":"Barcelona",
    "wof:name":"Tares Pujals Josefina",
    "wof:placetype":"venue"
},
  "geometry": {"coordinates":[1.7247010469,41.2245025635],"type":"Point"}
}