{
  "type": "Feature",
  "properties": {
    "iso:country":"ES",
    "sg:address":"Polig Los Alamos (p I Fuente Del Rey), 61",
    "sg:city":"Dos Hermanas",
    "sg:orig_category":"Contenedores (mercanc\u00cdas)",
    "sg:phone":"+34 954 69 28 97",
    "sg:postcode":"41700",
    "sg:province":"Sevilla",
    "wof:name":"Luque E Hijos S.l.",
    "wof:placetype":"venue"
},
  "geometry": {"coordinates":[-5.9281339645,37.2829055786],"type":"Point"}
}