{
  "type": "Feature",
  "properties": {
    "addr:full":"Ctra Pozuelo, 8 Argamason Albacete 02328",
    "addr:housenumber":"8",
    "addr:postcode":"02328",
    "addr:street":"Ctra Pozuelo",
    "iso:country":"ES",
    "sg:address":"Ctra Pozuelo, 8",
    "sg:city":"Argamason",
    "sg:orig_category":"Chapister\u00cda",
    "sg:phone":"+34 967 27 02 45",
    "sg:postcode":"02328",
    "sg:province":"Albacete",
    "wof:name":"Eloy Baidez Corcoles Y Teofilo Manuel Corcoles Garcia Cdad",
    "wof:placetype":"venue"
},
  "geometry": {"coordinates":[-1.9934519529,38.9028511047],"type":"Point"}
}