{
  "type": "Feature",
  "properties": {
    "addr:full":"Calle de Santiago, 1 Salamanca Salamanca 37008",
    "addr:housenumber":"1",
    "addr:postcode":"37008",
    "addr:street":"Calle De Santiago",
    "iso:country":"ES",
    "sg:address":"Calle de Santiago, 1",
    "sg:city":"Salamanca",
    "sg:orig_category":"Ense\u00d1anza, Formaci\u00d3n Profesional: Aprendizaje",
    "sg:phone":"+34 923 21 95 11",
    "sg:postcode":"37008",
    "sg:province":"Salamanca",
    "wof:name":"Casa Escuelas Pias Santiago 1 P.p. Escolapios",
    "wof:placetype":"venue"
},
  "geometry": {"coordinates":[-5.6677489281,40.9586791992],"type":"Point"}
}