{
  "type": "Feature",
  "properties": {
    "iso:country":"ES",
    "sg:address":"Pase Isabel La Catolica, 10",
    "sg:city":"Tordesillas",
    "sg:orig_category":"Carb\u00d3n, Carb\u00d3n De Madera (al Por Mayor)",
    "sg:phone":"+34 983 77 15 22",
    "sg:postcode":"47100",
    "sg:province":"Valladolid",
    "wof:name":"Lozar Garcia Modesto De",
    "wof:placetype":"venue"
},
  "geometry": {"coordinates":[-5.005384922,41.5045280457],"type":"Point"}
}