{
  "type": "Feature",
  "properties": {
    "addr:full":"Avda Nuestra Se\u00d1ora De Valvanera, 93 Madrid Madrid 28025",
    "addr:housenumber":"93",
    "addr:postcode":"madrid;28025",
    "addr:street":"Avda Nuestra Sen\u0303Ora De Valvanera",
    "iso:country":"ES",
    "sg:address":"Avda Nuestra Se\u00d1ora De Valvanera, 93",
    "sg:city":"Madrid",
    "sg:orig_category":"Fabricaci\u00d3n, Venta De Cuadros, Accesorios Para Enmarcar",
    "sg:phone":"+34 914 61 60 72",
    "sg:postcode":"28025",
    "sg:province":"Madrid",
    "wof:name":"Cuesta Romero Mariano",
    "wof:placetype":"venue"
},
  "geometry": {"coordinates":[-3.7381989956,40.3913536072],"type":"Point"}
}