{
  "type": "Feature",
  "properties": {
    "addr:full":"Avda Concepcion Arenal, 34 Praia Pontevedra 36950",
    "addr:housenumber":"34",
    "addr:postcode":"36950",
    "addr:street":"Avda Concepcion Arenal",
    "iso:country":"ES",
    "sg:address":"Avda Concepcion Arenal, 34",
    "sg:city":"Praia",
    "sg:orig_category":"Sanatorios M\u00c9dico",
    "sg:phone":"+34 986 31 17 12",
    "sg:postcode":"36950",
    "sg:province":"Pontevedra",
    "wof:name":"Sergas-gerencia De Atencion Primaria Pontevedra Sur",
    "wof:placetype":"venue"
},
  "geometry": {"coordinates":[-8.738442421,42.2772254944],"type":"Point"}
}