{
  "type": "Feature",
  "properties": {
    "iso:country":"ES",
    "sg:address":"Carrer de Comte D'urgell, 241",
    "sg:city":"Barcelona",
    "sg:orig_category":"Agentes Generales De Seguros",
    "sg:phone":"+34 934 19 25 22",
    "sg:postcode":"08036",
    "sg:province":"Barcelona",
    "wof:name":"Goyenchea Tejero Joaquin",
    "wof:placetype":"venue"
},
  "geometry": {"coordinates":[2.1467642784,41.3910140991],"type":"Point"}
}