{
  "type": "Feature",
  "properties": {
    "addr:full":"Carrer de Lluna, 25 Santa Barbara Tarragona 43570",
    "addr:housenumber":"25",
    "addr:postcode":"43570",
    "addr:street":"Carrer De Lluna",
    "iso:country":"ES",
    "sg:address":"Carrer de Lluna, 25",
    "sg:city":"Santa Barbara",
    "sg:orig_category":"Barnizadores",
    "sg:phone":"+34 977 71 94 35",
    "sg:postcode":"43570",
    "sg:province":"Tarragona",
    "wof:name":"Clua Espuny Miguel Angel",
    "wof:placetype":"venue"
},
  "geometry": {"coordinates":[0.4899500012,40.715221405],"type":"Point"}
}