{
  "type": "Feature",
  "properties": {
    "addr:full":"Calle de Gonzalo De Berceo, 14 Logro\u00f1o La Rioja 26005",
    "addr:housenumber":"14",
    "addr:postcode":"26005",
    "addr:street":"Calle De Gonzalo De Berceo;Rioja",
    "iso:country":"ES",
    "sg:address":"Calle de Gonzalo De Berceo, 14",
    "sg:city":"Logro\u00f1o",
    "sg:orig_category":"Oficinas: Suministros Para (fabricaci\u00d3n, Al Por Mayor)",
    "sg:phone":"+34 941 20 00 41",
    "sg:postcode":"26005",
    "sg:province":"La Rioja",
    "sg:website":"www.entrecomillas.net",
    "wof:name":"Maria Jesus Gonzalez Martinez Y Otro S.l.",
    "wof:placetype":"venue"
},
  "geometry": {"coordinates":[-2.4561550617,42.4658508301],"type":"Point"}
}