{
  "type": "Feature",
  "properties": {
    "iso:country":"ES",
    "sg:address":"Carr Galeries Sant Lluis, 13",
    "sg:city":"Platja D'aro",
    "sg:orig_category":"Ropa Para Caballeros (al Por Menor)",
    "sg:phone":"+34 972 81 78 46",
    "sg:postcode":"17250",
    "sg:province":"Girona",
    "wof:name":"Heras Darne S.l.",
    "wof:placetype":"venue"
},
  "geometry": {"coordinates":[2.8187398911,41.9808616638],"type":"Point"}
}