{
  "type": "Feature",
  "properties": {
    "addr:full":"Calle de Oviedo, 6 Humanes De Madrid Madrid 28970",
    "addr:housenumber":"6",
    "addr:postcode":"28970",
    "addr:street":"Calle De Oviedo",
    "iso:country":"ES",
    "sg:address":"Calle de Oviedo, 6",
    "sg:city":"Humanes De Madrid",
    "sg:orig_category":"Puertas Y Portales",
    "sg:phone":"+34 916 97 85 96",
    "sg:postcode":"28970",
    "sg:province":"Madrid",
    "wof:name":"Puertas Pege S.l.",
    "wof:placetype":"venue"
},
  "geometry": {"coordinates":[-3.8242499828,40.2717666626],"type":"Point"}
}