{
  "type": "Feature",
  "properties": {
    "addr:full":"Carr Sant Nicolau, 8 S. Lloren\u00e7 Morunys Lleida 25282",
    "addr:housenumber":"8",
    "addr:postcode":"25282",
    "addr:street":"Carr Sant Nicolau",
    "iso:country":"ES",
    "sg:address":"Carr Sant Nicolau, 8",
    "sg:city":"S. Lloren\u00e7 Morunys",
    "sg:orig_category":"Asociaciones Y Clubs Deportivos",
    "sg:phone":"+34 973 49 26 57",
    "sg:postcode":"25282",
    "sg:province":"Lleida",
    "wof:name":"Palau Nicolau Maria Isabel",
    "wof:placetype":"venue"
},
  "geometry": {"coordinates":[1.5712449551,42.1387481689],"type":"Point"}
}