{
  "type": "Feature",
  "properties": {
    "iso:country":"ES",
    "sg:address":"Calle de Orlando Agudo, 1",
    "sg:city":"Pozuelo De Alarcon",
    "sg:orig_category":"Mercer\u00cda, Lencer\u00cda (al Por Menor)",
    "sg:phone":"+34 913 52 10 81",
    "sg:postcode":"28224",
    "sg:province":"Madrid",
    "wof:name":"Asensio Garcia Antonio",
    "wof:placetype":"venue"
},
  "geometry": {"coordinates":[-3.7967083454,40.4515838623],"type":"Point"}
}