{
  "type": "Feature",
  "properties": {
    "iso:country":"ES",
    "sg:address":"Calle de Arabial, 73",
    "sg:city":"Granada",
    "sg:orig_category":"Materiales De Construcci\u00d3n (en General)",
    "sg:phone":"+34 958 29 06 87",
    "sg:postcode":"18004",
    "sg:province":"Granada",
    "sg:website":"www.memoriafamiliar.com",
    "wof:name":"Fast Forward Invest S.a.",
    "wof:placetype":"venue"
},
  "geometry": {"coordinates":[-3.6107406616,37.175567627],"type":"Point"}
}