{
  "type": "Feature",
  "properties": {
    "iso:country":"ES",
    "sg:address":"Calle de Santillana, 3",
    "sg:city":"Fuentepelayo",
    "sg:orig_category":"Farmacias",
    "sg:phone":"+34 921 57 43 92",
    "sg:postcode":"40260",
    "sg:province":"Segovia",
    "wof:name":"Sanchez Llanes Maria Victoria",
    "wof:placetype":"venue"
},
  "geometry": {"coordinates":[-4.1753840446,41.2203865051],"type":"Point"}
}