{
  "type": "Feature",
  "properties": {
    "iso:country":"ES",
    "sg:address":"Calle de Puente (el) Barrio Nuevo, 9",
    "sg:city":"San Cristobal De La Laguna",
    "sg:orig_category":"Ropa Para Se\u00d1oras Y Caballeros (al Por Menor)",
    "sg:phone":"+34 922 26 01 97",
    "sg:postcode":"38205",
    "sg:province":"Santa Cruz De Tenerife",
    "wof:name":"Salamel Lugo Rosa",
    "wof:placetype":"venue"
},
  "geometry": {"coordinates":[-16.298746109,28.4750785828],"type":"Point"}
}