{
  "type": "Feature",
  "properties": {
    "addr:full":"Avda Paz, S/n Valdecarros Salamanca 37881",
    "addr:housenumber":"s",
    "addr:postcode":"37881",
    "addr:street":"Avda Paz;/ N",
    "iso:country":"ES",
    "sg:address":"Avda Paz, S/n",
    "sg:city":"Valdecarros",
    "sg:orig_category":"Distribuci\u00d3n De Petr\u00d3leo Y Derivados",
    "sg:phone":"+34 923 38 34 29",
    "sg:postcode":"37881",
    "sg:province":"Salamanca",
    "wof:name":"Vicente Garcia Jesus Maria",
    "wof:placetype":"venue"
},
  "geometry": {"coordinates":[-5.4219989777,40.7693061829],"type":"Point"}
}