{
  "type": "Feature",
  "properties": {
    "addr:full":"Calle de Rico, 18 Huelva Huelva 21001",
    "addr:housenumber":"18",
    "addr:postcode":"21001",
    "addr:street":"Calle De Rico",
    "iso:country":"ES",
    "sg:address":"Calle de Rico, 18",
    "sg:city":"Huelva",
    "sg:orig_category":"Loter\u00cda Y T\u00d3mbola",
    "sg:phone":"+34 959 28 43 40",
    "sg:postcode":"21001",
    "sg:province":"Huelva",
    "wof:name":"Moreno Monserrat Alfonso Carlos",
    "wof:placetype":"venue"
},
  "geometry": {"coordinates":[-6.9525351524,37.2561798096],"type":"Point"}
}