{
  "type": "Feature",
  "properties": {
    "iso:country":"ES",
    "sg:address":"Carrer de Sant Jordi (de), 26",
    "sg:city":"Vila-seca",
    "sg:orig_category":"Puertas Y Portales",
    "sg:phone":"+34 977 39 08 58",
    "sg:postcode":"43480",
    "sg:province":"Tarragona",
    "wof:name":"Pe\u00f1a Vera Francisco",
    "wof:placetype":"venue"
},
  "geometry": {"coordinates":[1.1427619457,41.1112480164],"type":"Point"}
}