{
  "type": "Feature",
  "properties": {
    "iso:country":"ES",
    "sg:address":"Pase Alameda (la), 39",
    "sg:city":"Guadarrama",
    "sg:orig_category":"Zonas De Acampada, Aparcamiento Para Caravanas",
    "sg:phone":"+34 918 54 03 28",
    "sg:postcode":"28440",
    "sg:province":"Madrid",
    "wof:name":"Padres Agustinos De La Provincia De Castilla Fray Luis De Leon",
    "wof:placetype":"venue"
},
  "geometry": {"coordinates":[-4.0891890526,40.6723594666],"type":"Point"}
}