{
  "type": "Feature",
  "properties": {
    "iso:country":"ES",
    "sg:address":"Avda Rotary Internacional, 2",
    "sg:city":"Nueva Andalucia",
    "sg:orig_category":"Art\u00cdculos De Decoraci\u00d3n",
    "sg:phone":"+34 952 81 72 02",
    "sg:postcode":"29660",
    "sg:province":"M\u00e1laga",
    "sg:website":"www.zarahome.com",
    "wof:name":"Zara Home Espa\u00f1a",
    "wof:placetype":"venue"
},
  "geometry": {"coordinates":[-4.9550728798,36.4887199402],"type":"Point"}
}