{
  "type": "Feature",
  "properties": {
    "addr:full":"Plaz Italia, S/n Santander Cantabria 39005",
    "addr:housenumber":"s / n",
    "addr:postcode":"39005",
    "iso:country":"ES",
    "sg:address":"Plaz Italia, S/n",
    "sg:city":"Santander",
    "sg:orig_category":"Alimentaci\u00d3n General (al Por Menor)",
    "sg:phone":"+34 942 27 28 99",
    "sg:postcode":"39005",
    "sg:province":"Cantabria",
    "wof:name":"Gandara Garcia-monco Jesus",
    "wof:placetype":"venue"
},
  "geometry": {"coordinates":[-3.7830779552,43.4721870422],"type":"Point"}
}