{
  "type": "Feature",
  "properties": {
    "iso:country":"ES",
    "sg:address":"Calle de Bruselas, S/n",
    "sg:city":"Miguel Esteban",
    "sg:orig_category":"Centros Empresariales",
    "sg:phone":"+34 925 17 23 38",
    "sg:postcode":"45830",
    "sg:province":"Toledo",
    "wof:name":"Cerrajerias Del Este Sl",
    "wof:placetype":"venue"
},
  "geometry": {"coordinates":[-3.0776567459,39.5079116821],"type":"Point"}
}