{
  "type": "Feature",
  "properties": {
    "addr:full":"Calle de San Bartolome, 8 Cantillana Sevilla 41320",
    "addr:housenumber":"8",
    "addr:postcode":"41320",
    "addr:street":"Calle De San Bartolome",
    "iso:country":"ES",
    "sg:address":"Calle de San Bartolome, 8",
    "sg:city":"Cantillana",
    "sg:orig_category":"Cajas De Ahorro",
    "sg:phone":"+34 955 73 19 17",
    "sg:postcode":"41320",
    "sg:province":"Sevilla",
    "wof:name":"Caja San Fernando De Sevilla Y Jerez",
    "wof:placetype":"venue"
},
  "geometry": {"coordinates":[-5.824985981,37.6083374023],"type":"Point"}
}