{
  "type": "Feature",
  "properties": {
    "addr:full":"Avda Carlota Alessandri, 106 Torremolinos M\u00e1laga 29620",
    "addr:housenumber":"106",
    "addr:postcode":"29620",
    "addr:street":"Avda Carlota Alessandri;Ma\u0301Laga",
    "iso:country":"ES",
    "sg:address":"Avda Carlota Alessandri, 106",
    "sg:city":"Torremolinos",
    "sg:classifiers":[
        {
            "category":"Casinos & Gambling",
            "type":"Entertainment"
        }
    ],
    "sg:phone":"+34 952 37 77 32",
    "sg:postcode":"29620",
    "sg:province":"M\u00e1laga",
    "sg:tags":[
        "locale",
        "de",
        "juego"
    ],
    "wof:name":"Tecnirest Sociedad Limitada",
    "wof:placetype":"venue"
},
  "geometry": {"coordinates":[-4.5046749115,36.6129493713],"type":"Point"}
}