{
  "type": "Feature",
  "properties": {
    "iso:country":"ES",
    "sg:address":"Carrer de Clot, 63",
    "sg:city":"Barcelona",
    "sg:orig_category":"Fabricaci\u00d3n De Juegos Y Juguetes",
    "sg:phone":"+34 932 32 29 06",
    "sg:postcode":"08018",
    "sg:province":"Barcelona",
    "wof:name":"Paloma Hernandez Jaime Alfonso",
    "wof:placetype":"venue"
},
  "geometry": {"coordinates":[2.1882491112,41.4083404541],"type":"Point"}
}