{
  "type": "Feature",
  "properties": {
    "iso:country":"ES",
    "sg:address":"Carrer de Piscina, 36",
    "sg:city":"Costa D'en Gallina",
    "sg:orig_category":"Empresas De Pintura Y Revestimientos",
    "sg:phone":"+34 972 36 32 80",
    "sg:postcode":"17310",
    "sg:province":"Girona",
    "wof:name":"Gonzalez Ruiz Antonio",
    "wof:placetype":"venue"
},
  "geometry": {"coordinates":[2.7872281075,41.973236084],"type":"Point"}
}