{
  "type": "Feature",
  "properties": {
    "addr:full":"Avda Ntra Sra De Belen, 43 Alcala Henares Madrid 28802",
    "addr:housenumber":"43",
    "addr:postcode":"28802",
    "addr:street":"Avda Ntra Sra De Belen",
    "iso:country":"ES",
    "sg:address":"Avda Ntra Sra De Belen, 43",
    "sg:city":"Alcala Henares",
    "sg:orig_category":"Molduras, Junquillos, Listones Y Molduras Perforadas",
    "sg:phone":"+34 918 83 05 63",
    "sg:postcode":"28802",
    "sg:province":"Madrid",
    "wof:name":"Reyes Aguayo Antonio",
    "wof:placetype":"venue"
},
  "geometry": {"coordinates":[-3.3845410347,40.4774398804],"type":"Point"}
}