{
  "type": "Feature",
  "properties": {
    "addr:full":"Calle de Virgen De La Capilla, 15 Jaen Ja\u00e9n 23001",
    "addr:housenumber":"15;jae\u0301n",
    "addr:postcode":"23001",
    "addr:street":"Calle De Virgen De La Capilla",
    "iso:country":"ES",
    "sg:address":"Calle de Virgen De La Capilla, 15",
    "sg:city":"Jaen",
    "sg:orig_category":"Servicios De Telecomunicaciones",
    "sg:phone":"+34 953 29 10 97",
    "sg:postcode":"23001",
    "sg:province":"Ja\u00e9n",
    "sg:website":"www.unitec.es",
    "wof:name":"Unitec S.a.",
    "wof:placetype":"venue"
},
  "geometry": {"coordinates":[-3.786878109,37.7690734863],"type":"Point"}
}