{
  "type": "Feature",
  "properties": {
    "iso:country":"ES",
    "sg:address":"Calle de Lirios, Los, 44",
    "sg:city":"Siesta",
    "sg:orig_category":"Centros Empresariales",
    "sg:phone":"+34 971 33 93 66",
    "sg:postcode":"07840",
    "sg:province":"Islas Baleares",
    "wof:name":"Jansen Strutmann Doris",
    "wof:placetype":"venue"
},
  "geometry": {"coordinates":[1.5268269777,38.9830245972],"type":"Point"}
}