{
  "type": "Feature",
  "properties": {
    "iso:country":"ES",
    "sg:address":"Calle de Tejeras, 4",
    "sg:city":"Logro\u00f1o",
    "sg:orig_category":"Asociaciones Y Clubs Deportivos",
    "sg:phone":"+34 941 20 54 28",
    "sg:postcode":"26007",
    "sg:province":"La Rioja",
    "wof:name":"Dede S.l.",
    "wof:placetype":"venue"
},
  "geometry": {"coordinates":[-2.5187389851,42.4914894104],"type":"Point"}
}