{
  "type": "Feature",
  "properties": {
    "addr:full":"Plaz Doctor Laguna (del), 6 Segovia Segovia 40001",
    "addr:housenumber":"6",
    "addr:postcode":"40001",
    "addr:street":"Doctor Laguna Del",
    "iso:country":"ES",
    "sg:address":"Plaz Doctor Laguna (del), 6",
    "sg:city":"Segovia",
    "sg:orig_category":"Centros De Educaci\u00d3n Especial",
    "sg:phone":"+34 921 46 19 61",
    "sg:postcode":"40001",
    "sg:province":"Segovia",
    "wof:name":"Colegio Publico Domingo De Soto",
    "wof:placetype":"venue"
},
  "geometry": {"coordinates":[-4.1207609177,40.9500083923],"type":"Point"}
}