{
  "type": "Feature",
  "properties": {
    "addr:full":"Carrer de Girona, 16 S. Boi Llobregat Barcelona 08830",
    "addr:housenumber":"16",
    "addr:postcode":"08830",
    "addr:street":"Carrer De Girona",
    "iso:country":"ES",
    "sg:address":"Carrer de Girona, 16",
    "sg:city":"S. Boi Llobregat",
    "sg:orig_category":"Inmobiliaria (agencias)",
    "sg:phone":"+34 936 61 60 29",
    "sg:postcode":"08830",
    "sg:province":"Barcelona",
    "wof:name":"Ferman De Sant Boi Gestion Inmobiliaria S.l.",
    "wof:placetype":"venue"
},
  "geometry": {"coordinates":[2.0449779034,41.3480606079],"type":"Point"}
}