{
  "type": "Feature",
  "properties": {
    "addr:full":"Avda Alhambra, 20 Almeria Almer\u00eda 04007",
    "addr:housenumber":"20",
    "addr:postcode":"04007",
    "addr:street":"Avda Alhambra",
    "iso:country":"ES",
    "sg:address":"Avda Alhambra, 20",
    "sg:city":"Almeria",
    "sg:orig_category":"Panader\u00cdas, Panader\u00cdas",
    "sg:phone":"+34 950 27 09 53",
    "sg:postcode":"04007",
    "sg:province":"Almer\u00eda",
    "wof:name":"Martin Fernandez Josefa",
    "wof:placetype":"venue"
},
  "geometry": {"coordinates":[-2.4461894035,36.8263816833],"type":"Point"}
}