{
  "type": "Feature",
  "properties": {
    "iso:country":"ES",
    "sg:address":"Avda Llano Del, 8",
    "sg:city":"Gijon",
    "sg:orig_category":"Peluqueros: De Se\u00d1oras",
    "sg:phone":"+34 985 16 52 75",
    "sg:postcode":"33209",
    "sg:province":"Asturias",
    "wof:name":"Suadel S.l.",
    "wof:placetype":"venue"
},
  "geometry": {"coordinates":[-5.639647007,43.5119361877],"type":"Point"}
}