{
  "type": "Feature",
  "properties": {
    "iso:country":"ES",
    "sg:address":"Calle de Ulloa, 15",
    "sg:city":"Castellon",
    "sg:orig_category":"Negocio De Materiales De Construcci\u00d3n",
    "sg:phone":"+34 964 22 03 67",
    "sg:postcode":"12003",
    "sg:province":"Castell\u00f3n",
    "wof:name":"Iber Aqua 2002 S.l.",
    "wof:placetype":"venue"
},
  "geometry": {"coordinates":[-0.0307240002,39.9833145142],"type":"Point"}
}