{
  "type": "Feature",
  "properties": {
    "addr:full":"Calle de Ermodo Kalea, 3 Durango Vizcaya 48200",
    "addr:housenumber":"3",
    "addr:postcode":"48200",
    "addr:street":"Calle De Ermodo Kalea",
    "iso:country":"ES",
    "sg:address":"Calle de Ermodo Kalea, 3",
    "sg:city":"Durango",
    "sg:orig_category":"Confecci\u00d3n (fabricaci\u00d3n, Al Por Mayor)",
    "sg:phone":"+34 946 81 76 90",
    "sg:postcode":"48200",
    "sg:province":"Vizcaya",
    "wof:name":"Hermanos Del Rio Y Otros C.b.",
    "wof:placetype":"venue"
},
  "geometry": {"coordinates":[-2.6323869228,43.1695709229],"type":"Point"}
}