{
  "type": "Feature",
  "properties": {
    "iso:country":"ES",
    "sg:address":"Calle de Amalia Alayon, 12",
    "sg:city":"Cristianos",
    "sg:orig_category":"Art\u00cdculos De Regalo (al Por Menor)",
    "sg:phone":"+34 922 75 18 08",
    "sg:postcode":"38650",
    "sg:province":"Santa Cruz De Tenerife",
    "wof:name":"Gonzalez Fajardo Yadira",
    "wof:placetype":"venue"
},
  "geometry": {"coordinates":[-16.7156772614,28.052312851],"type":"Point"}
}