{
  "type": "Feature",
  "properties": {
    "iso:country":"ES",
    "sg:address":"Plaz Iglesia, 10",
    "sg:city":"Azaila",
    "sg:orig_category":"C\u00c1maras De Comercio E Industria, Oficios, Agricultura",
    "sg:phone":"+34 978 82 50 98",
    "sg:postcode":"44590",
    "sg:province":"Teruel",
    "wof:name":"Camara Agraria Local",
    "wof:placetype":"venue"
},
  "geometry": {"coordinates":[-0.4933570027,41.2891616821],"type":"Point"}
}