{
  "type": "Feature",
  "properties": {
    "addr:full":"Calle de Pelayo, 14 Gijon Asturias 33205",
    "addr:housenumber":"14",
    "addr:postcode":"33205",
    "addr:street":"Calle De Pelayo",
    "iso:country":"ES",
    "sg:address":"Calle de Pelayo, 14",
    "sg:city":"Gijon",
    "sg:orig_category":"Florister\u00cdas",
    "sg:phone":"+34 985 35 65 61",
    "sg:postcode":"33205",
    "sg:province":"Asturias",
    "wof:name":"Pi\u00f1ero Hevia Maria Aurora Bego\u00f1a",
    "wof:placetype":"venue"
},
  "geometry": {"coordinates":[-5.6626400948,43.538269043],"type":"Point"}
}