{
  "type": "Feature",
  "properties": {
    "addr:full":"Carretera De Valencia, S/n Villanueva Fresno Badajoz 06110",
    "addr:housenumber":"s",
    "addr:postcode":"06110",
    "addr:street":"Carretera De Valencia;/ N",
    "iso:country":"ES",
    "sg:address":"Carretera De Valencia, S/n",
    "sg:city":"Villanueva Fresno",
    "sg:orig_category":"Negocio De Materiales De Construcci\u00d3n",
    "sg:phone":"+34 924 42 73 85",
    "sg:postcode":"06110",
    "sg:province":"Badajoz",
    "wof:name":"Ardila Cumplido Manuela",
    "wof:placetype":"venue"
},
  "geometry": {"coordinates":[-7.1219921112,38.2706832886],"type":"Point"}
}