{
  "type": "Feature",
  "properties": {
    "addr:full":"Luga Cuesta Del Pozo, 1 Marzagan Las Palmas 35016",
    "addr:housenumber":"1",
    "addr:postcode":"35016",
    "addr:street":"Cuesta Del Pozo",
    "iso:country":"ES",
    "sg:address":"Luga Cuesta Del Pozo, 1",
    "sg:city":"Marzagan",
    "sg:orig_category":"Frutas Y Legumbres Frescas (al Por Mayor)",
    "sg:phone":"+34 928 70 90 95",
    "sg:postcode":"35016",
    "sg:province":"Las Palmas",
    "wof:name":"Organizacion De Productores De Frutas Y Hortalizas De Las Islas Canarias",
    "wof:placetype":"venue"
},
  "geometry": {"coordinates":[-15.4306898117,28.0386505127],"type":"Point"}
}