{
  "type": "Feature",
  "properties": {
    "iso:country":"ES",
    "sg:address":"Puerto Pesquero, S/n",
    "sg:city":"Motril",
    "sg:orig_category":"Empresas Portuarias",
    "sg:phone":"+34 958 82 51 55",
    "sg:postcode":"18600",
    "sg:province":"Granada",
    "wof:name":"Sociedad Estatal De Estiba Y Desestiba Del Puerto De Motril S.a.",
    "wof:placetype":"venue"
},
  "geometry": {"coordinates":[-3.5182590485,36.7550849915],"type":"Point"}
}