{
  "type": "Feature",
  "properties": {
    "addr:full":"Calle de Alberto Gomez Arroyo, S/n Villamuriel De Cerrato Palencia 34190",
    "addr:housenumber":"/ n",
    "addr:postcode":"34190",
    "addr:street":"Calle De Alberto Gomez Arroyo S",
    "iso:country":"ES",
    "sg:address":"Calle de Alberto Gomez Arroyo, S/n",
    "sg:city":"Villamuriel De Cerrato",
    "sg:orig_category":"Carnicer\u00cdas, Carnicer\u00cdas",
    "sg:phone":"+34 979 77 61 29",
    "sg:postcode":"34190",
    "sg:province":"Palencia",
    "wof:name":"Paredes De La Fuente Federico",
    "wof:placetype":"venue"
},
  "geometry": {"coordinates":[-4.5155472755,41.949672699],"type":"Point"}
}