{
  "type": "Feature",
  "properties": {
    "iso:country":"ES",
    "sg:address":"Calle de Libertad (la), 107",
    "sg:city":"Pto. Rosario",
    "sg:orig_category":"Asesor\u00cda Fiscal Y Jur\u00cddica",
    "sg:phone":"+34 928 85 93 05",
    "sg:postcode":"35600",
    "sg:province":"Las Palmas",
    "wof:name":"Barrera Y Rivero S.l.",
    "wof:placetype":"venue"
},
  "geometry": {"coordinates":[-13.8698987961,28.5073299408],"type":"Point"}
}