{
  "type": "Feature",
  "properties": {
    "iso:country":"ES",
    "sg:address":"Calle de Eugenio Salazar, 37",
    "sg:city":"Madrid",
    "sg:orig_category":"Asociaciones Humanitarias, De Cooperaci\u00d3n, De Acci\u00d3n Social",
    "sg:phone":"+34 914 13 89 54",
    "sg:postcode":"28002",
    "sg:province":"Madrid",
    "wof:name":"Socorro Urgente A Los Necesitados",
    "wof:placetype":"venue"
},
  "geometry": {"coordinates":[-3.6750817299,40.4467201233],"type":"Point"}
}