{
  "type": "Feature",
  "properties": {
    "iso:country":"ES",
    "sg:address":"C/ Bilbao, S/n",
    "sg:city":"Ripollet",
    "sg:orig_category":"Rectificaci\u00d3n, Mecanizado, Fresado",
    "sg:phone":"+34 936 92 34 40",
    "sg:postcode":"08291",
    "sg:province":"Barcelona",
    "wof:name":"Talleres Mecanicos Mont-sar S.l.",
    "wof:placetype":"venue"
},
  "geometry": {"coordinates":[2.1608951092,41.4929351807],"type":"Point"}
}