{
  "type": "Feature",
  "properties": {
    "iso:country":"ES",
    "sg:address":"Praz Irmans Garcia Naveira, 7",
    "sg:city":"Betanzos",
    "sg:orig_category":"M\u00c9dicos: Estomatolog\u00cda",
    "sg:phone":"+34 981 77 42 81",
    "sg:postcode":"15300",
    "sg:province":"La Coru\u00f1a",
    "wof:name":"Nu\u00f1ez Nu\u00f1ez Enrique",
    "wof:placetype":"venue"
},
  "geometry": {"coordinates":[-8.2098836899,43.2795906067],"type":"Point"}
}