{
  "type": "Feature",
  "properties": {
    "iso:country":"ES",
    "sg:address":"Pg Mare De Deu Del Coll, 18",
    "sg:city":"Barcelona",
    "sg:orig_category":"Alimentaci\u00d3n General (al Por Menor)",
    "sg:phone":"+34 932 13 34 59",
    "sg:postcode":"08023",
    "sg:province":"Barcelona",
    "wof:name":"Disbelen S. L.",
    "wof:placetype":"venue"
},
  "geometry": {"coordinates":[2.1453979015,41.4149436951],"type":"Point"}
}