{
  "type": "Feature",
  "properties": {
    "iso:country":"ES",
    "sg:address":"Carrer de Carme, 44",
    "sg:city":"Malgrat Mar",
    "sg:orig_category":"Bancos",
    "sg:phone":"+34 937 65 47 11",
    "sg:postcode":"08380",
    "sg:province":"Barcelona",
    "wof:name":"Banc Sabadell S.a.",
    "wof:placetype":"venue"
},
  "geometry": {"coordinates":[2.7406079769,41.6452522278],"type":"Point"}
}