{
  "type": "Feature",
  "properties": {
    "addr:full":"Carretera De Zaragoza Leci\u00f1ena, Km. 0023,0 Leci\u00d1ena Zaragoza 50160",
    "addr:postcode":"50160",
    "addr:street":"Carretera De Zaragoza Lecin\u0303Ena Km. 0023,0",
    "iso:country":"ES",
    "sg:address":"Carretera De Zaragoza Leci\u00f1ena, Km. 0023,0",
    "sg:city":"Leci\u00d1ena",
    "sg:orig_category":"Fabricaci\u00d3n Y Venta De Volquetes Y Remolques",
    "sg:phone":"+34 976 16 61 10",
    "sg:postcode":"50160",
    "sg:province":"Zaragoza",
    "sg:website":"www.fabrisem.com",
    "wof:name":"Fabrisem S.l.",
    "wof:placetype":"venue"
},
  "geometry": {"coordinates":[-0.6103140116,41.797618866],"type":"Point"}
}