{
  "type": "Feature",
  "properties": {
    "addr:full":"Velazquez, 83 Madrid Madrid 28006",
    "addr:housenumber":"83",
    "addr:postcode":"madrid;28006",
    "addr:street":"Velazquez",
    "iso:country":"ES",
    "sg:address":"Velazquez, 83",
    "sg:city":"Madrid",
    "sg:orig_category":"Notarios",
    "sg:phone":"+34 915 64 24 51",
    "sg:postcode":"28006",
    "sg:province":"Madrid",
    "wof:name":"Diez Herrera Juan",
    "wof:placetype":"venue"
},
  "geometry": {"coordinates":[-3.6836390495,40.4333152771],"type":"Point"}
}