{
  "type": "Feature",
  "properties": {
    "addr:full":"Calle de Alamos, 8 Alcala Real Ja\u00e9n 23680",
    "addr:housenumber":"8",
    "addr:postcode":"23680",
    "addr:street":"Calle De Alamos;Jae\u0301N",
    "iso:country":"ES",
    "sg:address":"Calle de Alamos, 8",
    "sg:city":"Alcala Real",
    "sg:orig_category":"Delegados, Agentes De Tr\u00c1nsito, Auxiliares De Transporte Internacional",
    "sg:phone":"+34 953 58 21 52",
    "sg:postcode":"23680",
    "sg:province":"Ja\u00e9n",
    "sg:website":"www.autocarescontreras.com",
    "wof:name":"Contreras S.a.",
    "wof:placetype":"venue"
},
  "geometry": {"coordinates":[-3.9422953129,37.5269393921],"type":"Point"}
}