{
  "type": "Feature",
  "properties": {
    "addr:full":"Calle de Real, 157 Castilleja Cuesta Sevilla 41950",
    "addr:housenumber":"157",
    "addr:postcode":"41950",
    "addr:street":"Calle De Real",
    "iso:country":"ES",
    "sg:address":"Calle de Real, 157",
    "sg:city":"Castilleja Cuesta",
    "sg:orig_category":"Florister\u00cdas",
    "sg:phone":"+34 954 16 29 53",
    "sg:postcode":"41950",
    "sg:province":"Sevilla",
    "wof:name":"Garcia Pimiento Angeles",
    "wof:placetype":"venue"
},
  "geometry": {"coordinates":[-6.0580182076,37.3850517273],"type":"Point"}
}