{
  "type": "Feature",
  "properties": {
    "addr:full":"Calle de Alfonso X El Sabio, 4 Toledo Toledo 45002",
    "addr:housenumber":"4",
    "addr:postcode":"45002",
    "addr:street":"Calle De Alfonso X El Sabio",
    "iso:country":"ES",
    "sg:address":"Calle de Alfonso X El Sabio, 4",
    "sg:city":"Toledo",
    "sg:orig_category":"Bordado, Marcado A Medida",
    "sg:phone":"+34 925 22 48 66",
    "sg:postcode":"45002",
    "sg:province":"Toledo",
    "wof:name":"Diaz Bermudez Roman",
    "wof:placetype":"venue"
},
  "geometry": {"coordinates":[-4.0256586075,39.8585128784],"type":"Point"}
}