{
  "type": "Feature",
  "properties": {
    "addr:full":"Rua Eduardo Iglesias, 2 Vigo Pontevedra 36202",
    "addr:housenumber":"2",
    "addr:postcode":"36202",
    "addr:street":"Rua Eduardo Iglesias",
    "iso:country":"ES",
    "sg:address":"Rua Eduardo Iglesias, 2",
    "sg:city":"Vigo",
    "sg:orig_category":"Ropa Para Se\u00d1oras (al Por Menor)",
    "sg:phone":"+34 986 43 63 55",
    "sg:postcode":"36202",
    "sg:province":"Pontevedra",
    "sg:website":"www.simorra.com",
    "wof:name":"Simorra Tiendas S.a.",
    "wof:placetype":"venue"
},
  "geometry": {"coordinates":[-8.7225465775,42.236579895],"type":"Point"}
}