{
  "type": "Feature",
  "properties": {
    "addr:full":"Calle de Corregidor Diego De Valderrabano, 70 Madrid Madrid 28030",
    "addr:housenumber":"70",
    "addr:postcode":"madrid;28030",
    "addr:street":"Calle De Corregidor Diego De Valderrabano",
    "iso:country":"ES",
    "sg:address":"Calle de Corregidor Diego De Valderrabano, 70",
    "sg:city":"Madrid",
    "sg:orig_category":"Asesor\u00cda Sobre Comunicaci\u00d3n De Empresas",
    "sg:phone":"+34 914 37 89 11",
    "sg:postcode":"28030",
    "sg:province":"Madrid",
    "wof:name":"Aserinte,asesoria De Empresas S.l",
    "wof:placetype":"venue"
},
  "geometry": {"coordinates":[-3.6580138206,40.4124526978],"type":"Point"}
}