{
  "type": "Feature",
  "properties": {
    "addr:full":"Plaz San Antonio De Padua, 1 Sevilla Sevilla 41002",
    "addr:housenumber":"1",
    "addr:postcode":"41002",
    "addr:street":"Plaz San Antonio;Padua",
    "iso:country":"ES",
    "sg:address":"Plaz San Antonio De Padua, 1",
    "sg:city":"Sevilla",
    "sg:orig_category":"Transportes Por Carretera: Lotes Completos, Mercanc\u00cdas Diversas",
    "sg:phone":"+34 954 90 22 84",
    "sg:postcode":"41002",
    "sg:province":"Sevilla",
    "wof:name":"Rangel Garcia Antonio",
    "wof:placetype":"venue"
},
  "geometry": {"coordinates":[-5.9983639717,37.3978500366],"type":"Point"}
}