{
  "type": "Feature",
  "properties": {
    "iso:country":"ES",
    "sg:address":"Calle de Durazno (el), 11",
    "sg:city":"Icod De Los Vinos",
    "sg:orig_category":"Cl\u00cdnicas Dentales",
    "sg:phone":"+34 922 81 29 98",
    "sg:postcode":"38430",
    "sg:province":"Santa Cruz De Tenerife",
    "wof:name":"Gonzalez Luis-ravelo Ana Gloria",
    "wof:placetype":"venue"
},
  "geometry": {"coordinates":[-16.7164764404,28.3677272797],"type":"Point"}
}