{
  "type": "Feature",
  "properties": {
    "iso:country":"ES",
    "sg:address":"Pol Ind Polirrosa, 7",
    "sg:city":"Huelva",
    "sg:orig_category":"Electricidad, Electr\u00d3nica: Material Y Suministros (al Por Mayor)",
    "sg:phone":"+34 959 27 00 73",
    "sg:postcode":"21007",
    "sg:province":"Huelva",
    "wof:name":"Alvarez Beltran S.a.",
    "wof:placetype":"venue"
},
  "geometry": {"coordinates":[-6.8994493484,37.2885742188],"type":"Point"}
}