{
  "type": "Feature",
  "properties": {
    "iso:country":"ES",
    "sg:address":"Carrer de Tenor Vi\u00d1as, 18",
    "sg:city":"Roca Valles",
    "sg:orig_category":"Maquinaria Para Industrias Diversas",
    "sg:phone":"+34 938 42 27 50",
    "sg:postcode":"08430",
    "sg:province":"Barcelona",
    "wof:name":"Metenic S. A.",
    "wof:placetype":"venue"
},
  "geometry": {"coordinates":[2.3770260811,41.6025276184],"type":"Point"}
}