{
  "type": "Feature",
  "properties": {
    "addr:full":"Calle de Talavera, 26 Plasencia C\u00e1ceres 10600",
    "addr:housenumber":"26",
    "addr:postcode":"10600",
    "addr:street":"Calle De Talavera;Ca\u0301Ceres",
    "iso:country":"ES",
    "sg:address":"Calle de Talavera, 26",
    "sg:city":"Plasencia",
    "sg:orig_category":"Bancos",
    "sg:phone":"+34 927 42 60 00",
    "sg:postcode":"10600",
    "sg:province":"C\u00e1ceres",
    "wof:name":"Banco Espa\u00f1ol De Credito S.a.",
    "wof:placetype":"venue"
},
  "geometry": {"coordinates":[-6.0895662308,40.0291900635],"type":"Point"}
}