{
  "type": "Feature",
  "properties": {
    "addr:full":"Carrer de Antonio Acedo De Sopetran, 6 Vilafranca Penedes Barcelona 08720",
    "addr:housenumber":"6",
    "addr:postcode":"08720",
    "addr:street":"Carrer De Antonio Acedo De Sopetran;Penedes Barcelona",
    "iso:country":"ES",
    "sg:address":"Carrer de Antonio Acedo De Sopetran, 6",
    "sg:city":"Vilafranca Penedes",
    "sg:orig_category":"Agencias Y Agentes Comerciales, Representantes",
    "sg:phone":"+34 938 18 23 96",
    "sg:postcode":"08720",
    "sg:province":"Barcelona",
    "wof:name":"Tellez Ramiro Maria Isabel",
    "wof:placetype":"venue"
},
  "geometry": {"coordinates":[1.6992199421,41.3447799683],"type":"Point"}
}