{
  "type": "Feature",
  "properties": {
    "addr:full":"Calle de Ruise\u00d1or, 8 Dos Hermanas Sevilla 41700",
    "addr:housenumber":"8",
    "addr:postcode":"41700",
    "addr:street":"Calle De Ruisen\u0303Or;Sevilla",
    "iso:country":"ES",
    "sg:address":"Calle de Ruise\u00d1or, 8",
    "sg:city":"Dos Hermanas",
    "sg:orig_category":"Reposter\u00cdas",
    "sg:phone":"+34 954 72 09 76",
    "sg:postcode":"41700",
    "sg:province":"Sevilla",
    "wof:name":"Ramos Orea Carmen",
    "wof:placetype":"venue"
},
  "geometry": {"coordinates":[-5.928399086,37.2737922668],"type":"Point"}
}