{
  "type": "Feature",
  "properties": {
    "addr:full":"Calle de Cal Nueva, 18 Lietor Albacete 02410",
    "addr:housenumber":"18",
    "addr:postcode":"02410",
    "addr:street":"Calle De Cal Nueva",
    "iso:country":"ES",
    "sg:address":"Calle de Cal Nueva, 18",
    "sg:city":"Lietor",
    "sg:orig_category":"Supermercados Y Hipermercados",
    "sg:phone":"+34 967 20 00 99",
    "sg:postcode":"02410",
    "sg:province":"Albacete",
    "wof:name":"Olmo Casta\u00f1o Rafael",
    "wof:placetype":"venue"
},
  "geometry": {"coordinates":[-1.9551196098,38.5400009155],"type":"Point"}
}