{
  "type": "Feature",
  "properties": {
    "iso:country":"ES",
    "sg:address":"Carrer de Alts Forns, 51",
    "sg:city":"Barcelona",
    "sg:orig_category":"Ingenier\u00cda, Centros De Estudios (diversos)",
    "sg:phone":"+34 932 96 42 89",
    "sg:postcode":"08038",
    "sg:province":"Barcelona",
    "wof:name":"Gonzalez Perez Antonio",
    "wof:placetype":"venue"
},
  "geometry": {"coordinates":[2.139195919,41.3581314087],"type":"Point"}
}