{
  "type": "Feature",
  "properties": {
    "addr:full":"Plaz Alonso Carrillo (de), 8 Alcala Henares Madrid 28805",
    "addr:postcode":"28805",
    "addr:street":"Plaz",
    "iso:country":"ES",
    "sg:address":"Plaz Alonso Carrillo (de), 8",
    "sg:city":"Alcala Henares",
    "sg:orig_category":"Pescader\u00cdas (al Por Menor)",
    "sg:phone":"+34 918 81 98 78",
    "sg:postcode":"28805",
    "sg:province":"Madrid",
    "wof:name":"Serrano Garcia Aurelio",
    "wof:placetype":"venue"
},
  "geometry": {"coordinates":[-3.3566870689,40.488735199],"type":"Point"}
}