{
  "type": "Feature",
  "properties": {
    "iso:country":"ES",
    "sg:address":"Calle de Arquitecto Tolsa, 20",
    "sg:city":"Valencia",
    "sg:orig_category":"Farmacias",
    "sg:phone":"+34 963 65 19 82",
    "sg:postcode":"46019",
    "sg:province":"Valencia",
    "wof:name":"Ferrer Jaureguizar Rufino",
    "wof:placetype":"venue"
},
  "geometry": {"coordinates":[-0.3681817949,39.4938659668],"type":"Point"}
}