{
  "type": "Feature",
  "properties": {
    "addr:full":"Calle de Don Tello, 7 Gernika-lumo Vizcaya 48300",
    "addr:housenumber":"7",
    "addr:postcode":"48300",
    "addr:street":"Calle De Don Tello",
    "iso:country":"ES",
    "sg:address":"Calle de Don Tello, 7",
    "sg:city":"Gernika-lumo",
    "sg:orig_category":"Fotocopias, Reprograf\u00cda",
    "sg:phone":"+34 946 27 01 26",
    "sg:postcode":"48300",
    "sg:province":"Vizcaya",
    "wof:name":"Gecopryd S.l.",
    "wof:placetype":"venue"
},
  "geometry": {"coordinates":[-2.6760191917,43.3167266846],"type":"Point"}
}