{
  "type": "Feature",
  "properties": {
    "addr:full":"Avda Andalucia, S/n Oria Almer\u00eda 04810",
    "addr:postcode":"04810",
    "addr:street":"Avda Andalucia S / N Oria Almeri\u0301A",
    "iso:country":"ES",
    "sg:address":"Avda Andalucia, S/n",
    "sg:city":"Oria",
    "sg:orig_category":"Distribuci\u00d3n De Petr\u00d3leo Y Derivados",
    "sg:phone":"+34 950 12 27 12",
    "sg:postcode":"04810",
    "sg:province":"Almer\u00eda",
    "wof:name":"Lizarte Torrente Jose Antonio",
    "wof:placetype":"venue"
},
  "geometry": {"coordinates":[-2.2899041176,37.4858551025],"type":"Point"}
}