{
  "type": "Feature",
  "properties": {
    "addr:full":"Avda Casalduch, 102 Castellon Castell\u00f3n 12005",
    "addr:housenumber":"102",
    "addr:postcode":"12005",
    "addr:street":"Avda Casalduch;Castello\u0301N",
    "iso:country":"ES",
    "sg:address":"Avda Casalduch, 102",
    "sg:city":"Castellon",
    "sg:orig_category":"Armas Y Municiones (fabricaci\u00d3n, Al Por Mayor)",
    "sg:phone":"+34 964 22 35 77",
    "sg:postcode":"12005",
    "sg:province":"Castell\u00f3n",
    "wof:name":"Badenes Calduch Manuel",
    "wof:placetype":"venue"
},
  "geometry": {"coordinates":[-0.0450907014,39.975151062],"type":"Point"}
}