{
  "type": "Feature",
  "properties": {
    "addr:full":"Avgd Balmes, 44 Lleida Lleida 25006",
    "addr:housenumber":"44",
    "addr:postcode":"25006",
    "addr:street":"Avgd Balmes",
    "iso:country":"ES",
    "sg:address":"Avgd Balmes, 44",
    "sg:city":"Lleida",
    "sg:orig_category":"Farmacias",
    "sg:phone":"+34 973 23 16 64",
    "sg:postcode":"25006",
    "sg:province":"Lleida",
    "wof:name":"Anadon Sole Ramon",
    "wof:placetype":"venue"
},
  "geometry": {"coordinates":[0.6193131208,41.6189727783],"type":"Point"}
}