{
  "type": "Feature",
  "properties": {
    "iso:country":"ES",
    "sg:address":"Calle de Juan Pablos, 21",
    "sg:city":"Sevilla",
    "sg:orig_category":"Mercer\u00cda, Lencer\u00cda (al Por Menor)",
    "sg:phone":"+34 954 61 71 97",
    "sg:postcode":"41013",
    "sg:province":"Sevilla",
    "wof:name":"Siatelo Martinez Ana",
    "wof:placetype":"venue"
},
  "geometry": {"coordinates":[-5.982006073,37.3708839417],"type":"Point"}
}