{
  "type": "Feature",
  "properties": {
    "addr:full":"Gta Guzman, 4 Le\u00f3n Le\u00f3n 24004",
    "addr:housenumber":"4",
    "addr:postcode":"24004",
    "addr:street":"Gta Guzman;Leo\u0301N",
    "iso:country":"ES",
    "sg:address":"Gta Guzman, 4",
    "sg:city":"Le\u00f3n",
    "sg:orig_category":"Asesor\u00cda Fiscal Y Jur\u00cddica",
    "sg:phone":"+34 987 20 78 82",
    "sg:postcode":"24004",
    "sg:province":"Le\u00f3n",
    "wof:name":"Simo Fernandez Vicente",
    "wof:placetype":"venue"
},
  "geometry": {"coordinates":[-5.5779700279,42.5961303711],"type":"Point"}
}