{
  "type": "Feature",
  "properties": {
    "addr:full":"Pla\u00c7 Reial, 2 Mao Islas Baleares 07702",
    "addr:housenumber":"2",
    "addr:postcode":"07702",
    "addr:street":"Reial",
    "iso:country":"ES",
    "sg:address":"Pla\u00c7 Reial, 2",
    "sg:city":"Mao",
    "sg:orig_category":"Bancos",
    "sg:phone":"+34 971 36 88 46",
    "sg:postcode":"07702",
    "sg:province":"Islas Baleares",
    "wof:name":"Bankinter S.a.",
    "wof:placetype":"venue"
},
  "geometry": {"coordinates":[4.2648172379,39.8880195618],"type":"Point"}
}