{
  "type": "Feature",
  "properties": {
    "iso:country":"ES",
    "sg:address":"Pase Santo Tomas (de), 8",
    "sg:city":"Avila",
    "sg:orig_category":"Empresarios",
    "sg:phone":"+34 920 22 06 64",
    "sg:postcode":"05003",
    "sg:province":"\u00c1vila",
    "wof:name":"Hernandez Jimenez Tomas",
    "wof:placetype":"venue"
},
  "geometry": {"coordinates":[-4.6925120354,40.6457748413],"type":"Point"}
}