{
  "type": "Feature",
  "properties": {
    "addr:full":"Calle de Bermudez De Castro, 9 Oviedo Asturias 33011",
    "addr:housenumber":"9",
    "addr:postcode":"33011",
    "addr:street":"Calle De Bermudez De Castro",
    "iso:country":"ES",
    "sg:address":"Calle de Bermudez De Castro, 9",
    "sg:city":"Oviedo",
    "sg:orig_category":"Peluqueros: De Se\u00d1oras",
    "sg:phone":"+34 985 28 22 40",
    "sg:postcode":"33011",
    "sg:province":"Asturias",
    "wof:name":"Alonso Mendoza Maria Josefa",
    "wof:placetype":"venue"
},
  "geometry": {"coordinates":[-5.8386983871,43.3680038452],"type":"Point"}
}