{
  "type": "Feature",
  "properties": {
    "addr:full":"Avda Jose Mesa Y Lopez, 39 Palmas De Gran Canaria Las Palmas 35010",
    "addr:postcode":"35010",
    "addr:street":"Avda Jose Mesa Y Lopez 39",
    "iso:country":"ES",
    "sg:address":"Avda Jose Mesa Y Lopez, 39",
    "sg:city":"Palmas De Gran Canaria",
    "sg:orig_category":"Agentes, Concesionarios Y Sucursales De Camiones Y Veh\u00cdculos Industriales",
    "sg:phone":"+34 928 22 97 11",
    "sg:postcode":"35010",
    "sg:province":"Las Palmas",
    "wof:name":"Brisa Motor S.l.",
    "wof:placetype":"venue"
},
  "geometry": {"coordinates":[-15.4363718033,28.1337337494],"type":"Point"}
}