{
  "type": "Feature",
  "properties": {
    "iso:country":"ES",
    "sg:address":"Avda Badajoz, 23",
    "sg:city":"Madrid",
    "sg:orig_category":"Arquitectos",
    "sg:phone":"+34 914 04 12 08",
    "sg:postcode":"28027",
    "sg:province":"Madrid",
    "wof:name":"Hernandez Carmona Manuel",
    "wof:placetype":"venue"
},
  "geometry": {"coordinates":[-3.6549339294,40.4417686462],"type":"Point"}
}