{
  "type": "Feature",
  "properties": {
    "iso:country":"ES",
    "sg:address":"Carrer de Carrer de Pto Rico, S/n",
    "sg:city":"Puerto Rico",
    "sg:orig_category":"Maquinaria, Instalaci\u00d3n Y Equipo Para Garajes Y Estaciones De Servicio",
    "sg:phone":"+34 928 56 11 97",
    "sg:postcode":"35130",
    "sg:province":"Las Palmas",
    "wof:name":"Chapenheit S.l.",
    "wof:placetype":"venue"
},
  "geometry": {"coordinates":[-15.7087993622,27.7916240692],"type":"Point"}
}