{
  "type": "Feature",
  "properties": {
    "iso:country":"ES",
    "sg:address":"Calle de Martires De La Ventilla, 41",
    "sg:city":"Madrid",
    "sg:orig_category":"Molduras, Junquillos, Listones Y Molduras Perforadas",
    "sg:phone":"+34 913 15 71 81",
    "sg:postcode":"28029",
    "sg:province":"Madrid",
    "wof:name":"Martin Gil Maria Jesus",
    "wof:placetype":"venue"
},
  "geometry": {"coordinates":[-3.691879034,40.4707984924],"type":"Point"}
}