{
  "type": "Feature",
  "properties": {
    "addr:full":"Plaz Rodriguez Acosta, S/n Torre Mar M\u00e1laga 29740",
    "addr:housenumber":"s / n",
    "addr:postcode":"29740",
    "addr:street":"Plaz;Acosta;Ma\u0301Laga",
    "iso:country":"ES",
    "sg:address":"Plaz Rodriguez Acosta, S/n",
    "sg:city":"Torre Mar",
    "sg:orig_category":"Molduras, Junquillos, Listones Y Molduras Perforadas",
    "sg:phone":"+34 952 54 22 99",
    "sg:postcode":"29740",
    "sg:province":"M\u00e1laga",
    "wof:name":"Diaz Garcia Rafael Antonio",
    "wof:placetype":"venue"
},
  "geometry": {"coordinates":[-4.4201588631,36.7183189392],"type":"Point"}
}