{
  "type": "Feature",
  "properties": {
    "addr:full":"Calle de Matadero, 21 Bujalance C\u00f3rdoba 14650",
    "addr:housenumber":"21",
    "addr:postcode":"14650",
    "addr:street":"Calle De Matadero",
    "iso:country":"ES",
    "sg:address":"Calle de Matadero, 21",
    "sg:city":"Bujalance",
    "sg:orig_category":"Venta, Montaje De Neum\u00c1ticos",
    "sg:phone":"+34 957 17 17 12",
    "sg:postcode":"14650",
    "sg:province":"C\u00f3rdoba",
    "wof:name":"Le\u00f1a Salazar Fernando",
    "wof:placetype":"venue"
},
  "geometry": {"coordinates":[-4.3805561066,37.8987846375],"type":"Point"}
}