{
  "type": "Feature",
  "properties": {
    "addr:full":"Calle de Carreras, 28 Medina Campo Valladolid 47400",
    "addr:housenumber":"28",
    "addr:postcode":"47400",
    "addr:street":"Calle De Carreras",
    "iso:country":"ES",
    "sg:address":"Calle de Carreras, 28",
    "sg:city":"Medina Campo",
    "sg:orig_category":"Centros Empresariales",
    "sg:phone":"+34 983 81 25 52",
    "sg:postcode":"47400",
    "sg:province":"Valladolid",
    "wof:name":"Bimagui Hermanos Sl",
    "wof:placetype":"venue"
},
  "geometry": {"coordinates":[-4.917183876,41.303478241],"type":"Point"}
}