{
  "type": "Feature",
  "properties": {
    "addr:full":"Calle de Pio Xii, 25 Sanlucar De Barrameda C\u00e1diz 11540",
    "addr:housenumber":"25",
    "addr:postcode":"11540",
    "addr:street":"Calle De Pio Xii;Ca\u0301Diz",
    "iso:country":"ES",
    "sg:address":"Calle de Pio Xii, 25",
    "sg:city":"Sanlucar De Barrameda",
    "sg:orig_category":"Abogados",
    "sg:phone":"+34 956 36 88 66",
    "sg:postcode":"11540",
    "sg:province":"C\u00e1diz",
    "wof:name":"Prieto Alarcon Eduardo",
    "wof:placetype":"venue"
},
  "geometry": {"coordinates":[-6.3537631035,36.7845230103],"type":"Point"}
}