{
  "type": "Feature",
  "properties": {
    "addr:full":"Calle de Aguilar, 88 Puente-genil C\u00f3rdoba 14500",
    "addr:housenumber":"88",
    "addr:postcode":"14500",
    "addr:street":"Calle De Aguilar;Co\u0301Rdoba",
    "iso:country":"ES",
    "sg:address":"Calle de Aguilar, 88",
    "sg:city":"Puente-genil",
    "sg:orig_category":"Zapatos (al Por Menor)",
    "sg:phone":"+34 957 60 58 03",
    "sg:postcode":"14500",
    "sg:province":"C\u00f3rdoba",
    "wof:name":"Zapamoda Genil S.l.",
    "wof:placetype":"venue"
},
  "geometry": {"coordinates":[-4.7734389305,37.3887443542],"type":"Point"}
}