{
  "type": "Feature",
  "properties": {
    "iso:country":"ES",
    "sg:address":"Calle de Pedro Antonio De Alarcon, 15",
    "sg:city":"Granada",
    "sg:classifiers":[
        {
            "category":"Arts & Performance",
            "subcategory":"Art Gallery",
            "type":"Entertainment"
        }
    ],
    "sg:phone":"+34 958 25 37 98",
    "sg:postcode":"18005",
    "sg:province":"Granada",
    "sg:tags":[
        "arte",
        "de",
        "galer\u00cdas"
    ],
    "wof:name":"Cartel Fine Art S.l.",
    "wof:placetype":"venue"
},
  "geometry": {"coordinates":[-3.6046910286,37.1701126099],"type":"Point"}
}