{
  "type": "Feature",
  "properties": {
    "addr:full":"Ciudad Real-valde., Km. 0039,0 Moral Calatrava Ciudad Real 13350",
    "addr:postcode":"13350",
    "addr:street":"Real-Valde. Km. 0039,0;Calatrava",
    "iso:country":"ES",
    "sg:address":"Ciudad Real-valde., Km. 0039,0",
    "sg:city":"Moral Calatrava",
    "sg:orig_category":"Molduras, Junquillos, Listones Y Molduras Perforadas",
    "sg:phone":"+34 926 33 01 54",
    "sg:postcode":"13350",
    "sg:province":"Ciudad Real",
    "wof:name":"Resgonza S.l.",
    "wof:placetype":"venue"
},
  "geometry": {"coordinates":[-3.5793139935,38.8292617798],"type":"Point"}
}