{
  "type": "Feature",
  "properties": {
    "iso:country":"ES",
    "sg:address":"Calle de Doctor Fleming, 5",
    "sg:city":"Dolores",
    "sg:orig_category":"Quincaller\u00cda (al Por Menor)",
    "sg:phone":"+34 965 72 63 53",
    "sg:postcode":"03150",
    "sg:province":"Alicante",
    "wof:name":"Cano Rodes Francisco Victor",
    "wof:placetype":"venue"
},
  "geometry": {"coordinates":[-0.7720178962,38.1383895874],"type":"Point"}
}