{
  "type": "Feature",
  "properties": {
    "addr:full":"Rua Garcia Caama\u00d1o, 16 Vilagarcia Pontevedra 36600",
    "addr:housenumber":"16",
    "addr:postcode":"36600",
    "addr:street":"Rua Garcia Caaman\u0303O",
    "iso:country":"ES",
    "sg:address":"Rua Garcia Caama\u00d1o, 16",
    "sg:city":"Vilagarcia",
    "sg:orig_category":"Abogados",
    "sg:phone":"+34 986 51 14 24",
    "sg:postcode":"36600",
    "sg:province":"Pontevedra",
    "wof:name":"Sande Llovo Abogados S.c.",
    "wof:placetype":"venue"
},
  "geometry": {"coordinates":[-8.7665739059,42.5927886963],"type":"Point"}
}