{
  "type": "Feature",
  "properties": {
    "iso:country":"ES",
    "sg:address":"Calle de Caldas De Reyes, 19",
    "sg:city":"Alcorcon",
    "sg:orig_category":"Alquiler De V\u00cddeo",
    "sg:phone":"+34 916 19 12 82",
    "sg:postcode":"28925",
    "sg:province":"Madrid",
    "wof:name":"Esteban Alba Jose",
    "wof:placetype":"venue"
},
  "geometry": {"coordinates":[-3.8110206127,40.3532295227],"type":"Point"}
}