{
  "type": "Feature",
  "properties": {
    "addr:full":"Carrer de Joan Blanques, 22 Barcelona Barcelona 08012",
    "addr:housenumber":"22",
    "addr:postcode":"08012",
    "addr:street":"Carrer De Joan Blanques",
    "iso:country":"ES",
    "sg:address":"Carrer de Joan Blanques, 22",
    "sg:city":"Barcelona",
    "sg:orig_category":"Papeler\u00cdas, Librer\u00cdas",
    "sg:phone":"+34 932 19 13 65",
    "sg:postcode":"08012",
    "sg:province":"Barcelona",
    "wof:name":"Sarbosa Mora Andres",
    "wof:placetype":"venue"
},
  "geometry": {"coordinates":[2.1608040333,41.4050827026],"type":"Point"}
}