{
  "type": "Feature",
  "properties": {
    "addr:full":"C/ Fra Pere Balaguer, 67 Elche Alicante 03202",
    "addr:housenumber":"67",
    "addr:postcode":"03202",
    "addr:street":"C / Fra Pere Balaguer",
    "iso:country":"ES",
    "sg:address":"C/ Fra Pere Balaguer, 67",
    "sg:city":"Elche",
    "sg:orig_category":"Venta, Instalaci\u00d3n De Cocinas",
    "sg:phone":"+34 965 42 40 77",
    "sg:postcode":"03202",
    "sg:province":"Alicante",
    "wof:name":"Rocamor Tenza Pascual",
    "wof:placetype":"venue"
},
  "geometry": {"coordinates":[-0.6801499724,38.2708740234],"type":"Point"}
}