{
  "type": "Feature",
  "properties": {
    "addr:full":"Ctra Logro\u00d1o, 11 Navarrete La Rioja 26370",
    "addr:housenumber":"11",
    "addr:postcode":"26370",
    "addr:street":"Ctra Logron\u0303O",
    "iso:country":"ES",
    "sg:address":"Ctra Logro\u00d1o, 11",
    "sg:city":"Navarrete",
    "sg:orig_category":"Ferreter\u00cda Artesanal",
    "sg:phone":"+34 941 44 02 57",
    "sg:postcode":"26370",
    "sg:province":"La Rioja",
    "wof:name":"Huergo Soto Pablo",
    "wof:placetype":"venue"
},
  "geometry": {"coordinates":[-2.581387043,42.4241256714],"type":"Point"}
}