{
  "type": "Feature",
  "properties": {
    "iso:country":"ES",
    "sg:address":"Calle de Leitza Kalea, S/n",
    "sg:city":"Tolosa",
    "sg:orig_category":"Estancos",
    "sg:phone":"+34 943 67 49 01",
    "sg:postcode":"20400",
    "sg:province":"Guip\u00f9zcoa",
    "wof:name":"Lakunza Mendizabal Maria Victoria",
    "wof:placetype":"venue"
},
  "geometry": {"coordinates":[-2.0734059811,43.1389427185],"type":"Point"}
}