{
  "type": "Feature",
  "properties": {
    "addr:full":"Calle de Santa Engracia, 137 Madrid Madrid 28003",
    "addr:housenumber":"137",
    "addr:postcode":"28003",
    "addr:street":"Calle De Santa Engracia",
    "iso:country":"ES",
    "sg:address":"Calle de Santa Engracia, 137",
    "sg:city":"Madrid",
    "sg:orig_category":"Contenedores (mercanc\u00cdas)",
    "sg:phone":"+34 913 99 09 46",
    "sg:postcode":"28003",
    "sg:province":"Madrid",
    "wof:name":"Biltmore Equipment S.l.",
    "wof:placetype":"venue"
},
  "geometry": {"coordinates":[-3.7022929192,40.4427452087],"type":"Point"}
}