{
  "type": "Feature",
  "properties": {
    "iso:country":"ES",
    "sg:address":"Avda La Libertad, 23",
    "sg:city":"San Vicente De Barakaldo",
    "sg:orig_category":"Lencer\u00cda Femenina, Corseter\u00cda, Trajes De Ba\u00d1o (al Por Menor)",
    "sg:phone":"+34 944 37 12 30",
    "sg:postcode":"48901",
    "sg:province":"Vizcaya",
    "wof:name":"Aquesolo Sierra Idoia",
    "wof:placetype":"venue"
},
  "geometry": {"coordinates":[-2.9909911156,43.2970924377],"type":"Point"}
}