{
  "type": "Feature",
  "properties": {
    "addr:full":"Calle de Muelle, 35 Santa Pola Alicante 03130",
    "addr:housenumber":"35",
    "addr:postcode":"03130",
    "addr:street":"Calle De Muelle",
    "iso:country":"ES",
    "sg:address":"Calle de Muelle, 35",
    "sg:city":"Santa Pola",
    "sg:classifiers":[
        {
            "category":"Recreation",
            "type":"Entertainment"
        }
    ],
    "sg:phone":"+34 965 41 67 72",
    "sg:postcode":"03130",
    "sg:province":"Alicante",
    "sg:tags":[
        "caza",
        "pr\u00c1ctica",
        "la",
        "de",
        "pesca",
        "y"
    ],
    "wof:name":"Cofradia De Pescadores De Santa Pola",
    "wof:placetype":"venue"
},
  "geometry": {"coordinates":[-0.5563690066,38.1904296875],"type":"Point"}
}