{
  "type": "Feature",
  "properties": {
    "iso:country":"ES",
    "sg:address":"Av Alfonso Puchades, 2",
    "sg:city":"Benidorm",
    "sg:orig_category":"Peluquer\u00cdas, Peluquer\u00cda Mixta",
    "sg:phone":"+34 966 80 42 03",
    "sg:postcode":"03500",
    "sg:province":"Alicante",
    "wof:name":"Garcia Burgos Maria Dolores",
    "wof:placetype":"venue"
},
  "geometry": {"coordinates":[-0.1739459932,38.5365180969],"type":"Point"}
}