{
  "type": "Feature",
  "properties": {
    "addr:full":"La Fabrica, Km. 0073,0 Villabermudo Palencia 34406",
    "addr:postcode":"34406",
    "addr:street":"0073,0",
    "iso:country":"ES",
    "sg:address":"La Fabrica, Km. 0073,0",
    "sg:city":"Villabermudo",
    "sg:orig_category":"Negocio De Madera",
    "sg:phone":"+34 979 18 74 69",
    "sg:postcode":"34406",
    "sg:province":"Palencia",
    "wof:name":"Madenorte S.l.",
    "wof:placetype":"venue"
},
  "geometry": {"coordinates":[-4.528275013,42.6681518555],"type":"Point"}
}