{
  "type": "Feature",
  "properties": {
    "iso:country":"ES",
    "sg:address":"Calle de Padre Larroca, 8",
    "sg:city":"Donostia-san Sebastian",
    "sg:orig_category":"Peluqueros: De Se\u00d1oras",
    "sg:phone":"+34 943 27 68 48",
    "sg:postcode":"20001",
    "sg:province":"Guip\u00f9zcoa",
    "wof:name":"Ubeda Garcia Guadalupe",
    "wof:placetype":"venue"
},
  "geometry": {"coordinates":[-1.9737910032,43.3228034973],"type":"Point"}
}