{
  "type": "Feature",
  "properties": {
    "addr:full":"Jaen, 4 San Pedro Alcantara M\u00e1laga 29670",
    "addr:housenumber":"4",
    "addr:postcode":"29670",
    "addr:street":"Jaen",
    "iso:country":"ES",
    "sg:address":"Jaen, 4",
    "sg:city":"San Pedro Alcantara",
    "sg:orig_category":"Electricidad: Instaladores",
    "sg:phone":"+34 952 78 45 08",
    "sg:postcode":"29670",
    "sg:province":"M\u00e1laga",
    "wof:name":"Instalaciones Electricas Lebri E Hijos S.l.",
    "wof:placetype":"venue"
},
  "geometry": {"coordinates":[-4.9881749153,36.4832420349],"type":"Point"}
}