{
  "type": "Feature",
  "properties": {
    "addr:full":"Carrer de Buigas, 19 Barcelona Barcelona 08017",
    "addr:housenumber":"19",
    "addr:postcode":"08017",
    "addr:street":"Carrer De Buigas",
    "iso:country":"ES",
    "sg:address":"Carrer de Buigas, 19",
    "sg:city":"Barcelona",
    "sg:orig_category":"M\u00c9dicos: Pediatr\u00cda. Enfermedades De Los Ni\u00d1os",
    "sg:phone":"+34 932 03 20 97",
    "sg:postcode":"08017",
    "sg:province":"Barcelona",
    "wof:name":"Inormfarma Espa\u00f1a S.l.",
    "wof:placetype":"venue"
},
  "geometry": {"coordinates":[2.1308660507,41.3937187195],"type":"Point"}
}