{
  "type": "Feature",
  "properties": {
    "addr:full":"Calle de Tarragona, 5 Castellon Castell\u00f3n 12003",
    "addr:housenumber":"5",
    "addr:postcode":"12003",
    "addr:street":"Calle De Tarragona;Castello\u0301N",
    "iso:country":"ES",
    "sg:address":"Calle de Tarragona, 5",
    "sg:city":"Castellon",
    "sg:orig_category":"Centros De Coordinaci\u00d3n",
    "sg:phone":"+34 964 23 73 12",
    "sg:postcode":"12003",
    "sg:province":"Castell\u00f3n",
    "sg:website":"www.sanzlamas.com",
    "wof:name":"Sanz-lamas Badenes Jose",
    "wof:placetype":"venue"
},
  "geometry": {"coordinates":[-0.0315140001,39.9867324829],"type":"Point"}
}