{
  "type": "Feature",
  "properties": {
    "addr:full":"Ctra Tortosa-la Senia, 5 Mas Barberans Tarragona 43514",
    "addr:housenumber":"5",
    "addr:postcode":"43514",
    "addr:street":"Ctra Tortosa-La Senia",
    "iso:country":"ES",
    "sg:address":"Ctra Tortosa-la Senia, 5",
    "sg:city":"Mas Barberans",
    "sg:orig_category":"Aceites Y Grasas Alimentarias (fabricaci\u00d3n, Al Por Mayor)",
    "sg:phone":"+34 977 73 90 30",
    "sg:postcode":"43514",
    "sg:province":"Tarragona",
    "wof:name":"Cooperativa Agricola San Isidro",
    "wof:placetype":"venue"
},
  "geometry": {"coordinates":[0.3747960031,40.7357978821],"type":"Point"}
}