{
  "type": "Feature",
  "properties": {
    "addr:full":"Calle de Cordoba, 5 San Fernando De Henares Madrid 28830",
    "addr:housenumber":"5",
    "addr:postcode":"28830",
    "addr:street":"Calle De Cordoba",
    "iso:country":"ES",
    "sg:address":"Calle de Cordoba, 5",
    "sg:city":"San Fernando De Henares",
    "sg:orig_category":"Carnicer\u00cdas, Carnicer\u00cdas",
    "sg:phone":"+34 916 69 69 07",
    "sg:postcode":"28830",
    "sg:province":"Madrid",
    "wof:name":"Mesonero Hernandez Jose Antonio",
    "wof:placetype":"venue"
},
  "geometry": {"coordinates":[-3.5333411694,40.4271011353],"type":"Point"}
}