{
  "type": "Feature",
  "properties": {
    "iso:country":"ES",
    "sg:address":"Calle de Real De Pinos Puente, 22",
    "sg:city":"Pinos-puente",
    "sg:orig_category":"Farmacias",
    "sg:phone":"+34 958 45 01 51",
    "sg:postcode":"18240",
    "sg:province":"Granada",
    "wof:name":"Farmacia V Y L Bernier Villamor C.b.",
    "wof:placetype":"venue"
},
  "geometry": {"coordinates":[-3.7521839142,37.2517814636],"type":"Point"}
}