{
  "type": "Feature",
  "properties": {
    "iso:country":"ES",
    "sg:address":"Carrer de Bartomeu Pi, 8",
    "sg:city":"Barcelona",
    "sg:orig_category":"Empresas De Portes Y Mensajer\u00cda",
    "sg:phone":"+34 934 32 93 00",
    "sg:postcode":"08014",
    "sg:province":"Barcelona",
    "wof:name":"Frei Union S.l.",
    "wof:placetype":"venue"
},
  "geometry": {"coordinates":[2.1396100521,41.3703804016],"type":"Point"}
}