{
  "type": "Feature",
  "properties": {
    "addr:full":"Carrer de Antoni Rubio I Lluch, 5 Reus Tarragona 43206",
    "addr:housenumber":"5",
    "addr:postcode":"43206",
    "addr:street":"Carrer De Antoni Rubio I Lluch",
    "iso:country":"ES",
    "sg:address":"Carrer de Antoni Rubio I Lluch, 5",
    "sg:city":"Reus",
    "sg:orig_category":"Fabricaci\u00d3n De Juegos Y Juguetes",
    "sg:phone":"+34 977 31 40 20",
    "sg:postcode":"43206",
    "sg:province":"Tarragona",
    "wof:name":"Dijoc S.a.",
    "wof:placetype":"venue"
},
  "geometry": {"coordinates":[1.0818909407,41.1587142944],"type":"Point"}
}