{
  "type": "Feature",
  "properties": {
    "addr:full":"Carrer de Napols, 216 Barcelona Barcelona 08013",
    "addr:housenumber":"216",
    "addr:postcode":"08013",
    "addr:street":"Carrer De Napols",
    "iso:country":"ES",
    "sg:address":"Carrer de Napols, 216",
    "sg:city":"Barcelona",
    "sg:orig_category":"Doctores En Medicina",
    "sg:phone":"+34 934 59 28 89",
    "sg:postcode":"08013",
    "sg:province":"Barcelona",
    "wof:name":"Garcia Suarez Juan Jose",
    "wof:placetype":"venue"
},
  "geometry": {"coordinates":[2.173126936,41.4002723694],"type":"Point"}
}