{
  "type": "Feature",
  "properties": {
    "addr:full":"Calle de Albarracin, 7 Madrid Madrid 28037",
    "addr:housenumber":"7",
    "addr:postcode":"madrid;28037",
    "addr:street":"Calle De Albarracin",
    "iso:country":"ES",
    "sg:address":"Calle de Albarracin, 7",
    "sg:city":"Madrid",
    "sg:orig_category":"Cervecer\u00cdas",
    "sg:phone":"+34 913 27 45 08",
    "sg:postcode":"28037",
    "sg:province":"Madrid",
    "wof:name":"Menendez Fernandez Hermenegildo",
    "wof:placetype":"venue"
},
  "geometry": {"coordinates":[-3.6349916458,40.4379425049],"type":"Point"}
}