{
  "type": "Feature",
  "properties": {
    "iso:country":"ES",
    "sg:address":"Calle de Santa Clara, 2",
    "sg:city":"Zamora",
    "sg:orig_category":"Asociaciones, Organismos Culturales Y Socioeducativos",
    "sg:phone":"+34 980 53 05 34",
    "sg:postcode":"49003",
    "sg:province":"Zamora",
    "wof:name":"Circulo De Zamora",
    "wof:placetype":"venue"
},
  "geometry": {"coordinates":[-5.7448539734,41.5042495728],"type":"Point"}
}