{
  "type": "Feature",
  "properties": {
    "iso:country":"ES",
    "sg:address":"Calle de Francisco Ruiz, 9",
    "sg:city":"Madrid",
    "sg:orig_category":"Carnicer\u00cdas, Carnicer\u00cdas",
    "sg:phone":"+34 914 76 24 34",
    "sg:postcode":"28026",
    "sg:province":"Madrid",
    "wof:name":"Sabugo Garcia Manuel",
    "wof:placetype":"venue"
},
  "geometry": {"coordinates":[-3.7034480572,40.3821296692],"type":"Point"}
}