{
  "type": "Feature",
  "properties": {
    "addr:full":"Calle de Silvela, 2 Fuente Cantos Badajoz 06240",
    "addr:housenumber":"2",
    "addr:postcode":"06240",
    "addr:street":"Calle De Silvela",
    "iso:country":"ES",
    "sg:address":"Calle de Silvela, 2",
    "sg:city":"Fuente Cantos",
    "sg:orig_category":"Reciclaje, Desguace De Veh\u00cdculos",
    "sg:phone":"+34 924 58 04 14",
    "sg:postcode":"06240",
    "sg:province":"Badajoz",
    "wof:name":"Trigo Rodriguez Antonio",
    "wof:placetype":"venue"
},
  "geometry": {"coordinates":[-6.3072094917,38.2500953674],"type":"Point"}
}