{
  "type": "Feature",
  "properties": {
    "iso:country":"ES",
    "sg:address":"Calle de Doctor Don Luis Bilbao Libano, 5",
    "sg:city":"Leioa",
    "sg:orig_category":"Impuestos, Tesoro P\u00dablico",
    "sg:phone":"+34 944 80 19 66",
    "sg:postcode":"48940",
    "sg:province":"Vizcaya",
    "wof:name":"Jaime Basterra - Tasper",
    "wof:placetype":"venue"
},
  "geometry": {"coordinates":[-2.9860498905,43.3238372803],"type":"Point"}
}