{
  "type": "Feature",
  "properties": {
    "addr:full":"Alam Boulevard Del, 4 Donostia-san Sebastian Guip\u00f9zcoa 20003",
    "addr:housenumber":"4",
    "addr:postcode":"20003",
    "addr:street":"Alam Boulevard Del",
    "iso:country":"ES",
    "sg:address":"Alam Boulevard Del, 4",
    "sg:city":"Donostia-san Sebastian",
    "sg:orig_category":"Telas Y Sedas (al Por Menor)",
    "sg:phone":"+34 943 42 42 97",
    "sg:postcode":"20003",
    "sg:province":"Guip\u00f9zcoa",
    "wof:name":"Gonzalez Peon Margarita",
    "wof:placetype":"venue"
},
  "geometry": {"coordinates":[-1.9832110405,43.3227500916],"type":"Point"}
}