{
  "type": "Feature",
  "properties": {
    "iso:country":"ES",
    "sg:address":"Av Pais Valencia, 17",
    "sg:city":"Elche",
    "sg:orig_category":"Pr\u00c9stamos Personales E Hipotecarios",
    "sg:phone":"+34 965 44 72 12",
    "sg:postcode":"03201",
    "sg:province":"Alicante",
    "wof:name":"Riquelme Rubira Francisco",
    "wof:placetype":"venue"
},
  "geometry": {"coordinates":[-0.7005850077,38.2667922974],"type":"Point"}
}