{
  "type": "Feature",
  "properties": {
    "iso:country":"ES",
    "sg:address":"Avda Constitucion, 30",
    "sg:city":"Monforte Cid",
    "sg:orig_category":"Material Y Herramientas Agr\u00cdcolas",
    "sg:phone":"+34 965 62 00 45",
    "sg:postcode":"03670",
    "sg:province":"Alicante",
    "wof:name":"Sirfran S.l.",
    "wof:placetype":"venue"
},
  "geometry": {"coordinates":[-0.7252690196,38.3822402954],"type":"Point"}
}