{
  "type": "Feature",
  "properties": {
    "addr:full":"Av Los Guindos (p I Los Guindos), 2 Malaga M\u00e1laga 29004",
    "addr:housenumber":"2",
    "addr:postcode":"29004",
    "addr:street":"Av Los Guindos P;Los Guindos;Ma\u0301Laga",
    "iso:country":"ES",
    "sg:address":"Av Los Guindos (p I Los Guindos), 2",
    "sg:city":"Malaga",
    "sg:orig_category":"Agentes, Concesionarios Y Sucursales De Veh\u00cdculos",
    "sg:phone":"+34 952 10 53 83",
    "sg:postcode":"29004",
    "sg:province":"M\u00e1laga",
    "wof:name":"Car Privilege Service S.a.",
    "wof:placetype":"venue"
},
  "geometry": {"coordinates":[-4.4536352158,36.6929855347],"type":"Point"}
}