{
  "type": "Feature",
  "properties": {
    "iso:country":"ES",
    "sg:address":"Amillaga Kalea, 10",
    "sg:city":"Bergara",
    "sg:orig_category":"Lavado, Limpieza De Veh\u00cdculos",
    "sg:phone":"+34 943 76 52 87",
    "sg:postcode":"20570",
    "sg:province":"Guip\u00f9zcoa",
    "wof:name":"Auto-servicio Bergara S.l.",
    "wof:placetype":"venue"
},
  "geometry": {"coordinates":[-2.4238159657,43.1245689392],"type":"Point"}
}