{
  "type": "Feature",
  "properties": {
    "addr:full":"Avda De Las Escritoras, 15 Mazagon Huelva 21130",
    "addr:housenumber":"15",
    "addr:postcode":"21130",
    "addr:street":"Avda De Las Escritoras",
    "iso:country":"ES",
    "sg:address":"Avda De Las Escritoras, 15",
    "sg:city":"Mazagon",
    "sg:orig_category":"Alquiler De V\u00cddeo",
    "sg:phone":"+34 959 53 63 49",
    "sg:postcode":"21130",
    "sg:province":"Huelva",
    "wof:name":"Aviles Martin Manuel",
    "wof:placetype":"venue"
},
  "geometry": {"coordinates":[-6.8201551437,37.1328620911],"type":"Point"}
}