{
  "type": "Feature",
  "properties": {
    "addr:full":"Plaz General Palacio, 9 Getafe Madrid 28901",
    "addr:housenumber":"9",
    "addr:postcode":"28901",
    "addr:street":"Palacio",
    "iso:country":"ES",
    "sg:address":"Plaz General Palacio, 9",
    "sg:city":"Getafe",
    "sg:orig_category":"Ropa Para Se\u00d1oras (al Por Menor)",
    "sg:phone":"+34 916 95 90 18",
    "sg:postcode":"28901",
    "sg:province":"Madrid",
    "wof:name":"Romero Martin Aurora",
    "wof:placetype":"venue"
},
  "geometry": {"coordinates":[-3.7278449535,40.3086051941],"type":"Point"}
}