{
  "type": "Feature",
  "properties": {
    "addr:full":"Pl. Ezpeleta, S/n Huarte Navarra 31620",
    "addr:housenumber":"s / n",
    "addr:postcode":"31620",
    "addr:street":"Ezpeleta;Navarra",
    "iso:country":"ES",
    "sg:address":"Pl. Ezpeleta, S/n",
    "sg:city":"Huarte",
    "sg:orig_category":"Peluquer\u00cdas, Peluquer\u00cda Mixta",
    "sg:phone":"+34 948 33 30 94",
    "sg:postcode":"31620",
    "sg:province":"Navarra",
    "wof:name":"Domezain Ganuza Jerusalen",
    "wof:placetype":"venue"
},
  "geometry": {"coordinates":[-1.5941590071,42.8305091858],"type":"Point"}
}