{
  "type": "Feature",
  "properties": {
    "addr:full":"Av Madrid, 192 Barcelona Barcelona 08028",
    "addr:housenumber":"192",
    "addr:postcode":"08028",
    "addr:street":"Av Madrid",
    "iso:country":"ES",
    "sg:address":"Av Madrid, 192",
    "sg:city":"Barcelona",
    "sg:orig_category":"Pod\u00d3logos: Pedicuros",
    "sg:phone":"+34 933 39 72 13",
    "sg:postcode":"08028",
    "sg:province":"Barcelona",
    "wof:name":"Alonso Guillamon Julio",
    "wof:placetype":"venue"
},
  "geometry": {"coordinates":[2.1330444813,41.3809890747],"type":"Point"}
}