{
  "type": "Feature",
  "properties": {
    "addr:full":"Calle de Industrias, 3 Consuegra Toledo 45700",
    "addr:housenumber":"3",
    "addr:postcode":"45700",
    "addr:street":"Calle De Industrias",
    "iso:country":"ES",
    "sg:address":"Calle de Industrias, 3",
    "sg:city":"Consuegra",
    "sg:orig_category":"Productores Recolectores, Venta Directa De Vinos",
    "sg:phone":"+34 925 48 09 95",
    "sg:postcode":"45700",
    "sg:province":"Toledo",
    "sg:website":"www.bodegasprieto.com",
    "wof:name":"Prieto Fernandez-layos Jesus",
    "wof:placetype":"venue"
},
  "geometry": {"coordinates":[-3.6143779755,39.4650382996],"type":"Point"}
}