{
  "type": "Feature",
  "properties": {
    "addr:full":"Rua Do Campo Santo, 17 Ordes La Coru\u00f1a 15680",
    "addr:postcode":"15680",
    "addr:street":"Rua;Corun\u0303A",
    "iso:country":"ES",
    "sg:address":"Rua Do Campo Santo, 17",
    "sg:city":"Ordes",
    "sg:orig_category":"Lavado, Limpieza De Veh\u00cdculos",
    "sg:phone":"+34 981 68 11 11",
    "sg:postcode":"15680",
    "sg:province":"La Coru\u00f1a",
    "wof:name":"Garaje Rey S.l.",
    "wof:placetype":"venue"
},
  "geometry": {"coordinates":[-8.418422699,43.0776176453],"type":"Point"}
}