{
  "type": "Feature",
  "properties": {
    "iso:country":"ES",
    "sg:address":"Calle de Miguel Garcia Castillo, 2",
    "sg:city":"Pozoblanco",
    "sg:orig_category":"Trabajos De Perforaciones, Sondeos, Construcci\u00d3n De Pozos",
    "sg:phone":"+34 957 13 15 25",
    "sg:postcode":"14400",
    "sg:province":"C\u00f3rdoba",
    "wof:name":"Sondeos Jurado S.l.",
    "wof:placetype":"venue"
},
  "geometry": {"coordinates":[-4.8587040901,38.3804016113],"type":"Point"}
}