{
  "type": "Feature",
  "properties": {
    "iso:country":"ES",
    "sg:address":"Avda Antonio Tore Tore, S/n",
    "sg:city":"Torre Mar",
    "sg:orig_category":"Reposter\u00cdas",
    "sg:phone":"+34 952 54 67 35",
    "sg:postcode":"29740",
    "sg:province":"M\u00e1laga",
    "wof:name":"Angela Keller Gabriele",
    "wof:placetype":"venue"
},
  "geometry": {"coordinates":[-4.4200186729,36.7196464539],"type":"Point"}
}