{
  "type": "Feature",
  "properties": {
    "iso:country":"ES",
    "sg:address":"Calle de Valladolid, 20",
    "sg:city":"Alcorcon",
    "sg:orig_category":"Molduras, Junquillos, Listones Y Molduras Perforadas",
    "sg:phone":"+34 916 41 45 93",
    "sg:postcode":"28922",
    "sg:province":"Madrid",
    "wof:name":"Herrero Marcos Elvira",
    "wof:placetype":"venue"
},
  "geometry": {"coordinates":[-3.8299789429,40.3414955139],"type":"Point"}
}