{
  "type": "Feature",
  "properties": {
    "iso:country":"ES",
    "sg:address":"Calle de Fuente Las Pilas, 4",
    "sg:city":"Requena",
    "sg:orig_category":"Arquitectos",
    "sg:phone":"+34 962 30 11 85",
    "sg:postcode":"46340",
    "sg:province":"Valencia",
    "wof:name":"Garcia Mu\u00f1oz Nicolas",
    "wof:placetype":"venue"
},
  "geometry": {"coordinates":[-1.1030291319,39.4860115051],"type":"Point"}
}