{
  "type": "Feature",
  "properties": {
    "addr:full":"Avda Angel Pesta\u00d1a, S/n Ponferrada Le\u00f3n 24400",
    "addr:housenumber":"s / n",
    "addr:postcode":"24400",
    "addr:street":"Avda Angel Pestan\u0303A",
    "iso:country":"ES",
    "sg:address":"Avda Angel Pesta\u00d1a, S/n",
    "sg:city":"Ponferrada",
    "sg:orig_category":"Promotores Constructores",
    "sg:phone":"+34 987 41 07 80",
    "sg:postcode":"24400",
    "sg:province":"Le\u00f3n",
    "wof:name":"Luis Fernandez Matachana S. A.",
    "wof:placetype":"venue"
},
  "geometry": {"coordinates":[-6.5843648911,42.5522575378],"type":"Point"}
}