{
  "type": "Feature",
  "properties": {
    "iso:country":"ES",
    "sg:address":"Calle de Isabel La Catolica, 8",
    "sg:city":"Valencia",
    "sg:orig_category":"Agencias Y Asesores De Publicidad",
    "sg:phone":"+34 963 53 06 20",
    "sg:postcode":"46004",
    "sg:province":"Valencia",
    "wof:name":"Publipress Media S.a.",
    "wof:placetype":"venue"
},
  "geometry": {"coordinates":[-0.3703044951,39.4685516357],"type":"Point"}
}