{
  "type": "Feature",
  "properties": {
    "iso:country":"ES",
    "sg:address":"Calle de Ruidera, 9",
    "sg:city":"Madrid",
    "sg:orig_category":"Iglesia Cat\u00d3lica",
    "sg:phone":"+34 915 07 19 71",
    "sg:postcode":"28053",
    "sg:province":"Madrid",
    "wof:name":"Parroquia San Francisco De Paula",
    "wof:placetype":"venue"
},
  "geometry": {"coordinates":[-3.6739139557,40.3809051514],"type":"Point"}
}