{
  "type": "Feature",
  "properties": {
    "iso:country":"ES",
    "sg:address":"Calle de Castilla (de), 3",
    "sg:city":"Mejorada Campo",
    "sg:orig_category":"Bronces Y Cobre Para Amueblado",
    "sg:phone":"+34 916 68 27 95",
    "sg:postcode":"28840",
    "sg:province":"Madrid",
    "wof:name":"Del Val Vallecillo Alfonso",
    "wof:placetype":"venue"
},
  "geometry": {"coordinates":[-3.4837529659,40.3891448975],"type":"Point"}
}