{
  "type": "Feature",
  "properties": {
    "addr:full":"Rua Tui, 62 Lugo Lugo 27004",
    "addr:housenumber":"62",
    "addr:postcode":"27004",
    "addr:street":"Rua Tui",
    "iso:country":"ES",
    "sg:address":"Rua Tui, 62",
    "sg:city":"Lugo",
    "sg:orig_category":"Barnizadores",
    "sg:phone":"+34 982 21 50 58",
    "sg:postcode":"27004",
    "sg:province":"Lugo",
    "wof:name":"Obradoiro Car S.l.",
    "wof:placetype":"venue"
},
  "geometry": {"coordinates":[-7.5654149055,43.0134925842],"type":"Point"}
}