{
  "type": "Feature",
  "properties": {
    "iso:country":"ES",
    "sg:address":"Calle de Nueva, 6",
    "sg:city":"Donostia-san Sebastian",
    "sg:orig_category":"Transporte En General",
    "sg:phone":"+34 943 27 34 26",
    "sg:postcode":"20001",
    "sg:province":"Guip\u00f9zcoa",
    "wof:name":"Fabo Ordo\u00f1ez Francisco De Borja",
    "wof:placetype":"venue"
},
  "geometry": {"coordinates":[-1.9735759497,43.3232269287],"type":"Point"}
}