{
  "type": "Feature",
  "properties": {
    "iso:country":"ES",
    "sg:address":"Barr Rioseco, S/n",
    "sg:city":"Rioseco",
    "sg:orig_category":"Art\u00cdculos De Limpieza Y De Cocina (fabricaci\u00d3n, Al Por Mayor)",
    "sg:phone":"+34 942 85 00 11",
    "sg:postcode":"39787",
    "sg:province":"Cantabria",
    "wof:name":"Vitrificados Del Norte S.a.l.",
    "wof:placetype":"venue"
},
  "geometry": {"coordinates":[-4.4123101234,43.2521781921],"type":"Point"}
}