{
  "type": "Feature",
  "properties": {
    "addr:full":"Vena Abella, S/n Abella Girona 17869",
    "addr:housenumber":"s / n",
    "addr:postcode":"17869",
    "addr:street":"Abella",
    "iso:country":"ES",
    "sg:address":"Vena Abella, S/n",
    "sg:city":"Abella",
    "sg:orig_category":"Promotores Constructores",
    "sg:phone":"+34 972 74 12 62",
    "sg:postcode":"17869",
    "sg:province":"Girona",
    "wof:name":"Promociones Rairot S.l.",
    "wof:placetype":"venue"
},
  "geometry": {"coordinates":[2.301361084,42.3755378723],"type":"Point"}
}