{
  "type": "Feature",
  "properties": {
    "iso:country":"ES",
    "sg:address":"Calle de Viacampo, 2",
    "sg:city":"Calahorra",
    "sg:orig_category":"Maquinaria Para Industrias Diversas",
    "sg:phone":"+34 941 13 34 45",
    "sg:postcode":"26500",
    "sg:province":"La Rioja",
    "wof:name":"Marin Cristobal Ricardo",
    "wof:placetype":"venue"
},
  "geometry": {"coordinates":[-1.9584399462,42.3094024658],"type":"Point"}
}