{
  "type": "Feature",
  "properties": {
    "addr:full":"Transv. R. Dario (p I S Cayetano), S/n Churriana Vega Granada 18194",
    "addr:housenumber":"s",
    "addr:postcode":"18194",
    "addr:street":"P I S Cayetano;/ N",
    "iso:country":"ES",
    "sg:address":"Transv. R. Dario (p I S Cayetano), S/n",
    "sg:city":"Churriana Vega",
    "sg:orig_category":"Empresas De Carpinter\u00cda De Madera",
    "sg:phone":"+34 958 55 09 44",
    "sg:postcode":"18194",
    "sg:province":"Granada",
    "wof:name":"Rodriguez Martinez Isacio",
    "wof:placetype":"venue"
},
  "geometry": {"coordinates":[-3.6773679256,37.1503562927],"type":"Point"}
}