{
  "type": "Feature",
  "properties": {
    "iso:country":"ES",
    "sg:address":"Calle de Puente De Muerte Y Vida (del), 10",
    "sg:city":"Segovia",
    "sg:orig_category":"Bricolaje, Herramientas (al Por Menor)",
    "sg:phone":"+34 921 42 86 61",
    "sg:postcode":"40005",
    "sg:province":"Segovia",
    "wof:name":"Gonzalez Sanchez Clemente",
    "wof:placetype":"venue"
},
  "geometry": {"coordinates":[-4.11627388,40.9440803528],"type":"Point"}
}