{
  "type": "Feature",
  "properties": {
    "iso:country":"ES",
    "sg:address":"Pg Garbi, 13",
    "sg:city":"Castelldefels",
    "sg:orig_category":"Sales (al Por Mayor)",
    "sg:phone":"+34 936 64 46 17",
    "sg:postcode":"08860",
    "sg:province":"Barcelona",
    "sg:website":"www.spiritscorner.com",
    "wof:name":"F & F S.l.",
    "wof:placetype":"venue"
},
  "geometry": {"coordinates":[1.9968099594,41.2666511536],"type":"Point"}
}