{
  "type": "Feature",
  "properties": {
    "addr:full":"Calle de Molino (del), 2 Pinseque Zaragoza 50298",
    "addr:housenumber":"2",
    "addr:postcode":"50298",
    "addr:street":"Calle De Molino Del",
    "iso:country":"ES",
    "sg:address":"Calle de Molino (del), 2",
    "sg:city":"Pinseque",
    "sg:orig_category":"Empresas De Desmonte",
    "sg:phone":"+34 976 65 16 35",
    "sg:postcode":"50298",
    "sg:province":"Zaragoza",
    "wof:name":"Sangros Ortigas Pedro Jose",
    "wof:placetype":"venue"
},
  "geometry": {"coordinates":[-1.10333395,41.737285614],"type":"Point"}
}