{
  "type": "Feature",
  "properties": {
    "addr:full":"Plaz Santiago, 1 Ermua Vizcaya 48260",
    "addr:housenumber":"1",
    "addr:postcode":"48260",
    "addr:street":"Plaz Santiago",
    "iso:country":"ES",
    "sg:address":"Plaz Santiago, 1",
    "sg:city":"Ermua",
    "sg:orig_category":"Peluquer\u00cdas, Peluquer\u00cda Mixta",
    "sg:phone":"+34 943 17 15 79",
    "sg:postcode":"48260",
    "sg:province":"Vizcaya",
    "wof:name":"Hernandez Rodriguez Tomas",
    "wof:placetype":"venue"
},
  "geometry": {"coordinates":[-2.4973800182,43.1792488098],"type":"Point"}
}