{
  "type": "Feature",
  "properties": {
    "iso:country":"ES",
    "sg:address":"Plaz Cedro, 15",
    "sg:city":"Valencia",
    "sg:orig_category":"Molduras, Junquillos, Listones Y Molduras Perforadas",
    "sg:phone":"+34 963 71 30 36",
    "sg:postcode":"46022",
    "sg:province":"Valencia",
    "wof:name":"Campos Canos Maria Del Carmen",
    "wof:placetype":"venue"
},
  "geometry": {"coordinates":[-0.3476620018,39.4718475342],"type":"Point"}
}