{
  "type": "Feature",
  "properties": {
    "addr:full":"Calle de Arturo Reyes, 5 Malaga M\u00e1laga 29011",
    "addr:housenumber":"5",
    "addr:postcode":"29011",
    "addr:street":"Calle De Arturo Reyes;Ma\u0301Laga",
    "iso:country":"ES",
    "sg:address":"Calle de Arturo Reyes, 5",
    "sg:city":"Malaga",
    "sg:orig_category":"Peluquer\u00cdas, Peluquer\u00cda Mixta",
    "sg:phone":"+34 952 30 20 02",
    "sg:postcode":"29011",
    "sg:province":"M\u00e1laga",
    "wof:name":"Rodriguez Pe\u00f1a Maria Remedios",
    "wof:placetype":"venue"
},
  "geometry": {"coordinates":[-4.4388260841,36.7295761108],"type":"Point"}
}