{
  "type": "Feature",
  "properties": {
    "iso:country":"ES",
    "sg:address":"Rbla Catalunya, 121",
    "sg:city":"Barcelona",
    "sg:orig_category":"Ropa Para Se\u00d1oras (al Por Menor)",
    "sg:phone":"+34 932 17 89 99",
    "sg:postcode":"08008",
    "sg:province":"Barcelona",
    "wof:name":"Monasterio Pena Maria Pilar",
    "wof:placetype":"venue"
},
  "geometry": {"coordinates":[2.1581799984,41.3946113586],"type":"Point"}
}