{
  "type": "Feature",
  "properties": {
    "addr:full":"Calle de Muleta, 50 Chiclana De La Frontera C\u00e1diz 11130",
    "addr:housenumber":"50",
    "addr:postcode":"11130",
    "addr:street":"Calle De Muleta",
    "iso:country":"ES",
    "sg:address":"Calle de Muleta, 50",
    "sg:city":"Chiclana De La Frontera",
    "sg:orig_category":"Transportes Por Carretera: Lotes Completos, Mercanc\u00cdas Diversas",
    "sg:phone":"+34 956 40 22 06",
    "sg:postcode":"11130",
    "sg:province":"C\u00e1diz",
    "wof:name":"Doblamar 2003 S.l.",
    "wof:placetype":"venue"
},
  "geometry": {"coordinates":[-6.1290330887,36.4181861877],"type":"Point"}
}