{
  "type": "Feature",
  "properties": {
    "addr:full":"Pl Gomila, 3 Palma Islas Baleares 07014",
    "addr:housenumber":"3",
    "addr:postcode":"07014",
    "addr:street":"Pl Gomila",
    "iso:country":"ES",
    "sg:address":"Pl Gomila, 3",
    "sg:city":"Palma",
    "sg:orig_category":"Servicios De Telecomunicaciones",
    "sg:phone":"+34 971 28 39 37",
    "sg:postcode":"07014",
    "sg:province":"Islas Baleares",
    "wof:name":"Singh  Mandeep",
    "wof:placetype":"venue"
},
  "geometry": {"coordinates":[2.6257479191,39.5630531311],"type":"Point"}
}