{
  "type": "Feature",
  "properties": {
    "iso:country":"ES",
    "sg:address":"Carr Calderon De La Barca, (de), 16",
    "sg:city":"Carlet",
    "sg:orig_category":"Carnicer\u00cdas, Carnicer\u00cdas",
    "sg:phone":"+34 962 53 04 60",
    "sg:postcode":"46240",
    "sg:province":"Valencia",
    "wof:name":"Ferriols Hervas Bernardo",
    "wof:placetype":"venue"
},
  "geometry": {"coordinates":[-0.520622015,39.2257537842],"type":"Point"}
}