{
  "type": "Feature",
  "properties": {
    "iso:country":"ES",
    "sg:address":"Calle de Fuente, 23",
    "sg:city":"Pradejon",
    "sg:orig_category":"Centros De Educaci\u00d3n Especial",
    "sg:phone":"+34 941 15 01 59",
    "sg:postcode":"26510",
    "sg:province":"La Rioja",
    "wof:name":"Colegio Publico Jose Ortega Valderrama",
    "wof:placetype":"venue"
},
  "geometry": {"coordinates":[-2.0696909428,42.3326759338],"type":"Point"}
}