{
  "type": "Feature",
  "properties": {
    "addr:full":"Calle de General Garcia De La Herran, 36 S. Fernando C\u00e1diz 11100",
    "addr:housenumber":"36",
    "addr:postcode":"11100",
    "addr:street":"Calle De General Garcia De La Herran;S. Fernando Ca\u0301Diz",
    "iso:country":"ES",
    "sg:address":"Calle de General Garcia De La Herran, 36",
    "sg:city":"S. Fernando",
    "sg:orig_category":"Cajas De Ahorro",
    "sg:phone":"+34 956 89 60 30",
    "sg:postcode":"11100",
    "sg:province":"C\u00e1diz",
    "wof:name":"Cajagranada",
    "wof:placetype":"venue"
},
  "geometry": {"coordinates":[-6.1983060837,36.4668273926],"type":"Point"}
}