{
  "type": "Feature",
  "properties": {
    "iso:country":"ES",
    "sg:address":"Av Madrid, 192",
    "sg:city":"Barcelona",
    "sg:orig_category":"Fabricaci\u00d3n De Sobres, Bolsas Y Fundas",
    "sg:phone":"+34 933 39 72 29",
    "sg:postcode":"08028",
    "sg:province":"Barcelona",
    "wof:name":"Reina Santos Antonio",
    "wof:placetype":"venue"
},
  "geometry": {"coordinates":[2.1331100464,41.380859375],"type":"Point"}
}