{
  "type": "Feature",
  "properties": {
    "addr:full":"Calle de Fotografos Darblade, 13 Torrevieja Alicante 03180",
    "addr:housenumber":"13",
    "addr:postcode":"03180",
    "addr:street":"Calle De Fotografos Darblade",
    "iso:country":"ES",
    "sg:address":"Calle de Fotografos Darblade, 13",
    "sg:city":"Torrevieja",
    "sg:orig_category":"M\u00c9dicos: An\u00c1lisis Cl\u00cdnicos",
    "sg:phone":"+34 965 71 71 71",
    "sg:postcode":"03180",
    "sg:province":"Alicante",
    "wof:name":"Laboratorio De Analisis Clinicos Albentosa-lopez Die C.b",
    "wof:placetype":"venue"
},
  "geometry": {"coordinates":[-0.6536790133,38.0173606873],"type":"Point"}
}