{
  "type": "Feature",
  "properties": {
    "addr:full":"Italia Ciudad Del Transporte, S/n Imarcoain Navarra 31119",
    "addr:housenumber":"s / n",
    "addr:postcode":"31119",
    "iso:country":"ES",
    "sg:address":"Italia Ciudad Del Transporte, S/n",
    "sg:city":"Imarcoain",
    "sg:orig_category":"Asesor\u00cda Sobre Comunicaci\u00d3n De Empresas",
    "sg:phone":"+34 948 31 49 31",
    "sg:postcode":"31119",
    "sg:province":"Navarra",
    "wof:name":"Sip-tec Soluciones Integrales S.l.",
    "wof:placetype":"venue"
},
  "geometry": {"coordinates":[-1.5951639414,42.7345542908],"type":"Point"}
}