{
  "type": "Feature",
  "properties": {
    "iso:country":"ES",
    "sg:address":"Calle de Bolivia, 15",
    "sg:city":"Coslada",
    "sg:orig_category":"Cl\u00cdnicas Dentales",
    "sg:phone":"+34 916 73 80 52",
    "sg:postcode":"28820",
    "sg:province":"Madrid",
    "wof:name":"Laboratorio Fouchard S.l.",
    "wof:placetype":"venue"
},
  "geometry": {"coordinates":[-3.552719593,40.4251937866],"type":"Point"}
}