{
  "type": "Feature",
  "properties": {
    "iso:country":"ES",
    "sg:address":"Calle de Maliayo, 5",
    "sg:city":"Villaviciosa",
    "sg:orig_category":"Art\u00cdculos De Regalo (al Por Menor)",
    "sg:phone":"+34 985 89 05 83",
    "sg:postcode":"33300",
    "sg:province":"Asturias",
    "wof:name":"Estrada Llera Maria Josefa",
    "wof:placetype":"venue"
},
  "geometry": {"coordinates":[-5.4331941605,43.480255127],"type":"Point"}
}