{
  "type": "Feature",
  "properties": {
    "iso:country":"ES",
    "sg:address":"Pol Ind Landabaso, 2",
    "sg:city":"Bermeo",
    "sg:orig_category":"Construcci\u00d3n Mec\u00c1nica",
    "sg:phone":"+34 946 18 77 96",
    "sg:postcode":"48370",
    "sg:province":"Vizcaya",
    "wof:name":"Galdaber S.l.",
    "wof:placetype":"venue"
},
  "geometry": {"coordinates":[-2.7251009941,43.41929245],"type":"Point"}
}