{
  "type": "Feature",
  "properties": {
    "iso:country":"ES",
    "sg:address":"Ctra Esplugues, 1",
    "sg:city":"Fatjo",
    "sg:orig_category":"Ropa Para Caballeros (al Por Menor)",
    "sg:phone":"+34 933 77 14 06",
    "sg:postcode":"08940",
    "sg:province":"Barcelona",
    "sg:website":"ww.jackjones.es",
    "wof:name":"Totfun S.l.",
    "wof:placetype":"venue"
},
  "geometry": {"coordinates":[2.0708940029,41.3559417725],"type":"Point"}
}