{
  "type": "Feature",
  "properties": {
    "addr:full":"Calle de Fraternidad, S/n Murchante Navarra 31521",
    "addr:housenumber":"s / n",
    "addr:postcode":"31521",
    "addr:street":"Calle De Fraternidad",
    "iso:country":"ES",
    "sg:address":"Calle de Fraternidad, S/n",
    "sg:city":"Murchante",
    "sg:orig_category":"Ropa Para Se\u00d1oras Y Caballeros (al Por Menor)",
    "sg:phone":"+34 948 83 81 55",
    "sg:postcode":"31521",
    "sg:province":"Navarra",
    "wof:name":"Alduan Alava Maria Nieves",
    "wof:placetype":"venue"
},
  "geometry": {"coordinates":[-1.657038331,42.0303535461],"type":"Point"}
}