{
  "type": "Feature",
  "properties": {
    "addr:full":"Calle de Colon, 17 Cuenca Cuenca 16002",
    "addr:housenumber":"17",
    "addr:postcode":"16002",
    "addr:street":"Calle De Colon",
    "iso:country":"ES",
    "sg:address":"Calle de Colon, 17",
    "sg:city":"Cuenca",
    "sg:orig_category":"Contables",
    "sg:phone":"+34 969 22 22 58",
    "sg:postcode":"16002",
    "sg:province":"Cuenca",
    "wof:name":"Garcia Martinez Jose Ramon",
    "wof:placetype":"venue"
},
  "geometry": {"coordinates":[-2.1377813816,40.0743370056],"type":"Point"}
}