{
  "type": "Feature",
  "properties": {
    "iso:country":"ES",
    "sg:address":"Urb. Nueva Andalucia, 246",
    "sg:city":"Nueva Andalucia",
    "sg:orig_category":"Asociaciones Y Clubs Deportivos",
    "sg:phone":"+34 952 81 45 40",
    "sg:postcode":"29660",
    "sg:province":"M\u00e1laga",
    "wof:name":"Club Nordico Cultural",
    "wof:placetype":"venue"
},
  "geometry": {"coordinates":[-4.9540290833,36.5049514771],"type":"Point"}
}