{
  "type": "Feature",
  "properties": {
    "iso:country":"ES",
    "sg:address":"Avgd Alameda Jaume I, 29",
    "sg:city":"Xativa",
    "sg:orig_category":"Confecci\u00d3n De Trajes Para Se\u00d1oras",
    "sg:phone":"+34 962 27 68 76",
    "sg:postcode":"46800",
    "sg:province":"Valencia",
    "wof:name":"Requena Gimenez Antonio",
    "wof:placetype":"venue"
},
  "geometry": {"coordinates":[-0.5237929821,38.9893226624],"type":"Point"}
}