{
  "type": "Feature",
  "properties": {
    "iso:country":"ES",
    "sg:address":"Carrer de Miquel Marques, 12",
    "sg:city":"Palma",
    "sg:orig_category":"Papeler\u00cdas, Librer\u00cdas",
    "sg:phone":"+34 971 46 65 46",
    "sg:postcode":"07005",
    "sg:province":"Islas Baleares",
    "wof:name":"Corbaes Fernandez Wilma",
    "wof:placetype":"venue"
},
  "geometry": {"coordinates":[2.6580059528,39.576171875],"type":"Point"}
}