{
  "type": "Feature",
  "properties": {
    "addr:full":"Pque Parque Del Carmen, 7 Logro\u00f1o La Rioja 26003",
    "addr:housenumber":"7",
    "addr:postcode":"26003",
    "addr:street":"Del Carmen;Rioja",
    "iso:country":"ES",
    "sg:address":"Pque Parque Del Carmen, 7",
    "sg:city":"Logro\u00f1o",
    "sg:orig_category":"Comit\u00c9s De Organizaci\u00d3n De Exposiciones, Ferias, Salones",
    "sg:phone":"+34 941 24 66 97",
    "sg:postcode":"26003",
    "sg:province":"La Rioja",
    "wof:name":"Organizacion De Congresos Y Exposiciones S.l.",
    "wof:placetype":"venue"
},
  "geometry": {"coordinates":[-2.4461789131,42.4652786255],"type":"Point"}
}