{
  "type": "Feature",
  "properties": {
    "iso:country":"ES",
    "sg:address":"Castejon, 119",
    "sg:city":"Lanjaron",
    "sg:orig_category":"Aceites Y Grasas Alimentarias (fabricaci\u00d3n, Al Por Mayor)",
    "sg:phone":"+34 958 77 01 76",
    "sg:postcode":"18420",
    "sg:province":"Granada",
    "wof:name":"Gallegos Galvez Antonio",
    "wof:placetype":"venue"
},
  "geometry": {"coordinates":[-3.470032692,36.9358253479],"type":"Point"}
}