{
  "type": "Feature",
  "properties": {
    "iso:country":"ES",
    "sg:address":"Calle de Arandano, 1",
    "sg:city":"Cabo Palos",
    "sg:orig_category":"Inmobiliaria (agencias)",
    "sg:phone":"+34 968 33 70 56",
    "sg:postcode":"30370",
    "sg:province":"Murcia",
    "sg:website":"www.abacasa.com",
    "wof:name":"Inmobiliarias Abacasa S.l.",
    "wof:placetype":"venue"
},
  "geometry": {"coordinates":[-0.7062845826,37.632648468],"type":"Point"}
}