{
  "type": "Feature",
  "properties": {
    "addr:full":"Avda Termica (la), S/n Robla Le\u00f3n 24640",
    "addr:postcode":"24640",
    "addr:street":"Avda Termica La S / N;Leo\u0301N",
    "iso:country":"ES",
    "sg:address":"Avda Termica (la), S/n",
    "sg:city":"Robla",
    "sg:orig_category":"Carb\u00d3n, Carb\u00d3n De Madera (al Por Mayor)",
    "sg:phone":"+34 987 57 02 26",
    "sg:postcode":"24640",
    "sg:province":"Le\u00f3n",
    "wof:name":"Cenizas Volantes Del Norte S. A.",
    "wof:placetype":"venue"
},
  "geometry": {"coordinates":[-5.6283431053,42.7975349426],"type":"Point"}
}