{
  "type": "Feature",
  "properties": {
    "iso:country":"ES",
    "sg:address":"Carrer de Ramon Llull, 17",
    "sg:city":"Gava",
    "sg:orig_category":"Formaci\u00d3n Continuada (variada)",
    "sg:phone":"+34 936 33 32 06",
    "sg:postcode":"08850",
    "sg:province":"Barcelona",
    "wof:name":"Aula Lluch S.coop.c.l.",
    "wof:placetype":"venue"
},
  "geometry": {"coordinates":[1.9996180534,41.3025856018],"type":"Point"}
}