{
  "type": "Feature",
  "properties": {
    "iso:country":"ES",
    "sg:address":"Calle de Pan Y Toros, 33",
    "sg:city":"Madrid",
    "sg:orig_category":"Carnicer\u00cdas, Carnicer\u00cdas",
    "sg:phone":"+34 913 17 52 60",
    "sg:postcode":"28041",
    "sg:province":"Madrid",
    "wof:name":"Parra De Matias Emiliano",
    "wof:placetype":"venue"
},
  "geometry": {"coordinates":[-3.6944189072,40.3583335876],"type":"Point"}
}