{
  "type": "Feature",
  "properties": {
    "iso:country":"ES",
    "sg:address":"Carrer de Padilla, 360",
    "sg:city":"Barcelona",
    "sg:orig_category":"Fabricaci\u00d3n, Importaci\u00d3n De L\u00c1mparas Y Bombillas",
    "sg:phone":"+34 934 50 45 89",
    "sg:postcode":"08025",
    "sg:province":"Barcelona",
    "wof:name":"Kitchen Room S.l.",
    "wof:placetype":"venue"
},
  "geometry": {"coordinates":[2.1701700687,41.4112205505],"type":"Point"}
}