{
  "type": "Feature",
  "properties": {
    "addr:full":"Av Marina, De Sa, S/n Cala D'or Islas Baleares 07660",
    "addr:postcode":"07660",
    "addr:street":"Av Marina De Sa S / N",
    "iso:country":"ES",
    "sg:address":"Av Marina, De Sa, S/n",
    "sg:city":"Cala D'or",
    "sg:orig_category":"Art\u00cdculos De Regalo (al Por Menor)",
    "sg:phone":"+34 971 64 86 46",
    "sg:postcode":"07660",
    "sg:province":"Islas Baleares",
    "wof:name":"Egos D'or S.l.",
    "wof:placetype":"venue"
},
  "geometry": {"coordinates":[2.9117100239,39.6136398315],"type":"Point"}
}