{
  "type": "Feature",
  "properties": {
    "iso:country":"ES",
    "sg:address":"Calle de Sierra Carbonera, 63",
    "sg:city":"Madrid",
    "sg:orig_category":"Quincaller\u00cda (al Por Menor)",
    "sg:phone":"+34 914 78 73 30",
    "sg:postcode":"28053",
    "sg:province":"Madrid",
    "wof:name":"Sanchez Moral Manuel",
    "wof:placetype":"venue"
},
  "geometry": {"coordinates":[-3.6647930145,40.3904838562],"type":"Point"}
}