{
  "type": "Feature",
  "properties": {
    "iso:country":"ES",
    "sg:address":"Calle de Teresa Zabell, 1",
    "sg:city":"Fuengirola",
    "sg:orig_category":"T\u00c9cnicos Veterinarios",
    "sg:phone":"+34 952 46 11 79",
    "sg:postcode":"29640",
    "sg:province":"M\u00e1laga",
    "wof:name":"Ogle Payeur Dominica",
    "wof:placetype":"venue"
},
  "geometry": {"coordinates":[-4.6196951866,36.5470237732],"type":"Point"}
}