{
  "type": "Feature",
  "properties": {
    "addr:full":"Pase Zumalakarregi Ibiltokia, 6 Tolosa Guip\u00f9zcoa 20400",
    "addr:housenumber":"6",
    "addr:postcode":"20400",
    "addr:street":"Zumalakarregi Ibiltokia;Guipu\u0300Zcoa",
    "iso:country":"ES",
    "sg:address":"Pase Zumalakarregi Ibiltokia, 6",
    "sg:city":"Tolosa",
    "sg:orig_category":"Telas Y Sedas (al Por Menor)",
    "sg:phone":"+34 943 65 24 01",
    "sg:postcode":"20400",
    "sg:province":"Guip\u00f9zcoa",
    "wof:name":"Beldarrain Sorrondegui Esperanza",
    "wof:placetype":"venue"
},
  "geometry": {"coordinates":[-2.0732319355,43.1355781555],"type":"Point"}
}