{
  "type": "Feature",
  "properties": {
    "addr:full":"Barr San Antonio, 5 Renedo Cantabria 39470",
    "addr:housenumber":"5",
    "addr:postcode":"39470",
    "addr:street":"San Antonio",
    "iso:country":"ES",
    "sg:address":"Barr San Antonio, 5",
    "sg:city":"Renedo",
    "sg:orig_category":"Electricidad Veh\u00cdculo",
    "sg:phone":"+34 942 57 21 57",
    "sg:postcode":"39470",
    "sg:province":"Cantabria",
    "wof:name":"Palazuelos Cobo Fernando",
    "wof:placetype":"venue"
},
  "geometry": {"coordinates":[-3.9539539814,43.3548316956],"type":"Point"}
}