{
  "type": "Feature",
  "properties": {
    "iso:country":"ES",
    "sg:address":"Calle de Empleo (del), 59",
    "sg:city":"Adaro",
    "sg:orig_category":"Promotores Constructores",
    "sg:phone":"+34 916 01 07 12",
    "sg:postcode":"28906",
    "sg:province":"Madrid",
    "wof:name":"Madler Maquinaria Construccion Y Servicios S.l.",
    "wof:placetype":"venue"
},
  "geometry": {"coordinates":[-3.7057700157,40.42029953],"type":"Point"}
}