{
  "type": "Feature",
  "properties": {
    "addr:full":"Calle de Medico Pascual Perez, 38 Alacant Alicante 03001",
    "addr:housenumber":"38",
    "addr:postcode":"03001",
    "addr:street":"Calle De Medico Pascual Perez",
    "iso:country":"ES",
    "sg:address":"Calle de Medico Pascual Perez, 38",
    "sg:city":"Alacant",
    "sg:orig_category":"Psic\u00d3logos",
    "sg:phone":"+34 965 20 74 39",
    "sg:postcode":"03001",
    "sg:province":"Alicante",
    "wof:name":"Farias De La Torre Gustavo",
    "wof:placetype":"venue"
},
  "geometry": {"coordinates":[-0.4886670113,38.3458862305],"type":"Point"}
}