{
  "type": "Feature",
  "properties": {
    "iso:country":"ES",
    "sg:address":"C/ Lluna (de La), 32",
    "sg:city":"Ripollet",
    "sg:orig_category":"Costureras",
    "sg:phone":"+34 935 86 42 49",
    "sg:postcode":"08291",
    "sg:province":"Barcelona",
    "wof:name":"Soria Pardo Rosario",
    "wof:placetype":"venue"
},
  "geometry": {"coordinates":[2.160271883,41.4985313416],"type":"Point"}
}