{
  "type": "Feature",
  "properties": {
    "addr:full":"Avda Espa\u00d1a (de), 110 Dos Hermanas Sevilla 41700",
    "addr:housenumber":"110",
    "addr:postcode":"41700",
    "addr:street":"Avda Espan\u0303A De;Sevilla",
    "iso:country":"ES",
    "sg:address":"Avda Espa\u00d1a (de), 110",
    "sg:city":"Dos Hermanas",
    "sg:orig_category":"Muebles, Minoristas",
    "sg:phone":"+34 954 72 88 13",
    "sg:postcode":"41700",
    "sg:province":"Sevilla",
    "sg:website":"www.misofa.es",
    "wof:name":"Tapesco S.l.",
    "wof:placetype":"venue"
},
  "geometry": {"coordinates":[-5.9145979881,37.2830238342],"type":"Point"}
}