{
  "type": "Feature",
  "properties": {
    "iso:country":"ES",
    "sg:address":"Avda Jose Antonio, 5",
    "sg:city":"Coca",
    "sg:orig_category":"Quincaller\u00cda (al Por Menor)",
    "sg:phone":"+34 921 58 60 65",
    "sg:postcode":"40480",
    "sg:province":"Segovia",
    "wof:name":"Fernandez Garcia Jose Angel",
    "wof:placetype":"venue"
},
  "geometry": {"coordinates":[-4.5210280418,41.2163925171],"type":"Point"}
}