{
  "type": "Feature",
  "properties": {
    "iso:country":"ES",
    "sg:address":"Calle de Diego Betancor Suarez, 16",
    "sg:city":"Palmas De Gran Canaria",
    "sg:orig_category":"Cl\u00cdnicas Dentales",
    "sg:phone":"+34 928 41 78 55",
    "sg:postcode":"35012",
    "sg:province":"Las Palmas",
    "wof:name":"Lopez Henriquez Dulce Maria",
    "wof:placetype":"venue"
},
  "geometry": {"coordinates":[-15.4454097748,28.1093769073],"type":"Point"}
}