{
  "type": "Feature",
  "properties": {
    "addr:full":"Ctra Tora, 31 Solsona Lleida 25280",
    "addr:housenumber":"31",
    "addr:postcode":"25280",
    "addr:street":"Ctra Tora",
    "iso:country":"ES",
    "sg:address":"Ctra Tora, 31",
    "sg:city":"Solsona",
    "sg:orig_category":"Farmacias",
    "sg:phone":"+34 973 48 38 46",
    "sg:postcode":"25280",
    "sg:province":"Lleida",
    "wof:name":"Parafarmacia Solsones Carme I Anna S.c.p.",
    "wof:placetype":"venue"
},
  "geometry": {"coordinates":[1.512879014,41.9920196533],"type":"Point"}
}