{
  "type": "Feature",
  "properties": {
    "iso:country":"ES",
    "sg:address":"Calle de Palma, 31",
    "sg:city":"Castro Rio",
    "sg:orig_category":"Ense\u00d1anza: Idiomas",
    "sg:phone":"+34 957 37 09 20",
    "sg:postcode":"14840",
    "sg:province":"C\u00f3rdoba",
    "wof:name":"Albany School Of English S.l.",
    "wof:placetype":"venue"
},
  "geometry": {"coordinates":[-4.482421875,37.6896438599],"type":"Point"}
}