{
  "type": "Feature",
  "properties": {
    "addr:full":"Calle de Ramon Y Cajal, 2 Onda Castell\u00f3n 12200",
    "addr:housenumber":"2",
    "addr:postcode":"12200",
    "addr:street":"Calle De Ramon Y Cajal;Castello\u0301N",
    "iso:country":"ES",
    "sg:address":"Calle de Ramon Y Cajal, 2",
    "sg:city":"Onda",
    "sg:orig_category":"Puros, Cigarrillos Y Tabaco (fabricaci\u00d3n, Al Por Mayor)",
    "sg:phone":"+34 964 60 08 25",
    "sg:postcode":"12200",
    "sg:province":"Castell\u00f3n",
    "wof:name":"Tabantesp S.l.",
    "wof:placetype":"venue"
},
  "geometry": {"coordinates":[-0.2613550127,39.9653701782],"type":"Point"}
}