{
  "type": "Feature",
  "properties": {
    "iso:country":"ES",
    "sg:address":"Carrer de Cort (la), 18",
    "sg:city":"Vilafranca Penedes",
    "sg:orig_category":"Centros De Coordinaci\u00d3n",
    "sg:phone":"+34 938 92 23 93",
    "sg:postcode":"08720",
    "sg:province":"Barcelona",
    "wof:name":"Gestoria Marce S.l.",
    "wof:placetype":"venue"
},
  "geometry": {"coordinates":[1.6976929903,41.3463401794],"type":"Point"}
}