{
  "type": "Feature",
  "properties": {
    "addr:full":"Carr Mallorquines, 4 Urbanitzacio Mallorquines Girona 17410",
    "addr:housenumber":"4",
    "addr:postcode":"17410",
    "addr:street":"Carr Mallorquines",
    "iso:country":"ES",
    "sg:address":"Carr Mallorquines, 4",
    "sg:city":"Urbanitzacio Mallorquines",
    "sg:orig_category":"Contenedores (mercanc\u00cdas)",
    "sg:phone":"+34 972 16 82 46",
    "sg:postcode":"17410",
    "sg:province":"Girona",
    "wof:name":"Mas Oller Lluis",
    "wof:placetype":"venue"
},
  "geometry": {"coordinates":[2.745290041,41.8085403442],"type":"Point"}
}