{
  "type": "Feature",
  "properties": {
    "iso:country":"ES",
    "sg:address":"El Tercio, S/n",
    "sg:city":"Tortoles De Esgueva",
    "sg:orig_category":"Producci\u00d3n, Venta De Productos De Agricultura Biol\u00d3gica",
    "sg:phone":"+34 947 55 17 00",
    "sg:postcode":"09312",
    "sg:province":"Burgos",
    "wof:name":"Valderas S.coop.",
    "wof:placetype":"venue"
},
  "geometry": {"coordinates":[-4.0226449966,41.8158721924],"type":"Point"}
}