{
  "type": "Feature",
  "properties": {
    "addr:full":"Calle de Julian Garcia Hernandez, 6 Almendralejo Badajoz 06200",
    "addr:housenumber":"6",
    "addr:postcode":"06200",
    "addr:street":"Calle De Julian Garcia Hernandez",
    "iso:country":"ES",
    "sg:address":"Calle de Julian Garcia Hernandez, 6",
    "sg:city":"Almendralejo",
    "sg:classifiers":[
        {
            "category":"Autos & Motor Vehicles",
            "subcategory":"Automobile Sales",
            "type":"Retail Goods"
        }
    ],
    "sg:phone":"+34 924 66 06 04",
    "sg:postcode":"06200",
    "sg:province":"Badajoz",
    "wof:name":"Almendralejo S. A.",
    "wof:placetype":"venue"
},
  "geometry": {"coordinates":[-6.4049062729,38.6838912964],"type":"Point"}
}