{
  "type": "Feature",
  "properties": {
    "iso:country":"ES",
    "sg:address":"Calle de Marbella, 9",
    "sg:city":"Estepona",
    "sg:orig_category":"Empresas De Vigilancia, Guardia Y Protecci\u00d3n",
    "sg:phone":"+34 952 92 82 02",
    "sg:postcode":"29680",
    "sg:province":"M\u00e1laga",
    "wof:name":"Gilma De Servicios 2000 S.l.",
    "wof:placetype":"venue"
},
  "geometry": {"coordinates":[-5.1828389168,36.4116592407],"type":"Point"}
}