{
  "type": "Feature",
  "properties": {
    "iso:country":"ES",
    "sg:address":"Carr Sant Antoni Maria Claret, 42",
    "sg:city":"Ciutadella Menorca",
    "sg:orig_category":"Maquinaria Para Industrias Diversas",
    "sg:phone":"+34 971 38 08 41",
    "sg:postcode":"07760",
    "sg:province":"Islas Baleares",
    "wof:name":"Benejam Piris Jaime",
    "wof:placetype":"venue"
},
  "geometry": {"coordinates":[3.8445839882,40.0037918091],"type":"Point"}
}