{
  "type": "Feature",
  "properties": {
    "addr:full":"Calle de Clara Del Rey, 50 Madrid Madrid 28002",
    "addr:housenumber":"50",
    "addr:postcode":"madrid;28002",
    "addr:street":"Calle De Clara Del Rey",
    "iso:country":"ES",
    "sg:address":"Calle de Clara Del Rey, 50",
    "sg:city":"Madrid",
    "sg:orig_category":"Bisuter\u00cda, Joyer\u00cda, Relojer\u00cda (al Por Menor)",
    "sg:phone":"+34 914 16 24 97",
    "sg:postcode":"28002",
    "sg:province":"Madrid",
    "wof:name":"Veya M.l. S.l.u.",
    "wof:placetype":"venue"
},
  "geometry": {"coordinates":[-3.6680989265,40.44556427],"type":"Point"}
}