{
  "type": "Feature",
  "properties": {
    "addr:full":"Avda Conde De Fenosa, 37 Barco Ourense 32300",
    "addr:housenumber":"37",
    "addr:postcode":"32300",
    "addr:street":"Avda Conde De Fenosa",
    "iso:country":"ES",
    "sg:address":"Avda Conde De Fenosa, 37",
    "sg:city":"Barco",
    "sg:orig_category":"Equitaci\u00d3n Y Centros De H\u00cdpica",
    "sg:phone":"+34 988 32 20 82",
    "sg:postcode":"32300",
    "sg:province":"Ourense",
    "wof:name":"Novo Rodriguez Rosa Maria",
    "wof:placetype":"venue"
},
  "geometry": {"coordinates":[-6.9890742302,42.4164886475],"type":"Point"}
}