{
  "type": "Feature",
  "properties": {
    "addr:full":"Crtra. Pinedas, 15 La Chica-carlota C\u00f3rdoba 14111",
    "addr:housenumber":"15",
    "addr:postcode":"14111",
    "addr:street":"Crtra. Pinedas;La Chica-Carlota Co\u0301Rdoba",
    "iso:country":"ES",
    "sg:address":"Crtra. Pinedas, 15",
    "sg:city":"La Chica-carlota",
    "sg:orig_category":"Electricidad: Instaladores",
    "sg:phone":"+34 957 30 03 02",
    "sg:postcode":"14111",
    "sg:province":"C\u00f3rdoba",
    "wof:name":"Urbano Algaba Juan",
    "wof:placetype":"venue"
},
  "geometry": {"coordinates":[-4.9494738579,37.698928833],"type":"Point"}
}