{
  "type": "Feature",
  "properties": {
    "iso:country":"ES",
    "sg:address":"Carrer de Puigbarral, 34",
    "sg:city":"Terrassa",
    "sg:orig_category":"Maquinaria Neum\u00c1tica",
    "sg:phone":"+34 937 85 42 45",
    "sg:postcode":"08227",
    "sg:province":"Barcelona",
    "sg:website":"www.gmsystem.net",
    "wof:name":"Garcia Marin System S.l.",
    "wof:placetype":"venue"
},
  "geometry": {"coordinates":[2.0342280865,41.5809936523],"type":"Point"}
}