{
  "type": "Feature",
  "properties": {
    "iso:country":"ES",
    "sg:address":"Carrer de Puig I Cadafalch, 50",
    "sg:city":"S. Cugat Valles",
    "sg:classifiers":[
        {
            "category":"Casinos & Gambling",
            "type":"Entertainment"
        }
    ],
    "sg:phone":"+34 935 89 39 38",
    "sg:postcode":"08172",
    "sg:province":"Barcelona",
    "sg:tags":[
        "locale",
        "de",
        "juego"
    ],
    "wof:name":"Badabadoc Punt Net S.l.",
    "wof:placetype":"venue"
},
  "geometry": {"coordinates":[2.0936100483,41.4717559814],"type":"Point"}
}