{
  "type": "Feature",
  "properties": {
    "iso:country":"ES",
    "sg:address":"Calle de San Pedro, 21",
    "sg:city":"Marchena",
    "sg:orig_category":"Promotores Constructores",
    "sg:phone":"+34 954 84 59 53",
    "sg:postcode":"41620",
    "sg:province":"Sevilla",
    "wof:name":"Colorasur S.l.",
    "wof:placetype":"venue"
},
  "geometry": {"coordinates":[-5.4159798622,37.3281707764],"type":"Point"}
}