{
  "type": "Feature",
  "properties": {
    "iso:country":"ES",
    "sg:address":"Calle de Olmo (del), S/n",
    "sg:city":"Camarena De La Sierra",
    "sg:orig_category":"Fabricaci\u00d3n De Quesos",
    "sg:phone":"+34 978 78 60 46",
    "sg:postcode":"44459",
    "sg:province":"Teruel",
    "wof:name":"Agrocamarena",
    "wof:placetype":"venue"
},
  "geometry": {"coordinates":[-1.0777722597,40.1197967529],"type":"Point"}
}