{
  "type": "Feature",
  "properties": {
    "iso:country":"ES",
    "sg:address":"Calle de San Antonio, 6",
    "sg:city":"Llosa Ranes",
    "sg:orig_category":"Fotograf\u00cda Art\u00cdstica Y Retratos",
    "sg:phone":"+34 962 23 03 01",
    "sg:postcode":"46815",
    "sg:province":"Valencia",
    "wof:name":"Fuentes Cucarella Salvador",
    "wof:placetype":"venue"
},
  "geometry": {"coordinates":[-0.5347129703,39.0183677673],"type":"Point"}
}