{
  "type": "Feature",
  "properties": {
    "addr:full":"Ctra. Oropesa, Km. 0001,5 Candeleda \u00c1vila 05480",
    "addr:postcode":"05480",
    "addr:street":"Ctra. Oropesa Km. 0001,5;A\u0301Vila",
    "iso:country":"ES",
    "sg:address":"Ctra. Oropesa, Km. 0001,5",
    "sg:city":"Candeleda",
    "sg:orig_category":"Transporte En General",
    "sg:phone":"+34 920 38 09 36",
    "sg:postcode":"05480",
    "sg:province":"\u00c1vila",
    "wof:name":"Lancho Candeleda S.l.",
    "wof:placetype":"venue"
},
  "geometry": {"coordinates":[-5.2322301865,40.1393127441],"type":"Point"}
}