{
  "type": "Feature",
  "properties": {
    "iso:country":"ES",
    "sg:address":"Plaz Leon Ortega, S/n",
    "sg:city":"Ayamonte",
    "sg:orig_category":"Televisi\u00d3n, V\u00cddeo: Aparatos Y Accesorios (venta)",
    "sg:phone":"+34 959 47 06 26",
    "sg:postcode":"21400",
    "sg:province":"Huelva",
    "wof:name":"Romero Riquelme Domingo",
    "wof:placetype":"venue"
},
  "geometry": {"coordinates":[-7.4030041695,37.2069358826],"type":"Point"}
}