{
  "type": "Feature",
  "properties": {
    "addr:full":"Carr Espados, 48 Almenar Lleida 25126",
    "addr:housenumber":"48",
    "addr:postcode":"25126",
    "addr:street":"Carr Espados",
    "iso:country":"ES",
    "sg:address":"Carr Espados, 48",
    "sg:city":"Almenar",
    "sg:orig_category":"Negocio De Materiales De Construcci\u00d3n",
    "sg:phone":"+34 973 77 12 59",
    "sg:postcode":"25126",
    "sg:province":"Lleida",
    "wof:name":"Estructures Bolesco Sl",
    "wof:placetype":"venue"
},
  "geometry": {"coordinates":[0.5701000094,41.7965431213],"type":"Point"}
}