{
  "type": "Feature",
  "properties": {
    "addr:full":"Cm\u00d1o Vello, 1 Vilamean Pontevedra 36350",
    "addr:housenumber":"1",
    "addr:postcode":"36350",
    "addr:street":"Vello",
    "iso:country":"ES",
    "sg:address":"Cm\u00d1o Vello, 1",
    "sg:city":"Vilamean",
    "sg:classifiers":[
        {
            "category":"Taxi",
            "type":"Transportation"
        }
    ],
    "sg:phone":"+34 986 36 50 95",
    "sg:postcode":"36350",
    "sg:province":"Pontevedra",
    "wof:name":"Vi\u00f1as Dominguez Antonia",
    "wof:placetype":"venue"
},
  "geometry": {"coordinates":[-8.8009996414,42.1586036682],"type":"Point"}
}