{
  "type": "Feature",
  "properties": {
    "iso:country":"ES",
    "sg:address":"Rua Velle (de), S/n",
    "sg:city":"Velle",
    "sg:orig_category":"Suministros Y Colocaci\u00d3n De Canalones Para Aguas Pluviales",
    "sg:phone":"+34 988 25 11 86",
    "sg:postcode":"32960",
    "sg:province":"Ourense",
    "wof:name":"Negreira Tarrios Samuel",
    "wof:placetype":"venue"
},
  "geometry": {"coordinates":[-7.8337731361,42.3690948486],"type":"Point"}
}