{
  "type": "Feature",
  "properties": {
    "iso:country":"ES",
    "sg:address":"Calle de Marcelo Usera, 85",
    "sg:city":"Madrid",
    "sg:orig_category":"Ropa Para Se\u00d1oras (al Por Menor)",
    "sg:phone":"+34 914 75 65 98",
    "sg:postcode":"28026",
    "sg:province":"Madrid",
    "wof:name":"Jupi S.l.",
    "wof:placetype":"venue"
},
  "geometry": {"coordinates":[-3.7065420151,40.3856277466],"type":"Point"}
}