{
  "type": "Feature",
  "properties": {
    "iso:country":"ES",
    "sg:address":"Urb. Santa Rita, 12",
    "sg:city":"Olivares",
    "sg:orig_category":"Agencias Y Agentes Comerciales, Representantes",
    "sg:phone":"+34 954 11 00 24",
    "sg:postcode":"41804",
    "sg:province":"Sevilla",
    "wof:name":"Perez Guzman Juan Jose",
    "wof:placetype":"venue"
},
  "geometry": {"coordinates":[-6.153439045,37.4184074402],"type":"Point"}
}