{
  "type": "Feature",
  "properties": {
    "iso:country":"ES",
    "sg:address":"Calle de Marques De Comillas, 36",
    "sg:city":"Benidorm",
    "sg:orig_category":"Caf\u00c9s, Bares, Cervecer\u00cdas",
    "sg:phone":"+34 965 86 08 55",
    "sg:postcode":"03500",
    "sg:province":"Alicante",
    "wof:name":"Lopez Ba\u00f1on Francisco",
    "wof:placetype":"venue"
},
  "geometry": {"coordinates":[-0.1344756037,38.5378684998],"type":"Point"}
}