{
  "type": "Feature",
  "properties": {
    "iso:country":"ES",
    "sg:address":"Montenegro, 955",
    "sg:city":"Puebla Vicar",
    "sg:orig_category":"Delegados, Agentes De Tr\u00c1nsito, Auxiliares De Transporte Internacional",
    "sg:phone":"+34 950 55 35 00",
    "sg:postcode":"04738",
    "sg:province":"Almer\u00eda",
    "wof:name":"Fernandez Fernandez Francisco",
    "wof:placetype":"venue"
},
  "geometry": {"coordinates":[-2.6420009136,36.8316612244],"type":"Point"}
}