{
  "type": "Feature",
  "properties": {
    "addr:full":"Ctra. Sagunto-burgos, Km. 0083,0 Sarrion Teruel 44460",
    "addr:postcode":"44460",
    "addr:street":"Ctra. Sagunto-Burgos Km. 0083,0",
    "iso:country":"ES",
    "sg:address":"Ctra. Sagunto-burgos, Km. 0083,0",
    "sg:city":"Sarrion",
    "sg:orig_category":"Control T\u00c9cnico De Veh\u00cdculos",
    "sg:phone":"+34 978 78 12 81",
    "sg:postcode":"44460",
    "sg:province":"Teruel",
    "wof:name":"Itv Barbastro S.a.",
    "wof:placetype":"venue"
},
  "geometry": {"coordinates":[-0.8065789938,40.1414604187],"type":"Point"}
}