{
  "type": "Feature",
  "properties": {
    "iso:country":"ES",
    "sg:address":"Rua Perfectino Vieitez, 21",
    "sg:city":"Carballi\u00f1o",
    "sg:classifiers":[
        {
            "category":"Personal",
            "subcategory":"Barber",
            "type":"Services"
        }
    ],
    "sg:phone":"+34 988 27 06 45",
    "sg:postcode":"32500",
    "sg:province":"Ourense",
    "sg:tags":[
        "caballeros",
        "de",
        "peluqueros"
    ],
    "wof:name":"Gonzalez Hermida Emilio",
    "wof:placetype":"venue"
},
  "geometry": {"coordinates":[-8.0770606995,42.4309005737],"type":"Point"}
}