{
  "type": "Feature",
  "properties": {
    "addr:full":"Pe\u00f1aullan, S/n Pravia Asturias 33127",
    "addr:postcode":"33127",
    "addr:street":"Pen\u0303Aullan S / N",
    "iso:country":"ES",
    "sg:address":"Pe\u00f1aullan, S/n",
    "sg:city":"Pravia",
    "sg:orig_category":"Chapister\u00cda",
    "sg:phone":"+34 985 82 07 02",
    "sg:postcode":"33127",
    "sg:province":"Asturias",
    "wof:name":"Talleres Meredal S.l.",
    "wof:placetype":"venue"
},
  "geometry": {"coordinates":[-6.0907092094,43.4918785095],"type":"Point"}
}