{
  "type": "Feature",
  "properties": {
    "iso:country":"ES",
    "sg:address":"Av Catalunya, 22",
    "sg:city":"Agramunt",
    "sg:orig_category":"Empresas De Pintura Y Revestimientos",
    "sg:phone":"+34 973 39 12 53",
    "sg:postcode":"25310",
    "sg:province":"Lleida",
    "wof:name":"Zurita Alcala Juan",
    "wof:placetype":"venue"
},
  "geometry": {"coordinates":[1.0951168537,41.7829666138],"type":"Point"}
}