{
  "type": "Feature",
  "properties": {
    "iso:country":"ES",
    "sg:address":"Calle de Juan Garcia Abellan Calle, 8",
    "sg:city":"Murcia",
    "sg:orig_category":"Asesor\u00cda Fiscal Y Jur\u00cddica",
    "sg:phone":"+34 968 23 38 88",
    "sg:postcode":"30007",
    "sg:province":"Murcia",
    "wof:name":"Martinez Martinez Antonio Gustavo",
    "wof:placetype":"venue"
},
  "geometry": {"coordinates":[-1.1197049618,37.9959373474],"type":"Point"}
}