{
  "type": "Feature",
  "properties": {
    "addr:full":"Calle de Romero (del), 10 Segovia Segovia 40002",
    "addr:housenumber":"10",
    "addr:postcode":"40002",
    "addr:street":"Calle De Romero Del",
    "iso:country":"ES",
    "sg:address":"Calle de Romero (del), 10",
    "sg:city":"Segovia",
    "sg:orig_category":"Restaurantes",
    "sg:phone":"+34 921 44 45 06",
    "sg:postcode":"40002",
    "sg:province":"Segovia",
    "wof:name":"Garcia Sanchez Jose Raul",
    "wof:placetype":"venue"
},
  "geometry": {"coordinates":[-4.1177930832,40.9400215149],"type":"Point"}
}