{
  "type": "Feature",
  "properties": {
    "addr:full":"Avda Santa Clara, 46 Santiago Murcia 30800",
    "addr:housenumber":"46",
    "addr:postcode":"30800",
    "addr:street":"Avda Santa Clara",
    "iso:country":"ES",
    "sg:address":"Avda Santa Clara, 46",
    "sg:city":"Santiago",
    "sg:orig_category":"Cooperativas Agr\u00cdcolas",
    "sg:phone":"+34 968 46 62 99",
    "sg:postcode":"30800",
    "sg:province":"Murcia",
    "wof:name":"Llamas Millan S.l.",
    "wof:placetype":"venue"
},
  "geometry": {"coordinates":[-1.6905640364,37.680557251],"type":"Point"}
}