{
  "type": "Feature",
  "properties": {
    "iso:country":"ES",
    "sg:address":"Calle de San Quilez, 13",
    "sg:city":"Binefar",
    "sg:orig_category":"Supermercados Y Hipermercados",
    "sg:phone":"+34 974 42 96 47",
    "sg:postcode":"22500",
    "sg:province":"Huesca",
    "wof:name":"Bunsuper S.l.",
    "wof:placetype":"venue"
},
  "geometry": {"coordinates":[0.2969709933,41.8494606018],"type":"Point"}
}