{
  "type": "Feature",
  "properties": {
    "addr:full":"Avda Cervantes De, 25 Aviles Asturias 33402",
    "addr:housenumber":"25",
    "addr:postcode":"33402",
    "addr:street":"Avda Cervantes De",
    "iso:country":"ES",
    "sg:address":"Avda Cervantes De, 25",
    "sg:city":"Aviles",
    "sg:orig_category":"Carnicer\u00cdas, Carnicer\u00cdas",
    "sg:phone":"+34 985 54 70 19",
    "sg:postcode":"33402",
    "sg:province":"Asturias",
    "wof:name":"Martinez Mendez Francisco Antonio",
    "wof:placetype":"venue"
},
  "geometry": {"coordinates":[-5.9263877869,43.534324646],"type":"Point"}
}