{
  "type": "Feature",
  "properties": {
    "addr:full":"Calle de Carlos Frontaura, 9 Malaga M\u00e1laga 29018",
    "addr:housenumber":"9",
    "addr:postcode":"29018",
    "addr:street":"Calle De Carlos Frontaura;Ma\u0301Laga",
    "iso:country":"ES",
    "sg:address":"Calle de Carlos Frontaura, 9",
    "sg:city":"Malaga",
    "sg:orig_category":"Molduras, Junquillos, Listones Y Molduras Perforadas",
    "sg:phone":"+34 952 20 30 90",
    "sg:postcode":"29018",
    "sg:province":"M\u00e1laga",
    "wof:name":"Diaz Ranea Francisco",
    "wof:placetype":"venue"
},
  "geometry": {"coordinates":[-4.357790947,36.7200889587],"type":"Point"}
}