{
  "type": "Feature",
  "properties": {
    "addr:full":"Avda Juan Sebastian Elcano, 23 Malaga M\u00e1laga 29017",
    "addr:housenumber":"23",
    "addr:postcode":"29017",
    "addr:street":"Avda Juan Sebastian Elcano;Ma\u0301Laga",
    "iso:country":"ES",
    "sg:address":"Avda Juan Sebastian Elcano, 23",
    "sg:city":"Malaga",
    "sg:orig_category":"Ense\u00d1anza: Idiomas",
    "sg:phone":"+34 952 29 15 11",
    "sg:postcode":"29017",
    "sg:province":"M\u00e1laga",
    "sg:website":"www.malaga-si.com",
    "wof:name":"Idiomas Si S.l.",
    "wof:placetype":"venue"
},
  "geometry": {"coordinates":[-4.3787469864,36.7221946716],"type":"Point"}
}