{
  "type": "Feature",
  "properties": {
    "addr:full":"Carrer de Pau Miralda, 33 Manresa Barcelona 08243",
    "addr:housenumber":"33",
    "addr:postcode":"08243",
    "addr:street":"Carrer De Pau Miralda",
    "iso:country":"ES",
    "sg:address":"Carrer de Pau Miralda, 33",
    "sg:city":"Manresa",
    "sg:orig_category":"Fabricaci\u00d3n De Pernos, Tornillos Y Clavos",
    "sg:phone":"+34 938 74 87 99",
    "sg:postcode":"08243",
    "sg:province":"Barcelona",
    "wof:name":"Ricard Vilellas Scp",
    "wof:placetype":"venue"
},
  "geometry": {"coordinates":[1.8475610018,41.7087287903],"type":"Point"}
}