{
  "type": "Feature",
  "properties": {
    "iso:country":"ES",
    "sg:address":"Bo Estacion Pol Ind, 51",
    "sg:city":"Zuera",
    "sg:orig_category":"Transportes Ferroviarios",
    "sg:phone":"+34 976 68 01 61",
    "sg:postcode":"50800",
    "sg:province":"Zaragoza",
    "wof:name":"Semat S.a.",
    "wof:placetype":"venue"
},
  "geometry": {"coordinates":[-0.7865840197,41.867225647],"type":"Point"}
}