{
  "type": "Feature",
  "properties": {
    "addr:full":"Rua Wenceslao Calvo Garra, 7 Lalin Pontevedra 36500",
    "addr:housenumber":"7",
    "addr:postcode":"36500",
    "addr:street":"Rua Wenceslao Calvo Garra",
    "iso:country":"ES",
    "sg:address":"Rua Wenceslao Calvo Garra, 7",
    "sg:city":"Lalin",
    "sg:orig_category":"Bazares, Art\u00cdculos De Limpieza Y De Cocina (al Por Menor)",
    "sg:phone":"+34 986 78 09 52",
    "sg:postcode":"36500",
    "sg:province":"Pontevedra",
    "wof:name":"Casa Y Algodon Mi Casa S.l.",
    "wof:placetype":"venue"
},
  "geometry": {"coordinates":[-8.1115865707,42.6617851257],"type":"Point"}
}