{
  "type": "Feature",
  "properties": {
    "iso:country":"ES",
    "sg:address":"Avda Baleares, 135",
    "sg:city":"Caba\u00d1uelas",
    "sg:orig_category":"Asesor\u00cda Sobre Comunicaci\u00d3n De Empresas",
    "sg:phone":"+34 950 55 44 31",
    "sg:postcode":"04738",
    "sg:province":"Almer\u00eda",
    "wof:name":"Navarro Estrella Javier Angel",
    "wof:placetype":"venue"
},
  "geometry": {"coordinates":[-2.6302781105,36.8037414551],"type":"Point"}
}