{
  "type": "Feature",
  "properties": {
    "iso:country":"ES",
    "sg:address":"Calle de Democracia, 6",
    "sg:city":"Celadas",
    "sg:orig_category":"Cr\u00cda De Animales",
    "sg:phone":"+34 978 65 20 03",
    "sg:postcode":"44194",
    "sg:province":"Teruel",
    "wof:name":"Saez Gomez Mariano",
    "wof:placetype":"venue"
},
  "geometry": {"coordinates":[-1.1503340006,40.474319458],"type":"Point"}
}