{
  "type": "Feature",
  "properties": {
    "iso:country":"ES",
    "sg:address":"Avda Fernando Diaz Villabella, 18",
    "sg:city":"Grado",
    "sg:orig_category":"Parafarmacias",
    "sg:phone":"+34 985 75 34 82",
    "sg:postcode":"33820",
    "sg:province":"Asturias",
    "sg:website":"www.farmarosa.es",
    "wof:name":"Rodriguez Gonzalez Mari Angeles",
    "wof:placetype":"venue"
},
  "geometry": {"coordinates":[-6.0734128952,43.3853988647],"type":"Point"}
}