{
  "type": "Feature",
  "properties": {
    "addr:full":"Carrer de Marina, 292 Barcelona Barcelona 08025",
    "addr:housenumber":"292",
    "addr:postcode":"08025",
    "addr:street":"Carrer De Marina",
    "iso:country":"ES",
    "sg:address":"Carrer de Marina, 292",
    "sg:city":"Barcelona",
    "sg:orig_category":"Molduras, Junquillos, Listones Y Molduras Perforadas",
    "sg:phone":"+34 934 35 38 07",
    "sg:postcode":"08025",
    "sg:province":"Barcelona",
    "wof:name":"Arque Oliva Esteban",
    "wof:placetype":"venue"
},
  "geometry": {"coordinates":[2.1737260818,41.4050445557],"type":"Point"}
}