{
  "type": "Feature",
  "properties": {
    "addr:full":"Calle de Pirineos, 8 Teruel Teruel 44003",
    "addr:housenumber":"8",
    "addr:postcode":"44003",
    "addr:street":"Calle De Pirineos",
    "iso:country":"ES",
    "sg:address":"Calle de Pirineos, 8",
    "sg:city":"Teruel",
    "sg:orig_category":"Agencias Y Agentes Comerciales, Representantes",
    "sg:phone":"+34 978 60 80 23",
    "sg:postcode":"44003",
    "sg:province":"Teruel",
    "wof:name":"Catalan Jarque Jose Antonio",
    "wof:placetype":"venue"
},
  "geometry": {"coordinates":[-1.1036690474,40.345954895],"type":"Point"}
}