{
  "type": "Feature",
  "properties": {
    "iso:country":"ES",
    "sg:address":"Calle de San Roke Kalea, 1",
    "sg:city":"Gernika-lumo",
    "sg:orig_category":"Zapatos (al Por Menor)",
    "sg:phone":"+34 946 25 18 54",
    "sg:postcode":"48300",
    "sg:province":"Vizcaya",
    "wof:name":"Alberto Conejo Gonzalez Y Otros, C.b.",
    "wof:placetype":"venue"
},
  "geometry": {"coordinates":[-2.676846981,43.3156890869],"type":"Point"}
}