{
  "type": "Feature",
  "properties": {
    "addr:full":"Calle de Fuencarral, 124 Madrid Madrid 28010",
    "addr:housenumber":"124",
    "addr:postcode":"28010",
    "addr:street":"Calle De Fuencarral",
    "iso:country":"ES",
    "sg:address":"Calle de Fuencarral, 124",
    "sg:city":"Madrid",
    "sg:orig_category":"Lencer\u00cda Femenina, Corseter\u00cda, Trajes De Ba\u00d1o (al Por Menor)",
    "sg:phone":"+34 914 48 83 55",
    "sg:postcode":"28010",
    "sg:province":"Madrid",
    "sg:website":"www.oyshoespa\u00f1a.com",
    "wof:name":"Oysho Espa\u00d1a S.a.",
    "wof:placetype":"venue"
},
  "geometry": {"coordinates":[-3.7027180195,40.4304008484],"type":"Point"}
}