{
  "type": "Feature",
  "properties": {
    "iso:country":"ES",
    "sg:address":"Calle de Meri\u00d1an, S/n",
    "sg:city":"Langreo",
    "sg:orig_category":"Construcciones Met\u00c1licas",
    "sg:phone":"+34 985 68 36 31",
    "sg:postcode":"33934",
    "sg:province":"Asturias",
    "wof:name":"Construcciones Metalicas Alba S.l.",
    "wof:placetype":"venue"
},
  "geometry": {"coordinates":[-5.7055912018,43.3097229004],"type":"Point"}
}