{
  "type": "Feature",
  "properties": {
    "addr:full":"Calle de B (poligono Industrial), 20 Villarrobledo Albacete 02600",
    "addr:housenumber":"20",
    "addr:postcode":"02600",
    "addr:street":"Calle De;Poligono Industrial",
    "iso:country":"ES",
    "sg:address":"Calle de B (poligono Industrial), 20",
    "sg:city":"Villarrobledo",
    "sg:orig_category":"Droguer\u00cdas (al Por Menor)",
    "sg:phone":"+34 967 14 60 41",
    "sg:postcode":"02600",
    "sg:province":"Albacete",
    "wof:name":"Ecoam P Limpieza Villarrobledo Sl",
    "wof:placetype":"venue"
},
  "geometry": {"coordinates":[-2.587526083,39.2759819031],"type":"Point"}
}