{
  "type": "Feature",
  "properties": {
    "addr:full":"Calle de Moral, 5 Noviercas Soria 42132",
    "addr:housenumber":"5",
    "addr:postcode":"42132",
    "addr:street":"Calle De Moral",
    "iso:country":"ES",
    "sg:address":"Calle de Moral, 5",
    "sg:city":"Noviercas",
    "sg:orig_category":"Iglesia Cat\u00d3lica",
    "sg:phone":"+34 975 38 50 53",
    "sg:postcode":"42132",
    "sg:province":"Soria",
    "wof:name":"Parroquia De Santos Justo Y Pastor",
    "wof:placetype":"venue"
},
  "geometry": {"coordinates":[-2.0366010666,41.7126350403],"type":"Point"}
}