{
  "type": "Feature",
  "properties": {
    "iso:country":"ES",
    "sg:address":"Calle de Salvador Sastre, 18",
    "sg:city":"Valencia",
    "sg:orig_category":"Asesor\u00cda Sobre Comunicaci\u00d3n De Empresas",
    "sg:phone":"+34 963 41 81 81",
    "sg:postcode":"46007",
    "sg:province":"Valencia",
    "wof:name":"Asesores Economicos Publicos S.l.",
    "wof:placetype":"venue"
},
  "geometry": {"coordinates":[-0.3805656135,39.4636268616],"type":"Point"}
}