{
  "type": "Feature",
  "properties": {
    "addr:full":"Calle de Virgen Del Amparo, 48 Guadalajara Guadalajara 19002",
    "addr:housenumber":"48",
    "addr:postcode":"19002",
    "addr:street":"Calle De Virgen Del Amparo",
    "iso:country":"ES",
    "sg:address":"Calle de Virgen Del Amparo, 48",
    "sg:city":"Guadalajara",
    "sg:orig_category":"Arquitectos",
    "sg:phone":"+34 949 21 30 25",
    "sg:postcode":"19002",
    "sg:province":"Guadalajara",
    "wof:name":"Burgos Gonzalez Rafael",
    "wof:placetype":"venue"
},
  "geometry": {"coordinates":[-3.16269207,40.6272354126],"type":"Point"}
}