{
  "type": "Feature",
  "properties": {
    "addr:full":"Calle de Roble, 3 Valladolid Valladolid 47009",
    "addr:housenumber":"3",
    "addr:postcode":"47009",
    "addr:street":"Calle De Roble",
    "iso:country":"ES",
    "sg:address":"Calle de Roble, 3",
    "sg:city":"Valladolid",
    "sg:orig_category":"Asesor\u00cda, Estudio Y Control Medioambiental",
    "sg:phone":"+34 983 37 10 90",
    "sg:postcode":"47009",
    "sg:province":"Valladolid",
    "wof:name":"Martinez Navarro Lidon",
    "wof:placetype":"venue"
},
  "geometry": {"coordinates":[-4.7305679321,41.6704139709],"type":"Point"}
}