{
  "type": "Feature",
  "properties": {
    "iso:country":"ES",
    "sg:address":"Calle de Pedro Teixeira, 8",
    "sg:city":"Madrid",
    "sg:orig_category":"Inform\u00c1tica (estudios, Servicios, Asesor\u00cda, Formaci\u00d3n)",
    "sg:phone":"+34 914 17 68 65",
    "sg:postcode":"28020",
    "sg:province":"Madrid",
    "sg:website":"www.stonesoft.com",
    "wof:name":"Stonesoft Espa\u00f1a S.a.",
    "wof:placetype":"venue"
},
  "geometry": {"coordinates":[-3.6941151619,40.4551086426],"type":"Point"}
}