{
  "type": "Feature",
  "properties": {
    "addr:full":"Calle de Mercado Chico, 80 Barraco \u00c1vila 05110",
    "addr:housenumber":"80",
    "addr:postcode":"05110",
    "addr:street":"Calle De Mercado Chico",
    "iso:country":"ES",
    "sg:address":"Calle de Mercado Chico, 80",
    "sg:city":"Barraco",
    "sg:orig_category":"Iglesia Cat\u00d3lica",
    "sg:phone":"+34 920 28 10 18",
    "sg:postcode":"05110",
    "sg:province":"\u00c1vila",
    "wof:name":"Parroquia De Nuestra Se\u00f1ora De La Asuncion",
    "wof:placetype":"venue"
},
  "geometry": {"coordinates":[-4.6423749924,40.4753456116],"type":"Point"}
}