{
  "type": "Feature",
  "properties": {
    "addr:full":"Calle de Garay Juan De, 29 Bilbao Vizcaya 48003",
    "addr:housenumber":"29",
    "addr:postcode":"48003",
    "addr:street":"Calle De Garay Juan De",
    "iso:country":"ES",
    "sg:address":"Calle de Garay Juan De, 29",
    "sg:city":"Bilbao",
    "sg:orig_category":"Pintura, Barniz, Productos Asimilables (fabricaci\u00d3n, Al Por Mayor)",
    "sg:phone":"+34 944 21 15 02",
    "sg:postcode":"48003",
    "sg:province":"Vizcaya",
    "wof:name":"Exel Industrial Equipos Y Extrusion S.a.",
    "wof:placetype":"venue"
},
  "geometry": {"coordinates":[-2.9340839386,43.2533607483],"type":"Point"}
}