{
  "type": "Feature",
  "properties": {
    "addr:full":"Sequia, 42 Palmera Valencia 46714",
    "addr:housenumber":"42",
    "addr:postcode":"46714",
    "addr:street":"Sequia",
    "iso:country":"ES",
    "sg:address":"Sequia, 42",
    "sg:city":"Palmera",
    "sg:orig_category":"Veh\u00cdculos De Ocasi\u00d3n",
    "sg:phone":"+34 962 89 30 87",
    "sg:postcode":"46714",
    "sg:province":"Valencia",
    "wof:name":"Palmotor Safor S.l.",
    "wof:placetype":"venue"
},
  "geometry": {"coordinates":[-0.1547189951,38.9409446716],"type":"Point"}
}