{
  "type": "Feature",
  "properties": {
    "addr:full":"Ctra Salas De Los Infantes, Km. 0004,5 Aranda Duero Burgos 09400",
    "addr:postcode":"09400",
    "addr:street":"Ctra Salas De Los Infantes Km. 0004,5 Aranda Duero",
    "iso:country":"ES",
    "sg:address":"Ctra Salas De Los Infantes, Km. 0004,5",
    "sg:city":"Aranda Duero",
    "sg:orig_category":"Equitaci\u00d3n Y Centros De H\u00cdpica",
    "sg:phone":"+34 947 56 11 34",
    "sg:postcode":"09400",
    "sg:province":"Burgos",
    "wof:name":"Mataranda S.l.",
    "wof:placetype":"venue"
},
  "geometry": {"coordinates":[-3.6889948845,41.6699256897],"type":"Point"}
}