{
  "type": "Feature",
  "properties": {
    "iso:country":"ES",
    "sg:address":"Pol Ind Los Vasalos, 35",
    "sg:city":"Onil",
    "sg:orig_category":"Fabricaci\u00d3n De Moldes Y Modelos",
    "sg:phone":"+34 966 55 76 72",
    "sg:postcode":"03430",
    "sg:province":"Alicante",
    "wof:name":"Novomolde S. L.",
    "wof:placetype":"venue"
},
  "geometry": {"coordinates":[-0.673289001,38.6250152588],"type":"Point"}
}