{
  "type": "Feature",
  "properties": {
    "addr:full":"Carrer de Jambrina, 9 Barcelona Barcelona 08027",
    "addr:housenumber":"9",
    "addr:postcode":"08027",
    "addr:street":"Carrer De Jambrina",
    "iso:country":"ES",
    "sg:address":"Carrer de Jambrina, 9",
    "sg:city":"Barcelona",
    "sg:orig_category":"Promotores Constructores",
    "sg:phone":"+34 933 40 63 28",
    "sg:postcode":"08027",
    "sg:province":"Barcelona",
    "wof:name":"Dexiga Construmat S.l.",
    "wof:placetype":"venue"
},
  "geometry": {"coordinates":[2.1883859634,41.4255371094],"type":"Point"}
}