{
  "type": "Feature",
  "properties": {
    "iso:country":"ES",
    "sg:address":"Calle de Cura Llinares, 14",
    "sg:city":"Altea Vella",
    "sg:orig_category":"Tintorer\u00cdas, Limpieza En Seco",
    "sg:phone":"+34 965 84 65 04",
    "sg:postcode":"03599",
    "sg:province":"Alicante",
    "wof:name":"Soler Martinez Diego",
    "wof:placetype":"venue"
},
  "geometry": {"coordinates":[-0.043407999,38.631942749],"type":"Point"}
}