{
  "type": "Feature",
  "properties": {
    "addr:full":"Carrer de Balmes, 1 Pineda Mar Barcelona 08397",
    "addr:housenumber":"1",
    "addr:postcode":"08397",
    "addr:street":"Carrer De Balmes;Barcelona",
    "iso:country":"ES",
    "sg:address":"Carrer de Balmes, 1",
    "sg:city":"Pineda Mar",
    "sg:orig_category":"Hoteles",
    "sg:phone":"+34 937 67 18 08",
    "sg:postcode":"08397",
    "sg:province":"Barcelona",
    "wof:name":"Hotel Brisamar Pineda S.a.",
    "wof:placetype":"venue"
},
  "geometry": {"coordinates":[2.6826798916,41.6266517639],"type":"Point"}
}