{
  "type": "Feature",
  "properties": {
    "iso:country":"ES",
    "sg:address":"Carrer de Almogavers, 229",
    "sg:city":"Barcelona",
    "sg:orig_category":"Estancos",
    "sg:phone":"+34 933 09 93 63",
    "sg:postcode":"08018",
    "sg:province":"Barcelona",
    "wof:name":"Antich Berche Manuel",
    "wof:placetype":"venue"
},
  "geometry": {"coordinates":[2.1971340179,41.4023971558],"type":"Point"}
}