{
  "type": "Feature",
  "properties": {
    "iso:country":"ES",
    "sg:address":"Ballena, S/n",
    "sg:city":"La Antilla",
    "sg:orig_category":"Molduras, Junquillos, Listones Y Molduras Perforadas",
    "sg:phone":"+34 959 48 63 37",
    "sg:postcode":"21449",
    "sg:province":"Huelva",
    "wof:name":"Hnos. Rosa Madrid S.c.",
    "wof:placetype":"venue"
},
  "geometry": {"coordinates":[-7.2178740501,37.2062454224],"type":"Point"}
}