{
  "type": "Feature",
  "properties": {
    "addr:full":"Calle de Arana, 37 Vitoria-gasteiz \u00c1lava 01002",
    "addr:housenumber":"37",
    "addr:postcode":"01002",
    "addr:street":"Calle De Arana",
    "iso:country":"ES",
    "sg:address":"Calle de Arana, 37",
    "sg:city":"Vitoria-gasteiz",
    "sg:orig_category":"Promotores Constructores",
    "sg:phone":"+34 945 27 53 13",
    "sg:postcode":"01002",
    "sg:province":"\u00c1lava",
    "wof:name":"Pan Garrido Jose",
    "wof:placetype":"venue"
},
  "geometry": {"coordinates":[-2.6616353989,42.8505172729],"type":"Point"}
}