{
  "type": "Feature",
  "properties": {
    "addr:full":"Calle de Manuel Arellano, S/n Sevilla Sevilla 41010",
    "addr:housenumber":"s / n",
    "addr:postcode":"41010",
    "addr:street":"Calle De Manuel Arellano",
    "iso:country":"ES",
    "sg:address":"Calle de Manuel Arellano, S/n",
    "sg:city":"Sevilla",
    "sg:orig_category":"Agencias Y Agentes Comerciales, Representantes",
    "sg:phone":"+34 954 33 65 27",
    "sg:postcode":"41010",
    "sg:province":"Sevilla",
    "wof:name":"Garcia Raposo Miguel Angel",
    "wof:placetype":"venue"
},
  "geometry": {"coordinates":[-6.0086817741,37.3867111206],"type":"Point"}
}