{
  "type": "Feature",
  "properties": {
    "addr:full":"Calle de Virgen De Valvanera, S/n Sevilla Sevilla 41018",
    "addr:housenumber":"s / n",
    "addr:postcode":"41018",
    "addr:street":"Calle De Virgen De Valvanera",
    "iso:country":"ES",
    "sg:address":"Calle de Virgen De Valvanera, S/n",
    "sg:city":"Sevilla",
    "sg:classifiers":[
        {
            "category":"Personal",
            "subcategory":"Barber",
            "type":"Services"
        }
    ],
    "sg:phone":"+34 954 57 50 13",
    "sg:postcode":"41018",
    "sg:province":"Sevilla",
    "sg:tags":[
        "caballeros",
        "de",
        "peluqueros"
    ],
    "wof:name":"Ceballos Salazar Fernando",
    "wof:placetype":"venue"
},
  "geometry": {"coordinates":[-5.9764790535,37.3863143921],"type":"Point"}
}