{
  "type": "Feature",
  "properties": {
    "iso:country":"ES",
    "sg:address":"Almda S Anton, 9",
    "sg:city":"Cartagena",
    "sg:orig_category":"Abogados",
    "sg:phone":"+34 968 50 67 15",
    "sg:postcode":"30205",
    "sg:province":"Murcia",
    "wof:name":"Lafuente Jimenez Matias",
    "wof:placetype":"venue"
},
  "geometry": {"coordinates":[-0.9923189878,37.6079368591],"type":"Point"}
}