{
  "type": "Feature",
  "properties": {
    "addr:full":"Avda Cieza (de), 59 Abaran Murcia 30550",
    "addr:housenumber":"59",
    "addr:postcode":"30550",
    "addr:street":"Avda Cieza De",
    "iso:country":"ES",
    "sg:address":"Avda Cieza (de), 59",
    "sg:city":"Abaran",
    "sg:orig_category":"Mec\u00c1nico Del Autom\u00d3vil",
    "sg:phone":"+34 968 77 00 24",
    "sg:postcode":"30550",
    "sg:province":"Murcia",
    "wof:name":"Garcia Villa Juan",
    "wof:placetype":"venue"
},
  "geometry": {"coordinates":[-1.3953950405,38.2076835632],"type":"Point"}
}