{
  "type": "Feature",
  "properties": {
    "addr:full":"Calle de Ramon Y Cajal, 14 Cuenca Cuenca 16004",
    "addr:housenumber":"14",
    "addr:postcode":"16004",
    "addr:street":"Calle De Ramon Y Cajal",
    "iso:country":"ES",
    "sg:address":"Calle de Ramon Y Cajal, 14",
    "sg:city":"Cuenca",
    "sg:orig_category":"Material Y Herramientas Agr\u00cdcolas",
    "sg:phone":"+34 969 22 96 14",
    "sg:postcode":"16004",
    "sg:province":"Cuenca",
    "wof:name":"Agrocuenca Forestal S.l.",
    "wof:placetype":"venue"
},
  "geometry": {"coordinates":[-2.1352615356,40.0700340271],"type":"Point"}
}