{
  "type": "Feature",
  "properties": {
    "addr:full":"Carrer de Doctor Reig, 40 Viladecans Barcelona 08840",
    "addr:housenumber":"40",
    "addr:postcode":"08840",
    "addr:street":"Carrer De Doctor Reig",
    "iso:country":"ES",
    "sg:address":"Carrer de Doctor Reig, 40",
    "sg:city":"Viladecans",
    "sg:orig_category":"Material Y Suministros Para Peluquer\u00cda",
    "sg:phone":"+34 936 58 78 04",
    "sg:postcode":"08840",
    "sg:province":"Barcelona",
    "sg:website":"www.rizos.es",
    "wof:name":"Salvador Langa Jose Antonio",
    "wof:placetype":"venue"
},
  "geometry": {"coordinates":[2.0144739151,41.3184127808],"type":"Point"}
}