{
  "type": "Feature",
  "properties": {
    "addr:full":"Psaj Marino Luis Cordoba Arce, 4 Cordoba C\u00f3rdoba 14011",
    "addr:housenumber":"4",
    "addr:postcode":"14011",
    "addr:street":"Arce;Co\u0301Rdoba",
    "iso:country":"ES",
    "sg:address":"Psaj Marino Luis Cordoba Arce, 4",
    "sg:city":"Cordoba",
    "sg:orig_category":"Loter\u00cda Y T\u00d3mbola",
    "sg:phone":"+34 957 46 38 91",
    "sg:postcode":"14011",
    "sg:province":"C\u00f3rdoba",
    "wof:name":"Cid Rubiano Juan",
    "wof:placetype":"venue"
},
  "geometry": {"coordinates":[-4.8054018021,37.8920440674],"type":"Point"}
}