{
  "type": "Feature",
  "properties": {
    "iso:country":"ES",
    "sg:address":"Av Madrid, 18",
    "sg:city":"Crevillent",
    "sg:orig_category":"Deportes Diversos",
    "sg:phone":"+34 965 40 11 04",
    "sg:postcode":"03330",
    "sg:province":"Alicante",
    "wof:name":"Creivllente Club De Billar",
    "wof:placetype":"venue"
},
  "geometry": {"coordinates":[-0.8095890284,38.2464981079],"type":"Point"}
}