{
  "type": "Feature",
  "properties": {
    "addr:full":"Ctra Villaba\u00d1ez, Km. 0002,0 Tudela Duero Valladolid 47320",
    "addr:postcode":"47320",
    "addr:street":"Ctra Villaban\u0303Ez Km. 0002,0",
    "iso:country":"ES",
    "sg:address":"Ctra Villaba\u00d1ez, Km. 0002,0",
    "sg:city":"Tudela Duero",
    "sg:orig_category":"Cooperativas Agr\u00cdcolas",
    "sg:phone":"+34 983 52 01 14",
    "sg:postcode":"47320",
    "sg:province":"Valladolid",
    "wof:name":"Cooperativa Agricola Comarcal Del Jaramiel",
    "wof:placetype":"venue"
},
  "geometry": {"coordinates":[-4.5823941231,41.5873565674],"type":"Point"}
}