{
  "type": "Feature",
  "properties": {
    "addr:full":"Avda Ricardo Carapeto Zambrano, 53 Badajoz Badajoz 06008",
    "addr:housenumber":"53",
    "addr:postcode":"06008",
    "addr:street":"Avda Ricardo Carapeto Zambrano",
    "iso:country":"ES",
    "sg:address":"Avda Ricardo Carapeto Zambrano, 53",
    "sg:city":"Badajoz",
    "sg:orig_category":"Plomeros",
    "sg:phone":"+34 924 24 38 52",
    "sg:postcode":"06008",
    "sg:province":"Badajoz",
    "wof:name":"Trujillo Martinez Andres",
    "wof:placetype":"venue"
},
  "geometry": {"coordinates":[-6.9516701698,38.8785324097],"type":"Point"}
}