{
  "type": "Feature",
  "properties": {
    "addr:full":"Pg Pere Iii, 31 Manresa Barcelona 08242",
    "addr:housenumber":"31",
    "addr:postcode":"08242",
    "addr:street":"Pg Pere Iii",
    "iso:country":"ES",
    "sg:address":"Pg Pere Iii, 31",
    "sg:city":"Manresa",
    "sg:orig_category":"Marroquiner\u00cda (confecci\u00d3n)",
    "sg:phone":"+34 938 72 05 25",
    "sg:postcode":"08242",
    "sg:province":"Barcelona",
    "wof:name":"Marroquineria Franquesa S.l.",
    "wof:placetype":"venue"
},
  "geometry": {"coordinates":[1.8233499527,41.7274398804],"type":"Point"}
}