{
  "type": "Feature",
  "properties": {
    "iso:country":"ES",
    "sg:address":"Carr Moll D'en Balleu, 6",
    "sg:city":"Port Selva",
    "sg:classifiers":[
        {
            "category":"Recreation",
            "type":"Entertainment"
        }
    ],
    "sg:phone":"+34 972 38 74 05",
    "sg:postcode":"17489",
    "sg:province":"Girona",
    "sg:tags":[
        "caza",
        "pr\u00c1ctica",
        "la",
        "de",
        "pesca",
        "y"
    ],
    "wof:name":"Cofradia De Pescadores De Puerto De La Selva",
    "wof:placetype":"venue"
},
  "geometry": {"coordinates":[3.1858310699,42.3232536316],"type":"Point"}
}