{
  "type": "Feature",
  "properties": {
    "iso:country":"ES",
    "sg:address":"Carrer de Josep Miret, 4",
    "sg:city":"Barcelona",
    "sg:orig_category":"Farmacias",
    "sg:phone":"+34 932 78 80 83",
    "sg:postcode":"08020",
    "sg:province":"Barcelona",
    "wof:name":"Salavert Girona Maria Del Carmen",
    "wof:placetype":"venue"
},
  "geometry": {"coordinates":[2.200633049,41.4212417603],"type":"Point"}
}