{
  "type": "Feature",
  "properties": {
    "addr:full":"Calle de Regueros, 15 Madrid Madrid 28004",
    "addr:housenumber":"15",
    "addr:postcode":"madrid;28004",
    "addr:street":"Calle De Regueros",
    "iso:country":"ES",
    "sg:address":"Calle de Regueros, 15",
    "sg:city":"Madrid",
    "sg:orig_category":"Ropa Para Se\u00d1oras (al Por Menor)",
    "sg:phone":"+34 913 10 66 76",
    "sg:postcode":"28004",
    "sg:province":"Madrid",
    "wof:name":"Nicase Quince S.l.",
    "wof:placetype":"venue"
},
  "geometry": {"coordinates":[-3.6962089539,40.4249801636],"type":"Point"}
}