{
  "type": "Feature",
  "properties": {
    "iso:country":"ES",
    "sg:address":"Plaz Maestro Jose Palmis, 1",
    "sg:city":"Campano",
    "sg:orig_category":"Centros De Educaci\u00d3n Especial",
    "sg:phone":"+34 968 52 27 74",
    "sg:postcode":"30202",
    "sg:province":"Murcia",
    "wof:name":"Colegio Nacional Asdrubal",
    "wof:placetype":"venue"
},
  "geometry": {"coordinates":[-1.1302499771,37.9829597473],"type":"Point"}
}