{
  "type": "Feature",
  "properties": {
    "addr:full":"Calle de Puerta De Valencia, 5 Albacete Albacete 02002",
    "addr:housenumber":"5",
    "addr:postcode":"02002",
    "addr:street":"Calle De Puerta De Valencia",
    "iso:country":"ES",
    "sg:address":"Calle de Puerta De Valencia, 5",
    "sg:city":"Albacete",
    "sg:orig_category":"Colchones (fabricaci\u00d3n, Al Por Mayor, Al Por Menor)",
    "sg:phone":"+34 967 24 18 80",
    "sg:postcode":"02002",
    "sg:province":"Albacete",
    "wof:name":"Diaz Montero Rodolfo",
    "wof:placetype":"venue"
},
  "geometry": {"coordinates":[-1.8492859602,38.9895973206],"type":"Point"}
}