{
  "type": "Feature",
  "properties": {
    "addr:full":"Avda R. Argentina, 11 Pozoblanco C\u00f3rdoba 14400",
    "addr:housenumber":"11",
    "addr:postcode":"14400",
    "addr:street":"Avda R. Argentina",
    "iso:country":"ES",
    "sg:address":"Avda R. Argentina, 11",
    "sg:city":"Pozoblanco",
    "sg:orig_category":"Pod\u00d3logos: Pedicuros",
    "sg:phone":"+34 957 13 11 86",
    "sg:postcode":"14400",
    "sg:province":"C\u00f3rdoba",
    "wof:name":"Due\u00f1as Moreno Juan",
    "wof:placetype":"venue"
},
  "geometry": {"coordinates":[-4.8492288589,38.3810462952],"type":"Point"}
}