{
  "type": "Feature",
  "properties": {
    "addr:full":"Avda Valladolid, 96 Tudela Duero Valladolid 47320",
    "addr:housenumber":"96;duero",
    "addr:postcode":"47320",
    "addr:street":"Avda Valladolid",
    "iso:country":"ES",
    "sg:address":"Avda Valladolid, 96",
    "sg:city":"Tudela Duero",
    "sg:orig_category":"Florister\u00cdas",
    "sg:phone":"+34 983 52 03 14",
    "sg:postcode":"47320",
    "sg:province":"Valladolid",
    "wof:name":"Tudecal Multiservicios C.b.",
    "wof:placetype":"venue"
},
  "geometry": {"coordinates":[-4.5843391418,41.5873718262],"type":"Point"}
}