{
  "type": "Feature",
  "properties": {
    "iso:country":"ES",
    "sg:address":"Calle de Mariano Baselga, 8",
    "sg:city":"Zaragoza",
    "sg:orig_category":"Muebles, Minoristas",
    "sg:phone":"+34 976 51 19 96",
    "sg:postcode":"50015",
    "sg:province":"Zaragoza",
    "wof:name":"Almudi Alcober Lorenzo",
    "wof:placetype":"venue"
},
  "geometry": {"coordinates":[-0.877107501,41.6609611511],"type":"Point"}
}