{
  "type": "Feature",
  "properties": {
    "addr:full":"Av Doctor Furest, 37 Caldes Malavella Girona 17455",
    "addr:housenumber":"37",
    "addr:postcode":"17455",
    "addr:street":"Av Doctor Furest",
    "iso:country":"ES",
    "sg:address":"Av Doctor Furest, 37",
    "sg:city":"Caldes Malavella",
    "sg:orig_category":"Mec\u00c1nico Del Autom\u00d3vil",
    "sg:phone":"+34 972 47 02 23",
    "sg:postcode":"17455",
    "sg:province":"Girona",
    "wof:name":"Germans Genoher C.b.",
    "wof:placetype":"venue"
},
  "geometry": {"coordinates":[2.8071229458,41.8371734619],"type":"Point"}
}