{
  "type": "Feature",
  "properties": {
    "addr:full":"Carrer de Casp, 146 Barcelona Barcelona 08013",
    "addr:housenumber":"146",
    "addr:postcode":"08013",
    "addr:street":"Carrer De Casp",
    "iso:country":"ES",
    "sg:address":"Carrer de Casp, 146",
    "sg:city":"Barcelona",
    "sg:orig_category":"Farmacias",
    "sg:phone":"+34 932 65 45 35",
    "sg:postcode":"08013",
    "sg:province":"Barcelona",
    "wof:name":"Cercavins Font Casimiro",
    "wof:placetype":"venue"
},
  "geometry": {"coordinates":[2.1799330711,41.3961105347],"type":"Point"}
}