{
  "type": "Feature",
  "properties": {
    "addr:full":"Calle de Zaida, 2 Granada Granada 18004",
    "addr:housenumber":"2",
    "addr:postcode":"18004",
    "addr:street":"Calle De Zaida",
    "iso:country":"ES",
    "sg:address":"Calle de Zaida, 2",
    "sg:city":"Granada",
    "sg:orig_category":"Muebles Y Accesorios Para Cocinas Y Cuartos De Ba\u00d1o (al Por Menor)",
    "sg:phone":"+34 958 52 03 22",
    "sg:postcode":"18004",
    "sg:province":"Granada",
    "wof:name":"Garcia Pavon Jose",
    "wof:placetype":"venue"
},
  "geometry": {"coordinates":[-3.6037991047,37.1670684814],"type":"Point"}
}