{
  "type": "Feature",
  "properties": {
    "iso:country":"ES",
    "sg:address":"Rua Rois De La Pe\u00d1a, S/n",
    "sg:city":"Fonsagrada",
    "sg:orig_category":"Electricidad: Instaladores",
    "sg:phone":"+34 982 34 02 88",
    "sg:postcode":"27100",
    "sg:province":"Lugo",
    "wof:name":"Castro Geunde Balbino",
    "wof:placetype":"venue"
},
  "geometry": {"coordinates":[-7.0673189163,43.125995636],"type":"Point"}
}