{
  "type": "Feature",
  "properties": {
    "addr:full":"Pl Dr Ortiz De Landazuri, 18 Iru\u00f1a Navarra 31012",
    "addr:housenumber":"18",
    "addr:postcode":"31012",
    "addr:street":"Pl Dr Ortiz De Landazuri",
    "iso:country":"ES",
    "sg:address":"Pl Dr Ortiz De Landazuri, 18",
    "sg:city":"Iru\u00f1a",
    "sg:orig_category":"Farmacias",
    "sg:phone":"+34 948 25 17 28",
    "sg:postcode":"31012",
    "sg:province":"Navarra",
    "wof:name":"Muruzabal Ardanaz Beatriz",
    "wof:placetype":"venue"
},
  "geometry": {"coordinates":[-1.6720689535,42.8199691772],"type":"Point"}
}