{
  "type": "Feature",
  "properties": {
    "iso:country":"ES",
    "sg:address":"Calle de Alonso Cano, 4",
    "sg:city":"Estepona",
    "sg:orig_category":"Promotores Constructores",
    "sg:phone":"+34 952 80 33 06",
    "sg:postcode":"29680",
    "sg:province":"M\u00e1laga",
    "wof:name":"Ferralla Estepona S.l.",
    "wof:placetype":"venue"
},
  "geometry": {"coordinates":[-5.1681880951,36.4315605164],"type":"Point"}
}