{
  "type": "Feature",
  "properties": {
    "iso:country":"ES",
    "sg:address":"C/ Circumval.lacio Baixa, 61",
    "sg:city":"Cerdanyola Valles",
    "sg:orig_category":"Fabricaci\u00d3n De Transformadores, De M\u00c1quinas Giratorias De Peque\u00d1a Y Media Potencia",
    "sg:phone":"+34 936 91 27 01",
    "sg:postcode":"08290",
    "sg:province":"Barcelona",
    "wof:name":"Llamazares Ania Maria Isabel",
    "wof:placetype":"venue"
},
  "geometry": {"coordinates":[2.1391310692,41.496887207],"type":"Point"}
}