{
  "type": "Feature",
  "properties": {
    "addr:full":"Avda Inventor Pedro Cawley, 14 Poligono Industrial Salinas De San Jose C\u00e1diz 11500",
    "addr:housenumber":"14",
    "addr:postcode":"11500",
    "addr:street":"Avda Inventor Pedro Cawley;Industrial;Ca\u0301Diz",
    "iso:country":"ES",
    "sg:address":"Avda Inventor Pedro Cawley, 14",
    "sg:city":"Poligono Industrial Salinas De San Jose",
    "sg:orig_category":"Contenedores (mercanc\u00cdas)",
    "sg:phone":"+34 956 85 16 41",
    "sg:postcode":"11500",
    "sg:province":"C\u00e1diz",
    "wof:name":"Sociedad Cooperativa Andaluza De Transportes Cotrareal",
    "wof:placetype":"venue"
},
  "geometry": {"coordinates":[-6.2197542191,36.6056632996],"type":"Point"}
}