{
  "type": "Feature",
  "properties": {
    "addr:full":"Via Emilio Ortu\u00d1o, 5 Benidorm Alicante 03500",
    "addr:housenumber":"5",
    "addr:postcode":"03500",
    "addr:street":"Via Emilio Ortun\u0303O",
    "iso:country":"ES",
    "sg:address":"Via Emilio Ortu\u00d1o, 5",
    "sg:city":"Benidorm",
    "sg:orig_category":"M\u00c9dicos: Estomatolog\u00cda",
    "sg:phone":"+34 966 80 68 00",
    "sg:postcode":"03500",
    "sg:province":"Alicante",
    "wof:name":"Ferrer Azcona Yolanda",
    "wof:placetype":"venue"
},
  "geometry": {"coordinates":[-0.1275379956,38.5379600525],"type":"Point"}
}