{
  "type": "Feature",
  "properties": {
    "addr:full":"Calle de Tres, 2 Madrid Madrid 28022",
    "addr:housenumber":"2",
    "addr:postcode":"28022",
    "addr:street":"Calle De Tres",
    "iso:country":"ES",
    "sg:address":"Calle de Tres, 2",
    "sg:city":"Madrid",
    "sg:orig_category":"Iglesia Cat\u00d3lica",
    "sg:phone":"+34 917 41 07 73",
    "sg:postcode":"28022",
    "sg:province":"Madrid",
    "wof:name":"Parroquia San Cristobal",
    "wof:placetype":"venue"
},
  "geometry": {"coordinates":[-3.5960481167,40.4490432739],"type":"Point"}
}