{
  "type": "Feature",
  "properties": {
    "iso:country":"ES",
    "sg:address":"Avda Palencia, 127",
    "sg:city":"Campuzano",
    "sg:orig_category":"Loter\u00cda Y T\u00d3mbola",
    "sg:phone":"+34 942 89 80 97",
    "sg:postcode":"39300",
    "sg:province":"Cantabria",
    "wof:name":"Barquin Rodriguez Maria Cristina",
    "wof:placetype":"venue"
},
  "geometry": {"coordinates":[-4.0520391464,43.34897995],"type":"Point"}
}