{
  "type": "Feature",
  "properties": {
    "iso:country":"ES",
    "sg:address":"Calle de Amos De Escalante, 4",
    "sg:city":"Santander",
    "sg:orig_category":"Procuradores",
    "sg:phone":"+34 942 31 32 40",
    "sg:postcode":"39002",
    "sg:province":"Cantabria",
    "wof:name":"Vara Garcia Yolanda",
    "wof:placetype":"venue"
},
  "geometry": {"coordinates":[-3.8106911182,43.4621391296],"type":"Point"}
}