{
  "type": "Feature",
  "properties": {
    "addr:full":"Pase Imperial, 6 Madrid Madrid 28005",
    "addr:housenumber":"6",
    "addr:postcode":"28005",
    "iso:country":"ES",
    "sg:address":"Pase Imperial, 6",
    "sg:city":"Madrid",
    "sg:orig_category":"Equipo De Refrigeraci\u00d3n Industrial",
    "sg:phone":"+34 913 54 62 27",
    "sg:postcode":"28005",
    "sg:province":"Madrid",
    "wof:name":"Comunitel Global S A",
    "wof:placetype":"venue"
},
  "geometry": {"coordinates":[-3.7180740833,40.4099731445],"type":"Point"}
}