{
  "type": "Feature",
  "properties": {
    "addr:full":"Pl Catalunya, 7 Cambrils Tarragona 43850",
    "addr:housenumber":"7",
    "addr:postcode":"43850",
    "addr:street":"Pl Catalunya",
    "iso:country":"ES",
    "sg:address":"Pl Catalunya, 7",
    "sg:city":"Cambrils",
    "sg:orig_category":"Art\u00cdculos De Regalo (al Por Menor)",
    "sg:phone":"+34 977 79 42 88",
    "sg:postcode":"43850",
    "sg:province":"Tarragona",
    "sg:website":"www.thefactory.com",
    "wof:name":"Cetusa 1020 S.l.",
    "wof:placetype":"venue"
},
  "geometry": {"coordinates":[1.0595730543,41.0655021667],"type":"Point"}
}