{
  "type": "Feature",
  "properties": {
    "addr:full":"Calle de Nardo, 22 Algeciras C\u00e1diz 11204",
    "addr:housenumber":"22;ca\u0301diz",
    "addr:postcode":"11204",
    "addr:street":"Calle De Nardo",
    "iso:country":"ES",
    "sg:address":"Calle de Nardo, 22",
    "sg:city":"Algeciras",
    "sg:orig_category":"Pescader\u00cdas (al Por Menor)",
    "sg:phone":"+34 956 66 63 73",
    "sg:postcode":"11204",
    "sg:province":"C\u00e1diz",
    "wof:name":"Garcia Gil Francisco Javier",
    "wof:placetype":"venue"
},
  "geometry": {"coordinates":[-5.4626708031,36.1479873657],"type":"Point"}
}