{
  "type": "Feature",
  "properties": {
    "iso:country":"ES",
    "sg:address":"Plaz Conservatorio, 8",
    "sg:city":"Coru\u00d1a",
    "sg:orig_category":"Librer\u00cdas",
    "sg:phone":"+34 981 25 75 93",
    "sg:postcode":"15011",
    "sg:province":"La Coru\u00f1a",
    "wof:name":"Ramos Moreira Jose",
    "wof:placetype":"venue"
},
  "geometry": {"coordinates":[-8.4410495758,43.3664398193],"type":"Point"}
}