{
  "type": "Feature",
  "properties": {
    "iso:country":"ES",
    "sg:address":"Calle de Alcalde Maximo Gonzalez, 2",
    "sg:city":"Tegueste Casco",
    "sg:orig_category":"Mec\u00c1nico Del Autom\u00d3vil",
    "sg:phone":"+34 922 54 46 06",
    "sg:postcode":"38280",
    "sg:province":"Santa Cruz De Tenerife",
    "wof:name":"Galvan Baez Aurelio",
    "wof:placetype":"venue"
},
  "geometry": {"coordinates":[-16.2548561096,28.4698104858],"type":"Point"}
}