{
  "type": "Feature",
  "properties": {
    "iso:country":"ES",
    "sg:address":"Calle de Mercedes (las), 31",
    "sg:city":"Arenas -areeta",
    "sg:orig_category":"Empresarios",
    "sg:phone":"+34 944 63 35 93",
    "sg:postcode":"48930",
    "sg:province":"Vizcaya",
    "wof:name":"Del Rio Grandes German",
    "wof:placetype":"venue"
},
  "geometry": {"coordinates":[-3.0124020576,43.3276100159],"type":"Point"}
}