{
  "type": "Feature",
  "properties": {
    "addr:full":"Trva Lopez Corton, 3 Cedeira La Coru\u00f1a 15350",
    "addr:housenumber":"3",
    "addr:postcode":"15350",
    "addr:street":"Trva Lopez Corton;La Corun\u0303A",
    "iso:country":"ES",
    "sg:address":"Trva Lopez Corton, 3",
    "sg:city":"Cedeira",
    "sg:orig_category":"Ense\u00d1anza Secundaria: Colegios Y Escuelas Privadas",
    "sg:phone":"+34 981 48 26 25",
    "sg:postcode":"15350",
    "sg:province":"La Coru\u00f1a",
    "wof:name":"I.e.s. Punta Candieira",
    "wof:placetype":"venue"
},
  "geometry": {"coordinates":[-8.052989006,43.6609916687],"type":"Point"}
}