{
  "type": "Feature",
  "properties": {
    "addr:full":"Calle de Prosperidad, 14 S. Jose Valle C\u00e1diz 11580",
    "addr:housenumber":"14",
    "addr:postcode":"11580",
    "addr:street":"Calle De Prosperidad;S. Jose Valle Ca\u0301Diz",
    "iso:country":"ES",
    "sg:address":"Calle de Prosperidad, 14",
    "sg:city":"S. Jose Valle",
    "sg:orig_category":"Estancos",
    "sg:phone":"+34 956 16 06 38",
    "sg:postcode":"11580",
    "sg:province":"C\u00e1diz",
    "wof:name":"Rebollo Erdosain Daniel Jesus",
    "wof:placetype":"venue"
},
  "geometry": {"coordinates":[-5.7985749245,36.6065635681],"type":"Point"}
}