{
  "type": "Feature",
  "properties": {
    "addr:full":"Carrer de Alt De Gironella, 3 Barcelona Barcelona 08017",
    "addr:housenumber":"3",
    "addr:postcode":"08017",
    "addr:street":"Carrer De Alt De Gironella",
    "iso:country":"ES",
    "sg:address":"Carrer de Alt De Gironella, 3",
    "sg:city":"Barcelona",
    "sg:orig_category":"Peluqueros: De Se\u00d1oras",
    "sg:phone":"+34 932 80 63 87",
    "sg:postcode":"08017",
    "sg:province":"Barcelona",
    "wof:name":"Soler Fernandez Leonor",
    "wof:placetype":"venue"
},
  "geometry": {"coordinates":[2.1295011044,41.3945884705],"type":"Point"}
}