{
  "type": "Feature",
  "properties": {
    "addr:full":"Carr Bisbe Torres, 9 Lleida Lleida 25002",
    "addr:housenumber":"9",
    "addr:postcode":"25002",
    "addr:street":"Carr Bisbe Torres",
    "iso:country":"ES",
    "sg:address":"Carr Bisbe Torres, 9",
    "sg:city":"Lleida",
    "sg:orig_category":"Florister\u00cdas",
    "sg:phone":"+34 973 26 59 67",
    "sg:postcode":"25002",
    "sg:province":"Lleida",
    "wof:name":"Bala\u00f1a Brugulat Natividad",
    "wof:placetype":"venue"
},
  "geometry": {"coordinates":[0.6204096079,41.6123504639],"type":"Point"}
}