{
  "type": "Feature",
  "properties": {
    "addr:full":"Calle de Hellin, 1 Almansa Albacete 02640",
    "addr:housenumber":"1",
    "addr:postcode":"02640",
    "addr:street":"Calle De Hellin",
    "iso:country":"ES",
    "sg:address":"Calle de Hellin, 1",
    "sg:city":"Almansa",
    "sg:orig_category":"Centros De Educaci\u00d3n Especial",
    "sg:phone":"+34 967 31 04 23",
    "sg:postcode":"02640",
    "sg:province":"Albacete",
    "wof:name":"Centro Publico De Educacion Permanente De Adultos",
    "wof:placetype":"venue"
},
  "geometry": {"coordinates":[-1.0859190226,38.8597373962],"type":"Point"}
}