{
  "type": "Feature",
  "properties": {
    "iso:country":"ES",
    "sg:address":"Calle de Pino, 12",
    "sg:city":"Alacant",
    "sg:orig_category":"Rejas Met\u00c1licas",
    "sg:phone":"+34 965 11 49 14",
    "sg:postcode":"03006",
    "sg:province":"Alicante",
    "wof:name":"Huertas Civantos Sandra",
    "wof:placetype":"venue"
},
  "geometry": {"coordinates":[-0.524740994,38.3517799377],"type":"Point"}
}