{
  "type": "Feature",
  "properties": {
    "addr:full":"Avda Luis Vives, S/n Elche Sierra Albacete 02430",
    "addr:housenumber":"s / n",
    "addr:postcode":"02430",
    "addr:street":"Avda Luis Vives;Sierra",
    "iso:country":"ES",
    "sg:address":"Avda Luis Vives, S/n",
    "sg:city":"Elche Sierra",
    "sg:orig_category":"Ense\u00d1anza Secundaria: Colegios Y Escuelas Privadas",
    "sg:phone":"+34 967 41 00 73",
    "sg:postcode":"02430",
    "sg:province":"Albacete",
    "wof:name":"Ministerio De Educacion Y Cultura-i.e.s.elche De La Sierra",
    "wof:placetype":"venue"
},
  "geometry": {"coordinates":[-2.0497999191,38.4541435242],"type":"Point"}
}