{
  "type": "Feature",
  "properties": {
    "iso:country":"ES",
    "sg:address":"Calle de San Juan Bosco, 36",
    "sg:city":"Armunia",
    "sg:orig_category":"Tapicer\u00cdas",
    "sg:phone":"+34 987 84 97 20",
    "sg:postcode":"24009",
    "sg:province":"Le\u00f3n",
    "sg:website":"www.tsoto.es",
    "wof:name":"Tapicerias Soto S. L.",
    "wof:placetype":"venue"
},
  "geometry": {"coordinates":[-5.5865879059,42.5799293518],"type":"Point"}
}