{
  "type": "Feature",
  "properties": {
    "addr:full":"Ctra Rellinars, 63 Terrassa Barcelona 08225",
    "addr:housenumber":"63",
    "addr:postcode":"08225",
    "addr:street":"Ctra Rellinars",
    "iso:country":"ES",
    "sg:address":"Ctra Rellinars, 63",
    "sg:city":"Terrassa",
    "sg:orig_category":"Comerciantes Al Por Mayor De Vinos, Licores Y Alcoholes",
    "sg:phone":"+34 937 80 97 25",
    "sg:postcode":"08225",
    "sg:province":"Barcelona",
    "wof:name":"Izaola Aguirre Arantza",
    "wof:placetype":"venue"
},
  "geometry": {"coordinates":[2.0091700554,41.5718002319],"type":"Point"}
}