{
  "type": "Feature",
  "properties": {
    "addr:full":"Carrer de Major, 43 Montmelo Barcelona 08160",
    "addr:housenumber":"43",
    "addr:postcode":"08160",
    "addr:street":"Carrer De Major",
    "iso:country":"ES",
    "sg:address":"Carrer de Major, 43",
    "sg:city":"Montmelo",
    "sg:orig_category":"Librer\u00cdas",
    "sg:phone":"+34 935 68 25 36",
    "sg:postcode":"08160",
    "sg:province":"Barcelona",
    "wof:name":"Libreria Guasch S.c.p.",
    "wof:placetype":"venue"
},
  "geometry": {"coordinates":[2.2468459606,41.550983429],"type":"Point"}
}