{
  "type": "Feature",
  "properties": {
    "addr:full":"Carrer de Floridablanca, 102 Barcelona Barcelona 08015",
    "addr:housenumber":"102",
    "addr:postcode":"08015",
    "addr:street":"Carrer De Floridablanca",
    "iso:country":"ES",
    "sg:address":"Carrer de Floridablanca, 102",
    "sg:city":"Barcelona",
    "sg:orig_category":"Ropa Para Se\u00d1oras (al Por Menor)",
    "sg:phone":"+34 934 23 47 90",
    "sg:postcode":"08015",
    "sg:province":"Barcelona",
    "wof:name":"Flaque Gri Montserrat",
    "wof:placetype":"venue"
},
  "geometry": {"coordinates":[2.1601250172,41.3795051575],"type":"Point"}
}