{
  "type": "Feature",
  "properties": {
    "addr:full":"Carrer de Parcerisses, 13 Barcelona Barcelona 08014",
    "addr:housenumber":"13",
    "addr:postcode":"08014",
    "addr:street":"Carrer De Parcerisses",
    "iso:country":"ES",
    "sg:address":"Carrer de Parcerisses, 13",
    "sg:city":"Barcelona",
    "sg:orig_category":"Desinfecci\u00d3n, Desinsectaci\u00d3n, Desratizaci\u00d3n",
    "sg:phone":"+34 933 31 32 09",
    "sg:postcode":"08014",
    "sg:province":"Barcelona",
    "wof:name":"Hicopla S.l.",
    "wof:placetype":"venue"
},
  "geometry": {"coordinates":[2.1343729496,41.368434906],"type":"Point"}
}