{
  "type": "Feature",
  "properties": {
    "iso:country":"ES",
    "sg:address":"Pol Ind El Portal, S/n",
    "sg:city":"Jerez",
    "sg:orig_category":"Patatas (al Por Mayor)",
    "sg:phone":"+34 956 14 36 52",
    "sg:postcode":"11408",
    "sg:province":"C\u00e1diz",
    "wof:name":"Avicola Andaluza S.l",
    "wof:placetype":"venue"
},
  "geometry": {"coordinates":[-6.1633043289,36.6765556335],"type":"Point"}
}