{
  "type": "Feature",
  "properties": {
    "addr:full":"Calle de Monta\u00d1es, 86 Matanza De Acentejo Santa Cruz De Tenerife 38370",
    "addr:housenumber":"86",
    "addr:postcode":"38370",
    "addr:street":"Calle De Montan\u0303Es",
    "iso:country":"ES",
    "sg:address":"Calle de Monta\u00d1es, 86",
    "sg:city":"Matanza De Acentejo",
    "sg:orig_category":"Alimentaci\u00d3n General (al Por Menor)",
    "sg:phone":"+34 922 57 72 17",
    "sg:postcode":"38370",
    "sg:province":"Santa Cruz De Tenerife",
    "wof:name":"Perez Afonso Julio",
    "wof:placetype":"venue"
},
  "geometry": {"coordinates":[-16.4427833557,28.4475135803],"type":"Point"}
}