{
  "type": "Feature",
  "properties": {
    "addr:full":"Carr Sebastia Trullol, 9 Figueres Girona 17600",
    "addr:housenumber":"9",
    "addr:postcode":"17600",
    "addr:street":"Carr Sebastia Trullol",
    "iso:country":"ES",
    "sg:address":"Carr Sebastia Trullol, 9",
    "sg:city":"Figueres",
    "sg:orig_category":"Carnicer\u00cdas, Carnicer\u00cdas",
    "sg:phone":"+34 972 67 04 90",
    "sg:postcode":"17600",
    "sg:province":"Girona",
    "wof:name":"Alech Pallarol Maria Teresa",
    "wof:placetype":"venue"
},
  "geometry": {"coordinates":[2.9616684914,42.2553253174],"type":"Point"}
}