{
  "type": "Feature",
  "properties": {
    "iso:country":"ES",
    "sg:address":"Ctra Tarrega (de), 35",
    "sg:city":"Agramunt",
    "sg:orig_category":"Mec\u00c1nico Del Autom\u00d3vil",
    "sg:phone":"+34 973 39 24 33",
    "sg:postcode":"25310",
    "sg:province":"Lleida",
    "wof:name":"Castro Motor Serveis Atomocio S.l.l.",
    "wof:placetype":"venue"
},
  "geometry": {"coordinates":[1.0939610004,41.7837028503],"type":"Point"}
}