{
  "type": "Feature",
  "properties": {
    "iso:country":"ES",
    "sg:address":"Rond Frederic Mistral, 7",
    "sg:city":"Mataro",
    "sg:orig_category":"Ense\u00d1anza Secundaria: Colegios Y Escuelas Privadas",
    "sg:phone":"+34 937 41 42 03",
    "sg:postcode":"08304",
    "sg:province":"Barcelona",
    "wof:name":"Ies Thos I Codina",
    "wof:placetype":"venue"
},
  "geometry": {"coordinates":[2.4384810925,41.549949646],"type":"Point"}
}