{
  "type": "Feature",
  "properties": {
    "addr:full":"Pg Colon, De, 36 Casco Urbano Valencia 46760",
    "addr:housenumber":"36",
    "addr:postcode":"46760",
    "addr:street":"Pg Colon De",
    "iso:country":"ES",
    "sg:address":"Pg Colon, De, 36",
    "sg:city":"Casco Urbano",
    "sg:orig_category":"Promotores Constructores",
    "sg:phone":"+34 962 83 64 19",
    "sg:postcode":"46760",
    "sg:province":"Valencia",
    "wof:name":"Jose Ciscar Clar S.l.",
    "wof:placetype":"venue"
},
  "geometry": {"coordinates":[-0.2594090104,39.0749702454],"type":"Point"}
}