{
  "type": "Feature",
  "properties": {
    "addr:full":"Calle de Guadalajara, 19 Parla Madrid 28980",
    "addr:housenumber":"19",
    "addr:postcode":"28980",
    "addr:street":"Calle De Guadalajara",
    "iso:country":"ES",
    "sg:address":"Calle de Guadalajara, 19",
    "sg:city":"Parla",
    "sg:orig_category":"Librer\u00cdas",
    "sg:phone":"+34 916 99 26 13",
    "sg:postcode":"28980",
    "sg:province":"Madrid",
    "wof:name":"Vidal Ja\u00f1es Aurea",
    "wof:placetype":"venue"
},
  "geometry": {"coordinates":[-3.7667880058,40.2431373596],"type":"Point"}
}