{
  "type": "Feature",
  "properties": {
    "iso:country":"ES",
    "sg:address":"Pase Constitucion De (la), 61",
    "sg:city":"Arnedo",
    "sg:orig_category":"Perfumer\u00cda, Art\u00cdculos De Ba\u00d1o (fabricaci\u00d3n, Al Por Mayor)",
    "sg:phone":"+34 941 38 37 53",
    "sg:postcode":"26580",
    "sg:province":"La Rioja",
    "wof:name":"Frescor S.l.",
    "wof:placetype":"venue"
},
  "geometry": {"coordinates":[-2.1026320457,42.226020813],"type":"Point"}
}