{
  "type": "Feature",
  "properties": {
    "iso:country":"ES",
    "sg:address":"Carrer de Mina, 40",
    "sg:city":"Hospitalet Llobregat",
    "sg:orig_category":"Florister\u00cdas",
    "sg:phone":"+34 934 37 04 87",
    "sg:postcode":"08906",
    "sg:province":"Barcelona",
    "wof:name":"Lopez Machado Maria Jose",
    "wof:placetype":"venue"
},
  "geometry": {"coordinates":[2.099364996,41.3707695007],"type":"Point"}
}