{
  "type": "Feature",
  "properties": {
    "addr:full":"Avda Compostela, 14 Padron La Coru\u00f1a 15900",
    "addr:housenumber":"14",
    "addr:postcode":"15900",
    "addr:street":"Avda Compostela;Padron La Corun\u0303A",
    "iso:country":"ES",
    "sg:address":"Avda Compostela, 14",
    "sg:city":"Padron",
    "sg:orig_category":"Material Hidr\u00c1ulico",
    "sg:phone":"+34 981 81 08 25",
    "sg:postcode":"15900",
    "sg:province":"La Coru\u00f1a",
    "wof:name":"Montajes Costamar S.l.",
    "wof:placetype":"venue"
},
  "geometry": {"coordinates":[-8.6590690613,42.7395629883],"type":"Point"}
}