{
  "type": "Feature",
  "properties": {
    "iso:country":"ES",
    "sg:address":"Rua Progreso (do), 31",
    "sg:city":"Lugo",
    "sg:orig_category":"Muebles, Minoristas",
    "sg:phone":"+34 982 25 38 93",
    "sg:postcode":"27001",
    "sg:province":"Lugo",
    "sg:website":"www.ka-international.com",
    "wof:name":"Abelleira Pereira Maria Jesus",
    "wof:placetype":"venue"
},
  "geometry": {"coordinates":[-7.555386,43.01165],"type":"Point"}
}