{
  "type": "Feature",
  "properties": {
    "addr:full":"Plaz Espa\u00d1a, 15 Llerena Badajoz 06900",
    "addr:housenumber":"15",
    "addr:postcode":"06900",
    "addr:street":"Plaz Espan\u0303A",
    "iso:country":"ES",
    "sg:address":"Plaz Espa\u00d1a, 15",
    "sg:city":"Llerena",
    "sg:orig_category":"Art\u00cdculos De Regalo (al Por Menor)",
    "sg:phone":"+34 924 87 01 42",
    "sg:postcode":"06900",
    "sg:province":"Badajoz",
    "wof:name":"Rabermar S. A.",
    "wof:placetype":"venue"
},
  "geometry": {"coordinates":[-6.0153741837,38.2413711548],"type":"Point"}
}