{
  "type": "Feature",
  "properties": {
    "addr:full":"Calle de San Bartolome, 11 Yeste Albacete 02480",
    "addr:housenumber":"11",
    "addr:postcode":"02480",
    "addr:street":"Calle De San Bartolome",
    "iso:country":"ES",
    "sg:address":"Calle de San Bartolome, 11",
    "sg:city":"Yeste",
    "sg:orig_category":"Ense\u00d1anza, Formaci\u00d3n Profesional: Aprendizaje",
    "sg:phone":"+34 967 43 14 42",
    "sg:postcode":"02480",
    "sg:province":"Albacete",
    "wof:name":"Junta De Comunidades Castilla-la Mancha",
    "wof:placetype":"venue"
},
  "geometry": {"coordinates":[-2.3156499863,38.3688278198],"type":"Point"}
}