{
  "type": "Feature",
  "properties": {
    "iso:country":"ES",
    "sg:address":"Av Torrent Gornal, 86",
    "sg:city":"Hospitalet Llobregat",
    "sg:orig_category":"Copas, Insignias, Trofeos",
    "sg:phone":"+34 933 34 20 77",
    "sg:postcode":"08904",
    "sg:province":"Barcelona",
    "wof:name":"Escobar Maqueda Pedro",
    "wof:placetype":"venue"
},
  "geometry": {"coordinates":[2.1131799221,41.3727493286],"type":"Point"}
}