{
  "type": "Feature",
  "properties": {
    "iso:country":"ES",
    "sg:address":"Calle de Servando Gutierrez, 1",
    "sg:city":"S. Fernando",
    "sg:orig_category":"Carga Y Descarga",
    "sg:phone":"+34 956 88 27 22",
    "sg:postcode":"11100",
    "sg:province":"C\u00e1diz",
    "wof:name":"Aparicio Segundo Jose",
    "wof:placetype":"venue"
},
  "geometry": {"coordinates":[-6.1972794533,36.4717941284],"type":"Point"}
}