{
  "type": "Feature",
  "properties": {
    "addr:full":"Carrer de Francesc Macia, S/n Mora Nova Tarragona 43770",
    "addr:housenumber":"s / n",
    "addr:postcode":"43770",
    "addr:street":"Carrer De Francesc Macia",
    "iso:country":"ES",
    "sg:address":"Carrer de Francesc Macia, S/n",
    "sg:city":"Mora Nova",
    "sg:orig_category":"Ense\u00d1anza, Formaci\u00d3n Profesional: Aprendizaje",
    "sg:phone":"+34 977 40 14 52",
    "sg:postcode":"43770",
    "sg:province":"Tarragona",
    "wof:name":"Centre De Telecomunicaciones De Catalunya",
    "wof:placetype":"venue"
},
  "geometry": {"coordinates":[0.6507350206,41.0978088379],"type":"Point"}
}