{
  "type": "Feature",
  "properties": {
    "iso:country":"ES",
    "sg:address":"Pase San Antonio, 6",
    "sg:city":"Salamanca",
    "sg:orig_category":"\u00d3ptica: Instrumentos (fabricaci\u00d3n)",
    "sg:phone":"+34 923 26 85 21",
    "sg:postcode":"37003",
    "sg:province":"Salamanca",
    "wof:name":"Ana Maria Salvador Sanchez Y Maria Isabel Salvador Sanchez Cdad",
    "wof:placetype":"venue"
},
  "geometry": {"coordinates":[-5.6578006744,40.964805603],"type":"Point"}
}