{
  "type": "Feature",
  "properties": {
    "iso:country":"ES",
    "sg:address":"Avda Balaidos, 59",
    "sg:city":"Vigo",
    "sg:orig_category":"Calefacci\u00d3n Central: Material (fabricaci\u00d3n, Al Por Mayor)",
    "sg:phone":"+34 986 20 83 33",
    "sg:postcode":"36210",
    "sg:province":"Pontevedra",
    "wof:name":"Comercial Bastos S. L.",
    "wof:placetype":"venue"
},
  "geometry": {"coordinates":[-8.7361288071,42.2127151489],"type":"Point"}
}