{
  "type": "Feature",
  "properties": {
    "addr:full":"Calle de Dean Mudarra, 24 Frailes Ja\u00e9n 23690",
    "addr:housenumber":"24",
    "addr:postcode":"23690",
    "addr:street":"Calle De Dean Mudarra",
    "iso:country":"ES",
    "sg:address":"Calle de Dean Mudarra, 24",
    "sg:city":"Frailes",
    "sg:orig_category":"Molduras, Junquillos, Listones Y Molduras Perforadas",
    "sg:phone":"+34 953 59 32 85",
    "sg:postcode":"23690",
    "sg:province":"Ja\u00e9n",
    "wof:name":"Garrido Collado Daniel",
    "wof:placetype":"venue"
},
  "geometry": {"coordinates":[-3.840275526,37.4846038818],"type":"Point"}
}