{
  "type": "Feature",
  "properties": {
    "iso:country":"ES",
    "sg:address":"Carr Francesc Layret, 173",
    "sg:city":"Badalona",
    "sg:orig_category":"Abogados",
    "sg:phone":"+34 933 84 01 21",
    "sg:postcode":"08911",
    "sg:province":"Barcelona",
    "wof:name":"Roldan-ribo-aloma Advocats Associats S.c.p",
    "wof:placetype":"venue"
},
  "geometry": {"coordinates":[2.2494590282,41.4521446228],"type":"Point"}
}