{
  "type": "Feature",
  "properties": {
    "iso:country":"ES",
    "sg:address":"Avda Justo Quesada, 3",
    "sg:city":"Rojales",
    "sg:orig_category":"Cerrajer\u00cda, Ferrallista",
    "sg:phone":"+34 966 71 42 93",
    "sg:postcode":"03170",
    "sg:province":"Alicante",
    "wof:name":"Ferrothader S.l.",
    "wof:placetype":"venue"
},
  "geometry": {"coordinates":[-0.7113239765,38.090045929],"type":"Point"}
}