{
  "type": "Feature",
  "properties": {
    "iso:country":"ES",
    "sg:address":"Calle de Gines Martin, 4",
    "sg:city":"Huelva",
    "sg:orig_category":"Artesanado",
    "sg:phone":"+34 959 24 01 53",
    "sg:postcode":"21002",
    "sg:province":"Huelva",
    "wof:name":"Ramon Urbano Artesania S.l.",
    "wof:placetype":"venue"
},
  "geometry": {"coordinates":[-6.9517040253,37.2594146729],"type":"Point"}
}