{
  "type": "Feature",
  "properties": {
    "addr:full":"Calle de Carmen, 3 Guadalajara Guadalajara 19001",
    "addr:housenumber":"3",
    "addr:postcode":"19001",
    "addr:street":"Calle De Carmen",
    "iso:country":"ES",
    "sg:address":"Calle de Carmen, 3",
    "sg:city":"Guadalajara",
    "sg:orig_category":"Asociaciones Humanitarias, De Cooperaci\u00d3n, De Acci\u00d3n Social",
    "sg:phone":"+34 949 24 82 28",
    "sg:postcode":"19001",
    "sg:province":"Guadalajara",
    "wof:name":"Asociacion Para La Mediacion E Intervencion Familiar En C.l.m.",
    "wof:placetype":"venue"
},
  "geometry": {"coordinates":[-3.1660969257,40.6320800781],"type":"Point"}
}