{
  "type": "Feature",
  "properties": {
    "addr:full":"Rua Garcia Lorca, 5 Vilaboa La Coru\u00f1a 15174",
    "addr:housenumber":"5",
    "addr:postcode":"15174",
    "addr:street":"Rua Garcia Lorca;La Corun\u0303A",
    "iso:country":"ES",
    "sg:address":"Rua Garcia Lorca, 5",
    "sg:city":"Vilaboa",
    "sg:orig_category":"Agencias Y Agentes Comerciales, Representantes",
    "sg:phone":"+34 981 65 00 48",
    "sg:postcode":"15174",
    "sg:province":"La Coru\u00f1a",
    "wof:name":"Rouco Vila Jorge",
    "wof:placetype":"venue"
},
  "geometry": {"coordinates":[-8.3831396103,43.3070106506],"type":"Point"}
}