{
  "type": "Feature",
  "properties": {
    "addr:full":"Carrer de Corsega, 562 Barcelona Barcelona 08025",
    "addr:housenumber":"562",
    "addr:postcode":"08025",
    "addr:street":"Carrer De Corsega",
    "iso:country":"ES",
    "sg:address":"Carrer de Corsega, 562",
    "sg:city":"Barcelona",
    "sg:orig_category":"Peluquer\u00cdas, Peluquer\u00cda Mixta",
    "sg:phone":"+34 934 50 05 57",
    "sg:postcode":"08025",
    "sg:province":"Barcelona",
    "wof:name":"Subias Carmen Manuela",
    "wof:placetype":"venue"
},
  "geometry": {"coordinates":[2.1735429764,41.4070701599],"type":"Point"}
}