{
  "type": "Feature",
  "properties": {
    "addr:full":"Calle de Maestro Alonso, 5 San Miguel Murcia 30005",
    "addr:housenumber":"5",
    "addr:postcode":"30005",
    "addr:street":"Calle De Maestro Alonso",
    "iso:country":"ES",
    "sg:address":"Calle de Maestro Alonso, 5",
    "sg:city":"San Miguel",
    "sg:classifiers":[
        {
            "category":"Professional",
            "subcategory":"Research",
            "type":"Services"
        }
    ],
    "sg:phone":"+34 968 21 72 61",
    "sg:postcode":"30005",
    "sg:province":"Murcia",
    "sg:tags":[
        "mercado",
        "de",
        "estudios"
    ],
    "wof:name":"Inmuebles En Arrendamiento Josefina Garcia S.l.",
    "wof:placetype":"venue"
},
  "geometry": {"coordinates":[-1.1317420006,37.987739563],"type":"Point"}
}