{
  "type": "Feature",
  "properties": {
    "addr:full":"Calle de Arcos, S/n Sevilla Sevilla 41011",
    "addr:housenumber":"s / n",
    "addr:postcode":"41011",
    "addr:street":"Calle De Arcos",
    "iso:country":"ES",
    "sg:address":"Calle de Arcos, S/n",
    "sg:city":"Sevilla",
    "sg:orig_category":"Iglesia Cat\u00d3lica",
    "sg:phone":"+34 954 45 14 71",
    "sg:postcode":"41011",
    "sg:province":"Sevilla",
    "wof:name":"Parroquia De Nuestra Se\u00f1ora De Los Remedios",
    "wof:placetype":"venue"
},
  "geometry": {"coordinates":[-5.9996747971,37.3768997192],"type":"Point"}
}