{
  "type": "Feature",
  "properties": {
    "addr:full":"Avda Primero De Mayo, 1 Coria Rio Sevilla 41100",
    "addr:housenumber":"1",
    "addr:postcode":"41100",
    "addr:street":"Avda Primero De Mayo;Rio Sevilla",
    "iso:country":"ES",
    "sg:address":"Avda Primero De Mayo, 1",
    "sg:city":"Coria Rio",
    "sg:orig_category":"Inmobiliaria (agencias)",
    "sg:phone":"+34 954 77 91 42",
    "sg:postcode":"41100",
    "sg:province":"Sevilla",
    "wof:name":"Coyven Aljarafe S.l.",
    "wof:placetype":"venue"
},
  "geometry": {"coordinates":[-6.0522208214,37.2865180969],"type":"Point"}
}