{
  "type": "Feature",
  "properties": {
    "addr:full":"Po Dr. Jose R Vazquez (oeste), S/n Catoira Pontevedra 36612",
    "addr:housenumber":"s / n",
    "addr:postcode":"36612",
    "addr:street":"Jose R Vazquez Oeste",
    "iso:country":"ES",
    "sg:address":"Po Dr. Jose R Vazquez (oeste), S/n",
    "sg:city":"Catoira",
    "sg:orig_category":"Restaurantes Para Recepciones, Banquetes, Conferencias",
    "sg:phone":"+34 986 54 60 13",
    "sg:postcode":"36612",
    "sg:province":"Pontevedra",
    "wof:name":"Rodriguez Rodriguez Maria Clotilde",
    "wof:placetype":"venue"
},
  "geometry": {"coordinates":[-8.7251787186,42.672088623],"type":"Point"}
}