{
  "type": "Feature",
  "properties": {
    "addr:full":"Calle de Rio Pisuerga, S/n Avila \u00c1vila 05004",
    "addr:housenumber":"s / n",
    "addr:postcode":"05004",
    "addr:street":"Calle De Rio Pisuerga;A\u0301Vila",
    "iso:country":"ES",
    "sg:address":"Calle de Rio Pisuerga, S/n",
    "sg:city":"Avila",
    "sg:orig_category":"Iluminaci\u00d3n Industrial, Alumbrado P\u00dablico: Material (fabricaci\u00d3n, Importaci\u00d3n)",
    "sg:phone":"+34 920 25 46 73",
    "sg:postcode":"05004",
    "sg:province":"\u00c1vila",
    "wof:name":"Ayuntamiento De Avila",
    "wof:placetype":"venue"
},
  "geometry": {"coordinates":[-4.6838974953,40.6671218872],"type":"Point"}
}