{
  "type": "Feature",
  "properties": {
    "addr:full":"Crrd Capuchinos, 1 Andujar Ja\u00e9n 23740",
    "addr:postcode":"23740",
    "addr:street":"Jae\u0301N",
    "iso:country":"ES",
    "sg:address":"Crrd Capuchinos, 1",
    "sg:city":"Andujar",
    "sg:orig_category":"Laboratorios Y Trabajos De Fotograf\u00cda, V\u00cddeo Y Cine",
    "sg:phone":"+34 953 51 15 72",
    "sg:postcode":"23740",
    "sg:province":"Ja\u00e9n",
    "wof:name":"Retrato Y Moda Manuel Fernando S.l.l.",
    "wof:placetype":"venue"
},
  "geometry": {"coordinates":[-4.051817894,38.0366325378],"type":"Point"}
}