{
  "type": "Feature",
  "properties": {
    "iso:country":"ES",
    "sg:address":"Calle de Gran Via De Jose Antonio Agirre Y Lekube, 90",
    "sg:city":"Sestao",
    "sg:orig_category":"Plomeros",
    "sg:phone":"+34 944 86 29 26",
    "sg:postcode":"48910",
    "sg:province":"Vizcaya",
    "wof:name":"Fontaneria Y Desatascos El Campillo, S.l.",
    "wof:placetype":"venue"
},
  "geometry": {"coordinates":[-3.0000603199,43.3071403503],"type":"Point"}
}