{
  "type": "Feature",
  "properties": {
    "addr:full":"Calle de Avila, 8 Mostoles Madrid 28931",
    "addr:housenumber":"8",
    "addr:postcode":"28931",
    "addr:street":"Calle De Avila",
    "iso:country":"ES",
    "sg:address":"Calle de Avila, 8",
    "sg:city":"Mostoles",
    "sg:orig_category":"Muebles, Minoristas",
    "sg:phone":"+34 916 14 72 89",
    "sg:postcode":"28931",
    "sg:province":"Madrid",
    "wof:name":"Riaza Rodriguez Petra",
    "wof:placetype":"venue"
},
  "geometry": {"coordinates":[-3.85947299,40.3250732422],"type":"Point"}
}