{
  "type": "Feature",
  "properties": {
    "addr:full":"Plaz Gabriel Lodares, 4 Albacete Albacete 02002",
    "addr:housenumber":"4",
    "addr:postcode":"02002",
    "iso:country":"ES",
    "sg:address":"Plaz Gabriel Lodares, 4",
    "sg:city":"Albacete",
    "sg:orig_category":"M\u00c9dicos: Neumolog\u00cda",
    "sg:phone":"+34 967 23 17 12",
    "sg:postcode":"02002",
    "sg:province":"Albacete",
    "wof:name":"Rodriguez Lopez Eloy",
    "wof:placetype":"venue"
},
  "geometry": {"coordinates":[-1.8540610075,38.9950675964],"type":"Point"}
}