{
  "type": "Feature",
  "properties": {
    "addr:full":"Ctra Doctor Robert, 26 Vendrell Tarragona 43700",
    "addr:housenumber":"26",
    "addr:postcode":"43700",
    "addr:street":"Ctra Doctor Robert",
    "iso:country":"ES",
    "sg:address":"Ctra Doctor Robert, 26",
    "sg:city":"Vendrell",
    "sg:orig_category":"Ropa Para Se\u00d1oras (al Por Menor)",
    "sg:phone":"+34 977 66 73 91",
    "sg:postcode":"43700",
    "sg:province":"Tarragona",
    "wof:name":"Calvet Bargallo Montserrat",
    "wof:placetype":"venue"
},
  "geometry": {"coordinates":[1.5368839502,41.2214012146],"type":"Point"}
}