{
  "type": "Feature",
  "properties": {
    "addr:full":"Calle de Puerta De Cuenca, 44 Roda Albacete 02630",
    "addr:housenumber":"44",
    "addr:postcode":"02630",
    "addr:street":"Calle De Puerta De Cuenca",
    "iso:country":"ES",
    "sg:address":"Calle de Puerta De Cuenca, 44",
    "sg:city":"Roda",
    "sg:orig_category":"Empresas De Carpinter\u00cda",
    "sg:phone":"+34 967 44 41 36",
    "sg:postcode":"02630",
    "sg:province":"Albacete",
    "wof:name":"Lozano Alarcon Regino",
    "wof:placetype":"venue"
},
  "geometry": {"coordinates":[-2.1291613579,39.2391700745],"type":"Point"}
}