{
  "type": "Feature",
  "properties": {
    "addr:full":"Carr Liria, 6 Eliana Valencia 46183",
    "addr:housenumber":"6",
    "addr:postcode":"46183",
    "addr:street":"Carr Liria",
    "iso:country":"ES",
    "sg:address":"Carr Liria, 6",
    "sg:city":"Eliana",
    "sg:orig_category":"Inform\u00c1tica (estudios, Servicios, Asesor\u00cda, Formaci\u00d3n)",
    "sg:phone":"+34 962 74 22 38",
    "sg:postcode":"46183",
    "sg:province":"Valencia",
    "wof:name":"Iredes 2003 S.l.l.",
    "wof:placetype":"venue"
},
  "geometry": {"coordinates":[-0.528208971,39.5667457581],"type":"Point"}
}