{
  "type": "Feature",
  "properties": {
    "iso:country":"ES",
    "sg:address":"Calle de Reyes Catolicos, 24",
    "sg:city":"Toledo",
    "sg:orig_category":"Artesan\u00cda",
    "sg:phone":"+34 925 21 24 14",
    "sg:postcode":"45002",
    "sg:province":"Toledo",
    "wof:name":"Erades Sanchez Luis",
    "wof:placetype":"venue"
},
  "geometry": {"coordinates":[-4.0313591957,39.8581390381],"type":"Point"}
}