{
  "type": "Feature",
  "properties": {
    "iso:country":"ES",
    "sg:address":"Ingeniero Algarra, 40",
    "sg:city":"Pals",
    "sg:orig_category":"Pizzer\u00cdas",
    "sg:phone":"+34 972 63 67 36",
    "sg:postcode":"17256",
    "sg:province":"Girona",
    "wof:name":"Menjar S.l.",
    "wof:placetype":"venue"
},
  "geometry": {"coordinates":[3.1482870579,41.9691963196],"type":"Point"}
}