{
  "type": "Feature",
  "properties": {
    "addr:full":"Calle de Zabaleta, 6 Donostia-san Sebastian Guip\u00f9zcoa 20002",
    "addr:housenumber":"6",
    "addr:postcode":"20002",
    "addr:street":"Calle De Zabaleta",
    "iso:country":"ES",
    "sg:address":"Calle de Zabaleta, 6",
    "sg:city":"Donostia-san Sebastian",
    "sg:orig_category":"Camiser\u00cda Y Ropa Interior Masculina (al Por Menor)",
    "sg:phone":"+34 943 27 92 48",
    "sg:postcode":"20002",
    "sg:province":"Guip\u00f9zcoa",
    "wof:name":"Ledir S.l.",
    "wof:placetype":"venue"
},
  "geometry": {"coordinates":[-1.9763300419,43.3227653503],"type":"Point"}
}