{
  "type": "Feature",
  "properties": {
    "addr:full":"Carr Sant Cristofol, 20 Villarreal Castell\u00f3n 12540",
    "addr:housenumber":"20",
    "addr:postcode":"12540",
    "addr:street":"Carr Sant Cristofol",
    "iso:country":"ES",
    "sg:address":"Carr Sant Cristofol, 20",
    "sg:city":"Villarreal",
    "sg:orig_category":"Art\u00cdculos Funerarios (al Por Menor)",
    "sg:phone":"+34 964 52 18 43",
    "sg:postcode":"12540",
    "sg:province":"Castell\u00f3n",
    "wof:name":"Jose Carlos Martinez Almela Y Otro Cdad.",
    "wof:placetype":"venue"
},
  "geometry": {"coordinates":[-0.1034846976,39.9383735657],"type":"Point"}
}