{
  "type": "Feature",
  "properties": {
    "iso:country":"ES",
    "sg:address":"Rbla Castell, 48",
    "sg:city":"Vilanova I La Geltru",
    "sg:orig_category":"Molduras, Junquillos, Listones Y Molduras Perforadas",
    "sg:phone":"+34 938 11 59 63",
    "sg:postcode":"08800",
    "sg:province":"Barcelona",
    "wof:name":"Rapsodia S.c.p.",
    "wof:placetype":"venue"
},
  "geometry": {"coordinates":[1.7297610044,41.2243003845],"type":"Point"}
}