{
  "type": "Feature",
  "properties": {
    "addr:full":"Calle de San Juan, S/n Alhaurin Torre M\u00e1laga 29130",
    "addr:housenumber":"s / n",
    "addr:postcode":"29130",
    "addr:street":"Calle De San Juan",
    "iso:country":"ES",
    "sg:address":"Calle de San Juan, S/n",
    "sg:city":"Alhaurin Torre",
    "sg:orig_category":"Cajas De Ahorro",
    "sg:phone":"+34 952 41 44 92",
    "sg:postcode":"29130",
    "sg:province":"M\u00e1laga",
    "wof:name":"Caja De Ahorros De Valencia Castellon Y Alicante",
    "wof:placetype":"venue"
},
  "geometry": {"coordinates":[-4.5618839264,36.6618843079],"type":"Point"}
}