{
  "type": "Feature",
  "properties": {
    "addr:full":"Calle de Juan Ii, 1 Vitoria-gasteiz \u00c1lava 01003",
    "addr:housenumber":"1",
    "addr:postcode":"01003",
    "addr:street":"Calle De Juan Ii",
    "iso:country":"ES",
    "sg:address":"Calle de Juan Ii, 1",
    "sg:city":"Vitoria-gasteiz",
    "sg:orig_category":"Bisuter\u00cda, Joyer\u00cda, Relojer\u00cda (al Por Menor)",
    "sg:phone":"+34 945 26 45 89",
    "sg:postcode":"01003",
    "sg:province":"\u00c1lava",
    "wof:name":"Bego\u00f1a Ogueta Romero",
    "wof:placetype":"venue"
},
  "geometry": {"coordinates":[-2.6652400494,42.8464431763],"type":"Point"}
}