{
  "type": "Feature",
  "properties": {
    "iso:country":"ES",
    "sg:address":"Plaz Salinas, 5",
    "sg:city":"Fuentealbilla",
    "sg:orig_category":"Empresas De Carpinter\u00cda De Madera",
    "sg:phone":"+34 967 47 20 28",
    "sg:postcode":"02260",
    "sg:province":"Albacete",
    "wof:name":"Salmeron Arjona Alonso",
    "wof:placetype":"venue"
},
  "geometry": {"coordinates":[-1.5474749804,39.2659912109],"type":"Point"}
}