{
  "type": "Feature",
  "properties": {
    "addr:full":"Ctra Galapagar (de), 8 Estacion Madrid 28250",
    "addr:postcode":"28250",
    "addr:street":"Ctra Galapagar De 8 Estacion",
    "iso:country":"ES",
    "sg:address":"Ctra Galapagar (de), 8",
    "sg:city":"Estacion",
    "sg:orig_category":"Centros De Educaci\u00d3n Especial",
    "sg:phone":"+34 918 59 19 90",
    "sg:postcode":"28250",
    "sg:province":"Madrid",
    "wof:name":"Cruz Ruiz Eva",
    "wof:placetype":"venue"
},
  "geometry": {"coordinates":[-3.9569671154,40.5764274597],"type":"Point"}
}