{
  "type": "Feature",
  "properties": {
    "addr:full":"Carrer de Sarriera, 35 Vilafranca Penedes Barcelona 08720",
    "addr:housenumber":"35",
    "addr:postcode":"08720",
    "addr:street":"Carrer De Sarriera",
    "iso:country":"ES",
    "sg:address":"Carrer de Sarriera, 35",
    "sg:city":"Vilafranca Penedes",
    "sg:orig_category":"Ense\u00d1anza, Formaci\u00d3n Profesional: Aprendizaje",
    "sg:phone":"+34 938 90 33 55",
    "sg:postcode":"08720",
    "sg:province":"Barcelona",
    "wof:name":"Instituto Agricola Catalan De San Isidro",
    "wof:placetype":"venue"
},
  "geometry": {"coordinates":[1.7051639557,41.3451004028],"type":"Point"}
}