{
  "type": "Feature",
  "properties": {
    "iso:country":"ES",
    "sg:address":"Avda Federico Garcia Lorca, 12",
    "sg:city":"Salobre\u00f1a",
    "sg:orig_category":"Notarios",
    "sg:phone":"+34 958 61 13 44",
    "sg:postcode":"18680",
    "sg:province":"Granada",
    "wof:name":"Diaz Garijo Rafael Eduardo",
    "wof:placetype":"venue"
},
  "geometry": {"coordinates":[-3.5854289532,36.7416915894],"type":"Point"}
}