{
  "type": "Feature",
  "properties": {
    "iso:country":"ES",
    "sg:address":"Calle de Lima (de), 69",
    "sg:city":"Fuenlabrada",
    "sg:orig_category":"Empresas De Vigilancia, Guardia Y Protecci\u00d3n",
    "sg:phone":"+34 914 92 11 58",
    "sg:postcode":"28945",
    "sg:province":"Madrid",
    "wof:name":"Hispania De Proteccion S.a",
    "wof:placetype":"venue"
},
  "geometry": {"coordinates":[-3.7868878841,40.2946777344],"type":"Point"}
}