{
  "type": "Feature",
  "properties": {
    "iso:country":"ES",
    "sg:address":"Avda Salle (de La), 13",
    "sg:city":"Santa Cruz De Tenerife",
    "sg:orig_category":"Materiales De Construcci\u00d3n (en General)",
    "sg:phone":"+34 922 21 47 98",
    "sg:postcode":"38005",
    "sg:province":"Santa Cruz De Tenerife",
    "wof:name":"Anpesa S. A.",
    "wof:placetype":"venue"
},
  "geometry": {"coordinates":[-16.2568187714,28.4611606598],"type":"Point"}
}