{
  "type": "Feature",
  "properties": {
    "addr:full":"Calle de Real Arriba, 42 Yebenes Toledo 45470",
    "addr:housenumber":"42",
    "addr:postcode":"45470",
    "addr:street":"Calle De;Arriba",
    "iso:country":"ES",
    "sg:address":"Calle de Real Arriba, 42",
    "sg:city":"Yebenes",
    "sg:orig_category":"Abogados",
    "sg:phone":"+34 925 32 04 06",
    "sg:postcode":"45470",
    "sg:province":"Toledo",
    "wof:name":"Valiente Herencia Saturnino",
    "wof:placetype":"venue"
},
  "geometry": {"coordinates":[-3.8690719604,39.5838470459],"type":"Point"}
}