{
  "type": "Feature",
  "properties": {
    "iso:country":"ES",
    "sg:address":"Calle de La Del Manojo De Rosas, 83",
    "sg:city":"Madrid",
    "sg:orig_category":"Papel Pintado (al Por Menor)",
    "sg:phone":"+34 913 17 21 81",
    "sg:postcode":"28041",
    "sg:province":"Madrid",
    "wof:name":"Cabello Ruiz Antonia",
    "wof:placetype":"venue"
},
  "geometry": {"coordinates":[-3.6981260777,40.3538970947],"type":"Point"}
}