{
  "type": "Feature",
  "properties": {
    "addr:full":"Avda San Miguel, 82 Iscar Valladolid 47420",
    "addr:housenumber":"82",
    "addr:postcode":"47420",
    "addr:street":"Avda San Miguel",
    "iso:country":"ES",
    "sg:address":"Avda San Miguel, 82",
    "sg:city":"Iscar",
    "sg:orig_category":"Venta, Instalaci\u00d3n De Calefacci\u00d3n",
    "sg:phone":"+34 983 61 22 68",
    "sg:postcode":"47420",
    "sg:province":"Valladolid",
    "wof:name":"Instalaciones Olmo S.l.",
    "wof:placetype":"venue"
},
  "geometry": {"coordinates":[-4.5376338959,41.3601837158],"type":"Point"}
}