{
  "type": "Feature",
  "properties": {
    "addr:full":"Psaj Maignon, 14 Badalona Barcelona 08911",
    "addr:housenumber":"14",
    "addr:postcode":"08911",
    "addr:street":"Maignon",
    "iso:country":"ES",
    "sg:address":"Psaj Maignon, 14",
    "sg:city":"Badalona",
    "sg:orig_category":"Agencias De Viajes",
    "sg:phone":"+34 934 64 25 76",
    "sg:postcode":"08911",
    "sg:province":"Barcelona",
    "sg:website":"www.marsans.es",
    "wof:name":"Viajes Marsans S.a.",
    "wof:placetype":"venue"
},
  "geometry": {"coordinates":[2.246915102,41.4479484558],"type":"Point"}
}