{
  "type": "Feature",
  "properties": {
    "addr:full":"Avda Sancho El Sabio, 6 Donostia-san Sebastian Guip\u00f9zcoa 20010",
    "addr:housenumber":"6",
    "addr:postcode":"20010",
    "addr:street":"Avda Sancho El Sabio",
    "iso:country":"ES",
    "sg:address":"Avda Sancho El Sabio, 6",
    "sg:city":"Donostia-san Sebastian",
    "sg:orig_category":"Bancos",
    "sg:phone":"+34 943 44 52 11",
    "sg:postcode":"20010",
    "sg:province":"Guip\u00f9zcoa",
    "wof:name":"Banco Guipuzcoano S.a.",
    "wof:placetype":"venue"
},
  "geometry": {"coordinates":[-1.9803980589,43.3106117249],"type":"Point"}
}