{
  "type": "Feature",
  "properties": {
    "iso:country":"ES",
    "sg:address":"Ctra Moya, 19",
    "sg:city":"Santa Maria De Guia",
    "sg:orig_category":"Grifer\u00cda Industrial",
    "sg:phone":"+34 928 55 37 13",
    "sg:postcode":"35450",
    "sg:province":"Las Palmas",
    "wof:name":"Fontaneria Marben S.l.",
    "wof:placetype":"venue"
},
  "geometry": {"coordinates":[-15.6319208145,28.1403903961],"type":"Point"}
}