{
  "type": "Feature",
  "properties": {
    "addr:full":"Rego Do Mui\u00f1o, 13 Pontes Garcia Rodriguez La Coru\u00f1a 15320",
    "addr:housenumber":"13",
    "addr:postcode":"15320",
    "addr:street":"Pontes Garcia Rodriguez La Corun\u0303A",
    "iso:country":"ES",
    "sg:address":"Rego Do Mui\u00f1o, 13",
    "sg:city":"Pontes Garcia Rodriguez",
    "sg:orig_category":"Electrodom\u00c9sticos (al Por Menor)",
    "sg:phone":"+34 981 45 12 73",
    "sg:postcode":"15320",
    "sg:province":"La Coru\u00f1a",
    "wof:name":"Gonzalez Lugo Edmundo",
    "wof:placetype":"venue"
},
  "geometry": {"coordinates":[-7.8582792282,43.4487495422],"type":"Point"}
}