{
  "type": "Feature",
  "properties": {
    "iso:country":"ES",
    "sg:address":"Pase Chopera (de La), 53",
    "sg:city":"Alcobendas",
    "sg:orig_category":"Peleter\u00cdas",
    "sg:phone":"+34 916 61 77 92",
    "sg:postcode":"28100",
    "sg:province":"Madrid",
    "wof:name":"Peleteria Galifer S.l.",
    "wof:placetype":"venue"
},
  "geometry": {"coordinates":[-3.6431369781,40.5426063538],"type":"Point"}
}