{
  "type": "Feature",
  "properties": {
    "addr:full":"Calle de Horno (del), 7 Jaulin Zaragoza 50141",
    "addr:housenumber":"7",
    "addr:postcode":"50141",
    "addr:street":"Calle De Horno Del",
    "iso:country":"ES",
    "sg:address":"Calle de Horno (del), 7",
    "sg:city":"Jaulin",
    "sg:classifiers":[
        {
            "category":"Casinos & Gambling",
            "type":"Entertainment"
        }
    ],
    "sg:phone":"+34 976 14 22 00",
    "sg:postcode":"50141",
    "sg:province":"Zaragoza",
    "sg:tags":[
        "locale",
        "de",
        "juego"
    ],
    "wof:name":"Telefonos Publicos De Aragon S L",
    "wof:placetype":"venue"
},
  "geometry": {"coordinates":[-0.9923490286,41.4525222778],"type":"Point"}
}