{
  "type": "Feature",
  "properties": {
    "addr:full":"Avda Portus Illicitanus, 9 Santa Pola Alicante 03130",
    "addr:housenumber":"9",
    "addr:postcode":"03130",
    "addr:street":"Avda Portus Illicitanus",
    "iso:country":"ES",
    "sg:address":"Avda Portus Illicitanus, 9",
    "sg:city":"Santa Pola",
    "sg:orig_category":"Inmobiliaria (agencias)",
    "sg:phone":"+34 966 69 45 72",
    "sg:postcode":"03130",
    "sg:province":"Alicante",
    "wof:name":"Quesada Rico Jose Antonio",
    "wof:placetype":"venue"
},
  "geometry": {"coordinates":[-0.5613200068,38.1934165955],"type":"Point"}
}