{
  "type": "Feature",
  "properties": {
    "addr:full":"Carrer de Lusacia, 43 Vall Suau-can Feliu Barcelona 08192",
    "addr:housenumber":"43",
    "addr:postcode":"08192",
    "addr:street":"Carrer De Lusacia",
    "iso:country":"ES",
    "sg:address":"Carrer de Lusacia, 43",
    "sg:city":"Vall Suau-can Feliu",
    "sg:orig_category":"Inversiones",
    "sg:phone":"+34 937 21 04 52",
    "sg:postcode":"08192",
    "sg:province":"Barcelona",
    "wof:name":"Alvarez Rodriguez Juan Felix",
    "wof:placetype":"venue"
},
  "geometry": {"coordinates":[2.0703895092,41.5291862488],"type":"Point"}
}