{
  "type": "Feature",
  "properties": {
    "iso:country":"ES",
    "sg:address":"C/ Magallanes, 13",
    "sg:city":"Madrid",
    "sg:classifiers":[
        {
            "category":"Professional",
            "subcategory":"Computer Services",
            "type":"Services"
        }
    ],
    "sg:postcode":"28015",
    "sg:tags":[
        "ivr",
        "ivvr",
        "voicexml",
        "vxi",
        "phone",
        "voip",
        "asterisk"
    ],
    "sg:website":"http://www.i6net.com",
    "wof:name":"I6NET",
    "wof:placetype":"venue"
},
  "geometry": {"coordinates":[-3.7056763,40.4342873],"type":"Point"}
}