{
  "type": "Feature",
  "properties": {
    "iso:country":"ES",
    "sg:address":"Ctra. Villacastin-vigo, S/n",
    "sg:city":"La Encomienda",
    "sg:orig_category":"Asociaciones Y Clubs Deportivos",
    "sg:phone":"+34 980 58 60 06",
    "sg:postcode":"49145",
    "sg:province":"Zamora",
    "wof:name":"Club Deportivo Del Esla",
    "wof:placetype":"venue"
},
  "geometry": {"coordinates":[-5.875234127,41.7268218994],"type":"Point"}
}