{
  "type": "Feature",
  "properties": {
    "addr:full":"Carrer de Sant Joan, 42 Ametlla Mar Tarragona 43860",
    "addr:housenumber":"42",
    "addr:postcode":"43860",
    "addr:street":"Carrer De Sant Joan",
    "iso:country":"ES",
    "sg:address":"Carrer de Sant Joan, 42",
    "sg:city":"Ametlla Mar",
    "sg:orig_category":"Agentes Generales De Seguros",
    "sg:phone":"+34 977 45 63 91",
    "sg:postcode":"43860",
    "sg:province":"Tarragona",
    "wof:name":"Marti Prime S.l.",
    "wof:placetype":"venue"
},
  "geometry": {"coordinates":[0.8035240173,40.8849487305],"type":"Point"}
}