{
  "type": "Feature",
  "properties": {
    "addr:full":"Finc Alamin, S/n Santa Cruz Del Retamar Toledo 45513",
    "addr:housenumber":"s / n",
    "addr:postcode":"45513",
    "iso:country":"ES",
    "sg:address":"Finc Alamin, S/n",
    "sg:city":"Santa Cruz Del Retamar",
    "sg:orig_category":"Deportes Diversos",
    "sg:phone":"+34 925 78 93 20",
    "sg:postcode":"45513",
    "sg:province":"Toledo",
    "wof:name":"Tecnocaza S.l",
    "wof:placetype":"venue"
},
  "geometry": {"coordinates":[-4.2387938499,40.1208534241],"type":"Point"}
}