{
  "type": "Feature",
  "properties": {
    "addr:full":"Calle de Sao Paulo, 30 Palmas De Gran Canaria Las Palmas 35...",
    "addr:housenumber":"30;35 ...",
    "addr:street":"Calle De Sao Paulo;Palmas",
    "iso:country":"ES",
    "sg:address":"Calle de Sao Paulo, 30",
    "sg:city":"Palmas De Gran Canaria",
    "sg:orig_category":"Fabricaci\u00d3n De Juegos Y Juguetes",
    "sg:phone":"+34 928 48 89 70",
    "sg:postcode":"35...",
    "sg:province":"Las Palmas",
    "wof:name":"Comercial Joman S.l.",
    "wof:placetype":"venue"
},
  "geometry": {"coordinates":[-15.4151544571,28.1578273773],"type":"Point"}
}