{
  "type": "Feature",
  "properties": {
    "iso:country":"ES",
    "sg:address":"Calle de Granado, 20",
    "sg:city":"Partija-santa Monica",
    "sg:orig_category":"Asesor\u00cda Fiscal Y Jur\u00cddica",
    "sg:phone":"+34 916 66 21 14",
    "sg:postcode":"28529",
    "sg:province":"Madrid",
    "wof:name":"Limites Prevencion S.l.",
    "wof:placetype":"venue"
},
  "geometry": {"coordinates":[-3.5102670193,40.314289093],"type":"Point"}
}