{
  "type": "Feature",
  "properties": {
    "iso:country":"ES",
    "sg:address":"Calle de Sol (el), 5",
    "sg:city":"Leganes",
    "sg:orig_category":"Supermercados Y Hipermercados",
    "sg:phone":"+34 916 89 41 95",
    "sg:postcode":"28911",
    "sg:province":"Madrid",
    "wof:name":"Ecozar S. A.",
    "wof:placetype":"venue"
},
  "geometry": {"coordinates":[-3.7667179108,40.3276939392],"type":"Point"}
}