{
  "type": "Feature",
  "properties": {
    "addr:full":"Avda Sagunto (de), 9 Teruel Teruel 44002",
    "addr:housenumber":"9",
    "addr:postcode":"44002",
    "addr:street":"Avda Sagunto De",
    "iso:country":"ES",
    "sg:address":"Avda Sagunto (de), 9",
    "sg:city":"Teruel",
    "sg:orig_category":"Transportes Por V\u00cdas Navegables",
    "sg:phone":"+34 978 60 42 16",
    "sg:postcode":"44002",
    "sg:province":"Teruel",
    "wof:name":"Torrecilla Sanchez Pablo",
    "wof:placetype":"venue"
},
  "geometry": {"coordinates":[-1.1040480137,40.3362541199],"type":"Point"}
}