{
  "type": "Feature",
  "properties": {
    "addr:full":"Carrer de Benviure, 54 S. Boi Llobregat Barcelona 08830",
    "addr:housenumber":"54",
    "addr:postcode":"08830",
    "addr:street":"Carrer De Benviure",
    "iso:country":"ES",
    "sg:address":"Carrer de Benviure, 54",
    "sg:city":"S. Boi Llobregat",
    "sg:orig_category":"Molduras, Junquillos, Listones Y Molduras Perforadas",
    "sg:phone":"+34 936 30 08 25",
    "sg:postcode":"08830",
    "sg:province":"Barcelona",
    "wof:name":"Jimenez Carmona Luis",
    "wof:placetype":"venue"
},
  "geometry": {"coordinates":[2.0257999897,41.3454284668],"type":"Point"}
}