{
  "type": "Feature",
  "properties": {
    "iso:country":"ES",
    "sg:address":"Avda Antonio Sarabia, 10",
    "sg:city":"Yeles",
    "sg:orig_category":"Abogados",
    "sg:phone":"+34 925 51 02 17",
    "sg:postcode":"45220",
    "sg:province":"Toledo",
    "wof:name":"Perez Polo Ignacio",
    "wof:placetype":"venue"
},
  "geometry": {"coordinates":[-3.8029019833,40.1195526123],"type":"Point"}
}