{
  "type": "Feature",
  "properties": {
    "iso:country":"ES",
    "sg:address":"Calle de Almansa, 3",
    "sg:city":"Madrid",
    "sg:orig_category":"Peluquer\u00cdas, Peluquer\u00cda Mixta",
    "sg:phone":"+34 915 54 85 87",
    "sg:postcode":"28039",
    "sg:province":"Madrid",
    "wof:name":"Ropero Murillo Eugenio",
    "wof:placetype":"venue"
},
  "geometry": {"coordinates":[-3.7038986683,40.4486427307],"type":"Point"}
}