{
  "type": "Feature",
  "properties": {
    "iso:country":"ES",
    "sg:address":"Calle de Jose Maluquer, 13",
    "sg:city":"Sevilla",
    "sg:orig_category":"Empresarios",
    "sg:phone":"+34 954 35 38 35",
    "sg:postcode":"41008",
    "sg:province":"Sevilla",
    "wof:name":"Montablock S.l.",
    "wof:placetype":"venue"
},
  "geometry": {"coordinates":[-5.9789104462,37.4031410217],"type":"Point"}
}