{
  "type": "Feature",
  "properties": {
    "iso:country":"ES",
    "sg:address":"Avda Puerta De Sancho, 24",
    "sg:city":"Zaragoza",
    "sg:orig_category":"Transportes Frigor\u00cdficos",
    "sg:phone":"+34 976 43 37 93",
    "sg:postcode":"50003",
    "sg:province":"Zaragoza",
    "wof:name":"Lostal Cabello Antonio",
    "wof:placetype":"venue"
},
  "geometry": {"coordinates":[-0.9015930295,41.6608886719],"type":"Point"}
}