{
  "type": "Feature",
  "properties": {
    "iso:country":"ES",
    "sg:address":"B. Cementerio, 45",
    "sg:city":"Callosa Segura",
    "sg:orig_category":"Chapister\u00cda",
    "sg:phone":"+34 965 31 11 47",
    "sg:postcode":"03360",
    "sg:province":"Alicante",
    "wof:name":"Caselles Garcia Jose Manuel",
    "wof:placetype":"venue"
},
  "geometry": {"coordinates":[-0.8776689768,38.1256752014],"type":"Point"}
}