{
  "type": "Feature",
  "properties": {
    "iso:country":"ES",
    "sg:address":"Av Rei Jaume I, 107",
    "sg:city":"Santa Pon\u00c7a",
    "sg:orig_category":"Zapatos (al Por Menor)",
    "sg:phone":"+34 971 69 58 32",
    "sg:postcode":"07180",
    "sg:province":"Islas Baleares",
    "wof:name":"Carrillo Pleguezuelos Maria Eugenia",
    "wof:placetype":"venue"
},
  "geometry": {"coordinates":[2.4842739105,39.5160675049],"type":"Point"}
}