{
  "type": "Feature",
  "properties": {
    "addr:full":"Ctra Madrid, S/n Badajoz Badajoz 06008",
    "addr:housenumber":"s / n",
    "addr:postcode":"06008",
    "addr:street":"Ctra Madrid",
    "iso:country":"ES",
    "sg:address":"Ctra Madrid, S/n",
    "sg:city":"Badajoz",
    "sg:orig_category":"Pintura, Barniz, Productos Asimilables (fabricaci\u00d3n, Al Por Mayor)",
    "sg:phone":"+34 924 26 23 58",
    "sg:postcode":"06008",
    "sg:province":"Badajoz",
    "wof:name":"Tallere De Chapisteria Madrid S.l.",
    "wof:placetype":"venue"
},
  "geometry": {"coordinates":[-6.9502191544,38.8765563965],"type":"Point"}
}