{
  "type": "Feature",
  "properties": {
    "iso:country":"ES",
    "sg:address":"Calle de General Vives, 6",
    "sg:city":"Palmas De Gran Canaria",
    "sg:orig_category":"Materias Pl\u00c1sticas: Art\u00cdculos Para La Industria",
    "sg:phone":"+34 928 23 12 24",
    "sg:postcode":"35006",
    "sg:province":"Las Palmas",
    "wof:name":"Ghazi Chiquiro Mustafa Abdelkader",
    "wof:placetype":"venue"
},
  "geometry": {"coordinates":[-15.4315843582,28.1403369904],"type":"Point"}
}