{
  "type": "Feature",
  "properties": {
    "addr:full":"Calle de Auntzetxeta, 3 Bilbao Vizcaya 48002",
    "addr:housenumber":"3",
    "addr:postcode":"48002",
    "addr:street":"Calle De Auntzetxeta",
    "iso:country":"ES",
    "sg:address":"Calle de Auntzetxeta, 3",
    "sg:city":"Bilbao",
    "sg:orig_category":"Asesor\u00cdas En Comunicaci\u00d3n",
    "sg:phone":"+34 944 27 22 37",
    "sg:postcode":"48002",
    "sg:province":"Vizcaya",
    "wof:name":"Expresiones Ediciones S.l.",
    "wof:placetype":"venue"
},
  "geometry": {"coordinates":[-2.9565424919,43.2583084106],"type":"Point"}
}