{
  "type": "Feature",
  "properties": {
    "addr:full":"Carrer de Constitucio, 1 Palma Islas Baleares 07001",
    "addr:housenumber":"1",
    "addr:postcode":"07001",
    "addr:street":"Carrer De Constitucio",
    "iso:country":"ES",
    "sg:address":"Carrer de Constitucio, 1",
    "sg:city":"Palma",
    "sg:orig_category":"Turismo",
    "sg:phone":"+34 971 72 53 96",
    "sg:postcode":"07001",
    "sg:province":"Islas Baleares",
    "sg:website":"www.newsmallorca.com",
    "wof:name":"Fomento De Turismo De Mallorca",
    "wof:placetype":"venue"
},
  "geometry": {"coordinates":[2.646930933,39.5698204041],"type":"Point"}
}