{
  "type": "Feature",
  "properties": {
    "addr:full":"Carrer de Sant Josep, 36 Terrassa Barcelona 08221",
    "addr:housenumber":"36",
    "addr:postcode":"08221",
    "addr:street":"Carrer De Sant Josep",
    "iso:country":"ES",
    "sg:address":"Carrer de Sant Josep, 36",
    "sg:city":"Terrassa",
    "sg:orig_category":"Inmobiliaria (agencias)",
    "sg:phone":"+34 937 31 79 74",
    "sg:postcode":"08221",
    "sg:province":"Barcelona",
    "wof:name":"Gersidosa S.a.",
    "wof:placetype":"venue"
},
  "geometry": {"coordinates":[2.0146939754,41.5646514893],"type":"Point"}
}