{
  "type": "Feature",
  "properties": {
    "addr:full":"Calle de Santa Lucia, 4 Zaragoza Zaragoza 50003",
    "addr:housenumber":"4",
    "addr:postcode":"50003",
    "addr:street":"Calle De Santa Lucia",
    "iso:country":"ES",
    "sg:address":"Calle de Santa Lucia, 4",
    "sg:city":"Zaragoza",
    "sg:orig_category":"Cl\u00cdnicas Dentales",
    "sg:phone":"+34 976 44 01 18",
    "sg:postcode":"50003",
    "sg:province":"Zaragoza",
    "wof:name":"Clinica Dental Santa Lucia S.cv.",
    "wof:placetype":"venue"
},
  "geometry": {"coordinates":[-0.8901209831,41.6583061218],"type":"Point"}
}