{
  "type": "Feature",
  "properties": {
    "iso:country":"ES",
    "sg:address":"Calle de Castro De Oro, 34",
    "sg:city":"Madrid",
    "sg:orig_category":"Centros Empresariales",
    "sg:phone":"+34 914 60 59 69",
    "sg:postcode":"28019",
    "sg:province":"Madrid",
    "wof:name":"Druida Gestion Cultural S.l.",
    "wof:placetype":"venue"
},
  "geometry": {"coordinates":[-3.7271363735,40.3881568909],"type":"Point"}
}