{
  "type": "Feature",
  "properties": {
    "addr:full":"Rua Bola\u00d1o Rivadeneira, 22 Lugo Lugo 27001",
    "addr:housenumber":"22",
    "addr:postcode":"27001",
    "addr:street":"Rua Bolan\u0303O Rivadeneira",
    "iso:country":"ES",
    "sg:address":"Rua Bola\u00d1o Rivadeneira, 22",
    "sg:city":"Lugo",
    "sg:orig_category":"Medias Y Calcetines (al Por Menor)",
    "sg:phone":"+34 982 25 32 75",
    "sg:postcode":"27001",
    "sg:province":"Lugo",
    "wof:name":"Abuin Gomez Maria Soledad",
    "wof:placetype":"venue"
},
  "geometry": {"coordinates":[-7.559786,43.012615],"type":"Point"}
}