{
  "type": "Feature",
  "properties": {
    "iso:country":"ES",
    "sg:address":"Av Isidor Macabich, 27",
    "sg:city":"Eivissa",
    "sg:orig_category":"Asesor\u00cda De Formaci\u00d3n Y Gesti\u00d3n De Personal",
    "sg:phone":"+34 971 30 65 12",
    "sg:postcode":"07800",
    "sg:province":"Islas Baleares",
    "wof:name":"Asesoria Alonso Y Miguel Mestre Y Teresa Tur C.b.",
    "wof:placetype":"venue"
},
  "geometry": {"coordinates":[1.4275659323,38.9101829529],"type":"Point"}
}