{
  "type": "Feature",
  "properties": {
    "iso:country":"ES",
    "sg:address":"Av Concordia, 71",
    "sg:city":"Sabadell",
    "sg:orig_category":"Papeler\u00cdas, Librer\u00cdas",
    "sg:phone":"+34 937 16 66 84",
    "sg:postcode":"08206",
    "sg:province":"Barcelona",
    "sg:website":"www.papeleriapaes.com",
    "wof:name":"Alvarez Garcia Rosa",
    "wof:placetype":"venue"
},
  "geometry": {"coordinates":[2.0926856995,41.5613975525],"type":"Point"}
}