{
  "type": "Feature",
  "properties": {
    "addr:full":"Calle de Muro De La Misericordia, 14 Cordoba C\u00f3rdoba 14001",
    "addr:housenumber":"14",
    "addr:postcode":"14001",
    "addr:street":"Calle De Muro De La Misericordia;Co\u0301Rdoba",
    "iso:country":"ES",
    "sg:address":"Calle de Muro De La Misericordia, 14",
    "sg:city":"Cordoba",
    "sg:orig_category":"Administradores De Bienes Y Delegados De Comunidades De Propietarios",
    "sg:phone":"+34 957 48 33 54",
    "sg:postcode":"14001",
    "sg:province":"C\u00f3rdoba",
    "wof:name":"Mu\u00f1oz Almoguera Antonio Jesus",
    "wof:placetype":"venue"
},
  "geometry": {"coordinates":[-4.771905899,37.891746521],"type":"Point"}
}