{
  "type": "Feature",
  "properties": {
    "addr:full":"Av Creu Roja, 1 Cerdanyola Valles Barcelona 08290",
    "addr:housenumber":"1",
    "addr:postcode":"08290",
    "addr:street":"Av Creu Roja;Valles Barcelona",
    "iso:country":"ES",
    "sg:address":"Av Creu Roja, 1",
    "sg:city":"Cerdanyola Valles",
    "sg:orig_category":"Agencias Y Asesores De Publicidad",
    "sg:phone":"+34 935 86 52 78",
    "sg:postcode":"08290",
    "sg:province":"Barcelona",
    "wof:name":"Promedios Exclusivas De Publicidad S.l.",
    "wof:placetype":"venue"
},
  "geometry": {"coordinates":[2.1486101151,41.4935913086],"type":"Point"}
}