{
  "type": "Feature",
  "properties": {
    "iso:country":"ES",
    "sg:address":"Carr Pirineus, 14",
    "sg:city":"Fornells Selva",
    "sg:orig_category":"Arboricultura Y Producci\u00d3n De Frutas",
    "sg:phone":"+34 972 47 51 94",
    "sg:postcode":"17458",
    "sg:province":"Girona",
    "wof:name":"Indalfrutas S.l.",
    "wof:placetype":"venue"
},
  "geometry": {"coordinates":[2.8099250793,41.9300727844],"type":"Point"}
}