{
  "type": "Feature",
  "properties": {
    "addr:full":"Calle de Arturo Barea, 20 Merida Badajoz 06800",
    "addr:housenumber":"20",
    "addr:postcode":"06800",
    "addr:street":"Calle De Arturo Barea",
    "iso:country":"ES",
    "sg:address":"Calle de Arturo Barea, 20",
    "sg:city":"Merida",
    "sg:orig_category":"Doctores En Medicina",
    "sg:phone":"+34 924 31 00 23",
    "sg:postcode":"06800",
    "sg:province":"Badajoz",
    "wof:name":"Narvaez Bermejo Jose Maria",
    "wof:placetype":"venue"
},
  "geometry": {"coordinates":[-6.3353075981,38.9105224609],"type":"Point"}
}