{
  "type": "Feature",
  "properties": {
    "addr:full":"Calle de Concha (de La), 60 Aranjuez Madrid 28300",
    "addr:housenumber":"60",
    "addr:postcode":"28300",
    "addr:street":"Calle De Concha De La",
    "iso:country":"ES",
    "sg:address":"Calle de Concha (de La), 60",
    "sg:city":"Aranjuez",
    "sg:orig_category":"Agencias Y Agentes Comerciales, Representantes",
    "sg:phone":"+34 918 92 19 90",
    "sg:postcode":"28300",
    "sg:province":"Madrid",
    "wof:name":"Almendros Galvez Mercedes",
    "wof:placetype":"venue"
},
  "geometry": {"coordinates":[-3.6015088558,40.0286636353],"type":"Point"}
}