{
  "type": "Feature",
  "properties": {
    "iso:country":"ES",
    "sg:address":"Calle de Consolacion, 29",
    "sg:city":"Villamartin",
    "sg:orig_category":"Contenedores (mercanc\u00cdas)",
    "sg:phone":"+34 956 73 35 62",
    "sg:postcode":"11650",
    "sg:province":"C\u00e1diz",
    "wof:name":"Reguera Gallardo Vicente",
    "wof:placetype":"venue"
},
  "geometry": {"coordinates":[-5.6391434669,36.8579711914],"type":"Point"}
}