{
  "type": "Feature",
  "properties": {
    "addr:full":"Calle de Panueva, 55 Tafalla Navarra 31300",
    "addr:housenumber":"55",
    "addr:postcode":"31300",
    "addr:street":"Calle De Panueva",
    "iso:country":"ES",
    "sg:address":"Calle de Panueva, 55",
    "sg:city":"Tafalla",
    "sg:orig_category":"Empresarios",
    "sg:phone":"+34 948 70 06 81",
    "sg:postcode":"31300",
    "sg:province":"Navarra",
    "wof:name":"Bermudez Ezcurra Carlos",
    "wof:placetype":"venue"
},
  "geometry": {"coordinates":[-1.671538949,42.5346298218],"type":"Point"}
}