{
  "type": "Feature",
  "properties": {
    "iso:country":"ES",
    "sg:address":"Plaz Bandos, 6",
    "sg:city":"Salamanca",
    "sg:orig_category":"Aparcamientos (infraestructuras, Accesorios)",
    "sg:phone":"+34 923 21 86 27",
    "sg:postcode":"37002",
    "sg:province":"Salamanca",
    "wof:name":"Gomez Blazquez Flora",
    "wof:placetype":"venue"
},
  "geometry": {"coordinates":[-5.6647028923,40.9668159485],"type":"Point"}
}