{
  "type": "Feature",
  "properties": {
    "addr:full":"Calle de Calvario, 27 Monzon Huesca 22400",
    "addr:housenumber":"27",
    "addr:postcode":"22400",
    "addr:street":"Calle De Calvario",
    "iso:country":"ES",
    "sg:address":"Calle de Calvario, 27",
    "sg:city":"Monzon",
    "sg:orig_category":"Electricidad: Instaladores",
    "sg:phone":"+34 974 41 50 17",
    "sg:postcode":"22400",
    "sg:province":"Huesca",
    "wof:name":"Imdelec S.l.",
    "wof:placetype":"venue"
},
  "geometry": {"coordinates":[0.1931113005,41.9169578552],"type":"Point"}
}