{
  "type": "Feature",
  "properties": {
    "addr:full":"Carrer de Sabadell, 37 Rubi Barcelona 08191",
    "addr:housenumber":"37",
    "addr:postcode":"08191",
    "addr:street":"Carrer De Sabadell",
    "iso:country":"ES",
    "sg:address":"Carrer de Sabadell, 37",
    "sg:city":"Rubi",
    "sg:orig_category":"Perfumer\u00cda Y Cosm\u00c9tica (fabricaci\u00d3n, Al Por Mayor)",
    "sg:phone":"+34 936 99 50 13",
    "sg:postcode":"08191",
    "sg:province":"Barcelona",
    "wof:name":"Gonzalez Bermudez Ana Isabel",
    "wof:placetype":"venue"
},
  "geometry": {"coordinates":[2.0345909595,41.4962692261],"type":"Point"}
}