{
  "type": "Feature",
  "properties": {
    "iso:country":"ES",
    "sg:address":"Calle de Garcia De Vinuesa, 21",
    "sg:city":"Sevilla",
    "sg:orig_category":"Caf\u00c9s, Bares, Cervecer\u00cdas",
    "sg:phone":"+34 954 21 77 60",
    "sg:postcode":"41001",
    "sg:province":"Sevilla",
    "wof:name":"Belmejo Ledesma Emilia Valentina",
    "wof:placetype":"venue"
},
  "geometry": {"coordinates":[-5.9950652122,37.3863182068],"type":"Point"}
}