{
  "type": "Feature",
  "properties": {
    "addr:full":"Pase Castellana, 222 Madrid Madrid 28046",
    "addr:housenumber":"222",
    "addr:postcode":"28046",
    "addr:street":"Castellana",
    "iso:country":"ES",
    "sg:address":"Pase Castellana, 222",
    "sg:city":"Madrid",
    "sg:orig_category":"Periodistas Profesionales",
    "sg:phone":"+34 913 15 40 40",
    "sg:postcode":"28046",
    "sg:province":"Madrid",
    "wof:name":"Mo Chang Eduardo Sou Er",
    "wof:placetype":"venue"
},
  "geometry": {"coordinates":[-3.688131094,40.4685401917],"type":"Point"}
}