{
  "type": "Feature",
  "properties": {
    "iso:country":"ES",
    "sg:address":"Calle de Pintor Lopez Mezquita, 6",
    "sg:city":"Granada",
    "sg:orig_category":"Dietistas",
    "sg:phone":"+34 958 29 62 91",
    "sg:postcode":"18002",
    "sg:province":"Granada",
    "wof:name":"Productos Dieteticos Karma S.l.",
    "wof:placetype":"venue"
},
  "geometry": {"coordinates":[-3.6076250076,37.1771392822],"type":"Point"}
}