{
  "type": "Feature",
  "properties": {
    "iso:country":"ES",
    "sg:address":"Carrer de Tallers, 6",
    "sg:city":"Barcelona",
    "sg:orig_category":"Residencias De Turismo, Residencias Hoteleras",
    "sg:phone":"+34 933 01 71 68",
    "sg:postcode":"08001",
    "sg:province":"Barcelona",
    "wof:name":"Aliaga Garcia Alicia",
    "wof:placetype":"venue"
},
  "geometry": {"coordinates":[2.1700680256,41.3847007751],"type":"Point"}
}