{
  "type": "Feature",
  "properties": {
    "iso:country":"ES",
    "sg:address":"Carr La Bassa, 29",
    "sg:city":"Alcarras",
    "sg:orig_category":"Producci\u00d3n, Venta De Productos De Agricultura Biol\u00d3gica",
    "sg:phone":"+34 973 79 02 45",
    "sg:postcode":"25180",
    "sg:province":"Lleida",
    "wof:name":"Godia Jove Albert",
    "wof:placetype":"venue"
},
  "geometry": {"coordinates":[0.5282099843,41.5634155273],"type":"Point"}
}