{
  "type": "Feature",
  "properties": {
    "iso:country":"ES",
    "sg:address":"Calle de Perez Galdos, 24",
    "sg:city":"Santa Cruz De Tenerife",
    "sg:orig_category":"Muebles, Minoristas",
    "sg:phone":"+34 922 27 02 77",
    "sg:postcode":"38002",
    "sg:province":"Santa Cruz De Tenerife",
    "sg:website":"www.gentedelmar.com",
    "wof:name":"Gente Del Mar S.l.",
    "wof:placetype":"venue"
},
  "geometry": {"coordinates":[-16.2525920868,28.4678974152],"type":"Point"}
}