{
  "type": "Feature",
  "properties": {
    "iso:country":"ES",
    "sg:address":"Carrer de Besalu, 13",
    "sg:city":"Poligon Industrial Pla De La Bruguera",
    "sg:orig_category":"Rectificaci\u00d3n, Mecanizado, Fresado",
    "sg:phone":"+34 937 14 30 26",
    "sg:postcode":"08211",
    "sg:province":"Barcelona",
    "wof:name":"Gil Pendon Edmundo",
    "wof:placetype":"venue"
},
  "geometry": {"coordinates":[2.0857300758,41.6151885986],"type":"Point"}
}