{
  "type": "Feature",
  "properties": {
    "addr:full":"Ptda Negret, S/n Elda Alicante 03600",
    "addr:housenumber":"s",
    "addr:postcode":"03600",
    "addr:street":"Ptda Negret;/ N",
    "iso:country":"ES",
    "sg:address":"Ptda Negret, S/n",
    "sg:city":"Elda",
    "sg:orig_category":"Centros De Educaci\u00d3n Especial",
    "sg:phone":"+34 966 98 14 56",
    "sg:postcode":"03600",
    "sg:province":"Alicante",
    "wof:name":"Colegio Nacional Pintor Sorolla",
    "wof:placetype":"venue"
},
  "geometry": {"coordinates":[-0.7966089845,38.4770317078],"type":"Point"}
}