{
  "type": "Feature",
  "properties": {
    "addr:full":"Calle de Ubeda, 4 Torreperogil Ja\u00e9n 23320",
    "addr:housenumber":"4",
    "addr:postcode":"23320",
    "addr:street":"Calle De Ubeda",
    "iso:country":"ES",
    "sg:address":"Calle de Ubeda, 4",
    "sg:city":"Torreperogil",
    "sg:orig_category":"Cajas De Ahorro",
    "sg:phone":"+34 953 77 87 42",
    "sg:postcode":"23320",
    "sg:province":"Ja\u00e9n",
    "wof:name":"Caixa D'estalvis I Pensions De Barcelona",
    "wof:placetype":"venue"
},
  "geometry": {"coordinates":[-3.2908189297,38.0341300964],"type":"Point"}
}