{
  "type": "Feature",
  "properties": {
    "addr:full":"A Cancela, 5 Cancela Pontevedra 36143",
    "addr:housenumber":"5",
    "addr:postcode":"36143",
    "addr:street":"Cancela",
    "iso:country":"ES",
    "sg:address":"A Cancela, 5",
    "sg:city":"Cancela",
    "sg:orig_category":"Abogados Especialistas En Derecho Mercantil",
    "sg:phone":"+34 986 85 51 05",
    "sg:postcode":"36143",
    "sg:province":"Pontevedra",
    "wof:name":"Pongranit S.l.",
    "wof:placetype":"venue"
},
  "geometry": {"coordinates":[-8.6421194077,42.4087219238],"type":"Point"}
}