{
  "type": "Feature",
  "properties": {
    "iso:country":"ES",
    "sg:address":"Calle de Maestro Arrieta, 8",
    "sg:city":"Castellon",
    "sg:orig_category":"Molduras, Junquillos, Listones Y Molduras Perforadas",
    "sg:phone":"+34 964 24 76 29",
    "sg:postcode":"12006",
    "sg:province":"Castell\u00f3n",
    "wof:name":"Angato S.l.",
    "wof:placetype":"venue"
},
  "geometry": {"coordinates":[-0.0462386012,39.9783744812],"type":"Point"}
}