{
  "type": "Feature",
  "properties": {
    "addr:full":"Calle de Cuenca (de), 15 Humanes De Madrid Madrid 28970",
    "addr:housenumber":"15",
    "addr:postcode":"28970",
    "addr:street":"Calle De Cuenca De",
    "iso:country":"ES",
    "sg:address":"Calle de Cuenca (de), 15",
    "sg:city":"Humanes De Madrid",
    "sg:orig_category":"Negocio De Materiales De Construcci\u00d3n",
    "sg:phone":"+34 916 15 03 86",
    "sg:postcode":"28970",
    "sg:province":"Madrid",
    "wof:name":"Distribuciones Sayago De Gri\u00f1on S.l.",
    "wof:placetype":"venue"
},
  "geometry": {"coordinates":[-3.815420866,40.2746734619],"type":"Point"}
}