{
  "type": "Feature",
  "properties": {
    "addr:full":"Poli Industrial Las Casas, 312 Soria Soria 42005",
    "addr:housenumber":"312",
    "addr:postcode":"42005",
    "addr:street":"Casas",
    "iso:country":"ES",
    "sg:address":"Poli Industrial Las Casas, 312",
    "sg:city":"Soria",
    "sg:orig_category":"Muebles Y Accesorios Para Cocinas Y Cuartos De Ba\u00d1o (al Por Menor)",
    "sg:phone":"+34 975 22 81 35",
    "sg:postcode":"42005",
    "sg:province":"Soria",
    "wof:name":"Peyca Decoracion S.l.",
    "wof:placetype":"venue"
},
  "geometry": {"coordinates":[-2.4691669941,41.7646598816],"type":"Point"}
}