{
  "type": "Feature",
  "properties": {
    "iso:country":"ES",
    "sg:address":"Calle de Rincon, 5",
    "sg:city":"Teruel",
    "sg:orig_category":"Caf\u00c9s, Bares, Cervecer\u00cdas",
    "sg:phone":"+34 978 60 10 22",
    "sg:postcode":"44001",
    "sg:province":"Teruel",
    "wof:name":"Cafe Bar La Posada S.cv",
    "wof:placetype":"venue"
},
  "geometry": {"coordinates":[-1.1058620214,40.3440170288],"type":"Point"}
}