{
  "type": "Feature",
  "properties": {
    "addr:full":"Calle de Alfonso Xiii, 27 Guijuelo Salamanca 37770",
    "addr:housenumber":"27",
    "addr:postcode":"37770",
    "addr:street":"Calle De Alfonso Xiii",
    "iso:country":"ES",
    "sg:address":"Calle de Alfonso Xiii, 27",
    "sg:city":"Guijuelo",
    "sg:orig_category":"Promotores Constructores",
    "sg:phone":"+34 923 58 02 49",
    "sg:postcode":"37770",
    "sg:province":"Salamanca",
    "wof:name":"Lucas Obras Y Promociones S.l.",
    "wof:placetype":"venue"
},
  "geometry": {"coordinates":[-5.6705036163,40.5554885864],"type":"Point"}
}