{
  "type": "Feature",
  "properties": {
    "addr:full":"Carrer de Font De La Salut, 4 Sant Cristofol Les Fonts Girona 17800",
    "addr:housenumber":"4",
    "addr:postcode":"17800",
    "addr:street":"Carrer De Font De La Salut;Cristofol",
    "iso:country":"ES",
    "sg:address":"Carrer de Font De La Salut, 4",
    "sg:city":"Sant Cristofol Les Fonts",
    "sg:orig_category":"Fabricaci\u00d3n De Art\u00cdculos Y Ornamentos Religiosos",
    "sg:phone":"+34 972 26 23 72",
    "sg:postcode":"17800",
    "sg:province":"Girona",
    "wof:name":"Darne Garriga Luis",
    "wof:placetype":"venue"
},
  "geometry": {"coordinates":[2.4893848896,42.1809463501],"type":"Point"}
}