{
  "type": "Feature",
  "properties": {
    "addr:full":"Avda Constitucion De La, 12 Caceres C\u00e1ceres 10195",
    "addr:housenumber":"12",
    "addr:postcode":"10195",
    "addr:street":"Avda Constitucion De La;Ca\u0301Ceres",
    "iso:country":"ES",
    "sg:address":"Avda Constitucion De La, 12",
    "sg:city":"Caceres",
    "sg:orig_category":"Carnicer\u00cdas, Carnicer\u00cdas",
    "sg:phone":"+34 927 23 16 65",
    "sg:postcode":"10195",
    "sg:province":"C\u00e1ceres",
    "wof:name":"Caldito Jorge Claudia",
    "wof:placetype":"venue"
},
  "geometry": {"coordinates":[-6.3878917694,39.4517097473],"type":"Point"}
}