{
  "type": "Feature",
  "properties": {
    "iso:country":"ES",
    "sg:address":"Avda Ategorrieta De, 35",
    "sg:city":"Donostia-san Sebastian",
    "sg:orig_category":"Pescader\u00cdas (al Por Menor)",
    "sg:phone":"+34 943 27 47 81",
    "sg:postcode":"20013",
    "sg:province":"Guip\u00f9zcoa",
    "wof:name":"Argando\u00f1a Esnal Maria Lourdes",
    "wof:placetype":"venue"
},
  "geometry": {"coordinates":[-1.9677284956,43.3242263794],"type":"Point"}
}