{
  "type": "Feature",
  "properties": {
    "iso:country":"ES",
    "sg:address":"Plaz Juan Xxiii, 3",
    "sg:city":"Fortuna",
    "sg:orig_category":"Cajas De Ahorro",
    "sg:phone":"+34 968 68 62 85",
    "sg:postcode":"30620",
    "sg:province":"Murcia",
    "wof:name":"Caixa D'estalvis I Pensions De Barcelona",
    "wof:placetype":"venue"
},
  "geometry": {"coordinates":[-1.1227289438,38.179473877],"type":"Point"}
}