{
  "type": "Feature",
  "properties": {
    "iso:country":"ES",
    "sg:address":"Barr Sedillo (el), S/n",
    "sg:city":"Entrambasaguas",
    "sg:orig_category":"Maquinaria Para Industrias Diversas",
    "sg:phone":"+34 942 52 40 01",
    "sg:postcode":"39715",
    "sg:province":"Cantabria",
    "wof:name":"Fernandez Garcia Marcelo",
    "wof:placetype":"venue"
},
  "geometry": {"coordinates":[-3.6829760075,43.3787002563],"type":"Point"}
}