{
  "type": "Feature",
  "properties": {
    "addr:full":"Calle de Pau Casals, 6 Novelda Alicante 03660",
    "addr:housenumber":"6",
    "addr:postcode":"03660",
    "addr:street":"Calle De Pau Casals",
    "iso:country":"ES",
    "sg:address":"Calle de Pau Casals, 6",
    "sg:city":"Novelda",
    "sg:orig_category":"Electricidad: Instaladores",
    "sg:phone":"+34 965 60 61 14",
    "sg:postcode":"03660",
    "sg:province":"Alicante",
    "wof:name":"Eugenio Ferrandiz Instalaciones Electricas S.l",
    "wof:placetype":"venue"
},
  "geometry": {"coordinates":[-0.7681049705,38.3808174133],"type":"Point"}
}