{
  "type": "Feature",
  "properties": {
    "addr:full":"Ctra Arnedo, 5 Quel La Rioja 26570",
    "addr:housenumber":"5",
    "addr:postcode":"26570",
    "addr:street":"Ctra Arnedo;Rioja",
    "iso:country":"ES",
    "sg:address":"Ctra Arnedo, 5",
    "sg:city":"Quel",
    "sg:orig_category":"Supermercados Y Hipermercados",
    "sg:phone":"+34 941 39 20 33",
    "sg:postcode":"26570",
    "sg:province":"La Rioja",
    "wof:name":"Ibaez Calatayud Jose Antonio",
    "wof:placetype":"venue"
},
  "geometry": {"coordinates":[-2.0563650131,42.233341217],"type":"Point"}
}