{
  "type": "Feature",
  "properties": {
    "addr:full":"Calle de Pelicano, 10 Valladolid Valladolid 47012",
    "addr:housenumber":"10",
    "addr:postcode":"47012",
    "addr:street":"Calle De Pelicano",
    "iso:country":"ES",
    "sg:address":"Calle de Pelicano, 10",
    "sg:city":"Valladolid",
    "sg:orig_category":"Molduras, Junquillos, Listones Y Molduras Perforadas",
    "sg:phone":"+34 983 29 08 26",
    "sg:postcode":"47012",
    "sg:province":"Valladolid",
    "wof:name":"Cuesta Requejo Juan Jose",
    "wof:placetype":"venue"
},
  "geometry": {"coordinates":[-4.708963871,41.6463775635],"type":"Point"}
}