{
  "type": "Feature",
  "properties": {
    "addr:full":"Carrer de Poeta Pitarra, 28 Selva Negra Catalana Barcelona 08759",
    "addr:housenumber":"28",
    "addr:postcode":"08759",
    "addr:street":"Carrer De Poeta Pitarra",
    "iso:country":"ES",
    "sg:address":"Carrer de Poeta Pitarra, 28",
    "sg:city":"Selva Negra Catalana",
    "sg:orig_category":"Maquinaria Para Industrias Diversas",
    "sg:phone":"+34 936 83 05 43",
    "sg:postcode":"08759",
    "sg:province":"Barcelona",
    "wof:name":"Excavaciones Ayllon Vallirana S.l.",
    "wof:placetype":"venue"
},
  "geometry": {"coordinates":[1.9340959787,41.3752861023],"type":"Point"}
}