{
  "type": "Feature",
  "properties": {
    "iso:country":"ES",
    "sg:address":"Calle de Rodriguez De La Fuente, 25",
    "sg:city":"Alhaurin Torre",
    "sg:orig_category":"Ense\u00d1anza Variada",
    "sg:phone":"+34 952 41 71 27",
    "sg:postcode":"29130",
    "sg:province":"M\u00e1laga",
    "wof:name":"Spanish Teachers S.l.",
    "wof:placetype":"venue"
},
  "geometry": {"coordinates":[-4.5624489784,36.6583900452],"type":"Point"}
}