{
  "type": "Feature",
  "properties": {
    "iso:country":"ES",
    "sg:address":"Calle de Virgen De Regla, 5",
    "sg:city":"Olivares",
    "sg:orig_category":"Mec\u00c1nico Del Autom\u00d3vil",
    "sg:phone":"+34 954 11 03 14",
    "sg:postcode":"41804",
    "sg:province":"Sevilla",
    "wof:name":"Gavira Pomar Juan Antonio",
    "wof:placetype":"venue"
},
  "geometry": {"coordinates":[-6.1520681381,37.4187011719],"type":"Point"}
}