{
  "type": "Feature",
  "properties": {
    "iso:country":"ES",
    "sg:address":"Cmno Hondo, S/n",
    "sg:city":"Zamora",
    "sg:orig_category":"Materiales De Construcci\u00d3n (en General)",
    "sg:phone":"+34 980 53 65 66",
    "sg:postcode":"49027",
    "sg:province":"Zamora",
    "wof:name":"General De Hormigones S.a",
    "wof:placetype":"venue"
},
  "geometry": {"coordinates":[-5.7542390823,41.4904251099],"type":"Point"}
}