{
  "type": "Feature",
  "properties": {
    "addr:full":"Avda Marques De Rozalejo, 11 Dolores Murcia 30739",
    "addr:housenumber":"11",
    "addr:postcode":"30739",
    "addr:street":"Avda Marques De Rozalejo",
    "iso:country":"ES",
    "sg:address":"Avda Marques De Rozalejo, 11",
    "sg:city":"Dolores",
    "sg:orig_category":"Fotograf\u00cda Y Cine: Aparatos, Pel\u00cdculas Y Accesorios (fabricaci\u00d3n, Al Por Mayor)",
    "sg:phone":"+34 968 17 31 81",
    "sg:postcode":"30739",
    "sg:province":"Murcia",
    "wof:name":"Nilot Fotografia S.l.",
    "wof:placetype":"venue"
},
  "geometry": {"coordinates":[-0.8677279949,37.7769622803],"type":"Point"}
}