{
  "type": "Feature",
  "properties": {
    "iso:country":"ES",
    "sg:address":"Col Ciudad Jardin Del Rosario, 1",
    "sg:city":"Torrejon Ardoz",
    "sg:orig_category":"Molduras, Junquillos, Listones Y Molduras Perforadas",
    "sg:phone":"+34 916 75 10 18",
    "sg:postcode":"28850",
    "sg:province":"Madrid",
    "wof:name":"Palacin Barroso Teodoro",
    "wof:placetype":"venue"
},
  "geometry": {"coordinates":[-3.4694280624,40.4541473389],"type":"Point"}
}