{
  "type": "Feature",
  "properties": {
    "iso:country":"ES",
    "sg:address":"Pl Mil.lenari, S/n",
    "sg:city":"Vic",
    "sg:orig_category":"Fabricaci\u00d3n De Muebles",
    "sg:phone":"+34 938 89 22 53",
    "sg:postcode":"08500",
    "sg:province":"Barcelona",
    "sg:website":"www.galeriasdeltresillo.com",
    "wof:name":"Serimebel S.l.",
    "wof:placetype":"venue"
},
  "geometry": {"coordinates":[2.25041008,41.9338989258],"type":"Point"}
}