{
  "type": "Feature",
  "properties": {
    "addr:full":"Crt. De Alhambra, Km. 0382,7 La Solana Ciudad Real 13240",
    "addr:postcode":"13240",
    "addr:street":"Km. 0382,7 La",
    "iso:country":"ES",
    "sg:address":"Crt. De Alhambra, Km. 0382,7",
    "sg:city":"La Solana",
    "sg:orig_category":"Restaurantes",
    "sg:phone":"+34 926 69 60 06",
    "sg:postcode":"13240",
    "sg:province":"Ciudad Real",
    "sg:website":"www.saloneslordcarrington.com",
    "wof:name":"Montefran S.l.",
    "wof:placetype":"venue"
},
  "geometry": {"coordinates":[-3.2367699146,38.9386825562],"type":"Point"}
}