{
  "type": "Feature",
  "properties": {
    "addr:full":"Calle de Florencio Rodriguez, 23 Pola De Siero Asturias 33510",
    "addr:housenumber":"23",
    "addr:postcode":"33510",
    "addr:street":"Calle De Florencio Rodriguez",
    "iso:country":"ES",
    "sg:address":"Calle de Florencio Rodriguez, 23",
    "sg:city":"Pola De Siero",
    "sg:orig_category":"Arquitectos",
    "sg:phone":"+34 985 72 13 38",
    "sg:postcode":"33510",
    "sg:province":"Asturias",
    "wof:name":"Rodriguez Cueva Jose Gonzalo",
    "wof:placetype":"venue"
},
  "geometry": {"coordinates":[-5.659886837,43.392829895],"type":"Point"}
}