{
  "type": "Feature",
  "properties": {
    "iso:country":"ES",
    "sg:address":"Avda Primero De Julio, 55",
    "sg:city":"Valdepe\u00f1as",
    "sg:orig_category":"Sociedades, Compa\u00d1\u00cdas Aseguradoras",
    "sg:phone":"+34 926 32 22 08",
    "sg:postcode":"13300",
    "sg:province":"Ciudad Real",
    "wof:name":"Coseba 1986 Sociedad Limitada De Corredu",
    "wof:placetype":"venue"
},
  "geometry": {"coordinates":[-3.390873909,38.7579193115],"type":"Point"}
}