{
  "type": "Feature",
  "properties": {
    "addr:full":"Av Puerto Rico, 1 Tossa Girona 17320",
    "addr:housenumber":"1",
    "addr:postcode":"17320",
    "addr:street":"Av Puerto Rico",
    "iso:country":"ES",
    "sg:address":"Av Puerto Rico, 1",
    "sg:city":"Tossa",
    "sg:orig_category":"Distribuci\u00d3n De Petr\u00d3leo Y Derivados",
    "sg:phone":"+34 972 34 10 87",
    "sg:postcode":"17320",
    "sg:province":"Girona",
    "wof:name":"Palou Coll Assumpcio",
    "wof:placetype":"venue"
},
  "geometry": {"coordinates":[2.9282739162,41.7216644287],"type":"Point"}
}