{
  "type": "Feature",
  "properties": {
    "iso:country":"ES",
    "sg:address":"Plaz Espa\u00d1a, 15",
    "sg:city":"Monforte De Lemos",
    "sg:orig_category":"Abogados",
    "sg:phone":"+34 982 40 41 20",
    "sg:postcode":"27400",
    "sg:province":"Lugo",
    "wof:name":"Tapia Fernandez Maria Jesus",
    "wof:placetype":"venue"
},
  "geometry": {"coordinates":[-7.5130977631,42.5219039917],"type":"Point"}
}