{
  "type": "Feature",
  "properties": {
    "addr:full":"Camino De San Miguel, 1 Cilleruelo De Abajo Burgos 09349",
    "addr:housenumber":"1",
    "addr:postcode":"09349",
    "addr:street":"Camino De San Miguel",
    "iso:country":"ES",
    "sg:address":"Camino De San Miguel, 1",
    "sg:city":"Cilleruelo De Abajo",
    "sg:orig_category":"Empresas De Carpinter\u00cda Met\u00c1lica",
    "sg:phone":"+34 947 50 18 82",
    "sg:postcode":"09349",
    "sg:province":"Burgos",
    "wof:name":"Maeso Gonzalez Julio",
    "wof:placetype":"venue"
},
  "geometry": {"coordinates":[-3.7994170189,41.88621521],"type":"Point"}
}