{
  "type": "Feature",
  "properties": {
    "addr:full":"Avda Juan Carlos I, 45 Corralejo Las Palmas 35660",
    "addr:housenumber":"45",
    "addr:postcode":"35660",
    "addr:street":"Avda Juan Carlos I",
    "iso:country":"ES",
    "sg:address":"Avda Juan Carlos I, 45",
    "sg:city":"Corralejo",
    "sg:orig_category":"Ropa Para Ni\u00d1os (al Por Menor)",
    "sg:phone":"+34 928 86 71 77",
    "sg:postcode":"35660",
    "sg:province":"Las Palmas",
    "wof:name":"Kids Memory S.l.",
    "wof:placetype":"venue"
},
  "geometry": {"coordinates":[-13.8709812164,28.7389678955],"type":"Point"}
}