{
  "type": "Feature",
  "properties": {
    "iso:country":"ES",
    "sg:address":"Avda Martires, 20",
    "sg:city":"Carral",
    "sg:orig_category":"Electricidad: Instaladores",
    "sg:phone":"+34 981 67 12 02",
    "sg:postcode":"15175",
    "sg:province":"La Coru\u00f1a",
    "wof:name":"Instelga Souto S.l.",
    "wof:placetype":"venue"
},
  "geometry": {"coordinates":[-8.3554649353,43.2286605835],"type":"Point"}
}