{
  "type": "Feature",
  "properties": {
    "iso:country":"ES",
    "sg:address":"Calle de Inesperada, 5",
    "sg:city":"Aguilar De La Frontera",
    "sg:orig_category":"Comercio De Piezas De Recambio Y De Accesorios De Veh\u00cdculos, Veh\u00cdculos Industriales",
    "sg:phone":"+34 957 66 12 07",
    "sg:postcode":"14920",
    "sg:province":"C\u00f3rdoba",
    "wof:name":"Yago Leon Gabriel",
    "wof:placetype":"venue"
},
  "geometry": {"coordinates":[-4.6505699158,37.5132713318],"type":"Point"}
}