{
  "type": "Feature",
  "properties": {
    "addr:full":"Centro Comercial Copo, S/n Ejido Almer\u00eda 04700",
    "addr:housenumber":"s",
    "addr:postcode":"04700",
    "addr:street":"/ N Ejido Almeri\u0301A",
    "iso:country":"ES",
    "sg:address":"Centro Comercial Copo, S/n",
    "sg:city":"Ejido",
    "sg:orig_category":"Cajas Para Embalar",
    "sg:phone":"+34 950 48 91 08",
    "sg:postcode":"04700",
    "sg:province":"Almer\u00eda",
    "sg:website":"www.cajamar.es",
    "wof:name":"Cajamar",
    "wof:placetype":"venue"
},
  "geometry": {"coordinates":[-2.8176040649,36.7727012634],"type":"Point"}
}