{
  "type": "Feature",
  "properties": {
    "iso:country":"ES",
    "sg:address":"Calle de Cristo Rey, 16",
    "sg:city":"Andujar",
    "sg:orig_category":"Equipo De Refrigeraci\u00d3n Industrial",
    "sg:phone":"+34 953 50 16 73",
    "sg:postcode":"23740",
    "sg:province":"Ja\u00e9n",
    "wof:name":"Frio Industrial Garcia Jaen S.l.",
    "wof:placetype":"venue"
},
  "geometry": {"coordinates":[-4.0494828224,38.0412902832],"type":"Point"}
}