{
  "type": "Feature",
  "properties": {
    "iso:country":"ES",
    "sg:address":"Carrer de Varsovia, 31",
    "sg:city":"Barcelona",
    "sg:orig_category":"Fachadas",
    "sg:phone":"+34 934 33 45 63",
    "sg:postcode":"08041",
    "sg:province":"Barcelona",
    "wof:name":"Anper 2000 S.l.",
    "wof:placetype":"venue"
},
  "geometry": {"coordinates":[2.1758899689,41.4229431152],"type":"Point"}
}