{
  "type": "Feature",
  "properties": {
    "addr:full":"Calle de Hermano Pedro Ignacio, S/n Barriada San Gines Murcia 30203",
    "addr:housenumber":"s / n",
    "addr:postcode":"30203",
    "addr:street":"Calle De Hermano Pedro Ignacio;Barriada San",
    "iso:country":"ES",
    "sg:address":"Calle de Hermano Pedro Ignacio, S/n",
    "sg:city":"Barriada San Gines",
    "sg:orig_category":"Ense\u00d1anza: Profesiones Art\u00cdsticas",
    "sg:phone":"+34 968 50 56 98",
    "sg:postcode":"30203",
    "sg:province":"Murcia",
    "wof:name":"Alter Musici Escuela De Base Y Altos Estudios Musicales S.l.",
    "wof:placetype":"venue"
},
  "geometry": {"coordinates":[-1.1756933928,37.9549827576],"type":"Point"}
}