{
  "type": "Feature",
  "properties": {
    "iso:country":"ES",
    "sg:address":"Calle de Gran Via De Colon, 47",
    "sg:city":"Granada",
    "sg:orig_category":"Agencias De Trabajo Temporal",
    "sg:phone":"+34 958 80 43 94",
    "sg:postcode":"18001",
    "sg:province":"Granada",
    "sg:website":"www.adecco.es",
    "wof:name":"Adecco E.t.t. S.a.",
    "wof:placetype":"venue"
},
  "geometry": {"coordinates":[-3.6003820896,37.1809196472],"type":"Point"}
}