{
  "type": "Feature",
  "properties": {
    "addr:full":"Calle de Real De Gandia, 3 Valencia Valencia 46020",
    "addr:housenumber":"3",
    "addr:postcode":"46020",
    "addr:street":"Calle De Real De Gandia",
    "iso:country":"ES",
    "sg:address":"Calle de Real De Gandia, 3",
    "sg:city":"Valencia",
    "sg:orig_category":"Molduras, Junquillos, Listones Y Molduras Perforadas",
    "sg:phone":"+34 963 61 40 18",
    "sg:postcode":"46020",
    "sg:province":"Valencia",
    "wof:name":"Montesinos Lucas Petra",
    "wof:placetype":"venue"
},
  "geometry": {"coordinates":[-0.3547399938,39.4856567383],"type":"Point"}
}