{
  "type": "Feature",
  "properties": {
    "iso:country":"ES",
    "sg:address":"El Calvario, S/n",
    "sg:city":"Villama\u00f1an",
    "sg:orig_category":"Restaurantes",
    "sg:phone":"+34 987 76 72 79",
    "sg:postcode":"24234",
    "sg:province":"Le\u00f3n",
    "wof:name":"Reinoso Blanco Javier",
    "wof:placetype":"venue"
},
  "geometry": {"coordinates":[-5.6617040634,42.2405090332],"type":"Point"}
}