{
  "type": "Feature",
  "properties": {
    "iso:country":"ES",
    "sg:address":"Calle de Santillana, 2",
    "sg:city":"San Fernando De Henares",
    "sg:orig_category":"M\u00c1rmoles, Granitos Y Piedras Naturales",
    "sg:phone":"+34 916 73 18 78",
    "sg:postcode":"28830",
    "sg:province":"Madrid",
    "wof:name":"Carrasco Mena Dolores Carmen",
    "wof:placetype":"venue"
},
  "geometry": {"coordinates":[-3.5317230225,40.4242286682],"type":"Point"}
}