{
  "type": "Feature",
  "properties": {
    "iso:country":"ES",
    "sg:address":"Calle de Basanta Silva, 14",
    "sg:city":"Vilalba",
    "sg:classifiers":[
        {
            "category":"Autos & Motor Vehicles",
            "subcategory":"Automobile Sales",
            "type":"Retail Goods"
        }
    ],
    "sg:phone":"+34 982 51 02 26",
    "sg:postcode":"27800",
    "sg:province":"Lugo",
    "wof:name":"Garcia Y Boado S.l.",
    "wof:placetype":"venue"
},
  "geometry": {"coordinates":[-7.6797614098,43.2983055115],"type":"Point"}
}