{
  "type": "Feature",
  "properties": {
    "iso:country":"ES",
    "sg:address":"Calle de Le\u00d1eros, 33",
    "sg:city":"Madrid",
    "sg:orig_category":"Agricultura: Abastecimiento Y Cosechado (negocio)",
    "sg:phone":"+34 914 59 64 24",
    "sg:postcode":"28039",
    "sg:province":"Madrid",
    "wof:name":"Sociedad Cooperativa Limitada Valdelafuente",
    "wof:placetype":"venue"
},
  "geometry": {"coordinates":[-3.7099370956,40.4547729492],"type":"Point"}
}