{
  "type": "Feature",
  "properties": {
    "iso:country":"ES",
    "sg:address":"Avda Carlos V, 71",
    "sg:city":"Carrizal",
    "sg:orig_category":"Panader\u00cdas, Panader\u00cdas",
    "sg:phone":"+34 928 78 56 25",
    "sg:postcode":"35240",
    "sg:province":"Las Palmas",
    "wof:name":"Panificadora Haypan S.l.",
    "wof:placetype":"venue"
},
  "geometry": {"coordinates":[-15.404255867,27.9120883942],"type":"Point"}
}