{
  "type": "Feature",
  "properties": {
    "addr:full":"Carrer de Miquel Santandreu, 30 Palma Islas Baleares 07006",
    "addr:housenumber":"30",
    "addr:postcode":"07006",
    "addr:street":"Carrer De Miquel Santandreu",
    "iso:country":"ES",
    "sg:address":"Carrer de Miquel Santandreu, 30",
    "sg:city":"Palma",
    "sg:orig_category":"Resinas Sint\u00c9ticas (fabricaci\u00d3n, Al Por Mayor)",
    "sg:phone":"+34 971 77 01 53",
    "sg:postcode":"07006",
    "sg:province":"Islas Baleares",
    "wof:name":"Sistemas Adytec De Baleares S.l.",
    "wof:placetype":"venue"
},
  "geometry": {"coordinates":[2.6609990597,39.5671005249],"type":"Point"}
}