{
  "type": "Feature",
  "properties": {
    "addr:full":"Calle de Puerto De Piedrafita, 17 Ponferrada Le\u00f3n 24400",
    "addr:housenumber":"17",
    "addr:postcode":"24400",
    "addr:street":"Calle De Puerto De Piedrafita",
    "iso:country":"ES",
    "sg:address":"Calle de Puerto De Piedrafita, 17",
    "sg:city":"Ponferrada",
    "sg:orig_category":"Ebanister\u00cda",
    "sg:phone":"+34 987 42 96 25",
    "sg:postcode":"24400",
    "sg:province":"Le\u00f3n",
    "wof:name":"Arca Fernandez Jesus Aniceto",
    "wof:placetype":"venue"
},
  "geometry": {"coordinates":[-6.5954165459,42.5530586243],"type":"Point"}
}