{
  "type": "Feature",
  "properties": {
    "iso:country":"ES",
    "sg:address":"Calle de Marques De Vallejo, 2",
    "sg:city":"Logro\u00f1o",
    "sg:orig_category":"Farmacias",
    "sg:phone":"+34 941 25 17 38",
    "sg:postcode":"26001",
    "sg:province":"La Rioja",
    "wof:name":"Serrano Ortega Manuel",
    "wof:placetype":"venue"
},
  "geometry": {"coordinates":[-2.4455559254,42.4653778076],"type":"Point"}
}