{
  "type": "Feature",
  "properties": {
    "addr:full":"Calle de Jose Domingo De Olarte, 11 Vitoria-gasteiz \u00c1lava 01010",
    "addr:housenumber":"11",
    "addr:postcode":"01010",
    "addr:street":"Calle De Jose Domingo De Olarte",
    "iso:country":"ES",
    "sg:address":"Calle de Jose Domingo De Olarte, 11",
    "sg:city":"Vitoria-gasteiz",
    "sg:orig_category":"Peluquer\u00cdas, Peluquer\u00cda Mixta",
    "sg:phone":"+34 945 17 21 87",
    "sg:postcode":"01010",
    "sg:province":"\u00c1lava",
    "wof:name":"Tagore, Sc",
    "wof:placetype":"venue"
},
  "geometry": {"coordinates":[-2.6953060627,42.8585929871],"type":"Point"}
}