{
  "type": "Feature",
  "properties": {
    "addr:full":"Calle de Arco De Avila, 27 Arevalo \u00c1vila 05200",
    "addr:housenumber":"27",
    "addr:postcode":"05200",
    "addr:street":"Calle De Arco De Avila",
    "iso:country":"ES",
    "sg:address":"Calle de Arco De Avila, 27",
    "sg:city":"Arevalo",
    "sg:orig_category":"Alimentaci\u00d3n General (al Por Menor)",
    "sg:phone":"+34 920 30 04 02",
    "sg:postcode":"05200",
    "sg:province":"\u00c1vila",
    "wof:name":"Tejeda Garcia Jose",
    "wof:placetype":"venue"
},
  "geometry": {"coordinates":[-4.7187662125,41.0600738525],"type":"Point"}
}