{
  "type": "Feature",
  "properties": {
    "iso:country":"ES",
    "sg:address":"Calle de San Sebastian, 10",
    "sg:city":"Campillos",
    "sg:orig_category":"Dietistas",
    "sg:phone":"+34 952 72 20 68",
    "sg:postcode":"29320",
    "sg:province":"M\u00e1laga",
    "wof:name":"Campidiet S.l.",
    "wof:placetype":"venue"
},
  "geometry": {"coordinates":[-4.8637580872,37.0476951599],"type":"Point"}
}