{
  "type": "Feature",
  "properties": {
    "addr:full":"Carrer de Doctor Ferran, 85 Terrassa Barcelona 08226",
    "addr:housenumber":"85",
    "addr:postcode":"08226",
    "addr:street":"Carrer De Doctor Ferran",
    "iso:country":"ES",
    "sg:address":"Carrer de Doctor Ferran, 85",
    "sg:city":"Terrassa",
    "sg:orig_category":"Bisuter\u00cda, Joyer\u00cda, Relojer\u00cda (al Por Menor)",
    "sg:phone":"+34 937 35 74 59",
    "sg:postcode":"08226",
    "sg:province":"Barcelona",
    "wof:name":"Arteaga Lobo Victor Manuel",
    "wof:placetype":"venue"
},
  "geometry": {"coordinates":[2.0217018127,41.5758705139],"type":"Point"}
}