{
  "type": "Feature",
  "properties": {
    "iso:country":"ES",
    "sg:address":"Calle de Santo Domingo, 8",
    "sg:city":"G\u00fcimar",
    "sg:orig_category":"Cristaler\u00cdas",
    "sg:phone":"+34 922 51 12 96",
    "sg:postcode":"38500",
    "sg:province":"Santa Cruz De Tenerife",
    "wof:name":"Perez Mesa Maria Concepcion",
    "wof:placetype":"venue"
},
  "geometry": {"coordinates":[-16.411195755,28.3151950836],"type":"Point"}
}