{
  "type": "Feature",
  "properties": {
    "iso:country":"ES",
    "sg:address":"Calle de Bolseria, 7",
    "sg:city":"Valencia",
    "sg:orig_category":"Ropa De Trabajo Y Profesionales (fabricaci\u00d3n, Al Por Mayor)",
    "sg:phone":"+34 963 91 06 94",
    "sg:postcode":"46001",
    "sg:province":"Valencia",
    "wof:name":"Miquel Gresa Jose",
    "wof:placetype":"venue"
},
  "geometry": {"coordinates":[-0.3798894882,39.4751281738],"type":"Point"}
}