{
  "type": "Feature",
  "properties": {
    "iso:country":"ES",
    "sg:address":"Calle de Liceo Politecnico, 6",
    "sg:city":"Almoradi",
    "sg:orig_category":"Inmobiliaria (agencias)",
    "sg:phone":"+34 966 78 02 93",
    "sg:postcode":"03160",
    "sg:province":"Alicante",
    "wof:name":"Negocios Divarca S.l.",
    "wof:placetype":"venue"
},
  "geometry": {"coordinates":[-0.7917990088,38.1129493713],"type":"Point"}
}