{
  "type": "Feature",
  "properties": {
    "iso:country":"ES",
    "sg:address":"G.v. Corts Catalanes, 571",
    "sg:city":"Barcelona",
    "sg:orig_category":"Farmacias",
    "sg:phone":"+34 934 54 24 38",
    "sg:postcode":"08011",
    "sg:province":"Barcelona",
    "wof:name":"Thomas Pallerola Victoria",
    "wof:placetype":"venue"
},
  "geometry": {"coordinates":[2.1618640423,41.3850517273],"type":"Point"}
}