{
  "type": "Feature",
  "properties": {
    "addr:full":"Avda. De Cadiz, 6 Ronda M\u00e1laga 29400",
    "addr:housenumber":"6",
    "addr:postcode":"29400",
    "addr:street":"Avda. De Cadiz;Ronda Ma\u0301Laga",
    "iso:country":"ES",
    "sg:address":"Avda. De Cadiz, 6",
    "sg:city":"Ronda",
    "sg:orig_category":"Molduras, Junquillos, Listones Y Molduras Perforadas",
    "sg:phone":"+34 952 87 35 94",
    "sg:postcode":"29400",
    "sg:province":"M\u00e1laga",
    "wof:name":"Corbacho Bocanegra Leocadio",
    "wof:placetype":"venue"
},
  "geometry": {"coordinates":[-5.1587100029,36.7475776672],"type":"Point"}
}