{
  "type": "Feature",
  "properties": {
    "addr:full":"Pase Ygareda, 1 Cabez\u00f3n Sal Cantabria 39500",
    "addr:housenumber":"1",
    "addr:postcode":"39500",
    "addr:street":"Ygareda",
    "iso:country":"ES",
    "sg:address":"Pase Ygareda, 1",
    "sg:city":"Cabez\u00f3n Sal",
    "sg:orig_category":"Ense\u00d1anza: Idiomas",
    "sg:phone":"+34 942 70 18 40",
    "sg:postcode":"39500",
    "sg:province":"Cantabria",
    "wof:name":"Times School S.cv.",
    "wof:placetype":"venue"
},
  "geometry": {"coordinates":[-4.2374691963,43.3085784912],"type":"Point"}
}