{
  "type": "Feature",
  "properties": {
    "iso:country":"ES",
    "sg:address":"Calle de Artesania, S/n",
    "sg:city":"Mairena Aljarafe",
    "sg:orig_category":"Asesor\u00cda Sobre Comunicaci\u00d3n De Empresas",
    "sg:phone":"+34 954 18 60 26",
    "sg:postcode":"41927",
    "sg:province":"Sevilla",
    "wof:name":"Integral Xxi Asesores S.l.",
    "wof:placetype":"venue"
},
  "geometry": {"coordinates":[-6.0581874847,37.3562736511],"type":"Point"}
}