{
  "type": "Feature",
  "properties": {
    "iso:country":"ES",
    "sg:address":"Carrer de Cerdanya, 20",
    "sg:city":"S. Boi Llobregat",
    "sg:orig_category":"Seguridad En El Trabajo Y Prevenci\u00d3n De Riesgos Laborales",
    "sg:phone":"+34 936 52 50 09",
    "sg:postcode":"08830",
    "sg:province":"Barcelona",
    "sg:website":"www.mgo.es",
    "wof:name":"Grupo Mgo S.a.",
    "wof:placetype":"venue"
},
  "geometry": {"coordinates":[2.0432140827,41.3431549072],"type":"Point"}
}