{
  "type": "Feature",
  "properties": {
    "iso:country":"ES",
    "sg:address":"Calle de Santa Ana, 15",
    "sg:city":"Soraluze-placencia Armas",
    "sg:orig_category":"Fabricaci\u00d3n De Pernos, Tornillos Y Clavos",
    "sg:phone":"+34 943 75 10 62",
    "sg:postcode":"20590",
    "sg:province":"Guip\u00f9zcoa",
    "wof:name":"Aguirre Arrizabalaga Amaya",
    "wof:placetype":"venue"
},
  "geometry": {"coordinates":[-2.4122202396,43.1731338501],"type":"Point"}
}