{
  "type": "Feature",
  "properties": {
    "addr:full":"Calle de Rebollares, 13 Jerte C\u00e1ceres 10612",
    "addr:housenumber":"13",
    "addr:postcode":"10612",
    "addr:street":"Calle De Rebollares;Ca\u0301Ceres",
    "iso:country":"ES",
    "sg:address":"Calle de Rebollares, 13",
    "sg:city":"Jerte",
    "sg:orig_category":"Empresarios",
    "sg:phone":"+34 927 47 03 54",
    "sg:postcode":"10612",
    "sg:province":"C\u00e1ceres",
    "wof:name":"Hernandez Duran Emilio",
    "wof:placetype":"venue"
},
  "geometry": {"coordinates":[-5.7511849403,40.2232398987],"type":"Point"}
}