{
  "type": "Feature",
  "properties": {
    "iso:country":"ES",
    "sg:address":"Carrer de Major, 26",
    "sg:city":"Begues",
    "sg:orig_category":"Agencias De Viajes",
    "sg:phone":"+34 936 39 08 53",
    "sg:postcode":"08859",
    "sg:province":"Barcelona",
    "wof:name":"Savia Amadeus S.a.",
    "wof:placetype":"venue"
},
  "geometry": {"coordinates":[1.9228349924,41.330657959],"type":"Point"}
}