{
  "type": "Feature",
  "properties": {
    "iso:country":"ES",
    "sg:address":"Cmno Palmeral, 23",
    "sg:city":"Sangonera La Verde O Ermita Nueva",
    "sg:orig_category":"Empresas De Carpinter\u00cda De Madera",
    "sg:phone":"+34 968 86 90 88",
    "sg:postcode":"30833",
    "sg:province":"Murcia",
    "wof:name":"Hermanos Pe\u00f1alver S.c.",
    "wof:placetype":"venue"
},
  "geometry": {"coordinates":[-1.2069989443,37.9333190918],"type":"Point"}
}