{
  "type": "Feature",
  "properties": {
    "iso:country":"ES",
    "sg:address":"Calle de Paz, 11",
    "sg:city":"Madrid",
    "sg:orig_category":"Teatros Y Salas De Espect\u00c1culos",
    "sg:phone":"+34 915 31 83 11",
    "sg:postcode":"28012",
    "sg:province":"Madrid",
    "sg:website":"www.madrid.org",
    "wof:name":"Teatro Albeniz",
    "wof:placetype":"venue"
},
  "geometry": {"coordinates":[-3.7040328979,40.4154205322],"type":"Point"}
}