{
  "type": "Feature",
  "properties": {
    "addr:full":"Cmno Torres (las), 19 Zaragoza Zaragoza 50008",
    "addr:housenumber":"19",
    "addr:postcode":"50008",
    "addr:street":"Cmno Torres Las",
    "iso:country":"ES",
    "sg:address":"Cmno Torres (las), 19",
    "sg:city":"Zaragoza",
    "sg:orig_category":"Electrodom\u00c9sticos (al Por Menor)",
    "sg:phone":"+34 976 48 12 65",
    "sg:postcode":"50008",
    "sg:province":"Zaragoza",
    "wof:name":"Electrodomesticos Europa S. A.",
    "wof:placetype":"venue"
},
  "geometry": {"coordinates":[-0.8753070235,41.6457290649],"type":"Point"}
}