{
  "type": "Feature",
  "properties": {
    "iso:country":"ES",
    "sg:address":"Carretera Lago, S/n",
    "sg:city":"Galende",
    "sg:orig_category":"Estudios Y Construcci\u00d3n De Acuarios Y Viveros",
    "sg:phone":"+34 980 62 67 70",
    "sg:postcode":"49360",
    "sg:province":"Zamora",
    "wof:name":"Blanco Villasante Manuel Francisco",
    "wof:placetype":"venue"
},
  "geometry": {"coordinates":[-6.6617341042,42.1040039062],"type":"Point"}
}