{
  "type": "Feature",
  "properties": {
    "addr:full":"Av Pas D'arro, 23 Vielha Lleida 25530",
    "addr:housenumber":"23",
    "addr:postcode":"25530",
    "addr:street":"Av Pas D'Arro",
    "iso:country":"ES",
    "sg:address":"Av Pas D'arro, 23",
    "sg:city":"Vielha",
    "sg:orig_category":"Molduras, Junquillos, Listones Y Molduras Perforadas",
    "sg:phone":"+34 973 64 24 49",
    "sg:postcode":"25530",
    "sg:province":"Lleida",
    "wof:name":"Garcia Castro Carlos",
    "wof:placetype":"venue"
},
  "geometry": {"coordinates":[0.7975779772,42.7008934021],"type":"Point"}
}