{
  "type": "Feature",
  "properties": {
    "addr:full":"Carrer de Miquel Sants Olive, 21 Palma Islas Baleares 07011",
    "addr:housenumber":"21",
    "addr:postcode":"07011",
    "addr:street":"Carrer De Miquel Sants Olive",
    "iso:country":"ES",
    "sg:address":"Carrer de Miquel Sants Olive, 21",
    "sg:city":"Palma",
    "sg:orig_category":"Agencias De Viajes",
    "sg:phone":"+34 971 45 32 11",
    "sg:postcode":"07011",
    "sg:province":"Islas Baleares",
    "sg:website":"www.halconviajes.com",
    "wof:name":"Viajes Halcon S.a.",
    "wof:placetype":"venue"
},
  "geometry": {"coordinates":[2.6421129704,39.5799102783],"type":"Point"}
}