{
  "type": "Feature",
  "properties": {
    "addr:full":"Ctra. Escorial, Km. 0036,0 Las Rozas Madrid 28230",
    "addr:postcode":"28230",
    "addr:street":"Ctra. Escorial Km. 0036,0",
    "iso:country":"ES",
    "sg:address":"Ctra. Escorial, Km. 0036,0",
    "sg:city":"Las Rozas",
    "sg:orig_category":"Ingenier\u00cda, Centros De Estudios (diversos)",
    "sg:phone":"+34 916 37 13 70",
    "sg:postcode":"28230",
    "sg:province":"Madrid",
    "wof:name":"Europa De Construcciones S.l.",
    "wof:placetype":"venue"
},
  "geometry": {"coordinates":[-3.8913800716,40.5247497559],"type":"Point"}
}