{
  "type": "Feature",
  "properties": {
    "iso:country":"ES",
    "sg:address":"Carr D'hernan Cortes, 7",
    "sg:city":"Benicarlo",
    "sg:orig_category":"Alquiler De V\u00cddeo",
    "sg:phone":"+34 964 47 56 02",
    "sg:postcode":"12580",
    "sg:province":"Castell\u00f3n",
    "wof:name":"Videoteca Norte S.l.",
    "wof:placetype":"venue"
},
  "geometry": {"coordinates":[0.4265680015,40.4175758362],"type":"Point"}
}