{
  "type": "Feature",
  "properties": {
    "iso:country":"ES",
    "sg:address":"Avda Juan Carlos I, 2",
    "sg:city":"Estepona",
    "sg:orig_category":"M\u00c9dicos: Estomatolog\u00cda",
    "sg:phone":"+34 952 80 31 17",
    "sg:postcode":"29680",
    "sg:province":"M\u00e1laga",
    "wof:name":"Alvarado Montoro Francisco Javier",
    "wof:placetype":"venue"
},
  "geometry": {"coordinates":[-5.1524500847,36.4253883362],"type":"Point"}
}