{
  "type": "Feature",
  "properties": {
    "addr:full":"Pl Josep Freixa I Argemi, 9 Terrassa Barcelona 08224",
    "addr:housenumber":"9",
    "addr:postcode":"08224",
    "addr:street":"Pl;Argemi",
    "iso:country":"ES",
    "sg:address":"Pl Josep Freixa I Argemi, 9",
    "sg:city":"Terrassa",
    "sg:orig_category":"Inmobiliaria (agencias)",
    "sg:phone":"+34 937 33 05 56",
    "sg:postcode":"08224",
    "sg:province":"Barcelona",
    "wof:name":"Baltres S.l.",
    "wof:placetype":"venue"
},
  "geometry": {"coordinates":[2.0046310425,41.5630950928],"type":"Point"}
}