{
  "type": "Feature",
  "properties": {
    "iso:country":"ES",
    "sg:address":"Calle de Gomez Ferrer, 74",
    "sg:city":"Torrent",
    "sg:orig_category":"Albergues",
    "sg:phone":"+34 961 55 45 53",
    "sg:postcode":"46900",
    "sg:province":"Valencia",
    "wof:name":"Rivodigo Gimenez Juan",
    "wof:placetype":"venue"
},
  "geometry": {"coordinates":[-0.462906003,39.4405097961],"type":"Point"}
}