{
  "type": "Feature",
  "properties": {
    "addr:full":"Calle de Herreros, 5 Ciudad Rodrigo Salamanca 37500",
    "addr:housenumber":"5",
    "addr:postcode":"37500",
    "addr:street":"Calle De Herreros",
    "iso:country":"ES",
    "sg:address":"Calle de Herreros, 5",
    "sg:city":"Ciudad Rodrigo",
    "sg:orig_category":"Alquiler De Camiones Y Veh\u00cdculos Industriales",
    "sg:phone":"+34 923 46 06 21",
    "sg:postcode":"37500",
    "sg:province":"Salamanca",
    "wof:name":"Carlos Vazquez S.l.",
    "wof:placetype":"venue"
},
  "geometry": {"coordinates":[-6.526099205,40.6095848083],"type":"Point"}
}