{
  "type": "Feature",
  "properties": {
    "iso:country":"ES",
    "sg:address":"Ctra Madrid, Km. 0097,0",
    "sg:city":"Corella",
    "sg:orig_category":"Comerciantes Al Por Mayor De Vinos, Licores Y Alcoholes",
    "sg:phone":"+34 948 40 19 83",
    "sg:postcode":"31591",
    "sg:province":"Navarra",
    "wof:name":"Vi\u00f1edos Del Camino Real S.a.",
    "wof:placetype":"venue"
},
  "geometry": {"coordinates":[-1.7791907787,42.1124992371],"type":"Point"}
}