{
  "type": "Feature",
  "properties": {
    "iso:country":"ES",
    "sg:address":"Calle de Cerro De Valdemartin, 12",
    "sg:city":"Madrid",
    "sg:orig_category":"Procuradores",
    "sg:phone":"+34 913 72 02 33",
    "sg:postcode":"28034",
    "sg:province":"Madrid",
    "wof:name":"Ortiz Gutierrez Maria Cruz",
    "wof:placetype":"venue"
},
  "geometry": {"coordinates":[-3.7070763111,40.4897613525],"type":"Point"}
}