{
  "type": "Feature",
  "properties": {
    "addr:full":"Calle de Maldonado, 14 Madrid Madrid 28006",
    "addr:housenumber":"14",
    "addr:postcode":"madrid;28006",
    "addr:street":"Calle De Maldonado",
    "iso:country":"ES",
    "sg:address":"Calle de Maldonado, 14",
    "sg:city":"Madrid",
    "sg:orig_category":"Restaurantes",
    "sg:phone":"+34 914 35 50 45",
    "sg:postcode":"28006",
    "sg:province":"Madrid",
    "wof:name":"Corogaba S.l.",
    "wof:placetype":"venue"
},
  "geometry": {"coordinates":[-3.6839580536,40.4337844849],"type":"Point"}
}