{
  "type": "Feature",
  "properties": {
    "iso:country":"ES",
    "sg:address":"Calle de Perez Diaz, 47",
    "sg:city":"Victoria Acentejo",
    "sg:orig_category":"Florister\u00cdas",
    "sg:phone":"+34 922 58 23 24",
    "sg:postcode":"38380",
    "sg:province":"Santa Cruz De Tenerife",
    "wof:name":"Govea Afonso Maria Del Mar",
    "wof:placetype":"venue"
},
  "geometry": {"coordinates":[-16.4696655273,28.4344177246],"type":"Point"}
}