{
  "type": "Feature",
  "properties": {
    "iso:country":"ES",
    "sg:address":"Plaz Santiago, 4",
    "sg:city":"Gibraleon",
    "sg:orig_category":"Alquiler De Casas Y Habitaciones Amuebladas",
    "sg:phone":"+34 959 30 02 00",
    "sg:postcode":"21500",
    "sg:province":"Huelva",
    "wof:name":"Asociacion De Obras Cristianas",
    "wof:placetype":"venue"
},
  "geometry": {"coordinates":[-6.9732608795,37.3763008118],"type":"Point"}
}