{
  "type": "Feature",
  "properties": {
    "iso:country":"ES",
    "sg:address":"Calle de Independencia, 9",
    "sg:city":"Tomelloso",
    "sg:orig_category":"Electrodom\u00c9sticos (al Por Menor)",
    "sg:phone":"+34 926 50 10 64",
    "sg:postcode":"13700",
    "sg:province":"Ciudad Real",
    "sg:website":"www.milar.es",
    "wof:name":"La Monta\u00d1a Digital Sl",
    "wof:placetype":"venue"
},
  "geometry": {"coordinates":[-3.0200750828,39.1553001404],"type":"Point"}
}