{
  "type": "Feature",
  "properties": {
    "iso:country":"ES",
    "sg:address":"Calle de Ciro Alegria, 17",
    "sg:city":"Malaga",
    "sg:orig_category":"Bordado, Marcado A Medida",
    "sg:phone":"+34 952 96 07 56",
    "sg:postcode":"29004",
    "sg:province":"M\u00e1laga",
    "wof:name":"Arizona Red S.l.",
    "wof:placetype":"venue"
},
  "geometry": {"coordinates":[-4.4810199738,36.6950378418],"type":"Point"}
}