{
  "type": "Feature",
  "properties": {
    "addr:full":"Calle de Colombia, 3 Toledo Toledo 45004",
    "addr:housenumber":"3",
    "addr:postcode":"45004",
    "addr:street":"Calle De Colombia",
    "iso:country":"ES",
    "sg:address":"Calle de Colombia, 3",
    "sg:city":"Toledo",
    "sg:orig_category":"Agencias De Viajes",
    "sg:phone":"+34 925 25 51 21",
    "sg:postcode":"45004",
    "sg:province":"Toledo",
    "sg:website":"www.marsans.es",
    "wof:name":"Viajes Marsans S.a.",
    "wof:placetype":"venue"
},
  "geometry": {"coordinates":[-4.0310320854,39.866191864],"type":"Point"}
}