{
  "type": "Feature",
  "properties": {
    "addr:full":"Calle de Mendibile, 7 Leioa Vizcaya 48940",
    "addr:housenumber":"7",
    "addr:postcode":"48940",
    "addr:street":"Calle De Mendibile",
    "iso:country":"ES",
    "sg:address":"Calle de Mendibile, 7",
    "sg:city":"Leioa",
    "sg:orig_category":"Productos Qu\u00cdmicos (fabricaci\u00d3n, Al Por Mayor)",
    "sg:phone":"+34 944 02 20 56",
    "sg:postcode":"48940",
    "sg:province":"Vizcaya",
    "wof:name":"Suministros Medicos Susana Lucas,s.l.",
    "wof:placetype":"venue"
},
  "geometry": {"coordinates":[-2.9822030067,43.3249473572],"type":"Point"}
}