{
  "type": "Feature",
  "properties": {
    "iso:country":"ES",
    "sg:address":"Calle de Hnos Espinosa Alfonso, 43",
    "sg:city":"Santa Maria Aguila",
    "sg:orig_category":"Panader\u00cdas, Panader\u00cdas",
    "sg:phone":"+34 950 58 03 60",
    "sg:postcode":"04710",
    "sg:province":"Almer\u00eda",
    "wof:name":"Pasteleria Dulce Sara S.r.l.l.",
    "wof:placetype":"venue"
},
  "geometry": {"coordinates":[-2.774214983,36.781463623],"type":"Point"}
}