{
  "type": "Feature",
  "properties": {
    "iso:country":"ES",
    "sg:address":"Calle de San Raimundo, 1",
    "sg:city":"Madrid",
    "sg:orig_category":"Arquitectos",
    "sg:phone":"+34 914 59 60 35",
    "sg:postcode":"28039",
    "sg:province":"Madrid",
    "wof:name":"Estudio Y Estrategia En Obra S.l.",
    "wof:placetype":"venue"
},
  "geometry": {"coordinates":[-3.703305006,40.4518585205],"type":"Point"}
}