{
  "type": "Feature",
  "properties": {
    "addr:full":"Julio Urkijo Etorbidea, 10 Azkoitia Guip\u00f9zcoa 20720",
    "addr:housenumber":"10",
    "addr:postcode":"20720",
    "addr:street":"Julio Urkijo Etorbidea;Guipu\u0300Zcoa",
    "iso:country":"ES",
    "sg:address":"Julio Urkijo Etorbidea, 10",
    "sg:city":"Azkoitia",
    "sg:orig_category":"Reposter\u00cdas",
    "sg:phone":"+34 943 85 06 27",
    "sg:postcode":"20720",
    "sg:province":"Guip\u00f9zcoa",
    "wof:name":"Landakanda Okindegia, C.b.",
    "wof:placetype":"venue"
},
  "geometry": {"coordinates":[-2.3083329201,43.1777992249],"type":"Point"}
}