{
  "type": "Feature",
  "properties": {
    "addr:full":"Calle de Nazario Calonge (de), 5 San Fernando De Henares Madrid 28830",
    "addr:postcode":"28830",
    "addr:street":"Calle De Nazario;De 5",
    "iso:country":"ES",
    "sg:address":"Calle de Nazario Calonge (de), 5",
    "sg:city":"San Fernando De Henares",
    "sg:orig_category":"Producci\u00d3n, Venta De Productos De Agricultura Biol\u00d3gica",
    "sg:phone":"+34 916 71 05 31",
    "sg:postcode":"28830",
    "sg:province":"Madrid",
    "wof:name":"Agricola Montesinos S.l.",
    "wof:placetype":"venue"
},
  "geometry": {"coordinates":[-3.5282707214,40.4264831543],"type":"Point"}
}