{
  "type": "Feature",
  "properties": {
    "iso:country":"ES",
    "sg:address":"Balanguera(pol Ind El Pla), 21",
    "sg:city":"Ontinyent",
    "sg:orig_category":"Electricidad: Instaladores",
    "sg:phone":"+34 962 91 00 06",
    "sg:postcode":"46870",
    "sg:province":"Valencia",
    "wof:name":"Romovi Electricas S.l.",
    "wof:placetype":"venue"
},
  "geometry": {"coordinates":[-0.5839009881,38.8245162964],"type":"Point"}
}