{
  "type": "Feature",
  "properties": {
    "iso:country":"ES",
    "sg:address":"Carrer de Marinada, 11",
    "sg:city":"Cala Romana",
    "sg:orig_category":"M\u00c9dicos: Cirug\u00cda Ortop\u00c9dica Y Traumatolog\u00cda",
    "sg:phone":"+34 977 20 73 39",
    "sg:postcode":"43007",
    "sg:province":"Tarragona",
    "wof:name":"Melia Avia Victor",
    "wof:placetype":"venue"
},
  "geometry": {"coordinates":[1.2932089567,41.1303329468],"type":"Point"}
}