{
  "type": "Feature",
  "properties": {
    "iso:country":"ES",
    "sg:address":"Av Diagonal, 10",
    "sg:city":"Gava",
    "sg:orig_category":"Empresas De Limpieza",
    "sg:phone":"+34 936 62 50 16",
    "sg:postcode":"08850",
    "sg:province":"Barcelona",
    "wof:name":"Servi Cris S.l.",
    "wof:placetype":"venue"
},
  "geometry": {"coordinates":[1.9988720417,41.3047561646],"type":"Point"}
}