{
  "type": "Feature",
  "properties": {
    "iso:country":"ES",
    "sg:address":"Calle de Godofredo Ortega Y Mu\u00d1oz, S/n",
    "sg:city":"Badajoz",
    "sg:orig_category":"Asociaciones Humanitarias, De Cooperaci\u00d3n, De Acci\u00d3n Social",
    "sg:phone":"+34 924 20 77 13",
    "sg:postcode":"06011",
    "sg:province":"Badajoz",
    "sg:website":"www.aoex.org",
    "wof:name":"Asociacion Oncologica Extreme\u00f1a",
    "wof:placetype":"venue"
},
  "geometry": {"coordinates":[-6.9841775894,38.8678436279],"type":"Point"}
}