{
  "type": "Feature",
  "properties": {
    "iso:country":"ES",
    "sg:address":"Calle de Antonio Machado, 52",
    "sg:city":"Cabezas S. Juan",
    "sg:orig_category":"Ropa Para Se\u00d1oras (al Por Menor)",
    "sg:phone":"+34 955 87 04 27",
    "sg:postcode":"41730",
    "sg:province":"Sevilla",
    "wof:name":"Quiros Guisado Milagrosa",
    "wof:placetype":"venue"
},
  "geometry": {"coordinates":[-5.9400081635,36.9831199646],"type":"Point"}
}