{
  "type": "Feature",
  "properties": {
    "addr:full":"Calle de Julio Verne, 6 Malaga M\u00e1laga 29010",
    "addr:housenumber":"6",
    "addr:postcode":"29010",
    "addr:street":"Calle De Julio Verne;Ma\u0301Laga",
    "iso:country":"ES",
    "sg:address":"Calle de Julio Verne, 6",
    "sg:city":"Malaga",
    "sg:orig_category":"Caf\u00c9s, Bares, Cervecer\u00cdas",
    "sg:phone":"+34 952 61 07 04",
    "sg:postcode":"29010",
    "sg:province":"M\u00e1laga",
    "wof:name":"Moreno Gonzalez Silvia",
    "wof:placetype":"venue"
},
  "geometry": {"coordinates":[-4.4661769867,36.7332000732],"type":"Point"}
}