{
  "type": "Feature",
  "properties": {
    "addr:full":"Nueva, 20 Lucena C\u00f3rdoba 14900",
    "addr:housenumber":"20",
    "addr:postcode":"14900",
    "addr:street":"Nueva",
    "iso:country":"ES",
    "sg:address":"Nueva, 20",
    "sg:city":"Lucena",
    "sg:orig_category":"Arquitectos",
    "sg:phone":"+34 957 50 02 93",
    "sg:postcode":"14900",
    "sg:province":"C\u00f3rdoba",
    "wof:name":"Arquiluc Estudio De Arquitectura C.b.",
    "wof:placetype":"venue"
},
  "geometry": {"coordinates":[-4.4855804443,37.4085769653],"type":"Point"}
}