{
  "type": "Feature",
  "properties": {
    "addr:full":"Calle de Nanclares De Oca, 40 Madrid Madrid 28022",
    "addr:housenumber":"40",
    "addr:postcode":"madrid;28022",
    "addr:street":"Calle De Nanclares De Oca",
    "iso:country":"ES",
    "sg:address":"Calle de Nanclares De Oca, 40",
    "sg:city":"Madrid",
    "sg:classifiers":[
        {
            "category":"Professional",
            "subcategory":"Management & Consulting",
            "type":"Services"
        }
    ],
    "sg:phone":"+34 917 47 67 19",
    "sg:postcode":"28022",
    "sg:province":"Madrid",
    "sg:tags":[
        "asesor\u00cda",
        "en",
        "marketing"
    ],
    "wof:name":"Oca Gold S.l.",
    "wof:placetype":"venue"
},
  "geometry": {"coordinates":[-3.5744819641,40.4462928772],"type":"Point"}
}