{
  "type": "Feature",
  "properties": {
    "addr:full":"Calle de Valdes Pumarino, 17 Candas Asturias 33430",
    "addr:housenumber":"17",
    "addr:postcode":"33430",
    "addr:street":"Calle De Valdes Pumarino",
    "iso:country":"ES",
    "sg:address":"Calle de Valdes Pumarino, 17",
    "sg:city":"Candas",
    "sg:orig_category":"Caf\u00c9s, Bares, Cervecer\u00cdas",
    "sg:phone":"+34 985 87 03 04",
    "sg:postcode":"33430",
    "sg:province":"Asturias",
    "wof:name":"Hevia Cueto Marta Maria",
    "wof:placetype":"venue"
},
  "geometry": {"coordinates":[-5.7639107704,43.5901603699],"type":"Point"}
}