{
  "type": "Feature",
  "properties": {
    "addr:full":"Pg Golf (del), 8 Gualta Girona 17257",
    "addr:postcode":"17257",
    "iso:country":"ES",
    "sg:address":"Pg Golf (del), 8",
    "sg:city":"Gualta",
    "sg:orig_category":"Asociaciones Y Clubs Deportivos",
    "sg:phone":"+34 972 75 96 16",
    "sg:postcode":"17257",
    "sg:province":"Girona",
    "wof:name":"Gorina Trias Ramon",
    "wof:placetype":"venue"
},
  "geometry": {"coordinates":[3.1034579277,42.0297164917],"type":"Point"}
}