{
  "type": "Feature",
  "properties": {
    "addr:full":"Carrer de Cristofor Colom, 51 Cambrils Tarragona 43850",
    "addr:housenumber":"51",
    "addr:postcode":"43850",
    "addr:street":"Carrer De Cristofor Colom",
    "iso:country":"ES",
    "sg:address":"Carrer de Cristofor Colom, 51",
    "sg:city":"Cambrils",
    "sg:orig_category":"Asesor\u00cda Fiscal Y Jur\u00cddica",
    "sg:phone":"+34 977 36 53 58",
    "sg:postcode":"43850",
    "sg:province":"Tarragona",
    "wof:name":"Pujals & Cia.assessors S.l.",
    "wof:placetype":"venue"
},
  "geometry": {"coordinates":[1.0614880323,41.0680503845],"type":"Point"}
}