{
  "type": "Feature",
  "properties": {
    "iso:country":"ES",
    "sg:address":"Calle de Barcelo, 4",
    "sg:city":"Grao",
    "sg:orig_category":"Plomeros",
    "sg:phone":"+34 964 28 36 56",
    "sg:postcode":"12100",
    "sg:province":"Castell\u00f3n",
    "wof:name":"Galmes Olivares Antonio Jose",
    "wof:placetype":"venue"
},
  "geometry": {"coordinates":[0.0129517,39.9724121094],"type":"Point"}
}