{
  "type": "Feature",
  "properties": {
    "iso:country":"ES",
    "sg:address":"Ptda Pe\u00f1alva, 1",
    "sg:city":"Pego",
    "sg:orig_category":"Aguas (distribuci\u00d3n, Servicios)",
    "sg:phone":"+34 965 57 29 04",
    "sg:postcode":"03780",
    "sg:province":"Alicante",
    "wof:name":"Manantial De Pe\u00d1alba S.l.",
    "wof:placetype":"venue"
},
  "geometry": {"coordinates":[-0.1150880009,38.8428840637],"type":"Point"}
}