{
  "type": "Feature",
  "properties": {
    "addr:full":"Vedra, S/n Vedra La Coru\u00f1a 15885",
    "addr:housenumber":"s / n",
    "addr:postcode":"15885",
    "addr:street":"Vedra;La Corun\u0303A",
    "iso:country":"ES",
    "sg:address":"Vedra, S/n",
    "sg:city":"Vedra",
    "sg:orig_category":"Frutas Y Legumbres Frescas (al Por Mayor)",
    "sg:phone":"+34 981 50 31 05",
    "sg:postcode":"15885",
    "sg:province":"La Coru\u00f1a",
    "wof:name":"Fuentes Zas Jose",
    "wof:placetype":"venue"
},
  "geometry": {"coordinates":[-8.4848213196,42.7748413086],"type":"Point"}
}