{
  "type": "Feature",
  "properties": {
    "addr:full":"Av Santa Barbara, 33 Amposta Tarragona 43870",
    "addr:housenumber":"33",
    "addr:postcode":"43870",
    "addr:street":"Av Santa Barbara",
    "iso:country":"ES",
    "sg:address":"Av Santa Barbara, 33",
    "sg:city":"Amposta",
    "sg:orig_category":"Clases De M\u00dasica Y Canto",
    "sg:phone":"+34 977 70 05 63",
    "sg:postcode":"43870",
    "sg:province":"Tarragona",
    "wof:name":"La Lira Ampostina Sociedad Musical",
    "wof:placetype":"venue"
},
  "geometry": {"coordinates":[0.5769490004,40.7111167908],"type":"Point"}
}