{
  "type": "Feature",
  "properties": {
    "iso:country":"ES",
    "sg:address":"Pl Prim, 12",
    "sg:city":"Reus",
    "sg:orig_category":"Frutas Y Legumbres Secas (al Por Mayor)",
    "sg:phone":"+34 977 34 43 67",
    "sg:postcode":"43201",
    "sg:province":"Tarragona",
    "wof:name":"Sat Fruits Secs Catalans",
    "wof:placetype":"venue"
},
  "geometry": {"coordinates":[1.1070150137,41.1557807922],"type":"Point"}
}