{
  "type": "Feature",
  "properties": {
    "iso:country":"ES",
    "sg:address":"Calle de Aristoteles, 2",
    "sg:city":"Roquetas Mar",
    "sg:orig_category":"Centros Empresariales",
    "sg:phone":"+34 950 32 47 51",
    "sg:postcode":"04740",
    "sg:province":"Almer\u00eda",
    "wof:name":"Cobos Lopez Maria Gracia",
    "wof:placetype":"venue"
},
  "geometry": {"coordinates":[-2.6120994091,36.7647132874],"type":"Point"}
}