{
  "type": "Feature",
  "properties": {
    "addr:full":"Ctra Nal Trescientos Cuarenta, S/n Xativa Valencia 46800",
    "addr:housenumber":"s",
    "addr:postcode":"46800",
    "addr:street":"Ctra Nal Trescientos Cuarenta;/ N",
    "iso:country":"ES",
    "sg:address":"Ctra Nal Trescientos Cuarenta, S/n",
    "sg:city":"Xativa",
    "sg:orig_category":"Distribuci\u00d3n De Petr\u00d3leo Y Derivados",
    "sg:phone":"+34 962 28 19 32",
    "sg:postcode":"46800",
    "sg:province":"Valencia",
    "wof:name":"Sumipetrol S.l.",
    "wof:placetype":"venue"
},
  "geometry": {"coordinates":[-0.5200830102,38.9934272766],"type":"Point"}
}