{
  "type": "Feature",
  "properties": {
    "addr:full":"Calle de Andre Gide, 28 Malaga M\u00e1laga 29004",
    "addr:housenumber":"28",
    "addr:postcode":"29004",
    "addr:street":"Calle De Andre Gide;Ma\u0301Laga",
    "iso:country":"ES",
    "sg:address":"Calle de Andre Gide, 28",
    "sg:city":"Malaga",
    "sg:orig_category":"Ropa Y Accesorios",
    "sg:phone":"+34 952 10 59 66",
    "sg:postcode":"29004",
    "sg:province":"M\u00e1laga",
    "wof:name":"Moda Esplendida S.l.",
    "wof:placetype":"venue"
},
  "geometry": {"coordinates":[-4.4741916656,36.6905860901],"type":"Point"}
}