{
  "type": "Feature",
  "properties": {
    "iso:country":"ES",
    "sg:address":"Carrer de Barcelona, 6",
    "sg:city":"Vandellos",
    "sg:orig_category":"Empresas De Pintura Y Revestimientos",
    "sg:phone":"+34 977 82 41 31",
    "sg:postcode":"43891",
    "sg:province":"Tarragona",
    "wof:name":"Capafons Figueres Francisco",
    "wof:placetype":"venue"
},
  "geometry": {"coordinates":[0.8287310004,41.0201263428],"type":"Point"}
}