{
  "type": "Feature",
  "properties": {
    "addr:full":"Calle de Alberca (de La), 3 Fuenlabrada Madrid 28942",
    "addr:housenumber":"3",
    "addr:postcode":"28942",
    "addr:street":"Calle De Alberca De La",
    "iso:country":"ES",
    "sg:address":"Calle de Alberca (de La), 3",
    "sg:city":"Fuenlabrada",
    "sg:orig_category":"Construcciones Prefabricadas Y Desmontables",
    "sg:phone":"+34 916 08 52 05",
    "sg:postcode":"28942",
    "sg:province":"Madrid",
    "wof:name":"Construcciones Y Naves Sifecam S L",
    "wof:placetype":"venue"
},
  "geometry": {"coordinates":[-3.8140323162,40.2950401306],"type":"Point"}
}