{
  "type": "Feature",
  "properties": {
    "addr:full":"Calle de Alvarez Sereix, 5 Alacant Alicante 03001",
    "addr:housenumber":"5",
    "addr:postcode":"03001",
    "addr:street":"Calle De Alvarez Sereix",
    "iso:country":"ES",
    "sg:address":"Calle de Alvarez Sereix, 5",
    "sg:city":"Alacant",
    "sg:orig_category":"Abogados",
    "sg:phone":"+34 965 21 51 32",
    "sg:postcode":"03001",
    "sg:province":"Alicante",
    "wof:name":"Navas Pastor Antonio Eduardo",
    "wof:placetype":"venue"
},
  "geometry": {"coordinates":[-0.48896119,38.3454360962],"type":"Point"}
}