{
  "type": "Feature",
  "properties": {
    "addr:full":"Calle de Garcia Salazar, 10 Madrid Madrid 28017",
    "addr:housenumber":"10",
    "addr:postcode":"madrid;28017",
    "addr:street":"Calle De Garcia Salazar",
    "iso:country":"ES",
    "sg:address":"Calle de Garcia Salazar, 10",
    "sg:city":"Madrid",
    "sg:orig_category":"Tapicer\u00cdas",
    "sg:phone":"+34 913 04 96 87",
    "sg:postcode":"28017",
    "sg:province":"Madrid",
    "wof:name":"Gomez Benito Isidro",
    "wof:placetype":"venue"
},
  "geometry": {"coordinates":[-3.6380422115,40.4255981445],"type":"Point"}
}