{
  "type": "Feature",
  "properties": {
    "iso:country":"ES",
    "sg:address":"Calle de Edison, 387",
    "sg:city":"Talavera Reina",
    "sg:orig_category":"Maquinaria Para Industrias Diversas",
    "sg:phone":"+34 925 81 06 33",
    "sg:postcode":"45600",
    "sg:province":"Toledo",
    "sg:website":"www.vifesa.es",
    "wof:name":"Vifesa S. L.",
    "wof:placetype":"venue"
},
  "geometry": {"coordinates":[-4.8326292038,39.9584884644],"type":"Point"}
}