{
  "type": "Feature",
  "properties": {
    "iso:country":"ES",
    "sg:address":"Pg Comte De Vilardaga, S/n",
    "sg:city":"Sant Feliu Llobregat",
    "sg:orig_category":"Asistencia Social",
    "sg:phone":"+34 936 66 67 53",
    "sg:postcode":"08980",
    "sg:province":"Barcelona",
    "wof:name":"Ajuntament De Sant Feliu De Llobregat Codi 654",
    "wof:placetype":"venue"
},
  "geometry": {"coordinates":[2.053204298,41.3864860535],"type":"Point"}
}