{
  "type": "Feature",
  "properties": {
    "addr:full":"Carrer de Vint-i-vuit, 33 Bonavista Tarragona 43100",
    "addr:housenumber":"33",
    "addr:postcode":"43100",
    "addr:street":"Carrer De Vint-I-Vuit",
    "iso:country":"ES",
    "sg:address":"Carrer de Vint-i-vuit, 33",
    "sg:city":"Bonavista",
    "sg:orig_category":"Reposter\u00cdas",
    "sg:phone":"+34 977 55 06 79",
    "sg:postcode":"43100",
    "sg:province":"Tarragona",
    "wof:name":"Andreu Reyes S.c.p.",
    "wof:placetype":"venue"
},
  "geometry": {"coordinates":[1.1913292408,41.1245765686],"type":"Point"}
}