{
  "type": "Feature",
  "properties": {
    "addr:full":"Pol Ind Tres Hermanas, S/n Aspe Alicante 03680",
    "addr:housenumber":"s / n",
    "addr:postcode":"03680",
    "addr:street":"Hermanas",
    "iso:country":"ES",
    "sg:address":"Pol Ind Tres Hermanas, S/n",
    "sg:city":"Aspe",
    "sg:orig_category":"Molduras, Junquillos, Listones Y Molduras Perforadas",
    "sg:phone":"+34 965 49 35 51",
    "sg:postcode":"03680",
    "sg:province":"Alicante",
    "sg:website":"www.dompi.es",
    "wof:name":"Aspe 100 S.l.",
    "wof:placetype":"venue"
},
  "geometry": {"coordinates":[-0.7722973824,38.3351173401],"type":"Point"}
}