{
  "type": "Feature",
  "properties": {
    "addr:full":"Avda Francisco Javier Sauquillo, 28 Fuenlabrada Madrid 28944",
    "addr:housenumber":"28",
    "addr:postcode":"28944",
    "addr:street":"Avda Francisco Javier Sauquillo",
    "iso:country":"ES",
    "sg:address":"Avda Francisco Javier Sauquillo, 28",
    "sg:city":"Fuenlabrada",
    "sg:orig_category":"Ropa Para Ni\u00d1os (al Por Menor)",
    "sg:phone":"+34 916 90 54 81",
    "sg:postcode":"28944",
    "sg:province":"Madrid",
    "wof:name":"Terrado Boveda Enrique",
    "wof:placetype":"venue"
},
  "geometry": {"coordinates":[-3.7887980938,40.2837944031],"type":"Point"}
}