{
  "type": "Feature",
  "properties": {
    "addr:full":"Plaza Solobarria, 1 Basauri Vizcaya 48970",
    "addr:housenumber":"1",
    "addr:postcode":"48970",
    "addr:street":"Solobarria",
    "iso:country":"ES",
    "sg:address":"Plaza Solobarria, 1",
    "sg:city":"Basauri",
    "sg:orig_category":"Molduras, Junquillos, Listones Y Molduras Perforadas",
    "sg:phone":"+34 944 02 08 42",
    "sg:postcode":"48970",
    "sg:province":"Vizcaya",
    "wof:name":"Idoia Perlado Lopez Y Otros C.b.",
    "wof:placetype":"venue"
},
  "geometry": {"coordinates":[-2.8850820065,43.2380218506],"type":"Point"}
}