{
  "type": "Feature",
  "properties": {
    "addr:full":"Avda Camelias, 27 Vigo Pontevedra 36202",
    "addr:housenumber":"27",
    "addr:postcode":"36202",
    "addr:street":"Avda Camelias",
    "iso:country":"ES",
    "sg:address":"Avda Camelias, 27",
    "sg:city":"Vigo",
    "sg:orig_category":"Ropa Para Se\u00d1oras (al Por Menor)",
    "sg:phone":"+34 986 41 86 90",
    "sg:postcode":"36202",
    "sg:province":"Pontevedra",
    "wof:name":"Pampillon Conde Mercedes",
    "wof:placetype":"venue"
},
  "geometry": {"coordinates":[-8.7293291092,42.231880188],"type":"Point"}
}