{
  "type": "Feature",
  "properties": {
    "addr:full":"Rua Regueiral, 33 Barco Ourense 32300",
    "addr:housenumber":"33",
    "addr:postcode":"32300",
    "addr:street":"Rua Regueiral",
    "iso:country":"ES",
    "sg:address":"Rua Regueiral, 33",
    "sg:city":"Barco",
    "sg:orig_category":"Electricidad Veh\u00cdculo",
    "sg:phone":"+34 988 32 10 26",
    "sg:postcode":"32300",
    "sg:province":"Ourense",
    "wof:name":"Myrsa S.l.",
    "wof:placetype":"venue"
},
  "geometry": {"coordinates":[-6.9935660362,42.4154014587],"type":"Point"}
}