{
  "type": "Feature",
  "properties": {
    "addr:full":"Avda Compostela, 11 Padron A Coru\u00f1a 15900",
    "addr:housenumber":"11",
    "addr:postcode":"15900",
    "addr:street":"Avda Compostela;Padron A Corun\u0303A",
    "iso:country":"ES",
    "sg:address":"Avda Compostela, 11",
    "sg:city":"Padron",
    "sg:orig_category":"Venta, Montaje De Neum\u00c1ticos",
    "sg:phone":"+34 981 81 15 51",
    "sg:postcode":"15900",
    "sg:province":"A Coru\u00f1a",
    "wof:name":"S.n. Rodisa S.l.",
    "wof:placetype":"venue"
},
  "geometry": {"coordinates":[-8.6587991714,42.7402801514],"type":"Point"}
}