{
  "type": "Feature",
  "properties": {
    "iso:country":"ES",
    "sg:address":"Calle de Francos Rodriguez, 74",
    "sg:city":"Madrid",
    "sg:orig_category":"\u00d3ptica: Instrumentos (fabricaci\u00d3n)",
    "sg:phone":"+34 914 59 12 14",
    "sg:postcode":"28039",
    "sg:province":"Madrid",
    "sg:website":"www.visionlab.es",
    "wof:name":"Visionlab S.a.",
    "wof:placetype":"venue"
},
  "geometry": {"coordinates":[-3.7093982697,40.4570884705],"type":"Point"}
}