{
  "type": "Feature",
  "properties": {
    "addr:full":"Partida Val De Fortun, S/n Mazaleon Teruel 44621",
    "addr:housenumber":"s / n",
    "addr:postcode":"44621",
    "addr:street":"Partida Val De Fortun",
    "iso:country":"ES",
    "sg:address":"Partida Val De Fortun, S/n",
    "sg:city":"Mazaleon",
    "sg:orig_category":"Poller\u00cda Y Caza (al Por Menor)",
    "sg:phone":"+34 978 89 87 22",
    "sg:postcode":"44621",
    "sg:province":"Teruel",
    "wof:name":"Pellicer Vandellos Jose Luis",
    "wof:placetype":"venue"
},
  "geometry": {"coordinates":[0.1034329981,41.0514335632],"type":"Point"}
}