{
  "type": "Feature",
  "properties": {
    "addr:full":"Calle de Pintor Zabaleta, 13 Torreperogil Ja\u00e9n 23320",
    "addr:housenumber":"13",
    "addr:postcode":"23320",
    "addr:street":"Calle De Pintor Zabaleta",
    "iso:country":"ES",
    "sg:address":"Calle de Pintor Zabaleta, 13",
    "sg:city":"Torreperogil",
    "sg:orig_category":"Carnicer\u00cdas, Carnicer\u00cdas",
    "sg:phone":"+34 953 77 62 53",
    "sg:postcode":"23320",
    "sg:province":"Ja\u00e9n",
    "wof:name":"Gallego Talavera Francisco Jose",
    "wof:placetype":"venue"
},
  "geometry": {"coordinates":[-3.2822959423,38.0391921997],"type":"Point"}
}