{
  "type": "Feature",
  "properties": {
    "addr:full":"Carrer de Carrio, 27 Manresa Barcelona 08242",
    "addr:housenumber":"27",
    "addr:postcode":"08242",
    "addr:street":"Carrer De Carrio",
    "iso:country":"ES",
    "sg:address":"Carrer de Carrio, 27",
    "sg:city":"Manresa",
    "sg:orig_category":"Arquitectos",
    "sg:phone":"+34 938 75 24 24",
    "sg:postcode":"08242",
    "sg:province":"Barcelona",
    "wof:name":"Eidee Arquitectes S.l.",
    "wof:placetype":"venue"
},
  "geometry": {"coordinates":[1.8226649761,41.7286186218],"type":"Point"}
}