{
  "type": "Feature",
  "properties": {
    "addr:full":"Av Joan Carles I, 132 Blanes Girona 17300",
    "addr:housenumber":"132",
    "addr:postcode":"17300",
    "addr:street":"Av Joan Carles I",
    "iso:country":"ES",
    "sg:address":"Av Joan Carles I, 132",
    "sg:city":"Blanes",
    "sg:orig_category":"Artes Gr\u00c1ficas, Artes Pl\u00c1sticas (curso)",
    "sg:phone":"+34 972 33 78 03",
    "sg:postcode":"17300",
    "sg:province":"Girona",
    "wof:name":"Quesada Carpio Jose",
    "wof:placetype":"venue"
},
  "geometry": {"coordinates":[2.7944359779,41.6843833923],"type":"Point"}
}