{
  "type": "Feature",
  "properties": {
    "addr:full":"Perez Colino, 1 Ponferrada Le\u00f3n 24400",
    "addr:housenumber":"1",
    "addr:postcode":"24400",
    "addr:street":"Colino",
    "iso:country":"ES",
    "sg:address":"Perez Colino, 1",
    "sg:city":"Ponferrada",
    "sg:orig_category":"Fabricaci\u00d3n, Importaci\u00d3n, Venta De Material De Telefon\u00cda, Peritelefon\u00cda",
    "sg:phone":"+34 987 40 99 90",
    "sg:postcode":"24400",
    "sg:province":"Le\u00f3n",
    "wof:name":"Telymovil Tiendas S.l.",
    "wof:placetype":"venue"
},
  "geometry": {"coordinates":[-6.5971989632,42.5451393127],"type":"Point"}
}