{
  "type": "Feature",
  "properties": {
    "iso:country":"ES",
    "sg:address":"Calle de Jose Benlliure, 125",
    "sg:city":"Valencia",
    "sg:orig_category":"Farmacias",
    "sg:phone":"+34 963 71 01 14",
    "sg:postcode":"46011",
    "sg:province":"Valencia",
    "wof:name":"Morales Villena Berta",
    "wof:placetype":"venue"
},
  "geometry": {"coordinates":[-0.3303233981,39.4691009521],"type":"Point"}
}