{
  "type": "Feature",
  "properties": {
    "addr:full":"Calle de Rey Pelayo, 1 Piedras Blancas Asturias 33450",
    "addr:housenumber":"1",
    "addr:postcode":"33450",
    "addr:street":"Calle De Rey Pelayo",
    "iso:country":"ES",
    "sg:address":"Calle de Rey Pelayo, 1",
    "sg:city":"Piedras Blancas",
    "sg:orig_category":"Carnicer\u00cdas, Carnicer\u00cdas",
    "sg:phone":"+34 985 53 24 33",
    "sg:postcode":"33450",
    "sg:province":"Asturias",
    "wof:name":"Ugarte Garcia Marcos Horacio",
    "wof:placetype":"venue"
},
  "geometry": {"coordinates":[-5.9774961472,43.5601882935],"type":"Point"}
}