{
  "type": "Feature",
  "properties": {
    "addr:full":"Calle de Almansa, 14 Malaga M\u00e1laga 29007",
    "addr:housenumber":"14",
    "addr:postcode":"29007",
    "addr:street":"Calle De Almansa;Ma\u0301Laga",
    "iso:country":"ES",
    "sg:address":"Calle de Almansa, 14",
    "sg:city":"Malaga",
    "sg:orig_category":"Asesor\u00cda Fiscal Y Jur\u00cddica",
    "sg:phone":"+34 952 28 55 87",
    "sg:postcode":"29007",
    "sg:province":"M\u00e1laga",
    "wof:name":"Crespo Riesco Juan Manuel",
    "wof:placetype":"venue"
},
  "geometry": {"coordinates":[-4.4290709496,36.7192192078],"type":"Point"}
}