{
  "type": "Feature",
  "properties": {
    "iso:country":"ES",
    "sg:address":"Carrer de Convent, S/n",
    "sg:city":"Cocentaina",
    "sg:orig_category":"Internados & Ense\u00d1anza Privada",
    "sg:phone":"+34 965 59 25 44",
    "sg:postcode":"03820",
    "sg:province":"Alicante",
    "wof:name":"Colegio San Francisco De Asis",
    "wof:placetype":"venue"
},
  "geometry": {"coordinates":[-0.4414289892,38.7394104004],"type":"Point"}
}