{
  "type": "Feature",
  "properties": {
    "addr:full":"Rovinals, 4 Alpicat Lleida 25110",
    "addr:housenumber":"4",
    "addr:postcode":"25110",
    "addr:street":"Rovinals",
    "iso:country":"ES",
    "sg:address":"Rovinals, 4",
    "sg:city":"Alpicat",
    "sg:orig_category":"Complementos De Vestir (al Por Menor)",
    "sg:phone":"+34 973 73 70 46",
    "sg:postcode":"25110",
    "sg:province":"Lleida",
    "wof:name":"Taller Ceramica 4 Mans",
    "wof:placetype":"venue"
},
  "geometry": {"coordinates":[0.5720689893,41.6661186218],"type":"Point"}
}