{
  "type": "Feature",
  "properties": {
    "addr:full":"Calle de Eulalia Alvarez, 33 Gijon Asturias 33209",
    "addr:housenumber":"33",
    "addr:postcode":"33209",
    "addr:street":"Calle De Eulalia Alvarez",
    "iso:country":"ES",
    "sg:address":"Calle de Eulalia Alvarez, 33",
    "sg:city":"Gijon",
    "sg:orig_category":"Molduras, Junquillos, Listones Y Molduras Perforadas",
    "sg:phone":"+34 985 39 95 22",
    "sg:postcode":"33209",
    "sg:province":"Asturias",
    "wof:name":"Rodriguez Fernandez Tomas",
    "wof:placetype":"venue"
},
  "geometry": {"coordinates":[-5.6644430161,43.5276908875],"type":"Point"}
}