{
  "type": "Feature",
  "properties": {
    "addr:full":"Rua Nova, 16 Ourense Ourense 32004",
    "addr:housenumber":"16",
    "addr:postcode":"32004",
    "addr:street":"Rua Nova",
    "iso:country":"ES",
    "sg:address":"Rua Nova, 16",
    "sg:city":"Ourense",
    "sg:orig_category":"Electricidad Veh\u00cdculo",
    "sg:phone":"+34 988 22 36 76",
    "sg:postcode":"32004",
    "sg:province":"Ourense",
    "wof:name":"Araujo Perez Raul",
    "wof:placetype":"venue"
},
  "geometry": {"coordinates":[-7.8560552597,42.343132019],"type":"Point"}
}