{
  "type": "Feature",
  "properties": {
    "iso:country":"ES",
    "sg:address":"Carr Sant Tomas, 119",
    "sg:city":"Benicasim",
    "sg:orig_category":"Bazares, Art\u00cdculos De Limpieza Y De Cocina (al Por Menor)",
    "sg:phone":"+34 964 30 22 12",
    "sg:postcode":"12560",
    "sg:province":"Castell\u00f3n",
    "wof:name":"De Los Santos Miro Carmen",
    "wof:placetype":"venue"
},
  "geometry": {"coordinates":[0.0457400009,40.0510292053],"type":"Point"}
}