{
  "type": "Feature",
  "properties": {
    "iso:country":"ES",
    "sg:address":"Calle de Trinidad, 29",
    "sg:city":"Talavera Reina",
    "sg:orig_category":"Institutos De Belleza",
    "sg:phone":"+34 925 80 63 06",
    "sg:postcode":"45600",
    "sg:province":"Toledo",
    "wof:name":"Rivas San Cristobal Ramona",
    "wof:placetype":"venue"
},
  "geometry": {"coordinates":[-4.8274130821,39.9631271362],"type":"Point"}
}