{
  "type": "Feature",
  "properties": {
    "addr:full":"Monte Bre\u00f1a, 76 Monte Bre\u00f1a Santa Cruz De Tenerife 38739",
    "addr:housenumber":"76",
    "addr:postcode":"38739",
    "addr:street":"Bren\u0303A;Bren\u0303A",
    "iso:country":"ES",
    "sg:address":"Monte Bre\u00f1a, 76",
    "sg:city":"Monte Bre\u00f1a",
    "sg:orig_category":"Florister\u00cdas",
    "sg:phone":"+34 922 44 02 05",
    "sg:postcode":"38739",
    "sg:province":"Santa Cruz De Tenerife",
    "wof:name":"Rodriguez Concepcion Luis Manuel",
    "wof:placetype":"venue"
},
  "geometry": {"coordinates":[-17.780620575,28.6173477173],"type":"Point"}
}