{
  "type": "Feature",
  "properties": {
    "iso:country":"ES",
    "sg:address":"Carrer de Girona, 49",
    "sg:city":"Granollers",
    "sg:orig_category":"Frutas, Legumbres Frescas Y Tempranas (al Por Menor)",
    "sg:phone":"+34 938 70 22 76",
    "sg:postcode":"08402",
    "sg:province":"Barcelona",
    "wof:name":"Montull Lopez Ana",
    "wof:placetype":"venue"
},
  "geometry": {"coordinates":[2.2910490036,41.6114959717],"type":"Point"}
}