{
  "type": "Feature",
  "properties": {
    "addr:full":"Lomalinda Fase Quinta, 27 Ogijares Granada 18151",
    "addr:housenumber":"27",
    "addr:postcode":"18151",
    "addr:street":"Quinta",
    "iso:country":"ES",
    "sg:address":"Lomalinda Fase Quinta, 27",
    "sg:city":"Ogijares",
    "sg:orig_category":"Materiales De Construcci\u00d3n, Herramientas",
    "sg:phone":"+34 958 50 36 64",
    "sg:postcode":"18151",
    "sg:province":"Granada",
    "wof:name":"Alquifegran S. L.",
    "wof:placetype":"venue"
},
  "geometry": {"coordinates":[-3.616714716,37.1191101074],"type":"Point"}
}