{
  "type": "Feature",
  "properties": {
    "iso:country":"ES",
    "sg:address":"Calle de General Shelly, 28",
    "sg:city":"Valladolid",
    "sg:orig_category":"Estancos",
    "sg:phone":"+34 983 47 97 03",
    "sg:postcode":"47013",
    "sg:province":"Valladolid",
    "wof:name":"Ferrero Casado Isabel",
    "wof:placetype":"venue"
},
  "geometry": {"coordinates":[-4.7192258835,41.6356430054],"type":"Point"}
}