{
  "type": "Feature",
  "properties": {
    "iso:country":"ES",
    "sg:address":"Calle de Bazan, 46",
    "sg:city":"Alacant",
    "sg:orig_category":"Maquinaria Para Industrias Diversas",
    "sg:phone":"+34 965 14 54 60",
    "sg:postcode":"03001",
    "sg:province":"Alicante",
    "wof:name":"Garcia Catala Juan Antonio",
    "wof:placetype":"venue"
},
  "geometry": {"coordinates":[-0.4864777029,38.3465003967],"type":"Point"}
}