{
  "type": "Feature",
  "properties": {
    "addr:full":"Av Vilallonga, 50 Figueres Girona 17600",
    "addr:housenumber":"50",
    "addr:postcode":"17600",
    "addr:street":"Av Vilallonga",
    "iso:country":"ES",
    "sg:address":"Av Vilallonga, 50",
    "sg:city":"Figueres",
    "sg:orig_category":"Negocio De Materiales De Construcci\u00d3n",
    "sg:phone":"+34 972 50 36 63",
    "sg:postcode":"17600",
    "sg:province":"Girona",
    "wof:name":"Azulgreco S.l.",
    "wof:placetype":"venue"
},
  "geometry": {"coordinates":[2.9702262878,42.2664413452],"type":"Point"}
}