{
  "type": "Feature",
  "properties": {
    "addr:full":"Calle de Floridablanca, 17 Carmen Murcia 30002",
    "addr:housenumber":"17",
    "addr:postcode":"30002",
    "addr:street":"Calle De Floridablanca",
    "iso:country":"ES",
    "sg:address":"Calle de Floridablanca, 17",
    "sg:city":"Carmen",
    "sg:orig_category":"Ense\u00d1anza: Profesiones Art\u00cdsticas",
    "sg:phone":"+34 968 26 47 44",
    "sg:postcode":"30002",
    "sg:province":"Murcia",
    "wof:name":"Martinez Lorca Salvador",
    "wof:placetype":"venue"
},
  "geometry": {"coordinates":[-1.1312830448,37.9782409668],"type":"Point"}
}