{
  "type": "Feature",
  "properties": {
    "iso:country":"ES",
    "sg:address":"Avda Feria (de La), S/n",
    "sg:city":"Villamartin",
    "sg:orig_category":"\u00d3ptica: Instrumentos (fabricaci\u00d3n)",
    "sg:phone":"+34 956 73 04 83",
    "sg:postcode":"11650",
    "sg:province":"C\u00e1diz",
    "wof:name":"Berengena Herrera Concepcion",
    "wof:placetype":"venue"
},
  "geometry": {"coordinates":[-5.6441640854,36.8604202271],"type":"Point"}
}