{
  "type": "Feature",
  "properties": {
    "iso:country":"ES",
    "sg:address":"Avda De Rosalia De Castro, 6",
    "sg:city":"Ponteareas",
    "sg:orig_category":"Comerciantes Al Por Mayor De Vinos, Licores Y Alcoholes",
    "sg:phone":"+34 986 66 08 26",
    "sg:postcode":"36860",
    "sg:province":"Pontevedra",
    "wof:name":"Carballo Estevez Manuel",
    "wof:placetype":"venue"
},
  "geometry": {"coordinates":[-8.5163888931,42.1783599854],"type":"Point"}
}