{
  "type": "Feature",
  "properties": {
    "iso:country":"ES",
    "sg:address":"Carr Riu, 6",
    "sg:city":"Lleida",
    "sg:orig_category":"Edici\u00d3n De Diarios, Revistas, Boletines",
    "sg:phone":"+34 973 24 80 00",
    "sg:postcode":"25...",
    "sg:province":"Lleida",
    "sg:website":"www.diarisegre.com",
    "wof:name":"Diari Segre S.l.",
    "wof:placetype":"venue"
},
  "geometry": {"coordinates":[0.627129972,41.6145210266],"type":"Point"}
}