{
  "type": "Feature",
  "properties": {
    "iso:country":"ES",
    "sg:address":"Calle de Principe, 33",
    "sg:city":"Madrid",
    "sg:orig_category":"Cl\u00cdnicas Dentales",
    "sg:phone":"+34 914 29 48 59",
    "sg:postcode":"28012",
    "sg:province":"Madrid",
    "wof:name":"Pelayo Clinica Odontologica C.b.",
    "wof:placetype":"venue"
},
  "geometry": {"coordinates":[-3.6999650002,40.4141578674],"type":"Point"}
}