{
  "type": "Feature",
  "properties": {
    "addr:full":"Calle de Nueva, 1 Padul Granada 18640",
    "addr:housenumber":"1",
    "addr:postcode":"18640",
    "addr:street":"Calle De Nueva",
    "iso:country":"ES",
    "sg:address":"Calle de Nueva, 1",
    "sg:city":"Padul",
    "sg:orig_category":"M\u00c9dicos: Estomatolog\u00cda",
    "sg:phone":"+34 958 79 02 88",
    "sg:postcode":"18640",
    "sg:province":"Granada",
    "wof:name":"Gonzalez Moles Miguel Angel",
    "wof:placetype":"venue"
},
  "geometry": {"coordinates":[-3.6247808933,37.0249481201],"type":"Point"}
}