{
  "type": "Feature",
  "properties": {
    "iso:country":"ES",
    "sg:address":"Daimler-espiritu Santo, 40",
    "sg:city":"Cambre",
    "sg:orig_category":"Material Y Suministros Para Fotocopiadoras, Reprograf\u00cda",
    "sg:phone":"+34 981 64 92 04",
    "sg:postcode":"15650",
    "sg:province":"La Coru\u00f1a",
    "wof:name":"Carrodeguas Estraviz S.l.",
    "wof:placetype":"venue"
},
  "geometry": {"coordinates":[-8.3069343567,43.2885551453],"type":"Point"}
}