{
  "type": "Feature",
  "properties": {
    "iso:country":"ES",
    "sg:address":"Carrer de Esteras, 15",
    "sg:city":"Barcelona",
    "sg:orig_category":"Mec\u00c1nico Del Autom\u00d3vil",
    "sg:phone":"+34 932 96 43 38",
    "sg:postcode":"08028",
    "sg:province":"Barcelona",
    "wof:name":"J. J. Motor S.c.p",
    "wof:placetype":"venue"
},
  "geometry": {"coordinates":[2.1295979023,41.3707809448],"type":"Point"}
}