{
  "type": "Feature",
  "properties": {
    "iso:country":"ES",
    "sg:address":"Calle de Salud, 1",
    "sg:city":"Valladolid",
    "sg:classifiers":[
        {
            "category":"Autos & Motor Vehicles",
            "subcategory":"Automobile Sales",
            "type":"Retail Goods"
        }
    ],
    "sg:phone":"+34 983 39 61 96",
    "sg:postcode":"47012",
    "sg:province":"Valladolid",
    "wof:name":"Blanco Otero Ismael",
    "wof:placetype":"venue"
},
  "geometry": {"coordinates":[-4.7150468826,41.6459007263],"type":"Point"}
}