{
  "type": "Feature",
  "properties": {
    "addr:full":"Carrer de Sant Francesc, 105 Vic Barcelona 08500",
    "addr:housenumber":"105",
    "addr:postcode":"08500",
    "addr:street":"Carrer De Sant Francesc",
    "iso:country":"ES",
    "sg:address":"Carrer de Sant Francesc, 105",
    "sg:city":"Vic",
    "sg:orig_category":"Fabricaci\u00d3n De Su\u00c9ters Y Chalecos De Punto",
    "sg:phone":"+34 938 89 43 53",
    "sg:postcode":"08500",
    "sg:province":"Barcelona",
    "wof:name":"Lara Garcia Pilar",
    "wof:placetype":"venue"
},
  "geometry": {"coordinates":[2.2832529545,41.9535446167],"type":"Point"}
}