{
  "type": "Feature",
  "properties": {
    "iso:country":"ES",
    "sg:address":"Calle de Infanta Maria Teresa, 6",
    "sg:city":"Madrid",
    "sg:classifiers":[
        {
            "category":"Professional",
            "subcategory":"Management & Consulting",
            "type":"Services"
        }
    ],
    "sg:phone":"+34 913 44 00 53",
    "sg:postcode":"28016",
    "sg:province":"Madrid",
    "sg:tags":[
        "asesor\u00cda",
        "en",
        "marketing"
    ],
    "wof:name":"Garcia Ruiz Fernando",
    "wof:placetype":"venue"
},
  "geometry": {"coordinates":[-3.6810650826,40.4539718628],"type":"Point"}
}