{
  "type": "Feature",
  "properties": {
    "iso:country":"ES",
    "sg:address":"Calle de Puntita (la), 4",
    "sg:city":"Candelaria",
    "sg:orig_category":"Telas Para Tapizar, Cortinas, Pasamaner\u00cda (fabricaci\u00d3n, Al Por Mayor)",
    "sg:phone":"+34 922 50 65 54",
    "sg:postcode":"38530",
    "sg:province":"Santa Cruz De Tenerife",
    "wof:name":"Decoracion Mosselbaai S.l.",
    "wof:placetype":"venue"
},
  "geometry": {"coordinates":[-16.369852066,28.3577060699],"type":"Point"}
}