{
  "type": "Feature",
  "properties": {
    "iso:country":"ES",
    "sg:address":"Av. Gola, 1",
    "sg:city":"Estartit",
    "sg:orig_category":"Peluquer\u00cdas, Peluquer\u00cda Mixta",
    "sg:phone":"+34 972 75 14 41",
    "sg:postcode":"17258",
    "sg:province":"Girona",
    "wof:name":"Cadanet Matas Fernando",
    "wof:placetype":"venue"
},
  "geometry": {"coordinates":[3.1878299713,42.0489959717],"type":"Point"}
}