{
  "type": "Feature",
  "properties": {
    "iso:country":"ES",
    "sg:address":"Crta Vall De Uxo, S/n",
    "sg:city":"Moncofa",
    "sg:orig_category":"Distribuci\u00d3n De Petr\u00d3leo Y Derivados",
    "sg:phone":"+34 964 58 05 32",
    "sg:postcode":"12593",
    "sg:province":"Castell\u00f3n",
    "wof:name":"Estacion De Servicio Moncofar S.l.",
    "wof:placetype":"venue"
},
  "geometry": {"coordinates":[-0.1429889947,39.8067741394],"type":"Point"}
}