{
  "type": "Feature",
  "properties": {
    "addr:full":"Calle de Santa Ana, 1 Villanueva De Las Torres Granada 18539",
    "addr:housenumber":"1",
    "addr:postcode":"18539",
    "addr:street":"Calle De Santa Ana",
    "iso:country":"ES",
    "sg:address":"Calle de Santa Ana, 1",
    "sg:city":"Villanueva De Las Torres",
    "sg:orig_category":"Carnicer\u00cdas, Carnicer\u00cdas",
    "sg:phone":"+34 958 69 40 38",
    "sg:postcode":"18539",
    "sg:province":"Granada",
    "wof:name":"Fabricacion De Embutidos Medina S.l.",
    "wof:placetype":"venue"
},
  "geometry": {"coordinates":[-3.0901679993,37.556728363],"type":"Point"}
}