{
  "type": "Feature",
  "properties": {
    "iso:country":"ES",
    "sg:address":"Calle de Doctor Ivorra, 9",
    "sg:city":"Sant Joan D'alacant",
    "sg:orig_category":"Bares, Piano",
    "sg:phone":"+34 965 65 57 93",
    "sg:postcode":"03550",
    "sg:province":"Alicante",
    "sg:website":"www.pubbennett.tk",
    "wof:name":"Domenech Monllor Guillermo",
    "wof:placetype":"venue"
},
  "geometry": {"coordinates":[-0.4329564869,38.3971214294],"type":"Point"}
}