{
  "type": "Feature",
  "properties": {
    "iso:country":"ES",
    "sg:address":"Carrer de Lorena, 18",
    "sg:city":"Barcelona",
    "sg:orig_category":"Inform\u00c1tica, Ofim\u00c1tica (estudios, Asesor\u00cda, Ingenier\u00cda, Formaci\u00d3n)",
    "sg:phone":"+34 933 59 88 14",
    "sg:postcode":"08042",
    "sg:province":"Barcelona",
    "wof:name":"Roquet Fernandez Josep",
    "wof:placetype":"venue"
},
  "geometry": {"coordinates":[2.1725509167,41.4374046326],"type":"Point"}
}