{
  "type": "Feature",
  "properties": {
    "iso:country":"ES",
    "sg:address":"Avda Doctor Solis Pascual, 30",
    "sg:city":"Ubrique",
    "sg:orig_category":"Doctores En Medicina",
    "sg:phone":"+34 956 46 49 12",
    "sg:postcode":"11600",
    "sg:province":"C\u00e1diz",
    "wof:name":"Dominguez Benitez Juan Manuel",
    "wof:placetype":"venue"
},
  "geometry": {"coordinates":[-5.4470410347,36.67760849],"type":"Point"}
}