{
  "type": "Feature",
  "properties": {
    "iso:country":"ES",
    "sg:address":"Jose Ferro Rodeiro(a Volta), 4",
    "sg:city":"Muras",
    "sg:orig_category":"Fabricaci\u00d3n De Moldes Y Modelos",
    "sg:phone":"+34 982 50 00 00",
    "sg:postcode":"27836",
    "sg:province":"Lugo",
    "wof:name":"Plasticos Ferro S.l.",
    "wof:placetype":"venue"
},
  "geometry": {"coordinates":[-7.7227787971,43.466835022],"type":"Point"}
}