{
  "type": "Feature",
  "properties": {
    "addr:full":"Calle de Jose Martinez Velasco, 20 Riaza Segovia 40500",
    "addr:housenumber":"20",
    "addr:postcode":"40500",
    "addr:street":"Calle De Jose Martinez Velasco",
    "iso:country":"ES",
    "sg:address":"Calle de Jose Martinez Velasco, 20",
    "sg:city":"Riaza",
    "sg:orig_category":"Pescader\u00cdas (al Por Menor)",
    "sg:phone":"+34 921 55 00 79",
    "sg:postcode":"40500",
    "sg:province":"Segovia",
    "wof:name":"Martin Martin Juan Manuel",
    "wof:placetype":"venue"
},
  "geometry": {"coordinates":[-3.4786560535,41.2796974182],"type":"Point"}
}