{
  "type": "Feature",
  "properties": {
    "addr:full":"Txirrita Maleo, 13 Errenteria Guip\u00f9zcoa 20100",
    "addr:housenumber":"13",
    "addr:postcode":"20100",
    "addr:street":"Maleo;Guipu\u0300Zcoa",
    "iso:country":"ES",
    "sg:address":"Txirrita Maleo, 13",
    "sg:city":"Errenteria",
    "sg:orig_category":"Maquinaria Para Industrias Diversas",
    "sg:phone":"+34 943 40 06 09",
    "sg:postcode":"20100",
    "sg:province":"Guip\u00f9zcoa",
    "wof:name":"Apina S.a.",
    "wof:placetype":"venue"
},
  "geometry": {"coordinates":[-1.8970370293,43.3210067749],"type":"Point"}
}