{
  "type": "Feature",
  "properties": {
    "iso:country":"ES",
    "sg:address":"Rua Fotografo Xose Gil, 10",
    "sg:city":"Vigo",
    "sg:orig_category":"\u00d3ptica: Instrumentos (fabricaci\u00d3n)",
    "sg:phone":"+34 986 20 82 27",
    "sg:postcode":"36209",
    "sg:province":"Pontevedra",
    "wof:name":"Centro Optico Uriguen S.l.",
    "wof:placetype":"venue"
},
  "geometry": {"coordinates":[-8.7462453842,42.2151756287],"type":"Point"}
}