{
  "type": "Feature",
  "properties": {
    "iso:country":"ES",
    "sg:address":"Plaz Hermanos Fernandez Criado, 15",
    "sg:city":"Illescas",
    "sg:orig_category":"Arquitectos",
    "sg:phone":"+34 925 51 35 22",
    "sg:postcode":"45200",
    "sg:province":"Toledo",
    "wof:name":"Alonso Robles Pedro Jesus",
    "wof:placetype":"venue"
},
  "geometry": {"coordinates":[-3.8489923477,40.1241645813],"type":"Point"}
}