{
  "type": "Feature",
  "properties": {
    "iso:country":"ES",
    "sg:address":"Ctra Creu Negra, (de La), 30",
    "sg:city":"Carlet",
    "sg:orig_category":"Veh\u00cdculos De Ocasi\u00d3n",
    "sg:phone":"+34 962 53 40 54",
    "sg:postcode":"46240",
    "sg:province":"Valencia",
    "wof:name":"Jacinto Cienfuegos E Hijos S.l.",
    "wof:placetype":"venue"
},
  "geometry": {"coordinates":[-0.5127189755,39.2281723022],"type":"Point"}
}