{
  "type": "Feature",
  "properties": {
    "addr:full":"Calle de Huerta Chica, 15 Chiclana De La Frontera C\u00e1diz 11130",
    "addr:housenumber":"15",
    "addr:postcode":"11130",
    "addr:street":"Calle De Huerta Chica",
    "iso:country":"ES",
    "sg:address":"Calle de Huerta Chica, 15",
    "sg:city":"Chiclana De La Frontera",
    "sg:orig_category":"Promotores Constructores",
    "sg:phone":"+34 956 53 80 59",
    "sg:postcode":"11130",
    "sg:province":"C\u00e1diz",
    "wof:name":"Construcciones Diego Vela S.l.",
    "wof:placetype":"venue"
},
  "geometry": {"coordinates":[-6.1452288628,36.4191093445],"type":"Point"}
}