{
  "type": "Feature",
  "properties": {
    "addr:full":"Calle de Juan Ramon Jimenez, 2 Merida Badajoz 06800",
    "addr:housenumber":"2",
    "addr:postcode":"06800",
    "addr:street":"Calle De Juan Ramon Jimenez",
    "iso:country":"ES",
    "sg:address":"Calle de Juan Ramon Jimenez, 2",
    "sg:city":"Merida",
    "sg:orig_category":"Confecci\u00d3n (fabricaci\u00d3n, Al Por Mayor)",
    "sg:phone":"+34 924 37 11 23",
    "sg:postcode":"06800",
    "sg:province":"Badajoz",
    "wof:name":"Benitez Huertas Manuel",
    "wof:placetype":"venue"
},
  "geometry": {"coordinates":[-6.3584289551,38.9134292603],"type":"Point"}
}