{
  "type": "Feature",
  "properties": {
    "iso:country":"ES",
    "sg:address":"Calle de Agustin Sales, 3",
    "sg:city":"Valencia",
    "sg:orig_category":"Bisuteros (fabricaci\u00d3n, Al Por Mayor)",
    "sg:phone":"+34 963 77 98 17",
    "sg:postcode":"46007",
    "sg:province":"Valencia",
    "wof:name":"Garviher S. L.",
    "wof:placetype":"venue"
},
  "geometry": {"coordinates":[-0.3879696131,39.4561004639],"type":"Point"}
}