{
  "type": "Feature",
  "properties": {
    "iso:country":"ES",
    "sg:address":"Calle de San Juan De Dios, 32",
    "sg:city":"Granada",
    "sg:orig_category":"Inmobiliaria (agencias)",
    "sg:phone":"+34 958 20 63 45",
    "sg:postcode":"18001",
    "sg:province":"Granada",
    "wof:name":"Ala\u00f1on Y Alcolea C.b.",
    "wof:placetype":"venue"
},
  "geometry": {"coordinates":[-3.6025574207,37.1813278198],"type":"Point"}
}