{
  "type": "Feature",
  "properties": {
    "iso:country":"ES",
    "sg:address":"Ctra. Malaga, Km. 0442,0",
    "sg:city":"Santa Fe",
    "sg:orig_category":"Distribuci\u00d3n De Petr\u00d3leo Y Derivados",
    "sg:phone":"+34 958 51 30 83",
    "sg:postcode":"18320",
    "sg:province":"Granada",
    "wof:name":"Vista Nevada Gasoleo A Domicilio S.l.",
    "wof:placetype":"venue"
},
  "geometry": {"coordinates":[-3.7262268066,37.1913642883],"type":"Point"}
}