{
  "type": "Feature",
  "properties": {
    "iso:country":"ES",
    "sg:address":"Calle de Francisco Baldoma, 59",
    "sg:city":"Valencia",
    "sg:orig_category":"Art\u00cdculos De Madera (fabricaci\u00d3n Y Al Por Mayor)",
    "sg:phone":"+34 963 71 27 10",
    "sg:postcode":"46011",
    "sg:province":"Valencia",
    "wof:name":"Decoraciones Valencia S.a.",
    "wof:placetype":"venue"
},
  "geometry": {"coordinates":[-0.3335140049,39.4662780762],"type":"Point"}
}