{
  "type": "Feature",
  "properties": {
    "addr:full":"Carrer de Arago, 33 Palma Islas Baleares 07005",
    "addr:housenumber":"33",
    "addr:postcode":"07005",
    "addr:street":"Carrer De Arago",
    "iso:country":"ES",
    "sg:address":"Carrer de Arago, 33",
    "sg:city":"Palma",
    "sg:orig_category":"Servicios Gsm",
    "sg:phone":"+34 971 77 43 80",
    "sg:postcode":"07005",
    "sg:province":"Islas Baleares",
    "sg:website":"www.teabla.es",
    "wof:name":"Teabla S.a.",
    "wof:placetype":"venue"
},
  "geometry": {"coordinates":[2.6589291096,39.5754470825],"type":"Point"}
}