{
  "type": "Feature",
  "properties": {
    "iso:country":"ES",
    "sg:address":"Plaz San Lazaro, 1",
    "sg:city":"Zamora",
    "sg:orig_category":"Iglesia Cat\u00d3lica",
    "sg:phone":"+34 980 52 70 29",
    "sg:postcode":"49005",
    "sg:province":"Zamora",
    "wof:name":"Parroquia De San Lazaro",
    "wof:placetype":"venue"
},
  "geometry": {"coordinates":[-5.7499670982,41.5058441162],"type":"Point"}
}