{
  "type": "Feature",
  "properties": {
    "iso:country":"ES",
    "sg:address":"Calle de Diego De Leon, 55",
    "sg:city":"Madrid",
    "sg:orig_category":"Electricidad, Electr\u00d3nica: Suministros (al Por Menor)",
    "sg:phone":"+34 914 01 36 08",
    "sg:postcode":"28006",
    "sg:province":"Madrid",
    "wof:name":"Gocar S.a.",
    "wof:placetype":"venue"
},
  "geometry": {"coordinates":[-3.6771008968,40.4347877502],"type":"Point"}
}