{
  "type": "Feature",
  "properties": {
    "iso:country":"ES",
    "sg:address":"Calle de Salamanca, 1",
    "sg:city":"Medina-sidonia",
    "sg:orig_category":"Muebles, Minoristas",
    "sg:phone":"+34 956 41 07 00",
    "sg:postcode":"11170",
    "sg:province":"C\u00e1diz",
    "wof:name":"Muebles Miguel Acedo S.l.",
    "wof:placetype":"venue"
},
  "geometry": {"coordinates":[-5.9287910461,36.4636001587],"type":"Point"}
}