{
  "type": "Feature",
  "properties": {
    "addr:full":"Av Herois De 1808 (dels), 28 Arbo\u00e7 Tarragona 43720",
    "addr:housenumber":"28",
    "addr:postcode":"43720",
    "addr:street":"Av Herois De 1808 Dels",
    "iso:country":"ES",
    "sg:address":"Av Herois De 1808 (dels), 28",
    "sg:city":"Arbo\u00e7",
    "sg:orig_category":"Chapister\u00cda",
    "sg:phone":"+34 977 67 11 06",
    "sg:postcode":"43720",
    "sg:province":"Tarragona",
    "wof:name":"J.c. Plancha Y Pintura S.l.",
    "wof:placetype":"venue"
},
  "geometry": {"coordinates":[1.6021560431,41.2644081116],"type":"Point"}
}