{
  "type": "Feature",
  "properties": {
    "addr:full":"Calle de Jacobo Camarero, 7 Albolote Granada 18220",
    "addr:housenumber":"7",
    "addr:postcode":"18220",
    "addr:street":"Calle De Jacobo Camarero",
    "iso:country":"ES",
    "sg:address":"Calle de Jacobo Camarero, 7",
    "sg:city":"Albolote",
    "sg:orig_category":"Imprenta",
    "sg:phone":"+34 958 46 81 99",
    "sg:postcode":"18220",
    "sg:province":"Granada",
    "wof:name":"Ribas Garcia Alberto",
    "wof:placetype":"venue"
},
  "geometry": {"coordinates":[-3.6530690193,37.2281188965],"type":"Point"}
}