{
  "type": "Feature",
  "properties": {
    "addr:full":"Calle de Doctor Criado, 9 Madrid Madrid 28021",
    "addr:housenumber":"9",
    "addr:postcode":"madrid;28021",
    "addr:street":"Calle De Doctor Criado",
    "iso:country":"ES",
    "sg:address":"Calle de Doctor Criado, 9",
    "sg:city":"Madrid",
    "sg:orig_category":"Comerciantes Al Por Mayor De Vinos, Licores Y Alcoholes",
    "sg:phone":"+34 917 97 30 40",
    "sg:postcode":"28021",
    "sg:province":"Madrid",
    "wof:name":"Serradilla Sanchez Francisco",
    "wof:placetype":"venue"
},
  "geometry": {"coordinates":[-3.7043960094,40.3480873108],"type":"Point"}
}