{
  "type": "Feature",
  "properties": {
    "iso:country":"ES",
    "sg:address":"Rua Ecuador, 75",
    "sg:city":"Vigo",
    "sg:orig_category":"Electrodom\u00c9sticos (al Por Menor)",
    "sg:phone":"+34 986 48 24 55",
    "sg:postcode":"36204",
    "sg:province":"Pontevedra",
    "wof:name":"Valle Garcia Jesus",
    "wof:placetype":"venue"
},
  "geometry": {"coordinates":[-8.7162809372,42.2323074341],"type":"Point"}
}