{
  "type": "Feature",
  "properties": {
    "addr:full":"Calle de Milagrosa, 48 Marchena Sevilla 41620",
    "addr:housenumber":"48",
    "addr:postcode":"41620",
    "addr:street":"Calle De Milagrosa",
    "iso:country":"ES",
    "sg:address":"Calle de Milagrosa, 48",
    "sg:city":"Marchena",
    "sg:orig_category":"Abogados",
    "sg:phone":"+34 955 84 72 69",
    "sg:postcode":"41620",
    "sg:province":"Sevilla",
    "wof:name":"Alvarez Alvarez Antonia",
    "wof:placetype":"venue"
},
  "geometry": {"coordinates":[-5.4179720879,37.3241767883],"type":"Point"}
}