{
  "type": "Feature",
  "properties": {
    "iso:country":"ES",
    "sg:address":"Carrer de Quetzal, 19",
    "sg:city":"Barcelona",
    "sg:orig_category":"Ingeniero",
    "sg:phone":"+34 934 32 29 95",
    "sg:postcode":"08014",
    "sg:province":"Barcelona",
    "sg:website":"www.fadisel.com",
    "wof:name":"Fadisel S.l.",
    "wof:placetype":"venue"
},
  "geometry": {"coordinates":[2.1332850456,41.3672714233],"type":"Point"}
}