{
  "type": "Feature",
  "properties": {
    "iso:country":"ES",
    "sg:address":"Calle de Ercilla, 1",
    "sg:city":"Bilbao",
    "sg:orig_category":"Administradores De Bienes Y Delegados De Comunidades De Propietarios",
    "sg:phone":"+34 944 23 16 54",
    "sg:postcode":"48009",
    "sg:province":"Vizcaya",
    "wof:name":"Azcona Jauregui Jose Pedro",
    "wof:placetype":"venue"
},
  "geometry": {"coordinates":[-2.9299960136,43.2651748657],"type":"Point"}
}