{
  "type": "Feature",
  "properties": {
    "iso:country":"ES",
    "sg:address":"Calle de General Mola, 11",
    "sg:city":"Autilla Pino",
    "sg:orig_category":"Empresas De Carpinter\u00cda Met\u00c1lica",
    "sg:phone":"+34 979 76 91 81",
    "sg:postcode":"34170",
    "sg:province":"Palencia",
    "wof:name":"Martin Villamediana Jose Javier",
    "wof:placetype":"venue"
},
  "geometry": {"coordinates":[-4.6619682312,42.0160064697],"type":"Point"}
}