{
  "type": "Feature",
  "properties": {
    "iso:country":"ES",
    "sg:address":"Rua Aragon, 114",
    "sg:city":"Vigo",
    "sg:orig_category":"Centros De Educaci\u00d3n Especial",
    "sg:phone":"+34 986 37 42 78",
    "sg:postcode":"36206",
    "sg:province":"Pontevedra",
    "wof:name":"Centro De Educacion Preescolar",
    "wof:placetype":"venue"
},
  "geometry": {"coordinates":[-8.7007665634,42.2378959656],"type":"Point"}
}