{
  "type": "Feature",
  "properties": {
    "iso:country":"ES",
    "sg:address":"C/ Sant Mer, 2",
    "sg:city":"Banyoles",
    "sg:orig_category":"Asociaciones, Organismos Culturales Y Socioeducativos",
    "sg:phone":"+34 972 57 61 54",
    "sg:postcode":"17820",
    "sg:province":"Girona",
    "wof:name":"Muntatages I Manteniments Girona S.l.",
    "wof:placetype":"venue"
},
  "geometry": {"coordinates":[2.7633519173,42.1229019165],"type":"Point"}
}