{
  "type": "Feature",
  "properties": {
    "addr:full":"Diseminados, S/n Tamarite Litera Huesca 22550",
    "addr:housenumber":"s",
    "addr:postcode":"22550",
    "addr:street":"Diseminados;/ N Tamarite",
    "iso:country":"ES",
    "sg:address":"Diseminados, S/n",
    "sg:city":"Tamarite Litera",
    "sg:orig_category":"Producci\u00d3n, Venta De Productos De Agricultura Biol\u00d3gica",
    "sg:phone":"+34 974 42 03 32",
    "sg:postcode":"22550",
    "sg:province":"Huesca",
    "wof:name":"Gabas Cortinat Jose Maria",
    "wof:placetype":"venue"
},
  "geometry": {"coordinates":[0.4240469933,41.8659324646],"type":"Point"}
}