{
  "type": "Feature",
  "properties": {
    "addr:full":"Avgd Alcalde Rovira Roure, 40 Lleida Lleida 25006",
    "addr:housenumber":"40",
    "addr:postcode":"25006",
    "addr:street":"Alcalde Rovira Roure",
    "iso:country":"ES",
    "sg:address":"Avgd Alcalde Rovira Roure, 40",
    "sg:city":"Lleida",
    "sg:orig_category":"Estancos",
    "sg:phone":"+34 973 23 08 29",
    "sg:postcode":"25006",
    "sg:province":"Lleida",
    "wof:name":"Ochagavia Rodriguez Jose Juan",
    "wof:placetype":"venue"
},
  "geometry": {"coordinates":[0.6172829866,41.6222991943],"type":"Point"}
}