{
  "type": "Feature",
  "properties": {
    "iso:country":"ES",
    "sg:address":"Carrer de Mallorca, 437",
    "sg:city":"Barcelona",
    "sg:orig_category":"Prendas Y Chalecos De Punto (al Por Menor)",
    "sg:phone":"+34 934 56 86 67",
    "sg:postcode":"08013",
    "sg:province":"Barcelona",
    "wof:name":"Junyent Rodriguez Albert",
    "wof:placetype":"venue"
},
  "geometry": {"coordinates":[2.1776130199,41.4052467346],"type":"Point"}
}