{
  "type": "Feature",
  "properties": {
    "iso:country":"ES",
    "sg:address":"Col Requena, S/n",
    "sg:city":"Alacant",
    "sg:orig_category":"Farmacias",
    "sg:phone":"+34 965 18 38 40",
    "sg:postcode":"03014",
    "sg:province":"Alicante",
    "wof:name":"Martinez Botella Juan Antonio",
    "wof:placetype":"venue"
},
  "geometry": {"coordinates":[-0.4804739952,38.3440856934],"type":"Point"}
}