{
  "type": "Feature",
  "properties": {
    "iso:country":"ES",
    "sg:address":"Plaz Encarnacion (la), 5",
    "sg:city":"Arjonilla",
    "sg:orig_category":"F\u00c1bricas De Ladrillo Y Tejas",
    "sg:phone":"+34 953 52 00 31",
    "sg:postcode":"23750",
    "sg:province":"Ja\u00e9n",
    "sg:website":"www.garciamoron.com",
    "wof:name":"S.a.t.garcia Moron",
    "wof:placetype":"venue"
},
  "geometry": {"coordinates":[-4.1077151299,37.9744873047],"type":"Point"}
}