{
  "type": "Feature",
  "properties": {
    "addr:full":"Avda V Centenario, 1 Playa Americas Santa Cruz De Tenerife 38660",
    "addr:housenumber":"1",
    "addr:postcode":"38660",
    "addr:street":"Avda V Centenario;Americas",
    "iso:country":"ES",
    "sg:address":"Avda V Centenario, 1",
    "sg:city":"Playa Americas",
    "sg:orig_category":"Alquiler De Veh\u00cdculos: Turismos Y Utilitarios",
    "sg:phone":"+34 922 75 23 54",
    "sg:postcode":"38660",
    "sg:province":"Santa Cruz De Tenerife",
    "wof:name":"Atlas Cars S.l.",
    "wof:placetype":"venue"
},
  "geometry": {"coordinates":[-16.7268848419,28.0673999786],"type":"Point"}
}