{
  "type": "Feature",
  "properties": {
    "iso:country":"ES",
    "sg:address":"Avda Camilo Alonso Vega, 4",
    "sg:city":"Santander",
    "sg:orig_category":"Sales (al Por Mayor)",
    "sg:phone":"+34 942 23 31 69",
    "sg:postcode":"39007",
    "sg:province":"Cantabria",
    "wof:name":"Bermejo Estebanez Ana Maria",
    "wof:placetype":"venue"
},
  "geometry": {"coordinates":[-3.8262689114,43.4589309692],"type":"Point"}
}