{
  "type": "Feature",
  "properties": {
    "addr:full":"Calle de Cigue\u00d1a (la), 27 Logro\u00f1o La Rioja 26004",
    "addr:housenumber":"27",
    "addr:postcode":"26004",
    "addr:street":"Calle De Ciguen\u0303A La;Rioja",
    "iso:country":"ES",
    "sg:address":"Calle de Cigue\u00d1a (la), 27",
    "sg:city":"Logro\u00f1o",
    "sg:orig_category":"Alquiler De V\u00cddeo",
    "sg:phone":"+34 941 24 54 34",
    "sg:postcode":"26004",
    "sg:province":"La Rioja",
    "wof:name":"Jimeno Rojas Pedro Jose",
    "wof:placetype":"venue"
},
  "geometry": {"coordinates":[-2.4320800304,42.4651412964],"type":"Point"}
}