{
  "type": "Feature",
  "properties": {
    "addr:full":"Poligono Vadillo, Km. 0002,5 Motril Granada 18600",
    "addr:postcode":"18600",
    "addr:street":"Vadillo Km. 0002,5;Granada",
    "iso:country":"ES",
    "sg:address":"Poligono Vadillo, Km. 0002,5",
    "sg:city":"Motril",
    "sg:orig_category":"Aparatos E Instalaci\u00d3n De Regad\u00cdos",
    "sg:phone":"+34 958 83 38 70",
    "sg:postcode":"18600",
    "sg:province":"Granada",
    "wof:name":"Montajes Del Guadalfeo S.l.",
    "wof:placetype":"venue"
},
  "geometry": {"coordinates":[-3.5152790546,36.7456130981],"type":"Point"}
}