{
  "type": "Feature",
  "properties": {
    "addr:full":"Barr Carrimon, 5 Renedo Cantabria 39470",
    "addr:housenumber":"5",
    "addr:postcode":"39470",
    "addr:street":"Carrimon",
    "iso:country":"ES",
    "sg:address":"Barr Carrimon, 5",
    "sg:city":"Renedo",
    "sg:orig_category":"Contenedores (mercanc\u00cdas)",
    "sg:phone":"+34 942 57 09 17",
    "sg:postcode":"39470",
    "sg:province":"Cantabria",
    "wof:name":"Santander Gonzalez Emilio",
    "wof:placetype":"venue"
},
  "geometry": {"coordinates":[-3.9473180771,43.3530044556],"type":"Point"}
}