{
  "type": "Feature",
  "properties": {
    "addr:full":"Calle de Domingo Garcia Regueral, 5 Langreo Asturias 33930",
    "addr:housenumber":"5",
    "addr:postcode":"33930",
    "addr:street":"Calle De Domingo Garcia Regueral",
    "iso:country":"ES",
    "sg:address":"Calle de Domingo Garcia Regueral, 5",
    "sg:city":"Langreo",
    "sg:orig_category":"Chapister\u00cda",
    "sg:phone":"+34 985 69 05 06",
    "sg:postcode":"33930",
    "sg:province":"Asturias",
    "wof:name":"Gajersutu S.l.",
    "wof:placetype":"venue"
},
  "geometry": {"coordinates":[-5.6898989677,43.312412262],"type":"Point"}
}