{
  "type": "Feature",
  "properties": {
    "iso:country":"ES",
    "sg:address":"Avda America (de), 6",
    "sg:city":"Granada",
    "sg:orig_category":"Farmacias",
    "sg:phone":"+34 958 13 33 13",
    "sg:postcode":"18006",
    "sg:province":"Granada",
    "wof:name":"Farmacia Garcia-olmedo C.b.",
    "wof:placetype":"venue"
},
  "geometry": {"coordinates":[-3.6010398865,37.1621856689],"type":"Point"}
}