{
  "type": "Feature",
  "properties": {
    "iso:country":"ES",
    "sg:address":"Calle de Alta Del Mar, 67",
    "sg:city":"Valencia",
    "sg:orig_category":"Bazares, Art\u00cdculos De Limpieza Y De Cocina (al Por Menor)",
    "sg:phone":"+34 963 67 74 54",
    "sg:postcode":"46024",
    "sg:province":"Valencia",
    "wof:name":"Rodritien S.l.",
    "wof:placetype":"venue"
},
  "geometry": {"coordinates":[-0.3337978125,39.4487838745],"type":"Point"}
}