{
  "type": "Feature",
  "properties": {
    "addr:full":"Carrer de Pallars, 233 Barcelona Barcelona 08005",
    "addr:housenumber":"233",
    "addr:postcode":"08005",
    "addr:street":"Carrer De Pallars",
    "iso:country":"ES",
    "sg:address":"Carrer de Pallars, 233",
    "sg:city":"Barcelona",
    "sg:orig_category":"Telas Y Sedas (al Por Menor)",
    "sg:phone":"+34 933 00 03 84",
    "sg:postcode":"08005",
    "sg:province":"Barcelona",
    "wof:name":"Ros Aira Andres",
    "wof:placetype":"venue"
},
  "geometry": {"coordinates":[2.1998050213,41.4028778076],"type":"Point"}
}