{
  "type": "Feature",
  "properties": {
    "iso:country":"ES",
    "sg:address":"Av Goles De L'ebre, 56",
    "sg:city":"Deltebre",
    "sg:orig_category":"Molduras, Junquillos, Listones Y Molduras Perforadas",
    "sg:phone":"+34 977 48 09 65",
    "sg:postcode":"43580",
    "sg:province":"Tarragona",
    "wof:name":"Ramirez Gonzalez Catalina",
    "wof:placetype":"venue"
},
  "geometry": {"coordinates":[0.7282419801,40.7201690674],"type":"Point"}
}