{
  "type": "Feature",
  "properties": {
    "iso:country":"ES",
    "sg:address":"Extramuros, 15",
    "sg:city":"Saucejo",
    "sg:orig_category":"Transportes Por V\u00cdas Navegables",
    "sg:phone":"+34 955 82 41 44",
    "sg:postcode":"41650",
    "sg:province":"Sevilla",
    "wof:name":"Campos Rivera Juan",
    "wof:placetype":"venue"
},
  "geometry": {"coordinates":[-5.0969829559,37.069519043],"type":"Point"}
}