{
  "type": "Feature",
  "properties": {
    "iso:country":"ES",
    "sg:address":"Calle de Camino Nuevo (del), 177",
    "sg:city":"Alcobendas",
    "sg:orig_category":"Centros Empresariales",
    "sg:phone":"+34 916 50 00 72",
    "sg:postcode":"28109",
    "sg:province":"Madrid",
    "wof:name":"Bacadora S.l.",
    "wof:placetype":"venue"
},
  "geometry": {"coordinates":[-3.6355919838,40.5233154297],"type":"Point"}
}