{
  "type": "Feature",
  "properties": {
    "addr:full":"Carrer de Bruc, 14 Barcelona Barcelona 08010",
    "addr:housenumber":"14",
    "addr:postcode":"08010",
    "addr:street":"Carrer De Bruc",
    "iso:country":"ES",
    "sg:address":"Carrer de Bruc, 14",
    "sg:city":"Barcelona",
    "sg:orig_category":"Ropa Para Se\u00d1oras (al Por Menor)",
    "sg:phone":"+34 933 17 10 19",
    "sg:postcode":"08010",
    "sg:province":"Barcelona",
    "wof:name":"Confecciones Cunbur S.a.",
    "wof:placetype":"venue"
},
  "geometry": {"coordinates":[2.1751539707,41.3902702332],"type":"Point"}
}