{
  "type": "Feature",
  "properties": {
    "iso:country":"ES",
    "sg:address":"Pase Alberto Palacios, 18",
    "sg:city":"Madrid",
    "sg:orig_category":"Pescader\u00cdas (al Por Menor)",
    "sg:phone":"+34 917 98 61 29",
    "sg:postcode":"28021",
    "sg:province":"Madrid",
    "wof:name":"Alvarez Barrio Jose",
    "wof:placetype":"venue"
},
  "geometry": {"coordinates":[-3.7109069824,40.346206665],"type":"Point"}
}