{
  "type": "Feature",
  "properties": {
    "iso:country":"ES",
    "sg:address":"Calle de Virgen Del Robledo, 110",
    "sg:city":"Constantina",
    "sg:orig_category":"Charcuter\u00cdas (al Por Mayor)",
    "sg:phone":"+34 955 88 12 66",
    "sg:postcode":"41450",
    "sg:province":"Sevilla",
    "wof:name":"Izquierdo Ricardo Francisco",
    "wof:placetype":"venue"
},
  "geometry": {"coordinates":[-5.6235890388,37.8805084229],"type":"Point"}
}