{
  "type": "Feature",
  "properties": {
    "addr:full":"Avda General Franco, 105 Santa Uxia De Ribeira A Coru\u00f1a 15960",
    "addr:housenumber":"105",
    "addr:postcode":"15960",
    "addr:street":"Avda General Franco;Corun\u0303A",
    "iso:country":"ES",
    "sg:address":"Avda General Franco, 105",
    "sg:city":"Santa Uxia De Ribeira",
    "sg:orig_category":"Supermercados Y Hipermercados",
    "sg:phone":"+34 981 87 39 08",
    "sg:postcode":"15960",
    "sg:province":"A Coru\u00f1a",
    "wof:name":"Sieira Pena Jose",
    "wof:placetype":"venue"
},
  "geometry": {"coordinates":[-8.9929037094,42.5581512451],"type":"Point"}
}