{
  "type": "Feature",
  "properties": {
    "addr:full":"Calle de Pastor Diaz, 62 Viveiro Lugo 27850",
    "addr:housenumber":"62",
    "addr:postcode":"27850",
    "addr:street":"Calle De Pastor Diaz",
    "iso:country":"ES",
    "sg:address":"Calle de Pastor Diaz, 62",
    "sg:city":"Viveiro",
    "sg:orig_category":"Bazares, Art\u00cdculos De Limpieza Y De Cocina (al Por Menor)",
    "sg:phone":"+34 982 56 05 28",
    "sg:postcode":"27850",
    "sg:province":"Lugo",
    "wof:name":"Fernandez Llanderrozas Balbino",
    "wof:placetype":"venue"
},
  "geometry": {"coordinates":[-7.5959348679,43.6629714966],"type":"Point"}
}