{
  "type": "Feature",
  "properties": {
    "iso:country":"ES",
    "sg:address":"Avda Blasco Iba\u00d1ez, 82",
    "sg:city":"Albal",
    "sg:orig_category":"Fabricaci\u00d3n De Taburetes, Sillas Y Sillones",
    "sg:phone":"+34 961 26 19 64",
    "sg:postcode":"46470",
    "sg:province":"Valencia",
    "wof:name":"Collado Enguita Vicente",
    "wof:placetype":"venue"
},
  "geometry": {"coordinates":[-0.406208992,39.3964500427],"type":"Point"}
}