{
  "type": "Feature",
  "properties": {
    "addr:full":"Carrer de Aigues Del Llobregat, 40 Hospitalet Llobregat Barcelona 08905",
    "addr:housenumber":"40",
    "addr:postcode":"08905",
    "addr:street":"Carrer De Aigues Del Llobregat",
    "iso:country":"ES",
    "sg:address":"Carrer de Aigues Del Llobregat, 40",
    "sg:city":"Hospitalet Llobregat",
    "sg:orig_category":"Peluquer\u00cdas, Peluquer\u00cda Mixta",
    "sg:phone":"+34 934 48 32 10",
    "sg:postcode":"08905",
    "sg:province":"Barcelona",
    "wof:name":"Caballero Osorio Tatiana",
    "wof:placetype":"venue"
},
  "geometry": {"coordinates":[2.107847929,41.3735237122],"type":"Point"}
}