{
  "type": "Feature",
  "properties": {
    "addr:full":"Calle de Meson De Paredes, 19 Madrid Madrid 28012",
    "addr:housenumber":"19",
    "addr:postcode":"madrid;28012",
    "addr:street":"Calle De Meson De Paredes",
    "iso:country":"ES",
    "sg:address":"Calle de Meson De Paredes, 19",
    "sg:city":"Madrid",
    "sg:orig_category":"Ropa Para Se\u00d1oras Y Caballeros (al Por Menor)",
    "sg:phone":"+34 915 28 08 59",
    "sg:postcode":"28012",
    "sg:province":"Madrid",
    "wof:name":"Dagafer  Abdul Zahra",
    "wof:placetype":"venue"
},
  "geometry": {"coordinates":[-3.7045059204,40.4106216431],"type":"Point"}
}