{
  "type": "Feature",
  "properties": {
    "iso:country":"ES",
    "sg:address":"Carrer de Binefar, 37",
    "sg:city":"Barcelona",
    "sg:orig_category":"Metales (labores, Pulido)",
    "sg:phone":"+34 932 78 30 24",
    "sg:postcode":"08020",
    "sg:province":"Barcelona",
    "wof:name":"Mecanizados Almi S.l.",
    "wof:placetype":"venue"
},
  "geometry": {"coordinates":[2.2055590153,41.4267997742],"type":"Point"}
}