{
  "type": "Feature",
  "properties": {
    "addr:full":"Calle de Fernandez Cuevas, 18 Melilla Melilla 52005",
    "addr:housenumber":"18",
    "addr:postcode":"52005",
    "addr:street":"Calle De Fernandez Cuevas",
    "iso:country":"ES",
    "sg:address":"Calle de Fernandez Cuevas, 18",
    "sg:city":"Melilla",
    "sg:orig_category":"Art\u00cdculos De Regalo (al Por Menor)",
    "sg:phone":"+34 952 67 91 01",
    "sg:postcode":"52005",
    "sg:province":"Melilla",
    "wof:name":"Retamero Pascual Antonia",
    "wof:placetype":"venue"
},
  "geometry": {"coordinates":[-2.9556701183,35.2835693359],"type":"Point"}
}