{
  "type": "Feature",
  "properties": {
    "iso:country":"ES",
    "sg:address":"Carrer de Nord, 3",
    "sg:city":"Garriga",
    "sg:orig_category":"Molduras, Junquillos, Listones Y Molduras Perforadas",
    "sg:phone":"+34 938 71 59 16",
    "sg:postcode":"08530",
    "sg:province":"Barcelona",
    "wof:name":"Muela Moreno Jose",
    "wof:placetype":"venue"
},
  "geometry": {"coordinates":[2.2852120399,41.690536499],"type":"Point"}
}