{
  "type": "Feature",
  "properties": {
    "addr:full":"Av Antoni Maura, 60 Inca Islas Baleares 07300",
    "addr:housenumber":"60",
    "addr:postcode":"07300",
    "addr:street":"Av Antoni Maura",
    "iso:country":"ES",
    "sg:address":"Av Antoni Maura, 60",
    "sg:city":"Inca",
    "sg:orig_category":"Cueros Y Pieles (al Por Mayor)",
    "sg:phone":"+34 971 50 22 75",
    "sg:postcode":"07300",
    "sg:province":"Islas Baleares",
    "wof:name":"Sarrio Montero Candido",
    "wof:placetype":"venue"
},
  "geometry": {"coordinates":[2.9027900696,39.72108078],"type":"Point"}
}