{
  "type": "Feature",
  "properties": {
    "iso:country":"ES",
    "sg:address":"Carr Estany Petit, 6",
    "sg:city":"Platja D'alcudia",
    "sg:orig_category":"Centros De Coordinaci\u00d3n",
    "sg:phone":"+34 971 89 07 86",
    "sg:postcode":"07408",
    "sg:province":"Islas Baleares",
    "wof:name":"Pol Bestard Miquel",
    "wof:placetype":"venue"
},
  "geometry": {"coordinates":[3.1075499058,39.8357009888],"type":"Point"}
}