{
  "type": "Feature",
  "properties": {
    "iso:country":"ES",
    "sg:address":"Calle de Jose Palanca, 1",
    "sg:city":"Malaga",
    "sg:orig_category":"Alquiler De V\u00cddeo",
    "sg:phone":"+34 952 35 54 06",
    "sg:postcode":"29003",
    "sg:province":"M\u00e1laga",
    "wof:name":"Lozano Diez De Los Rios Rafael",
    "wof:placetype":"venue"
},
  "geometry": {"coordinates":[-4.4472470284,36.7000694275],"type":"Point"}
}