{
  "type": "Feature",
  "properties": {
    "iso:country":"ES",
    "sg:address":"Plaz Hauries, 1",
    "sg:city":"Jerez De La Frontera",
    "sg:orig_category":"Inmobiliaria (agencias)",
    "sg:phone":"+34 956 30 72 53",
    "sg:postcode":"11405",
    "sg:province":"C\u00e1diz",
    "wof:name":"Inmobiliaria Tress S.a.",
    "wof:placetype":"venue"
},
  "geometry": {"coordinates":[-6.1076450348,36.6982269287],"type":"Point"}
}