{
  "type": "Feature",
  "properties": {
    "addr:full":"Carrer de Illes Balears (de Les), 9 Salou Tarragona 43840",
    "addr:postcode":"43840",
    "addr:street":"Carrer De Illes",
    "iso:country":"ES",
    "sg:address":"Carrer de Illes Balears (de Les), 9",
    "sg:city":"Salou",
    "sg:orig_category":"Agencias De Viajes",
    "sg:phone":"+34 977 38 39 09",
    "sg:postcode":"43840",
    "sg:province":"Tarragona",
    "wof:name":"Estival Holidays S.l.",
    "wof:placetype":"venue"
},
  "geometry": {"coordinates":[1.1332679987,41.0765762329],"type":"Point"}
}