{
  "type": "Feature",
  "properties": {
    "addr:full":"Avda Segovia, 15 Valladolid Valladolid 47013",
    "addr:housenumber":"15",
    "addr:postcode":"47013",
    "addr:street":"Avda Segovia",
    "iso:country":"ES",
    "sg:address":"Avda Segovia, 15",
    "sg:city":"Valladolid",
    "sg:orig_category":"Ropa Para Ni\u00d1os (al Por Menor)",
    "sg:phone":"+34 983 39 06 89",
    "sg:postcode":"47013",
    "sg:province":"Valladolid",
    "wof:name":"Tiendas De Bebelins 2006 S.l.",
    "wof:placetype":"venue"
},
  "geometry": {"coordinates":[-4.7208127975,41.6434326172],"type":"Point"}
}