{
  "type": "Feature",
  "properties": {
    "iso:country":"ES",
    "sg:address":"Ctra. Alajar, 1",
    "sg:city":"Aracena",
    "sg:orig_category":"Cooperativas Agr\u00cdcolas",
    "sg:phone":"+34 959 12 88 03",
    "sg:postcode":"21200",
    "sg:province":"Huelva",
    "wof:name":"Almazara Cooperativa San Blas",
    "wof:placetype":"venue"
},
  "geometry": {"coordinates":[-6.5684261322,37.8907623291],"type":"Point"}
}