{
  "type": "Feature",
  "properties": {
    "iso:country":"ES",
    "sg:address":"Ctra Jumilla, Km. 0003,5",
    "sg:city":"Estacion Ferrea",
    "sg:orig_category":"Material Y Herramientas Agr\u00cdcolas",
    "sg:phone":"+34 968 77 61 44",
    "sg:postcode":"30540",
    "sg:province":"Murcia",
    "wof:name":"Dimagro S.l.",
    "wof:placetype":"venue"
},
  "geometry": {"coordinates":[-1.3277870417,38.224407196],"type":"Point"}
}