{
  "type": "Feature",
  "properties": {
    "iso:country":"ES",
    "sg:address":"Carrer de Lepant, 347",
    "sg:city":"Barcelona",
    "sg:orig_category":"Arquitectos",
    "sg:phone":"+34 934 35 81 53",
    "sg:postcode":"08025",
    "sg:province":"Barcelona",
    "wof:name":"Garcia Gimeno Enric",
    "wof:placetype":"venue"
},
  "geometry": {"coordinates":[2.1715800762,41.4081535339],"type":"Point"}
}