{
  "type": "Feature",
  "properties": {
    "iso:country":"ES",
    "sg:address":"Calle de General Ricardos, 147",
    "sg:city":"Madrid",
    "sg:orig_category":"Empresas De Pintura Y Revestimientos",
    "sg:phone":"+34 914 71 26 71",
    "sg:postcode":"28019",
    "sg:province":"Madrid",
    "wof:name":"Calvo Sanchez Ignacio",
    "wof:placetype":"venue"
},
  "geometry": {"coordinates":[-3.7301239967,40.3894195557],"type":"Point"}
}