{
  "type": "Feature",
  "properties": {
    "iso:country":"ES",
    "sg:address":"Calle de Postas, 19",
    "sg:city":"Vitoria-gasteiz",
    "sg:orig_category":"Agencias Y Asesores De Publicidad",
    "sg:phone":"+34 945 23 22 38",
    "sg:postcode":"01004",
    "sg:province":"\u00c1lava",
    "wof:name":"Paisan Grisolia Soledad",
    "wof:placetype":"venue"
},
  "geometry": {"coordinates":[-2.6694989204,42.8457298279],"type":"Point"}
}