{
  "type": "Feature",
  "properties": {
    "addr:full":"I Poligono, S/n Soria Soria 42005",
    "addr:postcode":"42005",
    "addr:street":"I Poligono S / N",
    "iso:country":"ES",
    "sg:address":"I Poligono, S/n",
    "sg:city":"Soria",
    "sg:orig_category":"Cristaler\u00cdas",
    "sg:phone":"+34 975 23 04 83",
    "sg:postcode":"42005",
    "sg:province":"Soria",
    "wof:name":"Aseos 2000 S.l.",
    "wof:placetype":"venue"
},
  "geometry": {"coordinates":[-2.4798560143,41.9514465332],"type":"Point"}
}