{
  "type": "Feature",
  "properties": {
    "iso:country":"ES",
    "sg:address":"Ctra Estacion, 30",
    "sg:city":"Aranda Duero",
    "sg:orig_category":"Plomeros",
    "sg:phone":"+34 947 50 34 59",
    "sg:postcode":"09400",
    "sg:province":"Burgos",
    "wof:name":"Benito Picon Luis",
    "wof:placetype":"venue"
},
  "geometry": {"coordinates":[-3.6881229877,41.6646766663],"type":"Point"}
}