{
  "type": "Feature",
  "properties": {
    "addr:full":"Avda Europa, 58 Malaga M\u00e1laga 29003",
    "addr:housenumber":"58",
    "addr:postcode":"29003",
    "addr:street":"Avda Europa;Ma\u0301Laga",
    "iso:country":"ES",
    "sg:address":"Avda Europa, 58",
    "sg:city":"Malaga",
    "sg:orig_category":"Loter\u00cda Y T\u00d3mbola",
    "sg:phone":"+34 952 34 65 49",
    "sg:postcode":"29003",
    "sg:province":"M\u00e1laga",
    "wof:name":"Pardo Gomez Daniel",
    "wof:placetype":"venue"
},
  "geometry": {"coordinates":[-4.4511342049,36.7008743286],"type":"Point"}
}