{
  "type": "Feature",
  "properties": {
    "iso:country":"ES",
    "sg:address":"Calle de Juan De Balmaseda, 7",
    "sg:city":"Palencia",
    "sg:orig_category":"Reparaci\u00d3n Y Restauraci\u00d3n De Objetos Diversos",
    "sg:phone":"+34 979 72 66 75",
    "sg:postcode":"34004",
    "sg:province":"Palencia",
    "wof:name":"Barreda Sanchez Ana Isabel",
    "wof:placetype":"venue"
},
  "geometry": {"coordinates":[-4.5224142075,42.0032920837],"type":"Point"}
}