{
  "type": "Feature",
  "properties": {
    "addr:full":"Av Joan Miro, 279 Sant Agusti Islas Baleares 07015",
    "addr:housenumber":"279",
    "addr:postcode":"07015",
    "addr:street":"Av Joan Miro;Sant Agusti",
    "iso:country":"ES",
    "sg:address":"Av Joan Miro, 279",
    "sg:city":"Sant Agusti",
    "sg:orig_category":"Molduras, Junquillos, Listones Y Molduras Perforadas",
    "sg:phone":"+34 971 40 37 24",
    "sg:postcode":"07015",
    "sg:province":"Islas Baleares",
    "wof:name":"Zdraub Silin Galin",
    "wof:placetype":"venue"
},
  "geometry": {"coordinates":[2.6051235199,39.553768158],"type":"Point"}
}