{
  "type": "Feature",
  "properties": {
    "iso:country":"ES",
    "sg:address":"El Molino, 3",
    "sg:city":"Almodovar Campo",
    "sg:orig_category":"Mec\u00c1nico Del Autom\u00d3vil",
    "sg:phone":"+34 926 48 36 36",
    "sg:postcode":"13580",
    "sg:province":"Ciudad Real",
    "wof:name":"Taller Mecanico Automar S.l.l.",
    "wof:placetype":"venue"
},
  "geometry": {"coordinates":[-4.1693840027,38.7119865417],"type":"Point"}
}