{
  "type": "Feature",
  "properties": {
    "iso:country":"ES",
    "sg:address":"Calle de Marques De Lema, 13",
    "sg:city":"Madrid",
    "sg:orig_category":"Asociaciones Y Clubs Deportivos",
    "sg:phone":"+34 915 34 78 66",
    "sg:postcode":"28003",
    "sg:province":"Madrid",
    "sg:website":"www.gimnasiomuscle.es",
    "wof:name":"Manzano Velasco Manuel",
    "wof:placetype":"venue"
},
  "geometry": {"coordinates":[-3.7062990665,40.446269989],"type":"Point"}
}