{
  "type": "Feature",
  "properties": {
    "addr:full":"Ctra Vall D'uxo, Km. 0027,8 Nules Castell\u00f3n 12520",
    "addr:postcode":"12520",
    "addr:street":"Ctra Vall D'Uxo Km. 0027,8;Castello\u0301N",
    "iso:country":"ES",
    "sg:address":"Ctra Vall D'uxo, Km. 0027,8",
    "sg:city":"Nules",
    "sg:orig_category":"Arenas, Guijarros Y Granulados",
    "sg:phone":"+34 964 67 33 66",
    "sg:postcode":"12520",
    "sg:province":"Castell\u00f3n",
    "wof:name":"Transportes Martinez Alvaro Hermanos S. L.",
    "wof:placetype":"venue"
},
  "geometry": {"coordinates":[-0.166178003,39.8483543396],"type":"Point"}
}