{
  "type": "Feature",
  "properties": {
    "addr:full":"Carrer de Guardia Civil, De Sa, 8 Santanyi Islas Baleares 07650",
    "addr:housenumber":"8",
    "addr:postcode":"07650",
    "addr:street":"Carrer De Guardia;Santanyi Islas",
    "iso:country":"ES",
    "sg:address":"Carrer de Guardia Civil, De Sa, 8",
    "sg:city":"Santanyi",
    "sg:orig_category":"Arquitectos",
    "sg:phone":"+34 971 65 38 15",
    "sg:postcode":"07650",
    "sg:province":"Islas Baleares",
    "wof:name":"Amengual Coves Asociats S.l.",
    "wof:placetype":"venue"
},
  "geometry": {"coordinates":[3.1277854443,39.3513374329],"type":"Point"}
}