{
  "type": "Feature",
  "properties": {
    "addr:full":"Calle de Madrid, 29 Getafe Madrid 28901",
    "addr:housenumber":"29",
    "addr:postcode":"28901",
    "addr:street":"Calle De Madrid",
    "iso:country":"ES",
    "sg:address":"Calle de Madrid, 29",
    "sg:city":"Getafe",
    "sg:orig_category":"Medias Y Calcetines (al Por Menor)",
    "sg:phone":"+34 916 83 37 52",
    "sg:postcode":"28901",
    "sg:province":"Madrid",
    "wof:name":"Panty Y Socqs S.l.",
    "wof:placetype":"venue"
},
  "geometry": {"coordinates":[-3.7309670448,40.3065681458],"type":"Point"}
}