{
  "type": "Feature",
  "properties": {
    "iso:country":"ES",
    "sg:address":"Avda Ferrandis Salvador, 8",
    "sg:city":"Mas Dels Frares",
    "sg:orig_category":"Delegados, Agentes De Tr\u00c1nsito, Auxiliares De Transporte Internacional",
    "sg:phone":"+34 964 30 28 75",
    "sg:postcode":"12560",
    "sg:province":"Castell\u00f3n",
    "wof:name":"Iba\u00f1ez Cabedo Rafael",
    "wof:placetype":"venue"
},
  "geometry": {"coordinates":[0.0590550005,40.0523414612],"type":"Point"}
}