{
  "type": "Feature",
  "properties": {
    "iso:country":"ES",
    "sg:address":"Calle de Peru, 6",
    "sg:city":"Matas-pinar-monte Rozas",
    "sg:orig_category":"Ingeniero",
    "sg:phone":"+34 916 30 70 60",
    "sg:postcode":"28290",
    "sg:province":"Madrid",
    "wof:name":"Hidtma S.l.",
    "wof:placetype":"venue"
},
  "geometry": {"coordinates":[-3.8968040943,40.5449180603],"type":"Point"}
}