{
  "type": "Feature",
  "properties": {
    "iso:country":"ES",
    "sg:address":"Carrer de Calderon, 44",
    "sg:city":"Sabadell",
    "sg:orig_category":"Peluqueros: De Se\u00d1oras",
    "sg:phone":"+34 937 26 17 97",
    "sg:postcode":"08201",
    "sg:province":"Barcelona",
    "wof:name":"Carreras Alonso Maria Angeles",
    "wof:placetype":"venue"
},
  "geometry": {"coordinates":[2.1060390472,41.5481987],"type":"Point"}
}