{
  "type": "Feature",
  "properties": {
    "iso:country":"ES",
    "sg:address":"Calle de Sahagun, 2",
    "sg:city":"Madrid",
    "sg:orig_category":"Papeler\u00cdas, Librer\u00cdas",
    "sg:phone":"+34 914 59 20 45",
    "sg:postcode":"28039",
    "sg:province":"Madrid",
    "wof:name":"Compte Fernandez Arturo",
    "wof:placetype":"venue"
},
  "geometry": {"coordinates":[-3.7080309391,40.4554748535],"type":"Point"}
}