{
  "type": "Feature",
  "properties": {
    "iso:country":"ES",
    "sg:address":"Avda Reyes Catolicos, 34",
    "sg:city":"Merida",
    "sg:orig_category":"Agencias Y Agentes Comerciales, Representantes",
    "sg:phone":"+34 924 37 17 39",
    "sg:postcode":"06800",
    "sg:province":"Badajoz",
    "wof:name":"Martin Del Viejo Josefina",
    "wof:placetype":"venue"
},
  "geometry": {"coordinates":[-6.3598690033,38.9123382568],"type":"Point"}
}