{
  "type": "Feature",
  "properties": {
    "iso:country":"ES",
    "sg:address":"Carr Sant Lloren\u00c7, 7",
    "sg:city":"Lloseta",
    "sg:orig_category":"Inform\u00c1tica (estudios, Servicios, Asesor\u00cda, Formaci\u00d3n)",
    "sg:phone":"+34 971 51 40 00",
    "sg:postcode":"07360",
    "sg:province":"Islas Baleares",
    "wof:name":"Abrines Capo Bartolome",
    "wof:placetype":"venue"
},
  "geometry": {"coordinates":[2.866922,39.719288],"type":"Point"}
}