{
  "type": "Feature",
  "properties": {
    "addr:full":"Calle de Luis De Mateo, 7 Casasimarro Cuenca 16239",
    "addr:housenumber":"7",
    "addr:postcode":"16239",
    "addr:street":"Calle De Luis De Mateo",
    "iso:country":"ES",
    "sg:address":"Calle de Luis De Mateo, 7",
    "sg:city":"Casasimarro",
    "sg:orig_category":"Asilos De Ancianos. Centros Privados",
    "sg:phone":"+34 967 48 70 43",
    "sg:postcode":"16239",
    "sg:province":"Cuenca",
    "wof:name":"Residencia Parroquial De La Tercera Edad Virgen De Las Nieves",
    "wof:placetype":"venue"
},
  "geometry": {"coordinates":[-2.044244051,39.3918113708],"type":"Point"}
}