{
  "type": "Feature",
  "properties": {
    "addr:full":"Carr Turia, 13 Albuixech Valencia 46550",
    "addr:housenumber":"13",
    "addr:postcode":"46550",
    "addr:street":"Carr Turia",
    "iso:country":"ES",
    "sg:address":"Carr Turia, 13",
    "sg:city":"Albuixech",
    "sg:classifiers":[
        {
            "category":"Manufacturing",
            "subcategory":"Metals",
            "type":"Manufacturing & Wholesale Goods"
        }
    ],
    "sg:phone":"+34 961 41 70 91",
    "sg:postcode":"46550",
    "sg:province":"Valencia",
    "sg:tags":[
        "en",
        "fundiciones"
    ],
    "wof:name":"Inva S.l.",
    "wof:placetype":"venue"
},
  "geometry": {"coordinates":[-0.3256070018,39.5474662781],"type":"Point"}
}