{
  "type": "Feature",
  "properties": {
    "iso:country":"ES",
    "sg:address":"Calle de Fabrica Nueva, 54",
    "sg:city":"Salobre\u00f1a",
    "sg:orig_category":"Frutas Y Legumbres Secas (al Por Mayor)",
    "sg:phone":"+34 958 61 27 25",
    "sg:postcode":"18680",
    "sg:province":"Granada",
    "wof:name":"Murcia Collado Jose Antonio",
    "wof:placetype":"venue"
},
  "geometry": {"coordinates":[-3.5852870941,36.7426605225],"type":"Point"}
}