{
  "type": "Feature",
  "properties": {
    "addr:full":"Av J Ortega Y Gasset (p I El Viso), 252 Malaga M\u00e1laga 29006",
    "addr:housenumber":"252",
    "addr:postcode":"29006",
    "addr:street":"Av J Ortega Y Gasset P;El Viso;Ma\u0301Laga",
    "iso:country":"ES",
    "sg:address":"Av J Ortega Y Gasset (p I El Viso), 252",
    "sg:city":"Malaga",
    "sg:orig_category":"Electrodom\u00c9sticos (al Por Menor)",
    "sg:phone":"+34 952 35 33 02",
    "sg:postcode":"29006",
    "sg:province":"M\u00e1laga",
    "wof:name":"Bazar San Juan S. A.",
    "wof:placetype":"venue"
},
  "geometry": {"coordinates":[-4.4743599892,36.7075576782],"type":"Point"}
}