{
  "type": "Feature",
  "properties": {
    "iso:country":"ES",
    "sg:address":"Ctra. Almuradiel, Km. 0008,0",
    "sg:city":"Castellar Santiago",
    "sg:orig_category":"Producci\u00d3n, Venta De Productos De Agricultura Biol\u00d3gica",
    "sg:phone":"+34 926 33 80 52",
    "sg:postcode":"13750",
    "sg:province":"Ciudad Real",
    "wof:name":"Navalaumbria S.a.",
    "wof:placetype":"venue"
},
  "geometry": {"coordinates":[-3.2815680504,38.5403747559],"type":"Point"}
}