{
  "type": "Feature",
  "properties": {
    "iso:country":"ES",
    "sg:address":"Calle de Lopez Allue, 6",
    "sg:city":"Zaragoza",
    "sg:orig_category":"Centros De Coordinaci\u00d3n",
    "sg:phone":"+34 976 35 13 33",
    "sg:postcode":"50005",
    "sg:province":"Zaragoza",
    "wof:name":"Gomez Vela Jose Angel",
    "wof:placetype":"venue"
},
  "geometry": {"coordinates":[-0.8941860199,41.6447982788],"type":"Point"}
}