{
  "type": "Feature",
  "properties": {
    "addr:full":"Avda Txikia, 28 Pinos Vizcaya 48940",
    "addr:housenumber":"28",
    "addr:postcode":"48940",
    "addr:street":"Avda Txikia",
    "iso:country":"ES",
    "sg:address":"Avda Txikia, 28",
    "sg:city":"Pinos",
    "sg:orig_category":"Agentes, Concesionarios Y Sucursales De Veh\u00cdculos",
    "sg:phone":"+34 944 31 54 62",
    "sg:postcode":"48940",
    "sg:province":"Vizcaya",
    "wof:name":"Japan Car S.a.",
    "wof:placetype":"venue"
},
  "geometry": {"coordinates":[-2.9860789776,43.3275489807],"type":"Point"}
}