{
  "type": "Feature",
  "properties": {
    "iso:country":"ES",
    "sg:address":"Avgd Verge, De La, S/n",
    "sg:city":"Campos",
    "sg:orig_category":"Mec\u00c1nico Del Autom\u00d3vil",
    "sg:phone":"+34 971 65 27 42",
    "sg:postcode":"07630",
    "sg:province":"Islas Baleares",
    "wof:name":"Artigues Manresa Juan",
    "wof:placetype":"venue"
},
  "geometry": {"coordinates":[2.997559309,39.4272499084],"type":"Point"}
}