{
  "type": "Feature",
  "properties": {
    "addr:full":"Almeiras, S/n Culleredo La Coru\u00f1a 15180",
    "addr:housenumber":"/ n",
    "addr:postcode":"15180",
    "addr:street":"Almeiras S;La Corun\u0303A",
    "iso:country":"ES",
    "sg:address":"Almeiras, S/n",
    "sg:city":"Culleredo",
    "sg:orig_category":"Maquinaria Para Industrias Diversas",
    "sg:phone":"+34 981 65 19 36",
    "sg:postcode":"15180",
    "sg:province":"La Coru\u00f1a",
    "sg:website":"www.cotelopalasmotor.com",
    "wof:name":"Palas Motor S.l.",
    "wof:placetype":"venue"
},
  "geometry": {"coordinates":[-8.3616485596,43.3068237305],"type":"Point"}
}