{
  "type": "Feature",
  "properties": {
    "addr:full":"Avda Juan Xxiii, 8 Jaca Huesca 22700",
    "addr:housenumber":"8",
    "addr:postcode":"22700",
    "addr:street":"Avda Juan Xxiii",
    "iso:country":"ES",
    "sg:address":"Avda Juan Xxiii, 8",
    "sg:city":"Jaca",
    "sg:orig_category":"Alimentaci\u00d3n General (al Por Mayor)",
    "sg:phone":"+34 974 36 13 04",
    "sg:postcode":"22700",
    "sg:province":"Huesca",
    "wof:name":"Bescos Rapun Maria Joaquina",
    "wof:placetype":"venue"
},
  "geometry": {"coordinates":[-0.5480650067,42.5737075806],"type":"Point"}
}