{
  "type": "Feature",
  "properties": {
    "addr:full":"Avda Monte Igueldo, 18 Madrid Madrid 28053",
    "addr:housenumber":"18",
    "addr:postcode":"madrid;28053",
    "addr:street":"Avda Monte Igueldo",
    "iso:country":"ES",
    "sg:address":"Avda Monte Igueldo, 18",
    "sg:city":"Madrid",
    "sg:orig_category":"Ropa Para Se\u00d1oras (al Por Menor)",
    "sg:phone":"+34 915 01 18 93",
    "sg:postcode":"28053",
    "sg:province":"Madrid",
    "wof:name":"Gonzalez Casero Roberto",
    "wof:placetype":"venue"
},
  "geometry": {"coordinates":[-3.6684720516,40.3964042664],"type":"Point"}
}