{
  "type": "Feature",
  "properties": {
    "iso:country":"ES",
    "sg:address":"Avda Ris, 3",
    "sg:city":"Noja",
    "sg:orig_category":"Frutas, Legumbres Frescas Y Tempranas (al Por Menor)",
    "sg:phone":"+34 942 67 54 47",
    "sg:postcode":"39180",
    "sg:province":"Cantabria",
    "wof:name":"Gonzalez Santana Josebe",
    "wof:placetype":"venue"
},
  "geometry": {"coordinates":[-3.5286402702,43.4805717468],"type":"Point"}
}