{
  "type": "Feature",
  "properties": {
    "iso:country":"ES",
    "sg:address":"Carrer de Escultors Claperos, 43",
    "sg:city":"Barcelona",
    "sg:orig_category":"Electrodom\u00c9sticos (fabricaci\u00d3n, Al Por Mayor)",
    "sg:phone":"+34 933 00 52 59",
    "sg:postcode":"08018",
    "sg:province":"Barcelona",
    "wof:name":"Electrodomesticos Peinado S. L.",
    "wof:placetype":"venue"
},
  "geometry": {"coordinates":[2.1891269684,41.4060058594],"type":"Point"}
}