{
  "type": "Feature",
  "properties": {
    "addr:full":"Polig. Ind. Ordes, 95 Conde La Coru\u00f1a 15680",
    "addr:housenumber":"95",
    "addr:postcode":"15680",
    "addr:street":"Polig. Ind. Ordes;Conde La Corun\u0303A",
    "iso:country":"ES",
    "sg:address":"Polig. Ind. Ordes, 95",
    "sg:city":"Conde",
    "sg:orig_category":"M\u00c1rmoles, Granitos Y Piedras Naturales",
    "sg:phone":"+34 981 69 74 53",
    "sg:postcode":"15680",
    "sg:province":"La Coru\u00f1a",
    "wof:name":"Marmoles Y Granitos Ordenes S.l.",
    "wof:placetype":"venue"
},
  "geometry": {"coordinates":[-8.3959693909,43.3714904785],"type":"Point"}
}