{
  "type": "Feature",
  "properties": {
    "iso:country":"ES",
    "sg:address":"Av Arraona, 58",
    "sg:city":"Barbera Valles",
    "sg:orig_category":"Materias Pl\u00c1sticas: Art\u00cdculos Para La Industria",
    "sg:phone":"+34 937 18 29 00",
    "sg:postcode":"08210",
    "sg:province":"Barcelona",
    "wof:name":"Industrial Falco S. L.",
    "wof:placetype":"venue"
},
  "geometry": {"coordinates":[2.1480300426,41.5246238708],"type":"Point"}
}