{
  "type": "Feature",
  "properties": {
    "addr:full":"Calle de Rafael Lucenqui, 10 Badajoz Badajoz 06004",
    "addr:housenumber":"10",
    "addr:postcode":"06004",
    "addr:street":"Calle De Rafael Lucenqui",
    "iso:country":"ES",
    "sg:address":"Calle de Rafael Lucenqui, 10",
    "sg:city":"Badajoz",
    "sg:orig_category":"Urbanistas",
    "sg:phone":"+34 924 25 76 55",
    "sg:postcode":"06004",
    "sg:province":"Badajoz",
    "wof:name":"Arcos Consulting De Arquitectura S.l.",
    "wof:placetype":"venue"
},
  "geometry": {"coordinates":[-6.9761857986,38.8703231812],"type":"Point"}
}