{
  "type": "Feature",
  "properties": {
    "addr:full":"Calle de Alcarria, 5 Gijon Asturias 33210",
    "addr:housenumber":"5",
    "addr:postcode":"33210",
    "addr:street":"Calle De Alcarria",
    "iso:country":"ES",
    "sg:address":"Calle de Alcarria, 5",
    "sg:city":"Gijon",
    "sg:orig_category":"Supermercados Y Hipermercados",
    "sg:phone":"+34 985 14 30 88",
    "sg:postcode":"33210",
    "sg:province":"Asturias",
    "wof:name":"Hijos De Luis Rodriguez S.a.",
    "wof:placetype":"venue"
},
  "geometry": {"coordinates":[-5.6701908112,43.5249481201],"type":"Point"}
}