{
  "type": "Feature",
  "properties": {
    "iso:country":"ES",
    "sg:address":"Calle de Tenesor, 19",
    "sg:city":"Monta\u00e7eta Del Calero",
    "sg:orig_category":"Chapister\u00cda",
    "sg:phone":"+34 928 69 70 19",
    "sg:postcode":"35200",
    "sg:province":"Las Palmas",
    "wof:name":"Santos Hernandez Ramon Jose",
    "wof:placetype":"venue"
},
  "geometry": {"coordinates":[-15.4144220352,28.0029888153],"type":"Point"}
}