{
  "type": "Feature",
  "properties": {
    "iso:country":"ES",
    "sg:address":"Calle de Guzman El Bueno, 38",
    "sg:city":"Madrid",
    "sg:orig_category":"Peluqueros: De Se\u00d1oras",
    "sg:phone":"+34 915 44 07 95",
    "sg:postcode":"28015",
    "sg:province":"Madrid",
    "wof:name":"Promociones Las Calandrinas S.l.",
    "wof:placetype":"venue"
},
  "geometry": {"coordinates":[-3.713078022,40.4346618652],"type":"Point"}
}