{
  "type": "Feature",
  "properties": {
    "iso:country":"ES",
    "sg:address":"Carr Llevant, (de), 23",
    "sg:city":"Carlet",
    "sg:orig_category":"Arboricultura Y Producci\u00d3n De Frutas",
    "sg:phone":"+34 962 53 80 10",
    "sg:postcode":"46240",
    "sg:province":"Valencia",
    "wof:name":"S.a.t. 9400 Vidasol S.r.l.",
    "wof:placetype":"venue"
},
  "geometry": {"coordinates":[-0.4882879853,39.2351531982],"type":"Point"}
}