{
  "type": "Feature",
  "properties": {
    "addr:full":"Urb Vaguadas, 10 Vaguadas Badajoz 06010",
    "addr:housenumber":"10",
    "addr:postcode":"06010",
    "addr:street":"Urb Vaguadas",
    "iso:country":"ES",
    "sg:address":"Urb Vaguadas, 10",
    "sg:city":"Vaguadas",
    "sg:orig_category":"Promotores Constructores",
    "sg:phone":"+34 924 26 75 11",
    "sg:postcode":"06010",
    "sg:province":"Badajoz",
    "wof:name":"Promociones Construcciones Y Gestion Godolid 9 S.l.",
    "wof:placetype":"venue"
},
  "geometry": {"coordinates":[-6.9633808136,38.8150863647],"type":"Point"}
}