{
  "type": "Feature",
  "properties": {
    "iso:country":"ES",
    "sg:address":"Calle de Virgen De Los Dolores, S/n",
    "sg:city":"Archidona",
    "sg:orig_category":"Producci\u00d3n, Comercio De Cereales",
    "sg:phone":"+34 952 71 41 36",
    "sg:postcode":"29300",
    "sg:province":"M\u00e1laga",
    "wof:name":"Molina Nu\u00f1ez Cristobal",
    "wof:placetype":"venue"
},
  "geometry": {"coordinates":[-4.3886861801,37.0920066833],"type":"Point"}
}