{
  "type": "Feature",
  "properties": {
    "addr:full":"Pase Flamencos (de Los), S/n Retamar Almer\u00eda 04130",
    "addr:postcode":"04130",
    "addr:street":"Flamencos;Los S / N Retamar",
    "iso:country":"ES",
    "sg:address":"Pase Flamencos (de Los), S/n",
    "sg:city":"Retamar",
    "sg:orig_category":"Asesor\u00cda Sobre Comunicaci\u00d3n De Empresas",
    "sg:phone":"+34 950 20 70 23",
    "sg:postcode":"04130",
    "sg:province":"Almer\u00eda",
    "wof:name":"Caparros Cervantes Francisca Maria",
    "wof:placetype":"venue"
},
  "geometry": {"coordinates":[-2.3529150486,36.8523406982],"type":"Point"}
}