{
  "type": "Feature",
  "properties": {
    "addr:full":"Calle de Ortega Y Gasset, 9 Elda Alicante 03600",
    "addr:housenumber":"9",
    "addr:postcode":"03600",
    "addr:street":"Calle De Ortega Y Gasset",
    "iso:country":"ES",
    "sg:address":"Calle de Ortega Y Gasset, 9",
    "sg:city":"Elda",
    "sg:orig_category":"Agencias Y Agentes Comerciales, Representantes",
    "sg:phone":"+34 966 98 05 90",
    "sg:postcode":"03600",
    "sg:province":"Alicante",
    "wof:name":"Sogorb Gomez Francisco",
    "wof:placetype":"venue"
},
  "geometry": {"coordinates":[-0.7952520251,38.4790802002],"type":"Point"}
}