{
  "type": "Feature",
  "properties": {
    "addr:full":"Calle de Rasca\u00d1a, 14 Valencia Valencia 46015",
    "addr:housenumber":"14",
    "addr:postcode":"46015",
    "addr:street":"Calle De Rascan\u0303A",
    "iso:country":"ES",
    "sg:address":"Calle de Rasca\u00d1a, 14",
    "sg:city":"Valencia",
    "sg:orig_category":"Asesor\u00cda Sobre Comunicaci\u00d3n De Empresas",
    "sg:phone":"+34 963 40 93 01",
    "sg:postcode":"46015",
    "sg:province":"Valencia",
    "wof:name":"Fonoservice S.a.",
    "wof:placetype":"venue"
},
  "geometry": {"coordinates":[-0.3959529996,39.4819145203],"type":"Point"}
}