{
  "type": "Feature",
  "properties": {
    "iso:country":"ES",
    "sg:address":"Avda Pirineos, 12",
    "sg:city":"Barbastro",
    "sg:orig_category":"Asesor\u00cda Fiscal Y Jur\u00cddica",
    "sg:phone":"+34 974 30 83 90",
    "sg:postcode":"22300",
    "sg:province":"Huesca",
    "wof:name":"Turbon Asesores Legales Y Tributarios S.l.",
    "wof:placetype":"venue"
},
  "geometry": {"coordinates":[0.1296110004,42.037437439],"type":"Point"}
}