{
  "type": "Feature",
  "properties": {
    "addr:full":"Carrer de Joan Salvat Papasseit, 49 Mataro Barcelona 08304",
    "addr:housenumber":"49",
    "addr:postcode":"08304",
    "addr:street":"Carrer De Joan Salvat Papasseit",
    "iso:country":"ES",
    "sg:address":"Carrer de Joan Salvat Papasseit, 49",
    "sg:city":"Mataro",
    "sg:orig_category":"Motocicletas (agentes, Concesionarios)",
    "sg:phone":"+34 937 98 79 75",
    "sg:postcode":"08304",
    "sg:province":"Barcelona",
    "wof:name":"Motos Dimoto S.l.",
    "wof:placetype":"venue"
},
  "geometry": {"coordinates":[2.4411098957,41.5535125732],"type":"Point"}
}