{
  "type": "Feature",
  "properties": {
    "addr:full":"Calle de Senador Castillo Olivares, 40 Palmas De Gran Canaria Las Palmas 35003",
    "addr:postcode":"35003",
    "addr:street":"Calle De Senador Castillo Olivares 40",
    "iso:country":"ES",
    "sg:address":"Calle de Senador Castillo Olivares, 40",
    "sg:city":"Palmas De Gran Canaria",
    "sg:orig_category":"Alimentaci\u00d3n General (al Por Menor)",
    "sg:phone":"+34 928 37 19 23",
    "sg:postcode":"35003",
    "sg:province":"Las Palmas",
    "wof:name":"Perez Arencibia Francisco Javier",
    "wof:placetype":"venue"
},
  "geometry": {"coordinates":[-15.4218492508,28.1111240387],"type":"Point"}
}