{
  "type": "Feature",
  "properties": {
    "addr:full":"Avda Constitucion, 93 Nules Castell\u00f3n 12520",
    "addr:housenumber":"93",
    "addr:postcode":"12520",
    "addr:street":"Avda Constitucion",
    "iso:country":"ES",
    "sg:address":"Avda Constitucion, 93",
    "sg:city":"Nules",
    "sg:orig_category":"Ense\u00d1anza, Formaci\u00d3n Profesional: Aprendizaje",
    "sg:phone":"+34 964 67 36 76",
    "sg:postcode":"12520",
    "sg:province":"Castell\u00f3n",
    "wof:name":"Generalitat Valenciana",
    "wof:placetype":"venue"
},
  "geometry": {"coordinates":[-0.1580779999,39.8496665955],"type":"Point"}
}