{
  "type": "Feature",
  "properties": {
    "addr:full":"Calle de Corregeria, 29 Valencia Valencia 46001",
    "addr:housenumber":"29",
    "addr:postcode":"46001",
    "addr:street":"Calle De Corregeria",
    "iso:country":"ES",
    "sg:address":"Calle de Corregeria, 29",
    "sg:city":"Valencia",
    "sg:orig_category":"Compraventa De Antig\u00dcedades",
    "sg:phone":"+34 963 91 12 89",
    "sg:postcode":"46001",
    "sg:province":"Valencia",
    "wof:name":"Gento Moya Angel",
    "wof:placetype":"venue"
},
  "geometry": {"coordinates":[-0.3807210028,39.4741744995],"type":"Point"}
}