{
  "type": "Feature",
  "properties": {
    "iso:country":"ES",
    "sg:address":"Calle de Fuerzas Armadas, 5",
    "sg:city":"Estepona",
    "sg:orig_category":"Asociaciones Y Clubs Deportivos",
    "sg:phone":"+34 952 80 01 59",
    "sg:postcode":"29680",
    "sg:province":"M\u00e1laga",
    "wof:name":"Infantes Caravaca Maria Del Carmen",
    "wof:placetype":"venue"
},
  "geometry": {"coordinates":[-5.1505770683,36.4274520874],"type":"Point"}
}