{
  "type": "Feature",
  "properties": {
    "addr:full":"Avda Alfonso Viii, 1 Plasencia C\u00e1ceres 10600",
    "addr:housenumber":"1",
    "addr:postcode":"10600",
    "addr:street":"Avda Alfonso Viii;Ca\u0301Ceres",
    "iso:country":"ES",
    "sg:address":"Avda Alfonso Viii, 1",
    "sg:city":"Plasencia",
    "sg:orig_category":"Cajas De Ahorro",
    "sg:phone":"+34 927 42 42 65",
    "sg:postcode":"10600",
    "sg:province":"C\u00e1ceres",
    "wof:name":"Caja De Ahorros Y Monte De Piedad De Cordoba",
    "wof:placetype":"venue"
},
  "geometry": {"coordinates":[-6.0864701271,40.0302047729],"type":"Point"}
}