{
  "type": "Feature",
  "properties": {
    "iso:country":"ES",
    "sg:address":"Calle de Mayor, S/n",
    "sg:city":"Fitero",
    "sg:orig_category":"Caf\u00c9s, Bares, Cervecer\u00cdas",
    "sg:phone":"+34 948 77 60 76",
    "sg:postcode":"31593",
    "sg:province":"Navarra",
    "wof:name":"Gonzalez Garbayo Tomas Y Julio S.cv.",
    "wof:placetype":"venue"
},
  "geometry": {"coordinates":[-1.8594089746,42.056930542],"type":"Point"}
}