{
  "type": "Feature",
  "properties": {
    "iso:country":"ES",
    "sg:address":"Pl Fiveller, 15",
    "sg:city":"Mataro",
    "sg:orig_category":"Soldadura Y Recortado A L\u00c1ser",
    "sg:phone":"+34 937 90 14 18",
    "sg:postcode":"08301",
    "sg:province":"Barcelona",
    "wof:name":"C.roca S.a.",
    "wof:placetype":"venue"
},
  "geometry": {"coordinates":[2.4504098892,41.542755127],"type":"Point"}
}