{
  "type": "Feature",
  "properties": {
    "addr:full":"Calle de Albasanz, 34 Madrid Madrid 28037",
    "addr:housenumber":"34",
    "addr:postcode":"madrid;28037",
    "addr:street":"Calle De Albasanz",
    "iso:country":"ES",
    "sg:address":"Calle de Albasanz, 34",
    "sg:city":"Madrid",
    "sg:orig_category":"V\u00c1lvulas",
    "sg:phone":"+34 913 27 00 13",
    "sg:postcode":"28037",
    "sg:province":"Madrid",
    "sg:website":"www.stejasa.com",
    "wof:name":"Stejasa Agregados Industriales S.a.",
    "wof:placetype":"venue"
},
  "geometry": {"coordinates":[-3.6277446747,40.4373664856],"type":"Point"}
}