{
  "type": "Feature",
  "properties": {
    "addr:full":"Calle de A - Poligono Industrial De Asipo, 26 Coru\u00d1o Asturias 33428",
    "addr:housenumber":"26",
    "addr:postcode":"33428",
    "addr:street":"Calle De A Poligono Industrial De Asipo;Asturias",
    "iso:country":"ES",
    "sg:address":"Calle de A - Poligono Industrial De Asipo, 26",
    "sg:city":"Coru\u00d1o",
    "sg:orig_category":"Maquinaria Para Industrias Diversas",
    "sg:phone":"+34 985 98 71 45",
    "sg:postcode":"33428",
    "sg:province":"Asturias",
    "sg:website":"www.aph-concept.com",
    "wof:name":"Antonio Pavon Herrero S.l.",
    "wof:placetype":"venue"
},
  "geometry": {"coordinates":[-5.9832577705,43.2504386902],"type":"Point"}
}