{
  "type": "Feature",
  "properties": {
    "addr:full":"Ctra La Rinconada, 12 Rinconada Sevilla 41309",
    "addr:housenumber":"12",
    "addr:postcode":"41309",
    "addr:street":"Ctra La Rinconada",
    "iso:country":"ES",
    "sg:address":"Ctra La Rinconada, 12",
    "sg:city":"Rinconada",
    "sg:orig_category":"M\u00c1rmoles, Granitos Y Piedras Naturales",
    "sg:phone":"+34 954 38 91 59",
    "sg:postcode":"41309",
    "sg:province":"Sevilla",
    "wof:name":"Marmoles Rinconada S. L.",
    "wof:placetype":"venue"
},
  "geometry": {"coordinates":[-5.9782538414,37.492855072],"type":"Point"}
}