{
  "type": "Feature",
  "properties": {
    "addr:full":"Rua Fotografo Luis Ksado, 17 Vigo Pontevedra 36209",
    "addr:housenumber":"17",
    "addr:postcode":"36209",
    "addr:street":"Rua Fotografo Luis Ksado",
    "iso:country":"ES",
    "sg:address":"Rua Fotografo Luis Ksado, 17",
    "sg:city":"Vigo",
    "sg:orig_category":"Deportes Diversos",
    "sg:phone":"+34 986 20 73 95",
    "sg:postcode":"36209",
    "sg:province":"Pontevedra",
    "wof:name":"Federacion Gallega De Petanca",
    "wof:placetype":"venue"
},
  "geometry": {"coordinates":[-8.7462453842,42.2151756287],"type":"Point"}
}