{
  "type": "Feature",
  "properties": {
    "addr:full":"Calle de Castillejos, 6 Palmas De Gran Canaria Las Palmas 35010",
    "addr:housenumber":"6",
    "addr:postcode":"35010",
    "addr:street":"Calle De Castillejos",
    "iso:country":"ES",
    "sg:address":"Calle de Castillejos, 6",
    "sg:city":"Palmas De Gran Canaria",
    "sg:orig_category":"Internados & Ense\u00d1anza Privada",
    "sg:phone":"+34 928 26 01 38",
    "sg:postcode":"35010",
    "sg:province":"Las Palmas",
    "wof:name":"Hijas De Maria Auxiliadora",
    "wof:placetype":"venue"
},
  "geometry": {"coordinates":[-15.4420061111,28.1305332184],"type":"Point"}
}