{
  "type": "Feature",
  "properties": {
    "addr:full":"Calle de Larga, 28 Olivares Sevilla 41804",
    "addr:housenumber":"28",
    "addr:postcode":"41804",
    "addr:street":"Calle De Larga;Sevilla",
    "iso:country":"ES",
    "sg:address":"Calle de Larga, 28",
    "sg:city":"Olivares",
    "sg:orig_category":"Inform\u00c1tica: Material Y Suministros",
    "sg:phone":"+34 954 11 14 96",
    "sg:postcode":"41804",
    "sg:province":"Sevilla",
    "sg:website":"http://perso.wanadoo.es/intecolivares",
    "wof:name":"Perez Torremocha Jairo",
    "wof:placetype":"venue"
},
  "geometry": {"coordinates":[-6.1566419601,37.4187736511],"type":"Point"}
}