{
  "type": "Feature",
  "properties": {
    "iso:country":"ES",
    "sg:address":"Calle de Garcia De Loaysa, 4",
    "sg:city":"Ciudad Real",
    "sg:orig_category":"Plomeros",
    "sg:phone":"+34 926 22 61 93",
    "sg:postcode":"13003",
    "sg:province":"Ciudad Real",
    "wof:name":"Martin Cambronero Jose",
    "wof:placetype":"venue"
},
  "geometry": {"coordinates":[-3.9297170639,38.9919471741],"type":"Point"}
}