{
  "type": "Feature",
  "properties": {
    "addr:full":"Calle de Carrera (la), 20 Velez-malaga M\u00e1laga 29700",
    "addr:housenumber":"20",
    "addr:postcode":"29700",
    "addr:street":"Calle De Carrera La",
    "iso:country":"ES",
    "sg:address":"Calle de Carrera (la), 20",
    "sg:city":"Velez-malaga",
    "sg:orig_category":"Centros P\u00dablicos De Formaci\u00d3n Profesional Y T\u00c9cnica",
    "sg:phone":"+34 952 50 16 07",
    "sg:postcode":"29700",
    "sg:province":"M\u00e1laga",
    "wof:name":"Colegio Oficial De Abogados De Malaga",
    "wof:placetype":"venue"
},
  "geometry": {"coordinates":[-4.1026940346,36.7810401917],"type":"Point"}
}