{
  "type": "Feature",
  "properties": {
    "iso:country":"ES",
    "sg:address":"Lug. Dehesa Hoyas, S/n",
    "sg:city":"Aldea Del Fresno",
    "sg:orig_category":"Agricultores, Agricultores",
    "sg:phone":"+34 918 63 70 62",
    "sg:postcode":"28620",
    "sg:province":"Madrid",
    "wof:name":"Agropecuaria Las Hoyas S. A.",
    "wof:placetype":"venue"
},
  "geometry": {"coordinates":[-4.2230834961,40.3034286499],"type":"Point"}
}