{
  "type": "Feature",
  "properties": {
    "addr:full":"Calle de Serantes, 1 Bilbao Vizcaya 48002",
    "addr:housenumber":"1",
    "addr:postcode":"48002",
    "addr:street":"Calle De Serantes",
    "iso:country":"ES",
    "sg:address":"Calle de Serantes, 1",
    "sg:city":"Bilbao",
    "sg:orig_category":"Peluquer\u00cdas, Peluquer\u00cda Mixta",
    "sg:phone":"+34 944 44 77 19",
    "sg:postcode":"48002",
    "sg:province":"Vizcaya",
    "sg:website":"www.rizos.es",
    "wof:name":"Monica Guion Vali\u00f1o(peluqueria)",
    "wof:placetype":"venue"
},
  "geometry": {"coordinates":[-2.9465548992,43.2501945496],"type":"Point"}
}