{
  "type": "Feature",
  "properties": {
    "addr:full":"Carrer de Ramon Freixas, 23 Vilafranca Penedes Barcelona 08720",
    "addr:housenumber":"23",
    "addr:postcode":"08720",
    "addr:street":"Carrer De Ramon Freixas;Penedes Barcelona",
    "iso:country":"ES",
    "sg:address":"Carrer de Ramon Freixas, 23",
    "sg:city":"Vilafranca Penedes",
    "sg:orig_category":"Transportes Por V\u00cdas Navegables",
    "sg:phone":"+34 938 17 08 87",
    "sg:postcode":"08720",
    "sg:province":"Barcelona",
    "wof:name":"Transportes Ruiz Mila S.a.",
    "wof:placetype":"venue"
},
  "geometry": {"coordinates":[1.6991440058,41.341129303],"type":"Point"}
}