{
  "type": "Feature",
  "properties": {
    "addr:full":"Calle de San Marcos, 12 Guadix Granada 18500",
    "addr:housenumber":"12",
    "addr:postcode":"18500",
    "addr:street":"Calle De San Marcos",
    "iso:country":"ES",
    "sg:address":"Calle de San Marcos, 12",
    "sg:city":"Guadix",
    "sg:orig_category":"Carnicer\u00cdas, Carnicer\u00cdas",
    "sg:phone":"+34 958 66 12 01",
    "sg:postcode":"18500",
    "sg:province":"Granada",
    "wof:name":"Maso Burguillo Jose Luis",
    "wof:placetype":"venue"
},
  "geometry": {"coordinates":[-3.135417223,37.2970695496],"type":"Point"}
}