{
  "type": "Feature",
  "properties": {
    "iso:country":"ES",
    "sg:address":"Csta Santiago, 1",
    "sg:city":"Madrid",
    "sg:orig_category":"Talleres: Ropa A Medida",
    "sg:phone":"+34 915 48 39 13",
    "sg:postcode":"28013",
    "sg:province":"Madrid",
    "wof:name":"Vall Adell Ramon",
    "wof:placetype":"venue"
},
  "geometry": {"coordinates":[-3.7097659111,40.4160995483],"type":"Point"}
}