{
  "type": "Feature",
  "properties": {
    "iso:country":"ES",
    "sg:address":"Calle de Maria Bellido, 76",
    "sg:city":"Bailen",
    "sg:orig_category":"Seguros",
    "sg:phone":"+34 953 67 62 81",
    "sg:postcode":"23710",
    "sg:province":"Ja\u00e9n",
    "wof:name":"Lopez & Balibrea S.l.",
    "wof:placetype":"venue"
},
  "geometry": {"coordinates":[-3.7796289921,38.0985984802],"type":"Point"}
}