{
  "type": "Feature",
  "properties": {
    "addr:full":"Carrer de Huguet Des Far, 3 Santa Pon\u00c7a Islas Baleares 07180",
    "addr:housenumber":"3",
    "addr:postcode":"07180",
    "addr:street":"Carrer De Huguet Des Far",
    "iso:country":"ES",
    "sg:address":"Carrer de Huguet Des Far, 3",
    "sg:city":"Santa Pon\u00c7a",
    "sg:orig_category":"Molduras, Junquillos, Listones Y Molduras Perforadas",
    "sg:phone":"+34 971 69 49 66",
    "sg:postcode":"07180",
    "sg:province":"Islas Baleares",
    "wof:name":"Gonzales Rivera Marcelino",
    "wof:placetype":"venue"
},
  "geometry": {"coordinates":[2.4709439278,39.519947052],"type":"Point"}
}