{
  "type": "Feature",
  "properties": {
    "iso:country":"ES",
    "sg:address":"Roig I Soler, 16",
    "sg:city":"Badalona",
    "sg:orig_category":"Electricidad: Instaladores",
    "sg:phone":"+34 934 65 05 72",
    "sg:postcode":"08916",
    "sg:province":"Barcelona",
    "sg:website":"www.gestioninstall.com",
    "wof:name":"Gestio I Instalacions S.l.",
    "wof:placetype":"venue"
},
  "geometry": {"coordinates":[2.2381899357,41.4756011963],"type":"Point"}
}