{
  "type": "Feature",
  "properties": {
    "addr:full":"Carrer de Hipolit Lazaro, 13 Barcelona Barcelona 08025",
    "addr:housenumber":"13",
    "addr:postcode":"08025",
    "addr:street":"Carrer De Hipolit Lazaro",
    "iso:country":"ES",
    "sg:address":"Carrer de Hipolit Lazaro, 13",
    "sg:city":"Barcelona",
    "sg:orig_category":"Centros Empresariales",
    "sg:phone":"+34 932 85 17 48",
    "sg:postcode":"08025",
    "sg:province":"Barcelona",
    "wof:name":"Asideco S.c.p.",
    "wof:placetype":"venue"
},
  "geometry": {"coordinates":[2.1645066738,41.4065170288],"type":"Point"}
}