{
  "type": "Feature",
  "properties": {
    "addr:full":"Calle de Sevilla, 5 Lebrija Sevilla 41740",
    "addr:housenumber":"5",
    "addr:postcode":"41740",
    "addr:street":"Calle De Sevilla",
    "iso:country":"ES",
    "sg:address":"Calle de Sevilla, 5",
    "sg:city":"Lebrija",
    "sg:orig_category":"Farmacias",
    "sg:phone":"+34 955 97 37 39",
    "sg:postcode":"41740",
    "sg:province":"Sevilla",
    "wof:name":"Merchan Palacios Carmelo",
    "wof:placetype":"venue"
},
  "geometry": {"coordinates":[-6.0777897835,36.9201927185],"type":"Point"}
}