{
  "type": "Feature",
  "properties": {
    "iso:country":"ES",
    "sg:address":"Av De Los Olivos, 11",
    "sg:city":"Tomares",
    "sg:classifiers":[
        {
            "category":"Autos & Motor Vehicles",
            "subcategory":"Automobile Sales",
            "type":"Retail Goods"
        }
    ],
    "sg:phone":"+34 954 15 66 94",
    "sg:postcode":"41940",
    "sg:province":"Sevilla",
    "wof:name":"Vilches Navarro Francisco Javier",
    "wof:placetype":"venue"
},
  "geometry": {"coordinates":[-6.0459890366,37.3781700134],"type":"Point"}
}