{
  "type": "Feature",
  "properties": {
    "iso:country":"ES",
    "sg:address":"Carrer de Sant Antoni Maria Claret, 20",
    "sg:city":"Sabadell",
    "sg:orig_category":"Estilistas Y Estudios De Estilo De Corte Y Confecci\u00d3n",
    "sg:phone":"+34 937 25 19 94",
    "sg:postcode":"08202",
    "sg:province":"Barcelona",
    "wof:name":"Ruiz Garcia Josefa",
    "wof:placetype":"venue"
},
  "geometry": {"coordinates":[2.1098968983,41.5465812683],"type":"Point"}
}