{
  "type": "Feature",
  "properties": {
    "iso:country":"ES",
    "sg:address":"Calle de Andalucia, 3",
    "sg:city":"Ubeda",
    "sg:orig_category":"Producci\u00d3n, Distribuci\u00d3n De Gas Butano Y Propano",
    "sg:phone":"+34 953 75 11 40",
    "sg:postcode":"23400",
    "sg:province":"Ja\u00e9n",
    "wof:name":"Hija De Arsenio Jimenez S.a.",
    "wof:placetype":"venue"
},
  "geometry": {"coordinates":[-3.373439312,38.0150985718],"type":"Point"}
}