{
  "type": "Feature",
  "properties": {
    "addr:full":"Carrer de Galceran De Pinos, 23 Sabadell Barcelona 08203",
    "addr:housenumber":"23",
    "addr:postcode":"08203",
    "addr:street":"Carrer De Galceran De Pinos",
    "iso:country":"ES",
    "sg:address":"Carrer de Galceran De Pinos, 23",
    "sg:city":"Sabadell",
    "sg:orig_category":"Guarder\u00cdas",
    "sg:phone":"+34 937 26 15 60",
    "sg:postcode":"08203",
    "sg:province":"Barcelona",
    "wof:name":"Amils Corts Elisabeth",
    "wof:placetype":"venue"
},
  "geometry": {"coordinates":[2.1184499264,41.5429382324],"type":"Point"}
}