{
  "type": "Feature",
  "properties": {
    "iso:country":"ES",
    "sg:address":"Calle de Ambrosio Ballesteros, 2",
    "sg:city":"Torrijos",
    "sg:orig_category":"Comercio, Reparaci\u00d3n De Bicicletas, De Motocicletas, De Accesorios",
    "sg:phone":"+34 925 76 02 94",
    "sg:postcode":"45500",
    "sg:province":"Toledo",
    "wof:name":"Carrasco Cabrerizo Antonio",
    "wof:placetype":"venue"
},
  "geometry": {"coordinates":[-4.2827501297,39.9826431274],"type":"Point"}
}