{
  "type": "Feature",
  "properties": {
    "iso:country":"ES",
    "sg:address":"Av Diagonal, 158",
    "sg:city":"Barcelona",
    "sg:orig_category":"Peluqueros: De Se\u00d1oras",
    "sg:phone":"+34 933 07 23 60",
    "sg:postcode":"08018",
    "sg:province":"Barcelona",
    "wof:name":"Coma Pique Montserrat",
    "wof:placetype":"venue"
},
  "geometry": {"coordinates":[2.1974620819,41.406124115],"type":"Point"}
}