{
  "type": "Feature",
  "properties": {
    "addr:full":"Carrer de Enric Morera, 14 Prat Llobregat Barcelona 08820",
    "addr:housenumber":"14",
    "addr:postcode":"08820",
    "addr:street":"Carrer De Enric Morera;Llobregat",
    "iso:country":"ES",
    "sg:address":"Carrer de Enric Morera, 14",
    "sg:city":"Prat Llobregat",
    "sg:orig_category":"Pescader\u00cdas (al Por Menor)",
    "sg:phone":"+34 933 79 06 56",
    "sg:postcode":"08820",
    "sg:province":"Barcelona",
    "wof:name":"Vilanova Gasol Jaime",
    "wof:placetype":"venue"
},
  "geometry": {"coordinates":[2.0971200466,41.3281364441],"type":"Point"}
}