{
  "type": "Feature",
  "properties": {
    "iso:country":"ES",
    "sg:address":"Rua San Roque, 54",
    "sg:city":"Lugo",
    "sg:orig_category":"Asilos De Ancianos. Centros Privados",
    "sg:phone":"+34 982 22 09 50",
    "sg:postcode":"27002",
    "sg:province":"Lugo",
    "wof:name":"Religiosas Hermanitas De Los Ancianos Desamparados",
    "wof:placetype":"venue"
},
  "geometry": {"coordinates":[-7.5515980721,43.0082893372],"type":"Point"}
}