{
  "type": "Feature",
  "properties": {
    "iso:country":"ES",
    "sg:address":"Carrer de Ample, 92",
    "sg:city":"Terrassa",
    "sg:orig_category":"Venta, Instalaci\u00d3n De Calefacci\u00d3n",
    "sg:phone":"+34 937 35 63 25",
    "sg:postcode":"08225",
    "sg:province":"Barcelona",
    "wof:name":"Talleres Matarin S.a.",
    "wof:placetype":"venue"
},
  "geometry": {"coordinates":[2.0171248913,41.5728187561],"type":"Point"}
}