{
  "type": "Feature",
  "properties": {
    "addr:full":"Calle de Prudencio Maria Verastegui, 14 Vitoria-gasteiz \u00c1lava 01002",
    "addr:housenumber":"14",
    "addr:postcode":"01002",
    "addr:street":"Calle De Prudencio Maria Verastegui",
    "iso:country":"ES",
    "sg:address":"Calle de Prudencio Maria Verastegui, 14",
    "sg:city":"Vitoria-gasteiz",
    "sg:orig_category":"Almacenes Frigor\u00cdficos",
    "sg:phone":"+34 945 25 48 34",
    "sg:postcode":"01002",
    "sg:province":"\u00c1lava",
    "wof:name":"Instalaciones Ilarduya S.l.",
    "wof:placetype":"venue"
},
  "geometry": {"coordinates":[-2.6666910648,42.8490219116],"type":"Point"}
}