{
  "type": "Feature",
  "properties": {
    "addr:full":"Avda Zaragoza, S/n Santa Pola Alicante 03130",
    "addr:postcode":"03130",
    "addr:street":"Avda Zaragoza S / N",
    "iso:country":"ES",
    "sg:address":"Avda Zaragoza, S/n",
    "sg:city":"Santa Pola",
    "sg:orig_category":"Parques De Atracciones Y Centros De Esparcimiento",
    "sg:phone":"+34 965 41 70 60",
    "sg:postcode":"03130",
    "sg:province":"Alicante",
    "wof:name":"Pola Park S.l.",
    "wof:placetype":"venue"
},
  "geometry": {"coordinates":[-0.5767740011,38.1959991455],"type":"Point"}
}