{
  "type": "Feature",
  "properties": {
    "addr:full":"Rond Sobradiel, 65 Madrid Madrid 28043",
    "addr:housenumber":"65",
    "addr:postcode":"madrid;28043",
    "addr:street":"Rond Sobradiel",
    "iso:country":"ES",
    "sg:address":"Rond Sobradiel, 65",
    "sg:city":"Madrid",
    "sg:orig_category":"Promotores Constructores",
    "sg:phone":"+34 917 21 95 59",
    "sg:postcode":"28043",
    "sg:province":"Madrid",
    "wof:name":"Promociones Fasegar S.l.",
    "wof:placetype":"venue"
},
  "geometry": {"coordinates":[-3.6434860229,40.4545211792],"type":"Point"}
}