{
  "type": "Feature",
  "properties": {
    "iso:country":"ES",
    "sg:address":"Calle de Palma La, 5",
    "sg:city":"Huelva",
    "sg:orig_category":"Seguridad En El Trabajo Y Prevenci\u00d3n De Riesgos Laborales",
    "sg:phone":"+34 959 53 02 48",
    "sg:postcode":"21002",
    "sg:province":"Huelva",
    "wof:name":"Centros Para La Formacion Y Prevencion Laboral S.l.",
    "wof:placetype":"venue"
},
  "geometry": {"coordinates":[-6.9522981644,37.2598342896],"type":"Point"}
}