{
  "type": "Feature",
  "properties": {
    "addr:full":"Calle de Perez Hervas, 3 Sevilla Sevilla 41003",
    "addr:housenumber":"3",
    "addr:postcode":"41003",
    "addr:street":"Calle De Perez Hervas",
    "iso:country":"ES",
    "sg:address":"Calle de Perez Hervas, 3",
    "sg:city":"Sevilla",
    "sg:orig_category":"Caf\u00c9s, Bares, Cervecer\u00cdas",
    "sg:phone":"+34 954 41 51 02",
    "sg:postcode":"41003",
    "sg:province":"Sevilla",
    "wof:name":"Pan Portillo S.l.",
    "wof:placetype":"venue"
},
  "geometry": {"coordinates":[-5.9804987907,37.3941688538],"type":"Point"}
}