{
  "type": "Feature",
  "properties": {
    "addr:full":"Infesta(requian), 96 Infesta La Coru\u00f1a 15319",
    "addr:housenumber":"96",
    "addr:postcode":"15319",
    "addr:street":"Requian;La Corun\u0303A",
    "iso:country":"ES",
    "sg:address":"Infesta(requian), 96",
    "sg:city":"Infesta",
    "sg:orig_category":"Vinos Y Licores (venta Al Por Menor)",
    "sg:phone":"+34 981 77 64 53",
    "sg:postcode":"15319",
    "sg:province":"La Coru\u00f1a",
    "sg:website":"www.adegasvinsa.com",
    "wof:name":"Adegas Vinsa S.l.",
    "wof:placetype":"venue"
},
  "geometry": {"coordinates":[-8.2246341705,43.2704048157],"type":"Point"}
}