{
  "type": "Feature",
  "properties": {
    "iso:country":"ES",
    "sg:address":"Calle de Segundo Izpizua, 27",
    "sg:city":"Donostia-san Sebastian",
    "sg:orig_category":"Sociedades, Compa\u00d1\u00cdas Aseguradoras",
    "sg:phone":"+34 943 32 76 40",
    "sg:postcode":"20001",
    "sg:province":"Guip\u00f9zcoa",
    "wof:name":"Sanz Sanz Eduardo",
    "wof:placetype":"venue"
},
  "geometry": {"coordinates":[-1.9701689482,43.3242454529],"type":"Point"}
}