{
  "type": "Feature",
  "properties": {
    "iso:country":"ES",
    "sg:address":"Calle de Antonia Diaz, 18",
    "sg:city":"Marchena",
    "sg:orig_category":"M\u00c9dicos: Oftalmolog\u00cda",
    "sg:phone":"+34 955 84 55 24",
    "sg:postcode":"41620",
    "sg:province":"Sevilla",
    "wof:name":"Garcia Roldan Isabel Maria",
    "wof:placetype":"venue"
},
  "geometry": {"coordinates":[-5.4170746803,37.3289527893],"type":"Point"}
}