{
  "type": "Feature",
  "properties": {
    "iso:country":"ES",
    "sg:address":"Carr Constitucio, 48",
    "sg:city":"Vila Joiosa",
    "sg:orig_category":"Inmobiliaria (agencias)",
    "sg:phone":"+34 966 85 08 65",
    "sg:postcode":"03570",
    "sg:province":"Alicante",
    "wof:name":"Valdeprocasa S.l.",
    "wof:placetype":"venue"
},
  "geometry": {"coordinates":[-0.2327190042,38.505821228],"type":"Point"}
}