{
  "type": "Feature",
  "properties": {
    "iso:country":"ES",
    "sg:address":"Calle de Emilio Prados, 2",
    "sg:city":"Sevilla",
    "sg:orig_category":"Reposter\u00cdas",
    "sg:phone":"+34 954 35 44 43",
    "sg:postcode":"41008",
    "sg:province":"Sevilla",
    "wof:name":"Romero Santana Jose",
    "wof:placetype":"venue"
},
  "geometry": {"coordinates":[-5.9752588272,37.4061012268],"type":"Point"}
}