{
  "type": "Feature",
  "properties": {
    "addr:full":"Calle de Jose Miguel Barandiaran, 35 Santurtzi Vizcaya 48980",
    "addr:housenumber":"35",
    "addr:postcode":"48980",
    "addr:street":"Calle De Jose Miguel Barandiaran",
    "iso:country":"ES",
    "sg:address":"Calle de Jose Miguel Barandiaran, 35",
    "sg:city":"Santurtzi",
    "sg:orig_category":"Ense\u00d1anza: Profesiones Art\u00cdsticas",
    "sg:phone":"+34 944 06 98 86",
    "sg:postcode":"48980",
    "sg:province":"Vizcaya",
    "wof:name":"Josefa Garcia Lopez (foto Fuentes)",
    "wof:placetype":"venue"
},
  "geometry": {"coordinates":[-3.0364739895,43.3229370117],"type":"Point"}
}