{
  "type": "Feature",
  "properties": {
    "addr:full":"Calle de Maria Marin, 47 Albacete Albacete 02003",
    "addr:housenumber":"47",
    "addr:postcode":"02003",
    "addr:street":"Calle De Maria Marin",
    "iso:country":"ES",
    "sg:address":"Calle de Maria Marin, 47",
    "sg:city":"Albacete",
    "sg:orig_category":"Electricidad: Instaladores",
    "sg:phone":"+34 967 22 89 06",
    "sg:postcode":"02003",
    "sg:province":"Albacete",
    "wof:name":"Ure\u00f1a Ponce German",
    "wof:placetype":"venue"
},
  "geometry": {"coordinates":[-1.8629850149,38.989402771],"type":"Point"}
}