{
  "type": "Feature",
  "properties": {
    "iso:country":"ES",
    "sg:address":"Av Sant Miquel Del Pui, 7",
    "sg:city":"Pobla Segur",
    "sg:orig_category":"Prendas Y Chalecos De Punto (al Por Menor)",
    "sg:phone":"+34 973 68 05 86",
    "sg:postcode":"25500",
    "sg:province":"Lleida",
    "wof:name":"Sauquet Ricart Jose",
    "wof:placetype":"venue"
},
  "geometry": {"coordinates":[0.9674209952,42.2477226257],"type":"Point"}
}