{
  "type": "Feature",
  "properties": {
    "iso:country":"ES",
    "sg:address":"Avda Vigo, 5",
    "sg:city":"Cangas",
    "sg:orig_category":"Muebles, Minoristas",
    "sg:phone":"+34 986 30 42 47",
    "sg:postcode":"36940",
    "sg:province":"Pontevedra",
    "wof:name":"Moblelar Muebles Decoracion S.l.",
    "wof:placetype":"venue"
},
  "geometry": {"coordinates":[-8.7877874374,42.2579803467],"type":"Point"}
}