{
  "type": "Feature",
  "properties": {
    "addr:full":"Av Generalitat, 3 Abrera Barcelona 08630",
    "addr:housenumber":"3",
    "addr:postcode":"08630",
    "addr:street":"Av Generalitat",
    "iso:country":"ES",
    "sg:address":"Av Generalitat, 3",
    "sg:city":"Abrera",
    "sg:orig_category":"Cajas De Ahorro",
    "sg:phone":"+34 937 70 03 32",
    "sg:postcode":"08630",
    "sg:province":"Barcelona",
    "wof:name":"Caixa D'estalvis De Manresa",
    "wof:placetype":"venue"
},
  "geometry": {"coordinates":[1.9014149904,41.5175552368],"type":"Point"}
}