{
  "type": "Feature",
  "properties": {
    "iso:country":"ES",
    "sg:address":"Calle de Arroyo, 111",
    "sg:city":"Sevilla",
    "sg:orig_category":"Electricidad: Instaladores",
    "sg:phone":"+34 954 53 69 62",
    "sg:postcode":"41008",
    "sg:province":"Sevilla",
    "wof:name":"Antonio Reina S.l.",
    "wof:placetype":"venue"
},
  "geometry": {"coordinates":[-5.9738917351,37.3984413147],"type":"Point"}
}