{
  "type": "Feature",
  "properties": {
    "addr:full":"Calle de Prof. Agustin Millares Carlo, 7 Palmas De Gran Canaria Las Palmas 35003",
    "addr:housenumber":"7",
    "addr:postcode":"35003",
    "addr:street":"Calle De Prof. Agustin Millares Carlo",
    "iso:country":"ES",
    "sg:address":"Calle de Prof. Agustin Millares Carlo, 7",
    "sg:city":"Palmas De Gran Canaria",
    "sg:orig_category":"M\u00c9dicos: Estomatolog\u00cda",
    "sg:phone":"+34 928 38 01 62",
    "sg:postcode":"35003",
    "sg:province":"Las Palmas",
    "wof:name":"Vuillermoz Vuillermoz Romano",
    "wof:placetype":"venue"
},
  "geometry": {"coordinates":[-15.4170894623,28.1110038757],"type":"Point"}
}