{
  "type": "Feature",
  "properties": {
    "iso:country":"ES",
    "sg:address":"Calle de Cortes De Aragon, 10",
    "sg:city":"Tarazona",
    "sg:orig_category":"Electricidad: Instaladores",
    "sg:phone":"+34 976 64 27 52",
    "sg:postcode":"50500",
    "sg:province":"Zaragoza",
    "wof:name":"Arasitel S.l.",
    "wof:placetype":"venue"
},
  "geometry": {"coordinates":[-1.7221323252,41.9067802429],"type":"Point"}
}