{
  "type": "Feature",
  "properties": {
    "iso:country":"ES",
    "sg:address":"Plaz Conde Alpuente (del), 1",
    "sg:city":"Segovia",
    "sg:orig_category":"Peluqueros: De Se\u00d1oras",
    "sg:phone":"+34 921 46 29 93",
    "sg:postcode":"40001",
    "sg:province":"Segovia",
    "wof:name":"Cachorro Martin Angelita",
    "wof:placetype":"venue"
},
  "geometry": {"coordinates":[-4.1194968224,40.949886322],"type":"Point"}
}