{
  "type": "Feature",
  "properties": {
    "addr:full":"Rua Antolin Losada Torvisco, S/n Ourense Ourense 32005",
    "addr:housenumber":"s",
    "addr:postcode":"32005",
    "addr:street":"Rua Antolin Losada Torvisco;/ N",
    "iso:country":"ES",
    "sg:address":"Rua Antolin Losada Torvisco, S/n",
    "sg:city":"Ourense",
    "sg:orig_category":"Empresas De Carpinter\u00cda De Madera",
    "sg:phone":"+34 988 22 45 94",
    "sg:postcode":"32005",
    "sg:province":"Ourense",
    "wof:name":"Lopez Iglesias Ramon",
    "wof:placetype":"venue"
},
  "geometry": {"coordinates":[-7.8493680954,42.325214386],"type":"Point"}
}