{
  "type": "Feature",
  "properties": {
    "iso:country":"ES",
    "sg:address":"Avda Espa\u00d1a, 98",
    "sg:city":"Estepona",
    "sg:orig_category":"Asociaciones Y Clubs Deportivos",
    "sg:phone":"+34 952 80 22 43",
    "sg:postcode":"29680",
    "sg:province":"M\u00e1laga",
    "wof:name":"Iglesias Morales Rosa Maria",
    "wof:placetype":"venue"
},
  "geometry": {"coordinates":[-5.1435527802,36.4256477356],"type":"Point"}
}