{
  "type": "Feature",
  "properties": {
    "iso:country":"ES",
    "sg:address":"Calle de San Anton, 79",
    "sg:city":"Zudaire",
    "sg:orig_category":"Empresas De Carpinter\u00cda",
    "sg:phone":"+34 948 53 95 00",
    "sg:postcode":"31272",
    "sg:province":"Navarra",
    "wof:name":"Carpinteria Alubel S.l.",
    "wof:placetype":"venue"
},
  "geometry": {"coordinates":[-2.1329491138,42.7733001709],"type":"Point"}
}