{
  "type": "Feature",
  "properties": {
    "addr:full":"Carr Canceller Dou, 3 Cervera Lleida 25200",
    "addr:housenumber":"3",
    "addr:postcode":"25200",
    "addr:street":"Carr Canceller Dou",
    "iso:country":"ES",
    "sg:address":"Carr Canceller Dou, 3",
    "sg:city":"Cervera",
    "sg:orig_category":"Ense\u00d1anza, Formaci\u00d3n Profesional: Aprendizaje",
    "sg:phone":"+34 973 53 02 86",
    "sg:postcode":"25200",
    "sg:province":"Lleida",
    "wof:name":"Centre De Telecomunicaciones De Catalunya",
    "wof:placetype":"venue"
},
  "geometry": {"coordinates":[1.2714600563,41.6712989807],"type":"Point"}
}