{
  "type": "Feature",
  "properties": {
    "addr:full":"Barr Andramaria De Bego\u00d1a, 24 Bilbao Vizcaya 48007",
    "addr:housenumber":"24",
    "addr:postcode":"48007",
    "iso:country":"ES",
    "sg:address":"Barr Andramaria De Bego\u00d1a, 24",
    "sg:city":"Bilbao",
    "sg:orig_category":"Mec\u00c1nica Y Herramientas De Precisi\u00d3n",
    "sg:phone":"+34 944 45 26 47",
    "sg:postcode":"48007",
    "sg:province":"Vizcaya",
    "wof:name":"Colsa Xxi S.l.",
    "wof:placetype":"venue"
},
  "geometry": {"coordinates":[-2.9120130539,43.2627868652],"type":"Point"}
}