{
  "type": "Feature",
  "properties": {
    "addr:full":"Cervantes, S/n Favara Valencia 46614",
    "addr:housenumber":"s / n",
    "addr:postcode":"46614",
    "addr:street":"Cervantes",
    "iso:country":"ES",
    "sg:address":"Cervantes, S/n",
    "sg:city":"Favara",
    "sg:orig_category":"Asilos De Ancianos. Centros Privados",
    "sg:phone":"+34 961 76 95 20",
    "sg:postcode":"46614",
    "sg:province":"Valencia",
    "wof:name":"Asociacion Democratica Provincial De Jubilados Y Pensionistas De Valencia",
    "wof:placetype":"venue"
},
  "geometry": {"coordinates":[-0.2919229865,39.1257247925],"type":"Point"}
}