{
  "type": "Feature",
  "properties": {
    "addr:full":"Carrer de Terra Alta, 3 Hospitalet De L'infant Tarragona 43890",
    "addr:housenumber":"3",
    "addr:postcode":"43890",
    "addr:street":"Carrer De Terra Alta",
    "iso:country":"ES",
    "sg:address":"Carrer de Terra Alta, 3",
    "sg:city":"Hospitalet De L'infant",
    "sg:orig_category":"Mec\u00c1nico Del Autom\u00d3vil",
    "sg:phone":"+34 977 82 37 10",
    "sg:postcode":"43890",
    "sg:province":"Tarragona",
    "wof:name":"Talleres Callau C.b.",
    "wof:placetype":"venue"
},
  "geometry": {"coordinates":[1.2455840111,41.1117019653],"type":"Point"}
}