{
  "type": "Feature",
  "properties": {
    "iso:country":"ES",
    "sg:address":"Calle de Milicias (las), 2",
    "sg:city":"Avila",
    "sg:orig_category":"M\u00c9dicos: Medicina Interna",
    "sg:phone":"+34 920 22 03 74",
    "sg:postcode":"05003",
    "sg:province":"\u00c1vila",
    "wof:name":"Rodriguez Puebla Alfonso",
    "wof:placetype":"venue"
},
  "geometry": {"coordinates":[-4.6891450882,40.6535110474],"type":"Point"}
}