{
  "type": "Feature",
  "properties": {
    "addr:full":"Calle de Sol, 29 Campo Criptana Ciudad Real 13610",
    "addr:housenumber":"29",
    "addr:postcode":"13610",
    "addr:street":"Calle De Sol;Criptana",
    "iso:country":"ES",
    "sg:address":"Calle de Sol, 29",
    "sg:city":"Campo Criptana",
    "sg:orig_category":"Postigos, Persianas Y Celos\u00cdas",
    "sg:phone":"+34 926 56 25 28",
    "sg:postcode":"13610",
    "sg:province":"Ciudad Real",
    "wof:name":"Olivares Amores Andres",
    "wof:placetype":"venue"
},
  "geometry": {"coordinates":[-3.1293590069,39.4053192139],"type":"Point"}
}