{
  "type": "Feature",
  "properties": {
    "iso:country":"ES",
    "sg:address":"Calle de Puerto Rico, 20",
    "sg:city":"Santa Cruz De Tenerife",
    "sg:orig_category":"Chapister\u00cda",
    "sg:phone":"+34 922 22 19 06",
    "sg:postcode":"38009",
    "sg:province":"Santa Cruz De Tenerife",
    "wof:name":"Izquierdo Alvarez Virgilio",
    "wof:placetype":"venue"
},
  "geometry": {"coordinates":[-16.2674770355,28.4550075531],"type":"Point"}
}