{
  "type": "Feature",
  "properties": {
    "addr:full":"Calle de Mezo Kalea, 24 Erandio Vizcaya 48950",
    "addr:housenumber":"24",
    "addr:postcode":"48950",
    "addr:street":"Calle De Mezo Kalea",
    "iso:country":"ES",
    "sg:address":"Calle de Mezo Kalea, 24",
    "sg:city":"Erandio",
    "sg:orig_category":"Droguer\u00cdas (al Por Menor)",
    "sg:phone":"+34 944 67 44 47",
    "sg:postcode":"48950",
    "sg:province":"Vizcaya",
    "wof:name":"Ana Beatriz Menendez  - Modas Pereira",
    "wof:placetype":"venue"
},
  "geometry": {"coordinates":[-2.9825530052,43.3161735535],"type":"Point"}
}