{
  "type": "Feature",
  "properties": {
    "iso:country":"ES",
    "sg:address":"Rua Casti\u00d1eiri\u00d1o (do), 12",
    "sg:city":"Santiago De Compostela",
    "sg:orig_category":"Farmacias",
    "sg:phone":"+34 981 59 03 97",
    "sg:postcode":"15702",
    "sg:province":"La Coru\u00f1a",
    "wof:name":"Garcia Gomez Maria Jose",
    "wof:placetype":"venue"
},
  "geometry": {"coordinates":[-8.540930748,42.8606872559],"type":"Point"}
}