{
  "type": "Feature",
  "properties": {
    "addr:full":"G.v. Corts Catalanes, 569 Barcelona Barcelona 08011",
    "addr:housenumber":"569",
    "addr:postcode":"08011",
    "addr:street":"Catalanes",
    "iso:country":"ES",
    "sg:address":"G.v. Corts Catalanes, 569",
    "sg:city":"Barcelona",
    "sg:orig_category":"Fabricaci\u00d3n De Sobres, Bolsas Y Fundas",
    "sg:phone":"+34 934 54 56 49",
    "sg:postcode":"08011",
    "sg:province":"Barcelona",
    "wof:name":"Zalacain Diez Emiliana",
    "wof:placetype":"venue"
},
  "geometry": {"coordinates":[2.1617424488,41.3847579956],"type":"Point"}
}