{
  "type": "Feature",
  "properties": {
    "addr:full":"Pase Concepcion Del Castillo Romero, 13 Buen Paso Santa Cruz De Tenerife 38430",
    "addr:housenumber":"13",
    "addr:postcode":"38430",
    "addr:street":"Romero;Buen Paso",
    "iso:country":"ES",
    "sg:address":"Pase Concepcion Del Castillo Romero, 13",
    "sg:city":"Buen Paso",
    "sg:orig_category":"Embalajes",
    "sg:phone":"+34 922 81 06 82",
    "sg:postcode":"38430",
    "sg:province":"Santa Cruz De Tenerife",
    "wof:name":"Baez Baez Onelio",
    "wof:placetype":"venue"
},
  "geometry": {"coordinates":[-16.7204761505,28.3677654266],"type":"Point"}
}