{
  "type": "Feature",
  "properties": {
    "iso:country":"ES",
    "sg:address":"Calle de Dos De Mayo, 11",
    "sg:city":"Valladolid",
    "sg:orig_category":"Doctores En Medicina",
    "sg:phone":"+34 983 30 88 39",
    "sg:postcode":"47004",
    "sg:province":"Valladolid",
    "wof:name":"Herrero Andres Felipe",
    "wof:placetype":"venue"
},
  "geometry": {"coordinates":[-4.7245736122,41.6473236084],"type":"Point"}
}