{
  "type": "Feature",
  "properties": {
    "iso:country":"ES",
    "sg:address":"Labeaga Kalea, 72",
    "sg:city":"Urretxu",
    "sg:orig_category":"Zapatos (al Por Menor)",
    "sg:phone":"+34 943 53 48 62",
    "sg:postcode":"20700",
    "sg:province":"Guip\u00f9zcoa",
    "wof:name":"Ona Zentroa",
    "wof:placetype":"venue"
},
  "geometry": {"coordinates":[-2.3205049038,43.0886077881],"type":"Point"}
}