{
  "type": "Feature",
  "properties": {
    "addr:full":"Ctra. Burgos, Km. 0129,5 Arroyo De La Encomienda Valladolid 47195",
    "addr:postcode":"47195",
    "addr:street":"Ctra. Burgos Km. 0129,5",
    "iso:country":"ES",
    "sg:address":"Ctra. Burgos, Km. 0129,5",
    "sg:city":"Arroyo De La Encomienda",
    "sg:orig_category":"Venta, Alquiler, Mantenimiento De Calderas",
    "sg:phone":"+34 983 40 76 15",
    "sg:postcode":"47195",
    "sg:province":"Valladolid",
    "wof:name":"Hijas De Manuel Vidal S.l.",
    "wof:placetype":"venue"
},
  "geometry": {"coordinates":[-4.7954587936,41.6099090576],"type":"Point"}
}