{
  "type": "Feature",
  "properties": {
    "iso:country":"ES",
    "sg:address":"Calle de Cristo Rey, 17",
    "sg:city":"Palacios Y Villafranca",
    "sg:orig_category":"Empresas De Carpinter\u00cda",
    "sg:phone":"+34 955 81 51 20",
    "sg:postcode":"41720",
    "sg:province":"Sevilla",
    "wof:name":"Begines Sanchez Antonio",
    "wof:placetype":"venue"
},
  "geometry": {"coordinates":[-5.9293589592,37.1571846008],"type":"Point"}
}