{
  "type": "Feature",
  "properties": {
    "iso:country":"ES",
    "sg:address":"Pg Germanies (de Les), 10",
    "sg:city":"Gandia",
    "sg:orig_category":"Molduras, Junquillos, Listones Y Molduras Perforadas",
    "sg:phone":"+34 962 86 67 01",
    "sg:postcode":"46700",
    "sg:province":"Valencia",
    "wof:name":"Llacer Moran Vicente",
    "wof:placetype":"venue"
},
  "geometry": {"coordinates":[-0.1812320054,38.9654273987],"type":"Point"}
}