{
  "type": "Feature",
  "properties": {
    "addr:full":"Rua Doctor Jose Fari\u00d1a, 6 Betanzos La Coru\u00f1a 15300",
    "addr:housenumber":"6",
    "addr:postcode":"15300",
    "addr:street":"Rua Doctor Jose Farin\u0303A;La",
    "iso:country":"ES",
    "sg:address":"Rua Doctor Jose Fari\u00d1a, 6",
    "sg:city":"Betanzos",
    "sg:orig_category":"Flores Y Plantas Naturales (al Por Mayor)",
    "sg:phone":"+34 981 77 32 69",
    "sg:postcode":"15300",
    "sg:province":"La Coru\u00f1a",
    "wof:name":"Miramontes Y Otra S.c.",
    "wof:placetype":"venue"
},
  "geometry": {"coordinates":[-8.2114295959,43.2772712708],"type":"Point"}
}