{
  "type": "Feature",
  "properties": {
    "addr:full":"Carr Castellar, 19 Casc Urba Girona 17490",
    "addr:housenumber":"19;urba",
    "addr:postcode":"17490",
    "addr:street":"Carr Castellar",
    "iso:country":"ES",
    "sg:address":"Carr Castellar, 19",
    "sg:city":"Casc Urba",
    "sg:orig_category":"Caf\u00c9s, Bares, Cervecer\u00cdas",
    "sg:phone":"+34 972 38 09 66",
    "sg:postcode":"17490",
    "sg:province":"Girona",
    "wof:name":"Farjas Oliveras Miguel",
    "wof:placetype":"venue"
},
  "geometry": {"coordinates":[3.1481759548,42.3640785217],"type":"Point"}
}