{
  "type": "Feature",
  "properties": {
    "addr:full":"Avda Constitucion (la), 9 Sevilla Sevilla 41004",
    "addr:housenumber":"9",
    "addr:postcode":"41004",
    "addr:street":"Avda Constitucion La",
    "iso:country":"ES",
    "sg:address":"Avda Constitucion (la), 9",
    "sg:city":"Sevilla",
    "sg:orig_category":"Pe\u00d1as Y Asociaciones Varias",
    "sg:phone":"+34 954 21 00 37",
    "sg:postcode":"41004",
    "sg:province":"Sevilla",
    "wof:name":"Asociacion Provincial De Informadores Turisticos",
    "wof:placetype":"venue"
},
  "geometry": {"coordinates":[-5.9934468269,37.383430481],"type":"Point"}
}