{
  "type": "Feature",
  "properties": {
    "addr:full":"Calle de Francisco Ricci, 16 Madrid Madrid 28015",
    "addr:housenumber":"16",
    "addr:postcode":"madrid;28015",
    "addr:street":"Calle De Francisco Ricci",
    "iso:country":"ES",
    "sg:address":"Calle de Francisco Ricci, 16",
    "sg:city":"Madrid",
    "sg:orig_category":"Molduras, Junquillos, Listones Y Molduras Perforadas",
    "sg:phone":"+34 915 44 14 67",
    "sg:postcode":"28015",
    "sg:province":"Madrid",
    "wof:name":"Rubio Rubio Jesus",
    "wof:placetype":"venue"
},
  "geometry": {"coordinates":[-3.7130560875,40.4313278198],"type":"Point"}
}