{
  "type": "Feature",
  "properties": {
    "addr:full":"Avda Comarcas (de Las), 70 Fuenlabrada Madrid 28941",
    "addr:housenumber":"70",
    "addr:postcode":"28941",
    "addr:street":"Avda Comarcas De Las",
    "iso:country":"ES",
    "sg:address":"Avda Comarcas (de Las), 70",
    "sg:city":"Fuenlabrada",
    "sg:orig_category":"Internados & Ense\u00d1anza Privada",
    "sg:phone":"+34 916 15 95 00",
    "sg:postcode":"28941",
    "sg:province":"Madrid",
    "wof:name":"Dafne S.c.l.",
    "wof:placetype":"venue"
},
  "geometry": {"coordinates":[-3.8024790287,40.2986907959],"type":"Point"}
}