{
  "type": "Feature",
  "properties": {
    "addr:full":"Carrer de Pau (la), 67 Navas Barcelona 08670",
    "addr:housenumber":"67",
    "addr:postcode":"08670",
    "addr:street":"Carrer De Pau La",
    "iso:country":"ES",
    "sg:address":"Carrer de Pau (la), 67",
    "sg:city":"Navas",
    "sg:orig_category":"Energ\u00cda Solar Y Nuevas Energ\u00cdas (equipo, Estudios)",
    "sg:phone":"+34 938 20 49 33",
    "sg:postcode":"08670",
    "sg:province":"Barcelona",
    "wof:name":"Metalliques Autoporta S.l",
    "wof:placetype":"venue"
},
  "geometry": {"coordinates":[1.8799910545,41.9020385742],"type":"Point"}
}