{
  "type": "Feature",
  "properties": {
    "addr:full":"Calle de Sevilla, 19 Zafra Badajoz 06300",
    "addr:housenumber":"19",
    "addr:postcode":"06300",
    "addr:street":"Calle De Sevilla",
    "iso:country":"ES",
    "sg:address":"Calle de Sevilla, 19",
    "sg:city":"Zafra",
    "sg:orig_category":"Quincaller\u00cda (al Por Menor)",
    "sg:phone":"+34 924 55 02 95",
    "sg:postcode":"06300",
    "sg:province":"Badajoz",
    "wof:name":"Nueva Ferreteria El Candado Cdad",
    "wof:placetype":"venue"
},
  "geometry": {"coordinates":[-6.4183759689,38.4237937927],"type":"Point"}
}