{
  "type": "Feature",
  "properties": {
    "iso:country":"ES",
    "sg:address":"Calle de Doctor Antonio Cortes Llado, 11",
    "sg:city":"Sevilla",
    "sg:orig_category":"Ingenier\u00cda, Centros De Estudios (diversos)",
    "sg:phone":"+34 954 42 33 59",
    "sg:postcode":"41004",
    "sg:province":"Sevilla",
    "wof:name":"Flores Pereyta Pedro",
    "wof:placetype":"venue"
},
  "geometry": {"coordinates":[-5.9809012413,37.3788833618],"type":"Point"}
}