{
  "type": "Feature",
  "properties": {
    "iso:country":"ES",
    "sg:address":"Calle de Ugarteburu Jose Maria, 1",
    "sg:city":"Bilbao",
    "sg:orig_category":"Empresas De Carpinter\u00cda De Madera",
    "sg:phone":"+34 944 46 56 14",
    "sg:postcode":"48007",
    "sg:province":"Vizcaya",
    "wof:name":"Alejandro Bahillo Zamora",
    "wof:placetype":"venue"
},
  "geometry": {"coordinates":[-2.9126098156,43.2596931458],"type":"Point"}
}