{
  "type": "Feature",
  "properties": {
    "addr:full":"Pl Carles Iii (de), 53 S. Carles Rapita Tarragona 43540",
    "addr:housenumber":"53",
    "addr:postcode":"43540",
    "addr:street":"Pl Carles Iii De;S. Carles Rapita",
    "iso:country":"ES",
    "sg:address":"Pl Carles Iii (de), 53",
    "sg:city":"S. Carles Rapita",
    "sg:orig_category":"Panader\u00cdas, Panader\u00cdas",
    "sg:phone":"+34 977 74 04 61",
    "sg:postcode":"43540",
    "sg:province":"Tarragona",
    "wof:name":"Santos Ribot Angel",
    "wof:placetype":"venue"
},
  "geometry": {"coordinates":[0.593208015,40.6207809448],"type":"Point"}
}