{
  "type": "Feature",
  "properties": {
    "iso:country":"ES",
    "sg:address":"Calle de Azpiko-errota, 4",
    "sg:city":"Markina-xemein",
    "sg:orig_category":"Contenedores (mercanc\u00cdas)",
    "sg:phone":"+34 946 16 87 11",
    "sg:postcode":"48270",
    "sg:province":"Vizcaya",
    "wof:name":"Garate Guenechea Jesus Maria",
    "wof:placetype":"venue"
},
  "geometry": {"coordinates":[-2.4967355728,43.2713279724],"type":"Point"}
}