{
  "type": "Feature",
  "properties": {
    "addr:full":"Mexico, 10 Aljaraque Huelva 21110",
    "addr:postcode":"21110",
    "addr:street":"Mexico 10",
    "iso:country":"ES",
    "sg:address":"Mexico, 10",
    "sg:city":"Aljaraque",
    "sg:orig_category":"Reparaci\u00d3n De Cerrajer\u00cda",
    "sg:phone":"+34 959 31 61 75",
    "sg:postcode":"21110",
    "sg:province":"Huelva",
    "wof:name":"Osuna Gomez Manuel",
    "wof:placetype":"venue"
},
  "geometry": {"coordinates":[-7.0241990089,37.2709159851],"type":"Point"}
}