{
  "type": "Feature",
  "properties": {
    "iso:country":"ES",
    "sg:address":"Avda Paskual Abaroa Etorbidea, 24",
    "sg:city":"Lekeitio",
    "sg:orig_category":"Molduras, Junquillos, Listones Y Molduras Perforadas",
    "sg:phone":"+34 946 84 19 91",
    "sg:postcode":"48280",
    "sg:province":"Vizcaya",
    "wof:name":"Diego Besoitaguena Larruscain-bar Leihope",
    "wof:placetype":"venue"
},
  "geometry": {"coordinates":[-2.5050001144,43.3640327454],"type":"Point"}
}