{
  "type": "Feature",
  "properties": {
    "addr:full":"Calle de Real, 24 Pruna Sevilla 41670",
    "addr:housenumber":"24",
    "addr:postcode":"41670",
    "addr:street":"Calle De Real",
    "iso:country":"ES",
    "sg:address":"Calle de Real, 24",
    "sg:city":"Pruna",
    "sg:orig_category":"Cajas Para Embalar",
    "sg:phone":"+34 954 85 80 30",
    "sg:postcode":"41670",
    "sg:province":"Sevilla",
    "wof:name":"Caja Rural Del Sur Sociedad Cooperativa",
    "wof:placetype":"venue"
},
  "geometry": {"coordinates":[-5.2209701538,36.972454071],"type":"Point"}
}