{
  "type": "Feature",
  "properties": {
    "addr:full":"Calle de Bocinegro, 22 Corralejo Las Palmas 35660",
    "addr:housenumber":"22",
    "addr:postcode":"35660",
    "addr:street":"Calle De Bocinegro",
    "iso:country":"ES",
    "sg:address":"Calle de Bocinegro, 22",
    "sg:city":"Corralejo",
    "sg:orig_category":"Venta, Instalaci\u00d3n, Reparaci\u00d3n De Antenas Para Televisi\u00d3n",
    "sg:phone":"+34 928 53 57 51",
    "sg:postcode":"35660",
    "sg:province":"Las Palmas",
    "wof:name":"Gonzalez Casielles Hernan",
    "wof:placetype":"venue"
},
  "geometry": {"coordinates":[-13.8703994751,28.7402610779],"type":"Point"}
}