{
  "type": "Feature",
  "properties": {
    "addr:full":"Calle de Palafox, 26 Tauste Zaragoza 50660",
    "addr:housenumber":"26",
    "addr:postcode":"50660",
    "addr:street":"Calle De Palafox",
    "iso:country":"ES",
    "sg:address":"Calle de Palafox, 26",
    "sg:city":"Tauste",
    "sg:orig_category":"Promotores Constructores",
    "sg:phone":"+34 976 85 54 49",
    "sg:postcode":"50660",
    "sg:province":"Zaragoza",
    "wof:name":"Angoy Y Sancho Empresa Constructora S.l.",
    "wof:placetype":"venue"
},
  "geometry": {"coordinates":[-1.2518030405,41.9238357544],"type":"Point"}
}