{
  "type": "Feature",
  "properties": {
    "addr:full":"Pase Virgen De Linarejos, 6 Linares Ja\u00e9n 23700",
    "addr:housenumber":"6",
    "addr:postcode":"23700",
    "addr:street":"Jae\u0301N",
    "iso:country":"ES",
    "sg:address":"Pase Virgen De Linarejos, 6",
    "sg:city":"Linares",
    "sg:orig_category":"Ingenier\u00cda, Centros De Estudios (diversos)",
    "sg:phone":"+34 953 69 25 20",
    "sg:postcode":"23700",
    "sg:province":"Ja\u00e9n",
    "wof:name":"Martinez Rodriguez Blas",
    "wof:placetype":"venue"
},
  "geometry": {"coordinates":[-3.6420478821,38.1125907898],"type":"Point"}
}