{
  "type": "Feature",
  "properties": {
    "addr:full":"Ctra. Nal. Iii, Km. 0327,0 Riba-roja Turia Valencia 46190",
    "addr:postcode":"46190",
    "addr:street":"Ctra. Nal. Iii Km. 0327,0",
    "iso:country":"ES",
    "sg:address":"Ctra. Nal. Iii, Km. 0327,0",
    "sg:city":"Riba-roja Turia",
    "sg:orig_category":"Servicios Diversos",
    "sg:phone":"+34 961 66 82 54",
    "sg:postcode":"46190",
    "sg:province":"Valencia",
    "wof:name":"Grupo De Empresas Torsisa S.l.",
    "wof:placetype":"venue"
},
  "geometry": {"coordinates":[-0.5698940158,39.5458450317],"type":"Point"}
}