{
  "type": "Feature",
  "properties": {
    "addr:full":"Carrer de Joan Maragall, 81 Mataro Barcelona 08303",
    "addr:housenumber":"81",
    "addr:postcode":"08303",
    "addr:street":"Carrer De Joan Maragall",
    "iso:country":"ES",
    "sg:address":"Carrer de Joan Maragall, 81",
    "sg:city":"Mataro",
    "sg:orig_category":"Alquiler De Climatizadores",
    "sg:phone":"+34 937 99 81 85",
    "sg:postcode":"08303",
    "sg:province":"Barcelona",
    "wof:name":"Clima Fred Vilamajor S.l.",
    "wof:placetype":"venue"
},
  "geometry": {"coordinates":[2.428953886,41.5425758362],"type":"Point"}
}