{
  "type": "Feature",
  "properties": {
    "addr:full":"Av Pere Baurier, S/n Roda Ter Barcelona 08510",
    "addr:housenumber":"s / n",
    "addr:postcode":"08510",
    "addr:street":"Av Pere Baurier;Roda Ter Barcelona",
    "iso:country":"ES",
    "sg:address":"Av Pere Baurier, S/n",
    "sg:city":"Roda Ter",
    "sg:orig_category":"Poli\u00c9ster",
    "sg:phone":"+34 938 54 07 74",
    "sg:postcode":"08510",
    "sg:province":"Barcelona",
    "wof:name":"Vilaseca Sayos Jaime",
    "wof:placetype":"venue"
},
  "geometry": {"coordinates":[2.3115420341,41.9790878296],"type":"Point"}
}