{
  "type": "Feature",
  "properties": {
    "iso:country":"ES",
    "sg:address":"Calle de Industria, La, 6",
    "sg:city":"Torrent",
    "sg:orig_category":"Empresas De Carpinter\u00cda Met\u00c1lica",
    "sg:phone":"+34 961 55 35 83",
    "sg:postcode":"46900",
    "sg:province":"Valencia",
    "wof:name":"Marti Martinez Juan",
    "wof:placetype":"venue"
},
  "geometry": {"coordinates":[-0.4564799964,39.440826416],"type":"Point"}
}