{
  "type": "Feature",
  "properties": {
    "addr:full":"Avda Cruz Roja (la), 38 Sevilla Sevilla 41008",
    "addr:housenumber":"38",
    "addr:postcode":"41008",
    "addr:street":"Avda Cruz Roja La",
    "iso:country":"ES",
    "sg:address":"Avda Cruz Roja (la), 38",
    "sg:city":"Sevilla",
    "sg:orig_category":"Carb\u00d3n, Carb\u00d3n De Madera (al Por Mayor)",
    "sg:phone":"+34 954 35 46 00",
    "sg:postcode":"41008",
    "sg:province":"Sevilla",
    "wof:name":"Garcia Dominguez Joaquin",
    "wof:placetype":"venue"
},
  "geometry": {"coordinates":[-5.9819087982,37.4014282227],"type":"Point"}
}