{
  "type": "Feature",
  "properties": {
    "iso:country":"ES",
    "sg:address":"Hiribarren Kalea, S/n",
    "sg:city":"Lazkao",
    "sg:orig_category":"Empresas De Carpinter\u00cda Met\u00c1lica",
    "sg:phone":"+34 943 88 81 01",
    "sg:postcode":"20210",
    "sg:province":"Guip\u00f9zcoa",
    "wof:name":"Azkarate Beguiristain Juan Maria",
    "wof:placetype":"venue"
},
  "geometry": {"coordinates":[-2.1885669231,43.0414161682],"type":"Point"}
}