{
  "type": "Feature",
  "properties": {
    "addr:full":"Avda Finisterre, 13 Coru\u00d1a La Coru\u00f1a 15004",
    "addr:housenumber":"13",
    "addr:postcode":"15004",
    "addr:street":"Avda Finisterre;La Corun\u0303A",
    "iso:country":"ES",
    "sg:address":"Avda Finisterre, 13",
    "sg:city":"Coru\u00d1a",
    "sg:orig_category":"Listas De Boda, Menaje De Mesa Y Cocina",
    "sg:phone":"+34 981 25 23 00",
    "sg:postcode":"15004",
    "sg:province":"La Coru\u00f1a",
    "sg:website":"www.elpote.es",
    "wof:name":"El Pote S.a.",
    "wof:placetype":"venue"
},
  "geometry": {"coordinates":[-8.4096851349,43.3664550781],"type":"Point"}
}