{
  "type": "Feature",
  "properties": {
    "addr:full":"Calle de Tarragona, 3 Madrid Madrid 28045",
    "addr:housenumber":"3",
    "addr:postcode":"28045",
    "addr:street":"Calle De Tarragona",
    "iso:country":"ES",
    "sg:address":"Calle de Tarragona, 3",
    "sg:city":"Madrid",
    "sg:orig_category":"Florister\u00cdas",
    "sg:phone":"+34 915 28 47 51",
    "sg:postcode":"28045",
    "sg:province":"Madrid",
    "wof:name":"Sanchez-saus Laserna Marta",
    "wof:placetype":"venue"
},
  "geometry": {"coordinates":[-3.697947979,40.401802063],"type":"Point"}
}