{
  "type": "Feature",
  "properties": {
    "iso:country":"ES",
    "sg:address":"Calle de Mesones, 2",
    "sg:city":"Estepa",
    "sg:orig_category":"Telas Y Sedas (al Por Menor)",
    "sg:phone":"+34 955 91 31 02",
    "sg:postcode":"41560",
    "sg:province":"Sevilla",
    "wof:name":"Galerias Olmedo S.a.",
    "wof:placetype":"venue"
},
  "geometry": {"coordinates":[-4.877530098,37.291721344],"type":"Point"}
}