{
  "type": "Feature",
  "properties": {
    "iso:country":"ES",
    "sg:address":"Carr Sol, 10",
    "sg:city":"Massamagrell",
    "sg:orig_category":"Zapatos (al Por Menor)",
    "sg:phone":"+34 961 44 08 94",
    "sg:postcode":"46130",
    "sg:province":"Valencia",
    "wof:name":"Arnau Peris Julia",
    "wof:placetype":"venue"
},
  "geometry": {"coordinates":[-0.3329578042,39.5707015991],"type":"Point"}
}