{
  "type": "Feature",
  "properties": {
    "addr:full":"Calle de Cristo De La Epidemia, 68 Malaga M\u00e1laga 29013",
    "addr:housenumber":"68",
    "addr:postcode":"29013",
    "addr:street":"Calle De Cristo De La Epidemia;Ma\u0301Laga",
    "iso:country":"ES",
    "sg:address":"Calle de Cristo De La Epidemia, 68",
    "sg:city":"Malaga",
    "sg:orig_category":"Papeler\u00cdas, Librer\u00cdas",
    "sg:phone":"+34 952 25 04 90",
    "sg:postcode":"29013",
    "sg:province":"M\u00e1laga",
    "wof:name":"Camacho Marin Jose",
    "wof:placetype":"venue"
},
  "geometry": {"coordinates":[-4.4150252342,36.7308807373],"type":"Point"}
}