{
  "type": "Feature",
  "properties": {
    "addr:full":"Calle de Calatrava, 10 Ciudad Real Ciudad Real 13004",
    "addr:housenumber":"10",
    "addr:postcode":"13004",
    "addr:street":"Calle De Calatrava",
    "iso:country":"ES",
    "sg:address":"Calle de Calatrava, 10",
    "sg:city":"Ciudad Real",
    "sg:orig_category":"Caf\u00c9s, Bares, Cervecer\u00cdas",
    "sg:phone":"+34 926 23 01 86",
    "sg:postcode":"13004",
    "sg:province":"Ciudad Real",
    "wof:name":"Martin Martin Ismael",
    "wof:placetype":"venue"
},
  "geometry": {"coordinates":[-3.9274291992,38.9872589111],"type":"Point"}
}