{
  "type": "Feature",
  "properties": {
    "addr:full":"Xabier Munibe Kalea, 3 Azkoitia Guip\u00f9zcoa 20720",
    "addr:housenumber":"3",
    "addr:postcode":"20720",
    "addr:street":"Xabier Munibe Kalea;Guipu\u0300Zcoa",
    "iso:country":"ES",
    "sg:address":"Xabier Munibe Kalea, 3",
    "sg:city":"Azkoitia",
    "sg:orig_category":"Higiene, Belleza: Art\u00cdculos (al Por Menor)",
    "sg:phone":"+34 943 85 35 29",
    "sg:postcode":"20720",
    "sg:province":"Guip\u00f9zcoa",
    "wof:name":"Arantzazu Epelde Azkoitia",
    "wof:placetype":"venue"
},
  "geometry": {"coordinates":[-2.3097159863,43.1779632568],"type":"Point"}
}