{
  "type": "Feature",
  "properties": {
    "addr:full":"Calle de Mayor, 81 Canteras Murcia 30394",
    "addr:housenumber":"81",
    "addr:postcode":"30394",
    "addr:street":"Calle De Mayor",
    "iso:country":"ES",
    "sg:address":"Calle de Mayor, 81",
    "sg:city":"Canteras",
    "sg:orig_category":"Asesor\u00cda Sobre Comunicaci\u00d3n De Empresas",
    "sg:phone":"+34 968 55 36 86",
    "sg:postcode":"30394",
    "sg:province":"Murcia",
    "wof:name":"Asesoria Pedro's S.l.",
    "wof:placetype":"venue"
},
  "geometry": {"coordinates":[-1.0434467793,37.6118202209],"type":"Point"}
}