{
  "type": "Feature",
  "properties": {
    "iso:country":"ES",
    "sg:address":"Calle de Islas Baleares, S/n",
    "sg:city":"Onda",
    "sg:orig_category":"Comercio De Hierro",
    "sg:phone":"+34 964 60 30 53",
    "sg:postcode":"12200",
    "sg:province":"Castell\u00f3n",
    "wof:name":"Cesareo Munera S.l.",
    "wof:placetype":"venue"
},
  "geometry": {"coordinates":[-0.2387039959,39.9654693604],"type":"Point"}
}