{
  "type": "Feature",
  "properties": {
    "addr:full":"Calle de Parque De Monfrague, 14 Vaguadas Badajoz 06010",
    "addr:housenumber":"14",
    "addr:postcode":"06010",
    "addr:street":"Calle De Parque;Monfrague",
    "iso:country":"ES",
    "sg:address":"Calle de Parque De Monfrague, 14",
    "sg:city":"Vaguadas",
    "sg:orig_category":"Delegados, Agentes De Tr\u00c1nsito, Auxiliares De Transporte Internacional",
    "sg:phone":"+34 924 26 75 65",
    "sg:postcode":"06010",
    "sg:province":"Badajoz",
    "wof:name":"Saavedra Veloso Servicios Internacionales S.l.l",
    "wof:placetype":"venue"
},
  "geometry": {"coordinates":[-6.9633808136,38.8150863647],"type":"Point"}
}