{
  "type": "Feature",
  "properties": {
    "iso:country":"ES",
    "sg:address":"Calle de Breton De Los Herreros, 33",
    "sg:city":"Logro\u00f1o",
    "sg:orig_category":"Muebles, Minoristas",
    "sg:phone":"+34 941 21 00 81",
    "sg:postcode":"26001",
    "sg:province":"La Rioja",
    "wof:name":"Rencurel Zapata Blanca",
    "wof:placetype":"venue"
},
  "geometry": {"coordinates":[-2.4497847557,42.4656143188],"type":"Point"}
}