{
  "type": "Feature",
  "properties": {
    "iso:country":"ES",
    "sg:address":"Carrer de Craywinckel, 1",
    "sg:city":"Barcelona",
    "sg:orig_category":"Art\u00cdculos De Decoraci\u00d3n",
    "sg:phone":"+34 934 18 85 55",
    "sg:postcode":"08022",
    "sg:province":"Barcelona",
    "wof:name":"Marzo Diez S.l.",
    "wof:placetype":"venue"
},
  "geometry": {"coordinates":[2.1399240494,41.412273407],"type":"Point"}
}