{
  "type": "Feature",
  "properties": {
    "iso:country":"ES",
    "sg:address":"Calle de Capitan Blanco Argibay, 7",
    "sg:city":"Madrid",
    "sg:orig_category":"Caf\u00c9s, Bares, Cervecer\u00cdas",
    "sg:phone":"+34 915 71 82 47",
    "sg:postcode":"28029",
    "sg:province":"Madrid",
    "wof:name":"El Rincon De Monica S.l.",
    "wof:placetype":"venue"
},
  "geometry": {"coordinates":[-3.6958115101,40.4645614624],"type":"Point"}
}