{
  "type": "Feature",
  "properties": {
    "iso:country":"ES",
    "sg:address":"Avda Antonio Hernandez Gil, 56",
    "sg:city":"Badajoz",
    "sg:orig_category":"Empresas De Carpinter\u00cda Met\u00c1lica",
    "sg:phone":"+34 924 24 93 46",
    "sg:postcode":"06009",
    "sg:province":"Badajoz",
    "wof:name":"Transformados Sanjuan S.l.",
    "wof:placetype":"venue"
},
  "geometry": {"coordinates":[-6.9555139542,38.8710594177],"type":"Point"}
}