{
  "type": "Feature",
  "properties": {
    "addr:full":"Carrer de Jaume I, 36 S. Boi Llobregat Barcelona 08830",
    "addr:housenumber":"36",
    "addr:postcode":"08830",
    "addr:street":"Carrer De Jaume I",
    "iso:country":"ES",
    "sg:address":"Carrer de Jaume I, 36",
    "sg:city":"S. Boi Llobregat",
    "sg:orig_category":"Asesor\u00cda Fiscal Y Jur\u00cddica",
    "sg:phone":"+34 936 61 40 04",
    "sg:postcode":"08830",
    "sg:province":"Barcelona",
    "wof:name":"Serveis I Obres Joan Bisbal S.c.p.",
    "wof:placetype":"venue"
},
  "geometry": {"coordinates":[2.0404911041,41.345287323],"type":"Point"}
}