{
  "type": "Feature",
  "properties": {
    "iso:country":"ES",
    "sg:address":"Av. Nueve Octubre, S/n",
    "sg:city":"Playa Canet Berenguer",
    "sg:orig_category":"Hoteles",
    "sg:phone":"+34 962 60 78 02",
    "sg:postcode":"46529",
    "sg:province":"Valencia",
    "wof:name":"Termas De Canet S.l",
    "wof:placetype":"venue"
},
  "geometry": {"coordinates":[-0.2033659965,39.680393219],"type":"Point"}
}