{
  "type": "Feature",
  "properties": {
    "iso:country":"ES",
    "sg:address":"Calle de Salvador Ferrandis Luna, 4",
    "sg:city":"Valencia",
    "sg:orig_category":"Partidos Pol\u00cdticos",
    "sg:phone":"+34 963 85 19 48",
    "sg:postcode":"46018",
    "sg:province":"Valencia",
    "wof:name":"Partido Socialista Obrero Espa\u00f1ol",
    "wof:placetype":"venue"
},
  "geometry": {"coordinates":[-0.3948731124,39.4701766968],"type":"Point"}
}