{
  "type": "Feature",
  "properties": {
    "addr:full":"Calle de Domingo Lozano, 60 Malaga M\u00e1laga 29010",
    "addr:housenumber":"60",
    "addr:postcode":"29010",
    "addr:street":"Calle De Domingo Lozano;Ma\u0301Laga",
    "iso:country":"ES",
    "sg:address":"Calle de Domingo Lozano, 60",
    "sg:city":"Malaga",
    "sg:orig_category":"Laboratorios",
    "sg:phone":"+34 952 28 45 04",
    "sg:postcode":"29010",
    "sg:province":"M\u00e1laga",
    "wof:name":"Instituto Andaluz De Patologia Y Microbiologia",
    "wof:placetype":"venue"
},
  "geometry": {"coordinates":[-4.4382219315,36.726146698],"type":"Point"}
}