{
  "type": "Feature",
  "properties": {
    "iso:country":"ES",
    "sg:address":"C/ Maestro Albeniz, 1",
    "sg:city":"Elche",
    "sg:orig_category":"Promotores Constructores",
    "sg:phone":"+34 966 61 47 74",
    "sg:postcode":"03202",
    "sg:province":"Alicante",
    "wof:name":"Costa Sureste S.a.",
    "wof:placetype":"venue"
},
  "geometry": {"coordinates":[-0.6963610053,38.268497467],"type":"Point"}
}