{
  "type": "Feature",
  "properties": {
    "addr:full":"Pantano Cenajo, 4 Murcia Murcia 30007",
    "addr:housenumber":"4",
    "addr:postcode":"30007",
    "addr:street":"Cenajo",
    "iso:country":"ES",
    "sg:address":"Pantano Cenajo, 4",
    "sg:city":"Murcia",
    "sg:orig_category":"Asesor\u00cda Sobre Comunicaci\u00d3n De Empresas",
    "sg:phone":"+34 968 27 16 75",
    "sg:postcode":"30007",
    "sg:province":"Murcia",
    "wof:name":"Yagues Marco Asesores S.l.",
    "wof:placetype":"venue"
},
  "geometry": {"coordinates":[-1.1309372187,37.9997291565],"type":"Point"}
}