{
  "type": "Feature",
  "properties": {
    "addr:full":"C/ Peruga, 7 Grao Castell\u00f3n 12593",
    "addr:housenumber":"7",
    "addr:postcode":"12593",
    "addr:street":"C / Peruga",
    "iso:country":"ES",
    "sg:address":"C/ Peruga, 7",
    "sg:city":"Grao",
    "sg:orig_category":"Panader\u00cdas, Panader\u00cdas",
    "sg:phone":"+34 964 58 80 63",
    "sg:postcode":"12593",
    "sg:province":"Castell\u00f3n",
    "wof:name":"Alos Gavalda Leopoldo",
    "wof:placetype":"venue"
},
  "geometry": {"coordinates":[-0.0360242017,39.9860687256],"type":"Point"}
}