{
  "type": "Feature",
  "properties": {
    "addr:full":"Calle de Diego De Los Reyes, 161 Castilleja Cuesta Sevilla 41950",
    "addr:housenumber":"161",
    "addr:postcode":"41950",
    "addr:street":"Calle De Diego De Los Reyes;Cuesta Sevilla",
    "iso:country":"ES",
    "sg:address":"Calle de Diego De Los Reyes, 161",
    "sg:city":"Castilleja Cuesta",
    "sg:orig_category":"Ebanister\u00cda",
    "sg:phone":"+34 954 16 04 59",
    "sg:postcode":"41950",
    "sg:province":"Sevilla",
    "wof:name":"Fernandez Ruiz Josefa",
    "wof:placetype":"venue"
},
  "geometry": {"coordinates":[-6.0596842766,37.3846855164],"type":"Point"}
}