{
  "type": "Feature",
  "properties": {
    "addr:full":"Carrer de La Rambla, 138 Barcelona Barcelona 08002",
    "addr:housenumber":"138",
    "addr:postcode":"08002",
    "addr:street":"Carrer De La Rambla",
    "iso:country":"ES",
    "sg:address":"Carrer de La Rambla, 138",
    "sg:city":"Barcelona",
    "sg:orig_category":"Empresarios Y Productoras De Espect\u00c1culos",
    "sg:phone":"+34 934 12 03 37",
    "sg:postcode":"08002",
    "sg:province":"Barcelona",
    "wof:name":"Empresa Alianza S. L.",
    "wof:placetype":"venue"
},
  "geometry": {"coordinates":[2.1706728935,41.3851852417],"type":"Point"}
}