{
  "type": "Feature",
  "properties": {
    "addr:full":"Carrer de Maria Cubi, 65 Barcelona Barcelona 08006",
    "addr:housenumber":"65",
    "addr:postcode":"08006",
    "addr:street":"Carrer De Maria Cubi",
    "iso:country":"ES",
    "sg:address":"Carrer de Maria Cubi, 65",
    "sg:city":"Barcelona",
    "sg:orig_category":"Agencias De Viajes",
    "sg:phone":"+34 932 00 98 27",
    "sg:postcode":"08006",
    "sg:province":"Barcelona",
    "sg:website":"www.got-travel.com",
    "wof:name":"Camiro Travel S.a.l.",
    "wof:placetype":"venue"
},
  "geometry": {"coordinates":[2.1491448879,41.3977966309],"type":"Point"}
}