{
  "type": "Feature",
  "properties": {
    "addr:full":"Calle de Iturribarria, 3 Bilbao Vizcaya 48002",
    "addr:housenumber":"3",
    "addr:postcode":"48002",
    "addr:street":"Calle De Iturribarria",
    "iso:country":"ES",
    "sg:address":"Calle de Iturribarria, 3",
    "sg:city":"Bilbao",
    "sg:classifiers":[
        {
            "category":"Autos & Motor Vehicles",
            "subcategory":"Automobile Sales",
            "type":"Retail Goods"
        }
    ],
    "sg:phone":"+34 944 39 57 79",
    "sg:postcode":"48002",
    "sg:province":"Vizcaya",
    "wof:name":"Auto-escuela Basurto S.l.",
    "wof:placetype":"venue"
},
  "geometry": {"coordinates":[-2.9506173134,43.2576980591],"type":"Point"}
}