{
  "type": "Feature",
  "properties": {
    "iso:country":"ES",
    "sg:address":"Calle de San Nicolas, 36",
    "sg:city":"Coru\u00d1a",
    "sg:orig_category":"Loter\u00cda Y T\u00d3mbola",
    "sg:phone":"+34 981 20 70 82",
    "sg:postcode":"15001",
    "sg:province":"La Coru\u00f1a",
    "wof:name":"Franco Iglesias Luisa Victoria",
    "wof:placetype":"venue"
},
  "geometry": {"coordinates":[-8.3993396759,43.3720741272],"type":"Point"}
}