{
  "type": "Feature",
  "properties": {
    "iso:country":"ES",
    "sg:address":"Ctra. Quintanar, Km. 0090,2",
    "sg:city":"Tembleque",
    "sg:orig_category":"Fabricaci\u00d3n De Telas Y Sedas",
    "sg:phone":"+34 925 14 52 76",
    "sg:postcode":"45780",
    "sg:province":"Toledo",
    "sg:website":"www.castillatextil.com",
    "wof:name":"Castilla Textil 2 S.l.",
    "wof:placetype":"venue"
},
  "geometry": {"coordinates":[-3.5035789013,39.6947860718],"type":"Point"}
}