{
  "type": "Feature",
  "properties": {
    "iso:country":"ES",
    "sg:address":"Ctra Beniajan(la Azacaya), Km. 0003,2",
    "sg:city":"Murcia",
    "sg:orig_category":"Tubos Y Tuber\u00cdas De Goma Y Pl\u00c1stico (fabricaci\u00d3n, Al Por Mayor)",
    "sg:phone":"+34 968 25 13 19",
    "sg:postcode":"30011",
    "sg:province":"Murcia",
    "wof:name":"Star Tiger S.l.l. Distribucion",
    "wof:placetype":"venue"
},
  "geometry": {"coordinates":[-1.1055790186,37.9783668518],"type":"Point"}
}