{
  "type": "Feature",
  "properties": {
    "iso:country":"ES",
    "sg:address":"Pla\u00c7 Onze De Setembre, 19",
    "sg:city":"Blanes",
    "sg:orig_category":"Ingenier\u00cda, Centros De Estudios (diversos)",
    "sg:phone":"+34 972 33 31 01",
    "sg:postcode":"17300",
    "sg:province":"Girona",
    "wof:name":"Salva & Salva Enginyers, S.l",
    "wof:placetype":"venue"
},
  "geometry": {"coordinates":[2.7891509533,41.6779670715],"type":"Point"}
}