{
  "type": "Feature",
  "properties": {
    "iso:country":"ES",
    "sg:address":"Rua Zeus, 17",
    "sg:city":"Pazo Do Rio",
    "sg:orig_category":"Transportes Frigor\u00cdficos",
    "sg:phone":"+34 981 63 73 56",
    "sg:postcode":"15172",
    "sg:province":"La Coru\u00f1a",
    "wof:name":"Pellejero E Hijos S.l.",
    "wof:placetype":"venue"
},
  "geometry": {"coordinates":[-8.3740053177,43.3324584961],"type":"Point"}
}