{
  "type": "Feature",
  "properties": {
    "addr:full":"Barr Fuentona (la), 51 Veguilla Cantabria 39538",
    "addr:postcode":"39538",
    "iso:country":"ES",
    "sg:address":"Barr Fuentona (la), 51",
    "sg:city":"Veguilla",
    "sg:orig_category":"Empresarios",
    "sg:phone":"+34 942 82 03 40",
    "sg:postcode":"39538",
    "sg:province":"Cantabria",
    "wof:name":"Elsanpacsa S.a.",
    "wof:placetype":"venue"
},
  "geometry": {"coordinates":[-4.0969400406,43.3434638977],"type":"Point"}
}