{
  "type": "Feature",
  "properties": {
    "iso:country":"ES",
    "sg:address":"Calle de Ruidera, 45",
    "sg:city":"Madrid",
    "sg:orig_category":"Plomeros",
    "sg:phone":"+34 915 07 22 13",
    "sg:postcode":"28053",
    "sg:province":"Madrid",
    "wof:name":"Foyre S.l.a",
    "wof:placetype":"venue"
},
  "geometry": {"coordinates":[-3.6753768921,40.3799362183],"type":"Point"}
}