{
  "type": "Feature",
  "properties": {
    "iso:country":"ES",
    "sg:address":"Carrer de Major, 39",
    "sg:city":"Roquetes",
    "sg:orig_category":"Droguer\u00cdas (al Por Menor)",
    "sg:phone":"+34 977 50 32 03",
    "sg:postcode":"43520",
    "sg:province":"Tarragona",
    "wof:name":"Armengol Subirats Juana",
    "wof:placetype":"venue"
},
  "geometry": {"coordinates":[0.5031520724,40.8201980591],"type":"Point"}
}