{
  "type": "Feature",
  "properties": {
    "addr:full":"Calle de Huertas, 4 Majadahonda Madrid 28220",
    "addr:housenumber":"4",
    "addr:postcode":"28220",
    "addr:street":"Calle De Huertas",
    "iso:country":"ES",
    "sg:address":"Calle de Huertas, 4",
    "sg:city":"Majadahonda",
    "sg:orig_category":"Art\u00cdculos De Decoraci\u00d3n (fabricaci\u00d3n Y Al Por Mayor)",
    "sg:phone":"+34 916 38 69 76",
    "sg:postcode":"28220",
    "sg:province":"Madrid",
    "wof:name":"Adi Arquitectura Y Dise\u00f1o S.l.",
    "wof:placetype":"venue"
},
  "geometry": {"coordinates":[-3.8723526001,40.4778633118],"type":"Point"}
}