{
  "type": "Feature",
  "properties": {
    "addr:full":"Avda Sevilla, 10 Palacios Y Villafranca Sevilla 41720",
    "addr:housenumber":"10",
    "addr:postcode":"41720",
    "addr:street":"Avda Sevilla",
    "iso:country":"ES",
    "sg:address":"Avda Sevilla, 10",
    "sg:city":"Palacios Y Villafranca",
    "sg:orig_category":"Arreglo, Reparaci\u00d3n, Piezas Sueltas De Televisi\u00d3n, V\u00cddeo, Hi",
    "sg:phone":"+34 955 81 67 25",
    "sg:postcode":"41720",
    "sg:province":"Sevilla",
    "wof:name":"Ramon Perea S.l.",
    "wof:placetype":"venue"
},
  "geometry": {"coordinates":[-5.9236798286,37.1605262756],"type":"Point"}
}