{
  "type": "Feature",
  "properties": {
    "iso:country":"ES",
    "sg:address":"Ctra Madrid Toledo (1-3), Km. 0032,7",
    "sg:city":"Illescas",
    "sg:orig_category":"Agentes, Concesionarios Y Sucursales De Veh\u00cdculos",
    "sg:phone":"+34 925 53 24 14",
    "sg:postcode":"45200",
    "sg:province":"Toledo",
    "sg:website":"www.hvt.es",
    "wof:name":"Hermanos Vi\u00f1ares Toledo S.a.",
    "wof:placetype":"venue"
},
  "geometry": {"coordinates":[-3.8594288826,40.1091804504],"type":"Point"}
}