{
  "type": "Feature",
  "properties": {
    "addr:full":"Calle de Solana, 16 Morales Vino Zamora 49190",
    "addr:housenumber":"16",
    "addr:postcode":"49190",
    "addr:street":"Calle De Solana;Zamora",
    "iso:country":"ES",
    "sg:address":"Calle de Solana, 16",
    "sg:city":"Morales Vino",
    "sg:orig_category":"Librer\u00cdas",
    "sg:phone":"+34 980 57 40 99",
    "sg:postcode":"49190",
    "sg:province":"Zamora",
    "wof:name":"Kiosko Caprichos C.b.",
    "wof:placetype":"venue"
},
  "geometry": {"coordinates":[-5.7339162827,41.4446678162],"type":"Point"}
}