{
  "type": "Feature",
  "properties": {
    "iso:country":"ES",
    "sg:address":"Ctra S Pedro S Javier, 3",
    "sg:city":"S. Pedro Pinatar",
    "sg:orig_category":"M\u00c1rmoles, Granitos Y Piedras Naturales",
    "sg:phone":"+34 968 18 34 36",
    "sg:postcode":"30740",
    "sg:province":"Murcia",
    "wof:name":"Marmoles Y Granitos Pinatar S.l.l",
    "wof:placetype":"venue"
},
  "geometry": {"coordinates":[-0.7932540178,37.8340911865],"type":"Point"}
}