{
  "type": "Feature",
  "properties": {
    "iso:country":"ES",
    "sg:address":"Altzate Karrika, 21",
    "sg:city":"Bera",
    "sg:orig_category":"Panader\u00cdas, Panader\u00cdas",
    "sg:phone":"+34 948 63 07 86",
    "sg:postcode":"31780",
    "sg:province":"Navarra",
    "wof:name":"Iriarte Iparrea Juan Maria",
    "wof:placetype":"venue"
},
  "geometry": {"coordinates":[-1.679090023,43.2818107605],"type":"Point"}
}