{
  "type": "Feature",
  "properties": {
    "iso:country":"ES",
    "sg:address":"Carrer de Goya, 12",
    "sg:city":"Cardedeu",
    "sg:orig_category":"Centros Comerciales Y Grandes Tiendas",
    "sg:phone":"+34 938 41 87 64",
    "sg:postcode":"08440",
    "sg:province":"Barcelona",
    "wof:name":"Serveis Electrics Quatre Navas S.l.",
    "wof:placetype":"venue"
},
  "geometry": {"coordinates":[2.3601369858,41.6383056641],"type":"Point"}
}