{
  "type": "Feature",
  "properties": {
    "iso:country":"ES",
    "sg:address":"Calle de Iglesia, 13",
    "sg:city":"Ejido",
    "sg:orig_category":"M\u00c9dicos: Cardiolog\u00cda Y Afecciones Cardiovasculares",
    "sg:phone":"+34 950 48 20 04",
    "sg:postcode":"04700",
    "sg:province":"Almer\u00eda",
    "wof:name":"Albacete Martinez Jose Mario",
    "wof:placetype":"venue"
},
  "geometry": {"coordinates":[-2.8145089149,36.7736358643],"type":"Point"}
}