{
  "type": "Feature",
  "properties": {
    "iso:country":"ES",
    "sg:address":"Carrer de Son Espanyolet, 6",
    "sg:city":"Palma",
    "sg:orig_category":"Veh\u00cdculos De Ocasi\u00d3n",
    "sg:phone":"+34 971 45 70 03",
    "sg:postcode":"07014",
    "sg:province":"Islas Baleares",
    "sg:website":"www.autosmillennium.com",
    "wof:name":"Lavado Jaime Maria Salvadora",
    "wof:placetype":"venue"
},
  "geometry": {"coordinates":[2.6315920353,39.5739479065],"type":"Point"}
}