{
  "type": "Feature",
  "properties": {
    "addr:full":"Calle de Ramon Calabuig, 59 Madrid Madrid 28053",
    "addr:housenumber":"59",
    "addr:postcode":"madrid;28053",
    "addr:street":"Calle De Ramon Calabuig",
    "iso:country":"ES",
    "sg:address":"Calle de Ramon Calabuig, 59",
    "sg:city":"Madrid",
    "sg:orig_category":"Prot\u00c9sicos Dentales",
    "sg:phone":"+34 914 78 27 46",
    "sg:postcode":"28053",
    "sg:province":"Madrid",
    "wof:name":"Protesis Estetica Dental Avila Ma\u00f1as S.l.",
    "wof:placetype":"venue"
},
  "geometry": {"coordinates":[-3.6679439545,40.3942260742],"type":"Point"}
}