{
  "type": "Feature",
  "properties": {
    "addr:full":"Reboira, Km. 0029,2 Reboira La Coru\u00f1a 15689",
    "addr:postcode":"15689",
    "addr:street":"Reboira Km. 0029,2 Reboira La Corun\u0303A",
    "iso:country":"ES",
    "sg:address":"Reboira, Km. 0029,2",
    "sg:city":"Reboira",
    "sg:orig_category":"Arenas, Guijarros Y Granulados",
    "sg:phone":"+34 981 69 28 77",
    "sg:postcode":"15689",
    "sg:province":"La Coru\u00f1a",
    "wof:name":"Aridos De Reboira S. A.",
    "wof:placetype":"venue"
},
  "geometry": {"coordinates":[-8.3959693909,43.3714904785],"type":"Point"}
}