{
  "type": "Feature",
  "properties": {
    "iso:country":"ES",
    "sg:address":"Carrer de Joan Maragall, 15",
    "sg:city":"Prat Llobregat",
    "sg:orig_category":"Asociaciones Humanitarias, De Cooperaci\u00d3n, De Acci\u00d3n Social",
    "sg:phone":"+34 933 70 91 39",
    "sg:postcode":"08820",
    "sg:province":"Barcelona",
    "wof:name":"Asociacion Espa\u00f1ola Contra El Cancer",
    "wof:placetype":"venue"
},
  "geometry": {"coordinates":[2.1084303856,41.3630447388],"type":"Point"}
}