{
  "type": "Feature",
  "properties": {
    "iso:country":"ES",
    "sg:address":"Acillona Auzoa, S/n",
    "sg:city":"Elexalde",
    "sg:orig_category":"Almacenes Y Tiendas De Productos Variados",
    "sg:phone":"+34 946 15 35 35",
    "sg:postcode":"48113",
    "sg:province":"Vizcaya",
    "wof:name":"Uriarte Ormaetxe Javier",
    "wof:placetype":"venue"
},
  "geometry": {"coordinates":[-2.8110890388,43.3104438782],"type":"Point"}
}