{
  "type": "Feature",
  "properties": {
    "iso:country":"ES",
    "sg:address":"Carrer de Proven\u00c7a, 152",
    "sg:city":"Barcelona",
    "sg:orig_category":"Arquitectos",
    "sg:phone":"+34 934 54 04 53",
    "sg:postcode":"08036",
    "sg:province":"Barcelona",
    "wof:name":"Puiggros Guerendiain Francisco Jose",
    "wof:placetype":"venue"
},
  "geometry": {"coordinates":[2.1524059772,41.3877944946],"type":"Point"}
}