{
  "type": "Feature",
  "properties": {
    "addr:full":"Carrer de Maria Andreu, 17 Mataro Barcelona 08302",
    "addr:housenumber":"17",
    "addr:postcode":"08302",
    "addr:street":"Carrer De Maria Andreu",
    "iso:country":"ES",
    "sg:address":"Carrer de Maria Andreu, 17",
    "sg:city":"Mataro",
    "sg:orig_category":"Prot\u00c9sicos Dentales",
    "sg:phone":"+34 937 41 54 84",
    "sg:postcode":"08302",
    "sg:province":"Barcelona",
    "wof:name":"Pou Bernabeu Sergio",
    "wof:placetype":"venue"
},
  "geometry": {"coordinates":[2.4348220825,41.5392532349],"type":"Point"}
}