{
  "type": "Feature",
  "properties": {
    "iso:country":"ES",
    "sg:address":"Ctra Valladolid, 102",
    "sg:city":"Castellanos Moriscos",
    "sg:orig_category":"Molduras, Junquillos, Listones Y Molduras Perforadas",
    "sg:phone":"+34 923 36 15 05",
    "sg:postcode":"37439",
    "sg:province":"Salamanca",
    "wof:name":"Del Rio Garcia Francisco Javier",
    "wof:placetype":"venue"
},
  "geometry": {"coordinates":[-5.6063189507,41.0126113892],"type":"Point"}
}