{
  "type": "Feature",
  "properties": {
    "addr:full":"Vilasantar, S/n Vilasantar La Coru\u00f1a 15807",
    "addr:housenumber":"s / n",
    "addr:postcode":"15807",
    "addr:street":"Vilasantar;La Corun\u0303A",
    "iso:country":"ES",
    "sg:address":"Vilasantar, S/n",
    "sg:city":"Vilasantar",
    "sg:orig_category":"Paneles De Madera: Contrachapados, Fibras, Particulados, Estratificados (fabricaci\u00d3n, Venta)",
    "sg:phone":"+34 981 77 71 17",
    "sg:postcode":"15807",
    "sg:province":"La Coru\u00f1a",
    "wof:name":"Aserpal S.a.",
    "wof:placetype":"venue"
},
  "geometry": {"coordinates":[-8.1010923386,43.0716743469],"type":"Point"}
}