{
  "type": "Feature",
  "properties": {
    "iso:country":"ES",
    "sg:address":"Nueva-kale Berria, 30",
    "sg:city":"Iru\u00f1a",
    "sg:orig_category":"Pintura, Barniz, Productos Asimilables (fabricaci\u00d3n, Al Por Mayor)",
    "sg:phone":"+34 948 22 45 95",
    "sg:postcode":"31001",
    "sg:province":"Navarra",
    "wof:name":"Euroquimica De Bufi Y Planas S.a.",
    "wof:placetype":"venue"
},
  "geometry": {"coordinates":[-1.6437540054,42.81275177],"type":"Point"}
}