{
  "type": "Feature",
  "properties": {
    "addr:full":"Calle de Paz (la), 7 Ponferrada Le\u00f3n 24400",
    "addr:postcode":"24400",
    "addr:street":"Calle De Paz La 7;Leo\u0301N",
    "iso:country":"ES",
    "sg:address":"Calle de Paz (la), 7",
    "sg:city":"Ponferrada",
    "sg:orig_category":"Cervecer\u00cdas",
    "sg:phone":"+34 987 40 56 85",
    "sg:postcode":"24400",
    "sg:province":"Le\u00f3n",
    "wof:name":"Teldespa\u00d1a S.l.",
    "wof:placetype":"venue"
},
  "geometry": {"coordinates":[-6.5989141464,42.5489578247],"type":"Point"}
}