{
  "type": "Feature",
  "properties": {
    "iso:country":"ES",
    "sg:address":"Crri Torre Salinas, 156",
    "sg:city":"Torre Salinas",
    "sg:orig_category":"Teatro, Ballet, Danza (agrupaciones, Compa\u00d1\u00cdas)",
    "sg:phone":"+34 968 26 26 05",
    "sg:postcode":"30152",
    "sg:province":"Murcia",
    "wof:name":"Qui\u00f1onero Redondo Juan Manuel",
    "wof:placetype":"venue"
},
  "geometry": {"coordinates":[-1.1452490091,37.9643058777],"type":"Point"}
}