{
  "type": "Feature",
  "properties": {
    "iso:country":"ES",
    "sg:address":"Calle de San Luis, 20",
    "sg:city":"Guardo",
    "sg:orig_category":"Maquinaria Para Industrias Diversas",
    "sg:phone":"+34 979 85 19 19",
    "sg:postcode":"34880",
    "sg:province":"Palencia",
    "wof:name":"Cascallana Mures Manuel",
    "wof:placetype":"venue"
},
  "geometry": {"coordinates":[-4.8583788872,42.7898216248],"type":"Point"}
}