{
  "type": "Feature",
  "properties": {
    "iso:country":"ES",
    "sg:address":"Calle de Diego De Leon, 25",
    "sg:city":"Madrid",
    "sg:orig_category":"Barcos",
    "sg:phone":"+34 917 45 26 80",
    "sg:postcode":"28006",
    "sg:province":"Madrid",
    "wof:name":"Neinor Iberica S.a.",
    "wof:placetype":"venue"
},
  "geometry": {"coordinates":[-3.6818685532,40.4348907471],"type":"Point"}
}