{
  "type": "Feature",
  "properties": {
    "iso:country":"ES",
    "sg:address":"Pl L'estacio, 4",
    "sg:city":"Barcelona",
    "sg:orig_category":"Molduras, Junquillos, Listones Y Molduras Perforadas",
    "sg:phone":"+34 932 74 05 87",
    "sg:postcode":"08030",
    "sg:province":"Barcelona",
    "wof:name":"Carrasco Martin Emilio",
    "wof:placetype":"venue"
},
  "geometry": {"coordinates":[2.1927647591,41.4348144531],"type":"Point"}
}