{
  "type": "Feature",
  "properties": {
    "addr:full":"Calle de Ubaldo Calvo, S/n Priego Cordoba C\u00f3rdoba 14800",
    "addr:housenumber":"s / n",
    "addr:postcode":"14800",
    "addr:street":"Calle De Ubaldo Calvo;Cordoba Co\u0301Rdoba",
    "iso:country":"ES",
    "sg:address":"Calle de Ubaldo Calvo, S/n",
    "sg:city":"Priego Cordoba",
    "sg:orig_category":"Asilos De Ancianos. Centros Privados",
    "sg:phone":"+34 957 54 28 62",
    "sg:postcode":"14800",
    "sg:province":"C\u00f3rdoba",
    "wof:name":"Geiss-96 S.l.",
    "wof:placetype":"venue"
},
  "geometry": {"coordinates":[-4.1944289207,37.4363937378],"type":"Point"}
}