{
  "type": "Feature",
  "properties": {
    "iso:country":"ES",
    "sg:address":"Calle de Mayor, 76",
    "sg:city":"Anso",
    "sg:orig_category":"Carnicer\u00cdas, Carnicer\u00cdas",
    "sg:phone":"+34 974 37 01 71",
    "sg:postcode":"22728",
    "sg:province":"Huesca",
    "wof:name":"Carniceria Alimentacion Rosenda S.c.",
    "wof:placetype":"venue"
},
  "geometry": {"coordinates":[-0.828215003,42.7570037842],"type":"Point"}
}