{
  "type": "Feature",
  "properties": {
    "iso:country":"ES",
    "sg:address":"Carrer de Esglesia, 178",
    "sg:city":"Calella",
    "sg:orig_category":"Bisuter\u00cda, Joyer\u00cda, Relojer\u00cda (al Por Menor)",
    "sg:phone":"+34 937 69 16 58",
    "sg:postcode":"08370",
    "sg:province":"Barcelona",
    "wof:name":"Bosch Puigvert Concepcion",
    "wof:placetype":"venue"
},
  "geometry": {"coordinates":[2.663435936,41.6150512695],"type":"Point"}
}