{
  "type": "Feature",
  "properties": {
    "iso:country":"ES",
    "sg:address":"Via Julia, 113",
    "sg:city":"Barcelona",
    "sg:orig_category":"Lencer\u00cda Femenina, Corseter\u00cda, Trajes De Ba\u00d1o (al Por Menor)",
    "sg:phone":"+34 933 59 55 03",
    "sg:postcode":"08042",
    "sg:province":"Barcelona",
    "sg:website":"www.perlagris.com",
    "wof:name":"La Perla Gris S.l.",
    "wof:placetype":"venue"
},
  "geometry": {"coordinates":[2.1776390076,41.4423065186],"type":"Point"}
}