{
  "type": "Feature",
  "properties": {
    "iso:country":"ES",
    "sg:address":"Calle de Garcia Rivero Maestro, 8",
    "sg:city":"Bilbao",
    "sg:orig_category":"Molduras, Junquillos, Listones Y Molduras Perforadas",
    "sg:phone":"+34 944 41 59 37",
    "sg:postcode":"48011",
    "sg:province":"Vizcaya",
    "wof:name":"Pereda Ramila Maria Antonia",
    "wof:placetype":"venue"
},
  "geometry": {"coordinates":[-2.9392540455,43.2621498108],"type":"Point"}
}