{
  "type": "Feature",
  "properties": {
    "iso:country":"ES",
    "sg:address":"Rbla Guipuscoa, 16",
    "sg:city":"Barcelona",
    "sg:orig_category":"Bisuter\u00cda, Joyer\u00cda, Relojer\u00cda (al Por Menor)",
    "sg:phone":"+34 933 07 97 40",
    "sg:postcode":"08018",
    "sg:province":"Barcelona",
    "wof:name":"Garcia Medina Maria Dolores",
    "wof:placetype":"venue"
},
  "geometry": {"coordinates":[2.1936180592,41.4134178162],"type":"Point"}
}