{
  "type": "Feature",
  "properties": {
    "iso:country":"ES",
    "sg:address":"Carr Real (del), 38",
    "sg:city":"Albaida",
    "sg:orig_category":"Droguer\u00cdas (al Por Menor)",
    "sg:phone":"+34 962 39 03 67",
    "sg:postcode":"46860",
    "sg:province":"Valencia",
    "wof:name":"Albert Soler Maria Remedio",
    "wof:placetype":"venue"
},
  "geometry": {"coordinates":[-0.5184764862,38.8387756348],"type":"Point"}
}