{
  "type": "Feature",
  "properties": {
    "iso:country":"ES",
    "sg:address":"Calle de Puerta De Jaen, 12",
    "sg:city":"Torredonjimeno",
    "sg:orig_category":"Asociaciones Y Clubs Deportivos",
    "sg:phone":"+34 953 57 10 30",
    "sg:postcode":"23650",
    "sg:province":"Ja\u00e9n",
    "wof:name":"Vargas Sanchez Dolores",
    "wof:placetype":"venue"
},
  "geometry": {"coordinates":[-3.9555430412,37.7661743164],"type":"Point"}
}