{
  "type": "Feature",
  "properties": {
    "iso:country":"ES",
    "sg:address":"Los Molinos, 19",
    "sg:city":"Medina Rioseco",
    "sg:orig_category":"Transportes Por V\u00cdas Navegables",
    "sg:phone":"+34 983 70 08 86",
    "sg:postcode":"47800",
    "sg:province":"Valladolid",
    "wof:name":"Fuertes Agundez Jose",
    "wof:placetype":"venue"
},
  "geometry": {"coordinates":[-5.047519207,41.8827896118],"type":"Point"}
}