{
  "type": "Feature",
  "properties": {
    "addr:full":"Urb Se\u00d1orio De Marbella, 13 Marbella M\u00e1laga 29600",
    "addr:housenumber":"13",
    "addr:postcode":"29600",
    "addr:street":"Urb;Marbella;Ma\u0301Laga",
    "iso:country":"ES",
    "sg:address":"Urb Se\u00d1orio De Marbella, 13",
    "sg:city":"Marbella",
    "sg:orig_category":"Fabricaci\u00d3n De Juguetes Autom\u00c1ticos",
    "sg:phone":"+34 952 82 92 51",
    "sg:postcode":"29600",
    "sg:province":"M\u00e1laga",
    "wof:name":"Tcs Spain S.a.",
    "wof:placetype":"venue"
},
  "geometry": {"coordinates":[-4.8833007812,36.5079956055],"type":"Point"}
}