{
  "type": "Feature",
  "properties": {
    "iso:country":"ES",
    "sg:address":"Avda Jaraiz, S/n",
    "sg:city":"Torremenga",
    "sg:orig_category":"Empresas De Desmonte",
    "sg:phone":"+34 927 46 08 67",
    "sg:postcode":"10413",
    "sg:province":"C\u00e1ceres",
    "wof:name":"Rufino Y Alejandro Albalat S.l.",
    "wof:placetype":"venue"
},
  "geometry": {"coordinates":[-5.7714037895,40.0477142334],"type":"Point"}
}