{
  "type": "Feature",
  "properties": {
    "iso:country":"ES",
    "sg:address":"Carr San Fernando, 17",
    "sg:city":"Mao",
    "sg:orig_category":"Ense\u00d1anza Variada",
    "sg:phone":"+34 971 35 05 08",
    "sg:postcode":"07702",
    "sg:province":"Islas Baleares",
    "sg:website":"www.escoladeturisme.com",
    "wof:name":"Escuela De Turismo De Baleares S.l.",
    "wof:placetype":"venue"
},
  "geometry": {"coordinates":[4.265625,39.8903694153],"type":"Point"}
}