{
  "type": "Feature",
  "properties": {
    "iso:country":"ES",
    "sg:address":"Carrer de Pare Artigas, 73",
    "sg:city":"Viladecans",
    "sg:orig_category":"Electrodom\u00c9sticos (al Por Menor)",
    "sg:phone":"+34 936 37 63 08",
    "sg:postcode":"08840",
    "sg:province":"Barcelona",
    "wof:name":"Bergada Roig Ramon",
    "wof:placetype":"venue"
},
  "geometry": {"coordinates":[2.0150089264,41.3197937012],"type":"Point"}
}