{
  "type": "Feature",
  "properties": {
    "iso:country":"ES",
    "sg:address":"Rua Urzaiz, 32",
    "sg:city":"Vigo",
    "sg:orig_category":"Laboratorios Y Trabajos De Fotograf\u00cda, V\u00cddeo Y Cine",
    "sg:phone":"+34 986 43 89 60",
    "sg:postcode":"36201",
    "sg:province":"Pontevedra",
    "sg:website":"www.fotoprix.es",
    "wof:name":"Fernandez Miguez Luis Miguel",
    "wof:placetype":"venue"
},
  "geometry": {"coordinates":[-8.7181558609,42.2350387573],"type":"Point"}
}