{
  "type": "Feature",
  "properties": {
    "addr:full":"Mikelar Kalea, 1 Lazkao Guip\u00f9zcoa 20210",
    "addr:housenumber":"1",
    "addr:postcode":"20210",
    "addr:street":"Mikelar Kalea;Guipu\u0300Zcoa",
    "iso:country":"ES",
    "sg:address":"Mikelar Kalea, 1",
    "sg:city":"Lazkao",
    "sg:orig_category":"Herboristas (al Por Menor)",
    "sg:phone":"+34 943 88 93 62",
    "sg:postcode":"20210",
    "sg:province":"Guip\u00f9zcoa",
    "wof:name":"Ainhoa Elduaien Intxausti",
    "wof:placetype":"venue"
},
  "geometry": {"coordinates":[-2.1864843369,43.0331306458],"type":"Point"}
}