{
  "type": "Feature",
  "properties": {
    "iso:country":"ES",
    "sg:address":"Calle de Braganza, 3",
    "sg:city":"Sotogrande",
    "sg:orig_category":"Financiaci\u00d3n Y Cr\u00c9ditos",
    "sg:phone":"+34 956 79 50 86",
    "sg:postcode":"11310",
    "sg:province":"C\u00e1diz",
    "wof:name":"Kirkby  Christopher John",
    "wof:placetype":"venue"
},
  "geometry": {"coordinates":[-5.3095135689,36.2799301147],"type":"Point"}
}