{
  "type": "Feature",
  "properties": {
    "addr:full":"Carrer de Mossen Jacint Verdaguer, 86 S. Boi Llobregat Barcelona 08830",
    "addr:housenumber":"86",
    "addr:postcode":"08830",
    "addr:street":"Carrer De Mossen Jacint Verdaguer",
    "iso:country":"ES",
    "sg:address":"Carrer de Mossen Jacint Verdaguer, 86",
    "sg:city":"S. Boi Llobregat",
    "sg:orig_category":"Empresas De Carpinter\u00cda",
    "sg:phone":"+34 936 40 62 60",
    "sg:postcode":"08830",
    "sg:province":"Barcelona",
    "wof:name":"Alu-mobel S.l.",
    "wof:placetype":"venue"
},
  "geometry": {"coordinates":[2.0399782658,41.3414878845],"type":"Point"}
}