{
  "type": "Feature",
  "properties": {
    "iso:country":"ES",
    "sg:address":"Calle de Salamanca, 21",
    "sg:city":"Madrid",
    "sg:orig_category":"Chapister\u00cda",
    "sg:phone":"+34 915 70 57 88",
    "sg:postcode":"28020",
    "sg:province":"Madrid",
    "wof:name":"T.couto Automoviles S.l.",
    "wof:placetype":"venue"
},
  "geometry": {"coordinates":[-3.6999320984,40.4540214539],"type":"Point"}
}