{
  "type": "Feature",
  "properties": {
    "addr:full":"Carrer de Pep Ventura, 5 Martorell Barcelona 08760",
    "addr:housenumber":"5",
    "addr:postcode":"08760",
    "addr:street":"Carrer De Pep Ventura",
    "iso:country":"ES",
    "sg:address":"Carrer de Pep Ventura, 5",
    "sg:city":"Martorell",
    "sg:orig_category":"Molduras, Junquillos, Listones Y Molduras Perforadas",
    "sg:phone":"+34 937 74 29 49",
    "sg:postcode":"08760",
    "sg:province":"Barcelona",
    "wof:name":"Cordon Velasco Jose",
    "wof:placetype":"venue"
},
  "geometry": {"coordinates":[1.9167490005,41.4786148071],"type":"Point"}
}