{
  "type": "Feature",
  "properties": {
    "addr:full":"Pg Valldaura, 185 Barcelona Barcelona 08016",
    "addr:housenumber":"185",
    "addr:postcode":"08016",
    "addr:street":"Pg Valldaura",
    "iso:country":"ES",
    "sg:address":"Pg Valldaura, 185",
    "sg:city":"Barcelona",
    "sg:orig_category":"Cajas De Ahorro",
    "sg:phone":"+34 932 76 39 69",
    "sg:postcode":"08016",
    "sg:province":"Barcelona",
    "wof:name":"Caixa D'estalvis Laietana",
    "wof:placetype":"venue"
},
  "geometry": {"coordinates":[2.1752231121,41.4385795593],"type":"Point"}
}