{
  "type": "Feature",
  "properties": {
    "addr:full":"Psaj Comercio, 5 Linares Ja\u00e9n 23700",
    "addr:housenumber":"5",
    "addr:postcode":"23700",
    "addr:street":"Comercio;Jae\u0301N",
    "iso:country":"ES",
    "sg:address":"Psaj Comercio, 5",
    "sg:city":"Linares",
    "sg:orig_category":"Moda",
    "sg:phone":"+34 953 65 64 73",
    "sg:postcode":"23700",
    "sg:province":"Ja\u00e9n",
    "wof:name":"Oca\u00f1a Pe\u00f1afiel Isacio",
    "wof:placetype":"venue"
},
  "geometry": {"coordinates":[-3.6354470253,38.0946464539],"type":"Point"}
}