{
  "type": "Feature",
  "properties": {
    "addr:full":"Calle de Prim, 8 Madrid Madrid 28004",
    "addr:housenumber":"8",
    "addr:postcode":"madrid;28004",
    "addr:street":"Calle De Prim",
    "iso:country":"ES",
    "sg:address":"Calle de Prim, 8",
    "sg:city":"Madrid",
    "sg:orig_category":"Transportes Internacionales",
    "sg:phone":"+34 915 21 62 85",
    "sg:postcode":"28004",
    "sg:province":"Madrid",
    "wof:name":"Union De Servicios Logisticos Integrales S.a.",
    "wof:placetype":"venue"
},
  "geometry": {"coordinates":[-3.6939790249,40.4218788147],"type":"Point"}
}