{
  "type": "Feature",
  "properties": {
    "addr:full":"Conde Romanones, 20 Lo Pagan Murcia 30740",
    "addr:housenumber":"20",
    "addr:postcode":"30740",
    "addr:street":"Romanones",
    "iso:country":"ES",
    "sg:address":"Conde Romanones, 20",
    "sg:city":"Lo Pagan",
    "sg:orig_category":"Reposter\u00cdas",
    "sg:phone":"+34 968 18 11 66",
    "sg:postcode":"30740",
    "sg:province":"Murcia",
    "wof:name":"Patriher S.l.",
    "wof:placetype":"venue"
},
  "geometry": {"coordinates":[-0.7932540178,37.8340911865],"type":"Point"}
}