{
  "type": "Feature",
  "properties": {
    "addr:full":"Carr Ribarroja, 53 Manises Valencia 46940",
    "addr:housenumber":"53",
    "addr:postcode":"46940",
    "addr:street":"Carr Ribarroja",
    "iso:country":"ES",
    "sg:address":"Carr Ribarroja, 53",
    "sg:city":"Manises",
    "sg:orig_category":"Bazares, Art\u00cdculos De Limpieza Y De Cocina (al Por Menor)",
    "sg:phone":"+34 961 52 29 87",
    "sg:postcode":"46940",
    "sg:province":"Valencia",
    "wof:name":"J.m.garcia Garcia S.a.",
    "wof:placetype":"venue"
},
  "geometry": {"coordinates":[-0.4639309943,39.4928016663],"type":"Point"}
}