{
  "type": "Feature",
  "properties": {
    "iso:country":"ES",
    "sg:address":"Calle de Ca\u00d1ada, 36",
    "sg:city":"Madrid",
    "sg:orig_category":"Procuradores",
    "sg:phone":"+34 917 73 60 14",
    "sg:postcode":"28030",
    "sg:province":"Madrid",
    "wof:name":"Fernandez Diez Eduardo",
    "wof:placetype":"venue"
},
  "geometry": {"coordinates":[-3.6442859173,40.4053764343],"type":"Point"}
}