{
  "type": "Feature",
  "properties": {
    "addr:full":"Calle de Santa Ana, 32 Le\u00f3n Le\u00f3n 24003",
    "addr:housenumber":"32",
    "addr:postcode":"24003",
    "addr:street":"Calle De Santa Ana;Leo\u0301N",
    "iso:country":"ES",
    "sg:address":"Calle de Santa Ana, 32",
    "sg:city":"Le\u00f3n",
    "sg:orig_category":"Muebles Y Accesorios Para Cocinas Y Cuartos De Ba\u00d1o (al Por Menor)",
    "sg:phone":"+34 987 25 36 01",
    "sg:postcode":"24003",
    "sg:province":"Le\u00f3n",
    "wof:name":"Santos Vazquez Cesidio",
    "wof:placetype":"venue"
},
  "geometry": {"coordinates":[-5.5657439232,42.5934524536],"type":"Point"}
}