{
  "type": "Feature",
  "properties": {
    "addr:full":"Pl. Mercat, S/n Vilanova Geltru Barcelona 08800",
    "addr:housenumber":"s / n",
    "addr:postcode":"08800",
    "addr:street":"Mercat;Geltru Barcelona",
    "iso:country":"ES",
    "sg:address":"Pl. Mercat, S/n",
    "sg:city":"Vilanova Geltru",
    "sg:orig_category":"Mercados De Productos Alimenticios",
    "sg:phone":"+34 938 93 63 53",
    "sg:postcode":"08800",
    "sg:province":"Barcelona",
    "wof:name":"Asociacion De Comerciantes Concesionaris Del Mercat Public",
    "wof:placetype":"venue"
},
  "geometry": {"coordinates":[1.7185870409,41.2272720337],"type":"Point"}
}