{
  "type": "Feature",
  "properties": {
    "iso:country":"ES",
    "sg:address":"Calle de Mariana Pineda, 18",
    "sg:city":"Sestao",
    "sg:orig_category":"Comercio De Piezas De Recambio Y De Accesorios De Veh\u00cdculos, Veh\u00cdculos Industriales",
    "sg:phone":"+34 944 96 62 61",
    "sg:postcode":"48910",
    "sg:province":"Vizcaya",
    "wof:name":"Jimeno Arg\u00fcelles Francisco Javier",
    "wof:placetype":"venue"
},
  "geometry": {"coordinates":[-3.0116660595,43.3098335266],"type":"Point"}
}