{
  "type": "Feature",
  "properties": {
    "iso:country":"ES",
    "sg:address":"Rio Altzania, 31",
    "sg:city":"Iru\u00f1a",
    "sg:orig_category":"Ingenier\u00cda, Centros De Estudios (diversos)",
    "sg:phone":"+34 948 23 37 70",
    "sg:postcode":"31005",
    "sg:province":"Navarra",
    "wof:name":"Proyectos De Desarrollo Comercial Garapen S.a.",
    "wof:placetype":"venue"
},
  "geometry": {"coordinates":[-1.6456090212,42.8039703369],"type":"Point"}
}