{
  "type": "Feature",
  "properties": {
    "addr:full":"Rua Circunvalacion D. Aurelio, 49 Cuntis Pontevedra 36670",
    "addr:housenumber":"49",
    "addr:postcode":"36670",
    "addr:street":"Rua Circunvalacion D. Aurelio",
    "iso:country":"ES",
    "sg:address":"Rua Circunvalacion D. Aurelio, 49",
    "sg:city":"Cuntis",
    "sg:classifiers":[
        {
            "category":"Autos & Motor Vehicles",
            "subcategory":"Automobile Sales",
            "type":"Retail Goods"
        }
    ],
    "sg:phone":"+34 986 53 23 44",
    "sg:postcode":"36670",
    "sg:province":"Pontevedra",
    "wof:name":"Autoescuela Portela S.l.",
    "wof:placetype":"venue"
},
  "geometry": {"coordinates":[-8.5618314743,42.6336174011],"type":"Point"}
}