{
  "type": "Feature",
  "properties": {
    "iso:country":"ES",
    "sg:address":"Ctra Norte Del, 198",
    "sg:city":"Palmas De Gran Canaria",
    "sg:orig_category":"Molduras, Junquillos, Listones Y Molduras Perforadas",
    "sg:phone":"+34 928 42 70 66",
    "sg:postcode":"35013",
    "sg:province":"Las Palmas",
    "wof:name":"Xie  Jing",
    "wof:placetype":"venue"
},
  "geometry": {"coordinates":[-15.4417381287,28.1009349823],"type":"Point"}
}