{
  "type": "Feature",
  "properties": {
    "addr:full":"Avda Carlos V, 8 Carrizal Las Palmas 35240",
    "addr:housenumber":"8",
    "addr:postcode":"35240",
    "addr:street":"Avda Carlos V",
    "iso:country":"ES",
    "sg:address":"Avda Carlos V, 8",
    "sg:city":"Carrizal",
    "sg:orig_category":"Asesor\u00cda Fiscal Y Jur\u00cddica",
    "sg:phone":"+34 928 78 48 69",
    "sg:postcode":"35240",
    "sg:province":"Las Palmas",
    "wof:name":"Asesoria Garcia Y Medina Scp",
    "wof:placetype":"venue"
},
  "geometry": {"coordinates":[-15.403670311,27.9123363495],"type":"Point"}
}