{
  "type": "Feature",
  "properties": {
    "iso:country":"ES",
    "sg:address":"Calle de Jesus De Perceval, 10",
    "sg:city":"Almeria",
    "sg:orig_category":"Comercio, Reparaci\u00d3n De Bicicletas, De Motocicletas, De Accesorios",
    "sg:phone":"+34 950 25 55 19",
    "sg:postcode":"04003",
    "sg:province":"Almer\u00eda",
    "wof:name":"Sanchez Ruiz Blas",
    "wof:placetype":"venue"
},
  "geometry": {"coordinates":[-2.4637129307,36.8443641663],"type":"Point"}
}