{
  "type": "Feature",
  "properties": {
    "iso:country":"ES",
    "sg:address":"Avda Doctor Villa (circunvalacion Del Real), 20",
    "sg:city":"Carmona",
    "sg:orig_category":"Forjas Y Altos Hornos",
    "sg:phone":"+34 954 14 12 38",
    "sg:postcode":"41410",
    "sg:province":"Sevilla",
    "wof:name":"Tiendas Mi Confort S.c.",
    "wof:placetype":"venue"
},
  "geometry": {"coordinates":[-5.6433792114,37.4708709717],"type":"Point"}
}