{
  "type": "Feature",
  "properties": {
    "iso:country":"ES",
    "sg:address":"Ctra Alberic-tous, 123",
    "sg:city":"S. Cristobal",
    "sg:orig_category":"Asesores De Gesti\u00d3n Del Patrimonio",
    "sg:phone":"+34 962 44 11 29",
    "sg:postcode":"46260",
    "sg:province":"Valencia",
    "wof:name":"Patrimonialista Alberic S.l.",
    "wof:placetype":"venue"
},
  "geometry": {"coordinates":[-0.520138979,39.11901474],"type":"Point"}
}