{
  "type": "Feature",
  "properties": {
    "iso:country":"ES",
    "sg:address":"Pque. Tecn. De Asturias, S/n",
    "sg:city":"Cayes",
    "sg:orig_category":"Puros, Cigarrillos Y Tabaco (fabricaci\u00d3n, Al Por Mayor)",
    "sg:phone":"+34 985 26 68 02",
    "sg:postcode":"33428",
    "sg:province":"Asturias",
    "wof:name":"Philip Morris Spain S.l.",
    "wof:placetype":"venue"
},
  "geometry": {"coordinates":[-5.8358402252,43.4143867493],"type":"Point"}
}