{
  "type": "Feature",
  "properties": {
    "iso:country":"ES",
    "sg:address":"Carr Font (la), 9",
    "sg:city":"Ager",
    "sg:orig_category":"Deportes Y Programas De Aventura",
    "sg:phone":"+34 973 45 50 99",
    "sg:postcode":"25691",
    "sg:province":"Lleida",
    "sg:website":"www.entrenuvols.com",
    "wof:name":"Entrenuvols S.l.",
    "wof:placetype":"venue"
},
  "geometry": {"coordinates":[0.7641400099,42.0030517578],"type":"Point"}
}