{
  "type": "Feature",
  "properties": {
    "iso:country":"ES",
    "sg:address":"Calle de Juan De Herrera, 24",
    "sg:city":"Santander",
    "sg:orig_category":"Agencias Y Agentes Comerciales, Representantes",
    "sg:phone":"+34 942 36 24 52",
    "sg:postcode":"39001",
    "sg:province":"Cantabria",
    "wof:name":"Soler Galdona Alfredo",
    "wof:placetype":"venue"
},
  "geometry": {"coordinates":[-3.8070406914,43.4621734619],"type":"Point"}
}