{
  "type": "Feature",
  "properties": {
    "addr:full":"Calle de Muller, 42 Madrid Madrid 28029",
    "addr:housenumber":"42",
    "addr:postcode":"madrid;28029",
    "addr:street":"Calle De Muller",
    "iso:country":"ES",
    "sg:address":"Calle de Muller, 42",
    "sg:city":"Madrid",
    "sg:orig_category":"Pod\u00d3logos: Pedicuros",
    "sg:phone":"+34 913 14 30 96",
    "sg:postcode":"28029",
    "sg:province":"Madrid",
    "wof:name":"Moreno Villafuertes Conrado",
    "wof:placetype":"venue"
},
  "geometry": {"coordinates":[-3.6979959011,40.4655036926],"type":"Point"}
}