{
  "type": "Feature",
  "properties": {
    "addr:full":"Calle de Regimiento Tetuan, 3 Vall D'uixo Castell\u00f3n 12600",
    "addr:housenumber":"3",
    "addr:postcode":"12600",
    "addr:street":"Calle De Regimiento Tetuan",
    "iso:country":"ES",
    "sg:address":"Calle de Regimiento Tetuan, 3",
    "sg:city":"Vall D'uixo",
    "sg:orig_category":"Asesor\u00cdas Y Estudios Financieros",
    "sg:phone":"+34 964 66 40 14",
    "sg:postcode":"12600",
    "sg:province":"Castell\u00f3n",
    "wof:name":"Orenga Segarra Jose Ramon",
    "wof:placetype":"venue"
},
  "geometry": {"coordinates":[-0.0482099988,39.992477417],"type":"Point"}
}