{
  "type": "Feature",
  "properties": {
    "addr:full":"Calle de Correillo (el), 41 Playa Blanca Las Palmas 35580",
    "addr:housenumber":"41",
    "addr:postcode":"35580",
    "addr:street":"Calle De Correillo El",
    "iso:country":"ES",
    "sg:address":"Calle de Correillo (el), 41",
    "sg:city":"Playa Blanca",
    "sg:orig_category":"Inmobiliaria (agencias)",
    "sg:phone":"+34 928 51 77 31",
    "sg:postcode":"35580",
    "sg:province":"Las Palmas",
    "wof:name":"Complejo Lanzarote Sol S.l.",
    "wof:placetype":"venue"
},
  "geometry": {"coordinates":[-13.8313140869,28.8625717163],"type":"Point"}
}