{
  "type": "Feature",
  "properties": {
    "addr:full":"Carrer de Pas Del Llop, 1 Sant Vicen\u00c7 Dels Horts Barcelona 08620",
    "addr:housenumber":"1",
    "addr:postcode":"08620",
    "addr:street":"Carrer De Pas Del Llop",
    "iso:country":"ES",
    "sg:address":"Carrer de Pas Del Llop, 1",
    "sg:city":"Sant Vicen\u00c7 Dels Horts",
    "sg:orig_category":"Administradores De Bienes Y Delegados De Comunidades De Propietarios",
    "sg:phone":"+34 936 56 24 25",
    "sg:postcode":"08620",
    "sg:province":"Barcelona",
    "wof:name":"Fincaservice S.l.",
    "wof:placetype":"venue"
},
  "geometry": {"coordinates":[2.0105769634,41.3945617676],"type":"Point"}
}