{
  "type": "Feature",
  "properties": {
    "addr:full":"Calle de Ferial, 3 Soria Soria 42001",
    "addr:housenumber":"3",
    "addr:postcode":"42001",
    "addr:street":"Calle De Ferial",
    "iso:country":"ES",
    "sg:address":"Calle de Ferial, 3",
    "sg:city":"Soria",
    "sg:orig_category":"Abogados",
    "sg:phone":"+34 975 22 90 80",
    "sg:postcode":"42001",
    "sg:province":"Soria",
    "wof:name":"Garcia Romero Jose Antonio",
    "wof:placetype":"venue"
},
  "geometry": {"coordinates":[-2.469342947,41.7648200989],"type":"Point"}
}