{
  "type": "Feature",
  "properties": {
    "iso:country":"ES",
    "sg:address":"Avda Flores (las), 64",
    "sg:city":"Alcorcon",
    "sg:orig_category":"Promotores Constructores",
    "sg:phone":"+34 916 11 86 51",
    "sg:postcode":"28925",
    "sg:province":"Madrid",
    "wof:name":"Construcciones Somoza S.l.",
    "wof:placetype":"venue"
},
  "geometry": {"coordinates":[-3.8060719967,40.3569869995],"type":"Point"}
}