{
  "type": "Feature",
  "properties": {
    "addr:full":"Carrer de General O'donnell, 61 S. Boi Llobregat Barcelona 08830",
    "addr:housenumber":"61",
    "addr:postcode":"08830",
    "addr:street":"Carrer De General O'Donnell",
    "iso:country":"ES",
    "sg:address":"Carrer de General O'donnell, 61",
    "sg:city":"S. Boi Llobregat",
    "sg:orig_category":"Negocio De Materiales De Construcci\u00d3n",
    "sg:phone":"+34 936 40 24 26",
    "sg:postcode":"08830",
    "sg:province":"Barcelona",
    "wof:name":"Es & S S.l.",
    "wof:placetype":"venue"
},
  "geometry": {"coordinates":[2.0401880741,41.346698761],"type":"Point"}
}