{
  "type": "Feature",
  "properties": {
    "iso:country":"ES",
    "sg:address":"Calle de Rosario, 6",
    "sg:city":"Caspe",
    "sg:orig_category":"Asociaciones Y Clubs Deportivos",
    "sg:phone":"+34 976 63 31 44",
    "sg:postcode":"50700",
    "sg:province":"Zaragoza",
    "wof:name":"Sociedad Deportiva De Pesca",
    "wof:placetype":"venue"
},
  "geometry": {"coordinates":[-0.0409159996,41.2375564575],"type":"Point"}
}