{
  "type": "Feature",
  "properties": {
    "addr:full":"Pla\u00c7 Paeria, 3 Lleida Lleida 25007",
    "addr:housenumber":"3",
    "addr:postcode":"25007",
    "addr:street":"Plac\u0327 Paeria",
    "iso:country":"ES",
    "sg:address":"Pla\u00c7 Paeria, 3",
    "sg:city":"Lleida",
    "sg:orig_category":"Ropa Para Se\u00d1oras (al Por Menor)",
    "sg:phone":"+34 973 24 33 60",
    "sg:postcode":"25007",
    "sg:province":"Lleida",
    "wof:name":"Bujan Fernandez Maria Montserrat",
    "wof:placetype":"venue"
},
  "geometry": {"coordinates":[0.627129972,41.6145210266],"type":"Point"}
}