{
  "type": "Feature",
  "properties": {
    "iso:country":"ES",
    "sg:address":"Av Prat De La Riba, 4",
    "sg:city":"Tarragona",
    "sg:orig_category":"M\u00c9dicos: Estomatolog\u00cda",
    "sg:phone":"+34 977 22 52 55",
    "sg:postcode":"43001",
    "sg:province":"Tarragona",
    "wof:name":"Carrasco Sobrino Enrique",
    "wof:placetype":"venue"
},
  "geometry": {"coordinates":[1.2472569942,41.1148147583],"type":"Point"}
}