{
  "type": "Feature",
  "properties": {
    "addr:full":"Calle de Zaragoza, 7 Binefar Huesca 22500",
    "addr:housenumber":"7",
    "addr:postcode":"22500",
    "addr:street":"Calle De Zaragoza",
    "iso:country":"ES",
    "sg:address":"Calle de Zaragoza, 7",
    "sg:city":"Binefar",
    "sg:orig_category":"Material Y Herramientas Agr\u00cdcolas",
    "sg:phone":"+34 974 43 14 40",
    "sg:postcode":"22500",
    "sg:province":"Huesca",
    "wof:name":"Mecanobim S.l.",
    "wof:placetype":"venue"
},
  "geometry": {"coordinates":[0.2922489941,41.8502006531],"type":"Point"}
}