{
  "type": "Feature",
  "properties": {
    "iso:country":"ES",
    "sg:address":"Calle de Exposicion, 2",
    "sg:city":"Mairena Aljarafe",
    "sg:orig_category":"Artesan\u00cda",
    "sg:phone":"+34 954 18 08 57",
    "sg:postcode":"41927",
    "sg:province":"Sevilla",
    "wof:name":"Checa Navarro Francisco",
    "wof:placetype":"venue"
},
  "geometry": {"coordinates":[-6.0591378212,37.3517379761],"type":"Point"}
}