{
  "type": "Feature",
  "properties": {
    "addr:full":"C/ Diego De Cardenas, 8 Elche Alicante 03205",
    "addr:housenumber":"8",
    "addr:postcode":"03205",
    "addr:street":"C / Diego De Cardenas",
    "iso:country":"ES",
    "sg:address":"C/ Diego De Cardenas, 8",
    "sg:city":"Elche",
    "sg:orig_category":"Alimentaci\u00d3n General (al Por Menor)",
    "sg:phone":"+34 965 46 50 76",
    "sg:postcode":"03205",
    "sg:province":"Alicante",
    "wof:name":"Sanchez Salinas Francisco",
    "wof:placetype":"venue"
},
  "geometry": {"coordinates":[-0.7154589891,38.2718238831],"type":"Point"}
}