{
  "type": "Feature",
  "properties": {
    "iso:country":"ES",
    "sg:address":"Plaz Blas Leoncio De Pi\u00d1ar, 6",
    "sg:city":"Zubia",
    "sg:orig_category":"Agentes, Concesionarios Y Sucursales De Veh\u00cdculos",
    "sg:phone":"+34 958 59 30 19",
    "sg:postcode":"18140",
    "sg:province":"Granada",
    "wof:name":"Alixares Motor",
    "wof:placetype":"venue"
},
  "geometry": {"coordinates":[-3.5871829987,37.125919342],"type":"Point"}
}