{
  "type": "Feature",
  "properties": {
    "addr:full":"Tamariu (sec Puigmal), 8 Empuriabrava Girona 17487",
    "addr:housenumber":"8",
    "addr:postcode":"17487",
    "addr:street":"Puigmal",
    "iso:country":"ES",
    "sg:address":"Tamariu (sec Puigmal), 8",
    "sg:city":"Empuriabrava",
    "sg:orig_category":"Muebles, Minoristas",
    "sg:phone":"+34 972 45 33 28",
    "sg:postcode":"17487",
    "sg:province":"Girona",
    "wof:name":"Mobles Marcla S.l.",
    "wof:placetype":"venue"
},
  "geometry": {"coordinates":[3.1036469936,42.2594909668],"type":"Point"}
}