{
  "type": "Feature",
  "properties": {
    "iso:country":"ES",
    "sg:address":"Calle de Mayor, 93",
    "sg:city":"Gurrea Gallego",
    "sg:orig_category":"Cajas De Ahorro",
    "sg:phone":"+34 976 68 81 34",
    "sg:postcode":"22280",
    "sg:province":"Huesca",
    "wof:name":"Caja De Ahorros Y Monte De Piedad De Zaragoza Aragon Y Rioja",
    "wof:placetype":"venue"
},
  "geometry": {"coordinates":[-0.7597029805,42.0178794861],"type":"Point"}
}