{
  "type": "Feature",
  "properties": {
    "iso:country":"ES",
    "sg:address":"Av Juli Garreta, 30",
    "sg:city":"S. Feliu Guixols",
    "sg:orig_category":"Empresas De Limpieza",
    "sg:phone":"+34 972 82 00 14",
    "sg:postcode":"17220",
    "sg:province":"Girona",
    "wof:name":"Clavaguera Poch Silvia",
    "wof:placetype":"venue"
},
  "geometry": {"coordinates":[3.0276350975,41.7804298401],"type":"Point"}
}