{
  "type": "Feature",
  "properties": {
    "iso:country":"ES",
    "sg:address":"Carr Rutlla, 12",
    "sg:city":"Girona",
    "sg:orig_category":"Supermercados Y Hipermercados",
    "sg:phone":"+34 972 20 60 56",
    "sg:postcode":"17002",
    "sg:province":"Girona",
    "wof:name":"Ufana Ecomercats Girona, S.l.",
    "wof:placetype":"venue"
},
  "geometry": {"coordinates":[2.8233599663,41.9785766602],"type":"Point"}
}