{
  "type": "Feature",
  "properties": {
    "addr:full":"Praz Maior, 11 Viveiro Lugo 27850",
    "addr:housenumber":"11",
    "addr:postcode":"27850",
    "addr:street":"Praz Maior",
    "iso:country":"ES",
    "sg:address":"Praz Maior, 11",
    "sg:city":"Viveiro",
    "sg:orig_category":"Librer\u00cdas",
    "sg:phone":"+34 982 57 00 57",
    "sg:postcode":"27850",
    "sg:province":"Lugo",
    "wof:name":"Martinez Vigeiras Maria Dolores",
    "wof:placetype":"venue"
},
  "geometry": {"coordinates":[-7.5956220627,43.6619911194],"type":"Point"}
}