{
  "type": "Feature",
  "properties": {
    "addr:full":"Av Rius I Taulet, 17 S. Cugat Valles Barcelona 08172",
    "addr:housenumber":"17",
    "addr:postcode":"08172",
    "addr:street":"Av Rius I Taulet;S. Cugat Valles Barcelona",
    "iso:country":"ES",
    "sg:address":"Av Rius I Taulet, 17",
    "sg:city":"S. Cugat Valles",
    "sg:orig_category":"Maquinaria Para Industrias Diversas",
    "sg:phone":"+34 936 74 08 56",
    "sg:postcode":"08172",
    "sg:province":"Barcelona",
    "wof:name":"Bordas Camps Pedro",
    "wof:placetype":"venue"
},
  "geometry": {"coordinates":[2.0811710358,41.4719848633],"type":"Point"}
}