{
  "type": "Feature",
  "properties": {
    "iso:country":"ES",
    "sg:address":"Avgd Marti Pujol, 448",
    "sg:city":"Badalona",
    "sg:orig_category":"Asesor\u00cda Fiscal Y Jur\u00cddica",
    "sg:phone":"+34 933 98 02 10",
    "sg:postcode":"08915",
    "sg:province":"Barcelona",
    "wof:name":"Asesoria Gayse S.l.",
    "wof:placetype":"venue"
},
  "geometry": {"coordinates":[2.2403585911,41.4591560364],"type":"Point"}
}