{
  "type": "Feature",
  "properties": {
    "addr:full":"Florida Auzoa, 28 Hernani Guip\u00f9zcoa 20120",
    "addr:housenumber":"28",
    "addr:postcode":"20120",
    "addr:street":"Florida Auzoa;Guipu\u0300Zcoa",
    "iso:country":"ES",
    "sg:address":"Florida Auzoa, 28",
    "sg:city":"Hernani",
    "sg:orig_category":"Ense\u00d1anza Variada",
    "sg:phone":"+34 943 55 26 33",
    "sg:postcode":"20120",
    "sg:province":"Guip\u00f9zcoa",
    "wof:name":"Gobierno Vasco-eusko Jaurlaritza",
    "wof:placetype":"venue"
},
  "geometry": {"coordinates":[-1.9718589783,43.2695655823],"type":"Point"}
}