{
  "type": "Feature",
  "properties": {
    "addr:full":"Calle de San Pascual, 224 Torrevieja Alicante 03180",
    "addr:housenumber":"224",
    "addr:postcode":"03180",
    "addr:street":"Calle De San Pascual",
    "iso:country":"ES",
    "sg:address":"Calle de San Pascual, 224",
    "sg:city":"Torrevieja",
    "sg:orig_category":"Administradores De Bienes Y Delegados De Comunidades De Propietarios",
    "sg:phone":"+34 966 70 39 19",
    "sg:postcode":"03180",
    "sg:province":"Alicante",
    "wof:name":"Anguita Castillo Jose Manuel",
    "wof:placetype":"venue"
},
  "geometry": {"coordinates":[-0.665797174,37.9811058044],"type":"Point"}
}