{
  "type": "Feature",
  "properties": {
    "addr:full":"Carrer de Balmes, 66 Sant Vicen\u00c7 Dels Horts Barcelona 08620",
    "addr:housenumber":"66",
    "addr:postcode":"08620",
    "addr:street":"Carrer De Balmes",
    "iso:country":"ES",
    "sg:address":"Carrer de Balmes, 66",
    "sg:city":"Sant Vicen\u00c7 Dels Horts",
    "sg:orig_category":"Chapister\u00cda",
    "sg:phone":"+34 936 56 79 12",
    "sg:postcode":"08620",
    "sg:province":"Barcelona",
    "wof:name":"Alfonso Carrasco Domingo",
    "wof:placetype":"venue"
},
  "geometry": {"coordinates":[2.0057592392,41.399394989],"type":"Point"}
}