{
  "type": "Feature",
  "properties": {
    "iso:country":"ES",
    "sg:address":"Avgd Joaquim Sorolla, 39",
    "sg:city":"Alcasser",
    "sg:orig_category":"Institutos De Belleza",
    "sg:phone":"+34 961 24 26 76",
    "sg:postcode":"46290",
    "sg:province":"Valencia",
    "wof:name":"Navarro Primo Maria Vicenta",
    "wof:placetype":"venue"
},
  "geometry": {"coordinates":[-0.4429939985,39.3717002869],"type":"Point"}
}