{
  "type": "Feature",
  "properties": {
    "iso:country":"ES",
    "sg:address":"Av Can Pallas, 26",
    "sg:city":"Can Pallas-llobateras",
    "sg:orig_category":"Electricidad: Instaladores",
    "sg:phone":"+34 937 21 58 56",
    "sg:postcode":"08192",
    "sg:province":"Barcelona",
    "wof:name":"Delec 2002 S.l.",
    "wof:placetype":"venue"
},
  "geometry": {"coordinates":[2.0664401054,41.5386390686],"type":"Point"}
}