{
  "type": "Feature",
  "properties": {
    "iso:country":"ES",
    "sg:address":"Po. Inmaculada, 9",
    "sg:city":"Estella",
    "sg:orig_category":"Servicios Y Funcionarios De Polic\u00cda",
    "sg:phone":"+34 948 55 01 53",
    "sg:postcode":"31200",
    "sg:province":"Navarra",
    "wof:name":"Ayuntamiento De Estella",
    "wof:placetype":"venue"
},
  "geometry": {"coordinates":[-2.02242136,42.6653747559],"type":"Point"}
}