{
  "type": "Feature",
  "properties": {
    "addr:full":"Calle de Fuente De Las Risas, 7 Ubeda Ja\u00e9n 23400",
    "addr:housenumber":"7",
    "addr:postcode":"23400",
    "addr:street":"Calle De Fuente De Las Risas;Jae\u0301N",
    "iso:country":"ES",
    "sg:address":"Calle de Fuente De Las Risas, 7",
    "sg:city":"Ubeda",
    "sg:orig_category":"Productores Recolectores, Venta Directa De Vinos",
    "sg:phone":"+34 953 79 27 83",
    "sg:postcode":"23400",
    "sg:province":"Ja\u00e9n",
    "wof:name":"Hermanos Poveda Gomez C.b.",
    "wof:placetype":"venue"
},
  "geometry": {"coordinates":[-3.3747854233,38.0100479126],"type":"Point"}
}