{
  "type": "Feature",
  "properties": {
    "addr:full":"Calle de Montalban, 9 Granada Granada 18002",
    "addr:housenumber":"9",
    "addr:postcode":"18002",
    "addr:street":"Calle De Montalban",
    "iso:country":"ES",
    "sg:address":"Calle de Montalban, 9",
    "sg:city":"Granada",
    "sg:orig_category":"Tapicer\u00cdas",
    "sg:phone":"+34 958 27 93 88",
    "sg:postcode":"18002",
    "sg:province":"Granada",
    "wof:name":"Ruiz-coello Luna Manuel",
    "wof:placetype":"venue"
},
  "geometry": {"coordinates":[-3.6040539742,37.1767921448],"type":"Point"}
}