{
  "type": "Feature",
  "properties": {
    "addr:full":"Calle de Juan De La Cierva, 9 Leganes Madrid 28914",
    "addr:housenumber":"9",
    "addr:postcode":"28914",
    "addr:street":"Calle De Juan De La Cierva",
    "iso:country":"ES",
    "sg:address":"Calle de Juan De La Cierva, 9",
    "sg:city":"Leganes",
    "sg:orig_category":"Chapister\u00cda",
    "sg:phone":"+34 916 80 93 95",
    "sg:postcode":"28914",
    "sg:province":"Madrid",
    "wof:name":"Martin Gascue\u00f1a Valentin",
    "wof:placetype":"venue"
},
  "geometry": {"coordinates":[-3.8456571102,40.3159370422],"type":"Point"}
}