{
  "type": "Feature",
  "properties": {
    "addr:full":"Calle de Reja De La Capilla, 9 Jaen Ja\u00e9n 23001",
    "addr:housenumber":"9;jae\u0301n",
    "addr:postcode":"23001",
    "addr:street":"Calle De Reja De La Capilla",
    "iso:country":"ES",
    "sg:address":"Calle de Reja De La Capilla, 9",
    "sg:city":"Jaen",
    "sg:orig_category":"Bares, Piano",
    "sg:phone":"+34 953 24 00 14",
    "sg:postcode":"23001",
    "sg:province":"Ja\u00e9n",
    "wof:name":"Hermanos Martinez De La Casa, C.b.",
    "wof:placetype":"venue"
},
  "geometry": {"coordinates":[-3.7862839699,37.7668075562],"type":"Point"}
}