{
  "type": "Feature",
  "properties": {
    "addr:full":"Plaz Coca De La Pi\u00d1era, 8 Jaen Ja\u00e9n 23001",
    "addr:housenumber":"8;jae\u0301n",
    "addr:postcode":"23001",
    "addr:street":"Pin\u0303Era",
    "iso:country":"ES",
    "sg:address":"Plaz Coca De La Pi\u00d1era, 8",
    "sg:city":"Jaen",
    "sg:orig_category":"Elementos Para Suelos Prefabricados",
    "sg:phone":"+34 953 27 38 06",
    "sg:postcode":"23001",
    "sg:province":"Ja\u00e9n",
    "wof:name":"Lopez Barroso Manuel",
    "wof:placetype":"venue"
},
  "geometry": {"coordinates":[-3.7873268127,37.7660217285],"type":"Point"}
}