{
  "type": "Feature",
  "properties": {
    "addr:full":"Avda Galicia, 10 Vegadeo Asturias 33770",
    "addr:housenumber":"10",
    "addr:postcode":"33770",
    "addr:street":"Avda Galicia",
    "iso:country":"ES",
    "sg:address":"Avda Galicia, 10",
    "sg:city":"Vegadeo",
    "sg:orig_category":"Parafarmacias",
    "sg:phone":"+34 985 47 65 80",
    "sg:postcode":"33770",
    "sg:province":"Asturias",
    "wof:name":"Garcia Garcia Matilde",
    "wof:placetype":"venue"
},
  "geometry": {"coordinates":[-7.0533261299,43.4646911621],"type":"Point"}
}