{
  "type": "Feature",
  "properties": {
    "addr:full":"Avda Colon, 6 San Antonio Abad Murcia 30205",
    "addr:housenumber":"6",
    "addr:postcode":"30205",
    "addr:street":"Avda Colon",
    "iso:country":"ES",
    "sg:address":"Avda Colon, 6",
    "sg:city":"San Antonio Abad",
    "sg:orig_category":"Comercio De Piezas De Recambio Y De Accesorios De Veh\u00cdculos, Veh\u00cdculos Industriales",
    "sg:phone":"+34 968 51 27 59",
    "sg:postcode":"30205",
    "sg:province":"Murcia",
    "wof:name":"Garcia Perez Ramon",
    "wof:placetype":"venue"
},
  "geometry": {"coordinates":[-0.9954255819,37.6156425476],"type":"Point"}
}