{
  "type": "Feature",
  "properties": {
    "addr:full":"Calle de Porto Cristo, 2 Alcorcon Madrid 28924",
    "addr:housenumber":"2",
    "addr:postcode":"28924",
    "addr:street":"Calle De Porto Cristo",
    "iso:country":"ES",
    "sg:address":"Calle de Porto Cristo, 2",
    "sg:city":"Alcorcon",
    "sg:orig_category":"Tiendas De Grano, Frutas Y Legumbres Secas (al Por Menor)",
    "sg:phone":"+34 916 11 59 52",
    "sg:postcode":"28924",
    "sg:province":"Madrid",
    "wof:name":"Barrientos Seivane Lorenzo",
    "wof:placetype":"venue"
},
  "geometry": {"coordinates":[-3.8199989796,40.3525123596],"type":"Point"}
}