{
  "type": "Feature",
  "properties": {
    "addr:full":"Carr Segarra (de La), S/n Agramunt Lleida 25310",
    "addr:housenumber":"/ n",
    "addr:postcode":"25310",
    "addr:street":"Carr Segarra De La S",
    "iso:country":"ES",
    "sg:address":"Carr Segarra (de La), S/n",
    "sg:city":"Agramunt",
    "sg:orig_category":"Empresas De Carpinter\u00cda De Madera",
    "sg:phone":"+34 973 39 23 89",
    "sg:postcode":"25310",
    "sg:province":"Lleida",
    "wof:name":"Decoracio Lleron S.l.",
    "wof:placetype":"venue"
},
  "geometry": {"coordinates":[1.1053999662,41.7810058594],"type":"Point"}
}