{
  "type": "Feature",
  "properties": {
    "addr:full":"Carrer de Barcelona (de), 49 Salou Tarragona 43840",
    "addr:housenumber":"49",
    "addr:postcode":"43840",
    "addr:street":"Carrer De Barcelona De",
    "iso:country":"ES",
    "sg:address":"Carrer de Barcelona (de), 49",
    "sg:city":"Salou",
    "sg:orig_category":"Inmobiliaria (agencias)",
    "sg:phone":"+34 977 38 34 24",
    "sg:postcode":"43840",
    "sg:province":"Tarragona",
    "wof:name":"Fincas J.i. S.l.",
    "wof:placetype":"venue"
},
  "geometry": {"coordinates":[1.1308000088,41.0800132751],"type":"Point"}
}