{
  "type": "Feature",
  "properties": {
    "iso:country":"ES",
    "sg:address":"Rua Noria, 21",
    "sg:city":"Reboredo",
    "sg:orig_category":"Ropa Para Se\u00d1oras Y Caballeros (al Por Menor)",
    "sg:phone":"+34 986 30 54 86",
    "sg:postcode":"36940",
    "sg:province":"Pontevedra",
    "wof:name":"Rodrigues Santos Helen",
    "wof:placetype":"venue"
},
  "geometry": {"coordinates":[-8.8184690475,42.2741928101],"type":"Point"}
}