{
  "type": "Feature",
  "properties": {
    "addr:full":"Calle de Abajo, 6 Alconchel De La Estrella Cuenca 16433",
    "addr:housenumber":"6",
    "addr:postcode":"16433",
    "addr:street":"Calle De Abajo",
    "iso:country":"ES",
    "sg:address":"Calle de Abajo, 6",
    "sg:city":"Alconchel De La Estrella",
    "sg:orig_category":"Agricultura: Abastecimiento Y Cosechado (negocio)",
    "sg:phone":"+34 969 19 80 70",
    "sg:postcode":"16433",
    "sg:province":"Cuenca",
    "wof:name":"Comunidad De Bienes Alconchel",
    "wof:placetype":"venue"
},
  "geometry": {"coordinates":[-2.5750501156,39.718421936],"type":"Point"}
}