{
  "type": "Feature",
  "properties": {
    "addr:full":"Avda Cid Campeador, 10 Burgos Burgos 09005",
    "addr:housenumber":"10",
    "addr:postcode":"09005",
    "addr:street":"Avda Cid Campeador",
    "iso:country":"ES",
    "sg:address":"Avda Cid Campeador, 10",
    "sg:city":"Burgos",
    "sg:orig_category":"Panader\u00cdas, Panader\u00cdas",
    "sg:phone":"+34 947 20 66 23",
    "sg:postcode":"09005",
    "sg:province":"Burgos",
    "wof:name":"Dieste Iba\u00f1ez Ricarda",
    "wof:placetype":"venue"
},
  "geometry": {"coordinates":[-3.6980009079,42.3451805115],"type":"Point"}
}