{
  "type": "Feature",
  "properties": {
    "addr:full":"Carrer de Churruca, 21 Hospitalet Llobregat Barcelona 08906",
    "addr:housenumber":"21",
    "addr:postcode":"08906",
    "addr:street":"Carrer De Churruca",
    "iso:country":"ES",
    "sg:address":"Carrer de Churruca, 21",
    "sg:city":"Hospitalet Llobregat",
    "sg:orig_category":"Plomeros",
    "sg:phone":"+34 934 38 43 09",
    "sg:postcode":"08906",
    "sg:province":"Barcelona",
    "wof:name":"Escola Pellicero Pedro",
    "wof:placetype":"venue"
},
  "geometry": {"coordinates":[2.1012680531,41.3760795593],"type":"Point"}
}