{
  "type": "Feature",
  "properties": {
    "addr:full":"Calle de Federico Garcia Lorca, 7 Burgos Burgos 09007",
    "addr:housenumber":"7",
    "addr:postcode":"09007",
    "addr:street":"Calle De Federico Garcia Lorca",
    "iso:country":"ES",
    "sg:address":"Calle de Federico Garcia Lorca, 7",
    "sg:city":"Burgos",
    "sg:orig_category":"Fabricaci\u00d3n De Enlosados, Soler\u00cdas",
    "sg:phone":"+34 947 48 77 34",
    "sg:postcode":"09007",
    "sg:province":"Burgos",
    "wof:name":"Jose Maria Martin Roy Y Otra S.cv.",
    "wof:placetype":"venue"
},
  "geometry": {"coordinates":[-3.6656138897,42.3501205444],"type":"Point"}
}