{
  "type": "Feature",
  "properties": {
    "addr:full":"Carr Cervantes, 10 Alboraya Valencia 46120",
    "addr:housenumber":"10",
    "addr:postcode":"46120",
    "addr:street":"Carr Cervantes",
    "iso:country":"ES",
    "sg:address":"Carr Cervantes, 10",
    "sg:city":"Alboraya",
    "sg:orig_category":"Alimentaci\u00d3n General (al Por Menor)",
    "sg:phone":"+34 961 85 73 84",
    "sg:postcode":"46120",
    "sg:province":"Valencia",
    "wof:name":"Orts Fonfria Francisca",
    "wof:placetype":"venue"
},
  "geometry": {"coordinates":[-0.3489840031,39.4997596741],"type":"Point"}
}