{
  "type": "Feature",
  "properties": {
    "addr:full":"Calle de San Antonio, 17 Marbella M\u00e1laga 29600",
    "addr:housenumber":"17",
    "addr:postcode":"29600",
    "addr:street":"Calle De San Antonio;Ma\u0301Laga",
    "iso:country":"ES",
    "sg:address":"Calle de San Antonio, 17",
    "sg:city":"Marbella",
    "sg:orig_category":"Electricidad (montaje, Ensamblaje De Componentes)",
    "sg:phone":"+34 952 77 18 39",
    "sg:postcode":"29600",
    "sg:province":"M\u00e1laga",
    "wof:name":"Vida Palomo Miguel",
    "wof:placetype":"venue"
},
  "geometry": {"coordinates":[-4.8819179535,36.5126228333],"type":"Point"}
}