{
  "type": "Feature",
  "properties": {
    "iso:country":"ES",
    "sg:address":"Avda Pilar (del), 3",
    "sg:city":"Calahorra",
    "sg:orig_category":"Notarios",
    "sg:phone":"+34 941 13 07 38",
    "sg:postcode":"26500",
    "sg:province":"La Rioja",
    "wof:name":"Cabaero Navarro Diego Pablo",
    "wof:placetype":"venue"
},
  "geometry": {"coordinates":[-1.9654829502,42.3048248291],"type":"Point"}
}