{
  "type": "Feature",
  "properties": {
    "addr:full":"Calle de Esca\u00d1o, 31 Getafe Madrid 28902",
    "addr:housenumber":"31",
    "addr:postcode":"28902",
    "addr:street":"Calle De Escan\u0303O",
    "iso:country":"ES",
    "sg:address":"Calle de Esca\u00d1o, 31",
    "sg:city":"Getafe",
    "sg:orig_category":"Aparcamientos (infraestructuras, Accesorios)",
    "sg:phone":"+34 916 95 54 24",
    "sg:postcode":"28902",
    "sg:province":"Madrid",
    "wof:name":"Benavente Serrano Hermanas C.b.",
    "wof:placetype":"venue"
},
  "geometry": {"coordinates":[-3.727093935,40.30727005],"type":"Point"}
}