{
  "type": "Feature",
  "properties": {
    "addr:full":"Ctra Alicante, 41 Elche Alicante 03202",
    "addr:housenumber":"41",
    "addr:postcode":"03202",
    "addr:street":"Ctra Alicante",
    "iso:country":"ES",
    "sg:address":"Ctra Alicante, 41",
    "sg:city":"Elche",
    "sg:orig_category":"Quincaller\u00cda (al Por Menor)",
    "sg:phone":"+34 965 45 48 61",
    "sg:postcode":"03202",
    "sg:province":"Alicante",
    "wof:name":"Fernandez Garrido Mariano",
    "wof:placetype":"venue"
},
  "geometry": {"coordinates":[-0.672706008,38.2721786499],"type":"Point"}
}