{
  "type": "Feature",
  "properties": {
    "iso:country":"ES",
    "sg:address":"Trva Orense, S/n",
    "sg:city":"Astillero",
    "sg:orig_category":"Librer\u00cdas",
    "sg:phone":"+34 942 55 98 39",
    "sg:postcode":"39610",
    "sg:province":"Cantabria",
    "wof:name":"Cavada Diez Antonio",
    "wof:placetype":"venue"
},
  "geometry": {"coordinates":[-3.8205389977,43.3996810913],"type":"Point"}
}