{
  "type": "Feature",
  "properties": {
    "iso:country":"ES",
    "sg:address":"Calle de Chopos, 15",
    "sg:city":"Majadahonda",
    "sg:orig_category":"Aceites Y Grasas Alimentarias (fabricaci\u00d3n, Al Por Mayor)",
    "sg:phone":"+34 916 38 21 59",
    "sg:postcode":"28220",
    "sg:province":"Madrid",
    "wof:name":"Olivarera Santa Ana S.l.",
    "wof:placetype":"venue"
},
  "geometry": {"coordinates":[-3.8567419052,40.4717712402],"type":"Point"}
}