{
  "type": "Feature",
  "properties": {
    "addr:full":"Av Pi I Margall, 5 Caldes Montbui Barcelona 08140",
    "addr:housenumber":"5",
    "addr:postcode":"08140",
    "addr:street":"Av Pi I Margall;Montbui Barcelona",
    "iso:country":"ES",
    "sg:address":"Av Pi I Margall, 5",
    "sg:city":"Caldes Montbui",
    "sg:orig_category":"Cajas De Ahorro",
    "sg:phone":"+34 938 65 49 48",
    "sg:postcode":"08140",
    "sg:province":"Barcelona",
    "wof:name":"Caixa D'estalvis Del Penedes",
    "wof:placetype":"venue"
},
  "geometry": {"coordinates":[2.1686599255,41.631111145],"type":"Point"}
}