{
  "type": "Feature",
  "properties": {
    "iso:country":"ES",
    "sg:address":"Av Pais Valenciano, 71",
    "sg:city":"Guardamar Segura",
    "sg:orig_category":"Peluqueros: De Se\u00d1oras",
    "sg:phone":"+34 965 72 86 23",
    "sg:postcode":"03140",
    "sg:province":"Alicante",
    "wof:name":"Carbonell Perez Rosario",
    "wof:placetype":"venue"
},
  "geometry": {"coordinates":[-0.6540589929,38.0861701965],"type":"Point"}
}