{
  "type": "Feature",
  "properties": {
    "addr:full":"Plaz Marques Del Vado Del Maestre, 1 Malaga M\u00e1laga 29008",
    "addr:housenumber":"1",
    "addr:postcode":"29008",
    "addr:street":"Marques Del Vado Del Maestre;Ma\u0301Laga",
    "iso:country":"ES",
    "sg:address":"Plaz Marques Del Vado Del Maestre, 1",
    "sg:city":"Malaga",
    "sg:orig_category":"Agencias Y Asesores De Publicidad",
    "sg:phone":"+34 952 60 32 50",
    "sg:postcode":"29008",
    "sg:province":"M\u00e1laga",
    "wof:name":"Tyskland Und Hammer S.l.",
    "wof:placetype":"venue"
},
  "geometry": {"coordinates":[-4.4210338593,36.7223892212],"type":"Point"}
}