{
  "type": "Feature",
  "properties": {
    "iso:country":"ES",
    "sg:address":"Calle de Gravina, 17",
    "sg:city":"Chiclana De La Frontera",
    "sg:orig_category":"Alimentaci\u00d3n General (al Por Menor)",
    "sg:phone":"+34 956 40 01 58",
    "sg:postcode":"11130",
    "sg:province":"C\u00e1diz",
    "wof:name":"Mu\u00f1oz Romero Blas",
    "wof:placetype":"venue"
},
  "geometry": {"coordinates":[-6.1478791237,36.4178085327],"type":"Point"}
}