{
  "type": "Feature",
  "properties": {
    "iso:country":"ES",
    "sg:address":"N Copernico (p I Ca\u00f1amo Ii), 8",
    "sg:city":"San Jose Rinconada",
    "sg:orig_category":"Empresas De Carpinter\u00cda Met\u00c1lica",
    "sg:phone":"+34 955 79 14 53",
    "sg:postcode":"41300",
    "sg:province":"Sevilla",
    "wof:name":"Carpinteria Metalica Rodma S.l.",
    "wof:placetype":"venue"
},
  "geometry": {"coordinates":[-5.9507889748,37.4823112488],"type":"Point"}
}