{
  "type": "Feature",
  "properties": {
    "iso:country":"ES",
    "sg:address":"Av El Textil, 19",
    "sg:city":"Ontinyent",
    "sg:orig_category":"Maquinaria Para Industrias Diversas",
    "sg:phone":"+34 962 38 36 61",
    "sg:postcode":"46870",
    "sg:province":"Valencia",
    "sg:website":"www.tacome.com",
    "wof:name":"Tacome S. A.",
    "wof:placetype":"venue"
},
  "geometry": {"coordinates":[-0.6007180214,38.8258705139],"type":"Point"}
}