{
  "type": "Feature",
  "properties": {
    "iso:country":"ES",
    "sg:address":"Avda Cesareo Alierta, 95",
    "sg:city":"Zaragoza",
    "sg:orig_category":"Centros Empresariales",
    "sg:phone":"+34 976 41 18 02",
    "sg:postcode":"50008",
    "sg:province":"Zaragoza",
    "wof:name":"Perez Argiles Justo",
    "wof:placetype":"venue"
},
  "geometry": {"coordinates":[-0.8699579835,41.638759613],"type":"Point"}
}