{
  "type": "Feature",
  "properties": {
    "iso:country":"ES",
    "sg:address":"Na Llambies, 41",
    "sg:city":"Cala Millor",
    "sg:orig_category":"Residencias De Turismo, Residencias Hoteleras",
    "sg:phone":"+34 971 58 58 05",
    "sg:postcode":"07560",
    "sg:province":"Islas Baleares",
    "wof:name":"Marins Playa S. A.",
    "wof:placetype":"venue"
},
  "geometry": {"coordinates":[3.3887150288,39.6077690125],"type":"Point"}
}