{
  "type": "Feature",
  "properties": {
    "addr:full":"El Corro, 1 S. Cebrian Campos Palencia 34429",
    "addr:housenumber":"1",
    "addr:postcode":"34429",
    "addr:street":"El Corro;S. Cebrian Campos",
    "iso:country":"ES",
    "sg:address":"El Corro, 1",
    "sg:city":"S. Cebrian Campos",
    "sg:orig_category":"Cajas Para Embalar",
    "sg:phone":"+34 979 15 42 00",
    "sg:postcode":"34429",
    "sg:province":"Palencia",
    "wof:name":"Caja Rural Del Duero",
    "wof:placetype":"venue"
},
  "geometry": {"coordinates":[-4.570289135,42.2054786682],"type":"Point"}
}