{
  "type": "Feature",
  "properties": {
    "iso:country":"ES",
    "sg:address":"Avda Pirineos (de Los), 7",
    "sg:city":"San Sebastian De Los Reyes",
    "sg:orig_category":"Servicio De Salud",
    "sg:phone":"+34 916 54 77 92",
    "sg:postcode":"28700",
    "sg:province":"Madrid",
    "wof:name":"Fontanerias Hernandez S.l.",
    "wof:placetype":"venue"
},
  "geometry": {"coordinates":[-3.6103610992,40.5487136841],"type":"Point"}
}