{
  "type": "Feature",
  "properties": {
    "iso:country":"ES",
    "sg:address":"Avda Jesus Santos Rein, 4",
    "sg:city":"Fuengirola",
    "sg:orig_category":"M\u00c9dicos: Estomatolog\u00cda",
    "sg:phone":"+34 952 46 26 53",
    "sg:postcode":"29640",
    "sg:province":"M\u00e1laga",
    "wof:name":"Saavedra Vargas Aileen Mayito",
    "wof:placetype":"venue"
},
  "geometry": {"coordinates":[-4.6186008453,36.5496711731],"type":"Point"}
}