{
  "type": "Feature",
  "properties": {
    "addr:full":"Avda Paz (la), 28 Torredonjimeno Ja\u00e9n 23650",
    "addr:housenumber":"28",
    "addr:postcode":"23650",
    "addr:street":"Avda Paz La",
    "iso:country":"ES",
    "sg:address":"Avda Paz (la), 28",
    "sg:city":"Torredonjimeno",
    "sg:orig_category":"Electrodom\u00c9sticos (al Por Menor)",
    "sg:phone":"+34 953 34 01 31",
    "sg:postcode":"23650",
    "sg:province":"Ja\u00e9n",
    "wof:name":"Damas Arjona Manuel",
    "wof:placetype":"venue"
},
  "geometry": {"coordinates":[-3.9543919563,37.7662582397],"type":"Point"}
}