{
  "type": "Feature",
  "properties": {
    "addr:full":"Hondartza Kalea, 10 Deba Guip\u00f9zcoa 20820",
    "addr:housenumber":"10",
    "addr:postcode":"20820",
    "addr:street":"Hondartza Kalea;Guipu\u0300Zcoa",
    "iso:country":"ES",
    "sg:address":"Hondartza Kalea, 10",
    "sg:city":"Deba",
    "sg:orig_category":"Plomeros",
    "sg:phone":"+34 943 19 17 74",
    "sg:postcode":"20820",
    "sg:province":"Guip\u00f9zcoa",
    "wof:name":"Mikel Arakistain Ega\u00f1a",
    "wof:placetype":"venue"
},
  "geometry": {"coordinates":[-2.3532559872,43.2956504822],"type":"Point"}
}