{
  "type": "Feature",
  "properties": {
    "iso:country":"ES",
    "sg:address":"Carrer de Lluis Creus, 2",
    "sg:city":"Sabadell",
    "sg:orig_category":"Molduras, Junquillos, Listones Y Molduras Perforadas",
    "sg:phone":"+34 937 11 90 51",
    "sg:postcode":"08204",
    "sg:province":"Barcelona",
    "wof:name":"Casimiro Lopez Bueno S.l.",
    "wof:placetype":"venue"
},
  "geometry": {"coordinates":[2.1100718975,41.5291137695],"type":"Point"}
}