{
  "type": "Feature",
  "properties": {
    "addr:full":"Calle de Nicolas De La Fuente, 19 Barco De Avila \u00c1vila 05600",
    "addr:housenumber":"19",
    "addr:postcode":"05600",
    "addr:street":"Calle De Nicolas De La Fuente;A\u0301Vila",
    "iso:country":"ES",
    "sg:address":"Calle de Nicolas De La Fuente, 19",
    "sg:city":"Barco De Avila",
    "sg:orig_category":"Molduras, Junquillos, Listones Y Molduras Perforadas",
    "sg:phone":"+34 920 34 13 02",
    "sg:postcode":"05600",
    "sg:province":"\u00c1vila",
    "wof:name":"Trujillano Hernandez Fernando",
    "wof:placetype":"venue"
},
  "geometry": {"coordinates":[-5.5218648911,40.3584060669],"type":"Point"}
}