{
  "type": "Feature",
  "properties": {
    "iso:country":"ES",
    "sg:address":"Carrer de Panyo, 16",
    "sg:city":"Olot",
    "sg:orig_category":"M\u00c9dicos: An\u00c1lisis Cl\u00cdnicos",
    "sg:phone":"+34 972 26 62 77",
    "sg:postcode":"17800",
    "sg:province":"Girona",
    "wof:name":"Roqueta-esteve-rimbau S.l.",
    "wof:placetype":"venue"
},
  "geometry": {"coordinates":[2.4862771034,42.1797142029],"type":"Point"}
}