{
  "type": "Feature",
  "properties": {
    "addr:full":"Urb Nuevo Versalles, S/n Loranca Madrid 28942",
    "addr:housenumber":"s / n",
    "addr:postcode":"28942",
    "addr:street":"Urb Nuevo Versalles",
    "iso:country":"ES",
    "sg:address":"Urb Nuevo Versalles, S/n",
    "sg:city":"Loranca",
    "sg:orig_category":"Quincaller\u00cda (al Por Menor)",
    "sg:phone":"+34 916 04 69 67",
    "sg:postcode":"28942",
    "sg:province":"Madrid",
    "wof:name":"Aguado Garcia Angel",
    "wof:placetype":"venue"
},
  "geometry": {"coordinates":[-3.8354070187,40.3032112122],"type":"Point"}
}