{
  "type": "Feature",
  "properties": {
    "iso:country":"ES",
    "sg:address":"Calle de Salvador Allende, 46",
    "sg:city":"Torremolinos",
    "sg:orig_category":"Molduras, Junquillos, Listones Y Molduras Perforadas",
    "sg:phone":"+34 952 05 43 85",
    "sg:postcode":"29620",
    "sg:province":"M\u00e1laga",
    "wof:name":"Aljawara 29 S.l.",
    "wof:placetype":"venue"
},
  "geometry": {"coordinates":[-4.5095825195,36.6033058167],"type":"Point"}
}