{
  "type": "Feature",
  "properties": {
    "iso:country":"ES",
    "sg:address":"Altzola Kalea, 5",
    "sg:city":"Zarautz",
    "sg:orig_category":"Venta, Instalaci\u00d3n, Reparaci\u00d3n De Antenas Para Televisi\u00d3n",
    "sg:phone":"+34 943 13 28 03",
    "sg:postcode":"20800",
    "sg:province":"Guip\u00f9zcoa",
    "wof:name":"Miguel Canseco Trejo",
    "wof:placetype":"venue"
},
  "geometry": {"coordinates":[-2.1724720001,43.2822570801],"type":"Point"}
}