{
  "type": "Feature",
  "properties": {
    "iso:country":"ES",
    "sg:address":"Calle de Manzanera (la), 27",
    "sg:city":"Logro\u00f1o",
    "sg:orig_category":"Muebles Y Accesorios Para Cocinas Y Cuartos De Ba\u00d1o (al Por Menor)",
    "sg:phone":"+34 941 23 33 76",
    "sg:postcode":"26004",
    "sg:province":"La Rioja",
    "wof:name":"Santamaria Arina Manuel Jacinto",
    "wof:placetype":"venue"
},
  "geometry": {"coordinates":[-2.433975935,42.4688491821],"type":"Point"}
}