{
  "type": "Feature",
  "properties": {
    "addr:full":"Carrer de Emporda, S/n Santa Perpetua De Mogoda Barcelona 08130",
    "addr:housenumber":"s / n",
    "addr:postcode":"08130",
    "addr:street":"Carrer De Emporda",
    "iso:country":"ES",
    "sg:address":"Carrer de Emporda, S/n",
    "sg:city":"Santa Perpetua De Mogoda",
    "sg:orig_category":"Entrega Y Recogida (servicios)",
    "sg:phone":"+34 935 60 70 08",
    "sg:postcode":"08130",
    "sg:province":"Barcelona",
    "sg:website":"www.desmon.com",
    "wof:name":"Irme S. A.",
    "wof:placetype":"venue"
},
  "geometry": {"coordinates":[2.1802799702,41.5371818542],"type":"Point"}
}