{
  "type": "Feature",
  "properties": {
    "iso:country":"ES",
    "sg:address":"Rond Alarcos, 26",
    "sg:city":"Ciudad Real",
    "sg:orig_category":"Plomeros",
    "sg:phone":"+34 926 21 40 29",
    "sg:postcode":"13002",
    "sg:province":"Ciudad Real",
    "wof:name":"Loro Torres Jesus",
    "wof:placetype":"venue"
},
  "geometry": {"coordinates":[-3.9321250916,38.9821166992],"type":"Point"}
}