{
  "type": "Feature",
  "properties": {
    "addr:full":"Rua Venezuela, 52 Ferrol La Coru\u00f1a 15404",
    "addr:housenumber":"52",
    "addr:postcode":"15404",
    "addr:street":"Rua Venezuela;La Corun\u0303A",
    "iso:country":"ES",
    "sg:address":"Rua Venezuela, 52",
    "sg:city":"Ferrol",
    "sg:orig_category":"Venta, Montaje De Neum\u00c1ticos",
    "sg:phone":"+34 981 32 36 82",
    "sg:postcode":"15404",
    "sg:province":"La Coru\u00f1a",
    "wof:name":"Neumaticos Ultramar S.l.",
    "wof:placetype":"venue"
},
  "geometry": {"coordinates":[-8.2191362381,43.4890022278],"type":"Point"}
}