{
  "type": "Feature",
  "properties": {
    "iso:country":"ES",
    "sg:address":"Calle de Juan De Lepe, 7",
    "sg:city":"Lepe",
    "sg:orig_category":"Estancos",
    "sg:phone":"+34 959 38 04 96",
    "sg:postcode":"21440",
    "sg:province":"Huelva",
    "wof:name":"Verano Infante Maria Victoria",
    "wof:placetype":"venue"
},
  "geometry": {"coordinates":[-7.2037420273,37.2538337708],"type":"Point"}
}