{
  "type": "Feature",
  "properties": {
    "iso:country":"ES",
    "sg:address":"Calle de Martin Fernandez Villaran, 6",
    "sg:city":"Portugalete",
    "sg:orig_category":"Tintes (fabricaci\u00d3n, Al Por Mayor)",
    "sg:phone":"+34 944 62 12 87",
    "sg:postcode":"48920",
    "sg:province":"Vizcaya",
    "wof:name":"Nu\u00f1ez Barranco Maria",
    "wof:placetype":"venue"
},
  "geometry": {"coordinates":[-3.0200428963,43.322555542],"type":"Point"}
}