{
  "type": "Feature",
  "properties": {
    "addr:full":"Calle de Pozo Nuevo, 4 S. Juan Puerto Huelva 21610",
    "addr:housenumber":"4",
    "addr:postcode":"21610",
    "addr:street":"Calle De Pozo Nuevo;S. Juan Puerto",
    "iso:country":"ES",
    "sg:address":"Calle de Pozo Nuevo, 4",
    "sg:city":"S. Juan Puerto",
    "sg:orig_category":"Reposter\u00cdas",
    "sg:phone":"+34 959 36 72 25",
    "sg:postcode":"21610",
    "sg:province":"Huelva",
    "wof:name":"Hermanos Aquino Santiago S.l.",
    "wof:placetype":"venue"
},
  "geometry": {"coordinates":[-6.8419079781,37.3152236938],"type":"Point"}
}