{
  "type": "Feature",
  "properties": {
    "iso:country":"ES",
    "sg:address":"Calle de Italia, 4",
    "sg:city":"Alacant",
    "sg:orig_category":"Vinos Y Licores (venta Al Por Menor)",
    "sg:phone":"+34 965 92 17 38",
    "sg:postcode":"03003",
    "sg:province":"Alicante",
    "sg:website":"www.bodegaseleccion.com",
    "wof:name":"Vinos Calderon S.l.u.",
    "wof:placetype":"venue"
},
  "geometry": {"coordinates":[-0.4884459972,38.3417930603],"type":"Point"}
}