{
  "type": "Feature",
  "properties": {
    "addr:full":"Pol. La Casaza, 22 Utebo Zaragoza 50180",
    "addr:housenumber":"22",
    "addr:postcode":"50180",
    "addr:street":"Pol. La Casaza",
    "iso:country":"ES",
    "sg:address":"Pol. La Casaza, 22",
    "sg:city":"Utebo",
    "sg:orig_category":"Chapister\u00cda",
    "sg:phone":"+34 976 77 28 01",
    "sg:postcode":"50180",
    "sg:province":"Zaragoza",
    "wof:name":"Alfonso Navarro S.l.",
    "wof:placetype":"venue"
},
  "geometry": {"coordinates":[-0.9964085221,41.7115402222],"type":"Point"}
}