{
  "type": "Feature",
  "properties": {
    "addr:full":"Plaz Espa\u00d1a, 1 Calamocha Teruel 44200",
    "addr:housenumber":"1",
    "addr:postcode":"44200",
    "addr:street":"Plaz Espan\u0303A",
    "iso:country":"ES",
    "sg:address":"Plaz Espa\u00d1a, 1",
    "sg:city":"Calamocha",
    "sg:orig_category":"Administraciones Regionales, Departamentales Y Locales",
    "sg:phone":"+34 978 73 00 50",
    "sg:postcode":"44200",
    "sg:province":"Teruel",
    "wof:name":"Ayuntamiento",
    "wof:placetype":"venue"
},
  "geometry": {"coordinates":[-1.2969770432,40.9207839966],"type":"Point"}
}