{
  "type": "Feature",
  "properties": {
    "iso:country":"ES",
    "sg:address":"Avda Espina (la), 72",
    "sg:city":"Matarrosa Sil",
    "sg:orig_category":"Electrodom\u00c9sticos (al Por Menor)",
    "sg:phone":"+34 987 52 50 30",
    "sg:postcode":"24460",
    "sg:province":"Le\u00f3n",
    "wof:name":"Garcia Quiroga Vanessa",
    "wof:placetype":"venue"
},
  "geometry": {"coordinates":[-6.5295147896,42.7595825195],"type":"Point"}
}