{
  "type": "Feature",
  "properties": {
    "iso:country":"ES",
    "sg:address":"Calle de Nogal, 28",
    "sg:city":"Sevilla",
    "sg:orig_category":"Estancos",
    "sg:phone":"+34 954 40 88 56",
    "sg:postcode":"41017",
    "sg:province":"Sevilla",
    "wof:name":"Dominguez Navarro Encarnacion",
    "wof:placetype":"venue"
},
  "geometry": {"coordinates":[-5.9002771378,37.3832702637],"type":"Point"}
}