{
  "type": "Feature",
  "properties": {
    "addr:full":"Ctra. Puigpunyent, Km. 0002,0 Esporles Islas Baleares 07190",
    "addr:postcode":"07190",
    "addr:street":"Ctra. Puigpunyent Km. 0002,0",
    "iso:country":"ES",
    "sg:address":"Ctra. Puigpunyent, Km. 0002,0",
    "sg:city":"Esporles",
    "sg:orig_category":"Internados & Ense\u00d1anza Privada",
    "sg:phone":"+34 971 61 08 77",
    "sg:postcode":"07190",
    "sg:province":"Islas Baleares",
    "wof:name":"Padres Teatinos",
    "wof:placetype":"venue"
},
  "geometry": {"coordinates":[2.5819399357,39.6634292603],"type":"Point"}
}