{
  "type": "Feature",
  "properties": {
    "addr:full":"Avda Primero De Julio, 46 Valdepe\u00f1as Ciudad Real 13300",
    "addr:housenumber":"46",
    "addr:postcode":"13300",
    "addr:street":"Avda Primero De Julio",
    "iso:country":"ES",
    "sg:address":"Avda Primero De Julio, 46",
    "sg:city":"Valdepe\u00f1as",
    "sg:orig_category":"Organizaciones Internacionales",
    "sg:phone":"+34 926 32 49 35",
    "sg:postcode":"13300",
    "sg:province":"Ciudad Real",
    "wof:name":"Pueblos Sin Fronteras",
    "wof:placetype":"venue"
},
  "geometry": {"coordinates":[-3.3924539089,38.7558097839],"type":"Point"}
}