{
  "type": "Feature",
  "properties": {
    "addr:full":"Carr Pep Ventura, 7 Figueres Girona 17600",
    "addr:housenumber":"7",
    "addr:postcode":"17600",
    "addr:street":"Carr Pep Ventura",
    "iso:country":"ES",
    "sg:address":"Carr Pep Ventura, 7",
    "sg:city":"Figueres",
    "sg:orig_category":"Inform\u00c1tica (estudios, Servicios, Asesor\u00cda, Formaci\u00d3n)",
    "sg:phone":"+34 972 67 33 67",
    "sg:postcode":"17600",
    "sg:province":"Girona",
    "wof:name":"Innova Estudi Soft S.l.",
    "wof:placetype":"venue"
},
  "geometry": {"coordinates":[2.959184885,42.2667541504],"type":"Point"}
}