{
  "type": "Feature",
  "properties": {
    "addr:full":"Av Constitucio, 4 Xixona Alicante 03100",
    "addr:housenumber":"4",
    "addr:postcode":"03100",
    "addr:street":"Av Constitucio",
    "iso:country":"ES",
    "sg:address":"Av Constitucio, 4",
    "sg:city":"Xixona",
    "sg:orig_category":"Estancos",
    "sg:phone":"+34 965 61 01 22",
    "sg:postcode":"03100",
    "sg:province":"Alicante",
    "wof:name":"Sirvent Garcia Rafael",
    "wof:placetype":"venue"
},
  "geometry": {"coordinates":[-0.5072979927,38.5392684937],"type":"Point"}
}