{
  "type": "Feature",
  "properties": {
    "addr:full":"Avda Coru\u00d1a (da), 169 Lugo Lugo 27003",
    "addr:housenumber":"169",
    "addr:postcode":"27003",
    "addr:street":"Avda Corun\u0303A Da",
    "iso:country":"ES",
    "sg:address":"Avda Coru\u00d1a (da), 169",
    "sg:city":"Lugo",
    "sg:orig_category":"Peluqueros: De Se\u00d1oras",
    "sg:phone":"+34 982 20 16 07",
    "sg:postcode":"27003",
    "sg:province":"Lugo",
    "wof:name":"Gomez Lopez Guadalupe",
    "wof:placetype":"venue"
},
  "geometry": {"coordinates":[-7.5628871918,43.0199737549],"type":"Point"}
}