{
  "type": "Feature",
  "properties": {
    "addr:full":"Pla\u00c7 Catalunya, 2 Preixana Lleida 25263",
    "addr:housenumber":"2",
    "addr:postcode":"25263",
    "iso:country":"ES",
    "sg:address":"Pla\u00c7 Catalunya, 2",
    "sg:city":"Preixana",
    "sg:orig_category":"Carnes De Carnicer\u00cda (al Por Mayor)",
    "sg:phone":"+34 973 32 05 58",
    "sg:postcode":"25263",
    "sg:province":"Lleida",
    "wof:name":"Delicies De L'anec S.l.",
    "wof:placetype":"venue"
},
  "geometry": {"coordinates":[1.0368419886,41.607208252],"type":"Point"}
}