{
  "type": "Feature",
  "properties": {
    "addr:full":"Av Tarragona, 185 Vilafranca Penedes Barcelona 08720",
    "addr:housenumber":"185",
    "addr:postcode":"08720",
    "addr:street":"Av Tarragona;Penedes Barcelona",
    "iso:country":"ES",
    "sg:address":"Av Tarragona, 185",
    "sg:city":"Vilafranca Penedes",
    "sg:orig_category":"Pintura, Barniz, Productos Asimilables (fabricaci\u00d3n, Al Por Mayor)",
    "sg:phone":"+34 938 90 46 44",
    "sg:postcode":"08720",
    "sg:province":"Barcelona",
    "wof:name":"Aplicaciones Santisteban S.a.",
    "wof:placetype":"venue"
},
  "geometry": {"coordinates":[1.675080657,41.3283042908],"type":"Point"}
}