{
  "type": "Feature",
  "properties": {
    "iso:country":"ES",
    "sg:address":"Carrer de Balmes, 30",
    "sg:city":"Pineda Mar",
    "sg:orig_category":"Agencias Y Agentes Comerciales, Representantes",
    "sg:phone":"+34 937 62 14 89",
    "sg:postcode":"08397",
    "sg:province":"Barcelona",
    "wof:name":"Nualart Benet Emilia",
    "wof:placetype":"venue"
},
  "geometry": {"coordinates":[2.6877040863,41.6248893738],"type":"Point"}
}