{
  "type": "Feature",
  "properties": {
    "addr:full":"Carrer de Creu Gran, 69 Terrassa Barcelona 08221",
    "addr:housenumber":"69",
    "addr:postcode":"08221",
    "addr:street":"Carrer De Creu Gran",
    "iso:country":"ES",
    "sg:address":"Carrer de Creu Gran, 69",
    "sg:city":"Terrassa",
    "sg:orig_category":"Complementos De Vestir (al Por Menor)",
    "sg:phone":"+34 937 36 09 47",
    "sg:postcode":"08221",
    "sg:province":"Barcelona",
    "wof:name":"Costa Puyal Matilde",
    "wof:placetype":"venue"
},
  "geometry": {"coordinates":[2.016851902,41.5667610168],"type":"Point"}
}