{
  "type": "Feature",
  "properties": {
    "addr:full":"Calle de Antonia Ruiz Soro, 30 Madrid Madrid 28028",
    "addr:housenumber":"30",
    "addr:postcode":"madrid;28028",
    "addr:street":"Calle De Antonia Ruiz Soro",
    "iso:country":"ES",
    "sg:address":"Calle de Antonia Ruiz Soro, 30",
    "sg:city":"Madrid",
    "sg:orig_category":"Estancos",
    "sg:phone":"+34 913 55 94 31",
    "sg:postcode":"28028",
    "sg:province":"Madrid",
    "wof:name":"Ventura Romero Eleuterio",
    "wof:placetype":"venue"
},
  "geometry": {"coordinates":[-3.6648359299,40.4382781982],"type":"Point"}
}