{
  "type": "Feature",
  "properties": {
    "addr:full":"Jimenez Leon, 9 El Viso Alcor Sevilla 41520",
    "addr:housenumber":"9",
    "addr:postcode":"41520",
    "addr:street":"Leon",
    "iso:country":"ES",
    "sg:address":"Jimenez Leon, 9",
    "sg:city":"El Viso Alcor",
    "sg:orig_category":"Mercer\u00cda, Lencer\u00cda (al Por Menor)",
    "sg:phone":"+34 955 94 51 76",
    "sg:postcode":"41520",
    "sg:province":"Sevilla",
    "wof:name":"Roldan Cadena Alfonso",
    "wof:placetype":"venue"
},
  "geometry": {"coordinates":[-5.7233109474,37.3868141174],"type":"Point"}
}