{
  "type": "Feature",
  "properties": {
    "addr:full":"Carrer de Tres Roures, 9 Manresa Barcelona 08242",
    "addr:housenumber":"9",
    "addr:postcode":"08242",
    "addr:street":"Carrer De Tres Roures",
    "iso:country":"ES",
    "sg:address":"Carrer de Tres Roures, 9",
    "sg:city":"Manresa",
    "sg:orig_category":"Ingeniero",
    "sg:phone":"+34 938 75 01 13",
    "sg:postcode":"08242",
    "sg:province":"Barcelona",
    "wof:name":"Vidal Grifull Jaime",
    "wof:placetype":"venue"
},
  "geometry": {"coordinates":[1.8193130493,41.7275733948],"type":"Point"}
}