{
  "type": "Feature",
  "properties": {
    "iso:country":"ES",
    "sg:address":"Rond Sindic Antoni Albuixech, 29",
    "sg:city":"Almussafes",
    "sg:orig_category":"Electromec\u00c1nica",
    "sg:phone":"+34 961 78 31 19",
    "sg:postcode":"46440",
    "sg:province":"Valencia",
    "wof:name":"Electrodelta S.l.",
    "wof:placetype":"venue"
},
  "geometry": {"coordinates":[-0.4110909998,39.2889404297],"type":"Point"}
}