{
  "type": "Feature",
  "properties": {
    "addr:full":"Calle de Sebastian Elcano, 3 Petrer Alicante 03610",
    "addr:housenumber":"3",
    "addr:postcode":"03610",
    "addr:street":"Calle De Sebastian Elcano",
    "iso:country":"ES",
    "sg:address":"Calle de Sebastian Elcano, 3",
    "sg:city":"Petrer",
    "sg:orig_category":"Disfraces",
    "sg:phone":"+34 965 37 43 96",
    "sg:postcode":"03610",
    "sg:province":"Alicante",
    "wof:name":"Reig Iborra Amparo",
    "wof:placetype":"venue"
},
  "geometry": {"coordinates":[-0.786428988,38.480091095],"type":"Point"}
}