{
  "type": "Feature",
  "properties": {
    "addr:full":"Avda Magallanes, 4 Cabezo Santa Cruz De Tenerife 38612",
    "addr:housenumber":"4",
    "addr:postcode":"38612",
    "addr:street":"Avda Magallanes",
    "iso:country":"ES",
    "sg:address":"Avda Magallanes, 4",
    "sg:city":"Cabezo",
    "sg:orig_category":"Inmobiliaria (agencias)",
    "sg:phone":"+34 922 17 67 03",
    "sg:postcode":"38612",
    "sg:province":"Santa Cruz De Tenerife",
    "wof:name":"Medano Holidays S.l.",
    "wof:placetype":"venue"
},
  "geometry": {"coordinates":[-16.5262241364,28.0532035828],"type":"Point"}
}