{
  "type": "Feature",
  "properties": {
    "addr:full":"John F. Kennedy, S/n S. Joan Despi Barcelona 08970",
    "addr:housenumber":"s",
    "addr:postcode":"08970",
    "addr:street":"John F. Kennedy;/ N S. Joan Despi",
    "iso:country":"ES",
    "sg:address":"John F. Kennedy, S/n",
    "sg:city":"S. Joan Despi",
    "sg:orig_category":"Pescader\u00cdas (al Por Menor)",
    "sg:phone":"+34 933 73 89 51",
    "sg:postcode":"08970",
    "sg:province":"Barcelona",
    "wof:name":"Gines Flores C.b.",
    "wof:placetype":"venue"
},
  "geometry": {"coordinates":[2.0746150017,41.3682823181],"type":"Point"}
}