{
  "type": "Feature",
  "properties": {
    "addr:full":"Carrer de Sant Antoni Maria Claret, 57 Barcelona Barcelona 08025",
    "addr:housenumber":"57",
    "addr:postcode":"08025",
    "addr:street":"Carrer De Sant Antoni Maria Claret",
    "iso:country":"ES",
    "sg:address":"Carrer de Sant Antoni Maria Claret, 57",
    "sg:city":"Barcelona",
    "sg:orig_category":"Farmacias",
    "sg:phone":"+34 932 07 18 48",
    "sg:postcode":"08025",
    "sg:province":"Barcelona",
    "wof:name":"Soler Peix Eduardo Maria",
    "wof:placetype":"venue"
},
  "geometry": {"coordinates":[2.1679499149,41.4066123962],"type":"Point"}
}