{
  "type": "Feature",
  "properties": {
    "iso:country":"ES",
    "sg:address":"Calle de Toledo, 34",
    "sg:city":"Getafe",
    "sg:orig_category":"Farmacias",
    "sg:phone":"+34 916 95 08 73",
    "sg:postcode":"28901",
    "sg:province":"Madrid",
    "wof:name":"Pulido Albillo Maria Teresa",
    "wof:placetype":"venue"
},
  "geometry": {"coordinates":[-3.7330150604,40.302947998],"type":"Point"}
}