{
  "type": "Feature",
  "properties": {
    "addr:full":"Dotze (urb Tres Cales), 617 Ametlla Mar Tarragona 43860",
    "addr:housenumber":"617",
    "addr:postcode":"43860",
    "addr:street":"Urb Tres Cales",
    "iso:country":"ES",
    "sg:address":"Dotze (urb Tres Cales), 617",
    "sg:city":"Ametlla Mar",
    "sg:orig_category":"Inmobiliaria (agencias)",
    "sg:phone":"+34 977 49 34 20",
    "sg:postcode":"43860",
    "sg:province":"Tarragona",
    "wof:name":"Promocions Simo I Valiente S.l.",
    "wof:placetype":"venue"
},
  "geometry": {"coordinates":[0.7992730141,40.8853607178],"type":"Point"}
}