{
  "type": "Feature",
  "properties": {
    "addr:full":"Avda Coru\u00d1a (da), 40 Lugo Lugo 27003",
    "addr:housenumber":"40",
    "addr:postcode":"27003",
    "addr:street":"Avda Corun\u0303A Da",
    "iso:country":"ES",
    "sg:address":"Avda Coru\u00d1a (da), 40",
    "sg:city":"Lugo",
    "sg:orig_category":"Importaci\u00d3n, Exportaci\u00d3n Y Comercios De Productos Textiles",
    "sg:phone":"+34 982 23 01 95",
    "sg:postcode":"27003",
    "sg:province":"Lugo",
    "wof:name":"Badiee Badiee Riazollah",
    "wof:placetype":"venue"
},
  "geometry": {"coordinates":[-7.5591278076,43.0158691406],"type":"Point"}
}