{
  "type": "Feature",
  "properties": {
    "iso:country":"ES",
    "sg:address":"Avda Constitucion, 148",
    "sg:city":"S. Andres Rabanedo",
    "sg:orig_category":"Empresas De Carpinter\u00cda",
    "sg:phone":"+34 987 84 01 72",
    "sg:postcode":"24010",
    "sg:province":"Le\u00f3n",
    "wof:name":"Aluminios Alan S.l.l.",
    "wof:placetype":"venue"
},
  "geometry": {"coordinates":[-5.6154623032,42.6041183472],"type":"Point"}
}