{
  "type": "Feature",
  "properties": {
    "iso:country":"ES",
    "sg:address":"C/ Lepant, 11",
    "sg:city":"Grao",
    "sg:orig_category":"Promotores Constructores",
    "sg:phone":"+34 964 58 83 40",
    "sg:postcode":"12593",
    "sg:province":"Castell\u00f3n",
    "wof:name":"Torre Caida S.l.",
    "wof:placetype":"venue"
},
  "geometry": {"coordinates":[-0.1429889947,39.8067741394],"type":"Point"}
}