{
  "type": "Feature",
  "properties": {
    "addr:full":"Calle de San Bernardo, 40 Gijon Asturias 33201",
    "addr:housenumber":"40",
    "addr:postcode":"33201",
    "addr:street":"Calle De San Bernardo",
    "iso:country":"ES",
    "sg:address":"Calle de San Bernardo, 40",
    "sg:city":"Gijon",
    "sg:orig_category":"Zapatos (al Por Menor)",
    "sg:phone":"+34 985 35 81 29",
    "sg:postcode":"33201",
    "sg:province":"Asturias",
    "wof:name":"Suarez Garcia Adelina",
    "wof:placetype":"venue"
},
  "geometry": {"coordinates":[-5.6616210938,43.5420265198],"type":"Point"}
}