{
  "type": "Feature",
  "properties": {
    "iso:country":"ES",
    "sg:address":"Carrer de Antoni Gaudi, 76",
    "sg:city":"S. Boi Llobregat",
    "sg:orig_category":"Molduras, Junquillos, Listones Y Molduras Perforadas",
    "sg:phone":"+34 936 54 35 58",
    "sg:postcode":"08830",
    "sg:province":"Barcelona",
    "wof:name":"La Birreta S.l.",
    "wof:placetype":"venue"
},
  "geometry": {"coordinates":[2.0271539688,41.3485031128],"type":"Point"}
}