{
  "type": "Feature",
  "properties": {
    "addr:full":"Carrer de Alt De Sant Pere, 47 Torredembarra Tarragona 43830",
    "addr:housenumber":"47",
    "addr:postcode":"43830",
    "addr:street":"Carrer De Alt De Sant Pere",
    "iso:country":"ES",
    "sg:address":"Carrer de Alt De Sant Pere, 47",
    "sg:city":"Torredembarra",
    "sg:orig_category":"Sociedades, Compa\u00d1\u00cdas Aseguradoras",
    "sg:phone":"+34 977 64 47 00",
    "sg:postcode":"43830",
    "sg:province":"Tarragona",
    "wof:name":"Vernet Garcia Maria Dolores",
    "wof:placetype":"venue"
},
  "geometry": {"coordinates":[1.4003169537,41.1462097168],"type":"Point"}
}