{
  "type": "Feature",
  "properties": {
    "iso:country":"ES",
    "sg:address":"Carrer de Libra, 34",
    "sg:city":"Terrassa",
    "sg:orig_category":"Art\u00cdculos De Madera (fabricaci\u00d3n Y Al Por Mayor)",
    "sg:phone":"+34 937 85 04 57",
    "sg:postcode":"08228",
    "sg:province":"Barcelona",
    "wof:name":"C.p.f. S.l.",
    "wof:placetype":"venue"
},
  "geometry": {"coordinates":[2.0364499092,41.5409622192],"type":"Point"}
}