{
  "type": "Feature",
  "properties": {
    "addr:full":"Calle de Pe\u00d1a Santa, 7 Madrid Madrid 28034",
    "addr:housenumber":"7",
    "addr:postcode":"madrid;28034",
    "addr:street":"Calle De Pen\u0303A Santa",
    "iso:country":"ES",
    "sg:address":"Calle de Pe\u00d1a Santa, 7",
    "sg:city":"Madrid",
    "sg:orig_category":"Abogados",
    "sg:phone":"+34 917 34 13 14",
    "sg:postcode":"28034",
    "sg:province":"Madrid",
    "wof:name":"Gomez-coronado Godoy Angel",
    "wof:placetype":"venue"
},
  "geometry": {"coordinates":[-3.7054810524,40.4949226379],"type":"Point"}
}