{
  "type": "Feature",
  "properties": {
    "addr:full":"Ctra. Andujar, S/n Villanueva Reina Ja\u00e9n 23730",
    "addr:housenumber":"s",
    "addr:postcode":"23730",
    "addr:street":"Ctra. Andujar;/ N;Jae\u0301N",
    "iso:country":"ES",
    "sg:address":"Ctra. Andujar, S/n",
    "sg:city":"Villanueva Reina",
    "sg:orig_category":"Hoteles",
    "sg:phone":"+34 953 53 73 16",
    "sg:postcode":"23730",
    "sg:province":"Ja\u00e9n",
    "wof:name":"Gomez Gomez Francisco",
    "wof:placetype":"venue"
},
  "geometry": {"coordinates":[-3.9147191048,38.0040740967],"type":"Point"}
}