{
  "type": "Feature",
  "properties": {
    "addr:full":"Carrer de Blai, 2 Barcelona Barcelona 08004",
    "addr:housenumber":"2",
    "addr:postcode":"08004",
    "addr:street":"Carrer De Blai",
    "iso:country":"ES",
    "sg:address":"Carrer de Blai, 2",
    "sg:city":"Barcelona",
    "sg:orig_category":"Fabricaci\u00d3n, Importaci\u00d3n De L\u00c1mparas Y Bombillas",
    "sg:phone":"+34 934 41 79 59",
    "sg:postcode":"08004",
    "sg:province":"Barcelona",
    "wof:name":"Peteira Laguela Santiago",
    "wof:placetype":"venue"
},
  "geometry": {"coordinates":[2.1666970253,41.3729324341],"type":"Point"}
}