{
  "type": "Feature",
  "properties": {
    "iso:country":"ES",
    "sg:address":"Avda Castilla, 27",
    "sg:city":"Palencia",
    "sg:orig_category":"Chapister\u00cda",
    "sg:phone":"+34 979 70 07 92",
    "sg:postcode":"34005",
    "sg:province":"Palencia",
    "wof:name":"Bello Prieto Hermogenes",
    "wof:placetype":"venue"
},
  "geometry": {"coordinates":[-4.5393209457,42.0110282898],"type":"Point"}
}