{
  "type": "Feature",
  "properties": {
    "iso:country":"ES",
    "sg:address":"Avda Espa\u00d1a, 21",
    "sg:city":"Getafe",
    "sg:orig_category":"Tapiceros Y Tapiceros",
    "sg:phone":"+34 916 81 22 05",
    "sg:postcode":"28903",
    "sg:province":"Madrid",
    "wof:name":"Rodriguez Vital Francisco",
    "wof:placetype":"venue"
},
  "geometry": {"coordinates":[-3.7214770317,40.3129501343],"type":"Point"}
}