{
  "type": "Feature",
  "properties": {
    "addr:full":"Calle de Granadilla, 22 Majadahonda Madrid 28220",
    "addr:housenumber":"22",
    "addr:postcode":"28220",
    "addr:street":"Calle De Granadilla",
    "iso:country":"ES",
    "sg:address":"Calle de Granadilla, 22",
    "sg:city":"Majadahonda",
    "sg:orig_category":"Dom\u00d3tica",
    "sg:phone":"+34 916 38 46 53",
    "sg:postcode":"28220",
    "sg:province":"Madrid",
    "sg:website":"www.domohogar.com",
    "wof:name":"Domohogar Viviendas Inteligentes S.l.",
    "wof:placetype":"venue"
},
  "geometry": {"coordinates":[-3.8755180836,40.4704246521],"type":"Point"}
}