{
  "type": "Feature",
  "properties": {
    "iso:country":"ES",
    "sg:address":"Pase Mediterraneo, 45",
    "sg:city":"Marina D'or",
    "sg:orig_category":"Parafarmacias",
    "sg:phone":"+34 964 31 32 85",
    "sg:postcode":"12594",
    "sg:province":"Castell\u00f3n",
    "wof:name":"Parafarmacia S.osca S.l.",
    "wof:placetype":"venue"
},
  "geometry": {"coordinates":[0.1535436064,40.1114654541],"type":"Point"}
}