{
  "type": "Feature",
  "properties": {
    "addr:full":"Calle de Esquilache, 2 Madrid Madrid 28003",
    "addr:housenumber":"2",
    "addr:postcode":"28003",
    "addr:street":"Calle De Esquilache",
    "iso:country":"ES",
    "sg:address":"Calle de Esquilache, 2",
    "sg:city":"Madrid",
    "sg:orig_category":"Agencias Y Asesores De Publicidad",
    "sg:phone":"+34 915 33 91 94",
    "sg:postcode":"28003",
    "sg:province":"Madrid",
    "wof:name":"Publicitarios Asociados Hache Seis S.l.",
    "wof:placetype":"venue"
},
  "geometry": {"coordinates":[-3.7050638199,40.4428215027],"type":"Point"}
}