{
  "type": "Feature",
  "properties": {
    "addr:full":"Calle de Moises De Leon, 43 Le\u00f3n Le\u00f3n 24006",
    "addr:housenumber":"43",
    "addr:postcode":"24006",
    "addr:street":"Calle De Moises De Leon;Leo\u0301N",
    "iso:country":"ES",
    "sg:address":"Calle de Moises De Leon, 43",
    "sg:city":"Le\u00f3n",
    "sg:orig_category":"Electricidad: Instaladores",
    "sg:phone":"+34 987 21 88 62",
    "sg:postcode":"24006",
    "sg:province":"Le\u00f3n",
    "wof:name":"Schneider Electric Espa\u00f1a S.a.",
    "wof:placetype":"venue"
},
  "geometry": {"coordinates":[-5.5571041107,42.5887832642],"type":"Point"}
}