{
  "type": "Feature",
  "properties": {
    "addr:full":"Calle de Unceta, 1 Zaragoza Zaragoza 50010",
    "addr:housenumber":"1",
    "addr:postcode":"50010",
    "addr:street":"Calle De Unceta",
    "iso:country":"ES",
    "sg:address":"Calle de Unceta, 1",
    "sg:city":"Zaragoza",
    "sg:orig_category":"Telas Y Sedas (al Por Menor)",
    "sg:phone":"+34 976 33 26 20",
    "sg:postcode":"50010",
    "sg:province":"Zaragoza",
    "wof:name":"Rojas Gil Antonio",
    "wof:placetype":"venue"
},
  "geometry": {"coordinates":[-0.9024580121,41.6536636353],"type":"Point"}
}