{
  "type": "Feature",
  "properties": {
    "addr:full":"Carrer de Tetuan, 62 Mataro Barcelona 08302",
    "addr:housenumber":"62",
    "addr:postcode":"08302",
    "addr:street":"Carrer De Tetuan",
    "iso:country":"ES",
    "sg:address":"Carrer de Tetuan, 62",
    "sg:city":"Mataro",
    "sg:orig_category":"Importaci\u00d3n",
    "sg:phone":"+34 937 56 93 42",
    "sg:postcode":"08302",
    "sg:province":"Barcelona",
    "wof:name":"Global Imexpro S.l.",
    "wof:placetype":"venue"
},
  "geometry": {"coordinates":[2.4371809959,41.5397224426],"type":"Point"}
}