{
  "type": "Feature",
  "properties": {
    "addr:full":"Calle de Adoratrices, 2 Guadalajara Guadalajara 19002",
    "addr:housenumber":"2",
    "addr:postcode":"19002",
    "addr:street":"Calle De Adoratrices",
    "iso:country":"ES",
    "sg:address":"Calle de Adoratrices, 2",
    "sg:city":"Guadalajara",
    "sg:orig_category":"Molduras, Junquillos, Listones Y Molduras Perforadas",
    "sg:phone":"+34 949 21 22 24",
    "sg:postcode":"19002",
    "sg:province":"Guadalajara",
    "wof:name":"Mota Mimbrero Josefa",
    "wof:placetype":"venue"
},
  "geometry": {"coordinates":[-3.1561932564,40.623134613],"type":"Point"}
}