{
  "type": "Feature",
  "properties": {
    "addr:full":"Carrer de Joan Maragall, 7 Mollet Valles Barcelona 08100",
    "addr:housenumber":"7",
    "addr:postcode":"08100",
    "addr:street":"Carrer De Joan Maragall",
    "iso:country":"ES",
    "sg:address":"Carrer de Joan Maragall, 7",
    "sg:city":"Mollet Valles",
    "sg:orig_category":"Ingeniero",
    "sg:phone":"+34 935 93 04 88",
    "sg:postcode":"08100",
    "sg:province":"Barcelona",
    "wof:name":"Oliveras Argelaguet Jaime",
    "wof:placetype":"venue"
},
  "geometry": {"coordinates":[2.2061269283,41.5373344421],"type":"Point"}
}