{
  "type": "Feature",
  "properties": {
    "addr:full":"Cust Matadero, 7 Guadalajara Guadalajara 19001",
    "addr:housenumber":"7",
    "addr:postcode":"19001",
    "addr:street":"Matadero",
    "iso:country":"ES",
    "sg:address":"Cust Matadero, 7",
    "sg:city":"Guadalajara",
    "sg:orig_category":"Automatizaci\u00d3n De Procesos Industriales Y De Edificaci\u00d3n (estudios, Instalaci\u00d3n)",
    "sg:phone":"+34 949 21 31 09",
    "sg:postcode":"19001",
    "sg:province":"Guadalajara",
    "wof:name":"Dosban Industrial S.l.",
    "wof:placetype":"venue"
},
  "geometry": {"coordinates":[-3.1672129631,40.6323547363],"type":"Point"}
}