{
  "type": "Feature",
  "properties": {
    "iso:country":"ES",
    "sg:address":"Calle de Toledo, 71",
    "sg:city":"Madrid",
    "sg:orig_category":"Zapatos (al Por Menor)",
    "sg:phone":"+34 913 54 06 31",
    "sg:postcode":"28005",
    "sg:province":"Madrid",
    "wof:name":"Chen Y Matteo 2003 S.l.",
    "wof:placetype":"venue"
},
  "geometry": {"coordinates":[-3.7091810703,40.4100837708],"type":"Point"}
}