{
  "type": "Feature",
  "properties": {
    "addr:full":"Calle de Magdalena (la), S/n Colindres Cantabria 39750",
    "addr:housenumber":"/ n",
    "addr:postcode":"39750",
    "addr:street":"Calle De Magdalena La S",
    "iso:country":"ES",
    "sg:address":"Calle de Magdalena (la), S/n",
    "sg:city":"Colindres",
    "sg:orig_category":"Promotores Constructores",
    "sg:phone":"+34 942 65 10 92",
    "sg:postcode":"39750",
    "sg:province":"Cantabria",
    "wof:name":"Promociones Martin Canuto S.l",
    "wof:placetype":"venue"
},
  "geometry": {"coordinates":[-3.4500389099,43.3952903748],"type":"Point"}
}