{
  "type": "Feature",
  "properties": {
    "iso:country":"ES",
    "sg:address":"Rua Pati\u00d1o (de), 18",
    "sg:city":"Trabanca Badi\u00e7a",
    "sg:orig_category":"Hielo Artificial (fabricaci\u00d3n, Distribuci\u00d3n)",
    "sg:phone":"+34 986 50 21 92",
    "sg:postcode":"36613",
    "sg:province":"Pontevedra",
    "wof:name":"Jelfimar S. L.",
    "wof:placetype":"venue"
},
  "geometry": {"coordinates":[-8.6480531693,42.4336204529],"type":"Point"}
}