{
  "type": "Feature",
  "properties": {
    "addr:full":"Pio Xii, 20 Mora Ebre Tarragona 43740",
    "addr:housenumber":"20",
    "addr:postcode":"43740",
    "addr:street":"Pio Xii;Ebre",
    "iso:country":"ES",
    "sg:address":"Pio Xii, 20",
    "sg:city":"Mora Ebre",
    "sg:orig_category":"Promotores Constructores",
    "sg:phone":"+34 977 40 27 52",
    "sg:postcode":"43740",
    "sg:province":"Tarragona",
    "wof:name":"Goresa Builder S.l",
    "wof:placetype":"venue"
},
  "geometry": {"coordinates":[0.6383029819,41.0866165161],"type":"Point"}
}