{
  "type": "Feature",
  "properties": {
    "iso:country":"ES",
    "sg:address":"Calle de Sevilla, 23",
    "sg:city":"Valencia",
    "sg:orig_category":"Marroquiner\u00cda Y Art\u00cdculos De Viaje (al Por Menor)",
    "sg:phone":"+34 963 41 99 52",
    "sg:postcode":"46006",
    "sg:province":"Valencia",
    "wof:name":"Daycar S. L.",
    "wof:placetype":"venue"
},
  "geometry": {"coordinates":[-0.373537004,39.4631996155],"type":"Point"}
}