{
  "type": "Feature",
  "properties": {
    "addr:full":"Avda Moratalaz, 109 Madrid Madrid 28030",
    "addr:housenumber":"109",
    "addr:postcode":"28030",
    "addr:street":"Avda Moratalaz",
    "iso:country":"ES",
    "sg:address":"Avda Moratalaz, 109",
    "sg:city":"Madrid",
    "sg:orig_category":"Peluquer\u00cdas, Peluquer\u00cda Mixta",
    "sg:phone":"+34 913 28 20 00",
    "sg:postcode":"28030",
    "sg:province":"Madrid",
    "wof:name":"Estilo's R.f. C.b.",
    "wof:placetype":"venue"
},
  "geometry": {"coordinates":[-3.6526079178,40.4057693481],"type":"Point"}
}