{
  "type": "Feature",
  "properties": {
    "addr:full":"C/ Cristobal Sanz, 24 Elche Alicante 03201",
    "addr:housenumber":"24",
    "addr:postcode":"03201",
    "addr:street":"C / Cristobal Sanz",
    "iso:country":"ES",
    "sg:address":"C/ Cristobal Sanz, 24",
    "sg:city":"Elche",
    "sg:orig_category":"Caf\u00c9s, Bares, Cervecer\u00cdas",
    "sg:phone":"+34 965 43 41 08",
    "sg:postcode":"03201",
    "sg:province":"Alicante",
    "wof:name":"Ibarra Plaza Maria De La Luz",
    "wof:placetype":"venue"
},
  "geometry": {"coordinates":[-0.7035639882,38.2667045593],"type":"Point"}
}