{
  "type": "Feature",
  "properties": {
    "addr:full":"Calle de Perez De Ayala, 37 Gijon Asturias 33209",
    "addr:housenumber":"37",
    "addr:postcode":"33209",
    "addr:street":"Calle De Perez De Ayala",
    "iso:country":"ES",
    "sg:address":"Calle de Perez De Ayala, 37",
    "sg:city":"Gijon",
    "sg:orig_category":"Transportes Por V\u00cdas Navegables",
    "sg:phone":"+34 985 14 51 76",
    "sg:postcode":"33209",
    "sg:province":"Asturias",
    "wof:name":"Aparicio Villa Jose Manuel",
    "wof:placetype":"venue"
},
  "geometry": {"coordinates":[-5.6621465683,43.5317802429],"type":"Point"}
}