{
  "type": "Feature",
  "properties": {
    "addr:full":"Calle de Zurita, 26 Madrid Madrid 28012",
    "addr:housenumber":"26",
    "addr:postcode":"madrid;28012",
    "addr:street":"Calle De Zurita",
    "iso:country":"ES",
    "sg:address":"Calle de Zurita, 26",
    "sg:city":"Madrid",
    "sg:orig_category":"Imprenta",
    "sg:phone":"+34 915 27 01 97",
    "sg:postcode":"28012",
    "sg:province":"Madrid",
    "wof:name":"Rojo Rodriguez Jeronimo",
    "wof:placetype":"venue"
},
  "geometry": {"coordinates":[-3.6997299194,40.4092712402],"type":"Point"}
}