{
  "type": "Feature",
  "properties": {
    "addr:full":"Avda Alejandro Casona, 7 Cangas Narcea Asturias 33800",
    "addr:housenumber":"7",
    "addr:postcode":"33800",
    "addr:street":"Avda Alejandro Casona",
    "iso:country":"ES",
    "sg:address":"Avda Alejandro Casona, 7",
    "sg:city":"Cangas Narcea",
    "sg:orig_category":"Asociaciones Y Clubs Deportivos",
    "sg:phone":"+34 985 81 70 03",
    "sg:postcode":"33800",
    "sg:province":"Asturias",
    "wof:name":"Sociedad Deportiva Narcea",
    "wof:placetype":"venue"
},
  "geometry": {"coordinates":[-6.5502290726,43.1801643372],"type":"Point"}
}