{
  "type": "Feature",
  "properties": {
    "addr:full":"Calle de Mayor, 8 Bahillo Palencia 34127",
    "addr:housenumber":"8",
    "addr:postcode":"34127",
    "addr:street":"Calle De Mayor",
    "iso:country":"ES",
    "sg:address":"Calle de Mayor, 8",
    "sg:city":"Bahillo",
    "sg:orig_category":"Parques De Atracciones Y Centros De Esparcimiento",
    "sg:phone":"+34 979 88 50 88",
    "sg:postcode":"34127",
    "sg:province":"Palencia",
    "wof:name":"Automaticos Del Carrion S.a.",
    "wof:placetype":"venue"
},
  "geometry": {"coordinates":[-4.5778756142,42.4417152405],"type":"Point"}
}