{
  "type": "Feature",
  "properties": {
    "addr:full":"Plaz Mayor, 9 Lalueza Huesca 22214",
    "addr:housenumber":"9",
    "addr:postcode":"22214",
    "addr:street":"Plaz Mayor",
    "iso:country":"ES",
    "sg:address":"Plaz Mayor, 9",
    "sg:city":"Lalueza",
    "sg:orig_category":"Farmacias",
    "sg:phone":"+34 974 57 50 62",
    "sg:postcode":"22214",
    "sg:province":"Huesca",
    "wof:name":"Vilella Barrachina Santiago",
    "wof:placetype":"venue"
},
  "geometry": {"coordinates":[-0.2560670078,41.8407249451],"type":"Point"}
}