{
  "type": "Feature",
  "properties": {
    "addr:full":"Calle de General Moscardo, 63 Albujon Murcia 30330",
    "addr:housenumber":"63",
    "addr:postcode":"30330",
    "addr:street":"Calle De General Moscardo",
    "iso:country":"ES",
    "sg:address":"Calle de General Moscardo, 63",
    "sg:city":"Albujon",
    "sg:orig_category":"Herradores, Herreros, Carreteros",
    "sg:phone":"+34 968 16 01 33",
    "sg:postcode":"30330",
    "sg:province":"Murcia",
    "wof:name":"Segura Padilla Juan",
    "wof:placetype":"venue"
},
  "geometry": {"coordinates":[-1.0480289459,37.7181396484],"type":"Point"}
}