{
  "type": "Feature",
  "properties": {
    "iso:country":"ES",
    "sg:address":"Calle de Alcala, 122",
    "sg:city":"Madrid",
    "sg:orig_category":"Prot\u00c9sicos Dentales",
    "sg:phone":"+34 914 01 23 18",
    "sg:postcode":"28009",
    "sg:province":"Madrid",
    "wof:name":"Laboratorio Dental Ortosol S.l.",
    "wof:placetype":"venue"
},
  "geometry": {"coordinates":[-3.6721382141,40.4264450073],"type":"Point"}
}