{
  "type": "Feature",
  "properties": {
    "iso:country":"ES",
    "sg:address":"Carrer de Terrisser, 13",
    "sg:city":"Sant Feliu Llobregat",
    "sg:orig_category":"Locales Y Clases De Danza",
    "sg:phone":"+34 936 85 31 62",
    "sg:postcode":"08980",
    "sg:province":"Barcelona",
    "wof:name":"Cid Roldos Marta",
    "wof:placetype":"venue"
},
  "geometry": {"coordinates":[2.0528309345,41.3801345825],"type":"Point"}
}