{
  "type": "Feature",
  "properties": {
    "iso:country":"ES",
    "sg:address":"Calle de Alfonso Xiii, 8",
    "sg:city":"Parla",
    "sg:orig_category":"Molduras, Junquillos, Listones Y Molduras Perforadas",
    "sg:phone":"+34 916 98 22 03",
    "sg:postcode":"28980",
    "sg:province":"Madrid",
    "wof:name":"Ruiz Gomez Maria Del Carmen",
    "wof:placetype":"venue"
},
  "geometry": {"coordinates":[-3.7656385899,40.2336273193],"type":"Point"}
}