{
  "type": "Feature",
  "properties": {
    "addr:full":"Carrer de Major, 26 S. Feliu Guixols Girona 17220",
    "addr:housenumber":"26",
    "addr:postcode":"17220",
    "addr:street":"Carrer De Major;S. Feliu Guixols",
    "iso:country":"ES",
    "sg:address":"Carrer de Major, 26",
    "sg:city":"S. Feliu Guixols",
    "sg:orig_category":"Ropa Para Ni\u00d1os (al Por Menor)",
    "sg:phone":"+34 972 32 64 01",
    "sg:postcode":"17220",
    "sg:province":"Girona",
    "wof:name":"Van Winsen S.l.",
    "wof:placetype":"venue"
},
  "geometry": {"coordinates":[3.0307080746,41.7818031311],"type":"Point"}
}