{
  "type": "Feature",
  "properties": {
    "iso:country":"ES",
    "sg:address":"Carr Pobla De Segur, 12",
    "sg:city":"Lleida",
    "sg:orig_category":"Sonorizaci\u00d3n, Iluminaci\u00d3n Para Cine, Teatro Y Discotecas (al Por Mayor, Al Por Menor)",
    "sg:phone":"+34 973 24 89 82",
    "sg:postcode":"25005",
    "sg:province":"Lleida",
    "wof:name":"Elecson Sonido Profesional S.l.",
    "wof:placetype":"venue"
},
  "geometry": {"coordinates":[0.6320649981,41.6318473816],"type":"Point"}
}