{
  "type": "Feature",
  "properties": {
    "addr:full":"Carr Barranc (del), 20 Betxi Castell\u00f3n 12549",
    "addr:housenumber":"20",
    "addr:postcode":"12549",
    "addr:street":"Carr Barranc Del;Castello\u0301N",
    "iso:country":"ES",
    "sg:address":"Carr Barranc (del), 20",
    "sg:city":"Betxi",
    "sg:orig_category":"Molduras, Junquillos, Listones Y Molduras Perforadas",
    "sg:phone":"+34 964 62 21 53",
    "sg:postcode":"12549",
    "sg:province":"Castell\u00f3n",
    "wof:name":"Gumbau Garcia Jose Pascual",
    "wof:placetype":"venue"
},
  "geometry": {"coordinates":[-0.186204195,39.8594474792],"type":"Point"}
}