{
  "type": "Feature",
  "properties": {
    "addr:full":"Cno. Comepan, S/n Villanubla Valladolid 47620",
    "addr:postcode":"47620",
    "addr:street":"Comepan S / N",
    "iso:country":"ES",
    "sg:address":"Cno. Comepan, S/n",
    "sg:city":"Villanubla",
    "sg:orig_category":"Agricultores, Agricultores",
    "sg:phone":"+34 983 48 02 67",
    "sg:postcode":"47620",
    "sg:province":"Valladolid",
    "wof:name":"Herfe S.a.t.",
    "wof:placetype":"venue"
},
  "geometry": {"coordinates":[-4.818048954,41.6949462891],"type":"Point"}
}