{
  "type": "Feature",
  "properties": {
    "iso:country":"ES",
    "sg:address":"Calle de Fresnedilla, 24",
    "sg:city":"Lozoyuela",
    "sg:orig_category":"Serigraf\u00cda (material Y Suministros)",
    "sg:phone":"+34 918 69 44 17",
    "sg:postcode":"28752",
    "sg:province":"Madrid",
    "wof:name":"Pozo Garcia Marcelino Del",
    "wof:placetype":"venue"
},
  "geometry": {"coordinates":[-3.6220664978,40.9302558899],"type":"Point"}
}