{
  "type": "Feature",
  "properties": {
    "iso:country":"ES",
    "sg:address":"Avda Monforte De Lemos, 172",
    "sg:city":"Madrid",
    "sg:orig_category":"Inform\u00c1tica: Mantenimiento Y Reparaci\u00d3n De Ordenadores",
    "sg:phone":"+34 913 16 62 34",
    "sg:postcode":"28029",
    "sg:province":"Madrid",
    "wof:name":"Manservic S.l.",
    "wof:placetype":"venue"
},
  "geometry": {"coordinates":[-3.7151279449,40.4773139954],"type":"Point"}
}