{
  "type": "Feature",
  "properties": {
    "iso:country":"ES",
    "sg:address":"Cno. Casasbuenas, S/n",
    "sg:city":"Noez",
    "sg:orig_category":"Aceites Y Grasas Alimentarias (fabricaci\u00d3n, Al Por Mayor)",
    "sg:phone":"+34 925 59 02 27",
    "sg:postcode":"45162",
    "sg:province":"Toledo",
    "wof:name":"Ifama S.l.",
    "wof:placetype":"venue"
},
  "geometry": {"coordinates":[-4.1800341606,39.7407493591],"type":"Point"}
}