{
  "type": "Feature",
  "properties": {
    "addr:full":"Carr Conde De Rodezno, 38 Quart Poblet Valencia 46930",
    "addr:housenumber":"38",
    "addr:postcode":"46930",
    "addr:street":"Carr Conde De Rodezno;Poblet",
    "iso:country":"ES",
    "sg:address":"Carr Conde De Rodezno, 38",
    "sg:city":"Quart Poblet",
    "sg:orig_category":"Mec\u00c1nico Del Autom\u00d3vil",
    "sg:phone":"+34 961 53 40 11",
    "sg:postcode":"46930",
    "sg:province":"Valencia",
    "wof:name":"Talleres Tu Auto S.l.",
    "wof:placetype":"venue"
},
  "geometry": {"coordinates":[-0.4487380087,39.4809761047],"type":"Point"}
}