{
  "type": "Feature",
  "properties": {
    "addr:full":"Calle de Arquitecto Urteaga, 5 Javea Alicante 03730",
    "addr:housenumber":"5",
    "addr:postcode":"03730",
    "addr:street":"Calle De Arquitecto Urteaga",
    "iso:country":"ES",
    "sg:address":"Calle de Arquitecto Urteaga, 5",
    "sg:city":"Javea",
    "sg:orig_category":"Ropa De Trabajo Y Profesionales (al Por Menor)",
    "sg:phone":"+34 966 46 26 76",
    "sg:postcode":"03730",
    "sg:province":"Alicante",
    "wof:name":"Robatreball 2001 S.l.",
    "wof:placetype":"venue"
},
  "geometry": {"coordinates":[0.1656675935,38.7900238037],"type":"Point"}
}