{
  "type": "Feature",
  "properties": {
    "addr:full":"Carr Joanot Martorell, 16 Sueca Valencia 46410",
    "addr:housenumber":"16",
    "addr:postcode":"46410",
    "addr:street":"Carr Joanot Martorell",
    "iso:country":"ES",
    "sg:address":"Carr Joanot Martorell, 16",
    "sg:city":"Sueca",
    "sg:orig_category":"Agentes, Concesionarios Y Sucursales De Veh\u00cdculos",
    "sg:phone":"+34 961 70 04 64",
    "sg:postcode":"46410",
    "sg:province":"Valencia",
    "wof:name":"Movil-car Sueca S.l.",
    "wof:placetype":"venue"
},
  "geometry": {"coordinates":[-0.3147130013,39.1988525391],"type":"Point"}
}