{
  "type": "Feature",
  "properties": {
    "addr:full":"Calle de Emilio Castelar, 9 Alcazar S. Juan Ciudad Real 13600",
    "addr:housenumber":"9",
    "addr:postcode":"13600",
    "addr:street":"Calle De Emilio Castelar;Alcazar S. Juan Ciudad Real",
    "iso:country":"ES",
    "sg:address":"Calle de Emilio Castelar, 9",
    "sg:city":"Alcazar S. Juan",
    "sg:orig_category":"Ropa Para Caballeros (al Por Menor)",
    "sg:phone":"+34 926 54 14 55",
    "sg:postcode":"13600",
    "sg:province":"Ciudad Real",
    "wof:name":"Textil Daimiele\u00f1a S.a.",
    "wof:placetype":"venue"
},
  "geometry": {"coordinates":[-3.2095317841,39.3905334473],"type":"Point"}
}