{
  "type": "Feature",
  "properties": {
    "addr:full":"Luga Huertos Familiares, 29 S. Juan Puerto Huelva 21610",
    "addr:housenumber":"29",
    "addr:postcode":"21610",
    "addr:street":"Familiares;S. Juan Puerto",
    "iso:country":"ES",
    "sg:address":"Luga Huertos Familiares, 29",
    "sg:city":"S. Juan Puerto",
    "sg:orig_category":"Transportes Por V\u00cdas Navegables",
    "sg:phone":"+34 959 36 75 03",
    "sg:postcode":"21610",
    "sg:province":"Huelva",
    "wof:name":"Transportes San Juan Moguer S.l.",
    "wof:placetype":"venue"
},
  "geometry": {"coordinates":[-6.8440890312,37.3149261475],"type":"Point"}
}