{
  "type": "Feature",
  "properties": {
    "iso:country":"ES",
    "sg:address":"Avda Donostiarra, 14",
    "sg:city":"Madrid",
    "sg:orig_category":"Gastronom\u00cda: Especialidades Regionales Y Extranjeras (producci\u00d3n, Al Por Mayor)",
    "sg:phone":"+34 914 03 04 19",
    "sg:postcode":"28027",
    "sg:province":"Madrid",
    "sg:website":"www.jamonerias-manolo.com",
    "wof:name":"Lobato Palomero S.l.",
    "wof:placetype":"venue"
},
  "geometry": {"coordinates":[-3.6576709747,40.4346847534],"type":"Point"}
}