{
  "type": "Feature",
  "properties": {
    "addr:full":"Calle de Batalla De Lepanto, 4 Zaragoza Zaragoza 50002",
    "addr:housenumber":"4",
    "addr:postcode":"50002",
    "addr:street":"Calle De Batalla De Lepanto",
    "iso:country":"ES",
    "sg:address":"Calle de Batalla De Lepanto, 4",
    "sg:city":"Zaragoza",
    "sg:orig_category":"Iglesias Cristianas Diversas",
    "sg:phone":"+34 976 49 79 51",
    "sg:postcode":"50002",
    "sg:province":"Zaragoza",
    "wof:name":"Testigos Cristianos De Jehova",
    "wof:placetype":"venue"
},
  "geometry": {"coordinates":[-0.8663589954,41.6448783875],"type":"Point"}
}