{
  "type": "Feature",
  "properties": {
    "addr:full":"Avda Virgen De Argeme, 27 Coria C\u00e1ceres 10800",
    "addr:housenumber":"27",
    "addr:postcode":"10800",
    "addr:street":"Avda Virgen De Argeme;Ca\u0301Ceres",
    "iso:country":"ES",
    "sg:address":"Avda Virgen De Argeme, 27",
    "sg:city":"Coria",
    "sg:orig_category":"El Hogar: Amueblado, Acondicionamiento, Decoraci\u00d3n Y Mantenimiento",
    "sg:phone":"+34 927 50 36 89",
    "sg:postcode":"10800",
    "sg:province":"C\u00e1ceres",
    "wof:name":"Gutierrez Perez Julia",
    "wof:placetype":"venue"
},
  "geometry": {"coordinates":[-6.5415291786,39.9918403625],"type":"Point"}
}