{
  "type": "Feature",
  "properties": {
    "iso:country":"ES",
    "sg:address":"Martin Azpilcueta, 6",
    "sg:city":"Iru\u00f1a",
    "sg:orig_category":"Molduras, Junquillos, Listones Y Molduras Perforadas",
    "sg:phone":"+34 948 17 74 15",
    "sg:postcode":"31011",
    "sg:province":"Navarra",
    "wof:name":"La Bodega Seguota S.l.r.",
    "wof:placetype":"venue"
},
  "geometry": {"coordinates":[-1.6631759405,42.8146095276],"type":"Point"}
}