{
  "type": "Feature",
  "properties": {
    "addr:full":"Los Capelos, S/n Carral La Coru\u00f1a 15175",
    "addr:housenumber":"s / n",
    "addr:postcode":"15175",
    "addr:street":"La Corun\u0303A",
    "iso:country":"ES",
    "sg:address":"Los Capelos, S/n",
    "sg:city":"Carral",
    "sg:orig_category":"Construcciones Prefabricadas Y Desmontables",
    "sg:phone":"+34 981 67 00 11",
    "sg:postcode":"15175",
    "sg:province":"La Coru\u00f1a",
    "wof:name":"Intabar S. L.",
    "wof:placetype":"venue"
},
  "geometry": {"coordinates":[-8.3558940887,43.2296905518],"type":"Point"}
}