{
  "type": "Feature",
  "properties": {
    "iso:country":"ES",
    "sg:address":"Calle de Manteca, 11",
    "sg:city":"Zamora",
    "sg:orig_category":"Panader\u00cdas, Panader\u00cdas",
    "sg:phone":"+34 980 53 26 08",
    "sg:postcode":"49002",
    "sg:province":"Zamora",
    "wof:name":"Segurado Barbero Andres",
    "wof:placetype":"venue"
},
  "geometry": {"coordinates":[-5.7466778755,41.5006256104],"type":"Point"}
}