{
  "type": "Feature",
  "properties": {
    "addr:full":"Calle de Virgen De La Piedad, 9 Baza Granada 18800",
    "addr:housenumber":"9",
    "addr:postcode":"18800",
    "addr:street":"Calle De Virgen De La Piedad",
    "iso:country":"ES",
    "sg:address":"Calle de Virgen De La Piedad, 9",
    "sg:city":"Baza",
    "sg:orig_category":"Aceites Y Grasas Alimentarias (fabricaci\u00d3n, Al Por Mayor)",
    "sg:phone":"+34 958 70 15 68",
    "sg:postcode":"18800",
    "sg:province":"Granada",
    "wof:name":"Martinez Cerezo Maria Dolores",
    "wof:placetype":"venue"
},
  "geometry": {"coordinates":[-2.7814080715,37.4902648926],"type":"Point"}
}