{
  "type": "Feature",
  "properties": {
    "addr:full":"Calle de Escultor Rivera, 9 Ba\u00d1eza Le\u00f3n 24750",
    "addr:housenumber":"9",
    "addr:postcode":"24750",
    "addr:street":"Calle De Escultor Rivera;Leo\u0301N",
    "iso:country":"ES",
    "sg:address":"Calle de Escultor Rivera, 9",
    "sg:city":"Ba\u00d1eza",
    "sg:orig_category":"Peleter\u00cdas",
    "sg:phone":"+34 987 64 39 26",
    "sg:postcode":"24750",
    "sg:province":"Le\u00f3n",
    "wof:name":"Lopez Lopez Martin",
    "wof:placetype":"venue"
},
  "geometry": {"coordinates":[-5.8991293907,42.2988090515],"type":"Point"}
}