{
  "type": "Feature",
  "properties": {
    "iso:country":"ES",
    "sg:address":"Verbania, 68",
    "sg:city":"S'agaro",
    "sg:orig_category":"Alquiler De Salones",
    "sg:phone":"+34 972 82 22 39",
    "sg:postcode":"17248",
    "sg:province":"Girona",
    "wof:name":"Onema S.l.",
    "wof:placetype":"venue"
},
  "geometry": {"coordinates":[2.8187398911,41.9808616638],"type":"Point"}
}