{
  "type": "Feature",
  "properties": {
    "addr:full":"Calle de Valdecanillas, 29 Madrid Madrid 28037",
    "addr:housenumber":"29",
    "addr:postcode":"madrid;28037",
    "addr:street":"Calle De Valdecanillas",
    "iso:country":"ES",
    "sg:address":"Calle de Valdecanillas, 29",
    "sg:city":"Madrid",
    "sg:orig_category":"Molduras, Junquillos, Listones Y Molduras Perforadas",
    "sg:phone":"+34 913 04 92 79",
    "sg:postcode":"28037",
    "sg:province":"Madrid",
    "wof:name":"Valdecanillas Numero 29 S.l.",
    "wof:placetype":"venue"
},
  "geometry": {"coordinates":[-3.6280989647,40.4314231873],"type":"Point"}
}