{
  "type": "Feature",
  "properties": {
    "iso:country":"ES",
    "sg:address":"Plaz Funicular Del, 2",
    "sg:city":"Bilbao",
    "sg:orig_category":"Molduras, Junquillos, Listones Y Molduras Perforadas",
    "sg:phone":"+34 944 46 67 81",
    "sg:postcode":"48007",
    "sg:province":"Vizcaya",
    "wof:name":"Moran Nu\u00f1ez Raquel",
    "wof:placetype":"venue"
},
  "geometry": {"coordinates":[-2.9263989925,43.2686424255],"type":"Point"}
}