{
  "type": "Feature",
  "properties": {
    "iso:country":"ES",
    "sg:address":"Calle de Ramon Y Cajal, 24",
    "sg:city":"Ponferrada",
    "sg:orig_category":"Art\u00cdculos De Regalo (al Por Menor)",
    "sg:phone":"+34 987 42 44 97",
    "sg:postcode":"24400",
    "sg:province":"Le\u00f3n",
    "wof:name":"Gra\u00f1a Vazquez Maria Jose",
    "wof:placetype":"venue"
},
  "geometry": {"coordinates":[-6.6001348495,42.54945755],"type":"Point"}
}