{
  "type": "Feature",
  "properties": {
    "iso:country":"ES",
    "sg:address":"Calle de Estatuto De Galicia, 28",
    "sg:city":"Boiro",
    "sg:orig_category":"Ludotecas",
    "sg:phone":"+34 981 84 60 16",
    "sg:postcode":"15930",
    "sg:province":"La Coru\u00f1a",
    "wof:name":"Ciber Boiro S.l.",
    "wof:placetype":"venue"
},
  "geometry": {"coordinates":[-8.8847093582,42.6471214294],"type":"Point"}
}