{
  "type": "Feature",
  "properties": {
    "addr:full":"Rbla Catalunya, 10 Barcelona Barcelona 08007",
    "addr:housenumber":"10",
    "addr:postcode":"08007",
    "addr:street":"Rbla Catalunya",
    "iso:country":"ES",
    "sg:address":"Rbla Catalunya, 10",
    "sg:city":"Barcelona",
    "sg:orig_category":"Agencias De Prensa E Informaci\u00d3n",
    "sg:phone":"+34 933 01 95 38",
    "sg:postcode":"08007",
    "sg:province":"Barcelona",
    "wof:name":"Agencia France Presse",
    "wof:placetype":"venue"
},
  "geometry": {"coordinates":[2.1679048538,41.3878517151],"type":"Point"}
}