{
  "type": "Feature",
  "properties": {
    "iso:country":"ES",
    "sg:address":"Calle de Ricardo Del Arco, 16",
    "sg:city":"Huesca",
    "sg:orig_category":"Pod\u00d3logos: Pedicuros",
    "sg:phone":"+34 974 24 12 64",
    "sg:postcode":"22004",
    "sg:province":"Huesca",
    "wof:name":"Solana Bernal Marta",
    "wof:placetype":"venue"
},
  "geometry": {"coordinates":[-0.4171305001,42.1381072998],"type":"Point"}
}