{
  "type": "Feature",
  "properties": {
    "addr:full":"Avda Buenos Aires, 36 Ourense Ourense 32004",
    "addr:housenumber":"36",
    "addr:postcode":"32004",
    "addr:street":"Avda Buenos Aires",
    "iso:country":"ES",
    "sg:address":"Avda Buenos Aires, 36",
    "sg:city":"Ourense",
    "sg:orig_category":"Fabricaci\u00d3n, Venta De Cuadros, Accesorios Para Enmarcar",
    "sg:phone":"+34 988 25 55 67",
    "sg:postcode":"32004",
    "sg:province":"Ourense",
    "wof:name":"Gomez Sanchez Amadeo",
    "wof:placetype":"venue"
},
  "geometry": {"coordinates":[-7.8602528572,42.3396224976],"type":"Point"}
}