{
  "type": "Feature",
  "properties": {
    "iso:country":"ES",
    "sg:address":"Carrer de Sant Dalmir, 8",
    "sg:city":"Barcelona",
    "sg:orig_category":"Electrodom\u00c9sticos (al Por Menor)",
    "sg:phone":"+34 934 29 70 89",
    "sg:postcode":"08032",
    "sg:province":"Barcelona",
    "wof:name":"Gabriel Del Olmo Santiago",
    "wof:placetype":"venue"
},
  "geometry": {"coordinates":[2.1513910294,41.4233322144],"type":"Point"}
}