{
  "type": "Feature",
  "properties": {
    "iso:country":"ES",
    "sg:address":"Calle de Fray Martin De Alcazar, 3",
    "sg:city":"Alcazar S. Juan",
    "sg:orig_category":"Prot\u00c9sicos Dentales",
    "sg:phone":"+34 926 54 47 03",
    "sg:postcode":"13600",
    "sg:province":"Ciudad Real",
    "wof:name":"Alcazar Dental C.b.",
    "wof:placetype":"venue"
},
  "geometry": {"coordinates":[-3.2200193405,39.3879890442],"type":"Point"}
}