{
  "type": "Feature",
  "properties": {
    "addr:full":"Calle de Ronda De Las Adelfas, 4 Barca De La Florida C\u00e1diz 11570",
    "addr:housenumber":"4",
    "addr:postcode":"11570",
    "addr:street":"Calle De Ronda De Las Adelfas;Ca\u0301Diz",
    "iso:country":"ES",
    "sg:address":"Calle de Ronda De Las Adelfas, 4",
    "sg:city":"Barca De La Florida",
    "sg:orig_category":"Mercer\u00cda, Lencer\u00cda (al Por Menor)",
    "sg:phone":"+34 956 39 00 45",
    "sg:postcode":"11570",
    "sg:province":"C\u00e1diz",
    "wof:name":"Garcia Perea Emilio",
    "wof:placetype":"venue"
},
  "geometry": {"coordinates":[-5.9331851006,36.6492080688],"type":"Point"}
}