{
  "type": "Feature",
  "properties": {
    "iso:country":"ES",
    "sg:address":"Avda Compas Del, 12",
    "sg:city":"Mijas",
    "sg:orig_category":"Regalos, Souvenires (fabricaci\u00d3n, Al Por Mayor)",
    "sg:phone":"+34 952 48 66 41",
    "sg:postcode":"29650",
    "sg:province":"M\u00e1laga",
    "wof:name":"Gallardo Colmenero C.b.",
    "wof:placetype":"venue"
},
  "geometry": {"coordinates":[-4.6378788948,36.5949668884],"type":"Point"}
}