{
  "type": "Feature",
  "properties": {
    "iso:country":"ES",
    "sg:address":"Calle de Hernandez Iglesias, 19",
    "sg:city":"Madrid",
    "sg:orig_category":"Promotores Constructores",
    "sg:phone":"+34 914 07 61 96",
    "sg:postcode":"28027",
    "sg:province":"Madrid",
    "wof:name":"Tecnodasa S.a.",
    "wof:placetype":"venue"
},
  "geometry": {"coordinates":[-3.6442840099,40.442024231],"type":"Point"}
}