{
  "type": "Feature",
  "properties": {
    "addr:full":"Carrer de Pintor Cusachs, 4 Mas D'en Bosch Tarragona 43850",
    "addr:housenumber":"4",
    "addr:postcode":"43850",
    "addr:street":"Carrer De Pintor Cusachs",
    "iso:country":"ES",
    "sg:address":"Carrer de Pintor Cusachs, 4",
    "sg:city":"Mas D'en Bosch",
    "sg:orig_category":"Restaurantes",
    "sg:phone":"+34 977 79 55 51",
    "sg:postcode":"43850",
    "sg:province":"Tarragona",
    "wof:name":"Danes Passarrius Jose",
    "wof:placetype":"venue"
},
  "geometry": {"coordinates":[1.2401560545,41.1224555969],"type":"Point"}
}