{
  "type": "Feature",
  "properties": {
    "iso:country":"ES",
    "sg:address":"Calle de Rio Guadalix (del), 1",
    "sg:city":"Colmenar Viejo",
    "sg:orig_category":"Centros De Coordinaci\u00d3n",
    "sg:phone":"+34 918 45 28 49",
    "sg:postcode":"28770",
    "sg:province":"Madrid",
    "wof:name":"Marivela Rivas Javier",
    "wof:placetype":"venue"
},
  "geometry": {"coordinates":[-3.771584034,40.665019989],"type":"Point"}
}