{
  "type": "Feature",
  "properties": {
    "addr:full":"Calle de Chile, 2 Toledo Toledo 45004",
    "addr:housenumber":"2",
    "addr:postcode":"45004",
    "addr:street":"Calle De Chile",
    "iso:country":"ES",
    "sg:address":"Calle de Chile, 2",
    "sg:city":"Toledo",
    "sg:orig_category":"Molduras, Junquillos, Listones Y Molduras Perforadas",
    "sg:phone":"+34 925 25 77 77",
    "sg:postcode":"45004",
    "sg:province":"Toledo",
    "wof:name":"Dublin Toledo Club S.l.",
    "wof:placetype":"venue"
},
  "geometry": {"coordinates":[-4.0307707787,39.8666687012],"type":"Point"}
}