{
  "type": "Feature",
  "properties": {
    "iso:country":"ES",
    "sg:address":"Calle de Mayor, 68",
    "sg:city":"Alcantarilla",
    "sg:orig_category":"Asociaciones, Organismos Culturales Y Socioeducativos",
    "sg:phone":"+34 968 80 03 53",
    "sg:postcode":"30820",
    "sg:province":"Murcia",
    "wof:name":"Circulo Industrial",
    "wof:placetype":"venue"
},
  "geometry": {"coordinates":[-1.2123219967,37.9705581665],"type":"Point"}
}