{
  "type": "Feature",
  "properties": {
    "iso:country":"ES",
    "sg:address":"Ctra Palma Del Rio (villarrubia), Km. 0013,7",
    "sg:city":"Villarrubia",
    "sg:orig_category":"Organizaci\u00d3n De Actos, Seminarios Y Congresos",
    "sg:phone":"+34 957 45 84 75",
    "sg:postcode":"14710",
    "sg:province":"C\u00f3rdoba",
    "wof:name":"Cortijo El Alamillo De Cordoba S.l.",
    "wof:placetype":"venue"
},
  "geometry": {"coordinates":[-4.8645591736,37.8604507446],"type":"Point"}
}