{
  "type": "Feature",
  "properties": {
    "addr:full":"San J. Bosco, 7 Iru\u00f1a Navarra 31007",
    "addr:housenumber":"7",
    "addr:postcode":"31007",
    "addr:street":"Irun\u0303A Navarra",
    "iso:country":"ES",
    "sg:address":"San J. Bosco, 7",
    "sg:city":"Iru\u00f1a",
    "sg:orig_category":"Abogados",
    "sg:phone":"+34 948 19 72 02",
    "sg:postcode":"31007",
    "sg:province":"Navarra",
    "wof:name":"Aguirreolea Morales Teresa",
    "wof:placetype":"venue"
},
  "geometry": {"coordinates":[-1.6481051445,42.8059310913],"type":"Point"}
}