{
  "type": "Feature",
  "properties": {
    "addr:full":"Carrer de Calvet D'estrella, 47 Sabadell Barcelona 08203",
    "addr:housenumber":"47",
    "addr:postcode":"08203",
    "addr:street":"Carrer De Calvet D'Estrella",
    "iso:country":"ES",
    "sg:address":"Carrer de Calvet D'estrella, 47",
    "sg:city":"Sabadell",
    "sg:orig_category":"Herramientas Manuales (fabricaci\u00d3n, Al Por Mayor)",
    "sg:phone":"+34 937 10 46 30",
    "sg:postcode":"08203",
    "sg:province":"Barcelona",
    "wof:name":"Bautista Sanchez Rafael",
    "wof:placetype":"venue"
},
  "geometry": {"coordinates":[2.1171584129,41.5363464355],"type":"Point"}
}