{
  "type": "Feature",
  "properties": {
    "addr:full":"Avda Sierra Minera, 8 Union Murcia 30360",
    "addr:housenumber":"8",
    "addr:postcode":"30360",
    "addr:street":"Avda Sierra Minera",
    "iso:country":"ES",
    "sg:address":"Avda Sierra Minera, 8",
    "sg:city":"Union",
    "sg:classifiers":[
        {
            "category":"Communications",
            "type":"Services"
        }
    ],
    "sg:phone":"+34 968 33 75 25",
    "sg:postcode":"30360",
    "sg:province":"Murcia",
    "sg:tags":[
        "televisiones",
        "y",
        "radio"
    ],
    "wof:name":"Gonzalez Rodriguez Salvador",
    "wof:placetype":"venue"
},
  "geometry": {"coordinates":[-0.8755819798,37.6260108948],"type":"Point"}
}