{
  "type": "Feature",
  "properties": {
    "addr:full":"Pol Ind Llanos De Armijo, S/n La Puerta Segura Ja\u00e9n 23360",
    "addr:housenumber":"/ n",
    "addr:postcode":"23360",
    "addr:street":"S",
    "iso:country":"ES",
    "sg:address":"Pol Ind Llanos De Armijo, S/n",
    "sg:city":"La Puerta Segura",
    "sg:orig_category":"Empresas De Carpinter\u00cda Met\u00c1lica",
    "sg:phone":"+34 953 48 67 10",
    "sg:postcode":"23360",
    "sg:province":"Ja\u00e9n",
    "wof:name":"Carpinteria Metalica San Blas S.l.l.",
    "wof:placetype":"venue"
},
  "geometry": {"coordinates":[-2.7369730473,38.3500518799],"type":"Point"}
}