{
  "type": "Feature",
  "properties": {
    "iso:country":"ES",
    "sg:address":"Calle de Fuente La, 9",
    "sg:city":"Estacion Ferrea",
    "sg:orig_category":"Carnicer\u00cdas, Carnicer\u00cdas",
    "sg:phone":"+34 956 78 62 77",
    "sg:postcode":"11368",
    "sg:province":"C\u00e1diz",
    "wof:name":"Macias Ruiz Bernardina",
    "wof:placetype":"venue"
},
  "geometry": {"coordinates":[-5.4313435555,36.2149124146],"type":"Point"}
}