{
  "type": "Feature",
  "properties": {
    "addr:full":"Calle de Jose Luis Rodriguez Lopez De Haro, 1 Almaden Ciudad Real 13400",
    "addr:housenumber":"1",
    "addr:postcode":"almaden;13400",
    "addr:street":"Calle De Jose Luis Rodriguez Lopez De Haro;Real",
    "iso:country":"ES",
    "sg:address":"Calle de Jose Luis Rodriguez Lopez De Haro, 1",
    "sg:city":"Almaden",
    "sg:orig_category":"Explotaci\u00d3n De Minas",
    "sg:phone":"+34 926 26 45 20",
    "sg:postcode":"13400",
    "sg:province":"Ciudad Real",
    "wof:name":"Fundacion Almaden Francisco Javier De Villegas",
    "wof:placetype":"venue"
},
  "geometry": {"coordinates":[-4.8340392113,38.7724494934],"type":"Point"}
}