{
  "type": "Feature",
  "properties": {
    "addr:full":"Pl Iglesia, 1 Orihuela Alicante 03300",
    "addr:housenumber":"1",
    "addr:postcode":"03300",
    "addr:street":"Pl Iglesia",
    "iso:country":"ES",
    "sg:address":"Pl Iglesia, 1",
    "sg:city":"Orihuela",
    "sg:orig_category":"Iglesia Cat\u00d3lica",
    "sg:phone":"+34 965 30 46 39",
    "sg:postcode":"03300",
    "sg:province":"Alicante",
    "wof:name":"Parroquia Ecce Homo",
    "wof:placetype":"venue"
},
  "geometry": {"coordinates":[-1.009245038,38.0805397034],"type":"Point"}
}