{
  "type": "Feature",
  "properties": {
    "iso:country":"ES",
    "sg:address":"Barr Karabigane Auzoa, 4",
    "sg:city":"Berango",
    "sg:orig_category":"Centros De Educaci\u00d3n Especial",
    "sg:phone":"+34 946 68 11 17",
    "sg:postcode":"48640",
    "sg:province":"Vizcaya",
    "wof:name":"Ayuntamiento De Berango",
    "wof:placetype":"venue"
},
  "geometry": {"coordinates":[-2.9949066639,43.3657493591],"type":"Point"}
}