{
  "type": "Feature",
  "properties": {
    "addr:full":"Avgd Reis Catolics, 23 Silla Valencia 46460",
    "addr:housenumber":"23",
    "addr:postcode":"46460",
    "addr:street":"Catolics",
    "iso:country":"ES",
    "sg:address":"Avgd Reis Catolics, 23",
    "sg:city":"Silla",
    "sg:orig_category":"Sociedades, Compa\u00d1\u00cdas Aseguradoras",
    "sg:phone":"+34 961 21 06 70",
    "sg:postcode":"46460",
    "sg:province":"Valencia",
    "wof:name":"Futur Casa 2000 Silla S.l.",
    "wof:placetype":"venue"
},
  "geometry": {"coordinates":[-0.4090488851,39.3660812378],"type":"Point"}
}