{
  "type": "Feature",
  "properties": {
    "addr:full":"Carr Ballesteries, 3 Girona Girona 17003",
    "addr:housenumber":"3",
    "addr:postcode":"17003",
    "addr:street":"Carr Ballesteries",
    "iso:country":"ES",
    "sg:address":"Carr Ballesteries, 3",
    "sg:city":"Girona",
    "sg:orig_category":"Ropa Para Se\u00d1oras (al Por Menor)",
    "sg:phone":"+34 972 21 75 95",
    "sg:postcode":"17003",
    "sg:province":"Girona",
    "wof:name":"Laserna Manzanedo Oscar",
    "wof:placetype":"venue"
},
  "geometry": {"coordinates":[2.8187448978,41.9808616638],"type":"Point"}
}