{
  "type": "Feature",
  "properties": {
    "iso:country":"ES",
    "sg:address":"Plaz Victoria De (la), 1",
    "sg:city":"Marbella",
    "sg:orig_category":"Caf\u00c9s, Bares, Cervecer\u00cdas",
    "sg:phone":"+34 951 31 70 81",
    "sg:postcode":"29600",
    "sg:province":"M\u00e1laga",
    "wof:name":"Tutto Un Fiore S.l",
    "wof:placetype":"venue"
},
  "geometry": {"coordinates":[-4.8833007812,36.5079956055],"type":"Point"}
}