{
  "type": "Feature",
  "properties": {
    "addr:full":"Carr Obispo Mu\u00d1oz, 52 Burjassot Valencia 46100",
    "addr:housenumber":"52",
    "addr:postcode":"46100",
    "addr:street":"Carr Obispo Mun\u0303Oz",
    "iso:country":"ES",
    "sg:address":"Carr Obispo Mu\u00d1oz, 52",
    "sg:city":"Burjassot",
    "sg:orig_category":"Asociaciones, Organismos Culturales Y Socioeducativos",
    "sg:phone":"+34 963 64 04 53",
    "sg:postcode":"46100",
    "sg:province":"Valencia",
    "wof:name":"Asociacion Cultural Bassot S.r.c.",
    "wof:placetype":"venue"
},
  "geometry": {"coordinates":[-0.4092775881,39.5071334839],"type":"Point"}
}