{
  "type": "Feature",
  "properties": {
    "addr:full":"Ctra Malaga (de), 27 Granada Granada 18015",
    "addr:housenumber":"27",
    "addr:postcode":"18015",
    "addr:street":"Ctra Malaga De",
    "iso:country":"ES",
    "sg:address":"Ctra Malaga (de), 27",
    "sg:city":"Granada",
    "sg:orig_category":"Peluqueros: De Se\u00d1oras",
    "sg:phone":"+34 958 29 35 36",
    "sg:postcode":"18015",
    "sg:province":"Granada",
    "wof:name":"Romera Fernandez Silvia",
    "wof:placetype":"venue"
},
  "geometry": {"coordinates":[-3.6235990524,37.1894683838],"type":"Point"}
}