{
  "type": "Feature",
  "properties": {
    "addr:full":"Calle de Oviedo, 48 Merida Badajoz 06800",
    "addr:housenumber":"48",
    "addr:postcode":"06800",
    "addr:street":"Calle De Oviedo",
    "iso:country":"ES",
    "sg:address":"Calle de Oviedo, 48",
    "sg:city":"Merida",
    "sg:orig_category":"Alimentaci\u00d3n: Aditivos, Esencias Alimentarias, Levaduras (fabricaci\u00d3n, Al Por Mayor)",
    "sg:phone":"+34 924 33 06 37",
    "sg:postcode":"06800",
    "sg:province":"Badajoz",
    "wof:name":"Comercial Barroso Llamas S.l.",
    "wof:placetype":"venue"
},
  "geometry": {"coordinates":[-6.3428168297,38.911907196],"type":"Point"}
}