{
  "type": "Feature",
  "properties": {
    "addr:full":"Avda Monforte De Lemos, S/n Madrid Madrid 28029",
    "addr:housenumber":"s / n",
    "addr:postcode":"28029",
    "addr:street":"Avda Monforte De Lemos",
    "iso:country":"ES",
    "sg:address":"Avda Monforte De Lemos, S/n",
    "sg:city":"Madrid",
    "sg:orig_category":"Ropa Para Se\u00d1oras Y Caballeros (al Por Menor)",
    "sg:phone":"+34 917 39 53 02",
    "sg:postcode":"28029",
    "sg:province":"Madrid",
    "sg:website":"www.lacoste.es",
    "wof:name":"Matma S.a.",
    "wof:placetype":"venue"
},
  "geometry": {"coordinates":[-3.7155539989,40.4773712158],"type":"Point"}
}