{
  "type": "Feature",
  "properties": {
    "iso:country":"ES",
    "sg:address":"Calle de Oria Casta\u00d1eda, 28",
    "sg:city":"Lepe",
    "sg:orig_category":"Charcuter\u00cdas (al Por Mayor)",
    "sg:phone":"+34 959 38 03 93",
    "sg:postcode":"21440",
    "sg:province":"Huelva",
    "wof:name":"Casta\u00f1o Gomez Tomas",
    "wof:placetype":"venue"
},
  "geometry": {"coordinates":[-7.2031989098,37.2535095215],"type":"Point"}
}