{
  "type": "Feature",
  "properties": {
    "iso:country":"ES",
    "sg:address":"Calle de Arroyo De Las Pilillas, 52",
    "sg:city":"Madrid",
    "sg:orig_category":"Tintes (fabricaci\u00d3n, Al Por Mayor)",
    "sg:phone":"+34 914 30 09 46",
    "sg:postcode":"28030",
    "sg:province":"Madrid",
    "wof:name":"Ricote Lerin Pedro Jose",
    "wof:placetype":"venue"
},
  "geometry": {"coordinates":[-3.6514360905,40.4077987671],"type":"Point"}
}