{
  "type": "Feature",
  "properties": {
    "addr:full":"Poli Industrial 1 De Mayo, S/n Miajadas C\u00e1ceres 10100",
    "addr:housenumber":"s / n",
    "addr:postcode":"10100",
    "addr:street":"Mayo;Ca\u0301Ceres",
    "iso:country":"ES",
    "sg:address":"Poli Industrial 1 De Mayo, S/n",
    "sg:city":"Miajadas",
    "sg:orig_category":"Ferreter\u00cda (diversos)",
    "sg:phone":"+34 927 34 50 79",
    "sg:postcode":"10100",
    "sg:province":"C\u00e1ceres",
    "wof:name":"Hierros Y Ferrallas Miajadas S.l.",
    "wof:placetype":"venue"
},
  "geometry": {"coordinates":[-5.9304037094,39.1388778687],"type":"Point"}
}