{
  "type": "Feature",
  "properties": {
    "iso:country":"ES",
    "sg:address":"Carrer de Calabria, 13",
    "sg:city":"Garriga",
    "sg:classifiers":[
        {
            "category":"Cinema",
            "subcategory":"Movie Theater",
            "type":"Entertainment"
        }
    ],
    "sg:phone":"+34 938 71 61 11",
    "sg:postcode":"08530",
    "sg:province":"Barcelona",
    "sg:tags":[
        "salas",
        "de",
        "cine"
    ],
    "wof:name":"Miro Casula Jose Maria",
    "wof:placetype":"venue"
},
  "geometry": {"coordinates":[2.2853980064,41.6861686707],"type":"Point"}
}