{
  "type": "Feature",
  "properties": {
    "iso:country":"ES",
    "sg:address":"Nevero Doce, 19",
    "sg:city":"Badajoz",
    "sg:orig_category":"Maquinaria Para Industrias Diversas",
    "sg:phone":"+34 924 22 71 81",
    "sg:postcode":"06006",
    "sg:province":"Badajoz",
    "sg:website":"www.trademaquinaria.com",
    "wof:name":"Trade Maquinaria S.l.",
    "wof:placetype":"venue"
},
  "geometry": {"coordinates":[-6.9969129562,38.8958969116],"type":"Point"}
}