{
  "type": "Feature",
  "properties": {
    "iso:country":"ES",
    "sg:address":"Avda Club Deportivo, 43",
    "sg:city":"Logro\u00f1o",
    "sg:orig_category":"Cr\u00cda De Animales",
    "sg:phone":"+34 941 51 03 15",
    "sg:postcode":"26007",
    "sg:province":"La Rioja",
    "wof:name":"Herce Santolaya Jose Antonio",
    "wof:placetype":"venue"
},
  "geometry": {"coordinates":[-2.4607350826,42.4578170776],"type":"Point"}
}