{
  "type": "Feature",
  "properties": {
    "iso:country":"ES",
    "sg:address":"Carrer de Industria, 19",
    "sg:city":"Buvisa",
    "sg:orig_category":"Fabricaci\u00d3n De Etiquetas",
    "sg:phone":"+34 935 40 75 40",
    "sg:postcode":"08329",
    "sg:province":"Barcelona",
    "sg:website":"www.generaletiquetaje.com",
    "wof:name":"General De Etiquetaje S.a.",
    "wof:placetype":"venue"
},
  "geometry": {"coordinates":[2.3216049671,41.4981689453],"type":"Point"}
}