{
  "type": "Feature",
  "properties": {
    "iso:country":"ES",
    "sg:address":"Pl Tereses (de Les), 5",
    "sg:city":"Mataro",
    "sg:orig_category":"Abogados",
    "sg:phone":"+34 937 90 63 85",
    "sg:postcode":"08302",
    "sg:province":"Barcelona",
    "wof:name":"Quintian Rodriguez Cesar Ramon",
    "wof:placetype":"venue"
},
  "geometry": {"coordinates":[2.4424829483,41.5388832092],"type":"Point"}
}