{
  "type": "Feature",
  "properties": {
    "iso:country":"ES",
    "sg:address":"Calle de Rio Jalon, 1",
    "sg:city":"Mostoles",
    "sg:orig_category":"Papel (al Por Mayor)",
    "sg:phone":"+34 916 47 11 69",
    "sg:postcode":"28935",
    "sg:province":"Madrid",
    "wof:name":"Comercial Roelmar S.l.",
    "wof:placetype":"venue"
},
  "geometry": {"coordinates":[-3.8792901039,40.3130073547],"type":"Point"}
}