{
  "type": "Feature",
  "properties": {
    "iso:country":"ES",
    "sg:address":"Calle de Juana De Vega, 13",
    "sg:city":"Coru\u00d1a",
    "sg:orig_category":"Psic\u00d3logos",
    "sg:phone":"+34 981 22 25 96",
    "sg:postcode":"15004",
    "sg:province":"La Coru\u00f1a",
    "wof:name":"Gutierrez-moyano Zimmermann Mercedes",
    "wof:placetype":"venue"
},
  "geometry": {"coordinates":[-8.4055738449,43.3666343689],"type":"Point"}
}