{
  "type": "Feature",
  "properties": {
    "addr:full":"Pg Cordelles, 20 Cerdanyola Valles Barcelona 08290",
    "addr:housenumber":"20",
    "addr:postcode":"08290",
    "addr:street":"Pg Cordelles;Valles Barcelona",
    "iso:country":"ES",
    "sg:address":"Pg Cordelles, 20",
    "sg:city":"Cerdanyola Valles",
    "sg:orig_category":"Diarios, Prensa, Revistas (al Por Menor)",
    "sg:phone":"+34 936 92 34 89",
    "sg:postcode":"08290",
    "sg:province":"Barcelona",
    "wof:name":"Sanchis Guevara Maria",
    "wof:placetype":"venue"
},
  "geometry": {"coordinates":[2.1396930218,41.4923973083],"type":"Point"}
}