{
  "type": "Feature",
  "properties": {
    "iso:country":"ES",
    "sg:address":"Plaz Armas, 7",
    "sg:city":"Alburquerque",
    "sg:orig_category":"Agricultores, Agricultores",
    "sg:phone":"+34 924 40 05 02",
    "sg:postcode":"06510",
    "sg:province":"Badajoz",
    "wof:name":"Tarrat Vadillo Carlos",
    "wof:placetype":"venue"
},
  "geometry": {"coordinates":[-7.0021080971,39.2196922302],"type":"Point"}
}