{
  "type": "Feature",
  "properties": {
    "iso:country":"ES",
    "sg:address":"Calle de Antonio Machado, 69",
    "sg:city":"Albacete",
    "sg:orig_category":"Prot\u00c9sicos Dentales",
    "sg:phone":"+34 967 23 85 62",
    "sg:postcode":"02004",
    "sg:province":"Albacete",
    "wof:name":"Parra Martinez Antonio",
    "wof:placetype":"venue"
},
  "geometry": {"coordinates":[-1.8637440205,38.9912452698],"type":"Point"}
}