{
  "type": "Feature",
  "properties": {
    "iso:country":"ES",
    "sg:address":"Iglesia, 8",
    "sg:city":"Sta. Eularia Riu",
    "sg:orig_category":"Empresas De Limpieza",
    "sg:phone":"+34 971 33 19 19",
    "sg:postcode":"07840",
    "sg:province":"Islas Baleares",
    "wof:name":"Limpiezas Es Vedra S.l.",
    "wof:placetype":"venue"
},
  "geometry": {"coordinates":[1.5317820311,38.9847869873],"type":"Point"}
}