{
  "type": "Feature",
  "properties": {
    "addr:full":"Calle de Centro, 5 Zaragoza Zaragoza 50009",
    "addr:housenumber":"5",
    "addr:postcode":"50009",
    "addr:street":"Calle De Centro",
    "iso:country":"ES",
    "sg:address":"Calle de Centro, 5",
    "sg:city":"Zaragoza",
    "sg:orig_category":"Tintorer\u00cdas, Limpieza En Seco",
    "sg:phone":"+34 976 56 21 39",
    "sg:postcode":"50009",
    "sg:province":"Zaragoza",
    "wof:name":"Blanque Fustero Mercedes",
    "wof:placetype":"venue"
},
  "geometry": {"coordinates":[-0.9085080028,41.6320266724],"type":"Point"}
}