{
  "type": "Feature",
  "properties": {
    "addr:full":"Calle de Hilera, 6 Malaga M\u00e1laga 29007",
    "addr:housenumber":"6",
    "addr:postcode":"29007",
    "addr:street":"Calle De Hilera;Ma\u0301Laga",
    "iso:country":"ES",
    "sg:address":"Calle de Hilera, 6",
    "sg:city":"Malaga",
    "sg:orig_category":"Fabricaci\u00d3n De Sobres, Bolsas Y Fundas",
    "sg:phone":"+34 952 61 12 68",
    "sg:postcode":"29007",
    "sg:province":"M\u00e1laga",
    "wof:name":"Arjona Gonzalez Maria Jose",
    "wof:placetype":"venue"
},
  "geometry": {"coordinates":[-4.4290409088,36.7178764343],"type":"Point"}
}