{
  "type": "Feature",
  "properties": {
    "iso:country":"ES",
    "sg:address":"Calle de Muro De Francisco De La Mata, 1",
    "sg:city":"Logro\u00f1o",
    "sg:orig_category":"Cajas De Ahorro",
    "sg:phone":"+34 941 25 24 22",
    "sg:postcode":"26001",
    "sg:province":"La Rioja",
    "wof:name":"Caja De Ahorros Y Monte De Piedad De Zaragoza Aragon Y Rioja",
    "wof:placetype":"venue"
},
  "geometry": {"coordinates":[-2.4464850426,42.4653968811],"type":"Point"}
}