{
  "type": "Feature",
  "properties": {
    "addr:full":"Avda Aresti Gabriel, 16 Bilbao Vizcaya 48004",
    "addr:housenumber":"16",
    "addr:postcode":"48004",
    "addr:street":"Avda Aresti Gabriel",
    "iso:country":"ES",
    "sg:address":"Avda Aresti Gabriel, 16",
    "sg:city":"Bilbao",
    "sg:orig_category":"Muebles, Minoristas",
    "sg:phone":"+34 944 11 47 05",
    "sg:postcode":"48004",
    "sg:province":"Vizcaya",
    "wof:name":"Mugarri Mobiliario S.l.",
    "wof:placetype":"venue"
},
  "geometry": {"coordinates":[-2.9068470001,43.2582244873],"type":"Point"}
}