{
  "type": "Feature",
  "properties": {
    "iso:country":"ES",
    "sg:address":"C/ 9, 88",
    "sg:city":"Ca\u00d1ada",
    "sg:orig_category":"Diplomas Diversos",
    "sg:phone":"+34 961 32 06 92",
    "sg:postcode":"46182",
    "sg:province":"Valencia",
    "wof:name":"Montalva Conesa Jose Luis",
    "wof:placetype":"venue"
},
  "geometry": {"coordinates":[-0.4852339923,39.5221443176],"type":"Point"}
}