{
  "type": "Feature",
  "properties": {
    "iso:country":"ES",
    "sg:address":"Bo Galarza, 5",
    "sg:city":"Galartza",
    "sg:orig_category":"Fabricaci\u00d3n De Ventanas",
    "sg:phone":"+34 946 16 60 56",
    "sg:postcode":"48277",
    "sg:province":"Vizcaya",
    "wof:name":"Terrazos Iriondo S. A.",
    "wof:placetype":"venue"
},
  "geometry": {"coordinates":[-2.4781939983,43.2544898987],"type":"Point"}
}