{
  "type": "Feature",
  "properties": {
    "addr:full":"Plaz Sagrado Corazon De Jesus, Plaza, 4 Bilbao Vizcaya 48011",
    "addr:housenumber":"4",
    "addr:postcode":"48011",
    "iso:country":"ES",
    "sg:address":"Plaz Sagrado Corazon De Jesus, Plaza, 4",
    "sg:city":"Bilbao",
    "sg:orig_category":"Agencias Y Agentes Comerciales, Representantes",
    "sg:phone":"+34 944 27 63 27",
    "sg:postcode":"48011",
    "sg:province":"Vizcaya",
    "wof:name":"Martin Mateo Domingo Luis",
    "wof:placetype":"venue"
},
  "geometry": {"coordinates":[-2.9455618858,43.2655982971],"type":"Point"}
}