{
  "type": "Feature",
  "properties": {
    "iso:country":"ES",
    "sg:address":"Carr Sota Cami, S/n",
    "sg:city":"Ma\u00e7anet Selva",
    "sg:orig_category":"Electrodom\u00c9sticos (al Por Menor)",
    "sg:phone":"+34 972 85 82 30",
    "sg:postcode":"17412",
    "sg:province":"Girona",
    "wof:name":"Soler Garcia Virginia",
    "wof:placetype":"venue"
},
  "geometry": {"coordinates":[2.7342700958,41.7778396606],"type":"Point"}
}