{
  "type": "Feature",
  "properties": {
    "iso:country":"ES",
    "sg:address":"Calle de Nicolas Sanchez, 57",
    "sg:city":"Madrid",
    "sg:orig_category":"Electricidad, Electr\u00d3nica: Material Y Suministros (al Por Mayor)",
    "sg:phone":"+34 913 92 01 03",
    "sg:postcode":"28026",
    "sg:province":"Madrid",
    "wof:name":"Covamani S.l.",
    "wof:placetype":"venue"
},
  "geometry": {"coordinates":[-3.7058010101,40.3839187622],"type":"Point"}
}