{
  "type": "Feature",
  "properties": {
    "addr:full":"Av Generalitat, 59 Santa Coloma De Gramenet Barcelona 08922",
    "addr:housenumber":"59",
    "addr:postcode":"08922",
    "addr:street":"Av Generalitat",
    "iso:country":"ES",
    "sg:address":"Av Generalitat, 59",
    "sg:city":"Santa Coloma De Gramenet",
    "sg:orig_category":"Bancos",
    "sg:phone":"+34 933 85 54 02",
    "sg:postcode":"08922",
    "sg:province":"Barcelona",
    "sg:website":"www.bancopopular.es",
    "wof:name":"Banco Popular Espa\u00f1ol S.a.",
    "wof:placetype":"venue"
},
  "geometry": {"coordinates":[2.2109589577,41.4469795227],"type":"Point"}
}