{
  "type": "Feature",
  "properties": {
    "iso:country":"ES",
    "sg:address":"Calle de Deire, 2",
    "sg:city":"Torrox",
    "sg:orig_category":"Cristaler\u00cdas",
    "sg:phone":"+34 952 53 85 65",
    "sg:postcode":"29770",
    "sg:province":"M\u00e1laga",
    "wof:name":"Reyes Bravo Gabriel",
    "wof:placetype":"venue"
},
  "geometry": {"coordinates":[-3.9572374821,36.7701911926],"type":"Point"}
}