{
  "type": "Feature",
  "properties": {
    "iso:country":"ES",
    "sg:address":"Ctra Alca\u00d1iz, S/n",
    "sg:city":"Teruel",
    "sg:orig_category":"Asociaciones, Organismos Culturales Y Socioeducativos",
    "sg:phone":"+34 978 60 86 87",
    "sg:postcode":"44003",
    "sg:province":"Teruel",
    "wof:name":"Asociacion Cultural Banda De Musica Santa Cecilia Escuela De Musica",
    "wof:placetype":"venue"
},
  "geometry": {"coordinates":[-1.1083253622,40.3553962708],"type":"Point"}
}