{
  "type": "Feature",
  "properties": {
    "addr:full":"Calle de Diego De Leon, 61 Madrid Madrid 28006",
    "addr:housenumber":"61",
    "addr:postcode":"madrid;28006",
    "addr:street":"Calle De Diego De Leon",
    "iso:country":"ES",
    "sg:address":"Calle de Diego De Leon, 61",
    "sg:city":"Madrid",
    "sg:orig_category":"Electricidad: Instaladores",
    "sg:phone":"+34 914 02 82 25",
    "sg:postcode":"28006",
    "sg:province":"Madrid",
    "wof:name":"Sanz Navas Guillermo",
    "wof:placetype":"venue"
},
  "geometry": {"coordinates":[-3.6757400036,40.4347038269],"type":"Point"}
}