{
  "type": "Feature",
  "properties": {
    "addr:full":"Bizkaia Kalea, 2 Zarautz Guip\u00f9zcoa 20800",
    "addr:housenumber":"2",
    "addr:postcode":"20800",
    "addr:street":"Bizkaia Kalea;Guipu\u0300Zcoa",
    "iso:country":"ES",
    "sg:address":"Bizkaia Kalea, 2",
    "sg:city":"Zarautz",
    "sg:orig_category":"Venta, Alquiler De Instrumentos Y Accesorios De M\u00dasica",
    "sg:phone":"+34 943 01 09 03",
    "sg:postcode":"20800",
    "sg:province":"Guip\u00f9zcoa",
    "wof:name":"Alboka Salmenta Eta Konponketak, S.l.",
    "wof:placetype":"venue"
},
  "geometry": {"coordinates":[-2.1768000126,43.2836685181],"type":"Point"}
}