{
  "type": "Feature",
  "properties": {
    "iso:country":"ES",
    "sg:address":"Ptge Pau (de La), 3",
    "sg:city":"Creixell",
    "sg:orig_category":"Bisuter\u00cda, Joyer\u00cda, Relojer\u00cda (al Por Menor)",
    "sg:phone":"+34 977 80 08 47",
    "sg:postcode":"43839",
    "sg:province":"Tarragona",
    "wof:name":"Jofre Carbonell Josep",
    "wof:placetype":"venue"
},
  "geometry": {"coordinates":[1.4411480427,41.1675720215],"type":"Point"}
}