{
  "type": "Feature",
  "properties": {
    "iso:country":"ES",
    "sg:address":"Calle de Santa Maria, 11",
    "sg:city":"Portugalete",
    "sg:orig_category":"Molduras, Junquillos, Listones Y Molduras Perforadas",
    "sg:phone":"+34 944 96 10 54",
    "sg:postcode":"48920",
    "sg:province":"Vizcaya",
    "wof:name":"Lopez Santamaria Miguel Angel",
    "wof:placetype":"venue"
},
  "geometry": {"coordinates":[-3.0172889233,43.3204612732],"type":"Point"}
}