{
  "type": "Feature",
  "properties": {
    "addr:full":"Calle de Juan Carlos I, 2 Arenales De San Gregorio Ciudad Real 13619",
    "addr:housenumber":"2",
    "addr:postcode":"13619",
    "addr:street":"Calle De Juan Carlos I",
    "iso:country":"ES",
    "sg:address":"Calle de Juan Carlos I, 2",
    "sg:city":"Arenales De San Gregorio",
    "sg:orig_category":"Sindicatos De Trabajadores",
    "sg:phone":"+34 926 58 40 39",
    "sg:postcode":"13619",
    "sg:province":"Ciudad Real",
    "wof:name":"Grupo Sindical San Pedro",
    "wof:placetype":"venue"
},
  "geometry": {"coordinates":[-3.0267109871,39.3090133667],"type":"Point"}
}