{
  "type": "Feature",
  "properties": {
    "iso:country":"ES",
    "sg:address":"Avda Mediterraneo (del), 139",
    "sg:city":"Rincon Victoria",
    "sg:orig_category":"Inmobiliaria (agencias)",
    "sg:phone":"+34 952 40 33 22",
    "sg:postcode":"29730",
    "sg:province":"M\u00e1laga",
    "wof:name":"Asesoramiento Inmobiliarios Rincon S.l.",
    "wof:placetype":"venue"
},
  "geometry": {"coordinates":[-4.2832584381,36.7148780823],"type":"Point"}
}