{
  "type": "Feature",
  "properties": {
    "iso:country":"ES",
    "sg:address":"Cmno Valderribas, 112",
    "sg:city":"Madrid",
    "sg:orig_category":"Charcuter\u00cdas (al Por Mayor)",
    "sg:phone":"+34 914 30 36 33",
    "sg:postcode":"28038",
    "sg:province":"Madrid",
    "wof:name":"Merino Perez David",
    "wof:placetype":"venue"
},
  "geometry": {"coordinates":[-3.65823102,40.3981132507],"type":"Point"}
}