{
  "type": "Feature",
  "properties": {
    "addr:full":"Ajimez, 4 Sevilla Sevilla 41008",
    "addr:housenumber":"4",
    "addr:postcode":"41008",
    "addr:street":"Ajimez",
    "iso:country":"ES",
    "sg:address":"Ajimez, 4",
    "sg:city":"Sevilla",
    "sg:orig_category":"Limpieza Industrial",
    "sg:phone":"+34 954 95 29 23",
    "sg:postcode":"41008",
    "sg:province":"Sevilla",
    "wof:name":"Lymanco S.l.",
    "wof:placetype":"venue"
},
  "geometry": {"coordinates":[-5.9673728943,37.4105834961],"type":"Point"}
}