{
  "type": "Feature",
  "properties": {
    "iso:country":"ES",
    "sg:address":"Calle de Jose Hernandez Alfonso, 16",
    "sg:city":"Santa Cruz De Tenerife",
    "sg:orig_category":"Loter\u00cda Y T\u00d3mbola",
    "sg:phone":"+34 922 20 28 86",
    "sg:postcode":"38003",
    "sg:province":"Santa Cruz De Tenerife",
    "wof:name":"Organizacion Impulsora De Discapacitados O.i.d.",
    "wof:placetype":"venue"
},
  "geometry": {"coordinates":[-16.2532539368,28.4618301392],"type":"Point"}
}