{
  "type": "Feature",
  "properties": {
    "iso:country":"ES",
    "sg:address":"Calle de Aljibico, 10",
    "sg:city":"Jumilla",
    "sg:orig_category":"Arreglo, Reparaci\u00d3n, Piezas Sueltas De Televisi\u00d3n, V\u00cddeo, Hi",
    "sg:phone":"+34 968 78 26 15",
    "sg:postcode":"30520",
    "sg:province":"Murcia",
    "wof:name":"Mu\u00f1oz Bernal Juan",
    "wof:placetype":"venue"
},
  "geometry": {"coordinates":[-1.3286337852,38.4741668701],"type":"Point"}
}