{
  "type": "Feature",
  "properties": {
    "iso:country":"ES",
    "sg:address":"Crta. Eivissa Portinatx, Km. 0002,3",
    "sg:city":"Puig D'en Valls",
    "sg:orig_category":"Autob\u00das (explotaci\u00d3n Y Servicios De)",
    "sg:phone":"+34 971 31 16 62",
    "sg:postcode":"07819",
    "sg:province":"Islas Baleares",
    "wof:name":"Herederos De Francisco Vilas S.a.",
    "wof:placetype":"venue"
},
  "geometry": {"coordinates":[1.4312162399,38.9264984131],"type":"Point"}
}