{
  "type": "Feature",
  "properties": {
    "iso:country":"ES",
    "sg:address":"Avda Madrid De, Km. 0434,0",
    "sg:city":"Fraga",
    "sg:orig_category":"Agentes, Concesionarios Y Sucursales De Veh\u00cdculos",
    "sg:phone":"+34 974 47 04 12",
    "sg:postcode":"22520",
    "sg:province":"Huesca",
    "wof:name":"Les S. L.",
    "wof:placetype":"venue"
},
  "geometry": {"coordinates":[0.3438299894,41.5223045349],"type":"Point"}
}