{
  "type": "Feature",
  "properties": {
    "iso:country":"ES",
    "sg:address":"Velilla, S/n",
    "sg:city":"Ures Medina",
    "sg:orig_category":"Agricultores, Agricultores",
    "sg:phone":"+34 975 18 22 18",
    "sg:postcode":"42249",
    "sg:province":"Soria",
    "wof:name":"Majadillas Verdes S.l.",
    "wof:placetype":"venue"
},
  "geometry": {"coordinates":[-2.46916008,41.7646484375],"type":"Point"}
}