{
  "type": "Feature",
  "properties": {
    "iso:country":"ES",
    "sg:address":"Av Al Andalus, S/n",
    "sg:city":"Sanlucar",
    "sg:orig_category":"Lavado, Limpieza De Veh\u00cdculos",
    "sg:phone":"+34 956 36 09 33",
    "sg:postcode":"11540",
    "sg:province":"C\u00e1diz",
    "wof:name":"Mesa Caro Ana Maria",
    "wof:placetype":"venue"
},
  "geometry": {"coordinates":[-6.3411121368,36.7817001343],"type":"Point"}
}