{
  "type": "Feature",
  "properties": {
    "addr:full":"Calle de Alegria, 10 Madrid Madrid 28025",
    "addr:housenumber":"10",
    "addr:postcode":"madrid;28025",
    "addr:street":"Calle De Alegria",
    "iso:country":"ES",
    "sg:address":"Calle de Alegria, 10",
    "sg:city":"Madrid",
    "sg:orig_category":"Quincaller\u00cda (al Por Menor)",
    "sg:phone":"+34 914 66 20 92",
    "sg:postcode":"28025",
    "sg:province":"Madrid",
    "sg:website":"www.bronzaku.com",
    "wof:name":"Bronzaku S.l.",
    "wof:placetype":"venue"
},
  "geometry": {"coordinates":[-3.7326285839,40.3851661682],"type":"Point"}
}