{
  "type": "Feature",
  "properties": {
    "addr:full":"Calle de Hierro, 22 Villa Rio C\u00f3rdoba 14640",
    "addr:housenumber":"22",
    "addr:postcode":"14640",
    "addr:street":"Calle De Hierro;Rio Co\u0301Rdoba",
    "iso:country":"ES",
    "sg:address":"Calle de Hierro, 22",
    "sg:city":"Villa Rio",
    "sg:orig_category":"Molduras, Junquillos, Listones Y Molduras Perforadas",
    "sg:phone":"+34 957 17 77 50",
    "sg:postcode":"14640",
    "sg:province":"C\u00f3rdoba",
    "wof:name":"Arenas Quesada C.b.",
    "wof:placetype":"venue"
},
  "geometry": {"coordinates":[-4.29114151,37.9813957214],"type":"Point"}
}