{
  "type": "Feature",
  "properties": {
    "addr:full":"Avda Vitoria, Km. 0001,0 Alsasua Navarra 31800",
    "addr:postcode":"31800",
    "addr:street":"Avda Vitoria Km. 0001,0",
    "iso:country":"ES",
    "sg:address":"Avda Vitoria, Km. 0001,0",
    "sg:city":"Alsasua",
    "sg:orig_category":"Mec\u00c1nico Del Autom\u00d3vil",
    "sg:phone":"+34 948 56 24 56",
    "sg:postcode":"31800",
    "sg:province":"Navarra",
    "wof:name":"Garaje Urbasa S.a.",
    "wof:placetype":"venue"
},
  "geometry": {"coordinates":[-2.1941597462,42.9304695129],"type":"Point"}
}