{
  "type": "Feature",
  "properties": {
    "iso:country":"ES",
    "sg:address":"Calle de Parroco Antonio Pardo, 2",
    "sg:city":"Santa Cruz De Mudela",
    "sg:orig_category":"Artes Gr\u00c1ficas, Artes Pl\u00c1sticas (curso)",
    "sg:phone":"+34 926 34 24 98",
    "sg:postcode":"13730",
    "sg:province":"Ciudad Real",
    "wof:name":"Grafica Valverde 94 S.l.",
    "wof:placetype":"venue"
},
  "geometry": {"coordinates":[-3.4659290314,38.6393165588],"type":"Point"}
}