{
  "type": "Feature",
  "properties": {
    "addr:full":"Carrer de Alcalde Gadea, 5 Cocentaina Alicante 03820",
    "addr:housenumber":"5",
    "addr:postcode":"03820",
    "addr:street":"Carrer De Alcalde Gadea",
    "iso:country":"ES",
    "sg:address":"Carrer de Alcalde Gadea, 5",
    "sg:city":"Cocentaina",
    "sg:orig_category":"Escayola Y Productos De Escayola (fabricaci\u00d3n, Al Por Mayor)",
    "sg:phone":"+34 965 59 21 86",
    "sg:postcode":"03820",
    "sg:province":"Alicante",
    "wof:name":"Nadal Munllor Juan",
    "wof:placetype":"venue"
},
  "geometry": {"coordinates":[-0.4366660118,38.7428436279],"type":"Point"}
}