{
  "type": "Feature",
  "properties": {
    "addr:full":"Pg Carles Padros, 12 Mataro Barcelona 08304",
    "addr:housenumber":"12",
    "addr:postcode":"08304",
    "addr:street":"Pg Carles Padros",
    "iso:country":"ES",
    "sg:address":"Pg Carles Padros, 12",
    "sg:city":"Mataro",
    "sg:orig_category":"Deportes Diversos",
    "sg:phone":"+34 937 57 35 37",
    "sg:postcode":"08304",
    "sg:province":"Barcelona",
    "wof:name":"Federacion Catalana De Futbol",
    "wof:placetype":"venue"
},
  "geometry": {"coordinates":[2.4414820671,41.548286438],"type":"Point"}
}