{
  "type": "Feature",
  "properties": {
    "addr:full":"Calle de Delgadillo, 1 Talavera Reina Toledo 45600",
    "addr:housenumber":"1",
    "addr:postcode":"45600",
    "addr:street":"Calle De Delgadillo",
    "iso:country":"ES",
    "sg:address":"Calle de Delgadillo, 1",
    "sg:city":"Talavera Reina",
    "sg:orig_category":"Ropa Para Se\u00d1oras (al Por Menor)",
    "sg:phone":"+34 925 81 92 80",
    "sg:postcode":"45600",
    "sg:province":"Toledo",
    "wof:name":"Lian Shi S.l",
    "wof:placetype":"venue"
},
  "geometry": {"coordinates":[-4.8305721283,39.9606971741],"type":"Point"}
}