{
  "type": "Feature",
  "properties": {
    "iso:country":"ES",
    "sg:address":"Calle de Lorenzo Bosquet (de), 21",
    "sg:city":"Coslada",
    "sg:orig_category":"Peluqueros: De Se\u00d1oras",
    "sg:phone":"+34 916 69 62 84",
    "sg:postcode":"28820",
    "sg:province":"Madrid",
    "wof:name":"Garcia Ruiz Maria Del Carmen",
    "wof:placetype":"venue"
},
  "geometry": {"coordinates":[-3.5379369259,40.4265556335],"type":"Point"}
}