{
  "type": "Feature",
  "properties": {
    "addr:full":"Calle de Galvez, 1 Polan Toledo 45161",
    "addr:housenumber":"1",
    "addr:postcode":"45161",
    "addr:street":"Calle De Galvez",
    "iso:country":"ES",
    "sg:address":"Calle de Galvez, 1",
    "sg:city":"Polan",
    "sg:orig_category":"Agentes, Concesionarios Y Sucursales De Veh\u00cdculos",
    "sg:phone":"+34 925 37 06 29",
    "sg:postcode":"45161",
    "sg:province":"Toledo",
    "wof:name":"Talleres Paco Illan S.l.",
    "wof:placetype":"venue"
},
  "geometry": {"coordinates":[-4.1729860306,39.7855529785],"type":"Point"}
}