{
  "type": "Feature",
  "properties": {
    "iso:country":"ES",
    "sg:address":"Calle de San Vicente El Real, 1",
    "sg:city":"Segovia",
    "sg:classifiers":[
        {
            "category":"Personal",
            "subcategory":"Barber",
            "type":"Services"
        }
    ],
    "sg:phone":"+34 921 43 19 49",
    "sg:postcode":"40003",
    "sg:province":"Segovia",
    "sg:tags":[
        "caballeros",
        "de",
        "peluqueros"
    ],
    "wof:name":"Mayo Cuellar Luis Miguel",
    "wof:placetype":"venue"
},
  "geometry": {"coordinates":[-4.1126441956,40.9549369812],"type":"Point"}
}