{
  "type": "Feature",
  "properties": {
    "addr:full":"Pla\u00c7 Constitucio, 13 Estellencs Islas Baleares 07192",
    "addr:housenumber":"13",
    "addr:postcode":"07192",
    "addr:street":"Plac\u0327 Constitucio",
    "iso:country":"ES",
    "sg:address":"Pla\u00c7 Constitucio, 13",
    "sg:city":"Estellencs",
    "sg:orig_category":"Doctores En Medicina",
    "sg:phone":"+34 971 61 85 85",
    "sg:postcode":"07192",
    "sg:province":"Islas Baleares",
    "wof:name":"Pericas Garcia Bartolome",
    "wof:placetype":"venue"
},
  "geometry": {"coordinates":[2.482268095,39.6533966064],"type":"Point"}
}