{
  "type": "Feature",
  "properties": {
    "addr:full":"F. El Realengo, S/n Rafelguaraf Valencia 46666",
    "addr:housenumber":"s / n",
    "addr:postcode":"46666",
    "addr:street":"F.",
    "iso:country":"ES",
    "sg:address":"F. El Realengo, S/n",
    "sg:city":"Rafelguaraf",
    "sg:orig_category":"Explotaci\u00d3n De Bosques",
    "sg:phone":"+34 962 58 64 61",
    "sg:postcode":"46666",
    "sg:province":"Valencia",
    "wof:name":"Explotaciones Forestales Agricolas Y Pecuarias Alavesas S.a",
    "wof:placetype":"venue"
},
  "geometry": {"coordinates":[-0.4553639889,39.0506134033],"type":"Point"}
}