{
  "type": "Feature",
  "properties": {
    "addr:full":"Calle de Constantino Lazaro, 20 Puebla Calzada Badajoz 06490",
    "addr:housenumber":"20",
    "addr:postcode":"06490",
    "addr:street":"Calle De Constantino Lazaro;Calzada Badajoz",
    "iso:country":"ES",
    "sg:address":"Calle de Constantino Lazaro, 20",
    "sg:city":"Puebla Calzada",
    "sg:orig_category":"Producci\u00d3n, Venta De Productos De Agricultura Biol\u00d3gica",
    "sg:phone":"+34 924 45 45 00",
    "sg:postcode":"06490",
    "sg:province":"Badajoz",
    "wof:name":"Sevil S. A.",
    "wof:placetype":"venue"
},
  "geometry": {"coordinates":[-6.6236538887,38.8914833069],"type":"Point"}
}