{
  "type": "Feature",
  "properties": {
    "iso:country":"ES",
    "sg:address":"Avda Carlos De Haya, 204",
    "sg:city":"Malaga",
    "sg:orig_category":"Electrodom\u00c9sticos (al Por Menor)",
    "sg:phone":"+34 952 30 97 15",
    "sg:postcode":"29010",
    "sg:province":"M\u00e1laga",
    "wof:name":"Electrodomesticos Sociedad Cooperativa Andaluza",
    "wof:placetype":"venue"
},
  "geometry": {"coordinates":[-4.4578871727,36.7252464294],"type":"Point"}
}