{
  "type": "Feature",
  "properties": {
    "addr:full":"Trva Ronda, 6 Madrid Madrid 28022",
    "addr:housenumber":"6",
    "addr:postcode":"28022",
    "addr:street":"Trva Ronda",
    "iso:country":"ES",
    "sg:address":"Trva Ronda, 6",
    "sg:city":"Madrid",
    "sg:orig_category":"Artesan\u00cda Y Trabajos Manuales: Suministros (al Por Menor)",
    "sg:phone":"+34 917 75 71 16",
    "sg:postcode":"28022",
    "sg:province":"Madrid",
    "wof:name":"Caballero Fernandez Dolores",
    "wof:placetype":"venue"
},
  "geometry": {"coordinates":[-3.608620882,40.4320335388],"type":"Point"}
}