{
  "type": "Feature",
  "properties": {
    "iso:country":"ES",
    "sg:address":"Avda Republica Argentina, S/n",
    "sg:city":"Sevilla",
    "sg:orig_category":"Equipo Y Material Deportivo Y De Actividades Invernales Y De Monta\u00d1a",
    "sg:phone":"+34 954 45 40 85",
    "sg:postcode":"41011",
    "sg:province":"Sevilla",
    "wof:name":"Instituto Municipal De Deportes De Sevilla",
    "wof:placetype":"venue"
},
  "geometry": {"coordinates":[-5.9985790253,37.3795661926],"type":"Point"}
}