{
  "type": "Feature",
  "properties": {
    "iso:country":"ES",
    "sg:address":"Calle de Torres, 30",
    "sg:city":"Valencia",
    "sg:orig_category":"Peluquer\u00cdas, Peluquer\u00cda Mixta",
    "sg:phone":"+34 963 50 35 38",
    "sg:postcode":"46018",
    "sg:province":"Valencia",
    "wof:name":"Francisco Pulido Estilistas S.l.",
    "wof:placetype":"venue"
},
  "geometry": {"coordinates":[-0.3991259933,39.4722900391],"type":"Point"}
}