{
  "type": "Feature",
  "properties": {
    "addr:full":"Calle de Platero Lucas Valdes, 2 Cordoba C\u00f3rdoba 14007",
    "addr:housenumber":"2",
    "addr:postcode":"14007",
    "addr:street":"Calle De Platero Lucas Valdes;Co\u0301Rdoba",
    "iso:country":"ES",
    "sg:address":"Calle de Platero Lucas Valdes, 2",
    "sg:city":"Cordoba",
    "sg:orig_category":"Bisuteros (fabricaci\u00d3n, Al Por Mayor)",
    "sg:phone":"+34 957 26 43 99",
    "sg:postcode":"14007",
    "sg:province":"C\u00f3rdoba",
    "wof:name":"San Francisco Joyeros S.l.",
    "wof:placetype":"venue"
},
  "geometry": {"coordinates":[-4.7656879425,37.8950157166],"type":"Point"}
}