{
  "type": "Feature",
  "properties": {
    "iso:country":"ES",
    "sg:address":"Carrer de Ca\u00c7adors, 9",
    "sg:city":"Sant Jaume D'enveja",
    "sg:orig_category":"Empresarios",
    "sg:phone":"+34 977 46 84 62",
    "sg:postcode":"43877",
    "sg:province":"Tarragona",
    "wof:name":"Pepiol Fumado Rafael",
    "wof:placetype":"venue"
},
  "geometry": {"coordinates":[1.2599560022,41.1186828613],"type":"Point"}
}