{
  "type": "Feature",
  "properties": {
    "iso:country":"ES",
    "sg:address":"Calle de San Carlos, 30",
    "sg:city":"Alacant",
    "sg:orig_category":"Bisuter\u00cda, Joyer\u00cda, Relojer\u00cda (al Por Menor)",
    "sg:phone":"+34 965 24 20 37",
    "sg:postcode":"03012",
    "sg:province":"Alicante",
    "wof:name":"Comercial De Bisuteria Beypa S.l.",
    "wof:placetype":"venue"
},
  "geometry": {"coordinates":[-0.4839400053,38.353427887],"type":"Point"}
}