{
  "type": "Feature",
  "properties": {
    "iso:country":"ES",
    "sg:address":"Avda Zaragoza, 15",
    "sg:city":"Zuera",
    "sg:orig_category":"Transporte En General",
    "sg:phone":"+34 976 68 05 84",
    "sg:postcode":"50800",
    "sg:province":"Zaragoza",
    "wof:name":"Dagesa",
    "wof:placetype":"venue"
},
  "geometry": {"coordinates":[-0.7922030091,41.8628959656],"type":"Point"}
}