{
  "type": "Feature",
  "properties": {
    "iso:country":"ES",
    "sg:address":"Calle de Daoiz Y Velarde, 1",
    "sg:city":"Casas-iba\u00e7ez",
    "sg:orig_category":"Librer\u00cdas",
    "sg:phone":"+34 967 46 10 17",
    "sg:postcode":"02200",
    "sg:province":"Albacete",
    "wof:name":"Gomez Diaz Maria Dolores",
    "wof:placetype":"venue"
},
  "geometry": {"coordinates":[-1.4691650867,39.2869300842],"type":"Point"}
}