{
  "type": "Feature",
  "properties": {
    "addr:full":"L Da Vinci (p I Ca\u00f1amo Ii), 30 San Jose Rinconada Sevilla 41300",
    "addr:housenumber":"30",
    "addr:postcode":"41300",
    "addr:street":"L Da Vinci P;San",
    "iso:country":"ES",
    "sg:address":"L Da Vinci (p I Ca\u00f1amo Ii), 30",
    "sg:city":"San Jose Rinconada",
    "sg:orig_category":"Arquitectos",
    "sg:phone":"+34 954 79 09 14",
    "sg:postcode":"41300",
    "sg:province":"Sevilla",
    "wof:name":"Mu\u00f1oz Gonzalez Domingo",
    "wof:placetype":"venue"
},
  "geometry": {"coordinates":[-5.9434189796,37.443523407],"type":"Point"}
}