{
  "type": "Feature",
  "properties": {
    "addr:full":"Calle de Maestro Rodriguez Valdes, 11 Cabeza Buey Badajoz 06600",
    "addr:housenumber":"11",
    "addr:postcode":"06600",
    "addr:street":"Calle De Maestro Rodriguez Valdes",
    "iso:country":"ES",
    "sg:address":"Calle de Maestro Rodriguez Valdes, 11",
    "sg:city":"Cabeza Buey",
    "sg:orig_category":"Electricidad: Instaladores",
    "sg:phone":"+34 924 60 10 43",
    "sg:postcode":"06600",
    "sg:province":"Badajoz",
    "wof:name":"Montajes Electricos Sanchez-arevalo S.l.",
    "wof:placetype":"venue"
},
  "geometry": {"coordinates":[-5.224709034,38.7198181152],"type":"Point"}
}