{
  "type": "Feature",
  "properties": {
    "iso:country":"ES",
    "sg:address":"Calle de Antonio Nicolas, 45",
    "sg:city":"Sahagun",
    "sg:orig_category":"Asilos De Ancianos. Centros Privados",
    "sg:phone":"+34 987 78 00 85",
    "sg:postcode":"24320",
    "sg:province":"Le\u00f3n",
    "wof:name":"Fundacion Hogar Residencia San Jose",
    "wof:placetype":"venue"
},
  "geometry": {"coordinates":[-5.0319805145,42.3704490662],"type":"Point"}
}