{
  "type": "Feature",
  "properties": {
    "addr:full":"Calle de Antracita, 3 Madrid Madrid 28045",
    "addr:housenumber":"3",
    "addr:postcode":"28045",
    "addr:street":"Calle De Antracita",
    "iso:country":"ES",
    "sg:address":"Calle de Antracita, 3",
    "sg:city":"Madrid",
    "sg:orig_category":"Promotores Constructores",
    "sg:phone":"+34 914 67 36 19",
    "sg:postcode":"28045",
    "sg:province":"Madrid",
    "wof:name":"Bronce 2003 S.a.",
    "wof:placetype":"venue"
},
  "geometry": {"coordinates":[-3.6888370514,40.3905906677],"type":"Point"}
}