{
  "type": "Feature",
  "properties": {
    "iso:country":"ES",
    "sg:address":"Urb Casas Viejas, 176",
    "sg:city":"Urbanizacion Casas Viejas",
    "sg:orig_category":"Molduras, Junquillos, Listones Y Molduras Perforadas",
    "sg:phone":"+34 967 58 05 06",
    "sg:postcode":"02006",
    "sg:province":"Albacete",
    "wof:name":"Quilez Tomas Dionisia",
    "wof:placetype":"venue"
},
  "geometry": {"coordinates":[-1.9388129711,38.9837417603],"type":"Point"}
}