{
  "type": "Feature",
  "properties": {
    "iso:country":"ES",
    "sg:address":"Trva Bouzas Servicio Portuario, S/n",
    "sg:city":"Vigo",
    "sg:orig_category":"Congelados: Productos Alimentarios (fabricaci\u00d3n, Al Por Mayor)",
    "sg:phone":"+34 986 21 15 04",
    "sg:postcode":"36208",
    "sg:province":"Pontevedra",
    "sg:website":"www.iberconsa.es",
    "wof:name":"Iberica De Congelados S.a.",
    "wof:placetype":"venue"
},
  "geometry": {"coordinates":[-8.7529735565,42.2268791199],"type":"Point"}
}