{
  "type": "Feature",
  "properties": {
    "iso:country":"ES",
    "sg:address":"Calle de Algatocin, 9",
    "sg:city":"Malaga",
    "sg:orig_category":"Carnes De Carnicer\u00cda (al Por Mayor)",
    "sg:phone":"+34 952 23 65 67",
    "sg:postcode":"29004",
    "sg:province":"M\u00e1laga",
    "wof:name":"Productos Carnicos Burgaleses S.l.",
    "wof:placetype":"venue"
},
  "geometry": {"coordinates":[-4.4650273323,36.6807823181],"type":"Point"}
}