{
  "type": "Feature",
  "properties": {
    "iso:country":"ES",
    "sg:address":"Calle de Antillas, 2",
    "sg:city":"Puerto De Santa Maria",
    "sg:orig_category":"Bares, Piano",
    "sg:phone":"+34 956 85 67 03",
    "sg:postcode":"11500",
    "sg:province":"C\u00e1diz",
    "wof:name":"Gilabert Lopez Rafael",
    "wof:placetype":"venue"
},
  "geometry": {"coordinates":[-6.2447977066,36.59375],"type":"Point"}
}