{
  "type": "Feature",
  "properties": {
    "addr:full":"Carrer de Girona, 78 Barcelona Barcelona 08009",
    "addr:housenumber":"78",
    "addr:postcode":"08009",
    "addr:street":"Carrer De Girona",
    "iso:country":"ES",
    "sg:address":"Carrer de Girona, 78",
    "sg:city":"Barcelona",
    "sg:orig_category":"Alimentaci\u00d3n General (al Por Menor)",
    "sg:phone":"+34 932 65 02 94",
    "sg:postcode":"08009",
    "sg:province":"Barcelona",
    "wof:name":"Valladolid Escobar Digna Angela",
    "wof:placetype":"venue"
},
  "geometry": {"coordinates":[2.1705570221,41.3954544067],"type":"Point"}
}