{
  "type": "Feature",
  "properties": {
    "addr:full":"Calle de Dulzaina, 5 Madrid Madrid 28033",
    "addr:housenumber":"5",
    "addr:postcode":"28033",
    "addr:street":"Calle De Dulzaina",
    "iso:country":"ES",
    "sg:address":"Calle de Dulzaina, 5",
    "sg:city":"Madrid",
    "sg:orig_category":"Inform\u00c1tica: Mantenimiento Y Reparaci\u00d3n De Ordenadores",
    "sg:phone":"+34 913 83 32 24",
    "sg:postcode":"28033",
    "sg:province":"Madrid",
    "sg:website":"www.kabel.es",
    "wof:name":"Kabel Sistemas De Informacion S.l.",
    "wof:placetype":"venue"
},
  "geometry": {"coordinates":[-3.6633517742,40.4810943604],"type":"Point"}
}