{
  "type": "Feature",
  "properties": {
    "iso:country":"ES",
    "sg:address":"Avda Joaquin Costa, 31",
    "sg:city":"Caspe",
    "sg:orig_category":"Plomeros",
    "sg:phone":"+34 976 63 15 09",
    "sg:postcode":"50700",
    "sg:province":"Zaragoza",
    "wof:name":"Fillola Fuster Hector",
    "wof:placetype":"venue"
},
  "geometry": {"coordinates":[-0.0396169983,41.2322425842],"type":"Point"}
}