{
  "type": "Feature",
  "properties": {
    "addr:full":"Calle de La Florida, 9 Vitoria-gasteiz \u00c1lava 01005",
    "addr:housenumber":"9",
    "addr:postcode":"01005",
    "addr:street":"Calle De La Florida",
    "iso:country":"ES",
    "sg:address":"Calle de La Florida, 9",
    "sg:city":"Vitoria-gasteiz",
    "sg:orig_category":"Arquitectos",
    "sg:phone":"+34 945 14 02 17",
    "sg:postcode":"01005",
    "sg:province":"\u00c1lava",
    "wof:name":"Altuna Olaizola Juan Cruz",
    "wof:placetype":"venue"
},
  "geometry": {"coordinates":[-2.6746242046,42.8434410095],"type":"Point"}
}