{
  "type": "Feature",
  "properties": {
    "iso:country":"ES",
    "sg:address":"Valboa, 44",
    "sg:city":"Valboa",
    "sg:orig_category":"Venta, Montaje De Neum\u00c1ticos",
    "sg:phone":"+34 986 58 78 13",
    "sg:postcode":"36584",
    "sg:province":"Pontevedra",
    "wof:name":"Neumaticos Fuentes Barreiro S.l.",
    "wof:placetype":"venue"
},
  "geometry": {"coordinates":[-8.5918922424,42.6905059814],"type":"Point"}
}