{
  "type": "Feature",
  "properties": {
    "iso:country":"ES",
    "sg:address":"Calle de Ancha, 54",
    "sg:city":"Huetor-tajar",
    "sg:orig_category":"Doctores En Medicina",
    "sg:phone":"+34 958 33 39 60",
    "sg:postcode":"18360",
    "sg:province":"Granada",
    "wof:name":"Gamiz Gordo Manuel Jesus",
    "wof:placetype":"venue"
},
  "geometry": {"coordinates":[-4.0473837852,37.1972045898],"type":"Point"}
}