{
  "type": "Feature",
  "properties": {
    "iso:country":"ES",
    "sg:address":"Avda San Jose, 1",
    "sg:city":"Gines",
    "sg:orig_category":"Inform\u00c1tica (estudios, Servicios, Asesor\u00cda, Formaci\u00d3n)",
    "sg:phone":"+34 954 71 61 55",
    "sg:postcode":"41960",
    "sg:province":"Sevilla",
    "wof:name":"Integraciones Recursos Informaticos Y Servicios S.l.",
    "wof:placetype":"venue"
},
  "geometry": {"coordinates":[-6.0776290894,37.3880081177],"type":"Point"}
}