{
  "type": "Feature",
  "properties": {
    "addr:full":"Cmno Pilar Del, 2 Cortijo De Maza-el Olivar M\u00e1laga 29140",
    "addr:housenumber":"2",
    "addr:postcode":"29140",
    "addr:street":"Cmno Pilar Del;Ma\u0301Laga",
    "iso:country":"ES",
    "sg:address":"Cmno Pilar Del, 2",
    "sg:city":"Cortijo De Maza-el Olivar",
    "sg:orig_category":"Importaci\u00d3n",
    "sg:phone":"+34 952 43 62 78",
    "sg:postcode":"29140",
    "sg:province":"M\u00e1laga",
    "wof:name":"Zhan Zhou Zhizhou",
    "wof:placetype":"venue"
},
  "geometry": {"coordinates":[-4.4920105934,36.6525764465],"type":"Point"}
}