{
  "type": "Feature",
  "properties": {
    "addr:full":"Calle de Parque (del), S/n Casas De Fernando Alonso Cuenca 16610",
    "addr:postcode":"16610",
    "addr:street":"Calle De Parque Del S / N",
    "iso:country":"ES",
    "sg:address":"Calle de Parque (del), S/n",
    "sg:city":"Casas De Fernando Alonso",
    "sg:orig_category":"Ense\u00d1anza, Formaci\u00d3n Profesional: Aprendizaje",
    "sg:phone":"+34 969 38 30 13",
    "sg:postcode":"16610",
    "sg:province":"Cuenca",
    "wof:name":"Casa De La Cultura",
    "wof:placetype":"venue"
},
  "geometry": {"coordinates":[-2.3264489174,39.3467712402],"type":"Point"}
}