{
  "type": "Feature",
  "properties": {
    "addr:full":"Av Onze De Setembre, 58 S. Boi Llobregat Barcelona 08830",
    "addr:housenumber":"58",
    "addr:postcode":"08830",
    "addr:street":"Av Onze De Setembre",
    "iso:country":"ES",
    "sg:address":"Av Onze De Setembre, 58",
    "sg:city":"S. Boi Llobregat",
    "sg:orig_category":"Alquiler De V\u00cddeo",
    "sg:phone":"+34 936 52 70 50",
    "sg:postcode":"08830",
    "sg:province":"Barcelona",
    "wof:name":"S.boi Video Digital, S.l.",
    "wof:placetype":"venue"
},
  "geometry": {"coordinates":[2.0412540436,41.3387870789],"type":"Point"}
}