{
  "type": "Feature",
  "properties": {
    "iso:country":"ES",
    "sg:address":"Carrer de Palla, 33",
    "sg:city":"Barcelona",
    "sg:orig_category":"Compraventa De Antig\u00dcedades",
    "sg:phone":"+34 933 02 44 31",
    "sg:postcode":"08002",
    "sg:province":"Barcelona",
    "wof:name":"Masip Pascual Jose",
    "wof:placetype":"venue"
},
  "geometry": {"coordinates":[2.1748819351,41.3840866089],"type":"Point"}
}