{
  "type": "Feature",
  "properties": {
    "iso:country":"ES",
    "sg:address":"Calle de Estacion, 34",
    "sg:city":"Miranda Ebro",
    "sg:orig_category":"Consultas M\u00c9dicas",
    "sg:phone":"+34 947 31 40 26",
    "sg:postcode":"09200",
    "sg:province":"Burgos",
    "wof:name":"Cornejo Martin Daniel",
    "wof:placetype":"venue"
},
  "geometry": {"coordinates":[-2.9446320534,42.6872177124],"type":"Point"}
}