{
  "type": "Feature",
  "properties": {
    "iso:country":"ES",
    "sg:address":"Avda Eusebio Sempere, 16",
    "sg:city":"Alacant",
    "sg:orig_category":"Abogados",
    "sg:phone":"+34 965 13 16 08",
    "sg:postcode":"03003",
    "sg:province":"Alicante",
    "wof:name":"Sellers Miro Luis Miguel",
    "wof:placetype":"venue"
},
  "geometry": {"coordinates":[-0.4924480021,38.3397026062],"type":"Point"}
}