{
  "type": "Feature",
  "properties": {
    "iso:country":"ES",
    "sg:address":"Carrer de Fontanella, 17",
    "sg:city":"Barcelona",
    "sg:orig_category":"Asesor\u00cda Fiscal Y Jur\u00cddica",
    "sg:phone":"+34 933 17 08 54",
    "sg:postcode":"08010",
    "sg:province":"Barcelona",
    "wof:name":"Garcia Y Maroto Asesores S.a.",
    "wof:placetype":"venue"
},
  "geometry": {"coordinates":[2.1723461151,41.3882408142],"type":"Point"}
}