{
  "type": "Feature",
  "properties": {
    "addr:full":"Calle de Rector Marin Ocete, 8 Granada Granada 18014",
    "addr:housenumber":"8",
    "addr:postcode":"18014",
    "addr:street":"Calle De Rector Marin Ocete",
    "iso:country":"ES",
    "sg:address":"Calle de Rector Marin Ocete, 8",
    "sg:city":"Granada",
    "sg:orig_category":"Producci\u00d3n, Venta De Productos De Agricultura Biol\u00d3gica",
    "sg:phone":"+34 958 27 58 85",
    "sg:postcode":"18014",
    "sg:province":"Granada",
    "wof:name":"Piedra Del Genil S.a",
    "wof:placetype":"venue"
},
  "geometry": {"coordinates":[-3.6066319942,37.1840515137],"type":"Point"}
}