{
  "type": "Feature",
  "properties": {
    "addr:full":"Calle de Acacias, 5 Getxo Vizcaya 48990",
    "addr:housenumber":"5",
    "addr:postcode":"48990",
    "addr:street":"Calle De Acacias",
    "iso:country":"ES",
    "sg:address":"Calle de Acacias, 5",
    "sg:city":"Getxo",
    "sg:orig_category":"Peluqueros: De Se\u00d1oras",
    "sg:phone":"+34 944 30 39 63",
    "sg:postcode":"48990",
    "sg:province":"Vizcaya",
    "wof:name":"Pilar Zabala Menchaca",
    "wof:placetype":"venue"
},
  "geometry": {"coordinates":[-3.0034201145,43.339805603],"type":"Point"}
}