{
  "type": "Feature",
  "properties": {
    "addr:full":"Carr Industria, 622 Badalona Barcelona 08918",
    "addr:housenumber":"622",
    "addr:postcode":"08918",
    "addr:street":"Carr Industria",
    "iso:country":"ES",
    "sg:address":"Carr Industria, 622",
    "sg:city":"Badalona",
    "sg:orig_category":"Cajas Y Embalajes Met\u00c1licos",
    "sg:phone":"+34 933 88 27 42",
    "sg:postcode":"08918",
    "sg:province":"Barcelona",
    "wof:name":"Transformaciones Metalicas Canudas S.a.",
    "wof:placetype":"venue"
},
  "geometry": {"coordinates":[2.2321031094,41.4312820435],"type":"Point"}
}