{
  "type": "Feature",
  "properties": {
    "iso:country":"ES",
    "sg:address":"Calle de San Anton, 6",
    "sg:city":"San Anton",
    "sg:orig_category":"Azafatas Para Recepciones",
    "sg:phone":"+34 968 28 57 73",
    "sg:postcode":"30009",
    "sg:province":"Murcia",
    "wof:name":"Eventos Azafatas Traducciones Y Congresos S.l.",
    "wof:placetype":"venue"
},
  "geometry": {"coordinates":[-1.1389369965,37.989238739],"type":"Point"}
}