{
  "type": "Feature",
  "properties": {
    "addr:full":"Carrer de Pujos, 94 Hospitalet Llobregat Barcelona 08904",
    "addr:housenumber":"94",
    "addr:postcode":"08904",
    "addr:street":"Carrer De Pujos",
    "iso:country":"ES",
    "sg:address":"Carrer de Pujos, 94",
    "sg:city":"Hospitalet Llobregat",
    "sg:orig_category":"Reposter\u00cdas",
    "sg:phone":"+34 934 49 26 06",
    "sg:postcode":"08904",
    "sg:province":"Barcelona",
    "wof:name":"Hospipa S.l.",
    "wof:placetype":"venue"
},
  "geometry": {"coordinates":[2.115737915,41.3722763062],"type":"Point"}
}