{
  "type": "Feature",
  "properties": {
    "addr:full":"Avda Numancia, 32 Calahorra La Rioja 26500",
    "addr:housenumber":"32",
    "addr:postcode":"26500",
    "addr:street":"Avda Numancia",
    "iso:country":"ES",
    "sg:address":"Avda Numancia, 32",
    "sg:city":"Calahorra",
    "sg:orig_category":"Abogados",
    "sg:phone":"+34 941 13 00 96",
    "sg:postcode":"26500",
    "sg:province":"La Rioja",
    "wof:name":"Administracion De Justicia",
    "wof:placetype":"venue"
},
  "geometry": {"coordinates":[-1.9681156874,42.3030929565],"type":"Point"}
}