{
  "type": "Feature",
  "properties": {
    "addr:full":"Carrer de Guayaquil, 57 Granollers Barcelona 08401",
    "addr:housenumber":"57",
    "addr:postcode":"08401",
    "addr:street":"Carrer De Guayaquil",
    "iso:country":"ES",
    "sg:address":"Carrer de Guayaquil, 57",
    "sg:city":"Granollers",
    "sg:orig_category":"Asesor\u00cda Fiscal Y Jur\u00cddica",
    "sg:phone":"+34 938 79 38 42",
    "sg:postcode":"08401",
    "sg:province":"Barcelona",
    "wof:name":"Assessoria Masip-prat S.l.",
    "wof:placetype":"venue"
},
  "geometry": {"coordinates":[2.2875638008,41.6049423218],"type":"Point"}
}