{
  "type": "Feature",
  "properties": {
    "addr:full":"Cmno Conejeras (de Las), S/n Granada Granada 18008",
    "addr:postcode":"18008",
    "addr:street":"Cmno Conejeras De Las S / N",
    "iso:country":"ES",
    "sg:address":"Cmno Conejeras (de Las), S/n",
    "sg:city":"Granada",
    "sg:orig_category":"Asociaciones Y Clubs Deportivos",
    "sg:phone":"+34 958 12 53 02",
    "sg:postcode":"18008",
    "sg:province":"Granada",
    "wof:name":"Real Sociedad De Tenis De Granada",
    "wof:placetype":"venue"
},
  "geometry": {"coordinates":[-3.5813610554,37.1587181091],"type":"Point"}
}