{
  "type": "Feature",
  "properties": {
    "iso:country":"ES",
    "sg:address":"Avda Miguel Cano, 12",
    "sg:city":"Marbella",
    "sg:orig_category":"Supermercados Y Hipermercados",
    "sg:phone":"+34 952 77 16 49",
    "sg:postcode":"29600",
    "sg:province":"M\u00e1laga",
    "wof:name":"Triplo S.a.",
    "wof:placetype":"venue"
},
  "geometry": {"coordinates":[-4.8869681358,36.5083389282],"type":"Point"}
}