{
  "type": "Feature",
  "properties": {
    "iso:country":"ES",
    "sg:address":"Calle de Cea Bermudez, 44",
    "sg:city":"Madrid",
    "sg:orig_category":"Cl\u00cdnicas M\u00c9dicas",
    "sg:phone":"+34 915 35 26 20",
    "sg:postcode":"28003",
    "sg:province":"Madrid",
    "wof:name":"Cepsim S.a.",
    "wof:placetype":"venue"
},
  "geometry": {"coordinates":[-3.7117433548,40.4390220642],"type":"Point"}
}