{
  "type": "Feature",
  "properties": {
    "iso:country":"ES",
    "sg:address":"Calle de Junquico, 9",
    "sg:city":"Caravaca Cruz",
    "sg:orig_category":"Estudios, Instalaci\u00d3n De Climatizaci\u00d3n",
    "sg:phone":"+34 968 70 09 70",
    "sg:postcode":"30400",
    "sg:province":"Murcia",
    "wof:name":"Climatizaciones Y Derivados S.l.",
    "wof:placetype":"venue"
},
  "geometry": {"coordinates":[-1.8645700216,38.104763031],"type":"Point"}
}