{
  "type": "Feature",
  "properties": {
    "addr:full":"Calle de Segadores, 6 Miguelturra Ciudad Real 13170",
    "addr:housenumber":"6",
    "addr:postcode":"13170",
    "addr:street":"Calle De Segadores",
    "iso:country":"ES",
    "sg:address":"Calle de Segadores, 6",
    "sg:city":"Miguelturra",
    "sg:orig_category":"Promotores Constructores",
    "sg:phone":"+34 926 24 22 61",
    "sg:postcode":"13170",
    "sg:province":"Ciudad Real",
    "wof:name":"Construcciones Arenas Ruiz S.l.",
    "wof:placetype":"venue"
},
  "geometry": {"coordinates":[-3.9066269398,38.9729652405],"type":"Point"}
}