{
  "type": "Feature",
  "properties": {
    "addr:full":"Calle de Rio Arba, 39 Cuarte Huerva Zaragoza 50410",
    "addr:housenumber":"39",
    "addr:postcode":"50410",
    "addr:street":"Calle De Rio Arba",
    "iso:country":"ES",
    "sg:address":"Calle de Rio Arba, 39",
    "sg:city":"Cuarte Huerva",
    "sg:orig_category":"Alquiler De Gr\u00daas",
    "sg:phone":"+34 976 50 55 44",
    "sg:postcode":"50410",
    "sg:province":"Zaragoza",
    "sg:website":"www.gruasyplataformas.com",
    "wof:name":"Gruas Y Plataformas S.l.",
    "wof:placetype":"venue"
},
  "geometry": {"coordinates":[-0.9320409894,41.5983963013],"type":"Point"}
}