{
  "type": "Feature",
  "properties": {
    "addr:full":"Calle de Moreras, 2 Majadahonda Madrid 28220",
    "addr:housenumber":"2",
    "addr:postcode":"28220",
    "addr:street":"Calle De Moreras",
    "iso:country":"ES",
    "sg:address":"Calle de Moreras, 2",
    "sg:city":"Majadahonda",
    "sg:orig_category":"Art\u00cdculos De Decoraci\u00d3n",
    "sg:phone":"+34 916 38 75 49",
    "sg:postcode":"28220",
    "sg:province":"Madrid",
    "sg:website":"www.zarahome.com",
    "wof:name":"Zara Home Espa\u00f1a S.a.",
    "wof:placetype":"venue"
},
  "geometry": {"coordinates":[-3.861030817,40.4593772888],"type":"Point"}
}