{
  "type": "Feature",
  "properties": {
    "iso:country":"ES",
    "sg:address":"Carr Castell De Solterra, 3",
    "sg:city":"Girona",
    "sg:orig_category":"Grafistas",
    "sg:phone":"+34 972 22 68 43",
    "sg:postcode":"17003",
    "sg:province":"Girona",
    "wof:name":"Cub Creacio S.c.p",
    "wof:placetype":"venue"
},
  "geometry": {"coordinates":[2.8276879787,41.9731254578],"type":"Point"}
}