{
  "type": "Feature",
  "properties": {
    "iso:country":"ES",
    "sg:address":"Calle de Berruguete, S/n",
    "sg:city":"Roquetas Mar",
    "sg:orig_category":"Comercio, Reparaci\u00d3n De Motocicletas, Bicicletas Y Piezas Sueltas",
    "sg:phone":"+34 950 33 81 24",
    "sg:postcode":"04740",
    "sg:province":"Almer\u00eda",
    "wof:name":"Martinez Hernandez Jose",
    "wof:placetype":"venue"
},
  "geometry": {"coordinates":[-2.6158349514,36.7612304688],"type":"Point"}
}