{
  "type": "Feature",
  "properties": {
    "addr:full":"Calle de Violetas, 3 Molina Segura Murcia 30500",
    "addr:housenumber":"3",
    "addr:postcode":"30500",
    "addr:street":"Calle De Violetas",
    "iso:country":"ES",
    "sg:address":"Calle de Violetas, 3",
    "sg:city":"Molina Segura",
    "sg:orig_category":"Platos Preparados Refrigerados (fabricaci\u00d3n, Al Por Mayor)",
    "sg:phone":"+34 968 64 14 10",
    "sg:postcode":"30500",
    "sg:province":"Murcia",
    "wof:name":"Gracia Gonzalez Joaquina",
    "wof:placetype":"venue"
},
  "geometry": {"coordinates":[-1.2145309448,38.0560340881],"type":"Point"}
}