{
  "type": "Feature",
  "properties": {
    "addr:full":"Carrer de Major, 19 Nucia Alicante 03530",
    "addr:housenumber":"19",
    "addr:postcode":"03530",
    "addr:street":"Carrer De Major",
    "iso:country":"ES",
    "sg:address":"Carrer de Major, 19",
    "sg:city":"Nucia",
    "sg:orig_category":"Electrodom\u00c9sticos (al Por Menor)",
    "sg:phone":"+34 966 89 55 55",
    "sg:postcode":"03530",
    "sg:province":"Alicante",
    "wof:name":"Mira Ripoll Eduardo",
    "wof:placetype":"venue"
},
  "geometry": {"coordinates":[-0.1225930005,38.6180648804],"type":"Point"}
}