{
  "type": "Feature",
  "properties": {
    "iso:country":"ES",
    "sg:address":"Calle de Zaragoza, 23",
    "sg:city":"Guadalajara",
    "sg:orig_category":"Molduras, Junquillos, Listones Y Molduras Perforadas",
    "sg:phone":"+34 949 23 00 42",
    "sg:postcode":"19005",
    "sg:province":"Guadalajara",
    "wof:name":"Merino Montes Mariano",
    "wof:placetype":"venue"
},
  "geometry": {"coordinates":[-3.1560080051,40.6346168518],"type":"Point"}
}