{
  "type": "Feature",
  "properties": {
    "iso:country":"ES",
    "sg:address":"Avda Plaza De Toros, 14",
    "sg:city":"Ecija",
    "sg:orig_category":"Frutas, Legumbres Frescas Y Tempranas (al Por Menor)",
    "sg:phone":"+34 955 90 32 71",
    "sg:postcode":"41400",
    "sg:province":"Sevilla",
    "wof:name":"Garcia Lora Jose Manuel",
    "wof:placetype":"venue"
},
  "geometry": {"coordinates":[-5.0782690048,37.5395584106],"type":"Point"}
}