{
  "type": "Feature",
  "properties": {
    "addr:full":"Calle de Nueva, 62 Estacion Madrid 28400",
    "addr:housenumber":"62 estacion",
    "addr:postcode":"28400",
    "addr:street":"Calle De Nueva",
    "iso:country":"ES",
    "sg:address":"Calle de Nueva, 62",
    "sg:city":"Estacion",
    "sg:orig_category":"Abogados",
    "sg:phone":"+34 918 51 48 27",
    "sg:postcode":"28400",
    "sg:province":"Madrid",
    "wof:name":"Monasterio Abogados S.c.",
    "wof:placetype":"venue"
},
  "geometry": {"coordinates":[-4.0152587891,40.622833252],"type":"Point"}
}