{
  "type": "Feature",
  "properties": {
    "addr:full":"Bo La Pesa, 2 Cabez\u00f3n Sal Cantabria 39500",
    "addr:housenumber":"2",
    "addr:postcode":"39500",
    "addr:street":"Bo La Pesa",
    "iso:country":"ES",
    "sg:address":"Bo La Pesa, 2",
    "sg:city":"Cabez\u00f3n Sal",
    "sg:orig_category":"Molduras, Junquillos, Listones Y Molduras Perforadas",
    "sg:phone":"+34 942 70 02 44",
    "sg:postcode":"39500",
    "sg:province":"Cantabria",
    "wof:name":"Sociedad Regional De Informatica S.a.",
    "wof:placetype":"venue"
},
  "geometry": {"coordinates":[-4.2374691963,43.3085784912],"type":"Point"}
}