{
  "type": "Feature",
  "properties": {
    "addr:full":"Avda Ventisquero De La Condesa, 40 Madrid Madrid 28035",
    "addr:housenumber":"40",
    "addr:postcode":"madrid;28035",
    "addr:street":"Avda Ventisquero De La Condesa",
    "iso:country":"ES",
    "sg:address":"Avda Ventisquero De La Condesa, 40",
    "sg:city":"Madrid",
    "sg:orig_category":"Inform\u00c1tica (estudios, Servicios, Asesor\u00cda, Formaci\u00d3n)",
    "sg:phone":"+34 917 35 28 49",
    "sg:postcode":"28035",
    "sg:province":"Madrid",
    "wof:name":"Medictyon S.a.",
    "wof:placetype":"venue"
},
  "geometry": {"coordinates":[-3.717206955,40.4938774109],"type":"Point"}
}