{
  "type": "Feature",
  "properties": {
    "addr:full":"Carrer de Beniganim, 27 Pego Alicante 03780",
    "addr:housenumber":"27",
    "addr:postcode":"03780",
    "addr:street":"Carrer De Beniganim",
    "iso:country":"ES",
    "sg:address":"Carrer de Beniganim, 27",
    "sg:city":"Pego",
    "sg:orig_category":"Maquinaria Para Industrias Diversas",
    "sg:phone":"+34 966 40 03 22",
    "sg:postcode":"03780",
    "sg:province":"Alicante",
    "wof:name":"Xl Textiles Machineri S.l.",
    "wof:placetype":"venue"
},
  "geometry": {"coordinates":[-0.1006242037,38.843082428],"type":"Point"}
}