{
  "type": "Feature",
  "properties": {
    "iso:country":"ES",
    "sg:address":"Calle de Mu\u00d1oz De La Pe\u00d1a, 4",
    "sg:city":"San Antolin",
    "sg:orig_category":"Fabricaci\u00d3n De Sobres, Bolsas Y Fundas",
    "sg:phone":"+34 968 28 56 29",
    "sg:postcode":"30005",
    "sg:province":"Murcia",
    "wof:name":"Loum Modou Mbengue",
    "wof:placetype":"venue"
},
  "geometry": {"coordinates":[-1.1382600069,37.9846763611],"type":"Point"}
}