{
  "type": "Feature",
  "properties": {
    "addr:full":"Pase Delicias, 117 Madrid Madrid 28045",
    "addr:housenumber":"117",
    "addr:postcode":"madrid;28045",
    "iso:country":"ES",
    "sg:address":"Pase Delicias, 117",
    "sg:city":"Madrid",
    "sg:orig_category":"Peluquer\u00cdas, Peluquer\u00cda Mixta",
    "sg:phone":"+34 914 67 39 06",
    "sg:postcode":"28045",
    "sg:province":"Madrid",
    "wof:name":"Ruperez Crespo Yolanda",
    "wof:placetype":"venue"
},
  "geometry": {"coordinates":[-3.6946790218,40.3932037354],"type":"Point"}
}