{
  "type": "Feature",
  "properties": {
    "addr:full":"Carrer de Concepcion Arenal, 77 Barcelona Barcelona 08027",
    "addr:housenumber":"77",
    "addr:postcode":"08027",
    "addr:street":"Carrer De Concepcion Arenal",
    "iso:country":"ES",
    "sg:address":"Carrer de Concepcion Arenal, 77",
    "sg:city":"Barcelona",
    "sg:orig_category":"Herramientas Manuales (fabricaci\u00d3n, Al Por Mayor)",
    "sg:phone":"+34 933 40 95 04",
    "sg:postcode":"08027",
    "sg:province":"Barcelona",
    "wof:name":"Pujol Manzanera Jaime",
    "wof:placetype":"venue"
},
  "geometry": {"coordinates":[2.183825016,41.4223861694],"type":"Point"}
}