{
  "type": "Feature",
  "properties": {
    "addr:full":"Avda Miguel Servet, 77 Utebo Zaragoza 50180",
    "addr:housenumber":"77",
    "addr:postcode":"50180",
    "addr:street":"Avda Miguel Servet",
    "iso:country":"ES",
    "sg:address":"Avda Miguel Servet, 77",
    "sg:city":"Utebo",
    "sg:orig_category":"Art\u00cdculos De Quincaller\u00cda, Herramientas Y Maquinaria",
    "sg:phone":"+34 976 77 10 94",
    "sg:postcode":"50180",
    "sg:province":"Zaragoza",
    "wof:name":"Enamaq S.a.",
    "wof:placetype":"venue"
},
  "geometry": {"coordinates":[-1.0170890093,41.7150382996],"type":"Point"}
}