{
  "type": "Feature",
  "properties": {
    "iso:country":"ES",
    "sg:address":"Barrio El Portillo, 174",
    "sg:city":"Villanueva Pe\u00f1a",
    "sg:orig_category":"Transportes Por V\u00cdas Navegables",
    "sg:phone":"+34 942 70 82 95",
    "sg:postcode":"39509",
    "sg:province":"Cantabria",
    "wof:name":"Transporte Excavacion Construccion Y Saneamiento Fernandez S.l.",
    "wof:placetype":"venue"
},
  "geometry": {"coordinates":[-4.2100739479,43.2973518372],"type":"Point"}
}