{
  "type": "Feature",
  "properties": {
    "addr:full":"Cra. Pomar, S/n Badalona Barcelona 08915",
    "addr:housenumber":"s / n",
    "addr:postcode":"08915",
    "iso:country":"ES",
    "sg:address":"Cra. Pomar, S/n",
    "sg:city":"Badalona",
    "sg:classifiers":[
        {
            "category":"Government",
            "subcategory":"Office",
            "type":"Public Place"
        }
    ],
    "sg:phone":"+34 933 95 50 26",
    "sg:postcode":"08915",
    "sg:province":"Barcelona",
    "sg:tags":[
        "interior",
        "administraci\u00d3n",
        "en"
    ],
    "wof:name":"Centre De Telecomunicaciones De Catalunya",
    "wof:placetype":"venue"
},
  "geometry": {"coordinates":[2.2500369549,41.4697189331],"type":"Point"}
}