{
  "type": "Feature",
  "properties": {
    "addr:full":"Calle de Cervantes, 39 Villarta S. Juan Ciudad Real 13210",
    "addr:housenumber":"39",
    "addr:postcode":"13210",
    "addr:street":"Calle De Cervantes;S. Juan Ciudad Real",
    "iso:country":"ES",
    "sg:address":"Calle de Cervantes, 39",
    "sg:city":"Villarta S. Juan",
    "sg:orig_category":"Iglesia Cat\u00d3lica",
    "sg:phone":"+34 926 64 02 40",
    "sg:postcode":"13210",
    "sg:province":"Ciudad Real",
    "wof:name":"Parroquia De San Juan Bautista",
    "wof:placetype":"venue"
},
  "geometry": {"coordinates":[-3.4239981174,39.2388000488],"type":"Point"}
}