{
  "type": "Feature",
  "properties": {
    "iso:country":"ES",
    "sg:address":"Gta Lopez De Hoyos, 3",
    "sg:city":"Madrid",
    "sg:orig_category":"Sonorizaci\u00d3n, Iluminaci\u00d3n Para Cine, Teatro Y Discotecas (al Por Mayor, Al Por Menor)",
    "sg:phone":"+34 914 11 96 78",
    "sg:postcode":"28002",
    "sg:province":"Madrid",
    "wof:name":"Happy Jack S.a.l.",
    "wof:placetype":"venue"
},
  "geometry": {"coordinates":[-3.6803789139,40.4407348633],"type":"Point"}
}