{
  "type": "Feature",
  "properties": {
    "iso:country":"ES",
    "sg:address":"Segovia, 6",
    "sg:city":"Palazuelos Eresma",
    "sg:orig_category":"Venta, Alquiler De Instrumentos Y Accesorios De M\u00dasica",
    "sg:phone":"+34 921 44 87 82",
    "sg:postcode":"40194",
    "sg:province":"Segovia",
    "wof:name":"Ayuntamiento De Palazuelos De Eresma",
    "wof:placetype":"venue"
},
  "geometry": {"coordinates":[-4.1056008339,40.9410057068],"type":"Point"}
}