{
  "type": "Feature",
  "properties": {
    "addr:full":"P. Mdez Pelayo, S/n Ramales Victoria Cantabria 39800",
    "addr:housenumber":"s / n",
    "addr:postcode":"39800",
    "addr:street":"P. Mdez Pelayo",
    "iso:country":"ES",
    "sg:address":"P. Mdez Pelayo, S/n",
    "sg:city":"Ramales Victoria",
    "sg:orig_category":"Transportes Por Carretera: Lotes Completos, Mercanc\u00cdas Diversas",
    "sg:phone":"+34 942 67 83 46",
    "sg:postcode":"39800",
    "sg:province":"Cantabria",
    "wof:name":"Carbon Ruiz S.l.",
    "wof:placetype":"venue"
},
  "geometry": {"coordinates":[-3.442991972,43.2613754272],"type":"Point"}
}