{
  "type": "Feature",
  "properties": {
    "iso:country":"ES",
    "sg:address":"Calle de Granxas, 35",
    "sg:city":"Covas",
    "sg:orig_category":"Cl\u00cdnicas Dentales",
    "sg:phone":"+34 982 55 05 04",
    "sg:postcode":"27861",
    "sg:province":"Lugo",
    "wof:name":"Freites Arroyo Viviana Claudia",
    "wof:placetype":"venue"
},
  "geometry": {"coordinates":[-7.6583218575,43.691734314],"type":"Point"}
}