{
  "type": "Feature",
  "properties": {
    "iso:country":"ES",
    "sg:address":"Calle de Mossen Cuenca, 26",
    "sg:city":"Pinedo",
    "sg:orig_category":"Cl\u00cdnicas Dentales",
    "sg:phone":"+34 963 24 80 58",
    "sg:postcode":"46012",
    "sg:province":"Valencia",
    "wof:name":"Centre Odontologic Samblas-san Jose S.l.",
    "wof:placetype":"venue"
},
  "geometry": {"coordinates":[-0.3386439979,39.4222717285],"type":"Point"}
}