{
  "type": "Feature",
  "properties": {
    "iso:country":"ES",
    "sg:address":"Calle de Casillas De Prats, 10",
    "sg:city":"Granada",
    "sg:orig_category":"Institutos De Belleza",
    "sg:phone":"+34 958 26 63 65",
    "sg:postcode":"18002",
    "sg:province":"Granada",
    "wof:name":"Martin Civantos Marin",
    "wof:placetype":"venue"
},
  "geometry": {"coordinates":[-3.6053729057,37.1735801697],"type":"Point"}
}