{
  "type": "Feature",
  "properties": {
    "addr:full":"Calle de Marcelo Macias, 13 Bembibre Le\u00f3n 24300",
    "addr:housenumber":"13",
    "addr:postcode":"24300",
    "addr:street":"Calle De Marcelo Macias;Leo\u0301N",
    "iso:country":"ES",
    "sg:address":"Calle de Marcelo Macias, 13",
    "sg:city":"Bembibre",
    "sg:orig_category":"Empresarios",
    "sg:phone":"+34 987 51 20 39",
    "sg:postcode":"24300",
    "sg:province":"Le\u00f3n",
    "wof:name":"Manrique Alonso Manuel",
    "wof:placetype":"venue"
},
  "geometry": {"coordinates":[-6.4182691574,42.617565155],"type":"Point"}
}