{
  "type": "Feature",
  "properties": {
    "addr:full":"Carrer de Mallorca, 44 Playa De Calafell Tarragona 43820",
    "addr:housenumber":"44",
    "addr:postcode":"43820",
    "addr:street":"Carrer De Mallorca",
    "iso:country":"ES",
    "sg:address":"Carrer de Mallorca, 44",
    "sg:city":"Playa De Calafell",
    "sg:orig_category":"Inmobiliaria (agencias)",
    "sg:phone":"+34 977 69 14 55",
    "sg:postcode":"43820",
    "sg:province":"Tarragona",
    "wof:name":"Valls Singla Ramon",
    "wof:placetype":"venue"
},
  "geometry": {"coordinates":[1.5705159903,41.1887245178],"type":"Point"}
}