{
  "type": "Feature",
  "properties": {
    "addr:full":"Cmno Nacedero, S/n Vozmediano Soria 42109",
    "addr:housenumber":"s",
    "addr:postcode":"42109",
    "addr:street":"Cmno Nacedero;/ N",
    "iso:country":"ES",
    "sg:address":"Cmno Nacedero, S/n",
    "sg:city":"Vozmediano",
    "sg:orig_category":"Estudios Y Construcci\u00d3n De Acuarios Y Viveros",
    "sg:phone":"+34 976 19 71 68",
    "sg:postcode":"42109",
    "sg:province":"Soria",
    "wof:name":"Alevines Del Moncayo S.a.",
    "wof:placetype":"venue"
},
  "geometry": {"coordinates":[-1.8559117317,41.8392181396],"type":"Point"}
}