{
  "type": "Feature",
  "properties": {
    "iso:country":"ES",
    "sg:address":"Ctra. Baza, S/n",
    "sg:city":"Hijate",
    "sg:orig_category":"Cajas Y Embalajes De Cart\u00d3n Y Papel",
    "sg:phone":"+34 950 42 88 41",
    "sg:postcode":"04898",
    "sg:province":"Almer\u00eda",
    "wof:name":"Envases De Carton San Antonio S.l.",
    "wof:placetype":"venue"
},
  "geometry": {"coordinates":[-2.5923190117,37.3961601257],"type":"Point"}
}