{
  "type": "Feature",
  "properties": {
    "iso:country":"ES",
    "sg:address":"Ptda Cotes Altes, 10",
    "sg:city":"Alcoi",
    "sg:orig_category":"Telas Y Sedas (al Por Menor)",
    "sg:phone":"+34 965 33 08 06",
    "sg:postcode":"03804",
    "sg:province":"Alicante",
    "wof:name":"Lopez Botella Jose Andres",
    "wof:placetype":"venue"
},
  "geometry": {"coordinates":[-0.4732739925,38.6984100342],"type":"Point"}
}