{
  "type": "Feature",
  "properties": {
    "iso:country":"ES",
    "sg:address":"Calle de Ramon Y Cajal, 17",
    "sg:city":"Motril",
    "sg:orig_category":"Farmacias",
    "sg:phone":"+34 958 60 07 35",
    "sg:postcode":"18600",
    "sg:province":"Granada",
    "wof:name":"Lopez Rodriguez Juan Carlos",
    "wof:placetype":"venue"
},
  "geometry": {"coordinates":[-3.5165290833,36.7464981079],"type":"Point"}
}