{
  "type": "Feature",
  "properties": {
    "addr:full":"Avda Jacetania (de La), 22 Jaca Huesca 22700",
    "addr:housenumber":"22",
    "addr:postcode":"22700",
    "addr:street":"Avda Jacetania De La",
    "iso:country":"ES",
    "sg:address":"Avda Jacetania (de La), 22",
    "sg:city":"Jaca",
    "sg:orig_category":"Bancos",
    "sg:phone":"+34 974 35 54 00",
    "sg:postcode":"22700",
    "sg:province":"Huesca",
    "wof:name":"Banco Popular Espa\u00f1ol S.a.",
    "wof:placetype":"venue"
},
  "geometry": {"coordinates":[-0.5463790298,42.5695381165],"type":"Point"}
}