{
  "type": "Feature",
  "properties": {
    "iso:country":"ES",
    "sg:address":"Calle de Puebla, 38",
    "sg:city":"Burgos",
    "sg:orig_category":"Arquitectos",
    "sg:phone":"+34 947 27 99 88",
    "sg:postcode":"09004",
    "sg:province":"Burgos",
    "wof:name":"Vega Lavado Julian",
    "wof:placetype":"venue"
},
  "geometry": {"coordinates":[-3.6970689297,42.3424186707],"type":"Point"}
}