{
  "type": "Feature",
  "properties": {
    "iso:country":"ES",
    "sg:address":"Calle de Colon De Larreategui, 35",
    "sg:city":"Bilbao",
    "sg:orig_category":"Asesor\u00cda Sobre Comunicaci\u00d3n De Empresas",
    "sg:phone":"+34 944 00 04 69",
    "sg:postcode":"48009",
    "sg:province":"Vizcaya",
    "sg:website":"www.confianz.es",
    "wof:name":"Confianz, S.a.",
    "wof:placetype":"venue"
},
  "geometry": {"coordinates":[-2.9328598976,43.2636108398],"type":"Point"}
}