{
  "type": "Feature",
  "properties": {
    "addr:full":"Carrer de Torrent Dels Murris, 60 Garriga Barcelona 08530",
    "addr:housenumber":"60",
    "addr:postcode":"08530",
    "addr:street":"Carrer De Torrent Dels Murris",
    "iso:country":"ES",
    "sg:address":"Carrer de Torrent Dels Murris, 60",
    "sg:city":"Garriga",
    "sg:orig_category":"Tapicer\u00cdas",
    "sg:phone":"+34 938 71 86 86",
    "sg:postcode":"08530",
    "sg:province":"Barcelona",
    "wof:name":"Pibernat Pladelasala Juan",
    "wof:placetype":"venue"
},
  "geometry": {"coordinates":[2.2840359211,41.6830787659],"type":"Point"}
}