{
  "type": "Feature",
  "properties": {
    "iso:country":"ES",
    "sg:address":"A Moreira, 50",
    "sg:city":"Moreira",
    "sg:orig_category":"Navegaci\u00d3n (equipos Fluviales)",
    "sg:phone":"+34 986 88 36 88",
    "sg:postcode":"36915",
    "sg:province":"Pontevedra",
    "wof:name":"Gonzalez Cobelo Claudino",
    "wof:placetype":"venue"
},
  "geometry": {"coordinates":[-8.438583374,42.1240959167],"type":"Point"}
}