{
  "type": "Feature",
  "properties": {
    "addr:full":"Calle de Pe\u00d1arroya, 60 Tomelloso Ciudad Real 13700",
    "addr:housenumber":"60",
    "addr:postcode":"13700",
    "addr:street":"Calle De Pen\u0303Arroya",
    "iso:country":"ES",
    "sg:address":"Calle de Pe\u00d1arroya, 60",
    "sg:city":"Tomelloso",
    "sg:orig_category":"Confecci\u00d3n (fabricaci\u00d3n, Al Por Mayor)",
    "sg:phone":"+34 926 53 81 12",
    "sg:postcode":"13700",
    "sg:province":"Ciudad Real",
    "wof:name":"Confecciones Sevilla Martinez Sl",
    "wof:placetype":"venue"
},
  "geometry": {"coordinates":[-3.0330588818,39.1612091064],"type":"Point"}
}