{
  "type": "Feature",
  "properties": {
    "iso:country":"ES",
    "sg:address":"Calle de Claudio Sanchez Albornoz, 4",
    "sg:city":"Madrid",
    "sg:orig_category":"Cristaler\u00cdas",
    "sg:phone":"+34 917 11 13 49",
    "sg:postcode":"28024",
    "sg:province":"Madrid",
    "wof:name":"Alvaro Quiroga Jose Luis",
    "wof:placetype":"venue"
},
  "geometry": {"coordinates":[-3.7720704079,40.3969116211],"type":"Point"}
}