{
  "type": "Feature",
  "properties": {
    "addr:full":"Calle de San Antonio, S/n Guardo Palencia 34880",
    "addr:housenumber":"s / n",
    "addr:postcode":"34880",
    "addr:street":"Calle De San Antonio",
    "iso:country":"ES",
    "sg:address":"Calle de San Antonio, S/n",
    "sg:city":"Guardo",
    "sg:orig_category":"Centros De Salud",
    "sg:phone":"+34 979 85 02 74",
    "sg:postcode":"34880",
    "sg:province":"Palencia",
    "wof:name":"Guardo Proyecto 2000 S.l.",
    "wof:placetype":"venue"
},
  "geometry": {"coordinates":[-4.8446688652,42.7896537781],"type":"Point"}
}