{
  "type": "Feature",
  "properties": {
    "addr:full":"E. Molinon, S/n Gijon Asturias 33203",
    "addr:housenumber":"s",
    "addr:postcode":"33203",
    "addr:street":"/ N",
    "iso:country":"ES",
    "sg:address":"E. Molinon, S/n",
    "sg:city":"Gijon",
    "sg:orig_category":"Asociaciones Y Clubs Deportivos",
    "sg:phone":"+34 985 33 95 41",
    "sg:postcode":"33203",
    "sg:province":"Asturias",
    "wof:name":"Asociacion Asturiana De Atletas Veteranos",
    "wof:placetype":"venue"
},
  "geometry": {"coordinates":[-5.6384134293,43.5365562439],"type":"Point"}
}