{
  "type": "Feature",
  "properties": {
    "iso:country":"ES",
    "sg:address":"Calle de Hernan Cortes, 36",
    "sg:city":"Jaraiz Vera",
    "sg:orig_category":"Muebles Y Accesorios Para Cocinas Y Cuartos De Ba\u00d1o (al Por Menor)",
    "sg:phone":"+34 927 46 14 04",
    "sg:postcode":"10400",
    "sg:province":"C\u00e1ceres",
    "wof:name":"Sanchez Jaen Jesus Maria",
    "wof:placetype":"venue"
},
  "geometry": {"coordinates":[-5.7500939369,40.0608978271],"type":"Point"}
}