{
  "type": "Feature",
  "properties": {
    "addr:full":"Calle de Plaza (de La), 122 Pto Real C\u00e1diz 11510",
    "addr:housenumber":"122",
    "addr:postcode":"11510",
    "addr:street":"Calle De Plaza De La;Ca\u0301Diz",
    "iso:country":"ES",
    "sg:address":"Calle de Plaza (de La), 122",
    "sg:city":"Pto Real",
    "sg:orig_category":"Cajas De Ahorro",
    "sg:phone":"+34 956 83 30 11",
    "sg:postcode":"11510",
    "sg:province":"C\u00e1diz",
    "wof:name":"Caja De Ahorros Y Monte De Piedad De Cordoba",
    "wof:placetype":"venue"
},
  "geometry": {"coordinates":[-6.1904811859,36.5281066895],"type":"Point"}
}