{
  "type": "Feature",
  "properties": {
    "addr:full":"Calle de Ramon Y Cajal, 1 Huetor-tajar Granada 18360",
    "addr:housenumber":"1",
    "addr:postcode":"18360",
    "addr:street":"Calle De Ramon Y Cajal",
    "iso:country":"ES",
    "sg:address":"Calle de Ramon Y Cajal, 1",
    "sg:city":"Huetor-tajar",
    "sg:orig_category":"Parafarmacias",
    "sg:phone":"+34 958 33 41 43",
    "sg:postcode":"18360",
    "sg:province":"Granada",
    "wof:name":"Corrales Chinchilla Maria Del Carmen",
    "wof:placetype":"venue"
},
  "geometry": {"coordinates":[-4.0456390381,37.1972007751],"type":"Point"}
}