{
  "type": "Feature",
  "properties": {
    "addr:full":"Ctra. Camari\u00f1as, Km. 0000,8 Vimianzo La Coru\u00f1a 15120",
    "addr:postcode":"15120",
    "addr:street":"Ctra. Camarin\u0303As Km. 0000,8;La Corun\u0303A",
    "iso:country":"ES",
    "sg:address":"Ctra. Camari\u00f1as, Km. 0000,8",
    "sg:city":"Vimianzo",
    "sg:orig_category":"Empresas De Carpinter\u00cda Met\u00c1lica",
    "sg:phone":"+34 981 71 63 00",
    "sg:postcode":"15120",
    "sg:province":"La Coru\u00f1a",
    "sg:website":"www.induplan.es",
    "wof:name":"Induplan S. L.",
    "wof:placetype":"venue"
},
  "geometry": {"coordinates":[-9.0328435898,43.1112251282],"type":"Point"}
}