{
  "type": "Feature",
  "properties": {
    "iso:country":"ES",
    "sg:address":"Impressors, 28",
    "sg:city":"Ciutadella Menorca",
    "sg:orig_category":"Aparcamientos (infraestructuras, Accesorios)",
    "sg:phone":"+34 971 48 09 37",
    "sg:postcode":"07760",
    "sg:province":"Islas Baleares",
    "wof:name":"Ute-ramon Bosch Catello,gaspar Pons Vaquer,valeriano Alles Canet, S.l.",
    "wof:placetype":"venue"
},
  "geometry": {"coordinates":[3.8583900928,40.0094795227],"type":"Point"}
}