{
  "type": "Feature",
  "properties": {
    "iso:country":"ES",
    "sg:address":"Calle de Chapistas, 25",
    "sg:city":"Pilas",
    "sg:orig_category":"Comercio De Piezas De Recambio Y De Accesorios De Veh\u00cdculos, Veh\u00cdculos Industriales",
    "sg:phone":"+34 955 75 22 24",
    "sg:postcode":"41840",
    "sg:province":"Sevilla",
    "wof:name":"Remolques Remolsur S.l.",
    "wof:placetype":"venue"
},
  "geometry": {"coordinates":[-6.2966132164,37.2933158875],"type":"Point"}
}