{
  "type": "Feature",
  "properties": {
    "iso:country":"ES",
    "sg:address":"Rua Calvo Sotelo, 54",
    "sg:city":"Estrada",
    "sg:orig_category":"Ropa Para Se\u00d1oras (al Por Menor)",
    "sg:phone":"+34 986 57 25 80",
    "sg:postcode":"36680",
    "sg:province":"Pontevedra",
    "wof:name":"Asorey Cotobad Amparo",
    "wof:placetype":"venue"
},
  "geometry": {"coordinates":[-8.4877500534,42.6899147034],"type":"Point"}
}