{
  "type": "Feature",
  "properties": {
    "addr:full":"Carrer de Rogent, 39 Barcelona Barcelona 08026",
    "addr:housenumber":"39",
    "addr:postcode":"08026",
    "addr:street":"Carrer De Rogent",
    "iso:country":"ES",
    "sg:address":"Carrer de Rogent, 39",
    "sg:city":"Barcelona",
    "sg:orig_category":"Relojer\u00cda (al Por Menor, Reparaci\u00d3n)",
    "sg:phone":"+34 932 32 13 05",
    "sg:postcode":"08026",
    "sg:province":"Barcelona",
    "wof:name":"Rellotgeria Lara S.c.p",
    "wof:placetype":"venue"
},
  "geometry": {"coordinates":[2.1838259697,41.4096488953],"type":"Point"}
}