{
  "type": "Feature",
  "properties": {
    "iso:country":"ES",
    "sg:address":"Plaz Rasillo (del), 3",
    "sg:city":"Venturada",
    "sg:orig_category":"Producci\u00d3n De Abonos Y De Fertilizantes",
    "sg:phone":"+34 918 43 90 78",
    "sg:postcode":"28729",
    "sg:province":"Madrid",
    "wof:name":"Abonos Chichon S.l",
    "wof:placetype":"venue"
},
  "geometry": {"coordinates":[-3.622139,40.798687],"type":"Point"}
}