{
  "type": "Feature",
  "properties": {
    "iso:country":"ES",
    "sg:address":"Calle de Morco, 6",
    "sg:city":"Burgos",
    "sg:orig_category":"Asesor\u00cda Fiscal Y Jur\u00cddica",
    "sg:phone":"+34 947 27 77 89",
    "sg:postcode":"09004",
    "sg:province":"Burgos",
    "wof:name":"Alvarez Alvarez Luis Carlos",
    "wof:placetype":"venue"
},
  "geometry": {"coordinates":[-3.6937372684,42.3439750671],"type":"Point"}
}