{
  "type": "Feature",
  "properties": {
    "iso:country":"ES",
    "sg:address":"Av Cartagena, 140",
    "sg:city":"El Altet",
    "sg:orig_category":"Alquiler De Veh\u00cdculos: Turismos Y Utilitarios",
    "sg:phone":"+34 965 68 83 95",
    "sg:postcode":"03195",
    "sg:province":"Alicante",
    "wof:name":"Coastline Auto Rent S.l",
    "wof:placetype":"venue"
},
  "geometry": {"coordinates":[-0.5206289887,38.2537002563],"type":"Point"}
}