{
  "type": "Feature",
  "properties": {
    "addr:full":"Pg Albert, 15 Cambrils Tarragona 43850",
    "addr:housenumber":"15",
    "addr:postcode":"43850",
    "addr:street":"Pg Albert",
    "iso:country":"ES",
    "sg:address":"Pg Albert, 15",
    "sg:city":"Cambrils",
    "sg:orig_category":"Producci\u00d3n, Distribuci\u00d3n De Gas Butano Y Propano",
    "sg:phone":"+34 977 79 22 68",
    "sg:postcode":"43850",
    "sg:province":"Tarragona",
    "wof:name":"Gaca S.a.",
    "wof:placetype":"venue"
},
  "geometry": {"coordinates":[1.0531439781,41.0746421814],"type":"Point"}
}