{
  "type": "Feature",
  "properties": {
    "addr:full":"Calle de Olivilla, S/n San Roman De Los Montes Toledo 45646",
    "addr:housenumber":"s / n",
    "addr:postcode":"45646",
    "addr:street":"Calle De Olivilla;San Roman De Los",
    "iso:country":"ES",
    "sg:address":"Calle de Olivilla, S/n",
    "sg:city":"San Roman De Los Montes",
    "sg:orig_category":"Panader\u00cdas, Panader\u00cdas",
    "sg:phone":"+34 925 88 71 44",
    "sg:postcode":"45646",
    "sg:province":"Toledo",
    "wof:name":"Rodriguez Garcia Jose Luis",
    "wof:placetype":"venue"
},
  "geometry": {"coordinates":[-4.7309188843,40.0699615479],"type":"Point"}
}