{
  "type": "Feature",
  "properties": {
    "addr:full":"Pase Sagasta, 70 Zaragoza Zaragoza 50006",
    "addr:housenumber":"70",
    "addr:postcode":"50006",
    "iso:country":"ES",
    "sg:address":"Pase Sagasta, 70",
    "sg:city":"Zaragoza",
    "sg:orig_category":"Cajas De Ahorro",
    "sg:phone":"+34 976 25 90 78",
    "sg:postcode":"50006",
    "sg:province":"Zaragoza",
    "wof:name":"Caja De Ahorros Y Monte De Piedad De Zaragoza Aragon Y Rioja",
    "wof:placetype":"venue"
},
  "geometry": {"coordinates":[-0.8867310286,41.6402359009],"type":"Point"}
}