{
  "type": "Feature",
  "properties": {
    "iso:country":"ES",
    "sg:address":"Caseriu Del Boix, 13",
    "sg:city":"S. Feliu Pallerols",
    "sg:orig_category":"Escayola Y Productos De Escayola (fabricaci\u00d3n, Al Por Mayor)",
    "sg:phone":"+34 972 44 41 34",
    "sg:postcode":"17174",
    "sg:province":"Girona",
    "wof:name":"Boada Freixas Francisco",
    "wof:placetype":"venue"
},
  "geometry": {"coordinates":[2.5088319778,42.07862854],"type":"Point"}
}