{
  "type": "Feature",
  "properties": {
    "iso:country":"ES",
    "sg:address":"Calle de Almatriche, 85",
    "sg:city":"Tenoya",
    "sg:orig_category":"Carnicer\u00cdas, Carnicer\u00cdas",
    "sg:phone":"+34 928 67 13 02",
    "sg:postcode":"35018",
    "sg:province":"Las Palmas",
    "wof:name":"Cumbres Canarias S.l.",
    "wof:placetype":"venue"
},
  "geometry": {"coordinates":[-15.4591217041,28.0882816315],"type":"Point"}
}