{
  "type": "Feature",
  "properties": {
    "addr:full":"La Rosa, 13 Sta Cruz Tenerife Santa Cruz De Tenerife 38002",
    "addr:housenumber":"13",
    "addr:postcode":"38002",
    "addr:street":"Rosa;Sta Cruz Tenerife",
    "iso:country":"ES",
    "sg:address":"La Rosa, 13",
    "sg:city":"Sta Cruz Tenerife",
    "sg:orig_category":"Abogados",
    "sg:phone":"+34 922 29 66 85",
    "sg:postcode":"38002",
    "sg:province":"Santa Cruz De Tenerife",
    "wof:name":"Pelayo Duque Maria Dolores",
    "wof:placetype":"venue"
},
  "geometry": {"coordinates":[-16.2501869202,28.4703369141],"type":"Point"}
}