{
  "type": "Feature",
  "properties": {
    "iso:country":"ES",
    "sg:address":"Carrer de Pare Bartomeu Pou, 55",
    "sg:city":"Palma",
    "sg:orig_category":"Tintes (fabricaci\u00d3n, Al Por Mayor)",
    "sg:phone":"+34 971 75 36 66",
    "sg:postcode":"07003",
    "sg:province":"Islas Baleares",
    "wof:name":"Buenestado Gil Juan Carlos",
    "wof:placetype":"venue"
},
  "geometry": {"coordinates":[2.6476778984,39.5804176331],"type":"Point"}
}