{
  "type": "Feature",
  "properties": {
    "iso:country":"ES",
    "sg:address":"Calle de Estrella Altair, 2",
    "sg:city":"Cordoba",
    "sg:orig_category":"Consultas M\u00c9dicas",
    "sg:phone":"+34 957 26 94 02",
    "sg:postcode":"14007",
    "sg:province":"C\u00f3rdoba",
    "wof:name":"Navas Exposito Jose Antonio",
    "wof:placetype":"venue"
},
  "geometry": {"coordinates":[-4.7680134773,37.8936920166],"type":"Point"}
}