{
  "type": "Feature",
  "properties": {
    "iso:country":"ES",
    "sg:address":"Calle de Majada Calera, 3",
    "sg:city":"Ventanicas-el Cantal",
    "sg:orig_category":"Comercio De Piezas De Recambio Y De Accesorios De Veh\u00cdculos, Veh\u00cdculos Industriales",
    "sg:phone":"+34 950 47 26 90",
    "sg:postcode":"04638",
    "sg:province":"Almer\u00eda",
    "wof:name":"Janti  Mohamed",
    "wof:placetype":"venue"
},
  "geometry": {"coordinates":[-1.8406590223,37.122089386],"type":"Point"}
}