{
  "type": "Feature",
  "properties": {
    "addr:full":"Calle de Diputacion Foral, 7 Tafalla Navarra 31300",
    "addr:housenumber":"7",
    "addr:postcode":"31300",
    "addr:street":"Calle De Diputacion Foral",
    "iso:country":"ES",
    "sg:address":"Calle de Diputacion Foral, 7",
    "sg:city":"Tafalla",
    "sg:orig_category":"Supermercados Y Hipermercados",
    "sg:phone":"+34 948 75 50 01",
    "sg:postcode":"31300",
    "sg:province":"Navarra",
    "wof:name":"Eroski Sociedad Cooperativa",
    "wof:placetype":"venue"
},
  "geometry": {"coordinates":[-1.6736849546,42.5274848938],"type":"Point"}
}