{
  "type": "Feature",
  "properties": {
    "iso:country":"ES",
    "sg:address":"Ctra Provincial, Km. 0032,0",
    "sg:city":"Santa Ursula",
    "sg:orig_category":"Supermercados Y Hipermercados",
    "sg:phone":"+34 922 30 07 33",
    "sg:postcode":"38390",
    "sg:province":"Santa Cruz De Tenerife",
    "wof:name":"Comercial Jesuman S.a.",
    "wof:placetype":"venue"
},
  "geometry": {"coordinates":[-16.4917697906,28.425359726],"type":"Point"}
}