{
  "type": "Feature",
  "properties": {
    "iso:country":"ES",
    "sg:address":"Calle de Ancha, 70",
    "sg:city":"Sanlucar De Barrameda",
    "sg:orig_category":"Abogados",
    "sg:phone":"+34 956 36 32 83",
    "sg:postcode":"11540",
    "sg:province":"C\u00e1diz",
    "wof:name":"Barba Calvo Manuel Jesus",
    "wof:placetype":"venue"
},
  "geometry": {"coordinates":[-6.3521008492,36.7793045044],"type":"Point"}
}