{
  "type": "Feature",
  "properties": {
    "addr:full":"Av Principat D'andorra, 13 Tarragona Tarragona 43002",
    "addr:housenumber":"13",
    "addr:postcode":"43002",
    "addr:street":"Av Principat D'Andorra",
    "iso:country":"ES",
    "sg:address":"Av Principat D'andorra, 13",
    "sg:city":"Tarragona",
    "sg:orig_category":"Almacenes Frigor\u00cdficos",
    "sg:phone":"+34 977 21 48 04",
    "sg:postcode":"43002",
    "sg:province":"Tarragona",
    "wof:name":"Ramon Vizcaino Refrigeracion",
    "wof:placetype":"venue"
},
  "geometry": {"coordinates":[1.2421449423,41.1258277893],"type":"Point"}
}