{
  "type": "Feature",
  "properties": {
    "addr:full":"Avda America, 66 Zaragoza Zaragoza 50007",
    "addr:housenumber":"66",
    "addr:postcode":"50007",
    "addr:street":"Avda America",
    "iso:country":"ES",
    "sg:address":"Avda America, 66",
    "sg:city":"Zaragoza",
    "sg:orig_category":"Herboristas (al Por Menor)",
    "sg:phone":"+34 976 38 15 38",
    "sg:postcode":"50007",
    "sg:province":"Zaragoza",
    "wof:name":"La Colmena S.cv.",
    "wof:placetype":"venue"
},
  "geometry": {"coordinates":[-0.8862540126,41.6289138794],"type":"Point"}
}