{
  "type": "Feature",
  "properties": {
    "iso:country":"ES",
    "sg:address":"Avda Aragon, 13",
    "sg:city":"Montalban",
    "sg:orig_category":"Electricidad: Instaladores",
    "sg:phone":"+34 978 75 02 81",
    "sg:postcode":"44700",
    "sg:province":"Teruel",
    "wof:name":"Dielman S.l.",
    "wof:placetype":"venue"
},
  "geometry": {"coordinates":[-0.7980690002,40.8313903809],"type":"Point"}
}