{
  "type": "Feature",
  "properties": {
    "iso:country":"ES",
    "sg:address":"Cangas De Onis, 131",
    "sg:city":"Posada",
    "sg:orig_category":"Librer\u00cdas",
    "sg:phone":"+34 985 40 73 31",
    "sg:postcode":"33594",
    "sg:province":"Asturias",
    "wof:name":"Salas Pascual Monica",
    "wof:placetype":"venue"
},
  "geometry": {"coordinates":[-4.8618822098,43.4186553955],"type":"Point"}
}