{
  "type": "Feature",
  "properties": {
    "iso:country":"ES",
    "sg:address":"Urb Fuentebella (de La), 49",
    "sg:city":"Parla",
    "sg:orig_category":"Aguas (distribuci\u00d3n, Servicios)",
    "sg:phone":"+34 916 99 62 10",
    "sg:postcode":"28980",
    "sg:province":"Madrid",
    "wof:name":"Aguado De Haro Agustin",
    "wof:placetype":"venue"
},
  "geometry": {"coordinates":[-3.7727413177,40.237537384],"type":"Point"}
}