{
  "type": "Feature",
  "properties": {
    "iso:country":"ES",
    "sg:address":"Calle de Mazarron, 29",
    "sg:city":"Linares",
    "sg:orig_category":"Supermercados Y Hipermercados",
    "sg:phone":"+34 953 60 14 71",
    "sg:postcode":"23700",
    "sg:province":"Ja\u00e9n",
    "wof:name":"Prieto Rus Agustina",
    "wof:placetype":"venue"
},
  "geometry": {"coordinates":[-3.6375460625,38.1031265259],"type":"Point"}
}