{
  "type": "Feature",
  "properties": {
    "iso:country":"ES",
    "sg:address":"Barr Olaberria (dcha. Carr. Olaberria), 72",
    "sg:city":"Irun",
    "sg:orig_category":"Materias Pl\u00c1sticas: Art\u00cdculos Para La Industria",
    "sg:phone":"+34 943 63 11 35",
    "sg:postcode":"20303",
    "sg:province":"Guip\u00f9zcoa",
    "wof:name":"Hermanos Curiel S Cv",
    "wof:placetype":"venue"
},
  "geometry": {"coordinates":[-1.7902339697,43.3395233154],"type":"Point"}
}