{
  "type": "Feature",
  "properties": {
    "addr:full":"Avda Chilches, 13 Playa Chilches Castell\u00f3n 12592",
    "addr:housenumber":"13",
    "addr:postcode":"12592",
    "addr:street":"Avda Chilches",
    "iso:country":"ES",
    "sg:address":"Avda Chilches, 13",
    "sg:city":"Playa Chilches",
    "sg:orig_category":"Heladeros",
    "sg:phone":"+34 964 58 34 12",
    "sg:postcode":"12592",
    "sg:province":"Castell\u00f3n",
    "wof:name":"Carregui Martell Alicia",
    "wof:placetype":"venue"
},
  "geometry": {"coordinates":[-0.1846590042,39.7813034058],"type":"Point"}
}