{
  "type": "Feature",
  "properties": {
    "addr:full":"San Lorenzo, 4 Iru\u00f1a Navarra 31001",
    "addr:housenumber":"4",
    "addr:postcode":"31001",
    "addr:street":"San Lorenzo",
    "iso:country":"ES",
    "sg:address":"San Lorenzo, 4",
    "sg:city":"Iru\u00f1a",
    "sg:orig_category":"Pescader\u00cdas (al Por Menor)",
    "sg:phone":"+34 948 22 32 46",
    "sg:postcode":"31001",
    "sg:province":"Navarra",
    "wof:name":"Alarcon Espinar Maria Isabel",
    "wof:placetype":"venue"
},
  "geometry": {"coordinates":[-1.6488271952,42.8172683716],"type":"Point"}
}