{
  "type": "Feature",
  "properties": {
    "iso:country":"ES",
    "sg:address":"Plaz Espa\u00d1a (de), 1",
    "sg:city":"Najera",
    "sg:orig_category":"Asistencia Social",
    "sg:phone":"+34 941 41 01 59",
    "sg:postcode":"26300",
    "sg:province":"La Rioja",
    "wof:name":"Ayuntamiento De Najera",
    "wof:placetype":"venue"
},
  "geometry": {"coordinates":[-2.7481176853,42.41015625],"type":"Point"}
}