{
  "type": "Feature",
  "properties": {
    "iso:country":"ES",
    "sg:address":"Calle de Rio Guadalimar, S/n",
    "sg:city":"Atalayuela",
    "sg:orig_category":"Ferreter\u00cda (diversos)",
    "sg:phone":"+34 916 91 92 22",
    "sg:postcode":"28906",
    "sg:province":"Madrid",
    "wof:name":"Hettich Iberia S.l.c.",
    "wof:placetype":"venue"
},
  "geometry": {"coordinates":[-3.7057700157,40.42029953],"type":"Point"}
}