{
  "type": "Feature",
  "properties": {
    "addr:full":"Rua Urzaiz, 149 Vigo Pontevedra 36204",
    "addr:housenumber":"149",
    "addr:postcode":"36204",
    "addr:street":"Rua Urzaiz",
    "iso:country":"ES",
    "sg:address":"Rua Urzaiz, 149",
    "sg:city":"Vigo",
    "sg:orig_category":"Art\u00cdculos De Regalo (al Por Menor)",
    "sg:phone":"+34 986 28 07 89",
    "sg:postcode":"36204",
    "sg:province":"Pontevedra",
    "wof:name":"Mundicien S.l.",
    "wof:placetype":"venue"
},
  "geometry": {"coordinates":[-8.7092485428,42.2317008972],"type":"Point"}
}