{
  "type": "Feature",
  "properties": {
    "addr:full":"Calle de Errotabarria, 8 Barakaldo Vizcaya 48903",
    "addr:housenumber":"8",
    "addr:postcode":"48903",
    "addr:street":"Calle De Errotabarria",
    "iso:country":"ES",
    "sg:address":"Calle de Errotabarria, 8",
    "sg:city":"Barakaldo",
    "sg:orig_category":"Servicios Gsm",
    "sg:phone":"+34 944 99 28 01",
    "sg:postcode":"48903",
    "sg:province":"Vizcaya",
    "wof:name":"Juan Angel Corcuera Delgado",
    "wof:placetype":"venue"
},
  "geometry": {"coordinates":[-2.9771327972,43.2897987366],"type":"Point"}
}