{
  "type": "Feature",
  "properties": {
    "addr:full":"Carr Verge Del Pilar, 14 Picanya Valencia 46210",
    "addr:housenumber":"14",
    "addr:postcode":"46210",
    "addr:street":"Carr Verge Del Pilar",
    "iso:country":"ES",
    "sg:address":"Carr Verge Del Pilar, 14",
    "sg:city":"Picanya",
    "sg:orig_category":"Reposter\u00cdas",
    "sg:phone":"+34 961 59 32 38",
    "sg:postcode":"46210",
    "sg:province":"Valencia",
    "wof:name":"Martinez Alcantud Miguel",
    "wof:placetype":"venue"
},
  "geometry": {"coordinates":[-0.4341210127,39.4340934753],"type":"Point"}
}