{
  "type": "Feature",
  "properties": {
    "iso:country":"ES",
    "sg:address":"C/ Torras I Bages, 2",
    "sg:city":"Salt",
    "sg:orig_category":"Ropa Para Caballeros (al Por Menor)",
    "sg:phone":"+34 972 23 54 07",
    "sg:postcode":"17190",
    "sg:province":"Girona",
    "wof:name":"Jadama  Lang",
    "wof:placetype":"venue"
},
  "geometry": {"coordinates":[2.793487072,41.9738388062],"type":"Point"}
}