{
  "type": "Feature",
  "properties": {
    "iso:country":"ES",
    "sg:address":"Gipuzkoa Kalea, 47",
    "sg:city":"Zarautz",
    "sg:orig_category":"Asesor\u00cda Sobre Comunicaci\u00d3n De Empresas",
    "sg:phone":"+34 943 13 29 62",
    "sg:postcode":"20800",
    "sg:province":"Guip\u00f9zcoa",
    "wof:name":"Kima Plan S.l.",
    "wof:placetype":"venue"
},
  "geometry": {"coordinates":[-2.1613490582,43.284828186],"type":"Point"}
}