{
  "type": "Feature",
  "properties": {
    "addr:full":"Calle de San Francisco De, 22 Aviles Asturias 33402",
    "addr:housenumber":"22",
    "addr:postcode":"33402",
    "addr:street":"Calle De San Francisco De",
    "iso:country":"ES",
    "sg:address":"Calle de San Francisco De, 22",
    "sg:city":"Aviles",
    "sg:orig_category":"Estancos",
    "sg:phone":"+34 985 54 11 59",
    "sg:postcode":"33402",
    "sg:province":"Asturias",
    "wof:name":"Llames Mayo Maria Aurora",
    "wof:placetype":"venue"
},
  "geometry": {"coordinates":[-5.9237241745,43.5549659729],"type":"Point"}
}