{
  "type": "Feature",
  "properties": {
    "iso:country":"ES",
    "sg:address":"Calle de Ciriaco Garrido, 3",
    "sg:city":"Logro\u00f1o",
    "sg:orig_category":"Ropa Para Ni\u00d1os (al Por Menor)",
    "sg:phone":"+34 941 24 25 50",
    "sg:postcode":"26003",
    "sg:province":"La Rioja",
    "wof:name":"May-day S.c.",
    "wof:placetype":"venue"
},
  "geometry": {"coordinates":[-2.440438509,42.4631385803],"type":"Point"}
}