{
  "type": "Feature",
  "properties": {
    "iso:country":"ES",
    "sg:address":"Calle de Tadeo Pereda, 12",
    "sg:city":"Almansa",
    "sg:orig_category":"Alimentaci\u00d3n General (al Por Menor)",
    "sg:phone":"+34 967 34 16 61",
    "sg:postcode":"02640",
    "sg:province":"Albacete",
    "wof:name":"Gonzalez Garcia Antonio",
    "wof:placetype":"venue"
},
  "geometry": {"coordinates":[-1.0969580412,38.8730659485],"type":"Point"}
}