{
  "type": "Feature",
  "properties": {
    "addr:full":"Calle de Costa Rica, 28 Madrid Madrid 28016",
    "addr:housenumber":"28",
    "addr:postcode":"madrid;28016",
    "addr:street":"Calle De Costa Rica",
    "iso:country":"ES",
    "sg:address":"Calle de Costa Rica, 28",
    "sg:city":"Madrid",
    "sg:orig_category":"Arquitectos",
    "sg:phone":"+34 913 59 43 58",
    "sg:postcode":"28016",
    "sg:province":"Madrid",
    "wof:name":"Sugar Andina S.l.",
    "wof:placetype":"venue"
},
  "geometry": {"coordinates":[-3.6723914146,40.4584236145],"type":"Point"}
}