{
  "type": "Feature",
  "properties": {
    "addr:full":"Calle de General Oraa, 84 Madrid Madrid 28006",
    "addr:housenumber":"84",
    "addr:postcode":"madrid;28006",
    "addr:street":"Calle De General Oraa",
    "iso:country":"ES",
    "sg:address":"Calle de General Oraa, 84",
    "sg:city":"Madrid",
    "sg:orig_category":"Ingenier\u00cda, Centros De Estudios (diversos)",
    "sg:phone":"+34 915 62 15 24",
    "sg:postcode":"28006",
    "sg:province":"Madrid",
    "wof:name":"Fernandez Amigot Jose Angel",
    "wof:placetype":"venue"
},
  "geometry": {"coordinates":[-3.6765096188,40.4357910156],"type":"Point"}
}