{
  "type": "Feature",
  "properties": {
    "addr:full":"Avda Tomas Cruz Garcia (de), 36 G\u00fcimar Santa Cruz De Tenerife 38500",
    "addr:housenumber":"36",
    "addr:postcode":"38500",
    "addr:street":"Avda Tomas Cruz Garcia De",
    "iso:country":"ES",
    "sg:address":"Avda Tomas Cruz Garcia (de), 36",
    "sg:city":"G\u00fcimar",
    "sg:orig_category":"Asilos De Ancianos. Centros Privados",
    "sg:phone":"+34 922 51 02 32",
    "sg:postcode":"38500",
    "sg:province":"Santa Cruz De Tenerife",
    "wof:name":"Residencia Geriatrica Mixta 1 S.l.",
    "wof:placetype":"venue"
},
  "geometry": {"coordinates":[-16.4099674225,28.3124275208],"type":"Point"}
}