{
  "type": "Feature",
  "properties": {
    "iso:country":"ES",
    "sg:address":"Av Matadepera, 24",
    "sg:city":"Sabadell",
    "sg:orig_category":"Electrodom\u00c9sticos (al Por Menor)",
    "sg:phone":"+34 937 16 50 97",
    "sg:postcode":"08207",
    "sg:province":"Barcelona",
    "wof:name":"Butsa S. A.",
    "wof:placetype":"venue"
},
  "geometry": {"coordinates":[2.0904250145,41.5644493103],"type":"Point"}
}