{
  "type": "Feature",
  "properties": {
    "addr:full":"Sandoval, 4 Iru\u00f1a Navarra 31002",
    "addr:housenumber":"4",
    "addr:postcode":"31002",
    "addr:street":"Sandoval",
    "iso:country":"ES",
    "sg:address":"Sandoval, 4",
    "sg:city":"Iru\u00f1a",
    "sg:orig_category":"Panader\u00cdas, Panader\u00cdas",
    "sg:phone":"+34 948 22 91 92",
    "sg:postcode":"31002",
    "sg:province":"Navarra",
    "wof:name":"Espinosa Baez Yese\u00f1a Elisabeth",
    "wof:placetype":"venue"
},
  "geometry": {"coordinates":[-1.6498860121,42.8144760132],"type":"Point"}
}