{
  "type": "Feature",
  "properties": {
    "iso:country":"ES",
    "sg:address":"Calle de Azcoitia, 22",
    "sg:city":"Madrid",
    "sg:orig_category":"Servicios De Telecomunicaciones",
    "sg:phone":"+34 915 08 72 99",
    "sg:postcode":"28044",
    "sg:province":"Madrid",
    "wof:name":"Catesa",
    "wof:placetype":"venue"
},
  "geometry": {"coordinates":[-3.7553474903,40.3741149902],"type":"Point"}
}