{
  "type": "Feature",
  "properties": {
    "addr:full":"Partida Benimalluny, 82 Benissa Alicante 03720",
    "addr:housenumber":"82",
    "addr:postcode":"03720",
    "addr:street":"Partida Benimalluny",
    "iso:country":"ES",
    "sg:address":"Partida Benimalluny, 82",
    "sg:city":"Benissa",
    "sg:orig_category":"Promotores Constructores",
    "sg:phone":"+34 965 73 10 86",
    "sg:postcode":"03720",
    "sg:province":"Alicante",
    "sg:website":"www.inmo-benissa.com",
    "wof:name":"Inmo-benissa S.l.",
    "wof:placetype":"venue"
},
  "geometry": {"coordinates":[0.0279866997,38.6844329834],"type":"Point"}
}