{
  "type": "Feature",
  "properties": {
    "addr:full":"Calle de Gobernador, 65 Castellon Castell\u00f3n 12003",
    "addr:housenumber":"65",
    "addr:postcode":"12003",
    "addr:street":"Calle De Gobernador",
    "iso:country":"ES",
    "sg:address":"Calle de Gobernador, 65",
    "sg:city":"Castellon",
    "sg:orig_category":"Abogados",
    "sg:phone":"+34 964 23 62 60",
    "sg:postcode":"12003",
    "sg:province":"Castell\u00f3n",
    "wof:name":"Guzman-martinez & Asociados Abogados S.c.p.",
    "wof:placetype":"venue"
},
  "geometry": {"coordinates":[-0.0342416987,39.9862670898],"type":"Point"}
}