{
  "type": "Feature",
  "properties": {
    "addr:full":"Poli Albergueria (la), S/n Viana Navarra 31230",
    "addr:postcode":"31230",
    "addr:street":"La S / N",
    "iso:country":"ES",
    "sg:address":"Poli Albergueria (la), S/n",
    "sg:city":"Viana",
    "sg:orig_category":"Artes Gr\u00c1ficas, Artes Pl\u00c1sticas (curso)",
    "sg:phone":"+34 948 64 60 77",
    "sg:postcode":"31230",
    "sg:province":"Navarra",
    "wof:name":"Plastilas S.l.",
    "wof:placetype":"venue"
},
  "geometry": {"coordinates":[-2.3665559292,42.507686615],"type":"Point"}
}