{
  "type": "Feature",
  "properties": {
    "addr:full":"Ctra Nacional Ii, Km. 0436,9 Fraga Huesca 22520",
    "addr:postcode":"22520",
    "addr:street":"Ctra Nacional Ii Km. 0436,9 Fraga",
    "iso:country":"ES",
    "sg:address":"Ctra Nacional Ii, Km. 0436,9",
    "sg:city":"Fraga",
    "sg:orig_category":"Transportes Por V\u00cdas Navegables",
    "sg:phone":"+34 974 47 27 53",
    "sg:postcode":"22520",
    "sg:province":"Huesca",
    "sg:website":"www.chine-sa.com",
    "wof:name":"Mariano Chine Sanchez Y Juan Antonio Chine Sanchez Cdad.",
    "wof:placetype":"venue"
},
  "geometry": {"coordinates":[0.3438299894,41.5223045349],"type":"Point"}
}