{
  "type": "Feature",
  "properties": {
    "iso:country":"ES",
    "sg:address":"Calle de Elias Serrano, 26",
    "sg:city":"Minas Riotinto",
    "sg:orig_category":"Abogados",
    "sg:phone":"+34 959 59 17 00",
    "sg:postcode":"21660",
    "sg:province":"Huelva",
    "wof:name":"Gil Lopez Juan Ricardo",
    "wof:placetype":"venue"
},
  "geometry": {"coordinates":[-6.593506813,37.6919898987],"type":"Point"}
}