{
  "type": "Feature",
  "properties": {
    "iso:country":"ES",
    "sg:address":"Av Barcelona, 41",
    "sg:city":"Molins Rei",
    "sg:orig_category":"Inform\u00c1tica (estudios, Servicios, Asesor\u00cda, Formaci\u00d3n)",
    "sg:phone":"+34 936 80 45 28",
    "sg:postcode":"08750",
    "sg:province":"Barcelona",
    "wof:name":"Zapata Yerga Jose Antonio",
    "wof:placetype":"venue"
},
  "geometry": {"coordinates":[2.0304384232,41.4002571106],"type":"Point"}
}