{
  "type": "Feature",
  "properties": {
    "addr:full":"Calle de Torreblanca, 8 Castellon Castell\u00f3n 12003",
    "addr:housenumber":"8",
    "addr:postcode":"12003",
    "addr:street":"Calle De Torreblanca",
    "iso:country":"ES",
    "sg:address":"Calle de Torreblanca, 8",
    "sg:city":"Castellon",
    "sg:orig_category":"Muebles",
    "sg:phone":"+34 964 23 01 66",
    "sg:postcode":"12003",
    "sg:province":"Castell\u00f3n",
    "wof:name":"Moya Macias Vicente",
    "wof:placetype":"venue"
},
  "geometry": {"coordinates":[-0.0305029992,39.9858818054],"type":"Point"}
}