{
  "type": "Feature",
  "properties": {
    "addr:full":"Pla\u00c7 Gala I Salvador Dali, S/n Figueres Girona 17600",
    "addr:housenumber":"s / n",
    "addr:postcode":"17600",
    "iso:country":"ES",
    "sg:address":"Pla\u00c7 Gala I Salvador Dali, S/n",
    "sg:city":"Figueres",
    "sg:orig_category":"Molduras, Junquillos, Listones Y Molduras Perforadas",
    "sg:phone":"+34 972 50 24 01",
    "sg:postcode":"17600",
    "sg:province":"Girona",
    "wof:name":"Bar Divi Sl",
    "wof:placetype":"venue"
},
  "geometry": {"coordinates":[2.9601249695,42.2682151794],"type":"Point"}
}