{
  "type": "Feature",
  "properties": {
    "addr:full":"Calle de Velazquez, 1 Pto. Rosario Las Palmas 35600",
    "addr:housenumber":"1",
    "addr:postcode":"35600",
    "addr:street":"Calle De Velazquez;Pto. Rosario Las",
    "iso:country":"ES",
    "sg:address":"Calle de Velazquez, 1",
    "sg:city":"Pto. Rosario",
    "sg:orig_category":"Suministros Para Hoteles",
    "sg:phone":"+34 928 85 18 41",
    "sg:postcode":"35600",
    "sg:province":"Las Palmas",
    "wof:name":"Repuestos Morales Y Cabrera Sl",
    "wof:placetype":"venue"
},
  "geometry": {"coordinates":[-13.8689613342,28.5013866425],"type":"Point"}
}