{
  "type": "Feature",
  "properties": {
    "addr:full":"Calle de Korrokoitz, 9 Irun Guip\u00f9zcoa 20304",
    "addr:housenumber":"9",
    "addr:postcode":"20304",
    "addr:street":"Calle De Korrokoitz;Guipu\u0300Zcoa",
    "iso:country":"ES",
    "sg:address":"Calle de Korrokoitz, 9",
    "sg:city":"Irun",
    "sg:orig_category":"Peluqueros: De Se\u00d1oras",
    "sg:phone":"+34 943 62 18 27",
    "sg:postcode":"20304",
    "sg:province":"Guip\u00f9zcoa",
    "wof:name":"Alzate Ordoqui Maria Lourdes",
    "wof:placetype":"venue"
},
  "geometry": {"coordinates":[-1.7851810455,43.3377037048],"type":"Point"}
}