{
  "type": "Feature",
  "properties": {
    "iso:country":"ES",
    "sg:address":"Carrer de Muntanya, 7",
    "sg:city":"Valles Parc",
    "sg:orig_category":"Televisi\u00d3n, V\u00cddeo: Aparatos Y Accesorios (venta)",
    "sg:phone":"+34 937 21 48 64",
    "sg:postcode":"08192",
    "sg:province":"Barcelona",
    "wof:name":"Audio Alternativa S.l.",
    "wof:placetype":"venue"
},
  "geometry": {"coordinates":[2.0703129768,41.5233192444],"type":"Point"}
}