{
  "type": "Feature",
  "properties": {
    "addr:full":"Diseminados, 47 Urretxu Guip\u00f9zcoa 20700",
    "addr:housenumber":"47",
    "addr:postcode":"20700",
    "addr:street":"Diseminados;Guipu\u0300Zcoa",
    "iso:country":"ES",
    "sg:address":"Diseminados, 47",
    "sg:city":"Urretxu",
    "sg:orig_category":"Muebles, Minoristas",
    "sg:phone":"+34 943 72 53 26",
    "sg:postcode":"20700",
    "sg:province":"Guip\u00f9zcoa",
    "wof:name":"Apaolaza Jauregui Jon Eli",
    "wof:placetype":"venue"
},
  "geometry": {"coordinates":[-2.3314831257,43.091178894],"type":"Point"}
}