{
  "type": "Feature",
  "properties": {
    "addr:full":"Carr Nord, 17 Girona Girona 17001",
    "addr:housenumber":"17",
    "addr:postcode":"17001",
    "addr:street":"Carr Nord",
    "iso:country":"ES",
    "sg:address":"Carr Nord, 17",
    "sg:city":"Girona",
    "sg:orig_category":"Abogados",
    "sg:phone":"+34 972 20 36 14",
    "sg:postcode":"17001",
    "sg:province":"Girona",
    "wof:name":"Casadevall Canals Juan",
    "wof:placetype":"venue"
},
  "geometry": {"coordinates":[2.8187448978,41.9808616638],"type":"Point"}
}