{
  "type": "Feature",
  "properties": {
    "addr:full":"Calle de Real, S/n Puerto De Vega Asturias 33790",
    "addr:housenumber":"s / n",
    "addr:postcode":"33790",
    "addr:street":"Calle De Real",
    "iso:country":"ES",
    "sg:address":"Calle de Real, S/n",
    "sg:city":"Puerto De Vega",
    "sg:orig_category":"Quincaller\u00cda (al Por Menor)",
    "sg:phone":"+34 985 64 81 90",
    "sg:postcode":"33790",
    "sg:province":"Asturias",
    "wof:name":"Bedia Alonso Manuel",
    "wof:placetype":"venue"
},
  "geometry": {"coordinates":[-6.6473388672,43.5651741028],"type":"Point"}
}