{
  "type": "Feature",
  "properties": {
    "iso:country":"ES",
    "sg:address":"Calle de Augusto Figueroa, 29",
    "sg:city":"Madrid",
    "sg:orig_category":"Zapatos (al Por Menor)",
    "sg:phone":"+34 915 23 55 23",
    "sg:postcode":"28004",
    "sg:province":"Madrid",
    "wof:name":"Casas Merino Jesus",
    "wof:placetype":"venue"
},
  "geometry": {"coordinates":[-3.6983702183,40.4223899841],"type":"Point"}
}