{
  "type": "Feature",
  "properties": {
    "iso:country":"ES",
    "sg:address":"Calle de Albardin, 6",
    "sg:city":"Madrid",
    "sg:orig_category":"Ense\u00d1anza Secundaria: Colegios Y Escuelas Privadas",
    "sg:phone":"+34 914 69 90 13",
    "sg:postcode":"28026",
    "sg:province":"Madrid",
    "wof:name":"Instituto Formacion Profesional Pradolongo",
    "wof:placetype":"venue"
},
  "geometry": {"coordinates":[-3.7172420025,40.3797264099],"type":"Point"}
}