{
  "type": "Feature",
  "properties": {
    "iso:country":"ES",
    "sg:address":"Ctra Villalpando, Km. 0003,5",
    "sg:city":"Zamora",
    "sg:orig_category":"Ferreter\u00cda (diversos)",
    "sg:phone":"+34 980 67 19 33",
    "sg:postcode":"49023",
    "sg:province":"Zamora",
    "wof:name":"Ferrallas Duero,s.l.",
    "wof:placetype":"venue"
},
  "geometry": {"coordinates":[-5.7427082062,41.5157699585],"type":"Point"}
}