{
  "type": "Feature",
  "properties": {
    "addr:full":"Carrer de Doctor Marti I Julia, 110 Hospitalet Llobregat Barcelona 08903",
    "addr:housenumber":"110",
    "addr:postcode":"08903",
    "addr:street":"Carrer De Doctor Marti I Julia",
    "iso:country":"ES",
    "sg:address":"Carrer de Doctor Marti I Julia, 110",
    "sg:city":"Hospitalet Llobregat",
    "sg:orig_category":"Papeler\u00cdas, Librer\u00cdas",
    "sg:phone":"+34 934 49 67 68",
    "sg:postcode":"08903",
    "sg:province":"Barcelona",
    "wof:name":"Ortonobes Aran Marcel",
    "wof:placetype":"venue"
},
  "geometry": {"coordinates":[2.1240880489,41.3719406128],"type":"Point"}
}