{
  "type": "Feature",
  "properties": {
    "addr:full":"Av Sant Agusti, 134 S. Antoni Portmany Islas Baleares 07820",
    "addr:housenumber":"134",
    "addr:postcode":"07820",
    "addr:street":"Av Sant Agusti;S. Antoni Portmany",
    "iso:country":"ES",
    "sg:address":"Av Sant Agusti, 134",
    "sg:city":"S. Antoni Portmany",
    "sg:orig_category":"Frutas, Legumbres Frescas Y Tempranas (al Por Menor)",
    "sg:phone":"+34 971 34 81 29",
    "sg:postcode":"07820",
    "sg:province":"Islas Baleares",
    "wof:name":"Cabrera Rodriguez Dulcenombre",
    "wof:placetype":"venue"
},
  "geometry": {"coordinates":[1.5188339949,39.1094055176],"type":"Point"}
}