{
  "type": "Feature",
  "properties": {
    "iso:country":"ES",
    "sg:address":"Calle de Jose Uru\u00d1uela, 5",
    "sg:city":"Vitoria-gasteiz",
    "sg:orig_category":"Molduras, Junquillos, Listones Y Molduras Perforadas",
    "sg:phone":"+34 945 13 49 18",
    "sg:postcode":"01006",
    "sg:province":"\u00c1lava",
    "wof:name":"C.t.a. Comunicaciones Telefonicas Alavesas",
    "wof:placetype":"venue"
},
  "geometry": {"coordinates":[-2.6668999195,42.8397483826],"type":"Point"}
}