{
  "type": "Feature",
  "properties": {
    "addr:full":"Calle de Castilla, 2 Sevilla Sevilla 41010",
    "addr:housenumber":"2",
    "addr:postcode":"41010",
    "addr:street":"Calle De Castilla",
    "iso:country":"ES",
    "sg:address":"Calle de Castilla, 2",
    "sg:city":"Sevilla",
    "sg:orig_category":"Droguer\u00cdas (al Por Menor)",
    "sg:phone":"+34 954 33 23 34",
    "sg:postcode":"41010",
    "sg:province":"Sevilla",
    "wof:name":"Rodriguez Reina Manuel",
    "wof:placetype":"venue"
},
  "geometry": {"coordinates":[-6.0043349266,37.3861427307],"type":"Point"}
}