{
  "type": "Feature",
  "properties": {
    "addr:full":"Avda Pino Montano, 128 Sevilla Sevilla 41008",
    "addr:housenumber":"128",
    "addr:postcode":"41008",
    "addr:street":"Avda Pino Montano",
    "iso:country":"ES",
    "sg:address":"Avda Pino Montano, 128",
    "sg:city":"Sevilla",
    "sg:orig_category":"Molduras, Junquillos, Listones Y Molduras Perforadas",
    "sg:phone":"+34 954 95 47 60",
    "sg:postcode":"41008",
    "sg:province":"Sevilla",
    "wof:name":"Huelmos Marcos Miguel",
    "wof:placetype":"venue"
},
  "geometry": {"coordinates":[-5.9719891548,37.4097557068],"type":"Point"}
}