{
  "type": "Feature",
  "properties": {
    "iso:country":"ES",
    "sg:address":"Pase Pamplona, 9",
    "sg:city":"Zaragoza",
    "sg:orig_category":"Asesor\u00cda Sobre Comunicaci\u00d3n De Empresas",
    "sg:phone":"+34 976 22 01 40",
    "sg:postcode":"50004",
    "sg:province":"Zaragoza",
    "wof:name":"Perez Ma\u00f1es Antonio Pablo",
    "wof:placetype":"venue"
},
  "geometry": {"coordinates":[-0.8869370222,41.648563385],"type":"Point"}
}