{
  "type": "Feature",
  "properties": {
    "iso:country":"ES",
    "sg:address":"Avda Perez Galdos, 61",
    "sg:city":"Logro\u00f1o",
    "sg:orig_category":"Retoques De Vestidos",
    "sg:phone":"+34 941 21 20 97",
    "sg:postcode":"26005",
    "sg:province":"La Rioja",
    "wof:name":"Mi\u00f1ana Ruiz Maria Angeles",
    "wof:placetype":"venue"
},
  "geometry": {"coordinates":[-2.4545791149,42.4626541138],"type":"Point"}
}