{
  "type": "Feature",
  "properties": {
    "iso:country":"ES",
    "sg:address":"Carr Cami Des Castell, 2",
    "sg:city":"Mao",
    "sg:orig_category":"Florister\u00cdas",
    "sg:phone":"+34 971 36 98 18",
    "sg:postcode":"07702",
    "sg:province":"Islas Baleares",
    "wof:name":"Floral Mo S.l.",
    "wof:placetype":"venue"
},
  "geometry": {"coordinates":[4.2668709755,39.8879013062],"type":"Point"}
}