{
  "type": "Feature",
  "properties": {
    "addr:full":"Calle de Benito De Castro, 3 Madrid Madrid 28028",
    "addr:housenumber":"3",
    "addr:postcode":"28028",
    "addr:street":"Calle De Benito De Castro",
    "iso:country":"ES",
    "sg:address":"Calle de Benito De Castro, 3",
    "sg:city":"Madrid",
    "sg:orig_category":"Empresarios",
    "sg:phone":"+34 917 25 84 05",
    "sg:postcode":"28028",
    "sg:province":"Madrid",
    "wof:name":"Cruz Pelaez S.l.",
    "wof:placetype":"venue"
},
  "geometry": {"coordinates":[-3.6676576138,40.426486969],"type":"Point"}
}