{
  "type": "Feature",
  "properties": {
    "addr:full":"Calle de Ebro, 2 Burgos Burgos 09002",
    "addr:housenumber":"2",
    "addr:postcode":"09002",
    "addr:street":"Calle De Ebro",
    "iso:country":"ES",
    "sg:address":"Calle de Ebro, 2",
    "sg:city":"Burgos",
    "sg:orig_category":"Plomeros",
    "sg:phone":"+34 947 27 71 93",
    "sg:postcode":"09002",
    "sg:province":"Burgos",
    "wof:name":"Perez De La Cruz Claudio",
    "wof:placetype":"venue"
},
  "geometry": {"coordinates":[-3.6894080639,42.3362693787],"type":"Point"}
}