{
  "type": "Feature",
  "properties": {
    "addr:full":"Ispizua Kalea, 17 Hernani Guip\u00f9zcoa 20120",
    "addr:housenumber":"17",
    "addr:postcode":"20120",
    "addr:street":"Ispizua Kalea;Guipu\u0300Zcoa",
    "iso:country":"ES",
    "sg:address":"Ispizua Kalea, 17",
    "sg:city":"Hernani",
    "sg:orig_category":"Estilistas Y Estudios De Estilo De Corte Y Confecci\u00d3n",
    "sg:phone":"+34 943 55 29 47",
    "sg:postcode":"20120",
    "sg:province":"Guip\u00f9zcoa",
    "wof:name":"Zabalegui Vazquez Olatz",
    "wof:placetype":"venue"
},
  "geometry": {"coordinates":[-1.9748469591,43.2672615051],"type":"Point"}
}