{
  "type": "Feature",
  "properties": {
    "addr:full":"Calle de Hermano Garate, 8 Madrid Madrid 28020",
    "addr:housenumber":"8",
    "addr:postcode":"madrid;28020",
    "addr:street":"Calle De Hermano Garate",
    "iso:country":"ES",
    "sg:address":"Calle de Hermano Garate, 8",
    "sg:city":"Madrid",
    "sg:orig_category":"Caf\u00c9s, Bares, Cervecer\u00cdas",
    "sg:phone":"+34 915 79 69 86",
    "sg:postcode":"28020",
    "sg:province":"Madrid",
    "wof:name":"Esteban Mu\u00f1oz Martin Santiago",
    "wof:placetype":"venue"
},
  "geometry": {"coordinates":[-3.6958560944,40.4595222473],"type":"Point"}
}