{
  "type": "Feature",
  "properties": {
    "addr:full":"Carrer de Padilla, 236 Barcelona Barcelona 08013",
    "addr:housenumber":"236",
    "addr:postcode":"08013",
    "addr:street":"Carrer De Padilla",
    "iso:country":"ES",
    "sg:address":"Carrer de Padilla, 236",
    "sg:city":"Barcelona",
    "sg:orig_category":"Parques De Atracciones Y Centros De Esparcimiento",
    "sg:phone":"+34 934 56 04 13",
    "sg:postcode":"08013",
    "sg:province":"Barcelona",
    "wof:name":"Secumdum S. A.",
    "wof:placetype":"venue"
},
  "geometry": {"coordinates":[2.1777219772,41.4054832458],"type":"Point"}
}