{
  "type": "Feature",
  "properties": {
    "iso:country":"ES",
    "sg:address":"Carrer de Roca, 57",
    "sg:city":"Sabadell",
    "sg:orig_category":"Agencias Y Agentes Comerciales, Representantes",
    "sg:phone":"+34 937 27 24 25",
    "sg:postcode":"08208",
    "sg:province":"Barcelona",
    "wof:name":"Viade Julia Pedro",
    "wof:placetype":"venue"
},
  "geometry": {"coordinates":[2.0996880531,41.5521774292],"type":"Point"}
}