{
  "type": "Feature",
  "properties": {
    "addr:full":"Ctra Chipiona (de), Km. 0066,4 Sanlucar De Barrameda C\u00e1diz 11540",
    "addr:postcode":"11540",
    "addr:street":"Ctra Chipiona De Km. 0066,4;Ca\u0301Diz",
    "iso:country":"ES",
    "sg:address":"Ctra Chipiona (de), Km. 0066,4",
    "sg:city":"Sanlucar De Barrameda",
    "sg:orig_category":"Flores Y Plantas Naturales (al Por Mayor)",
    "sg:phone":"+34 956 38 94 48",
    "sg:postcode":"11540",
    "sg:province":"C\u00e1diz",
    "wof:name":"Martin Mateos Jose Maria",
    "wof:placetype":"venue"
},
  "geometry": {"coordinates":[-6.3553781509,36.7713165283],"type":"Point"}
}