{
  "type": "Feature",
  "properties": {
    "iso:country":"ES",
    "sg:address":"Agricultura(pol. Bankunion Ii), 24",
    "sg:city":"Gijon",
    "sg:orig_category":"Montaje (empresas De)",
    "sg:phone":"+34 985 32 56 62",
    "sg:postcode":"33211",
    "sg:province":"Asturias",
    "wof:name":"Montajes Tuberia Industrial S.a.",
    "wof:placetype":"venue"
},
  "geometry": {"coordinates":[-5.7159991264,43.5274391174],"type":"Point"}
}