{
  "type": "Feature",
  "properties": {
    "addr:full":"Ctra. S. Franc. La Savina, S/n S. Francesc Formentera Islas Baleares 07860",
    "addr:housenumber":"s",
    "addr:postcode":"07860",
    "addr:street":"Ctra. S. Franc. La Savina;/ N S. Francesc",
    "iso:country":"ES",
    "sg:address":"Ctra. S. Franc. La Savina, S/n",
    "sg:city":"S. Francesc Formentera",
    "sg:orig_category":"Ense\u00d1anza, Formaci\u00d3n Profesional: Aprendizaje",
    "sg:phone":"+34 971 32 26 21",
    "sg:postcode":"07860",
    "sg:province":"Islas Baleares",
    "wof:name":"Ajuntament De Formentera",
    "wof:placetype":"venue"
},
  "geometry": {"coordinates":[1.4531354904,38.6963996887],"type":"Point"}
}