{
  "type": "Feature",
  "properties": {
    "addr:full":"Calle de Juan De Medina, 2 Medina Pomar Burgos 09500",
    "addr:housenumber":"2",
    "addr:postcode":"09500",
    "addr:street":"Calle De Juan De Medina",
    "iso:country":"ES",
    "sg:address":"Calle de Juan De Medina, 2",
    "sg:city":"Medina Pomar",
    "sg:orig_category":"Arquitectos",
    "sg:phone":"+34 947 14 76 77",
    "sg:postcode":"09500",
    "sg:province":"Burgos",
    "wof:name":"Ortiz Ruiz Restituto",
    "wof:placetype":"venue"
},
  "geometry": {"coordinates":[-3.4869101048,42.9324760437],"type":"Point"}
}