{
  "type": "Feature",
  "properties": {
    "addr:full":"Fanderia Etorbidea, 21 Errenteria Guip\u00f9zcoa 20100",
    "addr:housenumber":"21",
    "addr:postcode":"20100",
    "addr:street":"Fanderia Etorbidea;Guipu\u0300Zcoa",
    "iso:country":"ES",
    "sg:address":"Fanderia Etorbidea, 21",
    "sg:city":"Errenteria",
    "sg:orig_category":"Molduras, Junquillos, Listones Y Molduras Perforadas",
    "sg:phone":"+34 943 51 90 50",
    "sg:postcode":"20100",
    "sg:province":"Guip\u00f9zcoa",
    "wof:name":"Calvi\u00f1o Eyo Jesus",
    "wof:placetype":"venue"
},
  "geometry": {"coordinates":[-1.8874989748,43.3085975647],"type":"Point"}
}