{
  "type": "Feature",
  "properties": {
    "iso:country":"ES",
    "sg:address":"Calle de Bri\u00d1as Luis, 18",
    "sg:city":"Bilbao",
    "sg:classifiers":[
        {
            "category":"Cinema",
            "subcategory":"Movie Theater",
            "type":"Entertainment"
        }
    ],
    "sg:phone":"+34 944 42 53 44",
    "sg:postcode":"48013",
    "sg:province":"Vizcaya",
    "sg:tags":[
        "salas",
        "de",
        "cine"
    ],
    "sg:website":"www.cineclubfas.net",
    "wof:name":"Cine Club Fas De Bilbao",
    "wof:placetype":"venue"
},
  "geometry": {"coordinates":[-2.94987607,43.2587203979],"type":"Point"}
}