{
  "type": "Feature",
  "properties": {
    "addr:full":"Calle de Garcia Morato, 51 Alacant Alicante 03004",
    "addr:housenumber":"51",
    "addr:postcode":"03004",
    "addr:street":"Calle De Garcia Morato",
    "iso:country":"ES",
    "sg:address":"Calle de Garcia Morato, 51",
    "sg:city":"Alacant",
    "sg:orig_category":"Institutos De Belleza",
    "sg:phone":"+34 965 14 11 45",
    "sg:postcode":"03004",
    "sg:province":"Alicante",
    "wof:name":"Crespo Y Rios S.l.",
    "wof:placetype":"venue"
},
  "geometry": {"coordinates":[-0.4880149961,38.3502197266],"type":"Point"}
}