{
  "type": "Feature",
  "properties": {
    "addr:full":"Calle de Pardo, 34 Bargas Toledo 45593",
    "addr:housenumber":"34",
    "addr:postcode":"45593",
    "addr:street":"Calle De Pardo",
    "iso:country":"ES",
    "sg:address":"Calle de Pardo, 34",
    "sg:city":"Bargas",
    "sg:orig_category":"Negocio De Materiales De Construcci\u00d3n",
    "sg:phone":"+34 925 35 85 86",
    "sg:postcode":"45593",
    "sg:province":"Toledo",
    "wof:name":"Gutierrez Brasal S.l.",
    "wof:placetype":"venue"
},
  "geometry": {"coordinates":[-4.0243759155,39.9391593933],"type":"Point"}
}