{
  "type": "Feature",
  "properties": {
    "addr:full":"Carretera De Pedroche, Km. 0002,0 Pozoblanco C\u00f3rdoba 14400",
    "addr:postcode":"14400",
    "addr:street":"Carretera De Pedroche Km. 0002,0;Co\u0301Rdoba",
    "iso:country":"ES",
    "sg:address":"Carretera De Pedroche, Km. 0002,0",
    "sg:city":"Pozoblanco",
    "sg:orig_category":"T\u00c9cnicos Veterinarios",
    "sg:phone":"+34 957 77 26 70",
    "sg:postcode":"14400",
    "sg:province":"C\u00f3rdoba",
    "wof:name":"Luna Caballero Emilio",
    "wof:placetype":"venue"
},
  "geometry": {"coordinates":[-4.8401651382,38.3838500977],"type":"Point"}
}