{
  "type": "Feature",
  "properties": {
    "iso:country":"ES",
    "sg:address":"Calle de Tordo, 7",
    "sg:city":"Valladolid",
    "sg:orig_category":"Asociaciones, Organismos Culturales Y Socioeducativos",
    "sg:phone":"+34 983 30 89 42",
    "sg:postcode":"47012",
    "sg:province":"Valladolid",
    "wof:name":"Liga Espa\u00f1ola De La Educacion Y La Cultura Popular-liga Vallisoletana",
    "wof:placetype":"venue"
},
  "geometry": {"coordinates":[-4.7050528526,41.6502189636],"type":"Point"}
}