{
  "type": "Feature",
  "properties": {
    "addr:full":"Calle de Nogal (del), 22 Nogal Madrid 28110",
    "addr:housenumber":"22",
    "addr:postcode":"28110",
    "addr:street":"Calle De Nogal Del",
    "iso:country":"ES",
    "sg:address":"Calle de Nogal (del), 22",
    "sg:city":"Nogal",
    "sg:orig_category":"Empresas De Carpinter\u00cda De Madera",
    "sg:phone":"+34 916 28 13 81",
    "sg:postcode":"28110",
    "sg:province":"Madrid",
    "wof:name":"Quercus Y Minguela S.l.",
    "wof:placetype":"venue"
},
  "geometry": {"coordinates":[-3.4999940395,40.5979003906],"type":"Point"}
}