{
  "type": "Feature",
  "properties": {
    "addr:full":"Xoane Da Ctra., 206 Goians A Coru\u00f1a 15106",
    "addr:postcode":"15106",
    "addr:street":"Ctra. 206 Goians A Corun\u0303A",
    "iso:country":"ES",
    "sg:address":"Xoane Da Ctra., 206",
    "sg:city":"Goians",
    "sg:orig_category":"Empresas De Carpinter\u00cda De Madera",
    "sg:phone":"+34 981 75 52 90",
    "sg:postcode":"15106",
    "sg:province":"A Coru\u00f1a",
    "wof:name":"Santiago Regueira S.c.",
    "wof:placetype":"venue"
},
  "geometry": {"coordinates":[-8.7134256363,43.2131004333],"type":"Point"}
}