{
  "type": "Feature",
  "properties": {
    "iso:country":"ES",
    "sg:address":"Avda Europa (de), 13",
    "sg:city":"Alcobendas",
    "sg:orig_category":"Lencer\u00cda Femenina, Corseter\u00cda, Trajes De Ba\u00d1o (al Por Menor)",
    "sg:phone":"+34 916 61 97 64",
    "sg:postcode":"28108",
    "sg:province":"Madrid",
    "wof:name":"Pirros S.l.",
    "wof:placetype":"venue"
},
  "geometry": {"coordinates":[-3.6563339233,40.5191040039],"type":"Point"}
}