{
  "type": "Feature",
  "properties": {
    "iso:country":"ES",
    "sg:address":"Calle de Hermenegildo Bielsa, 6",
    "sg:city":"Madrid",
    "sg:orig_category":"Confecci\u00d3n De Trajes Para Se\u00d1oras",
    "sg:phone":"+34 914 76 53 14",
    "sg:postcode":"28026",
    "sg:province":"Madrid",
    "wof:name":"Modas Teide S.l.",
    "wof:placetype":"venue"
},
  "geometry": {"coordinates":[-3.7023999691,40.3896636963],"type":"Point"}
}