{
  "type": "Feature",
  "properties": {
    "addr:full":"Pase Estacion (la), 33 Jaen Ja\u00e9n 23008",
    "addr:postcode":"23008",
    "addr:street":"Jae\u0301N",
    "iso:country":"ES",
    "sg:address":"Pase Estacion (la), 33",
    "sg:city":"Jaen",
    "sg:orig_category":"Psic\u00d3logos",
    "sg:phone":"+34 953 25 73 23",
    "sg:postcode":"23008",
    "sg:province":"Ja\u00e9n",
    "wof:name":"Rojas Torres Maria Estrella",
    "wof:placetype":"venue"
},
  "geometry": {"coordinates":[-3.7890689373,37.7752342224],"type":"Point"}
}