{
  "type": "Feature",
  "properties": {
    "addr:full":"Calle de Gascona, 29 Oviedo Asturias 33001",
    "addr:housenumber":"29",
    "addr:postcode":"33001",
    "addr:street":"Calle De Gascona",
    "iso:country":"ES",
    "sg:address":"Calle de Gascona, 29",
    "sg:city":"Oviedo",
    "sg:orig_category":"M\u00c9dicos: Reumatolog\u00cda",
    "sg:phone":"+34 985 21 68 66",
    "sg:postcode":"33001",
    "sg:province":"Asturias",
    "wof:name":"Gabinete Medico Gascona S.l.",
    "wof:placetype":"venue"
},
  "geometry": {"coordinates":[-5.8459229469,43.364982605],"type":"Point"}
}