{
  "type": "Feature",
  "properties": {
    "addr:full":"Estd Rua (da), 58 Viana Do Bolo Ourense 32550",
    "addr:housenumber":"58",
    "addr:postcode":"32550",
    "addr:street":"Rua Da",
    "iso:country":"ES",
    "sg:address":"Estd Rua (da), 58",
    "sg:city":"Viana Do Bolo",
    "sg:orig_category":"Ense\u00d1anza Secundaria: Colegios Y Escuelas Privadas",
    "sg:phone":"+34 988 34 00 41",
    "sg:postcode":"32550",
    "sg:province":"Ourense",
    "wof:name":"Ies Viana",
    "wof:placetype":"venue"
},
  "geometry": {"coordinates":[-7.1098628044,42.1833190918],"type":"Point"}
}