{
  "type": "Feature",
  "properties": {
    "iso:country":"ES",
    "sg:address":"Calle de Fruta De La, 3",
    "sg:city":"Aviles",
    "sg:orig_category":"Bisuter\u00cda, Joyer\u00cda, Relojer\u00cda (al Por Menor)",
    "sg:phone":"+34 985 56 45 18",
    "sg:postcode":"33402",
    "sg:province":"Asturias",
    "wof:name":"Vallina Luque Victor",
    "wof:placetype":"venue"
},
  "geometry": {"coordinates":[-5.9223256111,43.5558853149],"type":"Point"}
}