{
  "type": "Feature",
  "properties": {
    "addr:full":"Carrer de Napols, 99 Barcelona Barcelona 08013",
    "addr:housenumber":"99",
    "addr:postcode":"08013",
    "addr:street":"Carrer De Napols",
    "iso:country":"ES",
    "sg:address":"Carrer de Napols, 99",
    "sg:city":"Barcelona",
    "sg:orig_category":"Peluqueros: De Se\u00d1oras",
    "sg:phone":"+34 932 65 45 77",
    "sg:postcode":"08013",
    "sg:province":"Barcelona",
    "wof:name":"Carrasco Leon Concepcion",
    "wof:placetype":"venue"
},
  "geometry": {"coordinates":[2.1804339886,41.3944129944],"type":"Point"}
}