{
  "type": "Feature",
  "properties": {
    "addr:full":"General-bidenagusia, 10 Elexalde Vizcaya 48620",
    "addr:housenumber":"10",
    "addr:postcode":"48620",
    "addr:street":"General-Bidenagusia",
    "iso:country":"ES",
    "sg:address":"General-bidenagusia, 10",
    "sg:city":"Elexalde",
    "sg:orig_category":"Negocio De Materiales De Construcci\u00d3n",
    "sg:phone":"+34 946 77 30 92",
    "sg:postcode":"48620",
    "sg:province":"Vizcaya",
    "wof:name":"Material De Construccion Borinaga S.l",
    "wof:placetype":"venue"
},
  "geometry": {"coordinates":[-2.9458739758,43.4066467285],"type":"Point"}
}