{
  "type": "Feature",
  "properties": {
    "iso:country":"ES",
    "sg:address":"Avda Mohino, 40",
    "sg:city":"Cuadro Santiago",
    "sg:orig_category":"Revestimiento No Met\u00c1licos (esmaltado, Pintura, Plastificado)",
    "sg:phone":"+34 964 39 36 75",
    "sg:postcode":"12560",
    "sg:province":"Castell\u00f3n",
    "wof:name":"Sanalf Quimicas S.a.",
    "wof:placetype":"venue"
},
  "geometry": {"coordinates":[0.0590550005,40.0523414612],"type":"Point"}
}