{
  "type": "Feature",
  "properties": {
    "iso:country":"ES",
    "sg:address":"Calle de Esta\u00d1o, 10",
    "sg:city":"Sevilla",
    "sg:orig_category":"Promotores Constructores",
    "sg:phone":"+34 954 35 51 15",
    "sg:postcode":"41007",
    "sg:province":"Sevilla",
    "wof:name":"Gonzalez Martin Juan Antonio",
    "wof:placetype":"venue"
},
  "geometry": {"coordinates":[-5.9569211006,37.4071121216],"type":"Point"}
}