{
  "type": "Feature",
  "properties": {
    "addr:full":"Pase Maritimo De Mogor, S/n Baguin Pontevedra 36911",
    "addr:housenumber":"s",
    "addr:postcode":"36911",
    "addr:street":"/ N",
    "iso:country":"ES",
    "sg:address":"Pase Maritimo De Mogor, S/n",
    "sg:city":"Baguin",
    "sg:orig_category":"Iglesia Cat\u00d3lica",
    "sg:phone":"+34 986 88 17 80",
    "sg:postcode":"36911",
    "sg:province":"Pontevedra",
    "wof:name":"Arzobispado De Santiago",
    "wof:placetype":"venue"
},
  "geometry": {"coordinates":[-8.6480531693,42.4336204529],"type":"Point"}
}