{
  "type": "Feature",
  "properties": {
    "iso:country":"ES",
    "sg:address":"Poli Atxukarro, 1",
    "sg:city":"Arrigorriaga",
    "sg:orig_category":"Art\u00cdculos De Regalo (al Por Menor)",
    "sg:phone":"+34 946 32 00 46",
    "sg:postcode":"48480",
    "sg:province":"Vizcaya",
    "wof:name":"The Paper Office Equipment Spain Ass S.a.",
    "wof:placetype":"venue"
},
  "geometry": {"coordinates":[-2.8716180325,43.2117424011],"type":"Point"}
}