{
  "type": "Feature",
  "properties": {
    "iso:country":"ES",
    "sg:address":"Finca Corchado, S/n",
    "sg:city":"Bobadilla-estacion",
    "sg:orig_category":"Explotaci\u00d3n De Canteras",
    "sg:phone":"+34 952 03 11 86",
    "sg:postcode":"29540",
    "sg:province":"M\u00e1laga",
    "wof:name":"Ofitas Antequerana S.l.",
    "wof:placetype":"venue"
},
  "geometry": {"coordinates":[-4.7256388664,37.0369262695],"type":"Point"}
}