{
  "type": "Feature",
  "properties": {
    "iso:country":"ES",
    "sg:address":"Calle de Antxeta Juan De, 5",
    "sg:city":"Bilbao",
    "sg:orig_category":"Agencias Y Asesores De Publicidad",
    "sg:phone":"+34 944 21 41 34",
    "sg:postcode":"48015",
    "sg:province":"Vizcaya",
    "wof:name":"Biharko Reclamos Publicitarios, S.l.",
    "wof:placetype":"venue"
},
  "geometry": {"coordinates":[-2.9578919411,43.2787628174],"type":"Point"}
}