{
  "type": "Feature",
  "properties": {
    "iso:country":"ES",
    "sg:address":"Carrer de Europa, 20",
    "sg:city":"Barcelona",
    "sg:orig_category":"Art\u00cdculos De Regalo (al Por Menor)",
    "sg:phone":"+34 934 19 29 12",
    "sg:postcode":"08028",
    "sg:province":"Barcelona",
    "wof:name":"Garcia Aparicio Maria Rosa",
    "wof:placetype":"venue"
},
  "geometry": {"coordinates":[2.1298389435,41.3869743347],"type":"Point"}
}