{
  "type": "Feature",
  "properties": {
    "addr:full":"Partida De Les Sorts, S/n Gata Gorgos Alicante 03740",
    "addr:housenumber":"s",
    "addr:postcode":"03740",
    "addr:street":"Partida De Les Sorts;/ N Gata",
    "iso:country":"ES",
    "sg:address":"Partida De Les Sorts, S/n",
    "sg:city":"Gata Gorgos",
    "sg:orig_category":"Promotores Constructores",
    "sg:phone":"+34 965 75 74 86",
    "sg:postcode":"03740",
    "sg:province":"Alicante",
    "wof:name":"Generalitat Valenciana",
    "wof:placetype":"venue"
},
  "geometry": {"coordinates":[0.0839079991,38.7759056091],"type":"Point"}
}