{
  "type": "Feature",
  "properties": {
    "iso:country":"ES",
    "sg:address":"Calle de Ministro Luis Mayans, 12",
    "sg:city":"Valencia",
    "sg:orig_category":"Hornos Industriales",
    "sg:phone":"+34 963 66 27 96",
    "sg:postcode":"46009",
    "sg:province":"Valencia",
    "wof:name":"Sastre Gimeno Joaquin",
    "wof:placetype":"venue"
},
  "geometry": {"coordinates":[-0.3720650077,39.4850196838],"type":"Point"}
}