{
  "type": "Feature",
  "properties": {
    "addr:full":"Errekatxu Kalea, 5 Eibar Guip\u00f9zcoa 20600",
    "addr:housenumber":"5",
    "addr:postcode":"20600",
    "addr:street":"Errekatxu Kalea;Guipu\u0300Zcoa",
    "iso:country":"ES",
    "sg:address":"Errekatxu Kalea, 5",
    "sg:city":"Eibar",
    "sg:orig_category":"Metalurgia",
    "sg:phone":"+34 943 82 13 51",
    "sg:postcode":"20600",
    "sg:province":"Guip\u00f9zcoa",
    "wof:name":"Jose Alberto Garate S.c.l.",
    "wof:placetype":"venue"
},
  "geometry": {"coordinates":[-2.4692370892,43.184387207],"type":"Point"}
}