{
  "type": "Feature",
  "properties": {
    "iso:country":"ES",
    "sg:address":"Calle de Manuel Aznarez, 1",
    "sg:city":"Pina De Ebro",
    "sg:orig_category":"Caf\u00c9s, Bares, Cervecer\u00cdas",
    "sg:phone":"+34 976 16 52 92",
    "sg:postcode":"50750",
    "sg:province":"Zaragoza",
    "wof:name":"Sapi Bendi Venta S.l.",
    "wof:placetype":"venue"
},
  "geometry": {"coordinates":[-0.5292469859,41.4889831543],"type":"Point"}
}