{
  "type": "Feature",
  "properties": {
    "addr:full":"Rua Sagunto, 34 Vigo Pontevedra 36205",
    "addr:housenumber":"34",
    "addr:postcode":"36205",
    "addr:street":"Rua Sagunto",
    "iso:country":"ES",
    "sg:address":"Rua Sagunto, 34",
    "sg:city":"Vigo",
    "sg:orig_category":"Producci\u00d3n, Venta De Productos De Agricultura Biol\u00d3gica",
    "sg:phone":"+34 986 27 25 82",
    "sg:postcode":"36205",
    "sg:province":"Pontevedra",
    "wof:name":"Cooperativa Del Campo Santa Cristina",
    "wof:placetype":"venue"
},
  "geometry": {"coordinates":[-8.7020740509,42.2291412354],"type":"Point"}
}