{
  "type": "Feature",
  "properties": {
    "addr:full":"Carr Rafel Horrach, S/n Costitx Islas Baleares 07144",
    "addr:housenumber":"s",
    "addr:postcode":"07144",
    "addr:street":"Carr Rafel Horrach;/ N",
    "iso:country":"ES",
    "sg:address":"Carr Rafel Horrach, S/n",
    "sg:city":"Costitx",
    "sg:orig_category":"Museos",
    "sg:phone":"+34 971 87 60 70",
    "sg:postcode":"07144",
    "sg:province":"Islas Baleares",
    "wof:name":"Corro Arrom Catalina",
    "wof:placetype":"venue"
},
  "geometry": {"coordinates":[2.9483299255,39.6540184021],"type":"Point"}
}