{
  "type": "Feature",
  "properties": {
    "iso:country":"ES",
    "sg:address":"Se\u00f1orio De Echalaz, 1",
    "sg:city":"Iru\u00f1a",
    "sg:orig_category":"Iglesia Cat\u00d3lica",
    "sg:phone":"+34 948 16 15 55",
    "sg:postcode":"31016",
    "sg:province":"Navarra",
    "wof:name":"Parroquia Del Padre Nuestro",
    "wof:placetype":"venue"
},
  "geometry": {"coordinates":[-1.6128900051,42.8074874878],"type":"Point"}
}