{
  "type": "Feature",
  "properties": {
    "addr:full":"Calle de Sol, Del, 32 Talavera Reina Toledo 45600",
    "addr:housenumber":"32",
    "addr:postcode":"45600",
    "addr:street":"Calle De Sol Del",
    "iso:country":"ES",
    "sg:address":"Calle de Sol, Del, 32",
    "sg:city":"Talavera Reina",
    "sg:orig_category":"Pod\u00d3logos: Pedicuros",
    "sg:phone":"+34 925 80 85 55",
    "sg:postcode":"45600",
    "sg:province":"Toledo",
    "wof:name":"Fuentes Montero Jose Luis",
    "wof:placetype":"venue"
},
  "geometry": {"coordinates":[-4.8326292038,39.9584884644],"type":"Point"}
}