{
  "type": "Feature",
  "properties": {
    "iso:country":"ES",
    "sg:address":"Carr Sant Jaume, 12",
    "sg:city":"Lleida",
    "sg:orig_category":"Alimentaci\u00d3n General (al Por Menor)",
    "sg:phone":"+34 973 21 21 06",
    "sg:postcode":"25001",
    "sg:province":"Lleida",
    "wof:name":"Urgell S.c.p.",
    "wof:placetype":"venue"
},
  "geometry": {"coordinates":[0.6428070068,41.6049499512],"type":"Point"}
}