{
  "type": "Feature",
  "properties": {
    "iso:country":"ES",
    "sg:address":"Plaz Venta (de La), 1",
    "sg:city":"Iznajar",
    "sg:orig_category":"Peluquer\u00cdas, Peluquer\u00cda Mixta",
    "sg:phone":"+34 957 53 47 18",
    "sg:postcode":"14970",
    "sg:province":"C\u00f3rdoba",
    "wof:name":"Pavon Guerrero Maria Jose",
    "wof:placetype":"venue"
},
  "geometry": {"coordinates":[-4.3051857948,37.2579154968],"type":"Point"}
}