{
  "type": "Feature",
  "properties": {
    "addr:full":"Mozodiel, S/n Campo Ledesma Salamanca 37140",
    "addr:housenumber":"/ n",
    "addr:postcode":"37140",
    "addr:street":"Mozodiel S",
    "iso:country":"ES",
    "sg:address":"Mozodiel, S/n",
    "sg:city":"Campo Ledesma",
    "sg:orig_category":"Asociaciones Ecologistas",
    "sg:phone":"+34 923 16 60 98",
    "sg:postcode":"37140",
    "sg:province":"Salamanca",
    "wof:name":"Comunidad Regantes Campo De Ledesma",
    "wof:placetype":"venue"
},
  "geometry": {"coordinates":[-6.1015210152,41.113445282],"type":"Point"}
}