{
  "type": "Feature",
  "properties": {
    "addr:full":"Ctra Valencia, Km. 0090,0 S. Juan Alicante Alicante 03550",
    "addr:postcode":"03550",
    "addr:street":"Ctra Valencia Km. 0090,0 S. Juan",
    "iso:country":"ES",
    "sg:address":"Ctra Valencia, Km. 0090,0",
    "sg:city":"S. Juan Alicante",
    "sg:orig_category":"Distribuci\u00d3n De Petr\u00d3leo Y Derivados",
    "sg:phone":"+34 965 65 89 47",
    "sg:postcode":"03550",
    "sg:province":"Alicante",
    "wof:name":"Abril S.a.",
    "wof:placetype":"venue"
},
  "geometry": {"coordinates":[-0.411418,38.420639],"type":"Point"}
}