{
  "type": "Feature",
  "properties": {
    "addr:full":"Av Catalunya, 83 S. Adria Besos Barcelona 08930",
    "addr:housenumber":"83",
    "addr:postcode":"08930",
    "addr:street":"Av Catalunya;S. Adria Besos Barcelona",
    "iso:country":"ES",
    "sg:address":"Av Catalunya, 83",
    "sg:city":"S. Adria Besos",
    "sg:orig_category":"Fabricaci\u00d3n, Importaci\u00d3n De L\u00c1mparas Y Bombillas",
    "sg:phone":"+34 933 81 75 64",
    "sg:postcode":"08930",
    "sg:province":"Barcelona",
    "wof:name":"Rebollo Pozo Jose",
    "wof:placetype":"venue"
},
  "geometry": {"coordinates":[2.2203490734,41.4300956726],"type":"Point"}
}