{
  "type": "Feature",
  "properties": {
    "iso:country":"ES",
    "sg:address":"Carrer de Santa Perpetua, 1",
    "sg:city":"Castellar Valles",
    "sg:orig_category":"Peluquer\u00cdas, Peluquer\u00cda Mixta",
    "sg:phone":"+34 937 47 21 98",
    "sg:postcode":"08211",
    "sg:province":"Barcelona",
    "wof:name":"Urban Caballero Jose",
    "wof:placetype":"venue"
},
  "geometry": {"coordinates":[2.0885419846,41.6140174866],"type":"Point"}
}