{
  "type": "Feature",
  "properties": {
    "iso:country":"ES",
    "sg:address":"Psaj Mayoral, 1",
    "sg:city":"Toledo",
    "sg:orig_category":"Abogados",
    "sg:phone":"+34 925 25 21 97",
    "sg:postcode":"45003",
    "sg:province":"Toledo",
    "sg:website":"www.afisem@.es",
    "wof:name":"Rojas Garcia Martin",
    "wof:placetype":"venue"
},
  "geometry": {"coordinates":[-4.0222811699,39.8671531677],"type":"Point"}
}