{
  "type": "Feature",
  "properties": {
    "iso:country":"ES",
    "sg:address":"Rua Frei Rosendo Salvado (de), 26",
    "sg:city":"Santiago De Compostela",
    "sg:orig_category":"Supermercados Y Hipermercados",
    "sg:phone":"+34 981 59 74 58",
    "sg:postcode":"15701",
    "sg:province":"A Coru\u00f1a",
    "wof:name":"Supermercados Lorenzo Froiz S.a.",
    "wof:placetype":"venue"
},
  "geometry": {"coordinates":[-8.5516309738,42.8724632263],"type":"Point"}
}