{
  "type": "Feature",
  "properties": {
    "addr:full":"Calle de Torrejon, 12 Ajalvir Madrid 28864",
    "addr:housenumber":"12",
    "addr:postcode":"28864",
    "addr:street":"Calle De Torrejon",
    "iso:country":"ES",
    "sg:address":"Calle de Torrejon, 12",
    "sg:city":"Ajalvir",
    "sg:orig_category":"Contenedores (mercanc\u00cdas)",
    "sg:phone":"+34 918 84 41 03",
    "sg:postcode":"28864",
    "sg:province":"Madrid",
    "wof:name":"Transabina S.l.",
    "wof:placetype":"venue"
},
  "geometry": {"coordinates":[-3.4816849232,40.5275268555],"type":"Point"}
}