{
  "type": "Feature",
  "properties": {
    "iso:country":"ES",
    "sg:address":"S. Aizoain, S/n",
    "sg:city":"Iru\u00f1a",
    "sg:orig_category":"Distribuci\u00d3n De Petr\u00d3leo Y Derivados",
    "sg:phone":"+34 948 30 35 94",
    "sg:postcode":"31095",
    "sg:province":"Navarra",
    "wof:name":"Pescados Caridad S.l.",
    "wof:placetype":"venue"
},
  "geometry": {"coordinates":[-1.6437540054,42.81275177],"type":"Point"}
}