{
  "type": "Feature",
  "properties": {
    "addr:full":"San Lorentzo Auzoa, 11 O\u00f1ati Guip\u00f9zcoa 20560",
    "addr:housenumber":"11",
    "addr:postcode":"20560",
    "addr:street":"San Lorentzo Auzoa;Guipu\u0300Zcoa",
    "iso:country":"ES",
    "sg:address":"San Lorentzo Auzoa, 11",
    "sg:city":"O\u00f1ati",
    "sg:orig_category":"Caf\u00c9s, Bares, Cervecer\u00cdas",
    "sg:phone":"+34 943 78 28 81",
    "sg:postcode":"20560",
    "sg:province":"Guip\u00f9zcoa",
    "wof:name":"Labealde S.l.",
    "wof:placetype":"venue"
},
  "geometry": {"coordinates":[-2.4052670002,43.0321121216],"type":"Point"}
}