{
  "type": "Feature",
  "properties": {
    "iso:country":"ES",
    "sg:address":"Calle de San Ignacio, 1",
    "sg:city":"Gabia Grande",
    "sg:orig_category":"Maquinaria Para Industrias Diversas",
    "sg:phone":"+34 958 58 45 19",
    "sg:postcode":"18110",
    "sg:province":"Granada",
    "wof:name":"Reyes Gonzalez Pilar",
    "wof:placetype":"venue"
},
  "geometry": {"coordinates":[-3.6691040993,37.1345901489],"type":"Point"}
}