{
  "type": "Feature",
  "properties": {
    "iso:country":"ES",
    "sg:address":"Plaz Baron De Cortes, 20",
    "sg:city":"Valencia",
    "sg:orig_category":"Iglesia Cat\u00d3lica",
    "sg:phone":"+34 963 73 09 23",
    "sg:postcode":"46006",
    "sg:province":"Valencia",
    "wof:name":"Parroquia De San Valero",
    "wof:placetype":"venue"
},
  "geometry": {"coordinates":[-0.3716599941,39.4619560242],"type":"Point"}
}