{
  "type": "Feature",
  "properties": {
    "addr:full":"Calle de Santo Tomas, 2 Castellon Castell\u00f3n 12004",
    "addr:housenumber":"2",
    "addr:postcode":"12004",
    "addr:street":"Calle De Santo Tomas;Castello\u0301N",
    "iso:country":"ES",
    "sg:address":"Calle de Santo Tomas, 2",
    "sg:city":"Castellon",
    "sg:orig_category":"Promotores Constructores",
    "sg:phone":"+34 964 21 71 77",
    "sg:postcode":"12004",
    "sg:province":"Castell\u00f3n",
    "wof:name":"Villarroya Castellon S.l.",
    "wof:placetype":"venue"
},
  "geometry": {"coordinates":[-0.0377510004,39.990562439],"type":"Point"}
}