{
  "type": "Feature",
  "properties": {
    "iso:country":"ES",
    "sg:address":"Calle de Ceramica (la), 7",
    "sg:city":"Astorga",
    "sg:orig_category":"Transportes Por V\u00cdas Navegables",
    "sg:phone":"+34 987 61 58 27",
    "sg:postcode":"24700",
    "sg:province":"Le\u00f3n",
    "wof:name":"Cancillo Pozo Guillermo",
    "wof:placetype":"venue"
},
  "geometry": {"coordinates":[-6.0520792007,42.4596748352],"type":"Point"}
}