{
  "type": "Feature",
  "properties": {
    "iso:country":"ES",
    "sg:address":"Rua Frei Rosendo Salvado (de), 13",
    "sg:city":"Santiago De Compostela",
    "sg:orig_category":"Ingenier\u00cda, Centros De Estudios (diversos)",
    "sg:phone":"+34 981 59 61 97",
    "sg:postcode":"15701",
    "sg:province":"A Coru\u00f1a",
    "wof:name":"Taracido Peiteado Roberto",
    "wof:placetype":"venue"
},
  "geometry": {"coordinates":[-8.5505399704,42.8731498718],"type":"Point"}
}