{
  "type": "Feature",
  "properties": {
    "addr:full":"Florida Auzoa, 72 Hernani Guip\u00f9zcoa 20120",
    "addr:housenumber":"72",
    "addr:postcode":"20120",
    "addr:street":"Florida Auzoa;Guipu\u0300Zcoa",
    "iso:country":"ES",
    "sg:address":"Florida Auzoa, 72",
    "sg:city":"Hernani",
    "sg:orig_category":"Piedra, Vidrio, Cer\u00c1mica Y Porcelana",
    "sg:phone":"+34 943 55 75 00",
    "sg:postcode":"20120",
    "sg:province":"Guip\u00f9zcoa",
    "wof:name":"Amr Refractarios S.a.",
    "wof:placetype":"venue"
},
  "geometry": {"coordinates":[-1.9671529531,43.2720031738],"type":"Point"}
}