{
  "type": "Feature",
  "properties": {
    "addr:full":"Calle de Gaucin, 19 Malaga M\u00e1laga 29003",
    "addr:housenumber":"19",
    "addr:postcode":"29003",
    "addr:street":"Calle De Gaucin;Ma\u0301Laga",
    "iso:country":"ES",
    "sg:address":"Calle de Gaucin, 19",
    "sg:city":"Malaga",
    "sg:orig_category":"Coches Y Camiones (caja De Cambios, Embrague Y Frenos)",
    "sg:phone":"+34 952 33 90 74",
    "sg:postcode":"29003",
    "sg:province":"M\u00e1laga",
    "wof:name":"Autofrenos Arenas S.l.",
    "wof:placetype":"venue"
},
  "geometry": {"coordinates":[-4.4510445595,36.6991729736],"type":"Point"}
}