{
  "type": "Feature",
  "properties": {
    "iso:country":"ES",
    "sg:address":"Pol. Ind. La Salinilla, S/n",
    "sg:city":"Priego Cordoba",
    "sg:orig_category":"Muebles, Minoristas",
    "sg:phone":"+34 957 54 05 42",
    "sg:postcode":"14800",
    "sg:province":"C\u00f3rdoba",
    "sg:website":"www.mueblesjabalo.com",
    "wof:name":"Abalo Chumilla Jose Maria",
    "wof:placetype":"venue"
},
  "geometry": {"coordinates":[-4.779152,37.884727],"type":"Point"}
}