{
  "type": "Feature",
  "properties": {
    "addr:full":"Calle de Tarragona, 28 Madrid Madrid 28045",
    "addr:housenumber":"28",
    "addr:postcode":"madrid;28045",
    "addr:street":"Calle De Tarragona",
    "iso:country":"ES",
    "sg:address":"Calle de Tarragona, 28",
    "sg:city":"Madrid",
    "sg:orig_category":"Inmobiliaria (agencias)",
    "sg:phone":"+34 914 68 67 60",
    "sg:postcode":"28045",
    "sg:province":"Madrid",
    "wof:name":"Maria Garcia Gamonal S.l.",
    "wof:placetype":"venue"
},
  "geometry": {"coordinates":[-3.695499897,40.4013710022],"type":"Point"}
}