{
  "type": "Feature",
  "properties": {
    "iso:country":"ES",
    "sg:address":"Calle de Manuel Segarra Ribes, 4",
    "sg:city":"Castellon",
    "sg:orig_category":"Bisuter\u00cda, Joyer\u00cda, Relojer\u00cda (al Por Menor)",
    "sg:phone":"+34 964 23 57 74",
    "sg:postcode":"12005",
    "sg:province":"Castell\u00f3n",
    "wof:name":"Ferrer Segarra Norberto",
    "wof:placetype":"venue"
},
  "geometry": {"coordinates":[-0.0297400001,39.9624290466],"type":"Point"}
}