{
  "type": "Feature",
  "properties": {
    "addr:full":"Avda Constitucion, 22 Torrejon Ardoz Madrid 28850",
    "addr:housenumber":"22",
    "addr:postcode":"28850",
    "addr:street":"Avda Constitucion",
    "iso:country":"ES",
    "sg:address":"Avda Constitucion, 22",
    "sg:city":"Torrejon Ardoz",
    "sg:orig_category":"Caf\u00c9s, Bares, Cervecer\u00cdas",
    "sg:phone":"+34 916 77 63 91",
    "sg:postcode":"28850",
    "sg:province":"Madrid",
    "wof:name":"Herranz Lopez Jose Manuel",
    "wof:placetype":"venue"
},
  "geometry": {"coordinates":[-3.4830796719,40.455280304],"type":"Point"}
}