{
  "type": "Feature",
  "properties": {
    "addr:full":"Carrer de Ricardo Villa, 8 Barcelona Barcelona 08017",
    "addr:housenumber":"8",
    "addr:postcode":"08017",
    "addr:street":"Carrer De Ricardo Villa",
    "iso:country":"ES",
    "sg:address":"Carrer de Ricardo Villa, 8",
    "sg:city":"Barcelona",
    "sg:orig_category":"Zapatos (al Por Menor)",
    "sg:phone":"+34 932 03 10 46",
    "sg:postcode":"08017",
    "sg:province":"Barcelona",
    "wof:name":"Serna Mulero Araceli",
    "wof:placetype":"venue"
},
  "geometry": {"coordinates":[2.1329360008,41.3922576904],"type":"Point"}
}