{
  "type": "Feature",
  "properties": {
    "iso:country":"ES",
    "sg:address":"Calle de Leopoldo Lugones, 14",
    "sg:city":"Lugones",
    "sg:orig_category":"Bares, Piano",
    "sg:phone":"+34 985 26 42 45",
    "sg:postcode":"33420",
    "sg:province":"Asturias",
    "wof:name":"Garcia Gonzalez Ruben",
    "wof:placetype":"venue"
},
  "geometry": {"coordinates":[-5.805560112,43.4021759033],"type":"Point"}
}