{
  "type": "Feature",
  "properties": {
    "addr:full":"Carrer de Sol, 28 Barriada Nova Barcelona 08420",
    "addr:housenumber":"28",
    "addr:postcode":"08420",
    "addr:street":"Carrer De Sol;Nova Barcelona",
    "iso:country":"ES",
    "sg:address":"Carrer de Sol, 28",
    "sg:city":"Barriada Nova",
    "sg:orig_category":"Arquitectos",
    "sg:phone":"+34 938 40 07 11",
    "sg:postcode":"08420",
    "sg:province":"Barcelona",
    "wof:name":"Inversiones Arquitectononicas S.l.",
    "wof:placetype":"venue"
},
  "geometry": {"coordinates":[2.2783401012,41.6220207214],"type":"Point"}
}