{
  "type": "Feature",
  "properties": {
    "iso:country":"ES",
    "sg:address":"Calle de Pamplona, 41",
    "sg:city":"Sevilla",
    "sg:orig_category":"Reposter\u00cdas",
    "sg:phone":"+34 954 68 08 88",
    "sg:postcode":"41014",
    "sg:province":"Sevilla",
    "wof:name":"Montes Barrera Antonio",
    "wof:placetype":"venue"
},
  "geometry": {"coordinates":[-5.9660701752,37.3215255737],"type":"Point"}
}