{
  "type": "Feature",
  "properties": {
    "iso:country":"ES",
    "sg:address":"Calle de Orense (de), 3",
    "sg:city":"Alcobendas",
    "sg:orig_category":"Fotocopias, Reprograf\u00cda",
    "sg:phone":"+34 916 63 89 77",
    "sg:postcode":"28100",
    "sg:province":"Madrid",
    "sg:website":"www.reprotel.com",
    "wof:name":"Reprotel Servicios Digitales S.l.",
    "wof:placetype":"venue"
},
  "geometry": {"coordinates":[-3.6363730431,40.542137146],"type":"Point"}
}