{
  "type": "Feature",
  "properties": {
    "iso:country":"ES",
    "sg:address":"Calle de Minarete, 15",
    "sg:city":"Barriada De Santiago",
    "sg:orig_category":"Contenedores (mercanc\u00cdas)",
    "sg:phone":"+34 968 50 19 66",
    "sg:postcode":"30202",
    "sg:province":"Murcia",
    "wof:name":"Transportes Carthago S.l.",
    "wof:placetype":"venue"
},
  "geometry": {"coordinates":[-1.020810008,37.6775283813],"type":"Point"}
}