{
  "type": "Feature",
  "properties": {
    "iso:country":"ES",
    "sg:address":"G.v. Corts Catalanes, 544",
    "sg:city":"Barcelona",
    "sg:orig_category":"Abogados",
    "sg:phone":"+34 934 51 73 90",
    "sg:postcode":"08011",
    "sg:province":"Barcelona",
    "wof:name":"Ribas Balcells Rosa",
    "wof:placetype":"venue"
},
  "geometry": {"coordinates":[2.1601610184,41.3829078674],"type":"Point"}
}