{
  "type": "Feature",
  "properties": {
    "iso:country":"ES",
    "sg:address":"Carr Virgen Del Mar, 88",
    "sg:city":"Playa",
    "sg:orig_category":"Centros M\u00c9dicos Y Sociales, Dispensarios",
    "sg:phone":"+34 962 85 50 69",
    "sg:postcode":"46780",
    "sg:province":"Valencia",
    "wof:name":"Ayuntamiento De Oliva",
    "wof:placetype":"venue"
},
  "geometry": {"coordinates":[-0.0887352973,38.925075531],"type":"Point"}
}