{
  "type": "Feature",
  "properties": {
    "addr:full":"Avda Ramon Ortega, 2 Denia Alicante 03700",
    "addr:housenumber":"2",
    "addr:postcode":"03700",
    "addr:street":"Avda Ramon Ortega",
    "iso:country":"ES",
    "sg:address":"Avda Ramon Ortega, 2",
    "sg:city":"Denia",
    "sg:orig_category":"Promotores Constructores",
    "sg:phone":"+34 966 42 16 32",
    "sg:postcode":"03700",
    "sg:province":"Alicante",
    "wof:name":"Era Pedra S.l.",
    "wof:placetype":"venue"
},
  "geometry": {"coordinates":[0.1020890027,38.8369827271],"type":"Point"}
}