{
  "type": "Feature",
  "properties": {
    "iso:country":"ES",
    "sg:address":"Calle de Espiritu Santo, 14",
    "sg:city":"Puerto De Santa Maria",
    "sg:orig_category":"Semiller\u00cdas",
    "sg:phone":"+34 956 87 67 85",
    "sg:postcode":"11500",
    "sg:province":"C\u00e1diz",
    "wof:name":"Valoraciones Organicas Agricolas S.l.",
    "wof:placetype":"venue"
},
  "geometry": {"coordinates":[-6.2214097977,36.6032180786],"type":"Point"}
}