{
  "type": "Feature",
  "properties": {
    "addr:full":"Plaz Miguel Hernandez, 2 Segovia Segovia 40006",
    "addr:housenumber":"2",
    "addr:postcode":"40006",
    "addr:street":"Miguel Hernandez",
    "iso:country":"ES",
    "sg:address":"Plaz Miguel Hernandez, 2",
    "sg:city":"Segovia",
    "sg:orig_category":"Guarder\u00cdas",
    "sg:phone":"+34 921 43 64 06",
    "sg:postcode":"40006",
    "sg:province":"Segovia",
    "wof:name":"Cruz Garcia Jesus",
    "wof:placetype":"venue"
},
  "geometry": {"coordinates":[-4.0998849869,40.9343566895],"type":"Point"}
}