{
  "type": "Feature",
  "properties": {
    "addr:full":"Calle de Antillano Campos, 14 Sevilla Sevilla 41010",
    "addr:housenumber":"14",
    "addr:postcode":"41010",
    "addr:street":"Calle De Antillano Campos",
    "iso:country":"ES",
    "sg:address":"Calle de Antillano Campos, 14",
    "sg:city":"Sevilla",
    "sg:orig_category":"Artesan\u00cda Y Trabajos Manuales: Suministros (al Por Menor)",
    "sg:phone":"+34 954 33 21 79",
    "sg:postcode":"41010",
    "sg:province":"Sevilla",
    "sg:website":"www.ceramicatriana.com",
    "wof:name":"Revilla Esca\u00f1o Pedro Manuel",
    "wof:placetype":"venue"
},
  "geometry": {"coordinates":[-6.0049781799,37.3850822449],"type":"Point"}
}