{
  "type": "Feature",
  "properties": {
    "iso:country":"ES",
    "sg:address":"Calle de Conde De Xiquena, 8",
    "sg:city":"Madrid",
    "sg:classifiers":[
        {
            "category":"Arts & Performance",
            "subcategory":"Art Gallery",
            "type":"Entertainment"
        }
    ],
    "sg:phone":"+34 915 32 40 93",
    "sg:postcode":"28004",
    "sg:province":"Madrid",
    "sg:tags":[
        "arte",
        "de",
        "galer\u00cdas"
    ],
    "sg:website":"www.antoniomachon.com",
    "wof:name":"Machon Durango Antonio",
    "wof:placetype":"venue"
},
  "geometry": {"coordinates":[-3.6941246986,40.422908783],"type":"Point"}
}