{
  "type": "Feature",
  "properties": {
    "iso:country":"ES",
    "sg:address":"Calle de Ruiz De Alda, S/n",
    "sg:city":"Ezcaroz",
    "sg:orig_category":"Serrer\u00cdas De Madera",
    "sg:phone":"+34 948 89 01 05",
    "sg:postcode":"31690",
    "sg:province":"Navarra",
    "wof:name":"Maderas Roda S.l.",
    "wof:placetype":"venue"
},
  "geometry": {"coordinates":[-1.0951789618,42.8848800659],"type":"Point"}
}