{
  "type": "Feature",
  "properties": {
    "addr:full":"Son Bosch, 20 Andratx Islas Baleares 07150",
    "addr:housenumber":"20",
    "addr:postcode":"07150",
    "addr:street":"Bosch",
    "iso:country":"ES",
    "sg:address":"Son Bosch, 20",
    "sg:city":"Andratx",
    "sg:orig_category":"Alquiler De Casas Y Habitaciones Amuebladas",
    "sg:phone":"+34 971 23 57 16",
    "sg:postcode":"07150",
    "sg:province":"Islas Baleares",
    "wof:name":"Construcciones Nova Andratx S.l.u",
    "wof:placetype":"venue"
},
  "geometry": {"coordinates":[2.4238491058,39.5748100281],"type":"Point"}
}