{
  "type": "Feature",
  "properties": {
    "addr:full":"Carr Campanar, 7 Sils Girona 17410",
    "addr:housenumber":"7",
    "addr:postcode":"17410",
    "addr:street":"Carr Campanar",
    "iso:country":"ES",
    "sg:address":"Carr Campanar, 7",
    "sg:city":"Sils",
    "sg:orig_category":"Inmobiliaria (agencias)",
    "sg:phone":"+34 972 85 36 64",
    "sg:postcode":"17410",
    "sg:province":"Girona",
    "wof:name":"Quintana Mundet Maria Neus",
    "wof:placetype":"venue"
},
  "geometry": {"coordinates":[2.7422499657,41.8068771362],"type":"Point"}
}