{
  "type": "Feature",
  "properties": {
    "iso:country":"ES",
    "sg:address":"Calle de Parras (las), S/n",
    "sg:city":"Villamayor De Los Montes",
    "sg:orig_category":"Fabricaci\u00d3n Y Venta De Volquetes Y Remolques",
    "sg:phone":"+34 947 18 91 55",
    "sg:postcode":"09339",
    "sg:province":"Burgos",
    "wof:name":"Cantero Benito Y Otro S.cv.",
    "wof:placetype":"venue"
},
  "geometry": {"coordinates":[-3.7636899948,42.1072807312],"type":"Point"}
}