{
  "type": "Feature",
  "properties": {
    "iso:country":"ES",
    "sg:address":"Calle de Hernan Cortes, 38",
    "sg:city":"Riba-roja Turia",
    "sg:orig_category":"Fabrica De Cer\u00c1micas",
    "sg:phone":"+34 962 77 07 50",
    "sg:postcode":"46190",
    "sg:province":"Valencia",
    "wof:name":"Regina Artesania S.l.",
    "wof:placetype":"venue"
},
  "geometry": {"coordinates":[-0.5743650198,39.5491790771],"type":"Point"}
}