{
  "type": "Feature",
  "properties": {
    "addr:full":"Calle de Sellent, 5 Valencia Valencia 46019",
    "addr:housenumber":"5",
    "addr:postcode":"46019",
    "addr:street":"Calle De Sellent",
    "iso:country":"ES",
    "sg:address":"Calle de Sellent, 5",
    "sg:city":"Valencia",
    "sg:orig_category":"Cl\u00cdnicas Dentales",
    "sg:phone":"+34 963 68 01 41",
    "sg:postcode":"46019",
    "sg:province":"Valencia",
    "wof:name":"Casal-awad Odontologos C.b.",
    "wof:placetype":"venue"
},
  "geometry": {"coordinates":[-0.3683690131,39.4936676025],"type":"Point"}
}