{
  "type": "Feature",
  "properties": {
    "addr:full":"Av Costa I Llobera, De, 10 Arta Islas Baleares 07570",
    "addr:housenumber":"10",
    "addr:postcode":"07570",
    "addr:street":"Av Costa I Llobera De;Islas Baleares",
    "iso:country":"ES",
    "sg:address":"Av Costa I Llobera, De, 10",
    "sg:city":"Arta",
    "sg:orig_category":"Molduras, Junquillos, Listones Y Molduras Perforadas",
    "sg:phone":"+34 971 83 65 80",
    "sg:postcode":"07570",
    "sg:province":"Islas Baleares",
    "wof:name":"Negre Escanellas Miguel",
    "wof:placetype":"venue"
},
  "geometry": {"coordinates":[3.3270459175,39.70520401],"type":"Point"}
}