{
  "type": "Feature",
  "properties": {
    "addr:full":"Ptge Castavi, 3 Eivissa Islas Baleares 07800",
    "addr:housenumber":"3",
    "addr:postcode":"07800",
    "addr:street":"Ptge Castavi",
    "iso:country":"ES",
    "sg:address":"Ptge Castavi, 3",
    "sg:city":"Eivissa",
    "sg:orig_category":"Bisuter\u00cda, Joyer\u00cda, Relojer\u00cda (al Por Menor)",
    "sg:phone":"+34 971 30 07 23",
    "sg:postcode":"07800",
    "sg:province":"Islas Baleares",
    "wof:name":"Eurosterling S.l.",
    "wof:placetype":"venue"
},
  "geometry": {"coordinates":[1.4283030033,38.9100532532],"type":"Point"}
}