{
  "type": "Feature",
  "properties": {
    "addr:full":"Calle de Honorio Lozano, 35 Estacion Madrid 28400",
    "addr:housenumber":"35",
    "addr:postcode":"28400",
    "addr:street":"Calle De Honorio Lozano",
    "iso:country":"ES",
    "sg:address":"Calle de Honorio Lozano, 35",
    "sg:city":"Estacion",
    "sg:orig_category":"Zapatos (al Por Menor)",
    "sg:phone":"+34 918 49 26 96",
    "sg:postcode":"28400",
    "sg:province":"Madrid",
    "wof:name":"Serimar Zapateros S.l.l.",
    "wof:placetype":"venue"
},
  "geometry": {"coordinates":[-3.9919650555,40.6455612183],"type":"Point"}
}