{
  "type": "Feature",
  "properties": {
    "iso:country":"ES",
    "sg:address":"Carr Castella, 21",
    "sg:city":"Eivissa",
    "sg:orig_category":"M\u00c9dicos: Oftalmolog\u00cda",
    "sg:phone":"+34 971 30 34 16",
    "sg:postcode":"07800",
    "sg:province":"Islas Baleares",
    "wof:name":"Jimenez Corral Maria",
    "wof:placetype":"venue"
},
  "geometry": {"coordinates":[1.4288890362,38.9097480774],"type":"Point"}
}