{
  "type": "Feature",
  "properties": {
    "addr:full":"Calle de Maestro Calles, 6 Santurtzi Vizcaya 48980",
    "addr:postcode":"48980",
    "addr:street":"Calle De Maestro Calles 6",
    "iso:country":"ES",
    "sg:address":"Calle de Maestro Calles, 6",
    "sg:city":"Santurtzi",
    "sg:orig_category":"Fabricaci\u00d3n, Venta De Cuadros, Accesorios Para Enmarcar",
    "sg:phone":"+34 944 62 66 49",
    "sg:postcode":"48980",
    "sg:province":"Vizcaya",
    "wof:name":"Fonseca Alfonso Maria Soledad",
    "wof:placetype":"venue"
},
  "geometry": {"coordinates":[-3.0349891186,43.3285102844],"type":"Point"}
}