{
  "type": "Feature",
  "properties": {
    "iso:country":"ES",
    "sg:address":"Calle de Alcora, 221",
    "sg:city":"Almazora",
    "sg:orig_category":"Estancos",
    "sg:phone":"+34 964 56 40 27",
    "sg:postcode":"12550",
    "sg:province":"Castell\u00f3n",
    "wof:name":"Romera Torres Antonio",
    "wof:placetype":"venue"
},
  "geometry": {"coordinates":[-0.0702527016,39.9479370117],"type":"Point"}
}