{
  "type": "Feature",
  "properties": {
    "addr:full":"Calle de Juan Rumeu Garcia, 28 Santa Cruz De Tenerife Santa Cruz De Tenerife 38008",
    "addr:housenumber":"28",
    "addr:postcode":"38008",
    "addr:street":"Calle De Juan Rumeu Garcia",
    "iso:country":"ES",
    "sg:address":"Calle de Juan Rumeu Garcia, 28",
    "sg:city":"Santa Cruz De Tenerife",
    "sg:orig_category":"Organizaciones Internacionales",
    "sg:phone":"+34 922 22 11 42",
    "sg:postcode":"38008",
    "sg:province":"Santa Cruz De Tenerife",
    "wof:name":"Federacion De Asociacion De Sordos De Las Islas Canarias",
    "wof:placetype":"venue"
},
  "geometry": {"coordinates":[-16.2734603882,28.4652614594],"type":"Point"}
}