{
  "type": "Feature",
  "properties": {
    "addr:full":"Avda San Juan De Dios, S/n Bormujos Sevilla 41930",
    "addr:housenumber":"s / n",
    "addr:postcode":"41930",
    "addr:street":"Avda San Juan De Dios",
    "iso:country":"ES",
    "sg:address":"Avda San Juan De Dios, S/n",
    "sg:city":"Bormujos",
    "sg:orig_category":"Empresas De Limpieza",
    "sg:phone":"+34 955 72 46 77",
    "sg:postcode":"41930",
    "sg:province":"Sevilla",
    "wof:name":"Mantenimiento Y Montajes Elimco S.a.",
    "wof:placetype":"venue"
},
  "geometry": {"coordinates":[-6.0823941231,37.367729187],"type":"Point"}
}