{
  "type": "Feature",
  "properties": {
    "iso:country":"ES",
    "sg:address":"Calle de Cerrada, 10",
    "sg:city":"Valladolid",
    "sg:orig_category":"Congelados: Productos Alimentarios (fabricaci\u00d3n, Al Por Mayor)",
    "sg:phone":"+34 983 26 60 49",
    "sg:postcode":"47010",
    "sg:province":"Valladolid",
    "wof:name":"Inversiones Mamipa S.l.",
    "wof:placetype":"venue"
},
  "geometry": {"coordinates":[-4.7204036713,41.659992218],"type":"Point"}
}