{
  "type": "Feature",
  "properties": {
    "addr:full":"Avda Reyes Catolicos, 3 Jumilla Murcia 30520",
    "addr:housenumber":"3",
    "addr:postcode":"30520",
    "addr:street":"Avda Reyes Catolicos",
    "iso:country":"ES",
    "sg:address":"Avda Reyes Catolicos, 3",
    "sg:city":"Jumilla",
    "sg:orig_category":"Hielo Artificial (fabricaci\u00d3n, Distribuci\u00d3n)",
    "sg:phone":"+34 968 78 22 68",
    "sg:postcode":"30520",
    "sg:province":"Murcia",
    "wof:name":"Burruezo Mateo S.l.",
    "wof:placetype":"venue"
},
  "geometry": {"coordinates":[-1.3275029659,38.4731826782],"type":"Point"}
}