{
  "type": "Feature",
  "properties": {
    "addr:full":"Calle de Moscu, 14 Madrid Madrid 28022",
    "addr:housenumber":"14",
    "addr:postcode":"madrid;28022",
    "addr:street":"Calle De Moscu",
    "iso:country":"ES",
    "sg:address":"Calle de Moscu, 14",
    "sg:city":"Madrid",
    "sg:orig_category":"Fisioterapia",
    "sg:phone":"+34 913 13 26 64",
    "sg:postcode":"28022",
    "sg:province":"Madrid",
    "wof:name":"Pe\u00f1a Fernandez Carlos",
    "wof:placetype":"venue"
},
  "geometry": {"coordinates":[-3.6012670994,40.4256286621],"type":"Point"}
}