{
  "type": "Feature",
  "properties": {
    "iso:country":"ES",
    "sg:address":"Carrer de Sala Boadella, 6",
    "sg:city":"Castellar Valles",
    "sg:orig_category":"Bibliotecas, Mediatecas",
    "sg:phone":"+34 937 14 47 35",
    "sg:postcode":"08211",
    "sg:province":"Barcelona",
    "wof:name":"Ajuntament De Castellar Del Valles",
    "wof:placetype":"venue"
},
  "geometry": {"coordinates":[2.0879302025,41.6154098511],"type":"Point"}
}