{
  "type": "Feature",
  "properties": {
    "iso:country":"ES",
    "sg:address":"Ctra Viella (de), Km. 0064,1",
    "sg:city":"Benabarre",
    "sg:orig_category":"Distribuci\u00d3n De Petr\u00d3leo Y Derivados",
    "sg:phone":"+34 974 54 30 97",
    "sg:postcode":"22580",
    "sg:province":"Huesca",
    "wof:name":"Estacion De Servicio Benabarre S.l.",
    "wof:placetype":"venue"
},
  "geometry": {"coordinates":[0.4829050004,42.1056632996],"type":"Point"}
}