{
  "type": "Feature",
  "properties": {
    "iso:country":"ES",
    "sg:address":"Carrer de Josep Mestre I Puig, 12",
    "sg:city":"S. Pere Ribes",
    "sg:orig_category":"Productos Qu\u00cdmicos (fabricaci\u00d3n, Al Por Mayor)",
    "sg:phone":"+34 938 96 29 26",
    "sg:postcode":"08810",
    "sg:province":"Barcelona",
    "wof:name":"Benefit Of Food S.l.",
    "wof:placetype":"venue"
},
  "geometry": {"coordinates":[1.7817059755,41.2585906982],"type":"Point"}
}