{
  "type": "Feature",
  "properties": {
    "iso:country":"ES",
    "sg:address":"Ctra Zaragoza, Km. 0098,0",
    "sg:city":"Fontellas",
    "sg:orig_category":"Fabricaci\u00d3n De Muebles",
    "sg:phone":"+34 948 84 77 30",
    "sg:postcode":"31512",
    "sg:province":"Navarra",
    "wof:name":"Bravo Serrano Francisco Javier",
    "wof:placetype":"venue"
},
  "geometry": {"coordinates":[-1.5812790394,42.0257110596],"type":"Point"}
}