{
  "type": "Feature",
  "properties": {
    "iso:country":"ES",
    "sg:address":"Avda Blasco Iba\u00d1ez, 168",
    "sg:city":"Valencia",
    "sg:orig_category":"Telefon\u00cda: Instaladores Varios",
    "sg:phone":"+34 963 56 45 46",
    "sg:postcode":"46022",
    "sg:province":"Valencia",
    "wof:name":"Balanta Mera Milton Fabian",
    "wof:placetype":"venue"
},
  "geometry": {"coordinates":[-0.3400182128,39.4713363647],"type":"Point"}
}