{
  "type": "Feature",
  "properties": {
    "iso:country":"ES",
    "sg:address":"Calle de San Vicente, 39",
    "sg:city":"Castellon",
    "sg:orig_category":"Bisuter\u00cda, Joyer\u00cda, Relojer\u00cda (al Por Menor)",
    "sg:phone":"+34 964 25 06 57",
    "sg:postcode":"12002",
    "sg:province":"Castell\u00f3n",
    "wof:name":"Fernandez Serra Jose Vicente",
    "wof:placetype":"venue"
},
  "geometry": {"coordinates":[-0.0418369994,39.9856910706],"type":"Point"}
}