{
  "type": "Feature",
  "properties": {
    "addr:full":"Av. Zaragoza, 63 Iru\u00f1a Navarra 31005",
    "addr:housenumber":"63",
    "addr:postcode":"31005",
    "addr:street":"Av. Zaragoza",
    "iso:country":"ES",
    "sg:address":"Av. Zaragoza, 63",
    "sg:city":"Iru\u00f1a",
    "sg:orig_category":"Ropa Para Se\u00d1oras Y Caballeros (al Por Menor)",
    "sg:phone":"+34 948 23 51 24",
    "sg:postcode":"31005",
    "sg:province":"Navarra",
    "wof:name":"Esparza Esparza Jose Luis",
    "wof:placetype":"venue"
},
  "geometry": {"coordinates":[-1.6442090273,42.8037796021],"type":"Point"}
}