{
  "type": "Feature",
  "properties": {
    "iso:country":"ES",
    "sg:address":"Urbanizacion Los Alisios, S/n",
    "sg:city":"Garita",
    "sg:orig_category":"Promotores Constructores",
    "sg:phone":"+34 928 13 34 87",
    "sg:postcode":"35212",
    "sg:province":"Las Palmas",
    "wof:name":"El Rincon S.l.",
    "wof:placetype":"venue"
},
  "geometry": {"coordinates":[-15.3836965561,28.0140953064],"type":"Point"}
}