{
  "type": "Feature",
  "properties": {
    "addr:full":"Ctra Madrid, S/n Salamanca Salamanca 37008",
    "addr:housenumber":"s / n",
    "addr:postcode":"37008",
    "addr:street":"Ctra Madrid",
    "iso:country":"ES",
    "sg:address":"Ctra Madrid, S/n",
    "sg:city":"Salamanca",
    "sg:orig_category":"Deportes Diversos",
    "sg:phone":"+34 923 21 72 90",
    "sg:postcode":"37008",
    "sg:province":"Salamanca",
    "wof:name":"Federacion Castellano Leonesa De Tiro Olimpico",
    "wof:placetype":"venue"
},
  "geometry": {"coordinates":[-5.6684308052,40.9540176392],"type":"Point"}
}