{
  "type": "Feature",
  "properties": {
    "addr:full":"Calle de Catedratico D.j.cisneros, 16 Alacant Alicante 03012",
    "addr:housenumber":"16",
    "addr:postcode":"03012",
    "addr:street":"Calle De Catedratico D.J.Cisneros",
    "iso:country":"ES",
    "sg:address":"Calle de Catedratico D.j.cisneros, 16",
    "sg:city":"Alacant",
    "sg:orig_category":"Caf\u00c9s, Bares, Cervecer\u00cdas",
    "sg:phone":"+34 965 25 74 18",
    "sg:postcode":"03012",
    "sg:province":"Alicante",
    "wof:name":"Fernandez Zamora Pedro Alfonso",
    "wof:placetype":"venue"
},
  "geometry": {"coordinates":[-0.4785731137,38.3605804443],"type":"Point"}
}