{
  "type": "Feature",
  "properties": {
    "iso:country":"ES",
    "sg:address":"Calle de Betsaide, 4",
    "sg:city":"Elorrio",
    "sg:orig_category":"Comercio De Piezas De Recambio Y De Accesorios De Veh\u00cdculos, Veh\u00cdculos Industriales",
    "sg:phone":"+34 946 23 19 20",
    "sg:postcode":"48230",
    "sg:province":"Vizcaya",
    "sg:website":"www.iguria.com",
    "wof:name":"Iguria S.a.",
    "wof:placetype":"venue"
},
  "geometry": {"coordinates":[-2.5409374237,43.1263999939],"type":"Point"}
}