{
  "type": "Feature",
  "properties": {
    "iso:country":"ES",
    "sg:address":"Av Dr. Fleming, De, 16",
    "sg:city":"S. Antoni Portmany",
    "sg:orig_category":"Empresas De Labores Complejas De Carga Y Descarga, Montaje Con Elevadores",
    "sg:phone":"+34 971 34 74 36",
    "sg:postcode":"07820",
    "sg:province":"Islas Baleares",
    "wof:name":"Centro De Buceo Arenal S.l.",
    "wof:placetype":"venue"
},
  "geometry": {"coordinates":[1.3103170395,38.9687080383],"type":"Point"}
}