{
  "type": "Feature",
  "properties": {
    "addr:full":"Avda Rafael Cabrera, 1 Palmas De Gran Canaria Las Palmas 35002",
    "addr:housenumber":"1",
    "addr:postcode":"35002",
    "addr:street":"Avda Rafael Cabrera",
    "iso:country":"ES",
    "sg:address":"Avda Rafael Cabrera, 1",
    "sg:city":"Palmas De Gran Canaria",
    "sg:orig_category":"Audiovisuales, Tv, Hi",
    "sg:phone":"+34 928 36 70 96",
    "sg:postcode":"35002",
    "sg:province":"Las Palmas",
    "sg:website":"www.rpg.es",
    "wof:name":"Ibervideo R.g.b. S.l.",
    "wof:placetype":"venue"
},
  "geometry": {"coordinates":[-15.4143257141,28.1048049927],"type":"Point"}
}