{
  "type": "Feature",
  "properties": {
    "addr:full":"Carrer de Calabria, 44 Barcelona Barcelona 08015",
    "addr:housenumber":"44",
    "addr:postcode":"08015",
    "addr:street":"Carrer De Calabria",
    "iso:country":"ES",
    "sg:address":"Carrer de Calabria, 44",
    "sg:city":"Barcelona",
    "sg:orig_category":"Carnicer\u00cdas, Carnicer\u00cdas",
    "sg:phone":"+34 933 25 32 94",
    "sg:postcode":"08015",
    "sg:province":"Barcelona",
    "wof:name":"Finper, Perez Fenoll Asociados S.l.",
    "wof:placetype":"venue"
},
  "geometry": {"coordinates":[2.1590230465,41.3768692017],"type":"Point"}
}