{
  "type": "Feature",
  "properties": {
    "addr:full":"Barr Elexalde, 22 Elexalde Galdakao Vizcaya 48960",
    "addr:housenumber":"22",
    "addr:postcode":"48960",
    "addr:street":"Elexalde",
    "iso:country":"ES",
    "sg:address":"Barr Elexalde, 22",
    "sg:city":"Elexalde Galdakao",
    "sg:orig_category":"Restaurantes",
    "sg:phone":"+34 944 56 00 05",
    "sg:postcode":"48960",
    "sg:province":"Vizcaya",
    "wof:name":"Restaurantes Andra Mari S.a.",
    "wof:placetype":"venue"
},
  "geometry": {"coordinates":[-2.8470389843,43.2298049927],"type":"Point"}
}