{
  "type": "Feature",
  "properties": {
    "iso:country":"ES",
    "sg:address":"Carr Del Dos De Maig, 29",
    "sg:city":"Ontinyent",
    "sg:orig_category":"Promotores Constructores",
    "sg:phone":"+34 962 38 18 29",
    "sg:postcode":"46870",
    "sg:province":"Valencia",
    "wof:name":"Construcciones Jose Vidal Llin S.l.",
    "wof:placetype":"venue"
},
  "geometry": {"coordinates":[-0.6037430167,38.8246040344],"type":"Point"}
}