{
  "type": "Feature",
  "properties": {
    "iso:country":"ES",
    "sg:address":"Abejeras, 41",
    "sg:city":"Iru\u00f1a",
    "sg:classifiers":[
        {
            "category":"Professional",
            "subcategory":"Management & Consulting",
            "type":"Services"
        }
    ],
    "sg:phone":"+34 948 15 11 00",
    "sg:postcode":"31007",
    "sg:province":"Navarra",
    "sg:tags":[
        "asesor\u00cda",
        "en",
        "marketing"
    ],
    "wof:name":"Open Consulting De Informes S.l.",
    "wof:placetype":"venue"
},
  "geometry": {"coordinates":[-1.6472760439,42.8041572571],"type":"Point"}
}