{
  "type": "Feature",
  "properties": {
    "addr:full":"Carrer de Industria, 55 S. Boi Llobregat Barcelona 08830",
    "addr:housenumber":"55",
    "addr:postcode":"08830",
    "addr:street":"Carrer De Industria",
    "iso:country":"ES",
    "sg:address":"Carrer de Industria, 55",
    "sg:city":"S. Boi Llobregat",
    "sg:orig_category":"Organizaciones Internacionales",
    "sg:phone":"+34 936 30 92 47",
    "sg:postcode":"08830",
    "sg:province":"Barcelona",
    "wof:name":"Asc Age Adventista Para El Ds Rr Ass",
    "wof:placetype":"venue"
},
  "geometry": {"coordinates":[2.0442609787,41.3402633667],"type":"Point"}
}