{
  "type": "Feature",
  "properties": {
    "iso:country":"ES",
    "sg:address":"Calle de Comunidad De Madrid, 39",
    "sg:city":"Rozas De Madrid",
    "sg:orig_category":"Ropa Para Se\u00d1oras (al Por Menor)",
    "sg:phone":"+34 916 36 02 41",
    "sg:postcode":"28230",
    "sg:province":"Madrid",
    "wof:name":"Garcia Baez Azucena",
    "wof:placetype":"venue"
},
  "geometry": {"coordinates":[-3.8720195293,40.4840354919],"type":"Point"}
}