{
  "type": "Feature",
  "properties": {
    "addr:full":"Calle de Arganda, 39 Madrid Madrid 28005",
    "addr:housenumber":"39",
    "addr:postcode":"madrid;28005",
    "addr:street":"Calle De Arganda",
    "iso:country":"ES",
    "sg:address":"Calle de Arganda, 39",
    "sg:city":"Madrid",
    "sg:orig_category":"Ense\u00d1anza Variada",
    "sg:phone":"+34 915 17 24 47",
    "sg:postcode":"28005",
    "sg:province":"Madrid",
    "wof:name":"Izquierdo Relojero S.l.",
    "wof:placetype":"venue"
},
  "geometry": {"coordinates":[-3.7042257786,40.3972396851],"type":"Point"}
}