{
  "type": "Feature",
  "properties": {
    "iso:country":"ES",
    "sg:address":"Carrer de Jaume Huguet, 23",
    "sg:city":"Valls",
    "sg:orig_category":"Laboratorios Y Trabajos De Fotograf\u00cda, V\u00cddeo Y Cine",
    "sg:phone":"+34 977 61 25 00",
    "sg:postcode":"43800",
    "sg:province":"Tarragona",
    "sg:website":"www.fotoprix.es",
    "wof:name":"Amarcoy S. L.",
    "wof:placetype":"venue"
},
  "geometry": {"coordinates":[1.2512652874,41.2868118286],"type":"Point"}
}