{
  "type": "Feature",
  "properties": {
    "addr:full":"Calle de Alcala, 622 Madrid Madrid 28022",
    "addr:housenumber":"622",
    "addr:postcode":"28022",
    "addr:street":"Calle De Alcala",
    "iso:country":"ES",
    "sg:address":"Calle de Alcala, 622",
    "sg:city":"Madrid",
    "sg:orig_category":"Muebles, Minoristas",
    "sg:phone":"+34 913 20 77 88",
    "sg:postcode":"28022",
    "sg:province":"Madrid",
    "wof:name":"Vital Cocina S.l.",
    "wof:placetype":"venue"
},
  "geometry": {"coordinates":[-3.6097979546,40.4480171204],"type":"Point"}
}