{
  "type": "Feature",
  "properties": {
    "addr:full":"Calle de Ribadesella, 11 Gijon Asturias 33207",
    "addr:housenumber":"11",
    "addr:postcode":"33207",
    "addr:street":"Calle De Ribadesella",
    "iso:country":"ES",
    "sg:address":"Calle de Ribadesella, 11",
    "sg:city":"Gijon",
    "sg:orig_category":"Arquitectos",
    "sg:phone":"+34 985 35 38 28",
    "sg:postcode":"33207",
    "sg:province":"Asturias",
    "wof:name":"Vicente Diez Faixat Y Justo Garcia Arquitectos S.l.",
    "wof:placetype":"venue"
},
  "geometry": {"coordinates":[-5.6681470871,43.538936615],"type":"Point"}
}