{
  "type": "Feature",
  "properties": {
    "addr:full":"Calle de Andres Ramos, 3 Palmas De Gran Canaria Las Palmas 35016",
    "addr:housenumber":"3",
    "addr:postcode":"35016",
    "addr:street":"Calle De Andres Ramos",
    "iso:country":"ES",
    "sg:address":"Calle de Andres Ramos, 3",
    "sg:city":"Palmas De Gran Canaria",
    "sg:orig_category":"Empresarios",
    "sg:phone":"+34 928 31 47 52",
    "sg:postcode":"35016",
    "sg:province":"Las Palmas",
    "wof:name":"Santana Cabrera Juan Manuel",
    "wof:placetype":"venue"
},
  "geometry": {"coordinates":[-15.4193592072,28.0854454041],"type":"Point"}
}