{
  "type": "Feature",
  "properties": {
    "iso:country":"ES",
    "sg:address":"Calle de Miel, 8",
    "sg:city":"Aranda Duero",
    "sg:orig_category":"Ropa Para Se\u00d1oras (al Por Menor)",
    "sg:phone":"+34 947 50 48 16",
    "sg:postcode":"09400",
    "sg:province":"Burgos",
    "wof:name":"Adrian Barbero Isabel",
    "wof:placetype":"venue"
},
  "geometry": {"coordinates":[-3.6891479492,41.6708068848],"type":"Point"}
}