{
  "type": "Feature",
  "properties": {
    "addr:full":"Carrer de Bisbe Sivilla, 12 Calella Barcelona 08370",
    "addr:housenumber":"12",
    "addr:postcode":"08370",
    "addr:street":"Carrer De Bisbe Sivilla",
    "iso:country":"ES",
    "sg:address":"Carrer de Bisbe Sivilla, 12",
    "sg:city":"Calella",
    "sg:orig_category":"Torrefactado De Caf\u00c9",
    "sg:phone":"+34 937 69 36 78",
    "sg:postcode":"08370",
    "sg:province":"Barcelona",
    "wof:name":"Joraser Kf S.l.",
    "wof:placetype":"venue"
},
  "geometry": {"coordinates":[2.6577138901,41.6134300232],"type":"Point"}
}