{
  "type": "Feature",
  "properties": {
    "iso:country":"ES",
    "sg:address":"Carrer de Francesc Salvans, 52",
    "sg:city":"Terrassa",
    "sg:orig_category":"Servicios De Telecomunicaciones",
    "sg:phone":"+34 937 35 87 44",
    "sg:postcode":"08225",
    "sg:province":"Barcelona",
    "wof:name":"Glotelas S.l.",
    "wof:placetype":"venue"
},
  "geometry": {"coordinates":[2.013463974,41.5735816956],"type":"Point"}
}