{
  "type": "Feature",
  "properties": {
    "iso:country":"ES",
    "sg:address":"Calle de Juan Manuel Duran Gonzalez, 7",
    "sg:city":"Palmas De Gran Canaria",
    "sg:orig_category":"Asesor\u00cda De Formaci\u00d3n Y Gesti\u00d3n De Personal",
    "sg:phone":"+34 928 27 09 12",
    "sg:postcode":"35007",
    "sg:province":"Las Palmas",
    "wof:name":"Orive Montesdeoca Roberto Javier",
    "wof:placetype":"venue"
},
  "geometry": {"coordinates":[-15.433052063,28.135515213],"type":"Point"}
}