{
  "type": "Feature",
  "properties": {
    "iso:country":"ES",
    "sg:address":"Calle de Real, 45",
    "sg:city":"Villanueva Reina",
    "sg:orig_category":"Farmacias",
    "sg:phone":"+34 953 53 70 87",
    "sg:postcode":"23730",
    "sg:province":"Ja\u00e9n",
    "wof:name":"Cano Ortega Ana Maria",
    "wof:placetype":"venue"
},
  "geometry": {"coordinates":[-3.9163150787,38.0052261353],"type":"Point"}
}