{
  "type": "Feature",
  "properties": {
    "addr:full":"Calle de Goya, 66 Madrid Madrid 28001",
    "addr:housenumber":"66",
    "addr:postcode":"madrid;28001",
    "addr:street":"Calle De Goya",
    "iso:country":"ES",
    "sg:address":"Calle de Goya, 66",
    "sg:city":"Madrid",
    "sg:orig_category":"Trajes Y Adornos De Boda (confecci\u00d3n, Al Por Menor)",
    "sg:phone":"+34 914 31 10 42",
    "sg:postcode":"28001",
    "sg:province":"Madrid",
    "wof:name":"Costura Do\u00f1a Guiomar S.l.",
    "wof:placetype":"venue"
},
  "geometry": {"coordinates":[-3.6769580841,40.4247436523],"type":"Point"}
}