{
  "type": "Feature",
  "properties": {
    "iso:country":"ES",
    "sg:address":"Plaz Nafarroa Plaza, 4",
    "sg:city":"Durango",
    "sg:orig_category":"Plomeros",
    "sg:phone":"+34 946 81 43 09",
    "sg:postcode":"48200",
    "sg:province":"Vizcaya",
    "wof:name":"Frias Ramirez Jose",
    "wof:placetype":"venue"
},
  "geometry": {"coordinates":[-2.6225130558,43.1670951843],"type":"Point"}
}