{
  "type": "Feature",
  "properties": {
    "addr:full":"Avda America (de), 13 Teruel Teruel 44002",
    "addr:housenumber":"13",
    "addr:postcode":"44002",
    "addr:street":"Avda America De",
    "iso:country":"ES",
    "sg:address":"Avda America (de), 13",
    "sg:city":"Teruel",
    "sg:orig_category":"Arquitectos",
    "sg:phone":"+34 978 62 11 46",
    "sg:postcode":"44002",
    "sg:province":"Teruel",
    "wof:name":"Ferrer Cruzado Jose Luis",
    "wof:placetype":"venue"
},
  "geometry": {"coordinates":[-1.109416008,40.3300247192],"type":"Point"}
}