{
  "type": "Feature",
  "properties": {
    "addr:full":"Avda Federico Anaya, 1 Salamanca Salamanca 37005",
    "addr:housenumber":"1",
    "addr:postcode":"37005",
    "addr:street":"Avda Federico Anaya",
    "iso:country":"ES",
    "sg:address":"Avda Federico Anaya, 1",
    "sg:city":"Salamanca",
    "sg:orig_category":"Bancos",
    "sg:phone":"+34 923 22 46 00",
    "sg:postcode":"37005",
    "sg:province":"Salamanca",
    "wof:name":"Banc Sabadell S.a.",
    "wof:placetype":"venue"
},
  "geometry": {"coordinates":[-5.6580867767,40.9715042114],"type":"Point"}
}