{
  "type": "Feature",
  "properties": {
    "iso:country":"ES",
    "sg:address":"Otalora Lizentziaduna Kalea, 9",
    "sg:city":"Arrasate",
    "sg:orig_category":"Caf\u00c9s, Bares, Cervecer\u00cdas",
    "sg:phone":"+34 943 79 95 44",
    "sg:postcode":"20500",
    "sg:province":"Guip\u00f9zcoa",
    "wof:name":"Etxape Azkoaga Gregorio",
    "wof:placetype":"venue"
},
  "geometry": {"coordinates":[-2.487128973,43.066318512],"type":"Point"}
}