{
  "type": "Feature",
  "properties": {
    "addr:full":"Carrer de Sicilia, 15 Mataro Barcelona 08303",
    "addr:housenumber":"15",
    "addr:postcode":"08303",
    "addr:street":"Carrer De Sicilia",
    "iso:country":"ES",
    "sg:address":"Carrer de Sicilia, 15",
    "sg:city":"Mataro",
    "sg:orig_category":"Mec\u00c1nico Del Autom\u00d3vil",
    "sg:phone":"+34 937 98 38 97",
    "sg:postcode":"08303",
    "sg:province":"Barcelona",
    "wof:name":"Neila Gomez Pedro",
    "wof:placetype":"venue"
},
  "geometry": {"coordinates":[2.423899889,41.5403747559],"type":"Point"}
}