{
  "type": "Feature",
  "properties": {
    "addr:full":"Avda Paz De (la), 76 Logro\u00f1o La Rioja 26004",
    "addr:housenumber":"76",
    "addr:postcode":"26004",
    "addr:street":"Avda Paz De La;Rioja",
    "iso:country":"ES",
    "sg:address":"Avda Paz De (la), 76",
    "sg:city":"Logro\u00f1o",
    "sg:orig_category":"Librer\u00cdas",
    "sg:phone":"+34 941 24 92 62",
    "sg:postcode":"26004",
    "sg:province":"La Rioja",
    "wof:name":"Libreria Grimm S.l.",
    "wof:placetype":"venue"
},
  "geometry": {"coordinates":[-2.4340751171,42.4640007019],"type":"Point"}
}