{
  "type": "Feature",
  "properties": {
    "addr:full":"Calle de Alejandro Seiquer, 8 San Lorenzo Murcia 30001",
    "addr:housenumber":"8",
    "addr:postcode":"30001",
    "addr:street":"Calle De Alejandro Seiquer",
    "iso:country":"ES",
    "sg:address":"Calle de Alejandro Seiquer, 8",
    "sg:city":"San Lorenzo",
    "sg:orig_category":"Urbanistas",
    "sg:phone":"+34 968 21 69 85",
    "sg:postcode":"30001",
    "sg:province":"Murcia",
    "wof:name":"Consultores C.p.i C.b",
    "wof:placetype":"venue"
},
  "geometry": {"coordinates":[-1.1298867464,37.9834747314],"type":"Point"}
}