{
  "type": "Feature",
  "properties": {
    "addr:full":"Av Francesc Macia, 71 Vilanova I La Geltru Barcelona 08800",
    "addr:housenumber":"71",
    "addr:postcode":"08800",
    "addr:street":"Av Francesc Macia",
    "iso:country":"ES",
    "sg:address":"Av Francesc Macia, 71",
    "sg:city":"Vilanova I La Geltru",
    "sg:orig_category":"Art\u00cdculos De Decoraci\u00d3n",
    "sg:phone":"+34 938 15 87 13",
    "sg:postcode":"08800",
    "sg:province":"Barcelona",
    "wof:name":"Libra 29 S.l.",
    "wof:placetype":"venue"
},
  "geometry": {"coordinates":[1.7210530043,41.2225418091],"type":"Point"}
}