{
  "type": "Feature",
  "properties": {
    "addr:full":"Calle de Padre Mendez, 96 Torrent Valencia 46900",
    "addr:housenumber":"96",
    "addr:postcode":"46900",
    "addr:street":"Calle De Padre Mendez;Valencia",
    "iso:country":"ES",
    "sg:address":"Calle de Padre Mendez, 96",
    "sg:city":"Torrent",
    "sg:orig_category":"Abogados",
    "sg:phone":"+34 961 58 13 84",
    "sg:postcode":"46900",
    "sg:province":"Valencia",
    "wof:name":"Ndemensogo Oyono-okomo Antonio",
    "wof:placetype":"venue"
},
  "geometry": {"coordinates":[-0.4691190124,39.4329490662],"type":"Point"}
}