{
  "type": "Feature",
  "properties": {
    "iso:country":"ES",
    "sg:address":"Carrer de Comer\u00c7, 1",
    "sg:city":"Barcelona",
    "sg:orig_category":"Dibujo",
    "sg:phone":"+34 933 10 42 92",
    "sg:postcode":"08003",
    "sg:province":"Barcelona",
    "wof:name":"Saura Traver Cristina",
    "wof:placetype":"venue"
},
  "geometry": {"coordinates":[2.181538105,41.3888473511],"type":"Point"}
}