{
  "type": "Feature",
  "properties": {
    "addr:full":"Calle de Riglos, 1 Zaragoza Zaragoza 50012",
    "addr:housenumber":"1",
    "addr:postcode":"50012",
    "addr:street":"Calle De Riglos",
    "iso:country":"ES",
    "sg:address":"Calle de Riglos, 1",
    "sg:city":"Zaragoza",
    "sg:orig_category":"Empresas De Pintura Y Revestimientos",
    "sg:phone":"+34 976 56 46 15",
    "sg:postcode":"50012",
    "sg:province":"Zaragoza",
    "wof:name":"Victor Asensio S. L.",
    "wof:placetype":"venue"
},
  "geometry": {"coordinates":[-0.9108399749,41.6267433167],"type":"Point"}
}