{
  "type": "Feature",
  "properties": {
    "iso:country":"ES",
    "sg:address":"Calle de Alameda, 8",
    "sg:city":"Vegadeo",
    "sg:orig_category":"Asesor\u00cdas En Comunicaci\u00d3n",
    "sg:phone":"+34 985 63 47 25",
    "sg:postcode":"33770",
    "sg:province":"Asturias",
    "wof:name":"Imagen Y Sonido Arturo S.l.",
    "wof:placetype":"venue"
},
  "geometry": {"coordinates":[-7.050757885,43.4641647339],"type":"Point"}
}