{
  "type": "Feature",
  "properties": {
    "iso:country":"ES",
    "sg:address":"Matsaria Kalea, 10",
    "sg:city":"Eibar",
    "sg:orig_category":"Limpieza Con Chorro De Arena Y Con Granalla, Pulido",
    "sg:phone":"+34 943 20 10 11",
    "sg:postcode":"20600",
    "sg:province":"Guip\u00f9zcoa",
    "wof:name":"Garcia Fradejas Jose Luis",
    "wof:placetype":"venue"
},
  "geometry": {"coordinates":[-2.4665820599,43.1894493103],"type":"Point"}
}