{
  "type": "Feature",
  "properties": {
    "iso:country":"ES",
    "sg:address":"Ctra San Bartolome, 79",
    "sg:city":"Argana Baja",
    "sg:orig_category":"Venta, Montaje De Neum\u00c1ticos",
    "sg:phone":"+34 928 80 53 45",
    "sg:postcode":"35500",
    "sg:province":"Las Palmas",
    "wof:name":"Neumaticos Orlando S.l.",
    "wof:placetype":"venue"
},
  "geometry": {"coordinates":[-13.5490036011,28.9582099915],"type":"Point"}
}