{
  "type": "Feature",
  "properties": {
    "addr:full":"Rua Andori\u00d1as, 5 Lugo Lugo 27004",
    "addr:housenumber":"5",
    "addr:postcode":"27004",
    "addr:street":"Rua Andorin\u0303As",
    "iso:country":"ES",
    "sg:address":"Rua Andori\u00d1as, 5",
    "sg:city":"Lugo",
    "sg:orig_category":"Agencias Y Agentes Comerciales, Representantes",
    "sg:phone":"+34 982 21 80 92",
    "sg:postcode":"27004",
    "sg:province":"Lugo",
    "wof:name":"Diaz Se\u00f1or Manuel Roman",
    "wof:placetype":"venue"
},
  "geometry": {"coordinates":[-7.5628972054,43.012676239],"type":"Point"}
}