{
  "type": "Feature",
  "properties": {
    "iso:country":"ES",
    "sg:address":"Calle de Polo Y Peyrolon, 37",
    "sg:city":"Valencia",
    "sg:orig_category":"Restaurantes",
    "sg:phone":"+34 963 62 00 81",
    "sg:postcode":"46021",
    "sg:province":"Valencia",
    "wof:name":"Os Regresivos S.l.",
    "wof:placetype":"venue"
},
  "geometry": {"coordinates":[-0.3550139964,39.4736709595],"type":"Point"}
}