{
  "type": "Feature",
  "properties": {
    "addr:full":"Ctra Pe\u00d1oncillo (el), Km. 0285,0 Pe\u00d1oncillo M\u00e1laga 29793",
    "addr:postcode":"29793",
    "addr:street":"Ctra Pen\u0303Oncillo El Km. 0285,0 Pen\u0303Oncillo Ma\u0301Laga",
    "iso:country":"ES",
    "sg:address":"Ctra Pe\u00d1oncillo (el), Km. 0285,0",
    "sg:city":"Pe\u00d1oncillo",
    "sg:orig_category":"Semiller\u00cdas",
    "sg:phone":"+34 952 53 24 96",
    "sg:postcode":"29793",
    "sg:province":"M\u00e1laga",
    "wof:name":"Gonzalez Alvarez Maria Nieves",
    "wof:placetype":"venue"
},
  "geometry": {"coordinates":[-3.9633140564,36.7310066223],"type":"Point"}
}