{
  "type": "Feature",
  "properties": {
    "addr:full":"Ptda Racons, 10 Altea Alicante 03590",
    "addr:housenumber":"10",
    "addr:postcode":"03590",
    "addr:street":"Ptda Racons",
    "iso:country":"ES",
    "sg:address":"Ptda Racons, 10",
    "sg:city":"Altea",
    "sg:orig_category":"Arquitectos",
    "sg:phone":"+34 966 88 16 68",
    "sg:postcode":"03590",
    "sg:province":"Alicante",
    "wof:name":"Garcia Bellvert Monica",
    "wof:placetype":"venue"
},
  "geometry": {"coordinates":[-0.0522690006,38.601108551],"type":"Point"}
}