{
  "type": "Feature",
  "properties": {
    "addr:full":"Calle de Duque De Wellington, S/n Vitoria-gasteiz \u00c1lava 01010",
    "addr:postcode":"01010",
    "addr:street":"Calle De Duque De Wellington S / N",
    "iso:country":"ES",
    "sg:address":"Calle de Duque De Wellington, S/n",
    "sg:city":"Vitoria-gasteiz",
    "sg:orig_category":"Supermercados Y Hipermercados",
    "sg:phone":"+34 945 17 21 93",
    "sg:postcode":"01010",
    "sg:province":"\u00c1lava",
    "wof:name":"Supermercados Sabeco S.a.",
    "wof:placetype":"venue"
},
  "geometry": {"coordinates":[-2.6973159313,42.867515564],"type":"Point"}
}