{
  "type": "Feature",
  "properties": {
    "addr:full":"Urb Limonar, 49 Cala M\u00e1laga 29649",
    "addr:housenumber":"49",
    "addr:postcode":"29649",
    "addr:street":"Limonar;Ma\u0301Laga",
    "iso:country":"ES",
    "sg:address":"Urb Limonar, 49",
    "sg:city":"Cala",
    "sg:orig_category":"Empresas De Pintura Y Revestimientos",
    "sg:phone":"+34 952 49 45 38",
    "sg:postcode":"29649",
    "sg:province":"M\u00e1laga",
    "wof:name":"Rodriguez Gutierrez Juan",
    "wof:placetype":"venue"
},
  "geometry": {"coordinates":[-4.6790738106,36.5038642883],"type":"Point"}
}