{
  "type": "Feature",
  "properties": {
    "iso:country":"ES",
    "sg:address":"Ketama, 1",
    "sg:city":"Belicena",
    "sg:orig_category":"Peluquer\u00cdas, Peluquer\u00cda Mixta",
    "sg:phone":"+34 958 43 12 39",
    "sg:postcode":"18193",
    "sg:province":"Granada",
    "wof:name":"Fernandez Roldan Lucia",
    "wof:placetype":"venue"
},
  "geometry": {"coordinates":[-3.5402770042,37.1322402954],"type":"Point"}
}