{
  "type": "Feature",
  "properties": {
    "addr:full":"Calle de Iberia, 8 Sestao Vizcaya 48910",
    "addr:housenumber":"8",
    "addr:postcode":"48910",
    "addr:street":"Calle De Iberia",
    "iso:country":"ES",
    "sg:address":"Calle de Iberia, 8",
    "sg:city":"Sestao",
    "sg:orig_category":"Molduras, Junquillos, Listones Y Molduras Perforadas",
    "sg:phone":"+34 944 96 11 93",
    "sg:postcode":"48910",
    "sg:province":"Vizcaya",
    "wof:name":"Maria Luz Laje Rodriguez",
    "wof:placetype":"venue"
},
  "geometry": {"coordinates":[-3.0049710274,43.310459137],"type":"Point"}
}