{
  "type": "Feature",
  "properties": {
    "iso:country":"ES",
    "sg:address":"Avda Encarnacion, S/n",
    "sg:city":"Fuengirola",
    "sg:orig_category":"Bisuter\u00cda, Joyer\u00cda, Relojer\u00cda (al Por Menor)",
    "sg:phone":"+34 952 59 22 32",
    "sg:postcode":"29640",
    "sg:province":"M\u00e1laga",
    "wof:name":"Pbo Joyas S.l",
    "wof:placetype":"venue"
},
  "geometry": {"coordinates":[-4.6306362152,36.5269432068],"type":"Point"}
}