{
  "type": "Feature",
  "properties": {
    "addr:full":"Carrer de Antoni Gaudi, 8 S. Joan Despi Barcelona 08970",
    "addr:housenumber":"8",
    "addr:postcode":"08970",
    "addr:street":"Carrer De Antoni Gaudi;Joan",
    "iso:country":"ES",
    "sg:address":"Carrer de Antoni Gaudi, 8",
    "sg:city":"S. Joan Despi",
    "sg:orig_category":"Ense\u00d1anza: Idiomas",
    "sg:phone":"+34 933 73 45 11",
    "sg:postcode":"08970",
    "sg:province":"Barcelona",
    "wof:name":"Clubb  Sally Anne Victoria",
    "wof:placetype":"venue"
},
  "geometry": {"coordinates":[2.0687360764,41.3720741272],"type":"Point"}
}