{
  "type": "Feature",
  "properties": {
    "iso:country":"ES",
    "sg:address":"Diamante, 1",
    "sg:city":"Valdemoro",
    "sg:orig_category":"Contenedores (mercanc\u00cdas)",
    "sg:phone":"+34 918 08 19 82",
    "sg:postcode":"28340",
    "sg:province":"Madrid",
    "wof:name":"Transporte Y Logistica Avanzada S.l.",
    "wof:placetype":"venue"
},
  "geometry": {"coordinates":[-3.664329052,40.1736984253],"type":"Point"}
}