{
  "type": "Feature",
  "properties": {
    "iso:country":"ES",
    "sg:address":"Calle de Mayor, S/n",
    "sg:city":"Navalacruz",
    "sg:orig_category":"Estancos",
    "sg:phone":"+34 920 29 95 03",
    "sg:postcode":"05134",
    "sg:province":"\u00c1vila",
    "wof:name":"Arganda Diaz Catalino",
    "wof:placetype":"venue"
},
  "geometry": {"coordinates":[-4.9318809509,40.44008255],"type":"Point"}
}