{
  "type": "Feature",
  "properties": {
    "iso:country":"ES",
    "sg:address":"Calle de Cavanilles, 41",
    "sg:city":"Madrid",
    "sg:orig_category":"Ropa Y Accesorios",
    "sg:phone":"+34 915 01 09 34",
    "sg:postcode":"28007",
    "sg:province":"Madrid",
    "wof:name":"Lucky You S.l.",
    "wof:placetype":"venue"
},
  "geometry": {"coordinates":[-3.673666954,40.4049377441],"type":"Point"}
}