{
  "type": "Feature",
  "properties": {
    "iso:country":"ES",
    "sg:address":"Calle de Garcia Morato, 12",
    "sg:city":"Logro\u00f1o",
    "sg:orig_category":"Peluqueros: De Se\u00d1oras",
    "sg:phone":"+34 941 26 28 74",
    "sg:postcode":"26002",
    "sg:province":"La Rioja",
    "wof:name":"Albanta 95 S.l.",
    "wof:placetype":"venue"
},
  "geometry": {"coordinates":[-2.447842598,42.4621963501],"type":"Point"}
}