{
  "type": "Feature",
  "properties": {
    "addr:full":"Mestre Goldar, 18 Vigo Pontevedra 36213",
    "addr:housenumber":"18",
    "addr:postcode":"36213",
    "addr:street":"Goldar",
    "iso:country":"ES",
    "sg:address":"Mestre Goldar, 18",
    "sg:city":"Vigo",
    "sg:orig_category":"Centros De Educaci\u00d3n Especial",
    "sg:phone":"+34 986 20 83 95",
    "sg:postcode":"36213",
    "sg:province":"Pontevedra",
    "wof:name":"Aspanaex",
    "wof:placetype":"venue"
},
  "geometry": {"coordinates":[-8.7536239624,42.1922149658],"type":"Point"}
}