{
  "type": "Feature",
  "properties": {
    "addr:full":"Plaz Espa\u00d1a, 1 Aguaviva Teruel 44566",
    "addr:housenumber":"1",
    "addr:postcode":"44566",
    "addr:street":"Plaz Espan\u0303A",
    "iso:country":"ES",
    "sg:address":"Plaz Espa\u00d1a, 1",
    "sg:city":"Aguaviva",
    "sg:orig_category":"Asociaciones, Organismos Culturales Y Socioeducativos",
    "sg:phone":"+34 978 84 85 22",
    "sg:postcode":"44566",
    "sg:province":"Teruel",
    "wof:name":"Asociacion De La Tercera Edad La Amistad",
    "wof:placetype":"venue"
},
  "geometry": {"coordinates":[-0.1975589991,40.822807312],"type":"Point"}
}