{
  "type": "Feature",
  "properties": {
    "iso:country":"ES",
    "sg:address":"Calle de Pio Ix, 2",
    "sg:city":"Valencia",
    "sg:orig_category":"Molduras, Junquillos, Listones Y Molduras Perforadas",
    "sg:phone":"+34 963 57 62 59",
    "sg:postcode":"46017",
    "sg:province":"Valencia",
    "wof:name":"Herrera Coronado Maria Dolores",
    "wof:placetype":"venue"
},
  "geometry": {"coordinates":[-0.3926959932,39.4466552734],"type":"Point"}
}