{
  "type": "Feature",
  "properties": {
    "addr:full":"Pol Ind Fadricas, 30 S. Fernando C\u00e1diz 11100",
    "addr:housenumber":"30",
    "addr:postcode":"11100",
    "addr:street":"Fadricas;S. Fernando Ca\u0301Diz",
    "iso:country":"ES",
    "sg:address":"Pol Ind Fadricas, 30",
    "sg:city":"S. Fernando",
    "sg:orig_category":"Telas Y Sedas (al Por Menor)",
    "sg:phone":"+34 956 59 56 91",
    "sg:postcode":"11100",
    "sg:province":"C\u00e1diz",
    "wof:name":"M.f.cadiz S.a.",
    "wof:placetype":"venue"
},
  "geometry": {"coordinates":[-6.1967391968,36.4654541016],"type":"Point"}
}