{
  "type": "Feature",
  "properties": {
    "iso:country":"ES",
    "sg:address":"Plaz Nueva, 2",
    "sg:city":"Hellin",
    "sg:orig_category":"Peluquer\u00cdas, Peluquer\u00cda Mixta",
    "sg:phone":"+34 967 30 42 01",
    "sg:postcode":"02400",
    "sg:province":"Albacete",
    "wof:name":"Espinosa Aranda Manuela",
    "wof:placetype":"venue"
},
  "geometry": {"coordinates":[-1.7026000023,38.5154914856],"type":"Point"}
}