{
  "type": "Feature",
  "properties": {
    "iso:country":"ES",
    "sg:address":"Laranxeiras(rebordans), 3",
    "sg:city":"Naranjeiras",
    "sg:orig_category":"Centros De Educaci\u00d3n Especial",
    "sg:phone":"+34 986 60 36 68",
    "sg:postcode":"36712",
    "sg:province":"Pontevedra",
    "wof:name":"Ayuntamiento De Tuy",
    "wof:placetype":"venue"
},
  "geometry": {"coordinates":[-8.6573963165,42.0574684143],"type":"Point"}
}