{
  "type": "Feature",
  "properties": {
    "addr:full":"C. Rinconada, Km. 0005,0 Rinconada Sevilla 41309",
    "addr:postcode":"41309",
    "addr:street":"Rinconada Km. 0005,0",
    "iso:country":"ES",
    "sg:address":"C. Rinconada, Km. 0005,0",
    "sg:city":"Rinconada",
    "sg:orig_category":"Mataderos De Poller\u00cda",
    "sg:phone":"+34 954 90 77 70",
    "sg:postcode":"41309",
    "sg:province":"Sevilla",
    "wof:name":"Sada P.a. Andalucia S.a.",
    "wof:placetype":"venue"
},
  "geometry": {"coordinates":[-5.9782538414,37.492855072],"type":"Point"}
}