{
  "type": "Feature",
  "properties": {
    "iso:country":"ES",
    "sg:address":"Calle de Canal De Suez, 47",
    "sg:city":"Madrid",
    "sg:orig_category":"Electricidad Veh\u00cdculo",
    "sg:phone":"+34 917 47 00 44",
    "sg:postcode":"28042",
    "sg:province":"Madrid",
    "wof:name":"Fuentes Touzon Angel",
    "wof:placetype":"venue"
},
  "geometry": {"coordinates":[-3.5788676739,40.4744377136],"type":"Point"}
}