{
  "type": "Feature",
  "properties": {
    "addr:full":"Plaz Canalejas, 4 Lucena Cid Castell\u00f3n 12120",
    "addr:housenumber":"4",
    "addr:postcode":"12120",
    "addr:street":"Plaz Canalejas;Castello\u0301N",
    "iso:country":"ES",
    "sg:address":"Plaz Canalejas, 4",
    "sg:city":"Lucena Cid",
    "sg:orig_category":"Estancos",
    "sg:phone":"+34 964 38 02 40",
    "sg:postcode":"12120",
    "sg:province":"Castell\u00f3n",
    "wof:name":"Lahoz Beltran Etelvina",
    "wof:placetype":"venue"
},
  "geometry": {"coordinates":[-0.0456800014,39.9851417542],"type":"Point"}
}