{
  "type": "Feature",
  "properties": {
    "addr:full":"Calle de Embajadores, 74 Madrid Madrid 28012",
    "addr:housenumber":"74",
    "addr:postcode":"madrid;28012",
    "addr:street":"Calle De Embajadores",
    "iso:country":"ES",
    "sg:address":"Calle de Embajadores, 74",
    "sg:city":"Madrid",
    "sg:orig_category":"Tapiceros Y Tapiceros",
    "sg:phone":"+34 915 17 04 42",
    "sg:postcode":"28012",
    "sg:province":"Madrid",
    "wof:name":"Morales Bueno Arturo",
    "wof:placetype":"venue"
},
  "geometry": {"coordinates":[-3.7022309303,40.4043807983],"type":"Point"}
}