{
  "type": "Feature",
  "properties": {
    "addr:full":"Calle de Salud, 1 Zamora Zamora 49024",
    "addr:housenumber":"1",
    "addr:postcode":"49024",
    "addr:street":"Calle De Salud",
    "iso:country":"ES",
    "sg:address":"Calle de Salud, 1",
    "sg:city":"Zamora",
    "sg:orig_category":"Chapister\u00cda",
    "sg:phone":"+34 980 52 73 04",
    "sg:postcode":"49024",
    "sg:province":"Zamora",
    "wof:name":"Alvarez Campano Indalecio",
    "wof:placetype":"venue"
},
  "geometry": {"coordinates":[-5.7508449554,41.5141525269],"type":"Point"}
}