{
  "type": "Feature",
  "properties": {
    "iso:country":"ES",
    "sg:address":"Avda Manzanares, 60",
    "sg:city":"Madrid",
    "sg:orig_category":"Pescader\u00cdas (al Por Menor)",
    "sg:phone":"+34 915 69 31 53",
    "sg:postcode":"28019",
    "sg:province":"Madrid",
    "wof:name":"Velar Villar Maria Asuncion",
    "wof:placetype":"venue"
},
  "geometry": {"coordinates":[-3.7230870724,40.4023742676],"type":"Point"}
}