{
  "type": "Feature",
  "properties": {
    "iso:country":"ES",
    "sg:address":"Carrer de Molar (del), 3",
    "sg:city":"Reus",
    "sg:orig_category":"Cerrajer\u00cda, Ferrallista",
    "sg:phone":"+34 977 32 33 98",
    "sg:postcode":"43206",
    "sg:province":"Tarragona",
    "wof:name":"Aluminis Joan S.l.",
    "wof:placetype":"venue"
},
  "geometry": {"coordinates":[1.0795807838,41.1560173035],"type":"Point"}
}