{
  "type": "Feature",
  "properties": {
    "iso:country":"ES",
    "sg:address":"Calle de Diputacio Provincial, 20",
    "sg:city":"Vilafames",
    "sg:orig_category":"Museos",
    "sg:phone":"+34 964 32 91 52",
    "sg:postcode":"12192",
    "sg:province":"Castell\u00f3n",
    "wof:name":"Museo Popular De Arte Contemporaneo",
    "wof:placetype":"venue"
},
  "geometry": {"coordinates":[-0.0653340966,40.1145324707],"type":"Point"}
}