{
  "type": "Feature",
  "properties": {
    "iso:country":"ES",
    "sg:address":"Carrer de Doctor Fleming, 25",
    "sg:city":"Premia Mar",
    "sg:orig_category":"Cristaler\u00cdas",
    "sg:phone":"+34 937 52 42 72",
    "sg:postcode":"08330",
    "sg:province":"Barcelona",
    "wof:name":"Tomas Isach Jorge",
    "wof:placetype":"venue"
},
  "geometry": {"coordinates":[2.356523037,41.4935646057],"type":"Point"}
}