{
  "type": "Feature",
  "properties": {
    "addr:full":"Poli Anibarko-portua, 35 Orio Guip\u00f9zcoa 20810",
    "addr:housenumber":"35",
    "addr:postcode":"20810",
    "addr:street":"Anibarko-Portua;Guipu\u0300Zcoa",
    "iso:country":"ES",
    "sg:address":"Poli Anibarko-portua, 35",
    "sg:city":"Orio",
    "sg:orig_category":"Molduras, Junquillos, Listones Y Molduras Perforadas",
    "sg:phone":"+34 943 83 40 54",
    "sg:postcode":"20810",
    "sg:province":"Guip\u00f9zcoa",
    "wof:name":"Maria Angeles Lazkano Larra\u00f1aga",
    "wof:placetype":"venue"
},
  "geometry": {"coordinates":[-2.1156039238,43.2773895264],"type":"Point"}
}