{
  "type": "Feature",
  "properties": {
    "iso:country":"ES",
    "sg:address":"Carr Camprodon, 72",
    "sg:city":"Arbucies",
    "sg:orig_category":"Asesor\u00cda Sobre Comunicaci\u00d3n De Empresas",
    "sg:phone":"+34 972 86 09 70",
    "sg:postcode":"17401",
    "sg:province":"Girona",
    "wof:name":"Vertex Assessors S.l.",
    "wof:placetype":"venue"
},
  "geometry": {"coordinates":[2.5177209377,41.8149147034],"type":"Point"}
}