{
  "type": "Feature",
  "properties": {
    "addr:full":"Carr Estrella, 93 Badalona Barcelona 08917",
    "addr:housenumber":"93",
    "addr:postcode":"08917",
    "addr:street":"Carr Estrella",
    "iso:country":"ES",
    "sg:address":"Carr Estrella, 93",
    "sg:city":"Badalona",
    "sg:orig_category":"Empresas De Carpinter\u00cda",
    "sg:phone":"+34 933 87 40 62",
    "sg:postcode":"08917",
    "sg:province":"Barcelona",
    "wof:name":"Teyser Instalaciones S.l.",
    "wof:placetype":"venue"
},
  "geometry": {"coordinates":[2.226651907,41.4484214783],"type":"Point"}
}