{
  "type": "Feature",
  "properties": {
    "addr:full":"Calle de Victoria Kent, 5 Sevilla Sevilla 41008",
    "addr:housenumber":"5",
    "addr:postcode":"41008",
    "addr:street":"Calle De Victoria Kent",
    "iso:country":"ES",
    "sg:address":"Calle de Victoria Kent, 5",
    "sg:city":"Sevilla",
    "sg:orig_category":"Asociaciones Y Clubs Deportivos",
    "sg:phone":"+34 954 95 14 01",
    "sg:postcode":"41008",
    "sg:province":"Sevilla",
    "wof:name":"Arquellada Quiros Angel",
    "wof:placetype":"venue"
},
  "geometry": {"coordinates":[-5.9741072655,37.4146118164],"type":"Point"}
}