{
  "type": "Feature",
  "properties": {
    "addr:full":"Calle de Eguzkiza, 1 Irun Guip\u00f9zcoa 20304",
    "addr:housenumber":"1",
    "addr:postcode":"20304",
    "addr:street":"Calle De Eguzkiza;Guipu\u0300Zcoa",
    "iso:country":"ES",
    "sg:address":"Calle de Eguzkiza, 1",
    "sg:city":"Irun",
    "sg:orig_category":"Peluquer\u00cdas, Peluquer\u00cda Mixta",
    "sg:phone":"+34 943 63 31 39",
    "sg:postcode":"20304",
    "sg:province":"Guip\u00f9zcoa",
    "wof:name":"Recalde Maritorena Amaya",
    "wof:placetype":"venue"
},
  "geometry": {"coordinates":[-1.7885099649,43.3368453979],"type":"Point"}
}