{
  "type": "Feature",
  "properties": {
    "iso:country":"ES",
    "sg:address":"Ctra Far, 79",
    "sg:city":"Canyelles-almadrava-puig-rom",
    "sg:orig_category":"Supermercados Y Hipermercados",
    "sg:phone":"+34 972 15 16 64",
    "sg:postcode":"17480",
    "sg:province":"Girona",
    "wof:name":"Lobato Ramirez Maria Petra",
    "wof:placetype":"venue"
},
  "geometry": {"coordinates":[3.1815509796,42.2468185425],"type":"Point"}
}