{
  "type": "Feature",
  "properties": {
    "iso:country":"ES",
    "sg:address":"Calle de Lopez Grass, 5",
    "sg:city":"Madrid",
    "sg:orig_category":"Colchones (fabricaci\u00d3n, Al Por Mayor, Al Por Menor)",
    "sg:phone":"+34 913 28 06 79",
    "sg:postcode":"28038",
    "sg:province":"Madrid",
    "wof:name":"Madrigal Matellanes Domingo",
    "wof:placetype":"venue"
},
  "geometry": {"coordinates":[-3.6613149643,40.3950996399],"type":"Point"}
}