{
  "type": "Feature",
  "properties": {
    "iso:country":"ES",
    "sg:address":"Calle de Gladiolo, 3",
    "sg:city":"Pedrera",
    "sg:orig_category":"Centros De Coordinaci\u00d3n",
    "sg:phone":"+34 955 82 71 32",
    "sg:postcode":"41566",
    "sg:province":"Sevilla",
    "wof:name":"Gestora De Tramitaciones Julian S.c.",
    "wof:placetype":"venue"
},
  "geometry": {"coordinates":[-4.8948230743,37.2269172668],"type":"Point"}
}