{
  "type": "Feature",
  "properties": {
    "iso:country":"ES",
    "sg:address":"Calle de Menendez Y Pelayo, 23",
    "sg:city":"Palmas De Gran Canaria",
    "sg:orig_category":"Peluquer\u00cdas, Peluquer\u00cda Mixta",
    "sg:phone":"+34 928 23 46 00",
    "sg:postcode":"35006",
    "sg:province":"Las Palmas",
    "wof:name":"Santana Carballo Victor",
    "wof:placetype":"venue"
},
  "geometry": {"coordinates":[-15.4317302704,28.1334915161],"type":"Point"}
}