{
  "type": "Feature",
  "properties": {
    "addr:full":"Calle de Viana, Km. 0003,5 Boecillo Valladolid 47151",
    "addr:postcode":"47151",
    "addr:street":"Calle De Viana Km. 0003,5",
    "iso:country":"ES",
    "sg:address":"Calle de Viana, Km. 0003,5",
    "sg:city":"Boecillo",
    "sg:orig_category":"Cr\u00cda De Animales",
    "sg:phone":"+34 983 48 04 07",
    "sg:postcode":"47151",
    "sg:province":"Valladolid",
    "wof:name":"Granja El Pozo S. A. T.",
    "wof:placetype":"venue"
},
  "geometry": {"coordinates":[-4.699324131,41.5422782898],"type":"Point"}
}