{
  "type": "Feature",
  "properties": {
    "addr:full":"Carr Moli De La Torre, 25 Badalona Barcelona 08915",
    "addr:housenumber":"25",
    "addr:postcode":"08915",
    "addr:street":"Carr Moli De La Torre",
    "iso:country":"ES",
    "sg:address":"Carr Moli De La Torre, 25",
    "sg:city":"Badalona",
    "sg:orig_category":"Molduras, Junquillos, Listones Y Molduras Perforadas",
    "sg:phone":"+34 934 60 16 11",
    "sg:postcode":"08915",
    "sg:province":"Barcelona",
    "wof:name":"Prats Carmona Xavier",
    "wof:placetype":"venue"
},
  "geometry": {"coordinates":[2.2437000275,41.4611053467],"type":"Point"}
}