{
  "type": "Feature",
  "properties": {
    "iso:country":"ES",
    "sg:address":"Carrer de Major, 17",
    "sg:city":"Torrelles Llobregat",
    "sg:orig_category":"Bancos",
    "sg:phone":"+34 936 89 00 70",
    "sg:postcode":"08629",
    "sg:province":"Barcelona",
    "wof:name":"Banc Sabadell S.a.",
    "wof:placetype":"venue"
},
  "geometry": {"coordinates":[1.9813879728,41.3588409424],"type":"Point"}
}