{
  "type": "Feature",
  "properties": {
    "iso:country":"ES",
    "sg:address":"Carrer de Valencia, 30",
    "sg:city":"Barcelona",
    "sg:orig_category":"Transportes Por Carretera: Lotes Completos, Mercanc\u00cdas Diversas",
    "sg:phone":"+34 932 26 25 14",
    "sg:postcode":"08015",
    "sg:province":"Barcelona",
    "wof:name":"Vilalta Calvet Antonio",
    "wof:placetype":"venue"
},
  "geometry": {"coordinates":[2.1466720104,41.3799743652],"type":"Point"}
}