{
  "type": "Feature",
  "properties": {
    "iso:country":"ES",
    "sg:address":"Calle de Blasco, 15",
    "sg:city":"Alca\u00f1iz",
    "sg:orig_category":"Panader\u00cdas, Panader\u00cdas",
    "sg:phone":"+34 978 83 06 01",
    "sg:postcode":"44600",
    "sg:province":"Teruel",
    "wof:name":"Pasteleria Confiteria Alejos S.l.",
    "wof:placetype":"venue"
},
  "geometry": {"coordinates":[-0.1310787052,41.050945282],"type":"Point"}
}