{
  "type": "Feature",
  "properties": {
    "addr:full":"Carr Literato Azorin, 4 Oliva Valencia 46780",
    "addr:housenumber":"4",
    "addr:postcode":"46780",
    "addr:street":"Carr Literato Azorin",
    "iso:country":"ES",
    "sg:address":"Carr Literato Azorin, 4",
    "sg:city":"Oliva",
    "sg:orig_category":"Estudios, Instalaci\u00d3n De Climatizaci\u00d3n",
    "sg:phone":"+34 962 85 44 87",
    "sg:postcode":"46780",
    "sg:province":"Valencia",
    "wof:name":"Barreres Garcia Francisco",
    "wof:placetype":"venue"
},
  "geometry": {"coordinates":[-0.1164480001,38.9216995239],"type":"Point"}
}