{
  "type": "Feature",
  "properties": {
    "iso:country":"ES",
    "sg:address":"Calle de Fray Diego De Cadiz, 79",
    "sg:city":"Moron Frontera",
    "sg:orig_category":"Comercio, Reparaci\u00d3n De Motocicletas, Bicicletas Y Piezas Sueltas",
    "sg:phone":"+34 955 85 07 85",
    "sg:postcode":"41530",
    "sg:province":"Sevilla",
    "wof:name":"Gonzalez Ramos Francisco Javier",
    "wof:placetype":"venue"
},
  "geometry": {"coordinates":[-5.4553618431,37.1240539551],"type":"Point"}
}