{
  "type": "Feature",
  "properties": {
    "iso:country":"ES",
    "sg:address":"Calle de Pozokoetxe, 3",
    "sg:city":"Arizgoiti",
    "sg:orig_category":"Estancos",
    "sg:phone":"+34 944 49 52 12",
    "sg:postcode":"48970",
    "sg:province":"Vizcaya",
    "wof:name":"Bengoa Lapatza-gortazar Maria Del Mar",
    "wof:placetype":"venue"
},
  "geometry": {"coordinates":[-2.8872048855,43.2392654419],"type":"Point"}
}