{
  "type": "Feature",
  "properties": {
    "addr:full":"Rua Porto Do Molle, 11 Cartas Pontevedra 36379",
    "addr:housenumber":"11",
    "addr:postcode":"36379",
    "addr:street":"Rua Porto Do Molle",
    "iso:country":"ES",
    "sg:address":"Rua Porto Do Molle, 11",
    "sg:city":"Cartas",
    "sg:orig_category":"Empresas De Carpinter\u00cda Met\u00c1lica",
    "sg:phone":"+34 986 35 29 94",
    "sg:postcode":"36379",
    "sg:province":"Pontevedra",
    "wof:name":"Cerrajeria Hergon C De B",
    "wof:placetype":"venue"
},
  "geometry": {"coordinates":[-8.8124990463,42.1194648743],"type":"Point"}
}