{
  "type": "Feature",
  "properties": {
    "addr:full":"Erdiko Kalea, 4 Arrasate Guip\u00f9zcoa 20500",
    "addr:housenumber":"4",
    "addr:postcode":"20500",
    "addr:street":"Erdiko Kalea;Guipu\u0300Zcoa",
    "iso:country":"ES",
    "sg:address":"Erdiko Kalea, 4",
    "sg:city":"Arrasate",
    "sg:orig_category":"Abogados",
    "sg:phone":"+34 943 79 06 00",
    "sg:postcode":"20500",
    "sg:province":"Guip\u00f9zcoa",
    "wof:name":"Urteaga Biku\u00f1a Miren Arbil",
    "wof:placetype":"venue"
},
  "geometry": {"coordinates":[-2.4899659157,43.0658493042],"type":"Point"}
}