{
  "type": "Feature",
  "properties": {
    "iso:country":"ES",
    "sg:address":"Avda Turia (del), 2",
    "sg:city":"Xirivella",
    "sg:orig_category":"Plomeros",
    "sg:phone":"+34 963 59 05 62",
    "sg:postcode":"46950",
    "sg:province":"Valencia",
    "wof:name":"Emifont Fontaneria Y Gas S.l.",
    "wof:placetype":"venue"
},
  "geometry": {"coordinates":[-0.4229690135,39.4675598145],"type":"Point"}
}