{
  "type": "Feature",
  "properties": {
    "iso:country":"ES",
    "sg:address":"Calle de Iba\u00d1ez Marin, 13",
    "sg:city":"Andujar",
    "sg:orig_category":"Ropa Para Se\u00d1oras (al Por Menor)",
    "sg:phone":"+34 953 51 18 78",
    "sg:postcode":"23740",
    "sg:province":"Ja\u00e9n",
    "wof:name":"Pe\u00f1a Galaso Maria Teresa",
    "wof:placetype":"venue"
},
  "geometry": {"coordinates":[-4.0522828102,38.039226532],"type":"Point"}
}