{
  "type": "Feature",
  "properties": {
    "iso:country":"ES",
    "sg:address":"Pg Vara De Rey, 22",
    "sg:city":"Eivissa",
    "sg:orig_category":"Institutos De Belleza",
    "sg:phone":"+34 971 31 17 51",
    "sg:postcode":"07800",
    "sg:province":"Islas Baleares",
    "wof:name":"Cosmetic & Aestheticl Laser Surgery S.l",
    "wof:placetype":"venue"
},
  "geometry": {"coordinates":[1.4328010082,38.909198761],"type":"Point"}
}