{
  "type": "Feature",
  "properties": {
    "addr:full":"Ctra Madrid, Km. 0261,0 Benavente Zamora 49600",
    "addr:postcode":"49600",
    "addr:street":"Ctra Madrid Km. 0261,0",
    "iso:country":"ES",
    "sg:address":"Ctra Madrid, Km. 0261,0",
    "sg:city":"Benavente",
    "sg:orig_category":"Mec\u00c1nico Del Autom\u00d3vil",
    "sg:phone":"+34 980 63 60 48",
    "sg:postcode":"49600",
    "sg:province":"Zamora",
    "wof:name":"Vega Lobo Venancio De",
    "wof:placetype":"venue"
},
  "geometry": {"coordinates":[-5.6491689682,41.993221283],"type":"Point"}
}