{
  "type": "Feature",
  "properties": {
    "iso:country":"ES",
    "sg:address":"Calle de San Ildefonso, 17",
    "sg:city":"Monesterio",
    "sg:orig_category":"Empresas De Carpinter\u00cda De Madera",
    "sg:phone":"+34 924 51 61 26",
    "sg:postcode":"06260",
    "sg:province":"Badajoz",
    "wof:name":"Sanchez Pecellin Francisco Javier",
    "wof:placetype":"venue"
},
  "geometry": {"coordinates":[-6.2741937637,38.0892791748],"type":"Point"}
}