{
  "type": "Feature",
  "properties": {
    "iso:country":"ES",
    "sg:address":"Calle de Mariana Pineda, S/n",
    "sg:city":"Oca\u00f1a",
    "sg:orig_category":"Inmobiliaria (agencias)",
    "sg:phone":"+34 925 13 00 99",
    "sg:postcode":"45300",
    "sg:province":"Toledo",
    "wof:name":"Ilma S.l.",
    "wof:placetype":"venue"
},
  "geometry": {"coordinates":[-3.4971570969,39.9560546875],"type":"Point"}
}