{
  "type": "Feature",
  "properties": {
    "addr:full":"Carrer de Gran Via De Lluis Companys, 169 Premia Mar Barcelona 08330",
    "addr:housenumber":"169",
    "addr:postcode":"08330",
    "addr:street":"Carrer De Gran Via De Lluis Companys",
    "iso:country":"ES",
    "sg:address":"Carrer de Gran Via De Lluis Companys, 169",
    "sg:city":"Premia Mar",
    "sg:orig_category":"Cajas De Ahorro",
    "sg:phone":"+34 937 54 70 74",
    "sg:postcode":"08330",
    "sg:province":"Barcelona",
    "wof:name":"Caja De Ahorros De Valencia Castellon Y Alicante",
    "wof:placetype":"venue"
},
  "geometry": {"coordinates":[2.353110075,41.4906196594],"type":"Point"}
}