{
  "type": "Feature",
  "properties": {
    "addr:full":"Praz Quintela (de), S/n Quintela Ourense 32001",
    "addr:postcode":"32001",
    "addr:street":"Praz Quintela De S / N Quintela",
    "iso:country":"ES",
    "sg:address":"Praz Quintela (de), S/n",
    "sg:city":"Quintela",
    "sg:orig_category":"Agentes, Concesionarios Y Sucursales De Camiones Y Veh\u00cdculos Industriales",
    "sg:phone":"+34 988 21 22 84",
    "sg:postcode":"32001",
    "sg:province":"Ourense",
    "sg:website":"www.dasan-sa.com",
    "wof:name":"Carrocerias Dasan S. A.",
    "wof:placetype":"venue"
},
  "geometry": {"coordinates":[-7.8814702034,42.3738327026],"type":"Point"}
}