{
  "type": "Feature",
  "properties": {
    "iso:country":"ES",
    "sg:address":"Av Estrasburg, 11",
    "sg:city":"Platja D'aro",
    "sg:orig_category":"Masajes",
    "sg:phone":"+34 972 82 65 58",
    "sg:postcode":"17250",
    "sg:province":"Girona",
    "wof:name":"Sole Chavero Maria Isabel",
    "wof:placetype":"venue"
},
  "geometry": {"coordinates":[2.8226919174,41.9655265808],"type":"Point"}
}