{
  "type": "Feature",
  "properties": {
    "iso:country":"ES",
    "sg:address":"Calle de Cruz, 11",
    "sg:city":"Madrid",
    "sg:orig_category":"Ingeniero",
    "sg:phone":"+34 915 22 95 86",
    "sg:postcode":"28012",
    "sg:province":"Madrid",
    "sg:website":"www.redvistobueno.com/ati",
    "wof:name":"Asistencias Tecnicas De Ingenieria Consultores S.l.",
    "wof:placetype":"venue"
},
  "geometry": {"coordinates":[-3.701280117,40.4158935547],"type":"Point"}
}