{
  "type": "Feature",
  "properties": {
    "iso:country":"ES",
    "sg:address":"Poli Industrial Insider, 15",
    "sg:city":"Cartuja Baja",
    "sg:orig_category":"Charcuter\u00cdas (al Por Mayor)",
    "sg:phone":"+34 976 50 05 01",
    "sg:postcode":"50720",
    "sg:province":"Zaragoza",
    "wof:name":"Sanchez Aragonesa De Distribuciones S.a.",
    "wof:placetype":"venue"
},
  "geometry": {"coordinates":[-0.8264570236,41.6003952026],"type":"Point"}
}