{
  "type": "Feature",
  "properties": {
    "addr:full":"Pl. Ind. Los Cerezos, S/n Mora Rubielos Teruel 44400",
    "addr:postcode":"44400",
    "addr:street":"Los Cerezos S / N",
    "iso:country":"ES",
    "sg:address":"Pl. Ind. Los Cerezos, S/n",
    "sg:city":"Mora Rubielos",
    "sg:orig_category":"Carnicer\u00cdas, Carnicer\u00cdas",
    "sg:phone":"+34 978 80 02 78",
    "sg:postcode":"44400",
    "sg:province":"Teruel",
    "wof:name":"Secamora S. A.",
    "wof:placetype":"venue"
},
  "geometry": {"coordinates":[-0.7552589774,40.2504005432],"type":"Point"}
}