{
  "type": "Feature",
  "properties": {
    "addr:full":"Calle de Jose Del Hierro, 60 Madrid Madrid 28027",
    "addr:housenumber":"60",
    "addr:postcode":"madrid;28027",
    "addr:street":"Calle De Jose Del Hierro",
    "iso:country":"ES",
    "sg:address":"Calle de Jose Del Hierro, 60",
    "sg:city":"Madrid",
    "sg:orig_category":"Molduras, Junquillos, Listones Y Molduras Perforadas",
    "sg:phone":"+34 913 67 95 29",
    "sg:postcode":"28027",
    "sg:province":"Madrid",
    "wof:name":"Arevalo Garcia Marcelino",
    "wof:placetype":"venue"
},
  "geometry": {"coordinates":[-3.6425154209,40.4408111572],"type":"Point"}
}