{
  "type": "Feature",
  "properties": {
    "addr:full":"Calle de Cuartel De Artilleria, 19 Carmen Murcia 30002",
    "addr:housenumber":"19",
    "addr:postcode":"30002",
    "addr:street":"Calle De Cuartel;Artilleria",
    "iso:country":"ES",
    "sg:address":"Calle de Cuartel De Artilleria, 19",
    "sg:city":"Carmen",
    "sg:orig_category":"Venta, Colocaci\u00d3n, Reparaci\u00d3n De Radiadores Para Veh\u00cdculos",
    "sg:phone":"+34 968 25 37 56",
    "sg:postcode":"30002",
    "sg:province":"Murcia",
    "wof:name":"Melgarejo Torres Francisco Javier",
    "wof:placetype":"venue"
},
  "geometry": {"coordinates":[-1.1298867464,37.9834747314],"type":"Point"}
}