{
  "type": "Feature",
  "properties": {
    "addr:full":"Carrer de Riera Blanca, 150 Hospitalet Llobregat Barcelona 08903",
    "addr:housenumber":"150",
    "addr:postcode":"08903",
    "addr:street":"Carrer De Riera Blanca",
    "iso:country":"ES",
    "sg:address":"Carrer de Riera Blanca, 150",
    "sg:city":"Hospitalet Llobregat",
    "sg:orig_category":"Molduras, Junquillos, Listones Y Molduras Perforadas",
    "sg:phone":"+34 932 96 45 03",
    "sg:postcode":"08903",
    "sg:province":"Barcelona",
    "wof:name":"Piriz Ramos Avelina",
    "wof:placetype":"venue"
},
  "geometry": {"coordinates":[2.1291880608,41.3706092834],"type":"Point"}
}