{
  "type": "Feature",
  "properties": {
    "iso:country":"ES",
    "sg:address":"Avda Libertad, 33",
    "sg:city":"Ubeda",
    "sg:orig_category":"Farmacias",
    "sg:phone":"+34 953 75 19 15",
    "sg:postcode":"23400",
    "sg:province":"Ja\u00e9n",
    "wof:name":"Cruz Rodriguez Francisca",
    "wof:placetype":"venue"
},
  "geometry": {"coordinates":[-3.3658690453,38.0169410706],"type":"Point"}
}