{
  "type": "Feature",
  "properties": {
    "iso:country":"ES",
    "sg:address":"Kale Nagusia, 10",
    "sg:city":"Usurbil",
    "sg:orig_category":"Plomeros",
    "sg:phone":"+34 943 36 46 37",
    "sg:postcode":"20170",
    "sg:province":"Guip\u00f9zcoa",
    "wof:name":"Portularrume Azcue Severo",
    "wof:placetype":"venue"
},
  "geometry": {"coordinates":[-2.0539140701,43.2733459473],"type":"Point"}
}