{
  "type": "Feature",
  "properties": {
    "addr:full":"Avda Reyes Magos, 4 Alcala Henares Madrid 28806",
    "addr:housenumber":"4",
    "addr:postcode":"28806",
    "addr:street":"Avda Reyes Magos",
    "iso:country":"ES",
    "sg:address":"Avda Reyes Magos, 4",
    "sg:city":"Alcala Henares",
    "sg:orig_category":"Cajas De Ahorro",
    "sg:phone":"+34 918 78 80 00",
    "sg:postcode":"28806",
    "sg:province":"Madrid",
    "wof:name":"Caixa D'estalvis De Catalunya",
    "wof:placetype":"venue"
},
  "geometry": {"coordinates":[-3.376044035,40.490814209],"type":"Point"}
}