{
  "type": "Feature",
  "properties": {
    "addr:full":"Calle de Venezuela, 15 Galletas Santa Cruz De Tenerife 38631",
    "addr:housenumber":"15",
    "addr:postcode":"38631",
    "addr:street":"Calle De Venezuela",
    "iso:country":"ES",
    "sg:address":"Calle de Venezuela, 15",
    "sg:city":"Galletas",
    "sg:orig_category":"Ropa Para Se\u00d1oras (al Por Menor)",
    "sg:phone":"+34 922 73 18 49",
    "sg:postcode":"38631",
    "sg:province":"Santa Cruz De Tenerife",
    "wof:name":"Fabima 90 Tenerife S.l.",
    "wof:placetype":"venue"
},
  "geometry": {"coordinates":[-16.6549682617,28.0070705414],"type":"Point"}
}