{
  "type": "Feature",
  "properties": {
    "iso:country":"ES",
    "sg:address":"Avda Almeria, 27",
    "sg:city":"Caravaca Cruz",
    "sg:orig_category":"Bricolaje, Herramientas (al Por Menor)",
    "sg:phone":"+34 968 70 52 61",
    "sg:postcode":"30400",
    "sg:province":"Murcia",
    "wof:name":"Sanchez Garcia Martina",
    "wof:placetype":"venue"
},
  "geometry": {"coordinates":[-1.8651800156,38.1015548706],"type":"Point"}
}