{
  "type": "Feature",
  "properties": {
    "iso:country":"ES",
    "sg:address":"Calle de Celanova, 13",
    "sg:city":"Alcorcon",
    "sg:orig_category":"Asesor\u00cda Fiscal Y Jur\u00cddica",
    "sg:phone":"+34 916 11 30 85",
    "sg:postcode":"28925",
    "sg:province":"Madrid",
    "wof:name":"Lopez Lopez Andres",
    "wof:placetype":"venue"
},
  "geometry": {"coordinates":[-3.8111965656,40.3525505066],"type":"Point"}
}