{
  "type": "Feature",
  "properties": {
    "addr:full":"Calle de Profesor Lozano, 36 Palmas De Gran Canaria Las Palmas 35008",
    "addr:housenumber":"36",
    "addr:postcode":"35008",
    "addr:street":"Calle De Profesor Lozano",
    "iso:country":"ES",
    "sg:address":"Calle de Profesor Lozano, 36",
    "sg:city":"Palmas De Gran Canaria",
    "sg:orig_category":"Cables Y Hilos El\u00c9ctricos (fabricaci\u00d3n, Al Por Mayor)",
    "sg:phone":"+34 928 46 68 67",
    "sg:postcode":"35008",
    "sg:province":"Las Palmas",
    "sg:website":"www.cyesa.com",
    "wof:name":"Cables Y Eslingas S.a.",
    "wof:placetype":"venue"
},
  "geometry": {"coordinates":[-15.4212999344,28.1546821594],"type":"Point"}
}