{
  "type": "Feature",
  "properties": {
    "addr:full":"Avda Constitucion, 3 Jaraiz Vera C\u00e1ceres 10400",
    "addr:housenumber":"3",
    "addr:postcode":"10400",
    "addr:street":"Avda Constitucion",
    "iso:country":"ES",
    "sg:address":"Avda Constitucion, 3",
    "sg:city":"Jaraiz Vera",
    "sg:orig_category":"Universidades",
    "sg:phone":"+34 927 66 50 32",
    "sg:postcode":"10400",
    "sg:province":"C\u00e1ceres",
    "wof:name":"Patronato Universidad Popular Jaraiz De La Vera",
    "wof:placetype":"venue"
},
  "geometry": {"coordinates":[-5.7517299652,40.0622673035],"type":"Point"}
}