{
  "type": "Feature",
  "properties": {
    "addr:full":"Rua Lopez Mora, 68 Vigo Pontevedra 36211",
    "addr:housenumber":"68",
    "addr:postcode":"36211",
    "addr:street":"Rua Lopez Mora",
    "iso:country":"ES",
    "sg:address":"Rua Lopez Mora, 68",
    "sg:city":"Vigo",
    "sg:orig_category":"Supermercados Y Hipermercados",
    "sg:phone":"+34 986 29 70 79",
    "sg:postcode":"36211",
    "sg:province":"Pontevedra",
    "wof:name":"Ekoama S.l.",
    "wof:placetype":"venue"
},
  "geometry": {"coordinates":[-8.7324056625,42.2234687805],"type":"Point"}
}