{
  "type": "Feature",
  "properties": {
    "iso:country":"ES",
    "sg:address":"Calle de Cronista Carlos Valcarcel, 1",
    "sg:city":"Santa Maria De Gracia",
    "sg:orig_category":"M\u00c9dicos: Alergolog\u00cda",
    "sg:phone":"+34 968 23 23 58",
    "sg:postcode":"30008",
    "sg:province":"Murcia",
    "wof:name":"Hernandez Garcia Jeronimo",
    "wof:placetype":"venue"
},
  "geometry": {"coordinates":[-1.1298867464,37.9834747314],"type":"Point"}
}