{
  "type": "Feature",
  "properties": {
    "addr:full":"Carr Segria, 8 Torrefarrera Lleida 25123",
    "addr:housenumber":"8",
    "addr:postcode":"25123",
    "addr:street":"Carr Segria",
    "iso:country":"ES",
    "sg:address":"Carr Segria, 8",
    "sg:city":"Torrefarrera",
    "sg:orig_category":"Peluquer\u00cdas, Peluquer\u00cda Mixta",
    "sg:phone":"+34 973 75 16 41",
    "sg:postcode":"25123",
    "sg:province":"Lleida",
    "wof:name":"Peluqueria Aries C.b.",
    "wof:placetype":"venue"
},
  "geometry": {"coordinates":[0.6068980098,41.6742591858],"type":"Point"}
}