{
  "type": "Feature",
  "properties": {
    "addr:full":"Calle de Oca\u00d1a, 86 Madrid Madrid 28047",
    "addr:housenumber":"86",
    "addr:postcode":"madrid;28047",
    "addr:street":"Calle De Ocan\u0303A",
    "iso:country":"ES",
    "sg:address":"Calle de Oca\u00d1a, 86",
    "sg:city":"Madrid",
    "sg:orig_category":"Farmacias",
    "sg:phone":"+34 914 65 27 48",
    "sg:postcode":"28047",
    "sg:province":"Madrid",
    "wof:name":"Farmacia De La Pe\u00f1a Insausti C.b.",
    "wof:placetype":"venue"
},
  "geometry": {"coordinates":[-3.7521629333,40.3847579956],"type":"Point"}
}