{
  "type": "Feature",
  "properties": {
    "iso:country":"ES",
    "sg:address":"Calle de Nuestra Se\u00d1ora De La O, 3",
    "sg:city":"Chipiona",
    "sg:orig_category":"Inmobiliaria (agencias)",
    "sg:phone":"+34 956 37 31 63",
    "sg:postcode":"11550",
    "sg:province":"C\u00e1diz",
    "sg:website":"www.tecnocasa.es",
    "wof:name":"Estudio Santa Monica 2001 S.l.",
    "wof:placetype":"venue"
},
  "geometry": {"coordinates":[-6.4362711906,36.7394447327],"type":"Point"}
}