{
  "type": "Feature",
  "properties": {
    "iso:country":"ES",
    "sg:address":"Ctra Madrid Coru\u00d1a, 17",
    "sg:city":"Villalpando",
    "sg:orig_category":"Mec\u00c1nico Del Autom\u00d3vil",
    "sg:phone":"+34 980 66 00 88",
    "sg:postcode":"49630",
    "sg:province":"Zamora",
    "wof:name":"Granado Sanabria Jesus Arsenio",
    "wof:placetype":"venue"
},
  "geometry": {"coordinates":[-5.4164848328,41.862613678],"type":"Point"}
}