{
  "type": "Feature",
  "properties": {
    "addr:full":"Rua Cuba, 10 Noia La Coru\u00f1a 15200",
    "addr:housenumber":"10",
    "addr:postcode":"15200",
    "addr:street":"Rua Cuba;La Corun\u0303A",
    "iso:country":"ES",
    "sg:address":"Rua Cuba, 10",
    "sg:city":"Noia",
    "sg:orig_category":"Electricidad: Instalaciones Industriales",
    "sg:phone":"+34 981 82 21 50",
    "sg:postcode":"15200",
    "sg:province":"La Coru\u00f1a",
    "wof:name":"Electricidad Gameisa S.l",
    "wof:placetype":"venue"
},
  "geometry": {"coordinates":[-8.8845157623,42.7796592712],"type":"Point"}
}