{
  "type": "Feature",
  "properties": {
    "iso:country":"ES",
    "sg:address":"Avda Valentin Masip, 26",
    "sg:city":"Oviedo",
    "sg:orig_category":"Bisuter\u00cda, Joyer\u00cda, Relojer\u00cda (al Por Menor)",
    "sg:phone":"+34 985 27 63 13",
    "sg:postcode":"33013",
    "sg:province":"Asturias",
    "wof:name":"Garcia Cespedes Fernando",
    "wof:placetype":"venue"
},
  "geometry": {"coordinates":[-5.8621168137,43.362285614],"type":"Point"}
}