{
  "type": "Feature",
  "properties": {
    "iso:country":"ES",
    "sg:address":"San Fermin, 45",
    "sg:city":"Iru\u00f1a",
    "sg:orig_category":"Peluqueros: De Se\u00d1oras",
    "sg:phone":"+34 948 24 87 39",
    "sg:postcode":"31003",
    "sg:province":"Navarra",
    "wof:name":"Landiribar Barberena Rosalia",
    "wof:placetype":"venue"
},
  "geometry": {"coordinates":[-1.6393879652,42.8117637634],"type":"Point"}
}