{
  "type": "Feature",
  "properties": {
    "addr:full":"Ctra. Campos, Km. 0006,0 Colonia S. Jordi Islas Baleares 07638",
    "addr:postcode":"07638",
    "addr:street":"Ctra. Campos Km. 0006,0 Colonia S. Jordi",
    "iso:country":"ES",
    "sg:address":"Ctra. Campos, Km. 0006,0",
    "sg:city":"Colonia S. Jordi",
    "sg:orig_category":"Fabricaci\u00d3n De Quesos",
    "sg:phone":"+34 971 65 54 35",
    "sg:postcode":"07638",
    "sg:province":"Islas Baleares",
    "wof:name":"Formatges Burguera Sat Ba-71",
    "wof:placetype":"venue"
},
  "geometry": {"coordinates":[2.9928250313,39.3186759949],"type":"Point"}
}