{
  "type": "Feature",
  "properties": {
    "iso:country":"ES",
    "sg:address":"Carrer de Alfons Gubern, 7",
    "sg:city":"Castellar Valles",
    "sg:orig_category":"Cerrajer\u00cda, Ferrallista",
    "sg:phone":"+34 937 14 66 72",
    "sg:postcode":"08211",
    "sg:province":"Barcelona",
    "wof:name":"Sifer Castellar S.l.",
    "wof:placetype":"venue"
},
  "geometry": {"coordinates":[2.0832099915,41.6093215942],"type":"Point"}
}