{
  "type": "Feature",
  "properties": {
    "addr:full":"Pase Ronda, 21 Albolote Granada 18220",
    "addr:housenumber":"21",
    "addr:postcode":"18220",
    "addr:street":"Ronda",
    "iso:country":"ES",
    "sg:address":"Pase Ronda, 21",
    "sg:city":"Albolote",
    "sg:orig_category":"Farmacias",
    "sg:phone":"+34 958 46 58 21",
    "sg:postcode":"18220",
    "sg:province":"Granada",
    "wof:name":"Carmono Grupo Tres S.l",
    "wof:placetype":"venue"
},
  "geometry": {"coordinates":[-3.6585440636,37.2332839966],"type":"Point"}
}