{
  "type": "Feature",
  "properties": {
    "iso:country":"ES",
    "sg:address":"M. Montija, S/n",
    "sg:city":"Villalonquejar",
    "sg:orig_category":"Art\u00cdculos De Madera (fabricaci\u00d3n Y Al Por Mayor)",
    "sg:phone":"+34 947 29 87 08",
    "sg:postcode":"09001",
    "sg:province":"Burgos",
    "wof:name":"Riva Martin Julio De La",
    "wof:placetype":"venue"
},
  "geometry": {"coordinates":[-3.7355909348,42.375667572],"type":"Point"}
}