{
  "type": "Feature",
  "properties": {
    "addr:full":"Calle de Blasco De Garay, 52 Madrid Madrid 28015",
    "addr:housenumber":"52",
    "addr:postcode":"madrid;28015",
    "addr:street":"Calle De Blasco De Garay",
    "iso:country":"ES",
    "sg:address":"Calle de Blasco De Garay, 52",
    "sg:city":"Madrid",
    "sg:orig_category":"Confiter\u00cdas, Chocolater\u00cdas (al Por Menor)",
    "sg:phone":"+34 915 43 93 54",
    "sg:postcode":"28015",
    "sg:province":"Madrid",
    "wof:name":"Rubio Sanchez Jose",
    "wof:placetype":"venue"
},
  "geometry": {"coordinates":[-3.7114133835,40.4351921082],"type":"Point"}
}