{
  "type": "Feature",
  "properties": {
    "addr:full":"Ctra Villamediana, 66 Murillo De Rio Leza La Rioja 26143",
    "addr:housenumber":"66",
    "addr:postcode":"26143",
    "addr:street":"Ctra Villamediana;Rioja",
    "iso:country":"ES",
    "sg:address":"Ctra Villamediana, 66",
    "sg:city":"Murillo De Rio Leza",
    "sg:orig_category":"Instalaci\u00d3n, Reparaci\u00d3n De Calefacci\u00d3n Por Gas",
    "sg:phone":"+34 941 43 25 21",
    "sg:postcode":"26143",
    "sg:province":"La Rioja",
    "wof:name":"Saenz De Jubera S.l.",
    "wof:placetype":"venue"
},
  "geometry": {"coordinates":[-2.3255090714,42.401058197],"type":"Point"}
}