{
  "type": "Feature",
  "properties": {
    "iso:country":"ES",
    "sg:address":"Avda Logro\u00d1o, S/n",
    "sg:city":"Haro",
    "sg:orig_category":"Mec\u00c1nico Del Autom\u00d3vil",
    "sg:phone":"+34 941 31 02 38",
    "sg:postcode":"26200",
    "sg:province":"La Rioja",
    "wof:name":"Talleres Zabala S. L.",
    "wof:placetype":"venue"
},
  "geometry": {"coordinates":[-2.8460888863,42.571723938],"type":"Point"}
}