{
  "type": "Feature",
  "properties": {
    "addr:full":"Carr Joana Roca, De Na, 63 Son Servera Islas Baleares 07550",
    "addr:housenumber":"63",
    "addr:postcode":"07550",
    "addr:street":"Carr Joana Roca De Na",
    "iso:country":"ES",
    "sg:address":"Carr Joana Roca, De Na, 63",
    "sg:city":"Son Servera",
    "sg:orig_category":"Laboratorios Y Trabajos De Fotograf\u00cda, V\u00cddeo Y Cine",
    "sg:phone":"+34 971 81 74 09",
    "sg:postcode":"07550",
    "sg:province":"Islas Baleares",
    "wof:name":"Buttner  Miguel Tomas",
    "wof:placetype":"venue"
},
  "geometry": {"coordinates":[3.3609130383,39.6216545105],"type":"Point"}
}