{
  "type": "Feature",
  "properties": {
    "iso:country":"ES",
    "sg:address":"Carrer de Tauli, 16",
    "sg:city":"Sabadell",
    "sg:orig_category":"Sindicatos De Trabajadores",
    "sg:phone":"+34 937 17 53 01",
    "sg:postcode":"08208",
    "sg:province":"Barcelona",
    "wof:name":"Confederacion Nacional Del Trabajo",
    "wof:placetype":"venue"
},
  "geometry": {"coordinates":[2.1077229977,41.5532569885],"type":"Point"}
}