{
  "type": "Feature",
  "properties": {
    "iso:country":"ES",
    "sg:address":"Calle de Real, 117",
    "sg:city":"Estepona",
    "sg:orig_category":"Asesor\u00cda Fiscal Y Jur\u00cddica",
    "sg:phone":"+34 952 80 25 67",
    "sg:postcode":"29680",
    "sg:province":"M\u00e1laga",
    "wof:name":"Antonio Foncillas Estepona S.a.",
    "wof:placetype":"venue"
},
  "geometry": {"coordinates":[-5.1460118294,36.4241600037],"type":"Point"}
}