{
  "type": "Feature",
  "properties": {
    "addr:full":"Calle de Jose Recuerda Rubio, 2 Sevilla Sevilla 41018",
    "addr:housenumber":"2",
    "addr:postcode":"41018",
    "addr:street":"Calle De Jose Recuerda Rubio",
    "iso:country":"ES",
    "sg:address":"Calle de Jose Recuerda Rubio, 2",
    "sg:city":"Sevilla",
    "sg:orig_category":"M\u00c9dicos: Endocrinolog\u00cda Y Metabolismo",
    "sg:phone":"+34 954 92 52 14",
    "sg:postcode":"41018",
    "sg:province":"Sevilla",
    "wof:name":"Montenegro Rodriguez Luis Roberto",
    "wof:placetype":"venue"
},
  "geometry": {"coordinates":[-5.979227066,37.3799934387],"type":"Point"}
}