{
  "type": "Feature",
  "properties": {
    "iso:country":"ES",
    "sg:address":"Pl Azucena, 12",
    "sg:city":"Pedreguer",
    "sg:orig_category":"Supermercados Y Hipermercados",
    "sg:phone":"+34 965 76 03 78",
    "sg:postcode":"03750",
    "sg:province":"Alicante",
    "wof:name":"Tendes Margarida S.l.",
    "wof:placetype":"venue"
},
  "geometry": {"coordinates":[0.0347849987,38.7958145142],"type":"Point"}
}