{
  "type": "Feature",
  "properties": {
    "iso:country":"ES",
    "sg:address":"Calle de Federico Moreno Torroba, 1",
    "sg:city":"Madrid",
    "sg:orig_category":"Ingenier\u00cda, Centros De Estudios (diversos)",
    "sg:phone":"+34 915 01 96 53",
    "sg:postcode":"28007",
    "sg:province":"Madrid",
    "wof:name":"Rodriguez Mu\u00f1oz Jose",
    "wof:placetype":"venue"
},
  "geometry": {"coordinates":[-3.6671578884,40.4050369263],"type":"Point"}
}