{
  "type": "Feature",
  "properties": {
    "addr:full":"Cmno Esperanza, 22 Valladolid Valladolid 47007",
    "addr:housenumber":"22",
    "addr:postcode":"47007",
    "addr:street":"Cmno Esperanza",
    "iso:country":"ES",
    "sg:address":"Cmno Esperanza, 22",
    "sg:city":"Valladolid",
    "sg:orig_category":"Estancos",
    "sg:phone":"+34 983 23 21 66",
    "sg:postcode":"47007",
    "sg:province":"Valladolid",
    "wof:name":"Cancio Hernandez Maria Jesus",
    "wof:placetype":"venue"
},
  "geometry": {"coordinates":[-4.7365260124,41.6344299316],"type":"Point"}
}