{
  "type": "Feature",
  "properties": {
    "iso:country":"ES",
    "sg:address":"Plaz Canteras (de Las), 16",
    "sg:city":"Ubeda",
    "sg:orig_category":"Cristaler\u00cdas",
    "sg:phone":"+34 953 75 11 18",
    "sg:postcode":"23400",
    "sg:province":"Ja\u00e9n",
    "wof:name":"Quesada Molina Enrique",
    "wof:placetype":"venue"
},
  "geometry": {"coordinates":[-3.3655900955,38.0180702209],"type":"Point"}
}