{
  "type": "Feature",
  "properties": {
    "iso:country":"ES",
    "sg:address":"Calle de Ubeda, S/n",
    "sg:city":"Madrid",
    "sg:orig_category":"Venta, Montaje De Neum\u00c1ticos",
    "sg:phone":"+34 913 78 15 20",
    "sg:postcode":"28034",
    "sg:province":"Madrid",
    "wof:name":"Sadeco S.a.",
    "wof:placetype":"venue"
},
  "geometry": {"coordinates":[-3.7128410339,40.4831695557],"type":"Point"}
}