{
  "type": "Feature",
  "properties": {
    "addr:full":"Carrer de Valencia, 3 Sitges Barcelona 08870",
    "addr:housenumber":"3",
    "addr:postcode":"08870",
    "addr:street":"Carrer De Valencia",
    "iso:country":"ES",
    "sg:address":"Carrer de Valencia, 3",
    "sg:city":"Sitges",
    "sg:orig_category":"Abogados",
    "sg:phone":"+34 938 11 07 46",
    "sg:postcode":"08870",
    "sg:province":"Barcelona",
    "wof:name":"Casas Royo Josefina",
    "wof:placetype":"venue"
},
  "geometry": {"coordinates":[1.799867034,41.2364883423],"type":"Point"}
}