{
  "type": "Feature",
  "properties": {
    "iso:country":"ES",
    "sg:address":"Calle de Hermanos Miranda, 5",
    "sg:city":"Moreda",
    "sg:orig_category":"Flores Y Plantas Naturales (al Por Mayor)",
    "sg:phone":"+34 985 48 01 75",
    "sg:postcode":"33670",
    "sg:province":"Asturias",
    "wof:name":"Garcia Suarez Carmen",
    "wof:placetype":"venue"
},
  "geometry": {"coordinates":[-5.7376289368,43.1678504944],"type":"Point"}
}