{
  "type": "Feature",
  "properties": {
    "addr:full":"Psaj Botica La, 2 Huelva Huelva 21001",
    "addr:postcode":"21001",
    "iso:country":"ES",
    "sg:address":"Psaj Botica La, 2",
    "sg:city":"Huelva",
    "sg:orig_category":"Perfumer\u00cda, Art\u00cdculos De Ba\u00d1o (fabricaci\u00d3n, Al Por Mayor)",
    "sg:phone":"+34 959 25 15 40",
    "sg:postcode":"21001",
    "sg:province":"Huelva",
    "wof:name":"Suarez Salazar S.l.",
    "wof:placetype":"venue"
},
  "geometry": {"coordinates":[-6.9495940208,37.256313324],"type":"Point"}
}