{
  "type": "Feature",
  "properties": {
    "addr:full":"Calle de Jose Cabrera, 10 Madrid Madrid 28044",
    "addr:housenumber":"10",
    "addr:postcode":"madrid;28044",
    "addr:street":"Calle De Jose Cabrera",
    "iso:country":"ES",
    "sg:address":"Calle de Jose Cabrera, 10",
    "sg:city":"Madrid",
    "sg:orig_category":"Asesor\u00cda Sobre Comunicaci\u00d3n De Empresas",
    "sg:phone":"+34 915 09 53 20",
    "sg:postcode":"28044",
    "sg:province":"Madrid",
    "wof:name":"Gestiones Integrales Ases S.l.",
    "wof:placetype":"venue"
},
  "geometry": {"coordinates":[-3.7582490444,40.3728752136],"type":"Point"}
}