{
  "type": "Feature",
  "properties": {
    "addr:full":"Baixador Del Passeig De Gracia, S/n Barcelona Barcelona 08007",
    "addr:housenumber":"s / n",
    "addr:postcode":"08007",
    "addr:street":"Passeig De Gracia",
    "iso:country":"ES",
    "sg:address":"Baixador Del Passeig De Gracia, S/n",
    "sg:city":"Barcelona",
    "sg:orig_category":"Molduras, Junquillos, Listones Y Molduras Perforadas",
    "sg:phone":"+34 932 15 70 14",
    "sg:postcode":"08007",
    "sg:province":"Barcelona",
    "wof:name":"Areas S.a.",
    "wof:placetype":"venue"
},
  "geometry": {"coordinates":[2.1659004688,41.3896484375],"type":"Point"}
}