{
  "type": "Feature",
  "properties": {
    "iso:country":"ES",
    "sg:address":"Partida Pla Roig, S/n",
    "sg:city":"Gaianes",
    "sg:orig_category":"Hilaturas, Hilos Y Actividades Relacionadas",
    "sg:phone":"+34 965 51 51 56",
    "sg:postcode":"03840",
    "sg:province":"Alicante",
    "wof:name":"Arte Fil S. L.",
    "wof:placetype":"venue"
},
  "geometry": {"coordinates":[-0.4078058004,38.8146057129],"type":"Point"}
}