{
  "type": "Feature",
  "properties": {
    "iso:country":"ES",
    "sg:address":"Basadroa, S/n",
    "sg:city":"Eidian",
    "sg:orig_category":"Cr\u00cda De Animales",
    "sg:phone":"+34 986 78 81 81",
    "sg:postcode":"36527",
    "sg:province":"Pontevedra",
    "wof:name":"Seijo Souto Angel Luis",
    "wof:placetype":"venue"
},
  "geometry": {"coordinates":[-7.9774627686,42.8420181274],"type":"Point"}
}