{
  "type": "Feature",
  "properties": {
    "iso:country":"ES",
    "sg:address":"Ctra Santa Coloma, 99",
    "sg:city":"Girona",
    "sg:orig_category":"Agentes, Concesionarios Y Sucursales De Veh\u00cdculos",
    "sg:phone":"+34 972 23 12 14",
    "sg:postcode":"17005",
    "sg:province":"Girona",
    "sg:website":"www.tecnicamer.net",
    "wof:name":"Tecnicamer S.l.",
    "wof:placetype":"venue"
},
  "geometry": {"coordinates":[2.8043160439,41.9610366821],"type":"Point"}
}