{
  "type": "Feature",
  "properties": {
    "iso:country":"ES",
    "sg:address":"Pl Viladecans, 8",
    "sg:city":"Viladecans",
    "sg:orig_category":"Panader\u00cdas, Panader\u00cdas",
    "sg:phone":"+34 936 37 74 26",
    "sg:postcode":"08840",
    "sg:province":"Barcelona",
    "wof:name":"Marti Trias Miguel",
    "wof:placetype":"venue"
},
  "geometry": {"coordinates":[2.0205409527,41.3159446716],"type":"Point"}
}