{
  "type": "Feature",
  "properties": {
    "addr:full":"Calle de Emilia Ballester, 29 Madrid Madrid 28021",
    "addr:housenumber":"29",
    "addr:postcode":"madrid;28021",
    "addr:street":"Calle De Emilia Ballester",
    "iso:country":"ES",
    "sg:address":"Calle de Emilia Ballester, 29",
    "sg:city":"Madrid",
    "sg:orig_category":"Fachadas",
    "sg:phone":"+34 917 98 75 79",
    "sg:postcode":"28021",
    "sg:province":"Madrid",
    "wof:name":"Conservacion Y Proyectos Madrid S.l.",
    "wof:placetype":"venue"
},
  "geometry": {"coordinates":[-3.7129778862,40.3457107544],"type":"Point"}
}