{
  "type": "Feature",
  "properties": {
    "iso:country":"ES",
    "sg:address":"Carrer de Garrofers (dels), 21",
    "sg:city":"Torredembarra",
    "sg:orig_category":"Negocio De Materiales De Construcci\u00d3n",
    "sg:phone":"+34 977 64 11 64",
    "sg:postcode":"43830",
    "sg:province":"Tarragona",
    "wof:name":"Prieto Lopez Antonio",
    "wof:placetype":"venue"
},
  "geometry": {"coordinates":[1.4029899836,41.1460494995],"type":"Point"}
}