{
  "type": "Feature",
  "properties": {
    "addr:full":"Rua Nueva, 8 Padron La Coru\u00f1a 15900",
    "addr:housenumber":"8",
    "addr:postcode":"15900",
    "addr:street":"Rua Nueva;Padron La Corun\u0303A",
    "iso:country":"ES",
    "sg:address":"Rua Nueva, 8",
    "sg:city":"Padron",
    "sg:orig_category":"Iglesia Cat\u00d3lica",
    "sg:phone":"+34 981 81 03 50",
    "sg:postcode":"15900",
    "sg:province":"La Coru\u00f1a",
    "wof:name":"Arzobispado De Santiago",
    "wof:placetype":"venue"
},
  "geometry": {"coordinates":[-8.6605377197,42.7389755249],"type":"Point"}
}