{
  "type": "Feature",
  "properties": {
    "addr:full":"Calle de Otilia Diaz, 8 Arrecife Las Palmas 35500",
    "addr:housenumber":"8",
    "addr:postcode":"35500",
    "addr:street":"Calle De Otilia Diaz",
    "iso:country":"ES",
    "sg:address":"Calle de Otilia Diaz, 8",
    "sg:city":"Arrecife",
    "sg:orig_category":"Ingenier\u00cda, Centros De Estudios (diversos)",
    "sg:phone":"+34 928 81 67 95",
    "sg:postcode":"35500",
    "sg:province":"Las Palmas",
    "wof:name":"Montero Barreto Jose Manuel",
    "wof:placetype":"venue"
},
  "geometry": {"coordinates":[-13.5481920242,28.9593715668],"type":"Point"}
}