{
  "type": "Feature",
  "properties": {
    "addr:full":"Calle de Amparo, 100 Madrid Madrid 28012",
    "addr:housenumber":"100",
    "addr:postcode":"28012",
    "addr:street":"Calle De Amparo",
    "iso:country":"ES",
    "sg:address":"Calle de Amparo, 100",
    "sg:city":"Madrid",
    "sg:orig_category":"Bazares, Art\u00cdculos De Limpieza Y De Cocina (al Por Menor)",
    "sg:phone":"+34 915 30 40 58",
    "sg:postcode":"28012",
    "sg:province":"Madrid",
    "wof:name":"Hong Mei Gui S.l.",
    "wof:placetype":"venue"
},
  "geometry": {"coordinates":[-3.7001819611,40.4059143066],"type":"Point"}
}