{
  "type": "Feature",
  "properties": {
    "iso:country":"ES",
    "sg:address":"Ctra Sevilla-granada, Km. 0119,0",
    "sg:city":"Roda Andalucia",
    "sg:orig_category":"Aceites Y Grasas Alimentarias (fabricaci\u00d3n, Al Por Mayor)",
    "sg:phone":"+34 954 01 67 74",
    "sg:postcode":"41590",
    "sg:province":"Sevilla",
    "wof:name":"Aceitera Del Guadalquivir S.a.",
    "wof:placetype":"venue"
},
  "geometry": {"coordinates":[-5.9962949753,37.3826408386],"type":"Point"}
}