{
  "type": "Feature",
  "properties": {
    "iso:country":"ES",
    "sg:address":"Carrer de Sant Josep De Calassan\u00c7, 6",
    "sg:city":"Granollers",
    "sg:orig_category":"Agencias De Trabajo Temporal",
    "sg:phone":"+34 938 79 35 51",
    "sg:postcode":"08402",
    "sg:province":"Barcelona",
    "sg:website":"www.marlex.es",
    "wof:name":"Marlex Gestio Ett S.l.",
    "wof:placetype":"venue"
},
  "geometry": {"coordinates":[2.2898600101,41.6058006287],"type":"Point"}
}