{
  "type": "Feature",
  "properties": {
    "addr:full":"Calle de Iglesia, 22 Casas De Fernando Alonso Cuenca 16610",
    "addr:housenumber":"22",
    "addr:postcode":"16610",
    "addr:street":"Calle De Iglesia",
    "iso:country":"ES",
    "sg:address":"Calle de Iglesia, 22",
    "sg:city":"Casas De Fernando Alonso",
    "sg:orig_category":"Producci\u00d3n, Venta De Productos De Agricultura Biol\u00d3gica",
    "sg:phone":"+34 969 38 30 55",
    "sg:postcode":"16610",
    "sg:province":"Cuenca",
    "wof:name":"Agricola Esteso S.l.",
    "wof:placetype":"venue"
},
  "geometry": {"coordinates":[-2.3223323822,39.3511772156],"type":"Point"}
}