{
  "type": "Feature",
  "properties": {
    "addr:full":"Molinos, 25 Ronda M\u00e1laga 29400",
    "addr:housenumber":"25",
    "addr:postcode":"29400",
    "addr:street":"Molinos;Ronda Ma\u0301Laga",
    "iso:country":"ES",
    "sg:address":"Molinos, 25",
    "sg:city":"Ronda",
    "sg:orig_category":"Cerrajer\u00cda, Ferrallista",
    "sg:phone":"+34 952 87 70 61",
    "sg:postcode":"29400",
    "sg:province":"M\u00e1laga",
    "wof:name":"Gazaba Garcia Manuel",
    "wof:placetype":"venue"
},
  "geometry": {"coordinates":[-5.1669912338,36.7449226379],"type":"Point"}
}