{
  "type": "Feature",
  "properties": {
    "addr:full":"Av Rapita (de La), 152 Amposta Tarragona 43870",
    "addr:housenumber":"152",
    "addr:postcode":"43870",
    "addr:street":"Av Rapita De La",
    "iso:country":"ES",
    "sg:address":"Av Rapita (de La), 152",
    "sg:city":"Amposta",
    "sg:orig_category":"Radiocomunicaciones, Telefon\u00cda M\u00d3vil, Radiomensajer\u00cda: Servicios, Comercializaci\u00d3n",
    "sg:phone":"+34 977 70 40 70",
    "sg:postcode":"43870",
    "sg:province":"Tarragona",
    "wof:name":"Ebre Line S.l.",
    "wof:placetype":"venue"
},
  "geometry": {"coordinates":[0.5795159936,40.7021713257],"type":"Point"}
}