{
  "type": "Feature",
  "properties": {
    "addr:full":"Calle de Coronela (la), 10 Guincho Santa Cruz De Tenerife 38458",
    "addr:housenumber":"10",
    "addr:postcode":"38458",
    "addr:street":"Calle De Coronela La",
    "iso:country":"ES",
    "sg:address":"Calle de Coronela (la), 10",
    "sg:city":"Guincho",
    "sg:orig_category":"\u00c1rboles Frutales",
    "sg:phone":"+34 922 13 31 20",
    "sg:postcode":"38458",
    "sg:province":"Santa Cruz De Tenerife",
    "wof:name":"La Sorriba S.a.",
    "wof:placetype":"venue"
},
  "geometry": {"coordinates":[-16.7407798767,28.3733291626],"type":"Point"}
}