{
  "type": "Feature",
  "properties": {
    "addr:full":"Paredes, S/n Vilaboa Pontevedra 36141",
    "addr:postcode":"36141",
    "addr:street":"Paredes S / N",
    "iso:country":"ES",
    "sg:address":"Paredes, S/n",
    "sg:city":"Vilaboa",
    "sg:orig_category":"Centros De Educaci\u00d3n Especial",
    "sg:phone":"+34 986 70 92 54",
    "sg:postcode":"36141",
    "sg:province":"Pontevedra",
    "wof:name":"Ayuntamiento De Vilaboa",
    "wof:placetype":"venue"
},
  "geometry": {"coordinates":[-8.6231517792,42.355670929],"type":"Point"}
}