{
  "type": "Feature",
  "properties": {
    "addr:full":"Calle de Antonio Hurtado De Mendoza, 8 Castro Urdiales Cantabria 39700",
    "addr:housenumber":"8",
    "addr:postcode":"39700",
    "addr:street":"Calle De Antonio Hurtado De Mendoza",
    "iso:country":"ES",
    "sg:address":"Calle de Antonio Hurtado De Mendoza, 8",
    "sg:city":"Castro Urdiales",
    "sg:orig_category":"Asociaciones Y Clubs Deportivos",
    "sg:phone":"+34 942 86 47 28",
    "sg:postcode":"39700",
    "sg:province":"Cantabria",
    "wof:name":"Informacion Y Gestion Telematica S.l.",
    "wof:placetype":"venue"
},
  "geometry": {"coordinates":[-3.2204108238,43.3821105957],"type":"Point"}
}