{
  "type": "Feature",
  "properties": {
    "iso:country":"ES",
    "sg:address":"Calle de Emires Los, S/n",
    "sg:city":"Huelva",
    "sg:orig_category":"Guarder\u00cdas",
    "sg:phone":"+34 959 28 57 90",
    "sg:postcode":"21001",
    "sg:province":"Huelva",
    "wof:name":"Marjovimar Sl",
    "wof:placetype":"venue"
},
  "geometry": {"coordinates":[-6.9495940208,37.256313324],"type":"Point"}
}