{
  "type": "Feature",
  "properties": {
    "iso:country":"ES",
    "sg:address":"La Posada, 3",
    "sg:city":"Higueruela",
    "sg:orig_category":"Farmacias",
    "sg:phone":"+34 967 28 70 72",
    "sg:postcode":"02694",
    "sg:province":"Albacete",
    "wof:name":"Olivares Delicado Feliciana",
    "wof:placetype":"venue"
},
  "geometry": {"coordinates":[-1.4442009926,38.9629516602],"type":"Point"}
}