{
  "type": "Feature",
  "properties": {
    "addr:full":"Calle de Venezuela, 5 Coslada Madrid 28820",
    "addr:housenumber":"5",
    "addr:postcode":"28820",
    "addr:street":"Calle De Venezuela",
    "iso:country":"ES",
    "sg:address":"Calle de Venezuela, 5",
    "sg:city":"Coslada",
    "sg:orig_category":"Transportes Por V\u00cdas Navegables",
    "sg:phone":"+34 916 72 00 40",
    "sg:postcode":"28820",
    "sg:province":"Madrid",
    "wof:name":"Trahercosa S.l.",
    "wof:placetype":"venue"
},
  "geometry": {"coordinates":[-3.5417890549,40.4304466248],"type":"Point"}
}