{
  "type": "Feature",
  "properties": {
    "addr:full":"Calle de Collado, 34 Hervas C\u00e1ceres 10700",
    "addr:housenumber":"34",
    "addr:postcode":"10700",
    "addr:street":"Calle De Collado;Ca\u0301Ceres",
    "iso:country":"ES",
    "sg:address":"Calle de Collado, 34",
    "sg:city":"Hervas",
    "sg:orig_category":"Alimentaci\u00d3n General (al Por Menor)",
    "sg:phone":"+34 927 48 10 52",
    "sg:postcode":"10700",
    "sg:province":"C\u00e1ceres",
    "wof:name":"Dominguez Barbero Alipio",
    "wof:placetype":"venue"
},
  "geometry": {"coordinates":[-5.8595089912,40.274471283],"type":"Point"}
}