{
  "type": "Feature",
  "properties": {
    "iso:country":"ES",
    "sg:address":"Carrer de Diputacio, 477",
    "sg:city":"Barcelona",
    "sg:orig_category":"Mec\u00c1nico Del Autom\u00d3vil",
    "sg:phone":"+34 932 65 26 47",
    "sg:postcode":"08013",
    "sg:province":"Barcelona",
    "wof:name":"Talleres Del Automovil Spauto S.l.",
    "wof:placetype":"venue"
},
  "geometry": {"coordinates":[2.1815578938,41.4014472961],"type":"Point"}
}