{
  "type": "Feature",
  "properties": {
    "addr:full":"Carrer de Pau Casals, 25 Cambrils Tarragona 43850",
    "addr:housenumber":"25",
    "addr:postcode":"43850",
    "addr:street":"Carrer De Pau Casals",
    "iso:country":"ES",
    "sg:address":"Carrer de Pau Casals, 25",
    "sg:city":"Cambrils",
    "sg:orig_category":"Distribuci\u00d3n De Petr\u00d3leo Y Derivados",
    "sg:phone":"+34 977 36 00 50",
    "sg:postcode":"43850",
    "sg:province":"Tarragona",
    "wof:name":"Peixos Savall I Matas S.l.",
    "wof:placetype":"venue"
},
  "geometry": {"coordinates":[1.0617250204,41.066608429],"type":"Point"}
}