{
  "type": "Feature",
  "properties": {
    "addr:full":"Calle de Gongora, 7 Cordoba C\u00f3rdoba 14001",
    "addr:housenumber":"7",
    "addr:postcode":"14001",
    "addr:street":"Calle De Gongora;Co\u0301Rdoba",
    "iso:country":"ES",
    "sg:address":"Calle de Gongora, 7",
    "sg:city":"Cordoba",
    "sg:orig_category":"Transportes Por V\u00cdas Navegables",
    "sg:phone":"+34 957 47 83 22",
    "sg:postcode":"14001",
    "sg:province":"C\u00f3rdoba",
    "wof:name":"Peninsular De Servicios De Intermediacion",
    "wof:placetype":"venue"
},
  "geometry": {"coordinates":[-4.7804942131,37.8859176636],"type":"Point"}
}