{
  "type": "Feature",
  "properties": {
    "addr:full":"Plaz Independencia, 1 Carde\u00f1a C\u00f3rdoba 14445",
    "addr:housenumber":"1",
    "addr:postcode":"14445",
    "addr:street":"Plaz Independencia;Co\u0301Rdoba",
    "iso:country":"ES",
    "sg:address":"Plaz Independencia, 1",
    "sg:city":"Carde\u00f1a",
    "sg:orig_category":"Cajas Para Embalar",
    "sg:phone":"+34 957 17 42 95",
    "sg:postcode":"14445",
    "sg:province":"C\u00f3rdoba",
    "sg:website":"www.ruralvia.com",
    "wof:name":"Caja Rural De Cordoba",
    "wof:placetype":"venue"
},
  "geometry": {"coordinates":[-4.3238458633,38.270450592],"type":"Point"}
}