{
  "type": "Feature",
  "properties": {
    "addr:full":"Rua Burgas (das), 2 Ourense Ourense 32005",
    "addr:postcode":"32005",
    "addr:street":"Rua Burgas Das",
    "iso:country":"ES",
    "sg:address":"Rua Burgas (das), 2",
    "sg:city":"Ourense",
    "sg:orig_category":"M\u00c9dicos: An\u00c1lisis Cl\u00cdnicos",
    "sg:phone":"+34 988 24 07 26",
    "sg:postcode":"32005",
    "sg:province":"Ourense",
    "wof:name":"Gonzalez Hernandez Sara",
    "wof:placetype":"venue"
},
  "geometry": {"coordinates":[-7.8642029762,42.3347053528],"type":"Point"}
}