{
  "type": "Feature",
  "properties": {
    "iso:country":"ES",
    "sg:address":"Avda Puerta De La Villa, 4",
    "sg:city":"Adamuz",
    "sg:orig_category":"Peluquer\u00cdas, Peluquer\u00cda Mixta",
    "sg:phone":"+34 957 16 63 94",
    "sg:postcode":"14430",
    "sg:province":"C\u00f3rdoba",
    "wof:name":"Delgado Mendoza Rafael",
    "wof:placetype":"venue"
},
  "geometry": {"coordinates":[-4.5221991539,38.0266990662],"type":"Point"}
}