{
  "type": "Feature",
  "properties": {
    "iso:country":"ES",
    "sg:address":"Calle de Julio Burell, 3",
    "sg:city":"Begijar",
    "sg:orig_category":"Aparatos E Instalaci\u00d3n De Regad\u00cdos",
    "sg:phone":"+34 953 76 42 90",
    "sg:postcode":"23520",
    "sg:province":"Ja\u00e9n",
    "wof:name":"S.a.t. Via Nueva",
    "wof:placetype":"venue"
},
  "geometry": {"coordinates":[-3.5338039398,37.9853210449],"type":"Point"}
}