{
  "type": "Feature",
  "properties": {
    "iso:country":"ES",
    "sg:address":"Calle de Cervantes, 9",
    "sg:city":"Daimiel",
    "sg:orig_category":"Albergues",
    "sg:phone":"+34 926 85 29 75",
    "sg:postcode":"13250",
    "sg:province":"Ciudad Real",
    "wof:name":"Horuelo",
    "wof:placetype":"venue"
},
  "geometry": {"coordinates":[-3.6136388779,39.0714569092],"type":"Point"}
}