{
  "type": "Feature",
  "properties": {
    "addr:full":"Calle de Felipe Santander, 35 Tordesillas Valladolid 47100",
    "addr:housenumber":"35",
    "addr:postcode":"47100",
    "addr:street":"Calle De Felipe Santander",
    "iso:country":"ES",
    "sg:address":"Calle de Felipe Santander, 35",
    "sg:city":"Tordesillas",
    "sg:orig_category":"Pescader\u00cdas (al Por Menor)",
    "sg:phone":"+34 983 77 03 34",
    "sg:postcode":"47100",
    "sg:province":"Valladolid",
    "wof:name":"Bastida Gonzalez Pedro",
    "wof:placetype":"venue"
},
  "geometry": {"coordinates":[-5.0080041885,41.5020980835],"type":"Point"}
}