{
  "type": "Feature",
  "properties": {
    "iso:country":"ES",
    "sg:address":"Calle de Corredera, 104",
    "sg:city":"Almansa",
    "sg:orig_category":"Restaurantes",
    "sg:phone":"+34 967 34 00 35",
    "sg:postcode":"02640",
    "sg:province":"Albacete",
    "wof:name":"Salones Ramona S.l.",
    "wof:placetype":"venue"
},
  "geometry": {"coordinates":[-1.0939664841,38.8655815125],"type":"Point"}
}