{
  "type": "Feature",
  "properties": {
    "addr:full":"Calle de Moral (del), 2 Campo Real Madrid 28510",
    "addr:housenumber":"2",
    "addr:postcode":"28510",
    "addr:street":"Calle De Moral Del",
    "iso:country":"ES",
    "sg:address":"Calle de Moral (del), 2",
    "sg:city":"Campo Real",
    "sg:orig_category":"Asistencia Social",
    "sg:phone":"+34 918 73 38 88",
    "sg:postcode":"28510",
    "sg:province":"Madrid",
    "wof:name":"Mancomunidad De Servicios Sociales",
    "wof:placetype":"venue"
},
  "geometry": {"coordinates":[-3.3803160191,40.340171814],"type":"Point"}
}