{
  "type": "Feature",
  "properties": {
    "iso:country":"ES",
    "sg:address":"Carrer de Porto, 9",
    "sg:city":"Sabadell",
    "sg:orig_category":"Suministros Y Colocaci\u00d3n De Canalones Para Aguas Pluviales",
    "sg:phone":"+34 937 46 06 11",
    "sg:postcode":"08207",
    "sg:province":"Barcelona",
    "wof:name":"Canales Pluviales Hermanos Garcia S.l.",
    "wof:placetype":"venue"
},
  "geometry": {"coordinates":[2.1075999737,41.5487632751],"type":"Point"}
}