{
  "type": "Feature",
  "properties": {
    "addr:full":"Plaz Aragon, 2 Huerto Huesca 22210",
    "addr:housenumber":"2",
    "addr:postcode":"22210",
    "addr:street":"Huerto Huesca",
    "iso:country":"ES",
    "sg:address":"Plaz Aragon, 2",
    "sg:city":"Huerto",
    "sg:orig_category":"Cajas Para Embalar",
    "sg:phone":"+34 974 39 54 52",
    "sg:postcode":"22210",
    "sg:province":"Huesca",
    "wof:name":"Caja Rural Aragonesa Y De Los Pirineos",
    "wof:placetype":"venue"
},
  "geometry": {"coordinates":[-0.1668529958,41.9306793213],"type":"Point"}
}