{
  "type": "Feature",
  "properties": {
    "iso:country":"ES",
    "sg:address":"Plaz Constitucion (de La), 5",
    "sg:city":"Valdemoro",
    "sg:orig_category":"Ropa Para Se\u00d1oras (al Por Menor)",
    "sg:phone":"+34 918 95 01 53",
    "sg:postcode":"28340",
    "sg:province":"Madrid",
    "wof:name":"Prous Zaragoza Maria Dolores",
    "wof:placetype":"venue"
},
  "geometry": {"coordinates":[-3.6738090515,40.1909751892],"type":"Point"}
}