{
  "type": "Feature",
  "properties": {
    "iso:country":"ES",
    "sg:address":"Grup Sobalbadun, 29",
    "sg:city":"San Juan De Muskiz",
    "sg:orig_category":"Cl\u00cdnicas Dentales",
    "sg:phone":"+34 946 70 81 45",
    "sg:postcode":"48550",
    "sg:province":"Vizcaya",
    "wof:name":"Abarrategui Lopez Miren Itziar",
    "wof:placetype":"venue"
},
  "geometry": {"coordinates":[-3.116182,43.321442],"type":"Point"}
}