{
  "type": "Feature",
  "properties": {
    "addr:full":"Ctra Mojonera, Km. 0000,3 Santa Maria Aguila Almer\u00eda 04710",
    "addr:postcode":"04710",
    "addr:street":"Ctra Mojonera Km. 0000,3;Almeri\u0301A",
    "iso:country":"ES",
    "sg:address":"Ctra Mojonera, Km. 0000,3",
    "sg:city":"Santa Maria Aguila",
    "sg:orig_category":"Venta, Montaje De Neum\u00c1ticos",
    "sg:phone":"+34 950 58 15 29",
    "sg:postcode":"04710",
    "sg:province":"Almer\u00eda",
    "wof:name":"Neumaticos Ejido S.l.",
    "wof:placetype":"venue"
},
  "geometry": {"coordinates":[-2.7759139538,36.7795753479],"type":"Point"}
}