{
  "type": "Feature",
  "properties": {
    "addr:full":"Calle de Azucena, 8 Mora Toledo 45400",
    "addr:housenumber":"8",
    "addr:postcode":"45400",
    "addr:street":"Calle De Azucena",
    "iso:country":"ES",
    "sg:address":"Calle de Azucena, 8",
    "sg:city":"Mora",
    "sg:orig_category":"Laboratorios",
    "sg:phone":"+34 925 30 06 23",
    "sg:postcode":"45400",
    "sg:province":"Toledo",
    "wof:name":"Explotaciones Agropecuarias Tolivis S. L.",
    "wof:placetype":"venue"
},
  "geometry": {"coordinates":[-3.7720961571,39.6860961914],"type":"Point"}
}