{
  "type": "Feature",
  "properties": {
    "iso:country":"ES",
    "sg:address":"Pol Ind El Portal, S/n",
    "sg:city":"Jerez",
    "sg:orig_category":"Herramientas Y Suministros Para Plomeros",
    "sg:phone":"+34 956 14 50 53",
    "sg:postcode":"11408",
    "sg:province":"C\u00e1diz",
    "wof:name":"Sumistros De Obrasy Fontaneria S.l.",
    "wof:placetype":"venue"
},
  "geometry": {"coordinates":[-6.1592831612,36.6686592102],"type":"Point"}
}