{
  "type": "Feature",
  "properties": {
    "iso:country":"ES",
    "sg:address":"Calle de Belisana, 2",
    "sg:city":"Madrid",
    "sg:orig_category":"Iglesia Cat\u00d3lica",
    "sg:phone":"+34 913 88 61 37",
    "sg:postcode":"28043",
    "sg:province":"Madrid",
    "wof:name":"Parroquia Santa Maria De Cervellon",
    "wof:placetype":"venue"
},
  "geometry": {"coordinates":[-3.6575496197,40.4573707581],"type":"Point"}
}