{
  "type": "Feature",
  "properties": {
    "addr:full":"Calle de Subida Cuesta Piedra, 65 Santa Cruz De Tenerife Santa Cruz De Tenerife 38008",
    "addr:housenumber":"65",
    "addr:postcode":"38008",
    "addr:street":"Calle De Subida Cuesta Piedra",
    "iso:country":"ES",
    "sg:address":"Calle de Subida Cuesta Piedra, 65",
    "sg:city":"Santa Cruz De Tenerife",
    "sg:orig_category":"Asesor\u00cda, Estudio Y Control Medioambiental",
    "sg:phone":"+34 922 65 41 30",
    "sg:postcode":"38008",
    "sg:province":"Santa Cruz De Tenerife",
    "wof:name":"Gabinete De Proyectos Agroecologicos S.l.",
    "wof:placetype":"venue"
},
  "geometry": {"coordinates":[-16.2726783752,28.4713001251],"type":"Point"}
}