{
  "type": "Feature",
  "properties": {
    "iso:country":"ES",
    "sg:address":"Calle de Leon, 58",
    "sg:city":"Fuenlabrada",
    "sg:orig_category":"Materias Pl\u00c1sticas: Art\u00cdculos Para La Industria",
    "sg:phone":"+34 916 42 08 01",
    "sg:postcode":"28947",
    "sg:province":"Madrid",
    "sg:website":"www.plasgein.com",
    "wof:name":"Plasgein S. A.",
    "wof:placetype":"venue"
},
  "geometry": {"coordinates":[-3.7479979992,40.2589988708],"type":"Point"}
}