{
  "type": "Feature",
  "properties": {
    "iso:country":"ES",
    "sg:address":"Carrer de Manuel De Falla, 14",
    "sg:city":"Rubi",
    "sg:orig_category":"Cajas Y Embalajes De Cart\u00d3n Y Papel",
    "sg:phone":"+34 936 99 04 76",
    "sg:postcode":"08191",
    "sg:province":"Barcelona",
    "wof:name":"Cartonatges Riba S.l.",
    "wof:placetype":"venue"
},
  "geometry": {"coordinates":[2.0319609642,41.4731369019],"type":"Point"}
}