{
  "type": "Feature",
  "properties": {
    "iso:country":"ES",
    "sg:address":"Pase Castellana, 135",
    "sg:city":"Madrid",
    "sg:orig_category":"Arquitectos",
    "sg:phone":"+34 915 70 99 02",
    "sg:postcode":"28046",
    "sg:province":"Madrid",
    "wof:name":"Alten Espa\u00f1a Estudios Servicios Y Proyectos",
    "wof:placetype":"venue"
},
  "geometry": {"coordinates":[-3.6904275417,40.4595527649],"type":"Point"}
}