{
  "type": "Feature",
  "properties": {
    "iso:country":"ES",
    "sg:address":"Avda Corazon De Jesus, 26",
    "sg:city":"Vall D'uixo",
    "sg:orig_category":"Muebles, Minoristas",
    "sg:phone":"+34 964 69 61 56",
    "sg:postcode":"12600",
    "sg:province":"Castell\u00f3n",
    "wof:name":"Fenollosa Valls Maria Del Carmen",
    "wof:placetype":"venue"
},
  "geometry": {"coordinates":[-0.0482099988,39.992477417],"type":"Point"}
}