{
  "type": "Feature",
  "properties": {
    "addr:full":"Calle de Ernesto Sanz Y Sanz, 21 Quintanar Sierra Burgos 09670",
    "addr:housenumber":"21",
    "addr:postcode":"09670",
    "addr:street":"Calle De Ernesto Sanz Y Sanz",
    "iso:country":"ES",
    "sg:address":"Calle de Ernesto Sanz Y Sanz, 21",
    "sg:city":"Quintanar Sierra",
    "sg:orig_category":"Agencias Y Agentes Comerciales, Representantes",
    "sg:phone":"+34 947 39 57 29",
    "sg:postcode":"09670",
    "sg:province":"Burgos",
    "wof:name":"Pablo Pe\u00f1aranda Aquilino",
    "wof:placetype":"venue"
},
  "geometry": {"coordinates":[-3.0408570766,41.9812240601],"type":"Point"}
}