{
  "type": "Feature",
  "properties": {
    "iso:country":"ES",
    "sg:address":"Avda Gran Canaria (de), S/n",
    "sg:city":"Playa Del Ingles",
    "sg:orig_category":"Restaurantes",
    "sg:phone":"+34 928 76 97 33",
    "sg:postcode":"35100",
    "sg:province":"Las Palmas",
    "wof:name":"Zerpa Viera Santiago",
    "wof:placetype":"venue"
},
  "geometry": {"coordinates":[-15.567820549,27.7610931396],"type":"Point"}
}