{
  "type": "Feature",
  "properties": {
    "iso:country":"ES",
    "sg:address":"Calle de San Francisco, S/n",
    "sg:city":"Alba Tormes",
    "sg:orig_category":"Ense\u00d1anza Secundaria: Colegios Y Escuelas Privadas",
    "sg:phone":"+34 923 30 05 77",
    "sg:postcode":"37800",
    "sg:province":"Salamanca",
    "wof:name":"Instituto De Educacion Secundaria Leonardo Da Vinci",
    "wof:placetype":"venue"
},
  "geometry": {"coordinates":[-5.5111689568,40.8276901245],"type":"Point"}
}