{
  "type": "Feature",
  "properties": {
    "iso:country":"ES",
    "sg:address":"Calle de Acera Recoletos, 6",
    "sg:city":"Valladolid",
    "sg:orig_category":"Ingenier\u00cda, Centros De Estudios (diversos)",
    "sg:phone":"+34 983 30 08 91",
    "sg:postcode":"47004",
    "sg:province":"Valladolid",
    "wof:name":"Perez Gonzalez Angel",
    "wof:placetype":"venue"
},
  "geometry": {"coordinates":[-4.7284865379,41.6470413208],"type":"Point"}
}