{
  "type": "Feature",
  "properties": {
    "addr:full":"Baricentre (centre Comercial), Km. 0006,7 Barbera Valles Barcelona 08210",
    "addr:postcode":"08210",
    "addr:street":"Centre Comercial Km. 0006,7",
    "iso:country":"ES",
    "sg:address":"Baricentre (centre Comercial), Km. 0006,7",
    "sg:city":"Barbera Valles",
    "sg:orig_category":"Electrodom\u00c9sticos (al Por Menor)",
    "sg:phone":"+34 937 18 11 59",
    "sg:postcode":"08210",
    "sg:province":"Barcelona",
    "sg:website":"www.miro.es",
    "wof:name":"Establecimientos Miro S.l.",
    "wof:placetype":"venue"
},
  "geometry": {"coordinates":[2.1271760464,41.5150566101],"type":"Point"}
}