{
  "type": "Feature",
  "properties": {
    "iso:country":"ES",
    "sg:address":"Carrer de Sant Isidre (de), 97",
    "sg:city":"S. Carles Rapita",
    "sg:orig_category":"Promotores Constructores",
    "sg:phone":"+34 977 74 40 84",
    "sg:postcode":"43540",
    "sg:province":"Tarragona",
    "wof:name":"Cercle-pont Constructora S.l.",
    "wof:placetype":"venue"
},
  "geometry": {"coordinates":[0.5885040164,40.6164665222],"type":"Point"}
}