{
  "type": "Feature",
  "properties": {
    "addr:full":"C/ Sant Rafel, De, 7 S. Antoni Portmany Islas Baleares 07820",
    "addr:postcode":"07820",
    "addr:street":"C / Sant Rafel De 7 S. Antoni Portmany",
    "iso:country":"ES",
    "sg:address":"C/ Sant Rafel, De, 7",
    "sg:city":"S. Antoni Portmany",
    "sg:orig_category":"Zapatos (al Por Menor)",
    "sg:phone":"+34 971 34 41 56",
    "sg:postcode":"07820",
    "sg:province":"Islas Baleares",
    "wof:name":"Miro C.b.",
    "wof:placetype":"venue"
},
  "geometry": {"coordinates":[1.5188339949,39.1094055176],"type":"Point"}
}