{
  "type": "Feature",
  "properties": {
    "iso:country":"ES",
    "sg:address":"Ctra. Salamanca, Km. 0061,5",
    "sg:city":"Fresnedoso",
    "sg:orig_category":"Explotaci\u00d3n De Canteras",
    "sg:phone":"+34 923 41 36 64",
    "sg:postcode":"37775",
    "sg:province":"Salamanca",
    "wof:name":"Granitos Mateos S.l.",
    "wof:placetype":"venue"
},
  "geometry": {"coordinates":[-5.7097921371,40.4359016418],"type":"Point"}
}