{
  "type": "Feature",
  "properties": {
    "iso:country":"ES",
    "sg:address":"Avda Saladar Del, S/n",
    "sg:city":"Solana Matorral",
    "sg:orig_category":"Fabricaci\u00d3n De Juegos Y Juguetes",
    "sg:phone":"+34 928 16 61 66",
    "sg:postcode":"35625",
    "sg:province":"Las Palmas",
    "wof:name":"Automaticos Maxorata S.a.",
    "wof:placetype":"venue"
},
  "geometry": {"coordinates":[-14.3438739777,28.0489196777],"type":"Point"}
}