{
  "type": "Feature",
  "properties": {
    "iso:country":"ES",
    "sg:address":"Calle de Bergantin, 1",
    "sg:city":"Majadahonda",
    "sg:orig_category":"Maquinaria Para Industrias Diversas",
    "sg:phone":"+34 916 02 70 32",
    "sg:postcode":"28220",
    "sg:province":"Madrid",
    "wof:name":"Maquimadrid S.l.",
    "wof:placetype":"venue"
},
  "geometry": {"coordinates":[-3.8761572838,40.46251297],"type":"Point"}
}