{
  "type": "Feature",
  "properties": {
    "addr:full":"Calle de Juan Xxiii, 11 S. Nicolas Tolentino Las Palmas 35470",
    "addr:housenumber":"11",
    "addr:postcode":"35470",
    "addr:street":"Calle De Juan Xxiii;S. Nicolas Tolentino Las",
    "iso:country":"ES",
    "sg:address":"Calle de Juan Xxiii, 11",
    "sg:city":"S. Nicolas Tolentino",
    "sg:orig_category":"Motocicletas (agentes, Concesionarios)",
    "sg:phone":"+34 928 89 20 22",
    "sg:postcode":"35470",
    "sg:province":"Las Palmas",
    "wof:name":"Perez Perez Manuel De Los Angeles",
    "wof:placetype":"venue"
},
  "geometry": {"coordinates":[-15.7810029984,27.9816207886],"type":"Point"}
}