{
  "type": "Feature",
  "properties": {
    "iso:country":"ES",
    "sg:address":"Plaz Andalucia (de), 5",
    "sg:city":"Cordoba",
    "sg:orig_category":"Ense\u00d1anza Variada",
    "sg:phone":"+34 957 29 09 13",
    "sg:postcode":"14013",
    "sg:province":"C\u00f3rdoba",
    "sg:website":"www.azocor.com",
    "wof:name":"Academias De Formacion Cordobesa S.l.",
    "wof:placetype":"venue"
},
  "geometry": {"coordinates":[-4.7898731232,37.7753562927],"type":"Point"}
}