{
  "type": "Feature",
  "properties": {
    "iso:country":"ES",
    "sg:address":"Avda Maritima (san Marcial Rubicon), 30",
    "sg:city":"San Marcial De Rubicon",
    "sg:orig_category":"Promotores Constructores",
    "sg:phone":"+34 928 51 80 99",
    "sg:postcode":"35580",
    "sg:province":"Las Palmas",
    "sg:website":"www.agueri.com",
    "wof:name":"Explotaciones De Inversiones Agueri S.l.",
    "wof:placetype":"venue"
},
  "geometry": {"coordinates":[-13.8307790756,28.8657550812],"type":"Point"}
}