{
  "type": "Feature",
  "properties": {
    "addr:full":"Calle de Isabel La Catolica, 3 Campohermoso Almer\u00eda 04110",
    "addr:housenumber":"3",
    "addr:postcode":"04110",
    "addr:street":"Calle De Isabel La Catolica;Almeri\u0301A",
    "iso:country":"ES",
    "sg:address":"Calle de Isabel La Catolica, 3",
    "sg:city":"Campohermoso",
    "sg:orig_category":"Abogados",
    "sg:phone":"+34 950 38 64 30",
    "sg:postcode":"04110",
    "sg:province":"Almer\u00eda",
    "wof:name":"Lozano Y Alcala C.b.",
    "wof:placetype":"venue"
},
  "geometry": {"coordinates":[-2.1345140934,36.9384651184],"type":"Point"}
}