{
  "type": "Feature",
  "properties": {
    "addr:full":"Carrer de Esglesia, 355 Calella Barcelona 08370",
    "addr:housenumber":"355",
    "addr:postcode":"08370",
    "addr:street":"Carrer De Esglesia",
    "iso:country":"ES",
    "sg:address":"Carrer de Esglesia, 355",
    "sg:city":"Calella",
    "sg:orig_category":"Tintes (fabricaci\u00d3n, Al Por Mayor)",
    "sg:phone":"+34 937 69 37 55",
    "sg:postcode":"08370",
    "sg:province":"Barcelona",
    "wof:name":"La Sirenita S.c.p.",
    "wof:placetype":"venue"
},
  "geometry": {"coordinates":[2.6677401066,41.6166801453],"type":"Point"}
}