{
  "type": "Feature",
  "properties": {
    "addr:full":"Calle de Francisco Grandmontagne, 10 Burgos Burgos 09007",
    "addr:housenumber":"10",
    "addr:postcode":"09007",
    "addr:street":"Calle De Francisco Grandmontagne",
    "iso:country":"ES",
    "sg:address":"Calle de Francisco Grandmontagne, 10",
    "sg:city":"Burgos",
    "sg:orig_category":"Bazares, Art\u00cdculos De Limpieza Y De Cocina (al Por Menor)",
    "sg:phone":"+34 947 21 67 27",
    "sg:postcode":"09007",
    "sg:province":"Burgos",
    "wof:name":"Gomez Martinez Alejandro",
    "wof:placetype":"venue"
},
  "geometry": {"coordinates":[-3.6703064442,42.3513221741],"type":"Point"}
}