{
  "type": "Feature",
  "properties": {
    "iso:country":"ES",
    "sg:address":"Ctr Madrid-teruel, S/n",
    "sg:city":"Pobo Due\u00f1as",
    "sg:orig_category":"Distribuci\u00d3n De Petr\u00d3leo Y Derivados",
    "sg:phone":"+34 949 84 10 05",
    "sg:postcode":"19326",
    "sg:province":"Guadalajara",
    "sg:website":"www.cepsa.es",
    "wof:name":"Cedipsa Compa\u00d1ia Espa\u00d1ola Distribuidora De Petroleos S.a.",
    "wof:placetype":"venue"
},
  "geometry": {"coordinates":[-1.6494539976,40.7775688171],"type":"Point"}
}