{
  "type": "Feature",
  "properties": {
    "iso:country":"ES",
    "sg:address":"Carrer de Mila I Fontanals, 56",
    "sg:city":"Barcelona",
    "sg:orig_category":"Alimentaci\u00d3n General (al Por Menor)",
    "sg:phone":"+34 932 10 58 58",
    "sg:postcode":"08012",
    "sg:province":"Barcelona",
    "sg:website":"www.mjj786hotmail.com",
    "wof:name":"Jawad Jamil Muhammed",
    "wof:placetype":"venue"
},
  "geometry": {"coordinates":[2.1617100239,41.4018554688],"type":"Point"}
}