{
  "type": "Feature",
  "properties": {
    "addr:full":"Calle de Gacela, 20 Valdezorras Sevilla 41020",
    "addr:housenumber":"20",
    "addr:postcode":"41020",
    "addr:street":"Calle De Gacela",
    "iso:country":"ES",
    "sg:address":"Calle de Gacela, 20",
    "sg:city":"Valdezorras",
    "sg:orig_category":"Empresas De Desmonte",
    "sg:phone":"+34 954 52 24 98",
    "sg:postcode":"41020",
    "sg:province":"Sevilla",
    "wof:name":"Excavaciones Y Derribos Martin S.l.",
    "wof:placetype":"venue"
},
  "geometry": {"coordinates":[-5.9238481522,37.4302368164],"type":"Point"}
}