{
  "type": "Feature",
  "properties": {
    "iso:country":"ES",
    "sg:address":"Carr Salvador Albert I Pey, 1",
    "sg:city":"Palamos",
    "sg:orig_category":"Asociaciones Y Clubs Deportivos",
    "sg:phone":"+34 972 60 19 46",
    "sg:postcode":"17230",
    "sg:province":"Girona",
    "wof:name":"Fundacion Vilagran-maristany",
    "wof:placetype":"venue"
},
  "geometry": {"coordinates":[3.1307001114,41.8479614258],"type":"Point"}
}