{
  "type": "Feature",
  "properties": {
    "iso:country":"ES",
    "sg:address":"Calle de Flores, 5",
    "sg:city":"Zaragoza",
    "sg:orig_category":"Tapicer\u00cdas",
    "sg:phone":"+34 976 42 22 70",
    "sg:postcode":"50013",
    "sg:province":"Zaragoza",
    "wof:name":"Berne Gonzalvo Jesus Angel",
    "wof:placetype":"venue"
},
  "geometry": {"coordinates":[-0.8698800206,41.6400756836],"type":"Point"}
}