{
  "type": "Feature",
  "properties": {
    "iso:country":"ES",
    "sg:address":"Carrer de Sastres, Dels, S/n",
    "sg:city":"Olot",
    "sg:orig_category":"Lencer\u00cda Femenina, Corseter\u00cda, Trajes De Ba\u00d1o (al Por Menor)",
    "sg:phone":"+34 972 26 08 37",
    "sg:postcode":"17800",
    "sg:province":"Girona",
    "wof:name":"Girbau Sadurni Esteban",
    "wof:placetype":"venue"
},
  "geometry": {"coordinates":[2.4894649982,42.1831016541],"type":"Point"}
}