{
  "type": "Feature",
  "properties": {
    "iso:country":"ES",
    "sg:address":"Rivera De Molinos, S/n",
    "sg:city":"Priego Cordoba",
    "sg:orig_category":"Mec\u00c1nico Del Autom\u00d3vil",
    "sg:phone":"+34 957 70 06 63",
    "sg:postcode":"14800",
    "sg:province":"C\u00f3rdoba",
    "wof:name":"Talleres Bermudez C.b.",
    "wof:placetype":"venue"
},
  "geometry": {"coordinates":[-4.1937980652,37.4402656555],"type":"Point"}
}