{
  "type": "Feature",
  "properties": {
    "iso:country":"ES",
    "sg:address":"Lonja De Pescado, S/n",
    "sg:city":"Benicarlo",
    "sg:orig_category":"Transporte En General",
    "sg:phone":"+34 964 46 23 30",
    "sg:postcode":"12580",
    "sg:province":"Castell\u00f3n",
    "sg:website":"www.marinabenicarlo.com",
    "wof:name":"Marina Benicarlo S.a.",
    "wof:placetype":"venue"
},
  "geometry": {"coordinates":[0.4042100012,40.4457893372],"type":"Point"}
}