{
  "type": "Feature",
  "properties": {
    "addr:full":"Plg. Industrial De Manzanares, 188 Manzanares Ciudad Real 13200",
    "addr:housenumber":"188",
    "addr:postcode":"13200",
    "addr:street":"Manzanares",
    "iso:country":"ES",
    "sg:address":"Plg. Industrial De Manzanares, 188",
    "sg:city":"Manzanares",
    "sg:orig_category":"Complementos De Vestir (al Por Menor)",
    "sg:phone":"+34 926 62 02 76",
    "sg:postcode":"13200",
    "sg:province":"Ciudad Real",
    "wof:name":"Artesanos Camiseros Sa",
    "wof:placetype":"venue"
},
  "geometry": {"coordinates":[-3.3590445518,39.0437011719],"type":"Point"}
}