{
  "type": "Feature",
  "properties": {
    "addr:full":"Carrer de Freser, 9 Manlleu Barcelona 08560",
    "addr:housenumber":"9",
    "addr:postcode":"08560",
    "addr:street":"Carrer De Freser",
    "iso:country":"ES",
    "sg:address":"Carrer de Freser, 9",
    "sg:city":"Manlleu",
    "sg:orig_category":"Maquinaria Para Industrias Diversas",
    "sg:phone":"+34 938 51 04 32",
    "sg:postcode":"08560",
    "sg:province":"Barcelona",
    "wof:name":"Llop I Llop Germans S.l.",
    "wof:placetype":"venue"
},
  "geometry": {"coordinates":[2.2938969135,42.0107727051],"type":"Point"}
}