{
  "type": "Feature",
  "properties": {
    "addr:full":"Calle de Pintor Juan Gris, 2 Madrid Madrid 28020",
    "addr:housenumber":"2",
    "addr:postcode":"28020",
    "addr:street":"Calle De Pintor Juan Gris",
    "iso:country":"ES",
    "sg:address":"Calle de Pintor Juan Gris, 2",
    "sg:city":"Madrid",
    "sg:orig_category":"Alquiler De V\u00cddeo",
    "sg:phone":"+34 915 97 14 52",
    "sg:postcode":"28020",
    "sg:province":"Madrid",
    "wof:name":"Video Club Videomania S.l.",
    "wof:placetype":"venue"
},
  "geometry": {"coordinates":[-3.6909110546,40.4577445984],"type":"Point"}
}