{
  "type": "Feature",
  "properties": {
    "addr:full":"Ctra Frigiliana, Km. 0000,8 Nerja M\u00e1laga 29780",
    "addr:postcode":"29780",
    "addr:street":"Ctra Frigiliana Km. 0000,8",
    "iso:country":"ES",
    "sg:address":"Ctra Frigiliana, Km. 0000,8",
    "sg:city":"Nerja",
    "sg:orig_category":"Empresas De Carpinter\u00cda Met\u00c1lica",
    "sg:phone":"+34 952 52 10 98",
    "sg:postcode":"29780",
    "sg:province":"M\u00e1laga",
    "wof:name":"Herrero Cerezo Manuel",
    "wof:placetype":"venue"
},
  "geometry": {"coordinates":[-3.8762149811,36.751914978],"type":"Point"}
}