{
  "type": "Feature",
  "properties": {
    "addr:full":"Calle de Santa Eulalia, 20 Santurtzi Vizcaya 48980",
    "addr:housenumber":"20",
    "addr:postcode":"48980",
    "addr:street":"Calle De Santa Eulalia",
    "iso:country":"ES",
    "sg:address":"Calle de Santa Eulalia, 20",
    "sg:city":"Santurtzi",
    "sg:orig_category":"Molduras, Junquillos, Listones Y Molduras Perforadas",
    "sg:phone":"+34 944 62 21 17",
    "sg:postcode":"48980",
    "sg:province":"Vizcaya",
    "wof:name":"Mari Carmen Payo Fernandez (degustacion Mari Carmen)",
    "wof:placetype":"venue"
},
  "geometry": {"coordinates":[-3.0320980549,43.3260154724],"type":"Point"}
}