{
  "type": "Feature",
  "properties": {
    "iso:country":"ES",
    "sg:address":"Calle de San Mateo, 8",
    "sg:city":"Madrid",
    "sg:orig_category":"Procuradores",
    "sg:phone":"+34 915 22 79 06",
    "sg:postcode":"28004",
    "sg:province":"Madrid",
    "wof:name":"Lopez Lopez Manuel",
    "wof:placetype":"venue"
},
  "geometry": {"coordinates":[-3.6999719143,40.425239563],"type":"Point"}
}