{
  "type": "Feature",
  "properties": {
    "iso:country":"ES",
    "sg:address":"Calle de Sambara, 84",
    "sg:city":"Madrid",
    "sg:orig_category":"Albergues",
    "sg:phone":"+34 913 67 82 97",
    "sg:postcode":"28027",
    "sg:province":"Madrid",
    "wof:name":"Ramos Del Pino Jose Luis",
    "wof:placetype":"venue"
},
  "geometry": {"coordinates":[-3.6465818882,40.435634613],"type":"Point"}
}