{
  "type": "Feature",
  "properties": {
    "addr:full":"Calle de Pinta (la), 56 Mairena Aljarafe Sevilla 41927",
    "addr:housenumber":"56",
    "addr:postcode":"41927",
    "addr:street":"Calle De Pinta La",
    "iso:country":"ES",
    "sg:address":"Calle de Pinta (la), 56",
    "sg:city":"Mairena Aljarafe",
    "sg:orig_category":"Abogados",
    "sg:phone":"+34 955 60 05 57",
    "sg:postcode":"41927",
    "sg:province":"Sevilla",
    "wof:name":"Luna Fernandez Fernando Luis",
    "wof:placetype":"venue"
},
  "geometry": {"coordinates":[-6.0509138107,37.3516960144],"type":"Point"}
}