{
  "type": "Feature",
  "properties": {
    "iso:country":"ES",
    "sg:address":"Avda Menendez Y Pelayo, 1",
    "sg:city":"Valencia",
    "sg:orig_category":"Arquitectos",
    "sg:phone":"+34 963 69 69 19",
    "sg:postcode":"46010",
    "sg:province":"Valencia",
    "wof:name":"Ruiz Puchades Fernando Jose",
    "wof:placetype":"venue"
},
  "geometry": {"coordinates":[-0.3641830087,39.4804725647],"type":"Point"}
}