{
  "type": "Feature",
  "properties": {
    "addr:full":"Ctra. Montblanc-tarrega, S/n Solivella Tarragona 43412",
    "addr:housenumber":"s",
    "addr:postcode":"43412",
    "addr:street":"Ctra. Montblanc-Tarrega;/ N Solivella",
    "iso:country":"ES",
    "sg:address":"Ctra. Montblanc-tarrega, S/n",
    "sg:city":"Solivella",
    "sg:orig_category":"Centros De Educaci\u00d3n Especial",
    "sg:phone":"+34 977 89 23 61",
    "sg:postcode":"43412",
    "sg:province":"Tarragona",
    "wof:name":"Ajuntament De Solivella",
    "wof:placetype":"venue"
},
  "geometry": {"coordinates":[1.1833043098,41.4652099609],"type":"Point"}
}