{
  "type": "Feature",
  "properties": {
    "iso:country":"ES",
    "sg:address":"Calle de Maestro Mulet Borrell, 7",
    "sg:city":"Teulada",
    "sg:orig_category":"Bancos",
    "sg:phone":"+34 965 74 01 91",
    "sg:postcode":"03725",
    "sg:province":"Alicante",
    "wof:name":"Banco De Valencia S.a.",
    "wof:placetype":"venue"
},
  "geometry": {"coordinates":[0.1037809998,38.7287788391],"type":"Point"}
}