{
  "type": "Feature",
  "properties": {
    "iso:country":"ES",
    "sg:address":"Calle de Francisco Vitoria, 26",
    "sg:city":"Zaragoza",
    "sg:orig_category":"Asesor\u00cda Sobre Comunicaci\u00d3n De Empresas",
    "sg:phone":"+34 976 22 50 90",
    "sg:postcode":"50008",
    "sg:province":"Zaragoza",
    "wof:name":"Seyc S.l.",
    "wof:placetype":"venue"
},
  "geometry": {"coordinates":[-0.8793429732,41.6451377869],"type":"Point"}
}