{
  "type": "Feature",
  "properties": {
    "iso:country":"ES",
    "sg:address":"Calle de Zoa, 75",
    "sg:city":"Torrevieja",
    "sg:orig_category":"Caf\u00c9s, Bares, Cervecer\u00cdas",
    "sg:phone":"+34 965 70 87 11",
    "sg:postcode":"03180",
    "sg:province":"Alicante",
    "wof:name":"Romero Perez Francisco",
    "wof:placetype":"venue"
},
  "geometry": {"coordinates":[-0.6536790133,38.0173606873],"type":"Point"}
}