{
  "type": "Feature",
  "properties": {
    "iso:country":"ES",
    "sg:address":"Calle de Fernan Gonzalez, 28",
    "sg:city":"Madrid",
    "sg:orig_category":"M\u00c9dicos: Oftalmolog\u00cda",
    "sg:phone":"+34 915 75 59 40",
    "sg:postcode":"28009",
    "sg:province":"Madrid",
    "wof:name":"Cardenas Cardenas Angel",
    "wof:placetype":"venue"
},
  "geometry": {"coordinates":[-3.6745500565,40.4219436646],"type":"Point"}
}