{
  "type": "Feature",
  "properties": {
    "addr:full":"Avda Valencia, 30 Zaragoza Zaragoza 50005",
    "addr:housenumber":"30",
    "addr:postcode":"50005",
    "addr:street":"Avda Valencia",
    "iso:country":"ES",
    "sg:address":"Avda Valencia, 30",
    "sg:city":"Zaragoza",
    "sg:orig_category":"Agencias Y Agentes Comerciales, Representantes",
    "sg:phone":"+34 976 55 45 66",
    "sg:postcode":"50005",
    "sg:province":"Zaragoza",
    "wof:name":"Martinez Cuevas Jose Luis",
    "wof:placetype":"venue"
},
  "geometry": {"coordinates":[-0.8965190053,41.6466369629],"type":"Point"}
}