{
  "type": "Feature",
  "properties": {
    "addr:full":"Avda Reyes Catolicos, 12 Baza Granada 18800",
    "addr:housenumber":"12",
    "addr:postcode":"18800",
    "addr:street":"Avda Reyes Catolicos",
    "iso:country":"ES",
    "sg:address":"Avda Reyes Catolicos, 12",
    "sg:city":"Baza",
    "sg:orig_category":"Reposter\u00cdas",
    "sg:phone":"+34 958 71 21 84",
    "sg:postcode":"18800",
    "sg:province":"Granada",
    "wof:name":"Panaderia Hijos De Manuel Lopez Villegas Cb",
    "wof:placetype":"venue"
},
  "geometry": {"coordinates":[-2.7764968872,37.4920501709],"type":"Point"}
}