{
  "type": "Feature",
  "properties": {
    "iso:country":"ES",
    "sg:address":"Cmno Arroyo De Las Piedras, S/n",
    "sg:city":"Marbella",
    "sg:orig_category":"Promotores Constructores",
    "sg:phone":"+34 952 76 64 61",
    "sg:postcode":"29600",
    "sg:province":"M\u00e1laga",
    "sg:website":"www.dorica.es",
    "wof:name":"Dorica Empresa Constructora S.a.",
    "wof:placetype":"venue"
},
  "geometry": {"coordinates":[-4.8833007812,36.5079956055],"type":"Point"}
}