{
  "type": "Feature",
  "properties": {
    "iso:country":"ES",
    "sg:address":"Calle de Valdovi\u00d1o, 4",
    "sg:city":"Cedeira",
    "sg:orig_category":"Laboratorios Y Cl\u00cdnicas Veterinarias",
    "sg:phone":"+34 981 48 23 65",
    "sg:postcode":"15350",
    "sg:province":"A Coru\u00f1a",
    "wof:name":"Veterinario Cedeira, S.l.",
    "wof:placetype":"venue"
},
  "geometry": {"coordinates":[-8.052989006,43.6609916687],"type":"Point"}
}