{
  "type": "Feature",
  "properties": {
    "addr:full":"Av Rei Jaume I, 48 Benidorm Alicante 03500",
    "addr:housenumber":"48",
    "addr:postcode":"03500",
    "addr:street":"Av Rei Jaume I",
    "iso:country":"ES",
    "sg:address":"Av Rei Jaume I, 48",
    "sg:city":"Benidorm",
    "sg:orig_category":"Molduras, Junquillos, Listones Y Molduras Perforadas",
    "sg:phone":"+34 966 80 62 15",
    "sg:postcode":"03500",
    "sg:province":"Alicante",
    "wof:name":"Lopez Fernandez Jeronimo",
    "wof:placetype":"venue"
},
  "geometry": {"coordinates":[-0.1332969964,38.5419044495],"type":"Point"}
}