{
  "type": "Feature",
  "properties": {
    "addr:full":"Calle de Isidoro Salas, 46 Santo Domingo De La Calzada La Rioja 26250",
    "addr:housenumber":"46",
    "addr:postcode":"26250",
    "addr:street":"Calle De Isidoro Salas;Rioja",
    "iso:country":"ES",
    "sg:address":"Calle de Isidoro Salas, 46",
    "sg:city":"Santo Domingo De La Calzada",
    "sg:orig_category":"Ropa Para Beb\u00c9s Y Ni\u00d1os (confecci\u00d3n, Al Por Mayor)",
    "sg:phone":"+34 941 34 33 57",
    "sg:postcode":"26250",
    "sg:province":"La Rioja",
    "wof:name":"Maria Luisa Ureta Izurieta Y Otro Cdad",
    "wof:placetype":"venue"
},
  "geometry": {"coordinates":[-2.9540040493,42.4403457642],"type":"Point"}
}