{
  "type": "Feature",
  "properties": {
    "iso:country":"ES",
    "sg:address":"Calle de Primero De Mayo, 3",
    "sg:city":"Vegas",
    "sg:orig_category":"Mercer\u00cda, Lencer\u00cda (al Por Menor)",
    "sg:phone":"+34 985 57 44 03",
    "sg:postcode":"33404",
    "sg:province":"Asturias",
    "wof:name":"Alvarez Fernandez Maria Jesus",
    "wof:placetype":"venue"
},
  "geometry": {"coordinates":[-7.1471438408,43.4139633179],"type":"Point"}
}