{
  "type": "Feature",
  "properties": {
    "iso:country":"ES",
    "sg:address":"Calle de San Diego, 3",
    "sg:city":"Arjona",
    "sg:orig_category":"Promotores Constructores",
    "sg:phone":"+34 953 52 37 73",
    "sg:postcode":"23760",
    "sg:province":"Ja\u00e9n",
    "wof:name":"Construcciones Marin Barrera S.l.",
    "wof:placetype":"venue"
},
  "geometry": {"coordinates":[-4.0529141426,37.9357528687],"type":"Point"}
}