{
  "type": "Feature",
  "properties": {
    "addr:full":"Avda Nuestra Se\u00d1ora De Fatima, 59 Madrid Madrid 28047",
    "addr:housenumber":"59",
    "addr:postcode":"madrid;28047",
    "addr:street":"Avda Nuestra Sen\u0303Ora De Fatima",
    "iso:country":"ES",
    "sg:address":"Avda Nuestra Se\u00d1ora De Fatima, 59",
    "sg:city":"Madrid",
    "sg:orig_category":"Electrodom\u00c9sticos (fabricaci\u00d3n, Al Por Mayor)",
    "sg:phone":"+34 914 22 00 10",
    "sg:postcode":"28047",
    "sg:province":"Madrid",
    "wof:name":"Tv Casado S.l.",
    "wof:placetype":"venue"
},
  "geometry": {"coordinates":[-3.7471659184,40.3833961487],"type":"Point"}
}