{
  "type": "Feature",
  "properties": {
    "iso:country":"ES",
    "sg:address":"Carrer de Pineda, 3",
    "sg:city":"Mataro",
    "sg:orig_category":"Molduras, Junquillos, Listones Y Molduras Perforadas",
    "sg:phone":"+34 937 41 52 31",
    "sg:postcode":"08303",
    "sg:province":"Barcelona",
    "wof:name":"Gonzalez Martinez Angela",
    "wof:placetype":"venue"
},
  "geometry": {"coordinates":[2.42958498,41.5480270386],"type":"Point"}
}