{
  "type": "Feature",
  "properties": {
    "addr:full":"Calle de Solana, 5 Priego Cordoba C\u00f3rdoba 14800",
    "addr:housenumber":"5",
    "addr:postcode":"14800",
    "addr:street":"Calle De Solana;Cordoba Co\u0301Rdoba",
    "iso:country":"ES",
    "sg:address":"Calle de Solana, 5",
    "sg:city":"Priego Cordoba",
    "sg:orig_category":"Panader\u00cdas, Panader\u00cdas",
    "sg:phone":"+34 957 54 08 29",
    "sg:postcode":"14800",
    "sg:province":"C\u00f3rdoba",
    "wof:name":"Toro Cosano Rafael",
    "wof:placetype":"venue"
},
  "geometry": {"coordinates":[-4.1939787865,37.4388580322],"type":"Point"}
}