{
  "type": "Feature",
  "properties": {
    "addr:full":"Calle de San Gerardo, 17 Madrid Madrid 28035",
    "addr:housenumber":"17",
    "addr:postcode":"madrid;28035",
    "addr:street":"Calle De San Gerardo",
    "iso:country":"ES",
    "sg:address":"Calle de San Gerardo, 17",
    "sg:city":"Madrid",
    "sg:orig_category":"Administradores De Bienes Y Delegados De Comunidades De Propietarios",
    "sg:phone":"+34 913 16 56 15",
    "sg:postcode":"28035",
    "sg:province":"Madrid",
    "sg:website":"www.agisa.es",
    "wof:name":"Administracion General De Inmuebles S. A.",
    "wof:placetype":"venue"
},
  "geometry": {"coordinates":[-3.722026825,40.467830658],"type":"Point"}
}