{
  "type": "Feature",
  "properties": {
    "addr:full":"Calle de Mariana Pineda, 3 Alcorcon Madrid 28923",
    "addr:housenumber":"3",
    "addr:postcode":"28923",
    "addr:street":"Calle De Mariana Pineda",
    "iso:country":"ES",
    "sg:address":"Calle de Mariana Pineda, 3",
    "sg:city":"Alcorcon",
    "sg:orig_category":"Asociaciones Humanitarias, De Cooperaci\u00d3n, De Acci\u00d3n Social",
    "sg:phone":"+34 916 10 89 78",
    "sg:postcode":"28923",
    "sg:province":"Madrid",
    "wof:name":"Asociacion De Padres Y Amigos De Ni\u00f1os Subdotados De Alcorcon",
    "wof:placetype":"venue"
},
  "geometry": {"coordinates":[-3.8247990608,40.3522796631],"type":"Point"}
}