{
  "type": "Feature",
  "properties": {
    "addr:full":"Carrer de Margarit, 2 Barcelona Barcelona 08004",
    "addr:housenumber":"2",
    "addr:postcode":"08004",
    "addr:street":"Carrer De Margarit",
    "iso:country":"ES",
    "sg:address":"Carrer de Margarit, 2",
    "sg:city":"Barcelona",
    "sg:orig_category":"Herboristas (al Por Menor)",
    "sg:phone":"+34 934 41 99 55",
    "sg:postcode":"08004",
    "sg:province":"Barcelona",
    "wof:name":"Martinez Alvarez Eva",
    "wof:placetype":"venue"
},
  "geometry": {"coordinates":[2.1638350487,41.3748474121],"type":"Point"}
}