{
  "type": "Feature",
  "properties": {
    "addr:full":"Plaz Maestro Mateo, 2 Coru\u00d1a La Coru\u00f1a 15004",
    "addr:housenumber":"2",
    "addr:postcode":"15004",
    "addr:street":"Plaz Maestro Mateo;La Corun\u0303A",
    "iso:country":"ES",
    "sg:address":"Plaz Maestro Mateo, 2",
    "sg:city":"Coru\u00d1a",
    "sg:orig_category":"Asociaciones Humanitarias, De Cooperaci\u00d3n, De Acci\u00d3n Social",
    "sg:phone":"+34 981 14 27 40",
    "sg:postcode":"15004",
    "sg:province":"La Coru\u00f1a",
    "wof:name":"Asociacion Espa\u00f1ola Contra El Cancer",
    "wof:placetype":"venue"
},
  "geometry": {"coordinates":[-8.4115686417,43.3652801514],"type":"Point"}
}