{
  "type": "Feature",
  "properties": {
    "addr:full":"Avda Tres Cruces, 27 Zamora Zamora 49008",
    "addr:housenumber":"27",
    "addr:postcode":"49008",
    "addr:street":"Avda Tres Cruces",
    "iso:country":"ES",
    "sg:address":"Avda Tres Cruces, 27",
    "sg:city":"Zamora",
    "sg:orig_category":"Peluquer\u00cdas, Peluquer\u00cda Mixta",
    "sg:phone":"+34 980 67 23 88",
    "sg:postcode":"49008",
    "sg:province":"Zamora",
    "wof:name":"Hernandez Bragado Manuela",
    "wof:placetype":"venue"
},
  "geometry": {"coordinates":[-5.7410612106,41.5113067627],"type":"Point"}
}