{
  "type": "Feature",
  "properties": {
    "addr:full":"Avda Bonn, 15 Madrid Madrid 28028",
    "addr:housenumber":"15",
    "addr:postcode":"madrid;28028",
    "addr:street":"Avda Bonn",
    "iso:country":"ES",
    "sg:address":"Avda Bonn, 15",
    "sg:city":"Madrid",
    "sg:orig_category":"Asesor\u00cda Fiscal Y Jur\u00cddica",
    "sg:phone":"+34 917 25 18 51",
    "sg:postcode":"28028",
    "sg:province":"Madrid",
    "wof:name":"Gomez Calero Juana Maria",
    "wof:placetype":"venue"
},
  "geometry": {"coordinates":[-3.6633219719,40.4392280579],"type":"Point"}
}