{
  "type": "Feature",
  "properties": {
    "iso:country":"ES",
    "sg:address":"Coucieiro, 32",
    "sg:city":"Coucieiro",
    "sg:orig_category":"Ense\u00d1anza, Formaci\u00d3n Profesional: Aprendizaje",
    "sg:phone":"+34 988 49 44 30",
    "sg:postcode":"32229",
    "sg:province":"Ourense",
    "wof:name":"Ayuntamiento De Padrenda",
    "wof:placetype":"venue"
},
  "geometry": {"coordinates":[-8.180803299,42.1406288147],"type":"Point"}
}