{
  "type": "Feature",
  "properties": {
    "addr:full":"Avda San Gines, S/n S. Gines Murcia 30169",
    "addr:housenumber":"s",
    "addr:postcode":"30169",
    "addr:street":"Avda San Gines;/ N S.",
    "iso:country":"ES",
    "sg:address":"Avda San Gines, S/n",
    "sg:city":"S. Gines",
    "sg:orig_category":"Cajas Para Embalar",
    "sg:phone":"+34 968 37 98 01",
    "sg:postcode":"30169",
    "sg:province":"Murcia",
    "sg:website":"www.cajamar.es",
    "wof:name":"Cajamar",
    "wof:placetype":"venue"
},
  "geometry": {"coordinates":[-1.1753569841,37.9542694092],"type":"Point"}
}