{
  "type": "Feature",
  "properties": {
    "addr:full":"Calle de Ronda De Los Tejares, 13 Sevilla Sevilla 41010",
    "addr:housenumber":"13",
    "addr:postcode":"41010",
    "addr:street":"Calle De Ronda De Los Tejares",
    "iso:country":"ES",
    "sg:address":"Calle de Ronda De Los Tejares, 13",
    "sg:city":"Sevilla",
    "sg:orig_category":"Delegados, Agentes De Tr\u00c1nsito, Auxiliares De Transporte Internacional",
    "sg:phone":"+34 954 33 72 70",
    "sg:postcode":"41010",
    "sg:province":"Sevilla",
    "wof:name":"Transportes Rapidos Sevillanos S.l.",
    "wof:placetype":"venue"
},
  "geometry": {"coordinates":[-6.0134391785,37.3856697083],"type":"Point"}
}