{
  "type": "Feature",
  "properties": {
    "addr:full":"Calle de Pablo Parellada, 11 Zaragoza Zaragoza 50007",
    "addr:housenumber":"11",
    "addr:postcode":"50007",
    "addr:street":"Calle De Pablo Parellada",
    "iso:country":"ES",
    "sg:address":"Calle de Pablo Parellada, 11",
    "sg:city":"Zaragoza",
    "sg:orig_category":"Transporte En General",
    "sg:phone":"+34 976 27 66 03",
    "sg:postcode":"50007",
    "sg:province":"Zaragoza",
    "wof:name":"Terrin Moreno Francisca",
    "wof:placetype":"venue"
},
  "geometry": {"coordinates":[-0.8811519742,41.6276626587],"type":"Point"}
}