{
  "type": "Feature",
  "properties": {
    "iso:country":"ES",
    "sg:address":"La Nave, 6",
    "sg:city":"Estepona",
    "sg:orig_category":"Comercio, Reparaci\u00d3n De Motocicletas, Bicicletas Y Piezas Sueltas",
    "sg:phone":"+34 952 80 18 26",
    "sg:postcode":"29680",
    "sg:province":"M\u00e1laga",
    "wof:name":"Hermanos Infantes S.c.",
    "wof:placetype":"venue"
},
  "geometry": {"coordinates":[-5.1522197723,36.4200019836],"type":"Point"}
}