{
  "type": "Feature",
  "properties": {
    "addr:full":"Manuel De Falla(p Ind Saladas), 13 Torrellano Alicante 03320",
    "addr:housenumber":"13",
    "addr:postcode":"03320",
    "addr:street":"Manuel;Saladas",
    "iso:country":"ES",
    "sg:address":"Manuel De Falla(p Ind Saladas), 13",
    "sg:city":"Torrellano",
    "sg:orig_category":"Zapatos (al Por Mayor)",
    "sg:phone":"+34 965 68 12 65",
    "sg:postcode":"03320",
    "sg:province":"Alicante",
    "wof:name":"Micleta Difusion S.l.",
    "wof:placetype":"venue"
},
  "geometry": {"coordinates":[-0.5883839726,38.2929649353],"type":"Point"}
}