{
  "type": "Feature",
  "properties": {
    "iso:country":"ES",
    "sg:address":"Cust San Martin, 1",
    "sg:city":"Toledo",
    "sg:orig_category":"M\u00c9dicos: Radiolog\u00cda (radiodiagn\u00d3stico E Im\u00c1genes En Medicina)",
    "sg:phone":"+34 925 22 86 88",
    "sg:postcode":"45002",
    "sg:province":"Toledo",
    "wof:name":"Clinica Diagnostico Medico San Juan De Los Reyes S.l.",
    "wof:placetype":"venue"
},
  "geometry": {"coordinates":[-4.0320630074,39.8589439392],"type":"Point"}
}