{
  "type": "Feature",
  "properties": {
    "addr:full":"Calle de Padre Mariana, 1 Alacant Alicante 03004",
    "addr:housenumber":"1",
    "addr:postcode":"03004",
    "addr:street":"Calle De Padre Mariana",
    "iso:country":"ES",
    "sg:address":"Calle de Padre Mariana, 1",
    "sg:city":"Alacant",
    "sg:orig_category":"Peluquer\u00cdas, Peluquer\u00cda Mixta",
    "sg:phone":"+34 965 21 93 42",
    "sg:postcode":"03004",
    "sg:province":"Alicante",
    "wof:name":"Haro Romero Julia",
    "wof:placetype":"venue"
},
  "geometry": {"coordinates":[-0.4854309857,38.3511199951],"type":"Point"}
}