{
  "type": "Feature",
  "properties": {
    "iso:country":"ES",
    "sg:address":"Ctra Logro\u00d1o (de), Km. 0024,0",
    "sg:city":"Najera",
    "sg:orig_category":"Mec\u00c1nico Del Autom\u00d3vil",
    "sg:phone":"+34 941 36 32 87",
    "sg:postcode":"26300",
    "sg:province":"La Rioja",
    "wof:name":"Auto Soria De Najera S.l",
    "wof:placetype":"venue"
},
  "geometry": {"coordinates":[-2.7073256969,42.4131240845],"type":"Point"}
}