{
  "type": "Feature",
  "properties": {
    "iso:country":"ES",
    "sg:address":"Av Xativa (de), 27",
    "sg:city":"Cocentaina",
    "sg:orig_category":"Veh\u00cdculos De Ocasi\u00d3n",
    "sg:phone":"+34 965 59 21 76",
    "sg:postcode":"03820",
    "sg:province":"Alicante",
    "wof:name":"Auto-jorda S.l.",
    "wof:placetype":"venue"
},
  "geometry": {"coordinates":[-0.4391252995,38.7500457764],"type":"Point"}
}