{
  "type": "Feature",
  "properties": {
    "iso:country":"ES",
    "sg:address":"Plaz Azoguejo (del), 5",
    "sg:city":"Segovia",
    "sg:orig_category":"Cl\u00cdnicas Dentales",
    "sg:phone":"+34 921 42 84 08",
    "sg:postcode":"40001",
    "sg:province":"Segovia",
    "wof:name":"Montes Bautista Esther",
    "wof:placetype":"venue"
},
  "geometry": {"coordinates":[-4.1183261871,40.9482955933],"type":"Point"}
}