{
  "type": "Feature",
  "properties": {
    "iso:country":"ES",
    "sg:address":"Calle de Fuente, S/n",
    "sg:city":"Aldeadavila Ribera",
    "sg:orig_category":"Electricidad: Instaladores",
    "sg:phone":"+34 923 50 54 96",
    "sg:postcode":"37250",
    "sg:province":"Salamanca",
    "wof:name":"Hernandez Calvo Francisco",
    "wof:placetype":"venue"
},
  "geometry": {"coordinates":[-6.613114357,41.219417572],"type":"Point"}
}