{
  "type": "Feature",
  "properties": {
    "iso:country":"ES",
    "sg:address":"Calle de Naturalista Arevalo Baca, 3",
    "sg:city":"Valencia",
    "sg:orig_category":"Ingeniero",
    "sg:phone":"+34 963 60 46 43",
    "sg:postcode":"46010",
    "sg:province":"Valencia",
    "wof:name":"Roca Baixauli Francisco",
    "wof:placetype":"venue"
},
  "geometry": {"coordinates":[-0.3626640141,39.4742660522],"type":"Point"}
}