{
  "type": "Feature",
  "properties": {
    "addr:full":"Calle de Cervantes (de), 8 Mostoles Madrid 28932",
    "addr:postcode":"28932",
    "addr:street":"Calle De Cervantes De 8 Mostoles",
    "iso:country":"ES",
    "sg:address":"Calle de Cervantes (de), 8",
    "sg:city":"Mostoles",
    "sg:orig_category":"Cervecer\u00cdas",
    "sg:phone":"+34 916 17 72 87",
    "sg:postcode":"28932",
    "sg:province":"Madrid",
    "wof:name":"Iglesias Se\u00f1as Beatriz",
    "wof:placetype":"venue"
},
  "geometry": {"coordinates":[-3.859462738,40.3291282654],"type":"Point"}
}