{
  "type": "Feature",
  "properties": {
    "addr:full":"Psaj Meranges, 9 Badalona Barcelona 08915",
    "addr:housenumber":"9",
    "addr:postcode":"08915",
    "addr:street":"Meranges",
    "iso:country":"ES",
    "sg:address":"Psaj Meranges, 9",
    "sg:city":"Badalona",
    "sg:orig_category":"Alquiler De V\u00cddeo",
    "sg:phone":"+34 933 95 62 79",
    "sg:postcode":"08915",
    "sg:province":"Barcelona",
    "wof:name":"Silva Hortet David",
    "wof:placetype":"venue"
},
  "geometry": {"coordinates":[2.2402210236,41.4644622803],"type":"Point"}
}