{
  "type": "Feature",
  "properties": {
    "addr:full":"Plaz Colon, 8 Linares Ja\u00e9n 23700",
    "addr:housenumber":"8",
    "addr:postcode":"23700",
    "addr:street":"Colon;Jae\u0301N",
    "iso:country":"ES",
    "sg:address":"Plaz Colon, 8",
    "sg:city":"Linares",
    "sg:orig_category":"Caf\u00c9s, Bares, Cervecer\u00cdas",
    "sg:phone":"+34 953 65 26 94",
    "sg:postcode":"23700",
    "sg:province":"Ja\u00e9n",
    "wof:name":"Servencaf S.l.",
    "wof:placetype":"venue"
},
  "geometry": {"coordinates":[-3.6289970875,38.0940475464],"type":"Point"}
}