{
  "type": "Feature",
  "properties": {
    "iso:country":"ES",
    "sg:address":"Rua Illas Baleares, 24",
    "sg:city":"Vigo",
    "sg:orig_category":"Alimentaci\u00d3n General (al Por Menor)",
    "sg:phone":"+34 986 41 95 29",
    "sg:postcode":"36203",
    "sg:province":"Pontevedra",
    "wof:name":"Fernandez Dominguez Severo",
    "wof:placetype":"venue"
},
  "geometry": {"coordinates":[-8.7230405807,42.226524353],"type":"Point"}
}