{
  "type": "Feature",
  "properties": {
    "iso:country":"ES",
    "sg:address":"Calle de Coronel Valenzuela, 2",
    "sg:city":"Madrid",
    "sg:orig_category":"Inmobiliaria (agencias)",
    "sg:phone":"+34 915 65 12 09",
    "sg:postcode":"28019",
    "sg:province":"Madrid",
    "wof:name":"Blaucar Rent A Car S.a.",
    "wof:placetype":"venue"
},
  "geometry": {"coordinates":[-3.7094159126,40.3929328918],"type":"Point"}
}