{
  "type": "Feature",
  "properties": {
    "iso:country":"ES",
    "sg:address":"Calle de Dolores Marques, 50",
    "sg:city":"Valencia",
    "sg:orig_category":"Centros Comerciales Y Grandes Tiendas",
    "sg:phone":"+34 963 93 21 18",
    "sg:postcode":"46020",
    "sg:province":"Valencia",
    "wof:name":"Ba\u00d1on Y Valero S.l.",
    "wof:placetype":"venue"
},
  "geometry": {"coordinates":[-0.3611029983,39.4895935059],"type":"Point"}
}