{
  "type": "Feature",
  "properties": {
    "addr:full":"Pla\u00c7 Marques De Camps, 2 Girona Girona 17001",
    "addr:housenumber":"2",
    "addr:postcode":"17001",
    "addr:street":"Camps",
    "iso:country":"ES",
    "sg:address":"Pla\u00c7 Marques De Camps, 2",
    "sg:city":"Girona",
    "sg:orig_category":"Cajas De Ahorro",
    "sg:phone":"+34 972 20 97 67",
    "sg:postcode":"17001",
    "sg:province":"Girona",
    "sg:website":"www.ibercaja.es",
    "wof:name":"Caja De Ahorros Y Monte De Piedad De Zaragoza Aragon Y Rioja",
    "wof:placetype":"venue"
},
  "geometry": {"coordinates":[2.819480896,41.9826622009],"type":"Point"}
}