{
  "type": "Feature",
  "properties": {
    "addr:full":"Urbieta Kalea, 10 Hernani Guip\u00f9zcoa 20120",
    "addr:housenumber":"10",
    "addr:postcode":"20120",
    "addr:street":"Urbieta Kalea;Guipu\u0300Zcoa",
    "iso:country":"ES",
    "sg:address":"Urbieta Kalea, 10",
    "sg:city":"Hernani",
    "sg:orig_category":"Cajas De Ahorro",
    "sg:phone":"+34 943 55 18 50",
    "sg:postcode":"20120",
    "sg:province":"Guip\u00f9zcoa",
    "sg:website":"www.cajalaboral.es",
    "wof:name":"Caja Laboral Popular",
    "wof:placetype":"venue"
},
  "geometry": {"coordinates":[-1.9761350155,43.2672805786],"type":"Point"}
}