{
  "type": "Feature",
  "properties": {
    "addr:full":"Avda. Litoral, S/n Los Cristianos Santa Cruz De Tenerife 38650",
    "addr:housenumber":"s / n",
    "addr:postcode":"38650",
    "addr:street":"Avda. Litoral",
    "iso:country":"ES",
    "sg:address":"Avda. Litoral, S/n",
    "sg:city":"Los Cristianos",
    "sg:orig_category":"Inmobiliaria (agencias)",
    "sg:phone":"+34 922 78 82 78",
    "sg:postcode":"38650",
    "sg:province":"Santa Cruz De Tenerife",
    "wof:name":"Iversen  Frank Saaby",
    "wof:placetype":"venue"
},
  "geometry": {"coordinates":[-16.7228374481,28.0525436401],"type":"Point"}
}