{
  "type": "Feature",
  "properties": {
    "iso:country":"ES",
    "sg:address":"Cmno Suarez, 36",
    "sg:city":"Malaga",
    "sg:orig_category":"Chapister\u00cda",
    "sg:phone":"+34 952 61 07 45",
    "sg:postcode":"29011",
    "sg:province":"M\u00e1laga",
    "wof:name":"Jurado Ruiz Jose",
    "wof:placetype":"venue"
},
  "geometry": {"coordinates":[-4.4369821548,36.7274284363],"type":"Point"}
}