{
  "type": "Feature",
  "properties": {
    "addr:full":"Calle de Orense, 23 Madrid Madrid 28020",
    "addr:housenumber":"23",
    "addr:postcode":"madrid;28020",
    "addr:street":"Calle De Orense",
    "iso:country":"ES",
    "sg:address":"Calle de Orense, 23",
    "sg:city":"Madrid",
    "sg:orig_category":"Inmobiliaria (agencias)",
    "sg:phone":"+34 915 56 91 37",
    "sg:postcode":"28020",
    "sg:province":"Madrid",
    "wof:name":"Mediodia Desarrollo Inmobiliario",
    "wof:placetype":"venue"
},
  "geometry": {"coordinates":[-3.695305109,40.4510002136],"type":"Point"}
}