{
  "type": "Feature",
  "properties": {
    "iso:country":"ES",
    "sg:address":"Calle de Laguna Negra, 1",
    "sg:city":"Madrid",
    "sg:orig_category":"Frutas, Legumbres Frescas Y Tempranas (al Por Menor)",
    "sg:phone":"+34 917 73 25 50",
    "sg:postcode":"28030",
    "sg:province":"Madrid",
    "wof:name":"Nieto Gomez Alberto",
    "wof:placetype":"venue"
},
  "geometry": {"coordinates":[-3.6328821182,40.4046707153],"type":"Point"}
}