{
  "type": "Feature",
  "properties": {
    "addr:full":"Puzol, 35 Sagunt Valencia 46500",
    "addr:housenumber":"35",
    "addr:postcode":"46500",
    "addr:street":"Puzol",
    "iso:country":"ES",
    "sg:address":"Puzol, 35",
    "sg:city":"Sagunt",
    "sg:orig_category":"Frutas Y Legumbres Frescas (al Por Mayor)",
    "sg:phone":"+34 962 66 42 63",
    "sg:postcode":"46500",
    "sg:province":"Valencia",
    "wof:name":"Spain Fruit S.l.",
    "wof:placetype":"venue"
},
  "geometry": {"coordinates":[-0.2690379918,39.6778144836],"type":"Point"}
}