{
  "type": "Feature",
  "properties": {
    "iso:country":"ES",
    "sg:address":"Rua Esgos (de), 3",
    "sg:city":"Ourense",
    "sg:orig_category":"Transporte En General",
    "sg:phone":"+34 988 24 57 11",
    "sg:postcode":"32004",
    "sg:province":"Ourense",
    "wof:name":"Distribuciones Pimba S.l.",
    "wof:placetype":"venue"
},
  "geometry": {"coordinates":[-7.8551797867,42.3393096924],"type":"Point"}
}