{
  "type": "Feature",
  "properties": {
    "iso:country":"ES",
    "sg:address":"Calle de Burgos (de), 27",
    "sg:city":"Alcobendas",
    "sg:orig_category":"Agencias Y Agentes Comerciales, Representantes",
    "sg:phone":"+34 916 52 53 72",
    "sg:postcode":"28100",
    "sg:province":"Madrid",
    "wof:name":"Helguecom S.l.",
    "wof:placetype":"venue"
},
  "geometry": {"coordinates":[-3.6433763504,40.5515823364],"type":"Point"}
}