{
  "type": "Feature",
  "properties": {
    "addr:full":"Santa Agueda, 1 Santa Agueda Asturias 33171",
    "addr:housenumber":"1",
    "addr:postcode":"33171",
    "addr:street":"Agueda",
    "iso:country":"ES",
    "sg:address":"Santa Agueda, 1",
    "sg:city":"Santa Agueda",
    "sg:orig_category":"Asesor\u00cda, Estudio Y Control Medioambiental",
    "sg:phone":"+34 985 79 65 16",
    "sg:postcode":"33171",
    "sg:province":"Asturias",
    "wof:name":"Gabinete De Estudios Ambientales S.cv.",
    "wof:placetype":"venue"
},
  "geometry": {"coordinates":[-5.9610209465,43.3634529114],"type":"Point"}
}