{
  "type": "Feature",
  "properties": {
    "iso:country":"ES",
    "sg:address":"Ctra. Jaen, Km. 0006,0",
    "sg:city":"Albacete",
    "sg:orig_category":"Delegados, Agentes De Tr\u00c1nsito, Auxiliares De Transporte Internacional",
    "sg:phone":"+34 967 24 27 12",
    "sg:postcode":"02006",
    "sg:province":"Albacete",
    "wof:name":"Transportes Transcamancha S.l.",
    "wof:placetype":"venue"
},
  "geometry": {"coordinates":[-2.044303894,39.0605888367],"type":"Point"}
}