{
  "type": "Feature",
  "properties": {
    "iso:country":"ES",
    "sg:address":"Calle de La Chulapona, 1",
    "sg:city":"Madrid",
    "sg:orig_category":"\u00d3ptica: Instrumentos (fabricaci\u00d3n)",
    "sg:phone":"+34 913 17 73 70",
    "sg:postcode":"28041",
    "sg:province":"Madrid",
    "wof:name":"Ferrero Diaz Carmen",
    "wof:placetype":"venue"
},
  "geometry": {"coordinates":[-3.6963880062,40.3600006104],"type":"Point"}
}