{
  "type": "Feature",
  "properties": {
    "iso:country":"ES",
    "sg:address":"Calle de Lugo, 9",
    "sg:city":"Tomelloso",
    "sg:orig_category":"Asociaciones Humanitarias, De Cooperaci\u00d3n, De Acci\u00d3n Social",
    "sg:phone":"+34 926 51 21 20",
    "sg:postcode":"13700",
    "sg:province":"Ciudad Real",
    "wof:name":"Asociacion De Familiares Y Amigos De Personas Con Discapacidad",
    "wof:placetype":"venue"
},
  "geometry": {"coordinates":[-3.0173978806,39.1460266113],"type":"Point"}
}