{
  "type": "Feature",
  "properties": {
    "addr:full":"Calle de Domingo Ram, 19 Zaragoza Zaragoza 50017",
    "addr:housenumber":"19",
    "addr:postcode":"50017",
    "addr:street":"Calle De Domingo Ram",
    "iso:country":"ES",
    "sg:address":"Calle de Domingo Ram, 19",
    "sg:city":"Zaragoza",
    "sg:orig_category":"M\u00c9dicos: Estomatolog\u00cda",
    "sg:phone":"+34 976 53 83 37",
    "sg:postcode":"50017",
    "sg:province":"Zaragoza",
    "wof:name":"Garcia Cros Luis",
    "wof:placetype":"venue"
},
  "geometry": {"coordinates":[-0.9038162827,41.6486663818],"type":"Point"}
}