{
  "type": "Feature",
  "properties": {
    "addr:full":"Naon, 26 Viella Asturias 33429",
    "addr:housenumber":"26",
    "addr:postcode":"33429",
    "addr:street":"Naon",
    "iso:country":"ES",
    "sg:address":"Naon, 26",
    "sg:city":"Viella",
    "sg:orig_category":"Maquinaria Para Industrias Diversas",
    "sg:phone":"+34 985 26 57 79",
    "sg:postcode":"33429",
    "sg:province":"Asturias",
    "wof:name":"Talleres A.d.f.rural S.l.",
    "wof:placetype":"venue"
},
  "geometry": {"coordinates":[-5.7704091072,43.3952407837],"type":"Point"}
}