{
  "type": "Feature",
  "properties": {
    "addr:full":"Calle de Pintor Manuel Maldonado, 9 Granada Granada 18007",
    "addr:housenumber":"9",
    "addr:postcode":"18007",
    "addr:street":"Calle De Pintor Manuel Maldonado",
    "iso:country":"ES",
    "sg:address":"Calle de Pintor Manuel Maldonado, 9",
    "sg:city":"Granada",
    "sg:orig_category":"Peluqueros: De Se\u00d1oras",
    "sg:phone":"+34 958 81 90 08",
    "sg:postcode":"18007",
    "sg:province":"Granada",
    "wof:name":"Martin Cuevas Antonio",
    "wof:placetype":"venue"
},
  "geometry": {"coordinates":[-3.5963089466,37.157283783],"type":"Point"}
}