{
  "type": "Feature",
  "properties": {
    "iso:country":"ES",
    "sg:address":"Plaz Espa\u00d1a, 8",
    "sg:city":"Padul",
    "sg:orig_category":"Alquiler De V\u00cddeo",
    "sg:phone":"+34 958 77 30 66",
    "sg:postcode":"18640",
    "sg:province":"Granada",
    "wof:name":"Delgado Marquez Maria Dolores",
    "wof:placetype":"venue"
},
  "geometry": {"coordinates":[-3.6279389858,37.0232009888],"type":"Point"}
}