{
  "type": "Feature",
  "properties": {
    "iso:country":"ES",
    "sg:address":"Calle de Pedro Antonio Menendez, 1",
    "sg:city":"Oviedo",
    "sg:orig_category":"Ense\u00d1anza: Profesiones Art\u00cdsticas",
    "sg:phone":"+34 985 27 37 74",
    "sg:postcode":"33004",
    "sg:province":"Asturias",
    "wof:name":"Ros Wagener Enrique",
    "wof:placetype":"venue"
},
  "geometry": {"coordinates":[-5.8552131653,43.3634033203],"type":"Point"}
}