{
  "type": "Feature",
  "properties": {
    "addr:full":"Avda Doctor Federico Rubio Y Gali, 55 Madrid Madrid 28040",
    "addr:housenumber":"55",
    "addr:postcode":"madrid;28040",
    "addr:street":"Avda Doctor Federico Rubio Y Gali",
    "iso:country":"ES",
    "sg:address":"Avda Doctor Federico Rubio Y Gali, 55",
    "sg:city":"Madrid",
    "sg:classifiers":[
        {
            "category":"Government",
            "subcategory":"Office",
            "type":"Public Place"
        }
    ],
    "sg:phone":"+34 914 59 63 97",
    "sg:postcode":"28040",
    "sg:province":"Madrid",
    "sg:tags":[
        "interior",
        "administraci\u00d3n",
        "en"
    ],
    "wof:name":"Direccion General De La Policia",
    "wof:placetype":"venue"
},
  "geometry": {"coordinates":[-3.7119300365,40.4523582458],"type":"Point"}
}