{
  "type": "Feature",
  "properties": {
    "iso:country":"ES",
    "sg:address":"Av Marina Baixa, 3",
    "sg:city":"Cala",
    "sg:orig_category":"Marroquiner\u00cda (confecci\u00d3n)",
    "sg:phone":"+34 966 80 77 37",
    "sg:postcode":"03509",
    "sg:province":"Alicante",
    "wof:name":"R'himni  Ahmed",
    "wof:placetype":"venue"
},
  "geometry": {"coordinates":[-0.1924789995,38.5512695312],"type":"Point"}
}