{
  "type": "Feature",
  "properties": {
    "iso:country":"ES",
    "sg:address":"Carretera De Maella, Km. 0028,2",
    "sg:city":"Caspe",
    "sg:orig_category":"Producci\u00d3n, Comercio De Cereales",
    "sg:phone":"+34 976 63 09 28",
    "sg:postcode":"50700",
    "sg:province":"Zaragoza",
    "wof:name":"Larrosa Tello Cesareo",
    "wof:placetype":"venue"
},
  "geometry": {"coordinates":[-0.0443990007,41.2355766296],"type":"Point"}
}