{
  "type": "Feature",
  "properties": {
    "iso:country":"ES",
    "sg:address":"Calle de Obispo Fonseca, 27",
    "sg:city":"Palencia",
    "sg:orig_category":"Transporte En General",
    "sg:phone":"+34 979 71 14 82",
    "sg:postcode":"34004",
    "sg:province":"Palencia",
    "wof:name":"Curieses Moro Ascension",
    "wof:placetype":"venue"
},
  "geometry": {"coordinates":[-4.529979229,41.9985313416],"type":"Point"}
}