{
  "type": "Feature",
  "properties": {
    "addr:full":"Carrer de Rafael De Casanova, 12 Molins Rei Barcelona 08750",
    "addr:housenumber":"12",
    "addr:postcode":"08750",
    "addr:street":"Carrer De Rafael De Casanova;Barcelona",
    "iso:country":"ES",
    "sg:address":"Carrer de Rafael De Casanova, 12",
    "sg:city":"Molins Rei",
    "sg:orig_category":"Fabricaci\u00d3n, Importaci\u00d3n De L\u00c1mparas Y Bombillas",
    "sg:phone":"+34 936 68 59 55",
    "sg:postcode":"08750",
    "sg:province":"Barcelona",
    "wof:name":"Ribe Iglesias Juan",
    "wof:placetype":"venue"
},
  "geometry": {"coordinates":[2.0185270309,41.4111213684],"type":"Point"}
}