{
  "type": "Feature",
  "properties": {
    "addr:full":"Fermin Calbeton Kalea, 16 Eibar Guip\u00f9zcoa 20600",
    "addr:housenumber":"16",
    "addr:postcode":"20600",
    "addr:street":"Fermin Calbeton Kalea;Guipu\u0300Zcoa",
    "iso:country":"ES",
    "sg:address":"Fermin Calbeton Kalea, 16",
    "sg:city":"Eibar",
    "sg:orig_category":"Ropa Para Se\u00d1oras Y Caballeros (al Por Menor)",
    "sg:phone":"+34 943 20 80 06",
    "sg:postcode":"20600",
    "sg:province":"Guip\u00f9zcoa",
    "wof:name":"Roca Gonzalez Antonio",
    "wof:placetype":"venue"
},
  "geometry": {"coordinates":[-2.4725339413,43.1840133667],"type":"Point"}
}