{
  "type": "Feature",
  "properties": {
    "addr:full":"Calle de General Alvarez De Castro, 37 Madrid Madrid 28010",
    "addr:housenumber":"37",
    "addr:postcode":"madrid;28010",
    "addr:street":"Calle De General Alvarez De Castro",
    "iso:country":"ES",
    "sg:address":"Calle de General Alvarez De Castro, 37",
    "sg:city":"Madrid",
    "sg:orig_category":"Empresas De Limpieza",
    "sg:phone":"+34 914 46 32 50",
    "sg:postcode":"28010",
    "sg:province":"Madrid",
    "wof:name":"Central De Servicios Auxiliares S.a.",
    "wof:placetype":"venue"
},
  "geometry": {"coordinates":[-3.702862978,40.4377250671],"type":"Point"}
}