{
  "type": "Feature",
  "properties": {
    "addr:full":"Calle de Buenavista, 16 Massamagrell Valencia 46130",
    "addr:housenumber":"16",
    "addr:postcode":"46130",
    "addr:street":"Calle De Buenavista",
    "iso:country":"ES",
    "sg:address":"Calle de Buenavista, 16",
    "sg:city":"Massamagrell",
    "sg:orig_category":"Farmacias",
    "sg:phone":"+34 961 44 05 33",
    "sg:postcode":"46130",
    "sg:province":"Valencia",
    "wof:name":"Gil Tomas Maria",
    "wof:placetype":"venue"
},
  "geometry": {"coordinates":[-0.3437786102,39.5799713135],"type":"Point"}
}