{
  "type": "Feature",
  "properties": {
    "iso:country":"ES",
    "sg:address":"Zubiaurre, 12",
    "sg:city":"Ermua",
    "sg:orig_category":"Panader\u00cdas, Panader\u00cdas",
    "sg:phone":"+34 943 03 02 76",
    "sg:postcode":"48260",
    "sg:province":"Vizcaya",
    "wof:name":"Maria Aranzazu Castillo Arriola ( Panaderia )",
    "wof:placetype":"venue"
},
  "geometry": {"coordinates":[-2.503029108,43.1874046326],"type":"Point"}
}