{
  "type": "Feature",
  "properties": {
    "iso:country":"ES",
    "sg:address":"Psaj Tenesor, 50",
    "sg:city":"Llano Blanco",
    "sg:orig_category":"Geolog\u00cda Y Geof\u00cdsica",
    "sg:phone":"+34 928 63 39 63",
    "sg:postcode":"35413",
    "sg:province":"Las Palmas",
    "wof:name":"Morales Matos Guillermo",
    "wof:placetype":"venue"
},
  "geometry": {"coordinates":[-15.5489606857,28.1460952759],"type":"Point"}
}