{
  "type": "Feature",
  "properties": {
    "addr:full":"Calle de Ponce De Leon, 4 Madrid Madrid 28010",
    "addr:housenumber":"4",
    "addr:postcode":"28010",
    "addr:street":"Calle De Ponce De Leon",
    "iso:country":"ES",
    "sg:address":"Calle de Ponce De Leon, 4",
    "sg:city":"Madrid",
    "sg:orig_category":"Centros Empresariales",
    "sg:phone":"+34 915 91 38 07",
    "sg:postcode":"28010",
    "sg:province":"Madrid",
    "wof:name":"Comercializadora San Francisco S.l.",
    "wof:placetype":"venue"
},
  "geometry": {"coordinates":[-3.6987819672,40.435962677],"type":"Point"}
}