{
  "type": "Feature",
  "properties": {
    "iso:country":"ES",
    "sg:address":"Avda Valdelaparra (de), 57",
    "sg:city":"Alcobendas",
    "sg:orig_category":"Bancos",
    "sg:phone":"+34 916 61 59 70",
    "sg:postcode":"28108",
    "sg:province":"Madrid",
    "sg:website":"www.bancopopular.es",
    "wof:name":"Banco Popular Espa\u00f1ol",
    "wof:placetype":"venue"
},
  "geometry": {"coordinates":[-3.6519789696,40.5396118164],"type":"Point"}
}