{
  "type": "Feature",
  "properties": {
    "iso:country":"ES",
    "sg:address":"Avda Doctor Martinez Pardo - Teixeiro, 21",
    "sg:city":"Teijeiro",
    "sg:orig_category":"Electrodom\u00c9sticos (al Por Menor)",
    "sg:phone":"+34 981 78 95 00",
    "sg:postcode":"15310",
    "sg:province":"La Coru\u00f1a",
    "wof:name":"Ramos Gacio Jesus",
    "wof:placetype":"venue"
},
  "geometry": {"coordinates":[-8.1450586319,43.1260108948],"type":"Point"}
}