{
  "type": "Feature",
  "properties": {
    "addr:full":"Carrer de Pompeu Fabra, 15 Granollers Barcelona 08401",
    "addr:housenumber":"15",
    "addr:postcode":"08401",
    "addr:street":"Carrer De Pompeu Fabra",
    "iso:country":"ES",
    "sg:address":"Carrer de Pompeu Fabra, 15",
    "sg:city":"Granollers",
    "sg:orig_category":"Copas, Insignias, Trofeos",
    "sg:phone":"+34 938 70 55 28",
    "sg:postcode":"08401",
    "sg:province":"Barcelona",
    "wof:name":"Girabal Tresserres Pedro",
    "wof:placetype":"venue"
},
  "geometry": {"coordinates":[2.2841660976,41.6093254089],"type":"Point"}
}