{
  "type": "Feature",
  "properties": {
    "addr:full":"Calle de Pla Y Cancela, 37 Coru\u00d1a La Coru\u00f1a 15005",
    "addr:housenumber":"37",
    "addr:postcode":"15005",
    "addr:street":"Calle De Pla Y Cancela;Corun\u0303A",
    "iso:country":"ES",
    "sg:address":"Calle de Pla Y Cancela, 37",
    "sg:city":"Coru\u00d1a",
    "sg:orig_category":"Agentes Generales De Seguros",
    "sg:phone":"+34 981 24 33 62",
    "sg:postcode":"15005",
    "sg:province":"La Coru\u00f1a",
    "wof:name":"Briones Varela Jose Ramon",
    "wof:placetype":"venue"
},
  "geometry": {"coordinates":[-8.4100046158,43.3600273132],"type":"Point"}
}