{
  "type": "Feature",
  "properties": {
    "iso:country":"ES",
    "sg:address":"Calle de Vitoria, 23",
    "sg:city":"Burgos",
    "sg:orig_category":"Agencias Y Asesores De Publicidad",
    "sg:phone":"+34 947 27 25 25",
    "sg:postcode":"09004",
    "sg:province":"Burgos",
    "sg:website":"www.o2studio.net",
    "wof:name":"Oxshock Dll",
    "wof:placetype":"venue"
},
  "geometry": {"coordinates":[-3.6962850094,42.3416290283],"type":"Point"}
}