{
  "type": "Feature",
  "properties": {
    "iso:country":"ES",
    "sg:address":"Calle de Maria Fernandez Carmona 'mariquita', 2",
    "sg:city":"Cordoba",
    "sg:orig_category":"Venta, Instalaci\u00d3n De Calefacci\u00d3n",
    "sg:phone":"+34 957 47 60 03",
    "sg:postcode":"14001",
    "sg:province":"C\u00f3rdoba",
    "wof:name":"Hijos Rafael Belmonte S.l.",
    "wof:placetype":"venue"
},
  "geometry": {"coordinates":[-4.7752299309,37.8905792236],"type":"Point"}
}