{
  "type": "Feature",
  "properties": {
    "addr:full":"Trav Corts, 78 Barcelona Barcelona 08028",
    "addr:housenumber":"78",
    "addr:postcode":"08028",
    "addr:street":"Trav Corts",
    "iso:country":"ES",
    "sg:address":"Trav Corts, 78",
    "sg:city":"Barcelona",
    "sg:orig_category":"Muebles",
    "sg:phone":"+34 934 48 55 81",
    "sg:postcode":"08028",
    "sg:province":"Barcelona",
    "wof:name":"Proyecto Colonial S. L.",
    "wof:placetype":"venue"
},
  "geometry": {"coordinates":[2.1230010986,41.3788261414],"type":"Point"}
}