{
  "type": "Feature",
  "properties": {
    "iso:country":"ES",
    "sg:address":"Avda Bucaramanga, 2",
    "sg:city":"Madrid",
    "sg:orig_category":"Carnicer\u00cdas, Carnicer\u00cdas",
    "sg:phone":"+34 913 81 25 34",
    "sg:postcode":"28033",
    "sg:province":"Madrid",
    "wof:name":"Serrano Calvo Marcelino",
    "wof:placetype":"venue"
},
  "geometry": {"coordinates":[-3.6358850002,40.4720916748],"type":"Point"}
}