{
  "type": "Feature",
  "properties": {
    "addr:full":"Calle de Villajimena, 18 Madrid Madrid 28032",
    "addr:housenumber":"18",
    "addr:postcode":"madrid;28032",
    "addr:street":"Calle De Villajimena",
    "iso:country":"ES",
    "sg:address":"Calle de Villajimena, 18",
    "sg:city":"Madrid",
    "sg:orig_category":"Muebles, Minoristas",
    "sg:phone":"+34 917 75 39 07",
    "sg:postcode":"28032",
    "sg:province":"Madrid",
    "wof:name":"Asociacion Betel",
    "wof:placetype":"venue"
},
  "geometry": {"coordinates":[-3.6064510345,40.4069290161],"type":"Point"}
}