{
  "type": "Feature",
  "properties": {
    "addr:full":"Avda Menendez Pelayo, 67 Madrid Madrid 28009",
    "addr:housenumber":"67",
    "addr:postcode":"madrid;28009",
    "addr:street":"Avda Menendez Pelayo",
    "iso:country":"ES",
    "sg:address":"Avda Menendez Pelayo, 67",
    "sg:city":"Madrid",
    "sg:orig_category":"Laboratorios Farmac\u00c9uticos",
    "sg:phone":"+34 915 73 35 59",
    "sg:postcode":"28009",
    "sg:province":"Madrid",
    "sg:website":"www.lacer.es",
    "wof:name":"Lacer S.a.",
    "wof:placetype":"venue"
},
  "geometry": {"coordinates":[-3.6764230728,40.4122047424],"type":"Point"}
}