{
  "type": "Feature",
  "properties": {
    "iso:country":"ES",
    "sg:address":"Calle de Triana, 104",
    "sg:city":"Palmas De Gran Canaria",
    "sg:orig_category":"Arboricultura Y Producci\u00d3n De Frutas",
    "sg:phone":"+34 928 36 96 90",
    "sg:postcode":"35002",
    "sg:province":"Las Palmas",
    "wof:name":"Alvarez Sanchez Camilo",
    "wof:placetype":"venue"
},
  "geometry": {"coordinates":[-15.4162359238,28.1058540344],"type":"Point"}
}