{
  "type": "Feature",
  "properties": {
    "iso:country":"ES",
    "sg:address":"R. Bel, 12",
    "sg:city":"Atarrabia",
    "sg:orig_category":"Reparaci\u00d3n Y Restauraci\u00d3n De Objetos Diversos",
    "sg:phone":"+34 948 14 11 62",
    "sg:postcode":"31610",
    "sg:province":"Navarra",
    "wof:name":"Ortega Navarcorena Carlos",
    "wof:placetype":"venue"
},
  "geometry": {"coordinates":[-1.6093089581,42.8322181702],"type":"Point"}
}