{
  "type": "Feature",
  "properties": {
    "addr:full":"Pl Urquinaona, 9 Barcelona Barcelona 08010",
    "addr:housenumber":"9",
    "addr:postcode":"08010",
    "addr:street":"Pl Urquinaona",
    "iso:country":"ES",
    "sg:address":"Pl Urquinaona, 9",
    "sg:city":"Barcelona",
    "sg:orig_category":"Teatros Y Salas De Espect\u00c1culos",
    "sg:phone":"+34 933 01 19 68",
    "sg:postcode":"08010",
    "sg:province":"Barcelona",
    "sg:website":"www.serviticket.com",
    "wof:name":"Cine Teatro Borras S.a.",
    "wof:placetype":"venue"
},
  "geometry": {"coordinates":[2.1735050678,41.3888893127],"type":"Point"}
}