{
  "type": "Feature",
  "properties": {
    "addr:full":"Ctra. Del Viso, Km. 0016,5 Cedillo Condado Toledo 45214",
    "addr:postcode":"45214",
    "addr:street":"Ctra. Del Viso Km. 0016,5",
    "iso:country":"ES",
    "sg:address":"Ctra. Del Viso, Km. 0016,5",
    "sg:city":"Cedillo Condado",
    "sg:orig_category":"Agricultores, Agricultores",
    "sg:phone":"+34 925 50 85 22",
    "sg:postcode":"45214",
    "sg:province":"Toledo",
    "wof:name":"Ganados Fontelo S.l.",
    "wof:placetype":"venue"
},
  "geometry": {"coordinates":[-3.9259839058,40.1141433716],"type":"Point"}
}