{
  "type": "Feature",
  "properties": {
    "addr:full":"Gonzalez Tablas, 5 Iru\u00f1a Navarra 31003",
    "addr:housenumber":"5",
    "addr:postcode":"31003",
    "addr:street":"Tablas",
    "iso:country":"ES",
    "sg:address":"Gonzalez Tablas, 5",
    "sg:city":"Iru\u00f1a",
    "sg:orig_category":"Centros Empresariales",
    "sg:phone":"+34 948 23 58 43",
    "sg:postcode":"31003",
    "sg:province":"Navarra",
    "wof:name":"Grocin Gabas Carlos",
    "wof:placetype":"venue"
},
  "geometry": {"coordinates":[-1.6371619701,42.80909729],"type":"Point"}
}