{
  "type": "Feature",
  "properties": {
    "addr:full":"Plaz Bilbao De, 1 Donostia-san Sebastian Guip\u00f9zcoa 20005",
    "addr:postcode":"20005",
    "iso:country":"ES",
    "sg:address":"Plaz Bilbao De, 1",
    "sg:city":"Donostia-san Sebastian",
    "sg:orig_category":"Abogados",
    "sg:phone":"+34 943 43 13 04",
    "sg:postcode":"20005",
    "sg:province":"Guip\u00f9zcoa",
    "wof:name":"Sarasola Yurrita Maria Victoria",
    "wof:placetype":"venue"
},
  "geometry": {"coordinates":[-1.9794000387,43.3173789978],"type":"Point"}
}