{
  "type": "Feature",
  "properties": {
    "iso:country":"ES",
    "sg:address":"Plaz Espa\u00d1a, S/n",
    "sg:city":"Grazalema",
    "sg:orig_category":"Iglesia Cat\u00d3lica",
    "sg:phone":"+34 956 13 20 10",
    "sg:postcode":"11610",
    "sg:province":"C\u00e1diz",
    "wof:name":"Obispado De Jerez De La Frontera",
    "wof:placetype":"venue"
},
  "geometry": {"coordinates":[-5.3660140038,36.7582740784],"type":"Point"}
}