{
  "type": "Feature",
  "properties": {
    "addr:full":"Polg. Industrial, 17 Quintana Serena Badajoz 06450",
    "addr:housenumber":"17",
    "addr:postcode":"06450",
    "addr:street":"Quintana Serena",
    "iso:country":"ES",
    "sg:address":"Polg. Industrial, 17",
    "sg:city":"Quintana Serena",
    "sg:orig_category":"Contenedores (mercanc\u00cdas)",
    "sg:phone":"+34 924 78 64 76",
    "sg:postcode":"06450",
    "sg:province":"Badajoz",
    "wof:name":"Fernandez Benitez Francisco",
    "wof:placetype":"venue"
},
  "geometry": {"coordinates":[-5.6712579727,38.743019104],"type":"Point"}
}