{
  "type": "Feature",
  "properties": {
    "addr:full":"Plaz San Francisco, 17 Cartagena Murcia 30202",
    "addr:housenumber":"17",
    "addr:postcode":"30202",
    "addr:street":"Plaz San Francisco",
    "iso:country":"ES",
    "sg:address":"Plaz San Francisco, 17",
    "sg:city":"Cartagena",
    "sg:orig_category":"Estancos",
    "sg:phone":"+34 968 50 30 96",
    "sg:postcode":"30202",
    "sg:province":"Murcia",
    "wof:name":"Morales Marroig Adela",
    "wof:placetype":"venue"
},
  "geometry": {"coordinates":[-0.9831320047,37.6022186279],"type":"Point"}
}