{
  "type": "Feature",
  "properties": {
    "iso:country":"ES",
    "sg:address":"Carrer de Antoni Marques, 25",
    "sg:city":"Palma",
    "sg:classifiers":[
        {
            "category":"Cinema",
            "subcategory":"Movie Theater",
            "type":"Entertainment"
        }
    ],
    "sg:phone":"+34 971 75 12 62",
    "sg:postcode":"07003",
    "sg:province":"Islas Baleares",
    "sg:tags":[
        "salas",
        "de",
        "cine"
    ],
    "wof:name":"Antonio Servera S.l.",
    "wof:placetype":"venue"
},
  "geometry": {"coordinates":[2.649358511,39.5788269043],"type":"Point"}
}