{
  "type": "Feature",
  "properties": {
    "addr:full":"Finca Valrio, S/n Montehermoso C\u00e1ceres 10810",
    "addr:housenumber":"s / n",
    "addr:postcode":"10810",
    "addr:street":"Ca\u0301Ceres",
    "iso:country":"ES",
    "sg:address":"Finca Valrio, S/n",
    "sg:city":"Montehermoso",
    "sg:orig_category":"Cr\u00cda De Animales",
    "sg:phone":"+34 927 19 70 25",
    "sg:postcode":"10810",
    "sg:province":"C\u00e1ceres",
    "wof:name":"Arroyo Ballesteros Maria Victoria",
    "wof:placetype":"venue"
},
  "geometry": {"coordinates":[-6.3487591743,40.088508606],"type":"Point"}
}