{
  "type": "Feature",
  "properties": {
    "iso:country":"ES",
    "sg:address":"Calle de Do\u00d1ana, 8",
    "sg:city":"Lepe",
    "sg:orig_category":"Centros Empresariales",
    "sg:phone":"+34 959 38 35 23",
    "sg:postcode":"21440",
    "sg:province":"Huelva",
    "wof:name":"Ortiz Rubio Juana Maria",
    "wof:placetype":"venue"
},
  "geometry": {"coordinates":[-7.2063617706,37.2472419739],"type":"Point"}
}