{
  "type": "Feature",
  "properties": {
    "iso:country":"ES",
    "sg:address":"Calle de Montes Y Martin-baro, 9",
    "sg:city":"Valladolid",
    "sg:orig_category":"Delegados, Agentes De Tr\u00c1nsito, Auxiliares De Transporte Internacional",
    "sg:phone":"+34 983 27 34 85",
    "sg:postcode":"47008",
    "sg:province":"Valladolid",
    "wof:name":"Neira Ramos Jorge",
    "wof:placetype":"venue"
},
  "geometry": {"coordinates":[-4.7391228676,41.6257514954],"type":"Point"}
}