{
  "type": "Feature",
  "properties": {
    "addr:full":"Carrer de Joan Camiso, 63 S. Feliu Guixols Girona 17220",
    "addr:housenumber":"63",
    "addr:postcode":"17220",
    "addr:street":"Carrer De Joan Camiso;S. Feliu Guixols",
    "iso:country":"ES",
    "sg:address":"Carrer de Joan Camiso, 63",
    "sg:city":"S. Feliu Guixols",
    "sg:orig_category":"Escayola Y Productos De Escayola (fabricaci\u00d3n, Al Por Mayor)",
    "sg:phone":"+34 972 32 16 87",
    "sg:postcode":"17220",
    "sg:province":"Girona",
    "wof:name":"Vicenc-piquer S.l.",
    "wof:placetype":"venue"
},
  "geometry": {"coordinates":[3.0235419273,41.7931213379],"type":"Point"}
}