{
  "type": "Feature",
  "properties": {
    "iso:country":"ES",
    "sg:address":"Carrer de Joan Pfaff, 18",
    "sg:city":"S. Boi Llobregat",
    "sg:orig_category":"Asociaciones Y Clubs Deportivos",
    "sg:phone":"+34 936 54 53 41",
    "sg:postcode":"08830",
    "sg:province":"Barcelona",
    "wof:name":"Olimpic Figueras S.l.",
    "wof:placetype":"venue"
},
  "geometry": {"coordinates":[2.025881052,41.346950531],"type":"Point"}
}