{
  "type": "Feature",
  "properties": {
    "iso:country":"ES",
    "sg:address":"Calle de Padre Manjon, 1",
    "sg:city":"Puertollano",
    "sg:orig_category":"Comadronas",
    "sg:phone":"+34 926 42 64 72",
    "sg:postcode":"13500",
    "sg:province":"Ciudad Real",
    "wof:name":"Cabrera Espi Maria",
    "wof:placetype":"venue"
},
  "geometry": {"coordinates":[-4.1045799255,38.687877655],"type":"Point"}
}