{
  "type": "Feature",
  "properties": {
    "addr:full":"Plaz Txofre Del, 18 Donostia-san Sebastian Guip\u00f9zcoa 20001",
    "addr:housenumber":"18",
    "addr:postcode":"20001",
    "addr:street":"Plaz;Del",
    "iso:country":"ES",
    "sg:address":"Plaz Txofre Del, 18",
    "sg:city":"Donostia-san Sebastian",
    "sg:orig_category":"Abogados",
    "sg:phone":"+34 943 32 24 10",
    "sg:postcode":"20001",
    "sg:province":"Guip\u00f9zcoa",
    "wof:name":"Estudio Juridico Sunion S.l.",
    "wof:placetype":"venue"
},
  "geometry": {"coordinates":[-1.9736969471,43.3233299255],"type":"Point"}
}