{
  "type": "Feature",
  "properties": {
    "iso:country":"ES",
    "sg:address":"Ctr. Cuenca, Km. 0044,5",
    "sg:city":"Quintanar Rey",
    "sg:orig_category":"Mec\u00c1nico Del Autom\u00d3vil",
    "sg:phone":"+34 967 49 66 08",
    "sg:postcode":"16220",
    "sg:province":"Cuenca",
    "wof:name":"Isidoro Garcia Lopez Y Otro C.b.",
    "wof:placetype":"venue"
},
  "geometry": {"coordinates":[-1.9303289652,39.3473358154],"type":"Point"}
}