{
  "type": "Feature",
  "properties": {
    "addr:full":"Carrer de Congost, 27 Barcelona Barcelona 08024",
    "addr:housenumber":"27",
    "addr:postcode":"08024",
    "addr:street":"Carrer De Congost",
    "iso:country":"ES",
    "sg:address":"Carrer de Congost, 27",
    "sg:city":"Barcelona",
    "sg:orig_category":"Rotulistas",
    "sg:phone":"+34 932 13 24 98",
    "sg:postcode":"08024",
    "sg:province":"Barcelona",
    "wof:name":"Gonzalez Dominguez Juan",
    "wof:placetype":"venue"
},
  "geometry": {"coordinates":[2.1583590508,41.4064025879],"type":"Point"}
}