{
  "type": "Feature",
  "properties": {
    "addr:full":"Send Los Canonigos, 7 Vitoria-gasteiz \u00c1lava 01002",
    "addr:housenumber":"7",
    "addr:postcode":"01002",
    "addr:street":"Send Los Canonigos",
    "iso:country":"ES",
    "sg:address":"Send Los Canonigos, 7",
    "sg:city":"Vitoria-gasteiz",
    "sg:orig_category":"Reposter\u00cdas",
    "sg:phone":"+34 945 28 35 06",
    "sg:postcode":"01002",
    "sg:province":"\u00c1lava",
    "wof:name":"La Vitoriana De La Alimentacion S.l.",
    "wof:placetype":"venue"
},
  "geometry": {"coordinates":[-2.667140007,42.8534812927],"type":"Point"}
}