{
  "type": "Feature",
  "properties": {
    "iso:country":"ES",
    "sg:address":"Carrer de Bisbe Urquinaona, 13",
    "sg:city":"Castelldefels",
    "sg:orig_category":"Ense\u00d1anza: Idiomas",
    "sg:phone":"+34 936 36 02 20",
    "sg:postcode":"08860",
    "sg:province":"Barcelona",
    "sg:website":"www.anywayidiomas.com",
    "wof:name":"Anyway S.c.p.",
    "wof:placetype":"venue"
},
  "geometry": {"coordinates":[1.978058219,41.2822723389],"type":"Point"}
}