{
  "type": "Feature",
  "properties": {
    "iso:country":"ES",
    "sg:address":"C/ Cadiretes, 16",
    "sg:city":"Tossa",
    "sg:orig_category":"Transportes Por V\u00cdas Navegables",
    "sg:phone":"+34 972 34 01 14",
    "sg:postcode":"17320",
    "sg:province":"Girona",
    "wof:name":"Taberner Balma\u00f1a Sebastian",
    "wof:placetype":"venue"
},
  "geometry": {"coordinates":[2.9298949242,41.7226753235],"type":"Point"}
}