{
  "type": "Feature",
  "properties": {
    "iso:country":"ES",
    "sg:address":"Avda Cervantes, S/n",
    "sg:city":"Arizgoiti",
    "sg:orig_category":"Fabricaci\u00d3n Y Comercio De M\u00c1quinas",
    "sg:phone":"+34 944 40 10 36",
    "sg:postcode":"48970",
    "sg:province":"Vizcaya",
    "wof:name":"Autobas 77 S. A.",
    "wof:placetype":"venue"
},
  "geometry": {"coordinates":[-2.8811762333,43.2426109314],"type":"Point"}
}