{
  "type": "Feature",
  "properties": {
    "addr:full":"Calle de Benavente, 2 Santa Croya De Tera Zamora 49626",
    "addr:housenumber":"2",
    "addr:postcode":"49626",
    "addr:street":"Calle De Benavente",
    "iso:country":"ES",
    "sg:address":"Calle de Benavente, 2",
    "sg:city":"Santa Croya De Tera",
    "sg:orig_category":"Farmacias",
    "sg:phone":"+34 980 64 52 14",
    "sg:postcode":"49626",
    "sg:province":"Zamora",
    "wof:name":"Molezuelas Codesal Asterio",
    "wof:placetype":"venue"
},
  "geometry": {"coordinates":[-5.9733791351,41.986743927],"type":"Point"}
}