{
  "type": "Feature",
  "properties": {
    "addr:full":"Calle de Doctor Vallejo, 41 Madrid Madrid 28027",
    "addr:housenumber":"41",
    "addr:postcode":"madrid;28027",
    "addr:street":"Calle De Doctor Vallejo",
    "iso:country":"ES",
    "sg:address":"Calle de Doctor Vallejo, 41",
    "sg:city":"Madrid",
    "sg:orig_category":"Cristaler\u00cdas",
    "sg:phone":"+34 913 67 52 48",
    "sg:postcode":"28027",
    "sg:province":"Madrid",
    "wof:name":"Armada Lopez Felix",
    "wof:placetype":"venue"
},
  "geometry": {"coordinates":[-3.6450355053,40.4383506775],"type":"Point"}
}