{
  "type": "Feature",
  "properties": {
    "addr:full":"Avda Ramon Y Cajal, 2 Candeleda \u00c1vila 05480",
    "addr:housenumber":"2",
    "addr:postcode":"05480",
    "addr:street":"Avda Ramon Y Cajal",
    "iso:country":"ES",
    "sg:address":"Avda Ramon Y Cajal, 2",
    "sg:city":"Candeleda",
    "sg:orig_category":"Electricidad: Instaladores",
    "sg:phone":"+34 920 38 06 28",
    "sg:postcode":"05480",
    "sg:province":"\u00c1vila",
    "wof:name":"Grupo Campogar Servicio Integral S.l.",
    "wof:placetype":"venue"
},
  "geometry": {"coordinates":[-5.2410569191,40.1528015137],"type":"Point"}
}