{
  "type": "Feature",
  "properties": {
    "addr:full":"Av Ametlla De Mar, 19 Benidorm Alicante 03500",
    "addr:housenumber":"19",
    "addr:postcode":"03500",
    "addr:street":"Av Ametlla De Mar",
    "iso:country":"ES",
    "sg:address":"Av Ametlla De Mar, 19",
    "sg:city":"Benidorm",
    "sg:orig_category":"Reposter\u00cdas",
    "sg:phone":"+34 965 85 64 15",
    "sg:postcode":"03500",
    "sg:province":"Alicante",
    "wof:name":"Vendor Costablanca S.l.u",
    "wof:placetype":"venue"
},
  "geometry": {"coordinates":[-0.1739459932,38.5365180969],"type":"Point"}
}