{
  "type": "Feature",
  "properties": {
    "addr:full":"Carrer de Ordana (l'), 47 Sant Joan D'alacant Alicante 03550",
    "addr:housenumber":"47",
    "addr:postcode":"03550",
    "addr:street":"Carrer De Ordana L '",
    "iso:country":"ES",
    "sg:address":"Carrer de Ordana (l'), 47",
    "sg:city":"Sant Joan D'alacant",
    "sg:orig_category":"Reposter\u00cdas",
    "sg:phone":"+34 965 65 37 75",
    "sg:postcode":"03550",
    "sg:province":"Alicante",
    "wof:name":"Sebastia Catala Vicente",
    "wof:placetype":"venue"
},
  "geometry": {"coordinates":[-0.5334010124,38.3440818787],"type":"Point"}
}