{
  "type": "Feature",
  "properties": {
    "iso:country":"ES",
    "sg:address":"Carrer de Josep Maria Fabregas, 5",
    "sg:city":"Valls",
    "sg:orig_category":"Empresas De Portes Y Mensajer\u00cda",
    "sg:phone":"+34 977 61 44 46",
    "sg:postcode":"43800",
    "sg:province":"Tarragona",
    "wof:name":"Vecamax Logistica S.c.p",
    "wof:placetype":"venue"
},
  "geometry": {"coordinates":[1.2547329664,41.2910079956],"type":"Point"}
}