{
  "type": "Feature",
  "properties": {
    "addr:full":"Pase Prado (del), 2 Tudela Navarra 31500",
    "addr:postcode":"31500",
    "iso:country":"ES",
    "sg:address":"Pase Prado (del), 2",
    "sg:city":"Tudela",
    "sg:orig_category":"Asociaciones, Organismos Culturales Y Socioeducativos",
    "sg:phone":"+34 948 82 63 17",
    "sg:postcode":"31500",
    "sg:province":"Navarra",
    "wof:name":"Sociedad Deportivo Recreativa Arenas",
    "wof:placetype":"venue"
},
  "geometry": {"coordinates":[-1.60295403,42.0619239807],"type":"Point"}
}