{
  "type": "Feature",
  "properties": {
    "addr:full":"Barr Cerrazo, S/n Cerrazo Cantabria 39539",
    "addr:housenumber":"s",
    "addr:postcode":"39539",
    "addr:street":"/ N",
    "iso:country":"ES",
    "sg:address":"Barr Cerrazo, S/n",
    "sg:city":"Cerrazo",
    "sg:orig_category":"Iglesia Cat\u00d3lica",
    "sg:phone":"+34 942 82 04 03",
    "sg:postcode":"39539",
    "sg:province":"Cantabria",
    "wof:name":"Casa Parroquial",
    "wof:placetype":"venue"
},
  "geometry": {"coordinates":[-4.1089868546,43.3644638062],"type":"Point"}
}