{
  "type": "Feature",
  "properties": {
    "addr:full":"Carrer de Mare De Deu De Nuria, 18 Granollers Barcelona 08401",
    "addr:housenumber":"18",
    "addr:postcode":"08401",
    "addr:street":"Carrer De Mare De Deu De Nuria",
    "iso:country":"ES",
    "sg:address":"Carrer de Mare De Deu De Nuria, 18",
    "sg:city":"Granollers",
    "sg:orig_category":"Asociaciones Y Clubs Deportivos",
    "sg:phone":"+34 938 70 71 54",
    "sg:postcode":"08401",
    "sg:province":"Barcelona",
    "wof:name":"Manzano Selas Francisco",
    "wof:placetype":"venue"
},
  "geometry": {"coordinates":[2.2838089466,41.608745575],"type":"Point"}
}