{
  "type": "Feature",
  "properties": {
    "addr:full":"Calle de Poeta Emilio Prados, S/n Cordoba C\u00f3rdoba 14012",
    "addr:housenumber":"s / n",
    "addr:postcode":"14012",
    "addr:street":"Calle De Poeta Emilio Prados;Co\u0301Rdoba",
    "iso:country":"ES",
    "sg:address":"Calle de Poeta Emilio Prados, S/n",
    "sg:city":"Cordoba",
    "sg:orig_category":"Ropa Para Ni\u00d1os (al Por Menor)",
    "sg:phone":"+34 957 27 10 55",
    "sg:postcode":"14012",
    "sg:province":"C\u00f3rdoba",
    "sg:website":"www.e-stradivarius.com",
    "wof:name":"Stradivarius Espa\u00d1a S.a",
    "wof:placetype":"venue"
},
  "geometry": {"coordinates":[-4.7903699875,37.8989143372],"type":"Point"}
}