{
  "type": "Feature",
  "properties": {
    "iso:country":"ES",
    "sg:address":"Cami Ullastrell, S/n",
    "sg:city":"Rubi",
    "sg:orig_category":"Centros De Educaci\u00d3n Especial",
    "sg:phone":"+34 936 97 10 36",
    "sg:postcode":"08191",
    "sg:province":"Barcelona",
    "wof:name":"Ampa Joan Maragall",
    "wof:placetype":"venue"
},
  "geometry": {"coordinates":[2.0042629242,41.5047492981],"type":"Point"}
}