{
  "type": "Feature",
  "properties": {
    "iso:country":"ES",
    "sg:address":"Carrer de Afores, S/n",
    "sg:city":"Vila-rodona",
    "sg:orig_category":"Centros De Educaci\u00d3n Especial",
    "sg:phone":"+34 977 63 80 38",
    "sg:postcode":"43814",
    "sg:province":"Tarragona",
    "wof:name":"Ajuntament De Vila-rodona",
    "wof:placetype":"venue"
},
  "geometry": {"coordinates":[1.3758648634,41.3027763367],"type":"Point"}
}