{
  "type": "Feature",
  "properties": {
    "iso:country":"ES",
    "sg:address":"Rbla Catalunya, 35",
    "sg:city":"Almacelles",
    "sg:orig_category":"Institutos De Belleza",
    "sg:phone":"+34 973 74 02 71",
    "sg:postcode":"25100",
    "sg:province":"Lleida",
    "wof:name":"Lorente Martinez Carolina",
    "wof:placetype":"venue"
},
  "geometry": {"coordinates":[0.4439310133,41.7294960022],"type":"Point"}
}