{
  "type": "Feature",
  "properties": {
    "addr:full":"Plaz Iglesia (la), 1 Villanueva De San Juan Sevilla 41660",
    "addr:postcode":"41660",
    "iso:country":"ES",
    "sg:address":"Plaz Iglesia (la), 1",
    "sg:city":"Villanueva De San Juan",
    "sg:orig_category":"Cajas Para Embalar",
    "sg:phone":"+34 955 91 65 40",
    "sg:postcode":"41660",
    "sg:province":"Sevilla",
    "wof:name":"Caja Rural Del Sur Sociedad Cooperativa",
    "wof:placetype":"venue"
},
  "geometry": {"coordinates":[-5.1756110191,37.0507125854],"type":"Point"}
}