{
  "type": "Feature",
  "properties": {
    "iso:country":"ES",
    "sg:address":"Calle de Conde De Villanueva, 1",
    "sg:city":"Villafranca De Los Barros",
    "sg:orig_category":"Iglesia Cat\u00d3lica",
    "sg:phone":"+34 924 52 32 69",
    "sg:postcode":"06220",
    "sg:province":"Badajoz",
    "wof:name":"Parroquia Nuestra Se\u00f1ora Del Valle",
    "wof:placetype":"venue"
},
  "geometry": {"coordinates":[-6.3399348259,38.5613899231],"type":"Point"}
}