{
  "type": "Feature",
  "properties": {
    "iso:country":"ES",
    "sg:address":"A. Garcia, 9",
    "sg:city":"Atarrabia",
    "sg:orig_category":"Promotores Constructores",
    "sg:phone":"+34 948 33 20 34",
    "sg:postcode":"31610",
    "sg:province":"Navarra",
    "wof:name":"Promociones Oloriz S.l.",
    "wof:placetype":"venue"
},
  "geometry": {"coordinates":[-1.6098489761,42.8311386108],"type":"Point"}
}