{
  "type": "Feature",
  "properties": {
    "iso:country":"ES",
    "sg:address":"Carr Llevant, 16",
    "sg:city":"Port D'andratx",
    "sg:orig_category":"Administradores De Bienes Y Delegados De Comunidades De Propietarios",
    "sg:phone":"+34 971 67 47 72",
    "sg:postcode":"07157",
    "sg:province":"Islas Baleares",
    "wof:name":"Balear Finca Servis Mallorca S.l.",
    "wof:placetype":"venue"
},
  "geometry": {"coordinates":[2.4184219837,39.5753593445],"type":"Point"}
}