{
  "type": "Feature",
  "properties": {
    "addr:full":"Calle de Granja (de La), 88 Alcobendas Madrid 28108",
    "addr:housenumber":"88",
    "addr:postcode":"28108",
    "addr:street":"Calle De Granja De La",
    "iso:country":"ES",
    "sg:address":"Calle de Granja (de La), 88",
    "sg:city":"Alcobendas",
    "sg:orig_category":"Empresas De Carpinter\u00cda De Madera",
    "sg:phone":"+34 916 61 00 45",
    "sg:postcode":"28108",
    "sg:province":"Madrid",
    "wof:name":"Castrillo Moreno Martin",
    "wof:placetype":"venue"
},
  "geometry": {"coordinates":[-3.656056881,40.5356864929],"type":"Point"}
}