{
  "type": "Feature",
  "properties": {
    "addr:full":"Carrer de Balmes, 35 Pineda Mar Barcelona 08397",
    "addr:housenumber":"35",
    "addr:postcode":"08397",
    "addr:street":"Carrer De Balmes;Barcelona",
    "iso:country":"ES",
    "sg:address":"Carrer de Balmes, 35",
    "sg:city":"Pineda Mar",
    "sg:orig_category":"Fabricaci\u00d3n De Peines Y De Accesorios De Peluquer\u00cda",
    "sg:phone":"+34 937 62 68 71",
    "sg:postcode":"08397",
    "sg:province":"Barcelona",
    "wof:name":"Camacho Montsant Nuria",
    "wof:placetype":"venue"
},
  "geometry": {"coordinates":[2.6873450279,41.6250610352],"type":"Point"}
}