{
  "type": "Feature",
  "properties": {
    "iso:country":"ES",
    "sg:address":"Avda Gregorio Gea, 10",
    "sg:city":"Mislata",
    "sg:orig_category":"Electrodom\u00c9sticos (fabricaci\u00d3n, Al Por Mayor)",
    "sg:phone":"+34 963 13 58 87",
    "sg:postcode":"46920",
    "sg:province":"Valencia",
    "wof:name":"Radio Castilla S.a.",
    "wof:placetype":"venue"
},
  "geometry": {"coordinates":[-0.4141890109,39.4729270935],"type":"Point"}
}