{
  "type": "Feature",
  "properties": {
    "addr:full":"Carrer de Pompeu Fabra, 3 Santa Coloma De Gramenet Barcelona 08922",
    "addr:housenumber":"3",
    "addr:postcode":"08922",
    "addr:street":"Carrer De Pompeu Fabra",
    "iso:country":"ES",
    "sg:address":"Carrer de Pompeu Fabra, 3",
    "sg:city":"Santa Coloma De Gramenet",
    "sg:orig_category":"Ropa De Hogar (al Por Menor)",
    "sg:phone":"+34 933 86 16 72",
    "sg:postcode":"08922",
    "sg:province":"Barcelona",
    "wof:name":"Guinart Casquillo Daniel",
    "wof:placetype":"venue"
},
  "geometry": {"coordinates":[2.2093219757,41.4506950378],"type":"Point"}
}