{
  "type": "Feature",
  "properties": {
    "addr:full":"Av Cornella, 138 Esplugues Llobregat Barcelona 08950",
    "addr:housenumber":"138",
    "addr:postcode":"08950",
    "addr:street":"Av Cornella",
    "iso:country":"ES",
    "sg:address":"Av Cornella, 138",
    "sg:city":"Esplugues Llobregat",
    "sg:orig_category":"Agentes, Concesionarios Y Sucursales De Veh\u00cdculos",
    "sg:phone":"+34 933 72 07 91",
    "sg:postcode":"08950",
    "sg:province":"Barcelona",
    "wof:name":"Fiat Auto Espa\u00f1a S.a.",
    "wof:placetype":"venue"
},
  "geometry": {"coordinates":[2.080696106,41.3697052002],"type":"Point"}
}