{
  "type": "Feature",
  "properties": {
    "addr:full":"Avda Constitucion, 34 Pe\u00f1afiel Valladolid 47300",
    "addr:housenumber":"34",
    "addr:postcode":"47300",
    "addr:street":"Avda Constitucion",
    "iso:country":"ES",
    "sg:address":"Avda Constitucion, 34",
    "sg:city":"Pe\u00f1afiel",
    "sg:orig_category":"Zapatos (al Por Menor)",
    "sg:phone":"+34 983 88 01 19",
    "sg:postcode":"47300",
    "sg:province":"Valladolid",
    "sg:website":"www.calzadosgomez.es",
    "wof:name":"Gomez Puertas Alfonso",
    "wof:placetype":"venue"
},
  "geometry": {"coordinates":[-4.1179790497,41.6003799438],"type":"Point"}
}