{
  "type": "Feature",
  "properties": {
    "addr:full":"Calle de Primavera, 12 Viso Del Alcor Sevilla 41520",
    "addr:housenumber":"12",
    "addr:postcode":"41520",
    "addr:street":"Calle De Primavera",
    "iso:country":"ES",
    "sg:address":"Calle de Primavera, 12",
    "sg:city":"Viso Del Alcor",
    "sg:orig_category":"Contenedores (mercanc\u00cdas)",
    "sg:phone":"+34 955 94 50 41",
    "sg:postcode":"41520",
    "sg:province":"Sevilla",
    "wof:name":"Transmoybe S.l.",
    "wof:placetype":"venue"
},
  "geometry": {"coordinates":[-5.7262687683,37.382144928],"type":"Point"}
}