{
  "type": "Feature",
  "properties": {
    "iso:country":"ES",
    "sg:address":"Carrer de Sabino Arana, 18",
    "sg:city":"Barcelona",
    "sg:orig_category":"Inform\u00c1tica, Ofim\u00c1tica (estudios, Asesor\u00cda, Ingenier\u00cda, Formaci\u00d3n)",
    "sg:phone":"+34 934 09 84 80",
    "sg:postcode":"08028",
    "sg:province":"Barcelona",
    "sg:website":"www.comunycarse.com",
    "wof:name":"Comunycarse Network Consultans S.l.",
    "wof:placetype":"venue"
},
  "geometry": {"coordinates":[2.1255390644,41.3853645325],"type":"Point"}
}