{
  "type": "Feature",
  "properties": {
    "iso:country":"ES",
    "sg:address":"Calle de Metal (del), 4",
    "sg:city":"Alcorcon",
    "sg:orig_category":"Importaci\u00d3n",
    "sg:phone":"+34 916 43 64 84",
    "sg:postcode":"28925",
    "sg:province":"Madrid",
    "wof:name":"Canary Top Sport S.l.",
    "wof:placetype":"venue"
},
  "geometry": {"coordinates":[-3.8044879436,40.3450469971],"type":"Point"}
}