{
  "type": "Feature",
  "properties": {
    "addr:full":"Avda Gran Capitan (del), 38 Cordoba C\u00f3rdoba 14001",
    "addr:housenumber":"38",
    "addr:postcode":"14001",
    "addr:street":"Avda Gran Capitan Del;Co\u0301Rdoba",
    "iso:country":"ES",
    "sg:address":"Avda Gran Capitan (del), 38",
    "sg:city":"Cordoba",
    "sg:orig_category":"Caf\u00c9s, Bares, Cervecer\u00cdas",
    "sg:phone":"+34 957 49 67 84",
    "sg:postcode":"14001",
    "sg:province":"C\u00f3rdoba",
    "wof:name":"Promociones Turisticas Irlandesas",
    "wof:placetype":"venue"
},
  "geometry": {"coordinates":[-4.7826189995,37.8892555237],"type":"Point"}
}