{
  "type": "Feature",
  "properties": {
    "iso:country":"ES",
    "sg:address":"Avgd Francesc Macia, 35",
    "sg:city":"Lleida",
    "sg:orig_category":"Abogados",
    "sg:phone":"+34 973 23 01 66",
    "sg:postcode":"25007",
    "sg:province":"Lleida",
    "wof:name":"Baldellou Domingo Emilio",
    "wof:placetype":"venue"
},
  "geometry": {"coordinates":[0.6287553906,41.6164321899],"type":"Point"}
}