{
  "type": "Feature",
  "properties": {
    "addr:full":"Pg Pere Iii, 49 Manresa Barcelona 08242",
    "addr:housenumber":"49",
    "addr:postcode":"08242",
    "addr:street":"Pg Pere Iii",
    "iso:country":"ES",
    "sg:address":"Pg Pere Iii, 49",
    "sg:city":"Manresa",
    "sg:orig_category":"Mercer\u00cda, Lencer\u00cda (al Por Menor)",
    "sg:phone":"+34 938 73 71 18",
    "sg:postcode":"08242",
    "sg:province":"Barcelona",
    "wof:name":"Freixo Ponti Eva Marta",
    "wof:placetype":"venue"
},
  "geometry": {"coordinates":[1.8240469694,41.7292137146],"type":"Point"}
}