{
  "type": "Feature",
  "properties": {
    "addr:full":"Plaz Pueblo (del), 5 Alcobendas Madrid 28100",
    "addr:postcode":"28100",
    "iso:country":"ES",
    "sg:address":"Plaz Pueblo (del), 5",
    "sg:city":"Alcobendas",
    "sg:orig_category":"Bancos",
    "sg:phone":"+34 916 52 04 66",
    "sg:postcode":"28100",
    "sg:province":"Madrid",
    "wof:name":"Banco Popular Espa\u00f1ol",
    "wof:placetype":"venue"
},
  "geometry": {"coordinates":[-3.6340239048,40.5411491394],"type":"Point"}
}