{
  "type": "Feature",
  "properties": {
    "iso:country":"ES",
    "sg:address":"Calle de Huerta Pley, S/n",
    "sg:city":"Pto Real",
    "sg:orig_category":"Asesor\u00cda De Formaci\u00d3n Y Gesti\u00d3n De Personal",
    "sg:phone":"+34 956 83 60 30",
    "sg:postcode":"11510",
    "sg:province":"C\u00e1diz",
    "wof:name":"Campos Rodriguez Alfonso Maria",
    "wof:placetype":"venue"
},
  "geometry": {"coordinates":[-6.1837887764,36.5269584656],"type":"Point"}
}