{
  "type": "Feature",
  "properties": {
    "iso:country":"ES",
    "sg:address":"Avgd Morera, 36",
    "sg:city":"Badalona",
    "sg:orig_category":"Reposter\u00cdas",
    "sg:phone":"+34 933 95 01 55",
    "sg:postcode":"08915",
    "sg:province":"Barcelona",
    "wof:name":"Forn Clapes S.l.",
    "wof:placetype":"venue"
},
  "geometry": {"coordinates":[2.2485868931,41.4607467651],"type":"Point"}
}