{
  "type": "Feature",
  "properties": {
    "iso:country":"ES",
    "sg:address":"Crrd Capuchinos, 6",
    "sg:city":"Andujar",
    "sg:orig_category":"Reposter\u00cdas",
    "sg:phone":"+34 953 51 32 65",
    "sg:postcode":"23740",
    "sg:province":"Ja\u00e9n",
    "wof:name":"Panaderia Alfonso",
    "wof:placetype":"venue"
},
  "geometry": {"coordinates":[-4.0515098572,38.0363922119],"type":"Point"}
}