{
  "type": "Feature",
  "properties": {
    "addr:full":"Carrer de Bonastre, 20 Albinyana Tarragona 43716",
    "addr:housenumber":"20",
    "addr:postcode":"43716",
    "addr:street":"Carrer De Bonastre",
    "iso:country":"ES",
    "sg:address":"Carrer de Bonastre, 20",
    "sg:city":"Albinyana",
    "sg:orig_category":"Supermercados Y Hipermercados",
    "sg:phone":"+34 977 68 78 60",
    "sg:postcode":"43716",
    "sg:province":"Tarragona",
    "wof:name":"Mellado Pelegrin Antonio",
    "wof:placetype":"venue"
},
  "geometry": {"coordinates":[1.4848330021,41.242980957],"type":"Point"}
}