{
  "type": "Feature",
  "properties": {
    "addr:full":"Estd Maside (de), S/n Cea Ourense 32130",
    "addr:housenumber":"s",
    "addr:postcode":"32130",
    "addr:street":"/ N",
    "iso:country":"ES",
    "sg:address":"Estd Maside (de), S/n",
    "sg:city":"Cea",
    "sg:orig_category":"Cr\u00cda De Poller\u00cda Y De Conejos",
    "sg:phone":"+34 988 28 21 10",
    "sg:postcode":"32130",
    "sg:province":"Ourense",
    "wof:name":"Fernandez Rodriguez Jose",
    "wof:placetype":"venue"
},
  "geometry": {"coordinates":[-7.9874720573,42.4763221741],"type":"Point"}
}