{
  "type": "Feature",
  "properties": {
    "addr:full":"Avda Abona, 21 Castro Santa Cruz De Tenerife 38611",
    "addr:housenumber":"21",
    "addr:postcode":"38611",
    "addr:street":"Avda Abona",
    "iso:country":"ES",
    "sg:address":"Avda Abona, 21",
    "sg:city":"Castro",
    "sg:orig_category":"Laboratorios Y Trabajos De Fotograf\u00cda, V\u00cddeo Y Cine",
    "sg:phone":"+34 922 39 20 09",
    "sg:postcode":"38611",
    "sg:province":"Santa Cruz De Tenerife",
    "wof:name":"Frias Delgado Nazaret",
    "wof:placetype":"venue"
},
  "geometry": {"coordinates":[-16.5577411652,28.0779342651],"type":"Point"}
}