{
  "type": "Feature",
  "properties": {
    "iso:country":"ES",
    "sg:address":"Ctra. Borines, S/n",
    "sg:city":"Borines",
    "sg:orig_category":"Serrer\u00cdas De Madera",
    "sg:phone":"+34 985 70 72 56",
    "sg:postcode":"33583",
    "sg:province":"Asturias",
    "wof:name":"Laviada Catron Ignacio",
    "wof:placetype":"venue"
},
  "geometry": {"coordinates":[-5.3137249947,43.3825111389],"type":"Point"}
}