{
  "type": "Feature",
  "properties": {
    "iso:country":"ES",
    "sg:address":"Carrer de Sant Antoni, 6",
    "sg:city":"Vic",
    "sg:orig_category":"Transportes Por Carretera: Lotes Completos, Mercanc\u00cdas Diversas",
    "sg:phone":"+34 938 89 28 22",
    "sg:postcode":"08500",
    "sg:province":"Barcelona",
    "wof:name":"Bon Preu S. A.",
    "wof:placetype":"venue"
},
  "geometry": {"coordinates":[2.2562539577,41.9312286377],"type":"Point"}
}