{
  "type": "Feature",
  "properties": {
    "iso:country":"ES",
    "sg:address":"Calle de Corrida, 23",
    "sg:city":"Gijon",
    "sg:orig_category":"Parques De Atracciones Y Centros De Esparcimiento",
    "sg:phone":"+34 985 35 05 69",
    "sg:postcode":"33206",
    "sg:province":"Asturias",
    "wof:name":"Sodicarsa.s.a.",
    "wof:placetype":"venue"
},
  "geometry": {"coordinates":[-5.6641244888,43.5420837402],"type":"Point"}
}