{
  "type": "Feature",
  "properties": {
    "addr:full":"Av Europa, 189 Hospitalet Llobregat Barcelona 08907",
    "addr:housenumber":"189",
    "addr:postcode":"08907",
    "addr:street":"Av Europa",
    "iso:country":"ES",
    "sg:address":"Av Europa, 189",
    "sg:city":"Hospitalet Llobregat",
    "sg:orig_category":"Sociedades, Compa\u00d1\u00cdas Aseguradoras",
    "sg:phone":"+34 933 36 19 58",
    "sg:postcode":"08907",
    "sg:province":"Barcelona",
    "wof:name":"Mapfre Servicios De Informatica",
    "wof:placetype":"venue"
},
  "geometry": {"coordinates":[2.1127500534,41.356628418],"type":"Point"}
}