{
  "type": "Feature",
  "properties": {
    "addr:full":"Calle de Hermanos Barral, 3 Segovia Segovia 40001",
    "addr:housenumber":"3",
    "addr:postcode":"40001",
    "addr:street":"Calle De Hermanos Barral",
    "iso:country":"ES",
    "sg:address":"Calle de Hermanos Barral, 3",
    "sg:city":"Segovia",
    "sg:orig_category":"Restaurantes",
    "sg:phone":"+34 921 46 39 04",
    "sg:postcode":"40001",
    "sg:province":"Segovia",
    "wof:name":"C.b.la Codorniz",
    "wof:placetype":"venue"
},
  "geometry": {"coordinates":[-4.1201028824,40.9463233948],"type":"Point"}
}