{
  "type": "Feature",
  "properties": {
    "addr:full":"Avda Comuneros, 42 Salamanca Salamanca 37003",
    "addr:housenumber":"42",
    "addr:postcode":"37003",
    "addr:street":"Avda Comuneros",
    "iso:country":"ES",
    "sg:address":"Avda Comuneros, 42",
    "sg:city":"Salamanca",
    "sg:orig_category":"Bisuter\u00cda, Joyer\u00cda, Relojer\u00cda (al Por Menor)",
    "sg:phone":"+34 923 18 84 84",
    "sg:postcode":"37003",
    "sg:province":"Salamanca",
    "wof:name":"Martin Hernandez Maria Teresa",
    "wof:placetype":"venue"
},
  "geometry": {"coordinates":[-5.6495361328,40.9684562683],"type":"Point"}
}