{
  "type": "Feature",
  "properties": {
    "addr:full":"Calle de Santiago, 8 Santa Lucia Murcia 30202",
    "addr:housenumber":"8",
    "addr:postcode":"30202",
    "addr:street":"Calle De Santiago",
    "iso:country":"ES",
    "sg:address":"Calle de Santiago, 8",
    "sg:city":"Santa Lucia",
    "sg:orig_category":"Relojer\u00cda (al Por Menor, Reparaci\u00d3n)",
    "sg:phone":"+34 968 52 35 18",
    "sg:postcode":"30202",
    "sg:province":"Murcia",
    "wof:name":"Hr. Pedro Alcolea S.l.",
    "wof:placetype":"venue"
},
  "geometry": {"coordinates":[-1.1302499771,37.9829597473],"type":"Point"}
}