{
  "type": "Feature",
  "properties": {
    "iso:country":"ES",
    "sg:address":"Calle de Pintor Gisbert, 4",
    "sg:city":"Alacant",
    "sg:orig_category":"Ense\u00d1anza Variada",
    "sg:phone":"+34 965 13 39 38",
    "sg:postcode":"03005",
    "sg:province":"Alicante",
    "wof:name":"Pereto Sastre Carlos",
    "wof:placetype":"venue"
},
  "geometry": {"coordinates":[-0.4941349924,38.3483505249],"type":"Point"}
}