{
  "type": "Feature",
  "properties": {
    "addr:full":"Iparragirre Avda Z Industrial, 98 Elexalde Vizcaya 48940",
    "addr:housenumber":"98",
    "addr:postcode":"48940",
    "addr:street":"Avda Z Industrial",
    "iso:country":"ES",
    "sg:address":"Iparragirre Avda Z Industrial, 98",
    "sg:city":"Elexalde",
    "sg:orig_category":"Formaci\u00d3n Continuada (variada)",
    "sg:phone":"+34 944 80 60 30",
    "sg:postcode":"48940",
    "sg:province":"Vizcaya",
    "wof:name":"Ayuntamiento De Leioa",
    "wof:placetype":"venue"
},
  "geometry": {"coordinates":[-2.9860789776,43.3275489807],"type":"Point"}
}