{
  "type": "Feature",
  "properties": {
    "iso:country":"ES",
    "sg:address":"Pirineos I, 2",
    "sg:city":"Colmenar Viejo",
    "sg:orig_category":"Molduras, Junquillos, Listones Y Molduras Perforadas",
    "sg:phone":"+34 918 46 37 95",
    "sg:postcode":"28770",
    "sg:province":"Madrid",
    "wof:name":"Barroso Viso Jose",
    "wof:placetype":"venue"
},
  "geometry": {"coordinates":[-3.7713630199,40.6553382874],"type":"Point"}
}