{
  "type": "Feature",
  "properties": {
    "iso:country":"ES",
    "sg:address":"Calle de Mayor, 38",
    "sg:city":"Zuera",
    "sg:orig_category":"Panader\u00cdas, Panader\u00cdas",
    "sg:phone":"+34 976 69 04 27",
    "sg:postcode":"50800",
    "sg:province":"Zaragoza",
    "wof:name":"Solanas Apuntate Sandra",
    "wof:placetype":"venue"
},
  "geometry": {"coordinates":[-0.7873942852,41.8690948486],"type":"Point"}
}