{
  "type": "Feature",
  "properties": {
    "iso:country":"ES",
    "sg:address":"Calle de Nueva, 13",
    "sg:city":"Motril",
    "sg:orig_category":"Ropa Para Caballeros (al Por Menor)",
    "sg:phone":"+34 958 82 53 94",
    "sg:postcode":"18600",
    "sg:province":"Granada",
    "wof:name":"Andres Suarez Florentino",
    "wof:placetype":"venue"
},
  "geometry": {"coordinates":[-3.517226696,36.7459526062],"type":"Point"}
}