{
  "type": "Feature",
  "properties": {
    "addr:full":"Zubizargaina, S/n Sunbilla Navarra 31791",
    "addr:housenumber":"/ n",
    "addr:postcode":"31791",
    "addr:street":"Zubizargaina S",
    "iso:country":"ES",
    "sg:address":"Zubizargaina, S/n",
    "sg:city":"Sunbilla",
    "sg:orig_category":"Zonas De Acampada, Aparcamiento Para Caravanas",
    "sg:phone":"+34 948 45 05 40",
    "sg:postcode":"31791",
    "sg:province":"Navarra",
    "wof:name":"Lauaritz S.l.",
    "wof:placetype":"venue"
},
  "geometry": {"coordinates":[-1.6700350046,43.1636657715],"type":"Point"}
}