{
  "type": "Feature",
  "properties": {
    "addr:full":"La Luisiana, S/n Fuentes De Andalucia Sevilla 41420",
    "addr:housenumber":"s / n",
    "addr:postcode":"41420",
    "addr:street":"La Luisiana",
    "iso:country":"ES",
    "sg:address":"La Luisiana, S/n",
    "sg:city":"Fuentes De Andalucia",
    "sg:orig_category":"Producci\u00d3n, Comercio De Cereales",
    "sg:phone":"+34 954 83 82 04",
    "sg:postcode":"41420",
    "sg:province":"Sevilla",
    "wof:name":"Sociedad Agraria De Transformacion",
    "wof:placetype":"venue"
},
  "geometry": {"coordinates":[-5.341591835,37.4676780701],"type":"Point"}
}