{
  "type": "Feature",
  "properties": {
    "addr:full":"Calle de Puentelarra, 7 Madrid Madrid 28031",
    "addr:housenumber":"7",
    "addr:postcode":"madrid;28031",
    "addr:street":"Calle De Puentelarra",
    "iso:country":"ES",
    "sg:address":"Calle de Puentelarra, 7",
    "sg:city":"Madrid",
    "sg:orig_category":"Tintes (fabricaci\u00d3n, Al Por Mayor)",
    "sg:phone":"+34 913 31 33 70",
    "sg:postcode":"28031",
    "sg:province":"Madrid",
    "wof:name":"Gonzalez Vazquez Francisco",
    "wof:placetype":"venue"
},
  "geometry": {"coordinates":[-3.6090099812,40.3824729919],"type":"Point"}
}