{
  "type": "Feature",
  "properties": {
    "addr:full":"Calle de Sol, 43 Plasencia C\u00e1ceres 10600",
    "addr:housenumber":"43",
    "addr:postcode":"10600",
    "addr:street":"Calle De Sol;Ca\u0301Ceres",
    "iso:country":"ES",
    "sg:address":"Calle de Sol, 43",
    "sg:city":"Plasencia",
    "sg:classifiers":[
        {
            "category":"Shopping",
            "subcategory":"Clothing, Apparel, & Fashions",
            "type":"Retail Goods"
        }
    ],
    "sg:phone":"+34 927 42 26 58",
    "sg:postcode":"10600",
    "sg:province":"C\u00e1ceres",
    "sg:tags":[
        "boutique"
    ],
    "wof:name":"Juan Fuentes E Hijos S.a.",
    "wof:placetype":"venue"
},
  "geometry": {"coordinates":[-6.0860199928,40.0307388306],"type":"Point"}
}