{
  "type": "Feature",
  "properties": {
    "iso:country":"ES",
    "sg:address":"Av Republica Argentina, 38",
    "sg:city":"Barcelona",
    "sg:orig_category":"Agencias Y Agentes Comerciales, Representantes",
    "sg:phone":"+34 932 12 28 41",
    "sg:postcode":"08023",
    "sg:province":"Barcelona",
    "wof:name":"Sanchez Gonzalez Andres",
    "wof:placetype":"venue"
},
  "geometry": {"coordinates":[2.1471838951,41.4088401794],"type":"Point"}
}