{
  "type": "Feature",
  "properties": {
    "addr:full":"Urb Robles (los), 2 Saron Cantabria 39620",
    "addr:housenumber":"2",
    "addr:postcode":"39620",
    "addr:street":"Urb Robles Los",
    "iso:country":"ES",
    "sg:address":"Urb Robles (los), 2",
    "sg:city":"Saron",
    "sg:orig_category":"Farmacias",
    "sg:phone":"+34 942 56 30 28",
    "sg:postcode":"39620",
    "sg:province":"Cantabria",
    "wof:name":"Higuera Anuarbe Antonio",
    "wof:placetype":"venue"
},
  "geometry": {"coordinates":[-3.8540782928,43.3238258362],"type":"Point"}
}