{
  "type": "Feature",
  "properties": {
    "addr:full":"Calle de Triana, 83 Palmas De Gran Canaria Las Palmas 35002",
    "addr:housenumber":"83",
    "addr:postcode":"35002",
    "addr:street":"Calle De Triana",
    "iso:country":"ES",
    "sg:address":"Calle de Triana, 83",
    "sg:city":"Palmas De Gran Canaria",
    "sg:orig_category":"Cajas De Ahorro",
    "sg:phone":"+34 928 36 84 12",
    "sg:postcode":"35002",
    "sg:province":"Las Palmas",
    "wof:name":"Caixa D'estalvis I Pensions De Barcelona",
    "wof:placetype":"venue"
},
  "geometry": {"coordinates":[-15.4166259766,28.1064987183],"type":"Point"}
}