{
  "type": "Feature",
  "properties": {
    "addr:full":"Carrer de Sardenya, 499 Barcelona Barcelona 08024",
    "addr:housenumber":"499",
    "addr:postcode":"08024",
    "addr:street":"Carrer De Sardenya",
    "iso:country":"ES",
    "sg:address":"Carrer de Sardenya, 499",
    "sg:city":"Barcelona",
    "sg:orig_category":"Institutos De Belleza",
    "sg:phone":"+34 932 84 74 72",
    "sg:postcode":"08024",
    "sg:province":"Barcelona",
    "wof:name":"Vila Armengol Maria Del Carmen",
    "wof:placetype":"venue"
},
  "geometry": {"coordinates":[2.1639900208,41.4102935791],"type":"Point"}
}