{
  "type": "Feature",
  "properties": {
    "iso:country":"ES",
    "sg:address":"Pl Major, 10",
    "sg:city":"Tarrega",
    "sg:orig_category":"Sindicatos Y Colegios Profesionales",
    "sg:phone":"+34 973 31 17 56",
    "sg:postcode":"25300",
    "sg:province":"Lleida",
    "wof:name":"Foment Targari",
    "wof:placetype":"venue"
},
  "geometry": {"coordinates":[1.1394870281,41.6461753845],"type":"Point"}
}