{
  "type": "Feature",
  "properties": {
    "iso:country":"ES",
    "sg:address":"Calle de Arrayanes, 10",
    "sg:city":"Martos",
    "sg:orig_category":"Laboratorios Y Trabajos De Fotograf\u00cda, V\u00cddeo Y Cine",
    "sg:phone":"+34 953 55 30 18",
    "sg:postcode":"23600",
    "sg:province":"Ja\u00e9n",
    "wof:name":"Torre Fernandez Inmaculada De La",
    "wof:placetype":"venue"
},
  "geometry": {"coordinates":[-3.9740788937,37.7195587158],"type":"Point"}
}