{
  "type": "Feature",
  "properties": {
    "addr:full":"Calle de Nu\u00d1ez De Balboa, 101 Madrid Madrid 28006",
    "addr:housenumber":"101",
    "addr:postcode":"28006",
    "addr:street":"Calle De Nun\u0303Ez De Balboa",
    "iso:country":"ES",
    "sg:address":"Calle de Nu\u00d1ez De Balboa, 101",
    "sg:city":"Madrid",
    "sg:orig_category":"Centros Empresariales",
    "sg:phone":"+34 917 45 15 30",
    "sg:postcode":"28006",
    "sg:province":"Madrid",
    "wof:name":"Union Espa\u00f1ola De Entidades Aseguradoras Rea",
    "wof:placetype":"venue"
},
  "geometry": {"coordinates":[-3.6821110249,40.435295105],"type":"Point"}
}