{
  "type": "Feature",
  "properties": {
    "iso:country":"ES",
    "sg:address":"Carrer de Mallorca, 550",
    "sg:city":"Barcelona",
    "sg:orig_category":"Muebles",
    "sg:phone":"+34 932 65 38 72",
    "sg:postcode":"08026",
    "sg:province":"Barcelona",
    "wof:name":"Moreno Rivera Francisco Javier",
    "wof:placetype":"venue"
},
  "geometry": {"coordinates":[2.1828939915,41.4089279175],"type":"Point"}
}