{
  "type": "Feature",
  "properties": {
    "iso:country":"ES",
    "sg:address":"Senda Granada, S/n",
    "sg:city":"Espinardo",
    "sg:orig_category":"Formaci\u00d3n Continuada (variada)",
    "sg:phone":"+34 968 83 24 53",
    "sg:postcode":"30100",
    "sg:province":"Murcia",
    "wof:name":"Fundacion Laboral De La Construccion",
    "wof:placetype":"venue"
},
  "geometry": {"coordinates":[-1.1423859596,38.0058135986],"type":"Point"}
}