{
  "type": "Feature",
  "properties": {
    "iso:country":"ES",
    "sg:address":"Calle de Ruiz De Alda, 23",
    "sg:city":"Palmas De Gran Canaria",
    "sg:orig_category":"Venta, Montaje De Neum\u00c1ticos",
    "sg:phone":"+34 928 26 64 59",
    "sg:postcode":"35007",
    "sg:province":"Las Palmas",
    "wof:name":"Guillen De Leon Manuel",
    "wof:placetype":"venue"
},
  "geometry": {"coordinates":[-15.4335708618,28.1354866028],"type":"Point"}
}