{
  "type": "Feature",
  "properties": {
    "addr:full":"Poli Industrial Isasia, 8 Alsasua Navarra 31800",
    "addr:housenumber":"8",
    "addr:postcode":"31800",
    "addr:street":"Isasia",
    "iso:country":"ES",
    "sg:address":"Poli Industrial Isasia, 8",
    "sg:city":"Alsasua",
    "sg:orig_category":"Instalaci\u00d3n De Sanitarios",
    "sg:phone":"+34 948 46 88 00",
    "sg:postcode":"31800",
    "sg:province":"Navarra",
    "wof:name":"Ambulancias Baztan Bidasoa S.l.",
    "wof:placetype":"venue"
},
  "geometry": {"coordinates":[-2.1941597462,42.9304695129],"type":"Point"}
}