{
  "type": "Feature",
  "properties": {
    "iso:country":"ES",
    "sg:address":"C/ Cami Dels Magros, 64",
    "sg:city":"Elche",
    "sg:orig_category":"Carnicer\u00cdas, Carnicer\u00cdas",
    "sg:phone":"+34 965 46 43 92",
    "sg:postcode":"03206",
    "sg:province":"Alicante",
    "wof:name":"Aguado Rives Jose",
    "wof:placetype":"venue"
},
  "geometry": {"coordinates":[-0.7050392032,38.2748527527],"type":"Point"}
}