{
  "type": "Feature",
  "properties": {
    "addr:full":"Avda Tagomago, 5 Cala D'or Islas Baleares 07660",
    "addr:housenumber":"5",
    "addr:postcode":"07660",
    "addr:street":"Avda Tagomago",
    "iso:country":"ES",
    "sg:address":"Avda Tagomago, 5",
    "sg:city":"Cala D'or",
    "sg:orig_category":"Lencer\u00cda Femenina, Corseter\u00cda, Trajes De Ba\u00d1o (al Por Menor)",
    "sg:phone":"+34 971 65 80 34",
    "sg:postcode":"07660",
    "sg:province":"Islas Baleares",
    "wof:name":"Albarez  Alexsandra",
    "wof:placetype":"venue"
},
  "geometry": {"coordinates":[3.2297353745,39.3741035461],"type":"Point"}
}