{
  "type": "Feature",
  "properties": {
    "iso:country":"ES",
    "sg:address":"San Antonio, S/n",
    "sg:city":"Bre\u00f1a Baja",
    "sg:orig_category":"Autob\u00das (explotaci\u00d3n Y Servicios De)",
    "sg:phone":"+34 922 43 49 27",
    "sg:postcode":"38712",
    "sg:province":"Santa Cruz De Tenerife",
    "wof:name":"Transportes Insular La Palma S.coop.",
    "wof:placetype":"venue"
},
  "geometry": {"coordinates":[-17.7666397095,28.6466846466],"type":"Point"}
}