{
  "type": "Feature",
  "properties": {
    "iso:country":"ES",
    "sg:address":"Calle de Roll Del Colomer, S/n",
    "sg:city":"Rafelbunyol",
    "sg:orig_category":"Aluminio Y Aleaciones (producci\u00d3n, Transformaci\u00d3n, Negocio)",
    "sg:phone":"+34 961 41 32 05",
    "sg:postcode":"46138",
    "sg:province":"Valencia",
    "sg:website":"www.inalum.com",
    "wof:name":"Aluminios Inalum S. L.",
    "wof:placetype":"venue"
},
  "geometry": {"coordinates":[-0.3280330896,39.5856018066],"type":"Point"}
}