{
  "type": "Feature",
  "properties": {
    "iso:country":"ES",
    "sg:address":"Ctra Torralba, Km. 0000,0",
    "sg:city":"Malagon",
    "sg:orig_category":"Agentes, Concesionarios Y Sucursales De Veh\u00cdculos",
    "sg:phone":"+34 926 80 23 40",
    "sg:postcode":"13420",
    "sg:province":"Ciudad Real",
    "wof:name":"Nicolas Y Baltasar Automoviles S.l.",
    "wof:placetype":"venue"
},
  "geometry": {"coordinates":[-3.8483459949,39.1595840454],"type":"Point"}
}