{
  "type": "Feature",
  "properties": {
    "addr:full":"Plaz Espa\u00d1a, 1 Alacant Alicante 03004",
    "addr:housenumber":"1",
    "addr:postcode":"03004",
    "addr:street":"Plaz Espan\u0303A",
    "iso:country":"ES",
    "sg:address":"Plaz Espa\u00d1a, 1",
    "sg:city":"Alacant",
    "sg:orig_category":"Cl\u00cdnicas Dentales",
    "sg:phone":"+34 965 21 59 12",
    "sg:postcode":"03004",
    "sg:province":"Alicante",
    "wof:name":"Poveda Llopis Rafael",
    "wof:placetype":"venue"
},
  "geometry": {"coordinates":[-0.4849750102,38.3511009216],"type":"Point"}
}