{
  "type": "Feature",
  "properties": {
    "addr:full":"La Ni\u00f1a, 47 Mairena Aljarafe Sevilla 41927",
    "addr:housenumber":"47",
    "addr:postcode":"41927",
    "addr:street":"Nin\u0303A",
    "iso:country":"ES",
    "sg:address":"La Ni\u00f1a, 47",
    "sg:city":"Mairena Aljarafe",
    "sg:orig_category":"Inform\u00c1tica (estudios, Servicios, Asesor\u00cda, Formaci\u00d3n)",
    "sg:phone":"+34 955 60 14 30",
    "sg:postcode":"41927",
    "sg:province":"Sevilla",
    "sg:website":"www.timberlakeconsulting.com",
    "wof:name":"Timberlake Consulting S.l.",
    "wof:placetype":"venue"
},
  "geometry": {"coordinates":[-6.0518398285,37.3519630432],"type":"Point"}
}