{
  "type": "Feature",
  "properties": {
    "addr:full":"Calle de Juan De Urbieta, 27 Madrid Madrid 28007",
    "addr:housenumber":"27",
    "addr:postcode":"madrid;28007",
    "addr:street":"Calle De Juan De Urbieta",
    "iso:country":"ES",
    "sg:address":"Calle de Juan De Urbieta, 27",
    "sg:city":"Madrid",
    "sg:orig_category":"Centros Empresariales",
    "sg:phone":"+34 915 01 30 27",
    "sg:postcode":"28007",
    "sg:province":"Madrid",
    "wof:name":"Prado Ruiz Santaella Maria Del Carmen",
    "wof:placetype":"venue"
},
  "geometry": {"coordinates":[-3.6766290665,40.405834198],"type":"Point"}
}