{
  "type": "Feature",
  "properties": {
    "iso:country":"ES",
    "sg:address":"Calle de Padre Manjon, 32",
    "sg:city":"Zaragoza",
    "sg:orig_category":"M\u00c1rmoles, Granitos Y Piedras Naturales",
    "sg:phone":"+34 976 33 84 45",
    "sg:postcode":"50010",
    "sg:province":"Zaragoza",
    "wof:name":"Hernandez Oliver Isabel Maria",
    "wof:placetype":"venue"
},
  "geometry": {"coordinates":[-0.9035149813,41.6531028748],"type":"Point"}
}