{
  "type": "Feature",
  "properties": {
    "iso:country":"ES",
    "sg:address":"C/ Asuncion Parre\u00d1o Garcia, 6",
    "sg:city":"Elche",
    "sg:orig_category":"Molduras, Junquillos, Listones Y Molduras Perforadas",
    "sg:phone":"+34 965 43 07 92",
    "sg:postcode":"03205",
    "sg:province":"Alicante",
    "wof:name":"Blanes Sanchez Juan",
    "wof:placetype":"venue"
},
  "geometry": {"coordinates":[-0.7105569839,38.2715759277],"type":"Point"}
}