{
  "type": "Feature",
  "properties": {
    "addr:full":"Plaz Caudillo, 1 Honrubia Cuenca 16730",
    "addr:housenumber":"1",
    "addr:postcode":"16730",
    "addr:street":"Caudillo",
    "iso:country":"ES",
    "sg:address":"Plaz Caudillo, 1",
    "sg:city":"Honrubia",
    "sg:orig_category":"Abogados",
    "sg:phone":"+34 969 29 20 01",
    "sg:postcode":"16730",
    "sg:province":"Cuenca",
    "wof:name":"Ayuntamiento De Honrubia",
    "wof:placetype":"venue"
},
  "geometry": {"coordinates":[-2.3025538921,39.5436019897],"type":"Point"}
}