{
  "type": "Feature",
  "properties": {
    "addr:full":"Avda Santa Caterina, 14 Teulada Alicante 03725",
    "addr:housenumber":"14",
    "addr:postcode":"03725",
    "addr:street":"Avda Santa Caterina",
    "iso:country":"ES",
    "sg:address":"Avda Santa Caterina, 14",
    "sg:city":"Teulada",
    "sg:orig_category":"Papeler\u00cdas, Librer\u00cdas",
    "sg:phone":"+34 965 74 04 34",
    "sg:postcode":"03725",
    "sg:province":"Alicante",
    "wof:name":"Vidal Mayans Paqui",
    "wof:placetype":"venue"
},
  "geometry": {"coordinates":[0.1046999991,38.7285995483],"type":"Point"}
}