{
  "type": "Feature",
  "properties": {
    "iso:country":"ES",
    "sg:address":"Bard Aljariz, 133",
    "sg:city":"Aljariz",
    "sg:orig_category":"Promotores Constructores",
    "sg:phone":"+34 950 45 35 65",
    "sg:postcode":"04628",
    "sg:province":"Almer\u00eda",
    "wof:name":"Pedro Antonio Casta\u00f1o S.l.",
    "wof:placetype":"venue"
},
  "geometry": {"coordinates":[-1.9216589928,37.2441215515],"type":"Point"}
}