{
  "type": "Feature",
  "properties": {
    "addr:full":"Calle de Fuente (la), 3 Villafranca Segovia 40318",
    "addr:housenumber":"3",
    "addr:postcode":"40318",
    "addr:street":"Calle De Fuente La",
    "iso:country":"ES",
    "sg:address":"Calle de Fuente (la), 3",
    "sg:city":"Villafranca",
    "sg:orig_category":"Restaurantes",
    "sg:phone":"+34 921 53 11 11",
    "sg:postcode":"40318",
    "sg:province":"Segovia",
    "wof:name":"Asador David S.l.",
    "wof:placetype":"venue"
},
  "geometry": {"coordinates":[-3.7488400936,41.2599067688],"type":"Point"}
}