{
  "type": "Feature",
  "properties": {
    "addr:full":"Pla\u00c7 Mercat De La Miraculosa, S/n Picassent Valencia 46220",
    "addr:housenumber":"s",
    "addr:postcode":"46220",
    "addr:street":"/ N",
    "iso:country":"ES",
    "sg:address":"Pla\u00c7 Mercat De La Miraculosa, S/n",
    "sg:city":"Picassent",
    "sg:orig_category":"Carnicer\u00cdas, Carnicer\u00cdas",
    "sg:phone":"+34 961 23 01 89",
    "sg:postcode":"46220",
    "sg:province":"Valencia",
    "wof:name":"Guerola Pla Joaquin",
    "wof:placetype":"venue"
},
  "geometry": {"coordinates":[-0.4974358976,39.3506889343],"type":"Point"}
}