{
  "type": "Feature",
  "properties": {
    "addr:full":"Carrer de Amposta, 3 Torreforta Tarragona 43006",
    "addr:housenumber":"3",
    "addr:postcode":"43006",
    "addr:street":"Carrer De Amposta",
    "iso:country":"ES",
    "sg:address":"Carrer de Amposta, 3",
    "sg:city":"Torreforta",
    "sg:orig_category":"Inmobiliaria (agencias)",
    "sg:phone":"+34 977 55 36 72",
    "sg:postcode":"43006",
    "sg:province":"Tarragona",
    "wof:name":"Tarraco Inmobiliaria Del Hogar S.l.",
    "wof:placetype":"venue"
},
  "geometry": {"coordinates":[1.2169630527,41.1174240112],"type":"Point"}
}