{
  "type": "Feature",
  "properties": {
    "addr:full":"Carrer de Nou De La Rambla, 83 Barcelona Barcelona 08001",
    "addr:housenumber":"83",
    "addr:postcode":"08001",
    "addr:street":"Carrer De Nou De La Rambla",
    "iso:country":"ES",
    "sg:address":"Carrer de Nou De La Rambla, 83",
    "sg:city":"Barcelona",
    "sg:orig_category":"Librer\u00cdas",
    "sg:phone":"+34 934 42 30 34",
    "sg:postcode":"08001",
    "sg:province":"Barcelona",
    "wof:name":"Berto Pastor Maria",
    "wof:placetype":"venue"
},
  "geometry": {"coordinates":[2.1712720394,41.376033783],"type":"Point"}
}