{
  "type": "Feature",
  "properties": {
    "iso:country":"ES",
    "sg:address":"Pl Jaume Balmes, 2",
    "sg:city":"Gava",
    "sg:orig_category":"Reposter\u00cdas",
    "sg:phone":"+34 936 62 50 02",
    "sg:postcode":"08850",
    "sg:province":"Barcelona",
    "wof:name":"Forn M. Cruz S. L.",
    "wof:placetype":"venue"
},
  "geometry": {"coordinates":[1.9997589588,41.3035392761],"type":"Point"}
}