{
  "type": "Feature",
  "properties": {
    "addr:full":"Carrer de Ausias Marc, 157 Barcelona Barcelona 08013",
    "addr:housenumber":"157",
    "addr:postcode":"08013",
    "addr:street":"Carrer De Ausias Marc",
    "iso:country":"ES",
    "sg:address":"Carrer de Ausias Marc, 157",
    "sg:city":"Barcelona",
    "sg:orig_category":"Centros Empresariales",
    "sg:phone":"+34 932 65 50 04",
    "sg:postcode":"08013",
    "sg:province":"Barcelona",
    "wof:name":"Izquierdo Velasco Diego",
    "wof:placetype":"venue"
},
  "geometry": {"coordinates":[2.1839530468,41.3977737427],"type":"Point"}
}