{
  "type": "Feature",
  "properties": {
    "addr:full":"Calle de Roble, 12 Valladolid Valladolid 47009",
    "addr:housenumber":"12",
    "addr:postcode":"47009",
    "addr:street":"Calle De Roble",
    "iso:country":"ES",
    "sg:address":"Calle de Roble, 12",
    "sg:city":"Valladolid",
    "sg:orig_category":"Empresas De Demolici\u00d3n",
    "sg:phone":"+34 983 33 19 17",
    "sg:postcode":"47009",
    "sg:province":"Valladolid",
    "wof:name":"Aldemasan S.l.",
    "wof:placetype":"venue"
},
  "geometry": {"coordinates":[-4.7302150726,41.6701583862],"type":"Point"}
}