{
  "type": "Feature",
  "properties": {
    "addr:full":"Carrer de Montserrat, 2 Papiol Barcelona 08754",
    "addr:housenumber":"2",
    "addr:postcode":"08754",
    "addr:street":"Carrer De Montserrat",
    "iso:country":"ES",
    "sg:address":"Carrer de Montserrat, 2",
    "sg:city":"Papiol",
    "sg:orig_category":"Cajas De Ahorro",
    "sg:phone":"+34 936 73 01 84",
    "sg:postcode":"08754",
    "sg:province":"Barcelona",
    "sg:website":"www.lacaixa.es",
    "wof:name":"Caixa D'estalvis Del Penedes",
    "wof:placetype":"venue"
},
  "geometry": {"coordinates":[2.0113239288,41.439617157],"type":"Point"}
}