{
  "type": "Feature",
  "properties": {
    "iso:country":"ES",
    "sg:address":"Calle de Angel Senra, 12",
    "sg:city":"Coru\u00d1a",
    "sg:orig_category":"Lanas (al Por Menor)",
    "sg:phone":"+34 981 23 42 73",
    "sg:postcode":"15007",
    "sg:province":"La Coru\u00f1a",
    "wof:name":"Mujico Rodriguez Maria Ofelia",
    "wof:placetype":"venue"
},
  "geometry": {"coordinates":[-8.4095602036,43.3551673889],"type":"Point"}
}