{
  "type": "Feature",
  "properties": {
    "iso:country":"ES",
    "sg:address":"Aptos. Polo, 10",
    "sg:city":"Sotogrande",
    "sg:orig_category":"Centros Empresariales",
    "sg:phone":"+34 956 69 54 50",
    "sg:postcode":"11310",
    "sg:province":"C\u00e1diz",
    "wof:name":"Chapami S.l.",
    "wof:placetype":"venue"
},
  "geometry": {"coordinates":[-5.2829370499,36.2767448425],"type":"Point"}
}