{
  "type": "Feature",
  "properties": {
    "iso:country":"ES",
    "sg:address":"Carrer de Doctor Trueta, 210",
    "sg:city":"Barcelona",
    "sg:orig_category":"Confecci\u00d3n (fabricaci\u00d3n, Al Por Mayor)",
    "sg:phone":"+34 932 24 07 04",
    "sg:postcode":"08005",
    "sg:province":"Barcelona",
    "wof:name":"Urban Clothing S.l.",
    "wof:placetype":"venue"
},
  "geometry": {"coordinates":[2.2033479214,41.3983154297],"type":"Point"}
}