{
  "type": "Feature",
  "properties": {
    "iso:country":"ES",
    "sg:address":"Poligono Industrial La Palmera, 33",
    "sg:city":"Dos Hermanas",
    "sg:orig_category":"Fabricaci\u00d3n De Muebles",
    "sg:phone":"+34 954 69 16 01",
    "sg:postcode":"41700",
    "sg:province":"Sevilla",
    "wof:name":"Tapizados La Palmera Sll",
    "wof:placetype":"venue"
},
  "geometry": {"coordinates":[-5.9281339645,37.2829055786],"type":"Point"}
}