{
  "type": "Feature",
  "properties": {
    "addr:full":"Barr Gilera, 29 Cerrazo Cantabria 39539",
    "addr:housenumber":"29",
    "addr:postcode":"39539",
    "addr:street":"Gilera",
    "iso:country":"ES",
    "sg:address":"Barr Gilera, 29",
    "sg:city":"Cerrazo",
    "sg:orig_category":"Molduras, Junquillos, Listones Y Molduras Perforadas",
    "sg:phone":"+34 942 83 87 53",
    "sg:postcode":"39539",
    "sg:province":"Cantabria",
    "wof:name":"Ciaboga,s.c.",
    "wof:placetype":"venue"
},
  "geometry": {"coordinates":[-4.1089868546,43.3644638062],"type":"Point"}
}