{
  "type": "Feature",
  "properties": {
    "addr:full":"Carretera De Campillos-ronda, Km. 0015,0 Teba M\u00e1laga 29327",
    "addr:postcode":"29327",
    "addr:street":"Carretera De Campillos-Ronda Km. 0015,0;Ma\u0301Laga",
    "iso:country":"ES",
    "sg:address":"Carretera De Campillos-ronda, Km. 0015,0",
    "sg:city":"Teba",
    "sg:orig_category":"Limpieza Industrial",
    "sg:phone":"+34 952 74 85 09",
    "sg:postcode":"29327",
    "sg:province":"M\u00e1laga",
    "wof:name":"Latinteba Rent S.l.",
    "wof:placetype":"venue"
},
  "geometry": {"coordinates":[-4.9202542305,36.9836158752],"type":"Point"}
}