{
  "type": "Feature",
  "properties": {
    "addr:full":"Calle de Caldereros, 1 Villa Rio C\u00f3rdoba 14640",
    "addr:housenumber":"1",
    "addr:postcode":"14640",
    "addr:street":"Calle De Caldereros;Villa Rio Co\u0301Rdoba",
    "iso:country":"ES",
    "sg:address":"Calle de Caldereros, 1",
    "sg:city":"Villa Rio",
    "sg:orig_category":"Material Y Equipo Para Panader\u00cdas Y Pasteler\u00cdas",
    "sg:phone":"+34 957 17 62 27",
    "sg:postcode":"14640",
    "sg:province":"C\u00f3rdoba",
    "wof:name":"Cantero Cantero Antonio",
    "wof:placetype":"venue"
},
  "geometry": {"coordinates":[-4.2867097855,37.9817123413],"type":"Point"}
}