{
  "type": "Feature",
  "properties": {
    "iso:country":"ES",
    "sg:address":"Calle de Emeterio Cuadrado, 9",
    "sg:city":"Mula",
    "sg:orig_category":"Florister\u00cdas",
    "sg:phone":"+34 968 66 19 42",
    "sg:postcode":"30170",
    "sg:province":"Murcia",
    "wof:name":"Aparicio Hurtado Jose Maria",
    "wof:placetype":"venue"
},
  "geometry": {"coordinates":[-1.4944075346,38.0397529602],"type":"Point"}
}