{
  "type": "Feature",
  "properties": {
    "addr:full":"C/ Enrique Pire Garcia, 13 Elche Alicante 03204",
    "addr:housenumber":"13",
    "addr:postcode":"03204",
    "addr:street":"C / Enrique Pire Garcia",
    "iso:country":"ES",
    "sg:address":"C/ Enrique Pire Garcia, 13",
    "sg:city":"Elche",
    "sg:orig_category":"Electricidad: Instaladores",
    "sg:phone":"+34 966 63 29 69",
    "sg:postcode":"03204",
    "sg:province":"Alicante",
    "wof:name":"Electricidad Giber S.l.u.",
    "wof:placetype":"venue"
},
  "geometry": {"coordinates":[-0.7036759853,38.2563858032],"type":"Point"}
}