{
  "type": "Feature",
  "properties": {
    "addr:full":"Calle de Angel Cecilia, 3 Burgo Osma Soria 42300",
    "addr:housenumber":"3",
    "addr:postcode":"42300",
    "addr:street":"Calle De Angel Cecilia",
    "iso:country":"ES",
    "sg:address":"Calle de Angel Cecilia, 3",
    "sg:city":"Burgo Osma",
    "sg:classifiers":[
        {
            "category":"Taxi",
            "type":"Transportation"
        }
    ],
    "sg:phone":"+34 975 34 07 65",
    "sg:postcode":"42300",
    "sg:province":"Soria",
    "wof:name":"Cecilia Frias Jose Maria",
    "wof:placetype":"venue"
},
  "geometry": {"coordinates":[-3.0662586689,41.5870857239],"type":"Point"}
}