{
  "type": "Feature",
  "properties": {
    "iso:country":"ES",
    "sg:address":"Calle de Almazan, 6",
    "sg:city":"Alcala Henares",
    "sg:orig_category":"Promotores Constructores",
    "sg:phone":"+34 918 88 09 29",
    "sg:postcode":"28802",
    "sg:province":"Madrid",
    "wof:name":"Grupo Fiscal Maritimo S.a.",
    "wof:placetype":"venue"
},
  "geometry": {"coordinates":[-3.3717648983,40.4802894592],"type":"Point"}
}