{
  "type": "Feature",
  "properties": {
    "addr:full":"Carrer de Sepulveda, 80 Barcelona Barcelona 08015",
    "addr:housenumber":"80",
    "addr:postcode":"08015",
    "addr:street":"Carrer De Sepulveda",
    "iso:country":"ES",
    "sg:address":"Carrer de Sepulveda, 80",
    "sg:city":"Barcelona",
    "sg:orig_category":"M\u00c9dicos: Ginecolog\u00cda M\u00c9dica, Obstetricia",
    "sg:phone":"+34 934 26 97 34",
    "sg:postcode":"08015",
    "sg:province":"Barcelona",
    "wof:name":"Centro Casanovas De Ginecologia Y Planificacion Familiar S.l.",
    "wof:placetype":"venue"
},
  "geometry": {"coordinates":[2.1564049721,41.3785400391],"type":"Point"}
}