{
  "type": "Feature",
  "properties": {
    "iso:country":"ES",
    "sg:address":"Calle de Honduras, 8",
    "sg:city":"Vitoria-gasteiz",
    "sg:orig_category":"Psic\u00d3logos",
    "sg:phone":"+34 945 24 89 30",
    "sg:postcode":"01012",
    "sg:province":"\u00c1lava",
    "wof:name":"Urquizu Aranaga Javier",
    "wof:placetype":"venue"
},
  "geometry": {"coordinates":[-2.6775500774,42.8551483154],"type":"Point"}
}