{
  "type": "Feature",
  "properties": {
    "addr:full":"Carr Hospital, 21 Torroella Montgri Girona 17257",
    "addr:housenumber":"21",
    "addr:postcode":"17257",
    "addr:street":"Carr Hospital",
    "iso:country":"ES",
    "sg:address":"Carr Hospital, 21",
    "sg:city":"Torroella Montgri",
    "sg:orig_category":"Agencias Y Agentes Comerciales, Representantes",
    "sg:phone":"+34 972 76 01 61",
    "sg:postcode":"17257",
    "sg:province":"Girona",
    "wof:name":"Fmv Comercial S.l.",
    "wof:placetype":"venue"
},
  "geometry": {"coordinates":[3.1277420521,42.042766571],"type":"Point"}
}