{
  "type": "Feature",
  "properties": {
    "addr:full":"C/ Almansa, S/n Elche Alicante 03291",
    "addr:housenumber":"s / n",
    "addr:postcode":"03291",
    "addr:street":"C / Almansa",
    "iso:country":"ES",
    "sg:address":"C/ Almansa, S/n",
    "sg:city":"Elche",
    "sg:orig_category":"Zapatos (al Por Mayor)",
    "sg:phone":"+34 966 67 51 50",
    "sg:postcode":"03291",
    "sg:province":"Alicante",
    "wof:name":"Espa\u00f1a Valtinellis S.l.",
    "wof:placetype":"venue"
},
  "geometry": {"coordinates":[-0.6765189767,38.2994346619],"type":"Point"}
}