{
  "type": "Feature",
  "properties": {
    "iso:country":"ES",
    "sg:address":"Carrer de Sardenya, 363",
    "sg:city":"Barcelona",
    "sg:orig_category":"Carnicer\u00cdas, Carnicer\u00cdas",
    "sg:phone":"+34 934 57 06 18",
    "sg:postcode":"08025",
    "sg:province":"Barcelona",
    "wof:name":"Orihuela Santos Francisco Javier",
    "wof:placetype":"venue"
},
  "geometry": {"coordinates":[2.1699340343,41.405796051],"type":"Point"}
}