{
  "type": "Feature",
  "properties": {
    "addr:full":"Calle de Jarama, S/n Velilla S.antonio Madrid 28891",
    "addr:housenumber":"s",
    "addr:postcode":"28891",
    "addr:street":"Calle De Jarama;/ N",
    "iso:country":"ES",
    "sg:address":"Calle de Jarama, S/n",
    "sg:city":"Velilla S.antonio",
    "sg:orig_category":"Artes Gr\u00c1ficas, Artes Pl\u00c1sticas (curso)",
    "sg:phone":"+34 916 60 72 80",
    "sg:postcode":"28891",
    "sg:province":"Madrid",
    "wof:name":"Serrano Delgado Y Cia S. L.",
    "wof:placetype":"venue"
},
  "geometry": {"coordinates":[-3.4882860184,40.36510849],"type":"Point"}
}