{
  "type": "Feature",
  "properties": {
    "addr:full":"Calle de Encina, 53 Tolox M\u00e1laga 29109",
    "addr:housenumber":"53",
    "addr:postcode":"29109",
    "addr:street":"Calle De Encina",
    "iso:country":"ES",
    "sg:address":"Calle de Encina, 53",
    "sg:city":"Tolox",
    "sg:orig_category":"Loter\u00cda Y T\u00d3mbola",
    "sg:phone":"+34 952 48 73 35",
    "sg:postcode":"29109",
    "sg:province":"M\u00e1laga",
    "wof:name":"Vera Rey Juan",
    "wof:placetype":"venue"
},
  "geometry": {"coordinates":[-4.9052939415,36.6854972839],"type":"Point"}
}