{
  "type": "Feature",
  "properties": {
    "iso:country":"ES",
    "sg:address":"Pda Monte Horquera, 8",
    "sg:city":"Vilamarxant",
    "sg:orig_category":"Inmobiliaria (agencias)",
    "sg:phone":"+34 961 65 05 42",
    "sg:postcode":"46191",
    "sg:province":"Valencia",
    "wof:name":"Hierro Yubero Angel",
    "wof:placetype":"venue"
},
  "geometry": {"coordinates":[-0.6272540092,39.5677604675],"type":"Point"}
}