{
  "type": "Feature",
  "properties": {
    "addr:full":"Calle de Franco Tormo, 13 Valencia Valencia 46007",
    "addr:housenumber":"13",
    "addr:postcode":"46007",
    "addr:street":"Calle De Franco Tormo",
    "iso:country":"ES",
    "sg:address":"Calle de Franco Tormo, 13",
    "sg:city":"Valencia",
    "sg:orig_category":"Electrodom\u00c9sticos (al Por Menor)",
    "sg:phone":"+34 963 77 43 12",
    "sg:postcode":"46007",
    "sg:province":"Valencia",
    "wof:name":"Varelec Sociedad Cooperativa Limitada",
    "wof:placetype":"venue"
},
  "geometry": {"coordinates":[-0.3911260068,39.4585113525],"type":"Point"}
}