{
  "type": "Feature",
  "properties": {
    "addr:full":"Calle de Aleman, 11 Barcarrota Badajoz 06160",
    "addr:housenumber":"11",
    "addr:postcode":"06160",
    "addr:street":"Calle De Aleman",
    "iso:country":"ES",
    "sg:address":"Calle de Aleman, 11",
    "sg:city":"Barcarrota",
    "sg:orig_category":"Quincaller\u00cda (al Por Menor)",
    "sg:phone":"+34 924 73 61 45",
    "sg:postcode":"06160",
    "sg:province":"Badajoz",
    "wof:name":"Contador Carvajal Maria Del Carmen",
    "wof:placetype":"venue"
},
  "geometry": {"coordinates":[-6.848927021,38.5165290833],"type":"Point"}
}