{
  "type": "Feature",
  "properties": {
    "addr:full":"Calle de Juan Ramon Jimenez, S/n Burgos Burgos 09007",
    "addr:postcode":"09007",
    "addr:street":"Calle De Juan Ramon Jimenez S / N",
    "iso:country":"ES",
    "sg:address":"Calle de Juan Ramon Jimenez, S/n",
    "sg:city":"Burgos",
    "sg:orig_category":"Rectificaci\u00d3n, Mecanizado, Fresado",
    "sg:phone":"+34 947 47 44 15",
    "sg:postcode":"09007",
    "sg:province":"Burgos",
    "wof:name":"Bsh Electrodomesticos Espa\u00d1a S.a.",
    "wof:placetype":"venue"
},
  "geometry": {"coordinates":[-3.662375927,42.347492218],"type":"Point"}
}