{
  "type": "Feature",
  "properties": {
    "addr:full":"Carrer de Bellavista (de La), 7 Castellbisbal Barcelona 08755",
    "addr:housenumber":"7",
    "addr:postcode":"08755",
    "addr:street":"Carrer De Bellavista De La",
    "iso:country":"ES",
    "sg:address":"Carrer de Bellavista (de La), 7",
    "sg:city":"Castellbisbal",
    "sg:orig_category":"Confecci\u00d3n (fabricaci\u00d3n, Al Por Mayor)",
    "sg:phone":"+34 937 72 21 12",
    "sg:postcode":"08755",
    "sg:province":"Barcelona",
    "wof:name":"Rocus S.l.",
    "wof:placetype":"venue"
},
  "geometry": {"coordinates":[1.9790949821,41.4717292786],"type":"Point"}
}