{
  "type": "Feature",
  "properties": {
    "addr:full":"Calle de Casillas De Gallego, 1 Alhama Granada Granada 18120",
    "addr:housenumber":"1",
    "addr:postcode":"18120",
    "addr:street":"Calle De Casillas De Gallego",
    "iso:country":"ES",
    "sg:address":"Calle de Casillas De Gallego, 1",
    "sg:city":"Alhama Granada",
    "sg:orig_category":"Empresas De Desmonte",
    "sg:phone":"+34 958 35 02 41",
    "sg:postcode":"18120",
    "sg:province":"Granada",
    "wof:name":"Martin Puertas Francisco",
    "wof:placetype":"venue"
},
  "geometry": {"coordinates":[-3.9918262959,37.0009384155],"type":"Point"}
}