{
  "type": "Feature",
  "properties": {
    "addr:full":"Calle de Chinchon, 311 Alcala Henares Madrid 28805",
    "addr:housenumber":"311",
    "addr:postcode":"28805",
    "addr:street":"Calle De Chinchon",
    "iso:country":"ES",
    "sg:address":"Calle de Chinchon, 311",
    "sg:city":"Alcala Henares",
    "sg:orig_category":"Mensajer\u00cda Express, Portes Internacionales",
    "sg:phone":"+34 918 77 60 80",
    "sg:postcode":"28805",
    "sg:province":"Madrid",
    "wof:name":"Servihenares S.l.",
    "wof:placetype":"venue"
},
  "geometry": {"coordinates":[-3.3495841026,40.4929847717],"type":"Point"}
}