{
  "type": "Feature",
  "properties": {
    "addr:full":"Carrer de Mallorca, 219 Barcelona Barcelona 08008",
    "addr:housenumber":"219",
    "addr:postcode":"08008",
    "addr:street":"Carrer De Mallorca",
    "iso:country":"ES",
    "sg:address":"Carrer de Mallorca, 219",
    "sg:city":"Barcelona",
    "sg:orig_category":"Asociaciones Y Clubs Deportivos",
    "sg:phone":"+34 934 53 67 88",
    "sg:postcode":"08008",
    "sg:province":"Barcelona",
    "wof:name":"Lan Chio Chuen Ping",
    "wof:placetype":"venue"
},
  "geometry": {"coordinates":[2.1588010788,41.3912010193],"type":"Point"}
}