{
  "type": "Feature",
  "properties": {
    "iso:country":"ES",
    "sg:address":"Avda Gran Capitan (del), 9",
    "sg:city":"Cordoba",
    "sg:orig_category":"Asesor\u00cda Fiscal Y Jur\u00cddica",
    "sg:phone":"+34 957 47 83 94",
    "sg:postcode":"14008",
    "sg:province":"C\u00f3rdoba",
    "wof:name":"Gil Cerezo Luisa Maria",
    "wof:placetype":"venue"
},
  "geometry": {"coordinates":[-4.7824478149,37.8869018555],"type":"Point"}
}