{
  "type": "Feature",
  "properties": {
    "addr:full":"Avda Espa\u00d1a, 17 Caceres C\u00e1ceres 10002",
    "addr:housenumber":"17",
    "addr:postcode":"10002",
    "addr:street":"Avda Espan\u0303A;Ca\u0301Ceres",
    "iso:country":"ES",
    "sg:address":"Avda Espa\u00d1a, 17",
    "sg:city":"Caceres",
    "sg:orig_category":"Perfumer\u00cda, Art\u00cdculos De Ba\u00d1o (fabricaci\u00d3n, Al Por Mayor)",
    "sg:phone":"+34 927 21 09 56",
    "sg:postcode":"10002",
    "sg:province":"C\u00e1ceres",
    "wof:name":"Duran Lasso Maria Pilar",
    "wof:placetype":"venue"
},
  "geometry": {"coordinates":[-6.3774561882,39.4704055786],"type":"Point"}
}