{
  "type": "Feature",
  "properties": {
    "iso:country":"ES",
    "sg:address":"Calle de Favila, 12",
    "sg:city":"Oviedo",
    "sg:orig_category":"Venta, Instalaci\u00d3n De Calefacci\u00d3n",
    "sg:phone":"+34 985 25 48 41",
    "sg:postcode":"33013",
    "sg:province":"Asturias",
    "wof:name":"Jeronimo Moran Juan Carlos",
    "wof:placetype":"venue"
},
  "geometry": {"coordinates":[-5.871612072,43.3652496338],"type":"Point"}
}