{
  "type": "Feature",
  "properties": {
    "addr:full":"Rua Vi\u00d1as, 2 Vi\u00d1as Pontevedra 36163",
    "addr:housenumber":"2",
    "addr:postcode":"36163",
    "addr:street":"Rua Vin\u0303As",
    "iso:country":"ES",
    "sg:address":"Rua Vi\u00d1as, 2",
    "sg:city":"Vi\u00d1as",
    "sg:orig_category":"Centros De Educaci\u00d3n Especial",
    "sg:phone":"+34 986 87 23 25",
    "sg:postcode":"36163",
    "sg:province":"Pontevedra",
    "wof:name":"Colexio Publico De Vi\u00f1as",
    "wof:placetype":"venue"
},
  "geometry": {"coordinates":[-8.6428003311,42.4304618835],"type":"Point"}
}