{
  "type": "Feature",
  "properties": {
    "addr:full":"La Sierra, 3 Cembranos Le\u00f3n 24231",
    "addr:housenumber":"3",
    "addr:postcode":"24231",
    "addr:street":"La Sierra;Leo\u0301N",
    "iso:country":"ES",
    "sg:address":"La Sierra, 3",
    "sg:city":"Cembranos",
    "sg:orig_category":"Molduras, Junquillos, Listones Y Molduras Perforadas",
    "sg:phone":"+34 987 30 38 04",
    "sg:postcode":"24231",
    "sg:province":"Le\u00f3n",
    "wof:name":"Santos Campano Eusebio",
    "wof:placetype":"venue"
},
  "geometry": {"coordinates":[-5.5841889381,42.5260047913],"type":"Point"}
}