{
  "type": "Feature",
  "properties": {
    "addr:full":"Calle de Carlos Iii, 19 Fuente Palmera C\u00f3rdoba 14120",
    "addr:housenumber":"19",
    "addr:postcode":"14120",
    "addr:street":"Calle De Carlos Iii",
    "iso:country":"ES",
    "sg:address":"Calle de Carlos Iii, 19",
    "sg:city":"Fuente Palmera",
    "sg:orig_category":"Supermercados Y Hipermercados",
    "sg:phone":"+34 957 63 86 46",
    "sg:postcode":"14120",
    "sg:province":"C\u00f3rdoba",
    "wof:name":"Rodriguez Lucena Juan",
    "wof:placetype":"venue"
},
  "geometry": {"coordinates":[-5.103957653,37.7053642273],"type":"Point"}
}