{
  "type": "Feature",
  "properties": {
    "addr:full":"Calle de Milagrosa, 15 Valencia Valencia 46009",
    "addr:housenumber":"15",
    "addr:postcode":"46009",
    "addr:street":"Calle De Milagrosa",
    "iso:country":"ES",
    "sg:address":"Calle de Milagrosa, 15",
    "sg:city":"Valencia",
    "sg:orig_category":"Distribuci\u00d3n De Petr\u00d3leo Y Derivados",
    "sg:phone":"+34 963 46 35 69",
    "sg:postcode":"46009",
    "sg:province":"Valencia",
    "wof:name":"Markoil S.a.",
    "wof:placetype":"venue"
},
  "geometry": {"coordinates":[-0.3735319078,39.4843559265],"type":"Point"}
}