{
  "type": "Feature",
  "properties": {
    "addr:full":"Carretera, S/n Montanuy Huesca 22524",
    "addr:postcode":"22524",
    "addr:street":"Carretera S / N",
    "iso:country":"ES",
    "sg:address":"Carretera, S/n",
    "sg:city":"Montanuy",
    "sg:orig_category":"Agricultores, Agricultores",
    "sg:phone":"+34 974 55 40 54",
    "sg:postcode":"22524",
    "sg:province":"Huesca",
    "wof:name":"Bordas Saura Agustin",
    "wof:placetype":"venue"
},
  "geometry": {"coordinates":[0.6613659859,42.457736969],"type":"Point"}
}