{
  "type": "Feature",
  "properties": {
    "iso:country":"ES",
    "sg:address":"Carrer de Femenies, 4",
    "sg:city":"Palma",
    "sg:orig_category":"Art\u00cdculos De Limpieza Y De Cocina (fabricaci\u00d3n, Al Por Mayor)",
    "sg:phone":"+34 971 73 19 68",
    "sg:postcode":"07013",
    "sg:province":"Islas Baleares",
    "wof:name":"Pericas Canaves Bartolome",
    "wof:placetype":"venue"
},
  "geometry": {"coordinates":[2.6406099796,39.5773124695],"type":"Point"}
}