{
  "type": "Feature",
  "properties": {
    "addr:full":"Calle de Hermanos Del Moral, 52 Madrid Madrid 28019",
    "addr:housenumber":"52",
    "addr:postcode":"madrid;28019",
    "addr:street":"Calle De Hermanos Del Moral",
    "iso:country":"ES",
    "sg:address":"Calle de Hermanos Del Moral, 52",
    "sg:city":"Madrid",
    "sg:orig_category":"Fotograf\u00cda Art\u00cdstica Y Retratos",
    "sg:phone":"+34 914 69 86 83",
    "sg:postcode":"28019",
    "sg:province":"Madrid",
    "wof:name":"Anton Marques Enrique",
    "wof:placetype":"venue"
},
  "geometry": {"coordinates":[-3.7215945721,40.391078949],"type":"Point"}
}