{
  "type": "Feature",
  "properties": {
    "addr:full":"Av Escoles (de Les), S/n Vilanova D'escornalbou Tarragona 43311",
    "addr:housenumber":"s",
    "addr:postcode":"43311",
    "addr:street":"Av Escoles De Les;/ N",
    "iso:country":"ES",
    "sg:address":"Av Escoles (de Les), S/n",
    "sg:city":"Vilanova D'escornalbou",
    "sg:orig_category":"Centros De Educaci\u00d3n Especial",
    "sg:phone":"+34 977 83 76 70",
    "sg:postcode":"43311",
    "sg:province":"Tarragona",
    "wof:name":"Ajuntament De Vilanova D'escornalbou",
    "wof:placetype":"venue"
},
  "geometry": {"coordinates":[0.937610805,41.1122207642],"type":"Point"}
}