{
  "type": "Feature",
  "properties": {
    "iso:country":"ES",
    "sg:address":"Carrer de Francesc Suau, 7",
    "sg:city":"Palma",
    "sg:orig_category":"Servicios, Asesor\u00cda, Formaci\u00d3n En Ofim\u00c1tica",
    "sg:phone":"+34 971 29 47 03",
    "sg:postcode":"07010",
    "sg:province":"Islas Baleares",
    "wof:name":"Lancor S.l.",
    "wof:placetype":"venue"
},
  "geometry": {"coordinates":[2.6518239975,39.5831489563],"type":"Point"}
}