{
  "type": "Feature",
  "properties": {
    "addr:full":"Carrer de Numancia, 52 Barcelona Barcelona 08029",
    "addr:housenumber":"52",
    "addr:postcode":"08029",
    "addr:street":"Carrer De Numancia",
    "iso:country":"ES",
    "sg:address":"Carrer de Numancia, 52",
    "sg:city":"Barcelona",
    "sg:orig_category":"Agentes De Seguros",
    "sg:phone":"+34 934 19 51 22",
    "sg:postcode":"08029",
    "sg:province":"Barcelona",
    "wof:name":"Miquel Domenech Jose Antonio",
    "wof:placetype":"venue"
},
  "geometry": {"coordinates":[2.1388659477,41.3835983276],"type":"Point"}
}