{
  "type": "Feature",
  "properties": {
    "addr:full":"Calle de San Isidro Labrador, 9 Mairena Aljarafe Sevilla 41927",
    "addr:housenumber":"9",
    "addr:postcode":"41927",
    "addr:street":"Calle De San Isidro Labrador",
    "iso:country":"ES",
    "sg:address":"Calle de San Isidro Labrador, 9",
    "sg:city":"Mairena Aljarafe",
    "sg:orig_category":"Empresas De Limpieza",
    "sg:phone":"+34 954 18 39 76",
    "sg:postcode":"41927",
    "sg:province":"Sevilla",
    "wof:name":"Celia Limpieza Y Mantenimiento S.l",
    "wof:placetype":"venue"
},
  "geometry": {"coordinates":[-6.0454740524,37.3444366455],"type":"Point"}
}