{
  "type": "Feature",
  "properties": {
    "addr:full":"Pol Ind La Barrena, S/n Tudela Navarra 31500",
    "addr:housenumber":"s",
    "addr:postcode":"31500",
    "addr:street":"Barrena;/ N",
    "iso:country":"ES",
    "sg:address":"Pol Ind La Barrena, S/n",
    "sg:city":"Tudela",
    "sg:orig_category":"Armas Y Municiones (fabricaci\u00d3n, Al Por Mayor)",
    "sg:phone":"+34 948 82 68 81",
    "sg:postcode":"31500",
    "sg:province":"Navarra",
    "wof:name":"Armeria Cano S.l.",
    "wof:placetype":"venue"
},
  "geometry": {"coordinates":[-1.4821481705,42.1872329712],"type":"Point"}
}