{
  "type": "Feature",
  "properties": {
    "iso:country":"ES",
    "sg:address":"Cant Grande, S/n",
    "sg:city":"Coru\u00d1a",
    "sg:orig_category":"Aparcamientos (infraestructuras, Accesorios)",
    "sg:phone":"+34 981 22 93 77",
    "sg:postcode":"15003",
    "sg:province":"La Coru\u00f1a",
    "wof:name":"Apaga S.a.",
    "wof:placetype":"venue"
},
  "geometry": {"coordinates":[-8.4033460617,43.370677948],"type":"Point"}
}