{
  "type": "Feature",
  "properties": {
    "iso:country":"ES",
    "sg:address":"Calle de Poniente, 22",
    "sg:city":"Armilla",
    "sg:orig_category":"Librer\u00cdas",
    "sg:phone":"+34 958 57 18 02",
    "sg:postcode":"18100",
    "sg:province":"Granada",
    "wof:name":"Mochon Bedmar Manuel",
    "wof:placetype":"venue"
},
  "geometry": {"coordinates":[-3.6280138493,37.1436576843],"type":"Point"}
}