{
  "type": "Feature",
  "properties": {
    "addr:full":"Avda Siglo Xxi (del), 13 Boadilla Del Monte Madrid 28660",
    "addr:postcode":"28660",
    "addr:street":"Avda Siglo Xxi Del",
    "iso:country":"ES",
    "sg:address":"Avda Siglo Xxi (del), 13",
    "sg:city":"Boadilla Del Monte",
    "sg:orig_category":"Ense\u00d1anza Variada",
    "sg:phone":"+34 916 33 93 39",
    "sg:postcode":"28660",
    "sg:province":"Madrid",
    "sg:website":"www.delfis.com.es",
    "wof:name":"Centro De Formacion Delfis",
    "wof:placetype":"venue"
},
  "geometry": {"coordinates":[-3.8884119987,40.4057006836],"type":"Point"}
}