{
  "type": "Feature",
  "properties": {
    "iso:country":"ES",
    "sg:address":"Calle de Alcala, 507",
    "sg:city":"Madrid",
    "sg:orig_category":"Comercio De Piezas De Recambio Y De Accesorios De Veh\u00cdculos, Veh\u00cdculos Industriales",
    "sg:phone":"+34 913 24 26 33",
    "sg:postcode":"28027",
    "sg:province":"Madrid",
    "wof:name":"Migdam Sport Tunning S.l.",
    "wof:placetype":"venue"
},
  "geometry": {"coordinates":[-3.6282069683,40.4405899048],"type":"Point"}
}