{
  "type": "Feature",
  "properties": {
    "addr:full":"Avda Denia, 151 Alacant Alicante 03015",
    "addr:housenumber":"151",
    "addr:postcode":"03015",
    "addr:street":"Avda Denia",
    "iso:country":"ES",
    "sg:address":"Avda Denia, 151",
    "sg:city":"Alacant",
    "sg:orig_category":"Alquiler De Veh\u00cdculos: Turismos Y Utilitarios",
    "sg:phone":"+34 965 16 26 33",
    "sg:postcode":"03015",
    "sg:province":"Alicante",
    "sg:website":"www.dieselcar.es",
    "wof:name":"Diesel Car S.a.",
    "wof:placetype":"venue"
},
  "geometry": {"coordinates":[-0.4558129907,38.3732414246],"type":"Point"}
}