{
  "type": "Feature",
  "properties": {
    "iso:country":"ES",
    "sg:address":"Carr Castell De Sant Felip, D'es, 1",
    "sg:city":"Castell",
    "sg:orig_category":"Albergues",
    "sg:phone":"+34 971 36 59 99",
    "sg:postcode":"07720",
    "sg:province":"Islas Baleares",
    "wof:name":"Hostal Toni C.b",
    "wof:placetype":"venue"
},
  "geometry": {"coordinates":[2.9117100239,39.6136398315],"type":"Point"}
}