{
  "type": "Feature",
  "properties": {
    "addr:full":"Calle de Calixto Iii, 39 Valencia Valencia 46008",
    "addr:housenumber":"39",
    "addr:postcode":"46008",
    "addr:street":"Calle De Calixto Iii",
    "iso:country":"ES",
    "sg:address":"Calle de Calixto Iii, 39",
    "sg:city":"Valencia",
    "sg:orig_category":"Fabricaci\u00d3n, Venta De Cuadros, Accesorios Para Enmarcar",
    "sg:phone":"+34 963 85 02 35",
    "sg:postcode":"46008",
    "sg:province":"Valencia",
    "wof:name":"Maruenda Alba Regina",
    "wof:placetype":"venue"
},
  "geometry": {"coordinates":[-0.3902525902,39.4706993103],"type":"Point"}
}