{
  "type": "Feature",
  "properties": {
    "iso:country":"ES",
    "sg:address":"Calle de Ferraz, 3",
    "sg:city":"Alcala Henares",
    "sg:orig_category":"M\u00c1rmoles, Granitos Y Piedras Naturales",
    "sg:phone":"+34 918 78 84 02",
    "sg:postcode":"28807",
    "sg:province":"Madrid",
    "wof:name":"Marmoles Guadarrama S.l.",
    "wof:placetype":"venue"
},
  "geometry": {"coordinates":[-3.3640623093,40.4883804321],"type":"Point"}
}