{
  "type": "Feature",
  "properties": {
    "iso:country":"ES",
    "sg:address":"Carrer de Font De La Vila, 72",
    "sg:city":"Secar De La Real",
    "sg:orig_category":"Lubrificantes (fabricaci\u00d3n, Al Por Mayor)",
    "sg:phone":"+34 971 76 95 68",
    "sg:postcode":"07010",
    "sg:province":"Islas Baleares",
    "wof:name":"Arolas-amengual S.l.",
    "wof:placetype":"venue"
},
  "geometry": {"coordinates":[2.6364307404,39.609287262],"type":"Point"}
}