{
  "type": "Feature",
  "properties": {
    "addr:full":"Plaz Campuzano Emilio, 3 Bilbao Vizcaya 48012",
    "addr:postcode":"48012",
    "addr:street":"Emilio",
    "iso:country":"ES",
    "sg:address":"Plaz Campuzano Emilio, 3",
    "sg:city":"Bilbao",
    "sg:orig_category":"Zapater\u00cdas",
    "sg:phone":"+34 944 27 23 84",
    "sg:postcode":"48012",
    "sg:province":"Vizcaya",
    "wof:name":"Calzado Deportivo Uno Mas Uno S.l.",
    "wof:placetype":"venue"
},
  "geometry": {"coordinates":[-2.9461190701,43.2686500549],"type":"Point"}
}