{
  "type": "Feature",
  "properties": {
    "addr:full":"Calle de Segalar, 11 Binefar Huesca 22500",
    "addr:housenumber":"11",
    "addr:postcode":"22500",
    "addr:street":"Calle De Segalar",
    "iso:country":"ES",
    "sg:address":"Calle de Segalar, 11",
    "sg:city":"Binefar",
    "sg:orig_category":"Empresas De Desmonte",
    "sg:phone":"+34 974 42 80 12",
    "sg:postcode":"22500",
    "sg:province":"Huesca",
    "wof:name":"Fernandez Fernandez Juan Manuel",
    "wof:placetype":"venue"
},
  "geometry": {"coordinates":[0.2890099883,41.8545608521],"type":"Point"}
}