{
  "type": "Feature",
  "properties": {
    "iso:country":"ES",
    "sg:address":"Calle de Circunvalacion Encina, 1",
    "sg:city":"Granada",
    "sg:classifiers":[
        {
            "category":"Autos & Motor Vehicles",
            "subcategory":"Automobile Sales",
            "type":"Retail Goods"
        }
    ],
    "sg:phone":"+34 958 20 17 18",
    "sg:postcode":"18015",
    "sg:province":"Granada",
    "wof:name":"Autoescuela Jesus Molina S.l.",
    "wof:placetype":"venue"
},
  "geometry": {"coordinates":[-3.6216340065,37.1893997192],"type":"Point"}
}