{
  "type": "Feature",
  "properties": {
    "iso:country":"ES",
    "sg:address":"Calle de Fernan Velazquez, 16",
    "sg:city":"Lebrija",
    "sg:orig_category":"Ropa Para Caballeros (al Por Menor)",
    "sg:phone":"+34 955 97 19 24",
    "sg:postcode":"41740",
    "sg:province":"Sevilla",
    "wof:name":"Lopez Mu\u00f1oz Isabel",
    "wof:placetype":"venue"
},
  "geometry": {"coordinates":[-6.0779480934,36.9182395935],"type":"Point"}
}