{
  "type": "Feature",
  "properties": {
    "addr:full":"Calle de Rioja, 7 Vitoria-gasteiz \u00c1lava 01005",
    "addr:housenumber":"7",
    "addr:postcode":"01005",
    "addr:street":"Calle De Rioja",
    "iso:country":"ES",
    "sg:address":"Calle de Rioja, 7",
    "sg:city":"Vitoria-gasteiz",
    "sg:orig_category":"Inmobiliaria (agencias)",
    "sg:phone":"+34 945 25 01 11",
    "sg:postcode":"01005",
    "sg:province":"\u00c1lava",
    "wof:name":"Servicios De Vitoria Atico S.l.",
    "wof:placetype":"venue"
},
  "geometry": {"coordinates":[-2.6681489944,42.8425102234],"type":"Point"}
}