{
  "type": "Feature",
  "properties": {
    "iso:country":"ES",
    "sg:address":"Calle de Antonio Machado, 6",
    "sg:city":"Alhama Murcia",
    "sg:orig_category":"Sindicatos Y Colegios Profesionales",
    "sg:phone":"+34 968 63 36 37",
    "sg:postcode":"30840",
    "sg:province":"Murcia",
    "wof:name":"Asociacion Espa\u00d1ola De Tecnicos En Radiologia",
    "wof:placetype":"venue"
},
  "geometry": {"coordinates":[-1.4291343689,37.8460769653],"type":"Point"}
}