{
  "type": "Feature",
  "properties": {
    "addr:full":"Calle de San Miguel, 1 Avila \u00c1vila 05001",
    "addr:housenumber":"1",
    "addr:postcode":"05001",
    "addr:street":"Calle De San Miguel;A\u0301Vila",
    "iso:country":"ES",
    "sg:address":"Calle de San Miguel, 1",
    "sg:city":"Avila",
    "sg:orig_category":"Distribuci\u00d3n De Petr\u00d3leo Y Derivados",
    "sg:phone":"+34 920 25 70 02",
    "sg:postcode":"05001",
    "sg:province":"\u00c1vila",
    "wof:name":"Estacion De Servicio Nuestra Se\u00d1ora De Sonsoles S.l.",
    "wof:placetype":"venue"
},
  "geometry": {"coordinates":[-4.6954078674,40.6548156738],"type":"Point"}
}