{
  "type": "Feature",
  "properties": {
    "addr:full":"Avda Constitucion (de La), 24 Granada Granada 18012",
    "addr:housenumber":"24",
    "addr:postcode":"18012",
    "addr:street":"Avda Constitucion De La",
    "iso:country":"ES",
    "sg:address":"Avda Constitucion (de La), 24",
    "sg:city":"Granada",
    "sg:orig_category":"M\u00c9dicos: Medicina General Orientada A La Homeopat\u00cda",
    "sg:phone":"+34 958 27 32 95",
    "sg:postcode":"18012",
    "sg:province":"Granada",
    "wof:name":"Mora Montes Rafael Angel",
    "wof:placetype":"venue"
},
  "geometry": {"coordinates":[-3.6057090759,37.1851081848],"type":"Point"}
}