{
  "type": "Feature",
  "properties": {
    "iso:country":"ES",
    "sg:address":"Calle de Canalejas, 90",
    "sg:city":"Palmas De Gran Canaria",
    "sg:orig_category":"Inmobiliaria (agencias)",
    "sg:phone":"+34 928 43 35 03",
    "sg:postcode":"35003",
    "sg:province":"Las Palmas",
    "wof:name":"Montelongo Parada Juan De Dios",
    "wof:placetype":"venue"
},
  "geometry": {"coordinates":[-15.42141819,28.1127490997],"type":"Point"}
}