{
  "type": "Feature",
  "properties": {
    "addr:full":"Sbid Costa, 2 Vigo Pontevedra 36213",
    "addr:housenumber":"2",
    "addr:postcode":"36213",
    "addr:street":"Costa",
    "iso:country":"ES",
    "sg:address":"Sbid Costa, 2",
    "sg:city":"Vigo",
    "sg:orig_category":"M\u00c9dicos: Otorrinolaringolog\u00cda",
    "sg:phone":"+34 986 21 01 24",
    "sg:postcode":"36213",
    "sg:province":"Pontevedra",
    "wof:name":"Valdes Pons Roberto",
    "wof:placetype":"venue"
},
  "geometry": {"coordinates":[-8.7262926102,42.2142028809],"type":"Point"}
}