{
  "type": "Feature",
  "properties": {
    "iso:country":"ES",
    "sg:address":"Calle de General Yag\u00fce, 42",
    "sg:city":"Madrid",
    "sg:orig_category":"Turismo",
    "sg:phone":"+34 914 25 02 23",
    "sg:postcode":"28020",
    "sg:province":"Madrid",
    "sg:website":"www.consultoresturismo.com",
    "wof:name":"Gmm.consultores Turisticos S.l.",
    "wof:placetype":"venue"
},
  "geometry": {"coordinates":[-3.6973800659,40.4566917419],"type":"Point"}
}