{
  "type": "Feature",
  "properties": {
    "iso:country":"ES",
    "sg:address":"Cmno Tximilarre, S/n",
    "sg:city":"Kurtzea",
    "sg:orig_category":"Electricidad: Material Y Suministros De Instalaci\u00d3n (fabricaci\u00d3n)",
    "sg:phone":"+34 944 57 19 88",
    "sg:postcode":"48960",
    "sg:province":"Vizcaya",
    "sg:website":"www.resistenciasreyter.com",
    "wof:name":"Resistencias Reyter S.l.",
    "wof:placetype":"venue"
},
  "geometry": {"coordinates":[-2.8470389843,43.2298049927],"type":"Point"}
}