{
  "type": "Feature",
  "properties": {
    "addr:full":"Calle de Alfonso Xi, 28 Alcala Real Ja\u00e9n 23680",
    "addr:housenumber":"28",
    "addr:postcode":"23680",
    "addr:street":"Calle De Alfonso Xi;Jae\u0301N",
    "iso:country":"ES",
    "sg:address":"Calle de Alfonso Xi, 28",
    "sg:city":"Alcala Real",
    "sg:orig_category":"Fabricaci\u00d3n De Capiteles",
    "sg:phone":"+34 953 58 06 99",
    "sg:postcode":"23680",
    "sg:province":"Ja\u00e9n",
    "wof:name":"Trujillo Perez Francisca",
    "wof:placetype":"venue"
},
  "geometry": {"coordinates":[-3.9238419533,37.4578933716],"type":"Point"}
}