{
  "type": "Feature",
  "properties": {
    "iso:country":"ES",
    "sg:address":"Carrer de Corsega, 629",
    "sg:city":"Barcelona",
    "sg:orig_category":"Platos Preparados Refrigerados (fabricaci\u00d3n, Al Por Mayor)",
    "sg:phone":"+34 934 50 31 25",
    "sg:postcode":"08025",
    "sg:province":"Barcelona",
    "wof:name":"Kuay Fantieng S.l.",
    "wof:placetype":"venue"
},
  "geometry": {"coordinates":[2.1762909889,41.4094429016],"type":"Point"}
}