{
  "type": "Feature",
  "properties": {
    "addr:full":"Carr Doctor Callis, 12 Cadaques Girona 17488",
    "addr:housenumber":"12",
    "addr:postcode":"17488",
    "addr:street":"Carr Doctor Callis",
    "iso:country":"ES",
    "sg:address":"Carr Doctor Callis, 12",
    "sg:city":"Cadaques",
    "sg:orig_category":"Carnicer\u00cdas, Carnicer\u00cdas",
    "sg:phone":"+34 972 25 83 40",
    "sg:postcode":"17488",
    "sg:province":"Girona",
    "wof:name":"Carns Serrapla S.l.",
    "wof:placetype":"venue"
},
  "geometry": {"coordinates":[3.2766580582,42.2882194519],"type":"Point"}
}