{
  "type": "Feature",
  "properties": {
    "iso:country":"ES",
    "sg:address":"Carr Baro De Maials, 20",
    "sg:city":"Lleida",
    "sg:orig_category":"Ense\u00d1anza Secundaria: Colegios Y Escuelas Privadas",
    "sg:phone":"+34 973 23 10 17",
    "sg:postcode":"25005",
    "sg:province":"Lleida",
    "wof:name":"Aula Nova S.c.p.",
    "wof:placetype":"venue"
},
  "geometry": {"coordinates":[0.6362347007,41.6218910217],"type":"Point"}
}