{
  "type": "Feature",
  "properties": {
    "addr:full":"Calle de Altamirano, 12 Madrid Madrid 28008",
    "addr:housenumber":"12",
    "addr:postcode":"madrid;28008",
    "addr:street":"Calle De Altamirano",
    "iso:country":"ES",
    "sg:address":"Calle de Altamirano, 12",
    "sg:city":"Madrid",
    "sg:orig_category":"Fabricaci\u00d3n De Sobres, Bolsas Y Fundas",
    "sg:phone":"+34 915 43 72 05",
    "sg:postcode":"28008",
    "sg:province":"Madrid",
    "wof:name":"Siles Cazalla Maria Isabel",
    "wof:placetype":"venue"
},
  "geometry": {"coordinates":[-3.7179269791,40.4314498901],"type":"Point"}
}