{
  "type": "Feature",
  "properties": {
    "addr:full":"Plaz Palma De Burgos (de), S/n Ubeda Ja\u00e9n 23400",
    "addr:housenumber":"s",
    "addr:postcode":"23400",
    "addr:street":"/ N Ubeda Jae\u0301N",
    "iso:country":"ES",
    "sg:address":"Plaz Palma De Burgos (de), S/n",
    "sg:city":"Ubeda",
    "sg:orig_category":"Guarder\u00cdas",
    "sg:phone":"+34 953 75 45 04",
    "sg:postcode":"23400",
    "sg:province":"Ja\u00e9n",
    "wof:name":"Guarderia Laboral Municipal Escuela Infantil Ciudad De Ubeda C.b.",
    "wof:placetype":"venue"
},
  "geometry": {"coordinates":[-3.3590445518,37.994178772],"type":"Point"}
}