{
  "type": "Feature",
  "properties": {
    "addr:full":"Calle de Cine (el), 9 Noja Cantabria 39180",
    "addr:postcode":"39180",
    "addr:street":"Calle De",
    "iso:country":"ES",
    "sg:address":"Calle de Cine (el), 9",
    "sg:city":"Noja",
    "sg:classifiers":[
        {
            "category":"Taxi",
            "type":"Transportation"
        }
    ],
    "sg:phone":"+34 942 63 04 14",
    "sg:postcode":"39180",
    "sg:province":"Cantabria",
    "wof:name":"Somarriba Quintana Juan Antonio",
    "wof:placetype":"venue"
},
  "geometry": {"coordinates":[-3.5238029957,43.4806976318],"type":"Point"}
}