{
  "type": "Feature",
  "properties": {
    "iso:country":"ES",
    "sg:address":"Carrer de Fran\u00c7a, 21",
    "sg:city":"Hospitalet Llobregat",
    "sg:orig_category":"Laboratorios Dentales",
    "sg:phone":"+34 933 36 10 47",
    "sg:postcode":"08907",
    "sg:province":"Barcelona",
    "wof:name":"Laboratorio Dental L'h Esqueletic S.l.",
    "wof:placetype":"venue"
},
  "geometry": {"coordinates":[2.1118929386,41.3556785583],"type":"Point"}
}