{
  "type": "Feature",
  "properties": {
    "iso:country":"ES",
    "sg:address":"Calle de Calderon De La Barca (de), 12",
    "sg:city":"Algete",
    "sg:orig_category":"Inmobiliaria (agencias)",
    "sg:phone":"+34 916 28 26 19",
    "sg:postcode":"28110",
    "sg:province":"Madrid",
    "wof:name":"Frinvill S.l.",
    "wof:placetype":"venue"
},
  "geometry": {"coordinates":[-3.500282526,40.600151062],"type":"Point"}
}