{
  "type": "Feature",
  "properties": {
    "iso:country":"ES",
    "sg:address":"Avda Soria, Km. 0005,7",
    "sg:city":"Valladolid",
    "sg:orig_category":"Inmobiliaria (agencias)",
    "sg:phone":"+34 983 21 20 27",
    "sg:postcode":"47012",
    "sg:province":"Valladolid",
    "wof:name":"Urfica S.l.",
    "wof:placetype":"venue"
},
  "geometry": {"coordinates":[-4.695494175,41.6288452148],"type":"Point"}
}