{
  "type": "Feature",
  "properties": {
    "iso:country":"ES",
    "sg:address":"La Paz, 12",
    "sg:city":"Zaragoza",
    "sg:orig_category":"Ense\u00d1anza Variada",
    "sg:phone":"+34 976 22 34 56",
    "sg:postcode":"50008",
    "sg:province":"Zaragoza",
    "wof:name":"Lasheras Cardesa Antonio",
    "wof:placetype":"venue"
},
  "geometry": {"coordinates":[-0.8845430017,41.6423835754],"type":"Point"}
}