{
  "type": "Feature",
  "properties": {
    "addr:full":"Avda Pepe Lopez, S/n Castellar Ja\u00e9n 23260",
    "addr:housenumber":"s / n",
    "addr:postcode":"23260",
    "addr:street":"Lopez",
    "iso:country":"ES",
    "sg:address":"Avda Pepe Lopez, S/n",
    "sg:city":"Castellar",
    "sg:orig_category":"Sindicatos De Trabajadores",
    "sg:phone":"+34 953 46 03 33",
    "sg:postcode":"23260",
    "sg:province":"Ja\u00e9n",
    "wof:name":"Union General De Trabajadores",
    "wof:placetype":"venue"
},
  "geometry": {"coordinates":[-3.136095047,38.2541351318],"type":"Point"}
}