{
  "type": "Feature",
  "properties": {
    "addr:full":"Avda Valentin Masip, 3 Oviedo Asturias 33013",
    "addr:housenumber":"3",
    "addr:postcode":"33013",
    "addr:street":"Avda Valentin Masip",
    "iso:country":"ES",
    "sg:address":"Avda Valentin Masip, 3",
    "sg:city":"Oviedo",
    "sg:orig_category":"Muebles Y Decoraci\u00d3n De Jardines (fabricaci\u00d3n, Venta)",
    "sg:phone":"+34 985 23 71 40",
    "sg:postcode":"33013",
    "sg:province":"Asturias",
    "sg:website":"www.toldoselcampo.com",
    "wof:name":"Alvarez Menendez Maria Soledad",
    "wof:placetype":"venue"
},
  "geometry": {"coordinates":[-5.8599643707,43.3615074158],"type":"Point"}
}