{
  "type": "Feature",
  "properties": {
    "iso:country":"ES",
    "sg:address":"Pg Nit De L'alba, 21",
    "sg:city":"Elche",
    "sg:orig_category":"Zapatos (al Por Menor)",
    "sg:phone":"+34 965 46 36 81",
    "sg:postcode":"03206",
    "sg:province":"Alicante",
    "wof:name":"Berna Satoca Esther",
    "wof:placetype":"venue"
},
  "geometry": {"coordinates":[-0.7069749832,38.270275116],"type":"Point"}
}