{
  "type": "Feature",
  "properties": {
    "iso:country":"ES",
    "sg:address":"Pla\u00c7 Constitucion, 6",
    "sg:city":"Riola",
    "sg:orig_category":"Maquinaria Para Industrias Diversas",
    "sg:phone":"+34 961 71 08 37",
    "sg:postcode":"46417",
    "sg:province":"Valencia",
    "wof:name":"Miralles Piera Julian",
    "wof:placetype":"venue"
},
  "geometry": {"coordinates":[-0.3374440074,39.1949615479],"type":"Point"}
}