{
  "type": "Feature",
  "properties": {
    "addr:full":"Calle de Doctor Velazquez, 29 Segorbe Castell\u00f3n 12400",
    "addr:housenumber":"29",
    "addr:postcode":"12400",
    "addr:street":"Calle De Doctor Velazquez",
    "iso:country":"ES",
    "sg:address":"Calle de Doctor Velazquez, 29",
    "sg:city":"Segorbe",
    "sg:orig_category":"Pintura Y Barniz (al Por Menor)",
    "sg:phone":"+34 964 13 20 56",
    "sg:postcode":"12400",
    "sg:province":"Castell\u00f3n",
    "wof:name":"Bricodec Gimenez S.l.",
    "wof:placetype":"venue"
},
  "geometry": {"coordinates":[-0.4868989885,39.8481903076],"type":"Point"}
}