{
  "type": "Feature",
  "properties": {
    "addr:full":"Calle de Roque Barcia, 7 Huelva Huelva 21003",
    "addr:housenumber":"7",
    "addr:postcode":"21003",
    "addr:street":"Calle De Roque Barcia",
    "iso:country":"ES",
    "sg:address":"Calle de Roque Barcia, 7",
    "sg:city":"Huelva",
    "sg:orig_category":"Carnicer\u00cdas, Carnicer\u00cdas",
    "sg:phone":"+34 959 22 29 81",
    "sg:postcode":"21003",
    "sg:province":"Huelva",
    "wof:name":"Cardenas Raposo Manuel",
    "wof:placetype":"venue"
},
  "geometry": {"coordinates":[-6.9373297691,37.2559547424],"type":"Point"}
}