{
  "type": "Feature",
  "properties": {
    "iso:country":"ES",
    "sg:address":"Calle de Doctor Grai\u00d1o Del, 29",
    "sg:city":"Aviles",
    "sg:orig_category":"Centros De Coordinaci\u00d3n",
    "sg:phone":"+34 985 56 39 39",
    "sg:postcode":"33401",
    "sg:province":"Asturias",
    "wof:name":"Gestoria Administrativa Olivares S.l.",
    "wof:placetype":"venue"
},
  "geometry": {"coordinates":[-5.9267277718,43.5563926697],"type":"Point"}
}