{
  "type": "Feature",
  "properties": {
    "iso:country":"ES",
    "sg:address":"Urb Puerto Deportivo, 49",
    "sg:city":"Estepona",
    "sg:orig_category":"Agencias De Viajes",
    "sg:phone":"+34 952 79 50 02",
    "sg:postcode":"29680",
    "sg:province":"M\u00e1laga",
    "sg:website":"www.prestigefishingtours.com",
    "wof:name":"Prestige Fishing Tours S.l.",
    "wof:placetype":"venue"
},
  "geometry": {"coordinates":[-5.1452140808,36.4275817871],"type":"Point"}
}