{
  "type": "Feature",
  "properties": {
    "addr:full":"Calle de San Nicolas, 8 Villacedre Le\u00f3n 24194",
    "addr:housenumber":"8",
    "addr:postcode":"24194",
    "addr:street":"Calle De San;Villacedre Leo\u0301N",
    "iso:country":"ES",
    "sg:address":"Calle de San Nicolas, 8",
    "sg:city":"Villacedre",
    "sg:orig_category":"Tubos Y Tuber\u00cdas De Goma Y Pl\u00c1stico (fabricaci\u00d3n, Al Por Mayor)",
    "sg:phone":"+34 987 21 45 60",
    "sg:postcode":"24194",
    "sg:province":"Le\u00f3n",
    "wof:name":"Nueva Terrain S.l.",
    "wof:placetype":"venue"
},
  "geometry": {"coordinates":[-5.5872740746,42.5642318726],"type":"Point"}
}