{
  "type": "Feature",
  "properties": {
    "iso:country":"ES",
    "sg:address":"Castanyet, 75",
    "sg:city":"Sta. Coloma Farners",
    "sg:orig_category":"Cristaler\u00cdas",
    "sg:phone":"+34 972 87 71 94",
    "sg:postcode":"17430",
    "sg:province":"Girona",
    "wof:name":"Vidrio Y Aluminio Perlacasa S.l.",
    "wof:placetype":"venue"
},
  "geometry": {"coordinates":[2.657490015,41.8663482666],"type":"Point"}
}