{
  "type": "Feature",
  "properties": {
    "iso:country":"ES",
    "sg:address":"El Cabo, Trav., 4",
    "sg:city":"Grado",
    "sg:orig_category":"Empresas De Desmonte",
    "sg:phone":"+34 985 75 18 05",
    "sg:postcode":"33820",
    "sg:province":"Asturias",
    "wof:name":"Granado Hevia Jose Ramon",
    "wof:placetype":"venue"
},
  "geometry": {"coordinates":[-6.0700316429,43.3875083923],"type":"Point"}
}