{
  "type": "Feature",
  "properties": {
    "iso:country":"ES",
    "sg:address":"Carrer de Sants, 41",
    "sg:city":"Barcelona",
    "sg:orig_category":"Bisuter\u00cda, Joyer\u00cda, Relojer\u00cda (al Por Menor)",
    "sg:phone":"+34 934 21 03 28",
    "sg:postcode":"08014",
    "sg:province":"Barcelona",
    "wof:name":"Roe Claramunt Francisco",
    "wof:placetype":"venue"
},
  "geometry": {"coordinates":[2.138520956,41.3752250671],"type":"Point"}
}