{
  "type": "Feature",
  "properties": {
    "addr:full":"Pol. Industrial, S/n Jodar Ja\u00e9n 23500",
    "addr:housenumber":"/ n",
    "addr:postcode":"23500",
    "addr:street":"Pol. Industrial S;Jae\u0301N",
    "iso:country":"ES",
    "sg:address":"Pol. Industrial, S/n",
    "sg:city":"Jodar",
    "sg:orig_category":"Empresas De Carpinter\u00cda De Madera",
    "sg:phone":"+34 953 78 77 26",
    "sg:postcode":"23500",
    "sg:province":"Ja\u00e9n",
    "wof:name":"Raya Pastrana Luis Miguel",
    "wof:placetype":"venue"
},
  "geometry": {"coordinates":[-3.3526489735,37.8448600769],"type":"Point"}
}