{
  "type": "Feature",
  "properties": {
    "iso:country":"ES",
    "sg:address":"Calle de Hortaleza, 4",
    "sg:city":"Lantadilla",
    "sg:orig_category":"Pescader\u00cdas (al Por Menor)",
    "sg:phone":"+34 979 15 20 51",
    "sg:postcode":"34468",
    "sg:province":"Palencia",
    "wof:name":"Luena Santamaria Gregorio",
    "wof:placetype":"venue"
},
  "geometry": {"coordinates":[-4.2764878273,42.3413734436],"type":"Point"}
}