{
  "type": "Feature",
  "properties": {
    "addr:full":"Avda Castilla, 29 Aranda Duero Burgos 09400",
    "addr:housenumber":"29",
    "addr:postcode":"09400",
    "addr:street":"Avda Castilla",
    "iso:country":"ES",
    "sg:address":"Avda Castilla, 29",
    "sg:city":"Aranda Duero",
    "sg:orig_category":"Empresarios",
    "sg:phone":"+34 947 51 02 01",
    "sg:postcode":"09400",
    "sg:province":"Burgos",
    "wof:name":"Construcciones Gutierrez Nieto Aranda",
    "wof:placetype":"venue"
},
  "geometry": {"coordinates":[-3.6911430359,41.6673164368],"type":"Point"}
}