{
  "type": "Feature",
  "properties": {
    "addr:full":"Mayans(p I Cova), S/n Meliana Valencia 46133",
    "addr:housenumber":"s / n",
    "addr:postcode":"46133",
    "addr:street":"Cova",
    "iso:country":"ES",
    "sg:address":"Mayans(p I Cova), S/n",
    "sg:city":"Meliana",
    "sg:orig_category":"Fabricaci\u00d3n De Mobiliario Met\u00c1lico",
    "sg:phone":"+34 961 48 01 87",
    "sg:postcode":"46133",
    "sg:province":"Valencia",
    "wof:name":"Copper Levante S.l.",
    "wof:placetype":"venue"
},
  "geometry": {"coordinates":[-0.3533500135,39.5240211487],"type":"Point"}
}