{
  "type": "Feature",
  "properties": {
    "iso:country":"ES",
    "sg:address":"Calle de Nuestra Se\u00d1ora, 55",
    "sg:city":"Pe\u00e7aranda De Bracamonte",
    "sg:orig_category":"M\u00c9dicos: Estomatolog\u00cda",
    "sg:phone":"+34 923 54 08 98",
    "sg:postcode":"37300",
    "sg:province":"Salamanca",
    "wof:name":"Sanchez Bueno Mateo",
    "wof:placetype":"venue"
},
  "geometry": {"coordinates":[-5.2008399963,40.8999214172],"type":"Point"}
}