{
  "type": "Feature",
  "properties": {
    "iso:country":"ES",
    "sg:address":"Calle de Ingeniero Francisco Ruiz Martinez, 33",
    "sg:city":"Ubrique",
    "sg:orig_category":"Marroquiner\u00cda (confecci\u00d3n)",
    "sg:phone":"+34 956 46 11 69",
    "sg:postcode":"11600",
    "sg:province":"C\u00e1diz",
    "wof:name":"Rebajes Gomez S.l.l.",
    "wof:placetype":"venue"
},
  "geometry": {"coordinates":[-5.4439291954,36.6773681641],"type":"Point"}
}