{
  "type": "Feature",
  "properties": {
    "addr:full":"Plaz San Marcos, 6 Le\u00f3n Le\u00f3n 24002",
    "addr:housenumber":"6",
    "addr:postcode":"24002",
    "addr:street":"Plaz San Marcos;Leo\u0301N",
    "iso:country":"ES",
    "sg:address":"Plaz San Marcos, 6",
    "sg:city":"Le\u00f3n",
    "sg:orig_category":"Ense\u00d1anza Variada",
    "sg:phone":"+34 987 23 03 00",
    "sg:postcode":"24002",
    "sg:province":"Le\u00f3n",
    "wof:name":"Ricardo Blanco Oma\u00d1a S.l.",
    "wof:placetype":"venue"
},
  "geometry": {"coordinates":[-5.5807747841,42.6014404297],"type":"Point"}
}