{
  "type": "Feature",
  "properties": {
    "addr:full":"Avda Generalitat, 70 Palleja Barcelona 08780",
    "addr:housenumber":"70",
    "addr:postcode":"08780",
    "addr:street":"Avda Generalitat",
    "iso:country":"ES",
    "sg:address":"Avda Generalitat, 70",
    "sg:city":"Palleja",
    "sg:orig_category":"Asilos De Ancianos. Centros Privados",
    "sg:phone":"+34 936 63 03 50",
    "sg:postcode":"08780",
    "sg:province":"Barcelona",
    "wof:name":"Residencia Geriatrica Roma S.l.",
    "wof:placetype":"venue"
},
  "geometry": {"coordinates":[1.9967670441,41.4241485596],"type":"Point"}
}