{
  "type": "Feature",
  "properties": {
    "iso:country":"ES",
    "sg:address":"Calle de Melendez Valdes, 12",
    "sg:city":"Madrid",
    "sg:orig_category":"Bares, Piano",
    "sg:phone":"+34 914 45 70 13",
    "sg:postcode":"28015",
    "sg:province":"Madrid",
    "wof:name":"Hosteleria Republica S.l.",
    "wof:placetype":"venue"
},
  "geometry": {"coordinates":[-3.7096250057,40.4330291748],"type":"Point"}
}