{
  "type": "Feature",
  "properties": {
    "iso:country":"ES",
    "sg:address":"Pl Gabriel Ferrater I Soler, S/n",
    "sg:city":"Reus",
    "sg:orig_category":"Iglesia Cat\u00d3lica",
    "sg:phone":"+34 977 75 64 15",
    "sg:postcode":"43205",
    "sg:province":"Tarragona",
    "wof:name":"Arquebisbat De Tarragona",
    "wof:placetype":"venue"
},
  "geometry": {"coordinates":[1.1131489277,41.1430702209],"type":"Point"}
}