{
  "type": "Feature",
  "properties": {
    "addr:full":"Avda Plata, 85 Valencia Valencia 46006",
    "addr:housenumber":"85",
    "addr:postcode":"46006",
    "addr:street":"Avda Plata",
    "iso:country":"ES",
    "sg:address":"Avda Plata, 85",
    "sg:city":"Valencia",
    "sg:orig_category":"Platos Preparados Refrigerados (fabricaci\u00d3n, Al Por Mayor)",
    "sg:phone":"+34 963 95 16 60",
    "sg:postcode":"46006",
    "sg:province":"Valencia",
    "wof:name":"Fornes Rocafull Maria Luisa",
    "wof:placetype":"venue"
},
  "geometry": {"coordinates":[-0.361856997,39.4574165344],"type":"Point"}
}