{
  "type": "Feature",
  "properties": {
    "iso:country":"ES",
    "sg:address":"Calle de Cuenca, 6",
    "sg:city":"Segovia",
    "sg:orig_category":"Empresas De Portes Y Mensajer\u00cda",
    "sg:phone":"+34 921 44 50 00",
    "sg:postcode":"40004",
    "sg:province":"Segovia",
    "wof:name":"Asociacion Profesional De Radiotaxi De S",
    "wof:placetype":"venue"
},
  "geometry": {"coordinates":[-4.1030654907,40.9453277588],"type":"Point"}
}