{
  "type": "Feature",
  "properties": {
    "addr:full":"C/ Diego Pascual Oliver, 5 Elche Alicante 03206",
    "addr:housenumber":"5",
    "addr:postcode":"03206",
    "addr:street":"C / Diego Pascual Oliver",
    "iso:country":"ES",
    "sg:address":"C/ Diego Pascual Oliver, 5",
    "sg:city":"Elche",
    "sg:orig_category":"Fabricaci\u00d3n De Moldes Y Modelos",
    "sg:phone":"+34 965 43 84 52",
    "sg:postcode":"03206",
    "sg:province":"Alicante",
    "wof:name":"Poveda Hernandez Antonio",
    "wof:placetype":"venue"
},
  "geometry": {"coordinates":[-0.7102410197,38.2786102295],"type":"Point"}
}