{
  "type": "Feature",
  "properties": {
    "iso:country":"ES",
    "sg:address":"Merce Rodoreda(u Mas Palli), 15",
    "sg:city":"Calonge",
    "sg:orig_category":"Jardiner\u00cdas, Vegetales, Art\u00cdculos De Jardiner\u00cda (al Por Menor)",
    "sg:phone":"+34 972 65 15 41",
    "sg:postcode":"17251",
    "sg:province":"Girona",
    "wof:name":"Rivero Buxo Fernando",
    "wof:placetype":"venue"
},
  "geometry": {"coordinates":[3.0728890896,41.8403663635],"type":"Point"}
}