{
  "type": "Feature",
  "properties": {
    "iso:country":"ES",
    "sg:address":"Av Pais Valenciano, 90",
    "sg:city":"Guardamar Segura",
    "sg:orig_category":"Loter\u00cda Y T\u00d3mbola",
    "sg:phone":"+34 965 72 78 52",
    "sg:postcode":"03140",
    "sg:province":"Alicante",
    "wof:name":"Lucas Pallares Antonio",
    "wof:placetype":"venue"
},
  "geometry": {"coordinates":[-0.6544960141,38.0853729248],"type":"Point"}
}