{
  "type": "Feature",
  "properties": {
    "iso:country":"ES",
    "sg:address":"Carr Campet (del), 3",
    "sg:city":"Almafra",
    "sg:orig_category":"Lencer\u00cda Femenina, Corseter\u00cda, Trajes De Ba\u00d1o (al Por Menor)",
    "sg:phone":"+34 965 37 00 32",
    "sg:postcode":"03610",
    "sg:province":"Alicante",
    "wof:name":"Coloma Mu\u00f1oz Raul",
    "wof:placetype":"venue"
},
  "geometry": {"coordinates":[-0.7859489918,38.489315033],"type":"Point"}
}