{
  "type": "Feature",
  "properties": {
    "addr:full":"Ctra. Marbella, Km. 0004,0 Ojen M\u00e1laga 29610",
    "addr:postcode":"29610",
    "addr:street":"Ctra. Marbella Km. 0004,0 Ojen Ma\u0301Laga",
    "iso:country":"ES",
    "sg:address":"Ctra. Marbella, Km. 0004,0",
    "sg:city":"Ojen",
    "sg:orig_category":"Grafistas",
    "sg:phone":"+34 952 82 93 70",
    "sg:postcode":"29610",
    "sg:province":"M\u00e1laga",
    "wof:name":"Urquia Mu\u00f1oz Maria Teresa",
    "wof:placetype":"venue"
},
  "geometry": {"coordinates":[-4.8528089523,36.565536499],"type":"Point"}
}