{
  "type": "Feature",
  "properties": {
    "iso:country":"ES",
    "sg:address":"Calle de Real, 3",
    "sg:city":"Miajadas",
    "sg:orig_category":"Abogados",
    "sg:phone":"+34 927 34 71 37",
    "sg:postcode":"10100",
    "sg:province":"C\u00e1ceres",
    "wof:name":"Cintero Ramiro Alfonso",
    "wof:placetype":"venue"
},
  "geometry": {"coordinates":[-5.90711689,39.1513290405],"type":"Point"}
}