{
  "type": "Feature",
  "properties": {
    "addr:full":"Calle de Cachurra, 25 Negreira La Coru\u00f1a 15830",
    "addr:housenumber":"25",
    "addr:postcode":"15830",
    "addr:street":"Calle De Cachurra;La Corun\u0303A",
    "iso:country":"ES",
    "sg:address":"Calle de Cachurra, 25",
    "sg:city":"Negreira",
    "sg:orig_category":"Congelados: Productos Alimentarios (al Por Menor)",
    "sg:phone":"+34 981 88 16 35",
    "sg:postcode":"15830",
    "sg:province":"La Coru\u00f1a",
    "wof:name":"Congelados Pais S.l.",
    "wof:placetype":"venue"
},
  "geometry": {"coordinates":[-8.7371406555,42.9103927612],"type":"Point"}
}