{
  "type": "Feature",
  "properties": {
    "iso:country":"ES",
    "sg:address":"Avda Redondela, 61",
    "sg:city":"Igrexa",
    "sg:classifiers":[
        {
            "category":"Autos & Motor Vehicles",
            "subcategory":"Automobile Sales",
            "type":"Retail Goods"
        }
    ],
    "sg:phone":"+34 986 45 40 80",
    "sg:postcode":"36320",
    "sg:province":"Pontevedra",
    "wof:name":"Bugallo Fernandez Manuel",
    "wof:placetype":"venue"
},
  "geometry": {"coordinates":[-8.6428003311,42.4304618835],"type":"Point"}
}