{
  "type": "Feature",
  "properties": {
    "addr:full":"Avda Andalucia, 5 Onda Castell\u00f3n 12200",
    "addr:housenumber":"5",
    "addr:postcode":"12200",
    "addr:street":"Avda Andalucia;Castello\u0301N",
    "iso:country":"ES",
    "sg:address":"Avda Andalucia, 5",
    "sg:city":"Onda",
    "sg:orig_category":"Veh\u00cdculos De Ocasi\u00d3n",
    "sg:phone":"+34 964 60 13 97",
    "sg:postcode":"12200",
    "sg:province":"Castell\u00f3n",
    "wof:name":"Automoviles Castalia S.l.",
    "wof:placetype":"venue"
},
  "geometry": {"coordinates":[-0.2514280081,39.9667854309],"type":"Point"}
}