{
  "type": "Feature",
  "properties": {
    "iso:country":"ES",
    "sg:address":"Cami Ral, 450",
    "sg:city":"Mataro",
    "sg:orig_category":"Papeler\u00cdas, Librer\u00cdas",
    "sg:phone":"+34 937 90 65 65",
    "sg:postcode":"08302",
    "sg:province":"Barcelona",
    "wof:name":"Technos-papereria Scp.",
    "wof:placetype":"venue"
},
  "geometry": {"coordinates":[2.4426829815,41.5361061096],"type":"Point"}
}