{
  "type": "Feature",
  "properties": {
    "addr:full":"Caragol De Mar, 27 Port Alcudia Islas Baleares 07410",
    "addr:housenumber":"27",
    "addr:postcode":"07410",
    "addr:street":"Port;Islas",
    "iso:country":"ES",
    "sg:address":"Caragol De Mar, 27",
    "sg:city":"Port Alcudia",
    "sg:orig_category":"Alquiler De Veh\u00cdculos: Turismos Y Utilitarios",
    "sg:phone":"+34 971 54 62 29",
    "sg:postcode":"07410",
    "sg:province":"Islas Baleares",
    "wof:name":"Rent A Car Miguel Darder S.l.",
    "wof:placetype":"venue"
},
  "geometry": {"coordinates":[3.131759882,39.8426895142],"type":"Point"}
}