{
  "type": "Feature",
  "properties": {
    "addr:full":"Carr Poqueta Nit, 12 Montesano Valencia 46117",
    "addr:housenumber":"12",
    "addr:postcode":"46117",
    "addr:street":"Carr Poqueta Nit;Valencia",
    "iso:country":"ES",
    "sg:address":"Carr Poqueta Nit, 12",
    "sg:city":"Montesano",
    "sg:orig_category":"Ingenier\u00cda, Centros De Estudios (diversos)",
    "sg:phone":"+34 962 75 08 16",
    "sg:postcode":"46117",
    "sg:province":"Valencia",
    "wof:name":"Ingenieria De Comunicaciones Seyco S.a.l",
    "wof:placetype":"venue"
},
  "geometry": {"coordinates":[-0.4646939933,39.5906906128],"type":"Point"}
}