{
  "type": "Feature",
  "properties": {
    "iso:country":"ES",
    "sg:address":"Calle de Constitucion (de La), 84",
    "sg:city":"Alcobendas",
    "sg:orig_category":"Agencias De Viajes",
    "sg:phone":"+34 916 63 62 76",
    "sg:postcode":"28100",
    "sg:province":"Madrid",
    "sg:website":"www.viajesecuador.es",
    "wof:name":"Gelma Jimenez S.l.",
    "wof:placetype":"venue"
},
  "geometry": {"coordinates":[-3.6404275894,40.5443191528],"type":"Point"}
}