{
  "type": "Feature",
  "properties": {
    "addr:full":"Calle de O\u00d1ati, S/n Vitoria-gasteiz \u00c1lava 01013",
    "addr:housenumber":"s",
    "addr:postcode":"01013",
    "addr:street":"Calle De On\u0303Ati;/ N",
    "iso:country":"ES",
    "sg:address":"Calle de O\u00d1ati, S/n",
    "sg:city":"Vitoria-gasteiz",
    "sg:orig_category":"Tapicer\u00cdas",
    "sg:phone":"+34 945 28 99 69",
    "sg:postcode":"01013",
    "sg:province":"\u00c1lava",
    "wof:name":"Oses Romero Jose Ignacio",
    "wof:placetype":"venue"
},
  "geometry": {"coordinates":[-2.659678936,42.8587608337],"type":"Point"}
}