{
  "type": "Feature",
  "properties": {
    "iso:country":"ES",
    "sg:address":"Calle de Cuesta Amalia, S/n",
    "sg:city":"Pozo Alcon",
    "sg:orig_category":"Formaci\u00d3n Continuada (variada)",
    "sg:phone":"+34 953 73 80 62",
    "sg:postcode":"23485",
    "sg:province":"Ja\u00e9n",
    "wof:name":"Ayuntamiento De Pozo Alcon",
    "wof:placetype":"venue"
},
  "geometry": {"coordinates":[-2.9372222424,37.7067871094],"type":"Point"}
}