{
  "type": "Feature",
  "properties": {
    "iso:country":"ES",
    "sg:address":"Calle de Rodancha, 7",
    "sg:city":"Logro\u00f1o",
    "sg:orig_category":"Centros P\u00dablicos De Formaci\u00d3n Profesional Y T\u00c9cnica",
    "sg:phone":"+34 941 23 77 96",
    "sg:postcode":"26004",
    "sg:province":"La Rioja",
    "wof:name":"Colegio Oficial De Agentes Comerciales",
    "wof:placetype":"venue"
},
  "geometry": {"coordinates":[-2.4388968945,42.4700202942],"type":"Point"}
}