{
  "type": "Feature",
  "properties": {
    "addr:full":"Carrer de Joan Larrea, 2 Mataro Barcelona 08302",
    "addr:housenumber":"2",
    "addr:postcode":"08302",
    "addr:street":"Carrer De Joan Larrea",
    "iso:country":"ES",
    "sg:address":"Carrer de Joan Larrea, 2",
    "sg:city":"Mataro",
    "sg:orig_category":"Electricidad: Instaladores",
    "sg:phone":"+34 937 41 53 33",
    "sg:postcode":"08302",
    "sg:province":"Barcelona",
    "wof:name":"Climacon S.b.s S.l",
    "wof:placetype":"venue"
},
  "geometry": {"coordinates":[2.4333360195,41.5371284485],"type":"Point"}
}