{
  "type": "Feature",
  "properties": {
    "iso:country":"ES",
    "sg:address":"Carrer de Montau, 29",
    "sg:city":"Santa Eulalia",
    "sg:orig_category":"Desinfecci\u00d3n, Desinsectaci\u00d3n, Desratizaci\u00d3n",
    "sg:phone":"+34 936 39 10 64",
    "sg:postcode":"08859",
    "sg:province":"Barcelona",
    "wof:name":"Coll I Miro Tractaments S.l.",
    "wof:placetype":"venue"
},
  "geometry": {"coordinates":[1.9208400249,41.3350906372],"type":"Point"}
}