{
  "type": "Feature",
  "properties": {
    "iso:country":"ES",
    "sg:address":"Calle de Leon Y Castillo, 295",
    "sg:city":"Palmas De Gran Canaria",
    "sg:orig_category":"Centros P\u00dablicos De Formaci\u00d3n Profesional Y T\u00c9cnica",
    "sg:phone":"+34 928 24 38 48",
    "sg:postcode":"35005",
    "sg:province":"Las Palmas",
    "wof:name":"Colegio De Ingenieros De Caminos Canales Y Puertos",
    "wof:placetype":"venue"
},
  "geometry": {"coordinates":[-15.4299116135,28.1274261475],"type":"Point"}
}