{
  "type": "Feature",
  "properties": {
    "addr:full":"Carr Correu Vell, 1 Lleida Lleida 25002",
    "addr:housenumber":"1",
    "addr:postcode":"25002",
    "addr:street":"Carr Correu Vell",
    "iso:country":"ES",
    "sg:address":"Carr Correu Vell, 1",
    "sg:city":"Lleida",
    "sg:orig_category":"Art\u00cdculos De Regalo (al Por Menor)",
    "sg:phone":"+34 973 26 88 37",
    "sg:postcode":"25002",
    "sg:province":"Lleida",
    "wof:name":"Codina Castella Juan",
    "wof:placetype":"venue"
},
  "geometry": {"coordinates":[0.6229829788,41.6122245789],"type":"Point"}
}