{
  "type": "Feature",
  "properties": {
    "addr:full":"Carrer de Lluis Millet, S/n Mollet Valles Barcelona 08100",
    "addr:postcode":"08100",
    "addr:street":"Carrer De Lluis Millet S / N",
    "iso:country":"ES",
    "sg:address":"Carrer de Lluis Millet, S/n",
    "sg:city":"Mollet Valles",
    "sg:orig_category":"Asistencia Social",
    "sg:phone":"+34 935 93 93 53",
    "sg:postcode":"08100",
    "sg:province":"Barcelona",
    "wof:name":"Institut Municipal De Serveis Als Discapacitats De Mollet Del Valles",
    "wof:placetype":"venue"
},
  "geometry": {"coordinates":[2.2187550068,41.5485458374],"type":"Point"}
}