{
  "type": "Feature",
  "properties": {
    "iso:country":"ES",
    "sg:address":"Calle de Federico Coullaut Valera, 2",
    "sg:city":"Hellin",
    "sg:orig_category":"Complementos De Vestir (al Por Menor)",
    "sg:phone":"+34 967 30 78 70",
    "sg:postcode":"02400",
    "sg:province":"Albacete",
    "wof:name":"Guerrero Catalan Aurelia",
    "wof:placetype":"venue"
},
  "geometry": {"coordinates":[-1.7011450529,38.508556366],"type":"Point"}
}