{
  "type": "Feature",
  "properties": {
    "addr:full":"Calle de San Miguel, S/n Ciriza Navarra 31174",
    "addr:housenumber":"s",
    "addr:postcode":"31174",
    "addr:street":"Calle De San Miguel;/ N",
    "iso:country":"ES",
    "sg:address":"Calle de San Miguel, S/n",
    "sg:city":"Ciriza",
    "sg:orig_category":"Renovaci\u00d3n Inmobiliaria",
    "sg:phone":"+34 948 32 92 47",
    "sg:postcode":"31174",
    "sg:province":"Navarra",
    "wof:name":"Salas Juango Francisco Javier",
    "wof:placetype":"venue"
},
  "geometry": {"coordinates":[-1.8284540176,42.7905654907],"type":"Point"}
}