{
  "type": "Feature",
  "properties": {
    "iso:country":"ES",
    "sg:address":"Carrer de Monterols, 6",
    "sg:city":"Barcelona",
    "sg:orig_category":"Arquitectos",
    "sg:phone":"+34 932 03 41 57",
    "sg:postcode":"08034",
    "sg:province":"Barcelona",
    "wof:name":"De La Calzada Alvarez Carmen",
    "wof:placetype":"venue"
},
  "geometry": {"coordinates":[2.1218750477,41.3969726562],"type":"Point"}
}