{
  "type": "Feature",
  "properties": {
    "iso:country":"ES",
    "sg:address":"Ctra. Guare\u00f1a, S/n",
    "sg:city":"Cristina",
    "sg:orig_category":"Aceites Y Grasas Alimentarias (fabricaci\u00d3n, Al Por Mayor)",
    "sg:phone":"+34 924 35 10 11",
    "sg:postcode":"06479",
    "sg:province":"Badajoz",
    "wof:name":"Sociedad Cooperativa Limitada San Sebastian De Cristina",
    "wof:placetype":"venue"
},
  "geometry": {"coordinates":[-6.0997638702,38.8389701843],"type":"Point"}
}