{
  "type": "Feature",
  "properties": {
    "addr:full":"Ctra. Daganzo, Km. 0001,5 Alcala Henares Madrid 28806",
    "addr:postcode":"28806",
    "addr:street":"Ctra. Daganzo Km. 0001,5",
    "iso:country":"ES",
    "sg:address":"Ctra. Daganzo, Km. 0001,5",
    "sg:city":"Alcala Henares",
    "sg:orig_category":"Alquiler De Gr\u00daas",
    "sg:phone":"+34 918 89 28 10",
    "sg:postcode":"28806",
    "sg:province":"Madrid",
    "sg:website":"www.gruascorrea.com",
    "wof:name":"Correa Monedero Santiago",
    "wof:placetype":"venue"
},
  "geometry": {"coordinates":[-3.422385931,40.5286216736],"type":"Point"}
}