{
  "type": "Feature",
  "properties": {
    "addr:full":"Calle de Villavendimio, 6 Madrid Madrid 28021",
    "addr:housenumber":"6",
    "addr:postcode":"28021",
    "addr:street":"Calle De Villavendimio",
    "iso:country":"ES",
    "sg:address":"Calle de Villavendimio, 6",
    "sg:city":"Madrid",
    "sg:orig_category":"Contenedores (mercanc\u00cdas)",
    "sg:phone":"+34 917 98 33 93",
    "sg:postcode":"28021",
    "sg:province":"Madrid",
    "wof:name":"Airtrans S.l.",
    "wof:placetype":"venue"
},
  "geometry": {"coordinates":[-3.7144730091,40.3488922119],"type":"Point"}
}