{
  "type": "Feature",
  "properties": {
    "addr:full":"Calle de Alfambra, S/n Malaga M\u00e1laga 29006",
    "addr:housenumber":"s / n",
    "addr:postcode":"29006",
    "addr:street":"Calle De Alfambra;Ma\u0301Laga",
    "iso:country":"ES",
    "sg:address":"Calle de Alfambra, S/n",
    "sg:city":"Malaga",
    "sg:orig_category":"Ropa Para Ni\u00d1os (al Por Menor)",
    "sg:phone":"+34 952 35 63 64",
    "sg:postcode":"29006",
    "sg:province":"M\u00e1laga",
    "wof:name":"Ramirez Villar Jose Antonio",
    "wof:placetype":"venue"
},
  "geometry": {"coordinates":[-4.44181633,36.7106285095],"type":"Point"}
}