{
  "type": "Feature",
  "properties": {
    "iso:country":"ES",
    "sg:address":"Ctra Montcada, 630",
    "sg:city":"Terrassa",
    "sg:orig_category":"Veh\u00cdculos De Ocasi\u00d3n",
    "sg:phone":"+34 937 83 57 74",
    "sg:postcode":"08223",
    "sg:province":"Barcelona",
    "sg:website":"antoblanc@hotmail.com",
    "wof:name":"Blanco Ramirez Antonio Jose",
    "wof:placetype":"venue"
},
  "geometry": {"coordinates":[2.0106620789,41.55701828],"type":"Point"}
}