{
  "type": "Feature",
  "properties": {
    "addr:full":"Pol Ind Tres De Oros, S/n Arjona Ja\u00e9n 23760",
    "addr:housenumber":"s / n",
    "addr:postcode":"23760",
    "addr:street":"Jae\u0301N",
    "iso:country":"ES",
    "sg:address":"Pol Ind Tres De Oros, S/n",
    "sg:city":"Arjona",
    "sg:orig_category":"Administradores De Bienes Y Delegados De Comunidades De Propietarios",
    "sg:phone":"+34 953 51 80 87",
    "sg:postcode":"23760",
    "sg:province":"Ja\u00e9n",
    "wof:name":"Vaca Sanchez Josefa",
    "wof:placetype":"venue"
},
  "geometry": {"coordinates":[-4.0658540726,37.9382896423],"type":"Point"}
}