{
  "type": "Feature",
  "properties": {
    "addr:full":"Calle de Arcos, 15 Lebrija Sevilla 41740",
    "addr:housenumber":"15",
    "addr:postcode":"41740",
    "addr:street":"Calle De Arcos",
    "iso:country":"ES",
    "sg:address":"Calle de Arcos, 15",
    "sg:city":"Lebrija",
    "sg:orig_category":"Parafarmacias",
    "sg:phone":"+34 955 97 31 15",
    "sg:postcode":"41740",
    "sg:province":"Sevilla",
    "wof:name":"Garcia Vidal Manuela",
    "wof:placetype":"venue"
},
  "geometry": {"coordinates":[-6.0776734352,36.9184951782],"type":"Point"}
}