{
  "type": "Feature",
  "properties": {
    "addr:full":"Loiolako Inazio Hiribidea, 1 Azpeitia Guip\u00f9zcoa 20730",
    "addr:housenumber":"1",
    "addr:postcode":"20730",
    "addr:street":"Loiolako Inazio Hiribidea;Guipu\u0300Zcoa",
    "iso:country":"ES",
    "sg:address":"Loiolako Inazio Hiribidea, 1",
    "sg:city":"Azpeitia",
    "sg:orig_category":"Papeler\u00cdas, Librer\u00cdas",
    "sg:phone":"+34 943 15 01 32",
    "sg:postcode":"20730",
    "sg:province":"Guip\u00f9zcoa",
    "wof:name":"Maria Luisa Odriozola Mugica",
    "wof:placetype":"venue"
},
  "geometry": {"coordinates":[-2.270802021,43.1808929443],"type":"Point"}
}