{
  "type": "Feature",
  "properties": {
    "addr:full":"Calle de Tricio, Km. 0138,0 Najera La Rioja 26300",
    "addr:postcode":"26300",
    "addr:street":"Calle De Tricio Km. 0138,0 Najera;Rioja",
    "iso:country":"ES",
    "sg:address":"Calle de Tricio, Km. 0138,0",
    "sg:city":"Najera",
    "sg:orig_category":"Fabricaci\u00d3n De Harinas, S\u00c9molas, Productos De Elaboraci\u00d3n Del Grano",
    "sg:phone":"+34 941 36 33 64",
    "sg:postcode":"26300",
    "sg:province":"La Rioja",
    "wof:name":"Harinas Vazquez Sociedad Anonima",
    "wof:placetype":"venue"
},
  "geometry": {"coordinates":[-2.7281990051,42.4162445068],"type":"Point"}
}