{
  "type": "Feature",
  "properties": {
    "addr:full":"Calle de Puertas De Pro, 19 Soria Soria 42002",
    "addr:housenumber":"19",
    "addr:postcode":"42002",
    "addr:street":"Calle De Puertas De Pro",
    "iso:country":"ES",
    "sg:address":"Calle de Puertas De Pro, 19",
    "sg:city":"Soria",
    "sg:orig_category":"Copas, Insignias, Trofeos",
    "sg:phone":"+34 975 21 12 24",
    "sg:postcode":"42002",
    "sg:province":"Soria",
    "wof:name":"Romero De Leon Alejandro",
    "wof:placetype":"venue"
},
  "geometry": {"coordinates":[-2.467869997,41.765411377],"type":"Point"}
}