{
  "type": "Feature",
  "properties": {
    "addr:full":"Calle de Mercurio, 14 Arganda Madrid 28500",
    "addr:housenumber":"14",
    "addr:postcode":"28500",
    "addr:street":"Calle De Mercurio",
    "iso:country":"ES",
    "sg:address":"Calle de Mercurio, 14",
    "sg:city":"Arganda",
    "sg:orig_category":"Metalurgia",
    "sg:phone":"+34 918 70 34 94",
    "sg:postcode":"28500",
    "sg:province":"Madrid",
    "wof:name":"Trede S.a.",
    "wof:placetype":"venue"
},
  "geometry": {"coordinates":[-3.466766119,40.2991065979],"type":"Point"}
}