{
  "type": "Feature",
  "properties": {
    "addr:full":"Tarragona, 17 S. Jaume Enveja Tarragona 43877",
    "addr:housenumber":"17",
    "addr:postcode":"43877",
    "addr:street":"Tarragona;S. Jaume Enveja",
    "iso:country":"ES",
    "sg:address":"Tarragona, 17",
    "sg:city":"S. Jaume Enveja",
    "sg:classifiers":[
        {
            "category":"Taxi",
            "type":"Transportation"
        }
    ],
    "sg:phone":"+34 977 46 80 63",
    "sg:postcode":"43877",
    "sg:province":"Tarragona",
    "wof:name":"Cid Balague Jesus",
    "wof:placetype":"venue"
},
  "geometry": {"coordinates":[0.7200449705,40.7053794861],"type":"Point"}
}