{
  "type": "Feature",
  "properties": {
    "addr:full":"Calle de Carnicerias, 24 Salvatierra O Agurain \u00c1lava 01200",
    "addr:housenumber":"24",
    "addr:postcode":"01200",
    "addr:street":"Calle De Carnicerias;A\u0301Lava",
    "iso:country":"ES",
    "sg:address":"Calle de Carnicerias, 24",
    "sg:city":"Salvatierra O Agurain",
    "sg:orig_category":"Asociaciones, Organismos Culturales Y Socioeducativos",
    "sg:phone":"+34 945 30 09 76",
    "sg:postcode":"01200",
    "sg:province":"\u00c1lava",
    "wof:name":"Asociacion Sagarmin",
    "wof:placetype":"venue"
},
  "geometry": {"coordinates":[-2.3893313408,42.8525505066],"type":"Point"}
}