{
  "type": "Feature",
  "properties": {
    "iso:country":"ES",
    "sg:address":"Av Catalunya, 140",
    "sg:city":"Hospitalet Llobregat",
    "sg:orig_category":"Peluqueros: De Se\u00d1oras",
    "sg:phone":"+34 933 33 10 43",
    "sg:postcode":"08905",
    "sg:province":"Barcelona",
    "wof:name":"Abellan Barra Jose",
    "wof:placetype":"venue"
},
  "geometry": {"coordinates":[2.109399,41.368423],"type":"Point"}
}