{
  "type": "Feature",
  "properties": {
    "addr:full":"Avda Valladolid, 18 Tudela Duero Valladolid 47320",
    "addr:housenumber":"18;duero",
    "addr:postcode":"47320",
    "addr:street":"Avda Valladolid",
    "iso:country":"ES",
    "sg:address":"Avda Valladolid, 18",
    "sg:city":"Tudela Duero",
    "sg:orig_category":"Molduras, Junquillos, Listones Y Molduras Perforadas",
    "sg:phone":"+34 983 52 06 79",
    "sg:postcode":"47320",
    "sg:province":"Valladolid",
    "wof:name":"Lopez Rodrigo Pedro",
    "wof:placetype":"venue"
},
  "geometry": {"coordinates":[-4.5824460983,41.5871315002],"type":"Point"}
}