{
  "type": "Feature",
  "properties": {
    "iso:country":"ES",
    "sg:address":"Carr Creu, 14",
    "sg:city":"Girona",
    "sg:orig_category":"Arquitectos",
    "sg:phone":"+34 972 21 58 82",
    "sg:postcode":"17002",
    "sg:province":"Girona",
    "wof:name":"Elortegui Aburruzaga Valenti",
    "wof:placetype":"venue"
},
  "geometry": {"coordinates":[2.8187448978,41.9808616638],"type":"Point"}
}