{
  "type": "Feature",
  "properties": {
    "iso:country":"ES",
    "sg:address":"Calle de Antonio Lloret, 73",
    "sg:city":"Alberic",
    "sg:orig_category":"Promotores Constructores",
    "sg:phone":"+34 962 44 06 37",
    "sg:postcode":"46260",
    "sg:province":"Valencia",
    "wof:name":"Ingien Construc S-b S.l.",
    "wof:placetype":"venue"
},
  "geometry": {"coordinates":[-0.5238015056,39.1121063232],"type":"Point"}
}