{
  "type": "Feature",
  "properties": {
    "iso:country":"ES",
    "sg:address":"Calle de Rafael Mateos, 4",
    "sg:city":"Santaella",
    "sg:orig_category":"Muebles, Minoristas",
    "sg:phone":"+34 957 31 33 08",
    "sg:postcode":"14546",
    "sg:province":"C\u00f3rdoba",
    "wof:name":"Muebles Y Carpinteria Carmona S.l.",
    "wof:placetype":"venue"
},
  "geometry": {"coordinates":[-4.8445310593,37.564540863],"type":"Point"}
}