{
  "type": "Feature",
  "properties": {
    "iso:country":"ES",
    "sg:address":"Calle de Pozo De Hambre, 3",
    "sg:city":"Arroyo Luz",
    "sg:orig_category":"Fabricaci\u00d3n De Productos L\u00c1cteos Y Derivados",
    "sg:phone":"+34 927 27 01 77",
    "sg:postcode":"10900",
    "sg:province":"C\u00e1ceres",
    "wof:name":"Clesa Helados S.l.",
    "wof:placetype":"venue"
},
  "geometry": {"coordinates":[-6.5816159248,39.4856910706],"type":"Point"}
}