{
  "type": "Feature",
  "properties": {
    "iso:country":"ES",
    "sg:address":"Calle de Real, 69",
    "sg:city":"S. Fernando",
    "sg:orig_category":"Ingenier\u00cda, Centros De Estudios (diversos)",
    "sg:phone":"+34 956 59 31 35",
    "sg:postcode":"11100",
    "sg:province":"C\u00e1diz",
    "wof:name":"Proha Technologies S.l",
    "wof:placetype":"venue"
},
  "geometry": {"coordinates":[-6.1934227943,36.4668998718],"type":"Point"}
}