{
  "type": "Feature",
  "properties": {
    "addr:full":"Goicoechea-p I Plasencia, 28 Plasencia C\u00e1ceres 10600",
    "addr:housenumber":"28",
    "addr:postcode":"10600",
    "addr:street":"Plasencia;Ca\u0301Ceres",
    "iso:country":"ES",
    "sg:address":"Goicoechea-p I Plasencia, 28",
    "sg:city":"Plasencia",
    "sg:orig_category":"Fabricaci\u00d3n, Venta De Productos Base Farmac\u00c9uticos",
    "sg:phone":"+34 927 42 06 61",
    "sg:postcode":"10600",
    "sg:province":"C\u00e1ceres",
    "wof:name":"Cooperativa Farmaceutica Extreme\u00f1a",
    "wof:placetype":"venue"
},
  "geometry": {"coordinates":[-6.0898518562,40.0299453735],"type":"Point"}
}