{
  "type": "Feature",
  "properties": {
    "addr:full":"Ctra Torre Pacheco, Km. 0002,5 Los Alcazares Murcia 30710",
    "addr:postcode":"30710",
    "addr:street":"Ctra Torre Pacheco Km. 0002,5 Los Alcazares",
    "iso:country":"ES",
    "sg:address":"Ctra Torre Pacheco, Km. 0002,5",
    "sg:city":"Los Alcazares",
    "sg:orig_category":"Electricidad: Instaladores",
    "sg:phone":"+34 968 33 46 96",
    "sg:postcode":"30710",
    "sg:province":"Murcia",
    "wof:name":"Redes Electricas 2000 S.l.",
    "wof:placetype":"venue"
},
  "geometry": {"coordinates":[-0.8950669765,37.7512741089],"type":"Point"}
}