{
  "type": "Feature",
  "properties": {
    "iso:country":"ES",
    "sg:address":"Os Campos, S/n",
    "sg:city":"Campos",
    "sg:orig_category":"Electricidad: Instaladores",
    "sg:phone":"+34 981 50 07 33",
    "sg:postcode":"15819",
    "sg:province":"La Coru\u00f1a",
    "wof:name":"Electro Brandeso Sociedad Cooperativa Limitada",
    "wof:placetype":"venue"
},
  "geometry": {"coordinates":[-8.1643543243,42.9630203247],"type":"Point"}
}