{
  "type": "Feature",
  "properties": {
    "addr:full":"Calle de Mejorana, S/n Almeria Almer\u00eda 04007",
    "addr:housenumber":"s / n",
    "addr:postcode":"04007",
    "addr:street":"Calle De Mejorana",
    "iso:country":"ES",
    "sg:address":"Calle de Mejorana, S/n",
    "sg:city":"Almeria",
    "sg:orig_category":"Mec\u00c1nico Del Autom\u00d3vil",
    "sg:phone":"+34 950 27 06 32",
    "sg:postcode":"04007",
    "sg:province":"Almer\u00eda",
    "wof:name":"Galvez Iba\u00f1ez Felipe",
    "wof:placetype":"venue"
},
  "geometry": {"coordinates":[-2.443723917,36.8348846436],"type":"Point"}
}