{
  "type": "Feature",
  "properties": {
    "addr:full":"Carrer de Muralla (de La), 2 Arbo\u00e7 Tarragona 43720",
    "addr:housenumber":"2",
    "addr:postcode":"43720",
    "addr:street":"Carrer De Muralla De La",
    "iso:country":"ES",
    "sg:address":"Carrer de Muralla (de La), 2",
    "sg:city":"Arbo\u00e7",
    "sg:orig_category":"Alimentaci\u00d3n General (al Por Menor)",
    "sg:phone":"+34 977 67 02 35",
    "sg:postcode":"43720",
    "sg:province":"Tarragona",
    "wof:name":"Montserrat Ferrer Jose",
    "wof:placetype":"venue"
},
  "geometry": {"coordinates":[1.6022410393,41.2665596008],"type":"Point"}
}