{
  "type": "Feature",
  "properties": {
    "iso:country":"ES",
    "sg:address":"Calle de Ildefonso Sanchez Del Rio, 6",
    "sg:city":"Pola De Siero",
    "sg:orig_category":"Bancos",
    "sg:phone":"+34 985 72 11 05",
    "sg:postcode":"33510",
    "sg:province":"Asturias",
    "wof:name":"Bt Espa\u00d1a Compa\u00d1ia De Servicios Globales De Telecomunicaciones S.a.u.",
    "wof:placetype":"venue"
},
  "geometry": {"coordinates":[-5.663424015,43.3916358948],"type":"Point"}
}