{
  "type": "Feature",
  "properties": {
    "iso:country":"ES",
    "sg:address":"Carrer de Frederic Soler, 55",
    "sg:city":"Prat Llobregat",
    "sg:orig_category":"Farmacias",
    "sg:phone":"+34 933 79 48 07",
    "sg:postcode":"08820",
    "sg:province":"Barcelona",
    "wof:name":"Martinez Larriba Margarita",
    "wof:placetype":"venue"
},
  "geometry": {"coordinates":[2.0973858833,41.3252754211],"type":"Point"}
}