{
  "type": "Feature",
  "properties": {
    "iso:country":"ES",
    "sg:address":"Avda Huesca De, 17",
    "sg:city":"Sari\u00f1ena",
    "sg:orig_category":"Carnicer\u00cdas, Carnicer\u00cdas",
    "sg:phone":"+34 974 57 07 94",
    "sg:postcode":"22200",
    "sg:province":"Huesca",
    "wof:name":"Sagarra Gracia Primitivo",
    "wof:placetype":"venue"
},
  "geometry": {"coordinates":[-0.1568460017,41.7954864502],"type":"Point"}
}