{
  "type": "Feature",
  "properties": {
    "addr:full":"Avda Generalisimo, S/n Palacios Del Sil Le\u00f3n 24495",
    "addr:housenumber":"s / n",
    "addr:postcode":"24495",
    "addr:street":"Avda Generalisimo",
    "iso:country":"ES",
    "sg:address":"Avda Generalisimo, S/n",
    "sg:city":"Palacios Del Sil",
    "sg:orig_category":"Centros De Educaci\u00d3n Especial",
    "sg:phone":"+34 987 48 71 16",
    "sg:postcode":"24495",
    "sg:province":"Le\u00f3n",
    "wof:name":"Colegio Publico Ribas De Sil",
    "wof:placetype":"venue"
},
  "geometry": {"coordinates":[-6.4340538979,42.8757514954],"type":"Point"}
}