{
  "type": "Feature",
  "properties": {
    "iso:country":"ES",
    "sg:address":"Rua Castelao, 2",
    "sg:city":"Grove",
    "sg:orig_category":"Peluquer\u00cdas, Peluquer\u00cda Mixta",
    "sg:phone":"+34 986 73 05 78",
    "sg:postcode":"36980",
    "sg:province":"Pontevedra",
    "wof:name":"Mascato Briones Jesusa",
    "wof:placetype":"venue"
},
  "geometry": {"coordinates":[-8.8583307266,42.4907493591],"type":"Point"}
}