{
  "type": "Feature",
  "properties": {
    "addr:full":"Avda Constitucion, 108 Jaraiz Vera C\u00e1ceres 10400",
    "addr:housenumber":"108",
    "addr:postcode":"10400",
    "addr:street":"Avda Constitucion",
    "iso:country":"ES",
    "sg:address":"Avda Constitucion, 108",
    "sg:city":"Jaraiz Vera",
    "sg:orig_category":"Producci\u00d3n, Venta De Productos De Agricultura Biol\u00d3gica",
    "sg:phone":"+34 927 46 02 42",
    "sg:postcode":"10400",
    "sg:province":"C\u00e1ceres",
    "wof:name":"Sat Asociaciones Agrupadas Tab",
    "wof:placetype":"venue"
},
  "geometry": {"coordinates":[-5.7543549538,40.057598114],"type":"Point"}
}