{
  "type": "Feature",
  "properties": {
    "addr:full":"Calle de Jose Del Hierro, 41 Madrid Madrid 28027",
    "addr:housenumber":"41",
    "addr:postcode":"madrid;28027",
    "addr:street":"Calle De Jose Del Hierro",
    "iso:country":"ES",
    "sg:address":"Calle de Jose Del Hierro, 41",
    "sg:city":"Madrid",
    "sg:orig_category":"Peluquer\u00cdas, Peluquer\u00cda Mixta",
    "sg:phone":"+34 913 77 00 22",
    "sg:postcode":"28027",
    "sg:province":"Madrid",
    "wof:name":"Mamiestilistas Sl",
    "wof:placetype":"venue"
},
  "geometry": {"coordinates":[-3.6441829205,40.4402694702],"type":"Point"}
}