{
  "type": "Feature",
  "properties": {
    "iso:country":"ES",
    "sg:address":"Calle de Sierra De Aralar, 27",
    "sg:city":"Donostia-san Sebastian",
    "sg:orig_category":"Promotores Constructores",
    "sg:phone":"+34 943 47 29 38",
    "sg:postcode":"20014",
    "sg:province":"Guip\u00f9zcoa",
    "wof:name":"Redondo Gonzalez Juan",
    "wof:placetype":"venue"
},
  "geometry": {"coordinates":[-1.9657740593,43.3106422424],"type":"Point"}
}