{
  "type": "Feature",
  "properties": {
    "iso:country":"ES",
    "sg:address":"Calle de Ramon Y Cajal, 24",
    "sg:city":"Santurtzi",
    "sg:orig_category":"Estancos",
    "sg:phone":"+34 944 83 75 87",
    "sg:postcode":"48980",
    "sg:province":"Vizcaya",
    "wof:name":"Pilar Casado - Expenduria N\u00ba 8",
    "wof:placetype":"venue"
},
  "geometry": {"coordinates":[-3.0354590416,43.3304595947],"type":"Point"}
}