{
  "type": "Feature",
  "properties": {
    "addr:full":"Calle de Pintor Morales, 11 Merida Badajoz 06800",
    "addr:housenumber":"11",
    "addr:postcode":"06800",
    "addr:street":"Calle De Pintor Morales",
    "iso:country":"ES",
    "sg:address":"Calle de Pintor Morales, 11",
    "sg:city":"Merida",
    "sg:orig_category":"Institutos De Belleza",
    "sg:phone":"+34 924 30 06 60",
    "sg:postcode":"06800",
    "sg:province":"Badajoz",
    "wof:name":"Texeira Guerrero Marta Maria",
    "wof:placetype":"venue"
},
  "geometry": {"coordinates":[-6.3425531387,38.9107437134],"type":"Point"}
}