{
  "type": "Feature",
  "properties": {
    "addr:full":"Calle de Nuestro Padre Jesus, 7 Gabia Grande Granada 18110",
    "addr:housenumber":"7",
    "addr:postcode":"18110",
    "addr:street":"Calle De Nuestro Padre Jesus",
    "iso:country":"ES",
    "sg:address":"Calle de Nuestro Padre Jesus, 7",
    "sg:city":"Gabia Grande",
    "sg:orig_category":"Promotores Constructores",
    "sg:phone":"+34 958 58 04 81",
    "sg:postcode":"18110",
    "sg:province":"Granada",
    "wof:name":"Perti\u00f1ez Sanchez Rafael",
    "wof:placetype":"venue"
},
  "geometry": {"coordinates":[-3.6703779697,37.1329956055],"type":"Point"}
}