{
  "type": "Feature",
  "properties": {
    "addr:full":"Turia, 3 S. Antonio Benageber Valencia 46184",
    "addr:postcode":"46184",
    "addr:street":"Turia 3 S. Antonio Benageber",
    "iso:country":"ES",
    "sg:address":"Turia, 3",
    "sg:city":"S. Antonio Benageber",
    "sg:orig_category":"Ense\u00d1anza, Formaci\u00d3n Profesional: Aprendizaje",
    "sg:phone":"+34 961 35 12 02",
    "sg:postcode":"46184",
    "sg:province":"Valencia",
    "wof:name":"Ayuntamiento De San Antonio De Benageber",
    "wof:placetype":"venue"
},
  "geometry": {"coordinates":[-0.5005536079,39.5615119934],"type":"Point"}
}