{
  "type": "Feature",
  "properties": {
    "addr:full":"Calle de Macias Picavea, 14 Santander Cantabria 39003",
    "addr:housenumber":"14",
    "addr:postcode":"39003",
    "addr:street":"Calle De Macias Picavea",
    "iso:country":"ES",
    "sg:address":"Calle de Macias Picavea, 14",
    "sg:city":"Santander",
    "sg:orig_category":"Instalaci\u00d3n, Reparaci\u00d3n De Ascensores Y Montacargas",
    "sg:phone":"+34 942 21 79 61",
    "sg:postcode":"39003",
    "sg:province":"Cantabria",
    "sg:website":"www.otis.com",
    "wof:name":"Zardoya Otis S. A.",
    "wof:placetype":"venue"
},
  "geometry": {"coordinates":[-3.8016901016,43.4659080505],"type":"Point"}
}