{
  "type": "Feature",
  "properties": {
    "iso:country":"ES",
    "sg:address":"Jose Garrido, 16",
    "sg:city":"Padul",
    "sg:orig_category":"Agencias De Viajes",
    "sg:phone":"+34 958 77 31 10",
    "sg:postcode":"18640",
    "sg:province":"Granada",
    "wof:name":"Open Tours S.l.",
    "wof:placetype":"venue"
},
  "geometry": {"coordinates":[-3.622205019,37.0250816345],"type":"Point"}
}