{
  "type": "Feature",
  "properties": {
    "iso:country":"ES",
    "sg:address":"Carrer de Sant Cristofol, 3",
    "sg:city":"Lli\u00e7a Vall",
    "sg:orig_category":"Electricidad: Instaladores",
    "sg:phone":"+34 938 43 90 91",
    "sg:postcode":"08185",
    "sg:province":"Barcelona",
    "wof:name":"Instalaciones Y Reparaciones Del Valles S.l.",
    "wof:placetype":"venue"
},
  "geometry": {"coordinates":[2.2429590225,41.591758728],"type":"Point"}
}