{
  "type": "Feature",
  "properties": {
    "addr:full":"Calle de Ca\u00d1ada Real, 5 Montemayor Rio Salamanca 37727",
    "addr:housenumber":"5",
    "addr:postcode":"37727",
    "addr:street":"Calle De Can\u0303Ada Real",
    "iso:country":"ES",
    "sg:address":"Calle de Ca\u00d1ada Real, 5",
    "sg:city":"Montemayor Rio",
    "sg:orig_category":"Delegados, Agentes De Tr\u00c1nsito, Auxiliares De Transporte Internacional",
    "sg:phone":"+34 923 43 10 56",
    "sg:postcode":"37727",
    "sg:province":"Salamanca",
    "wof:name":"Martin Martin Jose Luis",
    "wof:placetype":"venue"
},
  "geometry": {"coordinates":[-5.8908014297,40.3508491516],"type":"Point"}
}