{
  "type": "Feature",
  "properties": {
    "iso:country":"ES",
    "sg:address":"Pl Del Mig De Can Clos, 2",
    "sg:city":"Barcelona",
    "sg:orig_category":"Fabricaci\u00d3n, Importaci\u00d3n De L\u00c1mparas Y Bombillas",
    "sg:phone":"+34 932 96 79 50",
    "sg:postcode":"08038",
    "sg:province":"Barcelona",
    "wof:name":"Valverde Daza Pedro",
    "wof:placetype":"venue"
},
  "geometry": {"coordinates":[2.1467399597,41.3619346619],"type":"Point"}
}