{
  "type": "Feature",
  "properties": {
    "iso:country":"ES",
    "sg:address":"Avda Americas (de Las), S/n",
    "sg:city":"Alcantarilla",
    "sg:orig_category":"Material Y Herramientas Agr\u00cdcolas",
    "sg:phone":"+34 968 89 11 11",
    "sg:postcode":"30820",
    "sg:province":"Murcia",
    "wof:name":"Asesores Y Tecnicas Agricola S.a.",
    "wof:placetype":"venue"
},
  "geometry": {"coordinates":[-1.211976409,37.9609603882],"type":"Point"}
}