{
  "type": "Feature",
  "properties": {
    "iso:country":"ES",
    "sg:address":"C/ Poeta Joan Valls, 14",
    "sg:city":"Alcoi",
    "sg:orig_category":"Productos Qu\u00cdmicos (fabricaci\u00d3n, Al Por Mayor)",
    "sg:phone":"+34 965 33 90 80",
    "sg:postcode":"03803",
    "sg:province":"Alicante",
    "wof:name":"Ecochemical S.l.",
    "wof:placetype":"venue"
},
  "geometry": {"coordinates":[-0.4761349857,38.7023849487],"type":"Point"}
}