{
  "type": "Feature",
  "properties": {
    "addr:full":"Calle de Llano Ponte, 15 Oviedo Asturias 33011",
    "addr:housenumber":"15",
    "addr:postcode":"33011",
    "addr:street":"Calle De Llano Ponte",
    "iso:country":"ES",
    "sg:address":"Calle de Llano Ponte, 15",
    "sg:city":"Oviedo",
    "sg:orig_category":"Asociaciones Y Clubs Deportivos",
    "sg:phone":"+34 985 11 41 77",
    "sg:postcode":"33011",
    "sg:province":"Asturias",
    "wof:name":"Carbaco",
    "wof:placetype":"venue"
},
  "geometry": {"coordinates":[-5.8483138084,43.3677482605],"type":"Point"}
}