{
  "type": "Feature",
  "properties": {
    "addr:full":"Pso. De Las Lomas, 79 Ejido Almer\u00eda 04700",
    "addr:housenumber":"79 ejido",
    "addr:postcode":"04700",
    "addr:street":"Las Lomas;Almeri\u0301A",
    "iso:country":"ES",
    "sg:address":"Pso. De Las Lomas, 79",
    "sg:city":"Ejido",
    "sg:orig_category":"Papeler\u00cdas, Librer\u00cdas",
    "sg:phone":"+34 950 48 12 70",
    "sg:postcode":"04700",
    "sg:province":"Almer\u00eda",
    "wof:name":"Cabeo Mu\u00d1oz Trinidad",
    "wof:placetype":"venue"
},
  "geometry": {"coordinates":[-2.8160340786,36.769569397],"type":"Point"}
}