{
  "type": "Feature",
  "properties": {
    "iso:country":"ES",
    "sg:address":"Ctra Mami A Viator (del), S/n",
    "sg:city":"Ca\u00e7ada De San Urbano",
    "sg:orig_category":"Asociaciones Humanitarias, De Cooperaci\u00d3n, De Acci\u00d3n Social",
    "sg:phone":"+34 950 29 19 37",
    "sg:postcode":"04120",
    "sg:province":"Almer\u00eda",
    "wof:name":"Asociacion Amigos De Alzheimer",
    "wof:placetype":"venue"
},
  "geometry": {"coordinates":[-2.4679217339,36.8401641846],"type":"Point"}
}