{
  "type": "Feature",
  "properties": {
    "iso:country":"ES",
    "sg:address":"Avda Alamos (los), S/n",
    "sg:city":"Pulpi",
    "sg:orig_category":"Electricidad Veh\u00cdculo",
    "sg:phone":"+34 950 46 41 29",
    "sg:postcode":"04640",
    "sg:province":"Almer\u00eda",
    "wof:name":"Electricidad Mu\u00d1oz Miras S.l",
    "wof:placetype":"venue"
},
  "geometry": {"coordinates":[-1.747838974,37.4072341919],"type":"Point"}
}