{
  "type": "Feature",
  "properties": {
    "iso:country":"ES",
    "sg:address":"Calle de Burdeos, 3",
    "sg:city":"Toledo",
    "sg:orig_category":"Reposter\u00cdas",
    "sg:phone":"+34 925 21 44 81",
    "sg:postcode":"45004",
    "sg:province":"Toledo",
    "wof:name":"Pages Romero Juan Jose",
    "wof:placetype":"venue"
},
  "geometry": {"coordinates":[-4.031686306,39.8703155518],"type":"Point"}
}