{
  "type": "Feature",
  "properties": {
    "addr:full":"Trva Dali, 10 Aranjuez Madrid 28300",
    "addr:housenumber":"10",
    "addr:postcode":"28300",
    "addr:street":"Trva Dali",
    "iso:country":"ES",
    "sg:address":"Trva Dali, 10",
    "sg:city":"Aranjuez",
    "sg:orig_category":"Abogados",
    "sg:phone":"+34 918 65 75 85",
    "sg:postcode":"28300",
    "sg:province":"Madrid",
    "wof:name":"Caballero Lorenzo Antonio",
    "wof:placetype":"venue"
},
  "geometry": {"coordinates":[-3.6004579067,40.0233001709],"type":"Point"}
}