{
  "type": "Feature",
  "properties": {
    "addr:full":"Calle de Eduardo Aunos, 32 Madrid Madrid 28028",
    "addr:housenumber":"32",
    "addr:postcode":"madrid;28028",
    "addr:street":"Calle De Eduardo Aunos",
    "iso:country":"ES",
    "sg:address":"Calle de Eduardo Aunos, 32",
    "sg:city":"Madrid",
    "sg:orig_category":"Internados & Ense\u00d1anza Privada",
    "sg:phone":"+34 915 73 31 54",
    "sg:postcode":"28028",
    "sg:province":"Madrid",
    "wof:name":"Congregacion Hijas De La Caridad San Vicente De Paul",
    "wof:placetype":"venue"
},
  "geometry": {"coordinates":[-3.6647157669,40.4219818115],"type":"Point"}
}