{
  "type": "Feature",
  "properties": {
    "addr:full":"Calle de Fontanales, 17 Palmas De Gran Canaria Las Palmas 35009",
    "addr:housenumber":"17",
    "addr:postcode":"35009",
    "addr:street":"Calle De Fontanales",
    "iso:country":"ES",
    "sg:address":"Calle de Fontanales, 17",
    "sg:city":"Palmas De Gran Canaria",
    "sg:orig_category":"Oficinas: Suministros Para (fabricaci\u00d3n, Al Por Mayor)",
    "sg:phone":"+34 928 46 08 57",
    "sg:postcode":"35009",
    "sg:province":"Las Palmas",
    "wof:name":"Quevedo Sosa Sebastian",
    "wof:placetype":"venue"
},
  "geometry": {"coordinates":[-15.426232338,28.1510391235],"type":"Point"}
}