{
  "type": "Feature",
  "properties": {
    "iso:country":"ES",
    "sg:address":"Plaz Colon (de), 17",
    "sg:city":"Cordoba",
    "sg:orig_category":"Ense\u00d1anza, Formaci\u00d3n Profesional: Aprendizaje",
    "sg:phone":"+34 957 47 57 44",
    "sg:postcode":"14001",
    "sg:province":"C\u00f3rdoba",
    "wof:name":"Instituto Social De Las Fuerzas Armadas",
    "wof:placetype":"venue"
},
  "geometry": {"coordinates":[-4.7794780731,37.8910293579],"type":"Point"}
}