{
  "type": "Feature",
  "properties": {
    "iso:country":"ES",
    "sg:address":"C/ Plana (la), 1",
    "sg:city":"Tarrega",
    "sg:orig_category":"M\u00c9dicos: Estomatolog\u00cda",
    "sg:phone":"+34 973 31 32 94",
    "sg:postcode":"25300",
    "sg:province":"Lleida",
    "wof:name":"Perez Vargas Juan Elias",
    "wof:placetype":"venue"
},
  "geometry": {"coordinates":[1.1405249834,41.6427497864],"type":"Point"}
}