{
  "type": "Feature",
  "properties": {
    "addr:full":"C/ Porta De La Morera, 6 Elche Alicante 03203",
    "addr:housenumber":"6",
    "addr:postcode":"03203",
    "addr:street":"C / Porta De La Morera",
    "iso:country":"ES",
    "sg:address":"C/ Porta De La Morera, 6",
    "sg:city":"Elche",
    "sg:orig_category":"Caf\u00c9s, Bares, Cervecer\u00cdas",
    "sg:phone":"+34 965 42 22 81",
    "sg:postcode":"03203",
    "sg:province":"Alicante",
    "wof:name":"Martinez Perez Ramon",
    "wof:placetype":"venue"
},
  "geometry": {"coordinates":[-0.694584012,38.2643814087],"type":"Point"}
}