{
  "type": "Feature",
  "properties": {
    "iso:country":"ES",
    "sg:address":"Ctra Badajoz, S/n",
    "sg:city":"Valverde Leganes",
    "sg:orig_category":"Cerrajer\u00cda, Ferrallista",
    "sg:phone":"+34 924 49 60 77",
    "sg:postcode":"06130",
    "sg:province":"Badajoz",
    "wof:name":"Garcia Zahi\u00f1os Antonio",
    "wof:placetype":"venue"
},
  "geometry": {"coordinates":[-6.9828391075,38.6747741699],"type":"Point"}
}