{
  "type": "Feature",
  "properties": {
    "iso:country":"ES",
    "sg:address":"Pase San Vicente, 35",
    "sg:city":"Valladolid",
    "sg:orig_category":"Centros Comerciales Y Grandes Tiendas",
    "sg:phone":"+34 983 39 81 23",
    "sg:postcode":"47013",
    "sg:province":"Valladolid",
    "wof:name":"Multiprecios Yeranhoa S.l.",
    "wof:placetype":"venue"
},
  "geometry": {"coordinates":[-4.7181119919,41.6430778503],"type":"Point"}
}