{
  "type": "Feature",
  "properties": {
    "addr:full":"Calle de Doctor Antonio Gonzalez, 4 Realejo Alto Santa Cruz De Tenerife 38410",
    "addr:housenumber":"4",
    "addr:postcode":"38410",
    "addr:street":"Calle De Doctor Antonio Gonzalez",
    "iso:country":"ES",
    "sg:address":"Calle de Doctor Antonio Gonzalez, 4",
    "sg:city":"Realejo Alto",
    "sg:orig_category":"Asociaciones Y Clubs Deportivos",
    "sg:phone":"+34 922 34 22 02",
    "sg:postcode":"38410",
    "sg:province":"Santa Cruz De Tenerife",
    "wof:name":"Mesa Espinola Vicente",
    "wof:placetype":"venue"
},
  "geometry": {"coordinates":[-16.5845718384,28.3797931671],"type":"Point"}
}