{
  "type": "Feature",
  "properties": {
    "addr:full":"A Hermida, S/n Roupar Lugo 27839",
    "addr:housenumber":"s",
    "addr:postcode":"27839",
    "addr:street":"/ N",
    "iso:country":"ES",
    "sg:address":"A Hermida, S/n",
    "sg:city":"Roupar",
    "sg:orig_category":"M\u00c9dicos: Estomatolog\u00cda",
    "sg:phone":"+34 982 17 92 39",
    "sg:postcode":"27839",
    "sg:province":"Lugo",
    "wof:name":"Buitron Lopez Elvira",
    "wof:placetype":"venue"
},
  "geometry": {"coordinates":[-7.5693798065,43.0095100403],"type":"Point"}
}