{
  "type": "Feature",
  "properties": {
    "addr:full":"Plaz Posito (el), S/n Jaen Ja\u00e9n 23001",
    "addr:postcode":"23001",
    "addr:street":"Plaz;El S / N Jaen Jae\u0301N",
    "iso:country":"ES",
    "sg:address":"Plaz Posito (el), S/n",
    "sg:city":"Jaen",
    "sg:orig_category":"Florister\u00cdas",
    "sg:phone":"+34 953 19 03 47",
    "sg:postcode":"23001",
    "sg:province":"Ja\u00e9n",
    "wof:name":"Colmenero De La Torre Maria Luisa",
    "wof:placetype":"venue"
},
  "geometry": {"coordinates":[-3.7887809277,37.7667160034],"type":"Point"}
}