{
  "type": "Feature",
  "properties": {
    "addr:full":"Pase Bachilleres, 10 Toledo Toledo 45003",
    "addr:postcode":"45003",
    "iso:country":"ES",
    "sg:address":"Pase Bachilleres, 10",
    "sg:city":"Toledo",
    "sg:orig_category":"Sociedades, Compa\u00d1\u00cdas Aseguradoras",
    "sg:phone":"+34 925 25 49 67",
    "sg:postcode":"45003",
    "sg:province":"Toledo",
    "wof:name":"Euromutua Seguros Y Reaseguros",
    "wof:placetype":"venue"
},
  "geometry": {"coordinates":[-4.0245890617,39.8694190979],"type":"Point"}
}