{
  "type": "Feature",
  "properties": {
    "iso:country":"ES",
    "sg:address":"Calle de Miracruz, 19",
    "sg:city":"Donostia-san Sebastian",
    "sg:orig_category":"Empresas De Portes Y Mensajer\u00cda",
    "sg:phone":"+34 943 32 04 69",
    "sg:postcode":"20001",
    "sg:province":"Guip\u00f9zcoa",
    "sg:website":"www.es.mbe.com",
    "wof:name":"Mail Reo S.l.",
    "wof:placetype":"venue"
},
  "geometry": {"coordinates":[-1.9728859663,43.3224525452],"type":"Point"}
}