{
  "type": "Feature",
  "properties": {
    "iso:country":"ES",
    "sg:address":"Pl Karl Marx, S/n",
    "sg:city":"Barcelona",
    "sg:orig_category":"Internados & Ense\u00d1anza Privada",
    "sg:phone":"+34 934 27 70 07",
    "sg:postcode":"08035",
    "sg:province":"Barcelona",
    "wof:name":"Hermanos De Las Escuelas Cristianas",
    "wof:placetype":"venue"
},
  "geometry": {"coordinates":[2.1615567207,41.4402427673],"type":"Point"}
}