{
  "type": "Feature",
  "properties": {
    "iso:country":"ES",
    "sg:address":"Calle de Portugal, 14",
    "sg:city":"Alacant",
    "sg:classifiers":[
        {
            "category":"Personal",
            "subcategory":"Barber",
            "type":"Services"
        }
    ],
    "sg:phone":"+34 965 92 22 22",
    "sg:postcode":"03003",
    "sg:province":"Alicante",
    "sg:tags":[
        "caballeros",
        "de",
        "peluqueros"
    ],
    "wof:name":"Abengozar Espi Juan Francisco",
    "wof:placetype":"venue"
},
  "geometry": {"coordinates":[-0.489221,38.340565],"type":"Point"}
}