{
  "type": "Feature",
  "properties": {
    "addr:full":"Avenida Ramon Y Cajal, 11 Albox Almer\u00eda 04800",
    "addr:housenumber":"11",
    "addr:postcode":"04800",
    "addr:street":"Avenida Ramon Y Cajal",
    "iso:country":"ES",
    "sg:address":"Avenida Ramon Y Cajal, 11",
    "sg:city":"Albox",
    "sg:orig_category":"Fotograf\u00cda Art\u00cdstica Y Retratos",
    "sg:phone":"+34 950 43 03 30",
    "sg:postcode":"04800",
    "sg:province":"Almer\u00eda",
    "wof:name":"Foto Imagen Caparros S.l.",
    "wof:placetype":"venue"
},
  "geometry": {"coordinates":[-2.1476771832,37.3871307373],"type":"Point"}
}