{
  "type": "Feature",
  "properties": {
    "addr:full":"Carrer de Esteve Terradas, 15 Barcelona Barcelona 08023",
    "addr:housenumber":"15",
    "addr:postcode":"08023",
    "addr:street":"Carrer De Esteve Terradas",
    "iso:country":"ES",
    "sg:address":"Carrer de Esteve Terradas, 15",
    "sg:city":"Barcelona",
    "sg:orig_category":"Inform\u00c1tica Equipo Y Programas (al Por Mayor)",
    "sg:phone":"+34 934 18 64 79",
    "sg:postcode":"08023",
    "sg:province":"Barcelona",
    "wof:name":"Silex Informatica S.l.",
    "wof:placetype":"venue"
},
  "geometry": {"coordinates":[2.1420230865,41.4126777649],"type":"Point"}
}