{
  "type": "Feature",
  "properties": {
    "addr:full":"Pla\u00c7 Alfons Iii, 6 Ciutadella Menorca Islas Baleares 07760",
    "addr:housenumber":"6",
    "addr:postcode":"07760",
    "addr:street":"Alfons Iii",
    "iso:country":"ES",
    "sg:address":"Pla\u00c7 Alfons Iii, 6",
    "sg:city":"Ciutadella Menorca",
    "sg:orig_category":"Radiocomunicaciones, Telefon\u00cda M\u00d3vil, Radiomensajer\u00cda: Servicios, Comercializaci\u00d3n",
    "sg:phone":"+34 971 48 22 23",
    "sg:postcode":"07760",
    "sg:province":"Islas Baleares",
    "wof:name":"Servifonia Menorca S.l.",
    "wof:placetype":"venue"
},
  "geometry": {"coordinates":[3.8410379887,40.0023536682],"type":"Point"}
}