{
  "type": "Feature",
  "properties": {
    "iso:country":"ES",
    "sg:address":"Rua Seis, S/n",
    "sg:city":"Negreira",
    "sg:orig_category":"Procuradores",
    "sg:phone":"+34 981 88 51 54",
    "sg:postcode":"15830",
    "sg:province":"La Coru\u00f1a",
    "wof:name":"Colegio De Procuradores De Santiago",
    "wof:placetype":"venue"
},
  "geometry": {"coordinates":[-8.7368841171,42.9089660645],"type":"Point"}
}