{
  "type": "Feature",
  "properties": {
    "addr:full":"B (p. I. La Nevera), S/n Mendavia Navarra 31587",
    "addr:housenumber":"s / n",
    "addr:postcode":"31587",
    "iso:country":"ES",
    "sg:address":"B (p. I. La Nevera), S/n",
    "sg:city":"Mendavia",
    "sg:orig_category":"Goma: Productos De Uso Industrial (fabricaci\u00d3n, Al Por Mayor)",
    "sg:phone":"+34 948 68 50 82",
    "sg:postcode":"31587",
    "sg:province":"Navarra",
    "wof:name":"Manipulados Mendavia S.l.",
    "wof:placetype":"venue"
},
  "geometry": {"coordinates":[-2.2146389484,42.4521636963],"type":"Point"}
}