{
  "type": "Feature",
  "properties": {
    "addr:full":"Calle de Nafarroa, 1 Arizgoiti Vizcaya 48970",
    "addr:housenumber":"1",
    "addr:postcode":"48970",
    "addr:street":"Calle De Nafarroa",
    "iso:country":"ES",
    "sg:address":"Calle de Nafarroa, 1",
    "sg:city":"Arizgoiti",
    "sg:orig_category":"Sociedades, Compa\u00d1\u00cdas Aseguradoras",
    "sg:phone":"+34 944 40 30 29",
    "sg:postcode":"48970",
    "sg:province":"Vizcaya",
    "wof:name":"Mapfre Servicios De Informatica",
    "wof:placetype":"venue"
},
  "geometry": {"coordinates":[-2.8873400688,43.2366294861],"type":"Point"}
}