{
  "type": "Feature",
  "properties": {
    "addr:full":"Calle de Bidebarrieta, 10 Bilbao Vizcaya 48005",
    "addr:housenumber":"10",
    "addr:postcode":"48005",
    "addr:street":"Calle De Bidebarrieta",
    "iso:country":"ES",
    "sg:address":"Calle de Bidebarrieta, 10",
    "sg:city":"Bilbao",
    "sg:orig_category":"Limpieza Con Chorro De Arena Y Con Granalla, Pulido",
    "sg:phone":"+34 944 15 25 75",
    "sg:postcode":"48005",
    "sg:province":"Vizcaya",
    "wof:name":"Aplicacion De Pinturas Paint S.l.",
    "wof:placetype":"venue"
},
  "geometry": {"coordinates":[-2.9244339466,43.258480072],"type":"Point"}
}