{
  "type": "Feature",
  "properties": {
    "addr:full":"Calle de Alejandro Rodriguez De Valcarcel, S/n Villarcayo Burgos 09550",
    "addr:housenumber":"s / n",
    "addr:postcode":"09550",
    "addr:street":"Calle De Alejandro Rodriguez De Valcarcel",
    "iso:country":"ES",
    "sg:address":"Calle de Alejandro Rodriguez De Valcarcel, S/n",
    "sg:city":"Villarcayo",
    "sg:orig_category":"Electricidad Veh\u00cdculo",
    "sg:phone":"+34 947 13 16 22",
    "sg:postcode":"09550",
    "sg:province":"Burgos",
    "wof:name":"Pereda Moneo Jose Antonio",
    "wof:placetype":"venue"
},
  "geometry": {"coordinates":[-3.5742249489,42.9368247986],"type":"Point"}
}