{
  "type": "Feature",
  "properties": {
    "iso:country":"ES",
    "sg:address":"Calle de Islas Baleares, 14",
    "sg:city":"Caceres",
    "sg:orig_category":"Agencias Y Agentes Comerciales, Representantes",
    "sg:phone":"+34 927 23 22 25",
    "sg:postcode":"10001",
    "sg:province":"C\u00e1ceres",
    "wof:name":"Rubio Alvarez Angel",
    "wof:placetype":"venue"
},
  "geometry": {"coordinates":[-6.3860311508,39.4751243591],"type":"Point"}
}