{
  "type": "Feature",
  "properties": {
    "iso:country":"ES",
    "sg:address":"Calle de Lavapies, 8",
    "sg:city":"Tabara",
    "sg:orig_category":"Art\u00cdculos Funerarios (al Por Menor)",
    "sg:phone":"+34 980 59 01 92",
    "sg:postcode":"49140",
    "sg:province":"Zamora",
    "wof:name":"Pernia Ballestero Juan",
    "wof:placetype":"venue"
},
  "geometry": {"coordinates":[-5.9600458145,41.82264328],"type":"Point"}
}