{
  "type": "Feature",
  "properties": {
    "iso:country":"ES",
    "sg:address":"Calle de Rio De Oro, S/n",
    "sg:city":"Gijon",
    "sg:orig_category":"Parques De Atracciones Y Centros De Esparcimiento",
    "sg:phone":"+34 985 16 45 69",
    "sg:postcode":"33209",
    "sg:province":"Asturias",
    "wof:name":"Sodicarsa.s.a.",
    "wof:placetype":"venue"
},
  "geometry": {"coordinates":[-5.6621818542,43.5328712463],"type":"Point"}
}