{
  "type": "Feature",
  "properties": {
    "iso:country":"ES",
    "sg:address":"Calle de Cantos Negros, 8",
    "sg:city":"Madrid",
    "sg:orig_category":"Arquitectos",
    "sg:phone":"+34 917 08 07 23",
    "sg:postcode":"28023",
    "sg:province":"Madrid",
    "wof:name":"Heredero Arquitectura Y Urbanismo S.c.p.",
    "wof:placetype":"venue"
},
  "geometry": {"coordinates":[-3.8332958221,40.4760475159],"type":"Point"}
}