{
  "type": "Feature",
  "properties": {
    "addr:full":"Carr Catalunya, 2 Bellver Cerdanya Lleida 25720",
    "addr:housenumber":"2",
    "addr:postcode":"25720",
    "addr:street":"Carr Catalunya",
    "iso:country":"ES",
    "sg:address":"Carr Catalunya, 2",
    "sg:city":"Bellver Cerdanya",
    "sg:orig_category":"Producci\u00d3n, Venta De Productos De Agricultura Biol\u00d3gica",
    "sg:phone":"+34 973 51 01 19",
    "sg:postcode":"25720",
    "sg:province":"Lleida",
    "wof:name":"Carol Canal Jaime",
    "wof:placetype":"venue"
},
  "geometry": {"coordinates":[1.7763129473,42.371257782],"type":"Point"}
}