{
  "type": "Feature",
  "properties": {
    "addr:full":"Botica, 3 Oropesa Toledo 45560",
    "addr:postcode":"45560",
    "iso:country":"ES",
    "sg:address":"Botica, 3",
    "sg:city":"Oropesa",
    "sg:orig_category":"T\u00c9cnicos Veterinarios",
    "sg:phone":"+34 925 45 03 85",
    "sg:postcode":"45560",
    "sg:province":"Toledo",
    "wof:name":"Santos-garcia Y Torres Francisco Javier",
    "wof:placetype":"venue"
},
  "geometry": {"coordinates":[-5.1742172241,39.9184112549],"type":"Point"}
}