{
  "type": "Feature",
  "properties": {
    "iso:country":"ES",
    "sg:address":"Calle de El Hondon, 5",
    "sg:city":"Cabezuela Valle",
    "sg:orig_category":"Sociedades, Compa\u00d1\u00cdas Aseguradoras",
    "sg:phone":"+34 927 47 22 58",
    "sg:postcode":"10610",
    "sg:province":"C\u00e1ceres",
    "wof:name":"Segurvaje S.l.",
    "wof:placetype":"venue"
},
  "geometry": {"coordinates":[-5.8073477745,40.1941413879],"type":"Point"}
}