{
  "type": "Feature",
  "properties": {
    "iso:country":"ES",
    "sg:address":"Huerto La Isla, S/n",
    "sg:city":"Alcudia",
    "sg:orig_category":"Frutas, Legumbres Frescas Y Tempranas (al Por Menor)",
    "sg:phone":"+34 962 54 30 08",
    "sg:postcode":"46250",
    "sg:province":"Valencia",
    "wof:name":"Sat Citricos Valencianos Opsh Numero 627",
    "wof:placetype":"venue"
},
  "geometry": {"coordinates":[-0.5070289969,39.1940689087],"type":"Point"}
}