{
  "type": "Feature",
  "properties": {
    "addr:full":"Avda Astronomia (de La), S/n Poligono De San Fernando De Henares Madrid 28830",
    "addr:postcode":"28830",
    "addr:street":"Avda Astronomia De La S / N Poligono De San",
    "iso:country":"ES",
    "sg:address":"Avda Astronomia (de La), S/n",
    "sg:city":"Poligono De San Fernando De Henares",
    "sg:orig_category":"Fabricaci\u00d3n De Jabones, Detergentes Y Lej\u00cdas",
    "sg:phone":"+34 916 56 62 54",
    "sg:postcode":"28830",
    "sg:province":"Madrid",
    "wof:name":"Productos Quimicos Iberin S.a.",
    "wof:placetype":"venue"
},
  "geometry": {"coordinates":[-3.5021440983,40.4477233887],"type":"Point"}
}