{
  "type": "Feature",
  "properties": {
    "addr:full":"Calle de Olimpica Conchita Puig, 1 Alcorcon Madrid 28923",
    "addr:housenumber":"1",
    "addr:postcode":"28923",
    "addr:street":"Calle De Olimpica Conchita Puig",
    "iso:country":"ES",
    "sg:address":"Calle de Olimpica Conchita Puig, 1",
    "sg:city":"Alcorcon",
    "sg:orig_category":"Empresas De Carpinter\u00cda",
    "sg:phone":"+34 916 12 32 74",
    "sg:postcode":"28923",
    "sg:province":"Madrid",
    "wof:name":"Aluminios Hermanos Garcia Luque S.l.",
    "wof:placetype":"venue"
},
  "geometry": {"coordinates":[-3.8197052479,40.3447990417],"type":"Point"}
}