{
  "type": "Feature",
  "properties": {
    "addr:full":"Calle de Jose M. Salaberria, 49 Donostia-san Sebastian Guip\u00f9zcoa 20010",
    "addr:housenumber":"49",
    "addr:postcode":"20010",
    "addr:street":"Calle De Jose M. Salaberria",
    "iso:country":"ES",
    "sg:address":"Calle de Jose M. Salaberria, 49",
    "sg:city":"Donostia-san Sebastian",
    "sg:orig_category":"Importaci\u00d3n",
    "sg:phone":"+34 943 47 39 61",
    "sg:postcode":"20010",
    "sg:province":"Guip\u00f9zcoa",
    "wof:name":"Sadeq Odeh Yaser",
    "wof:placetype":"venue"
},
  "geometry": {"coordinates":[-1.9799460173,43.3028831482],"type":"Point"}
}