{
  "type": "Feature",
  "properties": {
    "iso:country":"ES",
    "sg:address":"Avgd Vicent Andres Estelles, (de), 4",
    "sg:city":"Carlet",
    "sg:orig_category":"Promotores Constructores",
    "sg:phone":"+34 962 53 08 13",
    "sg:postcode":"46240",
    "sg:province":"Valencia",
    "wof:name":"Construccions Alcolara S.l.",
    "wof:placetype":"venue"
},
  "geometry": {"coordinates":[-0.5183410048,39.2215690613],"type":"Point"}
}