{
  "type": "Feature",
  "properties": {
    "iso:country":"ES",
    "sg:address":"Ctra. Salamanca, Km. 0061,0",
    "sg:city":"Vegas Coria",
    "sg:orig_category":"Frutas Y Legumbres Frescas (al Por Mayor)",
    "sg:phone":"+34 927 43 40 06",
    "sg:postcode":"10623",
    "sg:province":"C\u00e1ceres",
    "wof:name":"Sanchez Sanchez Julian",
    "wof:placetype":"venue"
},
  "geometry": {"coordinates":[-6.165222168,40.3793907166],"type":"Point"}
}