{
  "type": "Feature",
  "properties": {
    "addr:full":"Calle de Fuente Mariano, 8 Orgiva Granada 18400",
    "addr:housenumber":"8",
    "addr:postcode":"18400",
    "addr:street":"Calle De Fuente Mariano",
    "iso:country":"ES",
    "sg:address":"Calle de Fuente Mariano, 8",
    "sg:city":"Orgiva",
    "sg:orig_category":"Empresas De Carpinter\u00cda Met\u00c1lica",
    "sg:phone":"+34 958 78 57 29",
    "sg:postcode":"18400",
    "sg:province":"Granada",
    "wof:name":"Heredia Gomez Santiago Jorge",
    "wof:placetype":"venue"
},
  "geometry": {"coordinates":[-3.4262211323,36.9031333923],"type":"Point"}
}