{
  "type": "Feature",
  "properties": {
    "addr:full":"Carrer de Francesc Moragas, 6 S. Cugat Valles Barcelona 08172",
    "addr:housenumber":"6",
    "addr:postcode":"08172",
    "addr:street":"Carrer De Francesc Moragas;Barcelona",
    "iso:country":"ES",
    "sg:address":"Carrer de Francesc Moragas, 6",
    "sg:city":"S. Cugat Valles",
    "sg:orig_category":"Art\u00cdculos De Decoraci\u00d3n",
    "sg:phone":"+34 936 74 38 92",
    "sg:postcode":"08172",
    "sg:province":"Barcelona",
    "sg:website":"www.grupolober.com",
    "wof:name":"Garcia Ega\u00f1a Javier",
    "wof:placetype":"venue"
},
  "geometry": {"coordinates":[2.0821299553,41.4714508057],"type":"Point"}
}