{
  "type": "Feature",
  "properties": {
    "addr:full":"Vilamaior, S/n Novelua Lugo 27568",
    "addr:postcode":"27568",
    "addr:street":"Vilamaior S / N",
    "iso:country":"ES",
    "sg:address":"Vilamaior, S/n",
    "sg:city":"Novelua",
    "sg:orig_category":"Fabricaci\u00d3n, Venta De Cuadros, Accesorios Para Enmarcar",
    "sg:phone":"+34 982 18 37 94",
    "sg:postcode":"27568",
    "sg:province":"Lugo",
    "wof:name":"Marcos Monterroso",
    "wof:placetype":"venue"
},
  "geometry": {"coordinates":[-7.7804589272,42.8593635559],"type":"Point"}
}