{
  "type": "Feature",
  "properties": {
    "addr:full":"Calle de Carretas, 3 Madrid Madrid 28012",
    "addr:housenumber":"3",
    "addr:postcode":"28012",
    "addr:street":"Calle De Carretas",
    "iso:country":"ES",
    "sg:address":"Calle de Carretas, 3",
    "sg:city":"Madrid",
    "sg:orig_category":"Zapatos (al Por Menor)",
    "sg:phone":"+34 915 22 70 43",
    "sg:postcode":"28012",
    "sg:province":"Madrid",
    "wof:name":"Grecobar S.l.",
    "wof:placetype":"venue"
},
  "geometry": {"coordinates":[-3.7032570839,40.4165344238],"type":"Point"}
}