{
  "type": "Feature",
  "properties": {
    "iso:country":"ES",
    "sg:address":"Cami Son Ametler, 14",
    "sg:city":"Hostalot",
    "sg:orig_category":"Promotores Constructores",
    "sg:phone":"+34 971 42 65 01",
    "sg:postcode":"07198",
    "sg:province":"Islas Baleares",
    "wof:name":"Construcciones Egea Punzano S.l.",
    "wof:placetype":"venue"
},
  "geometry": {"coordinates":[2.7178099155,39.5789794922],"type":"Point"}
}