{
  "type": "Feature",
  "properties": {
    "addr:full":"Calle de Severino Pascual, 3 Iscar Valladolid 47420",
    "addr:housenumber":"3",
    "addr:postcode":"47420",
    "addr:street":"Calle De Severino Pascual",
    "iso:country":"ES",
    "sg:address":"Calle de Severino Pascual, 3",
    "sg:city":"Iscar",
    "sg:orig_category":"Estudios, Instalaci\u00d3n De Climatizaci\u00d3n",
    "sg:phone":"+34 983 62 01 68",
    "sg:postcode":"47420",
    "sg:province":"Valladolid",
    "wof:name":"Instalaciones Sange S.l.",
    "wof:placetype":"venue"
},
  "geometry": {"coordinates":[-4.5309491158,41.3612251282],"type":"Point"}
}