{
  "type": "Feature",
  "properties": {
    "addr:full":"Carrer de Vall, 12 Terrassa Barcelona 08221",
    "addr:housenumber":"12",
    "addr:postcode":"08221",
    "addr:street":"Carrer De Vall",
    "iso:country":"ES",
    "sg:address":"Carrer de Vall, 12",
    "sg:city":"Terrassa",
    "sg:orig_category":"Tapicer\u00cdas",
    "sg:phone":"+34 937 80 03 42",
    "sg:postcode":"08221",
    "sg:province":"Barcelona",
    "wof:name":"Casarramona Albero Montserrat",
    "wof:placetype":"venue"
},
  "geometry": {"coordinates":[2.0111439228,41.5611877441],"type":"Point"}
}