{
  "type": "Feature",
  "properties": {
    "iso:country":"ES",
    "sg:address":"Calle de Casino, 7",
    "sg:city":"Madrid",
    "sg:orig_category":"Centros De Educaci\u00d3n Especial",
    "sg:phone":"+34 915 27 52 81",
    "sg:postcode":"28005",
    "sg:province":"Madrid",
    "wof:name":"Colegio De Practicas Santa Maria",
    "wof:placetype":"venue"
},
  "geometry": {"coordinates":[-3.7068343163,40.4062042236],"type":"Point"}
}