{
  "type": "Feature",
  "properties": {
    "iso:country":"ES",
    "sg:address":"Avda Aragon, 18",
    "sg:city":"Binefar",
    "sg:orig_category":"Venta, Instalaci\u00d3n De Cocinas",
    "sg:phone":"+34 974 42 91 16",
    "sg:postcode":"22500",
    "sg:province":"Huesca",
    "wof:name":"Paul Tena Maria Carmen",
    "wof:placetype":"venue"
},
  "geometry": {"coordinates":[0.2938149869,41.8505554199],"type":"Point"}
}