{
  "type": "Feature",
  "properties": {
    "iso:country":"ES",
    "sg:address":"Carrer de Riera De Premia, 12",
    "sg:city":"Premia Mar",
    "sg:orig_category":"Persianas Interiores, Exteriores",
    "sg:phone":"+34 937 51 03 63",
    "sg:postcode":"08330",
    "sg:province":"Barcelona",
    "wof:name":"Climent Gutierrez Marina",
    "wof:placetype":"venue"
},
  "geometry": {"coordinates":[2.3547170162,41.4886665344],"type":"Point"}
}