{
  "type": "Feature",
  "properties": {
    "addr:full":"Av Pau Casals, 38 Lloret Mar Girona 17310",
    "addr:housenumber":"38",
    "addr:postcode":"17310",
    "addr:street":"Av Pau Casals",
    "iso:country":"ES",
    "sg:address":"Av Pau Casals, 38",
    "sg:city":"Lloret Mar",
    "sg:orig_category":"Importaci\u00d3n",
    "sg:phone":"+34 972 36 85 83",
    "sg:postcode":"17310",
    "sg:province":"Girona",
    "wof:name":"A Granel & Complements S.l",
    "wof:placetype":"venue"
},
  "geometry": {"coordinates":[2.8551638126,41.7026748657],"type":"Point"}
}