{
  "type": "Feature",
  "properties": {
    "addr:full":"Calle de Millan Astray, 7 Ceuta Ceuta 51001",
    "addr:housenumber":"7",
    "addr:postcode":"51001",
    "addr:street":"Calle De Millan Astray",
    "iso:country":"ES",
    "sg:address":"Calle de Millan Astray, 7",
    "sg:city":"Ceuta",
    "sg:orig_category":"Ense\u00d1anza Variada",
    "sg:phone":"+34 956 51 53 48",
    "sg:postcode":"51001",
    "sg:province":"Ceuta",
    "wof:name":"Cerda Peral Mariano",
    "wof:placetype":"venue"
},
  "geometry": {"coordinates":[-5.3088822365,35.8880805969],"type":"Point"}
}