{
  "type": "Feature",
  "properties": {
    "addr:full":"Avda Jose Mesa Y Lopez, 43 Palmas De Gran Canaria Las Palmas 35010",
    "addr:postcode":"35010",
    "addr:street":"Avda Jose Mesa Y Lopez 43",
    "iso:country":"ES",
    "sg:address":"Avda Jose Mesa Y Lopez, 43",
    "sg:city":"Palmas De Gran Canaria",
    "sg:orig_category":"Molduras, Junquillos, Listones Y Molduras Perforadas",
    "sg:phone":"+34 928 27 86 04",
    "sg:postcode":"35010",
    "sg:province":"Las Palmas",
    "wof:name":"Tasca Ca Mano",
    "wof:placetype":"venue"
},
  "geometry": {"coordinates":[-15.4369087219,28.1327571869],"type":"Point"}
}