{
  "type": "Feature",
  "properties": {
    "addr:full":"Avda Juan Carlos I, 2 Totana Murcia 30850",
    "addr:housenumber":"2",
    "addr:postcode":"30850",
    "addr:street":"Avda Juan Carlos I",
    "iso:country":"ES",
    "sg:address":"Avda Juan Carlos I, 2",
    "sg:city":"Totana",
    "sg:orig_category":"Producci\u00d3n De Abonos Y De Fertilizantes",
    "sg:phone":"+34 968 42 44 22",
    "sg:postcode":"30850",
    "sg:province":"Murcia",
    "wof:name":"Antonio Fuentes Mendez S.a.",
    "wof:placetype":"venue"
},
  "geometry": {"coordinates":[-1.4905984402,37.7748680115],"type":"Point"}
}