{
  "type": "Feature",
  "properties": {
    "iso:country":"ES",
    "sg:address":"Avgd Marques Del Palmer, 26",
    "sg:city":"Colonia S. Jordi",
    "sg:orig_category":"Financiaci\u00d3n Y Cr\u00c9ditos",
    "sg:phone":"+34 971 65 65 86",
    "sg:postcode":"07638",
    "sg:province":"Islas Baleares",
    "wof:name":"Martinez Fernandez Joaquin",
    "wof:placetype":"venue"
},
  "geometry": {"coordinates":[2.9928250313,39.3186759949],"type":"Point"}
}