{
  "type": "Feature",
  "properties": {
    "iso:country":"ES",
    "sg:address":"Ctra Puesta En Riego (villarrubia), S/n",
    "sg:city":"Villarrubia",
    "sg:orig_category":"Electricidad: Instaladores",
    "sg:phone":"+34 957 45 82 02",
    "sg:postcode":"14710",
    "sg:province":"C\u00f3rdoba",
    "wof:name":"Luque Soto Rafael",
    "wof:placetype":"venue"
},
  "geometry": {"coordinates":[-4.9146289825,37.8490753174],"type":"Point"}
}