{
  "type": "Feature",
  "properties": {
    "iso:country":"ES",
    "sg:address":"Calle de Benisa, 33",
    "sg:city":"Denia",
    "sg:orig_category":"Molduras, Junquillos, Listones Y Molduras Perforadas",
    "sg:phone":"+34 965 78 11 51",
    "sg:postcode":"03700",
    "sg:province":"Alicante",
    "wof:name":"Garcia Garcia Pedro",
    "wof:placetype":"venue"
},
  "geometry": {"coordinates":[0.0916972011,38.7272186279],"type":"Point"}
}