{
  "type": "Feature",
  "properties": {
    "addr:full":"Calle de Severo Ochoa, 1 Jaraiz Vera C\u00e1ceres 10400",
    "addr:housenumber":"1",
    "addr:postcode":"10400",
    "addr:street":"Calle De Severo Ochoa",
    "iso:country":"ES",
    "sg:address":"Calle de Severo Ochoa, 1",
    "sg:city":"Jaraiz Vera",
    "sg:orig_category":"Mec\u00c1nico Del Autom\u00d3vil",
    "sg:phone":"+34 927 46 02 26",
    "sg:postcode":"10400",
    "sg:province":"C\u00e1ceres",
    "wof:name":"Amador Cilleros Carlos",
    "wof:placetype":"venue"
},
  "geometry": {"coordinates":[-5.7559962273,40.0566596985],"type":"Point"}
}