{
  "type": "Feature",
  "properties": {
    "iso:country":"ES",
    "sg:address":"Calle de Puerta Del Mar, 8",
    "sg:city":"Nerja",
    "sg:orig_category":"Caf\u00c9s, Bares, Cervecer\u00cdas",
    "sg:phone":"+34 952 52 80 24",
    "sg:postcode":"29780",
    "sg:province":"M\u00e1laga",
    "wof:name":"Cafeteria Calabella S.l.",
    "wof:placetype":"venue"
},
  "geometry": {"coordinates":[-3.8756821156,36.7455215454],"type":"Point"}
}