{
  "type": "Feature",
  "properties": {
    "addr:full":"Avda Rompido El, 23 Cartaya Huelva 21450",
    "addr:postcode":"21450",
    "addr:street":"Avda Rompido El",
    "iso:country":"ES",
    "sg:address":"Avda Rompido El, 23",
    "sg:city":"Cartaya",
    "sg:orig_category":"Inmobiliaria (agencias)",
    "sg:phone":"+34 959 39 05 47",
    "sg:postcode":"21450",
    "sg:province":"Huelva",
    "wof:name":"Inmobiliaria Dinocasa Sur S.l.",
    "wof:placetype":"venue"
},
  "geometry": {"coordinates":[-7.1489610672,37.2828865051],"type":"Point"}
}