{
  "type": "Feature",
  "properties": {
    "addr:full":"Calle de Leon Y Castillo, 3 Palmas De Gran Canaria Las Palmas 35003",
    "addr:housenumber":"3",
    "addr:postcode":"35003",
    "addr:street":"Calle De Leon Y Castillo",
    "iso:country":"ES",
    "sg:address":"Calle de Leon Y Castillo, 3",
    "sg:city":"Palmas De Gran Canaria",
    "sg:orig_category":"Radiocomunicaciones, Telefon\u00cda M\u00d3vil, Radiomensajer\u00cda: Servicios, Comercializaci\u00d3n",
    "sg:phone":"+34 928 38 15 76",
    "sg:postcode":"35003",
    "sg:province":"Las Palmas",
    "sg:website":"www.telyco.es",
    "wof:name":"Teleinformatica Y Comunicaciones S.a.",
    "wof:placetype":"venue"
},
  "geometry": {"coordinates":[-15.4179334641,28.1093387604],"type":"Point"}
}