{
  "type": "Feature",
  "properties": {
    "iso:country":"ES",
    "sg:address":"Avda Carlos Iii, 401",
    "sg:city":"Campillo Del Moro",
    "sg:orig_category":"Embajadas, Consulados Y Otras Representaciones Diplom\u00c1ticas",
    "sg:phone":"+34 950 34 05 55",
    "sg:postcode":"04720",
    "sg:province":"Almer\u00eda",
    "wof:name":"Prinzen Consul Honorario Alexander",
    "wof:placetype":"venue"
},
  "geometry": {"coordinates":[-2.5741510391,36.8138160706],"type":"Point"}
}