{
  "type": "Feature",
  "properties": {
    "addr:full":"Avda Navarra, 9 Funes Navarra 31360",
    "addr:housenumber":"9",
    "addr:postcode":"31360",
    "addr:street":"Avda Navarra",
    "iso:country":"ES",
    "sg:address":"Avda Navarra, 9",
    "sg:city":"Funes",
    "sg:orig_category":"Lecher\u00cdas",
    "sg:phone":"+34 948 75 44 92",
    "sg:postcode":"31360",
    "sg:province":"Navarra",
    "wof:name":"S.a.t. No 677 Na Z.c.",
    "wof:placetype":"venue"
},
  "geometry": {"coordinates":[-1.7998540401,42.3152999878],"type":"Point"}
}