{
  "type": "Feature",
  "properties": {
    "addr:full":"Calle de San Teodomiro, 32 Carmona Sevilla 41410",
    "addr:housenumber":"32",
    "addr:postcode":"41410",
    "addr:street":"Calle De San Teodomiro",
    "iso:country":"ES",
    "sg:address":"Calle de San Teodomiro, 32",
    "sg:city":"Carmona",
    "sg:orig_category":"Porcelanas, Azulejos (fabricaci\u00d3n, Al Por Mayor)",
    "sg:phone":"+34 954 14 40 49",
    "sg:postcode":"41410",
    "sg:province":"Sevilla",
    "wof:name":"Vergara Cifuentes Jose Manuel",
    "wof:placetype":"venue"
},
  "geometry": {"coordinates":[-5.6406898499,37.4760437012],"type":"Point"}
}