{
  "type": "Feature",
  "properties": {
    "addr:full":"Calle de Villar, 5 Huetor-tajar Granada 18360",
    "addr:housenumber":"5",
    "addr:postcode":"18360",
    "addr:street":"Calle De Villar",
    "iso:country":"ES",
    "sg:address":"Calle de Villar, 5",
    "sg:city":"Huetor-tajar",
    "sg:orig_category":"Comercio, Reparaci\u00d3n De Motocicletas, Bicicletas Y Piezas Sueltas",
    "sg:phone":"+34 958 33 21 32",
    "sg:postcode":"18360",
    "sg:province":"Granada",
    "wof:name":"Trujillo Mercado Rafael",
    "wof:placetype":"venue"
},
  "geometry": {"coordinates":[-4.0470151901,37.1957092285],"type":"Point"}
}