{
  "type": "Feature",
  "properties": {
    "addr:full":"Carrer de Espirall, 7 Sabadell Barcelona 08201",
    "addr:housenumber":"7",
    "addr:postcode":"08201",
    "addr:street":"Carrer De Espirall",
    "iso:country":"ES",
    "sg:address":"Carrer de Espirall, 7",
    "sg:city":"Sabadell",
    "sg:orig_category":"Compraventa De Antig\u00dcedades",
    "sg:phone":"+34 937 25 88 62",
    "sg:postcode":"08201",
    "sg:province":"Barcelona",
    "wof:name":"Vendrell Torrella Javier",
    "wof:placetype":"venue"
},
  "geometry": {"coordinates":[2.1073060036,41.5433654785],"type":"Point"}
}