{
  "type": "Feature",
  "properties": {
    "iso:country":"ES",
    "sg:address":"Avda Gaviotas (las), S/n",
    "sg:city":"Urbanizacion Roquetas De Mar",
    "sg:orig_category":"Panader\u00cdas, Panader\u00cdas",
    "sg:phone":"+34 950 33 47 44",
    "sg:postcode":"04740",
    "sg:province":"Almer\u00eda",
    "wof:name":"Asensio Navarro Juan",
    "wof:placetype":"venue"
},
  "geometry": {"coordinates":[-2.6149346828,36.7642745972],"type":"Point"}
}