{
  "type": "Feature",
  "properties": {
    "iso:country":"ES",
    "sg:address":"Avda Juan Carlos I, 11",
    "sg:city":"Aguilas",
    "sg:orig_category":"Art\u00cdculos Funerarios (al Por Menor)",
    "sg:phone":"+34 968 41 35 04",
    "sg:postcode":"30880",
    "sg:province":"Murcia",
    "wof:name":"Jerez Mellado S.l.",
    "wof:placetype":"venue"
},
  "geometry": {"coordinates":[-1.5846600533,37.4043045044],"type":"Point"}
}