{
  "type": "Feature",
  "properties": {
    "iso:country":"ES",
    "sg:address":"Calle de Palencia, 37",
    "sg:city":"Granada",
    "sg:orig_category":"Plomeros",
    "sg:phone":"+34 958 81 47 38",
    "sg:postcode":"18008",
    "sg:province":"Granada",
    "wof:name":"Garcia Checa Antonio",
    "wof:placetype":"venue"
},
  "geometry": {"coordinates":[-3.5948150158,37.159778595],"type":"Point"}
}