{
  "type": "Feature",
  "properties": {
    "iso:country":"ES",
    "sg:address":"Carrer de General Prim, 3",
    "sg:city":"Cornella Llobregat",
    "sg:orig_category":"Inmobiliaria (agencias)",
    "sg:phone":"+34 934 75 16 66",
    "sg:postcode":"08940",
    "sg:province":"Barcelona",
    "wof:name":"Vigaus 2003 S.l.",
    "wof:placetype":"venue"
},
  "geometry": {"coordinates":[2.0699698925,41.3564910889],"type":"Point"}
}