{
  "type": "Feature",
  "properties": {
    "iso:country":"ES",
    "sg:address":"Nueva, S/n",
    "sg:city":"Apies",
    "sg:orig_category":"Empresarios",
    "sg:phone":"+34 974 27 10 54",
    "sg:postcode":"22195",
    "sg:province":"Huesca",
    "wof:name":"Claver Perez Ernesto",
    "wof:placetype":"venue"
},
  "geometry": {"coordinates":[-0.4028489888,42.2254486084],"type":"Point"}
}