{
  "type": "Feature",
  "properties": {
    "iso:country":"ES",
    "sg:address":"Calle de Jose Martinez Ruiz-azorin, 79",
    "sg:city":"Merida",
    "sg:orig_category":"Reposter\u00cdas",
    "sg:phone":"+34 924 31 80 15",
    "sg:postcode":"06800",
    "sg:province":"Badajoz",
    "wof:name":"Indupan S.l.",
    "wof:placetype":"venue"
},
  "geometry": {"coordinates":[-6.3382787704,38.9247589111],"type":"Point"}
}