{
  "type": "Feature",
  "properties": {
    "addr:full":"Avda San Javier(aparecida), 40 La Palma Murcia 30593",
    "addr:housenumber":"40",
    "addr:postcode":"30593",
    "addr:street":"Avda San Javier Aparecida",
    "iso:country":"ES",
    "sg:address":"Avda San Javier(aparecida), 40",
    "sg:city":"La Palma",
    "sg:orig_category":"Molduras, Junquillos, Listones Y Molduras Perforadas",
    "sg:phone":"+34 968 55 40 00",
    "sg:postcode":"30593",
    "sg:province":"Murcia",
    "wof:name":"Venta El Abasto S.l.",
    "wof:placetype":"venue"
},
  "geometry": {"coordinates":[-0.9635639787,37.689781189],"type":"Point"}
}