{
  "type": "Feature",
  "properties": {
    "addr:full":"Calle de Abubilla, 10 Veredillas Santa Cruz De Tenerife 38108",
    "addr:housenumber":"10",
    "addr:postcode":"38108",
    "addr:street":"Calle De Abubilla",
    "iso:country":"ES",
    "sg:address":"Calle de Abubilla, 10",
    "sg:city":"Veredillas",
    "sg:orig_category":"Chapister\u00cda",
    "sg:phone":"+34 922 62 14 75",
    "sg:postcode":"38108",
    "sg:province":"Santa Cruz De Tenerife",
    "wof:name":"Parte Camino S.l.",
    "wof:placetype":"venue"
},
  "geometry": {"coordinates":[-16.2548561096,28.4698104858],"type":"Point"}
}