{
  "type": "Feature",
  "properties": {
    "iso:country":"ES",
    "sg:address":"Raset, 136",
    "sg:city":"Vilablareix",
    "sg:orig_category":"Colchones (fabricaci\u00d3n, Al Por Mayor, Al Por Menor)",
    "sg:phone":"+34 972 24 10 23",
    "sg:postcode":"17180",
    "sg:province":"Girona",
    "wof:name":"Plastics I Tapisseries Ter S.l.",
    "wof:placetype":"venue"
},
  "geometry": {"coordinates":[2.799683094,41.9519538879],"type":"Point"}
}