{
  "type": "Feature",
  "properties": {
    "addr:full":"Calle de Geranio, 4 Corralejo Las Palmas 35660",
    "addr:housenumber":"4",
    "addr:postcode":"35660",
    "addr:street":"Calle De Geranio",
    "iso:country":"ES",
    "sg:address":"Calle de Geranio, 4",
    "sg:city":"Corralejo",
    "sg:orig_category":"Bazares, Art\u00cdculos De Limpieza Y De Cocina (al Por Menor)",
    "sg:phone":"+34 928 86 73 16",
    "sg:postcode":"35660",
    "sg:province":"Las Palmas",
    "wof:name":"Bali Business S.l.u.",
    "wof:placetype":"venue"
},
  "geometry": {"coordinates":[-13.8656816483,28.7318725586],"type":"Point"}
}