{
  "type": "Feature",
  "properties": {
    "iso:country":"ES",
    "sg:address":"Carrer de Barcelona, 8",
    "sg:city":"Sant Vicen\u00c7 Dels Horts",
    "sg:orig_category":"Alimentaci\u00d3n General (al Por Menor)",
    "sg:phone":"+34 936 56 02 04",
    "sg:postcode":"08620",
    "sg:province":"Barcelona",
    "wof:name":"Castells Serra Agustin",
    "wof:placetype":"venue"
},
  "geometry": {"coordinates":[2.0113430023,41.3934707642],"type":"Point"}
}