{
  "type": "Feature",
  "properties": {
    "addr:full":"Pl Vila (de La), 7 Torredembarra Tarragona 43830",
    "addr:housenumber":"7",
    "addr:postcode":"43830",
    "addr:street":"Pl Vila De La",
    "iso:country":"ES",
    "sg:address":"Pl Vila (de La), 7",
    "sg:city":"Torredembarra",
    "sg:orig_category":"Art\u00cdculos De Regalo (al Por Menor)",
    "sg:phone":"+34 977 64 57 53",
    "sg:postcode":"43830",
    "sg:province":"Tarragona",
    "wof:name":"Francino Marcos Carlos",
    "wof:placetype":"venue"
},
  "geometry": {"coordinates":[1.3967690468,41.1445121765],"type":"Point"}
}