{
  "type": "Feature",
  "properties": {
    "iso:country":"ES",
    "sg:address":"Avda Almogavares (de), 40",
    "sg:city":"Cordoba",
    "sg:orig_category":"Alimentaci\u00d3n General (al Por Menor)",
    "sg:phone":"+34 957 27 55 93",
    "sg:postcode":"14006",
    "sg:province":"C\u00f3rdoba",
    "wof:name":"Alpocor S.l.",
    "wof:placetype":"venue"
},
  "geometry": {"coordinates":[-4.7765636444,37.8969116211],"type":"Point"}
}