{
  "type": "Feature",
  "properties": {
    "iso:country":"ES",
    "sg:address":"Ctra Guardia (la), 7",
    "sg:city":"Jaen",
    "sg:orig_category":"Negocio De Materiales De Construcci\u00d3n",
    "sg:phone":"+34 953 23 90 89",
    "sg:postcode":"23001",
    "sg:province":"Ja\u00e9n",
    "wof:name":"Beltran Montoro S.a.",
    "wof:placetype":"venue"
},
  "geometry": {"coordinates":[-3.7906870842,37.7650947571],"type":"Point"}
}