{
  "type": "Feature",
  "properties": {
    "iso:country":"ES",
    "sg:address":"Avda Ramon Y Cajal, 49",
    "sg:city":"Catarroja",
    "sg:orig_category":"\u00d3ptica: Instrumentos (fabricaci\u00d3n)",
    "sg:phone":"+34 961 26 90 25",
    "sg:postcode":"46470",
    "sg:province":"Valencia",
    "wof:name":"Optica La Pobla S.l.",
    "wof:placetype":"venue"
},
  "geometry": {"coordinates":[-0.4024530053,39.4058609009],"type":"Point"}
}