{
  "type": "Feature",
  "properties": {
    "iso:country":"ES",
    "sg:address":"Carrer de Sant Elies, 37",
    "sg:city":"Barcelona",
    "sg:orig_category":"Pescader\u00cdas (al Por Menor)",
    "sg:phone":"+34 932 09 09 78",
    "sg:postcode":"08006",
    "sg:province":"Barcelona",
    "wof:name":"Vicent Jover Isabel",
    "wof:placetype":"venue"
},
  "geometry": {"coordinates":[2.1438550949,41.400642395],"type":"Point"}
}