{
  "type": "Feature",
  "properties": {
    "iso:country":"ES",
    "sg:address":"Calle de Velazquez (de), 2",
    "sg:city":"Coslada",
    "sg:orig_category":"Peluqueros: De Se\u00d1oras",
    "sg:phone":"+34 916 72 87 27",
    "sg:postcode":"28820",
    "sg:province":"Madrid",
    "wof:name":"Calero Gomez Consuelo",
    "wof:placetype":"venue"
},
  "geometry": {"coordinates":[-3.5649909973,40.4237976074],"type":"Point"}
}