{
  "type": "Feature",
  "properties": {
    "addr:full":"Calle de Aben Humeya, 15 Granada Granada 18005",
    "addr:housenumber":"15",
    "addr:postcode":"18005",
    "addr:street":"Calle De Aben Humeya",
    "iso:country":"ES",
    "sg:address":"Calle de Aben Humeya, 15",
    "sg:city":"Granada",
    "sg:orig_category":"Abogados",
    "sg:phone":"+34 958 52 06 75",
    "sg:postcode":"18005",
    "sg:province":"Granada",
    "wof:name":"Huertas Morales Jesus",
    "wof:placetype":"venue"
},
  "geometry": {"coordinates":[-3.6003344059,37.1692581177],"type":"Point"}
}