{
  "type": "Feature",
  "properties": {
    "iso:country":"ES",
    "sg:address":"Carrer de Malats, 32",
    "sg:city":"Barcelona",
    "sg:orig_category":"Filatelia",
    "sg:phone":"+34 933 46 32 15",
    "sg:postcode":"08030",
    "sg:province":"Barcelona",
    "wof:name":"Roig Bernus Ramon",
    "wof:placetype":"venue"
},
  "geometry": {"coordinates":[2.1893479824,41.436214447],"type":"Point"}
}