{
  "type": "Feature",
  "properties": {
    "addr:full":"Calle de Esteban Saez Alvarado, 9 Burgos Burgos 09007",
    "addr:housenumber":"9",
    "addr:postcode":"09007",
    "addr:street":"Calle De Esteban Saez Alvarado",
    "iso:country":"ES",
    "sg:address":"Calle de Esteban Saez Alvarado, 9",
    "sg:city":"Burgos",
    "sg:orig_category":"Peluquer\u00cdas, Peluquer\u00cda Mixta",
    "sg:phone":"+34 947 48 44 88",
    "sg:postcode":"09007",
    "sg:province":"Burgos",
    "wof:name":"Alonso Lopez Lourdes",
    "wof:placetype":"venue"
},
  "geometry": {"coordinates":[-3.6653647423,42.3584403992],"type":"Point"}
}