{
  "type": "Feature",
  "properties": {
    "addr:full":"Calle de San Juan Kalea, 46 Alegia Guip\u00f9zcoa 20260",
    "addr:housenumber":"46",
    "addr:postcode":"20260",
    "addr:street":"Calle De San Juan Kalea;Guipu\u0300Zcoa",
    "iso:country":"ES",
    "sg:address":"Calle de San Juan Kalea, 46",
    "sg:city":"Alegia",
    "sg:classifiers":[
        {
            "category":"Taxi",
            "type":"Transportation"
        }
    ],
    "sg:phone":"+34 943 65 33 36",
    "sg:postcode":"20260",
    "sg:province":"Guip\u00f9zcoa",
    "wof:name":"Ayuntamiento De Alegia",
    "wof:placetype":"venue"
},
  "geometry": {"coordinates":[-2.0985751152,43.094669342],"type":"Point"}
}