{
  "type": "Feature",
  "properties": {
    "iso:country":"ES",
    "sg:address":"Calle de Kasune, 48",
    "sg:city":"Algorta",
    "sg:orig_category":"Cristaler\u00cdas",
    "sg:phone":"+34 944 30 65 83",
    "sg:postcode":"48991",
    "sg:province":"Vizcaya",
    "wof:name":"J.m. Mu\u00f1iz Fernandez Y Otros C.b.",
    "wof:placetype":"venue"
},
  "geometry": {"coordinates":[-3.0082490444,43.3543815613],"type":"Point"}
}