{
  "type": "Feature",
  "properties": {
    "addr:full":"Plaz Flandes (de), 15 Mostoles Madrid 28936",
    "addr:postcode":"28936",
    "addr:street":"Mostoles",
    "iso:country":"ES",
    "sg:address":"Plaz Flandes (de), 15",
    "sg:city":"Mostoles",
    "sg:orig_category":"Empresas De Pintura Y Revestimientos",
    "sg:phone":"+34 916 46 27 83",
    "sg:postcode":"28936",
    "sg:province":"Madrid",
    "wof:name":"Fraile Bodas Juan Ramon",
    "wof:placetype":"venue"
},
  "geometry": {"coordinates":[-3.8514618874,40.3187522888],"type":"Point"}
}