{
  "type": "Feature",
  "properties": {
    "addr:full":"Pase General Davila, 35 Santander Cantabria 39006",
    "addr:housenumber":"35",
    "addr:postcode":"39006",
    "addr:street":"Davila",
    "iso:country":"ES",
    "sg:address":"Pase General Davila, 35",
    "sg:city":"Santander",
    "sg:orig_category":"Hospitales",
    "sg:phone":"+34 942 21 56 22",
    "sg:postcode":"39006",
    "sg:province":"Cantabria",
    "wof:name":"Aramark S.l.",
    "wof:placetype":"venue"
},
  "geometry": {"coordinates":[-3.7988436222,43.4683227539],"type":"Point"}
}