{
  "type": "Feature",
  "properties": {
    "iso:country":"ES",
    "sg:address":"Plaz Alemania, 3",
    "sg:city":"Zamora",
    "sg:orig_category":"Sociedades, Compa\u00d1\u00cdas Aseguradoras",
    "sg:phone":"+34 980 53 41 96",
    "sg:postcode":"49014",
    "sg:province":"Zamora",
    "wof:name":"Santa Lucia S.a.",
    "wof:placetype":"venue"
},
  "geometry": {"coordinates":[-5.7431340218,41.5078735352],"type":"Point"}
}