{
  "type": "Feature",
  "properties": {
    "iso:country":"ES",
    "sg:address":"Calle de Caballeros, 23",
    "sg:city":"Soria",
    "sg:orig_category":"Funcionario",
    "sg:phone":"+34 975 22 15 86",
    "sg:postcode":"42003",
    "sg:province":"Soria",
    "wof:name":"Colegio Oficial De Arquitectos",
    "wof:placetype":"venue"
},
  "geometry": {"coordinates":[-2.4661195278,41.7629623413],"type":"Point"}
}