{
  "type": "Feature",
  "properties": {
    "iso:country":"ES",
    "sg:address":"Avda Ejercito (del), 38",
    "sg:city":"Sabi\u00f1anigo",
    "sg:orig_category":"Molduras, Junquillos, Listones Y Molduras Perforadas",
    "sg:phone":"+34 974 48 06 11",
    "sg:postcode":"22600",
    "sg:province":"Huesca",
    "wof:name":"Valverde Rute Eloisa",
    "wof:placetype":"venue"
},
  "geometry": {"coordinates":[-0.3576309979,42.5070495605],"type":"Point"}
}