{
  "type": "Feature",
  "properties": {
    "addr:full":"Calle de Floridablanca, 20 Dolores Murcia 30310",
    "addr:housenumber":"20",
    "addr:postcode":"30310",
    "addr:street":"Calle De Floridablanca",
    "iso:country":"ES",
    "sg:address":"Calle de Floridablanca, 20",
    "sg:city":"Dolores",
    "sg:orig_category":"Chapister\u00cda",
    "sg:phone":"+34 968 31 49 62",
    "sg:postcode":"30310",
    "sg:province":"Murcia",
    "wof:name":"Fernandez Saura Juana",
    "wof:placetype":"venue"
},
  "geometry": {"coordinates":[-1.0027681589,37.6360321045],"type":"Point"}
}