{
  "type": "Feature",
  "properties": {
    "addr:full":"Calle de General Franco, 17 Cristianos Santa Cruz De Tenerife 38650",
    "addr:housenumber":"17",
    "addr:postcode":"38650",
    "addr:street":"Calle De General Franco",
    "iso:country":"ES",
    "sg:address":"Calle de General Franco, 17",
    "sg:city":"Cristianos",
    "sg:orig_category":"Ropa Y Accesorios",
    "sg:phone":"+34 922 79 72 25",
    "sg:postcode":"38650",
    "sg:province":"Santa Cruz De Tenerife",
    "wof:name":"Acosta Ramos Raimundo",
    "wof:placetype":"venue"
},
  "geometry": {"coordinates":[-16.7163887024,28.0523910522],"type":"Point"}
}