{
  "type": "Feature",
  "properties": {
    "addr:full":"Calle de Granados, 3 Malaga M\u00e1laga 29008",
    "addr:housenumber":"3",
    "addr:postcode":"29008",
    "addr:street":"Calle De Granados;Ma\u0301Laga",
    "iso:country":"ES",
    "sg:address":"Calle de Granados, 3",
    "sg:city":"Malaga",
    "sg:orig_category":"Administradores De Bienes Y Delegados De Comunidades De Propietarios",
    "sg:phone":"+34 952 21 48 09",
    "sg:postcode":"29008",
    "sg:province":"M\u00e1laga",
    "wof:name":"Mandly Garcia Maria Luisa",
    "wof:placetype":"venue"
},
  "geometry": {"coordinates":[-4.4198851585,36.7229232788],"type":"Point"}
}