{
  "type": "Feature",
  "properties": {
    "addr:full":"Calle de Uria, 54 Oviedo Asturias 33003",
    "addr:housenumber":"54",
    "addr:postcode":"33003",
    "addr:street":"Calle De Uria",
    "iso:country":"ES",
    "sg:address":"Calle de Uria, 54",
    "sg:city":"Oviedo",
    "sg:orig_category":"Bancos",
    "sg:phone":"+34 985 20 75 60",
    "sg:postcode":"33003",
    "sg:province":"Asturias",
    "wof:name":"Bankinter S.a.",
    "wof:placetype":"venue"
},
  "geometry": {"coordinates":[-5.852077961,43.3647689819],"type":"Point"}
}