{
  "type": "Feature",
  "properties": {
    "iso:country":"ES",
    "sg:address":"Avda Juan Carlos I, 8",
    "sg:city":"Santiago",
    "sg:orig_category":"Productos Qu\u00cdmicos (fabricaci\u00d3n, Al Por Mayor)",
    "sg:phone":"+34 968 46 41 53",
    "sg:postcode":"30800",
    "sg:province":"Murcia",
    "sg:website":"www.solinternet.es",
    "wof:name":"Lizaran S.l.",
    "wof:placetype":"venue"
},
  "geometry": {"coordinates":[-1.1298867464,37.9834747314],"type":"Point"}
}