{
  "type": "Feature",
  "properties": {
    "addr:full":"Rua Bispo Aguirre, 1 Lugo Lugo 27002",
    "addr:housenumber":"1",
    "addr:postcode":"27002",
    "addr:street":"Rua Bispo Aguirre",
    "iso:country":"ES",
    "sg:address":"Rua Bispo Aguirre, 1",
    "sg:city":"Lugo",
    "sg:orig_category":"Abogados",
    "sg:phone":"+34 982 25 40 24",
    "sg:postcode":"27002",
    "sg:province":"Lugo",
    "wof:name":"Garcia Rojo Y Lopez Barrio C.b.",
    "wof:placetype":"venue"
},
  "geometry": {"coordinates":[-7.556415081,43.0082893372],"type":"Point"}
}