{
  "type": "Feature",
  "properties": {
    "iso:country":"ES",
    "sg:address":"Calle de Almeria, 4",
    "sg:city":"Valladolid",
    "sg:orig_category":"Peluquer\u00cdas, Peluquer\u00cda Mixta",
    "sg:phone":"+34 983 20 85 76",
    "sg:postcode":"47012",
    "sg:province":"Valladolid",
    "wof:name":"Martin Garcia Ana Maria",
    "wof:placetype":"venue"
},
  "geometry": {"coordinates":[-4.7151217461,41.6427536011],"type":"Point"}
}