{
  "type": "Feature",
  "properties": {
    "iso:country":"ES",
    "sg:address":"Calle de Alcala, 397",
    "sg:city":"Madrid",
    "sg:orig_category":"Ropa Para Se\u00d1oras (al Por Menor)",
    "sg:phone":"+34 914 07 86 14",
    "sg:postcode":"28027",
    "sg:province":"Madrid",
    "wof:name":"Jimenez Mercado Maria Dolores",
    "wof:placetype":"venue"
},
  "geometry": {"coordinates":[-3.6411290169,40.436504364],"type":"Point"}
}