{
  "type": "Feature",
  "properties": {
    "addr:full":"Rua Junquera, 6 Cee A Coru\u00f1a 15270",
    "addr:housenumber":"6",
    "addr:postcode":"15270",
    "addr:street":"Rua Junquera",
    "iso:country":"ES",
    "sg:address":"Rua Junquera, 6",
    "sg:city":"Cee",
    "sg:orig_category":"Abogados",
    "sg:phone":"+34 981 74 75 57",
    "sg:postcode":"15270",
    "sg:province":"A Coru\u00f1a",
    "wof:name":"Santalo Junquera Jose Ignacio",
    "wof:placetype":"venue"
},
  "geometry": {"coordinates":[-9.1918792725,42.9536552429],"type":"Point"}
}