{
  "type": "Feature",
  "properties": {
    "iso:country":"ES",
    "sg:address":"Calle de Sacramento, 13",
    "sg:city":"Utrera",
    "sg:orig_category":"Sociedades, Compa\u00d1\u00cdas Aseguradoras",
    "sg:phone":"+34 955 86 78 96",
    "sg:postcode":"41710",
    "sg:province":"Sevilla",
    "wof:name":"Coseant S.l.",
    "wof:placetype":"venue"
},
  "geometry": {"coordinates":[-5.7795572281,37.1805114746],"type":"Point"}
}