{
  "type": "Feature",
  "properties": {
    "addr:full":"Avda Constitucion (de La), 3 Herencia Ciudad Real 13640",
    "addr:housenumber":"3",
    "addr:postcode":"13640",
    "addr:street":"Avda Constitucion De La",
    "iso:country":"ES",
    "sg:address":"Avda Constitucion (de La), 3",
    "sg:city":"Herencia",
    "sg:orig_category":"Confiter\u00cda, Galletas Y Pastas, Chocolater\u00cda (al Por Mayor)",
    "sg:phone":"+34 926 57 24 28",
    "sg:postcode":"13640",
    "sg:province":"Ciudad Real",
    "wof:name":"Hermanos Ramirez C.b.",
    "wof:placetype":"venue"
},
  "geometry": {"coordinates":[-3.3541069031,39.3683815002],"type":"Point"}
}