{
  "type": "Feature",
  "properties": {
    "addr:full":"Calle de Puerta De Aguilar, 38 Montilla C\u00f3rdoba 14550",
    "addr:housenumber":"38",
    "addr:postcode":"14550",
    "addr:street":"Calle De Puerta De Aguilar;Co\u0301Rdoba",
    "iso:country":"ES",
    "sg:address":"Calle de Puerta De Aguilar, 38",
    "sg:city":"Montilla",
    "sg:orig_category":"Ropa Para Se\u00d1oras Y Caballeros (al Por Menor)",
    "sg:phone":"+34 957 65 70 50",
    "sg:postcode":"14550",
    "sg:province":"C\u00f3rdoba",
    "wof:name":"Luque Baena Enma Maria",
    "wof:placetype":"venue"
},
  "geometry": {"coordinates":[-4.6409320831,37.5851554871],"type":"Point"}
}