{
  "type": "Feature",
  "properties": {
    "iso:country":"ES",
    "sg:address":"Calle de Mar (la), 45",
    "sg:city":"Colindres",
    "sg:orig_category":"Garajes De Veh\u00cdculos",
    "sg:phone":"+34 942 65 28 28",
    "sg:postcode":"39750",
    "sg:province":"Cantabria",
    "wof:name":"Turismos Riason S.a.",
    "wof:placetype":"venue"
},
  "geometry": {"coordinates":[-3.4612123966,43.3940124512],"type":"Point"}
}