{
  "type": "Feature",
  "properties": {
    "iso:country":"ES",
    "sg:address":"Ptda Empedrat (l'), S/n",
    "sg:city":"Olleria",
    "sg:orig_category":"Fabricaci\u00d3n De Pernos, Tornillos Y Clavos",
    "sg:phone":"+34 962 20 25 48",
    "sg:postcode":"46850",
    "sg:province":"Valencia",
    "wof:name":"Artigrau S.l.",
    "wof:placetype":"venue"
},
  "geometry": {"coordinates":[-0.554148972,38.9132995605],"type":"Point"}
}