{
  "type": "Feature",
  "properties": {
    "iso:country":"ES",
    "sg:address":"Carrer de Berruguete, 38",
    "sg:city":"Barcelona",
    "sg:orig_category":"Agencias Y Agentes Comerciales, Representantes",
    "sg:phone":"+34 934 28 25 77",
    "sg:postcode":"08035",
    "sg:province":"Barcelona",
    "wof:name":"Foncillas Corominas Joaquin",
    "wof:placetype":"venue"
},
  "geometry": {"coordinates":[2.1496601105,41.4330596924],"type":"Point"}
}