{
  "type": "Feature",
  "properties": {
    "iso:country":"ES",
    "sg:address":"Torre, 2",
    "sg:city":"Torre",
    "sg:classifiers":[
        {
            "category":"Banks & Credit Unions",
            "subcategory":"Bureau De Change",
            "type":"Services"
        }
    ],
    "sg:phone":"+34 986 80 12 00",
    "sg:postcode":"36...",
    "sg:province":"Pontevedra",
    "sg:tags":[
        "organismos",
        "control"
    ],
    "sg:website":"www.enmacosa.com",
    "wof:name":"Enmacosa S.a.",
    "wof:placetype":"venue"
},
  "geometry": {"coordinates":[-8.1979351044,42.6168479919],"type":"Point"}
}