{
  "type": "Feature",
  "properties": {
    "addr:full":"Via Augusta, 8 Tarragona Tarragona 43003",
    "addr:housenumber":"8",
    "addr:postcode":"43003",
    "addr:street":"Via Augusta",
    "iso:country":"ES",
    "sg:address":"Via Augusta, 8",
    "sg:city":"Tarragona",
    "sg:orig_category":"Reposter\u00cdas",
    "sg:phone":"+34 977 24 02 58",
    "sg:postcode":"43003",
    "sg:province":"Tarragona",
    "wof:name":"Maldonado Azuaga Monica",
    "wof:placetype":"venue"
},
  "geometry": {"coordinates":[1.259215951,41.1160087585],"type":"Point"}
}