{
  "type": "Feature",
  "properties": {
    "iso:country":"ES",
    "sg:address":"Calle de Siguenza, S/n",
    "sg:city":"Azuqueca Henares",
    "sg:orig_category":"Asesor\u00cda Sobre Comunicaci\u00d3n De Empresas",
    "sg:phone":"+34 949 26 34 74",
    "sg:postcode":"19200",
    "sg:province":"Guadalajara",
    "wof:name":"Amate Montero Carmen",
    "wof:placetype":"venue"
},
  "geometry": {"coordinates":[-3.2668735981,40.5651741028],"type":"Point"}
}