{
  "type": "Feature",
  "properties": {
    "addr:full":"Calle de Finlandia, 2 Lebrija Sevilla 41740",
    "addr:housenumber":"2",
    "addr:postcode":"41740",
    "addr:street":"Calle De Finlandia",
    "iso:country":"ES",
    "sg:address":"Calle de Finlandia, 2",
    "sg:city":"Lebrija",
    "sg:orig_category":"Empresas De Pintura Y Revestimientos",
    "sg:phone":"+34 955 97 50 93",
    "sg:postcode":"41740",
    "sg:province":"Sevilla",
    "wof:name":"Lebripinturas,s.l.u",
    "wof:placetype":"venue"
},
  "geometry": {"coordinates":[-6.0663614273,36.9208374023],"type":"Point"}
}