{
  "type": "Feature",
  "properties": {
    "iso:country":"ES",
    "sg:address":"Calle de Portal De Arriaga, 28",
    "sg:city":"Vitoria-gasteiz",
    "sg:orig_category":"Parques De Atracciones Y Centros De Esparcimiento",
    "sg:phone":"+34 945 27 84 82",
    "sg:postcode":"01013",
    "sg:province":"\u00c1lava",
    "wof:name":"Recreativos Perla Sociedad Civil",
    "wof:placetype":"venue"
},
  "geometry": {"coordinates":[-2.6751968861,42.862651825],"type":"Point"}
}