{
  "type": "Feature",
  "properties": {
    "addr:full":"Avda Mediterraneo, 4 Benidorm Alicante 03500",
    "addr:housenumber":"4",
    "addr:postcode":"03500",
    "addr:street":"Avda Mediterraneo",
    "iso:country":"ES",
    "sg:address":"Avda Mediterraneo, 4",
    "sg:city":"Benidorm",
    "sg:orig_category":"Abogados",
    "sg:phone":"+34 965 86 10 05",
    "sg:postcode":"03500",
    "sg:province":"Alicante",
    "wof:name":"Romain Marciano Thierry",
    "wof:placetype":"venue"
},
  "geometry": {"coordinates":[-0.1253480017,38.5370864868],"type":"Point"}
}