{
  "type": "Feature",
  "properties": {
    "addr:full":"Calle de Derechos, 36 Valencia Valencia 46001",
    "addr:housenumber":"36",
    "addr:postcode":"46001",
    "addr:street":"Calle De Derechos",
    "iso:country":"ES",
    "sg:address":"Calle de Derechos, 36",
    "sg:city":"Valencia",
    "sg:orig_category":"Ropa Para Ni\u00d1os (al Por Menor)",
    "sg:phone":"+34 963 91 79 23",
    "sg:postcode":"46001",
    "sg:province":"Valencia",
    "wof:name":"Morente Godoy Maria",
    "wof:placetype":"venue"
},
  "geometry": {"coordinates":[-0.3770568967,39.4736442566],"type":"Point"}
}