{
  "type": "Feature",
  "properties": {
    "iso:country":"ES",
    "sg:address":"Calle de Rey, 30",
    "sg:city":"Plasencia",
    "sg:orig_category":"Asociaciones Y Clubs Deportivos",
    "sg:phone":"+34 927 42 43 27",
    "sg:postcode":"10600",
    "sg:province":"C\u00e1ceres",
    "wof:name":"Plasencia Sports C.b.",
    "wof:placetype":"venue"
},
  "geometry": {"coordinates":[-6.0888538361,40.0308189392],"type":"Point"}
}