{
  "type": "Feature",
  "properties": {
    "iso:country":"ES",
    "sg:address":"Carrer de Lepant, 398",
    "sg:city":"Barcelona",
    "sg:orig_category":"Molduras, Junquillos, Listones Y Molduras Perforadas",
    "sg:phone":"+34 933 47 49 69",
    "sg:postcode":"08025",
    "sg:province":"Barcelona",
    "wof:name":"Gargallo Tarrazon Eduardo",
    "wof:placetype":"venue"
},
  "geometry": {"coordinates":[2.1697220802,41.409942627],"type":"Point"}
}