{
  "type": "Feature",
  "properties": {
    "addr:full":"Avda Esperanto, S/n Castillo Bajo-conejito M\u00e1laga 29793",
    "addr:housenumber":"s / n",
    "addr:postcode":"29793",
    "addr:street":"Avda Esperanto;Castillo Bajo-Conejito Ma\u0301Laga",
    "iso:country":"ES",
    "sg:address":"Avda Esperanto, S/n",
    "sg:city":"Castillo Bajo-conejito",
    "sg:orig_category":"Decoraci\u00d3n: Instalaci\u00d3n Y Talleres",
    "sg:phone":"+34 952 53 03 75",
    "sg:postcode":"29793",
    "sg:province":"M\u00e1laga",
    "wof:name":"Decoracion El Faro S.l.",
    "wof:placetype":"venue"
},
  "geometry": {"coordinates":[-3.9633140564,36.7310066223],"type":"Point"}
}