{
  "type": "Feature",
  "properties": {
    "addr:full":"Calle de Silvestre Ochoa, 9 Castro Urdiales Cantabria 39700",
    "addr:housenumber":"9",
    "addr:postcode":"39700",
    "addr:street":"Calle De Silvestre Ochoa",
    "iso:country":"ES",
    "sg:address":"Calle de Silvestre Ochoa, 9",
    "sg:city":"Castro Urdiales",
    "sg:orig_category":"Perreras, Pensiones Para Perros, Gatos Y Otros Animales",
    "sg:phone":"+34 942 87 13 54",
    "sg:postcode":"39700",
    "sg:province":"Cantabria",
    "wof:name":"Gorostiza Bilbao Miren Intzane",
    "wof:placetype":"venue"
},
  "geometry": {"coordinates":[-3.2241740227,43.384098053],"type":"Point"}
}