{
  "type": "Feature",
  "properties": {
    "addr:full":"Avgd Avinguda Del Parc, 14 Alzira Valencia 46600",
    "addr:housenumber":"14",
    "addr:postcode":"46600",
    "addr:street":"Avinguda Del Parc",
    "iso:country":"ES",
    "sg:address":"Avgd Avinguda Del Parc, 14",
    "sg:city":"Alzira",
    "sg:orig_category":"Reposter\u00cdas",
    "sg:phone":"+34 962 41 70 01",
    "sg:postcode":"46600",
    "sg:province":"Valencia",
    "wof:name":"Horno Rosario Lopez S.l.",
    "wof:placetype":"venue"
},
  "geometry": {"coordinates":[-0.4378489852,39.1517295837],"type":"Point"}
}