{
  "type": "Feature",
  "properties": {
    "addr:full":"Calle de Victor Hugo, 60 Palmas De Gran Canaria Las Palmas 35006",
    "addr:postcode":"35006",
    "addr:street":"Calle De Victor",
    "iso:country":"ES",
    "sg:address":"Calle de Victor Hugo, 60",
    "sg:city":"Palmas De Gran Canaria",
    "sg:orig_category":"Organismos De Turismo",
    "sg:phone":"+34 928 29 37 38",
    "sg:postcode":"35006",
    "sg:province":"Las Palmas",
    "sg:website":"www.saturno-canarias.org",
    "wof:name":"Promotur Turismo Canarias, S.a.",
    "wof:placetype":"venue"
},
  "geometry": {"coordinates":[-15.4343042374,28.1317977905],"type":"Point"}
}