{
  "type": "Feature",
  "properties": {
    "addr:full":"Avda Emigrantes (los), 26 Guadahortuna Granada 18560",
    "addr:housenumber":"26",
    "addr:postcode":"18560",
    "addr:street":"Avda Emigrantes Los",
    "iso:country":"ES",
    "sg:address":"Avda Emigrantes (los), 26",
    "sg:city":"Guadahortuna",
    "sg:orig_category":"Delegados, Agentes De Tr\u00c1nsito, Auxiliares De Transporte Internacional",
    "sg:phone":"+34 958 38 30 34",
    "sg:postcode":"18560",
    "sg:province":"Granada",
    "wof:name":"Quijada Martinez Jeronimo",
    "wof:placetype":"venue"
},
  "geometry": {"coordinates":[-3.396212101,37.5548324585],"type":"Point"}
}