{
  "type": "Feature",
  "properties": {
    "addr:full":"Calle de Teodoro Iriarte Reinoso, 5 Zaragoza Zaragoza 50010",
    "addr:housenumber":"5",
    "addr:postcode":"50010",
    "addr:street":"Calle De Teodoro Iriarte Reinoso",
    "iso:country":"ES",
    "sg:address":"Calle de Teodoro Iriarte Reinoso, 5",
    "sg:city":"Zaragoza",
    "sg:orig_category":"Peluqueros: De Se\u00d1oras",
    "sg:phone":"+34 976 34 94 50",
    "sg:postcode":"50010",
    "sg:province":"Zaragoza",
    "wof:name":"Woman's S.cv.",
    "wof:placetype":"venue"
},
  "geometry": {"coordinates":[-0.9029110074,41.6555786133],"type":"Point"}
}