{
  "type": "Feature",
  "properties": {
    "addr:full":"Trevias, S/n Trevias Asturias 33780",
    "addr:postcode":"33780",
    "addr:street":"Trevias S / N",
    "iso:country":"ES",
    "sg:address":"Trevias, S/n",
    "sg:city":"Trevias",
    "sg:orig_category":"Marmolistas Funerarios",
    "sg:phone":"+34 985 64 74 42",
    "sg:postcode":"33780",
    "sg:province":"Asturias",
    "wof:name":"Rico Gomez Gil",
    "wof:placetype":"venue"
},
  "geometry": {"coordinates":[-6.4858551025,43.4557800293],"type":"Point"}
}