{
  "type": "Feature",
  "properties": {
    "iso:country":"ES",
    "sg:address":"Calle de Miguel Agrait, 8",
    "sg:city":"Benimamet-beniferri",
    "sg:orig_category":"Reposter\u00cdas",
    "sg:phone":"+34 963 40 07 70",
    "sg:postcode":"46035",
    "sg:province":"Valencia",
    "wof:name":"Ferrandis Burguete Francisco",
    "wof:placetype":"venue"
},
  "geometry": {"coordinates":[-0.4180270135,39.4981155396],"type":"Point"}
}