{
  "type": "Feature",
  "properties": {
    "addr:full":"Calle de Eras (de Las), 2 Avila \u00c1vila 05002",
    "addr:housenumber":"2",
    "addr:postcode":"05002",
    "addr:street":"Calle De Eras De Las;A\u0301Vila",
    "iso:country":"ES",
    "sg:address":"Calle de Eras (de Las), 2",
    "sg:city":"Avila",
    "sg:orig_category":"M\u00c9dicos: Estomatolog\u00cda",
    "sg:phone":"+34 920 22 31 93",
    "sg:postcode":"05002",
    "sg:province":"\u00c1vila",
    "wof:name":"Rodriguez Garcia Cristina",
    "wof:placetype":"venue"
},
  "geometry": {"coordinates":[-4.6995768547,40.6503982544],"type":"Point"}
}