{
  "type": "Feature",
  "properties": {
    "addr:full":"Plaz Alcalde J. R. Aguirreche, 1 Irun Guip\u00f9zcoa 20302",
    "addr:housenumber":"1",
    "addr:postcode":"20302",
    "addr:street":"Plaz Alcalde J. R. Aguirreche;Guipu\u0300Zcoa",
    "iso:country":"ES",
    "sg:address":"Plaz Alcalde J. R. Aguirreche, 1",
    "sg:city":"Irun",
    "sg:orig_category":"Ense\u00d1anza: Idiomas",
    "sg:phone":"+34 943 62 80 56",
    "sg:postcode":"20302",
    "sg:province":"Guip\u00f9zcoa",
    "wof:name":"Academia Lacunza S.a.",
    "wof:placetype":"venue"
},
  "geometry": {"coordinates":[-1.7918339968,43.339427948],"type":"Point"}
}