{
  "type": "Feature",
  "properties": {
    "addr:full":"Calle de Mayor, 20 Arenas -areeta Vizcaya 48930",
    "addr:housenumber":"20;areeta",
    "addr:postcode":"48930",
    "addr:street":"Calle De Mayor",
    "iso:country":"ES",
    "sg:address":"Calle de Mayor, 20",
    "sg:city":"Arenas -areeta",
    "sg:orig_category":"Abogados",
    "sg:phone":"+34 944 63 33 66",
    "sg:postcode":"48930",
    "sg:province":"Vizcaya",
    "wof:name":"Picaza Cortes Juan Ignacio",
    "wof:placetype":"venue"
},
  "geometry": {"coordinates":[-3.012196064,43.3261985779],"type":"Point"}
}