{
  "type": "Feature",
  "properties": {
    "addr:full":"Rua C, 1 Cudeiro Ourense 32103",
    "addr:postcode":"32103",
    "addr:street":"C 1",
    "iso:country":"ES",
    "sg:address":"Rua C, 1",
    "sg:city":"Cudeiro",
    "sg:orig_category":"Fabricaci\u00d3n De Generadores De Aire Caliente",
    "sg:phone":"+34 988 23 03 18",
    "sg:postcode":"32103",
    "sg:province":"Ourense",
    "wof:name":"Doval Blanco Evaristo",
    "wof:placetype":"venue"
},
  "geometry": {"coordinates":[-7.8602490425,42.3681602478],"type":"Point"}
}