{
  "type": "Feature",
  "properties": {
    "addr:full":"Via Laietana, 54 Barcelona Barcelona 08003",
    "addr:housenumber":"54",
    "addr:postcode":"08003",
    "addr:street":"Via Laietana",
    "iso:country":"ES",
    "sg:address":"Via Laietana, 54",
    "sg:city":"Barcelona",
    "sg:orig_category":"Asociaciones, Organismos Culturales Y Socioeducativos",
    "sg:phone":"+34 933 19 67 28",
    "sg:postcode":"08003",
    "sg:province":"Barcelona",
    "sg:website":"www.europcantat.org",
    "wof:name":"Moviment Coral Catala",
    "wof:placetype":"venue"
},
  "geometry": {"coordinates":[2.1741900444,41.3874015808],"type":"Point"}
}