{
  "type": "Feature",
  "properties": {
    "iso:country":"ES",
    "sg:address":"Pg Can Sagrera, 16",
    "sg:city":"S. Just Desvern",
    "sg:orig_category":"\u00d3ptica: Instrumentos (fabricaci\u00d3n)",
    "sg:phone":"+34 934 99 05 75",
    "sg:postcode":"08960",
    "sg:province":"Barcelona",
    "wof:name":"Pallas  Thierry",
    "wof:placetype":"venue"
},
  "geometry": {"coordinates":[2.0710160732,41.3852958679],"type":"Point"}
}