{
  "type": "Feature",
  "properties": {
    "iso:country":"ES",
    "sg:address":"Calle de Rafael Terol, 32",
    "sg:city":"Alacant",
    "sg:orig_category":"Aparcamientos (infraestructuras, Accesorios)",
    "sg:phone":"+34 965 21 71 24",
    "sg:postcode":"03001",
    "sg:province":"Alicante",
    "wof:name":"Parkasa S.a.",
    "wof:placetype":"venue"
},
  "geometry": {"coordinates":[-0.4875400066,38.3424911499],"type":"Point"}
}