{
  "type": "Feature",
  "properties": {
    "addr:full":"Calle de Santa Clara, 15 Burgos Burgos 09002",
    "addr:housenumber":"15",
    "addr:postcode":"09002",
    "addr:street":"Calle De Santa Clara",
    "iso:country":"ES",
    "sg:address":"Calle de Santa Clara, 15",
    "sg:city":"Burgos",
    "sg:orig_category":"Mercer\u00cda, Lencer\u00cda (al Por Menor)",
    "sg:phone":"+34 947 27 77 00",
    "sg:postcode":"09002",
    "sg:province":"Burgos",
    "wof:name":"Perez Garcia Jesus Maria",
    "wof:placetype":"venue"
},
  "geometry": {"coordinates":[-3.6973009109,42.3381195068],"type":"Point"}
}