{
  "type": "Feature",
  "properties": {
    "addr:full":"Calle de Jolastokieta, 1 Arenas -areeta Vizcaya 48930",
    "addr:housenumber":"1;areeta",
    "addr:postcode":"48930",
    "addr:street":"Calle De Jolastokieta",
    "iso:country":"ES",
    "sg:address":"Calle de Jolastokieta, 1",
    "sg:city":"Arenas -areeta",
    "sg:orig_category":"Peluqueros: De Se\u00d1oras",
    "sg:phone":"+34 944 64 57 66",
    "sg:postcode":"48930",
    "sg:province":"Vizcaya",
    "wof:name":"Valencia Blanco Ana",
    "wof:placetype":"venue"
},
  "geometry": {"coordinates":[-2.6983869076,43.2204284668],"type":"Point"}
}