{
  "type": "Feature",
  "properties": {
    "iso:country":"ES",
    "sg:address":"Calle de Nicolas Usera, 65",
    "sg:city":"Madrid",
    "sg:orig_category":"Negocio De Materiales De Construcci\u00d3n",
    "sg:phone":"+34 914 75 60 41",
    "sg:postcode":"28026",
    "sg:province":"Madrid",
    "wof:name":"Marconsa S.l.",
    "wof:placetype":"venue"
},
  "geometry": {"coordinates":[-3.7051749229,40.3836288452],"type":"Point"}
}