{
  "type": "Feature",
  "properties": {
    "addr:full":"Avda Joaquin Costa, 8 Caspe Zaragoza 50700",
    "addr:housenumber":"8",
    "addr:postcode":"50700",
    "addr:street":"Avda Joaquin Costa",
    "iso:country":"ES",
    "sg:address":"Avda Joaquin Costa, 8",
    "sg:city":"Caspe",
    "sg:orig_category":"Promotores Constructores",
    "sg:phone":"+34 976 63 09 56",
    "sg:postcode":"50700",
    "sg:province":"Zaragoza",
    "wof:name":"Alonso Arcos Jose Manuel",
    "wof:placetype":"venue"
},
  "geometry": {"coordinates":[-0.0443414003,41.2348861694],"type":"Point"}
}