{
  "type": "Feature",
  "properties": {
    "addr:full":"Carretera De Alcolea, Km. 0002,0 Laujar Andarax Almer\u00eda 04470",
    "addr:postcode":"04470",
    "addr:street":"Carretera De Alcolea Km. 0002,0;Almeri\u0301A",
    "iso:country":"ES",
    "sg:address":"Carretera De Alcolea, Km. 0002,0",
    "sg:city":"Laujar Andarax",
    "sg:orig_category":"Distribuci\u00d3n De Petr\u00d3leo Y Derivados",
    "sg:phone":"+34 950 51 32 03",
    "sg:postcode":"04470",
    "sg:province":"Almer\u00eda",
    "wof:name":"Perez Herrero Jose",
    "wof:placetype":"venue"
},
  "geometry": {"coordinates":[-2.8938889503,36.9929962158],"type":"Point"}
}