{
  "type": "Feature",
  "properties": {
    "addr:full":"Plaz Carlos Lopez Bonilla, 3 Oca\u00f1a Toledo 45300",
    "addr:housenumber":"3",
    "addr:postcode":"45300",
    "addr:street":"Bonilla",
    "iso:country":"ES",
    "sg:address":"Plaz Carlos Lopez Bonilla, 3",
    "sg:city":"Oca\u00f1a",
    "sg:orig_category":"Supermercados Y Hipermercados",
    "sg:phone":"+34 925 13 02 17",
    "sg:postcode":"45300",
    "sg:province":"Toledo",
    "wof:name":"Autoservicio La Posada S.l.",
    "wof:placetype":"venue"
},
  "geometry": {"coordinates":[-3.5016310215,39.9581375122],"type":"Point"}
}