{
  "type": "Feature",
  "properties": {
    "iso:country":"ES",
    "sg:address":"Calle de Mayor, 18",
    "sg:city":"Castellon",
    "sg:orig_category":"Asesor\u00cda Fiscal Y Jur\u00cddica",
    "sg:phone":"+34 964 23 96 95",
    "sg:postcode":"12001",
    "sg:province":"Castell\u00f3n",
    "wof:name":"Confis Asesores Castellon S.l.",
    "wof:placetype":"venue"
},
  "geometry": {"coordinates":[-0.0390900001,39.9866714478],"type":"Point"}
}