{
  "type": "Feature",
  "properties": {
    "iso:country":"ES",
    "sg:address":"Calle de Rosa (la), 4",
    "sg:city":"Jaca",
    "sg:orig_category":"Grafistas",
    "sg:phone":"+34 974 35 60 70",
    "sg:postcode":"22700",
    "sg:province":"Huesca",
    "wof:name":"Moreno Irigaray Saul Abel",
    "wof:placetype":"venue"
},
  "geometry": {"coordinates":[-0.549087882,42.5700683594],"type":"Point"}
}