{
  "type": "Feature",
  "properties": {
    "iso:country":"ES",
    "sg:address":"Ctra Sils, 19",
    "sg:city":"Santa Coloma De Farners",
    "sg:orig_category":"Mec\u00c1nico Del Autom\u00d3vil",
    "sg:phone":"+34 972 84 06 89",
    "sg:postcode":"17430",
    "sg:province":"Girona",
    "wof:name":"Electromecanica Miquel S.l.",
    "wof:placetype":"venue"
},
  "geometry": {"coordinates":[2.6731309891,41.8579330444],"type":"Point"}
}