{
  "type": "Feature",
  "properties": {
    "addr:full":"Urbialde Plaza, 7 Beasain Guip\u00f9zcoa 20200",
    "addr:housenumber":"7",
    "addr:postcode":"20200",
    "addr:street":"Guipu\u0300Zcoa",
    "iso:country":"ES",
    "sg:address":"Urbialde Plaza, 7",
    "sg:city":"Beasain",
    "sg:orig_category":"Edici\u00d3n De Diarios, Revistas, Boletines",
    "sg:phone":"+34 943 16 00 56",
    "sg:postcode":"20200",
    "sg:province":"Guip\u00f9zcoa",
    "wof:name":"Goierriko Hedabideak S.l.",
    "wof:placetype":"venue"
},
  "geometry": {"coordinates":[-2.198579073,43.0478401184],"type":"Point"}
}