{
  "type": "Feature",
  "properties": {
    "iso:country":"ES",
    "sg:address":"Calle de General Vara De Rey, 41",
    "sg:city":"Logro\u00f1o",
    "sg:orig_category":"Organismos De Reclutamiento",
    "sg:phone":"+34 941 24 53 23",
    "sg:postcode":"26002",
    "sg:province":"La Rioja",
    "wof:name":"Cistra Consultoria S.l.l",
    "wof:placetype":"venue"
},
  "geometry": {"coordinates":[-2.4466691017,42.4585189819],"type":"Point"}
}