{
  "type": "Feature",
  "properties": {
    "iso:country":"ES",
    "sg:address":"Calle de Blas Perez Gonzalez, 27",
    "sg:city":"San Pedro De Bre\u00e7a Alta",
    "sg:orig_category":"Ense\u00d1anza, Formaci\u00d3n Profesional: Aprendizaje",
    "sg:phone":"+34 922 42 94 23",
    "sg:postcode":"38710",
    "sg:province":"Santa Cruz De Tenerife",
    "wof:name":"Ayuntamiento De Bre\u00f1a Alta",
    "wof:placetype":"venue"
},
  "geometry": {"coordinates":[-16.2548561096,28.4698104858],"type":"Point"}
}