{
  "type": "Feature",
  "properties": {
    "addr:full":"Cami Planas, S/n Mora Ebre Tarragona 43740",
    "addr:housenumber":"s / n",
    "addr:postcode":"43740",
    "addr:street":"Planas;Ebre",
    "iso:country":"ES",
    "sg:address":"Cami Planas, S/n",
    "sg:city":"Mora Ebre",
    "sg:orig_category":"Asociaciones Humanitarias, De Cooperaci\u00d3n, De Acci\u00d3n Social",
    "sg:phone":"+34 977 40 03 56",
    "sg:postcode":"43740",
    "sg:province":"Tarragona",
    "wof:name":"Asociacion Proyecto A.r.r.i.",
    "wof:placetype":"venue"
},
  "geometry": {"coordinates":[1.2454571724,41.11901474],"type":"Point"}
}