{
  "type": "Feature",
  "properties": {
    "iso:country":"ES",
    "sg:address":"Calle de Mayor, 38",
    "sg:city":"Joarilla De Las Matas",
    "sg:orig_category":"Lecher\u00cdas",
    "sg:phone":"+34 987 78 35 88",
    "sg:postcode":"24324",
    "sg:province":"Le\u00f3n",
    "wof:name":"Jorzaima S.l.",
    "wof:placetype":"venue"
},
  "geometry": {"coordinates":[-5.1881408691,42.3022079468],"type":"Point"}
}