{
  "type": "Feature",
  "properties": {
    "iso:country":"ES",
    "sg:address":"Carrer de Bassegoda, 11",
    "sg:city":"Barcelona",
    "sg:orig_category":"Artes Gr\u00c1ficas, Artes Pl\u00c1sticas: Material Y Suministros (al Por Menor)",
    "sg:phone":"+34 933 33 42 47",
    "sg:postcode":"08028",
    "sg:province":"Barcelona",
    "wof:name":"Taller Mecanico Dotesel S.l.l.",
    "wof:placetype":"venue"
},
  "geometry": {"coordinates":[2.1260139942,41.3751144409],"type":"Point"}
}