{
  "type": "Feature",
  "properties": {
    "addr:full":"Carr Sant Sebastia, 26 Pollen\u00e7a Islas Baleares 07460",
    "addr:housenumber":"26",
    "addr:postcode":"07460",
    "addr:street":"Carr Sant Sebastia;Islas",
    "iso:country":"ES",
    "sg:address":"Carr Sant Sebastia, 26",
    "sg:city":"Pollen\u00e7a",
    "sg:orig_category":"Internados & Ense\u00d1anza Privada",
    "sg:phone":"+34 971 53 26 65",
    "sg:postcode":"07460",
    "sg:province":"Islas Baleares",
    "wof:name":"L'escoleta Escola D'infants Sociedad Cooperativa",
    "wof:placetype":"venue"
},
  "geometry": {"coordinates":[3.0162899494,39.8792381287],"type":"Point"}
}