{
  "type": "Feature",
  "properties": {
    "iso:country":"ES",
    "sg:address":"Calle de Cristo, 15",
    "sg:city":"Carcelen",
    "sg:orig_category":"Cajas Para Embalar",
    "sg:phone":"+34 967 40 30 40",
    "sg:postcode":"02153",
    "sg:province":"Albacete",
    "wof:name":"Caja Rural De Albacete",
    "wof:placetype":"venue"
},
  "geometry": {"coordinates":[-1.3086876869,39.1042518616],"type":"Point"}
}