{
  "type": "Feature",
  "properties": {
    "iso:country":"ES",
    "sg:address":"Calle de Ramon Areces, 12",
    "sg:city":"Madrid",
    "sg:orig_category":"Ingeniero",
    "sg:phone":"+34 914 30 52 58",
    "sg:postcode":"28030",
    "sg:province":"Madrid",
    "wof:name":"Isolan Castilla La Mancha S.l.",
    "wof:placetype":"venue"
},
  "geometry": {"coordinates":[-3.6621990204,40.410194397],"type":"Point"}
}