{
  "type": "Feature",
  "properties": {
    "iso:country":"ES",
    "sg:address":"Calle de Major Sant Agusti, 3",
    "sg:city":"Alzira",
    "sg:orig_category":"Laboratorios Y Trabajos De Fotograf\u00cda, V\u00cddeo Y Cine",
    "sg:phone":"+34 962 41 37 88",
    "sg:postcode":"46600",
    "sg:province":"Valencia",
    "wof:name":"Amargos Cebolla Enrique",
    "wof:placetype":"venue"
},
  "geometry": {"coordinates":[-0.4364211857,39.1501960754],"type":"Point"}
}