{
  "type": "Feature",
  "properties": {
    "addr:full":"Avda Doctores Terron, 25 Fabero Le\u00f3n 24420",
    "addr:housenumber":"25",
    "addr:postcode":"24420",
    "addr:street":"Avda Doctores Terron;Leo\u0301N",
    "iso:country":"ES",
    "sg:address":"Avda Doctores Terron, 25",
    "sg:city":"Fabero",
    "sg:orig_category":"Inform\u00c1tica Equipo Y Programas (al Por Mayor)",
    "sg:phone":"+34 987 55 20 01",
    "sg:postcode":"24420",
    "sg:province":"Le\u00f3n",
    "wof:name":"Computer Set S.a.",
    "wof:placetype":"venue"
},
  "geometry": {"coordinates":[-6.6251740456,42.7678451538],"type":"Point"}
}