{
  "type": "Feature",
  "properties": {
    "addr:full":"Carrer de Pau Casals, 74 Ametlla Mar Tarragona 43860",
    "addr:housenumber":"74",
    "addr:postcode":"43860",
    "addr:street":"Carrer De Pau Casals",
    "iso:country":"ES",
    "sg:address":"Carrer de Pau Casals, 74",
    "sg:city":"Ametlla Mar",
    "sg:orig_category":"Asociaciones, Organismos Culturales Y Socioeducativos",
    "sg:phone":"+34 977 45 72 69",
    "sg:postcode":"43860",
    "sg:province":"Tarragona",
    "wof:name":"Ajuntament De L'ametlla De Mar",
    "wof:placetype":"venue"
},
  "geometry": {"coordinates":[0.8048622012,40.8834648132],"type":"Point"}
}