{
  "type": "Feature",
  "properties": {
    "iso:country":"ES",
    "sg:address":"Suecia (pol Ind Pla Llerona), S/n",
    "sg:city":"Llerona",
    "sg:orig_category":"Ingenier\u00cda, Centros De Estudios (industria)",
    "sg:phone":"+34 938 40 04 59",
    "sg:postcode":"08520",
    "sg:province":"Barcelona",
    "wof:name":"Aplicaciones Y Sistemas S.l.",
    "wof:placetype":"venue"
},
  "geometry": {"coordinates":[2.2982094288,41.6478767395],"type":"Point"}
}