{
  "type": "Feature",
  "properties": {
    "addr:full":"Plaz Cebada, 10 Madrid Madrid 28005",
    "addr:housenumber":"10",
    "addr:postcode":"madrid;28005",
    "addr:street":"Cebada",
    "iso:country":"ES",
    "sg:address":"Plaz Cebada, 10",
    "sg:city":"Madrid",
    "sg:orig_category":"Alimentaci\u00d3n General (al Por Menor)",
    "sg:phone":"+34 913 64 51 22",
    "sg:postcode":"28005",
    "sg:province":"Madrid",
    "wof:name":"Zhou  Song Chao",
    "wof:placetype":"venue"
},
  "geometry": {"coordinates":[-3.7103083134,40.4114646912],"type":"Point"}
}