{
  "type": "Feature",
  "properties": {
    "addr:full":"Calle de Illescas, 61 Madrid Madrid 28024",
    "addr:housenumber":"61",
    "addr:postcode":"madrid;28024",
    "addr:street":"Calle De Illescas",
    "iso:country":"ES",
    "sg:address":"Calle de Illescas, 61",
    "sg:city":"Madrid",
    "sg:orig_category":"Zapatos (al Por Menor)",
    "sg:phone":"+34 917 11 40 01",
    "sg:postcode":"28024",
    "sg:province":"Madrid",
    "wof:name":"Diaz Escalada Maria Dolores",
    "wof:placetype":"venue"
},
  "geometry": {"coordinates":[-3.7637729645,40.3954048157],"type":"Point"}
}