{
  "type": "Feature",
  "properties": {
    "addr:full":"Calle de Herman Hesse, 37 Malaga M\u00e1laga 29004",
    "addr:housenumber":"37",
    "addr:postcode":"29004",
    "addr:street":"Calle De Herman Hesse;Ma\u0301Laga",
    "iso:country":"ES",
    "sg:address":"Calle de Herman Hesse, 37",
    "sg:city":"Malaga",
    "sg:orig_category":"Mec\u00c1nico Del Autom\u00d3vil",
    "sg:phone":"+34 952 23 24 24",
    "sg:postcode":"29004",
    "sg:province":"M\u00e1laga",
    "wof:name":"Cooperauto Sociedad Cooperativa Andaluza",
    "wof:placetype":"venue"
},
  "geometry": {"coordinates":[-4.4654579163,36.6943397522],"type":"Point"}
}