{
  "type": "Feature",
  "properties": {
    "addr:full":"Fonsin, 18 Fonsin Pontevedra 36614",
    "addr:housenumber":"18",
    "addr:postcode":"36614",
    "addr:street":"Fonsin",
    "iso:country":"ES",
    "sg:address":"Fonsin, 18",
    "sg:city":"Fonsin",
    "sg:orig_category":"T\u00c9cnicos Veterinarios",
    "sg:phone":"+34 986 50 41 12",
    "sg:postcode":"36614",
    "sg:province":"Pontevedra",
    "wof:name":"Vazquez Vidal Francisco Javier",
    "wof:placetype":"venue"
},
  "geometry": {"coordinates":[-8.6971912384,42.5618476868],"type":"Point"}
}