{
  "type": "Feature",
  "properties": {
    "addr:full":"Calle de Gonzalo De Berceo, 13 Najera La Rioja 26300",
    "addr:housenumber":"13",
    "addr:postcode":"26300",
    "addr:street":"Calle De Gonzalo De Berceo;Rioja",
    "iso:country":"ES",
    "sg:address":"Calle de Gonzalo De Berceo, 13",
    "sg:city":"Najera",
    "sg:orig_category":"Institutos De Belleza",
    "sg:phone":"+34 941 36 03 45",
    "sg:postcode":"26300",
    "sg:province":"La Rioja",
    "wof:name":"Lacalle Garcia Maria Del Mar",
    "wof:placetype":"venue"
},
  "geometry": {"coordinates":[-2.7300989628,42.4183197021],"type":"Point"}
}