{
  "type": "Feature",
  "properties": {
    "addr:full":"Calle de Tomas Nougues, 13 Teruel Teruel 44001",
    "addr:housenumber":"13",
    "addr:postcode":"44001",
    "addr:street":"Calle De Tomas Nougues",
    "iso:country":"ES",
    "sg:address":"Calle de Tomas Nougues, 13",
    "sg:city":"Teruel",
    "sg:orig_category":"Agencias De Viajes",
    "sg:phone":"+34 978 61 05 22",
    "sg:postcode":"44001",
    "sg:province":"Teruel",
    "sg:website":"www.halconviajes.com",
    "wof:name":"Viajes Halcon S.a.",
    "wof:placetype":"venue"
},
  "geometry": {"coordinates":[-1.106441021,40.3415679932],"type":"Point"}
}