{
  "type": "Feature",
  "properties": {
    "iso:country":"ES",
    "sg:address":"Calle de Comercial Hercules, 8",
    "sg:city":"Coru\u00d1a",
    "sg:orig_category":"Arte, Cultura, Edici\u00d3n",
    "sg:phone":"+34 981 20 28 63",
    "sg:postcode":"15002",
    "sg:province":"La Coru\u00f1a",
    "wof:name":"Orfeon Herculino",
    "wof:placetype":"venue"
},
  "geometry": {"coordinates":[-8.4019651413,43.3774375916],"type":"Point"}
}