{
  "type": "Feature",
  "properties": {
    "iso:country":"ES",
    "sg:address":"Rond Sant Antoni, 102",
    "sg:city":"Barcelona",
    "sg:orig_category":"Fabricaci\u00d3n De Bebidas No Alcoh\u00d3licas",
    "sg:phone":"+34 933 01 95 33",
    "sg:postcode":"08001",
    "sg:province":"Barcelona",
    "wof:name":"Miquel Gisbert Jaime",
    "wof:placetype":"venue"
},
  "geometry": {"coordinates":[2.1640241146,41.3849983215],"type":"Point"}
}