{
  "type": "Feature",
  "properties": {
    "addr:full":"Carr Tenor Alonso, 55 Godella Valencia 46110",
    "addr:housenumber":"55",
    "addr:postcode":"46110",
    "addr:street":"Carr Tenor Alonso",
    "iso:country":"ES",
    "sg:address":"Carr Tenor Alonso, 55",
    "sg:city":"Godella",
    "sg:orig_category":"Cajas De Ahorro",
    "sg:phone":"+34 963 63 88 32",
    "sg:postcode":"46110",
    "sg:province":"Valencia",
    "sg:website":"www.bancaja.es",
    "wof:name":"Caja De Ahorros De Valencia Castellon Y Alicante",
    "wof:placetype":"venue"
},
  "geometry": {"coordinates":[-0.4115790129,39.5183105469],"type":"Point"}
}