{
  "type": "Feature",
  "properties": {
    "addr:full":"Calle de Luis Sauquillo, 90 Fuenlabrada Madrid 28944",
    "addr:housenumber":"90",
    "addr:postcode":"28944",
    "addr:street":"Calle De Luis Sauquillo",
    "iso:country":"ES",
    "sg:address":"Calle de Luis Sauquillo, 90",
    "sg:city":"Fuenlabrada",
    "sg:orig_category":"Promotores Constructores",
    "sg:phone":"+34 916 04 98 42",
    "sg:postcode":"28944",
    "sg:province":"Madrid",
    "wof:name":"Vias Y Construcciones S. A.",
    "wof:placetype":"venue"
},
  "geometry": {"coordinates":[-3.8050119877,40.2749214172],"type":"Point"}
}