{
  "type": "Feature",
  "properties": {
    "iso:country":"ES",
    "sg:address":"Calle de O\u00d1a, 55",
    "sg:city":"Madrid",
    "sg:orig_category":"Centros Empresariales",
    "sg:phone":"+34 917 66 71 55",
    "sg:postcode":"28050",
    "sg:province":"Madrid",
    "wof:name":"Perez-fajardo Frochoso Rocio",
    "wof:placetype":"venue"
},
  "geometry": {"coordinates":[-3.6665699482,40.4890823364],"type":"Point"}
}