{
  "type": "Feature",
  "properties": {
    "addr:full":"Calle de Jose Iturbi, 8 Marbella M\u00e1laga 29600",
    "addr:housenumber":"8",
    "addr:postcode":"29600",
    "addr:street":"Calle De Jose Iturbi;Ma\u0301Laga",
    "iso:country":"ES",
    "sg:address":"Calle de Jose Iturbi, 8",
    "sg:city":"Marbella",
    "sg:orig_category":"Molduras, Junquillos, Listones Y Molduras Perforadas",
    "sg:phone":"+34 952 90 07 55",
    "sg:postcode":"29600",
    "sg:province":"M\u00e1laga",
    "wof:name":"Shree Ganesh S L",
    "wof:placetype":"venue"
},
  "geometry": {"coordinates":[-4.8768191338,36.5139694214],"type":"Point"}
}