{
  "type": "Feature",
  "properties": {
    "addr:full":"Carrer de F. Pi I Margall, 73 Gava Barcelona 08850",
    "addr:housenumber":"73",
    "addr:postcode":"08850",
    "addr:street":"Carrer De F. Pi;Margall",
    "iso:country":"ES",
    "sg:address":"Carrer de F. Pi I Margall, 73",
    "sg:city":"Gava",
    "sg:orig_category":"Empresas De Carpinter\u00cda Met\u00c1lica",
    "sg:phone":"+34 936 62 92 41",
    "sg:postcode":"08850",
    "sg:province":"Barcelona",
    "wof:name":"Carpinteria Metalica J.garcia S.l.",
    "wof:placetype":"venue"
},
  "geometry": {"coordinates":[1.9996210337,41.2960395813],"type":"Point"}
}