{
  "type": "Feature",
  "properties": {
    "iso:country":"ES",
    "sg:address":"Avda Tenor Fleta, 93",
    "sg:city":"Zaragoza",
    "sg:orig_category":"Frutas Y Legumbres Secas (al Por Mayor)",
    "sg:phone":"+34 976 42 11 19",
    "sg:postcode":"50008",
    "sg:province":"Zaragoza",
    "wof:name":"Frutos Secos El Rincon S. L.",
    "wof:placetype":"venue"
},
  "geometry": {"coordinates":[-0.8770110011,41.6376686096],"type":"Point"}
}