{
  "type": "Feature",
  "properties": {
    "addr:full":"Carrer de Navarra, 22 Masnou Barcelona 08320",
    "addr:housenumber":"22",
    "addr:postcode":"08320",
    "addr:street":"Carrer De Navarra",
    "iso:country":"ES",
    "sg:address":"Carrer de Navarra, 22",
    "sg:city":"Masnou",
    "sg:orig_category":"Empresas De Carpinter\u00cda Met\u00c1lica",
    "sg:phone":"+34 935 40 15 28",
    "sg:postcode":"08320",
    "sg:province":"Barcelona",
    "wof:name":"Urduri Berri S.c.p.",
    "wof:placetype":"venue"
},
  "geometry": {"coordinates":[2.3172550201,41.4815673828],"type":"Point"}
}