{
  "type": "Feature",
  "properties": {
    "addr:full":"Carrer de Moli D'en Bisbe, S/n Mas Rampinyo Barcelona 08110",
    "addr:housenumber":"s",
    "addr:postcode":"08110",
    "addr:street":"Carrer De Moli D'En Bisbe;/ N Mas Rampinyo",
    "iso:country":"ES",
    "sg:address":"Carrer de Moli D'en Bisbe, S/n",
    "sg:city":"Mas Rampinyo",
    "sg:orig_category":"Comercio De Piezas De Recambio Y De Accesorios De Veh\u00cdculos, Veh\u00cdculos Industriales",
    "sg:phone":"+34 935 75 00 25",
    "sg:postcode":"08110",
    "sg:province":"Barcelona",
    "sg:website":"www.roadhouse.es",
    "wof:name":"Comercial De Recambis R.h. S.l.",
    "wof:placetype":"venue"
},
  "geometry": {"coordinates":[2.1798729897,41.4892082214],"type":"Point"}
}