{
  "type": "Feature",
  "properties": {
    "addr:full":"Carr Bisbe Ruano, 20 Lleida Lleida 25006",
    "addr:housenumber":"20",
    "addr:postcode":"25006",
    "addr:street":"Carr Bisbe Ruano",
    "iso:country":"ES",
    "sg:address":"Carr Bisbe Ruano, 20",
    "sg:city":"Lleida",
    "sg:orig_category":"Electrodom\u00c9sticos (al Por Menor)",
    "sg:phone":"+34 973 28 02 02",
    "sg:postcode":"25006",
    "sg:province":"Lleida",
    "wof:name":"Gefic S.l.",
    "wof:placetype":"venue"
},
  "geometry": {"coordinates":[0.617513001,41.6173019409],"type":"Point"}
}