{
  "type": "Feature",
  "properties": {
    "addr:full":"Pg Segre, 33 S. Lloren\u00e7 Montgai Lleida 25613",
    "addr:housenumber":"33",
    "addr:postcode":"25613",
    "addr:street":"Pg Segre;S. Llorenc\u0327",
    "iso:country":"ES",
    "sg:address":"Pg Segre, 33",
    "sg:city":"S. Lloren\u00e7 Montgai",
    "sg:orig_category":"Panader\u00cdas, Panader\u00cdas",
    "sg:phone":"+34 973 42 03 91",
    "sg:postcode":"25613",
    "sg:province":"Lleida",
    "wof:name":"Gaber S.c.p.",
    "wof:placetype":"venue"
},
  "geometry": {"coordinates":[0.9574335217,41.7990036011],"type":"Point"}
}