{
  "type": "Feature",
  "properties": {
    "addr:full":"Avda Cesareo Pondal, 84 Laxe La Coru\u00f1a 15117",
    "addr:housenumber":"84",
    "addr:postcode":"15117",
    "addr:street":"Avda Cesareo Pondal;La Corun\u0303A",
    "iso:country":"ES",
    "sg:address":"Avda Cesareo Pondal, 84",
    "sg:city":"Laxe",
    "sg:orig_category":"Arquitectos",
    "sg:phone":"+34 981 73 50 27",
    "sg:postcode":"15117",
    "sg:province":"La Coru\u00f1a",
    "wof:name":"Paredes Insua Jorge",
    "wof:placetype":"venue"
},
  "geometry": {"coordinates":[-8.9999494553,43.2139511108],"type":"Point"}
}