{
  "type": "Feature",
  "properties": {
    "addr:full":"Calle de Vi\u00d1agrande, 64 Soto Madrid 28978",
    "addr:housenumber":"64",
    "addr:postcode":"28978",
    "addr:street":"Calle De Vin\u0303Agrande",
    "iso:country":"ES",
    "sg:address":"Calle de Vi\u00d1agrande, 64",
    "sg:city":"Soto",
    "sg:orig_category":"Alquiler De Gr\u00daas",
    "sg:phone":"+34 918 14 28 92",
    "sg:postcode":"28978",
    "sg:province":"Madrid",
    "wof:name":"Fernandez Garcia Yolanda",
    "wof:placetype":"venue"
},
  "geometry": {"coordinates":[-3.8499689102,40.1990089417],"type":"Point"}
}