{
  "type": "Feature",
  "properties": {
    "iso:country":"ES",
    "sg:address":"Calle de Rio Alberche (del), 10",
    "sg:city":"Humanes De Madrid",
    "sg:orig_category":"Empresas De Carpinter\u00cda",
    "sg:phone":"+34 916 04 97 63",
    "sg:postcode":"28970",
    "sg:province":"Madrid",
    "sg:website":"www.jorkon.com",
    "wof:name":"Jorkon S.l.",
    "wof:placetype":"venue"
},
  "geometry": {"coordinates":[-3.8135008812,40.2655906677],"type":"Point"}
}