{
  "type": "Feature",
  "properties": {
    "iso:country":"ES",
    "sg:address":"Calle de Ortega Y Gasset, 32",
    "sg:city":"Elda",
    "sg:orig_category":"Ropa Para Se\u00d1oras Y Caballeros (al Por Menor)",
    "sg:phone":"+34 965 38 21 76",
    "sg:postcode":"03600",
    "sg:province":"Alicante",
    "wof:name":"Gimenez Egea Miguel",
    "wof:placetype":"venue"
},
  "geometry": {"coordinates":[-0.7949450016,38.4789085388],"type":"Point"}
}