{
  "type": "Feature",
  "properties": {
    "addr:full":"Carrer de Dolores Viudes Blasco, 4 Guardamar Segura Alicante 03140",
    "addr:housenumber":"4",
    "addr:postcode":"03140",
    "addr:street":"Carrer De Dolores Viudes Blasco",
    "iso:country":"ES",
    "sg:address":"Carrer de Dolores Viudes Blasco, 4",
    "sg:city":"Guardamar Segura",
    "sg:orig_category":"Empresas De Carpinter\u00cda De Madera",
    "sg:phone":"+34 965 72 90 25",
    "sg:postcode":"03140",
    "sg:province":"Alicante",
    "wof:name":"Sanchez Corredera Aurora",
    "wof:placetype":"venue"
},
  "geometry": {"coordinates":[-0.6538630128,38.0822105408],"type":"Point"}
}