{
  "type": "Feature",
  "properties": {
    "iso:country":"ES",
    "sg:address":"Ctra. Nnal. Seiscientos Uno, Km. 0145,3",
    "sg:city":"Cuellar",
    "sg:orig_category":"Mec\u00c1nico Del Autom\u00d3vil",
    "sg:phone":"+34 921 14 00 79",
    "sg:postcode":"40200",
    "sg:province":"Segovia",
    "wof:name":"Talleres Santa Clara S.l.",
    "wof:placetype":"venue"
},
  "geometry": {"coordinates":[-4.3119688034,41.4013137817],"type":"Point"}
}