{
  "type": "Feature",
  "properties": {
    "addr:full":"Calle de Mayor, 13 Vera Almer\u00eda 04620",
    "addr:housenumber":"13;almeri\u0301a",
    "addr:postcode":"04620",
    "addr:street":"Calle De Mayor",
    "iso:country":"ES",
    "sg:address":"Calle de Mayor, 13",
    "sg:city":"Vera",
    "sg:classifiers":[
        {
            "category":"Communications",
            "type":"Services"
        }
    ],
    "sg:phone":"+34 950 39 04 44",
    "sg:postcode":"04620",
    "sg:province":"Almer\u00eda",
    "sg:tags":[
        "televisiones",
        "y",
        "radio"
    ],
    "wof:name":"Comunicaciones Vera Levante S.l.",
    "wof:placetype":"venue"
},
  "geometry": {"coordinates":[-1.8687740564,37.2472915649],"type":"Point"}
}