{
  "type": "Feature",
  "properties": {
    "iso:country":"ES",
    "sg:address":"C/ Poeta Miguel Hernandez, 10",
    "sg:city":"Elche",
    "sg:orig_category":"Agencias Y Agentes Comerciales, Representantes",
    "sg:phone":"+34 965 44 56 02",
    "sg:postcode":"03201",
    "sg:province":"Alicante",
    "wof:name":"Ferrandez Marti Manuel",
    "wof:placetype":"venue"
},
  "geometry": {"coordinates":[-0.7033590078,38.2643928528],"type":"Point"}
}