{
  "type": "Feature",
  "properties": {
    "addr:full":"Avda Constitucion (de La), 16 Pedro Mu\u00e7oz Ciudad Real 13620",
    "addr:housenumber":"16",
    "addr:postcode":"13620",
    "addr:street":"Avda Constitucion De La;Pedro Muc\u0327Oz",
    "iso:country":"ES",
    "sg:address":"Avda Constitucion (de La), 16",
    "sg:city":"Pedro Mu\u00e7oz",
    "sg:orig_category":"M\u00c1rmoles, Granitos Y Piedras Naturales",
    "sg:phone":"+34 926 56 85 09",
    "sg:postcode":"13620",
    "sg:province":"Ciudad Real",
    "wof:name":"Marmoles Anjuvi S.l.",
    "wof:placetype":"venue"
},
  "geometry": {"coordinates":[-2.955878973,39.4055213928],"type":"Point"}
}