{
  "type": "Feature",
  "properties": {
    "addr:full":"Plaz Santa Maria, 5 Villarrobledo Albacete 02600",
    "addr:housenumber":"5",
    "addr:postcode":"02600",
    "addr:street":"Santa Maria",
    "iso:country":"ES",
    "sg:address":"Plaz Santa Maria, 5",
    "sg:city":"Villarrobledo",
    "sg:orig_category":"Organizaciones Internacionales",
    "sg:phone":"+34 967 14 16 72",
    "sg:postcode":"02600",
    "sg:province":"Albacete",
    "wof:name":"Caritas Diocesanas De Albacete-interparroquial De Villarrobledo",
    "wof:placetype":"venue"
},
  "geometry": {"coordinates":[-2.6060531139,39.2663192749],"type":"Point"}
}