{
  "type": "Feature",
  "properties": {
    "iso:country":"ES",
    "sg:address":"Calle de Rodil, 32",
    "sg:city":"Donostia-san Sebastian",
    "sg:orig_category":"Limpieza Industrial",
    "sg:phone":"+34 943 27 44 25",
    "sg:postcode":"20013",
    "sg:province":"Guip\u00f9zcoa",
    "wof:name":"Lavanderia Tauki S.cv.",
    "wof:placetype":"venue"
},
  "geometry": {"coordinates":[-1.9671939611,43.3252868652],"type":"Point"}
}