{
  "type": "Feature",
  "properties": {
    "addr:full":"Pg Cervantes, S/n Pego Alicante 03780",
    "addr:housenumber":"s / n",
    "addr:postcode":"03780",
    "addr:street":"Pg Cervantes",
    "iso:country":"ES",
    "sg:address":"Pg Cervantes, S/n",
    "sg:city":"Pego",
    "sg:orig_category":"Heladeros",
    "sg:phone":"+34 965 57 02 68",
    "sg:postcode":"03780",
    "sg:province":"Alicante",
    "wof:name":"Alcaraz Siscar Rosalia",
    "wof:placetype":"venue"
},
  "geometry": {"coordinates":[-0.120308198,38.8391571045],"type":"Point"}
}