{
  "type": "Feature",
  "properties": {
    "iso:country":"ES",
    "sg:address":"C/ Doctor Ferran, 1",
    "sg:city":"Salt",
    "sg:orig_category":"\u00d3ptica: Instrumentos (fabricaci\u00d3n)",
    "sg:phone":"+34 972 23 06 61",
    "sg:postcode":"17190",
    "sg:province":"Girona",
    "wof:name":"Njie Sanyang Adama",
    "wof:placetype":"venue"
},
  "geometry": {"coordinates":[2.7885611057,41.9744529724],"type":"Point"}
}