{
  "type": "Feature",
  "properties": {
    "addr:full":"Calle de Arrandi, 33 San Vicente De Barakaldo Vizcaya 48901",
    "addr:housenumber":"33",
    "addr:postcode":"48901",
    "addr:street":"Calle De Arrandi",
    "iso:country":"ES",
    "sg:address":"Calle de Arrandi, 33",
    "sg:city":"San Vicente De Barakaldo",
    "sg:orig_category":"Zapatos (al Por Menor)",
    "sg:phone":"+34 944 37 11 80",
    "sg:postcode":"48901",
    "sg:province":"Vizcaya",
    "wof:name":"Miguel Fresno Elena",
    "wof:placetype":"venue"
},
  "geometry": {"coordinates":[-2.9864742756,43.2946929932],"type":"Point"}
}