{
  "type": "Feature",
  "properties": {
    "addr:full":"Calle de Mesones, 29 Granada Granada 18001",
    "addr:housenumber":"29",
    "addr:postcode":"18001",
    "addr:street":"Calle De Mesones",
    "iso:country":"ES",
    "sg:address":"Calle de Mesones, 29",
    "sg:city":"Granada",
    "sg:orig_category":"Ropa Para Se\u00d1oras Y Caballeros (al Por Menor)",
    "sg:phone":"+34 958 52 36 51",
    "sg:postcode":"18001",
    "sg:province":"Granada",
    "wof:name":"Iniciativas Galascar S.a.",
    "wof:placetype":"venue"
},
  "geometry": {"coordinates":[-3.6005139351,37.1745872498],"type":"Point"}
}