{
  "type": "Feature",
  "properties": {
    "addr:full":"Calle de San Miguel, 31 Torremolinos M\u00e1laga 29620",
    "addr:housenumber":"31",
    "addr:postcode":"29620",
    "addr:street":"Calle De San Miguel;Ma\u0301Laga",
    "iso:country":"ES",
    "sg:address":"Calle de San Miguel, 31",
    "sg:city":"Torremolinos",
    "sg:orig_category":"M\u00c9dicos: An\u00c1lisis Cl\u00cdnicos",
    "sg:phone":"+34 952 38 36 60",
    "sg:postcode":"29620",
    "sg:province":"M\u00e1laga",
    "wof:name":"Sanchez Sanchez Manuel",
    "wof:placetype":"venue"
},
  "geometry": {"coordinates":[-4.4983778,36.6232795715],"type":"Point"}
}