{
  "type": "Feature",
  "properties": {
    "addr:full":"Calle de Nafarroa Calle, 1 Barakaldo Vizcaya 48901",
    "addr:postcode":"48901",
    "addr:street":"Calle De Nafarroa Calle 1",
    "iso:country":"ES",
    "sg:address":"Calle de Nafarroa Calle, 1",
    "sg:city":"Barakaldo",
    "sg:orig_category":"Centros De Coordinaci\u00d3n",
    "sg:phone":"+34 944 37 43 50",
    "sg:postcode":"48901",
    "sg:province":"Vizcaya",
    "wof:name":"Gestor\u00cda Administrativa Pe\u00d1a-manrique S.l.",
    "wof:placetype":"venue"
},
  "geometry": {"coordinates":[-2.9882760048,43.2968597412],"type":"Point"}
}