{
  "type": "Feature",
  "properties": {
    "addr:full":"Av Angel Sallent, 125 Terrassa Barcelona 08224",
    "addr:housenumber":"125",
    "addr:postcode":"08224",
    "addr:street":"Av Angel Sallent",
    "iso:country":"ES",
    "sg:address":"Av Angel Sallent, 125",
    "sg:city":"Terrassa",
    "sg:orig_category":"Agencias Y Agentes Comerciales, Representantes",
    "sg:phone":"+34 937 88 61 44",
    "sg:postcode":"08224",
    "sg:province":"Barcelona",
    "wof:name":"Font Palos Jose Maria",
    "wof:placetype":"venue"
},
  "geometry": {"coordinates":[1.9992289543,41.5593795776],"type":"Point"}
}