{
  "type": "Feature",
  "properties": {
    "addr:full":"Ctra. Toledo-avila, Km. 0051,4 Escalona Toledo 45910",
    "addr:postcode":"45910",
    "addr:street":"Ctra. Toledo-Avila Km. 0051,4",
    "iso:country":"ES",
    "sg:address":"Ctra. Toledo-avila, Km. 0051,4",
    "sg:city":"Escalona",
    "sg:orig_category":"Negocio De Madera",
    "sg:phone":"+34 925 78 31 68",
    "sg:postcode":"45910",
    "sg:province":"Toledo",
    "wof:name":"Brico Redondo S.l.",
    "wof:placetype":"venue"
},
  "geometry": {"coordinates":[-4.4054641724,40.1705665588],"type":"Point"}
}