{
  "type": "Feature",
  "properties": {
    "addr:full":"Pol Industrial, S/n Finestrat Alicante 03509",
    "addr:housenumber":"/ n",
    "addr:postcode":"03509",
    "addr:street":"Industrial",
    "iso:country":"ES",
    "sg:address":"Pol Industrial, S/n",
    "sg:city":"Finestrat",
    "sg:orig_category":"Aguas (distribuci\u00d3n, Servicios)",
    "sg:phone":"+34 965 85 02 23",
    "sg:postcode":"03509",
    "sg:province":"Alicante",
    "sg:website":"www.aquaagestlevanteagbar.net",
    "wof:name":"Aquagest Levante S.a.",
    "wof:placetype":"venue"
},
  "geometry": {"coordinates":[-0.1963364035,38.5793762207],"type":"Point"}
}