{
  "type": "Feature",
  "properties": {
    "iso:country":"ES",
    "sg:address":"Calle de Filiberto Villalobos, 69",
    "sg:city":"Guijuelo",
    "sg:orig_category":"Charcuter\u00cdas (al Por Mayor)",
    "sg:phone":"+34 923 58 06 08",
    "sg:postcode":"37770",
    "sg:province":"Salamanca",
    "wof:name":"Luis Domingo Hernandez E Hijos S.a.",
    "wof:placetype":"venue"
},
  "geometry": {"coordinates":[-5.6733989716,40.5556716919],"type":"Point"}
}