{
  "type": "Feature",
  "properties": {
    "addr:full":"Calle de Rosalia De Castro, 1 Santa Cruz De Tenerife Santa Cruz De Tenerife 38010",
    "addr:housenumber":"1",
    "addr:postcode":"38010",
    "addr:street":"Calle De Rosalia De Castro",
    "iso:country":"ES",
    "sg:address":"Calle de Rosalia De Castro, 1",
    "sg:city":"Santa Cruz De Tenerife",
    "sg:orig_category":"Venta, Instalaci\u00d3n, Reparaci\u00d3n De Antenas Para Televisi\u00d3n",
    "sg:phone":"+34 922 65 82 14",
    "sg:postcode":"38010",
    "sg:province":"Santa Cruz De Tenerife",
    "wof:name":"Intersat Canarias S.l.l.",
    "wof:placetype":"venue"
},
  "geometry": {"coordinates":[-16.290353775,28.4528846741],"type":"Point"}
}