{
  "type": "Feature",
  "properties": {
    "iso:country":"ES",
    "sg:address":"Calle de Santa Engracia, 40",
    "sg:city":"Madrid",
    "sg:orig_category":"Farmacias",
    "sg:phone":"+34 914 47 72 48",
    "sg:postcode":"28010",
    "sg:province":"Madrid",
    "wof:name":"Merinero Rivilla Beatriz",
    "wof:placetype":"venue"
},
  "geometry": {"coordinates":[-3.6976130009,40.4326591492],"type":"Point"}
}