{
  "type": "Feature",
  "properties": {
    "addr:full":"Carrer de Giralt El Pellisser, 6 Barcelona Barcelona 08003",
    "addr:housenumber":"6",
    "addr:postcode":"08003",
    "addr:street":"Carrer De Giralt El Pellisser",
    "iso:country":"ES",
    "sg:address":"Carrer de Giralt El Pellisser, 6",
    "sg:city":"Barcelona",
    "sg:orig_category":"Alimentaci\u00d3n General (al Por Menor)",
    "sg:phone":"+34 933 19 93 52",
    "sg:postcode":"08003",
    "sg:province":"Barcelona",
    "wof:name":"Granja Giralt S.c.p.",
    "wof:placetype":"venue"
},
  "geometry": {"coordinates":[2.1795830727,41.3861198425],"type":"Point"}
}