{
  "type": "Feature",
  "properties": {
    "iso:country":"ES",
    "sg:address":"Ctra Planes, S/n",
    "sg:city":"Muro Alcoy",
    "sg:orig_category":"Fabricaci\u00d3n, Venta De Cuadros, Accesorios Para Enmarcar",
    "sg:phone":"+34 965 53 11 52",
    "sg:postcode":"03830",
    "sg:province":"Alicante",
    "sg:website":"www.markestil.com",
    "wof:name":"Markestil S. L.",
    "wof:placetype":"venue"
},
  "geometry": {"coordinates":[-0.4414289892,38.7812538147],"type":"Point"}
}