{
  "type": "Feature",
  "properties": {
    "addr:full":"Calle de Santo Cristo, 2 Aranda Duero Burgos 09400",
    "addr:housenumber":"2",
    "addr:postcode":"09400",
    "addr:street":"Calle De Santo Cristo",
    "iso:country":"ES",
    "sg:address":"Calle de Santo Cristo, 2",
    "sg:city":"Aranda Duero",
    "sg:orig_category":"Ense\u00d1anza: Comercio, Gesti\u00d3n, Inform\u00c1tica",
    "sg:phone":"+34 947 51 10 64",
    "sg:postcode":"09400",
    "sg:province":"Burgos",
    "wof:name":"Academia Forinfo S.l.",
    "wof:placetype":"venue"
},
  "geometry": {"coordinates":[-3.6898989677,41.6705169678],"type":"Point"}
}