{
  "type": "Feature",
  "properties": {
    "addr:full":"Avda Constitucion, 71 Cistierna Le\u00f3n 24800",
    "addr:housenumber":"71",
    "addr:postcode":"24800",
    "addr:street":"Avda Constitucion;Leo\u0301N",
    "iso:country":"ES",
    "sg:address":"Avda Constitucion, 71",
    "sg:city":"Cistierna",
    "sg:orig_category":"Molduras, Junquillos, Listones Y Molduras Perforadas",
    "sg:phone":"+34 987 70 11 83",
    "sg:postcode":"24800",
    "sg:province":"Le\u00f3n",
    "wof:name":"Gonzalez Garcia Rosalina",
    "wof:placetype":"venue"
},
  "geometry": {"coordinates":[-5.1286687851,42.8040084839],"type":"Point"}
}