{
  "type": "Feature",
  "properties": {
    "addr:full":"Calle de Brezo, 55 Ciudad Real Ciudad Real 13197",
    "addr:housenumber":"55",
    "addr:postcode":"13197",
    "addr:street":"Calle De Brezo",
    "iso:country":"ES",
    "sg:address":"Calle de Brezo, 55",
    "sg:city":"Ciudad Real",
    "sg:orig_category":"Empresas De Limpieza",
    "sg:phone":"+34 926 21 72 18",
    "sg:postcode":"13197",
    "sg:province":"Ciudad Real",
    "wof:name":"Limpisol Limpiezas Sl",
    "wof:placetype":"venue"
},
  "geometry": {"coordinates":[-3.9424054623,38.9739456177],"type":"Point"}
}