{
  "type": "Feature",
  "properties": {
    "addr:full":"Afueras, S/n Pol.ind.son Castello Islas Baleares 07009",
    "addr:postcode":"07009",
    "addr:street":"Afueras S / N Pol.Ind.Son",
    "iso:country":"ES",
    "sg:address":"Afueras, S/n",
    "sg:city":"Pol.ind.son Castello",
    "sg:orig_category":"Fabricaci\u00d3n, Reparaci\u00d3n Y Mantenimiento De Construcciones Navales Y Fluviales",
    "sg:phone":"+34 971 43 10 23",
    "sg:postcode":"07009",
    "sg:province":"Islas Baleares",
    "wof:name":"R.c. Marine S.l.",
    "wof:placetype":"venue"
},
  "geometry": {"coordinates":[2.6741399765,39.6011390686],"type":"Point"}
}