{
  "type": "Feature",
  "properties": {
    "iso:country":"ES",
    "sg:address":"Calle de Isabelita Usera, 25",
    "sg:city":"Madrid",
    "sg:classifiers":[
        {
            "category":"Personal",
            "subcategory":"Barber",
            "type":"Services"
        }
    ],
    "sg:phone":"+34 915 00 31 24",
    "sg:postcode":"28026",
    "sg:province":"Madrid",
    "sg:tags":[
        "caballeros",
        "de",
        "peluqueros"
    ],
    "wof:name":"Camilo Benito Escudero Y Eduardo Gordo Juan C.b.",
    "wof:placetype":"venue"
},
  "geometry": {"coordinates":[-3.7077059746,40.3837776184],"type":"Point"}
}