{
  "type": "Feature",
  "properties": {
    "iso:country":"ES",
    "sg:address":"Carrer de Barnola, 4",
    "sg:city":"Barcelona",
    "sg:orig_category":"Promotores Constructores",
    "sg:phone":"+34 933 11 17 52",
    "sg:postcode":"08030",
    "sg:province":"Barcelona",
    "wof:name":"Comunidad De Propietarios Barnola 4-6",
    "wof:placetype":"venue"
},
  "geometry": {"coordinates":[2.2061920166,41.436542511],"type":"Point"}
}