{
  "type": "Feature",
  "properties": {
    "iso:country":"ES",
    "sg:address":"Calle de Alonso Cano, 93",
    "sg:city":"Madrid",
    "sg:orig_category":"Farmacias",
    "sg:phone":"+34 915 33 88 14",
    "sg:postcode":"28003",
    "sg:province":"Madrid",
    "wof:name":"Vegas Y Vegas Angela",
    "wof:placetype":"venue"
},
  "geometry": {"coordinates":[-3.6974699497,40.4444313049],"type":"Point"}
}