{
  "type": "Feature",
  "properties": {
    "addr:full":"Calle de Naval La, 39 Palmas De Gran Canaria Las Palmas 35008",
    "addr:postcode":"35008",
    "addr:street":"Calle De Naval La 39",
    "iso:country":"ES",
    "sg:address":"Calle de Naval La, 39",
    "sg:city":"Palmas De Gran Canaria",
    "sg:orig_category":"Estancos",
    "sg:phone":"+34 928 46 79 20",
    "sg:postcode":"35008",
    "sg:province":"Las Palmas",
    "wof:name":"Salvador Hussein Abdallah Ortega Sl",
    "wof:placetype":"venue"
},
  "geometry": {"coordinates":[-15.4267578125,28.1495552063],"type":"Point"}
}