{
  "type": "Feature",
  "properties": {
    "iso:country":"ES",
    "sg:address":"Calle de Lope De Rueda, 7",
    "sg:city":"Valladolid",
    "sg:orig_category":"Fabrica, Negocio De Vidrieras, Productos Vidriados Y Espejos",
    "sg:phone":"+34 983 25 10 10",
    "sg:postcode":"47010",
    "sg:province":"Valladolid",
    "wof:name":"Fradejas Monedero Lourdes",
    "wof:placetype":"venue"
},
  "geometry": {"coordinates":[-4.7220058441,41.6603507996],"type":"Point"}
}