{
  "type": "Feature",
  "properties": {
    "iso:country":"ES",
    "sg:address":"C/ Ceranova, 13",
    "sg:city":"Ripollet",
    "sg:orig_category":"Distribuci\u00d3n De Petr\u00d3leo Y Derivados",
    "sg:phone":"+34 935 80 89 41",
    "sg:postcode":"08291",
    "sg:province":"Barcelona",
    "wof:name":"Casamitjana Nonell S.c.p.",
    "wof:placetype":"venue"
},
  "geometry": {"coordinates":[2.1590371132,41.4968070984],"type":"Point"}
}