{
  "type": "Feature",
  "properties": {
    "iso:country":"ES",
    "sg:address":"Calle de Damaso Alonso, 42",
    "sg:city":"Segovia",
    "sg:orig_category":"Molduras, Junquillos, Listones Y Molduras Perforadas",
    "sg:phone":"+34 921 42 99 12",
    "sg:postcode":"40006",
    "sg:province":"Segovia",
    "wof:name":"Lopez Simo Jose Luis",
    "wof:placetype":"venue"
},
  "geometry": {"coordinates":[-4.0967683792,40.9321975708],"type":"Point"}
}