{
  "type": "Feature",
  "properties": {
    "iso:country":"ES",
    "sg:address":"Ctra. Arta-can Picafort, Km. 0013,7",
    "sg:city":"Son Serra De Marina",
    "sg:orig_category":"Equitaci\u00d3n Y Centros De H\u00cdpica",
    "sg:phone":"+34 971 85 41 63",
    "sg:postcode":"07459",
    "sg:province":"Islas Baleares",
    "wof:name":"Moolight Riding S.l.",
    "wof:placetype":"venue"
},
  "geometry": {"coordinates":[3.2209200859,39.739074707],"type":"Point"}
}