{
  "type": "Feature",
  "properties": {
    "iso:country":"ES",
    "sg:address":"Calle de Muza, 38",
    "sg:city":"Merida",
    "sg:orig_category":"Contenedores (mercanc\u00cdas)",
    "sg:phone":"+34 924 31 51 99",
    "sg:postcode":"06800",
    "sg:province":"Badajoz",
    "wof:name":"Vizcaino Galan Cecilio",
    "wof:placetype":"venue"
},
  "geometry": {"coordinates":[-6.347509861,38.9207267761],"type":"Point"}
}