{
  "type": "Feature",
  "properties": {
    "addr:full":"Carrer de Joaquim Ruyra, 3 Reus Tarragona 43206",
    "addr:housenumber":"3",
    "addr:postcode":"43206",
    "addr:street":"Carrer De Joaquim Ruyra",
    "iso:country":"ES",
    "sg:address":"Carrer de Joaquim Ruyra, 3",
    "sg:city":"Reus",
    "sg:orig_category":"Electricidad: Instalaciones Industriales",
    "sg:phone":"+34 977 31 13 72",
    "sg:postcode":"43206",
    "sg:province":"Tarragona",
    "wof:name":"Instalaciones Y Suministros Gacser S.a.",
    "wof:placetype":"venue"
},
  "geometry": {"coordinates":[1.0786030293,41.1583328247],"type":"Point"}
}