{
  "type": "Feature",
  "properties": {
    "iso:country":"ES",
    "sg:address":"Calle de Rosa Chacel, 2",
    "sg:city":"Burgos",
    "sg:orig_category":"Molduras, Junquillos, Listones Y Molduras Perforadas",
    "sg:phone":"+34 947 47 17 66",
    "sg:postcode":"09007",
    "sg:province":"Burgos",
    "wof:name":"Medina Maria Sira",
    "wof:placetype":"venue"
},
  "geometry": {"coordinates":[-3.6593039036,42.362903595],"type":"Point"}
}