{
  "type": "Feature",
  "properties": {
    "addr:full":"Calle de San Jacinto, 81 Sevilla Sevilla 41010",
    "addr:housenumber":"81",
    "addr:postcode":"41010",
    "addr:street":"Calle De San Jacinto",
    "iso:country":"ES",
    "sg:address":"Calle de San Jacinto, 81",
    "sg:city":"Sevilla",
    "sg:orig_category":"Bisuter\u00cda, Joyer\u00cda, Relojer\u00cda (al Por Menor)",
    "sg:phone":"+34 954 33 73 96",
    "sg:postcode":"41010",
    "sg:province":"Sevilla",
    "wof:name":"Ballesteros Montoro S.l.",
    "wof:placetype":"venue"
},
  "geometry": {"coordinates":[-6.0071191788,37.38230896],"type":"Point"}
}