{
  "type": "Feature",
  "properties": {
    "iso:country":"ES",
    "sg:address":"Calle de Costa Brava, 12",
    "sg:city":"Madrid",
    "sg:orig_category":"Promotores Constructores",
    "sg:phone":"+34 915 35 22 57",
    "sg:postcode":"28034",
    "sg:province":"Madrid",
    "wof:name":"Haus Construcciones R.e.p. S.a.",
    "wof:placetype":"venue"
},
  "geometry": {"coordinates":[-3.70723176,40.4983558655],"type":"Point"}
}