{
  "type": "Feature",
  "properties": {
    "iso:country":"ES",
    "sg:address":"Labeaga Kalea, 33 K",
    "sg:city":"Urretxu",
    "sg:orig_category":"Arreglo, Reparaci\u00d3n, Piezas Sueltas De Televisi\u00d3n, V\u00cddeo, Hi",
    "sg:phone":"+34 943 53 25 01",
    "sg:postcode":"20700",
    "sg:province":"Guip\u00f9zcoa",
    "wof:name":"Rafael Fernandez Nu\u00f1ez, Irsonic.",
    "wof:placetype":"venue"
},
  "geometry": {"coordinates":[-2.3134770393,43.086730957],"type":"Point"}
}