{
  "type": "Feature",
  "properties": {
    "addr:full":"Carr Pompeu Fabra, 19 Armentera Girona 17472",
    "addr:housenumber":"19",
    "addr:postcode":"17472",
    "addr:street":"Carr Pompeu Fabra",
    "iso:country":"ES",
    "sg:address":"Carr Pompeu Fabra, 19",
    "sg:city":"Armentera",
    "sg:orig_category":"Producci\u00d3n, Comercio De Cereales",
    "sg:phone":"+34 972 52 01 23",
    "sg:postcode":"17472",
    "sg:province":"Girona",
    "wof:name":"Carbo Isern Josep",
    "wof:placetype":"venue"
},
  "geometry": {"coordinates":[3.0733449459,42.1710243225],"type":"Point"}
}