{
  "type": "Feature",
  "properties": {
    "addr:full":"Av Lleida, S/n Bellpuig Lleida 25250",
    "addr:housenumber":"s / n",
    "addr:postcode":"25250",
    "addr:street":"Av Lleida",
    "iso:country":"ES",
    "sg:address":"Av Lleida, S/n",
    "sg:city":"Bellpuig",
    "sg:orig_category":"Ingenier\u00cda, Centros De Estudios (diversos)",
    "sg:phone":"+34 973 32 00 45",
    "sg:postcode":"25250",
    "sg:province":"Lleida",
    "wof:name":"Ferran Baque Mercedes",
    "wof:placetype":"venue"
},
  "geometry": {"coordinates":[1.0162949562,41.6314888],"type":"Point"}
}