{
  "type": "Feature",
  "properties": {
    "addr:full":"Torre, 20 Torre La Coru\u00f1a 15147",
    "addr:postcode":"15147",
    "addr:street":"Torre;Corun\u0303A",
    "iso:country":"ES",
    "sg:address":"Torre, 20",
    "sg:city":"Torre",
    "sg:orig_category":"Molduras, Junquillos, Listones Y Molduras Perforadas",
    "sg:phone":"+34 981 70 26 08",
    "sg:postcode":"15147",
    "sg:province":"La Coru\u00f1a",
    "wof:name":"Mu\u00f1iz Castro Jesus",
    "wof:placetype":"venue"
},
  "geometry": {"coordinates":[-8.7346086502,43.1884384155],"type":"Point"}
}