{
  "type": "Feature",
  "properties": {
    "addr:full":"Calle de General Saliquet, 2 Madrid Madrid 28044",
    "addr:housenumber":"2",
    "addr:postcode":"28044",
    "addr:street":"Calle De General Saliquet",
    "iso:country":"ES",
    "sg:address":"Calle de General Saliquet, 2",
    "sg:city":"Madrid",
    "sg:orig_category":"Plomeros",
    "sg:phone":"+34 917 06 66 95",
    "sg:postcode":"28044",
    "sg:province":"Madrid",
    "wof:name":"Saez De La Vara Angel",
    "wof:placetype":"venue"
},
  "geometry": {"coordinates":[-3.776088953,40.3767967224],"type":"Point"}
}