{
  "type": "Feature",
  "properties": {
    "addr:full":"Calle de General Pardi\u00d1as, 26 Madrid Madrid 28001",
    "addr:housenumber":"26",
    "addr:postcode":"madrid;28001",
    "addr:street":"Calle De General Pardin\u0303As",
    "iso:country":"ES",
    "sg:address":"Calle de General Pardi\u00d1as, 26",
    "sg:city":"Madrid",
    "sg:orig_category":"M\u00c9dicos: Oftalmolog\u00cda",
    "sg:phone":"+34 915 75 31 25",
    "sg:postcode":"28001",
    "sg:province":"Madrid",
    "wof:name":"Sanchez Ba\u00f1os Mariano",
    "wof:placetype":"venue"
},
  "geometry": {"coordinates":[-3.6784129143,40.4257164001],"type":"Point"}
}