{
  "type": "Feature",
  "properties": {
    "addr:full":"Calle de Puerta Del Mercado, 21 Toro Zamora 49800",
    "addr:housenumber":"21",
    "addr:postcode":"49800",
    "addr:street":"Calle De Puerta Del Mercado",
    "iso:country":"ES",
    "sg:address":"Calle de Puerta Del Mercado, 21",
    "sg:city":"Toro",
    "sg:orig_category":"Farmacias",
    "sg:phone":"+34 980 69 07 20",
    "sg:postcode":"49800",
    "sg:province":"Zamora",
    "wof:name":"Riol Santos Maturina",
    "wof:placetype":"venue"
},
  "geometry": {"coordinates":[-5.3932452202,41.5222244263],"type":"Point"}
}