{
  "type": "Feature",
  "properties": {
    "iso:country":"ES",
    "sg:address":"Calle de Carmen, S/n",
    "sg:city":"Carcabuey",
    "sg:orig_category":"Ingeniero",
    "sg:phone":"+34 957 55 30 45",
    "sg:postcode":"14810",
    "sg:province":"C\u00f3rdoba",
    "wof:name":"Marin Serrano El Lagar S. L.",
    "wof:placetype":"venue"
},
  "geometry": {"coordinates":[-4.2753148079,37.4466209412],"type":"Point"}
}