{
  "type": "Feature",
  "properties": {
    "addr:full":"Pase San Martin, 12 Salas Asturias 33860",
    "addr:housenumber":"12",
    "addr:postcode":"33860",
    "addr:street":"San Martin",
    "iso:country":"ES",
    "sg:address":"Pase San Martin, 12",
    "sg:city":"Salas",
    "sg:classifiers":[
        {
            "category":"Autos & Motor Vehicles",
            "subcategory":"Automobile Sales",
            "type":"Retail Goods"
        }
    ],
    "sg:phone":"+34 985 83 08 02",
    "sg:postcode":"33860",
    "sg:province":"Asturias",
    "wof:name":"Menendez Diaz Francisco",
    "wof:placetype":"venue"
},
  "geometry": {"coordinates":[-6.2543921471,43.4123497009],"type":"Point"}
}