{
  "type": "Feature",
  "properties": {
    "addr:full":"Calle de Torrelaguna, 108 Madrid Madrid 28043",
    "addr:housenumber":"108",
    "addr:postcode":"28043",
    "addr:street":"Calle De Torrelaguna",
    "iso:country":"ES",
    "sg:address":"Calle de Torrelaguna, 108",
    "sg:city":"Madrid",
    "sg:orig_category":"Peluqueros: De Se\u00d1oras",
    "sg:phone":"+34 915 19 19 18",
    "sg:postcode":"28043",
    "sg:province":"Madrid",
    "wof:name":"Dominguez Gonzalez Rosa",
    "wof:placetype":"venue"
},
  "geometry": {"coordinates":[-3.6604590416,40.4549293518],"type":"Point"}
}