{
  "type": "Feature",
  "properties": {
    "addr:full":"Carrer de Lleo Xiii, 34 Barcelona Barcelona 08022",
    "addr:housenumber":"34",
    "addr:postcode":"08022",
    "addr:street":"Carrer De Lleo Xiii",
    "iso:country":"ES",
    "sg:address":"Carrer de Lleo Xiii, 34",
    "sg:city":"Barcelona",
    "sg:orig_category":"Promotores Constructores",
    "sg:phone":"+34 932 53 13 85",
    "sg:postcode":"08022",
    "sg:province":"Barcelona",
    "sg:website":"www.waterair.com",
    "wof:name":"Waterair Iberica S.l.",
    "wof:placetype":"venue"
},
  "geometry": {"coordinates":[2.136380434,41.4140548706],"type":"Point"}
}