{
  "type": "Feature",
  "properties": {
    "addr:full":"Rua Paulino Freire, 32 Vigo Pontevedra 36208",
    "addr:housenumber":"32",
    "addr:postcode":"36208",
    "addr:street":"Rua Paulino Freire",
    "iso:country":"ES",
    "sg:address":"Rua Paulino Freire, 32",
    "sg:city":"Vigo",
    "sg:classifiers":[
        {
            "category":"Personal",
            "subcategory":"Barber",
            "type":"Services"
        }
    ],
    "sg:phone":"+34 986 20 88 12",
    "sg:postcode":"36208",
    "sg:province":"Pontevedra",
    "sg:tags":[
        "caballeros",
        "de",
        "peluqueros"
    ],
    "wof:name":"Fernandez Cabaleiro Angel",
    "wof:placetype":"venue"
},
  "geometry": {"coordinates":[-8.7529497147,42.2225723267],"type":"Point"}
}