{
  "type": "Feature",
  "properties": {
    "iso:country":"ES",
    "sg:address":"Dendaldegi Kalea, 1",
    "sg:city":"Urnieta",
    "sg:orig_category":"Charcuter\u00cdas (al Por Mayor)",
    "sg:phone":"+34 943 55 62 72",
    "sg:postcode":"20130",
    "sg:province":"Guip\u00f9zcoa",
    "wof:name":"Rosco Rosco Carlos",
    "wof:placetype":"venue"
},
  "geometry": {"coordinates":[-1.992759943,43.246295929],"type":"Point"}
}