{
  "type": "Feature",
  "properties": {
    "iso:country":"ES",
    "sg:address":"Ptda Inmediaciones, 138",
    "sg:city":"S. Vicente Raspeig",
    "sg:orig_category":"Autob\u00das (explotaci\u00d3n Y Servicios De)",
    "sg:phone":"+34 902 41 41 21",
    "sg:postcode":"03690",
    "sg:province":"Alicante",
    "wof:name":"Avecar Levante S.l.",
    "wof:placetype":"venue"
},
  "geometry": {"coordinates":[-0.5111595988,38.4068145752],"type":"Point"}
}