{
  "type": "Feature",
  "properties": {
    "iso:country":"ES",
    "sg:address":"Urbanizacion San Jos\u00e9, 18",
    "sg:city":"Benajarafe",
    "sg:orig_category":"Pescader\u00cdas (al Por Mayor)",
    "sg:phone":"+34 952 51 31 54",
    "sg:postcode":"29790",
    "sg:province":"M\u00e1laga",
    "wof:name":"Perez Robles Enrique",
    "wof:placetype":"venue"
},
  "geometry": {"coordinates":[-4.1975722313,36.7176513672],"type":"Point"}
}