{
  "type": "Feature",
  "properties": {
    "addr:full":"Calle de Alfonso Camin, 40 Mieres Asturias 33600",
    "addr:housenumber":"40",
    "addr:postcode":"33600",
    "addr:street":"Calle De Alfonso Camin",
    "iso:country":"ES",
    "sg:address":"Calle de Alfonso Camin, 40",
    "sg:city":"Mieres",
    "sg:orig_category":"Papeler\u00cdas, Librer\u00cdas",
    "sg:phone":"+34 985 46 19 16",
    "sg:postcode":"33600",
    "sg:province":"Asturias",
    "wof:name":"Valin Rouco Edelmiro",
    "wof:placetype":"venue"
},
  "geometry": {"coordinates":[-5.7755589485,43.2481193542],"type":"Point"}
}