{
  "type": "Feature",
  "properties": {
    "iso:country":"ES",
    "sg:address":"Pla\u00c7 De Sant Bartomeu, S/n",
    "sg:city":"Benicarlo",
    "sg:orig_category":"Peluquer\u00cdas, Peluquer\u00cda Mixta",
    "sg:phone":"+34 964 47 28 28",
    "sg:postcode":"12580",
    "sg:province":"Castell\u00f3n",
    "wof:name":"Arnau Caballer Santiago",
    "wof:placetype":"venue"
},
  "geometry": {"coordinates":[0.4030939937,40.4407463074],"type":"Point"}
}