{
  "type": "Feature",
  "properties": {
    "iso:country":"ES",
    "sg:address":"Avgd Dr Pasteur, 45",
    "sg:city":"Igualada",
    "sg:orig_category":"Venta, Instalaci\u00d3n De Cocinas",
    "sg:phone":"+34 938 04 33 51",
    "sg:postcode":"08700",
    "sg:province":"Barcelona",
    "wof:name":"Ferlau S.l.",
    "wof:placetype":"venue"
},
  "geometry": {"coordinates":[1.6092129946,41.5882148743],"type":"Point"}
}