{
  "type": "Feature",
  "properties": {
    "addr:full":"Ctra Pont De Vilomara, 73 Manresa Barcelona 08241",
    "addr:housenumber":"73",
    "addr:postcode":"08241",
    "addr:street":"Ctra Pont De Vilomara",
    "iso:country":"ES",
    "sg:address":"Ctra Pont De Vilomara, 73",
    "sg:city":"Manresa",
    "sg:orig_category":"Peluqueros: De Se\u00d1oras",
    "sg:phone":"+34 938 73 02 28",
    "sg:postcode":"08241",
    "sg:province":"Barcelona",
    "wof:name":"Fargas Perramon Valentin",
    "wof:placetype":"venue"
},
  "geometry": {"coordinates":[1.835819006,41.727355957],"type":"Point"}
}