{
  "type": "Feature",
  "properties": {
    "iso:country":"ES",
    "sg:address":"Pl Catalunya, 10",
    "sg:city":"Mollet Valles",
    "sg:orig_category":"M\u00c9dicos: Estomatolog\u00cda",
    "sg:phone":"+34 935 70 19 50",
    "sg:postcode":"08100",
    "sg:province":"Barcelona",
    "wof:name":"Nordberck Ferraz Ariadna",
    "wof:placetype":"venue"
},
  "geometry": {"coordinates":[2.2132129669,41.5381622314],"type":"Point"}
}