{
  "type": "Feature",
  "properties": {
    "iso:country":"ES",
    "sg:address":"Carrer de Arquebisbe Alemany, 33",
    "sg:city":"Vic",
    "sg:orig_category":"Asesor\u00cda Fiscal Y Jur\u00cddica",
    "sg:phone":"+34 938 83 35 50",
    "sg:postcode":"08500",
    "sg:province":"Barcelona",
    "wof:name":"Ylla Rico Miquel Arcangel",
    "wof:placetype":"venue"
},
  "geometry": {"coordinates":[2.2501609325,41.9317779541],"type":"Point"}
}