{
  "type": "Feature",
  "properties": {
    "iso:country":"ES",
    "sg:address":"Calle de Campomanes, 8",
    "sg:city":"Madrid",
    "sg:orig_category":"Arquitectos",
    "sg:phone":"+34 917 58 27 26",
    "sg:postcode":"28013",
    "sg:province":"Madrid",
    "wof:name":"Armero Exposiciones Y Ediciones S.l",
    "wof:placetype":"venue"
},
  "geometry": {"coordinates":[-3.7092797756,40.4190101624],"type":"Point"}
}