{
  "type": "Feature",
  "properties": {
    "addr:full":"Calle de Ronda Del Ferrocarril, 53 Miranda Ebro Burgos 09200",
    "addr:housenumber":"53",
    "addr:postcode":"09200",
    "addr:street":"Calle De Ronda Del Ferrocarril",
    "iso:country":"ES",
    "sg:address":"Calle de Ronda Del Ferrocarril, 53",
    "sg:city":"Miranda Ebro",
    "sg:orig_category":"Laboratorios Y Cl\u00cdnicas Veterinarias",
    "sg:phone":"+34 947 33 16 33",
    "sg:postcode":"09200",
    "sg:province":"Burgos",
    "wof:name":"Lopez Boutefeu Nuria",
    "wof:placetype":"venue"
},
  "geometry": {"coordinates":[-2.9453029633,42.6889152527],"type":"Point"}
}