{
  "type": "Feature",
  "properties": {
    "iso:country":"ES",
    "sg:address":"Calle de Fortuny, 22",
    "sg:city":"Madrid",
    "sg:orig_category":"Ense\u00d1anza, Formaci\u00d3n Profesional: Aprendizaje",
    "sg:phone":"+34 900 10 10 25",
    "sg:postcode":"28010",
    "sg:province":"Madrid",
    "wof:name":"Institucion Del Defensor Del Pueblo",
    "wof:placetype":"venue"
},
  "geometry": {"coordinates":[-3.6900801659,40.43334198],"type":"Point"}
}