{
  "type": "Feature",
  "properties": {
    "addr:full":"Avda Micaela Aramburu De Mora, 11 Puerto De Santa Maria C\u00e1diz 11500",
    "addr:housenumber":"11",
    "addr:postcode":"11500",
    "addr:street":"Avda Micaela Aramburu De Mora;Ca\u0301Diz",
    "iso:country":"ES",
    "sg:address":"Avda Micaela Aramburu De Mora, 11",
    "sg:city":"Puerto De Santa Maria",
    "sg:orig_category":"Bares, Piano",
    "sg:phone":"+34 956 87 12 62",
    "sg:postcode":"11500",
    "sg:province":"C\u00e1diz",
    "wof:name":"Anelo Lainez Jose Joaquin",
    "wof:placetype":"venue"
},
  "geometry": {"coordinates":[-6.2257122993,36.5961036682],"type":"Point"}
}