{
  "type": "Feature",
  "properties": {
    "iso:country":"ES",
    "sg:address":"Calle de Catral, 13",
    "sg:city":"Alacant",
    "sg:orig_category":"Mec\u00c1nico Del Autom\u00d3vil",
    "sg:phone":"+34 965 10 43 01",
    "sg:postcode":"03007",
    "sg:province":"Alicante",
    "wof:name":"Autocarburacion Franel S.l.",
    "wof:placetype":"venue"
},
  "geometry": {"coordinates":[-0.5114750266,38.3416976929],"type":"Point"}
}