{
  "type": "Feature",
  "properties": {
    "iso:country":"ES",
    "sg:address":"Carr Dr. Carles Pol I Aleu, 38",
    "sg:city":"Sort",
    "sg:orig_category":"Promotores Constructores",
    "sg:phone":"+34 973 62 14 74",
    "sg:postcode":"25560",
    "sg:province":"Lleida",
    "wof:name":"Construsort Del Pallars S.l.",
    "wof:placetype":"venue"
},
  "geometry": {"coordinates":[1.1319500208,42.4144287109],"type":"Point"}
}