{
  "type": "Feature",
  "properties": {
    "iso:country":"ES",
    "sg:address":"Plaz Espa\u00d1a (paseo Del Coso), 3",
    "sg:city":"Lucena",
    "sg:orig_category":"Peluqueros: De Se\u00d1oras",
    "sg:phone":"+34 957 51 44 91",
    "sg:postcode":"14900",
    "sg:province":"C\u00f3rdoba",
    "wof:name":"Valverde Rodriguez Araceli",
    "wof:placetype":"venue"
},
  "geometry": {"coordinates":[-4.4839987755,37.4078483582],"type":"Point"}
}