{
  "type": "Feature",
  "properties": {
    "addr:full":"Playa De Muchavista, Km. 0032,0 El Campello Alicante 03560",
    "addr:postcode":"03560",
    "addr:street":"Playa;Muchavista Km. 0032,0",
    "iso:country":"ES",
    "sg:address":"Playa De Muchavista, Km. 0032,0",
    "sg:city":"El Campello",
    "sg:orig_category":"Centros De Adelgazamiento Y De Est\u00c9tica",
    "sg:phone":"+34 965 65 73 15",
    "sg:postcode":"03560",
    "sg:province":"Alicante",
    "wof:name":"Seven Colours Estilis.muchavista S.l.",
    "wof:placetype":"venue"
},
  "geometry": {"coordinates":[-0.3906340003,38.4271888733],"type":"Point"}
}