{
  "type": "Feature",
  "properties": {
    "iso:country":"ES",
    "sg:address":"Carrer de Guadiana, 69",
    "sg:city":"Montcada Centre",
    "sg:orig_category":"Empresas De Carpinter\u00cda",
    "sg:phone":"+34 935 75 38 59",
    "sg:postcode":"08110",
    "sg:province":"Barcelona",
    "wof:name":"Reguera Marquez Rafael",
    "wof:placetype":"venue"
},
  "geometry": {"coordinates":[2.1885290146,41.4828147888],"type":"Point"}
}