{
  "type": "Feature",
  "properties": {
    "addr:full":"Calle de Geminis, 2 Granada Granada 18015",
    "addr:housenumber":"2",
    "addr:postcode":"18015",
    "addr:street":"Calle De Geminis",
    "iso:country":"ES",
    "sg:address":"Calle de Geminis, 2",
    "sg:city":"Granada",
    "sg:orig_category":"Cl\u00cdnicas Dentales",
    "sg:phone":"+34 958 80 61 74",
    "sg:postcode":"18015",
    "sg:province":"Granada",
    "wof:name":"Clinica Y Promociones Torres S.l.",
    "wof:placetype":"venue"
},
  "geometry": {"coordinates":[-3.6252839565,37.1906967163],"type":"Point"}
}