{
  "type": "Feature",
  "properties": {
    "addr:full":"I. Y Suit, 3 Iru\u00f1a Navarra 31004",
    "addr:postcode":"31004",
    "addr:street":"I.",
    "iso:country":"ES",
    "sg:address":"I. Y Suit, 3",
    "sg:city":"Iru\u00f1a",
    "sg:orig_category":"Peluqueros: De Se\u00d1oras",
    "sg:phone":"+34 948 15 36 12",
    "sg:postcode":"31004",
    "sg:province":"Navarra",
    "wof:name":"Cabrera Duque Purificacion",
    "wof:placetype":"venue"
},
  "geometry": {"coordinates":[-1.6334730387,42.8113021851],"type":"Point"}
}