{
  "type": "Feature",
  "properties": {
    "iso:country":"ES",
    "sg:address":"Carrer de Rubio I Balaguer, 71",
    "sg:city":"Barcelona",
    "sg:orig_category":"Arreglo, Reparaci\u00d3n, Piezas Sueltas De Televisi\u00d3n, V\u00cddeo, Hi",
    "sg:phone":"+34 934 28 42 94",
    "sg:postcode":"08035",
    "sg:province":"Barcelona",
    "wof:name":"Martinez Varela Manuel Alberto",
    "wof:placetype":"venue"
},
  "geometry": {"coordinates":[2.1483550072,41.4324760437],"type":"Point"}
}