{
  "type": "Feature",
  "properties": {
    "addr:full":"Pl Europa (d'), S/n Salou Tarragona 43840",
    "addr:housenumber":"s / n",
    "addr:postcode":"43840",
    "addr:street":"Pl Europa D '",
    "iso:country":"ES",
    "sg:address":"Pl Europa (d'), S/n",
    "sg:city":"Salou",
    "sg:orig_category":"Restaurantes",
    "sg:phone":"+34 977 38 49 16",
    "sg:postcode":"43840",
    "sg:province":"Tarragona",
    "wof:name":"Strudewick  Joana Patricia",
    "wof:placetype":"venue"
},
  "geometry": {"coordinates":[1.1427849531,41.0773239136],"type":"Point"}
}