{
  "type": "Feature",
  "properties": {
    "addr:full":"Valpertuna, S/n Fontellas Navarra 31512",
    "addr:postcode":"31512",
    "addr:street":"Valpertuna S / N",
    "iso:country":"ES",
    "sg:address":"Valpertuna, S/n",
    "sg:city":"Fontellas",
    "sg:orig_category":"Pistas Y Clases De Tenis",
    "sg:phone":"+34 948 82 60 82",
    "sg:postcode":"31512",
    "sg:province":"Navarra",
    "wof:name":"Tenis Club El Cerro S.d.",
    "wof:placetype":"venue"
},
  "geometry": {"coordinates":[-1.5819790363,42.0298309326],"type":"Point"}
}