{
  "type": "Feature",
  "properties": {
    "iso:country":"ES",
    "sg:address":"Rua Robustiano Perez Del Rio, 8",
    "sg:city":"Boiro",
    "sg:orig_category":"Bazares, Art\u00cdculos De Limpieza Y De Cocina (al Por Menor)",
    "sg:phone":"+34 981 84 59 05",
    "sg:postcode":"15930",
    "sg:province":"La Coru\u00f1a",
    "wof:name":"Hermanos Outeiral Miguez S.l.",
    "wof:placetype":"venue"
},
  "geometry": {"coordinates":[-8.8829441071,42.6467895508],"type":"Point"}
}