{
  "type": "Feature",
  "properties": {
    "iso:country":"ES",
    "sg:address":"Calle de Madre De Dios, 11",
    "sg:city":"Valladolid",
    "sg:orig_category":"Cajas Y Embalajes De Cart\u00d3n Y Papel",
    "sg:phone":"+34 983 25 48 30",
    "sg:postcode":"47011",
    "sg:province":"Valladolid",
    "wof:name":"Rodriguez Zazo Paula",
    "wof:placetype":"venue"
},
  "geometry": {"coordinates":[-4.7165131569,41.65858078],"type":"Point"}
}