{
  "type": "Feature",
  "properties": {
    "iso:country":"ES",
    "sg:address":"Calle de Huerta De Hierro, 14",
    "sg:city":"Cordoba",
    "sg:orig_category":"M\u00c9dicos: Anestesiolog\u00cda Y Reanimaci\u00d3n Quir\u00dargica",
    "sg:phone":"+34 957 40 06 52",
    "sg:postcode":"14012",
    "sg:province":"C\u00f3rdoba",
    "wof:name":"Alemany Esteban Fernando",
    "wof:placetype":"venue"
},
  "geometry": {"coordinates":[-4.7960987091,37.9210014343],"type":"Point"}
}