{
  "type": "Feature",
  "properties": {
    "iso:country":"ES",
    "sg:address":"Calle de Cruz De Piedra, 1",
    "sg:city":"Villarrobledo",
    "sg:orig_category":"Cl\u00cdnicas Dentales",
    "sg:phone":"+34 967 14 67 77",
    "sg:postcode":"02600",
    "sg:province":"Albacete",
    "wof:name":"Calidad Dental S.l.",
    "wof:placetype":"venue"
},
  "geometry": {"coordinates":[-2.6022212505,39.2662124634],"type":"Point"}
}