{
  "type": "Feature",
  "properties": {
    "iso:country":"ES",
    "sg:address":"Prol Lino Casimiro Iborra, S/n",
    "sg:city":"Santo\u00f1a",
    "sg:orig_category":"Arquitectos",
    "sg:phone":"+34 942 66 19 24",
    "sg:postcode":"39740",
    "sg:province":"Cantabria",
    "wof:name":"Casta\u00f1o Paltre Alberto",
    "wof:placetype":"venue"
},
  "geometry": {"coordinates":[-3.4542338848,43.4436836243],"type":"Point"}
}