{
  "type": "Feature",
  "properties": {
    "addr:full":"Calle de General Gutierrez Mellado (del), 10 Segovia Segovia 40005",
    "addr:housenumber":"10",
    "addr:postcode":"40005",
    "addr:street":"Calle De General Gutierrez Mellado Del",
    "iso:country":"ES",
    "sg:address":"Calle de General Gutierrez Mellado (del), 10",
    "sg:city":"Segovia",
    "sg:orig_category":"Peluqueros: De Se\u00d1oras",
    "sg:phone":"+34 921 42 21 83",
    "sg:postcode":"40005",
    "sg:province":"Segovia",
    "wof:name":"Gonzalez Arroyo Pilar",
    "wof:placetype":"venue"
},
  "geometry": {"coordinates":[-4.1132760048,40.9402580261],"type":"Point"}
}