{
  "type": "Feature",
  "properties": {
    "addr:full":"Calle de Garcia Escamez, 28 Pto. Rosario Las Palmas 35600",
    "addr:housenumber":"28",
    "addr:postcode":"35600",
    "addr:street":"Calle De Garcia Escamez;Pto. Rosario Las",
    "iso:country":"ES",
    "sg:address":"Calle de Garcia Escamez, 28",
    "sg:city":"Pto. Rosario",
    "sg:classifiers":[
        {
            "category":"Wholesale",
            "subcategory":"Construction Materials",
            "type":"Manufacturing & Wholesale Goods"
        }
    ],
    "sg:phone":"+34 928 53 28 80",
    "sg:postcode":"35600",
    "sg:province":"Las Palmas",
    "sg:tags":[
        "de",
        "embotellado"
    ],
    "wof:name":"Mantenimientos Servicios Fuerteventura S.l.l.",
    "wof:placetype":"venue"
},
  "geometry": {"coordinates":[-13.8614397049,28.4954471588],"type":"Point"}
}