{
  "type": "Feature",
  "properties": {
    "addr:full":"Pg Gran Passeig Ronda, 140 Lleida Lleida 25008",
    "addr:housenumber":"140",
    "addr:postcode":"25008",
    "addr:street":"Pg Gran Passeig Ronda",
    "iso:country":"ES",
    "sg:address":"Pg Gran Passeig Ronda, 140",
    "sg:city":"Lleida",
    "sg:orig_category":"Reposter\u00cdas",
    "sg:phone":"+34 973 23 80 59",
    "sg:postcode":"25008",
    "sg:province":"Lleida",
    "wof:name":"Sant Pancrac Forners S.l.",
    "wof:placetype":"venue"
},
  "geometry": {"coordinates":[0.6199160218,41.6229515076],"type":"Point"}
}