{
  "type": "Feature",
  "properties": {
    "addr:full":"Calle de Gonzalez Vicen, 26 Santa Pola Alicante 03130",
    "addr:housenumber":"26",
    "addr:postcode":"03130",
    "addr:street":"Calle De Gonzalez Vicen",
    "iso:country":"ES",
    "sg:address":"Calle de Gonzalez Vicen, 26",
    "sg:city":"Santa Pola",
    "sg:orig_category":"Arquitectos",
    "sg:phone":"+34 965 41 45 95",
    "sg:postcode":"03130",
    "sg:province":"Alicante",
    "wof:name":"Montoro Sanchez Elisa Maria",
    "wof:placetype":"venue"
},
  "geometry": {"coordinates":[-0.5515390038,38.1898612976],"type":"Point"}
}