{
  "type": "Feature",
  "properties": {
    "iso:country":"ES",
    "sg:address":"Avda Felipe V, 22",
    "sg:city":"Petrer",
    "sg:orig_category":"Adhesivos (fabricaci\u00d3n, Al Por Mayor)",
    "sg:phone":"+34 966 95 03 14",
    "sg:postcode":"03610",
    "sg:province":"Alicante",
    "wof:name":"Representaciones Cintex S.l.",
    "wof:placetype":"venue"
},
  "geometry": {"coordinates":[-0.7781980038,38.4813079834],"type":"Point"}
}