{
  "type": "Feature",
  "properties": {
    "iso:country":"ES",
    "sg:address":"Iglesia, 4",
    "sg:city":"Monovar",
    "sg:orig_category":"Promotores Constructores",
    "sg:phone":"+34 965 47 21 60",
    "sg:postcode":"03640",
    "sg:province":"Alicante",
    "wof:name":"Blaqueal S.l.",
    "wof:placetype":"venue"
},
  "geometry": {"coordinates":[-0.8375920057,38.4366912842],"type":"Point"}
}