{
  "type": "Feature",
  "properties": {
    "addr:full":"Calle de Rio De Oro, 3 Madrid Madrid 28019",
    "addr:housenumber":"3",
    "addr:postcode":"28019",
    "addr:street":"Calle De Rio De Oro",
    "iso:country":"ES",
    "sg:address":"Calle de Rio De Oro, 3",
    "sg:city":"Madrid",
    "sg:orig_category":"Negocio De Materiales De Construcci\u00d3n",
    "sg:phone":"+34 914 71 08 10",
    "sg:postcode":"28019",
    "sg:province":"Madrid",
    "wof:name":"Rodriguez Ortega Sergio",
    "wof:placetype":"venue"
},
  "geometry": {"coordinates":[-3.730066061,40.3889312744],"type":"Point"}
}