{
  "type": "Feature",
  "properties": {
    "iso:country":"ES",
    "sg:address":"Calle de San Francisco, 64",
    "sg:city":"Alacant",
    "sg:orig_category":"Material Y Suministros Para Peluquer\u00cda",
    "sg:phone":"+34 965 20 97 55",
    "sg:postcode":"03001",
    "sg:province":"Alicante",
    "wof:name":"Diaz Ferreiro Martin Jose",
    "wof:placetype":"venue"
},
  "geometry": {"coordinates":[-0.4871250093,38.3435020447],"type":"Point"}
}