{
  "type": "Feature",
  "properties": {
    "iso:country":"ES",
    "sg:address":"Carrer de Raval, 20",
    "sg:city":"Casc Antic",
    "sg:orig_category":"Bazares, Art\u00cdculos De Limpieza Y De Cocina (al Por Menor)",
    "sg:phone":"+34 935 62 42 05",
    "sg:postcode":"08150",
    "sg:province":"Barcelona",
    "wof:name":"Cortes Guasch Maria Dolors",
    "wof:placetype":"venue"
},
  "geometry": {"coordinates":[2.2293000221,41.5678787231],"type":"Point"}
}