{
  "type": "Feature",
  "properties": {
    "iso:country":"ES",
    "sg:address":"Idiazabal Kalea, 38",
    "sg:city":"Urnieta",
    "sg:orig_category":"Arquitectos",
    "sg:phone":"+34 943 33 02 60",
    "sg:postcode":"20130",
    "sg:province":"Guip\u00f9zcoa",
    "wof:name":"Aranburu Tolosa Raul",
    "wof:placetype":"venue"
},
  "geometry": {"coordinates":[-1.9927617311,43.2478141785],"type":"Point"}
}