{
  "type": "Feature",
  "properties": {
    "addr:full":"Calle de Leones, 31 Valencia Valencia 46022",
    "addr:housenumber":"31",
    "addr:postcode":"46022",
    "addr:street":"Calle De Leones",
    "iso:country":"ES",
    "sg:address":"Calle de Leones, 31",
    "sg:city":"Valencia",
    "sg:orig_category":"Perfumer\u00cda Y Cosm\u00c9tica (fabricaci\u00d3n, Al Por Mayor)",
    "sg:phone":"+34 963 56 26 63",
    "sg:postcode":"46022",
    "sg:province":"Valencia",
    "wof:name":"Marti Lozano Joaquin",
    "wof:placetype":"venue"
},
  "geometry": {"coordinates":[-0.3480469882,39.4673156738],"type":"Point"}
}