{
  "type": "Feature",
  "properties": {
    "iso:country":"ES",
    "sg:address":"Calle de Emilio Serra Fernandez De Moratin, 5",
    "sg:city":"Santa Cruz De Tenerife",
    "sg:orig_category":"M\u00c9dicos: Ginecolog\u00cda Y Obstetricia",
    "sg:phone":"+34 922 28 98 66",
    "sg:postcode":"38006",
    "sg:province":"Santa Cruz De Tenerife",
    "wof:name":"Zerolo Davidson Jose Miguel",
    "wof:placetype":"venue"
},
  "geometry": {"coordinates":[-16.260591507,28.4714946747],"type":"Point"}
}