{
  "type": "Feature",
  "properties": {
    "iso:country":"ES",
    "sg:address":"Carrer de Sant Marc, 24",
    "sg:city":"Indioteria",
    "sg:orig_category":"Agencias Y Agentes Comerciales, Representantes",
    "sg:phone":"+34 971 43 22 06",
    "sg:postcode":"07009",
    "sg:province":"Islas Baleares",
    "wof:name":"Majoristes Daudiovisuals Domestics Sl.",
    "wof:placetype":"venue"
},
  "geometry": {"coordinates":[2.6776249409,39.6072845459],"type":"Point"}
}