{
  "type": "Feature",
  "properties": {
    "iso:country":"ES",
    "sg:address":"Avda Europa, S/n",
    "sg:city":"Colindres",
    "sg:orig_category":"Promotores Constructores",
    "sg:phone":"+34 942 67 41 74",
    "sg:postcode":"39750",
    "sg:province":"Cantabria",
    "wof:name":"Construcciones Colindres S.a.",
    "wof:placetype":"venue"
},
  "geometry": {"coordinates":[-3.4531331062,43.3924827576],"type":"Point"}
}