{
  "type": "Feature",
  "properties": {
    "iso:country":"ES",
    "sg:address":"Calle de Medina Y Galnares, S/n",
    "sg:city":"Sevilla",
    "sg:orig_category":"Farmacias",
    "sg:phone":"+34 954 37 62 94",
    "sg:postcode":"41015",
    "sg:province":"Sevilla",
    "wof:name":"Ramirez Li\u00f1an Carlos",
    "wof:placetype":"venue"
},
  "geometry": {"coordinates":[-5.9823040962,37.4238700867],"type":"Point"}
}