{
  "type": "Feature",
  "properties": {
    "iso:country":"ES",
    "sg:address":"Calle de Jamilena, 4",
    "sg:city":"Torredelcampo",
    "sg:orig_category":"Cristaler\u00cdas",
    "sg:phone":"+34 953 41 03 84",
    "sg:postcode":"23640",
    "sg:province":"Ja\u00e9n",
    "wof:name":"Torrecristal Sociedad Cooperativa Andaluza",
    "wof:placetype":"venue"
},
  "geometry": {"coordinates":[-3.8912088871,37.7773513794],"type":"Point"}
}