{
  "type": "Feature",
  "properties": {
    "iso:country":"ES",
    "sg:address":"Calle de Valdelasierra, 6",
    "sg:city":"Madrid",
    "sg:orig_category":"Cubierta (tejado)",
    "sg:phone":"+34 914 73 81 55",
    "sg:postcode":"28005",
    "sg:province":"Madrid",
    "wof:name":"Josdel Constructora S.l.",
    "wof:placetype":"venue"
},
  "geometry": {"coordinates":[-3.7059159279,40.3979644775],"type":"Point"}
}