{
  "type": "Feature",
  "properties": {
    "addr:full":"Plaz Santo Domingo, 3 San Miguel Murcia 30008",
    "addr:housenumber":"3",
    "addr:postcode":"30008",
    "addr:street":"Santo Domingo",
    "iso:country":"ES",
    "sg:address":"Plaz Santo Domingo, 3",
    "sg:city":"San Miguel",
    "sg:orig_category":"Bisuter\u00cda, Joyer\u00cda, Relojer\u00cda (al Por Menor)",
    "sg:phone":"+34 968 23 70 80",
    "sg:postcode":"30008",
    "sg:province":"Murcia",
    "sg:website":"www.tous.es",
    "wof:name":"Tous Joyeros Murcia S.l.",
    "wof:placetype":"venue"
},
  "geometry": {"coordinates":[-1.129554987,37.9875869751],"type":"Point"}
}