{
  "type": "Feature",
  "properties": {
    "iso:country":"ES",
    "sg:address":"Calle de Lucio Del Valle, 5",
    "sg:city":"Madrid",
    "sg:orig_category":"Suministros Y Materiales Industriales",
    "sg:phone":"+34 915 34 43 49",
    "sg:postcode":"28003",
    "sg:province":"Madrid",
    "wof:name":"Petroltecna S.l.",
    "wof:placetype":"venue"
},
  "geometry": {"coordinates":[-3.7076780796,40.4398841858],"type":"Point"}
}