{
  "type": "Feature",
  "properties": {
    "addr:full":"Calle de Alcalde Antonio Codorniu Rodriguez, S/n Arucas Las Palmas 35400",
    "addr:housenumber":"/ n",
    "addr:postcode":"35400",
    "addr:street":"Calle De Alcalde Antonio Codorniu Rodriguez S",
    "iso:country":"ES",
    "sg:address":"Calle de Alcalde Antonio Codorniu Rodriguez, S/n",
    "sg:city":"Arucas",
    "sg:orig_category":"Bazares, Art\u00cdculos De Limpieza Y De Cocina (al Por Menor)",
    "sg:phone":"+34 928 60 53 33",
    "sg:postcode":"35400",
    "sg:province":"Las Palmas",
    "wof:name":"Sosa Santiago Raul",
    "wof:placetype":"venue"
},
  "geometry": {"coordinates":[-15.5290136337,28.1182327271],"type":"Point"}
}