{
  "type": "Feature",
  "properties": {
    "addr:full":"Carr Major, 6 Palamos Girona 17230",
    "addr:housenumber":"6",
    "addr:postcode":"17230",
    "addr:street":"Carr Major",
    "iso:country":"ES",
    "sg:address":"Carr Major, 6",
    "sg:city":"Palamos",
    "sg:orig_category":"Laboratorios Y Trabajos De Fotograf\u00cda, V\u00cddeo Y Cine",
    "sg:phone":"+34 972 31 45 34",
    "sg:postcode":"17230",
    "sg:province":"Girona",
    "wof:name":"Fotografia Serrat S.l.",
    "wof:placetype":"venue"
},
  "geometry": {"coordinates":[3.1295909882,41.8479309082],"type":"Point"}
}