{
  "type": "Feature",
  "properties": {
    "iso:country":"ES",
    "sg:address":"Rua Alcalde Maillata, 2",
    "sg:city":"Olite",
    "sg:orig_category":"Productores Recolectores, Venta Directa De Vinos",
    "sg:phone":"+34 948 74 00 48",
    "sg:postcode":"31390",
    "sg:province":"Navarra",
    "sg:website":"www.bodegasochoa.com",
    "wof:name":"Bodegas Ochoa S. A.",
    "wof:placetype":"venue"
},
  "geometry": {"coordinates":[-1.6495549679,42.4779129028],"type":"Point"}
}