{
  "type": "Feature",
  "properties": {
    "addr:full":"Carrer de Joan Guell, 152 Barcelona Barcelona 08028",
    "addr:housenumber":"152",
    "addr:postcode":"08028",
    "addr:street":"Carrer De Joan Guell",
    "iso:country":"ES",
    "sg:address":"Carrer de Joan Guell, 152",
    "sg:city":"Barcelona",
    "sg:orig_category":"Suministros Y Materiales Industriales",
    "sg:phone":"+34 934 11 06 79",
    "sg:postcode":"08028",
    "sg:province":"Barcelona",
    "wof:name":"Vallespir 195 S.l.",
    "wof:placetype":"venue"
},
  "geometry": {"coordinates":[2.1314909458,41.3832168579],"type":"Point"}
}