{
  "type": "Feature",
  "properties": {
    "iso:country":"ES",
    "sg:address":"Calle de Naval La, 215",
    "sg:city":"Palmas De Gran Canaria",
    "sg:orig_category":"Bazares, Art\u00cdculos De Limpieza Y De Cocina (al Por Menor)",
    "sg:phone":"+34 928 47 04 34",
    "sg:postcode":"35008",
    "sg:province":"Las Palmas",
    "wof:name":"Kim Yang Yong Min",
    "wof:placetype":"venue"
},
  "geometry": {"coordinates":[-15.4214782715,28.1506023407],"type":"Point"}
}