{
  "type": "Feature",
  "properties": {
    "addr:full":"Ctra. Caceres-merida, Km. 0604,1 Aljucen Badajoz 06894",
    "addr:postcode":"06894",
    "addr:street":"Ctra. Caceres-Merida Km. 0604,1",
    "iso:country":"ES",
    "sg:address":"Ctra. Caceres-merida, Km. 0604,1",
    "sg:city":"Aljucen",
    "sg:orig_category":"Distribuci\u00d3n De Petr\u00d3leo Y Derivados",
    "sg:phone":"+34 924 12 31 42",
    "sg:postcode":"06894",
    "sg:province":"Badajoz",
    "wof:name":"Erg Gestion Iberica S.l.",
    "wof:placetype":"venue"
},
  "geometry": {"coordinates":[-6.3304991722,39.0451126099],"type":"Point"}
}