{
  "type": "Feature",
  "properties": {
    "addr:full":"Calle de Barcelona, 8 Caravaca Cruz Murcia 30400",
    "addr:housenumber":"8",
    "addr:postcode":"30400",
    "addr:street":"Calle De Barcelona",
    "iso:country":"ES",
    "sg:address":"Calle de Barcelona, 8",
    "sg:city":"Caravaca Cruz",
    "sg:orig_category":"Confiter\u00cdas, Chocolater\u00cdas (al Por Menor)",
    "sg:phone":"+34 968 70 12 40",
    "sg:postcode":"30400",
    "sg:province":"Murcia",
    "wof:name":"Obleas Caravaca De La Cruz S.l.",
    "wof:placetype":"venue"
},
  "geometry": {"coordinates":[-1.8649067879,38.1030464172],"type":"Point"}
}