{
  "type": "Feature",
  "properties": {
    "addr:full":"Calle de Azalea (de La), 1 Alcobendas Madrid 28109",
    "addr:postcode":"28109",
    "addr:street":"Calle De Azalea De La 1",
    "iso:country":"ES",
    "sg:address":"Calle de Azalea (de La), 1",
    "sg:city":"Alcobendas",
    "sg:orig_category":"Promotores Constructores",
    "sg:phone":"+34 916 50 64 44",
    "sg:postcode":"28109",
    "sg:province":"Madrid",
    "wof:name":"Urbanizadora Residencial S.a.",
    "wof:placetype":"venue"
},
  "geometry": {"coordinates":[-3.6503260136,40.5188751221],"type":"Point"}
}