{
  "type": "Feature",
  "properties": {
    "addr:full":"Las Moreras, 11 Salteras Sevilla 41909",
    "addr:housenumber":"11",
    "addr:postcode":"41909",
    "addr:street":"Las Moreras",
    "iso:country":"ES",
    "sg:address":"Las Moreras, 11",
    "sg:city":"Salteras",
    "sg:orig_category":"Supermercados Y Hipermercados",
    "sg:phone":"+34 955 70 83 64",
    "sg:postcode":"41909",
    "sg:province":"Sevilla",
    "wof:name":"Supermercados Halsuper S.l.",
    "wof:placetype":"venue"
},
  "geometry": {"coordinates":[-6.108809948,37.4189682007],"type":"Point"}
}