{
  "type": "Feature",
  "properties": {
    "addr:full":"Calle de Trujillo, 18 Peraleda San Roman C\u00e1ceres 10334",
    "addr:housenumber":"18",
    "addr:postcode":"10334",
    "addr:street":"Calle De Trujillo;San;Ca\u0301Ceres",
    "iso:country":"ES",
    "sg:address":"Calle de Trujillo, 18",
    "sg:city":"Peraleda San Roman",
    "sg:orig_category":"Delegados, Agentes De Tr\u00c1nsito, Auxiliares De Transporte Internacional",
    "sg:phone":"+34 927 55 31 89",
    "sg:postcode":"10334",
    "sg:province":"C\u00e1ceres",
    "wof:name":"Lopez Santos Domingo",
    "wof:placetype":"venue"
},
  "geometry": {"coordinates":[-5.3884592056,39.740146637],"type":"Point"}
}