{
  "type": "Feature",
  "properties": {
    "iso:country":"ES",
    "sg:address":"Carrer de Burgos, 42",
    "sg:city":"S. Feliu Guixols",
    "sg:orig_category":"Plomeros",
    "sg:phone":"+34 972 82 24 02",
    "sg:postcode":"17220",
    "sg:province":"Girona",
    "wof:name":"Murcia Segura Manuel",
    "wof:placetype":"venue"
},
  "geometry": {"coordinates":[3.026417017,41.7896270752],"type":"Point"}
}