{
  "type": "Feature",
  "properties": {
    "addr:full":"Calle de Badajoz, 11 Alcorcon Madrid 28921",
    "addr:housenumber":"11",
    "addr:postcode":"28921",
    "addr:street":"Calle De Badajoz",
    "iso:country":"ES",
    "sg:address":"Calle de Badajoz, 11",
    "sg:city":"Alcorcon",
    "sg:orig_category":"Molduras, Junquillos, Listones Y Molduras Perforadas",
    "sg:phone":"+34 916 44 43 39",
    "sg:postcode":"28921",
    "sg:province":"Madrid",
    "wof:name":"Bar Borjas S.l.",
    "wof:placetype":"venue"
},
  "geometry": {"coordinates":[-3.8311390877,40.3462486267],"type":"Point"}
}