{
  "type": "Feature",
  "properties": {
    "addr:full":"Pol. Ind. El Pinatar, S/n Caldes Montbui Barcelona 08140",
    "addr:housenumber":"s / n",
    "addr:postcode":"08140",
    "addr:street":"Montbui Barcelona",
    "iso:country":"ES",
    "sg:address":"Pol. Ind. El Pinatar, S/n",
    "sg:city":"Caldes Montbui",
    "sg:orig_category":"Limpieza Industrial",
    "sg:phone":"+34 938 65 08 73",
    "sg:postcode":"08140",
    "sg:province":"Barcelona",
    "wof:name":"Lavanderia Camps S.a.",
    "wof:placetype":"venue"
},
  "geometry": {"coordinates":[2.1686599255,41.631111145],"type":"Point"}
}