{
  "type": "Feature",
  "properties": {
    "addr:full":"Calle de Rafael Alberti, 2 Tomares Sevilla 41940",
    "addr:housenumber":"2",
    "addr:postcode":"41940",
    "addr:street":"Calle De Rafael Alberti",
    "iso:country":"ES",
    "sg:address":"Calle de Rafael Alberti, 2",
    "sg:city":"Tomares",
    "sg:orig_category":"Inmobiliaria (agencias)",
    "sg:phone":"+34 954 15 18 27",
    "sg:postcode":"41940",
    "sg:province":"Sevilla",
    "wof:name":"Torres Peral Joaquin Jose",
    "wof:placetype":"venue"
},
  "geometry": {"coordinates":[-6.0412039757,37.3687095642],"type":"Point"}
}