{
  "type": "Feature",
  "properties": {
    "iso:country":"ES",
    "sg:address":"Calle de Muyay, 130",
    "sg:city":"Arrecife",
    "sg:orig_category":"Florister\u00cdas",
    "sg:phone":"+34 928 80 74 43",
    "sg:postcode":"35500",
    "sg:province":"Las Palmas",
    "wof:name":"Guadalupe Toledo Maria Luisa",
    "wof:placetype":"venue"
},
  "geometry": {"coordinates":[-13.5486888885,28.9802703857],"type":"Point"}
}