{
  "type": "Feature",
  "properties": {
    "iso:country":"ES",
    "sg:address":"Calle de Caucho, 39",
    "sg:city":"Torrejon Ardoz",
    "sg:orig_category":"Pintura Y Barniz (al Por Menor)",
    "sg:phone":"+34 916 56 03 64",
    "sg:postcode":"28850",
    "sg:province":"Madrid",
    "sg:website":"www.lolacar.com",
    "wof:name":"Talleres Lolacar S.l.",
    "wof:placetype":"venue"
},
  "geometry": {"coordinates":[-3.4546020031,40.4516372681],"type":"Point"}
}