{
  "type": "Feature",
  "properties": {
    "addr:full":"Plaz Cedro Del, 11 Donostia-san Sebastian Guip\u00f9zcoa 20016",
    "addr:housenumber":"11",
    "addr:postcode":"20016",
    "iso:country":"ES",
    "sg:address":"Plaz Cedro Del, 11",
    "sg:city":"Donostia-san Sebastian",
    "sg:orig_category":"Ingenier\u00cda, Centros De Estudios (diversos)",
    "sg:phone":"+34 943 39 49 71",
    "sg:postcode":"20016",
    "sg:province":"Guip\u00f9zcoa",
    "wof:name":"Hernandez Aina Javier",
    "wof:placetype":"venue"
},
  "geometry": {"coordinates":[-1.942620039,43.3229598999],"type":"Point"}
}