{
  "type": "Feature",
  "properties": {
    "iso:country":"ES",
    "sg:address":"Calle de Mayor, 34",
    "sg:city":"Riba-roja Turia",
    "sg:orig_category":"Estancos",
    "sg:phone":"+34 962 77 09 63",
    "sg:postcode":"46190",
    "sg:province":"Valencia",
    "wof:name":"Bodi Collo Concepcion",
    "wof:placetype":"venue"
},
  "geometry": {"coordinates":[-0.5698940158,39.5458450317],"type":"Point"}
}