{
  "type": "Feature",
  "properties": {
    "addr:full":"Pg Garcia I Faria, 69 Barcelona Barcelona 08005",
    "addr:housenumber":"69",
    "addr:postcode":"08005",
    "addr:street":"Pg Garcia I Faria",
    "iso:country":"ES",
    "sg:address":"Pg Garcia I Faria, 69",
    "sg:city":"Barcelona",
    "sg:orig_category":"Inmobiliaria (agencias)",
    "sg:phone":"+34 933 07 31 96",
    "sg:postcode":"08005",
    "sg:province":"Barcelona",
    "wof:name":"L'oncle D'america S.l.",
    "wof:placetype":"venue"
},
  "geometry": {"coordinates":[2.2103800774,41.4010009766],"type":"Point"}
}