{
  "type": "Feature",
  "properties": {
    "addr:full":"Psje Moron S Fernando, 25 Puebla Cazalla Sevilla 41540",
    "addr:housenumber":"25",
    "addr:postcode":"41540",
    "addr:street":"Psje Moron S Fernando",
    "iso:country":"ES",
    "sg:address":"Psje Moron S Fernando, 25",
    "sg:city":"Puebla Cazalla",
    "sg:orig_category":"Asesor\u00cda De Formaci\u00d3n Y Gesti\u00d3n De Personal",
    "sg:phone":"+34 955 84 38 73",
    "sg:postcode":"41540",
    "sg:province":"Sevilla",
    "wof:name":"Cardenas Cabello Consuelo",
    "wof:placetype":"venue"
},
  "geometry": {"coordinates":[-5.3132190704,37.2229957581],"type":"Point"}
}