{
  "type": "Feature",
  "properties": {
    "iso:country":"ES",
    "sg:address":"Calle de Union (la), 40",
    "sg:city":"Andorra",
    "sg:orig_category":"Lencer\u00cda Femenina, Corseter\u00cda, Trajes De Ba\u00d1o (al Por Menor)",
    "sg:phone":"+34 978 84 37 07",
    "sg:postcode":"44500",
    "sg:province":"Teruel",
    "wof:name":"Bersabe Lahoz Maria Luisa",
    "wof:placetype":"venue"
},
  "geometry": {"coordinates":[-0.4496180117,40.977645874],"type":"Point"}
}