{
  "type": "Feature",
  "properties": {
    "addr:full":"Pl. Castillo, 4 Montemayor Rio Salamanca 37727",
    "addr:housenumber":"4",
    "addr:postcode":"37727",
    "addr:street":"Pl. Castillo",
    "iso:country":"ES",
    "sg:address":"Pl. Castillo, 4",
    "sg:city":"Montemayor Rio",
    "sg:orig_category":"Limpieza Industrial",
    "sg:phone":"+34 923 43 10 78",
    "sg:postcode":"37727",
    "sg:province":"Salamanca",
    "wof:name":"Albaicin S.cop.l.",
    "wof:placetype":"venue"
},
  "geometry": {"coordinates":[-5.8928775787,40.3485794067],"type":"Point"}
}