{
  "type": "Feature",
  "properties": {
    "iso:country":"ES",
    "sg:address":"Rbla Josep Tarradellas, 5",
    "sg:city":"Castelldefels",
    "sg:orig_category":"Agencias De Viajes",
    "sg:phone":"+34 936 34 24 80",
    "sg:postcode":"08860",
    "sg:province":"Barcelona",
    "wof:name":"Avantravel Viatges S.l.",
    "wof:placetype":"venue"
},
  "geometry": {"coordinates":[2.0136129856,41.3150787354],"type":"Point"}
}