{
  "type": "Feature",
  "properties": {
    "iso:country":"ES",
    "sg:address":"Calle de Sauce, 39",
    "sg:city":"Torrejon Ardoz",
    "sg:orig_category":"V\u00c1lvulas",
    "sg:phone":"+34 916 75 53 07",
    "sg:postcode":"28850",
    "sg:province":"Madrid",
    "wof:name":"Sigeval S. A.",
    "wof:placetype":"venue"
},
  "geometry": {"coordinates":[-3.4557509422,40.4527015686],"type":"Point"}
}