{
  "type": "Feature",
  "properties": {
    "iso:country":"ES",
    "sg:address":"Calle de Gascon De Gotor, 27",
    "sg:city":"Zaragoza",
    "sg:orig_category":"Molduras, Junquillos, Listones Y Molduras Perforadas",
    "sg:phone":"+34 976 38 18 79",
    "sg:postcode":"50006",
    "sg:province":"Zaragoza",
    "wof:name":"Tong  Xiu Luan",
    "wof:placetype":"venue"
},
  "geometry": {"coordinates":[-0.8891000152,41.6383781433],"type":"Point"}
}