{
  "type": "Feature",
  "properties": {
    "addr:full":"Plaz San Juan De Los Gascos, S/n Toro Zamora 49800",
    "addr:housenumber":"s / n",
    "addr:postcode":"49800",
    "addr:street":"Plaz",
    "iso:country":"ES",
    "sg:address":"Plaz San Juan De Los Gascos, S/n",
    "sg:city":"Toro",
    "sg:orig_category":"Carnicer\u00cdas, Carnicer\u00cdas",
    "sg:phone":"+34 980 69 02 78",
    "sg:postcode":"49800",
    "sg:province":"Zamora",
    "wof:name":"Sanchez Martin Pedro",
    "wof:placetype":"venue"
},
  "geometry": {"coordinates":[-5.3963241577,41.5224761963],"type":"Point"}
}