{
  "type": "Feature",
  "properties": {
    "iso:country":"ES",
    "sg:address":"M Rguez Pi\u00f1ero, 1",
    "sg:city":"Sevilla",
    "sg:orig_category":"Abogados",
    "sg:phone":"+34 954 41 19 97",
    "sg:postcode":"41013",
    "sg:province":"Sevilla",
    "wof:name":"Fernandez Rebollo Simon",
    "wof:placetype":"venue"
},
  "geometry": {"coordinates":[-5.9789037704,37.3766555786],"type":"Point"}
}