{
  "type": "Feature",
  "properties": {
    "addr:full":"Calle de Alhondiga, 35 Granada Granada 18001",
    "addr:housenumber":"35",
    "addr:postcode":"18001",
    "addr:street":"Calle De Alhondiga",
    "iso:country":"ES",
    "sg:address":"Calle de Alhondiga, 35",
    "sg:city":"Granada",
    "sg:orig_category":"Farmacias",
    "sg:phone":"+34 958 25 74 61",
    "sg:postcode":"18001",
    "sg:province":"Granada",
    "wof:name":"Vallecillos Jimenez Jose",
    "wof:placetype":"venue"
},
  "geometry": {"coordinates":[-3.6018788815,37.1754760742],"type":"Point"}
}