{
  "type": "Feature",
  "properties": {
    "iso:country":"ES",
    "sg:address":"Urb. El Puerto, S/n",
    "sg:city":"Fregenal Sierra",
    "sg:orig_category":"Artes Gr\u00c1ficas, Artes Pl\u00c1sticas (curso)",
    "sg:phone":"+34 924 70 10 43",
    "sg:postcode":"06340",
    "sg:province":"Badajoz",
    "wof:name":"Graficolor Fregenal Scl",
    "wof:placetype":"venue"
},
  "geometry": {"coordinates":[-6.9702835083,38.8785972595],"type":"Point"}
}