{
  "type": "Feature",
  "properties": {
    "addr:full":"Carrer de Collblanc, 86 Barcelona Barcelona 08028",
    "addr:housenumber":"86",
    "addr:postcode":"08028",
    "addr:street":"Carrer De Collblanc",
    "iso:country":"ES",
    "sg:address":"Carrer de Collblanc, 86",
    "sg:city":"Barcelona",
    "sg:orig_category":"Internados & Ense\u00d1anza Privada",
    "sg:phone":"+34 934 49 05 70",
    "sg:postcode":"08028",
    "sg:province":"Barcelona",
    "wof:name":"Sant Ramon Nonat-sagrat Cor",
    "wof:placetype":"venue"
},
  "geometry": {"coordinates":[2.1162040234,41.3759689331],"type":"Point"}
}