{
  "type": "Feature",
  "properties": {
    "addr:full":"Avda Calleja Del Potro, S/n Guadarrama Madrid 28440",
    "addr:housenumber":"s / n",
    "addr:postcode":"28440",
    "addr:street":"Avda Calleja Del Potro",
    "iso:country":"ES",
    "sg:address":"Avda Calleja Del Potro, S/n",
    "sg:city":"Guadarrama",
    "sg:orig_category":"Productores Recolectores, Venta Directa De Vinos",
    "sg:phone":"+34 918 54 08 68",
    "sg:postcode":"28440",
    "sg:province":"Madrid",
    "wof:name":"La Taurina Del Norte S.a.",
    "wof:placetype":"venue"
},
  "geometry": {"coordinates":[-4.0891890526,40.6723594666],"type":"Point"}
}