{
  "type": "Feature",
  "properties": {
    "iso:country":"ES",
    "sg:address":"Cjon. Del Reposo, 3",
    "sg:city":"S. Roque",
    "sg:orig_category":"Promotores Constructores",
    "sg:phone":"+34 956 69 83 99",
    "sg:postcode":"11360",
    "sg:province":"C\u00e1diz",
    "wof:name":"Contrat Ingenieria Y Obras S.a.",
    "wof:placetype":"venue"
},
  "geometry": {"coordinates":[-5.3897438049,36.209690094],"type":"Point"}
}