{
  "type": "Feature",
  "properties": {
    "addr:full":"Carrer de Palomar, 40 Barcelona Barcelona 08030",
    "addr:housenumber":"40",
    "addr:postcode":"08030",
    "addr:street":"Carrer De Palomar",
    "iso:country":"ES",
    "sg:address":"Carrer de Palomar, 40",
    "sg:city":"Barcelona",
    "sg:orig_category":"Material Y Suministros Para Dentistas, Cirujanos",
    "sg:phone":"+34 932 74 13 64",
    "sg:postcode":"08030",
    "sg:province":"Barcelona",
    "wof:name":"Royal Sulgerins S.l.",
    "wof:placetype":"venue"
},
  "geometry": {"coordinates":[2.1905140877,41.4420166016],"type":"Point"}
}