{
  "type": "Feature",
  "properties": {
    "addr:full":"Carrer de Candela, 19 Valls Tarragona 43800",
    "addr:housenumber":"19",
    "addr:postcode":"43800",
    "addr:street":"Carrer De Candela",
    "iso:country":"ES",
    "sg:address":"Carrer de Candela, 19",
    "sg:city":"Valls",
    "sg:orig_category":"Electricidad: Instaladores",
    "sg:phone":"+34 977 61 47 52",
    "sg:postcode":"43800",
    "sg:province":"Tarragona",
    "wof:name":"Inspro Scp",
    "wof:placetype":"venue"
},
  "geometry": {"coordinates":[1.246006012,41.283416748],"type":"Point"}
}