{
  "type": "Feature",
  "properties": {
    "addr:full":"Pl Corona, 8 Granollers Barcelona 08400",
    "addr:housenumber":"8",
    "addr:postcode":"08400",
    "addr:street":"Pl Corona",
    "iso:country":"ES",
    "sg:address":"Pl Corona, 8",
    "sg:city":"Granollers",
    "sg:orig_category":"Consultor\u00cdas Diversas",
    "sg:phone":"+34 938 70 37 50",
    "sg:postcode":"08400",
    "sg:province":"Barcelona",
    "wof:name":"Font Enginyeria I Gestio S.l.",
    "wof:placetype":"venue"
},
  "geometry": {"coordinates":[2.2887299061,41.6059188843],"type":"Point"}
}