{
  "type": "Feature",
  "properties": {
    "addr:full":"Camino De Santiago, 6 Pte Villarente Le\u00f3n 24226",
    "addr:housenumber":"6",
    "addr:postcode":"24226",
    "addr:street":"Camino De Santiago;Pte Villarente Leo\u0301N",
    "iso:country":"ES",
    "sg:address":"Camino De Santiago, 6",
    "sg:city":"Pte Villarente",
    "sg:orig_category":"Quincaller\u00cda (al Por Menor)",
    "sg:phone":"+34 987 31 23 16",
    "sg:postcode":"24226",
    "sg:province":"Le\u00f3n",
    "wof:name":"Alvarez Mu\u00f1iz Lucinio",
    "wof:placetype":"venue"
},
  "geometry": {"coordinates":[-5.4601693153,42.5463142395],"type":"Point"}
}