{
  "type": "Feature",
  "properties": {
    "iso:country":"ES",
    "sg:address":"Calle de Condesa Mencia, 159",
    "sg:city":"Burgos",
    "sg:orig_category":"Farmacias",
    "sg:phone":"+34 947 24 43 79",
    "sg:postcode":"09006",
    "sg:province":"Burgos",
    "wof:name":"Castillejo Barron Maria Lourdes",
    "wof:placetype":"venue"
},
  "geometry": {"coordinates":[-3.6757981777,42.3615074158],"type":"Point"}
}