{
  "type": "Feature",
  "properties": {
    "addr:full":"Avda Castilla (de), 32 Poligono De San Fernando De Henares Madrid 28830",
    "addr:housenumber":"32",
    "addr:postcode":"28830",
    "addr:street":"Avda Castilla De",
    "iso:country":"ES",
    "sg:address":"Avda Castilla (de), 32",
    "sg:city":"Poligono De San Fernando De Henares",
    "sg:orig_category":"Electricidad: Instaladores",
    "sg:phone":"+34 916 76 40 87",
    "sg:postcode":"28830",
    "sg:province":"Madrid",
    "wof:name":"Talleres Electricos Jofran C. B.",
    "wof:placetype":"venue"
},
  "geometry": {"coordinates":[-3.4944779873,40.4541397095],"type":"Point"}
}