{
  "type": "Feature",
  "properties": {
    "iso:country":"ES",
    "sg:address":"Avda Rafael Puig Llivina, S/n",
    "sg:city":"Playa Americas",
    "sg:orig_category":"Bazares, Art\u00cdculos De Limpieza Y De Cocina (al Por Menor)",
    "sg:phone":"+34 922 75 35 99",
    "sg:postcode":"38660",
    "sg:province":"Santa Cruz De Tenerife",
    "wof:name":"K.r.h.k. Maya S.a.",
    "wof:placetype":"venue"
},
  "geometry": {"coordinates":[-16.7317714691,28.0760765076],"type":"Point"}
}