{
  "type": "Feature",
  "properties": {
    "addr:full":"Os Gozos(sta. Marta Moreiras), S/n Pereiro De Aguiar Ourense 32710",
    "addr:housenumber":"s / n",
    "addr:postcode":"32710",
    "iso:country":"ES",
    "sg:address":"Os Gozos(sta. Marta Moreiras), S/n",
    "sg:city":"Pereiro De Aguiar",
    "sg:orig_category":"Asilos De Ancianos. Centros Privados",
    "sg:phone":"+34 988 25 95 54",
    "sg:postcode":"32710",
    "sg:province":"Ourense",
    "wof:name":"Fundacion San Rosendo",
    "wof:placetype":"venue"
},
  "geometry": {"coordinates":[-7.8072919846,42.3483390808],"type":"Point"}
}