{
  "type": "Feature",
  "properties": {
    "iso:country":"ES",
    "sg:address":"Calle de Estacion (la), 1",
    "sg:city":"Cuevas Almanzora",
    "sg:orig_category":"Molduras, Junquillos, Listones Y Molduras Perforadas",
    "sg:phone":"+34 950 45 68 00",
    "sg:postcode":"04610",
    "sg:province":"Almer\u00eda",
    "wof:name":"Perales Larios Antonia",
    "wof:placetype":"venue"
},
  "geometry": {"coordinates":[-1.8816330433,37.2962532043],"type":"Point"}
}