{
  "type": "Feature",
  "properties": {
    "addr:full":"Calle de I(campollano), 2 Albacete Albacete 02006",
    "addr:housenumber":"2",
    "addr:postcode":"02006",
    "addr:street":"Calle De;Campollano",
    "iso:country":"ES",
    "sg:address":"Calle de I(campollano), 2",
    "sg:city":"Albacete",
    "sg:orig_category":"Agencias Y Agentes Comerciales, Representantes",
    "sg:phone":"+34 967 21 96 49",
    "sg:postcode":"02006",
    "sg:province":"Albacete",
    "wof:name":"Jose Bernad S. L.",
    "wof:placetype":"venue"
},
  "geometry": {"coordinates":[-1.8816790581,39.0102081299],"type":"Point"}
}