{
  "type": "Feature",
  "properties": {
    "iso:country":"ES",
    "sg:address":"Pol. Ind. Les Coromines, S/n",
    "sg:city":"S. Joan Fonts",
    "sg:orig_category":"Artes Gr\u00c1ficas, Artes Pl\u00c1sticas (curso)",
    "sg:phone":"+34 972 29 30 10",
    "sg:postcode":"17857",
    "sg:province":"Girona",
    "wof:name":"Aubert Imprimeix S.l.",
    "wof:placetype":"venue"
},
  "geometry": {"coordinates":[2.8236999512,41.9817962646],"type":"Point"}
}