{
  "type": "Feature",
  "properties": {
    "addr:full":"Calle de Alfonso Xii, 25 Mostoles Madrid 28934",
    "addr:housenumber":"25",
    "addr:postcode":"28934",
    "addr:street":"Calle De Alfonso Xii",
    "iso:country":"ES",
    "sg:address":"Calle de Alfonso Xii, 25",
    "sg:city":"Mostoles",
    "sg:orig_category":"Talleres De Corte Y Confecci\u00d3n",
    "sg:phone":"+34 916 13 95 92",
    "sg:postcode":"28934",
    "sg:province":"Madrid",
    "wof:name":"Confecciones M.gonzalo S.l",
    "wof:placetype":"venue"
},
  "geometry": {"coordinates":[-3.8748383522,40.3180198669],"type":"Point"}
}