{
  "type": "Feature",
  "properties": {
    "addr:full":"Avda. Carlos Iii, 8 Parador Hortichuelas Almer\u00eda 04720",
    "addr:housenumber":"8",
    "addr:postcode":"04720",
    "addr:street":"Avda. Carlos Iii;Almeri\u0301A",
    "iso:country":"ES",
    "sg:address":"Avda. Carlos Iii, 8",
    "sg:city":"Parador Hortichuelas",
    "sg:orig_category":"M\u00c9dicos: An\u00c1lisis Cl\u00cdnicos",
    "sg:phone":"+34 950 34 19 30",
    "sg:postcode":"04720",
    "sg:province":"Almer\u00eda",
    "wof:name":"Estrella Estrella Carmen",
    "wof:placetype":"venue"
},
  "geometry": {"coordinates":[-2.5991489887,36.80859375],"type":"Point"}
}