{
  "type": "Feature",
  "properties": {
    "iso:country":"ES",
    "sg:address":"Carrer de Union, 2",
    "sg:city":"Terrassa",
    "sg:orig_category":"Promotores Constructores",
    "sg:phone":"+34 937 89 36 02",
    "sg:postcode":"08221",
    "sg:province":"Barcelona",
    "wof:name":"Inmobiliaria Blau S.a.",
    "wof:placetype":"venue"
},
  "geometry": {"coordinates":[2.0092899799,41.5629653931],"type":"Point"}
}