{
  "type": "Feature",
  "properties": {
    "addr:full":"Luga Diseminado La Corte, S/n Antigua Las Palmas 35630",
    "addr:postcode":"35630",
    "addr:street":"Luga Diseminado La Corte S / N Antigua Las",
    "iso:country":"ES",
    "sg:address":"Luga Diseminado La Corte, S/n",
    "sg:city":"Antigua",
    "sg:orig_category":"Electrodom\u00c9sticos (al Por Menor)",
    "sg:phone":"+34 928 87 85 23",
    "sg:postcode":"35630",
    "sg:province":"Las Palmas",
    "wof:name":"Acosta Gutierrez Esteban",
    "wof:placetype":"venue"
},
  "geometry": {"coordinates":[-13.9376020432,28.3937339783],"type":"Point"}
}