{
  "type": "Feature",
  "properties": {
    "addr:full":"Ctra Ripollet, 58 Mas Rampinyo Barcelona 08110",
    "addr:housenumber":"58",
    "addr:postcode":"08110",
    "addr:street":"Ctra Ripollet",
    "iso:country":"ES",
    "sg:address":"Ctra Ripollet, 58",
    "sg:city":"Mas Rampinyo",
    "sg:orig_category":"Mec\u00c1nico Del Autom\u00d3vil",
    "sg:phone":"+34 935 75 02 75",
    "sg:postcode":"08110",
    "sg:province":"Barcelona",
    "wof:name":"Exposito Fontanillas Juan",
    "wof:placetype":"venue"
},
  "geometry": {"coordinates":[2.1814110279,41.4914588928],"type":"Point"}
}