{
  "type": "Feature",
  "properties": {
    "iso:country":"ES",
    "sg:address":"Rua Valdoncel, 74",
    "sg:city":"Betanzos",
    "sg:orig_category":"Electricidad: Equipos Industriales, Componentes (fabricaci\u00d3n)",
    "sg:phone":"+34 981 77 34 91",
    "sg:postcode":"15300",
    "sg:province":"La Coru\u00f1a",
    "wof:name":"Fernandez Presedo Maria Del Pilar",
    "wof:placetype":"venue"
},
  "geometry": {"coordinates":[-8.2130041122,43.2819595337],"type":"Point"}
}