{
  "type": "Feature",
  "properties": {
    "addr:full":"Calle de Alonso De Celada, 5 Badajoz Badajoz 06002",
    "addr:housenumber":"5",
    "addr:postcode":"06002",
    "addr:street":"Calle De Alonso De Celada",
    "iso:country":"ES",
    "sg:address":"Calle de Alonso De Celada, 5",
    "sg:city":"Badajoz",
    "sg:orig_category":"Peluquer\u00cdas, Peluquer\u00cda Mixta",
    "sg:phone":"+34 924 22 05 23",
    "sg:postcode":"06002",
    "sg:province":"Badajoz",
    "wof:name":"Fabian Tejeiro Virginia",
    "wof:placetype":"venue"
},
  "geometry": {"coordinates":[-6.9728245735,38.8754081726],"type":"Point"}
}