{
  "type": "Feature",
  "properties": {
    "addr:full":"Carrer de Pla De La Font, 24 Pego Alicante 03780",
    "addr:housenumber":"24",
    "addr:postcode":"03780",
    "addr:street":"Carrer De Pla De La Font",
    "iso:country":"ES",
    "sg:address":"Carrer de Pla De La Font, 24",
    "sg:city":"Pego",
    "sg:orig_category":"Asociaciones, Organismos Culturales Y Socioeducativos",
    "sg:phone":"+34 965 57 20 99",
    "sg:postcode":"03780",
    "sg:province":"Alicante",
    "wof:name":"Casal Cultural De Pego",
    "wof:placetype":"venue"
},
  "geometry": {"coordinates":[-0.1101740003,38.8434486389],"type":"Point"}
}