{
  "type": "Feature",
  "properties": {
    "iso:country":"ES",
    "sg:address":"Calle de Alameda, 10",
    "sg:city":"Santa Colomba De Las Monjas",
    "sg:orig_category":"Promotores Constructores",
    "sg:phone":"+34 980 65 41 58",
    "sg:postcode":"49699",
    "sg:province":"Zamora",
    "wof:name":"Construcciones Perez Del Amo S.a.",
    "wof:placetype":"venue"
},
  "geometry": {"coordinates":[-5.6837601662,41.9600105286],"type":"Point"}
}