{
  "type": "Feature",
  "properties": {
    "addr:full":"Avda Andalucia (de), 7 Estacion M\u00e1laga 29580",
    "addr:postcode":"29580",
    "addr:street":"Avda Andalucia De 7 Estacion Ma\u0301Laga",
    "iso:country":"ES",
    "sg:address":"Avda Andalucia (de), 7",
    "sg:city":"Estacion",
    "sg:orig_category":"Carnicer\u00cdas, Carnicer\u00cdas",
    "sg:phone":"+34 952 42 07 28",
    "sg:postcode":"29580",
    "sg:province":"M\u00e1laga",
    "wof:name":"Carniceria Hermanos Galvez S.l",
    "wof:placetype":"venue"
},
  "geometry": {"coordinates":[-4.602563858,36.7360610962],"type":"Point"}
}