{
  "type": "Feature",
  "properties": {
    "addr:full":"Calle de Monestir De Poblet, 24 Valencia Valencia 46015",
    "addr:housenumber":"24",
    "addr:postcode":"46015",
    "addr:street":"Calle De Monestir De Poblet",
    "iso:country":"ES",
    "sg:address":"Calle de Monestir De Poblet, 24",
    "sg:city":"Valencia",
    "sg:orig_category":"Asesor\u00cda Sobre Comunicaci\u00d3n De Empresas",
    "sg:phone":"+34 963 17 32 91",
    "sg:postcode":"46015",
    "sg:province":"Valencia",
    "wof:name":"Mecamerc Asesores S.l.",
    "wof:placetype":"venue"
},
  "geometry": {"coordinates":[-0.3941380084,39.4852485657],"type":"Point"}
}