{
  "type": "Feature",
  "properties": {
    "iso:country":"ES",
    "sg:address":"Calle de Pizarro, 25",
    "sg:city":"Huecas",
    "sg:orig_category":"Inmobiliaria (agencias)",
    "sg:phone":"+34 925 78 43 17",
    "sg:postcode":"45511",
    "sg:province":"Toledo",
    "wof:name":"Gonzalez Gomez-rey Donato",
    "wof:placetype":"venue"
},
  "geometry": {"coordinates":[-4.1959791183,40.0118255615],"type":"Point"}
}