{
  "type": "Feature",
  "properties": {
    "iso:country":"ES",
    "sg:address":"Gmo Franco, S/n",
    "sg:city":"Arrecife",
    "sg:orig_category":"Administraciones Regionales, Departamentales Y Locales",
    "sg:phone":"+34 928 81 31 74",
    "sg:postcode":"35500",
    "sg:province":"Las Palmas",
    "wof:name":"Ayuntamiento De Arrecife",
    "wof:placetype":"venue"
},
  "geometry": {"coordinates":[-13.561044693,28.9756126404],"type":"Point"}
}