{
  "type": "Feature",
  "properties": {
    "addr:full":"Rond Constitucio, 3 Monovar Alicante 03640",
    "addr:housenumber":"3",
    "addr:postcode":"03640",
    "addr:street":"Rond Constitucio;Alicante",
    "iso:country":"ES",
    "sg:address":"Rond Constitucio, 3",
    "sg:city":"Monovar",
    "sg:orig_category":"Molduras, Junquillos, Listones Y Molduras Perforadas",
    "sg:phone":"+34 965 47 29 88",
    "sg:postcode":"03640",
    "sg:province":"Alicante",
    "wof:name":"Lara Gallardo Miguel",
    "wof:placetype":"venue"
},
  "geometry": {"coordinates":[-0.8290240169,38.4391365051],"type":"Point"}
}