{
  "type": "Feature",
  "properties": {
    "addr:full":"Plaz San Pedro, 5 Huesca Huesca 22001",
    "addr:housenumber":"5",
    "addr:postcode":"22001",
    "addr:street":"Plaz San Pedro",
    "iso:country":"ES",
    "sg:address":"Plaz San Pedro, 5",
    "sg:city":"Huesca",
    "sg:orig_category":"Peluqueros: De Se\u00d1oras",
    "sg:phone":"+34 974 23 09 80",
    "sg:postcode":"22001",
    "sg:province":"Huesca",
    "wof:name":"Laglera Duran Jesus Angel",
    "wof:placetype":"venue"
},
  "geometry": {"coordinates":[-0.4070569873,42.1386070251],"type":"Point"}
}