{
  "type": "Feature",
  "properties": {
    "iso:country":"ES",
    "sg:address":"Avda Naciones, 189",
    "sg:city":"Ciudad Quesada",
    "sg:orig_category":"Cl\u00cdnicas Dentales",
    "sg:phone":"+34 966 71 64 96",
    "sg:postcode":"03170",
    "sg:province":"Alicante",
    "wof:name":"Smith  Ian",
    "wof:placetype":"venue"
},
  "geometry": {"coordinates":[-0.7292140126,38.0850296021],"type":"Point"}
}