{
  "type": "Feature",
  "properties": {
    "addr:full":"Rua Villar, 46 Ourense Ourense 32005",
    "addr:housenumber":"46",
    "addr:postcode":"32005",
    "addr:street":"Rua Villar",
    "iso:country":"ES",
    "sg:address":"Rua Villar, 46",
    "sg:city":"Ourense",
    "sg:orig_category":"Zapatos (al Por Menor)",
    "sg:phone":"+34 988 24 90 04",
    "sg:postcode":"32005",
    "sg:province":"Ourense",
    "wof:name":"Diaz Perez Margarita",
    "wof:placetype":"venue"
},
  "geometry": {"coordinates":[-7.8646941185,42.3323097229],"type":"Point"}
}