{
  "type": "Feature",
  "properties": {
    "iso:country":"ES",
    "sg:address":"Carrer de Maria Aguilo, 28",
    "sg:city":"Barcelona",
    "sg:orig_category":"Relojer\u00cda (al Por Menor, Reparaci\u00d3n)",
    "sg:phone":"+34 933 00 70 63",
    "sg:postcode":"08005",
    "sg:province":"Barcelona",
    "wof:name":"Relojeria Y Complementos S.l.",
    "wof:placetype":"venue"
},
  "geometry": {"coordinates":[2.2000579834,41.403137207],"type":"Point"}
}