{
  "type": "Feature",
  "properties": {
    "addr:full":"Barr Atxikorre, S/n Elexalde Vizcaya 48970",
    "addr:housenumber":"s",
    "addr:postcode":"48970",
    "addr:street":"/ N Elexalde Vizcaya",
    "iso:country":"ES",
    "sg:address":"Barr Atxikorre, S/n",
    "sg:city":"Elexalde",
    "sg:orig_category":"Ferreter\u00cda (diversos)",
    "sg:phone":"+34 944 49 25 44",
    "sg:postcode":"48970",
    "sg:province":"Vizcaya",
    "wof:name":"Rebolo Neira Alberto",
    "wof:placetype":"venue"
},
  "geometry": {"coordinates":[-2.8870439529,43.2375488281],"type":"Point"}
}