{
  "type": "Feature",
  "properties": {
    "iso:country":"ES",
    "sg:address":"Calle de Angelita Camarero, 3",
    "sg:city":"Madrid",
    "sg:orig_category":"Inmobiliaria (agencias)",
    "sg:phone":"+34 913 73 71 50",
    "sg:postcode":"28035",
    "sg:province":"Madrid",
    "wof:name":"Servicios Inmobiliarios Romasa S.l.",
    "wof:placetype":"venue"
},
  "geometry": {"coordinates":[-3.7278571129,40.4819068909],"type":"Point"}
}