{
  "type": "Feature",
  "properties": {
    "iso:country":"ES",
    "sg:address":"Carr Joan Burcet, 17",
    "sg:city":"Blanes",
    "sg:orig_category":"Molduras, Junquillos, Listones Y Molduras Perforadas",
    "sg:phone":"+34 972 33 50 78",
    "sg:postcode":"17300",
    "sg:province":"Girona",
    "wof:name":"Sola Perez Francisco Jose",
    "wof:placetype":"venue"
},
  "geometry": {"coordinates":[2.7881560326,41.6756515503],"type":"Point"}
}