{
  "type": "Feature",
  "properties": {
    "iso:country":"ES",
    "sg:address":"Avda Ciudad De Barcelona, 122",
    "sg:city":"Madrid",
    "sg:orig_category":"Abogados",
    "sg:phone":"+34 914 33 34 09",
    "sg:postcode":"28007",
    "sg:province":"Madrid",
    "wof:name":"Garcia Lari\u00f1o Jose",
    "wof:placetype":"venue"
},
  "geometry": {"coordinates":[-3.6818768978,40.4046096802],"type":"Point"}
}