{
  "type": "Feature",
  "properties": {
    "addr:full":"Calle de Joaquin Costa, 6 Barbastro Huesca 22300",
    "addr:housenumber":"6",
    "addr:postcode":"22300",
    "addr:street":"Calle De Joaquin Costa",
    "iso:country":"ES",
    "sg:address":"Calle de Joaquin Costa, 6",
    "sg:city":"Barbastro",
    "sg:orig_category":"Quincaller\u00cda (al Por Mayor)",
    "sg:phone":"+34 974 31 11 42",
    "sg:postcode":"22300",
    "sg:province":"Huesca",
    "wof:name":"Ferreteria Abadias S.l.",
    "wof:placetype":"venue"
},
  "geometry": {"coordinates":[0.1258029938,42.0354804993],"type":"Point"}
}