{
  "type": "Feature",
  "properties": {
    "iso:country":"ES",
    "sg:address":"Plaz Jacobo Roldan Losada, S/n",
    "sg:city":"Villacarriedo",
    "sg:orig_category":"Supermercados Y Hipermercados",
    "sg:phone":"+34 942 59 05 48",
    "sg:postcode":"39640",
    "sg:province":"Cantabria",
    "wof:name":"El Cruce De Carriedo S.l.",
    "wof:placetype":"venue"
},
  "geometry": {"coordinates":[-3.8113639355,43.2283859253],"type":"Point"}
}