{
  "type": "Feature",
  "properties": {
    "addr:full":"Calle de Argentina, 8 Caceres C\u00e1ceres 10001",
    "addr:housenumber":"8",
    "addr:postcode":"10001",
    "addr:street":"Calle De Argentina;Ca\u0301Ceres",
    "iso:country":"ES",
    "sg:address":"Calle de Argentina, 8",
    "sg:city":"Caceres",
    "sg:orig_category":"Comercio, Reparaci\u00d3n De Motocicletas, Bicicletas Y Piezas Sueltas",
    "sg:phone":"+34 927 21 02 95",
    "sg:postcode":"10001",
    "sg:province":"C\u00e1ceres",
    "wof:name":"Argimoto Racing S.l.",
    "wof:placetype":"venue"
},
  "geometry": {"coordinates":[-6.3811907768,39.4673538208],"type":"Point"}
}