{
  "type": "Feature",
  "properties": {
    "addr:full":"Calle de Virgen Del Puig, 14 Alacant Alicante 03009",
    "addr:housenumber":"14",
    "addr:postcode":"03009",
    "addr:street":"Calle De Virgen Del Puig",
    "iso:country":"ES",
    "sg:address":"Calle de Virgen Del Puig, 14",
    "sg:city":"Alacant",
    "sg:orig_category":"Persianas Interiores, Exteriores",
    "sg:phone":"+34 965 17 29 39",
    "sg:postcode":"03009",
    "sg:province":"Alicante",
    "wof:name":"Toldos Pepe E Hijos S.l.",
    "wof:placetype":"venue"
},
  "geometry": {"coordinates":[-0.5000720024,38.3681602478],"type":"Point"}
}