{
  "type": "Feature",
  "properties": {
    "iso:country":"ES",
    "sg:address":"Calle de Cigue\u00d1a, 7",
    "sg:city":"Valladolid",
    "sg:orig_category":"Escayola Y Productos De Escayola (fabricaci\u00d3n, Al Por Mayor)",
    "sg:phone":"+34 983 30 05 35",
    "sg:postcode":"47012",
    "sg:province":"Valladolid",
    "wof:name":"Escayolas Melgar S.l.",
    "wof:placetype":"venue"
},
  "geometry": {"coordinates":[-4.7130289078,41.6446037292],"type":"Point"}
}