{
  "type": "Feature",
  "properties": {
    "addr:full":"Cami Ca La Madrona (de), 40 Mataro Barcelona 08304",
    "addr:postcode":"08304",
    "addr:street":"Ca La;De 40",
    "iso:country":"ES",
    "sg:address":"Cami Ca La Madrona (de), 40",
    "sg:city":"Mataro",
    "sg:orig_category":"Fabricaci\u00d3n De Su\u00c9ters Y Chalecos De Punto",
    "sg:phone":"+34 937 90 75 40",
    "sg:postcode":"08304",
    "sg:province":"Barcelona",
    "wof:name":"Jimenez Gonzalez Joaquin",
    "wof:placetype":"venue"
},
  "geometry": {"coordinates":[2.4539899826,41.5548286438],"type":"Point"}
}