{
  "type": "Feature",
  "properties": {
    "iso:country":"ES",
    "sg:address":"Calle de Rafael Alberti, 43",
    "sg:city":"Mairena Alcor",
    "sg:orig_category":"Art\u00cdculos De Decoraci\u00d3n",
    "sg:phone":"+34 955 74 88 74",
    "sg:postcode":"41510",
    "sg:province":"Sevilla",
    "wof:name":"Montero Prieto Virginia",
    "wof:placetype":"venue"
},
  "geometry": {"coordinates":[-5.7555580139,37.373588562],"type":"Point"}
}