{
  "type": "Feature",
  "properties": {
    "iso:country":"ES",
    "sg:address":"Avda O.n.u. (de La), 1",
    "sg:city":"Mostoles",
    "sg:orig_category":"Ense\u00d1anza Secundaria: Colegios Y Escuelas Privadas",
    "sg:phone":"+34 916 46 14 17",
    "sg:postcode":"28936",
    "sg:province":"Madrid",
    "wof:name":"Instituto Bachillerato Clara Campoamor",
    "wof:placetype":"venue"
},
  "geometry": {"coordinates":[-3.8554348946,40.3301887512],"type":"Point"}
}