{
  "type": "Feature",
  "properties": {
    "addr:full":"Calle de Venus, 2 Mostoles Madrid 28936",
    "addr:housenumber":"2",
    "addr:postcode":"28936",
    "addr:street":"Calle De Venus",
    "iso:country":"ES",
    "sg:address":"Calle de Venus, 2",
    "sg:city":"Mostoles",
    "sg:orig_category":"Electromec\u00c1nica",
    "sg:phone":"+34 916 46 79 55",
    "sg:postcode":"28936",
    "sg:province":"Madrid",
    "wof:name":"Suministros Y Montajes Alfar S. L.",
    "wof:placetype":"venue"
},
  "geometry": {"coordinates":[-3.8460226059,40.3136825562],"type":"Point"}
}