{
  "type": "Feature",
  "properties": {
    "iso:country":"ES",
    "sg:address":"Carrer de Canaleta, 13",
    "sg:city":"Sant Feliu Raco",
    "sg:orig_category":"Inform\u00c1tica (estudios, Servicios, Asesor\u00cda, Formaci\u00d3n)",
    "sg:phone":"+34 937 15 90 81",
    "sg:postcode":"08211",
    "sg:province":"Barcelona",
    "wof:name":"Carca\u00f1o Torres Jordi",
    "wof:placetype":"venue"
},
  "geometry": {"coordinates":[2.0824799538,41.6114387512],"type":"Point"}
}