{
  "type": "Feature",
  "properties": {
    "addr:full":"Calle de Barrio Nuevo, 12 Aranda Duero Burgos 09400",
    "addr:housenumber":"12",
    "addr:postcode":"09400",
    "addr:street":"Calle De Barrio Nuevo",
    "iso:country":"ES",
    "sg:address":"Calle de Barrio Nuevo, 12",
    "sg:city":"Aranda Duero",
    "sg:orig_category":"Bares, Piano",
    "sg:phone":"+34 947 50 04 06",
    "sg:postcode":"09400",
    "sg:province":"Burgos",
    "wof:name":"Bodegas Esteban Sanz S.l.",
    "wof:placetype":"venue"
},
  "geometry": {"coordinates":[-3.6875500679,41.671672821],"type":"Point"}
}