{
  "type": "Feature",
  "properties": {
    "iso:country":"ES",
    "sg:address":"Carrer de Fatjo, 30",
    "sg:city":"Sabadell",
    "sg:orig_category":"Venta Al Preg\u00d3n",
    "sg:phone":"+34 937 11 30 97",
    "sg:postcode":"08204",
    "sg:province":"Barcelona",
    "wof:name":"Merino Lucas Joaquin",
    "wof:placetype":"venue"
},
  "geometry": {"coordinates":[2.1198129654,41.528175354],"type":"Point"}
}