{
  "type": "Feature",
  "properties": {
    "addr:full":"Calle de Historiador Antonio Aguilar Y Cano, 63 Puente-genil C\u00f3rdoba 14500",
    "addr:housenumber":"63",
    "addr:postcode":"14500",
    "addr:street":"Calle De Historiador Antonio;Puente-Genil Co\u0301Rdoba",
    "iso:country":"ES",
    "sg:address":"Calle de Historiador Antonio Aguilar Y Cano, 63",
    "sg:city":"Puente-genil",
    "sg:orig_category":"Equipo De Refrigeraci\u00d3n Industrial",
    "sg:phone":"+34 957 60 01 84",
    "sg:postcode":"14500",
    "sg:province":"C\u00f3rdoba",
    "wof:name":"Gomez Luque Francisco",
    "wof:placetype":"venue"
},
  "geometry": {"coordinates":[-4.7641592026,37.3910942078],"type":"Point"}
}