{
  "type": "Feature",
  "properties": {
    "iso:country":"ES",
    "sg:address":"Calle de Juncos, 2",
    "sg:city":"Laguna Duero",
    "sg:orig_category":"Fotocopias, Reprograf\u00cda",
    "sg:phone":"+34 983 54 36 98",
    "sg:postcode":"47140",
    "sg:province":"Valladolid",
    "wof:name":"Fraile Martin Roman",
    "wof:placetype":"venue"
},
  "geometry": {"coordinates":[-4.7257890701,41.5828895569],"type":"Point"}
}