{
  "type": "Feature",
  "properties": {
    "iso:country":"ES",
    "sg:address":"Carrer de Mossen Jacint Verdaguer, 45",
    "sg:city":"Esplugues Llobregat",
    "sg:orig_category":"Promotores Constructores",
    "sg:phone":"+34 934 80 90 85",
    "sg:postcode":"08950",
    "sg:province":"Barcelona",
    "sg:website":"www.jcheyman.com",
    "wof:name":"J C Eyman Inmobiliaria",
    "wof:placetype":"venue"
},
  "geometry": {"coordinates":[2.085324049,41.3768386841],"type":"Point"}
}