{
  "type": "Feature",
  "properties": {
    "iso:country":"ES",
    "sg:address":"Carrer de Enten\u00c7a, 172",
    "sg:city":"Barcelona",
    "sg:orig_category":"Abogados",
    "sg:phone":"+34 934 10 90 28",
    "sg:postcode":"08029",
    "sg:province":"Barcelona",
    "wof:name":"Gambus Sanchez Joaquim",
    "wof:placetype":"venue"
},
  "geometry": {"coordinates":[2.1452157497,41.3837089539],"type":"Point"}
}