{
  "type": "Feature",
  "properties": {
    "addr:full":"Ctra A-340 Estepa-guadix, Km. 0066,2 Bernabe C\u00f3rdoba 14810",
    "addr:postcode":"14810",
    "addr:street":"Ctra A-340 Estepa-Guadix Km. 0066,2 Bernabe Co\u0301Rdoba",
    "iso:country":"ES",
    "sg:address":"Ctra A-340 Estepa-guadix, Km. 0066,2",
    "sg:city":"Bernabe",
    "sg:orig_category":"Fabricaci\u00d3n De Muebles",
    "sg:phone":"+34 957 55 30 85",
    "sg:postcode":"14810",
    "sg:province":"C\u00f3rdoba",
    "wof:name":"Muebles Salomon S.l.",
    "wof:placetype":"venue"
},
  "geometry": {"coordinates":[-4.2726888657,37.4425811768],"type":"Point"}
}