{
  "type": "Feature",
  "properties": {
    "addr:full":"Calle de Canal De Panama, 5 Madrid Madrid 28027",
    "addr:housenumber":"5",
    "addr:postcode":"28027",
    "addr:street":"Calle De Canal De Panama",
    "iso:country":"ES",
    "sg:address":"Calle de Canal De Panama, 5",
    "sg:city":"Madrid",
    "sg:orig_category":"Agencias Y Asesores De Publicidad",
    "sg:phone":"+34 914 05 22 53",
    "sg:postcode":"28027",
    "sg:province":"Madrid",
    "wof:name":"Garcia Martin Roberto",
    "wof:placetype":"venue"
},
  "geometry": {"coordinates":[-3.6509950161,40.4399452209],"type":"Point"}
}