{
  "type": "Feature",
  "properties": {
    "addr:full":"Calle de Sor Angela De La Cruz, 18 Olivares Sevilla 41804",
    "addr:housenumber":"18",
    "addr:postcode":"41804",
    "addr:street":"Calle De Sor Angela De La Cruz;Sevilla",
    "iso:country":"ES",
    "sg:address":"Calle de Sor Angela De La Cruz, 18",
    "sg:city":"Olivares",
    "sg:orig_category":"Comercio De Hierro",
    "sg:phone":"+34 955 71 87 60",
    "sg:postcode":"41804",
    "sg:province":"Sevilla",
    "wof:name":"Hierros Olivares S.l.",
    "wof:placetype":"venue"
},
  "geometry": {"coordinates":[-6.1521539688,37.4176673889],"type":"Point"}
}