{
  "type": "Feature",
  "properties": {
    "iso:country":"ES",
    "sg:address":"Calle de Conde De Aranda, 24",
    "sg:city":"Aguilas",
    "sg:orig_category":"Farmacias",
    "sg:phone":"+34 968 41 01 46",
    "sg:postcode":"30880",
    "sg:province":"Murcia",
    "wof:name":"Santamaria Cas Alejandro Eduardo",
    "wof:placetype":"venue"
},
  "geometry": {"coordinates":[-1.5839509964,37.4046936035],"type":"Point"}
}