{
  "type": "Feature",
  "properties": {
    "iso:country":"ES",
    "sg:address":"Carrobide, 7",
    "sg:city":"Atarrabia",
    "sg:orig_category":"Quincaller\u00cda (al Por Menor)",
    "sg:phone":"+34 948 14 83 11",
    "sg:postcode":"31610",
    "sg:province":"Navarra",
    "wof:name":"Garcia Erro Miguel Angel",
    "wof:placetype":"venue"
},
  "geometry": {"coordinates":[-1.613132,42.8331985474],"type":"Point"}
}