{
  "type": "Feature",
  "properties": {
    "addr:full":"Avda Prado Pocito, 72 Valdelagua Salamanca 37194",
    "addr:housenumber":"72",
    "addr:postcode":"37194",
    "addr:street":"Avda Prado Pocito",
    "iso:country":"ES",
    "sg:address":"Avda Prado Pocito, 72",
    "sg:city":"Valdelagua",
    "sg:orig_category":"Doctores En Medicina",
    "sg:phone":"+34 923 13 92 90",
    "sg:postcode":"37194",
    "sg:province":"Salamanca",
    "wof:name":"Goncalves Estella Antonio",
    "wof:placetype":"venue"
},
  "geometry": {"coordinates":[-5.6208047867,40.9431800842],"type":"Point"}
}