{
  "type": "Feature",
  "properties": {
    "addr:full":"Granados, 1 Carchuna Granada 18730",
    "addr:housenumber":"1",
    "addr:postcode":"18730",
    "addr:street":"Granados",
    "iso:country":"ES",
    "sg:address":"Granados, 1",
    "sg:city":"Carchuna",
    "sg:orig_category":"Delegados, Agentes De Tr\u00c1nsito, Auxiliares De Transporte Internacional",
    "sg:phone":"+34 958 62 44 04",
    "sg:postcode":"18730",
    "sg:province":"Granada",
    "wof:name":"Rodriguez Noguera Maria",
    "wof:placetype":"venue"
},
  "geometry": {"coordinates":[-3.4161479473,36.7013244629],"type":"Point"}
}