{
  "type": "Feature",
  "properties": {
    "iso:country":"ES",
    "sg:address":"Pla\u00c7 Pla\u00c7a Alborxi, S/n",
    "sg:city":"Alzira",
    "sg:orig_category":"Orquestas De Variedades",
    "sg:phone":"+34 962 41 29 69",
    "sg:postcode":"46600",
    "sg:province":"Valencia",
    "wof:name":"Coral Polifonica Ciudad De Alzira",
    "wof:placetype":"venue"
},
  "geometry": {"coordinates":[-0.4378489852,39.1517295837],"type":"Point"}
}