{
  "type": "Feature",
  "properties": {
    "iso:country":"ES",
    "sg:address":"Carrer de Poetessa Capara, 21",
    "sg:city":"Terrassa",
    "sg:orig_category":"Peluquer\u00cdas, Peluquer\u00cda Mixta",
    "sg:phone":"+34 937 84 06 93",
    "sg:postcode":"08226",
    "sg:province":"Barcelona",
    "wof:name":"Cirre Pardo Carmen",
    "wof:placetype":"venue"
},
  "geometry": {"coordinates":[2.0232419968,41.5722579956],"type":"Point"}
}