{
  "type": "Feature",
  "properties": {
    "addr:full":"Calle de Hermanos Moroy, 12 Logro\u00f1o La Rioja 26001",
    "addr:housenumber":"12",
    "addr:postcode":"26001",
    "addr:street":"Calle De Hermanos Moroy;Rioja",
    "iso:country":"ES",
    "sg:address":"Calle de Hermanos Moroy, 12",
    "sg:city":"Logro\u00f1o",
    "sg:orig_category":"Charcuter\u00cdas (al Por Mayor)",
    "sg:phone":"+34 941 25 17 81",
    "sg:postcode":"26001",
    "sg:province":"La Rioja",
    "wof:name":"Loza Martinez Margarita",
    "wof:placetype":"venue"
},
  "geometry": {"coordinates":[-2.4463961124,42.466003418],"type":"Point"}
}