{
  "type": "Feature",
  "properties": {
    "addr:full":"Calle de Miguel Servet, 6 Torres Berrellen Zaragoza 50693",
    "addr:housenumber":"6",
    "addr:postcode":"50693",
    "addr:street":"Calle De Miguel Servet",
    "iso:country":"ES",
    "sg:address":"Calle de Miguel Servet, 6",
    "sg:city":"Torres Berrellen",
    "sg:orig_category":"Estudios, Instalaci\u00d3n De Climatizaci\u00d3n",
    "sg:phone":"+34 976 65 32 76",
    "sg:postcode":"50693",
    "sg:province":"Zaragoza",
    "wof:name":"Termo-aragon S.l.",
    "wof:placetype":"venue"
},
  "geometry": {"coordinates":[-1.0685089827,41.7593688965],"type":"Point"}
}