{
  "type": "Feature",
  "properties": {
    "iso:country":"ES",
    "sg:address":"Carrer de Volta D'en Bufanalla, 1",
    "sg:city":"Barcelona",
    "sg:orig_category":"Promotores Constructores",
    "sg:phone":"+34 932 68 31 09",
    "sg:postcode":"08003",
    "sg:province":"Barcelona",
    "wof:name":"Lovirent S.l.",
    "wof:placetype":"venue"
},
  "geometry": {"coordinates":[2.182571888,41.3840904236],"type":"Point"}
}