{
  "type": "Feature",
  "properties": {
    "iso:country":"ES",
    "sg:address":"Ptge Almirall Marquet, 6",
    "sg:city":"Sabadell",
    "sg:orig_category":"Peluqueros: De Se\u00d1oras",
    "sg:phone":"+34 937 17 03 53",
    "sg:postcode":"08208",
    "sg:province":"Barcelona",
    "wof:name":"Costa Molina Maria Carmen",
    "wof:placetype":"venue"
},
  "geometry": {"coordinates":[2.1345500946,41.5642738342],"type":"Point"}
}