{
  "type": "Feature",
  "properties": {
    "addr:full":"Avda Celso Muerza, 36 S. Adrian Navarra 31570",
    "addr:housenumber":"36",
    "addr:postcode":"31570",
    "addr:street":"Avda Celso Muerza;S. Adrian Navarra",
    "iso:country":"ES",
    "sg:address":"Avda Celso Muerza, 36",
    "sg:city":"S. Adrian",
    "sg:orig_category":"Lavado, Limpieza De Veh\u00cdculos",
    "sg:phone":"+34 948 67 02 46",
    "sg:postcode":"31570",
    "sg:province":"Navarra",
    "wof:name":"Ugarte Rico Francisco",
    "wof:placetype":"venue"
},
  "geometry": {"coordinates":[-1.9293819666,42.3343582153],"type":"Point"}
}