{
  "type": "Feature",
  "properties": {
    "addr:full":"Calle de Valdes, S/n Puerto De Santa Maria C\u00e1diz 11500",
    "addr:housenumber":"s / n",
    "addr:postcode":"11500",
    "addr:street":"Calle De Valdes;Ca\u0301Diz",
    "iso:country":"ES",
    "sg:address":"Calle de Valdes, S/n",
    "sg:city":"Puerto De Santa Maria",
    "sg:orig_category":"Carnicer\u00cdas, Carnicer\u00cdas",
    "sg:phone":"+34 956 87 08 35",
    "sg:postcode":"11500",
    "sg:province":"C\u00e1diz",
    "wof:name":"Amado  Juan Carlos",
    "wof:placetype":"venue"
},
  "geometry": {"coordinates":[-6.2326974869,36.5956039429],"type":"Point"}
}