{
  "type": "Feature",
  "properties": {
    "iso:country":"ES",
    "sg:address":"Av. Juan Carlos I, 54",
    "sg:city":"Fuente Fresno",
    "sg:orig_category":"Empresas De Carpinter\u00cda De Madera",
    "sg:phone":"+34 926 80 62 52",
    "sg:postcode":"13680",
    "sg:province":"Ciudad Real",
    "wof:name":"Casero Rodriguez Teodoro",
    "wof:placetype":"venue"
},
  "geometry": {"coordinates":[-3.7769839764,39.2241249084],"type":"Point"}
}