{
  "type": "Feature",
  "properties": {
    "addr:full":"Calle de Bache, 23 Villar Arzobispo Valencia 46170",
    "addr:housenumber":"23",
    "addr:postcode":"46170",
    "addr:street":"Calle De Bache",
    "iso:country":"ES",
    "sg:address":"Calle de Bache, 23",
    "sg:city":"Villar Arzobispo",
    "sg:orig_category":"Alfarer\u00cda",
    "sg:phone":"+34 962 72 06 76",
    "sg:postcode":"46170",
    "sg:province":"Valencia",
    "wof:name":"Lopez Garay Jose",
    "wof:placetype":"venue"
},
  "geometry": {"coordinates":[-0.8224163055,39.7314987183],"type":"Point"}
}