{
  "type": "Feature",
  "properties": {
    "addr:full":"Val De La Piedra, S/n Foz-calanda Teruel 44579",
    "addr:housenumber":"s / n",
    "addr:postcode":"44579",
    "addr:street":"Val;La Piedra",
    "iso:country":"ES",
    "sg:address":"Val De La Piedra, S/n",
    "sg:city":"Foz-calanda",
    "sg:orig_category":"Explotaci\u00d3n De Minas",
    "sg:phone":"+34 978 84 68 68",
    "sg:postcode":"44579",
    "sg:province":"Teruel",
    "wof:name":"Comunitel Global",
    "wof:placetype":"venue"
},
  "geometry": {"coordinates":[-0.2684589922,40.9232597351],"type":"Point"}
}