{
  "type": "Feature",
  "properties": {
    "iso:country":"ES",
    "sg:address":"Calle de Fola, 12",
    "sg:city":"Castellon",
    "sg:orig_category":"Abogados",
    "sg:phone":"+34 964 22 39 42",
    "sg:postcode":"12002",
    "sg:province":"Castell\u00f3n",
    "wof:name":"Nebot Perez Ramon",
    "wof:placetype":"venue"
},
  "geometry": {"coordinates":[-0.0385229997,39.9824333191],"type":"Point"}
}