{
  "type": "Feature",
  "properties": {
    "addr:full":"Calle de Rio (el), S/n Villanueva Carrizo Le\u00f3n 24270",
    "addr:postcode":"24270",
    "addr:street":"Calle De Rio El S / N",
    "iso:country":"ES",
    "sg:address":"Calle de Rio (el), S/n",
    "sg:city":"Villanueva Carrizo",
    "sg:orig_category":"Estudios Y Construcci\u00d3n De Acuarios Y Viveros",
    "sg:phone":"+34 987 35 74 55",
    "sg:postcode":"24270",
    "sg:province":"Le\u00f3n",
    "wof:name":"Casado Verdejo Luis Miguel",
    "wof:placetype":"venue"
},
  "geometry": {"coordinates":[-5.8175940514,42.5844345093],"type":"Point"}
}