{
  "type": "Feature",
  "properties": {
    "addr:full":"Avda Manuel Ardoy, 19 Beas Segura Ja\u00e9n 23280",
    "addr:housenumber":"19",
    "addr:postcode":"23280",
    "addr:street":"Avda Manuel Ardoy",
    "iso:country":"ES",
    "sg:address":"Avda Manuel Ardoy, 19",
    "sg:city":"Beas Segura",
    "sg:orig_category":"Ense\u00d1anza: Comercio, Gesti\u00d3n, Inform\u00c1tica",
    "sg:phone":"+34 953 42 53 79",
    "sg:postcode":"23280",
    "sg:province":"Ja\u00e9n",
    "wof:name":"Formacion Sierra De Segura S.l.l",
    "wof:placetype":"venue"
},
  "geometry": {"coordinates":[-2.89666605,38.2541351318],"type":"Point"}
}