{
  "type": "Feature",
  "properties": {
    "iso:country":"ES",
    "sg:address":"Calle de Dorado Montero, 13",
    "sg:city":"Salamanca",
    "sg:orig_category":"Mec\u00c1nico Del Autom\u00d3vil",
    "sg:phone":"+34 923 22 58 40",
    "sg:postcode":"37006",
    "sg:province":"Salamanca",
    "wof:name":"Sanchez Juan Alejandro",
    "wof:placetype":"venue"
},
  "geometry": {"coordinates":[-5.6648154259,40.9733543396],"type":"Point"}
}