{
  "type": "Feature",
  "properties": {
    "addr:full":"Cmno Pi Gros, 8 Castellon De La Plana Castell\u00f3n 12005",
    "addr:housenumber":"8",
    "addr:postcode":"12005",
    "addr:street":"Cmno Pi Gros",
    "iso:country":"ES",
    "sg:address":"Cmno Pi Gros, 8",
    "sg:city":"Castellon De La Plana",
    "sg:orig_category":"Paletas",
    "sg:phone":"+34 964 24 31 34",
    "sg:postcode":"12005",
    "sg:province":"Castell\u00f3n",
    "wof:name":"Madelpa S.l.",
    "wof:placetype":"venue"
},
  "geometry": {"coordinates":[-0.0570270009,39.9575424194],"type":"Point"}
}