{
  "type": "Feature",
  "properties": {
    "addr:full":"Plaz Ingeniero Manuel Becerra, S/n Palmas De Gran Canaria Las Palmas 35008",
    "addr:postcode":"35008",
    "addr:street":"Manuel Becerra S / N",
    "iso:country":"ES",
    "sg:address":"Plaz Ingeniero Manuel Becerra, S/n",
    "sg:city":"Palmas De Gran Canaria",
    "sg:orig_category":"Distribuci\u00d3n De Petr\u00d3leo Y Derivados",
    "sg:phone":"+34 928 46 43 70",
    "sg:postcode":"35008",
    "sg:province":"Las Palmas",
    "wof:name":"Sunifish S.l.",
    "wof:placetype":"venue"
},
  "geometry": {"coordinates":[-15.4218044281,28.1502952576],"type":"Point"}
}