{
  "type": "Feature",
  "properties": {
    "iso:country":"ES",
    "sg:address":"Pl. Ayuntamiento, S/n",
    "sg:city":"Castropol",
    "sg:orig_category":"Aguas (distribuci\u00d3n, Servicios)",
    "sg:phone":"+34 985 63 55 08",
    "sg:postcode":"33760",
    "sg:province":"Asturias",
    "wof:name":"Asturagua S.a.",
    "wof:placetype":"venue"
},
  "geometry": {"coordinates":[-7.0299491882,43.5277633667],"type":"Point"}
}