{
  "type": "Feature",
  "properties": {
    "iso:country":"ES",
    "sg:address":"Carrer de Valencia, 550",
    "sg:city":"Barcelona",
    "sg:orig_category":"Fabricaci\u00d3n De Muebles",
    "sg:phone":"+34 932 31 31 12",
    "sg:postcode":"08013",
    "sg:province":"Barcelona",
    "wof:name":"Barimueble S. A.",
    "wof:placetype":"venue"
},
  "geometry": {"coordinates":[2.1822500229,41.4069290161],"type":"Point"}
}