{
  "type": "Feature",
  "properties": {
    "iso:country":"ES",
    "sg:address":"Avda Francisco Chacon, 21",
    "sg:city":"Puebla De Alcocer",
    "sg:classifiers":[
        {
            "category":"Taxi",
            "type":"Transportation"
        }
    ],
    "sg:phone":"+34 924 62 00 67",
    "sg:postcode":"06630",
    "sg:province":"Badajoz",
    "wof:name":"Leon Saucedo Jesus",
    "wof:placetype":"venue"
},
  "geometry": {"coordinates":[-5.2555170059,38.986492157],"type":"Point"}
}