{
  "type": "Feature",
  "properties": {
    "addr:full":"Pg Muntanya, 25 Granollers Barcelona 08402",
    "addr:housenumber":"25",
    "addr:postcode":"08402",
    "addr:street":"Pg Muntanya",
    "iso:country":"ES",
    "sg:address":"Pg Muntanya, 25",
    "sg:city":"Granollers",
    "sg:orig_category":"Arreglo, Reparaci\u00d3n, Piezas Sueltas De Televisi\u00d3n, V\u00cddeo, Hi",
    "sg:phone":"+34 938 79 05 77",
    "sg:postcode":"08402",
    "sg:province":"Barcelona",
    "wof:name":"Rubio Bayo Jaime",
    "wof:placetype":"venue"
},
  "geometry": {"coordinates":[2.2931070328,41.6069717407],"type":"Point"}
}