{
  "type": "Feature",
  "properties": {
    "iso:country":"ES",
    "sg:address":"Pol Ind Isaac Peral, 23",
    "sg:city":"Don Benito",
    "sg:orig_category":"Suministros Para Hoteles",
    "sg:phone":"+34 924 80 06 83",
    "sg:postcode":"06400",
    "sg:province":"Badajoz",
    "wof:name":"Carmona Garcia Baltasar",
    "wof:placetype":"venue"
},
  "geometry": {"coordinates":[-5.8690190315,38.963596344],"type":"Point"}
}