{
  "type": "Feature",
  "properties": {
    "addr:full":"Av Jaume I El Conqueridor, S/n Playa Muchavista Alicante 03560",
    "addr:housenumber":"s / n",
    "addr:postcode":"03560",
    "addr:street":"Av Jaume I El Conqueridor;Muchavista",
    "iso:country":"ES",
    "sg:address":"Av Jaume I El Conqueridor, S/n",
    "sg:city":"Playa Muchavista",
    "sg:orig_category":"Asesor\u00cda Fiscal Y Jur\u00cddica",
    "sg:phone":"+34 965 65 03 08",
    "sg:postcode":"03560",
    "sg:province":"Alicante",
    "wof:name":"Penaalva Garcia Antonio",
    "wof:placetype":"venue"
},
  "geometry": {"coordinates":[-0.4088290036,38.38621521],"type":"Point"}
}