{
  "type": "Feature",
  "properties": {
    "addr:full":"Calle de Damasco, S/n Sevilla Sevilla 41007",
    "addr:housenumber":"s / n",
    "addr:postcode":"41007",
    "addr:street":"Calle De Damasco",
    "iso:country":"ES",
    "sg:address":"Calle de Damasco, S/n",
    "sg:city":"Sevilla",
    "sg:orig_category":"Empresas De Carpinter\u00cda Met\u00c1lica",
    "sg:phone":"+34 954 67 21 26",
    "sg:postcode":"41007",
    "sg:province":"Sevilla",
    "wof:name":"Romero Estirado Esteban",
    "wof:placetype":"venue"
},
  "geometry": {"coordinates":[-5.9570064545,37.396736145],"type":"Point"}
}