{
  "type": "Feature",
  "properties": {
    "iso:country":"ES",
    "sg:address":"Disseminat S. Caterina, S/n",
    "sg:city":"Manresa",
    "sg:orig_category":"Poli\u00c9ster",
    "sg:phone":"+34 938 72 33 12",
    "sg:postcode":"08241",
    "sg:province":"Barcelona",
    "wof:name":"Fiplas Cb",
    "wof:placetype":"venue"
},
  "geometry": {"coordinates":[1.8074586391,41.7116394043],"type":"Point"}
}