{
  "type": "Feature",
  "properties": {
    "addr:full":"Calle de Hernan Cortes, 27 Almoharin C\u00e1ceres 10132",
    "addr:housenumber":"27",
    "addr:postcode":"10132",
    "addr:street":"Calle De Hernan Cortes;Ca\u0301Ceres",
    "iso:country":"ES",
    "sg:address":"Calle de Hernan Cortes, 27",
    "sg:city":"Almoharin",
    "sg:orig_category":"Carnicer\u00cdas, Carnicer\u00cdas",
    "sg:phone":"+34 927 38 71 04",
    "sg:postcode":"10132",
    "sg:province":"C\u00e1ceres",
    "wof:name":"Romero Macia Alejandro",
    "wof:placetype":"venue"
},
  "geometry": {"coordinates":[-6.0446391106,39.1780586243],"type":"Point"}
}