{
  "type": "Feature",
  "properties": {
    "iso:country":"ES",
    "sg:address":"Carrer de Fran\u00c7a, 66",
    "sg:city":"Hospitalet Llobregat",
    "sg:orig_category":"Muebles Y Accesorios Para Cocinas Y Cuartos De Ba\u00d1o (al Por Menor)",
    "sg:phone":"+34 932 63 35 12",
    "sg:postcode":"08907",
    "sg:province":"Barcelona",
    "wof:name":"Martinez Albert Damian",
    "wof:placetype":"venue"
},
  "geometry": {"coordinates":[2.1118071079,41.3549957275],"type":"Point"}
}