{
  "type": "Feature",
  "properties": {
    "iso:country":"ES",
    "sg:address":"Avda Jose Quintana, S/n",
    "sg:city":"Salda\u00f1a",
    "sg:orig_category":"Molduras, Junquillos, Listones Y Molduras Perforadas",
    "sg:phone":"+34 979 89 12 21",
    "sg:postcode":"34100",
    "sg:province":"Palencia",
    "wof:name":"Salvador Vazquez Javier",
    "wof:placetype":"venue"
},
  "geometry": {"coordinates":[-4.7372059822,42.5220108032],"type":"Point"}
}