{
  "type": "Feature",
  "properties": {
    "iso:country":"ES",
    "sg:address":"Calle de Amistad (la), 13",
    "sg:city":"Zaragoza",
    "sg:orig_category":"Farmacias",
    "sg:phone":"+34 976 59 84 06",
    "sg:postcode":"50002",
    "sg:province":"Zaragoza",
    "wof:name":"Vega Malumbres Maria Pilar",
    "wof:placetype":"venue"
},
  "geometry": {"coordinates":[-0.858723104,41.6469688416],"type":"Point"}
}