{
  "type": "Feature",
  "properties": {
    "addr:full":"Calle de Federico Garcia Lorca, S/n Albacete Albacete 02001",
    "addr:housenumber":"/ n",
    "addr:postcode":"02001",
    "addr:street":"Calle De Federico Garcia Lorca S",
    "iso:country":"ES",
    "sg:address":"Calle de Federico Garcia Lorca, S/n",
    "sg:city":"Albacete",
    "sg:orig_category":"Cajas De Ahorro",
    "sg:phone":"+34 967 24 13 34",
    "sg:postcode":"02001",
    "sg:province":"Albacete",
    "sg:website":"www.ccm.es",
    "wof:name":"Caja De Ahorros De Castilla La Mancha",
    "wof:placetype":"venue"
},
  "geometry": {"coordinates":[-1.8463389874,38.9959106445],"type":"Point"}
}