{
  "type": "Feature",
  "properties": {
    "addr:full":"Carr Emili Ferrer I Gomez, 4 Catarroja Valencia 46470",
    "addr:housenumber":"4",
    "addr:postcode":"46470",
    "addr:street":"Carr Emili Ferrer I Gomez",
    "iso:country":"ES",
    "sg:address":"Carr Emili Ferrer I Gomez, 4",
    "sg:city":"Catarroja",
    "sg:orig_category":"Institutos De Belleza",
    "sg:phone":"+34 961 27 28 00",
    "sg:postcode":"46470",
    "sg:province":"Valencia",
    "wof:name":"Carbonera Arevalo Elvira",
    "wof:placetype":"venue"
},
  "geometry": {"coordinates":[-0.4026629925,39.4078102112],"type":"Point"}
}