{
  "type": "Feature",
  "properties": {
    "addr:full":"Pol Ind La Ceca, 34 Andujar Ja\u00e9n 23740",
    "addr:housenumber":"34",
    "addr:postcode":"23740",
    "iso:country":"ES",
    "sg:address":"Pol Ind La Ceca, 34",
    "sg:city":"Andujar",
    "sg:orig_category":"Contenedores (mercanc\u00cdas)",
    "sg:phone":"+34 953 50 79 47",
    "sg:postcode":"23740",
    "sg:province":"Ja\u00e9n",
    "wof:name":"Gonzalez Mesa Maria Dolores",
    "wof:placetype":"venue"
},
  "geometry": {"coordinates":[-4.057518959,38.0386962891],"type":"Point"}
}