{
  "type": "Feature",
  "properties": {
    "addr:full":"Ctra Boadilla, Km. 0002,0 Majadahonda Madrid 28220",
    "addr:postcode":"28220",
    "addr:street":"Ctra Boadilla Km. 0002,0",
    "iso:country":"ES",
    "sg:address":"Ctra Boadilla, Km. 0002,0",
    "sg:city":"Majadahonda",
    "sg:orig_category":"Florister\u00cdas",
    "sg:phone":"+34 916 38 07 21",
    "sg:postcode":"28220",
    "sg:province":"Madrid",
    "wof:name":"Fuentes Lopez Lara",
    "wof:placetype":"venue"
},
  "geometry": {"coordinates":[-3.8698990345,40.4642486572],"type":"Point"}
}