{
  "type": "Feature",
  "properties": {
    "iso:country":"ES",
    "sg:address":"Carrer de Amilcar, 173",
    "sg:city":"Barcelona",
    "sg:orig_category":"Librer\u00cdas",
    "sg:phone":"+34 934 50 05 89",
    "sg:postcode":"08032",
    "sg:province":"Barcelona",
    "wof:name":"Serveis Editorials De Catalunya S. A.",
    "wof:placetype":"venue"
},
  "geometry": {"coordinates":[2.1729199886,41.4233016968],"type":"Point"}
}