{
  "type": "Feature",
  "properties": {
    "iso:country":"ES",
    "sg:address":"Calle de Luis Cernuda, 26",
    "sg:city":"Olivares",
    "sg:orig_category":"Empresas De Desmonte",
    "sg:phone":"+34 954 11 11 94",
    "sg:postcode":"41804",
    "sg:province":"Sevilla",
    "wof:name":"Excavaciones Osuna S.l.",
    "wof:placetype":"venue"
},
  "geometry": {"coordinates":[-6.1571331024,37.4229011536],"type":"Point"}
}