{
  "type": "Feature",
  "properties": {
    "iso:country":"ES",
    "sg:address":"Calle de Unceta, 6",
    "sg:city":"Zaragoza",
    "sg:orig_category":"Orquestas Cl\u00c1sicas, Asociaciones De M\u00dasica, Coros Y Corales",
    "sg:phone":"+34 976 34 67 38",
    "sg:postcode":"50010",
    "sg:province":"Zaragoza",
    "wof:name":"Brioproducciones S.l.",
    "wof:placetype":"venue"
},
  "geometry": {"coordinates":[-0.9025899768,41.6533279419],"type":"Point"}
}