{
  "type": "Feature",
  "properties": {
    "addr:full":"Calle de Real, 49 Matamorosa Cantabria 39200",
    "addr:housenumber":"49",
    "addr:postcode":"39200",
    "addr:street":"Calle De Real",
    "iso:country":"ES",
    "sg:address":"Calle de Real, 49",
    "sg:city":"Matamorosa",
    "sg:orig_category":"Mec\u00c1nico Del Autom\u00d3vil",
    "sg:phone":"+34 942 75 10 91",
    "sg:postcode":"39200",
    "sg:province":"Cantabria",
    "wof:name":"Serna Izquierdo Maria Del Mar",
    "wof:placetype":"venue"
},
  "geometry": {"coordinates":[-4.1461029053,42.9855537415],"type":"Point"}
}