{
  "type": "Feature",
  "properties": {
    "addr:full":"Carrer de Abat Llort, 7 Valls Tarragona 43800",
    "addr:housenumber":"7",
    "addr:postcode":"43800",
    "addr:street":"Carrer De Abat Llort",
    "iso:country":"ES",
    "sg:address":"Carrer de Abat Llort, 7",
    "sg:city":"Valls",
    "sg:orig_category":"Cristaler\u00cdas",
    "sg:phone":"+34 977 60 13 14",
    "sg:postcode":"43800",
    "sg:province":"Tarragona",
    "wof:name":"Dalmau Masdeu Cb",
    "wof:placetype":"venue"
},
  "geometry": {"coordinates":[1.2495770454,41.2875785828],"type":"Point"}
}