{
  "type": "Feature",
  "properties": {
    "addr:full":"Calle de Eraso, 14 Madrid Madrid 28028",
    "addr:housenumber":"14",
    "addr:postcode":"madrid;28028",
    "addr:street":"Calle De Eraso",
    "iso:country":"ES",
    "sg:address":"Calle de Eraso, 14",
    "sg:city":"Madrid",
    "sg:orig_category":"Artes Gr\u00c1ficas, Artes Pl\u00c1sticas: Material Y Suministros (al Por Menor)",
    "sg:phone":"+34 917 25 68 02",
    "sg:postcode":"28028",
    "sg:province":"Madrid",
    "wof:name":"Lopez Montejo Sandra",
    "wof:placetype":"venue"
},
  "geometry": {"coordinates":[-3.6709589958,40.4340515137],"type":"Point"}
}