{
  "type": "Feature",
  "properties": {
    "addr:full":"Av Diagonal, 281 Barcelona Barcelona 08013",
    "addr:housenumber":"281",
    "addr:postcode":"08013",
    "addr:street":"Av Diagonal",
    "iso:country":"ES",
    "sg:address":"Av Diagonal, 281",
    "sg:city":"Barcelona",
    "sg:orig_category":"Asesor\u00cda Sobre Comunicaci\u00d3n De Empresas",
    "sg:phone":"+34 932 45 05 27",
    "sg:postcode":"08013",
    "sg:province":"Barcelona",
    "wof:name":"Roqueta Rodriguez Angels",
    "wof:placetype":"venue"
},
  "geometry": {"coordinates":[2.1750519276,41.4002532959],"type":"Point"}
}