{
  "type": "Feature",
  "properties": {
    "addr:full":"Psaj Palafox, 2 Calamocha Teruel 44200",
    "addr:housenumber":"2",
    "addr:postcode":"44200",
    "addr:street":"Palafox",
    "iso:country":"ES",
    "sg:address":"Psaj Palafox, 2",
    "sg:city":"Calamocha",
    "sg:classifiers":[
        {
            "category":"Autos & Motor Vehicles",
            "subcategory":"Automobile Sales",
            "type":"Retail Goods"
        }
    ],
    "sg:phone":"+34 978 73 00 33",
    "sg:postcode":"44200",
    "sg:province":"Teruel",
    "wof:name":"Autoescuela Jiloca S. A. L.",
    "wof:placetype":"venue"
},
  "geometry": {"coordinates":[-1.2980790138,40.9189949036],"type":"Point"}
}