{
  "type": "Feature",
  "properties": {
    "addr:full":"Rbla Brasil, 1 Barcelona Barcelona 08028",
    "addr:housenumber":"1",
    "addr:postcode":"08028",
    "addr:street":"Rbla Brasil",
    "iso:country":"ES",
    "sg:address":"Rbla Brasil, 1",
    "sg:city":"Barcelona",
    "sg:orig_category":"Electromedicina: Equipo",
    "sg:phone":"+34 934 91 52 44",
    "sg:postcode":"08028",
    "sg:province":"Barcelona",
    "wof:name":"Benitez Ribas Apolinar",
    "wof:placetype":"venue"
},
  "geometry": {"coordinates":[2.1300361156,41.3756332397],"type":"Point"}
}