{
  "type": "Feature",
  "properties": {
    "iso:country":"ES",
    "sg:address":"Carrer de Carme, 9",
    "sg:city":"Hospitalet Llobregat",
    "sg:orig_category":"Laboratorios Farmac\u00c9uticos",
    "sg:phone":"+34 932 64 09 58",
    "sg:postcode":"08908",
    "sg:province":"Barcelona",
    "wof:name":"Astrazeneca Farmaceutica Spain S.a.",
    "wof:placetype":"venue"
},
  "geometry": {"coordinates":[2.119004488,41.3477859497],"type":"Point"}
}