{
  "type": "Feature",
  "properties": {
    "addr:full":"Calle de Do\u00d1a Maria Barrabino, 16 Torremolinos M\u00e1laga 29620",
    "addr:housenumber":"16",
    "addr:postcode":"29620",
    "addr:street":"Calle De Don\u0303A Maria Barrabino;Ma\u0301Laga",
    "iso:country":"ES",
    "sg:address":"Calle de Do\u00d1a Maria Barrabino, 16",
    "sg:city":"Torremolinos",
    "sg:orig_category":"Asociaciones, Organismos Culturales Y Socioeducativos",
    "sg:phone":"+34 952 37 29 02",
    "sg:postcode":"29620",
    "sg:province":"M\u00e1laga",
    "wof:name":"Ayuntamiento De Torremolinos",
    "wof:placetype":"venue"
},
  "geometry": {"coordinates":[-4.5160393715,36.6265563965],"type":"Point"}
}