{
  "type": "Feature",
  "properties": {
    "addr:full":"Calle de San Onofre, 7 S. Fernando C\u00e1diz 11100",
    "addr:housenumber":"7",
    "addr:postcode":"11100",
    "addr:street":"Calle De San Onofre;S. Fernando Ca\u0301Diz",
    "iso:country":"ES",
    "sg:address":"Calle de San Onofre, 7",
    "sg:city":"S. Fernando",
    "sg:orig_category":"Negocio De Materiales De Construcci\u00d3n",
    "sg:phone":"+34 956 88 32 49",
    "sg:postcode":"11100",
    "sg:province":"C\u00e1diz",
    "wof:name":"Hermanos Garcia S.l.",
    "wof:placetype":"venue"
},
  "geometry": {"coordinates":[-6.1985831261,36.4579811096],"type":"Point"}
}