{
  "type": "Feature",
  "properties": {
    "addr:full":"Calle de Paraiso, 8 Valladolid Valladolid 47003",
    "addr:housenumber":"8",
    "addr:postcode":"47003",
    "addr:street":"Calle De Paraiso",
    "iso:country":"ES",
    "sg:address":"Calle de Paraiso, 8",
    "sg:city":"Valladolid",
    "sg:orig_category":"Artes Gr\u00c1ficas, Artes Pl\u00c1sticas (curso)",
    "sg:phone":"+34 983 29 18 60",
    "sg:postcode":"47003",
    "sg:province":"Valladolid",
    "wof:name":"Graficas Andres Martin S.l.",
    "wof:placetype":"venue"
},
  "geometry": {"coordinates":[-4.7211718559,41.6543273926],"type":"Point"}
}