{
  "type": "Feature",
  "properties": {
    "iso:country":"ES",
    "sg:address":"Ctra Canal, S/n",
    "sg:city":"Deltebre",
    "sg:orig_category":"Aguas (distribuci\u00d3n, Servicios)",
    "sg:phone":"+34 977 48 06 80",
    "sg:postcode":"43580",
    "sg:province":"Tarragona",
    "wof:name":"Comunidad De Regantes Sindicato Agricola",
    "wof:placetype":"venue"
},
  "geometry": {"coordinates":[0.7420939803,40.7212295532],"type":"Point"}
}