{
  "type": "Feature",
  "properties": {
    "iso:country":"ES",
    "sg:address":"Plaz Tercia, 2",
    "sg:city":"Campo Criptana",
    "sg:orig_category":"T\u00c9cnicos Veterinarios",
    "sg:phone":"+34 926 56 05 29",
    "sg:postcode":"13610",
    "sg:province":"Ciudad Real",
    "wof:name":"Reillo Valera Carlos",
    "wof:placetype":"venue"
},
  "geometry": {"coordinates":[-3.1243391037,39.403339386],"type":"Point"}
}