{
  "type": "Feature",
  "properties": {
    "iso:country":"ES",
    "sg:address":"Calle de San Juan, 2",
    "sg:city":"Luanco",
    "sg:orig_category":"Industria Qu\u00cdmica",
    "sg:phone":"+34 985 88 19 62",
    "sg:postcode":"33440",
    "sg:province":"Asturias",
    "wof:name":"Arias Arguelles Alfredo",
    "wof:placetype":"venue"
},
  "geometry": {"coordinates":[-5.7922410965,43.6143455505],"type":"Point"}
}