{
  "type": "Feature",
  "properties": {
    "addr:full":"Calle de Zaragoza, 14 Palmas De Gran Canaria Las Palmas 35012",
    "addr:postcode":"35012",
    "addr:street":"Calle De Zaragoza 14",
    "iso:country":"ES",
    "sg:address":"Calle de Zaragoza, 14",
    "sg:city":"Palmas De Gran Canaria",
    "sg:orig_category":"Alimentaci\u00d3n General (al Por Menor)",
    "sg:phone":"+34 928 20 67 16",
    "sg:postcode":"35012",
    "sg:province":"Las Palmas",
    "wof:name":"Montesdeoca Sanchez Pedro Damian",
    "wof:placetype":"venue"
},
  "geometry": {"coordinates":[-15.4322710037,28.1102962494],"type":"Point"}
}