{
  "type": "Feature",
  "properties": {
    "addr:full":"Calle de Principe De Vergara, 211 Madrid Madrid 28002",
    "addr:housenumber":"211",
    "addr:postcode":"28002",
    "addr:street":"Calle De Principe De Vergara",
    "iso:country":"ES",
    "sg:address":"Calle de Principe De Vergara, 211",
    "sg:city":"Madrid",
    "sg:orig_category":"Inform\u00c1tica (estudios, Servicios, Asesor\u00cda, Formaci\u00d3n)",
    "sg:phone":"+34 915 63 27 55",
    "sg:postcode":"28002",
    "sg:province":"Madrid",
    "wof:name":"Digital Universe Sl",
    "wof:placetype":"venue"
},
  "geometry": {"coordinates":[-3.6777999401,40.4512252808],"type":"Point"}
}