{
  "type": "Feature",
  "properties": {
    "addr:full":"Avda Celanova (de), 110 Valenza Ourense 32002",
    "addr:housenumber":"110",
    "addr:postcode":"32002",
    "addr:street":"Avda Celanova De",
    "iso:country":"ES",
    "sg:address":"Avda Celanova (de), 110",
    "sg:city":"Valenza",
    "sg:orig_category":"Reposter\u00cdas",
    "sg:phone":"+34 988 25 43 09",
    "sg:postcode":"32002",
    "sg:province":"Ourense",
    "wof:name":"Panaderia Sabucedo S.l.",
    "wof:placetype":"venue"
},
  "geometry": {"coordinates":[-7.8814001083,42.3220443726],"type":"Point"}
}