{
  "type": "Feature",
  "properties": {
    "addr:full":"Calle de Canillas, 37 Madrid Madrid 28002",
    "addr:housenumber":"37",
    "addr:postcode":"madrid;28002",
    "addr:street":"Calle De Canillas",
    "iso:country":"ES",
    "sg:address":"Calle de Canillas, 37",
    "sg:city":"Madrid",
    "sg:orig_category":"Asociaciones Y Clubs Deportivos",
    "sg:phone":"+34 915 64 62 66",
    "sg:postcode":"28002",
    "sg:province":"Madrid",
    "sg:website":"www.curvas.com",
    "wof:name":"Ardus S.l.",
    "wof:placetype":"venue"
},
  "geometry": {"coordinates":[-3.6742660999,40.4425773621],"type":"Point"}
}