{
  "type": "Feature",
  "properties": {
    "addr:full":"Pl Font De La Manxa, 7 Valls Tarragona 43800",
    "addr:housenumber":"7",
    "addr:postcode":"43800",
    "addr:street":"Pl",
    "iso:country":"ES",
    "sg:address":"Pl Font De La Manxa, 7",
    "sg:city":"Valls",
    "sg:orig_category":"Herboristas (al Por Menor)",
    "sg:phone":"+34 977 60 70 94",
    "sg:postcode":"43800",
    "sg:province":"Tarragona",
    "wof:name":"Simon De Sande Maria Jesus",
    "wof:placetype":"venue"
},
  "geometry": {"coordinates":[1.2525299788,41.2871513367],"type":"Point"}
}