{
  "type": "Feature",
  "properties": {
    "iso:country":"ES",
    "sg:address":"Av Xile, 5",
    "sg:city":"Sant Cristofol Les Fonts",
    "sg:orig_category":"Electrodom\u00c9sticos (al Por Menor)",
    "sg:phone":"+34 972 26 42 31",
    "sg:postcode":"17800",
    "sg:province":"Girona",
    "wof:name":"Masso Aiguabella Miguel",
    "wof:placetype":"venue"
},
  "geometry": {"coordinates":[2.4893848896,42.1809463501],"type":"Point"}
}