{
  "type": "Feature",
  "properties": {
    "iso:country":"ES",
    "sg:address":"Calle de Vall D'albaida, 20",
    "sg:city":"Mislata",
    "sg:orig_category":"Fabricaci\u00d3n De Ropa De Deportes",
    "sg:phone":"+34 963 70 49 52",
    "sg:postcode":"46920",
    "sg:province":"Valencia",
    "wof:name":"Confecciones Ascival S.l.",
    "wof:placetype":"venue"
},
  "geometry": {"coordinates":[-0.425056994,39.4778366089],"type":"Point"}
}