{
  "type": "Feature",
  "properties": {
    "iso:country":"ES",
    "sg:address":"Pase Yeserias, 33",
    "sg:city":"Madrid",
    "sg:orig_category":"Asesor\u00cda Fiscal Y Jur\u00cddica",
    "sg:phone":"+34 915 17 46 08",
    "sg:postcode":"28005",
    "sg:province":"Madrid",
    "wof:name":"Sefade Sociedad Cooperativa",
    "wof:placetype":"venue"
},
  "geometry": {"coordinates":[-3.7082240582,40.3983078003],"type":"Point"}
}