{
  "type": "Feature",
  "properties": {
    "iso:country":"ES",
    "sg:address":"Calle de Cipriano Larra\u00d1aga, S/n",
    "sg:city":"Irun",
    "sg:orig_category":"Centros Empresariales",
    "sg:phone":"+34 943 61 87 51",
    "sg:postcode":"20302",
    "sg:province":"Guip\u00f9zcoa",
    "wof:name":"P.a.m. S.l. Unipersonal",
    "wof:placetype":"venue"
},
  "geometry": {"coordinates":[-1.7945772409,43.3410606384],"type":"Point"}
}