{
  "type": "Feature",
  "properties": {
    "addr:full":"Calle de San Mateo, 9 Marchamalo Guadalajara 19180",
    "addr:housenumber":"9",
    "addr:postcode":"19180",
    "addr:street":"Calle De San Mateo",
    "iso:country":"ES",
    "sg:address":"Calle de San Mateo, 9",
    "sg:city":"Marchamalo",
    "sg:orig_category":"Empresas De Carpinter\u00cda De Madera",
    "sg:phone":"+34 949 25 04 47",
    "sg:postcode":"19180",
    "sg:province":"Guadalajara",
    "wof:name":"Oliveros Lozano Jose Maria",
    "wof:placetype":"venue"
},
  "geometry": {"coordinates":[-3.2037949562,40.6702728271],"type":"Point"}
}