{
  "type": "Feature",
  "properties": {
    "iso:country":"ES",
    "sg:address":"Ctra Madrid-cadiz, Km. 0320,0",
    "sg:city":"Andujar",
    "sg:orig_category":"Fabrica De Cer\u00c1micas",
    "sg:phone":"+34 953 50 16 97",
    "sg:postcode":"23740",
    "sg:province":"Ja\u00e9n",
    "wof:name":"Ceramica Iliturgitana Mu\u00f1oz S.l.",
    "wof:placetype":"venue"
},
  "geometry": {"coordinates":[-4.062543869,38.0306167603],"type":"Point"}
}