{
  "type": "Feature",
  "properties": {
    "iso:country":"ES",
    "sg:address":"Avda Logro\u00d1o, 21",
    "sg:city":"Haro",
    "sg:orig_category":"Mec\u00c1nico Del Autom\u00d3vil",
    "sg:phone":"+34 941 31 12 43",
    "sg:postcode":"26200",
    "sg:province":"La Rioja",
    "wof:name":"Talleres Auto Tractor S.l.",
    "wof:placetype":"venue"
},
  "geometry": {"coordinates":[-2.8423631191,42.5687713623],"type":"Point"}
}