{
  "type": "Feature",
  "properties": {
    "addr:full":"Avda Burjasot, 94 Valencia Valencia 46009",
    "addr:housenumber":"94",
    "addr:postcode":"46009",
    "addr:street":"Avda Burjasot",
    "iso:country":"ES",
    "sg:address":"Avda Burjasot, 94",
    "sg:city":"Valencia",
    "sg:orig_category":"Peluqueros: De Se\u00d1oras",
    "sg:phone":"+34 963 40 16 35",
    "sg:postcode":"46009",
    "sg:province":"Valencia",
    "wof:name":"Prades Diaz Concepcion",
    "wof:placetype":"venue"
},
  "geometry": {"coordinates":[-0.3878329992,39.4872703552],"type":"Point"}
}