{
  "type": "Feature",
  "properties": {
    "iso:country":"ES",
    "sg:address":"C/ Cami (el), 45",
    "sg:city":"Alcoi",
    "sg:orig_category":"Alimentaci\u00d3n General (al Por Menor)",
    "sg:phone":"+34 965 54 21 51",
    "sg:postcode":"03801",
    "sg:province":"Alicante",
    "wof:name":"Juan Fornes Fornes S.a.",
    "wof:placetype":"venue"
},
  "geometry": {"coordinates":[-0.4751479924,38.6929283142],"type":"Point"}
}