{
  "type": "Feature",
  "properties": {
    "iso:country":"ES",
    "sg:address":"Calle de Tegaso, 15",
    "sg:city":"Arrecife",
    "sg:orig_category":"Contenedores (mercanc\u00cdas)",
    "sg:phone":"+34 928 81 48 98",
    "sg:postcode":"35500",
    "sg:province":"Las Palmas",
    "wof:name":"Martin Machado Lorenzo Martin",
    "wof:placetype":"venue"
},
  "geometry": {"coordinates":[-13.5561800003,28.9736099243],"type":"Point"}
}