{
  "type": "Feature",
  "properties": {
    "iso:country":"ES",
    "sg:address":"Calle de Rio Pisuerga, 2",
    "sg:city":"Avila",
    "sg:orig_category":"Agentes, Concesionarios Y Sucursales De Veh\u00cdculos",
    "sg:phone":"+34 920 35 29 88",
    "sg:postcode":"05004",
    "sg:province":"\u00c1vila",
    "wof:name":"Gomez Francisco Javier Alvarez",
    "wof:placetype":"venue"
},
  "geometry": {"coordinates":[-4.6882328987,40.671546936],"type":"Point"}
}