{
  "type": "Feature",
  "properties": {
    "addr:full":"Carr Manises, 28 Aldaia Valencia 46960",
    "addr:housenumber":"28",
    "addr:postcode":"46960",
    "addr:street":"Carr Manises",
    "iso:country":"ES",
    "sg:address":"Carr Manises, 28",
    "sg:city":"Aldaia",
    "sg:orig_category":"Reposter\u00cdas",
    "sg:phone":"+34 961 50 14 42",
    "sg:postcode":"46960",
    "sg:province":"Valencia",
    "wof:name":"Sancho Usedo Remigio",
    "wof:placetype":"venue"
},
  "geometry": {"coordinates":[-0.4634059966,39.4676933289],"type":"Point"}
}