{
  "type": "Feature",
  "properties": {
    "iso:country":"ES",
    "sg:address":"Plaz Casilla, 7",
    "sg:city":"Bilbao",
    "sg:orig_category":"Librer\u00cdas",
    "sg:phone":"+34 944 21 61 80",
    "sg:postcode":"48012",
    "sg:province":"Vizcaya",
    "wof:name":"Uyarra Escudero Jose Miguel",
    "wof:placetype":"venue"
},
  "geometry": {"coordinates":[-2.9430770874,43.2568435669],"type":"Point"}
}