{
  "type": "Feature",
  "properties": {
    "addr:full":"Calle de Francisco Vitoria, 30 Zaragoza Zaragoza 50008",
    "addr:housenumber":"30",
    "addr:postcode":"50008",
    "addr:street":"Calle De Francisco Vitoria",
    "iso:country":"ES",
    "sg:address":"Calle de Francisco Vitoria, 30",
    "sg:city":"Zaragoza",
    "sg:orig_category":"Agencias Y Agentes Comerciales, Representantes",
    "sg:phone":"+34 976 22 02 09",
    "sg:postcode":"50008",
    "sg:province":"Zaragoza",
    "wof:name":"Blasco Lopez Maria Angel",
    "wof:placetype":"venue"
},
  "geometry": {"coordinates":[-0.8789659739,41.6447525024],"type":"Point"}
}