{
  "type": "Feature",
  "properties": {
    "iso:country":"ES",
    "sg:address":"Carrer de Pius Xii, 22",
    "sg:city":"Cornella Llobregat",
    "sg:orig_category":"Peluquer\u00cdas, Peluquer\u00cda Mixta",
    "sg:phone":"+34 933 77 90 53",
    "sg:postcode":"08940",
    "sg:province":"Barcelona",
    "wof:name":"Rubia Delgado Agustin De La",
    "wof:placetype":"venue"
},
  "geometry": {"coordinates":[2.0675449371,41.3556251526],"type":"Point"}
}