{
  "type": "Feature",
  "properties": {
    "addr:full":"Carr Sant Joan Baptista La Salle, 34 Girona Girona 17002",
    "addr:housenumber":"34",
    "addr:postcode":"17002",
    "addr:street":"Carr Sant Joan Baptista La Salle",
    "iso:country":"ES",
    "sg:address":"Carr Sant Joan Baptista La Salle, 34",
    "sg:city":"Girona",
    "sg:orig_category":"Doctores En Medicina",
    "sg:phone":"+34 972 20 08 72",
    "sg:postcode":"17002",
    "sg:province":"Girona",
    "wof:name":"Oduber Munta\u00f1ola Luis Francisco",
    "wof:placetype":"venue"
},
  "geometry": {"coordinates":[2.8184940815,41.9780921936],"type":"Point"}
}