{
  "type": "Feature",
  "properties": {
    "addr:full":"Carrer de Industria, S/n Mas Rampinyo Barcelona 08110",
    "addr:postcode":"08110",
    "addr:street":"Carrer De Industria S / N Mas Rampinyo",
    "iso:country":"ES",
    "sg:address":"Carrer de Industria, S/n",
    "sg:city":"Mas Rampinyo",
    "sg:orig_category":"Negocio De Materiales De Construcci\u00d3n",
    "sg:phone":"+34 935 75 17 61",
    "sg:postcode":"08110",
    "sg:province":"Barcelona",
    "wof:name":"Acabados De Obras Y Construcciones S.a.",
    "wof:placetype":"venue"
},
  "geometry": {"coordinates":[2.179281,41.492199],"type":"Point"}
}