{
  "type": "Feature",
  "properties": {
    "iso:country":"ES",
    "sg:address":"Avda Portugal, 98",
    "sg:city":"Salamanca",
    "sg:orig_category":"M\u00c9dicos: Pediatr\u00cda. Enfermedades De Los Ni\u00d1os",
    "sg:phone":"+34 923 23 32 30",
    "sg:postcode":"37005",
    "sg:province":"Salamanca",
    "wof:name":"Zakour  Polos Gorgi",
    "wof:placetype":"venue"
},
  "geometry": {"coordinates":[-5.6611208916,40.9720916748],"type":"Point"}
}