{
  "type": "Feature",
  "properties": {
    "iso:country":"ES",
    "sg:address":"Carrer de Vinyals, 145",
    "sg:city":"Terrassa",
    "sg:orig_category":"Asesor\u00cda Sobre Comunicaci\u00d3n De Empresas",
    "sg:phone":"+34 937 89 37 71",
    "sg:postcode":"08221",
    "sg:province":"Barcelona",
    "wof:name":"Catalu\u00f1a Asesores Scp",
    "wof:placetype":"venue"
},
  "geometry": {"coordinates":[2.0084860325,41.5574531555],"type":"Point"}
}