{
  "type": "Feature",
  "properties": {
    "addr:full":"Calle de Gustavo Bacarisas, 4 Sevilla Sevilla 41010",
    "addr:housenumber":"4",
    "addr:postcode":"41010",
    "addr:street":"Calle De Gustavo Bacarisas",
    "iso:country":"ES",
    "sg:address":"Calle de Gustavo Bacarisas, 4",
    "sg:city":"Sevilla",
    "sg:orig_category":"Peluquer\u00cdas, Peluquer\u00cda Mixta",
    "sg:phone":"+34 954 27 89 11",
    "sg:postcode":"41010",
    "sg:province":"Sevilla",
    "wof:name":"Banda Pichardo Maria Jose",
    "wof:placetype":"venue"
},
  "geometry": {"coordinates":[-5.9991059303,37.3801422119],"type":"Point"}
}