{
  "type": "Feature",
  "properties": {
    "iso:country":"ES",
    "sg:address":"Avda Doctor Galvez Ginachero, 10",
    "sg:city":"Malaga",
    "sg:orig_category":"Molduras, Junquillos, Listones Y Molduras Perforadas",
    "sg:phone":"+34 952 27 00 88",
    "sg:postcode":"29009",
    "sg:province":"M\u00e1laga",
    "wof:name":"Lopez Flores Antonio",
    "wof:placetype":"venue"
},
  "geometry": {"coordinates":[-4.4292159081,36.7270240784],"type":"Point"}
}