{
  "type": "Feature",
  "properties": {
    "iso:country":"ES",
    "sg:address":"Carrer de Carme, 69",
    "sg:city":"Barcelona",
    "sg:orig_category":"Molduras, Junquillos, Listones Y Molduras Perforadas",
    "sg:phone":"+34 934 42 50 48",
    "sg:postcode":"08001",
    "sg:province":"Barcelona",
    "wof:name":"Berlinches Berlinches Prudencio",
    "wof:placetype":"venue"
},
  "geometry": {"coordinates":[2.1677560806,41.3807563782],"type":"Point"}
}