{
  "type": "Feature",
  "properties": {
    "addr:full":"Avda America, 8 Madrid Madrid 28028",
    "addr:housenumber":"8",
    "addr:postcode":"madrid;28028",
    "addr:street":"Avda America",
    "iso:country":"ES",
    "sg:address":"Avda America, 8",
    "sg:city":"Madrid",
    "sg:orig_category":"M\u00c9dicos: Estomatolog\u00cda",
    "sg:phone":"+34 913 56 29 16",
    "sg:postcode":"28028",
    "sg:province":"Madrid",
    "wof:name":"Acero Sanz Carlos",
    "wof:placetype":"venue"
},
  "geometry": {"coordinates":[-3.676394701,40.4378623962],"type":"Point"}
}