{
  "type": "Feature",
  "properties": {
    "iso:country":"ES",
    "sg:address":"Calle de Pablo Gargallo, 43",
    "sg:city":"Madrid",
    "sg:orig_category":"Electrodom\u00c9sticos (fabricaci\u00d3n, Al Por Mayor)",
    "sg:phone":"+34 913 16 85 35",
    "sg:postcode":"28035",
    "sg:province":"Madrid",
    "wof:name":"Gidron Kalka Ron",
    "wof:placetype":"venue"
},
  "geometry": {"coordinates":[-3.73467803,40.4760246277],"type":"Point"}
}