{
  "type": "Feature",
  "properties": {
    "addr:full":"Calle de Arboledas, 32 Illescas Toledo 45200",
    "addr:housenumber":"32",
    "addr:postcode":"45200",
    "addr:street":"Calle De Arboledas",
    "iso:country":"ES",
    "sg:address":"Calle de Arboledas, 32",
    "sg:city":"Illescas",
    "sg:orig_category":"Empresas De Portes Y Mensajer\u00cda",
    "sg:phone":"+34 925 51 20 59",
    "sg:postcode":"45200",
    "sg:province":"Toledo",
    "wof:name":"Martin Perez Carmen",
    "wof:placetype":"venue"
},
  "geometry": {"coordinates":[-3.849303484,40.1289176941],"type":"Point"}
}