{
  "type": "Feature",
  "properties": {
    "iso:country":"ES",
    "sg:address":"Calle de Joaquin Maria Jalon, 15",
    "sg:city":"Valladolid",
    "sg:orig_category":"Ropa Para Se\u00d1oras Y Caballeros (al Por Menor)",
    "sg:phone":"+34 983 22 14 18",
    "sg:postcode":"47008",
    "sg:province":"Valladolid",
    "wof:name":"Alonso Martinez Regino",
    "wof:placetype":"venue"
},
  "geometry": {"coordinates":[-4.7411422729,41.6280555725],"type":"Point"}
}