{
  "type": "Feature",
  "properties": {
    "iso:country":"ES",
    "sg:address":"Avda Gomez Ferrer (doctor), 53",
    "sg:city":"Catarroja",
    "sg:orig_category":"Agencias Y Agentes Comerciales, Representantes",
    "sg:phone":"+34 961 26 12 00",
    "sg:postcode":"46470",
    "sg:province":"Valencia",
    "wof:name":"Soler Asuncion Jose Maria",
    "wof:placetype":"venue"
},
  "geometry": {"coordinates":[-0.3995490074,39.4042320251],"type":"Point"}
}