{
  "type": "Feature",
  "properties": {
    "addr:full":"Calle de Mayor Baja, 7 Crivillen Teruel 44557",
    "addr:housenumber":"7",
    "addr:postcode":"44557",
    "addr:street":"Calle De Mayor Baja",
    "iso:country":"ES",
    "sg:address":"Calle de Mayor Baja, 7",
    "sg:city":"Crivillen",
    "sg:orig_category":"Empresas De Pintura Y Revestimientos",
    "sg:phone":"+34 978 84 92 15",
    "sg:postcode":"44557",
    "sg:province":"Teruel",
    "wof:name":"Gines Lecina Jose Luis",
    "wof:placetype":"venue"
},
  "geometry": {"coordinates":[-0.5769860148,40.8829727173],"type":"Point"}
}