{
  "type": "Feature",
  "properties": {
    "iso:country":"ES",
    "sg:address":"Pg Torras I Bages, 14",
    "sg:city":"Barcelona",
    "sg:orig_category":"Agencias De Viajes",
    "sg:phone":"+34 933 45 40 50",
    "sg:postcode":"08030",
    "sg:province":"Barcelona",
    "wof:name":"Viajes Visamar S. A.",
    "wof:placetype":"venue"
},
  "geometry": {"coordinates":[2.1913740635,41.4369354248],"type":"Point"}
}