{
  "type": "Feature",
  "properties": {
    "addr:full":"Urbanizacion Los Picos, S/n Colombres Asturias 33590",
    "addr:housenumber":"s / n",
    "addr:postcode":"33590",
    "addr:street":"Urbanizacion;Picos",
    "iso:country":"ES",
    "sg:address":"Urbanizacion Los Picos, S/n",
    "sg:city":"Colombres",
    "sg:orig_category":"Publicidad (edici\u00d3n)",
    "sg:phone":"+34 985 41 30 10",
    "sg:postcode":"33590",
    "sg:province":"Asturias",
    "wof:name":"Soberon Perez Sonia",
    "wof:placetype":"venue"
},
  "geometry": {"coordinates":[-4.5418791771,43.3740348816],"type":"Point"}
}