{
  "type": "Feature",
  "properties": {
    "iso:country":"ES",
    "sg:address":"Carrer de Nou De Sant Francesc, 17",
    "sg:city":"Barcelona",
    "sg:orig_category":"Ingeniero",
    "sg:phone":"+34 933 17 64 19",
    "sg:postcode":"08002",
    "sg:province":"Barcelona",
    "wof:name":"Bagh Tecnica S.l.",
    "wof:placetype":"venue"
},
  "geometry": {"coordinates":[2.1777150631,41.3789291382],"type":"Point"}
}