{
  "type": "Feature",
  "properties": {
    "addr:full":"Avda Barcelona, 109 Cuevas Almanzora Almer\u00eda 04610",
    "addr:housenumber":"109",
    "addr:postcode":"04610",
    "addr:street":"Avda Barcelona;Almeri\u0301A",
    "iso:country":"ES",
    "sg:address":"Avda Barcelona, 109",
    "sg:city":"Cuevas Almanzora",
    "sg:orig_category":"Farmacias",
    "sg:phone":"+34 950 45 63 39",
    "sg:postcode":"04610",
    "sg:province":"Almer\u00eda",
    "wof:name":"Padua Arcos Daniel",
    "wof:placetype":"venue"
},
  "geometry": {"coordinates":[-1.8748179674,37.2939491272],"type":"Point"}
}