{
  "type": "Feature",
  "properties": {
    "addr:full":"Calle de Vereda De La Alcaidia, 2 Cordoba C\u00f3rdoba 14007",
    "addr:housenumber":"2",
    "addr:postcode":"14007",
    "addr:street":"Calle De Vereda De La Alcaidia;Co\u0301Rdoba",
    "iso:country":"ES",
    "sg:address":"Calle de Vereda De La Alcaidia, 2",
    "sg:city":"Cordoba",
    "sg:orig_category":"Ingenier\u00cda, Centros De Estudios (diversos)",
    "sg:phone":"+34 957 26 98 26",
    "sg:postcode":"14007",
    "sg:province":"C\u00f3rdoba",
    "wof:name":"Morales Viudez Diego",
    "wof:placetype":"venue"
},
  "geometry": {"coordinates":[-4.754971981,37.8971214294],"type":"Point"}
}