{
  "type": "Feature",
  "properties": {
    "addr:full":"Avda Juan Carlos I, S/n Cristianos Santa Cruz De Tenerife 38650",
    "addr:housenumber":"s / n",
    "addr:postcode":"38650",
    "addr:street":"Avda Juan Carlos I",
    "iso:country":"ES",
    "sg:address":"Avda Juan Carlos I, S/n",
    "sg:city":"Cristianos",
    "sg:orig_category":"Sociedades, Compa\u00d1\u00cdas Aseguradoras",
    "sg:phone":"+34 922 75 28 70",
    "sg:postcode":"38650",
    "sg:province":"Santa Cruz De Tenerife",
    "wof:name":"Euroteide Seguros S.l.",
    "wof:placetype":"venue"
},
  "geometry": {"coordinates":[-16.7118148804,28.0564250946],"type":"Point"}
}