{
  "type": "Feature",
  "properties": {
    "addr:full":"Calle de Danza Prima, 16 Pola De Siero Asturias 33510",
    "addr:housenumber":"16",
    "addr:postcode":"33510",
    "addr:street":"Calle De Danza Prima",
    "iso:country":"ES",
    "sg:address":"Calle de Danza Prima, 16",
    "sg:city":"Pola De Siero",
    "sg:orig_category":"Mutuas De Seguros",
    "sg:phone":"+34 985 72 43 56",
    "sg:postcode":"33510",
    "sg:province":"Asturias",
    "wof:name":"Montepio De La Mineria Asturiana Del Car",
    "wof:placetype":"venue"
},
  "geometry": {"coordinates":[-5.6646547318,43.390411377],"type":"Point"}
}