{
  "type": "Feature",
  "properties": {
    "addr:full":"Calle de Hernan Cortes, 21 Santander Cantabria 39003",
    "addr:housenumber":"21",
    "addr:postcode":"39003",
    "addr:street":"Calle De Hernan Cortes",
    "iso:country":"ES",
    "sg:address":"Calle de Hernan Cortes, 21",
    "sg:city":"Santander",
    "sg:orig_category":"Caf\u00c9s, Bares, Cervecer\u00cdas",
    "sg:phone":"+34 942 22 09 49",
    "sg:postcode":"39003",
    "sg:province":"Cantabria",
    "wof:name":"Cafe Bar La Vi\u00f1a S.l.",
    "wof:placetype":"venue"
},
  "geometry": {"coordinates":[-3.8022680283,43.4628562927],"type":"Point"}
}