{
  "type": "Feature",
  "properties": {
    "iso:country":"ES",
    "sg:address":"Calle de Adelantado, 18",
    "sg:city":"Sevilla",
    "sg:orig_category":"Farmacias",
    "sg:phone":"+34 954 37 72 86",
    "sg:postcode":"41009",
    "sg:province":"Sevilla",
    "wof:name":"Alvarez Jimenez Jose Maria",
    "wof:placetype":"venue"
},
  "geometry": {"coordinates":[-5.9917497635,37.4040145874],"type":"Point"}
}