{
  "type": "Feature",
  "properties": {
    "addr:full":"Carrer de Baro De Malda, 15 Hospitalet Llobregat Barcelona 08901",
    "addr:housenumber":"15",
    "addr:postcode":"08901",
    "addr:street":"Carrer De Baro De Malda",
    "iso:country":"ES",
    "sg:address":"Carrer de Baro De Malda, 15",
    "sg:city":"Hospitalet Llobregat",
    "sg:orig_category":"Asesor\u00cda Sobre Comunicaci\u00d3n De Empresas",
    "sg:phone":"+34 932 61 22 70",
    "sg:postcode":"08901",
    "sg:province":"Barcelona",
    "wof:name":"Perello Valles Assessors S.l.",
    "wof:placetype":"venue"
},
  "geometry": {"coordinates":[2.0999729633,41.3605766296],"type":"Point"}
}