{
  "type": "Feature",
  "properties": {
    "iso:country":"ES",
    "sg:address":"Calle de Fuenlabrada, 19",
    "sg:city":"Getafe",
    "sg:orig_category":"Arquitectos",
    "sg:phone":"+34 916 01 90 43",
    "sg:postcode":"28901",
    "sg:province":"Madrid",
    "wof:name":"Sanchez Guillen Mariano",
    "wof:placetype":"venue"
},
  "geometry": {"coordinates":[-3.7338290215,40.3028831482],"type":"Point"}
}