{
  "type": "Feature",
  "properties": {
    "iso:country":"ES",
    "sg:address":"Calle de Diana, 9",
    "sg:city":"Sagunt",
    "sg:orig_category":"Centros M\u00c9dicos Y Sociales, Dispensarios",
    "sg:phone":"+34 962 66 39 58",
    "sg:postcode":"46500",
    "sg:province":"Valencia",
    "wof:name":"Centro De Reconocimientos Medico-spicologicos Diana",
    "wof:placetype":"venue"
},
  "geometry": {"coordinates":[-0.2781789899,39.6822319031],"type":"Point"}
}