{
  "type": "Feature",
  "properties": {
    "addr:full":"Carrer de Raval, 14 Poboleda Tarragona 43376",
    "addr:housenumber":"14",
    "addr:postcode":"43376",
    "addr:street":"Carrer De Raval",
    "iso:country":"ES",
    "sg:address":"Carrer de Raval, 14",
    "sg:city":"Poboleda",
    "sg:orig_category":"Carnicer\u00cdas, Carnicer\u00cdas",
    "sg:phone":"+34 977 82 70 43",
    "sg:postcode":"43376",
    "sg:province":"Tarragona",
    "wof:name":"Vaque Lillo Juan Manuel",
    "wof:placetype":"venue"
},
  "geometry": {"coordinates":[0.8458030224,41.2337226868],"type":"Point"}
}