{
  "type": "Feature",
  "properties": {
    "iso:country":"ES",
    "sg:address":"Calle de Maestro Palau, 97",
    "sg:city":"Paiporta",
    "sg:orig_category":"Motocicletas (agentes, Concesionarios)",
    "sg:phone":"+34 963 97 90 21",
    "sg:postcode":"46200",
    "sg:province":"Valencia",
    "wof:name":"Racing Motos Paiporta S.l.",
    "wof:placetype":"venue"
},
  "geometry": {"coordinates":[-0.4144090116,39.4315414429],"type":"Point"}
}