{
  "type": "Feature",
  "properties": {
    "addr:full":"Poli Industrial San Valero, 4 Cartuja Baja Zaragoza 50720",
    "addr:housenumber":"4",
    "addr:postcode":"50720",
    "addr:street":"San Valero;Baja",
    "iso:country":"ES",
    "sg:address":"Poli Industrial San Valero, 4",
    "sg:city":"Cartuja Baja",
    "sg:orig_category":"Herramientas Y Suministros Para Plomeros",
    "sg:phone":"+34 976 50 03 16",
    "sg:postcode":"50720",
    "sg:province":"Zaragoza",
    "wof:name":"Conducciones Hidro Aragonesas S.l.",
    "wof:placetype":"venue"
},
  "geometry": {"coordinates":[-0.8236089945,41.602935791],"type":"Point"}
}