{
  "type": "Feature",
  "properties": {
    "addr:full":"Praz Fonseca (de), 3 Santiago De Compostela La Coru\u00f1a 15705",
    "addr:housenumber":"3",
    "addr:postcode":"15705",
    "addr:street":"Praz Fonseca De;Corun\u0303A",
    "iso:country":"ES",
    "sg:address":"Praz Fonseca (de), 3",
    "sg:city":"Santiago De Compostela",
    "sg:orig_category":"Servicios Diversos",
    "sg:phone":"+34 981 57 53 13",
    "sg:postcode":"15705",
    "sg:province":"La Coru\u00f1a",
    "sg:website":"www.dehistoria.net",
    "wof:name":"Dehistoria S.l.l",
    "wof:placetype":"venue"
},
  "geometry": {"coordinates":[-8.5449934006,42.8793945312],"type":"Point"}
}