{
  "type": "Feature",
  "properties": {
    "iso:country":"ES",
    "sg:address":"Carr Donzelles, 2",
    "sg:city":"Bisbal D'emporda",
    "sg:orig_category":"Carnicer\u00cdas, Carnicer\u00cdas",
    "sg:phone":"+34 972 64 04 36",
    "sg:postcode":"17100",
    "sg:province":"Girona",
    "wof:name":"Clos Codina Pere",
    "wof:placetype":"venue"
},
  "geometry": {"coordinates":[2.8243288994,41.9838523865],"type":"Point"}
}