{
  "type": "Feature",
  "properties": {
    "addr:full":"Calle de Jose Maria Iparragirre, 9 Vitoria-gasteiz \u00c1lava 01006",
    "addr:housenumber":"9",
    "addr:postcode":"01006",
    "addr:street":"Calle De Jose Maria Iparragirre",
    "iso:country":"ES",
    "sg:address":"Calle de Jose Maria Iparragirre, 9",
    "sg:city":"Vitoria-gasteiz",
    "sg:orig_category":"Suministros Y Materiales Industriales",
    "sg:phone":"+34 945 13 67 62",
    "sg:postcode":"01006",
    "sg:province":"\u00c1lava",
    "wof:name":"Mecanizados De Precision Oscar S.l.",
    "wof:placetype":"venue"
},
  "geometry": {"coordinates":[-2.6597790718,42.8379020691],"type":"Point"}
}