{
  "type": "Feature",
  "properties": {
    "iso:country":"ES",
    "sg:address":"Carrer de Calabria, 25",
    "sg:city":"Barcelona",
    "sg:orig_category":"Farmacias",
    "sg:phone":"+34 934 23 02 26",
    "sg:postcode":"08015",
    "sg:province":"Barcelona",
    "wof:name":"De Ciurana Ribas Teresa",
    "wof:placetype":"venue"
},
  "geometry": {"coordinates":[2.1592469215,41.3763198853],"type":"Point"}
}