{
  "type": "Feature",
  "properties": {
    "addr:full":"Avda Done Erroke Etorbidea, 22 Amurrio \u00c1lava 01470",
    "addr:housenumber":"22",
    "addr:postcode":"01470",
    "addr:street":"Avda Done Erroke Etorbidea",
    "iso:country":"ES",
    "sg:address":"Avda Done Erroke Etorbidea, 22",
    "sg:city":"Amurrio",
    "sg:orig_category":"Restaurantes",
    "sg:phone":"+34 945 89 09 49",
    "sg:postcode":"01470",
    "sg:province":"\u00c1lava",
    "wof:name":"Restaurante Ruperto S.c.",
    "wof:placetype":"venue"
},
  "geometry": {"coordinates":[-3.0217339993,43.0432891846],"type":"Point"}
}