{
  "type": "Feature",
  "properties": {
    "addr:full":"Calle de Miguel Yuste, 11 Madrid Madrid 28037",
    "addr:housenumber":"11",
    "addr:postcode":"madrid;28037",
    "addr:street":"Calle De Miguel Yuste",
    "iso:country":"ES",
    "sg:address":"Calle de Miguel Yuste, 11",
    "sg:city":"Madrid",
    "sg:orig_category":"Agencias Y Asesores De Publicidad",
    "sg:phone":"+34 914 40 00 98",
    "sg:postcode":"28037",
    "sg:province":"Madrid",
    "wof:name":"Creaciones Elba S.a.",
    "wof:placetype":"venue"
},
  "geometry": {"coordinates":[-3.6250100136,40.4402389526],"type":"Point"}
}