{
  "type": "Feature",
  "properties": {
    "addr:full":"Carr Sant Antoni, 8 Villarreal Castell\u00f3n 12540",
    "addr:housenumber":"8",
    "addr:postcode":"12540",
    "addr:street":"Carr Sant Antoni",
    "iso:country":"ES",
    "sg:address":"Carr Sant Antoni, 8",
    "sg:city":"Villarreal",
    "sg:orig_category":"Cristaler\u00cdas",
    "sg:phone":"+34 964 53 07 07",
    "sg:postcode":"12540",
    "sg:province":"Castell\u00f3n",
    "wof:name":"Orenga Benet Noelia",
    "wof:placetype":"venue"
},
  "geometry": {"coordinates":[-0.0952939987,39.9453048706],"type":"Point"}
}