{
  "type": "Feature",
  "properties": {
    "addr:full":"Rua Libertade, 17 Viana Do Bolo Ourense 32550",
    "addr:housenumber":"17",
    "addr:postcode":"32550",
    "addr:street":"Rua Libertade",
    "iso:country":"ES",
    "sg:address":"Rua Libertade, 17",
    "sg:city":"Viana Do Bolo",
    "sg:orig_category":"Empresas De Carpinter\u00cda Met\u00c1lica",
    "sg:phone":"+34 988 34 02 74",
    "sg:postcode":"32550",
    "sg:province":"Ourense",
    "wof:name":"Amadeo Hermanos S.l.",
    "wof:placetype":"venue"
},
  "geometry": {"coordinates":[-7.1121230125,42.1813774109],"type":"Point"}
}