{
  "type": "Feature",
  "properties": {
    "iso:country":"ES",
    "sg:address":"Pol I. La Pera, 4",
    "sg:city":"Pera",
    "sg:orig_category":"Frutas Y Legumbres Secas (al Por Mayor)",
    "sg:phone":"+34 972 48 90 20",
    "sg:postcode":"17120",
    "sg:province":"Girona",
    "wof:name":"Fruits Secs L'esquirol S.l.",
    "wof:placetype":"venue"
},
  "geometry": {"coordinates":[2.9733500481,42.020401001],"type":"Point"}
}