{
  "type": "Feature",
  "properties": {
    "iso:country":"ES",
    "sg:address":"Calle de Isabel Ii, 8",
    "sg:city":"Santander",
    "sg:orig_category":"Estilistas Y Estudios De Estilo De Corte Y Confecci\u00d3n",
    "sg:phone":"+34 942 22 26 21",
    "sg:postcode":"39002",
    "sg:province":"Cantabria",
    "wof:name":"Las Antillas S. A.",
    "wof:placetype":"venue"
},
  "geometry": {"coordinates":[-3.8093802929,43.4610786438],"type":"Point"}
}