{
  "type": "Feature",
  "properties": {
    "addr:full":"Carrer de Pere Iv, 120 Barcelona Barcelona 08005",
    "addr:housenumber":"120",
    "addr:postcode":"08005",
    "addr:street":"Carrer De Pere Iv",
    "iso:country":"ES",
    "sg:address":"Carrer de Pere Iv, 120",
    "sg:city":"Barcelona",
    "sg:orig_category":"Cervecer\u00cdas",
    "sg:phone":"+34 933 09 50 29",
    "sg:postcode":"08005",
    "sg:province":"Barcelona",
    "wof:name":"Ordal Recreatius S.l.",
    "wof:placetype":"venue"
},
  "geometry": {"coordinates":[2.1956419945,41.4000091553],"type":"Point"}
}