{
  "type": "Feature",
  "properties": {
    "iso:country":"ES",
    "sg:address":"Calle de Arquitecto Tioda, 13",
    "sg:city":"Oviedo",
    "sg:orig_category":"Inversiones",
    "sg:phone":"+34 985 25 69 61",
    "sg:postcode":"33012",
    "sg:province":"Asturias",
    "wof:name":"Inversiones Ferreiro Y Boto S.l.",
    "wof:placetype":"venue"
},
  "geometry": {"coordinates":[-5.8588752747,43.3646507263],"type":"Point"}
}