{
  "type": "Feature",
  "properties": {
    "addr:full":"Calle de Casablanca, 1 Roquetas Mar Almer\u00eda 04740",
    "addr:housenumber":"1",
    "addr:postcode":"04740",
    "addr:street":"Calle De Casablanca",
    "iso:country":"ES",
    "sg:address":"Calle de Casablanca, 1",
    "sg:city":"Roquetas Mar",
    "sg:orig_category":"Peluqueros: De Se\u00d1oras",
    "sg:phone":"+34 950 32 08 52",
    "sg:postcode":"04740",
    "sg:province":"Almer\u00eda",
    "wof:name":"Torres Paniagua Elvira",
    "wof:placetype":"venue"
},
  "geometry": {"coordinates":[-2.6182489395,36.763130188],"type":"Point"}
}