{
  "type": "Feature",
  "properties": {
    "iso:country":"ES",
    "sg:address":"Carrer de Sant Fruitos, 4",
    "sg:city":"Manresa",
    "sg:orig_category":"Promotores Constructores",
    "sg:phone":"+34 938 73 44 04",
    "sg:postcode":"08242",
    "sg:province":"Barcelona",
    "wof:name":"Construcciones Cots Y Claret S. L.",
    "wof:placetype":"venue"
},
  "geometry": {"coordinates":[1.8220210075,41.7294769287],"type":"Point"}
}