{
  "type": "Feature",
  "properties": {
    "addr:full":"Ctra Elche-santa Pola, 92 Santa Pola Alicante 03130",
    "addr:housenumber":"92",
    "addr:postcode":"03130",
    "addr:street":"Ctra Elche-Santa Pola",
    "iso:country":"ES",
    "sg:address":"Ctra Elche-santa Pola, 92",
    "sg:city":"Santa Pola",
    "sg:orig_category":"Fabricaci\u00d3n De Capiteles",
    "sg:phone":"+34 965 41 39 62",
    "sg:postcode":"03130",
    "sg:province":"Alicante",
    "wof:name":"Caseta Las Torres S.l",
    "wof:placetype":"venue"
},
  "geometry": {"coordinates":[-0.5565090179,38.190448761],"type":"Point"}
}