{
  "type": "Feature",
  "properties": {
    "iso:country":"ES",
    "sg:address":"Goribar Auzoa, 17",
    "sg:city":"Goribar",
    "sg:orig_category":"Quincaller\u00cda (al Por Menor)",
    "sg:phone":"+34 943 78 33 50",
    "sg:postcode":"20560",
    "sg:province":"Guip\u00f9zcoa",
    "wof:name":"Donika S.l.",
    "wof:placetype":"venue"
},
  "geometry": {"coordinates":[-2.4079990387,43.0313835144],"type":"Point"}
}