{
  "type": "Feature",
  "properties": {
    "iso:country":"ES",
    "sg:address":"Calle de Pilar, 13",
    "sg:city":"Higuera Vargas",
    "sg:orig_category":"Cerrajer\u00cda, Ferrallista",
    "sg:phone":"+34 924 42 41 09",
    "sg:postcode":"06132",
    "sg:province":"Badajoz",
    "wof:name":"Hidalgo Corbacho Antonio",
    "wof:placetype":"venue"
},
  "geometry": {"coordinates":[-6.9746799469,38.4423332214],"type":"Point"}
}