{
  "type": "Feature",
  "properties": {
    "iso:country":"ES",
    "sg:address":"Calle de Batalla De Otumba, 5",
    "sg:city":"Sax",
    "sg:orig_category":"Importaci\u00d3n",
    "sg:phone":"+34 965 47 55 31",
    "sg:postcode":"03630",
    "sg:province":"Alicante",
    "wof:name":"Kroning Import-export, Sl",
    "wof:placetype":"venue"
},
  "geometry": {"coordinates":[-0.8200662732,38.5329666138],"type":"Point"}
}