{
  "type": "Feature",
  "properties": {
    "iso:country":"ES",
    "sg:address":"Calle de Colmena Del Cura (de La), 14",
    "sg:city":"Colmenar Viejo",
    "sg:orig_category":"Supermercados Y Hipermercados",
    "sg:phone":"+34 918 45 01 09",
    "sg:postcode":"28770",
    "sg:province":"Madrid",
    "wof:name":"Garcia Diaz S.c.",
    "wof:placetype":"venue"
},
  "geometry": {"coordinates":[-3.768709898,40.6580467224],"type":"Point"}
}