{
  "type": "Feature",
  "properties": {
    "addr:full":"Calle de Ramon Gomez De La Serna, 22 Marbella M\u00e1laga 29600",
    "addr:housenumber":"22",
    "addr:postcode":"29600",
    "addr:street":"Calle De Ramon Gomez De La Serna;Ma\u0301Laga",
    "iso:country":"ES",
    "sg:address":"Calle de Ramon Gomez De La Serna, 22",
    "sg:city":"Marbella",
    "sg:orig_category":"M\u00c9dicos: Oftalmolog\u00cda",
    "sg:phone":"+34 952 82 22 46",
    "sg:postcode":"29600",
    "sg:province":"M\u00e1laga",
    "wof:name":"Rojano Pastor Antonio",
    "wof:placetype":"venue"
},
  "geometry": {"coordinates":[-4.9014258385,36.5095901489],"type":"Point"}
}