{
  "type": "Feature",
  "properties": {
    "iso:country":"ES",
    "sg:address":"Calle de Diagonal, 26",
    "sg:city":"Alacant",
    "sg:orig_category":"Mec\u00c1nico Del Autom\u00d3vil",
    "sg:phone":"+34 966 35 22 52",
    "sg:postcode":"03009",
    "sg:province":"Alicante",
    "wof:name":"Toledano Ivorra Alejandro 00150853j S.l.n.e.",
    "wof:placetype":"venue"
},
  "geometry": {"coordinates":[-0.4974609911,38.3651046753],"type":"Point"}
}