{
  "type": "Feature",
  "properties": {
    "iso:country":"ES",
    "sg:address":"Calle de Santa Ana, 10",
    "sg:city":"Estepona",
    "sg:orig_category":"Asociaciones Y Clubs Deportivos",
    "sg:phone":"+34 952 80 10 99",
    "sg:postcode":"29680",
    "sg:province":"M\u00e1laga",
    "wof:name":"Borrego Vallejo Antonio",
    "wof:placetype":"venue"
},
  "geometry": {"coordinates":[-5.1453099251,36.4251556396],"type":"Point"}
}