{
  "type": "Feature",
  "properties": {
    "iso:country":"ES",
    "sg:address":"Calle de Regino Martinez, 9",
    "sg:city":"Algeciras",
    "sg:orig_category":"Peritos En Seguros",
    "sg:phone":"+34 956 63 09 98",
    "sg:postcode":"11201",
    "sg:province":"C\u00e1diz",
    "wof:name":"Diego Becerra Y Asociados S.l.l.",
    "wof:placetype":"venue"
},
  "geometry": {"coordinates":[-5.4488921165,36.1327323914],"type":"Point"}
}