{
  "type": "Feature",
  "properties": {
    "addr:full":"Carr Guifre, 328 Badalona Barcelona 08912",
    "addr:housenumber":"328",
    "addr:postcode":"08912",
    "addr:street":"Carr Guifre",
    "iso:country":"ES",
    "sg:address":"Carr Guifre, 328",
    "sg:city":"Badalona",
    "sg:orig_category":"Molduras, Junquillos, Listones Y Molduras Perforadas",
    "sg:phone":"+34 933 87 42 77",
    "sg:postcode":"08912",
    "sg:province":"Barcelona",
    "wof:name":"Altabella Fanlo Ramon Pablo",
    "wof:placetype":"venue"
},
  "geometry": {"coordinates":[2.2387971878,41.4414291382],"type":"Point"}
}