{
  "type": "Feature",
  "properties": {
    "addr:full":"Crta. Helechal, S/n Monterrubio Serena Badajoz 06427",
    "addr:housenumber":"s / n",
    "addr:postcode":"06427",
    "addr:street":"Crta. Helechal;Monterrubio Serena",
    "iso:country":"ES",
    "sg:address":"Crta. Helechal, S/n",
    "sg:city":"Monterrubio Serena",
    "sg:orig_category":"Agricultores, Agricultores",
    "sg:phone":"+34 924 14 50 75",
    "sg:postcode":"06427",
    "sg:province":"Badajoz",
    "wof:name":"Mera Gomez-bravo Mario",
    "wof:placetype":"venue"
},
  "geometry": {"coordinates":[-5.4440069199,38.5882225037],"type":"Point"}
}