{
  "type": "Feature",
  "properties": {
    "iso:country":"ES",
    "sg:address":"Calle de Donoso Cortes, 69",
    "sg:city":"Madrid",
    "sg:orig_category":"Zapatos (al Por Menor)",
    "sg:phone":"+34 915 49 39 16",
    "sg:postcode":"28015",
    "sg:province":"Madrid",
    "wof:name":"Garcia Villardon Enrique",
    "wof:placetype":"venue"
},
  "geometry": {"coordinates":[-3.7155315876,40.436504364],"type":"Point"}
}