{
  "type": "Feature",
  "properties": {
    "iso:country":"ES",
    "sg:address":"Av Pere Iii, 10",
    "sg:city":"Balaguer",
    "sg:orig_category":"Limpieza Industrial",
    "sg:phone":"+34 973 44 81 22",
    "sg:postcode":"25600",
    "sg:province":"Lleida",
    "wof:name":"Netejes I Contractes S.a.",
    "wof:placetype":"venue"
},
  "geometry": {"coordinates":[0.8077049851,41.7887458801],"type":"Point"}
}