{
  "type": "Feature",
  "properties": {
    "addr:full":"Carrer de Pau Casals, 1 Peguera Islas Baleares 07160",
    "addr:housenumber":"1",
    "addr:postcode":"07160",
    "addr:street":"Carrer De Pau Casals",
    "iso:country":"ES",
    "sg:address":"Carrer de Pau Casals, 1",
    "sg:city":"Peguera",
    "sg:orig_category":"Art\u00cdculos De Regalo (al Por Menor)",
    "sg:phone":"+34 971 68 56 37",
    "sg:postcode":"07160",
    "sg:province":"Islas Baleares",
    "wof:name":"Benefeldt  Friedrich Franz",
    "wof:placetype":"venue"
},
  "geometry": {"coordinates":[2.4597980976,39.5365753174],"type":"Point"}
}