{
  "type": "Feature",
  "properties": {
    "iso:country":"ES",
    "sg:address":"Pase Menendez Pelayo, 16",
    "sg:city":"Santander",
    "sg:orig_category":"Albergues",
    "sg:phone":"+34 942 22 48 19",
    "sg:postcode":"39006",
    "sg:province":"Cantabria",
    "wof:name":"Sota Revuelta Maria",
    "wof:placetype":"venue"
},
  "geometry": {"coordinates":[-3.7980589867,43.4654960632],"type":"Point"}
}