{
  "type": "Feature",
  "properties": {
    "addr:full":"Oron, 12 Miranda Ebro Burgos 09200",
    "addr:housenumber":"12",
    "addr:postcode":"09200",
    "addr:street":"Oron",
    "iso:country":"ES",
    "sg:address":"Oron, 12",
    "sg:city":"Miranda Ebro",
    "sg:orig_category":"Metalurgia",
    "sg:phone":"+34 947 34 78 70",
    "sg:postcode":"09200",
    "sg:province":"Burgos",
    "wof:name":"Recubrimientos Miranda S.l.",
    "wof:placetype":"venue"
},
  "geometry": {"coordinates":[-2.921931982,42.6946868896],"type":"Point"}
}