{
  "type": "Feature",
  "properties": {
    "iso:country":"ES",
    "sg:address":"C/ Oliver, 3",
    "sg:city":"Alcoi",
    "sg:orig_category":"Droguer\u00cdas (al Por Menor)",
    "sg:phone":"+34 965 52 35 13",
    "sg:postcode":"03802",
    "sg:province":"Alicante",
    "wof:name":"Molto Segui Francisco Jose",
    "wof:placetype":"venue"
},
  "geometry": {"coordinates":[-0.4807710052,38.6950569153],"type":"Point"}
}