{
  "type": "Feature",
  "properties": {
    "addr:full":"Pol Ind Alberca, 28 La Nucia Alicante 03530",
    "addr:housenumber":"28",
    "addr:postcode":"03530",
    "addr:street":"Alberca",
    "iso:country":"ES",
    "sg:address":"Pol Ind Alberca, 28",
    "sg:city":"La Nucia",
    "sg:orig_category":"Cerrajer\u00cda, Ferrallista",
    "sg:phone":"+34 966 89 68 20",
    "sg:postcode":"03530",
    "sg:province":"Alicante",
    "wof:name":"Calzados Montiel S.l.",
    "wof:placetype":"venue"
},
  "geometry": {"coordinates":[-0.1249789968,38.6157951355],"type":"Point"}
}