{
  "type": "Feature",
  "properties": {
    "addr:full":"Calle de Chile, 15 Gijon Asturias 33212",
    "addr:housenumber":"15",
    "addr:postcode":"33212",
    "addr:street":"Calle De Chile",
    "iso:country":"ES",
    "sg:address":"Calle de Chile, 15",
    "sg:city":"Gijon",
    "sg:orig_category":"Estancos",
    "sg:phone":"+34 985 31 58 01",
    "sg:postcode":"33212",
    "sg:province":"Asturias",
    "wof:name":"Barrio Mata Fernando",
    "wof:placetype":"venue"
},
  "geometry": {"coordinates":[-5.6898112297,43.5379257202],"type":"Point"}
}