{
  "type": "Feature",
  "properties": {
    "addr:full":"Calle de Francisco Martinez Zaporta, 7 Logro\u00f1o La Rioja 26001",
    "addr:housenumber":"7",
    "addr:postcode":"26001",
    "addr:street":"Calle De Francisco Martinez Zaporta;Rioja",
    "iso:country":"ES",
    "sg:address":"Calle de Francisco Martinez Zaporta, 7",
    "sg:city":"Logro\u00f1o",
    "sg:orig_category":"Partidos Pol\u00cdticos",
    "sg:phone":"+34 941 22 45 66",
    "sg:postcode":"26001",
    "sg:province":"La Rioja",
    "wof:name":"Partido Socialista Obrero Espa\u00f1ol",
    "wof:placetype":"venue"
},
  "geometry": {"coordinates":[-2.4474189281,42.466758728],"type":"Point"}
}