{
  "type": "Feature",
  "properties": {
    "addr:full":"Afores, S/n El Perello Tarragona 43519",
    "addr:housenumber":"s / n",
    "addr:postcode":"43519",
    "addr:street":"Afores",
    "iso:country":"ES",
    "sg:address":"Afores, S/n",
    "sg:city":"El Perello",
    "sg:orig_category":"Cr\u00cda De Poller\u00cda Y De Conejos",
    "sg:phone":"+34 977 49 04 85",
    "sg:postcode":"43519",
    "sg:province":"Tarragona",
    "wof:name":"Cuniterrado S.c.c.l.",
    "wof:placetype":"venue"
},
  "geometry": {"coordinates":[0.7132700086,40.8763809204],"type":"Point"}
}