{
  "type": "Feature",
  "properties": {
    "iso:country":"ES",
    "sg:address":"Rua Cervantes, 2",
    "sg:city":"Foz",
    "sg:orig_category":"Peluquer\u00cdas, Peluquer\u00cda Mixta",
    "sg:phone":"+34 982 14 06 18",
    "sg:postcode":"27780",
    "sg:province":"Lugo",
    "wof:name":"Amaltea Servicios Inmobiliarios S.l.",
    "wof:placetype":"venue"
},
  "geometry": {"coordinates":[-7.257997036,43.5694541931],"type":"Point"}
}