{
  "type": "Feature",
  "properties": {
    "iso:country":"ES",
    "sg:address":"Bo Da Pedra-seixo, 3",
    "sg:city":"Pedra",
    "sg:orig_category":"Flores Y Plantas Naturales (al Por Mayor)",
    "sg:phone":"+34 986 60 80 07",
    "sg:postcode":"36740",
    "sg:province":"Pontevedra",
    "wof:name":"Pycflorga S.l.",
    "wof:placetype":"venue"
},
  "geometry": {"coordinates":[-8.731048584,41.9869499207],"type":"Point"}
}