{
  "type": "Feature",
  "properties": {
    "iso:country":"ES",
    "sg:address":"Calle de Bolivia, 4",
    "sg:city":"Toledo",
    "sg:orig_category":"Zapatos (al Por Menor)",
    "sg:phone":"+34 925 25 23 47",
    "sg:postcode":"45004",
    "sg:province":"Toledo",
    "wof:name":"I\u00f1iguez Perez Rosa Maria",
    "wof:placetype":"venue"
},
  "geometry": {"coordinates":[-4.0298609734,39.8663978577],"type":"Point"}
}