{
  "type": "Feature",
  "properties": {
    "addr:full":"Av Alcodar(pol Alcodar), 40 Gandia Valencia 46700",
    "addr:housenumber":"40",
    "addr:postcode":"46700",
    "addr:street":"Av Alcodar;Alcodar;Valencia",
    "iso:country":"ES",
    "sg:address":"Av Alcodar(pol Alcodar), 40",
    "sg:city":"Gandia",
    "sg:orig_category":"Chapa Y Pintura Veh\u00cdculos",
    "sg:phone":"+34 962 86 61 71",
    "sg:postcode":"46700",
    "sg:province":"Valencia",
    "wof:name":"Fenollar Martinez Francisco",
    "wof:placetype":"venue"
},
  "geometry": {"coordinates":[-0.1837529987,38.9873313904],"type":"Point"}
}