{
  "type": "Feature",
  "properties": {
    "iso:country":"ES",
    "sg:address":"Ctra Zaragoza, Km. 0363,8",
    "sg:city":"Calahorra",
    "sg:orig_category":"Distribuci\u00d3n De Petr\u00d3leo Y Derivados",
    "sg:phone":"+34 941 14 80 90",
    "sg:postcode":"26500",
    "sg:province":"La Rioja",
    "wof:name":"San Rafael Gestion S.l.",
    "wof:placetype":"venue"
},
  "geometry": {"coordinates":[-1.9463210106,42.2885627747],"type":"Point"}
}