{
  "type": "Feature",
  "properties": {
    "addr:full":"Carrer de Parellada (la), 20 Vilafranca Penedes Barcelona 08720",
    "addr:housenumber":"20",
    "addr:postcode":"08720",
    "addr:street":"Carrer De Parellada La;Penedes Barcelona",
    "iso:country":"ES",
    "sg:address":"Carrer de Parellada (la), 20",
    "sg:city":"Vilafranca Penedes",
    "sg:orig_category":"M\u00c9dicos: Estomatolog\u00cda",
    "sg:phone":"+34 938 92 37 00",
    "sg:postcode":"08720",
    "sg:province":"Barcelona",
    "wof:name":"Bosch Sadurni Vicenc",
    "wof:placetype":"venue"
},
  "geometry": {"coordinates":[1.6993089914,41.3464889526],"type":"Point"}
}