{
  "type": "Feature",
  "properties": {
    "addr:full":"Calle de Pasos (los), 3 Elche Sierra Albacete 02430",
    "addr:housenumber":"3",
    "addr:postcode":"02430",
    "addr:street":"Calle De Pasos Los;Sierra",
    "iso:country":"ES",
    "sg:address":"Calle de Pasos (los), 3",
    "sg:city":"Elche Sierra",
    "sg:orig_category":"Centros De Educaci\u00d3n Especial",
    "sg:phone":"+34 967 41 01 85",
    "sg:postcode":"02430",
    "sg:province":"Albacete",
    "wof:name":"Colegio Publico San Blas",
    "wof:placetype":"venue"
},
  "geometry": {"coordinates":[-2.0444200039,38.4494934082],"type":"Point"}
}