{
  "type": "Feature",
  "properties": {
    "iso:country":"ES",
    "sg:address":"Calle de Antonio Fernandez, 17",
    "sg:city":"Arizgoiti",
    "sg:orig_category":"Florister\u00cdas",
    "sg:phone":"+34 944 40 61 11",
    "sg:postcode":"48970",
    "sg:province":"Vizcaya",
    "wof:name":"Valverde Camacho Juana",
    "wof:placetype":"venue"
},
  "geometry": {"coordinates":[-2.8856139183,43.2383728027],"type":"Point"}
}