{
  "type": "Feature",
  "properties": {
    "iso:country":"ES",
    "sg:address":"Calle de Cristo, 1",
    "sg:city":"Villaca\u00f1as",
    "sg:orig_category":"M\u00c9dicos: Estomatolog\u00cda",
    "sg:phone":"+34 925 16 08 14",
    "sg:postcode":"45860",
    "sg:province":"Toledo",
    "sg:website":"wwwpaginasamarillas.es",
    "wof:name":"Tejero Checa Ana Belen",
    "wof:placetype":"venue"
},
  "geometry": {"coordinates":[-3.3330929279,39.6236495972],"type":"Point"}
}