{
  "type": "Feature",
  "properties": {
    "iso:country":"ES",
    "sg:address":"Calle de Santiago Ramon Y Cajal, 12",
    "sg:city":"Cartagena",
    "sg:orig_category":"Condimentos, Especias, Vinagres, Salsas Preparadas (fabricaci\u00d3n, Al Por Mayor)",
    "sg:phone":"+34 968 52 80 50",
    "sg:postcode":"30204",
    "sg:province":"Murcia",
    "wof:name":"Boj Cami\u00f1a Jose Manuel",
    "wof:placetype":"venue"
},
  "geometry": {"coordinates":[-0.9908649921,37.6088829041],"type":"Point"}
}