{
  "type": "Feature",
  "properties": {
    "iso:country":"ES",
    "sg:address":"Plaz Santo Domingo, 12",
    "sg:city":"San Miguel",
    "sg:orig_category":"Ropa Para Se\u00d1oras Y Caballeros (al Por Menor)",
    "sg:phone":"+34 968 22 20 32",
    "sg:postcode":"30008",
    "sg:province":"Murcia",
    "sg:website":"www.adolfo-dominguez.com",
    "wof:name":"Nuevas Franquicias S.a.",
    "wof:placetype":"venue"
},
  "geometry": {"coordinates":[-1.1284600496,37.9871520996],"type":"Point"}
}