{
  "type": "Feature",
  "properties": {
    "iso:country":"ES",
    "sg:address":"Calle de Rioja, 93",
    "sg:city":"Leganes",
    "sg:orig_category":"Farmacias",
    "sg:phone":"+34 916 87 11 48",
    "sg:postcode":"28915",
    "sg:province":"Madrid",
    "wof:name":"Sacristan Matesanz Beatriz",
    "wof:placetype":"venue"
},
  "geometry": {"coordinates":[-3.7520060539,40.3301773071],"type":"Point"}
}