{
  "type": "Feature",
  "properties": {
    "addr:full":"Calle de Rector Leopoldo Alas Hijo, 9 Oviedo Asturias 33006",
    "addr:housenumber":"9",
    "addr:postcode":"33006",
    "addr:street":"Calle De Rector Leopoldo Alas Hijo",
    "iso:country":"ES",
    "sg:address":"Calle de Rector Leopoldo Alas Hijo, 9",
    "sg:city":"Oviedo",
    "sg:orig_category":"Material Y Suministros Para Dentistas, Cirujanos",
    "sg:phone":"+34 985 27 42 07",
    "sg:postcode":"33006",
    "sg:province":"Asturias",
    "wof:name":"Rodriguez Fernandez Casimiro Vidal",
    "wof:placetype":"venue"
},
  "geometry": {"coordinates":[-5.8701891899,43.3586082458],"type":"Point"}
}