{
  "type": "Feature",
  "properties": {
    "iso:country":"ES",
    "sg:address":"Pl Triangular, 2",
    "sg:city":"Benidorm",
    "sg:orig_category":"Ropa Para Ni\u00d1os (al Por Menor)",
    "sg:phone":"+34 965 85 78 93",
    "sg:postcode":"03500",
    "sg:province":"Alicante",
    "wof:name":"Calvo Carrion Alberto",
    "wof:placetype":"venue"
},
  "geometry": {"coordinates":[-0.1743289977,38.5408058167],"type":"Point"}
}