{
  "type": "Feature",
  "properties": {
    "addr:full":"Carrer de Jacint Verdaguer, 120 Sabadell Barcelona 08205",
    "addr:housenumber":"120",
    "addr:postcode":"08205",
    "addr:street":"Carrer De Jacint Verdaguer",
    "iso:country":"ES",
    "sg:address":"Carrer de Jacint Verdaguer, 120",
    "sg:city":"Sabadell",
    "sg:orig_category":"Ingenier\u00cda, Centros De Estudios (diversos)",
    "sg:phone":"+34 937 11 45 53",
    "sg:postcode":"08205",
    "sg:province":"Barcelona",
    "wof:name":"Macfer Engenering S.l.",
    "wof:placetype":"venue"
},
  "geometry": {"coordinates":[2.1031210423,41.5360794067],"type":"Point"}
}