{
  "type": "Feature",
  "properties": {
    "addr:full":"Calle de Almirante Cervera, 13 Fuengirola M\u00e1laga 29640",
    "addr:housenumber":"13",
    "addr:postcode":"29640",
    "addr:street":"Calle De Almirante Cervera;Ma\u0301Laga",
    "iso:country":"ES",
    "sg:address":"Calle de Almirante Cervera, 13",
    "sg:city":"Fuengirola",
    "sg:orig_category":"Plomeros",
    "sg:phone":"+34 952 47 39 01",
    "sg:postcode":"29640",
    "sg:province":"M\u00e1laga",
    "wof:name":"Cortes Ruiz Jose",
    "wof:placetype":"venue"
},
  "geometry": {"coordinates":[-4.6195058823,36.5617294312],"type":"Point"}
}