{
  "type": "Feature",
  "properties": {
    "addr:full":"Calle de Federico Garcia Lorca (de), 2 Colmenar Viejo Madrid 28770",
    "addr:postcode":"28770",
    "addr:street":"Calle De Federico Garcia Lorca De",
    "iso:country":"ES",
    "sg:address":"Calle de Federico Garcia Lorca (de), 2",
    "sg:city":"Colmenar Viejo",
    "sg:orig_category":"Molduras, Junquillos, Listones Y Molduras Perforadas",
    "sg:phone":"+34 918 45 00 46",
    "sg:postcode":"28770",
    "sg:province":"Madrid",
    "wof:name":"Sanz Sanz Basilio",
    "wof:placetype":"venue"
},
  "geometry": {"coordinates":[-3.7610070705,40.6598815918],"type":"Point"}
}