{
  "type": "Feature",
  "properties": {
    "iso:country":"ES",
    "sg:address":"As Galanas, S/n",
    "sg:city":"Galanas",
    "sg:orig_category":"Electricidad: Instaladores",
    "sg:phone":"+34 981 52 25 24",
    "sg:postcode":"15895",
    "sg:province":"La Coru\u00f1a",
    "wof:name":"Gallega Santiago S.l.",
    "wof:placetype":"venue"
},
  "geometry": {"coordinates":[-8.5901298523,42.8309211731],"type":"Point"}
}