{
  "type": "Feature",
  "properties": {
    "addr:full":"Av. J. Pere Jacas, 15 S. Pere Ribes Barcelona 08810",
    "addr:housenumber":"15",
    "addr:postcode":"08810",
    "addr:street":"Av. J. Pere Jacas;S. Pere Ribes Barcelona",
    "iso:country":"ES",
    "sg:address":"Av. J. Pere Jacas, 15",
    "sg:city":"S. Pere Ribes",
    "sg:orig_category":"Asilos De Ancianos. Centros Privados",
    "sg:phone":"+34 938 96 32 49",
    "sg:postcode":"08810",
    "sg:province":"Barcelona",
    "wof:name":"Redos De San Jose Y De San Pedro",
    "wof:placetype":"venue"
},
  "geometry": {"coordinates":[1.7696499825,41.2599067688],"type":"Point"}
}