{
  "type": "Feature",
  "properties": {
    "iso:country":"ES",
    "sg:address":"Ctra Fuente En Corts, 234",
    "sg:city":"Valencia",
    "sg:orig_category":"Supermercados Y Hipermercados",
    "sg:phone":"+34 963 24 30 84",
    "sg:postcode":"46013",
    "sg:province":"Valencia",
    "wof:name":"Juan Fornes Fornes S.a.",
    "wof:placetype":"venue"
},
  "geometry": {"coordinates":[-0.3557589948,39.4363708496],"type":"Point"}
}