{
  "type": "Feature",
  "properties": {
    "addr:full":"Calle de Cristo Del Refugio, 4 Castellar-oliveral Valencia 46026",
    "addr:housenumber":"4",
    "addr:postcode":"46026",
    "addr:street":"Calle De Cristo Del Refugio",
    "iso:country":"ES",
    "sg:address":"Calle de Cristo Del Refugio, 4",
    "sg:city":"Castellar-oliveral",
    "sg:orig_category":"Farmacias",
    "sg:phone":"+34 963 96 13 66",
    "sg:postcode":"46026",
    "sg:province":"Valencia",
    "wof:name":"Marin Morales Fernando",
    "wof:placetype":"venue"
},
  "geometry": {"coordinates":[-0.3642545044,39.4263038635],"type":"Point"}
}