{
  "type": "Feature",
  "properties": {
    "addr:full":"Calle de Pablo Iglesias, S/n Casariche Sevilla 41580",
    "addr:postcode":"41580",
    "addr:street":"Calle De Pablo Iglesias S / N Casariche",
    "iso:country":"ES",
    "sg:address":"Calle de Pablo Iglesias, S/n",
    "sg:city":"Casariche",
    "sg:orig_category":"Reciclaje, Desguace De Veh\u00cdculos",
    "sg:phone":"+34 954 01 01 16",
    "sg:postcode":"41580",
    "sg:province":"Sevilla",
    "wof:name":"Moriana Perez Santiago",
    "wof:placetype":"venue"
},
  "geometry": {"coordinates":[-4.7569642067,37.295879364],"type":"Point"}
}