{
  "type": "Feature",
  "properties": {
    "addr:full":"Calle de Prim, 11 Haro La Rioja 26200",
    "addr:housenumber":"11",
    "addr:postcode":"26200",
    "addr:street":"Calle De Prim",
    "iso:country":"ES",
    "sg:address":"Calle de Prim, 11",
    "sg:city":"Haro",
    "sg:orig_category":"Cajas Para Embalar",
    "sg:phone":"+34 941 31 22 16",
    "sg:postcode":"26200",
    "sg:province":"La Rioja",
    "sg:website":"www.caja.ruralvia.com",
    "wof:name":"Caja Rural De Burgos",
    "wof:placetype":"venue"
},
  "geometry": {"coordinates":[-2.8457388878,42.5770111084],"type":"Point"}
}