{
  "type": "Feature",
  "properties": {
    "iso:country":"ES",
    "sg:address":"Avda Santiago Apostol, 35",
    "sg:city":"Onzonilla",
    "sg:orig_category":"Molduras, Junquillos, Listones Y Molduras Perforadas",
    "sg:phone":"+34 987 28 20 25",
    "sg:postcode":"24231",
    "sg:province":"Le\u00f3n",
    "wof:name":"Junta Vecinal Onzonilla",
    "wof:placetype":"venue"
},
  "geometry": {"coordinates":[-5.5809764862,42.5248985291],"type":"Point"}
}