{
  "type": "Feature",
  "properties": {
    "addr:full":"Calle de San Bruno, 3 Burgos Burgos 09007",
    "addr:housenumber":"3",
    "addr:postcode":"09007",
    "addr:street":"Calle De San Bruno",
    "iso:country":"ES",
    "sg:address":"Calle de San Bruno, 3",
    "sg:city":"Burgos",
    "sg:orig_category":"Colchones (fabricaci\u00d3n, Al Por Mayor, Al Por Menor)",
    "sg:phone":"+34 947 21 03 07",
    "sg:postcode":"09007",
    "sg:province":"Burgos",
    "wof:name":"Valle Colina Guillermo Carlos",
    "wof:placetype":"venue"
},
  "geometry": {"coordinates":[-3.6730840206,42.348526001],"type":"Point"}
}