{
  "type": "Feature",
  "properties": {
    "iso:country":"ES",
    "sg:address":"Calle de Arcipreste Esteban Diaz, 56",
    "sg:city":"Yecla",
    "sg:orig_category":"Ense\u00d1anza: Idiomas",
    "sg:phone":"+34 968 79 31 28",
    "sg:postcode":"30510",
    "sg:province":"Murcia",
    "wof:name":"Disla Gil Maria Dolores",
    "wof:placetype":"venue"
},
  "geometry": {"coordinates":[-1.1067945957,38.6097679138],"type":"Point"}
}