{
  "type": "Feature",
  "properties": {
    "addr:full":"Calle de Lopez De Hoyos, 142 Madrid Madrid 28002",
    "addr:housenumber":"142",
    "addr:postcode":"28002",
    "addr:street":"Calle De Lopez De Hoyos",
    "iso:country":"ES",
    "sg:address":"Calle de Lopez De Hoyos, 142",
    "sg:city":"Madrid",
    "sg:orig_category":"Aguas (distribuci\u00d3n, Servicios)",
    "sg:phone":"+34 914 15 55 86",
    "sg:postcode":"28002",
    "sg:province":"Madrid",
    "wof:name":"Amaragua Cloradores Salinos S.l.",
    "wof:placetype":"venue"
},
  "geometry": {"coordinates":[-3.6723201275,40.4453735352],"type":"Point"}
}