{
  "type": "Feature",
  "properties": {
    "iso:country":"ES",
    "sg:address":"Avda Sancho El Sabio, 20",
    "sg:city":"Donostia-san Sebastian",
    "sg:orig_category":"Asesor\u00cda Fiscal Y Jur\u00cddica",
    "sg:phone":"+34 943 45 23 69",
    "sg:postcode":"20010",
    "sg:province":"Guip\u00f9zcoa",
    "wof:name":"Pro Gonzalez Jose Roque",
    "wof:placetype":"venue"
},
  "geometry": {"coordinates":[-1.9796710014,43.3096046448],"type":"Point"}
}