{
  "type": "Feature",
  "properties": {
    "addr:full":"Av Catalunya, 86 Cervera Lleida 25200",
    "addr:housenumber":"86",
    "addr:postcode":"25200",
    "addr:street":"Av Catalunya",
    "iso:country":"ES",
    "sg:address":"Av Catalunya, 86",
    "sg:city":"Cervera",
    "sg:orig_category":"Molduras, Junquillos, Listones Y Molduras Perforadas",
    "sg:phone":"+34 973 53 13 51",
    "sg:postcode":"25200",
    "sg:province":"Lleida",
    "wof:name":"Eurobar Sant Ramon S.l.",
    "wof:placetype":"venue"
},
  "geometry": {"coordinates":[1.2723619938,41.6716079712],"type":"Point"}
}