{
  "type": "Feature",
  "properties": {
    "iso:country":"ES",
    "sg:address":"Cmno Pillotegi De, 12",
    "sg:city":"Donostia-san Sebastian",
    "sg:orig_category":"Inform\u00c1tica (estudios, Servicios, Asesor\u00cda, Formaci\u00d3n)",
    "sg:phone":"+34 943 22 36 36",
    "sg:postcode":"20018",
    "sg:province":"Guip\u00f9zcoa",
    "sg:website":"www.euskalserv.com",
    "wof:name":"Euskalserv Siglo Xxi, S.l.",
    "wof:placetype":"venue"
},
  "geometry": {"coordinates":[-2.0029520988,43.2836837769],"type":"Point"}
}