{
  "type": "Feature",
  "properties": {
    "iso:country":"ES",
    "sg:address":"Calle de Armenteros, 1",
    "sg:city":"Madrid",
    "sg:orig_category":"Ortopedia General",
    "sg:phone":"+34 913 73 42 45",
    "sg:postcode":"28039",
    "sg:province":"Madrid",
    "sg:website":"www.mydmovilidadya.com",
    "wof:name":"M I B Movilidad S.l.",
    "wof:placetype":"venue"
},
  "geometry": {"coordinates":[-3.7115812302,40.4630966187],"type":"Point"}
}