{
  "type": "Feature",
  "properties": {
    "addr:full":"Ctra Aguilar (de), S/n Anguita Guadalajara 19283",
    "addr:housenumber":"/ n",
    "addr:postcode":"19283",
    "addr:street":"Ctra Aguilar De S",
    "iso:country":"ES",
    "sg:address":"Ctra Aguilar (de), S/n",
    "sg:city":"Anguita",
    "sg:orig_category":"Cooperativas Agr\u00cdcolas",
    "sg:phone":"+34 949 30 44 48",
    "sg:postcode":"19283",
    "sg:province":"Guadalajara",
    "wof:name":"Cooperativa Virgen De La Lastra",
    "wof:placetype":"venue"
},
  "geometry": {"coordinates":[-2.3698160648,41.0253639221],"type":"Point"}
}