{
  "type": "Feature",
  "properties": {
    "addr:full":"Carr Josep Ametller I Vi\u00d1as, 4 Girona Girona 17003",
    "addr:housenumber":"4",
    "addr:postcode":"17003",
    "addr:street":"Carr Josep Ametller;Vin\u0303As",
    "iso:country":"ES",
    "sg:address":"Carr Josep Ametller I Vi\u00d1as, 4",
    "sg:city":"Girona",
    "sg:orig_category":"Empresas De Carpinter\u00cda De Madera",
    "sg:phone":"+34 972 20 70 60",
    "sg:postcode":"17003",
    "sg:province":"Girona",
    "wof:name":"Vila Vicente Josep",
    "wof:placetype":"venue"
},
  "geometry": {"coordinates":[2.8187448978,41.9808616638],"type":"Point"}
}