{
  "type": "Feature",
  "properties": {
    "iso:country":"ES",
    "sg:address":"Calle de Villagarcia, 17",
    "sg:city":"Madrid",
    "sg:orig_category":"Ingeniero",
    "sg:phone":"+34 915 26 46 85",
    "sg:postcode":"28011",
    "sg:province":"Madrid",
    "wof:name":"A.a. Cartografos",
    "wof:placetype":"venue"
},
  "geometry": {"coordinates":[-3.755255,40.405262],"type":"Point"}
}