{
  "type": "Feature",
  "properties": {
    "iso:country":"ES",
    "sg:address":"Avda Rioja De (la), S/n",
    "sg:city":"Quel",
    "sg:orig_category":"Ense\u00d1anza, Formaci\u00d3n Profesional: Aprendizaje",
    "sg:phone":"+34 941 40 31 51",
    "sg:postcode":"26570",
    "sg:province":"La Rioja",
    "wof:name":"Ayuntamiento De Quel",
    "wof:placetype":"venue"
},
  "geometry": {"coordinates":[-2.0567162037,42.2080039978],"type":"Point"}
}