{
  "type": "Feature",
  "properties": {
    "iso:country":"ES",
    "sg:address":"Calle de Garcia Carrera, 1",
    "sg:city":"Cadiz",
    "sg:orig_category":"Droguer\u00cdas (al Por Menor)",
    "sg:phone":"+34 956 25 13 16",
    "sg:postcode":"11009",
    "sg:province":"C\u00e1diz",
    "wof:name":"Vega Marin Salvador De La",
    "wof:placetype":"venue"
},
  "geometry": {"coordinates":[-6.2782859802,36.5143089294],"type":"Point"}
}