{
  "type": "Feature",
  "properties": {
    "iso:country":"ES",
    "sg:address":"Cementerio, 1",
    "sg:city":"Villovieco",
    "sg:orig_category":"Empresas De Carpinter\u00cda De Madera",
    "sg:phone":"+34 979 81 04 51",
    "sg:postcode":"34449",
    "sg:province":"Palencia",
    "wof:name":"Garrachon Mesiert Eduardo",
    "wof:placetype":"venue"
},
  "geometry": {"coordinates":[-4.5403580666,42.3171310425],"type":"Point"}
}