{
  "type": "Feature",
  "properties": {
    "addr:full":"Calle de Carranque, S/n Esquivias Toledo 45221",
    "addr:housenumber":"s / n",
    "addr:postcode":"45221",
    "addr:street":"Calle De Carranque",
    "iso:country":"ES",
    "sg:address":"Calle de Carranque, S/n",
    "sg:city":"Esquivias",
    "sg:orig_category":"Reparaci\u00d3n Y Restauraci\u00d3n De Objetos Diversos",
    "sg:phone":"+34 925 54 66 93",
    "sg:postcode":"45221",
    "sg:province":"Toledo",
    "wof:name":"Entredos S.c.",
    "wof:placetype":"venue"
},
  "geometry": {"coordinates":[-3.7739868164,40.0942192078],"type":"Point"}
}