{
  "type": "Feature",
  "properties": {
    "addr:full":"Calle de Medico Duran, 7 Coru\u00d1a La Coru\u00f1a 15005",
    "addr:postcode":"15005",
    "addr:street":"Calle De;Corun\u0303A",
    "iso:country":"ES",
    "sg:address":"Calle de Medico Duran, 7",
    "sg:city":"Coru\u00d1a",
    "sg:orig_category":"M\u00c9dicos: Cirug\u00cda Ortop\u00c9dica Y Traumatolog\u00cda",
    "sg:phone":"+34 981 27 88 19",
    "sg:postcode":"15005",
    "sg:province":"La Coru\u00f1a",
    "wof:name":"Pombo Prieto Javier",
    "wof:placetype":"venue"
},
  "geometry": {"coordinates":[-8.4083900452,43.3612632751],"type":"Point"}
}