{
  "type": "Feature",
  "properties": {
    "iso:country":"ES",
    "sg:address":"Plaz Aragon, 4",
    "sg:city":"Ayerbe",
    "sg:orig_category":"Molduras, Junquillos, Listones Y Molduras Perforadas",
    "sg:phone":"+34 974 38 03 56",
    "sg:postcode":"22800",
    "sg:province":"Huesca",
    "wof:name":"Marco Castillo Valero",
    "wof:placetype":"venue"
},
  "geometry": {"coordinates":[-0.6896799803,42.2771949768],"type":"Point"}
}