{
  "type": "Feature",
  "properties": {
    "addr:full":"Calle de Mayor, 112 Union Murcia 30360",
    "addr:housenumber":"112",
    "addr:postcode":"30360",
    "addr:street":"Calle De Mayor",
    "iso:country":"ES",
    "sg:address":"Calle de Mayor, 112",
    "sg:city":"Union",
    "sg:orig_category":"Florister\u00cdas",
    "sg:phone":"+34 968 54 06 97",
    "sg:postcode":"30360",
    "sg:province":"Murcia",
    "wof:name":"Sanchez Ba\u00f1os Angel",
    "wof:placetype":"venue"
},
  "geometry": {"coordinates":[-0.8769850135,37.6252479553],"type":"Point"}
}