{
  "type": "Feature",
  "properties": {
    "iso:country":"ES",
    "sg:address":"Calle de Gregorio Mara\u00d1on, 11",
    "sg:city":"Leganes",
    "sg:orig_category":"Electricidad, Electr\u00d3nica: Material Y Suministros (al Por Mayor)",
    "sg:phone":"+34 914 81 02 88",
    "sg:postcode":"28914",
    "sg:province":"Madrid",
    "sg:website":"www.peisa.com",
    "wof:name":"Peisa Madrid S. A.",
    "wof:placetype":"venue"
},
  "geometry": {"coordinates":[-3.7490150928,40.3228416443],"type":"Point"}
}