{
  "type": "Feature",
  "properties": {
    "iso:country":"ES",
    "sg:address":"Calle de Nueva, 18",
    "sg:city":"Cuellar",
    "sg:orig_category":"Servicio De Salud",
    "sg:phone":"+34 921 14 00 91",
    "sg:postcode":"40200",
    "sg:province":"Segovia",
    "wof:name":"Saneamientos Roque S.l.",
    "wof:placetype":"venue"
},
  "geometry": {"coordinates":[-4.3142991066,41.4025382996],"type":"Point"}
}