{
  "type": "Feature",
  "properties": {
    "addr:full":"Carr Major, 170 Bescano Girona 17162",
    "addr:housenumber":"170",
    "addr:postcode":"17162",
    "addr:street":"Carr Major",
    "iso:country":"ES",
    "sg:address":"Carr Major, 170",
    "sg:city":"Bescano",
    "sg:orig_category":"Mec\u00c1nico Del Autom\u00d3vil",
    "sg:phone":"+34 972 44 04 79",
    "sg:postcode":"17162",
    "sg:province":"Girona",
    "wof:name":"Taller  Solergasto",
    "wof:placetype":"venue"
},
  "geometry": {"coordinates":[2.7331809998,41.9670829773],"type":"Point"}
}