{
  "type": "Feature",
  "properties": {
    "addr:full":"Calle de Abasolo Apezpiku, 1 Amorebieta Vizcaya 48340",
    "addr:housenumber":"1",
    "addr:postcode":"48340",
    "addr:street":"Calle De Abasolo Apezpiku",
    "iso:country":"ES",
    "sg:address":"Calle de Abasolo Apezpiku, 1",
    "sg:city":"Amorebieta",
    "sg:orig_category":"Frutas Y Legumbres Frescas (al Por Mayor)",
    "sg:phone":"+34 946 73 07 25",
    "sg:postcode":"48340",
    "sg:province":"Vizcaya",
    "wof:name":"Gorospe Olea Jose Luis",
    "wof:placetype":"venue"
},
  "geometry": {"coordinates":[-2.7345445156,43.2200737],"type":"Point"}
}