{
  "type": "Feature",
  "properties": {
    "addr:full":"Calle de Padre Isla, 11 Cistierna Le\u00f3n 24800",
    "addr:housenumber":"11",
    "addr:postcode":"24800",
    "addr:street":"Calle De Padre Isla;Leo\u0301N",
    "iso:country":"ES",
    "sg:address":"Calle de Padre Isla, 11",
    "sg:city":"Cistierna",
    "sg:orig_category":"Carnicer\u00cdas, Carnicer\u00cdas",
    "sg:phone":"+34 987 70 10 26",
    "sg:postcode":"24800",
    "sg:province":"Le\u00f3n",
    "wof:name":"Mu\u00f1oz De La Varga Agustin Fulgencio",
    "wof:placetype":"venue"
},
  "geometry": {"coordinates":[-5.1273732185,42.8036727905],"type":"Point"}
}