{
  "type": "Feature",
  "properties": {
    "addr:full":"Ptda La Hoya, 155 Elche Alicante 03295",
    "addr:housenumber":"155",
    "addr:postcode":"03295",
    "addr:street":"Ptda La Hoya",
    "iso:country":"ES",
    "sg:address":"Ptda La Hoya, 155",
    "sg:city":"Elche",
    "sg:orig_category":"Arboricultura Y Producci\u00d3n De Frutas",
    "sg:phone":"+34 965 45 46 74",
    "sg:postcode":"03295",
    "sg:province":"Alicante",
    "wof:name":"Anton Esclapez Andres",
    "wof:placetype":"venue"
},
  "geometry": {"coordinates":[-0.6429250836,38.3055953979],"type":"Point"}
}