{
  "type": "Feature",
  "properties": {
    "iso:country":"ES",
    "sg:address":"Calle de Puerto De Canfranc, 56",
    "sg:city":"Madrid",
    "sg:orig_category":"Caf\u00c9s, Bares, Cervecer\u00cdas",
    "sg:phone":"+34 913 28 37 68",
    "sg:postcode":"28038",
    "sg:province":"Madrid",
    "wof:name":"Asto Huyhua Nestor Mauro",
    "wof:placetype":"venue"
},
  "geometry": {"coordinates":[-3.6616442204,40.3990745544],"type":"Point"}
}