{
  "type": "Feature",
  "properties": {
    "iso:country":"ES",
    "sg:address":"Calle de Campomanes, 13",
    "sg:city":"Madrid",
    "sg:orig_category":"Librer\u00cdas",
    "sg:phone":"+34 915 41 72 91",
    "sg:postcode":"28013",
    "sg:province":"Madrid",
    "sg:website":"www.petrasinternationalbookshoop",
    "wof:name":"Schlueter  Jennifer Lee",
    "wof:placetype":"venue"
},
  "geometry": {"coordinates":[-3.7093589306,40.4194717407],"type":"Point"}
}