{
  "type": "Feature",
  "properties": {
    "iso:country":"ES",
    "sg:address":"Calle de Diocles, S/n",
    "sg:city":"Merida",
    "sg:orig_category":"Molduras, Junquillos, Listones Y Molduras Perforadas",
    "sg:phone":"+34 924 31 78 02",
    "sg:postcode":"06800",
    "sg:province":"Badajoz",
    "wof:name":"Mateo Redondo Luis",
    "wof:placetype":"venue"
},
  "geometry": {"coordinates":[-6.3428916931,38.9115715027],"type":"Point"}
}