{
  "type": "Feature",
  "properties": {
    "addr:full":"Rua Dolores, 59 Ferrol La Coru\u00f1a 15402",
    "addr:housenumber":"59",
    "addr:postcode":"15402",
    "addr:street":"Rua Dolores;La Corun\u0303A",
    "iso:country":"ES",
    "sg:address":"Rua Dolores, 59",
    "sg:city":"Ferrol",
    "sg:orig_category":"Fabricaci\u00d3n, Venta De Cuadros, Accesorios Para Enmarcar",
    "sg:phone":"+34 981 35 38 55",
    "sg:postcode":"15402",
    "sg:province":"La Coru\u00f1a",
    "wof:name":"Galego Pena Andres",
    "wof:placetype":"venue"
},
  "geometry": {"coordinates":[-8.2361278534,43.4830780029],"type":"Point"}
}