{
  "type": "Feature",
  "properties": {
    "addr:full":"Barr San Pedro, 38 Rumoroso Cantabria 39313",
    "addr:housenumber":"38",
    "addr:postcode":"39313",
    "addr:street":"San Pedro",
    "iso:country":"ES",
    "sg:address":"Barr San Pedro, 38",
    "sg:city":"Rumoroso",
    "sg:orig_category":"Armaduras De Hormig\u00d3n",
    "sg:phone":"+34 942 84 51 85",
    "sg:postcode":"39313",
    "sg:province":"Cantabria",
    "wof:name":"Ruiz Santos Isidro Joaquin",
    "wof:placetype":"venue"
},
  "geometry": {"coordinates":[-4.0165991783,43.3861083984],"type":"Point"}
}