{
  "type": "Feature",
  "properties": {
    "iso:country":"ES",
    "sg:address":"Carrer de Frederic Soler, 1",
    "sg:city":"Prat Llobregat",
    "sg:orig_category":"Asilos De Ancianos. Centros Privados",
    "sg:phone":"+34 933 79 50 77",
    "sg:postcode":"08820",
    "sg:province":"Barcelona",
    "wof:name":"Il.luserveis S.l.",
    "wof:placetype":"venue"
},
  "geometry": {"coordinates":[2.0949840546,41.3278541565],"type":"Point"}
}