{
  "type": "Feature",
  "properties": {
    "iso:country":"ES",
    "sg:address":"Calle de Breton De Los Herreros, 23",
    "sg:city":"Madrid",
    "sg:orig_category":"Alimentaci\u00d3n General (al Por Menor)",
    "sg:phone":"+34 914 41 48 94",
    "sg:postcode":"28003",
    "sg:province":"Madrid",
    "wof:name":"Abascal Gomez Manuel",
    "wof:placetype":"venue"
},
  "geometry": {"coordinates":[-3.698829,40.43959],"type":"Point"}
}