{
  "type": "Feature",
  "properties": {
    "addr:full":"Rua Jose Antonio, 117 Ordes La Coru\u00f1a 15680",
    "addr:housenumber":"117",
    "addr:postcode":"15680",
    "addr:street":"Rua Jose Antonio;La Corun\u0303A",
    "iso:country":"ES",
    "sg:address":"Rua Jose Antonio, 117",
    "sg:city":"Ordes",
    "sg:orig_category":"Comercio De Piezas De Recambio Y De Accesorios De Veh\u00cdculos, Veh\u00cdculos Industriales",
    "sg:phone":"+34 981 68 03 57",
    "sg:postcode":"15680",
    "sg:province":"La Coru\u00f1a",
    "wof:name":"Dubra Pena Antonio",
    "wof:placetype":"venue"
},
  "geometry": {"coordinates":[-8.4085588455,43.0760612488],"type":"Point"}
}