{
  "type": "Feature",
  "properties": {
    "addr:full":"Calle de Iglesia, 6 Parla Madrid 28980",
    "addr:housenumber":"6",
    "addr:postcode":"28980",
    "addr:street":"Calle De Iglesia",
    "iso:country":"ES",
    "sg:address":"Calle de Iglesia, 6",
    "sg:city":"Parla",
    "sg:orig_category":"Asociaciones Y Clubs Deportivos",
    "sg:phone":"+34 916 99 33 59",
    "sg:postcode":"28980",
    "sg:province":"Madrid",
    "wof:name":"Bedecar S.a.",
    "wof:placetype":"venue"
},
  "geometry": {"coordinates":[-3.7734539509,40.237449646],"type":"Point"}
}