{
  "type": "Feature",
  "properties": {
    "addr:full":"Ctra General Del Norte, 124 Cantillo Santa Cruz De Tenerife 38350",
    "addr:housenumber":"124",
    "addr:postcode":"38350",
    "addr:street":"Ctra General Del Norte",
    "iso:country":"ES",
    "sg:address":"Ctra General Del Norte, 124",
    "sg:city":"Cantillo",
    "sg:orig_category":"Hospitales",
    "sg:phone":"+34 902 11 21 01",
    "sg:postcode":"38350",
    "sg:province":"Santa Cruz De Tenerife",
    "wof:name":"Clinica Tacoronte S.l.",
    "wof:placetype":"venue"
},
  "geometry": {"coordinates":[-16.4174289703,28.4756546021],"type":"Point"}
}