{
  "type": "Feature",
  "properties": {
    "iso:country":"ES",
    "sg:address":"Ctra Santa Cruz Laguna, Km. 0037,0",
    "sg:city":"Santa Cruz De Tenerife",
    "sg:orig_category":"Distribuci\u00d3n De Petr\u00d3leo Y Derivados",
    "sg:phone":"+34 922 65 53 96",
    "sg:postcode":"38293",
    "sg:province":"Santa Cruz De Tenerife",
    "wof:name":"Gonzalez Zamora Teobaldo",
    "wof:placetype":"venue"
},
  "geometry": {"coordinates":[-16.2907238007,28.5156917572],"type":"Point"}
}