{
  "type": "Feature",
  "properties": {
    "addr:full":"Calle de Fueros, 2 Irun Guip\u00f9zcoa 20302",
    "addr:housenumber":"2",
    "addr:postcode":"20302",
    "addr:street":"Calle De Fueros;Guipu\u0300Zcoa",
    "iso:country":"ES",
    "sg:address":"Calle de Fueros, 2",
    "sg:city":"Irun",
    "sg:orig_category":"Asociaciones, Instituciones De Consumidores Y Usuarios",
    "sg:phone":"+34 943 63 21 94",
    "sg:postcode":"20302",
    "sg:province":"Guip\u00f9zcoa",
    "wof:name":"Asociacion De Consumidores Y Usuarios Del Bidasoa",
    "wof:placetype":"venue"
},
  "geometry": {"coordinates":[-1.7900356054,43.3383712769],"type":"Point"}
}