{
  "type": "Feature",
  "properties": {
    "iso:country":"ES",
    "sg:address":"Maestro Torralba(zenia Ii), 1",
    "sg:city":"La Zenia",
    "sg:orig_category":"Persianas Interiores, Exteriores",
    "sg:phone":"+34 966 77 37 90",
    "sg:postcode":"03189",
    "sg:province":"Alicante",
    "wof:name":"Del Campo Ballesteros Gerardo",
    "wof:placetype":"venue"
},
  "geometry": {"coordinates":[-0.7311810255,37.9233779907],"type":"Point"}
}