{
  "type": "Feature",
  "properties": {
    "iso:country":"ES",
    "sg:address":"Calle de Poza Licenciado, 43",
    "sg:city":"Bilbao",
    "sg:orig_category":"Bisuter\u00cda, Joyer\u00cda, Relojer\u00cda (al Por Menor)",
    "sg:phone":"+34 944 41 18 76",
    "sg:postcode":"48011",
    "sg:province":"Vizcaya",
    "wof:name":"Matute Escandon Pablo Juan",
    "wof:placetype":"venue"
},
  "geometry": {"coordinates":[-2.9414401054,43.2623443604],"type":"Point"}
}