{
  "type": "Feature",
  "properties": {
    "iso:country":"ES",
    "sg:address":"Calle de Recesvinto, 96",
    "sg:city":"Madrid",
    "sg:orig_category":"Electricidad Veh\u00cdculo",
    "sg:phone":"+34 914 72 36 86",
    "sg:postcode":"28019",
    "sg:province":"Madrid",
    "wof:name":"Juan Villoria S.a.",
    "wof:placetype":"venue"
},
  "geometry": {"coordinates":[-3.7324640751,40.3961181641],"type":"Point"}
}