{
  "type": "Feature",
  "properties": {
    "iso:country":"ES",
    "sg:address":"Avda Beiramar, 8",
    "sg:city":"Vigo",
    "sg:orig_category":"Construcciones Navales Y Fluviales",
    "sg:phone":"+34 986 20 99 93",
    "sg:postcode":"36208",
    "sg:province":"Pontevedra",
    "wof:name":"Astilleros Y Varaderos San Gregorio S. L.",
    "wof:placetype":"venue"
},
  "geometry": {"coordinates":[-8.7331552505,42.2344818115],"type":"Point"}
}