{
  "type": "Feature",
  "properties": {
    "addr:full":"Carr Pont De La Barca, 12 Girona Girona 17007",
    "addr:housenumber":"12",
    "addr:postcode":"17007",
    "addr:street":"Carr Pont De La Barca",
    "iso:country":"ES",
    "sg:address":"Carr Pont De La Barca, 12",
    "sg:city":"Girona",
    "sg:orig_category":"Cervecer\u00cdas",
    "sg:phone":"+34 972 22 84 70",
    "sg:postcode":"17007",
    "sg:province":"Girona",
    "wof:name":"Gusp And Gusp 2001 S.l.",
    "wof:placetype":"venue"
},
  "geometry": {"coordinates":[2.8192050457,41.9900817871],"type":"Point"}
}