{
  "type": "Feature",
  "properties": {
    "iso:country":"ES",
    "sg:address":"Av Joan Miro, 65",
    "sg:city":"Palma",
    "sg:orig_category":"Aparcamientos (infraestructuras, Accesorios)",
    "sg:phone":"+34 971 18 09 59",
    "sg:postcode":"07015",
    "sg:province":"Islas Baleares",
    "wof:name":"Palma Gomila S.l.",
    "wof:placetype":"venue"
},
  "geometry": {"coordinates":[2.6248879433,39.5609550476],"type":"Point"}
}