{
  "type": "Feature",
  "properties": {
    "addr:full":"Carr Empuries, 32 Girona Girona 17005",
    "addr:housenumber":"32",
    "addr:postcode":"17005",
    "addr:street":"Carr Empuries",
    "iso:country":"ES",
    "sg:address":"Carr Empuries, 32",
    "sg:city":"Girona",
    "sg:orig_category":"Mec\u00c1nico Del Autom\u00d3vil",
    "sg:phone":"+34 972 40 16 34",
    "sg:postcode":"17005",
    "sg:province":"Girona",
    "wof:name":"Bonet Solench Jose Maria",
    "wof:placetype":"venue"
},
  "geometry": {"coordinates":[2.810765028,41.9702186584],"type":"Point"}
}