{
  "type": "Feature",
  "properties": {
    "iso:country":"ES",
    "sg:address":"Avda Bilbao, 8",
    "sg:city":"Medina Pomar",
    "sg:orig_category":"Ense\u00d1anza: Profesiones Art\u00cdsticas",
    "sg:phone":"+34 947 14 77 53",
    "sg:postcode":"09500",
    "sg:province":"Burgos",
    "wof:name":"Foto Ramon S.l.",
    "wof:placetype":"venue"
},
  "geometry": {"coordinates":[-3.4852690697,42.9362792969],"type":"Point"}
}