{
  "type": "Feature",
  "properties": {
    "iso:country":"ES",
    "sg:address":"Calle de Errekerte, 3",
    "sg:city":"Berriozar",
    "sg:orig_category":"Electricidad, Electr\u00d3nica: Material Y Suministros (al Por Mayor)",
    "sg:phone":"+34 948 21 58 20",
    "sg:postcode":"31013",
    "sg:province":"Navarra",
    "wof:name":"Promociones Recreativas Naex S.a.",
    "wof:placetype":"venue"
},
  "geometry": {"coordinates":[-1.6731740236,42.8358840942],"type":"Point"}
}