{
  "type": "Feature",
  "properties": {
    "iso:country":"ES",
    "sg:address":"Avgd Mossen Herminio Perez (de), 1",
    "sg:city":"Betxi",
    "sg:orig_category":"Sociedades, Compa\u00d1\u00cdas Aseguradoras",
    "sg:phone":"+34 964 62 07 19",
    "sg:postcode":"12549",
    "sg:province":"Castell\u00f3n",
    "wof:name":"Meneu Monzonis Maria Isabel",
    "wof:placetype":"venue"
},
  "geometry": {"coordinates":[-0.1960940063,39.9286193848],"type":"Point"}
}