{
  "type": "Feature",
  "properties": {
    "addr:full":"Malaga, 3 San Pedro Alcantara M\u00e1laga 29670",
    "addr:housenumber":"3",
    "addr:postcode":"29670",
    "addr:street":"Malaga",
    "iso:country":"ES",
    "sg:address":"Malaga, 3",
    "sg:city":"San Pedro Alcantara",
    "sg:orig_category":"Panader\u00cdas, Panader\u00cdas",
    "sg:phone":"+34 952 78 46 67",
    "sg:postcode":"29670",
    "sg:province":"M\u00e1laga",
    "wof:name":"De Luiz Albanes Alfredo",
    "wof:placetype":"venue"
},
  "geometry": {"coordinates":[-4.9880971909,36.4864349365],"type":"Point"}
}