{
  "type": "Feature",
  "properties": {
    "iso:country":"ES",
    "sg:address":"Calle de San Agustin, 7",
    "sg:city":"Olivenza",
    "sg:orig_category":"Carpinteros",
    "sg:phone":"+34 924 49 08 46",
    "sg:postcode":"06100",
    "sg:province":"Badajoz",
    "wof:name":"Carpinteria Metalica Y Aluminios Salas S.l.",
    "wof:placetype":"venue"
},
  "geometry": {"coordinates":[-7.1031050682,38.6854057312],"type":"Point"}
}