{
  "type": "Feature",
  "properties": {
    "addr:full":"Calle de Higueral, 9 Fuenlabrada Madrid 28944",
    "addr:housenumber":"9",
    "addr:postcode":"28944",
    "addr:street":"Calle De Higueral",
    "iso:country":"ES",
    "sg:address":"Calle de Higueral, 9",
    "sg:city":"Fuenlabrada",
    "sg:orig_category":"Asesor\u00cda De Formaci\u00d3n Y Gesti\u00d3n De Personal",
    "sg:phone":"+34 914 92 05 06",
    "sg:postcode":"28944",
    "sg:province":"Madrid",
    "wof:name":"Arisgestion Financiera S.l.",
    "wof:placetype":"venue"
},
  "geometry": {"coordinates":[-3.7975435257,40.2765197754],"type":"Point"}
}