{
  "type": "Feature",
  "properties": {
    "iso:country":"ES",
    "sg:address":"San Gregorio Auzoa, S/n",
    "sg:city":"San Gregorio",
    "sg:orig_category":"Semiller\u00cdas",
    "sg:phone":"+34 943 18 00 48",
    "sg:postcode":"20211",
    "sg:province":"Guip\u00f9zcoa",
    "wof:name":"Dorronsoro Goicoechea Estanislao",
    "wof:placetype":"venue"
},
  "geometry": {"coordinates":[-2.176306963,43.0065307617],"type":"Point"}
}