{
  "type": "Feature",
  "properties": {
    "iso:country":"ES",
    "sg:address":"Ctra. Baza-h. Overa, Km. 0043,0",
    "sg:city":"Tijola",
    "sg:orig_category":"Aguas (distribuci\u00d3n, Servicios)",
    "sg:phone":"+34 950 61 33 16",
    "sg:postcode":"04880",
    "sg:province":"Almer\u00eda",
    "wof:name":"Gestion De Aguas Del Levante Almeriense",
    "wof:placetype":"venue"
},
  "geometry": {"coordinates":[-2.4405939579,37.3462524414],"type":"Point"}
}