{
  "type": "Feature",
  "properties": {
    "iso:country":"ES",
    "sg:address":"Crta. Nacional 340, Km. 0062,0",
    "sg:city":"Almassora Pol. Ind.",
    "sg:orig_category":"Instalaci\u00d3n, Preparaci\u00d3n De Exposiciones, Ferias, Salones",
    "sg:phone":"+34 964 50 64 00",
    "sg:postcode":"12550",
    "sg:province":"Castell\u00f3n",
    "sg:website":"www.carmalasa.com",
    "wof:name":"Carpinteria Madera Lacada S.l.",
    "wof:placetype":"venue"
},
  "geometry": {"coordinates":[-0.0631740019,39.9439582825],"type":"Point"}
}