{
  "type": "Feature",
  "properties": {
    "addr:full":"Ctra Nova, 47 Vallgorguina Barcelona 08470",
    "addr:housenumber":"47",
    "addr:postcode":"08470",
    "addr:street":"Ctra Nova",
    "iso:country":"ES",
    "sg:address":"Ctra Nova, 47",
    "sg:city":"Vallgorguina",
    "sg:orig_category":"Lencer\u00cda Femenina, Corseter\u00cda, Trajes De Ba\u00d1o (al Por Menor)",
    "sg:phone":"+34 938 67 92 57",
    "sg:postcode":"08470",
    "sg:province":"Barcelona",
    "wof:name":"Mora Grau Marta",
    "wof:placetype":"venue"
},
  "geometry": {"coordinates":[2.510160923,41.647354126],"type":"Point"}
}