{
  "type": "Feature",
  "properties": {
    "iso:country":"ES",
    "sg:address":"Calle de Pozas, 18",
    "sg:city":"Madrid",
    "sg:orig_category":"Asesor\u00cda Fiscal Y Jur\u00cddica",
    "sg:phone":"+34 915 21 77 37",
    "sg:postcode":"28004",
    "sg:province":"Madrid",
    "wof:name":"Rizzo San Martin Mario Sergio",
    "wof:placetype":"venue"
},
  "geometry": {"coordinates":[-3.7065150738,40.4255638123],"type":"Point"}
}