{
  "type": "Feature",
  "properties": {
    "iso:country":"ES",
    "sg:address":"Mendigorria, 16",
    "sg:city":"Iru\u00f1a",
    "sg:orig_category":"Farmacias",
    "sg:phone":"+34 948 12 85 02",
    "sg:postcode":"31015",
    "sg:province":"Navarra",
    "wof:name":"Luquin Juaniz Asuncion",
    "wof:placetype":"venue"
},
  "geometry": {"coordinates":[-1.6313574314,42.8245010376],"type":"Point"}
}