{
  "type": "Feature",
  "properties": {
    "iso:country":"ES",
    "sg:address":"Calle de General Goded, 7",
    "sg:city":"Arrecife",
    "sg:orig_category":"Abogados",
    "sg:phone":"+34 928 80 23 47",
    "sg:postcode":"35500",
    "sg:province":"Las Palmas",
    "wof:name":"Guadalupe Perdomo Jose Basilio",
    "wof:placetype":"venue"
},
  "geometry": {"coordinates":[-13.5484552383,28.9601402283],"type":"Point"}
}