{
  "type": "Feature",
  "properties": {
    "iso:country":"ES",
    "sg:address":"Calle de Pradillo (del), S/n",
    "sg:city":"Colmenar Viejo",
    "sg:orig_category":"Montaje (empresas De)",
    "sg:phone":"+34 918 46 12 70",
    "sg:postcode":"28770",
    "sg:province":"Madrid",
    "wof:name":"Moncobra S.a.",
    "wof:placetype":"venue"
},
  "geometry": {"coordinates":[-3.7524840832,40.6568946838],"type":"Point"}
}