{
  "type": "Feature",
  "properties": {
    "addr:full":"H, 39 Alcoi Alicante 03800",
    "addr:housenumber":"39",
    "addr:postcode":"03800",
    "addr:street":"H",
    "iso:country":"ES",
    "sg:address":"H, 39",
    "sg:city":"Alcoi",
    "sg:orig_category":"M\u00c1rmoles, Granitos Y Piedras Naturales",
    "sg:phone":"+34 965 52 35 73",
    "sg:postcode":"03800",
    "sg:province":"Alicante",
    "wof:name":"Ferrer Coloma Juan Artemidor",
    "wof:placetype":"venue"
},
  "geometry": {"coordinates":[-0.4551649988,38.7141838074],"type":"Point"}
}