{
  "type": "Feature",
  "properties": {
    "addr:full":"Rua Xeneral Gutierrez Mellado, 12 Pontevedra Pontevedra 36001",
    "addr:housenumber":"12",
    "addr:postcode":"36001",
    "addr:street":"Rua Xeneral;Mellado",
    "iso:country":"ES",
    "sg:address":"Rua Xeneral Gutierrez Mellado, 12",
    "sg:city":"Pontevedra",
    "sg:orig_category":"Inform\u00c1tica: Soportes De Informaci\u00d3n, Suministros & Accesorios",
    "sg:phone":"+34 986 85 52 42",
    "sg:postcode":"36001",
    "sg:province":"Pontevedra",
    "wof:name":"Consultores Informaticos De Pontevedra S. L.",
    "wof:placetype":"venue"
},
  "geometry": {"coordinates":[-8.6464385986,42.4304580688],"type":"Point"}
}