{
  "type": "Feature",
  "properties": {
    "addr:full":"Avda Menendez Pidal, 15 Valencia Valencia 46009",
    "addr:housenumber":"15",
    "addr:postcode":"46009",
    "addr:street":"Avda Menendez Pidal",
    "iso:country":"ES",
    "sg:address":"Avda Menendez Pidal, 15",
    "sg:city":"Valencia",
    "sg:orig_category":"Sociedades, Compa\u00d1\u00cdas Aseguradoras",
    "sg:phone":"+34 963 40 14 77",
    "sg:postcode":"46009",
    "sg:province":"Valencia",
    "wof:name":"Centro De Seguros S. A.",
    "wof:placetype":"venue"
},
  "geometry": {"coordinates":[-0.3908750117,39.4791374207],"type":"Point"}
}