{
  "type": "Feature",
  "properties": {
    "addr:full":"Via Augusta, 68 Barcelona Barcelona 08006",
    "addr:housenumber":"68",
    "addr:postcode":"08006",
    "addr:street":"Via Augusta",
    "iso:country":"ES",
    "sg:address":"Via Augusta, 68",
    "sg:city":"Barcelona",
    "sg:orig_category":"Iglesia Cat\u00d3lica",
    "sg:phone":"+34 932 37 31 53",
    "sg:postcode":"08006",
    "sg:province":"Barcelona",
    "wof:name":"Parroquia De Santa Teresa Del Ni\u00f1o Jesus",
    "wof:placetype":"venue"
},
  "geometry": {"coordinates":[2.1517000198,41.4001846313],"type":"Point"}
}