{
  "type": "Feature",
  "properties": {
    "iso:country":"ES",
    "sg:address":"Calle de Desenga\u00d1o, 34",
    "sg:city":"Tomelloso",
    "sg:orig_category":"Venta, Instalaci\u00d3n De Calefacci\u00d3n",
    "sg:phone":"+34 926 51 00 51",
    "sg:postcode":"13700",
    "sg:province":"Ciudad Real",
    "wof:name":"Instalaciones J.a. Benito S.l.l.",
    "wof:placetype":"venue"
},
  "geometry": {"coordinates":[-3.0150847435,39.1610794067],"type":"Point"}
}