{
  "type": "Feature",
  "properties": {
    "addr:full":"Plaz Espa\u00d1a, 15 Salamanca Salamanca 37004",
    "addr:housenumber":"15",
    "addr:postcode":"37004",
    "addr:street":"Plaz Espan\u0303A",
    "iso:country":"ES",
    "sg:address":"Plaz Espa\u00d1a, 15",
    "sg:city":"Salamanca",
    "sg:orig_category":"Agentes Generales De Seguros",
    "sg:phone":"+34 923 26 43 75",
    "sg:postcode":"37004",
    "sg:province":"Salamanca",
    "wof:name":"Guzman Diaz Ana",
    "wof:placetype":"venue"
},
  "geometry": {"coordinates":[-5.6590881348,40.9686279297],"type":"Point"}
}