{
  "type": "Feature",
  "properties": {
    "addr:full":"La Paz, 3 Dos Aguas Valencia 46198",
    "addr:housenumber":"3",
    "addr:postcode":"46198",
    "addr:street":"La Paz",
    "iso:country":"ES",
    "sg:address":"La Paz, 3",
    "sg:city":"Dos Aguas",
    "sg:orig_category":"Cr\u00cda De Poller\u00cda Y De Conejos",
    "sg:phone":"+34 962 52 91 51",
    "sg:postcode":"46198",
    "sg:province":"Valencia",
    "wof:name":"Del Valle Alcacer Josefa",
    "wof:placetype":"venue"
},
  "geometry": {"coordinates":[-0.8000019789,39.2900619507],"type":"Point"}
}