{
  "type": "Feature",
  "properties": {
    "addr:full":"Calle de Rualasal, 4 Santander Cantabria 39001",
    "addr:housenumber":"4",
    "addr:postcode":"39001",
    "addr:street":"Calle De Rualasal",
    "iso:country":"ES",
    "sg:address":"Calle de Rualasal, 4",
    "sg:city":"Santander",
    "sg:orig_category":"M\u00c9dicos: Oftalmolog\u00cda",
    "sg:phone":"+34 942 21 06 59",
    "sg:postcode":"39001",
    "sg:province":"Cantabria",
    "wof:name":"Mier Durante Carlos",
    "wof:placetype":"venue"
},
  "geometry": {"coordinates":[-3.807913065,43.4625778198],"type":"Point"}
}