{
  "type": "Feature",
  "properties": {
    "addr:full":"Avda Reina Sofia, 98 Merida Badajoz 06800",
    "addr:housenumber":"98",
    "addr:postcode":"06800",
    "addr:street":"Avda Reina Sofia",
    "iso:country":"ES",
    "sg:address":"Avda Reina Sofia, 98",
    "sg:city":"Merida",
    "sg:orig_category":"Agencias De Viajes",
    "sg:phone":"+34 924 38 72 15",
    "sg:postcode":"06800",
    "sg:province":"Badajoz",
    "wof:name":"Viajes Galan Tours S.l.",
    "wof:placetype":"venue"
},
  "geometry": {"coordinates":[-6.3240418434,38.9258232117],"type":"Point"}
}