{
  "type": "Feature",
  "properties": {
    "addr:full":"Crt. Argamasilla, Km. 0002,8 Puertollano Ciudad Real 13500",
    "addr:postcode":"13500",
    "addr:street":"Argamasilla Km. 0002,8",
    "iso:country":"ES",
    "sg:address":"Crt. Argamasilla, Km. 0002,8",
    "sg:city":"Puertollano",
    "sg:orig_category":"Asociaciones Y Clubs Deportivos",
    "sg:phone":"+34 926 44 15 44",
    "sg:postcode":"13500",
    "sg:province":"Ciudad Real",
    "sg:website":"www.decimas.es",
    "wof:name":"Tinmar Sport S.l.",
    "wof:placetype":"venue"
},
  "geometry": {"coordinates":[-4.1123538017,38.6858253479],"type":"Point"}
}