{
  "type": "Feature",
  "properties": {
    "addr:full":"Calle de Gobernador Fernandez Jimenez (del), 15 Segovia Segovia 40002",
    "addr:housenumber":"15",
    "addr:postcode":"40002",
    "addr:street":"Calle De Gobernador Fernandez Jimenez Del",
    "iso:country":"ES",
    "sg:address":"Calle de Gobernador Fernandez Jimenez (del), 15",
    "sg:city":"Segovia",
    "sg:orig_category":"Inform\u00c1tica Equipo Y Programas (al Por Mayor)",
    "sg:phone":"+34 921 44 05 24",
    "sg:postcode":"40002",
    "sg:province":"Segovia",
    "wof:name":"Linea On Time S.l.",
    "wof:placetype":"venue"
},
  "geometry": {"coordinates":[-4.1186461449,40.9446487427],"type":"Point"}
}