{
  "type": "Feature",
  "properties": {
    "addr:full":"Av Jaume I, 28 Reus Tarragona 43205",
    "addr:housenumber":"28",
    "addr:postcode":"43205",
    "addr:street":"Av Jaume I",
    "iso:country":"ES",
    "sg:address":"Av Jaume I, 28",
    "sg:city":"Reus",
    "sg:orig_category":"Inmobiliaria (agencias)",
    "sg:phone":"+34 977 30 04 61",
    "sg:postcode":"43205",
    "sg:province":"Tarragona",
    "wof:name":"Tarraco Inmobiliaria Del Hogar S.l.",
    "wof:placetype":"venue"
},
  "geometry": {"coordinates":[1.1103459597,41.1492767334],"type":"Point"}
}