{
  "type": "Feature",
  "properties": {
    "addr:full":"Ctra. Cadiz, 202 Malaga M\u00e1laga 29004",
    "addr:housenumber":"202",
    "addr:postcode":"29004",
    "addr:street":"Ctra. Cadiz;Ma\u0301Laga",
    "iso:country":"ES",
    "sg:address":"Ctra. Cadiz, 202",
    "sg:city":"Malaga",
    "sg:orig_category":"Explotaci\u00d3n De Canteras",
    "sg:phone":"+34 952 23 30 11",
    "sg:postcode":"29004",
    "sg:province":"M\u00e1laga",
    "wof:name":"Aridos El Pinar S. A.",
    "wof:placetype":"venue"
},
  "geometry": {"coordinates":[-4.4979224205,36.6372871399],"type":"Point"}
}