{
  "type": "Feature",
  "properties": {
    "addr:full":"Avda Costa, 127 Gijon Asturias 33204",
    "addr:housenumber":"127",
    "addr:postcode":"33204",
    "addr:street":"Avda Costa",
    "iso:country":"ES",
    "sg:address":"Avda Costa, 127",
    "sg:city":"Gijon",
    "sg:orig_category":"Molduras, Junquillos, Listones Y Molduras Perforadas",
    "sg:phone":"+34 985 36 06 47",
    "sg:postcode":"33204",
    "sg:province":"Asturias",
    "wof:name":"Fernandez Priesca Jorge Vicente",
    "wof:placetype":"venue"
},
  "geometry": {"coordinates":[-5.6493887901,43.5369110107],"type":"Point"}
}