{
  "type": "Feature",
  "properties": {
    "addr:full":"Rua Rosalia De Castro, 7 Vilamean Pontevedra 36350",
    "addr:housenumber":"7",
    "addr:postcode":"36350",
    "addr:street":"Rua Rosalia De Castro",
    "iso:country":"ES",
    "sg:address":"Rua Rosalia De Castro, 7",
    "sg:city":"Vilamean",
    "sg:orig_category":"Cl\u00cdnicas Dentales",
    "sg:phone":"+34 986 38 01 87",
    "sg:postcode":"36350",
    "sg:province":"Pontevedra",
    "wof:name":"Baldan Candida Maria Luisa",
    "wof:placetype":"venue"
},
  "geometry": {"coordinates":[-8.8062238693,42.141494751],"type":"Point"}
}