{
  "type": "Feature",
  "properties": {
    "iso:country":"ES",
    "sg:address":"Calle de General Mas De Gaminde, 45",
    "sg:city":"Palmas De Gran Canaria",
    "sg:orig_category":"Ropa De Hogar (al Por Menor)",
    "sg:phone":"+34 928 24 02 66",
    "sg:postcode":"35006",
    "sg:province":"Las Palmas",
    "wof:name":"Comcan S.c.p.",
    "wof:placetype":"venue"
},
  "geometry": {"coordinates":[-15.4338760376,28.1337013245],"type":"Point"}
}