{
  "type": "Feature",
  "properties": {
    "iso:country":"ES",
    "sg:address":"Calle de Francisco Salto, 12",
    "sg:city":"Rute",
    "sg:orig_category":"Fisioterapia",
    "sg:phone":"+34 957 53 23 18",
    "sg:postcode":"14960",
    "sg:province":"C\u00f3rdoba",
    "wof:name":"Siendones Ruiz Jose Manuel",
    "wof:placetype":"venue"
},
  "geometry": {"coordinates":[-4.3699431419,37.3249969482],"type":"Point"}
}