{
  "type": "Feature",
  "properties": {
    "addr:full":"Calle de San Pablo, 46 Zaragoza Zaragoza 50003",
    "addr:housenumber":"46",
    "addr:postcode":"50003",
    "addr:street":"Calle De San Pablo",
    "iso:country":"ES",
    "sg:address":"Calle de San Pablo, 46",
    "sg:city":"Zaragoza",
    "sg:orig_category":"Frutas Y Legumbres Secas (al Por Mayor)",
    "sg:phone":"+34 976 44 50 42",
    "sg:postcode":"50003",
    "sg:province":"Zaragoza",
    "wof:name":"Primitivo Gil E Hijos S.l.",
    "wof:placetype":"venue"
},
  "geometry": {"coordinates":[-0.8866400123,41.6560325623],"type":"Point"}
}