{
  "type": "Feature",
  "properties": {
    "addr:full":"Calle de Huertos (los), 6 Castro Urdiales Cantabria 39700",
    "addr:housenumber":"6",
    "addr:postcode":"39700",
    "addr:street":"Calle De Huertos Los",
    "iso:country":"ES",
    "sg:address":"Calle de Huertos (los), 6",
    "sg:city":"Castro Urdiales",
    "sg:orig_category":"Art\u00cdculos Funerarios (al Por Menor)",
    "sg:phone":"+34 942 86 15 34",
    "sg:postcode":"39700",
    "sg:province":"Cantabria",
    "wof:name":"Funeraria Merino Diez S.l.",
    "wof:placetype":"venue"
},
  "geometry": {"coordinates":[-3.2211940289,43.3839988708],"type":"Point"}
}