{
  "type": "Feature",
  "properties": {
    "addr:full":"Avgd Paiporta, 3 Benetusser Valencia 46910",
    "addr:housenumber":"3",
    "addr:postcode":"46910",
    "addr:street":"Paiporta",
    "iso:country":"ES",
    "sg:address":"Avgd Paiporta, 3",
    "sg:city":"Benetusser",
    "sg:orig_category":"Abogados",
    "sg:phone":"+34 963 96 43 50",
    "sg:postcode":"46910",
    "sg:province":"Valencia",
    "wof:name":"Paya Mortes Jaime",
    "wof:placetype":"venue"
},
  "geometry": {"coordinates":[-0.3954620063,39.4240989685],"type":"Point"}
}