{
  "type": "Feature",
  "properties": {
    "iso:country":"ES",
    "sg:address":"Carrer de Ciclisme, S/n",
    "sg:city":"Rubi",
    "sg:orig_category":"Producci\u00d3n, Venta De Productos De Agricultura Biol\u00d3gica",
    "sg:phone":"+34 935 88 29 75",
    "sg:postcode":"08191",
    "sg:province":"Barcelona",
    "wof:name":"Ecomiden Jj S. L.",
    "wof:placetype":"venue"
},
  "geometry": {"coordinates":[2.038850069,41.5024452209],"type":"Point"}
}