{
  "type": "Feature",
  "properties": {
    "iso:country":"ES",
    "sg:address":"Ctra. Lorca-baza, Km. 0073,0",
    "sg:city":"Albox",
    "sg:orig_category":"Agentes, Concesionarios Y Sucursales De Veh\u00cdculos",
    "sg:phone":"+34 950 43 08 56",
    "sg:postcode":"04800",
    "sg:province":"Almer\u00eda",
    "wof:name":"Automecanica Carrillo Martos S.l.",
    "wof:placetype":"venue"
},
  "geometry": {"coordinates":[-2.1253852844,37.4704399109],"type":"Point"}
}