{
  "type": "Feature",
  "properties": {
    "iso:country":"ES",
    "sg:address":"Bard Ciudad Jardin, S/n",
    "sg:city":"Marchena",
    "sg:orig_category":"Alimentaci\u00d3n General (al Por Menor)",
    "sg:phone":"+34 955 84 57 27",
    "sg:postcode":"41620",
    "sg:province":"Sevilla",
    "wof:name":"Martin Lopez Francisco Jose",
    "wof:placetype":"venue"
},
  "geometry": {"coordinates":[-5.426276207,37.3293685913],"type":"Point"}
}