{
  "type": "Feature",
  "properties": {
    "iso:country":"ES",
    "sg:address":"Calle de Carlos Ramirez De Arellano, 25",
    "sg:city":"Melilla",
    "sg:orig_category":"Doctores En Medicina",
    "sg:phone":"+34 952 68 30 32",
    "sg:postcode":"52004",
    "sg:province":"Melilla",
    "wof:name":"Crespillo Montes Enrique",
    "wof:placetype":"venue"
},
  "geometry": {"coordinates":[-2.9414598942,35.2887496948],"type":"Point"}
}