{
  "type": "Feature",
  "properties": {
    "addr:full":"Pase Esperanza, 2 Madrid Madrid 28005",
    "addr:housenumber":"2",
    "addr:postcode":"28005",
    "addr:street":"Esperanza",
    "iso:country":"ES",
    "sg:address":"Pase Esperanza, 2",
    "sg:city":"Madrid",
    "sg:orig_category":"Farmacias",
    "sg:phone":"+34 914 67 41 29",
    "sg:postcode":"28005",
    "sg:province":"Madrid",
    "wof:name":"Ayllon Martinez Julia",
    "wof:placetype":"venue"
},
  "geometry": {"coordinates":[-3.7063639164,40.403678894],"type":"Point"}
}