{
  "type": "Feature",
  "properties": {
    "iso:country":"ES",
    "sg:address":"Calle de Villaba\u00d1ez, 7",
    "sg:city":"Valladolid",
    "sg:orig_category":"Comerciantes Al Por Mayor De Vinos, Licores Y Alcoholes",
    "sg:phone":"+34 983 39 86 25",
    "sg:postcode":"47012",
    "sg:province":"Valladolid",
    "wof:name":"Maroto Martin Luis Melchor",
    "wof:placetype":"venue"
},
  "geometry": {"coordinates":[-4.7100148201,41.6498451233],"type":"Point"}
}