{
  "type": "Feature",
  "properties": {
    "iso:country":"ES",
    "sg:address":"Alam Poeta Para Vico, 10",
    "sg:city":"Sutullena",
    "sg:orig_category":"Albergues",
    "sg:phone":"+34 968 46 95 67",
    "sg:postcode":"30800",
    "sg:province":"Murcia",
    "wof:name":"Clara Import,s.l",
    "wof:placetype":"venue"
},
  "geometry": {"coordinates":[-1.6905640364,37.680557251],"type":"Point"}
}