{
  "type": "Feature",
  "properties": {
    "addr:full":"Calle de San Jose, 2 Hoyo De Pinares \u00c1vila 05250",
    "addr:housenumber":"2",
    "addr:postcode":"05250",
    "addr:street":"Calle De San Jose;A\u0301Vila",
    "iso:country":"ES",
    "sg:address":"Calle de San Jose, 2",
    "sg:city":"Hoyo De Pinares",
    "sg:orig_category":"Supermercados Y Hipermercados",
    "sg:phone":"+34 918 63 80 60",
    "sg:postcode":"05250",
    "sg:province":"\u00c1vila",
    "wof:name":"Carvajal Sanchez Mariano",
    "wof:placetype":"venue"
},
  "geometry": {"coordinates":[-4.4236841202,40.50207901],"type":"Point"}
}