{
  "type": "Feature",
  "properties": {
    "addr:full":"Carr Maragall, 11 Lleida Lleida 25003",
    "addr:housenumber":"11",
    "addr:postcode":"25003",
    "addr:street":"Carr Maragall",
    "iso:country":"ES",
    "sg:address":"Carr Maragall, 11",
    "sg:city":"Lleida",
    "sg:orig_category":"Fabricaci\u00d3n De Su\u00c9ters Y Chalecos De Punto",
    "sg:phone":"+34 973 27 81 29",
    "sg:postcode":"25003",
    "sg:province":"Lleida",
    "wof:name":"Almacenes Santacreu S. A.",
    "wof:placetype":"venue"
},
  "geometry": {"coordinates":[0.6178284883,41.6139297485],"type":"Point"}
}