{
  "type": "Feature",
  "properties": {
    "addr:full":"Calle de Alf Gralla Llado, 64 Palma Islas Baleares 07004",
    "addr:housenumber":"64",
    "addr:postcode":"07004",
    "addr:street":"Calle De Alf;Llado",
    "iso:country":"ES",
    "sg:address":"Calle de Alf Gralla Llado, 64",
    "sg:city":"Palma",
    "sg:orig_category":"Internados & Ense\u00d1anza Privada",
    "sg:phone":"+34 971 29 02 68",
    "sg:postcode":"07004",
    "sg:province":"Islas Baleares",
    "wof:name":"Instituto De Las Adoratrices Esclavas Del Smo Sacramento Y De La Caridad",
    "wof:placetype":"venue"
},
  "geometry": {"coordinates":[2.6611232758,39.5878982544],"type":"Point"}
}