{
  "type": "Feature",
  "properties": {
    "addr:full":"Calle de Zarza, 29 Poligono Ind. La Mora Valladolid 47193",
    "addr:housenumber":"29",
    "addr:postcode":"47193",
    "addr:street":"Calle De Zarza;Ind.",
    "iso:country":"ES",
    "sg:address":"Calle de Zarza, 29",
    "sg:city":"Poligono Ind. La Mora",
    "sg:orig_category":"Electricidad: Instaladores",
    "sg:phone":"+34 983 40 18 78",
    "sg:postcode":"47193",
    "sg:province":"Valladolid",
    "wof:name":"Ca\u00f1o Hurtado Luis Angel",
    "wof:placetype":"venue"
},
  "geometry": {"coordinates":[-4.6859240532,41.6106681824],"type":"Point"}
}