{
  "type": "Feature",
  "properties": {
    "iso:country":"ES",
    "sg:address":"Carr Baro De Maials, 16",
    "sg:city":"Lleida",
    "sg:orig_category":"Gastronom\u00cda: Especialidades Regionales (al Por Menor)",
    "sg:phone":"+34 973 25 40 63",
    "sg:postcode":"25005",
    "sg:province":"Lleida",
    "wof:name":"Martinez Magdaleno Jose",
    "wof:placetype":"venue"
},
  "geometry": {"coordinates":[0.6363289952,41.6219863892],"type":"Point"}
}