{
  "type": "Feature",
  "properties": {
    "iso:country":"ES",
    "sg:address":"Os Seixi\u00f1os, 5",
    "sg:city":"Seixi\u00d1os",
    "sg:orig_category":"Bebidas",
    "sg:phone":"+34 986 74 31 53",
    "sg:postcode":"36967",
    "sg:province":"Pontevedra",
    "wof:name":"Trelles Gonzalez Jose",
    "wof:placetype":"venue"
},
  "geometry": {"coordinates":[-8.8113698959,42.4530296326],"type":"Point"}
}