{
  "type": "Feature",
  "properties": {
    "iso:country":"ES",
    "sg:address":"Calle de Huelva, 3",
    "sg:city":"Ubeda",
    "sg:orig_category":"Mec\u00c1nico Del Autom\u00d3vil",
    "sg:phone":"+34 953 75 32 53",
    "sg:postcode":"23400",
    "sg:province":"Ja\u00e9n",
    "wof:name":"Herrera Martos Juan Sebastian",
    "wof:placetype":"venue"
},
  "geometry": {"coordinates":[-3.3778688908,38.0129623413],"type":"Point"}
}