{
  "type": "Feature",
  "properties": {
    "addr:full":"Calle de Carlos Aurioles, 6 Madrid Madrid 28018",
    "addr:housenumber":"6",
    "addr:postcode":"28018",
    "addr:street":"Calle De Carlos Aurioles",
    "iso:country":"ES",
    "sg:address":"Calle de Carlos Aurioles, 6",
    "sg:city":"Madrid",
    "sg:orig_category":"Suministros Para Hoteles",
    "sg:phone":"+34 917 85 15 51",
    "sg:postcode":"28018",
    "sg:province":"Madrid",
    "wof:name":"Verano Ayllon Jose",
    "wof:placetype":"venue"
},
  "geometry": {"coordinates":[-3.6655879021,40.3838157654],"type":"Point"}
}