{
  "type": "Feature",
  "properties": {
    "addr:full":"Calle de Bizkai, 1 Galdakao Vizcaya 48960",
    "addr:housenumber":"1",
    "addr:postcode":"48960",
    "addr:street":"Calle De Bizkai",
    "iso:country":"ES",
    "sg:address":"Calle de Bizkai, 1",
    "sg:city":"Galdakao",
    "sg:orig_category":"Librer\u00cdas",
    "sg:phone":"+34 944 56 27 19",
    "sg:postcode":"48960",
    "sg:province":"Vizcaya",
    "wof:name":"Prensa Y Revistas La Cruz S.l",
    "wof:placetype":"venue"
},
  "geometry": {"coordinates":[-2.846449852,43.2340698242],"type":"Point"}
}