{
  "type": "Feature",
  "properties": {
    "addr:full":"Ctra Salinas, S/n Casco Viejo Navarra 31191",
    "addr:housenumber":"s / n",
    "addr:postcode":"31191",
    "addr:street":"Ctra Salinas",
    "iso:country":"ES",
    "sg:address":"Ctra Salinas, S/n",
    "sg:city":"Casco Viejo",
    "sg:orig_category":"Madera Para Construcci\u00d3n E Industria",
    "sg:phone":"+34 948 20 28 00",
    "sg:postcode":"31191",
    "sg:province":"Navarra",
    "wof:name":"Gonvauto Navarra S.a.",
    "wof:placetype":"venue"
},
  "geometry": {"coordinates":[-1.6518089771,42.7533912659],"type":"Point"}
}