{
  "type": "Feature",
  "properties": {
    "addr:full":"Calle de Alcalde Sainz De Baranda, 89 Madrid Madrid 28007",
    "addr:housenumber":"89",
    "addr:postcode":"madrid;28007",
    "addr:street":"Calle De Alcalde Sainz De Baranda",
    "iso:country":"ES",
    "sg:address":"Calle de Alcalde Sainz De Baranda, 89",
    "sg:city":"Madrid",
    "sg:orig_category":"Administradores De Bienes Y Delegados De Comunidades De Propietarios",
    "sg:phone":"+34 915 04 20 61",
    "sg:postcode":"28007",
    "sg:province":"Madrid",
    "wof:name":"Administralia Administracion De Fincas S.l.",
    "wof:placetype":"venue"
},
  "geometry": {"coordinates":[-3.668025732,40.4173049927],"type":"Point"}
}