{
  "type": "Feature",
  "properties": {
    "addr:full":"Calle de Isabel Ferrer, 68 Castellon Castell\u00f3n 12001",
    "addr:housenumber":"68",
    "addr:postcode":"12001",
    "addr:street":"Calle De Isabel Ferrer",
    "iso:country":"ES",
    "sg:address":"Calle de Isabel Ferrer, 68",
    "sg:city":"Castellon",
    "sg:orig_category":"Trabajos De Topograf\u00cda",
    "sg:phone":"+34 964 23 78 83",
    "sg:postcode":"12001",
    "sg:province":"Castell\u00f3n",
    "wof:name":"Masip Piqueras Miguel",
    "wof:placetype":"venue"
},
  "geometry": {"coordinates":[-0.0362810008,39.9885101318],"type":"Point"}
}