{
  "type": "Feature",
  "properties": {
    "iso:country":"ES",
    "sg:address":"Calle de General Vara De Rey, 41",
    "sg:city":"Logro\u00f1o",
    "sg:orig_category":"Alquiler De Veh\u00cdculos: Turismos Y Utilitarios",
    "sg:phone":"+34 941 24 57 03",
    "sg:postcode":"26002",
    "sg:province":"La Rioja",
    "sg:website":"www.autorentingrioja.com",
    "wof:name":"Auto Renting Rioja Sa",
    "wof:placetype":"venue"
},
  "geometry": {"coordinates":[-2.4466691017,42.4585189819],"type":"Point"}
}