{
  "type": "Feature",
  "properties": {
    "iso:country":"ES",
    "sg:address":"Carrer de Maladeta, 32",
    "sg:city":"Hospitalet Llobregat",
    "sg:orig_category":"Cristaler\u00cdas",
    "sg:phone":"+34 934 37 36 04",
    "sg:postcode":"08906",
    "sg:province":"Barcelona",
    "wof:name":"Guerrero Vi\u00f1ueca Eduardo",
    "wof:placetype":"venue"
},
  "geometry": {"coordinates":[2.1008601189,41.373500824],"type":"Point"}
}