{
  "type": "Feature",
  "properties": {
    "addr:full":"C/ 15, 15 Ca\u00d1ada Valencia 46182",
    "addr:housenumber":"15",
    "addr:postcode":"46182",
    "addr:street":"C / 15",
    "iso:country":"ES",
    "sg:address":"C/ 15, 15",
    "sg:city":"Ca\u00d1ada",
    "sg:orig_category":"Centros Empresariales",
    "sg:phone":"+34 961 32 08 15",
    "sg:postcode":"46182",
    "sg:province":"Valencia",
    "wof:name":"Martinez Gimenez Maria",
    "wof:placetype":"venue"
},
  "geometry": {"coordinates":[-0.4903610051,39.5279884338],"type":"Point"}
}