{
  "type": "Feature",
  "properties": {
    "addr:full":"Plaz Espa\u00d1a, 2 Melgar Fernamental Burgos 09100",
    "addr:housenumber":"2",
    "addr:postcode":"09100",
    "addr:street":"Plaz Espan\u0303A;Fernamental",
    "iso:country":"ES",
    "sg:address":"Plaz Espa\u00d1a, 2",
    "sg:city":"Melgar Fernamental",
    "sg:orig_category":"Bancos",
    "sg:phone":"+34 947 37 20 03",
    "sg:postcode":"09100",
    "sg:province":"Burgos",
    "sg:website":"www.banesto.es",
    "wof:name":"Banco Espa\u00f1ol De Credito S.a.",
    "wof:placetype":"venue"
},
  "geometry": {"coordinates":[-4.2453022003,42.4037704468],"type":"Point"}
}