{
  "type": "Feature",
  "properties": {
    "addr:full":"Calle de Geranio, 23 Puebla Alfinden Zaragoza 50171",
    "addr:housenumber":"23",
    "addr:postcode":"50171",
    "addr:street":"Calle De Geranio;Alfinden",
    "iso:country":"ES",
    "sg:address":"Calle de Geranio, 23",
    "sg:city":"Puebla Alfinden",
    "sg:orig_category":"Fabricaci\u00d3n De Cervezas",
    "sg:phone":"+34 976 10 82 74",
    "sg:postcode":"50171",
    "sg:province":"Zaragoza",
    "wof:name":"Serteco Aragon S.c",
    "wof:placetype":"venue"
},
  "geometry": {"coordinates":[-0.7687630057,41.6391067505],"type":"Point"}
}