{
  "type": "Feature",
  "properties": {
    "addr:full":"Plaz Villa (la), 4 Socovos Albacete 02435",
    "addr:housenumber":"4",
    "addr:postcode":"02435",
    "iso:country":"ES",
    "sg:address":"Plaz Villa (la), 4",
    "sg:city":"Socovos",
    "sg:orig_category":"Cajas Para Embalar",
    "sg:phone":"+34 967 42 00 04",
    "sg:postcode":"02435",
    "sg:province":"Albacete",
    "wof:name":"Caja Rural De Albacete",
    "wof:placetype":"venue"
},
  "geometry": {"coordinates":[-1.9884489775,38.3332366943],"type":"Point"}
}