{
  "type": "Feature",
  "properties": {
    "iso:country":"ES",
    "sg:address":"Calle de Felipe Ii, 70",
    "sg:city":"Yuncos",
    "sg:orig_category":"Agentes, Concesionarios Y Sucursales De Veh\u00cdculos",
    "sg:phone":"+34 925 53 61 51",
    "sg:postcode":"45210",
    "sg:province":"Toledo",
    "wof:name":"Safety Car Rentacar S.l.",
    "wof:placetype":"venue"
},
  "geometry": {"coordinates":[-3.870609045,40.0945091248],"type":"Point"}
}