{
  "type": "Feature",
  "properties": {
    "addr:full":"Carr Lleida, 52 Torregrossa Lleida 25141",
    "addr:housenumber":"52",
    "addr:postcode":"25141",
    "addr:street":"Carr Lleida",
    "iso:country":"ES",
    "sg:address":"Carr Lleida, 52",
    "sg:city":"Torregrossa",
    "sg:orig_category":"Peluqueros: De Se\u00d1oras",
    "sg:phone":"+34 973 17 02 47",
    "sg:postcode":"25141",
    "sg:province":"Lleida",
    "wof:name":"Ala Piera Maria Mercedes",
    "wof:placetype":"venue"
},
  "geometry": {"coordinates":[0.8280332088,41.5811882019],"type":"Point"}
}