{
  "type": "Feature",
  "properties": {
    "addr:full":"Calle de Lanjaron, 1 Almeria Almer\u00eda 04007",
    "addr:housenumber":"1",
    "addr:postcode":"04007",
    "addr:street":"Calle De Lanjaron",
    "iso:country":"ES",
    "sg:address":"Calle de Lanjaron, 1",
    "sg:city":"Almeria",
    "sg:orig_category":"Parafarmacias",
    "sg:phone":"+34 950 27 54 50",
    "sg:postcode":"04007",
    "sg:province":"Almer\u00eda",
    "wof:name":"Mu\u00f1oz Gutierrez Maria De Las Nieves",
    "wof:placetype":"venue"
},
  "geometry": {"coordinates":[-2.4506709576,36.8302307129],"type":"Point"}
}