{
  "type": "Feature",
  "properties": {
    "addr:full":"Vinya Vella, S/n Maia Montcal Girona 17851",
    "addr:housenumber":"s / n",
    "addr:postcode":"17851",
    "iso:country":"ES",
    "sg:address":"Vinya Vella, S/n",
    "sg:city":"Maia Montcal",
    "sg:orig_category":"Escayola Y Productos De Escayola (fabricaci\u00d3n, Al Por Mayor)",
    "sg:phone":"+34 972 59 07 41",
    "sg:postcode":"17851",
    "sg:province":"Girona",
    "wof:name":"Roca Vinyals Distribucions S.l.",
    "wof:placetype":"venue"
},
  "geometry": {"coordinates":[2.7448050976,42.2212715149],"type":"Point"}
}