{
  "type": "Feature",
  "properties": {
    "addr:full":"Avda Teruel, 1 Daroca Zaragoza 50360",
    "addr:housenumber":"1",
    "addr:postcode":"50360",
    "addr:street":"Avda Teruel",
    "iso:country":"ES",
    "sg:address":"Avda Teruel, 1",
    "sg:city":"Daroca",
    "sg:orig_category":"Procuradores",
    "sg:phone":"+34 976 80 08 91",
    "sg:postcode":"50360",
    "sg:province":"Zaragoza",
    "wof:name":"Juberias Hernandez Ana Maria",
    "wof:placetype":"venue"
},
  "geometry": {"coordinates":[-1.4165589809,41.109336853],"type":"Point"}
}