{
  "type": "Feature",
  "properties": {
    "iso:country":"ES",
    "sg:address":"Calle de Benegas, 16",
    "sg:city":"Badajoz",
    "sg:orig_category":"Prot\u00c9sicos Dentales",
    "sg:phone":"+34 924 26 26 05",
    "sg:postcode":"06002",
    "sg:province":"Badajoz",
    "wof:name":"Ortega Nu\u00f1ez Bernabe",
    "wof:placetype":"venue"
},
  "geometry": {"coordinates":[-6.9668054581,38.8788032532],"type":"Point"}
}