{
  "type": "Feature",
  "properties": {
    "addr:full":"Can Salv\u00e1, S/n Riells Girona 17404",
    "addr:housenumber":"s / n",
    "addr:postcode":"17404",
    "iso:country":"ES",
    "sg:address":"Can Salv\u00e1, S/n",
    "sg:city":"Riells",
    "sg:orig_category":"Administraciones Regionales, Departamentales Y Locales",
    "sg:phone":"+34 972 87 04 18",
    "sg:postcode":"17404",
    "sg:province":"Girona",
    "wof:name":"Ajuntament Riells I Viabrea",
    "wof:placetype":"venue"
},
  "geometry": {"coordinates":[2.5122041702,41.7767219543],"type":"Point"}
}