{
  "type": "Feature",
  "properties": {
    "addr:full":"Calle de Juan Zofio, 14 Madrid Madrid 28026",
    "addr:housenumber":"14",
    "addr:postcode":"madrid;28026",
    "addr:street":"Calle De Juan Zofio",
    "iso:country":"ES",
    "sg:address":"Calle de Juan Zofio, 14",
    "sg:city":"Madrid",
    "sg:orig_category":"Rectificaci\u00d3n, Mecanizado, Fresado",
    "sg:phone":"+34 915 60 35 41",
    "sg:postcode":"28026",
    "sg:province":"Madrid",
    "wof:name":"San Jose Prieto Alfonso",
    "wof:placetype":"venue"
},
  "geometry": {"coordinates":[-3.7152369022,40.3811645508],"type":"Point"}
}