{
  "type": "Feature",
  "properties": {
    "addr:full":"Calle de Alameda, 18 Marchamalo Guadalajara 19180",
    "addr:housenumber":"18",
    "addr:postcode":"19180",
    "addr:street":"Calle De Alameda",
    "iso:country":"ES",
    "sg:address":"Calle de Alameda, 18",
    "sg:city":"Marchamalo",
    "sg:orig_category":"Carnicer\u00cdas, Carnicer\u00cdas",
    "sg:phone":"+34 949 25 08 41",
    "sg:postcode":"19180",
    "sg:province":"Guadalajara",
    "wof:name":"Moreno Moreno Jose",
    "wof:placetype":"venue"
},
  "geometry": {"coordinates":[-3.2012093067,40.6683616638],"type":"Point"}
}