{
  "type": "Feature",
  "properties": {
    "iso:country":"ES",
    "sg:address":"Sabadell (p I Martin Jara), S/n",
    "sg:city":"Sierra Yeguas",
    "sg:orig_category":"Freidur\u00cdas: Equipos Y Suministros",
    "sg:phone":"+34 952 74 65 71",
    "sg:postcode":"29328",
    "sg:province":"M\u00e1laga",
    "wof:name":"El Tio De Las Papas S.l.l.",
    "wof:placetype":"venue"
},
  "geometry": {"coordinates":[-4.8733038902,37.1233901978],"type":"Point"}
}