{
  "type": "Feature",
  "properties": {
    "iso:country":"ES",
    "sg:address":"Pol Ind Binissalem, S/n",
    "sg:city":"Binissalem",
    "sg:orig_category":"Congelados: Productos Alimentarios (fabricaci\u00d3n, Al Por Mayor)",
    "sg:phone":"+34 971 88 63 96",
    "sg:postcode":"07350",
    "sg:province":"Islas Baleares",
    "wof:name":"Congelados Continental S.l.",
    "wof:placetype":"venue"
},
  "geometry": {"coordinates":[2.8762800694,39.6658592224],"type":"Point"}
}