{
  "type": "Feature",
  "properties": {
    "addr:full":"Calle de Beniel, 6 Torrevieja Alicante 03180",
    "addr:housenumber":"6",
    "addr:postcode":"03180",
    "addr:street":"Calle De Beniel",
    "iso:country":"ES",
    "sg:address":"Calle de Beniel, 6",
    "sg:city":"Torrevieja",
    "sg:orig_category":"Importaci\u00d3n",
    "sg:phone":"+34 966 70 21 14",
    "sg:postcode":"03180",
    "sg:province":"Alicante",
    "wof:name":"Herrero Ros Josefina",
    "wof:placetype":"venue"
},
  "geometry": {"coordinates":[-0.693932116,37.9738006592],"type":"Point"}
}