{
  "type": "Feature",
  "properties": {
    "iso:country":"ES",
    "sg:address":"Calle de Puerta Nueva, S/n",
    "sg:city":"San Lorenzo",
    "sg:orig_category":"Loter\u00cda Y T\u00d3mbola",
    "sg:phone":"+34 968 23 72 00",
    "sg:postcode":"30008",
    "sg:province":"Murcia",
    "wof:name":"Carrillo Molina Emilio",
    "wof:placetype":"venue"
},
  "geometry": {"coordinates":[-1.1280989647,37.9912605286],"type":"Point"}
}