{
  "type": "Feature",
  "properties": {
    "addr:full":"Calle de Unceta, 56 Zaragoza Zaragoza 50010",
    "addr:housenumber":"56",
    "addr:postcode":"50010",
    "addr:street":"Calle De Unceta",
    "iso:country":"ES",
    "sg:address":"Calle de Unceta, 56",
    "sg:city":"Zaragoza",
    "sg:orig_category":"Reposter\u00cdas",
    "sg:phone":"+34 976 32 49 41",
    "sg:postcode":"50010",
    "sg:province":"Zaragoza",
    "wof:name":"Gasca Domenech Pascual",
    "wof:placetype":"venue"
},
  "geometry": {"coordinates":[-0.9014610052,41.6507644653],"type":"Point"}
}