{
  "type": "Feature",
  "properties": {
    "iso:country":"ES",
    "sg:address":"Avda Fernando Conde, 38",
    "sg:city":"Estrada",
    "sg:orig_category":"Centros Empresariales",
    "sg:phone":"+34 986 58 48 49",
    "sg:postcode":"36680",
    "sg:province":"Pontevedra",
    "wof:name":"Ignire Sofiwere Empresariales Sl",
    "wof:placetype":"venue"
},
  "geometry": {"coordinates":[-8.4829673767,42.6898384094],"type":"Point"}
}