{
  "type": "Feature",
  "properties": {
    "iso:country":"ES",
    "sg:address":"Ctra Farhana, 96",
    "sg:city":"Melilla",
    "sg:orig_category":"Abogados",
    "sg:phone":"+34 952 69 58 56",
    "sg:postcode":"52005",
    "sg:province":"Melilla",
    "wof:name":"Afle S.l.",
    "wof:placetype":"venue"
},
  "geometry": {"coordinates":[-2.9583933353,35.2935371399],"type":"Point"}
}