{
  "type": "Feature",
  "properties": {
    "iso:country":"ES",
    "sg:address":"Calle de Juan Perez Zu\u00d1iga, 24",
    "sg:city":"Madrid",
    "sg:orig_category":"Panader\u00cdas, Panader\u00cdas",
    "sg:phone":"+34 914 08 99 46",
    "sg:postcode":"28027",
    "sg:province":"Madrid",
    "wof:name":"Moreno Garcia Ribera S.a.",
    "wof:placetype":"venue"
},
  "geometry": {"coordinates":[-3.6474421024,40.4434928894],"type":"Point"}
}