{
  "type": "Feature",
  "properties": {
    "addr:full":"Calle de San Juan, 18 Ostiz Navarra 31799",
    "addr:housenumber":"18",
    "addr:postcode":"31799",
    "addr:street":"Calle De San Juan",
    "iso:country":"ES",
    "sg:address":"Calle de San Juan, 18",
    "sg:city":"Ostiz",
    "sg:orig_category":"Fabricaci\u00d3n, Distribuci\u00d3n De Material Para La Climatizaci\u00d3n, Aireaci\u00d3n Y Ventilaci\u00d3n",
    "sg:phone":"+34 948 30 71 04",
    "sg:postcode":"31799",
    "sg:province":"Navarra",
    "sg:website":"perso.wanadoo.es/deshollinadospopins",
    "wof:name":"San Martin Morote Rafael",
    "wof:placetype":"venue"
},
  "geometry": {"coordinates":[-1.6185979843,42.913734436],"type":"Point"}
}