{
  "type": "Feature",
  "properties": {
    "iso:country":"ES",
    "sg:address":"Calle de Redonda, S/n",
    "sg:city":"Rambla",
    "sg:orig_category":"Pesca Y Caza: Art\u00cdculos (al Por Menor)",
    "sg:phone":"+34 957 68 28 89",
    "sg:postcode":"14540",
    "sg:province":"C\u00f3rdoba",
    "wof:name":"Sociedad De Cazadores De La Rambla",
    "wof:placetype":"venue"
},
  "geometry": {"coordinates":[-4.7444868088,37.6043624878],"type":"Point"}
}