{
  "type": "Feature",
  "properties": {
    "iso:country":"ES",
    "sg:address":"Calle de Federico Garcia Lorca, 1",
    "sg:city":"Burgos",
    "sg:orig_category":"Producci\u00d3n, Distribuci\u00d3n De Electricidad",
    "sg:phone":"+34 947 47 07 34",
    "sg:postcode":"09007",
    "sg:province":"Burgos",
    "wof:name":"Garcia Perez Luis",
    "wof:placetype":"venue"
},
  "geometry": {"coordinates":[-3.6666903496,42.3498268127],"type":"Point"}
}