{
  "type": "Feature",
  "properties": {
    "addr:full":"Calle de Ciudad De Mula, 13 Valencia Valencia 46021",
    "addr:housenumber":"13",
    "addr:postcode":"46021",
    "addr:street":"Calle De Ciudad De Mula",
    "iso:country":"ES",
    "sg:address":"Calle de Ciudad De Mula, 13",
    "sg:city":"Valencia",
    "sg:orig_category":"Estudios, Instalaci\u00d3n De Climatizaci\u00d3n",
    "sg:phone":"+34 963 93 11 85",
    "sg:postcode":"46021",
    "sg:province":"Valencia",
    "wof:name":"Serma Servicios De Mantenimiento S. A.",
    "wof:placetype":"venue"
},
  "geometry": {"coordinates":[-0.3540099859,39.4744033813],"type":"Point"}
}