{
  "type": "Feature",
  "properties": {
    "iso:country":"ES",
    "sg:address":"Calle de Fray Luis De Leon, 22",
    "sg:city":"Valladolid",
    "sg:orig_category":"Promotores Constructores",
    "sg:phone":"+34 983 29 87 46",
    "sg:postcode":"47002",
    "sg:province":"Valladolid",
    "sg:website":"www.const-level.es",
    "wof:name":"Constructora Level S.a.",
    "wof:placetype":"venue"
},
  "geometry": {"coordinates":[-4.721560955,41.6504440308],"type":"Point"}
}