{
  "type": "Feature",
  "properties": {
    "iso:country":"ES",
    "sg:address":"Calle de Juan Montes Hoyo, 2",
    "sg:city":"Malaga",
    "sg:orig_category":"Ropa De Trabajo Y Profesionales (fabricaci\u00d3n, Al Por Mayor)",
    "sg:phone":"+34 952 26 34 06",
    "sg:postcode":"29014",
    "sg:province":"M\u00e1laga",
    "wof:name":"Confecciones Macahi S.a.",
    "wof:placetype":"venue"
},
  "geometry": {"coordinates":[-4.4202399254,36.7502937317],"type":"Point"}
}