{
  "type": "Feature",
  "properties": {
    "addr:full":"Calle de Arroyo, 4 Marmolejo Ja\u00e9n 23770",
    "addr:housenumber":"4",
    "addr:postcode":"23770",
    "addr:street":"Calle De Arroyo;Jae\u0301N",
    "iso:country":"ES",
    "sg:address":"Calle de Arroyo, 4",
    "sg:city":"Marmolejo",
    "sg:orig_category":"Zapatos (al Por Menor)",
    "sg:phone":"+34 953 54 02 76",
    "sg:postcode":"23770",
    "sg:province":"Ja\u00e9n",
    "wof:name":"Vicaria Arevalo Alfonso",
    "wof:placetype":"venue"
},
  "geometry": {"coordinates":[-4.1708250046,38.0458030701],"type":"Point"}
}