{
  "type": "Feature",
  "properties": {
    "iso:country":"ES",
    "sg:address":"Carrer de Fabrica, 44",
    "sg:city":"Palma",
    "sg:orig_category":"Reposter\u00cdas",
    "sg:phone":"+34 971 73 90 50",
    "sg:postcode":"07013",
    "sg:province":"Islas Baleares",
    "wof:name":"Ferriol Bergas Juan",
    "wof:placetype":"venue"
},
  "geometry": {"coordinates":[2.6360330582,39.5732154846],"type":"Point"}
}