{
  "type": "Feature",
  "properties": {
    "iso:country":"ES",
    "sg:address":"Doctor J Vega Santos, 12",
    "sg:city":"Trobajo Camino",
    "sg:orig_category":"Promotores Constructores",
    "sg:phone":"+34 987 80 26 43",
    "sg:postcode":"24010",
    "sg:province":"Le\u00f3n",
    "wof:name":"Comunidad De Propietarios Doctor Vega, 12",
    "wof:placetype":"venue"
},
  "geometry": {"coordinates":[-5.5716600418,42.5981292725],"type":"Point"}
}