{
  "type": "Feature",
  "properties": {
    "iso:country":"ES",
    "sg:address":"Calle de Teresa Gil, 16",
    "sg:city":"Valladolid",
    "sg:orig_category":"M\u00c1quinas De Coser Y De Hacer Punto (al Por Mayor)",
    "sg:phone":"+34 983 30 30 88",
    "sg:postcode":"47002",
    "sg:province":"Valladolid",
    "sg:website":"www.virtoindustrial.es",
    "wof:name":"Virto Industrial S.l.",
    "wof:placetype":"venue"
},
  "geometry": {"coordinates":[-4.7259340286,41.6507453918],"type":"Point"}
}