{
  "type": "Feature",
  "properties": {
    "addr:full":"Carr Cerveri De Girona, 9 Girona Girona 17001",
    "addr:housenumber":"9",
    "addr:postcode":"17001",
    "addr:street":"Carr Cerveri;Girona",
    "iso:country":"ES",
    "sg:address":"Carr Cerveri De Girona, 9",
    "sg:city":"Girona",
    "sg:orig_category":"Caf\u00c9s, Bares, Cervecer\u00cdas",
    "sg:phone":"+34 972 20 86 16",
    "sg:postcode":"17001",
    "sg:province":"Girona",
    "wof:name":"El Cafe De La Devesa S.l",
    "wof:placetype":"venue"
},
  "geometry": {"coordinates":[2.8187448978,41.9808616638],"type":"Point"}
}