{
  "type": "Feature",
  "properties": {
    "addr:full":"Carrer de Fluvia, 247 Barcelona Barcelona 08020",
    "addr:housenumber":"247",
    "addr:postcode":"08020",
    "addr:street":"Carrer De Fluvia",
    "iso:country":"ES",
    "sg:address":"Carrer de Fluvia, 247",
    "sg:city":"Barcelona",
    "sg:orig_category":"Fijaciones Industriales",
    "sg:phone":"+34 933 07 16 72",
    "sg:postcode":"08020",
    "sg:province":"Barcelona",
    "wof:name":"Garcia Cortes Pedro",
    "wof:placetype":"venue"
},
  "geometry": {"coordinates":[2.1948609352,41.4159812927],"type":"Point"}
}