{
  "type": "Feature",
  "properties": {
    "addr:full":"Calle de Loiola, 14 Donostia-san Sebastian Guip\u00f9zcoa 20005",
    "addr:housenumber":"14",
    "addr:postcode":"20005",
    "addr:street":"Calle De Loiola",
    "iso:country":"ES",
    "sg:address":"Calle de Loiola, 14",
    "sg:city":"Donostia-san Sebastian",
    "sg:orig_category":"Institutos De Belleza",
    "sg:phone":"+34 943 42 05 66",
    "sg:postcode":"20005",
    "sg:province":"Guip\u00f9zcoa",
    "wof:name":"Urcola Echeverria Loreto",
    "wof:placetype":"venue"
},
  "geometry": {"coordinates":[-1.9822740555,43.3174705505],"type":"Point"}
}