{
  "type": "Feature",
  "properties": {
    "addr:full":"Calle de Profesor Waksman, 3 Madrid Madrid 28036",
    "addr:housenumber":"3",
    "addr:postcode":"28036",
    "addr:street":"Calle De Profesor Waksman",
    "iso:country":"ES",
    "sg:address":"Calle de Profesor Waksman, 3",
    "sg:city":"Madrid",
    "sg:orig_category":"Asesor\u00cda Fiscal Y Jur\u00cddica",
    "sg:phone":"+34 914 57 22 53",
    "sg:postcode":"28036",
    "sg:province":"Madrid",
    "wof:name":"Medbroker S.l.",
    "wof:placetype":"venue"
},
  "geometry": {"coordinates":[-3.6891980171,40.4562110901],"type":"Point"}
}