{
  "type": "Feature",
  "properties": {
    "iso:country":"ES",
    "sg:address":"Calle de Zacatin, 2",
    "sg:city":"Granada",
    "sg:orig_category":"Farmacias",
    "sg:phone":"+34 958 22 12 83",
    "sg:postcode":"18001",
    "sg:province":"Granada",
    "wof:name":"Salto Mendez-trelles Antonio Francisco",
    "wof:placetype":"venue"
},
  "geometry": {"coordinates":[-3.599296093,37.1749610901],"type":"Point"}
}