{
  "type": "Feature",
  "properties": {
    "iso:country":"ES",
    "sg:address":"Calle de Eduardo Iglesias, 3",
    "sg:city":"Gondomar",
    "sg:orig_category":"Reposter\u00cdas",
    "sg:phone":"+34 986 36 00 31",
    "sg:postcode":"36380",
    "sg:province":"Pontevedra",
    "wof:name":"Panaderia Copena Pasteleria S.l.",
    "wof:placetype":"venue"
},
  "geometry": {"coordinates":[-8.7612495422,42.1117134094],"type":"Point"}
}