{
  "type": "Feature",
  "properties": {
    "iso:country":"ES",
    "sg:address":"Calle de Dehesa, 47",
    "sg:city":"Valmojado",
    "sg:orig_category":"Negocio De Materiales De Construcci\u00d3n",
    "sg:phone":"+34 918 17 05 28",
    "sg:postcode":"45940",
    "sg:province":"Toledo",
    "wof:name":"Rodriguez Rodriguez Juan Jose",
    "wof:placetype":"venue"
},
  "geometry": {"coordinates":[-4.0931715965,40.2055664062],"type":"Point"}
}