{
  "type": "Feature",
  "properties": {
    "iso:country":"ES",
    "sg:address":"Calle de Torre Heliodoro De La, 2",
    "sg:city":"Bilbao",
    "sg:orig_category":"Asociaciones, Organismos Culturales Y Socioeducativos",
    "sg:phone":"+34 944 47 70 66",
    "sg:postcode":"48014",
    "sg:province":"Vizcaya",
    "wof:name":"Talleres Aurrera S.l",
    "wof:placetype":"venue"
},
  "geometry": {"coordinates":[-2.9440732002,43.2694396973],"type":"Point"}
}