{
  "type": "Feature",
  "properties": {
    "addr:full":"Calle de Simon De Pineda, S/n Sevilla Sevilla 41005",
    "addr:housenumber":"s / n",
    "addr:postcode":"41005",
    "addr:street":"Calle De Simon De Pineda",
    "iso:country":"ES",
    "sg:address":"Calle de Simon De Pineda, S/n",
    "sg:city":"Sevilla",
    "sg:orig_category":"Lavado, Limpieza De Veh\u00cdculos",
    "sg:phone":"+34 954 92 19 57",
    "sg:postcode":"41005",
    "sg:province":"Sevilla",
    "wof:name":"Imo Autolavados S.a",
    "wof:placetype":"venue"
},
  "geometry": {"coordinates":[-5.9613342285,37.3785934448],"type":"Point"}
}