{
  "type": "Feature",
  "properties": {
    "iso:country":"ES",
    "sg:address":"Calle de Villanubla, 17",
    "sg:city":"Valladolid",
    "sg:orig_category":"Internados & Ense\u00d1anza Privada",
    "sg:phone":"+34 983 33 31 41",
    "sg:postcode":"47009",
    "sg:province":"Valladolid",
    "wof:name":"Siervas Del Evangelio",
    "wof:placetype":"venue"
},
  "geometry": {"coordinates":[-4.7350797653,41.663143158],"type":"Point"}
}