{
  "type": "Feature",
  "properties": {
    "iso:country":"ES",
    "sg:address":"Av. De Huelva, S/n",
    "sg:city":"Sanlucar",
    "sg:orig_category":"Centros De Educaci\u00d3n Especial",
    "sg:phone":"+34 956 36 17 57",
    "sg:postcode":"11540",
    "sg:province":"C\u00e1diz",
    "wof:name":"Junta De Andalucia",
    "wof:placetype":"venue"
},
  "geometry": {"coordinates":[-6.339193821,36.7904167175],"type":"Point"}
}