{
  "type": "Feature",
  "properties": {
    "iso:country":"ES",
    "sg:address":"Calle de Sierra De Ronda, 15",
    "sg:city":"Viator",
    "sg:orig_category":"Agencias Y Asesores De Publicidad",
    "sg:phone":"+34 950 30 60 03",
    "sg:postcode":"04240",
    "sg:province":"Almer\u00eda",
    "wof:name":"Lopez Calatrava Cintpapel S.l.",
    "wof:placetype":"venue"
},
  "geometry": {"coordinates":[-2.4199690819,36.8799285889],"type":"Point"}
}