{
  "type": "Feature",
  "properties": {
    "iso:country":"ES",
    "sg:address":"Carrer de Amadeu Vives, 13",
    "sg:city":"Mataro",
    "sg:orig_category":"Ropa Para Se\u00d1oras (al Por Menor)",
    "sg:phone":"+34 937 99 26 25",
    "sg:postcode":"08304",
    "sg:province":"Barcelona",
    "wof:name":"Figueroa De La Osada Maria Del Pilar",
    "wof:placetype":"venue"
},
  "geometry": {"coordinates":[2.4435250759,41.5507164001],"type":"Point"}
}