{
  "type": "Feature",
  "properties": {
    "addr:full":"Avda Espa\u00d1a, 225 Rozas De Madrid Madrid 28231",
    "addr:housenumber":"225",
    "addr:postcode":"28231",
    "addr:street":"Avda Espan\u0303A",
    "iso:country":"ES",
    "sg:address":"Avda Espa\u00d1a, 225",
    "sg:city":"Rozas De Madrid",
    "sg:orig_category":"Inform\u00c1tica: Consultores",
    "sg:phone":"+34 916 34 34 73",
    "sg:postcode":"28231",
    "sg:province":"Madrid",
    "sg:website":"www.nosoloweb.com",
    "wof:name":"Mac-ilriach Viera Charles Alfred",
    "wof:placetype":"venue"
},
  "geometry": {"coordinates":[-3.8856399059,40.4903488159],"type":"Point"}
}