{
  "type": "Feature",
  "properties": {
    "iso:country":"ES",
    "sg:address":"Calle de Travieso, 22",
    "sg:city":"Palmas De Gran Canaria",
    "sg:orig_category":"Doctores En Medicina",
    "sg:phone":"+34 928 37 01 82",
    "sg:postcode":"35002",
    "sg:province":"Las Palmas",
    "wof:name":"Camino Perez Eusebio",
    "wof:placetype":"venue"
},
  "geometry": {"coordinates":[-15.4175167084,28.1044330597],"type":"Point"}
}