{
  "type": "Feature",
  "properties": {
    "iso:country":"ES",
    "sg:address":"Carrer de Cervantes, 41",
    "sg:city":"Reus",
    "sg:orig_category":"Guarder\u00cdas",
    "sg:phone":"+34 977 31 46 06",
    "sg:postcode":"43201",
    "sg:province":"Tarragona",
    "wof:name":"Corbella Redon Montserrat",
    "wof:placetype":"venue"
},
  "geometry": {"coordinates":[1.105347991,41.1643676758],"type":"Point"}
}