{
  "type": "Feature",
  "properties": {
    "iso:country":"ES",
    "sg:address":"Calle de Mora\u00d1a (la), 8",
    "sg:city":"Avila",
    "sg:orig_category":"Zapater\u00cdas",
    "sg:phone":"+34 920 25 53 59",
    "sg:postcode":"05002",
    "sg:province":"\u00c1vila",
    "wof:name":"Collado Jimenez Belen",
    "wof:placetype":"venue"
},
  "geometry": {"coordinates":[-4.6998739243,40.649597168],"type":"Point"}
}