{
  "type": "Feature",
  "properties": {
    "iso:country":"ES",
    "sg:address":"Av Joan Miro, 24",
    "sg:city":"Palma",
    "sg:orig_category":"Reposter\u00cdas",
    "sg:phone":"+34 971 73 01 68",
    "sg:postcode":"07014",
    "sg:province":"Islas Baleares",
    "sg:website":"www.fondecampo.com",
    "wof:name":"Maquinas De Internet S.l.",
    "wof:placetype":"venue"
},
  "geometry": {"coordinates":[2.6263599396,39.5653953552],"type":"Point"}
}