{
  "type": "Feature",
  "properties": {
    "iso:country":"ES",
    "sg:address":"Carrer de Asturies, 50",
    "sg:city":"Barcelona",
    "sg:orig_category":"T\u00c9s (al Por Menor)",
    "sg:phone":"+34 932 10 39 22",
    "sg:postcode":"08012",
    "sg:province":"Barcelona",
    "wof:name":"El Te Dels Ciutadans S.l.l.",
    "wof:placetype":"venue"
},
  "geometry": {"coordinates":[2.1551361084,41.4037094116],"type":"Point"}
}