{
  "type": "Feature",
  "properties": {
    "iso:country":"ES",
    "sg:address":"Carrer de Muntaner, 262",
    "sg:city":"Barcelona",
    "sg:orig_category":"Administradores De Bienes Y Delegados De Comunidades De Propietarios",
    "sg:phone":"+34 932 00 03 00",
    "sg:postcode":"08021",
    "sg:province":"Barcelona",
    "sg:website":"www.esponafinques.com",
    "wof:name":"Espona Finques S.c.p.",
    "wof:placetype":"venue"
},
  "geometry": {"coordinates":[2.1479620934,41.3954849243],"type":"Point"}
}