{
  "type": "Feature",
  "properties": {
    "iso:country":"ES",
    "sg:address":"C/ Ciutat De Lliria, Km. 0011,0",
    "sg:city":"Paterna",
    "sg:orig_category":"Producci\u00d3n, Distribuci\u00d3n De Gas Butano Y Propano",
    "sg:phone":"+34 961 32 05 56",
    "sg:postcode":"46988",
    "sg:province":"Valencia",
    "wof:name":"Eurotrigo S. A.",
    "wof:placetype":"venue"
},
  "geometry": {"coordinates":[-0.4661760032,39.5240783691],"type":"Point"}
}