{
  "type": "Feature",
  "properties": {
    "iso:country":"ES",
    "sg:address":"Carr Travessera D'albaida, 18",
    "sg:city":"Real Gandia",
    "sg:orig_category":"Transportes Internacionales",
    "sg:phone":"+34 962 87 81 76",
    "sg:postcode":"46727",
    "sg:province":"Valencia",
    "wof:name":"Transjufedi S.l.",
    "wof:placetype":"venue"
},
  "geometry": {"coordinates":[-0.1910810024,38.9556350708],"type":"Point"}
}