{
  "type": "Feature",
  "properties": {
    "iso:country":"ES",
    "sg:address":"Av M. Celayeta, 3",
    "sg:city":"Iru\u00f1a",
    "sg:orig_category":"Bancos",
    "sg:phone":"+34 948 14 16 40",
    "sg:postcode":"31014",
    "sg:province":"Navarra",
    "sg:website":"www.bancopopular.es",
    "wof:name":"Banco Popular Espa\u00f1ol",
    "wof:placetype":"venue"
},
  "geometry": {"coordinates":[-1.6437540054,42.81275177],"type":"Point"}
}