{
  "type": "Feature",
  "properties": {
    "addr:full":"Carrer de Llums, 2 Palma Islas Baleares 07001",
    "addr:housenumber":"2",
    "addr:postcode":"07001",
    "addr:street":"Carrer De Llums",
    "iso:country":"ES",
    "sg:address":"Carrer de Llums, 2",
    "sg:city":"Palma",
    "sg:orig_category":"Inmobiliaria (agencias)",
    "sg:phone":"+34 971 71 12 10",
    "sg:postcode":"07001",
    "sg:province":"Islas Baleares",
    "wof:name":"Vidal Pol Francisco",
    "wof:placetype":"venue"
},
  "geometry": {"coordinates":[2.6504750252,39.5695495605],"type":"Point"}
}