{
  "type": "Feature",
  "properties": {
    "addr:full":"Calle de Casta\u00d1os, 22 Alacant Alicante 03001",
    "addr:housenumber":"22",
    "addr:postcode":"03001",
    "addr:street":"Calle De Castan\u0303Os",
    "iso:country":"ES",
    "sg:address":"Calle de Casta\u00d1os, 22",
    "sg:city":"Alacant",
    "sg:orig_category":"Molduras, Junquillos, Listones Y Molduras Perforadas",
    "sg:phone":"+34 965 21 63 20",
    "sg:postcode":"03001",
    "sg:province":"Alicante",
    "wof:name":"Espla Y Martinez S.l. Cocteleria Nic",
    "wof:placetype":"venue"
},
  "geometry": {"coordinates":[-0.4851920009,38.3452987671],"type":"Point"}
}