{
  "type": "Feature",
  "properties": {
    "addr:full":"Calle de Ayuntamiento, 2 Herreruela De Oropesa Toledo 45588",
    "addr:housenumber":"2",
    "addr:postcode":"45588",
    "addr:street":"Calle De Ayuntamiento",
    "iso:country":"ES",
    "sg:address":"Calle de Ayuntamiento, 2",
    "sg:city":"Herreruela De Oropesa",
    "sg:classifiers":[
        {
            "category":"Communications",
            "type":"Services"
        }
    ],
    "sg:phone":"+34 925 43 50 54",
    "sg:postcode":"45588",
    "sg:province":"Toledo",
    "sg:tags":[
        "televisiones",
        "y",
        "radio"
    ],
    "wof:name":"Arzobispado De Toledo",
    "wof:placetype":"venue"
},
  "geometry": {"coordinates":[-5.2433586121,39.8879203796],"type":"Point"}
}