{
  "type": "Feature",
  "properties": {
    "addr:full":"Avda Compostela, 51 Padron La Coru\u00f1a 15900",
    "addr:housenumber":"51",
    "addr:postcode":"15900",
    "addr:street":"Avda Compostela;Padron La Corun\u0303A",
    "iso:country":"ES",
    "sg:address":"Avda Compostela, 51",
    "sg:city":"Padron",
    "sg:orig_category":"Asesor\u00cda Fiscal Y Jur\u00cddica",
    "sg:phone":"+34 981 81 17 51",
    "sg:postcode":"15900",
    "sg:province":"La Coru\u00f1a",
    "wof:name":"Cabo Naya Julio",
    "wof:placetype":"venue"
},
  "geometry": {"coordinates":[-8.6600198746,42.7365951538],"type":"Point"}
}