{
  "type": "Feature",
  "properties": {
    "iso:country":"ES",
    "sg:address":"Calle de Diego Caparros, 12",
    "sg:city":"Vera",
    "sg:orig_category":"Mec\u00c1nico Del Autom\u00d3vil",
    "sg:phone":"+34 950 39 30 64",
    "sg:postcode":"04620",
    "sg:province":"Almer\u00eda",
    "wof:name":"Meca Vera S.l.",
    "wof:placetype":"venue"
},
  "geometry": {"coordinates":[-1.8709248304,37.2474365234],"type":"Point"}
}