{
  "type": "Feature",
  "properties": {
    "iso:country":"ES",
    "sg:address":"Campo Futbol, S/n",
    "sg:city":"Brihuega",
    "sg:orig_category":"Centros De Educaci\u00d3n Especial",
    "sg:phone":"+34 949 28 01 14",
    "sg:postcode":"19400",
    "sg:province":"Guadalajara",
    "wof:name":"Colegio Nacional Nuestra Se\u00f1ora De La Pe\u00f1a Educacion Primaria",
    "wof:placetype":"venue"
},
  "geometry": {"coordinates":[-2.8703289032,40.7592315674],"type":"Point"}
}