{
  "type": "Feature",
  "properties": {
    "iso:country":"ES",
    "sg:address":"Ctra Castellar, 279",
    "sg:city":"Terrassa",
    "sg:orig_category":"Hielo Artificial (fabricaci\u00d3n, Distribuci\u00d3n)",
    "sg:phone":"+34 937 85 40 25",
    "sg:postcode":"08226",
    "sg:province":"Barcelona",
    "wof:name":"Garcia Zafra Asuncion",
    "wof:placetype":"venue"
},
  "geometry": {"coordinates":[2.029761076,41.5732002258],"type":"Point"}
}