{
  "type": "Feature",
  "properties": {
    "addr:full":"Plaz Eguzki, 1 Mutiloagoiti Navarra 31192",
    "addr:housenumber":"1",
    "addr:postcode":"31192",
    "addr:street":"Eguzki",
    "iso:country":"ES",
    "sg:address":"Plaz Eguzki, 1",
    "sg:city":"Mutiloagoiti",
    "sg:orig_category":"Asesor\u00cda Sobre Comunicaci\u00d3n De Empresas",
    "sg:phone":"+34 948 15 31 67",
    "sg:postcode":"31192",
    "sg:province":"Navarra",
    "wof:name":"Asesoria De Empresas Mutiloa S.a.l.",
    "wof:placetype":"venue"
},
  "geometry": {"coordinates":[-1.6190600395,42.7999420166],"type":"Point"}
}