{
  "type": "Feature",
  "properties": {
    "addr:full":"Carrer de Clementina Arderiu, 28 S. Cugat Valles Barcelona 08173",
    "addr:housenumber":"28",
    "addr:postcode":"08173",
    "addr:street":"Carrer De Clementina Arderiu;S. Cugat Valles Barcelona",
    "iso:country":"ES",
    "sg:address":"Carrer de Clementina Arderiu, 28",
    "sg:city":"S. Cugat Valles",
    "sg:orig_category":"Promotores Constructores",
    "sg:phone":"+34 935 89 54 08",
    "sg:postcode":"08173",
    "sg:province":"Barcelona",
    "wof:name":"Comunidad De Propietarios Sant Cugat Bloque 36",
    "wof:placetype":"venue"
},
  "geometry": {"coordinates":[2.086796999,41.4818572998],"type":"Point"}
}