{
  "type": "Feature",
  "properties": {
    "addr:full":"Rua Roberto Baamonde, 62 Monforte De Lemos Lugo 27400",
    "addr:housenumber":"62",
    "addr:postcode":"27400",
    "addr:street":"Rua Roberto Baamonde",
    "iso:country":"ES",
    "sg:address":"Rua Roberto Baamonde, 62",
    "sg:city":"Monforte De Lemos",
    "sg:orig_category":"Ropa Y Accesorios",
    "sg:phone":"+34 982 41 00 61",
    "sg:postcode":"27400",
    "sg:province":"Lugo",
    "wof:name":"Gomez Diaz Victor Manuel",
    "wof:placetype":"venue"
},
  "geometry": {"coordinates":[-7.5099577904,42.5209159851],"type":"Point"}
}