{
  "type": "Feature",
  "properties": {
    "addr:full":"Calle de Nueva, 135 Alhaurin El Grande M\u00e1laga 29120",
    "addr:housenumber":"135",
    "addr:postcode":"29120",
    "addr:street":"Calle De Nueva",
    "iso:country":"ES",
    "sg:address":"Calle de Nueva, 135",
    "sg:city":"Alhaurin El Grande",
    "sg:orig_category":"Panader\u00cdas, Panader\u00cdas",
    "sg:phone":"+34 952 49 03 70",
    "sg:postcode":"29120",
    "sg:province":"M\u00e1laga",
    "wof:name":"Guzman Rueda Juan Antonio",
    "wof:placetype":"venue"
},
  "geometry": {"coordinates":[-4.6921291351,36.6425514221],"type":"Point"}
}