{
  "type": "Feature",
  "properties": {
    "iso:country":"ES",
    "sg:address":"Avda Pamplona, 18",
    "sg:city":"Alsasua",
    "sg:orig_category":"Supermercados Y Hipermercados",
    "sg:phone":"+34 948 56 42 92",
    "sg:postcode":"31800",
    "sg:province":"Navarra",
    "wof:name":"Hiper Costa S.l.",
    "wof:placetype":"venue"
},
  "geometry": {"coordinates":[-2.1655700207,42.8916015625],"type":"Point"}
}