{
  "type": "Feature",
  "properties": {
    "addr:full":"Carrer de Salenques, 1 Sabadell Barcelona 08207",
    "addr:housenumber":"1",
    "addr:postcode":"08207",
    "addr:street":"Carrer De Salenques",
    "iso:country":"ES",
    "sg:address":"Carrer de Salenques, 1",
    "sg:city":"Sabadell",
    "sg:orig_category":"Venta, Instalaci\u00d3n De Calefacci\u00d3n",
    "sg:phone":"+34 937 17 43 52",
    "sg:postcode":"08207",
    "sg:province":"Barcelona",
    "wof:name":"Olpado S.l.",
    "wof:placetype":"venue"
},
  "geometry": {"coordinates":[2.0883219242,41.5672225952],"type":"Point"}
}