{
  "type": "Feature",
  "properties": {
    "iso:country":"ES",
    "sg:address":"Alhambra, S/n",
    "sg:city":"Granada",
    "sg:orig_category":"Complementos De Vestir (al Por Menor)",
    "sg:phone":"+34 958 22 13 84",
    "sg:postcode":"18009",
    "sg:province":"Granada",
    "wof:name":"Fundacion Margenes Y Vinculos",
    "wof:placetype":"venue"
},
  "geometry": {"coordinates":[-3.5713489056,37.1635093689],"type":"Point"}
}