{
  "type": "Feature",
  "properties": {
    "addr:full":"Calle de Ca\u00d1averal, 45 Alhaurin Torre M\u00e1laga 29130",
    "addr:housenumber":"45",
    "addr:postcode":"29130",
    "addr:street":"Calle De Can\u0303Averal",
    "iso:country":"ES",
    "sg:address":"Calle de Ca\u00d1averal, 45",
    "sg:city":"Alhaurin Torre",
    "sg:orig_category":"Empresas De Desmonte",
    "sg:phone":"+34 952 41 59 43",
    "sg:postcode":"29130",
    "sg:province":"M\u00e1laga",
    "wof:name":"Excavaciones Rialsa S.l.",
    "wof:placetype":"venue"
},
  "geometry": {"coordinates":[-4.5715641975,36.6564788818],"type":"Point"}
}