{
  "type": "Feature",
  "properties": {
    "addr:full":"Avda Deportista Miriam Blasco, 14 Alacant Alicante 03016",
    "addr:housenumber":"14",
    "addr:postcode":"03016",
    "addr:street":"Avda Deportista;Blasco",
    "iso:country":"ES",
    "sg:address":"Avda Deportista Miriam Blasco, 14",
    "sg:city":"Alacant",
    "sg:orig_category":"Comadronas",
    "sg:phone":"+34 965 15 29 91",
    "sg:postcode":"03016",
    "sg:province":"Alicante",
    "wof:name":"Rubio Herrero Ana Maria",
    "wof:placetype":"venue"
},
  "geometry": {"coordinates":[-0.4350070059,38.3689193726],"type":"Point"}
}