{
  "type": "Feature",
  "properties": {
    "addr:full":"Plaz Espa\u00d1a, 7 Campillos M\u00e1laga 29320",
    "addr:housenumber":"7",
    "addr:postcode":"29320",
    "addr:street":"Plaz Espan\u0303A",
    "iso:country":"ES",
    "sg:address":"Plaz Espa\u00d1a, 7",
    "sg:city":"Campillos",
    "sg:orig_category":"Abogados",
    "sg:phone":"+34 952 72 40 95",
    "sg:postcode":"29320",
    "sg:province":"M\u00e1laga",
    "wof:name":"Morales Morales Antonio Jose",
    "wof:placetype":"venue"
},
  "geometry": {"coordinates":[-4.8618001938,37.0467987061],"type":"Point"}
}