{
  "type": "Feature",
  "properties": {
    "addr:full":"Calle de Lopez De Ayala, 4 Montijo Badajoz 06480",
    "addr:housenumber":"4",
    "addr:postcode":"06480",
    "addr:street":"Calle De Lopez De Ayala",
    "iso:country":"ES",
    "sg:address":"Calle de Lopez De Ayala, 4",
    "sg:city":"Montijo",
    "sg:orig_category":"Transporte En General",
    "sg:phone":"+34 924 45 45 50",
    "sg:postcode":"06480",
    "sg:province":"Badajoz",
    "wof:name":"Serrano Gallardo Antonio",
    "wof:placetype":"venue"
},
  "geometry": {"coordinates":[-6.6142787933,38.9098892212],"type":"Point"}
}