{
  "type": "Feature",
  "properties": {
    "addr:full":"Carr Port, 35 Escala Girona 17130",
    "addr:housenumber":"35",
    "addr:postcode":"17130",
    "addr:street":"Carr Port",
    "iso:country":"ES",
    "sg:address":"Carr Port, 35",
    "sg:city":"Escala",
    "sg:orig_category":"Lencer\u00cda Femenina, Corseter\u00cda, Trajes De Ba\u00d1o (al Por Menor)",
    "sg:phone":"+34 972 77 61 18",
    "sg:postcode":"17130",
    "sg:province":"Girona",
    "wof:name":"Molinas Escandell Mari Carmen",
    "wof:placetype":"venue"
},
  "geometry": {"coordinates":[3.1321649551,42.1229934692],"type":"Point"}
}