{
  "type": "Feature",
  "properties": {
    "addr:full":"Calle de Magnesio, 138 Valladolid Valladolid 47012",
    "addr:housenumber":"138",
    "addr:postcode":"47012",
    "addr:street":"Calle De Magnesio",
    "iso:country":"ES",
    "sg:address":"Calle de Magnesio, 138",
    "sg:city":"Valladolid",
    "sg:orig_category":"Material Y Herramientas Agr\u00cdcolas",
    "sg:phone":"+34 983 30 50 44",
    "sg:postcode":"47012",
    "sg:province":"Valladolid",
    "wof:name":"Alfersan S. A.",
    "wof:placetype":"venue"
},
  "geometry": {"coordinates":[-4.706551075,41.6261901855],"type":"Point"}
}