{
  "type": "Feature",
  "properties": {
    "addr:full":"Calle de Isabel Ii, 10 Santander Cantabria 39002",
    "addr:housenumber":"10",
    "addr:postcode":"39002",
    "addr:street":"Calle De Isabel Ii",
    "iso:country":"ES",
    "sg:address":"Calle de Isabel Ii, 10",
    "sg:city":"Santander",
    "sg:orig_category":"Institutos De Belleza",
    "sg:phone":"+34 942 22 69 24",
    "sg:postcode":"39002",
    "sg:province":"Cantabria",
    "wof:name":"Irizabal Corral Ana Maria",
    "wof:placetype":"venue"
},
  "geometry": {"coordinates":[-3.8094990253,43.4608917236],"type":"Point"}
}