{
  "type": "Feature",
  "properties": {
    "iso:country":"ES",
    "sg:address":"Avda Castillo, 34",
    "sg:city":"Lora Rio",
    "sg:orig_category":"Frutas Y Legumbres Frescas (al Por Mayor)",
    "sg:phone":"+34 955 80 26 26",
    "sg:postcode":"41440",
    "sg:province":"Sevilla",
    "wof:name":"Jerez Nieto Juan",
    "wof:placetype":"venue"
},
  "geometry": {"coordinates":[-5.533867836,37.6560096741],"type":"Point"}
}