{
  "type": "Feature",
  "properties": {
    "addr:full":"Carrer de Arago, 488 Barcelona Barcelona 08013",
    "addr:housenumber":"488",
    "addr:postcode":"08013",
    "addr:street":"Carrer De Arago",
    "iso:country":"ES",
    "sg:address":"Carrer de Arago, 488",
    "sg:city":"Barcelona",
    "sg:orig_category":"Deportes N\u00c1uticos, Acu\u00c1ticos Y Subacu\u00c1ticos: Art\u00cdculos Y Equipo (al Por Menor)",
    "sg:phone":"+34 932 32 43 62",
    "sg:postcode":"08013",
    "sg:province":"Barcelona",
    "sg:website":"www.comercialskualo.com",
    "wof:name":"Comercial Skualo S. A.",
    "wof:placetype":"venue"
},
  "geometry": {"coordinates":[2.1809570789,41.4040756226],"type":"Point"}
}