{
  "type": "Feature",
  "properties": {
    "iso:country":"ES",
    "sg:address":"Calle de Hermanas Bronte, 60",
    "sg:city":"Malaga",
    "sg:orig_category":"Hormig\u00d3n (m\u00c1quinas E Instalaci\u00d3n)",
    "sg:phone":"+34 952 23 36 43",
    "sg:postcode":"29004",
    "sg:province":"M\u00e1laga",
    "wof:name":"Malaga De Transportes S.l.",
    "wof:placetype":"venue"
},
  "geometry": {"coordinates":[-4.4695549011,36.692905426],"type":"Point"}
}