{
  "type": "Feature",
  "properties": {
    "iso:country":"ES",
    "sg:address":"Calle de Domingo De Betanzos, 5",
    "sg:city":"Salamanca",
    "sg:orig_category":"Peluquer\u00cdas",
    "sg:phone":"+34 923 18 72 60",
    "sg:postcode":"37003",
    "sg:province":"Salamanca",
    "wof:name":"Juan Llamas Yolanda",
    "wof:placetype":"venue"
},
  "geometry": {"coordinates":[-5.6482496262,40.962890625],"type":"Point"}
}