{
  "type": "Feature",
  "properties": {
    "addr:full":"Cami Creu, 10 S. Cugat Valles Barcelona 08172",
    "addr:housenumber":"10",
    "addr:postcode":"08172",
    "addr:street":"Creu;Barcelona",
    "iso:country":"ES",
    "sg:address":"Cami Creu, 10",
    "sg:city":"S. Cugat Valles",
    "sg:orig_category":"Agencias Y Agentes Comerciales, Representantes",
    "sg:phone":"+34 936 74 17 61",
    "sg:postcode":"08172",
    "sg:province":"Barcelona",
    "wof:name":"Carrasco Alvarez David",
    "wof:placetype":"venue"
},
  "geometry": {"coordinates":[2.086796999,41.4752655029],"type":"Point"}
}