{
  "type": "Feature",
  "properties": {
    "addr:full":"Carrer de Alfons Iv, 71 Granollers Barcelona 08402",
    "addr:housenumber":"71",
    "addr:postcode":"08402",
    "addr:street":"Carrer De Alfons Iv",
    "iso:country":"ES",
    "sg:address":"Carrer de Alfons Iv, 71",
    "sg:city":"Granollers",
    "sg:orig_category":"Molduras, Junquillos, Listones Y Molduras Perforadas",
    "sg:phone":"+34 938 79 53 27",
    "sg:postcode":"08402",
    "sg:province":"Barcelona",
    "wof:name":"Iglesias Garcia David",
    "wof:placetype":"venue"
},
  "geometry": {"coordinates":[2.2881989479,41.6039924622],"type":"Point"}
}