{
  "type": "Feature",
  "properties": {
    "addr:full":"Urb Castell Montornes, 8 Pobla De Montornes Tarragona 43761",
    "addr:housenumber":"8",
    "addr:postcode":"43761",
    "addr:street":"Urb;Montornes",
    "iso:country":"ES",
    "sg:address":"Urb Castell Montornes, 8",
    "sg:city":"Pobla De Montornes",
    "sg:orig_category":"Distribuci\u00d3n De Petr\u00d3leo Y Derivados",
    "sg:phone":"+34 977 64 84 86",
    "sg:postcode":"43761",
    "sg:province":"Tarragona",
    "wof:name":"Peixos Arque S.l.",
    "wof:placetype":"venue"
},
  "geometry": {"coordinates":[1.4154100418,41.1786766052],"type":"Point"}
}