{
  "type": "Feature",
  "properties": {
    "addr:full":"Calle de Nuestra Se\u00d1ora De Fatima, 20 Santo Angel Murcia 30151",
    "addr:housenumber":"20",
    "addr:postcode":"30151",
    "addr:street":"Calle De Nuestra Sen\u0303Ora De Fatima",
    "iso:country":"ES",
    "sg:address":"Calle de Nuestra Se\u00d1ora De Fatima, 20",
    "sg:city":"Santo Angel",
    "sg:orig_category":"Agentes Generales De Seguros",
    "sg:phone":"+34 968 84 46 77",
    "sg:postcode":"30151",
    "sg:province":"Murcia",
    "wof:name":"Romero Garcia Francisco",
    "wof:placetype":"venue"
},
  "geometry": {"coordinates":[-1.1270910501,37.9453315735],"type":"Point"}
}