{
  "type": "Feature",
  "properties": {
    "addr:full":"Carr Enric Granados, 12 Mollerussa Lleida 25230",
    "addr:housenumber":"12",
    "addr:postcode":"25230",
    "addr:street":"Carr Enric Granados",
    "iso:country":"ES",
    "sg:address":"Carr Enric Granados, 12",
    "sg:city":"Mollerussa",
    "sg:orig_category":"Mec\u00c1nico Del Autom\u00d3vil",
    "sg:phone":"+34 973 60 32 37",
    "sg:postcode":"25230",
    "sg:province":"Lleida",
    "wof:name":"Moreno Vela Jose Antonio",
    "wof:placetype":"venue"
},
  "geometry": {"coordinates":[0.8999279737,41.6293449402],"type":"Point"}
}