{
  "type": "Feature",
  "properties": {
    "addr:full":"Calle de Jesus Aprendiz, 9 Madrid Madrid 28007",
    "addr:housenumber":"9",
    "addr:postcode":"madrid;28007",
    "addr:street":"Calle De Jesus Aprendiz",
    "iso:country":"ES",
    "sg:address":"Calle de Jesus Aprendiz, 9",
    "sg:city":"Madrid",
    "sg:orig_category":"Inmobiliaria (agencias)",
    "sg:phone":"+34 915 73 51 94",
    "sg:postcode":"28007",
    "sg:province":"Madrid",
    "wof:name":"Asociacion Cultural Y Social Redel",
    "wof:placetype":"venue"
},
  "geometry": {"coordinates":[-3.6711645126,40.4106140137],"type":"Point"}
}