{
  "type": "Feature",
  "properties": {
    "iso:country":"ES",
    "sg:address":"Av Vallvidrera, 71",
    "sg:city":"Barcelona",
    "sg:orig_category":"Discapacitados",
    "sg:phone":"+34 932 80 60 40",
    "sg:postcode":"08017",
    "sg:province":"Barcelona",
    "wof:name":"Associacio Bit",
    "wof:placetype":"venue"
},
  "geometry": {"coordinates":[2.1116368771,41.4088058472],"type":"Point"}
}