{
  "type": "Feature",
  "properties": {
    "iso:country":"ES",
    "sg:address":"Av Roma, 126",
    "sg:city":"Barcelona",
    "sg:orig_category":"Inform\u00c1tica (estudios, Servicios, Asesor\u00cda, Formaci\u00d3n)",
    "sg:phone":"+34 934 51 60 10",
    "sg:postcode":"08015",
    "sg:province":"Barcelona",
    "sg:website":"www.microblanc.es",
    "wof:name":"Micro-blanc Informatica S.l.",
    "wof:placetype":"venue"
},
  "geometry": {"coordinates":[2.1541221142,41.3848991394],"type":"Point"}
}