{
  "type": "Feature",
  "properties": {
    "iso:country":"ES",
    "sg:address":"Calle de Gallegos, 7",
    "sg:city":"Valladolid",
    "sg:orig_category":"Deportes Diversos",
    "sg:phone":"+34 983 35 01 72",
    "sg:postcode":"47002",
    "sg:province":"Valladolid",
    "wof:name":"Federacion Castellano Leonesa De Ciclismo",
    "wof:placetype":"venue"
},
  "geometry": {"coordinates":[-4.7256770134,41.6527404785],"type":"Point"}
}