{
  "type": "Feature",
  "properties": {
    "addr:full":"Calle de Arriba (de), 1 Guia Isora Santa Cruz De Tenerife 38680",
    "addr:housenumber":"1",
    "addr:postcode":"38680",
    "addr:street":"Calle De Arriba De",
    "iso:country":"ES",
    "sg:address":"Calle de Arriba (de), 1",
    "sg:city":"Guia Isora",
    "sg:orig_category":"Librer\u00cdas",
    "sg:phone":"+34 922 85 02 27",
    "sg:postcode":"38680",
    "sg:province":"Santa Cruz De Tenerife",
    "wof:name":"Casa\u00f1as Morales Ana Antonia",
    "wof:placetype":"venue"
},
  "geometry": {"coordinates":[-16.7782821655,28.2097568512],"type":"Point"}
}