{
  "type": "Feature",
  "properties": {
    "iso:country":"ES",
    "sg:address":"Calle de Ramon Y Cajal, 1",
    "sg:city":"Palmas De Gran Canaria",
    "sg:orig_category":"Obras Y Organismos Sociales",
    "sg:phone":"+34 928 33 61 03",
    "sg:postcode":"35001",
    "sg:province":"Las Palmas",
    "wof:name":"Asoc.familias Enf.psiquicos Lavanderia Y Servicios Slu",
    "wof:placetype":"venue"
},
  "geometry": {"coordinates":[-15.4183645248,28.0991249084],"type":"Point"}
}