{
  "type": "Feature",
  "properties": {
    "addr:full":"Av Comarques Catalanes, S/n Mora D'ebre Tarragona 43740",
    "addr:housenumber":"s / n",
    "addr:postcode":"43740",
    "addr:street":"Av Comarques Catalanes;D'Ebre",
    "iso:country":"ES",
    "sg:address":"Av Comarques Catalanes, S/n",
    "sg:city":"Mora D'ebre",
    "sg:orig_category":"Ense\u00d1anza Secundaria: Colegios Y Escuelas Privadas",
    "sg:phone":"+34 977 40 01 21",
    "sg:postcode":"43740",
    "sg:province":"Tarragona",
    "wof:name":"Centre De Telecomunicaciones De Catalunya",
    "wof:placetype":"venue"
},
  "geometry": {"coordinates":[1.2540999651,41.1169281006],"type":"Point"}
}