{
  "type": "Feature",
  "properties": {
    "addr:full":"Poli Tejerias Calle de San Lazaro, 6 Calahorra La Rioja 26500",
    "addr:housenumber":"6",
    "addr:postcode":"26500",
    "addr:street":"Calle De San Lazaro",
    "iso:country":"ES",
    "sg:address":"Poli Tejerias Calle de San Lazaro, 6",
    "sg:city":"Calahorra",
    "sg:orig_category":"Electromec\u00c1nica",
    "sg:phone":"+34 941 14 84 93",
    "sg:postcode":"26500",
    "sg:province":"La Rioja",
    "wof:name":"Maquinaria De Embalaje Industrial S.l.u.",
    "wof:placetype":"venue"
},
  "geometry": {"coordinates":[-1.9620640278,42.3058395386],"type":"Point"}
}