{
  "type": "Feature",
  "properties": {
    "iso:country":"ES",
    "sg:address":"Carrer de Escipio, 34",
    "sg:city":"Barcelona",
    "sg:orig_category":"Electricidad: Equipos Industriales, Componentes (fabricaci\u00d3n)",
    "sg:phone":"+34 932 12 06 85",
    "sg:postcode":"08023",
    "sg:province":"Barcelona",
    "wof:name":"Abello Romeu Juan",
    "wof:placetype":"venue"
},
  "geometry": {"coordinates":[2.144889,41.406658],"type":"Point"}
}