{
  "type": "Feature",
  "properties": {
    "iso:country":"ES",
    "sg:address":"Calle de Geologicas, 62",
    "sg:city":"Alcorcon",
    "sg:orig_category":"Edici\u00d3n De Diarios, Revistas, Boletines",
    "sg:phone":"+34 914 86 15 27",
    "sg:postcode":"28925",
    "sg:province":"Madrid",
    "sg:website":"www.hermeseditora.com",
    "wof:name":"Hermes Editora General S.a.",
    "wof:placetype":"venue"
},
  "geometry": {"coordinates":[-3.813393116,40.3362388611],"type":"Point"}
}