{
  "type": "Feature",
  "properties": {
    "addr:full":"Carrer de Proven\u00c7a, 269 Barcelona Barcelona 08008",
    "addr:housenumber":"269",
    "addr:postcode":"08008",
    "addr:street":"Carrer De Provenc\u0327A",
    "iso:country":"ES",
    "sg:address":"Carrer de Proven\u00c7a, 269",
    "sg:city":"Barcelona",
    "sg:orig_category":"Ropa Para Se\u00d1oras (al Por Menor)",
    "sg:phone":"+34 932 15 33 11",
    "sg:postcode":"08008",
    "sg:province":"Barcelona",
    "wof:name":"Castro Parera Elvira De",
    "wof:placetype":"venue"
},
  "geometry": {"coordinates":[2.1622860432,41.3955535889],"type":"Point"}
}