{
  "type": "Feature",
  "properties": {
    "addr:full":"Avda Fama, 3 Paz Murcia 30...",
    "addr:housenumber":"3;30 ...",
    "addr:street":"Avda Fama;Murcia",
    "iso:country":"ES",
    "sg:address":"Avda Fama, 3",
    "sg:city":"Paz",
    "sg:orig_category":"Administraciones Regionales, Departamentales Y Locales",
    "sg:phone":"+34 968 36 28 00",
    "sg:postcode":"30...",
    "sg:province":"Murcia",
    "sg:website":"www.ifrm-murcia.es",
    "wof:name":"Comunidad Autonoma De La Region De Murcia",
    "wof:placetype":"venue"
},
  "geometry": {"coordinates":[-1.1302499771,37.9829597473],"type":"Point"}
}