{
  "type": "Feature",
  "properties": {
    "iso:country":"ES",
    "sg:address":"Calle de General Franco, 18",
    "sg:city":"Montefrio",
    "sg:orig_category":"Carnicer\u00cdas, Carnicer\u00cdas",
    "sg:phone":"+34 958 33 62 69",
    "sg:postcode":"18270",
    "sg:province":"Granada",
    "wof:name":"Arroyo Baena Custodio",
    "wof:placetype":"venue"
},
  "geometry": {"coordinates":[-4.00974226,37.3176269531],"type":"Point"}
}