{
  "type": "Feature",
  "properties": {
    "addr:full":"Via Augusta, 59 Barcelona Barcelona 08006",
    "addr:housenumber":"59",
    "addr:postcode":"08006",
    "addr:street":"Via Augusta",
    "iso:country":"ES",
    "sg:address":"Via Augusta, 59",
    "sg:city":"Barcelona",
    "sg:orig_category":"Productos Fitosanitarios (negocio, Aplicaci\u00d3n)",
    "sg:phone":"+34 932 17 37 98",
    "sg:postcode":"08006",
    "sg:province":"Barcelona",
    "wof:name":"Health Solutions S.l.",
    "wof:placetype":"venue"
},
  "geometry": {"coordinates":[2.1519052982,41.3997421265],"type":"Point"}
}