{
  "type": "Feature",
  "properties": {
    "iso:country":"ES",
    "sg:address":"Calle de Bohemios, 1",
    "sg:city":"Madrid",
    "sg:orig_category":"Caf\u00c9s, Bares, Cervecer\u00cdas",
    "sg:phone":"+34 917 95 22 12",
    "sg:postcode":"28041",
    "sg:province":"Madrid",
    "wof:name":"Rodriguez Garrido Saturnino",
    "wof:placetype":"venue"
},
  "geometry": {"coordinates":[-3.6939520836,40.3564491272],"type":"Point"}
}