{
  "type": "Feature",
  "properties": {
    "addr:full":"Calle de Diputacion Provincial, 17 Daroca Zaragoza 50360",
    "addr:housenumber":"17",
    "addr:postcode":"50360",
    "addr:street":"Calle De Diputacion Provincial",
    "iso:country":"ES",
    "sg:address":"Calle de Diputacion Provincial, 17",
    "sg:city":"Daroca",
    "sg:orig_category":"Empresas De Desmonte",
    "sg:phone":"+34 976 80 02 75",
    "sg:postcode":"50360",
    "sg:province":"Zaragoza",
    "wof:name":"Excavaciones Mateo Marin S.c",
    "wof:placetype":"venue"
},
  "geometry": {"coordinates":[-1.4094284773,41.1152839661],"type":"Point"}
}