{
  "type": "Feature",
  "properties": {
    "addr:full":"Carrer de Roger De Lluria, 110 Barcelona Barcelona 08037",
    "addr:housenumber":"110",
    "addr:postcode":"08037",
    "addr:street":"Carrer De Roger De Lluria",
    "iso:country":"ES",
    "sg:address":"Carrer de Roger De Lluria, 110",
    "sg:city":"Barcelona",
    "sg:orig_category":"Centros De Coordinaci\u00d3n",
    "sg:phone":"+34 934 57 94 05",
    "sg:postcode":"08037",
    "sg:province":"Barcelona",
    "wof:name":"Crusi More Salvador",
    "wof:placetype":"venue"
},
  "geometry": {"coordinates":[2.1647291183,41.3964347839],"type":"Point"}
}