{
  "type": "Feature",
  "properties": {
    "addr:full":"Calle de Centelles, Los, 37 Valencia Valencia 46006",
    "addr:housenumber":"37",
    "addr:postcode":"46006",
    "addr:street":"Calle De Centelles Los",
    "iso:country":"ES",
    "sg:address":"Calle de Centelles, Los, 37",
    "sg:city":"Valencia",
    "sg:orig_category":"Muebles Y Accesorios Para Cocinas Y Cuartos De Ba\u00d1o (al Por Menor)",
    "sg:phone":"+34 963 73 70 11",
    "sg:postcode":"46006",
    "sg:province":"Valencia",
    "wof:name":"Estudio Guirefor S.l.",
    "wof:placetype":"venue"
},
  "geometry": {"coordinates":[-0.3733893931,39.4590988159],"type":"Point"}
}