{
  "type": "Feature",
  "properties": {
    "addr:full":"Calle de Real, 54 Pozuelo De Zarzon C\u00e1ceres 10813",
    "addr:housenumber":"54",
    "addr:postcode":"10813",
    "addr:street":"Calle De Real;Ca\u0301Ceres",
    "iso:country":"ES",
    "sg:address":"Calle de Real, 54",
    "sg:city":"Pozuelo De Zarzon",
    "sg:orig_category":"Electrodom\u00c9sticos (al Por Menor)",
    "sg:phone":"+34 927 44 80 17",
    "sg:postcode":"10813",
    "sg:province":"C\u00e1ceres",
    "wof:name":"Sancho Sanchez Heliodoro De",
    "wof:placetype":"venue"
},
  "geometry": {"coordinates":[-6.4166340828,40.1477355957],"type":"Point"}
}