{
  "type": "Feature",
  "properties": {
    "addr:full":"Avda Praia America, 2 Playa America Pontevedra 36379",
    "addr:housenumber":"2",
    "addr:postcode":"36379",
    "addr:street":"Avda Praia America",
    "iso:country":"ES",
    "sg:address":"Avda Praia America, 2",
    "sg:city":"Playa America",
    "sg:orig_category":"Institutos De Belleza",
    "sg:phone":"+34 986 38 60 18",
    "sg:postcode":"36379",
    "sg:province":"Pontevedra",
    "wof:name":"Centro Medico Estetico Kalos Go S.l.",
    "wof:placetype":"venue"
},
  "geometry": {"coordinates":[-8.8201990128,42.1243286133],"type":"Point"}
}