{
  "type": "Feature",
  "properties": {
    "iso:country":"ES",
    "sg:address":"Avda Praia America, 2",
    "sg:city":"Playa America",
    "sg:orig_category":"Institutos De Belleza",
    "sg:phone":"+34 986 38 60 18",
    "sg:postcode":"36379",
    "sg:province":"Pontevedra",
    "wof:name":"Centro Medico Estetico Kalos Go S.l.",
    "wof:placetype":"venue"
},
  "geometry": {"coordinates":[-8.8201990128,42.1243286133],"type":"Point"}
}