{
  "type": "Feature",
  "properties": {
    "addr:full":"Calle de Pico Balaitus, 26 Madrid Madrid 28035",
    "addr:housenumber":"26",
    "addr:postcode":"madrid;28035",
    "addr:street":"Calle De Pico Balaitus",
    "iso:country":"ES",
    "sg:address":"Calle de Pico Balaitus, 26",
    "sg:city":"Madrid",
    "sg:orig_category":"Mudanzas",
    "sg:phone":"+34 913 78 43 32",
    "sg:postcode":"28035",
    "sg:province":"Madrid",
    "sg:website":"www.galytrans.com",
    "wof:name":"Galytrans Aga S.l.",
    "wof:placetype":"venue"
},
  "geometry": {"coordinates":[-3.7206790447,40.4835891724],"type":"Point"}
}