{
  "type": "Feature",
  "properties": {
    "iso:country":"ES",
    "sg:address":"Avda Mariano Vicen, 29",
    "sg:city":"Soria",
    "sg:orig_category":"Carnicer\u00cdas, Carnicer\u00cdas",
    "sg:phone":"+34 975 23 29 21",
    "sg:postcode":"42003",
    "sg:province":"Soria",
    "wof:name":"Productos Carnicos Llorente S.a.",
    "wof:placetype":"venue"
},
  "geometry": {"coordinates":[-2.4696660042,41.7593994141],"type":"Point"}
}