{
  "type": "Feature",
  "properties": {
    "iso:country":"ES",
    "sg:address":"Avda Felipe V, 19",
    "sg:city":"Petrer",
    "sg:orig_category":"Carnicer\u00cdas, Carnicer\u00cdas",
    "sg:phone":"+34 966 95 11 89",
    "sg:postcode":"03610",
    "sg:province":"Alicante",
    "sg:website":"www.carniceriamarcos.com",
    "wof:name":"Martinez Ramos Pedro Luis",
    "wof:placetype":"venue"
},
  "geometry": {"coordinates":[-0.7778519988,38.4817581177],"type":"Point"}
}