{
  "type": "Feature",
  "properties": {
    "addr:full":"Plaz Constitucion (de La), 6 Rambla C\u00f3rdoba 14540",
    "addr:postcode":"14540",
    "addr:street":"Rambla Co\u0301Rdoba",
    "iso:country":"ES",
    "sg:address":"Plaz Constitucion (de La), 6",
    "sg:city":"Rambla",
    "sg:orig_category":"Supermercados Y Hipermercados",
    "sg:phone":"+34 957 68 28 94",
    "sg:postcode":"14540",
    "sg:province":"C\u00f3rdoba",
    "wof:name":"Nadales Luque S.l.",
    "wof:placetype":"venue"
},
  "geometry": {"coordinates":[-4.7416338921,37.6080932617],"type":"Point"}
}