{
  "type": "Feature",
  "properties": {
    "addr:full":"Calle de San Valero, 4 Zaragoza Zaragoza 50001",
    "addr:housenumber":"4",
    "addr:postcode":"50001",
    "addr:street":"Calle De San Valero",
    "iso:country":"ES",
    "sg:address":"Calle de San Valero, 4",
    "sg:city":"Zaragoza",
    "sg:orig_category":"Promotores Constructores",
    "sg:phone":"+34 976 20 00 67",
    "sg:postcode":"50001",
    "sg:province":"Zaragoza",
    "wof:name":"Hermanos Molinero Andreu S.a.",
    "wof:placetype":"venue"
},
  "geometry": {"coordinates":[-0.8764539957,41.6548118591],"type":"Point"}
}