{
  "type": "Feature",
  "properties": {
    "addr:full":"Ctra Rocafort, 26 Godella Valencia 46110",
    "addr:housenumber":"26",
    "addr:postcode":"46110",
    "addr:street":"Ctra Rocafort",
    "iso:country":"ES",
    "sg:address":"Ctra Rocafort, 26",
    "sg:city":"Godella",
    "sg:orig_category":"Ingeniero",
    "sg:phone":"+34 963 64 35 79",
    "sg:postcode":"46110",
    "sg:province":"Valencia",
    "wof:name":"Consulting De Ingenieria Y Formacion Valenciana S.l.",
    "wof:placetype":"venue"
},
  "geometry": {"coordinates":[-0.4148899913,39.5239028931],"type":"Point"}
}