{
  "type": "Feature",
  "properties": {
    "iso:country":"ES",
    "sg:address":"Calle de Reino, 1",
    "sg:city":"Valladolises",
    "sg:orig_category":"Asociaciones, Organismos Culturales Y Socioeducativos",
    "sg:phone":"+34 968 38 42 39",
    "sg:postcode":"30154",
    "sg:province":"Murcia",
    "wof:name":"Ayuntamiento De Murcia",
    "wof:placetype":"venue"
},
  "geometry": {"coordinates":[-1.1232949495,37.7769775391],"type":"Point"}
}