{
  "type": "Feature",
  "properties": {
    "iso:country":"ES",
    "sg:address":"Calle de Consolacion, 3",
    "sg:city":"Gijon",
    "sg:orig_category":"Inform\u00c1tica (estudios, Servicios, Asesor\u00cda, Formaci\u00d3n)",
    "sg:phone":"+34 985 15 03 08",
    "sg:postcode":"33210",
    "sg:province":"Asturias",
    "wof:name":"Carvajal De Las Heras Jose Francisco",
    "wof:placetype":"venue"
},
  "geometry": {"coordinates":[-5.6670722961,43.5243301392],"type":"Point"}
}