{
  "type": "Feature",
  "properties": {
    "iso:country":"ES",
    "sg:address":"La Rehoya, S/n",
    "sg:city":"Berlanga",
    "sg:orig_category":"Aceites Y Grasas Alimentarias (fabricaci\u00d3n, Al Por Mayor)",
    "sg:phone":"+34 924 14 40 16",
    "sg:postcode":"06930",
    "sg:province":"Badajoz",
    "wof:name":"Oleicola Berlangue\u00f1a S.l.",
    "wof:placetype":"venue"
},
  "geometry": {"coordinates":[-5.8296160698,38.2766189575],"type":"Point"}
}