{
  "type": "Feature",
  "properties": {
    "addr:full":"Calle de Juan Xxiii, 63 Albatera Alicante 03340",
    "addr:housenumber":"63",
    "addr:postcode":"03340",
    "addr:street":"Calle De Juan Xxiii",
    "iso:country":"ES",
    "sg:address":"Calle de Juan Xxiii, 63",
    "sg:city":"Albatera",
    "sg:orig_category":"Venta Al Preg\u00d3n",
    "sg:phone":"+34 965 48 55 53",
    "sg:postcode":"03340",
    "sg:province":"Alicante",
    "wof:name":"Gadea Adsuar Tomas",
    "wof:placetype":"venue"
},
  "geometry": {"coordinates":[-0.8653110266,38.1812934875],"type":"Point"}
}