{
  "type": "Feature",
  "properties": {
    "addr:full":"Calle de Narvaez, 43 Madrid Madrid 28009",
    "addr:housenumber":"43",
    "addr:postcode":"madrid;28009",
    "addr:street":"Calle De Narvaez",
    "iso:country":"ES",
    "sg:address":"Calle de Narvaez, 43",
    "sg:city":"Madrid",
    "sg:orig_category":"Inform\u00c1tica, Ofim\u00c1tica (estudios, Asesor\u00cda, Ingenier\u00cda, Formaci\u00d3n)",
    "sg:phone":"+34 915 74 44 51",
    "sg:postcode":"28009",
    "sg:province":"Madrid",
    "wof:name":"Serconi S.l.",
    "wof:placetype":"venue"
},
  "geometry": {"coordinates":[-3.6759669781,40.4196052551],"type":"Point"}
}