{
  "type": "Feature",
  "properties": {
    "addr:full":"Calle de Virgen De Covadonga, 5 Cuatro Vientos Valencia 46185",
    "addr:housenumber":"5",
    "addr:postcode":"46185",
    "addr:street":"Calle De Virgen De Covadonga;Vientos",
    "iso:country":"ES",
    "sg:address":"Calle de Virgen De Covadonga, 5",
    "sg:city":"Cuatro Vientos",
    "sg:orig_category":"Empresarios Y Productoras De Espect\u00c1culos",
    "sg:phone":"+34 961 65 65 16",
    "sg:postcode":"46185",
    "sg:province":"Valencia",
    "sg:website":"www.rochicostaeste.com",
    "wof:name":"Costa Este Management S.l.",
    "wof:placetype":"venue"
},
  "geometry": {"coordinates":[-0.5534440279,39.5925750732],"type":"Point"}
}