{
  "type": "Feature",
  "properties": {
    "iso:country":"ES",
    "sg:address":"Calle de Prim, 38",
    "sg:city":"Carmona",
    "sg:orig_category":"Art\u00cdculos De Regalo (al Por Menor)",
    "sg:phone":"+34 954 14 13 63",
    "sg:postcode":"41410",
    "sg:province":"Sevilla",
    "wof:name":"Inlacode S.l.",
    "wof:placetype":"venue"
},
  "geometry": {"coordinates":[-5.640414238,37.4713401794],"type":"Point"}
}