{
  "type": "Feature",
  "properties": {
    "addr:full":"Carrer de Gracia, 62 Sabadell Barcelona 08201",
    "addr:housenumber":"62",
    "addr:postcode":"08201",
    "addr:street":"Carrer De Gracia",
    "iso:country":"ES",
    "sg:address":"Carrer de Gracia, 62",
    "sg:city":"Sabadell",
    "sg:orig_category":"Tapiceros Y Tapiceros",
    "sg:phone":"+34 937 15 55 22",
    "sg:postcode":"08201",
    "sg:province":"Barcelona",
    "wof:name":"Arquitecturas De Interior Gracia 62 S.l.",
    "wof:placetype":"venue"
},
  "geometry": {"coordinates":[2.1063342094,41.5486526489],"type":"Point"}
}