{
  "type": "Feature",
  "properties": {
    "addr:full":"Avda Salsidu, 5 Algorta Vizcaya 48991",
    "addr:housenumber":"5",
    "addr:postcode":"48991",
    "addr:street":"Avda Salsidu",
    "iso:country":"ES",
    "sg:address":"Avda Salsidu, 5",
    "sg:city":"Algorta",
    "sg:orig_category":"Organismos Y Centros De Vacaciones Y Esparcimiento Para Ni\u00d1os Y Adolescentes",
    "sg:phone":"+34 944 30 46 74",
    "sg:postcode":"48991",
    "sg:province":"Vizcaya",
    "wof:name":"Circulo Mayor C.b",
    "wof:placetype":"venue"
},
  "geometry": {"coordinates":[-3.00918293,43.3521118164],"type":"Point"}
}