{
  "type": "Feature",
  "properties": {
    "addr:full":"Calle de Puebla, 3 Burgos Burgos 09004",
    "addr:housenumber":"3",
    "addr:postcode":"09004",
    "addr:street":"Calle De Puebla",
    "iso:country":"ES",
    "sg:address":"Calle de Puebla, 3",
    "sg:city":"Burgos",
    "sg:orig_category":"Restaurantes",
    "sg:phone":"+34 947 27 82 02",
    "sg:postcode":"09004",
    "sg:province":"Burgos",
    "wof:name":"Martinez Gonzalez Jose Ramon",
    "wof:placetype":"venue"
},
  "geometry": {"coordinates":[-3.6988120079,42.3419075012],"type":"Point"}
}