{
  "type": "Feature",
  "properties": {
    "addr:full":"Av Catalunya, 18 S. Cugat Valles Barcelona 08172",
    "addr:housenumber":"18",
    "addr:postcode":"08172",
    "addr:street":"Av Catalunya;S. Cugat Valles Barcelona",
    "iso:country":"ES",
    "sg:address":"Av Catalunya, 18",
    "sg:city":"S. Cugat Valles",
    "sg:orig_category":"Prendas Y Chalecos De Punto (al Por Menor)",
    "sg:phone":"+34 935 83 60 17",
    "sg:postcode":"08172",
    "sg:province":"Barcelona",
    "wof:name":"Borras Riera Montse",
    "wof:placetype":"venue"
},
  "geometry": {"coordinates":[2.0804460049,41.4728012085],"type":"Point"}
}