{
  "type": "Feature",
  "properties": {
    "addr:full":"Calle de San Carlos, 30 Hellin Albacete 02400",
    "addr:housenumber":"30",
    "addr:postcode":"02400",
    "addr:street":"Calle De San Carlos",
    "iso:country":"ES",
    "sg:address":"Calle de San Carlos, 30",
    "sg:city":"Hellin",
    "sg:orig_category":"Promotores Constructores",
    "sg:phone":"+34 967 30 44 33",
    "sg:postcode":"02400",
    "sg:province":"Albacete",
    "wof:name":"Construcciones Alsama S.c.l.",
    "wof:placetype":"venue"
},
  "geometry": {"coordinates":[-1.6979589462,38.50548172],"type":"Point"}
}