{
  "type": "Feature",
  "properties": {
    "addr:full":"Concejo De Elcano, 6 Iru\u00f1a Navarra 31016",
    "addr:housenumber":"6",
    "addr:postcode":"31016",
    "addr:street":"Irun\u0303A Navarra",
    "iso:country":"ES",
    "sg:address":"Concejo De Elcano, 6",
    "sg:city":"Iru\u00f1a",
    "sg:orig_category":"Agencias Y Agentes Comerciales, Representantes",
    "sg:phone":"+34 948 16 16 79",
    "sg:postcode":"31016",
    "sg:province":"Navarra",
    "wof:name":"Huarte Gorriz Francisco Javier",
    "wof:placetype":"venue"
},
  "geometry": {"coordinates":[-1.6134190559,42.8087806702],"type":"Point"}
}