{
  "type": "Feature",
  "properties": {
    "addr:full":"Rava Santa Anna, 17 Reus Tarragona 43201",
    "addr:housenumber":"17",
    "addr:postcode":"43201",
    "addr:street":"Anna",
    "iso:country":"ES",
    "sg:address":"Rava Santa Anna, 17",
    "sg:city":"Reus",
    "sg:orig_category":"Talleres: Ropa A Medida",
    "sg:phone":"+34 977 34 37 88",
    "sg:postcode":"43201",
    "sg:province":"Tarragona",
    "wof:name":"Salomon Brull Juan Marcos",
    "wof:placetype":"venue"
},
  "geometry": {"coordinates":[1.1090910435,41.1563873291],"type":"Point"}
}