{
  "type": "Feature",
  "properties": {
    "iso:country":"ES",
    "sg:address":"Mayor, 77",
    "sg:city":"Estella",
    "sg:orig_category":"Tintes (fabricaci\u00d3n, Al Por Mayor)",
    "sg:phone":"+34 948 55 13 76",
    "sg:postcode":"31200",
    "sg:province":"Navarra",
    "wof:name":"Sanz Lopez De Guere\u00f1u Guillermo",
    "wof:placetype":"venue"
},
  "geometry": {"coordinates":[-2.0304489136,42.6710205078],"type":"Point"}
}