{
  "type": "Feature",
  "properties": {
    "iso:country":"ES",
    "sg:address":"Avda Roll Major, S/n",
    "sg:city":"Rafelbunyol",
    "sg:orig_category":"Ferreter\u00cda (diversos)",
    "sg:phone":"+34 961 41 32 97",
    "sg:postcode":"46138",
    "sg:province":"Valencia",
    "wof:name":"Herrajes Y Complementos Para Muebles Rafel S.l",
    "wof:placetype":"venue"
},
  "geometry": {"coordinates":[-0.3277274966,39.5817909241],"type":"Point"}
}