{
  "type": "Feature",
  "properties": {
    "iso:country":"ES",
    "sg:address":"Avda Federico Silva, 205",
    "sg:city":"Benavente",
    "sg:orig_category":"Mec\u00c1nico Del Autom\u00d3vil",
    "sg:phone":"+34 980 63 72 40",
    "sg:postcode":"49600",
    "sg:province":"Zamora",
    "wof:name":"Pe\u00f1a De Dios Juan Carlos",
    "wof:placetype":"venue"
},
  "geometry": {"coordinates":[-5.660929203,41.998008728],"type":"Point"}
}