{
  "type": "Feature",
  "properties": {
    "addr:full":"Calle de Bernardo De La Torre, 108 Palmas De Gran Canaria Las Palmas 35007",
    "addr:housenumber":"108",
    "addr:postcode":"35007",
    "addr:street":"Calle De Bernardo De La Torre",
    "iso:country":"ES",
    "sg:address":"Calle de Bernardo De La Torre, 108",
    "sg:city":"Palmas De Gran Canaria",
    "sg:orig_category":"Venta, Instalaci\u00d3n, Reparaci\u00d3n De Antenas Para Televisi\u00d3n",
    "sg:phone":"+34 928 22 86 55",
    "sg:postcode":"35007",
    "sg:province":"Las Palmas",
    "wof:name":"Suero Rojo Luis Carlos",
    "wof:placetype":"venue"
},
  "geometry": {"coordinates":[-15.4347000122,28.1409187317],"type":"Point"}
}