{
  "type": "Feature",
  "properties": {
    "addr:full":"Calle de Jose Manuel Bobes, 8 Lugo De Llanera Asturias 33690",
    "addr:housenumber":"8",
    "addr:postcode":"33690",
    "addr:street":"Calle De Jose Manuel Bobes",
    "iso:country":"ES",
    "sg:address":"Calle de Jose Manuel Bobes, 8",
    "sg:city":"Lugo De Llanera",
    "sg:orig_category":"Tapicer\u00cdas",
    "sg:phone":"+34 985 77 20 44",
    "sg:postcode":"33690",
    "sg:province":"Asturias",
    "wof:name":"Roberto Alvarez Tamargo Y Luis Urdangaray Gonzalez Cdad.",
    "wof:placetype":"venue"
},
  "geometry": {"coordinates":[-5.8169288635,43.4419212341],"type":"Point"}
}