{
  "type": "Feature",
  "properties": {
    "addr:full":"Calle de General Sueiro, 37 Zaragoza Zaragoza 50008",
    "addr:housenumber":"37",
    "addr:postcode":"50008",
    "addr:street":"Calle De General Sueiro",
    "iso:country":"ES",
    "sg:address":"Calle de General Sueiro, 37",
    "sg:city":"Zaragoza",
    "sg:orig_category":"Contables",
    "sg:phone":"+34 976 21 79 02",
    "sg:postcode":"50008",
    "sg:province":"Zaragoza",
    "wof:name":"Gravalos Marin Ramon",
    "wof:placetype":"venue"
},
  "geometry": {"coordinates":[-0.8814030886,41.6443557739],"type":"Point"}
}