{
  "type": "Feature",
  "properties": {
    "addr:full":"Avda General Portome\u00d1e, S/n Antas Ulla Lugo 27570",
    "addr:housenumber":"s / n",
    "addr:postcode":"27570",
    "addr:street":"Avda General Portomen\u0303E",
    "iso:country":"ES",
    "sg:address":"Avda General Portome\u00d1e, S/n",
    "sg:city":"Antas Ulla",
    "sg:orig_category":"Servicios Y Funcionarios De Polic\u00cda",
    "sg:phone":"+34 982 37 90 82",
    "sg:postcode":"27570",
    "sg:province":"Lugo",
    "wof:name":"Direccion General De La Guardia Civil",
    "wof:placetype":"venue"
},
  "geometry": {"coordinates":[-7.8907341957,42.7823143005],"type":"Point"}
}