{
  "type": "Feature",
  "properties": {
    "iso:country":"ES",
    "sg:address":"Calle de Comunidad Valenciana, 21",
    "sg:city":"Catral",
    "sg:orig_category":"Bebidas",
    "sg:phone":"+34 965 72 34 80",
    "sg:postcode":"03158",
    "sg:province":"Alicante",
    "wof:name":"Distribuciones De Bebidas Catral S.l.",
    "wof:placetype":"venue"
},
  "geometry": {"coordinates":[-0.8004673123,38.164100647],"type":"Point"}
}