{
  "type": "Feature",
  "properties": {
    "iso:country":"ES",
    "sg:address":"Av Diagonal, 507",
    "sg:city":"Barcelona",
    "sg:orig_category":"Productos Qu\u00cdmicos (fabricaci\u00d3n, Al Por Mayor)",
    "sg:phone":"+34 934 30 40 94",
    "sg:postcode":"08029",
    "sg:province":"Barcelona",
    "wof:name":"Solvay Pharma S.a.",
    "wof:placetype":"venue"
},
  "geometry": {"coordinates":[2.1416079998,41.3915481567],"type":"Point"}
}