{
  "type": "Feature",
  "properties": {
    "addr:full":"Calle de Osa Mayor, 17 Valladolid Valladolid 47009",
    "addr:housenumber":"17",
    "addr:postcode":"47009",
    "addr:street":"Calle De Osa Mayor",
    "iso:country":"ES",
    "sg:address":"Calle de Osa Mayor, 17",
    "sg:city":"Valladolid",
    "sg:orig_category":"Ebanister\u00cda",
    "sg:phone":"+34 983 37 29 75",
    "sg:postcode":"47009",
    "sg:province":"Valladolid",
    "wof:name":"Madrigal Martin Jose Luis",
    "wof:placetype":"venue"
},
  "geometry": {"coordinates":[-4.7371292114,41.6667900085],"type":"Point"}
}