{
  "type": "Feature",
  "properties": {
    "addr:full":"Ctra. S. Miquel Corb, 11 Preses Girona 17178",
    "addr:housenumber":"11",
    "addr:postcode":"17178",
    "addr:street":"Ctra. S. Miquel Corb",
    "iso:country":"ES",
    "sg:address":"Ctra. S. Miquel Corb, 11",
    "sg:city":"Preses",
    "sg:orig_category":"Cajas Y Embalajes Met\u00c1licos",
    "sg:phone":"+34 972 69 37 84",
    "sg:postcode":"17178",
    "sg:province":"Girona",
    "wof:name":"Envasos Meta%ics Soypa S.l.",
    "wof:placetype":"venue"
},
  "geometry": {"coordinates":[2.4583799839,42.1440010071],"type":"Point"}
}