{
  "type": "Feature",
  "properties": {
    "addr:full":"Rua Ribadavia (de), 19 Carballi\u00f1o Ourense 32500",
    "addr:housenumber":"19",
    "addr:postcode":"32500",
    "addr:street":"Rua Ribadavia De",
    "iso:country":"ES",
    "sg:address":"Rua Ribadavia (de), 19",
    "sg:city":"Carballi\u00f1o",
    "sg:orig_category":"Mec\u00c1nico Del Autom\u00d3vil",
    "sg:phone":"+34 988 27 22 30",
    "sg:postcode":"32500",
    "sg:province":"Ourense",
    "wof:name":"Talleres Baranda S.l.",
    "wof:placetype":"venue"
},
  "geometry": {"coordinates":[-8.0796108246,42.4280891418],"type":"Point"}
}