{
  "type": "Feature",
  "properties": {
    "iso:country":"ES",
    "sg:address":"Carrer de Gracia, 38",
    "sg:city":"Sabadell",
    "sg:orig_category":"Abogados",
    "sg:phone":"+34 937 27 35 04",
    "sg:postcode":"08201",
    "sg:province":"Barcelona",
    "wof:name":"Reyes Delgado Jorge",
    "wof:placetype":"venue"
},
  "geometry": {"coordinates":[2.1069829464,41.548034668],"type":"Point"}
}