{
  "type": "Feature",
  "properties": {
    "iso:country":"ES",
    "sg:address":"Julio Ruiz De Salazar, 50",
    "sg:city":"Torrelavega",
    "sg:orig_category":"Empresas De Limpieza",
    "sg:phone":"+34 942 89 38 57",
    "sg:postcode":"39300",
    "sg:province":"Cantabria",
    "wof:name":"Esteban Arenal Carlos",
    "wof:placetype":"venue"
},
  "geometry": {"coordinates":[-4.0624089241,43.3447761536],"type":"Point"}
}