{
  "type": "Feature",
  "properties": {
    "iso:country":"ES",
    "sg:address":"Avda Cid, 130",
    "sg:city":"Valencia",
    "sg:orig_category":"Reparaciones Y Remolcado De Veh\u00cdculos",
    "sg:phone":"+34 963 70 09 94",
    "sg:postcode":"46014",
    "sg:province":"Valencia",
    "wof:name":"Pascual Alabau Luis",
    "wof:placetype":"venue"
},
  "geometry": {"coordinates":[-0.4071500003,39.4704475403],"type":"Point"}
}