{
  "type": "Feature",
  "properties": {
    "iso:country":"ES",
    "sg:address":"Calle de Clemente Beltran Heredia, 10",
    "sg:city":"Arizgoiti",
    "sg:orig_category":"Agencias De Viajes",
    "sg:phone":"+34 944 26 23 40",
    "sg:postcode":"48970",
    "sg:province":"Vizcaya",
    "sg:website":"www.viajeselcorteingles.es",
    "wof:name":"Viajes El Corte Ingles S A",
    "wof:placetype":"venue"
},
  "geometry": {"coordinates":[-2.8876299858,43.2359046936],"type":"Point"}
}