{
  "type": "Feature",
  "properties": {
    "iso:country":"ES",
    "sg:address":"Calle de Vicente Camaron, 43",
    "sg:city":"Madrid",
    "sg:orig_category":"Muebles Y Accesorios Para Cocinas Y Cuartos De Ba\u00d1o (al Por Menor)",
    "sg:phone":"+34 914 64 77 04",
    "sg:postcode":"28011",
    "sg:province":"Madrid",
    "wof:name":"Prieto Benito Raul",
    "wof:placetype":"venue"
},
  "geometry": {"coordinates":[-3.7404820919,40.406036377],"type":"Point"}
}