{
  "type": "Feature",
  "properties": {
    "addr:full":"Plaz Virgen (de La), 16 Guadix Granada 18500",
    "addr:housenumber":"16",
    "addr:postcode":"18500",
    "addr:street":"Plaz Virgen De La",
    "iso:country":"ES",
    "sg:address":"Plaz Virgen (de La), 16",
    "sg:city":"Guadix",
    "sg:orig_category":"Empresas De Carpinter\u00cda De Madera",
    "sg:phone":"+34 958 66 08 48",
    "sg:postcode":"18500",
    "sg:province":"Granada",
    "wof:name":"Perez Marruecos Antonio Manuel",
    "wof:placetype":"venue"
},
  "geometry": {"coordinates":[-3.1343479156,37.2965888977],"type":"Point"}
}