{
  "type": "Feature",
  "properties": {
    "addr:full":"Carrer de Nord, 1 Esplugues Llobregat Barcelona 08950",
    "addr:housenumber":"1",
    "addr:postcode":"08950",
    "addr:street":"Carrer De Nord",
    "iso:country":"ES",
    "sg:address":"Carrer de Nord, 1",
    "sg:city":"Esplugues Llobregat",
    "sg:orig_category":"Cajas De Ahorro",
    "sg:phone":"+34 933 72 88 00",
    "sg:postcode":"08950",
    "sg:province":"Barcelona",
    "wof:name":"Caixa D'estalvis Del Penedes",
    "wof:placetype":"venue"
},
  "geometry": {"coordinates":[2.0817210674,41.3809967041],"type":"Point"}
}