{
  "type": "Feature",
  "properties": {
    "addr:full":"Calle de Anselmo Clave, 37 Zaragoza Zaragoza 50004",
    "addr:housenumber":"37",
    "addr:postcode":"50004",
    "addr:street":"Calle De Anselmo Clave",
    "iso:country":"ES",
    "sg:address":"Calle de Anselmo Clave, 37",
    "sg:city":"Zaragoza",
    "sg:orig_category":"M\u00c9dicos: Estomatolog\u00cda",
    "sg:phone":"+34 976 28 39 84",
    "sg:postcode":"50004",
    "sg:province":"Zaragoza",
    "wof:name":"Zapatero Remon Luis Fernando",
    "wof:placetype":"venue"
},
  "geometry": {"coordinates":[-0.8937336802,41.6499176025],"type":"Point"}
}