{
  "type": "Feature",
  "properties": {
    "addr:full":"Calle de Miguel Morlan, 23 Villanueva Alcardete Toledo 45810",
    "addr:housenumber":"23",
    "addr:postcode":"45810",
    "addr:street":"Calle De Miguel Morlan",
    "iso:country":"ES",
    "sg:address":"Calle de Miguel Morlan, 23",
    "sg:city":"Villanueva Alcardete",
    "sg:orig_category":"Cajas De Ahorro",
    "sg:phone":"+34 925 16 61 25",
    "sg:postcode":"45810",
    "sg:province":"Toledo",
    "wof:name":"Caja De Ahorros De Castilla La Mancha",
    "wof:placetype":"venue"
},
  "geometry": {"coordinates":[-3.0136759281,39.6700668335],"type":"Point"}
}