{
  "type": "Feature",
  "properties": {
    "addr:full":"Calle de Diamante, S/n Cordoba C\u00f3rdoba 14014",
    "addr:housenumber":"s",
    "addr:postcode":"14014",
    "addr:street":"Calle De Diamante;/ N;Co\u0301Rdoba",
    "iso:country":"ES",
    "sg:address":"Calle de Diamante, S/n",
    "sg:city":"Cordoba",
    "sg:orig_category":"Chapister\u00cda",
    "sg:phone":"+34 957 26 56 61",
    "sg:postcode":"14014",
    "sg:province":"C\u00f3rdoba",
    "wof:name":"Talleres L.villegas S.l.",
    "wof:placetype":"venue"
},
  "geometry": {"coordinates":[-4.7489728928,37.8885993958],"type":"Point"}
}