{
  "type": "Feature",
  "properties": {
    "addr:full":"Calle de Juan Antonio Cavestany, 1 Sevilla Sevilla 41003",
    "addr:housenumber":"1",
    "addr:postcode":"41003",
    "addr:street":"Calle De Juan Antonio Cavestany",
    "iso:country":"ES",
    "sg:address":"Calle de Juan Antonio Cavestany, 1",
    "sg:city":"Sevilla",
    "sg:orig_category":"Peluqueros: De Se\u00d1oras",
    "sg:phone":"+34 954 42 64 79",
    "sg:postcode":"41003",
    "sg:province":"Sevilla",
    "wof:name":"Assai Peluquerias S.l.",
    "wof:placetype":"venue"
},
  "geometry": {"coordinates":[-5.9859018326,37.3942108154],"type":"Point"}
}