{
  "type": "Feature",
  "properties": {
    "addr:full":"Calle de General Sanz Pastor, 14 Burgos Burgos 09003",
    "addr:housenumber":"14",
    "addr:postcode":"09003",
    "addr:street":"Calle De General Sanz Pastor",
    "iso:country":"ES",
    "sg:address":"Calle de General Sanz Pastor, 14",
    "sg:city":"Burgos",
    "sg:orig_category":"Organizaciones Internacionales",
    "sg:phone":"+34 947 27 09 94",
    "sg:postcode":"09003",
    "sg:province":"Burgos",
    "wof:name":"Cristianos Sin Fronteras",
    "wof:placetype":"venue"
},
  "geometry": {"coordinates":[-3.6995799541,42.3444366455],"type":"Point"}
}