{
  "type": "Feature",
  "properties": {
    "addr:full":"Pol Ind Ruise\u00f1ores, S/n Zaragoza Zaragoza 50011",
    "addr:housenumber":"s / n",
    "addr:postcode":"50011",
    "iso:country":"ES",
    "sg:address":"Pol Ind Ruise\u00f1ores, S/n",
    "sg:city":"Zaragoza",
    "sg:orig_category":"Fabricaci\u00d3n, Instalaci\u00d3n De Estufas",
    "sg:phone":"+34 976 78 67 16",
    "sg:postcode":"50011",
    "sg:province":"Zaragoza",
    "sg:website":"www.norcalor.es",
    "wof:name":"Jotul Hispania S.l.",
    "wof:placetype":"venue"
},
  "geometry": {"coordinates":[-0.9913589954,41.662853241],"type":"Point"}
}