{
  "type": "Feature",
  "properties": {
    "iso:country":"ES",
    "sg:address":"Av Generalitat (de La), 161",
    "sg:city":"Tortosa",
    "sg:orig_category":"Mec\u00c1nico Del Autom\u00d3vil",
    "sg:phone":"+34 977 44 37 79",
    "sg:postcode":"43500",
    "sg:province":"Tarragona",
    "wof:name":"Talleres Tarragona Autolica S.a.",
    "wof:placetype":"venue"
},
  "geometry": {"coordinates":[0.5205469728,40.8038406372],"type":"Point"}
}