{
  "type": "Feature",
  "properties": {
    "iso:country":"ES",
    "sg:address":"Calle de Alianza, 7",
    "sg:city":"Madrid",
    "sg:orig_category":"Centros Empresariales",
    "sg:phone":"+34 913 17 23 09",
    "sg:postcode":"28041",
    "sg:province":"Madrid",
    "wof:name":"Kommad Publicidad S.l.",
    "wof:placetype":"venue"
},
  "geometry": {"coordinates":[-3.6916029453,40.3575286865],"type":"Point"}
}