{
  "type": "Feature",
  "properties": {
    "iso:country":"ES",
    "sg:address":"Plaz Mayor, 11",
    "sg:city":"Marchamalo",
    "sg:orig_category":"Molduras, Junquillos, Listones Y Molduras Perforadas",
    "sg:phone":"+34 949 25 07 63",
    "sg:postcode":"19180",
    "sg:province":"Guadalajara",
    "wof:name":"Fresno Gil Jacinto",
    "wof:placetype":"venue"
},
  "geometry": {"coordinates":[-3.2014451027,40.66954422],"type":"Point"}
}