{
  "type": "Feature",
  "properties": {
    "iso:country":"ES",
    "sg:address":"Calle de San Juan Bosco, 34",
    "sg:city":"Almeria",
    "sg:orig_category":"Estancos",
    "sg:phone":"+34 950 27 53 81",
    "sg:postcode":"04005",
    "sg:province":"Almer\u00eda",
    "wof:name":"Aguado Solis Serafin",
    "wof:placetype":"venue"
},
  "geometry": {"coordinates":[-2.454600811,36.8426094055],"type":"Point"}
}