{
  "type": "Feature",
  "properties": {
    "iso:country":"ES",
    "sg:address":"Calle de Piletes (les), 63",
    "sg:city":"Alzira",
    "sg:orig_category":"Ropa Y Accesorios",
    "sg:phone":"+34 962 40 12 20",
    "sg:postcode":"46600",
    "sg:province":"Valencia",
    "wof:name":"Manteletas Mercedes Romero S.l.",
    "wof:placetype":"venue"
},
  "geometry": {"coordinates":[-0.4342800081,39.1523323059],"type":"Point"}
}