{
  "type": "Feature",
  "properties": {
    "iso:country":"ES",
    "sg:address":"Iessa, 9",
    "sg:city":"Coma Cdad. Jardin",
    "sg:orig_category":"Iglesia Cat\u00d3lica",
    "sg:phone":"+34 963 64 18 07",
    "sg:postcode":"46980",
    "sg:province":"Valencia",
    "wof:name":"Parroquia Madre Del Redentor",
    "wof:placetype":"venue"
},
  "geometry": {"coordinates":[-0.4395389855,39.500629425],"type":"Point"}
}