{
  "type": "Feature",
  "properties": {
    "iso:country":"ES",
    "sg:address":"Calle de Errotalde, 2",
    "sg:city":"Andra Mari",
    "sg:orig_category":"Ingeniero",
    "sg:phone":"+34 944 91 25 96",
    "sg:postcode":"48993",
    "sg:province":"Vizcaya",
    "wof:name":"Ingenieria Electrica Exa S.l.",
    "wof:placetype":"venue"
},
  "geometry": {"coordinates":[-2.7541499138,43.2982711792],"type":"Point"}
}