{
  "type": "Feature",
  "properties": {
    "iso:country":"ES",
    "sg:address":"Calle de Juntas Generales, 20",
    "sg:city":"Vitoria-gasteiz",
    "sg:orig_category":"Obras Y Organismos Sociales",
    "sg:phone":"+34 945 17 69 23",
    "sg:postcode":"01010",
    "sg:province":"\u00c1lava",
    "wof:name":"Asociacion Barne Bidean",
    "wof:placetype":"venue"
},
  "geometry": {"coordinates":[-2.67988801,42.8652420044],"type":"Point"}
}