{
  "type": "Feature",
  "properties": {
    "addr:full":"Sol, 9 Cala Millor Islas Baleares 07560",
    "addr:housenumber":"9",
    "addr:postcode":"07560",
    "addr:street":"Sol;Millor",
    "iso:country":"ES",
    "sg:address":"Sol, 9",
    "sg:city":"Cala Millor",
    "sg:orig_category":"Confecci\u00d3n De Trajes Para Se\u00d1oras",
    "sg:phone":"+34 971 81 32 00",
    "sg:postcode":"07560",
    "sg:province":"Islas Baleares",
    "wof:name":"Cuatro Cubitos S.a.",
    "wof:placetype":"venue"
},
  "geometry": {"coordinates":[3.3843410015,39.6018676758],"type":"Point"}
}