{
  "type": "Feature",
  "properties": {
    "iso:country":"ES",
    "sg:address":"Calle de Domingo Ram, 26",
    "sg:city":"Zaragoza",
    "sg:orig_category":"Ropa Para Se\u00d1oras (al Por Menor)",
    "sg:phone":"+34 976 31 20 01",
    "sg:postcode":"50017",
    "sg:province":"Zaragoza",
    "wof:name":"Salvador Escolan Mercedes",
    "wof:placetype":"venue"
},
  "geometry": {"coordinates":[-0.9042403102,41.6485900879],"type":"Point"}
}