{
  "type": "Feature",
  "properties": {
    "iso:country":"ES",
    "sg:address":"Calle de Colon, 27",
    "sg:city":"Castellon",
    "sg:orig_category":"Telas Y Sedas (al Por Menor)",
    "sg:phone":"+34 964 22 49 89",
    "sg:postcode":"12001",
    "sg:province":"Castell\u00f3n",
    "wof:name":"Gimeno Navarro Filiberta",
    "wof:placetype":"venue"
},
  "geometry": {"coordinates":[-0.037934199,39.9865875244],"type":"Point"}
}