{
  "type": "Feature",
  "properties": {
    "iso:country":"ES",
    "sg:address":"Poli Industrial Corbones, S/n",
    "sg:city":"Puebla Cazalla",
    "sg:orig_category":"Servicio De Salud",
    "sg:phone":"+34 954 84 63 23",
    "sg:postcode":"41540",
    "sg:province":"Sevilla",
    "wof:name":"Perez Garrido Alejandro",
    "wof:placetype":"venue"
},
  "geometry": {"coordinates":[-5.3132190704,37.2229957581],"type":"Point"}
}