{
  "type": "Feature",
  "properties": {
    "iso:country":"ES",
    "sg:address":"C/ Mercadal, 16",
    "sg:city":"Banyoles",
    "sg:orig_category":"Farmacias",
    "sg:phone":"+34 972 58 21 79",
    "sg:postcode":"17820",
    "sg:province":"Girona",
    "wof:name":"Massgrau Vila Teodoro",
    "wof:placetype":"venue"
},
  "geometry": {"coordinates":[2.7730026245,42.1189346313],"type":"Point"}
}