{
  "type": "Feature",
  "properties": {
    "addr:full":"Nueva Apertura, S/n Palma Rio C\u00f3rdoba 14700",
    "addr:housenumber":"s",
    "addr:postcode":"14700",
    "addr:street":"/ N Palma Rio Co\u0301Rdoba",
    "iso:country":"ES",
    "sg:address":"Nueva Apertura, S/n",
    "sg:city":"Palma Rio",
    "sg:orig_category":"Producci\u00d3n, Venta De Productos De Agricultura Biol\u00d3gica",
    "sg:phone":"+34 957 71 05 12",
    "sg:postcode":"14700",
    "sg:province":"C\u00f3rdoba",
    "wof:name":"Hermanos Torres S.c.",
    "wof:placetype":"venue"
},
  "geometry": {"coordinates":[-5.2795991898,37.7004241943],"type":"Point"}
}