{
  "type": "Feature",
  "properties": {
    "iso:country":"ES",
    "sg:address":"Navio, S/n",
    "sg:city":"Garrucha",
    "sg:orig_category":"Agencias Y Agentes Comerciales, Representantes",
    "sg:phone":"+34 950 46 02 28",
    "sg:postcode":"04630",
    "sg:province":"Almer\u00eda",
    "wof:name":"Suarez Suela Jose Luis",
    "wof:placetype":"venue"
},
  "geometry": {"coordinates":[-1.8196489811,37.1859741211],"type":"Point"}
}