{
  "type": "Feature",
  "properties": {
    "addr:full":"Ctra Soria, S/n Torrecaballeros Segovia 40160",
    "addr:housenumber":"s / n",
    "addr:postcode":"40160",
    "addr:street":"Ctra Soria",
    "iso:country":"ES",
    "sg:address":"Ctra Soria, S/n",
    "sg:city":"Torrecaballeros",
    "sg:orig_category":"Molduras, Junquillos, Listones Y Molduras Perforadas",
    "sg:phone":"+34 921 40 13 03",
    "sg:postcode":"40160",
    "sg:province":"Segovia",
    "wof:name":"Miguel Hontoria Jose Ignacio",
    "wof:placetype":"venue"
},
  "geometry": {"coordinates":[-4.0244340897,40.9920578003],"type":"Point"}
}