{
  "type": "Feature",
  "properties": {
    "iso:country":"ES",
    "sg:address":"Ctra Barcelona, Km. 0006,6",
    "sg:city":"Foios",
    "sg:orig_category":"Agentes, Concesionarios Y Sucursales De Camiones Y Veh\u00cdculos Industriales",
    "sg:phone":"+34 961 49 53 02",
    "sg:postcode":"46134",
    "sg:province":"Valencia",
    "sg:website":"www.mebauto.com",
    "wof:name":"Bamauto Automocion S.l.",
    "wof:placetype":"venue"
},
  "geometry": {"coordinates":[-0.3501490057,39.5358009338],"type":"Point"}
}