{
  "type": "Feature",
  "properties": {
    "addr:full":"Calle de Almirante Cadarso, 11 Valencia Valencia 46005",
    "addr:housenumber":"11",
    "addr:postcode":"46005",
    "addr:street":"Calle De Almirante Cadarso",
    "iso:country":"ES",
    "sg:address":"Calle de Almirante Cadarso, 11",
    "sg:city":"Valencia",
    "sg:orig_category":"Abogados",
    "sg:phone":"+34 963 33 53 19",
    "sg:postcode":"46005",
    "sg:province":"Valencia",
    "wof:name":"Duran Lalaguna Mariano",
    "wof:placetype":"venue"
},
  "geometry": {"coordinates":[-0.3684572875,39.4659118652],"type":"Point"}
}