{
  "type": "Feature",
  "properties": {
    "addr:full":"Carretera De Don Benito-miajadas, Km. 0015,3 Don Benito Badajoz 06400",
    "addr:postcode":"06400",
    "addr:street":"Carretera De Don Benito-Miajadas Km. 0015,3",
    "iso:country":"ES",
    "sg:address":"Carretera De Don Benito-miajadas, Km. 0015,3",
    "sg:city":"Don Benito",
    "sg:orig_category":"Producci\u00d3n, Venta De Productos De Agricultura Biol\u00d3gica",
    "sg:phone":"+34 924 81 01 63",
    "sg:postcode":"06400",
    "sg:province":"Badajoz",
    "wof:name":"Agropecuaria De La Diputacion S.a.",
    "wof:placetype":"venue"
},
  "geometry": {"coordinates":[-5.907002,39.148457],"type":"Point"}
}