{
  "type": "Feature",
  "properties": {
    "addr:full":"Veinticinco D, 79 Nueva Andalucia M\u00e1laga 29660",
    "addr:housenumber":"79",
    "addr:postcode":"29660",
    "addr:street":"Veinticinco D;Ma\u0301Laga",
    "iso:country":"ES",
    "sg:address":"Veinticinco D, 79",
    "sg:city":"Nueva Andalucia",
    "sg:orig_category":"Inversiones",
    "sg:phone":"+34 952 90 69 08",
    "sg:postcode":"29660",
    "sg:province":"M\u00e1laga",
    "wof:name":"El Salobral Inversiones S.l.",
    "wof:placetype":"venue"
},
  "geometry": {"coordinates":[-4.9540901184,36.4891586304],"type":"Point"}
}