{
  "type": "Feature",
  "properties": {
    "addr:full":"Avda Gaiarre Julian, 42 A Bilbao Vizcaya 48004",
    "addr:housenumber":"42 a",
    "addr:postcode":"48004",
    "addr:street":"Avda Gaiarre Julian",
    "iso:country":"ES",
    "sg:address":"Avda Gaiarre Julian, 42 A",
    "sg:city":"Bilbao",
    "sg:orig_category":"Deportes Diversos",
    "sg:phone":"+34 944 12 44 87",
    "sg:postcode":"48004",
    "sg:province":"Vizcaya",
    "wof:name":"Federacion Vasca De Futbol. Comite Vasco Arbitros De Futbol",
    "wof:placetype":"venue"
},
  "geometry": {"coordinates":[-2.9461190701,43.2686500549],"type":"Point"}
}