{
  "type": "Feature",
  "properties": {
    "iso:country":"ES",
    "sg:address":"Poli Tejerias Calle de Huertos, De Los, S/n",
    "sg:city":"Calahorra",
    "sg:orig_category":"Contenedores (mercanc\u00cdas)",
    "sg:phone":"+34 941 13 11 40",
    "sg:postcode":"26500",
    "sg:province":"La Rioja",
    "wof:name":"Rosales Jimenez Piedad",
    "wof:placetype":"venue"
},
  "geometry": {"coordinates":[-1.9620640278,42.3058395386],"type":"Point"}
}