{
  "type": "Feature",
  "properties": {
    "iso:country":"ES",
    "sg:address":"Av Alacant, 28",
    "sg:city":"Mutxamel",
    "sg:orig_category":"Venta, Instalaci\u00d3n De Calefacci\u00d3n",
    "sg:phone":"+34 965 95 35 35",
    "sg:postcode":"03110",
    "sg:province":"Alicante",
    "wof:name":"Coindegas S.l.",
    "wof:placetype":"venue"
},
  "geometry": {"coordinates":[-0.4573760033,38.4327468872],"type":"Point"}
}