{
  "type": "Feature",
  "properties": {
    "addr:full":"Urb Laguia B, 2 Teruel Teruel 44003",
    "addr:postcode":"44003",
    "addr:street":"Urb",
    "iso:country":"ES",
    "sg:address":"Urb Laguia B, 2",
    "sg:city":"Teruel",
    "sg:orig_category":"Molduras, Junquillos, Listones Y Molduras Perforadas",
    "sg:phone":"+34 978 60 11 80",
    "sg:postcode":"44003",
    "sg:province":"Teruel",
    "wof:name":"Lamiral Diaz Omar Eduardo",
    "wof:placetype":"venue"
},
  "geometry": {"coordinates":[-1.1047320366,40.3476600647],"type":"Point"}
}