{
  "type": "Feature",
  "properties": {
    "iso:country":"ES",
    "sg:address":"Pasaje Espinel, 128",
    "sg:city":"Ronda",
    "sg:orig_category":"Molduras, Junquillos, Listones Y Molduras Perforadas",
    "sg:phone":"+34 952 87 96 74",
    "sg:postcode":"29400",
    "sg:province":"M\u00e1laga",
    "wof:name":"Jimenez Dominguez Manuel",
    "wof:placetype":"venue"
},
  "geometry": {"coordinates":[-5.1601924896,36.7455673218],"type":"Point"}
}