{
  "type": "Feature",
  "properties": {
    "addr:full":"Bijuters, 34 Ciutadella Menorca Islas Baleares 07760",
    "addr:housenumber":"34",
    "addr:postcode":"07760",
    "addr:street":"Bijuters",
    "iso:country":"ES",
    "sg:address":"Bijuters, 34",
    "sg:city":"Ciutadella Menorca",
    "sg:orig_category":"Bisuter\u00cda, Joyer\u00cda, Relojer\u00cda (al Por Menor)",
    "sg:phone":"+34 971 38 06 88",
    "sg:postcode":"07760",
    "sg:province":"Islas Baleares",
    "wof:name":"Juan Valera S. A.",
    "wof:placetype":"venue"
},
  "geometry": {"coordinates":[3.854113102,40.0107955933],"type":"Point"}
}