{
  "type": "Feature",
  "properties": {
    "iso:country":"ES",
    "sg:address":"Calle de Don Pedro De Luna, 87",
    "sg:city":"Zaragoza",
    "sg:orig_category":"Carnicer\u00cdas, Carnicer\u00cdas",
    "sg:phone":"+34 976 33 20 49",
    "sg:postcode":"50010",
    "sg:province":"Zaragoza",
    "wof:name":"Alimentacion Galan S.cv.",
    "wof:placetype":"venue"
},
  "geometry": {"coordinates":[-0.9032527804,41.6483802795],"type":"Point"}
}