{
  "type": "Feature",
  "properties": {
    "iso:country":"ES",
    "sg:address":"Calle de Sorgo, 65",
    "sg:city":"Madrid",
    "sg:orig_category":"Mec\u00c1nico Del Autom\u00d3vil",
    "sg:phone":"+34 913 14 56 12",
    "sg:postcode":"28029",
    "sg:province":"Madrid",
    "wof:name":"Preparaciones De Automocion A.j.s.l.",
    "wof:placetype":"venue"
},
  "geometry": {"coordinates":[-3.7056770325,40.4685974121],"type":"Point"}
}