{
  "type": "Feature",
  "properties": {
    "iso:country":"ES",
    "sg:address":"Calle de Orion, 20",
    "sg:city":"Getafe",
    "sg:orig_category":"Inmobiliaria (agencias)",
    "sg:phone":"+34 916 65 04 86",
    "sg:postcode":"28905",
    "sg:province":"Madrid",
    "wof:name":"Asesoramiento Integral De Fincas Orion 20 S.l.",
    "wof:placetype":"venue"
},
  "geometry": {"coordinates":[-3.7445363998,40.2924385071],"type":"Point"}
}