{
  "type": "Feature",
  "properties": {
    "addr:full":"Calle de Eraso, 25 Madrid Madrid 28028",
    "addr:housenumber":"25",
    "addr:postcode":"madrid;28028",
    "addr:street":"Calle De Eraso",
    "iso:country":"ES",
    "sg:address":"Calle de Eraso, 25",
    "sg:city":"Madrid",
    "sg:orig_category":"Aparatos, Sistemas De Tele",
    "sg:phone":"+34 913 61 34 38",
    "sg:postcode":"28028",
    "sg:province":"Madrid",
    "wof:name":"Guillermo Torres S. A.",
    "wof:placetype":"venue"
},
  "geometry": {"coordinates":[-3.6695230007,40.4350624084],"type":"Point"}
}