{
  "type": "Feature",
  "properties": {
    "addr:full":"Calle de Ebanisteria, 31 Torrejon Ardoz Madrid 28850",
    "addr:housenumber":"31",
    "addr:postcode":"28850",
    "addr:street":"Calle De Ebanisteria",
    "iso:country":"ES",
    "sg:address":"Calle de Ebanisteria, 31",
    "sg:city":"Torrejon Ardoz",
    "sg:orig_category":"Mec\u00c1nico Del Autom\u00d3vil",
    "sg:phone":"+34 916 74 93 79",
    "sg:postcode":"28850",
    "sg:province":"Madrid",
    "wof:name":"Talleres Bedacar C. B.",
    "wof:placetype":"venue"
},
  "geometry": {"coordinates":[-3.4635183811,40.4446372986],"type":"Point"}
}