{
  "type": "Feature",
  "properties": {
    "addr:full":"Calle de Paraguay, 17 Tablero Las Palmas 35100",
    "addr:housenumber":"17",
    "addr:postcode":"35100",
    "addr:street":"Calle De Paraguay;Las",
    "iso:country":"ES",
    "sg:address":"Calle de Paraguay, 17",
    "sg:city":"Tablero",
    "sg:orig_category":"Centros De Coordinaci\u00d3n",
    "sg:phone":"+34 928 14 19 20",
    "sg:postcode":"35100",
    "sg:province":"Las Palmas",
    "wof:name":"Oficina De Gestion Canaria S.l.",
    "wof:placetype":"venue"
},
  "geometry": {"coordinates":[-15.6032657623,27.7717208862],"type":"Point"}
}