{
  "type": "Feature",
  "properties": {
    "addr:full":"Calle de San Eloy, 19 Sevilla Sevilla 41001",
    "addr:housenumber":"19",
    "addr:postcode":"41001",
    "addr:street":"Calle De San Eloy",
    "iso:country":"ES",
    "sg:address":"Calle de San Eloy, 19",
    "sg:city":"Sevilla",
    "sg:orig_category":"Caf\u00c9s, Bares, Cervecer\u00cdas",
    "sg:phone":"+34 954 56 07 21",
    "sg:postcode":"41001",
    "sg:province":"Sevilla",
    "wof:name":"Soto Mata Carmen",
    "wof:placetype":"venue"
},
  "geometry": {"coordinates":[-5.9965977669,37.3920478821],"type":"Point"}
}