{
  "type": "Feature",
  "properties": {
    "addr:full":"Avda Ordo\u00d1o Ii, 7 Le\u00f3n Le\u00f3n 24001",
    "addr:housenumber":"7",
    "addr:postcode":"24001",
    "addr:street":"Avda Ordon\u0303O Ii;Leo\u0301N",
    "iso:country":"ES",
    "sg:address":"Avda Ordo\u00d1o Ii, 7",
    "sg:city":"Le\u00f3n",
    "sg:orig_category":"Abogados",
    "sg:phone":"+34 987 21 11 21",
    "sg:postcode":"24001",
    "sg:province":"Le\u00f3n",
    "wof:name":"Arce Mainzhausen Enrique",
    "wof:placetype":"venue"
},
  "geometry": {"coordinates":[-5.5727477074,42.5976982117],"type":"Point"}
}