{
  "type": "Feature",
  "properties": {
    "iso:country":"ES",
    "sg:address":"Calle de Roma, 11",
    "sg:city":"Humanes De Madrid",
    "sg:orig_category":"Pintura, Barniz, Productos Asimilables (fabricaci\u00d3n, Al Por Mayor)",
    "sg:phone":"+34 916 04 96 86",
    "sg:postcode":"28970",
    "sg:province":"Madrid",
    "wof:name":"Comercializadora Valresa S. L.",
    "wof:placetype":"venue"
},
  "geometry": {"coordinates":[-3.8107891083,40.2722015381],"type":"Point"}
}