{
  "type": "Feature",
  "properties": {
    "addr:full":"Avda Bruselas (de), 35 Alcobendas Madrid 28108",
    "addr:housenumber":"35",
    "addr:postcode":"28108",
    "addr:street":"Avda Bruselas De",
    "iso:country":"ES",
    "sg:address":"Avda Bruselas (de), 35",
    "sg:city":"Alcobendas",
    "sg:orig_category":"Cajas Para Embalar",
    "sg:phone":"+34 914 84 07 69",
    "sg:postcode":"28108",
    "sg:province":"Madrid",
    "wof:name":"Cajamar",
    "wof:placetype":"venue"
},
  "geometry": {"coordinates":[-3.6225941181,40.5358009338],"type":"Point"}
}