{
  "type": "Feature",
  "properties": {
    "addr:full":"Calle de Burgos, 6 Reinosa Cantabria 39200",
    "addr:housenumber":"6",
    "addr:postcode":"39200",
    "addr:street":"Calle De Burgos",
    "iso:country":"ES",
    "sg:address":"Calle de Burgos, 6",
    "sg:city":"Reinosa",
    "sg:orig_category":"Construcciones Met\u00c1licas",
    "sg:phone":"+34 942 75 36 37",
    "sg:postcode":"39200",
    "sg:province":"Cantabria",
    "wof:name":"Garcia Garcia Jose Carlos",
    "wof:placetype":"venue"
},
  "geometry": {"coordinates":[-4.1315841675,43.0033416748],"type":"Point"}
}