{
  "type": "Feature",
  "properties": {
    "addr:full":"P. Barace, 5 Iru\u00f1a Navarra 31007",
    "addr:housenumber":"5",
    "addr:postcode":"31007",
    "addr:street":"P. Barace",
    "iso:country":"ES",
    "sg:address":"P. Barace, 5",
    "sg:city":"Iru\u00f1a",
    "sg:orig_category":"Ingenier\u00cda, Centros De Estudios (diversos)",
    "sg:phone":"+34 948 19 96 18",
    "sg:postcode":"31007",
    "sg:province":"Navarra",
    "sg:website":"www.arroniz.net",
    "wof:name":"Arroniz Ingenieria S.l.",
    "wof:placetype":"venue"
},
  "geometry": {"coordinates":[-1.646902442,42.8060379028],"type":"Point"}
}