{
  "type": "Feature",
  "properties": {
    "addr:full":"Barr Boroa, S/n Boroa Vizcaya 48340",
    "addr:housenumber":"s / n",
    "addr:postcode":"48340",
    "addr:street":"Boroa",
    "iso:country":"ES",
    "sg:address":"Barr Boroa, S/n",
    "sg:city":"Boroa",
    "sg:orig_category":"Semiller\u00cdas",
    "sg:phone":"+34 946 73 03 97",
    "sg:postcode":"48340",
    "sg:province":"Vizcaya",
    "wof:name":"C.b. Boroa",
    "wof:placetype":"venue"
},
  "geometry": {"coordinates":[-2.7321588993,43.2210960388],"type":"Point"}
}