{
  "type": "Feature",
  "properties": {
    "iso:country":"ES",
    "sg:address":"Calle de Harinas, 20",
    "sg:city":"Sevilla",
    "sg:orig_category":"Inmobiliaria (agencias)",
    "sg:phone":"+34 954 50 00 59",
    "sg:postcode":"41001",
    "sg:province":"Sevilla",
    "wof:name":"Canaliega Inversiones Inmobiliarias S.l.",
    "wof:placetype":"venue"
},
  "geometry": {"coordinates":[-5.9958949089,37.3867492676],"type":"Point"}
}