{
  "type": "Feature",
  "properties": {
    "iso:country":"ES",
    "sg:address":"Calle de Hermanos Ubao, 4",
    "sg:city":"Portugalete",
    "sg:orig_category":"Molduras, Junquillos, Listones Y Molduras Perforadas",
    "sg:phone":"+34 944 61 10 32",
    "sg:postcode":"48920",
    "sg:province":"Vizcaya",
    "wof:name":"Beraza Cangas Jose Maria",
    "wof:placetype":"venue"
},
  "geometry": {"coordinates":[-3.0223650932,43.3235816956],"type":"Point"}
}