{
  "type": "Feature",
  "properties": {
    "addr:full":"Jose Artetxe Kalea, 17 Azpeitia Guip\u00f9zcoa 20730",
    "addr:housenumber":"17",
    "addr:postcode":"20730",
    "addr:street":"Jose Artetxe Kalea;Guipu\u0300Zcoa",
    "iso:country":"ES",
    "sg:address":"Jose Artetxe Kalea, 17",
    "sg:city":"Azpeitia",
    "sg:orig_category":"\u00d3ptica: Instrumentos (fabricaci\u00d3n)",
    "sg:phone":"+34 943 08 03 95",
    "sg:postcode":"20730",
    "sg:province":"Guip\u00f9zcoa",
    "wof:name":"Ostadar, C.b.",
    "wof:placetype":"venue"
},
  "geometry": {"coordinates":[-2.2670600414,43.1821327209],"type":"Point"}
}