{
  "type": "Feature",
  "properties": {
    "addr:full":"Rbla Principal, 1 Vilanova I La Geltru Barcelona 08800",
    "addr:housenumber":"1",
    "addr:postcode":"08800",
    "addr:street":"Rbla Principal",
    "iso:country":"ES",
    "sg:address":"Rbla Principal, 1",
    "sg:city":"Vilanova I La Geltru",
    "sg:orig_category":"Abogados",
    "sg:phone":"+34 938 93 41 45",
    "sg:postcode":"08800",
    "sg:province":"Barcelona",
    "wof:name":"Alba Cendre Pere",
    "wof:placetype":"venue"
},
  "geometry": {"coordinates":[1.724173665,41.2251739502],"type":"Point"}
}