{
  "type": "Feature",
  "properties": {
    "addr:full":"Avda Gaviotas, 33 Perellonet Valencia 46012",
    "addr:housenumber":"33",
    "addr:postcode":"46012",
    "addr:street":"Avda Gaviotas",
    "iso:country":"ES",
    "sg:address":"Avda Gaviotas, 33",
    "sg:city":"Perellonet",
    "sg:orig_category":"Molduras, Junquillos, Listones Y Molduras Perforadas",
    "sg:phone":"+34 961 77 75 82",
    "sg:postcode":"46012",
    "sg:province":"Valencia",
    "wof:name":"Restaurante Los Arcos S.coop.l.v.",
    "wof:placetype":"venue"
},
  "geometry": {"coordinates":[-0.2975589931,39.3079147339],"type":"Point"}
}