{
  "type": "Feature",
  "properties": {
    "iso:country":"ES",
    "sg:address":"Av Pirineus, 49",
    "sg:city":"Puigcerda",
    "sg:orig_category":"Jardiner\u00cdas, Vegetales, Art\u00cdculos De Jardiner\u00cda (al Por Menor)",
    "sg:phone":"+34 972 14 11 61",
    "sg:postcode":"17520",
    "sg:province":"Girona",
    "wof:name":"Jardineria Bernal S.l.",
    "wof:placetype":"venue"
},
  "geometry": {"coordinates":[1.9253900051,42.4297904968],"type":"Point"}
}