{
  "type": "Feature",
  "properties": {
    "iso:country":"ES",
    "sg:address":"Carr Gran, 140",
    "sg:city":"Castell",
    "sg:orig_category":"Caf\u00c9s, Bares, Cervecer\u00cdas",
    "sg:phone":"+34 971 36 08 69",
    "sg:postcode":"07720",
    "sg:province":"Islas Baleares",
    "wof:name":"Taltavull Martinez Jose Maria",
    "wof:placetype":"venue"
},
  "geometry": {"coordinates":[4.2850251198,39.8720703125],"type":"Point"}
}