{
  "type": "Feature",
  "properties": {
    "addr:full":"Avgd Alcalde Porqueres, 107 Lleida Lleida 25005",
    "addr:housenumber":"107",
    "addr:postcode":"25005",
    "addr:street":"Alcalde Porqueres",
    "iso:country":"ES",
    "sg:address":"Avgd Alcalde Porqueres, 107",
    "sg:city":"Lleida",
    "sg:orig_category":"Servidores Y Editores De Bases De Datos",
    "sg:phone":"+34 973 22 14 84",
    "sg:postcode":"25005",
    "sg:province":"Lleida",
    "wof:name":"Astrea La Infopista Juridica S.l.",
    "wof:placetype":"venue"
},
  "geometry": {"coordinates":[0.6218397021,41.6310462952],"type":"Point"}
}