{
  "type": "Feature",
  "properties": {
    "iso:country":"ES",
    "sg:address":"Belorrieta Auzoa, 6",
    "sg:city":"Aretxabaleta",
    "sg:orig_category":"M\u00c9dicos: Fisioterapia Y Rehabilitaci\u00d3n",
    "sg:phone":"+34 943 53 32 38",
    "sg:postcode":"20550",
    "sg:province":"Guip\u00f9zcoa",
    "wof:name":"Ekin",
    "wof:placetype":"venue"
},
  "geometry": {"coordinates":[-2.5053780079,43.0326843262],"type":"Point"}
}