{
  "type": "Feature",
  "properties": {
    "addr:full":"Carrer de Gilabert Centelles, 8 Palma Islas Baleares 07005",
    "addr:housenumber":"8",
    "addr:postcode":"07005",
    "addr:street":"Carrer De Gilabert Centelles",
    "iso:country":"ES",
    "sg:address":"Carrer de Gilabert Centelles, 8",
    "sg:city":"Palma",
    "sg:orig_category":"Muebles Y Accesorios Para Cocinas Y Cuartos De Ba\u00d1o (al Por Menor)",
    "sg:phone":"+34 971 46 29 26",
    "sg:postcode":"07005",
    "sg:province":"Islas Baleares",
    "wof:name":"Soolaimon S.a.l.",
    "wof:placetype":"venue"
},
  "geometry": {"coordinates":[2.6568579674,39.5741844177],"type":"Point"}
}