{
  "type": "Feature",
  "properties": {
    "iso:country":"ES",
    "sg:address":"Calle de Juan De Avalos, 14",
    "sg:city":"Esquivias",
    "sg:orig_category":"Cajas Para Embalar",
    "sg:phone":"+34 925 52 01 35",
    "sg:postcode":"45221",
    "sg:province":"Toledo",
    "wof:name":"Caja Rural Provincial De Toledo",
    "wof:placetype":"venue"
},
  "geometry": {"coordinates":[-3.7668690681,40.103969574],"type":"Point"}
}