{
  "type": "Feature",
  "properties": {
    "iso:country":"ES",
    "sg:address":"P. Industrial, S/n",
    "sg:city":"Rota",
    "sg:orig_category":"Mec\u00c1nico Del Autom\u00d3vil",
    "sg:phone":"+34 956 81 32 03",
    "sg:postcode":"11520",
    "sg:province":"C\u00e1diz",
    "wof:name":"Ruiz-henestrosa Verano Rafael",
    "wof:placetype":"venue"
},
  "geometry": {"coordinates":[-6.3688821793,36.6247940063],"type":"Point"}
}