{
  "type": "Feature",
  "properties": {
    "addr:full":"Calle de San Francisco, 79 Lucena C\u00f3rdoba 14900",
    "addr:housenumber":"79",
    "addr:postcode":"14900",
    "addr:street":"Calle De San Francisco",
    "iso:country":"ES",
    "sg:address":"Calle de San Francisco, 79",
    "sg:city":"Lucena",
    "sg:classifiers":[
        {
            "category":"Banks & Credit Unions",
            "subcategory":"Bureau De Change",
            "type":"Services"
        }
    ],
    "sg:phone":"+34 957 51 05 55",
    "sg:postcode":"14900",
    "sg:province":"C\u00f3rdoba",
    "sg:tags":[
        "organismos",
        "control"
    ],
    "wof:name":"Applus Norcontrol S.l.",
    "wof:placetype":"venue"
},
  "geometry": {"coordinates":[-4.487347126,37.4135055542],"type":"Point"}
}