{
  "type": "Feature",
  "properties": {
    "iso:country":"ES",
    "sg:address":"Calle de Emilio Castelar, 53",
    "sg:city":"Algeciras",
    "sg:orig_category":"Ropa Para Se\u00d1oras (al Por Menor)",
    "sg:phone":"+34 956 66 49 44",
    "sg:postcode":"11201",
    "sg:province":"C\u00e1diz",
    "wof:name":"Perea Postigo Juan Jose",
    "wof:placetype":"venue"
},
  "geometry": {"coordinates":[-5.447581768,36.1286888123],"type":"Point"}
}