{
  "type": "Feature",
  "properties": {
    "addr:full":"Carretera De Taboadela, 25 Taboadela Ourense 32690",
    "addr:housenumber":"25",
    "addr:postcode":"32690",
    "addr:street":"Carretera De Taboadela",
    "iso:country":"ES",
    "sg:address":"Carretera De Taboadela, 25",
    "sg:city":"Taboadela",
    "sg:orig_category":"Farmacias",
    "sg:phone":"+34 988 43 64 03",
    "sg:postcode":"32690",
    "sg:province":"Ourense",
    "wof:name":"Casares Dorribo Rosario",
    "wof:placetype":"venue"
},
  "geometry": {"coordinates":[-7.8257160187,42.2405128479],"type":"Point"}
}