{
  "type": "Feature",
  "properties": {
    "iso:country":"ES",
    "sg:address":"Calle de Roberto Martin Holgado (de), 7",
    "sg:city":"Pozuelo De Alarcon",
    "sg:orig_category":"Abogados",
    "sg:phone":"+34 913 52 46 79",
    "sg:postcode":"28223",
    "sg:province":"Madrid",
    "wof:name":"Romero-salazar Bravo Bernardino",
    "wof:placetype":"venue"
},
  "geometry": {"coordinates":[-3.8110771179,40.4338645935],"type":"Point"}
}