{
  "type": "Feature",
  "properties": {
    "addr:full":"Calle de Corredera De San Marcos, 27 Linares Ja\u00e9n 23700",
    "addr:housenumber":"27",
    "addr:postcode":"23700",
    "addr:street":"Calle De Corredera De San Marcos;Jae\u0301N",
    "iso:country":"ES",
    "sg:address":"Calle de Corredera De San Marcos, 27",
    "sg:city":"Linares",
    "sg:orig_category":"Sociedades, Compa\u00d1\u00cdas Aseguradoras",
    "sg:phone":"+34 953 69 20 55",
    "sg:postcode":"23700",
    "sg:province":"Ja\u00e9n",
    "wof:name":"Ocaso S.a. Compa\u00f1ia De Seguros Y Reaseguros",
    "wof:placetype":"venue"
},
  "geometry": {"coordinates":[-3.6340744495,38.0968093872],"type":"Point"}
}