{
  "type": "Feature",
  "properties": {
    "addr:full":"Carrer de Mas Adei, 116 Terrassa Barcelona 08221",
    "addr:housenumber":"116",
    "addr:postcode":"08221",
    "addr:street":"Carrer De Mas Adei",
    "iso:country":"ES",
    "sg:address":"Carrer de Mas Adei, 116",
    "sg:city":"Terrassa",
    "sg:orig_category":"Caf\u00c9s, Bares, Cervecer\u00cdas",
    "sg:phone":"+34 937 83 89 91",
    "sg:postcode":"08221",
    "sg:province":"Barcelona",
    "wof:name":"Martinez Garcia Josefa",
    "wof:placetype":"venue"
},
  "geometry": {"coordinates":[2.0147130489,41.5695266724],"type":"Point"}
}