{
  "type": "Feature",
  "properties": {
    "addr:full":"Calle de Francisco Pizarro, 17 San Antonio Murcia 30800",
    "addr:housenumber":"17",
    "addr:postcode":"30800",
    "addr:street":"Calle De Francisco Pizarro",
    "iso:country":"ES",
    "sg:address":"Calle de Francisco Pizarro, 17",
    "sg:city":"San Antonio",
    "sg:orig_category":"Venta, Colocaci\u00d3n, Reparaci\u00d3n De Radiadores Para Veh\u00cdculos",
    "sg:phone":"+34 968 47 06 81",
    "sg:postcode":"30800",
    "sg:province":"Murcia",
    "wof:name":"Terrones Soler Andres",
    "wof:placetype":"venue"
},
  "geometry": {"coordinates":[-1.1298867464,37.9834747314],"type":"Point"}
}