{
  "type": "Feature",
  "properties": {
    "iso:country":"ES",
    "sg:address":"Calle de Barranco, S/n",
    "sg:city":"Sartaguda",
    "sg:orig_category":"Producci\u00d3n De Abonos Y De Fertilizantes",
    "sg:phone":"+34 948 66 72 99",
    "sg:postcode":"31589",
    "sg:province":"Navarra",
    "wof:name":"Agricola Mangado S.l.",
    "wof:placetype":"venue"
},
  "geometry": {"coordinates":[-2.0566518307,42.3793830872],"type":"Point"}
}