{
  "type": "Feature",
  "properties": {
    "addr:full":"Calle de Marques De San Gregorio, 7 Madrid Madrid 28026",
    "addr:housenumber":"7",
    "addr:postcode":"madrid;28026",
    "addr:street":"Calle De Marques De San Gregorio",
    "iso:country":"ES",
    "sg:address":"Calle de Marques De San Gregorio, 7",
    "sg:city":"Madrid",
    "sg:orig_category":"Agentes, Concesionarios Y Sucursales De Veh\u00cdculos",
    "sg:phone":"+34 915 00 54 76",
    "sg:postcode":"28026",
    "sg:province":"Madrid",
    "sg:website":"www.yamotor.com",
    "wof:name":"Yamotor Multimedia S.l.",
    "wof:placetype":"venue"
},
  "geometry": {"coordinates":[-3.7069406509,40.3821716309],"type":"Point"}
}