{
  "type": "Feature",
  "properties": {
    "iso:country":"ES",
    "sg:address":"Calle de San Juan, 39",
    "sg:city":"Nerja",
    "sg:orig_category":"Ense\u00d1anza: Idiomas",
    "sg:phone":"+34 952 52 74 35",
    "sg:postcode":"29780",
    "sg:province":"M\u00e1laga",
    "wof:name":"Escuela De Idiomas Nerja S.l.",
    "wof:placetype":"venue"
},
  "geometry": {"coordinates":[-3.8739039898,36.7497406006],"type":"Point"}
}