{
  "type": "Feature",
  "properties": {
    "addr:full":"Rua Ponte De San Lazaro (da), 14 Santiago De Compostela A Coru\u00f1a 15703",
    "addr:postcode":"15703",
    "addr:street":"Rua Ponte De San;Da;Corun\u0303A",
    "iso:country":"ES",
    "sg:address":"Rua Ponte De San Lazaro (da), 14",
    "sg:city":"Santiago De Compostela",
    "sg:orig_category":"Alimentaci\u00d3n General (al Por Menor)",
    "sg:phone":"+34 981 58 94 56",
    "sg:postcode":"15703",
    "sg:province":"A Coru\u00f1a",
    "wof:name":"Vazquez Carollo S.l.",
    "wof:placetype":"venue"
},
  "geometry": {"coordinates":[-8.5082187653,42.8875999451],"type":"Point"}
}