{
  "type": "Feature",
  "properties": {
    "addr:full":"Calle de Puerta De Aguilar, 6 Montilla C\u00f3rdoba 14550",
    "addr:housenumber":"6",
    "addr:postcode":"14550",
    "addr:street":"Calle De Puerta De Aguilar;Co\u0301Rdoba",
    "iso:country":"ES",
    "sg:address":"Calle de Puerta De Aguilar, 6",
    "sg:city":"Montilla",
    "sg:orig_category":"Artes Gr\u00c1ficas, Artes Pl\u00c1sticas: Material Y Suministros (al Por Menor)",
    "sg:phone":"+34 957 65 03 63",
    "sg:postcode":"14550",
    "sg:province":"C\u00f3rdoba",
    "wof:name":"Ruz Requena Esperanza",
    "wof:placetype":"venue"
},
  "geometry": {"coordinates":[-4.6404490471,37.5855712891],"type":"Point"}
}