{
  "type": "Feature",
  "properties": {
    "addr:full":"Diputacion De Purias, S/n Purias Murcia 30813",
    "addr:postcode":"30813",
    "addr:street":"Diputacion;Purias S / N",
    "iso:country":"ES",
    "sg:address":"Diputacion De Purias, S/n",
    "sg:city":"Purias",
    "sg:orig_category":"Contenedores (mercanc\u00cdas)",
    "sg:phone":"+34 968 48 26 20",
    "sg:postcode":"30813",
    "sg:province":"Murcia",
    "wof:name":"Trans-paneuropa S.l.",
    "wof:placetype":"venue"
},
  "geometry": {"coordinates":[-1.7215889692,37.491394043],"type":"Point"}
}