{
  "type": "Feature",
  "properties": {
    "iso:country":"ES",
    "sg:address":"Carrer de Montseny, 163",
    "sg:city":"Hospitalet Llobregat",
    "sg:orig_category":"Artes Gr\u00c1ficas, Artes Pl\u00c1sticas (curso)",
    "sg:phone":"+34 933 34 05 58",
    "sg:postcode":"08904",
    "sg:province":"Barcelona",
    "wof:name":"Fernandez Miragaya Antonio",
    "wof:placetype":"venue"
},
  "geometry": {"coordinates":[2.1184399128,41.3693161011],"type":"Point"}
}