{
  "type": "Feature",
  "properties": {
    "addr:full":"Plaz Pilar, 4 Ciudad Real Ciudad Real 13001",
    "addr:housenumber":"4",
    "addr:postcode":"13001",
    "addr:street":"Plaz Pilar",
    "iso:country":"ES",
    "sg:address":"Plaz Pilar, 4",
    "sg:city":"Ciudad Real",
    "sg:orig_category":"Sociedades, Compa\u00d1\u00cdas Aseguradoras",
    "sg:phone":"+34 926 21 15 78",
    "sg:postcode":"13001",
    "sg:province":"Ciudad Real",
    "wof:name":"Mutua General Seguros",
    "wof:placetype":"venue"
},
  "geometry": {"coordinates":[-3.9301741123,38.9844093323],"type":"Point"}
}