{
  "type": "Feature",
  "properties": {
    "addr:full":"Ptda Santa Faz, 4 Santa Faz Alicante 03559",
    "addr:housenumber":"4",
    "addr:postcode":"03559",
    "addr:street":"Ptda Santa Faz",
    "iso:country":"ES",
    "sg:address":"Ptda Santa Faz, 4",
    "sg:city":"Santa Faz",
    "sg:orig_category":"Organizaciones Internacionales",
    "sg:phone":"+34 965 15 23 67",
    "sg:postcode":"03559",
    "sg:province":"Alicante",
    "wof:name":"Asociacion Daajla Solidarios Con El Pueblo Saharaui",
    "wof:placetype":"venue"
},
  "geometry": {"coordinates":[-0.4430165887,38.3895683289],"type":"Point"}
}