{
  "type": "Feature",
  "properties": {
    "iso:country":"ES",
    "sg:address":"Calle de Costa Rica, 7",
    "sg:city":"Pinto",
    "sg:orig_category":"Asociaciones, Organismos Culturales Y Socioeducativos",
    "sg:phone":"+34 916 91 09 03",
    "sg:postcode":"28320",
    "sg:province":"Madrid",
    "wof:name":"La Agrupacion A.i.j.",
    "wof:placetype":"venue"
},
  "geometry": {"coordinates":[-3.7004590034,40.2400550842],"type":"Point"}
}