{
  "type": "Feature",
  "properties": {
    "iso:country":"ES",
    "sg:address":"Calle de Jose Picon, 15",
    "sg:city":"Madrid",
    "sg:orig_category":"Centros Empresariales",
    "sg:phone":"+34 913 61 32 64",
    "sg:postcode":"28028",
    "sg:province":"Madrid",
    "wof:name":"Executive Business Training S.l.",
    "wof:placetype":"venue"
},
  "geometry": {"coordinates":[-3.6725230217,40.4350852966],"type":"Point"}
}