{
  "type": "Feature",
  "properties": {
    "iso:country":"ES",
    "sg:address":"Cami Sant Jeroni De Murtra, 3",
    "sg:city":"Badalona",
    "sg:orig_category":"Peluquer\u00cdas, Peluquer\u00cda Mixta",
    "sg:phone":"+34 934 65 75 19",
    "sg:postcode":"08917",
    "sg:province":"Barcelona",
    "wof:name":"Manchado Naranjo Monica",
    "wof:placetype":"venue"
},
  "geometry": {"coordinates":[2.2355649471,41.4545402527],"type":"Point"}
}