{
  "type": "Feature",
  "properties": {
    "iso:country":"ES",
    "sg:address":"Calle de Costa Rica, 9",
    "sg:city":"Madrid",
    "sg:orig_category":"Centros Empresariales",
    "sg:phone":"+34 913 53 01 92",
    "sg:postcode":"28016",
    "sg:province":"Madrid",
    "wof:name":"Clear Gestion S.l.",
    "wof:placetype":"venue"
},
  "geometry": {"coordinates":[-3.6753749847,40.4586639404],"type":"Point"}
}