{
  "type": "Feature",
  "properties": {
    "addr:full":"Rua Lalin, 4 Vigo Pontevedra 36209",
    "addr:housenumber":"4",
    "addr:postcode":"36209",
    "addr:street":"Rua Lalin",
    "iso:country":"ES",
    "sg:address":"Rua Lalin, 4",
    "sg:city":"Vigo",
    "sg:orig_category":"Estancos",
    "sg:phone":"+34 986 20 79 05",
    "sg:postcode":"36209",
    "sg:province":"Pontevedra",
    "wof:name":"Rodriguez Fidalgo Francisco",
    "wof:placetype":"venue"
},
  "geometry": {"coordinates":[-8.7349081039,42.2214126587],"type":"Point"}
}