{
  "type": "Feature",
  "properties": {
    "addr:full":"Calle de General Franco, 37 Padron La Coru\u00f1a 15900",
    "addr:housenumber":"37",
    "addr:postcode":"15900",
    "addr:street":"Calle De General Franco;Padron La Corun\u0303A",
    "iso:country":"ES",
    "sg:address":"Calle de General Franco, 37",
    "sg:city":"Padron",
    "sg:orig_category":"Arquitectos",
    "sg:phone":"+34 981 81 17 11",
    "sg:postcode":"15900",
    "sg:province":"La Coru\u00f1a",
    "wof:name":"Pi\u00f1eiro Bermudez Luciano",
    "wof:placetype":"venue"
},
  "geometry": {"coordinates":[-8.6605482101,42.7380867004],"type":"Point"}
}