{
  "type": "Feature",
  "properties": {
    "addr:full":"Calle de Sarrikobaso, 2 Algorta Vizcaya 48991",
    "addr:housenumber":"2",
    "addr:postcode":"48991",
    "addr:street":"Calle De Sarrikobaso",
    "iso:country":"ES",
    "sg:address":"Calle de Sarrikobaso, 2",
    "sg:city":"Algorta",
    "sg:orig_category":"M\u00c9dicos: Psiquiatr\u00cda",
    "sg:phone":"+34 944 30 88 39",
    "sg:postcode":"48991",
    "sg:province":"Vizcaya",
    "wof:name":"Barandiaran Garcia Isabel",
    "wof:placetype":"venue"
},
  "geometry": {"coordinates":[-3.0097200871,43.3521537781],"type":"Point"}
}