{
  "type": "Feature",
  "properties": {
    "addr:full":"Carr Girona, 8 Oliana Lleida 25790",
    "addr:housenumber":"8",
    "addr:postcode":"25790",
    "addr:street":"Carr Girona",
    "iso:country":"ES",
    "sg:address":"Carr Girona, 8",
    "sg:city":"Oliana",
    "sg:orig_category":"Sanatorios M\u00c9dico",
    "sg:phone":"+34 973 46 30 22",
    "sg:postcode":"25790",
    "sg:province":"Lleida",
    "wof:name":"Centre De Telecomunicaciones De Catalunya",
    "wof:placetype":"venue"
},
  "geometry": {"coordinates":[1.2682909966,42.0589828491],"type":"Point"}
}