{
  "type": "Feature",
  "properties": {
    "addr:full":"Carr Maragall, 4 Lleida Lleida 25003",
    "addr:housenumber":"4",
    "addr:postcode":"25003",
    "addr:street":"Carr Maragall",
    "iso:country":"ES",
    "sg:address":"Carr Maragall, 4",
    "sg:city":"Lleida",
    "sg:orig_category":"Asociaciones Humanitarias, De Cooperaci\u00d3n, De Acci\u00d3n Social",
    "sg:phone":"+34 973 26 67 53",
    "sg:postcode":"25003",
    "sg:province":"Lleida",
    "wof:name":"Fraternidad Cristiana De Enfermos Y Minusvalidos De La Provincia De Lerida",
    "wof:placetype":"venue"
},
  "geometry": {"coordinates":[0.6178060174,41.6132621765],"type":"Point"}
}