{
  "type": "Feature",
  "properties": {
    "addr:full":"Calle de Sacramento Esteve, 3 Xirivella Valencia 46950",
    "addr:housenumber":"3",
    "addr:postcode":"46950",
    "addr:street":"Calle De Sacramento Esteve",
    "iso:country":"ES",
    "sg:address":"Calle de Sacramento Esteve, 3",
    "sg:city":"Xirivella",
    "sg:orig_category":"Peluqueros: De Se\u00d1oras",
    "sg:phone":"+34 963 59 98 60",
    "sg:postcode":"46950",
    "sg:province":"Valencia",
    "wof:name":"Peluqueros Xirivella Cooperativa Valenciana V 1608",
    "wof:placetype":"venue"
},
  "geometry": {"coordinates":[-0.4291099906,39.4659309387],"type":"Point"}
}