{
  "type": "Feature",
  "properties": {
    "addr:full":"Calle de Leon, 8 Fuenlabrada Madrid 28947",
    "addr:housenumber":"8",
    "addr:postcode":"28947",
    "addr:street":"Calle De Leon",
    "iso:country":"ES",
    "sg:address":"Calle de Leon, 8",
    "sg:city":"Fuenlabrada",
    "sg:orig_category":"Importaci\u00d3n",
    "sg:phone":"+34 916 42 07 35",
    "sg:postcode":"28947",
    "sg:province":"Madrid",
    "wof:name":"Import-export Bey Ley S.l.",
    "wof:placetype":"venue"
},
  "geometry": {"coordinates":[-3.7435789108,40.2657623291],"type":"Point"}
}