{
  "type": "Feature",
  "properties": {
    "addr:full":"Avda Zaragoza, 15 Almunia De Do\u00e7a Godina Zaragoza 50100",
    "addr:housenumber":"15",
    "addr:postcode":"50100",
    "addr:street":"Avda Zaragoza",
    "iso:country":"ES",
    "sg:address":"Avda Zaragoza, 15",
    "sg:city":"Almunia De Do\u00e7a Godina",
    "sg:orig_category":"Chapister\u00cda",
    "sg:phone":"+34 976 81 26 84",
    "sg:postcode":"50100",
    "sg:province":"Zaragoza",
    "wof:name":"Talleres Aisa S.l.",
    "wof:placetype":"venue"
},
  "geometry": {"coordinates":[-1.3713589907,41.4831085205],"type":"Point"}
}