{
  "type": "Feature",
  "properties": {
    "iso:country":"ES",
    "sg:address":"Carr Sant Gregori, 11",
    "sg:city":"Vilanova I La Geltru",
    "sg:orig_category":"Ropa Para Se\u00d1oras Y Caballeros (al Por Menor)",
    "sg:phone":"+34 938 14 27 03",
    "sg:postcode":"08800",
    "sg:province":"Barcelona",
    "wof:name":"Oliva Galvez Antonio",
    "wof:placetype":"venue"
},
  "geometry": {"coordinates":[1.7249180079,41.2262191772],"type":"Point"}
}