{
  "type": "Feature",
  "properties": {
    "addr:full":"Calle de Padilla, 6 Valladolid Valladolid 47003",
    "addr:housenumber":"6",
    "addr:postcode":"47003",
    "addr:street":"Calle De Padilla",
    "iso:country":"ES",
    "sg:address":"Calle de Padilla, 6",
    "sg:city":"Valladolid",
    "sg:orig_category":"Servicios Diversos",
    "sg:phone":"+34 983 26 64 41",
    "sg:postcode":"47003",
    "sg:province":"Valladolid",
    "wof:name":"Forcoe S.l.",
    "wof:placetype":"venue"
},
  "geometry": {"coordinates":[-4.7218980789,41.6573257446],"type":"Point"}
}