{
  "type": "Feature",
  "properties": {
    "iso:country":"ES",
    "sg:address":"Calle de Zubitxueta, 2",
    "sg:city":"Barakaldo",
    "sg:orig_category":"Comercio De Piezas De Recambio Y De Accesorios De Veh\u00cdculos, Veh\u00cdculos Industriales",
    "sg:phone":"+34 944 90 41 43",
    "sg:postcode":"48903",
    "sg:province":"Vizcaya",
    "wof:name":"Autorecambios Retuerto",
    "wof:placetype":"venue"
},
  "geometry": {"coordinates":[-2.9977428913,43.2864151001],"type":"Point"}
}