{
  "type": "Feature",
  "properties": {
    "iso:country":"ES",
    "sg:address":"Calle de Raimundo Lulio, 1",
    "sg:city":"Madrid",
    "sg:orig_category":"Librer\u00cdas",
    "sg:phone":"+34 915 93 96 06",
    "sg:postcode":"28010",
    "sg:province":"Madrid",
    "sg:website":"www.axon.es",
    "wof:name":"Axon Libreria S.l.",
    "wof:placetype":"venue"
},
  "geometry": {"coordinates":[-3.7004342079,40.4325523376],"type":"Point"}
}