{
  "type": "Feature",
  "properties": {
    "iso:country":"ES",
    "sg:address":"Lausitta Kalea, S/n",
    "sg:city":"Aretxabaleta",
    "sg:orig_category":"Fabricaci\u00d3n De Pernos, Tornillos Y Clavos",
    "sg:phone":"+34 943 79 25 28",
    "sg:postcode":"20550",
    "sg:province":"Guip\u00f9zcoa",
    "wof:name":"Santiago Bengoa S. L.",
    "wof:placetype":"venue"
},
  "geometry": {"coordinates":[-2.5076930523,43.038356781],"type":"Point"}
}