{
  "type": "Feature",
  "properties": {
    "addr:full":"Carr Sant Mori, 2 Empuriabrava Girona 17487",
    "addr:housenumber":"2",
    "addr:postcode":"17487",
    "addr:street":"Carr Sant Mori",
    "iso:country":"ES",
    "sg:address":"Carr Sant Mori, 2",
    "sg:city":"Empuriabrava",
    "sg:orig_category":"Bisuter\u00cda, Joyer\u00cda, Relojer\u00cda (al Por Menor)",
    "sg:phone":"+34 972 45 42 51",
    "sg:postcode":"17487",
    "sg:province":"Girona",
    "wof:name":"Murcia Mateo Felix",
    "wof:placetype":"venue"
},
  "geometry": {"coordinates":[3.1070549488,42.2568092346],"type":"Point"}
}