{
  "type": "Feature",
  "properties": {
    "addr:full":"Carrer de Gaudi, 25 Manresa Barcelona 08243",
    "addr:housenumber":"25",
    "addr:postcode":"08243",
    "addr:street":"Carrer De Gaudi",
    "iso:country":"ES",
    "sg:address":"Carrer de Gaudi, 25",
    "sg:city":"Manresa",
    "sg:orig_category":"Electricidad: Instaladores",
    "sg:phone":"+34 938 77 05 66",
    "sg:postcode":"08243",
    "sg:province":"Barcelona",
    "wof:name":"Electricitat Felix Cornet S.l.",
    "wof:placetype":"venue"
},
  "geometry": {"coordinates":[1.8348400593,41.7292518616],"type":"Point"}
}