{
  "type": "Feature",
  "properties": {
    "iso:country":"ES",
    "sg:address":"Calle de Tiberiades, 8",
    "sg:city":"Sevilla",
    "sg:orig_category":"Delegados, Agentes De Tr\u00c1nsito, Auxiliares De Transporte Internacional",
    "sg:phone":"+34 954 58 15 23",
    "sg:postcode":"41007",
    "sg:province":"Sevilla",
    "wof:name":"Nieto Palomino Antonio",
    "wof:placetype":"venue"
},
  "geometry": {"coordinates":[-5.9706439972,37.391078949],"type":"Point"}
}