{
  "type": "Feature",
  "properties": {
    "addr:full":"Centro Empresarial San Miguel, 6 Armilla Granada 18100",
    "addr:housenumber":"6",
    "addr:postcode":"18100",
    "addr:street":"San Miguel",
    "iso:country":"ES",
    "sg:address":"Centro Empresarial San Miguel, 6",
    "sg:city":"Armilla",
    "sg:orig_category":"Molduras, Junquillos, Listones Y Molduras Perforadas",
    "sg:phone":"+34 958 55 33 90",
    "sg:postcode":"18100",
    "sg:province":"Granada",
    "wof:name":"Navarro Gomez Concepcion",
    "wof:placetype":"venue"
},
  "geometry": {"coordinates":[-3.6233580112,37.1459732056],"type":"Point"}
}