{
  "type": "Feature",
  "properties": {
    "iso:country":"ES",
    "sg:address":"Calle de Juan Manuel Duran Gonzalez, 6",
    "sg:city":"Palmas De Gran Canaria",
    "sg:orig_category":"Asociaciones Y Clubs Deportivos",
    "sg:phone":"+34 928 26 13 46",
    "sg:postcode":"35007",
    "sg:province":"Las Palmas",
    "wof:name":"Telo Nu\u00f1ez Jesus",
    "wof:placetype":"venue"
},
  "geometry": {"coordinates":[-15.43019104,28.1354236603],"type":"Point"}
}