{
  "type": "Feature",
  "properties": {
    "addr:full":"Calle de Villahermosa, Duquesa De, 5 Huesca Huesca 22001",
    "addr:housenumber":"5",
    "addr:postcode":"22001",
    "addr:street":"Calle De Villahermosa Duquesa De",
    "iso:country":"ES",
    "sg:address":"Calle de Villahermosa, Duquesa De, 5",
    "sg:city":"Huesca",
    "sg:orig_category":"M\u00c1quinas De Coser Y De Hacer Punto (al Por Mayor)",
    "sg:phone":"+34 974 23 03 84",
    "sg:postcode":"22001",
    "sg:province":"Huesca",
    "wof:name":"Dieste Castillo Maria Pilar",
    "wof:placetype":"venue"
},
  "geometry": {"coordinates":[-0.4082799852,42.1377449036],"type":"Point"}
}