{
  "type": "Feature",
  "properties": {
    "addr:full":"Calle de Francisco Gallego, 38 Avila \u00c1vila 05002",
    "addr:housenumber":"38",
    "addr:postcode":"05002",
    "addr:street":"Calle De Francisco Gallego;A\u0301Vila",
    "iso:country":"ES",
    "sg:address":"Calle de Francisco Gallego, 38",
    "sg:city":"Avila",
    "sg:orig_category":"Fabricaci\u00d3n, Instalaci\u00d3n De Armarios",
    "sg:phone":"+34 920 22 93 06",
    "sg:postcode":"05002",
    "sg:province":"\u00c1vila",
    "wof:name":"Martin Martin Maria Del Rosario",
    "wof:placetype":"venue"
},
  "geometry": {"coordinates":[-4.6971402168,40.6525611877],"type":"Point"}
}