{
  "type": "Feature",
  "properties": {
    "iso:country":"ES",
    "sg:address":"Carrer de Felip Ii, 23",
    "sg:city":"Barcelona",
    "sg:orig_category":"Alquiler De Veh\u00cdculos: Turismos Y Utilitarios",
    "sg:phone":"+34 934 08 26 02",
    "sg:postcode":"08027",
    "sg:province":"Barcelona",
    "wof:name":"Confort Bus Catalu\u00f1a S.l.",
    "wof:placetype":"venue"
},
  "geometry": {"coordinates":[2.1904220581,41.4175186157],"type":"Point"}
}