{
  "type": "Feature",
  "properties": {
    "addr:full":"Carrer de Calvet D'estrella, 98 Sabadell Barcelona 08203",
    "addr:housenumber":"98",
    "addr:postcode":"08203",
    "addr:street":"Carrer De Calvet D'Estrella",
    "iso:country":"ES",
    "sg:address":"Carrer de Calvet D'estrella, 98",
    "sg:city":"Sabadell",
    "sg:orig_category":"Desinfecci\u00d3n, Desinsectaci\u00d3n, Desratizaci\u00d3n",
    "sg:phone":"+34 937 10 83 83",
    "sg:postcode":"08203",
    "sg:province":"Barcelona",
    "wof:name":"Comercial Insec-raters S.c.p.",
    "wof:placetype":"venue"
},
  "geometry": {"coordinates":[2.1181147099,41.5365791321],"type":"Point"}
}