{
  "type": "Feature",
  "properties": {
    "addr:full":"Plaz San Francisco, 5 Baza Granada 18800",
    "addr:housenumber":"5",
    "addr:postcode":"18800",
    "addr:street":"Plaz San Francisco",
    "iso:country":"ES",
    "sg:address":"Plaz San Francisco, 5",
    "sg:city":"Baza",
    "sg:orig_category":"\u00d3ptica: Instrumentos (fabricaci\u00d3n)",
    "sg:phone":"+34 958 86 15 30",
    "sg:postcode":"18800",
    "sg:province":"Granada",
    "wof:name":"Garcia Chacon Remedios",
    "wof:placetype":"venue"
},
  "geometry": {"coordinates":[-2.7822339535,37.4883460999],"type":"Point"}
}