{
  "type": "Feature",
  "properties": {
    "addr:full":"Calle de Duque De La Torre, 10 Arona Santa Cruz De Tenerife 38640",
    "addr:housenumber":"10",
    "addr:postcode":"38640",
    "addr:street":"Calle De Duque De La Torre",
    "iso:country":"ES",
    "sg:address":"Calle de Duque De La Torre, 10",
    "sg:city":"Arona",
    "sg:orig_category":"Farmacias",
    "sg:phone":"+34 922 72 60 21",
    "sg:postcode":"38640",
    "sg:province":"Santa Cruz De Tenerife",
    "wof:name":"Comenge Acosta Juan",
    "wof:placetype":"venue"
},
  "geometry": {"coordinates":[-16.680770874,28.0987472534],"type":"Point"}
}