{
  "type": "Feature",
  "properties": {
    "iso:country":"ES",
    "sg:address":"Calle de Rosario, 60",
    "sg:city":"Gijon",
    "sg:orig_category":"Molduras, Junquillos, Listones Y Molduras Perforadas",
    "sg:phone":"+34 985 35 70 75",
    "sg:postcode":"33201",
    "sg:province":"Asturias",
    "wof:name":"Garcia Pi\u00f1era Enrique",
    "wof:placetype":"venue"
},
  "geometry": {"coordinates":[-5.6647338867,43.5465354919],"type":"Point"}
}