{
  "type": "Feature",
  "properties": {
    "addr:full":"Carrer de Horta Novella, 113 Sabadell Barcelona 08201",
    "addr:housenumber":"113",
    "addr:postcode":"08201",
    "addr:street":"Carrer De Horta Novella",
    "iso:country":"ES",
    "sg:address":"Carrer de Horta Novella, 113",
    "sg:city":"Sabadell",
    "sg:orig_category":"Electricidad: Instaladores",
    "sg:phone":"+34 937 45 10 30",
    "sg:postcode":"08201",
    "sg:province":"Barcelona",
    "wof:name":"Bit A Bit S.l.",
    "wof:placetype":"venue"
},
  "geometry": {"coordinates":[2.1038858891,41.5432052612],"type":"Point"}
}