{
  "type": "Feature",
  "properties": {
    "iso:country":"ES",
    "sg:address":"Rond Canaleta, S/n",
    "sg:city":"Banyoles",
    "sg:orig_category":"Maquinaria Para Industrias Diversas",
    "sg:phone":"+34 972 57 68 00",
    "sg:postcode":"17820",
    "sg:province":"Girona",
    "wof:name":"Servei Integral Maquina Eina S L",
    "wof:placetype":"venue"
},
  "geometry": {"coordinates":[2.7682349682,42.125164032],"type":"Point"}
}