{
  "type": "Feature",
  "properties": {
    "iso:country":"ES",
    "sg:address":"Carrer de Al-shafra, 3",
    "sg:city":"Crevillent",
    "sg:orig_category":"Peluqueros: De Se\u00d1oras",
    "sg:phone":"+34 966 68 00 35",
    "sg:postcode":"03330",
    "sg:province":"Alicante",
    "wof:name":"Bernabeu Candela Ana Maria",
    "wof:placetype":"venue"
},
  "geometry": {"coordinates":[-0.8067070246,38.248008728],"type":"Point"}
}