{
  "type": "Feature",
  "properties": {
    "addr:full":"Avda Mediterraneo (del), 195 Rincon Victoria M\u00e1laga 29730",
    "addr:housenumber":"195",
    "addr:postcode":"29730",
    "addr:street":"Avda Mediterraneo Del;Ma\u0301Laga",
    "iso:country":"ES",
    "sg:address":"Avda Mediterraneo (del), 195",
    "sg:city":"Rincon Victoria",
    "sg:orig_category":"M\u00c9dicos: Pediatr\u00cda. Enfermedades De Los Ni\u00d1os",
    "sg:phone":"+34 952 40 22 00",
    "sg:postcode":"29730",
    "sg:province":"M\u00e1laga",
    "wof:name":"Perez Fuentes Francisco De Asis",
    "wof:placetype":"venue"
},
  "geometry": {"coordinates":[-4.2733950615,36.7136116028],"type":"Point"}
}