{
  "type": "Feature",
  "properties": {
    "addr:full":"Avda Ana De Viya, 5 Cadiz C\u00e1diz 11009",
    "addr:housenumber":"5",
    "addr:postcode":"11009",
    "addr:street":"Avda Ana De Viya",
    "iso:country":"ES",
    "sg:address":"Avda Ana De Viya, 5",
    "sg:city":"Cadiz",
    "sg:orig_category":"Seguridad En El Trabajo Y Prevenci\u00d3n De Riesgos Laborales",
    "sg:phone":"+34 956 29 34 54",
    "sg:postcode":"11009",
    "sg:province":"C\u00e1diz",
    "wof:name":"Andalucia Prevencion De Riesgos Laborales S.l.",
    "wof:placetype":"venue"
},
  "geometry": {"coordinates":[-6.2800917625,36.5118942261],"type":"Point"}
}