{
  "type": "Feature",
  "properties": {
    "iso:country":"ES",
    "sg:address":"Calle de Castilla, S/n",
    "sg:city":"Caravaca Cruz",
    "sg:orig_category":"Electricidad (montaje, Ensamblaje De Componentes)",
    "sg:phone":"+34 968 70 77 82",
    "sg:postcode":"30400",
    "sg:province":"Murcia",
    "wof:name":"Marti Hurtado Roque",
    "wof:placetype":"venue"
},
  "geometry": {"coordinates":[-1.8590670824,38.1054725647],"type":"Point"}
}