{
  "type": "Feature",
  "properties": {
    "addr:full":"Calle de Alonso De Palencia, 16 Malaga M\u00e1laga 29007",
    "addr:housenumber":"16",
    "addr:postcode":"29007",
    "addr:street":"Calle De Alonso De Palencia;Ma\u0301Laga",
    "iso:country":"ES",
    "sg:address":"Calle de Alonso De Palencia, 16",
    "sg:city":"Malaga",
    "sg:orig_category":"Iglesias Evang\u00c9licas",
    "sg:phone":"+34 952 61 16 16",
    "sg:postcode":"29007",
    "sg:province":"M\u00e1laga",
    "wof:name":"Evangelismo En Accion",
    "wof:placetype":"venue"
},
  "geometry": {"coordinates":[-4.432697773,36.7206344604],"type":"Point"}
}