{
  "type": "Feature",
  "properties": {
    "iso:country":"ES",
    "sg:address":"Calle de Real, 56",
    "sg:city":"Badaran",
    "sg:orig_category":"Cajas De Ahorro",
    "sg:phone":"+34 941 36 70 63",
    "sg:postcode":"26310",
    "sg:province":"La Rioja",
    "wof:name":"Caja De Ahorros Y Monte De Piedad De Zaragoza Aragon Y Rioja",
    "wof:placetype":"venue"
},
  "geometry": {"coordinates":[-2.8082540035,42.3670158386],"type":"Point"}
}