{
  "type": "Feature",
  "properties": {
    "addr:full":"Calle de Torres Del Bierzo, 1 Fuenlabrada Madrid 28947",
    "addr:housenumber":"1",
    "addr:postcode":"28947",
    "addr:street":"Calle De Torres Del Bierzo",
    "iso:country":"ES",
    "sg:address":"Calle de Torres Del Bierzo, 1",
    "sg:city":"Fuenlabrada",
    "sg:orig_category":"Empresas De Carpinter\u00cda De Madera",
    "sg:phone":"+34 916 42 11 14",
    "sg:postcode":"28947",
    "sg:province":"Madrid",
    "wof:name":"Jaromol S. L.",
    "wof:placetype":"venue"
},
  "geometry": {"coordinates":[-3.748100996,40.2538223267],"type":"Point"}
}