{
  "type": "Feature",
  "properties": {
    "addr:full":"Avda Zaragoza, 29 Jaca Huesca 22700",
    "addr:housenumber":"29",
    "addr:postcode":"22700",
    "addr:street":"Avda Zaragoza",
    "iso:country":"ES",
    "sg:address":"Avda Zaragoza, 29",
    "sg:city":"Jaca",
    "sg:orig_category":"Empresas De Limpieza",
    "sg:phone":"+34 974 36 20 42",
    "sg:postcode":"22700",
    "sg:province":"Huesca",
    "wof:name":"Lorente Teruel Andres",
    "wof:placetype":"venue"
},
  "geometry": {"coordinates":[-0.5459480286,42.5748023987],"type":"Point"}
}