{
  "type": "Feature",
  "properties": {
    "addr:full":"Carrer de Sant Joan Bosco, 46 S. Boi Llobregat Barcelona 08830",
    "addr:housenumber":"46",
    "addr:postcode":"08830",
    "addr:street":"Carrer De Sant Joan Bosco",
    "iso:country":"ES",
    "sg:address":"Carrer de Sant Joan Bosco, 46",
    "sg:city":"S. Boi Llobregat",
    "sg:orig_category":"Molduras, Junquillos, Listones Y Molduras Perforadas",
    "sg:phone":"+34 936 54 13 12",
    "sg:postcode":"08830",
    "sg:province":"Barcelona",
    "wof:name":"Balsalobre Pe\u00f1alver Sebastian",
    "wof:placetype":"venue"
},
  "geometry": {"coordinates":[2.0455069542,41.3401832581],"type":"Point"}
}