{
  "type": "Feature",
  "properties": {
    "iso:country":"ES",
    "sg:address":"Calle de Museo De La Huerta, S/n",
    "sg:city":"Alcantarilla",
    "sg:orig_category":"M\u00c9dicos: Estomatolog\u00cda",
    "sg:phone":"+34 968 89 46 90",
    "sg:postcode":"30820",
    "sg:province":"Murcia",
    "wof:name":"Nicolas Silvente Ana Isabel",
    "wof:placetype":"venue"
},
  "geometry": {"coordinates":[-1.2146439552,37.9755249023],"type":"Point"}
}