{
  "type": "Feature",
  "properties": {
    "addr:full":"Calle de Feijoo, 99 Gijon Asturias 33204",
    "addr:housenumber":"99",
    "addr:postcode":"33204",
    "addr:street":"Calle De Feijoo",
    "iso:country":"ES",
    "sg:address":"Calle de Feijoo, 99",
    "sg:city":"Gijon",
    "sg:orig_category":"Plomeros",
    "sg:phone":"+34 985 37 33 26",
    "sg:postcode":"33204",
    "sg:province":"Asturias",
    "wof:name":"Medio Vi\u00f1a Andres Corsino",
    "wof:placetype":"venue"
},
  "geometry": {"coordinates":[-5.6465539932,43.5317497253],"type":"Point"}
}