{
  "type": "Feature",
  "properties": {
    "iso:country":"ES",
    "sg:address":"Calle de Cuesta, 4",
    "sg:city":"Consuegra",
    "sg:orig_category":"Panader\u00cdas, Pasteler\u00cdas, Boller\u00cda Industriale (fabricaci\u00d3n, Al Por Mayor)",
    "sg:phone":"+34 925 48 03 14",
    "sg:postcode":"45700",
    "sg:province":"Toledo",
    "wof:name":"Casta\u00f1eda Diaz-miguel Mariano",
    "wof:placetype":"venue"
},
  "geometry": {"coordinates":[-3.6038153172,39.4567909241],"type":"Point"}
}