{
  "type": "Feature",
  "properties": {
    "addr:full":"Avda Don Jose Garrido Farga, 33 Pobla Vallbona Valencia 46185",
    "addr:housenumber":"33",
    "addr:postcode":"46185",
    "addr:street":"Avda Don Jose Garrido Farga",
    "iso:country":"ES",
    "sg:address":"Avda Don Jose Garrido Farga, 33",
    "sg:city":"Pobla Vallbona",
    "sg:orig_category":"Aguas (distribuci\u00d3n, Servicios)",
    "sg:phone":"+34 962 76 03 69",
    "sg:postcode":"46185",
    "sg:province":"Valencia",
    "sg:website":"www.aquagestlevante.es/poblavallbona",
    "wof:name":"Aquagest Levante S.a.",
    "wof:placetype":"venue"
},
  "geometry": {"coordinates":[-0.5570746064,39.5908851624],"type":"Point"}
}