{
  "type": "Feature",
  "properties": {
    "addr:full":"Carrer de Cartella, 77 Barcelona Barcelona 08031",
    "addr:housenumber":"77",
    "addr:postcode":"08031",
    "addr:street":"Carrer De Cartella",
    "iso:country":"ES",
    "sg:address":"Carrer de Cartella, 77",
    "sg:city":"Barcelona",
    "sg:orig_category":"Estudios De Grabaci\u00d3n Sonora",
    "sg:phone":"+34 933 57 82 33",
    "sg:postcode":"08031",
    "sg:province":"Barcelona",
    "wof:name":"Digit Sound",
    "wof:placetype":"venue"
},
  "geometry": {"coordinates":[2.1717760563,41.4278755188],"type":"Point"}
}