{
  "type": "Feature",
  "properties": {
    "addr:full":"Calle de Sierra De Los Filabres, S/n Viator Almer\u00eda 04240",
    "addr:housenumber":"s / n",
    "addr:postcode":"04240",
    "addr:street":"Calle De Sierra De Los Filabres;Almeri\u0301A",
    "iso:country":"ES",
    "sg:address":"Calle de Sierra De Los Filabres, S/n",
    "sg:city":"Viator",
    "sg:orig_category":"Centros Empresariales",
    "sg:phone":"+34 950 30 44 77",
    "sg:postcode":"04240",
    "sg:province":"Almer\u00eda",
    "wof:name":"Dronas 2002 S.l.",
    "wof:placetype":"venue"
},
  "geometry": {"coordinates":[-2.419508934,36.8793983459],"type":"Point"}
}