{
  "type": "Feature",
  "properties": {
    "addr:full":"Rua Taxonera, 23 Ferrol La Coru\u00f1a 15403",
    "addr:housenumber":"23",
    "addr:postcode":"15403",
    "addr:street":"Rua Taxonera;La Corun\u0303A",
    "iso:country":"ES",
    "sg:address":"Rua Taxonera, 23",
    "sg:city":"Ferrol",
    "sg:classifiers":[
        {
            "category":"Food & Beverages",
            "subcategory":"Candy",
            "type":"Retail Goods"
        }
    ],
    "sg:phone":"+34 981 35 55 35",
    "sg:postcode":"15403",
    "sg:province":"La Coru\u00f1a",
    "sg:tags":[
        "confiter\u00cdas",
        "y",
        "de",
        "fabricaci\u00d3n",
        "chocolate"
    ],
    "wof:name":"Distribuciones Camba S.l.",
    "wof:placetype":"venue"
},
  "geometry": {"coordinates":[-8.2282800674,43.4818992615],"type":"Point"}
}