{
  "type": "Feature",
  "properties": {
    "iso:country":"ES",
    "sg:address":"Calle de San Isidro, 2",
    "sg:city":"Monzon",
    "sg:classifiers":[
        {
            "category":"Communications",
            "type":"Services"
        }
    ],
    "sg:phone":"+34 974 41 61 93",
    "sg:postcode":"22400",
    "sg:province":"Huesca",
    "sg:tags":[
        "televisiones",
        "y",
        "radio"
    ],
    "wof:name":"Radio Monzon S.a.",
    "wof:placetype":"venue"
},
  "geometry": {"coordinates":[0.1862950027,41.9160003662],"type":"Point"}
}