{
  "type": "Feature",
  "properties": {
    "addr:full":"Pase Zorrilla, 32 Valladolid Valladolid 47006",
    "addr:housenumber":"32",
    "addr:postcode":"47006",
    "addr:street":"Zorrilla",
    "iso:country":"ES",
    "sg:address":"Pase Zorrilla, 32",
    "sg:city":"Valladolid",
    "sg:orig_category":"Loter\u00cda Y T\u00d3mbola",
    "sg:phone":"+34 983 37 85 67",
    "sg:postcode":"47006",
    "sg:province":"Valladolid",
    "wof:name":"Navas Vela Amparo",
    "wof:placetype":"venue"
},
  "geometry": {"coordinates":[-4.7335910797,41.6455192566],"type":"Point"}
}