{
  "type": "Feature",
  "properties": {
    "iso:country":"ES",
    "sg:address":"Pla\u00c7 Maria Aurelia Capmany, 4",
    "sg:city":"Lleida",
    "sg:orig_category":"Televisi\u00d3n, V\u00cddeo: Aparatos Y Accesorios (venta)",
    "sg:phone":"+34 973 23 31 72",
    "sg:postcode":"25005",
    "sg:province":"Lleida",
    "wof:name":"Acustielec S.l.",
    "wof:placetype":"venue"
},
  "geometry": {"coordinates":[0.6322615147,41.6268920898],"type":"Point"}
}