{
  "type": "Feature",
  "properties": {
    "addr:full":"Pol Ind Ganadero, S/n Caceres C\u00e1ceres 10004",
    "addr:housenumber":"s / n",
    "addr:postcode":"10004",
    "addr:street":"Ca\u0301Ceres",
    "iso:country":"ES",
    "sg:address":"Pol Ind Ganadero, S/n",
    "sg:city":"Caceres",
    "sg:orig_category":"Cr\u00cda De Corderos Y De Cabras",
    "sg:phone":"+34 927 18 15 64",
    "sg:postcode":"10004",
    "sg:province":"C\u00e1ceres",
    "wof:name":"Palomino Manzano Fernando",
    "wof:placetype":"venue"
},
  "geometry": {"coordinates":[-6.3583831787,39.5027656555],"type":"Point"}
}