{
  "type": "Feature",
  "properties": {
    "addr:full":"Carr Fira De La Ceramica I Vidre, S/n Quart Poblet Valencia 46930",
    "addr:postcode":"46930",
    "addr:street":"Carr Fira De La Ceramica;Vidre S / N;Poblet",
    "iso:country":"ES",
    "sg:address":"Carr Fira De La Ceramica I Vidre, S/n",
    "sg:city":"Quart Poblet",
    "sg:orig_category":"Negocio De Materiales De Construcci\u00d3n",
    "sg:phone":"+34 961 54 96 99",
    "sg:postcode":"46930",
    "sg:province":"Valencia",
    "wof:name":"Jofiba S. A.",
    "wof:placetype":"venue"
},
  "geometry": {"coordinates":[-0.4419890046,39.482711792],"type":"Point"}
}