{
  "type": "Feature",
  "properties": {
    "iso:country":"ES",
    "sg:address":"Plaz Coso, 2",
    "sg:city":"Villarrubio",
    "sg:orig_category":"Ropa Para Se\u00d1oras Y Caballeros (al Por Menor)",
    "sg:phone":"+34 969 13 51 62",
    "sg:postcode":"16420",
    "sg:province":"Cuenca",
    "wof:name":"Amaya Aparicio Gema",
    "wof:placetype":"venue"
},
  "geometry": {"coordinates":[-2.8944220543,39.9453544617],"type":"Point"}
}