{
  "type": "Feature",
  "properties": {
    "addr:full":"Calle de Leon Y Castillo, 13 Arucas Las Palmas 35400",
    "addr:housenumber":"13",
    "addr:postcode":"35400",
    "addr:street":"Calle De Leon Y Castillo",
    "iso:country":"ES",
    "sg:address":"Calle de Leon Y Castillo, 13",
    "sg:city":"Arucas",
    "sg:orig_category":"\u00d3ptica: Instrumentos (fabricaci\u00d3n)",
    "sg:phone":"+34 928 60 18 87",
    "sg:postcode":"35400",
    "sg:province":"Las Palmas",
    "wof:name":"Centro Optico De Arucas S.l.",
    "wof:placetype":"venue"
},
  "geometry": {"coordinates":[-15.5240955353,28.1186199188],"type":"Point"}
}