{
  "type": "Feature",
  "properties": {
    "addr:full":"Rua Ramon Cabanillas, 10 Ourense Ourense 32004",
    "addr:housenumber":"10",
    "addr:postcode":"32004",
    "addr:street":"Rua Ramon Cabanillas",
    "iso:country":"ES",
    "sg:address":"Rua Ramon Cabanillas, 10",
    "sg:city":"Ourense",
    "sg:orig_category":"Arquitectos",
    "sg:phone":"+34 988 22 55 27",
    "sg:postcode":"32004",
    "sg:province":"Ourense",
    "wof:name":"Blanco Pi\u00f1eiro Maria Jesus",
    "wof:placetype":"venue"
},
  "geometry": {"coordinates":[-7.8606038094,42.3406562805],"type":"Point"}
}