{
  "type": "Feature",
  "properties": {
    "addr:full":"Carrer de Abat Oliba, 38 Manresa Barcelona 08242",
    "addr:housenumber":"38",
    "addr:postcode":"08242",
    "addr:street":"Carrer De Abat Oliba",
    "iso:country":"ES",
    "sg:address":"Carrer de Abat Oliba, 38",
    "sg:city":"Manresa",
    "sg:orig_category":"Perfumer\u00cda (al Por Menor)",
    "sg:phone":"+34 938 74 62 53",
    "sg:postcode":"08242",
    "sg:province":"Barcelona",
    "wof:name":"Bondia Serrat Victoria",
    "wof:placetype":"venue"
},
  "geometry": {"coordinates":[1.8288300037,41.733631134],"type":"Point"}
}