{
  "type": "Feature",
  "properties": {
    "iso:country":"ES",
    "sg:address":"Carrer de Marques Fontsanta, 42",
    "sg:city":"Palma",
    "sg:orig_category":"Complementos De Vestir (al Por Menor)",
    "sg:phone":"+34 971 77 02 84",
    "sg:postcode":"07005",
    "sg:province":"Islas Baleares",
    "wof:name":"Inversiones Xanamar S.l.",
    "wof:placetype":"venue"
},
  "geometry": {"coordinates":[2.6582159996,39.5778427124],"type":"Point"}
}