{
  "type": "Feature",
  "properties": {
    "iso:country":"ES",
    "sg:address":"Praz Mercedes (das), 1",
    "sg:city":"Ourense",
    "sg:orig_category":"Carnicer\u00cdas, Carnicer\u00cdas",
    "sg:phone":"+34 988 23 59 08",
    "sg:postcode":"32004",
    "sg:province":"Ourense",
    "wof:name":"Masid Rodriguez Emilio",
    "wof:placetype":"venue"
},
  "geometry": {"coordinates":[-7.8340759277,42.3372802734],"type":"Point"}
}