{
  "type": "Feature",
  "properties": {
    "addr:full":"Trav. La Nozaleda, 14 La Pola Asturias 33630",
    "addr:housenumber":"14",
    "addr:postcode":"33630",
    "addr:street":"Trav. La Nozaleda",
    "iso:country":"ES",
    "sg:address":"Trav. La Nozaleda, 14",
    "sg:city":"La Pola",
    "sg:orig_category":"Bebidas",
    "sg:phone":"+34 985 49 05 57",
    "sg:postcode":"33630",
    "sg:province":"Asturias",
    "wof:name":"Diez Tascon Justo",
    "wof:placetype":"venue"
},
  "geometry": {"coordinates":[-5.8293089867,43.1562805176],"type":"Point"}
}