{
  "type": "Feature",
  "properties": {
    "addr:full":"Calle de Cuba, 14 Aviles Asturias 33401",
    "addr:housenumber":"14",
    "addr:postcode":"33401",
    "addr:street":"Calle De Cuba",
    "iso:country":"ES",
    "sg:address":"Calle de Cuba, 14",
    "sg:city":"Aviles",
    "sg:orig_category":"M\u00c9dicos: Estomatolog\u00cda",
    "sg:phone":"+34 985 56 93 18",
    "sg:postcode":"33401",
    "sg:province":"Asturias",
    "wof:name":"Gonzalez Rodriguez Clemente",
    "wof:placetype":"venue"
},
  "geometry": {"coordinates":[-5.926856041,43.5572662354],"type":"Point"}
}