{
  "type": "Feature",
  "properties": {
    "iso:country":"ES",
    "sg:address":"Carrer de Consell De Cent, 217",
    "sg:city":"Barcelona",
    "sg:orig_category":"Importaci\u00d3n",
    "sg:phone":"+34 933 23 05 85",
    "sg:postcode":"08011",
    "sg:province":"Barcelona",
    "wof:name":"Aragones Forner Rafael Angel",
    "wof:placetype":"venue"
},
  "geometry": {"coordinates":[2.1576793194,41.3850746155],"type":"Point"}
}