{
  "type": "Feature",
  "properties": {
    "iso:country":"ES",
    "sg:address":"Dr. J. Codina, 48",
    "sg:city":"Cellera Ter",
    "sg:orig_category":"Confiter\u00cda, Galletas Y Pastas, Chocolater\u00cda (al Por Mayor)",
    "sg:phone":"+34 972 42 14 61",
    "sg:postcode":"17165",
    "sg:province":"Girona",
    "wof:name":"Vila Trafach Josep",
    "wof:placetype":"venue"
},
  "geometry": {"coordinates":[2.6213889122,41.9697608948],"type":"Point"}
}