{
  "type": "Feature",
  "properties": {
    "addr:full":"Calle de Cirilo Moreno, 64 Palmas De Gran Canaria Las Palmas 35007",
    "addr:postcode":"35007",
    "addr:street":"Calle De Cirilo Moreno 64",
    "iso:country":"ES",
    "sg:address":"Calle de Cirilo Moreno, 64",
    "sg:city":"Palmas De Gran Canaria",
    "sg:orig_category":"Agencias Y Agentes Comerciales, Representantes",
    "sg:phone":"+34 928 27 26 79",
    "sg:postcode":"35007",
    "sg:province":"Las Palmas",
    "wof:name":"Marrero Rodriguez Juan",
    "wof:placetype":"venue"
},
  "geometry": {"coordinates":[-15.4335794449,28.1367435455],"type":"Point"}
}