{
  "type": "Feature",
  "properties": {
    "iso:country":"ES",
    "sg:address":"Autop Sevilla-huelva, Km. 0027,0",
    "sg:city":"Carrion Cespedes",
    "sg:orig_category":"Productos Fitosanitarios (negocio, Aplicaci\u00d3n)",
    "sg:phone":"+34 954 75 51 30",
    "sg:postcode":"41820",
    "sg:province":"Sevilla",
    "sg:website":"www.fitotrans.com",
    "wof:name":"Fito Trans S.a.",
    "wof:placetype":"venue"
},
  "geometry": {"coordinates":[-6.3294568062,37.3691368103],"type":"Point"}
}