{
  "type": "Feature",
  "properties": {
    "addr:full":"Cno Naranjales, S/n Sanlucar Mayor Sevilla 41800",
    "addr:housenumber":"s / n",
    "addr:postcode":"41800",
    "addr:street":"Cno Naranjales",
    "iso:country":"ES",
    "sg:address":"Cno Naranjales, S/n",
    "sg:city":"Sanlucar Mayor",
    "sg:orig_category":"Producci\u00d3n, Venta De Productos De Agricultura Biol\u00d3gica",
    "sg:phone":"+34 955 70 03 89",
    "sg:postcode":"41800",
    "sg:province":"Sevilla",
    "wof:name":"El Romeral S.cv.",
    "wof:placetype":"venue"
},
  "geometry": {"coordinates":[-6.1956338882,37.3855361938],"type":"Point"}
}