{
  "type": "Feature",
  "properties": {
    "iso:country":"ES",
    "sg:address":"Laranxeiras(rebordans), 25",
    "sg:city":"Naranjeiras",
    "sg:orig_category":"Ambulancias",
    "sg:phone":"+34 986 60 05 36",
    "sg:postcode":"36712",
    "sg:province":"Pontevedra",
    "wof:name":"Ambulancias De Tuy S.l.",
    "wof:placetype":"venue"
},
  "geometry": {"coordinates":[-8.6480531693,42.4336204529],"type":"Point"}
}