{
  "type": "Feature",
  "properties": {
    "iso:country":"ES",
    "sg:address":"Calle de Javier Barkaiztegi, 9",
    "sg:city":"Donostia-san Sebastian",
    "sg:orig_category":"Trabajos De Soldaduras",
    "sg:phone":"+34 943 45 97 82",
    "sg:postcode":"20010",
    "sg:province":"Guip\u00f9zcoa",
    "wof:name":"Kempomat S.l.",
    "wof:placetype":"venue"
},
  "geometry": {"coordinates":[-1.9811359644,43.3056564331],"type":"Point"}
}