{
  "type": "Feature",
  "properties": {
    "addr:full":"Calle de San Pascual, 47 Yecla Murcia 30510",
    "addr:housenumber":"47",
    "addr:postcode":"30510",
    "addr:street":"Calle De San Pascual",
    "iso:country":"ES",
    "sg:address":"Calle de San Pascual, 47",
    "sg:city":"Yecla",
    "sg:orig_category":"Asesor\u00cda De Formaci\u00d3n Y Gesti\u00d3n De Personal",
    "sg:phone":"+34 968 71 86 11",
    "sg:postcode":"30510",
    "sg:province":"Murcia",
    "wof:name":"Lido Rico Asesores S.l.",
    "wof:placetype":"venue"
},
  "geometry": {"coordinates":[-1.1118170023,38.6136322021],"type":"Point"}
}