{
  "type": "Feature",
  "properties": {
    "addr:full":"Fray M De Arandiga, 9 Montesa Valencia 46692",
    "addr:housenumber":"9",
    "addr:postcode":"46692",
    "addr:street":"Fray M De Arandiga",
    "iso:country":"ES",
    "sg:address":"Fray M De Arandiga, 9",
    "sg:city":"Montesa",
    "sg:orig_category":"Empresarios",
    "sg:phone":"+34 962 29 92 12",
    "sg:postcode":"46692",
    "sg:province":"Valencia",
    "wof:name":"Monton Obras En General S.l.",
    "wof:placetype":"venue"
},
  "geometry": {"coordinates":[-0.650593996,38.9492149353],"type":"Point"}
}