{
  "type": "Feature",
  "properties": {
    "iso:country":"ES",
    "sg:address":"Carr Ribarroja, 11",
    "sg:city":"Manises",
    "sg:orig_category":"Florister\u00cdas",
    "sg:phone":"+34 961 52 48 67",
    "sg:postcode":"46940",
    "sg:province":"Valencia",
    "wof:name":"Gonzalez Garcia Jose Miguel",
    "wof:placetype":"venue"
},
  "geometry": {"coordinates":[-0.4604539871,39.4918670654],"type":"Point"}
}