{
  "type": "Feature",
  "properties": {
    "iso:country":"ES",
    "sg:address":"Calle de Escarcha (de La), 6",
    "sg:city":"Tres Cantos",
    "sg:orig_category":"Agencias Y Agentes Comerciales, Representantes",
    "sg:phone":"+34 918 03 33 65",
    "sg:postcode":"28760",
    "sg:province":"Madrid",
    "wof:name":"Martinez-trece\u00f1o Gutierrez Fernando",
    "wof:placetype":"venue"
},
  "geometry": {"coordinates":[-3.7126789093,40.5984687805],"type":"Point"}
}