{
  "type": "Feature",
  "properties": {
    "iso:country":"ES",
    "sg:address":"Calle de Faro, S/n",
    "sg:city":"Roquetas Mar",
    "sg:orig_category":"Comercio, Reparaci\u00d3n De Bicicletas, De Motocicletas, De Accesorios",
    "sg:phone":"+34 950 33 80 22",
    "sg:postcode":"04740",
    "sg:province":"Almer\u00eda",
    "wof:name":"Padilla Baldovin Antonio",
    "wof:placetype":"venue"
},
  "geometry": {"coordinates":[-2.6077439785,36.7552986145],"type":"Point"}
}