{
  "type": "Feature",
  "properties": {
    "addr:full":"Carrer de Gurb, 103 Vic Barcelona 08500",
    "addr:housenumber":"103",
    "addr:postcode":"08500",
    "addr:street":"Carrer De Gurb",
    "iso:country":"ES",
    "sg:address":"Carrer de Gurb, 103",
    "sg:city":"Vic",
    "sg:orig_category":"Artes Gr\u00c1ficas, Artes Pl\u00c1sticas (curso)",
    "sg:phone":"+34 938 83 33 42",
    "sg:postcode":"08500",
    "sg:province":"Barcelona",
    "wof:name":"Admira Scp",
    "wof:placetype":"venue"
},
  "geometry": {"coordinates":[2.2509181499,41.9335365295],"type":"Point"}
}