{
  "type": "Feature",
  "properties": {
    "iso:country":"ES",
    "sg:address":"Calle de Fuentes (las), 3",
    "sg:city":"Bembibre",
    "sg:orig_category":"Carb\u00d3n, Carb\u00d3n De Madera (al Por Mayor)",
    "sg:phone":"+34 987 51 03 98",
    "sg:postcode":"24300",
    "sg:province":"Le\u00f3n",
    "wof:name":"Castro Mendez Mombars",
    "wof:placetype":"venue"
},
  "geometry": {"coordinates":[-6.4179677963,42.6125030518],"type":"Point"}
}