{
  "type": "Feature",
  "properties": {
    "addr:full":"Pol Ind El Oliveral, 2 P. I. El Oliveral Valencia 46190",
    "addr:housenumber":"2",
    "addr:postcode":"46190",
    "addr:street":"Oliveral;P. I. El Oliveral",
    "iso:country":"ES",
    "sg:address":"Pol Ind El Oliveral, 2",
    "sg:city":"P. I. El Oliveral",
    "sg:orig_category":"Fabricaci\u00d3n, Distribuci\u00d3n De Material Para La Climatizaci\u00d3n, Aireaci\u00d3n Y Ventilaci\u00d3n",
    "sg:phone":"+34 961 66 53 86",
    "sg:postcode":"46190",
    "sg:province":"Valencia",
    "sg:website":"www.tecnorojas.com",
    "wof:name":"Rojas Jimenez David",
    "wof:placetype":"venue"
},
  "geometry": {"coordinates":[-0.5698940158,39.5458450317],"type":"Point"}
}