{
  "type": "Feature",
  "properties": {
    "iso:country":"ES",
    "sg:address":"Ctra Sevilla-huelva, 28",
    "sg:city":"Espartinas",
    "sg:orig_category":"Abogados",
    "sg:phone":"+34 954 71 42 77",
    "sg:postcode":"41807",
    "sg:province":"Sevilla",
    "wof:name":"Costa Luz Abogados S.l.",
    "wof:placetype":"venue"
},
  "geometry": {"coordinates":[-6.1235818863,37.3828926086],"type":"Point"}
}