{
  "type": "Feature",
  "properties": {
    "iso:country":"ES",
    "sg:address":"Matsaria Kalea, 10",
    "sg:city":"Eibar",
    "sg:orig_category":"Cromado Y Niquelado",
    "sg:phone":"+34 943 20 18 52",
    "sg:postcode":"20600",
    "sg:province":"Guip\u00f9zcoa",
    "wof:name":"Aplicaciones Industriales De Cromo Duro S. A.",
    "wof:placetype":"venue"
},
  "geometry": {"coordinates":[-2.4665820599,43.1894493103],"type":"Point"}
}