{
  "type": "Feature",
  "properties": {
    "addr:full":"Calle de Gravina, 40 Palmas De Gran Canaria Las Palmas 35010",
    "addr:housenumber":"40",
    "addr:postcode":"35010",
    "addr:street":"Calle De Gravina",
    "iso:country":"ES",
    "sg:address":"Calle de Gravina, 40",
    "sg:city":"Palmas De Gran Canaria",
    "sg:orig_category":"Importaci\u00d3n",
    "sg:phone":"+34 928 22 68 67",
    "sg:postcode":"35010",
    "sg:province":"Las Palmas",
    "wof:name":"Grupo Ramchand Tejumal Aswani S.l.",
    "wof:placetype":"venue"
},
  "geometry": {"coordinates":[-15.4386472702,28.133890152],"type":"Point"}
}