{
  "type": "Feature",
  "properties": {
    "iso:country":"ES",
    "sg:address":"Nou D'octubre, 14",
    "sg:city":"Benimodo",
    "sg:orig_category":"M\u00dasica Diversa",
    "sg:phone":"+34 962 53 00 81",
    "sg:postcode":"46291",
    "sg:province":"Valencia",
    "wof:name":"Unio Musical De Benimodo",
    "wof:placetype":"venue"
},
  "geometry": {"coordinates":[-0.526835978,39.2148094177],"type":"Point"}
}