{
  "type": "Feature",
  "properties": {
    "iso:country":"ES",
    "sg:address":"Calle de Eskutxi, 1",
    "sg:city":"Llodio",
    "sg:orig_category":"Empresas De Pintura Y Revestimientos",
    "sg:phone":"+34 946 72 28 65",
    "sg:postcode":"01400",
    "sg:province":"\u00c1lava",
    "wof:name":"Curras Lopez Concepcion",
    "wof:placetype":"venue"
},
  "geometry": {"coordinates":[-2.9598610401,43.1409568787],"type":"Point"}
}