{
  "type": "Feature",
  "properties": {
    "iso:country":"ES",
    "sg:address":"Calle de Astilleros, General, 49",
    "sg:city":"Melilla",
    "sg:orig_category":"Alimentaci\u00d3n General (al Por Menor)",
    "sg:phone":"+34 952 67 50 73",
    "sg:postcode":"52006",
    "sg:province":"Melilla",
    "wof:name":"Aissa Mohamed Dris",
    "wof:placetype":"venue"
},
  "geometry": {"coordinates":[-2.9372193813,35.2751197815],"type":"Point"}
}