{
  "type": "Feature",
  "properties": {
    "iso:country":"ES",
    "sg:address":"Calle de Zorzale\u00d1a, 11",
    "sg:city":"Castilleja Cuesta",
    "sg:orig_category":"Agencias Y Agentes Comerciales, Representantes",
    "sg:phone":"+34 954 16 06 74",
    "sg:postcode":"41950",
    "sg:province":"Sevilla",
    "wof:name":"Lancharro Escudero Fernando",
    "wof:placetype":"venue"
},
  "geometry": {"coordinates":[-6.0483999252,37.3900146484],"type":"Point"}
}