{
  "type": "Feature",
  "properties": {
    "iso:country":"ES",
    "sg:address":"Calle de Compa\u00d1ia De Maria, 8",
    "sg:city":"Jerez De La Frontera",
    "sg:orig_category":"Ense\u00d1anza: Idiomas",
    "sg:phone":"+34 956 34 95 92",
    "sg:postcode":"11402",
    "sg:province":"C\u00e1diz",
    "wof:name":"Peri\u00f1an Huelva Maria Del Carmen",
    "wof:placetype":"venue"
},
  "geometry": {"coordinates":[-6.1343741417,36.6875572205],"type":"Point"}
}