{
  "type": "Feature",
  "properties": {
    "addr:full":"Calle de Eras Altas, 18 Retuerta Bullaque Ciudad Real 13194",
    "addr:housenumber":"18",
    "addr:postcode":"bullaque;13194",
    "addr:street":"Calle De Eras Altas",
    "iso:country":"ES",
    "sg:address":"Calle de Eras Altas, 18",
    "sg:city":"Retuerta Bullaque",
    "sg:orig_category":"Materiales De Construcci\u00d3n (en General)",
    "sg:phone":"+34 925 42 18 66",
    "sg:postcode":"13194",
    "sg:province":"Ciudad Real",
    "wof:name":"Suministros Yoe S.l.",
    "wof:placetype":"venue"
},
  "geometry": {"coordinates":[-4.414785862,39.4628067017],"type":"Point"}
}