{
  "type": "Feature",
  "properties": {
    "iso:country":"ES",
    "sg:address":"Plaz Altozano (del), 9",
    "sg:city":"Utrera",
    "sg:orig_category":"Asesor\u00cdas Y Estudios Financieros",
    "sg:phone":"+34 954 86 36 72",
    "sg:postcode":"41710",
    "sg:province":"Sevilla",
    "wof:name":"Efyc S.l.",
    "wof:placetype":"venue"
},
  "geometry": {"coordinates":[-5.779173851,37.184223175],"type":"Point"}
}