{
  "type": "Feature",
  "properties": {
    "iso:country":"ES",
    "sg:address":"Carrer de Bassegoda, 48",
    "sg:city":"Barcelona",
    "sg:orig_category":"Pescader\u00cdas (al Por Menor)",
    "sg:phone":"+34 933 33 65 25",
    "sg:postcode":"08028",
    "sg:province":"Barcelona",
    "wof:name":"Falco Carneiro S.l.",
    "wof:placetype":"venue"
},
  "geometry": {"coordinates":[2.1242229939,41.3745079041],"type":"Point"}
}