{
  "type": "Feature",
  "properties": {
    "addr:full":"Pase Tomas Morales, 95 Palmas De Gran Canaria Las Palmas 35004",
    "addr:postcode":"35004",
    "addr:street":"Tomas Morales 95",
    "iso:country":"ES",
    "sg:address":"Pase Tomas Morales, 95",
    "sg:city":"Palmas De Gran Canaria",
    "sg:orig_category":"M\u00c9dicos: Dermatolog\u00cda Y Venereolog\u00cda",
    "sg:phone":"+34 928 24 28 00",
    "sg:postcode":"35004",
    "sg:province":"Las Palmas",
    "wof:name":"Trujillo Cubas Leandra",
    "wof:placetype":"venue"
},
  "geometry": {"coordinates":[-15.4265050888,28.1168994904],"type":"Point"}
}