{
  "type": "Feature",
  "properties": {
    "addr:full":"Calle de Gervasio Ramos, 2 Langreo Asturias 33900",
    "addr:housenumber":"2",
    "addr:postcode":"33900",
    "addr:street":"Calle De Gervasio Ramos",
    "iso:country":"ES",
    "sg:address":"Calle de Gervasio Ramos, 2",
    "sg:city":"Langreo",
    "sg:orig_category":"Lencer\u00cda Femenina, Corseter\u00cda, Trajes De Ba\u00d1o (al Por Menor)",
    "sg:phone":"+34 985 67 32 12",
    "sg:postcode":"33900",
    "sg:province":"Asturias",
    "wof:name":"Laura Comunidad De Bienes",
    "wof:placetype":"venue"
},
  "geometry": {"coordinates":[-5.682844162,43.2939872742],"type":"Point"}
}