{
  "type": "Feature",
  "properties": {
    "iso:country":"ES",
    "sg:address":"C/ Formentor, 91",
    "sg:city":"Inca",
    "sg:orig_category":"Carnicer\u00cdas, Carnicer\u00cdas",
    "sg:phone":"+34 971 50 56 46",
    "sg:postcode":"07300",
    "sg:province":"Islas Baleares",
    "wof:name":"Perello Molinas Gabriel",
    "wof:placetype":"venue"
},
  "geometry": {"coordinates":[2.9151139259,39.723991394],"type":"Point"}
}