{
  "type": "Feature",
  "properties": {
    "iso:country":"ES",
    "sg:address":"Av Ramon I Cajal, 62",
    "sg:city":"Tarragona",
    "sg:orig_category":"Partidos Pol\u00cdticos",
    "sg:phone":"+34 977 21 88 69",
    "sg:postcode":"43005",
    "sg:province":"Tarragona",
    "wof:name":"Esquerra Unida I Alternativa",
    "wof:placetype":"venue"
},
  "geometry": {"coordinates":[1.2433300018,41.1159324646],"type":"Point"}
}