{
  "type": "Feature",
  "properties": {
    "iso:country":"ES",
    "sg:address":"Calle de Pradillo, 19",
    "sg:city":"Madrid",
    "sg:orig_category":"Arquitectos",
    "sg:phone":"+34 915 61 44 45",
    "sg:postcode":"28002",
    "sg:province":"Madrid",
    "wof:name":"Cilindro Virtual S.l.",
    "wof:placetype":"venue"
},
  "geometry": {"coordinates":[-3.6741430759,40.448802948],"type":"Point"}
}