{
  "type": "Feature",
  "properties": {
    "addr:full":"Calle de Andia, 13 Donostia-san Sebastian Guip\u00f9zcoa 20004",
    "addr:housenumber":"13",
    "addr:postcode":"20004",
    "addr:street":"Calle De Andia",
    "iso:country":"ES",
    "sg:address":"Calle de Andia, 13",
    "sg:city":"Donostia-san Sebastian",
    "sg:orig_category":"Administraciones Regionales, Departamentales Y Locales",
    "sg:phone":"+34 943 02 28 10",
    "sg:postcode":"20004",
    "sg:province":"Guip\u00f9zcoa",
    "wof:name":"Eusko Jaurlaritza - Gobierno Vasco",
    "wof:placetype":"venue"
},
  "geometry": {"coordinates":[-1.9831508398,43.3202171326],"type":"Point"}
}