{
  "type": "Feature",
  "properties": {
    "iso:country":"ES",
    "sg:address":"Carrer de Llorer, 10",
    "sg:city":"Barcelona",
    "sg:orig_category":"Edici\u00d3n De Diarios, Revistas, Boletines",
    "sg:phone":"+34 932 85 02 20",
    "sg:postcode":"08024",
    "sg:province":"Barcelona",
    "sg:website":"www.informtex.com",
    "wof:name":"Gimferrer Baque Jose",
    "wof:placetype":"venue"
},
  "geometry": {"coordinates":[2.1588308811,41.4093208313],"type":"Point"}
}