{
  "type": "Feature",
  "properties": {
    "addr:full":"Cabezo Beaza, S/n Cartagena Murcia 30395",
    "addr:housenumber":"s / n",
    "addr:postcode":"30395",
    "iso:country":"ES",
    "sg:address":"Cabezo Beaza, S/n",
    "sg:city":"Cartagena",
    "sg:orig_category":"Artes Gr\u00c1ficas, Artes Pl\u00c1sticas: Material Y Suministros (al Por Menor)",
    "sg:phone":"+34 968 12 02 31",
    "sg:postcode":"30395",
    "sg:province":"Murcia",
    "wof:name":"Autonaval Rent S.l.",
    "wof:placetype":"venue"
},
  "geometry": {"coordinates":[-0.9499999881,37.6333351135],"type":"Point"}
}