{
  "type": "Feature",
  "properties": {
    "addr:full":"Calle de Puerto De Piedrafita, 10 Sevilla Sevilla 41006",
    "addr:housenumber":"10",
    "addr:postcode":"41006",
    "addr:street":"Calle De Puerto De Piedrafita",
    "iso:country":"ES",
    "sg:address":"Calle de Puerto De Piedrafita, 10",
    "sg:city":"Sevilla",
    "sg:orig_category":"M\u00c1rmoles, Granitos Y Piedras Naturales",
    "sg:phone":"+34 954 63 96 43",
    "sg:postcode":"41006",
    "sg:province":"Sevilla",
    "wof:name":"Cardenas Molina Francisco Javier",
    "wof:placetype":"venue"
},
  "geometry": {"coordinates":[-5.9538531303,37.3724784851],"type":"Point"}
}