{
  "type": "Feature",
  "properties": {
    "iso:country":"ES",
    "sg:address":"Calle de Pascual Canovas, 43",
    "sg:city":"Albatera",
    "sg:orig_category":"Empresas De Electricidad En General",
    "sg:phone":"+34 965 48 53 80",
    "sg:postcode":"03340",
    "sg:province":"Alicante",
    "wof:name":"Cooperativa Electrica Albaterense",
    "wof:placetype":"venue"
},
  "geometry": {"coordinates":[-0.8702210188,38.1765899658],"type":"Point"}
}