{
  "type": "Feature",
  "properties": {
    "addr:full":"Loiolako Inazio Hiribidea, 6 Azpeitia Guip\u00f9zcoa 20730",
    "addr:housenumber":"6",
    "addr:postcode":"20730",
    "addr:street":"Loiolako Inazio Hiribidea;Guipu\u0300Zcoa",
    "iso:country":"ES",
    "sg:address":"Loiolako Inazio Hiribidea, 6",
    "sg:city":"Azpeitia",
    "sg:orig_category":"Caf\u00c9s, Bares, Cervecer\u00cdas",
    "sg:phone":"+34 943 81 38 01",
    "sg:postcode":"20730",
    "sg:province":"Guip\u00f9zcoa",
    "wof:name":"Aliur Kafetegia",
    "wof:placetype":"venue"
},
  "geometry": {"coordinates":[-2.2702019215,43.1810836792],"type":"Point"}
}