{
  "type": "Feature",
  "properties": {
    "iso:country":"ES",
    "sg:address":"Ctra Torrejon (de), Km. 0000,3",
    "sg:city":"Ajalvir",
    "sg:orig_category":"Construcciones Met\u00c1licas",
    "sg:phone":"+34 918 84 40 05",
    "sg:postcode":"28864",
    "sg:province":"Madrid",
    "wof:name":"Verdugo Rodriguez Lucia",
    "wof:placetype":"venue"
},
  "geometry": {"coordinates":[-3.4812059402,40.5271034241],"type":"Point"}
}