{
  "type": "Feature",
  "properties": {
    "addr:full":"Av Catalunya, 76 S. Feliu Guixols Girona 17220",
    "addr:housenumber":"76",
    "addr:postcode":"17220",
    "addr:street":"Av Catalunya;S. Feliu Guixols",
    "iso:country":"ES",
    "sg:address":"Av Catalunya, 76",
    "sg:city":"S. Feliu Guixols",
    "sg:orig_category":"Alimentaci\u00d3n General (al Por Menor)",
    "sg:phone":"+34 972 32 16 89",
    "sg:postcode":"17220",
    "sg:province":"Girona",
    "wof:name":"Exposito Garcia Yolanda",
    "wof:placetype":"venue"
},
  "geometry": {"coordinates":[3.0378599167,41.7843742371],"type":"Point"}
}