{
  "type": "Feature",
  "properties": {
    "addr:full":"Calle de Manzanares, 26 Madrid Madrid 28005",
    "addr:housenumber":"26",
    "addr:postcode":"madrid;28005",
    "addr:street":"Calle De Manzanares",
    "iso:country":"ES",
    "sg:address":"Calle de Manzanares, 26",
    "sg:city":"Madrid",
    "sg:orig_category":"Fotograf\u00cda Y Cine: Material (reparaci\u00d3n)",
    "sg:phone":"+34 913 66 24 50",
    "sg:postcode":"28005",
    "sg:province":"Madrid",
    "wof:name":"Centro Tecnico",
    "wof:placetype":"venue"
},
  "geometry": {"coordinates":[-3.7210009098,40.412815094],"type":"Point"}
}