{
  "type": "Feature",
  "properties": {
    "addr:full":"Plaz Callao, 4 Madrid Madrid 28013",
    "addr:postcode":"4 madrid;28013",
    "iso:country":"ES",
    "sg:address":"Plaz Callao, 4",
    "sg:city":"Madrid",
    "sg:orig_category":"Empresarios Y Productoras De Espect\u00c1culos",
    "sg:phone":"+34 917 01 00 46",
    "sg:postcode":"28013",
    "sg:province":"Madrid",
    "sg:website":"www.kailash.es",
    "wof:name":"Kailash Model S.l.",
    "wof:placetype":"venue"
},
  "geometry": {"coordinates":[-3.7055690289,40.4203414917],"type":"Point"}
}