{
  "type": "Feature",
  "properties": {
    "iso:country":"ES",
    "sg:address":"Carr Pianc, 235",
    "sg:city":"Cadaques",
    "sg:orig_category":"Laboratorios Farmac\u00c9uticos",
    "sg:phone":"+34 972 25 82 52",
    "sg:postcode":"17488",
    "sg:province":"Girona",
    "wof:name":"Sala Bruses Maria Concepcion",
    "wof:placetype":"venue"
},
  "geometry": {"coordinates":[3.2777349949,42.2890510559],"type":"Point"}
}