{
  "type": "Feature",
  "properties": {
    "addr:full":"Avda Mari\u00d1a (da), S/n San Cibrao Lugo 27890",
    "addr:housenumber":"/ n",
    "addr:postcode":"27890",
    "addr:street":"Avda Marin\u0303A Da S",
    "iso:country":"ES",
    "sg:address":"Avda Mari\u00d1a (da), S/n",
    "sg:city":"San Cibrao",
    "sg:orig_category":"Carnicer\u00cdas, Carnicer\u00cdas",
    "sg:phone":"+34 982 59 30 28",
    "sg:postcode":"27890",
    "sg:province":"Lugo",
    "wof:name":"Ana Maria Gonzalez Rodriguez Y Otros Cdad.",
    "wof:placetype":"venue"
},
  "geometry": {"coordinates":[-7.5558514595,43.0120849609],"type":"Point"}
}