{
  "type": "Feature",
  "properties": {
    "iso:country":"ES",
    "sg:address":"Plaz Mayor, 2",
    "sg:city":"Alcampell",
    "sg:orig_category":"Iglesia Cat\u00d3lica",
    "sg:phone":"+34 974 42 19 03",
    "sg:postcode":"22560",
    "sg:province":"Huesca",
    "wof:name":"Parroquia De Alcampel",
    "wof:placetype":"venue"
},
  "geometry": {"coordinates":[0.432096988,41.9058227539],"type":"Point"}
}