{
  "type": "Feature",
  "properties": {
    "addr:full":"Av Montblanc, 10 Reus Tarragona 43206",
    "addr:housenumber":"10",
    "addr:postcode":"43206",
    "addr:street":"Av Montblanc",
    "iso:country":"ES",
    "sg:address":"Av Montblanc, 10",
    "sg:city":"Reus",
    "sg:orig_category":"M\u00c1rmoles, Granitos Y Piedras Naturales",
    "sg:phone":"+34 977 34 38 06",
    "sg:postcode":"43206",
    "sg:province":"Tarragona",
    "wof:name":"Artisticos De Levante S.l.",
    "wof:placetype":"venue"
},
  "geometry": {"coordinates":[1.1168408394,41.1609687805],"type":"Point"}
}