{
  "type": "Feature",
  "properties": {
    "iso:country":"ES",
    "sg:address":"Calle de Fraguas (de Las), 4",
    "sg:city":"Algete",
    "sg:orig_category":"Peluquer\u00cdas, Peluquer\u00cda Mixta",
    "sg:phone":"+34 916 29 19 99",
    "sg:postcode":"28110",
    "sg:province":"Madrid",
    "wof:name":"Moriam Peluqueros S.l.",
    "wof:placetype":"venue"
},
  "geometry": {"coordinates":[-3.4977521896,40.5961303711],"type":"Point"}
}