{
  "type": "Feature",
  "properties": {
    "iso:country":"ES",
    "sg:address":"Calle de Pedro Barba, 25",
    "sg:city":"Puerto Del Carmen",
    "sg:orig_category":"Bazares, Art\u00cdculos De Limpieza Y De Cocina (al Por Menor)",
    "sg:phone":"+34 928 51 56 28",
    "sg:postcode":"35510",
    "sg:province":"Las Palmas",
    "wof:name":"Hernandez Machin Barbara",
    "wof:placetype":"venue"
},
  "geometry": {"coordinates":[-13.6662149429,28.9237804413],"type":"Point"}
}