{
  "type": "Feature",
  "properties": {
    "iso:country":"ES",
    "sg:address":"San Antonio, 2",
    "sg:city":"Iru\u00f1a",
    "sg:orig_category":"Asociaciones, Organismos Culturales Y Socioeducativos",
    "sg:phone":"+34 948 14 35 95",
    "sg:postcode":"31014",
    "sg:province":"Navarra",
    "wof:name":"Gure-atseguin",
    "wof:placetype":"venue"
},
  "geometry": {"coordinates":[-1.6489312649,42.8254928589],"type":"Point"}
}