{
  "type": "Feature",
  "properties": {
    "iso:country":"ES",
    "sg:address":"Calle de Zurbaran, 8",
    "sg:city":"Badajoz",
    "sg:orig_category":"Abogados",
    "sg:phone":"+34 924 20 71 96",
    "sg:postcode":"06002",
    "sg:province":"Badajoz",
    "wof:name":"Alonso Fraile Jose Manuel",
    "wof:placetype":"venue"
},
  "geometry": {"coordinates":[-6.9704651833,38.877155304],"type":"Point"}
}