{
  "type": "Feature",
  "properties": {
    "iso:country":"ES",
    "sg:address":"Calle de Inspector Luis Martin, 8",
    "sg:city":"Arrecife",
    "sg:classifiers":[
        {
            "category":"Personal",
            "subcategory":"Barber",
            "type":"Services"
        }
    ],
    "sg:phone":"+34 928 81 19 75",
    "sg:postcode":"35500",
    "sg:province":"Las Palmas",
    "sg:tags":[
        "caballeros",
        "de",
        "peluqueros"
    ],
    "wof:name":"Tabares Dorta Jose",
    "wof:placetype":"venue"
},
  "geometry": {"coordinates":[-13.5476694107,28.9588775635],"type":"Point"}
}