{
  "type": "Feature",
  "properties": {
    "iso:country":"ES",
    "sg:address":"Avda Espa\u00d1a, 42",
    "sg:city":"Plasencia",
    "sg:orig_category":"Pintura, Barniz, Productos Asimilables (fabricaci\u00d3n, Al Por Mayor)",
    "sg:phone":"+34 927 41 52 73",
    "sg:postcode":"10600",
    "sg:province":"C\u00e1ceres",
    "wof:name":"Pinturas Mayo S.l",
    "wof:placetype":"venue"
},
  "geometry": {"coordinates":[-6.0975198746,40.0221595764],"type":"Point"}
}