{
  "type": "Feature",
  "properties": {
    "iso:country":"ES",
    "sg:address":"Plaz Mayor, S/n",
    "sg:city":"Monzon De Campos",
    "sg:orig_category":"Carnicer\u00cdas, Carnicer\u00cdas",
    "sg:phone":"+34 979 80 81 92",
    "sg:postcode":"34410",
    "sg:province":"Palencia",
    "wof:name":"Carlos Simon Amor Cb",
    "wof:placetype":"venue"
},
  "geometry": {"coordinates":[-4.4945487976,42.1160545349],"type":"Point"}
}