{
  "type": "Feature",
  "properties": {
    "iso:country":"ES",
    "sg:address":"Avda Axular Ibiltokia, 24",
    "sg:city":"Zumaia",
    "sg:orig_category":"Transportes Por V\u00cdas Navegables",
    "sg:phone":"+34 943 86 09 63",
    "sg:postcode":"20750",
    "sg:province":"Guip\u00f9zcoa",
    "wof:name":"Banda Praxedes Carlos",
    "wof:placetype":"venue"
},
  "geometry": {"coordinates":[-2.2595860958,43.2877082825],"type":"Point"}
}