{
  "type": "Feature",
  "properties": {
    "addr:full":"Calle de General Ricardos, 179 Madrid Madrid 28025",
    "addr:housenumber":"179",
    "addr:postcode":"28025",
    "addr:street":"Calle De General Ricardos",
    "iso:country":"ES",
    "sg:address":"Calle de General Ricardos, 179",
    "sg:city":"Madrid",
    "sg:orig_category":"Formaci\u00d3n Continuada (variada)",
    "sg:phone":"+34 915 25 08 93",
    "sg:postcode":"28025",
    "sg:province":"Madrid",
    "wof:name":"Organismo Autonomo De Informatica Y Comunicaciones De La Comunidad De Madrid",
    "wof:placetype":"venue"
},
  "geometry": {"coordinates":[-3.741091013,40.3833961487],"type":"Point"}
}