{
  "type": "Feature",
  "properties": {
    "iso:country":"ES",
    "sg:address":"Carr 9 D'octubre, 4",
    "sg:city":"Oliva",
    "sg:orig_category":"Ortopedia General",
    "sg:phone":"+34 962 85 52 51",
    "sg:postcode":"46780",
    "sg:province":"Valencia",
    "wof:name":"Ortopedia Paris S.l.",
    "wof:placetype":"venue"
},
  "geometry": {"coordinates":[-0.1482906938,38.9608764648],"type":"Point"}
}