{
  "type": "Feature",
  "properties": {
    "iso:country":"ES",
    "sg:address":"Carrer de Tudo, 11",
    "sg:city":"Son Ferrer",
    "sg:orig_category":"Alquiler De V\u00cddeo",
    "sg:phone":"+34 971 23 81 31",
    "sg:postcode":"07182",
    "sg:province":"Islas Baleares",
    "wof:name":"Multiocio Santa Pon\u00e7a S.l.l.",
    "wof:placetype":"venue"
},
  "geometry": {"coordinates":[2.5072999001,39.4970664978],"type":"Point"}
}