{
  "type": "Feature",
  "properties": {
    "addr:full":"Cdad Valenciana(base Dos Mil), 5 Lorqui Murcia 30564",
    "addr:postcode":"30564",
    "iso:country":"ES",
    "sg:address":"Cdad Valenciana(base Dos Mil), 5",
    "sg:city":"Lorqui",
    "sg:orig_category":"Agencias Y Asesores De Publicidad",
    "sg:phone":"+34 968 67 60 00",
    "sg:postcode":"30564",
    "sg:province":"Murcia",
    "sg:website":"www.modularscoop.com",
    "wof:name":"Modular S.c.o.p.",
    "wof:placetype":"venue"
},
  "geometry": {"coordinates":[-1.2288839817,38.1007652283],"type":"Point"}
}