{
  "type": "Feature",
  "properties": {
    "addr:full":"Calle de Juan Xxiii (de), 9 Parla Madrid 28980",
    "addr:postcode":"28980",
    "addr:street":"Calle De Juan Xxiii De 9",
    "iso:country":"ES",
    "sg:address":"Calle de Juan Xxiii (de), 9",
    "sg:city":"Parla",
    "sg:orig_category":"Inmobiliaria (agencias)",
    "sg:phone":"+34 916 05 46 48",
    "sg:postcode":"28980",
    "sg:province":"Madrid",
    "sg:website":"www.inmopalacin.com",
    "wof:name":"Union De Viviendas Familiares Jil S.l.",
    "wof:placetype":"venue"
},
  "geometry": {"coordinates":[-3.7628369331,40.2407073975],"type":"Point"}
}