{
  "type": "Feature",
  "properties": {
    "addr:full":"Carrer de Angel Guimera, 15 Manresa Barcelona 08241",
    "addr:housenumber":"15",
    "addr:postcode":"08241",
    "addr:street":"Carrer De Angel Guimera",
    "iso:country":"ES",
    "sg:address":"Carrer de Angel Guimera, 15",
    "sg:city":"Manresa",
    "sg:orig_category":"Fotograf\u00cda Art\u00cdstica Y Retratos",
    "sg:phone":"+34 938 72 33 50",
    "sg:postcode":"08241",
    "sg:province":"Barcelona",
    "wof:name":"Sarda Juanola Llorens",
    "wof:placetype":"venue"
},
  "geometry": {"coordinates":[1.8242080212,41.7262573242],"type":"Point"}
}