{
  "type": "Feature",
  "properties": {
    "addr:full":"Calle de Horcajo, 14 Marchamalo Guadalajara 19180",
    "addr:housenumber":"14",
    "addr:postcode":"19180",
    "addr:street":"Calle De Horcajo",
    "iso:country":"ES",
    "sg:address":"Calle de Horcajo, 14",
    "sg:city":"Marchamalo",
    "sg:orig_category":"Fabricaci\u00d3n, Importaci\u00d3n, Venta De Material De Telefon\u00cda, Peritelefon\u00cda",
    "sg:phone":"+34 949 25 02 19",
    "sg:postcode":"19180",
    "sg:province":"Guadalajara",
    "wof:name":"Optifhone",
    "wof:placetype":"venue"
},
  "geometry": {"coordinates":[-3.2071280479,40.6708068848],"type":"Point"}
}