{
  "type": "Feature",
  "properties": {
    "addr:full":"Ctra Zeneta (de), Km. 0002,5 Carretera De Zeneta Murcia 30130",
    "addr:postcode":"30130",
    "addr:street":"Ctra Zeneta De Km. 0002,5 Carretera De Zeneta",
    "iso:country":"ES",
    "sg:address":"Ctra Zeneta (de), Km. 0002,5",
    "sg:city":"Carretera De Zeneta",
    "sg:orig_category":"Hormigonados",
    "sg:phone":"+34 968 60 20 52",
    "sg:postcode":"30130",
    "sg:province":"Murcia",
    "wof:name":"Tarmac Iberia S.a.u.",
    "wof:placetype":"venue"
},
  "geometry": {"coordinates":[-1.0019739866,38.045753479],"type":"Point"}
}