{
  "type": "Feature",
  "properties": {
    "iso:country":"ES",
    "sg:address":"Calle de Alicante, 23",
    "sg:city":"Novelda",
    "sg:orig_category":"Metalurgia",
    "sg:phone":"+34 965 60 62 77",
    "sg:postcode":"03660",
    "sg:province":"Alicante",
    "wof:name":"Issodiamant S.a.",
    "wof:placetype":"venue"
},
  "geometry": {"coordinates":[-0.7688851953,38.3872032166],"type":"Point"}
}