{
  "type": "Feature",
  "properties": {
    "addr:full":"Calle de Torres De La Alameda, 2 Alcala Henares Madrid 28806",
    "addr:housenumber":"2",
    "addr:postcode":"28806",
    "addr:street":"Calle De Torres De La Alameda",
    "iso:country":"ES",
    "sg:address":"Calle de Torres De La Alameda, 2",
    "sg:city":"Alcala Henares",
    "sg:orig_category":"Materias Pl\u00c1sticas: Art\u00cdculos Para La Industria",
    "sg:phone":"+34 918 82 08 66",
    "sg:postcode":"28806",
    "sg:province":"Madrid",
    "wof:name":"Plasteuropa Embases Flexibles S.a.",
    "wof:placetype":"venue"
},
  "geometry": {"coordinates":[-3.3779819012,40.4958000183],"type":"Point"}
}