{
  "type": "Feature",
  "properties": {
    "addr:full":"Av Roma (de), S/n Tarragona Tarragona 43005",
    "addr:housenumber":"s / n",
    "addr:postcode":"43005",
    "addr:street":"Av Roma De",
    "iso:country":"ES",
    "sg:address":"Av Roma (de), S/n",
    "sg:city":"Tarragona",
    "sg:orig_category":"Peluquer\u00cdas, Peluquer\u00cda Mixta",
    "sg:phone":"+34 977 24 83 26",
    "sg:postcode":"43005",
    "sg:province":"Tarragona",
    "wof:name":"Ebanni Peluquerias Costa S.l.",
    "wof:placetype":"venue"
},
  "geometry": {"coordinates":[1.2375839949,41.117641449],"type":"Point"}
}