{
  "type": "Feature",
  "properties": {
    "addr:full":"Avda Marques De Paterna, 10 Merida Badajoz 06800",
    "addr:housenumber":"10",
    "addr:postcode":"06800",
    "addr:street":"Avda Marques De Paterna",
    "iso:country":"ES",
    "sg:address":"Avda Marques De Paterna, 10",
    "sg:city":"Merida",
    "sg:orig_category":"Carnicer\u00cdas, Carnicer\u00cdas",
    "sg:phone":"+34 924 31 75 54",
    "sg:postcode":"06800",
    "sg:province":"Badajoz",
    "wof:name":"Gutierrez Capilla Felipe",
    "wof:placetype":"venue"
},
  "geometry": {"coordinates":[-6.3329539299,38.9224700928],"type":"Point"}
}