{
  "type": "Feature",
  "properties": {
    "addr:full":"Calle de Pinar De Do\u00d1a Consuelo, 57 Majadahonda Madrid 28220",
    "addr:housenumber":"57",
    "addr:postcode":"28220",
    "addr:street":"Calle De Pinar De Don\u0303A Consuelo",
    "iso:country":"ES",
    "sg:address":"Calle de Pinar De Do\u00d1a Consuelo, 57",
    "sg:city":"Majadahonda",
    "sg:orig_category":"Inmobiliaria (agencias)",
    "sg:phone":"+34 916 38 04 02",
    "sg:postcode":"28220",
    "sg:province":"Madrid",
    "wof:name":"Castro Raso S.l.",
    "wof:placetype":"venue"
},
  "geometry": {"coordinates":[-3.8785400391,40.4835700989],"type":"Point"}
}