{
  "type": "Feature",
  "properties": {
    "iso:country":"ES",
    "sg:address":"Av Sant Julia, 222",
    "sg:city":"Granollers",
    "sg:orig_category":"Grabados",
    "sg:phone":"+34 938 40 53 20",
    "sg:postcode":"08403",
    "sg:province":"Barcelona",
    "wof:name":"Grabaciones Janoschka",
    "wof:placetype":"venue"
},
  "geometry": {"coordinates":[2.273088932,41.5791816711],"type":"Point"}
}