{
  "type": "Feature",
  "properties": {
    "addr:full":"Pl Llibertat, 7 Barcelona Barcelona 08012",
    "addr:housenumber":"7",
    "addr:postcode":"08012",
    "addr:street":"Pl Llibertat",
    "iso:country":"ES",
    "sg:address":"Pl Llibertat, 7",
    "sg:city":"Barcelona",
    "sg:orig_category":"Droguer\u00cdas (al Por Menor)",
    "sg:phone":"+34 932 18 43 97",
    "sg:postcode":"08012",
    "sg:province":"Barcelona",
    "wof:name":"Soltri S. A.",
    "wof:placetype":"venue"
},
  "geometry": {"coordinates":[2.1536970139,41.4002189636],"type":"Point"}
}