{
  "type": "Feature",
  "properties": {
    "addr:full":"Sobral, S/n Sobral Ourense 32100",
    "addr:housenumber":"s / n",
    "addr:postcode":"32100",
    "addr:street":"Sobral",
    "iso:country":"ES",
    "sg:address":"Sobral, S/n",
    "sg:city":"Sobral",
    "sg:orig_category":"Mec\u00c1nico Del Autom\u00d3vil",
    "sg:phone":"+34 988 20 42 02",
    "sg:postcode":"32100",
    "sg:province":"Ourense",
    "wof:name":"Automecanica Sobral S.l.",
    "wof:placetype":"venue"
},
  "geometry": {"coordinates":[-7.853331089,42.3797111511],"type":"Point"}
}