{
  "type": "Feature",
  "properties": {
    "iso:country":"ES",
    "sg:address":"Calle de Ramon Y Cajal, 8",
    "sg:city":"Ciudad Real",
    "sg:orig_category":"Moquetas, Alfombras (al Por Menor)",
    "sg:phone":"+34 926 22 20 45",
    "sg:postcode":"13001",
    "sg:province":"Ciudad Real",
    "wof:name":"Lopez Mu\u00f1oz Angel",
    "wof:placetype":"venue"
},
  "geometry": {"coordinates":[-3.9277420044,38.9841537476],"type":"Point"}
}