{
  "type": "Feature",
  "properties": {
    "iso:country":"ES",
    "sg:address":"Calle de Ahin, S/n",
    "sg:city":"Nules",
    "sg:orig_category":"M\u00c1rmoles, Granitos Y Piedras Naturales",
    "sg:phone":"+34 964 67 15 58",
    "sg:postcode":"12520",
    "sg:province":"Castell\u00f3n",
    "wof:name":"Beltran Porcar Enrique",
    "wof:placetype":"venue"
},
  "geometry": {"coordinates":[-0.1590383053,39.8585357666],"type":"Point"}
}