{
  "type": "Feature",
  "properties": {
    "iso:country":"ES",
    "sg:address":"Carrer de Jose De Agullo, 20",
    "sg:city":"Barcelona",
    "sg:orig_category":"Ingenier\u00cda, Centros De Estudios (diversos)",
    "sg:phone":"+34 932 01 48 98",
    "sg:postcode":"08017",
    "sg:province":"Barcelona",
    "wof:name":"Riera Comella Pablo",
    "wof:placetype":"venue"
},
  "geometry": {"coordinates":[2.1347908974,41.3959541321],"type":"Point"}
}