{
  "type": "Feature",
  "properties": {
    "addr:full":"Pase Hortaz (del), 2 Tamarite Litera Huesca 22550",
    "addr:postcode":"22550",
    "iso:country":"ES",
    "sg:address":"Pase Hortaz (del), 2",
    "sg:city":"Tamarite Litera",
    "sg:orig_category":"Peluqueros: De Se\u00d1oras",
    "sg:phone":"+34 974 42 15 19",
    "sg:postcode":"22550",
    "sg:province":"Huesca",
    "wof:name":"Cortes Monguia Maria Jose",
    "wof:placetype":"venue"
},
  "geometry": {"coordinates":[0.4240469933,41.8659324646],"type":"Point"}
}