{
  "type": "Feature",
  "properties": {
    "iso:country":"ES",
    "sg:address":"Pje El Ajoli, 5",
    "sg:city":"Huevar",
    "sg:orig_category":"Alquiler De V\u00cddeo",
    "sg:phone":"+34 954 75 63 23",
    "sg:postcode":"41830",
    "sg:province":"Sevilla",
    "wof:name":"Piris Terrones Antonio",
    "wof:placetype":"venue"
},
  "geometry": {"coordinates":[-6.2788071632,37.3557777405],"type":"Point"}
}