{
  "type": "Feature",
  "properties": {
    "addr:full":"Calle de San Ignacio, 6 Gijon Asturias 33205",
    "addr:housenumber":"6",
    "addr:postcode":"33205",
    "addr:street":"Calle De San Ignacio",
    "iso:country":"ES",
    "sg:address":"Calle de San Ignacio, 6",
    "sg:city":"Gijon",
    "sg:orig_category":"Comerciantes Al Por Mayor De Vinos, Licores Y Alcoholes",
    "sg:phone":"+34 985 36 11 38",
    "sg:postcode":"33205",
    "sg:province":"Asturias",
    "wof:name":"Moreno Sanchez Victoriano",
    "wof:placetype":"venue"
},
  "geometry": {"coordinates":[-5.6551251411,43.5337562561],"type":"Point"}
}