{
  "type": "Feature",
  "properties": {
    "addr:full":"Calle de Isaac Albeniz, 21 Granada Granada 18012",
    "addr:housenumber":"21",
    "addr:postcode":"18012",
    "addr:street":"Calle De Isaac Albeniz",
    "iso:country":"ES",
    "sg:address":"Calle de Isaac Albeniz, 21",
    "sg:city":"Granada",
    "sg:orig_category":"Expertos Contables, Revisores De Cuentas",
    "sg:phone":"+34 958 80 06 12",
    "sg:postcode":"18012",
    "sg:province":"Granada",
    "wof:name":"Echegaray Auditores C.b.",
    "wof:placetype":"venue"
},
  "geometry": {"coordinates":[-3.6082069874,37.1883468628],"type":"Point"}
}