{
  "type": "Feature",
  "properties": {
    "addr:full":"Calle de Veracruz, 9 Torreperogil Ja\u00e9n 23320",
    "addr:housenumber":"9",
    "addr:postcode":"23320",
    "addr:street":"Calle De Veracruz",
    "iso:country":"ES",
    "sg:address":"Calle de Veracruz, 9",
    "sg:city":"Torreperogil",
    "sg:classifiers":[
        {
            "category":"Taxi",
            "type":"Transportation"
        }
    ],
    "sg:phone":"+34 953 77 67 04",
    "sg:postcode":"23320",
    "sg:province":"Ja\u00e9n",
    "wof:name":"Villar Valero Antonio",
    "wof:placetype":"venue"
},
  "geometry": {"coordinates":[-3.2923910618,38.0338287354],"type":"Point"}
}