{
  "type": "Feature",
  "properties": {
    "iso:country":"ES",
    "sg:address":"Calle de Aldamar, 34",
    "sg:city":"Donostia-san Sebastian",
    "sg:orig_category":"Asesor\u00cda Sobre Comunicaci\u00d3n De Empresas",
    "sg:phone":"+34 943 42 03 91",
    "sg:postcode":"20003",
    "sg:province":"Guip\u00f9zcoa",
    "wof:name":"Donosti De Servicios S.a.",
    "wof:placetype":"venue"
},
  "geometry": {"coordinates":[-1.983407259,43.3248748779],"type":"Point"}
}