{
  "type": "Feature",
  "properties": {
    "addr:full":"Calle de Quevedo, 14 Gijon Asturias 33204",
    "addr:housenumber":"14",
    "addr:postcode":"33204",
    "addr:street":"Calle De Quevedo",
    "iso:country":"ES",
    "sg:address":"Calle de Quevedo, 14",
    "sg:city":"Gijon",
    "sg:orig_category":"Frutas, Legumbres Frescas Y Tempranas (al Por Menor)",
    "sg:phone":"+34 985 14 48 32",
    "sg:postcode":"33204",
    "sg:province":"Asturias",
    "wof:name":"Loche Suarez Felix Aquilino",
    "wof:placetype":"venue"
},
  "geometry": {"coordinates":[-5.6544408798,43.5316848755],"type":"Point"}
}