{
  "type": "Feature",
  "properties": {
    "addr:full":"Pla\u00c7 Medellin, 14 Blanes Girona 17300",
    "addr:housenumber":"14",
    "addr:postcode":"17300",
    "addr:street":"Plac\u0327 Medellin",
    "iso:country":"ES",
    "sg:address":"Pla\u00c7 Medellin, 14",
    "sg:city":"Blanes",
    "sg:orig_category":"Servicios De Telecomunicaciones",
    "sg:phone":"+34 972 35 36 11",
    "sg:postcode":"17300",
    "sg:province":"Girona",
    "wof:name":"Ibrahime  Toure",
    "wof:placetype":"venue"
},
  "geometry": {"coordinates":[2.7742230892,41.6675834656],"type":"Point"}
}