{
  "type": "Feature",
  "properties": {
    "iso:country":"ES",
    "sg:address":"Calle de San Juan Degollado, 5",
    "sg:city":"Arafo",
    "sg:orig_category":"Sanatorios M\u00c9dico",
    "sg:phone":"+34 922 51 45 60",
    "sg:postcode":"38550",
    "sg:province":"Santa Cruz De Tenerife",
    "wof:name":"Gobierno De Canarias",
    "wof:placetype":"venue"
},
  "geometry": {"coordinates":[-16.4181594849,28.340045929],"type":"Point"}
}