{
  "type": "Feature",
  "properties": {
    "iso:country":"ES",
    "sg:address":"Pl Centre, 5",
    "sg:city":"Barcelona",
    "sg:orig_category":"Estancos",
    "sg:phone":"+34 934 90 44 01",
    "sg:postcode":"08014",
    "sg:province":"Barcelona",
    "wof:name":"Formetin Iba\u00f1ez Vicente",
    "wof:placetype":"venue"
},
  "geometry": {"coordinates":[2.135529995,41.3822402954],"type":"Point"}
}