{
  "type": "Feature",
  "properties": {
    "addr:full":"Carrer de Arago, 184 Barcelona Barcelona 08011",
    "addr:housenumber":"184",
    "addr:postcode":"08011",
    "addr:street":"Carrer De Arago",
    "iso:country":"ES",
    "sg:address":"Carrer de Arago, 184",
    "sg:city":"Barcelona",
    "sg:orig_category":"Abogados",
    "sg:phone":"+34 933 23 81 88",
    "sg:postcode":"08011",
    "sg:province":"Barcelona",
    "wof:name":"Faura Santasusana Maria De Las Mercedes",
    "wof:placetype":"venue"
},
  "geometry": {"coordinates":[2.1580779552,41.3868637085],"type":"Point"}
}