{
  "type": "Feature",
  "properties": {
    "addr:full":"Calle de San Sebastian, 3 Dos Hermanas Sevilla 41700",
    "addr:housenumber":"3",
    "addr:postcode":"41700",
    "addr:street":"Calle De San Sebastian;Sevilla",
    "iso:country":"ES",
    "sg:address":"Calle de San Sebastian, 3",
    "sg:city":"Dos Hermanas",
    "sg:orig_category":"Loter\u00cda Y T\u00d3mbola",
    "sg:phone":"+34 955 66 80 71",
    "sg:postcode":"41700",
    "sg:province":"Sevilla",
    "wof:name":"Cardoso Lopez Eduardo",
    "wof:placetype":"venue"
},
  "geometry": {"coordinates":[-5.9206337929,37.2812080383],"type":"Point"}
}