{
  "type": "Feature",
  "properties": {
    "iso:country":"ES",
    "sg:address":"Poli Talluntxe / Talluntze Industrialdea, 61",
    "sg:city":"Noain",
    "sg:orig_category":"Art\u00cdculos De Aluminio",
    "sg:phone":"+34 948 31 22 33",
    "sg:postcode":"31110",
    "sg:province":"Navarra",
    "wof:name":"Aluminios Pamplona S.l.",
    "wof:placetype":"venue"
},
  "geometry": {"coordinates":[-1.5935460329,42.7209968567],"type":"Point"}
}