{
  "type": "Feature",
  "properties": {
    "addr:full":"Avda Andalucia, 36 Alcaudete Ja\u00e9n 23660",
    "addr:housenumber":"36",
    "addr:postcode":"23660",
    "addr:street":"Avda Andalucia;Jae\u0301N",
    "iso:country":"ES",
    "sg:address":"Avda Andalucia, 36",
    "sg:city":"Alcaudete",
    "sg:orig_category":"Notarios",
    "sg:phone":"+34 953 56 07 75",
    "sg:postcode":"23660",
    "sg:province":"Ja\u00e9n",
    "wof:name":"Angulo Gonzalez De Lara Maria Del Carmen",
    "wof:placetype":"venue"
},
  "geometry": {"coordinates":[-4.078151226,37.5908470154],"type":"Point"}
}