{
  "type": "Feature",
  "properties": {
    "addr:full":"Calle de Beko Kale, 14 Mungia Vizcaya 48100",
    "addr:housenumber":"14",
    "addr:postcode":"48100",
    "addr:street":"Calle De Beko Kale",
    "iso:country":"ES",
    "sg:address":"Calle de Beko Kale, 14",
    "sg:city":"Mungia",
    "sg:orig_category":"Cl\u00cdnicas Dentales",
    "sg:phone":"+34 944 06 13 88",
    "sg:postcode":"48100",
    "sg:province":"Vizcaya",
    "wof:name":"Maider Goti Llona",
    "wof:placetype":"venue"
},
  "geometry": {"coordinates":[-2.8277962208,43.3621711731],"type":"Point"}
}