{
  "type": "Feature",
  "properties": {
    "addr:full":"Av Alcalde Moix, 26 Sabadell Barcelona 08207",
    "addr:housenumber":"26",
    "addr:postcode":"08207",
    "addr:street":"Av Alcalde Moix",
    "iso:country":"ES",
    "sg:address":"Av Alcalde Moix, 26",
    "sg:city":"Sabadell",
    "sg:orig_category":"Venta, Instalaci\u00d3n De Calefacci\u00d3n",
    "sg:phone":"+34 937 23 10 83",
    "sg:postcode":"08207",
    "sg:province":"Barcelona",
    "sg:website":"www.clima-calor.com",
    "wof:name":"Instalaciones Clima Calor S.l.",
    "wof:placetype":"venue"
},
  "geometry": {"coordinates":[2.0981750488,41.5648422241],"type":"Point"}
}