{
  "type": "Feature",
  "properties": {
    "iso:country":"ES",
    "sg:address":"Avda Carlos Iii, 39",
    "sg:city":"S. Fernando",
    "sg:orig_category":"Instalaci\u00d3n, Reparaci\u00d3n De Ascensores Y Montacargas",
    "sg:phone":"+34 956 59 49 32",
    "sg:postcode":"11100",
    "sg:province":"C\u00e1diz",
    "sg:website":"www.kone.com",
    "wof:name":"Kone S.a.",
    "wof:placetype":"venue"
},
  "geometry": {"coordinates":[-6.1896481514,36.4725151062],"type":"Point"}
}