{
  "type": "Feature",
  "properties": {
    "iso:country":"ES",
    "sg:address":"Carrer de Sagrera, 162",
    "sg:city":"Barcelona",
    "sg:orig_category":"Material Y Suministros Para Peluquer\u00cda",
    "sg:phone":"+34 933 40 03 00",
    "sg:postcode":"08027",
    "sg:province":"Barcelona",
    "wof:name":"Tif Comercial S.c.p.",
    "wof:placetype":"venue"
},
  "geometry": {"coordinates":[2.1911480427,41.4255104065],"type":"Point"}
}