{
  "type": "Feature",
  "properties": {
    "addr:full":"Carrer de Indalecio Prieto, 9 Palma Islas Baleares 07008",
    "addr:housenumber":"9",
    "addr:postcode":"07008",
    "addr:street":"Carrer De Indalecio Prieto",
    "iso:country":"ES",
    "sg:address":"Carrer de Indalecio Prieto, 9",
    "sg:city":"Palma",
    "sg:orig_category":"Bisuter\u00cda, Joyer\u00cda, Relojer\u00cda (al Por Menor)",
    "sg:phone":"+34 971 27 54 64",
    "sg:postcode":"07008",
    "sg:province":"Islas Baleares",
    "wof:name":"Cortes Cladera Jose",
    "wof:placetype":"venue"
},
  "geometry": {"coordinates":[2.6696190834,39.5772476196],"type":"Point"}
}