{
  "type": "Feature",
  "properties": {
    "iso:country":"ES",
    "sg:address":"Calle de Hortaleza, 37",
    "sg:city":"Madrid",
    "sg:orig_category":"Caf\u00c9s, Bares, Cervecer\u00cdas",
    "sg:phone":"+34 915 23 29 82",
    "sg:postcode":"28004",
    "sg:province":"Madrid",
    "wof:name":"Priego Lopez Juan Alvaro",
    "wof:placetype":"venue"
},
  "geometry": {"coordinates":[-3.6997330189,40.4224128723],"type":"Point"}
}