{
  "type": "Feature",
  "properties": {
    "iso:country":"ES",
    "sg:address":"Cmno Malkuartu, 1",
    "sg:city":"Llodio",
    "sg:orig_category":"Restaurantes",
    "sg:phone":"+34 946 72 43 50",
    "sg:postcode":"01400",
    "sg:province":"\u00c1lava",
    "wof:name":"Balintxa S.c.",
    "wof:placetype":"venue"
},
  "geometry": {"coordinates":[-3.0252077579,43.1529998779],"type":"Point"}
}