{
  "type": "Feature",
  "properties": {
    "iso:country":"ES",
    "sg:address":"Ctra Daganzo, 18",
    "sg:city":"Ajalvir",
    "sg:orig_category":"Promotores Constructores",
    "sg:phone":"+34 918 84 30 75",
    "sg:postcode":"28864",
    "sg:province":"Madrid",
    "wof:name":"Aprosa S.a.",
    "wof:placetype":"venue"
},
  "geometry": {"coordinates":[-3.478946209,40.5334243774],"type":"Point"}
}