{
  "type": "Feature",
  "properties": {
    "iso:country":"ES",
    "sg:address":"Carrer de Progres, 44",
    "sg:city":"Santa Coloma De Queralt",
    "sg:orig_category":"Centros Empresariales",
    "sg:phone":"+34 977 88 08 15",
    "sg:postcode":"43420",
    "sg:province":"Tarragona",
    "wof:name":"Gae-scq S.l.l.",
    "wof:placetype":"venue"
},
  "geometry": {"coordinates":[1.3798400164,41.531829834],"type":"Point"}
}