{
  "type": "Feature",
  "properties": {
    "addr:full":"Videira, 13 Videira Pontevedra 36778",
    "addr:housenumber":"13",
    "addr:postcode":"36778",
    "addr:street":"Videira",
    "iso:country":"ES",
    "sg:address":"Videira, 13",
    "sg:city":"Videira",
    "sg:orig_category":"Negocio De Materiales De Construcci\u00d3n",
    "sg:phone":"+34 986 62 57 99",
    "sg:postcode":"36778",
    "sg:province":"Pontevedra",
    "wof:name":"J. Rivero Materiales De Construccion C.b.",
    "wof:placetype":"venue"
},
  "geometry": {"coordinates":[-8.6428003311,42.4304618835],"type":"Point"}
}