{
  "type": "Feature",
  "properties": {
    "iso:country":"ES",
    "sg:address":"Calle de San Juan Bautista, 26",
    "sg:city":"Ubrique",
    "sg:orig_category":"Bebidas",
    "sg:phone":"+34 956 46 10 41",
    "sg:postcode":"11600",
    "sg:province":"C\u00e1diz",
    "wof:name":"Herrera Gonzalez Roque",
    "wof:placetype":"venue"
},
  "geometry": {"coordinates":[-5.4469690323,36.6781806946],"type":"Point"}
}