{
  "type": "Feature",
  "properties": {
    "addr:full":"Se\u00f1orio De Egulbati, 2 Iru\u00f1a Navarra 31016",
    "addr:housenumber":"2",
    "addr:postcode":"31016",
    "addr:street":"Irun\u0303A Navarra",
    "iso:country":"ES",
    "sg:address":"Se\u00f1orio De Egulbati, 2",
    "sg:city":"Iru\u00f1a",
    "sg:orig_category":"Tintes (fabricaci\u00d3n, Al Por Mayor)",
    "sg:phone":"+34 948 16 34 11",
    "sg:postcode":"31016",
    "sg:province":"Navarra",
    "wof:name":"Cabodevilla Martinez Losa Rita",
    "wof:placetype":"venue"
},
  "geometry": {"coordinates":[-1.6109340191,42.8106079102],"type":"Point"}
}