{
  "type": "Feature",
  "properties": {
    "addr:full":"Avda Camelias, 88 Vigo Pontevedra 36211",
    "addr:housenumber":"88",
    "addr:postcode":"36211",
    "addr:street":"Avda Camelias",
    "iso:country":"ES",
    "sg:address":"Avda Camelias, 88",
    "sg:city":"Vigo",
    "sg:orig_category":"Asesor\u00cda Sobre Comunicaci\u00d3n De Empresas",
    "sg:phone":"+34 986 29 44 96",
    "sg:postcode":"36211",
    "sg:province":"Pontevedra",
    "wof:name":"Salvador Nu\u00f1ez Oscar",
    "wof:placetype":"venue"
},
  "geometry": {"coordinates":[-8.7298679352,42.2270431519],"type":"Point"}
}