{
  "type": "Feature",
  "properties": {
    "iso:country":"ES",
    "sg:address":"Calle de Micaela Portilla, 2",
    "sg:city":"Vitoria-gasteiz",
    "sg:orig_category":"Sociedades, Compa\u00d1\u00cdas Aseguradoras",
    "sg:phone":"+34 945 15 03 10",
    "sg:postcode":"01008",
    "sg:province":"\u00c1lava",
    "wof:name":"La Estrella S.a. De Seguros",
    "wof:placetype":"venue"
},
  "geometry": {"coordinates":[-2.6800570488,42.843952179],"type":"Point"}
}