{
  "type": "Feature",
  "properties": {
    "addr:full":"Carr Barcelona, 16 Girona Girona 17002",
    "addr:housenumber":"16",
    "addr:postcode":"17002",
    "addr:street":"Carr Barcelona",
    "iso:country":"ES",
    "sg:address":"Carr Barcelona, 16",
    "sg:city":"Girona",
    "sg:orig_category":"Asesor\u00cda Sobre Comunicaci\u00d3n De Empresas",
    "sg:phone":"+34 972 20 22 26",
    "sg:postcode":"17002",
    "sg:province":"Girona",
    "wof:name":"Assessoria Economica Administrativa I Juridica S.l.",
    "wof:placetype":"venue"
},
  "geometry": {"coordinates":[2.818803072,41.9810218811],"type":"Point"}
}