{
  "type": "Feature",
  "properties": {
    "iso:country":"ES",
    "sg:address":"Calle de Via Cornelia, 2",
    "sg:city":"Santander",
    "sg:orig_category":"Internados & Ense\u00d1anza Privada",
    "sg:phone":"+34 942 21 23 58",
    "sg:postcode":"39001",
    "sg:province":"Cantabria",
    "wof:name":"Colegio Compa\u00f1ia De Maria",
    "wof:placetype":"venue"
},
  "geometry": {"coordinates":[-3.8109750748,43.4645805359],"type":"Point"}
}