{
  "type": "Feature",
  "properties": {
    "addr:full":"Avda Constitucion, 72 Cebreros \u00c1vila 05260",
    "addr:housenumber":"72",
    "addr:postcode":"05260",
    "addr:street":"Avda Constitucion",
    "iso:country":"ES",
    "sg:address":"Avda Constitucion, 72",
    "sg:city":"Cebreros",
    "sg:orig_category":"Notarios",
    "sg:phone":"+34 918 63 05 36",
    "sg:postcode":"05260",
    "sg:province":"\u00c1vila",
    "wof:name":"Goma Lanzon Fernando",
    "wof:placetype":"venue"
},
  "geometry": {"coordinates":[-4.4643387794,40.4596595764],"type":"Point"}
}