{
  "type": "Feature",
  "properties": {
    "iso:country":"ES",
    "sg:address":"Calle de Gabriel Gomez, 2",
    "sg:city":"Madrid",
    "sg:orig_category":"Estudios, Instalaci\u00d3n De Climatizaci\u00d3n",
    "sg:phone":"+34 915 08 99 32",
    "sg:postcode":"28044",
    "sg:province":"Madrid",
    "wof:name":"Friem.clima Y Servicios S.a.",
    "wof:placetype":"venue"
},
  "geometry": {"coordinates":[-3.7611689568,40.3682136536],"type":"Point"}
}