{
  "type": "Feature",
  "properties": {
    "iso:country":"ES",
    "sg:address":"Carrer de Coll I Vehi, 26",
    "sg:city":"Barcelona",
    "sg:orig_category":"Asilos De Ancianos. Centros Privados",
    "sg:phone":"+34 934 50 25 77",
    "sg:postcode":"08026",
    "sg:province":"Barcelona",
    "wof:name":"Residencia Geriatrica San Pablo S.l.",
    "wof:placetype":"venue"
},
  "geometry": {"coordinates":[2.1822690964,41.4125175476],"type":"Point"}
}