{
  "type": "Feature",
  "properties": {
    "iso:country":"ES",
    "sg:address":"Avda Leioa, 2",
    "sg:city":"Algorta",
    "sg:orig_category":"Agencias Y Asesor\u00cda En Marketing Directo",
    "sg:phone":"+34 944 91 24 66",
    "sg:postcode":"48992",
    "sg:province":"Vizcaya",
    "wof:name":"Comunicacien Imagen Y Marketing Global S.l.",
    "wof:placetype":"venue"
},
  "geometry": {"coordinates":[-3.0074589252,43.3386917114],"type":"Point"}
}