{
  "type": "Feature",
  "properties": {
    "addr:full":"Calle de Zaragoza, 5 Torrejon Ardoz Madrid 28850",
    "addr:housenumber":"5",
    "addr:postcode":"28850",
    "addr:street":"Calle De Zaragoza",
    "iso:country":"ES",
    "sg:address":"Calle de Zaragoza, 5",
    "sg:city":"Torrejon Ardoz",
    "sg:orig_category":"Asesor\u00cda Fiscal Y Jur\u00cddica",
    "sg:phone":"+34 916 76 93 22",
    "sg:postcode":"28850",
    "sg:province":"Madrid",
    "wof:name":"Adeco S.l.",
    "wof:placetype":"venue"
},
  "geometry": {"coordinates":[-3.4779341221,40.5327339172],"type":"Point"}
}