{
  "type": "Feature",
  "properties": {
    "addr:full":"Calle de Morse, 32 Getafe Madrid 28906",
    "addr:housenumber":"32",
    "addr:postcode":"28906",
    "addr:street":"Calle De Morse",
    "iso:country":"ES",
    "sg:address":"Calle de Morse, 32",
    "sg:city":"Getafe",
    "sg:orig_category":"Albergues",
    "sg:phone":"+34 916 82 62 61",
    "sg:postcode":"28906",
    "sg:province":"Madrid",
    "sg:website":"www.hidalgoimport.com",
    "wof:name":"Hidalgo Import S.a.",
    "wof:placetype":"venue"
},
  "geometry": {"coordinates":[-3.694767952,40.3008270264],"type":"Point"}
}