{
  "type": "Feature",
  "properties": {
    "addr:full":"Pase Pereda, 15 Santander Cantabria 39004",
    "addr:housenumber":"15",
    "addr:postcode":"39004",
    "addr:street":"Pereda",
    "iso:country":"ES",
    "sg:address":"Pase Pereda, 15",
    "sg:city":"Santander",
    "sg:orig_category":"Loter\u00cda Y T\u00d3mbola",
    "sg:phone":"+34 942 21 27 71",
    "sg:postcode":"39004",
    "sg:province":"Cantabria",
    "wof:name":"San Jose Caballero Isabel",
    "wof:placetype":"venue"
},
  "geometry": {"coordinates":[-3.8020660877,43.462059021],"type":"Point"}
}