{
  "type": "Feature",
  "properties": {
    "addr:full":"Calle de Francisco Grandmontagne, 7 Burgos Burgos 09007",
    "addr:housenumber":"7",
    "addr:postcode":"09007",
    "addr:street":"Calle De Francisco Grandmontagne",
    "iso:country":"ES",
    "sg:address":"Calle de Francisco Grandmontagne, 7",
    "sg:city":"Burgos",
    "sg:orig_category":"Frutas, Legumbres Frescas Y Tempranas (al Por Menor)",
    "sg:phone":"+34 947 23 41 90",
    "sg:postcode":"09007",
    "sg:province":"Burgos",
    "wof:name":"Gonzalez Martinez Milagros",
    "wof:placetype":"venue"
},
  "geometry": {"coordinates":[-3.6702485085,42.3514442444],"type":"Point"}
}