{
  "type": "Feature",
  "properties": {
    "addr:full":"Calle de Carretera De Almeria, 33 Adra Almer\u00eda 04770",
    "addr:housenumber":"33",
    "addr:postcode":"04770",
    "addr:street":"Calle De Carretera De Almeria;Almeri\u0301A",
    "iso:country":"ES",
    "sg:address":"Calle de Carretera De Almeria, 33",
    "sg:city":"Adra",
    "sg:orig_category":"Alimentaci\u00d3n General (al Por Mayor)",
    "sg:phone":"+34 950 60 40 49",
    "sg:postcode":"04770",
    "sg:province":"Almer\u00eda",
    "wof:name":"Piensos La Foca S.a.",
    "wof:placetype":"venue"
},
  "geometry": {"coordinates":[-3.0057294369,36.7483558655],"type":"Point"}
}