{
  "type": "Feature",
  "properties": {
    "iso:country":"ES",
    "sg:address":"Calle de De Los Carros, 41",
    "sg:city":"Benavente",
    "sg:orig_category":"Formaci\u00d3n Continuada (variada)",
    "sg:phone":"+34 980 63 21 59",
    "sg:postcode":"49600",
    "sg:province":"Zamora",
    "wof:name":"Fundacion Formacion Y Empleo Castilla Y Leon",
    "wof:placetype":"venue"
},
  "geometry": {"coordinates":[-5.6022672653,41.9902305603],"type":"Point"}
}