{
  "type": "Feature",
  "properties": {
    "addr:full":"Calle de San Roque, 50 Algete Madrid 28110",
    "addr:housenumber":"50",
    "addr:postcode":"28110",
    "addr:street":"Calle De San Roque",
    "iso:country":"ES",
    "sg:address":"Calle de San Roque, 50",
    "sg:city":"Algete",
    "sg:orig_category":"Puertas Autom\u00c1ticas, Puertas De Garaje",
    "sg:phone":"+34 916 28 22 61",
    "sg:postcode":"28110",
    "sg:province":"Madrid",
    "wof:name":"Fernandez Garcia Pilar",
    "wof:placetype":"venue"
},
  "geometry": {"coordinates":[-3.4933769703,40.5970497131],"type":"Point"}
}