{
  "type": "Feature",
  "properties": {
    "addr:full":"Calle de San Francisco, 29 Talavera Reina Toledo 45600",
    "addr:housenumber":"29",
    "addr:postcode":"45600",
    "addr:street":"Calle De San Francisco",
    "iso:country":"ES",
    "sg:address":"Calle de San Francisco, 29",
    "sg:city":"Talavera Reina",
    "sg:orig_category":"Ense\u00d1anza: Idiomas",
    "sg:phone":"+34 925 81 60 08",
    "sg:postcode":"45600",
    "sg:province":"Toledo",
    "wof:name":"Gecesa Gestion De Centros Culturales S.a",
    "wof:placetype":"venue"
},
  "geometry": {"coordinates":[-4.8297219276,39.96144104],"type":"Point"}
}