{
  "type": "Feature",
  "properties": {
    "iso:country":"ES",
    "sg:address":"Pumar, 15",
    "sg:city":"Pumar",
    "sg:orig_category":"Producci\u00d3n, Venta De Productos De Agricultura Biol\u00d3gica",
    "sg:phone":"+34 982 17 06 01",
    "sg:postcode":"27258",
    "sg:province":"Lugo",
    "wof:name":"Cabo Da Vila S.a.t. N 1052 Xuga",
    "wof:placetype":"venue"
},
  "geometry": {"coordinates":[-7.4491767883,43.2154502869],"type":"Point"}
}