{
  "type": "Feature",
  "properties": {
    "iso:country":"ES",
    "sg:address":"Calle de Pintor Stolz, 50",
    "sg:city":"Valencia",
    "sg:orig_category":"Fabricaci\u00d3n, Venta De Cuadros, Accesorios Para Enmarcar",
    "sg:phone":"+34 963 79 94 79",
    "sg:postcode":"46018",
    "sg:province":"Valencia",
    "wof:name":"Miguel Angel Pastor Cuevas Y Maria Jose Marti Sala Cdad",
    "wof:placetype":"venue"
},
  "geometry": {"coordinates":[-0.4016849995,39.4700469971],"type":"Point"}
}