{
  "type": "Feature",
  "properties": {
    "addr:full":"Poli Industrial C/n, 8 Rozas De Madrid Madrid 28230",
    "addr:housenumber":"/ n 8",
    "addr:postcode":"28230",
    "iso:country":"ES",
    "sg:address":"Poli Industrial C/n, 8",
    "sg:city":"Rozas De Madrid",
    "sg:orig_category":"Cristaler\u00cdas",
    "sg:phone":"+34 916 36 19 37",
    "sg:postcode":"28230",
    "sg:province":"Madrid",
    "wof:name":"Antonio Ginestal S.l.",
    "wof:placetype":"venue"
},
  "geometry": {"coordinates":[-3.7003455162,40.4166908264],"type":"Point"}
}