{
  "type": "Feature",
  "properties": {
    "addr:full":"Calle de Oletxe, 25 Usansolo Vizcaya 48960",
    "addr:housenumber":"25",
    "addr:postcode":"48960",
    "addr:street":"Calle De Oletxe",
    "iso:country":"ES",
    "sg:address":"Calle de Oletxe, 25",
    "sg:city":"Usansolo",
    "sg:orig_category":"Fotocopias, Reprograf\u00cda",
    "sg:phone":"+34 944 57 27 85",
    "sg:postcode":"48960",
    "sg:province":"Vizcaya",
    "sg:website":"www.logarkopy.com",
    "wof:name":"Garcia Iglesias Maria Del Pilar",
    "wof:placetype":"venue"
},
  "geometry": {"coordinates":[-2.8187670708,43.217880249],"type":"Point"}
}