{
  "type": "Feature",
  "properties": {
    "iso:country":"ES",
    "sg:address":"Plaz Constitucion, 1",
    "sg:city":"Garbayuela",
    "sg:orig_category":"Administraciones Regionales, Departamentales Y Locales",
    "sg:phone":"+34 924 63 56 92",
    "sg:postcode":"06690",
    "sg:province":"Badajoz",
    "wof:name":"Ayuntamiento De Garbayuela",
    "wof:placetype":"venue"
},
  "geometry": {"coordinates":[-4.999669075,39.0493507385],"type":"Point"}
}