{
  "type": "Feature",
  "properties": {
    "addr:full":"Bo La Venta, 4 Igollo Cantabria 39608",
    "addr:housenumber":"4",
    "addr:postcode":"39608",
    "addr:street":"Bo La Venta",
    "iso:country":"ES",
    "sg:address":"Bo La Venta, 4",
    "sg:city":"Igollo",
    "sg:orig_category":"Promotores Constructores",
    "sg:phone":"+34 942 58 21 21",
    "sg:postcode":"39608",
    "sg:province":"Cantabria",
    "wof:name":"Mar Del Norte Obras Y Reformas S.l.",
    "wof:placetype":"venue"
},
  "geometry": {"coordinates":[-3.8830139637,43.4323272705],"type":"Point"}
}