{
  "type": "Feature",
  "properties": {
    "addr:full":"Calle de Mayor Principal, 27 Palencia Palencia 34001",
    "addr:housenumber":"27",
    "addr:postcode":"34001",
    "addr:street":"Calle De Mayor Principal",
    "iso:country":"ES",
    "sg:address":"Calle de Mayor Principal, 27",
    "sg:city":"Palencia",
    "sg:orig_category":"Asesor\u00cda Sobre Comunicaci\u00d3n De Empresas",
    "sg:phone":"+34 979 74 43 58",
    "sg:postcode":"34001",
    "sg:province":"Palencia",
    "wof:name":"Urraca Asesores S:l",
    "wof:placetype":"venue"
},
  "geometry": {"coordinates":[-4.5392618179,42.010433197],"type":"Point"}
}