{
  "type": "Feature",
  "properties": {
    "addr:full":"Avda Zaragoza (de), 44 Alagon Zaragoza 50630",
    "addr:housenumber":"44",
    "addr:postcode":"50630",
    "addr:street":"Avda Zaragoza De",
    "iso:country":"ES",
    "sg:address":"Avda Zaragoza (de), 44",
    "sg:city":"Alagon",
    "sg:orig_category":"Agencias Y Agentes Comerciales, Representantes",
    "sg:phone":"+34 976 61 23 97",
    "sg:postcode":"50630",
    "sg:province":"Zaragoza",
    "wof:name":"Blas Fernandez Fermin",
    "wof:placetype":"venue"
},
  "geometry": {"coordinates":[-1.1179590225,41.7682189941],"type":"Point"}
}