{
  "type": "Feature",
  "properties": {
    "addr:full":"Cno. La Cuesta, 54 Barranco De Las Lajas Santa Cruz De Tenerife 38355",
    "addr:housenumber":"54",
    "addr:postcode":"38355",
    "addr:street":"Cno. La Cuesta",
    "iso:country":"ES",
    "sg:address":"Cno. La Cuesta, 54",
    "sg:city":"Barranco De Las Lajas",
    "sg:orig_category":"Bazares, Art\u00cdculos De Limpieza Y De Cocina (al Por Menor)",
    "sg:phone":"+34 922 56 70 38",
    "sg:postcode":"38355",
    "sg:province":"Santa Cruz De Tenerife",
    "wof:name":"Pe\u00f1a Arvelo Teofilo",
    "wof:placetype":"venue"
},
  "geometry": {"coordinates":[-16.4059047699,28.4648990631],"type":"Point"}
}