{
  "type": "Feature",
  "properties": {
    "addr:full":"Avda Madrid, 8 Vigo Pontevedra 36204",
    "addr:housenumber":"8",
    "addr:postcode":"36204",
    "addr:street":"Avda Madrid",
    "iso:country":"ES",
    "sg:address":"Avda Madrid, 8",
    "sg:city":"Vigo",
    "sg:orig_category":"Universidades",
    "sg:phone":"+34 986 41 44 98",
    "sg:postcode":"36204",
    "sg:province":"Pontevedra",
    "sg:website":"www.telefonica.net/web/maxisteriovigo",
    "wof:name":"Fundacion Universitaria San Pablo Ceu",
    "wof:placetype":"venue"
},
  "geometry": {"coordinates":[-8.7187232971,42.2279930115],"type":"Point"}
}