{
  "type": "Feature",
  "properties": {
    "addr:full":"Carrer de Industria-barri Maritim (de La), 11 Torredembarra Tarragona 43830",
    "addr:housenumber":"11",
    "addr:postcode":"43830",
    "addr:street":"Carrer De Industria-Barri Maritim De La",
    "iso:country":"ES",
    "sg:address":"Carrer de Industria-barri Maritim (de La), 11",
    "sg:city":"Torredembarra",
    "sg:orig_category":"Tapiceros Y Tapiceros",
    "sg:phone":"+34 977 64 11 60",
    "sg:postcode":"43830",
    "sg:province":"Tarragona",
    "wof:name":"Pijuan Santeugini Angela",
    "wof:placetype":"venue"
},
  "geometry": {"coordinates":[1.395424962,41.1436691284],"type":"Point"}
}