{
  "type": "Feature",
  "properties": {
    "iso:country":"ES",
    "sg:address":"Carrer de Abadia, 10",
    "sg:city":"Galera",
    "sg:orig_category":"Panader\u00cdas, Panader\u00cdas",
    "sg:phone":"+34 977 71 89 86",
    "sg:postcode":"43515",
    "sg:province":"Tarragona",
    "wof:name":"Declere  Roxan",
    "wof:placetype":"venue"
},
  "geometry": {"coordinates":[0.4624710083,40.6807861328],"type":"Point"}
}