{
  "type": "Feature",
  "properties": {
    "iso:country":"ES",
    "sg:address":"Rua Xilgaro, 10",
    "sg:city":"Vigo",
    "sg:orig_category":"\u00d3ptica: Instrumentos (fabricaci\u00d3n)",
    "sg:phone":"+34 986 28 15 62",
    "sg:postcode":"36205",
    "sg:province":"Pontevedra",
    "wof:name":"Prats Optical S.a.",
    "wof:placetype":"venue"
},
  "geometry": {"coordinates":[-8.7072048187,42.2257957458],"type":"Point"}
}