{
  "type": "Feature",
  "properties": {
    "addr:full":"Calle de Saavedra Fajardo, 11 Santa Eulalia Murcia 30001",
    "addr:housenumber":"11",
    "addr:postcode":"30001",
    "addr:street":"Calle De Saavedra Fajardo",
    "iso:country":"ES",
    "sg:address":"Calle de Saavedra Fajardo, 11",
    "sg:city":"Santa Eulalia",
    "sg:orig_category":"Iglesia Cat\u00d3lica",
    "sg:phone":"+34 968 21 86 85",
    "sg:postcode":"30001",
    "sg:province":"Murcia",
    "wof:name":"Obispado De Cartagena",
    "wof:placetype":"venue"
},
  "geometry": {"coordinates":[-1.1272009611,37.9861335754],"type":"Point"}
}