{
  "type": "Feature",
  "properties": {
    "addr:full":"Calle de Duque De Alba, 9 Madrid Madrid 28012",
    "addr:housenumber":"9",
    "addr:postcode":"madrid;28012",
    "addr:street":"Calle De Duque De Alba",
    "iso:country":"ES",
    "sg:address":"Calle de Duque De Alba, 9",
    "sg:city":"Madrid",
    "sg:orig_category":"M\u00c9dicos: Salud P\u00dablica",
    "sg:phone":"+34 913 69 28 66",
    "sg:postcode":"28012",
    "sg:province":"Madrid",
    "wof:name":"Romero Palmeiro Jose",
    "wof:placetype":"venue"
},
  "geometry": {"coordinates":[-3.7063429356,40.4117431641],"type":"Point"}
}