{
  "type": "Feature",
  "properties": {
    "iso:country":"ES",
    "sg:address":"Calle de Prolongacion Corredera, S/n",
    "sg:city":"Baza",
    "sg:orig_category":"Fabricaci\u00d3n De Cortinas Y Visillos",
    "sg:phone":"+34 958 86 01 12",
    "sg:postcode":"18800",
    "sg:province":"Granada",
    "wof:name":"Asensio Bas Ramon",
    "wof:placetype":"venue"
},
  "geometry": {"coordinates":[-2.7689347267,37.4927253723],"type":"Point"}
}