{
  "type": "Feature",
  "properties": {
    "iso:country":"ES",
    "sg:address":"Avda Mateo Bosch, 10",
    "sg:city":"Port D'andratx",
    "sg:orig_category":"Deportes N\u00c1uticos, Acu\u00c1ticos Y Subacu\u00c1ticos: Art\u00cdculos Y Equipo (al Por Menor)",
    "sg:phone":"+34 971 67 16 19",
    "sg:postcode":"07157",
    "sg:province":"Islas Baleares",
    "wof:name":"Ferrer Farradons Roser",
    "wof:placetype":"venue"
},
  "geometry": {"coordinates":[2.38975811,39.5449943542],"type":"Point"}
}