{
  "type": "Feature",
  "properties": {
    "iso:country":"ES",
    "sg:address":"Calle de Primero De Mayo, 7",
    "sg:city":"Binefar",
    "sg:classifiers":[
        {
            "category":"Taxi",
            "type":"Transportation"
        }
    ],
    "sg:phone":"+34 974 42 80 98",
    "sg:postcode":"22500",
    "sg:province":"Huesca",
    "wof:name":"Cosialls Suelves Jose Maria",
    "wof:placetype":"venue"
},
  "geometry": {"coordinates":[0.2935779989,41.8492546082],"type":"Point"}
}