{
  "type": "Feature",
  "properties": {
    "iso:country":"ES",
    "sg:address":"Ebro, 19",
    "sg:city":"Cadrete",
    "sg:orig_category":"Fabricaci\u00d3n De Transformadores, De M\u00c1quinas Giratorias De Peque\u00d1a Y Media Potencia",
    "sg:phone":"+34 976 12 55 14",
    "sg:postcode":"50420",
    "sg:province":"Zaragoza",
    "wof:name":"Esteban Irazabal S.l.",
    "wof:placetype":"venue"
},
  "geometry": {"coordinates":[-0.9647430182,41.5514945984],"type":"Point"}
}