{
  "type": "Feature",
  "properties": {
    "iso:country":"ES",
    "sg:address":"Calle de Santa Teresa, 2",
    "sg:city":"Rafelbunyol",
    "sg:orig_category":"Venta Al Preg\u00d3n",
    "sg:phone":"+34 961 41 01 76",
    "sg:postcode":"46138",
    "sg:province":"Valencia",
    "wof:name":"Sanchez Garcia Maria Josefa",
    "wof:placetype":"venue"
},
  "geometry": {"coordinates":[-0.3328059912,39.5902786255],"type":"Point"}
}