{
  "type": "Feature",
  "properties": {
    "iso:country":"ES",
    "sg:address":"Ctra Nal Trescientos Cuarenta, S/n",
    "sg:city":"Xativa",
    "sg:orig_category":"Frutas Y Legumbres Frescas (al Por Mayor)",
    "sg:phone":"+34 962 27 59 52",
    "sg:postcode":"46800",
    "sg:province":"Valencia",
    "wof:name":"Hermanos Tormo E Hijos S.l.",
    "wof:placetype":"venue"
},
  "geometry": {"coordinates":[-0.5200830102,38.9934272766],"type":"Point"}
}