{
  "type": "Feature",
  "properties": {
    "iso:country":"ES",
    "sg:address":"Calle de Cerrillo, S/n",
    "sg:city":"Agreda",
    "sg:orig_category":"Material Y Herramientas Agr\u00cdcolas",
    "sg:phone":"+34 976 64 76 56",
    "sg:postcode":"42100",
    "sg:province":"Soria",
    "wof:name":"Quilez Calvo Jesus",
    "wof:placetype":"venue"
},
  "geometry": {"coordinates":[-1.92722404,41.8554611206],"type":"Point"}
}