{
  "type": "Feature",
  "properties": {
    "addr:full":"Avda Espa\u00d1a (de), 6 Ubrique C\u00e1diz 11600",
    "addr:housenumber":"6",
    "addr:postcode":"11600",
    "addr:street":"Avda Espan\u0303A De;Ca\u0301Diz",
    "iso:country":"ES",
    "sg:address":"Avda Espa\u00d1a (de), 6",
    "sg:city":"Ubrique",
    "sg:orig_category":"Marroquiner\u00cda (confecci\u00d3n)",
    "sg:phone":"+34 956 46 80 31",
    "sg:postcode":"11600",
    "sg:province":"C\u00e1diz",
    "wof:name":"Pe\u00f1a Fabero Jose Luis",
    "wof:placetype":"venue"
},
  "geometry": {"coordinates":[-5.4460129738,36.6769371033],"type":"Point"}
}