{
  "type": "Feature",
  "properties": {
    "addr:full":"Carrer de Mallorca (de), 11 Tarragona Tarragona 43001",
    "addr:housenumber":"11",
    "addr:postcode":"43001",
    "addr:street":"Carrer De Mallorca De",
    "iso:country":"ES",
    "sg:address":"Carrer de Mallorca (de), 11",
    "sg:city":"Tarragona",
    "sg:orig_category":"Locales Y Clases De Danza",
    "sg:phone":"+34 977 23 07 22",
    "sg:postcode":"43001",
    "sg:province":"Tarragona",
    "wof:name":"Casanova Sanchez Francisca",
    "wof:placetype":"venue"
},
  "geometry": {"coordinates":[1.2463419437,41.1148834229],"type":"Point"}
}