{
  "type": "Feature",
  "properties": {
    "addr:full":"Carr Francesc Ciurana, 2 Girona Girona 17002",
    "addr:housenumber":"2",
    "addr:postcode":"17002",
    "addr:street":"Carr Francesc Ciurana",
    "iso:country":"ES",
    "sg:address":"Carr Francesc Ciurana, 2",
    "sg:city":"Girona",
    "sg:orig_category":"Centros P\u00dablicos De Formaci\u00d3n Profesional Y T\u00c9cnica",
    "sg:phone":"+34 972 20 56 67",
    "sg:postcode":"17002",
    "sg:province":"Girona",
    "sg:website":"www.cafgi.org",
    "wof:name":"Co%egi D'administradors De Finques De Gi",
    "wof:placetype":"venue"
},
  "geometry": {"coordinates":[2.8191599846,41.9774932861],"type":"Point"}
}