{
  "type": "Feature",
  "properties": {
    "iso:country":"ES",
    "sg:address":"Bard Almendros (los), S/n",
    "sg:city":"Estacion",
    "sg:orig_category":"Arenas, Guijarros Y Granulados",
    "sg:phone":"+34 952 42 01 62",
    "sg:postcode":"29580",
    "sg:province":"M\u00e1laga",
    "wof:name":"Aridos Cordero Rio Grande S.l",
    "wof:placetype":"venue"
},
  "geometry": {"coordinates":[-4.6088900566,36.7374916077],"type":"Point"}
}