{
  "type": "Feature",
  "properties": {
    "iso:country":"ES",
    "sg:address":"Calle de Plantio, 2",
    "sg:city":"Estebanez Calzada",
    "sg:orig_category":"Artesan\u00cda",
    "sg:phone":"+34 987 37 76 50",
    "sg:postcode":"24288",
    "sg:province":"Le\u00f3n",
    "wof:name":"Mateos Panero Laurentino",
    "wof:placetype":"venue"
},
  "geometry": {"coordinates":[-5.9367718697,42.4372367859],"type":"Point"}
}