{
  "type": "Feature",
  "properties": {
    "addr:full":"Carr Primer De Maig, 6 Petrer Alicante 03610",
    "addr:housenumber":"6",
    "addr:postcode":"03610",
    "addr:street":"Carr Primer De Maig",
    "iso:country":"ES",
    "sg:address":"Carr Primer De Maig, 6",
    "sg:city":"Petrer",
    "sg:orig_category":"Confecci\u00d3n De Zapatos",
    "sg:phone":"+34 966 95 26 14",
    "sg:postcode":"03610",
    "sg:province":"Alicante",
    "wof:name":"Ruth Shoes S.l.",
    "wof:placetype":"venue"
},
  "geometry": {"coordinates":[-0.7900159955,38.5017280579],"type":"Point"}
}