{
  "type": "Feature",
  "properties": {
    "addr:full":"Avda Jose Gonzalez Forte, 37 Acantilados De Los Gigantes Santa Cruz De Tenerife 38683",
    "addr:housenumber":"37",
    "addr:postcode":"38683",
    "addr:street":"Avda Jose Gonzalez Forte",
    "iso:country":"ES",
    "sg:address":"Avda Jose Gonzalez Forte, 37",
    "sg:city":"Acantilados De Los Gigantes",
    "sg:orig_category":"Cajas De Ahorro",
    "sg:phone":"+34 922 86 10 25",
    "sg:postcode":"38683",
    "sg:province":"Santa Cruz De Tenerife",
    "sg:website":"www.lacaixa.es",
    "wof:name":"Caixa D'estalvis I Pensions De Barcelona",
    "wof:placetype":"venue"
},
  "geometry": {"coordinates":[-16.8412456512,28.2312526703],"type":"Point"}
}