{
  "type": "Feature",
  "properties": {
    "iso:country":"ES",
    "sg:address":"Carrer de Maria Vidal (de), 52",
    "sg:city":"Vilassar De Mar",
    "sg:orig_category":"Peluquer\u00cdas",
    "sg:phone":"+34 937 59 50 61",
    "sg:postcode":"08340",
    "sg:province":"Barcelona",
    "wof:name":"Guillamon Coba Monica",
    "wof:placetype":"venue"
},
  "geometry": {"coordinates":[2.3873999119,41.5018959045],"type":"Point"}
}