{
  "type": "Feature",
  "properties": {
    "addr:full":"Carrer de Tres, 26 Castelldefels Barcelona 08860",
    "addr:housenumber":"26",
    "addr:postcode":"08860",
    "addr:street":"Carrer De Tres",
    "iso:country":"ES",
    "sg:address":"Carrer de Tres, 26",
    "sg:city":"Castelldefels",
    "sg:orig_category":"Promotores Constructores",
    "sg:phone":"+34 936 36 69 29",
    "sg:postcode":"08860",
    "sg:province":"Barcelona",
    "wof:name":"Prec 90 De Promociones Inmobiliarias S.l.",
    "wof:placetype":"venue"
},
  "geometry": {"coordinates":[1.9730050564,41.2685546875],"type":"Point"}
}