{
  "type": "Feature",
  "properties": {
    "iso:country":"ES",
    "sg:address":"G.v. Corts Catalanes, 457",
    "sg:city":"Barcelona",
    "sg:orig_category":"Administradores De Bienes Y Delegados De Comunidades De Propietarios",
    "sg:phone":"+34 934 26 27 41",
    "sg:postcode":"08015",
    "sg:province":"Barcelona",
    "wof:name":"Domingo Pujadas Luis Y Cia Cd",
    "wof:placetype":"venue"
},
  "geometry": {"coordinates":[2.1542870998,41.3793487549],"type":"Point"}
}