{
  "type": "Feature",
  "properties": {
    "addr:full":"Cmno Sevilla (de), 11 Sanlucar De Barrameda C\u00e1diz 11540",
    "addr:housenumber":"11",
    "addr:postcode":"11540",
    "addr:street":"Cmno Sevilla De;Ca\u0301Diz",
    "iso:country":"ES",
    "sg:address":"Cmno Sevilla (de), 11",
    "sg:city":"Sanlucar De Barrameda",
    "sg:orig_category":"Lavado, Limpieza De Veh\u00cdculos",
    "sg:phone":"+34 956 36 59 75",
    "sg:postcode":"11540",
    "sg:province":"C\u00e1diz",
    "wof:name":"Lavado Y Engrase Rayca S.l.",
    "wof:placetype":"venue"
},
  "geometry": {"coordinates":[-6.3446040154,36.7776985168],"type":"Point"}
}