{
  "type": "Feature",
  "properties": {
    "addr:full":"Carrer de Sol, 7 Canonja Tarragona 43110",
    "addr:housenumber":"7",
    "addr:postcode":"43110",
    "addr:street":"Carrer De Sol",
    "iso:country":"ES",
    "sg:address":"Carrer de Sol, 7",
    "sg:city":"Canonja",
    "sg:orig_category":"Reposter\u00cdas",
    "sg:phone":"+34 977 54 74 67",
    "sg:postcode":"43110",
    "sg:province":"Tarragona",
    "wof:name":"Forn De Pa Martin S.l.",
    "wof:placetype":"venue"
},
  "geometry": {"coordinates":[1.1811649799,41.1221694946],"type":"Point"}
}