{
  "type": "Feature",
  "properties": {
    "iso:country":"ES",
    "sg:address":"La Nava, S/n",
    "sg:city":"Alconaba",
    "sg:orig_category":"Empresas De Demolici\u00d3n",
    "sg:phone":"+34 975 18 02 96",
    "sg:postcode":"42133",
    "sg:province":"Soria",
    "wof:name":"Martinez Tierno Eusebio",
    "wof:placetype":"venue"
},
  "geometry": {"coordinates":[-2.3864090443,41.7234153748],"type":"Point"}
}