{
  "type": "Feature",
  "properties": {
    "addr:full":"Carrer de Pareto, 33 Hospitalet Llobregat Barcelona 08902",
    "addr:housenumber":"33",
    "addr:postcode":"08902",
    "addr:street":"Carrer De Pareto",
    "iso:country":"ES",
    "sg:address":"Carrer de Pareto, 33",
    "sg:city":"Hospitalet Llobregat",
    "sg:orig_category":"Frutas Y Legumbres Frescas (al Por Mayor)",
    "sg:phone":"+34 933 31 45 93",
    "sg:postcode":"08902",
    "sg:province":"Barcelona",
    "wof:name":"Ferre Monton Elvira",
    "wof:placetype":"venue"
},
  "geometry": {"coordinates":[2.1276609898,41.3657493591],"type":"Point"}
}