{
  "type": "Feature",
  "properties": {
    "addr:full":"Rua Arcebispo Lago, S/n Vilagarcia Pontevedra 36600",
    "addr:housenumber":"s",
    "addr:postcode":"36600",
    "addr:street":"Rua Arcebispo Lago;/ N",
    "iso:country":"ES",
    "sg:address":"Rua Arcebispo Lago, S/n",
    "sg:city":"Vilagarcia",
    "sg:orig_category":"Molduras, Junquillos, Listones Y Molduras Perforadas",
    "sg:phone":"+34 986 50 17 64",
    "sg:postcode":"36600",
    "sg:province":"Pontevedra",
    "wof:name":"Romero Fernandez Maria Carmen",
    "wof:placetype":"venue"
},
  "geometry": {"coordinates":[-8.7675237656,42.5944786072],"type":"Point"}
}