{
  "type": "Feature",
  "properties": {
    "iso:country":"ES",
    "sg:address":"Calle de Coteros (los), 3",
    "sg:city":"Muriedas",
    "sg:orig_category":"F\u00c1bricas De Ladrillo Y Tejas",
    "sg:phone":"+34 942 25 16 00",
    "sg:postcode":"39600",
    "sg:province":"Cantabria",
    "wof:name":"Tejeria La Covadonga S. A.",
    "wof:placetype":"venue"
},
  "geometry": {"coordinates":[-3.8596580029,43.4302253723],"type":"Point"}
}