{
  "type": "Feature",
  "properties": {
    "addr:full":"Calle de Espoz Y Mina, 7 Zaragoza Zaragoza 50003",
    "addr:housenumber":"7",
    "addr:postcode":"50003",
    "addr:street":"Calle De Espoz Y Mina",
    "iso:country":"ES",
    "sg:address":"Calle de Espoz Y Mina, 7",
    "sg:city":"Zaragoza",
    "sg:orig_category":"Bisuteros (fabricaci\u00d3n, Al Por Mayor)",
    "sg:phone":"+34 976 29 26 72",
    "sg:postcode":"50003",
    "sg:province":"Zaragoza",
    "wof:name":"Armendariz Garcia Angel",
    "wof:placetype":"venue"
},
  "geometry": {"coordinates":[-0.8792855144,41.6551589966],"type":"Point"}
}