{
  "type": "Feature",
  "properties": {
    "addr:full":"Calle de Alonso Carrillo De Albornoz, 12 Malaga M\u00e1laga 29017",
    "addr:housenumber":"12",
    "addr:postcode":"29017",
    "addr:street":"Calle De Alonso Carrillo De Albornoz;Ma\u0301Laga",
    "iso:country":"ES",
    "sg:address":"Calle de Alonso Carrillo De Albornoz, 12",
    "sg:city":"Malaga",
    "sg:orig_category":"Confecci\u00d3n (fabricaci\u00d3n, Al Por Mayor)",
    "sg:phone":"+34 952 29 02 60",
    "sg:postcode":"29017",
    "sg:province":"M\u00e1laga",
    "wof:name":"Lechado Palma Francisca",
    "wof:placetype":"venue"
},
  "geometry": {"coordinates":[-4.3604397774,36.7197685242],"type":"Point"}
}