{
  "type": "Feature",
  "properties": {
    "addr:full":"Calle de Zamora, 37 Villaralbo Zamora 49159",
    "addr:housenumber":"37",
    "addr:postcode":"49159",
    "addr:street":"Calle De Zamora",
    "iso:country":"ES",
    "sg:address":"Calle de Zamora, 37",
    "sg:city":"Villaralbo",
    "sg:orig_category":"Reposter\u00cdas",
    "sg:phone":"+34 980 53 94 15",
    "sg:postcode":"49159",
    "sg:province":"Zamora",
    "wof:name":"Pan El Viso S.l.",
    "wof:placetype":"venue"
},
  "geometry": {"coordinates":[-5.6807589531,41.4919815063],"type":"Point"}
}