{
  "type": "Feature",
  "properties": {
    "iso:country":"ES",
    "sg:address":"Calle de Valle De La Ballestera, 56",
    "sg:city":"Valencia",
    "sg:orig_category":"Muebles",
    "sg:phone":"+34 963 47 96 47",
    "sg:postcode":"46015",
    "sg:province":"Valencia",
    "wof:name":"Tapizados Soria S.l.",
    "wof:placetype":"venue"
},
  "geometry": {"coordinates":[-0.4036029875,39.4787101746],"type":"Point"}
}