{
  "type": "Feature",
  "properties": {
    "iso:country":"ES",
    "sg:address":"Calle de Doctor Blanco Soler, 2",
    "sg:city":"Cordoba",
    "sg:orig_category":"Ense\u00d1anza: Profesiones Art\u00cdsticas",
    "sg:phone":"+34 957 20 31 41",
    "sg:postcode":"14004",
    "sg:province":"C\u00f3rdoba",
    "wof:name":"Lopez Esquivel Luis Manuel",
    "wof:placetype":"venue"
},
  "geometry": {"coordinates":[-4.7846069336,37.8789215088],"type":"Point"}
}