{
  "type": "Feature",
  "properties": {
    "addr:full":"Calle de Barcelona, 14 Vitoria-gasteiz \u00c1lava 01010",
    "addr:housenumber":"14",
    "addr:postcode":"01010",
    "addr:street":"Calle De Barcelona",
    "iso:country":"ES",
    "sg:address":"Calle de Barcelona, 14",
    "sg:city":"Vitoria-gasteiz",
    "sg:orig_category":"Agencias De Viajes",
    "sg:phone":"+34 945 17 94 99",
    "sg:postcode":"01010",
    "sg:province":"\u00c1lava",
    "wof:name":"Viajes Eroski S.a.",
    "wof:placetype":"venue"
},
  "geometry": {"coordinates":[-2.6936678886,42.8666267395],"type":"Point"}
}