{
  "type": "Feature",
  "properties": {
    "addr:full":"Rua Carrua (a), 40 Barco Ourense 32300",
    "addr:housenumber":"40",
    "addr:postcode":"32300",
    "addr:street":"Rua Carrua A",
    "iso:country":"ES",
    "sg:address":"Rua Carrua (a), 40",
    "sg:city":"Barco",
    "sg:orig_category":"Andamiajes Y Escaleras De Mano (fabricaci\u00d3n, Al Por Mayor)",
    "sg:phone":"+34 988 32 64 96",
    "sg:postcode":"32300",
    "sg:province":"Ourense",
    "wof:name":"Andamios Tarpa S.l.",
    "wof:placetype":"venue"
},
  "geometry": {"coordinates":[-6.9783530235,42.4159126282],"type":"Point"}
}