{
  "type": "Feature",
  "properties": {
    "iso:country":"ES",
    "sg:address":"Pase Cornisa La, 4",
    "sg:city":"Palmas De Gran Canaria",
    "sg:orig_category":"Agencias Y Agentes Comerciales, Representantes",
    "sg:phone":"+34 928 25 95 10",
    "sg:postcode":"35011",
    "sg:province":"Las Palmas",
    "wof:name":"Lorencio Chacon Juan Fernando",
    "wof:placetype":"venue"
},
  "geometry": {"coordinates":[-15.4344587326,28.1217498779],"type":"Point"}
}