{
  "type": "Feature",
  "properties": {
    "iso:country":"ES",
    "sg:address":"Calle de Cambil, 11",
    "sg:city":"Baeza",
    "sg:orig_category":"Electrodom\u00c9sticos (fabricaci\u00d3n, Al Por Mayor)",
    "sg:phone":"+34 953 74 16 42",
    "sg:postcode":"23440",
    "sg:province":"Ja\u00e9n",
    "wof:name":"Expodomothica S.l.",
    "wof:placetype":"venue"
},
  "geometry": {"coordinates":[-3.4642026424,37.994052887],"type":"Point"}
}