{
  "type": "Feature",
  "properties": {
    "addr:full":"Calle de Jaume I, 11 Paiporta Valencia 46200",
    "addr:housenumber":"11",
    "addr:postcode":"46200",
    "addr:street":"Calle De Jaume I",
    "iso:country":"ES",
    "sg:address":"Calle de Jaume I, 11",
    "sg:city":"Paiporta",
    "sg:orig_category":"Bancos",
    "sg:phone":"+34 963 97 61 98",
    "sg:postcode":"46200",
    "sg:province":"Valencia",
    "wof:name":"Banco Popular Espa\u00f1ol S.a.",
    "wof:placetype":"venue"
},
  "geometry": {"coordinates":[-0.4158709943,39.4298477173],"type":"Point"}
}