{
  "type": "Feature",
  "properties": {
    "addr:full":"Calle de Dos De Mayo, 83 Elda Alicante 03600",
    "addr:housenumber":"83",
    "addr:postcode":"03600",
    "addr:street":"Calle De Dos;Mayo",
    "iso:country":"ES",
    "sg:address":"Calle de Dos De Mayo, 83",
    "sg:city":"Elda",
    "sg:orig_category":"Molduras, Junquillos, Listones Y Molduras Perforadas",
    "sg:phone":"+34 965 39 55 10",
    "sg:postcode":"03600",
    "sg:province":"Alicante",
    "wof:name":"Garcia Martinez Andres",
    "wof:placetype":"venue"
},
  "geometry": {"coordinates":[-0.7913786173,38.4809494019],"type":"Point"}
}