{
  "type": "Feature",
  "properties": {
    "addr:full":"Ctra. Portocolom, S/n Felanitx Islas Baleares 07200",
    "addr:housenumber":"s",
    "addr:postcode":"07200",
    "addr:street":"Ctra. Portocolom;/ N",
    "iso:country":"ES",
    "sg:address":"Ctra. Portocolom, S/n",
    "sg:city":"Felanitx",
    "sg:orig_category":"Alfarer\u00cda",
    "sg:phone":"+34 971 58 13 23",
    "sg:postcode":"07200",
    "sg:province":"Islas Baleares",
    "wof:name":"Alfareria Soler C.b.",
    "wof:placetype":"venue"
},
  "geometry": {"coordinates":[3.1578874588,39.4644088745],"type":"Point"}
}