{
  "type": "Feature",
  "properties": {
    "addr:full":"Carrer de Luther King, 3 Mataro Barcelona 08304",
    "addr:housenumber":"3",
    "addr:postcode":"08304",
    "addr:street":"Carrer De Luther King",
    "iso:country":"ES",
    "sg:address":"Carrer de Luther King, 3",
    "sg:city":"Mataro",
    "sg:orig_category":"Comercio, Reparaci\u00d3n De Motocicletas, Bicicletas Y Piezas Sueltas",
    "sg:phone":"+34 937 96 49 94",
    "sg:postcode":"08304",
    "sg:province":"Barcelona",
    "wof:name":"Planas Julia Francisco",
    "wof:placetype":"venue"
},
  "geometry": {"coordinates":[2.4499299526,41.5504989624],"type":"Point"}
}