{
  "type": "Feature",
  "properties": {
    "addr:full":"Hnos Imaz, 5 Iru\u00f1a Navarra 31002",
    "addr:housenumber":"5",
    "addr:postcode":"31002",
    "addr:street":"Imaz",
    "iso:country":"ES",
    "sg:address":"Hnos Imaz, 5",
    "sg:city":"Iru\u00f1a",
    "sg:orig_category":"Producci\u00d3n, Distribuci\u00d3n De Gas Butano Y Propano",
    "sg:phone":"+34 948 22 97 43",
    "sg:postcode":"31002",
    "sg:province":"Navarra",
    "sg:website":"www.repsolypf.com",
    "wof:name":"Repsol Ypf S.a.",
    "wof:placetype":"venue"
},
  "geometry": {"coordinates":[-1.6503839493,42.8145446777],"type":"Point"}
}