{
  "type": "Feature",
  "properties": {
    "addr:full":"Pg Fabra I Puig, 311 Barcelona Barcelona 08031",
    "addr:housenumber":"311",
    "addr:postcode":"08031",
    "addr:street":"Pg Fabra I Puig",
    "iso:country":"ES",
    "sg:address":"Pg Fabra I Puig, 311",
    "sg:city":"Barcelona",
    "sg:orig_category":"Transportes Por Carretera: Lotes Completos, Mercanc\u00cdas Diversas",
    "sg:phone":"+34 934 20 61 79",
    "sg:postcode":"08031",
    "sg:province":"Barcelona",
    "wof:name":"Oro 10 S.l.",
    "wof:placetype":"venue"
},
  "geometry": {"coordinates":[2.1680600643,41.4303321838],"type":"Point"}
}