{
  "type": "Feature",
  "properties": {
    "iso:country":"ES",
    "sg:address":"Calle de Mayor, 27",
    "sg:city":"Getxo",
    "sg:orig_category":"Art\u00cdculos De Regalo (al Por Menor)",
    "sg:phone":"+34 944 63 32 04",
    "sg:postcode":"48930",
    "sg:province":"Vizcaya",
    "wof:name":"Adela Perez Salicio",
    "wof:placetype":"venue"
},
  "geometry": {"coordinates":[-3.012409687,43.326335907],"type":"Point"}
}