{
  "type": "Feature",
  "properties": {
    "addr:full":"Aralar, 41 Iru\u00f1a Navarra 31004",
    "addr:housenumber":"41",
    "addr:postcode":"31004",
    "addr:street":"Aralar",
    "iso:country":"ES",
    "sg:address":"Aralar, 41",
    "sg:city":"Iru\u00f1a",
    "sg:orig_category":"Arquitectos",
    "sg:phone":"+34 948 23 90 51",
    "sg:postcode":"31004",
    "sg:province":"Navarra",
    "wof:name":"Urmeneta Fernandez Ramon",
    "wof:placetype":"venue"
},
  "geometry": {"coordinates":[-1.6323180199,42.8109741211],"type":"Point"}
}