{
  "type": "Feature",
  "properties": {
    "iso:country":"ES",
    "sg:address":"Calle de Corredera (la), 29",
    "sg:city":"Villena",
    "sg:orig_category":"Agencias De Viajes",
    "sg:phone":"+34 965 80 61 61",
    "sg:postcode":"03400",
    "sg:province":"Alicante",
    "sg:website":"www.vesp.es",
    "wof:name":"Viajes Espa\u00f1a S.a.",
    "wof:placetype":"venue"
},
  "geometry": {"coordinates":[-0.8646280169,38.6311759949],"type":"Point"}
}