{
  "type": "Feature",
  "properties": {
    "addr:full":"Plaz Ayuntamiento, 9 Valencia Valencia 46002",
    "addr:housenumber":"9",
    "addr:postcode":"46002",
    "addr:street":"Ayuntamiento",
    "iso:country":"ES",
    "sg:address":"Plaz Ayuntamiento, 9",
    "sg:city":"Valencia",
    "sg:orig_category":"Edici\u00d3n De Diarios, Revistas, Boletines",
    "sg:phone":"+34 963 51 56 12",
    "sg:postcode":"46002",
    "sg:province":"Valencia",
    "wof:name":"Editorial Prensa Valenciana S. A.",
    "wof:placetype":"venue"
},
  "geometry": {"coordinates":[-0.3766010106,39.4720497131],"type":"Point"}
}