{
  "type": "Feature",
  "properties": {
    "iso:country":"ES",
    "sg:address":"Calle de Fuente Del Romero, 29",
    "sg:city":"Madrid",
    "sg:orig_category":"Abogados",
    "sg:phone":"+34 913 57 24 03",
    "sg:postcode":"28023",
    "sg:province":"Madrid",
    "wof:name":"Sgad Abogacia Y Defensa S.l.",
    "wof:placetype":"venue"
},
  "geometry": {"coordinates":[-3.7663021088,40.4515266418],"type":"Point"}
}