{
  "type": "Feature",
  "properties": {
    "addr:full":"Pase Santa Maria De La Cabeza, 168 Madrid Madrid 28019",
    "addr:housenumber":"168",
    "addr:postcode":"28019",
    "addr:street":"Cabeza",
    "iso:country":"ES",
    "sg:address":"Pase Santa Maria De La Cabeza, 168",
    "sg:city":"Madrid",
    "sg:orig_category":"Distribuci\u00d3n De Petr\u00d3leo Y Derivados",
    "sg:phone":"+34 915 69 21 98",
    "sg:postcode":"28019",
    "sg:province":"Madrid",
    "wof:name":"Lorusa S.l.cc13-65-69",
    "wof:placetype":"venue"
},
  "geometry": {"coordinates":[-3.7168800831,40.38621521],"type":"Point"}
}