{
  "type": "Feature",
  "properties": {
    "iso:country":"ES",
    "sg:address":"Pl Vila, 41",
    "sg:city":"Martorell",
    "sg:orig_category":"Ense\u00d1anza Variada",
    "sg:phone":"+34 937 75 55 46",
    "sg:postcode":"08760",
    "sg:province":"Barcelona",
    "wof:name":"Centre D'estudis Martorellencs",
    "wof:placetype":"venue"
},
  "geometry": {"coordinates":[1.9311699867,41.4746398926],"type":"Point"}
}