{
  "type": "Feature",
  "properties": {
    "addr:full":"Cmno Real, S/n Xove Lugo 27870",
    "addr:housenumber":"s / n",
    "addr:postcode":"27870",
    "addr:street":"Cmno Real",
    "iso:country":"ES",
    "sg:address":"Cmno Real, S/n",
    "sg:city":"Xove",
    "sg:orig_category":"Asilos De Ancianos. Centros Privados",
    "sg:phone":"+34 982 57 18 08",
    "sg:postcode":"27870",
    "sg:province":"Lugo",
    "wof:name":"Fundacion San Rosendo",
    "wof:placetype":"venue"
},
  "geometry": {"coordinates":[-7.5126390457,43.6849517822],"type":"Point"}
}