{
  "type": "Feature",
  "properties": {
    "iso:country":"ES",
    "sg:address":"Avda Vera, 30",
    "sg:city":"Plasencia",
    "sg:orig_category":"Carnicer\u00cdas, Carnicer\u00cdas",
    "sg:phone":"+34 927 42 24 64",
    "sg:postcode":"10600",
    "sg:province":"C\u00e1ceres",
    "wof:name":"Gonzalez Martin Maria Carmen",
    "wof:placetype":"venue"
},
  "geometry": {"coordinates":[-6.083398819,40.0317382812],"type":"Point"}
}