{
  "type": "Feature",
  "properties": {
    "iso:country":"ES",
    "sg:address":"Calle de Covadonga, 20",
    "sg:city":"Palmas De Gran Canaria",
    "sg:orig_category":"Tapicer\u00cdas",
    "sg:phone":"+34 928 48 10 69",
    "sg:postcode":"35010",
    "sg:province":"Las Palmas",
    "wof:name":"Decoracion Cronotex S.l.",
    "wof:placetype":"venue"
},
  "geometry": {"coordinates":[-15.4462985992,28.1292552948],"type":"Point"}
}