{
  "type": "Feature",
  "properties": {
    "iso:country":"ES",
    "sg:address":"Pase San Vicente, 58",
    "sg:city":"Salamanca",
    "sg:orig_category":"Hospitales",
    "sg:phone":"+34 923 29 12 00",
    "sg:postcode":"37...",
    "sg:province":"Salamanca",
    "wof:name":"Complejo Hospital Universitario Gerencia De Atencion Especializada De Salamanca",
    "wof:placetype":"venue"
},
  "geometry": {"coordinates":[-5.6731262207,40.9639701843],"type":"Point"}
}