{
  "type": "Feature",
  "properties": {
    "iso:country":"ES",
    "sg:address":"Carr Guifre, 674",
    "sg:city":"Badalona",
    "sg:orig_category":"Electricidad: Equipos Industriales, Componentes (fabricaci\u00d3n)",
    "sg:phone":"+34 933 87 98 66",
    "sg:postcode":"08918",
    "sg:province":"Barcelona",
    "wof:name":"L. Giralt Ca\u00f1ellas S.a.",
    "wof:placetype":"venue"
},
  "geometry": {"coordinates":[2.2314660549,41.4354362488],"type":"Point"}
}