{
  "type": "Feature",
  "properties": {
    "addr:full":"Plaz Reyes Huertas, 1 Navalvillar Pela Badajoz 06760",
    "addr:housenumber":"1",
    "addr:postcode":"06760",
    "addr:street":"Plaz;Huertas",
    "iso:country":"ES",
    "sg:address":"Plaz Reyes Huertas, 1",
    "sg:city":"Navalvillar Pela",
    "sg:classifiers":[
        {
            "category":"Autos & Motor Vehicles",
            "subcategory":"Automobile Sales",
            "type":"Retail Goods"
        }
    ],
    "sg:phone":"+34 924 86 03 28",
    "sg:postcode":"06760",
    "sg:province":"Badajoz",
    "wof:name":"Fernandez Rodriguez Juan Isidro",
    "wof:placetype":"venue"
},
  "geometry": {"coordinates":[-5.4656438828,39.0907363892],"type":"Point"}
}