{
  "type": "Feature",
  "properties": {
    "addr:full":"Calle de Marcos, 19 Almeria Almer\u00eda 04003",
    "addr:housenumber":"19",
    "addr:postcode":"04003",
    "addr:street":"Calle De Marcos",
    "iso:country":"ES",
    "sg:address":"Calle de Marcos, 19",
    "sg:city":"Almeria",
    "sg:orig_category":"Ense\u00d1anza Variada",
    "sg:phone":"+34 950 26 51 80",
    "sg:postcode":"04003",
    "sg:province":"Almer\u00eda",
    "wof:name":"Indalestudios S.l.",
    "wof:placetype":"venue"
},
  "geometry": {"coordinates":[-2.4632949829,36.8428535461],"type":"Point"}
}