{
  "type": "Feature",
  "properties": {
    "addr:full":"Calle de Alejo Carpentier, 8 Alcala Henares Madrid 28806",
    "addr:housenumber":"8",
    "addr:postcode":"28806",
    "addr:street":"Calle De Alejo Carpentier",
    "iso:country":"ES",
    "sg:address":"Calle de Alejo Carpentier, 8",
    "sg:city":"Alcala Henares",
    "sg:classifiers":[
        {
            "category":"Professional",
            "subcategory":"Management & Consulting",
            "type":"Services"
        }
    ],
    "sg:phone":"+34 918 83 75 56",
    "sg:postcode":"28806",
    "sg:province":"Madrid",
    "sg:tags":[
        "asesor\u00cda",
        "en",
        "marketing"
    ],
    "sg:website":"www.mkgarena.com",
    "wof:name":"Mkgarena S.l",
    "wof:placetype":"venue"
},
  "geometry": {"coordinates":[-3.3749864101,40.4939002991],"type":"Point"}
}