{
  "type": "Feature",
  "properties": {
    "addr:full":"Avgd Morera, 5 Badalona Barcelona 08915",
    "addr:housenumber":"5",
    "addr:postcode":"08915",
    "addr:street":"Morera",
    "iso:country":"ES",
    "sg:address":"Avgd Morera, 5",
    "sg:city":"Badalona",
    "sg:orig_category":"Electricidad: Instaladores",
    "sg:phone":"+34 934 65 22 00",
    "sg:postcode":"08915",
    "sg:province":"Barcelona",
    "wof:name":"Molinero Aguar Jose",
    "wof:placetype":"venue"
},
  "geometry": {"coordinates":[2.2501969337,41.4638252258],"type":"Point"}
}