{
  "type": "Feature",
  "properties": {
    "addr:full":"Calle de Madrid, 115 Getafe Madrid 28903",
    "addr:housenumber":"115",
    "addr:postcode":"28903",
    "addr:street":"Calle De Madrid",
    "iso:country":"ES",
    "sg:address":"Calle de Madrid, 115",
    "sg:city":"Getafe",
    "sg:orig_category":"Cajas De Ahorro",
    "sg:phone":"+34 916 01 04 36",
    "sg:postcode":"28903",
    "sg:province":"Madrid",
    "wof:name":"Caja De Ahorros Y Monte De Piedad De Navarra",
    "wof:placetype":"venue"
},
  "geometry": {"coordinates":[-3.7266089916,40.3201408386],"type":"Point"}
}