{
  "type": "Feature",
  "properties": {
    "addr:full":"Calle de Sanchez Balderas, 3 Madrid Madrid 28002",
    "addr:housenumber":"3",
    "addr:postcode":"28002",
    "addr:street":"Calle De Sanchez Balderas",
    "iso:country":"ES",
    "sg:address":"Calle de Sanchez Balderas, 3",
    "sg:city":"Madrid",
    "sg:orig_category":"Abogados",
    "sg:phone":"+34 914 13 97 26",
    "sg:postcode":"28002",
    "sg:province":"Madrid",
    "wof:name":"Moreno Lurue\u00f1a Javier",
    "wof:placetype":"venue"
},
  "geometry": {"coordinates":[-3.6622738838,40.4459114075],"type":"Point"}
}