{
  "type": "Feature",
  "properties": {
    "addr:full":"Los Castillos, 13 Moron Frontera Sevilla 41530",
    "addr:housenumber":"13",
    "addr:postcode":"41530",
    "addr:street":"Los Castillos",
    "iso:country":"ES",
    "sg:address":"Los Castillos, 13",
    "sg:city":"Moron Frontera",
    "sg:orig_category":"Reposter\u00cdas",
    "sg:phone":"+34 954 85 15 43",
    "sg:postcode":"41530",
    "sg:province":"Sevilla",
    "wof:name":"Sociedad Cooperativa Limitada Nuevo Pan San Jose De Moron",
    "wof:placetype":"venue"
},
  "geometry": {"coordinates":[-5.4473972321,37.1324653625],"type":"Point"}
}