{
  "type": "Feature",
  "properties": {
    "iso:country":"ES",
    "sg:address":"Calle de Leon Xiii, 16",
    "sg:city":"Sevilla",
    "sg:orig_category":"Asesor\u00cda Fiscal Y Jur\u00cddica",
    "sg:phone":"+34 954 36 70 33",
    "sg:postcode":"41009",
    "sg:province":"Sevilla",
    "wof:name":"Agrupacion 84 S.c.",
    "wof:placetype":"venue"
},
  "geometry": {"coordinates":[-5.9831018448,37.4008636475],"type":"Point"}
}