{
  "type": "Feature",
  "properties": {
    "addr:full":"Calle de Budapest, 110 Torreciega Murcia 30391",
    "addr:housenumber":"110",
    "addr:postcode":"30391",
    "addr:street":"Calle De Budapest",
    "iso:country":"ES",
    "sg:address":"Calle de Budapest, 110",
    "sg:city":"Torreciega",
    "sg:orig_category":"Tapiceros Y Tapiceros",
    "sg:phone":"+34 968 12 36 69",
    "sg:postcode":"30391",
    "sg:province":"Murcia",
    "wof:name":"Tapizados Leva S.l.",
    "wof:placetype":"venue"
},
  "geometry": {"coordinates":[-0.9592049122,37.6236190796],"type":"Point"}
}