{
  "type": "Feature",
  "properties": {
    "iso:country":"ES",
    "sg:address":"Calle de Espa\u00d1olito El, 6",
    "sg:city":"Aviles",
    "sg:orig_category":"Ingenier\u00cda, Centros De Estudios (diversos)",
    "sg:phone":"+34 985 56 80 60",
    "sg:postcode":"33403",
    "sg:province":"Asturias",
    "wof:name":"Estudios Y Proyectos Tecnicos Inas S.l.",
    "wof:placetype":"venue"
},
  "geometry": {"coordinates":[-5.9237408638,43.5347251892],"type":"Point"}
}