{
  "type": "Feature",
  "properties": {
    "addr:full":"Ctra. Segovia-aranda, Km. 0019,0 Pinillos Polendos Segovia 40392",
    "addr:postcode":"40392",
    "addr:street":"Ctra. Segovia-Aranda Km. 0019,0 Pinillos",
    "iso:country":"ES",
    "sg:address":"Ctra. Segovia-aranda, Km. 0019,0",
    "sg:city":"Pinillos Polendos",
    "sg:orig_category":"Charcuter\u00cdas (al Por Menor)",
    "sg:phone":"+34 921 49 70 31",
    "sg:postcode":"40392",
    "sg:province":"Segovia",
    "wof:name":"Embutidos Y Jamones Los Joaquines S.a.",
    "wof:placetype":"venue"
},
  "geometry": {"coordinates":[-4.1089739799,41.0664596558],"type":"Point"}
}