{
  "type": "Feature",
  "properties": {
    "addr:full":"Plaz Olmos (los), S/n Alcublas Valencia 46172",
    "addr:postcode":"46172",
    "addr:street":"Los S / N",
    "iso:country":"ES",
    "sg:address":"Plaz Olmos (los), S/n",
    "sg:city":"Alcublas",
    "sg:orig_category":"Prot\u00c9sicos Dentales",
    "sg:phone":"+34 962 70 40 71",
    "sg:postcode":"46172",
    "sg:province":"Valencia",
    "wof:name":"Clinica Dental Invesdent S.l.",
    "wof:placetype":"venue"
},
  "geometry": {"coordinates":[-0.7022590041,39.7975463867],"type":"Point"}
}