{
  "type": "Feature",
  "properties": {
    "addr:full":"Cami Arbeca (d'), S/n Mollerussa Lleida 25230",
    "addr:postcode":"25230",
    "addr:street":"Arbeca;' S / N",
    "iso:country":"ES",
    "sg:address":"Cami Arbeca (d'), S/n",
    "sg:city":"Mollerussa",
    "sg:orig_category":"Fabricaci\u00d3n De Bebidas No Alcoh\u00d3licas",
    "sg:phone":"+34 973 71 22 62",
    "sg:postcode":"25230",
    "sg:province":"Lleida",
    "wof:name":"Seimex Mollerussa S. A.",
    "wof:placetype":"venue"
},
  "geometry": {"coordinates":[0.8954600096,41.623714447],"type":"Point"}
}