{
  "type": "Feature",
  "properties": {
    "addr:full":"Plaz Ayuntamiento, 1 Capdesaso Huesca 22211",
    "addr:housenumber":"1",
    "addr:postcode":"22211",
    "addr:street":"Ayuntamiento",
    "iso:country":"ES",
    "sg:address":"Plaz Ayuntamiento, 1",
    "sg:city":"Capdesaso",
    "sg:orig_category":"Ense\u00d1anza, Formaci\u00d3n Profesional: Aprendizaje",
    "sg:phone":"+34 974 57 51 57",
    "sg:postcode":"22211",
    "sg:province":"Huesca",
    "wof:name":"Ayuntamiento De Capdesaso",
    "wof:placetype":"venue"
},
  "geometry": {"coordinates":[-0.1854228973,41.8439254761],"type":"Point"}
}