{
  "type": "Feature",
  "properties": {
    "iso:country":"ES",
    "sg:address":"Calle de Ruiz Morote, 8",
    "sg:city":"Manzanares",
    "sg:orig_category":"Asociaciones, Instituciones De Consumidores Y Usuarios",
    "sg:phone":"+34 926 61 25 80",
    "sg:postcode":"13200",
    "sg:province":"Ciudad Real",
    "wof:name":"Asociacion Vecinos Consumidores Y Usuarios Divina Pastora",
    "wof:placetype":"venue"
},
  "geometry": {"coordinates":[-3.3763525486,39.0044670105],"type":"Point"}
}