{
  "type": "Feature",
  "properties": {
    "addr:full":"Avda Baja Navarra, 13 Tafalla Navarra 31300",
    "addr:housenumber":"13",
    "addr:postcode":"31300",
    "addr:street":"Avda Baja Navarra",
    "iso:country":"ES",
    "sg:address":"Avda Baja Navarra, 13",
    "sg:city":"Tafalla",
    "sg:orig_category":"Escayola Y Productos De Escayola (fabricaci\u00d3n, Al Por Mayor)",
    "sg:phone":"+34 948 70 04 97",
    "sg:postcode":"31300",
    "sg:province":"Navarra",
    "wof:name":"Fernandez Villoslada Julian",
    "wof:placetype":"venue"
},
  "geometry": {"coordinates":[-1.6723690033,42.5320396423],"type":"Point"}
}