{
  "type": "Feature",
  "properties": {
    "iso:country":"ES",
    "sg:address":"Avda Constitucion, 3",
    "sg:city":"Casar Caceres",
    "sg:orig_category":"Centros De Coordinaci\u00d3n",
    "sg:phone":"+34 927 29 11 51",
    "sg:postcode":"10190",
    "sg:province":"C\u00e1ceres",
    "wof:name":"Jesus Rey S.l.",
    "wof:placetype":"venue"
},
  "geometry": {"coordinates":[-6.4173731804,39.5614624023],"type":"Point"}
}