{
  "type": "Feature",
  "properties": {
    "iso:country":"ES",
    "sg:address":"Av Francesc Macia, 32",
    "sg:city":"Sabadell",
    "sg:orig_category":"Ropa Para Ni\u00d1os (al Por Menor)",
    "sg:phone":"+34 937 16 52 93",
    "sg:postcode":"08206",
    "sg:province":"Barcelona",
    "sg:website":"www.e-stradivarius.com",
    "wof:name":"Stradivarius Espa\u00d1a S.a.",
    "wof:placetype":"venue"
},
  "geometry": {"coordinates":[2.0983610153,41.5526428223],"type":"Point"}
}