{
  "type": "Feature",
  "properties": {
    "addr:full":"Ctra Soria, 14 Quintanilla Onesimo Valladolid 47350",
    "addr:housenumber":"14",
    "addr:postcode":"47350",
    "addr:street":"Ctra Soria",
    "iso:country":"ES",
    "sg:address":"Ctra Soria, 14",
    "sg:city":"Quintanilla Onesimo",
    "sg:orig_category":"Carnicer\u00cdas, Carnicer\u00cdas",
    "sg:phone":"+34 983 68 00 71",
    "sg:postcode":"47350",
    "sg:province":"Valladolid",
    "wof:name":"Martin Ortega Fernando",
    "wof:placetype":"venue"
},
  "geometry": {"coordinates":[-4.3622441292,41.6264533997],"type":"Point"}
}