{
  "type": "Feature",
  "properties": {
    "addr:full":"Pol Ind La Vara, 4 Valdelacalzada Badajoz 06185",
    "addr:housenumber":"4",
    "addr:postcode":"06185",
    "iso:country":"ES",
    "sg:address":"Pol Ind La Vara, 4",
    "sg:city":"Valdelacalzada",
    "sg:orig_category":"Empresas De Carpinter\u00cda",
    "sg:phone":"+34 924 44 72 40",
    "sg:postcode":"06185",
    "sg:province":"Badajoz",
    "wof:name":"Aluminios Realze A&m C.b",
    "wof:placetype":"venue"
},
  "geometry": {"coordinates":[-6.6999053955,38.8907928467],"type":"Point"}
}