{
  "type": "Feature",
  "properties": {
    "iso:country":"ES",
    "sg:address":"Calle de Casilla, 9",
    "sg:city":"Rua De Valdeorras",
    "sg:orig_category":"Reposter\u00cdas",
    "sg:phone":"+34 988 31 21 27",
    "sg:postcode":"32350",
    "sg:province":"Ourense",
    "wof:name":"Vazquez Velasco Manuel",
    "wof:placetype":"venue"
},
  "geometry": {"coordinates":[-7.1246647835,42.3901329041],"type":"Point"}
}