{
  "type": "Feature",
  "properties": {
    "iso:country":"ES",
    "sg:address":"Carrer de Dositeo Andres (de), 48",
    "sg:city":"S. Carles Rapita",
    "sg:orig_category":"Empresas De Carpinter\u00cda De Madera",
    "sg:phone":"+34 977 74 26 05",
    "sg:postcode":"43540",
    "sg:province":"Tarragona",
    "wof:name":"Falco Pons Josep",
    "wof:placetype":"venue"
},
  "geometry": {"coordinates":[0.5896900296,40.6236000061],"type":"Point"}
}