{
  "type": "Feature",
  "properties": {
    "iso:country":"ES",
    "sg:address":"Calle de Eraso, 36",
    "sg:city":"Madrid",
    "sg:orig_category":"Prot\u00c9sicos Dentales",
    "sg:phone":"+34 913 61 25 99",
    "sg:postcode":"28028",
    "sg:province":"Madrid",
    "wof:name":"De Las Casas Protesis Dental S.a.",
    "wof:placetype":"venue"
},
  "geometry": {"coordinates":[-3.6681311131,40.4354133606],"type":"Point"}
}