{
  "type": "Feature",
  "properties": {
    "addr:full":"Crta Xerta, 1 Jesus Tarragona 43590",
    "addr:housenumber":"1",
    "addr:postcode":"43590",
    "addr:street":"Crta Xerta",
    "iso:country":"ES",
    "sg:address":"Crta Xerta, 1",
    "sg:city":"Jesus",
    "sg:orig_category":"Venta, Montaje De Neum\u00c1ticos",
    "sg:phone":"+34 977 50 46 51",
    "sg:postcode":"43590",
    "sg:province":"Tarragona",
    "wof:name":"Neumaticos Sevil S.a.",
    "wof:placetype":"venue"
},
  "geometry": {"coordinates":[0.5109859705,40.8273468018],"type":"Point"}
}