{
  "type": "Feature",
  "properties": {
    "addr:full":"Calle de Ronda De Altair, 38 Dos Hermanas Sevilla 41700",
    "addr:housenumber":"38",
    "addr:postcode":"41700",
    "addr:street":"Calle De Ronda De Altair",
    "iso:country":"ES",
    "sg:address":"Calle de Ronda De Altair, 38",
    "sg:city":"Dos Hermanas",
    "sg:orig_category":"Fabricaci\u00d3n De Enlosados, Soler\u00cdas",
    "sg:phone":"+34 954 72 34 39",
    "sg:postcode":"41700",
    "sg:province":"Sevilla",
    "wof:name":"Pareja Del Rosal Juan",
    "wof:placetype":"venue"
},
  "geometry": {"coordinates":[-5.9281339645,37.2829055786],"type":"Point"}
}