{
  "type": "Feature",
  "properties": {
    "iso:country":"ES",
    "sg:address":"Avda Jarea (la), 63",
    "sg:city":"Alagon",
    "sg:orig_category":"Comercio, Reparaci\u00d3n De Bicicletas, De Motocicletas, De Accesorios",
    "sg:phone":"+34 976 61 24 51",
    "sg:postcode":"50630",
    "sg:province":"Zaragoza",
    "sg:website":"www.alabike.com",
    "wof:name":"Enguita Gil Jose Miguel",
    "wof:placetype":"venue"
},
  "geometry": {"coordinates":[-1.1267240047,41.768196106],"type":"Point"}
}