{
  "type": "Feature",
  "properties": {
    "iso:country":"ES",
    "sg:address":"Ctra Madrid, Km. 0383,0",
    "sg:city":"Novelda",
    "sg:orig_category":"M\u00c1rmoles, Granitos Y Piedras Naturales",
    "sg:phone":"+34 965 60 33 34",
    "sg:postcode":"03660",
    "sg:province":"Alicante",
    "wof:name":"Europea De Marmoles S.a.",
    "wof:placetype":"venue"
},
  "geometry": {"coordinates":[-0.7718489766,38.389251709],"type":"Point"}
}