{
  "type": "Feature",
  "properties": {
    "addr:full":"Calle de Sable (el), 2 Castro Urdiales Cantabria 39700",
    "addr:housenumber":"2",
    "addr:postcode":"39700",
    "addr:street":"Calle De Sable El",
    "iso:country":"ES",
    "sg:address":"Calle de Sable (el), 2",
    "sg:city":"Castro Urdiales",
    "sg:orig_category":"Chocolater\u00cda Y Exquisiteces",
    "sg:phone":"+34 942 86 07 33",
    "sg:postcode":"39700",
    "sg:province":"Cantabria",
    "sg:website":"www.jamonjamon.net",
    "wof:name":"Martin San Norberto Manuel",
    "wof:placetype":"venue"
},
  "geometry": {"coordinates":[-3.2275590897,43.3896789551],"type":"Point"}
}