{
  "type": "Feature",
  "properties": {
    "iso:country":"ES",
    "sg:address":"Calle de Cueva Del Agua, 59",
    "sg:city":"Belerda",
    "sg:orig_category":"Transportes Por Carretera: Lotes Completos, Mercanc\u00cdas Diversas",
    "sg:phone":"+34 953 71 35 72",
    "sg:postcode":"23489",
    "sg:province":"Ja\u00e9n",
    "wof:name":"Bautista Navarrete Maria Angeles",
    "wof:placetype":"venue"
},
  "geometry": {"coordinates":[-3.032533884,37.7593383789],"type":"Point"}
}