{
  "type": "Feature",
  "properties": {
    "iso:country":"ES",
    "sg:address":"Calle de Mayor, 13",
    "sg:city":"Fuentespalda",
    "sg:orig_category":"Farmacias",
    "sg:phone":"+34 978 85 62 11",
    "sg:postcode":"44587",
    "sg:province":"Teruel",
    "wof:name":"Ballestero Nicolau Maria Angeles",
    "wof:placetype":"venue"
},
  "geometry": {"coordinates":[0.063409999,40.8071594238],"type":"Point"}
}