{
  "type": "Feature",
  "properties": {
    "addr:full":"Plaz Sanchez Cortes, 1 Don Benito Badajoz 06400",
    "addr:housenumber":"1",
    "addr:postcode":"06400",
    "addr:street":"Plaz Sanchez Cortes",
    "iso:country":"ES",
    "sg:address":"Plaz Sanchez Cortes, 1",
    "sg:city":"Don Benito",
    "sg:orig_category":"Peluqueros: De Se\u00d1oras",
    "sg:phone":"+34 924 80 56 49",
    "sg:postcode":"06400",
    "sg:province":"Badajoz",
    "wof:name":"Rodriguez Fernandez Maria Dolores",
    "wof:placetype":"venue"
},
  "geometry": {"coordinates":[-5.8648958206,38.9543991089],"type":"Point"}
}