{
  "type": "Feature",
  "properties": {
    "iso:country":"ES",
    "sg:address":"Calle de Pilar, S/n",
    "sg:city":"Dos-torres",
    "sg:orig_category":"Chapister\u00cda",
    "sg:phone":"+34 957 13 40 33",
    "sg:postcode":"14460",
    "sg:province":"C\u00f3rdoba",
    "wof:name":"Talleres Ruiz C.b",
    "wof:placetype":"venue"
},
  "geometry": {"coordinates":[-4.8962039948,38.4454231262],"type":"Point"}
}