{
  "type": "Feature",
  "properties": {
    "addr:full":"Carrer de Cardenal Cervantes, 12 Tarragona Tarragona 43001",
    "addr:housenumber":"12",
    "addr:postcode":"43001",
    "addr:street":"Carrer De Cardenal Cervantes",
    "iso:country":"ES",
    "sg:address":"Carrer de Cardenal Cervantes, 12",
    "sg:city":"Tarragona",
    "sg:classifiers":[
        {
            "category":"Arts & Performance",
            "subcategory":"Art Gallery",
            "type":"Entertainment"
        }
    ],
    "sg:phone":"+34 977 24 34 89",
    "sg:postcode":"43001",
    "sg:province":"Tarragona",
    "sg:tags":[
        "arte",
        "de",
        "galer\u00cdas"
    ],
    "sg:website":"www.galart.com",
    "wof:name":"Odena Rovira Jaime",
    "wof:placetype":"venue"
},
  "geometry": {"coordinates":[1.2498929501,41.1142807007],"type":"Point"}
}