{
  "type": "Feature",
  "properties": {
    "iso:country":"ES",
    "sg:address":"Calle de Hermanos Barral, 1",
    "sg:city":"Segovia",
    "sg:orig_category":"Arquitectos",
    "sg:phone":"+34 921 46 38 92",
    "sg:postcode":"40001",
    "sg:province":"Segovia",
    "wof:name":"Cabrero Miguelsanz Valeriano",
    "wof:placetype":"venue"
},
  "geometry": {"coordinates":[-4.1201992035,40.9464569092],"type":"Point"}
}