{
  "type": "Feature",
  "properties": {
    "iso:country":"ES",
    "sg:address":"Calle de Sabino Berthelot, 2",
    "sg:city":"Santa Cruz De Tenerife",
    "sg:orig_category":"Abogados",
    "sg:phone":"+34 922 27 54 86",
    "sg:postcode":"38003",
    "sg:province":"Santa Cruz De Tenerife",
    "wof:name":"Afonso Perdomo Pedro Roberto",
    "wof:placetype":"venue"
},
  "geometry": {"coordinates":[-16.2550678253,28.4677257538],"type":"Point"}
}