{
  "type": "Feature",
  "properties": {
    "iso:country":"ES",
    "sg:address":"Calle de Escalante, 201",
    "sg:city":"Valencia",
    "sg:orig_category":"Asociaciones, Organismos Culturales Y Socioeducativos",
    "sg:phone":"+34 963 55 08 04",
    "sg:postcode":"46011",
    "sg:province":"Valencia",
    "wof:name":"Sociedad Musical Poblados Maritimos",
    "wof:placetype":"venue"
},
  "geometry": {"coordinates":[-0.3306219876,39.4700927734],"type":"Point"}
}