{
  "type": "Feature",
  "properties": {
    "addr:full":"Carr Pi, Del, 24 Cala Millor Islas Baleares 07560",
    "addr:housenumber":"24",
    "addr:postcode":"07560",
    "addr:street":"Carr Pi Del;Millor",
    "iso:country":"ES",
    "sg:address":"Carr Pi, Del, 24",
    "sg:city":"Cala Millor",
    "sg:orig_category":"Molduras, Junquillos, Listones Y Molduras Perforadas",
    "sg:phone":"+34 971 58 71 14",
    "sg:postcode":"07560",
    "sg:province":"Islas Baleares",
    "wof:name":"C'an Simo S.a.",
    "wof:placetype":"venue"
},
  "geometry": {"coordinates":[3.3733510971,39.5831985474],"type":"Point"}
}