{
  "type": "Feature",
  "properties": {
    "addr:full":"Plaz Mayor, 1 Esquivias Toledo 45221",
    "addr:housenumber":"1",
    "addr:postcode":"45221",
    "addr:street":"Plaz Mayor",
    "iso:country":"ES",
    "sg:address":"Plaz Mayor, 1",
    "sg:city":"Esquivias",
    "sg:orig_category":"Restaurantes",
    "sg:phone":"+34 925 52 04 67",
    "sg:postcode":"45221",
    "sg:province":"Toledo",
    "wof:name":"Restaurante Deleite S.l.",
    "wof:placetype":"venue"
},
  "geometry": {"coordinates":[-3.7645170689,40.1039199829],"type":"Point"}
}