{
  "type": "Feature",
  "properties": {
    "iso:country":"ES",
    "sg:address":"Calle de La Rioja, 15",
    "sg:city":"Madrid",
    "sg:orig_category":"Agencias Y Agentes Comerciales, Representantes",
    "sg:phone":"+34 917 47 38 15",
    "sg:postcode":"28042",
    "sg:province":"Madrid",
    "wof:name":"Ortiz Segovia Angel",
    "wof:placetype":"venue"
},
  "geometry": {"coordinates":[-3.5874741077,40.4581832886],"type":"Point"}
}