{
  "type": "Feature",
  "properties": {
    "iso:country":"ES",
    "sg:address":"Calle de Olta, 41",
    "sg:city":"Valencia",
    "sg:orig_category":"Hielo Artificial (fabricaci\u00d3n, Distribuci\u00d3n)",
    "sg:phone":"+34 963 73 92 51",
    "sg:postcode":"46006",
    "sg:province":"Valencia",
    "wof:name":"Pico Llinares Josefa",
    "wof:placetype":"venue"
},
  "geometry": {"coordinates":[-0.3756990135,39.4527435303],"type":"Point"}
}