{
  "type": "Feature",
  "properties": {
    "iso:country":"ES",
    "sg:address":"Calle de Sese\u00d1a, 34",
    "sg:city":"Madrid",
    "sg:orig_category":"Ropa Y Accesorios",
    "sg:phone":"+34 915 18 71 46",
    "sg:postcode":"28024",
    "sg:province":"Madrid",
    "wof:name":"Estilo Viuca S.l.",
    "wof:placetype":"venue"
},
  "geometry": {"coordinates":[-3.7648129463,40.3975601196],"type":"Point"}
}