{
  "type": "Feature",
  "properties": {
    "iso:country":"ES",
    "sg:address":"Calle de San Vicente, 8",
    "sg:city":"Javea",
    "sg:orig_category":"Electricidad: Instaladores",
    "sg:phone":"+34 965 79 36 85",
    "sg:postcode":"03730",
    "sg:province":"Alicante",
    "wof:name":"Guillermo Mari Ronda S.l",
    "wof:placetype":"venue"
},
  "geometry": {"coordinates":[0.1590189934,38.7868728638],"type":"Point"}
}