{
  "type": "Feature",
  "properties": {
    "iso:country":"ES",
    "sg:address":"Paseo La Janda, 9",
    "sg:city":"Benalup",
    "sg:orig_category":"Ropa Para Se\u00d1oras Y Caballeros (al Por Menor)",
    "sg:phone":"+34 956 42 44 47",
    "sg:postcode":"11190",
    "sg:province":"C\u00e1diz",
    "wof:name":"Torres Garcia Tomasa",
    "wof:placetype":"venue"
},
  "geometry": {"coordinates":[-5.8117690086,36.3453788757],"type":"Point"}
}