{
  "type": "Feature",
  "properties": {
    "iso:country":"ES",
    "sg:address":"C/ Vicente Blasco Iba\u00d1ez, 19",
    "sg:city":"Elche",
    "sg:orig_category":"Asesor\u00cda Sobre Comunicaci\u00d3n De Empresas",
    "sg:phone":"+34 966 66 06 31",
    "sg:postcode":"03201",
    "sg:province":"Alicante",
    "wof:name":"Vicente Nicolas Y Gomez Consultores S.l.",
    "wof:placetype":"venue"
},
  "geometry": {"coordinates":[-0.7020699978,38.2677116394],"type":"Point"}
}