{
  "type": "Feature",
  "properties": {
    "iso:country":"ES",
    "sg:address":"Bard Majaneque, 17",
    "sg:city":"Majaneque",
    "sg:orig_category":"Limpieza Industrial",
    "sg:phone":"+34 957 32 80 10",
    "sg:postcode":"14193",
    "sg:province":"C\u00f3rdoba",
    "wof:name":"Lavanderia Ind S.nicolas",
    "wof:placetype":"venue"
},
  "geometry": {"coordinates":[-4.8424720764,37.844078064],"type":"Point"}
}