{
  "type": "Feature",
  "properties": {
    "iso:country":"ES",
    "sg:address":"Constitucion, 63",
    "sg:city":"Matallana Torio",
    "sg:orig_category":"Doctores En Medicina",
    "sg:phone":"+34 987 59 10 19",
    "sg:postcode":"24830",
    "sg:province":"Le\u00f3n",
    "wof:name":"Tascon Alvarez Ricardo",
    "wof:placetype":"venue"
},
  "geometry": {"coordinates":[-5.5226550102,42.8463439941],"type":"Point"}
}