{
  "type": "Feature",
  "properties": {
    "addr:full":"Calle de Ntra Sra Del Pilar, 17 Alcala Henares Madrid 28803",
    "addr:housenumber":"17",
    "addr:postcode":"28803",
    "addr:street":"Calle De Ntra Sra Del Pilar",
    "iso:country":"ES",
    "sg:address":"Calle de Ntra Sra Del Pilar, 17",
    "sg:city":"Alcala Henares",
    "sg:orig_category":"Radiocomunicaciones, Telefon\u00cda M\u00d3vil, Radiomensajer\u00cda: Servicios, Comercializaci\u00d3n",
    "sg:phone":"+34 918 82 28 03",
    "sg:postcode":"28803",
    "sg:province":"Madrid",
    "wof:name":"Casta\u00f1on Arce Guillermo Alfonso",
    "wof:placetype":"venue"
},
  "geometry": {"coordinates":[-3.3750500679,40.4718589783],"type":"Point"}
}