{
  "type": "Feature",
  "properties": {
    "iso:country":"ES",
    "sg:address":"Pg Pla\u00c7a Major, 57",
    "sg:city":"Sabadell",
    "sg:orig_category":"Promotores Constructores",
    "sg:phone":"+34 937 25 05 04",
    "sg:postcode":"08201",
    "sg:province":"Barcelona",
    "wof:name":"Jomag S.l.",
    "wof:placetype":"venue"
},
  "geometry": {"coordinates":[2.1086521149,41.5481071472],"type":"Point"}
}