{
  "type": "Feature",
  "properties": {
    "iso:country":"ES",
    "sg:address":"Avda Feria, S/n",
    "sg:city":"Yecla",
    "sg:orig_category":"Guarder\u00cdas",
    "sg:phone":"+34 968 75 28 96",
    "sg:postcode":"30510",
    "sg:province":"Murcia",
    "wof:name":"Ayuntamiento De Yecla-escuela Infantil",
    "wof:placetype":"venue"
},
  "geometry": {"coordinates":[-1.1068265438,38.6161422729],"type":"Point"}
}