{
  "type": "Feature",
  "properties": {
    "addr:full":"Avda Veinticinco De Abril, 56 Icod De Los Vinos Santa Cruz De Tenerife 38430",
    "addr:housenumber":"56",
    "addr:postcode":"38430",
    "addr:street":"Avda Veinticinco De Abril",
    "iso:country":"ES",
    "sg:address":"Avda Veinticinco De Abril, 56",
    "sg:city":"Icod De Los Vinos",
    "sg:orig_category":"Cl\u00cdnicas Dentales",
    "sg:phone":"+34 922 81 41 31",
    "sg:postcode":"38430",
    "sg:province":"Santa Cruz De Tenerife",
    "wof:name":"Morello Subiat Carlos Eduardo",
    "wof:placetype":"venue"
},
  "geometry": {"coordinates":[-16.7136173248,28.3696556091],"type":"Point"}
}