{
  "type": "Feature",
  "properties": {
    "addr:full":"Calle de Teruel, 1 Torrent Valencia 46900",
    "addr:housenumber":"1",
    "addr:postcode":"46900",
    "addr:street":"Calle De Teruel;Valencia",
    "iso:country":"ES",
    "sg:address":"Calle de Teruel, 1",
    "sg:city":"Torrent",
    "sg:orig_category":"Cajas Para Embalar",
    "sg:phone":"+34 961 57 15 63",
    "sg:postcode":"46900",
    "sg:province":"Valencia",
    "wof:name":"Caja Rural De Torrente",
    "wof:placetype":"venue"
},
  "geometry": {"coordinates":[-0.4693950117,39.432559967],"type":"Point"}
}