{
  "type": "Feature",
  "properties": {
    "iso:country":"ES",
    "sg:address":"Calle de Jerez, 6",
    "sg:city":"San Pedro Alcantara",
    "sg:orig_category":"Poller\u00cda Y Caza (al Por Menor)",
    "sg:phone":"+34 952 78 98 89",
    "sg:postcode":"29670",
    "sg:province":"M\u00e1laga",
    "wof:name":"Sanchez Barroso Juan Andres",
    "wof:placetype":"venue"
},
  "geometry": {"coordinates":[-4.9892420769,36.4836540222],"type":"Point"}
}