{
  "type": "Feature",
  "properties": {
    "addr:full":"Carrer de Mar (del), 30 Tarragona Tarragona 43004",
    "addr:postcode":"43004",
    "addr:street":"Carrer De;Del 30",
    "iso:country":"ES",
    "sg:address":"Carrer de Mar (del), 30",
    "sg:city":"Tarragona",
    "sg:orig_category":"Electricidad: Instaladores",
    "sg:phone":"+34 977 22 31 03",
    "sg:postcode":"43004",
    "sg:province":"Tarragona",
    "wof:name":"Ferre Buhigas C.b.",
    "wof:placetype":"venue"
},
  "geometry": {"coordinates":[1.2454570532,41.1109924316],"type":"Point"}
}