{
  "type": "Feature",
  "properties": {
    "iso:country":"ES",
    "sg:address":"Calle de Ancha, 41",
    "sg:city":"Cabezas S. Juan",
    "sg:classifiers":[
        {
            "category":"Autos & Motor Vehicles",
            "subcategory":"Automobile Sales",
            "type":"Retail Goods"
        }
    ],
    "sg:phone":"+34 955 87 10 47",
    "sg:postcode":"41730",
    "sg:province":"Sevilla",
    "wof:name":"Autoescuela Las Cabezas Sociedad Civil",
    "wof:placetype":"venue"
},
  "geometry": {"coordinates":[-5.9369897842,36.9845314026],"type":"Point"}
}