{
  "type": "Feature",
  "properties": {
    "iso:country":"ES",
    "sg:address":"Rbla Rambla, 10",
    "sg:city":"Figueres",
    "sg:orig_category":"Caf\u00c9s, Bares, Cervecer\u00cdas",
    "sg:phone":"+34 972 50 00 50",
    "sg:postcode":"17600",
    "sg:province":"Girona",
    "wof:name":"Hoteles Garcia Genis S.a.",
    "wof:placetype":"venue"
},
  "geometry": {"coordinates":[2.960725069,42.2666473389],"type":"Point"}
}