{
  "type": "Feature",
  "properties": {
    "addr:full":"Ctra Ba\u00d1os De Arteijo, S/n Coru\u00d1a La Coru\u00f1a 15008",
    "addr:housenumber":"s / n",
    "addr:postcode":"15008",
    "addr:street":"Ctra Ban\u0303Os De Arteijo;La Corun\u0303A",
    "iso:country":"ES",
    "sg:address":"Ctra Ba\u00d1os De Arteijo, S/n",
    "sg:city":"Coru\u00d1a",
    "sg:orig_category":"Frutas Y Legumbres Frescas (al Por Mayor)",
    "sg:phone":"+34 981 29 61 58",
    "sg:postcode":"15008",
    "sg:province":"La Coru\u00f1a",
    "wof:name":"Novoa Losada Emilio",
    "wof:placetype":"venue"
},
  "geometry": {"coordinates":[-8.4512443542,43.3434753418],"type":"Point"}
}