{
  "type": "Feature",
  "properties": {
    "addr:full":"Calle de Milan, 29 Alcala Henares Madrid 28805",
    "addr:housenumber":"29",
    "addr:postcode":"28805",
    "addr:street":"Calle De Milan",
    "iso:country":"ES",
    "sg:address":"Calle de Milan, 29",
    "sg:city":"Alcala Henares",
    "sg:orig_category":"Quincaller\u00cda (al Por Menor)",
    "sg:phone":"+34 912 96 59 36",
    "sg:postcode":"28805",
    "sg:province":"Madrid",
    "wof:name":"Daoiz Y Velarde 7 S.l.u.",
    "wof:placetype":"venue"
},
  "geometry": {"coordinates":[-3.3373160362,40.4975585938],"type":"Point"}
}