{
  "type": "Feature",
  "properties": {
    "iso:country":"ES",
    "sg:address":"Calle de Benavente, S/n",
    "sg:city":"Navas San Juan",
    "sg:orig_category":"Asociaciones, Organismos Culturales Y Socioeducativos",
    "sg:phone":"+34 953 68 74 52",
    "sg:postcode":"23240",
    "sg:province":"Ja\u00e9n",
    "wof:name":"Asociacion Cultural De Mujeres Stella",
    "wof:placetype":"venue"
},
  "geometry": {"coordinates":[-3.3158445358,38.1819763184],"type":"Point"}
}