{
  "type": "Feature",
  "properties": {
    "addr:full":"Carr Sant Joan Baptista, 13 Figueres Girona 17600",
    "addr:housenumber":"13",
    "addr:postcode":"17600",
    "addr:street":"Carr Sant Joan Baptista",
    "iso:country":"ES",
    "sg:address":"Carr Sant Joan Baptista, 13",
    "sg:city":"Figueres",
    "sg:orig_category":"Agencias Y Agentes Comerciales, Representantes",
    "sg:phone":"+34 972 50 33 53",
    "sg:postcode":"17600",
    "sg:province":"Girona",
    "wof:name":"Camps Oliveras Martin",
    "wof:placetype":"venue"
},
  "geometry": {"coordinates":[2.9652850628,42.2671051025],"type":"Point"}
}