{
  "type": "Feature",
  "properties": {
    "addr:full":"Calle de General Espartero, 45 Daimiel Ciudad Real 13250",
    "addr:housenumber":"45",
    "addr:postcode":"13250",
    "addr:street":"Calle De General Espartero",
    "iso:country":"ES",
    "sg:address":"Calle de General Espartero, 45",
    "sg:city":"Daimiel",
    "sg:orig_category":"Ingenier\u00cda, Centros De Estudios (diversos)",
    "sg:phone":"+34 926 85 26 82",
    "sg:postcode":"13250",
    "sg:province":"Ciudad Real",
    "wof:name":"Fisac Rodriguez Angel",
    "wof:placetype":"venue"
},
  "geometry": {"coordinates":[-3.6128089428,39.0687408447],"type":"Point"}
}