{
  "type": "Feature",
  "properties": {
    "addr:full":"Rbra De Deustu, 85 Bilbao Vizcaya 48014",
    "addr:housenumber":"85",
    "addr:postcode":"48014",
    "addr:street":"Deustu",
    "iso:country":"ES",
    "sg:address":"Rbra De Deustu, 85",
    "sg:city":"Bilbao",
    "sg:orig_category":"Fabricaci\u00d3n De Juegos Y Juguetes",
    "sg:phone":"+34 944 47 31 06",
    "sg:postcode":"48014",
    "sg:province":"Vizcaya",
    "wof:name":"Trenes Recreativos S.l.",
    "wof:placetype":"venue"
},
  "geometry": {"coordinates":[-2.9639599323,43.2705841064],"type":"Point"}
}