{
  "type": "Feature",
  "properties": {
    "addr:full":"Carr Industria, 413 Badalona Barcelona 08918",
    "addr:housenumber":"413",
    "addr:postcode":"08918",
    "addr:street":"Carr Industria",
    "iso:country":"ES",
    "sg:address":"Carr Industria, 413",
    "sg:city":"Badalona",
    "sg:orig_category":"Restaurantes",
    "sg:phone":"+34 934 60 89 89",
    "sg:postcode":"08918",
    "sg:province":"Barcelona",
    "wof:name":"Alifres S.a.",
    "wof:placetype":"venue"
},
  "geometry": {"coordinates":[2.2374653816,41.4361763],"type":"Point"}
}