{
  "type": "Feature",
  "properties": {
    "iso:country":"ES",
    "sg:address":"Calle de Tres De Noviembre, 26",
    "sg:city":"Santander",
    "sg:orig_category":"Fabricaci\u00d3n De Sobres, Bolsas Y Fundas",
    "sg:phone":"+34 942 37 66 66",
    "sg:postcode":"39010",
    "sg:province":"Cantabria",
    "wof:name":"Bolsos Esther S.l.",
    "wof:placetype":"venue"
},
  "geometry": {"coordinates":[-3.8185610771,43.4599685669],"type":"Point"}
}