{
  "type": "Feature",
  "properties": {
    "iso:country":"ES",
    "sg:address":"Calle de Mayor, 13",
    "sg:city":"Mejorada Campo",
    "sg:orig_category":"Ropa De Hogar (al Por Menor)",
    "sg:phone":"+34 916 79 34 60",
    "sg:postcode":"28840",
    "sg:province":"Madrid",
    "wof:name":"Gonzalez Fernandez Juan",
    "wof:placetype":"venue"
},
  "geometry": {"coordinates":[-3.4859549999,40.3973274231],"type":"Point"}
}