{
  "type": "Feature",
  "properties": {
    "addr:full":"Avda Pio Xii, 2 Valencia Valencia 46009",
    "addr:housenumber":"2",
    "addr:postcode":"46009",
    "addr:street":"Avda Pio Xii",
    "iso:country":"ES",
    "sg:address":"Avda Pio Xii, 2",
    "sg:city":"Valencia",
    "sg:orig_category":"Ropa Para Se\u00d1oras Y Caballeros (al Por Menor)",
    "sg:phone":"+34 963 48 75 89",
    "sg:postcode":"46009",
    "sg:province":"Valencia",
    "wof:name":"Cortefiel S.a.",
    "wof:placetype":"venue"
},
  "geometry": {"coordinates":[-0.3910419941,39.4790344238],"type":"Point"}
}