{
  "type": "Feature",
  "properties": {
    "iso:country":"ES",
    "sg:address":"Plaz Constitucion (de La), 13",
    "sg:city":"Arrecife",
    "sg:orig_category":"Refiner\u00cdas De Petr\u00d3leo",
    "sg:phone":"+34 928 80 32 43",
    "sg:postcode":"35500",
    "sg:province":"Las Palmas",
    "wof:name":"Hijos De Rafael Ramirez C.b.",
    "wof:placetype":"venue"
},
  "geometry": {"coordinates":[-13.5497016907,28.9588470459],"type":"Point"}
}