{
  "type": "Feature",
  "properties": {
    "iso:country":"ES",
    "sg:address":"Plaz Alcalde Domingo Torres, 3",
    "sg:city":"Valencia",
    "sg:orig_category":"Institutos De Belleza",
    "sg:phone":"+34 963 93 48 37",
    "sg:postcode":"46020",
    "sg:province":"Valencia",
    "wof:name":"Salon De Belleza Europa S.l.",
    "wof:placetype":"venue"
},
  "geometry": {"coordinates":[-0.3579879999,39.4818382263],"type":"Point"}
}