{
  "type": "Feature",
  "properties": {
    "addr:full":"Calle de Alpizar, 73 Palma Condado Huelva 21700",
    "addr:housenumber":"73",
    "addr:postcode":"21700",
    "addr:street":"Calle De Alpizar",
    "iso:country":"ES",
    "sg:address":"Calle de Alpizar, 73",
    "sg:city":"Palma Condado",
    "sg:orig_category":"Contenedores (mercanc\u00cdas)",
    "sg:phone":"+34 959 40 03 80",
    "sg:postcode":"21700",
    "sg:province":"Huelva",
    "wof:name":"Jose Avila E Hijos S.l.",
    "wof:placetype":"venue"
},
  "geometry": {"coordinates":[-6.5458040237,37.3912239075],"type":"Point"}
}