{
  "type": "Feature",
  "properties": {
    "addr:full":"Calle de Vi\u00d1a Vieja, 17 Llodio \u00c1lava 01400",
    "addr:housenumber":"17",
    "addr:postcode":"01400",
    "addr:street":"Calle De Vin\u0303A Vieja",
    "iso:country":"ES",
    "sg:address":"Calle de Vi\u00d1a Vieja, 17",
    "sg:city":"Llodio",
    "sg:orig_category":"Asistencia Domiciliaria",
    "sg:phone":"+34 946 72 59 67",
    "sg:postcode":"01400",
    "sg:province":"\u00c1lava",
    "wof:name":"Guztiontzat S.l.",
    "wof:placetype":"venue"
},
  "geometry": {"coordinates":[-2.9621920586,43.1451416016],"type":"Point"}
}