{
  "type": "Feature",
  "properties": {
    "iso:country":"ES",
    "sg:address":"Pol Ind Ipertegi Ii, 55",
    "sg:city":"Orkoien",
    "sg:orig_category":"Herramientas Manuales (fabricaci\u00d3n, Al Por Mayor)",
    "sg:phone":"+34 948 32 16 16",
    "sg:postcode":"31160",
    "sg:province":"Navarra",
    "sg:website":"www.samnet.biz",
    "wof:name":"Sam Herramientas S.l.",
    "wof:placetype":"venue"
},
  "geometry": {"coordinates":[-1.7060990334,42.8219032288],"type":"Point"}
}