{
  "type": "Feature",
  "properties": {
    "addr:full":"Pase Estacion (la), 23 Jaen Ja\u00e9n 23008",
    "addr:postcode":"23008",
    "addr:street":"Jae\u0301N",
    "iso:country":"ES",
    "sg:address":"Pase Estacion (la), 23",
    "sg:city":"Jaen",
    "sg:orig_category":"Procuradores",
    "sg:phone":"+34 953 25 60 09",
    "sg:postcode":"23008",
    "sg:province":"Ja\u00e9n",
    "wof:name":"Mendez Vilchez Jesus",
    "wof:placetype":"venue"
},
  "geometry": {"coordinates":[-3.7888469696,37.7734642029],"type":"Point"}
}