{
  "type": "Feature",
  "properties": {
    "iso:country":"ES",
    "sg:address":"Calle de Castillo, 100",
    "sg:city":"Hornachuelos",
    "sg:orig_category":"Art\u00cdculos Funerarios (al Por Menor)",
    "sg:phone":"+34 957 64 00 05",
    "sg:postcode":"14740",
    "sg:province":"C\u00f3rdoba",
    "wof:name":"Mediadora Cordobesa De Seguros C.b.",
    "wof:placetype":"venue"
},
  "geometry": {"coordinates":[-5.2463388443,37.8339805603],"type":"Point"}
}