{
  "type": "Feature",
  "properties": {
    "addr:full":"Ctra Pont De Vilomara, 33 Manresa Barcelona 08241",
    "addr:housenumber":"33",
    "addr:postcode":"08241",
    "addr:street":"Ctra Pont De Vilomara",
    "iso:country":"ES",
    "sg:address":"Ctra Pont De Vilomara, 33",
    "sg:city":"Manresa",
    "sg:orig_category":"Agentes, Concesionarios Y Sucursales De Veh\u00cdculos",
    "sg:phone":"+34 938 78 42 00",
    "sg:postcode":"08241",
    "sg:province":"Barcelona",
    "sg:website":"www.eurocotxes.com",
    "wof:name":"Eurocotxes S.a.",
    "wof:placetype":"venue"
},
  "geometry": {"coordinates":[1.8337340355,41.7285423279],"type":"Point"}
}