{
  "type": "Feature",
  "properties": {
    "iso:country":"ES",
    "sg:address":"Calle de Losas (las), 6",
    "sg:city":"Oyon-oion",
    "sg:orig_category":"Estancos",
    "sg:phone":"+34 945 60 10 06",
    "sg:postcode":"01320",
    "sg:province":"\u00c1lava",
    "wof:name":"Saez Valencia Maria Isabel",
    "wof:placetype":"venue"
},
  "geometry": {"coordinates":[-2.4353768826,42.5022087097],"type":"Point"}
}