{
  "type": "Feature",
  "properties": {
    "iso:country":"ES",
    "sg:address":"Carr L'alguer, 3",
    "sg:city":"Lleida",
    "sg:orig_category":"Servicios De Telecomunicaciones",
    "sg:phone":"+34 973 22 81 69",
    "sg:postcode":"25005",
    "sg:province":"Lleida",
    "wof:name":"Jazz Telecom S.a.",
    "wof:placetype":"venue"
},
  "geometry": {"coordinates":[0.6346560121,41.6235580444],"type":"Point"}
}