{
  "type": "Feature",
  "properties": {
    "iso:country":"ES",
    "sg:address":"Calle de Ciruela, 1",
    "sg:city":"Madrid",
    "sg:orig_category":"Quincaller\u00cda (al Por Menor)",
    "sg:phone":"+34 915 08 55 33",
    "sg:postcode":"28044",
    "sg:province":"Madrid",
    "wof:name":"Ferreteria Industrial Simarsan S.l.",
    "wof:placetype":"venue"
},
  "geometry": {"coordinates":[-3.7494559288,40.3714981079],"type":"Point"}
}