{
  "type": "Feature",
  "properties": {
    "addr:full":"Gandara, S/n Gandara La Coru\u00f1a 15145",
    "addr:housenumber":"s",
    "addr:postcode":"15145",
    "addr:street":"/ N;Corun\u0303A",
    "iso:country":"ES",
    "sg:address":"Gandara, S/n",
    "sg:city":"Gandara",
    "sg:orig_category":"Ferreter\u00cda (diversos)",
    "sg:phone":"+34 981 60 52 34",
    "sg:postcode":"15145",
    "sg:province":"La Coru\u00f1a",
    "wof:name":"Hierros A\u00f1on S.a.",
    "wof:placetype":"venue"
},
  "geometry": {"coordinates":[-8.5750217438,43.1730537415],"type":"Point"}
}