{
  "type": "Feature",
  "properties": {
    "addr:full":"Carrer de Casp, 116 Barcelona Barcelona 08013",
    "addr:housenumber":"116",
    "addr:postcode":"08013",
    "addr:street":"Carrer De Casp",
    "iso:country":"ES",
    "sg:address":"Carrer de Casp, 116",
    "sg:city":"Barcelona",
    "sg:orig_category":"Centros Empresariales",
    "sg:phone":"+34 932 65 22 27",
    "sg:postcode":"08013",
    "sg:province":"Barcelona",
    "sg:website":"www.cazorla-assl.com",
    "wof:name":"Cazorla Asesoramiento Y Servicios S.l.",
    "wof:placetype":"venue"
},
  "geometry": {"coordinates":[2.1783380508,41.3949127197],"type":"Point"}
}