{
  "type": "Feature",
  "properties": {
    "iso:country":"ES",
    "sg:address":"Plaz Ramon Y Cajal, 1",
    "sg:city":"Villarrobledo",
    "sg:orig_category":"Centros De Documentaci\u00d3n Y Archivo",
    "sg:phone":"+34 967 14 51 93",
    "sg:postcode":"02600",
    "sg:province":"Albacete",
    "wof:name":"Ayuntamiento De Villarrobledo",
    "wof:placetype":"venue"
},
  "geometry": {"coordinates":[-2.6044707298,39.2640533447],"type":"Point"}
}