{
  "type": "Feature",
  "properties": {
    "iso:country":"ES",
    "sg:address":"Calle de Mayor, S/n",
    "sg:city":"Hoya",
    "sg:orig_category":"Centros De Educaci\u00d3n Especial",
    "sg:phone":"+34 968 48 18 33",
    "sg:postcode":"30816",
    "sg:province":"Murcia",
    "wof:name":"Colegio Publico Juan Navarro Garcia",
    "wof:placetype":"venue"
},
  "geometry": {"coordinates":[-1.5710790157,37.7104187012],"type":"Point"}
}