{
  "type": "Feature",
  "properties": {
    "iso:country":"ES",
    "sg:address":"Calle de Lepanto, 7",
    "sg:city":"Solana",
    "sg:classifiers":[
        {
            "category":"Autos & Motor Vehicles",
            "subcategory":"Automobile Sales",
            "type":"Retail Goods"
        }
    ],
    "sg:phone":"+34 926 63 14 08",
    "sg:postcode":"13240",
    "sg:province":"Ciudad Real",
    "wof:name":"Moreno Orozco Fausto",
    "wof:placetype":"venue"
},
  "geometry": {"coordinates":[-3.2320189476,38.9411811829],"type":"Point"}
}