{
  "type": "Feature",
  "properties": {
    "iso:country":"ES",
    "sg:address":"Calle de Cerrillo, 24",
    "sg:city":"Villanueva Algaidas",
    "sg:classifiers":[
        {
            "category":"Taxi",
            "type":"Transportation"
        }
    ],
    "sg:phone":"+34 952 74 33 11",
    "sg:postcode":"29310",
    "sg:province":"M\u00e1laga",
    "wof:name":"Roldan Moreno Pablo",
    "wof:placetype":"venue"
},
  "geometry": {"coordinates":[-4.4518904686,37.1877937317],"type":"Point"}
}