{
  "type": "Feature",
  "properties": {
    "addr:full":"Joan Iturralde Kalea, 3 Beasain Guip\u00f9zcoa 20200",
    "addr:housenumber":"3",
    "addr:postcode":"20200",
    "addr:street":"Joan Iturralde Kalea;Guipu\u0300Zcoa",
    "iso:country":"ES",
    "sg:address":"Joan Iturralde Kalea, 3",
    "sg:city":"Beasain",
    "sg:orig_category":"Asesor\u00cda Sobre Comunicaci\u00d3n De Empresas",
    "sg:phone":"+34 943 88 98 78",
    "sg:postcode":"20200",
    "sg:province":"Guip\u00f9zcoa",
    "wof:name":"Asesoria Biga S.l.",
    "wof:placetype":"venue"
},
  "geometry": {"coordinates":[-2.1969559193,43.0461540222],"type":"Point"}
}