{
  "type": "Feature",
  "properties": {
    "addr:full":"Av Catalunya, 6 Deltebre Tarragona 43580",
    "addr:housenumber":"6",
    "addr:postcode":"43580",
    "addr:street":"Av Catalunya",
    "iso:country":"ES",
    "sg:address":"Av Catalunya, 6",
    "sg:city":"Deltebre",
    "sg:orig_category":"Peluquer\u00cdas, Peluquer\u00cda Mixta",
    "sg:phone":"+34 977 48 98 94",
    "sg:postcode":"43580",
    "sg:province":"Tarragona",
    "wof:name":"Paga Bo Sandra",
    "wof:placetype":"venue"
},
  "geometry": {"coordinates":[0.7229449749,40.7188110352],"type":"Point"}
}