{
  "type": "Feature",
  "properties": {
    "addr:full":"C/ Sabadell, 24 Alcoi Alicante 03804",
    "addr:housenumber":"24",
    "addr:postcode":"03804",
    "addr:street":"C / Sabadell",
    "iso:country":"ES",
    "sg:address":"C/ Sabadell, 24",
    "sg:city":"Alcoi",
    "sg:orig_category":"Fabricaci\u00d3n De Art\u00cdculos Para Papeler\u00cdas",
    "sg:phone":"+34 965 52 17 96",
    "sg:postcode":"03804",
    "sg:province":"Alicante",
    "wof:name":"Papeleria Universal C.b.",
    "wof:placetype":"venue"
},
  "geometry": {"coordinates":[-0.4668799937,38.7084579468],"type":"Point"}
}