{
  "type": "Feature",
  "properties": {
    "iso:country":"ES",
    "sg:address":"Calle de Cuesta Del Hospital Bajo, 41",
    "sg:city":"Santurtzi",
    "sg:orig_category":"Reparaciones Y Remolcado De Veh\u00cdculos",
    "sg:phone":"+34 944 83 70 41",
    "sg:postcode":"48980",
    "sg:province":"Vizcaya",
    "wof:name":"Manuel Rodriguez Vazquez",
    "wof:placetype":"venue"
},
  "geometry": {"coordinates":[-3.0389695168,43.3289833069],"type":"Point"}
}