{
  "type": "Feature",
  "properties": {
    "iso:country":"ES",
    "sg:address":"Aurrera Manzana 1, 61",
    "sg:city":"Valle Trapaga",
    "sg:orig_category":"Fabricaci\u00d3n De Bicicletas, Motocicletas Y Piezas Sueltas",
    "sg:phone":"+34 944 72 32 05",
    "sg:postcode":"48510",
    "sg:province":"Vizcaya",
    "wof:name":"Alejandro Echevarria Cano (motos Alex Sport)",
    "wof:placetype":"venue"
},
  "geometry": {"coordinates":[-3.0355479717,43.3031082153],"type":"Point"}
}