{
  "type": "Feature",
  "properties": {
    "iso:country":"ES",
    "sg:address":"Arrecife, 8",
    "sg:city":"Cangas",
    "sg:orig_category":"Fabricaci\u00d3n, Reparaci\u00d3n Y Mantenimiento De Construcciones Navales Y Fluviales",
    "sg:phone":"+34 986 30 09 78",
    "sg:postcode":"36940",
    "sg:province":"Pontevedra",
    "wof:name":"Central De Efectos Navales Cangas S.l.",
    "wof:placetype":"venue"
},
  "geometry": {"coordinates":[-8.7863054276,42.257850647],"type":"Point"}
}