{
  "type": "Feature",
  "properties": {
    "iso:country":"ES",
    "sg:address":"Av Constitucion, S/n",
    "sg:city":"Orba",
    "sg:orig_category":"Artesan\u00cda",
    "sg:phone":"+34 965 58 39 15",
    "sg:postcode":"03790",
    "sg:province":"Alicante",
    "wof:name":"La Bolata",
    "wof:placetype":"venue"
},
  "geometry": {"coordinates":[-0.0657640025,38.7804756165],"type":"Point"}
}