{
  "type": "Feature",
  "properties": {
    "addr:full":"Pase Alameda De Osuna, 75 Madrid Madrid 28042",
    "addr:housenumber":"75",
    "addr:postcode":"madrid;28042",
    "addr:street":"Alameda;Osuna",
    "iso:country":"ES",
    "sg:address":"Pase Alameda De Osuna, 75",
    "sg:city":"Madrid",
    "sg:orig_category":"Piscinas, Accesorios, Suministros (fabricaci\u00d3n, Al Por Mayor)",
    "sg:phone":"+34 913 29 10 60",
    "sg:postcode":"28042",
    "sg:province":"Madrid",
    "wof:name":"Mancomunidad Manzana N Cdad",
    "wof:placetype":"venue"
},
  "geometry": {"coordinates":[-3.5903410912,40.4577636719],"type":"Point"}
}