{
  "type": "Feature",
  "properties": {
    "iso:country":"ES",
    "sg:address":"Ctra Mig, 191",
    "sg:city":"Hospitalet Llobregat",
    "sg:orig_category":"Electricidad: Instaladores",
    "sg:phone":"+34 933 35 64 74",
    "sg:postcode":"08907",
    "sg:province":"Barcelona",
    "sg:website":"www.espelsa.es",
    "wof:name":"Especialidades Electricas S.a.",
    "wof:placetype":"venue"
},
  "geometry": {"coordinates":[2.1013100147,41.3527145386],"type":"Point"}
}