{
  "type": "Feature",
  "properties": {
    "iso:country":"ES",
    "sg:address":"Pase Baron De Adzaneta, 9",
    "sg:city":"Ramales Victoria",
    "sg:orig_category":"Cajas De Ahorro",
    "sg:phone":"+34 942 64 60 24",
    "sg:postcode":"39800",
    "sg:province":"Cantabria",
    "sg:website":"www.cajacantabria.com",
    "wof:name":"Cableuropa",
    "wof:placetype":"venue"
},
  "geometry": {"coordinates":[-3.442991972,43.2613754272],"type":"Point"}
}