{
  "type": "Feature",
  "properties": {
    "iso:country":"ES",
    "sg:address":"Carrer de Blas Infante (de), 6",
    "sg:city":"Montornes Centre",
    "sg:orig_category":"Venta, Alquiler De V\u00cddeo",
    "sg:phone":"+34 935 68 60 37",
    "sg:postcode":"08170",
    "sg:province":"Barcelona",
    "wof:name":"Vila Requena David",
    "wof:placetype":"venue"
},
  "geometry": {"coordinates":[2.2636899948,41.5415153503],"type":"Point"}
}