{
  "type": "Feature",
  "properties": {
    "addr:full":"Calle de Almendros, Los, 15 Calpe Alicante 03710",
    "addr:housenumber":"15",
    "addr:postcode":"03710",
    "addr:street":"Calle De Almendros Los",
    "iso:country":"ES",
    "sg:address":"Calle de Almendros, Los, 15",
    "sg:city":"Calpe",
    "sg:orig_category":"Bordado, Marcado A Medida",
    "sg:phone":"+34 965 83 50 43",
    "sg:postcode":"03710",
    "sg:province":"Alicante",
    "wof:name":"Perez Moreno Milagrosa",
    "wof:placetype":"venue"
},
  "geometry": {"coordinates":[0.0465146005,38.6449813843],"type":"Point"}
}