{
  "type": "Feature",
  "properties": {
    "iso:country":"ES",
    "sg:address":"Calle de Esperanto, 19",
    "sg:city":"Malaga",
    "sg:orig_category":"M\u00c9dicos: Oftalmolog\u00cda",
    "sg:phone":"+34 952 22 14 92",
    "sg:postcode":"29007",
    "sg:province":"M\u00e1laga",
    "wof:name":"Monta\u00f1ez Rittwagen Francisco Javier",
    "wof:placetype":"venue"
},
  "geometry": {"coordinates":[-4.4337625504,36.7190628052],"type":"Point"}
}