{
  "type": "Feature",
  "properties": {
    "iso:country":"ES",
    "sg:address":"Calle de Rey Juan Carlos I, 71",
    "sg:city":"Elda",
    "sg:orig_category":"Muebles, Minoristas",
    "sg:phone":"+34 966 98 22 25",
    "sg:postcode":"03600",
    "sg:province":"Alicante",
    "wof:name":"Martinez Jover Salvador",
    "wof:placetype":"venue"
},
  "geometry": {"coordinates":[-0.788639009,38.4794616699],"type":"Point"}
}