{
  "type": "Feature",
  "properties": {
    "iso:country":"ES",
    "sg:address":"Calle de Princesa, 28",
    "sg:city":"Madrid",
    "sg:orig_category":"Asesor\u00cda Fiscal Y Jur\u00cddica",
    "sg:phone":"+34 915 42 25 70",
    "sg:postcode":"28008",
    "sg:province":"Madrid",
    "wof:name":"Grupo Tecnico Asesor S.l.",
    "wof:placetype":"venue"
},
  "geometry": {"coordinates":[-3.7141499519,40.4278106689],"type":"Point"}
}