{
  "type": "Feature",
  "properties": {
    "iso:country":"ES",
    "sg:address":"Luga Carrus Poligono Industrial, 68",
    "sg:city":"Elche",
    "sg:orig_category":"Metalurgia",
    "sg:phone":"+34 965 46 88 09",
    "sg:postcode":"03291",
    "sg:province":"Alicante",
    "wof:name":"Revesmetal Elche S.l.",
    "wof:placetype":"venue"
},
  "geometry": {"coordinates":[-0.6860749722,38.299079895],"type":"Point"}
}