{
  "type": "Feature",
  "properties": {
    "iso:country":"ES",
    "sg:address":"Ingen Grrez Segura, 1",
    "sg:city":"Baza",
    "sg:orig_category":"Molduras, Junquillos, Listones Y Molduras Perforadas",
    "sg:phone":"+34 958 86 07 99",
    "sg:postcode":"18800",
    "sg:province":"Granada",
    "wof:name":"Simon Troyano Blas",
    "wof:placetype":"venue"
},
  "geometry": {"coordinates":[-2.7754399776,37.4931526184],"type":"Point"}
}