{
  "type": "Feature",
  "properties": {
    "addr:full":"C/ Jaume Ii, 12 Manacor Islas Baleares 07500",
    "addr:housenumber":"12",
    "addr:postcode":"07500",
    "addr:street":"C / Jaume Ii",
    "iso:country":"ES",
    "sg:address":"C/ Jaume Ii, 12",
    "sg:city":"Manacor",
    "sg:orig_category":"Cajas De Ahorro",
    "sg:phone":"+34 971 84 32 85",
    "sg:postcode":"07500",
    "sg:province":"Islas Baleares",
    "sg:website":"www.colonya.es",
    "wof:name":"Caja De Ahorros De Pollensa-colonya",
    "wof:placetype":"venue"
},
  "geometry": {"coordinates":[3.227793932,39.5640945435],"type":"Point"}
}