{
  "type": "Feature",
  "properties": {
    "addr:full":"Calle de Arenas Del Rey, 262 Madrid Madrid 28041",
    "addr:housenumber":"262",
    "addr:postcode":"28041",
    "addr:street":"Calle De Arenas Del Rey",
    "iso:country":"ES",
    "sg:address":"Calle de Arenas Del Rey, 262",
    "sg:city":"Madrid",
    "sg:orig_category":"Carnicer\u00cdas, Carnicer\u00cdas",
    "sg:phone":"+34 913 17 04 43",
    "sg:postcode":"28041",
    "sg:province":"Madrid",
    "wof:name":"Lopez Rubio Jose Antonio",
    "wof:placetype":"venue"
},
  "geometry": {"coordinates":[-3.7009029388,40.3652381897],"type":"Point"}
}