{
  "type": "Feature",
  "properties": {
    "iso:country":"ES",
    "sg:address":"Calle de San Ramon, 33",
    "sg:city":"Churriana Vega",
    "sg:orig_category":"Publicidad (soportes Y Gesti\u00d3n)",
    "sg:phone":"+34 958 55 34 24",
    "sg:postcode":"18194",
    "sg:province":"Granada",
    "wof:name":"Promociones Molinero Y Ariza S.l.",
    "wof:placetype":"venue"
},
  "geometry": {"coordinates":[-3.6773679256,37.1503562927],"type":"Point"}
}