{
  "type": "Feature",
  "properties": {
    "addr:full":"Avda Madrid (de), 21 Almeria Almer\u00eda 04007",
    "addr:housenumber":"21",
    "addr:postcode":"04007",
    "addr:street":"Avda Madrid De",
    "iso:country":"ES",
    "sg:address":"Avda Madrid (de), 21",
    "sg:city":"Almeria",
    "sg:orig_category":"Cajas Para Embalar",
    "sg:phone":"+34 950 15 18 60",
    "sg:postcode":"04007",
    "sg:province":"Almer\u00eda",
    "sg:website":"www.cajamar.es",
    "wof:name":"Cajamar",
    "wof:placetype":"venue"
},
  "geometry": {"coordinates":[-2.4491569996,36.8327484131],"type":"Point"}
}