{
  "type": "Feature",
  "properties": {
    "addr:full":"Calle de Anselmo Fernandez, 21 Requena Valencia 46340",
    "addr:housenumber":"21",
    "addr:postcode":"46340",
    "addr:street":"Calle De Anselmo Fernandez",
    "iso:country":"ES",
    "sg:address":"Calle de Anselmo Fernandez, 21",
    "sg:city":"Requena",
    "sg:orig_category":"Reposter\u00cdas",
    "sg:phone":"+34 962 30 12 72",
    "sg:postcode":"46340",
    "sg:province":"Valencia",
    "wof:name":"Latorre Perez Luis",
    "wof:placetype":"venue"
},
  "geometry": {"coordinates":[-1.097684145,39.4876785278],"type":"Point"}
}