{
  "type": "Feature",
  "properties": {
    "addr:full":"Nueve Mil Diez, 5 Las Palmas Las Palmas 35017",
    "addr:housenumber":"5",
    "addr:postcode":"35017",
    "addr:street":"Las",
    "iso:country":"ES",
    "sg:address":"Nueve Mil Diez, 5",
    "sg:city":"Las Palmas",
    "sg:orig_category":"Ense\u00d1ante, Direcci\u00d3n",
    "sg:phone":"+34 928 35 46 56",
    "sg:postcode":"35017",
    "sg:province":"Las Palmas",
    "wof:name":"Reina Griessler Alfredo",
    "wof:placetype":"venue"
},
  "geometry": {"coordinates":[-15.4912500381,28.061000824],"type":"Point"}
}