{
  "type": "Feature",
  "properties": {
    "addr:full":"Carrer de Moli Del Llobet, 15 Vic Barcelona 08500",
    "addr:housenumber":"15",
    "addr:postcode":"08500",
    "addr:street":"Carrer De Moli Del Llobet",
    "iso:country":"ES",
    "sg:address":"Carrer de Moli Del Llobet, 15",
    "sg:city":"Vic",
    "sg:orig_category":"Fibras De Vidrio",
    "sg:phone":"+34 938 89 14 10",
    "sg:postcode":"08500",
    "sg:province":"Barcelona",
    "wof:name":"Poliester Germans Pelegrina S.cv.",
    "wof:placetype":"venue"
},
  "geometry": {"coordinates":[2.277987957,41.9494552612],"type":"Point"}
}