{
  "type": "Feature",
  "properties": {
    "addr:full":"Avda Soldevilla Vazquez, 26 Posadas C\u00f3rdoba 14730",
    "addr:housenumber":"26;co\u0301rdoba",
    "addr:postcode":"14730",
    "addr:street":"Avda Soldevilla Vazquez",
    "iso:country":"ES",
    "sg:address":"Avda Soldevilla Vazquez, 26",
    "sg:city":"Posadas",
    "sg:orig_category":"Empresas De Desmonte",
    "sg:phone":"+34 957 63 04 53",
    "sg:postcode":"14730",
    "sg:province":"C\u00f3rdoba",
    "wof:name":"Fernandez Moreno Manuel Justo",
    "wof:placetype":"venue"
},
  "geometry": {"coordinates":[-97.78224945069999,45.7040786743],"type":"Point"}
}