{
  "type": "Feature",
  "properties": {
    "addr:full":"Rua Leiteiras (das), 15 Lugo Lugo 27003",
    "addr:housenumber":"15",
    "addr:postcode":"27003",
    "addr:street":"Rua Leiteiras Das",
    "iso:country":"ES",
    "sg:address":"Rua Leiteiras (das), 15",
    "sg:city":"Lugo",
    "sg:orig_category":"Reposter\u00cdas",
    "sg:phone":"+34 982 20 71 00",
    "sg:postcode":"27003",
    "sg:province":"Lugo",
    "wof:name":"Huelmo Lugo S.l.",
    "wof:placetype":"venue"
},
  "geometry": {"coordinates":[-7.5637841225,43.0511207581],"type":"Point"}
}