{
  "type": "Feature",
  "properties": {
    "iso:country":"ES",
    "sg:address":"Calle de Verge De La Murta, 7",
    "sg:city":"Alzira",
    "sg:orig_category":"Reposter\u00cdas",
    "sg:phone":"+34 962 41 36 41",
    "sg:postcode":"46600",
    "sg:province":"Valencia",
    "wof:name":"Panaderia Bolleria Lopez S.l.",
    "wof:placetype":"venue"
},
  "geometry": {"coordinates":[-0.4315919876,39.1513633728],"type":"Point"}
}