{
  "type": "Feature",
  "properties": {
    "addr:full":"Calle de Zubileta, 12 Barakaldo Vizcaya 48903",
    "addr:housenumber":"12",
    "addr:postcode":"48903",
    "addr:street":"Calle De Zubileta",
    "iso:country":"ES",
    "sg:address":"Calle de Zubileta, 12",
    "sg:city":"Barakaldo",
    "sg:orig_category":"Ambulancias",
    "sg:phone":"+34 946 55 92 74",
    "sg:postcode":"48903",
    "sg:province":"Vizcaya",
    "wof:name":"Servicio Asistido Medico Urgente, S.l.",
    "wof:placetype":"venue"
},
  "geometry": {"coordinates":[-2.9756829739,43.2675743103],"type":"Point"}
}