{
  "type": "Feature",
  "properties": {
    "iso:country":"ES",
    "sg:address":"Via Europa, 101",
    "sg:city":"Mataro",
    "sg:orig_category":"Laboratorios Y Cl\u00cdnicas Veterinarias",
    "sg:phone":"+34 937 41 44 24",
    "sg:postcode":"08303",
    "sg:province":"Barcelona",
    "wof:name":"Velazquez Forero Ruben Dario",
    "wof:placetype":"venue"
},
  "geometry": {"coordinates":[2.4324650764,41.5442733765],"type":"Point"}
}