{
  "type": "Feature",
  "properties": {
    "addr:full":"Avda Alvaro Cunqueiro, 15 Foz Lugo 27780",
    "addr:housenumber":"15",
    "addr:postcode":"27780",
    "addr:street":"Avda Alvaro Cunqueiro",
    "iso:country":"ES",
    "sg:address":"Avda Alvaro Cunqueiro, 15",
    "sg:city":"Foz",
    "sg:orig_category":"Centros De Coordinaci\u00d3n",
    "sg:phone":"+34 982 13 30 22",
    "sg:postcode":"27780",
    "sg:province":"Lugo",
    "wof:name":"Gestoria Fernandez S.l.",
    "wof:placetype":"venue"
},
  "geometry": {"coordinates":[-7.2595944405,43.5680427551],"type":"Point"}
}