{
  "type": "Feature",
  "properties": {
    "iso:country":"ES",
    "sg:address":"Avda Madrid, 71",
    "sg:city":"Sotillo Adrada",
    "sg:orig_category":"Inmobiliaria (agencias)",
    "sg:phone":"+34 918 66 02 20",
    "sg:postcode":"05420",
    "sg:province":"\u00c1vila",
    "wof:name":"Saugar Arenas Jose Maria",
    "wof:placetype":"venue"
},
  "geometry": {"coordinates":[-4.5862369537,40.293674469],"type":"Point"}
}