{
  "type": "Feature",
  "properties": {
    "addr:full":"Calle de Colon, 24 Alacant Alicante 03001",
    "addr:housenumber":"24",
    "addr:postcode":"03001",
    "addr:street":"Calle De Colon",
    "iso:country":"ES",
    "sg:address":"Calle de Colon, 24",
    "sg:city":"Alacant",
    "sg:orig_category":"Negocio De Materiales De Construcci\u00d3n",
    "sg:phone":"+34 965 20 26 22",
    "sg:postcode":"03001",
    "sg:province":"Alicante",
    "wof:name":"Ibaleba\u00f1o S.l.",
    "wof:placetype":"venue"
},
  "geometry": {"coordinates":[-0.4888041019,38.344417572],"type":"Point"}
}