{
  "type": "Feature",
  "properties": {
    "addr:full":"Avda Castelao, 17 Muros La Coru\u00f1a 15250",
    "addr:housenumber":"17",
    "addr:postcode":"15250",
    "addr:street":"Avda Castelao;La Corun\u0303A",
    "iso:country":"ES",
    "sg:address":"Avda Castelao, 17",
    "sg:city":"Muros",
    "sg:orig_category":"Molduras, Junquillos, Listones Y Molduras Perforadas",
    "sg:phone":"+34 981 76 21 93",
    "sg:postcode":"15250",
    "sg:province":"La Coru\u00f1a",
    "wof:name":"Ramos Castelo Jesus",
    "wof:placetype":"venue"
},
  "geometry": {"coordinates":[-9.0582809448,42.7753257751],"type":"Point"}
}