{
  "type": "Feature",
  "properties": {
    "addr:full":"Ctra Constanti, Km. 0001,1 Reus Tarragona 43206",
    "addr:postcode":"43206",
    "addr:street":"Ctra Constanti Km. 0001,1",
    "iso:country":"ES",
    "sg:address":"Ctra Constanti, Km. 0001,1",
    "sg:city":"Reus",
    "sg:orig_category":"Ingenier\u00cda, Centros De Estudios (diversos)",
    "sg:phone":"+34 977 75 36 67",
    "sg:postcode":"43206",
    "sg:province":"Tarragona",
    "wof:name":"Compa\u00f1ia De Construcciones Y Obras Publicas Balsells S.a.",
    "wof:placetype":"venue"
},
  "geometry": {"coordinates":[1.122887969,41.1599006653],"type":"Point"}
}