{
  "type": "Feature",
  "properties": {
    "addr:full":"Calle de Pintor Manuel Maldonado, 13 Granada Granada 18007",
    "addr:housenumber":"13",
    "addr:postcode":"18007",
    "addr:street":"Calle De Pintor Manuel Maldonado",
    "iso:country":"ES",
    "sg:address":"Calle de Pintor Manuel Maldonado, 13",
    "sg:city":"Granada",
    "sg:orig_category":"Librer\u00cdas",
    "sg:phone":"+34 958 81 97 60",
    "sg:postcode":"18007",
    "sg:province":"Granada",
    "wof:name":"Franco Gallardo Leonardo",
    "wof:placetype":"venue"
},
  "geometry": {"coordinates":[-3.5963089466,37.157283783],"type":"Point"}
}