{
  "type": "Feature",
  "properties": {
    "addr:full":"Calle de Barrenkale, 3 Mutriku Guip\u00f9zcoa 20830",
    "addr:housenumber":"3",
    "addr:postcode":"20830",
    "addr:street":"Calle De Barrenkale;Guipu\u0300Zcoa",
    "iso:country":"ES",
    "sg:address":"Calle de Barrenkale, 3",
    "sg:city":"Mutriku",
    "sg:orig_category":"Abogados",
    "sg:phone":"+34 943 60 30 91",
    "sg:postcode":"20830",
    "sg:province":"Guip\u00f9zcoa",
    "wof:name":"Churruca Iriondo Maria Teresa",
    "wof:placetype":"venue"
},
  "geometry": {"coordinates":[-2.3859820366,43.3067779541],"type":"Point"}
}