{
  "type": "Feature",
  "properties": {
    "addr:full":"Pla\u00c7 Major, 3 Consell Islas Baleares 07330",
    "addr:postcode":"07330",
    "iso:country":"ES",
    "sg:address":"Pla\u00c7 Major, 3",
    "sg:city":"Consell",
    "sg:orig_category":"Ense\u00d1anza, Formaci\u00d3n Profesional: Aprendizaje",
    "sg:phone":"+34 971 62 20 95",
    "sg:postcode":"07330",
    "sg:province":"Islas Baleares",
    "wof:name":"Ajuntament De Consell",
    "wof:placetype":"venue"
},
  "geometry": {"coordinates":[2.8228123188,39.6640625],"type":"Point"}
}