{
  "type": "Feature",
  "properties": {
    "addr:full":"Calle de Antonio Lopez Aguado, 12 Madrid Madrid 28029",
    "addr:housenumber":"12",
    "addr:postcode":"madrid;28029",
    "addr:street":"Calle De Antonio Lopez Aguado",
    "iso:country":"ES",
    "sg:address":"Calle de Antonio Lopez Aguado, 12",
    "sg:city":"Madrid",
    "sg:orig_category":"Inversiones",
    "sg:phone":"+34 913 14 70 99",
    "sg:postcode":"28029",
    "sg:province":"Madrid",
    "wof:name":"Invasa Inversiones Y Valores S.a.",
    "wof:placetype":"venue"
},
  "geometry": {"coordinates":[-3.7008032799,40.4825134277],"type":"Point"}
}