{
  "type": "Feature",
  "properties": {
    "iso:country":"ES",
    "sg:address":"Av Comunitat Valenciana, 7",
    "sg:city":"Monovar",
    "sg:orig_category":"Serrer\u00cdas De Madera",
    "sg:phone":"+34 965 47 05 89",
    "sg:postcode":"03640",
    "sg:province":"Alicante",
    "wof:name":"Lopez Vidal Jose",
    "wof:placetype":"venue"
},
  "geometry": {"coordinates":[-0.8399189711,38.4356842041],"type":"Point"}
}