{
  "type": "Feature",
  "properties": {
    "iso:country":"ES",
    "sg:address":"Calle de San Juan, 24",
    "sg:city":"Burgos",
    "sg:orig_category":"Filatelia",
    "sg:phone":"+34 947 20 01 08",
    "sg:postcode":"09004",
    "sg:province":"Burgos",
    "wof:name":"Basco Del Rio Jaime",
    "wof:placetype":"venue"
},
  "geometry": {"coordinates":[-3.6983931065,42.3426208496],"type":"Point"}
}