{
  "type": "Feature",
  "properties": {
    "iso:country":"ES",
    "sg:address":"Calle de Magdalena (la), 31",
    "sg:city":"Colindres",
    "sg:orig_category":"Empresas De Portes Y Mensajer\u00cda",
    "sg:phone":"+34 942 65 01 16",
    "sg:postcode":"39750",
    "sg:province":"Cantabria",
    "wof:name":"Piqueres Martinez Antonio",
    "wof:placetype":"venue"
},
  "geometry": {"coordinates":[-3.4492189884,43.3955345154],"type":"Point"}
}