{
  "type": "Feature",
  "properties": {
    "addr:full":"Calle de San Jose, 16 Socuellamos Ciudad Real 13630",
    "addr:housenumber":"16",
    "addr:postcode":"13630",
    "addr:street":"Calle De San",
    "iso:country":"ES",
    "sg:address":"Calle de San Jose, 16",
    "sg:city":"Socuellamos",
    "sg:orig_category":"Empresas De Carpinter\u00cda De Madera",
    "sg:phone":"+34 926 53 05 34",
    "sg:postcode":"13630",
    "sg:province":"Ciudad Real",
    "wof:name":"Ruiz Moya Ignacio",
    "wof:placetype":"venue"
},
  "geometry": {"coordinates":[-2.7987089157,39.2814216614],"type":"Point"}
}