{
  "type": "Feature",
  "properties": {
    "addr:full":"Ptge De Vintro, 3 Barcelona Barcelona 08026",
    "addr:housenumber":"3",
    "addr:postcode":"08026",
    "addr:street":"Ptge De Vintro",
    "iso:country":"ES",
    "sg:address":"Ptge De Vintro, 3",
    "sg:city":"Barcelona",
    "sg:orig_category":"Filtros Y Elementos Filtradores",
    "sg:phone":"+34 932 65 64 00",
    "sg:postcode":"08026",
    "sg:province":"Barcelona",
    "wof:name":"Barnafiltros S.l.",
    "wof:placetype":"venue"
},
  "geometry": {"coordinates":[2.1857819557,41.4065704346],"type":"Point"}
}