{
  "type": "Feature",
  "properties": {
    "iso:country":"ES",
    "sg:address":"Carrer de Rossello (de), 14",
    "sg:city":"Tortosa",
    "sg:orig_category":"Perfumer\u00cda Y Cosm\u00c9tica (fabricaci\u00d3n, Al Por Mayor)",
    "sg:phone":"+34 977 51 09 85",
    "sg:postcode":"43500",
    "sg:province":"Tarragona",
    "wof:name":"Productos Jamsol S.a.",
    "wof:placetype":"venue"
},
  "geometry": {"coordinates":[0.5209529996,40.8068466187],"type":"Point"}
}