{
  "type": "Feature",
  "properties": {
    "iso:country":"ES",
    "sg:address":"Pg Blay, 2",
    "sg:city":"Olot",
    "sg:orig_category":"Asociaciones, Organismos Culturales Y Socioeducativos",
    "sg:phone":"+34 972 26 38 28",
    "sg:postcode":"17800",
    "sg:province":"Girona",
    "wof:name":"Fomento Actividades Deportivas Culturales",
    "wof:placetype":"venue"
},
  "geometry": {"coordinates":[2.4874999523,42.1824188232],"type":"Point"}
}