{
  "type": "Feature",
  "properties": {
    "iso:country":"ES",
    "sg:address":"Rua Pe\u00d1a Trevinca, 44",
    "sg:city":"Ourense",
    "sg:orig_category":"Molduras, Junquillos, Listones Y Molduras Perforadas",
    "sg:phone":"+34 988 24 26 70",
    "sg:postcode":"32005",
    "sg:province":"Ourense",
    "wof:name":"Alvar Rua Serafin",
    "wof:placetype":"venue"
},
  "geometry": {"coordinates":[-7.8618192673,42.3310050964],"type":"Point"}
}