{
  "type": "Feature",
  "properties": {
    "addr:full":"Carrer de Agramunt, 15 Barcelona Barcelona 08023",
    "addr:housenumber":"15",
    "addr:postcode":"08023",
    "addr:street":"Carrer De Agramunt",
    "iso:country":"ES",
    "sg:address":"Carrer de Agramunt, 15",
    "sg:city":"Barcelona",
    "sg:orig_category":"Reposter\u00cdas",
    "sg:phone":"+34 934 17 25 76",
    "sg:postcode":"08023",
    "sg:province":"Barcelona",
    "wof:name":"Forn Lavi Manel S.l.",
    "wof:placetype":"venue"
},
  "geometry": {"coordinates":[2.1461770535,41.4094543457],"type":"Point"}
}