{
  "type": "Feature",
  "properties": {
    "iso:country":"ES",
    "sg:address":"Calle de Oso (el), S/n",
    "sg:city":"Riocabado",
    "sg:orig_category":"Agricultores, Agricultores",
    "sg:phone":"+34 920 24 03 68",
    "sg:postcode":"05164",
    "sg:province":"\u00c1vila",
    "wof:name":"Herrero Verdugo Socoop",
    "wof:placetype":"venue"
},
  "geometry": {"coordinates":[-4.8033618927,40.8321151733],"type":"Point"}
}