{
  "type": "Feature",
  "properties": {
    "addr:full":"Calle de Tajo (del), 3 Mejorada Campo Madrid 28840",
    "addr:housenumber":"3",
    "addr:postcode":"28840",
    "addr:street":"Calle De Tajo Del",
    "iso:country":"ES",
    "sg:address":"Calle de Tajo (del), 3",
    "sg:city":"Mejorada Campo",
    "sg:orig_category":"Comercio, Reparaci\u00d3n De Motocicletas, Bicicletas Y Piezas Sueltas",
    "sg:phone":"+34 916 68 07 75",
    "sg:postcode":"28840",
    "sg:province":"Madrid",
    "wof:name":"Tecnomoto S.a.",
    "wof:placetype":"venue"
},
  "geometry": {"coordinates":[-3.4877839088,40.3851127625],"type":"Point"}
}