{
  "type": "Feature",
  "properties": {
    "addr:full":"Carrer de Valencia, 84 Barcelona Barcelona 08015",
    "addr:housenumber":"84",
    "addr:postcode":"08015",
    "addr:street":"Carrer De Valencia",
    "iso:country":"ES",
    "sg:address":"Carrer de Valencia, 84",
    "sg:city":"Barcelona",
    "sg:orig_category":"Sociedades, Compa\u00d1\u00cdas Aseguradoras",
    "sg:phone":"+34 932 26 55 66",
    "sg:postcode":"08015",
    "sg:province":"Barcelona",
    "wof:name":"Martrat Perits S.l.",
    "wof:placetype":"venue"
},
  "geometry": {"coordinates":[2.1497778893,41.3823165894],"type":"Point"}
}