{
  "type": "Feature",
  "properties": {
    "addr:full":"Calle de Postas, 7 Vitoria-gasteiz \u00c1lava 01001",
    "addr:housenumber":"7",
    "addr:postcode":"01001",
    "addr:street":"Calle De Postas",
    "iso:country":"ES",
    "sg:address":"Calle de Postas, 7",
    "sg:city":"Vitoria-gasteiz",
    "sg:orig_category":"Bancos",
    "sg:phone":"+34 945 14 12 00",
    "sg:postcode":"01001",
    "sg:province":"\u00c1lava",
    "wof:name":"Banc Sabadell S.a.",
    "wof:placetype":"venue"
},
  "geometry": {"coordinates":[-2.6701788902,42.8458061218],"type":"Point"}
}