{
  "type": "Feature",
  "properties": {
    "iso:country":"ES",
    "sg:address":"Calle de Real, 17",
    "sg:city":"Lepe",
    "sg:orig_category":"Cajas De Ahorro",
    "sg:phone":"+34 959 38 05 00",
    "sg:postcode":"21440",
    "sg:province":"Huelva",
    "sg:website":"www.lacaixa.es",
    "wof:name":"Caixa D'estalvis I Pensions De Barcelona",
    "wof:placetype":"venue"
},
  "geometry": {"coordinates":[-7.2033720016,37.2549438477],"type":"Point"}
}