{
  "type": "Feature",
  "properties": {
    "addr:full":"Vgen. Angustias, 13 Puebla Almoradiel Toledo 45840",
    "addr:housenumber":"13",
    "addr:postcode":"45840",
    "addr:street":"Angustias;Almoradiel",
    "iso:country":"ES",
    "sg:address":"Vgen. Angustias, 13",
    "sg:city":"Puebla Almoradiel",
    "sg:orig_category":"Reposter\u00cdas",
    "sg:phone":"+34 925 17 83 30",
    "sg:postcode":"45840",
    "sg:province":"Toledo",
    "wof:name":"Paniagua Lozano Vicente",
    "wof:placetype":"venue"
},
  "geometry": {"coordinates":[-3.1186289787,39.5983505249],"type":"Point"}
}