{
  "type": "Feature",
  "properties": {
    "addr:full":"Avda Covadonga, 6 Cangas Onis Asturias 33550",
    "addr:housenumber":"6",
    "addr:postcode":"33550",
    "addr:street":"Avda Covadonga;Onis Asturias",
    "iso:country":"ES",
    "sg:address":"Avda Covadonga, 6",
    "sg:city":"Cangas Onis",
    "sg:orig_category":"Pensiones Familiares",
    "sg:phone":"+34 985 84 82 75",
    "sg:postcode":"33550",
    "sg:province":"Asturias",
    "wof:name":"Aventuras Astugala C.b.",
    "wof:placetype":"venue"
},
  "geometry": {"coordinates":[-5.128777504,43.3509788513],"type":"Point"}
}