{
  "type": "Feature",
  "properties": {
    "addr:full":"Calle de Santa Barbara, 16 Pozoblanco C\u00f3rdoba 14400",
    "addr:housenumber":"16",
    "addr:postcode":"14400",
    "addr:street":"Calle De Santa Barbara",
    "iso:country":"ES",
    "sg:address":"Calle de Santa Barbara, 16",
    "sg:city":"Pozoblanco",
    "sg:orig_category":"Animales (al Por Menor)",
    "sg:phone":"+34 957 77 31 90",
    "sg:postcode":"14400",
    "sg:province":"C\u00f3rdoba",
    "wof:name":"Distribuiciones Garcia Parra",
    "wof:placetype":"venue"
},
  "geometry": {"coordinates":[-4.8447480202,38.3815689087],"type":"Point"}
}