{
  "type": "Feature",
  "properties": {
    "iso:country":"ES",
    "sg:address":"Ctra. Orense-b. De Mi\u00f1o, 10",
    "sg:city":"Barra Mi\u00f1o",
    "sg:orig_category":"Carnicer\u00cdas, Carnicer\u00cdas",
    "sg:phone":"+34 988 20 50 47",
    "sg:postcode":"32950",
    "sg:province":"Ourense",
    "wof:name":"Rodriguez Goyanes Jose Antonio",
    "wof:placetype":"venue"
},
  "geometry": {"coordinates":[-7.8384737968,42.3799209595],"type":"Point"}
}