{
  "type": "Feature",
  "properties": {
    "addr:full":"Pase Arroyomolinos (de), 2 Mostoles Madrid 28934",
    "addr:postcode":"28934",
    "addr:street":"Mostoles",
    "iso:country":"ES",
    "sg:address":"Pase Arroyomolinos (de), 2",
    "sg:city":"Mostoles",
    "sg:orig_category":"Pod\u00d3logos: Pedicuros",
    "sg:phone":"+34 916 13 71 91",
    "sg:postcode":"28934",
    "sg:province":"Madrid",
    "wof:name":"Lopez Palomares Miguel Angel",
    "wof:placetype":"venue"
},
  "geometry": {"coordinates":[-3.866797924,40.3205451965],"type":"Point"}
}