{
  "type": "Feature",
  "properties": {
    "iso:country":"ES",
    "sg:address":"Carrer de Avi Riera, 2",
    "sg:city":"Vilassar Dalt",
    "sg:orig_category":"Sociedades, Compa\u00d1\u00cdas Aseguradoras",
    "sg:phone":"+34 937 50 93 22",
    "sg:postcode":"08339",
    "sg:province":"Barcelona",
    "wof:name":"Avi Riera 2 S.l.",
    "wof:placetype":"venue"
},
  "geometry": {"coordinates":[2.3557300568,41.5205764771],"type":"Point"}
}