{
  "type": "Feature",
  "properties": {
    "iso:country":"ES",
    "sg:address":"Plaz Cachupin, 6",
    "sg:city":"Laredo",
    "sg:orig_category":"M\u00c9dicos: Estomatolog\u00cda",
    "sg:phone":"+34 942 60 33 22",
    "sg:postcode":"39770",
    "sg:province":"Cantabria",
    "wof:name":"Echeberria Torrecilla Leire",
    "wof:placetype":"venue"
},
  "geometry": {"coordinates":[-3.4124660492,43.4106712341],"type":"Point"}
}