{
  "type": "Feature",
  "properties": {
    "addr:full":"C/ Sant Salvador, 3 Ripollet Barcelona 08291",
    "addr:housenumber":"3",
    "addr:postcode":"08291",
    "addr:street":"C / Sant Salvador",
    "iso:country":"ES",
    "sg:address":"C/ Sant Salvador, 3",
    "sg:city":"Ripollet",
    "sg:orig_category":"Serigraf\u00cda (material Y Suministros)",
    "sg:phone":"+34 935 80 38 49",
    "sg:postcode":"08291",
    "sg:province":"Barcelona",
    "wof:name":"Fernandez Jaren Bartolome",
    "wof:placetype":"venue"
},
  "geometry": {"coordinates":[2.154047966,41.5006332397],"type":"Point"}
}