{
  "type": "Feature",
  "properties": {
    "iso:country":"ES",
    "sg:address":"Calle de Virgen Del Pilar, 8",
    "sg:city":"Montefrio",
    "sg:orig_category":"Negocio De Materiales De Construcci\u00d3n",
    "sg:phone":"+34 958 31 03 50",
    "sg:postcode":"18270",
    "sg:province":"Granada",
    "wof:name":"Arco Tellado Francisco",
    "wof:placetype":"venue"
},
  "geometry": {"coordinates":[-4.0033965111,37.3214073181],"type":"Point"}
}