{
  "type": "Feature",
  "properties": {
    "addr:full":"Carrer de Maria Auxiliadora, 17 Barcelona Barcelona 08017",
    "addr:housenumber":"17",
    "addr:postcode":"08017",
    "addr:street":"Carrer De Maria Auxiliadora",
    "iso:country":"ES",
    "sg:address":"Carrer de Maria Auxiliadora, 17",
    "sg:city":"Barcelona",
    "sg:orig_category":"El Hogar: Amueblado, Acondicionamiento, Decoraci\u00d3n Y Mantenimiento",
    "sg:phone":"+34 932 05 25 56",
    "sg:postcode":"08017",
    "sg:province":"Barcelona",
    "wof:name":"Marcillas Molins Juan",
    "wof:placetype":"venue"
},
  "geometry": {"coordinates":[2.1292059422,41.3948822021],"type":"Point"}
}