{
  "type": "Feature",
  "properties": {
    "iso:country":"ES",
    "sg:address":"Calle de Corazon De Maria, 9",
    "sg:city":"Jerez De Los Caballeros",
    "sg:orig_category":"Abogados",
    "sg:phone":"+34 924 75 12 06",
    "sg:postcode":"06380",
    "sg:province":"Badajoz",
    "wof:name":"Badajoz Carrasco Inmaculada",
    "wof:placetype":"venue"
},
  "geometry": {"coordinates":[-6.7725081444,38.3204269409],"type":"Point"}
}