{
  "type": "Feature",
  "properties": {
    "addr:full":"Ctra Berga, Km. 0034,7 S. Fruitos Bages Barcelona 08272",
    "addr:postcode":"08272",
    "addr:street":"Ctra Berga Km. 0034,7 S. Fruitos Bages Barcelona",
    "iso:country":"ES",
    "sg:address":"Ctra Berga, Km. 0034,7",
    "sg:city":"S. Fruitos Bages",
    "sg:classifiers":[
        {
            "category":"Manufacturing",
            "subcategory":"Metals",
            "type":"Manufacturing & Wholesale Goods"
        }
    ],
    "sg:phone":"+34 938 76 10 52",
    "sg:postcode":"08272",
    "sg:province":"Barcelona",
    "sg:tags":[
        "en",
        "fundiciones"
    ],
    "wof:name":"Fundicion Pujol Muntala S.a.",
    "wof:placetype":"venue"
},
  "geometry": {"coordinates":[1.8779350519,41.7520599365],"type":"Point"}
}