{
  "type": "Feature",
  "properties": {
    "iso:country":"ES",
    "sg:address":"Calle de Fernando El Santo, 17",
    "sg:city":"Madrid",
    "sg:orig_category":"Arquitectos",
    "sg:phone":"+34 913 08 03 08",
    "sg:postcode":"28010",
    "sg:province":"Madrid",
    "sg:website":"www.arquitecturalangdon.com",
    "wof:name":"Arquitectura Langdon S.a.",
    "wof:placetype":"venue"
},
  "geometry": {"coordinates":[-3.6922829151,40.4281463623],"type":"Point"}
}