{
  "type": "Feature",
  "properties": {
    "addr:full":"Calle de Obispo De Las Navas, 4 Baza Granada 18800",
    "addr:housenumber":"4",
    "addr:postcode":"18800",
    "addr:street":"Calle De Obispo De Las Navas",
    "iso:country":"ES",
    "sg:address":"Calle de Obispo De Las Navas, 4",
    "sg:city":"Baza",
    "sg:orig_category":"M\u00c9dicos: Estomatolog\u00cda",
    "sg:phone":"+34 958 71 21 41",
    "sg:postcode":"18800",
    "sg:province":"Granada",
    "wof:name":"Fernandez Lopez Maria Praxedes",
    "wof:placetype":"venue"
},
  "geometry": {"coordinates":[-2.7673339844,37.4928855896],"type":"Point"}
}