{
  "type": "Feature",
  "properties": {
    "iso:country":"ES",
    "sg:address":"Carr Bufali (de), S/n",
    "sg:city":"Albaida",
    "sg:orig_category":"Confecci\u00d3n (fabricaci\u00d3n, Al Por Mayor)",
    "sg:phone":"+34 962 90 07 83",
    "sg:postcode":"46860",
    "sg:province":"Valencia",
    "wof:name":"Garmatex Albaida S.l.",
    "wof:placetype":"venue"
},
  "geometry": {"coordinates":[-0.5230889916,38.8398017883],"type":"Point"}
}