{
  "type": "Feature",
  "properties": {
    "addr:full":"Barr Sierrapando, 457 Sierrapando Cantabria 39317",
    "addr:housenumber":"457",
    "addr:postcode":"39317",
    "addr:street":"Sierrapando",
    "iso:country":"ES",
    "sg:address":"Barr Sierrapando, 457",
    "sg:city":"Sierrapando",
    "sg:classifiers":[
        {
            "category":"Taxi",
            "type":"Transportation"
        }
    ],
    "sg:phone":"+34 942 80 58 08",
    "sg:postcode":"39317",
    "sg:province":"Cantabria",
    "wof:name":"Gonzalez Martin Prudencio",
    "wof:placetype":"venue"
},
  "geometry": {"coordinates":[-4.0321497917,43.3432312012],"type":"Point"}
}