{
  "type": "Feature",
  "properties": {
    "iso:country":"ES",
    "sg:address":"Calle de Jose Maria Lope Toledo, 2",
    "sg:city":"Logro\u00f1o",
    "sg:orig_category":"Farmacias",
    "sg:phone":"+34 941 23 36 55",
    "sg:postcode":"26003",
    "sg:province":"La Rioja",
    "wof:name":"Martinez Garcia Maria De La Soledad",
    "wof:placetype":"venue"
},
  "geometry": {"coordinates":[-2.4368889332,42.4606361389],"type":"Point"}
}