{
  "type": "Feature",
  "properties": {
    "addr:full":"El Doctor, S/n S. Cebrian Campos Palencia 34429",
    "addr:housenumber":"s",
    "addr:postcode":"34429",
    "addr:street":"El Doctor;/ N S. Cebrian Campos",
    "iso:country":"ES",
    "sg:address":"El Doctor, S/n",
    "sg:city":"S. Cebrian Campos",
    "sg:orig_category":"Carnicer\u00cdas, Carnicer\u00cdas",
    "sg:phone":"+34 979 15 40 16",
    "sg:postcode":"34429",
    "sg:province":"Palencia",
    "wof:name":"Amor Amor Maria Mercedes",
    "wof:placetype":"venue"
},
  "geometry": {"coordinates":[-4.5293421745,42.2020874023],"type":"Point"}
}