{
  "type": "Feature",
  "properties": {
    "iso:country":"ES",
    "sg:address":"Praz Espa\u00d1a, 33",
    "sg:city":"Ferrol",
    "sg:orig_category":"Notarios",
    "sg:phone":"+34 981 37 25 20",
    "sg:postcode":"15402",
    "sg:province":"La Coru\u00f1a",
    "wof:name":"Otero Afonso Bruno",
    "wof:placetype":"venue"
},
  "geometry": {"coordinates":[-8.2289247513,43.4858665466],"type":"Point"}
}