{
  "type": "Feature",
  "properties": {
    "iso:country":"ES",
    "sg:address":"Av Girones, 18",
    "sg:city":"Llagostera",
    "sg:orig_category":"Electrodom\u00c9sticos (fabricaci\u00d3n, Al Por Mayor)",
    "sg:phone":"+34 972 83 10 25",
    "sg:postcode":"17240",
    "sg:province":"Girona",
    "wof:name":"Auladell Corbera Jose Maria",
    "wof:placetype":"venue"
},
  "geometry": {"coordinates":[2.894734621,41.8226280212],"type":"Point"}
}