{
  "type": "Feature",
  "properties": {
    "addr:full":"Calle de Oca, 31 Madrid Madrid 28025",
    "addr:housenumber":"31",
    "addr:postcode":"madrid;28025",
    "addr:street":"Calle De Oca",
    "iso:country":"ES",
    "sg:address":"Calle de Oca, 31",
    "sg:city":"Madrid",
    "sg:orig_category":"Peleter\u00cdas",
    "sg:phone":"+34 914 61 06 66",
    "sg:postcode":"28025",
    "sg:province":"Madrid",
    "wof:name":"Sanchez Martin Maria Teresa",
    "wof:placetype":"venue"
},
  "geometry": {"coordinates":[-3.735806942,40.389541626],"type":"Point"}
}