{
  "type": "Feature",
  "properties": {
    "iso:country":"ES",
    "sg:address":"Estda. De Vigo, S/n",
    "sg:city":"Ourense",
    "sg:orig_category":"Distribuci\u00d3n De Petr\u00d3leo Y Derivados",
    "sg:phone":"+34 988 21 68 85",
    "sg:postcode":"32001",
    "sg:province":"Ourense",
    "wof:name":"Comunidad De Herederos De Alfonso Noguerol Pernas C.b",
    "wof:placetype":"venue"
},
  "geometry": {"coordinates":[-7.8814702034,42.3738327026],"type":"Point"}
}