{
  "type": "Feature",
  "properties": {
    "addr:full":"Avda Rey Juan Carlos I, 44 Leganes Madrid 28915",
    "addr:housenumber":"44",
    "addr:postcode":"28915",
    "addr:street":"Avda Rey Juan Carlos I",
    "iso:country":"ES",
    "sg:address":"Avda Rey Juan Carlos I, 44",
    "sg:city":"Leganes",
    "sg:orig_category":"Florister\u00cdas",
    "sg:phone":"+34 916 80 97 88",
    "sg:postcode":"28915",
    "sg:province":"Madrid",
    "wof:name":"Alonso Cano Daniel",
    "wof:placetype":"venue"
},
  "geometry": {"coordinates":[-3.752351284,40.3344306946],"type":"Point"}
}