{
  "type": "Feature",
  "properties": {
    "iso:country":"ES",
    "sg:address":"Avda Sancho El Sabio, 21",
    "sg:city":"Arcos",
    "sg:orig_category":"Producci\u00d3n, Distribuci\u00d3n De Electricidad",
    "sg:phone":"+34 948 64 08 04",
    "sg:postcode":"31210",
    "sg:province":"Navarra",
    "wof:name":"Berrueza S.a.",
    "wof:placetype":"venue"
},
  "geometry": {"coordinates":[-2.194466114,42.56798172],"type":"Point"}
}