{
  "type": "Feature",
  "properties": {
    "addr:full":"Calle de Malteses (los), 42 Villamartin C\u00e1diz 11650",
    "addr:housenumber":"42",
    "addr:postcode":"11650",
    "addr:street":"Calle De Malteses Los;Ca\u0301Diz",
    "iso:country":"ES",
    "sg:address":"Calle de Malteses (los), 42",
    "sg:city":"Villamartin",
    "sg:orig_category":"Reposter\u00cdas",
    "sg:phone":"+34 956 73 02 81",
    "sg:postcode":"11650",
    "sg:province":"C\u00e1diz",
    "wof:name":"Panaderia Hermanos Cabral S.c.",
    "wof:placetype":"venue"
},
  "geometry": {"coordinates":[-5.6434688568,36.8600997925],"type":"Point"}
}