{
  "type": "Feature",
  "properties": {
    "addr:full":"Pl. Cristo, S/n Las Navas Marques \u00c1vila 05230",
    "addr:housenumber":"s / n",
    "addr:postcode":"05230",
    "addr:street":"Cristo;Navas;A\u0301Vila",
    "iso:country":"ES",
    "sg:address":"Pl. Cristo, S/n",
    "sg:city":"Las Navas Marques",
    "sg:orig_category":"Cervecer\u00cdas",
    "sg:phone":"+34 918 97 05 46",
    "sg:postcode":"05230",
    "sg:province":"\u00c1vila",
    "wof:name":"Frutos Moreno Crisanto De",
    "wof:placetype":"venue"
},
  "geometry": {"coordinates":[-4.3334889412,40.6027450562],"type":"Point"}
}