{
  "type": "Feature",
  "properties": {
    "iso:country":"ES",
    "sg:address":"Calle de O.n.g. Quesada Solidaria, 56",
    "sg:city":"Quesada",
    "sg:orig_category":"Supermercados Y Hipermercados",
    "sg:phone":"+34 953 71 41 37",
    "sg:postcode":"23480",
    "sg:province":"Ja\u00e9n",
    "wof:name":"Salamanca Aranda Maria Jesus",
    "wof:placetype":"venue"
},
  "geometry": {"coordinates":[-3.0672140121,37.845615387],"type":"Point"}
}