{
  "type": "Feature",
  "properties": {
    "iso:country":"ES",
    "sg:address":"Calle de Ferrer Del Rio, 25",
    "sg:city":"Madrid",
    "sg:orig_category":"Inmobiliaria (agencias)",
    "sg:phone":"+34 917 26 33 33",
    "sg:postcode":"28028",
    "sg:province":"Madrid",
    "wof:name":"C.r. Rimacenter S.l.",
    "wof:placetype":"venue"
},
  "geometry": {"coordinates":[-3.671282053,40.4352111816],"type":"Point"}
}