{
  "type": "Feature",
  "properties": {
    "addr:full":"Calle de Manuel Maria Gonzalez, 2 Jerez De La Frontera C\u00e1diz 11403",
    "addr:housenumber":"2",
    "addr:postcode":"11403",
    "addr:street":"Calle De Manuel Maria Gonzalez",
    "iso:country":"ES",
    "sg:address":"Calle de Manuel Maria Gonzalez, 2",
    "sg:city":"Jerez De La Frontera",
    "sg:orig_category":"Abogados",
    "sg:phone":"+34 956 32 13 49",
    "sg:postcode":"11403",
    "sg:province":"C\u00e1diz",
    "wof:name":"Delgado Nole Maria Inmaculada",
    "wof:placetype":"venue"
},
  "geometry": {"coordinates":[-6.1399068832,36.6817703247],"type":"Point"}
}