{
  "type": "Feature",
  "properties": {
    "addr:full":"Calle de Flores, 5 Zaragoza Zaragoza 50013",
    "addr:housenumber":"5",
    "addr:postcode":"50013",
    "addr:street":"Calle De Flores",
    "iso:country":"ES",
    "sg:address":"Calle de Flores, 5",
    "sg:city":"Zaragoza",
    "sg:orig_category":"Fabricaci\u00d3n De Su\u00c9ters Y Chalecos De Punto",
    "sg:phone":"+34 976 59 31 07",
    "sg:postcode":"50013",
    "sg:province":"Zaragoza",
    "wof:name":"Amjome S.c.",
    "wof:placetype":"venue"
},
  "geometry": {"coordinates":[-0.869934082,41.6397399902],"type":"Point"}
}