{
  "type": "Feature",
  "properties": {
    "addr:full":"Calle de Valentin Barrecheguren, 3 Granada Granada 18010",
    "addr:housenumber":"3",
    "addr:postcode":"18010",
    "addr:street":"Calle De Valentin Barrecheguren",
    "iso:country":"ES",
    "sg:address":"Calle de Valentin Barrecheguren, 3",
    "sg:city":"Granada",
    "sg:orig_category":"Abogados",
    "sg:phone":"+34 958 22 13 10",
    "sg:postcode":"18010",
    "sg:province":"Granada",
    "wof:name":"Gomez Quesada Luis",
    "wof:placetype":"venue"
},
  "geometry": {"coordinates":[-3.598459959,37.1779747009],"type":"Point"}
}