{
  "type": "Feature",
  "properties": {
    "addr:full":"Calle de Eduardo Zamacois, 13 Santa Cruz De Tenerife Santa Cruz De Tenerife 38005",
    "addr:housenumber":"13",
    "addr:postcode":"38005",
    "addr:street":"Calle De Eduardo Zamacois",
    "iso:country":"ES",
    "sg:address":"Calle de Eduardo Zamacois, 13",
    "sg:city":"Santa Cruz De Tenerife",
    "sg:orig_category":"Asociaciones Humanitarias, De Cooperaci\u00d3n, De Acci\u00d3n Social",
    "sg:phone":"+34 922 21 59 09",
    "sg:postcode":"38005",
    "sg:province":"Santa Cruz De Tenerife",
    "wof:name":"Coordinadora De Minusvalidos Fisicos De Canarias",
    "wof:placetype":"venue"
},
  "geometry": {"coordinates":[-16.262178421,28.4620094299],"type":"Point"}
}