{
  "type": "Feature",
  "properties": {
    "iso:country":"ES",
    "sg:address":"Avda Tenerife (de), 16",
    "sg:city":"San Sebastian De Los Reyes",
    "sg:orig_category":"Negocio De Materiales De Construcci\u00d3n",
    "sg:phone":"+34 916 52 87 11",
    "sg:postcode":"28700",
    "sg:province":"Madrid",
    "wof:name":"Segura E Hijos S.a.",
    "wof:placetype":"venue"
},
  "geometry": {"coordinates":[-3.6210689545,40.5597648621],"type":"Point"}
}