{
  "type": "Feature",
  "properties": {
    "addr:full":"Avda Duque De Arcos, S/n S. Fernando C\u00e1diz 11100",
    "addr:housenumber":"s",
    "addr:postcode":"11100",
    "addr:street":"Avda Duque De Arcos;/ N S. Fernando Ca\u0301Diz",
    "iso:country":"ES",
    "sg:address":"Avda Duque De Arcos, S/n",
    "sg:city":"S. Fernando",
    "sg:orig_category":"Molduras, Junquillos, Listones Y Molduras Perforadas",
    "sg:phone":"+34 956 59 21 29",
    "sg:postcode":"11100",
    "sg:province":"C\u00e1diz",
    "wof:name":"Eurotel Sur S L",
    "wof:placetype":"venue"
},
  "geometry": {"coordinates":[-6.2084388733,36.457408905],"type":"Point"}
}