{
  "type": "Feature",
  "properties": {
    "addr:full":"Carrer de Santa Elena (de), 36 Vilassar De Mar Barcelona 08340",
    "addr:postcode":"08340",
    "addr:street":"Carrer De Santa",
    "iso:country":"ES",
    "sg:address":"Carrer de Santa Elena (de), 36",
    "sg:city":"Vilassar De Mar",
    "sg:orig_category":"Agencias Y Agentes Comerciales, Representantes",
    "sg:phone":"+34 937 59 00 36",
    "sg:postcode":"08340",
    "sg:province":"Barcelona",
    "wof:name":"Serra Pujol Alberto",
    "wof:placetype":"venue"
},
  "geometry": {"coordinates":[2.3977019787,41.5068130493],"type":"Point"}
}