{
  "type": "Feature",
  "properties": {
    "addr:full":"Carrer de Alella, 2 Barcelona Barcelona 08016",
    "addr:housenumber":"2",
    "addr:postcode":"08016",
    "addr:street":"Carrer De Alella",
    "iso:country":"ES",
    "sg:address":"Carrer de Alella, 2",
    "sg:city":"Barcelona",
    "sg:orig_category":"Panader\u00cdas, Panader\u00cdas",
    "sg:phone":"+34 933 40 44 46",
    "sg:postcode":"08016",
    "sg:province":"Barcelona",
    "wof:name":"Forn I Nata Sierra Bravo S.l.",
    "wof:placetype":"venue"
},
  "geometry": {"coordinates":[2.1810998917,41.4316291809],"type":"Point"}
}