{
  "type": "Feature",
  "properties": {
    "iso:country":"ES",
    "sg:address":"Cmno Arana Bidea, 36",
    "sg:city":"Berango",
    "sg:orig_category":"Torrefactado De Caf\u00c9",
    "sg:phone":"+34 946 68 01 63",
    "sg:postcode":"48640",
    "sg:province":"Vizcaya",
    "wof:name":"Pascual De Diego Pablo",
    "wof:placetype":"venue"
},
  "geometry": {"coordinates":[-2.9994060993,43.3669509888],"type":"Point"}
}