{
  "type": "Feature",
  "properties": {
    "iso:country":"ES",
    "sg:address":"Avda Carlos I De, 30",
    "sg:city":"Donostia-san Sebastian",
    "sg:orig_category":"Tapicer\u00cdas",
    "sg:phone":"+34 943 45 92 02",
    "sg:postcode":"20011",
    "sg:province":"Guip\u00f9zcoa",
    "wof:name":"Pedrosa Alvarez Carlos",
    "wof:placetype":"venue"
},
  "geometry": {"coordinates":[-1.9789869785,43.3029060364],"type":"Point"}
}