{
  "type": "Feature",
  "properties": {
    "addr:full":"Calle de Regente La, 6 Malaga M\u00e1laga 29009",
    "addr:housenumber":"6",
    "addr:postcode":"29009",
    "addr:street":"Calle De Regente La;Ma\u0301Laga",
    "iso:country":"ES",
    "sg:address":"Calle de Regente La, 6",
    "sg:city":"Malaga",
    "sg:orig_category":"Juegos Y Juguetes (al Por Menor)",
    "sg:phone":"+34 952 24 50 33",
    "sg:postcode":"29009",
    "sg:province":"M\u00e1laga",
    "wof:name":"Conejo Janicke Miguel Angel",
    "wof:placetype":"venue"
},
  "geometry": {"coordinates":[-4.4272918701,36.7259941101],"type":"Point"}
}