{
  "type": "Feature",
  "properties": {
    "iso:country":"ES",
    "sg:address":"Calle de Mejia Lequerica, 19",
    "sg:city":"Madrid",
    "sg:orig_category":"Abogados",
    "sg:phone":"+34 914 47 37 13",
    "sg:postcode":"28004",
    "sg:province":"Madrid",
    "wof:name":"International Law Mastering S.l.",
    "wof:placetype":"venue"
},
  "geometry": {"coordinates":[-3.6994149685,40.4276046753],"type":"Point"}
}