{
  "type": "Feature",
  "properties": {
    "addr:full":"Carrer de Bellavista, 5 Hospitalet Llobregat Barcelona 08901",
    "addr:housenumber":"5",
    "addr:postcode":"08901",
    "addr:street":"Carrer De Bellavista",
    "iso:country":"ES",
    "sg:address":"Carrer de Bellavista, 5",
    "sg:city":"Hospitalet Llobregat",
    "sg:orig_category":"Impresi\u00d3n Digital",
    "sg:phone":"+34 933 38 01 51",
    "sg:postcode":"08901",
    "sg:province":"Barcelona",
    "wof:name":"Digitalmap Scp",
    "wof:placetype":"venue"
},
  "geometry": {"coordinates":[2.0945529938,41.3612747192],"type":"Point"}
}