{
  "type": "Feature",
  "properties": {
    "addr:full":"Avda Zamora (de), 162 Ourense Ourense 32005",
    "addr:housenumber":"162",
    "addr:postcode":"32005",
    "addr:street":"Avda Zamora De",
    "iso:country":"ES",
    "sg:address":"Avda Zamora (de), 162",
    "sg:city":"Ourense",
    "sg:orig_category":"Caf\u00c9s, Bares, Cervecer\u00cdas",
    "sg:phone":"+34 988 23 22 77",
    "sg:postcode":"32005",
    "sg:province":"Ourense",
    "wof:name":"Salgado Gomez Manuel",
    "wof:placetype":"venue"
},
  "geometry": {"coordinates":[-7.8624148369,42.3188209534],"type":"Point"}
}