{
  "type": "Feature",
  "properties": {
    "iso:country":"ES",
    "sg:address":"Barr Basotxu Auzoa, 3",
    "sg:city":"Baserri-santa Ana",
    "sg:orig_category":"Cristaler\u00cdas",
    "sg:phone":"+34 946 68 22 73",
    "sg:postcode":"48640",
    "sg:province":"Vizcaya",
    "wof:name":"Civicos Gonzalez Bernardo",
    "wof:placetype":"venue"
},
  "geometry": {"coordinates":[-2.9955940247,43.3641815186],"type":"Point"}
}