{
  "type": "Feature",
  "properties": {
    "iso:country":"ES",
    "sg:address":"Av Vidal I Barraquer, 12",
    "sg:city":"Cambrils",
    "sg:orig_category":"Institutos De Belleza",
    "sg:phone":"+34 977 36 07 60",
    "sg:postcode":"43850",
    "sg:province":"Tarragona",
    "wof:name":"Margalef Fortuny Josefina",
    "wof:placetype":"venue"
},
  "geometry": {"coordinates":[1.052834034,41.0705871582],"type":"Point"}
}