{
  "type": "Feature",
  "properties": {
    "addr:full":"Calle de Mayor, 92 Fuente-alamo Albacete 02651",
    "addr:housenumber":"92",
    "addr:postcode":"02651",
    "addr:street":"Calle De Mayor",
    "iso:country":"ES",
    "sg:address":"Calle de Mayor, 92",
    "sg:city":"Fuente-alamo",
    "sg:orig_category":"Peluqueros: De Se\u00d1oras",
    "sg:phone":"+34 967 32 10 76",
    "sg:postcode":"02651",
    "sg:province":"Albacete",
    "wof:name":"Gomez Garcia Blas",
    "wof:placetype":"venue"
},
  "geometry": {"coordinates":[-1.4322990179,38.6940383911],"type":"Point"}
}