{
  "type": "Feature",
  "properties": {
    "iso:country":"ES",
    "sg:address":"Praz Rodrigas (das), 11",
    "sg:city":"Rodrigas",
    "sg:orig_category":"Panader\u00cdas, Panader\u00cdas",
    "sg:phone":"+34 982 34 60 06",
    "sg:postcode":"27744",
    "sg:province":"Lugo",
    "wof:name":"Canto Seco Edelmiro",
    "wof:placetype":"venue"
},
  "geometry": {"coordinates":[-7.2605810165,43.3407554626],"type":"Point"}
}