{
  "type": "Feature",
  "properties": {
    "addr:full":"Ptge Pompeu, 2 Lleida Lleida 25006",
    "addr:housenumber":"2",
    "addr:postcode":"25006",
    "addr:street":"Ptge Pompeu",
    "iso:country":"ES",
    "sg:address":"Ptge Pompeu, 2",
    "sg:city":"Lleida",
    "sg:orig_category":"M\u00c9dicos: Oftalmolog\u00cda",
    "sg:phone":"+34 973 24 36 91",
    "sg:postcode":"25006",
    "sg:province":"Lleida",
    "wof:name":"Agua Lopez Eduardo Del",
    "wof:placetype":"venue"
},
  "geometry": {"coordinates":[0.6197308898,41.6194915771],"type":"Point"}
}