{
  "type": "Feature",
  "properties": {
    "addr:full":"Calle de Bronce, 8 Illescas Toledo 45200",
    "addr:housenumber":"8",
    "addr:postcode":"45200",
    "addr:street":"Calle De Bronce",
    "iso:country":"ES",
    "sg:address":"Calle de Bronce, 8",
    "sg:city":"Illescas",
    "sg:orig_category":"Papel (al Por Mayor)",
    "sg:phone":"+34 925 51 34 03",
    "sg:postcode":"45200",
    "sg:province":"Toledo",
    "wof:name":"Coydis Papel S.a.",
    "wof:placetype":"venue"
},
  "geometry": {"coordinates":[-3.8549301624,40.1138954163],"type":"Point"}
}