{
  "type": "Feature",
  "properties": {
    "addr:full":"Poli Industrial Las Casas, 30 Soria Soria 42005",
    "addr:housenumber":"30",
    "addr:postcode":"42005",
    "addr:street":"Casas",
    "iso:country":"ES",
    "sg:address":"Poli Industrial Las Casas, 30",
    "sg:city":"Soria",
    "sg:orig_category":"Artesanado",
    "sg:phone":"+34 975 21 46 96",
    "sg:postcode":"42005",
    "sg:province":"Soria",
    "wof:name":"Metalicas Duero S.l.l.",
    "wof:placetype":"venue"
},
  "geometry": {"coordinates":[-2.4691669941,41.7646598816],"type":"Point"}
}