{
  "type": "Feature",
  "properties": {
    "iso:country":"ES",
    "sg:address":"Avda Mediterraneo, 28",
    "sg:city":"Benidorm",
    "sg:orig_category":"Fabricaci\u00d3n De Juegos Y Juguetes",
    "sg:phone":"+34 965 85 33 67",
    "sg:postcode":"03500",
    "sg:province":"Alicante",
    "wof:name":"Toys Benidorm S.l.",
    "wof:placetype":"venue"
},
  "geometry": {"coordinates":[-0.1192340031,38.5367088318],"type":"Point"}
}