{
  "type": "Feature",
  "properties": {
    "iso:country":"ES",
    "sg:address":"Calle de Carlos Sole, 49",
    "sg:city":"Madrid",
    "sg:orig_category":"Cerrajer\u00cda, Ferrallista",
    "sg:phone":"+34 913 03 36 14",
    "sg:postcode":"28038",
    "sg:province":"Madrid",
    "wof:name":"Pe\u00f1a De Frutos Marcelino",
    "wof:placetype":"venue"
},
  "geometry": {"coordinates":[-3.647560358,40.3921699524],"type":"Point"}
}