{
  "type": "Feature",
  "properties": {
    "addr:full":"Avda Torrelavega De, 32 Oviedo Asturias 33010",
    "addr:housenumber":"32",
    "addr:postcode":"33010",
    "addr:street":"Avda Torrelavega De",
    "iso:country":"ES",
    "sg:address":"Avda Torrelavega De, 32",
    "sg:city":"Oviedo",
    "sg:orig_category":"Veh\u00cdculos De Ocasi\u00d3n",
    "sg:phone":"+34 985 20 10 33",
    "sg:postcode":"33010",
    "sg:province":"Asturias",
    "wof:name":"Gallinar Coya Angel",
    "wof:placetype":"venue"
},
  "geometry": {"coordinates":[-5.8356847763,43.3638687134],"type":"Point"}
}