{
  "type": "Feature",
  "properties": {
    "addr:full":"Calle de Abajo, 13 Callosa Segura Alicante 03360",
    "addr:housenumber":"13",
    "addr:postcode":"03360",
    "addr:street":"Calle De Abajo",
    "iso:country":"ES",
    "sg:address":"Calle de Abajo, 13",
    "sg:city":"Callosa Segura",
    "sg:orig_category":"Farmacias",
    "sg:phone":"+34 965 31 02 72",
    "sg:postcode":"03360",
    "sg:province":"Alicante",
    "wof:name":"Manresa Galiana Jose",
    "wof:placetype":"venue"
},
  "geometry": {"coordinates":[-0.8790972233,38.1214523315],"type":"Point"}
}