{
  "type": "Feature",
  "properties": {
    "addr:full":"Calle de Manuel Gonzalez Vigil, 6 Entrego Asturias 33940",
    "addr:housenumber":"6",
    "addr:postcode":"33940",
    "addr:street":"Calle De Manuel Gonzalez Vigil",
    "iso:country":"ES",
    "sg:address":"Calle de Manuel Gonzalez Vigil, 6",
    "sg:city":"Entrego",
    "sg:orig_category":"Zapatos (al Por Menor)",
    "sg:phone":"+34 985 66 33 13",
    "sg:postcode":"33940",
    "sg:province":"Asturias",
    "wof:name":"Fernandez Rodriguez Aurelio",
    "wof:placetype":"venue"
},
  "geometry": {"coordinates":[-5.6435742378,43.2864112854],"type":"Point"}
}