{
  "type": "Feature",
  "properties": {
    "addr:full":"Calle de Doctor Collado Pi\u00d1a, 56 Albacete Albacete 02003",
    "addr:housenumber":"56",
    "addr:postcode":"02003",
    "addr:street":"Calle De Doctor Collado Pin\u0303A",
    "iso:country":"ES",
    "sg:address":"Calle de Doctor Collado Pi\u00d1a, 56",
    "sg:city":"Albacete",
    "sg:orig_category":"Comercio, Reparaci\u00d3n De Motocicletas, Bicicletas Y Piezas Sueltas",
    "sg:phone":"+34 967 23 10 47",
    "sg:postcode":"02003",
    "sg:province":"Albacete",
    "wof:name":"Garcia Martinez Santiago",
    "wof:placetype":"venue"
},
  "geometry": {"coordinates":[-1.8615790606,38.9895324707],"type":"Point"}
}