{
  "type": "Feature",
  "properties": {
    "iso:country":"ES",
    "sg:address":"Carrer de Benavent, 31",
    "sg:city":"Barcelona",
    "sg:orig_category":"Fabricaci\u00d3n De Bombas De Calor",
    "sg:phone":"+34 933 34 08 12",
    "sg:postcode":"08028",
    "sg:province":"Barcelona",
    "wof:name":"Hoya Nieto Francisco",
    "wof:placetype":"venue"
},
  "geometry": {"coordinates":[2.1248269081,41.378326416],"type":"Point"}
}