{
  "type": "Feature",
  "properties": {
    "addr:full":"Calle de Villaondoeta, 1 Algorta Vizcaya 48991",
    "addr:housenumber":"1",
    "addr:postcode":"48991",
    "addr:street":"Calle De Villaondoeta",
    "iso:country":"ES",
    "sg:address":"Calle de Villaondoeta, 1",
    "sg:city":"Algorta",
    "sg:orig_category":"Fotocopias, Reprograf\u00cda",
    "sg:phone":"+34 944 30 02 75",
    "sg:postcode":"48991",
    "sg:province":"Vizcaya",
    "wof:name":"Centro Reprografico Industriales S.l",
    "wof:placetype":"venue"
},
  "geometry": {"coordinates":[-3.0079250336,43.3515930176],"type":"Point"}
}