{
  "type": "Feature",
  "properties": {
    "addr:full":"Calle de Barranquillo, 8 Arucas Las Palmas 35400",
    "addr:housenumber":"8",
    "addr:postcode":"35400",
    "addr:street":"Calle De Barranquillo",
    "iso:country":"ES",
    "sg:address":"Calle de Barranquillo, 8",
    "sg:city":"Arucas",
    "sg:orig_category":"Alimentaci\u00d3n General (al Por Mayor)",
    "sg:phone":"+34 928 63 33 85",
    "sg:postcode":"35400",
    "sg:province":"Las Palmas",
    "wof:name":"Rubio Guerra Clemente",
    "wof:placetype":"venue"
},
  "geometry": {"coordinates":[-15.524512291,28.1197185516],"type":"Point"}
}