{
  "type": "Feature",
  "properties": {
    "iso:country":"ES",
    "sg:address":"Calle de Doctor Oloriz, 2",
    "sg:city":"Valencia",
    "sg:orig_category":"Ingeniero",
    "sg:phone":"+34 963 46 34 24",
    "sg:postcode":"46009",
    "sg:province":"Valencia",
    "wof:name":"Aplicaciones Informaticas Y Nuevas Tecnologias S.a.",
    "wof:placetype":"venue"
},
  "geometry": {"coordinates":[-0.3804075122,39.4830665588],"type":"Point"}
}