{
  "type": "Feature",
  "properties": {
    "addr:full":"Calle de Plus Ultra, 8 Huelva Huelva 21001",
    "addr:housenumber":"8",
    "addr:postcode":"21001",
    "addr:street":"Calle De Plus Ultra",
    "iso:country":"ES",
    "sg:address":"Calle de Plus Ultra, 8",
    "sg:city":"Huelva",
    "sg:orig_category":"Aparcamientos (infraestructuras, Accesorios)",
    "sg:phone":"+34 959 28 31 99",
    "sg:postcode":"21001",
    "sg:province":"Huelva",
    "wof:name":"Dornier S.a.",
    "wof:placetype":"venue"
},
  "geometry": {"coordinates":[-6.9540967941,37.2576179504],"type":"Point"}
}