{
  "type": "Feature",
  "properties": {
    "addr:full":"Carr Coladores, 11 Aldaia Valencia 46960",
    "addr:housenumber":"11",
    "addr:postcode":"46960",
    "addr:street":"Carr Coladores",
    "iso:country":"ES",
    "sg:address":"Carr Coladores, 11",
    "sg:city":"Aldaia",
    "sg:orig_category":"Sociedades, Compa\u00d1\u00cdas Aseguradoras",
    "sg:phone":"+34 961 51 47 00",
    "sg:postcode":"46960",
    "sg:province":"Valencia",
    "wof:name":"Ruiz Boluda Maria",
    "wof:placetype":"venue"
},
  "geometry": {"coordinates":[-0.4604389966,39.4656066895],"type":"Point"}
}