{
  "type": "Feature",
  "properties": {
    "addr:full":"Luga Carrus Poligono Industrial, 70 Elche Alicante 03291",
    "addr:housenumber":"70",
    "addr:postcode":"03291",
    "addr:street":"Poligono Industrial",
    "iso:country":"ES",
    "sg:address":"Luga Carrus Poligono Industrial, 70",
    "sg:city":"Elche",
    "sg:orig_category":"Artes Gr\u00c1ficas, Artes Pl\u00c1sticas (curso)",
    "sg:phone":"+34 966 66 56 30",
    "sg:postcode":"03291",
    "sg:province":"Alicante",
    "wof:name":"Fotograbados Bonet S.l.",
    "wof:placetype":"venue"
},
  "geometry": {"coordinates":[-0.6765189767,38.2994346619],"type":"Point"}
}