{
  "type": "Feature",
  "properties": {
    "iso:country":"ES",
    "sg:address":"Calle de Carretera, 29",
    "sg:city":"Conil De La Frontera",
    "sg:orig_category":"Supermercados Y Hipermercados",
    "sg:phone":"+34 956 44 03 92",
    "sg:postcode":"11140",
    "sg:province":"C\u00e1diz",
    "wof:name":"Gonzalez De Alba Manuel",
    "wof:placetype":"venue"
},
  "geometry": {"coordinates":[-6.0847115517,36.2801742554],"type":"Point"}
}