{
  "type": "Feature",
  "properties": {
    "addr:full":"Calle de Fernando El Catolico, 3 Madrid Madrid 28015",
    "addr:housenumber":"3",
    "addr:postcode":"28015",
    "addr:street":"Calle De Fernando El Catolico",
    "iso:country":"ES",
    "sg:address":"Calle de Fernando El Catolico, 3",
    "sg:city":"Madrid",
    "sg:orig_category":"Telas Y Sedas (al Por Menor)",
    "sg:phone":"+34 914 47 00 04",
    "sg:postcode":"28015",
    "sg:province":"Madrid",
    "wof:name":"Textiles Sandra S.l.",
    "wof:placetype":"venue"
},
  "geometry": {"coordinates":[-3.7058370113,40.4337120056],"type":"Point"}
}