{
  "type": "Feature",
  "properties": {
    "addr:full":"Cabreira, S/n Busto La Coru\u00f1a 15860",
    "addr:housenumber":"s / n",
    "addr:postcode":"15860",
    "addr:street":"Cabreira;Busto La Corun\u0303A",
    "iso:country":"ES",
    "sg:address":"Cabreira, S/n",
    "sg:city":"Busto",
    "sg:orig_category":"Distribuci\u00d3n De Petr\u00d3leo Y Derivados",
    "sg:phone":"+34 981 88 22 88",
    "sg:postcode":"15860",
    "sg:province":"La Coru\u00f1a",
    "wof:name":"Cabreira S.l.",
    "wof:placetype":"venue"
},
  "geometry": {"coordinates":[-8.8533306122,43.1042556763],"type":"Point"}
}