{
  "type": "Feature",
  "properties": {
    "iso:country":"ES",
    "sg:address":"Carrer de Anselm Clave, 53",
    "sg:city":"Granollers",
    "sg:orig_category":"Discotecas Y Salas De Baile",
    "sg:phone":"+34 938 79 65 29",
    "sg:postcode":"08402",
    "sg:province":"Barcelona",
    "wof:name":"Iniciativa Del Parentesis S.l.",
    "wof:placetype":"venue"
},
  "geometry": {"coordinates":[2.2888300419,41.6067466736],"type":"Point"}
}