{
  "type": "Feature",
  "properties": {
    "addr:full":"Calle de Aben Al Abbar, 2 Valencia Valencia 46021",
    "addr:housenumber":"2",
    "addr:postcode":"46021",
    "addr:street":"Calle De Aben Al Abbar",
    "iso:country":"ES",
    "sg:address":"Calle de Aben Al Abbar, 2",
    "sg:city":"Valencia",
    "sg:orig_category":"Empresarios",
    "sg:phone":"+34 963 60 17 18",
    "sg:postcode":"46021",
    "sg:province":"Valencia",
    "wof:name":"Fund.laboral Transp.urbanos Valencia",
    "wof:placetype":"venue"
},
  "geometry": {"coordinates":[-0.3529998064,39.4663734436],"type":"Point"}
}