{
  "type": "Feature",
  "properties": {
    "addr:full":"Avda Tres De Mayo, 12 Realejo Alto Santa Cruz De Tenerife 38410",
    "addr:housenumber":"12",
    "addr:postcode":"38410",
    "addr:street":"Avda Tres De Mayo",
    "iso:country":"ES",
    "sg:address":"Avda Tres De Mayo, 12",
    "sg:city":"Realejo Alto",
    "sg:orig_category":"Abogados",
    "sg:phone":"+34 922 34 04 55",
    "sg:postcode":"38410",
    "sg:province":"Santa Cruz De Tenerife",
    "wof:name":"Jimenez Fregel Evelio",
    "wof:placetype":"venue"
},
  "geometry": {"coordinates":[-16.5807914734,28.3678131104],"type":"Point"}
}