{
  "type": "Feature",
  "properties": {
    "iso:country":"ES",
    "sg:address":"Calle de Aldatseta, 6",
    "sg:city":"Bermeo",
    "sg:orig_category":"Institutos De Belleza",
    "sg:phone":"+34 946 88 44 08",
    "sg:postcode":"48370",
    "sg:province":"Vizcaya",
    "wof:name":"Arantza Gabantxo Munitiz",
    "wof:placetype":"venue"
},
  "geometry": {"coordinates":[-2.7241854668,43.4199676514],"type":"Point"}
}