{
  "type": "Feature",
  "properties": {
    "iso:country":"ES",
    "sg:address":"Plaz Patxi Aita, 2",
    "sg:city":"Bilbao",
    "sg:orig_category":"Muebles, Minoristas",
    "sg:phone":"+34 944 47 23 31",
    "sg:postcode":"48015",
    "sg:province":"Vizcaya",
    "wof:name":"Studio Hogar C.b.",
    "wof:placetype":"venue"
},
  "geometry": {"coordinates":[-2.9571979046,43.2774772644],"type":"Point"}
}