{
  "type": "Feature",
  "properties": {
    "iso:country":"ES",
    "sg:address":"Cami Jesus, 34",
    "sg:city":"Poligon Industrial De Can Valero",
    "sg:orig_category":"Negocio De Madera",
    "sg:phone":"+34 971 20 91 25",
    "sg:postcode":"07011",
    "sg:province":"Islas Baleares",
    "wof:name":"Comercial Maderas Mallorca S.a.",
    "wof:placetype":"venue"
},
  "geometry": {"coordinates":[2.6271300316,39.5906105042],"type":"Point"}
}