{
  "type": "Feature",
  "properties": {
    "iso:country":"ES",
    "sg:address":"Calle de Martinez Maldonado, 69",
    "sg:city":"Malaga",
    "sg:classifiers":[
        {
            "category":"Personal",
            "subcategory":"Barber",
            "type":"Services"
        }
    ],
    "sg:phone":"+34 952 27 83 58",
    "sg:postcode":"29007",
    "sg:province":"M\u00e1laga",
    "sg:tags":[
        "caballeros",
        "de",
        "peluqueros"
    ],
    "wof:name":"Calvo Martin Benjamin",
    "wof:placetype":"venue"
},
  "geometry": {"coordinates":[-4.4357690811,36.7214698792],"type":"Point"}
}