{
  "type": "Feature",
  "properties": {
    "iso:country":"ES",
    "sg:address":"Avda Andalucia, 43",
    "sg:city":"Linares",
    "sg:orig_category":"Venta, Colocaci\u00d3n, Reparaci\u00d3n De Parabrisas, Techos Descapotables",
    "sg:phone":"+34 953 65 14 59",
    "sg:postcode":"23700",
    "sg:province":"Ja\u00e9n",
    "sg:website":"www.alviasa.com",
    "wof:name":"Linares Glass S.l.",
    "wof:placetype":"venue"
},
  "geometry": {"coordinates":[-3.6404490471,38.092716217],"type":"Point"}
}