{
  "type": "Feature",
  "properties": {
    "addr:full":"Avda Estacion, 1 Loja Granada 18300",
    "addr:housenumber":"1 loja",
    "addr:postcode":"18300",
    "addr:street":"Avda Estacion",
    "iso:country":"ES",
    "sg:address":"Avda Estacion, 1",
    "sg:city":"Loja",
    "sg:orig_category":"Molduras, Junquillos, Listones Y Molduras Perforadas",
    "sg:phone":"+34 958 32 00 87",
    "sg:postcode":"18300",
    "sg:province":"Granada",
    "wof:name":"Marchal Otero Francisco",
    "wof:placetype":"venue"
},
  "geometry": {"coordinates":[-4.1507439613,37.1713142395],"type":"Point"}
}