{
  "type": "Feature",
  "properties": {
    "iso:country":"ES",
    "sg:address":"Calle de Torrecerredo, 19",
    "sg:city":"Oviedo",
    "sg:orig_category":"Cajas De Ahorro",
    "sg:phone":"+34 985 29 38 06",
    "sg:postcode":"33012",
    "sg:province":"Asturias",
    "sg:website":"www.cajastur.com",
    "wof:name":"Caja De Ahorros De Asturias",
    "wof:placetype":"venue"
},
  "geometry": {"coordinates":[-5.8549408913,43.3701248169],"type":"Point"}
}