{
  "type": "Feature",
  "properties": {
    "addr:full":"Calle de Esteban Marugan, 9 Nava Asuncion Segovia 40450",
    "addr:housenumber":"9",
    "addr:postcode":"40450",
    "addr:street":"Calle De Esteban Marugan",
    "iso:country":"ES",
    "sg:address":"Calle de Esteban Marugan, 9",
    "sg:city":"Nava Asuncion",
    "sg:orig_category":"Mercer\u00cda, Lencer\u00cda (al Por Menor)",
    "sg:phone":"+34 921 58 01 92",
    "sg:postcode":"40450",
    "sg:province":"Segovia",
    "wof:name":"Estebanez Fragua Gloria",
    "wof:placetype":"venue"
},
  "geometry": {"coordinates":[-4.4858689308,41.1542434692],"type":"Point"}
}