{
  "type": "Feature",
  "properties": {
    "iso:country":"ES",
    "sg:address":"Calle de Leopoldo Alas Clarin, 2",
    "sg:city":"Zamora",
    "sg:orig_category":"M\u00c9dicos: Ginecolog\u00cda Y Obstetricia",
    "sg:phone":"+34 980 52 00 51",
    "sg:postcode":"49016",
    "sg:province":"Zamora",
    "wof:name":"Valencia Calderon Abelardo",
    "wof:placetype":"venue"
},
  "geometry": {"coordinates":[-5.7403440475,41.5067176819],"type":"Point"}
}