{
  "type": "Feature",
  "properties": {
    "addr:full":"Calle de Dolores Nebot, 4 Catarroja Valencia 46470",
    "addr:housenumber":"4",
    "addr:postcode":"46470",
    "addr:street":"Calle De Dolores Nebot",
    "iso:country":"ES",
    "sg:address":"Calle de Dolores Nebot, 4",
    "sg:city":"Catarroja",
    "sg:orig_category":"Agencias Y Agentes Comerciales, Representantes",
    "sg:phone":"+34 961 27 03 27",
    "sg:postcode":"46470",
    "sg:province":"Valencia",
    "wof:name":"Garcia Campos Antonio",
    "wof:placetype":"venue"
},
  "geometry": {"coordinates":[-0.401925087,39.4023857117],"type":"Point"}
}