{
  "type": "Feature",
  "properties": {
    "addr:full":"Carrer de Sardenya, 174 Barcelona Barcelona 08013",
    "addr:housenumber":"174",
    "addr:postcode":"08013",
    "addr:street":"Carrer De Sardenya",
    "iso:country":"ES",
    "sg:address":"Carrer de Sardenya, 174",
    "sg:city":"Barcelona",
    "sg:orig_category":"Molduras, Junquillos, Listones Y Molduras Perforadas",
    "sg:phone":"+34 932 65 88 47",
    "sg:postcode":"08013",
    "sg:province":"Barcelona",
    "wof:name":"Dong Fang S.c.p.",
    "wof:placetype":"venue"
},
  "geometry": {"coordinates":[2.1828689575,41.3963851929],"type":"Point"}
}