{
  "type": "Feature",
  "properties": {
    "addr:full":"Pase Alameda, 9 Valencia Valencia 46010",
    "addr:housenumber":"9",
    "addr:postcode":"46010",
    "addr:street":"Alameda",
    "iso:country":"ES",
    "sg:address":"Pase Alameda, 9",
    "sg:city":"Valencia",
    "sg:orig_category":"Edici\u00d3n De Diarios, Revistas, Boletines",
    "sg:phone":"+34 963 69 01 50",
    "sg:postcode":"46010",
    "sg:province":"Valencia",
    "wof:name":"Federico Domenech S.a.",
    "wof:placetype":"venue"
},
  "geometry": {"coordinates":[-0.3653199971,39.4755210876],"type":"Point"}
}