{
  "type": "Feature",
  "properties": {
    "addr:full":"Avda Profesor Tierno Galvan, S/n Guadiaro C\u00e1diz 11311",
    "addr:postcode":"11311",
    "addr:street":"Avda Profesor Tierno Galvan S / N;Ca\u0301Diz",
    "iso:country":"ES",
    "sg:address":"Avda Profesor Tierno Galvan, S/n",
    "sg:city":"Guadiaro",
    "sg:orig_category":"Sanatorios M\u00c9dico",
    "sg:phone":"+34 956 61 40 40",
    "sg:postcode":"11311",
    "sg:province":"C\u00e1diz",
    "wof:name":"Servicio Andaluz De Salud",
    "wof:placetype":"venue"
},
  "geometry": {"coordinates":[-5.3049869537,36.2982521057],"type":"Point"}
}