{
  "type": "Feature",
  "properties": {
    "addr:full":"Calle de Antonio Silva, 28 Algar C\u00e1diz 11639",
    "addr:housenumber":"28",
    "addr:postcode":"11639",
    "addr:street":"Calle De Antonio Silva",
    "iso:country":"ES",
    "sg:address":"Calle de Antonio Silva, 28",
    "sg:city":"Algar",
    "sg:orig_category":"T\u00c9cnicos Veterinarios",
    "sg:phone":"+34 956 71 02 54",
    "sg:postcode":"11639",
    "sg:province":"C\u00e1diz",
    "wof:name":"Sanchez Rodriguez Maria Estefania",
    "wof:placetype":"venue"
},
  "geometry": {"coordinates":[-5.6556777954,36.6557350159],"type":"Point"}
}