{
  "type": "Feature",
  "properties": {
    "iso:country":"ES",
    "sg:address":"Calle de Granada, 42",
    "sg:city":"Ronda",
    "sg:orig_category":"Mec\u00c1nico Del Autom\u00d3vil",
    "sg:phone":"+34 952 87 29 36",
    "sg:postcode":"29400",
    "sg:province":"M\u00e1laga",
    "wof:name":"Gomez Galindo Mariano Manuel",
    "wof:placetype":"venue"
},
  "geometry": {"coordinates":[-5.1601791382,36.744556427],"type":"Point"}
}