{
  "type": "Feature",
  "properties": {
    "iso:country":"ES",
    "sg:address":"Calle de Constitucion Espa\u00d1ola, 19",
    "sg:city":"Almazora",
    "sg:orig_category":"Reposter\u00cdas",
    "sg:phone":"+34 964 55 17 04",
    "sg:postcode":"12550",
    "sg:province":"Castell\u00f3n",
    "wof:name":"Panaderos Pasteleros Miralles S.l.",
    "wof:placetype":"venue"
},
  "geometry": {"coordinates":[-0.0636188984,39.9503974915],"type":"Point"}
}