{
  "type": "Feature",
  "properties": {
    "iso:country":"ES",
    "sg:address":"Calle de Sol, 27",
    "sg:city":"Argamasilla Calatrava",
    "sg:orig_category":"Negocio De Materiales De Construcci\u00d3n",
    "sg:phone":"+34 926 47 71 25",
    "sg:postcode":"13440",
    "sg:province":"Ciudad Real",
    "wof:name":"Escobar Mu\u00f1oz Ciriaco",
    "wof:placetype":"venue"
},
  "geometry": {"coordinates":[-4.0815091133,38.7258682251],"type":"Point"}
}