{
  "type": "Feature",
  "properties": {
    "iso:country":"ES",
    "sg:address":"Calle de Nueva, S/n",
    "sg:city":"Sevilla",
    "sg:orig_category":"Tapicer\u00cdas",
    "sg:phone":"+34 954 43 44 61",
    "sg:postcode":"41008",
    "sg:province":"Sevilla",
    "wof:name":"Linremaro S.l.",
    "wof:placetype":"venue"
},
  "geometry": {"coordinates":[-5.9093689919,37.388885498],"type":"Point"}
}