{
  "type": "Feature",
  "properties": {
    "addr:full":"Tarrio, S/n Vilanova Arousa Pontevedra 36629",
    "addr:postcode":"36629",
    "addr:street":"Tarrio S / N",
    "iso:country":"ES",
    "sg:address":"Tarrio, S/n",
    "sg:city":"Vilanova Arousa",
    "sg:orig_category":"Producci\u00d3n De Abonos Y De Fertilizantes",
    "sg:phone":"+34 986 56 15 67",
    "sg:postcode":"36629",
    "sg:province":"Pontevedra",
    "wof:name":"Servicios Y Manipulaciones Galicia S.l.",
    "wof:placetype":"venue"
},
  "geometry": {"coordinates":[-8.8165578842,42.5573997498],"type":"Point"}
}