{
  "type": "Feature",
  "properties": {
    "addr:full":"Ctra Madrid, Km. 0314,8 Zaragoza Zaragoza 50012",
    "addr:postcode":"50012",
    "addr:street":"Ctra Madrid Km. 0314,8",
    "iso:country":"ES",
    "sg:address":"Ctra Madrid, Km. 0314,8",
    "sg:city":"Zaragoza",
    "sg:orig_category":"Ingenier\u00cda, Centros De Estudios (industria)",
    "sg:phone":"+34 976 30 03 60",
    "sg:postcode":"50012",
    "sg:province":"Zaragoza",
    "sg:website":"www.edasa.com",
    "wof:name":"Edasa",
    "wof:placetype":"venue"
},
  "geometry": {"coordinates":[-0.9379739761,41.6436691284],"type":"Point"}
}