{
  "type": "Feature",
  "properties": {
    "addr:full":"Plaz Barrio Nuevo, 5 Toledo Toledo 45002",
    "addr:housenumber":"5",
    "addr:postcode":"45002",
    "addr:street":"Nuevo",
    "iso:country":"ES",
    "sg:address":"Plaz Barrio Nuevo, 5",
    "sg:city":"Toledo",
    "sg:orig_category":"Caf\u00c9s, Bares, Cervecer\u00cdas",
    "sg:phone":"+34 925 22 56 25",
    "sg:postcode":"45002",
    "sg:province":"Toledo",
    "sg:website":"paginasamarillas.es",
    "wof:name":"Dominguez Gonzalez Pilar",
    "wof:placetype":"venue"
},
  "geometry": {"coordinates":[-4.029941082,39.8567237854],"type":"Point"}
}