{
  "type": "Feature",
  "properties": {
    "addr:full":"Ptda Alzabares Bajo, 181 Elche Alicante 03290",
    "addr:housenumber":"181",
    "addr:postcode":"03290",
    "addr:street":"Ptda Alzabares Bajo",
    "iso:country":"ES",
    "sg:address":"Ptda Alzabares Bajo, 181",
    "sg:city":"Elche",
    "sg:orig_category":"Empresas De Hormig\u00d3n, Hormig\u00d3n Armado Y Pretensado",
    "sg:phone":"+34 965 45 77 57",
    "sg:postcode":"03290",
    "sg:province":"Alicante",
    "wof:name":"Prefabricados Alzabaras Bajo S. L.",
    "wof:placetype":"venue"
},
  "geometry": {"coordinates":[-0.6995239854,38.2634811401],"type":"Point"}
}