{
  "type": "Feature",
  "properties": {
    "iso:country":"ES",
    "sg:address":"Calle de Escuelas (de Las), S/n",
    "sg:city":"Cari\u00f1ena",
    "sg:orig_category":"Centros De Educaci\u00d3n Especial",
    "sg:phone":"+34 976 62 10 11",
    "sg:postcode":"50400",
    "sg:province":"Zaragoza",
    "wof:name":"Direccion Provicial Del Ministerio De Educacion Y Ciencia",
    "wof:placetype":"venue"
},
  "geometry": {"coordinates":[-1.2264670134,41.3356437683],"type":"Point"}
}