{
  "type": "Feature",
  "properties": {
    "addr:full":"Avda Catedratico Soler, 21 Alacant Alicante 03008",
    "addr:housenumber":"21",
    "addr:postcode":"03008",
    "addr:street":"Avda Catedratico Soler",
    "iso:country":"ES",
    "sg:address":"Avda Catedratico Soler, 21",
    "sg:city":"Alacant",
    "sg:orig_category":"Electricidad, Electr\u00d3nica: Suministros (al Por Menor)",
    "sg:phone":"+34 965 12 37 34",
    "sg:postcode":"03008",
    "sg:province":"Alicante",
    "wof:name":"Radio Castilla S.a.",
    "wof:placetype":"venue"
},
  "geometry": {"coordinates":[-0.497213006,38.3396377563],"type":"Point"}
}