{
  "type": "Feature",
  "properties": {
    "iso:country":"ES",
    "sg:address":"Plaz Nuestra Se\u00d1ora Del Pilar, 1",
    "sg:city":"Madrid",
    "sg:orig_category":"Arquitectos",
    "sg:phone":"+34 914 11 71 33",
    "sg:postcode":"28002",
    "sg:province":"Madrid",
    "wof:name":"Rofso Lopez Angel Luis",
    "wof:placetype":"venue"
},
  "geometry": {"coordinates":[-3.6764390469,40.4403076172],"type":"Point"}
}