{
  "type": "Feature",
  "properties": {
    "addr:full":"C/ Mestre Obrador, 12 Ferreries Islas Baleares 07750",
    "addr:housenumber":"12",
    "addr:postcode":"07750",
    "addr:street":"C / Mestre Obrador",
    "iso:country":"ES",
    "sg:address":"C/ Mestre Obrador, 12",
    "sg:city":"Ferreries",
    "sg:orig_category":"Laboratorios Y Trabajos De Fotograf\u00cda, V\u00cddeo Y Cine",
    "sg:phone":"+34 971 37 38 63",
    "sg:postcode":"07750",
    "sg:province":"Islas Baleares",
    "wof:name":"Pons Carreras Juana Isabel",
    "wof:placetype":"venue"
},
  "geometry": {"coordinates":[4.0127868652,39.9842300415],"type":"Point"}
}