{
  "type": "Feature",
  "properties": {
    "iso:country":"ES",
    "sg:address":"Carrer de Prat De La Riba, 32",
    "sg:city":"Santa Perpetua De Mogoda",
    "sg:orig_category":"Panader\u00cdas, Panader\u00cdas",
    "sg:phone":"+34 935 74 21 92",
    "sg:postcode":"08130",
    "sg:province":"Barcelona",
    "wof:name":"Pastisseria Granja L'anec Scp",
    "wof:placetype":"venue"
},
  "geometry": {"coordinates":[2.1815490723,41.5354309082],"type":"Point"}
}