{
  "type": "Feature",
  "properties": {
    "iso:country":"ES",
    "sg:address":"Carrer de Miguel De Cervantes, 1",
    "sg:city":"Lloret Mar",
    "sg:orig_category":"Bisuteros (fabricaci\u00d3n, Al Por Mayor)",
    "sg:phone":"+34 972 36 82 62",
    "sg:postcode":"17310",
    "sg:province":"Girona",
    "wof:name":"Maderas Nordicas Blanes 2010 S.l.",
    "wof:placetype":"venue"
},
  "geometry": {"coordinates":[2.8473529816,41.6988830566],"type":"Point"}
}