{
  "type": "Feature",
  "properties": {
    "iso:country":"ES",
    "sg:address":"Avda Vi\u00d1uelas (de), 45",
    "sg:city":"Tres Cantos",
    "sg:orig_category":"Promotores Constructores",
    "sg:phone":"+34 918 06 07 80",
    "sg:postcode":"28760",
    "sg:province":"Madrid",
    "wof:name":"Jodar Madrigal Pablo Jose",
    "wof:placetype":"venue"
},
  "geometry": {"coordinates":[-3.7000539303,40.5968284607],"type":"Point"}
}