{
  "type": "Feature",
  "properties": {
    "iso:country":"ES",
    "sg:address":"Avda Logro\u00d1o, 9",
    "sg:city":"Haro",
    "sg:orig_category":"Arquitectos",
    "sg:phone":"+34 941 30 41 75",
    "sg:postcode":"26200",
    "sg:province":"La Rioja",
    "wof:name":"Ibarra Leon Francisco",
    "wof:placetype":"venue"
},
  "geometry": {"coordinates":[-2.8460009098,42.5718421936],"type":"Point"}
}