{
  "type": "Feature",
  "properties": {
    "addr:full":"Calle de Aladierna, 14 Madrid Madrid 28021",
    "addr:housenumber":"14",
    "addr:postcode":"madrid;28021",
    "addr:street":"Calle De Aladierna",
    "iso:country":"ES",
    "sg:address":"Calle de Aladierna, 14",
    "sg:city":"Madrid",
    "sg:orig_category":"Molduras, Junquillos, Listones Y Molduras Perforadas",
    "sg:phone":"+34 917 97 64 96",
    "sg:postcode":"28021",
    "sg:province":"Madrid",
    "wof:name":"Casado Pe\u00f1alosa Ciriaca",
    "wof:placetype":"venue"
},
  "geometry": {"coordinates":[-3.7110817432,40.3457336426],"type":"Point"}
}