{
  "type": "Feature",
  "properties": {
    "iso:country":"ES",
    "sg:address":"Avda Peruleiro, 10",
    "sg:city":"Coru\u00d1a",
    "sg:orig_category":"Molduras, Junquillos, Listones Y Molduras Perforadas",
    "sg:phone":"+34 981 27 44 08",
    "sg:postcode":"15011",
    "sg:province":"La Coru\u00f1a",
    "wof:name":"Guijarro Lazcano Juan Jose",
    "wof:placetype":"venue"
},
  "geometry": {"coordinates":[-8.4215774536,43.3673057556],"type":"Point"}
}