{
  "type": "Feature",
  "properties": {
    "addr:full":"Cmno Pocico (el), 1 Aguadulce Almer\u00eda 04720",
    "addr:housenumber":"1",
    "addr:postcode":"04720",
    "addr:street":"Cmno Pocico El;Almeri\u0301A",
    "iso:country":"ES",
    "sg:address":"Cmno Pocico (el), 1",
    "sg:city":"Aguadulce",
    "sg:orig_category":"Psic\u00d3logos",
    "sg:phone":"+34 950 34 71 95",
    "sg:postcode":"04720",
    "sg:province":"Almer\u00eda",
    "wof:name":"Barema Seguridad S.l.l.",
    "wof:placetype":"venue"
},
  "geometry": {"coordinates":[-2.5974500179,36.801410675],"type":"Point"}
}