{
  "type": "Feature",
  "properties": {
    "iso:country":"ES",
    "sg:address":"Calle de Fuente Nueva, 41",
    "sg:city":"Algeciras",
    "sg:orig_category":"Laboratorios Y Cl\u00cdnicas Veterinarias",
    "sg:phone":"+34 956 66 83 70",
    "sg:postcode":"11203",
    "sg:province":"C\u00e1diz",
    "wof:name":"Fernandez Guzman Enrique",
    "wof:placetype":"venue"
},
  "geometry": {"coordinates":[-5.4537138939,36.130897522],"type":"Point"}
}