{
  "type": "Feature",
  "properties": {
    "iso:country":"ES",
    "sg:address":"Calle de Goya, 57",
    "sg:city":"Madrid",
    "sg:orig_category":"Zapatos (al Por Menor)",
    "sg:phone":"+34 915 76 91 28",
    "sg:postcode":"28001",
    "sg:province":"Madrid",
    "wof:name":"Zapatones S.l.",
    "wof:placetype":"venue"
},
  "geometry": {"coordinates":[-3.6810510159,40.4251899719],"type":"Point"}
}