{
  "type": "Feature",
  "properties": {
    "addr:full":"Carrer de Miquel Santandreu, 19 Palma Islas Baleares 07006",
    "addr:housenumber":"19",
    "addr:postcode":"07006",
    "addr:street":"Carrer De Miquel Santandreu",
    "iso:country":"ES",
    "sg:address":"Carrer de Miquel Santandreu, 19",
    "sg:city":"Palma",
    "sg:orig_category":"Peluqueros: De Se\u00d1oras",
    "sg:phone":"+34 971 46 27 55",
    "sg:postcode":"07006",
    "sg:province":"Islas Baleares",
    "wof:name":"Rodriguez Piza Maria",
    "wof:placetype":"venue"
},
  "geometry": {"coordinates":[2.6590750217,39.5676841736],"type":"Point"}
}