{
  "type": "Feature",
  "properties": {
    "addr:full":"Calle de Pintos, General, 26 Melilla Melilla 52005",
    "addr:housenumber":"26",
    "addr:postcode":"52005",
    "addr:street":"Calle De Pintos General",
    "iso:country":"ES",
    "sg:address":"Calle de Pintos, General, 26",
    "sg:city":"Melilla",
    "sg:orig_category":"Reposter\u00cdas",
    "sg:phone":"+34 952 67 13 49",
    "sg:postcode":"52005",
    "sg:province":"Melilla",
    "wof:name":"Mohtar Amar Habiba",
    "wof:placetype":"venue"
},
  "geometry": {"coordinates":[-2.9442741871,35.2867927551],"type":"Point"}
}