{
  "type": "Feature",
  "properties": {
    "iso:country":"ES",
    "sg:address":"Rua Illas Cies, 30",
    "sg:city":"Canido",
    "sg:orig_category":"Arquitectos",
    "sg:phone":"+34 986 36 67 46",
    "sg:postcode":"36350",
    "sg:province":"Pontevedra",
    "wof:name":"Laguna Fondovila Roberto",
    "wof:placetype":"venue"
},
  "geometry": {"coordinates":[-8.8062238693,42.141494751],"type":"Point"}
}