{
  "type": "Feature",
  "properties": {
    "addr:full":"Calle de Silvestre Perez, 14 Zaragoza Zaragoza 50002",
    "addr:housenumber":"14",
    "addr:postcode":"50002",
    "addr:street":"Calle De Silvestre Perez",
    "iso:country":"ES",
    "sg:address":"Calle de Silvestre Perez, 14",
    "sg:city":"Zaragoza",
    "sg:orig_category":"Empresas De Pintura Y Revestimientos",
    "sg:phone":"+34 976 42 06 37",
    "sg:postcode":"50002",
    "sg:province":"Zaragoza",
    "wof:name":"Lorente Serrano Aurelio",
    "wof:placetype":"venue"
},
  "geometry": {"coordinates":[-0.8625329733,41.6481704712],"type":"Point"}
}