{
  "type": "Feature",
  "properties": {
    "addr:full":"Calle de San Agustin, S/n Mota Cuervo Cuenca 16630",
    "addr:postcode":"16630",
    "addr:street":"Calle De San Agustin S / N Mota",
    "iso:country":"ES",
    "sg:address":"Calle de San Agustin, S/n",
    "sg:city":"Mota Cuervo",
    "sg:orig_category":"Productores Recolectores, Venta Directa De Vinos",
    "sg:phone":"+34 967 18 22 77",
    "sg:postcode":"16630",
    "sg:province":"Cuenca",
    "wof:name":"Santa Rita S.a.t.",
    "wof:placetype":"venue"
},
  "geometry": {"coordinates":[-2.8707540035,39.5063438416],"type":"Point"}
}