{
  "type": "Feature",
  "properties": {
    "addr:full":"Carrer de Bertran, 87 Barcelona Barcelona 08023",
    "addr:housenumber":"87",
    "addr:postcode":"08023",
    "addr:street":"Carrer De Bertran",
    "iso:country":"ES",
    "sg:address":"Carrer de Bertran, 87",
    "sg:city":"Barcelona",
    "sg:orig_category":"Arquitectos",
    "sg:phone":"+34 932 11 95 20",
    "sg:postcode":"08023",
    "sg:province":"Barcelona",
    "wof:name":"Feliu Lucas Georgina",
    "wof:placetype":"venue"
},
  "geometry": {"coordinates":[2.1395690441,41.4083137512],"type":"Point"}
}