{
  "type": "Feature",
  "properties": {
    "iso:country":"ES",
    "sg:address":"Calle de Anastasio Aroca, 7",
    "sg:city":"Madrid",
    "sg:orig_category":"Ebanister\u00cda",
    "sg:phone":"+34 914 15 21 88",
    "sg:postcode":"28002",
    "sg:province":"Madrid",
    "wof:name":"Zurdo Cano Antonio",
    "wof:placetype":"venue"
},
  "geometry": {"coordinates":[-3.6730120182,40.4408874512],"type":"Point"}
}