{
  "type": "Feature",
  "properties": {
    "addr:full":"Carr Campanitx, 9 Eivissa Islas Baleares 07800",
    "addr:housenumber":"9",
    "addr:postcode":"07800",
    "addr:street":"Carr Campanitx",
    "iso:country":"ES",
    "sg:address":"Carr Campanitx, 9",
    "sg:city":"Eivissa",
    "sg:orig_category":"Ropa Para Se\u00d1oras (al Por Menor)",
    "sg:phone":"+34 971 19 07 22",
    "sg:postcode":"07800",
    "sg:province":"Islas Baleares",
    "wof:name":"Castellon Benegas Rafaela",
    "wof:placetype":"venue"
},
  "geometry": {"coordinates":[1.41781497,38.9134521484],"type":"Point"}
}