{
  "type": "Feature",
  "properties": {
    "addr:full":"Calle de Pensamiento, 10 Madrid Madrid 28020",
    "addr:housenumber":"10",
    "addr:postcode":"madrid;28020",
    "addr:street":"Calle De Pensamiento",
    "iso:country":"ES",
    "sg:address":"Calle de Pensamiento, 10",
    "sg:city":"Madrid",
    "sg:orig_category":"Fabricaci\u00d3n De Ventanas",
    "sg:phone":"+34 915 79 30 54",
    "sg:postcode":"28020",
    "sg:province":"Madrid",
    "wof:name":"Lopez Serra Maria Del Mar",
    "wof:placetype":"venue"
},
  "geometry": {"coordinates":[-3.6981155872,40.4594612122],"type":"Point"}
}