{
  "type": "Feature",
  "properties": {
    "iso:country":"ES",
    "sg:address":"Calle de Franco Y Lopez, 30",
    "sg:city":"Zaragoza",
    "sg:orig_category":"Florister\u00cdas",
    "sg:phone":"+34 976 35 78 34",
    "sg:postcode":"50005",
    "sg:province":"Zaragoza",
    "wof:name":"Lopez Pinilla Francisco",
    "wof:placetype":"venue"
},
  "geometry": {"coordinates":[-0.9014030099,41.6475143433],"type":"Point"}
}