{
  "type": "Feature",
  "properties": {
    "addr:full":"Carrer de Forn Nou Del, 20 Valls Tarragona 43800",
    "addr:housenumber":"20",
    "addr:postcode":"43800",
    "addr:street":"Carrer De Forn Nou Del",
    "iso:country":"ES",
    "sg:address":"Carrer de Forn Nou Del, 20",
    "sg:city":"Valls",
    "sg:orig_category":"Zapatos (al Por Menor)",
    "sg:phone":"+34 977 60 10 71",
    "sg:postcode":"43800",
    "sg:province":"Tarragona",
    "wof:name":"Jove Fabregas Francisco",
    "wof:placetype":"venue"
},
  "geometry": {"coordinates":[1.2500020266,41.2846183777],"type":"Point"}
}