{
  "type": "Feature",
  "properties": {
    "addr:full":"Calle de Don Jaime I, 42 Zaragoza Zaragoza 50001",
    "addr:housenumber":"42",
    "addr:postcode":"50001",
    "addr:street":"Calle De Don Jaime I",
    "iso:country":"ES",
    "sg:address":"Calle de Don Jaime I, 42",
    "sg:city":"Zaragoza",
    "sg:classifiers":[
        {
            "category":"Personal",
            "subcategory":"Barber",
            "type":"Services"
        }
    ],
    "sg:phone":"+34 976 29 57 35",
    "sg:postcode":"50001",
    "sg:province":"Zaragoza",
    "sg:tags":[
        "caballeros",
        "de",
        "peluqueros"
    ],
    "wof:name":"Sebastian Anson Pascual",
    "wof:placetype":"venue"
},
  "geometry": {"coordinates":[-0.877425015,41.6542396545],"type":"Point"}
}