{
  "type": "Feature",
  "properties": {
    "iso:country":"ES",
    "sg:address":"Carretera General, Km. 0037,0",
    "sg:city":"Galdar",
    "sg:orig_category":"Enfermeras: Consultas, Atenci\u00d3n A Domicilio",
    "sg:phone":"+34 928 88 01 86",
    "sg:postcode":"35460",
    "sg:province":"Las Palmas",
    "wof:name":"Mendoza Padron Juan Daniel",
    "wof:placetype":"venue"
},
  "geometry": {"coordinates":[-15.6528720856,28.1450138092],"type":"Point"}
}