{
  "type": "Feature",
  "properties": {
    "addr:full":"Avgd Alcalde Porqueres, 105 Lleida Lleida 25005",
    "addr:housenumber":"105",
    "addr:postcode":"25005",
    "addr:street":"Alcalde Porqueres",
    "iso:country":"ES",
    "sg:address":"Avgd Alcalde Porqueres, 105",
    "sg:city":"Lleida",
    "sg:orig_category":"Comercio, Reparaci\u00d3n De Motocicletas, Bicicletas Y Piezas Sueltas",
    "sg:phone":"+34 973 24 10 15",
    "sg:postcode":"25005",
    "sg:province":"Lleida",
    "wof:name":"Cabrera Hidalgo Francisco",
    "wof:placetype":"venue"
},
  "geometry": {"coordinates":[0.621810019,41.6307029724],"type":"Point"}
}