{
  "type": "Feature",
  "properties": {
    "iso:country":"ES",
    "sg:address":"Avda Claveles, 23",
    "sg:city":"Majadahonda",
    "sg:orig_category":"Asesor\u00cda De Comercio Exterior",
    "sg:phone":"+34 916 34 04 42",
    "sg:postcode":"28220",
    "sg:province":"Madrid",
    "wof:name":"Palacios Esteban Carmelo",
    "wof:placetype":"venue"
},
  "geometry": {"coordinates":[-3.8632040024,40.4715690613],"type":"Point"}
}