{
  "type": "Feature",
  "properties": {
    "iso:country":"ES",
    "sg:address":"Cami Platera, S/n",
    "sg:city":"Estartit",
    "sg:orig_category":"Ense\u00d1anza Agr\u00cdcola",
    "sg:phone":"+34 972 75 02 68",
    "sg:postcode":"17258",
    "sg:province":"Girona",
    "wof:name":"Colonies R.v.s.a.",
    "wof:placetype":"venue"
},
  "geometry": {"coordinates":[3.1995449066,42.053730011],"type":"Point"}
}