{
  "type": "Feature",
  "properties": {
    "addr:full":"Carretera De Caceres-alcantara, S/n Brozas C\u00e1ceres 10950",
    "addr:housenumber":"s / n",
    "addr:postcode":"10950",
    "addr:street":"Carretera De Caceres-Alcantara;Ca\u0301Ceres",
    "iso:country":"ES",
    "sg:address":"Carretera De Caceres-alcantara, S/n",
    "sg:city":"Brozas",
    "sg:orig_category":"Restaurantes",
    "sg:phone":"+34 927 39 52 03",
    "sg:postcode":"10950",
    "sg:province":"C\u00e1ceres",
    "wof:name":"Hotel La Posada S.l.",
    "wof:placetype":"venue"
},
  "geometry": {"coordinates":[-6.7763600349,39.6160469055],"type":"Point"}
}