{
  "type": "Feature",
  "properties": {
    "addr:full":"Avda Jerez, S/n Sevilla Sevilla 41014",
    "addr:housenumber":"s / n",
    "addr:postcode":"41014",
    "addr:street":"Avda Jerez",
    "iso:country":"ES",
    "sg:address":"Avda Jerez, S/n",
    "sg:city":"Sevilla",
    "sg:orig_category":"Mec\u00c1nico Del Autom\u00d3vil",
    "sg:phone":"+34 954 69 34 03",
    "sg:postcode":"41014",
    "sg:province":"Sevilla",
    "wof:name":"Maroto Naranjo Andres",
    "wof:placetype":"venue"
},
  "geometry": {"coordinates":[-5.9662737846,37.3267402649],"type":"Point"}
}