{
  "type": "Feature",
  "properties": {
    "addr:full":"Calle de Albareda, S/n Palmas De Gran Canaria Las Palmas 35008",
    "addr:housenumber":"s",
    "addr:postcode":"35008",
    "addr:street":"Calle De Albareda;/ N",
    "iso:country":"ES",
    "sg:address":"Calle de Albareda, S/n",
    "sg:city":"Palmas De Gran Canaria",
    "sg:orig_category":"Distribuci\u00d3n De Petr\u00d3leo Y Derivados",
    "sg:phone":"+34 928 46 17 50",
    "sg:postcode":"35008",
    "sg:province":"Las Palmas",
    "wof:name":"Barreiro Grande Maria Teresa",
    "wof:placetype":"venue"
},
  "geometry": {"coordinates":[-15.4308443069,28.1419963837],"type":"Point"}
}