{
  "type": "Feature",
  "properties": {
    "iso:country":"ES",
    "sg:address":"Carrer de Saragossa, 7",
    "sg:city":"Terrassa",
    "sg:orig_category":"Farmacias",
    "sg:phone":"+34 937 85 09 18",
    "sg:postcode":"08227",
    "sg:province":"Barcelona",
    "wof:name":"Rubio Ingerto Maria Isabel",
    "wof:placetype":"venue"
},
  "geometry": {"coordinates":[2.0402441025,41.5616111755],"type":"Point"}
}