{
  "type": "Feature",
  "properties": {
    "addr:full":"Ctra Alicante-valencia, Km. 0114,0 S. Juan Alicante Alicante 03550",
    "addr:postcode":"03550",
    "addr:street":"Ctra Alicante-Valencia Km. 0114,0 S. Juan",
    "iso:country":"ES",
    "sg:address":"Ctra Alicante-valencia, Km. 0114,0",
    "sg:city":"S. Juan Alicante",
    "sg:orig_category":"Promotores Constructores",
    "sg:phone":"+34 965 94 01 94",
    "sg:postcode":"03550",
    "sg:province":"Alicante",
    "wof:name":"Vallemar Esp S.l",
    "wof:placetype":"venue"
},
  "geometry": {"coordinates":[-0.4289290011,38.400390625],"type":"Point"}
}