{
  "type": "Feature",
  "properties": {
    "addr:full":"Avda Vi\u00d1uelas (de), 17 Tres Cantos Madrid 28760",
    "addr:housenumber":"17",
    "addr:postcode":"28760",
    "addr:street":"Avda Vin\u0303Uelas De",
    "iso:country":"ES",
    "sg:address":"Avda Vi\u00d1uelas (de), 17",
    "sg:city":"Tres Cantos",
    "sg:orig_category":"Laboratorios Y Cl\u00cdnicas Veterinarias",
    "sg:phone":"+34 918 04 32 15",
    "sg:postcode":"28760",
    "sg:province":"Madrid",
    "wof:name":"Chamorro Jambrina Maria Cruz",
    "wof:placetype":"venue"
},
  "geometry": {"coordinates":[-3.7050991058,40.5960617065],"type":"Point"}
}