{
  "type": "Feature",
  "properties": {
    "addr:full":"Calle de Miguel Marquez, 52 Fuengirola M\u00e1laga 29640",
    "addr:housenumber":"52",
    "addr:postcode":"29640",
    "addr:street":"Calle De Miguel Marquez;Ma\u0301Laga",
    "iso:country":"ES",
    "sg:address":"Calle de Miguel Marquez, 52",
    "sg:city":"Fuengirola",
    "sg:orig_category":"Agencias Y Agentes Comerciales, Representantes",
    "sg:phone":"+34 952 47 90 63",
    "sg:postcode":"29640",
    "sg:province":"M\u00e1laga",
    "wof:name":"Fortes Toledo Manuel",
    "wof:placetype":"venue"
},
  "geometry": {"coordinates":[-4.6239590645,36.5346984863],"type":"Point"}
}