{
  "type": "Feature",
  "properties": {
    "addr:full":"Carrer de Jocs Florals, 77 Barcelona Barcelona 08014",
    "addr:housenumber":"77",
    "addr:postcode":"08014",
    "addr:street":"Carrer De Jocs Florals",
    "iso:country":"ES",
    "sg:address":"Carrer de Jocs Florals, 77",
    "sg:city":"Barcelona",
    "sg:classifiers":[
        {
            "category":"Personal",
            "subcategory":"Barber",
            "type":"Services"
        }
    ],
    "sg:phone":"+34 934 21 97 26",
    "sg:postcode":"08014",
    "sg:province":"Barcelona",
    "sg:tags":[
        "caballeros",
        "de",
        "peluqueros"
    ],
    "wof:name":"Rafols Sole Jose",
    "wof:placetype":"venue"
},
  "geometry": {"coordinates":[2.1352510452,41.3731384277],"type":"Point"}
}