{
  "type": "Feature",
  "properties": {
    "iso:country":"ES",
    "sg:address":"Carr Ultonia, 9",
    "sg:city":"Girona",
    "sg:orig_category":"Abogados",
    "sg:phone":"+34 972 21 32 19",
    "sg:postcode":"17002",
    "sg:province":"Girona",
    "wof:name":"Gomez Simon Francisco",
    "wof:placetype":"venue"
},
  "geometry": {"coordinates":[2.8229329586,41.9787483215],"type":"Point"}
}