{
  "type": "Feature",
  "properties": {
    "iso:country":"ES",
    "sg:address":"Calle de Limoneros, 8",
    "sg:city":"Padron",
    "sg:orig_category":"Peluqueros: De Se\u00d1oras",
    "sg:phone":"+34 981 81 15 53",
    "sg:postcode":"15900",
    "sg:province":"La Coru\u00f1a",
    "wof:name":"Garcia Rial Maria Rosario",
    "wof:placetype":"venue"
},
  "geometry": {"coordinates":[-8.6591444016,42.7387466431],"type":"Point"}
}