{
  "type": "Feature",
  "properties": {
    "iso:country":"ES",
    "sg:address":"Av Cerdanya (la), 49",
    "sg:city":"Bellver Cerdanya",
    "sg:orig_category":"Empresas De Carpinter\u00cda De Madera",
    "sg:phone":"+34 973 51 00 71",
    "sg:postcode":"25720",
    "sg:province":"Lleida",
    "wof:name":"Braipont S. L.",
    "wof:placetype":"venue"
},
  "geometry": {"coordinates":[1.7808669806,42.3699378967],"type":"Point"}
}