{
  "type": "Feature",
  "properties": {
    "iso:country":"ES",
    "sg:address":"Calle de Canovas Del Castillo, S/n",
    "sg:city":"Valladolid",
    "sg:orig_category":"Zapatos (al Por Menor)",
    "sg:phone":"+34 983 20 16 79",
    "sg:postcode":"47002",
    "sg:province":"Valladolid",
    "wof:name":"Iglesias Sanz Jose Manuel",
    "wof:placetype":"venue"
},
  "geometry": {"coordinates":[-4.7253975868,41.6520957947],"type":"Point"}
}