{
  "type": "Feature",
  "properties": {
    "addr:full":"Calle de Hermanos Machado, 10 Valencia Ventoso Badajoz 06330",
    "addr:housenumber":"10",
    "addr:postcode":"06330",
    "addr:street":"Calle De Hermanos Machado",
    "iso:country":"ES",
    "sg:address":"Calle de Hermanos Machado, 10",
    "sg:city":"Valencia Ventoso",
    "sg:orig_category":"Negocio De Materiales De Construcci\u00d3n",
    "sg:phone":"+34 924 56 27 87",
    "sg:postcode":"06330",
    "sg:province":"Badajoz",
    "wof:name":"Materiales San Isidro S.c.",
    "wof:placetype":"venue"
},
  "geometry": {"coordinates":[-6.4768052101,38.2664337158],"type":"Point"}
}