{
  "type": "Feature",
  "properties": {
    "iso:country":"ES",
    "sg:address":"Madame Courie-p I Llanos Jarata, 131",
    "sg:city":"Montilla",
    "sg:orig_category":"Fabricaci\u00d3n De Muebles De Cocina",
    "sg:phone":"+34 957 65 30 22",
    "sg:postcode":"14550",
    "sg:province":"C\u00f3rdoba",
    "wof:name":"Tepra Madera S.c.a",
    "wof:placetype":"venue"
},
  "geometry": {"coordinates":[-4.6404590607,37.58177948],"type":"Point"}
}