{
  "type": "Feature",
  "properties": {
    "addr:full":"Calle de Asilo, S/n Alacant Alicante 03007",
    "addr:housenumber":"/ n",
    "addr:postcode":"03007",
    "addr:street":"Calle De Asilo",
    "iso:country":"ES",
    "sg:address":"Calle de Asilo, S/n",
    "sg:city":"Alacant",
    "sg:orig_category":"Alimentaci\u00d3n General (al Por Menor)",
    "sg:phone":"+34 965 10 26 11",
    "sg:postcode":"03007",
    "sg:province":"Alicante",
    "wof:name":"Cano Torregrosa Jose Isabel",
    "wof:placetype":"venue"
},
  "geometry": {"coordinates":[-0.5048786998,38.3420753479],"type":"Point"}
}