{
  "type": "Feature",
  "properties": {
    "addr:full":"Calle de Constitucion (de La), 87 Alcobendas Madrid 28100",
    "addr:housenumber":"87",
    "addr:postcode":"28100",
    "addr:street":"Calle De Constitucion De La",
    "iso:country":"ES",
    "sg:address":"Calle de Constitucion (de La), 87",
    "sg:city":"Alcobendas",
    "sg:orig_category":"Cl\u00cdnicas M\u00c9dicas",
    "sg:phone":"+34 916 52 75 18",
    "sg:postcode":"28100",
    "sg:province":"Madrid",
    "wof:name":"Sonrisa 10 S.l.",
    "wof:placetype":"venue"
},
  "geometry": {"coordinates":[-3.6408457756,40.5445137024],"type":"Point"}
}