{
  "type": "Feature",
  "properties": {
    "iso:country":"ES",
    "sg:address":"Carrer de Francesc Layret, 12",
    "sg:city":"Molins Rei",
    "sg:orig_category":"Maquinaria Para Industrias Diversas",
    "sg:phone":"+34 936 80 00 06",
    "sg:postcode":"08750",
    "sg:province":"Barcelona",
    "wof:name":"Gutierrez Aviles Antonio",
    "wof:placetype":"venue"
},
  "geometry": {"coordinates":[2.0232930183,41.4047393799],"type":"Point"}
}