{
  "type": "Feature",
  "properties": {
    "addr:full":"Avda Alarcos (de), S/n Miguelturra Ciudad Real 13170",
    "addr:postcode":"13170",
    "addr:street":"Avda Alarcos De S / N Miguelturra",
    "iso:country":"ES",
    "sg:address":"Avda Alarcos (de), S/n",
    "sg:city":"Miguelturra",
    "sg:orig_category":"Panader\u00cdas, Panader\u00cdas",
    "sg:phone":"+34 926 27 21 32",
    "sg:postcode":"13170",
    "sg:province":"Ciudad Real",
    "wof:name":"Panificadora Calcade\u00f1a S.l.",
    "wof:placetype":"venue"
},
  "geometry": {"coordinates":[-3.8971140385,38.9654388428],"type":"Point"}
}