{
  "type": "Feature",
  "properties": {
    "iso:country":"ES",
    "sg:address":"Calle de Doctor Blanco Soler, 4",
    "sg:city":"Cordoba",
    "sg:orig_category":"M\u00c9dicos: Anestesiolog\u00cda Y Reanimaci\u00d3n Quir\u00dargica",
    "sg:phone":"+34 957 29 59 96",
    "sg:postcode":"14004",
    "sg:province":"C\u00f3rdoba",
    "wof:name":"Guerrero Arjona Andres",
    "wof:placetype":"venue"
},
  "geometry": {"coordinates":[-4.7849555016,37.8789367676],"type":"Point"}
}