{
  "type": "Feature",
  "properties": {
    "iso:country":"ES",
    "sg:address":"Calle de Cordoba, 4",
    "sg:city":"Ibi",
    "sg:orig_category":"Cajas Y Embalajes Met\u00c1licos",
    "sg:phone":"+34 966 55 20 19",
    "sg:postcode":"03440",
    "sg:province":"Alicante",
    "sg:website":"www.litochap.com",
    "wof:name":"Litochap S.l.",
    "wof:placetype":"venue"
},
  "geometry": {"coordinates":[-0.5949050188,38.6165237427],"type":"Point"}
}