{
  "type": "Feature",
  "properties": {
    "addr:full":"Pl Espanya, 16 Cambrils Tarragona 43850",
    "addr:housenumber":"16",
    "addr:postcode":"43850",
    "addr:street":"Pl Espanya",
    "iso:country":"ES",
    "sg:address":"Pl Espanya, 16",
    "sg:city":"Cambrils",
    "sg:orig_category":"Frutas, Legumbres Frescas Y Tempranas (al Por Menor)",
    "sg:phone":"+34 977 36 11 98",
    "sg:postcode":"43850",
    "sg:province":"Tarragona",
    "wof:name":"Garriga Sabate Francisco",
    "wof:placetype":"venue"
},
  "geometry": {"coordinates":[1.0530619621,41.0744743347],"type":"Point"}
}