{
  "type": "Feature",
  "properties": {
    "iso:country":"ES",
    "sg:address":"Carrer de Advocat Cirera, 2",
    "sg:city":"Sabadell",
    "sg:orig_category":"Ingenier\u00cda, Centros De Estudios (diversos)",
    "sg:phone":"+34 937 25 99 88",
    "sg:postcode":"08201",
    "sg:province":"Barcelona",
    "wof:name":"Costajussa Relat Esteve Maria",
    "wof:placetype":"venue"
},
  "geometry": {"coordinates":[2.1090140343,41.5460548401],"type":"Point"}
}