{
  "type": "Feature",
  "properties": {
    "iso:country":"ES",
    "sg:address":"Carr General Brito, 31",
    "sg:city":"Lleida",
    "sg:orig_category":"Lavado, Limpieza De Veh\u00cdculos",
    "sg:phone":"+34 973 22 30 26",
    "sg:postcode":"25007",
    "sg:province":"Lleida",
    "wof:name":"Espa\u00f1ol Mir Jorge",
    "wof:placetype":"venue"
},
  "geometry": {"coordinates":[0.6340060234,41.6174659729],"type":"Point"}
}