{
  "type": "Feature",
  "properties": {
    "iso:country":"ES",
    "sg:address":"Via Ronda (de), 52",
    "sg:city":"Playa",
    "sg:orig_category":"Heladeros",
    "sg:phone":"+34 962 85 19 53",
    "sg:postcode":"46780",
    "sg:province":"Valencia",
    "wof:name":"Helados La Ibense S.l.",
    "wof:placetype":"venue"
},
  "geometry": {"coordinates":[-0.1179220006,38.9189491272],"type":"Point"}
}