{
  "type": "Feature",
  "properties": {
    "addr:full":"Calle de Almendro, 22 Zafra Badajoz 06300",
    "addr:housenumber":"22",
    "addr:postcode":"06300",
    "addr:street":"Calle De Almendro",
    "iso:country":"ES",
    "sg:address":"Calle de Almendro, 22",
    "sg:city":"Zafra",
    "sg:orig_category":"Imprenta",
    "sg:phone":"+34 924 55 11 49",
    "sg:postcode":"06300",
    "sg:province":"Badajoz",
    "wof:name":"Imprenta Castro S.l.",
    "wof:placetype":"venue"
},
  "geometry": {"coordinates":[-6.4214696884,38.4227600098],"type":"Point"}
}