{
  "type": "Feature",
  "properties": {
    "iso:country":"ES",
    "sg:address":"Riera Vallromanes, 42",
    "sg:city":"Vallromanes",
    "sg:orig_category":"Droguer\u00cdas (al Por Menor)",
    "sg:phone":"+34 935 72 97 69",
    "sg:postcode":"08188",
    "sg:province":"Barcelona",
    "wof:name":"Florez Bosque Daniel",
    "wof:placetype":"venue"
},
  "geometry": {"coordinates":[2.2975182533,41.5233879089],"type":"Point"}
}