{
  "type": "Feature",
  "properties": {
    "iso:country":"ES",
    "sg:address":"Camino Del Salado, S/n",
    "sg:city":"Priego Cordoba",
    "sg:orig_category":"Aceites Y Grasas Alimentarias (fabricaci\u00d3n, Al Por Mayor)",
    "sg:phone":"+34 957 54 09 41",
    "sg:postcode":"14800",
    "sg:province":"C\u00f3rdoba",
    "wof:name":"Hijos De Garofano S. L.",
    "wof:placetype":"venue"
},
  "geometry": {"coordinates":[-4.211479187,37.3848991394],"type":"Point"}
}