{
  "type": "Feature",
  "properties": {
    "iso:country":"ES",
    "sg:address":"El Tobar (pol Ind B), 1",
    "sg:city":"Olivares",
    "sg:orig_category":"Venta, Montaje De Neum\u00c1ticos",
    "sg:phone":"+34 954 11 03 62",
    "sg:postcode":"41804",
    "sg:province":"Sevilla",
    "wof:name":"Morales Colorado Jesus",
    "wof:placetype":"venue"
},
  "geometry": {"coordinates":[-6.1529588699,37.4218406677],"type":"Point"}
}