{
  "type": "Feature",
  "properties": {
    "addr:full":"Monasterio Urdax, 12 Iru\u00f1a Navarra 31011",
    "addr:housenumber":"12",
    "addr:postcode":"31011",
    "addr:street":"Urdax",
    "iso:country":"ES",
    "sg:address":"Monasterio Urdax, 12",
    "sg:city":"Iru\u00f1a",
    "sg:orig_category":"M\u00c9dicos: Otorrinolaringolog\u00cda",
    "sg:phone":"+34 948 26 19 97",
    "sg:postcode":"31011",
    "sg:province":"Navarra",
    "wof:name":"Saiz Calleja Miguel Angel",
    "wof:placetype":"venue"
},
  "geometry": {"coordinates":[-1.6573870182,42.813999176],"type":"Point"}
}