{
  "type": "Feature",
  "properties": {
    "iso:country":"ES",
    "sg:address":"Calle de Cuatropea, 1",
    "sg:city":"Cacabelos",
    "sg:orig_category":"Peluqueros: De Se\u00d1oras",
    "sg:phone":"+34 987 54 91 04",
    "sg:postcode":"24540",
    "sg:province":"Le\u00f3n",
    "wof:name":"Salon De Belleza Alba's S.l.",
    "wof:placetype":"venue"
},
  "geometry": {"coordinates":[-6.7269492149,42.5988311768],"type":"Point"}
}