{
  "type": "Feature",
  "properties": {
    "iso:country":"ES",
    "sg:address":"Amieiro Longo, S/n",
    "sg:city":"Mos",
    "sg:orig_category":"Transportes Por V\u00cdas Navegables",
    "sg:phone":"+34 986 33 87 00",
    "sg:postcode":"36418",
    "sg:province":"Pontevedra",
    "wof:name":"Gali Cargo S.l.",
    "wof:placetype":"venue"
},
  "geometry": {"coordinates":[-8.617515564,42.1448669434],"type":"Point"}
}