{
  "type": "Feature",
  "properties": {
    "addr:full":"Calle de Calvo Sotelo, 21 Tui Pontevedra 36700",
    "addr:housenumber":"21",
    "addr:postcode":"36700",
    "addr:street":"Calle De Calvo Sotelo",
    "iso:country":"ES",
    "sg:address":"Calle de Calvo Sotelo, 21",
    "sg:city":"Tui",
    "sg:orig_category":"Zapatos (al Por Menor)",
    "sg:phone":"+34 986 60 12 13",
    "sg:postcode":"36700",
    "sg:province":"Pontevedra",
    "wof:name":"Gonzalez Moreiras Maria Milagros",
    "wof:placetype":"venue"
},
  "geometry": {"coordinates":[-8.6446218491,42.0476799011],"type":"Point"}
}