{
  "type": "Feature",
  "properties": {
    "iso:country":"ES",
    "sg:address":"Avda Zarauz (de), 28",
    "sg:city":"San Fernando De Henares",
    "sg:orig_category":"Peluquer\u00cdas, Peluquer\u00cda Mixta",
    "sg:phone":"+34 916 73 08 14",
    "sg:postcode":"28830",
    "sg:province":"Madrid",
    "wof:name":"Mu\u00f1oz Pedregal Carmen",
    "wof:placetype":"venue"
},
  "geometry": {"coordinates":[-3.5272409916,40.4186477661],"type":"Point"}
}