{
  "type": "Feature",
  "properties": {
    "iso:country":"ES",
    "sg:address":"Seminari, 14",
    "sg:city":"Ciutadella Menorca",
    "sg:orig_category":"T\u00c9cnicos Veterinarios",
    "sg:phone":"+34 971 38 14 60",
    "sg:postcode":"07760",
    "sg:province":"Islas Baleares",
    "wof:name":"Salord Sole Comunidad Bienes",
    "wof:placetype":"venue"
},
  "geometry": {"coordinates":[3.8385779858,40.0016021729],"type":"Point"}
}