{
  "type": "Feature",
  "properties": {
    "addr:full":"Calle de Cardenal Cisneros, 30 Alcala Henares Madrid 28802",
    "addr:housenumber":"30",
    "addr:postcode":"28802",
    "addr:street":"Calle De Cardenal Cisneros",
    "iso:country":"ES",
    "sg:address":"Calle de Cardenal Cisneros, 30",
    "sg:city":"Alcala Henares",
    "sg:orig_category":"Ense\u00d1anza: Comercio, Gesti\u00d3n, Inform\u00c1tica",
    "sg:phone":"+34 918 88 31 51",
    "sg:postcode":"28802",
    "sg:province":"Madrid",
    "wof:name":"Centro De Estudios Nueva Altea",
    "wof:placetype":"venue"
},
  "geometry": {"coordinates":[-3.3719191551,40.4806518555],"type":"Point"}
}