{
  "type": "Feature",
  "properties": {
    "addr:full":"Plaz Arenal Celestino M. Del, 14 Bilbao Vizcaya 48015",
    "addr:postcode":"48015",
    "addr:street":"Plaz",
    "iso:country":"ES",
    "sg:address":"Plaz Arenal Celestino M. Del, 14",
    "sg:city":"Bilbao",
    "sg:orig_category":"Peluquer\u00cdas, Peluquer\u00cda Mixta",
    "sg:phone":"+34 944 47 07 45",
    "sg:postcode":"48015",
    "sg:province":"Vizcaya",
    "wof:name":"Alcala Otazua Leire",
    "wof:placetype":"venue"
},
  "geometry": {"coordinates":[-2.9570410252,43.2768974304],"type":"Point"}
}