{
  "type": "Feature",
  "properties": {
    "addr:full":"Plaz Rafael Perez Del Alamo, 4 Arcos Frontera C\u00e1diz 11630",
    "addr:postcode":"11630",
    "addr:street":"Alamo;Arcos;Ca\u0301Diz",
    "iso:country":"ES",
    "sg:address":"Plaz Rafael Perez Del Alamo, 4",
    "sg:city":"Arcos Frontera",
    "sg:orig_category":"Florister\u00cdas",
    "sg:phone":"+34 956 70 18 18",
    "sg:postcode":"11630",
    "sg:province":"C\u00e1diz",
    "wof:name":"Morales Villalba Maria Nieves",
    "wof:placetype":"venue"
},
  "geometry": {"coordinates":[-5.8115739822,36.7515716553],"type":"Point"}
}