{
  "type": "Feature",
  "properties": {
    "addr:full":"Calle de Doctor Casas, 18 Zaragoza Zaragoza 50008",
    "addr:housenumber":"18",
    "addr:postcode":"50008",
    "addr:street":"Calle De Doctor Casas",
    "iso:country":"ES",
    "sg:address":"Calle de Doctor Casas, 18",
    "sg:city":"Zaragoza",
    "sg:orig_category":"Centros De Adelgazamiento Y De Est\u00c9tica",
    "sg:phone":"+34 976 23 99 56",
    "sg:postcode":"50008",
    "sg:province":"Zaragoza",
    "wof:name":"Campagne  Isabelle",
    "wof:placetype":"venue"
},
  "geometry": {"coordinates":[-0.8840100169,41.6433258057],"type":"Point"}
}