{
  "type": "Feature",
  "properties": {
    "iso:country":"ES",
    "sg:address":"Avda Monforte De Lemos, 87",
    "sg:city":"Madrid",
    "sg:orig_category":"Bisuter\u00cda, Joyer\u00cda, Relojer\u00cda (al Por Menor)",
    "sg:phone":"+34 917 40 51 73",
    "sg:postcode":"28029",
    "sg:province":"Madrid",
    "sg:website":"www.accessorize.es",
    "wof:name":"Compleshop S.l.",
    "wof:placetype":"venue"
},
  "geometry": {"coordinates":[-3.7029790878,40.479434967],"type":"Point"}
}