{
  "type": "Feature",
  "properties": {
    "iso:country":"ES",
    "sg:address":"Crt. Bola\u00f1os, 5",
    "sg:city":"Torralba Calatrava",
    "sg:orig_category":"Cerrajer\u00cda, Ferrallista",
    "sg:phone":"+34 926 81 02 19",
    "sg:postcode":"13160",
    "sg:province":"Ciudad Real",
    "wof:name":"Ba\u00f1os De Fuensanta S.l.",
    "wof:placetype":"venue"
},
  "geometry": {"coordinates":[-3.752959013,39.0169181824],"type":"Point"}
}