{
  "type": "Feature",
  "properties": {
    "addr:full":"Carrer de Carme, 4 S. Cugat Valles Barcelona 08172",
    "addr:housenumber":"4",
    "addr:postcode":"08172",
    "addr:street":"Carrer De Carme;Barcelona",
    "iso:country":"ES",
    "sg:address":"Carrer de Carme, 4",
    "sg:city":"S. Cugat Valles",
    "sg:orig_category":"Edici\u00d3n De Diarios, Revistas, Boletines",
    "sg:phone":"+34 935 90 26 66",
    "sg:postcode":"08172",
    "sg:province":"Barcelona",
    "sg:website":"www.vilbo.com",
    "wof:name":"Vilbo Ediciones Y Publicidad S.l.",
    "wof:placetype":"venue"
},
  "geometry": {"coordinates":[2.0844070911,41.4712142944],"type":"Point"}
}