{
  "type": "Feature",
  "properties": {
    "iso:country":"ES",
    "sg:address":"Ctra Vp Mil Treinta Y Seis, S/n",
    "sg:city":"Xativa",
    "sg:orig_category":"Metalurgia: Maquinaria Y Equipos",
    "sg:phone":"+34 962 27 70 12",
    "sg:postcode":"46800",
    "sg:province":"Valencia",
    "sg:website":"www.grupoperis.com/transmet",
    "wof:name":"Transmet S. A.",
    "wof:placetype":"venue"
},
  "geometry": {"coordinates":[-0.5327939987,38.9840393066],"type":"Point"}
}