{
  "type": "Feature",
  "properties": {
    "iso:country":"ES",
    "sg:address":"Calle de Trajano, 18",
    "sg:city":"Sevilla",
    "sg:orig_category":"Fotograf\u00cda Art\u00cdstica Y Retratos",
    "sg:phone":"+34 954 37 56 59",
    "sg:postcode":"41002",
    "sg:province":"Sevilla",
    "wof:name":"Grupo Hiper Foto S.l.",
    "wof:placetype":"venue"
},
  "geometry": {"coordinates":[-5.9950399399,37.394744873],"type":"Point"}
}