{
  "type": "Feature",
  "properties": {
    "addr:full":"Calle de Alfonso Xii, 64 Madrid Madrid 28014",
    "addr:housenumber":"64",
    "addr:postcode":"madrid;28014",
    "addr:street":"Calle De Alfonso Xii",
    "iso:country":"ES",
    "sg:address":"Calle de Alfonso Xii, 64",
    "sg:city":"Madrid",
    "sg:orig_category":"Delineantes",
    "sg:phone":"+34 915 28 70 33",
    "sg:postcode":"28014",
    "sg:province":"Madrid",
    "wof:name":"Ferrer Echezarra Jorge",
    "wof:placetype":"venue"
},
  "geometry": {"coordinates":[-3.6887888908,40.4084701538],"type":"Point"}
}