{
  "type": "Feature",
  "properties": {
    "iso:country":"ES",
    "sg:address":"Calle de Giltxaurdi, 15",
    "sg:city":"Elizondo",
    "sg:orig_category":"Electrodom\u00c9sticos (al Por Menor)",
    "sg:phone":"+34 948 58 04 25",
    "sg:postcode":"31700",
    "sg:province":"Navarra",
    "wof:name":"Arrechea Echeverria Pedro Maria",
    "wof:placetype":"venue"
},
  "geometry": {"coordinates":[-1.5195225477,43.1469841003],"type":"Point"}
}