{
  "type": "Feature",
  "properties": {
    "addr:full":"Calle de Esquila, 33 Valladolid Valladolid 47012",
    "addr:housenumber":"33",
    "addr:postcode":"47012",
    "addr:street":"Calle De Esquila",
    "iso:country":"ES",
    "sg:address":"Calle de Esquila, 33",
    "sg:city":"Valladolid",
    "sg:orig_category":"Peluqueros: De Se\u00d1oras",
    "sg:phone":"+34 983 30 69 66",
    "sg:postcode":"47012",
    "sg:province":"Valladolid",
    "wof:name":"Sastre Zurro Eduardo",
    "wof:placetype":"venue"
},
  "geometry": {"coordinates":[-4.711578846,41.646270752],"type":"Point"}
}