{
  "type": "Feature",
  "properties": {
    "iso:country":"ES",
    "sg:address":"Carrer de Girona, 21",
    "sg:city":"Mataro",
    "sg:orig_category":"Talleres De Corte Y Confecci\u00d3n",
    "sg:phone":"+34 937 57 04 73",
    "sg:postcode":"08303",
    "sg:province":"Barcelona",
    "wof:name":"Punsola S.c.p.",
    "wof:placetype":"venue"
},
  "geometry": {"coordinates":[2.4235858917,41.5443496704],"type":"Point"}
}