{
  "type": "Feature",
  "properties": {
    "iso:country":"ES",
    "sg:address":"Plaz Breton, 5",
    "sg:city":"Teruel",
    "sg:orig_category":"Ropa Para Ni\u00d1os (al Por Menor)",
    "sg:phone":"+34 978 60 45 44",
    "sg:postcode":"44001",
    "sg:province":"Teruel",
    "sg:website":"www.amichi.com",
    "wof:name":"Fuertes Y Galan S.l.",
    "wof:placetype":"venue"
},
  "geometry": {"coordinates":[-1.1060119867,40.3420028687],"type":"Point"}
}