{
  "type": "Feature",
  "properties": {
    "addr:full":"Calle de Hortaleza, 7 Madrid Madrid 28004",
    "addr:housenumber":"7",
    "addr:postcode":"madrid;28004",
    "addr:street":"Calle De Hortaleza",
    "iso:country":"ES",
    "sg:address":"Calle de Hortaleza, 7",
    "sg:city":"Madrid",
    "sg:orig_category":"Florister\u00cdas",
    "sg:phone":"+34 915 31 39 90",
    "sg:postcode":"28004",
    "sg:province":"Madrid",
    "wof:name":"Epf.laboratorio Multimedia S.l",
    "wof:placetype":"venue"
},
  "geometry": {"coordinates":[-3.7009129524,40.4206695557],"type":"Point"}
}