{
  "type": "Feature",
  "properties": {
    "iso:country":"ES",
    "sg:address":"Franco, 70",
    "sg:city":"Roales",
    "sg:orig_category":"Mayoristas E Intermediarios En Alcoholes",
    "sg:phone":"+34 980 53 87 11",
    "sg:postcode":"49192",
    "sg:province":"Zamora",
    "wof:name":"Zamorana De Bebidas 2003 S.l.",
    "wof:placetype":"venue"
},
  "geometry": {"coordinates":[-5.7720623016,41.5504875183],"type":"Point"}
}