{
  "type": "Feature",
  "properties": {
    "iso:country":"ES",
    "sg:address":"Carrer de Proven\u00c7a, 153",
    "sg:city":"Barcelona",
    "sg:orig_category":"Psic\u00d3logos",
    "sg:phone":"+34 934 51 44 00",
    "sg:postcode":"08036",
    "sg:province":"Barcelona",
    "sg:website":"www.autoestimaycambio.com",
    "wof:name":"Diez Calzada Eduardo",
    "wof:placetype":"venue"
},
  "geometry": {"coordinates":[2.1542749405,41.3894882202],"type":"Point"}
}