{
  "type": "Feature",
  "properties": {
    "iso:country":"ES",
    "sg:address":"Avda Monforte De Lemos, 167",
    "sg:city":"Madrid",
    "sg:orig_category":"Promotores Constructores",
    "sg:phone":"+34 913 86 33 87",
    "sg:postcode":"28029",
    "sg:province":"Madrid",
    "wof:name":"Cogolludo De La Cuadra Aquilino Vicente",
    "wof:placetype":"venue"
},
  "geometry": {"coordinates":[-3.7149820328,40.4769134521],"type":"Point"}
}