{
  "type": "Feature",
  "properties": {
    "addr:full":"Barr Moli D'en Rovira, S/n Moli D'en Rovira Barcelona 08720",
    "addr:housenumber":"s / n",
    "addr:postcode":"08720",
    "addr:street":"Moli D'En Rovira Barcelona",
    "iso:country":"ES",
    "sg:address":"Barr Moli D'en Rovira, S/n",
    "sg:city":"Moli D'en Rovira",
    "sg:orig_category":"Reciclaje Y Tratamiento De Desechos Varios",
    "sg:phone":"+34 937 43 14 82",
    "sg:postcode":"08720",
    "sg:province":"Barcelona",
    "wof:name":"Urbaser S.a.",
    "wof:placetype":"venue"
},
  "geometry": {"coordinates":[2.1940069199,41.4099731445],"type":"Point"}
}