{
  "type": "Feature",
  "properties": {
    "iso:country":"ES",
    "sg:address":"Pase Buenos Aires De, S/n",
    "sg:city":"Huelva",
    "sg:orig_category":"Restaurantes",
    "sg:phone":"+34 959 54 12 12",
    "sg:postcode":"21002",
    "sg:province":"Huelva",
    "wof:name":"Restaurante Mamma Mia Huelva S.l.u.",
    "wof:placetype":"venue"
},
  "geometry": {"coordinates":[-6.9517240524,37.2620697021],"type":"Point"}
}