{
  "type": "Feature",
  "properties": {
    "iso:country":"ES",
    "sg:address":"Calle de Moreria, 7",
    "sg:city":"Cordoba",
    "sg:orig_category":"Abogados",
    "sg:phone":"+34 957 48 61 44",
    "sg:postcode":"14008",
    "sg:province":"C\u00f3rdoba",
    "wof:name":"Casas Gimenez Alfonso",
    "wof:placetype":"venue"
},
  "geometry": {"coordinates":[-4.780796051,37.8849868774],"type":"Point"}
}