{
  "type": "Feature",
  "properties": {
    "iso:country":"ES",
    "sg:address":"Ctra General Arico Viejo, 13",
    "sg:city":"Arico Viejo",
    "sg:orig_category":"Asesor\u00cda De Formaci\u00d3n Y Gesti\u00d3n De Personal",
    "sg:phone":"+34 922 76 85 75",
    "sg:postcode":"38589",
    "sg:province":"Santa Cruz De Tenerife",
    "wof:name":"Asolafis S.l.",
    "wof:placetype":"venue"
},
  "geometry": {"coordinates":[-16.4805812836,28.1820068359],"type":"Point"}
}