{
  "type": "Feature",
  "properties": {
    "addr:full":"Rua Magdalena, 101 Ferrol La Coru\u00f1a 15402",
    "addr:housenumber":"101",
    "addr:postcode":"15402",
    "addr:street":"Rua Magdalena;La Corun\u0303A",
    "iso:country":"ES",
    "sg:address":"Rua Magdalena, 101",
    "sg:city":"Ferrol",
    "sg:orig_category":"Asociaciones, Organismos Culturales Y Socioeducativos",
    "sg:phone":"+34 981 35 08 10",
    "sg:postcode":"15402",
    "sg:province":"La Coru\u00f1a",
    "wof:name":"Circulo Filatelico De El Ferrol",
    "wof:placetype":"venue"
},
  "geometry": {"coordinates":[-8.2330350876,43.4833488464],"type":"Point"}
}