{
  "type": "Feature",
  "properties": {
    "iso:country":"ES",
    "sg:address":"Calle de Marques Del Arco (del), 8",
    "sg:city":"Segovia",
    "sg:orig_category":"Art\u00cdculos De Regalo (al Por Menor)",
    "sg:phone":"+34 921 46 05 15",
    "sg:postcode":"40003",
    "sg:province":"Segovia",
    "wof:name":"Gonzalez Juarez Jose Antonio",
    "wof:placetype":"venue"
},
  "geometry": {"coordinates":[-4.1245951653,40.9504356384],"type":"Point"}
}