{
  "type": "Feature",
  "properties": {
    "iso:country":"ES",
    "sg:address":"Rua Diego Pazos, 70",
    "sg:city":"Sarria",
    "sg:orig_category":"Muebles, Minoristas",
    "sg:phone":"+34 982 53 09 26",
    "sg:postcode":"27600",
    "sg:province":"Lugo",
    "wof:name":"Arias Mourin Lucia",
    "wof:placetype":"venue"
},
  "geometry": {"coordinates":[-7.4102749825,42.7807350159],"type":"Point"}
}