{
  "type": "Feature",
  "properties": {
    "addr:full":"Calle de Alejandro Sanchez, 102 Madrid Madrid 28019",
    "addr:housenumber":"102",
    "addr:postcode":"28019",
    "addr:street":"Calle De Alejandro Sanchez",
    "iso:country":"ES",
    "sg:address":"Calle de Alejandro Sanchez, 102",
    "sg:city":"Madrid",
    "sg:orig_category":"Venta, Instalaci\u00d3n De Calefacci\u00d3n",
    "sg:phone":"+34 915 60 52 53",
    "sg:postcode":"28019",
    "sg:province":"Madrid",
    "wof:name":"Tusain S. A.",
    "wof:placetype":"venue"
},
  "geometry": {"coordinates":[-3.7168939114,40.3890533447],"type":"Point"}
}