{
  "type": "Feature",
  "properties": {
    "addr:full":"Calle de Pintor Murillo, 4 Alacant Alicante 03004",
    "addr:housenumber":"4",
    "addr:postcode":"03004",
    "addr:street":"Calle De Pintor Murillo",
    "iso:country":"ES",
    "sg:address":"Calle de Pintor Murillo, 4",
    "sg:city":"Alacant",
    "sg:classifiers":[
        {
            "category":"Professional",
            "subcategory":"Management & Consulting",
            "type":"Services"
        }
    ],
    "sg:phone":"+34 965 20 06 74",
    "sg:postcode":"03004",
    "sg:province":"Alicante",
    "sg:tags":[
        "asesor\u00cda",
        "en",
        "marketing"
    ],
    "wof:name":"Yesares Alacala Maria Del Carmen",
    "wof:placetype":"venue"
},
  "geometry": {"coordinates":[-0.485727191,38.35181427],"type":"Point"}
}