{
  "type": "Feature",
  "properties": {
    "addr:full":"Carrer de Angel Guimera, 15 Mataro Barcelona 08303",
    "addr:housenumber":"15",
    "addr:postcode":"08303",
    "addr:street":"Carrer De Angel Guimera",
    "iso:country":"ES",
    "sg:address":"Carrer de Angel Guimera, 15",
    "sg:city":"Mataro",
    "sg:orig_category":"Planchado",
    "sg:phone":"+34 937 57 48 25",
    "sg:postcode":"08303",
    "sg:province":"Barcelona",
    "wof:name":"Plancha Vian S.c.p.",
    "wof:placetype":"venue"
},
  "geometry": {"coordinates":[2.42582798,41.5435600281],"type":"Point"}
}