{
  "type": "Feature",
  "properties": {
    "addr:full":"Rua Valdoncel, 62 Betanzos La Coru\u00f1a 15300",
    "addr:housenumber":"62",
    "addr:postcode":"15300",
    "addr:street":"Rua Valdoncel;La",
    "iso:country":"ES",
    "sg:address":"Rua Valdoncel, 62",
    "sg:city":"Betanzos",
    "sg:orig_category":"Quincaller\u00cda (al Por Menor)",
    "sg:phone":"+34 981 77 01 12",
    "sg:postcode":"15300",
    "sg:province":"La Coru\u00f1a",
    "wof:name":"Benito Dopico Miguel",
    "wof:placetype":"venue"
},
  "geometry": {"coordinates":[-8.2130041122,43.2819595337],"type":"Point"}
}