{
  "type": "Feature",
  "properties": {
    "addr:full":"Calle de Almagro, 15 Madrid Madrid 28010",
    "addr:housenumber":"15",
    "addr:postcode":"madrid;28010",
    "addr:street":"Calle De Almagro",
    "iso:country":"ES",
    "sg:address":"Calle de Almagro, 15",
    "sg:city":"Madrid",
    "sg:orig_category":"Cl\u00cdnicas M\u00c9dicas",
    "sg:phone":"+34 913 19 17 34",
    "sg:postcode":"28010",
    "sg:province":"Madrid",
    "sg:website":"www.secpre.org/dr/delaromana.html",
    "wof:name":"Perez De La Romana Gonzalez Federico",
    "wof:placetype":"venue"
},
  "geometry": {"coordinates":[-3.6927034855,40.4305267334],"type":"Point"}
}