{
  "type": "Feature",
  "properties": {
    "addr:full":"Calle de Puente (el), 8 Selaya Cantabria 39696",
    "addr:housenumber":"8",
    "addr:postcode":"39696",
    "addr:street":"Calle De Puente El",
    "iso:country":"ES",
    "sg:address":"Calle de Puente (el), 8",
    "sg:city":"Selaya",
    "sg:orig_category":"Molduras, Junquillos, Listones Y Molduras Perforadas",
    "sg:phone":"+34 942 59 02 70",
    "sg:postcode":"39696",
    "sg:province":"Cantabria",
    "wof:name":"Fernandez Barquim Gregorio",
    "wof:placetype":"venue"
},
  "geometry": {"coordinates":[-3.8073780537,43.2184371948],"type":"Point"}
}