{
  "type": "Feature",
  "properties": {
    "iso:country":"ES",
    "sg:address":"Rua Padre Celso, 27",
    "sg:city":"Vigo",
    "sg:orig_category":"Carnicer\u00cdas, Carnicer\u00cdas",
    "sg:phone":"+34 986 27 59 17",
    "sg:postcode":"36206",
    "sg:province":"Pontevedra",
    "wof:name":"Illanes Novo Juana",
    "wof:placetype":"venue"
},
  "geometry": {"coordinates":[-8.6995830536,42.2387809753],"type":"Point"}
}