{
  "type": "Feature",
  "properties": {
    "iso:country":"ES",
    "sg:address":"Plaz Gobernador, S/n",
    "sg:city":"Pozuelo De Alarcon",
    "sg:orig_category":"Inmobiliaria (agencias)",
    "sg:phone":"+34 913 51 80 26",
    "sg:postcode":"28224",
    "sg:province":"Madrid",
    "wof:name":"Diversus Patrimonial S.l.",
    "wof:placetype":"venue"
},
  "geometry": {"coordinates":[-3.801568985,40.4473838806],"type":"Point"}
}