{
  "type": "Feature",
  "properties": {
    "iso:country":"ES",
    "sg:address":"Carr Vicari Pastor, De, 5",
    "sg:city":"Soller",
    "sg:orig_category":"Centros M\u00c9dicos Y Sociales, Dispensarios",
    "sg:phone":"+34 971 63 35 21",
    "sg:postcode":"07100",
    "sg:province":"Islas Baleares",
    "wof:name":"Colom Mestre Bartolome",
    "wof:placetype":"venue"
},
  "geometry": {"coordinates":[2.7145628929,39.766078949],"type":"Point"}
}