{
  "type": "Feature",
  "properties": {
    "addr:full":"Plaz Canovas Del Castillo, 4 Madrid Madrid 28014",
    "addr:housenumber":"4",
    "addr:postcode":"28014",
    "addr:street":"Plaz Canovas Del Castillo",
    "iso:country":"ES",
    "sg:address":"Plaz Canovas Del Castillo, 4",
    "sg:city":"Madrid",
    "sg:orig_category":"Artesan\u00cda",
    "sg:phone":"+34 914 29 25 90",
    "sg:postcode":"28014",
    "sg:province":"Madrid",
    "wof:name":"Bajo Mu\u00d1oz Mari Carmen",
    "wof:placetype":"venue"
},
  "geometry": {"coordinates":[-3.6945323944,40.4148979187],"type":"Point"}
}