{
  "type": "Feature",
  "properties": {
    "addr:full":"Ctra Sanchidrian, Km. 0021,0 Hernansancho \u00c1vila 05164",
    "addr:postcode":"05164",
    "addr:street":"Ctra Sanchidrian Km. 0021,0;A\u0301Vila",
    "iso:country":"ES",
    "sg:address":"Ctra Sanchidrian, Km. 0021,0",
    "sg:city":"Hernansancho",
    "sg:orig_category":"Alimentaci\u00d3n General (al Por Menor)",
    "sg:phone":"+34 920 35 15 02",
    "sg:postcode":"05164",
    "sg:province":"\u00c1vila",
    "wof:name":"Estacion De Servicio La Mora\u00d1a S. L.",
    "wof:placetype":"venue"
},
  "geometry": {"coordinates":[-4.7309889793,40.8560142517],"type":"Point"}
}