{
  "type": "Feature",
  "properties": {
    "iso:country":"ES",
    "sg:address":"Pla\u00c7 Major, 4",
    "sg:city":"Olot",
    "sg:orig_category":"Ense\u00d1anza: Profesiones Art\u00cdsticas",
    "sg:phone":"+34 972 26 00 59",
    "sg:postcode":"17800",
    "sg:province":"Girona",
    "wof:name":"Farre Serradell Alvar",
    "wof:placetype":"venue"
},
  "geometry": {"coordinates":[2.490062952,42.1824951172],"type":"Point"}
}