{
  "type": "Feature",
  "properties": {
    "addr:full":"Avda Iparralde, 7 Irun Guip\u00f9zcoa 20304",
    "addr:housenumber":"7",
    "addr:postcode":"20304",
    "addr:street":"Avda Iparralde;Guipu\u0300Zcoa",
    "iso:country":"ES",
    "sg:address":"Avda Iparralde, 7",
    "sg:city":"Irun",
    "sg:orig_category":"Carnicer\u00cdas, Carnicer\u00cdas",
    "sg:phone":"+34 943 63 11 57",
    "sg:postcode":"20304",
    "sg:province":"Guip\u00f9zcoa",
    "wof:name":"Olasagasti Etxeberria S.l.",
    "wof:placetype":"venue"
},
  "geometry": {"coordinates":[-1.7885489464,43.3441581726],"type":"Point"}
}