{
  "type": "Feature",
  "properties": {
    "iso:country":"ES",
    "sg:address":"Rbla Pulido, 57",
    "sg:city":"Santa Cruz De Tenerife",
    "sg:orig_category":"\u00d3ptica: Instrumentos (fabricaci\u00d3n)",
    "sg:phone":"+34 922 28 42 61",
    "sg:postcode":"38004",
    "sg:province":"Santa Cruz De Tenerife",
    "wof:name":"Opticas Europeas S.l.",
    "wof:placetype":"venue"
},
  "geometry": {"coordinates":[-16.2591533661,28.4675197601],"type":"Point"}
}