{
  "type": "Feature",
  "properties": {
    "addr:full":"Ctra Asua-erletxe, S/n Asua-lauroeta Vizcaya 48950",
    "addr:housenumber":"s",
    "addr:postcode":"48950",
    "addr:street":"Ctra Asua-Erletxe;/ N",
    "iso:country":"ES",
    "sg:address":"Ctra Asua-erletxe, S/n",
    "sg:city":"Asua-lauroeta",
    "sg:orig_category":"M\u00c1quinas Para Recortar Y Pegar",
    "sg:phone":"+34 944 53 30 52",
    "sg:postcode":"48950",
    "sg:province":"Vizcaya",
    "wof:name":"Auxmat S.l.",
    "wof:placetype":"venue"
},
  "geometry": {"coordinates":[-2.9429705143,43.3003959656],"type":"Point"}
}