{
  "type": "Feature",
  "properties": {
    "addr:full":"Pase Habana, 26 Madrid Madrid 28036",
    "addr:housenumber":"26",
    "addr:postcode":"madrid;28036",
    "iso:country":"ES",
    "sg:address":"Pase Habana, 26",
    "sg:city":"Madrid",
    "sg:orig_category":"Centros Empresariales",
    "sg:phone":"+34 915 64 94 51",
    "sg:postcode":"28036",
    "sg:province":"Madrid",
    "wof:name":"Anafin Consultores S.l.",
    "wof:placetype":"venue"
},
  "geometry": {"coordinates":[-3.6889762878,40.4490737915],"type":"Point"}
}