{
  "type": "Feature",
  "properties": {
    "iso:country":"ES",
    "sg:address":"Calle de Real De La Plaza, 10",
    "sg:city":"Teror",
    "sg:orig_category":"Producci\u00d3n, Distribuci\u00d3n De Gas Butano Y Propano",
    "sg:phone":"+34 928 63 00 82",
    "sg:postcode":"35330",
    "sg:province":"Las Palmas",
    "wof:name":"Falcon Ortega Abraham",
    "wof:placetype":"venue"
},
  "geometry": {"coordinates":[-15.5466756821,28.0602245331],"type":"Point"}
}