{
  "type": "Feature",
  "properties": {
    "addr:full":"Calle de Sahagun, 1 Alcorcon Madrid 28925",
    "addr:housenumber":"1",
    "addr:postcode":"28925",
    "addr:street":"Calle De Sahagun",
    "iso:country":"ES",
    "sg:address":"Calle de Sahagun, 1",
    "sg:city":"Alcorcon",
    "sg:orig_category":"Arreglo, Instalaci\u00d3n Y Acondicionamiento De Talleres",
    "sg:phone":"+34 916 12 08 55",
    "sg:postcode":"28925",
    "sg:province":"Madrid",
    "wof:name":"Ayuntamiento De Alcorcon",
    "wof:placetype":"venue"
},
  "geometry": {"coordinates":[-3.8216199875,40.3543663025],"type":"Point"}
}