{
  "type": "Feature",
  "properties": {
    "iso:country":"ES",
    "sg:address":"Avda Cardenal Herrera Oria, 249",
    "sg:city":"Madrid",
    "sg:orig_category":"Zapatos (al Por Menor)",
    "sg:phone":"+34 917 38 96 45",
    "sg:postcode":"28035",
    "sg:province":"Madrid",
    "wof:name":"Alonso Plaza Maria Concepcion",
    "wof:placetype":"venue"
},
  "geometry": {"coordinates":[-3.7207500935,40.4809799194],"type":"Point"}
}