{
  "type": "Feature",
  "properties": {
    "addr:full":"Avda Huesca, 28 Alca\u00f1iz Teruel 44600",
    "addr:housenumber":"28",
    "addr:postcode":"44600",
    "addr:street":"Avda Huesca",
    "iso:country":"ES",
    "sg:address":"Avda Huesca, 28",
    "sg:city":"Alca\u00f1iz",
    "sg:classifiers":[
        {
            "category":"Casinos & Gambling",
            "type":"Entertainment"
        }
    ],
    "sg:phone":"+34 978 83 31 36",
    "sg:postcode":"44600",
    "sg:province":"Teruel",
    "sg:tags":[
        "locale",
        "de",
        "juego"
    ],
    "wof:name":"Zona Diver S.l.",
    "wof:placetype":"venue"
},
  "geometry": {"coordinates":[-0.1277503073,41.0477333069],"type":"Point"}
}