{
  "type": "Feature",
  "properties": {
    "iso:country":"ES",
    "sg:address":"Calle de Ceferino Calderon, 13",
    "sg:city":"Torrelavega",
    "sg:orig_category":"Discotecas Y Salas De Baile",
    "sg:phone":"+34 942 80 15 10",
    "sg:postcode":"39300",
    "sg:province":"Cantabria",
    "wof:name":"Tel Start 2000 S.l.",
    "wof:placetype":"venue"
},
  "geometry": {"coordinates":[-4.0474648476,43.3527984619],"type":"Point"}
}