{
  "type": "Feature",
  "properties": {
    "addr:full":"Calle de Rosalia De Castro, 16 Zaragoza Zaragoza 50015",
    "addr:housenumber":"16",
    "addr:postcode":"50015",
    "addr:street":"Calle De Rosalia De Castro",
    "iso:country":"ES",
    "sg:address":"Calle de Rosalia De Castro, 16",
    "sg:city":"Zaragoza",
    "sg:orig_category":"Promotores Constructores",
    "sg:phone":"+34 976 52 08 67",
    "sg:postcode":"50015",
    "sg:province":"Zaragoza",
    "wof:name":"Corban Ges S.l.",
    "wof:placetype":"venue"
},
  "geometry": {"coordinates":[-0.8629540205,41.6912841797],"type":"Point"}
}