{
  "type": "Feature",
  "properties": {
    "addr:full":"Calle de Julio Cesar, 6 Camas Sevilla 41900",
    "addr:housenumber":"6",
    "addr:postcode":"41900",
    "addr:street":"Calle De Julio Cesar",
    "iso:country":"ES",
    "sg:address":"Calle de Julio Cesar, 6",
    "sg:city":"Camas",
    "sg:orig_category":"Pescader\u00cdas (al Por Menor)",
    "sg:phone":"+34 954 39 36 78",
    "sg:postcode":"41900",
    "sg:province":"Sevilla",
    "wof:name":"Quemada Henares Jose",
    "wof:placetype":"venue"
},
  "geometry": {"coordinates":[-6.0395650864,37.4035339355],"type":"Point"}
}