{
  "type": "Feature",
  "properties": {
    "addr:full":"Carrer de Valencia, 573 Barcelona Barcelona 08026",
    "addr:housenumber":"573",
    "addr:postcode":"08026",
    "addr:street":"Carrer De Valencia",
    "iso:country":"ES",
    "sg:address":"Carrer de Valencia, 573",
    "sg:city":"Barcelona",
    "sg:orig_category":"Agencias De Viajes",
    "sg:phone":"+34 932 46 92 65",
    "sg:postcode":"08026",
    "sg:province":"Barcelona",
    "wof:name":"Euro Start Express S.l.",
    "wof:placetype":"venue"
},
  "geometry": {"coordinates":[2.183768034,41.4082565308],"type":"Point"}
}