{
  "type": "Feature",
  "properties": {
    "iso:country":"ES",
    "sg:address":"Avda Blas Infante, 31",
    "sg:city":"Mairena Alcor",
    "sg:orig_category":"Lavado, Limpieza De Veh\u00cdculos",
    "sg:phone":"+34 955 74 48 89",
    "sg:postcode":"41510",
    "sg:province":"Sevilla",
    "wof:name":"Espinosa Espinosa Manuel",
    "wof:placetype":"venue"
},
  "geometry": {"coordinates":[-5.7552490234,37.3667259216],"type":"Point"}
}