{
  "type": "Feature",
  "properties": {
    "addr:full":"Calle de Argentina, 20 Coslada Madrid 28820",
    "addr:housenumber":"20",
    "addr:postcode":"28820",
    "addr:street":"Calle De Argentina",
    "iso:country":"ES",
    "sg:address":"Calle de Argentina, 20",
    "sg:city":"Coslada",
    "sg:orig_category":"Molduras, Junquillos, Listones Y Molduras Perforadas",
    "sg:phone":"+34 916 73 70 86",
    "sg:postcode":"28820",
    "sg:province":"Madrid",
    "wof:name":"Mu\u00f1oz Sanchez Ignacio",
    "wof:placetype":"venue"
},
  "geometry": {"coordinates":[-3.5420548916,40.4266700745],"type":"Point"}
}