{
  "type": "Feature",
  "properties": {
    "iso:country":"ES",
    "sg:address":"Avda Gregorio Gea, 17",
    "sg:city":"Mislata",
    "sg:orig_category":"Arquitectos",
    "sg:phone":"+34 963 79 98 65",
    "sg:postcode":"46920",
    "sg:province":"Valencia",
    "wof:name":"Peris Campos Vicente",
    "wof:placetype":"venue"
},
  "geometry": {"coordinates":[-0.415365994,39.4729652405],"type":"Point"}
}