{
  "type": "Feature",
  "properties": {
    "addr:full":"Calle de Agustin Calvo, 26 Madrid Madrid 28043",
    "addr:housenumber":"26",
    "addr:postcode":"madrid;28043",
    "addr:street":"Calle De Agustin Calvo",
    "iso:country":"ES",
    "sg:address":"Calle de Agustin Calvo, 26",
    "sg:city":"Madrid",
    "sg:orig_category":"Peluqueros: De Se\u00d1oras",
    "sg:phone":"+34 917 59 87 45",
    "sg:postcode":"28043",
    "sg:province":"Madrid",
    "wof:name":"Martinez Rentero Carmen",
    "wof:placetype":"venue"
},
  "geometry": {"coordinates":[-3.6488473415,40.4642066956],"type":"Point"}
}