{
  "type": "Feature",
  "properties": {
    "iso:country":"ES",
    "sg:address":"Calle de Fernando Camino, 8",
    "sg:city":"Malaga",
    "sg:orig_category":"Fabricaci\u00d3n De Bibliotecas Y Estanter\u00cdas",
    "sg:phone":"+34 952 22 67 78",
    "sg:postcode":"29016",
    "sg:province":"M\u00e1laga",
    "wof:name":"Gomez De La Cruz Fernandez Jose Luis",
    "wof:placetype":"venue"
},
  "geometry": {"coordinates":[-4.409154892,36.7198295593],"type":"Point"}
}