{
  "type": "Feature",
  "properties": {
    "addr:full":"Rua Coru\u00d1a, 13 Santa Comba La Coru\u00f1a 15840",
    "addr:housenumber":"13",
    "addr:postcode":"15840",
    "addr:street":"Rua Corun\u0303A;Corun\u0303A",
    "iso:country":"ES",
    "sg:address":"Rua Coru\u00d1a, 13",
    "sg:city":"Santa Comba",
    "sg:orig_category":"Fotograf\u00cda Art\u00cdstica Y Retratos",
    "sg:phone":"+34 981 88 12 14",
    "sg:postcode":"15840",
    "sg:province":"La Coru\u00f1a",
    "wof:name":"Martinez Ramos Maria Isabel",
    "wof:placetype":"venue"
},
  "geometry": {"coordinates":[-8.8093090057,43.0326194763],"type":"Point"}
}