{
  "type": "Feature",
  "properties": {
    "iso:country":"ES",
    "sg:address":"Calle de Verdugo Y Massieu, 2",
    "sg:city":"Cuesta",
    "sg:orig_category":"Arquitectos",
    "sg:phone":"+34 922 67 02 71",
    "sg:postcode":"38320",
    "sg:province":"Santa Cruz De Tenerife",
    "wof:name":"Vera Morales Arquitectos S.l.",
    "wof:placetype":"venue"
},
  "geometry": {"coordinates":[-16.2896404266,28.4688148499],"type":"Point"}
}