{
  "type": "Feature",
  "properties": {
    "iso:country":"ES",
    "sg:address":"Calle de Retablo, 2",
    "sg:city":"Alcorcon",
    "sg:orig_category":"Muebles, Minoristas",
    "sg:phone":"+34 916 10 69 30",
    "sg:postcode":"28921",
    "sg:province":"Madrid",
    "wof:name":"Expomobelar S.a.",
    "wof:placetype":"venue"
},
  "geometry": {"coordinates":[-3.8262400627,40.3519706726],"type":"Point"}
}