{
  "type": "Feature",
  "properties": {
    "addr:full":"Plaz Salinas (de Las), 3 S. Fernando C\u00e1diz 11100",
    "addr:postcode":"11100",
    "addr:street":"Las 3 S. Fernando Ca\u0301Diz",
    "iso:country":"ES",
    "sg:address":"Plaz Salinas (de Las), 3",
    "sg:city":"S. Fernando",
    "sg:orig_category":"Fabricaci\u00d3n, Instalaci\u00d3n De Armarios",
    "sg:phone":"+34 956 59 53 80",
    "sg:postcode":"11100",
    "sg:province":"C\u00e1diz",
    "wof:name":"Dise\u00f1o Decoracion La Isla S.l.",
    "wof:placetype":"venue"
},
  "geometry": {"coordinates":[-6.1967391968,36.4654541016],"type":"Point"}
}