{
  "type": "Feature",
  "properties": {
    "addr:full":"Carrer de Alarcon, 25 Barcelona Barcelona 08035",
    "addr:housenumber":"25",
    "addr:postcode":"08035",
    "addr:street":"Carrer De Alarcon",
    "iso:country":"ES",
    "sg:address":"Carrer de Alarcon, 25",
    "sg:city":"Barcelona",
    "sg:orig_category":"Cerrajer\u00cda, Ferrallista",
    "sg:phone":"+34 933 57 71 65",
    "sg:postcode":"08035",
    "sg:province":"Barcelona",
    "wof:name":"Oton Guzman Jose",
    "wof:placetype":"venue"
},
  "geometry": {"coordinates":[2.1532130241,41.4277153015],"type":"Point"}
}