{
  "type": "Feature",
  "properties": {
    "addr:full":"C/ Rafael Sanchez Ceva, 42 Elche Alicante 03203",
    "addr:housenumber":"42",
    "addr:postcode":"03203",
    "addr:street":"C / Rafael Sanchez Ceva",
    "iso:country":"ES",
    "sg:address":"C/ Rafael Sanchez Ceva, 42",
    "sg:city":"Elche",
    "sg:orig_category":"Empresas De Limpieza",
    "sg:phone":"+34 966 66 05 83",
    "sg:postcode":"03203",
    "sg:province":"Alicante",
    "wof:name":"Redondo Vazquez Margarita",
    "wof:placetype":"venue"
},
  "geometry": {"coordinates":[-0.7039750218,38.2730369568],"type":"Point"}
}