{
  "type": "Feature",
  "properties": {
    "iso:country":"ES",
    "sg:address":"C/ Enrique Pire Garcia, 54",
    "sg:city":"Elche",
    "sg:orig_category":"Loter\u00cda Y T\u00d3mbola",
    "sg:phone":"+34 966 65 53 70",
    "sg:postcode":"03204",
    "sg:province":"Alicante",
    "wof:name":"Del Pozo Magari\u00f1o Santiago",
    "wof:placetype":"venue"
},
  "geometry": {"coordinates":[-0.7059109807,38.2566452026],"type":"Point"}
}