{
  "type": "Feature",
  "properties": {
    "iso:country":"ES",
    "sg:address":"Carrer de Industria, 93",
    "sg:city":"Barcelona",
    "sg:orig_category":"Psic\u00d3logos",
    "sg:phone":"+34 934 56 70 41",
    "sg:postcode":"08025",
    "sg:province":"Barcelona",
    "wof:name":"Morales Hernandez Maria Carmen",
    "wof:placetype":"venue"
},
  "geometry": {"coordinates":[2.1700570583,41.4064712524],"type":"Point"}
}