{
  "type": "Feature",
  "properties": {
    "addr:full":"Calle de Cordoba, 1 Teruel Teruel 44002",
    "addr:housenumber":"1",
    "addr:postcode":"44002",
    "addr:street":"Calle De Cordoba",
    "iso:country":"ES",
    "sg:address":"Calle de Cordoba, 1",
    "sg:city":"Teruel",
    "sg:orig_category":"Zapater\u00cdas",
    "sg:phone":"+34 978 61 05 16",
    "sg:postcode":"44002",
    "sg:province":"Teruel",
    "wof:name":"Sancho Saez Carlos Luis",
    "wof:placetype":"venue"
},
  "geometry": {"coordinates":[-1.1036592722,40.3362426758],"type":"Point"}
}