{
  "type": "Feature",
  "properties": {
    "addr:full":"Calle de Nicolas Sanchez, 30 Madrid Madrid 28026",
    "addr:housenumber":"30",
    "addr:postcode":"madrid;28026",
    "addr:street":"Calle De Nicolas Sanchez",
    "iso:country":"ES",
    "sg:address":"Calle de Nicolas Sanchez, 30",
    "sg:city":"Madrid",
    "sg:orig_category":"Lavado, Limpieza De Veh\u00cdculos",
    "sg:phone":"+34 914 75 50 20",
    "sg:postcode":"28026",
    "sg:province":"Madrid",
    "wof:name":"Sanchez Sanchez Eugenio",
    "wof:placetype":"venue"
},
  "geometry": {"coordinates":[-3.7063660622,40.3851242065],"type":"Point"}
}