{
  "type": "Feature",
  "properties": {
    "addr:full":"Carr Independencia, 285 Badalona Barcelona 08915",
    "addr:housenumber":"285",
    "addr:postcode":"08915",
    "addr:street":"Carr Independencia",
    "iso:country":"ES",
    "sg:address":"Carr Independencia, 285",
    "sg:city":"Badalona",
    "sg:orig_category":"Cajas De Ahorro",
    "sg:phone":"+34 933 87 70 49",
    "sg:postcode":"08915",
    "sg:province":"Barcelona",
    "wof:name":"Caixa D'estalvis I Pensions De Barcelona",
    "wof:placetype":"venue"
},
  "geometry": {"coordinates":[2.2407550812,41.4619522095],"type":"Point"}
}