{
  "type": "Feature",
  "properties": {
    "addr:full":"Av Meridiana, 306 Barcelona Barcelona 08027",
    "addr:housenumber":"306",
    "addr:postcode":"08027",
    "addr:street":"Meridiana",
    "iso:country":"ES",
    "sg:address":"Av Meridiana, 306",
    "sg:city":"Barcelona",
    "sg:orig_category":"Sociedades, Compa\u00d1\u00cdas Aseguradoras",
    "sg:phone":"+34 933 49 58 73",
    "sg:postcode":"08027",
    "sg:province":"Barcelona",
    "wof:name":"Gutierrez Seguros S.c.p.",
    "wof:placetype":"venue"
},
  "geometry": {"coordinates":[2.1871449947,41.4234199524],"type":"Point"}
}