{
  "type": "Feature",
  "properties": {
    "iso:country":"ES",
    "sg:address":"Calle de Alcoy, 3",
    "sg:city":"Sevilla",
    "sg:orig_category":"Abogados",
    "sg:phone":"+34 954 38 29 10",
    "sg:postcode":"41002",
    "sg:province":"Sevilla",
    "wof:name":"Zamorano Flores Felipe Agustin",
    "wof:placetype":"venue"
},
  "geometry": {"coordinates":[-5.9971570969,37.3977012634],"type":"Point"}
}