{
  "type": "Feature",
  "properties": {
    "iso:country":"ES",
    "sg:address":"Carr Santiago Rusi\u00d1ol, 14",
    "sg:city":"Badalona",
    "sg:orig_category":"Bisuter\u00cda, Joyer\u00cda, Relojer\u00cda (al Por Menor)",
    "sg:phone":"+34 934 64 15 24",
    "sg:postcode":"08911",
    "sg:province":"Barcelona",
    "wof:name":"Urquizu Conesa David",
    "wof:placetype":"venue"
},
  "geometry": {"coordinates":[2.2526750565,41.4515762329],"type":"Point"}
}