{
  "type": "Feature",
  "properties": {
    "iso:country":"ES",
    "sg:address":"Ctra. Navahermosa, Km. 0044,0",
    "sg:city":"Mazarambroz",
    "sg:orig_category":"Negocio De Enlosados, Soler\u00cdas",
    "sg:phone":"+34 925 39 76 24",
    "sg:postcode":"45114",
    "sg:province":"Toledo",
    "wof:name":"Diogenes E Hijo S.l.",
    "wof:placetype":"venue"
},
  "geometry": {"coordinates":[-4.0176510811,39.6934051514],"type":"Point"}
}