{
  "type": "Feature",
  "properties": {
    "iso:country":"ES",
    "sg:address":"Calle de Aller, 5",
    "sg:city":"Mieres",
    "sg:orig_category":"Electrodom\u00c9sticos (al Por Menor)",
    "sg:phone":"+34 985 46 00 24",
    "sg:postcode":"33600",
    "sg:province":"Asturias",
    "wof:name":"Garrocho Fernandez Juan Manuel",
    "wof:placetype":"venue"
},
  "geometry": {"coordinates":[-5.7767996788,43.2525444031],"type":"Point"}
}