{
  "type": "Feature",
  "properties": {
    "iso:country":"ES",
    "sg:address":"Telers, 49",
    "sg:city":"Ontinyent",
    "sg:orig_category":"Bebidas",
    "sg:phone":"+34 962 38 69 87",
    "sg:postcode":"46870",
    "sg:province":"Valencia",
    "wof:name":"Distribuciones Chati S.l.",
    "wof:placetype":"venue"
},
  "geometry": {"coordinates":[-0.576128006,38.8322525024],"type":"Point"}
}