{
  "type": "Feature",
  "properties": {
    "iso:country":"ES",
    "sg:address":"Calle de Cuba, 37",
    "sg:city":"Valencia",
    "sg:orig_category":"Maquinaria Para Industrias Diversas",
    "sg:phone":"+34 963 41 59 49",
    "sg:postcode":"46006",
    "sg:province":"Valencia",
    "wof:name":"Santamaria Revert Sixto",
    "wof:placetype":"venue"
},
  "geometry": {"coordinates":[-0.3761900067,39.4609870911],"type":"Point"}
}