{
  "type": "Feature",
  "properties": {
    "iso:country":"ES",
    "sg:address":"Calle de Hermanos Pinzon, 45",
    "sg:city":"Almeria",
    "sg:orig_category":"M\u00c1quinas De Coser Y De Hacer Punto (al Por Mayor)",
    "sg:phone":"+34 950 26 47 97",
    "sg:postcode":"04005",
    "sg:province":"Almer\u00eda",
    "wof:name":"Juan Verdejo S.l.",
    "wof:placetype":"venue"
},
  "geometry": {"coordinates":[-2.4556488991,36.8403739929],"type":"Point"}
}