{
  "type": "Feature",
  "properties": {
    "iso:country":"ES",
    "sg:address":"Calle de Jose Arana, 14",
    "sg:city":"Donostia-san Sebastian",
    "sg:orig_category":"Peluquer\u00cdas, Peluquer\u00cda Mixta",
    "sg:phone":"+34 943 27 51 82",
    "sg:postcode":"20001",
    "sg:province":"Guip\u00f9zcoa",
    "wof:name":"Milagros Zubiri Loiarte",
    "wof:placetype":"venue"
},
  "geometry": {"coordinates":[-1.9694360495,43.3238067627],"type":"Point"}
}