{
  "type": "Feature",
  "properties": {
    "addr:full":"Jose Troyano, 31 Cala\u00f1as Huelva 21300",
    "addr:housenumber":"31",
    "addr:postcode":"21300",
    "addr:street":"Jose Troyano",
    "iso:country":"ES",
    "sg:address":"Jose Troyano, 31",
    "sg:city":"Cala\u00f1as",
    "sg:orig_category":"Abogados",
    "sg:phone":"+34 959 56 52 24",
    "sg:postcode":"21300",
    "sg:province":"Huelva",
    "wof:name":"Pe\u00f1a Gonzalez Mario",
    "wof:placetype":"venue"
},
  "geometry": {"coordinates":[-6.8803548813,37.6552200317],"type":"Point"}
}