{
  "type": "Feature",
  "properties": {
    "addr:full":"Calle de Maria Auxiliadora, 14 Sevilla Sevilla 41003",
    "addr:housenumber":"14",
    "addr:postcode":"41003",
    "addr:street":"Calle De Maria Auxiliadora",
    "iso:country":"ES",
    "sg:address":"Calle de Maria Auxiliadora, 14",
    "sg:city":"Sevilla",
    "sg:orig_category":"Ense\u00d1anza Variada",
    "sg:phone":"+34 954 54 03 50",
    "sg:postcode":"41003",
    "sg:province":"Sevilla",
    "wof:name":"Viera Sanchez Ana Maria",
    "wof:placetype":"venue"
},
  "geometry": {"coordinates":[-5.9824819565,37.3955688477],"type":"Point"}
}