{
  "type": "Feature",
  "properties": {
    "iso:country":"ES",
    "sg:address":"Trva Calatrava (de), 26",
    "sg:city":"Fuente El Fresno",
    "sg:orig_category":"Mec\u00c1nico Del Autom\u00d3vil",
    "sg:phone":"+34 926 80 63 95",
    "sg:postcode":"13680",
    "sg:province":"Ciudad Real",
    "wof:name":"Sanchez Aparicio Cecilio",
    "wof:placetype":"venue"
},
  "geometry": {"coordinates":[-3.778498888,39.2257041931],"type":"Point"}
}