{
  "type": "Feature",
  "properties": {
    "iso:country":"ES",
    "sg:address":"Ctra Molins De Rei, Km. 0013,0",
    "sg:city":"Rubi",
    "sg:orig_category":"Suministros Y Materiales Industriales",
    "sg:phone":"+34 935 86 08 46",
    "sg:postcode":"08191",
    "sg:province":"Barcelona",
    "wof:name":"Friction Solutions S.l.",
    "wof:placetype":"venue"
},
  "geometry": {"coordinates":[2.0307109356,41.4825019836],"type":"Point"}
}