{
  "type": "Feature",
  "properties": {
    "iso:country":"ES",
    "sg:address":"Carr Canelones, 25",
    "sg:city":"Badalona",
    "sg:orig_category":"Venta, Instalaci\u00d3n De Calefacci\u00d3n",
    "sg:phone":"+34 934 65 52 29",
    "sg:postcode":"08917",
    "sg:province":"Barcelona",
    "wof:name":"Modegas S. A.",
    "wof:placetype":"venue"
},
  "geometry": {"coordinates":[2.2198500633,41.4571914673],"type":"Point"}
}