{
  "type": "Feature",
  "properties": {
    "addr:full":"Calle de Nuestra Se\u00d1ora De La Luz, 2 Madrid Madrid 28025",
    "addr:housenumber":"2",
    "addr:postcode":"28025",
    "addr:street":"Calle De Nuestra Sen\u0303Ora De La Luz",
    "iso:country":"ES",
    "sg:address":"Calle de Nuestra Se\u00d1ora De La Luz, 2",
    "sg:city":"Madrid",
    "sg:orig_category":"Madera Para Construcci\u00d3n E Industria",
    "sg:phone":"+34 914 62 64 94",
    "sg:postcode":"28025",
    "sg:province":"Madrid",
    "wof:name":"Eco Parquet Scarfer S.l.",
    "wof:placetype":"venue"
},
  "geometry": {"coordinates":[-3.7413370609,40.3830528259],"type":"Point"}
}