{
  "type": "Feature",
  "properties": {
    "addr:full":"F\u00e9lix Vera, 3 Torre-pacheco Murcia 30700",
    "addr:housenumber":"3",
    "addr:postcode":"30700",
    "addr:street":"Vera",
    "iso:country":"ES",
    "sg:address":"F\u00e9lix Vera, 3",
    "sg:city":"Torre-pacheco",
    "sg:orig_category":"Promotores Constructores",
    "sg:phone":"+34 968 58 51 78",
    "sg:postcode":"30700",
    "sg:province":"Murcia",
    "wof:name":"Almohaya Ballester S.l.",
    "wof:placetype":"venue"
},
  "geometry": {"coordinates":[-0.9564489126,37.7451705933],"type":"Point"}
}