{
  "type": "Feature",
  "properties": {
    "iso:country":"ES",
    "sg:address":"Avda Oliva, 45",
    "sg:city":"Majadahonda",
    "sg:orig_category":"Contables",
    "sg:phone":"+34 916 02 93 47",
    "sg:postcode":"28220",
    "sg:province":"Madrid",
    "wof:name":"Jimenez De Mu\u00d1ana Garcia,elena 000493080p Sl Ne",
    "wof:placetype":"venue"
},
  "geometry": {"coordinates":[-3.8659260273,40.4472084045],"type":"Point"}
}