{
  "type": "Feature",
  "properties": {
    "addr:full":"Calle de Real, 34 Estacion Madrid 28400",
    "addr:housenumber":"34",
    "addr:postcode":"28400",
    "addr:street":"Calle De Real",
    "iso:country":"ES",
    "sg:address":"Calle de Real, 34",
    "sg:city":"Estacion",
    "sg:orig_category":"Inform\u00c1tica: Material Y Suministros",
    "sg:phone":"+34 918 51 63 00",
    "sg:postcode":"28400",
    "sg:province":"Madrid",
    "wof:name":"Garcia Perez Manuel",
    "wof:placetype":"venue"
},
  "geometry": {"coordinates":[-3.9919650555,40.6455612183],"type":"Point"}
}