{
  "type": "Feature",
  "properties": {
    "addr:full":"Sepulcro, 3 Ciudad Rodrigo Salamanca 37500",
    "addr:housenumber":"3",
    "addr:postcode":"37500",
    "addr:street":"Sepulcro",
    "iso:country":"ES",
    "sg:address":"Sepulcro, 3",
    "sg:city":"Ciudad Rodrigo",
    "sg:orig_category":"Molduras, Junquillos, Listones Y Molduras Perforadas",
    "sg:phone":"+34 923 48 21 87",
    "sg:postcode":"37500",
    "sg:province":"Salamanca",
    "wof:name":"Martin Iglesias David Eugenio",
    "wof:placetype":"venue"
},
  "geometry": {"coordinates":[-6.5330991745,40.5977783203],"type":"Point"}
}