{
  "type": "Feature",
  "properties": {
    "addr:full":"Carrer de Frederica Montseny, 48 Sant Feliu Llobregat Barcelona 08980",
    "addr:housenumber":"48",
    "addr:postcode":"08980",
    "addr:street":"Carrer De Frederica Montseny",
    "iso:country":"ES",
    "sg:address":"Carrer de Frederica Montseny, 48",
    "sg:city":"Sant Feliu Llobregat",
    "sg:orig_category":"Asesor\u00cda Sobre Comunicaci\u00d3n De Empresas",
    "sg:phone":"+34 936 32 69 16",
    "sg:postcode":"08980",
    "sg:province":"Barcelona",
    "wof:name":"Quadraliger Sl",
    "wof:placetype":"venue"
},
  "geometry": {"coordinates":[2.0435750484,41.3816261292],"type":"Point"}
}