{
  "type": "Feature",
  "properties": {
    "iso:country":"ES",
    "sg:address":"Calle de Jorge Guillen, 12",
    "sg:city":"Vista Alegre",
    "sg:orig_category":"Agencias Y Agentes Comerciales, Representantes",
    "sg:phone":"+34 968 20 21 98",
    "sg:postcode":"30007",
    "sg:province":"Murcia",
    "wof:name":"Ayala Lopez Vicente Jesus",
    "wof:placetype":"venue"
},
  "geometry": {"coordinates":[-1.1142389774,37.9970092773],"type":"Point"}
}