{
  "type": "Feature",
  "properties": {
    "iso:country":"ES",
    "sg:address":"Calle de Carrasca (de La), 1",
    "sg:city":"Alhama Murcia",
    "sg:orig_category":"Electrodom\u00c9sticos (al Por Menor)",
    "sg:phone":"+34 968 63 10 11",
    "sg:postcode":"30840",
    "sg:province":"Murcia",
    "wof:name":"Alcon Rubio Juan",
    "wof:placetype":"venue"
},
  "geometry": {"coordinates":[-1.4311653376,37.8486289978],"type":"Point"}
}