{
  "type": "Feature",
  "properties": {
    "addr:full":"Avda Espa\u00d1a, 32 Ceuta Ceuta 51001",
    "addr:housenumber":"32",
    "addr:postcode":"51001",
    "addr:street":"Avda Espan\u0303A",
    "iso:country":"ES",
    "sg:address":"Avda Espa\u00d1a, 32",
    "sg:city":"Ceuta",
    "sg:orig_category":"Agencias Y Agentes Comerciales, Representantes",
    "sg:phone":"+34 956 52 21 11",
    "sg:postcode":"51001",
    "sg:province":"Ceuta",
    "wof:name":"M. De Hoyos S.l.",
    "wof:placetype":"venue"
},
  "geometry": {"coordinates":[-5.3248167038,35.8916893005],"type":"Point"}
}