{
  "type": "Feature",
  "properties": {
    "iso:country":"ES",
    "sg:address":"Barr Estacion (la), S/n",
    "sg:city":"Aguilar Campoo",
    "sg:orig_category":"Producci\u00d3n, Comercio De Cereales",
    "sg:phone":"+34 979 12 28 39",
    "sg:postcode":"34800",
    "sg:province":"Palencia",
    "wof:name":"Agraria Aguilarense Sociedad Cooperativa Limitada",
    "wof:placetype":"venue"
},
  "geometry": {"coordinates":[-4.5311746597,42.0124588013],"type":"Point"}
}