{
  "type": "Feature",
  "properties": {
    "iso:country":"ES",
    "sg:address":"Pl. Esglesia, 25",
    "sg:city":"Binissalem",
    "sg:orig_category":"Molduras, Junquillos, Listones Y Molduras Perforadas",
    "sg:phone":"+34 971 87 04 26",
    "sg:postcode":"07350",
    "sg:province":"Islas Baleares",
    "wof:name":"Borras Reynes Antonio",
    "wof:placetype":"venue"
},
  "geometry": {"coordinates":[2.8427169323,39.6889648438],"type":"Point"}
}