{
  "type": "Feature",
  "properties": {
    "iso:country":"ES",
    "sg:address":"Plaz San Martin, 25",
    "sg:city":"Benavente",
    "sg:orig_category":"Molinos",
    "sg:phone":"+34 980 63 07 12",
    "sg:postcode":"49600",
    "sg:province":"Zamora",
    "wof:name":"Robles Ramos Patricio",
    "wof:placetype":"venue"
},
  "geometry": {"coordinates":[-5.677795887,42.0033531189],"type":"Point"}
}