{
  "type": "Feature",
  "properties": {
    "addr:full":"Polig.industrial Azitain, 3 Eibar Guip\u00f9zcoa 20600",
    "addr:housenumber":"3",
    "addr:postcode":"20600",
    "addr:street":"Azitain;Guipu\u0300Zcoa",
    "iso:country":"ES",
    "sg:address":"Polig.industrial Azitain, 3",
    "sg:city":"Eibar",
    "sg:orig_category":"M\u00c1quinas Y Material Para La Industria De La Alimentaci\u00d3n",
    "sg:phone":"+34 943 82 01 00",
    "sg:postcode":"20600",
    "sg:province":"Guip\u00f9zcoa",
    "sg:website":"www.hannainst.es",
    "wof:name":"Hanna Instruments S.l.",
    "wof:placetype":"venue"
},
  "geometry": {"coordinates":[-2.4884390831,43.1800117493],"type":"Point"}
}