{
  "type": "Feature",
  "properties": {
    "addr:full":"Calle de Fernando Moran Lavandera, 15 Gijon Asturias 33209",
    "addr:housenumber":"15",
    "addr:postcode":"33209",
    "addr:street":"Calle De Fernando Moran Lavandera",
    "iso:country":"ES",
    "sg:address":"Calle de Fernando Moran Lavandera, 15",
    "sg:city":"Gijon",
    "sg:orig_category":"Pintura Y Barniz (al Por Menor)",
    "sg:phone":"+34 985 14 99 09",
    "sg:postcode":"33209",
    "sg:province":"Asturias",
    "wof:name":"Pelaez Tremols Montserrat",
    "wof:placetype":"venue"
},
  "geometry": {"coordinates":[-5.6608290672,43.534828186],"type":"Point"}
}