{
  "type": "Feature",
  "properties": {
    "addr:full":"Balneario Panticosa, S/n Ba\u00f1os Panticosa Huesca 22650",
    "addr:housenumber":"s / n",
    "addr:postcode":"22650",
    "iso:country":"ES",
    "sg:address":"Balneario Panticosa, S/n",
    "sg:city":"Ba\u00f1os Panticosa",
    "sg:orig_category":"Bazares, Art\u00cdculos De Limpieza Y De Cocina (al Por Menor)",
    "sg:phone":"+34 974 48 76 29",
    "sg:postcode":"22650",
    "sg:province":"Huesca",
    "wof:name":"Nuel Porcal Julio",
    "wof:placetype":"venue"
},
  "geometry": {"coordinates":[-0.2341679931,42.7594566345],"type":"Point"}
}