{
  "type": "Feature",
  "properties": {
    "iso:country":"ES",
    "sg:address":"Calle de Cristo Del, 17",
    "sg:city":"Bilbao",
    "sg:orig_category":"Peluqueros: De Se\u00d1oras",
    "sg:phone":"+34 944 45 25 64",
    "sg:postcode":"48007",
    "sg:province":"Vizcaya",
    "wof:name":"Martinez Munilla Maria Jesus",
    "wof:placetype":"venue"
},
  "geometry": {"coordinates":[-2.9223937988,43.2651977539],"type":"Point"}
}