{
  "type": "Feature",
  "properties": {
    "addr:full":"Calle de San Esteban, 4 Leganes Madrid 28912",
    "addr:housenumber":"4",
    "addr:postcode":"28912",
    "addr:street":"Calle De San Esteban",
    "iso:country":"ES",
    "sg:address":"Calle de San Esteban, 4",
    "sg:city":"Leganes",
    "sg:orig_category":"Arreglo E Instalaci\u00d3n De Caf\u00c9s, Hoteles Y Restaurantes",
    "sg:phone":"+34 916 86 63 36",
    "sg:postcode":"28912",
    "sg:province":"Madrid",
    "wof:name":"Jimeca S.l.",
    "wof:placetype":"venue"
},
  "geometry": {"coordinates":[-3.7602493763,40.3321151733],"type":"Point"}
}