{
  "type": "Feature",
  "properties": {
    "iso:country":"ES",
    "sg:address":"Carrer de Barcelona, 291",
    "sg:city":"Sant Vicen\u00c7 Dels Horts",
    "sg:orig_category":"Frutas, Legumbres Frescas Y Tempranas (al Por Menor)",
    "sg:phone":"+34 936 72 46 16",
    "sg:postcode":"08620",
    "sg:province":"Barcelona",
    "wof:name":"Frutas Andres S.a.",
    "wof:placetype":"venue"
},
  "geometry": {"coordinates":[2.0068171024,41.399974823],"type":"Point"}
}