{
  "type": "Feature",
  "properties": {
    "addr:full":"Carrer de Clavell, 32 Montcada Centre Barcelona 08110",
    "addr:housenumber":"32",
    "addr:postcode":"08110",
    "addr:street":"Carrer De Clavell",
    "iso:country":"ES",
    "sg:address":"Carrer de Clavell, 32",
    "sg:city":"Montcada Centre",
    "sg:orig_category":"Molduras, Junquillos, Listones Y Molduras Perforadas",
    "sg:phone":"+34 935 64 33 54",
    "sg:postcode":"08110",
    "sg:province":"Barcelona",
    "wof:name":"Mantenimiento Y Servicios Bernal S.l.",
    "wof:placetype":"venue"
},
  "geometry": {"coordinates":[2.1890830994,41.4842681885],"type":"Point"}
}