{
  "type": "Feature",
  "properties": {
    "iso:country":"ES",
    "sg:address":"Calle de Achucarro Doctor, 4",
    "sg:city":"Bilbao",
    "sg:orig_category":"Centros De Coordinaci\u00d3n",
    "sg:phone":"+34 944 02 51 15",
    "sg:postcode":"48011",
    "sg:province":"Vizcaya",
    "wof:name":"Manuel Sanz Torre",
    "wof:placetype":"venue"
},
  "geometry": {"coordinates":[-2.9388227463,43.2640609741],"type":"Point"}
}