{
  "type": "Feature",
  "properties": {
    "iso:country":"ES",
    "sg:address":"Carrer de Mina De La Ciutat, 16",
    "sg:city":"Barcelona",
    "sg:orig_category":"Comerciantes Al Por Mayor De Vinos, Licores Y Alcoholes",
    "sg:phone":"+34 933 54 23 92",
    "sg:postcode":"08042",
    "sg:province":"Barcelona",
    "wof:name":"Touza Feijoo Manuel",
    "wof:placetype":"venue"
},
  "geometry": {"coordinates":[2.173787117,41.4469985962],"type":"Point"}
}