{
  "type": "Feature",
  "properties": {
    "iso:country":"ES",
    "sg:address":"Calle de Colon, 10",
    "sg:city":"Bejar",
    "sg:orig_category":"Abogados",
    "sg:phone":"+34 923 40 01 29",
    "sg:postcode":"37700",
    "sg:province":"Salamanca",
    "wof:name":"Rodriguez-arias Sanchez Alfonso",
    "wof:placetype":"venue"
},
  "geometry": {"coordinates":[-5.7705168724,40.3864593506],"type":"Point"}
}