{
  "type": "Feature",
  "properties": {
    "addr:full":"Calle de Escuelas, S/n Nava Campa\u00e7a Albacete 02409",
    "addr:housenumber":"s / n",
    "addr:postcode":"02409",
    "addr:street":"Calle De Escuelas",
    "iso:country":"ES",
    "sg:address":"Calle de Escuelas, S/n",
    "sg:city":"Nava Campa\u00e7a",
    "sg:orig_category":"Centros De Educaci\u00d3n Especial",
    "sg:phone":"+34 967 30 72 16",
    "sg:postcode":"02409",
    "sg:province":"Albacete",
    "wof:name":"Colegio Rural Agrupado Rio Mundo",
    "wof:placetype":"venue"
},
  "geometry": {"coordinates":[-1.6512839794,38.4910469055],"type":"Point"}
}