{
  "type": "Feature",
  "properties": {
    "iso:country":"ES",
    "sg:address":"C/ Diagonal, 86",
    "sg:city":"Elche",
    "sg:orig_category":"Cajas De Ahorro",
    "sg:phone":"+34 965 43 14 48",
    "sg:postcode":"03206",
    "sg:province":"Alicante",
    "sg:website":"www.lacaixa.es",
    "wof:name":"Caixa D'estalvis I Pensions De Barcelona",
    "wof:placetype":"venue"
},
  "geometry": {"coordinates":[-0.7119640112,38.2737846375],"type":"Point"}
}