{
  "type": "Feature",
  "properties": {
    "iso:country":"ES",
    "sg:address":"Pg Sant Gervasi, 24",
    "sg:city":"Barcelona",
    "sg:orig_category":"Animales (al Por Menor)",
    "sg:phone":"+34 932 12 44 70",
    "sg:postcode":"08022",
    "sg:province":"Barcelona",
    "wof:name":"Gras Creus Daniel",
    "wof:placetype":"venue"
},
  "geometry": {"coordinates":[2.1347568035,41.4090461731],"type":"Point"}
}