{
  "type": "Feature",
  "properties": {
    "addr:full":"Calle de Sabino Arana, 8 Amorebieta Vizcaya 48340",
    "addr:housenumber":"8",
    "addr:postcode":"48340",
    "addr:street":"Calle De Sabino Arana",
    "iso:country":"ES",
    "sg:address":"Calle de Sabino Arana, 8",
    "sg:city":"Amorebieta",
    "sg:orig_category":"Bisuter\u00cda, Joyer\u00cda, Relojer\u00cda (al Por Menor)",
    "sg:phone":"+34 946 73 07 84",
    "sg:postcode":"48340",
    "sg:province":"Vizcaya",
    "wof:name":"Echeverria Churruca Jose Luis",
    "wof:placetype":"venue"
},
  "geometry": {"coordinates":[-2.7342579365,43.2195167542],"type":"Point"}
}