{
  "type": "Feature",
  "properties": {
    "iso:country":"ES",
    "sg:address":"Rua Trasariz, 14",
    "sg:city":"Vimianzo",
    "sg:orig_category":"Agentes Generales De Seguros",
    "sg:phone":"+34 981 70 74 60",
    "sg:postcode":"15120",
    "sg:province":"A Coru\u00f1a",
    "wof:name":"Seguros Costa Da Morte S.l.",
    "wof:placetype":"venue"
},
  "geometry": {"coordinates":[-9.0321779251,43.1106376648],"type":"Point"}
}