{
  "type": "Feature",
  "properties": {
    "iso:country":"ES",
    "sg:address":"Rond Caballero De La Mancha, 81",
    "sg:city":"Madrid",
    "sg:orig_category":"Agencias Y Asesores De Publicidad",
    "sg:phone":"+34 917 35 55 00",
    "sg:postcode":"28034",
    "sg:province":"Madrid",
    "wof:name":"Street Life Comunication S.l.",
    "wof:placetype":"venue"
},
  "geometry": {"coordinates":[-3.6919970512,40.5023231506],"type":"Point"}
}