{
  "type": "Feature",
  "properties": {
    "addr:full":"Calle de Rambla, 1 Garres Murcia 30158",
    "addr:housenumber":"1",
    "addr:postcode":"30158",
    "addr:street":"Calle De Rambla",
    "iso:country":"ES",
    "sg:address":"Calle de Rambla, 1",
    "sg:city":"Garres",
    "sg:orig_category":"Transportes Por V\u00cdas Navegables",
    "sg:phone":"+34 968 82 40 69",
    "sg:postcode":"30158",
    "sg:province":"Murcia",
    "wof:name":"Alquiler De Maquinaria Rentaire S.a",
    "wof:placetype":"venue"
},
  "geometry": {"coordinates":[-1.0949647427,37.9556846619],"type":"Point"}
}