{
  "type": "Feature",
  "properties": {
    "addr:full":"Calle de Martires, 56 Montijo Badajoz 06480",
    "addr:housenumber":"56",
    "addr:postcode":"06480",
    "addr:street":"Calle De Martires",
    "iso:country":"ES",
    "sg:address":"Calle de Martires, 56",
    "sg:city":"Montijo",
    "sg:orig_category":"Asesor\u00cda Sobre Comunicaci\u00d3n De Empresas",
    "sg:phone":"+34 924 45 24 54",
    "sg:postcode":"06480",
    "sg:province":"Badajoz",
    "wof:name":"Jipa S.l.",
    "wof:placetype":"venue"
},
  "geometry": {"coordinates":[-6.6209540367,38.9066314697],"type":"Point"}
}