{
  "type": "Feature",
  "properties": {
    "iso:country":"ES",
    "sg:address":"Calle de Mariano Adam, 7",
    "sg:city":"Zaragoza",
    "sg:orig_category":"Ebanister\u00cda",
    "sg:phone":"+34 976 59 28 64",
    "sg:postcode":"50013",
    "sg:province":"Zaragoza",
    "wof:name":"Linea Jem S. A. L.",
    "wof:placetype":"venue"
},
  "geometry": {"coordinates":[-0.8699569702,41.6408882141],"type":"Point"}
}