{
  "type": "Feature",
  "properties": {
    "iso:country":"ES",
    "sg:address":"Carrer de Morato (dels), 10",
    "sg:city":"Vic",
    "sg:orig_category":"Prot\u00c9sicos Dentales",
    "sg:phone":"+34 938 85 38 03",
    "sg:postcode":"08500",
    "sg:province":"Barcelona",
    "wof:name":"Aceves Cuellar Ismael",
    "wof:placetype":"venue"
},
  "geometry": {"coordinates":[2.249505,41.929787],"type":"Point"}
}