{
  "type": "Feature",
  "properties": {
    "iso:country":"ES",
    "sg:address":"Calle de Antonio Jorge, 1",
    "sg:city":"Pto. Rosario",
    "sg:orig_category":"Promotores Constructores",
    "sg:phone":"+34 928 85 81 04",
    "sg:postcode":"35600",
    "sg:province":"Las Palmas",
    "wof:name":"Construcciones Y Promociones Nipe S.l.",
    "wof:placetype":"venue"
},
  "geometry": {"coordinates":[-13.8706970215,28.5025310516],"type":"Point"}
}