{
  "type": "Feature",
  "properties": {
    "addr:full":"Avda Andalucia (de), 1 Coria Rio Sevilla 41100",
    "addr:postcode":"41100",
    "addr:street":"Avda Andalucia De",
    "iso:country":"ES",
    "sg:address":"Avda Andalucia (de), 1",
    "sg:city":"Coria Rio",
    "sg:orig_category":"Molduras, Junquillos, Listones Y Molduras Perforadas",
    "sg:phone":"+34 954 77 62 85",
    "sg:postcode":"41100",
    "sg:province":"Sevilla",
    "wof:name":"Garcia Gutierrez Maria Del Rosario",
    "wof:placetype":"venue"
},
  "geometry": {"coordinates":[-6.0485291481,37.2866516113],"type":"Point"}
}