{
  "type": "Feature",
  "properties": {
    "addr:full":"Partida Cap-blanch, 187 Cap-blanch Alicante 03590",
    "addr:housenumber":"187",
    "addr:postcode":"03590",
    "addr:street":"Partida Cap-Blanch;Alicante",
    "iso:country":"ES",
    "sg:address":"Partida Cap-blanch, 187",
    "sg:city":"Cap-blanch",
    "sg:orig_category":"Veh\u00cdculos De Ocasi\u00d3n",
    "sg:phone":"+34 965 84 12 77",
    "sg:postcode":"03590",
    "sg:province":"Alicante",
    "wof:name":"Auto Maq Altea S.l.",
    "wof:placetype":"venue"
},
  "geometry": {"coordinates":[-0.0506840013,38.6008338928],"type":"Point"}
}