{
  "type": "Feature",
  "properties": {
    "addr:full":"Calle de Buen Gobernador, 11 Madrid Madrid 28027",
    "addr:housenumber":"11",
    "addr:postcode":"madrid;28027",
    "addr:street":"Calle De Buen Gobernador",
    "iso:country":"ES",
    "sg:address":"Calle de Buen Gobernador, 11",
    "sg:city":"Madrid",
    "sg:orig_category":"Inmobiliaria (agencias)",
    "sg:phone":"+34 914 04 92 33",
    "sg:postcode":"28027",
    "sg:province":"Madrid",
    "wof:name":"Salazar Fernandez Jose",
    "wof:placetype":"venue"
},
  "geometry": {"coordinates":[-3.6545863152,40.4336662292],"type":"Point"}
}