{
  "type": "Feature",
  "properties": {
    "addr:full":"Avda Pirineos (de Los), 9 Huesca Huesca 22004",
    "addr:housenumber":"9",
    "addr:postcode":"22004",
    "addr:street":"Avda Pirineos De Los",
    "iso:country":"ES",
    "sg:address":"Avda Pirineos (de Los), 9",
    "sg:city":"Huesca",
    "sg:orig_category":"Librer\u00cdas",
    "sg:phone":"+34 974 22 85 41",
    "sg:postcode":"22004",
    "sg:province":"Huesca",
    "wof:name":"Albajar Barron Julio",
    "wof:placetype":"venue"
},
  "geometry": {"coordinates":[-0.4166531861,42.1422348022],"type":"Point"}
}