{
  "type": "Feature",
  "properties": {
    "iso:country":"ES",
    "sg:address":"Carr Sant Roc, 21",
    "sg:city":"Figueres",
    "sg:orig_category":"Cerrajer\u00cda, Ferrallista",
    "sg:phone":"+34 972 50 29 37",
    "sg:postcode":"17600",
    "sg:province":"Girona",
    "wof:name":"Alonso Alonso Francisco",
    "wof:placetype":"venue"
},
  "geometry": {"coordinates":[2.965113163,42.2691307068],"type":"Point"}
}