{
  "type": "Feature",
  "properties": {
    "addr:full":"Calle de Estacion, 1 Pe\u00e7arroya-pueblonuevo C\u00f3rdoba 14200",
    "addr:housenumber":"1",
    "addr:postcode":"14200",
    "addr:street":"Calle De Estacion;Co\u0301Rdoba",
    "iso:country":"ES",
    "sg:address":"Calle de Estacion, 1",
    "sg:city":"Pe\u00e7arroya-pueblonuevo",
    "sg:orig_category":"Transportes Por V\u00cdas Navegables",
    "sg:phone":"+34 957 56 02 35",
    "sg:postcode":"14200",
    "sg:province":"C\u00f3rdoba",
    "wof:name":"Auto Transportes Lopez S.a.",
    "wof:placetype":"venue"
},
  "geometry": {"coordinates":[-4.7791519165,37.884727478],"type":"Point"}
}