{
  "type": "Feature",
  "properties": {
    "addr:full":"Calle de Albaida, 2 Valencia Valencia 46018",
    "addr:housenumber":"2",
    "addr:postcode":"46018",
    "addr:street":"Calle De Albaida",
    "iso:country":"ES",
    "sg:address":"Calle de Albaida, 2",
    "sg:city":"Valencia",
    "sg:orig_category":"Televisi\u00d3n, V\u00cddeo: Aparatos Y Accesorios (venta)",
    "sg:phone":"+34 963 85 60 05",
    "sg:postcode":"46018",
    "sg:province":"Valencia",
    "wof:name":"Mayro Magnetics S.a.",
    "wof:placetype":"venue"
},
  "geometry": {"coordinates":[-0.3915381134,39.4663925171],"type":"Point"}
}