{
  "type": "Feature",
  "properties": {
    "addr:full":"Calle de Arganda, 34 Madrid Madrid 28005",
    "addr:housenumber":"34",
    "addr:postcode":"madrid;28005",
    "addr:street":"Calle De Arganda",
    "iso:country":"ES",
    "sg:address":"Calle de Arganda, 34",
    "sg:city":"Madrid",
    "sg:orig_category":"Sindicatos De Trabajadores",
    "sg:phone":"+34 914 74 78 31",
    "sg:postcode":"28005",
    "sg:province":"Madrid",
    "wof:name":"Simeco",
    "wof:placetype":"venue"
},
  "geometry": {"coordinates":[-3.7050490379,40.3982162476],"type":"Point"}
}