{
  "type": "Feature",
  "properties": {
    "addr:full":"Carrer de Cos (del), 3 Mataro Barcelona 08301",
    "addr:housenumber":"3",
    "addr:postcode":"08301",
    "addr:street":"Carrer De Cos Del",
    "iso:country":"ES",
    "sg:address":"Carrer de Cos (del), 3",
    "sg:city":"Mataro",
    "sg:orig_category":"Agencias De Trabajo Temporal",
    "sg:phone":"+34 937 96 49 20",
    "sg:postcode":"08301",
    "sg:province":"Barcelona",
    "sg:website":"www.vedior.es",
    "wof:name":"Laborman Trabajo Temporal Ett S.a.",
    "wof:placetype":"venue"
},
  "geometry": {"coordinates":[2.4474289417,41.5370979309],"type":"Point"}
}