{
  "type": "Feature",
  "properties": {
    "iso:country":"ES",
    "sg:address":"Castell Burjacenia, S/n",
    "sg:city":"L'aldea",
    "sg:orig_category":"Sales (al Por Mayor)",
    "sg:phone":"+34 977 45 00 96",
    "sg:postcode":"43896",
    "sg:province":"Tarragona",
    "wof:name":"Condominio Hermanos Reventos Soler",
    "wof:placetype":"venue"
},
  "geometry": {"coordinates":[0.5801349878,40.7140197754],"type":"Point"}
}