{
  "type": "Feature",
  "properties": {
    "addr:full":"Carrer de Pedraforca, 22 Hospitalet Llobregat Barcelona 08905",
    "addr:housenumber":"22",
    "addr:postcode":"08905",
    "addr:street":"Carrer De Pedraforca",
    "iso:country":"ES",
    "sg:address":"Carrer de Pedraforca, 22",
    "sg:city":"Hospitalet Llobregat",
    "sg:orig_category":"Electromec\u00c1nica",
    "sg:phone":"+34 934 40 77 60",
    "sg:postcode":"08905",
    "sg:province":"Barcelona",
    "wof:name":"Fernandez Rodriguez Antonio",
    "wof:placetype":"venue"
},
  "geometry": {"coordinates":[2.1108601093,41.3733024597],"type":"Point"}
}