{
  "type": "Feature",
  "properties": {
    "addr:full":"Camino Viejo De Jun, 1 Jun Granada 18213",
    "addr:housenumber":"1",
    "addr:postcode":"18213",
    "addr:street":"Camino Viejo De Jun",
    "iso:country":"ES",
    "sg:address":"Camino Viejo De Jun, 1",
    "sg:city":"Jun",
    "sg:orig_category":"Ebanister\u00cda",
    "sg:phone":"+34 958 41 40 12",
    "sg:postcode":"18213",
    "sg:province":"Granada",
    "wof:name":"Ebanisteria Emilio Gutierrez Sl",
    "wof:placetype":"venue"
},
  "geometry": {"coordinates":[-3.594162941,37.2198905945],"type":"Point"}
}