{
  "type": "Feature",
  "properties": {
    "addr:full":"Calle de Baco, 18 Ejido Almer\u00eda 04700",
    "addr:housenumber":"18 ejido",
    "addr:postcode":"04700",
    "addr:street":"Calle De Baco;Almeri\u0301A",
    "iso:country":"ES",
    "sg:address":"Calle de Baco, 18",
    "sg:city":"Ejido",
    "sg:orig_category":"Discapacitados",
    "sg:phone":"+34 950 57 23 32",
    "sg:postcode":"04700",
    "sg:province":"Almer\u00eda",
    "wof:name":"Asociacion De Minusvalidos Murgi",
    "wof:placetype":"venue"
},
  "geometry": {"coordinates":[-2.8117964268,36.779964447],"type":"Point"}
}