{
  "type": "Feature",
  "properties": {
    "iso:country":"ES",
    "sg:address":"Calle de Real, 59",
    "sg:city":"Miguelturra",
    "sg:orig_category":"Venta, Montaje De Neum\u00c1ticos",
    "sg:phone":"+34 926 24 12 79",
    "sg:postcode":"13170",
    "sg:province":"Ciudad Real",
    "wof:name":"N.r. Neumaticos Ramirez S.l.",
    "wof:placetype":"venue"
},
  "geometry": {"coordinates":[-3.8941841125,38.9677581787],"type":"Point"}
}