{
  "type": "Feature",
  "properties": {
    "iso:country":"ES",
    "sg:address":"Avda Castilla Y Leon, 58",
    "sg:city":"Burgos",
    "sg:orig_category":"Abogados",
    "sg:phone":"+34 947 21 78 13",
    "sg:postcode":"09006",
    "sg:province":"Burgos",
    "wof:name":"Frances Perez Joaquin",
    "wof:placetype":"venue"
},
  "geometry": {"coordinates":[-3.6760540009,42.3570632935],"type":"Point"}
}