{
  "type": "Feature",
  "properties": {
    "iso:country":"ES",
    "sg:address":"Plaz Miguel De Cervantes, 7",
    "sg:city":"Sabi\u00f1anigo",
    "sg:orig_category":"Arquitectos",
    "sg:phone":"+34 974 48 20 00",
    "sg:postcode":"22600",
    "sg:province":"Huesca",
    "wof:name":"Hernanz Ramirez Francisca",
    "wof:placetype":"venue"
},
  "geometry": {"coordinates":[-0.2432307005,42.4132461548],"type":"Point"}
}