{
  "type": "Feature",
  "properties": {
    "iso:country":"ES",
    "sg:address":"Carr Caputxins, 13",
    "sg:city":"Vilanova I La Geltru",
    "sg:orig_category":"Ropa Para Se\u00d1oras (al Por Menor)",
    "sg:phone":"+34 938 93 91 76",
    "sg:postcode":"08800",
    "sg:province":"Barcelona",
    "wof:name":"Foraste Soler Luisa Maria",
    "wof:placetype":"venue"
},
  "geometry": {"coordinates":[1.7256749868,41.2258758545],"type":"Point"}
}