{
  "type": "Feature",
  "properties": {
    "iso:country":"ES",
    "sg:address":"Cmno Gandul, 27",
    "sg:city":"Mairena Alcor",
    "sg:orig_category":"Construcciones Met\u00c1licas",
    "sg:phone":"+34 955 74 70 58",
    "sg:postcode":"41510",
    "sg:province":"Sevilla",
    "wof:name":"Solindest S.l.",
    "wof:placetype":"venue"
},
  "geometry": {"coordinates":[-5.7439141273,37.377117157],"type":"Point"}
}