{
  "type": "Feature",
  "properties": {
    "iso:country":"ES",
    "sg:address":"Av Fran\u00c7a (de), 22",
    "sg:city":"S. Julia Ramis",
    "sg:orig_category":"Electrodom\u00c9sticos (al Por Menor)",
    "sg:phone":"+34 972 17 30 20",
    "sg:postcode":"17481",
    "sg:province":"Girona",
    "wof:name":"Punt Electro-girona S.a.",
    "wof:placetype":"venue"
},
  "geometry": {"coordinates":[2.8267281055,42.0239982605],"type":"Point"}
}