{
  "type": "Feature",
  "properties": {
    "addr:full":"Calle de Natacion, 42 Fuensalida Toledo 45510",
    "addr:housenumber":"42",
    "addr:postcode":"45510",
    "addr:street":"Calle De Natacion",
    "iso:country":"ES",
    "sg:address":"Calle de Natacion, 42",
    "sg:city":"Fuensalida",
    "sg:orig_category":"Centros Empresariales",
    "sg:phone":"+34 925 78 42 01",
    "sg:postcode":"45510",
    "sg:province":"Toledo",
    "wof:name":"Barrasa Y Robles Consultores S.l.",
    "wof:placetype":"venue"
},
  "geometry": {"coordinates":[-4.1997189522,40.0531311035],"type":"Point"}
}