{
  "type": "Feature",
  "properties": {
    "iso:country":"ES",
    "sg:address":"Avda Touroperador Tjaereborg, S/n",
    "sg:city":"Campo Internacional",
    "sg:orig_category":"Organismos De Turismo",
    "sg:phone":"+34 928 77 39 14",
    "sg:postcode":"35100",
    "sg:province":"Las Palmas",
    "wof:name":"Grass Club S. A.",
    "wof:placetype":"venue"
},
  "geometry": {"coordinates":[-15.4397096634,28.1302204132],"type":"Point"}
}