{
  "type": "Feature",
  "properties": {
    "iso:country":"ES",
    "sg:address":"Carrer de Arago, 186",
    "sg:city":"Barcelona",
    "sg:orig_category":"Centros P\u00dablicos De Formaci\u00d3n Profesional Y T\u00c9cnica",
    "sg:phone":"+34 934 51 25 57",
    "sg:postcode":"08011",
    "sg:province":"Barcelona",
    "wof:name":"Co%egi Oficial D'enginyeria Informatica De Catalunya",
    "wof:placetype":"venue"
},
  "geometry": {"coordinates":[2.1581659317,41.386932373],"type":"Point"}
}