{
  "type": "Feature",
  "properties": {
    "iso:country":"ES",
    "sg:address":"Plaz Manises, 2",
    "sg:city":"Valencia",
    "sg:orig_category":"Abogados",
    "sg:phone":"+34 963 91 83 43",
    "sg:postcode":"46003",
    "sg:province":"Valencia",
    "wof:name":"Abogados Pastor Y Asociados S.l.",
    "wof:placetype":"venue"
},
  "geometry": {"coordinates":[-0.37686,39.476753],"type":"Point"}
}