{
  "type": "Feature",
  "properties": {
    "addr:full":"Av Novelda, 164 Elche Alicante 03206",
    "addr:housenumber":"164",
    "addr:postcode":"03206",
    "addr:street":"Av Novelda",
    "iso:country":"ES",
    "sg:address":"Av Novelda, 164",
    "sg:city":"Elche",
    "sg:orig_category":"Negocio De Madera",
    "sg:phone":"+34 966 66 56 56",
    "sg:postcode":"03206",
    "sg:province":"Alicante",
    "sg:website":"www.maderasyderivadoscastejon.com",
    "wof:name":"Maderas Y Derivados Castejon S.l.",
    "wof:placetype":"venue"
},
  "geometry": {"coordinates":[-0.7215260267,38.282497406],"type":"Point"}
}