{
  "type": "Feature",
  "properties": {
    "iso:country":"ES",
    "sg:address":"Calle de General Sanjurjo, 1",
    "sg:city":"Almarcha",
    "sg:orig_category":"Administraciones Regionales, Departamentales Y Locales",
    "sg:phone":"+34 969 29 10 22",
    "sg:postcode":"16740",
    "sg:province":"Cuenca",
    "wof:name":"Ayuntamiento De La Almarcha",
    "wof:placetype":"venue"
},
  "geometry": {"coordinates":[-2.3775346279,39.6856842041],"type":"Point"}
}