{
  "type": "Feature",
  "properties": {
    "iso:country":"ES",
    "sg:address":"C/ Sant Agusti, 29",
    "sg:city":"Paterna",
    "sg:orig_category":"Peluqueros: De Se\u00d1oras",
    "sg:phone":"+34 961 37 15 51",
    "sg:postcode":"46980",
    "sg:province":"Valencia",
    "wof:name":"Perdices Garcia Maria",
    "wof:placetype":"venue"
},
  "geometry": {"coordinates":[-0.4505220056,39.5059776306],"type":"Point"}
}