{
  "type": "Feature",
  "properties": {
    "iso:country":"ES",
    "sg:address":"Calle de Diego De Leon, 40",
    "sg:city":"Madrid",
    "sg:orig_category":"Centros De Coordinaci\u00d3n",
    "sg:phone":"+34 915 62 36 31",
    "sg:postcode":"28006",
    "sg:province":"Madrid",
    "wof:name":"Gestoria Administrativa Garcia-maga\u00f1a S.c.",
    "wof:placetype":"venue"
},
  "geometry": {"coordinates":[-3.6804118156,40.4347839355],"type":"Point"}
}