{
  "type": "Feature",
  "properties": {
    "iso:country":"ES",
    "sg:address":"Calle de San Andres, 21",
    "sg:city":"Coru\u00d1a",
    "sg:orig_category":"Marroquiner\u00cda (confecci\u00d3n)",
    "sg:phone":"+34 981 22 72 70",
    "sg:postcode":"15003",
    "sg:province":"La Coru\u00f1a",
    "wof:name":"Oasis 2001 S.l.",
    "wof:placetype":"venue"
},
  "geometry": {"coordinates":[-8.4010047913,43.3709182739],"type":"Point"}
}