{
  "type": "Feature",
  "properties": {
    "addr:full":"Ctra Palencia, S/n Salda\u00f1a Palencia 34100",
    "addr:housenumber":"s / n",
    "addr:postcode":"34100",
    "addr:street":"Ctra Palencia",
    "iso:country":"ES",
    "sg:address":"Ctra Palencia, S/n",
    "sg:city":"Salda\u00f1a",
    "sg:orig_category":"Negocio De Materiales De Construcci\u00d3n",
    "sg:phone":"+34 979 89 06 64",
    "sg:postcode":"34100",
    "sg:province":"Palencia",
    "wof:name":"Gonzalez Ordo\u00f1ez Jose Marcos",
    "wof:placetype":"venue"
},
  "geometry": {"coordinates":[-4.7338600159,42.5220756531],"type":"Point"}
}