{
  "type": "Feature",
  "properties": {
    "addr:full":"Calle de Toledo, 18 Getafe Madrid 28901",
    "addr:housenumber":"18",
    "addr:postcode":"28901",
    "addr:street":"Calle De Toledo",
    "iso:country":"ES",
    "sg:address":"Calle de Toledo, 18",
    "sg:city":"Getafe",
    "sg:orig_category":"Pescader\u00cdas (al Por Menor)",
    "sg:phone":"+34 916 65 12 80",
    "sg:postcode":"28901",
    "sg:province":"Madrid",
    "wof:name":"Martinez Gomez Alberto",
    "wof:placetype":"venue"
},
  "geometry": {"coordinates":[-3.7328031063,40.3038864136],"type":"Point"}
}