{
  "type": "Feature",
  "properties": {
    "iso:country":"ES",
    "sg:address":"Pase Padre Calatayud, 1",
    "sg:city":"Tafalla",
    "sg:orig_category":"Renovaci\u00d3n Inmobiliaria",
    "sg:phone":"+34 948 75 50 34",
    "sg:postcode":"31300",
    "sg:province":"Navarra",
    "wof:name":"Agrupacion De Entidades Locales Para La Gestion De La Orve Comarca De Tafalla",
    "wof:placetype":"venue"
},
  "geometry": {"coordinates":[-1.6738921404,42.5283508301],"type":"Point"}
}