{
  "type": "Feature",
  "properties": {
    "iso:country":"ES",
    "sg:address":"Calle de Madrigal De Las Altas Torres, 3",
    "sg:city":"Avila",
    "sg:orig_category":"Universidades",
    "sg:phone":"+34 920 35 36 00",
    "sg:postcode":"05003",
    "sg:province":"\u00c1vila",
    "wof:name":"Universidad Salamanca",
    "wof:placetype":"venue"
},
  "geometry": {"coordinates":[-4.7072339058,40.6581344604],"type":"Point"}
}