{
  "type": "Feature",
  "properties": {
    "iso:country":"ES",
    "sg:address":"Calle de Martinez Tornel, 10",
    "sg:city":"San Javier",
    "sg:orig_category":"Sociedades, Compa\u00d1\u00cdas Aseguradoras",
    "sg:phone":"+34 968 33 40 38",
    "sg:postcode":"30730",
    "sg:province":"Murcia",
    "wof:name":"Silvia Sanchez Delgado Inversiones S.l.",
    "wof:placetype":"venue"
},
  "geometry": {"coordinates":[-0.8349909782,37.8050765991],"type":"Point"}
}