{
  "type": "Feature",
  "properties": {
    "iso:country":"ES",
    "sg:address":"Carrer de Balmes, 10",
    "sg:city":"Calella",
    "sg:orig_category":"Grafistas",
    "sg:phone":"+34 937 69 72 86",
    "sg:postcode":"08370",
    "sg:province":"Barcelona",
    "wof:name":"Guri Feliu Carme",
    "wof:placetype":"venue"
},
  "geometry": {"coordinates":[2.6692199707,41.6163406372],"type":"Point"}
}