{
  "type": "Feature",
  "properties": {
    "addr:full":"Calle de Curas (de Los), 13 Casasimarro Cuenca 16239",
    "addr:housenumber":"13",
    "addr:postcode":"16239",
    "addr:street":"Calle De Curas De Los",
    "iso:country":"ES",
    "sg:address":"Calle de Curas (de Los), 13",
    "sg:city":"Casasimarro",
    "sg:orig_category":"Agencias Y Agentes Comerciales, Representantes",
    "sg:phone":"+34 967 48 72 99",
    "sg:postcode":"16239",
    "sg:province":"Cuenca",
    "wof:name":"Representaciones Garzo S.l.",
    "wof:placetype":"venue"
},
  "geometry": {"coordinates":[-2.0386352539,39.3916473389],"type":"Point"}
}