{
  "type": "Feature",
  "properties": {
    "addr:full":"Calle de Lobero, 22 Ejido Almer\u00eda 04700",
    "addr:housenumber":"22 ejido",
    "addr:postcode":"04700",
    "addr:street":"Calle De Lobero;Almeri\u0301A",
    "iso:country":"ES",
    "sg:address":"Calle de Lobero, 22",
    "sg:city":"Ejido",
    "sg:orig_category":"Bisuter\u00cda, Joyer\u00cda, Relojer\u00cda (al Por Menor)",
    "sg:phone":"+34 950 48 26 38",
    "sg:postcode":"04700",
    "sg:province":"Almer\u00eda",
    "wof:name":"Itaca H Y M S.l.l.",
    "wof:placetype":"venue"
},
  "geometry": {"coordinates":[-2.8131260872,36.7743644714],"type":"Point"}
}