{
  "type": "Feature",
  "properties": {
    "addr:full":"Calle de Calvo Sotelo, 40 Tui Pontevedra 36700",
    "addr:housenumber":"40",
    "addr:postcode":"36700",
    "addr:street":"Calle De Calvo Sotelo",
    "iso:country":"ES",
    "sg:address":"Calle de Calvo Sotelo, 40",
    "sg:city":"Tui",
    "sg:orig_category":"Trajes Y Adornos De Boda (confecci\u00d3n, Al Por Menor)",
    "sg:phone":"+34 986 60 04 29",
    "sg:postcode":"36700",
    "sg:province":"Pontevedra",
    "wof:name":"Fernandez Ferreiro Maria Del Pilar",
    "wof:placetype":"venue"
},
  "geometry": {"coordinates":[-8.6446847916,42.0475578308],"type":"Point"}
}