{
  "type": "Feature",
  "properties": {
    "iso:country":"ES",
    "sg:address":"Avda Europa, 109",
    "sg:city":"Mojonera",
    "sg:orig_category":"Cooperativas Agr\u00cdcolas",
    "sg:phone":"+34 950 33 02 57",
    "sg:postcode":"04745",
    "sg:province":"Almer\u00eda",
    "wof:name":"Union De Agricultores Y Ganaderos De Almeria",
    "wof:placetype":"venue"
},
  "geometry": {"coordinates":[-2.6868789196,36.7536697388],"type":"Point"}
}