{
  "type": "Feature",
  "properties": {
    "addr:full":"Carrer de Parellades, 4 Viladecans Barcelona 08840",
    "addr:housenumber":"4",
    "addr:postcode":"08840",
    "addr:street":"Carrer De Parellades",
    "iso:country":"ES",
    "sg:address":"Carrer de Parellades, 4",
    "sg:city":"Viladecans",
    "sg:orig_category":"Comidas Por Encargo, Organizaci\u00d3n De Recepciones",
    "sg:phone":"+34 936 37 75 03",
    "sg:postcode":"08840",
    "sg:province":"Barcelona",
    "wof:name":"Bellido Galvan Andres",
    "wof:placetype":"venue"
},
  "geometry": {"coordinates":[2.0235219002,41.3129425049],"type":"Point"}
}