{
  "type": "Feature",
  "properties": {
    "iso:country":"ES",
    "sg:address":"Av Antoni Gaudi, 18",
    "sg:city":"Mollet Valles",
    "sg:orig_category":"Molduras, Junquillos, Listones Y Molduras Perforadas",
    "sg:phone":"+34 935 93 92 65",
    "sg:postcode":"08100",
    "sg:province":"Barcelona",
    "wof:name":"Perulero Garcia Antonio",
    "wof:placetype":"venue"
},
  "geometry": {"coordinates":[2.2183389664,41.5453300476],"type":"Point"}
}