{
  "type": "Feature",
  "properties": {
    "iso:country":"ES",
    "sg:address":"Sefarad, S/n",
    "sg:city":"Vitoria-gasteiz",
    "sg:orig_category":"Piscinas (establecimientos)",
    "sg:phone":"+34 945 25 23 87",
    "sg:postcode":"01003",
    "sg:province":"\u00c1lava",
    "wof:name":"Club Natacion Urgain",
    "wof:placetype":"venue"
},
  "geometry": {"coordinates":[-2.6622240543,42.8450813293],"type":"Point"}
}