{
  "type": "Feature",
  "properties": {
    "iso:country":"ES",
    "sg:address":"Avda Manoteras, 20",
    "sg:city":"Madrid",
    "sg:orig_category":"Controles De Edificaci\u00d3n (construcci\u00d3n, Seguridad)",
    "sg:phone":"+34 917 43 41 00",
    "sg:postcode":"28050",
    "sg:province":"Madrid",
    "wof:name":"Urazca S.a.",
    "wof:placetype":"venue"
},
  "geometry": {"coordinates":[-3.6691761017,40.4882354736],"type":"Point"}
}