{
  "type": "Feature",
  "properties": {
    "addr:full":"C/ Pont De Sant Jordi, 6 Alcoi Alicante 03803",
    "addr:housenumber":"6",
    "addr:postcode":"03803",
    "addr:street":"C / Pont De Sant Jordi",
    "iso:country":"ES",
    "sg:address":"C/ Pont De Sant Jordi, 6",
    "sg:city":"Alcoi",
    "sg:orig_category":"Inform\u00c1tica: Soportes De Informaci\u00d3n, Suministros & Accesorios",
    "sg:phone":"+34 965 52 51 64",
    "sg:postcode":"03803",
    "sg:province":"Alicante",
    "sg:website":"www.alcoi.com/lom",
    "wof:name":"Equipamientos De Oficina Lom S.l.",
    "wof:placetype":"venue"
},
  "geometry": {"coordinates":[-0.4766710103,38.7018089294],"type":"Point"}
}