{
  "type": "Feature",
  "properties": {
    "iso:country":"ES",
    "sg:address":"Ctra Servicio (de), S/n",
    "sg:city":"Ceuta",
    "sg:orig_category":"Agentes, Concesionarios Y Sucursales De Veh\u00cdculos",
    "sg:phone":"+34 956 52 20 40",
    "sg:postcode":"51001",
    "sg:province":"Ceuta",
    "wof:name":"Distribucion Automocion Y Servicios Anex",
    "wof:placetype":"venue"
},
  "geometry": {"coordinates":[-5.3302302361,35.8947601318],"type":"Point"}
}