{
  "type": "Feature",
  "properties": {
    "addr:full":"Calle de Alfonso Morales, 3 Irun Guip\u00f9zcoa 20303",
    "addr:housenumber":"3",
    "addr:postcode":"20303",
    "addr:street":"Calle De Alfonso Morales;Guipu\u0300Zcoa",
    "iso:country":"ES",
    "sg:address":"Calle de Alfonso Morales, 3",
    "sg:city":"Irun",
    "sg:orig_category":"Mec\u00c1nico Del Autom\u00d3vil",
    "sg:phone":"+34 943 61 29 50",
    "sg:postcode":"20303",
    "sg:province":"Guip\u00f9zcoa",
    "wof:name":"San Sebastian Goyeneche Miguel",
    "wof:placetype":"venue"
},
  "geometry": {"coordinates":[-1.7955340147,43.3384857178],"type":"Point"}
}