{
  "type": "Feature",
  "properties": {
    "iso:country":"ES",
    "sg:address":"Calle de Jeronimo Santa Fe, 22",
    "sg:city":"San Jose",
    "sg:orig_category":"Ropa Para Se\u00d1oras (al Por Menor)",
    "sg:phone":"+34 968 46 02 83",
    "sg:postcode":"30800",
    "sg:province":"Murcia",
    "wof:name":"Morales Abellan Miguel",
    "wof:placetype":"venue"
},
  "geometry": {"coordinates":[-1.6905640364,37.680557251],"type":"Point"}
}