{
  "type": "Feature",
  "properties": {
    "iso:country":"ES",
    "sg:address":"Avda Reina Victoria, 17",
    "sg:city":"Madrid",
    "sg:orig_category":"Artes Gr\u00c1ficas, Artes Pl\u00c1sticas (curso)",
    "sg:phone":"+34 915 34 04 21",
    "sg:postcode":"28003",
    "sg:province":"Madrid",
    "wof:name":"Navarro Y Piscaer S.l.",
    "wof:placetype":"venue"
},
  "geometry": {"coordinates":[-3.7074179649,40.4468078613],"type":"Point"}
}