{
  "type": "Feature",
  "properties": {
    "addr:full":"Carrer de Balmes, 64 Barcelona Barcelona 08007",
    "addr:housenumber":"64",
    "addr:postcode":"08007",
    "addr:street":"Carrer De Balmes",
    "iso:country":"ES",
    "sg:address":"Carrer de Balmes, 64",
    "sg:city":"Barcelona",
    "sg:orig_category":"Administradores De Bienes Y Delegados De Comunidades De Propietarios",
    "sg:phone":"+34 934 88 32 48",
    "sg:postcode":"08007",
    "sg:province":"Barcelona",
    "wof:name":"Pujol Ferrusola Jordi",
    "wof:placetype":"venue"
},
  "geometry": {"coordinates":[2.1621549129,41.3898620605],"type":"Point"}
}