{
  "type": "Feature",
  "properties": {
    "addr:full":"Calle de Nu\u00d1ez De Balboa, 90 Madrid Madrid 28006",
    "addr:housenumber":"90",
    "addr:postcode":"madrid;28006",
    "addr:street":"Calle De Nun\u0303Ez De Balboa",
    "iso:country":"ES",
    "sg:address":"Calle de Nu\u00d1ez De Balboa, 90",
    "sg:city":"Madrid",
    "sg:orig_category":"Centros Empresariales",
    "sg:phone":"+34 915 77 55 89",
    "sg:postcode":"28006",
    "sg:province":"Madrid",
    "sg:website":"www.ahe.es",
    "wof:name":"Asociacion Hipotecaria Espa\u00f1ola",
    "wof:placetype":"venue"
},
  "geometry": {"coordinates":[-3.6821000576,40.4334564209],"type":"Point"}
}