{
  "type": "Feature",
  "properties": {
    "addr:full":"Calle de Virgen De Los Dolores, 33 Galvez Toledo 45164",
    "addr:housenumber":"33",
    "addr:postcode":"45164",
    "addr:street":"Calle De Virgen De Los Dolores",
    "iso:country":"ES",
    "sg:address":"Calle de Virgen De Los Dolores, 33",
    "sg:city":"Galvez",
    "sg:orig_category":"Agencias Y Agentes Comerciales, Representantes",
    "sg:phone":"+34 925 40 03 75",
    "sg:postcode":"45164",
    "sg:province":"Toledo",
    "wof:name":"Lopez Rodriguez Jesus Javier",
    "wof:placetype":"venue"
},
  "geometry": {"coordinates":[-4.2750191689,39.6998214722],"type":"Point"}
}