{
  "type": "Feature",
  "properties": {
    "addr:full":"Colom, S/n Can Parellada Barcelona 08228",
    "addr:housenumber":"s",
    "addr:postcode":"08228",
    "addr:street":"Colom;/ N",
    "iso:country":"ES",
    "sg:address":"Colom, S/n",
    "sg:city":"Can Parellada",
    "sg:orig_category":"Productos Qu\u00cdmicos (fabricaci\u00d3n, Al Por Mayor)",
    "sg:phone":"+34 937 36 39 40",
    "sg:postcode":"08228",
    "sg:province":"Barcelona",
    "wof:name":"Disproquima S.a.",
    "wof:placetype":"venue"
},
  "geometry": {"coordinates":[2.0362648964,41.5310096741],"type":"Point"}
}