{
  "type": "Feature",
  "properties": {
    "addr:full":"Centro Internacional, 86 Torrox-costa M\u00e1laga 29793",
    "addr:postcode":"29793",
    "addr:street":"Ma\u0301Laga",
    "iso:country":"ES",
    "sg:address":"Centro Internacional, 86",
    "sg:city":"Torrox-costa",
    "sg:orig_category":"Administradores De Bienes Y Delegados De Comunidades De Propietarios",
    "sg:phone":"+34 952 53 22 84",
    "sg:postcode":"29793",
    "sg:province":"M\u00e1laga",
    "wof:name":"Manuel Castro Consulting S.l.",
    "wof:placetype":"venue"
},
  "geometry": {"coordinates":[-3.9599940777,36.7289161682],"type":"Point"}
}