{
  "type": "Feature",
  "properties": {
    "addr:full":"Carr Muralla, 15 Castello D'empuries Girona 17486",
    "addr:housenumber":"15",
    "addr:postcode":"17486",
    "addr:street":"Carr Muralla",
    "iso:country":"ES",
    "sg:address":"Carr Muralla, 15",
    "sg:city":"Castello D'empuries",
    "sg:orig_category":"Cajas De Ahorro",
    "sg:phone":"+34 972 25 00 03",
    "sg:postcode":"17486",
    "sg:province":"Girona",
    "wof:name":"Caixa De Girona",
    "wof:placetype":"venue"
},
  "geometry": {"coordinates":[3.117882967,42.1298103333],"type":"Point"}
}