{
  "type": "Feature",
  "properties": {
    "addr:full":"Calle de Gabriel Garcia Marquez (de), 22 Alcobendas Madrid 28100",
    "addr:housenumber":"22",
    "addr:postcode":"28100",
    "addr:street":"Calle De Gabriel Garcia Marquez De",
    "iso:country":"ES",
    "sg:address":"Calle de Gabriel Garcia Marquez (de), 22",
    "sg:city":"Alcobendas",
    "sg:orig_category":"Delegados, Agentes De Tr\u00c1nsito, Auxiliares De Transporte Internacional",
    "sg:phone":"+34 916 61 75 44",
    "sg:postcode":"28100",
    "sg:province":"Madrid",
    "sg:website":"www.sanfiz.net",
    "wof:name":"Sanfiz S.l.",
    "wof:placetype":"venue"
},
  "geometry": {"coordinates":[-3.6558160782,40.5404624939],"type":"Point"}
}