{
  "type": "Feature",
  "properties": {
    "iso:country":"ES",
    "sg:address":"Avda Constitucion Espa\u00d1ola, 22",
    "sg:city":"Burgos",
    "sg:orig_category":"Asesor\u00cda Sobre Comunicaci\u00d3n De Empresas",
    "sg:phone":"+34 947 24 00 18",
    "sg:postcode":"09007",
    "sg:province":"Burgos",
    "wof:name":"Inclan Asesores S.l.",
    "wof:placetype":"venue"
},
  "geometry": {"coordinates":[-3.6708619595,42.3476676941],"type":"Point"}
}