{
  "type": "Feature",
  "properties": {
    "iso:country":"ES",
    "sg:address":"Ctra Huelva S Juan, Km. 0078,0",
    "sg:city":"S. Juan Puerto",
    "sg:orig_category":"Cooperativas Agr\u00cdcolas",
    "sg:phone":"+34 959 36 75 12",
    "sg:postcode":"21610",
    "sg:province":"Huelva",
    "wof:name":"Sociedad Cooperativa Andaluza Valle Ancho",
    "wof:placetype":"venue"
},
  "geometry": {"coordinates":[-6.8440890312,37.3149261475],"type":"Point"}
}