{
  "type": "Feature",
  "properties": {
    "iso:country":"ES",
    "sg:address":"Calle de Magdalena (de La), 38",
    "sg:city":"Getafe",
    "sg:orig_category":"Aceites Y Grasas Alimentarias (fabricaci\u00d3n, Al Por Mayor)",
    "sg:phone":"+34 916 81 36 04",
    "sg:postcode":"28901",
    "sg:province":"Madrid",
    "wof:name":"Ediciones Magadalena 2002 S.l.",
    "wof:placetype":"venue"
},
  "geometry": {"coordinates":[-3.729831934,40.3042106628],"type":"Point"}
}