{
  "type": "Feature",
  "properties": {
    "addr:full":"Pg Agusti Font, 16 Lloret Mar Girona 17310",
    "addr:housenumber":"16",
    "addr:postcode":"17310",
    "addr:street":"Pg Agusti Font",
    "iso:country":"ES",
    "sg:address":"Pg Agusti Font, 16",
    "sg:city":"Lloret Mar",
    "sg:orig_category":"Bancos",
    "sg:phone":"+34 972 36 13 26",
    "sg:postcode":"17310",
    "sg:province":"Girona",
    "sg:website":"www.bancosabadell.com",
    "wof:name":"Banc Sabadell S.a.",
    "wof:placetype":"venue"
},
  "geometry": {"coordinates":[2.8460900784,41.6979293823],"type":"Point"}
}