{
  "type": "Feature",
  "properties": {
    "addr:full":"Calle de San Miguel, 5 Aguilar Campoo Palencia 34800",
    "addr:housenumber":"5",
    "addr:postcode":"34800",
    "addr:street":"Calle De San Miguel",
    "iso:country":"ES",
    "sg:address":"Calle de San Miguel, 5",
    "sg:city":"Aguilar Campoo",
    "sg:orig_category":"Ropa Para Se\u00d1oras Y Caballeros (al Por Menor)",
    "sg:phone":"+34 979 12 34 53",
    "sg:postcode":"34800",
    "sg:province":"Palencia",
    "wof:name":"Las Antillas S.a.",
    "wof:placetype":"venue"
},
  "geometry": {"coordinates":[-4.2634310722,42.7933616638],"type":"Point"}
}