{
  "type": "Feature",
  "properties": {
    "addr:full":"Calle de Tinte, 22 Albacete Albacete 02002",
    "addr:housenumber":"22",
    "addr:postcode":"02002",
    "addr:street":"Calle De Tinte",
    "iso:country":"ES",
    "sg:address":"Calle de Tinte, 22",
    "sg:city":"Albacete",
    "sg:orig_category":"Centros De Adelgazamiento Y De Est\u00c9tica",
    "sg:phone":"+34 967 52 45 94",
    "sg:postcode":"02002",
    "sg:province":"Albacete",
    "wof:name":"Moragon Mesas Milagros",
    "wof:placetype":"venue"
},
  "geometry": {"coordinates":[-1.8553990126,38.9925994873],"type":"Point"}
}