{
  "type": "Feature",
  "properties": {
    "iso:country":"ES",
    "sg:address":"Calle de Rufino Gonzalez, 15",
    "sg:city":"Madrid",
    "sg:orig_category":"Radiocomunicaciones, Telefon\u00cda M\u00d3vil, Radiomensajer\u00cda: Servicios, Comercializaci\u00d3n",
    "sg:phone":"+34 913 77 23 52",
    "sg:postcode":"28037",
    "sg:province":"Madrid",
    "wof:name":"Asesores Tecnicos Comerciales De Comunicaciones S.l.",
    "wof:placetype":"venue"
},
  "geometry": {"coordinates":[-3.6264681816,40.4377212524],"type":"Point"}
}