{
  "type": "Feature",
  "properties": {
    "addr:full":"Carr Doctor Servera, Del, 34 Son Servera Islas Baleares 07550",
    "addr:housenumber":"34",
    "addr:postcode":"07550",
    "addr:street":"Carr Doctor Servera Del",
    "iso:country":"ES",
    "sg:address":"Carr Doctor Servera, Del, 34",
    "sg:city":"Son Servera",
    "sg:orig_category":"Diarios, Revistas Y Boletines (distribuidores)",
    "sg:phone":"+34 971 56 72 53",
    "sg:postcode":"07550",
    "sg:province":"Islas Baleares",
    "sg:website":"www.calamillor.net/calamillor7",
    "wof:name":"Turismo 2007 S.l.",
    "wof:placetype":"venue"
},
  "geometry": {"coordinates":[3.3585379124,39.619884491],"type":"Point"}
}