{
  "type": "Feature",
  "properties": {
    "iso:country":"ES",
    "sg:address":"Casa Parado Nou, S/n",
    "sg:city":"Lli\u00e7a Amunt",
    "sg:orig_category":"Invernaderos Y Semilleros",
    "sg:phone":"+34 938 41 91 59",
    "sg:postcode":"08186",
    "sg:province":"Barcelona",
    "wof:name":"Muichol's Garden S.l.",
    "wof:placetype":"venue"
},
  "geometry": {"coordinates":[2.2382690907,41.612449646],"type":"Point"}
}