{
  "type": "Feature",
  "properties": {
    "addr:full":"Urb. El Se\u00f1orio, 4 Gerindote Toledo 45518",
    "addr:housenumber":"4",
    "addr:postcode":"45518",
    "addr:street":"Sen\u0303Orio",
    "iso:country":"ES",
    "sg:address":"Urb. El Se\u00f1orio, 4",
    "sg:city":"Gerindote",
    "sg:orig_category":"Carnes De Carnicer\u00cda (al Por Mayor)",
    "sg:phone":"+34 925 76 22 45",
    "sg:postcode":"45518",
    "sg:province":"Toledo",
    "wof:name":"Industrias Carnicas Hermanos Gomez Herraiz S.l.",
    "wof:placetype":"venue"
},
  "geometry": {"coordinates":[-4.3021659851,39.9683151245],"type":"Point"}
}