{
  "type": "Feature",
  "properties": {
    "iso:country":"ES",
    "sg:address":"Avda Principes De Espa\u00d1a, 125",
    "sg:city":"Rota",
    "sg:orig_category":"Guarder\u00cdas",
    "sg:phone":"+34 956 81 30 95",
    "sg:postcode":"11520",
    "sg:province":"C\u00e1diz",
    "wof:name":"Membrive Lorente Remedios",
    "wof:placetype":"venue"
},
  "geometry": {"coordinates":[-6.3860797882,36.6345825195],"type":"Point"}
}