{
  "type": "Feature",
  "properties": {
    "iso:country":"ES",
    "sg:address":"Ctra Sta Isabel, Km. 0018,0",
    "sg:city":"S. Mateo Gallego",
    "sg:orig_category":"Paletas",
    "sg:phone":"+34 976 68 30 69",
    "sg:postcode":"50840",
    "sg:province":"Zaragoza",
    "wof:name":"Enguita S.l",
    "wof:placetype":"venue"
},
  "geometry": {"coordinates":[-0.7679479718,41.8305587769],"type":"Point"}
}