{
  "type": "Feature",
  "properties": {
    "iso:country":"ES",
    "sg:address":"Calle de Segovia, 4",
    "sg:city":"Navalmoral Mata",
    "sg:orig_category":"Panader\u00cdas, Panader\u00cdas",
    "sg:phone":"+34 927 53 22 04",
    "sg:postcode":"10300",
    "sg:province":"C\u00e1ceres",
    "wof:name":"Monje Alvarez Jesus",
    "wof:placetype":"venue"
},
  "geometry": {"coordinates":[-5.534509182,39.8933563232],"type":"Point"}
}