{
  "type": "Feature",
  "properties": {
    "iso:country":"ES",
    "sg:address":"Calle de Iglesia, 8",
    "sg:city":"Cazalla Sierra",
    "sg:orig_category":"Asilos De Ancianos. Centros Privados",
    "sg:phone":"+34 954 88 40 92",
    "sg:postcode":"41370",
    "sg:province":"Sevilla",
    "wof:name":"Diputacion Provincial De Sevilla",
    "wof:placetype":"venue"
},
  "geometry": {"coordinates":[-5.7578730583,37.9288673401],"type":"Point"}
}