{
  "type": "Feature",
  "properties": {
    "iso:country":"ES",
    "sg:address":"Calle de Garcia Sanchez, 24",
    "sg:city":"Zaragoza",
    "sg:orig_category":"Confecci\u00d3n (fabricaci\u00d3n, Al Por Mayor)",
    "sg:phone":"+34 976 55 81 59",
    "sg:postcode":"50005",
    "sg:province":"Zaragoza",
    "wof:name":"Segura Marco Jesus",
    "wof:placetype":"venue"
},
  "geometry": {"coordinates":[-0.8992390037,41.6474342346],"type":"Point"}
}