{
  "type": "Feature",
  "properties": {
    "iso:country":"ES",
    "sg:address":"Carrer de Sant Benet, 43",
    "sg:city":"Mataro",
    "sg:orig_category":"Abogados",
    "sg:phone":"+34 937 58 63 43",
    "sg:postcode":"08302",
    "sg:province":"Barcelona",
    "wof:name":"Roig Fornells Africa",
    "wof:placetype":"venue"
},
  "geometry": {"coordinates":[2.4399020672,41.538105011],"type":"Point"}
}