{
  "type": "Feature",
  "properties": {
    "addr:full":"Calle de Luna (la), 5 Puebla Cazalla Sevilla 41540",
    "addr:housenumber":"5",
    "addr:postcode":"41540",
    "addr:street":"Calle De Luna La",
    "iso:country":"ES",
    "sg:address":"Calle de Luna (la), 5",
    "sg:city":"Puebla Cazalla",
    "sg:orig_category":"Bebidas",
    "sg:phone":"+34 954 84 75 63",
    "sg:postcode":"41540",
    "sg:province":"Sevilla",
    "wof:name":"Bebidas Miguel Macho S.l.",
    "wof:placetype":"venue"
},
  "geometry": {"coordinates":[-5.3127951622,37.2219772339],"type":"Point"}
}