{
  "type": "Feature",
  "properties": {
    "addr:full":"Calle de Doctor Mara\u00d1on, 3 S. Pedro Pinatar Murcia 30740",
    "addr:housenumber":"3",
    "addr:postcode":"30740",
    "addr:street":"Calle De Doctor Maran\u0303On",
    "iso:country":"ES",
    "sg:address":"Calle de Doctor Mara\u00d1on, 3",
    "sg:city":"S. Pedro Pinatar",
    "sg:orig_category":"Material Y Suministros Para Peluquer\u00cda",
    "sg:phone":"+34 968 18 18 49",
    "sg:postcode":"30740",
    "sg:province":"Murcia",
    "wof:name":"Espinosa Galera Angel",
    "wof:placetype":"venue"
},
  "geometry": {"coordinates":[-0.7932360172,37.8323631287],"type":"Point"}
}