{
  "type": "Feature",
  "properties": {
    "iso:country":"ES",
    "sg:address":"Calle de La Coru\u00d1a, 12",
    "sg:city":"Madrid",
    "sg:orig_category":"Impresiones Sobre Tela",
    "sg:phone":"+34 915 79 28 20",
    "sg:postcode":"28020",
    "sg:province":"Madrid",
    "wof:name":"Raisa Futury S.l.",
    "wof:placetype":"venue"
},
  "geometry": {"coordinates":[-3.7008590698,40.4552574158],"type":"Point"}
}