{
  "type": "Feature",
  "properties": {
    "iso:country":"ES",
    "sg:address":"Erdi Kalea, 27",
    "sg:city":"Azpeitia",
    "sg:orig_category":"Molduras, Junquillos, Listones Y Molduras Perforadas",
    "sg:phone":"+34 943 81 60 55",
    "sg:postcode":"20730",
    "sg:province":"Guip\u00f9zcoa",
    "wof:name":"Sistelcom-telemensaje S.a.",
    "wof:placetype":"venue"
},
  "geometry": {"coordinates":[-2.264220953,43.1854782104],"type":"Point"}
}