{
  "type": "Feature",
  "properties": {
    "iso:country":"ES",
    "sg:address":"Calle de Jorge Juan, 88",
    "sg:city":"Madrid",
    "sg:orig_category":"Estancos",
    "sg:phone":"+34 915 76 35 58",
    "sg:postcode":"28009",
    "sg:province":"Madrid",
    "wof:name":"Antiguedad Jimenez Rosa Maria",
    "wof:placetype":"venue"
},
  "geometry": {"coordinates":[-3.6743872166,40.4233016968],"type":"Point"}
}