{
  "type": "Feature",
  "properties": {
    "iso:country":"ES",
    "sg:address":"Calle de Valle Inclan, 6",
    "sg:city":"Roquetas Mar",
    "sg:classifiers":[
        {
            "category":"Autos & Motor Vehicles",
            "subcategory":"Automobile Sales",
            "type":"Retail Goods"
        }
    ],
    "sg:phone":"+34 950 32 20 57",
    "sg:postcode":"04740",
    "sg:province":"Almer\u00eda",
    "wof:name":"Conde Del Cuerpo Manuel",
    "wof:placetype":"venue"
},
  "geometry": {"coordinates":[-2.6135950089,36.7640419006],"type":"Point"}
}