{
  "type": "Feature",
  "properties": {
    "addr:full":"Calle de Reis Catolics, 114 Alzira Valencia 46600",
    "addr:housenumber":"114",
    "addr:postcode":"46600",
    "addr:street":"Calle De Reis Catolics",
    "iso:country":"ES",
    "sg:address":"Calle de Reis Catolics, 114",
    "sg:city":"Alzira",
    "sg:orig_category":"Vinos Y Licores (venta Al Por Menor)",
    "sg:phone":"+34 962 40 54 03",
    "sg:postcode":"46600",
    "sg:province":"Valencia",
    "sg:website":"www.larugla.com",
    "wof:name":"La Rugla Cb",
    "wof:placetype":"venue"
},
  "geometry": {"coordinates":[-0.4378489852,39.1517295837],"type":"Point"}
}