{
  "type": "Feature",
  "properties": {
    "addr:full":"Vistalegre, S/n Mancha Real Ja\u00e9n 23100",
    "addr:housenumber":"s / n",
    "addr:postcode":"23100",
    "addr:street":"Vistalegre",
    "iso:country":"ES",
    "sg:address":"Vistalegre, S/n",
    "sg:city":"Mancha Real",
    "sg:orig_category":"Delegados, Agentes De Tr\u00c1nsito, Auxiliares De Transporte Internacional",
    "sg:phone":"+34 953 35 09 93",
    "sg:postcode":"23100",
    "sg:province":"Ja\u00e9n",
    "wof:name":"Cobos Romero Santiago",
    "wof:placetype":"venue"
},
  "geometry": {"coordinates":[-3.6168620586,37.7866783142],"type":"Point"}
}