{
  "type": "Feature",
  "properties": {
    "addr:full":"Calle de Postigos, S/n Priego Cordoba C\u00f3rdoba 14800",
    "addr:housenumber":"s",
    "addr:postcode":"14800",
    "addr:street":"Calle De Postigos;/ N Priego Cordoba Co\u0301Rdoba",
    "iso:country":"ES",
    "sg:address":"Calle de Postigos, S/n",
    "sg:city":"Priego Cordoba",
    "sg:orig_category":"Inmobiliaria (agencias)",
    "sg:phone":"+34 957 54 28 35",
    "sg:postcode":"14800",
    "sg:province":"C\u00f3rdoba",
    "wof:name":"Moral Jimenez Juan",
    "wof:placetype":"venue"
},
  "geometry": {"coordinates":[-4.1955041885,37.4387779236],"type":"Point"}
}