{
  "type": "Feature",
  "properties": {
    "iso:country":"ES",
    "sg:address":"Extramuros, S/n",
    "sg:city":"Almodovar",
    "sg:orig_category":"Asociaciones Y Clubs Deportivos",
    "sg:phone":"+34 957 33 83 40",
    "sg:postcode":"14720",
    "sg:province":"C\u00f3rdoba",
    "wof:name":"Club Nautico De Cordoba",
    "wof:placetype":"venue"
},
  "geometry": {"coordinates":[-5.0198187828,37.8093833923],"type":"Point"}
}