{
  "type": "Feature",
  "properties": {
    "addr:full":"Baltasar Garzon, 91 Torres Ja\u00e9n 23540",
    "addr:housenumber":"91",
    "addr:postcode":"23540",
    "addr:street":"Baltasar Garzon;Jae\u0301N",
    "iso:country":"ES",
    "sg:address":"Baltasar Garzon, 91",
    "sg:city":"Torres",
    "sg:orig_category":"Cajas Para Embalar",
    "sg:phone":"+34 953 36 30 82",
    "sg:postcode":"23540",
    "sg:province":"Ja\u00e9n",
    "wof:name":"Caja Rural De Jaen",
    "wof:placetype":"venue"
},
  "geometry": {"coordinates":[-3.5059790611,37.7840118408],"type":"Point"}
}