{
  "type": "Feature",
  "properties": {
    "iso:country":"ES",
    "sg:address":"Ctra Santa Creu De Calafell, 97",
    "sg:city":"S. Boi Llobregat",
    "sg:orig_category":"Fabricaci\u00d3n, Importaci\u00d3n De L\u00c1mparas Y Bombillas",
    "sg:phone":"+34 936 40 74 00",
    "sg:postcode":"08830",
    "sg:province":"Barcelona",
    "sg:website":"www.faladesa.com",
    "wof:name":"Fabrica De Lamparas Y Elementos Decorativos S. A.",
    "wof:placetype":"venue"
},
  "geometry": {"coordinates":[2.0333759785,41.3252868652],"type":"Point"}
}