{
  "type": "Feature",
  "properties": {
    "iso:country":"ES",
    "sg:address":"Calle de Tentudia, S/n",
    "sg:city":"Monesterio",
    "sg:orig_category":"Empresas De Electricidad En General",
    "sg:phone":"+34 924 51 64 39",
    "sg:postcode":"06260",
    "sg:province":"Badajoz",
    "wof:name":"Electrica Monesterio S.a.",
    "wof:placetype":"venue"
},
  "geometry": {"coordinates":[-6.2730398178,38.0855369568],"type":"Point"}
}