{
  "type": "Feature",
  "properties": {
    "iso:country":"ES",
    "sg:address":"Rua Lodeiro, 4",
    "sg:city":"Viveiro",
    "sg:orig_category":"M\u00c9dicos: Psiquiatr\u00cda",
    "sg:phone":"+34 982 55 07 04",
    "sg:postcode":"27850",
    "sg:province":"Lugo",
    "wof:name":"Perez Llamas Tomas Vicente",
    "wof:placetype":"venue"
},
  "geometry": {"coordinates":[-7.5928001404,43.6678848267],"type":"Point"}
}