{
  "type": "Feature",
  "properties": {
    "addr:full":"Calle de Extramuros, 11 Higuera Calatrava Ja\u00e9n 23611",
    "addr:housenumber":"11",
    "addr:postcode":"23611",
    "addr:street":"Calle De Extramuros",
    "iso:country":"ES",
    "sg:address":"Calle de Extramuros, 11",
    "sg:city":"Higuera Calatrava",
    "sg:orig_category":"Confecci\u00d3n (fabricaci\u00d3n, Al Por Mayor)",
    "sg:phone":"+34 953 52 91 50",
    "sg:postcode":"23611",
    "sg:province":"Ja\u00e9n",
    "wof:name":"Vera Lopez Gavino",
    "wof:placetype":"venue"
},
  "geometry": {"coordinates":[-4.1612701416,37.7979354858],"type":"Point"}
}