{
  "type": "Feature",
  "properties": {
    "iso:country":"ES",
    "sg:address":"Calle de Gaztainondo Kalea, 1",
    "sg:city":"Irun",
    "sg:orig_category":"Informaci\u00d3n Financiera Y Comercial",
    "sg:phone":"+34 943 61 33 56",
    "sg:postcode":"20301",
    "sg:province":"Guip\u00f9zcoa",
    "wof:name":"Garo Asesoria Consultoria Y Auditoria S.l.",
    "wof:placetype":"venue"
},
  "geometry": {"coordinates":[-1.8002040386,43.3405380249],"type":"Point"}
}