{
  "type": "Feature",
  "properties": {
    "iso:country":"ES",
    "sg:address":"Picasso, 5",
    "sg:city":"Prado Rey",
    "sg:orig_category":"Inmobiliaria (agencias)",
    "sg:phone":"+34 915 18 96 73",
    "sg:postcode":"28223",
    "sg:province":"Madrid",
    "wof:name":"A.g.a. Sport,s.l.",
    "wof:placetype":"venue"
},
  "geometry": {"coordinates":[-3.7003455162,40.4166908264],"type":"Point"}
}