{
  "type": "Feature",
  "properties": {
    "addr:full":"J. Espada, 15 Cartagena Murcia 30204",
    "addr:housenumber":"15",
    "addr:postcode":"30204",
    "addr:street":"Espada",
    "iso:country":"ES",
    "sg:address":"J. Espada, 15",
    "sg:city":"Cartagena",
    "sg:orig_category":"Venta Al Preg\u00d3n",
    "sg:phone":"+34 968 50 82 26",
    "sg:postcode":"30204",
    "sg:province":"Murcia",
    "wof:name":"Lobato Chuecos Diego",
    "wof:placetype":"venue"
},
  "geometry": {"coordinates":[-0.9877589941,37.6067504883],"type":"Point"}
}