{
  "type": "Feature",
  "properties": {
    "iso:country":"ES",
    "sg:address":"Calle de Beato Juan Grande, 9",
    "sg:city":"Jerez De La Frontera",
    "sg:orig_category":"Inmobiliaria (agencias)",
    "sg:phone":"+34 956 34 56 70",
    "sg:postcode":"11403",
    "sg:province":"C\u00e1diz",
    "wof:name":"Landsur Gestion Inmobiliaria S.l.",
    "wof:placetype":"venue"
},
  "geometry": {"coordinates":[-6.1377034187,36.6881027222],"type":"Point"}
}