{
  "type": "Feature",
  "properties": {
    "iso:country":"ES",
    "sg:address":"Pda Castell, 43",
    "sg:city":"Figueres",
    "sg:orig_category":"Ense\u00d1anza, Formaci\u00d3n Profesional: Aprendizaje",
    "sg:phone":"+34 972 51 30 97",
    "sg:postcode":"17600",
    "sg:province":"Girona",
    "wof:name":"Vila Pujol Maria Teresa",
    "wof:placetype":"venue"
},
  "geometry": {"coordinates":[2.9588079453,42.2680969238],"type":"Point"}
}