{
  "type": "Feature",
  "properties": {
    "iso:country":"ES",
    "sg:address":"Calle de Padre Camara, 1",
    "sg:city":"Salamanca",
    "sg:orig_category":"Internados & Ense\u00d1anza Privada",
    "sg:phone":"+34 923 28 24 31",
    "sg:postcode":"37004",
    "sg:province":"Salamanca",
    "wof:name":"Colegio Salesiano Maria Auxiliadora",
    "wof:placetype":"venue"
},
  "geometry": {"coordinates":[-5.6582250595,40.9703826904],"type":"Point"}
}