{
  "type": "Feature",
  "properties": {
    "addr:full":"Carrer de Climent Humet, 18 Sentmenat Barcelona 08181",
    "addr:housenumber":"18",
    "addr:postcode":"08181",
    "addr:street":"Carrer De Climent Humet",
    "iso:country":"ES",
    "sg:address":"Carrer de Climent Humet, 18",
    "sg:city":"Sentmenat",
    "sg:orig_category":"Institutos De Belleza",
    "sg:phone":"+34 937 15 16 25",
    "sg:postcode":"08181",
    "sg:province":"Barcelona",
    "wof:name":"Lop Segarra Monica",
    "wof:placetype":"venue"
},
  "geometry": {"coordinates":[2.1361289024,41.6112937927],"type":"Point"}
}