{
  "type": "Feature",
  "properties": {
    "iso:country":"ES",
    "sg:address":"Calle de Toro, 66",
    "sg:city":"Salamanca",
    "sg:orig_category":"Mercer\u00cda, Lencer\u00cda (al Por Menor)",
    "sg:phone":"+34 923 21 43 25",
    "sg:postcode":"37002",
    "sg:province":"Salamanca",
    "wof:name":"Criado Hernandez Teofila",
    "wof:placetype":"venue"
},
  "geometry": {"coordinates":[-5.6612110138,40.9676628113],"type":"Point"}
}