{
  "type": "Feature",
  "properties": {
    "iso:country":"ES",
    "sg:address":"Calle de Guzman, 1",
    "sg:city":"Almeria",
    "sg:orig_category":"Arquitectos",
    "sg:phone":"+34 950 25 01 00",
    "sg:postcode":"04001",
    "sg:province":"Almer\u00eda",
    "wof:name":"Martinez Leiva Cristobal",
    "wof:placetype":"venue"
},
  "geometry": {"coordinates":[-2.4643139839,36.8384590149],"type":"Point"}
}