{
  "type": "Feature",
  "properties": {
    "iso:country":"ES",
    "sg:address":"Carr Castella, 24",
    "sg:city":"Eivissa",
    "sg:orig_category":"Electricidad, Electr\u00d3nica: Material Y Suministros (al Por Mayor)",
    "sg:phone":"+34 971 30 27 48",
    "sg:postcode":"07800",
    "sg:province":"Islas Baleares",
    "wof:name":"Garcia Cebrian Maria Pilar",
    "wof:placetype":"venue"
},
  "geometry": {"coordinates":[1.4276109934,38.9096870422],"type":"Point"}
}