{
  "type": "Feature",
  "properties": {
    "iso:country":"ES",
    "sg:address":"Avda Paz (de La) (completa), 3",
    "sg:city":"Moraira",
    "sg:orig_category":"Inmobiliaria (agencias)",
    "sg:phone":"+34 966 49 23 33",
    "sg:postcode":"03724",
    "sg:province":"Alicante",
    "wof:name":"Grupo Moraira I S.l.",
    "wof:placetype":"venue"
},
  "geometry": {"coordinates":[0.1258890033,38.6994819641],"type":"Point"}
}