{
  "type": "Feature",
  "properties": {
    "addr:full":"Calle de Juan Ramon Jimenez, 5 Moguer Huelva 21800",
    "addr:housenumber":"5",
    "addr:postcode":"21800",
    "addr:street":"Calle De Juan Ramon Jimenez",
    "iso:country":"ES",
    "sg:address":"Calle de Juan Ramon Jimenez, 5",
    "sg:city":"Moguer",
    "sg:orig_category":"Alquiler De V\u00cddeo",
    "sg:phone":"+34 959 37 14 68",
    "sg:postcode":"21800",
    "sg:province":"Huelva",
    "wof:name":"Calero Zambrano Antonio",
    "wof:placetype":"venue"
},
  "geometry": {"coordinates":[-6.8374729156,37.2761726379],"type":"Point"}
}