{
  "type": "Feature",
  "properties": {
    "iso:country":"ES",
    "sg:address":"Rua Santo Domingo, 60",
    "sg:city":"Ourense",
    "sg:orig_category":"Bisuter\u00cda, Joyer\u00cda, Relojer\u00cda (al Por Menor)",
    "sg:phone":"+34 988 23 37 78",
    "sg:postcode":"32003",
    "sg:province":"Ourense",
    "sg:website":"joyeriasuyza.com",
    "wof:name":"Pato Garabatos S.l.",
    "wof:placetype":"venue"
},
  "geometry": {"coordinates":[-7.8628320694,42.3399772644],"type":"Point"}
}