{
  "type": "Feature",
  "properties": {
    "iso:country":"ES",
    "sg:address":"C/ Creu Del Sud, 1",
    "sg:city":"Badia Blava",
    "sg:orig_category":"Bazares, Art\u00cdculos De Limpieza Y De Cocina (al Por Menor)",
    "sg:phone":"+34 971 74 17 13",
    "sg:postcode":"07609",
    "sg:province":"Islas Baleares",
    "wof:name":"Sanchez Cervantes Carmen",
    "wof:placetype":"venue"
},
  "geometry": {"coordinates":[2.7505860329,39.4544029236],"type":"Point"}
}