{
  "type": "Feature",
  "properties": {
    "iso:country":"ES",
    "sg:address":"Plaz San Jeronimo Hermosilla, 8",
    "sg:city":"Santo Domingo De La Calzada",
    "sg:orig_category":"Molduras, Junquillos, Listones Y Molduras Perforadas",
    "sg:phone":"+34 941 34 03 98",
    "sg:postcode":"26250",
    "sg:province":"La Rioja",
    "wof:name":"Herrera Vitoria Domingo",
    "wof:placetype":"venue"
},
  "geometry": {"coordinates":[-2.9539759159,42.4381065369],"type":"Point"}
}