{
  "type": "Feature",
  "properties": {
    "addr:full":"Avda Pumarin De, 9 Oviedo Asturias 33001",
    "addr:housenumber":"9",
    "addr:postcode":"33001",
    "addr:street":"Avda Pumarin De",
    "iso:country":"ES",
    "sg:address":"Avda Pumarin De, 9",
    "sg:city":"Oviedo",
    "sg:orig_category":"Asesor\u00cda Sobre Comunicaci\u00d3n De Empresas",
    "sg:phone":"+34 985 11 52 73",
    "sg:postcode":"33001",
    "sg:province":"Asturias",
    "wof:name":"Alvarez Fernandez Lucia Isabel",
    "wof:placetype":"venue"
},
  "geometry": {"coordinates":[-5.8457593918,43.3669471741],"type":"Point"}
}