{
  "type": "Feature",
  "properties": {
    "iso:country":"ES",
    "sg:address":"Av Valencia, 14",
    "sg:city":"Molins Rei",
    "sg:orig_category":"Organizaciones Internacionales",
    "sg:phone":"+34 936 68 33 50",
    "sg:postcode":"08750",
    "sg:province":"Barcelona",
    "sg:website":"www.losemigrantes.org",
    "wof:name":"Feaer",
    "wof:placetype":"venue"
},
  "geometry": {"coordinates":[2.0186240673,41.4100036621],"type":"Point"}
}