{
  "type": "Feature",
  "properties": {
    "iso:country":"ES",
    "sg:address":"Rua San Amaro, 4",
    "sg:city":"Boveda",
    "sg:orig_category":"Comunidades Religiosas",
    "sg:phone":"+34 982 42 60 66",
    "sg:postcode":"27340",
    "sg:province":"Lugo",
    "wof:name":"Miguelez Blanco Manuel Eloy",
    "wof:placetype":"venue"
},
  "geometry": {"coordinates":[-7.4789791107,42.6256217957],"type":"Point"}
}