{
  "type": "Feature",
  "properties": {
    "addr:full":"Trva Pasaje 1, S/n Pasaje Pontevedra 36788",
    "addr:housenumber":"s / n",
    "addr:postcode":"36788",
    "addr:street":"Trva Pasaje 1;Pasaje Pontevedra",
    "iso:country":"ES",
    "sg:address":"Trva Pasaje 1, S/n",
    "sg:city":"Pasaje",
    "sg:orig_category":"Fabricaci\u00d3n, Reparaci\u00d3n Y Mantenimiento De Construcciones Navales Y Fluviales",
    "sg:phone":"+34 986 62 71 01",
    "sg:postcode":"36788",
    "sg:province":"Pontevedra",
    "wof:name":"Suministros Navales Santa Tecla S.l",
    "wof:placetype":"venue"
},
  "geometry": {"coordinates":[-8.8542041779,41.8935165405],"type":"Point"}
}