{
  "type": "Feature",
  "properties": {
    "addr:full":"Calle de Marines, 2 Betera Valencia 46117",
    "addr:housenumber":"2",
    "addr:postcode":"46117",
    "addr:street":"Calle De Marines",
    "iso:country":"ES",
    "sg:address":"Calle de Marines, 2",
    "sg:city":"Betera",
    "sg:orig_category":"Promotores Constructores",
    "sg:phone":"+34 961 60 10 76",
    "sg:postcode":"46117",
    "sg:province":"Valencia",
    "wof:name":"Ges 2 S.l.",
    "wof:placetype":"venue"
},
  "geometry": {"coordinates":[-0.4602240026,39.5874862671],"type":"Point"}
}