{
  "type": "Feature",
  "properties": {
    "addr:full":"Calle de Feria, 77 Albacete Albacete 02004",
    "addr:housenumber":"77",
    "addr:postcode":"02004",
    "addr:street":"Calle De Feria",
    "iso:country":"ES",
    "sg:address":"Calle de Feria, 77",
    "sg:city":"Albacete",
    "sg:orig_category":"Negocio De Materiales De Construcci\u00d3n",
    "sg:phone":"+34 967 50 36 85",
    "sg:postcode":"02004",
    "sg:province":"Albacete",
    "wof:name":"Materiales De Construccion Pedro Sanchez S.l",
    "wof:placetype":"venue"
},
  "geometry": {"coordinates":[-1.8643519878,38.9962463379],"type":"Point"}
}