{
  "type": "Feature",
  "properties": {
    "iso:country":"ES",
    "sg:address":"Calle de Doctor Aznar Molina, 1",
    "sg:city":"Zaragoza",
    "sg:orig_category":"Frutas Y Legumbres Secas (al Por Mayor)",
    "sg:phone":"+34 976 29 50 75",
    "sg:postcode":"50002",
    "sg:province":"Zaragoza",
    "wof:name":"Lax Lavilla Patrocinio",
    "wof:placetype":"venue"
},
  "geometry": {"coordinates":[-0.8651303053,41.6503143311],"type":"Point"}
}