{
  "type": "Feature",
  "properties": {
    "iso:country":"ES",
    "sg:address":"Calle de G(campollano), 36",
    "sg:city":"Albacete",
    "sg:orig_category":"Fabricaci\u00d3n, Importaci\u00d3n, Venta De Material De Telefon\u00cda, Peritelefon\u00cda",
    "sg:phone":"+34 967 24 86 35",
    "sg:postcode":"02006",
    "sg:province":"Albacete",
    "wof:name":"Secitel Comunicaciones S.a.",
    "wof:placetype":"venue"
},
  "geometry": {"coordinates":[-2.044303894,39.0605888367],"type":"Point"}
}