{
  "type": "Feature",
  "properties": {
    "addr:full":"Calle de Conde Autol, 30 Autol La Rioja 26560",
    "addr:housenumber":"30",
    "addr:postcode":"26560",
    "addr:street":"Calle De Conde Autol;Rioja",
    "iso:country":"ES",
    "sg:address":"Calle de Conde Autol, 30",
    "sg:city":"Autol",
    "sg:orig_category":"Pescader\u00cdas (al Por Menor)",
    "sg:phone":"+34 941 40 12 32",
    "sg:postcode":"26560",
    "sg:province":"La Rioja",
    "wof:name":"Calvo Martinez Luis",
    "wof:placetype":"venue"
},
  "geometry": {"coordinates":[-2.004224062,42.2131233215],"type":"Point"}
}