{
  "type": "Feature",
  "properties": {
    "addr:full":"Calle de Mayor, 6 Oca\u00f1a Toledo 45300",
    "addr:housenumber":"6",
    "addr:postcode":"45300",
    "addr:street":"Calle De Mayor",
    "iso:country":"ES",
    "sg:address":"Calle de Mayor, 6",
    "sg:city":"Oca\u00f1a",
    "sg:orig_category":"Pescader\u00cdas (al Por Menor)",
    "sg:phone":"+34 925 13 02 22",
    "sg:postcode":"45300",
    "sg:province":"Toledo",
    "wof:name":"Hijos De Isidro Del Rio C.b.",
    "wof:placetype":"venue"
},
  "geometry": {"coordinates":[-3.5000178814,39.9587020874],"type":"Point"}
}