{
  "type": "Feature",
  "properties": {
    "addr:full":"Calle de Fernando Guanarteme, 128 Palmas De Gran Canaria Las Palmas 35010",
    "addr:housenumber":"128",
    "addr:postcode":"35010",
    "addr:street":"Calle De Fernando Guanarteme",
    "iso:country":"ES",
    "sg:address":"Calle de Fernando Guanarteme, 128",
    "sg:city":"Palmas De Gran Canaria",
    "sg:orig_category":"Muebles, Minoristas",
    "sg:phone":"+34 928 27 84 11",
    "sg:postcode":"35010",
    "sg:province":"Las Palmas",
    "wof:name":"Brito Padron Dolores",
    "wof:placetype":"venue"
},
  "geometry": {"coordinates":[-15.4412727356,28.1313915253],"type":"Point"}
}