{
  "type": "Feature",
  "properties": {
    "addr:full":"Pl Constitucion(sta Lucia), 18 Cartagena Murcia 30202",
    "addr:housenumber":"18",
    "addr:postcode":"30202",
    "addr:street":"Pl Constitucion Sta Lucia",
    "iso:country":"ES",
    "sg:address":"Pl Constitucion(sta Lucia), 18",
    "sg:city":"Cartagena",
    "sg:orig_category":"Estancos",
    "sg:phone":"+34 968 50 62 28",
    "sg:postcode":"30202",
    "sg:province":"Murcia",
    "wof:name":"Lopez Martinez Josefa",
    "wof:placetype":"venue"
},
  "geometry": {"coordinates":[-0.9718570113,37.5989494324],"type":"Point"}
}