{
  "type": "Feature",
  "properties": {
    "iso:country":"ES",
    "sg:address":"Calle de Doctor Mu\u00d1oz Seca, 3",
    "sg:city":"Puerto De Santa Maria",
    "sg:orig_category":"Telas Y Sedas (al Por Menor)",
    "sg:phone":"+34 956 85 22 80",
    "sg:postcode":"11500",
    "sg:province":"C\u00e1diz",
    "wof:name":"Mena Rodriguez Miguel",
    "wof:placetype":"venue"
},
  "geometry": {"coordinates":[-6.2272362709,36.6004753113],"type":"Point"}
}