{
  "type": "Feature",
  "properties": {
    "iso:country":"ES",
    "sg:address":"Pol Ind El Trocadero, S/n",
    "sg:city":"Pto Real",
    "sg:orig_category":"Construcciones Navales Y Fluviales",
    "sg:phone":"+34 956 80 41 55",
    "sg:postcode":"11519",
    "sg:province":"C\u00e1diz",
    "wof:name":"Sk10 Andalucia S.a.",
    "wof:placetype":"venue"
},
  "geometry": {"coordinates":[-6.2170300484,36.5123291016],"type":"Point"}
}