{
  "type": "Feature",
  "properties": {
    "iso:country":"ES",
    "sg:address":"Plaz San Severino, 4",
    "sg:city":"Balmaseda",
    "sg:orig_category":"Agencias Y Agentes Comerciales, Representantes",
    "sg:phone":"+34 946 80 16 03",
    "sg:postcode":"48800",
    "sg:province":"Vizcaya",
    "wof:name":"Corcuera Ruiz Juan Jesus",
    "wof:placetype":"venue"
},
  "geometry": {"coordinates":[-3.1932899952,43.1960449219],"type":"Point"}
}