{
  "type": "Feature",
  "properties": {
    "iso:country":"ES",
    "sg:address":"Avda Periodista R. De Salazar, 30",
    "sg:city":"Alacant",
    "sg:orig_category":"Compresores",
    "sg:phone":"+34 965 24 83 00",
    "sg:postcode":"03012",
    "sg:province":"Alicante",
    "wof:name":"Vialca Color S.l.",
    "wof:placetype":"venue"
},
  "geometry": {"coordinates":[-0.4794549942,38.3624992371],"type":"Point"}
}