{
  "type": "Feature",
  "properties": {
    "addr:full":"Calle de San Francisco, 26 Villanueva Serena Badajoz 06700",
    "addr:housenumber":"26",
    "addr:postcode":"06700",
    "addr:street":"Calle De San Francisco",
    "iso:country":"ES",
    "sg:address":"Calle de San Francisco, 26",
    "sg:city":"Villanueva Serena",
    "sg:orig_category":"Fabricaci\u00d3n, Distribuci\u00d3n De Discos, V\u00cddeodiscos Y Musicassettes",
    "sg:phone":"+34 924 84 73 77",
    "sg:postcode":"06700",
    "sg:province":"Badajoz",
    "wof:name":"Robles Luengo Julian",
    "wof:placetype":"venue"
},
  "geometry": {"coordinates":[-5.7946591377,38.9732589722],"type":"Point"}
}