{
  "type": "Feature",
  "properties": {
    "iso:country":"ES",
    "sg:address":"Calle de Miguel Iscar, 14",
    "sg:city":"Valladolid",
    "sg:orig_category":"Arquitectos",
    "sg:phone":"+34 983 29 26 48",
    "sg:postcode":"47001",
    "sg:province":"Valladolid",
    "wof:name":"Arquitectura Y Urbanismo Proyectos Y2k S.l.",
    "wof:placetype":"venue"
},
  "geometry": {"coordinates":[-4.7266187668,41.6485671997],"type":"Point"}
}