{
  "type": "Feature",
  "properties": {
    "addr:full":"Calle de Padre Torres Silva, 14 Jerez De La Frontera C\u00e1diz 11401",
    "addr:housenumber":"14",
    "addr:postcode":"11401",
    "addr:street":"Calle De Padre Torres Silva",
    "iso:country":"ES",
    "sg:address":"Calle de Padre Torres Silva, 14",
    "sg:city":"Jerez De La Frontera",
    "sg:orig_category":"Ense\u00d1anza Variada",
    "sg:phone":"+34 956 33 66 50",
    "sg:postcode":"11401",
    "sg:province":"C\u00e1diz",
    "wof:name":"Marin Arniz Maria De Las Mercedes",
    "wof:placetype":"venue"
},
  "geometry": {"coordinates":[-6.1265029907,36.6780052185],"type":"Point"}
}