{
  "type": "Feature",
  "properties": {
    "iso:country":"ES",
    "sg:address":"Calle de Pico De Las Palomas, 13",
    "sg:city":"Malaga",
    "sg:orig_category":"Ingeniero",
    "sg:phone":"+34 952 31 24 20",
    "sg:postcode":"29004",
    "sg:province":"M\u00e1laga",
    "wof:name":"Velasco Leon Andres",
    "wof:placetype":"venue"
},
  "geometry": {"coordinates":[-4.4431180954,36.6959114075],"type":"Point"}
}