{
  "type": "Feature",
  "properties": {
    "iso:country":"ES",
    "sg:address":"Avda Primero De Mayo, 43",
    "sg:city":"Valle Trapaga",
    "sg:orig_category":"Zapatos (al Por Menor)",
    "sg:phone":"+34 944 92 28 52",
    "sg:postcode":"48510",
    "sg:province":"Vizcaya",
    "wof:name":"Fernanda Mesa Romero (fany Calzados)",
    "wof:placetype":"venue"
},
  "geometry": {"coordinates":[-3.0336210728,43.3016014099],"type":"Point"}
}