{
  "type": "Feature",
  "properties": {
    "iso:country":"ES",
    "sg:address":"Carrer de Julia Centelles, 2",
    "sg:city":"Granollers",
    "sg:orig_category":"Molduras, Junquillos, Listones Y Molduras Perforadas",
    "sg:phone":"+34 938 79 22 62",
    "sg:postcode":"08402",
    "sg:province":"Barcelona",
    "wof:name":"Lopez Hervas Jordi",
    "wof:placetype":"venue"
},
  "geometry": {"coordinates":[2.2882199287,41.5991783142],"type":"Point"}
}