{
  "type": "Feature",
  "properties": {
    "addr:full":"Carrer de Doctor Trueta, 180 Barcelona Barcelona 08005",
    "addr:housenumber":"180",
    "addr:postcode":"08005",
    "addr:street":"Carrer De Doctor Trueta",
    "iso:country":"ES",
    "sg:address":"Carrer de Doctor Trueta, 180",
    "sg:city":"Barcelona",
    "sg:orig_category":"Inform\u00c1tica (estudios, Servicios, Asesor\u00cda, Formaci\u00d3n)",
    "sg:phone":"+34 932 25 19 78",
    "sg:postcode":"08005",
    "sg:province":"Barcelona",
    "wof:name":"Environment Personal Computer S.l.u.",
    "wof:placetype":"venue"
},
  "geometry": {"coordinates":[2.2015140057,41.3969612122],"type":"Point"}
}