{
  "type": "Feature",
  "properties": {
    "iso:country":"ES",
    "sg:address":"Pol El Carrascal, 14",
    "sg:city":"Lanciego Lantziego",
    "sg:orig_category":"Andamiajes Y Escaleras De Mano (fabricaci\u00d3n, Al Por Mayor)",
    "sg:phone":"+34 945 62 52 37",
    "sg:postcode":"01308",
    "sg:province":"\u00c1lava",
    "wof:name":"Nor-este Rioja S.l.",
    "wof:placetype":"venue"
},
  "geometry": {"coordinates":[-2.5116169453,42.5591163635],"type":"Point"}
}