{
  "type": "Feature",
  "properties": {
    "addr:full":"Calle de Cruz Roja, S/n Santo Tome Ja\u00e9n 23311",
    "addr:housenumber":"s / n",
    "addr:postcode":"23311",
    "addr:street":"Calle De Cruz Roja",
    "iso:country":"ES",
    "sg:address":"Calle de Cruz Roja, S/n",
    "sg:city":"Santo Tome",
    "sg:orig_category":"Aguas (distribuci\u00d3n, Servicios)",
    "sg:phone":"+34 953 73 65 37",
    "sg:postcode":"23311",
    "sg:province":"Ja\u00e9n",
    "wof:name":"Aguas Jaen S.a.",
    "wof:placetype":"venue"
},
  "geometry": {"coordinates":[-3.0975337029,38.0287322998],"type":"Point"}
}