{
  "type": "Feature",
  "properties": {
    "iso:country":"ES",
    "sg:address":"Calle de Ba\u00d1ales, S/n",
    "sg:city":"Coria Rio",
    "sg:orig_category":"Molduras, Junquillos, Listones Y Molduras Perforadas",
    "sg:phone":"+34 954 77 34 26",
    "sg:postcode":"41100",
    "sg:province":"Sevilla",
    "wof:name":"Pertel S.cv.",
    "wof:placetype":"venue"
},
  "geometry": {"coordinates":[-6.0553627014,37.2867584229],"type":"Point"}
}