{
  "type": "Feature",
  "properties": {
    "addr:full":"Calle de Caveda Y Nava, 30 Villaviciosa Asturias 33300",
    "addr:housenumber":"30",
    "addr:postcode":"33300",
    "addr:street":"Calle De Caveda Y Nava",
    "iso:country":"ES",
    "sg:address":"Calle de Caveda Y Nava, 30",
    "sg:city":"Villaviciosa",
    "sg:orig_category":"Compraventa De Antig\u00dcedades",
    "sg:phone":"+34 985 89 21 87",
    "sg:postcode":"33300",
    "sg:province":"Asturias",
    "wof:name":"Valle Ordiales Maria Del Carmen",
    "wof:placetype":"venue"
},
  "geometry": {"coordinates":[-5.4359340668,43.4817352295],"type":"Point"}
}