{
  "type": "Feature",
  "properties": {
    "addr:full":"Calle de Bernardo Escos Catalan, 7 Tudela Navarra 31500",
    "addr:housenumber":"7",
    "addr:postcode":"31500",
    "addr:street":"Calle De Bernardo Escos Catalan",
    "iso:country":"ES",
    "sg:address":"Calle de Bernardo Escos Catalan, 7",
    "sg:city":"Tudela",
    "sg:orig_category":"Farmacias",
    "sg:phone":"+34 948 40 26 06",
    "sg:postcode":"31500",
    "sg:province":"Navarra",
    "wof:name":"Lopez Lopez Manuel",
    "wof:placetype":"venue"
},
  "geometry": {"coordinates":[-1.6045284271,42.0535087585],"type":"Point"}
}