{
  "type": "Feature",
  "properties": {
    "iso:country":"ES",
    "sg:address":"Poli Pol.indust. El Segre, S/n",
    "sg:city":"Lleida",
    "sg:orig_category":"Edici\u00d3n De Diarios, Revistas, Boletines",
    "sg:phone":"+34 973 20 16 46",
    "sg:postcode":"25191",
    "sg:province":"Lleida",
    "sg:website":"www.lama\u00f1anya.es",
    "wof:name":"Noves Formes Grafiques S.a.u.",
    "wof:placetype":"venue"
},
  "geometry": {"coordinates":[0.6831650138,41.5832138062],"type":"Point"}
}