{
  "type": "Feature",
  "properties": {
    "addr:full":"Cmno Arenas, S/n Valladolid Valladolid 47011",
    "addr:housenumber":"s / n",
    "addr:postcode":"47011",
    "addr:street":"Cmno Arenas",
    "iso:country":"ES",
    "sg:address":"Cmno Arenas, S/n",
    "sg:city":"Valladolid",
    "sg:orig_category":"Hormig\u00d3n (m\u00c1quinas E Instalaci\u00d3n)",
    "sg:phone":"+34 983 30 33 24",
    "sg:postcode":"47011",
    "sg:province":"Valladolid",
    "wof:name":"Autobombas De Hormigon Valladolid S.l.",
    "wof:placetype":"venue"
},
  "geometry": {"coordinates":[-4.6898450851,41.6635894775],"type":"Point"}
}