{
  "type": "Feature",
  "properties": {
    "iso:country":"ES",
    "sg:address":"Av Pau Casals, 8",
    "sg:city":"Barcelona",
    "sg:orig_category":"Abogados",
    "sg:phone":"+34 934 14 59 52",
    "sg:postcode":"08021",
    "sg:province":"Barcelona",
    "wof:name":"Ruizdelgado Balsach Ignacio",
    "wof:placetype":"venue"
},
  "geometry": {"coordinates":[2.1436669827,41.393535614],"type":"Point"}
}