{
  "type": "Feature",
  "properties": {
    "iso:country":"ES",
    "sg:address":"Urb Santa Ana, 1",
    "sg:city":"Bejar",
    "sg:orig_category":"Confecci\u00d3n De Ropa Interior",
    "sg:phone":"+34 923 41 17 46",
    "sg:postcode":"37700",
    "sg:province":"Salamanca",
    "wof:name":"Distribucion De Productos Textiles Especializados Disprotex S.l.",
    "wof:placetype":"venue"
},
  "geometry": {"coordinates":[-5.7728161812,40.3881263733],"type":"Point"}
}