{
  "type": "Feature",
  "properties": {
    "iso:country":"ES",
    "sg:address":"Calle de Salitre, 33",
    "sg:city":"Cartagena",
    "sg:orig_category":"Abogados",
    "sg:phone":"+34 968 50 49 26",
    "sg:postcode":"30205",
    "sg:province":"Murcia",
    "wof:name":"Martinez Pastor Manuel",
    "wof:placetype":"venue"
},
  "geometry": {"coordinates":[-0.9875789881,37.604850769],"type":"Point"}
}