{
  "type": "Feature",
  "properties": {
    "iso:country":"ES",
    "sg:address":"Avda Luis Movilla, 8",
    "sg:city":"Badajoz",
    "sg:orig_category":"Almacenes Frigor\u00cdficos",
    "sg:phone":"+34 924 23 45 30",
    "sg:postcode":"06011",
    "sg:province":"Badajoz",
    "wof:name":"Friger S.l.",
    "wof:placetype":"venue"
},
  "geometry": {"coordinates":[-7.1200389862,38.803768158],"type":"Point"}
}