{
  "type": "Feature",
  "properties": {
    "iso:country":"ES",
    "sg:address":"Avda Francisco Aguirre, 316",
    "sg:city":"Talavera Reina",
    "sg:orig_category":"Reposter\u00cdas",
    "sg:phone":"+34 925 82 88 44",
    "sg:postcode":"45600",
    "sg:province":"Toledo",
    "wof:name":"Panaderias Robledo S.l.",
    "wof:placetype":"venue"
},
  "geometry": {"coordinates":[-4.8406219482,39.9636268616],"type":"Point"}
}