{
  "type": "Feature",
  "properties": {
    "addr:full":"Calle de Nu\u00d1ez De Balboa, 12 Madrid Madrid 28001",
    "addr:housenumber":"12",
    "addr:postcode":"madrid;28001",
    "addr:street":"Calle De Nun\u0303Ez De Balboa",
    "iso:country":"ES",
    "sg:address":"Calle de Nu\u00d1ez De Balboa, 12",
    "sg:city":"Madrid",
    "sg:orig_category":"Fabricaci\u00d3n De Peines Y De Accesorios De Peluquer\u00cda",
    "sg:phone":"+34 914 02 83 21",
    "sg:postcode":"28001",
    "sg:province":"Madrid",
    "wof:name":"Colomer Beauty And Profesional Products S.l.",
    "wof:placetype":"venue"
},
  "geometry": {"coordinates":[-3.6827828884,40.4229812622],"type":"Point"}
}