{
  "type": "Feature",
  "properties": {
    "iso:country":"ES",
    "sg:address":"Calle de Castelar, 17",
    "sg:city":"Madrid",
    "sg:orig_category":"Deportes Diversos",
    "sg:phone":"+34 917 25 16 49",
    "sg:postcode":"28028",
    "sg:province":"Madrid",
    "sg:website":"www.fmgimnasia.com",
    "wof:name":"Federacion Castellana Gimnasia",
    "wof:placetype":"venue"
},
  "geometry": {"coordinates":[-3.6662278175,40.4306335449],"type":"Point"}
}