{
  "type": "Feature",
  "properties": {
    "iso:country":"ES",
    "sg:address":"Calle de Kasune, 10",
    "sg:city":"Algorta",
    "sg:orig_category":"M\u00c9dicos: Estomatolog\u00cda",
    "sg:phone":"+34 944 30 64 64",
    "sg:postcode":"48991",
    "sg:province":"Vizcaya",
    "wof:name":"Deprit Uriarte Enrique",
    "wof:placetype":"venue"
},
  "geometry": {"coordinates":[-3.0066900253,43.3520851135],"type":"Point"}
}