{
  "type": "Feature",
  "properties": {
    "addr:full":"Plaz Constitucion, 4 Donostia-san Sebastian Guip\u00f9zcoa 20003",
    "addr:housenumber":"4",
    "addr:postcode":"20003",
    "addr:street":"Constitucion",
    "iso:country":"ES",
    "sg:address":"Plaz Constitucion, 4",
    "sg:city":"Donostia-san Sebastian",
    "sg:orig_category":"Empresas De Carpinter\u00cda De Madera",
    "sg:phone":"+34 943 42 61 42",
    "sg:postcode":"20003",
    "sg:province":"Guip\u00f9zcoa",
    "wof:name":"Recarte Otermin Josefa",
    "wof:placetype":"venue"
},
  "geometry": {"coordinates":[-1.9849809408,43.3238182068],"type":"Point"}
}