{
  "type": "Feature",
  "properties": {
    "addr:full":"Calle de Molino, 18 Maire De Castroponce Zamora 49783",
    "addr:housenumber":"18",
    "addr:postcode":"49783",
    "addr:street":"Calle De Molino",
    "iso:country":"ES",
    "sg:address":"Calle de Molino, 18",
    "sg:city":"Maire De Castroponce",
    "sg:orig_category":"Farmacias",
    "sg:phone":"+34 980 65 00 17",
    "sg:postcode":"49783",
    "sg:province":"Zamora",
    "wof:name":"Garcia Blanco Inmaculada",
    "wof:placetype":"venue"
},
  "geometry": {"coordinates":[-5.7852239609,42.1121788025],"type":"Point"}
}