{
  "type": "Feature",
  "properties": {
    "addr:full":"Pla\u00c7 Major, S/n Bell-lloc D'urgell Lleida 25220",
    "addr:housenumber":"s / n",
    "addr:postcode":"25220",
    "iso:country":"ES",
    "sg:address":"Pla\u00c7 Major, S/n",
    "sg:city":"Bell-lloc D'urgell",
    "sg:orig_category":"Ense\u00d1anza, Formaci\u00d3n Profesional: Aprendizaje",
    "sg:phone":"+34 973 56 01 00",
    "sg:postcode":"25220",
    "sg:province":"Lleida",
    "wof:name":"Ayuntamiento De Bell-lloch",
    "wof:placetype":"venue"
},
  "geometry": {"coordinates":[0.6457189918,41.6027946472],"type":"Point"}
}