{
  "type": "Feature",
  "properties": {
    "iso:country":"ES",
    "sg:address":"Rond Alfons X El Savi (d'), 135",
    "sg:city":"Mataro",
    "sg:orig_category":"Confiter\u00cdas, Chocolater\u00cdas (al Por Menor)",
    "sg:phone":"+34 937 96 15 93",
    "sg:postcode":"08304",
    "sg:province":"Barcelona",
    "wof:name":"Pastisseria El Pilar S.l.",
    "wof:placetype":"venue"
},
  "geometry": {"coordinates":[2.4500141144,41.5458564758],"type":"Point"}
}