{
  "type": "Feature",
  "properties": {
    "addr:full":"Calle de Sigfrido, 10 Malaga M\u00e1laga 29006",
    "addr:housenumber":"10",
    "addr:postcode":"29006",
    "addr:street":"Calle De Sigfrido;Ma\u0301Laga",
    "iso:country":"ES",
    "sg:address":"Calle de Sigfrido, 10",
    "sg:city":"Malaga",
    "sg:orig_category":"Fabricaci\u00d3n De Etiquetas",
    "sg:phone":"+34 952 32 77 11",
    "sg:postcode":"29006",
    "sg:province":"M\u00e1laga",
    "wof:name":"Fabricacion Malague\u00f1a De Bolsas S.l.",
    "wof:placetype":"venue"
},
  "geometry": {"coordinates":[-4.4690680504,36.7075881958],"type":"Point"}
}