{
  "type": "Feature",
  "properties": {
    "iso:country":"ES",
    "sg:address":"Carrer de Porta, 16",
    "sg:city":"Barcelona",
    "sg:orig_category":"Mec\u00c1nico Del Autom\u00d3vil",
    "sg:phone":"+34 933 40 63 47",
    "sg:postcode":"08016",
    "sg:province":"Barcelona",
    "wof:name":"Vizcaino Martinez Vicente",
    "wof:placetype":"venue"
},
  "geometry": {"coordinates":[2.1748530865,41.432384491],"type":"Point"}
}