{
  "type": "Feature",
  "properties": {
    "iso:country":"ES",
    "sg:address":"Ptda Caxola, S/n",
    "sg:city":"Finestrat",
    "sg:orig_category":"Empresas De Carpinter\u00cda De Madera",
    "sg:phone":"+34 965 85 43 77",
    "sg:postcode":"03509",
    "sg:province":"Alicante",
    "wof:name":"Correa Mu\u00f1oz Luis Alberto",
    "wof:placetype":"venue"
},
  "geometry": {"coordinates":[-0.2106740028,38.5691642761],"type":"Point"}
}