{
  "type": "Feature",
  "properties": {
    "iso:country":"ES",
    "sg:address":"Urb Olivos (los), 8",
    "sg:city":"Beato",
    "sg:orig_category":"Conservas De Legumbres (fabricaci\u00d3n, Al Por Mayor)",
    "sg:phone":"+34 925 35 30 87",
    "sg:postcode":"45280",
    "sg:province":"Toledo",
    "wof:name":"Julian Garcia Martinez C.b.",
    "wof:placetype":"venue"
},
  "geometry": {"coordinates":[-3.9885389805,39.9435043335],"type":"Point"}
}