{
  "type": "Feature",
  "properties": {
    "iso:country":"ES",
    "sg:address":"Calle de Lope De Rueda, 9",
    "sg:city":"Meco",
    "sg:orig_category":"Venta, Colocaci\u00d3n De Tabiques",
    "sg:phone":"+34 918 87 65 02",
    "sg:postcode":"28880",
    "sg:province":"Madrid",
    "wof:name":"Labella Decoracion Y Aislamientos S.l.",
    "wof:placetype":"venue"
},
  "geometry": {"coordinates":[-3.3290731907,40.5571556091],"type":"Point"}
}