{
  "type": "Feature",
  "properties": {
    "iso:country":"ES",
    "sg:address":"Ctra Malpartida, Km. 0001,1",
    "sg:city":"Plasencia",
    "sg:orig_category":"Reciclaje, Desguace De Veh\u00cdculos",
    "sg:phone":"+34 927 41 76 82",
    "sg:postcode":"10600",
    "sg:province":"C\u00e1ceres",
    "wof:name":"Izquierdo Sanchez Miguel Angel",
    "wof:placetype":"venue"
},
  "geometry": {"coordinates":[-6.099822998,40.0152359009],"type":"Point"}
}