{
  "type": "Feature",
  "properties": {
    "iso:country":"ES",
    "sg:address":"Po. Neinver, S/n",
    "sg:city":"Arteaga",
    "sg:orig_category":"Fabricaci\u00d3n De Mobiliario Met\u00c1lico",
    "sg:phone":"+34 944 52 09 71",
    "sg:postcode":"48170",
    "sg:province":"Vizcaya",
    "wof:name":"Almacenaje Y Complementos S. A.",
    "wof:placetype":"venue"
},
  "geometry": {"coordinates":[-2.7841410637,43.1337165833],"type":"Point"}
}