{
  "type": "Feature",
  "properties": {
    "iso:country":"ES",
    "sg:address":"Plaz Virgen Del Mar, 1",
    "sg:city":"Santurtzi",
    "sg:orig_category":"Peluqueros: De Se\u00d1oras",
    "sg:phone":"+34 944 62 39 17",
    "sg:postcode":"48980",
    "sg:province":"Vizcaya",
    "wof:name":"Juana Galarraga Arenas Y Otra C.b.",
    "wof:placetype":"venue"
},
  "geometry": {"coordinates":[-3.0357220173,43.3308410645],"type":"Point"}
}