{
  "type": "Feature",
  "properties": {
    "addr:full":"Carrer de Santa Teresa, 38 Mataro Barcelona 08302",
    "addr:housenumber":"38",
    "addr:postcode":"08302",
    "addr:street":"Carrer De Santa Teresa",
    "iso:country":"ES",
    "sg:address":"Carrer de Santa Teresa, 38",
    "sg:city":"Mataro",
    "sg:orig_category":"Confiter\u00cdas, Chocolater\u00cdas (al Por Menor)",
    "sg:phone":"+34 937 90 29 96",
    "sg:postcode":"08302",
    "sg:province":"Barcelona",
    "wof:name":"Escorsa Calvo Maria Dolores",
    "wof:placetype":"venue"
},
  "geometry": {"coordinates":[2.4439079762,41.5379371643],"type":"Point"}
}