{
  "type": "Feature",
  "properties": {
    "iso:country":"ES",
    "sg:address":"Calle de Batalla Del Salado, 55",
    "sg:city":"Madrid",
    "sg:orig_category":"Distribuci\u00d3n De Petr\u00d3leo Y Derivados",
    "sg:phone":"+34 915 27 75 03",
    "sg:postcode":"28045",
    "sg:province":"Madrid",
    "wof:name":"Pescados Y Mariscos Santiago & Santiago S.l.",
    "wof:placetype":"venue"
},
  "geometry": {"coordinates":[-3.696518898,40.3974494934],"type":"Point"}
}