{
  "type": "Feature",
  "properties": {
    "iso:country":"ES",
    "sg:address":"Ctra Agost, Km. 0001,9",
    "sg:city":"San Vicente Del Raspeig-sant Vicent Del Raspeig",
    "sg:orig_category":"Aguas (distribuci\u00d3n, Servicios)",
    "sg:phone":"+34 965 66 55 97",
    "sg:postcode":"03690",
    "sg:province":"Alicante",
    "wof:name":"Exclusivas Aitana S. A. L.",
    "wof:placetype":"venue"
},
  "geometry": {"coordinates":[-0.5231339931,38.3981590271],"type":"Point"}
}