{
  "type": "Feature",
  "properties": {
    "addr:full":"Carrer de Comtes De Bell Lloc, 115 Barcelona Barcelona 08014",
    "addr:housenumber":"115",
    "addr:postcode":"08014",
    "addr:street":"Carrer De Comtes De Bell Lloc",
    "iso:country":"ES",
    "sg:address":"Carrer de Comtes De Bell Lloc, 115",
    "sg:city":"Barcelona",
    "sg:orig_category":"Frutas, Legumbres Frescas Y Tempranas (al Por Menor)",
    "sg:phone":"+34 934 90 51 63",
    "sg:postcode":"08014",
    "sg:province":"Barcelona",
    "wof:name":"Nugafruits Serveis De Distribucio S.a.",
    "wof:placetype":"venue"
},
  "geometry": {"coordinates":[2.1366760731,41.3812904358],"type":"Point"}
}