{
  "type": "Feature",
  "properties": {
    "iso:country":"ES",
    "sg:address":"Calle de Vicente Blasco Iba\u00d1ez, 19",
    "sg:city":"Madrid",
    "sg:orig_category":"Electr\u00d3nica Profesional: Material Y Componentes (al Por Mayor)",
    "sg:phone":"+34 917 67 87 22",
    "sg:postcode":"28050",
    "sg:province":"Madrid",
    "sg:website":"www.mtvasyprel.com",
    "wof:name":"Mtv Asesoramiento Y Pro Electricos S.l.",
    "wof:placetype":"venue"
},
  "geometry": {"coordinates":[-3.6568250656,40.4919052124],"type":"Point"}
}