{
  "type": "Feature",
  "properties": {
    "iso:country":"ES",
    "sg:address":"Plaz Major, 26",
    "sg:city":"Torrent",
    "sg:orig_category":"Agentes Generales De Seguros",
    "sg:phone":"+34 961 55 00 89",
    "sg:postcode":"46900",
    "sg:province":"Valencia",
    "wof:name":"Escorihuela Beltran Miguel",
    "wof:placetype":"venue"
},
  "geometry": {"coordinates":[-0.4636780024,39.437374115],"type":"Point"}
}