{
  "type": "Feature",
  "properties": {
    "addr:full":"Calle de Llana, 10 Cazalla Sierra Sevilla 41370",
    "addr:housenumber":"10",
    "addr:postcode":"41370",
    "addr:street":"Calle De Llana",
    "iso:country":"ES",
    "sg:address":"Calle de Llana, 10",
    "sg:city":"Cazalla Sierra",
    "sg:orig_category":"Producci\u00d3n, Distribuci\u00d3n De Electricidad",
    "sg:phone":"+34 954 88 30 78",
    "sg:postcode":"41370",
    "sg:province":"Sevilla",
    "wof:name":"Joma S.cv.",
    "wof:placetype":"venue"
},
  "geometry": {"coordinates":[-5.7596278191,37.932598114],"type":"Point"}
}