{
  "type": "Feature",
  "properties": {
    "addr:full":"Ctra Avila, S/n Espinar Segovia 40400",
    "addr:postcode":"40400",
    "addr:street":"Ctra Avila S / N;Segovia",
    "iso:country":"ES",
    "sg:address":"Ctra Avila, S/n",
    "sg:city":"Espinar",
    "sg:orig_category":"Organismos De Turismo",
    "sg:phone":"+34 921 18 18 76",
    "sg:postcode":"40400",
    "sg:province":"Segovia",
    "wof:name":"Lactofresc S.l.",
    "wof:placetype":"venue"
},
  "geometry": {"coordinates":[-4.2519388199,40.7149047852],"type":"Point"}
}