{
  "type": "Feature",
  "properties": {
    "addr:full":"Calle de Antonio Lopez, 235 Madrid Madrid 28041",
    "addr:housenumber":"235",
    "addr:postcode":"28041",
    "addr:street":"Calle De Antonio Lopez",
    "iso:country":"ES",
    "sg:address":"Calle de Antonio Lopez, 235",
    "sg:city":"Madrid",
    "sg:orig_category":"Caf\u00c9s, Bares, Cervecer\u00cdas",
    "sg:phone":"+34 914 75 50 41",
    "sg:postcode":"28041",
    "sg:province":"Madrid",
    "wof:name":"Garcia Gonzalez Jose Manuel",
    "wof:placetype":"venue"
},
  "geometry": {"coordinates":[-3.6954903603,40.3804588318],"type":"Point"}
}