{
  "type": "Feature",
  "properties": {
    "iso:country":"ES",
    "sg:address":"Carrer de Mogoda, 1",
    "sg:city":"Barbera Valles",
    "sg:orig_category":"Transportes Internacionales",
    "sg:phone":"+34 937 29 08 10",
    "sg:postcode":"08210",
    "sg:province":"Barcelona",
    "wof:name":"Brockers Company Courier Valles S.l.",
    "wof:placetype":"venue"
},
  "geometry": {"coordinates":[2.149969101,41.5153770447],"type":"Point"}
}