{
  "type": "Feature",
  "properties": {
    "addr:full":"Calle de Carmen Sevilla, 2 Estepona M\u00e1laga 29680",
    "addr:housenumber":"2",
    "addr:postcode":"29680",
    "addr:street":"Calle De Carmen Sevilla",
    "iso:country":"ES",
    "sg:address":"Calle de Carmen Sevilla, 2",
    "sg:city":"Estepona",
    "sg:orig_category":"Asesor\u00cda De Formaci\u00d3n Y Gesti\u00d3n De Personal",
    "sg:phone":"+34 952 80 09 99",
    "sg:postcode":"29680",
    "sg:province":"M\u00e1laga",
    "wof:name":"Fernandez Abogados Y Asociados S.l.",
    "wof:placetype":"venue"
},
  "geometry": {"coordinates":[-5.1449503899,36.425491333],"type":"Point"}
}