{
  "type": "Feature",
  "properties": {
    "iso:country":"ES",
    "sg:address":"Vega Tajo, S/n",
    "sg:city":"Quer",
    "sg:orig_category":"Pintura, Barniz, Productos Asimilables (fabricaci\u00d3n, Al Por Mayor)",
    "sg:phone":"+34 949 29 75 52",
    "sg:postcode":"19209",
    "sg:province":"Guadalajara",
    "wof:name":"Marcas Viales S. A.",
    "wof:placetype":"venue"
},
  "geometry": {"coordinates":[-3.2811589241,40.614654541],"type":"Point"}
}