{
  "type": "Feature",
  "properties": {
    "iso:country":"ES",
    "sg:address":"Ctra Ronda (de), S/n",
    "sg:city":"Vera",
    "sg:orig_category":"Agentes, Concesionarios Y Sucursales De Veh\u00cdculos",
    "sg:phone":"+34 950 39 30 97",
    "sg:postcode":"04620",
    "sg:province":"Almer\u00eda",
    "wof:name":"Automecanica Almeriense S. A.",
    "wof:placetype":"venue"
},
  "geometry": {"coordinates":[-1.8611011505,37.2291374207],"type":"Point"}
}