{
  "type": "Feature",
  "properties": {
    "iso:country":"ES",
    "sg:address":"Mas Puig, S/n",
    "sg:city":"Serinya",
    "sg:orig_category":"Fabricaci\u00d3n De Revestimientos De Suelos Pl\u00c1sticos Y De Goma",
    "sg:phone":"+34 972 59 33 13",
    "sg:postcode":"17852",
    "sg:province":"Girona",
    "wof:name":"Poliester S.l.",
    "wof:placetype":"venue"
},
  "geometry": {"coordinates":[2.744343996,42.169128418],"type":"Point"}
}