{
  "type": "Feature",
  "properties": {
    "iso:country":"ES",
    "sg:address":"Carrer de Sant Adria, 81",
    "sg:city":"Barcelona",
    "sg:orig_category":"Distribuci\u00d3n De Petr\u00d3leo Y Derivados",
    "sg:phone":"+34 933 46 98 77",
    "sg:postcode":"08030",
    "sg:province":"Barcelona",
    "wof:name":"Estacion De Servicio Sacasa S. A.",
    "wof:placetype":"venue"
},
  "geometry": {"coordinates":[2.2013349533,41.4359283447],"type":"Point"}
}