{
  "type": "Feature",
  "properties": {
    "addr:full":"Calle de Montero, 34 Mostoles Madrid 28934",
    "addr:housenumber":"34",
    "addr:postcode":"28934",
    "addr:street":"Calle De Montero",
    "iso:country":"ES",
    "sg:address":"Calle de Montero, 34",
    "sg:city":"Mostoles",
    "sg:orig_category":"Perfumer\u00cda (al Por Menor)",
    "sg:phone":"+34 916 13 04 97",
    "sg:postcode":"28934",
    "sg:province":"Madrid",
    "sg:website":"www.bodybell.com",
    "wof:name":"Iberica De Drogueria Y Perfumeria S.a.",
    "wof:placetype":"venue"
},
  "geometry": {"coordinates":[-3.8675971031,40.3209762573],"type":"Point"}
}