{
  "type": "Feature",
  "properties": {
    "addr:full":"Avda Parque Sur, 2 Albatana Albacete 02653",
    "addr:postcode":"02653",
    "addr:street":"Avda Parque;2",
    "iso:country":"ES",
    "sg:address":"Avda Parque Sur, 2",
    "sg:city":"Albatana",
    "sg:orig_category":"Carnicer\u00cdas, Carnicer\u00cdas",
    "sg:phone":"+34 967 32 33 58",
    "sg:postcode":"02653",
    "sg:province":"Albacete",
    "wof:name":"Garcia Vargas Pascual",
    "wof:placetype":"venue"
},
  "geometry": {"coordinates":[-1.522762537,38.5698318481],"type":"Point"}
}