{
  "type": "Feature",
  "properties": {
    "iso:country":"ES",
    "sg:address":"Avda Aragon, 30",
    "sg:city":"Valencia",
    "sg:orig_category":"Agencias De Viajes",
    "sg:phone":"+34 963 93 34 44",
    "sg:postcode":"46021",
    "sg:province":"Valencia",
    "sg:website":"www.viajescorteingles.es",
    "wof:name":"Viajes El Corte Ingles S.a.",
    "wof:placetype":"venue"
},
  "geometry": {"coordinates":[-0.3574480116,39.4716529846],"type":"Point"}
}