{
  "type": "Feature",
  "properties": {
    "addr:full":"Avda Pardaleras, 22 Badajoz Badajoz 06003",
    "addr:housenumber":"22",
    "addr:postcode":"06003",
    "addr:street":"Avda Pardaleras",
    "iso:country":"ES",
    "sg:address":"Avda Pardaleras, 22",
    "sg:city":"Badajoz",
    "sg:orig_category":"Cajas De Ahorro",
    "sg:phone":"+34 924 25 17 12",
    "sg:postcode":"06003",
    "sg:province":"Badajoz",
    "wof:name":"Caja De Badajoz",
    "wof:placetype":"venue"
},
  "geometry": {"coordinates":[-6.9685602188,38.8735389709],"type":"Point"}
}