{
  "type": "Feature",
  "properties": {
    "addr:full":"Calle de Escultor Ramirez, 5 Zaragoza Zaragoza 50007",
    "addr:housenumber":"5",
    "addr:postcode":"50007",
    "addr:street":"Calle De Escultor Ramirez",
    "iso:country":"ES",
    "sg:address":"Calle de Escultor Ramirez, 5",
    "sg:city":"Zaragoza",
    "sg:orig_category":"Empresas De Carpinter\u00cda Met\u00c1lica",
    "sg:phone":"+34 976 25 19 59",
    "sg:postcode":"50007",
    "sg:province":"Zaragoza",
    "wof:name":"Ferrer Lain Jose Luis",
    "wof:placetype":"venue"
},
  "geometry": {"coordinates":[-0.8764144182,41.6331863403],"type":"Point"}
}