{
  "type": "Feature",
  "properties": {
    "iso:country":"ES",
    "sg:address":"Carrer de Sant Francesc, 29",
    "sg:city":"Callosa D'en Sarria",
    "sg:orig_category":"Muebles, Minoristas",
    "sg:phone":"+34 965 88 02 77",
    "sg:postcode":"03510",
    "sg:province":"Alicante",
    "wof:name":"Saval Llinares Juan Antonio",
    "wof:placetype":"venue"
},
  "geometry": {"coordinates":[-0.1231636032,38.650604248],"type":"Point"}
}