{
  "type": "Feature",
  "properties": {
    "addr:full":"Carrer de Muntaner, 497 Barcelona Barcelona 08022",
    "addr:housenumber":"497",
    "addr:postcode":"08022",
    "addr:street":"Carrer De Muntaner",
    "iso:country":"ES",
    "sg:address":"Carrer de Muntaner, 497",
    "sg:city":"Barcelona",
    "sg:orig_category":"Grafistas",
    "sg:phone":"+34 934 18 12 28",
    "sg:postcode":"08022",
    "sg:province":"Barcelona",
    "sg:website":"www.cccimatge.com",
    "wof:name":"Castells Cuch Rosa",
    "wof:placetype":"venue"
},
  "geometry": {"coordinates":[2.1374490261,41.4030151367],"type":"Point"}
}