{
  "type": "Feature",
  "properties": {
    "addr:full":"Calle de Ramon Sainz, 14 Madrid Madrid 28025",
    "addr:housenumber":"14",
    "addr:postcode":"madrid;28025",
    "addr:street":"Calle De Ramon Sainz",
    "iso:country":"ES",
    "sg:address":"Calle de Ramon Sainz, 14",
    "sg:city":"Madrid",
    "sg:orig_category":"Empresas De Portes Y Mensajer\u00cda",
    "sg:phone":"+34 914 61 18 31",
    "sg:postcode":"28025",
    "sg:province":"Madrid",
    "wof:name":"Iqbal  Azhar",
    "wof:placetype":"venue"
},
  "geometry": {"coordinates":[-3.7368199825,40.3867988586],"type":"Point"}
}