{
  "type": "Feature",
  "properties": {
    "iso:country":"ES",
    "sg:address":"Calle de Sol, S/n",
    "sg:city":"Villacastin",
    "sg:orig_category":"Electricidad: Instaladores",
    "sg:phone":"+34 921 19 84 62",
    "sg:postcode":"40150",
    "sg:province":"Segovia",
    "wof:name":"Instalaciones Electricas Gil C.b.",
    "wof:placetype":"venue"
},
  "geometry": {"coordinates":[-4.406414032,40.7786483765],"type":"Point"}
}