{
  "type": "Feature",
  "properties": {
    "iso:country":"ES",
    "sg:address":"Carr Alberes, 49",
    "sg:city":"Blanes",
    "sg:orig_category":"Sanatorios M\u00c9dico",
    "sg:phone":"+34 972 33 39 79",
    "sg:postcode":"17300",
    "sg:province":"Girona",
    "wof:name":"Portal De Salut S.c.p.",
    "wof:placetype":"venue"
},
  "geometry": {"coordinates":[2.7906849384,41.6724243164],"type":"Point"}
}