{
  "type": "Feature",
  "properties": {
    "addr:full":"Acacias De Guadalmar, 4 Malaga M\u00e1laga 29004",
    "addr:housenumber":"4",
    "addr:postcode":"29004",
    "addr:street":"Malaga Ma\u0301Laga",
    "iso:country":"ES",
    "sg:address":"Acacias De Guadalmar, 4",
    "sg:city":"Malaga",
    "sg:orig_category":"Centros Empresariales",
    "sg:phone":"+34 952 24 04 25",
    "sg:postcode":"29004",
    "sg:province":"M\u00e1laga",
    "wof:name":"Salas Ariza Maria De Los Angeles",
    "wof:placetype":"venue"
},
  "geometry": {"coordinates":[-4.4569911957,36.6645927429],"type":"Point"}
}