{
  "type": "Feature",
  "properties": {
    "addr:full":"Estacio, S/n Figueres Girona 17600",
    "addr:housenumber":"s / n",
    "addr:postcode":"17600",
    "addr:street":"Estacio",
    "iso:country":"ES",
    "sg:address":"Estacio, S/n",
    "sg:city":"Figueres",
    "sg:orig_category":"Alquiler De Veh\u00cdculos: Turismos Y Utilitarios",
    "sg:phone":"+34 972 51 31 82",
    "sg:postcode":"17600",
    "sg:province":"Girona",
    "wof:name":"Avis Alquile Un Coche S.a.",
    "wof:placetype":"venue"
},
  "geometry": {"coordinates":[2.9676458836,42.2650680542],"type":"Point"}
}