{
  "type": "Feature",
  "properties": {
    "iso:country":"ES",
    "sg:address":"Calle de General Diaz Porlier, 84",
    "sg:city":"Madrid",
    "sg:orig_category":"Transportes Mar\u00cdtimos",
    "sg:phone":"+34 913 09 13 35",
    "sg:postcode":"28006",
    "sg:province":"Madrid",
    "wof:name":"Martankers I S.l.",
    "wof:placetype":"venue"
},
  "geometry": {"coordinates":[-3.6762149334,40.4348373413],"type":"Point"}
}