{
  "type": "Feature",
  "properties": {
    "addr:full":"Carrer de Gambo, 6 Benidorm Alicante 03500",
    "addr:housenumber":"6",
    "addr:postcode":"03500",
    "addr:street":"Carrer De Gambo",
    "iso:country":"ES",
    "sg:address":"Carrer de Gambo, 6",
    "sg:city":"Benidorm",
    "sg:orig_category":"Abogados",
    "sg:phone":"+34 966 80 49 52",
    "sg:postcode":"03500",
    "sg:province":"Alicante",
    "wof:name":"Valor Gil Adolfo",
    "wof:placetype":"venue"
},
  "geometry": {"coordinates":[-0.1279319972,38.5369796753],"type":"Point"}
}