{
  "type": "Feature",
  "properties": {
    "iso:country":"ES",
    "sg:address":"Calle de Polvoranca, 37",
    "sg:city":"Humanes De Madrid",
    "sg:orig_category":"Chapister\u00cda",
    "sg:phone":"+34 916 04 07 56",
    "sg:postcode":"28970",
    "sg:province":"Madrid",
    "wof:name":"Talleres Gutisan S.l.",
    "wof:placetype":"venue"
},
  "geometry": {"coordinates":[-3.8262693882,40.2556266785],"type":"Point"}
}