{
  "type": "Feature",
  "properties": {
    "iso:country":"ES",
    "sg:address":"Calle de Daniel Defoe, 18",
    "sg:city":"Malaga",
    "sg:orig_category":"Electricidad: Instaladores",
    "sg:phone":"+34 952 02 32 78",
    "sg:postcode":"29006",
    "sg:province":"M\u00e1laga",
    "wof:name":"Doblas Viso Francisco Rafael",
    "wof:placetype":"venue"
},
  "geometry": {"coordinates":[-4.4644088745,36.7114105225],"type":"Point"}
}