{
  "type": "Feature",
  "properties": {
    "addr:full":"Carrer de Severo Ochoa, 47 Terrassa Barcelona 08224",
    "addr:housenumber":"47",
    "addr:postcode":"08224",
    "addr:street":"Carrer De Severo Ochoa",
    "iso:country":"ES",
    "sg:address":"Carrer de Severo Ochoa, 47",
    "sg:city":"Terrassa",
    "sg:orig_category":"Reposter\u00cdas",
    "sg:phone":"+34 937 80 51 63",
    "sg:postcode":"08224",
    "sg:province":"Barcelona",
    "wof:name":"Fleques Zoe S.l.",
    "wof:placetype":"venue"
},
  "geometry": {"coordinates":[2.0008590221,41.5628623962],"type":"Point"}
}