{
  "type": "Feature",
  "properties": {
    "addr:full":"Rua Zamora, 75 Vigo Pontevedra 36211",
    "addr:housenumber":"75",
    "addr:postcode":"36211",
    "addr:street":"Rua Zamora",
    "iso:country":"ES",
    "sg:address":"Rua Zamora, 75",
    "sg:city":"Vigo",
    "sg:orig_category":"Agencias Y Agentes Comerciales, Representantes",
    "sg:phone":"+34 986 48 54 53",
    "sg:postcode":"36211",
    "sg:province":"Pontevedra",
    "wof:name":"Promociones Poza Real S.l.",
    "wof:placetype":"venue"
},
  "geometry": {"coordinates":[-8.7259616852,42.22290802],"type":"Point"}
}