{
  "type": "Feature",
  "properties": {
    "addr:full":"Rua Flor, 7 Cee La Coru\u00f1a 15270",
    "addr:housenumber":"7",
    "addr:postcode":"15270",
    "addr:street":"Rua Flor",
    "iso:country":"ES",
    "sg:address":"Rua Flor, 7",
    "sg:city":"Cee",
    "sg:orig_category":"Alquiler De V\u00cddeo",
    "sg:phone":"+34 981 74 67 40",
    "sg:postcode":"15270",
    "sg:province":"La Coru\u00f1a",
    "wof:name":"Lago Freire Tomas",
    "wof:placetype":"venue"
},
  "geometry": {"coordinates":[-9.1880493164,42.9557304382],"type":"Point"}
}