{
  "type": "Feature",
  "properties": {
    "iso:country":"ES",
    "sg:address":"Calle de Escofina, 22",
    "sg:city":"Estacion",
    "sg:orig_category":"Mudanzas",
    "sg:phone":"+34 918 49 13 65",
    "sg:postcode":"28400",
    "sg:province":"Madrid",
    "sg:website":"www.mudanzasramirez.com",
    "wof:name":"Gesteca Gestion S.l.",
    "wof:placetype":"venue"
},
  "geometry": {"coordinates":[-4.0194787979,40.6284141541],"type":"Point"}
}