{
  "type": "Feature",
  "properties": {
    "addr:full":"Calle de Liebre, 117 Malaga M\u00e1laga 29018",
    "addr:housenumber":"117",
    "addr:postcode":"29018",
    "addr:street":"Calle De Liebre;Ma\u0301Laga",
    "iso:country":"ES",
    "sg:address":"Calle de Liebre, 117",
    "sg:city":"Malaga",
    "sg:orig_category":"Art\u00cdculos M\u00c9dicos",
    "sg:phone":"+34 952 20 35 52",
    "sg:postcode":"29018",
    "sg:province":"M\u00e1laga",
    "wof:name":"Drf S.l.",
    "wof:placetype":"venue"
},
  "geometry": {"coordinates":[-4.3795418739,36.7372627258],"type":"Point"}
}