{
  "type": "Feature",
  "properties": {
    "iso:country":"ES",
    "sg:address":"Calle de Maestro Guerrero, 5",
    "sg:city":"Ugena",
    "sg:orig_category":"Empresas De Demolici\u00d3n",
    "sg:phone":"+34 925 53 35 73",
    "sg:postcode":"45217",
    "sg:province":"Toledo",
    "sg:website":"www.hidrodem.com",
    "wof:name":"Hidrodemolicion S A",
    "wof:placetype":"venue"
},
  "geometry": {"coordinates":[-3.8795590401,40.15832901],"type":"Point"}
}