{
  "type": "Feature",
  "properties": {
    "iso:country":"ES",
    "sg:address":"Calle de Pintor Gisbert, 7",
    "sg:city":"Alacant",
    "sg:orig_category":"Supermercados Y Hipermercados",
    "sg:phone":"+34 965 12 37 89",
    "sg:postcode":"03005",
    "sg:province":"Alicante",
    "wof:name":"Raferti S.l.",
    "wof:placetype":"venue"
},
  "geometry": {"coordinates":[-0.4943599999,38.3483314514],"type":"Point"}
}