{
  "type": "Feature",
  "properties": {
    "iso:country":"ES",
    "sg:address":"Barr A Moscadeira, S/n",
    "sg:city":"Ponteareas",
    "sg:orig_category":"Internados & Ense\u00d1anza Privada",
    "sg:phone":"+34 986 64 01 12",
    "sg:postcode":"36860",
    "sg:province":"Pontevedra",
    "wof:name":"Colegio Santiago Apostol De Puenteareas",
    "wof:placetype":"venue"
},
  "geometry": {"coordinates":[-8.5106678009,42.1751213074],"type":"Point"}
}