{
  "type": "Feature",
  "properties": {
    "addr:full":"Calle de Morote, 23 Huescar Granada 18830",
    "addr:housenumber":"23",
    "addr:postcode":"18830",
    "addr:street":"Calle De Morote",
    "iso:country":"ES",
    "sg:address":"Calle de Morote, 23",
    "sg:city":"Huescar",
    "sg:orig_category":"Ropa Para Se\u00d1oras (al Por Menor)",
    "sg:phone":"+34 958 74 16 18",
    "sg:postcode":"18830",
    "sg:province":"Granada",
    "wof:name":"Manteca Marquez Antonia",
    "wof:placetype":"venue"
},
  "geometry": {"coordinates":[-2.5417699814,37.8088188171],"type":"Point"}
}