{
  "type": "Feature",
  "properties": {
    "addr:full":"El Remedio, 2 S. Vicente Sonsierra La Rioja 26338",
    "addr:housenumber":"2",
    "addr:postcode":"26338",
    "addr:street":"El Remedio;S. Vicente Sonsierra;Rioja",
    "iso:country":"ES",
    "sg:address":"El Remedio, 2",
    "sg:city":"S. Vicente Sonsierra",
    "sg:orig_category":"Asociaciones, Organismos Culturales Y Socioeducativos",
    "sg:phone":"+34 941 30 80 78",
    "sg:postcode":"26338",
    "sg:province":"La Rioja",
    "wof:name":"Sociedad Recreativa Hogar Del Jubilado",
    "wof:placetype":"venue"
},
  "geometry": {"coordinates":[-2.7586228848,42.5630340576],"type":"Point"}
}