{
  "type": "Feature",
  "properties": {
    "addr:full":"Calle de Risquillo Bajo, 5 Ubeda Ja\u00e9n 23400",
    "addr:housenumber":"5",
    "addr:postcode":"23400",
    "addr:street":"Calle De Risquillo Bajo;Jae\u0301N",
    "iso:country":"ES",
    "sg:address":"Calle de Risquillo Bajo, 5",
    "sg:city":"Ubeda",
    "sg:orig_category":"Peluqueros: De Se\u00d1oras",
    "sg:phone":"+34 953 79 02 52",
    "sg:postcode":"23400",
    "sg:province":"Ja\u00e9n",
    "wof:name":"Salas Esquina Manuela",
    "wof:placetype":"venue"
},
  "geometry": {"coordinates":[-3.3659939766,38.016998291],"type":"Point"}
}