{
  "type": "Feature",
  "properties": {
    "iso:country":"ES",
    "sg:address":"Calle de Churruca, 41",
    "sg:city":"Alacant",
    "sg:orig_category":"Zapater\u00cdas",
    "sg:phone":"+34 965 92 29 63",
    "sg:postcode":"03003",
    "sg:province":"Alicante",
    "wof:name":"Nure S.l.",
    "wof:placetype":"venue"
},
  "geometry": {"coordinates":[-0.4937235117,38.3426132202],"type":"Point"}
}