{
  "type": "Feature",
  "properties": {
    "iso:country":"ES",
    "sg:address":"Calle de Tejares, 61",
    "sg:city":"Albacete",
    "sg:orig_category":"Inmobiliaria (agencias)",
    "sg:phone":"+34 967 22 96 59",
    "sg:postcode":"02002",
    "sg:province":"Albacete",
    "wof:name":"Aprovechamientos Cinegeticos S.l",
    "wof:placetype":"venue"
},
  "geometry": {"coordinates":[-1.8537751436,38.9888725281],"type":"Point"}
}