{
  "type": "Feature",
  "properties": {
    "addr:full":"Ameijenda, S/n Cee La Coru\u00f1a 15270",
    "addr:postcode":"15270",
    "addr:street":"Ameijenda S / N;La",
    "iso:country":"ES",
    "sg:address":"Ameijenda, S/n",
    "sg:city":"Cee",
    "sg:classifiers":[
        {
            "category":"Taxi",
            "type":"Transportation"
        }
    ],
    "sg:phone":"+34 981 74 70 03",
    "sg:postcode":"15270",
    "sg:province":"La Coru\u00f1a",
    "wof:name":"Castro Caama\u00f1o Emilio",
    "wof:placetype":"venue"
},
  "geometry": {"coordinates":[-9.187494278,42.9554710388],"type":"Point"}
}