{
  "type": "Feature",
  "properties": {
    "iso:country":"ES",
    "sg:address":"Carr Sequia De Rascanya, 20",
    "sg:city":"Picanya",
    "sg:orig_category":"Comercio De Piezas De Recambio Y De Accesorios De Veh\u00cdculos, Veh\u00cdculos Industriales",
    "sg:phone":"+34 961 59 05 66",
    "sg:postcode":"46210",
    "sg:province":"Valencia",
    "wof:name":"Distribuciones Electricas Auto-industrias S.l.",
    "wof:placetype":"venue"
},
  "geometry": {"coordinates":[-0.4267579913,39.4406166077],"type":"Point"}
}