{
  "type": "Feature",
  "properties": {
    "addr:full":"Carrer de Alt, 6 Vendrell Tarragona 43700",
    "addr:housenumber":"6",
    "addr:postcode":"43700",
    "addr:street":"Carrer De Alt",
    "iso:country":"ES",
    "sg:address":"Carrer de Alt, 6",
    "sg:city":"Vendrell",
    "sg:orig_category":"Ropa Para Se\u00d1oras (al Por Menor)",
    "sg:phone":"+34 977 66 77 62",
    "sg:postcode":"43700",
    "sg:province":"Tarragona",
    "wof:name":"Iglesias Gomez Maria Guadalupe",
    "wof:placetype":"venue"
},
  "geometry": {"coordinates":[1.5351040363,41.2205276489],"type":"Point"}
}