{
  "type": "Feature",
  "properties": {
    "iso:country":"ES",
    "sg:address":"Trva Barrio Del Salobrar, S/n",
    "sg:city":"Jaraiz Vera",
    "sg:orig_category":"Mec\u00c1nico Del Autom\u00d3vil",
    "sg:phone":"+34 927 46 10 20",
    "sg:postcode":"10400",
    "sg:province":"C\u00e1ceres",
    "wof:name":"Amador Cilleros Jacinto",
    "wof:placetype":"venue"
},
  "geometry": {"coordinates":[-6.3707604408,39.4761772156],"type":"Point"}
}