{
  "type": "Feature",
  "properties": {
    "iso:country":"ES",
    "sg:address":"Av Vidreres, 163",
    "sg:city":"Lloret Mar",
    "sg:orig_category":"Plomeros",
    "sg:phone":"+34 972 36 84 29",
    "sg:postcode":"17310",
    "sg:province":"Girona",
    "wof:name":"Comas Baltrons Antonio",
    "wof:placetype":"venue"
},
  "geometry": {"coordinates":[2.8418300152,41.7077102661],"type":"Point"}
}