{
  "type": "Feature",
  "properties": {
    "iso:country":"ES",
    "sg:address":"O Outeiro, 9",
    "sg:city":"Amorin",
    "sg:orig_category":"Perfumer\u00cda Y Cosm\u00c9tica (fabricaci\u00d3n, Al Por Mayor)",
    "sg:phone":"+34 986 63 36 63",
    "sg:postcode":"36730",
    "sg:province":"Pontevedra",
    "wof:name":"Ferlain Cosmetica S.l.",
    "wof:placetype":"venue"
},
  "geometry": {"coordinates":[-8.7277517319,41.9853744507],"type":"Point"}
}