{
  "type": "Feature",
  "properties": {
    "addr:full":"Carrer de Gremi De Sabaters, 55 Poligon Industrial De Son Castello Islas Baleares 07009",
    "addr:housenumber":"55",
    "addr:postcode":"07009",
    "addr:street":"Carrer De Gremi De Sabaters;Islas",
    "iso:country":"ES",
    "sg:address":"Carrer de Gremi De Sabaters, 55",
    "sg:city":"Poligon Industrial De Son Castello",
    "sg:orig_category":"Aceros Inoxidables",
    "sg:phone":"+34 971 20 84 25",
    "sg:postcode":"07009",
    "sg:province":"Islas Baleares",
    "wof:name":"Garrigo Metales S.a.",
    "wof:placetype":"venue"
},
  "geometry": {"coordinates":[2.6639704704,39.605342865],"type":"Point"}
}