{
  "type": "Feature",
  "properties": {
    "addr:full":"Pol Ind Juan Carlos I, S/n Almussafes Valencia 46440",
    "addr:housenumber":"s / n",
    "addr:postcode":"46440",
    "addr:street":"Carlos I",
    "iso:country":"ES",
    "sg:address":"Pol Ind Juan Carlos I, S/n",
    "sg:city":"Almussafes",
    "sg:orig_category":"Transportes Internacionales",
    "sg:phone":"+34 961 78 83 80",
    "sg:postcode":"46440",
    "sg:province":"Valencia",
    "wof:name":"Westermann Espa\u00d1a S.a.",
    "wof:placetype":"venue"
},
  "geometry": {"coordinates":[-0.4078058004,39.28358078],"type":"Point"}
}