{
  "type": "Feature",
  "properties": {
    "iso:country":"ES",
    "sg:address":"Calle de San Isidro, 52",
    "sg:city":"Molina Segura",
    "sg:orig_category":"Centros Empresariales",
    "sg:phone":"+34 968 64 29 48",
    "sg:postcode":"30500",
    "sg:province":"Murcia",
    "wof:name":"Hernandez Garcia Francisco",
    "wof:placetype":"venue"
},
  "geometry": {"coordinates":[-1.2078210115,38.0588645935],"type":"Point"}
}