{
  "type": "Feature",
  "properties": {
    "addr:full":"Carrer de Sardenya, 37 Barcelona Barcelona 08005",
    "addr:housenumber":"37",
    "addr:postcode":"08005",
    "addr:street":"Carrer De Sardenya",
    "iso:country":"ES",
    "sg:address":"Carrer de Sardenya, 37",
    "sg:city":"Barcelona",
    "sg:orig_category":"Alimentaci\u00d3n General (al Por Menor)",
    "sg:phone":"+34 932 21 17 38",
    "sg:postcode":"08005",
    "sg:province":"Barcelona",
    "wof:name":"Lezcano Mella Pilar",
    "wof:placetype":"venue"
},
  "geometry": {"coordinates":[2.1888360977,41.3914756775],"type":"Point"}
}