{
  "type": "Feature",
  "properties": {
    "addr:full":"Carrer de Roger De Lluria, 6 Bassioles Barcelona 08759",
    "addr:housenumber":"6",
    "addr:postcode":"08759",
    "addr:street":"Carrer De Roger De Lluria;Barcelona",
    "iso:country":"ES",
    "sg:address":"Carrer de Roger De Lluria, 6",
    "sg:city":"Bassioles",
    "sg:orig_category":"Electricidad: Instaladores",
    "sg:phone":"+34 936 83 12 35",
    "sg:postcode":"08759",
    "sg:province":"Barcelona",
    "wof:name":"Suministros E Instalaciones Vallirana S.",
    "wof:placetype":"venue"
},
  "geometry": {"coordinates":[1.8953200579,41.3680915833],"type":"Point"}
}