{
  "type": "Feature",
  "properties": {
    "addr:full":"Carrer de Capcir, 15 Barcelona Barcelona 08035",
    "addr:housenumber":"15",
    "addr:postcode":"08035",
    "addr:street":"Carrer De Capcir",
    "iso:country":"ES",
    "sg:address":"Carrer de Capcir, 15",
    "sg:city":"Barcelona",
    "sg:orig_category":"Molduras, Junquillos, Listones Y Molduras Perforadas",
    "sg:phone":"+34 934 29 27 55",
    "sg:postcode":"08035",
    "sg:province":"Barcelona",
    "wof:name":"Manzanares Brioso Antonio",
    "wof:placetype":"venue"
},
  "geometry": {"coordinates":[2.1507520676,41.4268684387],"type":"Point"}
}