{
  "type": "Feature",
  "properties": {
    "iso:country":"ES",
    "sg:address":"Pla\u00c7 Catalunya, 2",
    "sg:city":"Poal",
    "sg:orig_category":"Doctores En Medicina",
    "sg:phone":"+34 973 56 56 60",
    "sg:postcode":"25143",
    "sg:province":"Lleida",
    "wof:name":"Garcia Deza Jose Maria",
    "wof:placetype":"venue"
},
  "geometry": {"coordinates":[0.856850028,41.6762161255],"type":"Point"}
}