{
  "type": "Feature",
  "properties": {
    "addr:full":"Pg Sant Joan, 22 Barcelona Barcelona 08010",
    "addr:housenumber":"22",
    "addr:postcode":"08010",
    "addr:street":"Pg Sant Joan",
    "iso:country":"ES",
    "sg:address":"Pg Sant Joan, 22",
    "sg:city":"Barcelona",
    "sg:orig_category":"Confecci\u00d3n De Trajes Para Se\u00d1oras",
    "sg:phone":"+34 932 44 40 28",
    "sg:postcode":"08010",
    "sg:province":"Barcelona",
    "wof:name":"Mediano Vizuete Felix",
    "wof:placetype":"venue"
},
  "geometry": {"coordinates":[2.1787970066,41.3926277161],"type":"Point"}
}