{
  "type": "Feature",
  "properties": {
    "iso:country":"ES",
    "sg:address":"Carr Major, 6",
    "sg:city":"Espluga Calba",
    "sg:orig_category":"Supermercados Y Hipermercados",
    "sg:phone":"+34 973 15 60 74",
    "sg:postcode":"25410",
    "sg:province":"Lleida",
    "wof:name":"Gaya Ribes Miquel",
    "wof:placetype":"venue"
},
  "geometry": {"coordinates":[1.0044250488,41.4963111877],"type":"Point"}
}