{
  "type": "Feature",
  "properties": {
    "addr:full":"Valdemuel, S/n Epila Zaragoza 50290",
    "addr:postcode":"50290",
    "addr:street":"Valdemuel S / N Epila",
    "iso:country":"ES",
    "sg:address":"Valdemuel, S/n",
    "sg:city":"Epila",
    "sg:orig_category":"Empresas De Carpinter\u00cda",
    "sg:phone":"+34 976 60 42 77",
    "sg:postcode":"50290",
    "sg:province":"Zaragoza",
    "wof:name":"Carpinteria Metalica Rocal S.l.",
    "wof:placetype":"venue"
},
  "geometry": {"coordinates":[-1.2849140167,41.6030502319],"type":"Point"}
}