{
  "type": "Feature",
  "properties": {
    "iso:country":"ES",
    "sg:address":"Calle de Santander, 6",
    "sg:city":"Polan",
    "sg:orig_category":"Trabajos De Perforaciones, Sondeos, Construcci\u00d3n De Pozos",
    "sg:phone":"+34 925 37 05 87",
    "sg:postcode":"45161",
    "sg:province":"Toledo",
    "wof:name":"Jimenez Lorente Margarita",
    "wof:placetype":"venue"
},
  "geometry": {"coordinates":[-4.2538452148,39.8007354736],"type":"Point"}
}