{
  "type": "Feature",
  "properties": {
    "iso:country":"ES",
    "sg:address":"Calle de Kapelamendi, 1",
    "sg:city":"Vitoria-gasteiz",
    "sg:orig_category":"Rectificaci\u00d3n, Mecanizado, Fresado",
    "sg:phone":"+34 945 25 75 99",
    "sg:postcode":"01013",
    "sg:province":"\u00c1lava",
    "wof:name":"Mecanizados Lera Sl",
    "wof:placetype":"venue"
},
  "geometry": {"coordinates":[-2.6447188854,42.8688049316],"type":"Point"}
}