{
  "type": "Feature",
  "properties": {
    "iso:country":"ES",
    "sg:address":"Estda. Nal. Seiscientos Cuarenta, S/n",
    "sg:city":"Arcos",
    "sg:orig_category":"Transportes Por Carretera: Lotes Completos, Mercanc\u00cdas Diversas",
    "sg:phone":"+34 986 54 81 00",
    "sg:postcode":"36677",
    "sg:province":"Pontevedra",
    "wof:name":"Bujan Carbia Higinio",
    "wof:placetype":"venue"
},
  "geometry": {"coordinates":[-8.551858902,42.6542053223],"type":"Point"}
}