{
  "type": "Feature",
  "properties": {
    "addr:full":"Calle de San Bartolome, 6 Donostia-san Sebastian Guip\u00f9zcoa 20007",
    "addr:housenumber":"6",
    "addr:postcode":"20007",
    "addr:street":"Calle De San Bartolome",
    "iso:country":"ES",
    "sg:address":"Calle de San Bartolome, 6",
    "sg:city":"Donostia-san Sebastian",
    "sg:orig_category":"Librer\u00cdas",
    "sg:phone":"+34 943 42 15 06",
    "sg:postcode":"20007",
    "sg:province":"Guip\u00f9zcoa",
    "wof:name":"Maria Pilar Arenas Hernandez",
    "wof:placetype":"venue"
},
  "geometry": {"coordinates":[-1.9828419685,43.3165588379],"type":"Point"}
}