{
  "type": "Feature",
  "properties": {
    "iso:country":"ES",
    "sg:address":"Calle de Navarro Villoslada, 2",
    "sg:city":"Bilbao",
    "sg:orig_category":"Electricidad: Instaladores",
    "sg:phone":"+34 944 05 34 99",
    "sg:postcode":"48015",
    "sg:province":"Vizcaya",
    "wof:name":"Electricidad Larrako S. L.",
    "wof:placetype":"venue"
},
  "geometry": {"coordinates":[-2.9610309601,43.2767333984],"type":"Point"}
}