{
  "type": "Feature",
  "properties": {
    "addr:full":"Cno. Vell Bunyola, 29 Pol.ind.son Castello Islas Baleares 07009",
    "addr:housenumber":"29",
    "addr:postcode":"07009",
    "addr:street":"Cno. Vell Bunyola;Islas",
    "iso:country":"ES",
    "sg:address":"Cno. Vell Bunyola, 29",
    "sg:city":"Pol.ind.son Castello",
    "sg:orig_category":"Ense\u00d1anza, Formaci\u00d3n Profesional: Aprendizaje",
    "sg:phone":"+34 971 75 42 45",
    "sg:postcode":"07009",
    "sg:province":"Islas Baleares",
    "wof:name":"Productos Fontanet S.a.",
    "wof:placetype":"venue"
},
  "geometry": {"coordinates":[2.6776249409,39.6072845459],"type":"Point"}
}