{
  "type": "Feature",
  "properties": {
    "iso:country":"ES",
    "sg:address":"Rua San Paio, 164",
    "sg:city":"Quintela",
    "sg:orig_category":"Molduras, Junquillos, Listones Y Molduras Perforadas",
    "sg:phone":"+34 986 24 02 30",
    "sg:postcode":"36212",
    "sg:province":"Pontevedra",
    "wof:name":"Gandara Fernandez Manuel Eugenio",
    "wof:placetype":"venue"
},
  "geometry": {"coordinates":[-8.7656679153,42.2123451233],"type":"Point"}
}