{
  "type": "Feature",
  "properties": {
    "addr:full":"Calle de Gandia, 3 Madrid Madrid 28007",
    "addr:housenumber":"3",
    "addr:postcode":"28007",
    "addr:street":"Calle De Gandia",
    "iso:country":"ES",
    "sg:address":"Calle de Gandia, 3",
    "sg:city":"Madrid",
    "sg:orig_category":"M\u00c1quinas De Escribir, M\u00c1quinas De Oficina (al Por Menor, Reparaci\u00d3n)",
    "sg:phone":"+34 914 33 00 40",
    "sg:postcode":"28007",
    "sg:province":"Madrid",
    "sg:website":"www.sistemsl.com",
    "wof:name":"Sistemas De Mecanizacion De Oficinas S.l.",
    "wof:placetype":"venue"
},
  "geometry": {"coordinates":[-3.6715199947,40.3984375],"type":"Point"}
}