{
  "type": "Feature",
  "properties": {
    "iso:country":"ES",
    "sg:address":"Calle de Juan Van-halen, 1",
    "sg:city":"Torrelodones",
    "sg:orig_category":"Piscinas, Accesorios, Suministros (fabricaci\u00d3n, Al Por Mayor)",
    "sg:phone":"+34 918 59 34 95",
    "sg:postcode":"28250",
    "sg:province":"Madrid",
    "wof:name":"C.d.piscinas Almansa S.l.",
    "wof:placetype":"venue"
},
  "geometry": {"coordinates":[-3.9284780025,40.5772094727],"type":"Point"}
}