{
  "type": "Feature",
  "properties": {
    "addr:full":"Avda Canarias, 120 Vecindario Las Palmas 35110",
    "addr:housenumber":"120",
    "addr:postcode":"35110",
    "addr:street":"Avda Canarias;Palmas",
    "iso:country":"ES",
    "sg:address":"Avda Canarias, 120",
    "sg:city":"Vecindario",
    "sg:orig_category":"Ropa Para Se\u00d1oras Y Caballeros (al Por Menor)",
    "sg:phone":"+34 928 75 53 44",
    "sg:postcode":"35110",
    "sg:province":"Las Palmas",
    "wof:name":"Matos Medina Jose",
    "wof:placetype":"venue"
},
  "geometry": {"coordinates":[-15.4406194687,27.8517799377],"type":"Point"}
}