{
  "type": "Feature",
  "properties": {
    "iso:country":"ES",
    "sg:address":"Calle de Serrablo (de), 120",
    "sg:city":"Sabi\u00f1anigo",
    "sg:orig_category":"Agentes, Concesionarios Y Sucursales De Veh\u00cdculos",
    "sg:phone":"+34 974 48 00 79",
    "sg:postcode":"22600",
    "sg:province":"Huesca",
    "wof:name":"Lanuza Oros Florencio",
    "wof:placetype":"venue"
},
  "geometry": {"coordinates":[-0.3615950048,42.5198631287],"type":"Point"}
}