{
  "type": "Feature",
  "properties": {
    "addr:full":"Calle de Buenaventura Bonnet, 14 Santa Cruz De Tenerife Santa Cruz De Tenerife 38008",
    "addr:housenumber":"14",
    "addr:postcode":"38008",
    "addr:street":"Calle De Buenaventura Bonnet",
    "iso:country":"ES",
    "sg:address":"Calle de Buenaventura Bonnet, 14",
    "sg:city":"Santa Cruz De Tenerife",
    "sg:orig_category":"Productos Qu\u00cdmicos (fabricaci\u00d3n, Al Por Mayor)",
    "sg:phone":"+34 922 29 43 83",
    "sg:postcode":"38008",
    "sg:province":"Santa Cruz De Tenerife",
    "wof:name":"Sanicheck S.l.",
    "wof:placetype":"venue"
},
  "geometry": {"coordinates":[-16.2728710175,28.4668731689],"type":"Point"}
}