{
  "type": "Feature",
  "properties": {
    "addr:full":"Cant San Francisco Javier, 10 Vitoria-gasteiz \u00c1lava 01001",
    "addr:housenumber":"10",
    "addr:postcode":"01001",
    "addr:street":"Cant San Francisco Javier",
    "iso:country":"ES",
    "sg:address":"Cant San Francisco Javier, 10",
    "sg:city":"Vitoria-gasteiz",
    "sg:orig_category":"Bisuter\u00cda, Joyer\u00cda, Relojer\u00cda (al Por Menor)",
    "sg:phone":"+34 945 25 42 01",
    "sg:postcode":"01001",
    "sg:province":"\u00c1lava",
    "wof:name":"Barcena Llano Jose Manuel",
    "wof:placetype":"venue"
},
  "geometry": {"coordinates":[-2.6700270176,42.848865509],"type":"Point"}
}