{
  "type": "Feature",
  "properties": {
    "iso:country":"ES",
    "sg:address":"Calle de Santa Lucia, 7",
    "sg:city":"Madrid",
    "sg:orig_category":"Artes Gr\u00c1ficas, Artes Pl\u00c1sticas (curso)",
    "sg:phone":"+34 915 22 17 11",
    "sg:postcode":"28004",
    "sg:province":"Madrid",
    "wof:name":"Graficas Jostom S.l.",
    "wof:placetype":"venue"
},
  "geometry": {"coordinates":[-3.7052268982,40.4254989624],"type":"Point"}
}