{
  "type": "Feature",
  "properties": {
    "addr:full":"Avda Cantabria, 52 Burgos Burgos 09006",
    "addr:housenumber":"52",
    "addr:postcode":"09006",
    "addr:street":"Avda Cantabria",
    "iso:country":"ES",
    "sg:address":"Avda Cantabria, 52",
    "sg:city":"Burgos",
    "sg:orig_category":"Agentes, Concesionarios Y Sucursales De Camiones Y Veh\u00cdculos Industriales",
    "sg:phone":"+34 947 22 38 03",
    "sg:postcode":"09006",
    "sg:province":"Burgos",
    "wof:name":"Diaz Espartosa Eloy",
    "wof:placetype":"venue"
},
  "geometry": {"coordinates":[-3.6915121078,42.3549232483],"type":"Point"}
}