{
  "type": "Feature",
  "properties": {
    "iso:country":"ES",
    "sg:address":"Av Roma, 49",
    "sg:city":"Manlleu",
    "sg:orig_category":"Reposter\u00cdas",
    "sg:phone":"+34 938 51 43 50",
    "sg:postcode":"08560",
    "sg:province":"Barcelona",
    "wof:name":"Forn De Pa Altarriba S.l.",
    "wof:placetype":"venue"
},
  "geometry": {"coordinates":[2.2883899212,42.0050392151],"type":"Point"}
}