{
  "type": "Feature",
  "properties": {
    "iso:country":"ES",
    "sg:address":"Cust Raqueta, 10",
    "sg:city":"Salamanca",
    "sg:orig_category":"Ense\u00d1anza: Comercio, Gesti\u00d3n, Inform\u00c1tica",
    "sg:phone":"+34 923 28 15 16",
    "sg:postcode":"37001",
    "sg:province":"Salamanca",
    "wof:name":"Crespo Ruano Millan",
    "wof:placetype":"venue"
},
  "geometry": {"coordinates":[-5.6582632065,40.9673843384],"type":"Point"}
}