{
  "type": "Feature",
  "properties": {
    "addr:full":"Rua Montero Rios, 28 Lugo Lugo 27002",
    "addr:housenumber":"28",
    "addr:postcode":"27002",
    "addr:street":"Rua Montero Rios",
    "iso:country":"ES",
    "sg:address":"Rua Montero Rios, 28",
    "sg:city":"Lugo",
    "sg:orig_category":"Prot\u00c9sicos Dentales",
    "sg:phone":"+34 982 22 56 66",
    "sg:postcode":"27002",
    "sg:province":"Lugo",
    "wof:name":"Jose Vilaboa Sierra Y Otros Cdad",
    "wof:placetype":"venue"
},
  "geometry": {"coordinates":[-7.5510787964,43.0123596191],"type":"Point"}
}