{
  "type": "Feature",
  "properties": {
    "addr:full":"Carrer de Pi I Margall, 32 Molins Rei Barcelona 08750",
    "addr:housenumber":"32",
    "addr:postcode":"08750",
    "addr:street":"Carrer De Pi I Margall;Barcelona",
    "iso:country":"ES",
    "sg:address":"Carrer de Pi I Margall, 32",
    "sg:city":"Molins Rei",
    "sg:orig_category":"Perfumer\u00cda Y Cosm\u00c9tica (fabricaci\u00d3n, Al Por Mayor)",
    "sg:phone":"+34 936 68 27 32",
    "sg:postcode":"08750",
    "sg:province":"Barcelona",
    "wof:name":"Comercial Lomark S.c.p.",
    "wof:placetype":"venue"
},
  "geometry": {"coordinates":[2.018846035,41.4093551636],"type":"Point"}
}