{
  "type": "Feature",
  "properties": {
    "iso:country":"ES",
    "sg:address":"Avda Doctor Espinosa, 15",
    "sg:city":"Puebla Cazalla",
    "sg:orig_category":"Farmacias",
    "sg:phone":"+34 955 84 39 75",
    "sg:postcode":"41540",
    "sg:province":"Sevilla",
    "wof:name":"Lopez Correa Alfonso",
    "wof:placetype":"venue"
},
  "geometry": {"coordinates":[-5.3161640167,37.2219696045],"type":"Point"}
}