{
  "type": "Feature",
  "properties": {
    "iso:country":"ES",
    "sg:address":"Calle de Fueros, 26",
    "sg:city":"Vitoria-gasteiz",
    "sg:orig_category":"Moda",
    "sg:phone":"+34 945 23 05 01",
    "sg:postcode":"01005",
    "sg:province":"\u00c1lava",
    "wof:name":"Arrizabalaga Arregui Maria Carmen",
    "wof:placetype":"venue"
},
  "geometry": {"coordinates":[-2.6703321934,42.8421859741],"type":"Point"}
}