{
  "type": "Feature",
  "properties": {
    "iso:country":"ES",
    "sg:address":"Avda Virgen De Gracia, 52",
    "sg:city":"Oliva Frontera",
    "sg:orig_category":"Cr\u00cda De Animales",
    "sg:phone":"+34 924 74 03 05",
    "sg:postcode":"06120",
    "sg:province":"Badajoz",
    "wof:name":"Diaz Rangel Valeriano",
    "wof:placetype":"venue"
},
  "geometry": {"coordinates":[-6.9213290215,38.2791786194],"type":"Point"}
}