{
  "type": "Feature",
  "properties": {
    "iso:country":"ES",
    "sg:address":"Calle de Pio Baroja, 34",
    "sg:city":"Sax",
    "sg:orig_category":"Inform\u00c1tica: Material Y Suministros",
    "sg:phone":"+34 965 47 43 33",
    "sg:postcode":"03630",
    "sg:province":"Alicante",
    "wof:name":"Gil Richarte Mariano",
    "wof:placetype":"venue"
},
  "geometry": {"coordinates":[-0.8191769719,38.5358161926],"type":"Point"}
}