{
  "type": "Feature",
  "properties": {
    "addr:full":"Partida Els Rincons, 2 Rincons Valencia 46185",
    "addr:housenumber":"2",
    "addr:postcode":"46185",
    "addr:street":"Partida Els Rincons",
    "iso:country":"ES",
    "sg:address":"Partida Els Rincons, 2",
    "sg:city":"Rincons",
    "sg:orig_category":"Molduras, Junquillos, Listones Y Molduras Perforadas",
    "sg:phone":"+34 961 66 22 55",
    "sg:postcode":"46185",
    "sg:province":"Valencia",
    "wof:name":"Mamimar C.b",
    "wof:placetype":"venue"
},
  "geometry": {"coordinates":[-0.5534440279,39.5925750732],"type":"Point"}
}