{
  "type": "Feature",
  "properties": {
    "addr:full":"Carrer de Josep Torras I Bages, 18 Granollers Barcelona 08401",
    "addr:housenumber":"18",
    "addr:postcode":"08401",
    "addr:street":"Carrer De Josep Torras I Bages",
    "iso:country":"ES",
    "sg:address":"Carrer de Josep Torras I Bages, 18",
    "sg:city":"Granollers",
    "sg:orig_category":"Asesor\u00cda Sobre Comunicaci\u00d3n De Empresas",
    "sg:phone":"+34 938 46 73 62",
    "sg:postcode":"08401",
    "sg:province":"Barcelona",
    "wof:name":"A.i.g. Assessoria S.l.",
    "wof:placetype":"venue"
},
  "geometry": {"coordinates":[2.2802755833,41.5911216736],"type":"Point"}
}