{
  "type": "Feature",
  "properties": {
    "addr:full":"Calle de Talud, 27 Villalba Rey Cuenca 16535",
    "addr:housenumber":"27",
    "addr:postcode":"16535",
    "addr:street":"Calle De Talud;Rey",
    "iso:country":"ES",
    "sg:address":"Calle de Talud, 27",
    "sg:city":"Villalba Rey",
    "sg:orig_category":"Aceites Y Grasas Alimentarias (fabricaci\u00d3n, Al Por Mayor)",
    "sg:phone":"+34 969 37 00 23",
    "sg:postcode":"16535",
    "sg:province":"Cuenca",
    "wof:name":"Hermanos Benito Huete S. L.",
    "wof:placetype":"venue"
},
  "geometry": {"coordinates":[-2.6407051086,40.3441314697],"type":"Point"}
}