{
  "type": "Feature",
  "properties": {
    "iso:country":"ES",
    "sg:address":"Avda Costa, 132",
    "sg:city":"Gijon",
    "sg:orig_category":"Cajas De Ahorro",
    "sg:phone":"+34 985 19 57 58",
    "sg:postcode":"33204",
    "sg:province":"Asturias",
    "sg:website":"www.cajaespana.es",
    "wof:name":"Caja Espa\u00f1a De Inversiones Caja De Ahorros Y Monte De Piedad",
    "wof:placetype":"venue"
},
  "geometry": {"coordinates":[-5.6486887932,43.5365180969],"type":"Point"}
}