{
  "type": "Feature",
  "properties": {
    "addr:full":"Plaz Espa\u00d1a, 13 Villabuena Puente Zamora 49820",
    "addr:housenumber":"13",
    "addr:postcode":"49820",
    "addr:street":"Plaz Espan\u0303A;Puente Zamora",
    "iso:country":"ES",
    "sg:address":"Plaz Espa\u00d1a, 13",
    "sg:city":"Villabuena Puente",
    "sg:orig_category":"Carnicer\u00cdas, Carnicer\u00cdas",
    "sg:phone":"+34 980 60 66 61",
    "sg:postcode":"49820",
    "sg:province":"Zamora",
    "wof:name":"Mayoral Crespo Gregorio",
    "wof:placetype":"venue"
},
  "geometry": {"coordinates":[-5.4064941406,41.3804168701],"type":"Point"}
}