{
  "type": "Feature",
  "properties": {
    "addr:full":"Pase Pisones, 167 Burgos Burgos 09001",
    "addr:housenumber":"167",
    "addr:postcode":"09001",
    "addr:street":"Pase Pisones",
    "iso:country":"ES",
    "sg:address":"Pase Pisones, 167",
    "sg:city":"Burgos",
    "sg:orig_category":"Materias Pl\u00c1sticas: Productos De Consumo Masivo (fabricaci\u00d3n, Al Por Mayor)",
    "sg:phone":"+34 947 27 67 37",
    "sg:postcode":"09001",
    "sg:province":"Burgos",
    "wof:name":"Martin Vadillo Maria Visitacion",
    "wof:placetype":"venue"
},
  "geometry": {"coordinates":[-3.6958930492,42.3234214783],"type":"Point"}
}