{
  "type": "Feature",
  "properties": {
    "iso:country":"ES",
    "sg:address":"Calle de Juan Salcedo Guillen, S/n",
    "sg:city":"Bailen",
    "sg:orig_category":"Asistencia Social",
    "sg:phone":"+34 953 67 32 91",
    "sg:postcode":"23710",
    "sg:province":"Ja\u00e9n",
    "wof:name":"Diputacion Provincial De Jaen",
    "wof:placetype":"venue"
},
  "geometry": {"coordinates":[-3.7812941074,38.0949554443],"type":"Point"}
}