{
  "type": "Feature",
  "properties": {
    "iso:country":"ES",
    "sg:address":"Avda Viveiro (de), 34",
    "sg:city":"Ferreira",
    "sg:orig_category":"Ferreter\u00cda (diversos)",
    "sg:phone":"+34 982 57 40 87",
    "sg:postcode":"27770",
    "sg:province":"Lugo",
    "wof:name":"Hierros Valle De Oro S.l.",
    "wof:placetype":"venue"
},
  "geometry": {"coordinates":[-7.4420590401,43.5536613464],"type":"Point"}
}