{
  "type": "Feature",
  "properties": {
    "iso:country":"ES",
    "sg:address":"Calle de Hermanas Bronte, S/n",
    "sg:city":"Malaga",
    "sg:orig_category":"Ropa Y Accesorios",
    "sg:phone":"+34 952 24 60 73",
    "sg:postcode":"29004",
    "sg:province":"M\u00e1laga",
    "sg:website":"www.americanzone.net",
    "wof:name":"Rubio Augusto Juan Fernando",
    "wof:placetype":"venue"
},
  "geometry": {"coordinates":[-4.4649710655,36.6945724487],"type":"Point"}
}