{
  "type": "Feature",
  "properties": {
    "iso:country":"ES",
    "sg:address":"Plaz Souto (do), 3",
    "sg:city":"Amoeiro",
    "sg:orig_category":"Farmacias",
    "sg:phone":"+34 988 28 10 27",
    "sg:postcode":"32170",
    "sg:province":"Ourense",
    "wof:name":"Guitian Carballal Rosa Maria",
    "wof:placetype":"venue"
},
  "geometry": {"coordinates":[-7.9537911415,42.4101867676],"type":"Point"}
}