{
  "type": "Feature",
  "properties": {
    "iso:country":"ES",
    "sg:address":"Carrer de Novell, 79",
    "sg:city":"Barcelona",
    "sg:orig_category":"Mec\u00c1nico Del Autom\u00d3vil",
    "sg:phone":"+34 934 91 45 43",
    "sg:postcode":"08014",
    "sg:province":"Barcelona",
    "wof:name":"Ferri Sagarra Salvador",
    "wof:placetype":"venue"
},
  "geometry": {"coordinates":[2.1351509094,41.3842277527],"type":"Point"}
}