{
  "type": "Feature",
  "properties": {
    "addr:full":"Calle de Mercado, 2 San Javier Murcia 30730",
    "addr:housenumber":"2",
    "addr:postcode":"30730",
    "addr:street":"Calle De Mercado",
    "iso:country":"ES",
    "sg:address":"Calle de Mercado, 2",
    "sg:city":"San Javier",
    "sg:orig_category":"M\u00c9dicos: Estomatolog\u00cda",
    "sg:phone":"+34 968 19 30 55",
    "sg:postcode":"30730",
    "sg:province":"Murcia",
    "wof:name":"Ortiz Albaladejo Francisco Jose",
    "wof:placetype":"venue"
},
  "geometry": {"coordinates":[-0.8350098729,37.8066215515],"type":"Point"}
}