{
  "type": "Feature",
  "properties": {
    "iso:country":"ES",
    "sg:address":"Avda Martin Palomino, S/n",
    "sg:city":"Plasencia",
    "sg:orig_category":"Alimentaci\u00d3n General (al Por Mayor)",
    "sg:phone":"+34 927 41 74 04",
    "sg:postcode":"10600",
    "sg:province":"C\u00e1ceres",
    "wof:name":"Adrian Sanchez Olmedo Y Jose Luis Sanchez Olmedo C.b.",
    "wof:placetype":"venue"
},
  "geometry": {"coordinates":[-6.1079235077,40.0117225647],"type":"Point"}
}