{
  "type": "Feature",
  "properties": {
    "addr:full":"Calle de Gobela, 18 Arenas -areeta Vizcaya 48930",
    "addr:housenumber":"18;areeta",
    "addr:postcode":"48930",
    "addr:street":"Calle De Gobela",
    "iso:country":"ES",
    "sg:address":"Calle de Gobela, 18",
    "sg:city":"Arenas -areeta",
    "sg:orig_category":"Abogados",
    "sg:phone":"+34 944 63 73 20",
    "sg:postcode":"48930",
    "sg:province":"Vizcaya",
    "wof:name":"Gamero Delgado Ignacio",
    "wof:placetype":"venue"
},
  "geometry": {"coordinates":[-2.6983869076,43.2204284668],"type":"Point"}
}