{
  "type": "Feature",
  "properties": {
    "iso:country":"ES",
    "sg:address":"Carlos Cano, 4",
    "sg:city":"Olivares",
    "sg:orig_category":"Muebles, Minoristas",
    "sg:phone":"+34 954 11 01 33",
    "sg:postcode":"41804",
    "sg:province":"Sevilla",
    "sg:website":"www.muebleshermanosherrera.com",
    "wof:name":"Muebles Hermanos Herrera S.c.",
    "wof:placetype":"venue"
},
  "geometry": {"coordinates":[-6.1536769867,37.418964386],"type":"Point"}
}