{
  "type": "Feature",
  "properties": {
    "addr:full":"Calle de Mimosas Las, S/n Poligono Industrial De Arinaga Las Palmas 35118",
    "addr:postcode":"35118",
    "addr:street":"Calle De Mimosas Las S / N Poligono Industrial De Arinaga Las",
    "iso:country":"ES",
    "sg:address":"Calle de Mimosas Las, S/n",
    "sg:city":"Poligono Industrial De Arinaga",
    "sg:orig_category":"Plomeros",
    "sg:phone":"+34 928 75 72 75",
    "sg:postcode":"35118",
    "sg:province":"Las Palmas",
    "sg:website":"www.saneamientosdoctoral.com",
    "wof:name":"Saneamientos Doctoral S.l.",
    "wof:placetype":"venue"
},
  "geometry": {"coordinates":[-15.4319887161,27.8808555603],"type":"Point"}
}