{
  "type": "Feature",
  "properties": {
    "iso:country":"ES",
    "sg:address":"Calle de Padre Manjon, 14",
    "sg:city":"Elda",
    "sg:orig_category":"Agencias Y Agentes Comerciales, Representantes",
    "sg:phone":"+34 965 38 20 09",
    "sg:postcode":"03600",
    "sg:province":"Alicante",
    "wof:name":"Coloma Bernabeu Julio",
    "wof:placetype":"venue"
},
  "geometry": {"coordinates":[-0.7931290269,38.4756851196],"type":"Point"}
}