{
  "type": "Feature",
  "properties": {
    "addr:full":"Carrer de Neptu, 1 Barcelona Barcelona 08006",
    "addr:housenumber":"1",
    "addr:postcode":"08006",
    "addr:street":"Carrer De Neptu",
    "iso:country":"ES",
    "sg:address":"Carrer de Neptu, 1",
    "sg:city":"Barcelona",
    "sg:orig_category":"Librer\u00cdas",
    "sg:phone":"+34 932 37 03 61",
    "sg:postcode":"08006",
    "sg:province":"Barcelona",
    "wof:name":"Sociedad Anonima De Distribucion Edicion Y Librerias",
    "wof:placetype":"venue"
},
  "geometry": {"coordinates":[2.1550490856,41.3971672058],"type":"Point"}
}