{
  "type": "Feature",
  "properties": {
    "addr:full":"Pl Mercadal, 4 Reus Tarragona 43201",
    "addr:housenumber":"4",
    "addr:postcode":"43201",
    "addr:street":"Pl Mercadal",
    "iso:country":"ES",
    "sg:address":"Pl Mercadal, 4",
    "sg:city":"Reus",
    "sg:orig_category":"Bisuter\u00cda, Joyer\u00cda, Relojer\u00cda (al Por Menor)",
    "sg:phone":"+34 977 34 50 47",
    "sg:postcode":"43201",
    "sg:province":"Tarragona",
    "wof:name":"Brull Palau Josep Maria",
    "wof:placetype":"venue"
},
  "geometry": {"coordinates":[1.1083290577,41.1551017761],"type":"Point"}
}