{
  "type": "Feature",
  "properties": {
    "iso:country":"ES",
    "sg:address":"Urb Dehesa Campoamor, S/n",
    "sg:city":"Dehesa Campoamor",
    "sg:orig_category":"Ingenier\u00cda, Centros De Estudios (diversos)",
    "sg:phone":"+34 965 32 07 20",
    "sg:postcode":"03189",
    "sg:province":"Alicante",
    "wof:name":"Callizo Soler Eugenio",
    "wof:placetype":"venue"
},
  "geometry": {"coordinates":[-0.7677609921,37.9303321838],"type":"Point"}
}