{
  "type": "Feature",
  "properties": {
    "iso:country":"ES",
    "sg:address":"El Fresno, S/n",
    "sg:city":"Pedrajas",
    "sg:orig_category":"Cr\u00cda De Cerdos",
    "sg:phone":"+34 975 18 07 38",
    "sg:postcode":"42152",
    "sg:province":"Soria",
    "wof:name":"Copiso Soria Sociedad Cooperativa",
    "wof:placetype":"venue"
},
  "geometry": {"coordinates":[-2.5768098831,41.8265304565],"type":"Point"}
}