{
  "type": "Feature",
  "properties": {
    "addr:full":"Calle de Montevideo, 37 Huelva Huelva 21005",
    "addr:housenumber":"37",
    "addr:postcode":"21005",
    "addr:street":"Calle De Montevideo",
    "iso:country":"ES",
    "sg:address":"Calle de Montevideo, 37",
    "sg:city":"Huelva",
    "sg:orig_category":"Molduras, Junquillos, Listones Y Molduras Perforadas",
    "sg:phone":"+34 959 15 06 22",
    "sg:postcode":"21005",
    "sg:province":"Huelva",
    "wof:name":"Sistelcom-telemensaje S.a.",
    "wof:placetype":"venue"
},
  "geometry": {"coordinates":[-6.9438591003,37.2833404541],"type":"Point"}
}