{
  "type": "Feature",
  "properties": {
    "iso:country":"ES",
    "sg:address":"Calle de Cartaya (la), 43",
    "sg:city":"Cartaya",
    "sg:orig_category":"Carnicer\u00cdas, Carnicer\u00cdas",
    "sg:phone":"+34 922 34 14 53",
    "sg:postcode":"38413",
    "sg:province":"Santa Cruz De Tenerife",
    "wof:name":"Yanes Sosa Manuel",
    "wof:placetype":"venue"
},
  "geometry": {"coordinates":[-16.5637607574,28.3813018799],"type":"Point"}
}