{
  "type": "Feature",
  "properties": {
    "addr:full":"Cra. Nal. Cent Cinquanta Dos, 18 Parets Del Valles Barcelona 08150",
    "addr:postcode":"08150",
    "iso:country":"ES",
    "sg:address":"Cra. Nal. Cent Cinquanta Dos, 18",
    "sg:city":"Parets Del Valles",
    "sg:orig_category":"Ferreter\u00cda Artesanal",
    "sg:phone":"+34 935 62 18 02",
    "sg:postcode":"08150",
    "sg:province":"Barcelona",
    "wof:name":"Hierros Tous, S.l.u.",
    "wof:placetype":"venue"
},
  "geometry": {"coordinates":[2.226911068,41.5624809265],"type":"Point"}
}