{
  "type": "Feature",
  "properties": {
    "addr:full":"La Palma, 19 Sta Cruz Tenerife Santa Cruz De Tenerife 38003",
    "addr:housenumber":"19",
    "addr:postcode":"38003",
    "addr:street":"La Palma;Sta Cruz Tenerife",
    "iso:country":"ES",
    "sg:address":"La Palma, 19",
    "sg:city":"Sta Cruz Tenerife",
    "sg:orig_category":"Importaci\u00d3n",
    "sg:phone":"+34 922 24 53 01",
    "sg:postcode":"38003",
    "sg:province":"Santa Cruz De Tenerife",
    "wof:name":"Lakhani S.a.",
    "wof:placetype":"venue"
},
  "geometry": {"coordinates":[-16.2508049011,28.4667510986],"type":"Point"}
}