{
  "type": "Feature",
  "properties": {
    "addr:full":"Carrer de Doctor Fleming, 11 Barbera Valles Barcelona 08210",
    "addr:housenumber":"11",
    "addr:postcode":"08210",
    "addr:street":"Carrer De Doctor Fleming",
    "iso:country":"ES",
    "sg:address":"Carrer de Doctor Fleming, 11",
    "sg:city":"Barbera Valles",
    "sg:orig_category":"Fabricaci\u00d3n De Juegos Y Juguetes",
    "sg:phone":"+34 937 18 01 04",
    "sg:postcode":"08210",
    "sg:province":"Barcelona",
    "wof:name":"Pasqual Arnella S.l.",
    "wof:placetype":"venue"
},
  "geometry": {"coordinates":[2.1194729805,41.5211715698],"type":"Point"}
}