{
  "type": "Feature",
  "properties": {
    "addr:full":"Calle de Faya, 34 Cornisa Del Suroeste Las Palmas 35120",
    "addr:housenumber":"34",
    "addr:postcode":"35120",
    "addr:street":"Calle De Faya",
    "iso:country":"ES",
    "sg:address":"Calle de Faya, 34",
    "sg:city":"Cornisa Del Suroeste",
    "sg:orig_category":"Transportes Por V\u00cdas Navegables",
    "sg:phone":"+34 928 73 54 71",
    "sg:postcode":"35120",
    "sg:province":"Las Palmas",
    "wof:name":"Transportes Ivanlore S.l.",
    "wof:placetype":"venue"
},
  "geometry": {"coordinates":[-15.4300060272,28.1248226166],"type":"Point"}
}