{
  "type": "Feature",
  "properties": {
    "addr:full":"Calle de Angorrilla, 23 Arcos Frontera C\u00e1diz 11630",
    "addr:housenumber":"23",
    "addr:postcode":"11630",
    "addr:street":"Calle De Angorrilla",
    "iso:country":"ES",
    "sg:address":"Calle de Angorrilla, 23",
    "sg:city":"Arcos Frontera",
    "sg:orig_category":"Reposter\u00cdas",
    "sg:phone":"+34 956 70 03 58",
    "sg:postcode":"11630",
    "sg:province":"C\u00e1diz",
    "wof:name":"Martiz Castillo Francisca Isabel",
    "wof:placetype":"venue"
},
  "geometry": {"coordinates":[-5.7964406013,36.7450790405],"type":"Point"}
}