{
  "type": "Feature",
  "properties": {
    "addr:full":"Calle de Torreperogil, 52 Sevilla Sevilla 41016",
    "addr:housenumber":"52",
    "addr:postcode":"41016",
    "addr:street":"Calle De Torreperogil",
    "iso:country":"ES",
    "sg:address":"Calle de Torreperogil, 52",
    "sg:city":"Sevilla",
    "sg:orig_category":"Carnicer\u00cdas, Carnicer\u00cdas",
    "sg:phone":"+34 954 40 77 32",
    "sg:postcode":"41016",
    "sg:province":"Sevilla",
    "wof:name":"Rodriguez Lopez Claudio",
    "wof:placetype":"venue"
},
  "geometry": {"coordinates":[-5.906484127,37.3851737976],"type":"Point"}
}