{
  "type": "Feature",
  "properties": {
    "addr:full":"Calle de Condado De Trevi\u00d1o, 2 Madrid Madrid 28033",
    "addr:housenumber":"2",
    "addr:postcode":"28033",
    "addr:street":"Calle De Condado De Trevin\u0303O",
    "iso:country":"ES",
    "sg:address":"Calle de Condado De Trevi\u00d1o, 2",
    "sg:city":"Madrid",
    "sg:orig_category":"C\u00c1maras De Comercio E Industria, Oficios, Agricultura",
    "sg:phone":"+34 913 02 70 31",
    "sg:postcode":"28033",
    "sg:province":"Madrid",
    "wof:name":"Camara De Comercio De Venezuela",
    "wof:placetype":"venue"
},
  "geometry": {"coordinates":[-3.6738069057,40.4774208069],"type":"Point"}
}