{
  "type": "Feature",
  "properties": {
    "addr:full":"Calle de Santa Leonor, 57 Madrid Madrid 28037",
    "addr:housenumber":"57",
    "addr:postcode":"madrid;28037",
    "addr:street":"Calle De Santa Leonor",
    "iso:country":"ES",
    "sg:address":"Calle de Santa Leonor, 57",
    "sg:city":"Madrid",
    "sg:orig_category":"Bisuteros (fabricaci\u00d3n, Al Por Mayor)",
    "sg:phone":"+34 913 75 02 57",
    "sg:postcode":"28037",
    "sg:province":"Madrid",
    "wof:name":"Union Diamante Y Joyeria S.l.",
    "wof:placetype":"venue"
},
  "geometry": {"coordinates":[-3.629324913,40.4346809387],"type":"Point"}
}