{
  "type": "Feature",
  "properties": {
    "addr:full":"Urb. J. Reina, S/n Granada Granada 18006",
    "addr:housenumber":"s / n",
    "addr:postcode":"18006",
    "iso:country":"ES",
    "sg:address":"Urb. J. Reina, S/n",
    "sg:city":"Granada",
    "sg:orig_category":"Inmobiliaria (agencias)",
    "sg:phone":"+34 958 12 43 44",
    "sg:postcode":"18006",
    "sg:province":"Granada",
    "wof:name":"Euroserrallo S.l.",
    "wof:placetype":"venue"
},
  "geometry": {"coordinates":[-3.6054260731,37.1703987122],"type":"Point"}
}