{
  "type": "Feature",
  "properties": {
    "iso:country":"ES",
    "sg:address":"Urb La Espartera, S/n",
    "sg:city":"Guadix",
    "sg:orig_category":"Empresas De Impermeabilizaci\u00d3n",
    "sg:phone":"+34 958 66 50 44",
    "sg:postcode":"18500",
    "sg:province":"Granada",
    "wof:name":"Aislamietos Guadix Sl",
    "wof:placetype":"venue"
},
  "geometry": {"coordinates":[-3.0776567459,37.4068832397],"type":"Point"}
}