{
  "type": "Feature",
  "properties": {
    "iso:country":"ES",
    "sg:address":"Calle de Pelayo, 14",
    "sg:city":"Palmas De Gran Canaria",
    "sg:orig_category":"Embajadas, Consulados Y Otras Representaciones Diplom\u00c1ticas",
    "sg:phone":"+34 928 26 28 59",
    "sg:postcode":"35010",
    "sg:province":"Las Palmas",
    "wof:name":"Consulado General Del Reino De Marruecos",
    "wof:placetype":"venue"
},
  "geometry": {"coordinates":[-15.4376869202,28.1344776154],"type":"Point"}
}