{
  "type": "Feature",
  "properties": {
    "iso:country":"ES",
    "sg:address":"Calle de Becerro De Bengoa, 6",
    "sg:city":"Palencia",
    "sg:orig_category":"Herboristas (al Por Menor)",
    "sg:phone":"+34 979 70 01 07",
    "sg:postcode":"34002",
    "sg:province":"Palencia",
    "wof:name":"Dietetica Palentina S.l.",
    "wof:placetype":"venue"
},
  "geometry": {"coordinates":[-4.5318446159,42.0088005066],"type":"Point"}
}