{
  "type": "Feature",
  "properties": {
    "addr:full":"Avda Rosalia Castro, 34 Milladoiro La Coru\u00f1a 15895",
    "addr:housenumber":"34",
    "addr:postcode":"15895",
    "addr:street":"Avda Rosalia Castro;La Corun\u0303A",
    "iso:country":"ES",
    "sg:address":"Avda Rosalia Castro, 34",
    "sg:city":"Milladoiro",
    "sg:orig_category":"M\u00c9dicos: Estomatolog\u00cda",
    "sg:phone":"+34 981 53 15 65",
    "sg:postcode":"15895",
    "sg:province":"La Coru\u00f1a",
    "wof:name":"Muruais Gonzalez Covadonga",
    "wof:placetype":"venue"
},
  "geometry": {"coordinates":[-8.5771541595,42.8436088562],"type":"Point"}
}