{
  "type": "Feature",
  "properties": {
    "addr:full":"Ctra Yecla, S/n Villena Alicante 03400",
    "addr:housenumber":"s / n",
    "addr:postcode":"03400",
    "addr:street":"Ctra Yecla",
    "iso:country":"ES",
    "sg:address":"Ctra Yecla, S/n",
    "sg:city":"Villena",
    "sg:orig_category":"Muebles Y Accesorios Para Cocinas Y Cuartos De Ba\u00d1o (al Por Menor)",
    "sg:phone":"+34 965 81 33 12",
    "sg:postcode":"03400",
    "sg:province":"Alicante",
    "wof:name":"Idea Losa S.a",
    "wof:placetype":"venue"
},
  "geometry": {"coordinates":[-0.8705040216,38.6358566284],"type":"Point"}
}