{
  "type": "Feature",
  "properties": {
    "iso:country":"ES",
    "sg:address":"Ctra Artica, 40",
    "sg:city":"Artica",
    "sg:orig_category":"Maquinaria Para Industrias Diversas",
    "sg:phone":"+34 948 22 41 88",
    "sg:postcode":"31013",
    "sg:province":"Navarra",
    "wof:name":"Larumbe Martin Jaime",
    "wof:placetype":"venue"
},
  "geometry": {"coordinates":[-1.6696590185,42.8440933228],"type":"Point"}
}