{
  "type": "Feature",
  "properties": {
    "iso:country":"ES",
    "sg:address":"Calle de Mayor, 355",
    "sg:city":"Raal",
    "sg:orig_category":"Platos Preparados Refrigerados (fabricaci\u00d3n, Al Por Mayor)",
    "sg:phone":"+34 968 37 91 96",
    "sg:postcode":"30139",
    "sg:province":"Murcia",
    "wof:name":"Asador Las Dos Hermanas S.c",
    "wof:placetype":"venue"
},
  "geometry": {"coordinates":[-1.0168565512,38.0462913513],"type":"Point"}
}