{
  "type": "Feature",
  "properties": {
    "addr:full":"Ctra Gral, S/n Arenas Igu\u00f1a Cantabria 39450",
    "addr:postcode":"39450",
    "addr:street":"Ctra Gral S / N Arenas",
    "iso:country":"ES",
    "sg:address":"Ctra Gral, S/n",
    "sg:city":"Arenas Igu\u00f1a",
    "sg:orig_category":"Plomeros",
    "sg:phone":"+34 942 82 60 79",
    "sg:postcode":"39450",
    "sg:province":"Cantabria",
    "wof:name":"Gallo Diaz Gonzalo",
    "wof:placetype":"venue"
},
  "geometry": {"coordinates":[-3.9878427982,43.1828384399],"type":"Point"}
}