{
  "type": "Feature",
  "properties": {
    "addr:full":"Rond Navacerrada, 89 Sabadell Barcelona 08207",
    "addr:housenumber":"89",
    "addr:postcode":"08207",
    "addr:street":"Rond Navacerrada",
    "iso:country":"ES",
    "sg:address":"Rond Navacerrada, 89",
    "sg:city":"Sabadell",
    "sg:orig_category":"Empresas De Carpinter\u00cda Met\u00c1lica",
    "sg:phone":"+34 937 17 47 04",
    "sg:postcode":"08207",
    "sg:province":"Barcelona",
    "wof:name":"Metalisteria Y Automatismos Larrosa S.l.",
    "wof:placetype":"venue"
},
  "geometry": {"coordinates":[2.0903830528,41.5707015991],"type":"Point"}
}