{
  "type": "Feature",
  "properties": {
    "iso:country":"ES",
    "sg:address":"Fonfria, S/n",
    "sg:city":"Valdepares",
    "sg:orig_category":"Iglesia Cat\u00d3lica",
    "sg:phone":"+34 985 63 73 35",
    "sg:postcode":"33746",
    "sg:province":"Asturias",
    "wof:name":"Diocesis De Oviedo",
    "wof:placetype":"venue"
},
  "geometry": {"coordinates":[-6.8597688675,43.557849884],"type":"Point"}
}