{
  "type": "Feature",
  "properties": {
    "iso:country":"ES",
    "sg:address":"Calle de Covadonga, 16",
    "sg:city":"Cox",
    "sg:orig_category":"Orquestas De Variedades",
    "sg:phone":"+34 965 36 06 71",
    "sg:postcode":"03350",
    "sg:province":"Alicante",
    "wof:name":"Sociedad Musical La Armonica",
    "wof:placetype":"venue"
},
  "geometry": {"coordinates":[-0.8935989738,38.1436195374],"type":"Point"}
}