{
  "type": "Feature",
  "properties": {
    "addr:full":"Carrer de Pau Casals, 23 Cambrils Tarragona 43850",
    "addr:housenumber":"23",
    "addr:postcode":"43850",
    "addr:street":"Carrer De Pau Casals",
    "iso:country":"ES",
    "sg:address":"Carrer de Pau Casals, 23",
    "sg:city":"Cambrils",
    "sg:orig_category":"Platos Preparados Refrigerados (fabricaci\u00d3n, Al Por Mayor)",
    "sg:phone":"+34 977 79 31 41",
    "sg:postcode":"43850",
    "sg:province":"Tarragona",
    "wof:name":"Cuina Del Marino S.l.",
    "wof:placetype":"venue"
},
  "geometry": {"coordinates":[1.0616550446,41.066619873],"type":"Point"}
}