{
  "type": "Feature",
  "properties": {
    "iso:country":"ES",
    "sg:address":"Calle de Arroyo, 2",
    "sg:city":"Torrejon Ardoz",
    "sg:orig_category":"Farmacias",
    "sg:phone":"+34 916 76 55 91",
    "sg:postcode":"28850",
    "sg:province":"Madrid",
    "wof:name":"Arranz Jimenez Jesus Maria",
    "wof:placetype":"venue"
},
  "geometry": {"coordinates":[-3.4801671505,40.5119247437],"type":"Point"}
}