{
  "type": "Feature",
  "properties": {
    "iso:country":"ES",
    "sg:address":"Quatre (pol Ind Precis), S/n",
    "sg:city":"S. Esteve Sesrovires",
    "sg:orig_category":"Fabricaci\u00d3n De Pernos, Tornillos Y Clavos",
    "sg:phone":"+34 937 71 43 13",
    "sg:postcode":"08635",
    "sg:province":"Barcelona",
    "wof:name":"Torge S.a.",
    "wof:placetype":"venue"
},
  "geometry": {"coordinates":[1.8844000101,41.5057868958],"type":"Point"}
}