{
  "type": "Feature",
  "properties": {
    "addr:full":"Remiro De Go\u00f1i, 38 Iru\u00f1a Navarra 31010",
    "addr:housenumber":"38",
    "addr:postcode":"31010",
    "addr:street":"Gon\u0303I",
    "iso:country":"ES",
    "sg:address":"Remiro De Go\u00f1i, 38",
    "sg:city":"Iru\u00f1a",
    "sg:orig_category":"Molduras, Junquillos, Listones Y Molduras Perforadas",
    "sg:phone":"+34 948 18 34 48",
    "sg:postcode":"31010",
    "sg:province":"Navarra",
    "wof:name":"Prieto Legarra Fernando",
    "wof:placetype":"venue"
},
  "geometry": {"coordinates":[-1.6793069839,42.8024024963],"type":"Point"}
}