{
  "type": "Feature",
  "properties": {
    "addr:full":"Ctra Sentmenat, 54 Castellar Valles Barcelona 08211",
    "addr:housenumber":"54",
    "addr:postcode":"08211",
    "addr:street":"Ctra Sentmenat",
    "iso:country":"ES",
    "sg:address":"Ctra Sentmenat, 54",
    "sg:city":"Castellar Valles",
    "sg:orig_category":"Frutas, Legumbres Frescas Y Tempranas (al Por Menor)",
    "sg:phone":"+34 937 47 10 93",
    "sg:postcode":"08211",
    "sg:province":"Barcelona",
    "wof:name":"Morantes Fernandez Sergio",
    "wof:placetype":"venue"
},
  "geometry": {"coordinates":[2.0857300758,41.6151885986],"type":"Point"}
}