{
  "type": "Feature",
  "properties": {
    "iso:country":"ES",
    "sg:address":"Ctra Madrid, Km. 0352,0",
    "sg:city":"Cieza",
    "sg:orig_category":"Adaptaciones, Acondicionamientos Especiales Para Veh\u00cdculos, Veh\u00cdculos Industriales",
    "sg:phone":"+34 968 76 20 74",
    "sg:postcode":"30530",
    "sg:province":"Murcia",
    "wof:name":"Salinas Lopez Juan",
    "wof:placetype":"venue"
},
  "geometry": {"coordinates":[-1.4274940491,38.2550163269],"type":"Point"}
}