{
  "type": "Feature",
  "properties": {
    "addr:full":"Calle de Rio Orbigo, 17 Avila \u00c1vila 05004",
    "addr:housenumber":"17",
    "addr:postcode":"05004",
    "addr:street":"Calle De Rio Orbigo;A\u0301Vila",
    "iso:country":"ES",
    "sg:address":"Calle de Rio Orbigo, 17",
    "sg:city":"Avila",
    "sg:orig_category":"Negocio De Metales No Ferrosos",
    "sg:phone":"+34 920 25 48 52",
    "sg:postcode":"05004",
    "sg:province":"\u00c1vila",
    "wof:name":"Avila Logistica S.l.",
    "wof:placetype":"venue"
},
  "geometry": {"coordinates":[-4.6834192276,40.6659965515],"type":"Point"}
}