{
  "type": "Feature",
  "properties": {
    "addr:full":"Calle de Cruces, 3 Hornachos Badajoz 06228",
    "addr:housenumber":"3",
    "addr:postcode":"06228",
    "addr:street":"Calle De Cruces",
    "iso:country":"ES",
    "sg:address":"Calle de Cruces, 3",
    "sg:city":"Hornachos",
    "sg:orig_category":"Reposter\u00cdas",
    "sg:phone":"+34 924 53 35 57",
    "sg:postcode":"06228",
    "sg:province":"Badajoz",
    "wof:name":"Ortiz Gonzalez Francisco",
    "wof:placetype":"venue"
},
  "geometry": {"coordinates":[-6.0709900856,38.5548286438],"type":"Point"}
}