{
  "type": "Feature",
  "properties": {
    "iso:country":"ES",
    "sg:address":"Calle de Extremadura, 12",
    "sg:city":"Vitoria-gasteiz",
    "sg:orig_category":"Peluqueros: De Se\u00d1oras",
    "sg:phone":"+34 945 26 16 55",
    "sg:postcode":"01003",
    "sg:province":"\u00c1lava",
    "wof:name":"Maria Jose Ortiz De Zarate",
    "wof:placetype":"venue"
},
  "geometry": {"coordinates":[-2.6598520279,42.850112915],"type":"Point"}
}