{
  "type": "Feature",
  "properties": {
    "addr:full":"Avda Reguera, 5 Langreo Asturias 33930",
    "addr:housenumber":"5",
    "addr:postcode":"33930",
    "addr:street":"Avda Reguera",
    "iso:country":"ES",
    "sg:address":"Avda Reguera, 5",
    "sg:city":"Langreo",
    "sg:orig_category":"Reposter\u00cdas",
    "sg:phone":"+34 985 69 13 28",
    "sg:postcode":"33930",
    "sg:province":"Asturias",
    "wof:name":"Suarez Arbesu Gonzalo",
    "wof:placetype":"venue"
},
  "geometry": {"coordinates":[-5.6905298233,43.3116722107],"type":"Point"}
}