{
  "type": "Feature",
  "properties": {
    "iso:country":"ES",
    "sg:address":"Calle de Guadalquivir, 84",
    "sg:city":"Horno De Alcedo",
    "sg:orig_category":"Fabricaci\u00d3n De Juegos Y Juguetes",
    "sg:phone":"+34 963 76 51 51",
    "sg:postcode":"46026",
    "sg:province":"Valencia",
    "wof:name":"Eleval Electronicos Valencia S.a.",
    "wof:placetype":"venue"
},
  "geometry": {"coordinates":[-0.3777849972,39.4282569885],"type":"Point"}
}