{
  "type": "Feature",
  "properties": {
    "addr:full":"Calle de Norias, 23 Majadahonda Madrid 28220",
    "addr:housenumber":"23",
    "addr:postcode":"28220",
    "addr:street":"Calle De Norias",
    "iso:country":"ES",
    "sg:address":"Calle de Norias, 23",
    "sg:city":"Majadahonda",
    "sg:orig_category":"Panader\u00cdas, Panader\u00cdas",
    "sg:phone":"+34 916 39 73 02",
    "sg:postcode":"28220",
    "sg:province":"Madrid",
    "wof:name":"Perez Nieto Concepcion",
    "wof:placetype":"venue"
},
  "geometry": {"coordinates":[-3.8706190586,40.471031189],"type":"Point"}
}