{
  "type": "Feature",
  "properties": {
    "addr:full":"I Guadalmina(guadalmina Alta), S/n San Pedro Alcantara M\u00e1laga 29670",
    "addr:housenumber":"s / n",
    "addr:postcode":"29670",
    "addr:street":"I;Guadalmina Alta",
    "iso:country":"ES",
    "sg:address":"I Guadalmina(guadalmina Alta), S/n",
    "sg:city":"San Pedro Alcantara",
    "sg:orig_category":"Soportes L\u00d3gicos, Programas Integradores De Aplicaciones (progiciels)",
    "sg:phone":"+34 952 92 89 44",
    "sg:postcode":"29670",
    "sg:province":"M\u00e1laga",
    "sg:website":"www.dominia.es",
    "wof:name":"Dominia Sistemas Inteligentes Sl",
    "wof:placetype":"venue"
},
  "geometry": {"coordinates":[-4.9825482368,36.4844207764],"type":"Point"}
}