{
  "type": "Feature",
  "properties": {
    "addr:full":"Calle de Crucero Baleares, 3 Puerto De Santa Maria C\u00e1diz 11500",
    "addr:housenumber":"3",
    "addr:postcode":"11500",
    "addr:street":"Calle De Crucero Baleares;Ca\u0301Diz",
    "iso:country":"ES",
    "sg:address":"Calle de Crucero Baleares, 3",
    "sg:city":"Puerto De Santa Maria",
    "sg:orig_category":"Asociaciones Y Clubs Deportivos",
    "sg:phone":"+34 956 87 58 05",
    "sg:postcode":"11500",
    "sg:province":"C\u00e1diz",
    "wof:name":"Federacion Andaluza De Voleibol",
    "wof:placetype":"venue"
},
  "geometry": {"coordinates":[-6.2325263023,36.5907554626],"type":"Point"}
}