{
  "type": "Feature",
  "properties": {
    "addr:full":"Calle de General Armero, 32 Fuentes De Andalucia Sevilla 41420",
    "addr:housenumber":"32",
    "addr:postcode":"41420",
    "addr:street":"Calle De General Armero",
    "iso:country":"ES",
    "sg:address":"Calle de General Armero, 32",
    "sg:city":"Fuentes De Andalucia",
    "sg:orig_category":"Cr\u00cda De Cerdos",
    "sg:phone":"+34 954 83 70 65",
    "sg:postcode":"41420",
    "sg:province":"Sevilla",
    "wof:name":"Agropecuaria Santa Juliana S.l.",
    "wof:placetype":"venue"
},
  "geometry": {"coordinates":[-5.3467001915,37.4623947144],"type":"Point"}
}