{
  "type": "Feature",
  "properties": {
    "addr:full":"Avda Constitucion (de La), 8 Abaran Murcia 30550",
    "addr:housenumber":"8",
    "addr:postcode":"30550",
    "addr:street":"Avda Constitucion De La",
    "iso:country":"ES",
    "sg:address":"Avda Constitucion (de La), 8",
    "sg:city":"Abaran",
    "sg:orig_category":"Artes Gr\u00c1ficas, Artes Pl\u00c1sticas: Material Y Suministros (al Por Menor)",
    "sg:phone":"+34 968 45 15 62",
    "sg:postcode":"30550",
    "sg:province":"Murcia",
    "wof:name":"Comunidad De Propietarios Vivi Uno",
    "wof:placetype":"venue"
},
  "geometry": {"coordinates":[-1.3973850012,38.2064170837],"type":"Point"}
}