{
  "type": "Feature",
  "properties": {
    "addr:full":"Rua Wenceslao Calvo Garra, S/n Lalin Pontevedra 36500",
    "addr:housenumber":"s",
    "addr:postcode":"36500",
    "addr:street":"Rua Wenceslao Calvo Garra;/ N",
    "iso:country":"ES",
    "sg:address":"Rua Wenceslao Calvo Garra, S/n",
    "sg:city":"Lalin",
    "sg:orig_category":"Restaurantes",
    "sg:phone":"+34 986 78 08 99",
    "sg:postcode":"36500",
    "sg:province":"Pontevedra",
    "wof:name":"Meson Los Arcos C.b.",
    "wof:placetype":"venue"
},
  "geometry": {"coordinates":[-8.1110992432,42.6618118286],"type":"Point"}
}