{
  "type": "Feature",
  "properties": {
    "addr:full":"Calle de Pepito Etxebeste, 2 Irun Guip\u00f9zcoa 20302",
    "addr:housenumber":"2",
    "addr:postcode":"20302",
    "addr:street":"Calle De Pepito Etxebeste;Guipu\u0300Zcoa",
    "iso:country":"ES",
    "sg:address":"Calle de Pepito Etxebeste, 2",
    "sg:city":"Irun",
    "sg:orig_category":"Ropa Para Ni\u00d1os (al Por Menor)",
    "sg:phone":"+34 943 61 39 30",
    "sg:postcode":"20302",
    "sg:province":"Guip\u00f9zcoa",
    "wof:name":"Francisco De Borja Campos Sanchez Y Otro",
    "wof:placetype":"venue"
},
  "geometry": {"coordinates":[-1.796759963,43.3369941711],"type":"Point"}
}