{
  "type": "Feature",
  "properties": {
    "iso:country":"ES",
    "sg:address":"Canapes, S/n",
    "sg:city":"Aviles",
    "sg:orig_category":"Distribuci\u00d3n De Petr\u00d3leo Y Derivados",
    "sg:phone":"+34 985 57 51 01",
    "sg:postcode":"33405",
    "sg:province":"Asturias",
    "sg:website":"www.cepsa.es",
    "wof:name":"Estacion De Servicio Los Canapes S. A.",
    "wof:placetype":"venue"
},
  "geometry": {"coordinates":[-5.9125041962,43.547088623],"type":"Point"}
}