{
  "type": "Feature",
  "properties": {
    "addr:full":"Calle de Capitan Muro Duran, 9 Leganes Madrid 28911",
    "addr:housenumber":"9",
    "addr:postcode":"28911",
    "addr:street":"Calle De Capitan Muro Duran",
    "iso:country":"ES",
    "sg:address":"Calle de Capitan Muro Duran, 9",
    "sg:city":"Leganes",
    "sg:orig_category":"Institutos De Belleza",
    "sg:phone":"+34 916 89 49 13",
    "sg:postcode":"28911",
    "sg:province":"Madrid",
    "wof:name":"Lara Garcia Julia",
    "wof:placetype":"venue"
},
  "geometry": {"coordinates":[-3.7654800415,40.3263969421],"type":"Point"}
}