{
  "type": "Feature",
  "properties": {
    "iso:country":"ES",
    "sg:address":"Calle de Punta Alta, 14",
    "sg:city":"Malaga",
    "sg:orig_category":"Muebles Y Accesorios Para Cocinas Y Cuartos De Ba\u00d1o (al Por Menor)",
    "sg:phone":"+34 952 35 13 09",
    "sg:postcode":"29006",
    "sg:province":"M\u00e1laga",
    "wof:name":"Cocinatres S.l.",
    "wof:placetype":"venue"
},
  "geometry": {"coordinates":[-4.4763031006,36.7062225342],"type":"Point"}
}