{
  "type": "Feature",
  "properties": {
    "addr:full":"Carrer de Baix (de), 1 Mazaleon Teruel 44621",
    "addr:postcode":"44621",
    "addr:street":"Carrer De Baix De 1",
    "iso:country":"ES",
    "sg:address":"Carrer de Baix (de), 1",
    "sg:city":"Mazaleon",
    "sg:orig_category":"Cajas De Ahorro",
    "sg:phone":"+34 978 89 86 67",
    "sg:postcode":"44621",
    "sg:province":"Teruel",
    "sg:website":"www.ibercaja.es",
    "wof:name":"Caja De Ahorros Y Monte De Piedad De Zaragoza Aragon Y Rioja",
    "wof:placetype":"venue"
},
  "geometry": {"coordinates":[0.1034329981,41.0514335632],"type":"Point"}
}