{
  "type": "Feature",
  "properties": {
    "addr:full":"Rua Alto Do Castro, 1 Carral La Coru\u00f1a 15175",
    "addr:housenumber":"1",
    "addr:postcode":"15175",
    "addr:street":"Rua Alto Do Castro;La Corun\u0303A",
    "iso:country":"ES",
    "sg:address":"Rua Alto Do Castro, 1",
    "sg:city":"Carral",
    "sg:orig_category":"Agencias Y Agentes Comerciales, Representantes",
    "sg:phone":"+34 981 67 06 73",
    "sg:postcode":"15175",
    "sg:province":"La Coru\u00f1a",
    "wof:name":"Garcia Garcia Marcos",
    "wof:placetype":"venue"
},
  "geometry": {"coordinates":[-8.35688591,43.2238349915],"type":"Point"}
}