{
  "type": "Feature",
  "properties": {
    "addr:full":"Calle de Periodista Sanchez Asensio, 3 Caceres C\u00e1ceres 10004",
    "addr:housenumber":"3",
    "addr:postcode":"10004",
    "addr:street":"Calle De Periodista Sanchez Asensio;Ca\u0301Ceres",
    "iso:country":"ES",
    "sg:address":"Calle de Periodista Sanchez Asensio, 3",
    "sg:city":"Caceres",
    "sg:orig_category":"Fabricaci\u00d3n De Juguetes Autom\u00c1ticos",
    "sg:phone":"+34 927 21 29 89",
    "sg:postcode":"10004",
    "sg:province":"C\u00e1ceres",
    "wof:name":"Cedosca S.l.",
    "wof:placetype":"venue"
},
  "geometry": {"coordinates":[-6.3583831787,39.5027656555],"type":"Point"}
}