{
  "type": "Feature",
  "properties": {
    "addr:full":"Calle de Ibiza, 19 Totana Murcia 30850",
    "addr:housenumber":"19",
    "addr:postcode":"30850",
    "addr:street":"Calle De Ibiza",
    "iso:country":"ES",
    "sg:address":"Calle de Ibiza, 19",
    "sg:city":"Totana",
    "sg:orig_category":"Alimentaci\u00d3n General (al Por Menor)",
    "sg:phone":"+34 968 42 52 47",
    "sg:postcode":"30850",
    "sg:province":"Murcia",
    "wof:name":"Larios Gonzalez Pedro",
    "wof:placetype":"venue"
},
  "geometry": {"coordinates":[-1.5012949705,37.7647247314],"type":"Point"}
}