{
  "type": "Feature",
  "properties": {
    "addr:full":"Carrer de Tetuan, 132 Sabadell Barcelona 08203",
    "addr:housenumber":"132",
    "addr:postcode":"08203",
    "addr:street":"Carrer De Tetuan",
    "iso:country":"ES",
    "sg:address":"Carrer de Tetuan, 132",
    "sg:city":"Sabadell",
    "sg:orig_category":"Ropa Para Se\u00d1oras Y Caballeros (al Por Menor)",
    "sg:phone":"+34 937 11 26 58",
    "sg:postcode":"08203",
    "sg:province":"Barcelona",
    "wof:name":"Bellmunt Molins Joan",
    "wof:placetype":"venue"
},
  "geometry": {"coordinates":[2.1077580452,41.5372505188],"type":"Point"}
}