{
  "type": "Feature",
  "properties": {
    "addr:full":"Calle de General O'donnell, 3 Santa Cruz De Tenerife Santa Cruz De Tenerife 38004",
    "addr:housenumber":"3",
    "addr:postcode":"38004",
    "addr:street":"Calle De General O'Donnell",
    "iso:country":"ES",
    "sg:address":"Calle de General O'donnell, 3",
    "sg:city":"Santa Cruz De Tenerife",
    "sg:orig_category":"Trabajos De Asfalto, De Alquitr\u00c1n Y Asfalto",
    "sg:phone":"+34 922 24 79 82",
    "sg:postcode":"38004",
    "sg:province":"Santa Cruz De Tenerife",
    "wof:name":"Distribuidora De Betunes De Canarias S.a.",
    "wof:placetype":"venue"
},
  "geometry": {"coordinates":[-16.255279541,28.4710578918],"type":"Point"}
}