{
  "type": "Feature",
  "properties": {
    "addr:full":"Av Reina Maria Cristina, 14 Tarragona Tarragona 43002",
    "addr:housenumber":"14",
    "addr:postcode":"43002",
    "addr:street":"Av Reina Maria Cristina",
    "iso:country":"ES",
    "sg:address":"Av Reina Maria Cristina, 14",
    "sg:city":"Tarragona",
    "sg:orig_category":"Agencias Y Agentes Comerciales, Representantes",
    "sg:phone":"+34 977 24 42 20",
    "sg:postcode":"43002",
    "sg:province":"Tarragona",
    "wof:name":"Miro Fabregat Jose Maria",
    "wof:placetype":"venue"
},
  "geometry": {"coordinates":[1.2518049479,41.1184844971],"type":"Point"}
}