{
  "type": "Feature",
  "properties": {
    "iso:country":"ES",
    "sg:address":"Carrer de Plaute, 57",
    "sg:city":"Sabadell",
    "sg:orig_category":"Alimentaci\u00d3n General (al Por Menor)",
    "sg:phone":"+34 937 16 99 50",
    "sg:postcode":"08206",
    "sg:province":"Barcelona",
    "wof:name":"Garcia Tarrega Bartolome",
    "wof:placetype":"venue"
},
  "geometry": {"coordinates":[2.0829529762,41.5516929626],"type":"Point"}
}