{
  "type": "Feature",
  "properties": {
    "iso:country":"ES",
    "sg:address":"Carrer de Marc Aureli, 3",
    "sg:city":"Barcelona",
    "sg:orig_category":"Tintes (fabricaci\u00d3n, Al Por Mayor)",
    "sg:phone":"+34 932 00 52 01",
    "sg:postcode":"08006",
    "sg:province":"Barcelona",
    "wof:name":"Tintoreria Zona Alta S.l.",
    "wof:placetype":"venue"
},
  "geometry": {"coordinates":[2.1431510448,41.4002151489],"type":"Point"}
}