{
  "type": "Feature",
  "properties": {
    "addr:full":"Calle de Anzofe, 113 Palmas De Gran Canaria Las Palmas 35009",
    "addr:housenumber":"113",
    "addr:postcode":"35009",
    "addr:street":"Calle De Anzofe",
    "iso:country":"ES",
    "sg:address":"Calle de Anzofe, 113",
    "sg:city":"Palmas De Gran Canaria",
    "sg:orig_category":"Andamiajes Y Escaleras De Mano (fabricaci\u00d3n, Al Por Mayor)",
    "sg:phone":"+34 928 46 09 71",
    "sg:postcode":"35009",
    "sg:province":"Las Palmas",
    "wof:name":"Galvez Gomez Luisa",
    "wof:placetype":"venue"
},
  "geometry": {"coordinates":[-15.422170639,28.1507320404],"type":"Point"}
}