{
  "type": "Feature",
  "properties": {
    "addr:full":"Calle de Trillo, 6 Cisterniga Valladolid 47193",
    "addr:housenumber":"6",
    "addr:postcode":"47193",
    "addr:street":"Calle De Trillo",
    "iso:country":"ES",
    "sg:address":"Calle de Trillo, 6",
    "sg:city":"Cisterniga",
    "sg:orig_category":"Agencias Y Agentes Comerciales, Representantes",
    "sg:phone":"+34 983 40 17 04",
    "sg:postcode":"47193",
    "sg:province":"Valladolid",
    "wof:name":"Riosca Difusion S.l.",
    "wof:placetype":"venue"
},
  "geometry": {"coordinates":[-4.6810531616,41.6082496643],"type":"Point"}
}