{
  "type": "Feature",
  "properties": {
    "iso:country":"ES",
    "sg:address":"Calle de Maria Montessori, 2",
    "sg:city":"Zaragoza",
    "sg:orig_category":"Muebles, Minoristas",
    "sg:phone":"+34 976 07 32 30",
    "sg:postcode":"50015",
    "sg:province":"Zaragoza",
    "wof:name":"Limbali Negre, S.a.",
    "wof:placetype":"venue"
},
  "geometry": {"coordinates":[-0.8822569847,41.6632881165],"type":"Point"}
}