{
  "type": "Feature",
  "properties": {
    "iso:country":"ES",
    "sg:address":"Calle de Pino, 7",
    "sg:city":"Don Benito",
    "sg:orig_category":"Confecci\u00d3n De Trajes Para Se\u00d1oras",
    "sg:phone":"+34 924 80 35 20",
    "sg:postcode":"06400",
    "sg:province":"Badajoz",
    "wof:name":"Asensio Ortega Francisco",
    "wof:placetype":"venue"
},
  "geometry": {"coordinates":[-5.8614907265,38.9571495056],"type":"Point"}
}