{
  "type": "Feature",
  "properties": {
    "iso:country":"ES",
    "sg:address":"Ctra Sabadell, Km. 0002,0",
    "sg:city":"Terra Nostra",
    "sg:orig_category":"Molduras, Junquillos, Listones Y Molduras Perforadas",
    "sg:phone":"+34 935 75 15 68",
    "sg:postcode":"08110",
    "sg:province":"Barcelona",
    "wof:name":"Riba Pares Juan",
    "wof:placetype":"venue"
},
  "geometry": {"coordinates":[2.1817660332,41.4890899658],"type":"Point"}
}