{
  "type": "Feature",
  "properties": {
    "iso:country":"ES",
    "sg:address":"Zelaia Auzoa, S/n",
    "sg:city":"Zelaia",
    "sg:orig_category":"Construcci\u00d3n Mec\u00c1nica",
    "sg:phone":"+34 946 73 60 40",
    "sg:postcode":"48140",
    "sg:province":"Vizcaya",
    "wof:name":"Comecaran S.a.l.",
    "wof:placetype":"venue"
},
  "geometry": {"coordinates":[-2.7893249989,43.1561317444],"type":"Point"}
}