{
  "type": "Feature",
  "properties": {
    "addr:full":"Avda Espa\u00d1a, 17 Ponferrada Le\u00f3n 24400",
    "addr:housenumber":"17",
    "addr:postcode":"24400",
    "addr:street":"Avda Espan\u0303A",
    "iso:country":"ES",
    "sg:address":"Avda Espa\u00d1a, 17",
    "sg:city":"Ponferrada",
    "sg:orig_category":"Panader\u00cdas, Panader\u00cdas",
    "sg:phone":"+34 987 41 04 73",
    "sg:postcode":"24400",
    "sg:province":"Le\u00f3n",
    "wof:name":"Confiteria Pili S. A.",
    "wof:placetype":"venue"
},
  "geometry": {"coordinates":[-6.5994400978,42.547618866],"type":"Point"}
}