{
  "type": "Feature",
  "properties": {
    "iso:country":"ES",
    "sg:address":"Pase Bomba (de La), 13",
    "sg:city":"Granada",
    "sg:orig_category":"Abogados",
    "sg:phone":"+34 958 22 14 26",
    "sg:postcode":"18008",
    "sg:province":"Granada",
    "wof:name":"Vilchez Cuesta Cristina",
    "wof:placetype":"venue"
},
  "geometry": {"coordinates":[-3.5900480747,37.1687240601],"type":"Point"}
}