{
  "type": "Feature",
  "properties": {
    "addr:full":"Calle de Martin Carramolino, 8 Avila \u00c1vila 05001",
    "addr:housenumber":"8",
    "addr:postcode":"05001",
    "addr:street":"Calle De Martin Carramolino;A\u0301Vila",
    "iso:country":"ES",
    "sg:address":"Calle de Martin Carramolino, 8",
    "sg:city":"Avila",
    "sg:orig_category":"Comercios E Industrias (cesi\u00d3n Y Reactivaci\u00d3n)",
    "sg:phone":"+34 920 25 04 35",
    "sg:postcode":"05001",
    "sg:province":"\u00c1vila",
    "wof:name":"Rodrigues Martin Julia",
    "wof:placetype":"venue"
},
  "geometry": {"coordinates":[-4.7007741928,40.6562004089],"type":"Point"}
}