{
  "type": "Feature",
  "properties": {
    "addr:full":"Carr Orient, 38 Ciutadella Menorca Islas Baleares 07760",
    "addr:housenumber":"38",
    "addr:postcode":"07760",
    "addr:street":"Carr Orient",
    "iso:country":"ES",
    "sg:address":"Carr Orient, 38",
    "sg:city":"Ciutadella Menorca",
    "sg:orig_category":"Supermercados Y Hipermercados",
    "sg:phone":"+34 971 38 63 28",
    "sg:postcode":"07760",
    "sg:province":"Islas Baleares",
    "wof:name":"Hiper Ciutadella S.l.",
    "wof:placetype":"venue"
},
  "geometry": {"coordinates":[3.8416149616,40.0027542114],"type":"Point"}
}