{
  "type": "Feature",
  "properties": {
    "addr:full":"G. Franco, 15 Chilluevar Ja\u00e9n 23477",
    "addr:housenumber":"15",
    "addr:postcode":"23477",
    "addr:street":"G. Franco;Jae\u0301N",
    "iso:country":"ES",
    "sg:address":"G. Franco, 15",
    "sg:city":"Chilluevar",
    "sg:orig_category":"Ropa Para Ni\u00d1os (al Por Menor)",
    "sg:phone":"+34 953 71 70 24",
    "sg:postcode":"23477",
    "sg:province":"Ja\u00e9n",
    "wof:name":"Uceda Carrascosa Maria Victoria",
    "wof:placetype":"venue"
},
  "geometry": {"coordinates":[-3.0308589935,38.0016899109],"type":"Point"}
}