{
  "type": "Feature",
  "properties": {
    "iso:country":"ES",
    "sg:address":"Calle de Casilda Iturrizar, 6",
    "sg:city":"Portugalete",
    "sg:orig_category":"Publicidad (soportes Y Gesti\u00d3n)",
    "sg:phone":"+34 944 72 10 19",
    "sg:postcode":"48920",
    "sg:province":"Vizcaya",
    "wof:name":"Kalekua Uno S.l.",
    "wof:placetype":"venue"
},
  "geometry": {"coordinates":[-3.0185492039,43.3212623596],"type":"Point"}
}