{
  "type": "Feature",
  "properties": {
    "iso:country":"ES",
    "sg:address":"Plaz Maestro Tarrega (del), 1",
    "sg:city":"Alcobendas",
    "sg:orig_category":"Farmacias",
    "sg:phone":"+34 916 63 86 24",
    "sg:postcode":"28100",
    "sg:province":"Madrid",
    "wof:name":"Garcia Martos Mercedes",
    "wof:placetype":"venue"
},
  "geometry": {"coordinates":[-3.6446769238,40.5491943359],"type":"Point"}
}