{
  "type": "Feature",
  "properties": {
    "iso:country":"ES",
    "sg:address":"Carrer de Alzina, 17",
    "sg:city":"Palma",
    "sg:orig_category":"Administradores De Bienes Y Delegados De Comunidades De Propietarios",
    "sg:phone":"+34 971 73 93 67",
    "sg:postcode":"07014",
    "sg:province":"Islas Baleares",
    "wof:name":"Molada Rossello Javier",
    "wof:placetype":"venue"
},
  "geometry": {"coordinates":[2.6304190159,39.5770187378],"type":"Point"}
}