{
  "type": "Feature",
  "properties": {
    "addr:full":"Poli Poliviso, S/n Viso Del Alcor Sevilla 41520",
    "addr:housenumber":"s",
    "addr:postcode":"41520",
    "addr:street":"/ N",
    "iso:country":"ES",
    "sg:address":"Poli Poliviso, S/n",
    "sg:city":"Viso Del Alcor",
    "sg:orig_category":"Fabrica De Cer\u00c1micas",
    "sg:phone":"+34 955 94 50 42",
    "sg:postcode":"41520",
    "sg:province":"Sevilla",
    "wof:name":"Revestimientos Sevilla S.l.",
    "wof:placetype":"venue"
},
  "geometry": {"coordinates":[-5.7224740982,37.3872108459],"type":"Point"}
}