{
  "type": "Feature",
  "properties": {
    "addr:full":"Calle de Angulema, 6 Vitoria-gasteiz \u00c1lava 01004",
    "addr:housenumber":"6",
    "addr:postcode":"01004",
    "addr:street":"Calle De Angulema",
    "iso:country":"ES",
    "sg:address":"Calle de Angulema, 6",
    "sg:city":"Vitoria-gasteiz",
    "sg:orig_category":"Alquiler De Casas Y Habitaciones Amuebladas",
    "sg:phone":"+34 945 25 83 53",
    "sg:postcode":"01004",
    "sg:province":"\u00c1lava",
    "wof:name":"Residencia M Inmaculada En Vitoria Maria Inmaculada Servicio Domestico Prov Iberica Nordeste",
    "wof:placetype":"venue"
},
  "geometry": {"coordinates":[-2.6674575806,42.8431243896],"type":"Point"}
}