{
  "type": "Feature",
  "properties": {
    "addr:full":"Calle de Maria Auxiliadora, 22 Bollullos Par Condado Huelva 21710",
    "addr:housenumber":"22",
    "addr:postcode":"21710",
    "addr:street":"Calle De Maria Auxiliadora",
    "iso:country":"ES",
    "sg:address":"Calle de Maria Auxiliadora, 22",
    "sg:city":"Bollullos Par Condado",
    "sg:orig_category":"\u00d3ptica: Instrumentos (fabricaci\u00d3n)",
    "sg:phone":"+34 959 41 05 35",
    "sg:postcode":"21710",
    "sg:province":"Huelva",
    "wof:name":"Romero Perez Inmaculada",
    "wof:placetype":"venue"
},
  "geometry": {"coordinates":[-6.5400290489,37.3424797058],"type":"Point"}
}