{
  "type": "Feature",
  "properties": {
    "addr:full":"Plgno. Industrial, S/n Amurrio \u00c1lava 01470",
    "addr:housenumber":"/ n",
    "addr:postcode":"01470",
    "addr:street":"Industrial",
    "iso:country":"ES",
    "sg:address":"Plgno. Industrial, S/n",
    "sg:city":"Amurrio",
    "sg:orig_category":"Mec\u00c1nico Del Autom\u00d3vil",
    "sg:phone":"+34 945 89 22 91",
    "sg:postcode":"01470",
    "sg:province":"\u00c1lava",
    "wof:name":"Ayala Motor S.a.",
    "wof:placetype":"venue"
},
  "geometry": {"coordinates":[-2.9475662708,43.0302124023],"type":"Point"}
}