{
  "type": "Feature",
  "properties": {
    "addr:full":"Carrer de Sax, 6 Playa Muchavista Alicante 03560",
    "addr:housenumber":"6",
    "addr:postcode":"03560",
    "addr:street":"Carrer De Sax;Muchavista",
    "iso:country":"ES",
    "sg:address":"Carrer de Sax, 6",
    "sg:city":"Playa Muchavista",
    "sg:orig_category":"Artes Gr\u00c1ficas, Artes Pl\u00c1sticas: Material Y Suministros (al Por Menor)",
    "sg:phone":"+34 965 94 19 44",
    "sg:postcode":"03560",
    "sg:province":"Alicante",
    "wof:name":"Dcdc Division Informatica S.l.",
    "wof:placetype":"venue"
},
  "geometry": {"coordinates":[-0.4053089917,38.4074058533],"type":"Point"}
}