{
  "type": "Feature",
  "properties": {
    "iso:country":"ES",
    "sg:address":"Ctra L'escala, Km. 0004,0",
    "sg:city":"Siurana",
    "sg:orig_category":"Reciclaje, Desguace De Veh\u00cdculos",
    "sg:phone":"+34 972 19 30 57",
    "sg:postcode":"17469",
    "sg:province":"Girona",
    "wof:name":"Doromeu 929 S.l.",
    "wof:placetype":"venue"
},
  "geometry": {"coordinates":[2.9943900108,42.2092208862],"type":"Point"}
}