{
  "type": "Feature",
  "properties": {
    "addr:full":"Calle de Juan Gonzalez Cruz, 8 Barriada Del Chan Zaragoza 50820",
    "addr:housenumber":"8",
    "addr:postcode":"50820",
    "addr:street":"Calle De Juan Gonzalez Cruz;Del Chan",
    "iso:country":"ES",
    "sg:address":"Calle de Juan Gonzalez Cruz, 8",
    "sg:city":"Barriada Del Chan",
    "sg:orig_category":"Materias Pl\u00c1sticas: Art\u00cdculos Para La Industria",
    "sg:phone":"+34 976 15 06 02",
    "sg:postcode":"50820",
    "sg:province":"Zaragoza",
    "wof:name":"Norte\u00f1a De Distribucion S. L.",
    "wof:placetype":"venue"
},
  "geometry": {"coordinates":[-0.8429120183,41.7160720825],"type":"Point"}
}