{
  "type": "Feature",
  "properties": {
    "addr:full":"Calle de Emilia Pardo Bazan, 40 Alcazar S. Juan Ciudad Real 13600",
    "addr:housenumber":"40",
    "addr:postcode":"13600",
    "addr:street":"Calle De Emilia Pardo Bazan;Alcazar S. Juan Ciudad Real",
    "iso:country":"ES",
    "sg:address":"Calle de Emilia Pardo Bazan, 40",
    "sg:city":"Alcazar S. Juan",
    "sg:orig_category":"Agencias Y Agentes Comerciales, Representantes",
    "sg:phone":"+34 926 54 15 09",
    "sg:postcode":"13600",
    "sg:province":"Ciudad Real",
    "wof:name":"Sanchez Rodriguez Yolanda",
    "wof:placetype":"venue"
},
  "geometry": {"coordinates":[-3.2219040394,39.3928756714],"type":"Point"}
}