{
  "type": "Feature",
  "properties": {
    "iso:country":"ES",
    "sg:address":"Calle de Velazquez, 11",
    "sg:city":"Pedro Mu\u00e7oz",
    "sg:orig_category":"Muebles, Minoristas",
    "sg:phone":"+34 926 56 85 86",
    "sg:postcode":"13620",
    "sg:province":"Ciudad Real",
    "wof:name":"Pliego Sanchez-cruzado Manuel",
    "wof:placetype":"venue"
},
  "geometry": {"coordinates":[-2.9405200481,39.3987808228],"type":"Point"}
}