{
  "type": "Feature",
  "properties": {
    "addr:full":"Haritz Bakar, 12 Lezo Guip\u00f9zcoa 20100",
    "addr:housenumber":"12",
    "addr:postcode":"20100",
    "addr:street":"Guipu\u0300Zcoa",
    "iso:country":"ES",
    "sg:address":"Haritz Bakar, 12",
    "sg:city":"Lezo",
    "sg:orig_category":"Fabricaci\u00d3n De Moldes Y Modelos",
    "sg:phone":"+34 943 34 40 98",
    "sg:postcode":"20100",
    "sg:province":"Guip\u00f9zcoa",
    "wof:name":"Plasticos De Lezo S.a.",
    "wof:placetype":"venue"
},
  "geometry": {"coordinates":[-1.8789340258,43.3262557983],"type":"Point"}
}