{
  "type": "Feature",
  "properties": {
    "iso:country":"ES",
    "sg:address":"Calle de Mar, 20",
    "sg:city":"Benlloch",
    "sg:orig_category":"Pescader\u00cdas (al Por Menor)",
    "sg:phone":"+34 964 33 92 12",
    "sg:postcode":"12181",
    "sg:province":"Castell\u00f3n",
    "wof:name":"Barreda Bernat Isabel",
    "wof:placetype":"venue"
},
  "geometry": {"coordinates":[0.0273669995,40.2103042603],"type":"Point"}
}