{
  "type": "Feature",
  "properties": {
    "iso:country":"ES",
    "sg:address":"Lazkaibar Kalea, 5",
    "sg:city":"Beasain",
    "sg:orig_category":"Aparcamientos (infraestructuras, Accesorios)",
    "sg:phone":"+34 943 88 45 64",
    "sg:postcode":"20200",
    "sg:province":"Guip\u00f9zcoa",
    "wof:name":"Irastorza Machain Jesus",
    "wof:placetype":"venue"
},
  "geometry": {"coordinates":[-2.1910400391,43.0493011475],"type":"Point"}
}