{
  "type": "Feature",
  "properties": {
    "iso:country":"ES",
    "sg:address":"Calle de Venus, 5",
    "sg:city":"Sanlucar",
    "sg:orig_category":"Psic\u00d3logos",
    "sg:phone":"+34 956 38 23 79",
    "sg:postcode":"11540",
    "sg:province":"C\u00e1diz",
    "wof:name":"Humanes Ceballos Juan Manuel",
    "wof:placetype":"venue"
},
  "geometry": {"coordinates":[-6.3444900513,36.7763595581],"type":"Point"}
}