{
  "type": "Feature",
  "properties": {
    "iso:country":"ES",
    "sg:address":"Plaz Espa\u00d1a, S/n",
    "sg:city":"Alcazar S. Juan",
    "sg:orig_category":"Carnicer\u00cdas, Carnicer\u00cdas",
    "sg:phone":"+34 926 54 51 01",
    "sg:postcode":"13600",
    "sg:province":"Ciudad Real",
    "wof:name":"Rubio Tejado Jose Luis",
    "wof:placetype":"venue"
},
  "geometry": {"coordinates":[-3.210203886,39.3900718689],"type":"Point"}
}