{
  "type": "Feature",
  "properties": {
    "addr:full":"Carrer de Muntaner, 172 Barcelona Barcelona 08036",
    "addr:housenumber":"172",
    "addr:postcode":"08036",
    "addr:street":"Carrer De Muntaner",
    "iso:country":"ES",
    "sg:address":"Carrer de Muntaner, 172",
    "sg:city":"Barcelona",
    "sg:orig_category":"Expertos Contables Pasantes Autorizados",
    "sg:phone":"+34 933 21 98 08",
    "sg:postcode":"08036",
    "sg:province":"Barcelona",
    "wof:name":"Ferrer Bures Daniel",
    "wof:placetype":"venue"
},
  "geometry": {"coordinates":[2.1526529789,41.3918952942],"type":"Point"}
}