{
  "type": "Feature",
  "properties": {
    "iso:country":"ES",
    "sg:address":"Calle de Andres Martinez, 27",
    "sg:city":"Cervera Del Rio Alhama",
    "sg:orig_category":"Loter\u00cda Y T\u00d3mbola",
    "sg:phone":"+34 941 19 89 84",
    "sg:postcode":"26520",
    "sg:province":"La Rioja",
    "wof:name":"Gonzalez Sesma Ana Julia",
    "wof:placetype":"venue"
},
  "geometry": {"coordinates":[-1.9565315247,42.0039405823],"type":"Point"}
}