{
  "type": "Feature",
  "properties": {
    "iso:country":"ES",
    "sg:address":"Calle de Rio Ca\u00d1amares, 12",
    "sg:city":"Alcala Henares",
    "sg:classifiers":[
        {
            "category":"Personal",
            "subcategory":"Barber",
            "type":"Services"
        }
    ],
    "sg:phone":"+34 918 83 67 20",
    "sg:postcode":"28804",
    "sg:province":"Madrid",
    "sg:tags":[
        "caballeros",
        "de",
        "peluqueros"
    ],
    "wof:name":"Gonzalez Buendia Raul",
    "wof:placetype":"venue"
},
  "geometry": {"coordinates":[-3.3641750813,40.4785385132],"type":"Point"}
}