{
  "type": "Feature",
  "properties": {
    "iso:country":"ES",
    "sg:address":"Calle de Buenos Aires, 1",
    "sg:city":"Ribadeo",
    "sg:orig_category":"Ense\u00d1anza Variada",
    "sg:phone":"+34 982 12 87 56",
    "sg:postcode":"27700",
    "sg:province":"Lugo",
    "wof:name":"Goyos Basanta Jose Maria",
    "wof:placetype":"venue"
},
  "geometry": {"coordinates":[-7.0393996239,43.5360488892],"type":"Point"}
}