{
  "type": "Feature",
  "properties": {
    "iso:country":"ES",
    "sg:address":"C/ Poeta Joan Valls, 12",
    "sg:city":"Alcoi",
    "sg:orig_category":"Colorantes, Colores Y Pigmentos (fabricaci\u00d3n, Al Por Mayor)",
    "sg:phone":"+34 966 52 03 36",
    "sg:postcode":"03803",
    "sg:province":"Alicante",
    "wof:name":"Marcial Gonzalez S. A.",
    "wof:placetype":"venue"
},
  "geometry": {"coordinates":[-0.4756850004,38.7020759583],"type":"Point"}
}