{
  "type": "Feature",
  "properties": {
    "addr:full":"San Roque Do Monte, 66 Cangas Pontevedra 36940",
    "addr:postcode":"36940",
    "iso:country":"ES",
    "sg:address":"San Roque Do Monte, 66",
    "sg:city":"Cangas",
    "sg:orig_category":"Plomeros",
    "sg:phone":"+34 986 30 48 08",
    "sg:postcode":"36940",
    "sg:province":"Pontevedra",
    "wof:name":"Lemos Molanes Jesus",
    "wof:placetype":"venue"
},
  "geometry": {"coordinates":[-8.7976932526,42.2769508362],"type":"Point"}
}