{
  "type": "Feature",
  "properties": {
    "addr:full":"Carrer de Francesc Macia, 18 Suredes D'en Mairo-grecs-muntanyeta Girona 17480",
    "addr:housenumber":"18",
    "addr:postcode":"17480",
    "addr:street":"Carrer De Francesc Macia",
    "iso:country":"ES",
    "sg:address":"Carrer de Francesc Macia, 18",
    "sg:city":"Suredes D'en Mairo-grecs-muntanyeta",
    "sg:orig_category":"Institutos De Belleza",
    "sg:phone":"+34 972 25 55 93",
    "sg:postcode":"17480",
    "sg:province":"Girona",
    "wof:name":"Maranjon-chapier  Catherine",
    "wof:placetype":"venue"
},
  "geometry": {"coordinates":[2.8309860229,41.9961509705],"type":"Point"}
}