{
  "type": "Feature",
  "properties": {
    "iso:country":"ES",
    "sg:address":"Calle de Jose Gurruchaga, 5",
    "sg:city":"Santurtzi",
    "sg:orig_category":"Carnicer\u00cdas, Carnicer\u00cdas",
    "sg:phone":"+34 944 61 03 21",
    "sg:postcode":"48980",
    "sg:province":"Vizcaya",
    "wof:name":"Garmendia Herranz Antonio Maria",
    "wof:placetype":"venue"
},
  "geometry": {"coordinates":[-3.0350809097,43.3277320862],"type":"Point"}
}