{
  "type": "Feature",
  "properties": {
    "addr:full":"Calle de Fundicion, S/n Rodalquilar Almer\u00eda 04115",
    "addr:postcode":"04115",
    "addr:street":"Calle De Fundicion S / N;Almeri\u0301A",
    "iso:country":"ES",
    "sg:address":"Calle de Fundicion, S/n",
    "sg:city":"Rodalquilar",
    "sg:orig_category":"Turismo",
    "sg:phone":"+34 950 38 98 25",
    "sg:postcode":"04115",
    "sg:province":"Almer\u00eda",
    "wof:name":"Ecoalmeria Iniciativas Ambientales S.l.",
    "wof:placetype":"venue"
},
  "geometry": {"coordinates":[-2.0423789024,36.8466186523],"type":"Point"}
}