{
  "type": "Feature",
  "properties": {
    "iso:country":"ES",
    "sg:address":"Avda Paz (la), 26",
    "sg:city":"Villena",
    "sg:orig_category":"Fabricaci\u00d3n, Importaci\u00d3n De L\u00c1mparas Y Bombillas",
    "sg:phone":"+34 965 34 84 56",
    "sg:postcode":"03400",
    "sg:province":"Alicante",
    "wof:name":"Luz Galery S.l.",
    "wof:placetype":"venue"
},
  "geometry": {"coordinates":[-0.867865026,38.645275116],"type":"Point"}
}