{
  "type": "Feature",
  "properties": {
    "addr:full":"Carrer de Tenor Masini, 6 Barcelona Barcelona 08028",
    "addr:housenumber":"6",
    "addr:postcode":"08028",
    "addr:street":"Carrer De Tenor Masini",
    "iso:country":"ES",
    "sg:address":"Carrer de Tenor Masini, 6",
    "sg:city":"Barcelona",
    "sg:orig_category":"Restaurantes",
    "sg:phone":"+34 934 91 52 68",
    "sg:postcode":"08028",
    "sg:province":"Barcelona",
    "wof:name":"Garcia Cisneros Carmen",
    "wof:placetype":"venue"
},
  "geometry": {"coordinates":[2.1325690746,41.3759307861],"type":"Point"}
}