{
  "type": "Feature",
  "properties": {
    "addr:full":"La Hondura, 9 Puerto Santiago Santa Cruz De Tenerife 38683",
    "addr:housenumber":"9",
    "addr:postcode":"38683",
    "addr:street":"Hondura",
    "iso:country":"ES",
    "sg:address":"La Hondura, 9",
    "sg:city":"Puerto Santiago",
    "sg:orig_category":"Deportes Y Ocio: Art\u00cdculos Y Equipos (al Por Mayor)",
    "sg:phone":"+34 922 86 22 58",
    "sg:postcode":"38683",
    "sg:province":"Santa Cruz De Tenerife",
    "wof:name":"Supsasol S.l.",
    "wof:placetype":"venue"
},
  "geometry": {"coordinates":[-16.8446083069,28.2388057709],"type":"Point"}
}