{
  "type": "Feature",
  "properties": {
    "addr:full":"Calle de Jose Maria Lacasa, 14 Huesca Huesca 22001",
    "addr:housenumber":"14",
    "addr:postcode":"22001",
    "addr:street":"Calle De Jose Maria Lacasa",
    "iso:country":"ES",
    "sg:address":"Calle de Jose Maria Lacasa, 14",
    "sg:city":"Huesca",
    "sg:orig_category":"Empresas De Carpinter\u00cda De Madera",
    "sg:phone":"+34 974 24 35 66",
    "sg:postcode":"22001",
    "sg:province":"Huesca",
    "wof:name":"Izuel Gracia Jose Maria",
    "wof:placetype":"venue"
},
  "geometry": {"coordinates":[-0.4026759863,42.137928009],"type":"Point"}
}