{
  "type": "Feature",
  "properties": {
    "iso:country":"ES",
    "sg:address":"Carrer de Rocafort, 240",
    "sg:city":"Barcelona",
    "sg:orig_category":"Arquitectos",
    "sg:phone":"+34 933 22 20 19",
    "sg:postcode":"08029",
    "sg:province":"Barcelona",
    "wof:name":"Sanchez Domenech Ignacio",
    "wof:placetype":"venue"
},
  "geometry": {"coordinates":[2.1446781158,41.3859939575],"type":"Point"}
}