{
  "type": "Feature",
  "properties": {
    "iso:country":"ES",
    "sg:address":"Libertad, 14",
    "sg:city":"Algete",
    "sg:orig_category":"Inmobiliaria (agencias)",
    "sg:phone":"+34 916 28 70 85",
    "sg:postcode":"28110",
    "sg:province":"Madrid",
    "wof:name":"De Zulueta Poves Ricardo",
    "wof:placetype":"venue"
},
  "geometry": {"coordinates":[-3.5406610966,40.6068916321],"type":"Point"}
}