{
  "type": "Feature",
  "properties": {
    "addr:full":"Avda Juan Carlos I, Rey, 18 Melilla Melilla 52001",
    "addr:housenumber":"18",
    "addr:postcode":"52001",
    "addr:street":"Avda Juan Carlos I Rey",
    "iso:country":"ES",
    "sg:address":"Avda Juan Carlos I, Rey, 18",
    "sg:city":"Melilla",
    "sg:orig_category":"Confecci\u00d3n (fabricaci\u00d3n, Al Por Mayor)",
    "sg:phone":"+34 952 67 27 99",
    "sg:postcode":"52001",
    "sg:province":"Melilla",
    "wof:name":"Cohen Bengio Salomon Meir",
    "wof:placetype":"venue"
},
  "geometry": {"coordinates":[-2.9401979446,35.2935714722],"type":"Point"}
}