{
  "type": "Feature",
  "properties": {
    "addr:full":"Calle de Errekatxu, 15 Mungia Vizcaya 48100",
    "addr:housenumber":"15",
    "addr:postcode":"48100",
    "addr:street":"Calle De Errekatxu",
    "iso:country":"ES",
    "sg:address":"Calle de Errekatxu, 15",
    "sg:city":"Mungia",
    "sg:orig_category":"Comercio De Piezas De Recambio Y De Accesorios De Veh\u00cdculos, Veh\u00cdculos Industriales",
    "sg:phone":"+34 946 74 33 24",
    "sg:postcode":"48100",
    "sg:province":"Vizcaya",
    "wof:name":"Auto Industrial Basconia S. A.",
    "wof:placetype":"venue"
},
  "geometry": {"coordinates":[-2.8489289284,43.3545417786],"type":"Point"}
}