{
  "type": "Feature",
  "properties": {
    "iso:country":"ES",
    "sg:address":"C/ Sant Eloi, 9",
    "sg:city":"Alcoi",
    "sg:orig_category":"Empresas De Carpinter\u00cda De Madera",
    "sg:phone":"+34 965 33 20 37",
    "sg:postcode":"03804",
    "sg:province":"Alicante",
    "wof:name":"Carpinteria Pico S.l.",
    "wof:placetype":"venue"
},
  "geometry": {"coordinates":[-0.465918988,38.7090988159],"type":"Point"}
}