{
  "type": "Feature",
  "properties": {
    "iso:country":"ES",
    "sg:address":"Calle de Cervantes, 27",
    "sg:city":"Villafranca De Los Caballeros",
    "sg:orig_category":"Carnicer\u00cdas, Carnicer\u00cdas",
    "sg:phone":"+34 926 57 83 07",
    "sg:postcode":"45730",
    "sg:province":"Toledo",
    "wof:name":"Carrion Reino Jesus",
    "wof:placetype":"venue"
},
  "geometry": {"coordinates":[-3.3599152565,39.4269828796],"type":"Point"}
}