{
  "type": "Feature",
  "properties": {
    "addr:full":"Calle de Anboto, 7 Vitoria-gasteiz \u00c1lava 01006",
    "addr:housenumber":"7",
    "addr:postcode":"01006",
    "addr:street":"Calle De Anboto",
    "iso:country":"ES",
    "sg:address":"Calle de Anboto, 7",
    "sg:city":"Vitoria-gasteiz",
    "sg:orig_category":"Material Y Herramientas Agr\u00cdcolas",
    "sg:phone":"+34 945 13 35 24",
    "sg:postcode":"01006",
    "sg:province":"\u00c1lava",
    "wof:name":"Agrirepuestos S.l.",
    "wof:placetype":"venue"
},
  "geometry": {"coordinates":[-2.6562459469,42.8296432495],"type":"Point"}
}