{
  "type": "Feature",
  "properties": {
    "iso:country":"ES",
    "sg:address":"Carrer de Caputxins (dels), 22",
    "sg:city":"Tarragona",
    "sg:orig_category":"Molduras, Junquillos, Listones Y Molduras Perforadas",
    "sg:phone":"+34 977 22 11 59",
    "sg:postcode":"43001",
    "sg:province":"Tarragona",
    "wof:name":"Berbel Fernandez Maria Juana",
    "wof:placetype":"venue"
},
  "geometry": {"coordinates":[1.2473319769,41.113571167],"type":"Point"}
}