{
  "type": "Feature",
  "properties": {
    "addr:full":"Carrer de Wilson, 22 Terrassa Barcelona 08223",
    "addr:housenumber":"22",
    "addr:postcode":"08223",
    "addr:street":"Carrer De Wilson",
    "iso:country":"ES",
    "sg:address":"Carrer de Wilson, 22",
    "sg:city":"Terrassa",
    "sg:orig_category":"Frutas Y Legumbres Frescas (al Por Mayor)",
    "sg:phone":"+34 937 85 12 49",
    "sg:postcode":"08223",
    "sg:province":"Barcelona",
    "wof:name":"Aceitunas Y Encurtidos Ropri S.l.",
    "wof:placetype":"venue"
},
  "geometry": {"coordinates":[2.0217177868,41.5542984009],"type":"Point"}
}