{
  "type": "Feature",
  "properties": {
    "iso:country":"ES",
    "sg:address":"Calle de Sierra Toledana, 51",
    "sg:city":"Madrid",
    "sg:orig_category":"Empresas De Carpinter\u00cda De Madera",
    "sg:phone":"+34 915 51 01 46",
    "sg:postcode":"28038",
    "sg:province":"Madrid",
    "wof:name":"Puertas Monica S.l.",
    "wof:placetype":"venue"
},
  "geometry": {"coordinates":[-3.6597158909,40.4039840698],"type":"Point"}
}