{
  "type": "Feature",
  "properties": {
    "iso:country":"ES",
    "sg:address":"Avda Camino De Los Hondos Del, 13",
    "sg:city":"Fraga",
    "sg:orig_category":"Bancos",
    "sg:phone":"+34 974 47 13 45",
    "sg:postcode":"22520",
    "sg:province":"Huesca",
    "wof:name":"Bordados Zanmor S.l.",
    "wof:placetype":"venue"
},
  "geometry": {"coordinates":[0.3438299894,41.5223045349],"type":"Point"}
}