{
  "type": "Feature",
  "properties": {
    "addr:full":"Avda Mendavia, 32 Logro\u00f1o La Rioja 26006",
    "addr:housenumber":"32",
    "addr:postcode":"26006",
    "addr:street":"Avda Mendavia;Rioja",
    "iso:country":"ES",
    "sg:address":"Avda Mendavia, 32",
    "sg:city":"Logro\u00f1o",
    "sg:orig_category":"Asociaciones Humanitarias, De Cooperaci\u00d3n, De Acci\u00d3n Social",
    "sg:phone":"+34 941 23 36 97",
    "sg:postcode":"26006",
    "sg:province":"La Rioja",
    "wof:name":"Fundacion Aspace-rioja",
    "wof:placetype":"venue"
},
  "geometry": {"coordinates":[-2.4049019814,42.4734802246],"type":"Point"}
}