{
  "type": "Feature",
  "properties": {
    "addr:full":"Calle de Doctor Martin Arevalo, 4 Madrid Madrid 28021",
    "addr:housenumber":"4",
    "addr:postcode":"28021",
    "addr:street":"Calle De Doctor Martin Arevalo",
    "iso:country":"ES",
    "sg:address":"Calle de Doctor Martin Arevalo, 4",
    "sg:city":"Madrid",
    "sg:classifiers":[
        {
            "category":"Autos & Motor Vehicles",
            "subcategory":"Automobile Sales",
            "type":"Retail Goods"
        }
    ],
    "sg:phone":"+34 917 98 01 80",
    "sg:postcode":"28021",
    "sg:province":"Madrid",
    "wof:name":"Victoria Medina Daniel",
    "wof:placetype":"venue"
},
  "geometry": {"coordinates":[-3.7083179951,40.3462486267],"type":"Point"}
}