{
  "type": "Feature",
  "properties": {
    "iso:country":"ES",
    "sg:address":"Calle de Pablo Laloux, 13",
    "sg:city":"Salinas",
    "sg:orig_category":"M\u00c9dicos: Cardiolog\u00cda Y Afecciones Cardiovasculares",
    "sg:phone":"+34 985 50 14 87",
    "sg:postcode":"33405",
    "sg:province":"Asturias",
    "wof:name":"Casares Garcia Gerardo",
    "wof:placetype":"venue"
},
  "geometry": {"coordinates":[-5.9541759491,43.5785102844],"type":"Point"}
}