{
  "type": "Feature",
  "properties": {
    "addr:full":"Calle de Acequia Alta, 4 Arucas Las Palmas 35400",
    "addr:housenumber":"4",
    "addr:postcode":"35400",
    "addr:street":"Calle De Acequia Alta",
    "iso:country":"ES",
    "sg:address":"Calle de Acequia Alta, 4",
    "sg:city":"Arucas",
    "sg:orig_category":"Textil",
    "sg:phone":"+34 928 63 46 87",
    "sg:postcode":"35400",
    "sg:province":"Las Palmas",
    "wof:name":"Socas Malvarez Armando",
    "wof:placetype":"venue"
},
  "geometry": {"coordinates":[-15.5248355865,28.1205635071],"type":"Point"}
}