{
  "type": "Feature",
  "properties": {
    "iso:country":"ES",
    "sg:address":"Carrer de Industria, 8",
    "sg:city":"Valls",
    "sg:orig_category":"Poller\u00cda Y Caza (al Por Menor)",
    "sg:phone":"+34 977 61 33 89",
    "sg:postcode":"43800",
    "sg:province":"Tarragona",
    "wof:name":"Lopez Garcia Maria",
    "wof:placetype":"venue"
},
  "geometry": {"coordinates":[1.2503780127,41.2873306274],"type":"Point"}
}