{
  "type": "Feature",
  "properties": {
    "addr:full":"Calle de Tomas Breton, 46 Madrid Madrid 28045",
    "addr:housenumber":"46",
    "addr:postcode":"madrid;28045",
    "addr:street":"Calle De Tomas Breton",
    "iso:country":"ES",
    "sg:address":"Calle de Tomas Breton, 46",
    "sg:city":"Madrid",
    "sg:orig_category":"Rectificaci\u00d3n, Mecanizado, Fresado",
    "sg:phone":"+34 914 68 19 90",
    "sg:postcode":"28045",
    "sg:province":"Madrid",
    "wof:name":"Tejedor Tapia Antonio",
    "wof:placetype":"venue"
},
  "geometry": {"coordinates":[-3.6923360825,40.3972930908],"type":"Point"}
}