{
  "type": "Feature",
  "properties": {
    "iso:country":"ES",
    "sg:address":"Plaz Sancho Garcia, 35",
    "sg:city":"Espinosa De Los Monteros",
    "sg:orig_category":"Iglesia Cat\u00d3lica",
    "sg:phone":"+34 947 12 01 52",
    "sg:postcode":"09560",
    "sg:province":"Burgos",
    "wof:name":"Parroquia De Santa Cecilia",
    "wof:placetype":"venue"
},
  "geometry": {"coordinates":[-3.5472691059,43.0784416199],"type":"Point"}
}