{
  "type": "Feature",
  "properties": {
    "addr:full":"Carrer de Ausias Carbonell, 12 Xixona Alicante 03100",
    "addr:housenumber":"12",
    "addr:postcode":"03100",
    "addr:street":"Carrer De Ausias Carbonell",
    "iso:country":"ES",
    "sg:address":"Carrer de Ausias Carbonell, 12",
    "sg:city":"Xixona",
    "sg:orig_category":"Venta, Montaje De Neum\u00c1ticos",
    "sg:phone":"+34 965 61 21 06",
    "sg:postcode":"03100",
    "sg:province":"Alicante",
    "wof:name":"Martinez Gomez Juan Manuel",
    "wof:placetype":"venue"
},
  "geometry": {"coordinates":[-0.5058990121,38.5401000977],"type":"Point"}
}