{
  "type": "Feature",
  "properties": {
    "addr:full":"Calle de Zumel, 12 Madrid Madrid 28037",
    "addr:housenumber":"12",
    "addr:postcode":"madrid;28037",
    "addr:street":"Calle De Zumel",
    "iso:country":"ES",
    "sg:address":"Calle de Zumel, 12",
    "sg:city":"Madrid",
    "sg:orig_category":"Bisuter\u00cda, Joyer\u00cda, Relojer\u00cda (al Por Menor)",
    "sg:phone":"+34 913 04 75 07",
    "sg:postcode":"28037",
    "sg:province":"Madrid",
    "wof:name":"Narvaez Villa Coral",
    "wof:placetype":"venue"
},
  "geometry": {"coordinates":[-3.6260929108,40.4290313721],"type":"Point"}
}