{
  "type": "Feature",
  "properties": {
    "iso:country":"ES",
    "sg:address":"Carrer de Beethoven, 41",
    "sg:city":"Santa Coloma De Gramenet",
    "sg:orig_category":"Discapacitados",
    "sg:phone":"+34 933 91 71 90",
    "sg:postcode":"08922",
    "sg:province":"Barcelona",
    "wof:name":"Fundacion Privada Aspanide",
    "wof:placetype":"venue"
},
  "geometry": {"coordinates":[2.2178809643,41.4519119263],"type":"Point"}
}