{
  "type": "Feature",
  "properties": {
    "iso:country":"ES",
    "sg:address":"Calle de Fray Atanasio Lobera, 31",
    "sg:city":"Herce",
    "sg:orig_category":"Agencias Y Agentes Comerciales, Representantes",
    "sg:phone":"+34 941 40 70 48",
    "sg:postcode":"26584",
    "sg:province":"La Rioja",
    "wof:name":"Garrido Iba\u00f1ez Silvia",
    "wof:placetype":"venue"
},
  "geometry": {"coordinates":[-2.1708860397,42.2129402161],"type":"Point"}
}