{
  "type": "Feature",
  "properties": {
    "iso:country":"ES",
    "sg:address":"G. Boyvia, 15",
    "sg:city":"Callosa Segura",
    "sg:orig_category":"Fabrica De Charcuter\u00cda",
    "sg:phone":"+34 965 31 29 46",
    "sg:postcode":"03360",
    "sg:province":"Alicante",
    "wof:name":"Navarro Berna Antonio",
    "wof:placetype":"venue"
},
  "geometry": {"coordinates":[-0.8776689768,38.1256752014],"type":"Point"}
}