{
  "type": "Feature",
  "properties": {
    "iso:country":"ES",
    "sg:address":"Av Paral.lel, 110",
    "sg:city":"Barcelona",
    "sg:orig_category":"Guarder\u00cdas",
    "sg:phone":"+34 933 29 06 68",
    "sg:postcode":"08015",
    "sg:province":"Barcelona",
    "wof:name":"Nadal Torres Maria Montserrat",
    "wof:placetype":"venue"
},
  "geometry": {"coordinates":[2.164222002,41.3751296997],"type":"Point"}
}