{
  "type": "Feature",
  "properties": {
    "addr:full":"Avda Blas Infante, S/n Algeciras C\u00e1diz 11201",
    "addr:postcode":"11201",
    "addr:street":"Avda Blas Infante S / N;Ca\u0301Diz",
    "iso:country":"ES",
    "sg:address":"Avda Blas Infante, S/n",
    "sg:city":"Algeciras",
    "sg:orig_category":"M\u00c9dicos: Cirug\u00cda Pl\u00c1stica, Reconstructiva Y Est\u00c9tica",
    "sg:phone":"+34 956 65 19 82",
    "sg:postcode":"11201",
    "sg:province":"C\u00e1diz",
    "wof:name":"Campos Marti Maria Luz",
    "wof:placetype":"venue"
},
  "geometry": {"coordinates":[-5.448428154,36.1333808899],"type":"Point"}
}