{
  "type": "Feature",
  "properties": {
    "addr:full":"Calle de Padre Melchor Cano, 17 Guadalajara Guadalajara 19002",
    "addr:housenumber":"17",
    "addr:postcode":"19002",
    "addr:street":"Calle De Padre Melchor Cano",
    "iso:country":"ES",
    "sg:address":"Calle de Padre Melchor Cano, 17",
    "sg:city":"Guadalajara",
    "sg:classifiers":[
        {
            "category":"Personal",
            "subcategory":"Barber",
            "type":"Services"
        }
    ],
    "sg:phone":"+34 949 22 00 31",
    "sg:postcode":"19002",
    "sg:province":"Guadalajara",
    "sg:tags":[
        "caballeros",
        "de",
        "peluqueros"
    ],
    "wof:name":"Diaz Juarez Carlos",
    "wof:placetype":"venue"
},
  "geometry": {"coordinates":[-3.1609389782,40.6279525757],"type":"Point"}
}