{
  "type": "Feature",
  "properties": {
    "addr:full":"Calle de Merida, 4 Madrid Madrid 28030",
    "addr:housenumber":"4",
    "addr:postcode":"28030",
    "addr:street":"Calle De Merida",
    "iso:country":"ES",
    "sg:address":"Calle de Merida, 4",
    "sg:city":"Madrid",
    "sg:orig_category":"Comercio De Piezas De Recambio Y De Accesorios De Veh\u00cdculos, Veh\u00cdculos Industriales",
    "sg:phone":"+34 917 72 60 65",
    "sg:postcode":"28030",
    "sg:province":"Madrid",
    "wof:name":"Rodriguez Martinez Venancio",
    "wof:placetype":"venue"
},
  "geometry": {"coordinates":[-3.6368639469,40.4078979492],"type":"Point"}
}