{
  "type": "Feature",
  "properties": {
    "addr:full":"Carrer de Castillejos, 408 Barcelona Barcelona 08024",
    "addr:housenumber":"408",
    "addr:postcode":"08024",
    "addr:street":"Carrer De Castillejos",
    "iso:country":"ES",
    "sg:address":"Carrer de Castillejos, 408",
    "sg:city":"Barcelona",
    "sg:orig_category":"Molduras, Junquillos, Listones Y Molduras Perforadas",
    "sg:phone":"+34 933 48 17 23",
    "sg:postcode":"08024",
    "sg:province":"Barcelona",
    "wof:name":"Martin Campo Alfonso",
    "wof:placetype":"venue"
},
  "geometry": {"coordinates":[2.1693320274,41.4133796692],"type":"Point"}
}