{
  "type": "Feature",
  "properties": {
    "iso:country":"ES",
    "sg:address":"Calle de Marques Del Duero, 21",
    "sg:city":"San Pedro Alcantara",
    "sg:orig_category":"Edici\u00d3n De Diarios, Revistas, Boletines",
    "sg:phone":"+34 952 78 01 07",
    "sg:postcode":"29670",
    "sg:province":"M\u00e1laga",
    "wof:name":"Editorial De Informaciones Y Monograficos S.l.",
    "wof:placetype":"venue"
},
  "geometry": {"coordinates":[-4.9893407822,36.4858512878],"type":"Point"}
}