{
  "type": "Feature",
  "properties": {
    "addr:full":"Calle de Jesus De San Antonio (de), 22 Coslada Madrid 28820",
    "addr:postcode":"28820",
    "addr:street":"Calle De Jesus De San Antonio",
    "iso:country":"ES",
    "sg:address":"Calle de Jesus De San Antonio (de), 22",
    "sg:city":"Coslada",
    "sg:orig_category":"M\u00c9dicos: Medicina Y Biolog\u00cda Del Deporte",
    "sg:phone":"+34 916 69 79 79",
    "sg:postcode":"28820",
    "sg:province":"Madrid",
    "wof:name":"Sata Centro Medico Deportivo S.l.l.",
    "wof:placetype":"venue"
},
  "geometry": {"coordinates":[-3.5380659103,40.4253768921],"type":"Point"}
}