{
  "type": "Feature",
  "properties": {
    "addr:full":"Calle de Fray Luis De Leon, 4 Palma Islas Baleares 07011",
    "addr:housenumber":"4",
    "addr:postcode":"07011",
    "addr:street":"Calle De Fray Luis De Leon",
    "iso:country":"ES",
    "sg:address":"Calle de Fray Luis De Leon, 4",
    "sg:city":"Palma",
    "sg:orig_category":"Perfumer\u00cda Y Cosm\u00c9tica (fabricaci\u00d3n, Al Por Mayor)",
    "sg:phone":"+34 971 22 10 08",
    "sg:postcode":"07011",
    "sg:province":"Islas Baleares",
    "sg:website":"www.mcisl.com",
    "wof:name":"M.c.i. Consulting S.l.",
    "wof:placetype":"venue"
},
  "geometry": {"coordinates":[2.6410810947,39.5738182068],"type":"Point"}
}