{
  "type": "Feature",
  "properties": {
    "addr:full":"Avda Pablo Iglesias, 22 Loranca Madrid 28942",
    "addr:housenumber":"22",
    "addr:postcode":"28942",
    "addr:street":"Avda Pablo Iglesias",
    "iso:country":"ES",
    "sg:address":"Avda Pablo Iglesias, 22",
    "sg:city":"Loranca",
    "sg:orig_category":"Estilistas Y Estudios De Estilo De Corte Y Confecci\u00d3n",
    "sg:phone":"+34 916 04 78 87",
    "sg:postcode":"28942",
    "sg:province":"Madrid",
    "wof:name":"Zarramen S.l.",
    "wof:placetype":"venue"
},
  "geometry": {"coordinates":[-3.8326547146,40.2991142273],"type":"Point"}
}