{
  "type": "Feature",
  "properties": {
    "iso:country":"ES",
    "sg:address":"Carrer de Maragall, 18",
    "sg:city":"S. Adria Besos",
    "sg:orig_category":"Asociaciones Y Clubs Deportivos",
    "sg:phone":"+34 934 62 18 56",
    "sg:postcode":"08930",
    "sg:province":"Barcelona",
    "wof:name":"Pe\u00f1a Barcelonista Sant Adria Del Besos",
    "wof:placetype":"venue"
},
  "geometry": {"coordinates":[2.2185740471,41.4292793274],"type":"Point"}
}