{
  "type": "Feature",
  "properties": {
    "iso:country":"ES",
    "sg:address":"Carrer de Azorin, 9",
    "sg:city":"Castalla",
    "sg:orig_category":"Reposter\u00cdas",
    "sg:phone":"+34 966 56 10 60",
    "sg:postcode":"03420",
    "sg:province":"Alicante",
    "wof:name":"Forn De Pa Seva S.l.",
    "wof:placetype":"venue"
},
  "geometry": {"coordinates":[-0.6702489853,38.5921897888],"type":"Point"}
}