{
  "type": "Feature",
  "properties": {
    "addr:full":"Calle de Sabino Arana, 30 Sopelana Vizcaya 48600",
    "addr:housenumber":"30",
    "addr:postcode":"48600",
    "addr:street":"Calle De Sabino Arana",
    "iso:country":"ES",
    "sg:address":"Calle de Sabino Arana, 30",
    "sg:city":"Sopelana",
    "sg:orig_category":"Confecci\u00d3n (fabricaci\u00d3n, Al Por Mayor)",
    "sg:phone":"+34 946 76 37 16",
    "sg:postcode":"48600",
    "sg:province":"Vizcaya",
    "wof:name":"El Rincon De Eva S.l",
    "wof:placetype":"venue"
},
  "geometry": {"coordinates":[-2.9781160355,43.3812675476],"type":"Point"}
}