{
  "type": "Feature",
  "properties": {
    "addr:full":"Urbanizacion Teran, 14 Vivar Del Cid Burgos 09140",
    "addr:housenumber":"14",
    "addr:postcode":"09140",
    "addr:street":"Teran",
    "iso:country":"ES",
    "sg:address":"Urbanizacion Teran, 14",
    "sg:city":"Vivar Del Cid",
    "sg:orig_category":"Empresas De Pintura Y Revestimientos",
    "sg:phone":"+34 947 29 23 21",
    "sg:postcode":"09140",
    "sg:province":"Burgos",
    "wof:name":"Rastrilla Calleja Miguel",
    "wof:placetype":"venue"
},
  "geometry": {"coordinates":[-3.6831541061,42.4509162903],"type":"Point"}
}