{
  "type": "Feature",
  "properties": {
    "iso:country":"ES",
    "sg:address":"Calle de Maldonado, 73",
    "sg:city":"Madrid",
    "sg:orig_category":"Frutas, Legumbres Frescas Y Tempranas (al Por Menor)",
    "sg:phone":"+34 914 02 19 57",
    "sg:postcode":"28006",
    "sg:province":"Madrid",
    "wof:name":"Brazuelo Seves Julian",
    "wof:placetype":"venue"
},
  "geometry": {"coordinates":[-3.6743340492,40.4335746765],"type":"Point"}
}