{
  "type": "Feature",
  "properties": {
    "iso:country":"ES",
    "sg:address":"Urb. Colina, S/n",
    "sg:city":"Torremolinos",
    "sg:orig_category":"Pintura Y Barniz (al Por Menor)",
    "sg:phone":"+34 952 37 19 07",
    "sg:postcode":"29620",
    "sg:province":"M\u00e1laga",
    "wof:name":"Medina Sanchez Salvador",
    "wof:placetype":"venue"
},
  "geometry": {"coordinates":[-4.5160393715,36.6265563965],"type":"Point"}
}