{
  "type": "Feature",
  "properties": {
    "addr:full":"Calle de Juanelo, 18 Madrid Madrid 28012",
    "addr:housenumber":"18",
    "addr:postcode":"madrid;28012",
    "addr:street":"Calle De Juanelo",
    "iso:country":"ES",
    "sg:address":"Calle de Juanelo, 18",
    "sg:city":"Madrid",
    "sg:orig_category":"Ropa Para Ni\u00d1os (al Por Menor)",
    "sg:phone":"+34 914 20 07 82",
    "sg:postcode":"28012",
    "sg:province":"Madrid",
    "wof:name":"Huang  Haishao",
    "wof:placetype":"venue"
},
  "geometry": {"coordinates":[-3.7062420845,40.4112968445],"type":"Point"}
}