{
  "type": "Feature",
  "properties": {
    "iso:country":"ES",
    "sg:address":"Pl Bonanova, 10",
    "sg:city":"Barcelona",
    "sg:orig_category":"T\u00c9cnicos Veterinarios",
    "sg:phone":"+34 932 11 02 04",
    "sg:postcode":"08022",
    "sg:province":"Barcelona",
    "wof:name":"Sterry Ballus Taryn",
    "wof:placetype":"venue"
},
  "geometry": {"coordinates":[2.1333699226,41.4061393738],"type":"Point"}
}