{
  "type": "Feature",
  "properties": {
    "iso:country":"ES",
    "sg:address":"Calle de Maria Inmaculada, 14",
    "sg:city":"Armunia",
    "sg:orig_category":"Transporte En General",
    "sg:phone":"+34 987 26 20 11",
    "sg:postcode":"24009",
    "sg:province":"Le\u00f3n",
    "wof:name":"Mata Gonzalez Froilan",
    "wof:placetype":"venue"
},
  "geometry": {"coordinates":[-5.584564209,42.5831336975],"type":"Point"}
}