{
  "type": "Feature",
  "properties": {
    "addr:full":"Calle de San Juan Bautista, 14 Santa Cruz De Tenerife Santa Cruz De Tenerife 38002",
    "addr:housenumber":"14",
    "addr:postcode":"38002",
    "addr:street":"Calle De San",
    "iso:country":"ES",
    "sg:address":"Calle de San Juan Bautista, 14",
    "sg:city":"Santa Cruz De Tenerife",
    "sg:orig_category":"Inmobiliaria (agencias)",
    "sg:phone":"+34 922 24 84 13",
    "sg:postcode":"38002",
    "sg:province":"Santa Cruz De Tenerife",
    "wof:name":"Mahersu S.a.",
    "wof:placetype":"venue"
},
  "geometry": {"coordinates":[-16.2490520477,28.469165802],"type":"Point"}
}