{
  "type": "Feature",
  "properties": {
    "iso:country":"ES",
    "sg:address":"Urb El Rocio, 65",
    "sg:city":"Coria Rio",
    "sg:orig_category":"Construcciones Navales Y Fluviales",
    "sg:phone":"+34 955 95 00 74",
    "sg:postcode":"41100",
    "sg:province":"Sevilla",
    "wof:name":"Guerrero Torres Maria Jose",
    "wof:placetype":"venue"
},
  "geometry": {"coordinates":[-6.0509738922,37.2873153687],"type":"Point"}
}