{
  "type": "Feature",
  "properties": {
    "addr:full":"Ctra. V-alquian, Km. 0001,0 Viator Almer\u00eda 04240",
    "addr:postcode":"04240",
    "addr:street":"Ctra. V-Alquian Km. 0001,0 Viator Almeri\u0301A",
    "iso:country":"ES",
    "sg:address":"Ctra. V-alquian, Km. 0001,0",
    "sg:city":"Viator",
    "sg:orig_category":"Maquinaria Para Industrias Diversas",
    "sg:phone":"+34 950 30 41 04",
    "sg:postcode":"04240",
    "sg:province":"Almer\u00eda",
    "wof:name":"Almesu S.l.",
    "wof:placetype":"venue"
},
  "geometry": {"coordinates":[-2.4223577976,36.874168396],"type":"Point"}
}