{
  "type": "Feature",
  "properties": {
    "addr:full":"Carrer de Cami Roma, 73 Granollers Barcelona 08402",
    "addr:housenumber":"73",
    "addr:postcode":"08402",
    "addr:street":"Carrer De;Roma",
    "iso:country":"ES",
    "sg:address":"Carrer de Cami Roma, 73",
    "sg:city":"Granollers",
    "sg:orig_category":"Herramientas Manuales (fabricaci\u00d3n, Al Por Mayor)",
    "sg:phone":"+34 938 46 43 92",
    "sg:postcode":"08402",
    "sg:province":"Barcelona",
    "wof:name":"Comercial Marvi Eines 1 S.l.",
    "wof:placetype":"venue"
},
  "geometry": {"coordinates":[2.2927000523,41.6173706055],"type":"Point"}
}