{
  "type": "Feature",
  "properties": {
    "iso:country":"ES",
    "sg:address":"Plaz Espa\u00d1a, 12",
    "sg:city":"Valladolid",
    "sg:orig_category":"Agentes De Seguros",
    "sg:phone":"+34 983 21 94 95",
    "sg:postcode":"47001",
    "sg:province":"Valladolid",
    "wof:name":"2001-sys Correduria De Seguros S.l.",
    "wof:placetype":"venue"
},
  "geometry": {"coordinates":[-4.729693,41.650513],"type":"Point"}
}