{
  "type": "Feature",
  "properties": {
    "iso:country":"ES",
    "sg:address":"Calle de Agustin Del Ca\u00d1izo, 6",
    "sg:city":"Salamanca",
    "sg:orig_category":"Psic\u00d3logos",
    "sg:phone":"+34 923 12 16 27",
    "sg:postcode":"37007",
    "sg:province":"Salamanca",
    "wof:name":"Palomo Alvarez Charo",
    "wof:placetype":"venue"
},
  "geometry": {"coordinates":[-5.6672148705,40.9716072083],"type":"Point"}
}