{
  "type": "Feature",
  "properties": {
    "iso:country":"ES",
    "sg:address":"Calle de Miro, 29",
    "sg:city":"Cadrete",
    "sg:orig_category":"Fabricaci\u00d3n Y Venta De Volquetes Y Remolques",
    "sg:phone":"+34 976 12 63 27",
    "sg:postcode":"50420",
    "sg:province":"Zaragoza",
    "sg:website":"www.asali.es",
    "wof:name":"Asali S.l.",
    "wof:placetype":"venue"
},
  "geometry": {"coordinates":[-0.968272686,41.5612602234],"type":"Point"}
}