{
  "type": "Feature",
  "properties": {
    "iso:country":"ES",
    "sg:address":"Pla\u00c7 Temple (del), 1",
    "sg:city":"Grau I Platja",
    "sg:orig_category":"Molduras, Junquillos, Listones Y Molduras Perforadas",
    "sg:phone":"+34 962 84 10 07",
    "sg:postcode":"46730",
    "sg:province":"Valencia",
    "wof:name":"Hoscorbi S.l.",
    "wof:placetype":"venue"
},
  "geometry": {"coordinates":[-0.1664949954,38.9994888306],"type":"Point"}
}