{
  "type": "Feature",
  "properties": {
    "iso:country":"ES",
    "sg:address":"Av. Blanco Rajoy, 35",
    "sg:city":"Vimianzo",
    "sg:orig_category":"Comercio, Reparaci\u00d3n De Motocicletas, Bicicletas Y Piezas Sueltas",
    "sg:phone":"+34 981 71 61 08",
    "sg:postcode":"15120",
    "sg:province":"La Coru\u00f1a",
    "wof:name":"Perez Fernandez Alfredo",
    "wof:placetype":"venue"
},
  "geometry": {"coordinates":[-9.0328435898,43.1112251282],"type":"Point"}
}