{
  "type": "Feature",
  "properties": {
    "addr:full":"Avgd Gregorio Molina, 3 Xativa Valencia 46800",
    "addr:housenumber":"3",
    "addr:postcode":"46800",
    "addr:street":"Gregorio Molina",
    "iso:country":"ES",
    "sg:address":"Avgd Gregorio Molina, 3",
    "sg:city":"Xativa",
    "sg:orig_category":"Cl\u00cdnicas Dentales",
    "sg:phone":"+34 962 28 23 80",
    "sg:postcode":"46800",
    "sg:province":"Valencia",
    "wof:name":"Piera Navarro Maria Nieves",
    "wof:placetype":"venue"
},
  "geometry": {"coordinates":[-0.5235130191,38.9913902283],"type":"Point"}
}