{
  "type": "Feature",
  "properties": {
    "iso:country":"ES",
    "sg:address":"Calle de Bencomo, 28",
    "sg:city":"Cruce De Arinaga",
    "sg:orig_category":"Caf\u00c9s, Bares, Cervecer\u00cdas",
    "sg:phone":"+34 928 18 92 70",
    "sg:postcode":"35118",
    "sg:province":"Las Palmas",
    "wof:name":"Mendez Mendez Juan Ramon",
    "wof:placetype":"venue"
},
  "geometry": {"coordinates":[-15.4260845184,27.8778381348],"type":"Point"}
}