{
  "type": "Feature",
  "properties": {
    "iso:country":"ES",
    "sg:address":"Avda Doctor Galvez Ginachero, 21",
    "sg:city":"Malaga",
    "sg:orig_category":"Fabricaci\u00d3n De Su\u00c9ters Y Chalecos De Punto",
    "sg:phone":"+34 952 30 39 61",
    "sg:postcode":"29009",
    "sg:province":"M\u00e1laga",
    "wof:name":"Rotama Punto S.l.",
    "wof:placetype":"venue"
},
  "geometry": {"coordinates":[-4.4290509224,36.726776123],"type":"Point"}
}