{
  "type": "Feature",
  "properties": {
    "addr:full":"Calle de Ingeniero Ruiz De La Cuesta, 4 Poligono Industrial Salinas De San Jose C\u00e1diz 11500",
    "addr:housenumber":"4",
    "addr:postcode":"11500",
    "addr:street":"Calle De Ingeniero Ruiz De La Cuesta;Poligono Industrial Salinas De;Ca\u0301Diz",
    "iso:country":"ES",
    "sg:address":"Calle de Ingeniero Ruiz De La Cuesta, 4",
    "sg:city":"Poligono Industrial Salinas De San Jose",
    "sg:orig_category":"Inmobiliaria (agencias)",
    "sg:phone":"+34 956 87 63 52",
    "sg:postcode":"11500",
    "sg:province":"C\u00e1diz",
    "wof:name":"Fomento Y Desarrollo Bahia S.l.",
    "wof:placetype":"venue"
},
  "geometry": {"coordinates":[-6.2197542191,36.6056632996],"type":"Point"}
}