{
  "type": "Feature",
  "properties": {
    "addr:full":"Ctra Nacional 111, Km. 0318,4 Nalda La Rioja 26190",
    "addr:postcode":"26190",
    "addr:street":"Ctra Nacional 111 Km. 0318,4;Rioja",
    "iso:country":"ES",
    "sg:address":"Ctra Nacional 111, Km. 0318,4",
    "sg:city":"Nalda",
    "sg:orig_category":"Comercio De Piezas De Recambio Y De Accesorios De Veh\u00cdculos, Veh\u00cdculos Industriales",
    "sg:phone":"+34 941 44 74 73",
    "sg:postcode":"26190",
    "sg:province":"La Rioja",
    "wof:name":"Fico Mirrors S.a.",
    "wof:placetype":"venue"
},
  "geometry": {"coordinates":[-2.4869959354,42.3356437683],"type":"Point"}
}