{
  "type": "Feature",
  "properties": {
    "addr:full":"Urb Santa Clara, 122 Altea Vella Alicante 03599",
    "addr:housenumber":"122",
    "addr:postcode":"03599",
    "addr:street":"Urb Santa Clara",
    "iso:country":"ES",
    "sg:address":"Urb Santa Clara, 122",
    "sg:city":"Altea Vella",
    "sg:orig_category":"Charcuter\u00cdas (al Por Mayor)",
    "sg:phone":"+34 965 84 70 49",
    "sg:postcode":"03599",
    "sg:province":"Alicante",
    "wof:name":"Especialista De Embutidos;s.l.",
    "wof:placetype":"venue"
},
  "geometry": {"coordinates":[-0.0454870015,38.6320343018],"type":"Point"}
}