{
  "type": "Feature",
  "properties": {
    "iso:country":"ES",
    "sg:address":"Urdaneta Kalea, 10",
    "sg:city":"Ordizia",
    "sg:orig_category":"Zapatos (al Por Menor)",
    "sg:phone":"+34 943 08 75 23",
    "sg:postcode":"20240",
    "sg:province":"Guip\u00f9zcoa",
    "wof:name":"Carmen Insausti Leunda (calzados Arizmendi)",
    "wof:placetype":"venue"
},
  "geometry": {"coordinates":[-2.1816120148,43.0534324646],"type":"Point"}
}