{
  "type": "Feature",
  "properties": {
    "addr:full":"Afueras, S/n Badajoz Badajoz 06008",
    "addr:postcode":"06008",
    "addr:street":"Afueras S / N",
    "iso:country":"ES",
    "sg:address":"Afueras, S/n",
    "sg:city":"Badajoz",
    "sg:orig_category":"Agricultores, Agricultores",
    "sg:phone":"+34 924 14 02 15",
    "sg:postcode":"06008",
    "sg:province":"Badajoz",
    "wof:name":"Agropecuaria Valdesequera S.a.",
    "wof:placetype":"venue"
},
  "geometry": {"coordinates":[-6.6745042801,38.9741096497],"type":"Point"}
}