{
  "type": "Feature",
  "properties": {
    "iso:country":"ES",
    "sg:address":"Ctra Gral, S/n",
    "sg:city":"Puente Viesgo",
    "sg:orig_category":"Cajas De Ahorro",
    "sg:phone":"+34 942 59 81 24",
    "sg:postcode":"39670",
    "sg:province":"Cantabria",
    "sg:website":"www.cajacantabria.es",
    "wof:name":"Cableuropa",
    "wof:placetype":"venue"
},
  "geometry": {"coordinates":[-3.9674789906,43.2993736267],"type":"Point"}
}