{
  "type": "Feature",
  "properties": {
    "addr:full":"Ctra. Ansies, S/n Planes Hostoles Girona 17172",
    "addr:housenumber":"s / n",
    "addr:postcode":"17172",
    "addr:street":"Ctra. Ansies",
    "iso:country":"ES",
    "sg:address":"Ctra. Ansies, S/n",
    "sg:city":"Planes Hostoles",
    "sg:orig_category":"Zonas De Acampada, Aparcamiento Para Caravanas",
    "sg:phone":"+34 972 44 86 00",
    "sg:postcode":"17172",
    "sg:province":"Girona",
    "wof:name":"Camping Restaurant Piscina L'alguer",
    "wof:placetype":"venue"
},
  "geometry": {"coordinates":[2.5423851013,42.055229187],"type":"Point"}
}