{
  "type": "Feature",
  "properties": {
    "addr:full":"Pte Monjardin, S/n Cabra C\u00f3rdoba 14940",
    "addr:postcode":"14940",
    "addr:street":"Pte;S / N",
    "iso:country":"ES",
    "sg:address":"Pte Monjardin, S/n",
    "sg:city":"Cabra",
    "sg:orig_category":"M\u00c1rmoles, Granitos Y Piedras Naturales",
    "sg:phone":"+34 957 52 02 16",
    "sg:postcode":"14940",
    "sg:province":"C\u00f3rdoba",
    "wof:name":"Fernandez Ortiz Juan",
    "wof:placetype":"venue"
},
  "geometry": {"coordinates":[-4.4467329979,37.4725837708],"type":"Point"}
}