{
  "type": "Feature",
  "properties": {
    "addr:full":"Calle de Mayor, S/n Martin Del Rio Teruel 44750",
    "addr:housenumber":"s / n",
    "addr:postcode":"44750",
    "addr:street":"Calle De Mayor",
    "iso:country":"ES",
    "sg:address":"Calle de Mayor, S/n",
    "sg:city":"Martin Del Rio",
    "sg:orig_category":"Reposter\u00cdas",
    "sg:phone":"+34 978 75 03 51",
    "sg:postcode":"44750",
    "sg:province":"Teruel",
    "wof:name":"Biel Aznar Joaquin",
    "wof:placetype":"venue"
},
  "geometry": {"coordinates":[-0.8956590295,40.8442344666],"type":"Point"}
}