{
  "type": "Feature",
  "properties": {
    "iso:country":"ES",
    "sg:address":"Carrer de Santa Cinta (de La), 18",
    "sg:city":"Vinallop",
    "sg:orig_category":"Empresas De Portes Y Mensajer\u00cda",
    "sg:phone":"+34 977 47 43 02",
    "sg:postcode":"43517",
    "sg:province":"Tarragona",
    "wof:name":"Garcia Bel Paquita",
    "wof:placetype":"venue"
},
  "geometry": {"coordinates":[0.5135560036,40.774055481],"type":"Point"}
}