{
  "type": "Feature",
  "properties": {
    "addr:full":"Calle de Barbalanca, S/n Borja Zaragoza 50540",
    "addr:housenumber":"s",
    "addr:postcode":"50540",
    "addr:street":"Calle De Barbalanca;/ N Borja",
    "iso:country":"ES",
    "sg:address":"Calle de Barbalanca, S/n",
    "sg:city":"Borja",
    "sg:orig_category":"Ba\u00d1os Y Duchas P\u00dablicos",
    "sg:phone":"+34 976 86 79 06",
    "sg:postcode":"50540",
    "sg:province":"Zaragoza",
    "wof:name":"Ayuntamiento De Borja",
    "wof:placetype":"venue"
},
  "geometry": {"coordinates":[-1.5402326584,41.8895072937],"type":"Point"}
}