{
  "type": "Feature",
  "properties": {
    "addr:full":"Calle de Jose Rufino Olaso, 48 Valle Trapaga Vizcaya 48510",
    "addr:housenumber":"48",
    "addr:postcode":"48510",
    "addr:street":"Calle De Jose Rufino Olaso;Trapaga",
    "iso:country":"ES",
    "sg:address":"Calle de Jose Rufino Olaso, 48",
    "sg:city":"Valle Trapaga",
    "sg:orig_category":"Promotores Constructores",
    "sg:phone":"+34 944 03 09 00",
    "sg:postcode":"48510",
    "sg:province":"Vizcaya",
    "wof:name":"Inmuebles Hermanos Flores, S.l.",
    "wof:placetype":"venue"
},
  "geometry": {"coordinates":[-3.0366649628,43.3025131226],"type":"Point"}
}