{
  "type": "Feature",
  "properties": {
    "addr:full":"La Fuente, 13 Solana Barros Badajoz 06209",
    "addr:housenumber":"13",
    "addr:postcode":"06209",
    "addr:street":"La Fuente",
    "iso:country":"ES",
    "sg:address":"La Fuente, 13",
    "sg:city":"Solana Barros",
    "sg:orig_category":"Electrodom\u00c9sticos (fabricaci\u00d3n, Al Por Mayor)",
    "sg:phone":"+34 924 68 41 76",
    "sg:postcode":"06209",
    "sg:province":"Badajoz",
    "wof:name":"Garcedo Martin Manuel",
    "wof:placetype":"venue"
},
  "geometry": {"coordinates":[-6.5462560654,38.7277183533],"type":"Point"}
}