{
  "type": "Feature",
  "properties": {
    "addr:full":"Carrer de Volca Croscat, 19 Sant Cristofol Les Fonts Girona 17800",
    "addr:housenumber":"19",
    "addr:postcode":"17800",
    "addr:street":"Carrer De Volca Croscat;Cristofol",
    "iso:country":"ES",
    "sg:address":"Carrer de Volca Croscat, 19",
    "sg:city":"Sant Cristofol Les Fonts",
    "sg:orig_category":"Cajas De Ahorro",
    "sg:phone":"+34 972 27 64 44",
    "sg:postcode":"17800",
    "sg:province":"Girona",
    "sg:website":"www.caixagirona.es",
    "wof:name":"Caixa De Girona",
    "wof:placetype":"venue"
},
  "geometry": {"coordinates":[2.4893848896,42.1809463501],"type":"Point"}
}