{
  "type": "Feature",
  "properties": {
    "iso:country":"ES",
    "sg:address":"Carr Barranquet, 1",
    "sg:city":"Vila Joiosa",
    "sg:orig_category":"M\u00c9dicos: Ginecolog\u00cda Y Obstetricia",
    "sg:phone":"+34 966 85 00 00",
    "sg:postcode":"03570",
    "sg:province":"Alicante",
    "wof:name":"Lloret Blanco Agustin",
    "wof:placetype":"venue"
},
  "geometry": {"coordinates":[-0.2327190042,38.505821228],"type":"Point"}
}