{
  "type": "Feature",
  "properties": {
    "iso:country":"ES",
    "sg:address":"Avda Peris Y Valero, 121",
    "sg:city":"Valencia",
    "sg:orig_category":"Estudios, Instalaci\u00d3n De Climatizaci\u00d3n",
    "sg:phone":"+34 963 34 40 64",
    "sg:postcode":"46005",
    "sg:province":"Valencia",
    "wof:name":"Garcia Puchau S. A.",
    "wof:placetype":"venue"
},
  "geometry": {"coordinates":[-0.3688932061,39.4598503113],"type":"Point"}
}