{
  "type": "Feature",
  "properties": {
    "iso:country":"ES",
    "sg:address":"Calle de Ibaigane, 8",
    "sg:city":"Arizgoiti",
    "sg:orig_category":"Asociaciones, Organismos Culturales Y Socioeducativos",
    "sg:phone":"+34 944 49 00 18",
    "sg:postcode":"48970",
    "sg:province":"Vizcaya",
    "wof:name":"Sociedad Recreativa Ibaigane",
    "wof:placetype":"venue"
},
  "geometry": {"coordinates":[-2.884553194,43.235332489],"type":"Point"}
}