{
  "type": "Feature",
  "properties": {
    "iso:country":"ES",
    "sg:address":"Ctra Utrera-arahal, Km. 0077,3",
    "sg:city":"Utrera",
    "sg:orig_category":"Veh\u00cdculos De Ocasi\u00d3n",
    "sg:phone":"+34 954 86 14 80",
    "sg:postcode":"41710",
    "sg:province":"Sevilla",
    "sg:website":"www.autoslineroehijos.citroen.es",
    "wof:name":"Autos Linero E Hijos S.l.",
    "wof:placetype":"venue"
},
  "geometry": {"coordinates":[-5.6421113014,37.0714607239],"type":"Point"}
}