{
  "type": "Feature",
  "properties": {
    "addr:full":"Jazmin, 48 Mijas M\u00e1laga 29650",
    "addr:housenumber":"48",
    "addr:postcode":"29650",
    "addr:street":"Jazmin",
    "iso:country":"ES",
    "sg:address":"Jazmin, 48",
    "sg:city":"Mijas",
    "sg:orig_category":"Mec\u00c1nico Del Autom\u00d3vil",
    "sg:phone":"+34 952 66 35 40",
    "sg:postcode":"29650",
    "sg:province":"M\u00e1laga",
    "wof:name":"Martin Santana Juan Carlos",
    "wof:placetype":"venue"
},
  "geometry": {"coordinates":[-4.6469988823,36.5533905029],"type":"Point"}
}