{
  "type": "Feature",
  "properties": {
    "addr:full":"Ctra Comarcal, Km. 0021,3 S. Celoni Barcelona 08470",
    "addr:postcode":"08470",
    "addr:street":"Ctra Comarcal Km. 0021,3 S. Celoni Barcelona",
    "iso:country":"ES",
    "sg:address":"Ctra Comarcal, Km. 0021,3",
    "sg:city":"S. Celoni",
    "sg:orig_category":"Suministros Y Materiales Industriales",
    "sg:phone":"+34 938 48 40 80",
    "sg:postcode":"08470",
    "sg:province":"Barcelona",
    "sg:website":"www.trullas.com",
    "wof:name":"Suministros A. Trullas S.a.",
    "wof:placetype":"venue"
},
  "geometry": {"coordinates":[2.489289999,41.6902389526],"type":"Point"}
}