{
  "type": "Feature",
  "properties": {
    "addr:full":"Av. Catalunya (b. Xiol), 10 Lli\u00e7a Vall Barcelona 08185",
    "addr:housenumber":"10",
    "addr:postcode":"08185",
    "addr:street":"Av. Catalunya B. Xiol;Vall Barcelona",
    "iso:country":"ES",
    "sg:address":"Av. Catalunya (b. Xiol), 10",
    "sg:city":"Lli\u00e7a Vall",
    "sg:orig_category":"Inmobiliaria (agencias)",
    "sg:phone":"+34 938 43 77 71",
    "sg:postcode":"08185",
    "sg:province":"Barcelona",
    "wof:name":"Gestions Inmobiliarias L'esmai S.l.",
    "wof:placetype":"venue"
},
  "geometry": {"coordinates":[2.1699187756,41.3879165649],"type":"Point"}
}