{
  "type": "Feature",
  "properties": {
    "addr:full":"Carrer de General Josep Moragues, 8 Gava Barcelona 08850",
    "addr:housenumber":"8",
    "addr:postcode":"08850",
    "addr:street":"Carrer De General Josep Moragues",
    "iso:country":"ES",
    "sg:address":"Carrer de General Josep Moragues, 8",
    "sg:city":"Gava",
    "sg:orig_category":"Carnicer\u00cdas, Carnicer\u00cdas",
    "sg:phone":"+34 936 62 18 21",
    "sg:postcode":"08850",
    "sg:province":"Barcelona",
    "wof:name":"Leon Montalvo Gertrudis",
    "wof:placetype":"venue"
},
  "geometry": {"coordinates":[1.99474895,41.306186676],"type":"Point"}
}