{
  "type": "Feature",
  "properties": {
    "addr:full":"Calle de Virgen (la), 27 Villena Alicante 03400",
    "addr:housenumber":"27",
    "addr:postcode":"03400",
    "addr:street":"Calle De Virgen La",
    "iso:country":"ES",
    "sg:address":"Calle de Virgen (la), 27",
    "sg:city":"Villena",
    "sg:orig_category":"Venta, Montaje De Neum\u00c1ticos",
    "sg:phone":"+34 965 80 44 93",
    "sg:postcode":"03400",
    "sg:province":"Alicante",
    "wof:name":"Mico Sarrio Francisco",
    "wof:placetype":"venue"
},
  "geometry": {"coordinates":[-0.8697119951,38.6358375549],"type":"Point"}
}