{
  "type": "Feature",
  "properties": {
    "iso:country":"ES",
    "sg:address":"Portal De Gamarra Carrer de Carrer de Boulevard, 36",
    "sg:city":"Vitoria-gasteiz",
    "sg:orig_category":"Centros De Documentaci\u00d3n Y Archivo",
    "sg:phone":"+34 945 25 74 27",
    "sg:postcode":"01013",
    "sg:province":"\u00c1lava",
    "sg:website":"www.custarsl.com",
    "wof:name":"Custar, Sl",
    "wof:placetype":"venue"
},
  "geometry": {"coordinates":[-2.6840889454,42.8761367798],"type":"Point"}
}