{
  "type": "Feature",
  "properties": {
    "iso:country":"ES",
    "sg:address":"Calle de Dos De Maig, 17",
    "sg:city":"Alzira",
    "sg:orig_category":"Promotores Constructores",
    "sg:phone":"+34 962 41 02 73",
    "sg:postcode":"46600",
    "sg:province":"Valencia",
    "wof:name":"Eviga S. L.",
    "wof:placetype":"venue"
},
  "geometry": {"coordinates":[-0.4385432899,39.1484260559],"type":"Point"}
}