{
  "type": "Feature",
  "properties": {
    "addr:full":"Avda Odon, 34 Villaviciosa Odon Madrid 28670",
    "addr:housenumber":"34",
    "addr:postcode":"28670",
    "addr:street":"Avda Odon;Odon",
    "iso:country":"ES",
    "sg:address":"Avda Odon, 34",
    "sg:city":"Villaviciosa Odon",
    "sg:orig_category":"Art\u00cdculos Funerarios (al Por Menor)",
    "sg:phone":"+34 916 16 17 80",
    "sg:postcode":"28670",
    "sg:province":"Madrid",
    "wof:name":"Gabriel Garcia Lucio",
    "wof:placetype":"venue"
},
  "geometry": {"coordinates":[-3.9072980881,40.3547363281],"type":"Point"}
}