{
  "type": "Feature",
  "properties": {
    "iso:country":"ES",
    "sg:address":"Calle de Alvarez Quintero, 31",
    "sg:city":"Sevilla",
    "sg:orig_category":"Abogados",
    "sg:phone":"+34 954 56 25 36",
    "sg:postcode":"41004",
    "sg:province":"Sevilla",
    "wof:name":"Martin A\u00f1ino Javier",
    "wof:placetype":"venue"
},
  "geometry": {"coordinates":[-5.9932069778,37.3880958557],"type":"Point"}
}