{
  "type": "Feature",
  "properties": {
    "iso:country":"ES",
    "sg:address":"Calle de Jose Echegaray, 21",
    "sg:city":"Cala\u00f1as",
    "sg:orig_category":"Transportes Internacionales",
    "sg:phone":"+34 959 56 50 86",
    "sg:postcode":"21300",
    "sg:province":"Huelva",
    "wof:name":"Romero Gomez Luis",
    "wof:placetype":"venue"
},
  "geometry": {"coordinates":[-6.8777918816,37.6517715454],"type":"Point"}
}