{
  "type": "Feature",
  "properties": {
    "addr:full":"Calle de Ca\u00d1o, 7 Cordoba C\u00f3rdoba 14001",
    "addr:housenumber":"7",
    "addr:postcode":"14001",
    "addr:street":"Calle De Can\u0303O;Co\u0301Rdoba",
    "iso:country":"ES",
    "sg:address":"Calle de Ca\u00d1o, 7",
    "sg:city":"Cordoba",
    "sg:orig_category":"Arquitectos",
    "sg:phone":"+34 957 47 03 90",
    "sg:postcode":"14001",
    "sg:province":"C\u00f3rdoba",
    "wof:name":"Segura Montero Federico Manuel",
    "wof:placetype":"venue"
},
  "geometry": {"coordinates":[-4.7803039551,37.8881645203],"type":"Point"}
}