{
  "type": "Feature",
  "properties": {
    "iso:country":"ES",
    "sg:address":"Calle de Gran Canaria, 46",
    "sg:city":"Pto. Rosario",
    "sg:orig_category":"\u00d3ptica: Instrumentos (fabricaci\u00d3n)",
    "sg:phone":"+34 928 85 87 62",
    "sg:postcode":"35600",
    "sg:province":"Las Palmas",
    "wof:name":"Aguilo Caballero Nuria",
    "wof:placetype":"venue"
},
  "geometry": {"coordinates":[-13.8716440201,28.507938385],"type":"Point"}
}