{
  "type": "Feature",
  "properties": {
    "iso:country":"ES",
    "sg:address":"Pg Industria, 28",
    "sg:city":"Banyoles",
    "sg:orig_category":"Librer\u00cdas",
    "sg:phone":"+34 972 58 14 81",
    "sg:postcode":"17820",
    "sg:province":"Girona",
    "wof:name":"Alsius Su\u00f1er Josep",
    "wof:placetype":"venue"
},
  "geometry": {"coordinates":[2.7629351616,42.1159858704],"type":"Point"}
}