{
  "type": "Feature",
  "properties": {
    "iso:country":"ES",
    "sg:address":"Carrer de Padilla, 240",
    "sg:city":"Barcelona",
    "sg:orig_category":"Inmobiliaria (agencias)",
    "sg:phone":"+34 934 36 72 85",
    "sg:postcode":"08013",
    "sg:province":"Barcelona",
    "wof:name":"Inmobiliaria Bipsall S. A.",
    "wof:placetype":"venue"
},
  "geometry": {"coordinates":[2.1775000095,41.4056510925],"type":"Point"}
}