{
  "type": "Feature",
  "properties": {
    "addr:full":"Urb La Florida, 66 Urbanizacion La Florida Albacete 02006",
    "addr:housenumber":"66",
    "addr:postcode":"02006",
    "addr:street":"La Florida;La",
    "iso:country":"ES",
    "sg:address":"Urb La Florida, 66",
    "sg:city":"Urbanizacion La Florida",
    "sg:orig_category":"Promotores Constructores",
    "sg:phone":"+34 967 58 00 68",
    "sg:postcode":"02006",
    "sg:province":"Albacete",
    "wof:name":"Construrosa S.l.",
    "wof:placetype":"venue"
},
  "geometry": {"coordinates":[-2.044303894,39.0605888367],"type":"Point"}
}