{
  "type": "Feature",
  "properties": {
    "addr:full":"Plaz Espolon, 3 Le\u00f3n Le\u00f3n 24007",
    "addr:housenumber":"3",
    "addr:postcode":"24007",
    "addr:street":"Plaz Espolon;Leo\u0301N",
    "iso:country":"ES",
    "sg:address":"Plaz Espolon, 3",
    "sg:city":"Le\u00f3n",
    "sg:orig_category":"Cajas De Ahorro",
    "sg:phone":"+34 987 87 64 40",
    "sg:postcode":"24007",
    "sg:province":"Le\u00f3n",
    "wof:name":"Caja Laboral Popular",
    "wof:placetype":"venue"
},
  "geometry": {"coordinates":[-5.5701141357,42.6027526855],"type":"Point"}
}