{
  "type": "Feature",
  "properties": {
    "iso:country":"ES",
    "sg:address":"Avda Paris, 5",
    "sg:city":"Caceres",
    "sg:orig_category":"Alimentaci\u00d3n General (al Por Menor)",
    "sg:phone":"+34 927 23 97 84",
    "sg:postcode":"10005",
    "sg:province":"C\u00e1ceres",
    "wof:name":"Luna Burdalo Maria Joaquina",
    "wof:placetype":"venue"
},
  "geometry": {"coordinates":[-6.3864693642,39.4682044983],"type":"Point"}
}