{
  "type": "Feature",
  "properties": {
    "iso:country":"ES",
    "sg:address":"Barr El Campillo, S/n",
    "sg:city":"Campillo",
    "sg:orig_category":"Acero: Productos Sider\u00dargicos Y Transformados (fabricaci\u00d3n, Negocio)",
    "sg:phone":"+34 946 36 01 28",
    "sg:postcode":"48509",
    "sg:province":"Vizcaya",
    "sg:website":"www.cuprum.es",
    "wof:name":"Cuprum S. A.",
    "wof:placetype":"venue"
},
  "geometry": {"coordinates":[-2.9316000938,43.2383995056],"type":"Point"}
}