{
  "type": "Feature",
  "properties": {
    "iso:country":"ES",
    "sg:address":"Carr Comtessa Elvira, 1",
    "sg:city":"Lleida",
    "sg:orig_category":"Guarder\u00cdas",
    "sg:phone":"+34 973 23 39 72",
    "sg:postcode":"25008",
    "sg:province":"Lleida",
    "wof:name":"Llar D'infants Sociedad Cooperativa Limi",
    "wof:placetype":"venue"
},
  "geometry": {"coordinates":[0.6202679873,41.6207695007],"type":"Point"}
}