{
  "type": "Feature",
  "properties": {
    "addr:full":"Calle de Poeta Mas Y Ros, 118 Valencia Valencia 46022",
    "addr:housenumber":"118",
    "addr:postcode":"46022",
    "addr:street":"Calle De Poeta Mas Y Ros",
    "iso:country":"ES",
    "sg:address":"Calle de Poeta Mas Y Ros, 118",
    "sg:city":"Valencia",
    "sg:orig_category":"Peluquer\u00cdas, Peluquer\u00cda Mixta",
    "sg:phone":"+34 963 55 33 75",
    "sg:postcode":"46022",
    "sg:province":"Valencia",
    "wof:name":"Amano C.b.",
    "wof:placetype":"venue"
},
  "geometry": {"coordinates":[-0.3403469026,39.468120575],"type":"Point"}
}