{
  "type": "Feature",
  "properties": {
    "iso:country":"ES",
    "sg:address":"Calle de Cielo, 2",
    "sg:city":"Lomo De La Herradura",
    "sg:orig_category":"Farmacias",
    "sg:phone":"+34 928 69 39 77",
    "sg:postcode":"35200",
    "sg:province":"Las Palmas",
    "wof:name":"Gonzalez Valido Luis Sebastian",
    "wof:placetype":"venue"
},
  "geometry": {"coordinates":[-15.4249362946,27.9965209961],"type":"Point"}
}