{
  "type": "Feature",
  "properties": {
    "iso:country":"ES",
    "sg:address":"Calle de Giner De Los Rios, 4",
    "sg:city":"Ronda",
    "sg:orig_category":"Alimentaci\u00d3n General (al Por Menor)",
    "sg:phone":"+34 952 87 58 97",
    "sg:postcode":"29400",
    "sg:province":"M\u00e1laga",
    "wof:name":"Monreal Garcia Antonia",
    "wof:placetype":"venue"
},
  "geometry": {"coordinates":[-5.1722350121,36.7524757385],"type":"Point"}
}