{
  "type": "Feature",
  "properties": {
    "iso:country":"ES",
    "sg:address":"Pg Vint-i-dos De Juliol, 708",
    "sg:city":"Terrassa",
    "sg:orig_category":"Centros Empresariales",
    "sg:phone":"+34 937 31 84 38",
    "sg:postcode":"08222",
    "sg:province":"Barcelona",
    "wof:name":"Sepisa S.l.",
    "wof:placetype":"venue"
},
  "geometry": {"coordinates":[2.0255489349,41.5685424805],"type":"Point"}
}