{
  "type": "Feature",
  "properties": {
    "addr:full":"Carrer de Corsega, 495 Barcelona Barcelona 08025",
    "addr:housenumber":"495",
    "addr:postcode":"08025",
    "addr:street":"Carrer De Corsega",
    "iso:country":"ES",
    "sg:address":"Carrer de Corsega, 495",
    "sg:city":"Barcelona",
    "sg:orig_category":"Barnizadores",
    "sg:phone":"+34 934 57 21 71",
    "sg:postcode":"08025",
    "sg:province":"Barcelona",
    "wof:name":"Merlos Vidal Cristina",
    "wof:placetype":"venue"
},
  "geometry": {"coordinates":[2.1688389778,41.4038085938],"type":"Point"}
}