{
  "type": "Feature",
  "properties": {
    "addr:full":"Calle de San Vicente, 14 Chert Castell\u00f3n 12360",
    "addr:housenumber":"14",
    "addr:postcode":"12360",
    "addr:street":"Calle De San Vicente;Castello\u0301N",
    "iso:country":"ES",
    "sg:address":"Calle de San Vicente, 14",
    "sg:city":"Chert",
    "sg:classifiers":[
        {
            "category":"Professional",
            "subcategory":"Management & Consulting",
            "type":"Services"
        }
    ],
    "sg:phone":"+34 964 49 00 62",
    "sg:postcode":"12360",
    "sg:province":"Castell\u00f3n",
    "sg:tags":[
        "asesor\u00cda",
        "en",
        "marketing"
    ],
    "wof:name":"Esteller Rallo Luis",
    "wof:placetype":"venue"
},
  "geometry": {"coordinates":[0.1581050009,40.518661499],"type":"Point"}
}