{
  "type": "Feature",
  "properties": {
    "addr:full":"Calle de Horno Nuevo, 4 Epila Zaragoza 50290",
    "addr:housenumber":"4",
    "addr:postcode":"50290",
    "addr:street":"Calle De Horno Nuevo",
    "iso:country":"ES",
    "sg:address":"Calle de Horno Nuevo, 4",
    "sg:city":"Epila",
    "sg:orig_category":"Loter\u00cda Y T\u00d3mbola",
    "sg:phone":"+34 976 60 38 91",
    "sg:postcode":"50290",
    "sg:province":"Zaragoza",
    "wof:name":"Berna Sanchez Julio Miguel",
    "wof:placetype":"venue"
},
  "geometry": {"coordinates":[-1.2807780504,41.6004180908],"type":"Point"}
}