{
  "type": "Feature",
  "properties": {
    "iso:country":"ES",
    "sg:address":"Calle de Mayor, 41",
    "sg:city":"Cangas Narcea",
    "sg:orig_category":"Zapater\u00cdas",
    "sg:phone":"+34 985 81 03 11",
    "sg:postcode":"33800",
    "sg:province":"Asturias",
    "wof:name":"Perez Cuesta Alejandro",
    "wof:placetype":"venue"
},
  "geometry": {"coordinates":[-6.5512938499,43.1789398193],"type":"Point"}
}