{
  "type": "Feature",
  "properties": {
    "addr:full":"Calle de Peregrina (la), 1 Pozuelo De Alarcon Madrid 28223",
    "addr:housenumber":"1",
    "addr:postcode":"28223",
    "addr:street":"Calle De Peregrina La",
    "iso:country":"ES",
    "sg:address":"Calle de Peregrina (la), 1",
    "sg:city":"Pozuelo De Alarcon",
    "sg:classifiers":[
        {
            "category":"Banks & Credit Unions",
            "subcategory":"Bureau De Change",
            "type":"Services"
        }
    ],
    "sg:phone":"+34 913 52 48 37",
    "sg:postcode":"28223",
    "sg:province":"Madrid",
    "sg:tags":[
        "organismos",
        "control"
    ],
    "wof:name":"Estudios Geotecnicos Y Control De Obras S A",
    "wof:placetype":"venue"
},
  "geometry": {"coordinates":[-3.808161974,40.4409790039],"type":"Point"}
}