{
  "type": "Feature",
  "properties": {
    "iso:country":"ES",
    "sg:address":"Calle de Santiago, 4",
    "sg:city":"Orihuela",
    "sg:orig_category":"Molduras, Junquillos, Listones Y Molduras Perforadas",
    "sg:phone":"+34 965 30 49 78",
    "sg:postcode":"03300",
    "sg:province":"Alicante",
    "wof:name":"Cuenca Sanchez Jose Manuel",
    "wof:placetype":"venue"
},
  "geometry": {"coordinates":[-0.9504110217,38.0875854492],"type":"Point"}
}