{
  "type": "Feature",
  "properties": {
    "iso:country":"ES",
    "sg:address":"Calle de Posito, 2",
    "sg:city":"Campana",
    "sg:orig_category":"Bibliotecas, Mediatecas",
    "sg:phone":"+34 954 19 81 45",
    "sg:postcode":"41429",
    "sg:province":"Sevilla",
    "wof:name":"Ayuntamiento De La Campana",
    "wof:placetype":"venue"
},
  "geometry": {"coordinates":[-5.4260749817,37.5702781677],"type":"Point"}
}