{
  "type": "Feature",
  "properties": {
    "iso:country":"ES",
    "sg:address":"Calle de Antonio Machado, 28",
    "sg:city":"Cuenca",
    "sg:orig_category":"Ortopedia General",
    "sg:phone":"+34 969 23 43 66",
    "sg:postcode":"16003",
    "sg:province":"Cuenca",
    "wof:name":"Manzano Ruiz Silvestre",
    "wof:placetype":"venue"
},
  "geometry": {"coordinates":[-2.1364769936,40.0579948425],"type":"Point"}
}