{
  "type": "Feature",
  "properties": {
    "addr:full":"Calle de Pablo Iglesias, 2 Villargordo Ja\u00e9n 23630",
    "addr:housenumber":"2",
    "addr:postcode":"23630",
    "addr:street":"Calle De Pablo Iglesias;Jae\u0301N",
    "iso:country":"ES",
    "sg:address":"Calle de Pablo Iglesias, 2",
    "sg:city":"Villargordo",
    "sg:orig_category":"Caf\u00c9s, Bares, Cervecer\u00cdas",
    "sg:phone":"+34 953 37 82 94",
    "sg:postcode":"23630",
    "sg:province":"Ja\u00e9n",
    "wof:name":"Martos Moreno Alonso",
    "wof:placetype":"venue"
},
  "geometry": {"coordinates":[-3.7307140827,37.9388046265],"type":"Point"}
}