{
  "type": "Feature",
  "properties": {
    "iso:country":"ES",
    "sg:address":"Calle de Granada, 100",
    "sg:city":"Almeria",
    "sg:orig_category":"Mec\u00c1nico Del Autom\u00d3vil",
    "sg:phone":"+34 950 14 01 93",
    "sg:postcode":"04008",
    "sg:province":"Almer\u00eda",
    "wof:name":"Palomeque Rojano Diego",
    "wof:placetype":"venue"
},
  "geometry": {"coordinates":[-2.4601402283,36.8451042175],"type":"Point"}
}