{
  "type": "Feature",
  "properties": {
    "iso:country":"ES",
    "sg:address":"Rua Dous De Maio, 49",
    "sg:city":"Xinzo De Limia",
    "sg:orig_category":"Supermercados Y Hipermercados",
    "sg:phone":"+34 988 46 04 28",
    "sg:postcode":"32630",
    "sg:province":"Ourense",
    "wof:name":"Supercuatro S.l.",
    "wof:placetype":"venue"
},
  "geometry": {"coordinates":[-7.7258520126,42.0619735718],"type":"Point"}
}