{
  "type": "Feature",
  "properties": {
    "addr:full":"El Villar, 58 Villar C\u00f3rdoba 14115",
    "addr:housenumber":"58;co\u0301rdoba",
    "addr:postcode":"14115",
    "addr:street":"El Villar",
    "iso:country":"ES",
    "sg:address":"El Villar, 58",
    "sg:city":"Villar",
    "sg:orig_category":"Transportes Por V\u00cdas Navegables",
    "sg:phone":"+34 957 71 56 28",
    "sg:postcode":"14115",
    "sg:province":"C\u00f3rdoba",
    "wof:name":"Castillo Caro Salvador",
    "wof:placetype":"venue"
},
  "geometry": {"coordinates":[-5.0596451759,37.6351737976],"type":"Point"}
}