{
  "type": "Feature",
  "properties": {
    "iso:country":"ES",
    "sg:address":"Calle de Garcia Castellanos, 8",
    "sg:city":"Almazan",
    "sg:orig_category":"Transportes Por Carretera: Lotes Completos, Mercanc\u00cdas Diversas",
    "sg:phone":"+34 975 30 00 29",
    "sg:postcode":"42200",
    "sg:province":"Soria",
    "wof:name":"Carretero Jimenez Eduardo",
    "wof:placetype":"venue"
},
  "geometry": {"coordinates":[-2.5326740742,41.4875831604],"type":"Point"}
}