{
  "type": "Feature",
  "properties": {
    "addr:full":"Carr Mariano Amigo, 21 Pu\u00e7ol Valencia 46530",
    "addr:housenumber":"21",
    "addr:postcode":"46530",
    "addr:street":"Carr Mariano Amigo",
    "iso:country":"ES",
    "sg:address":"Carr Mariano Amigo, 21",
    "sg:city":"Pu\u00e7ol",
    "sg:orig_category":"Formaci\u00d3n Continuada (variada)",
    "sg:phone":"+34 961 46 47 70",
    "sg:postcode":"46530",
    "sg:province":"Valencia",
    "wof:name":"Claramunt Martin Juan Enrique",
    "wof:placetype":"venue"
},
  "geometry": {"coordinates":[-0.3005959988,39.6173210144],"type":"Point"}
}