{
  "type": "Feature",
  "properties": {
    "iso:country":"ES",
    "sg:address":"Ctra Nacional Iii, Km. 0329,0",
    "sg:city":"Quart Poblet",
    "sg:orig_category":"Agentes, Concesionarios Y Sucursales De Camiones Y Veh\u00cdculos Industriales",
    "sg:phone":"+34 961 92 09 87",
    "sg:postcode":"46930",
    "sg:province":"Valencia",
    "wof:name":"Paco Perez S. A.",
    "wof:placetype":"venue"
},
  "geometry": {"coordinates":[-0.4419890046,39.482711792],"type":"Point"}
}