{
  "type": "Feature",
  "properties": {
    "iso:country":"ES",
    "sg:address":"Pl Aleixandre, 6",
    "sg:city":"Puerto Sagunto",
    "sg:orig_category":"Cajas De Ahorro",
    "sg:phone":"+34 962 67 54 86",
    "sg:postcode":"46520",
    "sg:province":"Valencia",
    "wof:name":"Caja De Ahorros De Valencia Castellon Y Alicante",
    "wof:placetype":"venue"
},
  "geometry": {"coordinates":[-0.2025949955,39.7040786743],"type":"Point"}
}