{
  "type": "Feature",
  "properties": {
    "addr:full":"Carrer de Joan Maragall, 42 S. Celoni Barcelona 08470",
    "addr:housenumber":"42",
    "addr:postcode":"08470",
    "addr:street":"Carrer De Joan Maragall;S. Celoni Barcelona",
    "iso:country":"ES",
    "sg:address":"Carrer de Joan Maragall, 42",
    "sg:city":"S. Celoni",
    "sg:orig_category":"Comercio, Reparaci\u00d3n De Motocicletas, Bicicletas Y Piezas Sueltas",
    "sg:phone":"+34 938 67 30 94",
    "sg:postcode":"08470",
    "sg:province":"Barcelona",
    "wof:name":"Sanchez Nu\u00f1ez Alejandro",
    "wof:placetype":"venue"
},
  "geometry": {"coordinates":[2.500797987,41.6941642761],"type":"Point"}
}