{
  "type": "Feature",
  "properties": {
    "addr:full":"Po Enamorados, 31 Iru\u00f1a Navarra 31014",
    "addr:housenumber":"31",
    "addr:postcode":"31014",
    "addr:street":"Enamorados",
    "iso:country":"ES",
    "sg:address":"Po Enamorados, 31",
    "sg:city":"Iru\u00f1a",
    "sg:orig_category":"Empresas De Carpinter\u00cda De Madera",
    "sg:phone":"+34 948 12 48 89",
    "sg:postcode":"31014",
    "sg:province":"Navarra",
    "wof:name":"Azcarate Aranguren Francisco Javier",
    "wof:placetype":"venue"
},
  "geometry": {"coordinates":[-1.6493531466,42.8251419067],"type":"Point"}
}