{
  "type": "Feature",
  "properties": {
    "iso:country":"ES",
    "sg:address":"Calle de Santa Engracia, 171",
    "sg:city":"Madrid",
    "sg:classifiers":[
        {
            "category":"Autos & Motor Vehicles",
            "subcategory":"Automobile Sales",
            "type":"Retail Goods"
        }
    ],
    "sg:phone":"+34 915 34 85 75",
    "sg:postcode":"28003",
    "sg:province":"Madrid",
    "wof:name":"Autoescuela Zires C.b.",
    "wof:placetype":"venue"
},
  "geometry": {"coordinates":[-3.7033188343,40.4453697205],"type":"Point"}
}