{
  "type": "Feature",
  "properties": {
    "iso:country":"ES",
    "sg:address":"Urb. Agronovo(alqueidon), 30",
    "sg:city":"Brion",
    "sg:orig_category":"Barbacoas Y Accesorios",
    "sg:phone":"+34 981 88 77 39",
    "sg:postcode":"15280",
    "sg:province":"La Coru\u00f1a",
    "wof:name":"Meson Asador Casa Abelleira S.l.",
    "wof:placetype":"venue"
},
  "geometry": {"coordinates":[-8.6716041565,42.8535842896],"type":"Point"}
}