{
  "type": "Feature",
  "properties": {
    "addr:full":"Atxubiaga Kalea, 5 Azpeitia Guip\u00f9zcoa 20730",
    "addr:housenumber":"5",
    "addr:postcode":"20730",
    "addr:street":"Atxubiaga Kalea;Guipu\u0300Zcoa",
    "iso:country":"ES",
    "sg:address":"Atxubiaga Kalea, 5",
    "sg:city":"Azpeitia",
    "sg:orig_category":"Negocio De Madera",
    "sg:phone":"+34 943 15 18 84",
    "sg:postcode":"20730",
    "sg:province":"Guip\u00f9zcoa",
    "wof:name":"Egurgor C.b.",
    "wof:placetype":"venue"
},
  "geometry": {"coordinates":[-2.2581501007,43.1763114929],"type":"Point"}
}