{
  "type": "Feature",
  "properties": {
    "addr:full":"Carrer de Ramon Freixas, 44 Vilafranca Penedes Barcelona 08720",
    "addr:housenumber":"44",
    "addr:postcode":"08720",
    "addr:street":"Carrer De Ramon Freixas",
    "iso:country":"ES",
    "sg:address":"Carrer de Ramon Freixas, 44",
    "sg:city":"Vilafranca Penedes",
    "sg:orig_category":"Mec\u00c1nico Del Autom\u00d3vil",
    "sg:phone":"+34 938 90 09 98",
    "sg:postcode":"08720",
    "sg:province":"Barcelona",
    "wof:name":"Julia Bosch Pere",
    "wof:placetype":"venue"
},
  "geometry": {"coordinates":[1.6976579428,41.3406143188],"type":"Point"}
}