{
  "type": "Feature",
  "properties": {
    "iso:country":"ES",
    "sg:address":"A Carretera, 14",
    "sg:city":"Noche",
    "sg:orig_category":"Reciclaje, Desguace De Veh\u00cdculos",
    "sg:phone":"+34 982 51 18 56",
    "sg:postcode":"27812",
    "sg:province":"Lugo",
    "wof:name":"Vazquez Villares Antonio",
    "wof:placetype":"venue"
},
  "geometry": {"coordinates":[-7.6286292076,43.2555503845],"type":"Point"}
}