{
  "type": "Feature",
  "properties": {
    "addr:full":"Calle de Fernan Caballero, 4 Barrio De Peral Murcia 30300",
    "addr:housenumber":"4",
    "addr:postcode":"30300",
    "addr:street":"Calle De Fernan Caballero",
    "iso:country":"ES",
    "sg:address":"Calle de Fernan Caballero, 4",
    "sg:city":"Barrio De Peral",
    "sg:orig_category":"Estudios, Instalaci\u00d3n De Climatizaci\u00d3n",
    "sg:phone":"+34 968 31 62 72",
    "sg:postcode":"30300",
    "sg:province":"Murcia",
    "wof:name":"Airecarthago",
    "wof:placetype":"venue"
},
  "geometry": {"coordinates":[-0.992444098,37.6282272339],"type":"Point"}
}