{
  "type": "Feature",
  "properties": {
    "iso:country":"ES",
    "sg:address":"Calle de Parroco Camino, 19",
    "sg:city":"Luarca",
    "sg:orig_category":"Gafas (fabricaci\u00d3n)",
    "sg:phone":"+34 985 47 02 50",
    "sg:postcode":"33700",
    "sg:province":"Asturias",
    "wof:name":"Fernandez Fernandez Ricardo",
    "wof:placetype":"venue"
},
  "geometry": {"coordinates":[-6.5345277786,43.5448722839],"type":"Point"}
}