{
  "type": "Feature",
  "properties": {
    "addr:full":"Carr Calderon De La Barca, 104 Badalona Barcelona 08914",
    "addr:housenumber":"104",
    "addr:postcode":"08914",
    "addr:street":"Carr Calderon De La Barca",
    "iso:country":"ES",
    "sg:address":"Carr Calderon De La Barca, 104",
    "sg:city":"Badalona",
    "sg:orig_category":"Peluqueros: De Se\u00d1oras",
    "sg:phone":"+34 933 99 08 71",
    "sg:postcode":"08914",
    "sg:province":"Barcelona",
    "wof:name":"Castro Leon Jose",
    "wof:placetype":"venue"
},
  "geometry": {"coordinates":[2.2250199318,41.4436416626],"type":"Point"}
}