{
  "type": "Feature",
  "properties": {
    "addr:full":"Calle de Casas De Cotallo, 2 Caceres C\u00e1ceres 10004",
    "addr:housenumber":"2",
    "addr:postcode":"10004",
    "addr:street":"Calle De Casas De Cotallo;Ca\u0301Ceres",
    "iso:country":"ES",
    "sg:address":"Calle de Casas De Cotallo, 2",
    "sg:city":"Caceres",
    "sg:orig_category":"Florister\u00cdas",
    "sg:phone":"+34 927 21 59 22",
    "sg:postcode":"10004",
    "sg:province":"C\u00e1ceres",
    "wof:name":"Flores El Calambuco S.l.",
    "wof:placetype":"venue"
},
  "geometry": {"coordinates":[-6.3756313324,39.4733047485],"type":"Point"}
}