{
  "type": "Feature",
  "properties": {
    "iso:country":"ES",
    "sg:address":"Calle de San Erasmo, 42",
    "sg:city":"Madrid",
    "sg:orig_category":"Venta, Alquiler De Toldos",
    "sg:phone":"+34 914 03 71 84",
    "sg:postcode":"28021",
    "sg:province":"Madrid",
    "wof:name":"Abc Felix Calleja S.l.",
    "wof:placetype":"venue"
},
  "geometry": {"coordinates":[-3.706471,40.333408],"type":"Point"}
}