{
  "type": "Feature",
  "properties": {
    "addr:full":"Avda Miguel Cosano, S/n Aguilar De La Frontera C\u00f3rdoba 14920",
    "addr:housenumber":"s",
    "addr:postcode":"14920",
    "addr:street":"Avda Miguel Cosano;/ N",
    "iso:country":"ES",
    "sg:address":"Avda Miguel Cosano, S/n",
    "sg:city":"Aguilar De La Frontera",
    "sg:orig_category":"Lavado, Limpieza De Veh\u00cdculos",
    "sg:phone":"+34 957 66 05 91",
    "sg:postcode":"14920",
    "sg:province":"C\u00f3rdoba",
    "wof:name":"Zafra Y Trapero S.l",
    "wof:placetype":"venue"
},
  "geometry": {"coordinates":[-4.6520590782,37.511882782],"type":"Point"}
}