{
  "type": "Feature",
  "properties": {
    "addr:full":"Sector Club Nautico, S/n Platja Aro Girona 17250",
    "addr:housenumber":"s / n",
    "addr:postcode":"17250",
    "iso:country":"ES",
    "sg:address":"Sector Club Nautico, S/n",
    "sg:city":"Platja Aro",
    "sg:orig_category":"Deportes N\u00c1uticos, Acu\u00c1ticos Y Subacu\u00c1ticos: Art\u00cdculos Y Equipo (al Por Menor)",
    "sg:phone":"+34 972 82 63 88",
    "sg:postcode":"17250",
    "sg:province":"Girona",
    "wof:name":"Varadero Port D'aro S.l.",
    "wof:placetype":"venue"
},
  "geometry": {"coordinates":[3.0639550686,41.8142547607],"type":"Point"}
}