{
  "type": "Feature",
  "properties": {
    "addr:full":"Veigui\u00f1a, S/n Veigui\u00d1a Lugo 27320",
    "addr:postcode":"27320",
    "addr:street":"Veiguin\u0303A S / N",
    "iso:country":"ES",
    "sg:address":"Veigui\u00f1a, S/n",
    "sg:city":"Veigui\u00d1a",
    "sg:orig_category":"Pizzer\u00cdas",
    "sg:phone":"+34 982 43 88 91",
    "sg:postcode":"27320",
    "sg:province":"Lugo",
    "wof:name":"Louval S.l.",
    "wof:placetype":"venue"
},
  "geometry": {"coordinates":[-7.5558514595,43.0120849609],"type":"Point"}
}