{
  "type": "Feature",
  "properties": {
    "addr:full":"Carrer de Arenys, 89 Barcelona Barcelona 08035",
    "addr:housenumber":"89",
    "addr:postcode":"08035",
    "addr:street":"Carrer De Arenys",
    "iso:country":"ES",
    "sg:address":"Carrer de Arenys, 89",
    "sg:city":"Barcelona",
    "sg:orig_category":"M\u00c9dicos: Estomatolog\u00cda",
    "sg:phone":"+34 933 58 41 03",
    "sg:postcode":"08035",
    "sg:province":"Barcelona",
    "wof:name":"Obradors Giro Domingo",
    "wof:placetype":"venue"
},
  "geometry": {"coordinates":[2.1456859112,41.422832489],"type":"Point"}
}