{
  "type": "Feature",
  "properties": {
    "iso:country":"ES",
    "sg:address":"Ctra Bajada De Las Guayarminas, Km. 0027,0",
    "sg:city":"Galdar",
    "sg:orig_category":"Asociaciones Y Clubs Deportivos",
    "sg:phone":"+34 928 55 18 09",
    "sg:postcode":"35460",
    "sg:province":"Las Palmas",
    "wof:name":"Asociacion De Pesca Deportiva Del Norte Roque Negro",
    "wof:placetype":"venue"
},
  "geometry": {"coordinates":[-15.6517400742,28.1454563141],"type":"Point"}
}