{
  "type": "Feature",
  "properties": {
    "addr:full":"Calle de Doctor Julian Martin Renedo, 17 Tudela Duero Valladolid 47320",
    "addr:housenumber":"17;duero",
    "addr:postcode":"47320",
    "addr:street":"Calle De Doctor Julian Martin Renedo",
    "iso:country":"ES",
    "sg:address":"Calle de Doctor Julian Martin Renedo, 17",
    "sg:city":"Tudela Duero",
    "sg:orig_category":"Loter\u00cda Y T\u00d3mbola",
    "sg:phone":"+34 983 52 21 49",
    "sg:postcode":"47320",
    "sg:province":"Valladolid",
    "wof:name":"De Blas Gonzalez Maria Del Carmen",
    "wof:placetype":"venue"
},
  "geometry": {"coordinates":[-4.581433773,41.5855865479],"type":"Point"}
}