{
  "type": "Feature",
  "properties": {
    "addr:full":"Calle de Portales, 87 Logro\u00f1o La Rioja 26001",
    "addr:housenumber":"87",
    "addr:postcode":"26001",
    "addr:street":"Calle De Portales;Rioja",
    "iso:country":"ES",
    "sg:address":"Calle de Portales, 87",
    "sg:city":"Logro\u00f1o",
    "sg:orig_category":"Electrodom\u00c9sticos (al Por Menor)",
    "sg:phone":"+34 941 20 24 08",
    "sg:postcode":"26001",
    "sg:province":"La Rioja",
    "wof:name":"Saenz Ramirez Julian",
    "wof:placetype":"venue"
},
  "geometry": {"coordinates":[-2.4505839348,42.4660415649],"type":"Point"}
}