{
  "type": "Feature",
  "properties": {
    "iso:country":"ES",
    "sg:address":"Calle de Maestro Gozalbo, 5",
    "sg:city":"Valencia",
    "sg:orig_category":"Supermercados Y Hipermercados",
    "sg:phone":"+34 963 95 50 87",
    "sg:postcode":"46005",
    "sg:province":"Valencia",
    "sg:website":"www.mercadona.es",
    "wof:name":"Mercadona S.a.",
    "wof:placetype":"venue"
},
  "geometry": {"coordinates":[-0.3695909977,39.465927124],"type":"Point"}
}