{
  "type": "Feature",
  "properties": {
    "iso:country":"ES",
    "sg:address":"Calle de Baja De San Pedro, 19",
    "sg:city":"Binefar",
    "sg:orig_category":"Talleres De Corte Y Confecci\u00d3n",
    "sg:phone":"+34 974 42 96 65",
    "sg:postcode":"22500",
    "sg:province":"Huesca",
    "wof:name":"Space Internacional S.l",
    "wof:placetype":"venue"
},
  "geometry": {"coordinates":[0.2923958898,41.8510513306],"type":"Point"}
}