{
  "type": "Feature",
  "properties": {
    "iso:country":"ES",
    "sg:address":"Calle de Coronel Ildefonso Valls De La Torre, 13",
    "sg:city":"Arrecife",
    "sg:orig_category":"Farmacias",
    "sg:phone":"+34 928 80 36 86",
    "sg:postcode":"35500",
    "sg:province":"Las Palmas",
    "wof:name":"Retana Schwartz Rosa Del Carmen",
    "wof:placetype":"venue"
},
  "geometry": {"coordinates":[-13.5555610657,28.9584541321],"type":"Point"}
}