{
  "type": "Feature",
  "properties": {
    "addr:full":"Calle de Real, 94 Illescas Toledo 45200",
    "addr:housenumber":"94",
    "addr:postcode":"45200",
    "addr:street":"Calle De Real",
    "iso:country":"ES",
    "sg:address":"Calle de Real, 94",
    "sg:city":"Illescas",
    "sg:orig_category":"Papeler\u00cdas: Art\u00cdculos (al Por Mayor)",
    "sg:phone":"+34 925 54 13 40",
    "sg:postcode":"45200",
    "sg:province":"Toledo",
    "wof:name":"Artes Graficas Morales S.l.",
    "wof:placetype":"venue"
},
  "geometry": {"coordinates":[-3.8481004238,40.1260032654],"type":"Point"}
}