{
  "type": "Feature",
  "properties": {
    "iso:country":"ES",
    "sg:address":"Carr Empuries, 17",
    "sg:city":"Girona",
    "sg:orig_category":"Equipo De Refrigeraci\u00d3n Industrial",
    "sg:phone":"+34 972 23 45 69",
    "sg:postcode":"17005",
    "sg:province":"Girona",
    "wof:name":"Babores Exposito Jose",
    "wof:placetype":"venue"
},
  "geometry": {"coordinates":[2.8098049164,41.9683227539],"type":"Point"}
}