{
  "type": "Feature",
  "properties": {
    "iso:country":"ES",
    "sg:address":"Carrer de Jaume Balmes, 9",
    "sg:city":"S. Pere Ribes",
    "sg:orig_category":"Pescader\u00cdas (al Por Menor)",
    "sg:phone":"+34 938 96 04 51",
    "sg:postcode":"08810",
    "sg:province":"Barcelona",
    "wof:name":"Mestres Carnoma Nuria",
    "wof:placetype":"venue"
},
  "geometry": {"coordinates":[1.7700059414,41.261844635],"type":"Point"}
}