{
  "type": "Feature",
  "properties": {
    "iso:country":"ES",
    "sg:address":"Calle de Juan De La Cierva, 7",
    "sg:city":"San Jose Rinconada",
    "sg:orig_category":"Chapister\u00cda",
    "sg:phone":"+34 954 79 15 77",
    "sg:postcode":"41300",
    "sg:province":"Sevilla",
    "wof:name":"Talleres Flocar S.%.",
    "wof:placetype":"venue"
},
  "geometry": {"coordinates":[-5.9472270012,37.4866333008],"type":"Point"}
}