{
  "type": "Feature",
  "properties": {
    "iso:country":"ES",
    "sg:address":"Plaza De Covadonga, 3",
    "sg:city":"Torrelavega",
    "sg:orig_category":"Mercer\u00cda, Lencer\u00cda (al Por Menor)",
    "sg:phone":"+34 942 89 21 25",
    "sg:postcode":"39300",
    "sg:province":"Cantabria",
    "wof:name":"Setien Setien Maria De Los Angeles",
    "wof:placetype":"venue"
},
  "geometry": {"coordinates":[-4.0605721474,43.3445739746],"type":"Point"}
}