{
  "type": "Feature",
  "properties": {
    "iso:country":"ES",
    "sg:address":"La Iglesia, 11",
    "sg:city":"La Robla",
    "sg:orig_category":"Bisuter\u00cda, Joyer\u00cda, Relojer\u00cda (al Por Menor)",
    "sg:phone":"+34 987 57 25 91",
    "sg:postcode":"24640",
    "sg:province":"Le\u00f3n",
    "wof:name":"Miguelez Miguelez Maria Jose",
    "wof:placetype":"venue"
},
  "geometry": {"coordinates":[-5.6280670166,42.8031616211],"type":"Point"}
}