{
  "type": "Feature",
  "properties": {
    "addr:full":"Calle de Marques De Vistabella, 19 Motril Granada 18600",
    "addr:housenumber":"19",
    "addr:postcode":"18600",
    "addr:street":"Calle De Marques De Vistabella",
    "iso:country":"ES",
    "sg:address":"Calle de Marques De Vistabella, 19",
    "sg:city":"Motril",
    "sg:orig_category":"Institutos De Belleza",
    "sg:phone":"+34 958 82 06 96",
    "sg:postcode":"18600",
    "sg:province":"Granada",
    "wof:name":"Jodar Fernandez Dolores",
    "wof:placetype":"venue"
},
  "geometry": {"coordinates":[-3.5190091133,36.7459716797],"type":"Point"}
}