{
  "type": "Feature",
  "properties": {
    "addr:full":"La Cerquilla, 13 Nueva Andalucia M\u00e1laga 29660",
    "addr:housenumber":"13",
    "addr:postcode":"29660",
    "addr:street":"Cerquilla;Ma\u0301Laga",
    "iso:country":"ES",
    "sg:address":"La Cerquilla, 13",
    "sg:city":"Nueva Andalucia",
    "sg:orig_category":"Abogados",
    "sg:phone":"+34 952 90 75 54",
    "sg:postcode":"29660",
    "sg:province":"M\u00e1laga",
    "wof:name":"Galama Inversiones S.l.",
    "wof:placetype":"venue"
},
  "geometry": {"coordinates":[-4.9540901184,36.4891586304],"type":"Point"}
}