{
  "type": "Feature",
  "properties": {
    "addr:full":"Calle de Diego Maria Crehuet, 15 Caceres C\u00e1ceres 10004",
    "addr:housenumber":"15",
    "addr:postcode":"10004",
    "addr:street":"Calle De Diego Maria Crehuet;Ca\u0301Ceres",
    "iso:country":"ES",
    "sg:address":"Calle de Diego Maria Crehuet, 15",
    "sg:city":"Caceres",
    "sg:orig_category":"Asociaciones Humanitarias, De Cooperaci\u00d3n, De Acci\u00d3n Social",
    "sg:phone":"+34 927 22 76 13",
    "sg:postcode":"10004",
    "sg:province":"C\u00e1ceres",
    "wof:name":"Comite Ciudadano Antisida De Caceres",
    "wof:placetype":"venue"
},
  "geometry": {"coordinates":[-6.3745379448,39.4712028503],"type":"Point"}
}