{
  "type": "Feature",
  "properties": {
    "iso:country":"ES",
    "sg:address":"Calle de Turina, 8",
    "sg:city":"Barakaldo",
    "sg:orig_category":"Institutos De Belleza",
    "sg:phone":"+34 944 99 16 12",
    "sg:postcode":"48903",
    "sg:province":"Vizcaya",
    "wof:name":"Idoia Velasco Rodriguez",
    "wof:placetype":"venue"
},
  "geometry": {"coordinates":[-2.9789960384,43.2861022949],"type":"Point"}
}