{
  "type": "Feature",
  "properties": {
    "addr:full":"Plaz Pintor Pedro Flores, S/n Carmen Murcia 30002",
    "addr:housenumber":"s / n",
    "addr:postcode":"30002",
    "addr:street":"Plaz;Pedro Flores",
    "iso:country":"ES",
    "sg:address":"Plaz Pintor Pedro Flores, S/n",
    "sg:city":"Carmen",
    "sg:orig_category":"Peluqueros: De Se\u00d1oras",
    "sg:phone":"+34 968 34 64 18",
    "sg:postcode":"30002",
    "sg:province":"Murcia",
    "wof:name":"Erena Negrillo Laura",
    "wof:placetype":"venue"
},
  "geometry": {"coordinates":[-1.1302499771,37.9829597473],"type":"Point"}
}