{
  "type": "Feature",
  "properties": {
    "addr:full":"Calle de Asturias, 30 Fuengirola M\u00e1laga 29640",
    "addr:housenumber":"30",
    "addr:postcode":"29640",
    "addr:street":"Calle De Asturias;Ma\u0301Laga",
    "iso:country":"ES",
    "sg:address":"Calle de Asturias, 30",
    "sg:city":"Fuengirola",
    "sg:orig_category":"Ropa Para Se\u00d1oras Y Caballeros (al Por Menor)",
    "sg:phone":"+34 952 47 04 50",
    "sg:postcode":"29640",
    "sg:province":"M\u00e1laga",
    "wof:name":"Don Miguel S. A.",
    "wof:placetype":"venue"
},
  "geometry": {"coordinates":[-4.6174669266,36.5471343994],"type":"Point"}
}