{
  "type": "Feature",
  "properties": {
    "addr:full":"Pl Esglesia, S/n Caldes Montbui Barcelona 08140",
    "addr:housenumber":"s / n",
    "addr:postcode":"08140",
    "addr:street":"Pl Esglesia;Montbui Barcelona",
    "iso:country":"ES",
    "sg:address":"Pl Esglesia, S/n",
    "sg:city":"Caldes Montbui",
    "sg:orig_category":"Iglesia Cat\u00d3lica",
    "sg:phone":"+34 938 65 00 82",
    "sg:postcode":"08140",
    "sg:province":"Barcelona",
    "wof:name":"Parroquia De Santa Maria",
    "wof:placetype":"venue"
},
  "geometry": {"coordinates":[2.1626939774,41.6326408386],"type":"Point"}
}