{
  "type": "Feature",
  "properties": {
    "addr:full":"Calle de Alcoraz, 4 Huesca Huesca 22002",
    "addr:housenumber":"4",
    "addr:postcode":"22002",
    "addr:street":"Calle De Alcoraz",
    "iso:country":"ES",
    "sg:address":"Calle de Alcoraz, 4",
    "sg:city":"Huesca",
    "sg:orig_category":"M\u00c9dicos: Oftalmolog\u00cda",
    "sg:phone":"+34 974 21 13 77",
    "sg:postcode":"22002",
    "sg:province":"Huesca",
    "wof:name":"Susin Brabo Ramon",
    "wof:placetype":"venue"
},
  "geometry": {"coordinates":[-0.4098629951,42.1357116699],"type":"Point"}
}