{
  "type": "Feature",
  "properties": {
    "iso:country":"ES",
    "sg:address":"Carrer de Antonio Machado, S/n",
    "sg:city":"Castelldefels",
    "sg:orig_category":"Carnicer\u00cdas, Carnicer\u00cdas",
    "sg:phone":"+34 936 64 35 62",
    "sg:postcode":"08860",
    "sg:province":"Barcelona",
    "wof:name":"Achell Nosas Jose",
    "wof:placetype":"venue"
},
  "geometry": {"coordinates":[1.9830360413,41.2889328003],"type":"Point"}
}