{
  "type": "Feature",
  "properties": {
    "addr:full":"Calle de Postigo, 7 Puerto De Santa Maria C\u00e1diz 11500",
    "addr:housenumber":"7",
    "addr:postcode":"11500",
    "addr:street":"Calle De Postigo;Ca\u0301Diz",
    "iso:country":"ES",
    "sg:address":"Calle de Postigo, 7",
    "sg:city":"Puerto De Santa Maria",
    "sg:orig_category":"Empresas De Carpinter\u00cda De Madera",
    "sg:phone":"+34 956 85 06 13",
    "sg:postcode":"11500",
    "sg:province":"C\u00e1diz",
    "wof:name":"Picazo Sanchez Manuel",
    "wof:placetype":"venue"
},
  "geometry": {"coordinates":[-6.2292408943,36.6000213623],"type":"Point"}
}