{
  "type": "Feature",
  "properties": {
    "addr:full":"Calle de Arabial, 36 Granada Granada 18004",
    "addr:housenumber":"36",
    "addr:postcode":"18004",
    "addr:street":"Calle De Arabial",
    "iso:country":"ES",
    "sg:address":"Calle de Arabial, 36",
    "sg:city":"Granada",
    "sg:orig_category":"Empresas De Portes Y Mensajer\u00cda",
    "sg:phone":"+34 958 25 58 62",
    "sg:postcode":"18004",
    "sg:province":"Granada",
    "wof:name":"Servilogra S.l.",
    "wof:placetype":"venue"
},
  "geometry": {"coordinates":[-3.6074919701,37.170589447],"type":"Point"}
}