{
  "type": "Feature",
  "properties": {
    "addr:full":"Plaz Hidrogeno, 4 Madrid Madrid 28026",
    "addr:housenumber":"4",
    "addr:postcode":"28026",
    "addr:street":"Plaz Hidrogeno",
    "iso:country":"ES",
    "sg:address":"Plaz Hidrogeno, 4",
    "sg:city":"Madrid",
    "sg:orig_category":"Pescader\u00cdas (al Por Menor)",
    "sg:phone":"+34 915 00 54 01",
    "sg:postcode":"28026",
    "sg:province":"Madrid",
    "wof:name":"Judith-innova S.l.",
    "wof:placetype":"venue"
},
  "geometry": {"coordinates":[-3.7080359459,40.3831138611],"type":"Point"}
}