{
  "type": "Feature",
  "properties": {
    "iso:country":"ES",
    "sg:address":"Via Roma, 33",
    "sg:city":"Andratx",
    "sg:orig_category":"M\u00c9dicos: Estomatolog\u00cda",
    "sg:phone":"+34 971 13 62 16",
    "sg:postcode":"07150",
    "sg:province":"Islas Baleares",
    "wof:name":"Ortiz Rodrigo Yoana Amaia",
    "wof:placetype":"venue"
},
  "geometry": {"coordinates":[2.4200510979,39.5755157471],"type":"Point"}
}