{
  "type": "Feature",
  "properties": {
    "iso:country":"ES",
    "sg:address":"Calle de Tramontana, 21",
    "sg:city":"Majadahonda",
    "sg:orig_category":"Orquestas De Variedades",
    "sg:phone":"+34 916 39 40 76",
    "sg:postcode":"28220",
    "sg:province":"Madrid",
    "wof:name":"Padilla Valencia Mercedes",
    "wof:placetype":"venue"
},
  "geometry": {"coordinates":[-3.8572280407,40.4792251587],"type":"Point"}
}