{
  "type": "Feature",
  "properties": {
    "addr:full":"Sa Alzina, 27 Castell Bendinat Islas Baleares 07181",
    "addr:housenumber":"27",
    "addr:postcode":"07181",
    "addr:street":"Alzina;Islas",
    "iso:country":"ES",
    "sg:address":"Sa Alzina, 27",
    "sg:city":"Castell Bendinat",
    "sg:orig_category":"Inmobiliaria (agencias)",
    "sg:phone":"+34 971 40 01 63",
    "sg:postcode":"07181",
    "sg:province":"Islas Baleares",
    "wof:name":"Philina Inversiones S.l.",
    "wof:placetype":"venue"
},
  "geometry": {"coordinates":[2.5657799244,39.5388221741],"type":"Point"}
}