{
  "type": "Feature",
  "properties": {
    "addr:full":"Rbla Iberia, 201 Sabadell Barcelona 08205",
    "addr:housenumber":"201",
    "addr:postcode":"08205",
    "addr:street":"Iberia",
    "iso:country":"ES",
    "sg:address":"Rbla Iberia, 201",
    "sg:city":"Sabadell",
    "sg:orig_category":"Agentes, Concesionarios Y Sucursales De Veh\u00cdculos",
    "sg:phone":"+34 937 45 94 15",
    "sg:postcode":"08205",
    "sg:province":"Barcelona",
    "wof:name":"Turismes Valles S.a.",
    "wof:placetype":"venue"
},
  "geometry": {"coordinates":[2.0964090824,41.5369873047],"type":"Point"}
}