{
  "type": "Feature",
  "properties": {
    "addr:full":"Calle de Rio Mi\u00d1o, 5 Mostoles Madrid 28935",
    "addr:housenumber":"5",
    "addr:postcode":"28935",
    "addr:street":"Calle De Rio Min\u0303O",
    "iso:country":"ES",
    "sg:address":"Calle de Rio Mi\u00d1o, 5",
    "sg:city":"Mostoles",
    "sg:orig_category":"Discotecas Y Salas De Baile",
    "sg:phone":"+34 916 47 77 04",
    "sg:postcode":"28935",
    "sg:province":"Madrid",
    "wof:name":"Pais De Nunca Jamas S.l.",
    "wof:placetype":"venue"
},
  "geometry": {"coordinates":[-3.879445076,40.3161582947],"type":"Point"}
}