{
  "type": "Feature",
  "properties": {
    "iso:country":"ES",
    "sg:address":"Calle de Catedratico Antonio Silva, 2",
    "sg:city":"Caceres",
    "sg:orig_category":"Loter\u00cda Y T\u00d3mbola",
    "sg:phone":"+34 927 21 10 42",
    "sg:postcode":"10002",
    "sg:province":"C\u00e1ceres",
    "wof:name":"Sanguino Gil Maria Jose",
    "wof:placetype":"venue"
},
  "geometry": {"coordinates":[-6.3777050972,39.4699554443],"type":"Point"}
}