{
  "type": "Feature",
  "properties": {
    "addr:full":"Ctra. Chipiona-sanlucar, Km. 0005,0 Chipiona C\u00e1diz 11550",
    "addr:postcode":"11550",
    "addr:street":"Ctra. Chipiona-Sanlucar Km. 0005,0",
    "iso:country":"ES",
    "sg:address":"Ctra. Chipiona-sanlucar, Km. 0005,0",
    "sg:city":"Chipiona",
    "sg:orig_category":"Ingeniero",
    "sg:phone":"+34 956 37 31 45",
    "sg:postcode":"11550",
    "sg:province":"C\u00e1diz",
    "sg:website":"www.serviagri.com",
    "wof:name":"Serviagri 98 S.l.",
    "wof:placetype":"venue"
},
  "geometry": {"coordinates":[-6.4288592339,36.7313156128],"type":"Point"}
}