{
  "type": "Feature",
  "properties": {
    "iso:country":"ES",
    "sg:address":"Calle de Frantzisko Perea, 2",
    "sg:city":"Basauri",
    "sg:orig_category":"Reposter\u00cdas",
    "sg:phone":"+34 944 40 74 76",
    "sg:postcode":"48970",
    "sg:province":"Vizcaya",
    "wof:name":"Panaderia Alex",
    "wof:placetype":"venue"
},
  "geometry": {"coordinates":[-2.8950099945,43.2385559082],"type":"Point"}
}