{
  "type": "Feature",
  "properties": {
    "addr:full":"Torrent De Les Piques, 6 Mataro Barcelona 08304",
    "addr:housenumber":"6",
    "addr:postcode":"08304",
    "addr:street":"Torrent;Mataro Barcelona",
    "iso:country":"ES",
    "sg:address":"Torrent De Les Piques, 6",
    "sg:city":"Mataro",
    "sg:orig_category":"Zapatos (al Por Menor)",
    "sg:phone":"+34 937 98 75 94",
    "sg:postcode":"08304",
    "sg:province":"Barcelona",
    "wof:name":"Gea Caballero Carmen De",
    "wof:placetype":"venue"
},
  "geometry": {"coordinates":[2.4407339096,41.5530776978],"type":"Point"}
}