{
  "type": "Feature",
  "properties": {
    "iso:country":"ES",
    "sg:address":"Calle de Mayor, 7",
    "sg:city":"Allepuz",
    "sg:orig_category":"Sanatorios M\u00c9dico",
    "sg:phone":"+34 978 77 81 56",
    "sg:postcode":"44145",
    "sg:province":"Teruel",
    "wof:name":"Ayuntamiento De Allepuz",
    "wof:placetype":"venue"
},
  "geometry": {"coordinates":[-0.7274159193,40.4922218323],"type":"Point"}
}