{
  "type": "Feature",
  "properties": {
    "iso:country":"ES",
    "sg:address":"Calle de Francisco Navacerrada, 25",
    "sg:city":"Madrid",
    "sg:orig_category":"Masajistas Kinesiterapeutas",
    "sg:phone":"+34 913 56 88 71",
    "sg:postcode":"28028",
    "sg:province":"Madrid",
    "wof:name":"Huespedes Confort S.l.",
    "wof:placetype":"venue"
},
  "geometry": {"coordinates":[-3.6688549519,40.4310874939],"type":"Point"}
}