{
  "type": "Feature",
  "properties": {
    "iso:country":"ES",
    "sg:address":"Calle de Porto Cristo, 17",
    "sg:city":"Alcorcon",
    "sg:orig_category":"Poller\u00cda Y Caza (al Por Menor)",
    "sg:phone":"+34 916 11 57 76",
    "sg:postcode":"28924",
    "sg:province":"Madrid",
    "wof:name":"Pascual Ovejero Fernando",
    "wof:placetype":"venue"
},
  "geometry": {"coordinates":[-3.8178899288,40.3515014648],"type":"Point"}
}