{
  "type": "Feature",
  "properties": {
    "iso:country":"ES",
    "sg:address":"La Cerca, S/n",
    "sg:city":"Fisterra",
    "sg:orig_category":"Asociaciones, Organismos Culturales Y Socioeducativos",
    "sg:phone":"+34 981 74 02 27",
    "sg:postcode":"15155",
    "sg:province":"La Coru\u00f1a",
    "wof:name":"Centro Cultural Y Recreativo De Finisterre",
    "wof:placetype":"venue"
},
  "geometry": {"coordinates":[-9.2622337341,42.9055366516],"type":"Point"}
}