{
  "type": "Feature",
  "properties": {
    "addr:full":"Dret De Reunio, S/n Alzira Valencia 46600",
    "addr:housenumber":"s",
    "addr:postcode":"46600",
    "addr:street":"/ N;Valencia",
    "iso:country":"ES",
    "sg:address":"Dret De Reunio, S/n",
    "sg:city":"Alzira",
    "sg:orig_category":"Armaduras De Hormig\u00d3n",
    "sg:phone":"+34 962 40 48 25",
    "sg:postcode":"46600",
    "sg:province":"Valencia",
    "sg:website":"www.blauverd-habitat.com",
    "wof:name":"Construcciones Blauverd S.l.",
    "wof:placetype":"venue"
},
  "geometry": {"coordinates":[-0.4378489852,39.1517295837],"type":"Point"}
}