{
  "type": "Feature",
  "properties": {
    "addr:full":"Avda Castro Del Rio, 102 Baena C\u00f3rdoba 14850",
    "addr:housenumber":"102",
    "addr:postcode":"14850",
    "addr:street":"Avda Castro Del Rio",
    "iso:country":"ES",
    "sg:address":"Avda Castro Del Rio, 102",
    "sg:city":"Baena",
    "sg:orig_category":"Promotores Constructores",
    "sg:phone":"+34 957 69 00 70",
    "sg:postcode":"14850",
    "sg:province":"C\u00f3rdoba",
    "wof:name":"Iberobras General De Construcciones S.l",
    "wof:placetype":"venue"
},
  "geometry": {"coordinates":[-4.3287916183,37.6178970337],"type":"Point"}
}