{
  "type": "Feature",
  "properties": {
    "addr:full":"Calle de Mozoncillo, S/n Carbonero El Mayor Segovia 40270",
    "addr:housenumber":"s / n",
    "addr:postcode":"40270",
    "addr:street":"Calle De Mozoncillo",
    "iso:country":"ES",
    "sg:address":"Calle de Mozoncillo, S/n",
    "sg:city":"Carbonero El Mayor",
    "sg:orig_category":"Material Y Suministros Para Horticultura, Arboricultura",
    "sg:phone":"+34 921 12 21 40",
    "sg:postcode":"40270",
    "sg:province":"Segovia",
    "wof:name":"Mu\u00f1oz Pascual Candido",
    "wof:placetype":"venue"
},
  "geometry": {"coordinates":[-4.2457499504,41.1290855408],"type":"Point"}
}