{
  "type": "Feature",
  "properties": {
    "addr:full":"Carrer de Sant Joan, 4 S. Esteve Sesrovires Barcelona 08635",
    "addr:housenumber":"4",
    "addr:postcode":"08635",
    "addr:street":"Carrer De Sant Joan",
    "iso:country":"ES",
    "sg:address":"Carrer de Sant Joan, 4",
    "sg:city":"S. Esteve Sesrovires",
    "sg:orig_category":"Pescader\u00cdas (al Por Menor)",
    "sg:phone":"+34 937 71 42 26",
    "sg:postcode":"08635",
    "sg:province":"Barcelona",
    "wof:name":"Garriga Valls Jaime",
    "wof:placetype":"venue"
},
  "geometry": {"coordinates":[1.8721109629,41.4941368103],"type":"Point"}
}