{
  "type": "Feature",
  "properties": {
    "addr:full":"Calle de Vergara, 37 Salamanca Salamanca 37003",
    "addr:housenumber":"37",
    "addr:postcode":"37003",
    "addr:street":"Calle De Vergara",
    "iso:country":"ES",
    "sg:address":"Calle de Vergara, 37",
    "sg:city":"Salamanca",
    "sg:orig_category":"Ense\u00d1anza, Formaci\u00d3n Profesional: Aprendizaje",
    "sg:phone":"+34 923 18 47 70",
    "sg:postcode":"37003",
    "sg:province":"Salamanca",
    "wof:name":"Hijas De La Caridad",
    "wof:placetype":"venue"
},
  "geometry": {"coordinates":[-5.6536359787,40.9624557495],"type":"Point"}
}