{
  "type": "Feature",
  "properties": {
    "iso:country":"ES",
    "sg:address":"Carrer de Oblit, 48",
    "sg:city":"Barcelona",
    "sg:orig_category":"Carnicer\u00cdas, Carnicer\u00cdas",
    "sg:phone":"+34 934 35 58 82",
    "sg:postcode":"08041",
    "sg:province":"Barcelona",
    "wof:name":"Portas Soler Ferreol",
    "wof:placetype":"venue"
},
  "geometry": {"coordinates":[2.1775610447,41.4194335938],"type":"Point"}
}