{
  "type": "Feature",
  "properties": {
    "addr:full":"Calle de Santa Lucia, 14 Merida Badajoz 06800",
    "addr:housenumber":"14",
    "addr:postcode":"06800",
    "addr:street":"Calle De Santa Lucia",
    "iso:country":"ES",
    "sg:address":"Calle de Santa Lucia, 14",
    "sg:city":"Merida",
    "sg:orig_category":"M\u00c9dicos: Otorrinolaringolog\u00cda",
    "sg:phone":"+34 924 30 12 06",
    "sg:postcode":"06800",
    "sg:province":"Badajoz",
    "wof:name":"Guillen Asensio Vicente",
    "wof:placetype":"venue"
},
  "geometry": {"coordinates":[-6.340157032,38.91929245],"type":"Point"}
}