{
  "type": "Feature",
  "properties": {
    "iso:country":"ES",
    "sg:address":"Calle de Erudito Pages, 16",
    "sg:city":"Valencia",
    "sg:orig_category":"Fabricaci\u00d3n De Motores El\u00c9ctricos",
    "sg:phone":"+34 963 66 53 54",
    "sg:postcode":"46019",
    "sg:province":"Valencia",
    "wof:name":"Fornas Giralt Jose Antonio",
    "wof:placetype":"venue"
},
  "geometry": {"coordinates":[-0.3785179853,39.4955635071],"type":"Point"}
}