{
  "type": "Feature",
  "properties": {
    "iso:country":"ES",
    "sg:address":"Av Argentina, 28",
    "sg:city":"Palma",
    "sg:orig_category":"Agencias De Viajes",
    "sg:phone":"+34 971 78 70 70",
    "sg:postcode":"07011",
    "sg:province":"Islas Baleares",
    "sg:website":"www.marsans.es",
    "wof:name":"Viajes Marsans S.a.",
    "wof:placetype":"venue"
},
  "geometry": {"coordinates":[2.6409950256,39.5758857727],"type":"Point"}
}