{
  "type": "Feature",
  "properties": {
    "addr:full":"Calle de Obispo Alonso Suarez, 1 Jaen Ja\u00e9n 23008",
    "addr:housenumber":"1;jae\u0301n",
    "addr:postcode":"23008",
    "addr:street":"Calle De Obispo Alonso Suarez",
    "iso:country":"ES",
    "sg:address":"Calle de Obispo Alonso Suarez, 1",
    "sg:city":"Jaen",
    "sg:orig_category":"Abogados",
    "sg:phone":"+34 953 00 35 00",
    "sg:postcode":"23008",
    "sg:province":"Ja\u00e9n",
    "wof:name":"Junta De Andalucia-consejeria De Justicia",
    "wof:placetype":"venue"
},
  "geometry": {"coordinates":[-3.7852520943,37.7744369507],"type":"Point"}
}