{
  "type": "Feature",
  "properties": {
    "iso:country":"ES",
    "sg:address":"Calle de Calvario, 51",
    "sg:city":"Rota",
    "sg:orig_category":"Muebles, Minoristas",
    "sg:phone":"+34 956 81 20 51",
    "sg:postcode":"11520",
    "sg:province":"C\u00e1diz",
    "wof:name":"Escalante Dorante Juan",
    "wof:placetype":"venue"
},
  "geometry": {"coordinates":[-6.3565797806,36.6240348816],"type":"Point"}
}