{
  "type": "Feature",
  "properties": {
    "iso:country":"ES",
    "sg:address":"C/ Enric De Carcer, S/n",
    "sg:city":"Tarrega",
    "sg:orig_category":"Molduras, Junquillos, Listones Y Molduras Perforadas",
    "sg:phone":"+34 973 50 07 37",
    "sg:postcode":"25300",
    "sg:province":"Lleida",
    "wof:name":"Ribau Sole Rosa",
    "wof:placetype":"venue"
},
  "geometry": {"coordinates":[1.1405550241,41.6525192261],"type":"Point"}
}