{
  "type": "Feature",
  "properties": {
    "iso:country":"ES",
    "sg:address":"Calle de Atazar (del), 4",
    "sg:city":"Colmenar Viejo",
    "sg:orig_category":"Enfermeras: Consultas, Atenci\u00d3n A Domicilio",
    "sg:phone":"+34 918 45 12 44",
    "sg:postcode":"28770",
    "sg:province":"Madrid",
    "wof:name":"Ciriza Colmenarejo Juan Carlos",
    "wof:placetype":"venue"
},
  "geometry": {"coordinates":[-3.7698745728,40.6648712158],"type":"Point"}
}