{
  "type": "Feature",
  "properties": {
    "addr:full":"Calle de Real, 3 Casillas De Coria C\u00e1ceres 10818",
    "addr:housenumber":"3",
    "addr:postcode":"10818",
    "addr:street":"Calle De Real",
    "iso:country":"ES",
    "sg:address":"Calle de Real, 3",
    "sg:city":"Casillas De Coria",
    "sg:orig_category":"Carnicer\u00cdas, Carnicer\u00cdas",
    "sg:phone":"+34 927 14 60 89",
    "sg:postcode":"10818",
    "sg:province":"C\u00e1ceres",
    "wof:name":"Sanchez Gines Jose Felipe",
    "wof:placetype":"venue"
},
  "geometry": {"coordinates":[-6.6366257668,39.9652061462],"type":"Point"}
}