{
  "type": "Feature",
  "properties": {
    "addr:full":"Sant Sebastia, 52 Manacor Islas Baleares 07500",
    "addr:housenumber":"52",
    "addr:postcode":"07500",
    "addr:street":"Sebastia",
    "iso:country":"ES",
    "sg:address":"Sant Sebastia, 52",
    "sg:city":"Manacor",
    "sg:orig_category":"Madera Para Construcci\u00d3n E Industria",
    "sg:phone":"+34 971 55 60 45",
    "sg:postcode":"07500",
    "sg:province":"Islas Baleares",
    "wof:name":"Gold Wood S.l.",
    "wof:placetype":"venue"
},
  "geometry": {"coordinates":[3.2126579285,39.567073822],"type":"Point"}
}