{
  "type": "Feature",
  "properties": {
    "addr:full":"Carrer de Sant Ferran, 206 Sabadell Barcelona 08205",
    "addr:housenumber":"206",
    "addr:postcode":"08205",
    "addr:street":"Carrer De Sant Ferran",
    "iso:country":"ES",
    "sg:address":"Carrer de Sant Ferran, 206",
    "sg:city":"Sabadell",
    "sg:orig_category":"Restaurantes",
    "sg:phone":"+34 937 11 04 39",
    "sg:postcode":"08205",
    "sg:province":"Barcelona",
    "wof:name":"Bar Restaurante Vip S.l.",
    "wof:placetype":"venue"
},
  "geometry": {"coordinates":[2.0984199047,41.5355987549],"type":"Point"}
}