{
  "type": "Feature",
  "properties": {
    "addr:full":"Calle de Micer Masco, 17 Valencia Valencia 46010",
    "addr:housenumber":"17",
    "addr:postcode":"46010",
    "addr:street":"Calle De Micer Masco",
    "iso:country":"ES",
    "sg:address":"Calle de Micer Masco, 17",
    "sg:city":"Valencia",
    "sg:orig_category":"Alimentaci\u00d3n General (al Por Menor)",
    "sg:phone":"+34 963 69 19 01",
    "sg:postcode":"46010",
    "sg:province":"Valencia",
    "wof:name":"Rodrigo Serna Vicente",
    "wof:placetype":"venue"
},
  "geometry": {"coordinates":[-0.3622809947,39.4755210876],"type":"Point"}
}