{
  "type": "Feature",
  "properties": {
    "iso:country":"ES",
    "sg:address":"Calle de Madre Maria Teresa, 47",
    "sg:city":"Sevilla",
    "sg:orig_category":"Frutas, Legumbres Frescas Y Tempranas (al Por Menor)",
    "sg:phone":"+34 954 57 19 79",
    "sg:postcode":"41005",
    "sg:province":"Sevilla",
    "wof:name":"Aceitunas Galocha E Hijos S.l.",
    "wof:placetype":"venue"
},
  "geometry": {"coordinates":[-5.9616150856,37.3833045959],"type":"Point"}
}