{
  "type": "Feature",
  "properties": {
    "iso:country":"ES",
    "sg:address":"Plz. Trabuco, 1",
    "sg:city":"Cuenca",
    "sg:orig_category":"Iglesia Cat\u00d3lica",
    "sg:phone":"+34 969 21 34 44",
    "sg:postcode":"16001",
    "sg:province":"Cuenca",
    "wof:name":"Parroquia Santiago Apostol",
    "wof:placetype":"venue"
},
  "geometry": {"coordinates":[-2.1285998821,40.0811233521],"type":"Point"}
}