{
  "type": "Feature",
  "properties": {
    "iso:country":"ES",
    "sg:address":"Avda Juan Carlos I, 6",
    "sg:city":"Zaragoza",
    "sg:orig_category":"Transportes Por Carretera: Lotes Completos, Mercanc\u00cdas Diversas",
    "sg:phone":"+34 976 75 57 31",
    "sg:postcode":"50009",
    "sg:province":"Zaragoza",
    "wof:name":"Dagesa",
    "wof:placetype":"venue"
},
  "geometry": {"coordinates":[-0.9115129709,41.6426048279],"type":"Point"}
}