{
  "type": "Feature",
  "properties": {
    "addr:full":"Calle de Maria Diaz De Haro, 66 Portugalete Vizcaya 48920",
    "addr:housenumber":"66",
    "addr:postcode":"48920",
    "addr:street":"Calle De Maria Diaz De Haro",
    "iso:country":"ES",
    "sg:address":"Calle de Maria Diaz De Haro, 66",
    "sg:city":"Portugalete",
    "sg:orig_category":"Muebles, Minoristas",
    "sg:phone":"+34 944 96 34 55",
    "sg:postcode":"48920",
    "sg:province":"Vizcaya",
    "wof:name":"Irusta De Los Hoyos Gerardo",
    "wof:placetype":"venue"
},
  "geometry": {"coordinates":[-3.0213038921,43.3257255554],"type":"Point"}
}