{
  "type": "Feature",
  "properties": {
    "addr:full":"Calle de Almirante Cervera, 27 S. Fernando C\u00e1diz 11100",
    "addr:housenumber":"27",
    "addr:postcode":"11100",
    "addr:street":"Calle De Almirante Cervera;S. Fernando Ca\u0301Diz",
    "iso:country":"ES",
    "sg:address":"Calle de Almirante Cervera, 27",
    "sg:city":"S. Fernando",
    "sg:orig_category":"Carnicer\u00cdas, Carnicer\u00cdas",
    "sg:phone":"+34 956 59 47 54",
    "sg:postcode":"11100",
    "sg:province":"C\u00e1diz",
    "wof:name":"Gomez Rodriguez Agustin",
    "wof:placetype":"venue"
},
  "geometry": {"coordinates":[-6.1934747696,36.4654541016],"type":"Point"}
}