{
  "type": "Feature",
  "properties": {
    "addr:full":"Pza. Del Camarin, 3 Torrijos Toledo 45500",
    "addr:housenumber":"3",
    "addr:postcode":"45500",
    "addr:street":"Pza. Del Camarin",
    "iso:country":"ES",
    "sg:address":"Pza. Del Camarin, 3",
    "sg:city":"Torrijos",
    "sg:orig_category":"Asociaciones Y Clubs Deportivos",
    "sg:phone":"+34 925 77 06 51",
    "sg:postcode":"45500",
    "sg:province":"Toledo",
    "wof:name":"Forloz S.l.",
    "wof:placetype":"venue"
},
  "geometry": {"coordinates":[-4.2832770348,39.983253479],"type":"Point"}
}