{
  "type": "Feature",
  "properties": {
    "iso:country":"ES",
    "sg:address":"Mula, S/n",
    "sg:city":"Torres Cotillas",
    "sg:orig_category":"Zapater\u00cdas",
    "sg:phone":"+34 968 38 70 10",
    "sg:postcode":"30565",
    "sg:province":"Murcia",
    "sg:website":"www.palc.es",
    "wof:name":"Palc Chemical Espa\u00d1ola S.l.",
    "wof:placetype":"venue"
},
  "geometry": {"coordinates":[-1.2483240366,38.0309638977],"type":"Point"}
}