{
  "type": "Feature",
  "properties": {
    "addr:full":"Calle de Ntra Sra Del Salz, 15 Zaragoza Zaragoza 50017",
    "addr:housenumber":"15",
    "addr:postcode":"50017",
    "addr:street":"Calle De Ntra Sra Del Salz",
    "iso:country":"ES",
    "sg:address":"Calle de Ntra Sra Del Salz, 15",
    "sg:city":"Zaragoza",
    "sg:orig_category":"Imprenta",
    "sg:phone":"+34 976 53 30 75",
    "sg:postcode":"50017",
    "sg:province":"Zaragoza",
    "wof:name":"Imprenta Kaixo S.l.",
    "wof:placetype":"venue"
},
  "geometry": {"coordinates":[-0.9148240089,41.649723053],"type":"Point"}
}