{
  "type": "Feature",
  "properties": {
    "addr:full":"Calle de Picon, 23 Fernan Caballero Ciudad Real 13140",
    "addr:housenumber":"23",
    "addr:postcode":"13140",
    "addr:street":"Calle De Picon",
    "iso:country":"ES",
    "sg:address":"Calle de Picon, 23",
    "sg:city":"Fernan Caballero",
    "sg:orig_category":"Ingeniero",
    "sg:phone":"+34 926 80 91 00",
    "sg:postcode":"13140",
    "sg:province":"Ciudad Real",
    "wof:name":"Iba\u00f1ez Goicoechea Ana Maria",
    "wof:placetype":"venue"
},
  "geometry": {"coordinates":[-3.9014279842,39.1229934692],"type":"Point"}
}