{
  "type": "Feature",
  "properties": {
    "addr:full":"C/ Trencadors, 62 Arenal Islas Baleares 07600",
    "addr:housenumber":"62",
    "addr:postcode":"07600",
    "addr:street":"C / Trencadors",
    "iso:country":"ES",
    "sg:address":"C/ Trencadors, 62",
    "sg:city":"Arenal",
    "sg:orig_category":"Marroquiner\u00cda (confecci\u00d3n)",
    "sg:phone":"+34 971 44 33 30",
    "sg:postcode":"07600",
    "sg:province":"Islas Baleares",
    "wof:name":"Diop  Ablaye",
    "wof:placetype":"venue"
},
  "geometry": {"coordinates":[2.752327919,39.5086097717],"type":"Point"}
}