{
  "type": "Feature",
  "properties": {
    "iso:country":"ES",
    "sg:address":"Carrer de Sant Domenec, 8",
    "sg:city":"Barcelona",
    "sg:orig_category":"Psic\u00d3logos",
    "sg:phone":"+34 932 37 69 57",
    "sg:postcode":"08012",
    "sg:province":"Barcelona",
    "wof:name":"Rosales Manfredi Ines",
    "wof:placetype":"venue"
},
  "geometry": {"coordinates":[2.1563930511,41.3995857239],"type":"Point"}
}