{
  "type": "Feature",
  "properties": {
    "addr:full":"Rua Garcia Caama\u00d1o, 9 Vilagarcia Pontevedra 36600",
    "addr:housenumber":"9",
    "addr:postcode":"36600",
    "addr:street":"Rua Garcia Caaman\u0303O",
    "iso:country":"ES",
    "sg:address":"Rua Garcia Caama\u00d1o, 9",
    "sg:city":"Vilagarcia",
    "sg:orig_category":"Sociedades, Compa\u00d1\u00cdas Aseguradoras",
    "sg:phone":"+34 986 51 24 40",
    "sg:postcode":"36600",
    "sg:province":"Pontevedra",
    "sg:website":"www.agenteallianz.com/bouzada_carril",
    "wof:name":"Bouzada Carril C.b.",
    "wof:placetype":"venue"
},
  "geometry": {"coordinates":[-8.7662601471,42.5921325684],"type":"Point"}
}