{
  "type": "Feature",
  "properties": {
    "addr:full":"Avda De Niebla, 45 Bonares Huelva 21830",
    "addr:housenumber":"45",
    "addr:postcode":"21830",
    "addr:street":"Avda De Niebla",
    "iso:country":"ES",
    "sg:address":"Avda De Niebla, 45",
    "sg:city":"Bonares",
    "sg:orig_category":"Empresas De Carpinter\u00cda Met\u00c1lica",
    "sg:phone":"+34 959 36 66 75",
    "sg:postcode":"21830",
    "sg:province":"Huelva",
    "wof:name":"Sistemas Innoval S.l.l.",
    "wof:placetype":"venue"
},
  "geometry": {"coordinates":[-6.6792860031,37.3259811401],"type":"Point"}
}