{
  "type": "Feature",
  "properties": {
    "addr:full":"Av Miramar, 17 Pujols Islas Baleares 07871",
    "addr:housenumber":"17",
    "addr:postcode":"07871",
    "addr:street":"Av Miramar",
    "iso:country":"ES",
    "sg:address":"Av Miramar, 17",
    "sg:city":"Pujols",
    "sg:orig_category":"Publicidad (soportes Y Gesti\u00d3n)",
    "sg:phone":"+34 971 32 91 57",
    "sg:postcode":"07871",
    "sg:province":"Islas Baleares",
    "wof:name":"Forindopacifik S.l.",
    "wof:placetype":"venue"
},
  "geometry": {"coordinates":[1.4576120377,38.7231826782],"type":"Point"}
}