{
  "type": "Feature",
  "properties": {
    "addr:full":"Calle de Duque De Frias, 21 Burgos Burgos 09006",
    "addr:housenumber":"21",
    "addr:postcode":"09006",
    "addr:street":"Calle De Duque De Frias",
    "iso:country":"ES",
    "sg:address":"Calle de Duque De Frias, 21",
    "sg:city":"Burgos",
    "sg:orig_category":"Panader\u00cdas, Panader\u00cdas",
    "sg:phone":"+34 947 21 78 20",
    "sg:postcode":"09006",
    "sg:province":"Burgos",
    "wof:name":"Panaderia Ricardo Y Jaime Camara S.l.",
    "wof:placetype":"venue"
},
  "geometry": {"coordinates":[-3.6786267757,42.3608131409],"type":"Point"}
}