{
  "type": "Feature",
  "properties": {
    "addr:full":"Ctra Canet Berenguer, S/n Faura Valencia 46512",
    "addr:housenumber":"s",
    "addr:postcode":"46512",
    "addr:street":"Ctra Canet Berenguer;/ N",
    "iso:country":"ES",
    "sg:address":"Ctra Canet Berenguer, S/n",
    "sg:city":"Faura",
    "sg:orig_category":"Cajas Y Embalajes De Madera",
    "sg:phone":"+34 962 60 22 16",
    "sg:postcode":"46512",
    "sg:province":"Valencia",
    "wof:name":"Envases Fruyver S.l.",
    "wof:placetype":"venue"
},
  "geometry": {"coordinates":[-0.2641490102,39.726108551],"type":"Point"}
}