{
  "type": "Feature",
  "properties": {
    "iso:country":"ES",
    "sg:address":"Avda Aguirre Lehendakari, 5",
    "sg:city":"Bilbao",
    "sg:orig_category":"Asociaciones, Organismos Culturales Y Socioeducativos",
    "sg:phone":"+34 944 76 62 00",
    "sg:postcode":"48014",
    "sg:province":"Vizcaya",
    "wof:name":"Sociedad Vasca De Minusvalidos Bidaideak De Bilbao",
    "wof:placetype":"venue"
},
  "geometry": {"coordinates":[-2.9427399635,43.2713890076],"type":"Point"}
}