{
  "type": "Feature",
  "properties": {
    "iso:country":"ES",
    "sg:address":"Carrer de Francesc Cambo, 2",
    "sg:city":"S. Joan Despi",
    "sg:orig_category":"Sociedades, Compa\u00d1\u00cdas Aseguradoras",
    "sg:phone":"+34 934 77 06 47",
    "sg:postcode":"08970",
    "sg:province":"Barcelona",
    "wof:name":"Seguros Catalana Occidente S.a. De Seguros Y Reaseguros",
    "wof:placetype":"venue"
},
  "geometry": {"coordinates":[2.072715044,41.3680419922],"type":"Point"}
}