{
  "type": "Feature",
  "properties": {
    "iso:country":"ES",
    "sg:address":"Urb Humboldt, 2",
    "sg:city":"Cuevas",
    "sg:orig_category":"Charcuter\u00cdas (al Por Mayor)",
    "sg:phone":"+34 922 33 65 67",
    "sg:postcode":"38314",
    "sg:province":"Santa Cruz De Tenerife",
    "wof:name":"Sprungmann Schoega Gerardo",
    "wof:placetype":"venue"
},
  "geometry": {"coordinates":[-16.5165729523,28.4114284515],"type":"Point"}
}