{
  "type": "Feature",
  "properties": {
    "iso:country":"ES",
    "sg:address":"Calle de Esteban Salmeron, 1",
    "sg:city":"Carolina",
    "sg:orig_category":"Zapatos (al Por Menor)",
    "sg:phone":"+34 953 66 06 87",
    "sg:postcode":"23200",
    "sg:province":"Ja\u00e9n",
    "wof:name":"Casta\u00f1o Bofill Juan Carlos",
    "wof:placetype":"venue"
},
  "geometry": {"coordinates":[-3.6131050587,38.2751922607],"type":"Point"}
}