{
  "type": "Feature",
  "properties": {
    "addr:full":"Calle de 28 De Febrero, 97 Berja Almer\u00eda 04760",
    "addr:housenumber":"28;97",
    "addr:postcode":"04760",
    "addr:street":"Calle De;De Febrero",
    "iso:country":"ES",
    "sg:address":"Calle de 28 De Febrero, 97",
    "sg:city":"Berja",
    "sg:orig_category":"Venta, Montaje De Neum\u00c1ticos",
    "sg:phone":"+34 950 49 07 39",
    "sg:postcode":"04760",
    "sg:province":"Almer\u00eda",
    "wof:name":"Sanchez Roda Francisco",
    "wof:placetype":"venue"
},
  "geometry": {"coordinates":[-2.9477443695,36.84217453],"type":"Point"}
}