{
  "type": "Feature",
  "properties": {
    "addr:full":"C/ Pont Dels Ortissos, 16 Elche Alicante 03202",
    "addr:housenumber":"16",
    "addr:postcode":"03202",
    "addr:street":"C / Pont Dels Ortissos",
    "iso:country":"ES",
    "sg:address":"C/ Pont Dels Ortissos, 16",
    "sg:city":"Elche",
    "sg:orig_category":"Cl\u00cdnicas Dentales",
    "sg:phone":"+34 965 42 19 45",
    "sg:postcode":"03202",
    "sg:province":"Alicante",
    "wof:name":"Garcia Pinilla Soledad",
    "wof:placetype":"venue"
},
  "geometry": {"coordinates":[-0.6950430274,38.266834259],"type":"Point"}
}