{
  "type": "Feature",
  "properties": {
    "addr:full":"Avda Extremadura, S/n Ribera Fresno Badajoz 06225",
    "addr:postcode":"06225",
    "addr:street":"Avda Extremadura S / N",
    "iso:country":"ES",
    "sg:address":"Avda Extremadura, S/n",
    "sg:city":"Ribera Fresno",
    "sg:orig_category":"Transportes Por V\u00cdas Navegables",
    "sg:phone":"+34 924 53 62 54",
    "sg:postcode":"06225",
    "sg:province":"Badajoz",
    "wof:name":"Baez Tavero Juan",
    "wof:placetype":"venue"
},
  "geometry": {"coordinates":[-6.2374835014,38.5506706238],"type":"Point"}
}