{
  "type": "Feature",
  "properties": {
    "iso:country":"ES",
    "sg:address":"Calle de San Diego, 33",
    "sg:city":"Aguilas",
    "sg:orig_category":"Electricidad: Instaladores",
    "sg:phone":"+34 968 44 94 39",
    "sg:postcode":"30880",
    "sg:province":"Murcia",
    "wof:name":"Instalaciones Electricas De Aguilas S.c.",
    "wof:placetype":"venue"
},
  "geometry": {"coordinates":[-1.5846090317,37.4092483521],"type":"Point"}
}