{
  "type": "Feature",
  "properties": {
    "addr:full":"Ctra Aznalc-pilas, Km. 0002,2 Aznalcazar Sevilla 41849",
    "addr:postcode":"41849",
    "addr:street":"Ctra Aznalc-Pilas Km. 0002,2 Aznalcazar",
    "iso:country":"ES",
    "sg:address":"Ctra Aznalc-pilas, Km. 0002,2",
    "sg:city":"Aznalcazar",
    "sg:orig_category":"Muebles, Minoristas",
    "sg:phone":"+34 955 75 08 93",
    "sg:postcode":"41849",
    "sg:province":"Sevilla",
    "wof:name":"Bahama Decor Sl",
    "wof:placetype":"venue"
},
  "geometry": {"coordinates":[-6.2510838509,37.303768158],"type":"Point"}
}