{
  "type": "Feature",
  "properties": {
    "addr:full":"Carrer de Sor Lluisa Estivill, 10 Reus Tarragona 43202",
    "addr:housenumber":"10",
    "addr:postcode":"43202",
    "addr:street":"Carrer De Sor Lluisa Estivill",
    "iso:country":"ES",
    "sg:address":"Carrer de Sor Lluisa Estivill, 10",
    "sg:city":"Reus",
    "sg:orig_category":"Librer\u00cdas",
    "sg:phone":"+34 977 32 02 02",
    "sg:postcode":"43202",
    "sg:province":"Tarragona",
    "wof:name":"Malex Papeleria S.l.",
    "wof:placetype":"venue"
},
  "geometry": {"coordinates":[1.1007709503,41.1506958008],"type":"Point"}
}