{
  "type": "Feature",
  "properties": {
    "addr:full":"Ctra. Burgos, 1 Sto. Domingo Calzada La Rioja 26250",
    "addr:housenumber":"1",
    "addr:postcode":"26250",
    "addr:street":"Ctra. Burgos;Calzada;Rioja",
    "iso:country":"ES",
    "sg:address":"Ctra. Burgos, 1",
    "sg:city":"Sto. Domingo Calzada",
    "sg:orig_category":"Mataderos Y Talleres De Despiezado",
    "sg:phone":"+34 941 34 30 96",
    "sg:postcode":"26250",
    "sg:province":"La Rioja",
    "wof:name":"Carnicas Del Oja S.l.",
    "wof:placetype":"venue"
},
  "geometry": {"coordinates":[-2.9541339874,42.4394760132],"type":"Point"}
}