{
  "type": "Feature",
  "properties": {
    "iso:country":"ES",
    "sg:address":"Calle de Antonio Vi\u00d1es, 16",
    "sg:city":"Coru\u00d1a",
    "sg:orig_category":"Inmobiliaria (agencias)",
    "sg:phone":"+34 981 15 15 78",
    "sg:postcode":"15007",
    "sg:province":"La Coru\u00f1a",
    "wof:name":"Gesai S.a.",
    "wof:placetype":"venue"
},
  "geometry": {"coordinates":[-8.4082565308,43.3571434021],"type":"Point"}
}