{
  "type": "Feature",
  "properties": {
    "iso:country":"ES",
    "sg:address":"Avda Cabo Noval, 45",
    "sg:city":"Sanlucar De Barrameda",
    "sg:orig_category":"Inform\u00c1tica: Redes",
    "sg:phone":"+34 956 36 47 06",
    "sg:postcode":"11540",
    "sg:province":"C\u00e1diz",
    "sg:website":"www.rentel.es",
    "wof:name":"Rentel Comunicaciones S.l.",
    "wof:placetype":"venue"
},
  "geometry": {"coordinates":[-6.3519158363,36.7848510742],"type":"Point"}
}