{
  "type": "Feature",
  "properties": {
    "addr:full":"Calle de San Pablo, 33 Baeza Ja\u00e9n 23440",
    "addr:housenumber":"33",
    "addr:postcode":"23440",
    "addr:street":"Calle De San Pablo",
    "iso:country":"ES",
    "sg:address":"Calle de San Pablo, 33",
    "sg:city":"Baeza",
    "sg:orig_category":"Molduras, Junquillos, Listones Y Molduras Perforadas",
    "sg:phone":"+34 953 74 05 18",
    "sg:postcode":"23440",
    "sg:province":"Ja\u00e9n",
    "wof:name":"Garrido Ruiz Diego",
    "wof:placetype":"venue"
},
  "geometry": {"coordinates":[-3.4657430649,37.9944229126],"type":"Point"}
}