{
  "type": "Feature",
  "properties": {
    "addr:full":"Carrer de Mestre Joan Corrales, 24 Esplugues Llobregat Barcelona 08950",
    "addr:housenumber":"24",
    "addr:postcode":"08950",
    "addr:street":"Carrer De Mestre Joan Corrales",
    "iso:country":"ES",
    "sg:address":"Carrer de Mestre Joan Corrales, 24",
    "sg:city":"Esplugues Llobregat",
    "sg:orig_category":"Bricolaje, Herramientas (al Por Menor)",
    "sg:phone":"+34 933 71 02 71",
    "sg:postcode":"08950",
    "sg:province":"Barcelona",
    "wof:name":"Boves C.b.",
    "wof:placetype":"venue"
},
  "geometry": {"coordinates":[2.0866150856,41.3741111755],"type":"Point"}
}