{
  "type": "Feature",
  "properties": {
    "addr:full":"Calle de German Perez Carrasco, 2 Madrid Madrid 28027",
    "addr:housenumber":"2",
    "addr:postcode":"28027",
    "addr:street":"Calle De German Perez Carrasco",
    "iso:country":"ES",
    "sg:address":"Calle de German Perez Carrasco, 2",
    "sg:city":"Madrid",
    "sg:orig_category":"Caf\u00c9s, Bares, Cervecer\u00cdas",
    "sg:phone":"+34 914 07 30 73",
    "sg:postcode":"28027",
    "sg:province":"Madrid",
    "wof:name":"Leandro Fernandez Fausta",
    "wof:placetype":"venue"
},
  "geometry": {"coordinates":[-3.6473343372,40.4343795776],"type":"Point"}
}