{
  "type": "Feature",
  "properties": {
    "addr:full":"Rua Montiron, 177 Lugo Lugo 27002",
    "addr:housenumber":"177",
    "addr:postcode":"27002",
    "addr:street":"Rua Montiron",
    "iso:country":"ES",
    "sg:address":"Rua Montiron, 177",
    "sg:city":"Lugo",
    "sg:orig_category":"Tapicer\u00cdas",
    "sg:phone":"+34 982 22 69 23",
    "sg:postcode":"27002",
    "sg:province":"Lugo",
    "wof:name":"Fonteboa Alvarez Manuel",
    "wof:placetype":"venue"
},
  "geometry": {"coordinates":[-7.5425519943,42.9999160767],"type":"Point"}
}