{
  "type": "Feature",
  "properties": {
    "addr:full":"Rua Mayor, 67 Fonsagrada Lugo 27100",
    "addr:housenumber":"67",
    "addr:postcode":"27100",
    "addr:street":"Rua Mayor",
    "iso:country":"ES",
    "sg:address":"Rua Mayor, 67",
    "sg:city":"Fonsagrada",
    "sg:orig_category":"Mec\u00c1nico Del Autom\u00d3vil",
    "sg:phone":"+34 982 34 02 01",
    "sg:postcode":"27100",
    "sg:province":"Lugo",
    "wof:name":"Fernandez Alvarez Jose",
    "wof:placetype":"venue"
},
  "geometry": {"coordinates":[-7.0685892105,43.123500824],"type":"Point"}
}