{
  "type": "Feature",
  "properties": {
    "addr:full":"Calle de Meson De Paredes, 4 Madrid Madrid 28012",
    "addr:housenumber":"4",
    "addr:postcode":"28012",
    "addr:street":"Calle De Meson De Paredes",
    "iso:country":"ES",
    "sg:address":"Calle de Meson De Paredes, 4",
    "sg:city":"Madrid",
    "sg:orig_category":"Bisuter\u00cda, Joyer\u00cda, Relojer\u00cda (al Por Menor)",
    "sg:phone":"+34 914 20 27 16",
    "sg:postcode":"28012",
    "sg:province":"Madrid",
    "wof:name":"Old Fas S.l.",
    "wof:placetype":"venue"
},
  "geometry": {"coordinates":[-3.7054018974,40.4117240906],"type":"Point"}
}