{
  "type": "Feature",
  "properties": {
    "iso:country":"ES",
    "sg:address":"Carrer de Muntanya, 82",
    "sg:city":"Barcelona",
    "sg:orig_category":"Peleter\u00cdas",
    "sg:phone":"+34 934 35 31 47",
    "sg:postcode":"08026",
    "sg:province":"Barcelona",
    "wof:name":"Vazquez Lopez Domingo",
    "wof:placetype":"venue"
},
  "geometry": {"coordinates":[2.1837909222,41.4125404358],"type":"Point"}
}