{
  "type": "Feature",
  "properties": {
    "addr:full":"Calle de Askao, 25 Bilbao Vizcaya 48005",
    "addr:housenumber":"25",
    "addr:postcode":"48005",
    "addr:street":"Calle De Askao",
    "iso:country":"ES",
    "sg:address":"Calle de Askao, 25",
    "sg:city":"Bilbao",
    "sg:orig_category":"Zapater\u00cdas",
    "sg:phone":"+34 944 15 91 60",
    "sg:postcode":"48005",
    "sg:province":"Vizcaya",
    "wof:name":"Egusquiza Vidaurrazaga Juan Antonio",
    "wof:placetype":"venue"
},
  "geometry": {"coordinates":[-2.921952486,43.258769989],"type":"Point"}
}