{
  "type": "Feature",
  "properties": {
    "addr:full":"Calle de Sor Eloisa, 36 Ayamonte Huelva 21400",
    "addr:housenumber":"36",
    "addr:postcode":"21400",
    "addr:street":"Calle De Sor Eloisa",
    "iso:country":"ES",
    "sg:address":"Calle de Sor Eloisa, 36",
    "sg:city":"Ayamonte",
    "sg:orig_category":"Sindicatos De Trabajadores",
    "sg:phone":"+34 959 32 13 17",
    "sg:postcode":"21400",
    "sg:province":"Huelva",
    "wof:name":"Sindicato Unitario",
    "wof:placetype":"venue"
},
  "geometry": {"coordinates":[-7.3975491524,37.2163009644],"type":"Point"}
}