{
  "type": "Feature",
  "properties": {
    "addr:full":"Calle de Laguna, 62 Quintana Serena Badajoz 06450",
    "addr:housenumber":"62",
    "addr:postcode":"06450",
    "addr:street":"Calle De Laguna",
    "iso:country":"ES",
    "sg:address":"Calle de Laguna, 62",
    "sg:city":"Quintana Serena",
    "sg:orig_category":"M\u00c1rmoles, Granitos Y Piedras Naturales",
    "sg:phone":"+34 924 78 66 62",
    "sg:postcode":"06450",
    "sg:province":"Badajoz",
    "wof:name":"Granitos La Vi\u00f1a Sociedad Cooperativa",
    "wof:placetype":"venue"
},
  "geometry": {"coordinates":[-5.6649160385,38.7419281006],"type":"Point"}
}