{
  "type": "Feature",
  "properties": {
    "addr:full":"Calle de Pio Bermejillo, 44 Balmaseda Vizcaya 48800",
    "addr:housenumber":"44",
    "addr:postcode":"48800",
    "addr:street":"Calle De Pio Bermejillo",
    "iso:country":"ES",
    "sg:address":"Calle de Pio Bermejillo, 44",
    "sg:city":"Balmaseda",
    "sg:orig_category":"Carnicer\u00cdas, Carnicer\u00cdas",
    "sg:phone":"+34 946 80 09 81",
    "sg:postcode":"48800",
    "sg:province":"Vizcaya",
    "wof:name":"Cirion Castresana Francisco",
    "wof:placetype":"venue"
},
  "geometry": {"coordinates":[-3.1929540634,43.1949310303],"type":"Point"}
}