{
  "type": "Feature",
  "properties": {
    "iso:country":"ES",
    "sg:address":"Trva Cara De Dios, 14",
    "sg:city":"Sacedon",
    "sg:orig_category":"Reposter\u00cdas",
    "sg:phone":"+34 949 35 01 15",
    "sg:postcode":"19120",
    "sg:province":"Guadalajara",
    "wof:name":"Notario Orusco Miguel",
    "wof:placetype":"venue"
},
  "geometry": {"coordinates":[-2.7346689701,40.4803581238],"type":"Point"}
}