{
  "type": "Feature",
  "properties": {
    "addr:full":"Calle de Vicente Blasco Iba\u00d1ez, 59 Torrevieja Alicante 03180",
    "addr:housenumber":"59",
    "addr:postcode":"03180",
    "addr:street":"Calle De Vicente Blasco Iban\u0303Ez",
    "iso:country":"ES",
    "sg:address":"Calle de Vicente Blasco Iba\u00d1ez, 59",
    "sg:city":"Torrevieja",
    "sg:orig_category":"Centros Empresariales",
    "sg:phone":"+34 966 70 85 90",
    "sg:postcode":"03180",
    "sg:province":"Alicante",
    "sg:website":"www.euroteamconsultores.es",
    "wof:name":"Euroteam Consultores Asociados Sa",
    "wof:placetype":"venue"
},
  "geometry": {"coordinates":[-0.6792129874,37.9790153503],"type":"Point"}
}