{
  "type": "Feature",
  "properties": {
    "iso:country":"ES",
    "sg:address":"Calle de Gladiolo, 11",
    "sg:city":"Algaba",
    "sg:orig_category":"Reposter\u00cdas",
    "sg:phone":"+34 955 78 82 07",
    "sg:postcode":"41980",
    "sg:province":"Sevilla",
    "wof:name":"Carranza Cruz Mauricio",
    "wof:placetype":"venue"
},
  "geometry": {"coordinates":[-6.0145411491,37.4592666626],"type":"Point"}
}