{
  "type": "Feature",
  "properties": {
    "addr:full":"Urb Miramar, S/n Manga Mar Menor Murcia 30380",
    "addr:housenumber":"/ n",
    "addr:postcode":"30380",
    "addr:street":"Urb Miramar S",
    "iso:country":"ES",
    "sg:address":"Urb Miramar, S/n",
    "sg:city":"Manga Mar Menor",
    "sg:orig_category":"Inmobiliaria (agencias)",
    "sg:phone":"+34 968 56 33 33",
    "sg:postcode":"30380",
    "sg:province":"Murcia",
    "sg:website":"www.inmogestion.es",
    "wof:name":"Inmogestion E Inversiones S.l.",
    "wof:placetype":"venue"
},
  "geometry": {"coordinates":[-0.7281540036,37.6686553955],"type":"Point"}
}