{
  "type": "Feature",
  "properties": {
    "addr:full":"Rond Barcelona, 48 Figueres Girona 17600",
    "addr:postcode":"17600",
    "iso:country":"ES",
    "sg:address":"Rond Barcelona, 48",
    "sg:city":"Figueres",
    "sg:orig_category":"Agentes, Concesionarios Y Sucursales De Veh\u00cdculos",
    "sg:phone":"+34 972 67 28 67",
    "sg:postcode":"17600",
    "sg:province":"Girona",
    "wof:name":"Am 94 Motors S.a.",
    "wof:placetype":"venue"
},
  "geometry": {"coordinates":[2.9656808376,42.256778717],"type":"Point"}
}