{
  "type": "Feature",
  "properties": {
    "iso:country":"ES",
    "sg:address":"Disseminat, S/n",
    "sg:city":"Moia",
    "sg:orig_category":"Fabricaci\u00d3n De Quesos",
    "sg:phone":"+34 938 20 90 10",
    "sg:postcode":"08180",
    "sg:province":"Barcelona",
    "wof:name":"Antunez Roca Pedro",
    "wof:placetype":"venue"
},
  "geometry": {"coordinates":[2.0959429741,41.811214447],"type":"Point"}
}