{
  "type": "Feature",
  "properties": {
    "addr:full":"Plaz Ignacio Mercader, 4 Donostia-san Sebastian Guip\u00f9zcoa 20011",
    "addr:housenumber":"4",
    "addr:postcode":"20011",
    "addr:street":"Ignacio Mercader",
    "iso:country":"ES",
    "sg:address":"Plaz Ignacio Mercader, 4",
    "sg:city":"Donostia-san Sebastian",
    "sg:orig_category":"Herboristas (al Por Menor)",
    "sg:phone":"+34 943 46 95 89",
    "sg:postcode":"20011",
    "sg:province":"Guip\u00f9zcoa",
    "wof:name":"Aldasoro Ruiz Aranzazu",
    "wof:placetype":"venue"
},
  "geometry": {"coordinates":[-1.9734469652,43.3046989441],"type":"Point"}
}