{
  "type": "Feature",
  "properties": {
    "iso:country":"ES",
    "sg:address":"Calle de Sagarminaga, 30",
    "sg:city":"Bilbao",
    "sg:orig_category":"Guarder\u00cdas",
    "sg:phone":"+34 944 11 14 07",
    "sg:postcode":"48004",
    "sg:province":"Vizcaya",
    "wof:name":"Consorcio Haurreskolak",
    "wof:placetype":"venue"
},
  "geometry": {"coordinates":[-2.9099020958,43.2482719421],"type":"Point"}
}