{
  "type": "Feature",
  "properties": {
    "iso:country":"ES",
    "sg:address":"Calle de Numancia, 57",
    "sg:city":"Madrid",
    "sg:orig_category":"Arquitectos",
    "sg:phone":"+34 913 11 75 37",
    "sg:postcode":"28039",
    "sg:province":"Madrid",
    "wof:name":"Estarnu 57 Arquitectos S.l.",
    "wof:placetype":"venue"
},
  "geometry": {"coordinates":[-3.7105131149,40.4562072754],"type":"Point"}
}