{
  "type": "Feature",
  "properties": {
    "iso:country":"ES",
    "sg:address":"Carr Bisbe Sever, 7",
    "sg:city":"Mao",
    "sg:orig_category":"Universidades",
    "sg:phone":"+34 971 35 46 64",
    "sg:postcode":"07703",
    "sg:province":"Islas Baleares",
    "wof:name":"Mascaro I Villalonga S.l.",
    "wof:placetype":"venue"
},
  "geometry": {"coordinates":[4.2572960854,39.8879089355],"type":"Point"}
}