{
  "type": "Feature",
  "properties": {
    "addr:full":"Avda Ruiz De Alda, 49 Barbate C\u00e1diz 11160",
    "addr:housenumber":"49",
    "addr:postcode":"11160",
    "addr:street":"Avda Ruiz De Alda",
    "iso:country":"ES",
    "sg:address":"Avda Ruiz De Alda, 49",
    "sg:city":"Barbate",
    "sg:orig_category":"Organismos De Turismo",
    "sg:phone":"+34 956 43 46 40",
    "sg:postcode":"11160",
    "sg:province":"C\u00e1diz",
    "wof:name":"Ayuntamiento",
    "wof:placetype":"venue"
},
  "geometry": {"coordinates":[-5.9199848175,36.188419342],"type":"Point"}
}