{
  "type": "Feature",
  "properties": {
    "iso:country":"ES",
    "sg:address":"Av Cornella, 37",
    "sg:city":"Esplugues Llobregat",
    "sg:orig_category":"Inform\u00c1tica (estudios, Servicios, Asesor\u00cda, Formaci\u00d3n)",
    "sg:phone":"+34 934 99 05 58",
    "sg:postcode":"08950",
    "sg:province":"Barcelona",
    "wof:name":"Sistemas Informaticos Martin S.l.",
    "wof:placetype":"venue"
},
  "geometry": {"coordinates":[2.0868289471,41.3754196167],"type":"Point"}
}