{
  "type": "Feature",
  "properties": {
    "addr:full":"Ctra. P. Rio, 3 Fuente Palmera C\u00f3rdoba 14120",
    "addr:housenumber":"3",
    "addr:postcode":"14120",
    "addr:street":"Ctra. P. Rio",
    "iso:country":"ES",
    "sg:address":"Ctra. P. Rio, 3",
    "sg:city":"Fuente Palmera",
    "sg:orig_category":"Bazares, Art\u00cdculos De Limpieza Y De Cocina (al Por Menor)",
    "sg:phone":"+34 957 63 81 71",
    "sg:postcode":"14120",
    "sg:province":"C\u00f3rdoba",
    "wof:name":"Martinez Pe\u00f1a Antonio",
    "wof:placetype":"venue"
},
  "geometry": {"coordinates":[-5.104033947,37.7035446167],"type":"Point"}
}