{
  "type": "Feature",
  "properties": {
    "addr:full":"Carr Sant Miquel, 35 Badalona Barcelona 08911",
    "addr:housenumber":"35",
    "addr:postcode":"08911",
    "addr:street":"Carr Sant Miquel",
    "iso:country":"ES",
    "sg:address":"Carr Sant Miquel, 35",
    "sg:city":"Badalona",
    "sg:orig_category":"Laboratorios Y Cl\u00cdnicas Veterinarias",
    "sg:phone":"+34 933 84 25 12",
    "sg:postcode":"08911",
    "sg:province":"Barcelona",
    "wof:name":"Clinica Veterinaria Badalona S. C. P.",
    "wof:placetype":"venue"
},
  "geometry": {"coordinates":[2.2493569851,41.4497756958],"type":"Point"}
}