{
  "type": "Feature",
  "properties": {
    "addr:full":"Calle de Constitucion (de La), 81 Navalcarnero Madrid 28600",
    "addr:housenumber":"81",
    "addr:postcode":"28600",
    "addr:street":"Calle De Constitucion De La",
    "iso:country":"ES",
    "sg:address":"Calle de Constitucion (de La), 81",
    "sg:city":"Navalcarnero",
    "sg:orig_category":"Comercio, Reparaci\u00d3n De Bicicletas, De Motocicletas, De Accesorios",
    "sg:phone":"+34 918 11 36 92",
    "sg:postcode":"28600",
    "sg:province":"Madrid",
    "wof:name":"Carde\u00f1a Diaz Angel",
    "wof:placetype":"venue"
},
  "geometry": {"coordinates":[-4.0100984573,40.2867431641],"type":"Point"}
}