{
  "type": "Feature",
  "properties": {
    "iso:country":"ES",
    "sg:address":"Calle de Motilla Del Palancar, 3",
    "sg:city":"Madrid",
    "sg:orig_category":"Inmobiliaria (agencias)",
    "sg:phone":"+34 913 88 26 30",
    "sg:postcode":"28043",
    "sg:province":"Madrid",
    "wof:name":"Comunidad De Propietarios Motilla De Palancar 3",
    "wof:placetype":"venue"
},
  "geometry": {"coordinates":[-3.6331999302,40.4653663635],"type":"Point"}
}