{
  "type": "Feature",
  "properties": {
    "iso:country":"ES",
    "sg:address":"Pase Canarina, 6",
    "sg:city":"Mancha",
    "sg:orig_category":"Venta, Montaje De Neum\u00c1ticos",
    "sg:phone":"+34 922 12 19 64",
    "sg:postcode":"38430",
    "sg:province":"Santa Cruz De Tenerife",
    "wof:name":"Supermercado De La Cubierta S.l.",
    "wof:placetype":"venue"
},
  "geometry": {"coordinates":[-16.7204761505,28.3677654266],"type":"Point"}
}