{
  "type": "Feature",
  "properties": {
    "addr:full":"Calle de Esteban Salazar Chapela, 69 Malaga M\u00e1laga 29004",
    "addr:housenumber":"69",
    "addr:postcode":"29004",
    "addr:street":"Calle De Esteban Salazar Chapela;Ma\u0301Laga",
    "iso:country":"ES",
    "sg:address":"Calle de Esteban Salazar Chapela, 69",
    "sg:city":"Malaga",
    "sg:orig_category":"Bazares, Art\u00cdculos De Limpieza Y De Cocina (al Por Menor)",
    "sg:phone":"+34 952 24 35 77",
    "sg:postcode":"29004",
    "sg:province":"M\u00e1laga",
    "wof:name":"Xie  Liming",
    "wof:placetype":"venue"
},
  "geometry": {"coordinates":[-4.4756069183,36.6921463013],"type":"Point"}
}