{
  "type": "Feature",
  "properties": {
    "addr:full":"Calle de Margarita Iturralde, 65 Trujillo C\u00e1ceres 10200",
    "addr:housenumber":"65",
    "addr:postcode":"10200",
    "addr:street":"Calle De Margarita Iturralde;Ca\u0301Ceres",
    "iso:country":"ES",
    "sg:address":"Calle de Margarita Iturralde, 65",
    "sg:city":"Trujillo",
    "sg:orig_category":"Inform\u00c1tica: Soportes De Informaci\u00d3n, Suministros & Accesorios",
    "sg:phone":"+34 927 32 15 64",
    "sg:postcode":"10200",
    "sg:province":"C\u00e1ceres",
    "wof:name":"Morales Naharro Candido",
    "wof:placetype":"venue"
},
  "geometry": {"coordinates":[-5.8797111511,39.4581565857],"type":"Point"}
}