{
  "type": "Feature",
  "properties": {
    "iso:country":"ES",
    "sg:address":"Calle de Alcandara, 8",
    "sg:city":"Raya Del Palancar-guadamonte",
    "sg:orig_category":"Inform\u00c1tica, Ofim\u00c1tica (estudios, Asesor\u00cda, Ingenier\u00cda, Formaci\u00d3n)",
    "sg:phone":"+34 918 11 34 75",
    "sg:postcode":"28690",
    "sg:province":"Madrid",
    "sg:website":"www.atys.es",
    "wof:name":"Atys Productos Informaticos S.l.",
    "wof:placetype":"venue"
},
  "geometry": {"coordinates":[-3.9747416973,40.4257926941],"type":"Point"}
}