{
  "type": "Feature",
  "properties": {
    "addr:full":"Avda Madrid (de), 31 Granada Granada 18012",
    "addr:housenumber":"31",
    "addr:postcode":"18012",
    "addr:street":"Avda Madrid De",
    "iso:country":"ES",
    "sg:address":"Avda Madrid (de), 31",
    "sg:city":"Granada",
    "sg:orig_category":"Agencias Y Agentes Comerciales, Representantes",
    "sg:phone":"+34 958 16 19 90",
    "sg:postcode":"18012",
    "sg:province":"Granada",
    "wof:name":"Ayuso Morales Angel Miguel",
    "wof:placetype":"venue"
},
  "geometry": {"coordinates":[-3.6073789597,37.1907310486],"type":"Point"}
}