{
  "type": "Feature",
  "properties": {
    "iso:country":"ES",
    "sg:address":"Carrer de Mallorca, 30",
    "sg:city":"Mas Rampinyo",
    "sg:orig_category":"Electricidad (montaje, Ensamblaje De Componentes)",
    "sg:phone":"+34 935 64 37 24",
    "sg:postcode":"08110",
    "sg:province":"Barcelona",
    "wof:name":"Sariol Grau Manuel",
    "wof:placetype":"venue"
},
  "geometry": {"coordinates":[2.1859691143,41.4872894287],"type":"Point"}
}