{
  "type": "Feature",
  "properties": {
    "addr:full":"Pintor Vicente Abreu, 17 Vitoria-gasteiz \u00c1lava 01008",
    "addr:housenumber":"17",
    "addr:postcode":"01008",
    "addr:street":"Pintor Vicente Abreu",
    "iso:country":"ES",
    "sg:address":"Pintor Vicente Abreu, 17",
    "sg:city":"Vitoria-gasteiz",
    "sg:orig_category":"Abogados",
    "sg:phone":"+34 945 22 04 42",
    "sg:postcode":"01008",
    "sg:province":"\u00c1lava",
    "wof:name":"Ortiz Martin Julian",
    "wof:placetype":"venue"
},
  "geometry": {"coordinates":[-2.6844789982,42.848651886],"type":"Point"}
}