{
  "type": "Feature",
  "properties": {
    "addr:full":"Calle de Ortega Y Gasset, 7 Sevilla Sevilla 41006",
    "addr:housenumber":"7",
    "addr:postcode":"41006",
    "addr:street":"Calle De Ortega Y Gasset",
    "iso:country":"ES",
    "sg:address":"Calle de Ortega Y Gasset, 7",
    "sg:city":"Sevilla",
    "sg:orig_category":"Frutas Y Legumbres Frescas (al Por Mayor)",
    "sg:phone":"+34 954 63 77 86",
    "sg:postcode":"41006",
    "sg:province":"Sevilla",
    "wof:name":"Rocha Solis Manuel",
    "wof:placetype":"venue"
},
  "geometry": {"coordinates":[-5.9482169151,37.3726654053],"type":"Point"}
}