{
  "type": "Feature",
  "properties": {
    "addr:full":"Calle de Miguel De Cervantes, 14 Rua De Valdeorras Ourense 32350",
    "addr:housenumber":"14",
    "addr:postcode":"32350",
    "addr:street":"Calle De Miguel De Cervantes;Rua De",
    "iso:country":"ES",
    "sg:address":"Calle de Miguel De Cervantes, 14",
    "sg:city":"Rua De Valdeorras",
    "sg:orig_category":"Librer\u00cdas",
    "sg:phone":"+34 988 31 08 34",
    "sg:postcode":"32350",
    "sg:province":"Ourense",
    "wof:name":"Alvarez Carballo Jose Luis",
    "wof:placetype":"venue"
},
  "geometry": {"coordinates":[-7.1150140762,42.3934898376],"type":"Point"}
}