{
  "type": "Feature",
  "properties": {
    "addr:full":"Avda Reyes Catolicos De Los, 31 Fraga Huesca 22520",
    "addr:housenumber":"31",
    "addr:postcode":"22520",
    "addr:street":"Avda Reyes Catolicos De Los",
    "iso:country":"ES",
    "sg:address":"Avda Reyes Catolicos De Los, 31",
    "sg:city":"Fraga",
    "sg:orig_category":"Comercio, Reparaci\u00d3n De Motocicletas, Bicicletas Y Piezas Sueltas",
    "sg:phone":"+34 974 47 03 43",
    "sg:postcode":"22520",
    "sg:province":"Huesca",
    "wof:name":"Gari E Hijos S.r.c.",
    "wof:placetype":"venue"
},
  "geometry": {"coordinates":[0.3472279906,41.5219535828],"type":"Point"}
}