{
  "type": "Feature",
  "properties": {
    "addr:full":"Pl. Villamonte, 4 Algorta Vizcaya 48991",
    "addr:housenumber":"4",
    "addr:postcode":"48991",
    "addr:street":"Pl. Villamonte",
    "iso:country":"ES",
    "sg:address":"Pl. Villamonte, 4",
    "sg:city":"Algorta",
    "sg:orig_category":"Alquiler De V\u00cddeo",
    "sg:phone":"+34 944 30 51 31",
    "sg:postcode":"48991",
    "sg:province":"Vizcaya",
    "wof:name":"Palacio Portillo Maria Jesus",
    "wof:placetype":"venue"
},
  "geometry": {"coordinates":[-3.0073800087,43.3505935669],"type":"Point"}
}