{
  "type": "Feature",
  "properties": {
    "addr:full":"Carrer de Camp Arriassa, 53 Barcelona Barcelona 08020",
    "addr:housenumber":"53",
    "addr:postcode":"08020",
    "addr:street":"Carrer De Camp Arriassa",
    "iso:country":"ES",
    "sg:address":"Carrer de Camp Arriassa, 53",
    "sg:city":"Barcelona",
    "sg:orig_category":"Librer\u00cdas",
    "sg:phone":"+34 933 13 19 81",
    "sg:postcode":"08020",
    "sg:province":"Barcelona",
    "wof:name":"Cubillo Fontanet Maria Teresa",
    "wof:placetype":"venue"
},
  "geometry": {"coordinates":[2.2050890923,41.4227409363],"type":"Point"}
}