{
  "type": "Feature",
  "properties": {
    "iso:country":"ES",
    "sg:address":"C/ Estrella, 15",
    "sg:city":"Inca",
    "sg:orig_category":"Bisuter\u00cda, Joyer\u00cda, Relojer\u00cda (al Por Menor)",
    "sg:phone":"+34 971 50 14 60",
    "sg:postcode":"07300",
    "sg:province":"Islas Baleares",
    "sg:website":"www.ordi\u00f1anajoier.com",
    "wof:name":"Ordilla\u00f1a Llobera Jose",
    "wof:placetype":"venue"
},
  "geometry": {"coordinates":[2.9101839066,39.7206306458],"type":"Point"}
}