{
  "type": "Feature",
  "properties": {
    "iso:country":"ES",
    "sg:address":"Avda Criptana, 32",
    "sg:city":"Alcazar S. Juan",
    "sg:orig_category":"Ense\u00d1anza, Formaci\u00d3n Profesional: Aprendizaje",
    "sg:phone":"+34 926 55 10 41",
    "sg:postcode":"13600",
    "sg:province":"Ciudad Real",
    "wof:name":"Ayuntamiento De Alcazar De San Juan",
    "wof:placetype":"venue"
},
  "geometry": {"coordinates":[-3.2029561996,39.393699646],"type":"Point"}
}