{
  "type": "Feature",
  "properties": {
    "addr:full":"Calle de Real, 8 Coru\u00d1a La Coru\u00f1a 15003",
    "addr:housenumber":"8",
    "addr:postcode":"15003",
    "addr:street":"Calle De Real;La Corun\u0303A",
    "iso:country":"ES",
    "sg:address":"Calle de Real, 8",
    "sg:city":"Coru\u00d1a",
    "sg:orig_category":"Ropa Para Se\u00d1oras Y Caballeros (al Por Menor)",
    "sg:phone":"+34 981 20 99 64",
    "sg:postcode":"15003",
    "sg:province":"La Coru\u00f1a",
    "sg:website":"www.pullbear.com",
    "wof:name":"Pull & Bear Espa\u00f1a S.a.",
    "wof:placetype":"venue"
},
  "geometry": {"coordinates":[-8.4038801193,43.369720459],"type":"Point"}
}