{
  "type": "Feature",
  "properties": {
    "iso:country":"ES",
    "sg:address":"Carr Trencall, 32",
    "sg:city":"Puig",
    "sg:orig_category":"Empresas De Carpinter\u00cda De Madera",
    "sg:phone":"+34 961 47 10 09",
    "sg:postcode":"46540",
    "sg:province":"Valencia",
    "wof:name":"Jose Navarro Blanco S.l.",
    "wof:placetype":"venue"
},
  "geometry": {"coordinates":[-0.3043780029,39.5881080627],"type":"Point"}
}