{
  "type": "Feature",
  "properties": {
    "addr:full":"Calle de Jeronima Llorente, 76 Madrid Madrid 28039",
    "addr:housenumber":"76",
    "addr:postcode":"madrid;28039",
    "addr:street":"Calle De Jeronima Llorente",
    "iso:country":"ES",
    "sg:address":"Calle de Jeronima Llorente, 76",
    "sg:city":"Madrid",
    "sg:orig_category":"Molduras, Junquillos, Listones Y Molduras Perforadas",
    "sg:phone":"+34 914 59 10 33",
    "sg:postcode":"28039",
    "sg:province":"Madrid",
    "wof:name":"Rocha Rodriguez S.c.",
    "wof:placetype":"venue"
},
  "geometry": {"coordinates":[-3.7093191147,40.4523696899],"type":"Point"}
}