{
  "type": "Feature",
  "properties": {
    "addr:full":"Calle de Duque De Mandas, 41 Valencia Valencia 46019",
    "addr:housenumber":"41",
    "addr:postcode":"46019",
    "addr:street":"Calle De Duque De Mandas",
    "iso:country":"ES",
    "sg:address":"Calle de Duque De Mandas, 41",
    "sg:city":"Valencia",
    "sg:orig_category":"Cajas De Ahorro",
    "sg:phone":"+34 963 65 21 96",
    "sg:postcode":"46019",
    "sg:province":"Valencia",
    "sg:website":"www.bancaja.es",
    "wof:name":"Caja De Ahorros De Valencia Castellon Y Alicante",
    "wof:placetype":"venue"
},
  "geometry": {"coordinates":[-0.3672519922,39.492351532],"type":"Point"}
}