{
  "type": "Feature",
  "properties": {
    "addr:full":"Avda Parque (del), 8 Molina Segura Murcia 30500",
    "addr:housenumber":"8",
    "addr:postcode":"30500",
    "addr:street":"Avda Parque Del",
    "iso:country":"ES",
    "sg:address":"Avda Parque (del), 8",
    "sg:city":"Molina Segura",
    "sg:orig_category":"Bisuter\u00cda, Joyer\u00cda, Relojer\u00cda (al Por Menor)",
    "sg:phone":"+34 968 64 00 74",
    "sg:postcode":"30500",
    "sg:province":"Murcia",
    "wof:name":"Joyeria Jose Luis S. L.",
    "wof:placetype":"venue"
},
  "geometry": {"coordinates":[-1.2119740248,38.0535736084],"type":"Point"}
}