{
  "type": "Feature",
  "properties": {
    "addr:full":"Calle de Rubio Vergara (de Los), 5 Calatayud Zaragoza 50300",
    "addr:postcode":"50300",
    "addr:street":"Calle De Rubio Vergara De Los",
    "iso:country":"ES",
    "sg:address":"Calle de Rubio Vergara (de Los), 5",
    "sg:city":"Calatayud",
    "sg:orig_category":"Artes Gr\u00c1ficas, Artes Pl\u00c1sticas (curso)",
    "sg:phone":"+34 976 88 48 14",
    "sg:postcode":"50300",
    "sg:province":"Zaragoza",
    "wof:name":"Navarro Arias Luis Fernando",
    "wof:placetype":"venue"
},
  "geometry": {"coordinates":[-1.6414469481,41.3498916626],"type":"Point"}
}