{
  "type": "Feature",
  "properties": {
    "addr:full":"Calle de Coso Alto, 67 Huesca Huesca 22003",
    "addr:housenumber":"67",
    "addr:postcode":"22003",
    "addr:street":"Calle De Coso Alto",
    "iso:country":"ES",
    "sg:address":"Calle de Coso Alto, 67",
    "sg:city":"Huesca",
    "sg:orig_category":"Fabricaci\u00d3n, Venta De Cuadros, Accesorios Para Enmarcar",
    "sg:phone":"+34 974 22 56 40",
    "sg:postcode":"22003",
    "sg:province":"Huesca",
    "wof:name":"Coiduras Costa Montserrat",
    "wof:placetype":"venue"
},
  "geometry": {"coordinates":[-0.4113286138,42.1405525208],"type":"Point"}
}