{
  "type": "Feature",
  "properties": {
    "addr:full":"Calle de Libro (del), 3 Casasimarro Cuenca 16239",
    "addr:postcode":"16239",
    "addr:street":"Calle De;Del",
    "iso:country":"ES",
    "sg:address":"Calle de Libro (del), 3",
    "sg:city":"Casasimarro",
    "sg:orig_category":"Empresas De Carpinter\u00cda Met\u00c1lica",
    "sg:phone":"+34 967 48 71 68",
    "sg:postcode":"16239",
    "sg:province":"Cuenca",
    "wof:name":"Alujavi S.l.",
    "wof:placetype":"venue"
},
  "geometry": {"coordinates":[-2.0373222828,39.3874816895],"type":"Point"}
}