{
  "type": "Feature",
  "properties": {
    "addr:full":"Carr Ntra Sra Montserrat, 37 Almacelles Lleida 25100",
    "addr:housenumber":"37",
    "addr:postcode":"25100",
    "addr:street":"Carr Ntra Sra Montserrat",
    "iso:country":"ES",
    "sg:address":"Carr Ntra Sra Montserrat, 37",
    "sg:city":"Almacelles",
    "sg:orig_category":"Chapister\u00cda",
    "sg:phone":"+34 973 74 18 45",
    "sg:postcode":"25100",
    "sg:province":"Lleida",
    "wof:name":"Planchisteria Rapor S.l.",
    "wof:placetype":"venue"
},
  "geometry": {"coordinates":[0.4432210028,41.7280578613],"type":"Point"}
}