{
  "type": "Feature",
  "properties": {
    "addr:full":"Cno. Cementerio, S/n Villafranca Ebro Zaragoza 50174",
    "addr:housenumber":"s / n",
    "addr:postcode":"50174",
    "addr:street":"Cno. Cementerio",
    "iso:country":"ES",
    "sg:address":"Cno. Cementerio, S/n",
    "sg:city":"Villafranca Ebro",
    "sg:orig_category":"Motocicletas (agentes, Concesionarios)",
    "sg:phone":"+34 976 16 92 20",
    "sg:postcode":"50174",
    "sg:province":"Zaragoza",
    "wof:name":"Moto Mundi S.l.",
    "wof:placetype":"venue"
},
  "geometry": {"coordinates":[-0.6457740068,41.5761795044],"type":"Point"}
}