{
  "type": "Feature",
  "properties": {
    "addr:full":"Ctra Gral. Norte, 279 Los Naranjeros Santa Cruz De Tenerife 38340",
    "addr:housenumber":"279",
    "addr:postcode":"38340",
    "addr:street":"Ctra Gral. Norte;Naranjeros",
    "iso:country":"ES",
    "sg:address":"Ctra Gral. Norte, 279",
    "sg:city":"Los Naranjeros",
    "sg:orig_category":"Muebles Y Accesorios Para Cocinas Y Cuartos De Ba\u00d1o (al Por Menor)",
    "sg:phone":"+34 922 57 20 19",
    "sg:postcode":"38340",
    "sg:province":"Santa Cruz De Tenerife",
    "wof:name":"Almacenes Miguel Perez E Hijos S.l.",
    "wof:placetype":"venue"
},
  "geometry": {"coordinates":[-16.3810482025,28.4885368347],"type":"Point"}
}