{
  "type": "Feature",
  "properties": {
    "addr:full":"Calle de General Prim, 32 Cieza Murcia 30530",
    "addr:housenumber":"32",
    "addr:postcode":"30530",
    "addr:street":"Calle De General Prim",
    "iso:country":"ES",
    "sg:address":"Calle de General Prim, 32",
    "sg:city":"Cieza",
    "sg:orig_category":"M\u00c9dicos: Oftalmolog\u00cda",
    "sg:phone":"+34 968 76 72 26",
    "sg:postcode":"30530",
    "sg:province":"Murcia",
    "wof:name":"Lucas Elio Gloria",
    "wof:placetype":"venue"
},
  "geometry": {"coordinates":[-1.4211709499,38.2392044067],"type":"Point"}
}