{
  "type": "Feature",
  "properties": {
    "addr:full":"Carretera General(almu\u00f1a), S/n Luarca Asturias 33700",
    "addr:housenumber":"s / n",
    "addr:postcode":"33700",
    "addr:street":"Carretera General Almun\u0303A",
    "iso:country":"ES",
    "sg:address":"Carretera General(almu\u00f1a), S/n",
    "sg:city":"Luarca",
    "sg:orig_category":"Panader\u00cdas, Pasteler\u00cdas, Boller\u00cda Industriale (fabricaci\u00d3n, Al Por Mayor)",
    "sg:phone":"+34 985 64 20 81",
    "sg:postcode":"33700",
    "sg:province":"Asturias",
    "wof:name":"Panrico S.l.u.",
    "wof:placetype":"venue"
},
  "geometry": {"coordinates":[-6.5366139412,43.5418891907],"type":"Point"}
}