{
  "type": "Feature",
  "properties": {
    "iso:country":"ES",
    "sg:address":"Calle de Cortes (las), 11",
    "sg:city":"S. Fernando",
    "sg:orig_category":"Ense\u00d1anza: Costura",
    "sg:phone":"+34 956 59 49 73",
    "sg:postcode":"11100",
    "sg:province":"C\u00e1diz",
    "wof:name":"Bueno Camacho Antonia",
    "wof:placetype":"venue"
},
  "geometry": {"coordinates":[-6.1977338791,36.4654693604],"type":"Point"}
}