{
  "type": "Feature",
  "properties": {
    "addr:full":"Calle de Zacarias De La Hera, S/n Almendralejo Badajoz 06200",
    "addr:housenumber":"s / n",
    "addr:postcode":"06200",
    "addr:street":"Calle De Zacarias De La Hera",
    "iso:country":"ES",
    "sg:address":"Calle de Zacarias De La Hera, S/n",
    "sg:city":"Almendralejo",
    "sg:classifiers":[
        {
            "category":"Communications",
            "type":"Services"
        }
    ],
    "sg:phone":"+34 924 66 17 12",
    "sg:postcode":"06200",
    "sg:province":"Badajoz",
    "sg:tags":[
        "televisiones",
        "y",
        "radio"
    ],
    "wof:name":"Radio Almendralejo S.l.",
    "wof:placetype":"venue"
},
  "geometry": {"coordinates":[-6.4061589241,38.6896781921],"type":"Point"}
}