{
  "type": "Feature",
  "properties": {
    "addr:full":"Calle de Ba\u00d1os, 9 Sevilla Sevilla 41002",
    "addr:housenumber":"9",
    "addr:postcode":"41002",
    "addr:street":"Calle De Ban\u0303Os",
    "iso:country":"ES",
    "sg:address":"Calle de Ba\u00d1os, 9",
    "sg:city":"Sevilla",
    "sg:orig_category":"Audiovisuales (producci\u00d3n, Edici\u00d3n, Realizaci\u00d3n)",
    "sg:phone":"+34 954 21 86 16",
    "sg:postcode":"41002",
    "sg:province":"Sevilla",
    "sg:website":"www.prorvg.com",
    "wof:name":"Rvg S.l.",
    "wof:placetype":"venue"
},
  "geometry": {"coordinates":[-5.9978280067,37.3951721191],"type":"Point"}
}