{
  "type": "Feature",
  "properties": {
    "addr:full":"Barr Pe\u00d1acastillo Campon, 45 Pe\u00d1acastillo Cantabria 39011",
    "addr:housenumber":"45",
    "addr:postcode":"39011",
    "addr:street":"Campon",
    "iso:country":"ES",
    "sg:address":"Barr Pe\u00d1acastillo Campon, 45",
    "sg:city":"Pe\u00d1acastillo",
    "sg:orig_category":"Puertas Y Portales",
    "sg:phone":"+34 942 32 36 60",
    "sg:postcode":"39011",
    "sg:province":"Cantabria",
    "sg:website":"www.msimon@ceoecant.es",
    "wof:name":"Puertas Cantovi S.l.",
    "wof:placetype":"venue"
},
  "geometry": {"coordinates":[-3.8739891052,43.4491386414],"type":"Point"}
}