{
  "type": "Feature",
  "properties": {
    "iso:country":"ES",
    "sg:address":"Rbla Catalunya, 25",
    "sg:city":"Olesa Montserrat",
    "sg:orig_category":"Importaci\u00d3n",
    "sg:phone":"+34 937 78 64 47",
    "sg:postcode":"08640",
    "sg:province":"Barcelona",
    "sg:website":"www.pixel.olesa.com",
    "wof:name":"Pixels Corporate S.l.",
    "wof:placetype":"venue"
},
  "geometry": {"coordinates":[1.8945000172,41.5405082703],"type":"Point"}
}