{
  "type": "Feature",
  "properties": {
    "iso:country":"ES",
    "sg:address":"Calle de Colonia Santa Isabel, S/n",
    "sg:city":"San Vicente Del Raspeig-sant Vicent Del Raspeig",
    "sg:orig_category":"Iglesia Cat\u00d3lica",
    "sg:phone":"+34 965 66 03 69",
    "sg:postcode":"03690",
    "sg:province":"Alicante",
    "wof:name":"Parroquia De Santa Isabel",
    "wof:placetype":"venue"
},
  "geometry": {"coordinates":[-0.5026882291,38.3817825317],"type":"Point"}
}