{
  "type": "Feature",
  "properties": {
    "iso:country":"ES",
    "sg:address":"Calle de Carlos I, 5",
    "sg:city":"Ponferrada",
    "sg:orig_category":"Plomeros",
    "sg:phone":"+34 987 42 77 83",
    "sg:postcode":"24400",
    "sg:province":"Le\u00f3n",
    "wof:name":"Garcia Fernandez Baltasar",
    "wof:placetype":"venue"
},
  "geometry": {"coordinates":[-6.5954012871,42.5457572937],"type":"Point"}
}