{
  "type": "Feature",
  "properties": {
    "iso:country":"ES",
    "sg:address":"Calle de Hombre De Palo, 17",
    "sg:city":"Toledo",
    "sg:orig_category":"Bisuter\u00cda, Joyer\u00cda, Relojer\u00cda (al Por Menor)",
    "sg:phone":"+34 925 21 67 99",
    "sg:postcode":"45001",
    "sg:province":"Toledo",
    "sg:website":"www.tous.es",
    "wof:name":"Joyeria Tous S.a.",
    "wof:placetype":"venue"
},
  "geometry": {"coordinates":[-4.0235848427,39.8582458496],"type":"Point"}
}