{
  "type": "Feature",
  "properties": {
    "iso:country":"ES",
    "sg:address":"Avda Carretera De Nules, S/n",
    "sg:city":"Alquerias Valencia",
    "sg:orig_category":"Construcciones Navales Y Fluviales",
    "sg:phone":"+34 964 51 47 44",
    "sg:postcode":"12530",
    "sg:province":"Castell\u00f3n",
    "wof:name":"Longitud Cero Composites, S.l.",
    "wof:placetype":"venue"
},
  "geometry": {"coordinates":[-0.0852660015,39.8894195557],"type":"Point"}
}