{
  "type": "Feature",
  "properties": {
    "iso:country":"ES",
    "sg:address":"Avenida San Jeronimo, 40",
    "sg:city":"Bornos",
    "sg:orig_category":"M\u00c9dicos: Estomatolog\u00cda",
    "sg:phone":"+34 956 71 27 01",
    "sg:postcode":"11640",
    "sg:province":"C\u00e1diz",
    "wof:name":"Ory Louro Maria Gloria De",
    "wof:placetype":"venue"
},
  "geometry": {"coordinates":[-5.7430238724,36.817440033],"type":"Point"}
}