{
  "type": "Feature",
  "properties": {
    "addr:full":"Calle de Santa Margarita, S/n Osso Cinca Huesca 22532",
    "addr:housenumber":"s / n",
    "addr:postcode":"22532",
    "addr:street":"Calle De Santa Margarita",
    "iso:country":"ES",
    "sg:address":"Calle de Santa Margarita, S/n",
    "sg:city":"Osso Cinca",
    "sg:orig_category":"Confecci\u00d3n (fabricaci\u00d3n, Al Por Mayor)",
    "sg:phone":"+34 974 45 60 88",
    "sg:postcode":"22532",
    "sg:province":"Huesca",
    "wof:name":"Manufacturas Textiles Rosa Sociedad Cooperativa",
    "wof:placetype":"venue"
},
  "geometry": {"coordinates":[0.1921519935,41.6650886536],"type":"Point"}
}