{
  "type": "Feature",
  "properties": {
    "addr:full":"Carrer de Proven\u00c7a, 337 Barcelona Barcelona 08037",
    "addr:housenumber":"337",
    "addr:postcode":"08037",
    "addr:street":"Carrer De Provenc\u0327A",
    "iso:country":"ES",
    "sg:address":"Carrer de Proven\u00c7a, 337",
    "sg:city":"Barcelona",
    "sg:orig_category":"Centros P\u00dablicos De Formaci\u00d3n Profesional Y T\u00c9cnica",
    "sg:phone":"+34 934 59 40 30",
    "sg:postcode":"08037",
    "sg:province":"Barcelona",
    "wof:name":"Colegio Oficial De Protesicos Dentales De Catalu\u00d1a",
    "wof:placetype":"venue"
},
  "geometry": {"coordinates":[2.167953968,41.3998069763],"type":"Point"}
}