{
  "type": "Feature",
  "properties": {
    "addr:full":"Avda Basagoiti, 73 Getxo Vizcaya 48990",
    "addr:housenumber":"73",
    "addr:postcode":"48990",
    "addr:street":"Avda Basagoiti",
    "iso:country":"ES",
    "sg:address":"Avda Basagoiti, 73",
    "sg:city":"Getxo",
    "sg:orig_category":"Alquiler De V\u00cddeo",
    "sg:phone":"+34 944 60 85 53",
    "sg:postcode":"48990",
    "sg:province":"Vizcaya",
    "wof:name":"Audiovisuales Izarra",
    "wof:placetype":"venue"
},
  "geometry": {"coordinates":[-3.0125768185,43.3512916565],"type":"Point"}
}