{
  "type": "Feature",
  "properties": {
    "addr:full":"Calle de Diego De Leon, 29 Madrid Madrid 28006",
    "addr:housenumber":"29",
    "addr:postcode":"madrid;28006",
    "addr:street":"Calle De Diego De Leon",
    "iso:country":"ES",
    "sg:address":"Calle de Diego De Leon, 29",
    "sg:city":"Madrid",
    "sg:orig_category":"Zapatos (al Por Menor)",
    "sg:phone":"+34 915 62 02 32",
    "sg:postcode":"28006",
    "sg:province":"Madrid",
    "wof:name":"Perez Sanz Joaquina",
    "wof:placetype":"venue"
},
  "geometry": {"coordinates":[-3.6813650131,40.4348640442],"type":"Point"}
}