{
  "type": "Feature",
  "properties": {
    "iso:country":"ES",
    "sg:address":"Psaj A Camino Vallado, Km. 0001,0",
    "sg:city":"San Cristobal De La Laguna",
    "sg:orig_category":"Bordado, Marcado A Medida",
    "sg:phone":"+34 922 26 10 79",
    "sg:postcode":"38206",
    "sg:province":"Santa Cruz De Tenerife",
    "wof:name":"Distribuciones Alman C.b.",
    "wof:placetype":"venue"
},
  "geometry": {"coordinates":[-16.3255290985,28.4841270447],"type":"Point"}
}