{
  "type": "Feature",
  "properties": {
    "iso:country":"ES",
    "sg:address":"Carrer de Moli, 15",
    "sg:city":"Argentona",
    "sg:orig_category":"Molduras, Junquillos, Listones Y Molduras Perforadas",
    "sg:phone":"+34 937 56 05 52",
    "sg:postcode":"08310",
    "sg:province":"Barcelona",
    "wof:name":"Gonzalez Bedia Eduardo",
    "wof:placetype":"venue"
},
  "geometry": {"coordinates":[2.4053599834,41.5551681519],"type":"Point"}
}