{
  "type": "Feature",
  "properties": {
    "addr:full":"Avda Virgen De Fatima (de), 21 Cordoba C\u00f3rdoba 14014",
    "addr:postcode":"14014",
    "addr:street":"Avda Virgen;Co\u0301Rdoba",
    "iso:country":"ES",
    "sg:address":"Avda Virgen De Fatima (de), 21",
    "sg:city":"Cordoba",
    "sg:orig_category":"Bazares, Art\u00cdculos De Limpieza Y De Cocina (al Por Menor)",
    "sg:phone":"+34 957 26 07 42",
    "sg:postcode":"14014",
    "sg:province":"C\u00f3rdoba",
    "wof:name":"Bazares Eva De Cordoba S.l.",
    "wof:placetype":"venue"
},
  "geometry": {"coordinates":[-4.7566318512,37.8980674744],"type":"Point"}
}