{
  "type": "Feature",
  "properties": {
    "addr:full":"Plaz Clemente Fuertes, 5 Bronchales Teruel 44367",
    "addr:housenumber":"5",
    "addr:postcode":"44367",
    "addr:street":"Fuertes",
    "iso:country":"ES",
    "sg:address":"Plaz Clemente Fuertes, 5",
    "sg:city":"Bronchales",
    "sg:orig_category":"Supermercados Y Hipermercados",
    "sg:phone":"+34 978 70 11 07",
    "sg:postcode":"44367",
    "sg:province":"Teruel",
    "wof:name":"Rijomavi S.l.",
    "wof:placetype":"venue"
},
  "geometry": {"coordinates":[-1.5887060165,40.5089950562],"type":"Point"}
}