{
  "type": "Feature",
  "properties": {
    "addr:full":"Carr Vicario Ricardo Belenguer, 2 Alboraya Valencia 46120",
    "addr:housenumber":"2",
    "addr:postcode":"46120",
    "addr:street":"Carr Vicario Ricardo Belenguer",
    "iso:country":"ES",
    "sg:address":"Carr Vicario Ricardo Belenguer, 2",
    "sg:city":"Alboraya",
    "sg:orig_category":"Fisioterapia",
    "sg:phone":"+34 961 86 25 99",
    "sg:postcode":"46120",
    "sg:province":"Valencia",
    "wof:name":"Beltran Alos Luis",
    "wof:placetype":"venue"
},
  "geometry": {"coordinates":[-0.3507989943,39.4980583191],"type":"Point"}
}