{
  "type": "Feature",
  "properties": {
    "addr:full":"Calle de San Fernando, 16 Santander Cantabria 39010",
    "addr:housenumber":"16",
    "addr:postcode":"39010",
    "addr:street":"Calle De San Fernando",
    "iso:country":"ES",
    "sg:address":"Calle de San Fernando, 16",
    "sg:city":"Santander",
    "sg:orig_category":"Empresas De Limpieza",
    "sg:phone":"+34 942 37 17 77",
    "sg:postcode":"39010",
    "sg:province":"Cantabria",
    "wof:name":"Garnica S. A.",
    "wof:placetype":"venue"
},
  "geometry": {"coordinates":[-3.8195800781,43.460521698],"type":"Point"}
}