{
  "type": "Feature",
  "properties": {
    "iso:country":"ES",
    "sg:address":"Avda Sierra De Gata, 19",
    "sg:city":"Coria",
    "sg:orig_category":"Ropa Para Ni\u00d1os (al Por Menor)",
    "sg:phone":"+34 927 50 43 11",
    "sg:postcode":"10800",
    "sg:province":"C\u00e1ceres",
    "wof:name":"Plasencia Garcia Leticia",
    "wof:placetype":"venue"
},
  "geometry": {"coordinates":[-6.5369467735,39.9854202271],"type":"Point"}
}