{
  "type": "Feature",
  "properties": {
    "addr:full":"Pseo. Constitucion, 41 Beas Segura Ja\u00e9n 23280",
    "addr:housenumber":"41",
    "addr:postcode":"23280",
    "addr:street":"Constitucion",
    "iso:country":"ES",
    "sg:address":"Pseo. Constitucion, 41",
    "sg:city":"Beas Segura",
    "sg:orig_category":"Asesor\u00cda Sobre Comunicaci\u00d3n De Empresas",
    "sg:phone":"+34 953 42 42 80",
    "sg:postcode":"23280",
    "sg:province":"Ja\u00e9n",
    "wof:name":"Perez Sanchez Jose",
    "wof:placetype":"venue"
},
  "geometry": {"coordinates":[-2.8957929611,38.25440979],"type":"Point"}
}