{
  "type": "Feature",
  "properties": {
    "iso:country":"ES",
    "sg:address":"Carrer de Jaume I (de), 29",
    "sg:city":"Tarragona",
    "sg:orig_category":"Contenedores (mercanc\u00cdas)",
    "sg:phone":"+34 977 22 10 60",
    "sg:postcode":"43005",
    "sg:province":"Tarragona",
    "wof:name":"Federacion Empresarial De Auto-transportes",
    "wof:placetype":"venue"
},
  "geometry": {"coordinates":[1.2442979813,41.1138191223],"type":"Point"}
}