{
  "type": "Feature",
  "properties": {
    "iso:country":"ES",
    "sg:address":"Rond Ponent, 160",
    "sg:city":"Sabadell",
    "sg:orig_category":"Televisi\u00d3n, V\u00cddeo: Aparatos Y Accesorios (venta)",
    "sg:phone":"+34 937 27 50 95",
    "sg:postcode":"08201",
    "sg:province":"Barcelona",
    "wof:name":"Hi-fi Sabadell S.l.",
    "wof:placetype":"venue"
},
  "geometry": {"coordinates":[2.0988938808,41.5487251282],"type":"Point"}
}