{
  "type": "Feature",
  "properties": {
    "iso:country":"ES",
    "sg:address":"Avda Libertad De La, 7",
    "sg:city":"Donostia-san Sebastian",
    "sg:orig_category":"Empresarios",
    "sg:phone":"+34 943 42 69 04",
    "sg:postcode":"20004",
    "sg:province":"Guip\u00f9zcoa",
    "wof:name":"De Zabala Sarria Ignacio",
    "wof:placetype":"venue"
},
  "geometry": {"coordinates":[-1.9802390337,43.3201026917],"type":"Point"}
}