{
  "type": "Feature",
  "properties": {
    "addr:full":"Calle de Palencia, 31 Madrid Madrid 28020",
    "addr:housenumber":"31",
    "addr:postcode":"madrid;28020",
    "addr:street":"Calle De Palencia",
    "iso:country":"ES",
    "sg:address":"Calle de Palencia, 31",
    "sg:city":"Madrid",
    "sg:orig_category":"Inform\u00c1tica, Ofim\u00c1tica (estudios, Asesor\u00cda, Ingenier\u00cda, Formaci\u00d3n)",
    "sg:phone":"+34 914 56 04 55",
    "sg:postcode":"28020",
    "sg:province":"Madrid",
    "wof:name":"Eureka Soluciones Informaticas S.l.",
    "wof:placetype":"venue"
},
  "geometry": {"coordinates":[-3.7011239529,40.4498558044],"type":"Point"}
}