{
  "type": "Feature",
  "properties": {
    "iso:country":"ES",
    "sg:address":"Cmno Pago Barranco, S/n",
    "sg:city":"Archena",
    "sg:orig_category":"Maquinaria Para Industrias Diversas",
    "sg:phone":"+34 968 67 07 18",
    "sg:postcode":"30600",
    "sg:province":"Murcia",
    "wof:name":"Industrias Juan Jose Rojo S.l.",
    "wof:placetype":"venue"
},
  "geometry": {"coordinates":[-1.2977989912,38.1132583618],"type":"Point"}
}