{
  "type": "Feature",
  "properties": {
    "addr:full":"Estd Maside (de), 15 Cea Ourense 32130",
    "addr:postcode":"32130",
    "iso:country":"ES",
    "sg:address":"Estd Maside (de), 15",
    "sg:city":"Cea",
    "sg:orig_category":"Negocio De Materiales De Construcci\u00d3n",
    "sg:phone":"+34 988 28 20 58",
    "sg:postcode":"32130",
    "sg:province":"Ourense",
    "wof:name":"Transportes A F Mosquera S.l.",
    "wof:placetype":"venue"
},
  "geometry": {"coordinates":[-7.9874720573,42.4763221741],"type":"Point"}
}