{
  "type": "Feature",
  "properties": {
    "addr:full":"Calle de Luis Bejar, 16 Pozuelo De Alarcon Madrid 28223",
    "addr:housenumber":"16",
    "addr:postcode":"28223",
    "addr:street":"Calle De Luis Bejar",
    "iso:country":"ES",
    "sg:address":"Calle de Luis Bejar, 16",
    "sg:city":"Pozuelo De Alarcon",
    "sg:orig_category":"Promotores Constructores",
    "sg:phone":"+34 913 52 86 30",
    "sg:postcode":"28223",
    "sg:province":"Madrid",
    "wof:name":"Torrecerredo Promociones Sl",
    "wof:placetype":"venue"
},
  "geometry": {"coordinates":[-3.8153877258,40.4361305237],"type":"Point"}
}