{
  "type": "Feature",
  "properties": {
    "addr:full":"Calle de Ba\u00d1uelos, 34 Estepa Sevilla 41560",
    "addr:housenumber":"34",
    "addr:postcode":"41560",
    "addr:street":"Calle De Ban\u0303Uelos;Sevilla",
    "iso:country":"ES",
    "sg:address":"Calle de Ba\u00d1uelos, 34",
    "sg:city":"Estepa",
    "sg:orig_category":"Electricidad: Instaladores",
    "sg:phone":"+34 954 82 04 97",
    "sg:postcode":"41560",
    "sg:province":"Sevilla",
    "wof:name":"Valderrama Jimenez Rafael",
    "wof:placetype":"venue"
},
  "geometry": {"coordinates":[-4.8831410408,37.2934074402],"type":"Point"}
}