{
  "type": "Feature",
  "properties": {
    "iso:country":"ES",
    "sg:address":"Rua Carud, 1",
    "sg:city":"Monforte De Lemos",
    "sg:orig_category":"Molduras, Junquillos, Listones Y Molduras Perforadas",
    "sg:phone":"+34 982 40 20 68",
    "sg:postcode":"27400",
    "sg:province":"Lugo",
    "wof:name":"Recreativos Dandy S.l.",
    "wof:placetype":"venue"
},
  "geometry": {"coordinates":[-7.51831007,42.5165100098],"type":"Point"}
}