{
  "type": "Feature",
  "properties": {
    "addr:full":"Calle de Pe\u00d1alara (de), 8 Pozuelo De Alarcon Madrid 28224",
    "addr:housenumber":"8",
    "addr:postcode":"28224",
    "addr:street":"Calle De Pen\u0303Alara De",
    "iso:country":"ES",
    "sg:address":"Calle de Pe\u00d1alara (de), 8",
    "sg:city":"Pozuelo De Alarcon",
    "sg:orig_category":"Organismos De Reclutamiento",
    "sg:phone":"+34 917 15 94 39",
    "sg:postcode":"28224",
    "sg:province":"Madrid",
    "wof:name":"Iberex S.l.",
    "wof:placetype":"venue"
},
  "geometry": {"coordinates":[-3.800153017,40.4591941833],"type":"Point"}
}