{
  "type": "Feature",
  "properties": {
    "addr:full":"Calle de Juan De Garay, 4 Villarcayo Burgos 09550",
    "addr:housenumber":"4",
    "addr:postcode":"09550",
    "addr:street":"Calle De Juan De Garay",
    "iso:country":"ES",
    "sg:address":"Calle de Juan De Garay, 4",
    "sg:city":"Villarcayo",
    "sg:orig_category":"Electricidad Veh\u00cdculo",
    "sg:phone":"+34 947 13 19 96",
    "sg:postcode":"09550",
    "sg:province":"Burgos",
    "wof:name":"Garcia Diaz Jose",
    "wof:placetype":"venue"
},
  "geometry": {"coordinates":[-3.5718889236,42.9366416931],"type":"Point"}
}