{
  "type": "Feature",
  "properties": {
    "iso:country":"ES",
    "sg:address":"Plaz Cuartel Viejo, 2",
    "sg:city":"Zamora",
    "sg:orig_category":"Registro De Empresas",
    "sg:phone":"+34 980 52 00 97",
    "sg:postcode":"49006",
    "sg:province":"Zamora",
    "wof:name":"Registro De La Propiedad Y Mercantil N\u00ba-2",
    "wof:placetype":"venue"
},
  "geometry": {"coordinates":[-5.7447619438,41.5062446594],"type":"Point"}
}