{
  "type": "Feature",
  "properties": {
    "iso:country":"ES",
    "sg:address":"Pl Bassa, De Sa, 6",
    "sg:city":"Manacor",
    "sg:orig_category":"Bisuter\u00cda, Joyer\u00cda, Relojer\u00cda (al Por Menor)",
    "sg:phone":"+34 971 55 11 90",
    "sg:postcode":"07500",
    "sg:province":"Islas Baleares",
    "wof:name":"Joyeria Manacor S.l",
    "wof:placetype":"venue"
},
  "geometry": {"coordinates":[3.227793932,39.5640945435],"type":"Point"}
}