{
  "type": "Feature",
  "properties": {
    "addr:full":"Rua Marco (do), 2 Pontevedra Pontevedra 36004",
    "addr:housenumber":"2",
    "addr:postcode":"36004",
    "addr:street":"Rua Marco Do",
    "iso:country":"ES",
    "sg:address":"Rua Marco (do), 2",
    "sg:city":"Pontevedra",
    "sg:orig_category":"Asesor\u00cda Fiscal Y Jur\u00cddica",
    "sg:phone":"+34 986 86 81 01",
    "sg:postcode":"36004",
    "sg:province":"Pontevedra",
    "wof:name":"Laborsenn Asesores S.l.l.",
    "wof:placetype":"venue"
},
  "geometry": {"coordinates":[-8.63052845,42.4180755615],"type":"Point"}
}