{
  "type": "Feature",
  "properties": {
    "iso:country":"ES",
    "sg:address":"Calle de Ca\u00d1os, S/n",
    "sg:city":"Sanchonu\u00d1o",
    "sg:orig_category":"Alimentaci\u00d3n General (al Por Menor)",
    "sg:phone":"+34 921 16 00 75",
    "sg:postcode":"40297",
    "sg:province":"Segovia",
    "wof:name":"Pascual Colomo Cesareo",
    "wof:placetype":"venue"
},
  "geometry": {"coordinates":[-4.3051543236,41.3309135437],"type":"Point"}
}