{
  "type": "Feature",
  "properties": {
    "addr:full":"Carr Salvador Rodrigo, 14 Albal Valencia 46470",
    "addr:housenumber":"14",
    "addr:postcode":"46470",
    "addr:street":"Carr Salvador Rodrigo",
    "iso:country":"ES",
    "sg:address":"Carr Salvador Rodrigo, 14",
    "sg:city":"Albal",
    "sg:orig_category":"Electromec\u00c1nica",
    "sg:phone":"+34 961 26 18 57",
    "sg:postcode":"46470",
    "sg:province":"Valencia",
    "wof:name":"Crespo Bayona Rafael",
    "wof:placetype":"venue"
},
  "geometry": {"coordinates":[-0.4133450091,39.3982048035],"type":"Point"}
}