{
  "type": "Feature",
  "properties": {
    "addr:full":"Rua Acceso Recinto Ferial, 2 Silleda Pontevedra 36540",
    "addr:housenumber":"2",
    "addr:postcode":"36540",
    "addr:street":"Rua Acceso Recinto Ferial",
    "iso:country":"ES",
    "sg:address":"Rua Acceso Recinto Ferial, 2",
    "sg:city":"Silleda",
    "sg:orig_category":"Contenedores (mercanc\u00cdas)",
    "sg:phone":"+34 986 58 11 74",
    "sg:postcode":"36540",
    "sg:province":"Pontevedra",
    "wof:name":"Gutierrez Lopez Carlos",
    "wof:placetype":"venue"
},
  "geometry": {"coordinates":[-8.2418241501,42.6958084106],"type":"Point"}
}