{
  "type": "Feature",
  "properties": {
    "iso:country":"ES",
    "sg:address":"Calle de Vereda Del Tiro (de), 6",
    "sg:city":"Alcobendas",
    "sg:orig_category":"Promotores Constructores",
    "sg:phone":"+34 916 50 05 05",
    "sg:postcode":"28109",
    "sg:province":"Madrid",
    "wof:name":"Fuenroble S.a.",
    "wof:placetype":"venue"
},
  "geometry": {"coordinates":[-3.6275610924,40.5214004517],"type":"Point"}
}