{
  "type": "Feature",
  "properties": {
    "addr:full":"Calle de Estacion, 30 Fuente Obejuna C\u00f3rdoba 14290",
    "addr:housenumber":"30",
    "addr:postcode":"14290",
    "addr:street":"Calle De Estacion",
    "iso:country":"ES",
    "sg:address":"Calle de Estacion, 30",
    "sg:city":"Fuente Obejuna",
    "sg:orig_category":"Alimentaci\u00d3n General (al Por Menor)",
    "sg:phone":"+34 957 58 43 03",
    "sg:postcode":"14290",
    "sg:province":"C\u00f3rdoba",
    "wof:name":"Rodriguez Redondo Pedro",
    "wof:placetype":"venue"
},
  "geometry": {"coordinates":[-5.416135788,38.2688140869],"type":"Point"}
}