{
  "type": "Feature",
  "properties": {
    "iso:country":"ES",
    "sg:address":"Calle de Toro, 78",
    "sg:city":"Salamanca",
    "sg:orig_category":"Talleres: Ropa A Medida",
    "sg:phone":"+34 923 21 49 84",
    "sg:postcode":"37002",
    "sg:province":"Salamanca",
    "wof:name":"Garcia Alonso Leonides",
    "wof:placetype":"venue"
},
  "geometry": {"coordinates":[-5.6608982086,40.967956543],"type":"Point"}
}