{
  "type": "Feature",
  "properties": {
    "iso:country":"ES",
    "sg:address":"Carrer de Mossen Jacint Verdaguer, 202",
    "sg:city":"Sant Vicen\u00c7 Dels Horts",
    "sg:orig_category":"\u00d3ptica: Instrumentos (fabricaci\u00d3n)",
    "sg:phone":"+34 936 76 92 09",
    "sg:postcode":"08620",
    "sg:province":"Barcelona",
    "wof:name":"Sanou Amigo Jaime",
    "wof:placetype":"venue"
},
  "geometry": {"coordinates":[2.0068640709,41.3985328674],"type":"Point"}
}