{
  "type": "Feature",
  "properties": {
    "addr:full":"Pase Sixto Celorrio, 38 Calatayud Zaragoza 50300",
    "addr:housenumber":"38",
    "addr:postcode":"50300",
    "addr:street":"Sixto Celorrio",
    "iso:country":"ES",
    "sg:address":"Pase Sixto Celorrio, 38",
    "sg:city":"Calatayud",
    "sg:orig_category":"Venta, Instalaci\u00d3n De Calefacci\u00d3n",
    "sg:phone":"+34 976 88 30 48",
    "sg:postcode":"50300",
    "sg:province":"Zaragoza",
    "wof:name":"Disarbutan 2006 S.l.",
    "wof:placetype":"venue"
},
  "geometry": {"coordinates":[-1.6426689625,41.349609375],"type":"Point"}
}