{
  "type": "Feature",
  "properties": {
    "addr:full":"Calle de Higueras, 31 Madrid Madrid 28011",
    "addr:housenumber":"31",
    "addr:postcode":"madrid;28011",
    "addr:street":"Calle De Higueras",
    "iso:country":"ES",
    "sg:address":"Calle de Higueras, 31",
    "sg:city":"Madrid",
    "sg:orig_category":"Veh\u00cdculos De Ocasi\u00d3n",
    "sg:phone":"+34 914 64 58 57",
    "sg:postcode":"28011",
    "sg:province":"Madrid",
    "wof:name":"Excell Kentya S.l.",
    "wof:placetype":"venue"
},
  "geometry": {"coordinates":[-3.7449390888,40.4066352844],"type":"Point"}
}