{
  "type": "Feature",
  "properties": {
    "iso:country":"ES",
    "sg:address":"Plaz Miramar Del Palo, S/n",
    "sg:city":"Malaga",
    "sg:orig_category":"Tintorer\u00cdas, Limpieza En Seco",
    "sg:phone":"+34 952 20 42 11",
    "sg:postcode":"29017",
    "sg:province":"M\u00e1laga",
    "sg:website":"www.pressto.com",
    "wof:name":"C.b. Laly S.l.",
    "wof:placetype":"venue"
},
  "geometry": {"coordinates":[-4.363984108,36.721408844],"type":"Point"}
}