{
  "type": "Feature",
  "properties": {
    "addr:full":"Carrer de Endavallada, 18 S. Cugat Valles Barcelona 08172",
    "addr:housenumber":"18",
    "addr:postcode":"08172",
    "addr:street":"Carrer De Endavallada;S. Cugat Valles Barcelona",
    "iso:country":"ES",
    "sg:address":"Carrer de Endavallada, 18",
    "sg:city":"S. Cugat Valles",
    "sg:orig_category":"Carnicer\u00cdas, Carnicer\u00cdas",
    "sg:phone":"+34 936 75 03 54",
    "sg:postcode":"08172",
    "sg:province":"Barcelona",
    "wof:name":"Grau Oriol Joaquim",
    "wof:placetype":"venue"
},
  "geometry": {"coordinates":[2.0823891163,41.4726905823],"type":"Point"}
}