{
  "type": "Feature",
  "properties": {
    "iso:country":"ES",
    "sg:address":"Calle de Fernando El Catolico, 21",
    "sg:city":"Madrid",
    "sg:orig_category":"Cl\u00cdnicas M\u00c9dicas",
    "sg:phone":"+34 914 47 38 69",
    "sg:postcode":"28015",
    "sg:province":"Madrid",
    "wof:name":"Paredes Castellares Jorge Luis",
    "wof:placetype":"venue"
},
  "geometry": {"coordinates":[-3.7088034153,40.4339599609],"type":"Point"}
}