{
  "type": "Feature",
  "properties": {
    "addr:full":"Avda Boliches De Los, 84 Fuengirola M\u00e1laga 29640",
    "addr:postcode":"29640",
    "addr:street":"Avda Boliches De Los;Ma\u0301Laga",
    "iso:country":"ES",
    "sg:address":"Avda Boliches De Los, 84",
    "sg:city":"Fuengirola",
    "sg:orig_category":"Estancos",
    "sg:phone":"+34 952 47 32 63",
    "sg:postcode":"29640",
    "sg:province":"M\u00e1laga",
    "wof:name":"Gonzalez Palenque Juan",
    "wof:placetype":"venue"
},
  "geometry": {"coordinates":[-4.6156640053,36.550907135],"type":"Point"}
}