{
  "type": "Feature",
  "properties": {
    "addr:full":"Calle de Juan De La Cierva, 1 San Jose Rinconada Sevilla 41300",
    "addr:housenumber":"1",
    "addr:postcode":"41300",
    "addr:street":"Calle De Juan De La Cierva",
    "iso:country":"ES",
    "sg:address":"Calle de Juan De La Cierva, 1",
    "sg:city":"San Jose Rinconada",
    "sg:orig_category":"Aluminio Y Aleaciones (producci\u00d3n, Transformaci\u00d3n, Negocio)",
    "sg:phone":"+34 954 79 26 98",
    "sg:postcode":"41300",
    "sg:province":"Sevilla",
    "wof:name":"Inalmar S.l.",
    "wof:placetype":"venue"
},
  "geometry": {"coordinates":[-5.9474101067,37.4867591858],"type":"Point"}
}