{
  "type": "Feature",
  "properties": {
    "iso:country":"ES",
    "sg:address":"Calle de Juan De Aranda, 1",
    "sg:city":"Alcala Real",
    "sg:orig_category":"Ense\u00d1anza: Peluquer\u00cda Est\u00c9tica",
    "sg:phone":"+34 953 58 39 09",
    "sg:postcode":"23680",
    "sg:province":"Ja\u00e9n",
    "wof:name":"Cano Lopez Antonia",
    "wof:placetype":"venue"
},
  "geometry": {"coordinates":[-3.9229838848,37.4568214417],"type":"Point"}
}