{
  "type": "Feature",
  "properties": {
    "iso:country":"ES",
    "sg:address":"Carr Riu Palancia (del), 1",
    "sg:city":"Manises",
    "sg:orig_category":"Comercio De Piezas De Recambio Y De Accesorios De Veh\u00cdculos, Veh\u00cdculos Industriales",
    "sg:phone":"+34 961 52 05 46",
    "sg:postcode":"46940",
    "sg:province":"Valencia",
    "wof:name":"Auto Recambios Vilber S.l.",
    "wof:placetype":"venue"
},
  "geometry": {"coordinates":[-0.4499100149,39.4894828796],"type":"Point"}
}