{
  "type": "Feature",
  "properties": {
    "iso:country":"ES",
    "sg:address":"Calle de San Jose, 3",
    "sg:city":"Alaquas",
    "sg:orig_category":"Seguridad Social",
    "sg:phone":"+34 961 50 90 07",
    "sg:postcode":"46970",
    "sg:province":"Valencia",
    "wof:name":"Asociacion Democratica Provincial De Jubilados Y Pensionistas De Valencia",
    "wof:placetype":"venue"
},
  "geometry": {"coordinates":[-0.4650531113,39.4559898376],"type":"Point"}
}