{
  "type": "Feature",
  "properties": {
    "iso:country":"ES",
    "sg:address":"Rio De Agua, 6",
    "sg:city":"Viator",
    "sg:orig_category":"Maquinaria Neum\u00c1tica",
    "sg:phone":"+34 950 30 52 74",
    "sg:postcode":"04240",
    "sg:province":"Almer\u00eda",
    "wof:name":"Hidraulicos R.c S.l",
    "wof:placetype":"venue"
},
  "geometry": {"coordinates":[-2.4221930504,36.8850784302],"type":"Point"}
}