{
  "type": "Feature",
  "properties": {
    "iso:country":"ES",
    "sg:address":"Av Generalitat (de La), 30",
    "sg:city":"Tortosa",
    "sg:orig_category":"Servicios Gsm",
    "sg:phone":"+34 977 44 81 36",
    "sg:postcode":"43500",
    "sg:province":"Tarragona",
    "wof:name":"Ilertel Comunicaciones S.l.u.",
    "wof:placetype":"venue"
},
  "geometry": {"coordinates":[0.5201699734,40.8112831116],"type":"Point"}
}