{
  "type": "Feature",
  "properties": {
    "addr:full":"Carrer de Santa Coloma (de), 32 Vilassar De Mar Barcelona 08340",
    "addr:postcode":"08340",
    "addr:street":"Carrer De Santa",
    "iso:country":"ES",
    "sg:address":"Carrer de Santa Coloma (de), 32",
    "sg:city":"Vilassar De Mar",
    "sg:orig_category":"Empresas De Carpinter\u00cda De Madera",
    "sg:phone":"+34 937 59 48 08",
    "sg:postcode":"08340",
    "sg:province":"Barcelona",
    "wof:name":"Fusteria Ascensio Scp",
    "wof:placetype":"venue"
},
  "geometry": {"coordinates":[2.3965389729,41.5046958923],"type":"Point"}
}