{
  "type": "Feature",
  "properties": {
    "addr:full":"Calle de Ramon Del Valle, 3 Arriondas Asturias 33540",
    "addr:housenumber":"3",
    "addr:postcode":"33540",
    "addr:street":"Calle De Ramon Del Valle",
    "iso:country":"ES",
    "sg:address":"Calle de Ramon Del Valle, 3",
    "sg:city":"Arriondas",
    "sg:orig_category":"Producci\u00d3n De Sidra",
    "sg:phone":"+34 985 84 16 74",
    "sg:postcode":"33540",
    "sg:province":"Asturias",
    "wof:name":"Sanchez Garcia Manuel Ramon",
    "wof:placetype":"venue"
},
  "geometry": {"coordinates":[-5.1874399185,43.3906211853],"type":"Point"}
}