{
  "type": "Feature",
  "properties": {
    "addr:full":"Calle de Menendez Pelayo, 13 Gijon Asturias 33202",
    "addr:housenumber":"13",
    "addr:postcode":"33202",
    "addr:street":"Calle De Menendez Pelayo",
    "iso:country":"ES",
    "sg:address":"Calle de Menendez Pelayo, 13",
    "sg:city":"Gijon",
    "sg:orig_category":"Agencias De Viajes",
    "sg:phone":"+34 985 13 08 26",
    "sg:postcode":"33202",
    "sg:province":"Asturias",
    "wof:name":"Viajes Iberia S.a.",
    "wof:placetype":"venue"
},
  "geometry": {"coordinates":[-5.6523499489,43.5380363464],"type":"Point"}
}