{
  "type": "Feature",
  "properties": {
    "addr:full":"Calle de Arias, 5 Zaragoza Zaragoza 50010",
    "addr:housenumber":"5",
    "addr:postcode":"50010",
    "addr:street":"Calle De Arias",
    "iso:country":"ES",
    "sg:address":"Calle de Arias, 5",
    "sg:city":"Zaragoza",
    "sg:orig_category":"Agencias Y Agentes Comerciales, Representantes",
    "sg:phone":"+34 976 31 95 21",
    "sg:postcode":"50010",
    "sg:province":"Zaragoza",
    "wof:name":"De Jesus Santos Antonia",
    "wof:placetype":"venue"
},
  "geometry": {"coordinates":[-0.9086233974,41.6528930664],"type":"Point"}
}