{
  "type": "Feature",
  "properties": {
    "addr:full":"Avda Andalucia, 18 Sevilla Sevilla 41005",
    "addr:housenumber":"18",
    "addr:postcode":"41005",
    "addr:street":"Avda Andalucia",
    "iso:country":"ES",
    "sg:address":"Avda Andalucia, 18",
    "sg:city":"Sevilla",
    "sg:orig_category":"Fabricaci\u00d3n De Ventanas",
    "sg:phone":"+34 954 57 11 65",
    "sg:postcode":"41005",
    "sg:province":"Sevilla",
    "wof:name":"Barrio Barrera Jesus",
    "wof:placetype":"venue"
},
  "geometry": {"coordinates":[-5.9602460861,37.3873062134],"type":"Point"}
}