{
  "type": "Feature",
  "properties": {
    "iso:country":"ES",
    "sg:address":"Carrer de Jovellanos, 95",
    "sg:city":"Sabadell",
    "sg:orig_category":"M\u00c9dicos: Estomatolog\u00cda",
    "sg:phone":"+34 937 25 60 60",
    "sg:postcode":"08201",
    "sg:province":"Barcelona",
    "wof:name":"Busoms Dentistes Associats S.l.",
    "wof:placetype":"venue"
},
  "geometry": {"coordinates":[2.1039729118,41.5503807068],"type":"Point"}
}