{
  "type": "Feature",
  "properties": {
    "addr:full":"Av Sant Julia, 204 Granollers Barcelona 08403",
    "addr:housenumber":"204",
    "addr:postcode":"08403",
    "addr:street":"Av Sant Julia",
    "iso:country":"ES",
    "sg:address":"Av Sant Julia, 204",
    "sg:city":"Granollers",
    "sg:orig_category":"Producci\u00d3n, Distribuci\u00d3n De Electricidad",
    "sg:phone":"+34 938 40 53 18",
    "sg:postcode":"08403",
    "sg:province":"Barcelona",
    "wof:name":"Connectors Hidraulics S.l.",
    "wof:placetype":"venue"
},
  "geometry": {"coordinates":[2.2733659744,41.5818481445],"type":"Point"}
}