{
  "type": "Feature",
  "properties": {
    "addr:full":"Calle de Calvo Sotelo, 3 Pto. Rosario Las Palmas 35600",
    "addr:housenumber":"3",
    "addr:postcode":"35600",
    "addr:street":"Calle De Calvo Sotelo;Pto. Rosario Las",
    "iso:country":"ES",
    "sg:address":"Calle de Calvo Sotelo, 3",
    "sg:city":"Pto. Rosario",
    "sg:orig_category":"Organizaciones Profesionales",
    "sg:phone":"+34 928 85 05 63",
    "sg:postcode":"35600",
    "sg:province":"Las Palmas",
    "wof:name":"Ruiz Mendez Mari Carmen",
    "wof:placetype":"venue"
},
  "geometry": {"coordinates":[-13.8503522873,28.500951767],"type":"Point"}
}