{
  "type": "Feature",
  "properties": {
    "iso:country":"ES",
    "sg:address":"Calle de Frailes, 17",
    "sg:city":"Granada",
    "sg:orig_category":"Agentes Generales De Seguros",
    "sg:phone":"+34 958 26 31 24",
    "sg:postcode":"18005",
    "sg:province":"Granada",
    "wof:name":"Varela Carrillo Juan Manuel",
    "wof:placetype":"venue"
},
  "geometry": {"coordinates":[-3.6014740467,37.1719322205],"type":"Point"}
}