{
  "type": "Feature",
  "properties": {
    "addr:full":"Pla\u00c7 Esglesia, 5 Estartit Girona 17258",
    "addr:housenumber":"5",
    "addr:postcode":"17258",
    "addr:street":"Plac\u0327 Esglesia",
    "iso:country":"ES",
    "sg:address":"Pla\u00c7 Esglesia, 5",
    "sg:city":"Estartit",
    "sg:orig_category":"Alimentaci\u00d3n General (al Por Menor)",
    "sg:phone":"+34 972 75 15 18",
    "sg:postcode":"17258",
    "sg:province":"Girona",
    "wof:name":"Calvet Batlle Francisco",
    "wof:placetype":"venue"
},
  "geometry": {"coordinates":[3.1878299713,42.0489959717],"type":"Point"}
}