{
  "type": "Feature",
  "properties": {
    "iso:country":"ES",
    "sg:address":"Calle de Ercilla, 14",
    "sg:city":"Alacant",
    "sg:orig_category":"Empresas De Carpinter\u00cda Met\u00c1lica",
    "sg:phone":"+34 965 24 32 84",
    "sg:postcode":"03015",
    "sg:province":"Alicante",
    "wof:name":"Inoxcon Alicante S.l.",
    "wof:placetype":"venue"
},
  "geometry": {"coordinates":[-0.475210011,38.3640556335],"type":"Point"}
}