{
  "type": "Feature",
  "properties": {
    "addr:full":"Carretera Del Baden, 8 Talavera Real Badajoz 06140",
    "addr:housenumber":"8",
    "addr:postcode":"06140",
    "addr:street":"Carretera Del Baden",
    "iso:country":"ES",
    "sg:address":"Carretera Del Baden, 8",
    "sg:city":"Talavera Real",
    "sg:orig_category":"Mec\u00c1nico Del Autom\u00d3vil",
    "sg:phone":"+34 924 44 13 18",
    "sg:postcode":"06140",
    "sg:province":"Badajoz",
    "wof:name":"Gomez Diaz Manuel",
    "wof:placetype":"venue"
},
  "geometry": {"coordinates":[-6.7690382004,38.8795204163],"type":"Point"}
}