{
  "type": "Feature",
  "properties": {
    "iso:country":"ES",
    "sg:address":"Quintana, 11",
    "sg:city":"Quintana",
    "sg:orig_category":"Suministros Y Materiales Industriales",
    "sg:phone":"+34 986 40 02 62",
    "sg:postcode":"36818",
    "sg:province":"Pontevedra",
    "sg:website":"www.tecsumaga.com",
    "wof:name":"Tecsumaga S.l.",
    "wof:placetype":"venue"
},
  "geometry": {"coordinates":[-8.609254837,42.3069534302],"type":"Point"}
}