{
  "type": "Feature",
  "properties": {
    "addr:full":"Calle de Jose Cabrera Ramirez, 44 Molino Las Palmas 35300",
    "addr:housenumber":"44",
    "addr:postcode":"35300",
    "addr:street":"Calle De Jose Cabrera Ramirez;Las",
    "iso:country":"ES",
    "sg:address":"Calle de Jose Cabrera Ramirez, 44",
    "sg:city":"Molino",
    "sg:orig_category":"Empresas De Carpinter\u00cda De Madera",
    "sg:phone":"+34 928 64 12 84",
    "sg:postcode":"35300",
    "sg:province":"Las Palmas",
    "wof:name":"Deniz Marrero Clemente",
    "wof:placetype":"venue"
},
  "geometry": {"coordinates":[-15.4988956451,28.0369472504],"type":"Point"}
}