{
  "type": "Feature",
  "properties": {
    "addr:full":"Calle de Corredera, 58 Montoro C\u00f3rdoba 14600",
    "addr:housenumber":"58",
    "addr:postcode":"14600",
    "addr:street":"Calle De Corredera;Co\u0301Rdoba",
    "iso:country":"ES",
    "sg:address":"Calle de Corredera, 58",
    "sg:city":"Montoro",
    "sg:orig_category":"Cajas Para Embalar",
    "sg:phone":"+34 957 16 07 17",
    "sg:postcode":"14600",
    "sg:province":"C\u00f3rdoba",
    "wof:name":"Caja Rural De Cordoba",
    "wof:placetype":"venue"
},
  "geometry": {"coordinates":[-4.3817400932,38.0242424011],"type":"Point"}
}