{
  "type": "Feature",
  "properties": {
    "addr:full":"Calle de Meteorologo Fco. Garcia, 26 Villafranqueza - Palamo Alicante 03112",
    "addr:housenumber":"26",
    "addr:postcode":"03112",
    "addr:street":"Calle De Meteorologo Fco. Garcia",
    "iso:country":"ES",
    "sg:address":"Calle de Meteorologo Fco. Garcia, 26",
    "sg:city":"Villafranqueza - Palamo",
    "sg:orig_category":"Empresas De Carpinter\u00cda De Madera",
    "sg:phone":"+34 965 17 23 10",
    "sg:postcode":"03112",
    "sg:province":"Alicante",
    "wof:name":"Santos Interiorismo S.l.",
    "wof:placetype":"venue"
},
  "geometry": {"coordinates":[-0.4690259993,38.4094772339],"type":"Point"}
}