{
  "type": "Feature",
  "properties": {
    "iso:country":"ES",
    "sg:address":"Plaz Asociacion De La Prensa, 5",
    "sg:city":"Granada",
    "sg:orig_category":"Instalaci\u00d3n De Aspiraci\u00d3n De Gases Y Humos",
    "sg:phone":"+34 958 17 26 41",
    "sg:postcode":"18015",
    "sg:province":"Granada",
    "wof:name":"Disgas Los Neveros S.l.",
    "wof:placetype":"venue"
},
  "geometry": {"coordinates":[-3.6287379265,37.1988716125],"type":"Point"}
}