{
  "type": "Feature",
  "properties": {
    "iso:country":"ES",
    "sg:address":"Plaz Nueva, 2",
    "sg:city":"Lucena",
    "sg:orig_category":"Abogados",
    "sg:phone":"+34 957 50 01 35",
    "sg:postcode":"14900",
    "sg:province":"C\u00f3rdoba",
    "wof:name":"Manjon-cabezas Fuerte Vicente",
    "wof:placetype":"venue"
},
  "geometry": {"coordinates":[-4.5418143272,37.3598442078],"type":"Point"}
}