{
  "type": "Feature",
  "properties": {
    "iso:country":"ES",
    "sg:address":"Pje El Algarrobo, 64",
    "sg:city":"Santa Maria Aguila",
    "sg:orig_category":"Negocio De Materiales De Construcci\u00d3n",
    "sg:phone":"+34 950 58 11 50",
    "sg:postcode":"04710",
    "sg:province":"Almer\u00eda",
    "wof:name":"J.craviotto S.a.",
    "wof:placetype":"venue"
},
  "geometry": {"coordinates":[-2.7759139538,36.7795753479],"type":"Point"}
}