{
  "type": "Feature",
  "properties": {
    "iso:country":"ES",
    "sg:address":"Avda Miramar, 9",
    "sg:city":"S. Vicente Barquera",
    "sg:orig_category":"Restaurantes",
    "sg:phone":"+34 942 71 01 33",
    "sg:postcode":"39540",
    "sg:province":"Cantabria",
    "wof:name":"Santia\u00f1ez Roiz Daniel Andres",
    "wof:placetype":"venue"
},
  "geometry": {"coordinates":[-4.398001194,43.3822479248],"type":"Point"}
}