{
  "type": "Feature",
  "properties": {
    "iso:country":"ES",
    "sg:address":"Ptge. Raval De Baix, 36",
    "sg:city":"Vall-llobrega",
    "sg:orig_category":"Cr\u00cda De Animales De Caza Menor",
    "sg:phone":"+34 972 60 23 15",
    "sg:postcode":"17253",
    "sg:province":"Girona",
    "sg:website":"www.fedecaza.com",
    "wof:name":"Especies Cinegetiques Catalanes S.l.",
    "wof:placetype":"venue"
},
  "geometry": {"coordinates":[3.1464159489,41.9082527161],"type":"Point"}
}