{
  "type": "Feature",
  "properties": {
    "iso:country":"ES",
    "sg:address":"Carretera De Infantes, S/n",
    "sg:city":"Villanueva Fuente",
    "sg:orig_category":"Hormigonados",
    "sg:phone":"+34 967 39 61 81",
    "sg:postcode":"13330",
    "sg:province":"Ciudad Real",
    "wof:name":"Aridos Villahermosa S.l.",
    "wof:placetype":"venue"
},
  "geometry": {"coordinates":[-2.6943438053,38.6970291138],"type":"Point"}
}