{
  "type": "Feature",
  "properties": {
    "addr:full":"Herrerias, S/n Alcuescar C\u00e1ceres 10160",
    "addr:housenumber":"s / n",
    "addr:postcode":"10160",
    "addr:street":"Herrerias;Ca\u0301Ceres",
    "iso:country":"ES",
    "sg:address":"Herrerias, S/n",
    "sg:city":"Alcuescar",
    "sg:orig_category":"Tapones Y Art\u00cdculos De Corcho",
    "sg:phone":"+34 927 38 40 60",
    "sg:postcode":"10160",
    "sg:province":"C\u00e1ceres",
    "wof:name":"Borrego Gil Juan Carlos",
    "wof:placetype":"venue"
},
  "geometry": {"coordinates":[-6.2622241974,39.1643104553],"type":"Point"}
}