{
  "type": "Feature",
  "properties": {
    "iso:country":"ES",
    "sg:address":"Carrer de Boqueria, 2",
    "sg:city":"Barcelona",
    "sg:orig_category":"Ropa Para Se\u00d1oras Y Caballeros (al Por Menor)",
    "sg:phone":"+34 933 17 82 85",
    "sg:postcode":"08002",
    "sg:province":"Barcelona",
    "sg:website":"ww.lacoste.es",
    "wof:name":"Casa Sarret S. A.",
    "wof:placetype":"venue"
},
  "geometry": {"coordinates":[2.1734271049,41.3812904358],"type":"Point"}
}