{
  "type": "Feature",
  "properties": {
    "addr:full":"Rua San Pedro, 25 Lugo Lugo 27001",
    "addr:housenumber":"25",
    "addr:postcode":"27001",
    "addr:street":"Rua San Pedro",
    "iso:country":"ES",
    "sg:address":"Rua San Pedro, 25",
    "sg:city":"Lugo",
    "sg:orig_category":"Arquitectos",
    "sg:phone":"+34 982 28 02 48",
    "sg:postcode":"27001",
    "sg:province":"Lugo",
    "wof:name":"Orgaz Lopez Susana",
    "wof:placetype":"venue"
},
  "geometry": {"coordinates":[-7.5533871651,43.0104637146],"type":"Point"}
}