{
  "type": "Feature",
  "properties": {
    "iso:country":"ES",
    "sg:address":"Calle de Sierra Toledana, 5",
    "sg:city":"Madrid",
    "sg:orig_category":"Inform\u00c1tica: Mantenimiento Y Reparaci\u00d3n De Ordenadores",
    "sg:phone":"+34 914 37 42 38",
    "sg:postcode":"28038",
    "sg:province":"Madrid",
    "wof:name":"Equipo A & Redes S.l.",
    "wof:placetype":"venue"
},
  "geometry": {"coordinates":[-3.6608099937,40.3997917175],"type":"Point"}
}