{
  "type": "Feature",
  "properties": {
    "iso:country":"ES",
    "sg:address":"Pase Puentes, 2",
    "sg:city":"Coru\u00d1a",
    "sg:orig_category":"Agentes Y Bufetes De Negocio",
    "sg:phone":"+34 981 27 81 81",
    "sg:postcode":"15004",
    "sg:province":"La Coru\u00f1a",
    "wof:name":"Centro De Iniciativas Profesionales Cip S.l.",
    "wof:placetype":"venue"
},
  "geometry": {"coordinates":[-8.4130973816,43.3638305664],"type":"Point"}
}