{
  "type": "Feature",
  "properties": {
    "iso:country":"ES",
    "sg:address":"Av Anselm Clave, 37",
    "sg:city":"Castellsera",
    "sg:orig_category":"Maquinaria Para Industrias Diversas",
    "sg:phone":"+34 973 61 01 83",
    "sg:postcode":"25334",
    "sg:province":"Lleida",
    "wof:name":"Industries Mecaniques Fabregat S.l.",
    "wof:placetype":"venue"
},
  "geometry": {"coordinates":[0.9866999984,41.7436523438],"type":"Point"}
}