{
  "type": "Feature",
  "properties": {
    "iso:country":"ES",
    "sg:address":"Calle de Rafael Azcona, 8",
    "sg:city":"Logro\u00f1o",
    "sg:orig_category":"Comercio De Mobiliario De Oficina",
    "sg:phone":"+34 941 25 24 33",
    "sg:postcode":"26006",
    "sg:province":"La Rioja",
    "wof:name":"Sistemas De Oficina De Rioja S.l.",
    "wof:placetype":"venue"
},
  "geometry": {"coordinates":[-2.4611740112,42.4721298218],"type":"Point"}
}