{
  "type": "Feature",
  "properties": {
    "addr:full":"Ptda Benadresa, 110 Borriol Castell\u00f3n 12190",
    "addr:housenumber":"110",
    "addr:postcode":"12190",
    "addr:street":"Ptda Benadresa",
    "iso:country":"ES",
    "sg:address":"Ptda Benadresa, 110",
    "sg:city":"Borriol",
    "sg:orig_category":"Asociaciones Humanitarias, De Cooperaci\u00d3n, De Acci\u00d3n Social",
    "sg:phone":"+34 964 25 90 01",
    "sg:postcode":"12190",
    "sg:province":"Castell\u00f3n",
    "wof:name":"Afanias Asociacion De Familiares Con Ni\u00f1os Y Adultos Discapacitados De Castellon",
    "wof:placetype":"venue"
},
  "geometry": {"coordinates":[-0.0653340966,40.0530395508],"type":"Point"}
}