{
  "type": "Feature",
  "properties": {
    "addr:full":"Rieral (pol Can Coll-perdellot), S/n Lli\u00e7a Vall Barcelona 08185",
    "addr:housenumber":"s",
    "addr:postcode":"08185",
    "addr:street":"/ N;Vall Barcelona",
    "iso:country":"ES",
    "sg:address":"Rieral (pol Can Coll-perdellot), S/n",
    "sg:city":"Lli\u00e7a Vall",
    "sg:orig_category":"Barnizadores",
    "sg:phone":"+34 938 43 61 97",
    "sg:postcode":"08185",
    "sg:province":"Barcelona",
    "wof:name":"J. Payan Barnizados Y Lacados S.l.",
    "wof:placetype":"venue"
},
  "geometry": {"coordinates":[2.2325119972,41.5866622925],"type":"Point"}
}