{
  "type": "Feature",
  "properties": {
    "iso:country":"ES",
    "sg:address":"Carr Ausias March, (d'), 7",
    "sg:city":"Carlet",
    "sg:orig_category":"M\u00c9dicos: Psiquiatr\u00cda",
    "sg:phone":"+34 962 53 24 78",
    "sg:postcode":"46240",
    "sg:province":"Valencia",
    "wof:name":"Galbis Domenech Antonio",
    "wof:placetype":"venue"
},
  "geometry": {"coordinates":[-0.5249320269,39.2261695862],"type":"Point"}
}