{
  "type": "Feature",
  "properties": {
    "addr:full":"Carr Leonor Servera, S/n Cala Ratjada Islas Baleares 07590",
    "addr:housenumber":"s / n",
    "addr:postcode":"07590",
    "addr:street":"Carr Leonor Servera",
    "iso:country":"ES",
    "sg:address":"Carr Leonor Servera, S/n",
    "sg:city":"Cala Ratjada",
    "sg:orig_category":"Bisuter\u00cda, Joyer\u00cda, Relojer\u00cda (al Por Menor)",
    "sg:phone":"+34 971 56 38 89",
    "sg:postcode":"07590",
    "sg:province":"Islas Baleares",
    "wof:name":"Fuster Barcelo Gabriel",
    "wof:placetype":"venue"
},
  "geometry": {"coordinates":[3.4593300819,39.7099304199],"type":"Point"}
}