{
  "type": "Feature",
  "properties": {
    "iso:country":"ES",
    "sg:address":"Pl Fruita (la), 42",
    "sg:city":"Elche",
    "sg:orig_category":"Alimentaci\u00d3n General (al Por Menor)",
    "sg:phone":"+34 966 61 02 56",
    "sg:postcode":"03202",
    "sg:province":"Alicante",
    "wof:name":"Roman Agullo Vicente",
    "wof:placetype":"venue"
},
  "geometry": {"coordinates":[-0.6990320086,38.2657546997],"type":"Point"}
}