{
  "type": "Feature",
  "properties": {
    "addr:full":"Calle de Federico Vial, 5 Santander Cantabria 39009",
    "addr:housenumber":"5",
    "addr:postcode":"39009",
    "addr:street":"Calle De Federico Vial",
    "iso:country":"ES",
    "sg:address":"Calle de Federico Vial, 5",
    "sg:city":"Santander",
    "sg:orig_category":"Bricolaje, Herramientas (al Por Menor)",
    "sg:phone":"+34 942 36 50 56",
    "sg:postcode":"39009",
    "sg:province":"Cantabria",
    "wof:name":"Bricolage Salas S.l.",
    "wof:placetype":"venue"
},
  "geometry": {"coordinates":[-3.8130760193,43.4565353394],"type":"Point"}
}