{
  "type": "Feature",
  "properties": {
    "iso:country":"ES",
    "sg:address":"Carrer de Emili Darder,batle, 41",
    "sg:city":"Palma",
    "sg:orig_category":"Bisuter\u00cda, Joyer\u00cda, Relojer\u00cda (al Por Menor)",
    "sg:phone":"+34 971 73 45 07",
    "sg:postcode":"07013",
    "sg:province":"Islas Baleares",
    "wof:name":"Jovani Crespi Juan Luis",
    "wof:placetype":"venue"
},
  "geometry": {"coordinates":[2.6379759312,39.577129364],"type":"Point"}
}