{
  "type": "Feature",
  "properties": {
    "addr:full":"Calle de Egia, 24 Donostia-san Sebastian Guip\u00f9zcoa 20012",
    "addr:housenumber":"24",
    "addr:postcode":"20012",
    "addr:street":"Calle De Egia",
    "iso:country":"ES",
    "sg:address":"Calle de Egia, 24",
    "sg:city":"Donostia-san Sebastian",
    "sg:orig_category":"Estancos",
    "sg:phone":"+34 943 27 53 84",
    "sg:postcode":"20012",
    "sg:province":"Guip\u00f9zcoa",
    "wof:name":"Mendizabal Balda Francisca",
    "wof:placetype":"venue"
},
  "geometry": {"coordinates":[-1.972630024,43.3164176941],"type":"Point"}
}