{
  "type": "Feature",
  "properties": {
    "iso:country":"ES",
    "sg:address":"Cust Descargas, 12",
    "sg:city":"Madrid",
    "sg:orig_category":"Inform\u00c1tica (estudios, Servicios, Asesor\u00cda, Formaci\u00d3n)",
    "sg:phone":"+34 913 64 16 27",
    "sg:postcode":"28005",
    "sg:province":"Madrid",
    "wof:name":"Telecomunicaciones E Informatica Creativa S.l.",
    "wof:placetype":"venue"
},
  "geometry": {"coordinates":[-3.7141969204,40.4077453613],"type":"Point"}
}