{
  "type": "Feature",
  "properties": {
    "addr:full":"Carrer de Mestre Hierro, 5 Ulldecona Tarragona 43550",
    "addr:postcode":"43550",
    "addr:street":"Carrer De Mestre Hierro 5",
    "iso:country":"ES",
    "sg:address":"Carrer de Mestre Hierro, 5",
    "sg:city":"Ulldecona",
    "sg:orig_category":"Agentes Generales De Seguros",
    "sg:phone":"+34 977 72 00 48",
    "sg:postcode":"43550",
    "sg:province":"Tarragona",
    "wof:name":"Sauch-viladot S.l",
    "wof:placetype":"venue"
},
  "geometry": {"coordinates":[0.4446560144,40.5966033936],"type":"Point"}
}