{
  "type": "Feature",
  "properties": {
    "addr:full":"Calle de Lugo, 17 Arzua La Coru\u00f1a 15810",
    "addr:housenumber":"17",
    "addr:postcode":"15810",
    "addr:street":"Calle De Lugo;La Corun\u0303A",
    "iso:country":"ES",
    "sg:address":"Calle de Lugo, 17",
    "sg:city":"Arzua",
    "sg:orig_category":"Bancos",
    "sg:phone":"+34 981 50 01 00",
    "sg:postcode":"15810",
    "sg:province":"La Coru\u00f1a",
    "wof:name":"Banco De Galicia",
    "wof:placetype":"venue"
},
  "geometry": {"coordinates":[-8.1626091003,42.9267997742],"type":"Point"}
}