{
  "type": "Feature",
  "properties": {
    "iso:country":"ES",
    "sg:address":"Calle de Fermin Sosa Pino, 6",
    "sg:city":"Paso",
    "sg:orig_category":"Asociaciones Y Clubs Deportivos",
    "sg:phone":"+34 922 48 62 33",
    "sg:postcode":"38750",
    "sg:province":"Santa Cruz De Tenerife",
    "wof:name":"Rodriguez Arzola Nieves Luz",
    "wof:placetype":"venue"
},
  "geometry": {"coordinates":[-17.8803157806,28.6513309479],"type":"Point"}
}