{
  "type": "Feature",
  "properties": {
    "iso:country":"ES",
    "sg:address":"Calle de Narrica, 7",
    "sg:city":"Donostia-san Sebastian",
    "sg:orig_category":"Reposter\u00cdas",
    "sg:phone":"+34 943 43 15 22",
    "sg:postcode":"20003",
    "sg:province":"Guip\u00f9zcoa",
    "wof:name":"Rodellar Arasanz Maria Rosa",
    "wof:placetype":"venue"
},
  "geometry": {"coordinates":[-1.9841330051,43.3228569031],"type":"Point"}
}