{
  "type": "Feature",
  "properties": {
    "iso:country":"ES",
    "sg:address":"Carr Santa Anna, S/n",
    "sg:city":"Bescano",
    "sg:orig_category":"Asilos De Ancianos. Centros Privados",
    "sg:phone":"+34 972 44 28 86",
    "sg:postcode":"17162",
    "sg:province":"Girona",
    "sg:website":"www.residenciassantanna.com",
    "wof:name":"Santa Anna Resicencia I Centre De Dia S.l.",
    "wof:placetype":"venue"
},
  "geometry": {"coordinates":[2.7449400425,41.9648246765],"type":"Point"}
}