{
  "type": "Feature",
  "properties": {
    "iso:country":"ES",
    "sg:address":"Calle de San Lorenzo, 7",
    "sg:city":"Valladolid",
    "sg:orig_category":"M\u00c9dicos: Estomatolog\u00cda",
    "sg:phone":"+34 983 33 04 09",
    "sg:postcode":"47001",
    "sg:province":"Valladolid",
    "wof:name":"Rodriguez Diaz Angel",
    "wof:placetype":"venue"
},
  "geometry": {"coordinates":[-4.7314190865,41.6522331238],"type":"Point"}
}