{
  "type": "Feature",
  "properties": {
    "iso:country":"ES",
    "sg:address":"Carr Francesc Macia, 11",
    "sg:city":"Badalona",
    "sg:orig_category":"Guarder\u00cdas",
    "sg:phone":"+34 933 83 70 10",
    "sg:postcode":"08912",
    "sg:province":"Barcelona",
    "wof:name":"Iba\u00f1ez Castella Ana Maria",
    "wof:placetype":"venue"
},
  "geometry": {"coordinates":[2.2426590919,41.4475326538],"type":"Point"}
}