{
  "type": "Feature",
  "properties": {
    "addr:full":"Rua Urzaiz, 215 Vigo Pontevedra 36205",
    "addr:housenumber":"215",
    "addr:postcode":"36205",
    "addr:street":"Rua Urzaiz",
    "iso:country":"ES",
    "sg:address":"Rua Urzaiz, 215",
    "sg:city":"Vigo",
    "sg:orig_category":"Consultas M\u00c9dicas",
    "sg:phone":"+34 986 37 44 80",
    "sg:postcode":"36205",
    "sg:province":"Pontevedra",
    "wof:name":"Centro Medico Psicotecnico Vigo S. A.",
    "wof:placetype":"venue"
},
  "geometry": {"coordinates":[-8.702337265,42.2311477661],"type":"Point"}
}