{
  "type": "Feature",
  "properties": {
    "addr:full":"Calle de Arquitecto Mateo Gaya, 36 Baena C\u00f3rdoba 14850",
    "addr:housenumber":"36",
    "addr:postcode":"14850",
    "addr:street":"Calle De Arquitecto Mateo Gaya",
    "iso:country":"ES",
    "sg:address":"Calle de Arquitecto Mateo Gaya, 36",
    "sg:city":"Baena",
    "sg:orig_category":"Piscinas, Accesorios, Suministros (fabricaci\u00d3n, Al Por Mayor)",
    "sg:phone":"+34 957 67 08 06",
    "sg:postcode":"14850",
    "sg:province":"C\u00f3rdoba",
    "wof:name":"Unidad De Servicios Caesol S.l.",
    "wof:placetype":"venue"
},
  "geometry": {"coordinates":[-4.3190999031,37.6189994812],"type":"Point"}
}