{
  "type": "Feature",
  "properties": {
    "addr:full":"Carrer de Sant Pere, 54 Lloret Mar Girona 17310",
    "addr:housenumber":"54",
    "addr:postcode":"17310",
    "addr:street":"Carrer De Sant Pere",
    "iso:country":"ES",
    "sg:address":"Carrer de Sant Pere, 54",
    "sg:city":"Lloret Mar",
    "sg:orig_category":"Art\u00cdculos De Regalo (al Por Menor)",
    "sg:phone":"+34 972 36 96 21",
    "sg:postcode":"17310",
    "sg:province":"Girona",
    "wof:name":"Lamrani  Zahara",
    "wof:placetype":"venue"
},
  "geometry": {"coordinates":[2.8458819389,41.7013549805],"type":"Point"}
}