{
  "type": "Feature",
  "properties": {
    "addr:full":"Avda Constitucion (de La), 29 Granada Granada 18014",
    "addr:housenumber":"29",
    "addr:postcode":"18014",
    "addr:street":"Avda Constitucion De La",
    "iso:country":"ES",
    "sg:address":"Avda Constitucion (de La), 29",
    "sg:city":"Granada",
    "sg:orig_category":"Promotores Constructores",
    "sg:phone":"+34 958 29 24 22",
    "sg:postcode":"18014",
    "sg:province":"Granada",
    "wof:name":"Visogsa S.a.",
    "wof:placetype":"venue"
},
  "geometry": {"coordinates":[-3.6087448597,37.1860961914],"type":"Point"}
}