{
  "type": "Feature",
  "properties": {
    "addr:full":"Calle de Campanario, 2 Donostia-san Sebastian Guip\u00f9zcoa 20003",
    "addr:housenumber":"2",
    "addr:postcode":"20003",
    "addr:street":"Calle De Campanario",
    "iso:country":"ES",
    "sg:address":"Calle de Campanario, 2",
    "sg:city":"Donostia-san Sebastian",
    "sg:orig_category":"Centros De Educaci\u00d3n Especial",
    "sg:phone":"+34 943 42 95 22",
    "sg:postcode":"20003",
    "sg:province":"Guip\u00f9zcoa",
    "wof:name":"Asociacion Cultural Recreativa Orixe",
    "wof:placetype":"venue"
},
  "geometry": {"coordinates":[-1.9865722656,43.3227272034],"type":"Point"}
}