{
  "type": "Feature",
  "properties": {
    "addr:full":"Avda General Franco, 7 Santa Uxia De Ribeira La Coru\u00f1a 15960",
    "addr:housenumber":"7",
    "addr:postcode":"15960",
    "addr:street":"Avda General Franco;Corun\u0303A",
    "iso:country":"ES",
    "sg:address":"Avda General Franco, 7",
    "sg:city":"Santa Uxia De Ribeira",
    "sg:orig_category":"Bancos",
    "sg:phone":"+34 981 87 01 44",
    "sg:postcode":"15960",
    "sg:province":"La Coru\u00f1a",
    "wof:name":"Banco Gallego S.a.",
    "wof:placetype":"venue"
},
  "geometry": {"coordinates":[-8.9913682938,42.55493927],"type":"Point"}
}