{
  "type": "Feature",
  "properties": {
    "addr:full":"Afores, S/n Masquefa Barcelona 08783",
    "addr:housenumber":"s / n",
    "addr:postcode":"08783",
    "addr:street":"Afores",
    "iso:country":"ES",
    "sg:address":"Afores, S/n",
    "sg:city":"Masquefa",
    "sg:orig_category":"Agricultores, Agricultores",
    "sg:phone":"+34 937 72 87 08",
    "sg:postcode":"08783",
    "sg:province":"Barcelona",
    "sg:website":"www.affinity-petcare.com",
    "wof:name":"Affinity Petcare S.a.",
    "wof:placetype":"venue"
},
  "geometry": {"coordinates":[1.8025852442,41.4972038269],"type":"Point"}
}