{
  "type": "Feature",
  "properties": {
    "iso:country":"ES",
    "sg:address":"Av. Da Praia(pol. Sabon), 142",
    "sg:city":"Arteixo",
    "sg:orig_category":"Confecci\u00d3n De Trajes Para Se\u00d1oras",
    "sg:phone":"+34 981 60 18 16",
    "sg:postcode":"15141",
    "sg:province":"La Coru\u00f1a",
    "wof:name":"Carros 2005 S.l.",
    "wof:placetype":"venue"
},
  "geometry": {"coordinates":[-8.4798288345,43.3172454834],"type":"Point"}
}