{
  "type": "Feature",
  "properties": {
    "iso:country":"ES",
    "sg:address":"Plaz Gonzalo De Ayora (de), 2",
    "sg:city":"Cordoba",
    "sg:orig_category":"Cl\u00cdnicas Dentales",
    "sg:phone":"+34 957 47 97 37",
    "sg:postcode":"14001",
    "sg:province":"C\u00f3rdoba",
    "wof:name":"Anaya Henares Eduardo",
    "wof:placetype":"venue"
},
  "geometry": {"coordinates":[-4.7769255638,37.8897323608],"type":"Point"}
}