{
  "type": "Feature",
  "properties": {
    "addr:full":"Calle de Campoamor, 29 Oviedo Asturias 33001",
    "addr:housenumber":"29",
    "addr:postcode":"33001",
    "addr:street":"Calle De Campoamor",
    "iso:country":"ES",
    "sg:address":"Calle de Campoamor, 29",
    "sg:city":"Oviedo",
    "sg:orig_category":"Tapiceros Y Tapiceros",
    "sg:phone":"+34 985 22 27 73",
    "sg:postcode":"33001",
    "sg:province":"Asturias",
    "sg:website":"www.ssai.es",
    "wof:name":"Sistemas Y Servicios De Arquitectura Interior S.l.",
    "wof:placetype":"venue"
},
  "geometry": {"coordinates":[-5.8538188934,43.3662605286],"type":"Point"}
}