{
  "type": "Feature",
  "properties": {
    "iso:country":"ES",
    "sg:address":"Calle de Diego Mazquiaran, 1",
    "sg:city":"Sestao",
    "sg:orig_category":"Comercio De Cuadros, L\u00c1minas Y Reproducciones De Obras De Arte",
    "sg:phone":"+34 944 96 16 25",
    "sg:postcode":"48910",
    "sg:province":"Vizcaya",
    "wof:name":"Lozano Valenzuela Eladio",
    "wof:placetype":"venue"
},
  "geometry": {"coordinates":[-3.0046570301,43.3099479675],"type":"Point"}
}