{
  "type": "Feature",
  "properties": {
    "iso:country":"ES",
    "sg:address":"Avda Feira (da), 3",
    "sg:city":"Pontenova",
    "sg:orig_category":"Quincaller\u00cda (al Por Menor)",
    "sg:phone":"+34 982 34 20 19",
    "sg:postcode":"27720",
    "sg:province":"Lugo",
    "wof:name":"Diaz Freijo Ramon",
    "wof:placetype":"venue"
},
  "geometry": {"coordinates":[-7.1766328812,43.3744239807],"type":"Point"}
}