{
  "type": "Feature",
  "properties": {
    "addr:full":"Calle de Burgo Nuevo, 24 Le\u00f3n Le\u00f3n 24001",
    "addr:housenumber":"24",
    "addr:postcode":"24001",
    "addr:street":"Calle De Burgo Nuevo;Leo\u0301N",
    "iso:country":"ES",
    "sg:address":"Calle de Burgo Nuevo, 24",
    "sg:city":"Le\u00f3n",
    "sg:orig_category":"Sociedades, Compa\u00d1\u00cdas Aseguradoras",
    "sg:phone":"+34 987 20 47 74",
    "sg:postcode":"24001",
    "sg:province":"Le\u00f3n",
    "wof:name":"Martinez Rodriguez Maria Carmen",
    "wof:placetype":"venue"
},
  "geometry": {"coordinates":[-5.5730609894,42.5965118408],"type":"Point"}
}