{
  "type": "Feature",
  "properties": {
    "iso:country":"ES",
    "sg:address":"Rbla Bentacayse, S/n",
    "sg:city":"A\u00d1aza",
    "sg:orig_category":"Agencias De Viajes",
    "sg:phone":"+34 922 68 62 33",
    "sg:postcode":"38111",
    "sg:province":"Santa Cruz De Tenerife",
    "sg:website":"www.halconviajes.com",
    "wof:name":"Viajes Halcon S.a.",
    "wof:placetype":"venue"
},
  "geometry": {"coordinates":[-16.3000564575,28.4232654572],"type":"Point"}
}