{
  "type": "Feature",
  "properties": {
    "iso:country":"ES",
    "sg:address":"Calle de Nicolas Salmeron, 10",
    "sg:city":"Valladolid",
    "sg:orig_category":"Colchones (fabricaci\u00d3n, Al Por Mayor, Al Por Menor)",
    "sg:phone":"+34 983 39 04 09",
    "sg:postcode":"47004",
    "sg:province":"Valladolid",
    "sg:website":"www.noctalia.es",
    "wof:name":"Noctalia",
    "wof:placetype":"venue"
},
  "geometry": {"coordinates":[-4.7213039398,41.6458473206],"type":"Point"}
}