{
  "type": "Feature",
  "properties": {
    "iso:country":"ES",
    "sg:address":"Calle de Malague\u00d1as, 24",
    "sg:city":"Palmas De Gran Canaria",
    "sg:orig_category":"Transporte En General",
    "sg:phone":"+34 928 31 50 40",
    "sg:postcode":"35015",
    "sg:province":"Las Palmas",
    "wof:name":"Suarez Deniz Antonio",
    "wof:placetype":"venue"
},
  "geometry": {"coordinates":[-15.4276332855,28.0982589722],"type":"Point"}
}