{
  "type": "Feature",
  "properties": {
    "iso:country":"ES",
    "sg:address":"Carr Baltasar Palmero, 3",
    "sg:city":"Turis",
    "sg:orig_category":"Maquinaria Para Industrias Diversas",
    "sg:phone":"+34 962 52 64 23",
    "sg:postcode":"46389",
    "sg:province":"Valencia",
    "wof:name":"Guaita Almonacil Antonio Jose",
    "wof:placetype":"venue"
},
  "geometry": {"coordinates":[-0.7180141211,39.3900756836],"type":"Point"}
}