{
  "type": "Feature",
  "properties": {
    "addr:full":"Av Pais Valencia, 7 Alfas Pi Alicante 03580",
    "addr:housenumber":"7",
    "addr:postcode":"03580",
    "addr:street":"Av Pais Valencia",
    "iso:country":"ES",
    "sg:address":"Av Pais Valencia, 7",
    "sg:city":"Alfas Pi",
    "sg:orig_category":"Juegos Y Juguetes (al Por Menor)",
    "sg:phone":"+34 966 86 06 91",
    "sg:postcode":"03580",
    "sg:province":"Alicante",
    "wof:name":"Don Dino Levante Sl",
    "wof:placetype":"venue"
},
  "geometry": {"coordinates":[-0.1012490019,38.5771141052],"type":"Point"}
}