{
  "type": "Feature",
  "properties": {
    "addr:full":"Calle de Arrasate, 45 Donostia-san Sebastian Guip\u00f9zcoa 20005",
    "addr:housenumber":"45",
    "addr:postcode":"20005",
    "addr:street":"Calle De Arrasate",
    "iso:country":"ES",
    "sg:address":"Calle de Arrasate, 45",
    "sg:city":"Donostia-san Sebastian",
    "sg:orig_category":"Fabricaci\u00d3n De Papel Para Embalar",
    "sg:phone":"+34 943 42 25 13",
    "sg:postcode":"20005",
    "sg:province":"Guip\u00f9zcoa",
    "wof:name":"Tampel S.l.",
    "wof:placetype":"venue"
},
  "geometry": {"coordinates":[-1.9837379456,43.317276001],"type":"Point"}
}