{
  "type": "Feature",
  "properties": {
    "addr:full":"Cid, 6 Castalla Alicante 03420",
    "addr:housenumber":"6",
    "addr:postcode":"03420",
    "addr:street":"Cid",
    "iso:country":"ES",
    "sg:address":"Cid, 6",
    "sg:city":"Castalla",
    "sg:orig_category":"Agencias Y Agentes Comerciales, Representantes",
    "sg:phone":"+34 966 56 07 63",
    "sg:postcode":"03420",
    "sg:province":"Alicante",
    "wof:name":"Corda Inuc S.l.",
    "wof:placetype":"venue"
},
  "geometry": {"coordinates":[-0.6746739745,38.5921287537],"type":"Point"}
}