{
  "type": "Feature",
  "properties": {
    "addr:full":"Calle de Cristo Agonias, 4 Alhaurin El Grande M\u00e1laga 29120",
    "addr:housenumber":"4",
    "addr:postcode":"29120",
    "addr:street":"Calle De Cristo Agonias",
    "iso:country":"ES",
    "sg:address":"Calle de Cristo Agonias, 4",
    "sg:city":"Alhaurin El Grande",
    "sg:orig_category":"Muebles, Minoristas",
    "sg:phone":"+34 952 59 51 87",
    "sg:postcode":"29120",
    "sg:province":"M\u00e1laga",
    "wof:name":"Watkinson  Jess",
    "wof:placetype":"venue"
},
  "geometry": {"coordinates":[-4.684568882,36.6446037292],"type":"Point"}
}