{
  "type": "Feature",
  "properties": {
    "addr:full":"Av Generalitat, S/n Falset Tarragona 43730",
    "addr:housenumber":"s / n",
    "addr:postcode":"43730",
    "addr:street":"Av Generalitat",
    "iso:country":"ES",
    "sg:address":"Av Generalitat, S/n",
    "sg:city":"Falset",
    "sg:orig_category":"Restaurantes",
    "sg:phone":"+34 977 83 10 42",
    "sg:postcode":"43730",
    "sg:province":"Tarragona",
    "wof:name":"Pi Munter Enric",
    "wof:placetype":"venue"
},
  "geometry": {"coordinates":[0.8189809918,41.1432876587],"type":"Point"}
}