{
  "type": "Feature",
  "properties": {
    "addr:full":"Calle de Marques De Villamagna, 3 Madrid Madrid 28001",
    "addr:housenumber":"3",
    "addr:postcode":"28001",
    "addr:street":"Calle De Marques De Villamagna",
    "iso:country":"ES",
    "sg:address":"Calle de Marques De Villamagna, 3",
    "sg:city":"Madrid",
    "sg:orig_category":"Inversiones",
    "sg:phone":"+34 914 31 32 67",
    "sg:postcode":"28001",
    "sg:province":"Madrid",
    "wof:name":"Inova Capital Scr S.a.",
    "wof:placetype":"venue"
},
  "geometry": {"coordinates":[-3.6883780956,40.4292068481],"type":"Point"}
}