{
  "type": "Feature",
  "properties": {
    "iso:country":"ES",
    "sg:address":"Abetos, 7",
    "sg:city":"Chaparral",
    "sg:orig_category":"Centros De Coordinaci\u00d3n",
    "sg:phone":"+34 958 53 73 26",
    "sg:postcode":"18290",
    "sg:province":"Granada",
    "wof:name":"Roca Fernandez Eugenia",
    "wof:placetype":"venue"
},
  "geometry": {"coordinates":[-3.620634079,37.2736816406],"type":"Point"}
}