{
  "type": "Feature",
  "properties": {
    "addr:full":"Carrer de Girona, 3 Mataro Barcelona 08303",
    "addr:housenumber":"3",
    "addr:postcode":"08303",
    "addr:street":"Carrer De Girona",
    "iso:country":"ES",
    "sg:address":"Carrer de Girona, 3",
    "sg:city":"Mataro",
    "sg:orig_category":"Fabricaci\u00d3n De Telas Y Sedas",
    "sg:phone":"+34 937 57 99 86",
    "sg:postcode":"08303",
    "sg:province":"Barcelona",
    "wof:name":"Gudiel Rebollo Fernando",
    "wof:placetype":"venue"
},
  "geometry": {"coordinates":[2.4240980148,41.5437202454],"type":"Point"}
}