{
  "type": "Feature",
  "properties": {
    "addr:full":"Urb Oasis, 14 Alfas Pi Alicante 03580",
    "addr:housenumber":"14",
    "addr:postcode":"03580",
    "addr:street":"Urb Oasis",
    "iso:country":"ES",
    "sg:address":"Urb Oasis, 14",
    "sg:city":"Alfas Pi",
    "sg:orig_category":"Internados & Ense\u00d1anza Privada",
    "sg:phone":"+34 965 88 77 67",
    "sg:postcode":"03580",
    "sg:province":"Alicante",
    "wof:name":"Fundacion Noruega Costablanca",
    "wof:placetype":"venue"
},
  "geometry": {"coordinates":[-0.1106439978,38.5881652832],"type":"Point"}
}