{
  "type": "Feature",
  "properties": {
    "addr:full":"Calle de Maria De Molina, 34 Madrid Madrid 28006",
    "addr:housenumber":"34",
    "addr:postcode":"madrid;28006",
    "addr:street":"Calle De Maria De Molina",
    "iso:country":"ES",
    "sg:address":"Calle de Maria De Molina, 34",
    "sg:city":"Madrid",
    "sg:orig_category":"Bancos",
    "sg:phone":"+34 915 62 66 55",
    "sg:postcode":"28006",
    "sg:province":"Madrid",
    "wof:name":"Banco Popular Espa\u00d1ol S.a.",
    "wof:placetype":"venue"
},
  "geometry": {"coordinates":[-3.6839148998,40.4374771118],"type":"Point"}
}