{
  "type": "Feature",
  "properties": {
    "addr:full":"Avda Ricardo Carapeto Zambrano, 52 Badajoz Badajoz 06008",
    "addr:housenumber":"52",
    "addr:postcode":"06008",
    "addr:street":"Avda Ricardo Carapeto Zambrano",
    "iso:country":"ES",
    "sg:address":"Avda Ricardo Carapeto Zambrano, 52",
    "sg:city":"Badajoz",
    "sg:orig_category":"Peluquer\u00cdas, Peluquer\u00cda Mixta",
    "sg:phone":"+34 924 23 16 12",
    "sg:postcode":"06008",
    "sg:province":"Badajoz",
    "sg:website":"www.rizos.es",
    "wof:name":"Azuldafe S.l.",
    "wof:placetype":"venue"
},
  "geometry": {"coordinates":[-6.9584999084,38.8791007996],"type":"Point"}
}