{
  "type": "Feature",
  "properties": {
    "addr:full":"Plaz Tres Olivos, 2 Madrid Madrid 28034",
    "addr:housenumber":"2",
    "addr:postcode":"28034",
    "addr:street":"Plaz;Olivos",
    "iso:country":"ES",
    "sg:address":"Plaz Tres Olivos, 2",
    "sg:city":"Madrid",
    "sg:orig_category":"Carnicer\u00cdas, Carnicer\u00cdas",
    "sg:phone":"+34 917 34 26 64",
    "sg:postcode":"28034",
    "sg:province":"Madrid",
    "wof:name":"Productos Carnicos Alfer S.l.",
    "wof:placetype":"venue"
},
  "geometry": {"coordinates":[-3.6897859573,40.5009346008],"type":"Point"}
}