{
  "type": "Feature",
  "properties": {
    "addr:full":"Avda Juan Carlos I, 43 Ibi Alicante 03440",
    "addr:housenumber":"43",
    "addr:postcode":"03440",
    "addr:street":"Avda Juan Carlos I",
    "iso:country":"ES",
    "sg:address":"Avda Juan Carlos I, 43",
    "sg:city":"Ibi",
    "sg:orig_category":"M\u00c9dicos: Estomatolog\u00cda",
    "sg:phone":"+34 965 55 35 67",
    "sg:postcode":"03440",
    "sg:province":"Alicante",
    "wof:name":"Blanes Frances Milagros",
    "wof:placetype":"venue"
},
  "geometry": {"coordinates":[-0.5738019943,38.6229248047],"type":"Point"}
}