{
  "type": "Feature",
  "properties": {
    "addr:full":"Carrer de Coroleu, 2 Barcelona Barcelona 08030",
    "addr:housenumber":"2",
    "addr:postcode":"08030",
    "addr:street":"Carrer De Coroleu",
    "iso:country":"ES",
    "sg:address":"Carrer de Coroleu, 2",
    "sg:city":"Barcelona",
    "sg:orig_category":"Florister\u00cdas",
    "sg:phone":"+34 933 11 47 04",
    "sg:postcode":"08030",
    "sg:province":"Barcelona",
    "wof:name":"Bullo Otero Carmen",
    "wof:placetype":"venue"
},
  "geometry": {"coordinates":[2.1891400814,41.4328460693],"type":"Point"}
}