{
  "type": "Feature",
  "properties": {
    "addr:full":"Calle de Camino Viejo De Leganes, 171 Madrid Madrid 28025",
    "addr:housenumber":"171",
    "addr:postcode":"28025",
    "addr:street":"Calle De Camino Viejo De Leganes",
    "iso:country":"ES",
    "sg:address":"Calle de Camino Viejo De Leganes, 171",
    "sg:city":"Madrid",
    "sg:orig_category":"Venta, Instalaci\u00d3n De Cocinas",
    "sg:phone":"+34 915 25 32 29",
    "sg:postcode":"28025",
    "sg:province":"Madrid",
    "wof:name":"Valdelacete Del Val Agustin",
    "wof:placetype":"venue"
},
  "geometry": {"coordinates":[-3.7324419022,40.3792877197],"type":"Point"}
}