{
  "type": "Feature",
  "properties": {
    "iso:country":"ES",
    "sg:address":"Avda Industria (de La), 60",
    "sg:city":"Tres Cantos",
    "sg:orig_category":"Asesor\u00cda Fiscal Y Jur\u00cddica",
    "sg:phone":"+34 918 06 00 30",
    "sg:postcode":"28760",
    "sg:province":"Madrid",
    "wof:name":"Alsa Metropolitana S.a.u.",
    "wof:placetype":"venue"
},
  "geometry": {"coordinates":[-3.7039396763,40.6151504517],"type":"Point"}
}