{
  "type": "Feature",
  "properties": {
    "iso:country":"ES",
    "sg:address":"Calle de San Pedro (tagle), 8",
    "sg:city":"Tagle",
    "sg:orig_category":"Locales Y Clases De Danza",
    "sg:phone":"+34 942 81 15 29",
    "sg:postcode":"39360",
    "sg:province":"Cantabria",
    "wof:name":"Cuesta Torralba Jose Antonio",
    "wof:placetype":"venue"
},
  "geometry": {"coordinates":[-4.0760388374,43.4248085022],"type":"Point"}
}