{
  "type": "Feature",
  "properties": {
    "addr:full":"Pl San Agustin, 1 Estella Navarra 31200",
    "addr:housenumber":"1",
    "addr:postcode":"31200",
    "addr:street":"Pl San Agustin",
    "iso:country":"ES",
    "sg:address":"Pl San Agustin, 1",
    "sg:city":"Estella",
    "sg:orig_category":"Pompas F\u00danebres, Inhumaciones Y Cremaciones",
    "sg:phone":"+34 948 55 04 76",
    "sg:postcode":"31200",
    "sg:province":"Navarra",
    "wof:name":"Tanatorio Y Funeraria San Agustin S.l.",
    "wof:placetype":"venue"
},
  "geometry": {"coordinates":[-2.0254120827,42.6706085205],"type":"Point"}
}