{
  "type": "Feature",
  "properties": {
    "addr:full":"Avda Ntra Sra Rosario, 3 Navahermosa Toledo 45150",
    "addr:housenumber":"3",
    "addr:postcode":"45150",
    "addr:street":"Avda Ntra Sra Rosario",
    "iso:country":"ES",
    "sg:address":"Avda Ntra Sra Rosario, 3",
    "sg:city":"Navahermosa",
    "sg:orig_category":"Caf\u00c9s, Bares, Cervecer\u00cdas",
    "sg:phone":"+34 925 42 84 01",
    "sg:postcode":"45150",
    "sg:province":"Toledo",
    "wof:name":"Cytasa Comunicaciones S.l.",
    "wof:placetype":"venue"
},
  "geometry": {"coordinates":[-4.469440937,39.6354255676],"type":"Point"}
}