{
  "type": "Feature",
  "properties": {
    "addr:full":"Calle de Pintor Matheu, 6 Ubrique C\u00e1diz 11600",
    "addr:housenumber":"6",
    "addr:postcode":"11600",
    "addr:street":"Calle De Pintor Matheu;Ca\u0301Diz",
    "iso:country":"ES",
    "sg:address":"Calle de Pintor Matheu, 6",
    "sg:city":"Ubrique",
    "sg:orig_category":"Maquinaria Para Industrias Diversas",
    "sg:phone":"+34 956 46 05 01",
    "sg:postcode":"11600",
    "sg:province":"C\u00e1diz",
    "wof:name":"Villalba Rodriguez Dolores",
    "wof:placetype":"venue"
},
  "geometry": {"coordinates":[-5.4467887878,36.6790084839],"type":"Point"}
}