{
  "type": "Feature",
  "properties": {
    "iso:country":"ES",
    "sg:address":"Calle de Lisa, 14",
    "sg:city":"Punta Umbria",
    "sg:orig_category":"M\u00c9dicos: Estomatolog\u00cda",
    "sg:phone":"+34 959 31 09 08",
    "sg:postcode":"21100",
    "sg:province":"Huelva",
    "wof:name":"Plaza Cascon Jose Luis",
    "wof:placetype":"venue"
},
  "geometry": {"coordinates":[-6.9666171074,37.1818847656],"type":"Point"}
}