{
  "type": "Feature",
  "properties": {
    "addr:full":"Avda Mejico, 24 Mieres Asturias 33600",
    "addr:housenumber":"24",
    "addr:postcode":"33600",
    "addr:street":"Avda Mejico",
    "iso:country":"ES",
    "sg:address":"Avda Mejico, 24",
    "sg:city":"Mieres",
    "sg:orig_category":"Supermercados Y Hipermercados",
    "sg:phone":"+34 985 45 60 49",
    "sg:postcode":"33600",
    "sg:province":"Asturias",
    "wof:name":"Merkaprecio S.a.",
    "wof:placetype":"venue"
},
  "geometry": {"coordinates":[-5.7795238495,43.254825592],"type":"Point"}
}