{
  "type": "Feature",
  "properties": {
    "addr:full":"Calle de Constitucion, 5 Valladolid Valladolid 47001",
    "addr:housenumber":"5",
    "addr:postcode":"47001",
    "addr:street":"Calle De Constitucion",
    "iso:country":"ES",
    "sg:address":"Calle de Constitucion, 5",
    "sg:city":"Valladolid",
    "sg:orig_category":"Agencias Y Agentes Comerciales, Representantes",
    "sg:phone":"+34 983 34 40 99",
    "sg:postcode":"47001",
    "sg:province":"Valladolid",
    "wof:name":"Blanco Cerron Miguel Angel",
    "wof:placetype":"venue"
},
  "geometry": {"coordinates":[-4.727891922,41.6511535645],"type":"Point"}
}