{
  "type": "Feature",
  "properties": {
    "iso:country":"ES",
    "sg:address":"Ctro Cial Alcampo, S/n",
    "sg:city":"Son Ramonell Nou",
    "sg:orig_category":"Fabricaci\u00d3n, Importaci\u00d3n, Venta De Material De Telefon\u00cda, Peritelefon\u00cda",
    "sg:phone":"+34 971 22 65 99",
    "sg:postcode":"07141",
    "sg:province":"Islas Baleares",
    "wof:name":"Bt Espa\u00d1a Compa\u00d1ia De Servicios Globales De Telecomunicaciones S.a.u.",
    "wof:placetype":"venue"
},
  "geometry": {"coordinates":[2.7445349693,39.6195487976],"type":"Point"}
}