{
  "type": "Feature",
  "properties": {
    "addr:full":"Av Vidal I Barraquer, 23 Cambrils Tarragona 43850",
    "addr:housenumber":"23",
    "addr:postcode":"43850",
    "addr:street":"Av Vidal I Barraquer",
    "iso:country":"ES",
    "sg:address":"Av Vidal I Barraquer, 23",
    "sg:city":"Cambrils",
    "sg:orig_category":"Electrodom\u00c9sticos (al Por Menor)",
    "sg:phone":"+34 977 36 06 72",
    "sg:postcode":"43850",
    "sg:province":"Tarragona",
    "wof:name":"Guell Esteve Jose Maria",
    "wof:placetype":"venue"
},
  "geometry": {"coordinates":[1.0526180267,41.0701789856],"type":"Point"}
}