{
  "type": "Feature",
  "properties": {
    "addr:full":"Calle de Sor Concepcion Suarez, 3 S.gregorio Las Palmas 35200",
    "addr:housenumber":"3",
    "addr:postcode":"35200",
    "addr:street":"Calle De Sor Concepcion Suarez;Las Palmas",
    "iso:country":"ES",
    "sg:address":"Calle de Sor Concepcion Suarez, 3",
    "sg:city":"S.gregorio",
    "sg:orig_category":"Consultas M\u00c9dicas",
    "sg:phone":"+34 928 69 23 27",
    "sg:postcode":"35200",
    "sg:province":"Las Palmas",
    "wof:name":"Centro Reconocimientos Medicos Telde S.l.",
    "wof:placetype":"venue"
},
  "geometry": {"coordinates":[-15.4144220352,28.0029888153],"type":"Point"}
}