{
  "type": "Feature",
  "properties": {
    "iso:country":"ES",
    "sg:address":"Calle de Guatifay, 5",
    "sg:city":"Arrecife",
    "sg:orig_category":"Abogados",
    "sg:phone":"+34 928 80 21 32",
    "sg:postcode":"35500",
    "sg:province":"Las Palmas",
    "wof:name":"Gobierno De Canarias",
    "wof:placetype":"venue"
},
  "geometry": {"coordinates":[-13.5478916168,28.9602489471],"type":"Point"}
}