{
  "type": "Feature",
  "properties": {
    "addr:full":"Avda Milagros (dos), 28 Maceda Ourense 32700",
    "addr:housenumber":"28",
    "addr:postcode":"32700",
    "addr:street":"Avda Milagros Dos",
    "iso:country":"ES",
    "sg:address":"Avda Milagros (dos), 28",
    "sg:city":"Maceda",
    "sg:orig_category":"Molduras, Junquillos, Listones Y Molduras Perforadas",
    "sg:phone":"+34 988 46 33 11",
    "sg:postcode":"32700",
    "sg:province":"Ourense",
    "wof:name":"Rivas Rodriguez Eladio",
    "wof:placetype":"venue"
},
  "geometry": {"coordinates":[-7.6499590874,42.266292572],"type":"Point"}
}