{
  "type": "Feature",
  "properties": {
    "addr:full":"Calle de Maria Cristina, 8 Novelda Alicante 03660",
    "addr:housenumber":"8",
    "addr:postcode":"03660",
    "addr:street":"Calle De Maria Cristina",
    "iso:country":"ES",
    "sg:address":"Calle de Maria Cristina, 8",
    "sg:city":"Novelda",
    "sg:orig_category":"Veh\u00cdculos De Ocasi\u00d3n",
    "sg:phone":"+34 965 60 66 23",
    "sg:postcode":"03660",
    "sg:province":"Alicante",
    "wof:name":"Jesus Amoros Segura S.l.",
    "wof:placetype":"venue"
},
  "geometry": {"coordinates":[-0.7699890137,38.3804626465],"type":"Point"}
}