{
  "type": "Feature",
  "properties": {
    "addr:full":"Rbla Bobiles, 3 Martorell Barcelona 08760",
    "addr:housenumber":"3",
    "addr:postcode":"08760",
    "addr:street":"Rbla Bobiles",
    "iso:country":"ES",
    "sg:address":"Rbla Bobiles, 3",
    "sg:city":"Martorell",
    "sg:classifiers":[
        {
            "category":"Autos & Motor Vehicles",
            "subcategory":"Automobile Sales",
            "type":"Retail Goods"
        }
    ],
    "sg:phone":"+34 937 73 53 61",
    "sg:postcode":"08760",
    "sg:province":"Barcelona",
    "sg:website":"www.autoescolanova.com",
    "wof:name":"Salinas Bosch Jose",
    "wof:placetype":"venue"
},
  "geometry": {"coordinates":[1.9169800282,41.4771957397],"type":"Point"}
}