{
  "type": "Feature",
  "properties": {
    "addr:full":"Calle de Lopez De Hoyos, 123 Madrid Madrid 28002",
    "addr:housenumber":"123",
    "addr:postcode":"28002",
    "addr:street":"Calle De Lopez De Hoyos",
    "iso:country":"ES",
    "sg:address":"Calle de Lopez De Hoyos, 123",
    "sg:city":"Madrid",
    "sg:orig_category":"Centros Empresariales",
    "sg:phone":"+34 914 16 84 22",
    "sg:postcode":"28002",
    "sg:province":"Madrid",
    "wof:name":"Helma Baumaschinen S.l.",
    "wof:placetype":"venue"
},
  "geometry": {"coordinates":[-3.6711249352,40.4462966919],"type":"Point"}
}