{
  "type": "Feature",
  "properties": {
    "iso:country":"ES",
    "sg:address":"Calle de General Franco, 1",
    "sg:city":"Melgar De Yuso",
    "sg:orig_category":"Centros De Educaci\u00d3n Especial",
    "sg:phone":"+34 979 15 18 29",
    "sg:postcode":"34458",
    "sg:province":"Palencia",
    "wof:name":"Ayuntamiento De Melgar De Yuso",
    "wof:placetype":"venue"
},
  "geometry": {"coordinates":[-4.2527532578,42.2530136108],"type":"Point"}
}