{
  "type": "Feature",
  "properties": {
    "addr:full":"Av Sant Esteve, 67 Castellar Valles Barcelona 08211",
    "addr:housenumber":"67",
    "addr:postcode":"08211",
    "addr:street":"Av Sant Esteve",
    "iso:country":"ES",
    "sg:address":"Av Sant Esteve, 67",
    "sg:city":"Castellar Valles",
    "sg:orig_category":"Ropa Para Caballeros (al Por Menor)",
    "sg:phone":"+34 937 15 89 61",
    "sg:postcode":"08211",
    "sg:province":"Barcelona",
    "wof:name":"Marin Segarra Ana",
    "wof:placetype":"venue"
},
  "geometry": {"coordinates":[2.0900480747,41.6152305603],"type":"Point"}
}