{
  "type": "Feature",
  "properties": {
    "iso:country":"ES",
    "sg:address":"Calle de Tellos, 13",
    "sg:city":"Corral Almaguer",
    "sg:orig_category":"Promotores Constructores",
    "sg:phone":"+34 925 19 07 47",
    "sg:postcode":"45880",
    "sg:province":"Toledo",
    "wof:name":"Real Manche\u00f1o Eugenio",
    "wof:placetype":"venue"
},
  "geometry": {"coordinates":[-3.1666710377,39.7570953369],"type":"Point"}
}