{
  "type": "Feature",
  "properties": {
    "iso:country":"ES",
    "sg:address":"Cra. Calaf, S/n",
    "sg:city":"S. Joan Vilatorrada",
    "sg:orig_category":"Polideportivos",
    "sg:phone":"+34 938 76 40 67",
    "sg:postcode":"08250",
    "sg:province":"Barcelona",
    "wof:name":"Ajuntament De Sant Joan De Vilatorrada",
    "wof:placetype":"venue"
},
  "geometry": {"coordinates":[1.7594095469,41.7557182312],"type":"Point"}
}