{
  "type": "Feature",
  "properties": {
    "iso:country":"ES",
    "sg:address":"Carrer de Bassegoda, 6",
    "sg:city":"Barcelona",
    "sg:orig_category":"Peluquer\u00cdas, Peluquer\u00cda Mixta",
    "sg:phone":"+34 934 48 13 76",
    "sg:postcode":"08028",
    "sg:province":"Barcelona",
    "wof:name":"Querol Puchercos Carolina",
    "wof:placetype":"venue"
},
  "geometry": {"coordinates":[2.1259279251,41.3753967285],"type":"Point"}
}