{
  "type": "Feature",
  "properties": {
    "iso:country":"ES",
    "sg:address":"Av Carrilet, 125",
    "sg:city":"Hospitalet Llobregat",
    "sg:orig_category":"Molduras, Junquillos, Listones Y Molduras Perforadas",
    "sg:phone":"+34 934 22 02 20",
    "sg:postcode":"08902",
    "sg:province":"Barcelona",
    "wof:name":"Cordero Pizarro Vicente",
    "wof:placetype":"venue"
},
  "geometry": {"coordinates":[2.1216669083,41.3647041321],"type":"Point"}
}