{
  "type": "Feature",
  "properties": {
    "iso:country":"ES",
    "sg:address":"Valle Moro, 2",
    "sg:city":"Lomas",
    "sg:orig_category":"Ense\u00d1anza, Formaci\u00d3n Profesional: Aprendizaje",
    "sg:phone":"+34 916 33 43 75",
    "sg:postcode":"28669",
    "sg:province":"Madrid",
    "wof:name":"Ayuntamiento De Boadilla Del Monte",
    "wof:placetype":"venue"
},
  "geometry": {"coordinates":[-3.9006915092,40.4231338501],"type":"Point"}
}