{
  "type": "Feature",
  "properties": {
    "addr:full":"Carrer de Toledo-valmojado, S/n Camarenilla Toledo 45181",
    "addr:housenumber":"s",
    "addr:postcode":"45181",
    "addr:street":"Carrer De Toledo-Valmojado;/ N Camarenilla",
    "iso:country":"ES",
    "sg:address":"Carrer de Toledo-valmojado, S/n",
    "sg:city":"Camarenilla",
    "sg:orig_category":"Suministros Para Carrocer\u00cdas",
    "sg:phone":"+34 925 35 90 03",
    "sg:postcode":"45181",
    "sg:province":"Toledo",
    "wof:name":"Carrocerias Los Toledanos S.c.l.",
    "wof:placetype":"venue"
},
  "geometry": {"coordinates":[-4.0711340904,40.016746521],"type":"Point"}
}