{
  "type": "Feature",
  "properties": {
    "addr:full":"Traverti(zo. Ind. Melianta), S/n Fontcoberta Girona 17833",
    "addr:housenumber":"/ n",
    "addr:postcode":"17833",
    "addr:street":"Ind.;S",
    "iso:country":"ES",
    "sg:address":"Traverti(zo. Ind. Melianta), S/n",
    "sg:city":"Fontcoberta",
    "sg:orig_category":"Rectificaci\u00d3n, Mecanizado, Fresado",
    "sg:phone":"+34 972 58 13 70",
    "sg:postcode":"17833",
    "sg:province":"Girona",
    "wof:name":"Isnac S.l.",
    "wof:placetype":"venue"
},
  "geometry": {"coordinates":[2.7688651085,42.1472244263],"type":"Point"}
}