{
  "type": "Feature",
  "properties": {
    "addr:full":"Carrer de Sant Antoni, 21 Maspujols Tarragona 43382",
    "addr:housenumber":"21",
    "addr:postcode":"43382",
    "addr:street":"Carrer De Sant Antoni",
    "iso:country":"ES",
    "sg:address":"Carrer de Sant Antoni, 21",
    "sg:city":"Maspujols",
    "sg:orig_category":"Cooperativas Agr\u00cdcolas",
    "sg:phone":"+34 977 81 50 09",
    "sg:postcode":"43382",
    "sg:province":"Tarragona",
    "wof:name":"Sociedad Cooperativa Agricola Y Caja Rural San Isidro",
    "wof:placetype":"venue"
},
  "geometry": {"coordinates":[1.0446490049,41.1821746826],"type":"Point"}
}