{
  "type": "Feature",
  "properties": {
    "iso:country":"ES",
    "sg:address":"Calle de Pino, 22",
    "sg:city":"Montemayor Rio",
    "sg:orig_category":"Transportes Por V\u00cdas Navegables",
    "sg:phone":"+34 923 43 11 55",
    "sg:postcode":"37727",
    "sg:province":"Salamanca",
    "wof:name":"Barragan Tostado Lorenzo",
    "wof:placetype":"venue"
},
  "geometry": {"coordinates":[-5.8931589127,40.3480300903],"type":"Point"}
}