{
  "type": "Feature",
  "properties": {
    "iso:country":"ES",
    "sg:address":"Praz Toural (do), 16",
    "sg:city":"Vilar De Barrio",
    "sg:orig_category":"Distribuci\u00d3n De Petr\u00d3leo Y Derivados",
    "sg:phone":"+34 988 46 83 85",
    "sg:postcode":"32702",
    "sg:province":"Ourense",
    "wof:name":"Dapia Prieto Pilar",
    "wof:placetype":"venue"
},
  "geometry": {"coordinates":[-7.6092882156,42.1607093811],"type":"Point"}
}