{
  "type": "Feature",
  "properties": {
    "addr:full":"Carrer de Alp, 25 Calafell-park Tarragona 43820",
    "addr:housenumber":"25",
    "addr:postcode":"43820",
    "addr:street":"Carrer De Alp",
    "iso:country":"ES",
    "sg:address":"Carrer de Alp, 25",
    "sg:city":"Calafell-park",
    "sg:orig_category":"Tapicer\u00cdas",
    "sg:phone":"+34 977 69 41 32",
    "sg:postcode":"43820",
    "sg:province":"Tarragona",
    "wof:name":"Ruiz Ochoa Antonio",
    "wof:placetype":"venue"
},
  "geometry": {"coordinates":[1.5935360193,41.2249488831],"type":"Point"}
}