{
  "type": "Feature",
  "properties": {
    "addr:full":"Carrer de Navas De Tolosa, 355 Barcelona Barcelona 08041",
    "addr:housenumber":"355",
    "addr:postcode":"08041",
    "addr:street":"Carrer De Navas De Tolosa",
    "iso:country":"ES",
    "sg:address":"Carrer de Navas De Tolosa, 355",
    "sg:city":"Barcelona",
    "sg:orig_category":"Supermercados Y Hipermercados",
    "sg:phone":"+34 932 43 01 31",
    "sg:postcode":"08041",
    "sg:province":"Barcelona",
    "sg:website":"www.condis.es",
    "wof:name":"Cs Establiments De Proximitat S.l.",
    "wof:placetype":"venue"
},
  "geometry": {"coordinates":[2.1830689907,41.4179992676],"type":"Point"}
}