{
  "type": "Feature",
  "properties": {
    "iso:country":"ES",
    "sg:address":"Calle de Uria, 62",
    "sg:city":"Oviedo",
    "sg:orig_category":"\u00d3ptica: Instrumentos (fabricaci\u00d3n)",
    "sg:phone":"+34 985 20 56 18",
    "sg:postcode":"33003",
    "sg:province":"Asturias",
    "sg:website":"www.visionlab.es",
    "wof:name":"Visionlab",
    "wof:placetype":"venue"
},
  "geometry": {"coordinates":[-5.8528904915,43.3650856018],"type":"Point"}
}