{
  "type": "Feature",
  "properties": {
    "addr:full":"Carr Major, 15 Palamos Girona 17230",
    "addr:housenumber":"15",
    "addr:postcode":"17230",
    "addr:street":"Carr Major",
    "iso:country":"ES",
    "sg:address":"Carr Major, 15",
    "sg:city":"Palamos",
    "sg:orig_category":"Ropa Para Ni\u00d1os (al Por Menor)",
    "sg:phone":"+34 972 31 59 01",
    "sg:postcode":"17230",
    "sg:province":"Girona",
    "wof:name":"Vila Pons Rosa",
    "wof:placetype":"venue"
},
  "geometry": {"coordinates":[3.1293749809,41.8477096558],"type":"Point"}
}