{
  "type": "Feature",
  "properties": {
    "iso:country":"ES",
    "sg:address":"Avda Constitucion, 104",
    "sg:city":"Cistierna",
    "sg:orig_category":"Doctores En Medicina",
    "sg:phone":"+34 987 70 14 32",
    "sg:postcode":"24800",
    "sg:province":"Le\u00f3n",
    "wof:name":"Gabriel Perez Miguel De",
    "wof:placetype":"venue"
},
  "geometry": {"coordinates":[-5.1286687851,42.8040084839],"type":"Point"}
}