{
  "type": "Feature",
  "properties": {
    "iso:country":"ES",
    "sg:address":"Calle de Calancha, 1",
    "sg:city":"Andujar",
    "sg:classifiers":[
        {
            "category":"Personal",
            "subcategory":"Barber",
            "type":"Services"
        }
    ],
    "sg:phone":"+34 953 50 10 78",
    "sg:postcode":"23740",
    "sg:province":"Ja\u00e9n",
    "sg:tags":[
        "caballeros",
        "de",
        "peluqueros"
    ],
    "wof:name":"Romera Gisbert Francisco",
    "wof:placetype":"venue"
},
  "geometry": {"coordinates":[-4.0565295219,38.0403060913],"type":"Point"}
}