{
  "type": "Feature",
  "properties": {
    "addr:full":"Carr Roca Labrador, 8 Lleida Lleida 25003",
    "addr:housenumber":"8",
    "addr:postcode":"25003",
    "addr:street":"Carr Roca Labrador",
    "iso:country":"ES",
    "sg:address":"Carr Roca Labrador, 8",
    "sg:city":"Lleida",
    "sg:orig_category":"Cobro De Pr\u00c9stamos",
    "sg:phone":"+34 902 28 05 11",
    "sg:postcode":"25003",
    "sg:province":"Lleida",
    "wof:name":"Gestimpost S.l.",
    "wof:placetype":"venue"
},
  "geometry": {"coordinates":[0.6156110168,41.6140518188],"type":"Point"}
}