{
  "type": "Feature",
  "properties": {
    "addr:full":"Pase Limonar, 29 Malaga M\u00e1laga 29016",
    "addr:housenumber":"29",
    "addr:postcode":"29016",
    "addr:street":"Limonar;Ma\u0301Laga",
    "iso:country":"ES",
    "sg:address":"Pase Limonar, 29",
    "sg:city":"Malaga",
    "sg:orig_category":"Supermercados Y Hipermercados",
    "sg:phone":"+34 952 21 72 88",
    "sg:postcode":"29016",
    "sg:province":"M\u00e1laga",
    "wof:name":"Pastor Ramos Jose Maria",
    "wof:placetype":"venue"
},
  "geometry": {"coordinates":[-4.4018688202,36.7272834778],"type":"Point"}
}