{
  "type": "Feature",
  "properties": {
    "addr:full":"Calle de Sierra De La Cabrera, 2 Arganda Madrid 28500",
    "addr:housenumber":"2",
    "addr:postcode":"28500",
    "addr:street":"Calle De Sierra De La Cabrera",
    "iso:country":"ES",
    "sg:address":"Calle de Sierra De La Cabrera, 2",
    "sg:city":"Arganda",
    "sg:orig_category":"Empresas De Operaciones Portuarias Y Elevaci\u00d3n De Mercanc\u00cdas",
    "sg:phone":"+34 918 72 01 34",
    "sg:postcode":"28500",
    "sg:province":"Madrid",
    "wof:name":"Manipulados Gava S.l.",
    "wof:placetype":"venue"
},
  "geometry": {"coordinates":[-3.481388092,40.3044586182],"type":"Point"}
}