{
  "type": "Feature",
  "properties": {
    "iso:country":"ES",
    "sg:address":"Carr Gaudi, S/n",
    "sg:city":"Solsona",
    "sg:orig_category":"Centros De Educaci\u00d3n Especial",
    "sg:phone":"+34 973 48 18 46",
    "sg:postcode":"25280",
    "sg:province":"Lleida",
    "wof:name":"Ajuntament De Solsona",
    "wof:placetype":"venue"
},
  "geometry": {"coordinates":[1.5126821995,41.9958000183],"type":"Point"}
}