{
  "type": "Feature",
  "properties": {
    "iso:country":"ES",
    "sg:address":"Calle de Libertad (la), 29",
    "sg:city":"Azuqueca Henares",
    "sg:orig_category":"Restaurantes",
    "sg:phone":"+34 949 26 46 74",
    "sg:postcode":"19200",
    "sg:province":"Guadalajara",
    "wof:name":"Garcia Molina Vicente",
    "wof:placetype":"venue"
},
  "geometry": {"coordinates":[-3.2620429993,40.5673828125],"type":"Point"}
}