{
  "type": "Feature",
  "properties": {
    "addr:full":"Calle de Metge Juan Insa, 8 Onda Castell\u00f3n 12200",
    "addr:housenumber":"8",
    "addr:postcode":"12200",
    "addr:street":"Calle De Metge Juan Insa;Castello\u0301N",
    "iso:country":"ES",
    "sg:address":"Calle de Metge Juan Insa, 8",
    "sg:city":"Onda",
    "sg:orig_category":"Fabricaci\u00d3n De Enlosados, Soler\u00cdas",
    "sg:phone":"+34 964 77 02 33",
    "sg:postcode":"12200",
    "sg:province":"Castell\u00f3n",
    "wof:name":"Azulejos Ruz Badenes S.l.",
    "wof:placetype":"venue"
},
  "geometry": {"coordinates":[-0.2671163082,39.9624671936],"type":"Point"}
}