{
  "type": "Feature",
  "properties": {
    "addr:full":"Calle de Eucalipto, 1 Madrid Madrid 28016",
    "addr:housenumber":"1",
    "addr:postcode":"28016",
    "addr:street":"Calle De Eucalipto",
    "iso:country":"ES",
    "sg:address":"Calle de Eucalipto, 1",
    "sg:city":"Madrid",
    "sg:orig_category":"Ropa Para Se\u00d1oras Y Caballeros (al Por Menor)",
    "sg:phone":"+34 914 15 22 12",
    "sg:postcode":"28016",
    "sg:province":"Madrid",
    "wof:name":"Cotton Moon S.l.",
    "wof:placetype":"venue"
},
  "geometry": {"coordinates":[-3.6641790867,40.4557113647],"type":"Point"}
}