{
  "type": "Feature",
  "properties": {
    "addr:full":"Calle de Rio Tormes, 11 Mostoles Madrid 28935",
    "addr:housenumber":"11",
    "addr:postcode":"28935",
    "addr:street":"Calle De Rio Tormes",
    "iso:country":"ES",
    "sg:address":"Calle de Rio Tormes, 11",
    "sg:city":"Mostoles",
    "sg:orig_category":"Peluqueros: De Se\u00d1oras",
    "sg:phone":"+34 916 47 41 84",
    "sg:postcode":"28935",
    "sg:province":"Madrid",
    "wof:name":"Peluquerias Luna S.l.",
    "wof:placetype":"venue"
},
  "geometry": {"coordinates":[-3.8770155907,40.3173599243],"type":"Point"}
}