{
  "type": "Feature",
  "properties": {
    "iso:country":"ES",
    "sg:address":"Calle de Higinio Mangas, 3",
    "sg:city":"Valladolid",
    "sg:orig_category":"Carnicer\u00cdas, Carnicer\u00cdas",
    "sg:phone":"+34 983 29 67 80",
    "sg:postcode":"47005",
    "sg:province":"Valladolid",
    "wof:name":"Mucientes Lloret Jose Angel",
    "wof:placetype":"venue"
},
  "geometry": {"coordinates":[-4.712635994,41.6505355835],"type":"Point"}
}