{
  "type": "Feature",
  "properties": {
    "iso:country":"ES",
    "sg:address":"Calle de San Torcuato, 1",
    "sg:city":"Zamora",
    "sg:orig_category":"Ropa Para Caballeros (al Por Menor)",
    "sg:phone":"+34 980 53 40 90",
    "sg:postcode":"49004",
    "sg:province":"Zamora",
    "wof:name":"Anton Olivares Angel",
    "wof:placetype":"venue"
},
  "geometry": {"coordinates":[-5.7456011772,41.5042114258],"type":"Point"}
}