{
  "type": "Feature",
  "properties": {
    "addr:full":"Calle de Marques De Figueroa, 12 Coru\u00d1a La Coru\u00f1a 15007",
    "addr:housenumber":"12",
    "addr:postcode":"15007",
    "addr:street":"Calle De Marques De Figueroa;La Corun\u0303A",
    "iso:country":"ES",
    "sg:address":"Calle de Marques De Figueroa, 12",
    "sg:city":"Coru\u00d1a",
    "sg:orig_category":"Juegos Y Juguetes (al Por Menor)",
    "sg:phone":"+34 981 15 11 14",
    "sg:postcode":"15007",
    "sg:province":"La Coru\u00f1a",
    "wof:name":"Lema Varela Maria Del Carmen",
    "wof:placetype":"venue"
},
  "geometry": {"coordinates":[-8.4077911377,43.3536643982],"type":"Point"}
}