{
  "type": "Feature",
  "properties": {
    "iso:country":"ES",
    "sg:address":"Cra Doctoral (del), 20",
    "sg:city":"Almeria",
    "sg:orig_category":"Zapatos (al Por Menor)",
    "sg:phone":"+34 950 22 93 50",
    "sg:postcode":"04006",
    "sg:province":"Almer\u00eda",
    "wof:name":"Blanes Joven S.l.",
    "wof:placetype":"venue"
},
  "geometry": {"coordinates":[-2.4467589855,36.839553833],"type":"Point"}
}