{
  "type": "Feature",
  "properties": {
    "addr:full":"Avda Hermanos Felgueroso, 1 Gijon Asturias 33205",
    "addr:housenumber":"1",
    "addr:postcode":"33205",
    "addr:street":"Avda Hermanos Felgueroso",
    "iso:country":"ES",
    "sg:address":"Avda Hermanos Felgueroso, 1",
    "sg:city":"Gijon",
    "sg:orig_category":"Art\u00cdculos De Decoraci\u00d3n",
    "sg:phone":"+34 984 39 89 95",
    "sg:postcode":"33205",
    "sg:province":"Asturias",
    "wof:name":"Raquel Lorenzo Ordo\u00f1ez",
    "wof:placetype":"venue"
},
  "geometry": {"coordinates":[-5.65812397,43.5350265503],"type":"Point"}
}