{
  "type": "Feature",
  "properties": {
    "addr:full":"Carrer de Ingeniero Mira, 21 Guardamar Segura Alicante 03140",
    "addr:housenumber":"21",
    "addr:postcode":"03140",
    "addr:street":"Carrer De Ingeniero Mira",
    "iso:country":"ES",
    "sg:address":"Carrer de Ingeniero Mira, 21",
    "sg:city":"Guardamar Segura",
    "sg:orig_category":"Heladeros",
    "sg:phone":"+34 965 72 84 58",
    "sg:postcode":"03140",
    "sg:province":"Alicante",
    "wof:name":"Hernandez Mira Juan Manuel",
    "wof:placetype":"venue"
},
  "geometry": {"coordinates":[-0.6540290117,38.086681366],"type":"Point"}
}