{
  "type": "Feature",
  "properties": {
    "addr:full":"Ctra Nacional 420(1-1), Km. 0277,0 Herencia Ciudad Real 13640",
    "addr:postcode":"13640",
    "addr:street":"Ctra Nacional 420 1-1 Km. 0277,0",
    "iso:country":"ES",
    "sg:address":"Ctra Nacional 420(1-1), Km. 0277,0",
    "sg:city":"Herencia",
    "sg:orig_category":"Materiales De Construcci\u00d3n (en General)",
    "sg:phone":"+34 926 57 00 18",
    "sg:postcode":"13640",
    "sg:province":"Ciudad Real",
    "sg:website":"www.tubyder.es",
    "wof:name":"Tubyder S. L.",
    "wof:placetype":"venue"
},
  "geometry": {"coordinates":[-3.3541069031,39.3683815002],"type":"Point"}
}