{
  "type": "Feature",
  "properties": {
    "iso:country":"ES",
    "sg:address":"Rua Huertas (de Las), 48",
    "sg:city":"Monforte De Lemos",
    "sg:orig_category":"Ropa Para Caballeros (al Por Menor)",
    "sg:phone":"+34 982 40 35 53",
    "sg:postcode":"27400",
    "sg:province":"Lugo",
    "wof:name":"Tosar Ferreiro S.l.",
    "wof:placetype":"venue"
},
  "geometry": {"coordinates":[-7.5142941475,42.5226707458],"type":"Point"}
}