{
  "type": "Feature",
  "properties": {
    "addr:full":"Carrer de Tarragona, 24 Vic Barcelona 08500",
    "addr:housenumber":"24",
    "addr:postcode":"08500",
    "addr:street":"Carrer De Tarragona",
    "iso:country":"ES",
    "sg:address":"Carrer de Tarragona, 24",
    "sg:city":"Vic",
    "sg:orig_category":"Rectificaci\u00d3n, Mecanizado, Fresado",
    "sg:phone":"+34 938 86 35 34",
    "sg:postcode":"08500",
    "sg:province":"Barcelona",
    "wof:name":"Pou Ta\u00f1a Jose",
    "wof:placetype":"venue"
},
  "geometry": {"coordinates":[2.2650659084,41.9491462708],"type":"Point"}
}