{
  "type": "Feature",
  "properties": {
    "iso:country":"ES",
    "sg:address":"Puente Romano, 35",
    "sg:city":"Cortijillos",
    "sg:orig_category":"Extinci\u00d3n De Incendios: Material Y Suministros (fabricaci\u00d3n, Al Por Mayor)",
    "sg:phone":"+34 956 62 16 35",
    "sg:postcode":"11379",
    "sg:province":"C\u00e1diz",
    "wof:name":"Vinaches S.a.",
    "wof:placetype":"venue"
},
  "geometry": {"coordinates":[-5.4411177635,36.1861877441],"type":"Point"}
}