{
  "type": "Feature",
  "properties": {
    "iso:country":"ES",
    "sg:address":"Calle de Doctor Ivorra, 46",
    "sg:city":"Sant Joan D'alacant",
    "sg:orig_category":"Abogados",
    "sg:phone":"+34 965 65 66 02",
    "sg:postcode":"03550",
    "sg:province":"Alicante",
    "wof:name":"Ayuntamiento De San Juan.",
    "wof:placetype":"venue"
},
  "geometry": {"coordinates":[-0.483047992,38.3590507507],"type":"Point"}
}