{
  "type": "Feature",
  "properties": {
    "addr:full":"Calle de Gran Canaria (de), 33 Humanes De Madrid Madrid 28970",
    "addr:postcode":"28970",
    "addr:street":"Calle De Gran",
    "iso:country":"ES",
    "sg:address":"Calle de Gran Canaria (de), 33",
    "sg:city":"Humanes De Madrid",
    "sg:orig_category":"Flores Y Plantas Naturales (al Por Mayor)",
    "sg:phone":"+34 914 92 26 80",
    "sg:postcode":"28970",
    "sg:province":"Madrid",
    "wof:name":"Pinisan S.l.",
    "wof:placetype":"venue"
},
  "geometry": {"coordinates":[-3.8150880337,40.2711906433],"type":"Point"}
}