{
  "type": "Feature",
  "properties": {
    "addr:full":"Los Marrones, 11 Covarrubias Burgos 09346",
    "addr:housenumber":"11",
    "addr:postcode":"09346",
    "addr:street":"Marrones",
    "iso:country":"ES",
    "sg:address":"Los Marrones, 11",
    "sg:city":"Covarrubias",
    "sg:orig_category":"Delegados, Agentes De Tr\u00c1nsito, Auxiliares De Transporte Internacional",
    "sg:phone":"+34 947 40 65 29",
    "sg:postcode":"09346",
    "sg:province":"Burgos",
    "wof:name":"Lopez Alonso Ricardo",
    "wof:placetype":"venue"
},
  "geometry": {"coordinates":[-3.5186479092,42.0583114624],"type":"Point"}
}