{
  "type": "Feature",
  "properties": {
    "addr:full":"Carr Urgell, 61 Balaguer Lleida 25600",
    "addr:housenumber":"61",
    "addr:postcode":"25600",
    "addr:street":"Carr Urgell",
    "iso:country":"ES",
    "sg:address":"Carr Urgell, 61",
    "sg:city":"Balaguer",
    "sg:orig_category":"Supermercados Y Hipermercados",
    "sg:phone":"+34 973 44 31 04",
    "sg:postcode":"25600",
    "sg:province":"Lleida",
    "sg:website":"www.capraboacasa.com",
    "wof:name":"Caprabo S.a.",
    "wof:placetype":"venue"
},
  "geometry": {"coordinates":[0.8071600199,41.7896003723],"type":"Point"}
}