{
  "type": "Feature",
  "properties": {
    "addr:full":"Calle de Larga, 70 Puebla Del Rio Sevilla 41130",
    "addr:housenumber":"70",
    "addr:postcode":"41130",
    "addr:street":"Calle De Larga",
    "iso:country":"ES",
    "sg:address":"Calle de Larga, 70",
    "sg:city":"Puebla Del Rio",
    "sg:orig_category":"Cajas De Ahorro",
    "sg:phone":"+34 955 77 04 69",
    "sg:postcode":"41130",
    "sg:province":"Sevilla",
    "wof:name":"Monte De Piedad Y Caja De Ahorros De Huelva Y Sevilla",
    "wof:placetype":"venue"
},
  "geometry": {"coordinates":[-6.0616579056,37.2684288025],"type":"Point"}
}