{
  "type": "Feature",
  "properties": {
    "addr:full":"Calle de Reyes Catolicos, 7 Cordoba C\u00f3rdoba 14001",
    "addr:housenumber":"7",
    "addr:postcode":"14001",
    "addr:street":"Calle De Reyes Catolicos;Co\u0301Rdoba",
    "iso:country":"ES",
    "sg:address":"Calle de Reyes Catolicos, 7",
    "sg:city":"Cordoba",
    "sg:orig_category":"Ense\u00d1anza: Comercio, Gesti\u00d3n, Inform\u00c1tica",
    "sg:phone":"+34 957 49 24 41",
    "sg:postcode":"14001",
    "sg:province":"C\u00f3rdoba",
    "wof:name":"General De Informatica De Formacion S.l.",
    "wof:placetype":"venue"
},
  "geometry": {"coordinates":[-4.7817668915,37.8891563416],"type":"Point"}
}