{
  "type": "Feature",
  "properties": {
    "addr:full":"Poli Pol.indust. El Segre, 16 Lleida Lleida 25191",
    "addr:housenumber":"16",
    "addr:postcode":"25191",
    "addr:street":"El Segre",
    "iso:country":"ES",
    "sg:address":"Poli Pol.indust. El Segre, 16",
    "sg:city":"Lleida",
    "sg:orig_category":"Autob\u00das (explotaci\u00d3n Y Servicios De)",
    "sg:phone":"+34 973 20 21 54",
    "sg:postcode":"25191",
    "sg:province":"Lleida",
    "sg:website":"www. autocarespons.com",
    "wof:name":"Autocares Pons S. L.",
    "wof:placetype":"venue"
},
  "geometry": {"coordinates":[0.6630749702,41.6341972351],"type":"Point"}
}