{
  "type": "Feature",
  "properties": {
    "addr:full":"Trva Cristo Arrigorriaga Vizcaya 48480",
    "addr:postcode":"48480",
    "addr:street":"Trva Cristo",
    "iso:country":"ES",
    "sg:address":"Trva Cristo",
    "sg:city":"Arrigorriaga",
    "sg:orig_category":"Asociaciones Y Clubs Deportivos",
    "sg:phone":"+34 946 71 23 37",
    "sg:postcode":"48480",
    "sg:province":"Vizcaya",
    "wof:name":"Club Deportivo Padura",
    "wof:placetype":"venue"
},
  "geometry": {"coordinates":[-2.8888719082,43.2068519592],"type":"Point"}
}