{
  "type": "Feature",
  "properties": {
    "addr:full":"Ctra Plasencia-soria, Km. 0360,0 Tornavacas C\u00e1ceres 10611",
    "addr:postcode":"10611",
    "addr:street":"Ctra Plasencia-Soria Km. 0360,0;Ca\u0301Ceres",
    "iso:country":"ES",
    "sg:address":"Ctra Plasencia-soria, Km. 0360,0",
    "sg:city":"Tornavacas",
    "sg:orig_category":"Frutas Y Legumbres Frescas (al Por Mayor)",
    "sg:phone":"+34 927 17 70 77",
    "sg:postcode":"10611",
    "sg:province":"C\u00e1ceres",
    "wof:name":"Fruticola Tornavaque\u00f1a Sociedad Cooperativa Limitada",
    "wof:placetype":"venue"
},
  "geometry": {"coordinates":[-5.6907949448,40.2543983459],"type":"Point"}
}