{
  "type": "Feature",
  "properties": {
    "addr:full":"Calle de Acueducto, S/n Fuente Del Rey Sevilla 41700",
    "addr:postcode":"41700",
    "addr:street":"Calle De Acueducto S / N Fuente Del",
    "iso:country":"ES",
    "sg:address":"Calle de Acueducto, S/n",
    "sg:city":"Fuente Del Rey",
    "sg:orig_category":"Mec\u00c1nico Del Autom\u00d3vil",
    "sg:phone":"+34 954 93 01 84",
    "sg:postcode":"41700",
    "sg:province":"Sevilla",
    "wof:name":"Talleres Auto-mec Isla S.l.",
    "wof:placetype":"venue"
},
  "geometry": {"coordinates":[-5.9756040573,37.3112182617],"type":"Point"}
}