{
  "type": "Feature",
  "properties": {
    "iso:country":"ES",
    "sg:address":"Calle de Reyes Catolicos, 15 D",
    "sg:city":"Vitoria-gasteiz",
    "sg:orig_category":"Venta, Instalaci\u00d3n De Calefacci\u00d3n",
    "sg:phone":"+34 945 28 29 21",
    "sg:postcode":"01013",
    "sg:province":"\u00c1lava",
    "wof:name":"Juan Santamarta Barral",
    "wof:placetype":"venue"
},
  "geometry": {"coordinates":[-2.6840889454,42.8761367798],"type":"Point"}
}