{
  "type": "Feature",
  "properties": {
    "addr:full":"Avda Alcalde Luis Uru\u00d1uela, 1 Sevilla Sevilla 41020",
    "addr:housenumber":"1",
    "addr:postcode":"41020",
    "addr:street":"Avda Alcalde Luis Urun\u0303Uela",
    "iso:country":"ES",
    "sg:address":"Avda Alcalde Luis Uru\u00d1uela, 1",
    "sg:city":"Sevilla",
    "sg:orig_category":"Asesor\u00cda Sobre Comunicaci\u00d3n De Empresas",
    "sg:phone":"+34 954 51 22 65",
    "sg:postcode":"41020",
    "sg:province":"Sevilla",
    "wof:name":"Santos Fernandez Luisa",
    "wof:placetype":"venue"
},
  "geometry": {"coordinates":[-5.9419989586,37.4018707275],"type":"Point"}
}