{
  "type": "Feature",
  "properties": {
    "addr:full":"Carrer de L'art, 84 Barcelona Barcelona 08041",
    "addr:housenumber":"84",
    "addr:postcode":"08041",
    "addr:street":"Carrer De L'Art",
    "iso:country":"ES",
    "sg:address":"Carrer de L'art, 84",
    "sg:city":"Barcelona",
    "sg:orig_category":"Agentes, Concesionarios Y Sucursales De Veh\u00cdculos",
    "sg:phone":"+34 933 47 85 53",
    "sg:postcode":"08041",
    "sg:province":"Barcelona",
    "wof:name":"Gimenez Alvarez Francesc",
    "wof:placetype":"venue"
},
  "geometry": {"coordinates":[2.1751503944,41.4193382263],"type":"Point"}
}