{
  "type": "Feature",
  "properties": {
    "iso:country":"ES",
    "sg:address":"Calle de Camino De Valladolid, S/n",
    "sg:city":"Torrelodones",
    "sg:orig_category":"Distribuci\u00d3n De Petr\u00d3leo Y Derivados",
    "sg:phone":"+34 918 59 17 53",
    "sg:postcode":"28250",
    "sg:province":"Madrid",
    "wof:name":"Unidad De Servicios Lucsan",
    "wof:placetype":"venue"
},
  "geometry": {"coordinates":[-3.9270288944,40.5745239258],"type":"Point"}
}