{
  "type": "Feature",
  "properties": {
    "iso:country":"ES",
    "sg:address":"Calle de Mariano Benlliure, 75",
    "sg:city":"Sevilla",
    "sg:orig_category":"Fabricaci\u00d3n De Peines Y De Accesorios De Peluquer\u00cda",
    "sg:phone":"+34 954 58 39 35",
    "sg:postcode":"41005",
    "sg:province":"Sevilla",
    "wof:name":"Hiper Peluqueria S.l.",
    "wof:placetype":"venue"
},
  "geometry": {"coordinates":[-5.9624800682,37.3826637268],"type":"Point"}
}