{
  "type": "Feature",
  "properties": {
    "addr:full":"Plaz Llibertat,de La, 14 Torrent Valencia 46900",
    "addr:postcode":"46900",
    "iso:country":"ES",
    "sg:address":"Plaz Llibertat,de La, 14",
    "sg:city":"Torrent",
    "sg:orig_category":"Arquitectos",
    "sg:phone":"+34 961 57 04 57",
    "sg:postcode":"46900",
    "sg:province":"Valencia",
    "wof:name":"Mu\u00f1oz Garcia Rafael",
    "wof:placetype":"venue"
},
  "geometry": {"coordinates":[-0.4623290002,39.441619873],"type":"Point"}
}