{
  "type": "Feature",
  "properties": {
    "iso:country":"ES",
    "sg:address":"Avda Andalucia, 14",
    "sg:city":"Cadiz",
    "sg:orig_category":"Peluqueros: De Se\u00d1oras",
    "sg:phone":"+34 956 25 51 05",
    "sg:postcode":"11008",
    "sg:province":"C\u00e1diz",
    "wof:name":"Gibru Spain S.l.",
    "wof:placetype":"venue"
},
  "geometry": {"coordinates":[-6.2865581512,36.5228996277],"type":"Point"}
}