{
  "type": "Feature",
  "properties": {
    "iso:country":"ES",
    "sg:address":"Carrer de Puigmal, 13",
    "sg:city":"Terrassa",
    "sg:orig_category":"Molduras, Junquillos, Listones Y Molduras Perforadas",
    "sg:phone":"+34 937 31 44 47",
    "sg:postcode":"08227",
    "sg:province":"Barcelona",
    "wof:name":"Marquez Mendoza Jose",
    "wof:placetype":"venue"
},
  "geometry": {"coordinates":[2.0354790688,41.5693283081],"type":"Point"}
}