{
  "type": "Feature",
  "properties": {
    "iso:country":"ES",
    "sg:address":"Carrer de Ramon Y Cajal, 35",
    "sg:city":"Mutxamel",
    "sg:orig_category":"Asilos De Ancianos. Centros Privados",
    "sg:phone":"+34 965 95 13 61",
    "sg:postcode":"03110",
    "sg:province":"Alicante",
    "sg:website":"www.capblau.com",
    "wof:name":"Residencia Tercera Edat Cap Blau S.l.",
    "wof:placetype":"venue"
},
  "geometry": {"coordinates":[-0.4424020052,38.4175071716],"type":"Point"}
}