{
  "type": "Feature",
  "properties": {
    "addr:full":"Calle de San Hermenegildo, S/n Cordoba C\u00f3rdoba 14011",
    "addr:housenumber":"s / n",
    "addr:postcode":"14011",
    "addr:street":"Calle De San Hermenegildo;Co\u0301Rdoba",
    "iso:country":"ES",
    "sg:address":"Calle de San Hermenegildo, S/n",
    "sg:city":"Cordoba",
    "sg:orig_category":"Centros De Educaci\u00d3n Especial",
    "sg:phone":"+34 957 27 87 51",
    "sg:postcode":"14011",
    "sg:province":"C\u00f3rdoba",
    "wof:name":"Junta De Andalucia",
    "wof:placetype":"venue"
},
  "geometry": {"coordinates":[-4.7966341972,37.8924407959],"type":"Point"}
}