{
  "type": "Feature",
  "properties": {
    "iso:country":"ES",
    "sg:address":"Ctra. Perdigon, S/n",
    "sg:city":"Entrala",
    "sg:orig_category":"Panader\u00cdas, Panader\u00cdas",
    "sg:phone":"+34 980 57 63 55",
    "sg:postcode":"49721",
    "sg:province":"Zamora",
    "wof:name":"Reposteria Mateos S.a.",
    "wof:placetype":"venue"
},
  "geometry": {"coordinates":[-5.7544689178,41.4298667908],"type":"Point"}
}