{
  "type": "Feature",
  "properties": {
    "addr:full":"Barreras, 9 Baeza Ja\u00e9n 23440",
    "addr:housenumber":"9",
    "addr:postcode":"23440",
    "iso:country":"ES",
    "sg:address":"Barreras, 9",
    "sg:city":"Baeza",
    "sg:orig_category":"Promotores Constructores",
    "sg:phone":"+34 953 74 13 68",
    "sg:postcode":"23440",
    "sg:province":"Ja\u00e9n",
    "sg:website":"www.aifos.com",
    "wof:name":"Aifos S.a.",
    "wof:placetype":"venue"
},
  "geometry": {"coordinates":[-3.4676589966,37.9928855896],"type":"Point"}
}