{
  "type": "Feature",
  "properties": {
    "iso:country":"ES",
    "sg:address":"Avda Andalucia, 2",
    "sg:city":"Punta Umbria",
    "sg:orig_category":"Aparcamientos (infraestructuras, Accesorios)",
    "sg:phone":"+34 959 31 10 02",
    "sg:postcode":"21100",
    "sg:province":"Huelva",
    "wof:name":"Garajes Torre Umbria S.l.",
    "wof:placetype":"venue"
},
  "geometry": {"coordinates":[-6.9638986588,37.1849861145],"type":"Point"}
}