{
  "type": "Feature",
  "properties": {
    "iso:country":"ES",
    "sg:address":"Calle de Alfonso I, 2",
    "sg:city":"Zaragoza",
    "sg:orig_category":"\u00d3ptica: Instrumentos (fabricaci\u00d3n)",
    "sg:phone":"+34 976 29 03 42",
    "sg:postcode":"50003",
    "sg:province":"Zaragoza",
    "wof:name":"Camara Opticos S.a.",
    "wof:placetype":"venue"
},
  "geometry": {"coordinates":[-0.8820613027,41.6530761719],"type":"Point"}
}