{
  "type": "Feature",
  "properties": {
    "addr:full":"Ctra Alcantarilla, 249 Nonduermas Murcia 30166",
    "addr:housenumber":"249",
    "addr:postcode":"30166",
    "addr:street":"Ctra Alcantarilla",
    "iso:country":"ES",
    "sg:address":"Ctra Alcantarilla, 249",
    "sg:city":"Nonduermas",
    "sg:orig_category":"Sociedades, Compa\u00d1\u00cdas Aseguradoras",
    "sg:phone":"+34 968 34 08 20",
    "sg:postcode":"30166",
    "sg:province":"Murcia",
    "wof:name":"Lopez Pintado Pedro",
    "wof:placetype":"venue"
},
  "geometry": {"coordinates":[-1.1575789452,37.9739112854],"type":"Point"}
}