{
  "type": "Feature",
  "properties": {
    "addr:full":"Ctra Alca\u00d1iz, 64 Teruel Teruel 44003",
    "addr:housenumber":"64",
    "addr:postcode":"44003",
    "addr:street":"Ctra Alcan\u0303Iz",
    "iso:country":"ES",
    "sg:address":"Ctra Alca\u00d1iz, 64",
    "sg:city":"Teruel",
    "sg:orig_category":"Equipo De Refrigeraci\u00d3n Industrial",
    "sg:phone":"+34 978 61 90 83",
    "sg:postcode":"44003",
    "sg:province":"Teruel",
    "wof:name":"Comercial Hostelera Ferrando S.l.",
    "wof:placetype":"venue"
},
  "geometry": {"coordinates":[-1.1082019806,40.353969574],"type":"Point"}
}