{
  "type": "Feature",
  "properties": {
    "addr:full":"Calle de Pilar, 8 Matas-pinar-monte Rozas Madrid 28290",
    "addr:housenumber":"8",
    "addr:postcode":"28290",
    "addr:street":"Calle De Pilar",
    "iso:country":"ES",
    "sg:address":"Calle de Pilar, 8",
    "sg:city":"Matas-pinar-monte Rozas",
    "sg:orig_category":"Molduras, Junquillos, Listones Y Molduras Perforadas",
    "sg:phone":"+34 916 30 25 84",
    "sg:postcode":"28290",
    "sg:province":"Madrid",
    "wof:name":"Ferbayo S.l.",
    "wof:placetype":"venue"
},
  "geometry": {"coordinates":[-3.8968660831,40.5541534424],"type":"Point"}
}