{
  "type": "Feature",
  "properties": {
    "addr:full":"Calle de Ronda De La Manca, 10 Cordoba C\u00f3rdoba 14010",
    "addr:housenumber":"10",
    "addr:postcode":"14010",
    "addr:street":"Calle De Ronda De La Manca;Co\u0301Rdoba",
    "iso:country":"ES",
    "sg:address":"Calle de Ronda De La Manca, 10",
    "sg:city":"Cordoba",
    "sg:orig_category":"Bisuteros (fabricaci\u00d3n, Al Por Mayor)",
    "sg:phone":"+34 957 26 14 07",
    "sg:postcode":"14010",
    "sg:province":"C\u00f3rdoba",
    "wof:name":"Pineda Jimenez Gonzalo",
    "wof:placetype":"venue"
},
  "geometry": {"coordinates":[-4.7651147842,37.88722229],"type":"Point"}
}