{
  "type": "Feature",
  "properties": {
    "addr:full":"Calle de Rico, 202 Huelva Huelva 21001",
    "addr:housenumber":"202",
    "addr:postcode":"21001",
    "addr:street":"Calle De Rico",
    "iso:country":"ES",
    "sg:address":"Calle de Rico, 202",
    "sg:city":"Huelva",
    "sg:orig_category":"M\u00c9dicos: Salud P\u00dablica",
    "sg:phone":"+34 959 24 11 01",
    "sg:postcode":"21001",
    "sg:province":"Huelva",
    "wof:name":"Aguado Nu\u00f1ez-cornejo Antonio",
    "wof:placetype":"venue"
},
  "geometry": {"coordinates":[-6.952682972,37.2558288574],"type":"Point"}
}