{
  "type": "Feature",
  "properties": {
    "addr:full":"Avda Habana, 29 Melide A Coru\u00f1a 15800",
    "addr:housenumber":"29",
    "addr:postcode":"15800",
    "addr:street":"Avda Habana;Corun\u0303A",
    "iso:country":"ES",
    "sg:address":"Avda Habana, 29",
    "sg:city":"Melide",
    "sg:orig_category":"Librer\u00cdas",
    "sg:phone":"+34 981 50 57 75",
    "sg:postcode":"15800",
    "sg:province":"A Coru\u00f1a",
    "wof:name":"Vidal Vidal Ramon",
    "wof:placetype":"venue"
},
  "geometry": {"coordinates":[-8.0112762451,42.9146537781],"type":"Point"}
}