{
  "type": "Feature",
  "properties": {
    "iso:country":"ES",
    "sg:address":"Trav De Gracia, 124",
    "sg:city":"Barcelona",
    "sg:orig_category":"Peleter\u00cdas",
    "sg:phone":"+34 932 37 60 91",
    "sg:postcode":"08012",
    "sg:province":"Barcelona",
    "wof:name":"Coll Aris Jaime",
    "wof:placetype":"venue"
},
  "geometry": {"coordinates":[2.1560559273,41.4000434875],"type":"Point"}
}