{
  "type": "Feature",
  "properties": {
    "addr:full":"Ctra Estacion, 8 Llerena Badajoz 06900",
    "addr:housenumber":"8",
    "addr:postcode":"06900",
    "addr:street":"Ctra Estacion",
    "iso:country":"ES",
    "sg:address":"Ctra Estacion, 8",
    "sg:city":"Llerena",
    "sg:orig_category":"Agentes, Concesionarios Y Sucursales De Veh\u00cdculos",
    "sg:phone":"+34 924 87 04 22",
    "sg:postcode":"06900",
    "sg:province":"Badajoz",
    "wof:name":"Talleres Julian E Hijos S.l.",
    "wof:placetype":"venue"
},
  "geometry": {"coordinates":[-6.0117950439,38.2379837036],"type":"Point"}
}