{
  "type": "Feature",
  "properties": {
    "iso:country":"ES",
    "sg:address":"Calle de Esteban Salazar Chapela, 20",
    "sg:city":"Malaga",
    "sg:orig_category":"Adaptaciones, Acondicionamientos Especiales Para Veh\u00cdculos, Veh\u00cdculos Industriales",
    "sg:phone":"+34 952 17 62 61",
    "sg:postcode":"29004",
    "sg:province":"M\u00e1laga",
    "wof:name":"Division Natur S.l.",
    "wof:placetype":"venue"
},
  "geometry": {"coordinates":[-4.4735608101,36.6914787292],"type":"Point"}
}