{
  "type": "Feature",
  "properties": {
    "iso:country":"ES",
    "sg:address":"Calle de Gabriel Miro, 1",
    "sg:city":"Altea",
    "sg:orig_category":"Pod\u00d3logos: Pedicuros",
    "sg:phone":"+34 966 88 00 01",
    "sg:postcode":"03590",
    "sg:province":"Alicante",
    "wof:name":"Garrido Llopis Araceli",
    "wof:placetype":"venue"
},
  "geometry": {"coordinates":[-0.0473470017,38.6024475098],"type":"Point"}
}