{
  "type": "Feature",
  "properties": {
    "addr:full":"Calle de Almazan, 28 Madrid Madrid 28011",
    "addr:housenumber":"28",
    "addr:postcode":"madrid;28011",
    "addr:street":"Calle De Almazan",
    "iso:country":"ES",
    "sg:address":"Calle de Almazan, 28",
    "sg:city":"Madrid",
    "sg:orig_category":"Poller\u00cda Y Caza (al Por Menor)",
    "sg:phone":"+34 914 64 84 09",
    "sg:postcode":"28011",
    "sg:province":"Madrid",
    "wof:name":"Diaz Zurita Ricardo",
    "wof:placetype":"venue"
},
  "geometry": {"coordinates":[-3.745071888,40.4053726196],"type":"Point"}
}