{
  "type": "Feature",
  "properties": {
    "iso:country":"ES",
    "sg:address":"Calle de Lopez Trigo, 12",
    "sg:city":"Ayora",
    "sg:orig_category":"Electricidad Veh\u00cdculo",
    "sg:phone":"+34 962 19 10 72",
    "sg:postcode":"46620",
    "sg:province":"Valencia",
    "wof:name":"Gavidia Catalan Miguel",
    "wof:placetype":"venue"
},
  "geometry": {"coordinates":[-1.0548039675,39.062953949],"type":"Point"}
}