{
  "type": "Feature",
  "properties": {
    "addr:full":"Calle de Canton, 12 Pradejon La Rioja 26510",
    "addr:housenumber":"12",
    "addr:postcode":"26510",
    "addr:street":"Calle De Canton;Rioja",
    "iso:country":"ES",
    "sg:address":"Calle de Canton, 12",
    "sg:city":"Pradejon",
    "sg:orig_category":"Carnicer\u00cdas, Carnicer\u00cdas",
    "sg:phone":"+34 941 15 02 07",
    "sg:postcode":"26510",
    "sg:province":"La Rioja",
    "wof:name":"Gonzalez Alonso Luisa Jesus",
    "wof:placetype":"venue"
},
  "geometry": {"coordinates":[-2.0707080364,42.3349151611],"type":"Point"}
}