{
  "type": "Feature",
  "properties": {
    "iso:country":"ES",
    "sg:address":"Calle de Gre\u00d1a Mora, 26",
    "sg:city":"Guia Isora",
    "sg:orig_category":"Chapister\u00cda",
    "sg:phone":"+34 922 85 24 10",
    "sg:postcode":"38680",
    "sg:province":"Santa Cruz De Tenerife",
    "wof:name":"C.b Fumero Vargas",
    "wof:placetype":"venue"
},
  "geometry": {"coordinates":[-16.7765598297,28.2141609192],"type":"Point"}
}