{
  "type": "Feature",
  "properties": {
    "iso:country":"ES",
    "sg:address":"Carrer de Japo, 33",
    "sg:city":"Barcelona",
    "sg:orig_category":"Montaje (empresas De)",
    "sg:phone":"+34 933 59 84 40",
    "sg:postcode":"08016",
    "sg:province":"Barcelona",
    "wof:name":"Inasu S.l.",
    "wof:placetype":"venue"
},
  "geometry": {"coordinates":[2.1780600548,41.4414710999],"type":"Point"}
}