{
  "type": "Feature",
  "properties": {
    "iso:country":"ES",
    "sg:address":"A Florida, S/n",
    "sg:city":"Florida",
    "sg:orig_category":"Empresas De Carpinter\u00cda",
    "sg:phone":"+34 981 80 91 01",
    "sg:postcode":"15883",
    "sg:province":"La Coru\u00f1a",
    "wof:name":"Conpeal S. L.",
    "wof:placetype":"venue"
},
  "geometry": {"coordinates":[-8.5444011688,42.8382263184],"type":"Point"}
}