{
  "type": "Feature",
  "properties": {
    "iso:country":"ES",
    "sg:address":"Av Verge Montserrat, 121",
    "sg:city":"Prat Llobregat",
    "sg:orig_category":"M\u00c9dicos: Medicina General Orientada A La Acupuntura",
    "sg:phone":"+34 933 70 13 01",
    "sg:postcode":"08820",
    "sg:province":"Barcelona",
    "wof:name":"Aguirre Laserna Miguel",
    "wof:placetype":"venue"
},
  "geometry": {"coordinates":[2.0946292877,41.3255805969],"type":"Point"}
}