{
  "type": "Feature",
  "properties": {
    "addr:full":"Calle de Alberto Aguilera, 7 Madrid Madrid 28015",
    "addr:housenumber":"7",
    "addr:postcode":"madrid;28015",
    "addr:street":"Calle De Alberto Aguilera",
    "iso:country":"ES",
    "sg:address":"Calle de Alberto Aguilera, 7",
    "sg:city":"Madrid",
    "sg:orig_category":"Transportes P\u00dablicos",
    "sg:phone":"+34 915 91 43 65",
    "sg:postcode":"28015",
    "sg:province":"Madrid",
    "sg:website":"www.elipsos.com",
    "wof:name":"Elipsos Internacional S.a.",
    "wof:placetype":"venue"
},
  "geometry": {"coordinates":[-3.7082593441,40.429775238],"type":"Point"}
}