{
  "type": "Feature",
  "properties": {
    "addr:full":"German Bernacer(pol Ind), 72 Torrellano Alicante 03320",
    "addr:housenumber":"72",
    "addr:postcode":"03320",
    "addr:street":"Ind",
    "iso:country":"ES",
    "sg:address":"German Bernacer(pol Ind), 72",
    "sg:city":"Torrellano",
    "sg:orig_category":"Hilaturas, Hilos Y Actividades Relacionadas",
    "sg:phone":"+34 965 68 52 29",
    "sg:postcode":"03320",
    "sg:province":"Alicante",
    "wof:name":"Versa Textil S.l.",
    "wof:placetype":"venue"
},
  "geometry": {"coordinates":[-0.5883839726,38.2929649353],"type":"Point"}
}