{
  "type": "Feature",
  "properties": {
    "iso:country":"ES",
    "sg:address":"Calle de Saenz Diez, 52",
    "sg:city":"Ourense",
    "sg:orig_category":"Centros De Educaci\u00d3n Especial",
    "sg:phone":"+34 988 37 20 43",
    "sg:postcode":"32003",
    "sg:province":"Ourense",
    "wof:name":"Colexio Publico De E.x.b. Curros Enriquez",
    "wof:placetype":"venue"
},
  "geometry": {"coordinates":[-7.8636479378,42.3447875977],"type":"Point"}
}