{
  "type": "Feature",
  "properties": {
    "iso:country":"ES",
    "sg:address":"Carr Sant Francesc De Borja, 48",
    "sg:city":"Gandia",
    "sg:orig_category":"Delegados, Agentes De Tr\u00c1nsito, Auxiliares De Transporte Internacional",
    "sg:phone":"+34 962 87 21 56",
    "sg:postcode":"46700",
    "sg:province":"Valencia",
    "wof:name":"Borras Faus Vicente",
    "wof:placetype":"venue"
},
  "geometry": {"coordinates":[-0.1913339943,38.960735321],"type":"Point"}
}