{
  "type": "Feature",
  "properties": {
    "addr:full":"Calle de Miguel Hernandez, 2 Ciudad Rodrigo Salamanca 37500",
    "addr:housenumber":"2",
    "addr:postcode":"37500",
    "addr:street":"Calle De Miguel Hernandez",
    "iso:country":"ES",
    "sg:address":"Calle de Miguel Hernandez, 2",
    "sg:city":"Ciudad Rodrigo",
    "sg:orig_category":"Molduras, Junquillos, Listones Y Molduras Perforadas",
    "sg:phone":"+34 923 46 20 25",
    "sg:postcode":"37500",
    "sg:province":"Salamanca",
    "wof:name":"Montero Merino Antonio",
    "wof:placetype":"venue"
},
  "geometry": {"coordinates":[-6.5242905617,40.6069068909],"type":"Point"}
}