{
  "type": "Feature",
  "properties": {
    "iso:country":"ES",
    "sg:address":"Calle de Naranjo De Bulnes, 5",
    "sg:city":"Oviedo",
    "sg:orig_category":"Agencias De Viajes",
    "sg:phone":"+34 985 11 87 63",
    "sg:postcode":"33...",
    "sg:province":"Asturias",
    "sg:website":"www.travelplan.es",
    "wof:name":"Travelplan S.a.",
    "wof:placetype":"venue"
},
  "geometry": {"coordinates":[-5.8568592072,43.3677787781],"type":"Point"}
}