{
  "type": "Feature",
  "properties": {
    "addr:full":"Txikierdi Auzoa, 7 Txikierdi Guip\u00f9zcoa 20170",
    "addr:housenumber":"7",
    "addr:postcode":"20170",
    "addr:street":"Txikierdi Auzoa;Guipu\u0300Zcoa",
    "iso:country":"ES",
    "sg:address":"Txikierdi Auzoa, 7",
    "sg:city":"Txikierdi",
    "sg:orig_category":"Art\u00cdculos De Regalo (al Por Menor)",
    "sg:phone":"+34 943 37 65 93",
    "sg:postcode":"20170",
    "sg:province":"Guip\u00f9zcoa",
    "wof:name":"Selecciones A2 S.l.",
    "wof:placetype":"venue"
},
  "geometry": {"coordinates":[-2.0539140701,43.2733459473],"type":"Point"}
}