{
  "type": "Feature",
  "properties": {
    "iso:country":"ES",
    "sg:address":"Avda Ruzafa, 57",
    "sg:city":"Benidorm",
    "sg:orig_category":"Laboratorios Y Trabajos De Fotograf\u00cda, V\u00cddeo Y Cine",
    "sg:phone":"+34 965 85 90 61",
    "sg:postcode":"03500",
    "sg:province":"Alicante",
    "wof:name":"Molina Morata Manuel",
    "wof:placetype":"venue"
},
  "geometry": {"coordinates":[-0.130723998,38.5408477783],"type":"Point"}
}