{
  "type": "Feature",
  "properties": {
    "iso:country":"ES",
    "sg:address":"C\u00ba Marsella, 56",
    "sg:city":"Sta. Eularia Riu",
    "sg:orig_category":"Bebidas",
    "sg:phone":"+34 971 33 00 11",
    "sg:postcode":"07840",
    "sg:province":"Islas Baleares",
    "wof:name":"Mari Bofill Josep Maria",
    "wof:placetype":"venue"
},
  "geometry": {"coordinates":[2.8577105999,39.5341796875],"type":"Point"}
}