{
  "type": "Feature",
  "properties": {
    "iso:country":"ES",
    "sg:address":"Calle de Estacion, 50",
    "sg:city":"Miranda Ebro",
    "sg:orig_category":"Fabricaci\u00d3n, Importaci\u00d3n, Venta De Material De Telefon\u00cda, Peritelefon\u00cda",
    "sg:phone":"+34 947 31 43 91",
    "sg:postcode":"09200",
    "sg:province":"Burgos",
    "wof:name":"Zeta Telecomunicaciones S.l.",
    "wof:placetype":"venue"
},
  "geometry": {"coordinates":[-2.9437069893,42.687828064],"type":"Point"}
}