{
  "type": "Feature",
  "properties": {
    "addr:full":"Calle de Balendin Berrio-otxoa, 8 Elorrio Vizcaya 48230",
    "addr:housenumber":"8",
    "addr:postcode":"48230",
    "addr:street":"Calle De Balendin Berrio-Otxoa",
    "iso:country":"ES",
    "sg:address":"Calle de Balendin Berrio-otxoa, 8",
    "sg:city":"Elorrio",
    "sg:orig_category":"Mercer\u00cda, Lencer\u00cda (al Por Menor)",
    "sg:phone":"+34 946 82 13 69",
    "sg:postcode":"48230",
    "sg:province":"Vizcaya",
    "wof:name":"Amorrortu Petralanda Francisco Javier",
    "wof:placetype":"venue"
},
  "geometry": {"coordinates":[-2.5296971798,43.1177749634],"type":"Point"}
}