{
  "type": "Feature",
  "properties": {
    "iso:country":"ES",
    "sg:address":"Calle de La Florida, 62",
    "sg:city":"Vitoria-gasteiz",
    "sg:orig_category":"Arquitectos",
    "sg:phone":"+34 945 26 72 93",
    "sg:postcode":"01005",
    "sg:province":"\u00c1lava",
    "wof:name":"Martinez Larraz Rafael",
    "wof:placetype":"venue"
},
  "geometry": {"coordinates":[-2.6701390743,42.8428001404],"type":"Point"}
}