{
  "type": "Feature",
  "properties": {
    "iso:country":"ES",
    "sg:address":"Calle de Rubicon, 49",
    "sg:city":"S. Bartolome",
    "sg:orig_category":"Museos",
    "sg:phone":"+34 928 52 06 55",
    "sg:postcode":"35550",
    "sg:province":"Las Palmas",
    "wof:name":"Museo Etnografico Tanit",
    "wof:placetype":"venue"
},
  "geometry": {"coordinates":[-13.6092777252,29.0041389465],"type":"Point"}
}