{
  "type": "Feature",
  "properties": {
    "addr:full":"Plaz Jose Antonio, 2 Alcorisa Teruel 44550",
    "addr:housenumber":"2",
    "addr:postcode":"44550",
    "addr:street":"Jose Antonio",
    "iso:country":"ES",
    "sg:address":"Plaz Jose Antonio, 2",
    "sg:city":"Alcorisa",
    "sg:orig_category":"Contenedores (mercanc\u00cdas)",
    "sg:phone":"+34 978 84 00 06",
    "sg:postcode":"44550",
    "sg:province":"Teruel",
    "wof:name":"Lapuente Carbo Pascual",
    "wof:placetype":"venue"
},
  "geometry": {"coordinates":[-0.3819589913,40.8916816711],"type":"Point"}
}