{
  "type": "Feature",
  "properties": {
    "addr:full":"Pg Mare De Deu Del Coll, 191 Barcelona Barcelona 08032",
    "addr:housenumber":"191",
    "addr:postcode":"08032",
    "addr:street":"Pg Mare De Deu Del Coll",
    "iso:country":"ES",
    "sg:address":"Pg Mare De Deu Del Coll, 191",
    "sg:city":"Barcelona",
    "sg:orig_category":"Molduras, Junquillos, Listones Y Molduras Perforadas",
    "sg:phone":"+34 933 58 49 81",
    "sg:postcode":"08032",
    "sg:province":"Barcelona",
    "wof:name":"Carmona Almendros Juan",
    "wof:placetype":"venue"
},
  "geometry": {"coordinates":[2.1512179375,41.4243164062],"type":"Point"}
}