{
  "type": "Feature",
  "properties": {
    "addr:full":"Avda Mari\u00d1a (da), 29 Burela Lugo 27880",
    "addr:housenumber":"29",
    "addr:postcode":"27880",
    "addr:street":"Avda Marin\u0303A Da",
    "iso:country":"ES",
    "sg:address":"Avda Mari\u00d1a (da), 29",
    "sg:city":"Burela",
    "sg:orig_category":"Postigos, Persianas Y Celos\u00cdas",
    "sg:phone":"+34 982 58 52 01",
    "sg:postcode":"27880",
    "sg:province":"Lugo",
    "wof:name":"Segade Dopazo Luis",
    "wof:placetype":"venue"
},
  "geometry": {"coordinates":[-7.3580889702,43.6645278931],"type":"Point"}
}