{
  "type": "Feature",
  "properties": {
    "iso:country":"ES",
    "sg:address":"Plaz Rafael Cano, 7",
    "sg:city":"Valladolid",
    "sg:orig_category":"Molduras, Junquillos, Listones Y Molduras Perforadas",
    "sg:phone":"+34 983 29 77 42",
    "sg:postcode":"47005",
    "sg:province":"Valladolid",
    "wof:name":"Centeno Pedrero Luis",
    "wof:placetype":"venue"
},
  "geometry": {"coordinates":[-4.7100777626,41.6521568298],"type":"Point"}
}