{
  "type": "Feature",
  "properties": {
    "addr:full":"Calle de Orense, 12 Madrid Madrid 28020",
    "addr:housenumber":"12",
    "addr:postcode":"madrid;28020",
    "addr:street":"Calle De Orense",
    "iso:country":"ES",
    "sg:address":"Calle de Orense, 12",
    "sg:city":"Madrid",
    "sg:orig_category":"Cl\u00cdnicas Dentales",
    "sg:phone":"+34 915 55 05 14",
    "sg:postcode":"28020",
    "sg:province":"Madrid",
    "wof:name":"Perez Zapata Ana Maria",
    "wof:placetype":"venue"
},
  "geometry": {"coordinates":[-3.6952986717,40.4490852356],"type":"Point"}
}