{
  "type": "Feature",
  "properties": {
    "addr:full":"Carrer de Moja, S/n Vilafranca Penedes Barcelona 08720",
    "addr:housenumber":"s / n",
    "addr:postcode":"08720",
    "addr:street":"Carrer De Moja;Penedes Barcelona",
    "iso:country":"ES",
    "sg:address":"Carrer de Moja, S/n",
    "sg:city":"Vilafranca Penedes",
    "sg:orig_category":"Cristaler\u00cdas",
    "sg:phone":"+34 938 17 01 99",
    "sg:postcode":"08720",
    "sg:province":"Barcelona",
    "wof:name":"Cristalleria Vilafranca Scp",
    "wof:placetype":"venue"
},
  "geometry": {"coordinates":[1.6967669725,41.3367462158],"type":"Point"}
}