{
  "type": "Feature",
  "properties": {
    "iso:country":"ES",
    "sg:address":"Calle de Estrella Polar, 41",
    "sg:city":"Alacant",
    "sg:orig_category":"Quincaller\u00cda (al Por Menor)",
    "sg:phone":"+34 965 28 09 13",
    "sg:postcode":"03006",
    "sg:province":"Alicante",
    "wof:name":"Fluidos Y Transmisiones S.l.",
    "wof:placetype":"venue"
},
  "geometry": {"coordinates":[-0.5236799717,38.3391609192],"type":"Point"}
}