{
  "type": "Feature",
  "properties": {
    "addr:full":"Av. Serapio Huici, 9 Atarrabia Navarra 31610",
    "addr:housenumber":"9",
    "addr:postcode":"31610",
    "addr:street":"Av. Serapio Huici",
    "iso:country":"ES",
    "sg:address":"Av. Serapio Huici, 9",
    "sg:city":"Atarrabia",
    "sg:orig_category":"Juristas",
    "sg:phone":"+34 948 13 66 49",
    "sg:postcode":"31610",
    "sg:province":"Navarra",
    "wof:name":"Berruezo Gambarte Francisco Javier",
    "wof:placetype":"venue"
},
  "geometry": {"coordinates":[-1.6113300323,42.828994751],"type":"Point"}
}