{
  "type": "Feature",
  "properties": {
    "iso:country":"ES",
    "sg:address":"Tulipanes, 41",
    "sg:city":"Lo Pagan",
    "sg:orig_category":"Venta Y Reparaci\u00d3n De Naves De Recreo, Accesorios",
    "sg:phone":"+34 968 18 43 31",
    "sg:postcode":"30740",
    "sg:province":"Murcia",
    "sg:website":"www.navisurest.com",
    "wof:name":"Navisurest International Yacht Brocker Gestion S.l.",
    "wof:placetype":"venue"
},
  "geometry": {"coordinates":[-0.7932540178,37.8340911865],"type":"Point"}
}