{
  "type": "Feature",
  "properties": {
    "iso:country":"ES",
    "sg:address":"A Vi\u00f1a, S/n",
    "sg:city":"Cartaya",
    "sg:orig_category":"Arboricultura Y Producci\u00d3n De Frutas",
    "sg:phone":"+34 959 39 10 53",
    "sg:postcode":"21450",
    "sg:province":"Huelva",
    "wof:name":"Herrero Marquez Rosa",
    "wof:placetype":"venue"
},
  "geometry": {"coordinates":[-7.1528987885,37.2844581604],"type":"Point"}
}