{
  "type": "Feature",
  "properties": {
    "iso:country":"ES",
    "sg:address":"Calle de Aldeanueva De La Vera, 25",
    "sg:city":"Madrid",
    "sg:orig_category":"C\u00c1maras De Comercio E Industria, Oficios, Agricultura",
    "sg:phone":"+34 917 06 96 56",
    "sg:postcode":"28044",
    "sg:province":"Madrid",
    "wof:name":"Vallecillos Garcia Maria Rosa",
    "wof:placetype":"venue"
},
  "geometry": {"coordinates":[-3.7763524055,40.3766479492],"type":"Point"}
}