{
  "type": "Feature",
  "properties": {
    "addr:full":"Calle de Maiquez, 20 Madrid Madrid 28009",
    "addr:housenumber":"20",
    "addr:postcode":"madrid;28009",
    "addr:street":"Calle De Maiquez",
    "iso:country":"ES",
    "sg:address":"Calle de Maiquez, 20",
    "sg:city":"Madrid",
    "sg:orig_category":"Urbanistas",
    "sg:phone":"+34 915 04 67 61",
    "sg:postcode":"28009",
    "sg:province":"Madrid",
    "wof:name":"Porras La Casta Arquitectos S.c.p.",
    "wof:placetype":"venue"
},
  "geometry": {"coordinates":[-3.6730699539,40.4208030701],"type":"Point"}
}