{
  "type": "Feature",
  "properties": {
    "iso:country":"ES",
    "sg:address":"Pase Manuel Antonio, S/n",
    "sg:city":"Rianxo",
    "sg:orig_category":"Sindicatos Y Colegios Profesionales",
    "sg:phone":"+34 981 86 65 90",
    "sg:postcode":"15920",
    "sg:province":"La Coru\u00f1a",
    "wof:name":"Agrupacion Mexiloeira Rianxeira",
    "wof:placetype":"venue"
},
  "geometry": {"coordinates":[-8.7646389008,42.6790809631],"type":"Point"}
}