{
  "type": "Feature",
  "properties": {
    "iso:country":"ES",
    "sg:address":"Calle de Berio Kalea, 8",
    "sg:city":"Irun",
    "sg:orig_category":"Carnicer\u00cdas, Carnicer\u00cdas",
    "sg:phone":"+34 943 63 37 31",
    "sg:postcode":"20303",
    "sg:province":"Guip\u00f9zcoa",
    "wof:name":"Placido Jorge Cepa",
    "wof:placetype":"venue"
},
  "geometry": {"coordinates":[-1.790667057,43.3331985474],"type":"Point"}
}