{
  "type": "Feature",
  "properties": {
    "addr:full":"Avda Augusto Vazquez, 30 Badajoz Badajoz 06006",
    "addr:housenumber":"30",
    "addr:postcode":"06006",
    "addr:street":"Avda Augusto Vazquez",
    "iso:country":"ES",
    "sg:address":"Avda Augusto Vazquez, 30",
    "sg:city":"Badajoz",
    "sg:orig_category":"Electricidad, Electr\u00d3nica: Suministros (al Por Menor)",
    "sg:phone":"+34 924 24 83 05",
    "sg:postcode":"06006",
    "sg:province":"Badajoz",
    "wof:name":"Garcia Antequera S.l.",
    "wof:placetype":"venue"
},
  "geometry": {"coordinates":[-6.9858670235,38.888507843],"type":"Point"}
}