{
  "type": "Feature",
  "properties": {
    "addr:full":"Calle de Santa Lucia, 8 Zaragoza Zaragoza 50003",
    "addr:housenumber":"8",
    "addr:postcode":"50003",
    "addr:street":"Calle De Santa Lucia",
    "iso:country":"ES",
    "sg:address":"Calle de Santa Lucia, 8",
    "sg:city":"Zaragoza",
    "sg:orig_category":"Carnicer\u00cdas, Carnicer\u00cdas",
    "sg:phone":"+34 976 43 53 04",
    "sg:postcode":"50003",
    "sg:province":"Zaragoza",
    "wof:name":"Gonzalvo Escriche Ramiro",
    "wof:placetype":"venue"
},
  "geometry": {"coordinates":[-0.8909029961,41.6584091187],"type":"Point"}
}