{
  "type": "Feature",
  "properties": {
    "addr:full":"Pol. Palancares, S/n Cuenca Cuenca 16003",
    "addr:housenumber":"/ n",
    "addr:postcode":"16003",
    "addr:street":"Palancares S",
    "iso:country":"ES",
    "sg:address":"Pol. Palancares, S/n",
    "sg:city":"Cuenca",
    "sg:orig_category":"Agentes, Concesionarios Y Sucursales De Veh\u00cdculos",
    "sg:phone":"+34 969 23 43 55",
    "sg:postcode":"16003",
    "sg:province":"Cuenca",
    "wof:name":"Talleres Abarca S.l.",
    "wof:placetype":"venue"
},
  "geometry": {"coordinates":[-2.1361989975,40.0586967468],"type":"Point"}
}