{
  "type": "Feature",
  "properties": {
    "addr:full":"Las Cruces, 9 Valdeganga Albacete 02150",
    "addr:housenumber":"9",
    "addr:postcode":"02150",
    "addr:street":"Las Cruces",
    "iso:country":"ES",
    "sg:address":"Las Cruces, 9",
    "sg:city":"Valdeganga",
    "sg:orig_category":"Bisuter\u00cda, Joyer\u00cda, Relojer\u00cda (al Por Menor)",
    "sg:phone":"+34 967 40 01 51",
    "sg:postcode":"02150",
    "sg:province":"Albacete",
    "wof:name":"Romero Gil Juan Gines",
    "wof:placetype":"venue"
},
  "geometry": {"coordinates":[-1.6746579409,39.1355018616],"type":"Point"}
}