{
  "type": "Feature",
  "properties": {
    "iso:country":"ES",
    "sg:address":"Avda Burgos, 23",
    "sg:city":"Sasamon",
    "sg:orig_category":"Contenedores Para Dep\u00d3sito De Sustancias Peligrosas (fabricaci\u00d3n, Al Por Mayor)",
    "sg:phone":"+34 947 37 00 16",
    "sg:postcode":"09123",
    "sg:province":"Burgos",
    "wof:name":"Metalicas Llorente S.a.",
    "wof:placetype":"venue"
},
  "geometry": {"coordinates":[-4.0416049957,42.4144744873],"type":"Point"}
}