{
  "type": "Feature",
  "properties": {
    "addr:full":"Calle de Saenz Laguna, 22 Algeciras C\u00e1diz 11201",
    "addr:housenumber":"22;ca\u0301diz",
    "addr:postcode":"11201",
    "addr:street":"Calle De Saenz Laguna",
    "iso:country":"ES",
    "sg:address":"Calle de Saenz Laguna, 22",
    "sg:city":"Algeciras",
    "sg:orig_category":"Asociaciones Y Clubs Deportivos",
    "sg:phone":"+34 956 66 16 50",
    "sg:postcode":"11201",
    "sg:province":"C\u00e1diz",
    "wof:name":"Finness 100 Compa\u00f1ia De Wellness S.l.",
    "wof:placetype":"venue"
},
  "geometry": {"coordinates":[-5.4474921227,36.1328430176],"type":"Point"}
}