{
  "type": "Feature",
  "properties": {
    "iso:country":"ES",
    "sg:address":"Rua Bernardo Gonzalez Cachamui\u00d1a, 8",
    "sg:city":"Ourense",
    "sg:orig_category":"Mec\u00c1nico Del Autom\u00d3vil",
    "sg:phone":"+34 988 23 15 15",
    "sg:postcode":"32004",
    "sg:province":"Ourense",
    "wof:name":"Perez Doval Luis",
    "wof:placetype":"venue"
},
  "geometry": {"coordinates":[-7.854514122,42.3430366516],"type":"Point"}
}