{
  "type": "Feature",
  "properties": {
    "iso:country":"ES",
    "sg:address":"Calle de Libertad, 13",
    "sg:city":"Martos",
    "sg:orig_category":"Profesiones M\u00c9dicas, Param\u00c9dicas",
    "sg:phone":"+34 953 70 00 36",
    "sg:postcode":"23600",
    "sg:province":"Ja\u00e9n",
    "wof:name":"Del Moral Sanchez Joaquin",
    "wof:placetype":"venue"
},
  "geometry": {"coordinates":[-3.9707970619,37.7211151123],"type":"Point"}
}