{
  "type": "Feature",
  "properties": {
    "iso:country":"ES",
    "sg:address":"Avda Baron De Carcer, 46",
    "sg:city":"Valencia",
    "sg:orig_category":"Abogados",
    "sg:phone":"+34 963 52 01 38",
    "sg:postcode":"46001",
    "sg:province":"Valencia",
    "wof:name":"Perez Pascual Eduardo",
    "wof:placetype":"venue"
},
  "geometry": {"coordinates":[-0.3797520101,39.4698791504],"type":"Point"}
}