{
  "type": "Feature",
  "properties": {
    "iso:country":"ES",
    "sg:address":"Carr Rossinyol, 26",
    "sg:city":"Pont D'inca",
    "sg:orig_category":"Agencias De Viajes",
    "sg:phone":"+34 971 60 81 06",
    "sg:postcode":"07009",
    "sg:province":"Islas Baleares",
    "wof:name":"Turistic Meditram S.l.",
    "wof:placetype":"venue"
},
  "geometry": {"coordinates":[2.9054980278,39.7162857056],"type":"Point"}
}