{
  "type": "Feature",
  "properties": {
    "addr:full":"Carrer de Cecili Metel, 10 Palma Islas Baleares 07003",
    "addr:housenumber":"10",
    "addr:postcode":"07003",
    "addr:street":"Carrer De Cecili Metel",
    "iso:country":"ES",
    "sg:address":"Carrer de Cecili Metel, 10",
    "sg:city":"Palma",
    "sg:orig_category":"Oficinas Y Gesti\u00d3n De Inmuebles",
    "sg:phone":"+34 971 21 48 21",
    "sg:postcode":"07003",
    "sg:province":"Islas Baleares",
    "wof:name":"Gerencia Inmobiliaria Balear S.l.",
    "wof:placetype":"venue"
},
  "geometry": {"coordinates":[2.6513020992,39.5768241882],"type":"Point"}
}