{
  "type": "Feature",
  "properties": {
    "iso:country":"ES",
    "sg:address":"Avda Amistad De La, S/n",
    "sg:city":"S. Bartolome Torre",
    "sg:orig_category":"Aceites Y Grasas Alimentarias (fabricaci\u00d3n, Al Por Mayor)",
    "sg:phone":"+34 959 38 74 43",
    "sg:postcode":"21510",
    "sg:province":"Huelva",
    "wof:name":"Cooperativa Olivarera San Bartlome De La Torre",
    "wof:placetype":"venue"
},
  "geometry": {"coordinates":[-7.1026139259,37.4456367493],"type":"Point"}
}