{
  "type": "Feature",
  "properties": {
    "addr:full":"Avda Coria, 30 Palomares Rio Sevilla 41928",
    "addr:housenumber":"30",
    "addr:postcode":"41928",
    "addr:street":"Avda Coria;Rio Sevilla",
    "iso:country":"ES",
    "sg:address":"Avda Coria, 30",
    "sg:city":"Palomares Rio",
    "sg:orig_category":"Farmacias",
    "sg:phone":"+34 955 76 34 02",
    "sg:postcode":"41928",
    "sg:province":"Sevilla",
    "wof:name":"Fernandez Santa-cruz Sanchez-matamoros Pedro",
    "wof:placetype":"venue"
},
  "geometry": {"coordinates":[-6.060049057,37.3203125],"type":"Point"}
}