{
  "type": "Feature",
  "properties": {
    "iso:country":"ES",
    "sg:address":"Avda Paz De (la), 69",
    "sg:city":"Logro\u00f1o",
    "sg:orig_category":"Ropa Para Se\u00d1oras (al Por Menor)",
    "sg:phone":"+34 941 25 68 95",
    "sg:postcode":"26004",
    "sg:province":"La Rioja",
    "wof:name":"Garcia Santa Maria Marina",
    "wof:placetype":"venue"
},
  "geometry": {"coordinates":[-2.4317500591,42.4638061523],"type":"Point"}
}