{
  "type": "Feature",
  "properties": {
    "iso:country":"ES",
    "sg:address":"Av El Textil, 52",
    "sg:city":"Ontinyent",
    "sg:orig_category":"Ingeniero",
    "sg:phone":"+34 962 91 52 08",
    "sg:postcode":"46870",
    "sg:province":"Valencia",
    "wof:name":"Federacion Nacional De Agentes Renault",
    "wof:placetype":"venue"
},
  "geometry": {"coordinates":[-0.5984740257,38.8257331848],"type":"Point"}
}