{
  "type": "Feature",
  "properties": {
    "addr:full":"M. S. Telmo, S/n San Telmo Huelva 21330",
    "addr:housenumber":"/ n",
    "addr:postcode":"21330",
    "addr:street":"M.;Telmo S",
    "iso:country":"ES",
    "sg:address":"M. S. Telmo, S/n",
    "sg:city":"San Telmo",
    "sg:classifiers":[
        {
            "category":"Taxi",
            "type":"Transportation"
        }
    ],
    "sg:phone":"+34 959 57 56 04",
    "sg:postcode":"21330",
    "sg:province":"Huelva",
    "wof:name":"Romero Romero Juan Alonso",
    "wof:placetype":"venue"
},
  "geometry": {"coordinates":[-6.8023939133,37.7839317322],"type":"Point"}
}