{
  "type": "Feature",
  "properties": {
    "iso:country":"ES",
    "sg:address":"C/ Jaume I, 15",
    "sg:city":"Ripollet",
    "sg:orig_category":"Comercio De Piezas De Recambio Y De Accesorios De Veh\u00cdculos, Veh\u00cdculos Industriales",
    "sg:phone":"+34 935 80 43 42",
    "sg:postcode":"08291",
    "sg:province":"Barcelona",
    "wof:name":"Ad Marina Automocio S.l.",
    "wof:placetype":"venue"
},
  "geometry": {"coordinates":[2.1623446941,41.4923210144],"type":"Point"}
}