{
  "type": "Feature",
  "properties": {
    "addr:full":"Carrer de Poeta Gui Colom, 6 Palma Islas Baleares 07010",
    "addr:housenumber":"6",
    "addr:postcode":"07010",
    "addr:street":"Carrer De Poeta Gui Colom",
    "iso:country":"ES",
    "sg:address":"Carrer de Poeta Gui Colom, 6",
    "sg:city":"Palma",
    "sg:orig_category":"Florister\u00cdas",
    "sg:phone":"+34 971 29 83 12",
    "sg:postcode":"07010",
    "sg:province":"Islas Baleares",
    "wof:name":"Carangelo  Annie",
    "wof:placetype":"venue"
},
  "geometry": {"coordinates":[2.6521470547,39.5843734741],"type":"Point"}
}