{
  "type": "Feature",
  "properties": {
    "addr:full":"Calle de Carretera Pantano, 30 Cuevas San Marcos M\u00e1laga 29210",
    "addr:housenumber":"30",
    "addr:postcode":"29210",
    "addr:street":"Calle De Carretera Pantano",
    "iso:country":"ES",
    "sg:address":"Calle de Carretera Pantano, 30",
    "sg:city":"Cuevas San Marcos",
    "sg:orig_category":"Empresas De Pintura Y Revestimientos",
    "sg:phone":"+34 952 72 85 29",
    "sg:postcode":"29210",
    "sg:province":"M\u00e1laga",
    "wof:name":"Hermanos Reina Jimenez S.l.",
    "wof:placetype":"venue"
},
  "geometry": {"coordinates":[-4.4157581329,37.264755249],"type":"Point"}
}