{
  "type": "Feature",
  "properties": {
    "addr:full":"Calle de Castelar, 2 Valladolid Valladolid 47002",
    "addr:housenumber":"2",
    "addr:postcode":"47002",
    "addr:street":"Calle De Castelar",
    "iso:country":"ES",
    "sg:address":"Calle de Castelar, 2",
    "sg:city":"Valladolid",
    "sg:orig_category":"Negocio De Metales No Ferrosos",
    "sg:phone":"+34 983 20 17 33",
    "sg:postcode":"47002",
    "sg:province":"Valladolid",
    "wof:name":"Asociacion Empresarial Metalurgica",
    "wof:placetype":"venue"
},
  "geometry": {"coordinates":[-4.725151062,41.651714325],"type":"Point"}
}