{
  "type": "Feature",
  "properties": {
    "iso:country":"ES",
    "sg:address":"Calle de Isla De Tavira, 18",
    "sg:city":"Madrid",
    "sg:orig_category":"Estudios Y Construcci\u00d3n De Acuarios Y Viveros",
    "sg:phone":"+34 917 38 82 91",
    "sg:postcode":"28035",
    "sg:province":"Madrid",
    "wof:name":"Alvarez Santos Rafael",
    "wof:placetype":"venue"
},
  "geometry": {"coordinates":[-3.7186169624,40.4814338684],"type":"Point"}
}