{
  "type": "Feature",
  "properties": {
    "iso:country":"ES",
    "sg:address":"Calle de Parroco Fernandez Pedrera, 23",
    "sg:city":"Pola De Siero",
    "sg:orig_category":"Encuadernaci\u00d3n E Impresi\u00d3n De Folletos",
    "sg:phone":"+34 985 72 53 09",
    "sg:postcode":"33510",
    "sg:province":"Asturias",
    "wof:name":"Noval Fonseca Fernando",
    "wof:placetype":"venue"
},
  "geometry": {"coordinates":[-5.6583662033,43.3897438049],"type":"Point"}
}