{
  "type": "Feature",
  "properties": {
    "addr:full":"Calle de Marques De Rafal, 42 Rafal Alicante 03369",
    "addr:housenumber":"42",
    "addr:postcode":"03369",
    "addr:street":"Calle De Marques De Rafal",
    "iso:country":"ES",
    "sg:address":"Calle de Marques De Rafal, 42",
    "sg:city":"Rafal",
    "sg:orig_category":"Cajas De Ahorro",
    "sg:phone":"+34 966 75 26 93",
    "sg:postcode":"03369",
    "sg:province":"Alicante",
    "sg:website":"www.cajamurcia.es",
    "wof:name":"Caja De Ahorros De Murcia",
    "wof:placetype":"venue"
},
  "geometry": {"coordinates":[-0.8482819796,38.1051483154],"type":"Point"}
}