{
  "type": "Feature",
  "properties": {
    "iso:country":"ES",
    "sg:address":"Cno. Albolote, 28",
    "sg:city":"Maracena",
    "sg:orig_category":"Agentes, Concesionarios Y Sucursales De Veh\u00cdculos",
    "sg:phone":"+34 958 42 01 71",
    "sg:postcode":"18200",
    "sg:province":"Granada",
    "wof:name":"Vilchez Torralba Agustin",
    "wof:placetype":"venue"
},
  "geometry": {"coordinates":[-3.6359829903,37.2127876282],"type":"Point"}
}