{
  "type": "Feature",
  "properties": {
    "iso:country":"ES",
    "sg:address":"Calle de Canarias, 21",
    "sg:city":"Conil De La Frontera",
    "sg:orig_category":"Alimentaci\u00d3n General (al Por Menor)",
    "sg:phone":"+34 956 44 00 94",
    "sg:postcode":"11140",
    "sg:province":"C\u00e1diz",
    "wof:name":"Pi\u00f1a Sanchez Antonio",
    "wof:placetype":"venue"
},
  "geometry": {"coordinates":[-6.0856838226,36.2808685303],"type":"Point"}
}