{
  "type": "Feature",
  "properties": {
    "addr:full":"Pase Marina Espa\u00d1ola (de La), 12 Ceuta Ceuta 51001",
    "addr:postcode":"51001",
    "iso:country":"ES",
    "sg:address":"Pase Marina Espa\u00d1ola (de La), 12",
    "sg:city":"Ceuta",
    "sg:orig_category":"Agentes, Concesionarios Y Sucursales De Veh\u00cdculos",
    "sg:phone":"+34 956 51 70 44",
    "sg:postcode":"51001",
    "sg:province":"Ceuta",
    "wof:name":"Italcar Ceuta S.l.",
    "wof:placetype":"venue"
},
  "geometry": {"coordinates":[-5.3193998337,35.8888816833],"type":"Point"}
}