{
  "type": "Feature",
  "properties": {
    "addr:full":"Calle de Galileo, 12 Palmas De Gran Canaria Las Palmas 35010",
    "addr:housenumber":"12",
    "addr:postcode":"35010",
    "addr:street":"Calle De Galileo",
    "iso:country":"ES",
    "sg:address":"Calle de Galileo, 12",
    "sg:city":"Palmas De Gran Canaria",
    "sg:orig_category":"Bazares, Art\u00cdculos De Limpieza Y De Cocina (al Por Menor)",
    "sg:phone":"+34 928 22 22 37",
    "sg:postcode":"35010",
    "sg:province":"Las Palmas",
    "wof:name":"Rosales Gonzalez Olga Maria",
    "wof:placetype":"venue"
},
  "geometry": {"coordinates":[-15.4369344711,28.1369533539],"type":"Point"}
}