{
  "type": "Feature",
  "properties": {
    "iso:country":"ES",
    "sg:address":"Ctra Sur, Km. 0040,0",
    "sg:city":"C. Romeral-juan Grande",
    "sg:orig_category":"Aguas (distribuci\u00d3n, Servicios)",
    "sg:phone":"+34 928 17 25 86",
    "sg:postcode":"35107",
    "sg:province":"Las Palmas",
    "wof:name":"Juliano Bonny Gomez S.a.",
    "wof:placetype":"venue"
},
  "geometry": {"coordinates":[-15.4633636475,27.7981491089],"type":"Point"}
}