{
  "type": "Feature",
  "properties": {
    "addr:full":"Avda Arana Sabino, 36 Bilbao Vizcaya 48013",
    "addr:housenumber":"36",
    "addr:postcode":"48013",
    "addr:street":"Avda Arana Sabino",
    "iso:country":"ES",
    "sg:address":"Avda Arana Sabino, 36",
    "sg:city":"Bilbao",
    "sg:orig_category":"Empresas De Limpieza",
    "sg:phone":"+34 944 39 30 12",
    "sg:postcode":"48013",
    "sg:province":"Vizcaya",
    "wof:name":"Eulen S.a.",
    "wof:placetype":"venue"
},
  "geometry": {"coordinates":[-2.9478569031,43.2599067688],"type":"Point"}
}