{
  "type": "Feature",
  "properties": {
    "addr:full":"Calle de Obispo Salvador De Los Reyes, 5 Malaga M\u00e1laga 29014",
    "addr:housenumber":"5",
    "addr:postcode":"29014",
    "addr:street":"Calle De Obispo Salvador De Los Reyes;Ma\u0301Laga",
    "iso:country":"ES",
    "sg:address":"Calle de Obispo Salvador De Los Reyes, 5",
    "sg:city":"Malaga",
    "sg:orig_category":"Electromec\u00c1nica",
    "sg:phone":"+34 952 65 71 74",
    "sg:postcode":"29014",
    "sg:province":"M\u00e1laga",
    "wof:name":"Automocion Peypa Malaga Sl",
    "wof:placetype":"venue"
},
  "geometry": {"coordinates":[-4.4183425903,36.7357902527],"type":"Point"}
}