{
  "type": "Feature",
  "properties": {
    "addr:full":"Ctra Pandorado, 4 Astorga Le\u00f3n 24700",
    "addr:housenumber":"4",
    "addr:postcode":"24700",
    "addr:street":"Ctra Pandorado;Leo\u0301N",
    "iso:country":"ES",
    "sg:address":"Ctra Pandorado, 4",
    "sg:city":"Astorga",
    "sg:orig_category":"Carnicer\u00cdas, Carnicer\u00cdas",
    "sg:phone":"+34 987 61 89 55",
    "sg:postcode":"24700",
    "sg:province":"Le\u00f3n",
    "wof:name":"Garcia Gonzalez Gregorio",
    "wof:placetype":"venue"
},
  "geometry": {"coordinates":[-6.0533699989,42.4585037231],"type":"Point"}
}