{
  "type": "Feature",
  "properties": {
    "addr:full":"Calle de Antonio Machado, 10 Redovan Alicante 03370",
    "addr:housenumber":"10",
    "addr:postcode":"03370",
    "addr:street":"Calle De Antonio Machado;Alicante",
    "iso:country":"ES",
    "sg:address":"Calle de Antonio Machado, 10",
    "sg:city":"Redovan",
    "sg:orig_category":"Contenedores (mercanc\u00cdas)",
    "sg:phone":"+34 966 75 40 88",
    "sg:postcode":"03370",
    "sg:province":"Alicante",
    "wof:name":"Belmonte Aparicio Manuel",
    "wof:placetype":"venue"
},
  "geometry": {"coordinates":[-0.9106029868,38.1153869629],"type":"Point"}
}