{
  "type": "Feature",
  "properties": {
    "addr:full":"Carrer de Torcuato Luca Tena, 7 Palma Islas Baleares 07005",
    "addr:housenumber":"7",
    "addr:postcode":"07005",
    "addr:street":"Carrer De Torcuato Luca Tena",
    "iso:country":"ES",
    "sg:address":"Carrer de Torcuato Luca Tena, 7",
    "sg:city":"Palma",
    "sg:orig_category":"Droguer\u00cdas (al Por Menor)",
    "sg:phone":"+34 971 24 96 10",
    "sg:postcode":"07005",
    "sg:province":"Islas Baleares",
    "sg:website":"www.schlecker.com",
    "wof:name":"Schlecker S.a.",
    "wof:placetype":"venue"
},
  "geometry": {"coordinates":[2.66375494,39.5759124756],"type":"Point"}
}