{
  "type": "Feature",
  "properties": {
    "iso:country":"ES",
    "sg:address":"Carrer de Aprestadora, 9",
    "sg:city":"Hospitalet Llobregat",
    "sg:orig_category":"Iglesia Cat\u00d3lica",
    "sg:phone":"+34 933 32 78 98",
    "sg:postcode":"08902",
    "sg:province":"Barcelona",
    "wof:name":"Parroquia De San Isidro",
    "wof:placetype":"venue"
},
  "geometry": {"coordinates":[2.1309459209,41.3645133972],"type":"Point"}
}