{
  "type": "Feature",
  "properties": {
    "addr:full":"Rua Rio (do), 9 Burela Lugo 27880",
    "addr:postcode":"27880",
    "addr:street":"Rua",
    "iso:country":"ES",
    "sg:address":"Rua Rio (do), 9",
    "sg:city":"Burela",
    "sg:orig_category":"Abogados",
    "sg:phone":"+34 982 58 16 62",
    "sg:postcode":"27880",
    "sg:province":"Lugo",
    "wof:name":"Tarron Couto Benito Pascual",
    "wof:placetype":"venue"
},
  "geometry": {"coordinates":[-7.3581209183,43.6630134583],"type":"Point"}
}