{
  "type": "Feature",
  "properties": {
    "addr:full":"Calle de San Julian, 8 Albacete Albacete 02001",
    "addr:housenumber":"8",
    "addr:postcode":"02001",
    "addr:street":"Calle De San Julian",
    "iso:country":"ES",
    "sg:address":"Calle de San Julian, 8",
    "sg:city":"Albacete",
    "sg:orig_category":"Cuchiller\u00cda (al Por Menor)",
    "sg:phone":"+34 967 24 65 06",
    "sg:postcode":"02001",
    "sg:province":"Albacete",
    "wof:name":"Bravo Bravo Josefina",
    "wof:placetype":"venue"
},
  "geometry": {"coordinates":[-1.8569689989,38.995880127],"type":"Point"}
}