{
  "type": "Feature",
  "properties": {
    "iso:country":"ES",
    "sg:address":"Carrer de Cafes, 4",
    "sg:city":"Vendrell",
    "sg:orig_category":"Ropa Para Caballeros (al Por Menor)",
    "sg:phone":"+34 977 66 02 24",
    "sg:postcode":"43700",
    "sg:province":"Tarragona",
    "wof:name":"Giro Murtro Rafael",
    "wof:placetype":"venue"
},
  "geometry": {"coordinates":[1.5351799726,41.2214126587],"type":"Point"}
}