{
  "type": "Feature",
  "properties": {
    "iso:country":"ES",
    "sg:address":"Calle de Pedro Cartagena, S/n",
    "sg:city":"Sagunt",
    "sg:orig_category":"Ense\u00d1anza, Formaci\u00d3n Profesional: Aprendizaje",
    "sg:phone":"+34 962 66 41 51",
    "sg:postcode":"46500",
    "sg:province":"Valencia",
    "wof:name":"Teatres De La Generalitat Valenciana",
    "wof:placetype":"venue"
},
  "geometry": {"coordinates":[-0.2763318121,39.6738777161],"type":"Point"}
}