{
  "type": "Feature",
  "properties": {
    "addr:full":"Rbla Josep Antoni Vidal, 26 Vilanova I La Geltru Barcelona 08800",
    "addr:housenumber":"26",
    "addr:postcode":"08800",
    "addr:street":"Rbla Josep Antoni Vidal",
    "iso:country":"ES",
    "sg:address":"Rbla Josep Antoni Vidal, 26",
    "sg:city":"Vilanova I La Geltru",
    "sg:orig_category":"Estancos",
    "sg:phone":"+34 938 15 07 45",
    "sg:postcode":"08800",
    "sg:province":"Barcelona",
    "wof:name":"Tobella Ca\u00d1is Lluis",
    "wof:placetype":"venue"
},
  "geometry": {"coordinates":[1.7248649597,41.2206306458],"type":"Point"}
}