{
  "type": "Feature",
  "properties": {
    "addr:full":"Plaz Domingo Gascon, 5 Teruel Teruel 44001",
    "addr:housenumber":"5",
    "addr:postcode":"44001",
    "addr:street":"Plaz Domingo Gascon",
    "iso:country":"ES",
    "sg:address":"Plaz Domingo Gascon, 5",
    "sg:city":"Teruel",
    "sg:orig_category":"Electricidad: Instaladores",
    "sg:phone":"+34 978 61 85 50",
    "sg:postcode":"44001",
    "sg:province":"Teruel",
    "wof:name":"Garcia Gorbe Elena",
    "wof:placetype":"venue"
},
  "geometry": {"coordinates":[-1.1045490503,40.3420944214],"type":"Point"}
}