{
  "type": "Feature",
  "properties": {
    "iso:country":"ES",
    "sg:address":"Muralla Del Castell, 2",
    "sg:city":"Valls",
    "sg:orig_category":"Electricidad: Instaladores",
    "sg:phone":"+34 977 60 02 47",
    "sg:postcode":"43800",
    "sg:province":"Tarragona",
    "wof:name":"Manresa Dalmau Joan Salvador",
    "wof:placetype":"venue"
},
  "geometry": {"coordinates":[1.2601079941,41.29920578],"type":"Point"}
}