{
  "type": "Feature",
  "properties": {
    "iso:country":"ES",
    "sg:address":"Calle de Ramon Y Cajal, 7",
    "sg:city":"Villanueva Serena",
    "sg:orig_category":"Ropa Para Se\u00d1oras (al Por Menor)",
    "sg:phone":"+34 924 84 53 98",
    "sg:postcode":"06700",
    "sg:province":"Badajoz",
    "sg:website":"www.benetton.com",
    "wof:name":"Modas Benales S.l.",
    "wof:placetype":"venue"
},
  "geometry": {"coordinates":[-5.7990751266,38.9744338989],"type":"Point"}
}