{
  "type": "Feature",
  "properties": {
    "addr:full":"Carrer de Josep Gras, 11 Esplugues Llobregat Barcelona 08950",
    "addr:housenumber":"11",
    "addr:postcode":"08950",
    "addr:street":"Carrer De Josep Gras",
    "iso:country":"ES",
    "sg:address":"Carrer de Josep Gras, 11",
    "sg:city":"Esplugues Llobregat",
    "sg:orig_category":"Quincaller\u00cda (al Por Menor)",
    "sg:phone":"+34 933 72 32 55",
    "sg:postcode":"08950",
    "sg:province":"Barcelona",
    "wof:name":"Vega Pecellin Jacinta",
    "wof:placetype":"venue"
},
  "geometry": {"coordinates":[2.0974829197,41.3699226379],"type":"Point"}
}