{
  "type": "Feature",
  "properties": {
    "addr:full":"Calle de Orense, 39 Madrid Madrid 28020",
    "addr:housenumber":"39",
    "addr:postcode":"madrid;28020",
    "addr:street":"Calle De Orense",
    "iso:country":"ES",
    "sg:address":"Calle de Orense, 39",
    "sg:city":"Madrid",
    "sg:orig_category":"Funcionario De Justicia",
    "sg:phone":"+34 915 55 74 38",
    "sg:postcode":"28020",
    "sg:province":"Madrid",
    "wof:name":"De Luis Diaz-monasterio Felix",
    "wof:placetype":"venue"
},
  "geometry": {"coordinates":[-3.6950850487,40.4538383484],"type":"Point"}
}