{
  "type": "Feature",
  "properties": {
    "iso:country":"ES",
    "sg:address":"Calle de Fuente Vieja (la), 7",
    "sg:city":"Utrera",
    "sg:orig_category":"Bazares, Art\u00cdculos De Limpieza Y De Cocina (al Por Menor)",
    "sg:phone":"+34 955 86 00 63",
    "sg:postcode":"41710",
    "sg:province":"Sevilla",
    "wof:name":"Florido Campos David",
    "wof:placetype":"venue"
},
  "geometry": {"coordinates":[-5.783724308,37.181427002],"type":"Point"}
}