{
  "type": "Feature",
  "properties": {
    "addr:full":"Poli Paz (la), S/n Teruel Teruel 44195",
    "addr:postcode":"44195",
    "addr:street":"La S / N;Teruel",
    "iso:country":"ES",
    "sg:address":"Poli Paz (la), S/n",
    "sg:city":"Teruel",
    "sg:orig_category":"Arenas, Guijarros Y Granulados",
    "sg:phone":"+34 978 61 08 70",
    "sg:postcode":"44195",
    "sg:province":"Teruel",
    "wof:name":"Hormigones La Paz S.l.",
    "wof:placetype":"venue"
},
  "geometry": {"coordinates":[-1.1755470037,40.358417511],"type":"Point"}
}