{
  "type": "Feature",
  "properties": {
    "addr:full":"Pase Cordon (del), 81 Villarrubia De Los Ojos Ciudad Real 13670",
    "addr:postcode":"13670",
    "iso:country":"ES",
    "sg:address":"Pase Cordon (del), 81",
    "sg:city":"Villarrubia De Los Ojos",
    "sg:orig_category":"Molduras, Junquillos, Listones Y Molduras Perforadas",
    "sg:phone":"+34 926 89 72 41",
    "sg:postcode":"13670",
    "sg:province":"Ciudad Real",
    "wof:name":"Carretero Zamora Rosario",
    "wof:placetype":"venue"
},
  "geometry": {"coordinates":[-3.6060490608,39.2222137451],"type":"Point"}
}