{
  "type": "Feature",
  "properties": {
    "addr:full":"Plaz Houston De, 1 Huelva Huelva 21006",
    "addr:postcode":"21006",
    "iso:country":"ES",
    "sg:address":"Plaz Houston De, 1",
    "sg:city":"Huelva",
    "sg:orig_category":"Cl\u00cdnicas Dentales",
    "sg:phone":"+34 959 27 07 40",
    "sg:postcode":"21006",
    "sg:province":"Huelva",
    "wof:name":"Martin Garcia Raquel",
    "wof:placetype":"venue"
},
  "geometry": {"coordinates":[-6.9386649132,37.2594413757],"type":"Point"}
}