{
  "type": "Feature",
  "properties": {
    "addr:full":"Avda Reina Mercedes, 19 Sevilla Sevilla 41012",
    "addr:housenumber":"19",
    "addr:postcode":"41012",
    "addr:street":"Avda Reina Mercedes",
    "iso:country":"ES",
    "sg:address":"Avda Reina Mercedes, 19",
    "sg:city":"Sevilla",
    "sg:orig_category":"Radiocomunicaciones, Telefon\u00cda M\u00d3vil, Radiomensajer\u00cda: Servicios, Comercializaci\u00d3n",
    "sg:phone":"+34 954 23 21 79",
    "sg:postcode":"41012",
    "sg:province":"Sevilla",
    "wof:name":"Tobar Telefonia Movil S.c.",
    "wof:placetype":"venue"
},
  "geometry": {"coordinates":[-5.986178875,37.3608016968],"type":"Point"}
}