{
  "type": "Feature",
  "properties": {
    "addr:full":"Avda Marques De La Vega De Armijo, 73 Montilla C\u00f3rdoba 14550",
    "addr:housenumber":"73",
    "addr:postcode":"14550",
    "addr:street":"Avda Marques De La Vega De Armijo;Co\u0301Rdoba",
    "iso:country":"ES",
    "sg:address":"Avda Marques De La Vega De Armijo, 73",
    "sg:city":"Montilla",
    "sg:orig_category":"Empresas De Carpinter\u00cda",
    "sg:phone":"+34 957 65 66 45",
    "sg:postcode":"14550",
    "sg:province":"C\u00f3rdoba",
    "wof:name":"Aluminios Y Cristales De Cordoba S.l.",
    "wof:placetype":"venue"
},
  "geometry": {"coordinates":[-4.6322464943,37.5863494873],"type":"Point"}
}