{
  "type": "Feature",
  "properties": {
    "addr:full":"Plaz Primero De Mayo, S/n Melilla Melilla 52003",
    "addr:housenumber":"s / n",
    "addr:postcode":"52003",
    "addr:street":"Plaz Primero;Mayo",
    "iso:country":"ES",
    "sg:address":"Plaz Primero De Mayo, S/n",
    "sg:city":"Melilla",
    "sg:orig_category":"Internados & Ense\u00d1anza Privada",
    "sg:phone":"+34 952 67 61 12",
    "sg:postcode":"52003",
    "sg:province":"Melilla",
    "wof:name":"Instituto De Formacion Y Estudios Sociales",
    "wof:placetype":"venue"
},
  "geometry": {"coordinates":[-2.955919981,35.3033714294],"type":"Point"}
}