{
  "type": "Feature",
  "properties": {
    "iso:country":"ES",
    "sg:address":"Avda Gran Via, 114",
    "sg:city":"Vigo",
    "sg:orig_category":"Mutuas De Seguros",
    "sg:phone":"+34 986 41 57 11",
    "sg:postcode":"36203",
    "sg:province":"Pontevedra",
    "wof:name":"Fraternidad-muprespa Mutua De Accidentes De Trabajo Y Enfermedades Profesionales",
    "wof:placetype":"venue"
},
  "geometry": {"coordinates":[-8.7232446671,42.2245635986],"type":"Point"}
}