{
  "type": "Feature",
  "properties": {
    "addr:full":"Carrer de Pintor Antonio Lopez, 7 Guardamar Segura Alicante 03140",
    "addr:housenumber":"7",
    "addr:postcode":"03140",
    "addr:street":"Carrer De Pintor Antonio Lopez",
    "iso:country":"ES",
    "sg:address":"Carrer de Pintor Antonio Lopez, 7",
    "sg:city":"Guardamar Segura",
    "sg:orig_category":"Asesor\u00cda Sobre Comunicaci\u00d3n De Empresas",
    "sg:phone":"+34 966 72 66 26",
    "sg:postcode":"03140",
    "sg:province":"Alicante",
    "wof:name":"Garrido Monta\u00d1es Manuel",
    "wof:placetype":"venue"
},
  "geometry": {"coordinates":[-0.6537879705,38.0812263489],"type":"Point"}
}