{
  "type": "Feature",
  "properties": {
    "iso:country":"ES",
    "sg:address":"Calle de Juan Garcia Abellan, 8",
    "sg:city":"Flota",
    "sg:orig_category":"Tapiceros Y Tapiceros",
    "sg:phone":"+34 968 24 03 09",
    "sg:postcode":"30007",
    "sg:province":"Murcia",
    "wof:name":"Fernandez Pedre\u00f1o Jose",
    "wof:placetype":"venue"
},
  "geometry": {"coordinates":[-1.1142389774,37.9970092773],"type":"Point"}
}