{
  "type": "Feature",
  "properties": {
    "addr:full":"Calle de Bellavista, S/n Columbrianos Le\u00f3n 24490",
    "addr:housenumber":"s",
    "addr:postcode":"24490",
    "addr:street":"Calle De Bellavista;/ N Columbrianos Leo\u0301N",
    "iso:country":"ES",
    "sg:address":"Calle de Bellavista, S/n",
    "sg:city":"Columbrianos",
    "sg:orig_category":"Construcciones Met\u00c1licas",
    "sg:phone":"+34 987 41 23 79",
    "sg:postcode":"24490",
    "sg:province":"Le\u00f3n",
    "wof:name":"Baudimetal S.l.",
    "wof:placetype":"venue"
},
  "geometry": {"coordinates":[-6.6084270477,42.5627708435],"type":"Point"}
}