{
  "type": "Feature",
  "properties": {
    "iso:country":"ES",
    "sg:address":"Avda Medina Olmos, 8",
    "sg:city":"Guadix",
    "sg:orig_category":"Ropa Para Se\u00d1oras (al Por Menor)",
    "sg:phone":"+34 958 66 50 40",
    "sg:postcode":"18500",
    "sg:province":"Granada",
    "sg:website":"www.amichi.com",
    "wof:name":"Medialdea Casado Maria Del Carmen",
    "wof:placetype":"venue"
},
  "geometry": {"coordinates":[-3.13230896,37.3007698059],"type":"Point"}
}