{
  "type": "Feature",
  "properties": {
    "addr:full":"Calle de Robleda, 24 Fuenteguinaldo Salamanca 37540",
    "addr:housenumber":"24",
    "addr:postcode":"37540",
    "addr:street":"Calle De Robleda",
    "iso:country":"ES",
    "sg:address":"Calle de Robleda, 24",
    "sg:city":"Fuenteguinaldo",
    "sg:orig_category":"Empresas De Carpinter\u00cda",
    "sg:phone":"+34 923 47 12 00",
    "sg:postcode":"37540",
    "sg:province":"Salamanca",
    "wof:name":"Villoria Paton Olegario",
    "wof:placetype":"venue"
},
  "geometry": {"coordinates":[-6.6726365089,40.4274406433],"type":"Point"}
}