{
  "type": "Feature",
  "properties": {
    "iso:country":"ES",
    "sg:address":"Ptda Pla De La Vallonga, S/n",
    "sg:city":"Pla De La Vallonga",
    "sg:orig_category":"Fabricaci\u00d3n De Distribuidores Autom\u00c1ticos",
    "sg:phone":"+34 965 10 65 05",
    "sg:postcode":"03113",
    "sg:province":"Alicante",
    "wof:name":"Logivend S.l.",
    "wof:placetype":"venue"
},
  "geometry": {"coordinates":[-0.5904179811,38.3435401917],"type":"Point"}
}