{
  "type": "Feature",
  "properties": {
    "addr:full":"Zubillaga Auzoa, 87 Zubillaga Guip\u00f9zcoa 20569",
    "addr:housenumber":"87",
    "addr:postcode":"20569",
    "addr:street":"Zubillaga Auzoa;Guipu\u0300Zcoa",
    "iso:country":"ES",
    "sg:address":"Zubillaga Auzoa, 87",
    "sg:city":"Zubillaga",
    "sg:orig_category":"Comercio De Hierro",
    "sg:phone":"+34 943 71 64 85",
    "sg:postcode":"20569",
    "sg:province":"Guip\u00f9zcoa",
    "wof:name":"Hierros Alo\u00f1a S.a.",
    "wof:placetype":"venue"
},
  "geometry": {"coordinates":[-2.4320240021,43.0534896851],"type":"Point"}
}