{
  "type": "Feature",
  "properties": {
    "iso:country":"ES",
    "sg:address":"Calle de Silos, 93",
    "sg:city":"Alcala Guadaira",
    "sg:orig_category":"Peluqueros: De Se\u00d1oras",
    "sg:phone":"+34 955 62 17 67",
    "sg:postcode":"41500",
    "sg:province":"Sevilla",
    "sg:website":"www.spejos.es",
    "wof:name":"Spejo's Difusion S.l.",
    "wof:placetype":"venue"
},
  "geometry": {"coordinates":[-5.8443627357,37.346157074],"type":"Point"}
}