{
  "type": "Feature",
  "properties": {
    "addr:full":"Rond Sant Antoni Maria Claret, 20 Girona Girona 17001",
    "addr:housenumber":"20",
    "addr:postcode":"17001",
    "addr:street":"Sant Antoni Maria Claret",
    "iso:country":"ES",
    "sg:address":"Rond Sant Antoni Maria Claret, 20",
    "sg:city":"Girona",
    "sg:orig_category":"Restaurantes",
    "sg:phone":"+34 972 20 58 33",
    "sg:postcode":"17001",
    "sg:province":"Girona",
    "wof:name":"Catering Bofill S.l.",
    "wof:placetype":"venue"
},
  "geometry": {"coordinates":[2.8206520081,41.9795684814],"type":"Point"}
}