{
  "type": "Feature",
  "properties": {
    "addr:full":"Calle de Zubiaurre, 63 Donostia-san Sebastian Guip\u00f9zcoa 20015",
    "addr:housenumber":"63",
    "addr:postcode":"20015",
    "addr:street":"Calle De Zubiaurre",
    "iso:country":"ES",
    "sg:address":"Calle de Zubiaurre, 63",
    "sg:city":"Donostia-san Sebastian",
    "sg:orig_category":"Cajas De Ahorro",
    "sg:phone":"+34 943 27 46 88",
    "sg:postcode":"20015",
    "sg:province":"Guip\u00f9zcoa",
    "wof:name":"Caixa D'estalvis I Pensions De Barcelona",
    "wof:placetype":"venue"
},
  "geometry": {"coordinates":[-1.9523459673,43.3198547363],"type":"Point"}
}