{
  "type": "Feature",
  "properties": {
    "addr:full":"Ptda Garganta, 5 Crevillente Alicante 03330",
    "addr:housenumber":"5",
    "addr:postcode":"03330",
    "addr:street":"Ptda Garganta",
    "iso:country":"ES",
    "sg:address":"Ptda Garganta, 5",
    "sg:city":"Crevillente",
    "sg:orig_category":"Fabricaci\u00d3n De Bibliotecas Y Estanter\u00cdas",
    "sg:phone":"+34 966 67 56 35",
    "sg:postcode":"03330",
    "sg:province":"Alicante",
    "sg:website":"www.ili-stand.com",
    "wof:name":"Anylu Equipamientos S.l.",
    "wof:placetype":"venue"
},
  "geometry": {"coordinates":[-0.8079771996,38.2478981018],"type":"Point"}
}