{
  "type": "Feature",
  "properties": {
    "iso:country":"ES",
    "sg:address":"C. Sotelo, 18",
    "sg:city":"Casas De Reina",
    "sg:orig_category":"Charcuter\u00cdas (al Por Mayor)",
    "sg:phone":"+34 924 87 23 77",
    "sg:postcode":"06960",
    "sg:province":"Badajoz",
    "wof:name":"Palacios Milans Angel",
    "wof:placetype":"venue"
},
  "geometry": {"coordinates":[-5.970181942,38.1995201111],"type":"Point"}
}