{
  "type": "Feature",
  "properties": {
    "iso:country":"ES",
    "sg:address":"Calle de Embajador Vich, 3",
    "sg:city":"Valencia",
    "sg:orig_category":"Empresas De Limpieza",
    "sg:phone":"+34 963 51 06 92",
    "sg:postcode":"46002",
    "sg:province":"Valencia",
    "wof:name":"Amelim S.a.",
    "wof:placetype":"venue"
},
  "geometry": {"coordinates":[-0.3754071891,39.4727172852],"type":"Point"}
}