{
  "type": "Feature",
  "properties": {
    "addr:full":"Carr Moreres, 1 Mao Islas Baleares 07703",
    "addr:housenumber":"1",
    "addr:postcode":"07703",
    "addr:street":"Carr Moreres",
    "iso:country":"ES",
    "sg:address":"Carr Moreres, 1",
    "sg:city":"Mao",
    "sg:orig_category":"Art\u00cdculos De Regalo (al Por Menor)",
    "sg:phone":"+34 971 35 05 42",
    "sg:postcode":"07703",
    "sg:province":"Islas Baleares",
    "wof:name":"Pons Pons Carmen",
    "wof:placetype":"venue"
},
  "geometry": {"coordinates":[4.262816906,39.8883781433],"type":"Point"}
}