{
  "type": "Feature",
  "properties": {
    "addr:full":"Pase Pontones, 28 Madrid Madrid 28005",
    "addr:housenumber":"28",
    "addr:postcode":"madrid;28005",
    "iso:country":"ES",
    "sg:address":"Pase Pontones, 28",
    "sg:city":"Madrid",
    "sg:orig_category":"Art\u00cdculos De Regalo (al Por Menor)",
    "sg:phone":"+34 913 65 99 46",
    "sg:postcode":"28005",
    "sg:province":"Madrid",
    "wof:name":"Ca\u00f1adas Lopez Gloria",
    "wof:placetype":"venue"
},
  "geometry": {"coordinates":[-3.7057740688,40.42029953],"type":"Point"}
}