{
  "type": "Feature",
  "properties": {
    "addr:full":"Plaz Colon (de), 9 Cordoba C\u00f3rdoba 14001",
    "addr:postcode":"14001",
    "addr:street":"Co\u0301Rdoba",
    "iso:country":"ES",
    "sg:address":"Plaz Colon (de), 9",
    "sg:city":"Cordoba",
    "sg:orig_category":"Abogados",
    "sg:phone":"+34 957 49 05 46",
    "sg:postcode":"14001",
    "sg:province":"C\u00f3rdoba",
    "wof:name":"Rey Puyou Manuel",
    "wof:placetype":"venue"
},
  "geometry": {"coordinates":[-4.7768039703,37.8888473511],"type":"Point"}
}