{
  "type": "Feature",
  "properties": {
    "addr:full":"Calle de Obispo Jaime Perez, 13 Valencia Valencia 46006",
    "addr:housenumber":"13",
    "addr:postcode":"46006",
    "addr:street":"Calle De Obispo Jaime Perez",
    "iso:country":"ES",
    "sg:address":"Calle de Obispo Jaime Perez, 13",
    "sg:city":"Valencia",
    "sg:orig_category":"Librer\u00cdas",
    "sg:phone":"+34 963 33 06 19",
    "sg:postcode":"46006",
    "sg:province":"Valencia",
    "wof:name":"Edisol Libros S.l.",
    "wof:placetype":"venue"
},
  "geometry": {"coordinates":[-0.3660480082,39.4590454102],"type":"Point"}
}