{
  "type": "Feature",
  "properties": {
    "iso:country":"ES",
    "sg:address":"Entrada, 125",
    "sg:city":"Benaguasil",
    "sg:orig_category":"Molduras, Junquillos, Listones Y Molduras Perforadas",
    "sg:phone":"+34 962 73 03 64",
    "sg:postcode":"46180",
    "sg:province":"Valencia",
    "wof:name":"Real Arrue Enrique",
    "wof:placetype":"venue"
},
  "geometry": {"coordinates":[-0.5919209719,39.5934066772],"type":"Point"}
}