{
  "type": "Feature",
  "properties": {
    "addr:full":"Carr Sant Josep, 18 Mas Aliu Girona 17181",
    "addr:housenumber":"18",
    "addr:postcode":"17181",
    "addr:street":"Carr Sant Josep",
    "iso:country":"ES",
    "sg:address":"Carr Sant Josep, 18",
    "sg:city":"Mas Aliu",
    "sg:orig_category":"Maquinaria Para Industrias Diversas",
    "sg:phone":"+34 972 23 83 92",
    "sg:postcode":"17181",
    "sg:province":"Girona",
    "wof:name":"Peima S.cv.",
    "wof:placetype":"venue"
},
  "geometry": {"coordinates":[2.7822089195,41.9453315735],"type":"Point"}
}