{
  "type": "Feature",
  "properties": {
    "iso:country":"ES",
    "sg:address":"Calle de San Sebastian, 13",
    "sg:city":"Campillos",
    "sg:orig_category":"Muebles, Minoristas",
    "sg:phone":"+34 952 72 33 62",
    "sg:postcode":"29320",
    "sg:province":"M\u00e1laga",
    "wof:name":"Sanchez Sanchez Miguel",
    "wof:placetype":"venue"
},
  "geometry": {"coordinates":[-4.8639302254,37.0474662781],"type":"Point"}
}