{
  "type": "Feature",
  "properties": {
    "iso:country":"ES",
    "sg:address":"Calle de Voladero, 31",
    "sg:city":"Ciudad Rodrigo",
    "sg:orig_category":"Empresas De Pintura Y Revestimientos",
    "sg:phone":"+34 923 46 25 53",
    "sg:postcode":"37500",
    "sg:province":"Salamanca",
    "wof:name":"Losada Estevez Jesus",
    "wof:placetype":"venue"
},
  "geometry": {"coordinates":[-6.5243291855,40.5990982056],"type":"Point"}
}