{
  "type": "Feature",
  "properties": {
    "iso:country":"ES",
    "sg:address":"Calle de Francisco De Medina Y Mendoza, 12",
    "sg:city":"Cabanillas Campo",
    "sg:orig_category":"Adaptaciones, Acondicionamientos Especiales Para Veh\u00cdculos, Veh\u00cdculos Industriales",
    "sg:phone":"+34 949 20 70 75",
    "sg:postcode":"19171",
    "sg:province":"Guadalajara",
    "wof:name":"Imlfernovuis T15 S.l.",
    "wof:placetype":"venue"
},
  "geometry": {"coordinates":[-3.2059490681,40.6179618835],"type":"Point"}
}