{
  "type": "Feature",
  "properties": {
    "iso:country":"ES",
    "sg:address":"Calle de Gran Via, 63",
    "sg:city":"Hellin",
    "sg:classifiers":[
        {
            "category":"Taxi",
            "type":"Transportation"
        }
    ],
    "sg:phone":"+34 967 30 33 71",
    "sg:postcode":"02400",
    "sg:province":"Albacete",
    "wof:name":"Morcillo Garcia Jesus",
    "wof:placetype":"venue"
},
  "geometry": {"coordinates":[-1.7034820318,38.5079460144],"type":"Point"}
}