{
  "type": "Feature",
  "properties": {
    "iso:country":"ES",
    "sg:address":"Pg. Platja, S/n",
    "sg:city":"Escala",
    "sg:orig_category":"Restaurantes",
    "sg:phone":"+34 972 77 10 02",
    "sg:postcode":"17130",
    "sg:province":"Girona",
    "wof:name":"Serveis Hotelers Cala Montgo S. L.",
    "wof:placetype":"venue"
},
  "geometry": {"coordinates":[3.1336700916,42.1263389587],"type":"Point"}
}