{
  "type": "Feature",
  "properties": {
    "iso:country":"ES",
    "sg:address":"Calle de Juan Ramon Jimenez, 1",
    "sg:city":"Albacete",
    "sg:orig_category":"Caf\u00c9s, Bares, Cervecer\u00cdas",
    "sg:phone":"+34 967 21 21 85",
    "sg:postcode":"02001",
    "sg:province":"Albacete",
    "wof:name":"Lopez Illera Benito Luis",
    "wof:placetype":"venue"
},
  "geometry": {"coordinates":[-1.8472249508,38.9977645874],"type":"Point"}
}