{
  "type": "Feature",
  "properties": {
    "addr:full":"Calle de Padre Tenaguillo, 8 Avila \u00c1vila 05004",
    "addr:housenumber":"8",
    "addr:postcode":"05004",
    "addr:street":"Calle De Padre Tenaguillo;A\u0301Vila",
    "iso:country":"ES",
    "sg:address":"Calle de Padre Tenaguillo, 8",
    "sg:city":"Avila",
    "sg:orig_category":"Cr\u00cda De Animales",
    "sg:phone":"+34 920 21 13 49",
    "sg:postcode":"05004",
    "sg:province":"\u00c1vila",
    "wof:name":"Asociacion Nacional De Criadores De Ganado Vacuno De Raza Avile\u00f1a-negra Iberica",
    "wof:placetype":"venue"
},
  "geometry": {"coordinates":[-4.6679339409,40.6612014771],"type":"Point"}
}