{
  "type": "Feature",
  "properties": {
    "addr:full":"Pol Ind Los Ventolines, 136 Pilas Sevilla 41840",
    "addr:housenumber":"136",
    "addr:postcode":"41840",
    "iso:country":"ES",
    "sg:address":"Pol Ind Los Ventolines, 136",
    "sg:city":"Pilas",
    "sg:orig_category":"Suministros Para Carrocer\u00cdas",
    "sg:phone":"+34 954 75 16 13",
    "sg:postcode":"41840",
    "sg:province":"Sevilla",
    "wof:name":"La Nueva Talleres Zitros Sl",
    "wof:placetype":"venue"
},
  "geometry": {"coordinates":[-6.3043088913,37.3053894043],"type":"Point"}
}