{
  "type": "Feature",
  "properties": {
    "iso:country":"ES",
    "sg:address":"Calle de Coso Bajo, 66",
    "sg:city":"Huesca",
    "sg:orig_category":"Institutos De Belleza",
    "sg:phone":"+34 974 23 13 35",
    "sg:postcode":"22001",
    "sg:province":"Huesca",
    "wof:name":"Aladren Camino Concepcion",
    "wof:placetype":"venue"
},
  "geometry": {"coordinates":[-0.405411005,42.1388549805],"type":"Point"}
}