{
  "type": "Feature",
  "properties": {
    "iso:country":"ES",
    "sg:address":"Uhaitz Kalea, 2",
    "sg:city":"Lazkao",
    "sg:orig_category":"Pescader\u00cdas (al Por Menor)",
    "sg:phone":"+34 943 88 24 44",
    "sg:postcode":"20210",
    "sg:province":"Guip\u00f9zcoa",
    "wof:name":"Soraluce Lete Jose Maria",
    "wof:placetype":"venue"
},
  "geometry": {"coordinates":[-2.1862709522,43.0338172913],"type":"Point"}
}