{
  "type": "Feature",
  "properties": {
    "iso:country":"ES",
    "sg:address":"Avda Guadiana, S/n",
    "sg:city":"Badajoz",
    "sg:orig_category":"Ropa Para Se\u00d1oras (al Por Menor)",
    "sg:phone":"+34 924 24 66 53",
    "sg:postcode":"06011",
    "sg:province":"Badajoz",
    "wof:name":"Maria Fagundez Francisco Javier",
    "wof:placetype":"venue"
},
  "geometry": {"coordinates":[-6.9874839783,38.8731384277],"type":"Point"}
}