{
  "type": "Feature",
  "properties": {
    "iso:country":"ES",
    "sg:address":"Calle de Miguel Rios, 1",
    "sg:city":"Chauchina",
    "sg:orig_category":"Quincaller\u00cda (al Por Menor)",
    "sg:phone":"+34 958 44 63 43",
    "sg:postcode":"18330",
    "sg:province":"Granada",
    "wof:name":"Canas De La Fuente Tomasa",
    "wof:placetype":"venue"
},
  "geometry": {"coordinates":[-3.7702291012,37.2024650574],"type":"Point"}
}