{
  "type": "Feature",
  "properties": {
    "addr:full":"Calle de Urquiza, 9 Sevilla Sevilla 41003",
    "addr:housenumber":"9",
    "addr:postcode":"41003",
    "addr:street":"Calle De Urquiza",
    "iso:country":"ES",
    "sg:address":"Calle de Urquiza, 9",
    "sg:city":"Sevilla",
    "sg:orig_category":"Peluqueros: De Se\u00d1oras",
    "sg:phone":"+34 954 42 66 15",
    "sg:postcode":"41003",
    "sg:province":"Sevilla",
    "wof:name":"Arevalo Jimenez Isabel",
    "wof:placetype":"venue"
},
  "geometry": {"coordinates":[-5.9791512489,37.3941955566],"type":"Point"}
}