{
  "type": "Feature",
  "properties": {
    "addr:full":"Calle de Celestino Alvarez, 5 Oviedo Asturias 33011",
    "addr:housenumber":"5",
    "addr:postcode":"33011",
    "addr:street":"Calle De Celestino Alvarez",
    "iso:country":"ES",
    "sg:address":"Calle de Celestino Alvarez, 5",
    "sg:city":"Oviedo",
    "sg:orig_category":"Material Y Suministros Para Minas Y Canteras",
    "sg:phone":"+34 985 20 81 92",
    "sg:postcode":"33011",
    "sg:province":"Asturias",
    "wof:name":"Ingenieria Mecanica Y Minera S.a.",
    "wof:placetype":"venue"
},
  "geometry": {"coordinates":[-5.8653450012,43.3525428772],"type":"Point"}
}