{
  "type": "Feature",
  "properties": {
    "iso:country":"ES",
    "sg:address":"Avda Antibioticos, 110",
    "sg:city":"Armunia",
    "sg:orig_category":"Molduras, Junquillos, Listones Y Molduras Perforadas",
    "sg:phone":"+34 987 20 10 17",
    "sg:postcode":"24009",
    "sg:province":"Le\u00f3n",
    "wof:name":"Hermanas Godos C.b.",
    "wof:placetype":"venue"
},
  "geometry": {"coordinates":[-5.5836958885,42.5785598755],"type":"Point"}
}