{
  "type": "Feature",
  "properties": {
    "addr:full":"Muel Nardiz Tar Benanzio, S/n Bermeo Vizcaya 48370",
    "addr:housenumber":"s / n",
    "addr:postcode":"48370",
    "iso:country":"ES",
    "sg:address":"Muel Nardiz Tar Benanzio, S/n",
    "sg:city":"Bermeo",
    "sg:classifiers":[
        {
            "category":"Recreation",
            "type":"Entertainment"
        }
    ],
    "sg:phone":"+34 946 88 43 72",
    "sg:postcode":"48370",
    "sg:province":"Vizcaya",
    "sg:tags":[
        "caza",
        "pr\u00c1ctica",
        "la",
        "de",
        "pesca",
        "y"
    ],
    "wof:name":"Cofradia De Pescadores San Pedro De Bermeo",
    "wof:placetype":"venue"
},
  "geometry": {"coordinates":[-2.720510006,43.4195022583],"type":"Point"}
}