{
  "type": "Feature",
  "properties": {
    "addr:full":"Carrer de Regal, 16 Palma Islas Baleares 07007",
    "addr:housenumber":"16",
    "addr:postcode":"07007",
    "addr:street":"Carrer De Regal",
    "iso:country":"ES",
    "sg:address":"Carrer de Regal, 16",
    "sg:city":"Palma",
    "sg:orig_category":"Centros De Educaci\u00d3n Especial",
    "sg:phone":"+34 971 27 49 29",
    "sg:postcode":"07007",
    "sg:province":"Islas Baleares",
    "wof:name":"Co%egi Public La Soledat",
    "wof:placetype":"venue"
},
  "geometry": {"coordinates":[2.6734099388,39.5722503662],"type":"Point"}
}