{
  "type": "Feature",
  "properties": {
    "addr:full":"Carrer de Milanesat, 14 Barcelona Barcelona 08017",
    "addr:housenumber":"14",
    "addr:postcode":"08017",
    "addr:street":"Carrer De Milanesat",
    "iso:country":"ES",
    "sg:address":"Carrer de Milanesat, 14",
    "sg:city":"Barcelona",
    "sg:orig_category":"Alimentaci\u00d3n General (al Por Menor)",
    "sg:phone":"+34 932 03 26 87",
    "sg:postcode":"08017",
    "sg:province":"Barcelona",
    "wof:name":"Fernandez Prieto Fernando",
    "wof:placetype":"venue"
},
  "geometry": {"coordinates":[2.1289739609,41.3971099854],"type":"Point"}
}