{
  "type": "Feature",
  "properties": {
    "addr:full":"Calle de Canga Arguelles, 16 Gijon Asturias 33202",
    "addr:housenumber":"16",
    "addr:postcode":"33202",
    "addr:street":"Calle De Canga Arguelles",
    "iso:country":"ES",
    "sg:address":"Calle de Canga Arguelles, 16",
    "sg:city":"Gijon",
    "sg:orig_category":"Art\u00cdculos De Decoraci\u00d3n (fabricaci\u00d3n Y Al Por Mayor)",
    "sg:phone":"+34 985 33 55 31",
    "sg:postcode":"33202",
    "sg:province":"Asturias",
    "wof:name":"Suarez Martin Jose Luis",
    "wof:placetype":"venue"
},
  "geometry": {"coordinates":[-5.6506576538,43.5387840271],"type":"Point"}
}