{
  "type": "Feature",
  "properties": {
    "addr:full":"Calle de Bernardo Alfageme, 15 Candas Asturias 33430",
    "addr:housenumber":"15",
    "addr:postcode":"33430",
    "addr:street":"Calle De Bernardo Alfageme",
    "iso:country":"ES",
    "sg:address":"Calle de Bernardo Alfageme, 15",
    "sg:city":"Candas",
    "sg:orig_category":"Arquitectos",
    "sg:phone":"+34 985 88 51 02",
    "sg:postcode":"33430",
    "sg:province":"Asturias",
    "wof:name":"Fernandez Aller Violeta",
    "wof:placetype":"venue"
},
  "geometry": {"coordinates":[-5.7674593925,43.5898551941],"type":"Point"}
}