{
  "type": "Feature",
  "properties": {
    "iso:country":"ES",
    "sg:address":"Avda Conde Campomanes, 3",
    "sg:city":"Tineo",
    "sg:orig_category":"Papeler\u00cdas, Librer\u00cdas",
    "sg:phone":"+34 985 80 13 24",
    "sg:postcode":"33870",
    "sg:province":"Asturias",
    "wof:name":"Garcia Garcia Manuel",
    "wof:placetype":"venue"
},
  "geometry": {"coordinates":[-6.4163022041,43.33385849],"type":"Point"}
}