{
  "type": "Feature",
  "properties": {
    "addr:full":"Ctra Barcelona, Km. 0006,0 Barbera Valles Barcelona 08210",
    "addr:postcode":"08210",
    "addr:street":"Ctra Barcelona Km. 0006,0",
    "iso:country":"ES",
    "sg:address":"Ctra Barcelona, Km. 0006,0",
    "sg:city":"Barbera Valles",
    "sg:orig_category":"Zapatos (al Por Menor)",
    "sg:phone":"+34 937 18 93 50",
    "sg:postcode":"08210",
    "sg:province":"Barcelona",
    "wof:name":"Yorga S. A.",
    "wof:placetype":"venue"
},
  "geometry": {"coordinates":[2.1270000935,41.5181808472],"type":"Point"}
}