{
  "type": "Feature",
  "properties": {
    "iso:country":"ES",
    "sg:address":"Calle de Padre Lara\u00d1a, 1",
    "sg:city":"Huelva",
    "sg:orig_category":"M\u00c9dicos: Medicina General",
    "sg:phone":"+34 959 26 23 02",
    "sg:postcode":"21003",
    "sg:province":"Huelva",
    "wof:name":"Centro Huelva S. L.",
    "wof:placetype":"venue"
},
  "geometry": {"coordinates":[-6.9438199997,37.2537155151],"type":"Point"}
}