{
  "type": "Feature",
  "properties": {
    "addr:full":"Calle de Real, 43 Estacion Madrid 28400",
    "addr:housenumber":"43",
    "addr:postcode":"28400",
    "addr:street":"Calle De Real",
    "iso:country":"ES",
    "sg:address":"Calle de Real, 43",
    "sg:city":"Estacion",
    "sg:classifiers":[
        {
            "category":"Casinos & Gambling",
            "type":"Entertainment"
        }
    ],
    "sg:phone":"+34 918 50 03 81",
    "sg:postcode":"28400",
    "sg:province":"Madrid",
    "sg:tags":[
        "locale",
        "de",
        "juego"
    ],
    "wof:name":"Multiocio La Sierra S.l.",
    "wof:placetype":"venue"
},
  "geometry": {"coordinates":[-3.5821557045,40.453994751],"type":"Point"}
}