{
  "type": "Feature",
  "properties": {
    "iso:country":"ES",
    "sg:address":"Calle de Sorni, 12",
    "sg:city":"Valencia",
    "sg:orig_category":"Electromedicina: Equipo",
    "sg:phone":"+34 963 51 54 92",
    "sg:postcode":"46004",
    "sg:province":"Valencia",
    "wof:name":"Millas Covas Carlos Francisco",
    "wof:placetype":"venue"
},
  "geometry": {"coordinates":[-0.3691489995,39.4701385498],"type":"Point"}
}