{
  "type": "Feature",
  "properties": {
    "addr:full":"Calle de Conde Aranda, 41 Zaragoza Zaragoza 50004",
    "addr:housenumber":"41",
    "addr:postcode":"50004",
    "addr:street":"Calle De Conde Aranda",
    "iso:country":"ES",
    "sg:address":"Calle de Conde Aranda, 41",
    "sg:city":"Zaragoza",
    "sg:orig_category":"Institutos De Belleza",
    "sg:phone":"+34 976 43 19 92",
    "sg:postcode":"50004",
    "sg:province":"Zaragoza",
    "wof:name":"Centro Estetico Mary Adan S.cv.",
    "wof:placetype":"venue"
},
  "geometry": {"coordinates":[-0.8882700801,41.6551017761],"type":"Point"}
}