{
  "type": "Feature",
  "properties": {
    "addr:full":"Plaz Mayor, 1 Titulcia Madrid 28359",
    "addr:housenumber":"1",
    "addr:postcode":"28359",
    "addr:street":"Plaz Mayor",
    "iso:country":"ES",
    "sg:address":"Plaz Mayor, 1",
    "sg:city":"Titulcia",
    "sg:orig_category":"Administraciones Regionales, Departamentales Y Locales",
    "sg:phone":"+34 918 01 02 71",
    "sg:postcode":"28359",
    "sg:province":"Madrid",
    "wof:name":"Ayuntamiento De Titulcia",
    "wof:placetype":"venue"
},
  "geometry": {"coordinates":[-3.5708999634,40.1358833313],"type":"Point"}
}