{
  "type": "Feature",
  "properties": {
    "iso:country":"ES",
    "sg:address":"Carr Pinell, 4",
    "sg:city":"Llafranc",
    "sg:orig_category":"Goma: Productos De Uso Industrial (fabricaci\u00d3n, Al Por Mayor)",
    "sg:phone":"+34 972 61 04 26",
    "sg:postcode":"17211",
    "sg:province":"Girona",
    "wof:name":"Area Codolar S.l.",
    "wof:placetype":"venue"
},
  "geometry": {"coordinates":[3.1998353004,41.8921928406],"type":"Point"}
}