{
  "type": "Feature",
  "properties": {
    "addr:full":"Calle de San Prudencio, 6 Najera La Rioja 26300",
    "addr:housenumber":"6",
    "addr:postcode":"26300",
    "addr:street":"Calle De San Prudencio;Rioja",
    "iso:country":"ES",
    "sg:address":"Calle de San Prudencio, 6",
    "sg:city":"Najera",
    "sg:orig_category":"Asilos De Ancianos. Centros Privados",
    "sg:phone":"+34 941 36 37 58",
    "sg:postcode":"26300",
    "sg:province":"La Rioja",
    "wof:name":"Mensajeros De La Paz Scp",
    "wof:placetype":"venue"
},
  "geometry": {"coordinates":[-2.7346189022,42.4165687561],"type":"Point"}
}