{
  "type": "Feature",
  "properties": {
    "iso:country":"ES",
    "sg:address":"Calle de Valdehuertos, 1",
    "sg:city":"Tordesillas",
    "sg:orig_category":"Ense\u00d1anza, Formaci\u00d3n Profesional: Aprendizaje",
    "sg:phone":"+34 983 77 13 05",
    "sg:postcode":"47100",
    "sg:province":"Valladolid",
    "wof:name":"Ayuntamiento De Tordesillas",
    "wof:placetype":"venue"
},
  "geometry": {"coordinates":[-5.0043239594,41.5024604797],"type":"Point"}
}