{
  "type": "Feature",
  "properties": {
    "addr:full":"Cno. Bodegas, S/n Cigales Valladolid 47270",
    "addr:housenumber":"s / n",
    "addr:postcode":"47270",
    "addr:street":"Cno. Bodegas",
    "iso:country":"ES",
    "sg:address":"Cno. Bodegas, S/n",
    "sg:city":"Cigales",
    "sg:orig_category":"Fabricaci\u00d3n, Venta, Instalaci\u00d3n De R\u00d3tulos, De R\u00d3tulos Luminosos",
    "sg:phone":"+34 983 58 68 70",
    "sg:postcode":"47270",
    "sg:province":"Valladolid",
    "wof:name":"Garces Latorre Luis Carlos",
    "wof:placetype":"venue"
},
  "geometry": {"coordinates":[-4.6973237991,41.7601966858],"type":"Point"}
}