{
  "type": "Feature",
  "properties": {
    "addr:full":"Calle de Cardenal Mendoza, 2 Sig\u00fcenza Guadalajara 19250",
    "addr:housenumber":"2",
    "addr:postcode":"19250",
    "addr:street":"Calle De Cardenal Mendoza",
    "iso:country":"ES",
    "sg:address":"Calle de Cardenal Mendoza, 2",
    "sg:city":"Sig\u00fcenza",
    "sg:orig_category":"Alimentaci\u00d3n General (al Por Menor)",
    "sg:phone":"+34 949 39 07 85",
    "sg:postcode":"19250",
    "sg:province":"Guadalajara",
    "wof:name":"El Caseton S.l.",
    "wof:placetype":"venue"
},
  "geometry": {"coordinates":[-2.6435010433,41.0678443909],"type":"Point"}
}