{
  "type": "Feature",
  "properties": {
    "addr:full":"Plaz Quijano, 6 Alacant Alicante 03002",
    "addr:housenumber":"6",
    "addr:postcode":"03002",
    "addr:street":"Plaz Quijano",
    "iso:country":"ES",
    "sg:address":"Plaz Quijano, 6",
    "sg:city":"Alacant",
    "sg:orig_category":"Bares, Piano",
    "sg:phone":"+34 965 14 37 27",
    "sg:postcode":"03002",
    "sg:province":"Alicante",
    "wof:name":"Gutierrez Rodriguez Andres",
    "wof:placetype":"venue"
},
  "geometry": {"coordinates":[-0.481716007,38.3468360901],"type":"Point"}
}