{
  "type": "Feature",
  "properties": {
    "addr:full":"Pl Javea Park, 74 Javea Alicante 03730",
    "addr:housenumber":"74",
    "addr:postcode":"03730",
    "addr:street":"Pl Javea Park",
    "iso:country":"ES",
    "sg:address":"Pl Javea Park, 74",
    "sg:city":"Javea",
    "sg:orig_category":"Pr\u00c1ctica Del Submarinismo Y De Deportes Y Actividades Subacu\u00c1ticos",
    "sg:phone":"+34 965 79 68 31",
    "sg:postcode":"03730",
    "sg:province":"Alicante",
    "sg:website":"www.cabolanao.com",
    "wof:name":"Centro Buceo Cabo La Nao S.l.",
    "wof:placetype":"venue"
},
  "geometry": {"coordinates":[0.1668650061,38.7890739441],"type":"Point"}
}