{
  "type": "Feature",
  "properties": {
    "addr:full":"Guillermo Reina, 7 Huercal-overa Almer\u00eda 04600",
    "addr:housenumber":"7",
    "addr:postcode":"04600",
    "addr:street":"Guillermo Reina;Almeri\u0301A",
    "iso:country":"ES",
    "sg:address":"Guillermo Reina, 7",
    "sg:city":"Huercal-overa",
    "sg:orig_category":"Fabricaci\u00d3n De Peines Y De Accesorios De Peluquer\u00cda",
    "sg:phone":"+34 950 13 51 47",
    "sg:postcode":"04600",
    "sg:province":"Almer\u00eda",
    "wof:name":"Lopez Torregrosa Angela",
    "wof:placetype":"venue"
},
  "geometry": {"coordinates":[-1.9444589615,37.392288208],"type":"Point"}
}