{
  "type": "Feature",
  "properties": {
    "addr:full":"Carr Club Vista Mar, Del, S/n Cala Vedella Islas Baleares 07830",
    "addr:housenumber":"/ n",
    "addr:postcode":"07830",
    "addr:street":"Carr Club Vista;Del S",
    "iso:country":"ES",
    "sg:address":"Carr Club Vista Mar, Del, S/n",
    "sg:city":"Cala Vedella",
    "sg:orig_category":"Alquiler De Veh\u00cdculos: Turismos Y Utilitarios",
    "sg:phone":"+34 971 80 81 59",
    "sg:postcode":"07830",
    "sg:province":"Islas Baleares",
    "wof:name":"Autos Isla Blanca Rent A Car S.l.",
    "wof:placetype":"venue"
},
  "geometry": {"coordinates":[1.2937799692,38.9217262268],"type":"Point"}
}