{
  "type": "Feature",
  "properties": {
    "iso:country":"ES",
    "sg:address":"Calle de Miguel Angel, 50",
    "sg:city":"Sevilla",
    "sg:orig_category":"Cl\u00cdnicas Dentales",
    "sg:phone":"+34 954 69 29 65",
    "sg:postcode":"41014",
    "sg:province":"Sevilla",
    "wof:name":"Gomez Tarraga Francisca",
    "wof:placetype":"venue"
},
  "geometry": {"coordinates":[-5.9668450356,37.3213539124],"type":"Point"}
}