{
  "type": "Feature",
  "properties": {
    "iso:country":"ES",
    "sg:address":"Cra. Lleida-puigcerda, Km. 0023,5",
    "sg:city":"Balaguer",
    "sg:orig_category":"Producci\u00d3n, Venta De Productos De Agricultura Biol\u00d3gica",
    "sg:phone":"+34 973 45 11 01",
    "sg:postcode":"25600",
    "sg:province":"Lleida",
    "wof:name":"Forratges Estepa S.l.",
    "wof:placetype":"venue"
},
  "geometry": {"coordinates":[0.8071600199,41.7896003723],"type":"Point"}
}