{
  "type": "Feature",
  "properties": {
    "iso:country":"ES",
    "sg:address":"Carrer de Sol I Padris, 10",
    "sg:city":"Sabadell",
    "sg:orig_category":"Tintorer\u00cdas, Limpieza En Seco",
    "sg:phone":"+34 937 25 36 05",
    "sg:postcode":"08203",
    "sg:province":"Barcelona",
    "wof:name":"Corpas Gordillo Montserrat",
    "wof:placetype":"venue"
},
  "geometry": {"coordinates":[2.1169409752,41.5406723022],"type":"Point"}
}