{
  "type": "Feature",
  "properties": {
    "iso:country":"ES",
    "sg:address":"C/ Francesc Aulet, 40",
    "sg:city":"Llucmajor",
    "sg:orig_category":"Arquitectos",
    "sg:phone":"+34 971 12 04 43",
    "sg:postcode":"07620",
    "sg:province":"Islas Baleares",
    "wof:name":"Ballester Gornals Marita",
    "wof:placetype":"venue"
},
  "geometry": {"coordinates":[2.8844189644,39.4884605408],"type":"Point"}
}