{
  "type": "Feature",
  "properties": {
    "iso:country":"ES",
    "sg:address":"Calle de Moscatelar, 14",
    "sg:city":"Madrid",
    "sg:orig_category":"Cl\u00cdnicas M\u00c9dicas",
    "sg:phone":"+34 913 00 33 81",
    "sg:postcode":"28043",
    "sg:province":"Madrid",
    "wof:name":"Estomaplan S.l.",
    "wof:placetype":"venue"
},
  "geometry": {"coordinates":[-3.648514986,40.4569778442],"type":"Point"}
}