{
  "type": "Feature",
  "properties": {
    "iso:country":"ES",
    "sg:address":"C/ Cronista Jordan, 19",
    "sg:city":"Alcoi",
    "sg:orig_category":"Equipo De Refrigeraci\u00d3n Industrial",
    "sg:phone":"+34 965 33 54 42",
    "sg:postcode":"03802",
    "sg:province":"Alicante",
    "sg:website":"www.antoniollorens.com",
    "wof:name":"Antonio Llorens Cerda S.l.",
    "wof:placetype":"venue"
},
  "geometry": {"coordinates":[-0.4873921871,38.6978416443],"type":"Point"}
}