{
  "type": "Feature",
  "properties": {
    "addr:full":"Calle de Urbanizacion Alzuza 2, 79 Alzuza Navarra 31486",
    "addr:housenumber":"2 79",
    "addr:postcode":"31486",
    "addr:street":"Calle De Urbanizacion Alzuza;Alzuza Navarra",
    "iso:country":"ES",
    "sg:address":"Calle de Urbanizacion Alzuza 2, 79",
    "sg:city":"Alzuza",
    "sg:orig_category":"Procuradores",
    "sg:phone":"+34 948 33 20 71",
    "sg:postcode":"31486",
    "sg:province":"Navarra",
    "wof:name":"Orradre Paternain Joaquin",
    "wof:placetype":"venue"
},
  "geometry": {"coordinates":[-1.5519039631,42.8252906799],"type":"Point"}
}