{
  "type": "Feature",
  "properties": {
    "iso:country":"ES",
    "sg:address":"Calle de Ramon Y Cajal, 9",
    "sg:city":"Acehuche",
    "sg:orig_category":"Droguer\u00cdas (al Por Menor)",
    "sg:phone":"+34 927 37 41 40",
    "sg:postcode":"10879",
    "sg:province":"C\u00e1ceres",
    "wof:name":"Porras Montero Vicente",
    "wof:placetype":"venue"
},
  "geometry": {"coordinates":[-6.6329689026,39.8017082214],"type":"Point"}
}