{
  "type": "Feature",
  "properties": {
    "iso:country":"ES",
    "sg:address":"Calle de Monse\u00d1or Martinez Somalo, 5",
    "sg:city":"Ba\u00e7os De Rio Tobia",
    "sg:orig_category":"Peluqueros: De Se\u00d1oras",
    "sg:phone":"+34 941 37 46 46",
    "sg:postcode":"26320",
    "sg:province":"La Rioja",
    "wof:name":"Somalo Mu\u00f1oz Elena",
    "wof:placetype":"venue"
},
  "geometry": {"coordinates":[-2.7583599091,42.332611084],"type":"Point"}
}