{
  "type": "Feature",
  "properties": {
    "iso:country":"ES",
    "sg:address":"Carrer de Escorredors De Sant Francesc, 19",
    "sg:city":"Reus",
    "sg:orig_category":"M\u00c9dicos: Estomatolog\u00cda",
    "sg:phone":"+34 977 77 51 02",
    "sg:postcode":"43205",
    "sg:province":"Tarragona",
    "wof:name":"Lagorio Giorgi Sergio",
    "wof:placetype":"venue"
},
  "geometry": {"coordinates":[1.107929945,41.1519889832],"type":"Point"}
}