{
  "type": "Feature",
  "properties": {
    "iso:country":"ES",
    "sg:address":"Pol Ind La Mora, 3",
    "sg:city":"La Cisterniga",
    "sg:orig_category":"Estudios, Instalaci\u00d3n De Climatizaci\u00d3n",
    "sg:phone":"+34 983 40 23 76",
    "sg:postcode":"47193",
    "sg:province":"Valladolid",
    "wof:name":"Aislamientos Termicos Alonso S.l.",
    "wof:placetype":"venue"
},
  "geometry": {"coordinates":[-4.6553678513,41.5969200134],"type":"Point"}
}