{
  "type": "Feature",
  "properties": {
    "iso:country":"ES",
    "sg:address":"Calle de Colon, 34",
    "sg:city":"Palencia",
    "sg:orig_category":"Fotocopias, Reprograf\u00cda",
    "sg:phone":"+34 979 70 20 31",
    "sg:postcode":"34002",
    "sg:province":"Palencia",
    "wof:name":"Organizacion Palencia Im-tell Comunicacion S.l.",
    "wof:placetype":"venue"
},
  "geometry": {"coordinates":[-4.5307202339,42.0068778992],"type":"Point"}
}