{
  "type": "Feature",
  "properties": {
    "addr:full":"Calle de San Isidro, 18 Motilla Palancar Cuenca 16200",
    "addr:housenumber":"18",
    "addr:postcode":"16200",
    "addr:street":"Calle De San Isidro",
    "iso:country":"ES",
    "sg:address":"Calle de San Isidro, 18",
    "sg:city":"Motilla Palancar",
    "sg:orig_category":"Ense\u00d1anza: Comercio, Gesti\u00d3n, Inform\u00c1tica",
    "sg:phone":"+34 969 33 14 91",
    "sg:postcode":"16200",
    "sg:province":"Cuenca",
    "sg:website":"www.verproin.com",
    "wof:name":"Verproin S.l.",
    "wof:placetype":"venue"
},
  "geometry": {"coordinates":[-1.9062039852,39.5607185364],"type":"Point"}
}