{
  "type": "Feature",
  "properties": {
    "addr:full":"Calle de Alcalde Retamino, 15 Mairena Alcor Sevilla 41510",
    "addr:housenumber":"15",
    "addr:postcode":"41510",
    "addr:street":"Calle De Alcalde Retamino",
    "iso:country":"ES",
    "sg:address":"Calle de Alcalde Retamino, 15",
    "sg:city":"Mairena Alcor",
    "sg:orig_category":"Agencias Y Agentes Comerciales, Representantes",
    "sg:phone":"+34 955 74 64 18",
    "sg:postcode":"41510",
    "sg:province":"Sevilla",
    "wof:name":"B C Comercial Del Sur S.l.",
    "wof:placetype":"venue"
},
  "geometry": {"coordinates":[-5.7478604317,37.376537323],"type":"Point"}
}