{
  "type": "Feature",
  "properties": {
    "iso:country":"ES",
    "sg:address":"Avda Ayora, 25",
    "sg:city":"Almansa",
    "sg:orig_category":"Fabricaci\u00d3n De Muebles",
    "sg:phone":"+34 967 31 20 05",
    "sg:postcode":"02640",
    "sg:province":"Albacete",
    "wof:name":"Nogal Mobiliario S.l.",
    "wof:placetype":"venue"
},
  "geometry": {"coordinates":[-1.101698041,38.8724784851],"type":"Point"}
}