{
  "type": "Feature",
  "properties": {
    "addr:full":"Carr Poeta Querol, 18 Oliva Valencia 46780",
    "addr:housenumber":"18",
    "addr:postcode":"46780",
    "addr:street":"Carr Poeta Querol",
    "iso:country":"ES",
    "sg:address":"Carr Poeta Querol, 18",
    "sg:city":"Oliva",
    "sg:orig_category":"Fabricaci\u00d3n De Telas Y Sedas",
    "sg:phone":"+34 962 85 63 68",
    "sg:postcode":"46780",
    "sg:province":"Valencia",
    "wof:name":"Llopis Climent Rosa",
    "wof:placetype":"venue"
},
  "geometry": {"coordinates":[-0.1177209988,38.9196968079],"type":"Point"}
}