{
  "type": "Feature",
  "properties": {
    "addr:full":"Plaz Italia, 2 Avila \u00c1vila 05001",
    "addr:housenumber":"2",
    "addr:postcode":"05001",
    "addr:street":"A\u0301Vila",
    "iso:country":"ES",
    "sg:address":"Plaz Italia, 2",
    "sg:city":"Avila",
    "sg:orig_category":"Cajas De Ahorro",
    "sg:phone":"+34 920 21 32 64",
    "sg:postcode":"05001",
    "sg:province":"\u00c1vila",
    "wof:name":"Caja De Avila",
    "wof:placetype":"venue"
},
  "geometry": {"coordinates":[-4.7072339058,40.6581344604],"type":"Point"}
}