{
  "type": "Feature",
  "properties": {
    "iso:country":"ES",
    "sg:address":"Calle de Bergara, 20",
    "sg:city":"Donostia-san Sebastian",
    "sg:orig_category":"M\u00c9dicos: Estomatolog\u00cda",
    "sg:phone":"+34 943 42 83 68",
    "sg:postcode":"20005",
    "sg:province":"Guip\u00f9zcoa",
    "wof:name":"Gorostegui Echave Bego\u00f1a",
    "wof:placetype":"venue"
},
  "geometry": {"coordinates":[-1.979870677,43.3182907104],"type":"Point"}
}