{
  "type": "Feature",
  "properties": {
    "addr:full":"Avda Doctor Mara\u00d1on, 27 Malaga M\u00e1laga 29009",
    "addr:housenumber":"27",
    "addr:postcode":"29009",
    "addr:street":"Avda Doctor Maran\u0303On;Ma\u0301Laga",
    "iso:country":"ES",
    "sg:address":"Avda Doctor Mara\u00d1on, 27",
    "sg:city":"Malaga",
    "sg:orig_category":"Radiocomunicaciones, Telefon\u00cda M\u00d3vil, Radiomensajer\u00cda: Servicios, Comercializaci\u00d3n",
    "sg:phone":"+34 952 10 05 96",
    "sg:postcode":"29009",
    "sg:province":"M\u00e1laga",
    "wof:name":"Soluciones Y Accesorios De Telefonia Sl",
    "wof:placetype":"venue"
},
  "geometry": {"coordinates":[-4.4286022186,36.7303543091],"type":"Point"}
}