{
  "type": "Feature",
  "properties": {
    "iso:country":"ES",
    "sg:address":"Calle de Santa Rosalia, 1",
    "sg:city":"Cabra",
    "sg:orig_category":"Congelados: Productos Alimentarios (fabricaci\u00d3n, Al Por Mayor)",
    "sg:phone":"+34 957 52 41 70",
    "sg:postcode":"14940",
    "sg:province":"C\u00f3rdoba",
    "wof:name":"Espinar Roldan Rafael",
    "wof:placetype":"venue"
},
  "geometry": {"coordinates":[-4.4430580139,37.4719734192],"type":"Point"}
}