{
  "type": "Feature",
  "properties": {
    "addr:full":"Pla\u00c7 Major, Pla\u00c7a, 17 Casco Urbano Valencia 46760",
    "addr:housenumber":"17",
    "addr:postcode":"46760",
    "addr:street":"Plac\u0327A",
    "iso:country":"ES",
    "sg:address":"Pla\u00c7 Major, Pla\u00c7a, 17",
    "sg:city":"Casco Urbano",
    "sg:orig_category":"Farmacias",
    "sg:phone":"+34 962 82 02 85",
    "sg:postcode":"46760",
    "sg:province":"Valencia",
    "wof:name":"Juan Nadal Luis",
    "wof:placetype":"venue"
},
  "geometry": {"coordinates":[-0.2594090104,39.0749702454],"type":"Point"}
}