{
  "type": "Feature",
  "properties": {
    "addr:full":"Calle de Minerva, 20 Madrid Madrid 28032",
    "addr:housenumber":"20",
    "addr:postcode":"madrid;28032",
    "addr:street":"Calle De Minerva",
    "iso:country":"ES",
    "sg:address":"Calle de Minerva, 20",
    "sg:city":"Madrid",
    "sg:orig_category":"Arquitectos",
    "sg:phone":"+34 917 76 47 06",
    "sg:postcode":"28032",
    "sg:province":"Madrid",
    "wof:name":"Caballero Lopez Emilio",
    "wof:placetype":"venue"
},
  "geometry": {"coordinates":[-3.5992240906,40.4025726318],"type":"Point"}
}