{
  "type": "Feature",
  "properties": {
    "addr:full":"Pg Bonanova, 47 Barcelona Barcelona 08017",
    "addr:housenumber":"47",
    "addr:postcode":"08017",
    "addr:street":"Pg Bonanova",
    "iso:country":"ES",
    "sg:address":"Pg Bonanova, 47",
    "sg:city":"Barcelona",
    "sg:orig_category":"Restaurantes",
    "sg:phone":"+34 934 18 85 91",
    "sg:postcode":"08017",
    "sg:province":"Barcelona",
    "wof:name":"Fia Catalana De Catering I Restauracions",
    "wof:placetype":"venue"
},
  "geometry": {"coordinates":[2.129283905,41.4041442871],"type":"Point"}
}