{
  "type": "Feature",
  "properties": {
    "iso:country":"ES",
    "sg:address":"Avda Constitucion, S/n",
    "sg:city":"Guare\u00f1a",
    "sg:orig_category":"Empresas De Carpinter\u00cda Met\u00c1lica",
    "sg:phone":"+34 924 35 21 89",
    "sg:postcode":"06470",
    "sg:province":"Badajoz",
    "wof:name":"Monago Dominguez Bernardo",
    "wof:placetype":"venue"
},
  "geometry": {"coordinates":[-6.0976238251,38.8564147949],"type":"Point"}
}