{
  "type": "Feature",
  "properties": {
    "addr:full":"Navarro Villoslada, 5 Iru\u00f1a Navarra 31003",
    "addr:housenumber":"5",
    "addr:postcode":"31003",
    "addr:street":"Villoslada",
    "iso:country":"ES",
    "sg:address":"Navarro Villoslada, 5",
    "sg:city":"Iru\u00f1a",
    "sg:orig_category":"Alquiler De Muebles",
    "sg:phone":"+34 948 24 67 51",
    "sg:postcode":"31003",
    "sg:province":"Navarra",
    "wof:name":"Pieiro Gil Maria Antonia",
    "wof:placetype":"venue"
},
  "geometry": {"coordinates":[-1.6402859688,42.8122673035],"type":"Point"}
}