{
  "type": "Feature",
  "properties": {
    "iso:country":"ES",
    "sg:address":"Calle de Virtudes, 3",
    "sg:city":"Madrid",
    "sg:orig_category":"M\u00c9dicos: Ginecolog\u00cda Y Obstetricia",
    "sg:phone":"+34 915 94 39 00",
    "sg:postcode":"28010",
    "sg:province":"Madrid",
    "wof:name":"Villarreal Alcaraz Antonio Jose",
    "wof:placetype":"venue"
},
  "geometry": {"coordinates":[-3.698941946,40.43699646],"type":"Point"}
}