{
  "type": "Feature",
  "properties": {
    "addr:full":"Avda Jable (el), 41 Callao Salvaje Santa Cruz De Tenerife 38678",
    "addr:postcode":"38678",
    "addr:street":"Avda Jable El",
    "iso:country":"ES",
    "sg:address":"Avda Jable (el), 41",
    "sg:city":"Callao Salvaje",
    "sg:orig_category":"Supermercados Y Hipermercados",
    "sg:phone":"+34 922 74 13 79",
    "sg:postcode":"38678",
    "sg:province":"Santa Cruz De Tenerife",
    "wof:name":"Summersield Supermarket S.l.",
    "wof:placetype":"venue"
},
  "geometry": {"coordinates":[-16.7803936005,28.1306934357],"type":"Point"}
}