{
  "type": "Feature",
  "properties": {
    "addr:full":"Ctra Tremp, 67 Artesa Segre Lleida 25730",
    "addr:housenumber":"67",
    "addr:postcode":"25730",
    "addr:street":"Ctra Tremp",
    "iso:country":"ES",
    "sg:address":"Ctra Tremp, 67",
    "sg:city":"Artesa Segre",
    "sg:orig_category":"Mec\u00c1nico Del Autom\u00d3vil",
    "sg:phone":"+34 973 40 05 51",
    "sg:postcode":"25730",
    "sg:province":"Lleida",
    "wof:name":"Carde\u00f1es Reig Juan",
    "wof:placetype":"venue"
},
  "geometry": {"coordinates":[1.0548989773,41.8964004517],"type":"Point"}
}