{
  "type": "Feature",
  "properties": {
    "addr:full":"Calle de Nardos, 3 Torrejon Ardoz Madrid 28850",
    "addr:housenumber":"3",
    "addr:postcode":"28850",
    "addr:street":"Calle De Nardos",
    "iso:country":"ES",
    "sg:address":"Calle de Nardos, 3",
    "sg:city":"Torrejon Ardoz",
    "sg:orig_category":"Venta, Instalaci\u00d3n, Reparaci\u00d3n De Antenas Para Televisi\u00d3n",
    "sg:phone":"+34 916 56 80 30",
    "sg:postcode":"28850",
    "sg:province":"Madrid",
    "wof:name":"Antenas Telesys S.l.",
    "wof:placetype":"venue"
},
  "geometry": {"coordinates":[-3.4784977436,40.4613075256],"type":"Point"}
}