{
  "type": "Feature",
  "properties": {
    "iso:country":"ES",
    "sg:address":"Pol Tecnum, 13",
    "sg:city":"Cartuja Baja",
    "sg:orig_category":"Cristaler\u00cdas",
    "sg:phone":"+34 976 59 77 12",
    "sg:postcode":"50720",
    "sg:province":"Zaragoza",
    "wof:name":"Lopez Lopez Jesus Manuel",
    "wof:placetype":"venue"
},
  "geometry": {"coordinates":[-0.8241500258,41.6057167053],"type":"Point"}
}