{
  "type": "Feature",
  "properties": {
    "iso:country":"ES",
    "sg:address":"Calle de Soria, 2",
    "sg:city":"San Sebastian De Los Reyes",
    "sg:orig_category":"Tintes (fabricaci\u00d3n, Al Por Mayor)",
    "sg:phone":"+34 916 54 94 58",
    "sg:postcode":"28700",
    "sg:province":"Madrid",
    "wof:name":"Sanchez Algaba Yolanda",
    "wof:placetype":"venue"
},
  "geometry": {"coordinates":[-3.630507946,40.5614776611],"type":"Point"}
}