{
  "type": "Feature",
  "properties": {
    "addr:full":"Carr Ponent, 5 Santa Anna Islas Baleares 07720",
    "addr:housenumber":"5",
    "addr:postcode":"07720",
    "addr:street":"Carr Ponent",
    "iso:country":"ES",
    "sg:address":"Carr Ponent, 5",
    "sg:city":"Santa Anna",
    "sg:orig_category":"Promotores Constructores",
    "sg:phone":"+34 971 36 91 18",
    "sg:postcode":"07720",
    "sg:province":"Islas Baleares",
    "wof:name":"Berja Molina Manuel",
    "wof:placetype":"venue"
},
  "geometry": {"coordinates":[4.2850251198,39.8720703125],"type":"Point"}
}