{
  "type": "Feature",
  "properties": {
    "iso:country":"ES",
    "sg:address":"Calle de Parque (del), 44",
    "sg:city":"Huesca",
    "sg:orig_category":"Pod\u00d3logos: Pedicuros",
    "sg:phone":"+34 974 22 35 08",
    "sg:postcode":"22003",
    "sg:province":"Huesca",
    "wof:name":"Pueyo Torres Rosana",
    "wof:placetype":"venue"
},
  "geometry": {"coordinates":[-0.4137870073,42.1399078369],"type":"Point"}
}