{
  "type": "Feature",
  "properties": {
    "addr:full":"Carrer de Bilbao, 145 Barcelona Barcelona 08018",
    "addr:housenumber":"145",
    "addr:postcode":"08018",
    "addr:street":"Carrer De Bilbao",
    "iso:country":"ES",
    "sg:address":"Carrer de Bilbao, 145",
    "sg:city":"Barcelona",
    "sg:orig_category":"Centros De Coordinaci\u00d3n",
    "sg:phone":"+34 933 07 46 68",
    "sg:postcode":"08018",
    "sg:province":"Barcelona",
    "wof:name":"Assessoria Omega S.c.p.",
    "wof:placetype":"venue"
},
  "geometry": {"coordinates":[2.1980230808,41.4069061279],"type":"Point"}
}