{
  "type": "Feature",
  "properties": {
    "iso:country":"ES",
    "sg:address":"Bidebarrieta Kalea, 3",
    "sg:city":"Eibar",
    "sg:orig_category":"Centros De Coordinaci\u00d3n",
    "sg:phone":"+34 943 20 17 41",
    "sg:postcode":"20600",
    "sg:province":"Guip\u00f9zcoa",
    "wof:name":"Luengo Gaztelu Ana",
    "wof:placetype":"venue"
},
  "geometry": {"coordinates":[-2.4696960449,43.1852226257],"type":"Point"}
}