{
  "type": "Feature",
  "properties": {
    "addr:full":"Calle de Huevar, 2 Jerez De La Frontera C\u00e1diz 11403",
    "addr:housenumber":"2",
    "addr:postcode":"11403",
    "addr:street":"Calle De Huevar",
    "iso:country":"ES",
    "sg:address":"Calle de Huevar, 2",
    "sg:city":"Jerez De La Frontera",
    "sg:orig_category":"Asesor\u00cda Fiscal Y Jur\u00cddica",
    "sg:phone":"+34 956 33 74 27",
    "sg:postcode":"11403",
    "sg:province":"C\u00e1diz",
    "wof:name":"Parra Romero Agustin",
    "wof:placetype":"venue"
},
  "geometry": {"coordinates":[-6.1373100281,36.6830787659],"type":"Point"}
}