{
  "type": "Feature",
  "properties": {
    "iso:country":"ES",
    "sg:address":"Calle de Juan Yague, 13",
    "sg:city":"Salas De Los Infantes",
    "sg:orig_category":"Asilos De Ancianos. Centros Privados",
    "sg:phone":"+34 947 38 07 50",
    "sg:postcode":"09600",
    "sg:province":"Burgos",
    "wof:name":"Patronato De Santa Maria La Mayor Residencia De Ancianos",
    "wof:placetype":"venue"
},
  "geometry": {"coordinates":[-3.2877960205,42.020904541],"type":"Point"}
}