{
  "type": "Feature",
  "properties": {
    "iso:country":"ES",
    "sg:address":"Calle de Gran Via, 16",
    "sg:city":"Madrid",
    "sg:orig_category":"Empresarios",
    "sg:phone":"+34 915 22 57 52",
    "sg:postcode":"28013",
    "sg:province":"Madrid",
    "sg:website":"www.arteyderecho.org",
    "wof:name":"Fundacion Arte Y Derecho",
    "wof:placetype":"venue"
},
  "geometry": {"coordinates":[-3.6995220184,40.419670105],"type":"Point"}
}