{
  "type": "Feature",
  "properties": {
    "addr:full":"Calle de Cuatro Esquinas, S/n Santomera Murcia 30140",
    "addr:housenumber":"s / n",
    "addr:postcode":"30140",
    "addr:street":"Calle De Cuatro Esquinas",
    "iso:country":"ES",
    "sg:address":"Calle de Cuatro Esquinas, S/n",
    "sg:city":"Santomera",
    "sg:orig_category":"Peluqueros: De Se\u00d1oras",
    "sg:phone":"+34 968 86 55 50",
    "sg:postcode":"30140",
    "sg:province":"Murcia",
    "wof:name":"Sarrias Alegria Maria Carmen",
    "wof:placetype":"venue"
},
  "geometry": {"coordinates":[-1.0489389896,38.063999176],"type":"Point"}
}