{
  "type": "Feature",
  "properties": {
    "iso:country":"ES",
    "sg:address":"Calle de Calvario, 18",
    "sg:city":"Puerto De Santa Maria",
    "sg:orig_category":"Empresas De Carpinter\u00cda",
    "sg:phone":"+34 956 87 04 92",
    "sg:postcode":"11500",
    "sg:province":"C\u00e1diz",
    "wof:name":"Zaragozin Mayi Jose",
    "wof:placetype":"venue"
},
  "geometry": {"coordinates":[-6.2191162109,36.6098976135],"type":"Point"}
}