{
  "type": "Feature",
  "properties": {
    "iso:country":"ES",
    "sg:address":"Calle de Torrejon, 37",
    "sg:city":"Parla",
    "sg:orig_category":"Bisuter\u00cda, Joyer\u00cda, Relojer\u00cda (al Por Menor)",
    "sg:phone":"+34 916 05 24 42",
    "sg:postcode":"28980",
    "sg:province":"Madrid",
    "wof:name":"Jimenez Diosdado Maria Esther",
    "wof:placetype":"venue"
},
  "geometry": {"coordinates":[-3.7659645081,40.236743927],"type":"Point"}
}