{
  "type": "Feature",
  "properties": {
    "addr:full":"Barr Larrotegi Auzotegia, 5 Lekeitio Vizcaya 48280",
    "addr:housenumber":"5",
    "addr:postcode":"48280",
    "addr:street":"Auzotegia",
    "iso:country":"ES",
    "sg:address":"Barr Larrotegi Auzotegia, 5",
    "sg:city":"Lekeitio",
    "sg:orig_category":"Guarder\u00cdas",
    "sg:phone":"+34 946 24 33 92",
    "sg:postcode":"48280",
    "sg:province":"Vizcaya",
    "wof:name":"Consorcio Haurreskolak",
    "wof:placetype":"venue"
},
  "geometry": {"coordinates":[-2.5051689148,43.3635787964],"type":"Point"}
}