{
  "type": "Feature",
  "properties": {
    "iso:country":"ES",
    "sg:address":"Calle de Diego Fernandez Herrera, 6",
    "sg:city":"Jerez De La Frontera",
    "sg:orig_category":"Comunidades Religiosas",
    "sg:phone":"+34 956 34 13 62",
    "sg:postcode":"11401",
    "sg:province":"C\u00e1diz",
    "wof:name":"Hermandad De Las Cinco Yagas",
    "wof:placetype":"venue"
},
  "geometry": {"coordinates":[-6.1321620941,36.6807098389],"type":"Point"}
}