{
  "type": "Feature",
  "properties": {
    "iso:country":"ES",
    "sg:address":"Calle de Jose Luis Bugallal Marchesi, 16",
    "sg:city":"Coru\u00d1a",
    "sg:orig_category":"Molduras, Junquillos, Listones Y Molduras Perforadas",
    "sg:phone":"+34 981 15 35 09",
    "sg:postcode":"15008",
    "sg:province":"La Coru\u00f1a",
    "wof:name":"Campos Santiso Ramon",
    "wof:placetype":"venue"
},
  "geometry": {"coordinates":[-8.4093055725,43.3470039368],"type":"Point"}
}