{
  "type": "Feature",
  "properties": {
    "iso:country":"ES",
    "sg:address":"Carrer de Aribau, 84",
    "sg:city":"Barcelona",
    "sg:orig_category":"Fabricaci\u00d3n, Venta, Instalaci\u00d3n De R\u00d3tulos, De R\u00d3tulos Luminosos",
    "sg:phone":"+34 933 23 51 15",
    "sg:postcode":"08036",
    "sg:province":"Barcelona",
    "wof:name":"General De Retols Exteriors I Interiors S.a.",
    "wof:placetype":"venue"
},
  "geometry": {"coordinates":[2.1580150127,41.3896217346],"type":"Point"}
}