{
  "type": "Feature",
  "properties": {
    "addr:full":"Bulevar Indalecio Prieto Madrid Madrid 28032",
    "addr:postcode":"28032",
    "addr:street":"Bulevar Indalecio Prieto Madrid",
    "iso:country":"ES",
    "sg:address":"Bulevar Indalecio Prieto",
    "sg:city":"Madrid",
    "sg:orig_category":"Frutas Y Legumbres Frescas (al Por Mayor)",
    "sg:phone":"+34 917 72 78 28",
    "sg:postcode":"28032",
    "sg:province":"Madrid",
    "wof:name":"C.c. Darbe S.l.",
    "wof:placetype":"venue"
},
  "geometry": {"coordinates":[-3.6204240322,40.4033546448],"type":"Point"}
}