{
  "type": "Feature",
  "properties": {
    "iso:country":"ES",
    "sg:address":"Calle de Venerable, 12",
    "sg:city":"Agreda",
    "sg:orig_category":"Ense\u00d1anza: Profesiones Art\u00cdsticas",
    "sg:phone":"+34 976 64 66 94",
    "sg:postcode":"42100",
    "sg:province":"Soria",
    "wof:name":"Foto Estudio Iris S.cv.",
    "wof:placetype":"venue"
},
  "geometry": {"coordinates":[-1.9256390333,41.8540802002],"type":"Point"}
}