{
  "type": "Feature",
  "properties": {
    "iso:country":"ES",
    "sg:address":"Los Romeros, 120",
    "sg:city":"El Provencio",
    "sg:classifiers":[
        {
            "category":"Taxi",
            "type":"Transportation"
        }
    ],
    "sg:phone":"+34 967 16 56 29",
    "sg:postcode":"16670",
    "sg:province":"Cuenca",
    "wof:name":"Berruga Mu\u00f1oz Pedro",
    "wof:placetype":"venue"
},
  "geometry": {"coordinates":[-2.5722990036,39.3736991882],"type":"Point"}
}