{
  "type": "Feature",
  "properties": {
    "iso:country":"ES",
    "sg:address":"Calle de Lepanto, 5",
    "sg:city":"Novelda",
    "sg:orig_category":"Reposter\u00cdas",
    "sg:phone":"+34 965 60 17 95",
    "sg:postcode":"03660",
    "sg:province":"Alicante",
    "wof:name":"Panaderia Sirvent S.l.",
    "wof:placetype":"venue"
},
  "geometry": {"coordinates":[-0.7653489709,38.3845367432],"type":"Point"}
}