{
  "type": "Feature",
  "properties": {
    "addr:full":"Carrer de Prat De La Riba, 43 Rubi Barcelona 08191",
    "addr:housenumber":"43",
    "addr:postcode":"08191",
    "addr:street":"Carrer De Prat De La Riba",
    "iso:country":"ES",
    "sg:address":"Carrer de Prat De La Riba, 43",
    "sg:city":"Rubi",
    "sg:orig_category":"Ingeniero",
    "sg:phone":"+34 936 97 16 51",
    "sg:postcode":"08191",
    "sg:province":"Barcelona",
    "wof:name":"Mas Jove Jose Oriol",
    "wof:placetype":"venue"
},
  "geometry": {"coordinates":[2.0315489769,41.4957084656],"type":"Point"}
}