{
  "type": "Feature",
  "properties": {
    "iso:country":"ES",
    "sg:address":"Avda Andalucia, 18",
    "sg:city":"Algodonales",
    "sg:orig_category":"Alimentaci\u00d3n General (al Por Menor)",
    "sg:phone":"+34 956 13 81 52",
    "sg:postcode":"11680",
    "sg:province":"C\u00e1diz",
    "wof:name":"Martin Berzal Antonio",
    "wof:placetype":"venue"
},
  "geometry": {"coordinates":[-5.4039201736,36.880771637],"type":"Point"}
}