{
  "type": "Feature",
  "properties": {
    "iso:country":"ES",
    "sg:address":"Av Pare Castro (del), 13",
    "sg:city":"S. Carles Rapita",
    "sg:orig_category":"Pescader\u00cdas (al Por Mayor)",
    "sg:phone":"+34 977 74 24 00",
    "sg:postcode":"43540",
    "sg:province":"Tarragona",
    "wof:name":"Peix I Marisc Romeu S.c.p.",
    "wof:placetype":"venue"
},
  "geometry": {"coordinates":[0.5931149721,40.6206436157],"type":"Point"}
}