{
  "type": "Feature",
  "properties": {
    "addr:full":"Avda Ciudad De Pescia, 5 Nerja M\u00e1laga 29780",
    "addr:housenumber":"5",
    "addr:postcode":"29780",
    "addr:street":"Avda Ciudad De Pescia",
    "iso:country":"ES",
    "sg:address":"Avda Ciudad De Pescia, 5",
    "sg:city":"Nerja",
    "sg:orig_category":"Inmobiliaria (agencias)",
    "sg:phone":"+34 952 52 34 23",
    "sg:postcode":"29780",
    "sg:province":"M\u00e1laga",
    "wof:name":"Tropical La Zubia S.l.",
    "wof:placetype":"venue"
},
  "geometry": {"coordinates":[-3.8762149811,36.751914978],"type":"Point"}
}