{
  "type": "Feature",
  "properties": {
    "iso:country":"ES",
    "sg:address":"Calle de Garcia Morato, S/n",
    "sg:city":"Corrales",
    "sg:orig_category":"Carnicer\u00cdas, Carnicer\u00cdas",
    "sg:phone":"+34 942 83 12 21",
    "sg:postcode":"39400",
    "sg:province":"Cantabria",
    "wof:name":"Ceballos Gonzalez Julio",
    "wof:placetype":"venue"
},
  "geometry": {"coordinates":[-4.0706181526,43.2597236633],"type":"Point"}
}