{
  "type": "Feature",
  "properties": {
    "iso:country":"ES",
    "sg:address":"Av Josep Tarradellas, 110",
    "sg:city":"Barcelona",
    "sg:orig_category":"Mutuas De Seguros",
    "sg:phone":"+34 933 63 06 00",
    "sg:postcode":"08029",
    "sg:province":"Barcelona",
    "wof:name":"Union Mutuas Matepss",
    "wof:placetype":"venue"
},
  "geometry": {"coordinates":[2.1437358856,41.3894615173],"type":"Point"}
}