{
  "type": "Feature",
  "properties": {
    "iso:country":"ES",
    "sg:address":"Calle de Concepcion, 7",
    "sg:city":"Mansilla Mulas",
    "sg:orig_category":"Iglesia Cat\u00d3lica",
    "sg:phone":"+34 987 31 01 91",
    "sg:postcode":"24210",
    "sg:province":"Le\u00f3n",
    "wof:name":"Parroquia De Mansilla De Las Mulas",
    "wof:placetype":"venue"
},
  "geometry": {"coordinates":[-5.4162516594,42.4994621277],"type":"Point"}
}