{
  "type": "Feature",
  "properties": {
    "iso:country":"ES",
    "sg:address":"Av Mare Deu De Montserrat, 17",
    "sg:city":"Barcelona",
    "sg:orig_category":"Molduras, Junquillos, Listones Y Molduras Perforadas",
    "sg:phone":"+34 932 19 79 65",
    "sg:postcode":"08024",
    "sg:province":"Barcelona",
    "wof:name":"Gamez Sanchez Manuel",
    "wof:placetype":"venue"
},
  "geometry": {"coordinates":[2.1613268852,41.4137153625],"type":"Point"}
}