{
  "type": "Feature",
  "properties": {
    "iso:country":"ES",
    "sg:address":"Luchente, 2",
    "sg:city":"Pobla Del Duc",
    "sg:orig_category":"Arboricultura Y Producci\u00d3n De Frutas",
    "sg:phone":"+34 962 25 00 88",
    "sg:postcode":"46840",
    "sg:province":"Valencia",
    "wof:name":"Blas Bosca S.l.",
    "wof:placetype":"venue"
},
  "geometry": {"coordinates":[-0.4222159982,38.9052238464],"type":"Point"}
}