{
  "type": "Feature",
  "properties": {
    "addr:full":"Calle de Rio Genil, 18 Playa Honda Murcia 30370",
    "addr:housenumber":"18",
    "addr:postcode":"30370",
    "addr:street":"Calle De Rio Genil",
    "iso:country":"ES",
    "sg:address":"Calle de Rio Genil, 18",
    "sg:city":"Playa Honda",
    "sg:orig_category":"Inmobiliaria (agencias)",
    "sg:phone":"+34 968 43 78 26",
    "sg:postcode":"30370",
    "sg:province":"Murcia",
    "wof:name":"Moreno Espejo Ramon",
    "wof:placetype":"venue"
},
  "geometry": {"coordinates":[-0.7051039934,37.631401062],"type":"Point"}
}