{
  "type": "Feature",
  "properties": {
    "addr:full":"Avda Mairena, 7 San Juan De Aznalfarache Sevilla 41920",
    "addr:housenumber":"7",
    "addr:postcode":"41920",
    "addr:street":"Avda Mairena",
    "iso:country":"ES",
    "sg:address":"Avda Mairena, 7",
    "sg:city":"San Juan De Aznalfarache",
    "sg:orig_category":"Panader\u00cdas, Panader\u00cdas",
    "sg:phone":"+34 954 76 72 50",
    "sg:postcode":"41920",
    "sg:province":"Sevilla",
    "wof:name":"Resporteria Cecilia S.l.",
    "wof:placetype":"venue"
},
  "geometry": {"coordinates":[-6.0378890038,37.3574867249],"type":"Point"}
}