{
  "type": "Feature",
  "properties": {
    "addr:full":"Avda Almazora, 62 Castellon Castell\u00f3n 12005",
    "addr:housenumber":"62",
    "addr:postcode":"12005",
    "addr:street":"Avda Almazora",
    "iso:country":"ES",
    "sg:address":"Avda Almazora, 62",
    "sg:city":"Castellon",
    "sg:orig_category":"Supermercados Y Hipermercados",
    "sg:phone":"+34 964 24 82 10",
    "sg:postcode":"12005",
    "sg:province":"Castell\u00f3n",
    "sg:website":"www.mercadona.es",
    "wof:name":"Mercadona S.a.",
    "wof:placetype":"venue"
},
  "geometry": {"coordinates":[-0.0297400001,39.9624290466],"type":"Point"}
}