{
  "type": "Feature",
  "properties": {
    "addr:full":"Cruz, 4 Espinardo Murcia 30100",
    "addr:housenumber":"4",
    "addr:postcode":"30100",
    "addr:street":"Cruz",
    "iso:country":"ES",
    "sg:address":"Cruz, 4",
    "sg:city":"Espinardo",
    "sg:orig_category":"Condimentos, Especias, Vinagres, Salsas Preparadas (fabricaci\u00d3n, Al Por Mayor)",
    "sg:phone":"+34 968 83 05 84",
    "sg:postcode":"30100",
    "sg:province":"Murcia",
    "wof:name":"Pe\u00f1aranda Gomez Cayetano",
    "wof:placetype":"venue"
},
  "geometry": {"coordinates":[-1.153594017,38.0103034973],"type":"Point"}
}