{
  "type": "Feature",
  "properties": {
    "iso:country":"ES",
    "sg:address":"Carrer de Doctor Ferran I Clua, 27",
    "sg:city":"Viladecans",
    "sg:orig_category":"Asesor\u00cda De Formaci\u00d3n Y Gesti\u00d3n De Personal",
    "sg:phone":"+34 936 58 83 01",
    "sg:postcode":"08840",
    "sg:province":"Barcelona",
    "sg:website":"www.duomar.com",
    "wof:name":"Duomar Assessors S.l.",
    "wof:placetype":"venue"
},
  "geometry": {"coordinates":[2.0135300159,41.3121986389],"type":"Point"}
}