{
  "type": "Feature",
  "properties": {
    "addr:full":"Calle de Pablo Luengo, 38 Navalmoral Mata C\u00e1ceres 10300",
    "addr:housenumber":"38",
    "addr:postcode":"10300",
    "addr:street":"Calle De Pablo Luengo;Ca\u0301Ceres",
    "iso:country":"ES",
    "sg:address":"Calle de Pablo Luengo, 38",
    "sg:city":"Navalmoral Mata",
    "sg:orig_category":"Asociaciones Y Clubs Deportivos",
    "sg:phone":"+34 927 53 38 87",
    "sg:postcode":"10300",
    "sg:province":"C\u00e1ceres",
    "wof:name":"Parra Hernandez Alberto",
    "wof:placetype":"venue"
},
  "geometry": {"coordinates":[-5.5428490639,39.8952560425],"type":"Point"}
}