{
  "type": "Feature",
  "properties": {
    "addr:full":"Pg Generalitat, 22 Banyoles Girona 17820",
    "addr:housenumber":"22",
    "addr:postcode":"17820",
    "addr:street":"Pg Generalitat",
    "iso:country":"ES",
    "sg:address":"Pg Generalitat, 22",
    "sg:city":"Banyoles",
    "sg:orig_category":"Laboratorios Y Trabajos De Fotograf\u00cda, V\u00cddeo Y Cine",
    "sg:phone":"+34 972 58 05 06",
    "sg:postcode":"17820",
    "sg:province":"Girona",
    "sg:website":"www.titfotograf.com",
    "wof:name":"Tit Fotograf S.l.",
    "wof:placetype":"venue"
},
  "geometry": {"coordinates":[2.760974884,42.1240348816],"type":"Point"}
}