{
  "type": "Feature",
  "properties": {
    "iso:country":"ES",
    "sg:address":"Calle de Yolanda De Bar, S/n",
    "sg:city":"Zaragoza",
    "sg:orig_category":"Lavado, Limpieza De Veh\u00cdculos",
    "sg:phone":"+34 976 41 94 50",
    "sg:postcode":"50013",
    "sg:province":"Zaragoza",
    "wof:name":"Imo Autolavados S.a.",
    "wof:placetype":"venue"
},
  "geometry": {"coordinates":[-0.8630740047,41.6413955688],"type":"Point"}
}