{
  "type": "Feature",
  "properties": {
    "iso:country":"ES",
    "sg:address":"Calle de General Ricardos, 20",
    "sg:city":"Barbastro",
    "sg:orig_category":"Listas De Boda, Menaje De Mesa Y Cocina",
    "sg:phone":"+34 974 31 29 73",
    "sg:postcode":"22300",
    "sg:province":"Huesca",
    "wof:name":"Umbela S.cv.",
    "wof:placetype":"venue"
},
  "geometry": {"coordinates":[0.1256220043,42.0356712341],"type":"Point"}
}