{
  "type": "Feature",
  "properties": {
    "iso:country":"ES",
    "sg:address":"Plaz America, 20",
    "sg:city":"Utrillas",
    "sg:orig_category":"Librer\u00cdas",
    "sg:phone":"+34 978 75 73 61",
    "sg:postcode":"44760",
    "sg:province":"Teruel",
    "wof:name":"Gascon Campos Pablo",
    "wof:placetype":"venue"
},
  "geometry": {"coordinates":[-0.8442590237,40.8141403198],"type":"Point"}
}