{
  "type": "Feature",
  "properties": {
    "iso:country":"ES",
    "sg:address":"Calle de Rancho, 12",
    "sg:city":"Madrid",
    "sg:orig_category":"Molduras, Junquillos, Listones Y Molduras Perforadas",
    "sg:phone":"+34 913 41 27 09",
    "sg:postcode":"28041",
    "sg:province":"Madrid",
    "wof:name":"Mulero Antelo Eusebio",
    "wof:placetype":"venue"
},
  "geometry": {"coordinates":[-3.7089829445,40.3701782227],"type":"Point"}
}