{
  "type": "Feature",
  "properties": {
    "iso:country":"ES",
    "sg:address":"Calle de Marques De Teverga, 2",
    "sg:city":"Oviedo",
    "sg:orig_category":"M\u00c9dicos: Estomatolog\u00cda",
    "sg:phone":"+34 985 27 14 15",
    "sg:postcode":"33005",
    "sg:province":"Asturias",
    "wof:name":"Martinez Pelaez Adolfo",
    "wof:placetype":"venue"
},
  "geometry": {"coordinates":[-5.8565311432,43.3613128662],"type":"Point"}
}