{
  "type": "Feature",
  "properties": {
    "addr:full":"Barr Goitondo, S/n Berano Nagusi Vizcaya 48269",
    "addr:housenumber":"s",
    "addr:postcode":"48269",
    "addr:street":"/ N Berano Nagusi Vizcaya",
    "iso:country":"ES",
    "sg:address":"Barr Goitondo, S/n",
    "sg:city":"Berano Nagusi",
    "sg:orig_category":"Rectificaci\u00d3n, Mecanizado, Fresado",
    "sg:phone":"+34 943 17 67 55",
    "sg:postcode":"48269",
    "sg:province":"Vizcaya",
    "wof:name":"Finesse Rectificados S.l.",
    "wof:placetype":"venue"
},
  "geometry": {"coordinates":[-2.5300109386,43.1897888184],"type":"Point"}
}