{
  "type": "Feature",
  "properties": {
    "addr:full":"Calle de Manuel Tovar, 9 Madrid Madrid 28...",
    "addr:housenumber":"9;28 ...",
    "addr:postcode":"madrid",
    "addr:street":"Calle De Manuel Tovar;Madrid",
    "iso:country":"ES",
    "sg:address":"Calle de Manuel Tovar, 9",
    "sg:city":"Madrid",
    "sg:orig_category":"Loter\u00cda Y T\u00d3mbola",
    "sg:phone":"+34 913 48 91 00",
    "sg:postcode":"28...",
    "sg:province":"Madrid",
    "wof:name":"Sistemas Tecnicos De Loterias Del Estado",
    "wof:placetype":"venue"
},
  "geometry": {"coordinates":[-3.687513113,40.4877128601],"type":"Point"}
}