{
  "type": "Feature",
  "properties": {
    "addr:full":"Avda Reyes Catolicos, S/n Albolote Granada 18220",
    "addr:housenumber":"s / n",
    "addr:postcode":"18220",
    "addr:street":"Avda Reyes Catolicos",
    "iso:country":"ES",
    "sg:address":"Avda Reyes Catolicos, S/n",
    "sg:city":"Albolote",
    "sg:orig_category":"Asociaciones, Organismos Culturales Y Socioeducativos",
    "sg:phone":"+34 958 46 68 16",
    "sg:postcode":"18220",
    "sg:province":"Granada",
    "wof:name":"Ayuntamiento De Albolote",
    "wof:placetype":"venue"
},
  "geometry": {"coordinates":[-3.6564340591,37.2279167175],"type":"Point"}
}