{
  "type": "Feature",
  "properties": {
    "addr:full":"Errekatxu Kalea, 8 Eibar Guip\u00f9zcoa 20600",
    "addr:housenumber":"8",
    "addr:postcode":"20600",
    "addr:street":"Errekatxu Kalea;Guipu\u0300Zcoa",
    "iso:country":"ES",
    "sg:address":"Errekatxu Kalea, 8",
    "sg:city":"Eibar",
    "sg:orig_category":"Grabados",
    "sg:phone":"+34 943 70 04 71",
    "sg:postcode":"20600",
    "sg:province":"Guip\u00f9zcoa",
    "wof:name":"Bermudez Arteche Jose Maria",
    "wof:placetype":"venue"
},
  "geometry": {"coordinates":[-2.4685430527,43.1837730408],"type":"Point"}
}