{
  "type": "Feature",
  "properties": {
    "iso:country":"ES",
    "sg:address":"Avda Jose Maria Alcaraz Y Alenda, 20",
    "sg:city":"Badajoz",
    "sg:orig_category":"Dom\u00d3tica",
    "sg:phone":"+34 924 24 95 85",
    "sg:postcode":"06011",
    "sg:province":"Badajoz",
    "wof:name":"Gallego Gallego Miguel Angel",
    "wof:placetype":"venue"
},
  "geometry": {"coordinates":[-6.9947738647,38.8652305603],"type":"Point"}
}