{
  "type": "Feature",
  "properties": {
    "iso:country":"ES",
    "sg:address":"Carrer de Tossa De Mar, 22",
    "sg:city":"Vilafranca Penedes",
    "sg:orig_category":"Papeler\u00cdas, Librer\u00cdas",
    "sg:phone":"+34 938 90 34 48",
    "sg:postcode":"08720",
    "sg:province":"Barcelona",
    "wof:name":"Bonell Solsona S.l.",
    "wof:placetype":"venue"
},
  "geometry": {"coordinates":[1.6964850426,41.3404273987],"type":"Point"}
}