{
  "type": "Feature",
  "properties": {
    "addr:full":"Calle de Ribesalbes, 16 Onda Castell\u00f3n 12200",
    "addr:housenumber":"16",
    "addr:postcode":"12200",
    "addr:street":"Calle De Ribesalbes;Castello\u0301N",
    "iso:country":"ES",
    "sg:address":"Calle de Ribesalbes, 16",
    "sg:city":"Onda",
    "sg:orig_category":"Librer\u00cdas",
    "sg:phone":"+34 964 60 54 93",
    "sg:postcode":"12200",
    "sg:province":"Castell\u00f3n",
    "wof:name":"Olucha Juarez Maria Jose",
    "wof:placetype":"venue"
},
  "geometry": {"coordinates":[-0.2619900107,39.9642486572],"type":"Point"}
}