{
  "type": "Feature",
  "properties": {
    "iso:country":"ES",
    "sg:address":"Pl Llucmajor, 3",
    "sg:city":"Barcelona",
    "sg:orig_category":"Cl\u00cdnicas Dentales",
    "sg:phone":"+34 933 59 63 62",
    "sg:postcode":"08042",
    "sg:province":"Barcelona",
    "wof:name":"Clinica Dental Llucmajor S.l.",
    "wof:placetype":"venue"
},
  "geometry": {"coordinates":[2.1745920181,41.4381942749],"type":"Point"}
}