{
  "type": "Feature",
  "properties": {
    "addr:full":"Calle de Ildefonso Carrascosa, 12 Poligono Ind. Mediterraneo Valencia 46560",
    "addr:housenumber":"12 poligono",
    "addr:postcode":"46560",
    "addr:street":"Calle De Ildefonso Carrascosa;Ind. Mediterraneo",
    "iso:country":"ES",
    "sg:address":"Calle de Ildefonso Carrascosa, 12",
    "sg:city":"Poligono Ind. Mediterraneo",
    "sg:orig_category":"Engranajes Y Elementos De Transmisi\u00d3n",
    "sg:phone":"+34 961 40 14 46",
    "sg:postcode":"46560",
    "sg:province":"Valencia",
    "wof:name":"Reductores Cu\u00f1at S.a.",
    "wof:placetype":"venue"
},
  "geometry": {"coordinates":[-0.3252330124,39.5581474304],"type":"Point"}
}