{
  "type": "Feature",
  "properties": {
    "addr:full":"Calle de Canarias Islas, 21 Bilbao Vizcaya 48015",
    "addr:housenumber":"21",
    "addr:postcode":"48015",
    "addr:street":"Calle De Canarias Islas",
    "iso:country":"ES",
    "sg:address":"Calle de Canarias Islas, 21",
    "sg:city":"Bilbao",
    "sg:orig_category":"Maquinaria Para Industrias Diversas",
    "sg:phone":"+34 944 47 43 94",
    "sg:postcode":"48015",
    "sg:province":"Vizcaya",
    "wof:name":"Tenkor Industrial S.l.",
    "wof:placetype":"venue"
},
  "geometry": {"coordinates":[-2.9644610882,43.2806015015],"type":"Point"}
}