{
  "type": "Feature",
  "properties": {
    "addr:full":"Calle de Naval La, 34 Palmas De Gran Canaria Las Palmas 35008",
    "addr:postcode":"35008",
    "addr:street":"Calle De Naval La 34",
    "iso:country":"ES",
    "sg:address":"Calle de Naval La, 34",
    "sg:city":"Palmas De Gran Canaria",
    "sg:orig_category":"Centros Comerciales Y Grandes Tiendas",
    "sg:phone":"+34 928 47 10 09",
    "sg:postcode":"35008",
    "sg:province":"Las Palmas",
    "wof:name":"Jumarpe S. A.",
    "wof:placetype":"venue"
},
  "geometry": {"coordinates":[-15.4289617538,28.1491737366],"type":"Point"}
}