{
  "type": "Feature",
  "properties": {
    "iso:country":"ES",
    "sg:address":"Calle de Carreteria, 115",
    "sg:city":"Malaga",
    "sg:orig_category":"Motocicletas (agentes, Concesionarios)",
    "sg:phone":"+34 952 22 90 27",
    "sg:postcode":"29008",
    "sg:province":"M\u00e1laga",
    "wof:name":"Comercial Navarro Hermanos Malaga S.a.",
    "wof:placetype":"venue"
},
  "geometry": {"coordinates":[-4.4205188751,36.7242889404],"type":"Point"}
}