{
  "type": "Feature",
  "properties": {
    "addr:full":"Cruz De San Sebastian, S/n Alcazaren Valladolid 47238",
    "addr:housenumber":"s",
    "addr:postcode":"47238",
    "addr:street":"Cruz;/ N",
    "iso:country":"ES",
    "sg:address":"Cruz De San Sebastian, S/n",
    "sg:city":"Alcazaren",
    "sg:orig_category":"Metales (labores, Pulido)",
    "sg:phone":"+34 983 60 90 44",
    "sg:postcode":"47238",
    "sg:province":"Valladolid",
    "wof:name":"Industrias Alcazare\u00f1as Vallisoletanas S.l.",
    "wof:placetype":"venue"
},
  "geometry": {"coordinates":[-4.6726145744,41.3696670532],"type":"Point"}
}