{
  "type": "Feature",
  "properties": {
    "iso:country":"ES",
    "sg:address":"Calle de Santiago Apostol, 1",
    "sg:city":"San Vicente De Barakaldo",
    "sg:orig_category":"Pescader\u00cdas (al Por Menor)",
    "sg:phone":"+34 944 99 97 09",
    "sg:postcode":"48902",
    "sg:province":"Vizcaya",
    "wof:name":"Sanchez Vieites Pedro Luis",
    "wof:placetype":"venue"
},
  "geometry": {"coordinates":[-2.9929850101,43.2926216125],"type":"Point"}
}