{
  "type": "Feature",
  "properties": {
    "iso:country":"ES",
    "sg:address":"Carr Doctor Robert, 40",
    "sg:city":"Badalona",
    "sg:orig_category":"Fabricaci\u00d3n, Venta, Instalaci\u00d3n De R\u00d3tulos, De R\u00d3tulos Luminosos",
    "sg:phone":"+34 933 83 30 88",
    "sg:postcode":"08915",
    "sg:province":"Barcelona",
    "sg:website":"www.publiverd.com",
    "wof:name":"Publiverd S.l.",
    "wof:placetype":"venue"
},
  "geometry": {"coordinates":[2.2436039448,41.4568443298],"type":"Point"}
}