{
  "type": "Feature",
  "properties": {
    "iso:country":"ES",
    "sg:address":"Calle de Valle Colorado, 52",
    "sg:city":"Mairena Aljarafe",
    "sg:orig_category":"Arquitectos",
    "sg:phone":"+34 954 18 02 27",
    "sg:postcode":"41927",
    "sg:province":"Sevilla",
    "wof:name":"Camoyan Perez Salvador",
    "wof:placetype":"venue"
},
  "geometry": {"coordinates":[-6.0351691246,37.3391609192],"type":"Point"}
}