{
  "type": "Feature",
  "properties": {
    "addr:full":"Calle de Paz, 9 Quintanar Orden Toledo 45800",
    "addr:housenumber":"9",
    "addr:postcode":"45800",
    "addr:street":"Calle De Paz",
    "iso:country":"ES",
    "sg:address":"Calle de Paz, 9",
    "sg:city":"Quintanar Orden",
    "sg:orig_category":"Reposter\u00cdas",
    "sg:phone":"+34 925 18 09 84",
    "sg:postcode":"45800",
    "sg:province":"Toledo",
    "wof:name":"Alcolado Reneses Julio",
    "wof:placetype":"venue"
},
  "geometry": {"coordinates":[-3.0371222496,39.593421936],"type":"Point"}
}