{
  "type": "Feature",
  "properties": {
    "addr:full":"Calle de Josefa Valcarcel, 40 Madrid Madrid 28...",
    "addr:housenumber":"40;28 ...",
    "addr:postcode":"madrid",
    "addr:street":"Calle De Josefa Valcarcel;Madrid",
    "iso:country":"ES",
    "sg:address":"Calle de Josefa Valcarcel, 40",
    "sg:city":"Madrid",
    "sg:orig_category":"Bancos",
    "sg:phone":"+34 913 13 70 00",
    "sg:postcode":"28...",
    "sg:province":"Madrid",
    "sg:website":"www.bancourquijo.es",
    "wof:name":"Banc Sabadell S.a.",
    "wof:placetype":"venue"
},
  "geometry": {"coordinates":[-3.6390240192,40.448387146],"type":"Point"}
}