{
  "type": "Feature",
  "properties": {
    "addr:full":"Calle de Pozuetakogaina Kalea, 15 Irun Guip\u00f9zcoa 20305",
    "addr:housenumber":"15",
    "addr:postcode":"20305",
    "addr:street":"Calle De Pozuetakogaina Kalea;Guipu\u0300Zcoa",
    "iso:country":"ES",
    "sg:address":"Calle de Pozuetakogaina Kalea, 15",
    "sg:city":"Irun",
    "sg:orig_category":"Electricidad, Electr\u00d3nica: Suministros (al Por Menor)",
    "sg:phone":"+34 943 63 50 69",
    "sg:postcode":"20305",
    "sg:province":"Guip\u00f9zcoa",
    "wof:name":"Sumat Electrosistemas S.l.",
    "wof:placetype":"venue"
},
  "geometry": {"coordinates":[-1.8167350292,43.3346443176],"type":"Point"}
}