{
  "type": "Feature",
  "properties": {
    "addr:full":"Amaya-amaia, 15 Iru\u00f1a Navarra 31004",
    "addr:housenumber":"15",
    "addr:postcode":"31004",
    "addr:street":"Amaya-Amaia",
    "iso:country":"ES",
    "sg:address":"Amaya-amaia, 15",
    "sg:city":"Iru\u00f1a",
    "sg:orig_category":"Ropa Para Se\u00d1oras (al Por Menor)",
    "sg:phone":"+34 948 23 27 27",
    "sg:postcode":"31004",
    "sg:province":"Navarra",
    "wof:name":"Emmanuel Mendioroz Eadberto",
    "wof:placetype":"venue"
},
  "geometry": {"coordinates":[-1.6367189884,42.8123245239],"type":"Point"}
}