{
  "type": "Feature",
  "properties": {
    "iso:country":"ES",
    "sg:address":"Carr Mare De Deu Del Remei, 34",
    "sg:city":"Girona",
    "sg:orig_category":"Fabricaci\u00d3n De Bibliotecas Y Estanter\u00cdas",
    "sg:phone":"+34 972 23 78 76",
    "sg:postcode":"17005",
    "sg:province":"Girona",
    "wof:name":"Ferreteria Industrial Olotense S.a.",
    "wof:placetype":"venue"
},
  "geometry": {"coordinates":[2.8112668991,41.978187561],"type":"Point"}
}