{
  "type": "Feature",
  "properties": {
    "addr:full":"Calle de Beatriz De Suabia, 41 Sevilla Sevilla 41005",
    "addr:housenumber":"41",
    "addr:postcode":"41005",
    "addr:street":"Calle De Beatriz De Suabia",
    "iso:country":"ES",
    "sg:address":"Calle de Beatriz De Suabia, 41",
    "sg:city":"Sevilla",
    "sg:orig_category":"Abogados",
    "sg:phone":"+34 954 58 29 85",
    "sg:postcode":"41005",
    "sg:province":"Sevilla",
    "wof:name":"Carnerero Parra Francisco Javier",
    "wof:placetype":"venue"
},
  "geometry": {"coordinates":[-5.9667077065,37.3854064941],"type":"Point"}
}