{
  "type": "Feature",
  "properties": {
    "iso:country":"ES",
    "sg:address":"Pase Santa Ana, 1",
    "sg:city":"Villatobas",
    "sg:orig_category":"Material Y Herramientas Agr\u00cdcolas",
    "sg:phone":"+34 925 15 21 17",
    "sg:postcode":"45310",
    "sg:province":"Toledo",
    "wof:name":"Maga Cdad. De Bienes",
    "wof:placetype":"venue"
},
  "geometry": {"coordinates":[-3.321228981,39.9009857178],"type":"Point"}
}