{
  "type": "Feature",
  "properties": {
    "addr:full":"Avda Alemania, 26 Sevilla Sevilla 41012",
    "addr:housenumber":"26",
    "addr:postcode":"41012",
    "addr:street":"Avda Alemania",
    "iso:country":"ES",
    "sg:address":"Avda Alemania, 26",
    "sg:city":"Sevilla",
    "sg:orig_category":"Cajas De Ahorro",
    "sg:phone":"+34 954 29 64 02",
    "sg:postcode":"41012",
    "sg:province":"Sevilla",
    "sg:website":"www.inicaja.es",
    "wof:name":"Unicaja",
    "wof:placetype":"venue"
},
  "geometry": {"coordinates":[-5.9785890579,37.3460083008],"type":"Point"}
}