{
  "type": "Feature",
  "properties": {
    "iso:country":"ES",
    "sg:address":"Carr Palleter, Del, 8",
    "sg:city":"Quart Poblet",
    "sg:orig_category":"Servicios De Telecomunicaciones",
    "sg:phone":"+34 961 52 48 79",
    "sg:postcode":"46930",
    "sg:province":"Valencia",
    "wof:name":"Telecomunicaciones Digitales Quart S.l.",
    "wof:placetype":"venue"
},
  "geometry": {"coordinates":[-0.4419890046,39.482711792],"type":"Point"}
}