{
  "type": "Feature",
  "properties": {
    "iso:country":"ES",
    "sg:address":"C/ Mar, De La, 17",
    "sg:city":"Porto Cristo",
    "sg:orig_category":"Caf\u00c9s, Bares, Cervecer\u00cdas",
    "sg:phone":"+34 971 82 21 07",
    "sg:postcode":"07680",
    "sg:province":"Islas Baleares",
    "wof:name":"Asegurado Terrasa Gaspar",
    "wof:placetype":"venue"
},
  "geometry": {"coordinates":[3.3330509663,39.5405426025],"type":"Point"}
}