{
  "type": "Feature",
  "properties": {
    "iso:country":"ES",
    "sg:address":"Plaz Fuente, 3",
    "sg:city":"Monforte Sierra",
    "sg:orig_category":"Alquiler De Casas Y Habitaciones Amuebladas",
    "sg:phone":"+34 923 41 80 57",
    "sg:postcode":"37618",
    "sg:province":"Salamanca",
    "wof:name":"Garcia Lopez Angel",
    "wof:placetype":"venue"
},
  "geometry": {"coordinates":[-5.6687088013,40.76121521],"type":"Point"}
}