{
  "type": "Feature",
  "properties": {
    "iso:country":"ES",
    "sg:address":"Calle de Castilla, 19",
    "sg:city":"Santander",
    "sg:orig_category":"Cl\u00cdnicas Dentales",
    "sg:phone":"+34 942 31 17 71",
    "sg:postcode":"39009",
    "sg:province":"Cantabria",
    "wof:name":"Franco Marcos Maria Josefa",
    "wof:placetype":"venue"
},
  "geometry": {"coordinates":[-3.8116796017,43.4577293396],"type":"Point"}
}