{
  "type": "Feature",
  "properties": {
    "iso:country":"ES",
    "sg:address":"Zona Ferrov. (p I Juncaril), S/n",
    "sg:city":"Albolote",
    "sg:orig_category":"Polideportivos",
    "sg:phone":"+34 958 46 53 55",
    "sg:postcode":"18220",
    "sg:province":"Granada",
    "wof:name":"Ayuntamiento De Albolote",
    "wof:placetype":"venue"
},
  "geometry": {"coordinates":[-3.6521849632,37.3158683777],"type":"Point"}
}