{
  "type": "Feature",
  "properties": {
    "iso:country":"ES",
    "sg:address":"Calle de Isaac Peral, 25",
    "sg:city":"Valencia",
    "sg:orig_category":"Discapacitados",
    "sg:phone":"+34 963 30 14 77",
    "sg:postcode":"46024",
    "sg:province":"Valencia",
    "wof:name":"Bona Gent Amigos Del Deficiente Mental",
    "wof:placetype":"venue"
},
  "geometry": {"coordinates":[-0.3389529884,39.4591255188],"type":"Point"}
}