{
  "type": "Feature",
  "properties": {
    "addr:full":"Plaz Juego De Pelota, 3 Cobisa Toledo 45111",
    "addr:housenumber":"3",
    "addr:postcode":"45111",
    "iso:country":"ES",
    "sg:address":"Plaz Juego De Pelota, 3",
    "sg:city":"Cobisa",
    "sg:classifiers":[
        {
            "category":"Personal",
            "subcategory":"Barber",
            "type":"Services"
        }
    ],
    "sg:phone":"+34 925 37 85 08",
    "sg:postcode":"45111",
    "sg:province":"Toledo",
    "sg:tags":[
        "caballeros",
        "de",
        "peluqueros"
    ],
    "wof:name":"Ruiz Cano Diego",
    "wof:placetype":"venue"
},
  "geometry": {"coordinates":[-4.0247011185,39.8051834106],"type":"Point"}
}