{
  "type": "Feature",
  "properties": {
    "iso:country":"ES",
    "sg:address":"Calle de Londres, 1",
    "sg:city":"Benidorm",
    "sg:orig_category":"Herboristas (al Por Menor)",
    "sg:phone":"+34 966 80 99 32",
    "sg:postcode":"03500",
    "sg:province":"Alicante",
    "wof:name":"Ripoll Ripoll Fernando",
    "wof:placetype":"venue"
},
  "geometry": {"coordinates":[-0.1063489988,38.5364608765],"type":"Point"}
}