{
  "type": "Feature",
  "properties": {
    "addr:full":"Calle de Esteban Carros, 61 Madrid Madrid 28053",
    "addr:housenumber":"61",
    "addr:postcode":"madrid;28053",
    "addr:street":"Calle De Esteban Carros",
    "iso:country":"ES",
    "sg:address":"Calle de Esteban Carros, 61",
    "sg:city":"Madrid",
    "sg:orig_category":"Alimentaci\u00d3n General (al Por Menor)",
    "sg:phone":"+34 917 85 70 88",
    "sg:postcode":"28053",
    "sg:province":"Madrid",
    "wof:name":"Martinez Barcala Alfredo",
    "wof:placetype":"venue"
},
  "geometry": {"coordinates":[-3.6593608856,40.3701438904],"type":"Point"}
}