{
  "type": "Feature",
  "properties": {
    "addr:full":"Calle de Rioja, 77 Leganes Madrid 28915",
    "addr:housenumber":"77",
    "addr:postcode":"28915",
    "addr:street":"Calle De Rioja",
    "iso:country":"ES",
    "sg:address":"Calle de Rioja, 77",
    "sg:city":"Leganes",
    "sg:orig_category":"Fabricaci\u00d3n, Importaci\u00d3n De L\u00c1mparas Y Bombillas",
    "sg:phone":"+34 916 87 05 65",
    "sg:postcode":"28915",
    "sg:province":"Madrid",
    "wof:name":"Gomez Gomez Eulogio",
    "wof:placetype":"venue"
},
  "geometry": {"coordinates":[-3.7531530857,40.3301048279],"type":"Point"}
}