{
  "type": "Feature",
  "properties": {
    "iso:country":"ES",
    "sg:address":"Sa Sinia Costabella, 13",
    "sg:city":"Mao",
    "sg:orig_category":"Institutos De Belleza",
    "sg:phone":"+34 971 36 85 95",
    "sg:postcode":"07702",
    "sg:province":"Islas Baleares",
    "wof:name":"Mercadal Muntaner Magdalena",
    "wof:placetype":"venue"
},
  "geometry": {"coordinates":[4.2634840012,39.884601593],"type":"Point"}
}