{
  "type": "Feature",
  "properties": {
    "iso:country":"ES",
    "sg:address":"Avda Oporto, 2",
    "sg:city":"Madrid",
    "sg:orig_category":"Caf\u00c9s, Bares, Cervecer\u00cdas",
    "sg:phone":"+34 915 69 18 93",
    "sg:postcode":"28019",
    "sg:province":"Madrid",
    "wof:name":"Lavian S.a.",
    "wof:placetype":"venue"
},
  "geometry": {"coordinates":[-3.7180273533,40.3851318359],"type":"Point"}
}