{
  "type": "Feature",
  "properties": {
    "iso:country":"ES",
    "sg:address":"Calle de Lazarillo De Tormes, 4",
    "sg:city":"Escalona",
    "sg:orig_category":"M\u00c9dicos: Estomatolog\u00cda",
    "sg:phone":"+34 925 78 00 48",
    "sg:postcode":"45910",
    "sg:province":"Toledo",
    "wof:name":"Morbidelli  Jorge Enrique",
    "wof:placetype":"venue"
},
  "geometry": {"coordinates":[-4.4043660164,40.1662101746],"type":"Point"}
}