{
  "type": "Feature",
  "properties": {
    "iso:country":"ES",
    "sg:address":"Plaz Elizondo, S/n",
    "sg:city":"Berriz-olakueta",
    "sg:orig_category":"Polideportivos",
    "sg:phone":"+34 946 82 43 74",
    "sg:postcode":"48240",
    "sg:province":"Vizcaya",
    "wof:name":"Berrizko Udala-kiroldegia - Polideportivo",
    "wof:placetype":"venue"
},
  "geometry": {"coordinates":[-2.5769429207,43.177822113],"type":"Point"}
}