{
  "type": "Feature",
  "properties": {
    "addr:full":"Carr Abeurador, 5 Albi Lleida 25450",
    "addr:housenumber":"5",
    "addr:postcode":"25450",
    "addr:street":"Carr Abeurador",
    "iso:country":"ES",
    "sg:address":"Carr Abeurador, 5",
    "sg:city":"Albi",
    "sg:orig_category":"\u00c1rboles Frutales",
    "sg:phone":"+34 973 17 54 84",
    "sg:postcode":"25450",
    "sg:province":"Lleida",
    "wof:name":"Bernat Ciurana Emili",
    "wof:placetype":"venue"
},
  "geometry": {"coordinates":[0.9390789866,41.4253921509],"type":"Point"}
}