{
  "type": "Feature",
  "properties": {
    "iso:country":"ES",
    "sg:address":"Carrer de Horta, 12",
    "sg:city":"Barcelona",
    "sg:orig_category":"Asesor\u00cda Sobre Comunicaci\u00d3n De Empresas",
    "sg:phone":"+34 933 57 32 65",
    "sg:postcode":"08031",
    "sg:province":"Barcelona",
    "wof:name":"Agemar S.l.",
    "wof:placetype":"venue"
},
  "geometry": {"coordinates":[2.1623387337,41.4306678772],"type":"Point"}
}