{
  "type": "Feature",
  "properties": {
    "iso:country":"ES",
    "sg:address":"Urb Polig Ind La Ermita, 3",
    "sg:city":"Poligono Industrial La Ermita",
    "sg:orig_category":"Material Y Herramientas Agr\u00cdcolas",
    "sg:phone":"+34 925 55 93 77",
    "sg:postcode":"45215",
    "sg:province":"Toledo",
    "wof:name":"Casagro Toledo S.l.",
    "wof:placetype":"venue"
},
  "geometry": {"coordinates":[-3.9173390865,40.1418914795],"type":"Point"}
}