{
  "type": "Feature",
  "properties": {
    "addr:full":"Avda Campos Goticos, 18 Palencia Palencia 34003",
    "addr:housenumber":"18",
    "addr:postcode":"34003",
    "addr:street":"Avda Campos Goticos",
    "iso:country":"ES",
    "sg:address":"Avda Campos Goticos, 18",
    "sg:city":"Palencia",
    "sg:orig_category":"Suministros Para Hoteles",
    "sg:phone":"+34 979 74 35 14",
    "sg:postcode":"34003",
    "sg:province":"Palencia",
    "wof:name":"Garcia Maestro Jose Antonio",
    "wof:placetype":"venue"
},
  "geometry": {"coordinates":[-4.5268759727,42.017578125],"type":"Point"}
}