{
  "type": "Feature",
  "properties": {
    "iso:country":"ES",
    "sg:address":"Calle de Leon Xiii, 13",
    "sg:city":"Sevilla",
    "sg:orig_category":"Reposter\u00cdas",
    "sg:phone":"+34 954 37 82 39",
    "sg:postcode":"41009",
    "sg:province":"Sevilla",
    "wof:name":"Mopan S.l.",
    "wof:placetype":"venue"
},
  "geometry": {"coordinates":[-5.9837260246,37.4020729065],"type":"Point"}
}