{
  "type": "Feature",
  "properties": {
    "iso:country":"ES",
    "sg:address":"Ctr Lucena-loja, Km. 0034,0",
    "sg:city":"Iznajar",
    "sg:orig_category":"Transportes Por V\u00cdas Navegables",
    "sg:phone":"+34 957 53 45 66",
    "sg:postcode":"14970",
    "sg:province":"C\u00f3rdoba",
    "wof:name":"Materiales De Construcciones Los Ignagenios S.l.",
    "wof:placetype":"venue"
},
  "geometry": {"coordinates":[-4.3051857948,37.2579154968],"type":"Point"}
}