{
  "type": "Feature",
  "properties": {
    "addr:full":"Calle de Ramon De Campoamor, 3 Hellin Albacete 02400",
    "addr:housenumber":"3",
    "addr:postcode":"02400",
    "addr:street":"Calle De Ramon De Campoamor",
    "iso:country":"ES",
    "sg:address":"Calle de Ramon De Campoamor, 3",
    "sg:city":"Hellin",
    "sg:orig_category":"Juegos Y Juguetes (al Por Menor)",
    "sg:phone":"+34 967 54 32 05",
    "sg:postcode":"02400",
    "sg:province":"Albacete",
    "wof:name":"Salvador Bernabeu S.l.",
    "wof:placetype":"venue"
},
  "geometry": {"coordinates":[-1.6967029572,38.5078086853],"type":"Point"}
}