{
  "type": "Feature",
  "properties": {
    "iso:country":"ES",
    "sg:address":"Avda Agirre Lehendakaria, 51",
    "sg:city":"Basauri",
    "sg:orig_category":"M\u00c9dicos: Estomatolog\u00cda",
    "sg:phone":"+34 944 26 05 03",
    "sg:postcode":"48970",
    "sg:province":"Vizcaya",
    "wof:name":"Eduardo Eguileor Gurtubai",
    "wof:placetype":"venue"
},
  "geometry": {"coordinates":[-2.8845338821,43.2369194031],"type":"Point"}
}