{
  "type": "Feature",
  "properties": {
    "iso:country":"ES",
    "sg:address":"Carr Isabel La Catolica, 4",
    "sg:city":"Moncada",
    "sg:orig_category":"Internados & Ense\u00d1anza Privada",
    "sg:phone":"+34 961 39 04 75",
    "sg:postcode":"46113",
    "sg:province":"Valencia",
    "wof:name":"Hermanas Franciscanas De La Inmaculada",
    "wof:placetype":"venue"
},
  "geometry": {"coordinates":[-0.3944489062,39.5426864624],"type":"Point"}
}