{
  "type": "Feature",
  "properties": {
    "addr:full":"Calle de Angel Ganivet, 10 Zaragoza Zaragoza 50008",
    "addr:housenumber":"10",
    "addr:postcode":"50008",
    "addr:street":"Calle De Angel Ganivet",
    "iso:country":"ES",
    "sg:address":"Calle de Angel Ganivet, 10",
    "sg:city":"Zaragoza",
    "sg:orig_category":"Carnicer\u00cdas, Carnicer\u00cdas",
    "sg:phone":"+34 976 41 53 61",
    "sg:postcode":"50008",
    "sg:province":"Zaragoza",
    "wof:name":"Villarroya Villarroya Joaquin",
    "wof:placetype":"venue"
},
  "geometry": {"coordinates":[-0.8744950294,41.6382026672],"type":"Point"}
}