{
  "type": "Feature",
  "properties": {
    "iso:country":"ES",
    "sg:address":"Calle de Torrevejenses Ausentes, 2",
    "sg:city":"Torrevieja",
    "sg:orig_category":"Arquitectos",
    "sg:phone":"+34 966 70 32 43",
    "sg:postcode":"03180",
    "sg:province":"Alicante",
    "wof:name":"Molpeceres S.l.",
    "wof:placetype":"venue"
},
  "geometry": {"coordinates":[-0.6780669093,37.976146698],"type":"Point"}
}