{
  "type": "Feature",
  "properties": {
    "iso:country":"ES",
    "sg:address":"Avda Regne De Valencia, 30",
    "sg:city":"Valencia",
    "sg:orig_category":"Peluqueros: De Se\u00d1oras",
    "sg:phone":"+34 963 33 16 96",
    "sg:postcode":"46005",
    "sg:province":"Valencia",
    "wof:name":"Sanfelix And Carrera S.l.",
    "wof:placetype":"venue"
},
  "geometry": {"coordinates":[-0.3704079986,39.4640731812],"type":"Point"}
}