{
  "type": "Feature",
  "properties": {
    "addr:full":"Carrer de Ripoll, 10 Manlleu Barcelona 08560",
    "addr:housenumber":"10",
    "addr:postcode":"08560",
    "addr:street":"Carrer De Ripoll",
    "iso:country":"ES",
    "sg:address":"Carrer de Ripoll, 10",
    "sg:city":"Manlleu",
    "sg:orig_category":"Suministros Y Materiales Industriales",
    "sg:phone":"+34 938 51 52 10",
    "sg:postcode":"08560",
    "sg:province":"Barcelona",
    "sg:website":"www.sicosavic.com",
    "wof:name":"Suministros Comarca De Osona S.c.l.",
    "wof:placetype":"venue"
},
  "geometry": {"coordinates":[2.2891509533,42.0028839111],"type":"Point"}
}