{
  "type": "Feature",
  "properties": {
    "iso:country":"ES",
    "sg:address":"Ctra De Cordoba-almeria, Km. 0139,7",
    "sg:city":"Cambil",
    "sg:orig_category":"Distribuci\u00d3n De Petr\u00d3leo Y Derivados",
    "sg:phone":"+34 953 30 05 58",
    "sg:postcode":"23120",
    "sg:province":"Ja\u00e9n",
    "wof:name":"Estacion De Servicio De Cambil S.l.",
    "wof:placetype":"venue"
},
  "geometry": {"coordinates":[-3.564399004,37.6802139282],"type":"Point"}
}