{
  "type": "Feature",
  "properties": {
    "iso:country":"ES",
    "sg:address":"Calle de Portal De Foronda, 32",
    "sg:city":"Vitoria-gasteiz",
    "sg:orig_category":"Institutos De Belleza",
    "sg:phone":"+34 945 17 14 16",
    "sg:postcode":"01010",
    "sg:province":"\u00c1lava",
    "wof:name":"Selene S.c.",
    "wof:placetype":"venue"
},
  "geometry": {"coordinates":[-2.6857790947,42.8656997681],"type":"Point"}
}