{
  "type": "Feature",
  "properties": {
    "iso:country":"ES",
    "sg:address":"Golf De Cadis, 4",
    "sg:city":"Palma",
    "sg:orig_category":"Centros Empresariales",
    "sg:phone":"+34 971 24 61 68",
    "sg:postcode":"07007",
    "sg:province":"Islas Baleares",
    "wof:name":"Balear Flug S.l.",
    "wof:placetype":"venue"
},
  "geometry": {"coordinates":[2.6868975163,39.5551795959],"type":"Point"}
}