{
  "type": "Feature",
  "properties": {
    "iso:country":"ES",
    "sg:address":"Carrer de Llan\u00c7a, 52",
    "sg:city":"Barcelona",
    "sg:orig_category":"Agencias Y Agentes Comerciales, Representantes",
    "sg:phone":"+34 932 26 46 65",
    "sg:postcode":"08015",
    "sg:province":"Barcelona",
    "wof:name":"Punti Perello Jaume",
    "wof:placetype":"venue"
},
  "geometry": {"coordinates":[2.1455290318,41.3802452087],"type":"Point"}
}