{
  "type": "Feature",
  "properties": {
    "iso:country":"ES",
    "sg:address":"Carrer de Protectora, 10",
    "sg:city":"Palma",
    "sg:orig_category":"Peluquer\u00cdas, Peluquer\u00cda Mixta",
    "sg:phone":"+34 971 72 75 38",
    "sg:postcode":"07012",
    "sg:province":"Islas Baleares",
    "wof:name":"Gabric  Susanne",
    "wof:placetype":"venue"
},
  "geometry": {"coordinates":[2.644687891,39.5715866089],"type":"Point"}
}