{
  "type": "Feature",
  "properties": {
    "addr:full":"Pol Ind Santa Olalla, S/n Campohermoso Almer\u00eda 04110",
    "addr:housenumber":"s / n",
    "addr:postcode":"04110",
    "addr:street":"Almeri\u0301A",
    "iso:country":"ES",
    "sg:address":"Pol Ind Santa Olalla, S/n",
    "sg:city":"Campohermoso",
    "sg:orig_category":"Producci\u00d3n De Abonos Y De Fertilizantes",
    "sg:phone":"+34 950 38 62 64",
    "sg:postcode":"04110",
    "sg:province":"Almer\u00eda",
    "wof:name":"Ferticampo Del Levante S.l.",
    "wof:placetype":"venue"
},
  "geometry": {"coordinates":[-2.1324241161,36.9409065247],"type":"Point"}
}