{
  "type": "Feature",
  "properties": {
    "addr:full":"Calle de Eulalia Gil, 8 Madrid Madrid 28025",
    "addr:housenumber":"8",
    "addr:postcode":"madrid;28025",
    "addr:street":"Calle De Eulalia Gil",
    "iso:country":"ES",
    "sg:address":"Calle de Eulalia Gil, 8",
    "sg:city":"Madrid",
    "sg:orig_category":"Mec\u00c1nico Del Autom\u00d3vil",
    "sg:phone":"+34 914 65 39 66",
    "sg:postcode":"28025",
    "sg:province":"Madrid",
    "wof:name":"Diez Fernandez Julio",
    "wof:placetype":"venue"
},
  "geometry": {"coordinates":[-3.7423260212,40.3859100342],"type":"Point"}
}