{
  "type": "Feature",
  "properties": {
    "iso:country":"ES",
    "sg:address":"Ctra Igualada (d'), 51",
    "sg:city":"Santa Coloma De Queralt",
    "sg:orig_category":"Producci\u00d3n, Comercio De Cereales",
    "sg:phone":"+34 977 88 00 31",
    "sg:postcode":"43420",
    "sg:province":"Tarragona",
    "wof:name":"Cereals Santa Coloma S.l.",
    "wof:placetype":"venue"
},
  "geometry": {"coordinates":[1.3841739893,41.5357055664],"type":"Point"}
}