{
  "type": "Feature",
  "properties": {
    "iso:country":"ES",
    "sg:address":"Calle de Calleja Y Zurita, 5",
    "sg:city":"Burgos",
    "sg:orig_category":"Agencias Y Agentes Comerciales, Representantes",
    "sg:phone":"+34 947 26 23 09",
    "sg:postcode":"09001",
    "sg:province":"Burgos",
    "wof:name":"Briones Arauzo Pablo",
    "wof:placetype":"venue"
},
  "geometry": {"coordinates":[-3.7010800838,42.3320732117],"type":"Point"}
}