{
  "type": "Feature",
  "properties": {
    "iso:country":"ES",
    "sg:address":"Avda Valdelaparra (de), 4",
    "sg:city":"Alcobendas",
    "sg:orig_category":"Ropa De Casa (fabricaci\u00d3n, Al Por Mayor)",
    "sg:phone":"+34 916 62 66 54",
    "sg:postcode":"28108",
    "sg:province":"Madrid",
    "sg:website":"www.mastroraphael.com",
    "wof:name":"Mc La Esencia Del Color S.l.",
    "wof:placetype":"venue"
},
  "geometry": {"coordinates":[-3.641505003,40.536529541],"type":"Point"}
}