{
  "type": "Feature",
  "properties": {
    "addr:full":"Calle de Sebastian Elcano, 13 Sevilla Sevilla 41011",
    "addr:housenumber":"13",
    "addr:postcode":"41011",
    "addr:street":"Calle De Sebastian Elcano",
    "iso:country":"ES",
    "sg:address":"Calle de Sebastian Elcano, 13",
    "sg:city":"Sevilla",
    "sg:orig_category":"Centros M\u00c9dicos Y Sociales, Dispensarios",
    "sg:phone":"+34 954 28 13 28",
    "sg:postcode":"41011",
    "sg:province":"Sevilla",
    "sg:website":"www.centroaudiologico.com",
    "wof:name":"Centro Audiologico S.l.",
    "wof:placetype":"venue"
},
  "geometry": {"coordinates":[-5.9958620071,37.3743591309],"type":"Point"}
}