{
  "type": "Feature",
  "properties": {
    "addr:full":"Calle de Refino, 36 Malaga M\u00e1laga 29013",
    "addr:housenumber":"36",
    "addr:postcode":"29013",
    "addr:street":"Calle De Refino;Ma\u0301Laga",
    "iso:country":"ES",
    "sg:address":"Calle de Refino, 36",
    "sg:city":"Malaga",
    "sg:orig_category":"Arquitectos",
    "sg:phone":"+34 952 31 88 20",
    "sg:postcode":"29013",
    "sg:province":"M\u00e1laga",
    "wof:name":"Arquyres S.l.",
    "wof:placetype":"venue"
},
  "geometry": {"coordinates":[-4.4201188087,36.726360321],"type":"Point"}
}