{
  "type": "Feature",
  "properties": {
    "addr:full":"Carrera de San Jeronimo 15 Madrid 28013",
    "addr:housenumber":"15",
    "addr:postcode":"28013",
    "addr:street":"Carrera De San Jeronimo",
    "iso:country":"ES",
    "sg:address":"Carrera de San Jeronimo 15",
    "sg:city":"Madrid",
    "sg:classifiers":[
        {
            "category":"Professional",
            "subcategory":"Computer Services",
            "type":"Services"
        }
    ],
    "sg:postcode":"28013",
    "sg:tags":[
        "ruby",
        "rails",
        "ruby-on-rails",
        "software",
        "agile",
        "less-is-more",
        "web-solutions",
        "agile-technology",
        "agile-development"
    ],
    "sg:website":"http://aspgems.com",
    "wof:name":"ASPgems",
    "wof:placetype":"venue"
},
  "geometry": {"coordinates":[-3.6992667,40.4165967],"type":"Point"}
}