{
  "type": "Feature",
  "properties": {
    "addr:full":"Calle de Real, 68 Gumiel De Izan Burgos 09370",
    "addr:housenumber":"68",
    "addr:postcode":"09370",
    "addr:street":"Calle De Real",
    "iso:country":"ES",
    "sg:address":"Calle de Real, 68",
    "sg:city":"Gumiel De Izan",
    "sg:orig_category":"Molduras, Junquillos, Listones Y Molduras Perforadas",
    "sg:phone":"+34 947 54 42 86",
    "sg:postcode":"09370",
    "sg:province":"Burgos",
    "wof:name":"Gonzalez Alonso Julian",
    "wof:placetype":"venue"
},
  "geometry": {"coordinates":[-3.6889688969,41.7734603882],"type":"Point"}
}