{
  "type": "Feature",
  "properties": {
    "iso:country":"ES",
    "sg:address":"Pol Ind Pozueta Mendieta, S/n",
    "sg:city":"Lemoa",
    "sg:orig_category":"Mayoristas E Intermediarios En Alcoholes",
    "sg:phone":"+34 946 31 25 38",
    "sg:postcode":"48330",
    "sg:province":"Vizcaya",
    "wof:name":"Beer Edariak S.l",
    "wof:placetype":"venue"
},
  "geometry": {"coordinates":[-2.7691090107,43.2078361511],"type":"Point"}
}