{
  "type": "Feature",
  "properties": {
    "iso:country":"ES",
    "sg:address":"Carrer de Tibidabo, 3",
    "sg:city":"Ca N'amat",
    "sg:orig_category":"Delegados, Agentes De Tr\u00c1nsito, Auxiliares De Transporte Internacional",
    "sg:phone":"+34 937 70 08 48",
    "sg:postcode":"08630",
    "sg:province":"Barcelona",
    "wof:name":"Logtravi S. L.",
    "wof:placetype":"venue"
},
  "geometry": {"coordinates":[1.8560167551,41.5234680176],"type":"Point"}
}