{
  "type": "Feature",
  "properties": {
    "iso:country":"ES",
    "sg:address":"Calle de Nuestro Padre Jesus, 5",
    "sg:city":"Bailen",
    "sg:orig_category":"Producci\u00d3n, Distribuci\u00d3n De Gas Butano Y Propano",
    "sg:phone":"+34 953 67 07 65",
    "sg:postcode":"23710",
    "sg:province":"Ja\u00e9n",
    "wof:name":"Duro Lopez Celia",
    "wof:placetype":"venue"
},
  "geometry": {"coordinates":[-3.7751760483,38.0961265564],"type":"Point"}
}