{
  "type": "Feature",
  "properties": {
    "iso:country":"ES",
    "sg:address":"Pg Saralegui, 50",
    "sg:city":"Puerto De Pollen\u00c7a",
    "sg:orig_category":"Alquiler De Veh\u00cdculos: Turismos Y Utilitarios",
    "sg:phone":"+34 971 86 54 92",
    "sg:postcode":"07470",
    "sg:province":"Islas Baleares",
    "wof:name":"Motos Formentor S.l.",
    "wof:placetype":"venue"
},
  "geometry": {"coordinates":[3.0815610886,39.9049530029],"type":"Point"}
}