{
  "type": "Feature",
  "properties": {
    "addr:full":"Rond Francesc Camprodon, 43 Vic Barcelona 08500",
    "addr:housenumber":"43",
    "addr:postcode":"08500",
    "addr:street":"Rond;Camprodon",
    "iso:country":"ES",
    "sg:address":"Rond Francesc Camprodon, 43",
    "sg:city":"Vic",
    "sg:orig_category":"Ense\u00d1anza: Idiomas",
    "sg:phone":"+34 938 86 11 07",
    "sg:postcode":"08500",
    "sg:province":"Barcelona",
    "wof:name":"Boix Garrido Isabel",
    "wof:placetype":"venue"
},
  "geometry": {"coordinates":[2.2521190643,41.9336662292],"type":"Point"}
}