{
  "type": "Feature",
  "properties": {
    "iso:country":"ES",
    "sg:address":"Bo. Auto, 66",
    "sg:city":"Garrapinillos",
    "sg:orig_category":"Granos Y Forrajes",
    "sg:phone":"+34 976 78 01 05",
    "sg:postcode":"50190",
    "sg:province":"Zaragoza",
    "wof:name":"Agroluna S.l.",
    "wof:placetype":"venue"
},
  "geometry": {"coordinates":[-1.0273573399,41.6837768555],"type":"Point"}
}