{
  "type": "Feature",
  "properties": {
    "iso:country":"ES",
    "sg:address":"Carretera De Selaya, 88",
    "sg:city":"Iruz",
    "sg:orig_category":"Material Y Herramientas Agr\u00cdcolas",
    "sg:phone":"+34 942 59 60 13",
    "sg:postcode":"39697",
    "sg:province":"Cantabria",
    "wof:name":"Gonzalez Urquijo Arturo",
    "wof:placetype":"venue"
},
  "geometry": {"coordinates":[-3.9474210739,43.2660255432],"type":"Point"}
}