{
  "type": "Feature",
  "properties": {
    "iso:country":"ES",
    "sg:address":"Av Montbrio, S/n",
    "sg:city":"Riudoms",
    "sg:orig_category":"Carnicer\u00cdas, Carnicer\u00cdas",
    "sg:phone":"+34 977 76 81 81",
    "sg:postcode":"43330",
    "sg:province":"Tarragona",
    "wof:name":"Ciers S.l.",
    "wof:placetype":"venue"
},
  "geometry": {"coordinates":[1.0495849848,41.1374855042],"type":"Point"}
}