{
  "type": "Feature",
  "properties": {
    "iso:country":"ES",
    "sg:address":"Carrer de Joan Bauza, 9",
    "sg:city":"Palma",
    "sg:orig_category":"Agencias Y Agentes Comerciales, Representantes",
    "sg:phone":"+34 971 46 32 15",
    "sg:postcode":"07005",
    "sg:province":"Islas Baleares",
    "wof:name":"Esteve Burgaya Ramon",
    "wof:placetype":"venue"
},
  "geometry": {"coordinates":[2.6623868942,39.5733108521],"type":"Point"}
}