{
  "type": "Feature",
  "properties": {
    "addr:full":"Calle de Marcos Del Torniello, 50 Aviles Asturias 33401",
    "addr:housenumber":"50",
    "addr:postcode":"33401",
    "addr:street":"Calle De Marcos Del Torniello",
    "iso:country":"ES",
    "sg:address":"Calle de Marcos Del Torniello, 50",
    "sg:city":"Aviles",
    "sg:orig_category":"Mantenimiento Industrial",
    "sg:phone":"+34 985 52 73 60",
    "sg:postcode":"33401",
    "sg:province":"Asturias",
    "wof:name":"Ingenieria Montajes Norte S.a.",
    "wof:placetype":"venue"
},
  "geometry": {"coordinates":[-5.9248771667,43.561958313],"type":"Point"}
}