{
  "type": "Feature",
  "properties": {
    "iso:country":"ES",
    "sg:address":"Calle de Fuente De Los Corzos, 3",
    "sg:city":"Jaen",
    "sg:orig_category":"Arquitectos",
    "sg:phone":"+34 953 26 38 06",
    "sg:postcode":"23006",
    "sg:province":"Ja\u00e9n",
    "wof:name":"Ortega Perea Blas",
    "wof:placetype":"venue"
},
  "geometry": {"coordinates":[-3.8050239086,37.7802352905],"type":"Point"}
}