{
  "type": "Feature",
  "properties": {
    "iso:country":"ES",
    "sg:address":"Calle de Arturo Soria, 29",
    "sg:city":"Madrid",
    "sg:orig_category":"Distribuci\u00d3n De Petr\u00d3leo Y Derivados",
    "sg:phone":"+34 913 67 10 46",
    "sg:postcode":"28027",
    "sg:province":"Madrid",
    "wof:name":"Onyher S.l.",
    "wof:placetype":"venue"
},
  "geometry": {"coordinates":[-3.6407730579,40.4414291382],"type":"Point"}
}