{
  "type": "Feature",
  "properties": {
    "iso:country":"ES",
    "sg:address":"Calle de Luis Montoto, 107",
    "sg:city":"Sevilla",
    "sg:orig_category":"Centros Empresariales",
    "sg:phone":"+34 954 57 22 69",
    "sg:postcode":"41007",
    "sg:province":"Sevilla",
    "sg:website":"www.ac-g.com",
    "wof:name":"Asesoria Consultoria Y Gestion Andalucia S.a",
    "wof:placetype":"venue"
},
  "geometry": {"coordinates":[-5.9704885483,37.3874816895],"type":"Point"}
}