{
  "type": "Feature",
  "properties": {
    "addr:full":"Calle de Poeta Herrero, 22 Requena Valencia 46340",
    "addr:housenumber":"22",
    "addr:postcode":"46340",
    "addr:street":"Calle De Poeta Herrero",
    "iso:country":"ES",
    "sg:address":"Calle de Poeta Herrero, 22",
    "sg:city":"Requena",
    "sg:orig_category":"Electrodom\u00c9sticos (al Por Menor)",
    "sg:phone":"+34 962 30 41 64",
    "sg:postcode":"46340",
    "sg:province":"Valencia",
    "wof:name":"Electrodomesticos Antonio Martinez S.l",
    "wof:placetype":"venue"
},
  "geometry": {"coordinates":[-1.0988750458,39.4884567261],"type":"Point"}
}