{
  "type": "Feature",
  "properties": {
    "addr:full":"Calle de Cayetano Muriel, 10 Benameji C\u00f3rdoba 14910",
    "addr:housenumber":"10",
    "addr:postcode":"14910",
    "addr:street":"Calle De Cayetano Muriel;Co\u0301Rdoba",
    "iso:country":"ES",
    "sg:address":"Calle de Cayetano Muriel, 10",
    "sg:city":"Benameji",
    "sg:orig_category":"Ropa Para Ni\u00d1os (al Por Menor)",
    "sg:phone":"+34 957 53 13 56",
    "sg:postcode":"14910",
    "sg:province":"C\u00f3rdoba",
    "wof:name":"Aguilar Cabello Rosario",
    "wof:placetype":"venue"
},
  "geometry": {"coordinates":[-4.5403423309,37.2678642273],"type":"Point"}
}