{
  "type": "Feature",
  "properties": {
    "iso:country":"ES",
    "sg:address":"Carrer de Garrofers, 31",
    "sg:city":"Hospitalet Llobregat",
    "sg:orig_category":"Fabricaci\u00d3n De Ventanas",
    "sg:phone":"+34 934 40 88 33",
    "sg:postcode":"08905",
    "sg:province":"Barcelona",
    "wof:name":"Salvador Fontao Maria Isabel",
    "wof:placetype":"venue"
},
  "geometry": {"coordinates":[2.1117238998,41.367980957],"type":"Point"}
}