{
  "type": "Feature",
  "properties": {
    "iso:country":"ES",
    "sg:address":"Carrer de Garcilaso, 141",
    "sg:city":"Sabadell",
    "sg:orig_category":"Asesor\u00cda De Formaci\u00d3n Y Gesti\u00d3n De Personal",
    "sg:phone":"+34 937 26 42 42",
    "sg:postcode":"08201",
    "sg:province":"Barcelona",
    "wof:name":"Rus Associats S.c.p.",
    "wof:placetype":"venue"
},
  "geometry": {"coordinates":[2.1009368896,41.5489273071],"type":"Point"}
}