{
  "type": "Feature",
  "properties": {
    "addr:full":"Rua Clerigos (dos), 5 Lugo Lugo 27001",
    "addr:housenumber":"5",
    "addr:postcode":"27001",
    "addr:street":"Rua Clerigos Dos",
    "iso:country":"ES",
    "sg:address":"Rua Clerigos (dos), 5",
    "sg:city":"Lugo",
    "sg:classifiers":[
        {
            "category":"Arts & Performance",
            "subcategory":"Art Gallery",
            "type":"Entertainment"
        }
    ],
    "sg:phone":"+34 982 25 39 24",
    "sg:postcode":"27001",
    "sg:province":"Lugo",
    "sg:tags":[
        "arte",
        "de",
        "galer\u00cdas"
    ],
    "sg:website":"www.art-es.com",
    "wof:name":"Jose Luis Garcia Boente Y Otros C.b.",
    "wof:placetype":"venue"
},
  "geometry": {"coordinates":[-7.5568737984,43.0088424683],"type":"Point"}
}