{
  "type": "Feature",
  "properties": {
    "addr:full":"Calle de Bravo, 5 Medina Campo Valladolid 47400",
    "addr:housenumber":"5",
    "addr:postcode":"47400",
    "addr:street":"Calle De Bravo",
    "iso:country":"ES",
    "sg:address":"Calle de Bravo, 5",
    "sg:city":"Medina Campo",
    "sg:orig_category":"Zapatos (al Por Menor)",
    "sg:phone":"+34 983 80 22 18",
    "sg:postcode":"47400",
    "sg:province":"Valladolid",
    "wof:name":"Gonzalez Gago Asterio",
    "wof:placetype":"venue"
},
  "geometry": {"coordinates":[-4.9147462845,41.3077850342],"type":"Point"}
}