{
  "type": "Feature",
  "properties": {
    "addr:full":"Plaz Espa\u00d1a, S/n Valladolid Valladolid 47001",
    "addr:housenumber":"s / n",
    "addr:postcode":"47001",
    "addr:street":"Plaz Espan\u0303A",
    "iso:country":"ES",
    "sg:address":"Plaz Espa\u00d1a, S/n",
    "sg:city":"Valladolid",
    "sg:orig_category":"Aparcamientos (infraestructuras, Accesorios)",
    "sg:phone":"+34 983 29 96 60",
    "sg:postcode":"47001",
    "sg:province":"Valladolid",
    "wof:name":"Aplaes S.a.",
    "wof:placetype":"venue"
},
  "geometry": {"coordinates":[-4.7296929359,41.6505126953],"type":"Point"}
}