{
  "type": "Feature",
  "properties": {
    "iso:country":"ES",
    "sg:address":"Rua Santa Cristina, 16",
    "sg:city":"Pardavila",
    "sg:orig_category":"Caf\u00c9s, Bares, Cervecer\u00cdas",
    "sg:phone":"+34 986 27 82 83",
    "sg:postcode":"36214",
    "sg:province":"Pontevedra",
    "wof:name":"Frasquet Santos Maria Del Carmen",
    "wof:placetype":"venue"
},
  "geometry": {"coordinates":[-8.7059106827,42.2124443054],"type":"Point"}
}