{
  "type": "Feature",
  "properties": {
    "iso:country":"ES",
    "sg:address":"Calle de Carretera, S/n",
    "sg:city":"Mataporquera",
    "sg:orig_category":"Reparaciones Y Remolcado De Veh\u00cdculos",
    "sg:phone":"+34 942 77 03 19",
    "sg:postcode":"39410",
    "sg:province":"Cantabria",
    "wof:name":"Gutierrez Hidalgo Carlos",
    "wof:placetype":"venue"
},
  "geometry": {"coordinates":[-4.1625947952,42.874835968],"type":"Point"}
}