{
  "type": "Feature",
  "properties": {
    "iso:country":"ES",
    "sg:address":"Poli Talluntxe / Talluntze Industrialdea, S/n",
    "sg:city":"Noain",
    "sg:orig_category":"Fabricaci\u00d3n, Instalaci\u00d3n De Armarios",
    "sg:phone":"+34 948 31 65 06",
    "sg:postcode":"31110",
    "sg:province":"Navarra",
    "sg:website":"www.imor.es",
    "wof:name":"Armifren S.l.",
    "wof:placetype":"venue"
},
  "geometry": {"coordinates":[-1.5935460329,42.7209968567],"type":"Point"}
}