{
  "type": "Feature",
  "properties": {
    "addr:full":"Avgd Maria Jolonch (de), 2 Agramunt Lleida 25310",
    "addr:postcode":"25310",
    "iso:country":"ES",
    "sg:address":"Avgd Maria Jolonch (de), 2",
    "sg:city":"Agramunt",
    "sg:orig_category":"Molduras, Junquillos, Listones Y Molduras Perforadas",
    "sg:phone":"+34 973 39 06 02",
    "sg:postcode":"25310",
    "sg:province":"Lleida",
    "wof:name":"Carreras Roca Josep",
    "wof:placetype":"venue"
},
  "geometry": {"coordinates":[1.0976400375,41.7860717773],"type":"Point"}
}