{
  "type": "Feature",
  "properties": {
    "iso:country":"ES",
    "sg:address":"Calle de Tellagorri, 1",
    "sg:city":"Bilbao",
    "sg:orig_category":"Quincaller\u00cda (al Por Menor)",
    "sg:phone":"+34 944 42 31 58",
    "sg:postcode":"48012",
    "sg:province":"Vizcaya",
    "wof:name":"Rodriguez Murias Aurelio",
    "wof:placetype":"venue"
},
  "geometry": {"coordinates":[-2.9496920109,43.2569389343],"type":"Point"}
}