{
  "type": "Feature",
  "properties": {
    "addr:full":"Calle de Bocas Las, 12 Huelva Huelva 21001",
    "addr:housenumber":"12",
    "addr:postcode":"21001",
    "addr:street":"Calle De Bocas Las",
    "iso:country":"ES",
    "sg:address":"Calle de Bocas Las, 12",
    "sg:city":"Huelva",
    "sg:orig_category":"Asesor\u00cda Sobre Comunicaci\u00d3n De Empresas",
    "sg:phone":"+34 959 25 57 29",
    "sg:postcode":"21001",
    "sg:province":"Huelva",
    "sg:website":"www.asemaba.com",
    "wof:name":"Centro De Gestion De Empresas Asemaba S.l.",
    "wof:placetype":"venue"
},
  "geometry": {"coordinates":[-6.9540581703,37.2567367554],"type":"Point"}
}