{
  "type": "Feature",
  "properties": {
    "addr:full":"Mirallo De Arriba, S/n San Facundo Asturias 33875",
    "addr:housenumber":"s / n",
    "addr:postcode":"33875",
    "addr:street":"Mirallo;Arriba",
    "iso:country":"ES",
    "sg:address":"Mirallo De Arriba, S/n",
    "sg:city":"San Facundo",
    "sg:orig_category":"Chapa Y Pintura Veh\u00cdculos",
    "sg:phone":"+34 985 92 99 20",
    "sg:postcode":"33875",
    "sg:province":"Asturias",
    "wof:name":"Cornas Mora Jose",
    "wof:placetype":"venue"
},
  "geometry": {"coordinates":[-6.5462470055,43.2659797668],"type":"Point"}
}