{
  "type": "Feature",
  "properties": {
    "iso:country":"ES",
    "sg:address":"Av Carrilet, 237",
    "sg:city":"Hospitalet Llobregat",
    "sg:orig_category":"Agencias Y Agentes Comerciales, Representantes",
    "sg:phone":"+34 933 37 62 78",
    "sg:postcode":"08907",
    "sg:province":"Barcelona",
    "wof:name":"Comercial Wiblis Sl",
    "wof:placetype":"venue"
},
  "geometry": {"coordinates":[2.1026198864,41.3577919006],"type":"Point"}
}