{
  "type": "Feature",
  "properties": {
    "addr:full":"Amaya-amaia, 2 Iru\u00f1a Navarra 31002",
    "addr:housenumber":"2",
    "addr:postcode":"31002",
    "addr:street":"Amaya-Amaia",
    "iso:country":"ES",
    "sg:address":"Amaya-amaia, 2",
    "sg:city":"Iru\u00f1a",
    "sg:orig_category":"Cl\u00cdnicas Dentales",
    "sg:phone":"+34 948 22 58 54",
    "sg:postcode":"31002",
    "sg:province":"Navarra",
    "wof:name":"Duarte Fajardo Olga",
    "wof:placetype":"venue"
},
  "geometry": {"coordinates":[-1.6407630444,42.8155555725],"type":"Point"}
}