{
  "type": "Feature",
  "properties": {
    "addr:full":"Calle de Enmedio, 60 Castellon Castell\u00f3n 12001",
    "addr:housenumber":"60",
    "addr:postcode":"12001",
    "addr:street":"Calle De Enmedio",
    "iso:country":"ES",
    "sg:address":"Calle de Enmedio, 60",
    "sg:city":"Castellon",
    "sg:orig_category":"Asesor\u00cda Sobre Comunicaci\u00d3n De Empresas",
    "sg:phone":"+34 964 23 57 70",
    "sg:postcode":"12001",
    "sg:province":"Castell\u00f3n",
    "sg:website":"www.bmb.es",
    "wof:name":"B M B Gestion Documental S.l.",
    "wof:placetype":"venue"
},
  "geometry": {"coordinates":[-0.0386710018,39.9862747192],"type":"Point"}
}