{
  "type": "Feature",
  "properties": {
    "iso:country":"ES",
    "sg:address":"Calle de Francisco Pizarro, 47",
    "sg:city":"Almendralejo",
    "sg:orig_category":"Ropa Para Se\u00d1oras Y Caballeros (al Por Menor)",
    "sg:phone":"+34 924 66 63 37",
    "sg:postcode":"06200",
    "sg:province":"Badajoz",
    "wof:name":"Asuar Perez Isabel",
    "wof:placetype":"venue"
},
  "geometry": {"coordinates":[-6.4040932655,38.6826286316],"type":"Point"}
}