{
  "type": "Feature",
  "properties": {
    "addr:full":"Pase San Frantzisko Ibiltokia, 25 Tolosa Guip\u00f9zcoa 20400",
    "addr:housenumber":"25",
    "addr:postcode":"20400",
    "addr:street":"San Frantzisko Ibiltokia;Guipu\u0300Zcoa",
    "iso:country":"ES",
    "sg:address":"Pase San Frantzisko Ibiltokia, 25",
    "sg:city":"Tolosa",
    "sg:orig_category":"Carnicer\u00cdas, Carnicer\u00cdas",
    "sg:phone":"+34 943 65 20 47",
    "sg:postcode":"20400",
    "sg:province":"Guip\u00f9zcoa",
    "wof:name":"Leire Gorostiaga Iraola",
    "wof:placetype":"venue"
},
  "geometry": {"coordinates":[-2.0765988827,43.1351242065],"type":"Point"}
}