{
  "type": "Feature",
  "properties": {
    "addr:full":"Carrer de Granio, 1 Terrassa Barcelona 08224",
    "addr:housenumber":"1",
    "addr:postcode":"08224",
    "addr:street":"Carrer De Granio",
    "iso:country":"ES",
    "sg:address":"Carrer de Granio, 1",
    "sg:city":"Terrassa",
    "sg:orig_category":"Fabricaci\u00d3n, Venta De Cuadros, Accesorios Para Enmarcar",
    "sg:phone":"+34 937 89 20 20",
    "sg:postcode":"08224",
    "sg:province":"Barcelona",
    "wof:name":"Mir Celdran Francisco Javier",
    "wof:placetype":"venue"
},
  "geometry": {"coordinates":[2.0076179504,41.5629501343],"type":"Point"}
}