{
  "type": "Feature",
  "properties": {
    "iso:country":"ES",
    "sg:address":"Carrer de Baix Del Carme, 2",
    "sg:city":"Reus",
    "sg:orig_category":"Retoques De Vestidos",
    "sg:phone":"+34 977 31 96 48",
    "sg:postcode":"43205",
    "sg:province":"Tarragona",
    "wof:name":"Retocs Catalu\u00d1a S.l.",
    "wof:placetype":"venue"
},
  "geometry": {"coordinates":[1.107929945,41.1519889832],"type":"Point"}
}