{
  "type": "Feature",
  "properties": {
    "addr:full":"Calle de Atardecer, 13 Pozuelo De Alarcon Madrid 28223",
    "addr:housenumber":"13",
    "addr:postcode":"28223",
    "addr:street":"Calle De Atardecer",
    "iso:country":"ES",
    "sg:address":"Calle de Atardecer, 13",
    "sg:city":"Pozuelo De Alarcon",
    "sg:orig_category":"Impermeabilizantes",
    "sg:phone":"+34 913 51 72 84",
    "sg:postcode":"28223",
    "sg:province":"Madrid",
    "wof:name":"Ondaplac Iberica S.l",
    "wof:placetype":"venue"
},
  "geometry": {"coordinates":[-3.8122060299,40.4429893494],"type":"Point"}
}