{
  "type": "Feature",
  "properties": {
    "iso:country":"ES",
    "sg:address":"Las Meninas, 29",
    "sg:city":"San J. Aznalfarache",
    "sg:orig_category":"Bebidas",
    "sg:phone":"+34 954 76 20 70",
    "sg:postcode":"41920",
    "sg:province":"Sevilla",
    "wof:name":"Al Boustani Alboustani Ahmad Fawaz",
    "wof:placetype":"venue"
},
  "geometry": {"coordinates":[-6.0373015404,37.3660049438],"type":"Point"}
}