{
  "type": "Feature",
  "properties": {
    "iso:country":"ES",
    "sg:address":"Calle de Chicos (los), 15",
    "sg:city":"Ajalvir",
    "sg:orig_category":"Panader\u00cdas, Pasteler\u00cdas, Boller\u00cda Industriale (fabricaci\u00d3n, Al Por Mayor)",
    "sg:phone":"+34 918 84 46 16",
    "sg:postcode":"28864",
    "sg:province":"Madrid",
    "wof:name":"Bollyfres S.l.",
    "wof:placetype":"venue"
},
  "geometry": {"coordinates":[-3.4800190926,40.5092506409],"type":"Point"}
}