{
  "type": "Feature",
  "properties": {
    "addr:full":"Calle de Badajoz, 21 Sabatera Alicante 03725",
    "addr:housenumber":"21",
    "addr:postcode":"03725",
    "addr:street":"Calle De Badajoz;Alicante",
    "iso:country":"ES",
    "sg:address":"Calle de Badajoz, 21",
    "sg:city":"Sabatera",
    "sg:orig_category":"Servidores Y Editores De Bases De Datos",
    "sg:phone":"+34 966 49 06 87",
    "sg:postcode":"03725",
    "sg:province":"Alicante",
    "sg:website":"www.mmm-team.com",
    "wof:name":"Mmm-team S.l.",
    "wof:placetype":"venue"
},
  "geometry": {"coordinates":[-0.4810059965,38.3452033997],"type":"Point"}
}