{
  "type": "Feature",
  "properties": {
    "iso:country":"ES",
    "sg:address":"Calle de Leon Y Castillo, 4",
    "sg:city":"Ingenio",
    "sg:orig_category":"Molduras, Junquillos, Listones Y Molduras Perforadas",
    "sg:phone":"+34 928 78 26 92",
    "sg:postcode":"35250",
    "sg:province":"Las Palmas",
    "wof:name":"Rivera Tejera David",
    "wof:placetype":"venue"
},
  "geometry": {"coordinates":[-15.4372816086,27.9198226929],"type":"Point"}
}