{
  "type": "Feature",
  "properties": {
    "iso:country":"ES",
    "sg:address":"Calle de Okendo, 6",
    "sg:city":"Donostia-san Sebastian",
    "sg:orig_category":"Enfermeras: Consultas, Atenci\u00d3n A Domicilio",
    "sg:phone":"+34 943 42 77 17",
    "sg:postcode":"20004",
    "sg:province":"Guip\u00f9zcoa",
    "wof:name":"Ruiz Lopez De Bri\u00f1as Concepcion",
    "wof:placetype":"venue"
},
  "geometry": {"coordinates":[-1.9817579985,43.3222999573],"type":"Point"}
}