{
  "type": "Feature",
  "properties": {
    "iso:country":"ES",
    "sg:address":"Plaz Pedro Cornel, 10",
    "sg:city":"Almazora",
    "sg:orig_category":"Zapatos (al Por Menor)",
    "sg:phone":"+34 964 55 17 36",
    "sg:postcode":"12550",
    "sg:province":"Castell\u00f3n",
    "wof:name":"Agusti Llueca Carmen",
    "wof:placetype":"venue"
},
  "geometry": {"coordinates":[-0.0606637001,39.945274353],"type":"Point"}
}