{
  "type": "Feature",
  "properties": {
    "iso:country":"ES",
    "sg:address":"Calle de Reyes Catolicos, 12",
    "sg:city":"Montijo",
    "sg:orig_category":"Reposter\u00cdas",
    "sg:phone":"+34 924 45 48 77",
    "sg:postcode":"06480",
    "sg:province":"Badajoz",
    "wof:name":"Panaderia Coto E Hijos S.l.",
    "wof:placetype":"venue"
},
  "geometry": {"coordinates":[-6.6175889969,38.9137611389],"type":"Point"}
}