{
  "type": "Feature",
  "properties": {
    "addr:full":"Calle de Abolengo, 23 Madrid Madrid 28025",
    "addr:housenumber":"23",
    "addr:postcode":"madrid;28025",
    "addr:street":"Calle De Abolengo",
    "iso:country":"ES",
    "sg:address":"Calle de Abolengo, 23",
    "sg:city":"Madrid",
    "sg:orig_category":"Promotores Constructores",
    "sg:phone":"+34 914 61 20 50",
    "sg:postcode":"28025",
    "sg:province":"Madrid",
    "wof:name":"Zalm Octogo S.l",
    "wof:placetype":"venue"
},
  "geometry": {"coordinates":[-3.7375290394,40.3889503479],"type":"Point"}
}