{
  "type": "Feature",
  "properties": {
    "addr:full":"Carrer de Eduard Toldra, S/n Sant Quirze Jardi Barcelona 08192",
    "addr:housenumber":"s",
    "addr:postcode":"08192",
    "addr:street":"Carrer De Eduard Toldra;/ N",
    "iso:country":"ES",
    "sg:address":"Carrer de Eduard Toldra, S/n",
    "sg:city":"Sant Quirze Jardi",
    "sg:orig_category":"Molduras, Junquillos, Listones Y Molduras Perforadas",
    "sg:phone":"+34 937 21 01 68",
    "sg:postcode":"08192",
    "sg:province":"Barcelona",
    "wof:name":"Bea Soriano Carme",
    "wof:placetype":"venue"
},
  "geometry": {"coordinates":[2.0749499798,41.5331497192],"type":"Point"}
}