{
  "type": "Feature",
  "properties": {
    "iso:country":"ES",
    "sg:address":"Avda Cardenal Benlloch, 36",
    "sg:city":"Valencia",
    "sg:orig_category":"Cajas Y Embalajes De Pl\u00c1stico",
    "sg:phone":"+34 963 62 41 18",
    "sg:postcode":"46021",
    "sg:province":"Valencia",
    "wof:name":"Perpi\u00f1a Almela Ismael",
    "wof:placetype":"venue"
},
  "geometry": {"coordinates":[-0.3555490077,39.4689331055],"type":"Point"}
}