{
  "type": "Feature",
  "properties": {
    "addr:full":"Calle de Pedro Pidal Arroyo, 2 Villaviciosa Asturias 33300",
    "addr:housenumber":"2",
    "addr:postcode":"33300",
    "addr:street":"Calle De Pedro Pidal Arroyo",
    "iso:country":"ES",
    "sg:address":"Calle de Pedro Pidal Arroyo, 2",
    "sg:city":"Villaviciosa",
    "sg:orig_category":"Comercio, Reparaci\u00d3n De Bicicletas, De Motocicletas, De Accesorios",
    "sg:phone":"+34 985 89 00 21",
    "sg:postcode":"33300",
    "sg:province":"Asturias",
    "wof:name":"Cueto Solares Juan",
    "wof:placetype":"venue"
},
  "geometry": {"coordinates":[-5.4385499954,43.479385376],"type":"Point"}
}