{
  "type": "Feature",
  "properties": {
    "iso:country":"ES",
    "sg:address":"Plaz Tarragona, 4",
    "sg:city":"Melilla",
    "sg:orig_category":"Alimentaci\u00d3n General (al Por Mayor)",
    "sg:phone":"+34 952 68 04 34",
    "sg:postcode":"52001",
    "sg:province":"Melilla",
    "wof:name":"Diaz Lopez Pedro",
    "wof:placetype":"venue"
},
  "geometry": {"coordinates":[-2.9512500763,35.3091583252],"type":"Point"}
}