{
  "type": "Feature",
  "properties": {
    "iso:country":"ES",
    "sg:address":"Calle de Juan Milla, 6",
    "sg:city":"Petrer",
    "sg:orig_category":"Peluquer\u00cdas, Peluquer\u00cda Mixta",
    "sg:phone":"+34 966 95 29 61",
    "sg:postcode":"03610",
    "sg:province":"Alicante",
    "sg:website":"www.llongueras.com",
    "wof:name":"\u00d1iguez Peluqueros S.l.",
    "wof:placetype":"venue"
},
  "geometry": {"coordinates":[-0.7844499946,38.4828491211],"type":"Point"}
}