{
  "type": "Feature",
  "properties": {
    "addr:full":"Psaj Aguila Del, S/n Arroyo De La Miel-benalmadena Costa M\u00e1laga 29630",
    "addr:housenumber":"/ n",
    "addr:postcode":"29630",
    "addr:street":"S;Ma\u0301Laga",
    "iso:country":"ES",
    "sg:address":"Psaj Aguila Del, S/n",
    "sg:city":"Arroyo De La Miel-benalmadena Costa",
    "sg:orig_category":"Agencias De Viajes",
    "sg:phone":"+34 952 57 75 95",
    "sg:postcode":"29630",
    "sg:province":"M\u00e1laga",
    "sg:website":"www.noemiviajes.com",
    "wof:name":"Noemi Viajes S.l.",
    "wof:placetype":"venue"
},
  "geometry": {"coordinates":[-4.5382881165,36.581993103],"type":"Point"}
}