{
  "type": "Feature",
  "properties": {
    "iso:country":"ES",
    "sg:address":"Tragove, S/n",
    "sg:city":"Tragove",
    "sg:orig_category":"Pescader\u00cdas (al Por Mayor)",
    "sg:phone":"+34 986 52 00 00",
    "sg:postcode":"36639",
    "sg:province":"Pontevedra",
    "sg:website":"www.mariscosdaporta.com",
    "wof:name":"Mariscos Daporta S.l.",
    "wof:placetype":"venue"
},
  "geometry": {"coordinates":[-8.8220100403,42.4838981628],"type":"Point"}
}