{
  "type": "Feature",
  "properties": {
    "iso:country":"ES",
    "sg:address":"Calle de Fragua, S/n",
    "sg:city":"Huermeces Cerro",
    "sg:orig_category":"Centros Empresariales",
    "sg:phone":"+34 949 39 77 73",
    "sg:postcode":"19295",
    "sg:province":"Guadalajara",
    "wof:name":"Cezon Perez Maria Esther",
    "wof:placetype":"venue"
},
  "geometry": {"coordinates":[-2.7958459854,41.0530815125],"type":"Point"}
}