{
  "type": "Feature",
  "properties": {
    "addr:full":"Pque Ruperto Chapi, 14 Villena Alicante 03400",
    "addr:housenumber":"14",
    "addr:postcode":"03400",
    "addr:street":"Chapi",
    "iso:country":"ES",
    "sg:address":"Pque Ruperto Chapi, 14",
    "sg:city":"Villena",
    "sg:orig_category":"Caf\u00c9s, Bares, Cervecer\u00cdas",
    "sg:phone":"+34 965 80 71 91",
    "sg:postcode":"03400",
    "sg:province":"Alicante",
    "wof:name":"Haiping  Liu",
    "wof:placetype":"venue"
},
  "geometry": {"coordinates":[-0.8657540083,38.6356544495],"type":"Point"}
}