{
  "type": "Feature",
  "properties": {
    "iso:country":"ES",
    "sg:address":"Calle de Mariano Sainz, 5",
    "sg:city":"San Lorenzo De El Escorial",
    "sg:orig_category":"Papeler\u00cdas: Art\u00cdculos (al Por Mayor)",
    "sg:phone":"+34 918 90 61 47",
    "sg:postcode":"28200",
    "sg:province":"Madrid",
    "wof:name":"Mitsubishi Pencil Espa\u00d1a S.a.",
    "wof:placetype":"venue"
},
  "geometry": {"coordinates":[-4.1430120468,40.5937232971],"type":"Point"}
}