{
  "type": "Feature",
  "properties": {
    "addr:full":"Calle de Juan Ramon Jimenez, S/n Gilena Sevilla 41565",
    "addr:postcode":"41565",
    "addr:street":"Calle De Juan Ramon Jimenez S / N",
    "iso:country":"ES",
    "sg:address":"Calle de Juan Ramon Jimenez, S/n",
    "sg:city":"Gilena",
    "sg:orig_category":"Herramientas Manuales (fabricaci\u00d3n, Al Por Mayor)",
    "sg:phone":"+34 955 82 63 85",
    "sg:postcode":"41565",
    "sg:province":"Sevilla",
    "wof:name":"Electrolux Construction Products Espa\u00f1a S.a.",
    "wof:placetype":"venue"
},
  "geometry": {"coordinates":[-4.9105381966,37.2544898987],"type":"Point"}
}