{
  "type": "Feature",
  "properties": {
    "addr:full":"Carrer de Penedes, 24 Prat Llobregat Barcelona 08820",
    "addr:housenumber":"24",
    "addr:postcode":"08820",
    "addr:street":"Carrer De Penedes;Llobregat",
    "iso:country":"ES",
    "sg:address":"Carrer de Penedes, 24",
    "sg:city":"Prat Llobregat",
    "sg:orig_category":"Materias Pl\u00c1sticas: Material, Equipos Industriales",
    "sg:phone":"+34 933 70 41 56",
    "sg:postcode":"08820",
    "sg:province":"Barcelona",
    "sg:website":"www.alimatic.com",
    "wof:name":"Alimatic S.l.",
    "wof:placetype":"venue"
},
  "geometry": {"coordinates":[2.0896427631,41.3287162781],"type":"Point"}
}