{
  "type": "Feature",
  "properties": {
    "iso:country":"ES",
    "sg:address":"Carrer de Tuset, 18",
    "sg:city":"Barcelona",
    "sg:orig_category":"M\u00c9dicos: Estomatolog\u00cda",
    "sg:phone":"+34 934 16 15 30",
    "sg:postcode":"08006",
    "sg:province":"Barcelona",
    "wof:name":"Asociacion Dental Espa\u00f1ola S.a.",
    "wof:placetype":"venue"
},
  "geometry": {"coordinates":[2.1521801949,41.3958091736],"type":"Point"}
}