{
  "type": "Feature",
  "properties": {
    "addr:full":"Txonta Kalea, 26 Eibar Guip\u00f9zcoa 20600",
    "addr:housenumber":"26",
    "addr:postcode":"20600",
    "addr:street":"Txonta Kalea;Guipu\u0300Zcoa",
    "iso:country":"ES",
    "sg:address":"Txonta Kalea, 26",
    "sg:city":"Eibar",
    "sg:orig_category":"Rectificaci\u00d3n, Mecanizado, Fresado",
    "sg:phone":"+34 943 12 70 17",
    "sg:postcode":"20600",
    "sg:province":"Guip\u00f9zcoa",
    "wof:name":"Cestafe Del Campo Jose Antonio",
    "wof:placetype":"venue"
},
  "geometry": {"coordinates":[-2.4623970985,43.1841125488],"type":"Point"}
}