{
  "type": "Feature",
  "properties": {
    "addr:full":"Carr Lluis Companys, 31 Lleida Lleida 25003",
    "addr:housenumber":"31",
    "addr:postcode":"25003",
    "addr:street":"Carr Lluis Companys",
    "iso:country":"ES",
    "sg:address":"Carr Lluis Companys, 31",
    "sg:city":"Lleida",
    "sg:orig_category":"Cl\u00cdnicas Dentales",
    "sg:phone":"+34 973 28 28 17",
    "sg:postcode":"25003",
    "sg:province":"Lleida",
    "sg:website":"www.paginasamarillas.es",
    "wof:name":"Clinica Dental Porta Corretger S.c.p.",
    "wof:placetype":"venue"
},
  "geometry": {"coordinates":[0.6150929928,41.6117706299],"type":"Point"}
}