{
  "type": "Feature",
  "properties": {
    "iso:country":"ES",
    "sg:address":"Ctra Terrassa, 210",
    "sg:city":"Rubi",
    "sg:orig_category":"Electricidad: Equipos Industriales, Componentes (fabricaci\u00d3n)",
    "sg:phone":"+34 935 87 21 37",
    "sg:postcode":"08191",
    "sg:province":"Barcelona",
    "wof:name":"Circuitos Impresos Profesionales S.a.",
    "wof:placetype":"venue"
},
  "geometry": {"coordinates":[2.0362501144,41.5052680969],"type":"Point"}
}