{
  "type": "Feature",
  "properties": {
    "iso:country":"ES",
    "sg:address":"Avda Oviedo, 77",
    "sg:city":"Torres",
    "sg:orig_category":"Molduras, Junquillos, Listones Y Molduras Perforadas",
    "sg:phone":"+34 942 88 18 67",
    "sg:postcode":"39300",
    "sg:province":"Cantabria",
    "wof:name":"Sierra Izaguirre Jose",
    "wof:placetype":"venue"
},
  "geometry": {"coordinates":[-4.0648288727,43.3539390564],"type":"Point"}
}