{
  "type": "Feature",
  "properties": {
    "addr:full":"Calle de Bolivar Simon, 3 Bilbao Vizcaya 48010",
    "addr:housenumber":"3",
    "addr:postcode":"48010",
    "addr:street":"Calle De Bolivar Simon",
    "iso:country":"ES",
    "sg:address":"Calle de Bolivar Simon, 3",
    "sg:city":"Bilbao",
    "sg:orig_category":"Lencer\u00cda Femenina, Corseter\u00cda, Trajes De Ba\u00d1o (al Por Menor)",
    "sg:phone":"+34 944 43 20 71",
    "sg:postcode":"48010",
    "sg:province":"Vizcaya",
    "wof:name":"Martinez Fuentes Marta",
    "wof:placetype":"venue"
},
  "geometry": {"coordinates":[-2.9405939579,43.2597427368],"type":"Point"}
}