{
  "type": "Feature",
  "properties": {
    "addr:full":"Calle de Alcalde Asunsolo, 2 Coru\u00d1a La Coru\u00f1a 15007",
    "addr:housenumber":"2",
    "addr:postcode":"15007",
    "addr:street":"Calle De Alcalde Asunsolo;La Corun\u0303A",
    "iso:country":"ES",
    "sg:address":"Calle de Alcalde Asunsolo, 2",
    "sg:city":"Coru\u00d1a",
    "sg:orig_category":"Alumbrados",
    "sg:phone":"+34 981 23 24 16",
    "sg:postcode":"15007",
    "sg:province":"La Coru\u00f1a",
    "sg:website":"www.eiroadecoracion.com",
    "wof:name":"Consuelo Y Jose Manuel Eiroa Cotelo S.c.",
    "wof:placetype":"venue"
},
  "geometry": {"coordinates":[-8.4076023102,43.3550033569],"type":"Point"}
}