{
  "type": "Feature",
  "properties": {
    "addr:full":"Calle de Escoriales (los), 4 Guadarrama Madrid 28440",
    "addr:housenumber":"4",
    "addr:postcode":"28440",
    "addr:street":"Calle De Escoriales Los",
    "iso:country":"ES",
    "sg:address":"Calle de Escoriales (los), 4",
    "sg:city":"Guadarrama",
    "sg:orig_category":"Alquiler De Muebles",
    "sg:phone":"+34 918 54 75 49",
    "sg:postcode":"28440",
    "sg:province":"Madrid",
    "wof:name":"Ortopedias Y Ayuda Guadarrama C.b",
    "wof:placetype":"venue"
},
  "geometry": {"coordinates":[-4.0868201256,40.6701011658],"type":"Point"}
}