{
  "type": "Feature",
  "properties": {
    "iso:country":"ES",
    "sg:address":"Ctra Segovia, 59",
    "sg:city":"Sanchonu\u00d1o",
    "sg:orig_category":"Contenedores (mercanc\u00cdas)",
    "sg:phone":"+34 921 16 03 96",
    "sg:postcode":"40297",
    "sg:province":"Segovia",
    "wof:name":"Gomez Miguel Melchor",
    "wof:placetype":"venue"
},
  "geometry": {"coordinates":[-4.3066282272,41.3224334717],"type":"Point"}
}