{
  "type": "Feature",
  "properties": {
    "addr:full":"Carrer de Covadonga (de), 10 Tarragona Tarragona 43005",
    "addr:housenumber":"10",
    "addr:postcode":"43005",
    "addr:street":"Carrer De Covadonga De",
    "iso:country":"ES",
    "sg:address":"Carrer de Covadonga (de), 10",
    "sg:city":"Tarragona",
    "sg:orig_category":"Molduras, Junquillos, Listones Y Molduras Perforadas",
    "sg:phone":"+34 977 21 60 53",
    "sg:postcode":"43005",
    "sg:province":"Tarragona",
    "wof:name":"Ribas Llaurado Montserrat",
    "wof:placetype":"venue"
},
  "geometry": {"coordinates":[1.2420740128,41.1229972839],"type":"Point"}
}