{
  "type": "Feature",
  "properties": {
    "iso:country":"ES",
    "sg:address":"Calle de Hernandez Caballero (sjm), 18",
    "sg:city":"San Juan De Mozarrifar",
    "sg:orig_category":"Ense\u00d1anza, Formaci\u00d3n Profesional: Aprendizaje",
    "sg:phone":"+34 976 58 74 86",
    "sg:postcode":"50820",
    "sg:province":"Zaragoza",
    "wof:name":"Ayuntamiento De Zaragoza",
    "wof:placetype":"venue"
},
  "geometry": {"coordinates":[-0.8407598138,41.7179450989],"type":"Point"}
}