{
  "type": "Feature",
  "properties": {
    "iso:country":"ES",
    "sg:address":"Carr Exercits Espanyols, 2",
    "sg:city":"Alfas Pi",
    "sg:orig_category":"Inmobiliaria (agencias)",
    "sg:phone":"+34 965 88 76 58",
    "sg:postcode":"03580",
    "sg:province":"Alicante",
    "wof:name":"Prince Villas S.l.",
    "wof:placetype":"venue"
},
  "geometry": {"coordinates":[-0.1002039984,38.5765342712],"type":"Point"}
}