{
  "type": "Feature",
  "properties": {
    "addr:full":"Calle de Kalebarren, 2 Soraluze-placencia Armas Guip\u00f9zcoa 20590",
    "addr:housenumber":"2",
    "addr:postcode":"20590",
    "addr:street":"Calle De Kalebarren;Armas Guipu\u0300Zcoa",
    "iso:country":"ES",
    "sg:address":"Calle de Kalebarren, 2",
    "sg:city":"Soraluze-placencia Armas",
    "sg:orig_category":"Iglesia Cat\u00d3lica",
    "sg:phone":"+34 943 75 13 70",
    "sg:postcode":"20590",
    "sg:province":"Guip\u00f9zcoa",
    "wof:name":"Parroquia Santa Maria La Real",
    "wof:placetype":"venue"
},
  "geometry": {"coordinates":[-2.4135439396,43.1750526428],"type":"Point"}
}