{
  "type": "Feature",
  "properties": {
    "addr:full":"Calle de General Oraa, 48 Madrid Madrid 28006",
    "addr:housenumber":"48",
    "addr:postcode":"madrid;28006",
    "addr:street":"Calle De General Oraa",
    "iso:country":"ES",
    "sg:address":"Calle de General Oraa, 48",
    "sg:city":"Madrid",
    "sg:orig_category":"Alumbrados",
    "sg:phone":"+34 915 62 18 28",
    "sg:postcode":"28006",
    "sg:province":"Madrid",
    "sg:website":"www.ideasluz.com",
    "wof:name":"Ideas Luz S.l.",
    "wof:placetype":"venue"
},
  "geometry": {"coordinates":[-3.6808300018,40.4359016418],"type":"Point"}
}