{
  "type": "Feature",
  "properties": {
    "addr:full":"Barr Santa Barbara, S/n Puente San Miguel Cantabria 39530",
    "addr:housenumber":"/ n",
    "addr:postcode":"39530",
    "addr:street":"Santa Barbara S",
    "iso:country":"ES",
    "sg:address":"Barr Santa Barbara, S/n",
    "sg:city":"Puente San Miguel",
    "sg:orig_category":"Neum\u00c1ticos (fabricaci\u00d3n, Al Por Mayor)",
    "sg:phone":"+34 942 88 39 38",
    "sg:postcode":"39530",
    "sg:province":"Cantabria",
    "wof:name":"Bridgestone Hispania S.a.",
    "wof:placetype":"venue"
},
  "geometry": {"coordinates":[-4.0821290016,43.357421875],"type":"Point"}
}