{
  "type": "Feature",
  "properties": {
    "addr:full":"Verge Del Remei, 17 Sta. Oliva Tarragona 43710",
    "addr:housenumber":"17",
    "addr:postcode":"43710",
    "addr:street":"Sta. Oliva",
    "iso:country":"ES",
    "sg:address":"Verge Del Remei, 17",
    "sg:city":"Sta. Oliva",
    "sg:orig_category":"Caf\u00c9s, Bares, Cervecer\u00cdas",
    "sg:phone":"+34 977 67 95 43",
    "sg:postcode":"43710",
    "sg:province":"Tarragona",
    "wof:name":"Romero Cepeda Maria Pilar",
    "wof:placetype":"venue"
},
  "geometry": {"coordinates":[1.5496449471,41.2515335083],"type":"Point"}
}