{
  "type": "Feature",
  "properties": {
    "iso:country":"ES",
    "sg:address":"Carrer de Vic (de), 2",
    "sg:city":"Vila-seca",
    "sg:orig_category":"Molduras, Junquillos, Listones Y Molduras Perforadas",
    "sg:phone":"+34 977 39 32 32",
    "sg:postcode":"43480",
    "sg:province":"Tarragona",
    "wof:name":"Gea Garcia Amador",
    "wof:placetype":"venue"
},
  "geometry": {"coordinates":[1.1489210129,41.1087303162],"type":"Point"}
}