{
  "type": "Feature",
  "properties": {
    "addr:full":"Carr Raval, 1 Campdevanol Girona 17530",
    "addr:housenumber":"1",
    "addr:postcode":"17530",
    "addr:street":"Carr Raval",
    "iso:country":"ES",
    "sg:address":"Carr Raval, 1",
    "sg:city":"Campdevanol",
    "sg:orig_category":"Inform\u00c1tica (estudios, Servicios, Asesor\u00cda, Formaci\u00d3n)",
    "sg:phone":"+34 972 73 02 51",
    "sg:postcode":"17530",
    "sg:province":"Girona",
    "wof:name":"Mapfre Servicios De Informatica",
    "wof:placetype":"venue"
},
  "geometry": {"coordinates":[2.1704668999,42.2252960205],"type":"Point"}
}