{
  "type": "Feature",
  "properties": {
    "iso:country":"ES",
    "sg:address":"Calle de Arcangeles, 49",
    "sg:city":"Malaga",
    "sg:orig_category":"Abogados",
    "sg:phone":"+34 952 20 29 85",
    "sg:postcode":"29018",
    "sg:province":"M\u00e1laga",
    "wof:name":"Rodriguez Vibora Soledad",
    "wof:placetype":"venue"
},
  "geometry": {"coordinates":[-4.3787145615,36.7280197144],"type":"Point"}
}