{
  "type": "Feature",
  "properties": {
    "iso:country":"ES",
    "sg:address":"Cm\u00d1o Aviseiro, 16",
    "sg:city":"Aviseiro",
    "sg:orig_category":"Contenedores (mercanc\u00cdas)",
    "sg:phone":"+34 986 33 07 38",
    "sg:postcode":"36400",
    "sg:province":"Pontevedra",
    "wof:name":"Perez Rodriguez Antonio Ismael",
    "wof:placetype":"venue"
},
  "geometry": {"coordinates":[-8.6179990768,42.1610298157],"type":"Point"}
}