{
  "type": "Feature",
  "properties": {
    "addr:full":"Bista-eder Kalea, 1 Eibar Guip\u00f9zcoa 20600",
    "addr:housenumber":"1",
    "addr:postcode":"20600",
    "addr:street":"Bista-Eder Kalea;Guipu\u0300Zcoa",
    "iso:country":"ES",
    "sg:address":"Bista-eder Kalea, 1",
    "sg:city":"Eibar",
    "sg:orig_category":"Asociaciones, Organismos Culturales Y Socioeducativos",
    "sg:phone":"+34 943 20 71 22",
    "sg:postcode":"20600",
    "sg:province":"Guip\u00f9zcoa",
    "wof:name":"Sociedad Zazpi Gazte",
    "wof:placetype":"venue"
},
  "geometry": {"coordinates":[-2.4710009098,43.1845474243],"type":"Point"}
}