{
  "type": "Feature",
  "properties": {
    "iso:country":"ES",
    "sg:address":"Calle de Mirlo, 13",
    "sg:city":"Granada",
    "sg:orig_category":"Suministros Para Hoteles",
    "sg:phone":"+34 958 20 65 69",
    "sg:postcode":"18014",
    "sg:province":"Granada",
    "wof:name":"Salinero Diestro Agustin",
    "wof:placetype":"venue"
},
  "geometry": {"coordinates":[-3.6111340523,37.1861038208],"type":"Point"}
}