{
  "type": "Feature",
  "properties": {
    "addr:full":"Calle de Federico Balart, 1 Mula Murcia 30170",
    "addr:housenumber":"1",
    "addr:postcode":"30170",
    "addr:street":"Calle De Federico Balart",
    "iso:country":"ES",
    "sg:address":"Calle de Federico Balart, 1",
    "sg:city":"Mula",
    "sg:orig_category":"Sindicatos De Trabajadores",
    "sg:phone":"+34 968 66 15 95",
    "sg:postcode":"30170",
    "sg:province":"Murcia",
    "wof:name":"Cc.oo.region De Murcia",
    "wof:placetype":"venue"
},
  "geometry": {"coordinates":[-1.4925379753,38.040058136],"type":"Point"}
}