{
  "type": "Feature",
  "properties": {
    "addr:full":"Carrer de Estacio, 78 Caldes Montbui Barcelona 08140",
    "addr:housenumber":"78",
    "addr:postcode":"08140",
    "addr:street":"Carrer De Estacio;Montbui Barcelona",
    "iso:country":"ES",
    "sg:address":"Carrer de Estacio, 78",
    "sg:city":"Caldes Montbui",
    "sg:orig_category":"Inform\u00c1tica, Ofim\u00c1tica (estudios, Asesor\u00cda, Ingenier\u00cda, Formaci\u00d3n)",
    "sg:phone":"+34 938 62 64 63",
    "sg:postcode":"08140",
    "sg:province":"Barcelona",
    "wof:name":"Serveis Informatics I Telecomunicacions Del Valles S.l.",
    "wof:placetype":"venue"
},
  "geometry": {"coordinates":[2.1707139015,41.6313934326],"type":"Point"}
}