{
  "type": "Feature",
  "properties": {
    "iso:country":"ES",
    "sg:address":"Calle de Jenaro Oraa, 1",
    "sg:city":"Santurtzi",
    "sg:orig_category":"Confiter\u00cda, Galletas Y Pastas, Chocolater\u00cda (al Por Mayor)",
    "sg:phone":"+34 944 62 62 31",
    "sg:postcode":"48980",
    "sg:province":"Vizcaya",
    "wof:name":"Maria Elena Rodriguez Mancebo",
    "wof:placetype":"venue"
},
  "geometry": {"coordinates":[-3.0328741074,43.3282661438],"type":"Point"}
}