{
  "type": "Feature",
  "properties": {
    "addr:full":"Ctra Jaen, 6 Hellin Albacete 02400",
    "addr:housenumber":"6",
    "addr:postcode":"02400",
    "addr:street":"Ctra Jaen",
    "iso:country":"ES",
    "sg:address":"Ctra Jaen, 6",
    "sg:city":"Hellin",
    "sg:orig_category":"Fabricaci\u00d3n De Su\u00c9ters Y Chalecos De Punto",
    "sg:phone":"+34 967 30 48 46",
    "sg:postcode":"02400",
    "sg:province":"Albacete",
    "wof:name":"Asfalto Hellin S.l.",
    "wof:placetype":"venue"
},
  "geometry": {"coordinates":[-1.7045704126,38.50756073],"type":"Point"}
}