{
  "type": "Feature",
  "properties": {
    "addr:full":"Calle de Argumosa, 30 Madrid Madrid 28012",
    "addr:housenumber":"30",
    "addr:postcode":"madrid;28012",
    "addr:street":"Calle De Argumosa",
    "iso:country":"ES",
    "sg:address":"Calle de Argumosa, 30",
    "sg:city":"Madrid",
    "sg:orig_category":"Farmacias",
    "sg:phone":"+34 915 39 72 42",
    "sg:postcode":"28012",
    "sg:province":"Madrid",
    "wof:name":"Lopez Ormazabal Victoria Eugenia",
    "wof:placetype":"venue"
},
  "geometry": {"coordinates":[-3.6959822178,40.4073524475],"type":"Point"}
}