{
  "type": "Feature",
  "properties": {
    "addr:full":"Carrer de Pedraforca, 116 Hospitalet Llobregat Barcelona 08905",
    "addr:housenumber":"116",
    "addr:postcode":"08905",
    "addr:street":"Carrer De Pedraforca",
    "iso:country":"ES",
    "sg:address":"Carrer de Pedraforca, 116",
    "sg:city":"Hospitalet Llobregat",
    "sg:orig_category":"Mec\u00c1nico Del Autom\u00d3vil",
    "sg:phone":"+34 934 37 38 54",
    "sg:postcode":"08905",
    "sg:province":"Barcelona",
    "wof:name":"Gomez Calvete Jose",
    "wof:placetype":"venue"
},
  "geometry": {"coordinates":[2.1074531078,41.3709182739],"type":"Point"}
}