{
  "type": "Feature",
  "properties": {
    "addr:full":"Co Algarrada, 11 Calahorra La Rioja 26500",
    "addr:housenumber":"11",
    "addr:postcode":"26500",
    "addr:street":"Algarrada",
    "iso:country":"ES",
    "sg:address":"Co Algarrada, 11",
    "sg:city":"Calahorra",
    "sg:orig_category":"Mec\u00c1nico Del Autom\u00d3vil",
    "sg:phone":"+34 941 14 75 27",
    "sg:postcode":"26500",
    "sg:province":"La Rioja",
    "wof:name":"Herce Grijalba Jose Antonio",
    "wof:placetype":"venue"
},
  "geometry": {"coordinates":[-1.9533619881,42.3119087219],"type":"Point"}
}