{
  "type": "Feature",
  "properties": {
    "addr:full":"Avda Lugo, 14 Melide La Coru\u00f1a 15800",
    "addr:housenumber":"14",
    "addr:postcode":"15800",
    "addr:street":"Avda Lugo;La Corun\u0303A",
    "iso:country":"ES",
    "sg:address":"Avda Lugo, 14",
    "sg:city":"Melide",
    "sg:orig_category":"Comercio, Reparaci\u00d3n De Bicicletas, De Motocicletas, De Accesorios",
    "sg:phone":"+34 981 50 52 03",
    "sg:postcode":"15800",
    "sg:province":"La Coru\u00f1a",
    "wof:name":"Rua Vazquez Isidro",
    "wof:placetype":"venue"
},
  "geometry": {"coordinates":[-8.011177063,42.913356781],"type":"Point"}
}