{
  "type": "Feature",
  "properties": {
    "addr:full":"Ctra Galapagar (de), S/n Estacion Madrid 28250",
    "addr:postcode":"28250",
    "addr:street":"Ctra Galapagar De S / N Estacion",
    "iso:country":"ES",
    "sg:address":"Ctra Galapagar (de), S/n",
    "sg:city":"Estacion",
    "sg:classifiers":[
        {
            "category":"Personal",
            "subcategory":"Barber",
            "type":"Services"
        }
    ],
    "sg:phone":"+34 918 59 08 15",
    "sg:postcode":"28250",
    "sg:province":"Madrid",
    "sg:tags":[
        "caballeros",
        "de",
        "peluqueros"
    ],
    "wof:name":"Gracia Vicente Manuel",
    "wof:placetype":"venue"
},
  "geometry": {"coordinates":[-3.7003455162,40.4166908264],"type":"Point"}
}