{
  "type": "Feature",
  "properties": {
    "iso:country":"ES",
    "sg:address":"Calle de Trake Kalea, 1",
    "sg:city":"Bermeo",
    "sg:orig_category":"Laboratorios Y Trabajos De Fotograf\u00cda, V\u00cddeo Y Cine",
    "sg:phone":"+34 946 88 25 75",
    "sg:postcode":"48370",
    "sg:province":"Vizcaya",
    "wof:name":"Bonilla Gil Victor Adolfo",
    "wof:placetype":"venue"
},
  "geometry": {"coordinates":[-2.7251009941,43.41929245],"type":"Point"}
}