{
  "type": "Feature",
  "properties": {
    "iso:country":"ES",
    "sg:address":"Calle de Fernando Miranda, 5",
    "sg:city":"Ponferrada",
    "sg:orig_category":"Ingenier\u00cda, Centros De Estudios (diversos)",
    "sg:phone":"+34 987 41 62 39",
    "sg:postcode":"24400",
    "sg:province":"Le\u00f3n",
    "wof:name":"Ingenor Bierzo S.l",
    "wof:placetype":"venue"
},
  "geometry": {"coordinates":[-6.6015782356,42.5470352173],"type":"Point"}
}