{
  "type": "Feature",
  "properties": {
    "iso:country":"ES",
    "sg:address":"Calle de Karmelo, 4",
    "sg:city":"Bilbao",
    "sg:orig_category":"Inmobiliaria (agencias)",
    "sg:phone":"+34 944 33 70 91",
    "sg:postcode":"48004",
    "sg:province":"Vizcaya",
    "wof:name":"Gestion Inmobiliaria Alegre Cimas, S.l.",
    "wof:placetype":"venue"
},
  "geometry": {"coordinates":[-2.9153790474,43.2534866333],"type":"Point"}
}