{
  "type": "Feature",
  "properties": {
    "addr:full":"Carrer de Vint, 30 Bonavista Tarragona 43100",
    "addr:housenumber":"30",
    "addr:postcode":"43100",
    "addr:street":"Carrer De Vint",
    "iso:country":"ES",
    "sg:address":"Carrer de Vint, 30",
    "sg:city":"Bonavista",
    "sg:orig_category":"Muebles Y Accesorios Para Cocinas Y Cuartos De Ba\u00d1o (al Por Menor)",
    "sg:phone":"+34 977 54 97 31",
    "sg:postcode":"43100",
    "sg:province":"Tarragona",
    "wof:name":"Eurocuin S.l.",
    "wof:placetype":"venue"
},
  "geometry": {"coordinates":[1.1939769983,41.1177787781],"type":"Point"}
}