{
  "type": "Feature",
  "properties": {
    "iso:country":"ES",
    "sg:address":"Avgd Pius Xii, 17",
    "sg:city":"Lleida",
    "sg:orig_category":"Inmobiliaria (agencias)",
    "sg:phone":"+34 973 28 12 33",
    "sg:postcode":"25003",
    "sg:province":"Lleida",
    "wof:name":"Via Fincas Ponent S.l.",
    "wof:placetype":"venue"
},
  "geometry": {"coordinates":[0.6146100163,41.6142807007],"type":"Point"}
}