{
  "type": "Feature",
  "properties": {
    "iso:country":"ES",
    "sg:address":"Elizgibela, S/n",
    "sg:city":"Burlada",
    "sg:orig_category":"Ense\u00d1anza, Formaci\u00d3n Profesional: Aprendizaje",
    "sg:phone":"+34 948 13 02 60",
    "sg:postcode":"31600",
    "sg:province":"Navarra",
    "wof:name":"Patronato Municipal De Deportes De Burlada",
    "wof:placetype":"venue"
},
  "geometry": {"coordinates":[-1.6140090227,42.826210022],"type":"Point"}
}