{
  "type": "Feature",
  "properties": {
    "iso:country":"ES",
    "sg:address":"Calle de Mineria (de La), S/n",
    "sg:city":"Huesca",
    "sg:orig_category":"Suministros Para Hoteles",
    "sg:phone":"+34 974 24 19 32",
    "sg:postcode":"22006",
    "sg:province":"Huesca",
    "wof:name":"Bolskam Bbs S. L.",
    "wof:placetype":"venue"
},
  "geometry": {"coordinates":[-0.4077720046,42.1481895447],"type":"Point"}
}