{
  "type": "Feature",
  "properties": {
    "addr:full":"Plaz Iglesia, 5 Vila Joiosa Alicante 03570",
    "addr:housenumber":"5",
    "addr:postcode":"03570",
    "addr:street":"Iglesia",
    "iso:country":"ES",
    "sg:address":"Plaz Iglesia, 5",
    "sg:city":"Vila Joiosa",
    "sg:orig_category":"Agentes Generales De Seguros",
    "sg:phone":"+34 965 89 50 38",
    "sg:postcode":"03570",
    "sg:province":"Alicante",
    "wof:name":"Inmoket S.l.u.",
    "wof:placetype":"venue"
},
  "geometry": {"coordinates":[-0.7466139793,38.3102035522],"type":"Point"}
}