{
  "type": "Feature",
  "properties": {
    "iso:country":"ES",
    "sg:address":"Plaz Mestre Ripoll, 9",
    "sg:city":"Valencia",
    "sg:orig_category":"Inform\u00c1tica Equipo Y Programas (al Por Mayor)",
    "sg:phone":"+34 963 56 05 87",
    "sg:postcode":"46022",
    "sg:province":"Valencia",
    "sg:website":"www.metroplus.net",
    "wof:name":"I.c.p. Ingenieria Civil Y Progamacion S.l.",
    "wof:placetype":"venue"
},
  "geometry": {"coordinates":[-0.3382340074,39.4727325439],"type":"Point"}
}