{
  "type": "Feature",
  "properties": {
    "iso:country":"ES",
    "sg:address":"Calle de Benartemi, 3",
    "sg:city":"Galdar",
    "sg:orig_category":"Ortopedia General",
    "sg:phone":"+34 928 88 21 94",
    "sg:postcode":"35460",
    "sg:province":"Las Palmas",
    "wof:name":"Ortopedia Siete Islas S.l.",
    "wof:placetype":"venue"
},
  "geometry": {"coordinates":[-15.6542444229,28.1438274384],"type":"Point"}
}