{
  "type": "Feature",
  "properties": {
    "iso:country":"ES",
    "sg:address":"Calle de Molino Blanco, 3",
    "sg:city":"Guijarrosa",
    "sg:orig_category":"Asociaciones, Organismos Culturales Y Socioeducativos",
    "sg:phone":"+34 957 31 52 11",
    "sg:postcode":"14547",
    "sg:province":"C\u00f3rdoba",
    "wof:name":"Ayuntamiento La Guijarrosa",
    "wof:placetype":"venue"
},
  "geometry": {"coordinates":[-4.8650112152,37.6365966797],"type":"Point"}
}