{
  "type": "Feature",
  "properties": {
    "addr:full":"Calle de Iberia, 65 Aguilas Murcia 30880",
    "addr:housenumber":"65",
    "addr:postcode":"30880",
    "addr:street":"Calle De Iberia",
    "iso:country":"ES",
    "sg:address":"Calle de Iberia, 65",
    "sg:city":"Aguilas",
    "sg:orig_category":"Alquiler De Veh\u00cdculos: Turismos Y Utilitarios",
    "sg:phone":"+34 968 41 45 82",
    "sg:postcode":"30880",
    "sg:province":"Murcia",
    "sg:website":"www.aurigarcar.com",
    "wof:name":"Aurigacrown Car Hire S.l.",
    "wof:placetype":"venue"
},
  "geometry": {"coordinates":[-1.5977897644,37.3986282349],"type":"Point"}
}