{
  "type": "Feature",
  "properties": {
    "addr:full":"Avda Jose Antonio, S/n Suances Cantabria 39340",
    "addr:housenumber":"s / n",
    "addr:postcode":"39340",
    "addr:street":"Avda Jose Antonio",
    "iso:country":"ES",
    "sg:address":"Avda Jose Antonio, S/n",
    "sg:city":"Suances",
    "sg:orig_category":"Distribuci\u00d3n De Petr\u00d3leo Y Derivados",
    "sg:phone":"+34 942 84 42 62",
    "sg:postcode":"39340",
    "sg:province":"Cantabria",
    "sg:website":"www.cepsa.es",
    "wof:name":"Estacion De Servicio Suances S.l.",
    "wof:placetype":"venue"
},
  "geometry": {"coordinates":[-4.0396342278,43.4223403931],"type":"Point"}
}