{
  "type": "Feature",
  "properties": {
    "addr:full":"Carrer de Sant Bonaventura, 8 S. Cugat Valles Barcelona 08172",
    "addr:housenumber":"8",
    "addr:postcode":"08172",
    "addr:street":"Carrer De Sant Bonaventura;Barcelona",
    "iso:country":"ES",
    "sg:address":"Carrer de Sant Bonaventura, 8",
    "sg:city":"S. Cugat Valles",
    "sg:orig_category":"Alimentaci\u00d3n: Aditivos, Esencias Alimentarias, Levaduras (fabricaci\u00d3n, Al Por Mayor)",
    "sg:phone":"+34 935 90 70 51",
    "sg:postcode":"08172",
    "sg:province":"Barcelona",
    "wof:name":"Orffa Espa\u00d1a S.l.",
    "wof:placetype":"venue"
},
  "geometry": {"coordinates":[2.0820128918,41.4704208374],"type":"Point"}
}