{
  "type": "Feature",
  "properties": {
    "iso:country":"ES",
    "sg:address":"Avda Portugal, 24",
    "sg:city":"Brenes",
    "sg:orig_category":"Abogados",
    "sg:phone":"+34 954 79 60 49",
    "sg:postcode":"41310",
    "sg:province":"Sevilla",
    "wof:name":"Calderon Torres Rafael",
    "wof:placetype":"venue"
},
  "geometry": {"coordinates":[-5.8682222366,37.5549888611],"type":"Point"}
}