{
  "type": "Feature",
  "properties": {
    "addr:full":"Calle de Tesifonte Gallego, 7 Albacete Albacete 02002",
    "addr:housenumber":"7",
    "addr:postcode":"02002",
    "addr:street":"Calle De Tesifonte Gallego",
    "iso:country":"ES",
    "sg:address":"Calle de Tesifonte Gallego, 7",
    "sg:city":"Albacete",
    "sg:orig_category":"Bisuter\u00cda, Joyer\u00cda, Relojer\u00cda (al Por Menor)",
    "sg:phone":"+34 967 21 55 32",
    "sg:postcode":"02002",
    "sg:province":"Albacete",
    "wof:name":"Royo Joyero S. L.",
    "wof:placetype":"venue"
},
  "geometry": {"coordinates":[-1.8553270102,38.9924278259],"type":"Point"}
}