{
  "type": "Feature",
  "properties": {
    "addr:full":"Calle de Vega, 8 Chiclana De La Frontera C\u00e1diz 11130",
    "addr:housenumber":"8",
    "addr:postcode":"11130",
    "addr:street":"Calle De Vega",
    "iso:country":"ES",
    "sg:address":"Calle de Vega, 8",
    "sg:city":"Chiclana De La Frontera",
    "sg:orig_category":"Farmacias",
    "sg:phone":"+34 956 40 16 09",
    "sg:postcode":"11130",
    "sg:province":"C\u00e1diz",
    "wof:name":"Guerrero Fernandez Manuel",
    "wof:placetype":"venue"
},
  "geometry": {"coordinates":[-6.1476860046,36.4209671021],"type":"Point"}
}