{
  "type": "Feature",
  "properties": {
    "iso:country":"ES",
    "sg:address":"Urb Serralba, 44",
    "sg:city":"Albatera",
    "sg:orig_category":"Asociaciones Y Clubs Deportivos",
    "sg:phone":"+34 965 48 81 24",
    "sg:postcode":"03340",
    "sg:province":"Alicante",
    "wof:name":"Manresa Santacruz Elias",
    "wof:placetype":"venue"
},
  "geometry": {"coordinates":[-0.8711339831,38.1797294617],"type":"Point"}
}