{
  "type": "Feature",
  "properties": {
    "addr:full":"Calle de Romero, 12 Cordoba C\u00f3rdoba 14003",
    "addr:housenumber":"12",
    "addr:postcode":"14003",
    "addr:street":"Calle De Romero;Co\u0301Rdoba",
    "iso:country":"ES",
    "sg:address":"Calle de Romero, 12",
    "sg:city":"Cordoba",
    "sg:orig_category":"Librer\u00cdas",
    "sg:phone":"+34 957 29 64 36",
    "sg:postcode":"14003",
    "sg:province":"C\u00f3rdoba",
    "wof:name":"Perez De La Concha Camacho Mariano",
    "wof:placetype":"venue"
},
  "geometry": {"coordinates":[-4.7816338539,37.8800544739],"type":"Point"}
}