{
  "type": "Feature",
  "properties": {
    "addr:full":"Avda Toreros, 9 Rozas De Madrid Madrid 28230",
    "addr:housenumber":"9",
    "addr:postcode":"28230",
    "addr:street":"Avda Toreros",
    "iso:country":"ES",
    "sg:address":"Avda Toreros, 9",
    "sg:city":"Rozas De Madrid",
    "sg:orig_category":"Quincaller\u00cda (al Por Menor)",
    "sg:phone":"+34 916 36 01 72",
    "sg:postcode":"28230",
    "sg:province":"Madrid",
    "wof:name":"Nu\u00f1ez Chabarri Miguel Angel",
    "wof:placetype":"venue"
},
  "geometry": {"coordinates":[-3.8753581047,40.4929275513],"type":"Point"}
}