{
  "type": "Feature",
  "properties": {
    "iso:country":"ES",
    "sg:address":"La Paz, S/n",
    "sg:city":"Jacarilla",
    "sg:orig_category":"Carpinteros",
    "sg:phone":"+34 965 35 00 13",
    "sg:postcode":"03310",
    "sg:province":"Alicante",
    "wof:name":"Cerrajeria Loymar S.l.",
    "wof:placetype":"venue"
},
  "geometry": {"coordinates":[-0.8710039854,38.0600242615],"type":"Point"}
}