{
  "type": "Feature",
  "properties": {
    "iso:country":"ES",
    "sg:address":"Plaz Colon (de), 8",
    "sg:city":"Galapagar",
    "sg:orig_category":"Telas Para Tapizar, Cortinas, Pasamaner\u00cda (fabricaci\u00d3n, Al Por Mayor)",
    "sg:phone":"+34 918 58 17 69",
    "sg:postcode":"28260",
    "sg:province":"Madrid",
    "sg:website":"www.ka-international.com",
    "wof:name":"Diego Isasa Maria Paz De",
    "wof:placetype":"venue"
},
  "geometry": {"coordinates":[-4.0020170212,40.5765609741],"type":"Point"}
}