{
  "type": "Feature",
  "properties": {
    "addr:full":"Calle de Sedano, 8 Madrid Madrid 28024",
    "addr:housenumber":"8",
    "addr:postcode":"madrid;28024",
    "addr:street":"Calle De Sedano",
    "iso:country":"ES",
    "sg:address":"Calle de Sedano, 8",
    "sg:city":"Madrid",
    "sg:orig_category":"Transportes Ferroviarios",
    "sg:phone":"+34 917 11 48 02",
    "sg:postcode":"28024",
    "sg:province":"Madrid",
    "wof:name":"Sevimfe S.l.",
    "wof:placetype":"venue"
},
  "geometry": {"coordinates":[-3.7731919289,40.3970451355],"type":"Point"}
}