{
  "type": "Feature",
  "properties": {
    "iso:country":"ES",
    "sg:address":"Calle de Toro, 82",
    "sg:city":"Salamanca",
    "sg:orig_category":"Asesor\u00cda Fiscal Y Jur\u00cddica",
    "sg:phone":"+34 923 21 18 72",
    "sg:postcode":"37002",
    "sg:province":"Salamanca",
    "wof:name":"Cueva Lopez-chaves Ignacio De La",
    "wof:placetype":"venue"
},
  "geometry": {"coordinates":[-5.6608371735,40.9681129456],"type":"Point"}
}