{
  "type": "Feature",
  "properties": {
    "addr:full":"Calle de Marmol, 2 Arganda Madrid 28500",
    "addr:housenumber":"2",
    "addr:postcode":"28500",
    "addr:street":"Calle De Marmol",
    "iso:country":"ES",
    "sg:address":"Calle de Marmol, 2",
    "sg:city":"Arganda",
    "sg:orig_category":"Empresas De Carpinter\u00cda De Madera",
    "sg:phone":"+34 918 71 78 20",
    "sg:postcode":"28500",
    "sg:province":"Madrid",
    "wof:name":"Indimad S.l.",
    "wof:placetype":"venue"
},
  "geometry": {"coordinates":[-3.4621551037,40.3029174805],"type":"Point"}
}