{
  "type": "Feature",
  "properties": {
    "addr:full":"Calle de Doctor Ledo Del Pozo, 14 Benavente Zamora 49600",
    "addr:housenumber":"14",
    "addr:postcode":"49600",
    "addr:street":"Calle De Doctor Ledo Del Pozo",
    "iso:country":"ES",
    "sg:address":"Calle de Doctor Ledo Del Pozo, 14",
    "sg:city":"Benavente",
    "sg:orig_category":"Dibujantes (diversos)",
    "sg:phone":"+34 980 63 43 66",
    "sg:postcode":"49600",
    "sg:province":"Zamora",
    "wof:name":"Torres Mielgo Juan",
    "wof:placetype":"venue"
},
  "geometry": {"coordinates":[-5.6760425568,42.0037193298],"type":"Point"}
}