{
  "type": "Feature",
  "properties": {
    "iso:country":"ES",
    "sg:address":"Calle de Fontanares, 82",
    "sg:city":"Valencia",
    "sg:orig_category":"Puertas Y Portales",
    "sg:phone":"+34 963 57 66 78",
    "sg:postcode":"46018",
    "sg:province":"Valencia",
    "wof:name":"Puertas Blindadas Y Acorazadas Borras S.l.",
    "wof:placetype":"venue"
},
  "geometry": {"coordinates":[-0.394878,39.4606895447],"type":"Point"}
}