{
  "type": "Feature",
  "properties": {
    "iso:country":"ES",
    "sg:address":"Avda Reconquista, 34",
    "sg:city":"Ayllon",
    "sg:orig_category":"Instalaci\u00d3n, Reparaci\u00d3n De Calefacci\u00d3n Por Gas",
    "sg:phone":"+34 921 55 32 89",
    "sg:postcode":"40520",
    "sg:province":"Segovia",
    "sg:website":"www.buquerin.es",
    "wof:name":"Buquerin Gutierrez Felix",
    "wof:placetype":"venue"
},
  "geometry": {"coordinates":[-3.3720591068,41.4192008972],"type":"Point"}
}