{
  "type": "Feature",
  "properties": {
    "iso:country":"ES",
    "sg:address":"Pl Catalunya, 4",
    "sg:city":"Prat Llobregat",
    "sg:orig_category":"Ropa Para Caballeros (al Por Menor)",
    "sg:phone":"+34 933 79 89 55",
    "sg:postcode":"08820",
    "sg:province":"Barcelona",
    "wof:name":"Cebrian Calvo Sebastian",
    "wof:placetype":"venue"
},
  "geometry": {"coordinates":[2.0926969051,41.3217468262],"type":"Point"}
}