{
  "type": "Feature",
  "properties": {
    "iso:country":"ES",
    "sg:address":"C/ Enric De Carcer, 5",
    "sg:city":"Tarrega",
    "sg:orig_category":"Fisioterapia",
    "sg:phone":"+34 973 31 36 95",
    "sg:postcode":"25300",
    "sg:province":"Lleida",
    "wof:name":"Balcells Macia Gemma",
    "wof:placetype":"venue"
},
  "geometry": {"coordinates":[1.1403859854,41.6524734497],"type":"Point"}
}