{
  "type": "Feature",
  "properties": {
    "addr:full":"Ctra. Manacor, Km. 0001,2 Petra Islas Baleares 07520",
    "addr:postcode":"07520",
    "addr:street":"Ctra. Manacor Km. 0001,2 Petra Islas",
    "iso:country":"ES",
    "sg:address":"Ctra. Manacor, Km. 0001,2",
    "sg:city":"Petra",
    "sg:orig_category":"Material Y Herramientas Agr\u00cdcolas",
    "sg:phone":"+34 971 56 11 78",
    "sg:postcode":"07520",
    "sg:province":"Islas Baleares",
    "wof:name":"Ribot C.b.",
    "wof:placetype":"venue"
},
  "geometry": {"coordinates":[3.1145501137,39.6108894348],"type":"Point"}
}