{
  "type": "Feature",
  "properties": {
    "addr:full":"M. Poniente, 11 Adra Almer\u00eda 04770",
    "addr:housenumber":"11",
    "addr:postcode":"04770",
    "addr:street":"M. Poniente;Almeri\u0301A",
    "iso:country":"ES",
    "sg:address":"M. Poniente, 11",
    "sg:city":"Adra",
    "sg:orig_category":"Distribuci\u00d3n De Petr\u00d3leo Y Derivados",
    "sg:phone":"+34 950 40 33 04",
    "sg:postcode":"04770",
    "sg:province":"Almer\u00eda",
    "wof:name":"Translina S.a.",
    "wof:placetype":"venue"
},
  "geometry": {"coordinates":[-3.0349578857,36.7481460571],"type":"Point"}
}