{
  "type": "Feature",
  "properties": {
    "iso:country":"ES",
    "sg:address":"Trva Jose Luis De Arrese, 6",
    "sg:city":"Madrid",
    "sg:orig_category":"Inmobiliaria (agencias)",
    "sg:phone":"+34 913 55 26 48",
    "sg:postcode":"28017",
    "sg:province":"Madrid",
    "wof:name":"Conrocasa Madrid S.l.",
    "wof:placetype":"venue"
},
  "geometry": {"coordinates":[-3.6549429893,40.4225196838],"type":"Point"}
}