{
  "type": "Feature",
  "properties": {
    "iso:country":"ES",
    "sg:address":"Calle de Fray Ceferino, 9",
    "sg:city":"Oviedo",
    "sg:orig_category":"Agencias Y Agentes Comerciales, Representantes",
    "sg:phone":"+34 985 21 50 59",
    "sg:postcode":"33001",
    "sg:province":"Asturias",
    "wof:name":"Suarez-llanos Cubiles Maria Elena",
    "wof:placetype":"venue"
},
  "geometry": {"coordinates":[-5.8523163795,43.3657455444],"type":"Point"}
}