{
  "type": "Feature",
  "properties": {
    "addr:full":"Gran Chaparral, S/n S. Agustin-playa Ingles Las Palmas 35100",
    "addr:housenumber":"s",
    "addr:postcode":"35100",
    "addr:street":"/ N S. Agustin-Playa",
    "iso:country":"ES",
    "sg:address":"Gran Chaparral, S/n",
    "sg:city":"S. Agustin-playa Ingles",
    "sg:orig_category":"Caf\u00c9s, Bares, Cervecer\u00cdas",
    "sg:phone":"+34 928 77 36 90",
    "sg:postcode":"35100",
    "sg:province":"Las Palmas",
    "wof:name":"Sijbring  Lucas Jan Johannes",
    "wof:placetype":"venue"
},
  "geometry": {"coordinates":[-15.4397096634,28.1302204132],"type":"Point"}
}