{
  "type": "Feature",
  "properties": {
    "iso:country":"ES",
    "sg:address":"Ctra Basurtu-kastrexana, 195",
    "sg:city":"Bilbao",
    "sg:orig_category":"Transportes Por Carretera: Lotes Completos, Mercanc\u00cdas Diversas",
    "sg:phone":"+34 944 27 78 75",
    "sg:postcode":"48013",
    "sg:province":"Vizcaya",
    "wof:name":"Sociedad Distribuidora De Alimentacion S.l.",
    "wof:placetype":"venue"
},
  "geometry": {"coordinates":[-2.9714670181,43.269493103],"type":"Point"}
}