{
  "type": "Feature",
  "properties": {
    "iso:country":"ES",
    "sg:address":"Ctra. Fuentesauco, Km. 0012,0",
    "sg:city":"Gema",
    "sg:orig_category":"Poli\u00c9ster",
    "sg:phone":"+34 980 57 68 36",
    "sg:postcode":"49151",
    "sg:province":"Zamora",
    "wof:name":"Mart-pools, S.l.",
    "wof:placetype":"venue"
},
  "geometry": {"coordinates":[-5.6763739586,41.4399642944],"type":"Point"}
}