{
  "type": "Feature",
  "properties": {
    "addr:full":"Avgd Catalunya, 45 Badalona Barcelona 08917",
    "addr:housenumber":"45",
    "addr:postcode":"08917",
    "iso:country":"ES",
    "sg:address":"Avgd Catalunya, 45",
    "sg:city":"Badalona",
    "sg:orig_category":"Peluquer\u00cdas, Peluquer\u00cda Mixta",
    "sg:phone":"+34 933 87 60 44",
    "sg:postcode":"08917",
    "sg:province":"Barcelona",
    "wof:name":"Fuente Hernandez Carmen De La",
    "wof:placetype":"venue"
},
  "geometry": {"coordinates":[2.2300310135,41.4502677917],"type":"Point"}
}