{
  "type": "Feature",
  "properties": {
    "addr:full":"Calle de Monteleon, 48 Madrid Madrid 28010",
    "addr:housenumber":"48",
    "addr:postcode":"madrid;28010",
    "addr:street":"Calle De Monteleon",
    "iso:country":"ES",
    "sg:address":"Calle de Monteleon, 48",
    "sg:city":"Madrid",
    "sg:orig_category":"Prendas Y Chalecos De Punto (al Por Menor)",
    "sg:phone":"+34 914 47 25 98",
    "sg:postcode":"28010",
    "sg:province":"Madrid",
    "wof:name":"Aguado Esteban Beatriz",
    "wof:placetype":"venue"
},
  "geometry": {"coordinates":[-3.7044267654,40.4308166504],"type":"Point"}
}