{
  "type": "Feature",
  "properties": {
    "addr:full":"Urb Poligono Juncaril, 12 Albolote Granada 18220",
    "addr:housenumber":"12",
    "addr:postcode":"18220",
    "addr:street":"Urb Poligono Juncaril",
    "iso:country":"ES",
    "sg:address":"Urb Poligono Juncaril, 12",
    "sg:city":"Albolote",
    "sg:orig_category":"Quincaller\u00cda (al Por Menor)",
    "sg:phone":"+34 958 46 53 74",
    "sg:postcode":"18220",
    "sg:province":"Granada",
    "wof:name":"Vilchez Prieto Jose Andres",
    "wof:placetype":"venue"
},
  "geometry": {"coordinates":[-3.6585440636,37.2332839966],"type":"Point"}
}