{
  "type": "Feature",
  "properties": {
    "addr:full":"Carrer de Santa Maria, 20 S. Cugat Valles Barcelona 08172",
    "addr:housenumber":"20",
    "addr:postcode":"08172",
    "addr:street":"Carrer De Santa Maria;S. Cugat Valles Barcelona",
    "iso:country":"ES",
    "sg:address":"Carrer de Santa Maria, 20",
    "sg:city":"S. Cugat Valles",
    "sg:orig_category":"\u00d3ptica: Instrumentos (fabricaci\u00d3n)",
    "sg:phone":"+34 936 74 15 37",
    "sg:postcode":"08172",
    "sg:province":"Barcelona",
    "wof:name":"Sociedad Anonima Cottet",
    "wof:placetype":"venue"
},
  "geometry": {"coordinates":[2.0814409256,41.4712753296],"type":"Point"}
}