{
  "type": "Feature",
  "properties": {
    "iso:country":"ES",
    "sg:address":"Calle de Tejar (del), S/n",
    "sg:city":"Cubas",
    "sg:orig_category":"Fabricaci\u00d3n De Moldes Y Modelos",
    "sg:phone":"+34 918 14 23 68",
    "sg:postcode":"28978",
    "sg:province":"Madrid",
    "wof:name":"Hecamar S.l.",
    "wof:placetype":"venue"
},
  "geometry": {"coordinates":[-3.8450319767,40.189414978],"type":"Point"}
}