{
  "type": "Feature",
  "properties": {
    "addr:full":"Calle de Diputacion Provincial, 21 Nerja M\u00e1laga 29780",
    "addr:housenumber":"21",
    "addr:postcode":"29780",
    "addr:street":"Calle De Diputacion Provincial",
    "iso:country":"ES",
    "sg:address":"Calle de Diputacion Provincial, 21",
    "sg:city":"Nerja",
    "sg:orig_category":"Abogados",
    "sg:phone":"+34 952 52 72 74",
    "sg:postcode":"29780",
    "sg:province":"M\u00e1laga",
    "wof:name":"Del Prado And Partners Solicitors S.l.",
    "wof:placetype":"venue"
},
  "geometry": {"coordinates":[-3.8793048859,36.7453765869],"type":"Point"}
}