{
  "type": "Feature",
  "properties": {
    "addr:full":"Via Julia, 160 Barcelona Barcelona 08016",
    "addr:housenumber":"160",
    "addr:postcode":"08016",
    "addr:street":"Via Julia",
    "iso:country":"ES",
    "sg:address":"Via Julia, 160",
    "sg:city":"Barcelona",
    "sg:orig_category":"Ropa Para Caballeros (al Por Menor)",
    "sg:phone":"+34 933 50 08 25",
    "sg:postcode":"08016",
    "sg:province":"Barcelona",
    "wof:name":"Gil Hernandez Gonzalez",
    "wof:placetype":"venue"
},
  "geometry": {"coordinates":[2.1794550419,41.4448204041],"type":"Point"}
}