{
  "type": "Feature",
  "properties": {
    "iso:country":"ES",
    "sg:address":"El Puerto, S/n",
    "sg:city":"Colindres",
    "sg:orig_category":"Suministros Y Materiales Industriales",
    "sg:phone":"+34 942 65 02 86",
    "sg:postcode":"39750",
    "sg:province":"Cantabria",
    "wof:name":"Torre Rocillo Jesus Maria",
    "wof:placetype":"venue"
},
  "geometry": {"coordinates":[-3.4410049915,43.3926849365],"type":"Point"}
}