{
  "type": "Feature",
  "properties": {
    "addr:full":"Calle de Rodrigo De La Fuente, 2 Toledo Toledo 45005",
    "addr:housenumber":"2",
    "addr:postcode":"45005",
    "addr:street":"Calle De Rodrigo De La Fuente",
    "iso:country":"ES",
    "sg:address":"Calle de Rodrigo De La Fuente, 2",
    "sg:city":"Toledo",
    "sg:orig_category":"Asesor\u00cda Sobre Comunicaci\u00d3n De Empresas",
    "sg:phone":"+34 925 24 60 27",
    "sg:postcode":"45005",
    "sg:province":"Toledo",
    "wof:name":"Rajeva 2005 S.l",
    "wof:placetype":"venue"
},
  "geometry": {"coordinates":[-4.059325695,39.9001274109],"type":"Point"}
}