{
  "type": "Feature",
  "properties": {
    "addr:full":"Calle de Isabel La Catolica, 4 Arlanzon Burgos 09199",
    "addr:housenumber":"4",
    "addr:postcode":"09199",
    "addr:street":"Calle De Isabel La Catolica",
    "iso:country":"ES",
    "sg:address":"Calle de Isabel La Catolica, 4",
    "sg:city":"Arlanzon",
    "sg:orig_category":"Frutas, Legumbres Frescas Y Tempranas (al Por Menor)",
    "sg:phone":"+34 947 42 15 55",
    "sg:postcode":"09199",
    "sg:province":"Burgos",
    "wof:name":"Guemes Martinez Carlos",
    "wof:placetype":"venue"
},
  "geometry": {"coordinates":[-3.4568490982,42.3230285645],"type":"Point"}
}