{
  "type": "Feature",
  "properties": {
    "addr:full":"Plaz Castillo, 20 Higuera Vargas Badajoz 06132",
    "addr:housenumber":"20",
    "addr:postcode":"06132",
    "addr:street":"Plaz Castillo",
    "iso:country":"ES",
    "sg:address":"Plaz Castillo, 20",
    "sg:city":"Higuera Vargas",
    "sg:orig_category":"Cajas Para Embalar",
    "sg:phone":"+34 924 42 42 51",
    "sg:postcode":"06132",
    "sg:province":"Badajoz",
    "wof:name":"Caja Rural De Extremadura",
    "wof:placetype":"venue"
},
  "geometry": {"coordinates":[-6.9746799469,38.4423332214],"type":"Point"}
}