{
  "type": "Feature",
  "properties": {
    "addr:full":"Calle de Bizkaia Kalea, 3 Irun Guip\u00f9zcoa 20305",
    "addr:housenumber":"3",
    "addr:postcode":"20305",
    "addr:street":"Calle De Bizkaia Kalea;Guipu\u0300Zcoa",
    "iso:country":"ES",
    "sg:address":"Calle de Bizkaia Kalea, 3",
    "sg:city":"Irun",
    "sg:orig_category":"Alimentaci\u00d3n General (al Por Menor)",
    "sg:phone":"+34 943 62 71 12",
    "sg:postcode":"20305",
    "sg:province":"Guip\u00f9zcoa",
    "wof:name":"Garcia Cuesta Alfredo",
    "wof:placetype":"venue"
},
  "geometry": {"coordinates":[-1.8152509928,43.3297462463],"type":"Point"}
}