{
  "type": "Feature",
  "properties": {
    "addr:full":"Ctra Navalmorales, S/n Navahermosa Toledo 45150",
    "addr:housenumber":"s",
    "addr:postcode":"45150",
    "addr:street":"Ctra Navalmorales;/ N Navahermosa",
    "iso:country":"ES",
    "sg:address":"Ctra Navalmorales, S/n",
    "sg:city":"Navahermosa",
    "sg:orig_category":"Alquiler De Veh\u00cdculos: Turismos Y Utilitarios",
    "sg:phone":"+34 925 41 00 98",
    "sg:postcode":"45150",
    "sg:province":"Toledo",
    "wof:name":"Pinilla Menor Lorenzo",
    "wof:placetype":"venue"
},
  "geometry": {"coordinates":[-4.4761991501,39.6348190308],"type":"Point"}
}