{
  "type": "Feature",
  "properties": {
    "addr:full":"Calle de Calvo Sotelo, 17 Tui Pontevedra 36700",
    "addr:housenumber":"17",
    "addr:postcode":"36700",
    "addr:street":"Calle De Calvo Sotelo",
    "iso:country":"ES",
    "sg:address":"Calle de Calvo Sotelo, 17",
    "sg:city":"Tui",
    "sg:orig_category":"Agentes Generales De Seguros",
    "sg:phone":"+34 986 60 15 39",
    "sg:postcode":"36700",
    "sg:province":"Pontevedra",
    "wof:name":"Paredes Gonzalez Juan Ramon",
    "wof:placetype":"venue"
},
  "geometry": {"coordinates":[-8.6447496414,42.0475006104],"type":"Point"}
}