{
  "type": "Feature",
  "properties": {
    "iso:country":"ES",
    "sg:address":"Calle de Bolsa, 6",
    "sg:city":"Malaga",
    "sg:orig_category":"Clubes, Asociaciones De Ocio",
    "sg:phone":"+34 952 21 69 72",
    "sg:postcode":"29015",
    "sg:province":"M\u00e1laga",
    "wof:name":"Amorina 1934 S.l.",
    "wof:placetype":"venue"
},
  "geometry": {"coordinates":[-4.4208984375,36.7193374634],"type":"Point"}
}