{
  "type": "Feature",
  "properties": {
    "iso:country":"ES",
    "sg:address":"Calle de Carmen (del), 14",
    "sg:city":"Aranjuez",
    "sg:orig_category":"Mec\u00c1nico Del Autom\u00d3vil",
    "sg:phone":"+34 918 92 16 90",
    "sg:postcode":"28300",
    "sg:province":"Madrid",
    "wof:name":"Aldo Sl",
    "wof:placetype":"venue"
},
  "geometry": {"coordinates":[-3.6000802517,40.0276565552],"type":"Point"}
}