{
  "type": "Feature",
  "properties": {
    "iso:country":"ES",
    "sg:address":"Ctra Sanlucar-benacazon, S/n",
    "sg:city":"Sanlucar Mayor",
    "sg:orig_category":"Controles De Edificaci\u00d3n (construcci\u00d3n, Seguridad)",
    "sg:phone":"+34 955 70 33 93",
    "sg:postcode":"41800",
    "sg:province":"Sevilla",
    "wof:name":"Inverlet S.l.",
    "wof:placetype":"venue"
},
  "geometry": {"coordinates":[-6.1956338882,37.3855361938],"type":"Point"}
}