{
  "type": "Feature",
  "properties": {
    "addr:full":"Calle de A, 7 Argamasilla Calatrava Ciudad Real 13440",
    "addr:housenumber":"7",
    "addr:postcode":"calatrava;13440",
    "addr:street":"Calle De A",
    "iso:country":"ES",
    "sg:address":"Calle de A, 7",
    "sg:city":"Argamasilla Calatrava",
    "sg:orig_category":"Autob\u00das (explotaci\u00d3n Y Servicios De)",
    "sg:phone":"+34 926 47 81 76",
    "sg:postcode":"13440",
    "sg:province":"Ciudad Real",
    "wof:name":"Autocares Cid S.l.",
    "wof:placetype":"venue"
},
  "geometry": {"coordinates":[-4.1364383698,38.7871437073],"type":"Point"}
}