{
  "type": "Feature",
  "properties": {
    "iso:country":"ES",
    "sg:address":"Calle de Pedro Orbea, 5",
    "sg:city":"Vitoria-gasteiz",
    "sg:orig_category":"Disfraces",
    "sg:phone":"+34 945 26 52 40",
    "sg:postcode":"01002",
    "sg:province":"\u00c1lava",
    "wof:name":"Rodriguez Sierra Antonio",
    "wof:placetype":"venue"
},
  "geometry": {"coordinates":[-2.6684279442,42.8513946533],"type":"Point"}
}