{
  "type": "Feature",
  "properties": {
    "addr:full":"Carrer de Joventut, 92 Hospitalet Llobregat Barcelona 08904",
    "addr:housenumber":"92",
    "addr:postcode":"08904",
    "addr:street":"Carrer De Joventut",
    "iso:country":"ES",
    "sg:address":"Carrer de Joventut, 92",
    "sg:city":"Hospitalet Llobregat",
    "sg:orig_category":"Cerrajer\u00cda, Ferrallista",
    "sg:phone":"+34 934 48 14 09",
    "sg:postcode":"08904",
    "sg:province":"Barcelona",
    "wof:name":"Payma 92 S.c.p.",
    "wof:placetype":"venue"
},
  "geometry": {"coordinates":[2.1203188896,41.3699913025],"type":"Point"}
}