{
  "type": "Feature",
  "properties": {
    "addr:full":"Avda Lasalle, 131 Salamanca Salamanca 37008",
    "addr:housenumber":"131",
    "addr:postcode":"37008",
    "addr:street":"Avda Lasalle",
    "iso:country":"ES",
    "sg:address":"Avda Lasalle, 131",
    "sg:city":"Salamanca",
    "sg:orig_category":"Cooperativas Agr\u00cdcolas",
    "sg:phone":"+34 923 19 27 79",
    "sg:postcode":"37008",
    "sg:province":"Salamanca",
    "wof:name":"Remolachera Salmantina Sociedad Cooperativa",
    "wof:placetype":"venue"
},
  "geometry": {"coordinates":[-5.685406208,40.9546585083],"type":"Point"}
}