{
  "type": "Feature",
  "properties": {
    "iso:country":"ES",
    "sg:address":"Calle de Antonio Lopez, 117",
    "sg:city":"Madrid",
    "sg:orig_category":"Comercio De Piezas De Recambio Y De Accesorios De Veh\u00cdculos, Veh\u00cdculos Industriales",
    "sg:phone":"+34 914 75 47 93",
    "sg:postcode":"28026",
    "sg:province":"Madrid",
    "wof:name":"Rallye Manzanares S.l.",
    "wof:placetype":"venue"
},
  "geometry": {"coordinates":[-3.7004938126,40.3891334534],"type":"Point"}
}