{
  "type": "Feature",
  "properties": {
    "iso:country":"ES",
    "sg:address":"Ctra Estacion, 1",
    "sg:city":"Pe\u00f1iscola",
    "sg:classifiers":[
        {
            "category":"Autos & Motor Vehicles",
            "subcategory":"Automobile Sales",
            "type":"Retail Goods"
        }
    ],
    "sg:phone":"+34 964 48 01 79",
    "sg:postcode":"12598",
    "sg:province":"Castell\u00f3n",
    "wof:name":"Calvo Estaun Maria Dolores",
    "wof:placetype":"venue"
},
  "geometry": {"coordinates":[-0.0456800014,39.9851417542],"type":"Point"}
}