{
  "type": "Feature",
  "properties": {
    "iso:country":"ES",
    "sg:address":"Carrer de Avella, 1",
    "sg:city":"Barcelona",
    "sg:orig_category":"Comunidades Religiosas",
    "sg:phone":"+34 932 68 43 54",
    "sg:postcode":"08003",
    "sg:province":"Barcelona",
    "wof:name":"Residencia Javeriana En Cl Avella N 1 De Barcelona-institucion Javeriana",
    "wof:placetype":"venue"
},
  "geometry": {"coordinates":[2.1776540279,41.3857955933],"type":"Point"}
}