{
  "type": "Feature",
  "properties": {
    "addr:full":"Calle de Mariano Gil, 3 Arevalo \u00c1vila 05200",
    "addr:housenumber":"3",
    "addr:postcode":"05200",
    "addr:street":"Calle De Mariano Gil",
    "iso:country":"ES",
    "sg:address":"Calle de Mariano Gil, 3",
    "sg:city":"Arevalo",
    "sg:orig_category":"Frutas, Legumbres Frescas Y Tempranas (al Por Menor)",
    "sg:phone":"+34 920 30 19 90",
    "sg:postcode":"05200",
    "sg:province":"\u00c1vila",
    "wof:name":"Tejeda Garcia Feliciana",
    "wof:placetype":"venue"
},
  "geometry": {"coordinates":[-4.7181301117,41.0564994812],"type":"Point"}
}