{
  "type": "Feature",
  "properties": {
    "iso:country":"ES",
    "sg:address":"Rua Cami\u00d1o Novo, 38",
    "sg:city":"Porto Do Son",
    "sg:orig_category":"Promotores Constructores",
    "sg:phone":"+34 981 85 40 73",
    "sg:postcode":"15970",
    "sg:province":"La Coru\u00f1a",
    "wof:name":"Promociones Ytasca Mil S.l.",
    "wof:placetype":"venue"
},
  "geometry": {"coordinates":[-9.0034942627,42.7242050171],"type":"Point"}
}