{
  "type": "Feature",
  "properties": {
    "addr:full":"Calle de General Martinez Benito (del), 42 S. Martin Valdeiglesias Madrid 28680",
    "addr:housenumber":"42",
    "addr:postcode":"28680",
    "addr:street":"Calle De General Martinez Benito Del;S. Martin Valdeiglesias",
    "iso:country":"ES",
    "sg:address":"Calle de General Martinez Benito (del), 42",
    "sg:city":"S. Martin Valdeiglesias",
    "sg:orig_category":"Deportes Y Programas De Aventura",
    "sg:phone":"+34 918 61 29 33",
    "sg:postcode":"28680",
    "sg:province":"Madrid",
    "wof:name":"Yucalcari Aventura S.l.",
    "wof:placetype":"venue"
},
  "geometry": {"coordinates":[-4.3949818611,40.3620529175],"type":"Point"}
}