{
  "type": "Feature",
  "properties": {
    "iso:country":"ES",
    "sg:address":"Calle de Marianela Garcia Villas, 1",
    "sg:city":"Zaragoza",
    "sg:orig_category":"Centros De Educaci\u00d3n Especial",
    "sg:phone":"+34 976 34 79 95",
    "sg:postcode":"50017",
    "sg:province":"Zaragoza",
    "wof:name":"Colegio Publico Apa Monsalud",
    "wof:placetype":"venue"
},
  "geometry": {"coordinates":[-0.9132840037,41.6536483765],"type":"Point"}
}