{
  "type": "Feature",
  "properties": {
    "addr:full":"Calle de Corredera, 27 Jerez De La Frontera C\u00e1diz 11402",
    "addr:housenumber":"27",
    "addr:postcode":"11402",
    "addr:street":"Calle De Corredera",
    "iso:country":"ES",
    "sg:address":"Calle de Corredera, 27",
    "sg:city":"Jerez De La Frontera",
    "sg:orig_category":"Sociedades, Compa\u00d1\u00cdas Aseguradoras",
    "sg:phone":"+34 956 34 10 16",
    "sg:postcode":"11402",
    "sg:province":"C\u00e1diz",
    "wof:name":"David Genero Y Asociados S.l.",
    "wof:placetype":"venue"
},
  "geometry": {"coordinates":[-6.135737896,36.681224823],"type":"Point"}
}