{
  "type": "Feature",
  "properties": {
    "iso:country":"ES",
    "sg:address":"Calle de Alcazabilla, 1",
    "sg:city":"Malaga",
    "sg:orig_category":"Inversiones",
    "sg:phone":"+34 952 60 83 04",
    "sg:postcode":"29015",
    "sg:province":"M\u00e1laga",
    "wof:name":"Crosseling S.a.",
    "wof:placetype":"venue"
},
  "geometry": {"coordinates":[-4.417342186,36.7206916809],"type":"Point"}
}