{
  "type": "Feature",
  "properties": {
    "addr:full":"Avda Juan Sebastian Elcano, 31 Badajoz Badajoz 06003",
    "addr:housenumber":"31",
    "addr:postcode":"06003",
    "addr:street":"Avda Juan Sebastian Elcano",
    "iso:country":"ES",
    "sg:address":"Avda Juan Sebastian Elcano, 31",
    "sg:city":"Badajoz",
    "sg:orig_category":"Supermercados Y Hipermercados",
    "sg:phone":"+34 924 23 05 71",
    "sg:postcode":"06003",
    "sg:province":"Badajoz",
    "wof:name":"Lider Aliment S.a.",
    "wof:placetype":"venue"
},
  "geometry": {"coordinates":[-6.968184948,38.8702583313],"type":"Point"}
}