{
  "type": "Feature",
  "properties": {
    "addr:full":"Calle de Pages Del Corro, 121 Sevilla Sevilla 41010",
    "addr:housenumber":"121",
    "addr:postcode":"41010",
    "addr:street":"Calle De Pages Del Corro",
    "iso:country":"ES",
    "sg:address":"Calle de Pages Del Corro, 121",
    "sg:city":"Sevilla",
    "sg:orig_category":"Procuradores",
    "sg:phone":"+34 954 27 79 44",
    "sg:postcode":"41010",
    "sg:province":"Sevilla",
    "wof:name":"Escudero Morcillo Eduardo",
    "wof:placetype":"venue"
},
  "geometry": {"coordinates":[-6.0017237663,37.3823623657],"type":"Point"}
}