{
  "type": "Feature",
  "properties": {
    "iso:country":"ES",
    "sg:address":"Calle de Ayora, 24",
    "sg:city":"Valencia",
    "sg:orig_category":"Internados & Ense\u00d1anza Privada",
    "sg:phone":"+34 963 85 16 09",
    "sg:postcode":"46018",
    "sg:province":"Valencia",
    "wof:name":"Colegio Esclavas De Maria De Valencia Esclavas De Maria Inmaculada Prov Dep Curia General",
    "wof:placetype":"venue"
},
  "geometry": {"coordinates":[-0.3930447102,39.4652442932],"type":"Point"}
}