{
  "type": "Feature",
  "properties": {
    "addr:full":"Avda Ejercito (del), 54 Arganda Madrid 28500",
    "addr:housenumber":"54",
    "addr:postcode":"28500",
    "addr:street":"Avda Ejercito Del",
    "iso:country":"ES",
    "sg:address":"Avda Ejercito (del), 54",
    "sg:city":"Arganda",
    "sg:orig_category":"Negocio De Materiales De Construcci\u00d3n",
    "sg:phone":"+34 918 70 15 49",
    "sg:postcode":"28500",
    "sg:province":"Madrid",
    "wof:name":"Azulejos Y Pavimentos Orejon Ruiz S.l.",
    "wof:placetype":"venue"
},
  "geometry": {"coordinates":[-3.4500200748,40.3036804199],"type":"Point"}
}