{
  "type": "Feature",
  "properties": {
    "addr:full":"Ctra Cartagena, S/n Fuente Alamo Murcia 30320",
    "addr:housenumber":"s / n",
    "addr:postcode":"30320",
    "addr:street":"Ctra Cartagena",
    "iso:country":"ES",
    "sg:address":"Ctra Cartagena, S/n",
    "sg:city":"Fuente Alamo",
    "sg:orig_category":"Trabajos De Perforaciones, Sondeos, Construcci\u00d3n De Pozos",
    "sg:phone":"+34 968 59 77 23",
    "sg:postcode":"30320",
    "sg:province":"Murcia",
    "wof:name":"Garcia Hernandez Domingo",
    "wof:placetype":"venue"
},
  "geometry": {"coordinates":[-1.1543140411,37.7228355408],"type":"Point"}
}