{
  "type": "Feature",
  "properties": {
    "addr:full":"Carrer de Escorxador, 1 Ondara Alicante 03760",
    "addr:housenumber":"1",
    "addr:postcode":"03760",
    "addr:street":"Carrer De Escorxador",
    "iso:country":"ES",
    "sg:address":"Carrer de Escorxador, 1",
    "sg:city":"Ondara",
    "sg:orig_category":"Prot\u00c9sicos Dentales",
    "sg:phone":"+34 965 76 74 34",
    "sg:postcode":"03760",
    "sg:province":"Alicante",
    "wof:name":"Almi\u00f1ana Noguera Ruben",
    "wof:placetype":"venue"
},
  "geometry": {"coordinates":[0.0167316999,38.8263015747],"type":"Point"}
}