{
  "type": "Feature",
  "properties": {
    "iso:country":"ES",
    "sg:address":"Carrer de Cami Ral, S/n",
    "sg:city":"Esparreguera",
    "sg:orig_category":"Electricidad: Instalaciones Industriales",
    "sg:phone":"+34 937 77 13 73",
    "sg:postcode":"08292",
    "sg:province":"Barcelona",
    "wof:name":"Serra Serra S.l.",
    "wof:placetype":"venue"
},
  "geometry": {"coordinates":[1.8712849617,41.5335845947],"type":"Point"}
}