{
  "type": "Feature",
  "properties": {
    "addr:full":"Calle de Ferrocarril, 19 Almeria Almer\u00eda 04007",
    "addr:housenumber":"19",
    "addr:postcode":"04007",
    "addr:street":"Calle De Ferrocarril",
    "iso:country":"ES",
    "sg:address":"Calle de Ferrocarril, 19",
    "sg:city":"Almeria",
    "sg:orig_category":"Ropa Para Se\u00d1oras Y Caballeros (al Por Menor)",
    "sg:phone":"+34 950 26 96 43",
    "sg:postcode":"04007",
    "sg:province":"Almer\u00eda",
    "wof:name":"Ruano Hernandez Carmen",
    "wof:placetype":"venue"
},
  "geometry": {"coordinates":[-2.452229023,36.8344802856],"type":"Point"}
}