{
  "type": "Feature",
  "properties": {
    "iso:country":"ES",
    "sg:address":"Avda Aguirre Lehendakari, 145",
    "sg:city":"Bilbao",
    "sg:orig_category":"Tiendas De Grano, Frutas Y Legumbres Secas (al Por Menor)",
    "sg:phone":"+34 944 47 88 81",
    "sg:postcode":"48015",
    "sg:province":"Vizcaya",
    "wof:name":"Almaraz Moro Jose Antonio",
    "wof:placetype":"venue"
},
  "geometry": {"coordinates":[-2.9603738785,43.2761383057],"type":"Point"}
}