{
  "type": "Feature",
  "properties": {
    "iso:country":"ES",
    "sg:address":"Carrer de Joan Crespi, 34",
    "sg:city":"Palma",
    "sg:orig_category":"Estancos",
    "sg:phone":"+34 971 28 57 42",
    "sg:postcode":"07014",
    "sg:province":"Islas Baleares",
    "wof:name":"Trujillo Fernandez Caridad",
    "wof:placetype":"venue"
},
  "geometry": {"coordinates":[2.6346960068,39.5756874084],"type":"Point"}
}