{
  "type": "Feature",
  "properties": {
    "addr:full":"Carr Pintor Goya, 27 Burjassot Valencia 46100",
    "addr:housenumber":"27",
    "addr:postcode":"46100",
    "addr:street":"Carr Pintor Goya",
    "iso:country":"ES",
    "sg:address":"Carr Pintor Goya, 27",
    "sg:city":"Burjassot",
    "sg:orig_category":"Plomeros",
    "sg:phone":"+34 963 63 77 32",
    "sg:postcode":"46100",
    "sg:province":"Valencia",
    "wof:name":"Argilez Gonzalez Pedro",
    "wof:placetype":"venue"
},
  "geometry": {"coordinates":[-0.4127312005,39.5029563904],"type":"Point"}
}