{
  "type": "Feature",
  "properties": {
    "iso:country":"ES",
    "sg:address":"Calle de Manuel Iradier, 37",
    "sg:city":"Vitoria-gasteiz",
    "sg:orig_category":"Comercio De Mobiliario De Oficina",
    "sg:phone":"+34 945 25 20 00",
    "sg:postcode":"01005",
    "sg:province":"\u00c1lava",
    "wof:name":"Valbuena Mansilla Heli",
    "wof:placetype":"venue"
},
  "geometry": {"coordinates":[-2.6673870087,42.8418006897],"type":"Point"}
}