{
  "type": "Feature",
  "properties": {
    "addr:full":"Calle de Martinez De La Rosa, 27 Granada Granada 18002",
    "addr:housenumber":"27",
    "addr:postcode":"18002",
    "addr:street":"Calle De Martinez De La Rosa",
    "iso:country":"ES",
    "sg:address":"Calle de Martinez De La Rosa, 27",
    "sg:city":"Granada",
    "sg:orig_category":"Frutas, Legumbres Frescas Y Tempranas (al Por Menor)",
    "sg:phone":"+34 958 27 14 36",
    "sg:postcode":"18002",
    "sg:province":"Granada",
    "wof:name":"Montoya Lopez Jose Luis",
    "wof:placetype":"venue"
},
  "geometry": {"coordinates":[-3.6094019413,37.177192688],"type":"Point"}
}