{
  "type": "Feature",
  "properties": {
    "addr:full":"Carr Miquel Servet, 230 Badalona Barcelona 08912",
    "addr:housenumber":"230",
    "addr:postcode":"08912",
    "addr:street":"Carr Miquel Servet",
    "iso:country":"ES",
    "sg:address":"Carr Miquel Servet, 230",
    "sg:city":"Badalona",
    "sg:orig_category":"Imprenta",
    "sg:phone":"+34 933 87 28 93",
    "sg:postcode":"08912",
    "sg:province":"Barcelona",
    "wof:name":"Duran Impressors S.l.",
    "wof:placetype":"venue"
},
  "geometry": {"coordinates":[2.238090992,41.4478492737],"type":"Point"}
}