{
  "type": "Feature",
  "properties": {
    "addr:full":"Av Sant Jordi, 6 Ma\u00e7anet Selva Girona 17412",
    "addr:housenumber":"6",
    "addr:postcode":"17412",
    "addr:street":"Av Sant Jordi",
    "iso:country":"ES",
    "sg:address":"Av Sant Jordi, 6",
    "sg:city":"Ma\u00e7anet Selva",
    "sg:orig_category":"Inmobiliaria (agencias)",
    "sg:phone":"+34 972 16 56 99",
    "sg:postcode":"17412",
    "sg:province":"Girona",
    "wof:name":"Gestion Inmobiliaria Dominica Almaraz S.l.",
    "wof:placetype":"venue"
},
  "geometry": {"coordinates":[2.7316699028,41.7760887146],"type":"Point"}
}