{
  "type": "Feature",
  "properties": {
    "addr:full":"Calle de Antonio Ruiz Rivas, 2 Algarrobo M\u00e1laga 29750",
    "addr:housenumber":"2;ma\u0301laga",
    "addr:postcode":"29750",
    "addr:street":"Calle De Antonio Ruiz Rivas",
    "iso:country":"ES",
    "sg:address":"Calle de Antonio Ruiz Rivas, 2",
    "sg:city":"Algarrobo",
    "sg:orig_category":"Centros Empresariales",
    "sg:phone":"+34 952 55 29 03",
    "sg:postcode":"29750",
    "sg:province":"M\u00e1laga",
    "wof:name":"Asociacion Empresarios Algarrobo",
    "wof:placetype":"venue"
},
  "geometry": {"coordinates":[-4.0391964912,36.7722129822],"type":"Point"}
}