{
  "type": "Feature",
  "properties": {
    "iso:country":"ES",
    "sg:address":"Calle de Antonio Ruiz Rivas, 2",
    "sg:city":"Algarrobo",
    "sg:orig_category":"Centros Empresariales",
    "sg:phone":"+34 952 55 29 03",
    "sg:postcode":"29750",
    "sg:province":"M\u00e1laga",
    "wof:name":"Asociacion Empresarios Algarrobo",
    "wof:placetype":"venue"
},
  "geometry": {"coordinates":[-4.0391964912,36.7722129822],"type":"Point"}
}