{
  "type": "Feature",
  "properties": {
    "iso:country":"ES",
    "sg:address":"Calle de Candelaria Ruiz Arbol, 13",
    "sg:city":"Zamora",
    "sg:orig_category":"Peluqueros: De Se\u00d1oras",
    "sg:phone":"+34 980 52 57 72",
    "sg:postcode":"49016",
    "sg:province":"Zamora",
    "wof:name":"H & F Cb.",
    "wof:placetype":"venue"
},
  "geometry": {"coordinates":[-5.7379875183,41.5044784546],"type":"Point"}
}