{
  "type": "Feature",
  "properties": {
    "iso:country":"ES",
    "sg:address":"Urbanizaci\u00f3n Marca De L'ham, 40",
    "sg:city":"Figueres",
    "sg:orig_category":"Art\u00cdculos De Regalo (al Por Menor)",
    "sg:phone":"+34 972 50 57 79",
    "sg:postcode":"17600",
    "sg:province":"Girona",
    "wof:name":"Euro Confort Hogar S. A.",
    "wof:placetype":"venue"
},
  "geometry": {"coordinates":[2.9814391136,42.2672157288],"type":"Point"}
}