{
  "type": "Feature",
  "properties": {
    "iso:country":"ES",
    "sg:address":"Seber Altube Plaza, 8",
    "sg:city":"Arrasate",
    "sg:orig_category":"Herboristas (al Por Menor)",
    "sg:phone":"+34 943 79 75 79",
    "sg:postcode":"20500",
    "sg:province":"Guip\u00f9zcoa",
    "wof:name":"Aramburu Zabalo Maria Carmen",
    "wof:placetype":"venue"
},
  "geometry": {"coordinates":[-2.4887208939,43.0664749146],"type":"Point"}
}