{
  "type": "Feature",
  "properties": {
    "iso:country":"ES",
    "sg:address":"Pg Germanies (de Les), 79",
    "sg:city":"Gandia",
    "sg:orig_category":"Asociaciones, Organismos Culturales Y Socioeducativos",
    "sg:phone":"+34 962 86 14 37",
    "sg:postcode":"46700",
    "sg:province":"Valencia",
    "wof:name":"Asociacion Cultural Club Falco",
    "wof:placetype":"venue"
},
  "geometry": {"coordinates":[-0.1937536001,38.9673576355],"type":"Point"}
}