{
  "type": "Feature",
  "properties": {
    "iso:country":"ES",
    "sg:address":"Puente Pia, S/n",
    "sg:city":"Lorca",
    "sg:orig_category":"Quincaller\u00cda (al Por Menor)",
    "sg:phone":"+34 968 46 93 59",
    "sg:postcode":"30800",
    "sg:province":"Murcia",
    "wof:name":"Peran Jimenez Simon",
    "wof:placetype":"venue"
},
  "geometry": {"coordinates":[-1.6865990162,37.6663398743],"type":"Point"}
}