{
  "type": "Feature",
  "properties": {
    "iso:country":"ES",
    "sg:address":"Cra. S. Celoni A Campins, 2",
    "sg:city":"S. Celoni",
    "sg:orig_category":"Peluquer\u00cdas, Peluquer\u00cda Mixta",
    "sg:phone":"+34 938 67 06 32",
    "sg:postcode":"08470",
    "sg:province":"Barcelona",
    "wof:name":"Puigdefabregas Oliver Francisco",
    "wof:placetype":"venue"
},
  "geometry": {"coordinates":[2.463572979,41.7227363586],"type":"Point"}
}