{
  "type": "Feature",
  "properties": {
    "addr:full":"Calle de Santisima Trinidad, 29 Tarifa C\u00e1diz 11380",
    "addr:housenumber":"29",
    "addr:postcode":"11380",
    "addr:street":"Calle De Santisima Trinidad;Ca\u0301Diz",
    "iso:country":"ES",
    "sg:address":"Calle de Santisima Trinidad, 29",
    "sg:city":"Tarifa",
    "sg:orig_category":"Molduras, Junquillos, Listones Y Molduras Perforadas",
    "sg:phone":"+34 956 68 04 17",
    "sg:postcode":"11380",
    "sg:province":"C\u00e1diz",
    "wof:name":"Naveira Pe\u00f1a Liliana",
    "wof:placetype":"venue"
},
  "geometry": {"coordinates":[-5.6045088768,36.0130500793],"type":"Point"}
}