{
  "type": "Feature",
  "properties": {
    "addr:full":"Pg Maragall, 412 Barcelona Barcelona 08031",
    "addr:housenumber":"412",
    "addr:postcode":"08031",
    "addr:street":"Pg Maragall",
    "iso:country":"ES",
    "sg:address":"Pg Maragall, 412",
    "sg:city":"Barcelona",
    "sg:orig_category":"Molduras, Junquillos, Listones Y Molduras Perforadas",
    "sg:phone":"+34 934 20 72 27",
    "sg:postcode":"08031",
    "sg:province":"Barcelona",
    "wof:name":"Carpintero Ca\u00f1ete Francisco Jose",
    "wof:placetype":"venue"
},
  "geometry": {"coordinates":[2.1622209549,41.4296035767],"type":"Point"}
}