{
  "type": "Feature",
  "properties": {
    "iso:country":"ES",
    "sg:address":"Carr Major, 7",
    "sg:city":"Lleida",
    "sg:orig_category":"Marroquiner\u00cda (confecci\u00d3n)",
    "sg:phone":"+34 973 24 34 22",
    "sg:postcode":"25007",
    "sg:province":"Lleida",
    "wof:name":"Marroquineria Franquesa S.l.",
    "wof:placetype":"venue"
},
  "geometry": {"coordinates":[0.627129972,41.6145210266],"type":"Point"}
}