{
  "type": "Feature",
  "properties": {
    "addr:full":"Carrer de Valira, 5 Terrassa Barcelona 08227",
    "addr:housenumber":"5",
    "addr:postcode":"08227",
    "addr:street":"Carrer De Valira",
    "iso:country":"ES",
    "sg:address":"Carrer de Valira, 5",
    "sg:city":"Terrassa",
    "sg:orig_category":"Asesor\u00cda Fiscal Y Jur\u00cddica",
    "sg:phone":"+34 937 31 73 84",
    "sg:postcode":"08227",
    "sg:province":"Barcelona",
    "wof:name":"Assessoria Prima Ius S.c.p.",
    "wof:placetype":"venue"
},
  "geometry": {"coordinates":[2.036765337,41.5750389099],"type":"Point"}
}