{
  "type": "Feature",
  "properties": {
    "addr:full":"Pl Tetuan, 25 Barcelona Barcelona 08010",
    "addr:housenumber":"25",
    "addr:postcode":"08010",
    "addr:street":"Pl Tetuan",
    "iso:country":"ES",
    "sg:address":"Pl Tetuan, 25",
    "sg:city":"Barcelona",
    "sg:orig_category":"Comercio De Hierro",
    "sg:phone":"+34 932 46 43 32",
    "sg:postcode":"08010",
    "sg:province":"Barcelona",
    "wof:name":"Arimany Bover Agustin",
    "wof:placetype":"venue"
},
  "geometry": {"coordinates":[2.1749145985,41.395565033],"type":"Point"}
}