{
  "type": "Feature",
  "properties": {
    "addr:full":"Calle de Iriarte, 23 Puerto Cruz Santa Cruz De Tenerife 38400",
    "addr:housenumber":"23",
    "addr:postcode":"38400",
    "addr:street":"Calle De Iriarte;Puerto Cruz",
    "iso:country":"ES",
    "sg:address":"Calle de Iriarte, 23",
    "sg:city":"Puerto Cruz",
    "sg:orig_category":"Peluquer\u00cdas, Peluquer\u00cda Mixta",
    "sg:phone":"+34 922 37 49 86",
    "sg:postcode":"38400",
    "sg:province":"Santa Cruz De Tenerife",
    "wof:name":"Szasz  Roudolf",
    "wof:placetype":"venue"
},
  "geometry": {"coordinates":[-16.5480289459,28.41588974],"type":"Point"}
}