{
  "type": "Feature",
  "properties": {
    "iso:country":"ES",
    "sg:address":"Carrer de Manacor, 23",
    "sg:city":"Palma",
    "sg:orig_category":"Insecticidas, Fumigaci\u00d3n",
    "sg:phone":"+34 971 46 23 44",
    "sg:postcode":"07006",
    "sg:province":"Islas Baleares",
    "wof:name":"Procamp C'an Llaneras S. A.",
    "wof:placetype":"venue"
},
  "geometry": {"coordinates":[2.6593039036,39.5715827942],"type":"Point"}
}