{
  "type": "Feature",
  "properties": {
    "iso:country":"ES",
    "sg:address":"Pl. Ayuntamiento, 4",
    "sg:city":"Arespalditza",
    "sg:classifiers":[
        {
            "category":"Recreation",
            "type":"Entertainment"
        }
    ],
    "sg:phone":"+34 945 39 94 28",
    "sg:postcode":"01476",
    "sg:province":"\u00c1lava",
    "sg:tags":[
        "caza",
        "pr\u00c1ctica",
        "la",
        "de",
        "pesca",
        "y"
    ],
    "wof:name":"Sociedad Caza Y Pesca Aiala",
    "wof:placetype":"venue"
},
  "geometry": {"coordinates":[-3.0558218956,43.0860595703],"type":"Point"}
}