{
  "type": "Feature",
  "properties": {
    "addr:full":"Pol Ind Elviria, 1 Elviria M\u00e1laga 29604",
    "addr:housenumber":"1",
    "addr:postcode":"29604",
    "addr:street":"Elviria;Ma\u0301Laga",
    "iso:country":"ES",
    "sg:address":"Pol Ind Elviria, 1",
    "sg:city":"Elviria",
    "sg:orig_category":"Empresas De Vigilancia, Guardia Y Protecci\u00d3n",
    "sg:phone":"+34 952 85 03 94",
    "sg:postcode":"29604",
    "sg:province":"M\u00e1laga",
    "wof:name":"Costa Servicios Y Mantenimiento S.l.",
    "wof:placetype":"venue"
},
  "geometry": {"coordinates":[-4.7747840881,36.4966812134],"type":"Point"}
}