{
  "type": "Feature",
  "properties": {
    "addr:full":"Calle de Rio Tormes (del), 10 Nogal Madrid 28110",
    "addr:housenumber":"10",
    "addr:postcode":"28110",
    "addr:street":"Calle De Rio Tormes Del",
    "iso:country":"ES",
    "sg:address":"Calle de Rio Tormes (del), 10",
    "sg:city":"Nogal",
    "sg:orig_category":"Aparatos, Sistemas De Tele",
    "sg:phone":"+34 916 28 90 95",
    "sg:postcode":"28110",
    "sg:province":"Madrid",
    "wof:name":"Sopair 2 Comercial",
    "wof:placetype":"venue"
},
  "geometry": {"coordinates":[-3.7003455162,40.4166908264],"type":"Point"}
}