{
  "type": "Feature",
  "properties": {
    "addr:full":"Calle de Heroes Leoneses, 2 Le\u00f3n Le\u00f3n 24002",
    "addr:housenumber":"2",
    "addr:postcode":"24002",
    "addr:street":"Calle De Heroes Leoneses;Leo\u0301N",
    "iso:country":"ES",
    "sg:address":"Calle de Heroes Leoneses, 2",
    "sg:city":"Le\u00f3n",
    "sg:orig_category":"Pizzer\u00cdas",
    "sg:phone":"+34 987 22 33 60",
    "sg:postcode":"24002",
    "sg:province":"Le\u00f3n",
    "wof:name":"Pizzeria Latina S.l.",
    "wof:placetype":"venue"
},
  "geometry": {"coordinates":[-5.5724878311,42.5985107422],"type":"Point"}
}