{
  "type": "Feature",
  "properties": {
    "addr:full":"Carrer de Torrent Mal, 23 Esparreguera Barcelona 08292",
    "addr:housenumber":"23",
    "addr:postcode":"08292",
    "addr:street":"Carrer De Torrent Mal",
    "iso:country":"ES",
    "sg:address":"Carrer de Torrent Mal, 23",
    "sg:city":"Esparreguera",
    "sg:orig_category":"Empresas De Pintura Y Revestimientos",
    "sg:phone":"+34 937 77 45 37",
    "sg:postcode":"08292",
    "sg:province":"Barcelona",
    "wof:name":"Mata Busquets Enric",
    "wof:placetype":"venue"
},
  "geometry": {"coordinates":[1.8658000231,41.5382385254],"type":"Point"}
}