{
  "type": "Feature",
  "properties": {
    "iso:country":"ES",
    "sg:address":"Avda Luis Espada, 49",
    "sg:city":"Verin",
    "sg:orig_category":"Mercer\u00cda, Lencer\u00cda (al Por Menor)",
    "sg:phone":"+34 988 41 07 30",
    "sg:postcode":"32600",
    "sg:province":"Ourense",
    "wof:name":"Sarria Alvarez Vicente",
    "wof:placetype":"venue"
},
  "geometry": {"coordinates":[-7.4374990463,41.9401817322],"type":"Point"}
}