{
  "type": "Feature",
  "properties": {
    "addr:full":"Ctra Avila, 72 Cuevas Valle \u00c1vila 05414",
    "addr:housenumber":"72",
    "addr:postcode":"05414",
    "addr:street":"Ctra Avila;A\u0301Vila",
    "iso:country":"ES",
    "sg:address":"Ctra Avila, 72",
    "sg:city":"Cuevas Valle",
    "sg:orig_category":"Maquinaria Para Industrias Diversas",
    "sg:phone":"+34 920 38 31 96",
    "sg:postcode":"05414",
    "sg:province":"\u00c1vila",
    "wof:name":"Robledo Martin Juan Jose",
    "wof:placetype":"venue"
},
  "geometry": {"coordinates":[-5.0106320381,40.297039032],"type":"Point"}
}