{
  "type": "Feature",
  "properties": {
    "iso:country":"ES",
    "sg:address":"Rua Real, 100",
    "sg:city":"Ferrol",
    "sg:classifiers":[
        {
            "category":"Casinos & Gambling",
            "type":"Entertainment"
        }
    ],
    "sg:phone":"+34 981 35 30 92",
    "sg:postcode":"15402",
    "sg:province":"La Coru\u00f1a",
    "sg:tags":[
        "locale",
        "de",
        "juego"
    ],
    "wof:name":"Casino Ferrolano",
    "wof:placetype":"venue"
},
  "geometry": {"coordinates":[-8.2344465256,43.483505249],"type":"Point"}
}