{
  "type": "Feature",
  "properties": {
    "addr:full":"Campello(pol Font De Muza), 13 Benifaio Valencia 46450",
    "addr:housenumber":"13",
    "addr:postcode":"46450",
    "iso:country":"ES",
    "sg:address":"Campello(pol Font De Muza), 13",
    "sg:city":"Benifaio",
    "sg:orig_category":"Adaptaciones, Acondicionamientos Especiales Para Veh\u00cdculos, Veh\u00cdculos Industriales",
    "sg:phone":"+34 961 79 54 96",
    "sg:postcode":"46450",
    "sg:province":"Valencia",
    "wof:name":"Process And Assembly S.l.",
    "wof:placetype":"venue"
},
  "geometry": {"coordinates":[-0.4454739988,39.2874679565],"type":"Point"}
}