{
  "type": "Feature",
  "properties": {
    "addr:full":"Calle de Pico, 56 Olvera C\u00e1diz 11690",
    "addr:housenumber":"56",
    "addr:postcode":"11690",
    "addr:street":"Calle De Pico;Ca\u0301Diz",
    "iso:country":"ES",
    "sg:address":"Calle de Pico, 56",
    "sg:city":"Olvera",
    "sg:orig_category":"Comerciantes Al Por Mayor De Vinos, Licores Y Alcoholes",
    "sg:phone":"+34 956 13 02 55",
    "sg:postcode":"11690",
    "sg:province":"C\u00e1diz",
    "wof:name":"Leo Rosa Rosa",
    "wof:placetype":"venue"
},
  "geometry": {"coordinates":[-5.2665190697,36.9358291626],"type":"Point"}
}