{
  "type": "Feature",
  "properties": {
    "iso:country":"ES",
    "sg:address":"Calle de Lope De Vega, 2",
    "sg:city":"Linares",
    "sg:orig_category":"Sociedades, Compa\u00d1\u00cdas Aseguradoras",
    "sg:phone":"+34 953 60 17 61",
    "sg:postcode":"23700",
    "sg:province":"Ja\u00e9n",
    "wof:name":"Mediacion Y Asesoria Correduria De Seguros S.l.",
    "wof:placetype":"venue"
},
  "geometry": {"coordinates":[-3.6311340332,38.0983963013],"type":"Point"}
}