{
  "type": "Feature",
  "properties": {
    "iso:country":"ES",
    "sg:address":"Avda Rosalia Castro, 29",
    "sg:city":"Milladoiro",
    "sg:orig_category":"Quincaller\u00cda (al Por Menor)",
    "sg:phone":"+34 981 59 17 90",
    "sg:postcode":"15895",
    "sg:province":"A Coru\u00f1a",
    "wof:name":"Vilari\u00f1o Gomez Olga",
    "wof:placetype":"venue"
},
  "geometry": {"coordinates":[-8.5773620605,42.843837738],"type":"Point"}
}