{
  "type": "Feature",
  "properties": {
    "iso:country":"ES",
    "sg:address":"C/ General Prieto, 8",
    "sg:city":"Alcoi",
    "sg:orig_category":"Artes Gr\u00c1ficas, Artes Pl\u00c1sticas (curso)",
    "sg:phone":"+34 966 52 05 03",
    "sg:postcode":"03804",
    "sg:province":"Alicante",
    "wof:name":"Masia Castro Antonio",
    "wof:placetype":"venue"
},
  "geometry": {"coordinates":[-0.4691520035,38.7067298889],"type":"Point"}
}