{
  "type": "Feature",
  "properties": {
    "addr:full":"Afores, S/n Capellades Barcelona 08786",
    "addr:housenumber":"s / n",
    "addr:postcode":"08786",
    "addr:street":"Afores",
    "iso:country":"ES",
    "sg:address":"Afores, S/n",
    "sg:city":"Capellades",
    "sg:orig_category":"Colorantes, Colores Y Pigmentos (fabricaci\u00d3n, Al Por Mayor)",
    "sg:phone":"+34 938 01 08 25",
    "sg:postcode":"08786",
    "sg:province":"Barcelona",
    "wof:name":"Tintes Igualada S. A.",
    "wof:placetype":"venue"
},
  "geometry": {"coordinates":[-97.78224945069999,45.7040786743],"type":"Point"}
}