{
  "type": "Feature",
  "properties": {
    "addr:full":"Carrer de Ali Bei, 113 Barcelona Barcelona 08013",
    "addr:housenumber":"113",
    "addr:postcode":"08013",
    "addr:street":"Carrer De Ali Bei",
    "iso:country":"ES",
    "sg:address":"Carrer de Ali Bei, 113",
    "sg:city":"Barcelona",
    "sg:orig_category":"Locales Y Clases De Danza",
    "sg:phone":"+34 932 46 59 62",
    "sg:postcode":"08013",
    "sg:province":"Barcelona",
    "wof:name":"Blasi Gerones Eulalia",
    "wof:placetype":"venue"
},
  "geometry": {"coordinates":[2.183727026,41.3959121704],"type":"Point"}
}