{
  "type": "Feature",
  "properties": {
    "addr:full":"C/ Mestre Guell, 97 Tarrega Lleida 25300",
    "addr:housenumber":"97",
    "addr:postcode":"25300",
    "addr:street":"C / Mestre Guell",
    "iso:country":"ES",
    "sg:address":"C/ Mestre Guell, 97",
    "sg:city":"Tarrega",
    "sg:orig_category":"Agencias Y Asesores De Publicidad",
    "sg:phone":"+34 973 31 03 36",
    "sg:postcode":"25300",
    "sg:province":"Lleida",
    "wof:name":"Naranjo Gili Isabel Maria",
    "wof:placetype":"venue"
},
  "geometry": {"coordinates":[1.1410850286,41.6482696533],"type":"Point"}
}