{
  "type": "Feature",
  "properties": {
    "iso:country":"ES",
    "sg:address":"Autopista Del Norte, Km. 0018,0",
    "sg:city":"Tacoronte",
    "sg:orig_category":"Veh\u00cdculos De Ocasi\u00d3n",
    "sg:phone":"+34 922 56 03 14",
    "sg:postcode":"38350",
    "sg:province":"Santa Cruz De Tenerife",
    "wof:name":"Hernandez Yanes Victor Manuel",
    "wof:placetype":"venue"
},
  "geometry": {"coordinates":[-16.4174289703,28.4756546021],"type":"Point"}
}