{
  "type": "Feature",
  "properties": {
    "addr:full":"Carrer de Aribau, 254 Barcelona Barcelona 08006",
    "addr:housenumber":"254",
    "addr:postcode":"08006",
    "addr:street":"Carrer De Aribau",
    "iso:country":"ES",
    "sg:address":"Carrer de Aribau, 254",
    "sg:city":"Barcelona",
    "sg:orig_category":"Panader\u00cdas, Panader\u00cdas",
    "sg:phone":"+34 932 09 49 37",
    "sg:postcode":"08006",
    "sg:province":"Barcelona",
    "wof:name":"Pujol Drets Josep",
    "wof:placetype":"venue"
},
  "geometry": {"coordinates":[2.1490321159,41.396446228],"type":"Point"}
}