{
  "type": "Feature",
  "properties": {
    "iso:country":"ES",
    "sg:address":"Rond Coru\u00d1a, 34",
    "sg:city":"Melide",
    "sg:orig_category":"Alimentaci\u00d3n General (al Por Menor)",
    "sg:phone":"+34 981 50 50 13",
    "sg:postcode":"15800",
    "sg:province":"La Coru\u00f1a",
    "wof:name":"Pampin Prado Presentacion",
    "wof:placetype":"venue"
},
  "geometry": {"coordinates":[-8.0154466629,42.9153213501],"type":"Point"}
}