{
  "type": "Feature",
  "properties": {
    "iso:country":"ES",
    "sg:address":"Ctra. Daganzo, Km. 0002,1",
    "sg:city":"Alcala Henares",
    "sg:orig_category":"Transporte En General",
    "sg:phone":"+34 918 80 46 99",
    "sg:postcode":"28806",
    "sg:province":"Madrid",
    "sg:website":"www.philips.es",
    "wof:name":"Philips Iberica S.a.",
    "wof:placetype":"venue"
},
  "geometry": {"coordinates":[-3.422385931,40.5286216736],"type":"Point"}
}