{
  "type": "Feature",
  "properties": {
    "addr:full":"Avda Aragon, 87 Alca\u00f1iz Teruel 44600",
    "addr:housenumber":"87",
    "addr:postcode":"44600",
    "addr:street":"Avda Aragon",
    "iso:country":"ES",
    "sg:address":"Avda Aragon, 87",
    "sg:city":"Alca\u00f1iz",
    "sg:orig_category":"Fabricaci\u00d3n De Cortinas Y Visillos",
    "sg:phone":"+34 978 87 12 71",
    "sg:postcode":"44600",
    "sg:province":"Teruel",
    "wof:name":"Andres Emperador Antolin Maximo",
    "wof:placetype":"venue"
},
  "geometry": {"coordinates":[-0.1291521937,41.0452690125],"type":"Point"}
}