{
  "type": "Feature",
  "properties": {
    "iso:country":"ES",
    "sg:address":"Ctra Botija, S/n",
    "sg:city":"Puerto De Sardina",
    "sg:orig_category":"Poller\u00cda Y Caza (al Por Menor)",
    "sg:phone":"+34 928 89 57 99",
    "sg:postcode":"35469",
    "sg:province":"Las Palmas",
    "wof:name":"Atlantico 7 S.l.",
    "wof:placetype":"venue"
},
  "geometry": {"coordinates":[-15.4663276672,27.8457489014],"type":"Point"}
}