{
  "type": "Feature",
  "properties": {
    "addr:full":"Calle de Manuela Malasa\u00d1a, 25 Madrid Madrid 28004",
    "addr:housenumber":"25",
    "addr:postcode":"madrid;28004",
    "addr:street":"Calle De Manuela Malasan\u0303A",
    "iso:country":"ES",
    "sg:address":"Calle de Manuela Malasa\u00d1a, 25",
    "sg:city":"Madrid",
    "sg:orig_category":"Peluquer\u00cdas, Peluquer\u00cda Mixta",
    "sg:phone":"+34 914 48 57 02",
    "sg:postcode":"28004",
    "sg:province":"Madrid",
    "wof:name":"Charcopen S.l.",
    "wof:placetype":"venue"
},
  "geometry": {"coordinates":[-3.7044560909,40.4286079407],"type":"Point"}
}