{
  "type": "Feature",
  "properties": {
    "addr:full":"Avda Perez Galdos, 43 Logro\u00f1o La Rioja 26002",
    "addr:housenumber":"43",
    "addr:postcode":"26002",
    "addr:street":"Avda Perez Galdos;Rioja",
    "iso:country":"ES",
    "sg:address":"Avda Perez Galdos, 43",
    "sg:city":"Logro\u00f1o",
    "sg:orig_category":"Ropa Para Caballeros (al Por Menor)",
    "sg:phone":"+34 941 22 14 23",
    "sg:postcode":"26002",
    "sg:province":"La Rioja",
    "wof:name":"Fernandez Peso Jose David",
    "wof:placetype":"venue"
},
  "geometry": {"coordinates":[-2.4520840645,42.4620704651],"type":"Point"}
}