{
  "type": "Feature",
  "properties": {
    "addr:full":"Calle de Damaso Alonso, 2 Pizarra M\u00e1laga 29560",
    "addr:housenumber":"2",
    "addr:postcode":"29560",
    "addr:street":"Calle De Damaso Alonso",
    "iso:country":"ES",
    "sg:address":"Calle de Damaso Alonso, 2",
    "sg:city":"Pizarra",
    "sg:orig_category":"Muebles, Minoristas",
    "sg:phone":"+34 952 48 37 83",
    "sg:postcode":"29560",
    "sg:province":"M\u00e1laga",
    "wof:name":"Electro Mueble Vera Reyes S.l.",
    "wof:placetype":"venue"
},
  "geometry": {"coordinates":[-4.7104239464,36.7634963989],"type":"Point"}
}