{
  "type": "Feature",
  "properties": {
    "iso:country":"ES",
    "sg:address":"Avda Doctor Oloriz, 27",
    "sg:city":"Granada",
    "sg:orig_category":"Estancos",
    "sg:phone":"+34 958 16 03 42",
    "sg:postcode":"18012",
    "sg:province":"Granada",
    "wof:name":"Jimenez Garrido Francisco",
    "wof:placetype":"venue"
},
  "geometry": {"coordinates":[-3.6063730717,37.1895675659],"type":"Point"}
}