{
  "type": "Feature",
  "properties": {
    "addr:full":"Av Puig De Castellet, 7 Lloret Mar Girona 17310",
    "addr:housenumber":"7",
    "addr:postcode":"17310",
    "addr:street":"Av Puig De Castellet",
    "iso:country":"ES",
    "sg:address":"Av Puig De Castellet, 7",
    "sg:city":"Lloret Mar",
    "sg:orig_category":"Molduras, Junquillos, Listones Y Molduras Perforadas",
    "sg:phone":"+34 972 36 90 43",
    "sg:postcode":"17310",
    "sg:province":"Girona",
    "wof:name":"Gonzalez Vizcaino Rosalen",
    "wof:placetype":"venue"
},
  "geometry": {"coordinates":[2.8447999954,41.7043838501],"type":"Point"}
}