{
  "type": "Feature",
  "properties": {
    "iso:country":"ES",
    "sg:address":"Calle de Castelar, 49",
    "sg:city":"Santander",
    "sg:orig_category":"Art\u00cdculos De Pvc (fabricaci\u00d3n Y Al Por Mayor)",
    "sg:phone":"+34 942 36 35 49",
    "sg:postcode":"39004",
    "sg:province":"Cantabria",
    "sg:website":"www.kommeling.com",
    "wof:name":"Profine Iberia S. A.",
    "wof:placetype":"venue"
},
  "geometry": {"coordinates":[-3.7900078297,43.4634208679],"type":"Point"}
}