{
  "type": "Feature",
  "properties": {
    "iso:country":"ES",
    "sg:address":"Calle de Ganimedes, 24",
    "sg:city":"Madrid",
    "sg:orig_category":"Agencias Y Asesores De Publicidad",
    "sg:phone":"+34 913 57 53 65",
    "sg:postcode":"28023",
    "sg:province":"Madrid",
    "wof:name":"Aspa Patrocinios S.l.",
    "wof:placetype":"venue"
},
  "geometry": {"coordinates":[-3.7829754353,40.4684486389],"type":"Point"}
}