{
  "type": "Feature",
  "properties": {
    "addr:full":"Carrer de Fortuny (de), 21 Tarragona Tarragona 43001",
    "addr:housenumber":"21",
    "addr:postcode":"43001",
    "addr:street":"Carrer De Fortuny De",
    "iso:country":"ES",
    "sg:address":"Carrer de Fortuny (de), 21",
    "sg:city":"Tarragona",
    "sg:orig_category":"Asilos De Ancianos. Centros Privados",
    "sg:phone":"+34 977 23 40 19",
    "sg:postcode":"43001",
    "sg:province":"Tarragona",
    "wof:name":"Asociacion De Jubilados Y Pensionistas De Tarragona",
    "wof:placetype":"venue"
},
  "geometry": {"coordinates":[1.2507261038,41.1148643494],"type":"Point"}
}