{
  "type": "Feature",
  "properties": {
    "iso:country":"ES",
    "sg:address":"Calle de Algodonales, 34",
    "sg:city":"Madrid",
    "sg:orig_category":"Negocio De Madera",
    "sg:phone":"+34 913 11 68 09",
    "sg:postcode":"28039",
    "sg:province":"Madrid",
    "wof:name":"Manuel Marin Arribas S. A.",
    "wof:placetype":"venue"
},
  "geometry": {"coordinates":[-3.7020480633,40.4610366821],"type":"Point"}
}