{
  "type": "Feature",
  "properties": {
    "addr:full":"Calle de Rodriguez Arias, 45 Bilbao Vizcaya 48011",
    "addr:housenumber":"45",
    "addr:postcode":"48011",
    "addr:street":"Calle De Rodriguez Arias",
    "iso:country":"ES",
    "sg:address":"Calle de Rodriguez Arias, 45",
    "sg:city":"Bilbao",
    "sg:orig_category":"Comisarios",
    "sg:phone":"+34 944 41 27 77",
    "sg:postcode":"48011",
    "sg:province":"Vizcaya",
    "wof:name":"De Sarachaga Ramirez Txomin",
    "wof:placetype":"venue"
},
  "geometry": {"coordinates":[-2.9404470921,43.2628898621],"type":"Point"}
}