{
  "type": "Feature",
  "properties": {
    "iso:country":"ES",
    "sg:address":"Rua Lamas De Prado, 198",
    "sg:city":"Lugo",
    "sg:orig_category":"Electricidad: Instaladores",
    "sg:phone":"+34 982 20 00 81",
    "sg:postcode":"27004",
    "sg:province":"Lugo",
    "wof:name":"Equipos De Se\u00d1alizacion Y Control S.a.",
    "wof:placetype":"venue"
},
  "geometry": {"coordinates":[-7.5727210045,43.0173530579],"type":"Point"}
}