{
  "type": "Feature",
  "properties": {
    "iso:country":"ES",
    "sg:address":"Calle de Luis Fernandez Gomez, 12",
    "sg:city":"Portugalete",
    "sg:orig_category":"Labores Dom\u00c9sticas",
    "sg:phone":"+34 944 96 71 91",
    "sg:postcode":"48920",
    "sg:province":"Vizcaya",
    "wof:name":"Pinturacon S.l.",
    "wof:placetype":"venue"
},
  "geometry": {"coordinates":[-3.0182609558,43.315826416],"type":"Point"}
}