{
  "type": "Feature",
  "properties": {
    "addr:full":"Carrer de Doctor Esteve, 35 Manresa Barcelona 08242",
    "addr:housenumber":"35",
    "addr:postcode":"08242",
    "addr:street":"Carrer De Doctor Esteve",
    "iso:country":"ES",
    "sg:address":"Carrer de Doctor Esteve, 35",
    "sg:city":"Manresa",
    "sg:orig_category":"Electricidad (montaje, Ensamblaje De Componentes)",
    "sg:phone":"+34 938 74 47 55",
    "sg:postcode":"08242",
    "sg:province":"Barcelona",
    "wof:name":"Sielec S.l.",
    "wof:placetype":"venue"
},
  "geometry": {"coordinates":[1.8236199617,41.7331085205],"type":"Point"}
}