{
  "type": "Feature",
  "properties": {
    "addr:full":"Pol Industrial, S/n Pinoso Alicante 03650",
    "addr:housenumber":"/ n",
    "addr:postcode":"03650",
    "addr:street":"Industrial",
    "iso:country":"ES",
    "sg:address":"Pol Industrial, S/n",
    "sg:city":"Pinoso",
    "sg:orig_category":"Maquinaria Para Industrias Diversas",
    "sg:phone":"+34 965 47 85 84",
    "sg:postcode":"03650",
    "sg:province":"Alicante",
    "wof:name":"Abellan Fernandez David",
    "wof:placetype":"venue"
},
  "geometry": {"coordinates":[-1.039464,38.417294],"type":"Point"}
}