{
  "type": "Feature",
  "properties": {
    "iso:country":"ES",
    "sg:address":"Carrer de Casanova, 96",
    "sg:city":"Barcelona",
    "sg:orig_category":"Librer\u00cdas",
    "sg:phone":"+34 934 53 74 12",
    "sg:postcode":"08011",
    "sg:province":"Barcelona",
    "wof:name":"Costa Fumaz Angela",
    "wof:placetype":"venue"
},
  "geometry": {"coordinates":[2.1568329334,41.3870544434],"type":"Point"}
}