{
  "type": "Feature",
  "properties": {
    "iso:country":"ES",
    "sg:address":"Ctra. Madrid-irun, Km. 0296,0",
    "sg:city":"Sta Maria-ribarredonda",
    "sg:orig_category":"Fabricaci\u00d3n, Importaci\u00d3n De Material Y Sistemas De Telecomunicaciones",
    "sg:phone":"+34 947 34 75 09",
    "sg:postcode":"09219",
    "sg:province":"Burgos",
    "wof:name":"Revenga Ingenieros S.a.",
    "wof:placetype":"venue"
},
  "geometry": {"coordinates":[-3.0773189068,42.6026649475],"type":"Point"}
}