{
  "type": "Feature",
  "properties": {
    "addr:full":"Calle de Erribera, 12 Ondarroa Vizcaya 48700",
    "addr:housenumber":"12",
    "addr:postcode":"48700",
    "addr:street":"Calle De Erribera",
    "iso:country":"ES",
    "sg:address":"Calle de Erribera, 12",
    "sg:city":"Ondarroa",
    "sg:orig_category":"Molduras, Junquillos, Listones Y Molduras Perforadas",
    "sg:phone":"+34 946 83 10 37",
    "sg:postcode":"48700",
    "sg:province":"Vizcaya",
    "wof:name":"Sara Urresti Burga\u00f1a",
    "wof:placetype":"venue"
},
  "geometry": {"coordinates":[-2.4229569435,43.3202972412],"type":"Point"}
}