{
  "type": "Feature",
  "properties": {
    "iso:country":"ES",
    "sg:address":"Carrer de Duran I Sors, 53",
    "sg:city":"Sabadell",
    "sg:orig_category":"Inmobiliaria (agencias)",
    "sg:phone":"+34 937 15 58 11",
    "sg:postcode":"08201",
    "sg:province":"Barcelona",
    "wof:name":"Suryagest S.l.",
    "wof:placetype":"venue"
},
  "geometry": {"coordinates":[2.1092400551,41.5396385193],"type":"Point"}
}