{
  "type": "Feature",
  "properties": {
    "iso:country":"ES",
    "sg:address":"Carr Jardi, 72",
    "sg:city":"Vilanova I La Geltru",
    "sg:orig_category":"Reposter\u00cdas",
    "sg:phone":"+34 938 93 48 10",
    "sg:postcode":"08800",
    "sg:province":"Barcelona",
    "wof:name":"Morera E Hijos S. A.",
    "wof:placetype":"venue"
},
  "geometry": {"coordinates":[1.7200510502,41.2239570618],"type":"Point"}
}