{
  "type": "Feature",
  "properties": {
    "iso:country":"ES",
    "sg:address":"Calle de Leitariegos, 1",
    "sg:city":"Villablino",
    "sg:orig_category":"Sociedades, Compa\u00d1\u00cdas Aseguradoras",
    "sg:phone":"+34 987 47 08 88",
    "sg:postcode":"24100",
    "sg:province":"Le\u00f3n",
    "wof:name":"Angel Alvarez Villalan S.l.",
    "wof:placetype":"venue"
},
  "geometry": {"coordinates":[-6.3194761276,42.9381828308],"type":"Point"}
}