{
  "type": "Feature",
  "properties": {
    "iso:country":"ES",
    "sg:address":"Pol Industrial Ii, S/n",
    "sg:city":"Campillo Arenas",
    "sg:orig_category":"Reparaciones Y Remolcado De Veh\u00cdculos",
    "sg:phone":"+34 953 30 71 77",
    "sg:postcode":"23130",
    "sg:province":"Ja\u00e9n",
    "wof:name":"Herrero Mu\u00f1oz Francisco",
    "wof:placetype":"venue"
},
  "geometry": {"coordinates":[-3.7895176411,37.7657394409],"type":"Point"}
}