{
  "type": "Feature",
  "properties": {
    "addr:full":"Virgen, S/n Otero Herreros Segovia 40422",
    "addr:postcode":"40422",
    "addr:street":"Virgen S / N Otero",
    "iso:country":"ES",
    "sg:address":"Virgen, S/n",
    "sg:city":"Otero Herreros",
    "sg:orig_category":"Cerrajer\u00cda, Ferrallista",
    "sg:phone":"+34 921 12 03 07",
    "sg:postcode":"40422",
    "sg:province":"Segovia",
    "wof:name":"Garcia Martin Carlos",
    "wof:placetype":"venue"
},
  "geometry": {"coordinates":[-4.2063589096,40.8213500977],"type":"Point"}
}