{
  "type": "Feature",
  "properties": {
    "addr:full":"Calle de Aires De Los, 7 Toro Zamora 49800",
    "addr:housenumber":"7",
    "addr:postcode":"49800",
    "addr:street":"Calle De Aires De Los",
    "iso:country":"ES",
    "sg:address":"Calle de Aires De Los, 7",
    "sg:city":"Toro",
    "sg:orig_category":"Charcuter\u00cdas (al Por Mayor)",
    "sg:phone":"+34 980 69 09 44",
    "sg:postcode":"49800",
    "sg:province":"Zamora",
    "wof:name":"Perez De La Calle Felipe",
    "wof:placetype":"venue"
},
  "geometry": {"coordinates":[-5.3862490654,41.5219917297],"type":"Point"}
}