{
  "type": "Feature",
  "properties": {
    "iso:country":"ES",
    "sg:address":"Avda Espa\u00d1a, 99",
    "sg:city":"Segorbe",
    "sg:orig_category":"Florister\u00cdas",
    "sg:phone":"+34 964 71 32 73",
    "sg:postcode":"12400",
    "sg:province":"Castell\u00f3n",
    "wof:name":"Franco Ordi\u00f1ana Maria Jose",
    "wof:placetype":"venue"
},
  "geometry": {"coordinates":[-0.4934689999,39.8479385376],"type":"Point"}
}