{
  "type": "Feature",
  "properties": {
    "addr:full":"Calle de Velazquez, 59 Madrid Madrid 28001",
    "addr:housenumber":"59",
    "addr:postcode":"madrid;28001",
    "addr:street":"Calle De Velazquez",
    "iso:country":"ES",
    "sg:address":"Calle de Velazquez, 59",
    "sg:city":"Madrid",
    "sg:orig_category":"Promotores Constructores",
    "sg:phone":"+34 915 77 39 07",
    "sg:postcode":"28001",
    "sg:province":"Madrid",
    "wof:name":"Promotoras Inmobiliarias Agrupadas S.a.",
    "wof:placetype":"venue"
},
  "geometry": {"coordinates":[-3.68384552,40.4289779663],"type":"Point"}
}