{
  "type": "Feature",
  "properties": {
    "addr:full":"Rbla Granja, 12 Molins Rei Barcelona 08750",
    "addr:housenumber":"12",
    "addr:postcode":"08750",
    "addr:street":"Rbla Granja;Barcelona",
    "iso:country":"ES",
    "sg:address":"Rbla Granja, 12",
    "sg:city":"Molins Rei",
    "sg:orig_category":"Frutas, Legumbres Frescas Y Tempranas (al Por Menor)",
    "sg:phone":"+34 936 68 99 81",
    "sg:postcode":"08750",
    "sg:province":"Barcelona",
    "wof:name":"Alabart Reyes Jorge",
    "wof:placetype":"venue"
},
  "geometry": {"coordinates":[2.0128216743,41.4161643982],"type":"Point"}
}