{
  "type": "Feature",
  "properties": {
    "iso:country":"ES",
    "sg:address":"Carrer de Maximi Fornes, 25",
    "sg:city":"Rubi",
    "sg:orig_category":"\u00d3ptica: Instrumentos (fabricaci\u00d3n)",
    "sg:phone":"+34 935 88 80 55",
    "sg:postcode":"08191",
    "sg:province":"Barcelona",
    "wof:name":"Optica Maestrat S.l.",
    "wof:placetype":"venue"
},
  "geometry": {"coordinates":[2.0308570862,41.4912605286],"type":"Point"}
}