{
  "type": "Feature",
  "properties": {
    "addr:full":"Rua Jardines (de Los), S/n Quiroga Lugo 27320",
    "addr:postcode":"27320",
    "addr:street":"Rua Jardines De Los S / N",
    "iso:country":"ES",
    "sg:address":"Rua Jardines (de Los), S/n",
    "sg:city":"Quiroga",
    "sg:orig_category":"Oficinas De Turismo, Asociaciones De Iniciativa",
    "sg:phone":"+34 982 42 89 46",
    "sg:postcode":"27320",
    "sg:province":"Lugo",
    "wof:name":"Concello De Quiroga",
    "wof:placetype":"venue"
},
  "geometry": {"coordinates":[-7.2701539993,42.4753761292],"type":"Point"}
}