{
  "type": "Feature",
  "properties": {
    "iso:country":"ES",
    "sg:address":"Calle de Calderon De La Barca, 11",
    "sg:city":"Calamonte",
    "sg:orig_category":"Comercio, Reparaci\u00d3n De Motocicletas, Bicicletas Y Piezas Sueltas",
    "sg:phone":"+34 924 32 35 58",
    "sg:postcode":"06810",
    "sg:province":"Badajoz",
    "wof:name":"Macias Mateos Victor",
    "wof:placetype":"venue"
},
  "geometry": {"coordinates":[-6.384677887,38.8851890564],"type":"Point"}
}