{
  "type": "Feature",
  "properties": {
    "iso:country":"ES",
    "sg:address":"Calle de Nueva, 15",
    "sg:city":"Sellent",
    "sg:orig_category":"Producci\u00d3n De Abonos Y De Fertilizantes",
    "sg:phone":"+34 962 25 42 75",
    "sg:postcode":"46295",
    "sg:province":"Valencia",
    "wof:name":"Vicente Llacer E Hijos S.l.",
    "wof:placetype":"venue"
},
  "geometry": {"coordinates":[-0.630621016,39.0945587158],"type":"Point"}
}