{
  "type": "Feature",
  "properties": {
    "addr:full":"Rua Simon Bolivar, 15 Vigo Pontevedra 36203",
    "addr:housenumber":"15",
    "addr:postcode":"36203",
    "addr:street":"Rua Simon Bolivar",
    "iso:country":"ES",
    "sg:address":"Rua Simon Bolivar, 15",
    "sg:city":"Vigo",
    "sg:orig_category":"Congelados: Productos Alimentarios (al Por Menor)",
    "sg:phone":"+34 986 41 19 19",
    "sg:postcode":"36203",
    "sg:province":"Pontevedra",
    "wof:name":"Laplaza De Congelados S.a.",
    "wof:placetype":"venue"
},
  "geometry": {"coordinates":[-8.720079422,42.2320861816],"type":"Point"}
}