{
  "type": "Feature",
  "properties": {
    "iso:country":"ES",
    "sg:address":"Calle de Reina, 39",
    "sg:city":"Madrid",
    "sg:orig_category":"Arquitectos",
    "sg:phone":"+34 917 01 06 66",
    "sg:postcode":"28004",
    "sg:province":"Madrid",
    "wof:name":"Martin & Mazza Arquitectos S.l.",
    "wof:placetype":"venue"
},
  "geometry": {"coordinates":[-3.6974859238,40.4197731018],"type":"Point"}
}