{
  "type": "Feature",
  "properties": {
    "addr:full":"Calle de Mare Nostrum, S/n Playa Chilches Castell\u00f3n 12592",
    "addr:housenumber":"s / n",
    "addr:postcode":"12592",
    "addr:street":"Calle De Mare Nostrum",
    "iso:country":"ES",
    "sg:address":"Calle de Mare Nostrum, S/n",
    "sg:city":"Playa Chilches",
    "sg:orig_category":"Zonas De Acampada, Aparcamiento Para Caravanas",
    "sg:phone":"+34 964 58 32 18",
    "sg:postcode":"12592",
    "sg:province":"Castell\u00f3n",
    "wof:name":"Mecho Gines S.a.",
    "wof:placetype":"venue"
},
  "geometry": {"coordinates":[-0.1846590042,39.7813034058],"type":"Point"}
}