{
  "type": "Feature",
  "properties": {
    "iso:country":"ES",
    "sg:address":"Avda Mediterraneo (del), S/n",
    "sg:city":"Almeria",
    "sg:orig_category":"Caf\u00c9s, Bares, Cervecer\u00cdas",
    "sg:phone":"+34 950 14 35 31",
    "sg:postcode":"04007",
    "sg:province":"Almer\u00eda",
    "sg:website":"www.cafeandte.com",
    "wof:name":"Compa\u00f1ia Del Tropico De Cafe Y Te S.l.",
    "wof:placetype":"venue"
},
  "geometry": {"coordinates":[-2.4460990429,36.8307914734],"type":"Point"}
}