{
  "type": "Feature",
  "properties": {
    "addr:full":"Carr Providencia, 25 Vilanova I La Geltru Barcelona 08800",
    "addr:housenumber":"25",
    "addr:postcode":"08800",
    "addr:street":"Carr Providencia",
    "iso:country":"ES",
    "sg:address":"Carr Providencia, 25",
    "sg:city":"Vilanova I La Geltru",
    "sg:orig_category":"Panader\u00cdas, Panader\u00cdas",
    "sg:phone":"+34 938 14 36 21",
    "sg:postcode":"08800",
    "sg:province":"Barcelona",
    "wof:name":"Crespo Mendoza S.l.",
    "wof:placetype":"venue"
},
  "geometry": {"coordinates":[1.7298020124,41.2241668701],"type":"Point"}
}