{
  "type": "Feature",
  "properties": {
    "addr:full":"Carrer de Gori, 45 S. Joan Vilatorrada Barcelona 08250",
    "addr:housenumber":"45",
    "addr:postcode":"08250",
    "addr:street":"Carrer De Gori;S. Joan Vilatorrada Barcelona",
    "iso:country":"ES",
    "sg:address":"Carrer de Gori, 45",
    "sg:city":"S. Joan Vilatorrada",
    "sg:orig_category":"Mataderos De Poller\u00cda",
    "sg:phone":"+34 938 72 68 33",
    "sg:postcode":"08250",
    "sg:province":"Barcelona",
    "wof:name":"Avibages S.l.",
    "wof:placetype":"venue"
},
  "geometry": {"coordinates":[1.8062570095,41.7398452759],"type":"Point"}
}