{
  "type": "Feature",
  "properties": {
    "addr:full":"Carrer de Beat Oriol, S/n Mas Rampinyo Barcelona 08110",
    "addr:housenumber":"s / n",
    "addr:postcode":"08110",
    "addr:street":"Carrer De;Oriol",
    "iso:country":"ES",
    "sg:address":"Carrer de Beat Oriol, S/n",
    "sg:city":"Mas Rampinyo",
    "sg:orig_category":"Pintura, Barniz, Productos Asimilables (fabricaci\u00d3n, Al Por Mayor)",
    "sg:phone":"+34 935 64 57 56",
    "sg:postcode":"08110",
    "sg:province":"Barcelona",
    "wof:name":"Lidl Supermercados S.a.u.",
    "wof:placetype":"venue"
},
  "geometry": {"coordinates":[2.1815750599,41.4910697937],"type":"Point"}
}