{
  "type": "Feature",
  "properties": {
    "iso:country":"ES",
    "sg:address":"Calle de Francisco De Medina Y Mendoza, S/n",
    "sg:city":"Cabanillas Campo",
    "sg:orig_category":"Artes Gr\u00c1ficas, Artes Pl\u00c1sticas (curso)",
    "sg:phone":"+34 949 20 23 92",
    "sg:postcode":"19171",
    "sg:province":"Guadalajara",
    "wof:name":"Ponton Importaciones Graficas S.l.",
    "wof:placetype":"venue"
},
  "geometry": {"coordinates":[-3.2051389217,40.6177062988],"type":"Point"}
}