{
  "type": "Feature",
  "properties": {
    "iso:country":"ES",
    "sg:address":"Carrer de Reina Victoria, 8",
    "sg:city":"Barcelona",
    "sg:orig_category":"Ense\u00d1anza Variada",
    "sg:phone":"+34 934 14 68 51",
    "sg:postcode":"08021",
    "sg:province":"Barcelona",
    "sg:website":"www.iccic.edu",
    "wof:name":"Institucio Cultural Del C.i.c.",
    "wof:placetype":"venue"
},
  "geometry": {"coordinates":[2.1398580074,41.3971252441],"type":"Point"}
}