{
  "type": "Feature",
  "properties": {
    "addr:full":"Carr Illa, 25 Port Selva Girona 17489",
    "addr:housenumber":"25",
    "addr:postcode":"17489",
    "addr:street":"Carr Illa",
    "iso:country":"ES",
    "sg:address":"Carr Illa, 25",
    "sg:city":"Port Selva",
    "sg:orig_category":"Reposter\u00cdas",
    "sg:phone":"+34 972 38 71 13",
    "sg:postcode":"17489",
    "sg:province":"Girona",
    "wof:name":"Arques Galceran Eudaldo",
    "wof:placetype":"venue"
},
  "geometry": {"coordinates":[3.2037696838,42.3379211426],"type":"Point"}
}