{
  "type": "Feature",
  "properties": {
    "addr:full":"Rua Abeledo, S/n Abeledo Ourense 32690",
    "addr:housenumber":"s",
    "addr:postcode":"32690",
    "addr:street":"Rua Abeledo;/ N",
    "iso:country":"ES",
    "sg:address":"Rua Abeledo, S/n",
    "sg:city":"Abeledo",
    "sg:orig_category":"Chapister\u00cda",
    "sg:phone":"+34 988 43 64 50",
    "sg:postcode":"32690",
    "sg:province":"Ourense",
    "wof:name":"Grande Seara Carlos",
    "wof:placetype":"venue"
},
  "geometry": {"coordinates":[-7.7960629463,42.2523612976],"type":"Point"}
}