{
  "type": "Feature",
  "properties": {
    "iso:country":"ES",
    "sg:address":"Carr Aigua, 204",
    "sg:city":"Vilanova I La Geltru",
    "sg:orig_category":"Venta, Alquiler De V\u00cddeo",
    "sg:phone":"+34 938 10 10 30",
    "sg:postcode":"08800",
    "sg:province":"Barcelona",
    "wof:name":"San Vicente Barrientos Consuelo",
    "wof:placetype":"venue"
},
  "geometry": {"coordinates":[1.7116349936,41.2214584351],"type":"Point"}
}