{
  "type": "Feature",
  "properties": {
    "iso:country":"ES",
    "sg:address":"Soroetaberri, 16",
    "sg:city":"Akartegi",
    "sg:orig_category":"Televisi\u00d3n, V\u00cddeo: Aparatos Y Accesorios (venta)",
    "sg:phone":"+34 943 64 50 33",
    "sg:postcode":"20280",
    "sg:province":"Guip\u00f9zcoa",
    "sg:website":"www.antenasilargi.com",
    "wof:name":"Antenas Ilargi S.l.",
    "wof:placetype":"venue"
},
  "geometry": {"coordinates":[-1.7967164516,43.3664932251],"type":"Point"}
}