{
  "type": "Feature",
  "properties": {
    "addr:full":"Carrer de Jacint Verdaguer, 30 Vic Barcelona 08500",
    "addr:housenumber":"30",
    "addr:postcode":"08500",
    "addr:street":"Carrer De Jacint Verdaguer",
    "iso:country":"ES",
    "sg:address":"Carrer de Jacint Verdaguer, 30",
    "sg:city":"Vic",
    "sg:orig_category":"Psic\u00d3logos",
    "sg:phone":"+34 938 89 56 33",
    "sg:postcode":"08500",
    "sg:province":"Barcelona",
    "wof:name":"Vi\u00f1as Leoz S.l.",
    "wof:placetype":"venue"
},
  "geometry": {"coordinates":[2.2505447865,41.9307975769],"type":"Point"}
}