{
  "type": "Feature",
  "properties": {
    "iso:country":"ES",
    "sg:address":"Calle de Gonzalo Gallas, 13",
    "sg:city":"Granada",
    "sg:orig_category":"Fotocopias, Reprograf\u00cda",
    "sg:phone":"+34 958 28 78 27",
    "sg:postcode":"18003",
    "sg:province":"Granada",
    "wof:name":"Cuadros Barrales Jose Manuel",
    "wof:placetype":"venue"
},
  "geometry": {"coordinates":[-3.6104090214,37.1794395447],"type":"Point"}
}