{
  "type": "Feature",
  "properties": {
    "addr:full":"Calle de Gutemberg, 9 Salamanca Salamanca 37007",
    "addr:housenumber":"9",
    "addr:postcode":"37007",
    "addr:street":"Calle De Gutemberg",
    "iso:country":"ES",
    "sg:address":"Calle de Gutemberg, 9",
    "sg:city":"Salamanca",
    "sg:orig_category":"Fabricaci\u00d3n, Importaci\u00d3n, Venta De Material De Telefon\u00cda, Peritelefon\u00cda",
    "sg:phone":"+34 923 12 05 81",
    "sg:postcode":"37007",
    "sg:province":"Salamanca",
    "wof:name":"Serintel Comunicaciones S.l.",
    "wof:placetype":"venue"
},
  "geometry": {"coordinates":[-5.668885231,40.9723472595],"type":"Point"}
}