{
  "type": "Feature",
  "properties": {
    "iso:country":"ES",
    "sg:address":"Urb Acapulco, S/n",
    "sg:city":"Torrenueva",
    "sg:orig_category":"Plomeros",
    "sg:phone":"+34 958 65 51 99",
    "sg:postcode":"18720",
    "sg:province":"Granada",
    "wof:name":"Amador Cortes Juan",
    "wof:placetype":"venue"
},
  "geometry": {"coordinates":[-3.4832921028,36.7008666992],"type":"Point"}
}