{
  "type": "Feature",
  "properties": {
    "iso:country":"ES",
    "sg:address":"Calle de Puebla De Sanabria, 3",
    "sg:city":"Zamora",
    "sg:orig_category":"Comercio De Piezas De Recambio Y De Accesorios De Veh\u00cdculos, Veh\u00cdculos Industriales",
    "sg:phone":"+34 980 52 87 88",
    "sg:postcode":"49005",
    "sg:province":"Zamora",
    "wof:name":"Auto Repuestos Marpa S.l.",
    "wof:placetype":"venue"
},
  "geometry": {"coordinates":[-5.7491416931,41.5054206848],"type":"Point"}
}