{
  "type": "Feature",
  "properties": {
    "addr:full":"Calle de Don Ambrosio, 5 Villacarrillo Ja\u00e9n 23300",
    "addr:housenumber":"5",
    "addr:postcode":"23300",
    "addr:street":"Calle De Don Ambrosio;Jae\u0301N",
    "iso:country":"ES",
    "sg:address":"Calle de Don Ambrosio, 5",
    "sg:city":"Villacarrillo",
    "sg:orig_category":"Marmolistas Funerarios",
    "sg:phone":"+34 953 44 08 35",
    "sg:postcode":"23300",
    "sg:province":"Ja\u00e9n",
    "wof:name":"Serrano Quesada Juan Ignacio",
    "wof:placetype":"venue"
},
  "geometry": {"coordinates":[-3.0856618881,38.1148910522],"type":"Point"}
}