{
  "type": "Feature",
  "properties": {
    "addr:full":"Afueras, Km. 0104,0 Salorino C\u00e1ceres 10570",
    "addr:postcode":"10570",
    "addr:street":"Afueras Km. 0104,0;Ca\u0301Ceres",
    "iso:country":"ES",
    "sg:address":"Afueras, Km. 0104,0",
    "sg:city":"Salorino",
    "sg:orig_category":"Agricultores, Agricultores",
    "sg:phone":"+34 927 49 10 11",
    "sg:postcode":"10570",
    "sg:province":"C\u00e1ceres",
    "wof:name":"Garcia Gonzalez Daniel",
    "wof:placetype":"venue"
},
  "geometry": {"coordinates":[-6.985347271,39.4628448486],"type":"Point"}
}