{
  "type": "Feature",
  "properties": {
    "iso:country":"ES",
    "sg:address":"Ctra. Cuellar, Km. 0016,0",
    "sg:city":"Campaspero",
    "sg:orig_category":"Artesanado",
    "sg:phone":"+34 983 69 85 27",
    "sg:postcode":"47310",
    "sg:province":"Valladolid",
    "wof:name":"Gabriel Garcia Acebes Y Otro Cdad",
    "wof:placetype":"venue"
},
  "geometry": {"coordinates":[-4.1938490868,41.4916954041],"type":"Point"}
}