{
  "type": "Feature",
  "properties": {
    "addr:full":"Calle de Musico Barbieri, 4 Valencia Valencia 46018",
    "addr:housenumber":"4",
    "addr:postcode":"46018",
    "addr:street":"Calle De Musico Barbieri",
    "iso:country":"ES",
    "sg:address":"Calle de Musico Barbieri, 4",
    "sg:city":"Valencia",
    "sg:orig_category":"Comercio De Cuadros, L\u00c1minas Y Reproducciones De Obras De Arte",
    "sg:phone":"+34 963 58 10 87",
    "sg:postcode":"46018",
    "sg:province":"Valencia",
    "wof:name":"Catala Mu\u00f1oz Manuel",
    "wof:placetype":"venue"
},
  "geometry": {"coordinates":[-0.3935149908,39.4612045288],"type":"Point"}
}