{
  "type": "Feature",
  "properties": {
    "addr:full":"Rbla Menceyes (los), S/n Candelaria Santa Cruz De Tenerife 38530",
    "addr:postcode":"38530",
    "addr:street":"Rbla Menceyes Los S / N",
    "iso:country":"ES",
    "sg:address":"Rbla Menceyes (los), S/n",
    "sg:city":"Candelaria",
    "sg:orig_category":"Fabricaci\u00d3n De Art\u00cdculos Y Equipos Deportivos Y De Ocio",
    "sg:phone":"+34 922 50 52 55",
    "sg:postcode":"38530",
    "sg:province":"Santa Cruz De Tenerife",
    "wof:name":"Memcas S.l.",
    "wof:placetype":"venue"
},
  "geometry": {"coordinates":[-16.3678607941,28.3607463837],"type":"Point"}
}