{
  "type": "Feature",
  "properties": {
    "iso:country":"ES",
    "sg:address":"Calle de Nereidas, S/n",
    "sg:city":"Cadiz",
    "sg:orig_category":"Cojinetes De Bolas, Agujas Y Rodillos (fabricaci\u00d3n, Al Por Mayor)",
    "sg:phone":"+34 956 28 22 04",
    "sg:postcode":"11011",
    "sg:province":"C\u00e1diz",
    "sg:website":"www.rodausa.es",
    "wof:name":"Rodamientos Usa S.a.",
    "wof:placetype":"venue"
},
  "geometry": {"coordinates":[-6.2728638649,36.498298645],"type":"Point"}
}