{
  "type": "Feature",
  "properties": {
    "addr:full":"Avgd Gaudi, 19 Igualada Barcelona 08700",
    "addr:housenumber":"19",
    "addr:postcode":"08700",
    "addr:street":"Gaudi",
    "iso:country":"ES",
    "sg:address":"Avgd Gaudi, 19",
    "sg:city":"Igualada",
    "sg:orig_category":"Comercio, Reparaci\u00d3n De Bicicletas, De Motocicletas, De Accesorios",
    "sg:phone":"+34 938 04 25 51",
    "sg:postcode":"08700",
    "sg:province":"Barcelona",
    "wof:name":"Cicles Anoia S.l.",
    "wof:placetype":"venue"
},
  "geometry": {"coordinates":[1.6099380255,41.5839195251],"type":"Point"}
}