{
  "type": "Feature",
  "properties": {
    "addr:full":"Avda Teodomiro, 14 Orihuela Alicante 03300",
    "addr:housenumber":"14",
    "addr:postcode":"03300",
    "addr:street":"Avda Teodomiro",
    "iso:country":"ES",
    "sg:address":"Avda Teodomiro, 14",
    "sg:city":"Orihuela",
    "sg:orig_category":"Bancos",
    "sg:phone":"+34 966 73 67 44",
    "sg:postcode":"03300",
    "sg:province":"Alicante",
    "wof:name":"Bankinter S.a.",
    "wof:placetype":"venue"
},
  "geometry": {"coordinates":[-0.9455410242,38.0814056396],"type":"Point"}
}