{
  "type": "Feature",
  "properties": {
    "iso:country":"ES",
    "sg:address":"Calle de Borroto, S/n",
    "sg:city":"Donostia-san Sebastian",
    "sg:orig_category":"Farmacias",
    "sg:phone":"+34 943 21 23 86",
    "sg:postcode":"20009",
    "sg:province":"Guip\u00f9zcoa",
    "wof:name":"Urbistondo Arotzarena Ana Maria",
    "wof:placetype":"venue"
},
  "geometry": {"coordinates":[-1.9876660109,43.3027305603],"type":"Point"}
}