{
  "type": "Feature",
  "properties": {
    "addr:full":"Calle de Marinos De Santo\u00d1a, 6 Santo\u00f1a Cantabria 39740",
    "addr:housenumber":"6",
    "addr:postcode":"39740",
    "addr:street":"Calle De Marinos De Santon\u0303A",
    "iso:country":"ES",
    "sg:address":"Calle de Marinos De Santo\u00d1a, 6",
    "sg:city":"Santo\u00f1a",
    "sg:orig_category":"Laboratorios Y Cl\u00cdnicas Veterinarias",
    "sg:phone":"+34 942 67 12 22",
    "sg:postcode":"39740",
    "sg:province":"Cantabria",
    "wof:name":"Veterinarios De Santo\u00f1a S.l.",
    "wof:placetype":"venue"
},
  "geometry": {"coordinates":[-3.4545609951,43.4455223083],"type":"Point"}
}