{
  "type": "Feature",
  "properties": {
    "iso:country":"ES",
    "sg:address":"Av. Scho Fuerte, 3",
    "sg:city":"Iru\u00f1a",
    "sg:orig_category":"Cooperativas Agr\u00cdcolas",
    "sg:phone":"+34 948 19 63 91",
    "sg:postcode":"31007",
    "sg:province":"Navarra",
    "wof:name":"Sociedad De Funcionarios Cruz Negra",
    "wof:placetype":"venue"
},
  "geometry": {"coordinates":[-1.6453319788,42.8078956604],"type":"Point"}
}