{
  "type": "Feature",
  "properties": {
    "addr:full":"Avda Gran Via Rey Juan Carlos I, 17 Logro\u00f1o La Rioja 26002",
    "addr:housenumber":"17",
    "addr:postcode":"26002",
    "addr:street":"Avda Gran Via Rey Juan Carlos I;Rioja",
    "iso:country":"ES",
    "sg:address":"Avda Gran Via Rey Juan Carlos I, 17",
    "sg:city":"Logro\u00f1o",
    "sg:orig_category":"M\u00c9dicos: Estomatolog\u00cda",
    "sg:phone":"+34 941 24 66 44",
    "sg:postcode":"26002",
    "sg:province":"La Rioja",
    "wof:name":"Perez Mangas Federico",
    "wof:placetype":"venue"
},
  "geometry": {"coordinates":[-2.4475460052,42.4631309509],"type":"Point"}
}