{
  "type": "Feature",
  "properties": {
    "iso:country":"ES",
    "sg:address":"Plaz Moraleja (de La), S/n",
    "sg:city":"Alcobendas",
    "sg:orig_category":"M\u00c9dicos: Estomatolog\u00cda",
    "sg:phone":"+34 916 50 55 42",
    "sg:postcode":"28109",
    "sg:province":"Madrid",
    "wof:name":"Espuelas Pe\u00f1alva Santiago",
    "wof:placetype":"venue"
},
  "geometry": {"coordinates":[-3.6530759335,40.5149269104],"type":"Point"}
}