{
  "type": "Feature",
  "properties": {
    "iso:country":"ES",
    "sg:address":"Casillas, Km. 0037,0",
    "sg:city":"Casillas",
    "sg:orig_category":"Ense\u00d1anza, Formaci\u00d3n Profesional: Aprendizaje",
    "sg:phone":"+34 981 69 75 47",
    "sg:postcode":"15680",
    "sg:province":"A Coru\u00f1a",
    "wof:name":"Sociedad Para O Desenvolvemento Comarcal De Galicia",
    "wof:placetype":"venue"
},
  "geometry": {"coordinates":[-8.4072790146,43.0771408081],"type":"Point"}
}