{
  "type": "Feature",
  "properties": {
    "addr:full":"Calle de Diputacion, 5 Bilbao Vizcaya 48009",
    "addr:housenumber":"5",
    "addr:postcode":"48009",
    "addr:street":"Calle De Diputacion",
    "iso:country":"ES",
    "sg:address":"Calle de Diputacion, 5",
    "sg:city":"Bilbao",
    "sg:orig_category":"Notarios",
    "sg:phone":"+34 944 24 42 29",
    "sg:postcode":"48009",
    "sg:province":"Vizcaya",
    "wof:name":"Linares Castrillon Ignacio",
    "wof:placetype":"venue"
},
  "geometry": {"coordinates":[-2.9322726727,43.262588501],"type":"Point"}
}