{
  "type": "Feature",
  "properties": {
    "iso:country":"ES",
    "sg:address":"Calle de Cocherito De Bilbao, 1",
    "sg:city":"Bilbao",
    "sg:orig_category":"Empresas De Carpinter\u00cda Met\u00c1lica",
    "sg:phone":"+34 944 12 11 10",
    "sg:postcode":"48004",
    "sg:province":"Vizcaya",
    "wof:name":"Pedro Hernangomez Fresno",
    "wof:placetype":"venue"
},
  "geometry": {"coordinates":[-2.9090092182,43.2504234314],"type":"Point"}
}