{
  "type": "Feature",
  "properties": {
    "addr:full":"Calle de Cuenca, 18 Azuqueca Henares Guadalajara 19200",
    "addr:housenumber":"18",
    "addr:postcode":"19200",
    "addr:street":"Calle De Cuenca",
    "iso:country":"ES",
    "sg:address":"Calle de Cuenca, 18",
    "sg:city":"Azuqueca Henares",
    "sg:orig_category":"Abogados",
    "sg:phone":"+34 949 26 42 29",
    "sg:postcode":"19200",
    "sg:province":"Guadalajara",
    "wof:name":"Lopez Martin Susana",
    "wof:placetype":"venue"
},
  "geometry": {"coordinates":[-3.2642393112,40.5640296936],"type":"Point"}
}