{
  "type": "Feature",
  "properties": {
    "addr:full":"Calle de Rojo Hermogenes Bilbao Vizcaya 48013",
    "addr:postcode":"48013",
    "addr:street":"Calle De Rojo Hermogenes",
    "iso:country":"ES",
    "sg:address":"Calle de Rojo Hermogenes",
    "sg:city":"Bilbao",
    "sg:orig_category":"Ambulancias",
    "sg:phone":"+34 944 82 00 34",
    "sg:postcode":"48013",
    "sg:province":"Vizcaya",
    "wof:name":"Ambulancias Bizkaia",
    "wof:placetype":"venue"
},
  "geometry": {"coordinates":[-2.9730803967,43.2784004211],"type":"Point"}
}