{
  "type": "Feature",
  "properties": {
    "addr:full":"Rond Roca Blanca, 83 Mataro Barcelona 08303",
    "addr:housenumber":"83",
    "addr:postcode":"08303",
    "addr:street":"Blanca",
    "iso:country":"ES",
    "sg:address":"Rond Roca Blanca, 83",
    "sg:city":"Mataro",
    "sg:orig_category":"Bisuter\u00cda, Joyer\u00cda, Relojer\u00cda (al Por Menor)",
    "sg:phone":"+34 937 57 53 47",
    "sg:postcode":"08303",
    "sg:province":"Barcelona",
    "wof:name":"Diaz Espinosa Juan Carlos",
    "wof:placetype":"venue"
},
  "geometry": {"coordinates":[2.4257800579,41.5446968079],"type":"Point"}
}