{
  "type": "Feature",
  "properties": {
    "addr:full":"Pg Valldaura, 218 Barcelona Barcelona 08042",
    "addr:housenumber":"218",
    "addr:postcode":"08042",
    "addr:street":"Pg Valldaura",
    "iso:country":"ES",
    "sg:address":"Pg Valldaura, 218",
    "sg:city":"Barcelona",
    "sg:orig_category":"Inmobiliaria (agencias)",
    "sg:phone":"+34 932 76 24 25",
    "sg:postcode":"08042",
    "sg:province":"Barcelona",
    "wof:name":"Vifer 2001s.l.",
    "wof:placetype":"venue"
},
  "geometry": {"coordinates":[2.1740748882,41.4382896423],"type":"Point"}
}