{
  "type": "Feature",
  "properties": {
    "iso:country":"ES",
    "sg:address":"Calle de Alfonso Martinez Conde, 13",
    "sg:city":"Madrid",
    "sg:orig_category":"Caf\u00c9s, Bares, Cervecer\u00cdas",
    "sg:phone":"+34 914 61 11 91",
    "sg:postcode":"28025",
    "sg:province":"Madrid",
    "wof:name":"Rivas Fernandez Enrique",
    "wof:placetype":"venue"
},
  "geometry": {"coordinates":[-3.7292509079,40.3808479309],"type":"Point"}
}