{
  "type": "Feature",
  "properties": {
    "iso:country":"ES",
    "sg:address":"Avda Primado Reig, 147",
    "sg:city":"Valencia",
    "sg:orig_category":"Inmobiliaria (agencias)",
    "sg:phone":"+34 963 69 48 04",
    "sg:postcode":"46020",
    "sg:province":"Valencia",
    "wof:name":"Saez Olivares Julian",
    "wof:placetype":"venue"
},
  "geometry": {"coordinates":[-0.3611589968,39.4827003479],"type":"Point"}
}