{
  "type": "Feature",
  "properties": {
    "addr:full":"Reboredo, 18 Noalla Ourense 32901",
    "addr:housenumber":"18",
    "addr:postcode":"32901",
    "addr:street":"Reboredo",
    "iso:country":"ES",
    "sg:address":"Reboredo, 18",
    "sg:city":"Noalla",
    "sg:orig_category":"Farmacias",
    "sg:phone":"+34 988 23 97 95",
    "sg:postcode":"32901",
    "sg:province":"Ourense",
    "wof:name":"Baladron Senra Manuel Fernando",
    "wof:placetype":"venue"
},
  "geometry": {"coordinates":[-7.8350739479,42.2879486084],"type":"Point"}
}