{
  "type": "Feature",
  "properties": {
    "iso:country":"ES",
    "sg:address":"Crt Madrid-alicante, 60",
    "sg:city":"El Pedernoso",
    "sg:orig_category":"Mec\u00c1nico Del Autom\u00d3vil",
    "sg:phone":"+34 967 16 40 13",
    "sg:postcode":"16638",
    "sg:province":"Cuenca",
    "wof:name":"Cantarero Pradillo Juan",
    "wof:placetype":"venue"
},
  "geometry": {"coordinates":[-2.7439210415,39.4858131409],"type":"Point"}
}