{
  "type": "Feature",
  "properties": {
    "addr:full":"Carrer de Santa Creu, 25 Sant Feliu Llobregat Barcelona 08980",
    "addr:housenumber":"25",
    "addr:postcode":"08980",
    "addr:street":"Carrer De Santa Creu",
    "iso:country":"ES",
    "sg:address":"Carrer de Santa Creu, 25",
    "sg:city":"Sant Feliu Llobregat",
    "sg:classifiers":[
        {
            "category":"Personal",
            "subcategory":"Barber",
            "type":"Services"
        }
    ],
    "sg:phone":"+34 936 66 42 11",
    "sg:postcode":"08980",
    "sg:province":"Barcelona",
    "sg:tags":[
        "caballeros",
        "de",
        "peluqueros"
    ],
    "wof:name":"Guillen Monsalve Jose Antonio",
    "wof:placetype":"venue"
},
  "geometry": {"coordinates":[2.0466361046,41.3861198425],"type":"Point"}
}