{
  "type": "Feature",
  "properties": {
    "addr:full":"Muel Ca\u00d1onero Dato, 6 Ceuta Ceuta 51001",
    "addr:housenumber":"6",
    "addr:postcode":"51001",
    "addr:street":"Dato",
    "iso:country":"ES",
    "sg:address":"Muel Ca\u00d1onero Dato, 6",
    "sg:city":"Ceuta",
    "sg:orig_category":"Diarios, Revistas Y Boletines (suscripciones)",
    "sg:phone":"+34 956 50 44 82",
    "sg:postcode":"51001",
    "sg:province":"Ceuta",
    "wof:name":"Almagro Fuentes Manuel",
    "wof:placetype":"venue"
},
  "geometry": {"coordinates":[-5.3193998337,35.8888816833],"type":"Point"}
}