{
  "type": "Feature",
  "properties": {
    "iso:country":"ES",
    "sg:address":"Dehesa De Boyar, S/n",
    "sg:city":"Villargordo",
    "sg:orig_category":"Fabricaci\u00d3n De Muebles",
    "sg:phone":"+34 953 37 82 16",
    "sg:postcode":"23630",
    "sg:province":"Ja\u00e9n",
    "wof:name":"Nature Mueble Sdad Coop Andaluza",
    "wof:placetype":"venue"
},
  "geometry": {"coordinates":[-3.7307140827,37.9388046265],"type":"Point"}
}