{
  "type": "Feature",
  "properties": {
    "iso:country":"ES",
    "sg:address":"Avda Miguel Servet, 17",
    "sg:city":"Utebo",
    "sg:orig_category":"Negocio De Materiales De Construcci\u00d3n",
    "sg:phone":"+34 976 77 23 96",
    "sg:postcode":"50180",
    "sg:province":"Zaragoza",
    "wof:name":"Mataragon S.l.",
    "wof:placetype":"venue"
},
  "geometry": {"coordinates":[-1.020498991,41.7118911743],"type":"Point"}
}