{
  "type": "Feature",
  "properties": {
    "addr:full":"Calle de I\u00d1aki Deuna, 23 Ondarroa Vizcaya 48700",
    "addr:housenumber":"23",
    "addr:postcode":"48700",
    "addr:street":"Calle De In\u0303Aki Deuna",
    "iso:country":"ES",
    "sg:address":"Calle de I\u00d1aki Deuna, 23",
    "sg:city":"Ondarroa",
    "sg:orig_category":"Inform\u00c1tica (estudios, Servicios, Asesor\u00cda, Formaci\u00d3n)",
    "sg:phone":"+34 946 13 44 61",
    "sg:postcode":"48700",
    "sg:province":"Vizcaya",
    "wof:name":"Ibarrola Arrasate Estibaliz",
    "wof:placetype":"venue"
},
  "geometry": {"coordinates":[-2.4265139103,43.3198852539],"type":"Point"}
}