{
  "type": "Feature",
  "properties": {
    "iso:country":"ES",
    "sg:address":"Avda Reyes Catolicos, 4",
    "sg:city":"Salda\u00f1a",
    "sg:orig_category":"Explotaci\u00d3n De Bosques",
    "sg:phone":"+34 979 89 25 26",
    "sg:postcode":"34100",
    "sg:province":"Palencia",
    "wof:name":"Talher S. A.",
    "wof:placetype":"venue"
},
  "geometry": {"coordinates":[-4.7316451073,42.5258216858],"type":"Point"}
}