{
  "type": "Feature",
  "properties": {
    "addr:full":"Calle de Conde De Aranda, 18 Aguilas Murcia 30880",
    "addr:housenumber":"18",
    "addr:postcode":"30880",
    "addr:street":"Calle De Conde De Aranda",
    "iso:country":"ES",
    "sg:address":"Calle de Conde De Aranda, 18",
    "sg:city":"Aguilas",
    "sg:orig_category":"Asesor\u00cda Fiscal Y Jur\u00cddica",
    "sg:phone":"+34 968 41 01 28",
    "sg:postcode":"30880",
    "sg:province":"Murcia",
    "wof:name":"Asensio Molina Antonio",
    "wof:placetype":"venue"
},
  "geometry": {"coordinates":[-1.5832942724,37.4045181274],"type":"Point"}
}