{
  "type": "Feature",
  "properties": {
    "addr:full":"Candis, S/n Sobradelo Ourense 32330",
    "addr:housenumber":"s / n",
    "addr:postcode":"32330",
    "addr:street":"Candis",
    "iso:country":"ES",
    "sg:address":"Candis, S/n",
    "sg:city":"Sobradelo",
    "sg:orig_category":"Caf\u00c9s, Bares, Cervecer\u00cdas",
    "sg:phone":"+34 988 33 49 43",
    "sg:postcode":"32330",
    "sg:province":"Ourense",
    "wof:name":"Almeida Leon Laureano Augusto",
    "wof:placetype":"venue"
},
  "geometry": {"coordinates":[-6.9119062424,42.4156265259],"type":"Point"}
}