{
  "type": "Feature",
  "properties": {
    "iso:country":"ES",
    "sg:address":"Alam Revilla Gregorio De La, 23",
    "sg:city":"Bilbao",
    "sg:orig_category":"Peluqueros: De Se\u00d1oras",
    "sg:phone":"+34 944 27 07 99",
    "sg:postcode":"48011",
    "sg:province":"Vizcaya",
    "wof:name":"Peluquerias Loro\u00f1o S.l.",
    "wof:placetype":"venue"
},
  "geometry": {"coordinates":[-2.9401099682,43.2611312866],"type":"Point"}
}