{
  "type": "Feature",
  "properties": {
    "addr:full":"Calle de Estadium, 14 Badajoz Badajoz 06003",
    "addr:housenumber":"14",
    "addr:postcode":"06003",
    "addr:street":"Calle De Estadium",
    "iso:country":"ES",
    "sg:address":"Calle de Estadium, 14",
    "sg:city":"Badajoz",
    "sg:orig_category":"Tiendas De Grano, Frutas Y Legumbres Secas (al Por Menor)",
    "sg:phone":"+34 924 23 77 90",
    "sg:postcode":"06003",
    "sg:province":"Badajoz",
    "wof:name":"Reguera Pantoja Pedro",
    "wof:placetype":"venue"
},
  "geometry": {"coordinates":[-6.9679551125,38.8743858337],"type":"Point"}
}