{
  "type": "Feature",
  "properties": {
    "iso:country":"ES",
    "sg:address":"Calle de Manuel Cue, 8",
    "sg:city":"Llanes",
    "sg:orig_category":"Restaurantes",
    "sg:phone":"+34 985 40 05 84",
    "sg:postcode":"33500",
    "sg:province":"Asturias",
    "wof:name":"Amieva Gutierrez Maria Elena",
    "wof:placetype":"venue"
},
  "geometry": {"coordinates":[-4.7542457581,43.420124054],"type":"Point"}
}