{
  "type": "Feature",
  "properties": {
    "addr:full":"Avda Blas Infante, 2 Sevilla Sevilla 41...",
    "addr:housenumber":"2;41 ...",
    "addr:street":"Avda Blas Infante;Sevilla",
    "iso:country":"ES",
    "sg:address":"Avda Blas Infante, 2",
    "sg:city":"Sevilla",
    "sg:orig_category":"Ense\u00d1anza, Formaci\u00d3n Profesional: Aprendizaje",
    "sg:phone":"+34 954 28 93 00",
    "sg:postcode":"41...",
    "sg:province":"Sevilla",
    "sg:website":"www.mir.es",
    "wof:name":"Direccion General De La Policia",
    "wof:placetype":"venue"
},
  "geometry": {"coordinates":[-6.0059762001,37.3759307861],"type":"Point"}
}