{
  "type": "Feature",
  "properties": {
    "iso:country":"ES",
    "sg:address":"Carrer de Alfons Iv, 61",
    "sg:city":"Granollers",
    "sg:orig_category":"Pirotecnia (espect\u00c1culos)",
    "sg:phone":"+34 938 79 50 95",
    "sg:postcode":"08402",
    "sg:province":"Barcelona",
    "sg:website":"www.arspirotecnia.com",
    "wof:name":"Ars Pirotecnia S.l.",
    "wof:placetype":"venue"
},
  "geometry": {"coordinates":[2.2880437374,41.6040153503],"type":"Point"}
}