{
  "type": "Feature",
  "properties": {
    "addr:full":"Pol Ind El Granadal, 2 Cordoba C\u00f3rdoba 14014",
    "addr:housenumber":"2",
    "addr:postcode":"14014",
    "addr:street":"Granadal;Co\u0301Rdoba",
    "iso:country":"ES",
    "sg:address":"Pol Ind El Granadal, 2",
    "sg:city":"Cordoba",
    "sg:orig_category":"Pintura, Barniz, Productos Asimilables (fabricaci\u00d3n, Al Por Mayor)",
    "sg:phone":"+34 957 26 70 86",
    "sg:postcode":"14014",
    "sg:province":"C\u00f3rdoba",
    "sg:website":"www.procolor.es",
    "wof:name":"Akzo Nobel Distribucion S.l.",
    "wof:placetype":"venue"
},
  "geometry": {"coordinates":[-4.6243748665,37.9513511658],"type":"Point"}
}