{
  "type": "Feature",
  "properties": {
    "addr:full":"Carrer de Lletra D De La Zona Franca, 28 Barcelona Barcelona 08040",
    "addr:housenumber":"28",
    "addr:postcode":"08040",
    "addr:street":"Carrer De Lletra D De La;Franca",
    "iso:country":"ES",
    "sg:address":"Carrer de Lletra D De La Zona Franca, 28",
    "sg:city":"Barcelona",
    "sg:orig_category":"Maquinaria Para Industrias Diversas",
    "sg:phone":"+34 933 35 08 54",
    "sg:postcode":"08040",
    "sg:province":"Barcelona",
    "wof:name":"Abantia Mantenimiento S.a.",
    "wof:placetype":"venue"
},
  "geometry": {"coordinates":[2.131448,41.322556],"type":"Point"}
}