{
  "type": "Feature",
  "properties": {
    "iso:country":"ES",
    "sg:address":"Plaz Pantaleon Romero, 3",
    "sg:city":"Competa",
    "sg:orig_category":"Fabricaci\u00d3n, Venta De Productos Base Farmac\u00c9uticos",
    "sg:phone":"+34 952 55 34 01",
    "sg:postcode":"29754",
    "sg:province":"M\u00e1laga",
    "wof:name":"Lechuga Lopez Francisco Javier",
    "wof:placetype":"venue"
},
  "geometry": {"coordinates":[-3.9743690491,36.8326416016],"type":"Point"}
}