{
  "type": "Feature",
  "properties": {
    "addr:full":"Rua Da Cruz, 27 Verin Ourense 32600",
    "addr:housenumber":"27",
    "addr:postcode":"32600",
    "addr:street":"Rua Da Cruz",
    "iso:country":"ES",
    "sg:address":"Rua Da Cruz, 27",
    "sg:city":"Verin",
    "sg:orig_category":"Agentes Generales De Seguros",
    "sg:phone":"+34 988 41 26 34",
    "sg:postcode":"32600",
    "sg:province":"Ourense",
    "wof:name":"Rodrimor Servicios S.l.",
    "wof:placetype":"venue"
},
  "geometry": {"coordinates":[-7.4368638992,41.9417915344],"type":"Point"}
}