{
  "type": "Feature",
  "properties": {
    "addr:full":"Avda Paz La, 2 Entrego Asturias 33940",
    "addr:housenumber":"2",
    "addr:postcode":"33940",
    "addr:street":"Avda Paz La",
    "iso:country":"ES",
    "sg:address":"Avda Paz La, 2",
    "sg:city":"Entrego",
    "sg:orig_category":"Librer\u00cdas",
    "sg:phone":"+34 985 66 23 96",
    "sg:postcode":"33940",
    "sg:province":"Asturias",
    "wof:name":"Vazquez Perez Felix Xabel",
    "wof:placetype":"venue"
},
  "geometry": {"coordinates":[-5.6435742378,43.2864112854],"type":"Point"}
}