{
  "type": "Feature",
  "properties": {
    "addr:full":"Ctra. M-lisboa, Km. 0386,0 Talavera Real Badajoz 06140",
    "addr:postcode":"06140",
    "addr:street":"Ctra. M-Lisboa Km. 0386,0",
    "iso:country":"ES",
    "sg:address":"Ctra. M-lisboa, Km. 0386,0",
    "sg:city":"Talavera Real",
    "sg:orig_category":"Mec\u00c1nico Del Autom\u00d3vil",
    "sg:phone":"+34 924 44 04 52",
    "sg:postcode":"06140",
    "sg:province":"Badajoz",
    "wof:name":"Talleres Rodriguez Labrador S.l.",
    "wof:placetype":"venue"
},
  "geometry": {"coordinates":[-6.7671589851,38.8753318787],"type":"Point"}
}