{
  "type": "Feature",
  "properties": {
    "iso:country":"ES",
    "sg:address":"Calle de Castillo De Utrera, 2",
    "sg:city":"Sevilla",
    "sg:orig_category":"Promotores Constructores",
    "sg:phone":"+34 954 22 77 49",
    "sg:postcode":"41013",
    "sg:province":"Sevilla",
    "wof:name":"Chivalges S.l.",
    "wof:placetype":"venue"
},
  "geometry": {"coordinates":[-5.9793066978,37.3586387634],"type":"Point"}
}