{
  "type": "Feature",
  "properties": {
    "addr:full":"Calle de Arquitecto Magdalena, 1 Zaragoza Zaragoza 50001",
    "addr:housenumber":"1",
    "addr:postcode":"50001",
    "addr:street":"Calle De Arquitecto Magdalena",
    "iso:country":"ES",
    "sg:address":"Calle de Arquitecto Magdalena, 1",
    "sg:city":"Zaragoza",
    "sg:orig_category":"Comunidades Religiosas",
    "sg:phone":"+34 976 22 23 84",
    "sg:postcode":"50001",
    "sg:province":"Zaragoza",
    "wof:name":"Clarisas Convento De Santa Catalina",
    "wof:placetype":"venue"
},
  "geometry": {"coordinates":[-0.8794003725,41.6497917175],"type":"Point"}
}