{
  "type": "Feature",
  "properties": {
    "addr:full":"Carrer de Marti Molins, 60 Barcelona Barcelona 08027",
    "addr:housenumber":"60",
    "addr:postcode":"08027",
    "addr:street":"Carrer De Marti Molins",
    "iso:country":"ES",
    "sg:address":"Carrer de Marti Molins, 60",
    "sg:city":"Barcelona",
    "sg:orig_category":"Herboristas (al Por Menor)",
    "sg:phone":"+34 933 49 10 98",
    "sg:postcode":"08027",
    "sg:province":"Barcelona",
    "wof:name":"Modrego Garralda Maria Luisa",
    "wof:placetype":"venue"
},
  "geometry": {"coordinates":[2.1881520748,41.4240455627],"type":"Point"}
}