{
  "type": "Feature",
  "properties": {
    "iso:country":"ES",
    "sg:address":"Plaz Santo Domingo De Silos, 8",
    "sg:city":"Toro",
    "sg:orig_category":"Delegados, Agentes De Tr\u00c1nsito, Auxiliares De Transporte Internacional",
    "sg:phone":"+34 980 69 32 49",
    "sg:postcode":"49800",
    "sg:province":"Zamora",
    "wof:name":"Frutas Marban S. L.",
    "wof:placetype":"venue"
},
  "geometry": {"coordinates":[-5.399269104,41.525680542],"type":"Point"}
}