{
  "type": "Feature",
  "properties": {
    "iso:country":"ES",
    "sg:address":"Carr Pi I Margall, 17",
    "sg:city":"Lleida",
    "sg:classifiers":[
        {
            "category":"Casinos & Gambling",
            "type":"Entertainment"
        }
    ],
    "sg:phone":"+34 973 22 06 55",
    "sg:postcode":"25004",
    "sg:province":"Lleida",
    "sg:tags":[
        "locale",
        "de",
        "juego"
    ],
    "sg:website":"www.jartoys.com",
    "wof:name":"J.a.r.toys S.l.",
    "wof:placetype":"venue"
},
  "geometry": {"coordinates":[0.6278560758,41.6208381653],"type":"Point"}
}