{
  "type": "Feature",
  "properties": {
    "addr:full":"Calle de Maestranza, 27 Malaga M\u00e1laga 29016",
    "addr:housenumber":"27",
    "addr:postcode":"29016",
    "addr:street":"Calle De Maestranza;Ma\u0301Laga",
    "iso:country":"ES",
    "sg:address":"Calle de Maestranza, 27",
    "sg:city":"Malaga",
    "sg:orig_category":"Inform\u00c1tica, Ofim\u00c1tica (estudios, Asesor\u00cda, Ingenier\u00cda, Formaci\u00d3n)",
    "sg:phone":"+34 952 22 14 75",
    "sg:postcode":"29016",
    "sg:province":"M\u00e1laga",
    "sg:website":"www.ciberactiva.com",
    "wof:name":"Abaco Y Ciberactiva S.l.",
    "wof:placetype":"venue"
},
  "geometry": {"coordinates":[-4.40802,36.71962],"type":"Point"}
}