{
  "type": "Feature",
  "properties": {
    "iso:country":"ES",
    "sg:address":"Calle de Alferez Justino Perti\u00d1ez, 1",
    "sg:city":"Tarifa",
    "sg:classifiers":[
        {
            "category":"Autos & Motor Vehicles",
            "subcategory":"Automobile Sales",
            "type":"Retail Goods"
        }
    ],
    "sg:phone":"+34 956 68 42 57",
    "sg:postcode":"11380",
    "sg:province":"C\u00e1diz",
    "wof:name":"Barrios Moya Ana Isabel",
    "wof:placetype":"venue"
},
  "geometry": {"coordinates":[-5.6025109291,36.0138244629],"type":"Point"}
}