{
  "type": "Feature",
  "properties": {
    "addr:full":"Calle de Urbanos (los), 19 Cenicero La Rioja 26350",
    "addr:housenumber":"19",
    "addr:postcode":"26350",
    "addr:street":"Calle De Urbanos Los;Rioja",
    "iso:country":"ES",
    "sg:address":"Calle de Urbanos (los), 19",
    "sg:city":"Cenicero",
    "sg:orig_category":"Pescader\u00cdas (al Por Menor)",
    "sg:phone":"+34 941 45 40 02",
    "sg:postcode":"26350",
    "sg:province":"La Rioja",
    "wof:name":"Gomez Maestro Alberto",
    "wof:placetype":"venue"
},
  "geometry": {"coordinates":[-2.6427900791,42.4809799194],"type":"Point"}
}