{
  "type": "Feature",
  "properties": {
    "iso:country":"ES",
    "sg:address":"N. Del Rosario, 8",
    "sg:city":"Cullar-vega",
    "sg:orig_category":"Fabricaci\u00d3n De Acumuladores Y De Pilas El\u00c9ctricas",
    "sg:phone":"+34 958 58 02 79",
    "sg:postcode":"18195",
    "sg:province":"Granada",
    "wof:name":"Instalaciones Y Fontaneria Jorge Reinoso S.l.",
    "wof:placetype":"venue"
},
  "geometry": {"coordinates":[-3.6707088947,37.1548995972],"type":"Point"}
}