{
  "type": "Feature",
  "properties": {
    "iso:country":"ES",
    "sg:address":"Av Valles, S/n",
    "sg:city":"Terrassa",
    "sg:orig_category":"Cerrajer\u00cda, Ferrallista",
    "sg:phone":"+34 937 35 05 70",
    "sg:postcode":"08227",
    "sg:province":"Barcelona",
    "wof:name":"Girbau Buxo Carlos",
    "wof:placetype":"venue"
},
  "geometry": {"coordinates":[2.0275709629,41.5820960999],"type":"Point"}
}