{
  "type": "Feature",
  "properties": {
    "addr:full":"Carr Vall D'aran, 2 Tarrega Lleida 25300",
    "addr:housenumber":"2",
    "addr:postcode":"25300",
    "addr:street":"Carr Vall D'Aran",
    "iso:country":"ES",
    "sg:address":"Carr Vall D'aran, 2",
    "sg:city":"Tarrega",
    "sg:orig_category":"Fabricaci\u00d3n, Distribuci\u00d3n De Material Para La Climatizaci\u00d3n, Aireaci\u00d3n Y Ventilaci\u00d3n",
    "sg:phone":"+34 973 50 10 20",
    "sg:postcode":"25300",
    "sg:province":"Lleida",
    "wof:name":"Comercial Valmon S. A.",
    "wof:placetype":"venue"
},
  "geometry": {"coordinates":[1.1588950157,41.6550483704],"type":"Point"}
}