{
  "type": "Feature",
  "properties": {
    "addr:full":"Calle de Evaristo San Miguel, 18 Madrid Madrid 28008",
    "addr:housenumber":"18",
    "addr:postcode":"madrid;28008",
    "addr:street":"Calle De Evaristo San Miguel",
    "iso:country":"ES",
    "sg:address":"Calle de Evaristo San Miguel, 18",
    "sg:city":"Madrid",
    "sg:orig_category":"Edici\u00d3n De Diarios, Revistas, Boletines",
    "sg:phone":"+34 915 42 93 52",
    "sg:postcode":"28008",
    "sg:province":"Madrid",
    "wof:name":"Videocinco S.a.",
    "wof:placetype":"venue"
},
  "geometry": {"coordinates":[-3.7160019875,40.4264297485],"type":"Point"}
}