{
  "type": "Feature",
  "properties": {
    "iso:country":"ES",
    "sg:address":"Calle de San Bernardo, 8",
    "sg:city":"Madrid",
    "sg:orig_category":"Bisuter\u00cda, Joyer\u00cda, Relojer\u00cda (al Por Menor)",
    "sg:phone":"+34 915 21 81 30",
    "sg:postcode":"28015",
    "sg:province":"Madrid",
    "wof:name":"Bajo Marin Emilio",
    "wof:placetype":"venue"
},
  "geometry": {"coordinates":[-3.7058105469,40.429309845],"type":"Point"}
}