{
  "type": "Feature",
  "properties": {
    "addr:full":"Calle de Jose Domingo De Olarte, 9 Vitoria-gasteiz \u00c1lava 01010",
    "addr:housenumber":"9",
    "addr:postcode":"01010",
    "addr:street":"Calle De Jose Domingo De Olarte",
    "iso:country":"ES",
    "sg:address":"Calle de Jose Domingo De Olarte, 9",
    "sg:city":"Vitoria-gasteiz",
    "sg:orig_category":"Molduras, Junquillos, Listones Y Molduras Perforadas",
    "sg:phone":"+34 945 17 38 53",
    "sg:postcode":"01010",
    "sg:province":"\u00c1lava",
    "wof:name":"Bar La Terraza",
    "wof:placetype":"venue"
},
  "geometry": {"coordinates":[-2.6956760883,42.8584480286],"type":"Point"}
}