{
  "type": "Feature",
  "properties": {
    "iso:country":"ES",
    "sg:address":"Pase Blas Cabrera Felipe 'fisico', 12",
    "sg:city":"Palmas De Gran Canaria",
    "sg:orig_category":"Electricidad Veh\u00cdculo",
    "sg:phone":"+34 928 31 15 46",
    "sg:postcode":"35016",
    "sg:province":"Las Palmas",
    "wof:name":"Navarro Almeida Isidoro",
    "wof:placetype":"venue"
},
  "geometry": {"coordinates":[-15.4189300537,28.082736969],"type":"Point"}
}