{
  "type": "Feature",
  "properties": {
    "addr:full":"Calle de Profesor Manuel Cruz, 23 Galdar Las Palmas 35460",
    "addr:housenumber":"23",
    "addr:postcode":"35460",
    "addr:street":"Calle De Profesor Manuel Cruz",
    "iso:country":"ES",
    "sg:address":"Calle de Profesor Manuel Cruz, 23",
    "sg:city":"Galdar",
    "sg:orig_category":"Ambulancias",
    "sg:phone":"+34 928 88 24 05",
    "sg:postcode":"35460",
    "sg:province":"Las Palmas",
    "wof:name":"Ambulancias Garcia Tacoronte S.l.",
    "wof:placetype":"venue"
},
  "geometry": {"coordinates":[-15.6459712982,28.1475162506],"type":"Point"}
}