{
  "type": "Feature",
  "properties": {
    "addr:full":"Talavera, S/n Cebolla Toledo 45550",
    "addr:housenumber":"s / n",
    "addr:postcode":"45550",
    "addr:street":"Talavera",
    "iso:country":"ES",
    "sg:address":"Talavera, S/n",
    "sg:city":"Cebolla",
    "sg:orig_category":"Empresas De Carpinter\u00cda De Madera",
    "sg:phone":"+34 925 86 63 73",
    "sg:postcode":"45550",
    "sg:province":"Toledo",
    "wof:name":"Carpinteria Y Persianas La Picota S.l.",
    "wof:placetype":"venue"
},
  "geometry": {"coordinates":[-4.5719251633,39.9457473755],"type":"Point"}
}