{
  "type": "Feature",
  "properties": {
    "iso:country":"ES",
    "sg:address":"Alam Capuchinos, 7",
    "sg:city":"Carmen",
    "sg:orig_category":"Bisuter\u00cda, Joyer\u00cda, Relojer\u00cda (al Por Menor)",
    "sg:phone":"+34 968 25 49 91",
    "sg:postcode":"30002",
    "sg:province":"Murcia",
    "wof:name":"Tortosa Nieto Genoveva",
    "wof:placetype":"venue"
},
  "geometry": {"coordinates":[-1.1302499771,37.9829597473],"type":"Point"}
}