{
  "type": "Feature",
  "properties": {
    "addr:full":"Carrer de Major, 5 Castelldefels Barcelona 08860",
    "addr:housenumber":"5",
    "addr:postcode":"08860",
    "addr:street":"Carrer De Major",
    "iso:country":"ES",
    "sg:address":"Carrer de Major, 5",
    "sg:city":"Castelldefels",
    "sg:orig_category":"Bazares, Art\u00cdculos De Limpieza Y De Cocina (al Por Menor)",
    "sg:phone":"+34 936 36 59 80",
    "sg:postcode":"08860",
    "sg:province":"Barcelona",
    "wof:name":"Zhang  Yolgjul",
    "wof:placetype":"venue"
},
  "geometry": {"coordinates":[1.9788600206,41.2813682556],"type":"Point"}
}