{
  "type": "Feature",
  "properties": {
    "iso:country":"ES",
    "sg:address":"Luga Ables, 9",
    "sg:city":"Ables",
    "sg:orig_category":"Asilos De Ancianos. Centros Privados",
    "sg:phone":"+34 985 77 19 30",
    "sg:postcode":"33424",
    "sg:province":"Asturias",
    "wof:name":"Residencia 3\u00ba Edad La Familia S.l.",
    "wof:placetype":"venue"
},
  "geometry": {"coordinates":[-5.8513188362,43.4396247864],"type":"Point"}
}