{
  "type": "Feature",
  "properties": {
    "iso:country":"ES",
    "sg:address":"Garagartza Plaza, 8",
    "sg:city":"Ordizia",
    "sg:orig_category":"Hosteler\u00cda, Empleados",
    "sg:phone":"+34 943 16 00 66",
    "sg:postcode":"20240",
    "sg:province":"Guip\u00f9zcoa",
    "wof:name":"Sanz Roa Ana Maria",
    "wof:placetype":"venue"
},
  "geometry": {"coordinates":[-2.1808280945,43.0543861389],"type":"Point"}
}