{
  "type": "Feature",
  "properties": {
    "iso:country":"ES",
    "sg:address":"Carr Aubarca, S/n",
    "sg:city":"Eivissa",
    "sg:orig_category":"Internados & Ense\u00d1anza Privada",
    "sg:phone":"+34 971 31 47 25",
    "sg:postcode":"07800",
    "sg:province":"Islas Baleares",
    "wof:name":"Iniciativas Academicas S.l.",
    "wof:placetype":"venue"
},
  "geometry": {"coordinates":[1.4150664806,38.9128570557],"type":"Point"}
}