{
  "type": "Feature",
  "properties": {
    "iso:country":"ES",
    "sg:address":"Carrer de Mare De Deu Del Coll, 41",
    "sg:city":"Barcelona",
    "sg:orig_category":"Centros M\u00c9dicos Y Sociales, Dispensarios",
    "sg:phone":"+34 932 18 93 02",
    "sg:postcode":"08023",
    "sg:province":"Barcelona",
    "wof:name":"Hermanas Hospitalarias Del Sagrado Corazon De Jesus",
    "wof:placetype":"venue"
},
  "geometry": {"coordinates":[2.1490859985,41.4092674255],"type":"Point"}
}