{
  "type": "Feature",
  "properties": {
    "iso:country":"ES",
    "sg:address":"Carr Migjorn, 25",
    "sg:city":"Bateria",
    "sg:classifiers":[
        {
            "category":"Taxi",
            "type":"Transportation"
        }
    ],
    "sg:phone":"+34 972 38 13 44",
    "sg:postcode":"17490",
    "sg:province":"Girona",
    "wof:name":"Ortiz Vegas Felix",
    "wof:placetype":"venue"
},
  "geometry": {"coordinates":[3.1481759548,42.3640785217],"type":"Point"}
}