{
  "type": "Feature",
  "properties": {
    "iso:country":"ES",
    "sg:address":"C/ Sant Diego Vell, De, 8",
    "sg:city":"Alaior",
    "sg:orig_category":"Peluquer\u00cdas, Peluquer\u00cda Mixta",
    "sg:phone":"+34 971 37 13 18",
    "sg:postcode":"07730",
    "sg:province":"Islas Baleares",
    "wof:name":"Juanico Villalonga Agueda",
    "wof:placetype":"venue"
},
  "geometry": {"coordinates":[4.1383051872,39.93309021],"type":"Point"}
}