{
  "type": "Feature",
  "properties": {
    "iso:country":"ES",
    "sg:address":"Calle de Aguirre Maximo, 16",
    "sg:city":"Bilbao",
    "sg:orig_category":"Venta, Instalaci\u00d3n De Calefacci\u00d3n",
    "sg:phone":"+34 944 39 91 22",
    "sg:postcode":"48011",
    "sg:province":"Vizcaya",
    "wof:name":"Ascensores Ulahi S.a.",
    "wof:placetype":"venue"
},
  "geometry": {"coordinates":[-2.9379014969,43.263256073],"type":"Point"}
}