{
  "type": "Feature",
  "properties": {
    "iso:country":"ES",
    "sg:address":"Calle de Tadeo Pereda, 10",
    "sg:city":"Almansa",
    "sg:orig_category":"Peluquer\u00cdas, Peluquer\u00cda Mixta",
    "sg:phone":"+34 967 34 49 09",
    "sg:postcode":"02640",
    "sg:province":"Albacete",
    "wof:name":"Redondo Garcia Maria Encarnacion",
    "wof:placetype":"venue"
},
  "geometry": {"coordinates":[-1.0969419479,38.8729743958],"type":"Point"}
}