{
  "type": "Feature",
  "properties": {
    "addr:full":"Prje La Solana, 9 Villena Alicante 03400",
    "addr:postcode":"03400",
    "addr:street":"Solana",
    "iso:country":"ES",
    "sg:address":"Prje La Solana, 9",
    "sg:city":"Villena",
    "sg:orig_category":"Freidur\u00cdas",
    "sg:phone":"+34 965 80 71 07",
    "sg:postcode":"03400",
    "sg:province":"Alicante",
    "wof:name":"Snacks El Valle S.l.",
    "wof:placetype":"venue"
},
  "geometry": {"coordinates":[-0.8657540083,38.6356544495],"type":"Point"}
}