{
  "type": "Feature",
  "properties": {
    "addr:full":"Carrer de Emilio Serrano, 4 Palma Islas Baleares 07005",
    "addr:housenumber":"4",
    "addr:postcode":"07005",
    "addr:street":"Carrer De Emilio Serrano",
    "iso:country":"ES",
    "sg:address":"Carrer de Emilio Serrano, 4",
    "sg:city":"Palma",
    "sg:orig_category":"Papeler\u00cdas, Librer\u00cdas",
    "sg:phone":"+34 971 29 83 19",
    "sg:postcode":"07005",
    "sg:province":"Islas Baleares",
    "wof:name":"Pleguezuelos Martinez Ana Maria",
    "wof:placetype":"venue"
},
  "geometry": {"coordinates":[2.6648750305,39.5845108032],"type":"Point"}
}