{
  "type": "Feature",
  "properties": {
    "iso:country":"ES",
    "sg:address":"Calle de Amistad, 8",
    "sg:city":"San Pedro Alcantara",
    "sg:orig_category":"Bordado, Marcado A Medida",
    "sg:phone":"+34 952 78 29 04",
    "sg:postcode":"29670",
    "sg:province":"M\u00e1laga",
    "wof:name":"Bordariz S.l.",
    "wof:placetype":"venue"
},
  "geometry": {"coordinates":[-4.9864258766,36.4906806946],"type":"Point"}
}