{
  "type": "Feature",
  "properties": {
    "iso:country":"ES",
    "sg:address":"Calle de Cullera, 12",
    "sg:city":"Madrid",
    "sg:orig_category":"Cerrajer\u00cda, Ferrallista",
    "sg:phone":"+34 914 61 71 76",
    "sg:postcode":"28047",
    "sg:province":"Madrid",
    "wof:name":"Iberservi Reparaciones S.l.",
    "wof:placetype":"venue"
},
  "geometry": {"coordinates":[-3.7449631691,40.3968887329],"type":"Point"}
}