{
  "type": "Feature",
  "properties": {
    "iso:country":"ES",
    "sg:address":"Ctra Forest, S/n",
    "sg:city":"S. Silvestre Guzman",
    "sg:orig_category":"Agricultura: Abastecimiento Y Cosechado (negocio)",
    "sg:phone":"+34 959 50 21 12",
    "sg:postcode":"21591",
    "sg:province":"Huelva",
    "wof:name":"Monterias De Berastegui S.l.",
    "wof:placetype":"venue"
},
  "geometry": {"coordinates":[-7.347383976,37.3891067505],"type":"Point"}
}