{
  "type": "Feature",
  "properties": {
    "iso:country":"ES",
    "sg:address":"Calle de Batalla De Villaviciosa, 4",
    "sg:city":"Guadalajara",
    "sg:orig_category":"Empresas De Demolici\u00d3n",
    "sg:phone":"+34 949 20 83 44",
    "sg:postcode":"19004",
    "sg:province":"Guadalajara",
    "wof:name":"Esteban Fernandez Aridos Y Excavaciones S.l.",
    "wof:placetype":"venue"
},
  "geometry": {"coordinates":[-3.1851878166,40.6312446594],"type":"Point"}
}