{
  "type": "Feature",
  "properties": {
    "iso:country":"ES",
    "sg:address":"Mayor, 3",
    "sg:city":"Fuentemilanos",
    "sg:orig_category":"Molduras, Junquillos, Listones Y Molduras Perforadas",
    "sg:phone":"+34 921 48 51 07",
    "sg:postcode":"40153",
    "sg:province":"Segovia",
    "wof:name":"Marazuela Orejudo Bego\u00f1a",
    "wof:placetype":"venue"
},
  "geometry": {"coordinates":[-4.2289366722,40.876663208],"type":"Point"}
}