{
  "type": "Feature",
  "properties": {
    "addr:full":"Calle de Pirineos, 45 Madrid Madrid 28040",
    "addr:housenumber":"45",
    "addr:postcode":"madrid;28040",
    "addr:street":"Calle De Pirineos",
    "iso:country":"ES",
    "sg:address":"Calle de Pirineos, 45",
    "sg:city":"Madrid",
    "sg:orig_category":"Arquitectos",
    "sg:phone":"+34 914 50 56 65",
    "sg:postcode":"28040",
    "sg:province":"Madrid",
    "wof:name":"Voluar Arquitectura S.l.",
    "wof:placetype":"venue"
},
  "geometry": {"coordinates":[-3.7180550098,40.4544067383],"type":"Point"}
}