{
  "type": "Feature",
  "properties": {
    "iso:country":"ES",
    "sg:address":"Carr Doctor Fleming, 66",
    "sg:city":"Vilanova I La Geltru",
    "sg:orig_category":"C\u00c1maras De Comercio E Industria, Oficios, Agricultura",
    "sg:phone":"+34 938 16 00 00",
    "sg:postcode":"08800",
    "sg:province":"Barcelona",
    "wof:name":"Incofisa Webservice S.l.",
    "wof:placetype":"venue"
},
  "geometry": {"coordinates":[1.7222479582,41.2198524475],"type":"Point"}
}