{
  "type": "Feature",
  "properties": {
    "addr:full":"Castillo De Ribadavia, 824 Parque Castillas Guadalajara 19174",
    "addr:housenumber":"824",
    "addr:postcode":"19174",
    "addr:street":"Parque",
    "iso:country":"ES",
    "sg:address":"Castillo De Ribadavia, 824",
    "sg:city":"Parque Castillas",
    "sg:orig_category":"Organizaciones Profesionales",
    "sg:phone":"+34 949 32 75 52",
    "sg:postcode":"19174",
    "sg:province":"Guadalajara",
    "wof:name":"Tejedor Tejedor Pilar",
    "wof:placetype":"venue"
},
  "geometry": {"coordinates":[-3.336879015,40.6445465088],"type":"Point"}
}