{
  "type": "Feature",
  "properties": {
    "iso:country":"ES",
    "sg:address":"Ctra Vic, 60",
    "sg:city":"Garriga",
    "sg:orig_category":"Muebles, Minoristas",
    "sg:phone":"+34 938 71 45 12",
    "sg:postcode":"08530",
    "sg:province":"Barcelona",
    "wof:name":"Consorci Del Moble S.l.",
    "wof:placetype":"venue"
},
  "geometry": {"coordinates":[2.2851901054,41.7017440796],"type":"Point"}
}