{
  "type": "Feature",
  "properties": {
    "addr:full":"Avda Zamora (de), 146 Ourense Ourense 32005",
    "addr:housenumber":"146",
    "addr:postcode":"32005",
    "addr:street":"Avda Zamora De",
    "iso:country":"ES",
    "sg:address":"Avda Zamora (de), 146",
    "sg:city":"Ourense",
    "sg:orig_category":"Peluquer\u00cdas",
    "sg:phone":"+34 988 24 44 06",
    "sg:postcode":"32005",
    "sg:province":"Ourense",
    "wof:name":"Freire Guede Susana",
    "wof:placetype":"venue"
},
  "geometry": {"coordinates":[-7.8625049591,42.3205490112],"type":"Point"}
}