{
  "type": "Feature",
  "properties": {
    "addr:full":"Calle de Villafranca, 1 Madrid Madrid 28028",
    "addr:housenumber":"1",
    "addr:postcode":"28028",
    "addr:street":"Calle De Villafranca",
    "iso:country":"ES",
    "sg:address":"Calle de Villafranca, 1",
    "sg:city":"Madrid",
    "sg:orig_category":"Venta, Montaje De Neum\u00c1ticos",
    "sg:phone":"+34 913 55 10 81",
    "sg:postcode":"28028",
    "sg:province":"Madrid",
    "wof:name":"Serrano Visiedo Antonio",
    "wof:placetype":"venue"
},
  "geometry": {"coordinates":[-3.6653499603,40.4336357117],"type":"Point"}
}