{
  "type": "Feature",
  "properties": {
    "addr:full":"Urba Vileta De Mar, 5 Vileta De Mar Tarragona 43007",
    "addr:housenumber":"5",
    "addr:postcode":"43007",
    "addr:street":"Vileta De Mar",
    "iso:country":"ES",
    "sg:address":"Urba Vileta De Mar, 5",
    "sg:city":"Vileta De Mar",
    "sg:orig_category":"Restaurantes",
    "sg:phone":"+34 977 29 01 99",
    "sg:postcode":"43007",
    "sg:province":"Tarragona",
    "wof:name":"Can Bonachi S.l.",
    "wof:placetype":"venue"
},
  "geometry": {"coordinates":[1.2779040337,41.1217727661],"type":"Point"}
}