{
  "type": "Feature",
  "properties": {
    "iso:country":"ES",
    "sg:address":"Calle de Gaudi, 19",
    "sg:city":"Estepona",
    "sg:orig_category":"Carnes De Carnicer\u00cda (al Por Mayor)",
    "sg:phone":"+34 952 79 58 23",
    "sg:postcode":"29680",
    "sg:province":"M\u00e1laga",
    "wof:name":"Carnes Rojo Y Asociados S.l.",
    "wof:placetype":"venue"
},
  "geometry": {"coordinates":[-5.1673169136,36.4296302795],"type":"Point"}
}