{
  "type": "Feature",
  "properties": {
    "addr:full":"Calle de San Antonio, 42 Yecla Murcia 30510",
    "addr:housenumber":"42",
    "addr:postcode":"30510",
    "addr:street":"Calle De San Antonio",
    "iso:country":"ES",
    "sg:address":"Calle de San Antonio, 42",
    "sg:city":"Yecla",
    "sg:orig_category":"Centros De Educaci\u00d3n Especial",
    "sg:phone":"+34 968 79 14 46",
    "sg:postcode":"30510",
    "sg:province":"Murcia",
    "wof:name":"Colegio Publico San Jose De Calasanz",
    "wof:placetype":"venue"
},
  "geometry": {"coordinates":[-1.1129629612,38.6124725342],"type":"Point"}
}