{
  "type": "Feature",
  "properties": {
    "addr:full":"Calle de Orixe, 22 Bilbao Vizcaya 48015",
    "addr:housenumber":"22",
    "addr:postcode":"48015",
    "addr:street":"Calle De Orixe",
    "iso:country":"ES",
    "sg:address":"Calle de Orixe, 22",
    "sg:city":"Bilbao",
    "sg:orig_category":"Molduras, Junquillos, Listones Y Molduras Perforadas",
    "sg:phone":"+34 944 47 34 06",
    "sg:postcode":"48015",
    "sg:province":"Vizcaya",
    "wof:name":"Cesar Sanchez Alonso Y Benjamin Monta\u00f1a Estevez Cdad",
    "wof:placetype":"venue"
},
  "geometry": {"coordinates":[-2.95885396,43.2803611755],"type":"Point"}
}