{
  "type": "Feature",
  "properties": {
    "iso:country":"ES",
    "sg:address":"Calle de Castillo (del), 4",
    "sg:city":"Barbastro",
    "sg:classifiers":[
        {
            "category":"Taxi",
            "type":"Transportation"
        }
    ],
    "sg:phone":"+34 974 31 15 86",
    "sg:postcode":"22300",
    "sg:province":"Huesca",
    "wof:name":"Sampietro Ayerbe Antonio",
    "wof:placetype":"venue"
},
  "geometry": {"coordinates":[0.1260388941,42.0340309143],"type":"Point"}
}