{
  "type": "Feature",
  "properties": {
    "addr:full":"Calle de Eras (las), 29 Montalban De Cordoba C\u00f3rdoba 14548",
    "addr:housenumber":"29",
    "addr:postcode":"14548",
    "addr:street":"Calle De Eras Las;Co\u0301Rdoba",
    "iso:country":"ES",
    "sg:address":"Calle de Eras (las), 29",
    "sg:city":"Montalban De Cordoba",
    "sg:orig_category":"Bares, Piano",
    "sg:phone":"+34 957 31 10 47",
    "sg:postcode":"14548",
    "sg:province":"C\u00f3rdoba",
    "wof:name":"Almacenes Maestre S.l.",
    "wof:placetype":"venue"
},
  "geometry": {"coordinates":[-4.7512230873,37.5754470825],"type":"Point"}
}