{
  "type": "Feature",
  "properties": {
    "iso:country":"ES",
    "sg:address":"Carrer de Casal Dels Mogoda, 44",
    "sg:city":"Florida",
    "sg:orig_category":"Promotores Constructores",
    "sg:phone":"+34 935 44 80 03",
    "sg:postcode":"08130",
    "sg:province":"Barcelona",
    "wof:name":"Tenencia De Solares S. L.",
    "wof:placetype":"venue"
},
  "geometry": {"coordinates":[2.1863150597,41.5187606812],"type":"Point"}
}