{
  "type": "Feature",
  "properties": {
    "iso:country":"ES",
    "sg:address":"Carrer de Francisco Martinez Ots, 5",
    "sg:city":"Mutxamel",
    "sg:orig_category":"M\u00dasica Diversa",
    "sg:phone":"+34 965 95 54 18",
    "sg:postcode":"03110",
    "sg:province":"Alicante",
    "wof:name":"Sociedad Musical La Alianza",
    "wof:placetype":"venue"
},
  "geometry": {"coordinates":[-0.445333004,38.4152679443],"type":"Point"}
}