{
  "type": "Feature",
  "properties": {
    "addr:full":"Calle de Isabelita Usera, 36 Madrid Madrid 28026",
    "addr:housenumber":"36",
    "addr:postcode":"madrid;28026",
    "addr:street":"Calle De Isabelita Usera",
    "iso:country":"ES",
    "sg:address":"Calle de Isabelita Usera, 36",
    "sg:city":"Madrid",
    "sg:orig_category":"Comercio, Reparaci\u00d3n De Bicicletas, De Motocicletas, De Accesorios",
    "sg:phone":"+34 914 75 02 19",
    "sg:postcode":"28026",
    "sg:province":"Madrid",
    "sg:website":"www.usera.arrakis.es",
    "wof:name":"Mu\u00f1oz Felipe Julian",
    "wof:placetype":"venue"
},
  "geometry": {"coordinates":[-3.7079770565,40.3833389282],"type":"Point"}
}