{
  "type": "Feature",
  "properties": {
    "addr:full":"Calle de Granada, 1 Peligros Granada 18210",
    "addr:housenumber":"1",
    "addr:postcode":"18210",
    "addr:street":"Calle De Granada",
    "iso:country":"ES",
    "sg:address":"Calle de Granada, 1",
    "sg:city":"Peligros",
    "sg:orig_category":"Fabricaci\u00d3n De Tapices Y Moquetas Para Suelos Y Paredes",
    "sg:phone":"+34 958 40 53 51",
    "sg:postcode":"18210",
    "sg:province":"Granada",
    "wof:name":"Revestimientos Arevimsa S.l.",
    "wof:placetype":"venue"
},
  "geometry": {"coordinates":[-3.6286890507,37.2269859314],"type":"Point"}
}