{
  "type": "Feature",
  "properties": {
    "iso:country":"ES",
    "sg:address":"Calle de Abella, 20",
    "sg:city":"Madrid",
    "sg:orig_category":"Servicio De Salud",
    "sg:phone":"+34 915 08 39 44",
    "sg:postcode":"28044",
    "sg:province":"Madrid",
    "wof:name":"Martin Fernandez Santiago",
    "wof:placetype":"venue"
},
  "geometry": {"coordinates":[-3.7538487911,40.370677948],"type":"Point"}
}