{
  "type": "Feature",
  "properties": {
    "addr:full":"Carrer de Muntaner, 458 Barcelona Barcelona 08006",
    "addr:housenumber":"458",
    "addr:postcode":"08006",
    "addr:street":"Carrer De Muntaner",
    "iso:country":"ES",
    "sg:address":"Carrer de Muntaner, 458",
    "sg:city":"Barcelona",
    "sg:orig_category":"Carnicer\u00cdas, Carnicer\u00cdas",
    "sg:phone":"+34 932 01 91 89",
    "sg:postcode":"08006",
    "sg:province":"Barcelona",
    "wof:name":"Cortes Gil Ricardo",
    "wof:placetype":"venue"
},
  "geometry": {"coordinates":[2.1393840313,41.4019165039],"type":"Point"}
}