{
  "type": "Feature",
  "properties": {
    "addr:full":"Av Catalunya, 64 S. Adria Besos Barcelona 08930",
    "addr:housenumber":"64",
    "addr:postcode":"08930",
    "addr:street":"Av Catalunya;S. Adria Besos Barcelona",
    "iso:country":"ES",
    "sg:address":"Av Catalunya, 64",
    "sg:city":"S. Adria Besos",
    "sg:orig_category":"Dietistas",
    "sg:phone":"+34 933 81 95 93",
    "sg:postcode":"08930",
    "sg:province":"Barcelona",
    "wof:name":"Prats Chaves Rosa Maria",
    "wof:placetype":"venue"
},
  "geometry": {"coordinates":[2.2192280293,41.4303855896],"type":"Point"}
}