{
  "type": "Feature",
  "properties": {
    "addr:full":"Calle de San Francisco, 6 Alcora Castell\u00f3n 12110",
    "addr:housenumber":"6",
    "addr:postcode":"12110",
    "addr:street":"Calle De San Francisco;Castello\u0301N",
    "iso:country":"ES",
    "sg:address":"Calle de San Francisco, 6",
    "sg:city":"Alcora",
    "sg:orig_category":"M\u00c9dicos: Estomatolog\u00cda",
    "sg:phone":"+34 964 36 34 00",
    "sg:postcode":"12110",
    "sg:province":"Castell\u00f3n",
    "wof:name":"Salvador Badenes Sara",
    "wof:placetype":"venue"
},
  "geometry": {"coordinates":[-0.2135999948,40.0743865967],"type":"Point"}
}