{
  "type": "Feature",
  "properties": {
    "iso:country":"ES",
    "sg:address":"Calle de Bilbao, S/n",
    "sg:city":"Placa",
    "sg:orig_category":"Negocio De Madera",
    "sg:phone":"+34 987 41 59 38",
    "sg:postcode":"24400",
    "sg:province":"Le\u00f3n",
    "wof:name":"Jose De Ezpeleta S. A.",
    "wof:placetype":"venue"
},
  "geometry": {"coordinates":[-5.5717520714,42.5998764038],"type":"Point"}
}