{
  "type": "Feature",
  "properties": {
    "addr:full":"Calle de Carquizano, 8 Donostia-san Sebastian Guip\u00f9zcoa 20001",
    "addr:housenumber":"8",
    "addr:postcode":"20001",
    "addr:street":"Calle De Carquizano",
    "iso:country":"ES",
    "sg:address":"Calle de Carquizano, 8",
    "sg:city":"Donostia-san Sebastian",
    "sg:orig_category":"Peluqueros: De Se\u00d1oras",
    "sg:phone":"+34 943 27 13 61",
    "sg:postcode":"20001",
    "sg:province":"Guip\u00f9zcoa",
    "wof:name":"Fernandez Mendizabal Maria Del Pilar",
    "wof:placetype":"venue"
},
  "geometry": {"coordinates":[-1.9732723236,43.3228111267],"type":"Point"}
}