{
  "type": "Feature",
  "properties": {
    "addr:full":"Avda Constitucion (de La), 19 Granada Granada 18014",
    "addr:housenumber":"19",
    "addr:postcode":"18014",
    "addr:street":"Avda Constitucion De La",
    "iso:country":"ES",
    "sg:address":"Avda Constitucion (de La), 19",
    "sg:city":"Granada",
    "sg:orig_category":"Farmacias",
    "sg:phone":"+34 958 27 02 34",
    "sg:postcode":"18014",
    "sg:province":"Granada",
    "wof:name":"Gomez Medina Maria Del Carmen",
    "wof:placetype":"venue"
},
  "geometry": {"coordinates":[-3.6064839363,37.1849060059],"type":"Point"}
}