{
  "type": "Feature",
  "properties": {
    "addr:full":"Calle de Juan Montilla, 12 Jaen Ja\u00e9n 23002",
    "addr:housenumber":"12;jae\u0301n",
    "addr:postcode":"23002",
    "addr:street":"Calle De Juan Montilla",
    "iso:country":"ES",
    "sg:address":"Calle de Juan Montilla, 12",
    "sg:city":"Jaen",
    "sg:orig_category":"Molduras, Junquillos, Listones Y Molduras Perforadas",
    "sg:phone":"+34 953 23 10 39",
    "sg:postcode":"23002",
    "sg:province":"Ja\u00e9n",
    "wof:name":"Montejo Nobel Enrique",
    "wof:placetype":"venue"
},
  "geometry": {"coordinates":[-3.7949678898,37.7613868713],"type":"Point"}
}