{
  "type": "Feature",
  "properties": {
    "iso:country":"ES",
    "sg:address":"Carrer de Notari Jesus Led, 9",
    "sg:city":"Sentmenat",
    "sg:orig_category":"Panader\u00cdas, Panader\u00cdas",
    "sg:phone":"+34 937 15 47 09",
    "sg:postcode":"08181",
    "sg:province":"Barcelona",
    "wof:name":"Pasteleria Tribo S.l.l.",
    "wof:placetype":"venue"
},
  "geometry": {"coordinates":[2.1413600445,41.6114768982],"type":"Point"}
}