{
  "type": "Feature",
  "properties": {
    "addr:full":"Calle de Preciados, 42 Madrid Madrid 28013",
    "addr:housenumber":"42",
    "addr:postcode":"madrid;28013",
    "addr:street":"Calle De Preciados",
    "iso:country":"ES",
    "sg:address":"Calle de Preciados, 42",
    "sg:city":"Madrid",
    "sg:orig_category":"Peluqueros: De Se\u00d1oras",
    "sg:phone":"+34 915 48 45 25",
    "sg:postcode":"28013",
    "sg:province":"Madrid",
    "wof:name":"Fernandez Yorente Claudina",
    "wof:placetype":"venue"
},
  "geometry": {"coordinates":[-3.7073259354,40.4199066162],"type":"Point"}
}