{
  "type": "Feature",
  "properties": {
    "iso:country":"ES",
    "sg:address":"Calle de Sierra Cabo De Gata, S/n",
    "sg:city":"Viator",
    "sg:orig_category":"Puros, Cigarrillos Y Tabaco (fabricaci\u00d3n, Al Por Mayor)",
    "sg:phone":"+34 950 30 62 48",
    "sg:postcode":"04240",
    "sg:province":"Almer\u00eda",
    "wof:name":"Fernandez Francisco Gabriel",
    "wof:placetype":"venue"
},
  "geometry": {"coordinates":[-2.4226388931,36.8810195923],"type":"Point"}
}