{
  "type": "Feature",
  "properties": {
    "addr:full":"Larra\u00f1eta, S/n Lakuntza Navarra 31830",
    "addr:postcode":"31830",
    "addr:street":"Larran\u0303Eta S / N Lakuntza Navarra",
    "iso:country":"ES",
    "sg:address":"Larra\u00f1eta, S/n",
    "sg:city":"Lakuntza",
    "sg:orig_category":"Alimentaci\u00d3n General (al Por Menor)",
    "sg:phone":"+34 948 57 62 46",
    "sg:postcode":"31830",
    "sg:province":"Navarra",
    "wof:name":"Arregui Razquin Juncal Y Susana",
    "wof:placetype":"venue"
},
  "geometry": {"coordinates":[-2.0393605232,42.9112510681],"type":"Point"}
}