{
  "type": "Feature",
  "properties": {
    "addr:full":"Carrer de Caputxins, 16 Manresa Barcelona 08241",
    "addr:housenumber":"16",
    "addr:postcode":"08241",
    "addr:street":"Carrer De Caputxins",
    "iso:country":"ES",
    "sg:address":"Carrer de Caputxins, 16",
    "sg:city":"Manresa",
    "sg:orig_category":"Seguridad En El Trabajo Y Prevenci\u00d3n De Riesgos Laborales",
    "sg:phone":"+34 938 78 71 61",
    "sg:postcode":"08241",
    "sg:province":"Barcelona",
    "wof:name":"Prevencio I Salut Del Bages Sl",
    "wof:placetype":"venue"
},
  "geometry": {"coordinates":[1.8321199417,41.7228126526],"type":"Point"}
}