{
  "type": "Feature",
  "properties": {
    "addr:full":"Calle de Instituto, S/n Villaca\u00f1as Toledo 45860",
    "addr:housenumber":"s / n",
    "addr:postcode":"45860",
    "addr:street":"Calle De Instituto",
    "iso:country":"ES",
    "sg:address":"Calle de Instituto, S/n",
    "sg:city":"Villaca\u00f1as",
    "sg:orig_category":"Centros De Educaci\u00d3n Especial",
    "sg:phone":"+34 925 16 05 41",
    "sg:postcode":"45860",
    "sg:province":"Toledo",
    "wof:name":"Colegio Publico Santa Barbara",
    "wof:placetype":"venue"
},
  "geometry": {"coordinates":[-3.3337590694,39.6166343689],"type":"Point"}
}