{
  "type": "Feature",
  "properties": {
    "addr:full":"Extramuros Norte, S/n Elciego \u00c1lava 01340",
    "addr:housenumber":"s / n",
    "addr:postcode":"01340",
    "addr:street":"Norte",
    "iso:country":"ES",
    "sg:address":"Extramuros Norte, S/n",
    "sg:city":"Elciego",
    "sg:orig_category":"Aceros Inoxidables",
    "sg:phone":"+34 945 60 62 11",
    "sg:postcode":"01340",
    "sg:province":"\u00c1lava",
    "wof:name":"Condesa Fabril S.a.",
    "wof:placetype":"venue"
},
  "geometry": {"coordinates":[-2.6165890694,42.5141601562],"type":"Point"}
}