{
  "type": "Feature",
  "properties": {
    "addr:full":"Calle de Ramon Franco, 2 Cangas Pontevedra 36940",
    "addr:housenumber":"2",
    "addr:postcode":"36940",
    "addr:street":"Calle De Ramon Franco",
    "iso:country":"ES",
    "sg:address":"Calle de Ramon Franco, 2",
    "sg:city":"Cangas",
    "sg:orig_category":"Partidos Pol\u00cdticos",
    "sg:phone":"+34 986 30 28 37",
    "sg:postcode":"36940",
    "sg:province":"Pontevedra",
    "wof:name":"Partido Popular",
    "wof:placetype":"venue"
},
  "geometry": {"coordinates":[-8.7851219177,42.2648277283],"type":"Point"}
}