{
  "type": "Feature",
  "properties": {
    "iso:country":"ES",
    "sg:address":"Calle de Gerona, 6",
    "sg:city":"Benidorm",
    "sg:orig_category":"Molduras, Junquillos, Listones Y Molduras Perforadas",
    "sg:phone":"+34 966 80 20 55",
    "sg:postcode":"03500",
    "sg:province":"Alicante",
    "wof:name":"Judge  Graham",
    "wof:placetype":"venue"
},
  "geometry": {"coordinates":[-0.1221930012,38.5379638672],"type":"Point"}
}