{
  "type": "Feature",
  "properties": {
    "iso:country":"ES",
    "sg:address":"Avda De Castelao, 61",
    "sg:city":"Ponteareas",
    "sg:orig_category":"Estudios, Instalaci\u00d3n De Climatizaci\u00d3n",
    "sg:phone":"+34 986 64 44 55",
    "sg:postcode":"36860",
    "sg:province":"Pontevedra",
    "sg:website":"www.thermoclima.net",
    "wof:name":"Thermoclima Europa S.l.",
    "wof:placetype":"venue"
},
  "geometry": {"coordinates":[-8.5092916489,42.174369812],"type":"Point"}
}