{
  "type": "Feature",
  "properties": {
    "addr:full":"Carr Annibal, 15 Eivissa Islas Baleares 07800",
    "addr:housenumber":"15",
    "addr:postcode":"07800",
    "addr:street":"Carr Annibal",
    "iso:country":"ES",
    "sg:address":"Carr Annibal, 15",
    "sg:city":"Eivissa",
    "sg:orig_category":"Bisuter\u00cda, Joyer\u00cda, Relojer\u00cda (al Por Menor)",
    "sg:phone":"+34 971 31 41 80",
    "sg:postcode":"07800",
    "sg:province":"Islas Baleares",
    "wof:name":"Avrahami  Lior",
    "wof:placetype":"venue"
},
  "geometry": {"coordinates":[1.4188899994,38.9061164856],"type":"Point"}
}