{
  "type": "Feature",
  "properties": {
    "addr:full":"Pg Industria, 39 Banyoles Girona 17820",
    "addr:housenumber":"39",
    "addr:postcode":"17820",
    "addr:street":"Industria",
    "iso:country":"ES",
    "sg:address":"Pg Industria, 39",
    "sg:city":"Banyoles",
    "sg:orig_category":"Papeler\u00cdas, Librer\u00cdas",
    "sg:phone":"+34 972 58 29 45",
    "sg:postcode":"17820",
    "sg:province":"Girona",
    "wof:name":"Tecnicopi Digital Imatges S.l.",
    "wof:placetype":"venue"
},
  "geometry": {"coordinates":[2.7630081177,42.1162376404],"type":"Point"}
}