{
  "type": "Feature",
  "properties": {
    "iso:country":"ES",
    "sg:address":"Anejo De Fuente De Cesna, S/n",
    "sg:city":"Fuentes Cesna",
    "sg:orig_category":"Aceites Y Grasas Alimentarias (fabricaci\u00d3n, Al Por Mayor)",
    "sg:phone":"+34 958 34 82 07",
    "sg:postcode":"18295",
    "sg:province":"Granada",
    "wof:name":"Aceites Fuente Cesna S.c.a.",
    "wof:placetype":"venue"
},
  "geometry": {"coordinates":[-3.5979290009,37.176486969],"type":"Point"}
}