{
  "type": "Feature",
  "properties": {
    "iso:country":"ES",
    "sg:address":"Calle de Pio Loperena, 2",
    "sg:city":"Burlada",
    "sg:orig_category":"Telas Y Sedas (al Por Menor)",
    "sg:phone":"+34 948 14 76 23",
    "sg:postcode":"31600",
    "sg:province":"Navarra",
    "wof:name":"Balda Echeguia Maria Lourdes",
    "wof:placetype":"venue"
},
  "geometry": {"coordinates":[-1.6175404787,42.8245620728],"type":"Point"}
}