{
  "type": "Feature",
  "properties": {
    "iso:country":"ES",
    "sg:address":"Calle de Maudes, 26",
    "sg:city":"Madrid",
    "sg:orig_category":"Relojer\u00cda (al Por Menor, Reparaci\u00d3n)",
    "sg:phone":"+34 915 54 72 49",
    "sg:postcode":"28003",
    "sg:province":"Madrid",
    "wof:name":"Valempa Servicio Tecnico S.l.",
    "wof:placetype":"venue"
},
  "geometry": {"coordinates":[-3.7002079487,40.4451217651],"type":"Point"}
}