{
  "type": "Feature",
  "properties": {
    "addr:full":"Carrer de Maria Cubi, 126 Barcelona Barcelona 08021",
    "addr:housenumber":"126",
    "addr:postcode":"08021",
    "addr:street":"Carrer De Maria Cubi",
    "iso:country":"ES",
    "sg:address":"Carrer de Maria Cubi, 126",
    "sg:city":"Barcelona",
    "sg:orig_category":"Cajas De Ahorro",
    "sg:phone":"+34 932 00 27 65",
    "sg:postcode":"08021",
    "sg:province":"Barcelona",
    "wof:name":"Caixa D'estalvis I Pensions De Barcelona",
    "wof:placetype":"venue"
},
  "geometry": {"coordinates":[2.1460330486,41.3962898254],"type":"Point"}
}