{
  "type": "Feature",
  "properties": {
    "addr:full":"Calle de Virgen Del Pilar, 30 Palmas De Gran Canaria Las Palmas 35012",
    "addr:housenumber":"30",
    "addr:postcode":"35012",
    "addr:street":"Calle De Virgen Del Pilar",
    "iso:country":"ES",
    "sg:address":"Calle de Virgen Del Pilar, 30",
    "sg:city":"Palmas De Gran Canaria",
    "sg:orig_category":"Venta, Localizaci\u00d3n, Reparaci\u00d3n De Material E Instrumental M\u00c9dico",
    "sg:phone":"+34 928 42 76 85",
    "sg:postcode":"35012",
    "sg:province":"Las Palmas",
    "wof:name":"Medican S.l.",
    "wof:placetype":"venue"
},
  "geometry": {"coordinates":[-15.4444255829,28.1167316437],"type":"Point"}
}