{
  "type": "Feature",
  "properties": {
    "iso:country":"ES",
    "sg:address":"Avda Barcelona, 18",
    "sg:city":"Guadalajara",
    "sg:orig_category":"Pescader\u00cdas (al Por Menor)",
    "sg:phone":"+34 949 25 52 62",
    "sg:postcode":"19005",
    "sg:province":"Guadalajara",
    "wof:name":"Pescaderias Mata S.l.",
    "wof:placetype":"venue"
},
  "geometry": {"coordinates":[-3.1575200558,40.6344108582],"type":"Point"}
}