{
  "type": "Feature",
  "properties": {
    "addr:full":"Calle de Isidoro Luz, 10 Santa Ursula Santa Cruz De Tenerife 38390",
    "addr:housenumber":"10",
    "addr:postcode":"38390",
    "addr:street":"Calle De Isidoro Luz",
    "iso:country":"ES",
    "sg:address":"Calle de Isidoro Luz, 10",
    "sg:city":"Santa Ursula",
    "sg:orig_category":"Confecci\u00d3n De Uniformes",
    "sg:phone":"+34 922 30 45 32",
    "sg:postcode":"38390",
    "sg:province":"Santa Cruz De Tenerife",
    "wof:name":"Uniformes Del Atlantico S.l.",
    "wof:placetype":"venue"
},
  "geometry": {"coordinates":[-16.4882984161,28.4260005951],"type":"Point"}
}