{
  "type": "Feature",
  "properties": {
    "iso:country":"ES",
    "sg:address":"Calle de Vi\u00d1a, 3",
    "sg:city":"Santovenia Pisuerga",
    "sg:orig_category":"Pintura, Barniz, Productos Asimilables (fabricaci\u00d3n, Al Por Mayor)",
    "sg:phone":"+34 983 40 01 50",
    "sg:postcode":"47155",
    "sg:province":"Valladolid",
    "wof:name":"Dosuna Mancebo Marcelino Benito",
    "wof:placetype":"venue"
},
  "geometry": {"coordinates":[-4.6871137619,41.6903953552],"type":"Point"}
}