{
  "type": "Feature",
  "properties": {
    "iso:country":"ES",
    "sg:address":"Carrer de Mallorca, 126",
    "sg:city":"Barcelona",
    "sg:orig_category":"Aparcamientos (infraestructuras, Accesorios)",
    "sg:phone":"+34 934 51 42 58",
    "sg:postcode":"08036",
    "sg:province":"Barcelona",
    "wof:name":"Rosell Canals Esteban",
    "wof:placetype":"venue"
},
  "geometry": {"coordinates":[2.1533789635,41.3867225647],"type":"Point"}
}