{
  "type": "Feature",
  "properties": {
    "addr:full":"Ctra. Majadahonda, Km. 0002,0 Pozuelo Madrid 28223",
    "addr:postcode":"28223",
    "addr:street":"Ctra. Majadahonda Km. 0002,0",
    "iso:country":"ES",
    "sg:address":"Ctra. Majadahonda, Km. 0002,0",
    "sg:city":"Pozuelo",
    "sg:orig_category":"Limpieza Industrial",
    "sg:phone":"+34 913 52 91 25",
    "sg:postcode":"28223",
    "sg:province":"Madrid",
    "wof:name":"Artesa S.l.",
    "wof:placetype":"venue"
},
  "geometry": {"coordinates":[-3.8355491161,40.437713623],"type":"Point"}
}