{
  "type": "Feature",
  "properties": {
    "addr:full":"Po S'alamera, 11 Sta. Eularia Riu Islas Baleares 07840",
    "addr:housenumber":"11",
    "addr:postcode":"07840",
    "addr:street":"S'Alamera;Baleares",
    "iso:country":"ES",
    "sg:address":"Po S'alamera, 11",
    "sg:city":"Sta. Eularia Riu",
    "sg:orig_category":"Laboratorios Y Trabajos De Fotograf\u00cda, V\u00cddeo Y Cine",
    "sg:phone":"+34 971 33 82 21",
    "sg:postcode":"07840",
    "sg:province":"Islas Baleares",
    "sg:website":"www.fotoprix.es",
    "wof:name":"Magic Pic S.l",
    "wof:placetype":"venue"
},
  "geometry": {"coordinates":[2.9117100239,39.6136398315],"type":"Point"}
}