{
  "type": "Feature",
  "properties": {
    "iso:country":"ES",
    "sg:address":"Calle de Payo Gomez, 11",
    "sg:city":"Coru\u00d1a",
    "sg:orig_category":"Radiocomunicaciones, Telefon\u00cda M\u00d3vil, Radiomensajer\u00cda: Servicios, Comercializaci\u00d3n",
    "sg:phone":"+34 981 22 21 11",
    "sg:postcode":"15004",
    "sg:province":"A Coru\u00f1a",
    "sg:website":"www.telyco.es",
    "wof:name":"Teleinformatica Y Comunicaciones S.a.",
    "wof:placetype":"venue"
},
  "geometry": {"coordinates":[-8.4072313309,43.3670120239],"type":"Point"}
}