{
  "type": "Feature",
  "properties": {
    "addr:full":"Calle de Ciudad De La Habana, 9 Valladolid Valladolid 47014",
    "addr:housenumber":"9",
    "addr:postcode":"47014",
    "addr:street":"Calle De Ciudad De La Habana",
    "iso:country":"ES",
    "sg:address":"Calle de Ciudad De La Habana, 9",
    "sg:city":"Valladolid",
    "sg:orig_category":"Inform\u00c1tica: Soportes De Informaci\u00d3n, Suministros & Accesorios",
    "sg:phone":"+34 983 33 80 69",
    "sg:postcode":"47014",
    "sg:province":"Valladolid",
    "wof:name":"Jump Ordenadores S.l.",
    "wof:placetype":"venue"
},
  "geometry": {"coordinates":[-4.7610454559,41.636013031],"type":"Point"}
}