{
  "type": "Feature",
  "properties": {
    "addr:full":"Alxibre E Grova, S/n Rodrigas Lugo 27744",
    "addr:housenumber":"s / n",
    "addr:postcode":"27744",
    "iso:country":"ES",
    "sg:address":"Alxibre E Grova, S/n",
    "sg:city":"Rodrigas",
    "sg:orig_category":"Comercio, Reparaci\u00d3n De Motocicletas, Bicicletas Y Piezas Sueltas",
    "sg:phone":"+34 982 34 63 76",
    "sg:postcode":"27744",
    "sg:province":"Lugo",
    "wof:name":"Gonzalez Reimonde Ramon",
    "wof:placetype":"venue"
},
  "geometry": {"coordinates":[-7.2599711418,43.3427810669],"type":"Point"}
}