{
  "type": "Feature",
  "properties": {
    "iso:country":"ES",
    "sg:address":"Carrer de Rafael De Casanova, 15",
    "sg:city":"Molins Rei",
    "sg:orig_category":"Mercer\u00cda, Lencer\u00cda (al Por Menor)",
    "sg:phone":"+34 936 68 53 55",
    "sg:postcode":"08750",
    "sg:province":"Barcelona",
    "wof:name":"Lozano Campesino Rosa Pia",
    "wof:placetype":"venue"
},
  "geometry": {"coordinates":[2.0182209015,41.4109077454],"type":"Point"}
}