{
  "type": "Feature",
  "properties": {
    "iso:country":"ES",
    "sg:address":"Avda Aguirre Lehendakari, 11",
    "sg:city":"Bilbao",
    "sg:orig_category":"Asistencia Social",
    "sg:phone":"+34 944 75 76 71",
    "sg:postcode":"48014",
    "sg:province":"Vizcaya",
    "wof:name":"Agintzari S Coop",
    "wof:placetype":"venue"
},
  "geometry": {"coordinates":[-2.9476065636,43.2718811035],"type":"Point"}
}