{
  "type": "Feature",
  "properties": {
    "iso:country":"ES",
    "sg:address":"Pg Marques De Camps, 7",
    "sg:city":"Salt",
    "sg:orig_category":"Caf\u00c9s, Bares, Cervecer\u00cdas",
    "sg:phone":"+34 972 23 94 17",
    "sg:postcode":"17190",
    "sg:province":"Girona",
    "wof:name":"Cabrera Sanchez Manuel",
    "wof:placetype":"venue"
},
  "geometry": {"coordinates":[2.7860798836,41.9734039307],"type":"Point"}
}