{
  "type": "Feature",
  "properties": {
    "iso:country":"ES",
    "sg:address":"Calle de Ander Deuna, 8",
    "sg:city":"Usansolo",
    "sg:orig_category":"Reposter\u00cdas",
    "sg:phone":"+34 944 56 77 79",
    "sg:postcode":"48960",
    "sg:province":"Vizcaya",
    "wof:name":"Iruretagoyena Rodriguez Josune",
    "wof:placetype":"venue"
},
  "geometry": {"coordinates":[-2.819258213,43.2189826965],"type":"Point"}
}