{
  "type": "Feature",
  "properties": {
    "iso:country":"ES",
    "sg:address":"Avda Mejico (de), 10",
    "sg:city":"Jerez De La Frontera",
    "sg:orig_category":"M\u00c9dicos: Ginecolog\u00cda Y Obstetricia",
    "sg:phone":"+34 956 31 24 35",
    "sg:postcode":"11405",
    "sg:province":"C\u00e1diz",
    "wof:name":"Sainz De Rozas Mora Figueroa Manuel",
    "wof:placetype":"venue"
},
  "geometry": {"coordinates":[-6.128704071,36.6929931641],"type":"Point"}
}