{
  "type": "Feature",
  "properties": {
    "iso:country":"ES",
    "sg:address":"Calle de Cartagena, 10",
    "sg:city":"Espinardo",
    "sg:orig_category":"Florister\u00cdas",
    "sg:phone":"+34 968 21 03 51",
    "sg:postcode":"30002",
    "sg:province":"Murcia",
    "wof:name":"Agudo Vazquez Juan Manuel",
    "wof:placetype":"venue"
},
  "geometry": {"coordinates":[-1.1313891411,37.9809188843],"type":"Point"}
}