{
  "type": "Feature",
  "properties": {
    "iso:country":"ES",
    "sg:address":"Rua Pezoca, S/n",
    "sg:city":"Pezoca",
    "sg:orig_category":"Distribuci\u00d3n De Petr\u00d3leo Y Derivados",
    "sg:phone":"+34 981 61 07 75",
    "sg:postcode":"15173",
    "sg:province":"La Coru\u00f1a",
    "sg:website":"www.cepsa.es",
    "wof:name":"Calopaz S.l.",
    "wof:placetype":"venue"
},
  "geometry": {"coordinates":[-8.3093490601,43.3329620361],"type":"Point"}
}