{
  "type": "Feature",
  "properties": {
    "addr:full":"Rua Circunvalacion D. Aurelio, 40 Cuntis Pontevedra 36670",
    "addr:housenumber":"40",
    "addr:postcode":"36670",
    "addr:street":"Rua Circunvalacion D. Aurelio",
    "iso:country":"ES",
    "sg:address":"Rua Circunvalacion D. Aurelio, 40",
    "sg:city":"Cuntis",
    "sg:orig_category":"Panader\u00cdas, Panader\u00cdas",
    "sg:phone":"+34 986 54 84 85",
    "sg:postcode":"36670",
    "sg:province":"Pontevedra",
    "wof:name":"Sistelcom-telemensaje S.a.",
    "wof:placetype":"venue"
},
  "geometry": {"coordinates":[-8.5611791611,42.6424484253],"type":"Point"}
}