{
  "type": "Feature",
  "properties": {
    "iso:country":"ES",
    "sg:address":"Calle de Cortes, 12",
    "sg:city":"Barca De La Florida",
    "sg:orig_category":"Zapatos (al Por Menor)",
    "sg:phone":"+34 956 39 01 29",
    "sg:postcode":"11570",
    "sg:province":"C\u00e1diz",
    "wof:name":"Morilla Gutierrez Antonia",
    "wof:placetype":"venue"
},
  "geometry": {"coordinates":[-5.9328193665,36.6491127014],"type":"Point"}
}