{
  "type": "Feature",
  "properties": {
    "addr:full":"C/ Fila Navarros, 41 Alcoi Alicante 03801",
    "addr:housenumber":"41",
    "addr:postcode":"03801",
    "addr:street":"C / Fila Navarros",
    "iso:country":"ES",
    "sg:address":"C/ Fila Navarros, 41",
    "sg:city":"Alcoi",
    "sg:orig_category":"Autob\u00das (explotaci\u00d3n Y Servicios De)",
    "sg:phone":"+34 965 54 10 28",
    "sg:postcode":"03801",
    "sg:province":"Alicante",
    "sg:website":"www.grposubus.es",
    "wof:name":"Transporte Urbano De Autobuses De Alcoy S. A.",
    "wof:placetype":"venue"
},
  "geometry": {"coordinates":[-0.4769690037,38.6835098267],"type":"Point"}
}