{
  "type": "Feature",
  "properties": {
    "iso:country":"ES",
    "sg:address":"Carrer de Nou, 36",
    "sg:city":"Roses",
    "sg:orig_category":"Peluquer\u00cdas, Peluquer\u00cda Mixta",
    "sg:phone":"+34 972 15 04 38",
    "sg:postcode":"17480",
    "sg:province":"Girona",
    "wof:name":"Anna-consol Clara S.c.",
    "wof:placetype":"venue"
},
  "geometry": {"coordinates":[3.1796929836,42.2619857788],"type":"Point"}
}