{
  "type": "Feature",
  "properties": {
    "addr:full":"Calle de Crucero, 7 Palmones C\u00e1diz 11379",
    "addr:housenumber":"7",
    "addr:postcode":"11379",
    "addr:street":"Calle De Crucero;Ca\u0301Diz",
    "iso:country":"ES",
    "sg:address":"Calle de Crucero, 7",
    "sg:city":"Palmones",
    "sg:orig_category":"Suministros Y Materiales Industriales",
    "sg:phone":"+34 956 67 50 83",
    "sg:postcode":"11379",
    "sg:province":"C\u00e1diz",
    "wof:name":"Stop-fluid S.l.",
    "wof:placetype":"venue"
},
  "geometry": {"coordinates":[-5.4361271858,36.1820106506],"type":"Point"}
}