{
  "type": "Feature",
  "properties": {
    "addr:full":"Cami Mallol (d'en), 15 Palma Islas Baleares 07009",
    "addr:housenumber":"15",
    "addr:postcode":"07009",
    "addr:street":"Mallol D'En",
    "iso:country":"ES",
    "sg:address":"Cami Mallol (d'en), 15",
    "sg:city":"Palma",
    "sg:orig_category":"Construcciones Met\u00c1licas",
    "sg:phone":"+34 971 47 11 12",
    "sg:postcode":"07009",
    "sg:province":"Islas Baleares",
    "wof:name":"Instalaciones Son Vida S.l.",
    "wof:placetype":"venue"
},
  "geometry": {"coordinates":[2.6817760468,39.5960617065],"type":"Point"}
}