{
  "type": "Feature",
  "properties": {
    "iso:country":"ES",
    "sg:address":"Cami Voltes, S/n",
    "sg:city":"Villarreal",
    "sg:orig_category":"Mec\u00c1nico Del Autom\u00d3vil",
    "sg:phone":"+34 964 53 46 73",
    "sg:postcode":"12540",
    "sg:province":"Castell\u00f3n",
    "wof:name":"Sanchez Alfaro Rafael",
    "wof:placetype":"venue"
},
  "geometry": {"coordinates":[-0.1091340035,39.9300308228],"type":"Point"}
}