{
  "type": "Feature",
  "properties": {
    "addr:full":"Av Barceloneta, 5 Ampolla Tarragona 43895",
    "addr:housenumber":"5",
    "addr:postcode":"43895",
    "addr:street":"Av Barceloneta",
    "iso:country":"ES",
    "sg:address":"Av Barceloneta, 5",
    "sg:city":"Ampolla",
    "sg:orig_category":"Inmobiliaria (agencias)",
    "sg:phone":"+34 977 46 05 62",
    "sg:postcode":"43895",
    "sg:province":"Tarragona",
    "wof:name":"Franquilandia S.l.",
    "wof:placetype":"venue"
},
  "geometry": {"coordinates":[0.7137140036,40.8128166199],"type":"Point"}
}