{
  "type": "Feature",
  "properties": {
    "iso:country":"ES",
    "sg:address":"Carrer de Saragossa, 32",
    "sg:city":"Barcelona",
    "sg:orig_category":"M\u00c9dicos: Psiquiatr\u00cda",
    "sg:phone":"+34 934 15 99 25",
    "sg:postcode":"08006",
    "sg:province":"Barcelona",
    "wof:name":"Sanz Cid Alfonso",
    "wof:placetype":"venue"
},
  "geometry": {"coordinates":[2.149107933,41.4021759033],"type":"Point"}
}