{
  "type": "Feature",
  "properties": {
    "iso:country":"ES",
    "sg:address":"Calle de Pedro Cerdan, 4",
    "sg:city":"Torre-pacheco",
    "sg:orig_category":"Zapatos (al Por Menor)",
    "sg:phone":"+34 968 57 74 04",
    "sg:postcode":"30700",
    "sg:province":"Murcia",
    "wof:name":"Martinez Rosique Francisco",
    "wof:placetype":"venue"
},
  "geometry": {"coordinates":[-0.9553949833,37.7436256409],"type":"Point"}
}