{
  "type": "Feature",
  "properties": {
    "iso:country":"ES",
    "sg:address":"Calle de Mieses, 19",
    "sg:city":"Majadahonda",
    "sg:orig_category":"Alimentaci\u00d3n General (al Por Menor)",
    "sg:phone":"+34 916 34 01 13",
    "sg:postcode":"28220",
    "sg:province":"Madrid",
    "wof:name":"Paredes Chaves Juana Elena",
    "wof:placetype":"venue"
},
  "geometry": {"coordinates":[-3.87373209,40.4733428955],"type":"Point"}
}