{
  "type": "Feature",
  "properties": {
    "iso:country":"ES",
    "sg:address":"Carrer de Mig, 5",
    "sg:city":"Espelt",
    "sg:orig_category":"Bazares, Art\u00cdculos De Limpieza Y De Cocina (al Por Menor)",
    "sg:phone":"+34 938 03 38 60",
    "sg:postcode":"08711",
    "sg:province":"Barcelona",
    "wof:name":"Garcia Martinez Felix Angel",
    "wof:placetype":"venue"
},
  "geometry": {"coordinates":[1.6436359882,41.6064567566],"type":"Point"}
}