{
  "type": "Feature",
  "properties": {
    "addr:full":"Rua Santo Graal, 80 Lugo Lugo 27003",
    "addr:housenumber":"80",
    "addr:postcode":"27003",
    "addr:street":"Rua Santo Graal",
    "iso:country":"ES",
    "sg:address":"Rua Santo Graal, 80",
    "sg:city":"Lugo",
    "sg:orig_category":"Ebanister\u00cda",
    "sg:phone":"+34 982 21 83 50",
    "sg:postcode":"27003",
    "sg:province":"Lugo",
    "wof:name":"Rodriguez Lopez Amelia",
    "wof:placetype":"venue"
},
  "geometry": {"coordinates":[-7.5726108551,43.0249404907],"type":"Point"}
}