{
  "type": "Feature",
  "properties": {
    "iso:country":"ES",
    "sg:address":"Avda Pais Valencia, 123",
    "sg:city":"Torrent",
    "sg:orig_category":"Asesor\u00cda De Formaci\u00d3n Y Gesti\u00d3n De Personal",
    "sg:phone":"+34 961 55 82 08",
    "sg:postcode":"46900",
    "sg:province":"Valencia",
    "wof:name":"Iuris Torrent S.l.",
    "wof:placetype":"venue"
},
  "geometry": {"coordinates":[-0.475120008,39.4307136536],"type":"Point"}
}