{
  "type": "Feature",
  "properties": {
    "addr:full":"Rond Zamenhof, 7 Sabadell Barcelona 08201",
    "addr:housenumber":"7",
    "addr:postcode":"08201",
    "addr:street":"Zamenhof",
    "iso:country":"ES",
    "sg:address":"Rond Zamenhof, 7",
    "sg:city":"Sabadell",
    "sg:orig_category":"Abogados",
    "sg:phone":"+34 937 25 27 32",
    "sg:postcode":"08201",
    "sg:province":"Barcelona",
    "wof:name":"Feliubadalo Plans Jose",
    "wof:placetype":"venue"
},
  "geometry": {"coordinates":[2.1060268879,41.5518531799],"type":"Point"}
}