{
  "type": "Feature",
  "properties": {
    "addr:full":"Carrer de Lorena, 57 Barcelona Barcelona 08042",
    "addr:housenumber":"57",
    "addr:postcode":"08042",
    "addr:street":"Carrer De Lorena",
    "iso:country":"ES",
    "sg:address":"Carrer de Lorena, 57",
    "sg:city":"Barcelona",
    "sg:orig_category":"Peluqueros: De Se\u00d1oras",
    "sg:phone":"+34 933 59 05 54",
    "sg:postcode":"08042",
    "sg:province":"Barcelona",
    "wof:name":"Rio Alonso German Del",
    "wof:placetype":"venue"
},
  "geometry": {"coordinates":[2.1725111008,41.4375724792],"type":"Point"}
}