{
  "type": "Feature",
  "properties": {
    "addr:full":"Plaz General Mu\u00d1oz Grandes, 1 Zaragoza Zaragoza 50007",
    "addr:housenumber":"1",
    "addr:postcode":"50007",
    "addr:street":"Grandes",
    "iso:country":"ES",
    "sg:address":"Plaz General Mu\u00d1oz Grandes, 1",
    "sg:city":"Zaragoza",
    "sg:orig_category":"Farmacias",
    "sg:phone":"+34 976 27 24 92",
    "sg:postcode":"50007",
    "sg:province":"Zaragoza",
    "wof:name":"Senante Lop Maria Isabel",
    "wof:placetype":"venue"
},
  "geometry": {"coordinates":[-0.8801509738,41.6332626343],"type":"Point"}
}