{
  "type": "Feature",
  "properties": {
    "iso:country":"ES",
    "sg:address":"Carrer de Martinez De La Rosa, 71",
    "sg:city":"Barcelona",
    "sg:orig_category":"Alquiler De V\u00cddeo",
    "sg:phone":"+34 932 17 07 88",
    "sg:postcode":"08012",
    "sg:province":"Barcelona",
    "sg:website":"www.deuvedes.com",
    "wof:name":"Deuvedes S.c.p.",
    "wof:placetype":"venue"
},
  "geometry": {"coordinates":[2.1576020718,41.401008606],"type":"Point"}
}