{
  "type": "Feature",
  "properties": {
    "iso:country":"ES",
    "sg:address":"Calle de Carmen (la), 50",
    "sg:city":"Arrecife",
    "sg:orig_category":"Poller\u00cda Y Caza (al Por Menor)",
    "sg:phone":"+34 928 80 01 55",
    "sg:postcode":"35500",
    "sg:province":"Las Palmas",
    "wof:name":"Morales Cabrera Jose",
    "wof:placetype":"venue"
},
  "geometry": {"coordinates":[-13.5604076385,28.9687976837],"type":"Point"}
}