{
  "type": "Feature",
  "properties": {
    "addr:full":"Calle de Juan Jose Martinez Seco, 68 Madrid Madrid 28021",
    "addr:housenumber":"68",
    "addr:postcode":"madrid;28021",
    "addr:street":"Calle De Juan Jose Martinez Seco",
    "iso:country":"ES",
    "sg:address":"Calle de Juan Jose Martinez Seco, 68",
    "sg:city":"Madrid",
    "sg:orig_category":"Papeler\u00cdas, Librer\u00cdas",
    "sg:phone":"+34 917 98 77 48",
    "sg:postcode":"28021",
    "sg:province":"Madrid",
    "wof:name":"Alvarez Pino Claudia",
    "wof:placetype":"venue"
},
  "geometry": {"coordinates":[-3.6857185364,40.3519096375],"type":"Point"}
}