{
  "type": "Feature",
  "properties": {
    "iso:country":"ES",
    "sg:address":"Carrer de Ribes, 38",
    "sg:city":"Barcelona",
    "sg:orig_category":"Mec\u00c1nico Del Autom\u00d3vil",
    "sg:phone":"+34 932 45 24 59",
    "sg:postcode":"08013",
    "sg:province":"Barcelona",
    "wof:name":"Talleres Auto Sefer S. A.",
    "wof:placetype":"venue"
},
  "geometry": {"coordinates":[2.1832230091,41.3982276917],"type":"Point"}
}