{
  "type": "Feature",
  "properties": {
    "iso:country":"ES",
    "sg:address":"Carrer de Escocia, 126",
    "sg:city":"Barcelona",
    "sg:orig_category":"Bancos",
    "sg:phone":"+34 934 08 42 88",
    "sg:postcode":"08016",
    "sg:province":"Barcelona",
    "wof:name":"Valbuena Sanchez Rafael",
    "wof:placetype":"venue"
},
  "geometry": {"coordinates":[2.1770839691,41.4288253784],"type":"Point"}
}