{
  "type": "Feature",
  "properties": {
    "iso:country":"ES",
    "sg:address":"Calle de San Antonio, 32",
    "sg:city":"Santa Cruz De Tenerife",
    "sg:orig_category":"Florister\u00cdas",
    "sg:phone":"+34 922 24 14 74",
    "sg:postcode":"38001",
    "sg:province":"Santa Cruz De Tenerife",
    "wof:name":"Rivero Herrera Jose Damaso",
    "wof:placetype":"venue"
},
  "geometry": {"coordinates":[-16.2538375854,28.4946174622],"type":"Point"}
}