{
  "type": "Feature",
  "properties": {
    "addr:full":"Calle de Fragata Danmark, 4 Santa Cruz De Tenerife Santa Cruz De Tenerife 38005",
    "addr:housenumber":"4",
    "addr:postcode":"38005",
    "addr:street":"Calle De Fragata Danmark",
    "iso:country":"ES",
    "sg:address":"Calle de Fragata Danmark, 4",
    "sg:city":"Santa Cruz De Tenerife",
    "sg:orig_category":"Bisuter\u00cda, Joyer\u00cda, Relojer\u00cda (al Por Menor)",
    "sg:phone":"+34 922 22 98 92",
    "sg:postcode":"38005",
    "sg:province":"Santa Cruz De Tenerife",
    "wof:name":"Morales Cano Francisco Jose",
    "wof:placetype":"venue"
},
  "geometry": {"coordinates":[-16.2626934052,28.4589958191],"type":"Point"}
}