{
  "type": "Feature",
  "properties": {
    "iso:country":"ES",
    "sg:address":"Calle de Iradier -urb Los Balcones, 5",
    "sg:city":"Balcones",
    "sg:orig_category":"Piscinas, Accesorios, Suministros (fabricaci\u00d3n, Al Por Mayor)",
    "sg:phone":"+34 966 79 85 73",
    "sg:postcode":"03186",
    "sg:province":"Alicante",
    "wof:name":"Pool-shop Los Balcones S.l.",
    "wof:placetype":"venue"
},
  "geometry": {"coordinates":[-0.7276489735,37.9641990662],"type":"Point"}
}