{
  "type": "Feature",
  "properties": {
    "addr:full":"Pase Cauce, 66 Valladolid Valladolid 47005",
    "addr:housenumber":"66",
    "addr:postcode":"47005",
    "addr:street":"Cauce",
    "iso:country":"ES",
    "sg:address":"Pase Cauce, 66",
    "sg:city":"Valladolid",
    "sg:orig_category":"Peluqueros: De Se\u00d1oras",
    "sg:phone":"+34 983 29 51 16",
    "sg:postcode":"47005",
    "sg:province":"Valladolid",
    "wof:name":"Lopez Garcia Angelines",
    "wof:placetype":"venue"
},
  "geometry": {"coordinates":[-4.7120299339,41.65284729],"type":"Point"}
}