{
  "type": "Feature",
  "properties": {
    "iso:country":"ES",
    "sg:address":"Monse\u00f1or Ramon Zubieta, 8",
    "sg:city":"Virgen Camino",
    "sg:orig_category":"Centros De Educaci\u00d3n Especial",
    "sg:phone":"+34 987 30 00 36",
    "sg:postcode":"24198",
    "sg:province":"Le\u00f3n",
    "wof:name":"Misioneras Dominicas",
    "wof:placetype":"venue"
},
  "geometry": {"coordinates":[-5.6423802376,42.5781364441],"type":"Point"}
}