{
  "type": "Feature",
  "properties": {
    "iso:country":"ES",
    "sg:address":"Calle de Gijon, 15",
    "sg:city":"Pola De Laviana",
    "sg:orig_category":"Peluqueros: De Se\u00d1oras",
    "sg:phone":"+34 985 61 06 86",
    "sg:postcode":"33980",
    "sg:province":"Asturias",
    "wof:name":"Trabancal Garcia Enedina",
    "wof:placetype":"venue"
},
  "geometry": {"coordinates":[-5.5619277954,43.2421340942],"type":"Point"}
}