{
  "type": "Feature",
  "properties": {
    "addr:full":"Calle de Sos Del Rey Catolico, 1 Granada Granada 18006",
    "addr:housenumber":"1",
    "addr:postcode":"18006",
    "addr:street":"Calle De Sos Del Rey Catolico",
    "iso:country":"ES",
    "sg:address":"Calle de Sos Del Rey Catolico, 1",
    "sg:city":"Granada",
    "sg:orig_category":"Formaci\u00d3n Continuada (variada)",
    "sg:phone":"+34 958 12 02 44",
    "sg:postcode":"18006",
    "sg:province":"Granada",
    "wof:name":"Moreno Ya\u00f1ez Jose Luis",
    "wof:placetype":"venue"
},
  "geometry": {"coordinates":[-3.5962269306,37.1657981873],"type":"Point"}
}