{
  "type": "Feature",
  "properties": {
    "iso:country":"ES",
    "sg:address":"Calle de Herradores, 79",
    "sg:city":"San Cristobal De La Laguna",
    "sg:orig_category":"Comercio De Muebles De Estilo Y Contempor\u00c1neos",
    "sg:phone":"+34 922 26 37 16",
    "sg:postcode":"38201",
    "sg:province":"Santa Cruz De Tenerife",
    "wof:name":"Sidoruk Corteses Carla",
    "wof:placetype":"venue"
},
  "geometry": {"coordinates":[-16.3189983368,28.489315033],"type":"Point"}
}