{
  "type": "Feature",
  "properties": {
    "iso:country":"ES",
    "sg:address":"Calle de Alonso Cano, 66",
    "sg:city":"Madrid",
    "sg:orig_category":"Expertos Contables, Revisores De Cuentas",
    "sg:phone":"+34 915 34 41 22",
    "sg:postcode":"28003",
    "sg:province":"Madrid",
    "wof:name":"Fernandez Lopez Jose",
    "wof:placetype":"venue"
},
  "geometry": {"coordinates":[-3.6973590851,40.4434280396],"type":"Point"}
}