{
  "type": "Feature",
  "properties": {
    "iso:country":"ES",
    "sg:address":"Calle de Covadonga, 8",
    "sg:city":"Barrio De Peral",
    "sg:orig_category":"Farmacias",
    "sg:phone":"+34 968 51 01 97",
    "sg:postcode":"30300",
    "sg:province":"Murcia",
    "wof:name":"Buendia Mayordomo Diego",
    "wof:placetype":"venue"
},
  "geometry": {"coordinates":[-1.1302499771,37.9829597473],"type":"Point"}
}