{
  "type": "Feature",
  "properties": {
    "addr:full":"Calle de Villanueva, 36 Madrid Madrid 28001",
    "addr:housenumber":"36",
    "addr:postcode":"madrid;28001",
    "addr:street":"Calle De Villanueva",
    "iso:country":"ES",
    "sg:address":"Calle de Villanueva, 36",
    "sg:city":"Madrid",
    "sg:orig_category":"Comisarios",
    "sg:phone":"+34 914 35 16 80",
    "sg:postcode":"28001",
    "sg:province":"Madrid",
    "wof:name":"Parlade Olaso Natalia",
    "wof:placetype":"venue"
},
  "geometry": {"coordinates":[-3.6837050915,40.4221725464],"type":"Point"}
}