{
  "type": "Feature",
  "properties": {
    "addr:full":"Calle de Villacarrillo (blq), 3 Madrid Madrid 28008",
    "addr:housenumber":"3",
    "addr:postcode":"28008",
    "addr:street":"Calle De Villacarrillo Blq",
    "iso:country":"ES",
    "sg:address":"Calle de Villacarrillo (blq), 3",
    "sg:city":"Madrid",
    "sg:orig_category":"Arquitectos",
    "sg:phone":"+34 915 47 34 03",
    "sg:postcode":"28008",
    "sg:province":"Madrid",
    "wof:name":"Illan Del Pino Julian",
    "wof:placetype":"venue"
},
  "geometry": {"coordinates":[-3.6645209789,40.3753547668],"type":"Point"}
}