{
  "type": "Feature",
  "properties": {
    "iso:country":"ES",
    "sg:address":"Calle de Villagloria, 17",
    "sg:city":"Villamartin De La Abadia",
    "sg:orig_category":"Construcciones Met\u00c1licas",
    "sg:phone":"+34 987 56 26 40",
    "sg:postcode":"24550",
    "sg:province":"Le\u00f3n",
    "wof:name":"Garcia Vazquez Antonio",
    "wof:placetype":"venue"
},
  "geometry": {"coordinates":[-6.7489089966,42.5686683655],"type":"Point"}
}