{
  "type": "Feature",
  "properties": {
    "addr:full":"Calle de Mayor, 34 Alcala Henares Madrid 28801",
    "addr:housenumber":"34",
    "addr:postcode":"28801",
    "addr:street":"Calle De Mayor",
    "iso:country":"ES",
    "sg:address":"Calle de Mayor, 34",
    "sg:city":"Alcala Henares",
    "sg:orig_category":"Farmacias",
    "sg:phone":"+34 918 88 02 72",
    "sg:postcode":"28801",
    "sg:province":"Madrid",
    "wof:name":"Ruiz Lomas Magin",
    "wof:placetype":"venue"
},
  "geometry": {"coordinates":[-3.3663420677,40.4825401306],"type":"Point"}
}