{
  "type": "Feature",
  "properties": {
    "addr:full":"Plaz Mayor, 8 Marchamalo Guadalajara 19180",
    "addr:housenumber":"8",
    "addr:postcode":"19180",
    "addr:street":"Plaz Mayor",
    "iso:country":"ES",
    "sg:address":"Plaz Mayor, 8",
    "sg:city":"Marchamalo",
    "sg:orig_category":"Molduras, Junquillos, Listones Y Molduras Perforadas",
    "sg:phone":"+34 949 25 03 76",
    "sg:postcode":"19180",
    "sg:province":"Guadalajara",
    "wof:name":"Fernandez Briega Raul",
    "wof:placetype":"venue"
},
  "geometry": {"coordinates":[-3.2014839649,40.6696891785],"type":"Point"}
}