{
  "type": "Feature",
  "properties": {
    "iso:country":"ES",
    "sg:address":"Pase Olof Palme, 16",
    "sg:city":"Badalona",
    "sg:orig_category":"Molduras, Junquillos, Listones Y Molduras Perforadas",
    "sg:phone":"+34 933 95 62 83",
    "sg:postcode":"08917",
    "sg:province":"Barcelona",
    "wof:name":"Malia Oliva Diego",
    "wof:placetype":"venue"
},
  "geometry": {"coordinates":[2.2270700932,41.4546203613],"type":"Point"}
}