{
  "type": "Feature",
  "properties": {
    "iso:country":"ES",
    "sg:address":"Leon-astorga, 68",
    "sg:city":"Villadangos Paramo",
    "sg:orig_category":"Peluquer\u00cdas, Peluquer\u00cda Mixta",
    "sg:phone":"+34 987 39 01 10",
    "sg:postcode":"24392",
    "sg:province":"Le\u00f3n",
    "wof:name":"Barrioluengo Arguello Miguel",
    "wof:placetype":"venue"
},
  "geometry": {"coordinates":[-5.7662639618,42.5171508789],"type":"Point"}
}