{
  "type": "Feature",
  "properties": {
    "iso:country":"ES",
    "sg:address":"Carr Joan Josep Amengual I Reus, S/n",
    "sg:city":"Binissalem",
    "sg:orig_category":"Asociaciones Y Clubs Deportivos",
    "sg:phone":"+34 971 88 65 91",
    "sg:postcode":"07350",
    "sg:province":"Islas Baleares",
    "wof:name":"Moya Pons Margarita",
    "wof:placetype":"venue"
},
  "geometry": {"coordinates":[2.8456048965,39.68907547],"type":"Point"}
}