{
  "type": "Feature",
  "properties": {
    "iso:country":"ES",
    "sg:address":"Urb. Fuentes, S/n",
    "sg:city":"Monterrebollo",
    "sg:orig_category":"Inmobiliaria (agencias)",
    "sg:phone":"+34 949 38 97 01",
    "sg:postcode":"19113",
    "sg:province":"Guadalajara",
    "wof:name":"Residencial Monte Rebollo S. A",
    "wof:placetype":"venue"
},
  "geometry": {"coordinates":[-3.0948090553,40.3641281128],"type":"Point"}
}