{
  "type": "Feature",
  "properties": {
    "addr:full":"Luga Tajo Del Pinto, S/n Tajo Del Pinto M\u00e1laga 29749",
    "addr:housenumber":"s / n",
    "addr:postcode":"29749",
    "addr:street":"Ma\u0301Laga",
    "iso:country":"ES",
    "sg:address":"Luga Tajo Del Pinto, S/n",
    "sg:city":"Tajo Del Pinto",
    "sg:orig_category":"Calderer\u00cda",
    "sg:phone":"+34 952 55 63 98",
    "sg:postcode":"29749",
    "sg:province":"M\u00e1laga",
    "wof:name":"Talleres Martin Molina S.l.",
    "wof:placetype":"venue"
},
  "geometry": {"coordinates":[-4.1290340424,36.7308235168],"type":"Point"}
}