{
  "type": "Feature",
  "properties": {
    "addr:full":"Plaz Major, 23 Torrent Valencia 46900",
    "addr:housenumber":"23",
    "addr:postcode":"46900",
    "addr:street":"Plaz Major;Valencia",
    "iso:country":"ES",
    "sg:address":"Plaz Major, 23",
    "sg:city":"Torrent",
    "sg:orig_category":"Panader\u00cdas, Panader\u00cdas",
    "sg:phone":"+34 961 55 06 59",
    "sg:postcode":"46900",
    "sg:province":"Valencia",
    "wof:name":"Perez Prieto Isidro",
    "wof:placetype":"venue"
},
  "geometry": {"coordinates":[-0.463537991,39.4364738464],"type":"Point"}
}