{
  "type": "Feature",
  "properties": {
    "iso:country":"ES",
    "sg:address":"Pase Serapio Mugica De, 1",
    "sg:city":"Donostia-san Sebastian",
    "sg:orig_category":"Polideportivos",
    "sg:phone":"+34 943 39 39 93",
    "sg:postcode":"20016",
    "sg:province":"Guip\u00f9zcoa",
    "wof:name":"Atletico Bera-bera R.t.",
    "wof:placetype":"venue"
},
  "geometry": {"coordinates":[-1.9454929829,43.322593689],"type":"Point"}
}