{
  "type": "Feature",
  "properties": {
    "addr:full":"Pl. Moreres, S/n Esplugues Llobregat Barcelona 08950",
    "addr:housenumber":"s / n",
    "addr:postcode":"08950",
    "addr:street":"Moreres",
    "iso:country":"ES",
    "sg:address":"Pl. Moreres, S/n",
    "sg:city":"Esplugues Llobregat",
    "sg:orig_category":"Polideportivos",
    "sg:phone":"+34 934 73 19 21",
    "sg:postcode":"08950",
    "sg:province":"Barcelona",
    "wof:name":"Ajuntament D'esplugues De Llobregat",
    "wof:placetype":"venue"
},
  "geometry": {"coordinates":[2.0866160393,41.3797874451],"type":"Point"}
}