{
  "type": "Feature",
  "properties": {
    "addr:full":"Avda Mineria (la), 3 Ponferrada Le\u00f3n 24400",
    "addr:postcode":"24400",
    "addr:street":"Avda Mineria La 3;Leo\u0301N",
    "iso:country":"ES",
    "sg:address":"Avda Mineria (la), 3",
    "sg:city":"Ponferrada",
    "sg:orig_category":"Arquitectos",
    "sg:phone":"+34 987 40 17 72",
    "sg:postcode":"24400",
    "sg:province":"Le\u00f3n",
    "wof:name":"Martin Perez Fernandez S.l.",
    "wof:placetype":"venue"
},
  "geometry": {"coordinates":[-6.603143692,42.5484428406],"type":"Point"}
}