{
  "type": "Feature",
  "properties": {
    "addr:full":"Calle de Newton, 25 Estepona M\u00e1laga 29680",
    "addr:housenumber":"25",
    "addr:postcode":"29680",
    "addr:street":"Calle De Newton",
    "iso:country":"ES",
    "sg:address":"Calle de Newton, 25",
    "sg:city":"Estepona",
    "sg:orig_category":"Cerrajer\u00cda, Ferrallista",
    "sg:phone":"+34 952 80 22 40",
    "sg:postcode":"29680",
    "sg:province":"M\u00e1laga",
    "wof:name":"Cesurmatic, S.l.",
    "wof:placetype":"venue"
},
  "geometry": {"coordinates":[-5.1697487831,36.4298171997],"type":"Point"}
}