{
  "type": "Feature",
  "properties": {
    "addr:full":"Ctra Madrid-irun, Km. 0203,7 Villalmanzo Burgos 09390",
    "addr:postcode":"09390",
    "addr:street":"Ctra Madrid-Irun Km. 0203,7",
    "iso:country":"ES",
    "sg:address":"Ctra Madrid-irun, Km. 0203,7",
    "sg:city":"Villalmanzo",
    "sg:orig_category":"Cooperativas Agr\u00cdcolas",
    "sg:phone":"+34 947 17 05 59",
    "sg:postcode":"09390",
    "sg:province":"Burgos",
    "wof:name":"Sociedad Cooperativa De 2 Grado Duero Arlanza",
    "wof:placetype":"venue"
},
  "geometry": {"coordinates":[-3.7047789097,42.0872116089],"type":"Point"}
}