{
  "type": "Feature",
  "properties": {
    "iso:country":"ES",
    "sg:address":"Calle de Larga, 13",
    "sg:city":"Villarrasa",
    "sg:orig_category":"Bazares, Art\u00cdculos De Limpieza Y De Cocina (al Por Menor)",
    "sg:phone":"+34 959 41 90 88",
    "sg:postcode":"21850",
    "sg:province":"Huelva",
    "wof:name":"Gomez Garcia Laureana",
    "wof:placetype":"venue"
},
  "geometry": {"coordinates":[-6.6032481194,37.3883666992],"type":"Point"}
}