{
  "type": "Feature",
  "properties": {
    "addr:full":"Calle de San Juan, 13 Puerto De Santa Maria C\u00e1diz 11500",
    "addr:housenumber":"13",
    "addr:postcode":"11500",
    "addr:street":"Calle De San Juan;Ca\u0301Diz",
    "iso:country":"ES",
    "sg:address":"Calle de San Juan, 13",
    "sg:city":"Puerto De Santa Maria",
    "sg:orig_category":"Estancos",
    "sg:phone":"+34 956 87 45 84",
    "sg:postcode":"11500",
    "sg:province":"C\u00e1diz",
    "wof:name":"Jimenez Portillo Teresa",
    "wof:placetype":"venue"
},
  "geometry": {"coordinates":[-6.2291507721,36.600692749],"type":"Point"}
}