{
  "type": "Feature",
  "properties": {
    "iso:country":"ES",
    "sg:address":"Carrer de Proven\u00c7a, 330",
    "sg:city":"Barcelona",
    "sg:orig_category":"Asesor\u00cda Fiscal Y Jur\u00cddica",
    "sg:phone":"+34 934 57 08 32",
    "sg:postcode":"08037",
    "sg:province":"Barcelona",
    "wof:name":"S.i.q. Gabinete Empresarial S.l.",
    "wof:placetype":"venue"
},
  "geometry": {"coordinates":[2.1648430824,41.3970909119],"type":"Point"}
}