{
  "type": "Feature",
  "properties": {
    "iso:country":"ES",
    "sg:address":"Carrer de Beat Oriol, 22",
    "sg:city":"Mas Rampinyo",
    "sg:orig_category":"Molduras, Junquillos, Listones Y Molduras Perforadas",
    "sg:phone":"+34 935 75 05 26",
    "sg:postcode":"08110",
    "sg:province":"Barcelona",
    "wof:name":"Alvarez Perez Dionisio",
    "wof:placetype":"venue"
},
  "geometry": {"coordinates":[2.1781036854,41.4914855957],"type":"Point"}
}