{
  "type": "Feature",
  "properties": {
    "addr:full":"Av Bosc, 67 Hospitalet Llobregat Barcelona 08906",
    "addr:housenumber":"67",
    "addr:postcode":"08906",
    "addr:street":"Av Bosc",
    "iso:country":"ES",
    "sg:address":"Av Bosc, 67",
    "sg:city":"Hospitalet Llobregat",
    "sg:orig_category":"Muebles Y Accesorios Para Cocinas Y Cuartos De Ba\u00d1o (al Por Menor)",
    "sg:phone":"+34 934 37 26 86",
    "sg:postcode":"08906",
    "sg:province":"Barcelona",
    "wof:name":"Sole Pardo Juan",
    "wof:placetype":"venue"
},
  "geometry": {"coordinates":[2.1020390987,41.3732223511],"type":"Point"}
}