{
  "type": "Feature",
  "properties": {
    "iso:country":"ES",
    "sg:address":"Urb Paraiso Alto, 495",
    "sg:city":"Cortes",
    "sg:orig_category":"Inmobiliaria (agencias)",
    "sg:phone":"+34 952 88 64 95",
    "sg:postcode":"29679",
    "sg:province":"M\u00e1laga",
    "wof:name":"Nogueroles Lopez Jose Maria",
    "wof:placetype":"venue"
},
  "geometry": {"coordinates":[-5.0462741852,36.5238952637],"type":"Point"}
}