{
  "type": "Feature",
  "properties": {
    "iso:country":"ES",
    "sg:address":"Carr Concepcion Arenal, 2",
    "sg:city":"Burjassot",
    "sg:orig_category":"Promotores Constructores",
    "sg:phone":"+34 963 63 92 28",
    "sg:postcode":"46100",
    "sg:province":"Valencia",
    "wof:name":"Pascual Badelles Jose",
    "wof:placetype":"venue"
},
  "geometry": {"coordinates":[-0.4110539854,39.5094413757],"type":"Point"}
}