{
  "type": "Feature",
  "properties": {
    "addr:full":"Calle de Yunque, 15 Leganes Madrid 28918",
    "addr:housenumber":"15",
    "addr:postcode":"28918",
    "addr:street":"Calle De Yunque",
    "iso:country":"ES",
    "sg:address":"Calle de Yunque, 15",
    "sg:city":"Leganes",
    "sg:orig_category":"Inform\u00c1tica (estudios, Servicios, Asesor\u00cda, Formaci\u00d3n)",
    "sg:phone":"+34 916 11 31 01",
    "sg:postcode":"28918",
    "sg:province":"Madrid",
    "wof:name":"D.m.j.informatica C.s.l.",
    "wof:placetype":"venue"
},
  "geometry": {"coordinates":[-3.8018329144,40.3430023193],"type":"Point"}
}