{
  "type": "Feature",
  "properties": {
    "addr:full":"Calle de Fuente, 10 Villores Castell\u00f3n 12311",
    "addr:housenumber":"10",
    "addr:postcode":"12311",
    "addr:street":"Calle De Fuente;Castello\u0301N",
    "iso:country":"ES",
    "sg:address":"Calle de Fuente, 10",
    "sg:city":"Villores",
    "sg:orig_category":"Confecci\u00d3n De Zapatos",
    "sg:phone":"+34 964 17 11 51",
    "sg:postcode":"12311",
    "sg:province":"Castell\u00f3n",
    "wof:name":"Gil Bonet Antonio",
    "wof:placetype":"venue"
},
  "geometry": {"coordinates":[-0.166159004,40.7288360596],"type":"Point"}
}