{
  "type": "Feature",
  "properties": {
    "addr:full":"Calle de Marques De Lozoya, 2 Madrid Madrid 28007",
    "addr:housenumber":"2",
    "addr:postcode":"28007",
    "addr:street":"Calle De Marques De Lozoya",
    "iso:country":"ES",
    "sg:address":"Calle de Marques De Lozoya, 2",
    "sg:city":"Madrid",
    "sg:orig_category":"Empresas De Limpieza",
    "sg:phone":"+34 915 74 31 73",
    "sg:postcode":"28007",
    "sg:province":"Madrid",
    "wof:name":"Limpiezas Cardesol S.l.",
    "wof:placetype":"venue"
},
  "geometry": {"coordinates":[-3.6630880833,40.4190444946],"type":"Point"}
}