{
  "type": "Feature",
  "properties": {
    "addr:full":"Calle de Arroyo De Las Pilillas, 20 Madrid Madrid 28030",
    "addr:housenumber":"20",
    "addr:postcode":"madrid;28030",
    "addr:street":"Calle De Arroyo De Las Pilillas",
    "iso:country":"ES",
    "sg:address":"Calle de Arroyo De Las Pilillas, 20",
    "sg:city":"Madrid",
    "sg:orig_category":"Asesor\u00cda De Comercio Exterior",
    "sg:phone":"+34 913 28 72 38",
    "sg:postcode":"28030",
    "sg:province":"Madrid",
    "sg:website":"www.gescoex.es",
    "wof:name":"Gescoex S.l.",
    "wof:placetype":"venue"
},
  "geometry": {"coordinates":[-3.6503801346,40.4081420898],"type":"Point"}
}