{
  "type": "Feature",
  "properties": {
    "iso:country":"ES",
    "sg:address":"Calle de Uruguay, 35",
    "sg:city":"Madrid",
    "sg:orig_category":"M\u00c9dicos: Estomatolog\u00cda",
    "sg:phone":"+34 914 13 86 43",
    "sg:postcode":"28016",
    "sg:province":"Madrid",
    "wof:name":"Sanz Perez Ana Maria",
    "wof:placetype":"venue"
},
  "geometry": {"coordinates":[-3.6715450287,40.455078125],"type":"Point"}
}