{
  "type": "Feature",
  "properties": {
    "addr:full":"G.v. Corts Catalanes, 670 Barcelona Barcelona 08010",
    "addr:housenumber":"670",
    "addr:postcode":"08010",
    "addr:street":"Catalanes",
    "iso:country":"ES",
    "sg:address":"G.v. Corts Catalanes, 670",
    "sg:city":"Barcelona",
    "sg:orig_category":"Sindicatos Y Colegios Profesionales",
    "sg:phone":"+34 933 17 62 00",
    "sg:postcode":"08010",
    "sg:province":"Barcelona",
    "wof:name":"Gremi Industries Confeccio Barcelona",
    "wof:placetype":"venue"
},
  "geometry": {"coordinates":[2.1718978882,41.3917121887],"type":"Point"}
}