{
  "type": "Feature",
  "properties": {
    "addr:full":"Calle de Don Juan, S/n San Pedro De Las Due\u00e7as Le\u00f3n 24248",
    "addr:housenumber":"s / n",
    "addr:postcode":"24248",
    "addr:street":"Calle De Don Juan;Leo\u0301N",
    "iso:country":"ES",
    "sg:address":"Calle de Don Juan, S/n",
    "sg:city":"San Pedro De Las Due\u00e7as",
    "sg:orig_category":"Iglesia Cat\u00d3lica",
    "sg:phone":"+34 987 38 42 00",
    "sg:postcode":"24248",
    "sg:province":"Le\u00f3n",
    "wof:name":"Parroquia De San Pedro",
    "wof:placetype":"venue"
},
  "geometry": {"coordinates":[-5.5717520714,42.5998764038],"type":"Point"}
}