{
  "type": "Feature",
  "properties": {
    "iso:country":"ES",
    "sg:address":"Calle de Fortuny, 5",
    "sg:city":"Madrid",
    "sg:orig_category":"Inform\u00c1tica (estudios, Servicios, Asesor\u00cda, Formaci\u00d3n)",
    "sg:phone":"+34 913 19 42 11",
    "sg:postcode":"28010",
    "sg:province":"Madrid",
    "wof:name":"Global Finance Advisors S.l.",
    "wof:placetype":"venue"
},
  "geometry": {"coordinates":[-3.6910924911,40.428565979],"type":"Point"}
}