{
  "type": "Feature",
  "properties": {
    "addr:full":"Rua Baiona, S/n Vigo Pontevedra 36209",
    "addr:housenumber":"s / n",
    "addr:postcode":"36209",
    "addr:street":"Rua Baiona",
    "iso:country":"ES",
    "sg:address":"Rua Baiona, S/n",
    "sg:city":"Vigo",
    "sg:orig_category":"Peluqueros: De Se\u00d1oras",
    "sg:phone":"+34 986 20 63 75",
    "sg:postcode":"36209",
    "sg:province":"Pontevedra",
    "wof:name":"Iglesias Alvarez Maria Josefa",
    "wof:placetype":"venue"
},
  "geometry": {"coordinates":[-8.7520065308,42.2146148682],"type":"Point"}
}