{
  "type": "Feature",
  "properties": {
    "addr:full":"Carrer de Mare De Deu Dels Desemparats, 13 Hospitalet Llobregat Barcelona 08903",
    "addr:housenumber":"13",
    "addr:postcode":"08903",
    "addr:street":"Carrer De Mare De Deu;Desemparats",
    "iso:country":"ES",
    "sg:address":"Carrer de Mare De Deu Dels Desemparats, 13",
    "sg:city":"Hospitalet Llobregat",
    "sg:orig_category":"Promotores Constructores",
    "sg:phone":"+34 933 33 25 52",
    "sg:postcode":"08903",
    "sg:province":"Barcelona",
    "wof:name":"Construccions Riu Pujol S.l.",
    "wof:placetype":"venue"
},
  "geometry": {"coordinates":[2.1253149509,41.3722915649],"type":"Point"}
}