{
  "type": "Feature",
  "properties": {
    "addr:full":"Calle de Gran Via, 3 Donostia-san Sebastian Guip\u00f9zcoa 20002",
    "addr:housenumber":"3",
    "addr:postcode":"20002",
    "addr:street":"Calle De Gran Via",
    "iso:country":"ES",
    "sg:address":"Calle de Gran Via, 3",
    "sg:city":"Donostia-san Sebastian",
    "sg:orig_category":"Dentistas: Cirujanos Dentistas Cualificados En Ortopedia Odontofacial",
    "sg:phone":"+34 943 27 33 29",
    "sg:postcode":"20002",
    "sg:province":"Guip\u00f9zcoa",
    "wof:name":"J J Dent S.l.",
    "wof:placetype":"venue"
},
  "geometry": {"coordinates":[-1.9749736786,43.3250427246],"type":"Point"}
}