{
  "type": "Feature",
  "properties": {
    "iso:country":"ES",
    "sg:address":"Carrer de Son Ferragut, 21",
    "sg:city":"Palma",
    "sg:orig_category":"Librer\u00cdas",
    "sg:phone":"+34 971 29 53 01",
    "sg:postcode":"07004",
    "sg:province":"Islas Baleares",
    "wof:name":"Pernas Guerrero Maria Eugenia",
    "wof:placetype":"venue"
},
  "geometry": {"coordinates":[2.6547620296,39.5856132507],"type":"Point"}
}