{
  "type": "Feature",
  "properties": {
    "iso:country":"ES",
    "sg:address":"Calle de Blas Perez Gonzalez, S/n",
    "sg:city":"San Pedro De Bre\u00e7a Alta",
    "sg:orig_category":"Formaci\u00d3n Continuada (variada)",
    "sg:phone":"+34 922 43 70 01",
    "sg:postcode":"38710",
    "sg:province":"Santa Cruz De Tenerife",
    "wof:name":"Ayuntamiento De Bre\u00f1a Alta-recaudacion",
    "wof:placetype":"venue"
},
  "geometry": {"coordinates":[-17.7874984741,28.6631908417],"type":"Point"}
}