{
  "type": "Feature",
  "properties": {
    "addr:full":"Carrer de Sol, 1 Mollet Valles Barcelona 08100",
    "addr:housenumber":"1",
    "addr:postcode":"08100",
    "addr:street":"Carrer De Sol",
    "iso:country":"ES",
    "sg:address":"Carrer de Sol, 1",
    "sg:city":"Mollet Valles",
    "sg:orig_category":"Peluqueros: De Se\u00d1oras",
    "sg:phone":"+34 935 70 10 62",
    "sg:postcode":"08100",
    "sg:province":"Barcelona",
    "wof:name":"Perez Oliver Juana",
    "wof:placetype":"venue"
},
  "geometry": {"coordinates":[2.2146770954,41.5415916443],"type":"Point"}
}