{
  "type": "Feature",
  "properties": {
    "addr:full":"Barr Charca Musia, S/n Caceres C\u00e1ceres 10005",
    "addr:housenumber":"s",
    "addr:postcode":"10005",
    "addr:street":"/ N;Ca\u0301Ceres",
    "iso:country":"ES",
    "sg:address":"Barr Charca Musia, S/n",
    "sg:city":"Caceres",
    "sg:orig_category":"Muebles Y Accesorios Para Cocinas Y Cuartos De Ba\u00d1o (al Por Menor)",
    "sg:phone":"+34 927 22 14 01",
    "sg:postcode":"10005",
    "sg:province":"C\u00e1ceres",
    "wof:name":"Fegocesa S. L.",
    "wof:placetype":"venue"
},
  "geometry": {"coordinates":[-6.3693461418,39.4525108337],"type":"Point"}
}