{
  "type": "Feature",
  "properties": {
    "iso:country":"ES",
    "sg:address":"Calle de Crucero Baleares, 31",
    "sg:city":"Puerto De Santa Maria",
    "sg:classifiers":[
        {
            "category":"Autos & Motor Vehicles",
            "subcategory":"Automobile Sales",
            "type":"Retail Goods"
        }
    ],
    "sg:phone":"+34 956 87 07 84",
    "sg:postcode":"11500",
    "sg:province":"C\u00e1diz",
    "wof:name":"Auto Escuela Sherry S.l.",
    "wof:placetype":"venue"
},
  "geometry": {"coordinates":[-6.2382612228,36.5928688049],"type":"Point"}
}