{
  "type": "Feature",
  "properties": {
    "iso:country":"ES",
    "sg:address":"Afores, S/n",
    "sg:city":"Bisbal Del Penedes",
    "sg:classifiers":[
        {
            "category":"Home & Garden",
            "subcategory":"Household Appliances",
            "type":"Retail Goods"
        }
    ],
    "sg:phone":"+34 977 16 99 05",
    "sg:postcode":"43717",
    "sg:province":"Tarragona",
    "sg:tags":[
        "bodega",
        "de",
        "vino",
        "acondicionamiento"
    ],
    "wof:name":"Pijoan Escocet S.a.t.",
    "wof:placetype":"venue"
},
  "geometry": {"coordinates":[1.4905450344,41.2773857117],"type":"Point"}
}