{
  "type": "Feature",
  "properties": {
    "iso:country":"ES",
    "sg:address":"Calle de Palma Del Rio, 19",
    "sg:city":"Malaga",
    "sg:orig_category":"Agencias Y Asesores De Publicidad",
    "sg:phone":"+34 952 23 75 86",
    "sg:postcode":"29004",
    "sg:province":"M\u00e1laga",
    "sg:website":"www.vider.net",
    "wof:name":"Vired Sur S.l.",
    "wof:placetype":"venue"
},
  "geometry": {"coordinates":[-4.4555091858,36.6888084412],"type":"Point"}
}