{
  "type": "Feature",
  "properties": {
    "iso:country":"ES",
    "sg:address":"Avda Almendros (los), 22",
    "sg:city":"Barrera",
    "sg:orig_category":"Caf\u00c9s, Bares, Cervecer\u00cdas",
    "sg:phone":"+34 928 70 58 42",
    "sg:postcode":"35217",
    "sg:province":"Las Palmas",
    "wof:name":"Ramirez Lopez Julio",
    "wof:placetype":"venue"
},
  "geometry": {"coordinates":[-15.4697036743,27.9951267242],"type":"Point"}
}