{
  "type": "Feature",
  "properties": {
    "iso:country":"ES",
    "sg:address":"Calle de Bolivia, 8",
    "sg:city":"Petrer",
    "sg:orig_category":"Empresas De Pintura Y Revestimientos",
    "sg:phone":"+34 965 37 38 94",
    "sg:postcode":"03610",
    "sg:province":"Alicante",
    "wof:name":"Rodriguez Albert Gabriel",
    "wof:placetype":"venue"
},
  "geometry": {"coordinates":[-0.7672867179,38.4824371338],"type":"Point"}
}