{
  "type": "Feature",
  "properties": {
    "addr:full":"Pol Ind Zamarra, 4 Xirivella Valencia 46950",
    "addr:housenumber":"4",
    "addr:postcode":"46950",
    "addr:street":"Zamarra",
    "iso:country":"ES",
    "sg:address":"Pol Ind Zamarra, 4",
    "sg:city":"Xirivella",
    "sg:orig_category":"Construcciones Met\u00c1licas",
    "sg:phone":"+34 963 50 16 54",
    "sg:postcode":"46950",
    "sg:province":"Valencia",
    "wof:name":"Alumetal System 2003 Sl",
    "wof:placetype":"venue"
},
  "geometry": {"coordinates":[-0.426658392,39.4597816467],"type":"Point"}
}