{
  "type": "Feature",
  "properties": {
    "iso:country":"ES",
    "sg:address":"Calle de Beniajan, 16",
    "sg:city":"Torrevieja",
    "sg:orig_category":"Agencias Y Agentes Comerciales, Representantes",
    "sg:phone":"+34 966 70 58 36",
    "sg:postcode":"03180",
    "sg:province":"Alicante",
    "wof:name":"Villagordo Garcia Antonio Moises",
    "wof:placetype":"venue"
},
  "geometry": {"coordinates":[-0.6536790133,38.0173606873],"type":"Point"}
}