{
  "type": "Feature",
  "properties": {
    "addr:full":"Calle de Real, 101 Estepona M\u00e1laga 29680",
    "addr:housenumber":"101",
    "addr:postcode":"29680",
    "addr:street":"Calle De Real",
    "iso:country":"ES",
    "sg:address":"Calle de Real, 101",
    "sg:city":"Estepona",
    "sg:orig_category":"M\u00c9dicos: Estomatolog\u00cda",
    "sg:phone":"+34 952 80 62 09",
    "sg:postcode":"29680",
    "sg:province":"M\u00e1laga",
    "wof:name":"Daws  Nicholas Geoffrey",
    "wof:placetype":"venue"
},
  "geometry": {"coordinates":[-5.1451859474,36.4250602722],"type":"Point"}
}