{
  "type": "Feature",
  "properties": {
    "addr:full":"Calle de San Luis, 22 Santander Cantabria 39010",
    "addr:housenumber":"22",
    "addr:postcode":"39010",
    "addr:street":"Calle De San Luis",
    "iso:country":"ES",
    "sg:address":"Calle de San Luis, 22",
    "sg:city":"Santander",
    "sg:orig_category":"Molduras, Junquillos, Listones Y Molduras Perforadas",
    "sg:phone":"+34 942 37 61 51",
    "sg:postcode":"39010",
    "sg:province":"Cantabria",
    "wof:name":"Rodriguez Garcia Ignacio",
    "wof:placetype":"venue"
},
  "geometry": {"coordinates":[-3.8160119057,43.4618148804],"type":"Point"}
}