{
  "type": "Feature",
  "properties": {
    "addr:full":"Calle de Gorbeia, 14 Zubiaur Vizcaya 48410",
    "addr:housenumber":"14",
    "addr:postcode":"48410",
    "addr:street":"Calle De Gorbeia",
    "iso:country":"ES",
    "sg:address":"Calle de Gorbeia, 14",
    "sg:city":"Zubiaur",
    "sg:orig_category":"Automatizaci\u00d3n De Procesos Industriales Y De Edificaci\u00d3n (estudios, Instalaci\u00d3n)",
    "sg:phone":"+34 946 33 98 03",
    "sg:postcode":"48410",
    "sg:province":"Vizcaya",
    "sg:website":"www.ingenet.es",
    "wof:name":"Ingenet Ingenieria De Informatica Y Control S.l.",
    "wof:placetype":"venue"
},
  "geometry": {"coordinates":[-2.9089961052,43.1062583923],"type":"Point"}
}