{
  "type": "Feature",
  "properties": {
    "iso:country":"ES",
    "sg:address":"Avda Deportista Miriam Blasco, 1",
    "sg:city":"Alacant",
    "sg:orig_category":"Cobro De Pr\u00c9stamos",
    "sg:phone":"+34 965 23 34 50",
    "sg:postcode":"03...",
    "sg:province":"Alicante",
    "wof:name":"Gestion Tributaria Territorial",
    "wof:placetype":"venue"
},
  "geometry": {"coordinates":[-0.4333190024,38.365436554],"type":"Point"}
}