{
  "type": "Feature",
  "properties": {
    "iso:country":"ES",
    "sg:address":"Carrer de Licoristes, S/n",
    "sg:city":"Valls",
    "sg:orig_category":"Negocio De Madera",
    "sg:phone":"+34 977 60 16 37",
    "sg:postcode":"43800",
    "sg:province":"Tarragona",
    "wof:name":"Morera Cinc S.l.",
    "wof:placetype":"venue"
},
  "geometry": {"coordinates":[1.2717380524,41.3125610352],"type":"Point"}
}