{
  "type": "Feature",
  "properties": {
    "iso:country":"ES",
    "sg:address":"Calle de Tirso De Molina, 5",
    "sg:city":"Granada",
    "sg:classifiers":[
        {
            "category":"Personal",
            "subcategory":"Barber",
            "type":"Services"
        }
    ],
    "sg:phone":"+34 958 13 56 56",
    "sg:postcode":"18006",
    "sg:province":"Granada",
    "sg:tags":[
        "caballeros",
        "de",
        "peluqueros"
    ],
    "wof:name":"Fernandez Miranda Jose Antonio",
    "wof:placetype":"venue"
},
  "geometry": {"coordinates":[-3.5946938992,37.1654167175],"type":"Point"}
}