{
  "type": "Feature",
  "properties": {
    "addr:full":"Calle de Calderon De La Barca, 2 Santomera Murcia 30140",
    "addr:housenumber":"2",
    "addr:postcode":"30140",
    "addr:street":"Calle De Calderon De La Barca",
    "iso:country":"ES",
    "sg:address":"Calle de Calderon De La Barca, 2",
    "sg:city":"Santomera",
    "sg:orig_category":"Zapatos (al Por Menor)",
    "sg:phone":"+34 968 86 34 59",
    "sg:postcode":"30140",
    "sg:province":"Murcia",
    "wof:name":"Discolmed S.l.",
    "wof:placetype":"venue"
},
  "geometry": {"coordinates":[-1.0527837276,38.0613327026],"type":"Point"}
}