{
  "type": "Feature",
  "properties": {
    "addr:full":"Calle de Veinticuatro, 32 Navalquejigo Madrid 28280",
    "addr:housenumber":"32",
    "addr:postcode":"28280",
    "addr:street":"Calle De Veinticuatro",
    "iso:country":"ES",
    "sg:address":"Calle de Veinticuatro, 32",
    "sg:city":"Navalquejigo",
    "sg:orig_category":"Peritos Mar\u00cdtimos",
    "sg:phone":"+34 918 53 45 96",
    "sg:postcode":"28280",
    "sg:province":"Madrid",
    "wof:name":"F.e.m. Shipbrokers S.l.",
    "wof:placetype":"venue"
},
  "geometry": {"coordinates":[-4.1260890961,40.5817756653],"type":"Point"}
}