{
  "type": "Feature",
  "properties": {
    "iso:country":"ES",
    "sg:address":"Calle de San Antonio, 25",
    "sg:city":"Aranda Duero",
    "sg:orig_category":"Empresas De Pintura Y Revestimientos",
    "sg:phone":"+34 947 50 21 71",
    "sg:postcode":"09400",
    "sg:province":"Burgos",
    "wof:name":"Pinturas Nuevo Estilo S.l.",
    "wof:placetype":"venue"
},
  "geometry": {"coordinates":[-3.6865971088,41.6727371216],"type":"Point"}
}