{
  "type": "Feature",
  "properties": {
    "iso:country":"ES",
    "sg:address":"Calle de Colon, 45",
    "sg:city":"Linea De La Concepcion",
    "sg:orig_category":"Reposter\u00cdas",
    "sg:phone":"+34 956 17 17 86",
    "sg:postcode":"11300",
    "sg:province":"C\u00e1diz",
    "wof:name":"Camacho Tobaruela Ignacla",
    "wof:placetype":"venue"
},
  "geometry": {"coordinates":[-5.3522510529,36.1663322449],"type":"Point"}
}