{
  "type": "Feature",
  "properties": {
    "addr:full":"Av Goles De L'ebre, 299 Deltebre Tarragona 43580",
    "addr:housenumber":"299",
    "addr:postcode":"43580",
    "addr:street":"Av Goles De L'Ebre",
    "iso:country":"ES",
    "sg:address":"Av Goles De L'ebre, 299",
    "sg:city":"Deltebre",
    "sg:orig_category":"Inmobiliaria (agencias)",
    "sg:phone":"+34 977 48 24 24",
    "sg:postcode":"43580",
    "sg:province":"Tarragona",
    "wof:name":"Piso Perfecto S.l.",
    "wof:placetype":"venue"
},
  "geometry": {"coordinates":[0.7402570248,40.7168083191],"type":"Point"}
}