{
  "type": "Feature",
  "properties": {
    "iso:country":"ES",
    "sg:address":"Carrer de Santa Madrona, 6",
    "sg:city":"Mora D'ebre",
    "sg:orig_category":"Peluquer\u00cdas, Peluquer\u00cda Mixta",
    "sg:phone":"+34 977 40 03 02",
    "sg:postcode":"43740",
    "sg:province":"Tarragona",
    "wof:name":"Perruquerria Perfils S.c.p.",
    "wof:placetype":"venue"
},
  "geometry": {"coordinates":[1.2572339773,41.1183700562],"type":"Point"}
}