{
  "type": "Feature",
  "properties": {
    "iso:country":"ES",
    "sg:address":"Ctra Madrid-cadiz (monte Alto), Km. 0430,0",
    "sg:city":"Carlota",
    "sg:orig_category":"Florister\u00cdas",
    "sg:phone":"+34 957 30 09 96",
    "sg:postcode":"14100",
    "sg:province":"C\u00f3rdoba",
    "wof:name":"Echevarria Zafra Juan Antonio",
    "wof:placetype":"venue"
},
  "geometry": {"coordinates":[-4.9374890327,37.6685142517],"type":"Point"}
}