{
  "type": "Feature",
  "properties": {
    "addr:full":"Carrer de Sant Pere, 35 Altea Alicante 03590",
    "addr:housenumber":"35",
    "addr:postcode":"03590",
    "addr:street":"Carrer De Sant Pere",
    "iso:country":"ES",
    "sg:address":"Carrer de Sant Pere, 35",
    "sg:city":"Altea",
    "sg:orig_category":"Centros De Coordinaci\u00d3n",
    "sg:phone":"+34 966 88 51 78",
    "sg:postcode":"03590",
    "sg:province":"Alicante",
    "wof:name":"Guinzo Perez Jesus Liberto",
    "wof:placetype":"venue"
},
  "geometry": {"coordinates":[-0.0520259999,38.5949897766],"type":"Point"}
}