{
  "type": "Feature",
  "properties": {
    "addr:full":"Calle de Principe De Vergara, 252 Madrid Madrid 28016",
    "addr:housenumber":"252",
    "addr:postcode":"28016",
    "addr:street":"Calle De Principe De Vergara",
    "iso:country":"ES",
    "sg:address":"Calle de Principe De Vergara, 252",
    "sg:city":"Madrid",
    "sg:orig_category":"Centros M\u00c9dicos Y Sociales, Dispensarios",
    "sg:phone":"+34 914 43 00 21",
    "sg:postcode":"28016",
    "sg:province":"Madrid",
    "wof:name":"Jacobs  Thomas Q.",
    "wof:placetype":"venue"
},
  "geometry": {"coordinates":[-3.6769459248,40.4559288025],"type":"Point"}
}