{
  "type": "Feature",
  "properties": {
    "addr:full":"Calle de Favareta, 31 Alzira Valencia 46600",
    "addr:housenumber":"31",
    "addr:postcode":"46600",
    "addr:street":"Calle De Favareta",
    "iso:country":"ES",
    "sg:address":"Calle de Favareta, 31",
    "sg:city":"Alzira",
    "sg:orig_category":"Librer\u00cdas",
    "sg:phone":"+34 962 41 87 99",
    "sg:postcode":"46600",
    "sg:province":"Valencia",
    "wof:name":"Fruits Secs I Llepolies S.l.l.",
    "wof:placetype":"venue"
},
  "geometry": {"coordinates":[-0.4307869971,39.1538047791],"type":"Point"}
}