{
  "type": "Feature",
  "properties": {
    "addr:full":"M Rosario Hernandez Santana, 2 Telde Las Palmas 35200",
    "addr:postcode":"35200",
    "addr:street":"Santana",
    "iso:country":"ES",
    "sg:address":"M Rosario Hernandez Santana, 2",
    "sg:city":"Telde",
    "sg:orig_category":"Ingenier\u00cda, Centros De Estudios (diversos)",
    "sg:phone":"+34 928 69 14 14",
    "sg:postcode":"35200",
    "sg:province":"Las Palmas",
    "wof:name":"Garcia Martel Artemio",
    "wof:placetype":"venue"
},
  "geometry": {"coordinates":[-15.4157962799,27.9997558594],"type":"Point"}
}