{
  "type": "Feature",
  "properties": {
    "iso:country":"ES",
    "sg:address":"Calle de Antonio Lopez, 6",
    "sg:city":"Madrid",
    "sg:orig_category":"Casquer\u00cda (al Por Menor)",
    "sg:phone":"+34 915 60 93 88",
    "sg:postcode":"28019",
    "sg:province":"Madrid",
    "wof:name":"Vazquez Garcia Francisco",
    "wof:placetype":"venue"
},
  "geometry": {"coordinates":[-3.7142949104,40.3969955444],"type":"Point"}
}