{
  "type": "Feature",
  "properties": {
    "addr:full":"Carrer de Sant Quinti, 20 Sant Pere De Riudebitlles Barcelona 08776",
    "addr:housenumber":"20",
    "addr:postcode":"08776",
    "addr:street":"Carrer De Sant Quinti",
    "iso:country":"ES",
    "sg:address":"Carrer de Sant Quinti, 20",
    "sg:city":"Sant Pere De Riudebitlles",
    "sg:orig_category":"Fabricaci\u00d3n, Importaci\u00d3n De L\u00c1mparas Y Bombillas",
    "sg:phone":"+34 938 99 71 31",
    "sg:postcode":"08776",
    "sg:province":"Barcelona",
    "wof:name":"Gumarcris S.l.",
    "wof:placetype":"venue"
},
  "geometry": {"coordinates":[1.6999000311,41.4530715942],"type":"Point"}
}