{
  "type": "Feature",
  "properties": {
    "addr:full":"Calle de Alameda De Santa Eufemia, 26 Tomares Sevilla 41940",
    "addr:housenumber":"26",
    "addr:postcode":"41940",
    "addr:street":"Calle De Alameda De Santa Eufemia",
    "iso:country":"ES",
    "sg:address":"Calle de Alameda De Santa Eufemia, 26",
    "sg:city":"Tomares",
    "sg:orig_category":"Arquitectos",
    "sg:phone":"+34 954 15 72 07",
    "sg:postcode":"41940",
    "sg:province":"Sevilla",
    "wof:name":"Artefacto S.c.",
    "wof:placetype":"venue"
},
  "geometry": {"coordinates":[-6.043659687,37.3759040833],"type":"Point"}
}