{
  "type": "Feature",
  "properties": {
    "addr:full":"Calle de Isilla, 3 Aranda Duero Burgos 09400",
    "addr:housenumber":"3",
    "addr:postcode":"09400",
    "addr:street":"Calle De Isilla",
    "iso:country":"ES",
    "sg:address":"Calle de Isilla, 3",
    "sg:city":"Aranda Duero",
    "sg:orig_category":"Ropa Para Se\u00d1oras Y Caballeros (al Por Menor)",
    "sg:phone":"+34 947 50 43 10",
    "sg:postcode":"09400",
    "sg:province":"Burgos",
    "wof:name":"Aubeso Renedo Maria Teresa",
    "wof:placetype":"venue"
},
  "geometry": {"coordinates":[-3.6851458549,41.6716804504],"type":"Point"}
}