{
  "type": "Feature",
  "properties": {
    "addr:full":"La Cadellada, S/n Oviedo Asturias 33011",
    "addr:housenumber":"s / n",
    "addr:postcode":"33011",
    "iso:country":"ES",
    "sg:address":"La Cadellada, S/n",
    "sg:city":"Oviedo",
    "sg:orig_category":"Cl\u00cdnicas Psiqui\u00c1tricas",
    "sg:phone":"+34 985 28 03 31",
    "sg:postcode":"33011",
    "sg:province":"Asturias",
    "wof:name":"Servicio De Salud Del Principado De Asturias",
    "wof:placetype":"venue"
},
  "geometry": {"coordinates":[-5.8241991997,43.3843231201],"type":"Point"}
}