{
  "type": "Feature",
  "properties": {
    "iso:country":"ES",
    "sg:address":"Calle de Derechos, 1",
    "sg:city":"Valencia",
    "sg:orig_category":"Cl\u00cdnicas Dentales",
    "sg:phone":"+34 963 92 38 19",
    "sg:postcode":"46001",
    "sg:province":"Valencia",
    "wof:name":"Clinica Guerrero S.l.",
    "wof:placetype":"venue"
},
  "geometry": {"coordinates":[-0.3762061,39.473197937],"type":"Point"}
}