{
  "type": "Feature",
  "properties": {
    "addr:full":"Calle de Puentezuelas, 18 Granada Granada 18002",
    "addr:housenumber":"18",
    "addr:postcode":"18002",
    "addr:street":"Calle De Puentezuelas",
    "iso:country":"ES",
    "sg:address":"Calle de Puentezuelas, 18",
    "sg:city":"Granada",
    "sg:orig_category":"Abogados",
    "sg:phone":"+34 958 52 24 16",
    "sg:postcode":"18002",
    "sg:province":"Granada",
    "wof:name":"Tejerizo Linares German Enrique",
    "wof:placetype":"venue"
},
  "geometry": {"coordinates":[-3.601444006,37.1736564636],"type":"Point"}
}