{
  "type": "Feature",
  "properties": {
    "addr:full":"Pase Juan Carlos I, 113 Valladolid Valladolid 47012",
    "addr:housenumber":"113",
    "addr:postcode":"47012",
    "addr:street":"Carlos I",
    "iso:country":"ES",
    "sg:address":"Pase Juan Carlos I, 113",
    "sg:city":"Valladolid",
    "sg:orig_category":"Distribuci\u00d3n De Petr\u00d3leo Y Derivados",
    "sg:phone":"+34 983 29 03 06",
    "sg:postcode":"47012",
    "sg:province":"Valladolid",
    "sg:website":"www.cepsa.es",
    "wof:name":"Cedipsa Compa\u00d1ia Espa\u00d1ola Distribuidora De Petroleos S.a.",
    "wof:placetype":"venue"
},
  "geometry": {"coordinates":[-4.695494175,41.6288452148],"type":"Point"}
}