{
  "type": "Feature",
  "properties": {
    "addr:full":"Calle de Carmen, 8 Torremolinos M\u00e1laga 29620",
    "addr:housenumber":"8",
    "addr:postcode":"29620",
    "addr:street":"Calle De Carmen;Ma\u0301Laga",
    "iso:country":"ES",
    "sg:address":"Calle de Carmen, 8",
    "sg:city":"Torremolinos",
    "sg:orig_category":"Cajas De Ahorro",
    "sg:phone":"+34 952 38 24 87",
    "sg:postcode":"29620",
    "sg:province":"M\u00e1laga",
    "wof:name":"Unicaja",
    "wof:placetype":"venue"
},
  "geometry": {"coordinates":[-4.5025458336,36.6119918823],"type":"Point"}
}