{
  "type": "Feature",
  "properties": {
    "addr:full":"Carrer de Sant Pere Mitja, 68 Barcelona Barcelona 08003",
    "addr:housenumber":"68",
    "addr:postcode":"08003",
    "addr:street":"Carrer De Sant;Mitja",
    "iso:country":"ES",
    "sg:address":"Carrer de Sant Pere Mitja, 68",
    "sg:city":"Barcelona",
    "sg:orig_category":"Negocio De Materiales De Construcci\u00d3n",
    "sg:phone":"+34 932 68 32 30",
    "sg:postcode":"08003",
    "sg:province":"Barcelona",
    "wof:name":"Prat Martin Manuel",
    "wof:placetype":"venue"
},
  "geometry": {"coordinates":[2.1790120602,41.3890609741],"type":"Point"}
}