{
  "type": "Feature",
  "properties": {
    "addr:full":"Finca Bellavista, S/n Monforte Cid Alicante 03670",
    "addr:housenumber":"s",
    "addr:postcode":"03670",
    "addr:street":"/ N",
    "iso:country":"ES",
    "sg:address":"Finca Bellavista, S/n",
    "sg:city":"Monforte Cid",
    "sg:orig_category":"M\u00c1rmoles, Granitos Y Piedras Naturales",
    "sg:phone":"+34 965 62 01 31",
    "sg:postcode":"03670",
    "sg:province":"Alicante",
    "wof:name":"Marmoles Playmar S.l",
    "wof:placetype":"venue"
},
  "geometry": {"coordinates":[-0.7296299934,38.3807296753],"type":"Point"}
}