{
  "type": "Feature",
  "properties": {
    "addr:full":"Ctra Malaga (de), 91 Granada Granada 18015",
    "addr:housenumber":"91",
    "addr:postcode":"18015",
    "addr:street":"Ctra Malaga De",
    "iso:country":"ES",
    "sg:address":"Ctra Malaga (de), 91",
    "sg:city":"Granada",
    "sg:orig_category":"Empresas De Limpieza",
    "sg:phone":"+34 958 29 48 45",
    "sg:postcode":"18015",
    "sg:province":"Granada",
    "sg:website":"www.aerus-globaltek.com",
    "wof:name":"Molina Todo Para La Limpieza",
    "wof:placetype":"venue"
},
  "geometry": {"coordinates":[-3.6259379387,37.1891975403],"type":"Point"}
}