{
  "type": "Feature",
  "properties": {
    "addr:full":"Cmno Rosales (somio), 5 Gijon Asturias 33203",
    "addr:housenumber":"5",
    "addr:postcode":"33203",
    "addr:street":"Cmno Rosales Somio",
    "iso:country":"ES",
    "sg:address":"Cmno Rosales (somio), 5",
    "sg:city":"Gijon",
    "sg:orig_category":"Importaci\u00d3n",
    "sg:phone":"+34 985 36 32 32",
    "sg:postcode":"33203",
    "sg:province":"Asturias",
    "wof:name":"Loring Armada Maria Magdalena",
    "wof:placetype":"venue"
},
  "geometry": {"coordinates":[-5.6268200874,43.5349349976],"type":"Point"}
}