{
  "type": "Feature",
  "properties": {
    "iso:country":"ES",
    "sg:address":"Calle de Nu\u00d1ez De Arce, 7",
    "sg:city":"Valladolid",
    "sg:orig_category":"Centros P\u00dablicos De Formaci\u00d3n Profesional Y T\u00c9cnica",
    "sg:phone":"+34 983 30 38 02",
    "sg:postcode":"47002",
    "sg:province":"Valladolid",
    "sg:website":"www.enfermeriavalladolid.com",
    "wof:name":"Colegio Oficial De Ayudantes Tecnicos Sanitarios Y Diplomados En Enfermeria De Valladolid",
    "wof:placetype":"venue"
},
  "geometry": {"coordinates":[-4.7233338356,41.6519966125],"type":"Point"}
}