{
  "type": "Feature",
  "properties": {
    "iso:country":"ES",
    "sg:address":"Martin Azpilcueta, 22",
    "sg:city":"Iru\u00f1a",
    "sg:orig_category":"Librer\u00cdas",
    "sg:phone":"+34 948 25 48 23",
    "sg:postcode":"31011",
    "sg:province":"Navarra",
    "wof:name":"Huarte Larumbe Blanca Esther",
    "wof:placetype":"venue"
},
  "geometry": {"coordinates":[-1.6619839668,42.8133735657],"type":"Point"}
}