{
  "type": "Feature",
  "properties": {
    "addr:full":"Calle de Cruz Del Estudiante, 69 Puente-genil C\u00f3rdoba 14500",
    "addr:housenumber":"69",
    "addr:postcode":"14500",
    "addr:street":"Calle De Cruz Del Estudiante;Co\u0301Rdoba",
    "iso:country":"ES",
    "sg:address":"Calle de Cruz Del Estudiante, 69",
    "sg:city":"Puente-genil",
    "sg:orig_category":"Ense\u00d1anza Variada",
    "sg:phone":"+34 957 60 39 97",
    "sg:postcode":"14500",
    "sg:province":"C\u00f3rdoba",
    "wof:name":"Formacion E Innovacion Tenologica De Andalucia S.l.",
    "wof:placetype":"venue"
},
  "geometry": {"coordinates":[-4.7672743797,37.389125824],"type":"Point"}
}