{
  "type": "Feature",
  "properties": {
    "addr:full":"Industrias, 19 Arroyo De La Encomienda Valladolid 47195",
    "addr:housenumber":"19",
    "addr:postcode":"47195",
    "addr:street":"Industrias",
    "iso:country":"ES",
    "sg:address":"Industrias, 19",
    "sg:city":"Arroyo De La Encomienda",
    "sg:orig_category":"Farmacias",
    "sg:phone":"+34 983 40 80 69",
    "sg:postcode":"47195",
    "sg:province":"Valladolid",
    "wof:name":"Carrascal Del Solar Maria Concepcion",
    "wof:placetype":"venue"
},
  "geometry": {"coordinates":[-4.7737689018,41.6252746582],"type":"Point"}
}