{
  "type": "Feature",
  "properties": {
    "iso:country":"ES",
    "sg:address":"Calle de Juliana Sancho, 13",
    "sg:city":"Madrid",
    "sg:orig_category":"Transporte En General",
    "sg:phone":"+34 917 77 36 37",
    "sg:postcode":"28018",
    "sg:province":"Madrid",
    "wof:name":"Fandico S.l.",
    "wof:placetype":"venue"
},
  "geometry": {"coordinates":[-3.6556060314,40.3871383667],"type":"Point"}
}