{
  "type": "Feature",
  "properties": {
    "addr:full":"La Rioja(base Dos Mil), S/n Lorqui Murcia 30564",
    "addr:housenumber":"s",
    "addr:postcode":"30564",
    "addr:street":"/ N",
    "iso:country":"ES",
    "sg:address":"La Rioja(base Dos Mil), S/n",
    "sg:city":"Lorqui",
    "sg:orig_category":"Maquinaria Para Industrias Diversas",
    "sg:phone":"+34 968 69 45 48",
    "sg:postcode":"30564",
    "sg:province":"Murcia",
    "wof:name":"Fabricacion Especial De Maquinarias Y Piecerio S.l",
    "wof:placetype":"venue"
},
  "geometry": {"coordinates":[-1.2308739424,38.101650238],"type":"Point"}
}