{
  "type": "Feature",
  "properties": {
    "addr:full":"Poife, 3 Ferreries Islas Baleares 07750",
    "addr:housenumber":"3",
    "addr:postcode":"07750",
    "addr:street":"Poife",
    "iso:country":"ES",
    "sg:address":"Poife, 3",
    "sg:city":"Ferreries",
    "sg:orig_category":"Metales (labores, Pulido)",
    "sg:phone":"+34 971 15 50 85",
    "sg:postcode":"07750",
    "sg:province":"Islas Baleares",
    "wof:name":"Pons Janer Antonio",
    "wof:placetype":"venue"
},
  "geometry": {"coordinates":[4.0080771446,39.9823303223],"type":"Point"}
}