{
  "type": "Feature",
  "properties": {
    "addr:full":"Avda. Monte Aljarafe, 43 Mairena Aljarafe Sevilla 41927",
    "addr:housenumber":"43",
    "addr:postcode":"41927",
    "addr:street":"Avda. Monte Aljarafe",
    "iso:country":"ES",
    "sg:address":"Avda. Monte Aljarafe, 43",
    "sg:city":"Mairena Aljarafe",
    "sg:orig_category":"M\u00c9dicos: Foniatr\u00cda Y Logopedia",
    "sg:phone":"+34 954 76 11 00",
    "sg:postcode":"41927",
    "sg:province":"Sevilla",
    "wof:name":"Hortigosa Utrera Jose Antonio",
    "wof:placetype":"venue"
},
  "geometry": {"coordinates":[-6.0442042351,37.353477478],"type":"Point"}
}