{
  "type": "Feature",
  "properties": {
    "addr:full":"Carrer de Juan Sebastian Elcano, 19 Cambrils Tarragona 43850",
    "addr:housenumber":"19",
    "addr:postcode":"43850",
    "addr:street":"Carrer De Juan Sebastian Elcano",
    "iso:country":"ES",
    "sg:address":"Carrer de Juan Sebastian Elcano, 19",
    "sg:city":"Cambrils",
    "sg:orig_category":"Peluqueros: De Se\u00d1oras",
    "sg:phone":"+34 977 79 10 18",
    "sg:postcode":"43850",
    "sg:province":"Tarragona",
    "wof:name":"Salvatoriello  Marta",
    "wof:placetype":"venue"
},
  "geometry": {"coordinates":[1.0589009523,41.0667991638],"type":"Point"}
}