{
  "type": "Feature",
  "properties": {
    "addr:full":"Carrer de Rossello, 122 Barcelona Barcelona 08036",
    "addr:housenumber":"122",
    "addr:postcode":"08036",
    "addr:street":"Carrer De Rossello",
    "iso:country":"ES",
    "sg:address":"Carrer de Rossello, 122",
    "sg:city":"Barcelona",
    "sg:orig_category":"Ropa Para Ni\u00d1os (al Por Menor)",
    "sg:phone":"+34 934 53 66 79",
    "sg:postcode":"08036",
    "sg:province":"Barcelona",
    "wof:name":"Catalan Ventura Asuncion",
    "wof:placetype":"venue"
},
  "geometry": {"coordinates":[2.1516571045,41.3889083862],"type":"Point"}
}