{
  "type": "Feature",
  "properties": {
    "iso:country":"ES",
    "sg:address":"Avda Galtzaraborda, 3",
    "sg:city":"Errenteria",
    "sg:orig_category":"Ense\u00d1anza: Comercio, Gesti\u00d3n, Inform\u00c1tica",
    "sg:phone":"+34 943 51 59 82",
    "sg:postcode":"20100",
    "sg:province":"Guip\u00f9zcoa",
    "wof:name":"Torrealdea Folgado C.b.",
    "wof:placetype":"venue"
},
  "geometry": {"coordinates":[-1.9029749632,43.3118133545],"type":"Point"}
}