{
  "type": "Feature",
  "properties": {
    "iso:country":"ES",
    "sg:address":"Carrer de Merce Rodoreda, 9",
    "sg:city":"Casco Urbano",
    "sg:orig_category":"Porcelana Decorativa",
    "sg:phone":"+34 938 41 16 81",
    "sg:postcode":"08450",
    "sg:province":"Barcelona",
    "wof:name":"Alcantara Rajo Raquel Maria",
    "wof:placetype":"venue"
},
  "geometry": {"coordinates":[2.2800750732,41.599155426],"type":"Point"}
}