{
  "type": "Feature",
  "properties": {
    "iso:country":"ES",
    "sg:address":"Carrer de Bonaire, 2",
    "sg:city":"Barcelona",
    "sg:orig_category":"Arquitectos",
    "sg:phone":"+34 933 15 25 78",
    "sg:postcode":"08003",
    "sg:province":"Barcelona",
    "wof:name":"Estudio De Arquitectura Ba\u00f1os Melendre S.l.",
    "wof:placetype":"venue"
},
  "geometry": {"coordinates":[2.1835200787,41.3840446472],"type":"Point"}
}