{
  "type": "Feature",
  "properties": {
    "iso:country":"ES",
    "sg:address":"Calle de Brasil, 16",
    "sg:city":"Sevilla",
    "sg:classifiers":[
        {
            "category":"Manufacturing",
            "subcategory":"Building Materials",
            "type":"Manufacturing & Wholesale Goods"
        }
    ],
    "sg:phone":"+34 954 61 19 88",
    "sg:postcode":"41013",
    "sg:province":"Sevilla",
    "sg:tags":[
        "cemento",
        "y",
        "de",
        "fabricaci\u00d3n",
        "cal"
    ],
    "wof:name":"Rodio Cimentaciones Especiales S.a.",
    "wof:placetype":"venue"
},
  "geometry": {"coordinates":[-5.9830651283,37.3736381531],"type":"Point"}
}