{
  "type": "Feature",
  "properties": {
    "addr:full":"Plaz Constitucion (de La), 8 Torrevieja Alicante 03180",
    "addr:postcode":"03180",
    "iso:country":"ES",
    "sg:address":"Plaz Constitucion (de La), 8",
    "sg:city":"Torrevieja",
    "sg:orig_category":"Administradores De Bienes Y Delegados De Comunidades De Propietarios",
    "sg:phone":"+34 966 70 04 27",
    "sg:postcode":"03180",
    "sg:province":"Alicante",
    "wof:name":"Administraciones E Inversiones Torrevieja S.l.",
    "wof:placetype":"venue"
},
  "geometry": {"coordinates":[-0.6824756861,37.9774284363],"type":"Point"}
}