{
  "type": "Feature",
  "properties": {
    "iso:country":"ES",
    "sg:address":"Calle de Torreta De Miramar, 6",
    "sg:city":"Valencia",
    "sg:orig_category":"Asesor\u00cda Fiscal Y Jur\u00cddica",
    "sg:phone":"+34 963 69 81 68",
    "sg:postcode":"46020",
    "sg:province":"Valencia",
    "wof:name":"Carrasco Navarro Juan Carlos",
    "wof:placetype":"venue"
},
  "geometry": {"coordinates":[-0.3623780012,39.4876747131],"type":"Point"}
}