{
  "type": "Feature",
  "properties": {
    "addr:full":"Carrer de Moli Dels Frares, 13 Sant Vicen\u00c7 Dels Horts Barcelona 08620",
    "addr:housenumber":"13",
    "addr:postcode":"08620",
    "addr:street":"Carrer De Moli Dels Frares",
    "iso:country":"ES",
    "sg:address":"Carrer de Moli Dels Frares, 13",
    "sg:city":"Sant Vicen\u00c7 Dels Horts",
    "sg:orig_category":"Molduras, Junquillos, Listones Y Molduras Perforadas",
    "sg:phone":"+34 936 56 75 12",
    "sg:postcode":"08620",
    "sg:province":"Barcelona",
    "wof:name":"Miranius S.l.",
    "wof:placetype":"venue"
},
  "geometry": {"coordinates":[1.9992687702,41.4023895264],"type":"Point"}
}