{
  "type": "Feature",
  "properties": {
    "iso:country":"ES",
    "sg:address":"Calle de Juan De Velasco, 4",
    "sg:city":"Vitoria-gasteiz",
    "sg:orig_category":"Promotores Constructores",
    "sg:phone":"+34 945 17 60 69",
    "sg:postcode":"01010",
    "sg:province":"\u00c1lava",
    "wof:name":"Construcciones Lorosan S.coop.",
    "wof:placetype":"venue"
},
  "geometry": {"coordinates":[-2.6971850395,42.8577384949],"type":"Point"}
}