{
  "type": "Feature",
  "properties": {
    "addr:full":"Pg Torroja (de), S/n Tarragona Tarragona 43007",
    "addr:postcode":"43007",
    "addr:street":"Pg Torroja De S / N",
    "iso:country":"ES",
    "sg:address":"Pg Torroja (de), S/n",
    "sg:city":"Tarragona",
    "sg:orig_category":"Asociaciones Y Clubs Deportivos",
    "sg:phone":"+34 977 23 20 34",
    "sg:postcode":"43007",
    "sg:province":"Tarragona",
    "wof:name":"Club Natacio Tarraco",
    "wof:placetype":"venue"
},
  "geometry": {"coordinates":[1.2614860535,41.1190795898],"type":"Point"}
}