{
  "type": "Feature",
  "properties": {
    "addr:full":"C/ Girones, 25 Celra Girona 17460",
    "addr:housenumber":"25",
    "addr:postcode":"17460",
    "addr:street":"C / Girones",
    "iso:country":"ES",
    "sg:address":"C/ Girones, 25",
    "sg:city":"Celra",
    "sg:orig_category":"Empresas De Desmonte",
    "sg:phone":"+34 972 49 20 43",
    "sg:postcode":"17460",
    "sg:province":"Girona",
    "wof:name":"Soler Juanola Jaume",
    "wof:placetype":"venue"
},
  "geometry": {"coordinates":[2.8742320538,42.0255393982],"type":"Point"}
}