{
  "type": "Feature",
  "properties": {
    "addr:full":"Carr Carretera De Lliria, 15 Burjassot Valencia 46100",
    "addr:housenumber":"15",
    "addr:postcode":"46100",
    "addr:street":"Carr Carretera De Lliria",
    "iso:country":"ES",
    "sg:address":"Carr Carretera De Lliria, 15",
    "sg:city":"Burjassot",
    "sg:orig_category":"Droguer\u00cdas (al Por Menor)",
    "sg:phone":"+34 963 63 14 74",
    "sg:postcode":"46100",
    "sg:province":"Valencia",
    "wof:name":"Alonso Palacios Francisco",
    "wof:placetype":"venue"
},
  "geometry": {"coordinates":[-0.4129450023,39.5087242126],"type":"Point"}
}