{
  "type": "Feature",
  "properties": {
    "iso:country":"ES",
    "sg:address":"Cm\u00d1o Pinal, 55",
    "sg:city":"Gandara",
    "sg:orig_category":"M\u00c9dicos: Cirug\u00cda Urol\u00d3gica",
    "sg:phone":"+34 986 46 80 27",
    "sg:postcode":"36315",
    "sg:province":"Pontevedra",
    "wof:name":"Comesa\u00f1a Davila Enrique",
    "wof:placetype":"venue"
},
  "geometry": {"coordinates":[-8.7240085602,42.1735153198],"type":"Point"}
}