{
  "type": "Feature",
  "properties": {
    "iso:country":"ES",
    "sg:address":"Carrer de Prat De La Riba, 5",
    "sg:city":"Vendrell",
    "sg:orig_category":"M\u00c9dicos: Estomatolog\u00cda",
    "sg:phone":"+34 977 66 43 96",
    "sg:postcode":"43700",
    "sg:province":"Tarragona",
    "wof:name":"Alvarez Perez Rosario",
    "wof:placetype":"venue"
},
  "geometry": {"coordinates":[1.5359374285,41.2202339172],"type":"Point"}
}