{
  "type": "Feature",
  "properties": {
    "iso:country":"ES",
    "sg:address":"Ctra Barinaga, S/n",
    "sg:city":"Erbera",
    "sg:orig_category":"Maquinaria Para Industrias Diversas",
    "sg:phone":"+34 946 16 87 08",
    "sg:postcode":"48277",
    "sg:province":"Vizcaya",
    "wof:name":"Maguregui Arano Alberto",
    "wof:placetype":"venue"
},
  "geometry": {"coordinates":[-2.4781939983,43.2544898987],"type":"Point"}
}