{
  "type": "Feature",
  "properties": {
    "iso:country":"ES",
    "sg:address":"Cllo San Roque, 2",
    "sg:city":"Pinoso",
    "sg:orig_category":"Reposter\u00cdas",
    "sg:phone":"+34 965 47 73 49",
    "sg:postcode":"03650",
    "sg:province":"Alicante",
    "wof:name":"Panaderia Rico S.l.",
    "wof:placetype":"venue"
},
  "geometry": {"coordinates":[-1.0406390429,38.4035568237],"type":"Point"}
}