{
  "type": "Feature",
  "properties": {
    "iso:country":"ES",
    "sg:address":"Avda Virgen De Lidon, 3",
    "sg:city":"Castellon",
    "sg:orig_category":"Alimentaci\u00d3n General (al Por Menor)",
    "sg:phone":"+34 964 22 03 74",
    "sg:postcode":"12003",
    "sg:province":"Castell\u00f3n",
    "wof:name":"Sales Radiu Jaime",
    "wof:placetype":"venue"
},
  "geometry": {"coordinates":[-0.0077,39.9838409424],"type":"Point"}
}