{
  "type": "Feature",
  "properties": {
    "iso:country":"ES",
    "sg:address":"Rbla Ducs Palma De Mca, 7",
    "sg:city":"Palma",
    "sg:orig_category":"Costura (alta Costura, Creaci\u00d3n)",
    "sg:phone":"+34 971 72 20 85",
    "sg:postcode":"07003",
    "sg:province":"Islas Baleares",
    "wof:name":"Martin Gomez Carlos",
    "wof:placetype":"venue"
},
  "geometry": {"coordinates":[2.6500279903,39.5728874207],"type":"Point"}
}