{
  "type": "Feature",
  "properties": {
    "addr:full":"Calle de Carpinteros, 16 Malaga M\u00e1laga 29006",
    "addr:housenumber":"16",
    "addr:postcode":"29006",
    "addr:street":"Calle De Carpinteros;Ma\u0301Laga",
    "iso:country":"ES",
    "sg:address":"Calle de Carpinteros, 16",
    "sg:city":"Malaga",
    "sg:orig_category":"Maquinaria Para Industrias Diversas",
    "sg:phone":"+34 952 31 78 47",
    "sg:postcode":"29006",
    "sg:province":"M\u00e1laga",
    "wof:name":"Compresores Saez S. A.",
    "wof:placetype":"venue"
},
  "geometry": {"coordinates":[-4.4462881088,36.7078285217],"type":"Point"}
}