{
  "type": "Feature",
  "properties": {
    "addr:full":"Carrer de Josep Anselm Clave, 2 Palma Islas Baleares 07002",
    "addr:housenumber":"2",
    "addr:postcode":"07002",
    "addr:street":"Carrer De Josep Anselm Clave",
    "iso:country":"ES",
    "sg:address":"Carrer de Josep Anselm Clave, 2",
    "sg:city":"Palma",
    "sg:orig_category":"Inmobiliaria (agencias)",
    "sg:phone":"+34 971 71 69 46",
    "sg:postcode":"07002",
    "sg:province":"Islas Baleares",
    "wof:name":"S.mas C.b.",
    "wof:placetype":"venue"
},
  "geometry": {"coordinates":[2.6546800137,39.5738143921],"type":"Point"}
}