{
  "type": "Feature",
  "properties": {
    "addr:full":"Plaz Seo (la), 12 Tarazona Zaragoza 50500",
    "addr:postcode":"50500",
    "iso:country":"ES",
    "sg:address":"Plaz Seo (la), 12",
    "sg:city":"Tarazona",
    "sg:orig_category":"M\u00c9dicos: Pediatr\u00cda. Enfermedades De Los Ni\u00d1os",
    "sg:phone":"+34 976 64 21 59",
    "sg:postcode":"50500",
    "sg:province":"Zaragoza",
    "wof:name":"Rubio Iba\u00f1ez Fernando",
    "wof:placetype":"venue"
},
  "geometry": {"coordinates":[-1.722843051,41.9045448303],"type":"Point"}
}