{
  "type": "Feature",
  "properties": {
    "iso:country":"ES",
    "sg:address":"Can Male, S/n",
    "sg:city":"Lli\u00e7a Amunt",
    "sg:orig_category":"Productos Qu\u00cdmicos (fabricaci\u00d3n, Al Por Mayor)",
    "sg:phone":"+34 938 60 90 00",
    "sg:postcode":"08186",
    "sg:province":"Barcelona",
    "sg:website":"www.biokit.com",
    "wof:name":"Biokit S.a.",
    "wof:placetype":"venue"
},
  "geometry": {"coordinates":[2.2512130737,41.6102142334],"type":"Point"}
}