{
  "type": "Feature",
  "properties": {
    "addr:full":"Cami Lloveras, S/n S. Feliu Codines Barcelona 08182",
    "addr:postcode":"08182",
    "addr:street":"Lloveras S / N S. Feliu",
    "iso:country":"ES",
    "sg:address":"Cami Lloveras, S/n",
    "sg:city":"S. Feliu Codines",
    "sg:orig_category":"Muebles Y Accesorios Para Cocinas Y Cuartos De Ba\u00d1o (al Por Menor)",
    "sg:phone":"+34 938 66 13 28",
    "sg:postcode":"08182",
    "sg:province":"Barcelona",
    "wof:name":"Mobles Clapers S.l.",
    "wof:placetype":"venue"
},
  "geometry": {"coordinates":[2.1647150517,41.6881217957],"type":"Point"}
}