{
  "type": "Feature",
  "properties": {
    "addr:full":"Calle de Vega La, 20 Nava Asturias 33520",
    "addr:housenumber":"20",
    "addr:postcode":"33520",
    "addr:street":"Calle De Vega La",
    "iso:country":"ES",
    "sg:address":"Calle de Vega La, 20",
    "sg:city":"Nava",
    "sg:orig_category":"Electricidad: Instalaciones Industriales",
    "sg:phone":"+34 985 71 72 42",
    "sg:postcode":"33520",
    "sg:province":"Asturias",
    "wof:name":"Vega Ordo\u00f1ez Roberto",
    "wof:placetype":"venue"
},
  "geometry": {"coordinates":[-5.5083208084,43.3589096069],"type":"Point"}
}