{
  "type": "Feature",
  "properties": {
    "addr:full":"Calle de Val, 24 Traspinedo Valladolid 47330",
    "addr:housenumber":"24",
    "addr:postcode":"47330",
    "addr:street":"Calle De Val",
    "iso:country":"ES",
    "sg:address":"Calle de Val, 24",
    "sg:city":"Traspinedo",
    "sg:orig_category":"Cajas Para Embalar",
    "sg:phone":"+34 983 68 25 52",
    "sg:postcode":"47330",
    "sg:province":"Valladolid",
    "wof:name":"Caja Rural Del Duero",
    "wof:placetype":"venue"
},
  "geometry": {"coordinates":[-4.4767022133,41.5763702393],"type":"Point"}
}