{
  "type": "Feature",
  "properties": {
    "iso:country":"ES",
    "sg:address":"Calle de Shakespeare, 93",
    "sg:city":"Pardilla",
    "sg:orig_category":"Producci\u00d3n, Venta De Productos De Agricultura Biol\u00d3gica",
    "sg:phone":"+34 928 68 47 59",
    "sg:postcode":"35200",
    "sg:province":"Las Palmas",
    "wof:name":"Sociedad Agraria De Transformacion Afraja 9098",
    "wof:placetype":"venue"
},
  "geometry": {"coordinates":[-15.4144220352,28.0029888153],"type":"Point"}
}