{
  "type": "Feature",
  "properties": {
    "addr:full":"Carr Tirant Lo Blanc, 3 Petrer Alicante 03610",
    "addr:housenumber":"3",
    "addr:postcode":"03610",
    "addr:street":"Carr Tirant Lo Blanc",
    "iso:country":"ES",
    "sg:address":"Carr Tirant Lo Blanc, 3",
    "sg:city":"Petrer",
    "sg:orig_category":"Zapater\u00cdas",
    "sg:phone":"+34 965 37 71 11",
    "sg:postcode":"03610",
    "sg:province":"Alicante",
    "sg:website":"www.studiopaloma.es",
    "wof:name":"Borse S.l.",
    "wof:placetype":"venue"
},
  "geometry": {"coordinates":[-0.78916502,38.4896621704],"type":"Point"}
}