{
  "type": "Feature",
  "properties": {
    "addr:full":"Carr General Guell, 26 Cervera Lleida 25200",
    "addr:housenumber":"26",
    "addr:postcode":"25200",
    "addr:street":"Carr General Guell",
    "iso:country":"ES",
    "sg:address":"Carr General Guell, 26",
    "sg:city":"Cervera",
    "sg:orig_category":"Congelados: Productos Alimentarios (al Por Menor)",
    "sg:phone":"+34 973 53 09 40",
    "sg:postcode":"25200",
    "sg:province":"Lleida",
    "wof:name":"Distribucions Alimentarias Trepat S.l.",
    "wof:placetype":"venue"
},
  "geometry": {"coordinates":[1.2743530273,41.6719093323],"type":"Point"}
}