{
  "type": "Feature",
  "properties": {
    "addr:full":"Calle de Rio Nela, 102 Burgos Burgos 09006",
    "addr:housenumber":"102",
    "addr:postcode":"09006",
    "addr:street":"Calle De Rio Nela",
    "iso:country":"ES",
    "sg:address":"Calle de Rio Nela, 102",
    "sg:city":"Burgos",
    "sg:orig_category":"Chapister\u00cda",
    "sg:phone":"+34 947 23 90 10",
    "sg:postcode":"09006",
    "sg:province":"Burgos",
    "wof:name":"Gonzalez Ruiz Enrique",
    "wof:placetype":"venue"
},
  "geometry": {"coordinates":[-3.6817240715,42.3574142456],"type":"Point"}
}