{
  "type": "Feature",
  "properties": {
    "iso:country":"ES",
    "sg:address":"Avda Jacinto Benavente, 10",
    "sg:city":"Valencia",
    "sg:orig_category":"Sindicatos Y Colegios Profesionales",
    "sg:phone":"+34 963 73 46 59",
    "sg:postcode":"46005",
    "sg:province":"Valencia",
    "sg:website":"www.apd.es",
    "wof:name":"Asociacion Para El Progreso De La Direcc",
    "wof:placetype":"venue"
},
  "geometry": {"coordinates":[-0.3633821905,39.4672546387],"type":"Point"}
}