{
  "type": "Feature",
  "properties": {
    "addr:full":"Calle de Rincona, 39 Lepe Huelva 21440",
    "addr:housenumber":"39",
    "addr:postcode":"21440",
    "addr:street":"Calle De Rincona",
    "iso:country":"ES",
    "sg:address":"Calle de Rincona, 39",
    "sg:city":"Lepe",
    "sg:orig_category":"Comercio De Piezas De Recambio Y De Accesorios De Veh\u00cdculos, Veh\u00cdculos Industriales",
    "sg:phone":"+34 959 38 19 33",
    "sg:postcode":"21440",
    "sg:province":"Huelva",
    "wof:name":"Autorrecambios De Lepe S.l.",
    "wof:placetype":"venue"
},
  "geometry": {"coordinates":[-7.2037606239,37.2546043396],"type":"Point"}
}