{
  "type": "Feature",
  "properties": {
    "addr:full":"Huelga, S/n Tamon Asturias 33469",
    "addr:postcode":"33469",
    "addr:street":"Huelga S / N Tamon Asturias",
    "iso:country":"ES",
    "sg:address":"Huelga, S/n",
    "sg:city":"Tamon",
    "sg:orig_category":"Montaje (empresas De)",
    "sg:phone":"+34 985 57 90 76",
    "sg:postcode":"33469",
    "sg:province":"Asturias",
    "wof:name":"Talleres Tabaza S.a.",
    "wof:placetype":"venue"
},
  "geometry": {"coordinates":[-5.8119959831,43.5127182007],"type":"Point"}
}