{
  "type": "Feature",
  "properties": {
    "addr:full":"Antoiu Kalea, 5 Lesaka Navarra 31770",
    "addr:housenumber":"5",
    "addr:postcode":"31770",
    "addr:street":"Antoiu Kalea",
    "iso:country":"ES",
    "sg:address":"Antoiu Kalea, 5",
    "sg:city":"Lesaka",
    "sg:orig_category":"M\u00c9dicos: Estomatolog\u00cda",
    "sg:phone":"+34 948 63 72 82",
    "sg:postcode":"31770",
    "sg:province":"Navarra",
    "wof:name":"Lacar Juan Luis",
    "wof:placetype":"venue"
},
  "geometry": {"coordinates":[-1.7029080391,43.2474517822],"type":"Point"}
}