{
  "type": "Feature",
  "properties": {
    "addr:full":"Barragans, 22 Barragans Pontevedra 36157",
    "addr:housenumber":"22",
    "addr:postcode":"36157",
    "addr:street":"Barragans",
    "iso:country":"ES",
    "sg:address":"Barragans, 22",
    "sg:city":"Barragans",
    "sg:orig_category":"M\u00c9dicos: Pediatr\u00cda. Enfermedades De Los Ni\u00d1os",
    "sg:phone":"+34 986 87 11 02",
    "sg:postcode":"36157",
    "sg:province":"Pontevedra",
    "wof:name":"Rodriguez Costa Alberto",
    "wof:placetype":"venue"
},
  "geometry": {"coordinates":[-8.6582126617,42.4889144897],"type":"Point"}
}