{
  "type": "Feature",
  "properties": {
    "addr:full":"Calle de Ramon Y Cajal, 6 Granja Torrehermosa Badajoz 06910",
    "addr:housenumber":"6",
    "addr:postcode":"06910",
    "addr:street":"Calle De Ramon Y Cajal",
    "iso:country":"ES",
    "sg:address":"Calle de Ramon Y Cajal, 6",
    "sg:city":"Granja Torrehermosa",
    "sg:orig_category":"Supermercados Y Hipermercados",
    "sg:phone":"+34 924 89 52 68",
    "sg:postcode":"06910",
    "sg:province":"Badajoz",
    "wof:name":"Super Eva Spar Azuaga S.l.",
    "wof:placetype":"venue"
},
  "geometry": {"coordinates":[-5.599609375,38.3090438843],"type":"Point"}
}