{
  "type": "Feature",
  "properties": {
    "addr:full":"Pl Verdum(urb Torre Conill), 14 Betera Valencia 46117",
    "addr:housenumber":"14",
    "addr:postcode":"46117",
    "addr:street":"Pl Verdum Urb Torre Conill",
    "iso:country":"ES",
    "sg:address":"Pl Verdum(urb Torre Conill), 14",
    "sg:city":"Betera",
    "sg:orig_category":"Inmobiliaria (agencias)",
    "sg:phone":"+34 961 69 82 22",
    "sg:postcode":"46117",
    "sg:province":"Valencia",
    "sg:website":"www.escorpioninmobiliaria.com",
    "wof:name":"Valsuetec S.l.",
    "wof:placetype":"venue"
},
  "geometry": {"coordinates":[-0.473668009,39.5664749146],"type":"Point"}
}