{
  "type": "Feature",
  "properties": {
    "addr:full":"Calle de Marques De Velasco, 7 Noja Cantabria 39180",
    "addr:housenumber":"7",
    "addr:postcode":"39180",
    "addr:street":"Calle De Marques De Velasco",
    "iso:country":"ES",
    "sg:address":"Calle de Marques De Velasco, 7",
    "sg:city":"Noja",
    "sg:orig_category":"Promotores Constructores",
    "sg:phone":"+34 942 63 06 10",
    "sg:postcode":"39180",
    "sg:province":"Cantabria",
    "wof:name":"Residencial Nojatres S.l.",
    "wof:placetype":"venue"
},
  "geometry": {"coordinates":[-3.5220839977,43.4821548462],"type":"Point"}
}