{
  "type": "Feature",
  "properties": {
    "addr:full":"Calle de Barriocepo, 40 Logro\u00f1o La Rioja 26001",
    "addr:housenumber":"40",
    "addr:postcode":"26001",
    "addr:street":"Calle De Barriocepo;Rioja",
    "iso:country":"ES",
    "sg:address":"Calle de Barriocepo, 40",
    "sg:city":"Logro\u00f1o",
    "sg:orig_category":"Centros P\u00dablicos De Formaci\u00d3n Profesional Y T\u00c9cnica",
    "sg:phone":"+34 941 22 01 08",
    "sg:postcode":"26001",
    "sg:province":"La Rioja",
    "sg:website":"www.coar.es",
    "wof:name":"Colegio Oficial De Arquitectos De La Rioja",
    "wof:placetype":"venue"
},
  "geometry": {"coordinates":[-2.4490599632,42.4673156738],"type":"Point"}
}