{
  "type": "Feature",
  "properties": {
    "addr:full":"Cra Nacional Ii, 648 Mataro Barcelona 08301",
    "addr:housenumber":"648",
    "addr:postcode":"08301",
    "addr:street":"Mataro Barcelona",
    "iso:country":"ES",
    "sg:address":"Cra Nacional Ii, 648",
    "sg:city":"Mataro",
    "sg:orig_category":"Pe\u00d1as Y Asociaciones Varias",
    "sg:phone":"+34 937 96 33 14",
    "sg:postcode":"08301",
    "sg:province":"Barcelona",
    "sg:website":"www.protectoramataro.org",
    "wof:name":"Societat Per La Proteccio D'animals I Plantes De Mataro",
    "wof:placetype":"venue"
},
  "geometry": {"coordinates":[2.4479300976,41.5427207947],"type":"Point"}
}