{
  "type": "Feature",
  "properties": {
    "iso:country":"ES",
    "sg:address":"Calle de Pintor Velazquez, 18",
    "sg:city":"Alacant",
    "sg:orig_category":"Centros De Educaci\u00d3n Especial",
    "sg:phone":"+34 965 14 28 35",
    "sg:postcode":"03004",
    "sg:province":"Alicante",
    "wof:name":"Patronato Municipal De La Cultura D'alacant",
    "wof:placetype":"venue"
},
  "geometry": {"coordinates":[-0.4861440063,38.3502311707],"type":"Point"}
}