{
  "type": "Feature",
  "properties": {
    "iso:country":"ES",
    "sg:address":"Avda Libertad De La, 27",
    "sg:city":"Donostia-san Sebastian",
    "sg:orig_category":"Abogados",
    "sg:phone":"+34 943 42 35 63",
    "sg:postcode":"20004",
    "sg:province":"Guip\u00f9zcoa",
    "wof:name":"Dambolenea Garayalde Ramon",
    "wof:placetype":"venue"
},
  "geometry": {"coordinates":[-1.9828929901,43.3190879822],"type":"Point"}
}