{
  "type": "Feature",
  "properties": {
    "addr:full":"Saturno(riviera Del Sol), 91 Mijas Costa M\u00e1laga 29649",
    "addr:housenumber":"91",
    "addr:postcode":"29649",
    "addr:street":"Del Sol",
    "iso:country":"ES",
    "sg:address":"Saturno(riviera Del Sol), 91",
    "sg:city":"Mijas Costa",
    "sg:orig_category":"Inmobiliaria (agencias)",
    "sg:phone":"+34 952 93 54 07",
    "sg:postcode":"29649",
    "sg:province":"M\u00e1laga",
    "sg:website":"www.homes-in-marbella.com",
    "wof:name":"Home Sweet Home",
    "wof:placetype":"venue"
},
  "geometry": {"coordinates":[-4.7038187981,36.4913902283],"type":"Point"}
}