{
  "type": "Feature",
  "properties": {
    "iso:country":"ES",
    "sg:address":"Zona Aeroport, S/n",
    "sg:city":"Prat Llobregat",
    "sg:orig_category":"Agencias De Aduana",
    "sg:phone":"+34 933 70 66 73",
    "sg:postcode":"08820",
    "sg:province":"Barcelona",
    "wof:name":"Saice S. A.",
    "wof:placetype":"venue"
},
  "geometry": {"coordinates":[2.0864720345,41.3289909363],"type":"Point"}
}