{
  "type": "Feature",
  "properties": {
    "iso:country":"ES",
    "sg:address":"Calle de Parres Sobrino, 9",
    "sg:city":"Llanes",
    "sg:orig_category":"Zapatos (al Por Menor)",
    "sg:phone":"+34 985 40 03 02",
    "sg:postcode":"33500",
    "sg:province":"Asturias",
    "wof:name":"Sordo Fernandez Guillermo Gabriel",
    "wof:placetype":"venue"
},
  "geometry": {"coordinates":[-4.7551374435,43.4198913574],"type":"Point"}
}