{
  "type": "Feature",
  "properties": {
    "iso:country":"ES",
    "sg:address":"Carr Illa Formentera, 16",
    "sg:city":"Girona",
    "sg:orig_category":"Impuestos, Tesoro P\u00dablico",
    "sg:phone":"+34 972 20 67 44",
    "sg:postcode":"17007",
    "sg:province":"Girona",
    "wof:name":"Lopez Ester Salvador",
    "wof:placetype":"venue"
},
  "geometry": {"coordinates":[2.8236908913,42.005531311],"type":"Point"}
}