{
  "type": "Feature",
  "properties": {
    "addr:full":"Carrer de Eduard Toda, 8 Reus Tarragona 43204",
    "addr:housenumber":"8",
    "addr:postcode":"43204",
    "addr:street":"Carrer De Eduard Toda",
    "iso:country":"ES",
    "sg:address":"Carrer de Eduard Toda, 8",
    "sg:city":"Reus",
    "sg:orig_category":"Librer\u00cdas",
    "sg:phone":"+34 977 75 50 03",
    "sg:postcode":"43204",
    "sg:province":"Tarragona",
    "wof:name":"Sancho Save Agustin",
    "wof:placetype":"venue"
},
  "geometry": {"coordinates":[1.1294599771,41.1497001648],"type":"Point"}
}