{
  "type": "Feature",
  "properties": {
    "addr:full":"Plaz Vendimiador, 2 Almendralejo Badajoz 06200",
    "addr:housenumber":"2",
    "addr:postcode":"06200",
    "addr:street":"Plaz Vendimiador",
    "iso:country":"ES",
    "sg:address":"Plaz Vendimiador, 2",
    "sg:city":"Almendralejo",
    "sg:orig_category":"Seguridad En El Trabajo Y Prevenci\u00d3n De Riesgos Laborales",
    "sg:phone":"+34 924 67 09 22",
    "sg:postcode":"06200",
    "sg:province":"Badajoz",
    "wof:name":"Suministros De Proteccion Laboral S.l.",
    "wof:placetype":"venue"
},
  "geometry": {"coordinates":[-6.4068241119,38.6845092773],"type":"Point"}
}