{
  "type": "Feature",
  "properties": {
    "addr:full":"Calle de Arequipa, 1 Madrid Madrid 28043",
    "addr:housenumber":"1",
    "addr:postcode":"28043",
    "addr:street":"Calle De Arequipa",
    "iso:country":"ES",
    "sg:address":"Calle de Arequipa, 1",
    "sg:city":"Madrid",
    "sg:orig_category":"Caf\u00c9s, Bares, Cervecer\u00cdas",
    "sg:phone":"+34 913 81 93 39",
    "sg:postcode":"28043",
    "sg:province":"Madrid",
    "wof:name":"Compa\u00d1ia Del Tropico De Cafe Y Te S.l.",
    "wof:placetype":"venue"
},
  "geometry": {"coordinates":[-3.6422693729,40.4692268372],"type":"Point"}
}