{
  "type": "Feature",
  "properties": {
    "iso:country":"ES",
    "sg:address":"Carrer de Pere Iv, 177",
    "sg:city":"Barcelona",
    "sg:orig_category":"Bancos",
    "sg:phone":"+34 933 00 49 13",
    "sg:postcode":"08018",
    "sg:province":"Barcelona",
    "wof:name":"Barclays Bank S.a.e.",
    "wof:placetype":"venue"
},
  "geometry": {"coordinates":[2.1939339638,41.400177002],"type":"Point"}
}