{
  "type": "Feature",
  "properties": {
    "iso:country":"ES",
    "sg:address":"Calle de Sagunto, 11",
    "sg:city":"Bola\u00e7os De Calatrava",
    "sg:orig_category":"Metalurgia",
    "sg:phone":"+34 926 87 12 61",
    "sg:postcode":"13260",
    "sg:province":"Ciudad Real",
    "wof:name":"Fernandez Montes Antonio",
    "wof:placetype":"venue"
},
  "geometry": {"coordinates":[-3.6641540527,38.9084472656],"type":"Point"}
}