{
  "type": "Feature",
  "properties": {
    "iso:country":"ES",
    "sg:address":"Calle de Montes Y Martin-baro, 6",
    "sg:city":"Valladolid",
    "sg:orig_category":"Productos Fitosanitarios (negocio, Aplicaci\u00d3n)",
    "sg:phone":"+34 983 22 06 61",
    "sg:postcode":"47008",
    "sg:province":"Valladolid",
    "sg:website":"www.agrodan.net",
    "wof:name":"Agrodan S.a",
    "wof:placetype":"venue"
},
  "geometry": {"coordinates":[-4.737906456,41.6288414001],"type":"Point"}
}