{
  "type": "Feature",
  "properties": {
    "iso:country":"ES",
    "sg:address":"Calle de Real, 64",
    "sg:city":"Horcajo De Los Montes",
    "sg:orig_category":"Iglesia Cat\u00d3lica",
    "sg:phone":"+34 926 77 50 14",
    "sg:postcode":"13110",
    "sg:province":"Ciudad Real",
    "wof:name":"Parroquia De San Antonio Abad",
    "wof:placetype":"venue"
},
  "geometry": {"coordinates":[-4.6497988701,39.3254203796],"type":"Point"}
}