{
  "type": "Feature",
  "properties": {
    "addr:full":"Calle de Santo Domingo De La Calzada, 15 Sevilla Sevilla 41018",
    "addr:housenumber":"15",
    "addr:postcode":"41018",
    "addr:street":"Calle De Santo Domingo De La Calzada",
    "iso:country":"ES",
    "sg:address":"Calle de Santo Domingo De La Calzada, 15",
    "sg:city":"Sevilla",
    "sg:orig_category":"Peluqueros: De Se\u00d1oras",
    "sg:phone":"+34 954 53 93 54",
    "sg:postcode":"41018",
    "sg:province":"Sevilla",
    "wof:name":"Carrasco Carmona Consuelo",
    "wof:placetype":"venue"
},
  "geometry": {"coordinates":[-5.9739480019,37.3854789734],"type":"Point"}
}