{
  "type": "Feature",
  "properties": {
    "addr:full":"Carrer de Bilbao, 207 Barcelona Barcelona 08018",
    "addr:housenumber":"207",
    "addr:postcode":"08018",
    "addr:street":"Carrer De Bilbao",
    "iso:country":"ES",
    "sg:address":"Carrer de Bilbao, 207",
    "sg:city":"Barcelona",
    "sg:orig_category":"Molduras, Junquillos, Listones Y Molduras Perforadas",
    "sg:phone":"+34 933 07 21 97",
    "sg:postcode":"08018",
    "sg:province":"Barcelona",
    "wof:name":"Galcera Gorres Rogelio",
    "wof:placetype":"venue"
},
  "geometry": {"coordinates":[2.1938729286,41.409866333],"type":"Point"}
}