{
  "type": "Feature",
  "properties": {
    "iso:country":"ES",
    "sg:address":"Carrer de Concepcion Arenal, 9",
    "sg:city":"Barcelona",
    "sg:orig_category":"Comercio De Piezas De Recambio Y De Accesorios De Veh\u00cdculos, Veh\u00cdculos Industriales",
    "sg:phone":"+34 932 43 10 00",
    "sg:postcode":"08027",
    "sg:province":"Barcelona",
    "wof:name":"A.d.herma Grup S.l.",
    "wof:placetype":"venue"
},
  "geometry": {"coordinates":[2.1837451458,41.4185180664],"type":"Point"}
}