{
  "type": "Feature",
  "properties": {
    "iso:country":"ES",
    "sg:address":"Pl Sant Joan (de), 5",
    "sg:city":"Tortosa",
    "sg:orig_category":"Ense\u00d1anza, Formaci\u00d3n Profesional: Aprendizaje",
    "sg:phone":"+34 977 44 41 63",
    "sg:postcode":"43500",
    "sg:province":"Tarragona",
    "wof:name":"Diputacio Provincial De Tarragona",
    "wof:placetype":"venue"
},
  "geometry": {"coordinates":[0.5249279737,40.8132209778],"type":"Point"}
}