{
  "type": "Feature",
  "properties": {
    "addr:full":"Afueras, S/n Esparragalejo Badajoz 06860",
    "addr:postcode":"06860",
    "addr:street":"Afueras S / N",
    "iso:country":"ES",
    "sg:address":"Afueras, S/n",
    "sg:city":"Esparragalejo",
    "sg:orig_category":"Alimentaci\u00d3n General (al Por Mayor)",
    "sg:phone":"+34 924 32 25 71",
    "sg:postcode":"06860",
    "sg:province":"Badajoz",
    "wof:name":"Piensos Los Barros S.a.",
    "wof:placetype":"venue"
},
  "geometry": {"coordinates":[-6.432156086,38.9404792786],"type":"Point"}
}