{
  "type": "Feature",
  "properties": {
    "addr:full":"Calle de Eustaquio Casado, 4 Nava Asuncion Segovia 40450",
    "addr:housenumber":"4",
    "addr:postcode":"40450",
    "addr:street":"Calle De Eustaquio Casado",
    "iso:country":"ES",
    "sg:address":"Calle de Eustaquio Casado, 4",
    "sg:city":"Nava Asuncion",
    "sg:orig_category":"Venta, Instalaci\u00d3n De Calefacci\u00d3n",
    "sg:phone":"+34 921 58 01 48",
    "sg:postcode":"40450",
    "sg:province":"Segovia",
    "wof:name":"Saneamientos Virseda Esbe S.l.",
    "wof:placetype":"venue"
},
  "geometry": {"coordinates":[-4.4875597954,41.1573371887],"type":"Point"}
}