{
  "type": "Feature",
  "properties": {
    "addr:full":"Calle de Arriba, S/n Molinos Duero Soria 42155",
    "addr:housenumber":"s / n",
    "addr:postcode":"42155",
    "addr:street":"Calle De Arriba",
    "iso:country":"ES",
    "sg:address":"Calle de Arriba, S/n",
    "sg:city":"Molinos Duero",
    "sg:orig_category":"Serrer\u00cdas De Madera",
    "sg:phone":"+34 975 37 82 74",
    "sg:postcode":"42155",
    "sg:province":"Soria",
    "wof:name":"Depresoria S.a.l.",
    "wof:placetype":"venue"
},
  "geometry": {"coordinates":[-2.7885406017,41.8849868774],"type":"Point"}
}