{
  "type": "Feature",
  "properties": {
    "iso:country":"ES",
    "sg:address":"Calle de Fe, 8",
    "sg:city":"Madrid",
    "sg:orig_category":"Carnicer\u00cdas, Carnicer\u00cdas",
    "sg:phone":"+34 915 27 50 45",
    "sg:postcode":"28012",
    "sg:province":"Madrid",
    "wof:name":"Iman  Ali",
    "wof:placetype":"venue"
},
  "geometry": {"coordinates":[-3.7003099918,40.4088821411],"type":"Point"}
}