{
  "type": "Feature",
  "properties": {
    "addr:full":"Calle de Concepcion, 23 Borja Zaragoza 50540",
    "addr:housenumber":"23",
    "addr:postcode":"50540",
    "addr:street":"Calle De Concepcion",
    "iso:country":"ES",
    "sg:address":"Calle de Concepcion, 23",
    "sg:city":"Borja",
    "sg:classifiers":[
        {
            "category":"Taxi",
            "type":"Transportation"
        }
    ],
    "sg:phone":"+34 976 86 73 39",
    "sg:postcode":"50540",
    "sg:province":"Zaragoza",
    "wof:name":"Gimeno Zabala Gloria",
    "wof:placetype":"venue"
},
  "geometry": {"coordinates":[-1.5320158005,41.8335533142],"type":"Point"}
}