{
  "type": "Feature",
  "properties": {
    "addr:full":"Calle de Felipe Iv, 9 Madrid Madrid 28014",
    "addr:housenumber":"9",
    "addr:postcode":"madrid;28014",
    "addr:street":"Calle De Felipe Iv",
    "iso:country":"ES",
    "sg:address":"Calle de Felipe Iv, 9",
    "sg:city":"Madrid",
    "sg:orig_category":"Edici\u00d3n De Diarios, Revistas, Boletines",
    "sg:phone":"+34 915 22 16 48",
    "sg:postcode":"28014",
    "sg:province":"Madrid",
    "wof:name":"Randriamandriato Holdings S.a.",
    "wof:placetype":"venue"
},
  "geometry": {"coordinates":[-3.6909089088,40.4153556824],"type":"Point"}
}