{
  "type": "Feature",
  "properties": {
    "iso:country":"ES",
    "sg:address":"Avda Libertad, 21",
    "sg:city":"Ubeda",
    "sg:orig_category":"Bazares, Art\u00cdculos De Limpieza Y De Cocina (al Por Menor)",
    "sg:phone":"+34 953 79 21 90",
    "sg:postcode":"23400",
    "sg:province":"Ja\u00e9n",
    "wof:name":"Chen  Yousa",
    "wof:placetype":"venue"
},
  "geometry": {"coordinates":[-3.3624610901,38.0164489746],"type":"Point"}
}