{
  "type": "Feature",
  "properties": {
    "iso:country":"ES",
    "sg:address":"Ctra Miralcamp, 1",
    "sg:city":"Mollerussa",
    "sg:orig_category":"Edici\u00d3n De Diarios, Revistas, Boletines",
    "sg:phone":"+34 973 71 03 57",
    "sg:postcode":"25230",
    "sg:province":"Lleida",
    "wof:name":"Edicions Pla D'urgell S.l.",
    "wof:placetype":"venue"
},
  "geometry": {"coordinates":[0.8930749893,41.6239814758],"type":"Point"}
}