{
  "type": "Feature",
  "properties": {
    "addr:full":"Avda Markola, 6 Errenteria Guip\u00f9zcoa 20100",
    "addr:housenumber":"6",
    "addr:postcode":"20100",
    "addr:street":"Avda Markola;Guipu\u0300Zcoa",
    "iso:country":"ES",
    "sg:address":"Avda Markola, 6",
    "sg:city":"Errenteria",
    "sg:orig_category":"Mec\u00c1nico Del Autom\u00d3vil",
    "sg:phone":"+34 943 52 39 59",
    "sg:postcode":"20100",
    "sg:province":"Guip\u00f9zcoa",
    "wof:name":"Francisco Pavon Villoria Y Otro Cdad",
    "wof:placetype":"venue"
},
  "geometry": {"coordinates":[-1.8942780495,43.3081932068],"type":"Point"}
}