{
  "type": "Feature",
  "properties": {
    "addr:full":"Carrer de Pau Claris, 70 Barcelona Barcelona 08010",
    "addr:housenumber":"70",
    "addr:postcode":"08010",
    "addr:street":"Carrer De Pau Claris",
    "iso:country":"ES",
    "sg:address":"Carrer de Pau Claris, 70",
    "sg:city":"Barcelona",
    "sg:orig_category":"Asesor\u00cdas Y Estudios Financieros",
    "sg:phone":"+34 933 17 77 70",
    "sg:postcode":"08010",
    "sg:province":"Barcelona",
    "wof:name":"Pallares Assessorament Economic S.l.",
    "wof:placetype":"venue"
},
  "geometry": {"coordinates":[2.1719551086,41.3892784119],"type":"Point"}
}