{
  "type": "Feature",
  "properties": {
    "addr:full":"Calle de Marrodan, 15 Tarazona Zaragoza 50500",
    "addr:housenumber":"15",
    "addr:postcode":"50500",
    "addr:street":"Calle De Marrodan",
    "iso:country":"ES",
    "sg:address":"Calle de Marrodan, 15",
    "sg:city":"Tarazona",
    "sg:classifiers":[
        {
            "category":"Autos & Motor Vehicles",
            "subcategory":"Automobile Sales",
            "type":"Retail Goods"
        }
    ],
    "sg:phone":"+34 976 64 01 05",
    "sg:postcode":"50500",
    "sg:province":"Zaragoza",
    "sg:website":"www.aprenderaconducir.com",
    "wof:name":"Autoescuela Salizmar S.l.",
    "wof:placetype":"venue"
},
  "geometry": {"coordinates":[-1.7263189554,41.905090332],"type":"Point"}
}