{
  "type": "Feature",
  "properties": {
    "addr:full":"Sta. Marina Piedramuelle, 40 San Claudio Asturias 33191",
    "addr:housenumber":"40",
    "addr:postcode":"33191",
    "addr:street":"Piedramuelle",
    "iso:country":"ES",
    "sg:address":"Sta. Marina Piedramuelle, 40",
    "sg:city":"San Claudio",
    "sg:orig_category":"Muebles Y Accesorios Para Cocinas Y Cuartos De Ba\u00d1o (al Por Menor)",
    "sg:phone":"+34 985 78 12 60",
    "sg:postcode":"33191",
    "sg:province":"Asturias",
    "wof:name":"Aller Alvarez-azulejos Y Gres Materiales De Construccion S.l.",
    "wof:placetype":"venue"
},
  "geometry": {"coordinates":[-5.9156770706,43.3567352295],"type":"Point"}
}