{
  "type": "Feature",
  "properties": {
    "iso:country":"ES",
    "sg:address":"Plaz Portal, 3",
    "sg:city":"Requena",
    "sg:orig_category":"Electrodom\u00c9sticos (al Por Menor)",
    "sg:phone":"+34 962 30 41 39",
    "sg:postcode":"46340",
    "sg:province":"Valencia",
    "wof:name":"Jose Garcia E Hijos S.l.",
    "wof:placetype":"venue"
},
  "geometry": {"coordinates":[-1.1000981331,39.48802948],"type":"Point"}
}