{
  "type": "Feature",
  "properties": {
    "addr:full":"Avda Ruiz Jarabo, 7 Teruel Teruel 44002",
    "addr:housenumber":"7",
    "addr:postcode":"44002",
    "addr:street":"Avda Ruiz Jarabo",
    "iso:country":"ES",
    "sg:address":"Avda Ruiz Jarabo, 7",
    "sg:city":"Teruel",
    "sg:orig_category":"Hospitales",
    "sg:phone":"+34 978 62 22 64",
    "sg:postcode":"44002",
    "sg:province":"Teruel",
    "wof:name":"H. Obispo Polanco",
    "wof:placetype":"venue"
},
  "geometry": {"coordinates":[-1.1080050468,40.3325309753],"type":"Point"}
}