{
  "type": "Feature",
  "properties": {
    "addr:full":"Carrer de Sant Jordi, 104 Pineda Mar Barcelona 08397",
    "addr:housenumber":"104",
    "addr:postcode":"08397",
    "addr:street":"Carrer De Sant Jordi;Barcelona",
    "iso:country":"ES",
    "sg:address":"Carrer de Sant Jordi, 104",
    "sg:city":"Pineda Mar",
    "sg:orig_category":"Molduras, Junquillos, Listones Y Molduras Perforadas",
    "sg:phone":"+34 937 67 06 61",
    "sg:postcode":"08397",
    "sg:province":"Barcelona",
    "wof:name":"Mantenimiento Y Servicios Bernal S.l.",
    "wof:placetype":"venue"
},
  "geometry": {"coordinates":[2.694740057,41.6284103394],"type":"Point"}
}