{
  "type": "Feature",
  "properties": {
    "addr:full":"Pase Malecon (del), S/n Garrucha Almer\u00eda 04630",
    "addr:housenumber":"/ n",
    "addr:postcode":"04630",
    "addr:street":"Malecon Del S;Almeri\u0301A",
    "iso:country":"ES",
    "sg:address":"Pase Malecon (del), S/n",
    "sg:city":"Garrucha",
    "sg:orig_category":"Ense\u00d1anza, Formaci\u00d3n Profesional: Aprendizaje",
    "sg:phone":"+34 950 13 31 82",
    "sg:postcode":"04630",
    "sg:province":"Almer\u00eda",
    "wof:name":"Junta De Andalucia-consejeria De Cultura",
    "wof:placetype":"venue"
},
  "geometry": {"coordinates":[-1.8293952942,37.1894836426],"type":"Point"}
}