{
  "type": "Feature",
  "properties": {
    "iso:country":"ES",
    "sg:address":"Calle de Parque De Gasset, S/n",
    "sg:city":"Ciudad Real",
    "sg:orig_category":"Centros De Educaci\u00d3n Especial",
    "sg:phone":"+34 926 22 40 40",
    "sg:postcode":"13002",
    "sg:province":"Ciudad Real",
    "wof:name":"Colegio Publico Ferroviario",
    "wof:placetype":"venue"
},
  "geometry": {"coordinates":[-3.9301741123,38.9844093323],"type":"Point"}
}