{
  "type": "Feature",
  "properties": {
    "iso:country":"ES",
    "sg:address":"Bard San Miguel, 5",
    "sg:city":"Benaojan",
    "sg:orig_category":"Fabrica De Charcuter\u00cda",
    "sg:phone":"+34 952 16 71 28",
    "sg:postcode":"29370",
    "sg:province":"M\u00e1laga",
    "wof:name":"Montes Carrasco Jose Luis",
    "wof:placetype":"venue"
},
  "geometry": {"coordinates":[-5.2514500618,36.7221336365],"type":"Point"}
}