{
  "type": "Feature",
  "properties": {
    "iso:country":"ES",
    "sg:address":"Calle de Garelly De La Camara, 1",
    "sg:city":"Laredo",
    "sg:orig_category":"Centros Pms (psico",
    "sg:phone":"+34 942 60 81 10",
    "sg:postcode":"39770",
    "sg:province":"Cantabria",
    "wof:name":"Centro De Orientacion Familiar",
    "wof:placetype":"venue"
},
  "geometry": {"coordinates":[-3.4152400494,43.4111289978],"type":"Point"}
}