{
  "type": "Feature",
  "properties": {
    "iso:country":"ES",
    "sg:address":"Ptge Permanyer, 14",
    "sg:city":"Barcelona",
    "sg:orig_category":"Audiovisuales (producci\u00d3n, Edici\u00d3n, Realizaci\u00d3n)",
    "sg:phone":"+34 934 67 70 40",
    "sg:postcode":"08009",
    "sg:province":"Barcelona",
    "sg:website":"www.eddiesaeta.com",
    "wof:name":"Eddie Saeta S.a.",
    "wof:placetype":"venue"
},
  "geometry": {"coordinates":[2.1686971188,41.3926696777],"type":"Point"}
}