{
  "type": "Feature",
  "properties": {
    "iso:country":"ES",
    "sg:address":"Avda Cosculluela, 10",
    "sg:city":"Ejea De Los Caballeros",
    "sg:orig_category":"Florister\u00cdas",
    "sg:phone":"+34 976 66 41 41",
    "sg:postcode":"50600",
    "sg:province":"Zaragoza",
    "wof:name":"Perez Flores Isabel",
    "wof:placetype":"venue"
},
  "geometry": {"coordinates":[-1.1384710073,42.1244850159],"type":"Point"}
}