{
  "type": "Feature",
  "properties": {
    "addr:full":"Calle de Capacho, 27 Guadalcacin Del Caudillo C\u00e1diz 11591",
    "addr:housenumber":"27",
    "addr:postcode":"11591",
    "addr:street":"Calle De Capacho",
    "iso:country":"ES",
    "sg:address":"Calle de Capacho, 27",
    "sg:city":"Guadalcacin Del Caudillo",
    "sg:orig_category":"Sociedades, Compa\u00d1\u00cdas Aseguradoras",
    "sg:phone":"+34 956 15 73 98",
    "sg:postcode":"11591",
    "sg:province":"C\u00e1diz",
    "wof:name":"Rio Sanchez Eduardo Del",
    "wof:placetype":"venue"
},
  "geometry": {"coordinates":[-6.0935726166,36.7109413147],"type":"Point"}
}