{
  "type": "Feature",
  "properties": {
    "iso:country":"ES",
    "sg:address":"Avda Somosierra (de), 22",
    "sg:city":"San Sebastian De Los Reyes",
    "sg:orig_category":"Ebanister\u00cda",
    "sg:phone":"+34 916 23 95 42",
    "sg:postcode":"28700",
    "sg:province":"Madrid",
    "wof:name":"Pmt Carpinteria Toribio S.l.",
    "wof:placetype":"venue"
},
  "geometry": {"coordinates":[-3.6158521175,40.5544471741],"type":"Point"}
}