{
  "type": "Feature",
  "properties": {
    "iso:country":"ES",
    "sg:address":"Avda Malecon, 16",
    "sg:city":"Santa Uxia De Ribeira",
    "sg:orig_category":"Molduras, Junquillos, Listones Y Molduras Perforadas",
    "sg:phone":"+34 981 87 45 19",
    "sg:postcode":"15960",
    "sg:province":"La Coru\u00f1a",
    "wof:name":"Martinez Torres Francisca",
    "wof:placetype":"venue"
},
  "geometry": {"coordinates":[-8.9911203384,42.5572013855],"type":"Point"}
}