{
  "type": "Feature",
  "properties": {
    "addr:full":"Salins, S/n Empuriabrava Girona 17487",
    "addr:housenumber":"s",
    "addr:postcode":"17487",
    "addr:street":"Salins;/ N Empuriabrava",
    "iso:country":"ES",
    "sg:address":"Salins, S/n",
    "sg:city":"Empuriabrava",
    "sg:orig_category":"Deportes N\u00c1uticos, Acu\u00c1ticos Y Subacu\u00c1ticos: Art\u00cdculos Y Equipo (al Por Menor)",
    "sg:phone":"+34 972 45 04 18",
    "sg:postcode":"17487",
    "sg:province":"Girona",
    "wof:name":"Wegener Ledwic Nicolas",
    "wof:placetype":"venue"
},
  "geometry": {"coordinates":[3.1292304993,42.2459335327],"type":"Point"}
}