{
  "type": "Feature",
  "properties": {
    "addr:full":"Cno Guardarany, S/n Sueca Valencia 46410",
    "addr:housenumber":"s",
    "addr:postcode":"46410",
    "addr:street":"Cno Guardarany;/ N",
    "iso:country":"ES",
    "sg:address":"Cno Guardarany, S/n",
    "sg:city":"Sueca",
    "sg:orig_category":"Materias Pl\u00c1sticas: Art\u00cdculos Para La Industria",
    "sg:phone":"+34 961 70 04 04",
    "sg:postcode":"46410",
    "sg:province":"Valencia",
    "wof:name":"Model Fibra S. L.",
    "wof:placetype":"venue"
},
  "geometry": {"coordinates":[-0.3076440096,39.2027435303],"type":"Point"}
}