{
  "type": "Feature",
  "properties": {
    "addr:full":"Carrer de Boteria, 4 Palma Islas Baleares 07012",
    "addr:housenumber":"4",
    "addr:postcode":"07012",
    "addr:street":"Carrer De Boteria",
    "iso:country":"ES",
    "sg:address":"Carrer de Boteria, 4",
    "sg:city":"Palma",
    "sg:orig_category":"Molduras, Junquillos, Listones Y Molduras Perforadas",
    "sg:phone":"+34 971 71 20 05",
    "sg:postcode":"07012",
    "sg:province":"Islas Baleares",
    "wof:name":"Cin Cin Palma S.l",
    "wof:placetype":"venue"
},
  "geometry": {"coordinates":[2.6450600624,39.568447113],"type":"Point"}
}