{
  "type": "Feature",
  "properties": {
    "iso:country":"ES",
    "sg:address":"Calle de Cabeza, 8",
    "sg:city":"Baza",
    "sg:orig_category":"Inform\u00c1tica: Material Y Suministros",
    "sg:phone":"+34 958 70 33 23",
    "sg:postcode":"18800",
    "sg:province":"Granada",
    "wof:name":"Informatica Baza S.l.",
    "wof:placetype":"venue"
},
  "geometry": {"coordinates":[-2.7729928493,37.4897689819],"type":"Point"}
}