{
  "type": "Feature",
  "properties": {
    "iso:country":"ES",
    "sg:address":"Fontan, 43",
    "sg:city":"Fontan",
    "sg:orig_category":"Peluquer\u00cdas, Peluquer\u00cda Mixta",
    "sg:phone":"+34 981 62 19 47",
    "sg:postcode":"15160",
    "sg:province":"La Coru\u00f1a",
    "wof:name":"Pardi\u00f1o Campos Isabel",
    "wof:placetype":"venue"
},
  "geometry": {"coordinates":[-8.2548141479,43.3510665894],"type":"Point"}
}