{
  "type": "Feature",
  "properties": {
    "iso:country":"ES",
    "sg:address":"Calle de San Ildefonso, 20",
    "sg:city":"Fortuna",
    "sg:orig_category":"Dietistas",
    "sg:phone":"+34 968 68 54 90",
    "sg:postcode":"30620",
    "sg:province":"Murcia",
    "wof:name":"Greensoil Iberica S.l.",
    "wof:placetype":"venue"
},
  "geometry": {"coordinates":[-1.1260459423,38.1809387207],"type":"Point"}
}