{
  "type": "Feature",
  "properties": {
    "addr:full":"Rua Jesus Marzoa, 11 Igrexa Pontevedra 36379",
    "addr:housenumber":"11",
    "addr:postcode":"36379",
    "addr:street":"Rua Jesus Marzoa",
    "iso:country":"ES",
    "sg:address":"Rua Jesus Marzoa, 11",
    "sg:city":"Igrexa",
    "sg:orig_category":"Cristaler\u00cdas",
    "sg:phone":"+34 986 35 05 02",
    "sg:postcode":"36379",
    "sg:province":"Pontevedra",
    "wof:name":"Cristaleria Val Mi\u00f1or S.l.",
    "wof:placetype":"venue"
},
  "geometry": {"coordinates":[-8.7793598175,42.1308021545],"type":"Point"}
}