{
  "type": "Feature",
  "properties": {
    "addr:full":"Disem Afores, S/n Ivars D'urgell Lleida 25260",
    "addr:housenumber":"s / n",
    "addr:postcode":"25260",
    "addr:street":"Disem Afores",
    "iso:country":"ES",
    "sg:address":"Disem Afores, S/n",
    "sg:city":"Ivars D'urgell",
    "sg:orig_category":"F\u00c1bricas De Ladrillo Y Tejas",
    "sg:phone":"+34 973 58 03 36",
    "sg:postcode":"25260",
    "sg:province":"Lleida",
    "wof:name":"Agusti Guasch S.a.",
    "wof:placetype":"venue"
},
  "geometry": {"coordinates":[0.9725084901,41.6868400574],"type":"Point"}
}