{
  "type": "Feature",
  "properties": {
    "iso:country":"ES",
    "sg:address":"Calle de Huertas, 4",
    "sg:city":"Borox",
    "sg:orig_category":"Agentes, Concesionarios Y Sucursales De Camiones Y Veh\u00cdculos Industriales",
    "sg:phone":"+34 925 54 80 88",
    "sg:postcode":"45222",
    "sg:province":"Toledo",
    "wof:name":"Handsrie Develop S.l.",
    "wof:placetype":"venue"
},
  "geometry": {"coordinates":[-3.720482111,40.0417442322],"type":"Point"}
}