{
  "type": "Feature",
  "properties": {
    "iso:country":"ES",
    "sg:address":"Calle de San Martin, 20",
    "sg:city":"Cabez\u00f3n Sal",
    "sg:orig_category":"Panader\u00cdas, Panader\u00cdas",
    "sg:phone":"+34 942 70 08 29",
    "sg:postcode":"39500",
    "sg:province":"Cantabria",
    "wof:name":"Chapero Ruiz Eduardo",
    "wof:placetype":"venue"
},
  "geometry": {"coordinates":[-4.2370491028,43.3074493408],"type":"Point"}
}