{
  "type": "Feature",
  "properties": {
    "addr:full":"Av Catalunya, S/n Casc Antic Barcelona 08150",
    "addr:housenumber":"s",
    "addr:postcode":"08150",
    "addr:street":"Av Catalunya;/ N Casc;Barcelona",
    "iso:country":"ES",
    "sg:address":"Av Catalunya, S/n",
    "sg:city":"Casc Antic",
    "sg:orig_category":"Sanatorios M\u00c9dico",
    "sg:phone":"+34 935 62 16 89",
    "sg:postcode":"08150",
    "sg:province":"Barcelona",
    "wof:name":"Centre De Telecomunicaciones De Catalunya",
    "wof:placetype":"venue"
},
  "geometry": {"coordinates":[2.2304179668,41.5672721863],"type":"Point"}
}