{
  "type": "Feature",
  "properties": {
    "addr:full":"Avda Castilla, 69 Aranda Duero Burgos 09400",
    "addr:housenumber":"69",
    "addr:postcode":"09400",
    "addr:street":"Avda Castilla",
    "iso:country":"ES",
    "sg:address":"Avda Castilla, 69",
    "sg:city":"Aranda Duero",
    "sg:orig_category":"Agencias De Viajes",
    "sg:phone":"+34 947 54 61 05",
    "sg:postcode":"09400",
    "sg:province":"Burgos",
    "sg:website":"www.barceloviajes.com",
    "wof:name":"Garcia Castrillo Ana",
    "wof:placetype":"venue"
},
  "geometry": {"coordinates":[-3.6914231777,41.6637535095],"type":"Point"}
}