{
  "type": "Feature",
  "properties": {
    "iso:country":"ES",
    "sg:address":"Calle de Costa Y Borras, 33",
    "sg:city":"Vinaros",
    "sg:orig_category":"Agencias Y Agentes Comerciales, Representantes",
    "sg:phone":"+34 964 45 11 86",
    "sg:postcode":"12500",
    "sg:province":"Castell\u00f3n",
    "wof:name":"Forner Vidiella Juan Jose",
    "wof:placetype":"venue"
},
  "geometry": {"coordinates":[0.4752432108,40.4672470093],"type":"Point"}
}