{
  "type": "Feature",
  "properties": {
    "addr:full":"Calle de San Antonio, 1 Aliaga Teruel 44150",
    "addr:housenumber":"1",
    "addr:postcode":"44150",
    "addr:street":"Calle De San Antonio",
    "iso:country":"ES",
    "sg:address":"Calle de San Antonio, 1",
    "sg:city":"Aliaga",
    "sg:orig_category":"Medicamentos",
    "sg:phone":"+34 978 77 10 50",
    "sg:postcode":"44150",
    "sg:province":"Teruel",
    "wof:name":"Vicent Juan Rosa Maria",
    "wof:placetype":"venue"
},
  "geometry": {"coordinates":[-0.7040489912,40.6719398499],"type":"Point"}
}