{
  "type": "Feature",
  "properties": {
    "addr:full":"Ptda Pla De La Vallonga, S/n Pla De La Vallonga Alicante 03113",
    "addr:housenumber":"s",
    "addr:postcode":"03113",
    "addr:street":"Ptda Pla De La Vallonga;/ N Pla De La Vallonga",
    "iso:country":"ES",
    "sg:address":"Ptda Pla De La Vallonga, S/n",
    "sg:city":"Pla De La Vallonga",
    "sg:orig_category":"Revisi\u00d3n, Reconstrucci\u00d3n De M\u00c1quinas Y Herramientas",
    "sg:phone":"+34 965 93 20 61",
    "sg:postcode":"03113",
    "sg:province":"Alicante",
    "sg:website":"www.wurth.es",
    "wof:name":"Wurth Espa\u00d1a S.a.",
    "wof:placetype":"venue"
},
  "geometry": {"coordinates":[-0.5889509916,38.3436164856],"type":"Point"}
}