{
  "type": "Feature",
  "properties": {
    "addr:full":"Calle de Arzobispo Olaechea, 32 Valencia Valencia 46017",
    "addr:housenumber":"32",
    "addr:postcode":"46017",
    "addr:street":"Calle De Arzobispo Olaechea",
    "iso:country":"ES",
    "sg:address":"Calle de Arzobispo Olaechea, 32",
    "sg:city":"Valencia",
    "sg:orig_category":"Reposter\u00cdas",
    "sg:phone":"+34 963 57 24 49",
    "sg:postcode":"46017",
    "sg:province":"Valencia",
    "wof:name":"Garcia Roger Tomas",
    "wof:placetype":"venue"
},
  "geometry": {"coordinates":[-0.391554296,39.4440307617],"type":"Point"}
}