{
  "type": "Feature",
  "properties": {
    "addr:full":"Calle de Moises De Leon, 1 Le\u00f3n Le\u00f3n 24006",
    "addr:housenumber":"1",
    "addr:postcode":"24006",
    "addr:street":"Calle De Moises De Leon;Leo\u0301N",
    "iso:country":"ES",
    "sg:address":"Calle de Moises De Leon, 1",
    "sg:city":"Le\u00f3n",
    "sg:orig_category":"Peluqueros: De Se\u00d1oras",
    "sg:phone":"+34 987 26 02 82",
    "sg:postcode":"24006",
    "sg:province":"Le\u00f3n",
    "wof:name":"Diez Martinez Esperanza",
    "wof:placetype":"venue"
},
  "geometry": {"coordinates":[-5.561975956,42.5912322998],"type":"Point"}
}