{
  "type": "Feature",
  "properties": {
    "iso:country":"ES",
    "sg:address":"Avgd Fira (de La), 4",
    "sg:city":"Albaida",
    "sg:classifiers":[
        {
            "category":"Autos & Motor Vehicles",
            "subcategory":"Automobile Sales",
            "type":"Retail Goods"
        }
    ],
    "sg:phone":"+34 962 39 11 64",
    "sg:postcode":"46860",
    "sg:province":"Valencia",
    "wof:name":"Fernando Guillem E Hijos S.l.",
    "wof:placetype":"venue"
},
  "geometry": {"coordinates":[-0.5223839879,38.8395118713],"type":"Point"}
}