{
  "type": "Feature",
  "properties": {
    "addr:full":"Plaz General Franco, 4 Cantalejo Segovia 40320",
    "addr:housenumber":"4",
    "addr:postcode":"40320",
    "addr:street":"Franco",
    "iso:country":"ES",
    "sg:address":"Plaz General Franco, 4",
    "sg:city":"Cantalejo",
    "sg:orig_category":"Molduras, Junquillos, Listones Y Molduras Perforadas",
    "sg:phone":"+34 921 52 20 73",
    "sg:postcode":"40320",
    "sg:province":"Segovia",
    "wof:name":"Rodriguez De Miguel Ignacio",
    "wof:placetype":"venue"
},
  "geometry": {"coordinates":[-3.9273369312,41.2588844299],"type":"Point"}
}