{
  "type": "Feature",
  "properties": {
    "iso:country":"ES",
    "sg:address":"Calle de Colon, 19",
    "sg:city":"Valencia",
    "sg:orig_category":"Perfumer\u00cda (al Por Menor)",
    "sg:phone":"+34 963 51 89 23",
    "sg:postcode":"46004",
    "sg:province":"Valencia",
    "sg:website":"www.yves-rocher.com",
    "wof:name":"Yves Rocher Espa\u00f1ola S.a.",
    "wof:placetype":"venue"
},
  "geometry": {"coordinates":[-0.3726707995,39.4686698914],"type":"Point"}
}