{
  "type": "Feature",
  "properties": {
    "addr:full":"Calle de Alemania, 141 Toledo Toledo 45005",
    "addr:housenumber":"141",
    "addr:postcode":"45005",
    "addr:street":"Calle De Alemania",
    "iso:country":"ES",
    "sg:address":"Calle de Alemania, 141",
    "sg:city":"Toledo",
    "sg:orig_category":"Agricultores, Agricultores",
    "sg:phone":"+34 925 22 02 51",
    "sg:postcode":"45005",
    "sg:province":"Toledo",
    "wof:name":"Argapor C.m.",
    "wof:placetype":"venue"
},
  "geometry": {"coordinates":[-4.0334630013,39.8834991455],"type":"Point"}
}