{
  "type": "Feature",
  "properties": {
    "addr:full":"Avda Ramon Y Cajal, 9 Ayamonte Huelva 21400",
    "addr:housenumber":"9",
    "addr:postcode":"21400",
    "addr:street":"Avda Ramon Y Cajal",
    "iso:country":"ES",
    "sg:address":"Avda Ramon Y Cajal, 9",
    "sg:city":"Ayamonte",
    "sg:orig_category":"Fabricaci\u00d3n De Productos Textiles Sin Tejer",
    "sg:phone":"+34 959 32 09 44",
    "sg:postcode":"21400",
    "sg:province":"Huelva",
    "wof:name":"Jesus Rodriguez Antonio",
    "wof:placetype":"venue"
},
  "geometry": {"coordinates":[-7.4022808075,37.2127761841],"type":"Point"}
}