{
  "type": "Feature",
  "properties": {
    "iso:country":"ES",
    "sg:address":"Calle de Melendez Valdes, 8",
    "sg:city":"Badajoz",
    "sg:orig_category":"Loter\u00cda Y T\u00d3mbola",
    "sg:phone":"+34 924 22 46 01",
    "sg:postcode":"06002",
    "sg:province":"Badajoz",
    "wof:name":"Galan Rodriguez Federico",
    "wof:placetype":"venue"
},
  "geometry": {"coordinates":[-6.9704527855,38.8787689209],"type":"Point"}
}