{
  "type": "Feature",
  "properties": {
    "iso:country":"ES",
    "sg:address":"Carr Francesc Ribera, 71",
    "sg:city":"Colera",
    "sg:orig_category":"Inmobiliaria (agencias)",
    "sg:phone":"+34 972 38 92 30",
    "sg:postcode":"17469",
    "sg:province":"Girona",
    "wof:name":"Ferrer Pabo Jose",
    "wof:placetype":"venue"
},
  "geometry": {"coordinates":[2.9704549313,42.2177505493],"type":"Point"}
}