{
  "type": "Feature",
  "properties": {
    "addr:full":"Calle de Doctores Castroviejo, 33 Logro\u00f1o La Rioja 26003",
    "addr:housenumber":"33",
    "addr:postcode":"26003",
    "addr:street":"Calle De Doctores Castroviejo;Rioja",
    "iso:country":"ES",
    "sg:address":"Calle de Doctores Castroviejo, 33",
    "sg:city":"Logro\u00f1o",
    "sg:orig_category":"Carnicer\u00cdas, Carnicer\u00cdas",
    "sg:phone":"+34 941 25 90 72",
    "sg:postcode":"26003",
    "sg:province":"La Rioja",
    "wof:name":"Agustin Garrido Isabel",
    "wof:placetype":"venue"
},
  "geometry": {"coordinates":[-2.4402580261,42.4623413086],"type":"Point"}
}