{
  "type": "Feature",
  "properties": {
    "iso:country":"ES",
    "sg:address":"Carrer de Joan Blanques, 5",
    "sg:city":"Barcelona",
    "sg:orig_category":"Institutos De Belleza",
    "sg:phone":"+34 932 84 06 55",
    "sg:postcode":"08012",
    "sg:province":"Barcelona",
    "wof:name":"Ramon Borras Juan Antonio",
    "wof:placetype":"venue"
},
  "geometry": {"coordinates":[2.1614201069,41.4040374756],"type":"Point"}
}