{
  "type": "Feature",
  "properties": {
    "addr:full":"Tramuntana, 1 Port Selva Girona 17489",
    "addr:housenumber":"1",
    "addr:postcode":"17489",
    "addr:street":"Tramuntana",
    "iso:country":"ES",
    "sg:address":"Tramuntana, 1",
    "sg:city":"Port Selva",
    "sg:orig_category":"Empresas De Carpinter\u00cda Met\u00c1lica",
    "sg:phone":"+34 972 38 71 35",
    "sg:postcode":"17489",
    "sg:province":"Girona",
    "wof:name":"Aymar Martinez Daniel",
    "wof:placetype":"venue"
},
  "geometry": {"coordinates":[3.1548640728,42.3821487427],"type":"Point"}
}