{
  "type": "Feature",
  "properties": {
    "addr:full":"Carr Plana Alta, 10 Villafranca Cid Castell\u00f3n 12150",
    "addr:housenumber":"10",
    "addr:postcode":"12150",
    "addr:street":"Carr Plana Alta",
    "iso:country":"ES",
    "sg:address":"Carr Plana Alta, 10",
    "sg:city":"Villafranca Cid",
    "sg:orig_category":"Cerrajer\u00cda, Ferrallista",
    "sg:phone":"+34 964 44 01 19",
    "sg:postcode":"12150",
    "sg:province":"Castell\u00f3n",
    "wof:name":"Folch Monferrer Juan",
    "wof:placetype":"venue"
},
  "geometry": {"coordinates":[-0.2566109896,40.4322319031],"type":"Point"}
}