{
  "type": "Feature",
  "properties": {
    "iso:country":"ES",
    "sg:address":"Calle de Canovas, 42",
    "sg:city":"Zaragoza",
    "sg:orig_category":"Electricidad: Instaladores",
    "sg:phone":"+34 976 21 61 37",
    "sg:postcode":"50004",
    "sg:province":"Zaragoza",
    "wof:name":"Montajes Electricos Machin S.l.",
    "wof:placetype":"venue"
},
  "geometry": {"coordinates":[-0.8935943842,41.6470947266],"type":"Point"}
}