{
  "type": "Feature",
  "properties": {
    "addr:full":"Rond Ponent, 12 Llucmajor Islas Baleares 07620",
    "addr:housenumber":"12",
    "addr:postcode":"07620",
    "addr:street":"Rond Ponent",
    "iso:country":"ES",
    "sg:address":"Rond Ponent, 12",
    "sg:city":"Llucmajor",
    "sg:orig_category":"Mec\u00c1nico Del Autom\u00d3vil",
    "sg:phone":"+34 971 66 12 67",
    "sg:postcode":"07620",
    "sg:province":"Islas Baleares",
    "wof:name":"Tomas Oliver Baltasar",
    "wof:placetype":"venue"
},
  "geometry": {"coordinates":[2.8861610889,39.4943771362],"type":"Point"}
}