{
  "type": "Feature",
  "properties": {
    "addr:full":"C/ De Giralt, 2 Cerdanyola Valles Barcelona 08290",
    "addr:housenumber":"2",
    "addr:postcode":"08290",
    "addr:street":"C / De Giralt;Valles Barcelona",
    "iso:country":"ES",
    "sg:address":"C/ De Giralt, 2",
    "sg:city":"Cerdanyola Valles",
    "sg:orig_category":"Promotores Constructores",
    "sg:phone":"+34 936 91 38 13",
    "sg:postcode":"08290",
    "sg:province":"Barcelona",
    "wof:name":"Comunidad De Propietarios Giralt 2",
    "wof:placetype":"venue"
},
  "geometry": {"coordinates":[2.1399400234,41.4827842712],"type":"Point"}
}