{
  "type": "Feature",
  "properties": {
    "addr:full":"Calle de Julian Ceballos, 7 Torrelavega Cantabria 39300",
    "addr:housenumber":"7",
    "addr:postcode":"39300",
    "addr:street":"Calle De Julian Ceballos",
    "iso:country":"ES",
    "sg:address":"Calle de Julian Ceballos, 7",
    "sg:city":"Torrelavega",
    "sg:orig_category":"Carnicer\u00cdas, Carnicer\u00cdas",
    "sg:phone":"+34 942 88 87 88",
    "sg:postcode":"39300",
    "sg:province":"Cantabria",
    "wof:name":"Angulo Nu\u00f1ez Esteban Jose",
    "wof:placetype":"venue"
},
  "geometry": {"coordinates":[-4.0515937805,43.3488464355],"type":"Point"}
}