{
  "type": "Feature",
  "properties": {
    "iso:country":"ES",
    "sg:address":"Carrer de Amalia Soler, 145",
    "sg:city":"Vilafranca Penedes",
    "sg:orig_category":"Perfumer\u00cda (al Por Menor)",
    "sg:phone":"+34 938 90 08 30",
    "sg:postcode":"08720",
    "sg:province":"Barcelona",
    "wof:name":"Balague Domingo Maria Carmen",
    "wof:placetype":"venue"
},
  "geometry": {"coordinates":[1.6959215403,41.340713501],"type":"Point"}
}