{
  "type": "Feature",
  "properties": {
    "iso:country":"ES",
    "sg:address":"Calle de Gonzalo Ximenez De Quesada, S/n",
    "sg:city":"Cordoba",
    "sg:orig_category":"Peluqueros: De Se\u00d1oras",
    "sg:phone":"+34 957 23 91 91",
    "sg:postcode":"14004",
    "sg:province":"C\u00f3rdoba",
    "wof:name":"Greace C.b.",
    "wof:placetype":"venue"
},
  "geometry": {"coordinates":[-4.7869429588,37.8840026855],"type":"Point"}
}