{
  "type": "Feature",
  "properties": {
    "addr:full":"Calle de Alemania, 97 Elda Alicante 03600",
    "addr:housenumber":"97",
    "addr:postcode":"03600",
    "addr:street":"Calle De Alemania",
    "iso:country":"ES",
    "sg:address":"Calle de Alemania, 97",
    "sg:city":"Elda",
    "sg:orig_category":"Modistas",
    "sg:phone":"+34 965 38 54 84",
    "sg:postcode":"03600",
    "sg:province":"Alicante",
    "wof:name":"Fernando Arellano S.l.",
    "wof:placetype":"venue"
},
  "geometry": {"coordinates":[-0.8198332191,38.4602928162],"type":"Point"}
}