{
  "type": "Feature",
  "properties": {
    "iso:country":"ES",
    "sg:address":"Calle de Fermin Caballero, 16",
    "sg:city":"Cuenca",
    "sg:orig_category":"Lencer\u00cda Femenina, Corseter\u00cda, Trajes De Ba\u00d1o (al Por Menor)",
    "sg:phone":"+34 969 21 11 27",
    "sg:postcode":"16004",
    "sg:province":"Cuenca",
    "wof:name":"Molinero Ferrer Jezabel",
    "wof:placetype":"venue"
},
  "geometry": {"coordinates":[-2.1352109909,40.0671691895],"type":"Point"}
}