{
  "type": "Feature",
  "properties": {
    "addr:full":"Extr Villaflores, 14 Valdecelada Madrid 28840",
    "addr:housenumber":"14",
    "addr:postcode":"28840",
    "addr:street":"Valdecelada",
    "iso:country":"ES",
    "sg:address":"Extr Villaflores, 14",
    "sg:city":"Valdecelada",
    "sg:orig_category":"Fabricaci\u00d3n, Venta, Instalaci\u00d3n De R\u00d3tulos, De R\u00d3tulos Luminosos",
    "sg:phone":"+34 917 65 02 73",
    "sg:postcode":"28840",
    "sg:province":"Madrid",
    "wof:name":"J.calderon Gonzalez S.l",
    "wof:placetype":"venue"
},
  "geometry": {"coordinates":[-3.4838440418,40.3967437744],"type":"Point"}
}