{
  "type": "Feature",
  "properties": {
    "addr:full":"Calle de Jovellanos, 5 Cuatrovientos Le\u00f3n 24400",
    "addr:housenumber":"5",
    "addr:postcode":"24400",
    "addr:street":"Calle De Jovellanos",
    "iso:country":"ES",
    "sg:address":"Calle de Jovellanos, 5",
    "sg:city":"Cuatrovientos",
    "sg:orig_category":"Centros De Educaci\u00d3n Especial",
    "sg:phone":"+34 987 41 25 96",
    "sg:postcode":"24400",
    "sg:province":"Le\u00f3n",
    "wof:name":"Colegio Publico Jesus Maestro",
    "wof:placetype":"venue"
},
  "geometry": {"coordinates":[-6.5983390808,42.5483360291],"type":"Point"}
}