{
  "type": "Feature",
  "properties": {
    "addr:full":"Calle de San Andres, 60 Coru\u00d1a La Coru\u00f1a 15003",
    "addr:housenumber":"60",
    "addr:postcode":"15003",
    "addr:street":"Calle De San Andres;La Corun\u0303A",
    "iso:country":"ES",
    "sg:address":"Calle de San Andres, 60",
    "sg:city":"Coru\u00d1a",
    "sg:orig_category":"Art\u00cdculos De Regalo (al Por Menor)",
    "sg:phone":"+34 981 22 44 49",
    "sg:postcode":"15003",
    "sg:province":"La Coru\u00f1a",
    "wof:name":"Jimenez Casti\u00f1eiras Jose Luis",
    "wof:placetype":"venue"
},
  "geometry": {"coordinates":[-8.4030342102,43.3701286316],"type":"Point"}
}