{
  "type": "Feature",
  "properties": {
    "addr:full":"Praj Poligono Industrial El Melero, S/n Utiel Valencia 46300",
    "addr:housenumber":"/ n",
    "addr:postcode":"46300",
    "addr:street":"Poligono Industrial El;S",
    "iso:country":"ES",
    "sg:address":"Praj Poligono Industrial El Melero, S/n",
    "sg:city":"Utiel",
    "sg:orig_category":"Distribuci\u00d3n De Petr\u00d3leo Y Derivados",
    "sg:phone":"+34 962 17 33 61",
    "sg:postcode":"46300",
    "sg:province":"Valencia",
    "wof:name":"Navarro Lopez Gabriel",
    "wof:placetype":"venue"
},
  "geometry": {"coordinates":[-1.2064390182,39.5707588196],"type":"Point"}
}