{
  "type": "Feature",
  "properties": {
    "iso:country":"ES",
    "sg:address":"O Souto, S/n",
    "sg:city":"Vilari\u00f1o Conso",
    "sg:orig_category":"Art\u00cdculos Funerarios (al Por Menor)",
    "sg:phone":"+34 988 34 03 03",
    "sg:postcode":"32557",
    "sg:province":"Ourense",
    "wof:name":"Levices Dopazo Jose",
    "wof:placetype":"venue"
},
  "geometry": {"coordinates":[-7.1826543808,42.167137146],"type":"Point"}
}