{
  "type": "Feature",
  "properties": {
    "iso:country":"ES",
    "sg:address":"Cami Pedra Estela, 144",
    "sg:city":"Reus",
    "sg:orig_category":"Producci\u00d3n, Venta De Productos De Agricultura Biol\u00d3gica",
    "sg:phone":"+34 977 75 32 07",
    "sg:postcode":"43205",
    "sg:province":"Tarragona",
    "wof:name":"Otzet Casacuberta Antonio",
    "wof:placetype":"venue"
},
  "geometry": {"coordinates":[1.1067999601,41.1375198364],"type":"Point"}
}