{
  "type": "Feature",
  "properties": {
    "addr:full":"Carrer de Botanica, 160 Hospitalet Llobregat Barcelona 08908",
    "addr:housenumber":"160",
    "addr:postcode":"08908",
    "addr:street":"Carrer De Botanica",
    "iso:country":"ES",
    "sg:address":"Carrer de Botanica, 160",
    "sg:city":"Hospitalet Llobregat",
    "sg:orig_category":"Materias Pl\u00c1sticas: Art\u00cdculos Para La Industria",
    "sg:phone":"+34 933 36 71 46",
    "sg:postcode":"08908",
    "sg:province":"Barcelona",
    "wof:name":"Plasticos Altumax S.a.",
    "wof:placetype":"venue"
},
  "geometry": {"coordinates":[2.1200079918,41.346321106],"type":"Point"}
}