{
  "type": "Feature",
  "properties": {
    "addr:full":"Calle de Padre Mendez, 107 Torrent Valencia 46900",
    "addr:housenumber":"107",
    "addr:postcode":"46900",
    "addr:street":"Calle De Padre Mendez;Valencia",
    "iso:country":"ES",
    "sg:address":"Calle de Padre Mendez, 107",
    "sg:city":"Torrent",
    "sg:orig_category":"Telefon\u00cda: Instaladores Varios",
    "sg:phone":"+34 961 57 00 76",
    "sg:postcode":"46900",
    "sg:province":"Valencia",
    "wof:name":"Bonilla Bonilla Maria Gladys",
    "wof:placetype":"venue"
},
  "geometry": {"coordinates":[-0.4705109894,39.4321403503],"type":"Point"}
}