{
  "type": "Feature",
  "properties": {
    "addr:full":"Carrer de Moli, 57 Barcelona Barcelona 08016",
    "addr:housenumber":"57",
    "addr:postcode":"08016",
    "addr:street":"Carrer De Moli",
    "iso:country":"ES",
    "sg:address":"Carrer de Moli, 57",
    "sg:city":"Barcelona",
    "sg:orig_category":"Ense\u00d1anza Secundaria: Colegios Y Escuelas Privadas",
    "sg:phone":"+34 933 54 30 11",
    "sg:postcode":"08016",
    "sg:province":"Barcelona",
    "wof:name":"Centre De Telecomunicaciones De Catalunya",
    "wof:placetype":"venue"
},
  "geometry": {"coordinates":[2.1809329987,41.4444541931],"type":"Point"}
}