{
  "type": "Feature",
  "properties": {
    "addr:full":"Carrer de Rossello (de), 2 Tortosa Tarragona 43500",
    "addr:postcode":"43500",
    "addr:street":"Carrer De Rossello De",
    "iso:country":"ES",
    "sg:address":"Carrer de Rossello (de), 2",
    "sg:city":"Tortosa",
    "sg:orig_category":"Molduras, Junquillos, Listones Y Molduras Perforadas",
    "sg:phone":"+34 977 44 53 23",
    "sg:postcode":"43500",
    "sg:province":"Tarragona",
    "wof:name":"Roca Domenech Oscar",
    "wof:placetype":"venue"
},
  "geometry": {"coordinates":[0.5219290257,40.8069152832],"type":"Point"}
}