{
  "type": "Feature",
  "properties": {
    "iso:country":"ES",
    "sg:address":"Luga Hoya Del Pedregal, 76",
    "sg:city":"Almatriche Alto",
    "sg:orig_category":"Compresores",
    "sg:phone":"+34 928 67 60 76",
    "sg:postcode":"35018",
    "sg:province":"Las Palmas",
    "wof:name":"Rivero Medina Alexis Manuel",
    "wof:placetype":"venue"
},
  "geometry": {"coordinates":[-15.4623088837,28.0813903809],"type":"Point"}
}