{
  "type": "Feature",
  "properties": {
    "addr:full":"Plaz Constitucion (de La), 9 Almodovar Del Rio C\u00f3rdoba 14720",
    "addr:housenumber":"9",
    "addr:postcode":"14720",
    "addr:street":"Co\u0301Rdoba",
    "iso:country":"ES",
    "sg:address":"Plaz Constitucion (de La), 9",
    "sg:city":"Almodovar Del Rio",
    "sg:orig_category":"Asociaciones, Organismos Culturales Y Socioeducativos",
    "sg:phone":"+34 957 63 51 77",
    "sg:postcode":"14720",
    "sg:province":"C\u00f3rdoba",
    "wof:name":"Sociedad Ateneo Popular",
    "wof:placetype":"venue"
},
  "geometry": {"coordinates":[-5.0199689865,37.8092956543],"type":"Point"}
}