{
  "type": "Feature",
  "properties": {
    "iso:country":"ES",
    "sg:address":"Avda Suero De Qui\u00d1ones, 24",
    "sg:city":"Le\u00f3n",
    "sg:orig_category":"Ingenieros Asesor\u00cda",
    "sg:phone":"+34 987 22 05 08",
    "sg:postcode":"24002",
    "sg:province":"Le\u00f3n",
    "sg:website":"www.acis.es",
    "wof:name":"Acis 2002 S.l.",
    "wof:placetype":"venue"
},
  "geometry": {"coordinates":[-5.5781140327,42.6018409729],"type":"Point"}
}