{
  "type": "Feature",
  "properties": {
    "iso:country":"ES",
    "sg:address":"Carrer de Maria Rosa, 25",
    "sg:city":"Fatjo",
    "sg:orig_category":"Maquinaria Para Industrias Diversas",
    "sg:phone":"+34 933 77 93 03",
    "sg:postcode":"08940",
    "sg:province":"Barcelona",
    "wof:name":"Mecaelectric Arnau S.l.",
    "wof:placetype":"venue"
},
  "geometry": {"coordinates":[2.0740599632,41.356880188],"type":"Point"}
}