{
  "type": "Feature",
  "properties": {
    "addr:full":"Calle de Mercurio, 2 Sevilla Sevilla 41003",
    "addr:housenumber":"2",
    "addr:postcode":"41003",
    "addr:street":"Calle De Mercurio",
    "iso:country":"ES",
    "sg:address":"Calle de Mercurio, 2",
    "sg:city":"Sevilla",
    "sg:orig_category":"Guarder\u00cdas",
    "sg:phone":"+34 954 90 71 70",
    "sg:postcode":"41003",
    "sg:province":"Sevilla",
    "wof:name":"Martinez Ocon Lucia",
    "wof:placetype":"venue"
},
  "geometry": {"coordinates":[-5.9900841713,37.3977279663],"type":"Point"}
}