{
  "type": "Feature",
  "properties": {
    "addr:full":"Carrer de Horta Novella, 65 Sabadell Barcelona 08201",
    "addr:housenumber":"65",
    "addr:postcode":"08201",
    "addr:street":"Carrer De Horta Novella",
    "iso:country":"ES",
    "sg:address":"Carrer de Horta Novella, 65",
    "sg:city":"Sabadell",
    "sg:orig_category":"Organismos De Turismo",
    "sg:phone":"+34 937 25 80 55",
    "sg:postcode":"08201",
    "sg:province":"Barcelona",
    "wof:name":"Gremio Comarcal De Hosteleria Y Turismo De Sabadell",
    "wof:placetype":"venue"
},
  "geometry": {"coordinates":[2.1049659252,41.544002533],"type":"Point"}
}