{
  "type": "Feature",
  "properties": {
    "iso:country":"ES",
    "sg:address":"Calle de Fernandez Ballesteros, 4",
    "sg:city":"Cadiz",
    "sg:orig_category":"Muebles, Minoristas",
    "sg:phone":"+34 956 28 82 64",
    "sg:postcode":"11009",
    "sg:province":"C\u00e1diz",
    "sg:website":"www.nuevalinea.es",
    "wof:name":"Armarios-dise\u00f1os S.l.",
    "wof:placetype":"venue"
},
  "geometry": {"coordinates":[-6.2793664932,36.5096626282],"type":"Point"}
}