{
  "type": "Feature",
  "properties": {
    "iso:country":"ES",
    "sg:address":"Calle de Chillar, 10",
    "sg:city":"Nerja",
    "sg:orig_category":"Desinfecci\u00d3n, Desinsectaci\u00d3n, Desratizaci\u00d3n",
    "sg:phone":"+34 952 52 23 44",
    "sg:postcode":"29780",
    "sg:province":"M\u00e1laga",
    "wof:name":"Aplitex Fumigacion Nerja S.c.",
    "wof:placetype":"venue"
},
  "geometry": {"coordinates":[-3.8777868748,36.7505187988],"type":"Point"}
}