{
  "type": "Feature",
  "properties": {
    "iso:country":"ES",
    "sg:address":"Calle de Prim, 53",
    "sg:city":"Bilbao",
    "sg:orig_category":"Administradores De Bienes Y Delegados De Comunidades De Propietarios",
    "sg:phone":"+34 944 05 86 64",
    "sg:postcode":"48006",
    "sg:province":"Vizcaya",
    "wof:name":"Etxelar, C.b",
    "wof:placetype":"venue"
},
  "geometry": {"coordinates":[-2.9149520397,43.2571372986],"type":"Point"}
}