{
  "type": "Feature",
  "properties": {
    "addr:full":"Calle de Antonio Pascual, S/n Aljorra Murcia 30390",
    "addr:housenumber":"s / n",
    "addr:postcode":"30390",
    "addr:street":"Calle De Antonio Pascual",
    "iso:country":"ES",
    "sg:address":"Calle de Antonio Pascual, S/n",
    "sg:city":"Aljorra",
    "sg:orig_category":"Alimentaci\u00d3n General (al Por Menor)",
    "sg:phone":"+34 968 55 83 55",
    "sg:postcode":"30390",
    "sg:province":"Murcia",
    "wof:name":"Benzal Saura Maria Jesus",
    "wof:placetype":"venue"
},
  "geometry": {"coordinates":[-1.0737639666,37.6933631897],"type":"Point"}
}