{
  "type": "Feature",
  "properties": {
    "addr:full":"Calle de San Roque, 80 Cervera Pisuerga Palencia 34840",
    "addr:housenumber":"80",
    "addr:postcode":"34840",
    "addr:street":"Calle De San Roque",
    "iso:country":"ES",
    "sg:address":"Calle de San Roque, 80",
    "sg:city":"Cervera Pisuerga",
    "sg:orig_category":"Transportes Por V\u00cdas Navegables",
    "sg:phone":"+34 979 87 06 61",
    "sg:postcode":"34840",
    "sg:province":"Palencia",
    "wof:name":"Llorente Rodriguez Justo",
    "wof:placetype":"venue"
},
  "geometry": {"coordinates":[-4.4988012314,42.8674736023],"type":"Point"}
}