{
  "type": "Feature",
  "properties": {
    "iso:country":"ES",
    "sg:address":"Calle de Alcalde Parrondo, 18",
    "sg:city":"Pola De Siero",
    "sg:orig_category":"Edici\u00d3n De Diarios, Revistas, Boletines",
    "sg:phone":"+34 985 72 52 10",
    "sg:postcode":"33510",
    "sg:province":"Asturias",
    "wof:name":"El Comercio Sa",
    "wof:placetype":"venue"
},
  "geometry": {"coordinates":[-5.6592307091,43.3917884827],"type":"Point"}
}