{
  "type": "Feature",
  "properties": {
    "iso:country":"ES",
    "sg:address":"Plaz Constitucion (de La), S/n",
    "sg:city":"Almu\u00f1ecar",
    "sg:orig_category":"Institutos M\u00c9dicos",
    "sg:phone":"+34 958 63 56 92",
    "sg:postcode":"18690",
    "sg:province":"Granada",
    "wof:name":"Servicio Andaluz De Salud",
    "wof:placetype":"venue"
},
  "geometry": {"coordinates":[-3.6912341118,36.7338142395],"type":"Point"}
}