{
  "type": "Feature",
  "properties": {
    "addr:full":"Carrer de Sant Isidre, 21 Sitges Barcelona 08870",
    "addr:housenumber":"21",
    "addr:postcode":"08870",
    "addr:street":"Carrer De Sant Isidre",
    "iso:country":"ES",
    "sg:address":"Carrer de Sant Isidre, 21",
    "sg:city":"Sitges",
    "sg:orig_category":"Fisioterapia",
    "sg:phone":"+34 938 94 29 58",
    "sg:postcode":"08870",
    "sg:province":"Barcelona",
    "wof:name":"Cami Scp",
    "wof:placetype":"venue"
},
  "geometry": {"coordinates":[1.8106980324,41.2381057739],"type":"Point"}
}