{
  "type": "Feature",
  "properties": {
    "addr:full":"Calle de Soria, 10 Gijon Asturias 33208",
    "addr:housenumber":"10",
    "addr:postcode":"33208",
    "addr:street":"Calle De Soria",
    "iso:country":"ES",
    "sg:address":"Calle de Soria, 10",
    "sg:city":"Gijon",
    "sg:orig_category":"Peluqueros: De Se\u00d1oras",
    "sg:phone":"+34 985 16 17 18",
    "sg:postcode":"33208",
    "sg:province":"Asturias",
    "wof:name":"Gonzalez Perez Maria Jesus",
    "wof:placetype":"venue"
},
  "geometry": {"coordinates":[-5.6701660156,43.5294036865],"type":"Point"}
}