{
  "type": "Feature",
  "properties": {
    "iso:country":"ES",
    "sg:address":"Calle de Curtidores, 4",
    "sg:city":"Utrera",
    "sg:orig_category":"Arte, Cultura, Edici\u00d3n",
    "sg:phone":"+34 955 86 47 50",
    "sg:postcode":"41710",
    "sg:province":"Sevilla",
    "wof:name":"Seyma Prefabricados Y Piedra Artificial S.l.",
    "wof:placetype":"venue"
},
  "geometry": {"coordinates":[-5.7940239906,37.1995201111],"type":"Point"}
}