{
  "type": "Feature",
  "properties": {
    "iso:country":"ES",
    "sg:address":"Calle de Negubide, 13",
    "sg:city":"Arenas -areeta",
    "sg:orig_category":"Art\u00cdculos De Limpieza Y De Cocina (fabricaci\u00d3n, Al Por Mayor)",
    "sg:phone":"+34 944 64 29 54",
    "sg:postcode":"48930",
    "sg:province":"Vizcaya",
    "sg:website":"www.lladro.com",
    "wof:name":"Abasotas 22 S.a.",
    "wof:placetype":"venue"
},
  "geometry": {"coordinates":[-2.698387,43.220428],"type":"Point"}
}