{
  "type": "Feature",
  "properties": {
    "iso:country":"ES",
    "sg:address":"C/ 29, 94",
    "sg:city":"Ca\u00d1ada",
    "sg:orig_category":"Inmobiliaria (agencias)",
    "sg:phone":"+34 961 32 51 37",
    "sg:postcode":"46182",
    "sg:province":"Valencia",
    "sg:website":"www.inmobiliariacargimar.com",
    "wof:name":"Inversiones Inmobiliarias Cargimar S.l.",
    "wof:placetype":"venue"
},
  "geometry": {"coordinates":[-0.4740270972,39.5308456421],"type":"Point"}
}