{
  "type": "Feature",
  "properties": {
    "addr:full":"Carretera Almeria-murcia, Km. 0043,3 Tabernas Almer\u00eda 04200",
    "addr:postcode":"04200",
    "addr:street":"Carretera Almeria-Murcia Km. 0043,3;Almeri\u0301A",
    "iso:country":"ES",
    "sg:address":"Carretera Almeria-murcia, Km. 0043,3",
    "sg:city":"Tabernas",
    "sg:orig_category":"Molduras, Junquillos, Listones Y Molduras Perforadas",
    "sg:phone":"+34 950 36 50 59",
    "sg:postcode":"04200",
    "sg:province":"Almer\u00eda",
    "wof:name":"Sanchez Rodriguez Jesus",
    "wof:placetype":"venue"
},
  "geometry": {"coordinates":[-2.389993906,37.0518913269],"type":"Point"}
}