{
  "type": "Feature",
  "properties": {
    "iso:country":"ES",
    "sg:address":"Calle de Empresarios, S/n",
    "sg:city":"Pilar Horadada",
    "sg:orig_category":"Mec\u00c1nico Del Autom\u00d3vil",
    "sg:phone":"+34 966 76 64 31",
    "sg:postcode":"03190",
    "sg:province":"Alicante",
    "wof:name":"Talleres Gines Gracia S.l.",
    "wof:placetype":"venue"
},
  "geometry": {"coordinates":[-0.7781640291,37.8660583496],"type":"Point"}
}