{
  "type": "Feature",
  "properties": {
    "iso:country":"ES",
    "sg:address":"Calle de Purita De La Riva, 6",
    "sg:city":"Oviedo",
    "sg:orig_category":"Electricidad, Electr\u00d3nica: Material Y Suministros (al Por Mayor)",
    "sg:phone":"+34 985 20 55 24",
    "sg:postcode":"33008",
    "sg:province":"Asturias",
    "wof:name":"T-systems Eytc S. A.",
    "wof:placetype":"venue"
},
  "geometry": {"coordinates":[-5.8360381126,43.3526687622],"type":"Point"}
}