{
  "type": "Feature",
  "properties": {
    "addr:full":"Galtzaur Kalea, 25 Astigarraga Guip\u00f9zcoa 20115",
    "addr:housenumber":"25",
    "addr:postcode":"20115",
    "addr:street":"Galtzaur Kalea;Guipu\u0300Zcoa",
    "iso:country":"ES",
    "sg:address":"Galtzaur Kalea, 25",
    "sg:city":"Astigarraga",
    "sg:orig_category":"Traductores",
    "sg:phone":"+34 943 55 77 31",
    "sg:postcode":"20115",
    "sg:province":"Guip\u00f9zcoa",
    "wof:name":"Xabier Galarreta Velazquez",
    "wof:placetype":"venue"
},
  "geometry": {"coordinates":[-1.9472105503,43.2831726074],"type":"Point"}
}