{
  "type": "Feature",
  "properties": {
    "iso:country":"ES",
    "sg:address":"Urb Marinas (las), S/n",
    "sg:city":"Garrucha",
    "sg:orig_category":"Electromec\u00c1nica",
    "sg:phone":"+34 950 13 34 03",
    "sg:postcode":"04630",
    "sg:province":"Almer\u00eda",
    "wof:name":"Cervantes Cervantes Juan Diego",
    "wof:placetype":"venue"
},
  "geometry": {"coordinates":[-1.8196489811,37.1859741211],"type":"Point"}
}