{
  "type": "Feature",
  "properties": {
    "addr:full":"Calle de Dise\u00d1o, 12 Mairena Aljarafe Sevilla 41927",
    "addr:housenumber":"12",
    "addr:postcode":"41927",
    "addr:street":"Calle De Disen\u0303O",
    "iso:country":"ES",
    "sg:address":"Calle de Dise\u00d1o, 12",
    "sg:city":"Mairena Aljarafe",
    "sg:orig_category":"Papel (al Por Mayor)",
    "sg:phone":"+34 954 18 65 18",
    "sg:postcode":"41927",
    "sg:province":"Sevilla",
    "wof:name":"Papeles Del Norte S.l.",
    "wof:placetype":"venue"
},
  "geometry": {"coordinates":[-6.0577340126,37.3532562256],"type":"Point"}
}