{
  "type": "Feature",
  "properties": {
    "addr:full":"Carrer de Javimel, 6 Cornella Llobregat Barcelona 08940",
    "addr:housenumber":"6",
    "addr:postcode":"08940",
    "addr:street":"Carrer De Javimel",
    "iso:country":"ES",
    "sg:address":"Carrer de Javimel, 6",
    "sg:city":"Cornella Llobregat",
    "sg:orig_category":"Arreglo, Reparaci\u00d3n, Piezas Sueltas De Televisi\u00d3n, V\u00cddeo, Hi",
    "sg:phone":"+34 933 77 42 88",
    "sg:postcode":"08940",
    "sg:province":"Barcelona",
    "wof:name":"Ribas Blanch Jose",
    "wof:placetype":"venue"
},
  "geometry": {"coordinates":[2.0708940029,41.3559417725],"type":"Point"}
}