{
  "type": "Feature",
  "properties": {
    "addr:full":"Avda Frontera (de La), 50 Torrejon Velasco Madrid 28990",
    "addr:housenumber":"50",
    "addr:postcode":"28990",
    "addr:street":"Avda Frontera De La",
    "iso:country":"ES",
    "sg:address":"Avda Frontera (de La), 50",
    "sg:city":"Torrejon Velasco",
    "sg:orig_category":"Fabricaci\u00d3n De Jabones, Detergentes Y Lej\u00cdas",
    "sg:phone":"+34 918 16 16 99",
    "sg:postcode":"28990",
    "sg:province":"Madrid",
    "wof:name":"Gamaquimp S.l.",
    "wof:placetype":"venue"
},
  "geometry": {"coordinates":[-3.7652854919,40.1870193481],"type":"Point"}
}