{
  "type": "Feature",
  "properties": {
    "iso:country":"ES",
    "sg:address":"Calle de Puerta De Murcia, 16",
    "sg:city":"Cartagena",
    "sg:orig_category":"Aud\u00cdfonos",
    "sg:phone":"+34 968 50 75 92",
    "sg:postcode":"30201",
    "sg:province":"Murcia",
    "wof:name":"Rodero Paterna Maria Jose",
    "wof:placetype":"venue"
},
  "geometry": {"coordinates":[-0.9869719744,37.6019058228],"type":"Point"}
}