{
  "type": "Feature",
  "properties": {
    "addr:full":"Trva Ezquerro, 34 Autol La Rioja 26560",
    "addr:housenumber":"34",
    "addr:postcode":"26560",
    "addr:street":"Trva Ezquerro;Rioja",
    "iso:country":"ES",
    "sg:address":"Trva Ezquerro, 34",
    "sg:city":"Autol",
    "sg:orig_category":"Cajas De Ahorro",
    "sg:phone":"+34 941 40 10 03",
    "sg:postcode":"26560",
    "sg:province":"La Rioja",
    "sg:website":"www.lacaixa.es",
    "wof:name":"Caixa D'estalvis I Pensions De Barcelona",
    "wof:placetype":"venue"
},
  "geometry": {"coordinates":[-2.0051250458,42.2151451111],"type":"Point"}
}