{
  "type": "Feature",
  "properties": {
    "iso:country":"ES",
    "sg:address":"Calle de Virgen De Lluc, 144",
    "sg:city":"Madrid",
    "sg:orig_category":"Empresas De Limpieza",
    "sg:phone":"+34 913 77 24 58",
    "sg:postcode":"28027",
    "sg:province":"Madrid",
    "wof:name":"Garmar Tratamientos Exteriores S.l.",
    "wof:placetype":"venue"
},
  "geometry": {"coordinates":[-3.6422469616,40.4384880066],"type":"Point"}
}