{
  "type": "Feature",
  "properties": {
    "iso:country":"ES",
    "sg:address":"Avda Torrelaguna (de), 18",
    "sg:city":"Azuqueca Henares",
    "sg:orig_category":"Caf\u00c9s, Bares, Cervecer\u00cdas",
    "sg:phone":"+34 949 34 89 89",
    "sg:postcode":"19200",
    "sg:province":"Guadalajara",
    "wof:name":"Del Castillo Perez Jose Antonio",
    "wof:placetype":"venue"
},
  "geometry": {"coordinates":[-3.2652840614,40.565448761],"type":"Point"}
}