{
  "type": "Feature",
  "properties": {
    "iso:country":"ES",
    "sg:address":"Calle de Balcon De Segovia (el), 18",
    "sg:city":"Lastrilla",
    "sg:orig_category":"Traductores",
    "sg:phone":"+34 921 43 25 49",
    "sg:postcode":"40196",
    "sg:province":"Segovia",
    "wof:name":"Bazire  Philip James",
    "wof:placetype":"venue"
},
  "geometry": {"coordinates":[-4.108959198,40.9703102112],"type":"Point"}
}