{
  "type": "Feature",
  "properties": {
    "addr:full":"Avda Constitucion (de La), 22 Granada Granada 18012",
    "addr:housenumber":"22",
    "addr:postcode":"18012",
    "addr:street":"Avda Constitucion De La",
    "iso:country":"ES",
    "sg:address":"Avda Constitucion (de La), 22",
    "sg:city":"Granada",
    "sg:orig_category":"Cl\u00cdnicas M\u00c9dicas",
    "sg:phone":"+34 958 20 56 46",
    "sg:postcode":"18012",
    "sg:province":"Granada",
    "wof:name":"Citopatologia Y Ginecologia Asociadas",
    "wof:placetype":"venue"
},
  "geometry": {"coordinates":[-3.6056230068,37.1850662231],"type":"Point"}
}