{
  "type": "Feature",
  "properties": {
    "iso:country":"ES",
    "sg:address":"Rond General Mitre, 90",
    "sg:city":"Barcelona",
    "sg:orig_category":"Agencias Y Asesores De Publicidad",
    "sg:phone":"+34 934 17 37 28",
    "sg:postcode":"08021",
    "sg:province":"Barcelona",
    "wof:name":"Free Marr's Neteja S.l.",
    "wof:placetype":"venue"
},
  "geometry": {"coordinates":[2.1348779202,41.3998413086],"type":"Point"}
}