{
  "type": "Feature",
  "properties": {
    "iso:country":"ES",
    "sg:address":"Calle de Rendueles Llanos, 6",
    "sg:city":"Gijon",
    "sg:classifiers":[
        {
            "category":"Professional",
            "subcategory":"Research",
            "type":"Services"
        }
    ],
    "sg:phone":"+34 985 13 09 70",
    "sg:postcode":"33205",
    "sg:province":"Asturias",
    "sg:tags":[
        "mercado",
        "de",
        "estudios"
    ],
    "wof:name":"Invesmark S.l.",
    "wof:placetype":"venue"
},
  "geometry": {"coordinates":[-5.6565208435,43.5352706909],"type":"Point"}
}