{
  "type": "Feature",
  "properties": {
    "addr:full":"Rua Tapia, S/n Temple La Coru\u00f1a 15679",
    "addr:housenumber":"s / n",
    "addr:postcode":"15679",
    "addr:street":"Rua Tapia;La Corun\u0303A",
    "iso:country":"ES",
    "sg:address":"Rua Tapia, S/n",
    "sg:city":"Temple",
    "sg:orig_category":"M\u00c9dicos: Estomatolog\u00cda",
    "sg:phone":"+34 981 66 61 66",
    "sg:postcode":"15679",
    "sg:province":"La Coru\u00f1a",
    "wof:name":"Perez Pose Teodomiro",
    "wof:placetype":"venue"
},
  "geometry": {"coordinates":[-8.3685693741,43.3172721863],"type":"Point"}
}