{
  "type": "Feature",
  "properties": {
    "iso:country":"ES",
    "sg:address":"Ctra. Eivissa S. Antoni, Km. 4800,0",
    "sg:city":"S. Rafel Creu",
    "sg:orig_category":"Edici\u00d3n De Diarios, Revistas, Boletines",
    "sg:phone":"+34 971 19 49 81",
    "sg:postcode":"07816",
    "sg:province":"Islas Baleares",
    "wof:name":"Transtar Managing S.l.",
    "wof:placetype":"venue"
},
  "geometry": {"coordinates":[1.3828419447,39.0397987366],"type":"Point"}
}