{
  "type": "Feature",
  "properties": {
    "iso:country":"ES",
    "sg:address":"Plaz Pan, 5",
    "sg:city":"Medina Campo",
    "sg:orig_category":"Cooperativas Agr\u00cdcolas",
    "sg:phone":"+34 983 81 17 94",
    "sg:postcode":"47400",
    "sg:province":"Valladolid",
    "wof:name":"Cooperativa Campesinos De Valladolid S. L.",
    "wof:placetype":"venue"
},
  "geometry": {"coordinates":[-4.913184166,41.3120155334],"type":"Point"}
}