{
  "type": "Feature",
  "properties": {
    "iso:country":"ES",
    "sg:address":"Av Circunvalacio(pol Industrial), 14",
    "sg:city":"Sant Lluis",
    "sg:orig_category":"Transportes Por Carretera: Lotes Completos, Mercanc\u00cdas Diversas",
    "sg:phone":"+34 971 15 11 51",
    "sg:postcode":"07710",
    "sg:province":"Islas Baleares",
    "wof:name":"Granja Avicola Consell S.l.",
    "wof:placetype":"venue"
},
  "geometry": {"coordinates":[4.2691421509,39.8487739563],"type":"Point"}
}