{
  "type": "Feature",
  "properties": {
    "addr:full":"Los Silos, 1 Aceuchal Badajoz 06207",
    "addr:housenumber":"1",
    "addr:postcode":"06207",
    "addr:street":"Los Silos",
    "iso:country":"ES",
    "sg:address":"Los Silos, 1",
    "sg:city":"Aceuchal",
    "sg:orig_category":"Empresarios",
    "sg:phone":"+34 924 68 04 08",
    "sg:postcode":"06207",
    "sg:province":"Badajoz",
    "wof:name":"Cortes Diaz Francisco",
    "wof:placetype":"venue"
},
  "geometry": {"coordinates":[-6.4874281883,38.644317627],"type":"Point"}
}