{
  "type": "Feature",
  "properties": {
    "addr:full":"Calle de Sierra De Gredos, S/n Guijuelo Salamanca 37770",
    "addr:housenumber":"s / n",
    "addr:postcode":"37770",
    "addr:street":"Calle De Sierra De Gredos",
    "iso:country":"ES",
    "sg:address":"Calle de Sierra De Gredos, S/n",
    "sg:city":"Guijuelo",
    "sg:orig_category":"Transportes Frigor\u00cdficos",
    "sg:phone":"+34 923 58 00 70",
    "sg:postcode":"37770",
    "sg:province":"Salamanca",
    "wof:name":"Plataforma Frigorifica S.l.",
    "wof:placetype":"venue"
},
  "geometry": {"coordinates":[-5.6772289276,40.5363883972],"type":"Point"}
}