{
  "type": "Feature",
  "properties": {
    "addr:full":"Avda General Primo De Rivera, 5 San Miguel Murcia 30008",
    "addr:housenumber":"5",
    "addr:postcode":"30008",
    "addr:street":"Avda General Primo De Rivera",
    "iso:country":"ES",
    "sg:address":"Avda General Primo De Rivera, 5",
    "sg:city":"San Miguel",
    "sg:orig_category":"M\u00c9dicos: Pediatr\u00cda. Enfermedades De Los Ni\u00d1os",
    "sg:phone":"+34 968 23 44 75",
    "sg:postcode":"30008",
    "sg:province":"Murcia",
    "wof:name":"Pajaron De Ahumada Manuel",
    "wof:placetype":"venue"
},
  "geometry": {"coordinates":[-1.1323560476,37.9916114807],"type":"Point"}
}