{
  "type": "Feature",
  "properties": {
    "addr:full":"Calle de Don Lope De Los Rios, 13 Cordoba C\u00f3rdoba 14006",
    "addr:housenumber":"13",
    "addr:postcode":"14006",
    "addr:street":"Calle De Don Lope De Los Rios;Co\u0301Rdoba",
    "iso:country":"ES",
    "sg:address":"Calle de Don Lope De Los Rios, 13",
    "sg:city":"Cordoba",
    "sg:orig_category":"Centros De Educaci\u00d3n Especial",
    "sg:phone":"+34 957 27 09 20",
    "sg:postcode":"14006",
    "sg:province":"C\u00f3rdoba",
    "wof:name":"Junta De Andalucia",
    "wof:placetype":"venue"
},
  "geometry": {"coordinates":[-4.7766981125,37.8988609314],"type":"Point"}
}