{
  "type": "Feature",
  "properties": {
    "addr:full":"Calle de Pino Apolinario, 24 Palmas De Gran Canaria Las Palmas 35014",
    "addr:housenumber":"24",
    "addr:postcode":"35014",
    "addr:street":"Calle De Pino Apolinario",
    "iso:country":"ES",
    "sg:address":"Calle de Pino Apolinario, 24",
    "sg:city":"Palmas De Gran Canaria",
    "sg:orig_category":"Muebles, Minoristas",
    "sg:phone":"+34 928 25 12 31",
    "sg:postcode":"35014",
    "sg:province":"Las Palmas",
    "wof:name":"Comercial Roger & Santana S.l.l.",
    "wof:placetype":"venue"
},
  "geometry": {"coordinates":[-15.4361915588,28.0978450775],"type":"Point"}
}