{
  "type": "Feature",
  "properties": {
    "addr:full":"Ctra Litos, Km. 0025,0 Mozar Zamora 49698",
    "addr:postcode":"49698",
    "addr:street":"Ctra Litos Km. 0025,0 Mozar Zamora",
    "iso:country":"ES",
    "sg:address":"Ctra Litos, Km. 0025,0",
    "sg:city":"Mozar",
    "sg:orig_category":"Patatas (al Por Mayor)",
    "sg:phone":"+34 980 64 07 20",
    "sg:postcode":"49698",
    "sg:province":"Zamora",
    "wof:name":"Sociedad Cooperativa Gexvall",
    "wof:placetype":"venue"
},
  "geometry": {"coordinates":[-5.7810750008,41.9211845398],"type":"Point"}
}