{
  "type": "Feature",
  "properties": {
    "addr:full":"Avda Arcadio Pardi\u00d1as, 165 Burela Lugo 27880",
    "addr:housenumber":"165",
    "addr:postcode":"27880",
    "addr:street":"Avda Arcadio Pardin\u0303As",
    "iso:country":"ES",
    "sg:address":"Avda Arcadio Pardi\u00d1as, 165",
    "sg:city":"Burela",
    "sg:classifiers":[
        {
            "category":"Autos & Motor Vehicles",
            "subcategory":"Automobile Sales",
            "type":"Retail Goods"
        }
    ],
    "sg:phone":"+34 982 57 50 20",
    "sg:postcode":"27880",
    "sg:province":"Lugo",
    "wof:name":"Mundial Viveiro-foz S.l.",
    "wof:placetype":"venue"
},
  "geometry": {"coordinates":[-7.3563251495,43.6540489197],"type":"Point"}
}