{
  "type": "Feature",
  "properties": {
    "iso:country":"ES",
    "sg:address":"Plaz Mayor, 10",
    "sg:city":"Aviles",
    "sg:orig_category":"Estancos",
    "sg:phone":"+34 985 57 30 43",
    "sg:postcode":"33460",
    "sg:province":"Asturias",
    "wof:name":"Alvarez De Tejera Hevia Paloma",
    "wof:placetype":"venue"
},
  "geometry": {"coordinates":[-5.8999352455,43.5481643677],"type":"Point"}
}