{
  "type": "Feature",
  "properties": {
    "iso:country":"ES",
    "sg:address":"Calle de Consolacion, 28",
    "sg:city":"Torrelavega",
    "sg:orig_category":"Bisuter\u00cda, Joyer\u00cda, Relojer\u00cda (al Por Menor)",
    "sg:phone":"+34 942 88 23 15",
    "sg:postcode":"39300",
    "sg:province":"Cantabria",
    "wof:name":"Martinez Somacarrera Jose Maria",
    "wof:placetype":"venue"
},
  "geometry": {"coordinates":[-4.0475120544,43.3508262634],"type":"Point"}
}