{
  "type": "Feature",
  "properties": {
    "iso:country":"ES",
    "sg:address":"Ermita Santa Lucia, S/n",
    "sg:city":"Ibi",
    "sg:classifiers":[
        {
            "category":"Taxi",
            "type":"Transportation"
        }
    ],
    "sg:phone":"+34 965 55 44 34",
    "sg:postcode":"03440",
    "sg:province":"Alicante",
    "wof:name":"Ayuntamiento De Ibi",
    "wof:placetype":"venue"
},
  "geometry": {"coordinates":[-0.571219027,38.6303901672],"type":"Point"}
}