{
  "type": "Feature",
  "properties": {
    "addr:full":"Avda Antonio Masa Campos, 22 Badajoz Badajoz 06011",
    "addr:housenumber":"22",
    "addr:postcode":"06011",
    "addr:street":"Avda Antonio Masa Campos",
    "iso:country":"ES",
    "sg:address":"Avda Antonio Masa Campos, 22",
    "sg:city":"Badajoz",
    "sg:orig_category":"Artes Gr\u00c1ficas, Artes Pl\u00c1sticas (curso)",
    "sg:phone":"+34 924 22 72 25",
    "sg:postcode":"06011",
    "sg:province":"Badajoz",
    "wof:name":"G.and D.iberica S.a.",
    "wof:placetype":"venue"
},
  "geometry": {"coordinates":[-6.9814729691,38.8736228943],"type":"Point"}
}