{
  "type": "Feature",
  "properties": {
    "addr:full":"Pla\u00c7 Clara, 12 Olot Girona 17800",
    "addr:housenumber":"12",
    "addr:postcode":"17800",
    "addr:street":"Clara",
    "iso:country":"ES",
    "sg:address":"Pla\u00c7 Clara, 12",
    "sg:city":"Olot",
    "sg:orig_category":"Psic\u00d3logos",
    "sg:phone":"+34 972 27 20 21",
    "sg:postcode":"17800",
    "sg:province":"Girona",
    "wof:name":"Coromina Pujol Adriana",
    "wof:placetype":"venue"
},
  "geometry": {"coordinates":[2.4893848896,42.1809463501],"type":"Point"}
}