{
  "type": "Feature",
  "properties": {
    "iso:country":"ES",
    "sg:address":"Carrer de Reina M Cristina, 4",
    "sg:city":"Palma",
    "sg:orig_category":"Asesor\u00cda Fiscal Y Jur\u00cddica",
    "sg:phone":"+34 971 75 01 69",
    "sg:postcode":"07004",
    "sg:province":"Islas Baleares",
    "wof:name":"Pons Bonet Pedro",
    "wof:placetype":"venue"
},
  "geometry": {"coordinates":[2.6536231041,39.5770606995],"type":"Point"}
}