{
  "type": "Feature",
  "properties": {
    "iso:country":"ES",
    "sg:address":"Calle de Portugal, 8",
    "sg:city":"Alacant",
    "sg:orig_category":"Abogados",
    "sg:phone":"+34 965 92 39 83",
    "sg:postcode":"03003",
    "sg:province":"Alicante",
    "wof:name":"Andres Canales Asesores Asociados S.l.",
    "wof:placetype":"venue"
},
  "geometry": {"coordinates":[-0.4888384938,38.340045929],"type":"Point"}
}