{
  "type": "Feature",
  "properties": {
    "addr:full":"Calle de Abad Juan Catalan, 1 Madrid Madrid 28032",
    "addr:housenumber":"1",
    "addr:postcode":"28032",
    "addr:street":"Calle De Abad Juan Catalan",
    "iso:country":"ES",
    "sg:address":"Calle de Abad Juan Catalan, 1",
    "sg:city":"Madrid",
    "sg:orig_category":"Electrodom\u00c9sticos (al Por Menor)",
    "sg:phone":"+34 914 28 08 50",
    "sg:postcode":"28032",
    "sg:province":"Madrid",
    "wof:name":"Junkers Aa Asistencia Tecnica Averias Servicio Tecnico Y Reparaciones C.b.",
    "wof:placetype":"venue"
},
  "geometry": {"coordinates":[-3.5932872295,40.4055290222],"type":"Point"}
}