{
  "type": "Feature",
  "properties": {
    "addr:full":"Avda Orense, S/n Marin Pontevedra 36900",
    "addr:housenumber":"s / n",
    "addr:postcode":"36900",
    "addr:street":"Avda Orense",
    "iso:country":"ES",
    "sg:address":"Avda Orense, S/n",
    "sg:city":"Marin",
    "sg:orig_category":"Caf\u00c9s, Bares, Cervecer\u00cdas",
    "sg:phone":"+34 986 88 21 38",
    "sg:postcode":"36900",
    "sg:province":"Pontevedra",
    "wof:name":"Migarco S.l.",
    "wof:placetype":"venue"
},
  "geometry": {"coordinates":[-8.6970291138,42.3926391602],"type":"Point"}
}