{
  "type": "Feature",
  "properties": {
    "addr:full":"J. Bonastre (pol Ind La Borda), 19 Caldes Montbui Barcelona 08140",
    "addr:housenumber":"19",
    "addr:postcode":"08140",
    "addr:street":"J.;Pol;La Borda;Montbui Barcelona",
    "iso:country":"ES",
    "sg:address":"J. Bonastre (pol Ind La Borda), 19",
    "sg:city":"Caldes Montbui",
    "sg:orig_category":"Promotores Constructores",
    "sg:phone":"+34 938 66 51 03",
    "sg:postcode":"08140",
    "sg:province":"Barcelona",
    "wof:name":"Vi\u00f1a Blanch Ramon",
    "wof:placetype":"venue"
},
  "geometry": {"coordinates":[2.1699187756,41.3879165649],"type":"Point"}
}