{
  "type": "Feature",
  "properties": {
    "iso:country":"ES",
    "sg:address":"Calle de Barrantes, 1",
    "sg:city":"Burgos",
    "sg:orig_category":"Asilos De Ancianos. Centros Privados",
    "sg:phone":"+34 947 20 18 47",
    "sg:postcode":"09003",
    "sg:province":"Burgos",
    "wof:name":"Hospital De Barrantes",
    "wof:placetype":"venue"
},
  "geometry": {"coordinates":[-3.7077376842,42.3391342163],"type":"Point"}
}