{
  "type": "Feature",
  "properties": {
    "iso:country":"ES",
    "sg:address":"Rua Pintor Ramon Buch, 2",
    "sg:city":"Vigo",
    "sg:orig_category":"T\u00c9cnicos Veterinarios",
    "sg:phone":"+34 986 20 83 67",
    "sg:postcode":"36209",
    "sg:province":"Pontevedra",
    "wof:name":"Pascual Portanet Mercedes",
    "wof:placetype":"venue"
},
  "geometry": {"coordinates":[-8.7462453842,42.2151756287],"type":"Point"}
}