{
  "type": "Feature",
  "properties": {
    "iso:country":"ES",
    "sg:address":"Rua Carpinteiros (dos), 1",
    "sg:city":"Lugo",
    "sg:orig_category":"Suministros Para Carrocer\u00cdas",
    "sg:phone":"+34 982 20 70 69",
    "sg:postcode":"27003",
    "sg:province":"Lugo",
    "wof:name":"Industrias Doval Tac S.l.",
    "wof:placetype":"venue"
},
  "geometry": {"coordinates":[-7.5599241257,43.0418548584],"type":"Point"}
}