{
  "type": "Feature",
  "properties": {
    "addr:full":"Carrer de Santa Tecla, 18 S. Celoni Barcelona 08470",
    "addr:housenumber":"18",
    "addr:postcode":"08470",
    "addr:street":"Carrer De Santa Tecla;S. Celoni Barcelona",
    "iso:country":"ES",
    "sg:address":"Carrer de Santa Tecla, 18",
    "sg:city":"S. Celoni",
    "sg:orig_category":"M\u00c9dicos: Pediatr\u00cda. Enfermedades De Los Ni\u00d1os",
    "sg:phone":"+34 938 67 07 49",
    "sg:postcode":"08470",
    "sg:province":"Barcelona",
    "wof:name":"Consultori Punt Medic S.c.p.",
    "wof:placetype":"venue"
},
  "geometry": {"coordinates":[2.4864649773,41.6882400513],"type":"Point"}
}