{
  "type": "Feature",
  "properties": {
    "addr:full":"Cmno Pbla Montalban, S/n Galvez Toledo 45164",
    "addr:housenumber":"s / n",
    "addr:postcode":"45164",
    "addr:street":"Cmno Pbla Montalban",
    "iso:country":"ES",
    "sg:address":"Cmno Pbla Montalban, S/n",
    "sg:city":"Galvez",
    "sg:orig_category":"Productores Recolectores, Venta Directa De Vinos",
    "sg:phone":"+34 925 40 01 47",
    "sg:postcode":"45164",
    "sg:province":"Toledo",
    "wof:name":"Cooperativa Del Campo San Agustin",
    "wof:placetype":"venue"
},
  "geometry": {"coordinates":[-4.27850914,39.7078094482],"type":"Point"}
}