{
  "type": "Feature",
  "properties": {
    "addr:full":"Pl Francesc Macia, 8 Barcelona Barcelona 08029",
    "addr:housenumber":"8",
    "addr:postcode":"08029",
    "addr:street":"Pl Francesc Macia",
    "iso:country":"ES",
    "sg:address":"Pl Francesc Macia, 8",
    "sg:city":"Barcelona",
    "sg:orig_category":"M\u00c9dicos: Otorrinolaringolog\u00cda",
    "sg:phone":"+34 934 30 34 48",
    "sg:postcode":"08029",
    "sg:province":"Barcelona",
    "wof:name":"Pi\u00f1as Masso Juan",
    "wof:placetype":"venue"
},
  "geometry": {"coordinates":[2.1446549892,41.3922958374],"type":"Point"}
}