{
  "type": "Feature",
  "properties": {
    "addr:full":"Pol. Ind. Valle G\u00fcimar, S/n Pol.ind. Guimar Santa Cruz De Tenerife 38509",
    "addr:housenumber":"s / n",
    "addr:postcode":"38509",
    "addr:street":"Pol.Ind. Guimar",
    "iso:country":"ES",
    "sg:address":"Pol. Ind. Valle G\u00fcimar, S/n",
    "sg:city":"Pol.ind. Guimar",
    "sg:orig_category":"Comercio De Mobiliario De Oficina",
    "sg:phone":"+34 922 50 30 01",
    "sg:postcode":"38509",
    "sg:province":"Santa Cruz De Tenerife",
    "sg:website":"www.laoficina-tenerife.com",
    "wof:name":"Maquinas Y Equipos De Oficina S.l.",
    "wof:placetype":"venue"
},
  "geometry": {"coordinates":[-16.3739471436,28.3589134216],"type":"Point"}
}