{
  "type": "Feature",
  "properties": {
    "iso:country":"ES",
    "sg:address":"Ctra. Pedro Mu\u00f1oz, Km. 0118,5",
    "sg:city":"Mota Cuervo",
    "sg:orig_category":"Comercio De Hierro",
    "sg:phone":"+34 967 18 09 80",
    "sg:postcode":"16630",
    "sg:province":"Cuenca",
    "wof:name":"Francisco Ros Casares S.l.",
    "wof:placetype":"venue"
},
  "geometry": {"coordinates":[-2.871309042,39.503036499],"type":"Point"}
}