{
  "type": "Feature",
  "properties": {
    "addr:full":"Calle de Mariana De Pineda, 9 Valencina Concepcion Sevilla 41907",
    "addr:housenumber":"9",
    "addr:postcode":"41907",
    "addr:street":"Calle De Mariana De Pineda",
    "iso:country":"ES",
    "sg:address":"Calle de Mariana De Pineda, 9",
    "sg:city":"Valencina Concepcion",
    "sg:orig_category":"Plomeros",
    "sg:phone":"+34 955 72 05 26",
    "sg:postcode":"41907",
    "sg:province":"Sevilla",
    "wof:name":"Fontanerias Riego Y Gas S.l.",
    "wof:placetype":"venue"
},
  "geometry": {"coordinates":[-6.0782990456,37.4167175293],"type":"Point"}
}