{
  "type": "Feature",
  "properties": {
    "addr:full":"Calle de Carreras, 7 Le\u00f3n Le\u00f3n 24007",
    "addr:housenumber":"7",
    "addr:postcode":"24007",
    "addr:street":"Calle De Carreras;Leo\u0301N",
    "iso:country":"ES",
    "sg:address":"Calle de Carreras, 7",
    "sg:city":"Le\u00f3n",
    "sg:orig_category":"Agencias Y Agentes Comerciales, Representantes",
    "sg:phone":"+34 987 23 00 29",
    "sg:postcode":"24007",
    "sg:province":"Le\u00f3n",
    "wof:name":"Gonzalez Quintano Marta",
    "wof:placetype":"venue"
},
  "geometry": {"coordinates":[-5.5692691803,42.6026878357],"type":"Point"}
}