{
  "type": "Feature",
  "properties": {
    "addr:full":"Calle de Cardenal Rodrigo De Castro, 29 Sevilla Sevilla 41005",
    "addr:housenumber":"29",
    "addr:postcode":"41005",
    "addr:street":"Calle De Cardenal Rodrigo De Castro",
    "iso:country":"ES",
    "sg:address":"Calle de Cardenal Rodrigo De Castro, 29",
    "sg:city":"Sevilla",
    "sg:orig_category":"Molduras, Junquillos, Listones Y Molduras Perforadas",
    "sg:phone":"+34 954 65 64 01",
    "sg:postcode":"41005",
    "sg:province":"Sevilla",
    "wof:name":"Verdugo Palma Pedro",
    "wof:placetype":"venue"
},
  "geometry": {"coordinates":[-5.9620141983,37.3778076172],"type":"Point"}
}