{
  "type": "Feature",
  "properties": {
    "addr:full":"Calle de Port De Catarroja - Diseminados, 129 Catarroja Valencia 46470",
    "addr:housenumber":"129",
    "addr:postcode":"46470",
    "addr:street":"Calle De Port De Catarroja Diseminados",
    "iso:country":"ES",
    "sg:address":"Calle de Port De Catarroja - Diseminados, 129",
    "sg:city":"Catarroja",
    "sg:orig_category":"Venta, Colocaci\u00d3n, Reparaci\u00d3n De Radiadores Para Veh\u00cdculos",
    "sg:phone":"+34 961 27 33 31",
    "sg:postcode":"46470",
    "sg:province":"Valencia",
    "sg:website":"www.radiadoressanjos.com",
    "wof:name":"Radiadores Sanjo S.l.",
    "wof:placetype":"venue"
},
  "geometry": {"coordinates":[-0.414440006,39.3972015381],"type":"Point"}
}