{
  "type": "Feature",
  "properties": {
    "addr:full":"Carrer de Comer\u00c7 (del), S/n Tortosa Tarragona 43500",
    "addr:housenumber":"/ n",
    "addr:postcode":"43500",
    "addr:street":"Carrer De Comerc\u0327 Del S",
    "iso:country":"ES",
    "sg:address":"Carrer de Comer\u00c7 (del), S/n",
    "sg:city":"Tortosa",
    "sg:orig_category":"Cerrajer\u00cda, Ferrallista",
    "sg:phone":"+34 977 50 17 27",
    "sg:postcode":"43500",
    "sg:province":"Tarragona",
    "wof:name":"Borras Lapeira Baltasar",
    "wof:placetype":"venue"
},
  "geometry": {"coordinates":[0.5167149901,40.8188743591],"type":"Point"}
}