{
  "type": "Feature",
  "properties": {
    "iso:country":"ES",
    "sg:address":"Escuelas, 16",
    "sg:city":"Salda\u00f1a",
    "sg:orig_category":"Venta, Instalaci\u00d3n De Cocinas",
    "sg:phone":"+34 979 89 05 14",
    "sg:postcode":"34100",
    "sg:province":"Palencia",
    "wof:name":"Santander Leonardo Nuria",
    "wof:placetype":"venue"
},
  "geometry": {"coordinates":[-4.6643338203,42.5343017578],"type":"Point"}
}