{
  "type": "Feature",
  "properties": {
    "iso:country":"ES",
    "sg:address":"Calle de Alfonso Ii De Aragon, 11",
    "sg:city":"Huesca",
    "sg:orig_category":"Empresas De Pintura Y Revestimientos",
    "sg:phone":"+34 974 24 30 46",
    "sg:postcode":"22005",
    "sg:province":"Huesca",
    "wof:name":"Calvo Sanz Roberto",
    "wof:placetype":"venue"
},
  "geometry": {"coordinates":[-0.4027375877,42.1321983337],"type":"Point"}
}