{
  "type": "Feature",
  "properties": {
    "addr:full":"Calle de Camino Del Vallin, 13 Grado Asturias 33820",
    "addr:housenumber":"13",
    "addr:postcode":"33820",
    "addr:street":"Calle De Camino Del Vallin",
    "iso:country":"ES",
    "sg:address":"Calle de Camino Del Vallin, 13",
    "sg:city":"Grado",
    "sg:orig_category":"Promotores Constructores",
    "sg:phone":"+34 985 75 30 62",
    "sg:postcode":"33820",
    "sg:province":"Asturias",
    "wof:name":"New Construction S.l.",
    "wof:placetype":"venue"
},
  "geometry": {"coordinates":[-6.0573301315,43.3139686584],"type":"Point"}
}