{
  "type": "Feature",
  "properties": {
    "addr:full":"Calle de Acera Del Rio, 88 Cordoba C\u00f3rdoba 14009",
    "addr:housenumber":"88",
    "addr:postcode":"14009",
    "addr:street":"Calle De Acera Del Rio;Co\u0301Rdoba",
    "iso:country":"ES",
    "sg:address":"Calle de Acera Del Rio, 88",
    "sg:city":"Cordoba",
    "sg:orig_category":"Librer\u00cdas",
    "sg:phone":"+34 957 20 44 62",
    "sg:postcode":"14009",
    "sg:province":"C\u00f3rdoba",
    "wof:name":"Millan Pinillo Dolores",
    "wof:placetype":"venue"
},
  "geometry": {"coordinates":[-4.7707371712,37.8679962158],"type":"Point"}
}