{
  "type": "Feature",
  "properties": {
    "iso:country":"ES",
    "sg:address":"Calle de Miguel Villanueva, 10",
    "sg:city":"Logro\u00f1o",
    "sg:orig_category":"Compraventa De Antig\u00dcedades",
    "sg:phone":"+34 941 24 73 70",
    "sg:postcode":"26001",
    "sg:province":"La Rioja",
    "wof:name":"Bordados Dama",
    "wof:placetype":"venue"
},
  "geometry": {"coordinates":[-2.4449241161,42.4639778137],"type":"Point"}
}