{
  "type": "Feature",
  "properties": {
    "addr:full":"Plaz Nespral, 1 Langreo Asturias 33900",
    "addr:housenumber":"1",
    "addr:postcode":"33900",
    "addr:street":"Plaz Nespral",
    "iso:country":"ES",
    "sg:address":"Plaz Nespral, 1",
    "sg:city":"Langreo",
    "sg:orig_category":"Zapatos (al Por Menor)",
    "sg:phone":"+34 985 67 39 13",
    "sg:postcode":"33900",
    "sg:province":"Asturias",
    "wof:name":"Fernandez Rodriguez Carmen",
    "wof:placetype":"venue"
},
  "geometry": {"coordinates":[-5.6827945709,43.2960968018],"type":"Point"}
}