{
  "type": "Feature",
  "properties": {
    "addr:full":"Urb San Nicolas, 2 Vernejo Cantabria 39506",
    "addr:housenumber":"2",
    "addr:postcode":"39506",
    "addr:street":"San Nicolas",
    "iso:country":"ES",
    "sg:address":"Urb San Nicolas, 2",
    "sg:city":"Vernejo",
    "sg:orig_category":"T\u00c9cnicos Veterinarios",
    "sg:phone":"+34 942 70 20 48",
    "sg:postcode":"39506",
    "sg:province":"Cantabria",
    "wof:name":"Alonso Martinez Jesus Angel",
    "wof:placetype":"venue"
},
  "geometry": {"coordinates":[-4.2232317924,43.3019752502],"type":"Point"}
}