{
  "type": "Feature",
  "properties": {
    "iso:country":"ES",
    "sg:address":"Don Carnal(pol Ind Labradorcico), S/n",
    "sg:city":"Aguilas",
    "sg:orig_category":"Bebidas",
    "sg:phone":"+34 968 41 07 25",
    "sg:postcode":"30880",
    "sg:province":"Murcia",
    "wof:name":"Jose Luis Salas Martinez S.l.",
    "wof:placetype":"venue"
},
  "geometry": {"coordinates":[-1.5811840296,37.4023399353],"type":"Point"}
}