{
  "type": "Feature",
  "properties": {
    "iso:country":"ES",
    "sg:address":"Carrer de Gelabert, 22",
    "sg:city":"Barcelona",
    "sg:orig_category":"Publicidad (soportes Y Gesti\u00d3n)",
    "sg:phone":"+34 934 19 06 00",
    "sg:postcode":"08029",
    "sg:province":"Barcelona",
    "wof:name":"Creaciones Olimpia S.a.",
    "wof:placetype":"venue"
},
  "geometry": {"coordinates":[2.1419870853,41.388092041],"type":"Point"}
}