{
  "type": "Feature",
  "properties": {
    "iso:country":"ES",
    "sg:address":"Carrer de Sant Ermengol, 6",
    "sg:city":"Abrera",
    "sg:orig_category":"Ropa Para Ni\u00d1os (al Por Menor)",
    "sg:phone":"+34 937 70 25 83",
    "sg:postcode":"08630",
    "sg:province":"Barcelona",
    "wof:name":"Espinosa Ospina Iliana Beatriz",
    "wof:placetype":"venue"
},
  "geometry": {"coordinates":[1.8942470551,41.521030426],"type":"Point"}
}