{
  "type": "Feature",
  "properties": {
    "addr:full":"Calle de Nicolas Salmeron, 30 Valladolid Valladolid 47004",
    "addr:housenumber":"30",
    "addr:postcode":"47004",
    "addr:street":"Calle De Nicolas Salmeron",
    "iso:country":"ES",
    "sg:address":"Calle de Nicolas Salmeron, 30",
    "sg:city":"Valladolid",
    "sg:orig_category":"Farmacias",
    "sg:phone":"+34 983 29 13 06",
    "sg:postcode":"47004",
    "sg:province":"Valladolid",
    "wof:name":"Monedero Vega Maria Del Pilar",
    "wof:placetype":"venue"
},
  "geometry": {"coordinates":[-4.7191419601,41.6463165283],"type":"Point"}
}