{
  "type": "Feature",
  "properties": {
    "iso:country":"ES",
    "sg:address":"Avda Pinos (los), 28",
    "sg:city":"Guardamar Segura",
    "sg:orig_category":"Electrodom\u00c9sticos (al Por Menor)",
    "sg:phone":"+34 965 72 91 01",
    "sg:postcode":"03140",
    "sg:province":"Alicante",
    "wof:name":"Diego Miller Daniel",
    "wof:placetype":"venue"
},
  "geometry": {"coordinates":[-0.6523429751,38.088508606],"type":"Point"}
}