{
  "type": "Feature",
  "properties": {
    "addr:full":"Carrer de Mare De Deu Dels Desemparats, 65 Hospitalet Llobregat Barcelona 08903",
    "addr:housenumber":"65",
    "addr:postcode":"08903",
    "addr:street":"Carrer De Mare De Deu;Desemparats",
    "iso:country":"ES",
    "sg:address":"Carrer de Mare De Deu Dels Desemparats, 65",
    "sg:city":"Hospitalet Llobregat",
    "sg:orig_category":"Internados & Ense\u00d1anza Privada",
    "sg:phone":"+34 934 49 59 00",
    "sg:postcode":"08903",
    "sg:province":"Barcelona",
    "wof:name":"Fundacio Escoles Parroquials Co%egi Sant Jaume Apostol",
    "wof:placetype":"venue"
},
  "geometry": {"coordinates":[2.1228559017,41.3708267212],"type":"Point"}
}