{
  "type": "Feature",
  "properties": {
    "addr:full":"Calle de Periodista Azzati, 9 Puerto Valencia 46520",
    "addr:housenumber":"9",
    "addr:postcode":"46520",
    "addr:street":"Calle De Periodista Azzati",
    "iso:country":"ES",
    "sg:address":"Calle de Periodista Azzati, 9",
    "sg:city":"Puerto",
    "sg:orig_category":"Electrodom\u00c9sticos (al Por Menor)",
    "sg:phone":"+34 962 67 33 21",
    "sg:postcode":"46520",
    "sg:province":"Valencia",
    "wof:name":"Radio Castilla S.a.",
    "wof:placetype":"venue"
},
  "geometry": {"coordinates":[-0.2264869958,39.6657905579],"type":"Point"}
}