{
  "type": "Feature",
  "properties": {
    "iso:country":"ES",
    "sg:address":"Pase Estacion (la), 22",
    "sg:city":"Jaen",
    "sg:orig_category":"Financiaci\u00d3n Y Cr\u00c9ditos",
    "sg:phone":"+34 953 27 19 36",
    "sg:postcode":"23003",
    "sg:province":"Ja\u00e9n",
    "wof:name":"Avalunion S.g.r.",
    "wof:placetype":"venue"
},
  "geometry": {"coordinates":[-3.7269899845,37.7898101807],"type":"Point"}
}