{
  "type": "Feature",
  "properties": {
    "addr:full":"Calle de Caballero De Rodas, 22 Torrevieja Alicante 03180",
    "addr:housenumber":"22",
    "addr:postcode":"03180",
    "addr:street":"Calle De Caballero De Rodas",
    "iso:country":"ES",
    "sg:address":"Calle de Caballero De Rodas, 22",
    "sg:city":"Torrevieja",
    "sg:orig_category":"Ropa Para Caballeros (al Por Menor)",
    "sg:phone":"+34 965 71 59 09",
    "sg:postcode":"03180",
    "sg:province":"Alicante",
    "wof:name":"Modas Torredevilla S.l.",
    "wof:placetype":"venue"
},
  "geometry": {"coordinates":[-0.681684494,37.9778518677],"type":"Point"}
}