{
  "type": "Feature",
  "properties": {
    "iso:country":"ES",
    "sg:address":"Calle de Zamacola, 57",
    "sg:city":"Bilbao",
    "sg:orig_category":"Supermercados Y Hipermercados",
    "sg:phone":"+34 944 15 93 64",
    "sg:postcode":"48003",
    "sg:province":"Vizcaya",
    "wof:name":"Jose Luis Alonso Melgar",
    "wof:placetype":"venue"
},
  "geometry": {"coordinates":[-2.9240961075,43.2414894104],"type":"Point"}
}