{
  "type": "Feature",
  "properties": {
    "iso:country":"ES",
    "sg:address":"Calle de Alcaudete, 12",
    "sg:city":"Talavera Reina",
    "sg:orig_category":"Empresas De Carpinter\u00cda",
    "sg:phone":"+34 925 81 16 93",
    "sg:postcode":"45600",
    "sg:province":"Toledo",
    "wof:name":"Moreno Bravo Juan Jose",
    "wof:placetype":"venue"
},
  "geometry": {"coordinates":[-4.8307337761,39.9504013062],"type":"Point"}
}