{
  "type": "Feature",
  "properties": {
    "addr:full":"Calle de Olivar (el), 16 Barraco \u00c1vila 05110",
    "addr:housenumber":"16",
    "addr:postcode":"05110",
    "addr:street":"Calle De Olivar El",
    "iso:country":"ES",
    "sg:address":"Calle de Olivar (el), 16",
    "sg:city":"Barraco",
    "sg:orig_category":"Cr\u00cda De Animales",
    "sg:phone":"+34 920 28 14 72",
    "sg:postcode":"05110",
    "sg:province":"\u00c1vila",
    "wof:name":"Diaz Maqueda Jesus",
    "wof:placetype":"venue"
},
  "geometry": {"coordinates":[-4.6392588615,40.4724388123],"type":"Point"}
}