{
  "type": "Feature",
  "properties": {
    "addr:full":"Ctra Sant Joan, 28 Sineu Islas Baleares 07510",
    "addr:housenumber":"28",
    "addr:postcode":"07510",
    "addr:street":"Ctra Sant Joan",
    "iso:country":"ES",
    "sg:address":"Ctra Sant Joan, 28",
    "sg:city":"Sineu",
    "sg:orig_category":"Empresas De Carpinter\u00cda De Madera",
    "sg:phone":"+34 971 52 00 80",
    "sg:postcode":"07510",
    "sg:province":"Islas Baleares",
    "wof:name":"Ramis Amorosl Miquel",
    "wof:placetype":"venue"
},
  "geometry": {"coordinates":[3.0104799271,39.63904953],"type":"Point"}
}