{
  "type": "Feature",
  "properties": {
    "addr:full":"Ctra. Huelva-punta Umbria, Km. 0006,0 Aljaraque Huelva 21110",
    "addr:postcode":"21110",
    "addr:street":"Ctra. Huelva-Punta Umbria Km. 0006,0",
    "iso:country":"ES",
    "sg:address":"Ctra. Huelva-punta Umbria, Km. 0006,0",
    "sg:city":"Aljaraque",
    "sg:orig_category":"Deportes Y Ocio: Art\u00cdculos Y Ropas (al Por Menor Y Accesorios)",
    "sg:phone":"+34 959 52 15 08",
    "sg:postcode":"21110",
    "sg:province":"Huelva",
    "wof:name":"Sanchez Becerra Miguel",
    "wof:placetype":"venue"
},
  "geometry": {"coordinates":[-7.0241990089,37.2709159851],"type":"Point"}
}