{
  "type": "Feature",
  "properties": {
    "addr:full":"Calle de Cine (el), 10 Noja Cantabria 39180",
    "addr:postcode":"39180",
    "addr:street":"Calle De",
    "iso:country":"ES",
    "sg:address":"Calle de Cine (el), 10",
    "sg:city":"Noja",
    "sg:orig_category":"T\u00c9cnicos Veterinarios",
    "sg:phone":"+34 942 63 12 96",
    "sg:postcode":"39180",
    "sg:province":"Cantabria",
    "wof:name":"Garcia Velarde Jose",
    "wof:placetype":"venue"
},
  "geometry": {"coordinates":[-3.5234599113,43.4816131592],"type":"Point"}
}