{
  "type": "Feature",
  "properties": {
    "iso:country":"ES",
    "sg:address":"Barr Islares, 26",
    "sg:city":"Islares",
    "sg:orig_category":"M\u00c1quinas De Escribir, M\u00c1quinas De Oficina (al Por Menor, Reparaci\u00d3n)",
    "sg:phone":"+34 942 86 76 83",
    "sg:postcode":"39798",
    "sg:province":"Cantabria",
    "wof:name":"Chueca Pedrueza Francisco Javier",
    "wof:placetype":"venue"
},
  "geometry": {"coordinates":[-3.3002378941,43.4040870667],"type":"Point"}
}