{
  "type": "Feature",
  "properties": {
    "addr:full":"Calle de Vizcaya, 4 Aljaraque Huelva 21110",
    "addr:housenumber":"4",
    "addr:postcode":"21110",
    "addr:street":"Calle De Vizcaya",
    "iso:country":"ES",
    "sg:address":"Calle de Vizcaya, 4",
    "sg:city":"Aljaraque",
    "sg:orig_category":"Bazares, Art\u00cdculos De Limpieza Y De Cocina (al Por Menor)",
    "sg:phone":"+34 959 31 83 76",
    "sg:postcode":"21110",
    "sg:province":"Huelva",
    "wof:name":"Illesca Rodriguez Francisco",
    "wof:placetype":"venue"
},
  "geometry": {"coordinates":[-7.0254921913,37.2673797607],"type":"Point"}
}