{
  "type": "Feature",
  "properties": {
    "addr:full":"Avda Alemania -urb Los Balcones, S/n Balcones Alicante 03186",
    "addr:housenumber":"s / n",
    "addr:postcode":"03186",
    "addr:street":"Avda Alemania Urb Los",
    "iso:country":"ES",
    "sg:address":"Avda Alemania -urb Los Balcones, S/n",
    "sg:city":"Balcones",
    "sg:orig_category":"Asociaciones Y Clubs Deportivos",
    "sg:phone":"+34 966 72 21 67",
    "sg:postcode":"03186",
    "sg:province":"Alicante",
    "wof:name":"Club De Tenis Torrevieja",
    "wof:placetype":"venue"
},
  "geometry": {"coordinates":[-0.7286139727,37.9577560425],"type":"Point"}
}