{
  "type": "Feature",
  "properties": {
    "iso:country":"ES",
    "sg:address":"Calle de Laguna, 103",
    "sg:city":"Madrid",
    "sg:orig_category":"Ropa Para Caballeros (al Por Menor)",
    "sg:phone":"+34 914 62 98 07",
    "sg:postcode":"28025",
    "sg:province":"Madrid",
    "wof:name":"Gonzalez Esperon Ramon",
    "wof:placetype":"venue"
},
  "geometry": {"coordinates":[-3.7419428825,40.3897781372],"type":"Point"}
}