{
  "type": "Feature",
  "properties": {
    "iso:country":"ES",
    "sg:address":"Plaza Martires, 4",
    "sg:city":"Cehegin",
    "sg:orig_category":"Alimentaci\u00d3n General (al Por Menor)",
    "sg:phone":"+34 968 74 01 86",
    "sg:postcode":"30430",
    "sg:province":"Murcia",
    "wof:name":"O\u00d1ate Corbalan Juan",
    "wof:placetype":"venue"
},
  "geometry": {"coordinates":[-1.796923995,38.0913162231],"type":"Point"}
}