{
  "type": "Feature",
  "properties": {
    "addr:full":"Carr Alexandre De Cabanyes, 38 Vilanova I La Geltru Barcelona 08800",
    "addr:housenumber":"38",
    "addr:postcode":"08800",
    "addr:street":"Carr Alexandre De Cabanyes",
    "iso:country":"ES",
    "sg:address":"Carr Alexandre De Cabanyes, 38",
    "sg:city":"Vilanova I La Geltru",
    "sg:orig_category":"Peluquer\u00cdas, Peluquer\u00cda Mixta",
    "sg:phone":"+34 938 15 54 29",
    "sg:postcode":"08800",
    "sg:province":"Barcelona",
    "wof:name":"Sanchez Castillo Maria Isabel",
    "wof:placetype":"venue"
},
  "geometry": {"coordinates":[1.7163579464,41.2131538391],"type":"Point"}
}