{
  "type": "Feature",
  "properties": {
    "iso:country":"ES",
    "sg:address":"Calle de Miguel Cruz Cuenca, 11",
    "sg:city":"Lucena",
    "sg:orig_category":"Centros Empresariales",
    "sg:phone":"+34 957 51 48 27",
    "sg:postcode":"14900",
    "sg:province":"C\u00f3rdoba",
    "sg:website":"www.jfprogram.lucenaonline.net",
    "wof:name":"Sistemas Informaticos Lucentinos Y Comercio Electronico S.l.",
    "wof:placetype":"venue"
},
  "geometry": {"coordinates":[-4.4935688972,37.4098510742],"type":"Point"}
}