{
  "type": "Feature",
  "properties": {
    "iso:country":"ES",
    "sg:address":"Calle de De Las Eras, 38",
    "sg:city":"Benavente",
    "sg:orig_category":"Agencias Y Asesores De Publicidad",
    "sg:phone":"+34 980 63 75 21",
    "sg:postcode":"49600",
    "sg:province":"Zamora",
    "wof:name":"T Y D Agencia De Publicidad S.l.",
    "wof:placetype":"venue"
},
  "geometry": {"coordinates":[-5.7452836037,42.0332946777],"type":"Point"}
}