{
  "type": "Feature",
  "properties": {
    "addr:full":"Pol Ind San Diego, S/n Huelva Huelva 21007",
    "addr:postcode":"21007",
    "addr:street":"Diego S / N",
    "iso:country":"ES",
    "sg:address":"Pol Ind San Diego, S/n",
    "sg:city":"Huelva",
    "sg:orig_category":"Centros Empresariales",
    "sg:phone":"+34 959 27 18 62",
    "sg:postcode":"21007",
    "sg:province":"Huelva",
    "wof:name":"Fibroplac S.l.",
    "wof:placetype":"venue"
},
  "geometry": {"coordinates":[-6.9495940208,37.256313324],"type":"Point"}
}