{
  "type": "Feature",
  "properties": {
    "addr:full":"Calle de Mayor Alta, 11 Fuenmayor La Rioja 26360",
    "addr:housenumber":"11",
    "addr:postcode":"26360",
    "addr:street":"Calle De Mayor Alta;Rioja",
    "iso:country":"ES",
    "sg:address":"Calle de Mayor Alta, 11",
    "sg:city":"Fuenmayor",
    "sg:orig_category":"Estancos",
    "sg:phone":"+34 941 45 01 08",
    "sg:postcode":"26360",
    "sg:province":"La Rioja",
    "wof:name":"Granado Aguado Felix",
    "wof:placetype":"venue"
},
  "geometry": {"coordinates":[-2.5610060692,42.4670066833],"type":"Point"}
}