{
  "type": "Feature",
  "properties": {
    "iso:country":"ES",
    "sg:address":"Calle de Santas Patronas, 12",
    "sg:city":"Sevilla",
    "sg:orig_category":"Peluquer\u00cdas, Peluquer\u00cda Mixta",
    "sg:phone":"+34 954 21 65 02",
    "sg:postcode":"41001",
    "sg:province":"Sevilla",
    "wof:name":"Alvarez Beigdeber Luis",
    "wof:placetype":"venue"
},
  "geometry": {"coordinates":[-5.9992423058,37.3887290955],"type":"Point"}
}