{
  "type": "Feature",
  "properties": {
    "iso:country":"ES",
    "sg:address":"Calle de Independencia, 11",
    "sg:city":"Oviedo",
    "sg:orig_category":"Inmobiliaria (agencias)",
    "sg:phone":"+34 985 22 40 20",
    "sg:postcode":"33004",
    "sg:province":"Asturias",
    "wof:name":"Eureca Servicios Inmobiliarios S.l",
    "wof:placetype":"venue"
},
  "geometry": {"coordinates":[-5.8557910919,43.364616394],"type":"Point"}
}