{
  "type": "Feature",
  "properties": {
    "iso:country":"ES",
    "sg:address":"Calle de Ca\u00d1ada Del Pilar, 33",
    "sg:city":"Lepe",
    "sg:orig_category":"Empresas De Carpinter\u00cda Met\u00c1lica",
    "sg:phone":"+34 959 64 52 50",
    "sg:postcode":"21440",
    "sg:province":"Huelva",
    "wof:name":"Santisa La Bella S.l.l.",
    "wof:placetype":"venue"
},
  "geometry": {"coordinates":[-7.2040290833,37.2498512268],"type":"Point"}
}