{
  "type": "Feature",
  "properties": {
    "iso:country":"ES",
    "sg:address":"Carrer de Roger De Flor, 94",
    "sg:city":"Barcelona",
    "sg:orig_category":"Caf\u00c9s, Bares, Cervecer\u00cdas",
    "sg:phone":"+34 932 31 69 64",
    "sg:postcode":"08013",
    "sg:province":"Barcelona",
    "wof:name":"R. De Flor S.l.",
    "wof:placetype":"venue"
},
  "geometry": {"coordinates":[2.178951025,41.3942451477],"type":"Point"}
}