{
  "type": "Feature",
  "properties": {
    "iso:country":"ES",
    "sg:address":"Ctra Alcolea, S/n",
    "sg:city":"Villanueva Rio Y Minas",
    "sg:orig_category":"Empresas De Electricidad En General",
    "sg:phone":"+34 955 64 44 11",
    "sg:postcode":"41350",
    "sg:province":"Sevilla",
    "wof:name":"Endesa Servicios S.l. Sociedad Unipersonal",
    "wof:placetype":"venue"
},
  "geometry": {"coordinates":[-5.7183542252,37.6519584656],"type":"Point"}
}