{
  "type": "Feature",
  "properties": {
    "addr:full":"Barr Pol (el), 1 Hoznayo Cantabria 39716",
    "addr:housenumber":"1",
    "addr:postcode":"39716",
    "addr:street":"El",
    "iso:country":"ES",
    "sg:address":"Barr Pol (el), 1",
    "sg:city":"Hoznayo",
    "sg:orig_category":"Contenedores (mercanc\u00cdas)",
    "sg:phone":"+34 942 52 59 00",
    "sg:postcode":"39716",
    "sg:province":"Cantabria",
    "wof:name":"Christian Salvensen Gerposa S.a.",
    "wof:placetype":"venue"
},
  "geometry": {"coordinates":[-3.6326639652,43.3630180359],"type":"Point"}
}