{
  "type": "Feature",
  "properties": {
    "iso:country":"ES",
    "sg:address":"P. Industrial, S/n",
    "sg:city":"Melilla",
    "sg:orig_category":"Ropa Y Accesorios",
    "sg:phone":"+34 952 67 37 79",
    "sg:postcode":"52006",
    "sg:province":"Melilla",
    "wof:name":"Meki Jeans Textil Shoes S.l.",
    "wof:placetype":"venue"
},
  "geometry": {"coordinates":[-2.9383699894,35.2764587402],"type":"Point"}
}