{
  "type": "Feature",
  "properties": {
    "iso:country":"ES",
    "sg:address":"Calle de Enmedio, 46",
    "sg:city":"Castellon",
    "sg:orig_category":"Fotograf\u00cda Y Cine: Aparatos, Pel\u00cdculas Y Accesorios (fabricaci\u00d3n, Al Por Mayor)",
    "sg:phone":"+34 964 22 12 08",
    "sg:postcode":"12001",
    "sg:province":"Castell\u00f3n",
    "wof:name":"Fotografia Galart C.b.",
    "wof:placetype":"venue"
},
  "geometry": {"coordinates":[-0.0388239995,39.9858398438],"type":"Point"}
}