{
  "type": "Feature",
  "properties": {
    "iso:country":"ES",
    "sg:address":"Avda Virgen Del Carmen, S/n",
    "sg:city":"Algeciras",
    "sg:orig_category":"M\u00c9dicos: Ginecolog\u00cda Y Obstetricia",
    "sg:phone":"+34 956 65 58 51",
    "sg:postcode":"11204",
    "sg:province":"C\u00e1diz",
    "wof:name":"Sanchez Barrado Francisco",
    "wof:placetype":"venue"
},
  "geometry": {"coordinates":[-5.453663826,36.1419258118],"type":"Point"}
}