{
  "type": "Feature",
  "properties": {
    "addr:full":"Calle de Madrid, 71 Getafe Madrid 28901",
    "addr:housenumber":"71",
    "addr:postcode":"28901",
    "addr:street":"Calle De Madrid",
    "iso:country":"ES",
    "sg:address":"Calle de Madrid, 71",
    "sg:city":"Getafe",
    "sg:orig_category":"Cl\u00cdnicas M\u00c9dicas",
    "sg:phone":"+34 916 95 94 71",
    "sg:postcode":"28901",
    "sg:province":"Madrid",
    "wof:name":"Centro Medico Quirurgico Nuestra Se\u00f1ora De Los Angeles",
    "wof:placetype":"venue"
},
  "geometry": {"coordinates":[-3.7294199467,40.3083992004],"type":"Point"}
}