{
  "type": "Feature",
  "properties": {
    "addr:full":"Calle de Tajos, 9 Yunquera M\u00e1laga 29410",
    "addr:housenumber":"9",
    "addr:postcode":"29410",
    "addr:street":"Calle De Tajos",
    "iso:country":"ES",
    "sg:address":"Calle de Tajos, 9",
    "sg:city":"Yunquera",
    "sg:orig_category":"Electrodom\u00c9sticos (al Por Menor)",
    "sg:phone":"+34 952 48 25 67",
    "sg:postcode":"29410",
    "sg:province":"M\u00e1laga",
    "wof:name":"Rivas Camacho Francisco",
    "wof:placetype":"venue"
},
  "geometry": {"coordinates":[-4.9194321632,36.7311286926],"type":"Point"}
}