{
  "type": "Feature",
  "properties": {
    "iso:country":"ES",
    "sg:address":"Avda Islas Canarias, S/n",
    "sg:city":"Costa Teguise",
    "sg:orig_category":"Alquiler De Apartamentos",
    "sg:phone":"+34 928 59 20 00",
    "sg:postcode":"35509",
    "sg:province":"Las Palmas",
    "wof:name":"Realizaciones Inmobiliarias Canarias S.a.",
    "wof:placetype":"venue"
},
  "geometry": {"coordinates":[-13.5916891098,28.955160141],"type":"Point"}
}