{
  "type": "Feature",
  "properties": {
    "iso:country":"ES",
    "sg:address":"Plaz Republica Del Ecuador, 7",
    "sg:city":"Madrid",
    "sg:orig_category":"Muebles, Minoristas",
    "sg:phone":"+34 914 57 01 22",
    "sg:postcode":"28016",
    "sg:province":"Madrid",
    "wof:name":"Martinez-botas Mateo Jose Andres",
    "wof:placetype":"venue"
},
  "geometry": {"coordinates":[-3.6805109978,40.4527587891],"type":"Point"}
}