{
  "type": "Feature",
  "properties": {
    "addr:full":"Carr Rovellada De Baix, 34 Mao Islas Baleares 07703",
    "addr:housenumber":"34",
    "addr:postcode":"07703",
    "addr:street":"Carr Rovellada De Baix",
    "iso:country":"ES",
    "sg:address":"Carr Rovellada De Baix, 34",
    "sg:city":"Mao",
    "sg:orig_category":"Institutos De Belleza",
    "sg:phone":"+34 971 35 31 55",
    "sg:postcode":"07703",
    "sg:province":"Islas Baleares",
    "wof:name":"Sintes Pons Cristina",
    "wof:placetype":"venue"
},
  "geometry": {"coordinates":[4.2599368095,39.8892860413],"type":"Point"}
}