{
  "type": "Feature",
  "properties": {
    "iso:country":"ES",
    "sg:address":"Calle de Virgen De La Soledad, 13",
    "sg:city":"Guadalajara",
    "sg:orig_category":"Art\u00cdculos De Regalo (al Por Menor)",
    "sg:phone":"+34 949 22 07 43",
    "sg:postcode":"19003",
    "sg:province":"Guadalajara",
    "wof:name":"Pepa Y Rosa S.l.",
    "wof:placetype":"venue"
},
  "geometry": {"coordinates":[-3.1656219959,40.6281661987],"type":"Point"}
}