{
  "type": "Feature",
  "properties": {
    "iso:country":"ES",
    "sg:address":"Calle de Don Jaime I, 2",
    "sg:city":"Zaragoza",
    "sg:orig_category":"Bisuter\u00cda, Joyer\u00cda, Relojer\u00cda (al Por Menor)",
    "sg:phone":"+34 976 39 70 51",
    "sg:postcode":"50001",
    "sg:province":"Zaragoza",
    "wof:name":"Mu\u00f1io Perez Ester",
    "wof:placetype":"venue"
},
  "geometry": {"coordinates":[-0.8799827099,41.6520385742],"type":"Point"}
}