{
  "type": "Feature",
  "properties": {
    "iso:country":"ES",
    "sg:address":"Carrer de Roger De Lluria, 51",
    "sg:city":"Barcelona",
    "sg:orig_category":"Ropa De Trabajo Y Profesionales (fabricaci\u00d3n, Al Por Mayor)",
    "sg:phone":"+34 934 88 04 70",
    "sg:postcode":"08009",
    "sg:province":"Barcelona",
    "wof:name":"Regas Esteve Paul",
    "wof:placetype":"venue"
},
  "geometry": {"coordinates":[2.1683270931,41.3933525085],"type":"Point"}
}