{
  "type": "Feature",
  "properties": {
    "addr:full":"Calle de Cristobal Colon, 4 Ayamonte Huelva 21400",
    "addr:housenumber":"4",
    "addr:postcode":"21400",
    "addr:street":"Calle De Cristobal Colon",
    "iso:country":"ES",
    "sg:address":"Calle de Cristobal Colon, 4",
    "sg:city":"Ayamonte",
    "sg:orig_category":"Fabricaci\u00d3n De Sobres, Bolsas Y Fundas",
    "sg:phone":"+34 959 47 01 85",
    "sg:postcode":"21400",
    "sg:province":"Huelva",
    "wof:name":"Delgado Casal Maria Del Carmen",
    "wof:placetype":"venue"
},
  "geometry": {"coordinates":[-7.4080610275,37.2131538391],"type":"Point"}
}