{
  "type": "Feature",
  "properties": {
    "addr:full":"Calle de Alcaudon, S/n Fuenlabrada Madrid 28946",
    "addr:housenumber":"s",
    "addr:postcode":"28946",
    "addr:street":"Calle De Alcaudon;/ N",
    "iso:country":"ES",
    "sg:address":"Calle de Alcaudon, S/n",
    "sg:city":"Fuenlabrada",
    "sg:orig_category":"Materias Pl\u00c1sticas: Art\u00cdculos Para La Industria",
    "sg:phone":"+34 916 42 27 40",
    "sg:postcode":"28946",
    "sg:province":"Madrid",
    "wof:name":"Carradilla Perlado Elvira",
    "wof:placetype":"venue"
},
  "geometry": {"coordinates":[-3.7611234188,40.2613525391],"type":"Point"}
}