{
  "type": "Feature",
  "properties": {
    "iso:country":"ES",
    "sg:address":"Ctra General Icod El Alto, S/n",
    "sg:city":"Icod El Alto",
    "sg:orig_category":"Ense\u00d1anza Variada",
    "sg:phone":"+34 922 35 98 90",
    "sg:postcode":"38414",
    "sg:province":"Santa Cruz De Tenerife",
    "wof:name":"Mancomunidad Del Norte De Tenerife",
    "wof:placetype":"venue"
},
  "geometry": {"coordinates":[-16.6046619415,28.3820896149],"type":"Point"}
}