{
  "type": "Feature",
  "properties": {
    "addr:full":"Avda Huertas Del Sacramento, 8 Ponferrada Le\u00f3n 24400",
    "addr:housenumber":"8",
    "addr:postcode":"24400",
    "addr:street":"Avda Huertas Del Sacramento",
    "iso:country":"ES",
    "sg:address":"Avda Huertas Del Sacramento, 8",
    "sg:city":"Ponferrada",
    "sg:orig_category":"Centros De Educaci\u00d3n Especial",
    "sg:phone":"+34 987 40 28 68",
    "sg:postcode":"24400",
    "sg:province":"Le\u00f3n",
    "wof:name":"Colegio Publico Pe\u00f1alba",
    "wof:placetype":"venue"
},
  "geometry": {"coordinates":[-6.5941858292,42.5523643494],"type":"Point"}
}