{
  "type": "Feature",
  "properties": {
    "addr:full":"Calle de Doctor Ferran, S/n Salamanca Salamanca 37008",
    "addr:housenumber":"s / n",
    "addr:postcode":"37008",
    "addr:street":"Calle De Doctor Ferran",
    "iso:country":"ES",
    "sg:address":"Calle de Doctor Ferran, S/n",
    "sg:city":"Salamanca",
    "sg:orig_category":"Fabricaci\u00d3n Y Comercio De M\u00c1quinas",
    "sg:phone":"+34 923 19 03 80",
    "sg:postcode":"37008",
    "sg:province":"Salamanca",
    "wof:name":"Comercial Agricola Salmantina S. A.",
    "wof:placetype":"venue"
},
  "geometry": {"coordinates":[-5.6648292542,40.9439125061],"type":"Point"}
}