{
  "type": "Feature",
  "properties": {
    "addr:full":"Carrer de Lisboa, 13 Barcelona Barcelona 08032",
    "addr:housenumber":"13",
    "addr:postcode":"08032",
    "addr:street":"Carrer De Lisboa",
    "iso:country":"ES",
    "sg:address":"Carrer de Lisboa, 13",
    "sg:city":"Barcelona",
    "sg:orig_category":"Reposter\u00cdas",
    "sg:phone":"+34 934 29 96 42",
    "sg:postcode":"08032",
    "sg:province":"Barcelona",
    "wof:name":"Desiree Y Carlos Panaderias S.l.",
    "wof:placetype":"venue"
},
  "geometry": {"coordinates":[2.1584200859,41.4294090271],"type":"Point"}
}