{
  "type": "Feature",
  "properties": {
    "addr:full":"Cno. Muntanya, 160 Son Ferriol Islas Baleares 07198",
    "addr:housenumber":"160",
    "addr:postcode":"07198",
    "addr:street":"Cno. Muntanya",
    "iso:country":"ES",
    "sg:address":"Cno. Muntanya, 160",
    "sg:city":"Son Ferriol",
    "sg:orig_category":"Empresas De Carpinter\u00cda De Madera",
    "sg:phone":"+34 971 42 90 52",
    "sg:postcode":"07198",
    "sg:province":"Islas Baleares",
    "wof:name":"Construciones Y Alquileres Arabesco",
    "wof:placetype":"venue"
},
  "geometry": {"coordinates":[2.7178099155,39.5789794922],"type":"Point"}
}