{
  "type": "Feature",
  "properties": {
    "addr:full":"Avda Perez Galdos, 7 Castellon Castell\u00f3n 12002",
    "addr:housenumber":"7",
    "addr:postcode":"12002",
    "addr:street":"Avda Perez Galdos;Castello\u0301N",
    "iso:country":"ES",
    "sg:address":"Avda Perez Galdos, 7",
    "sg:city":"Castellon",
    "sg:orig_category":"M\u00c9dicos: Foniatr\u00cda Y Logopedia",
    "sg:phone":"+34 964 25 50 09",
    "sg:postcode":"12002",
    "sg:province":"Castell\u00f3n",
    "wof:name":"Iba\u00f1ez Recatala Froilan",
    "wof:placetype":"venue"
},
  "geometry": {"coordinates":[-0.0436520018,39.9861030579],"type":"Point"}
}