{
  "type": "Feature",
  "properties": {
    "addr:full":"Calle de Mar Caspio, 31 Madrid Madrid 28033",
    "addr:housenumber":"31",
    "addr:postcode":"madrid;28033",
    "addr:street":"Calle De Mar Caspio",
    "iso:country":"ES",
    "sg:address":"Calle de Mar Caspio, 31",
    "sg:city":"Madrid",
    "sg:orig_category":"Molduras, Junquillos, Listones Y Molduras Perforadas",
    "sg:phone":"+34 917 63 59 92",
    "sg:postcode":"28033",
    "sg:province":"Madrid",
    "wof:name":"Pinto Uceda Cesareo Elias",
    "wof:placetype":"venue"
},
  "geometry": {"coordinates":[-3.6444239616,40.4736099243],"type":"Point"}
}