{
  "type": "Feature",
  "properties": {
    "iso:country":"ES",
    "sg:address":"Cmno Aperribai, 4",
    "sg:city":"Galdakao",
    "sg:orig_category":"Empresas De Carpinter\u00cda De Madera",
    "sg:phone":"+34 944 56 27 87",
    "sg:postcode":"48960",
    "sg:province":"Vizcaya",
    "wof:name":"Carpinteria Onena (urrutikoetxea Uriarte Roberto)",
    "wof:placetype":"venue"
},
  "geometry": {"coordinates":[-2.8606379032,43.2332572937],"type":"Point"}
}