{
  "type": "Feature",
  "properties": {
    "iso:country":"ES",
    "sg:address":"Xarol, 7",
    "sg:city":"Badalona",
    "sg:orig_category":"Material Y Herramientas Agr\u00cdcolas",
    "sg:phone":"+34 933 81 00 62",
    "sg:postcode":"08915",
    "sg:province":"Barcelona",
    "wof:name":"Europea De Recambios S.a.",
    "wof:placetype":"venue"
},
  "geometry": {"coordinates":[2.2536950111,41.4615898132],"type":"Point"}
}