{
  "type": "Feature",
  "properties": {
    "iso:country":"ES",
    "sg:address":"Navarra-nafarroa Ebde, 7",
    "sg:city":"Iru\u00f1a",
    "sg:orig_category":"Desinfecci\u00d3n, Desinsectaci\u00d3n, Desratizaci\u00d3n",
    "sg:phone":"+34 948 26 30 90",
    "sg:postcode":"31012",
    "sg:province":"Navarra",
    "wof:name":"Alvarez Gomez Alfonso",
    "wof:placetype":"venue"
},
  "geometry": {"coordinates":[-1.6809283495,42.8271217346],"type":"Point"}
}