{
  "type": "Feature",
  "properties": {
    "iso:country":"ES",
    "sg:address":"Calle de Logro\u00d1o, 33",
    "sg:city":"Aranda Duero",
    "sg:orig_category":"Escotaduras, Torneados",
    "sg:phone":"+34 947 50 96 20",
    "sg:postcode":"09400",
    "sg:province":"Burgos",
    "wof:name":"Mecanizados Mar-be S. L.",
    "wof:placetype":"venue"
},
  "geometry": {"coordinates":[-3.7060389519,41.664768219],"type":"Point"}
}