{
  "type": "Feature",
  "properties": {
    "addr:full":"Calle de Jaime Roig, 25 Valencia Valencia 46010",
    "addr:housenumber":"25",
    "addr:postcode":"46010",
    "addr:street":"Calle De Jaime Roig",
    "iso:country":"ES",
    "sg:address":"Calle de Jaime Roig, 25",
    "sg:city":"Valencia",
    "sg:orig_category":"Librer\u00cdas",
    "sg:phone":"+34 962 11 00 71",
    "sg:postcode":"46010",
    "sg:province":"Valencia",
    "wof:name":"Arroyo Sanchez Cid Remedios",
    "wof:placetype":"venue"
},
  "geometry": {"coordinates":[-0.3630498946,39.4834136963],"type":"Point"}
}