{
  "type": "Feature",
  "properties": {
    "addr:full":"Tabaza, S/n Tamon Asturias 33469",
    "addr:postcode":"33469",
    "addr:street":"Tabaza S / N Tamon Asturias",
    "iso:country":"ES",
    "sg:address":"Tabaza, S/n",
    "sg:city":"Tamon",
    "sg:orig_category":"Promotores Constructores",
    "sg:phone":"+34 985 50 50 13",
    "sg:postcode":"33469",
    "sg:province":"Asturias",
    "wof:name":"Dragados S.a.",
    "wof:placetype":"venue"
},
  "geometry": {"coordinates":[-5.8119959831,43.5127182007],"type":"Point"}
}