{
  "type": "Feature",
  "properties": {
    "addr:full":"Avda Alcalde Diaz Saavedra Navarro, 44 Palmas De Gran Canaria Las Palmas 35001",
    "addr:postcode":"35001",
    "addr:street":"Avda Alcalde Diaz Saavedra Navarro 44",
    "iso:country":"ES",
    "sg:address":"Avda Alcalde Diaz Saavedra Navarro, 44",
    "sg:city":"Palmas De Gran Canaria",
    "sg:orig_category":"Refiner\u00cdas De Petr\u00d3leo",
    "sg:phone":"+34 928 31 30 33",
    "sg:postcode":"35001",
    "sg:province":"Las Palmas",
    "wof:name":"Jose Qui\u00d1onez,s.l.",
    "wof:placetype":"venue"
},
  "geometry": {"coordinates":[-15.4124126434,28.0954036713],"type":"Point"}
}