{
  "type": "Feature",
  "properties": {
    "iso:country":"ES",
    "sg:address":"Calle de Fernan Gonzalez, 79",
    "sg:city":"Madrid",
    "sg:orig_category":"Abogados",
    "sg:phone":"+34 914 09 53 28",
    "sg:postcode":"28009",
    "sg:province":"Madrid",
    "wof:name":"Gonzalez Mancha Juan Antonio",
    "wof:placetype":"venue"
},
  "geometry": {"coordinates":[-3.6746048927,40.4160881042],"type":"Point"}
}