{
  "type": "Feature",
  "properties": {
    "iso:country":"ES",
    "sg:address":"Calle de Biar, 26",
    "sg:city":"Onil",
    "sg:orig_category":"Venta Al Preg\u00d3n",
    "sg:phone":"+34 965 56 57 76",
    "sg:postcode":"03430",
    "sg:province":"Alicante",
    "wof:name":"Juan Fernandez Vicente",
    "wof:placetype":"venue"
},
  "geometry": {"coordinates":[-0.6778901815,38.6281890869],"type":"Point"}
}