{
  "type": "Feature",
  "properties": {
    "addr:full":"Plaz Constitucion, 26 S. Fulgencio Alicante 03177",
    "addr:postcode":"03177",
    "addr:street":"Constitucion 26 S. Fulgencio Alicante",
    "iso:country":"ES",
    "sg:address":"Plaz Constitucion, 26",
    "sg:city":"S. Fulgencio",
    "sg:orig_category":"Iglesia Cat\u00d3lica",
    "sg:phone":"+34 966 79 42 63",
    "sg:postcode":"03177",
    "sg:province":"Alicante",
    "wof:name":"Parroquia San Fulgencio",
    "wof:placetype":"venue"
},
  "geometry": {"coordinates":[-0.7383440137,38.1049537659],"type":"Point"}
}