{
  "type": "Feature",
  "properties": {
    "iso:country":"ES",
    "sg:address":"Ptge Doctor Ferran, 10",
    "sg:city":"Rubi",
    "sg:orig_category":"Fabricaci\u00d3n De Jabones, Detergentes Y Lej\u00cdas",
    "sg:phone":"+34 936 97 55 27",
    "sg:postcode":"08191",
    "sg:province":"Barcelona",
    "wof:name":"Miquel Buxaus S.c.p.",
    "wof:placetype":"venue"
},
  "geometry": {"coordinates":[2.0327570438,41.4804420471],"type":"Point"}
}