{
  "type": "Feature",
  "properties": {
    "iso:country":"ES",
    "sg:address":"Calle de Iru\u00d1a, 1 Bis",
    "sg:city":"Bilbao",
    "sg:orig_category":"Fabricaci\u00d3n De Peines Y De Accesorios De Peluquer\u00cda",
    "sg:phone":"+34 944 47 68 53",
    "sg:postcode":"48014",
    "sg:province":"Vizcaya",
    "wof:name":"Hulma Cosmeticos Del Norte, S.l.",
    "wof:placetype":"venue"
},
  "geometry": {"coordinates":[-2.9461190701,43.2686500549],"type":"Point"}
}