{
  "type": "Feature",
  "properties": {
    "iso:country":"ES",
    "sg:address":"Cpjo S. Enrique, S/n",
    "sg:city":"Torremolinos",
    "sg:orig_category":"Art\u00cdculos De Regalo (al Por Menor)",
    "sg:phone":"+34 952 38 71 19",
    "sg:postcode":"29620",
    "sg:province":"M\u00e1laga",
    "wof:name":"Shirdi International S.c.",
    "wof:placetype":"venue"
},
  "geometry": {"coordinates":[-4.4998540878,36.6244087219],"type":"Point"}
}