{
  "type": "Feature",
  "properties": {
    "iso:country":"ES",
    "sg:address":"Calle de Errekatxu, 6",
    "sg:city":"Mungia",
    "sg:classifiers":[
        {
            "category":"Autos & Motor Vehicles",
            "subcategory":"Automobile Sales",
            "type":"Retail Goods"
        }
    ],
    "sg:phone":"+34 946 74 23 35",
    "sg:postcode":"48100",
    "sg:province":"Vizcaya",
    "wof:name":"Auto Eskola Agustin, Agustin Urrutia  Arrizabalaga",
    "wof:placetype":"venue"
},
  "geometry": {"coordinates":[-2.8493490219,43.3551902771],"type":"Point"}
}