{
  "type": "Feature",
  "properties": {
    "iso:country":"ES",
    "sg:address":"Carlos Chaves, S/n",
    "sg:city":"Javea",
    "sg:orig_category":"Ense\u00d1anza: Profesiones Art\u00cdsticas",
    "sg:phone":"+34 965 77 17 69",
    "sg:postcode":"03730",
    "sg:province":"Alicante",
    "wof:name":"Haiku S.l.",
    "wof:placetype":"venue"
},
  "geometry": {"coordinates":[0.1667460054,38.7912406921],"type":"Point"}
}