{
  "type": "Feature",
  "properties": {
    "addr:full":"Calle de Santa Teresa, 8 San Nicolas Murcia 30005",
    "addr:housenumber":"8",
    "addr:postcode":"30005",
    "addr:street":"Calle De Santa Teresa",
    "iso:country":"ES",
    "sg:address":"Calle de Santa Teresa, 8",
    "sg:city":"San Nicolas",
    "sg:orig_category":"Carnicer\u00cdas, Carnicer\u00cdas",
    "sg:phone":"+34 968 28 36 39",
    "sg:postcode":"30005",
    "sg:province":"Murcia",
    "wof:name":"Miguel Botia Sanchez Y Otra C.b.",
    "wof:placetype":"venue"
},
  "geometry": {"coordinates":[-1.1345909834,37.9869995117],"type":"Point"}
}