{
  "type": "Feature",
  "properties": {
    "addr:full":"Calle de Valle Niza, 45 Malaga M\u00e1laga 29196",
    "addr:housenumber":"45",
    "addr:postcode":"29196",
    "addr:street":"Calle De Valle Niza;Ma\u0301Laga",
    "iso:country":"ES",
    "sg:address":"Calle de Valle Niza, 45",
    "sg:city":"Malaga",
    "sg:orig_category":"Fabricaci\u00d3n De Su\u00c9ters Y Chalecos De Punto",
    "sg:phone":"+34 952 24 41 27",
    "sg:postcode":"29196",
    "sg:province":"M\u00e1laga",
    "wof:name":"J.arggido S.l.",
    "wof:placetype":"venue"
},
  "geometry": {"coordinates":[-4.4988331795,36.6974639893],"type":"Point"}
}