{
  "type": "Feature",
  "properties": {
    "iso:country":"ES",
    "sg:address":"Calle de Palencia, 10",
    "sg:city":"Madrid",
    "sg:classifiers":[
        {
            "category":"Banks & Credit Unions",
            "subcategory":"Bureau De Change",
            "type":"Services"
        }
    ],
    "sg:phone":"+34 915 54 97 28",
    "sg:postcode":"28020",
    "sg:province":"Madrid",
    "sg:tags":[
        "organismos",
        "control"
    ],
    "wof:name":"Asociacion Cultural Euroamericana",
    "wof:placetype":"venue"
},
  "geometry": {"coordinates":[-3.7018241882,40.4497833252],"type":"Point"}
}