{
  "type": "Feature",
  "properties": {
    "iso:country":"ES",
    "sg:address":"Avda Sancho El Sabio, 13",
    "sg:city":"Arcos",
    "sg:orig_category":"Comunidades Religiosas",
    "sg:phone":"+34 948 64 01 56",
    "sg:postcode":"31210",
    "sg:province":"Navarra",
    "wof:name":"Congregacion De Las Hijas De La Cruz",
    "wof:placetype":"venue"
},
  "geometry": {"coordinates":[-2.1964919567,42.5676040649],"type":"Point"}
}