{
  "type": "Feature",
  "properties": {
    "iso:country":"ES",
    "sg:address":"Valle Del Puntal, S/n",
    "sg:city":"Padul",
    "sg:orig_category":"Inmobiliaria (agencias)",
    "sg:phone":"+34 958 79 02 62",
    "sg:postcode":"18640",
    "sg:province":"Granada",
    "wof:name":"Francisca Hidalgo Sanchez Y Otros Cdad.",
    "wof:placetype":"venue"
},
  "geometry": {"coordinates":[-3.6222009659,37.0186729431],"type":"Point"}
}