{
  "type": "Feature",
  "properties": {
    "iso:country":"ES",
    "sg:address":"Calle de Alcalde Mu\u00d1oz, 30",
    "sg:city":"Almeria",
    "sg:orig_category":"Confecci\u00d3n De Chales, De Bufandas Y De Pa\u00d1uelos De Vestir",
    "sg:phone":"+34 950 23 62 91",
    "sg:postcode":"04004",
    "sg:province":"Almer\u00eda",
    "wof:name":"Rodriguez Hita Agustin",
    "wof:placetype":"venue"
},
  "geometry": {"coordinates":[-2.4599201679,36.842376709],"type":"Point"}
}