{
  "type": "Feature",
  "properties": {
    "addr:full":"Ctra. Gral. Las Arenas, 26 Puerto Cruz Santa Cruz De Tenerife 38400",
    "addr:housenumber":"26",
    "addr:postcode":"38400",
    "addr:street":"Ctra. Gral. Las Arenas;Puerto Cruz",
    "iso:country":"ES",
    "sg:address":"Ctra. Gral. Las Arenas, 26",
    "sg:city":"Puerto Cruz",
    "sg:orig_category":"Veh\u00cdculos De Ocasi\u00d3n",
    "sg:phone":"+34 922 37 49 57",
    "sg:postcode":"38400",
    "sg:province":"Santa Cruz De Tenerife",
    "wof:name":"Grupo Ojeda De Inversiones S.l.",
    "wof:placetype":"venue"
},
  "geometry": {"coordinates":[-16.5473842621,28.4141807556],"type":"Point"}
}