{
  "type": "Feature",
  "properties": {
    "iso:country":"ES",
    "sg:address":"Pase Sixto Celorrio, 10",
    "sg:city":"Calatayud",
    "sg:orig_category":"Electrodom\u00c9sticos (al Por Menor)",
    "sg:phone":"+34 976 88 30 84",
    "sg:postcode":"50300",
    "sg:province":"Zaragoza",
    "wof:name":"Lacasa Calatayud S.a.",
    "wof:placetype":"venue"
},
  "geometry": {"coordinates":[-1.6408940554,41.3475265503],"type":"Point"}
}