{
  "type": "Feature",
  "properties": {
    "iso:country":"ES",
    "sg:address":"Calle de Villa De Plentzia, 8",
    "sg:city":"Getxo",
    "sg:orig_category":"Molduras, Junquillos, Listones Y Molduras Perforadas",
    "sg:phone":"+34 944 63 31 35",
    "sg:postcode":"48930",
    "sg:province":"Vizcaya",
    "wof:name":"Bar El Tablon (miguel Angel Gamero Delgado)",
    "wof:placetype":"venue"
},
  "geometry": {"coordinates":[-3.0051229,43.3334236145],"type":"Point"}
}