{
  "type": "Feature",
  "properties": {
    "iso:country":"ES",
    "sg:address":"Calle de Eras, 1",
    "sg:city":"Villaviciosa Odon",
    "sg:orig_category":"Arquitectos",
    "sg:phone":"+34 916 16 47 36",
    "sg:postcode":"28670",
    "sg:province":"Madrid",
    "sg:website":"www.inmoastudillo.com",
    "wof:name":"Astudillo Sanz Maria De La Luz",
    "wof:placetype":"venue"
},
  "geometry": {"coordinates":[-3.9956934452,40.4004364014],"type":"Point"}
}