{
  "type": "Feature",
  "properties": {
    "iso:country":"ES",
    "sg:address":"Calle de Mesones, 32",
    "sg:city":"Granada",
    "sg:orig_category":"Zapatos (al Por Menor)",
    "sg:phone":"+34 958 25 25 36",
    "sg:postcode":"18001",
    "sg:province":"Granada",
    "wof:name":"Gonzalez Mari Antonio",
    "wof:placetype":"venue"
},
  "geometry": {"coordinates":[-3.6005280018,37.1750106812],"type":"Point"}
}