{
  "type": "Feature",
  "properties": {
    "iso:country":"ES",
    "sg:address":"Calle de San Antolin, 1",
    "sg:city":"Barakaldo",
    "sg:orig_category":"Asociaciones, Organismos Culturales Y Socioeducativos",
    "sg:phone":"+34 944 37 68 00",
    "sg:postcode":"48901",
    "sg:province":"Vizcaya",
    "wof:name":"Casa Palentina (centro Castellano Leones)",
    "wof:placetype":"venue"
},
  "geometry": {"coordinates":[-2.9894900322,43.2961997986],"type":"Point"}
}