{
  "type": "Feature",
  "properties": {
    "addr:full":"Carrer de Mare De Deu De La Cisa, S/n Mataro Barcelona 08303",
    "addr:housenumber":"s",
    "addr:postcode":"08303",
    "addr:street":"Carrer De Mare De Deu De La Cisa;/ N Mataro Barcelona",
    "iso:country":"ES",
    "sg:address":"Carrer de Mare De Deu De La Cisa, S/n",
    "sg:city":"Mataro",
    "sg:orig_category":"Ahumados Y Salazones",
    "sg:phone":"+34 937 57 09 63",
    "sg:postcode":"08303",
    "sg:province":"Barcelona",
    "wof:name":"Garcia Jimenez Francisco",
    "wof:placetype":"venue"
},
  "geometry": {"coordinates":[2.4233250618,41.5353393555],"type":"Point"}
}