{
  "type": "Feature",
  "properties": {
    "addr:full":"Calle de Luchada (la), 39 Tias Las Palmas 35572",
    "addr:housenumber":"39",
    "addr:postcode":"35572",
    "addr:street":"Calle De Luchada La",
    "iso:country":"ES",
    "sg:address":"Calle de Luchada (la), 39",
    "sg:city":"Tias",
    "sg:orig_category":"Inmobiliaria (agencias)",
    "sg:phone":"+34 928 52 42 69",
    "sg:postcode":"35572",
    "sg:province":"Las Palmas",
    "wof:name":"Gestion Inmobiliaria Tias S.c.p.",
    "wof:placetype":"venue"
},
  "geometry": {"coordinates":[-13.659070015,28.9522476196],"type":"Point"}
}