{
  "type": "Feature",
  "properties": {
    "iso:country":"ES",
    "sg:address":"Calle de Subida Al Mayorazgo, S/n",
    "sg:city":"Santa Cruz De Tenerife",
    "sg:orig_category":"Electricidad: Equipos Industriales, Componentes (fabricaci\u00d3n)",
    "sg:phone":"+34 922 20 07 86",
    "sg:postcode":"38010",
    "sg:province":"Santa Cruz De Tenerife",
    "wof:name":"Comercial Electrica Canarias S.a.",
    "wof:placetype":"venue"
},
  "geometry": {"coordinates":[-16.3302192688,28.4371891022],"type":"Point"}
}