{
  "type": "Feature",
  "properties": {
    "addr:full":"Calle de Silio, 12 Santiponce Sevilla 41970",
    "addr:housenumber":"12",
    "addr:postcode":"41970",
    "addr:street":"Calle De Silio",
    "iso:country":"ES",
    "sg:address":"Calle de Silio, 12",
    "sg:city":"Santiponce",
    "sg:orig_category":"Arquitectos",
    "sg:phone":"+34 955 99 66 64",
    "sg:postcode":"41970",
    "sg:province":"Sevilla",
    "wof:name":"Dominguez Ortega Eusebio",
    "wof:placetype":"venue"
},
  "geometry": {"coordinates":[-6.0412979126,37.4370536804],"type":"Point"}
}