{
  "type": "Feature",
  "properties": {
    "iso:country":"ES",
    "sg:address":"Rond Industria (de La), S/n",
    "sg:city":"Huesca",
    "sg:orig_category":"Maquinaria Para Industrias Diversas",
    "sg:phone":"+34 974 24 24 47",
    "sg:postcode":"22006",
    "sg:province":"Huesca",
    "wof:name":"Talleres Obasca S.l.",
    "wof:placetype":"venue"
},
  "geometry": {"coordinates":[-0.3883090019,42.1444015503],"type":"Point"}
}