{
  "type": "Feature",
  "properties": {
    "iso:country":"ES",
    "sg:address":"Carrer de Consell De Cent, 185",
    "sg:city":"Barcelona",
    "sg:orig_category":"Discotecas Y Salas De Baile",
    "sg:phone":"+34 934 54 18 48",
    "sg:postcode":"08015",
    "sg:province":"Barcelona",
    "wof:name":"Sevinia S.a.",
    "wof:placetype":"venue"
},
  "geometry": {"coordinates":[2.1557250023,41.3837814331],"type":"Point"}
}