{
  "type": "Feature",
  "properties": {
    "addr:full":"Calle de San Juan, 9 Aguadulce Sevilla 41550",
    "addr:housenumber":"9",
    "addr:postcode":"41550",
    "addr:street":"Calle De San Juan",
    "iso:country":"ES",
    "sg:address":"Calle de San Juan, 9",
    "sg:city":"Aguadulce",
    "sg:orig_category":"Formaci\u00d3n Continuada (variada)",
    "sg:phone":"+34 954 81 64 09",
    "sg:postcode":"41550",
    "sg:province":"Sevilla",
    "wof:name":"Asesoria Haro Garcia S.cv.",
    "wof:placetype":"venue"
},
  "geometry": {"coordinates":[-4.9914722443,37.2518730164],"type":"Point"}
}