{
  "type": "Feature",
  "properties": {
    "iso:country":"ES",
    "sg:address":"Carr Ramon Argiles, S/n",
    "sg:city":"Lleida",
    "sg:orig_category":"Art\u00cdculos De Madera (fabricaci\u00d3n Y Al Por Mayor)",
    "sg:phone":"+34 973 22 17 88",
    "sg:postcode":"25005",
    "sg:province":"Lleida",
    "wof:name":"Asociacion Shalom",
    "wof:placetype":"venue"
},
  "geometry": {"coordinates":[0.6396752,41.6268577576],"type":"Point"}
}