{
  "type": "Feature",
  "properties": {
    "iso:country":"ES",
    "sg:address":"Carr Sequia (de La), 16",
    "sg:city":"Villanueva De Castellon",
    "sg:orig_category":"Sindicatos De Trabajadores",
    "sg:phone":"+34 962 45 25 92",
    "sg:postcode":"46270",
    "sg:province":"Valencia",
    "wof:name":"Comissions Obreres Del Pais Valencia",
    "wof:placetype":"venue"
},
  "geometry": {"coordinates":[-0.5138689876,39.077545166],"type":"Point"}
}