{
  "type": "Feature",
  "properties": {
    "iso:country":"ES",
    "sg:address":"Calle de Marquesa Viuda De Aldama (de La), 2",
    "sg:city":"Alcobendas",
    "sg:orig_category":"Perfumer\u00cda (al Por Menor)",
    "sg:phone":"+34 916 51 49 21",
    "sg:postcode":"28100",
    "sg:province":"Madrid",
    "sg:website":"www.marionnaud.es",
    "wof:name":"Marionnaud Perfumeries Iberica S.l.",
    "wof:placetype":"venue"
},
  "geometry": {"coordinates":[-3.633480072,40.5410118103],"type":"Point"}
}