{
  "type": "Feature",
  "properties": {
    "iso:country":"ES",
    "sg:address":"Calle de Panaderos, 39",
    "sg:city":"Talavera Reina",
    "sg:orig_category":"Confecci\u00d3n (fabricaci\u00d3n, Al Por Mayor)",
    "sg:phone":"+34 925 72 00 90",
    "sg:postcode":"45600",
    "sg:province":"Toledo",
    "wof:name":"Confecciones Ancomart S.l.",
    "wof:placetype":"venue"
},
  "geometry": {"coordinates":[-4.8480148315,39.956199646],"type":"Point"}
}