{
  "type": "Feature",
  "properties": {
    "addr:full":"Carrer de Mariano Alvarez De Castro, 25 Granollers Barcelona 08402",
    "addr:housenumber":"25",
    "addr:postcode":"08402",
    "addr:street":"Carrer De Mariano Alvarez De Castro",
    "iso:country":"ES",
    "sg:address":"Carrer de Mariano Alvarez De Castro, 25",
    "sg:city":"Granollers",
    "sg:orig_category":"Delegados, Agentes De Tr\u00c1nsito, Auxiliares De Transporte Internacional",
    "sg:phone":"+34 938 70 02 69",
    "sg:postcode":"08402",
    "sg:province":"Barcelona",
    "wof:name":"Ca\u00f1ellas Escude Elias",
    "wof:placetype":"venue"
},
  "geometry": {"coordinates":[2.2887530327,41.6008262634],"type":"Point"}
}