{
  "type": "Feature",
  "properties": {
    "addr:full":"Carr Colon, 3 Vila Joiosa Alicante 03570",
    "addr:housenumber":"3",
    "addr:postcode":"03570",
    "addr:street":"Carr Colon",
    "iso:country":"ES",
    "sg:address":"Carr Colon, 3",
    "sg:city":"Vila Joiosa",
    "sg:orig_category":"Ropa De Hogar (al Por Menor)",
    "sg:phone":"+34 965 89 42 74",
    "sg:postcode":"03570",
    "sg:province":"Alicante",
    "wof:name":"Asuncion Cardona S.l.",
    "wof:placetype":"venue"
},
  "geometry": {"coordinates":[-0.2326467037,38.5065841675],"type":"Point"}
}