{
  "type": "Feature",
  "properties": {
    "iso:country":"ES",
    "sg:address":"Rua Rof Codina, 1",
    "sg:city":"Monforte De Lemos",
    "sg:orig_category":"Urbanistas",
    "sg:phone":"+34 982 41 63 20",
    "sg:postcode":"27400",
    "sg:province":"Lugo",
    "wof:name":"Arquitectura Decoracion Y Dise\u00f1o S.l.",
    "wof:placetype":"venue"
},
  "geometry": {"coordinates":[-7.51658535,42.5212211609],"type":"Point"}
}