{
  "type": "Feature",
  "properties": {
    "iso:country":"ES",
    "sg:address":"Oikia Auzoa, 59",
    "sg:city":"Oikia",
    "sg:orig_category":"Fabricaci\u00d3n, Instalaci\u00d3n De Armarios",
    "sg:phone":"+34 943 86 27 37",
    "sg:postcode":"20759",
    "sg:province":"Guip\u00f9zcoa",
    "sg:website":"www.kitmar.com",
    "wof:name":"Armarios Kitmar Mobel S.l.",
    "wof:placetype":"venue"
},
  "geometry": {"coordinates":[-2.2343187332,43.2795410156],"type":"Point"}
}