{
  "type": "Feature",
  "properties": {
    "addr:full":"Carrer de Alaba, 4 S. Boi Llobregat Barcelona 08830",
    "addr:housenumber":"4",
    "addr:postcode":"08830",
    "addr:street":"Carrer De Alaba",
    "iso:country":"ES",
    "sg:address":"Carrer de Alaba, 4",
    "sg:city":"S. Boi Llobregat",
    "sg:orig_category":"Ingenier\u00cda, Centros De Estudios (diversos)",
    "sg:phone":"+34 936 30 37 92",
    "sg:postcode":"08830",
    "sg:province":"Barcelona",
    "wof:name":"Stachys S. A.",
    "wof:placetype":"venue"
},
  "geometry": {"coordinates":[2.0415000916,41.3300514221],"type":"Point"}
}