{
  "type": "Feature",
  "properties": {
    "iso:country":"ES",
    "sg:address":"Rond Segovia, 47",
    "sg:city":"Madrid",
    "sg:orig_category":"Mec\u00c1nico Del Autom\u00d3vil",
    "sg:phone":"+34 913 65 03 96",
    "sg:postcode":"28005",
    "sg:province":"Madrid",
    "wof:name":"Garcia Del Rio Manuel",
    "wof:placetype":"venue"
},
  "geometry": {"coordinates":[-3.7173469067,40.4136276245],"type":"Point"}
}