{
  "type": "Feature",
  "properties": {
    "addr:full":"Rosalia De Castro(urb. Montouto), 29 Parque Montouto La Coru\u00f1a 15894",
    "addr:housenumber":"29",
    "addr:postcode":"15894",
    "addr:street":"Rosalia De Castro Urb. Montouto;Corun\u0303A",
    "iso:country":"ES",
    "sg:address":"Rosalia De Castro(urb. Montouto), 29",
    "sg:city":"Parque Montouto",
    "sg:orig_category":"Ingenier\u00cda, Centros De Estudios (diversos)",
    "sg:phone":"+34 981 81 93 57",
    "sg:postcode":"15894",
    "sg:province":"La Coru\u00f1a",
    "wof:name":"Placer Gomez Jose Antonio",
    "wof:placetype":"venue"
},
  "geometry": {"coordinates":[-8.5459394455,42.8326034546],"type":"Point"}
}