{
  "type": "Feature",
  "properties": {
    "iso:country":"ES",
    "sg:address":"Calle de Safona (la), 22",
    "sg:city":"Onda",
    "sg:orig_category":"Piscinas (establecimientos)",
    "sg:phone":"+34 964 77 23 82",
    "sg:postcode":"12200",
    "sg:province":"Castell\u00f3n",
    "wof:name":"Club Natacion Onda",
    "wof:placetype":"venue"
},
  "geometry": {"coordinates":[-0.2617880106,39.9633560181],"type":"Point"}
}