{
  "type": "Feature",
  "properties": {
    "iso:country":"ES",
    "sg:address":"Avda Novelda, 98",
    "sg:city":"Alacant",
    "sg:orig_category":"Materias Pl\u00c1sticas: Productos De Consumo Masivo (fabricaci\u00d3n, Al Por Mayor)",
    "sg:phone":"+34 965 17 11 67",
    "sg:postcode":"03010",
    "sg:province":"Alicante",
    "wof:name":"Sanchez Navarro Enrique Antonio",
    "wof:placetype":"venue"
},
  "geometry": {"coordinates":[-0.4956479967,38.3663635254],"type":"Point"}
}