{
  "type": "Feature",
  "properties": {
    "addr:full":"Carrer de Vall D'aran, 19 Mora Tarragona 43008",
    "addr:housenumber":"19",
    "addr:postcode":"43008",
    "addr:street":"Carrer De Vall D'Aran",
    "iso:country":"ES",
    "sg:address":"Carrer de Vall D'aran, 19",
    "sg:city":"Mora",
    "sg:orig_category":"Arquitectos",
    "sg:phone":"+34 977 65 22 16",
    "sg:postcode":"43008",
    "sg:province":"Tarragona",
    "wof:name":"Manrubia Mirete Aurelio",
    "wof:placetype":"venue"
},
  "geometry": {"coordinates":[0.6394169927,41.0935668945],"type":"Point"}
}