{
  "type": "Feature",
  "properties": {
    "iso:country":"ES",
    "sg:address":"Ctra. Jaen, 4",
    "sg:city":"Albacete",
    "sg:orig_category":"Quincaller\u00cda (al Por Menor)",
    "sg:phone":"+34 967 22 29 00",
    "sg:postcode":"02006",
    "sg:province":"Albacete",
    "wof:name":"Jersan S.l.",
    "wof:placetype":"venue"
},
  "geometry": {"coordinates":[-1.8717600107,38.9945526123],"type":"Point"}
}