{
  "type": "Feature",
  "properties": {
    "iso:country":"ES",
    "sg:address":"Calle de Felipe Ii, 2",
    "sg:city":"Valladolid",
    "sg:orig_category":"M\u00c9dicos: Naturistas",
    "sg:phone":"+34 983 30 09 27",
    "sg:postcode":"47003",
    "sg:province":"Valladolid",
    "wof:name":"Ortiz Lobete Juan Francisco",
    "wof:placetype":"venue"
},
  "geometry": {"coordinates":[-4.7258481979,41.6542663574],"type":"Point"}
}