{
  "type": "Feature",
  "properties": {
    "addr:full":"Calle de Bolta\u00d1a, 68 Madrid Madrid 28022",
    "addr:housenumber":"68",
    "addr:postcode":"madrid;28022",
    "addr:street":"Calle De Boltan\u0303A",
    "iso:country":"ES",
    "sg:address":"Calle de Bolta\u00d1a, 68",
    "sg:city":"Madrid",
    "sg:orig_category":"Bancos",
    "sg:phone":"+34 917 41 27 23",
    "sg:postcode":"28022",
    "sg:province":"Madrid",
    "sg:website":"www.gruposantander.es",
    "wof:name":"Bt Espa\u00d1a Compa\u00d1ia De Servicios Globales De Telecomunicaciones S.a.u.",
    "wof:placetype":"venue"
},
  "geometry": {"coordinates":[-3.6119179726,40.4461288452],"type":"Point"}
}