{
  "type": "Feature",
  "properties": {
    "addr:full":"Pase Habana, 107 Madrid Madrid 28036",
    "addr:housenumber":"107",
    "addr:postcode":"madrid;28036",
    "iso:country":"ES",
    "sg:address":"Pase Habana, 107",
    "sg:city":"Madrid",
    "sg:orig_category":"Farmacias",
    "sg:phone":"+34 913 59 14 14",
    "sg:postcode":"28036",
    "sg:province":"Madrid",
    "wof:name":"Barahona Guemes Carmen",
    "wof:placetype":"venue"
},
  "geometry": {"coordinates":[-3.6816871166,40.4591293335],"type":"Point"}
}