{
  "type": "Feature",
  "properties": {
    "iso:country":"ES",
    "sg:address":"Calle de Molino De Viento, S/n",
    "sg:city":"Villamartin",
    "sg:orig_category":"Marroquiner\u00cda (confecci\u00d3n)",
    "sg:phone":"+34 956 73 10 87",
    "sg:postcode":"11650",
    "sg:province":"C\u00e1diz",
    "wof:name":"Marroquineria Mocabi S.l.",
    "wof:placetype":"venue"
},
  "geometry": {"coordinates":[-5.6003570557,36.868183136],"type":"Point"}
}