{
  "type": "Feature",
  "properties": {
    "addr:full":"Avda Cosculluela, 10 Ejea De Los Caballeros Zaragoza 50600",
    "addr:housenumber":"10",
    "addr:postcode":"50600",
    "addr:street":"Avda Cosculluela",
    "iso:country":"ES",
    "sg:address":"Avda Cosculluela, 10",
    "sg:city":"Ejea De Los Caballeros",
    "sg:orig_category":"Contenedores (mercanc\u00cdas)",
    "sg:phone":"+34 976 66 12 86",
    "sg:postcode":"50600",
    "sg:province":"Zaragoza",
    "wof:name":"Dieste Navarro Javier",
    "wof:placetype":"venue"
},
  "geometry": {"coordinates":[-1.1384710073,42.1244850159],"type":"Point"}
}