{
  "type": "Feature",
  "properties": {
    "addr:full":"Cra Espinel, 25 Ronda M\u00e1laga 29400",
    "addr:postcode":"29400",
    "addr:street":"Ronda Ma\u0301Laga",
    "iso:country":"ES",
    "sg:address":"Cra Espinel, 25",
    "sg:city":"Ronda",
    "sg:orig_category":"Ropa Para Se\u00d1oras Y Caballeros (al Por Menor)",
    "sg:phone":"+34 952 87 27 83",
    "sg:postcode":"29400",
    "sg:province":"M\u00e1laga",
    "wof:name":"Garcia Guzman Juan Jose",
    "wof:placetype":"venue"
},
  "geometry": {"coordinates":[-5.1648159027,36.7431221008],"type":"Point"}
}