{
  "type": "Feature",
  "properties": {
    "iso:country":"ES",
    "sg:address":"Miguel Astrain, 13",
    "sg:city":"Iru\u00f1a",
    "sg:orig_category":"Molduras, Junquillos, Listones Y Molduras Perforadas",
    "sg:phone":"+34 948 24 45 69",
    "sg:postcode":"31006",
    "sg:province":"Navarra",
    "wof:name":"Perez Recarte Florencio",
    "wof:placetype":"venue"
},
  "geometry": {"coordinates":[-1.6442209482,42.8011817932],"type":"Point"}
}