{
  "type": "Feature",
  "properties": {
    "iso:country":"ES",
    "sg:address":"Av Reis Catolics, 7",
    "sg:city":"Olot",
    "sg:orig_category":"Fabricaci\u00d3n De Su\u00c9ters Y Chalecos De Punto",
    "sg:phone":"+34 972 26 01 72",
    "sg:postcode":"17800",
    "sg:province":"Girona",
    "wof:name":"Selecciones Moda S.a.",
    "wof:placetype":"venue"
},
  "geometry": {"coordinates":[2.4826779366,42.1809272766],"type":"Point"}
}