{
  "type": "Feature",
  "properties": {
    "addr:full":"Praz Fernando O Catolico, S/n Vigo Pontevedra 36204",
    "addr:housenumber":"s / n",
    "addr:postcode":"36204",
    "addr:street":"Praz Fernando O Catolico",
    "iso:country":"ES",
    "sg:address":"Praz Fernando O Catolico, S/n",
    "sg:city":"Vigo",
    "sg:orig_category":"Aparcamientos (infraestructuras, Accesorios)",
    "sg:phone":"+34 986 41 57 67",
    "sg:postcode":"36204",
    "sg:province":"Pontevedra",
    "wof:name":"Conycase S.l.",
    "wof:placetype":"venue"
},
  "geometry": {"coordinates":[-8.7117185593,42.2325286865],"type":"Point"}
}