{
  "type": "Feature",
  "properties": {
    "iso:country":"ES",
    "sg:address":"Calle de Francisco Guzman, 49",
    "sg:city":"Illescas",
    "sg:orig_category":"Ebanister\u00cda",
    "sg:phone":"+34 925 54 00 07",
    "sg:postcode":"45200",
    "sg:province":"Toledo",
    "wof:name":"Caro Rodriguez Antonio",
    "wof:placetype":"venue"
},
  "geometry": {"coordinates":[-3.8457589149,40.12474823],"type":"Point"}
}