{
  "type": "Feature",
  "properties": {
    "iso:country":"ES",
    "sg:address":"Pase Juan Xxiii, 46",
    "sg:city":"Madrid",
    "sg:orig_category":"Arquitectos",
    "sg:phone":"+34 915 35 82 28",
    "sg:postcode":"28040",
    "sg:province":"Madrid",
    "wof:name":"Martinez Trujillo Vicente",
    "wof:placetype":"venue"
},
  "geometry": {"coordinates":[-3.7130839825,40.4504547119],"type":"Point"}
}