{
  "type": "Feature",
  "properties": {
    "iso:country":"ES",
    "sg:address":"Calle de Victoria, 98",
    "sg:city":"Malaga",
    "sg:orig_category":"Ingeniero",
    "sg:phone":"+34 952 26 43 34",
    "sg:postcode":"29012",
    "sg:province":"M\u00e1laga",
    "wof:name":"Oliva Gomez Pedro",
    "wof:placetype":"venue"
},
  "geometry": {"coordinates":[-4.4141659737,36.7261810303],"type":"Point"}
}