{
  "type": "Feature",
  "properties": {
    "addr:full":"Barr Eitua, 68 Eitua Vizcaya 48240",
    "addr:housenumber":"68",
    "addr:postcode":"48240",
    "addr:street":"Eitua",
    "iso:country":"ES",
    "sg:address":"Barr Eitua, 68",
    "sg:city":"Eitua",
    "sg:orig_category":"Maquinaria Para Industrias Diversas",
    "sg:phone":"+34 946 82 45 50",
    "sg:postcode":"48240",
    "sg:province":"Vizcaya",
    "wof:name":"Alkimax S.l.",
    "wof:placetype":"venue"
},
  "geometry": {"coordinates":[-2.5865347385,43.1676864624],"type":"Point"}
}