{
  "type": "Feature",
  "properties": {
    "iso:country":"ES",
    "sg:address":"Calvo Sotelo, S/n",
    "sg:city":"Covelo",
    "sg:orig_category":"Iglesia Cat\u00d3lica",
    "sg:phone":"+34 986 65 02 27",
    "sg:postcode":"36872",
    "sg:province":"Pontevedra",
    "wof:name":"Parroquia Santiago De Covelo",
    "wof:placetype":"venue"
},
  "geometry": {"coordinates":[-8.3823957443,42.2239990234],"type":"Point"}
}