{
  "type": "Feature",
  "properties": {
    "addr:full":"Calle de Pedro Perez Fernandez, 17 Sevilla Sevilla 41011",
    "addr:housenumber":"17",
    "addr:postcode":"41011",
    "addr:street":"Calle De Pedro Perez Fernandez",
    "iso:country":"ES",
    "sg:address":"Calle de Pedro Perez Fernandez, 17",
    "sg:city":"Sevilla",
    "sg:orig_category":"Bisuter\u00cda, Joyer\u00cda, Relojer\u00cda (al Por Menor)",
    "sg:phone":"+34 954 27 05 66",
    "sg:postcode":"41011",
    "sg:province":"Sevilla",
    "wof:name":"Comercial Orogold S.l.",
    "wof:placetype":"venue"
},
  "geometry": {"coordinates":[-6.0011591911,37.3754501343],"type":"Point"}
}