{
  "type": "Feature",
  "properties": {
    "iso:country":"ES",
    "sg:address":"Calle de Capitan Haya, 24",
    "sg:city":"Madrid",
    "sg:orig_category":"Bancos",
    "sg:phone":"+34 915 98 06 00",
    "sg:postcode":"28020",
    "sg:province":"Madrid",
    "wof:name":"Banco Espa\u00f1ol De Credito S.a.",
    "wof:placetype":"venue"
},
  "geometry": {"coordinates":[-3.6918408871,40.4589424133],"type":"Point"}
}