{
  "type": "Feature",
  "properties": {
    "iso:country":"ES",
    "sg:address":"Calle de Canongia (la), 21",
    "sg:city":"Hontoria",
    "sg:orig_category":"Alimentaci\u00d3n General (al Por Menor)",
    "sg:phone":"+34 921 44 00 12",
    "sg:postcode":"40195",
    "sg:province":"Segovia",
    "wof:name":"Martin Martin Maria Cruz",
    "wof:placetype":"venue"
},
  "geometry": {"coordinates":[-4.1242012978,40.9071350098],"type":"Point"}
}