{
  "type": "Feature",
  "properties": {
    "iso:country":"ES",
    "sg:address":"Cami Mollons (dels), 25",
    "sg:city":"Alaquas",
    "sg:orig_category":"Albergues",
    "sg:phone":"+34 961 50 89 38",
    "sg:postcode":"46970",
    "sg:province":"Valencia",
    "sg:website":"www.sierradepadelma.com",
    "wof:name":"Sierra De Padelma Sl",
    "wof:placetype":"venue"
},
  "geometry": {"coordinates":[-0.4668590128,39.4477310181],"type":"Point"}
}