{
  "type": "Feature",
  "properties": {
    "addr:full":"Calle de Carreteros, 43 Santa Pola Alicante 03130",
    "addr:housenumber":"43",
    "addr:postcode":"03130",
    "addr:street":"Calle De Carreteros",
    "iso:country":"ES",
    "sg:address":"Calle de Carreteros, 43",
    "sg:city":"Santa Pola",
    "sg:orig_category":"Plomeros",
    "sg:phone":"+34 966 69 25 68",
    "sg:postcode":"03130",
    "sg:province":"Alicante",
    "wof:name":"Franvi C.b.",
    "wof:placetype":"venue"
},
  "geometry": {"coordinates":[-0.5576227903,38.196472168],"type":"Point"}
}