{
  "type": "Feature",
  "properties": {
    "iso:country":"ES",
    "sg:address":"Calle de Diego Betancor Suarez, 2",
    "sg:city":"Palmas De Gran Canaria",
    "sg:orig_category":"Molduras, Junquillos, Listones Y Molduras Perforadas",
    "sg:phone":"+34 928 42 83 72",
    "sg:postcode":"35012",
    "sg:province":"Las Palmas",
    "wof:name":"Automaticos Lantigua S.l.",
    "wof:placetype":"venue"
},
  "geometry": {"coordinates":[-15.4458303452,28.1072177887],"type":"Point"}
}