{
  "type": "Feature",
  "properties": {
    "iso:country":"ES",
    "sg:address":"Carrer de Marina, 23",
    "sg:city":"Barcelona",
    "sg:orig_category":"Asesor\u00cdas Y Estudios Financieros",
    "sg:phone":"+34 932 21 89 66",
    "sg:postcode":"08005",
    "sg:province":"Barcelona",
    "wof:name":"Hernandez Gomez Manuel",
    "wof:placetype":"venue"
},
  "geometry": {"coordinates":[2.1956028938,41.3880233765],"type":"Point"}
}