{
  "type": "Feature",
  "properties": {
    "addr:full":"Cost Mirador, Des - Serpentona, S/n Serpentona Islas Baleares 07750",
    "addr:housenumber":"s",
    "addr:postcode":"07750",
    "addr:street":"/ N",
    "iso:country":"ES",
    "sg:address":"Cost Mirador, Des - Serpentona, S/n",
    "sg:city":"Serpentona",
    "sg:orig_category":"Supermercados Y Hipermercados",
    "sg:phone":"+34 971 15 47 15",
    "sg:postcode":"07750",
    "sg:province":"Islas Baleares",
    "wof:name":"Supermercados Bosch Taltavull S.l.",
    "wof:placetype":"venue"
},
  "geometry": {"coordinates":[4.0079188347,39.9823875427],"type":"Point"}
}