{
  "type": "Feature",
  "properties": {
    "iso:country":"ES",
    "sg:address":"Calle de Fernando El Catolico, 11",
    "sg:city":"Alcala Real",
    "sg:orig_category":"Bisuter\u00cda, Joyer\u00cda, Relojer\u00cda (al Por Menor)",
    "sg:phone":"+34 953 58 47 52",
    "sg:postcode":"23680",
    "sg:province":"Ja\u00e9n",
    "wof:name":"Julio Gallardo S.l.",
    "wof:placetype":"venue"
},
  "geometry": {"coordinates":[-3.921423912,37.4600524902],"type":"Point"}
}