{
  "type": "Feature",
  "properties": {
    "iso:country":"ES",
    "sg:address":"Calle de San Blas, 3",
    "sg:city":"Olivenza",
    "sg:orig_category":"Reposter\u00cdas",
    "sg:phone":"+34 924 49 00 18",
    "sg:postcode":"06100",
    "sg:province":"Badajoz",
    "wof:name":"Panaderia Artesana Piquer E Hijos S.l.",
    "wof:placetype":"venue"
},
  "geometry": {"coordinates":[-7.0983867645,38.6835136414],"type":"Point"}
}