{
  "type": "Feature",
  "properties": {
    "iso:country":"ES",
    "sg:address":"Estudios De Gramatica, 48",
    "sg:city":"Estella",
    "sg:orig_category":"Molduras, Junquillos, Listones Y Molduras Perforadas",
    "sg:phone":"+34 948 55 46 49",
    "sg:postcode":"31200",
    "sg:province":"Navarra",
    "wof:name":"Garcia Anaya Manuel",
    "wof:placetype":"venue"
},
  "geometry": {"coordinates":[-2.029558897,42.6720581055],"type":"Point"}
}