{
  "type": "Feature",
  "properties": {
    "iso:country":"ES",
    "sg:address":"Avda Capiscol, 20",
    "sg:city":"Capiscol",
    "sg:orig_category":"Psicoanalistas",
    "sg:phone":"+34 965 94 17 68",
    "sg:postcode":"03550",
    "sg:province":"Alicante",
    "wof:name":"Ander-egg Zamboni Javier",
    "wof:placetype":"venue"
},
  "geometry": {"coordinates":[-0.4810059965,38.3452033997],"type":"Point"}
}