{
  "type": "Feature",
  "properties": {
    "addr:full":"Calle de Pablo Sarasate, 9 Tudela Navarra 31500",
    "addr:housenumber":"9",
    "addr:postcode":"31500",
    "addr:street":"Calle De Pablo Sarasate",
    "iso:country":"ES",
    "sg:address":"Calle de Pablo Sarasate, 9",
    "sg:city":"Tudela",
    "sg:orig_category":"Psicoterapeutas",
    "sg:phone":"+34 948 40 30 73",
    "sg:postcode":"31500",
    "sg:province":"Navarra",
    "wof:name":"Gil Tejero Jose Antonio",
    "wof:placetype":"venue"
},
  "geometry": {"coordinates":[-1.6031899452,42.060218811],"type":"Point"}
}