{
  "type": "Feature",
  "properties": {
    "addr:full":"Carrer de Cardener, 22 Barcelona Barcelona 08024",
    "addr:housenumber":"22",
    "addr:postcode":"08024",
    "addr:street":"Carrer De Cardener",
    "iso:country":"ES",
    "sg:address":"Carrer de Cardener, 22",
    "sg:city":"Barcelona",
    "sg:orig_category":"Comercio, Reparaci\u00d3n De Motocicletas, Bicicletas Y Piezas Sueltas",
    "sg:phone":"+34 932 19 22 12",
    "sg:postcode":"08024",
    "sg:province":"Barcelona",
    "wof:name":"Comercial De Componentes Para Motocicleta S.a.",
    "wof:placetype":"venue"
},
  "geometry": {"coordinates":[2.1551349163,41.4089012146],"type":"Point"}
}