{
  "type": "Feature",
  "properties": {
    "addr:full":"Carr Botanico Cavanilles, 16 Alboraya Valencia 46120",
    "addr:housenumber":"16",
    "addr:postcode":"46120",
    "addr:street":"Carr Botanico Cavanilles",
    "iso:country":"ES",
    "sg:address":"Carr Botanico Cavanilles, 16",
    "sg:city":"Alboraya",
    "sg:orig_category":"Cajas De Ahorro",
    "sg:phone":"+34 961 86 15 60",
    "sg:postcode":"46120",
    "sg:province":"Valencia",
    "sg:website":"www.caixacatalunya.es",
    "wof:name":"Caixa D'estalvis De Catalunya",
    "wof:placetype":"venue"
},
  "geometry": {"coordinates":[-0.3405140042,39.4990692139],"type":"Point"}
}