{
  "type": "Feature",
  "properties": {
    "iso:country":"ES",
    "sg:address":"Calle de San Jose, 52",
    "sg:city":"Cantillana",
    "sg:orig_category":"Ense\u00d1anza, Formaci\u00d3n Profesional: Aprendizaje",
    "sg:phone":"+34 955 73 11 90",
    "sg:postcode":"41320",
    "sg:province":"Sevilla",
    "wof:name":"Servicio Andaluz De Empleo",
    "wof:placetype":"venue"
},
  "geometry": {"coordinates":[-5.8238391876,37.6076431274],"type":"Point"}
}