{
  "type": "Feature",
  "properties": {
    "addr:full":"Plz. Puerta Hierro, 1 Sig\u00fcenza Guadalajara 19250",
    "addr:housenumber":"1",
    "addr:postcode":"19250",
    "addr:street":"Hierro",
    "iso:country":"ES",
    "sg:address":"Plz. Puerta Hierro, 1",
    "sg:city":"Sig\u00fcenza",
    "sg:orig_category":"Bares, Piano",
    "sg:phone":"+34 949 39 32 01",
    "sg:postcode":"19250",
    "sg:province":"Guadalajara",
    "wof:name":"Ranz Martinez Jose Luis",
    "wof:placetype":"venue"
},
  "geometry": {"coordinates":[-2.6444160938,41.0686836243],"type":"Point"}
}