{
  "type": "Feature",
  "properties": {
    "iso:country":"ES",
    "sg:address":"Calle de San Sebastian (de), 6",
    "sg:city":"Pinto",
    "sg:orig_category":"Carnicer\u00cdas, Carnicer\u00cdas",
    "sg:phone":"+34 916 92 22 71",
    "sg:postcode":"28320",
    "sg:province":"Madrid",
    "wof:name":"Herrera Jerez Luis",
    "wof:placetype":"venue"
},
  "geometry": {"coordinates":[-3.6995511055,40.2460517883],"type":"Point"}
}