{
  "type": "Feature",
  "properties": {
    "iso:country":"ES",
    "sg:address":"Calle de Fernando El Catolico, 58",
    "sg:city":"Madrid",
    "sg:orig_category":"Abogados",
    "sg:phone":"+34 915 49 38 37",
    "sg:postcode":"28015",
    "sg:province":"Madrid",
    "wof:name":"Rodriguez Martin Maria De Los Angeles",
    "wof:placetype":"venue"
},
  "geometry": {"coordinates":[-3.713727951,40.4344329834],"type":"Point"}
}