{
  "type": "Feature",
  "properties": {
    "iso:country":"ES",
    "sg:address":"Calle de I\u00d1aki Deuna, 39",
    "sg:city":"Ondarroa",
    "sg:orig_category":"Artes Gr\u00c1ficas, Artes Pl\u00c1sticas (curso)",
    "sg:phone":"+34 946 83 41 43",
    "sg:postcode":"48700",
    "sg:province":"Vizcaya",
    "wof:name":"Caballero Cabanillas Andoni Y Gonzalez Aranbarri Mirennaya S.c.",
    "wof:placetype":"venue"
},
  "geometry": {"coordinates":[-2.4284629822,43.3209533691],"type":"Point"}
}