{
  "type": "Feature",
  "properties": {
    "addr:full":"Pg Vara De Rey, 17 Eivissa Islas Baleares 07800",
    "addr:housenumber":"17",
    "addr:postcode":"07800",
    "addr:street":"Pg Vara De Rey",
    "iso:country":"ES",
    "sg:address":"Pg Vara De Rey, 17",
    "sg:city":"Eivissa",
    "sg:orig_category":"Armas Y Municiones (fabricaci\u00d3n, Al Por Mayor)",
    "sg:phone":"+34 971 30 05 89",
    "sg:postcode":"07800",
    "sg:province":"Islas Baleares",
    "wof:name":"Balanzat Planells Jose",
    "wof:placetype":"venue"
},
  "geometry": {"coordinates":[1.4328039885,38.9088859558],"type":"Point"}
}