{
  "type": "Feature",
  "properties": {
    "iso:country":"ES",
    "sg:address":"Calle de Burruezo, 5",
    "sg:city":"San Nicolas",
    "sg:orig_category":"Arquitectos",
    "sg:phone":"+34 968 27 44 38",
    "sg:postcode":"30005",
    "sg:province":"Murcia",
    "wof:name":"Edar Arquitectura S.l.",
    "wof:placetype":"venue"
},
  "geometry": {"coordinates":[-1.7970391512,37.9042510986],"type":"Point"}
}