{
  "type": "Feature",
  "properties": {
    "addr:full":"Carrer de Sant Josep, 17 Balsareny Barcelona 08660",
    "addr:housenumber":"17",
    "addr:postcode":"08660",
    "addr:street":"Carrer De Sant Josep",
    "iso:country":"ES",
    "sg:address":"Carrer de Sant Josep, 17",
    "sg:city":"Balsareny",
    "sg:orig_category":"Pintura Industrial (trabajos De)",
    "sg:phone":"+34 938 39 64 79",
    "sg:postcode":"08660",
    "sg:province":"Barcelona",
    "wof:name":"Lackstuc S.l.",
    "wof:placetype":"venue"
},
  "geometry": {"coordinates":[1.8728870153,41.863822937],"type":"Point"}
}