{
  "type": "Feature",
  "properties": {
    "iso:country":"ES",
    "sg:address":"Calle de Pedro De Alvarado, 7",
    "sg:city":"Malaga",
    "sg:orig_category":"Arquitectos",
    "sg:phone":"+34 952 29 08 88",
    "sg:postcode":"29018",
    "sg:province":"M\u00e1laga",
    "wof:name":"Lopez Fernandez Antonio",
    "wof:placetype":"venue"
},
  "geometry": {"coordinates":[-4.3744130135,36.7264938354],"type":"Point"}
}