{
  "type": "Feature",
  "properties": {
    "iso:country":"ES",
    "sg:address":"Alameda, 38",
    "sg:city":"Antequera",
    "sg:orig_category":"Sociedades, Compa\u00d1\u00cdas Aseguradoras",
    "sg:phone":"+34 952 84 62 87",
    "sg:postcode":"29200",
    "sg:province":"M\u00e1laga",
    "wof:name":"Preventiva S.a.",
    "wof:placetype":"venue"
},
  "geometry": {"coordinates":[-4.5636138916,37.0203018188],"type":"Point"}
}