{
  "type": "Feature",
  "properties": {
    "iso:country":"ES",
    "sg:address":"Fatima, 4",
    "sg:city":"Pinoso",
    "sg:orig_category":"Agencias De Viajes",
    "sg:phone":"+34 966 96 60 45",
    "sg:postcode":"03650",
    "sg:province":"Alicante",
    "wof:name":"Vidal Fernandez Pilar",
    "wof:placetype":"venue"
},
  "geometry": {"coordinates":[-1.0394539833,38.3975219727],"type":"Point"}
}