{
  "type": "Feature",
  "properties": {
    "addr:full":"Pase Salut, 39 Badalona Barcelona 08914",
    "addr:housenumber":"39",
    "addr:postcode":"08914",
    "iso:country":"ES",
    "sg:address":"Pase Salut, 39",
    "sg:city":"Badalona",
    "sg:orig_category":"Confiter\u00cdas, Chocolater\u00cdas (al Por Menor)",
    "sg:phone":"+34 933 83 73 56",
    "sg:postcode":"08914",
    "sg:province":"Barcelona",
    "wof:name":"La Bruixa Pirula S. A.",
    "wof:placetype":"venue"
},
  "geometry": {"coordinates":[2.2272648811,41.4405288696],"type":"Point"}
}