{
  "type": "Feature",
  "properties": {
    "addr:full":"Carrer de Muntaner, 376 Barcelona Barcelona 08006",
    "addr:housenumber":"376",
    "addr:postcode":"08006",
    "addr:street":"Carrer De Muntaner",
    "iso:country":"ES",
    "sg:address":"Carrer de Muntaner, 376",
    "sg:city":"Barcelona",
    "sg:orig_category":"Inmobiliaria (agencias)",
    "sg:phone":"+34 932 18 61 58",
    "sg:postcode":"08006",
    "sg:province":"Barcelona",
    "wof:name":"Ventiberica Asociados S. A.",
    "wof:placetype":"venue"
},
  "geometry": {"coordinates":[2.1427309513,41.3994216919],"type":"Point"}
}