{
  "type": "Feature",
  "properties": {
    "iso:country":"ES",
    "sg:address":"Calle de Doctor Araez Pacheco, 2",
    "sg:city":"Almeria",
    "sg:orig_category":"Arquitectos",
    "sg:phone":"+34 950 24 37 55",
    "sg:postcode":"04004",
    "sg:province":"Almer\u00eda",
    "wof:name":"Ordaz Rebollar Jose Antonio",
    "wof:placetype":"venue"
},
  "geometry": {"coordinates":[-2.4598927498,36.8346061707],"type":"Point"}
}