{
  "type": "Feature",
  "properties": {
    "iso:country":"ES",
    "sg:address":"Calle de Cordoba, Km. 0431,0",
    "sg:city":"Atarfe",
    "sg:orig_category":"Hoteles",
    "sg:phone":"+34 958 43 41 06",
    "sg:postcode":"18230",
    "sg:province":"Granada",
    "wof:name":"Meson Bar El Flamenco S.l.",
    "wof:placetype":"venue"
},
  "geometry": {"coordinates":[-3.6886684895,37.2209014893],"type":"Point"}
}