{
  "type": "Feature",
  "properties": {
    "addr:full":"Calle de Valle Inclan, 4 Cari\u00f1o La Coru\u00f1a 15360",
    "addr:housenumber":"4",
    "addr:postcode":"15360",
    "addr:street":"Calle De Valle Inclan;La Corun\u0303A",
    "iso:country":"ES",
    "sg:address":"Calle de Valle Inclan, 4",
    "sg:city":"Cari\u00f1o",
    "sg:orig_category":"Plomeros",
    "sg:phone":"+34 981 40 51 65",
    "sg:postcode":"15360",
    "sg:province":"La Coru\u00f1a",
    "wof:name":"Montajes Barcia S.l.u",
    "wof:placetype":"venue"
},
  "geometry": {"coordinates":[-7.8749351501,43.7366905212],"type":"Point"}
}