{
  "type": "Feature",
  "properties": {
    "addr:full":"Pl. Jose Antonio, 6 Salas Asturias 33860",
    "addr:housenumber":"6",
    "addr:postcode":"33860",
    "addr:street":"Jose Antonio",
    "iso:country":"ES",
    "sg:address":"Pl. Jose Antonio, 6",
    "sg:city":"Salas",
    "sg:orig_category":"Negocio De Materiales De Construcci\u00d3n",
    "sg:phone":"+34 985 83 00 52",
    "sg:postcode":"33860",
    "sg:province":"Asturias",
    "wof:name":"Almacenes Casa Javier Sl",
    "wof:placetype":"venue"
},
  "geometry": {"coordinates":[-6.2694606781,43.4179077148],"type":"Point"}
}