{
  "type": "Feature",
  "properties": {
    "iso:country":"ES",
    "sg:address":"Cami Vileta (la), 130",
    "sg:city":"Vileta",
    "sg:orig_category":"Laboratorios Y Trabajos De Fotograf\u00cda, V\u00cddeo Y Cine",
    "sg:phone":"+34 971 79 89 96",
    "sg:postcode":"07011",
    "sg:province":"Islas Baleares",
    "wof:name":"Caldentey Sanchez Bernardo",
    "wof:placetype":"venue"
},
  "geometry": {"coordinates":[2.6198680401,39.5934906006],"type":"Point"}
}