{
  "type": "Feature",
  "properties": {
    "addr:full":"Carrer de Permanyer, 298 Sabadell Barcelona 08205",
    "addr:housenumber":"298",
    "addr:postcode":"08205",
    "addr:street":"Carrer De Permanyer",
    "iso:country":"ES",
    "sg:address":"Carrer de Permanyer, 298",
    "sg:city":"Sabadell",
    "sg:orig_category":"Otros Trabajos De Limpieza Y Mantenimiento (extracci\u00d3n De Polvo, Recogida De Amianto Y Desespumado)",
    "sg:phone":"+34 937 11 57 03",
    "sg:postcode":"08205",
    "sg:province":"Barcelona",
    "wof:name":"Mecsan Mantenimiento S.l.",
    "wof:placetype":"venue"
},
  "geometry": {"coordinates":[2.1020510197,41.5351600647],"type":"Point"}
}