{
  "type": "Feature",
  "properties": {
    "iso:country":"ES",
    "sg:address":"Calle de Ca\u00d1as (las), 7",
    "sg:city":"Logro\u00f1o",
    "sg:orig_category":"Pintura, Barniz, Productos Asimilables (fabricaci\u00d3n, Al Por Mayor)",
    "sg:phone":"+34 941 25 16 50",
    "sg:postcode":"26006",
    "sg:province":"La Rioja",
    "wof:name":"Industrias Quimicas Ilbasol S.l.",
    "wof:placetype":"venue"
},
  "geometry": {"coordinates":[-2.4126567841,42.4782714844],"type":"Point"}
}