{
  "type": "Feature",
  "properties": {
    "iso:country":"ES",
    "sg:address":"Pg Bonanova, 54",
    "sg:city":"Barcelona",
    "sg:orig_category":"Doctores En Medicina",
    "sg:phone":"+34 932 12 60 70",
    "sg:postcode":"08017",
    "sg:province":"Barcelona",
    "wof:name":"Euroayca S.l.",
    "wof:placetype":"venue"
},
  "geometry": {"coordinates":[2.127612114,41.4035491943],"type":"Point"}
}