{
  "type": "Feature",
  "properties": {
    "iso:country":"ES",
    "sg:address":"Calle de Perez Vengut, 1",
    "sg:city":"Alacant",
    "sg:orig_category":"Electricidad: Instaladores",
    "sg:phone":"+34 965 25 07 88",
    "sg:postcode":"03010",
    "sg:province":"Alicante",
    "wof:name":"Instalaciones Y Mantenimientos Eloy, S.l.",
    "wof:placetype":"venue"
},
  "geometry": {"coordinates":[-0.4839319885,38.3615531921],"type":"Point"}
}