{
  "type": "Feature",
  "properties": {
    "addr:full":"Carr Gasco (dels), 6 Gandia Valencia 46700",
    "addr:housenumber":"6",
    "addr:postcode":"46700",
    "addr:street":"Carr Gasco Dels;Valencia",
    "iso:country":"ES",
    "sg:address":"Carr Gasco (dels), 6",
    "sg:city":"Gandia",
    "sg:orig_category":"Entrega Y Recogida (servicios)",
    "sg:phone":"+34 962 96 04 15",
    "sg:postcode":"46700",
    "sg:province":"Valencia",
    "wof:name":"Sipal Alimentaria S.l.",
    "wof:placetype":"venue"
},
  "geometry": {"coordinates":[-0.1913339943,38.960735321],"type":"Point"}
}