{
  "type": "Feature",
  "properties": {
    "addr:full":"San Juan Kalea, 3 Eibar Guip\u00f9zcoa 20600",
    "addr:housenumber":"3",
    "addr:postcode":"20600",
    "addr:street":"San Juan Kalea;Guipu\u0300Zcoa",
    "iso:country":"ES",
    "sg:address":"San Juan Kalea, 3",
    "sg:city":"Eibar",
    "sg:orig_category":"Caf\u00c9s, Bares, Cervecer\u00cdas",
    "sg:phone":"+34 943 20 61 43",
    "sg:postcode":"20600",
    "sg:province":"Guip\u00f9zcoa",
    "wof:name":"Bono Burgos Araceli",
    "wof:placetype":"venue"
},
  "geometry": {"coordinates":[-2.4732489586,43.184841156],"type":"Point"}
}