{
  "type": "Feature",
  "properties": {
    "iso:country":"ES",
    "sg:address":"Pase General Davila, 84",
    "sg:city":"Santander",
    "sg:orig_category":"Limpieza Industrial",
    "sg:phone":"+34 942 31 27 94",
    "sg:postcode":"39006",
    "sg:province":"Cantabria",
    "sg:website":"www.pressto.com",
    "wof:name":"Landry Press S.l.",
    "wof:placetype":"venue"
},
  "geometry": {"coordinates":[-3.801956892,43.4677047729],"type":"Point"}
}