{
  "type": "Feature",
  "properties": {
    "iso:country":"ES",
    "sg:address":"Carr Reina De La, 21",
    "sg:city":"Xativa",
    "sg:orig_category":"Centros De Coordinaci\u00d3n",
    "sg:phone":"+34 962 28 32 94",
    "sg:postcode":"46800",
    "sg:province":"Valencia",
    "wof:name":"Clemente Richart Fernando Luis",
    "wof:placetype":"venue"
},
  "geometry": {"coordinates":[-0.5200830102,38.9934272766],"type":"Point"}
}