{
  "type": "Feature",
  "properties": {
    "addr:full":"Calle de Santutxu, 28 Bilbao Vizcaya 48004",
    "addr:housenumber":"28",
    "addr:postcode":"48004",
    "addr:street":"Calle De Santutxu",
    "iso:country":"ES",
    "sg:address":"Calle de Santutxu, 28",
    "sg:city":"Bilbao",
    "sg:orig_category":"Frutas Y Legumbres Frescas (al Por Mayor)",
    "sg:phone":"+34 944 33 59 37",
    "sg:postcode":"48004",
    "sg:province":"Vizcaya",
    "wof:name":"Micolta Urrutia Estibaliz",
    "wof:placetype":"venue"
},
  "geometry": {"coordinates":[-2.915391922,43.252494812],"type":"Point"}
}