{
  "type": "Feature",
  "properties": {
    "iso:country":"ES",
    "sg:address":"Cami Artesa, S/n",
    "sg:city":"Alcoletge",
    "sg:orig_category":"Establecimientos De Cura, Prevenci\u00d3n Y Readaptaci\u00d3n",
    "sg:phone":"+34 973 19 60 18",
    "sg:postcode":"25660",
    "sg:province":"Lleida",
    "wof:name":"Iglesia Evangelica Centro Benefico Nueva Imagen",
    "wof:placetype":"venue"
},
  "geometry": {"coordinates":[0.6990600228,41.6367340088],"type":"Point"}
}