{
  "type": "Feature",
  "properties": {
    "iso:country":"ES",
    "sg:address":"Avda Manuel Siurot, 25",
    "sg:city":"Huelva",
    "sg:orig_category":"Empresarios Y Productoras De Espect\u00c1culos",
    "sg:phone":"+34 959 25 51 63",
    "sg:postcode":"21004",
    "sg:province":"Huelva",
    "wof:name":"Espectaculos A.conde S.l.",
    "wof:placetype":"venue"
},
  "geometry": {"coordinates":[-6.9469051361,37.265537262],"type":"Point"}
}