{
  "type": "Feature",
  "properties": {
    "iso:country":"ES",
    "sg:address":"Calle de Tercia, 27",
    "sg:city":"Casas-iba\u00e7ez",
    "sg:orig_category":"Plomeros",
    "sg:phone":"+34 967 46 01 21",
    "sg:postcode":"02200",
    "sg:province":"Albacete",
    "wof:name":"Gri\u00f1an C.b.",
    "wof:placetype":"venue"
},
  "geometry": {"coordinates":[-1.470296979,39.2869377136],"type":"Point"}
}