{
  "type": "Feature",
  "properties": {
    "addr:full":"Calle de Villanueva, (de), 6 Carlet Valencia 46240",
    "addr:postcode":"46240",
    "addr:street":"Calle De Villanueva De 6",
    "iso:country":"ES",
    "sg:address":"Calle de Villanueva, (de), 6",
    "sg:city":"Carlet",
    "sg:orig_category":"Mec\u00c1nico Del Autom\u00d3vil",
    "sg:phone":"+34 962 53 02 52",
    "sg:postcode":"46240",
    "sg:province":"Valencia",
    "wof:name":"Ernesto Cast Martinez Y Vicente Renart Martinez C.b.",
    "wof:placetype":"venue"
},
  "geometry": {"coordinates":[-0.5241069794,39.2313728333],"type":"Point"}
}