{
  "type": "Feature",
  "properties": {
    "addr:full":"Calle de Union, 17 Malaga M\u00e1laga 29006",
    "addr:housenumber":"17",
    "addr:postcode":"29006",
    "addr:street":"Calle De;Malaga Ma\u0301Laga",
    "iso:country":"ES",
    "sg:address":"Calle de Union, 17",
    "sg:city":"Malaga",
    "sg:orig_category":"Confecci\u00d3n De Trajes Para Se\u00d1oras",
    "sg:phone":"+34 952 34 05 98",
    "sg:postcode":"29006",
    "sg:province":"M\u00e1laga",
    "wof:name":"Benitez Garcia Maria Alicia",
    "wof:placetype":"venue"
},
  "geometry": {"coordinates":[-4.4359989166,36.7120552063],"type":"Point"}
}