{
  "type": "Feature",
  "properties": {
    "iso:country":"ES",
    "sg:address":"Pg Sant Antoni, 2",
    "sg:city":"Barcelona",
    "sg:orig_category":"Molduras, Junquillos, Listones Y Molduras Perforadas",
    "sg:phone":"+34 932 96 69 85",
    "sg:postcode":"08014",
    "sg:province":"Barcelona",
    "wof:name":"Barjuan Escabia Maria Josep",
    "wof:placetype":"venue"
},
  "geometry": {"coordinates":[2.1362450123,41.3759422302],"type":"Point"}
}