{
  "type": "Feature",
  "properties": {
    "addr:full":"Plaz Espa\u00d1a, 1 Montoro C\u00f3rdoba 14600",
    "addr:housenumber":"1",
    "addr:postcode":"14600",
    "addr:street":"Plaz Espan\u0303A;Co\u0301Rdoba",
    "iso:country":"ES",
    "sg:address":"Plaz Espa\u00d1a, 1",
    "sg:city":"Montoro",
    "sg:orig_category":"Ense\u00d1anza, Formaci\u00d3n Profesional: Aprendizaje",
    "sg:phone":"+34 957 16 04 25",
    "sg:postcode":"14600",
    "sg:province":"C\u00f3rdoba",
    "wof:name":"Ayuntamiento",
    "wof:placetype":"venue"
},
  "geometry": {"coordinates":[-4.3565130234,38.1094436646],"type":"Point"}
}