{
  "type": "Feature",
  "properties": {
    "addr:full":"Calle de Silicio, 10 Torrejon Ardoz Madrid 28850",
    "addr:housenumber":"10",
    "addr:postcode":"28850",
    "addr:street":"Calle De Silicio",
    "iso:country":"ES",
    "sg:address":"Calle de Silicio, 10",
    "sg:city":"Torrejon Ardoz",
    "sg:orig_category":"Muebles, Minoristas",
    "sg:phone":"+34 916 75 23 19",
    "sg:postcode":"28850",
    "sg:province":"Madrid",
    "sg:website":"www.casayjardin.es",
    "wof:name":"Casa Y Jardin S. L.",
    "wof:placetype":"venue"
},
  "geometry": {"coordinates":[-3.4647929668,40.445022583],"type":"Point"}
}