{
  "type": "Feature",
  "properties": {
    "iso:country":"ES",
    "sg:address":"Calle de Alcalde Tarrega, 75",
    "sg:city":"Castellon",
    "sg:orig_category":"Carnicer\u00cdas, Carnicer\u00cdas",
    "sg:phone":"+34 964 22 25 91",
    "sg:postcode":"12004",
    "sg:province":"Castell\u00f3n",
    "wof:name":"Ramos Soler Jose",
    "wof:placetype":"venue"
},
  "geometry": {"coordinates":[-0.0353629999,39.9931602478],"type":"Point"}
}