{
  "type": "Feature",
  "properties": {
    "iso:country":"ES",
    "sg:address":"Pol Ind Los Pinos, 70",
    "sg:city":"Mazagon",
    "sg:orig_category":"Centros Empresariales",
    "sg:phone":"+34 959 37 70 46",
    "sg:postcode":"21130",
    "sg:province":"Huelva",
    "wof:name":"Servicios Integrales Costa De La Luz S.l.",
    "wof:placetype":"venue"
},
  "geometry": {"coordinates":[-6.8279538155,37.1366615295],"type":"Point"}
}