{
  "type": "Feature",
  "properties": {
    "addr:full":"Ctra Carcagente, Km. 0018,7 Alzira Valencia 46600",
    "addr:postcode":"46600",
    "addr:street":"Ctra Carcagente Km. 0018,7;Valencia",
    "iso:country":"ES",
    "sg:address":"Ctra Carcagente, Km. 0018,7",
    "sg:city":"Alzira",
    "sg:orig_category":"Perreras, Pensiones Para Perros, Gatos Y Otros Animales",
    "sg:phone":"+34 962 40 21 68",
    "sg:postcode":"46600",
    "sg:province":"Valencia",
    "wof:name":"Litteldog S.l.",
    "wof:placetype":"venue"
},
  "geometry": {"coordinates":[-0.4378489852,39.1517295837],"type":"Point"}
}