{
  "type": "Feature",
  "properties": {
    "iso:country":"ES",
    "sg:address":"Calle de Jose Recuerda Rubio, 5",
    "sg:city":"Sevilla",
    "sg:orig_category":"Abogados",
    "sg:phone":"+34 954 66 29 11",
    "sg:postcode":"41018",
    "sg:province":"Sevilla",
    "wof:name":"Arevalo Espejo Jose Luis",
    "wof:placetype":"venue"
},
  "geometry": {"coordinates":[-5.9773659706,37.3796844482],"type":"Point"}
}