{
  "type": "Feature",
  "properties": {
    "addr:full":"Herrerieta Kalea, 4 Getaria Guip\u00f9zcoa 20808",
    "addr:housenumber":"4",
    "addr:postcode":"20808",
    "addr:street":"Herrerieta Kalea;Guipu\u0300Zcoa",
    "iso:country":"ES",
    "sg:address":"Herrerieta Kalea, 4",
    "sg:city":"Getaria",
    "sg:orig_category":"Cajas De Ahorro",
    "sg:phone":"+34 943 89 60 05",
    "sg:postcode":"20808",
    "sg:province":"Guip\u00f9zcoa",
    "sg:website":"www.cajalaboral.com",
    "wof:name":"Caja Laboral Popular",
    "wof:placetype":"venue"
},
  "geometry": {"coordinates":[-2.2078208923,43.3037033081],"type":"Point"}
}