{
  "type": "Feature",
  "properties": {
    "iso:country":"ES",
    "sg:address":"Carr Mar, 42",
    "sg:city":"Massamagrell",
    "sg:orig_category":"C\u00c1maras De Comercio E Industria, Oficios, Agricultura",
    "sg:phone":"+34 961 44 05 56",
    "sg:postcode":"46130",
    "sg:province":"Valencia",
    "wof:name":"Camara Agraria Local",
    "wof:placetype":"venue"
},
  "geometry": {"coordinates":[-0.3329139948,39.5671310425],"type":"Point"}
}