{
  "type": "Feature",
  "properties": {
    "iso:country":"ES",
    "sg:address":"Carr San Juan De Ribera, 39",
    "sg:city":"Olleria",
    "sg:orig_category":"Fabricaci\u00d3n De Distribuidores Autom\u00c1ticos",
    "sg:phone":"+34 962 20 13 86",
    "sg:postcode":"46850",
    "sg:province":"Valencia",
    "wof:name":"Va\u00f1o Albi\u00f1ana Maria Ines",
    "wof:placetype":"venue"
},
  "geometry": {"coordinates":[-0.5524070263,38.9134483337],"type":"Point"}
}