{
  "type": "Feature",
  "properties": {
    "addr:full":"Calle de Atajate, 2 Malaga M\u00e1laga 29006",
    "addr:housenumber":"2",
    "addr:postcode":"29006",
    "addr:street":"Calle De Atajate;Ma\u0301Laga",
    "iso:country":"ES",
    "sg:address":"Calle de Atajate, 2",
    "sg:city":"Malaga",
    "sg:orig_category":"Fabricaci\u00d3n, Distribuci\u00d3n De Material Para La Climatizaci\u00d3n, Aireaci\u00d3n Y Ventilaci\u00d3n",
    "sg:phone":"+34 952 33 12 16",
    "sg:postcode":"29006",
    "sg:province":"M\u00e1laga",
    "wof:name":"Insta. Industriales Aireco S.l.",
    "wof:placetype":"venue"
},
  "geometry": {"coordinates":[-4.4686303139,36.7025756836],"type":"Point"}
}