{
  "type": "Feature",
  "properties": {
    "iso:country":"ES",
    "sg:address":"Carrer de Cierva, 27",
    "sg:city":"Zona Industrial",
    "sg:orig_category":"Contenedores (mercanc\u00cdas)",
    "sg:phone":"+34 937 62 53 96",
    "sg:postcode":"08397",
    "sg:province":"Barcelona",
    "wof:name":"Jiporapi Sl",
    "wof:placetype":"venue"
},
  "geometry": {"coordinates":[2.6826798916,41.6266517639],"type":"Point"}
}