{
  "type": "Feature",
  "properties": {
    "addr:full":"Plaz Constitucion (de La), 11 Comillas Cantabria 39520",
    "addr:postcode":"39520",
    "iso:country":"ES",
    "sg:address":"Plaz Constitucion (de La), 11",
    "sg:city":"Comillas",
    "sg:orig_category":"Bazares, Art\u00cdculos De Limpieza Y De Cocina (al Por Menor)",
    "sg:phone":"+34 942 72 22 57",
    "sg:postcode":"39520",
    "sg:province":"Cantabria",
    "wof:name":"Dualde Lopez Ignacio Pedro",
    "wof:placetype":"venue"
},
  "geometry": {"coordinates":[-4.2923278809,43.3905715942],"type":"Point"}
}