{
  "type": "Feature",
  "properties": {
    "iso:country":"ES",
    "sg:address":"Plaz Alfereces, 2",
    "sg:city":"Badajoz",
    "sg:orig_category":"Edici\u00d3n De Diarios, Revistas, Boletines",
    "sg:phone":"+34 924 24 70 00",
    "sg:postcode":"06004",
    "sg:province":"Badajoz",
    "sg:website":"www.oup.com/es",
    "wof:name":"Oxford University Press Espa\u00f1a S.a.",
    "wof:placetype":"venue"
},
  "geometry": {"coordinates":[-6.9726238251,38.874835968],"type":"Point"}
}