{
  "type": "Feature",
  "properties": {
    "iso:country":"ES",
    "sg:address":"Rua Uruguay, 17",
    "sg:city":"Vigo",
    "sg:orig_category":"Asociaciones, Organismos Culturales Y Socioeducativos",
    "sg:phone":"+34 986 43 90 96",
    "sg:postcode":"36201",
    "sg:province":"Pontevedra",
    "wof:name":"Agrupacion Fotografica Gallega",
    "wof:placetype":"venue"
},
  "geometry": {"coordinates":[-8.717628479,42.2361831665],"type":"Point"}
}