{
  "type": "Feature",
  "properties": {
    "iso:country":"ES",
    "sg:address":"Pase Jesuitas, 44",
    "sg:city":"Madrid",
    "sg:orig_category":"Frutas, Legumbres Frescas Y Tempranas (al Por Menor)",
    "sg:phone":"+34 915 26 31 30",
    "sg:postcode":"28011",
    "sg:province":"Madrid",
    "wof:name":"Otero Mu\u00f1iz Antonio",
    "wof:placetype":"venue"
},
  "geometry": {"coordinates":[-3.732738018,40.4100341797],"type":"Point"}
}