{
  "type": "Feature",
  "properties": {
    "addr:full":"Yanguas Y Miranda, 21 Iru\u00f1a Navarra 31003",
    "addr:housenumber":"21",
    "addr:postcode":"31003",
    "addr:street":"Yanguas;Miranda",
    "iso:country":"ES",
    "sg:address":"Yanguas Y Miranda, 21",
    "sg:city":"Iru\u00f1a",
    "sg:orig_category":"Abogados",
    "sg:phone":"+34 948 24 62 42",
    "sg:postcode":"31003",
    "sg:province":"Navarra",
    "wof:name":"Garcia Arias Miguel",
    "wof:placetype":"venue"
},
  "geometry": {"coordinates":[-1.6447709799,42.8117408752],"type":"Point"}
}