{
  "type": "Feature",
  "properties": {
    "addr:full":"Senda De Los Canonigos, 4 Vitoria-gasteiz \u00c1lava 01002",
    "addr:housenumber":"4",
    "addr:postcode":"01002",
    "addr:street":"Senda De Los Canonigos",
    "iso:country":"ES",
    "sg:address":"Senda De Los Canonigos, 4",
    "sg:city":"Vitoria-gasteiz",
    "sg:orig_category":"Inform\u00c1tica, Ofim\u00c1tica (estudios, Asesor\u00cda, Ingenier\u00cda, Formaci\u00d3n)",
    "sg:phone":"+34 945 28 15 82",
    "sg:postcode":"01002",
    "sg:province":"\u00c1lava",
    "wof:name":"Javier Perez Ria\u00f1o",
    "wof:placetype":"venue"
},
  "geometry": {"coordinates":[-2.6618700027,42.8527183533],"type":"Point"}
}