{
  "type": "Feature",
  "properties": {
    "addr:full":"Calle de Santiago Fernandez Portoles, 33 Tudela Navarra 31500",
    "addr:housenumber":"33",
    "addr:postcode":"31500",
    "addr:street":"Calle De Santiago;Portoles",
    "iso:country":"ES",
    "sg:address":"Calle de Santiago Fernandez Portoles, 33",
    "sg:city":"Tudela",
    "sg:orig_category":"Venta, Instalaci\u00d3n De Calefacci\u00d3n",
    "sg:phone":"+34 948 82 36 29",
    "sg:postcode":"31500",
    "sg:province":"Navarra",
    "wof:name":"Yague Gonzalez Joaquin",
    "wof:placetype":"venue"
},
  "geometry": {"coordinates":[-1.6020300388,42.0553779602],"type":"Point"}
}