{
  "type": "Feature",
  "properties": {
    "iso:country":"ES",
    "sg:address":"Carrer de Cobalt, 53",
    "sg:city":"Hospitalet Llobregat",
    "sg:orig_category":"Empresarios",
    "sg:phone":"+34 932 61 08 82",
    "sg:postcode":"08907",
    "sg:province":"Barcelona",
    "wof:name":"Barba Pujol Antonio",
    "wof:placetype":"venue"
},
  "geometry": {"coordinates":[2.1114189625,41.3592147827],"type":"Point"}
}