{
  "type": "Feature",
  "properties": {
    "addr:full":"Rio Henares, 10 Pqe. Boadilla Madrid 28669",
    "addr:housenumber":"10",
    "addr:postcode":"28669",
    "addr:street":"Henares",
    "iso:country":"ES",
    "sg:address":"Rio Henares, 10",
    "sg:city":"Pqe. Boadilla",
    "sg:orig_category":"Art\u00cdculos De Limpieza Y De Cocina (fabricaci\u00d3n, Al Por Mayor)",
    "sg:phone":"+34 916 33 01 45",
    "sg:postcode":"28669",
    "sg:province":"Madrid",
    "wof:name":"Solinteco S.l.",
    "wof:placetype":"venue"
},
  "geometry": {"coordinates":[-3.9161970615,40.4313735962],"type":"Point"}
}