{
  "type": "Feature",
  "properties": {
    "iso:country":"ES",
    "sg:address":"Carrer de Carcassi, 6",
    "sg:city":"Rubi",
    "sg:orig_category":"Artes Gr\u00c1ficas, Artes Pl\u00c1sticas: Material Y Suministros (al Por Menor)",
    "sg:phone":"+34 935 86 20 40",
    "sg:postcode":"08191",
    "sg:province":"Barcelona",
    "sg:website":"www.chimigraf.com",
    "wof:name":"Chimigraf Iberica S.l.",
    "wof:placetype":"venue"
},
  "geometry": {"coordinates":[2.0202679634,41.4752922058],"type":"Point"}
}