{
  "type": "Feature",
  "properties": {
    "addr:full":"Avda Rey Juan Carlos I, 4 Puerto Lumbreras Murcia 30890",
    "addr:housenumber":"4",
    "addr:postcode":"30890",
    "addr:street":"Avda Rey Juan Carlos I",
    "iso:country":"ES",
    "sg:address":"Avda Rey Juan Carlos I, 4",
    "sg:city":"Puerto Lumbreras",
    "sg:orig_category":"Comercio De Piezas De Recambio Y De Accesorios De Veh\u00cdculos, Veh\u00cdculos Industriales",
    "sg:phone":"+34 968 40 27 98",
    "sg:postcode":"30890",
    "sg:province":"Murcia",
    "wof:name":"Lopez Domene Luis",
    "wof:placetype":"venue"
},
  "geometry": {"coordinates":[-1.8049550056,37.5657310486],"type":"Point"}
}