{
  "type": "Feature",
  "properties": {
    "addr:full":"Avda Feria (de La), 5 Villamartin C\u00e1diz 11650",
    "addr:housenumber":"5",
    "addr:postcode":"11650",
    "addr:street":"Avda Feria De La;Ca\u0301Diz",
    "iso:country":"ES",
    "sg:address":"Avda Feria (de La), 5",
    "sg:city":"Villamartin",
    "sg:orig_category":"Farmacias",
    "sg:phone":"+34 956 73 00 75",
    "sg:postcode":"11650",
    "sg:province":"C\u00e1diz",
    "wof:name":"Sepulveda Siles Rodrigo",
    "wof:placetype":"venue"
},
  "geometry": {"coordinates":[-5.6430211067,36.8609085083],"type":"Point"}
}