{
  "type": "Feature",
  "properties": {
    "iso:country":"ES",
    "sg:address":"Calle de Garcia Prieto, 6",
    "sg:city":"Astorga",
    "sg:classifiers":[
        {
            "category":"Autos & Motor Vehicles",
            "subcategory":"Automobile Sales",
            "type":"Retail Goods"
        }
    ],
    "sg:phone":"+34 987 61 53 13",
    "sg:postcode":"24700",
    "sg:province":"Le\u00f3n",
    "wof:name":"Palacio Perez Ulpiana",
    "wof:placetype":"venue"
},
  "geometry": {"coordinates":[-6.0547480583,42.455745697],"type":"Point"}
}