{
  "type": "Feature",
  "properties": {
    "addr:full":"Calle de Virgen Del Carmen, 15 Sabiote Ja\u00e9n 23410",
    "addr:housenumber":"15",
    "addr:postcode":"23410",
    "addr:street":"Calle De Virgen Del Carmen;Jae\u0301N",
    "iso:country":"ES",
    "sg:address":"Calle de Virgen Del Carmen, 15",
    "sg:city":"Sabiote",
    "sg:orig_category":"Molduras, Junquillos, Listones Y Molduras Perforadas",
    "sg:phone":"+34 953 77 32 37",
    "sg:postcode":"23410",
    "sg:province":"Ja\u00e9n",
    "wof:name":"Hurtado Antolinez Vicente",
    "wof:placetype":"venue"
},
  "geometry": {"coordinates":[-3.3082690239,38.0687484741],"type":"Point"}
}