{
  "type": "Feature",
  "properties": {
    "addr:full":"Avda Extremadura, S/n Castuera Badajoz 06420",
    "addr:postcode":"06420",
    "addr:street":"Avda Extremadura S / N",
    "iso:country":"ES",
    "sg:address":"Avda Extremadura, S/n",
    "sg:city":"Castuera",
    "sg:orig_category":"Piscinas, Accesorios, Suministros (fabricaci\u00d3n, Al Por Mayor)",
    "sg:phone":"+34 924 76 15 61",
    "sg:postcode":"06420",
    "sg:province":"Badajoz",
    "wof:name":"Ayuntamiento De Castuera",
    "wof:placetype":"venue"
},
  "geometry": {"coordinates":[-5.5401368141,38.7287483215],"type":"Point"}
}