{
  "type": "Feature",
  "properties": {
    "iso:country":"ES",
    "sg:address":"Llevant, 18",
    "sg:city":"Vilablareix",
    "sg:orig_category":"Chapister\u00cda",
    "sg:phone":"+34 972 40 19 06",
    "sg:postcode":"17180",
    "sg:province":"Girona",
    "wof:name":"Autotaller Francisco S. L.",
    "wof:placetype":"venue"
},
  "geometry": {"coordinates":[2.800839901,41.9528923035],"type":"Point"}
}