{
  "type": "Feature",
  "properties": {
    "addr:full":"Cami Ca N'oriol, S/n Rubi Barcelona 08191",
    "addr:housenumber":"s",
    "addr:postcode":"08191",
    "addr:street":"Ca N'Oriol;/ N",
    "iso:country":"ES",
    "sg:address":"Cami Ca N'oriol, S/n",
    "sg:city":"Rubi",
    "sg:orig_category":"Reposter\u00cdas",
    "sg:phone":"+34 936 99 13 89",
    "sg:postcode":"08191",
    "sg:province":"Barcelona",
    "wof:name":"Presas Pages Juan",
    "wof:placetype":"venue"
},
  "geometry": {"coordinates":[2.0316200256,41.4919090271],"type":"Point"}
}