{
  "type": "Feature",
  "properties": {
    "iso:country":"ES",
    "sg:address":"Calle de Goya, 1",
    "sg:city":"Puertollano",
    "sg:orig_category":"Agencias Y Asesores De Publicidad",
    "sg:phone":"+34 926 41 35 45",
    "sg:postcode":"13500",
    "sg:province":"Ciudad Real",
    "wof:name":"Unnica Desarrollo Digital Y Dise\u00f1o S.l.",
    "wof:placetype":"venue"
},
  "geometry": {"coordinates":[-4.1035490036,38.685218811],"type":"Point"}
}