{
  "type": "Feature",
  "properties": {
    "addr:full":"Plaz Mayor, 8 Baza Granada 18800",
    "addr:housenumber":"8",
    "addr:postcode":"18800",
    "addr:street":"Plaz Mayor",
    "iso:country":"ES",
    "sg:address":"Plaz Mayor, 8",
    "sg:city":"Baza",
    "sg:orig_category":"Farmacias",
    "sg:phone":"+34 958 70 13 06",
    "sg:postcode":"18800",
    "sg:province":"Granada",
    "wof:name":"Farmacia Ortega Garcia",
    "wof:placetype":"venue"
},
  "geometry": {"coordinates":[-2.7741849422,37.4901275635],"type":"Point"}
}