{
  "type": "Feature",
  "properties": {
    "addr:full":"La Encrucijada, S/n Fresneu Asturias 33529",
    "addr:housenumber":"s / n",
    "addr:postcode":"33529",
    "addr:street":"La Encrucijada",
    "iso:country":"ES",
    "sg:address":"La Encrucijada, S/n",
    "sg:city":"Fresneu",
    "sg:orig_category":"Alimentaci\u00d3n General (al Por Mayor)",
    "sg:phone":"+34 985 89 80 31",
    "sg:postcode":"33529",
    "sg:province":"Asturias",
    "wof:name":"Martinez Sanchez Pedro",
    "wof:placetype":"venue"
},
  "geometry": {"coordinates":[-5.4692487717,43.408908844],"type":"Point"}
}