{
  "type": "Feature",
  "properties": {
    "addr:full":"I\u00f1igo Arista, 18 Iru\u00f1a Navarra 31007",
    "addr:housenumber":"18",
    "addr:postcode":"31007",
    "addr:street":"Arista",
    "iso:country":"ES",
    "sg:address":"I\u00f1igo Arista, 18",
    "sg:city":"Iru\u00f1a",
    "sg:classifiers":[
        {
            "category":"Personal",
            "subcategory":"Barber",
            "type":"Services"
        }
    ],
    "sg:phone":"+34 948 26 97 55",
    "sg:postcode":"31007",
    "sg:province":"Navarra",
    "sg:tags":[
        "caballeros",
        "de",
        "peluqueros"
    ],
    "wof:name":"Ibaez Martinez Losa Felix",
    "wof:placetype":"venue"
},
  "geometry": {"coordinates":[-1.6539740562,42.8071060181],"type":"Point"}
}