{
  "type": "Feature",
  "properties": {
    "addr:full":"Calle de Carrera, 7 Fuentes De Andalucia Sevilla 41420",
    "addr:postcode":"41420",
    "addr:street":"Calle De Carrera 7 Fuentes De Andalucia",
    "iso:country":"ES",
    "sg:address":"Calle de Carrera, 7",
    "sg:city":"Fuentes De Andalucia",
    "sg:orig_category":"Estancos",
    "sg:phone":"+34 954 83 72 44",
    "sg:postcode":"41420",
    "sg:province":"Sevilla",
    "wof:name":"Fernandez Garcia Rafael",
    "wof:placetype":"venue"
},
  "geometry": {"coordinates":[-5.3480610847,37.4634094238],"type":"Point"}
}