{
  "type": "Feature",
  "properties": {
    "addr:full":"Buenos Aires, 1 Jimenado Murcia 30708",
    "addr:housenumber":"1",
    "addr:postcode":"30708",
    "addr:street":"Buenos Aires",
    "iso:country":"ES",
    "sg:address":"Buenos Aires, 1",
    "sg:city":"Jimenado",
    "sg:orig_category":"Cajas Para Embalar",
    "sg:phone":"+34 968 58 79 04",
    "sg:postcode":"30708",
    "sg:province":"Murcia",
    "sg:website":"www.cajamar.es",
    "wof:name":"Cajamar",
    "wof:placetype":"venue"
},
  "geometry": {"coordinates":[-1.0384089947,37.7581214905],"type":"Point"}
}