{
  "type": "Feature",
  "properties": {
    "addr:full":"Plaz Gure Zumardia, 3 Pasai Antxo Guip\u00f9zcoa 20110",
    "addr:housenumber":"3",
    "addr:postcode":"20110",
    "addr:street":"Gure Zumardia;Guipu\u0300Zcoa",
    "iso:country":"ES",
    "sg:address":"Plaz Gure Zumardia, 3",
    "sg:city":"Pasai Antxo",
    "sg:orig_category":"Ropa Para Se\u00d1oras (al Por Menor)",
    "sg:phone":"+34 943 51 13 46",
    "sg:postcode":"20110",
    "sg:province":"Guip\u00f9zcoa",
    "wof:name":"Garcia Serna Valentin",
    "wof:placetype":"venue"
},
  "geometry": {"coordinates":[-1.9183219671,43.3175811768],"type":"Point"}
}