{
  "type": "Feature",
  "properties": {
    "iso:country":"ES",
    "sg:address":"Carrer de Arago, 9",
    "sg:city":"Barcelona",
    "sg:orig_category":"Perfumer\u00cda Y Cosm\u00c9tica (fabricaci\u00d3n, Al Por Mayor)",
    "sg:phone":"+34 932 28 24 42",
    "sg:postcode":"08015",
    "sg:province":"Barcelona",
    "wof:name":"Skeyndor S.l.",
    "wof:placetype":"venue"
},
  "geometry": {"coordinates":[2.1462759972,41.3784942627],"type":"Point"}
}