{
  "type": "Feature",
  "properties": {
    "addr:full":"Cm\u00d1o Glorieta (da), 16 Verin Ourense 32600",
    "addr:housenumber":"16",
    "addr:postcode":"32600",
    "addr:street":"Glorieta Da",
    "iso:country":"ES",
    "sg:address":"Cm\u00d1o Glorieta (da), 16",
    "sg:city":"Verin",
    "sg:orig_category":"Guarder\u00cdas",
    "sg:phone":"+34 988 41 14 91",
    "sg:postcode":"32600",
    "sg:province":"Ourense",
    "wof:name":"Daelcarma S.l.u.",
    "wof:placetype":"venue"
},
  "geometry": {"coordinates":[-7.4346928596,41.9324111938],"type":"Point"}
}