{
  "type": "Feature",
  "properties": {
    "iso:country":"ES",
    "sg:address":"Calle de Carmen (del), 2",
    "sg:city":"Cartagena",
    "sg:orig_category":"Perfumer\u00cda, Art\u00cdculos De Ba\u00d1o (fabricaci\u00d3n, Al Por Mayor)",
    "sg:phone":"+34 968 52 13 96",
    "sg:postcode":"30201",
    "sg:province":"Murcia",
    "wof:name":"Lolianna S.l.",
    "wof:placetype":"venue"
},
  "geometry": {"coordinates":[-0.9891585708,37.6039352417],"type":"Point"}
}