{
  "type": "Feature",
  "properties": {
    "addr:full":"Calle de Juan De Mena, 10 Madrid Madrid 28014",
    "addr:housenumber":"10",
    "addr:postcode":"madrid;28014",
    "addr:street":"Calle De Juan;Mena",
    "iso:country":"ES",
    "sg:address":"Calle de Juan De Mena, 10",
    "sg:city":"Madrid",
    "sg:orig_category":"Agencias Y Asesores De Publicidad",
    "sg:phone":"+34 915 24 90 35",
    "sg:postcode":"28014",
    "sg:province":"Madrid",
    "sg:website":"www.defederyco.com",
    "wof:name":"De Federyco 1991 S.a.",
    "wof:placetype":"venue"
},
  "geometry": {"coordinates":[-3.6902120113,40.4171905518],"type":"Point"}
}