{
  "type": "Feature",
  "properties": {
    "iso:country":"ES",
    "sg:address":"Calle de Molino, 1",
    "sg:city":"Don Benito",
    "sg:orig_category":"Asesor\u00cda Fiscal Y Jur\u00cddica",
    "sg:phone":"+34 924 80 42 22",
    "sg:postcode":"06400",
    "sg:province":"Badajoz",
    "wof:name":"Pulido Lazaro Asesores S.l.",
    "wof:placetype":"venue"
},
  "geometry": {"coordinates":[-5.8593401909,38.9599952698],"type":"Point"}
}