{
  "type": "Feature",
  "properties": {
    "addr:full":"Calle de Romero, 1 Valtierra Navarra 31514",
    "addr:housenumber":"1",
    "addr:postcode":"31514",
    "addr:street":"Calle De Romero",
    "iso:country":"ES",
    "sg:address":"Calle de Romero, 1",
    "sg:city":"Valtierra",
    "sg:orig_category":"Alimentaci\u00d3n General (al Por Menor)",
    "sg:phone":"+34 948 86 70 55",
    "sg:postcode":"31514",
    "sg:province":"Navarra",
    "wof:name":"Rodrigo Goicoechea Jose Luis",
    "wof:placetype":"venue"
},
  "geometry": {"coordinates":[-1.6344890594,42.1966400146],"type":"Point"}
}