{
  "type": "Feature",
  "properties": {
    "iso:country":"ES",
    "sg:address":"Garcia Ximenez, 1",
    "sg:city":"Iru\u00f1a",
    "sg:orig_category":"Camiser\u00cda Y Ropa Interior Masculina (al Por Menor)",
    "sg:phone":"+34 948 22 58 14",
    "sg:postcode":"31002",
    "sg:province":"Navarra",
    "wof:name":"Altube Belascuain Camino",
    "wof:placetype":"venue"
},
  "geometry": {"coordinates":[-1.6434701681,42.8138542175],"type":"Point"}
}