{
  "type": "Feature",
  "properties": {
    "iso:country":"ES",
    "sg:address":"Avda Primero De Mayo, 31",
    "sg:city":"Valle Trapaga",
    "sg:orig_category":"Asesor\u00cda Sobre Comunicaci\u00d3n De Empresas",
    "sg:phone":"+34 944 86 20 01",
    "sg:postcode":"48510",
    "sg:province":"Vizcaya",
    "wof:name":"Trapaga Asesores S.l.",
    "wof:placetype":"venue"
},
  "geometry": {"coordinates":[-3.0345220566,43.3023719788],"type":"Point"}
}