{
  "type": "Feature",
  "properties": {
    "addr:full":"Carrer de Buenos Aires, 12 Barcelona Barcelona 08029",
    "addr:housenumber":"12",
    "addr:postcode":"08029",
    "addr:street":"Carrer De Buenos Aires",
    "iso:country":"ES",
    "sg:address":"Carrer de Buenos Aires, 12",
    "sg:city":"Barcelona",
    "sg:orig_category":"Peluquer\u00cdas, Peluquer\u00cda Mixta",
    "sg:phone":"+34 934 10 30 39",
    "sg:postcode":"08029",
    "sg:province":"Barcelona",
    "wof:name":"Martinez Cruz Francisco",
    "wof:placetype":"venue"
},
  "geometry": {"coordinates":[2.1455199718,41.3911132812],"type":"Point"}
}