{
  "type": "Feature",
  "properties": {
    "addr:full":"Calle de Real, 41 San Sebastian De Los Reyes Madrid 28700",
    "addr:housenumber":"41",
    "addr:postcode":"28700",
    "addr:street":"Calle De Real",
    "iso:country":"ES",
    "sg:address":"Calle de Real, 41",
    "sg:city":"San Sebastian De Los Reyes",
    "sg:orig_category":"Bancos",
    "sg:phone":"+34 916 58 60 55",
    "sg:postcode":"28700",
    "sg:province":"Madrid",
    "wof:name":"Banco Espa\u00f1ol De Credito S.a.",
    "wof:placetype":"venue"
},
  "geometry": {"coordinates":[-3.6253619194,40.5475273132],"type":"Point"}
}