{
  "type": "Feature",
  "properties": {
    "addr:full":"Calle de Almoradi, 7 Alacant Alicante 03010",
    "addr:housenumber":"7",
    "addr:postcode":"03010",
    "addr:street":"Calle De Almoradi",
    "iso:country":"ES",
    "sg:address":"Calle de Almoradi, 7",
    "sg:city":"Alacant",
    "sg:orig_category":"Prot\u00c9sicos Dentales",
    "sg:phone":"+34 965 17 46 55",
    "sg:postcode":"03010",
    "sg:province":"Alicante",
    "wof:name":"Arenas Bernabeu Jose Pedro",
    "wof:placetype":"venue"
},
  "geometry": {"coordinates":[-0.4943690002,38.3652076721],"type":"Point"}
}