{
  "type": "Feature",
  "properties": {
    "iso:country":"ES",
    "sg:address":"Calle de Carlos Iii, S/n",
    "sg:city":"Santa Marta De Tormes",
    "sg:orig_category":"Vinos Y Licores (venta Al Por Menor)",
    "sg:phone":"+34 923 20 05 86",
    "sg:postcode":"37900",
    "sg:province":"Salamanca",
    "wof:name":"Andres Gallego Jose",
    "wof:placetype":"venue"
},
  "geometry": {"coordinates":[-5.6314716339,40.9496383667],"type":"Point"}
}