{
  "type": "Feature",
  "properties": {
    "addr:full":"Calle de Ramon Y Cajal, 52 Pe\u00f1aflor Sevilla 41470",
    "addr:housenumber":"52",
    "addr:postcode":"41470",
    "addr:street":"Calle De Ramon Y Cajal",
    "iso:country":"ES",
    "sg:address":"Calle de Ramon Y Cajal, 52",
    "sg:city":"Pe\u00f1aflor",
    "sg:orig_category":"Droguer\u00cdas (al Por Menor)",
    "sg:phone":"+34 954 80 71 01",
    "sg:postcode":"41470",
    "sg:province":"Sevilla",
    "wof:name":"Sojo Guadalupe Francisco",
    "wof:placetype":"venue"
},
  "geometry": {"coordinates":[-5.3466691971,37.7092666626],"type":"Point"}
}