{
  "type": "Feature",
  "properties": {
    "addr:full":"Calle de Covadonga, 8 Gijon Asturias 33201",
    "addr:housenumber":"8",
    "addr:postcode":"33201",
    "addr:street":"Calle De Covadonga",
    "iso:country":"ES",
    "sg:address":"Calle de Covadonga, 8",
    "sg:city":"Gijon",
    "sg:orig_category":"M\u00c9dicos: Estomatolog\u00cda",
    "sg:phone":"+34 985 34 12 61",
    "sg:postcode":"33201",
    "sg:province":"Asturias",
    "wof:name":"Pipa Vallejo Adolfo",
    "wof:placetype":"venue"
},
  "geometry": {"coordinates":[-5.6586556435,43.5395431519],"type":"Point"}
}