{
  "type": "Feature",
  "properties": {
    "iso:country":"ES",
    "sg:address":"Calle de Alcala, 236",
    "sg:city":"Madrid",
    "sg:orig_category":"Librer\u00cdas",
    "sg:phone":"+34 917 25 32 87",
    "sg:postcode":"28027",
    "sg:province":"Madrid",
    "wof:name":"Gutierrez Grimaldos Eduardo",
    "wof:placetype":"venue"
},
  "geometry": {"coordinates":[-3.6571185589,40.4318389893],"type":"Point"}
}