{
  "type": "Feature",
  "properties": {
    "addr:full":"Avda Don Juan De Borbon, S/n Getafe Madrid 28903",
    "addr:housenumber":"s / n",
    "addr:postcode":"28903",
    "addr:street":"Avda Don Juan De Borbon",
    "iso:country":"ES",
    "sg:address":"Avda Don Juan De Borbon, S/n",
    "sg:city":"Getafe",
    "sg:orig_category":"Deportes Diversos",
    "sg:phone":"+34 916 96 10 15",
    "sg:postcode":"28903",
    "sg:province":"Madrid",
    "sg:website":"www.cemafusagetafe.com",
    "wof:name":"Federacion Madrile\u00f1a De Futbol Sala",
    "wof:placetype":"venue"
},
  "geometry": {"coordinates":[-3.7137789726,40.3161964417],"type":"Point"}
}