{
  "type": "Feature",
  "properties": {
    "iso:country":"ES",
    "sg:address":"Av Lleida, S/n",
    "sg:city":"Bellpuig",
    "sg:orig_category":"Frutas Y Legumbres Frescas (al Por Mayor)",
    "sg:phone":"+34 973 33 70 42",
    "sg:postcode":"25250",
    "sg:province":"Lleida",
    "wof:name":"Ibos Tudela Ramon",
    "wof:placetype":"venue"
},
  "geometry": {"coordinates":[1.0162949562,41.6314888],"type":"Point"}
}