{
  "type": "Feature",
  "properties": {
    "addr:full":"Ctra Igualada (d'), 15 Santa Coloma De Queralt Tarragona 43420",
    "addr:housenumber":"15",
    "addr:postcode":"43420",
    "addr:street":"Ctra Igualada D '",
    "iso:country":"ES",
    "sg:address":"Ctra Igualada (d'), 15",
    "sg:city":"Santa Coloma De Queralt",
    "sg:orig_category":"Cerrajer\u00cda, Ferrallista",
    "sg:phone":"+34 977 88 15 36",
    "sg:postcode":"43420",
    "sg:province":"Tarragona",
    "wof:name":"Soler Mas Magin",
    "wof:placetype":"venue"
},
  "geometry": {"coordinates":[1.385076046,41.5344810486],"type":"Point"}
}