{
  "type": "Feature",
  "properties": {
    "iso:country":"ES",
    "sg:address":"Carrer de Berenguer Santjoan, 4",
    "sg:city":"Palma",
    "sg:orig_category":"Ropa Para Ni\u00d1os (al Por Menor)",
    "sg:phone":"+34 971 72 48 78",
    "sg:postcode":"07012",
    "sg:province":"Islas Baleares",
    "wof:name":"Calvo Lamata Maria Jose",
    "wof:placetype":"venue"
},
  "geometry": {"coordinates":[2.6448819637,39.5734596252],"type":"Point"}
}