{
  "type": "Feature",
  "properties": {
    "addr:full":"Calle de Picadero, 4 Marchena Sevilla 41620",
    "addr:housenumber":"4",
    "addr:postcode":"41620",
    "addr:street":"Calle De Picadero",
    "iso:country":"ES",
    "sg:address":"Calle de Picadero, 4",
    "sg:city":"Marchena",
    "sg:orig_category":"Empresas De Carpinter\u00cda Met\u00c1lica",
    "sg:phone":"+34 954 84 30 42",
    "sg:postcode":"41620",
    "sg:province":"Sevilla",
    "wof:name":"Salvador Falcon Manuel",
    "wof:placetype":"venue"
},
  "geometry": {"coordinates":[-5.4176359177,37.3329620361],"type":"Point"}
}