{
  "type": "Feature",
  "properties": {
    "iso:country":"ES",
    "sg:address":"Calle de Juan Lerida, 22",
    "sg:city":"Poligono Nacoisa",
    "sg:orig_category":"Centros Empresariales",
    "sg:phone":"+34 954 91 59 35",
    "sg:postcode":"41309",
    "sg:province":"Sevilla",
    "wof:name":"Grupo Empresarial Mara S.l",
    "wof:placetype":"venue"
},
  "geometry": {"coordinates":[-5.9782538414,37.492855072],"type":"Point"}
}