{
  "type": "Feature",
  "properties": {
    "addr:full":"Calle de Malpica, S/n Malaga M\u00e1laga 29002",
    "addr:housenumber":"s / n",
    "addr:postcode":"29002",
    "addr:street":"Calle De Malpica;Ma\u0301Laga",
    "iso:country":"ES",
    "sg:address":"Calle de Malpica, S/n",
    "sg:city":"Malaga",
    "sg:orig_category":"Ense\u00d1anza, Formaci\u00d3n Profesional: Aprendizaje",
    "sg:phone":"+34 952 33 46 07",
    "sg:postcode":"29002",
    "sg:province":"M\u00e1laga",
    "wof:name":"Junta De Andalucia-consejeria De Cultura",
    "wof:placetype":"venue"
},
  "geometry": {"coordinates":[-4.4295687675,36.7149658203],"type":"Point"}
}