{
  "type": "Feature",
  "properties": {
    "addr:full":"Rua Insuas (das), 44 Sarria Lugo 27600",
    "addr:housenumber":"44",
    "addr:postcode":"27600",
    "addr:street":"Rua Insuas Das",
    "iso:country":"ES",
    "sg:address":"Rua Insuas (das), 44",
    "sg:city":"Sarria",
    "sg:orig_category":"Empresarios",
    "sg:phone":"+34 982 53 01 53",
    "sg:postcode":"27600",
    "sg:province":"Lugo",
    "wof:name":"Vazquez Paramo Antonio",
    "wof:placetype":"venue"
},
  "geometry": {"coordinates":[-7.4146690369,42.7846412659],"type":"Point"}
}