{
  "type": "Feature",
  "properties": {
    "addr:full":"Calle de Honda, 11 Herencia Ciudad Real 13640",
    "addr:housenumber":"11",
    "addr:postcode":"13640",
    "addr:street":"Calle De Honda",
    "iso:country":"ES",
    "sg:address":"Calle de Honda, 11",
    "sg:city":"Herencia",
    "sg:orig_category":"Material Y Suministros Para Horticultura, Arboricultura",
    "sg:phone":"+34 926 57 30 98",
    "sg:postcode":"13640",
    "sg:province":"Ciudad Real",
    "wof:name":"Tajuelo Fernandez-baillo Inocente Mercenario",
    "wof:placetype":"venue"
},
  "geometry": {"coordinates":[-3.3559279442,39.3698387146],"type":"Point"}
}