{
  "type": "Feature",
  "properties": {
    "addr:full":"Calle de Rafael Garcia Perez, 23 Palmas De Gran Canaria Las Palmas 35014",
    "addr:postcode":"35014",
    "addr:street":"Calle De Rafael Garcia Perez 23",
    "iso:country":"ES",
    "sg:address":"Calle de Rafael Garcia Perez, 23",
    "sg:city":"Palmas De Gran Canaria",
    "sg:orig_category":"Ense\u00d1anza Variada",
    "sg:phone":"+34 928 38 52 33",
    "sg:postcode":"35014",
    "sg:province":"Las Palmas",
    "wof:name":"Perez Aguado Jesus Fernando",
    "wof:placetype":"venue"
},
  "geometry": {"coordinates":[-15.4316415787,28.1046524048],"type":"Point"}
}