{
  "type": "Feature",
  "properties": {
    "iso:country":"ES",
    "sg:address":"Carrer de Rosa De Alejandria, 18",
    "sg:city":"Hospitalet Llobregat",
    "sg:orig_category":"Muebles, Minoristas",
    "sg:phone":"+34 934 38 14 19",
    "sg:postcode":"08906",
    "sg:province":"Barcelona",
    "wof:name":"Garcia Sanchez Jose",
    "wof:placetype":"venue"
},
  "geometry": {"coordinates":[12.4903001785,51.6163101196],"type":"Point"}
}