{
  "type": "Feature",
  "properties": {
    "iso:country":"ES",
    "sg:address":"Calle de San Anton, 64",
    "sg:city":"Parla",
    "sg:orig_category":"Zapatos (al Por Menor)",
    "sg:phone":"+34 916 98 40 68",
    "sg:postcode":"28980",
    "sg:province":"Madrid",
    "wof:name":"Gonzalez Lahera Jorge",
    "wof:placetype":"venue"
},
  "geometry": {"coordinates":[-3.7682449818,40.2406463623],"type":"Point"}
}