{
  "type": "Feature",
  "properties": {
    "addr:full":"Calle de Alberche, 13 Madrid Madrid 28045",
    "addr:housenumber":"13",
    "addr:postcode":"madrid;28045",
    "addr:street":"Calle De Alberche",
    "iso:country":"ES",
    "sg:address":"Calle de Alberche, 13",
    "sg:city":"Madrid",
    "sg:orig_category":"Comisarios",
    "sg:phone":"+34 915 39 39 62",
    "sg:postcode":"28045",
    "sg:province":"Madrid",
    "wof:name":"Garcia Naharro Jose Luis",
    "wof:placetype":"venue"
},
  "geometry": {"coordinates":[-3.680398941,40.3977737427],"type":"Point"}
}