{
  "type": "Feature",
  "properties": {
    "addr:full":"Calle de Romana, 47 Sevilla Sevilla 41020",
    "addr:housenumber":"47",
    "addr:postcode":"41020",
    "addr:street":"Calle De Romana",
    "iso:country":"ES",
    "sg:address":"Calle de Romana, 47",
    "sg:city":"Sevilla",
    "sg:orig_category":"Centros Comerciales Y Grandes Tiendas",
    "sg:phone":"+34 954 51 05 75",
    "sg:postcode":"41020",
    "sg:province":"Sevilla",
    "wof:name":"Shanghai",
    "wof:placetype":"venue"
},
  "geometry": {"coordinates":[-5.9392790794,37.3935699463],"type":"Point"}
}