{
  "type": "Feature",
  "properties": {
    "iso:country":"ES",
    "sg:address":"Avda Palacio Valdes, 4",
    "sg:city":"Ribadesella",
    "sg:orig_category":"Pescader\u00cdas (al Por Menor)",
    "sg:phone":"+34 985 86 04 22",
    "sg:postcode":"33560",
    "sg:province":"Asturias",
    "wof:name":"Segundo Gonzalez Gonzalez S. A.",
    "wof:placetype":"venue"
},
  "geometry": {"coordinates":[-5.0615811348,43.4555435181],"type":"Point"}
}