{
  "type": "Feature",
  "properties": {
    "iso:country":"ES",
    "sg:address":"Carrer de Clotas, 9",
    "sg:city":"Pallaresos",
    "sg:orig_category":"Fabricaci\u00d3n De Cervezas",
    "sg:phone":"+34 977 61 05 71",
    "sg:postcode":"43151",
    "sg:province":"Tarragona",
    "wof:name":"Coimpro Alimentacion S.a.",
    "wof:placetype":"venue"
},
  "geometry": {"coordinates":[1.2705910206,41.1747894287],"type":"Point"}
}