{
  "type": "Feature",
  "properties": {
    "addr:full":"Carr Doctor Fleming, 13 Aldaia Valencia 46960",
    "addr:housenumber":"13",
    "addr:postcode":"46960",
    "addr:street":"Carr Doctor Fleming",
    "iso:country":"ES",
    "sg:address":"Carr Doctor Fleming, 13",
    "sg:city":"Aldaia",
    "sg:orig_category":"Mec\u00c1nico Del Autom\u00d3vil",
    "sg:phone":"+34 961 50 13 84",
    "sg:postcode":"46960",
    "sg:province":"Valencia",
    "wof:name":"Automoviles Pinel S.l.",
    "wof:placetype":"venue"
},
  "geometry": {"coordinates":[-0.4697540104,39.4626350403],"type":"Point"}
}