{
  "type": "Feature",
  "properties": {
    "addr:full":"Plaz Espa\u00d1a (de), 3 Horcajo Santiago Cuenca 16410",
    "addr:postcode":"16410",
    "addr:street":"Plaz;Cuenca",
    "iso:country":"ES",
    "sg:address":"Plaz Espa\u00d1a (de), 3",
    "sg:city":"Horcajo Santiago",
    "sg:orig_category":"Bancos",
    "sg:phone":"+34 969 32 75 01",
    "sg:postcode":"16410",
    "sg:province":"Cuenca",
    "sg:website":"www.bancozaragozano.es",
    "wof:name":"Barclays Bank S.a.e.",
    "wof:placetype":"venue"
},
  "geometry": {"coordinates":[-3.0003340244,39.8414802551],"type":"Point"}
}