{
  "type": "Feature",
  "properties": {
    "addr:full":"Escuelas, S/n Royuela De Rio Franco Burgos 09344",
    "addr:housenumber":"s",
    "addr:postcode":"09344",
    "addr:street":"Escuelas;/ N",
    "iso:country":"ES",
    "sg:address":"Escuelas, S/n",
    "sg:city":"Royuela De Rio Franco",
    "sg:classifiers":[
        {
            "category":"Taxi",
            "type":"Transportation"
        }
    ],
    "sg:phone":"+34 947 18 70 83",
    "sg:postcode":"09344",
    "sg:province":"Burgos",
    "wof:name":"Arnaiz Garcia Hipolito",
    "wof:placetype":"venue"
},
  "geometry": {"coordinates":[-3.8858840466,42.0023384094],"type":"Point"}
}