{
  "type": "Feature",
  "properties": {
    "addr:full":"Ctra Arbucies, 83 Breda Girona 17400",
    "addr:housenumber":"83",
    "addr:postcode":"17400",
    "addr:street":"Ctra Arbucies",
    "iso:country":"ES",
    "sg:address":"Ctra Arbucies, 83",
    "sg:city":"Breda",
    "sg:orig_category":"Porcelanas, Azulejos (fabricaci\u00d3n, Al Por Mayor)",
    "sg:phone":"+34 972 87 02 56",
    "sg:postcode":"17400",
    "sg:province":"Girona",
    "wof:name":"Terraforta S.c.",
    "wof:placetype":"venue"
},
  "geometry": {"coordinates":[2.5585401058,41.7448234558],"type":"Point"}
}