{
  "type": "Feature",
  "properties": {
    "addr:full":"Cust San Miguel, 8 Guadalajara Guadalajara 19001",
    "addr:housenumber":"8",
    "addr:postcode":"19001",
    "addr:street":"San Miguel",
    "iso:country":"ES",
    "sg:address":"Cust San Miguel, 8",
    "sg:city":"Guadalajara",
    "sg:orig_category":"Agentes Generales De Seguros",
    "sg:phone":"+34 949 22 09 31",
    "sg:postcode":"19001",
    "sg:province":"Guadalajara",
    "wof:name":"Navarro Lozano Andres",
    "wof:placetype":"venue"
},
  "geometry": {"coordinates":[-3.163120985,40.6337661743],"type":"Point"}
}