{
  "type": "Feature",
  "properties": {
    "iso:country":"ES",
    "sg:address":"Calle de Casimiro Sainz, 8",
    "sg:city":"Santander",
    "sg:orig_category":"Mercer\u00cda, Lencer\u00cda (al Por Menor)",
    "sg:phone":"+34 942 21 67 68",
    "sg:postcode":"39003",
    "sg:province":"Cantabria",
    "wof:name":"Pe\u00f1a Concha Ramona",
    "wof:placetype":"venue"
},
  "geometry": {"coordinates":[-3.7967040539,43.4643440247],"type":"Point"}
}