{
  "type": "Feature",
  "properties": {
    "addr:full":"Carr Masnou, De, S/n Consell Islas Baleares 07330",
    "addr:housenumber":"/ n",
    "addr:postcode":"07330",
    "addr:street":"Carr Masnou De S",
    "iso:country":"ES",
    "sg:address":"Carr Masnou, De, S/n",
    "sg:city":"Consell",
    "sg:orig_category":"Cr\u00cda De Cerdos",
    "sg:phone":"+34 971 62 20 03",
    "sg:postcode":"07330",
    "sg:province":"Islas Baleares",
    "wof:name":"Ganadera Maynou S.l.",
    "wof:placetype":"venue"
},
  "geometry": {"coordinates":[2.8202500343,39.6667709351],"type":"Point"}
}