{
  "type": "Feature",
  "properties": {
    "iso:country":"ES",
    "sg:address":"Calle de Mesones, 44",
    "sg:city":"Ubeda",
    "sg:orig_category":"Zapatos (al Por Menor)",
    "sg:phone":"+34 953 75 00 65",
    "sg:postcode":"23400",
    "sg:province":"Ja\u00e9n",
    "wof:name":"Ojeda Estrada Miguel",
    "wof:placetype":"venue"
},
  "geometry": {"coordinates":[-3.3724009991,38.0115394592],"type":"Point"}
}