{
  "type": "Feature",
  "properties": {
    "addr:full":"Calle de Villafranca Del Bierzo, 4 Madrid Madrid 28050",
    "addr:housenumber":"4",
    "addr:postcode":"28050",
    "addr:street":"Calle De Villafranca Del Bierzo",
    "iso:country":"ES",
    "sg:address":"Calle de Villafranca Del Bierzo, 4",
    "sg:city":"Madrid",
    "sg:orig_category":"Chapister\u00cda",
    "sg:phone":"+34 917 64 14 95",
    "sg:postcode":"28050",
    "sg:province":"Madrid",
    "wof:name":"Sanchez Rodriguez Francisco",
    "wof:placetype":"venue"
},
  "geometry": {"coordinates":[-3.6327810287,40.4812278748],"type":"Point"}
}