{
  "type": "Feature",
  "properties": {
    "iso:country":"ES",
    "sg:address":"Calle de San Joaquin, 1",
    "sg:city":"Sevilla",
    "sg:orig_category":"Instalaci\u00d3n, Reparaci\u00d3n De Ascensores Y Montacargas",
    "sg:phone":"+34 954 53 97 12",
    "sg:postcode":"41008",
    "sg:province":"Sevilla",
    "wof:name":"Instalacion Y Mantenimiento Del Ascensor S.l",
    "wof:placetype":"venue"
},
  "geometry": {"coordinates":[-5.9786138535,37.3951911926],"type":"Point"}
}