{
  "type": "Feature",
  "properties": {
    "iso:country":"ES",
    "sg:address":"Av Mossen Jaume Soler, 37",
    "sg:city":"Playa De Calafell",
    "sg:orig_category":"Supermercados Y Hipermercados",
    "sg:phone":"+34 977 69 12 43",
    "sg:postcode":"43820",
    "sg:province":"Tarragona",
    "wof:name":"Supermercats Ribetans S.l.",
    "wof:placetype":"venue"
},
  "geometry": {"coordinates":[1.5740669966,41.1893463135],"type":"Point"}
}