{
  "type": "Feature",
  "properties": {
    "addr:full":"Fca. Corralejo, S/n Aranjuez Madrid 28300",
    "addr:postcode":"28300",
    "addr:street":"S / N",
    "iso:country":"ES",
    "sg:address":"Fca. Corralejo, S/n",
    "sg:city":"Aranjuez",
    "sg:orig_category":"Agricultura: Abastecimiento Y Cosechado (negocio)",
    "sg:phone":"+34 918 94 92 11",
    "sg:postcode":"28300",
    "sg:province":"Madrid",
    "wof:name":"Aguila De Goicoechea Jose Maria Del",
    "wof:placetype":"venue"
},
  "geometry": {"coordinates":[-3.6521849632,39.9956932068],"type":"Point"}
}