{
  "type": "Feature",
  "properties": {
    "addr:full":"Calle de Menceyes, 5 Cruce De Arinaga Las Palmas 35118",
    "addr:housenumber":"5",
    "addr:postcode":"35118",
    "addr:street":"Calle De Menceyes",
    "iso:country":"ES",
    "sg:address":"Calle de Menceyes, 5",
    "sg:city":"Cruce De Arinaga",
    "sg:orig_category":"Peluquer\u00cdas, Peluquer\u00cda Mixta",
    "sg:phone":"+34 928 18 84 84",
    "sg:postcode":"35118",
    "sg:province":"Las Palmas",
    "wof:name":"Figueroa Herrera Olga Del Carmen",
    "wof:placetype":"venue"
},
  "geometry": {"coordinates":[-15.4269266129,27.8782348633],"type":"Point"}
}