{
  "type": "Feature",
  "properties": {
    "iso:country":"ES",
    "sg:address":"Calle de Musico Gines, 33",
    "sg:city":"Valencia",
    "sg:orig_category":"Arquitectos",
    "sg:phone":"+34 963 72 12 29",
    "sg:postcode":"46022",
    "sg:province":"Valencia",
    "wof:name":"Garcia-lliberos Sanchez-robles Jose",
    "wof:placetype":"venue"
},
  "geometry": {"coordinates":[-0.3426780105,39.4719085693],"type":"Point"}
}