{
  "type": "Feature",
  "properties": {
    "iso:country":"ES",
    "sg:address":"Cmno Silva, 20",
    "sg:city":"Cedeira",
    "sg:orig_category":"Peluquer\u00cdas, Peluquer\u00cda Mixta",
    "sg:phone":"+34 981 48 14 70",
    "sg:postcode":"15350",
    "sg:province":"La Coru\u00f1a",
    "wof:name":"Alonso Arrivi Bego\u00f1a",
    "wof:placetype":"venue"
},
  "geometry": {"coordinates":[-8.0505647659,43.66198349],"type":"Point"}
}