{
  "type": "Feature",
  "properties": {
    "iso:country":"ES",
    "sg:address":"Calle de Maseda, 4",
    "sg:city":"Madrid",
    "sg:orig_category":"Tapicer\u00cdas",
    "sg:phone":"+34 913 11 04 52",
    "sg:postcode":"28039",
    "sg:province":"Madrid",
    "wof:name":"Tapicerias Hellin S.l.",
    "wof:placetype":"venue"
},
  "geometry": {"coordinates":[-3.7065219879,40.4600028992],"type":"Point"}
}