{
  "type": "Feature",
  "properties": {
    "iso:country":"ES",
    "sg:address":"Plaz Espa\u00d1a, 7",
    "sg:city":"Burguillos Cerro",
    "sg:orig_category":"Farmacias",
    "sg:phone":"+34 924 54 12 05",
    "sg:postcode":"06370",
    "sg:province":"Badajoz",
    "wof:name":"Fernandez-salguero Salguero Carmen",
    "wof:placetype":"venue"
},
  "geometry": {"coordinates":[-6.5910739899,38.3806800842],"type":"Point"}
}