{
  "type": "Feature",
  "properties": {
    "addr:full":"Ctra Medellin, Km. 0095,0 Don Benito Badajoz 06400",
    "addr:postcode":"06400",
    "addr:street":"Ctra Medellin Km. 0095,0",
    "iso:country":"ES",
    "sg:address":"Ctra Medellin, Km. 0095,0",
    "sg:city":"Don Benito",
    "sg:orig_category":"Empresas De Carpinter\u00cda Met\u00c1lica",
    "sg:phone":"+34 924 80 57 54",
    "sg:postcode":"06400",
    "sg:province":"Badajoz",
    "sg:website":"www.ifex-guadiana.com",
    "wof:name":"Ifex-guadiana C.b.",
    "wof:placetype":"venue"
},
  "geometry": {"coordinates":[-5.8681616783,38.959400177],"type":"Point"}
}