{
  "type": "Feature",
  "properties": {
    "addr:full":"Calle de Godofredo Ortega Y Mu\u00d1oz, 48 Badajoz Badajoz 06011",
    "addr:housenumber":"48",
    "addr:postcode":"06011",
    "addr:street":"Calle De Godofredo Ortega Y Mun\u0303Oz",
    "iso:country":"ES",
    "sg:address":"Calle de Godofredo Ortega Y Mu\u00d1oz, 48",
    "sg:city":"Badajoz",
    "sg:orig_category":"Peluquer\u00cdas, Peluquer\u00cda Mixta",
    "sg:phone":"+34 924 24 68 08",
    "sg:postcode":"06011",
    "sg:province":"Badajoz",
    "wof:name":"Ortiz Velero Silvia",
    "wof:placetype":"venue"
},
  "geometry": {"coordinates":[-6.9857192039,38.8671607971],"type":"Point"}
}