{
  "type": "Feature",
  "properties": {
    "iso:country":"ES",
    "sg:address":"Avda Peris Y Valero, 42",
    "sg:city":"Valencia",
    "sg:orig_category":"Laboratorios Y Trabajos De Fotograf\u00cda, V\u00cddeo Y Cine",
    "sg:phone":"+34 963 33 38 26",
    "sg:postcode":"46006",
    "sg:province":"Valencia",
    "wof:name":"Xing  Yunchao",
    "wof:placetype":"venue"
},
  "geometry": {"coordinates":[-0.3745889962,39.4574279785],"type":"Point"}
}