{
  "type": "Feature",
  "properties": {
    "addr:full":"Calle de Larga, 38 Villarrasa Huelva 21850",
    "addr:housenumber":"38",
    "addr:postcode":"21850",
    "addr:street":"Calle De Larga",
    "iso:country":"ES",
    "sg:address":"Calle de Larga, 38",
    "sg:city":"Villarrasa",
    "sg:orig_category":"Empresas De Carpinter\u00cda De Madera",
    "sg:phone":"+34 959 41 90 65",
    "sg:postcode":"21850",
    "sg:province":"Huelva",
    "wof:name":"Alonso Ligero Guillermo Antonio",
    "wof:placetype":"venue"
},
  "geometry": {"coordinates":[-6.6317462921,37.3996543884],"type":"Point"}
}