{
  "type": "Feature",
  "properties": {
    "addr:full":"Avda Sierra (la), 55 Najera La Rioja 26300",
    "addr:housenumber":"55",
    "addr:postcode":"26300",
    "addr:street":"Avda Sierra La;Rioja",
    "iso:country":"ES",
    "sg:address":"Avda Sierra (la), 55",
    "sg:city":"Najera",
    "sg:orig_category":"Fabricaci\u00d3n, Venta De Cuadros, Accesorios Para Enmarcar",
    "sg:phone":"+34 941 36 14 21",
    "sg:postcode":"26300",
    "sg:province":"La Rioja",
    "wof:name":"Moldumar S.c",
    "wof:placetype":"venue"
},
  "geometry": {"coordinates":[-2.7274029255,42.414024353],"type":"Point"}
}