{
  "type": "Feature",
  "properties": {
    "addr:full":"Calle de Marcial Del Adalid, 21 Coru\u00d1a La Coru\u00f1a 15005",
    "addr:housenumber":"21",
    "addr:postcode":"15005",
    "addr:street":"Calle De Marcial Del Adalid;La Corun\u0303A",
    "iso:country":"ES",
    "sg:address":"Calle de Marcial Del Adalid, 21",
    "sg:city":"Coru\u00d1a",
    "sg:orig_category":"Farmacias",
    "sg:phone":"+34 981 23 22 08",
    "sg:postcode":"15005",
    "sg:province":"La Coru\u00f1a",
    "wof:name":"Rascon Negreira Pio",
    "wof:placetype":"venue"
},
  "geometry": {"coordinates":[-8.4078845978,43.3620834351],"type":"Point"}
}