{
  "type": "Feature",
  "properties": {
    "iso:country":"ES",
    "sg:address":"Calle de Francisco Lizaur, 9",
    "sg:city":"Brozas",
    "sg:orig_category":"Alimentaci\u00d3n General (al Por Menor)",
    "sg:phone":"+34 927 39 50 30",
    "sg:postcode":"10950",
    "sg:province":"C\u00e1ceres",
    "wof:name":"Qui\u00f1ones Santano Carlos Lorenzo",
    "wof:placetype":"venue"
},
  "geometry": {"coordinates":[-6.7778401375,39.6105384827],"type":"Point"}
}