{
  "type": "Feature",
  "properties": {
    "iso:country":"ES",
    "sg:address":"Crrd San Fernando, 34",
    "sg:city":"Ubeda",
    "sg:orig_category":"Abogados",
    "sg:phone":"+34 953 75 70 55",
    "sg:postcode":"23400",
    "sg:province":"Ja\u00e9n",
    "wof:name":"Cuadra Rodriguez Pedro Angel",
    "wof:placetype":"venue"
},
  "geometry": {"coordinates":[-3.3685760498,38.0115394592],"type":"Point"}
}