{
  "type": "Feature",
  "properties": {
    "addr:full":"Pase Ezequiel Gonzalez, 9 Segovia Segovia 40002",
    "addr:housenumber":"9",
    "addr:postcode":"40002",
    "addr:street":"Gonzalez",
    "iso:country":"ES",
    "sg:address":"Pase Ezequiel Gonzalez, 9",
    "sg:city":"Segovia",
    "sg:orig_category":"Molduras, Junquillos, Listones Y Molduras Perforadas",
    "sg:phone":"+34 921 46 11 97",
    "sg:postcode":"40002",
    "sg:province":"Segovia",
    "wof:name":"Sistelcom-telemensaje S.a.",
    "wof:placetype":"venue"
},
  "geometry": {"coordinates":[-4.1234607697,40.9463195801],"type":"Point"}
}