{
  "type": "Feature",
  "properties": {
    "iso:country":"ES",
    "sg:address":"Avda Andalucia, 41",
    "sg:city":"Peal Becerro",
    "sg:orig_category":"Quincaller\u00cda (al Por Menor)",
    "sg:phone":"+34 953 71 62 80",
    "sg:postcode":"23460",
    "sg:province":"Ja\u00e9n",
    "wof:name":"Alcazar Lopez Pedro",
    "wof:placetype":"venue"
},
  "geometry": {"coordinates":[-3.1172618866,37.9136886597],"type":"Point"}
}