{
  "type": "Feature",
  "properties": {
    "iso:country":"ES",
    "sg:address":"Franch, 20",
    "sg:city":"Pobla Cervoles",
    "sg:orig_category":"Agricultura: Abastecimiento Y Cosechado (negocio)",
    "sg:phone":"+34 973 17 51 07",
    "sg:postcode":"25471",
    "sg:province":"Lleida",
    "wof:name":"Gili Fernandez Fernando",
    "wof:placetype":"venue"
},
  "geometry": {"coordinates":[0.9142799973,41.3669586182],"type":"Point"}
}