{
  "type": "Feature",
  "properties": {
    "iso:country":"ES",
    "sg:address":"Rua Venezuela, 27",
    "sg:city":"Vigo",
    "sg:orig_category":"Medicamentos",
    "sg:phone":"+34 986 47 09 37",
    "sg:postcode":"36203",
    "sg:province":"Pontevedra",
    "wof:name":"Lopez Martinez Maria Luz",
    "wof:placetype":"venue"
},
  "geometry": {"coordinates":[-8.7202501297,42.2331848145],"type":"Point"}
}