{
  "type": "Feature",
  "properties": {
    "addr:full":"Av Baix Camp, 20 Cambrils Tarragona 43850",
    "addr:housenumber":"20",
    "addr:postcode":"43850",
    "addr:street":"Av Baix Camp",
    "iso:country":"ES",
    "sg:address":"Av Baix Camp, 20",
    "sg:city":"Cambrils",
    "sg:orig_category":"Zapater\u00cdas",
    "sg:phone":"+34 977 79 39 39",
    "sg:postcode":"43850",
    "sg:province":"Tarragona",
    "wof:name":"Vazquez Vazquez Josefa",
    "wof:placetype":"venue"
},
  "geometry": {"coordinates":[1.0526549816,41.0714645386],"type":"Point"}
}