{
  "type": "Feature",
  "properties": {
    "addr:full":"Calle de Isaac Peral, 14 S. Fernando C\u00e1diz 11100",
    "addr:housenumber":"14",
    "addr:postcode":"11100",
    "addr:street":"Calle De Isaac Peral;S. Fernando Ca\u0301Diz",
    "iso:country":"ES",
    "sg:address":"Calle de Isaac Peral, 14",
    "sg:city":"S. Fernando",
    "sg:orig_category":"Administradores De Bienes Y Delegados De Comunidades De Propietarios",
    "sg:phone":"+34 956 88 59 42",
    "sg:postcode":"11100",
    "sg:province":"C\u00e1diz",
    "wof:name":"Roca Jimenez Carlos Manuel",
    "wof:placetype":"venue"
},
  "geometry": {"coordinates":[-6.199570179,36.4653663635],"type":"Point"}
}