{
  "type": "Feature",
  "properties": {
    "addr:full":"Calle de Malaga, 2 Javea Alicante 03730",
    "addr:housenumber":"2",
    "addr:postcode":"03730",
    "addr:street":"Calle De Malaga",
    "iso:country":"ES",
    "sg:address":"Calle de Malaga, 2",
    "sg:city":"Javea",
    "sg:classifiers":[
        {
            "category":"Professional",
            "subcategory":"Management & Consulting",
            "type":"Services"
        }
    ],
    "sg:phone":"+34 965 79 53 30",
    "sg:postcode":"03730",
    "sg:province":"Alicante",
    "sg:tags":[
        "asesor\u00cda",
        "en",
        "marketing"
    ],
    "wof:name":"Grant  Charlie",
    "wof:placetype":"venue"
},
  "geometry": {"coordinates":[0.1498380005,38.7920303345],"type":"Point"}
}