{
  "type": "Feature",
  "properties": {
    "addr:full":"Avda Quel, 58 Arnedo La Rioja 26580",
    "addr:housenumber":"58",
    "addr:postcode":"26580",
    "addr:street":"Avda Quel;Rioja",
    "iso:country":"ES",
    "sg:address":"Avda Quel, 58",
    "sg:city":"Arnedo",
    "sg:orig_category":"Confecci\u00d3n De Zapatos",
    "sg:phone":"+34 941 38 43 84",
    "sg:postcode":"26580",
    "sg:province":"La Rioja",
    "wof:name":"Pakulas S.l.",
    "wof:placetype":"venue"
},
  "geometry": {"coordinates":[-2.0872631073,42.2298583984],"type":"Point"}
}