{
  "type": "Feature",
  "properties": {
    "addr:full":"Calle de Baratzategi, 48 Donostia-san Sebastian Guip\u00f9zcoa 20015",
    "addr:housenumber":"48",
    "addr:postcode":"20015",
    "addr:street":"Calle De Baratzategi",
    "iso:country":"ES",
    "sg:address":"Calle de Baratzategi, 48",
    "sg:city":"Donostia-san Sebastian",
    "sg:orig_category":"Alimentaci\u00d3n General (al Por Menor)",
    "sg:phone":"+34 943 29 72 68",
    "sg:postcode":"20015",
    "sg:province":"Guip\u00f9zcoa",
    "wof:name":"Gp-kemen Producciones, S.l.",
    "wof:placetype":"venue"
},
  "geometry": {"coordinates":[-1.9509757757,43.3129119873],"type":"Point"}
}