{
  "type": "Feature",
  "properties": {
    "iso:country":"ES",
    "sg:address":"Calle de Jerico, 14",
    "sg:city":"Parla",
    "sg:orig_category":"Molduras, Junquillos, Listones Y Molduras Perforadas",
    "sg:phone":"+34 916 05 01 82",
    "sg:postcode":"28980",
    "sg:province":"Madrid",
    "wof:name":"Carretero Pavon Alejandro",
    "wof:placetype":"venue"
},
  "geometry": {"coordinates":[-3.7755799294,40.2364234924],"type":"Point"}
}