{
  "type": "Feature",
  "properties": {
    "iso:country":"ES",
    "sg:address":"Calle de Sabino Arana, 6",
    "sg:city":"Santurtzi",
    "sg:orig_category":"M\u00c9dicos: Estomatolog\u00cda",
    "sg:phone":"+34 944 61 80 18",
    "sg:postcode":"48980",
    "sg:province":"Vizcaya",
    "wof:name":"Juan Carlos Cotano Casalod",
    "wof:placetype":"venue"
},
  "geometry": {"coordinates":[-3.0339169502,43.32995224],"type":"Point"}
}