{
  "type": "Feature",
  "properties": {
    "addr:full":"Ptda Valverde Bajo, 51 Valverde Alicante 03139",
    "addr:housenumber":"51",
    "addr:postcode":"03139",
    "addr:street":"Ptda Valverde Bajo",
    "iso:country":"ES",
    "sg:address":"Ptda Valverde Bajo, 51",
    "sg:city":"Valverde",
    "sg:orig_category":"Plomeros",
    "sg:phone":"+34 966 63 82 00",
    "sg:postcode":"03139",
    "sg:province":"Alicante",
    "wof:name":"Fontaneria Marco Mas S.l.",
    "wof:placetype":"venue"
},
  "geometry": {"coordinates":[-0.5954089761,38.2363204956],"type":"Point"}
}