{
  "type": "Feature",
  "properties": {
    "addr:full":"Calle de Cristo De La Epidemia, 60 Malaga M\u00e1laga 29013",
    "addr:housenumber":"60",
    "addr:postcode":"29013",
    "addr:street":"Calle De Cristo De La Epidemia;Ma\u0301Laga",
    "iso:country":"ES",
    "sg:address":"Calle de Cristo De La Epidemia, 60",
    "sg:city":"Malaga",
    "sg:orig_category":"Frutas, Legumbres Frescas Y Tempranas (al Por Menor)",
    "sg:phone":"+34 952 25 15 40",
    "sg:postcode":"29013",
    "sg:province":"M\u00e1laga",
    "wof:name":"Gomez Holgado Maria Del Carmen",
    "wof:placetype":"venue"
},
  "geometry": {"coordinates":[-4.4149804115,36.7303352356],"type":"Point"}
}