{
  "type": "Feature",
  "properties": {
    "addr:full":"Calle de San Cristobal, 43 Puente-genil C\u00f3rdoba 14500",
    "addr:housenumber":"43",
    "addr:postcode":"14500",
    "addr:street":"Calle De San Cristobal;Co\u0301Rdoba",
    "iso:country":"ES",
    "sg:address":"Calle de San Cristobal, 43",
    "sg:city":"Puente-genil",
    "sg:orig_category":"Agencias De Viajes",
    "sg:phone":"+34 957 60 13 13",
    "sg:postcode":"14500",
    "sg:province":"C\u00f3rdoba",
    "wof:name":"Viajes Munda S.l.",
    "wof:placetype":"venue"
},
  "geometry": {"coordinates":[-4.7711658478,37.3893280029],"type":"Point"}
}