{
  "type": "Feature",
  "properties": {
    "addr:full":"Calle de Melchor Fernandez Almagro, 58 Madrid Madrid 28029",
    "addr:housenumber":"58",
    "addr:postcode":"madrid;28029",
    "addr:street":"Calle De Melchor Fernandez Almagro",
    "iso:country":"ES",
    "sg:address":"Calle de Melchor Fernandez Almagro, 58",
    "sg:city":"Madrid",
    "sg:orig_category":"Poller\u00cda Y Caza (al Por Menor)",
    "sg:phone":"+34 917 30 83 79",
    "sg:postcode":"28029",
    "sg:province":"Madrid",
    "wof:name":"Dolado Fernandez Rafael",
    "wof:placetype":"venue"
},
  "geometry": {"coordinates":[-3.7063219547,40.4764518738],"type":"Point"}
}