{
  "type": "Feature",
  "properties": {
    "addr:full":"Ctra San Juan, 31 Valverde Camino Huelva 21600",
    "addr:housenumber":"31",
    "addr:postcode":"21600",
    "addr:street":"Ctra San Juan;Camino Huelva",
    "iso:country":"ES",
    "sg:address":"Ctra San Juan, 31",
    "sg:city":"Valverde Camino",
    "sg:orig_category":"Veh\u00cdculos De Ocasi\u00d3n",
    "sg:phone":"+34 959 55 24 52",
    "sg:postcode":"21600",
    "sg:province":"Huelva",
    "wof:name":"Valmotor 2005 S.l.",
    "wof:placetype":"venue"
},
  "geometry": {"coordinates":[-6.7534661293,37.576335907],"type":"Point"}
}