{
  "type": "Feature",
  "properties": {
    "iso:country":"ES",
    "sg:address":"Calle de Bernardo Balbuena, 2",
    "sg:city":"Ciudad Real",
    "sg:orig_category":"Ropa Para Caballeros (al Por Menor)",
    "sg:phone":"+34 926 21 29 63",
    "sg:postcode":"13002",
    "sg:province":"Ciudad Real",
    "wof:name":"Recuero Recuero Angel",
    "wof:placetype":"venue"
},
  "geometry": {"coordinates":[-3.9327144623,38.9839782715],"type":"Point"}
}