{
  "type": "Feature",
  "properties": {
    "addr:full":"Pol. Ind. La Curiscada, S/n Sta Eulalia Asturias 33877",
    "addr:housenumber":"s / n",
    "addr:postcode":"33877",
    "addr:street":"Sta Eulalia Asturias",
    "iso:country":"ES",
    "sg:address":"Pol. Ind. La Curiscada, S/n",
    "sg:city":"Sta Eulalia",
    "sg:orig_category":"Madera Para Construcci\u00d3n E Industria",
    "sg:phone":"+34 985 90 07 47",
    "sg:postcode":"33877",
    "sg:province":"Asturias",
    "wof:name":"Aserradores De Madera Fernandez S.l.",
    "wof:placetype":"venue"
},
  "geometry": {"coordinates":[-5.9832577705,43.2504386902],"type":"Point"}
}