{
  "type": "Feature",
  "properties": {
    "iso:country":"ES",
    "sg:address":"Calle de Avenida De Bijues, S/n",
    "sg:city":"Lumbier",
    "sg:orig_category":"Hoteles",
    "sg:phone":"+34 948 88 04 35",
    "sg:postcode":"31440",
    "sg:province":"Navarra",
    "wof:name":"Leoz Etxe S.l.",
    "wof:placetype":"venue"
},
  "geometry": {"coordinates":[-1.2987349033,42.6513710022],"type":"Point"}
}