{
  "type": "Feature",
  "properties": {
    "addr:full":"Afores, S/n Arbucies Girona 17401",
    "addr:housenumber":"s / n",
    "addr:postcode":"17401",
    "addr:street":"Afores",
    "iso:country":"ES",
    "sg:address":"Afores, S/n",
    "sg:city":"Arbucies",
    "sg:orig_category":"Servicios Diversos",
    "sg:phone":"+34 972 86 09 87",
    "sg:postcode":"17401",
    "sg:province":"Girona",
    "wof:name":"Carbonell Masso Maria",
    "wof:placetype":"venue"
},
  "geometry": {"coordinates":[2.518239975,41.8144645691],"type":"Point"}
}