{
  "type": "Feature",
  "properties": {
    "addr:full":"Mayor, 13 Sada Navarra 31491",
    "addr:housenumber":"13",
    "addr:postcode":"31491",
    "addr:street":"Mayor",
    "iso:country":"ES",
    "sg:address":"Mayor, 13",
    "sg:city":"Sada",
    "sg:orig_category":"Agencias Y Agentes Comerciales, Representantes",
    "sg:phone":"+34 948 87 70 44",
    "sg:postcode":"31491",
    "sg:province":"Navarra",
    "wof:name":"Otazu Orduna S.l.",
    "wof:placetype":"venue"
},
  "geometry": {"coordinates":[-97.78224945069999,45.7040786743],"type":"Point"}
}