{
  "type": "Feature",
  "properties": {
    "addr:full":"Calle de Breton De Los Herreros, 39 Madrid Madrid 28003",
    "addr:housenumber":"39",
    "addr:postcode":"madrid;28003",
    "addr:street":"Calle De Breton De Los Herreros",
    "iso:country":"ES",
    "sg:address":"Calle de Breton De Los Herreros, 39",
    "sg:city":"Madrid",
    "sg:orig_category":"Centros Empresariales",
    "sg:phone":"+34 913 95 01 03",
    "sg:postcode":"28003",
    "sg:province":"Madrid",
    "wof:name":"Breton Xxxix S.l.",
    "wof:placetype":"venue"
},
  "geometry": {"coordinates":[-3.6970710754,40.4395103455],"type":"Point"}
}