{
  "type": "Feature",
  "properties": {
    "iso:country":"ES",
    "sg:address":"Ptda Fuente Negra, S/n",
    "sg:city":"Anna",
    "sg:orig_category":"Congelados: Productos Alimentarios (al Por Menor)",
    "sg:phone":"+34 962 21 00 12",
    "sg:postcode":"46820",
    "sg:province":"Valencia",
    "wof:name":"Distribuciones Mucarmy S. L.",
    "wof:placetype":"venue"
},
  "geometry": {"coordinates":[-0.6493399739,39.0253372192],"type":"Point"}
}