{
  "type": "Feature",
  "properties": {
    "iso:country":"ES",
    "sg:address":"Iglesia, 2",
    "sg:city":"Igrexa",
    "sg:orig_category":"Art\u00cdculos Funerarios (al Por Menor)",
    "sg:phone":"+34 982 14 62 50",
    "sg:postcode":"27751",
    "sg:province":"Lugo",
    "wof:name":"Gayoso Rodriguez Maria Remedios",
    "wof:placetype":"venue"
},
  "geometry": {"coordinates":[-7.2695918083,43.4194831848],"type":"Point"}
}