{
  "type": "Feature",
  "properties": {
    "iso:country":"ES",
    "sg:address":"Ctra Granada (de), Km. 0266,9",
    "sg:city":"San Jose",
    "sg:orig_category":"Contenedores (mercanc\u00cdas)",
    "sg:phone":"+34 968 46 33 24",
    "sg:postcode":"30800",
    "sg:province":"Murcia",
    "sg:website":"www.transportesalcaraz.com",
    "wof:name":"Hermanos Alcaraz Torroglosa S.a.",
    "wof:placetype":"venue"
},
  "geometry": {"coordinates":[-1.6905640364,37.680557251],"type":"Point"}
}