{
  "type": "Feature",
  "properties": {
    "iso:country":"ES",
    "sg:address":"Calle de Febrero, 70",
    "sg:city":"Madrid",
    "sg:orig_category":"Arquitectos",
    "sg:phone":"+34 913 03 11 00",
    "sg:postcode":"28022",
    "sg:province":"Madrid",
    "wof:name":"Proyeco S.a.",
    "wof:placetype":"venue"
},
  "geometry": {"coordinates":[-3.5636041164,40.4465637207],"type":"Point"}
}