{
  "type": "Feature",
  "properties": {
    "addr:full":"Poligono Industrial, 1 Andosilla Navarra 31261",
    "addr:postcode":"31261",
    "addr:street":"Industrial",
    "iso:country":"ES",
    "sg:address":"Poligono Industrial, 1",
    "sg:city":"Andosilla",
    "sg:orig_category":"Caf\u00c9s, Bares, Cervecer\u00cdas",
    "sg:phone":"+34 948 69 01 56",
    "sg:postcode":"31261",
    "sg:province":"Navarra",
    "wof:name":"Asador Restaurante Sector 5 S.l.",
    "wof:placetype":"venue"
},
  "geometry": {"coordinates":[-1.9425271749,42.3631439209],"type":"Point"}
}