{
  "type": "Feature",
  "properties": {
    "iso:country":"ES",
    "sg:address":"Ctra. Caceres, S/n",
    "sg:city":"Brozas",
    "sg:orig_category":"Asilos De Ancianos. Centros Privados",
    "sg:phone":"+34 927 39 50 23",
    "sg:postcode":"10950",
    "sg:province":"C\u00e1ceres",
    "wof:name":"Residencia Nuestro Hogar Condesa De La Encina",
    "wof:placetype":"venue"
},
  "geometry": {"coordinates":[-6.7763600349,39.6160469055],"type":"Point"}
}