{
  "type": "Feature",
  "properties": {
    "iso:country":"ES",
    "sg:address":"Calle de Rafael Fernandez, 3",
    "sg:city":"Oviedo",
    "sg:orig_category":"Organismos De Reclutamiento",
    "sg:phone":"+34 985 22 76 45",
    "sg:postcode":"33008",
    "sg:province":"Asturias",
    "wof:name":"Prieto Fernandez Jose Luis",
    "wof:placetype":"venue"
},
  "geometry": {"coordinates":[-5.8363399506,43.3554992676],"type":"Point"}
}