{
  "type": "Feature",
  "properties": {
    "addr:full":"Carr Ferrocarril D'alcoi, 37 Gandia Valencia 46700",
    "addr:housenumber":"37",
    "addr:postcode":"46700",
    "addr:street":"Carr Ferrocarril D'Alcoi;Valencia",
    "iso:country":"ES",
    "sg:address":"Carr Ferrocarril D'alcoi, 37",
    "sg:city":"Gandia",
    "sg:orig_category":"Promotores Constructores",
    "sg:phone":"+34 962 87 89 54",
    "sg:postcode":"46700",
    "sg:province":"Valencia",
    "wof:name":"Grupo Inmobiliario 2002 S.l.",
    "wof:placetype":"venue"
},
  "geometry": {"coordinates":[-0.1852419972,38.9650650024],"type":"Point"}
}