{
  "type": "Feature",
  "properties": {
    "iso:country":"ES",
    "sg:address":"Calle de Don Prudencio Verdejo, 16",
    "sg:city":"Villanubla",
    "sg:orig_category":"Forjas Y Altos Hornos",
    "sg:phone":"+34 983 56 00 48",
    "sg:postcode":"47620",
    "sg:province":"Valladolid",
    "wof:name":"Martinez Rodriguez Justino",
    "wof:placetype":"venue"
},
  "geometry": {"coordinates":[-4.8405785561,41.6982650757],"type":"Point"}
}