{
  "type": "Feature",
  "properties": {
    "iso:country":"ES",
    "sg:address":"Calle de Puerto, 62",
    "sg:city":"Toledo",
    "sg:orig_category":"Centros De Educaci\u00d3n Especial",
    "sg:phone":"+34 925 22 13 87",
    "sg:postcode":"45006",
    "sg:province":"Toledo",
    "wof:name":"Colegio Publico Angel Del Alcazar",
    "wof:placetype":"venue"
},
  "geometry": {"coordinates":[-4.0077991486,39.8597297668],"type":"Point"}
}