{
  "type": "Feature",
  "properties": {
    "iso:country":"ES",
    "sg:address":"Carrer de Mare Molas, 27",
    "sg:city":"Reus",
    "sg:orig_category":"Farmacias",
    "sg:phone":"+34 977 31 10 47",
    "sg:postcode":"43202",
    "sg:province":"Tarragona",
    "wof:name":"Butille Ferre Mercedes",
    "wof:placetype":"venue"
},
  "geometry": {"coordinates":[1.1011630297,41.1514091492],"type":"Point"}
}