{
  "type": "Feature",
  "properties": {
    "iso:country":"ES",
    "sg:address":"Calle de Camara La, 42",
    "sg:city":"Aviles",
    "sg:orig_category":"Abogados",
    "sg:phone":"+34 985 56 75 19",
    "sg:postcode":"33401",
    "sg:province":"Asturias",
    "wof:name":"Llamas Rodriguez Maria Eugenia",
    "wof:placetype":"venue"
},
  "geometry": {"coordinates":[-5.9250044823,43.5591812134],"type":"Point"}
}