{
  "type": "Feature",
  "properties": {
    "addr:full":"Calle de Autonomia, 8 Donostia-san Sebastian Guip\u00f9zcoa 20006",
    "addr:housenumber":"8",
    "addr:postcode":"20006",
    "addr:street":"Calle De Autonomia",
    "iso:country":"ES",
    "sg:address":"Calle de Autonomia, 8",
    "sg:city":"Donostia-san Sebastian",
    "sg:orig_category":"Pod\u00d3logos: Pedicuros",
    "sg:phone":"+34 943 47 40 72",
    "sg:postcode":"20006",
    "sg:province":"Guip\u00f9zcoa",
    "wof:name":"Sara Mujika Mendiola Y Otra C.b.",
    "wof:placetype":"venue"
},
  "geometry": {"coordinates":[-1.9822249413,43.3131637573],"type":"Point"}
}