{
  "type": "Feature",
  "properties": {
    "addr:full":"Calle de Obispo Estenaga, 6 Ciudad Real Ciudad Real 13002",
    "addr:housenumber":"6",
    "addr:postcode":"13002",
    "addr:street":"Calle De Obispo Estenaga",
    "iso:country":"ES",
    "sg:address":"Calle de Obispo Estenaga, 6",
    "sg:city":"Ciudad Real",
    "sg:orig_category":"Cr\u00cda De Animales",
    "sg:phone":"+34 926 21 25 19",
    "sg:postcode":"13002",
    "sg:province":"Ciudad Real",
    "wof:name":"Torrecilla Y Albala S.a.",
    "wof:placetype":"venue"
},
  "geometry": {"coordinates":[-3.9318039417,38.9839477539],"type":"Point"}
}