{
  "type": "Feature",
  "properties": {
    "addr:full":"Cllo Pajarillo Verde, 1 Malaga M\u00e1laga 29190",
    "addr:postcode":"29190",
    "addr:street":"Ma\u0301Laga",
    "iso:country":"ES",
    "sg:address":"Cllo Pajarillo Verde, 1",
    "sg:city":"Malaga",
    "sg:orig_category":"Asesor\u00cda Fiscal Y Jur\u00cddica",
    "sg:phone":"+34 952 43 24 98",
    "sg:postcode":"29190",
    "sg:province":"M\u00e1laga",
    "wof:name":"Asesoria Y Seguros Puerto De La Torre S.l.",
    "wof:placetype":"venue"
},
  "geometry": {"coordinates":[-4.5025129318,36.7206001282],"type":"Point"}
}