{
  "type": "Feature",
  "properties": {
    "iso:country":"ES",
    "sg:address":"Playa Lagoa, 3",
    "sg:city":"Valdecaba\u00f1as",
    "sg:orig_category":"Inmobiliaria (agencias)",
    "sg:phone":"+34 916 33 33 50",
    "sg:postcode":"28669",
    "sg:province":"Madrid",
    "wof:name":"Promociones Nemesio Tomas S.a.",
    "wof:placetype":"venue"
},
  "geometry": {"coordinates":[-3.8833069801,40.443775177],"type":"Point"}
}