{
  "type": "Feature",
  "properties": {
    "addr:full":"Pase Casta\u00d1os (los), 11 Aguadulce Almer\u00eda 04720",
    "addr:postcode":"04720",
    "addr:street":"Los;Almeri\u0301A",
    "iso:country":"ES",
    "sg:address":"Pase Casta\u00d1os (los), 11",
    "sg:city":"Aguadulce",
    "sg:orig_category":"Abogados",
    "sg:phone":"+34 950 34 82 48",
    "sg:postcode":"04720",
    "sg:province":"Almer\u00eda",
    "wof:name":"Davies  Michael John",
    "wof:placetype":"venue"
},
  "geometry": {"coordinates":[-2.5974500179,36.801410675],"type":"Point"}
}