{
  "type": "Feature",
  "properties": {
    "iso:country":"ES",
    "sg:address":"Calle de San Diego, 6",
    "sg:city":"Sestao",
    "sg:orig_category":"Molduras, Junquillos, Listones Y Molduras Perforadas",
    "sg:phone":"+34 944 96 31 27",
    "sg:postcode":"48910",
    "sg:province":"Vizcaya",
    "wof:name":"Bock C.b",
    "wof:placetype":"venue"
},
  "geometry": {"coordinates":[-3.0063309669,43.3097419739],"type":"Point"}
}