{
  "type": "Feature",
  "properties": {
    "addr:full":"Guzman, 26 Vall Uixo Castell\u00f3n 12600",
    "addr:housenumber":"26",
    "addr:postcode":"12600",
    "addr:street":"Guzman;Castello\u0301N",
    "iso:country":"ES",
    "sg:address":"Guzman, 26",
    "sg:city":"Vall Uixo",
    "sg:orig_category":"T\u00c9cnicos Veterinarios",
    "sg:phone":"+34 964 69 00 91",
    "sg:postcode":"12600",
    "sg:province":"Castell\u00f3n",
    "wof:name":"Murria Molina Maria Soledad",
    "wof:placetype":"venue"
},
  "geometry": {"coordinates":[-0.2315589935,39.8232955933],"type":"Point"}
}