{
  "type": "Feature",
  "properties": {
    "addr:full":"Carrer de Gran Via De Lluis Companys, 101 Premia Mar Barcelona 08330",
    "addr:housenumber":"101",
    "addr:postcode":"08330",
    "addr:street":"Carrer De Gran Via De Lluis Companys",
    "iso:country":"ES",
    "sg:address":"Carrer de Gran Via De Lluis Companys, 101",
    "sg:city":"Premia Mar",
    "sg:orig_category":"Inmobiliaria (agencias)",
    "sg:phone":"+34 937 52 26 03",
    "sg:postcode":"08330",
    "sg:province":"Barcelona",
    "wof:name":"Inversiones Premia S.l.",
    "wof:placetype":"venue"
},
  "geometry": {"coordinates":[2.353110075,41.4906196594],"type":"Point"}
}