{
  "type": "Feature",
  "properties": {
    "iso:country":"ES",
    "sg:address":"Ptda Pla De La Vallonga, S/n",
    "sg:city":"Pla De La Vallonga",
    "sg:orig_category":"Comercio De Piezas De Recambio Y De Accesorios De Veh\u00cdculos, Veh\u00cdculos Industriales",
    "sg:phone":"+34 965 11 27 84",
    "sg:postcode":"03113",
    "sg:province":"Alicante",
    "wof:name":"Auto-recambios Vicente S.a.",
    "wof:placetype":"venue"
},
  "geometry": {"coordinates":[-0.5904179811,38.3435401917],"type":"Point"}
}