{
  "type": "Feature",
  "properties": {
    "addr:full":"Calle de Maestro Vives, 8 Castellon Castell\u00f3n 12005",
    "addr:housenumber":"8",
    "addr:postcode":"12005",
    "addr:street":"Calle De Maestro Vives",
    "iso:country":"ES",
    "sg:address":"Calle de Maestro Vives, 8",
    "sg:city":"Castellon",
    "sg:orig_category":"Peluqueros: De Se\u00d1oras",
    "sg:phone":"+34 964 22 30 17",
    "sg:postcode":"12005",
    "sg:province":"Castell\u00f3n",
    "wof:name":"Gomez Albalate Maria Jose",
    "wof:placetype":"venue"
},
  "geometry": {"coordinates":[-0.0353580005,39.9812545776],"type":"Point"}
}