{
  "type": "Feature",
  "properties": {
    "iso:country":"ES",
    "sg:address":"Carrer de Mallorca, 214",
    "sg:city":"Barcelona",
    "sg:orig_category":"Jefes De Obra Y Construcciones",
    "sg:phone":"+34 934 54 67 07",
    "sg:postcode":"08008",
    "sg:province":"Barcelona",
    "wof:name":"Assessors De Construccio Associats S. A.",
    "wof:placetype":"venue"
},
  "geometry": {"coordinates":[2.1587717533,41.3909645081],"type":"Point"}
}