{
  "type": "Feature",
  "properties": {
    "addr:full":"Calle de Tafur, 39 Villafranca Cordoba C\u00f3rdoba 14420",
    "addr:housenumber":"39",
    "addr:postcode":"14420",
    "addr:street":"Calle De Tafur",
    "iso:country":"ES",
    "sg:address":"Calle de Tafur, 39",
    "sg:city":"Villafranca Cordoba",
    "sg:orig_category":"Supermercados Y Hipermercados",
    "sg:phone":"+34 957 19 00 96",
    "sg:postcode":"14420",
    "sg:province":"C\u00f3rdoba",
    "wof:name":"Casa Ponce S.l.",
    "wof:placetype":"venue"
},
  "geometry": {"coordinates":[-4.5466070175,37.9645347595],"type":"Point"}
}