{
  "type": "Feature",
  "properties": {
    "iso:country":"ES",
    "sg:address":"Calle de Portillo Del Prado, 17",
    "sg:city":"Valladolid",
    "sg:orig_category":"Ferreter\u00cda (diversos)",
    "sg:phone":"+34 983 26 20 38",
    "sg:postcode":"47011",
    "sg:province":"Valladolid",
    "wof:name":"Ruiz Placer Gerardo",
    "wof:placetype":"venue"
},
  "geometry": {"coordinates":[-4.7158169746,41.6594772339],"type":"Point"}
}