{
  "type": "Feature",
  "properties": {
    "iso:country":"ES",
    "sg:address":"Calle de Duquesa De La Victoria, 8",
    "sg:city":"Logro\u00f1o",
    "sg:orig_category":"Doctores En Medicina",
    "sg:phone":"+34 941 26 14 11",
    "sg:postcode":"26003",
    "sg:province":"La Rioja",
    "wof:name":"De La Villa Vela Alberto",
    "wof:placetype":"venue"
},
  "geometry": {"coordinates":[-2.4426379204,42.4649925232],"type":"Point"}
}