{
  "type": "Feature",
  "properties": {
    "iso:country":"ES",
    "sg:address":"Barr Barrataguren, 8",
    "sg:city":"Artziniega",
    "sg:orig_category":"Alimentaci\u00d3n General (al Por Menor)",
    "sg:phone":"+34 945 39 61 85",
    "sg:postcode":"01474",
    "sg:province":"\u00c1lava",
    "sg:website":"www.quesosibar.com",
    "wof:name":"Quesos Ibar S.l.",
    "wof:placetype":"venue"
},
  "geometry": {"coordinates":[-3.1292920113,43.122543335],"type":"Point"}
}