{
  "type": "Feature",
  "properties": {
    "addr:full":"Rier Escuder, 9 Barcelona Barcelona 08028",
    "addr:housenumber":"9",
    "addr:postcode":"08028",
    "addr:street":"Rier Escuder",
    "iso:country":"ES",
    "sg:address":"Rier Escuder, 9",
    "sg:city":"Barcelona",
    "sg:orig_category":"Centro De Estudios",
    "sg:phone":"+34 934 11 14 81",
    "sg:postcode":"08028",
    "sg:province":"Barcelona",
    "wof:name":"Monje Gil Francisco Javier",
    "wof:placetype":"venue"
},
  "geometry": {"coordinates":[2.1326150894,41.374332428],"type":"Point"}
}