{
  "type": "Feature",
  "properties": {
    "iso:country":"ES",
    "sg:address":"De La Plaza, 15",
    "sg:city":"Iniesta",
    "sg:orig_category":"Molduras, Junquillos, Listones Y Molduras Perforadas",
    "sg:phone":"+34 967 49 12 24",
    "sg:postcode":"16235",
    "sg:province":"Cuenca",
    "wof:name":"Huerta Cruz Ana Belen",
    "wof:placetype":"venue"
},
  "geometry": {"coordinates":[-1.7489440441,39.4435081482],"type":"Point"}
}