{
  "type": "Feature",
  "properties": {
    "iso:country":"ES",
    "sg:address":"Calle de Alcalde Jose Ramirez Bethencourt, 51",
    "sg:city":"Burrero",
    "sg:orig_category":"Quincaller\u00cda (al Por Menor)",
    "sg:phone":"+34 928 73 85 69",
    "sg:postcode":"35240",
    "sg:province":"Las Palmas",
    "wof:name":"Gonzalez Ojeda Basilio",
    "wof:placetype":"venue"
},
  "geometry": {"coordinates":[-15.3884372711,27.9077167511],"type":"Point"}
}