{
  "type": "Feature",
  "properties": {
    "iso:country":"ES",
    "sg:address":"Calle de Gravina, 13",
    "sg:city":"Sevilla",
    "sg:orig_category":"Psicoterapeutas",
    "sg:phone":"+34 954 22 64 18",
    "sg:postcode":"41001",
    "sg:province":"Sevilla",
    "wof:name":"Rivas Martinez Manuel",
    "wof:placetype":"venue"
},
  "geometry": {"coordinates":[-6.0009989738,37.392364502],"type":"Point"}
}