{
  "type": "Feature",
  "properties": {
    "iso:country":"ES",
    "sg:address":"Calle de Ibarra, 24",
    "sg:city":"Elorrio",
    "sg:orig_category":"Plomeros",
    "sg:phone":"+34 946 23 14 34",
    "sg:postcode":"48230",
    "sg:province":"Vizcaya",
    "wof:name":"Eugenio Herreros Bernalte",
    "wof:placetype":"venue"
},
  "geometry": {"coordinates":[-2.5488090515,43.1323204041],"type":"Point"}
}