{
  "type": "Feature",
  "properties": {
    "iso:country":"ES",
    "sg:address":"Calle de Real De Arriba, 107",
    "sg:city":"Valverde Camino",
    "sg:orig_category":"Zapater\u00cdas",
    "sg:phone":"+34 959 55 04 64",
    "sg:postcode":"21600",
    "sg:province":"Huelva",
    "wof:name":"Calzados Bermejo Gonzalez S.l.",
    "wof:placetype":"venue"
},
  "geometry": {"coordinates":[-6.7525081635,37.5771446228],"type":"Point"}
}