{
  "type": "Feature",
  "properties": {
    "iso:country":"ES",
    "sg:address":"Carr Jaume Ii, S/n",
    "sg:city":"Bisbal D'emporda",
    "sg:orig_category":"Deportes N\u00c1uticos, Acu\u00c1ticos Y Subacu\u00c1ticos: Art\u00cdculos Y Equipo (al Por Menor)",
    "sg:phone":"+34 972 64 24 52",
    "sg:postcode":"17100",
    "sg:province":"Girona",
    "wof:name":"Comercial Caproig S.l.",
    "wof:placetype":"venue"
},
  "geometry": {"coordinates":[2.813131094,41.9749221802],"type":"Point"}
}