{
  "type": "Feature",
  "properties": {
    "addr:full":"Calle de Pedro De Lorenzo, 4 Plasencia C\u00e1ceres 10600",
    "addr:housenumber":"4",
    "addr:postcode":"10600",
    "addr:street":"Calle De Pedro De Lorenzo;Ca\u0301Ceres",
    "iso:country":"ES",
    "sg:address":"Calle de Pedro De Lorenzo, 4",
    "sg:city":"Plasencia",
    "sg:orig_category":"Parques De Atracciones Y Centros De Esparcimiento",
    "sg:phone":"+34 927 42 03 71",
    "sg:postcode":"10600",
    "sg:province":"C\u00e1ceres",
    "wof:name":"Recerativos Riego S.l.",
    "wof:placetype":"venue"
},
  "geometry": {"coordinates":[-6.0884890556,40.0319290161],"type":"Point"}
}