{
  "type": "Feature",
  "properties": {
    "addr:full":"Calle de Virgen Del Rosario, 8 Cox Alicante 03350",
    "addr:housenumber":"8",
    "addr:postcode":"03350",
    "addr:street":"Calle De Virgen Del Rosario",
    "iso:country":"ES",
    "sg:address":"Calle de Virgen Del Rosario, 8",
    "sg:city":"Cox",
    "sg:orig_category":"Perfumer\u00cda, Art\u00cdculos De Ba\u00d1o (fabricaci\u00d3n, Al Por Mayor)",
    "sg:phone":"+34 965 36 09 24",
    "sg:postcode":"03350",
    "sg:province":"Alicante",
    "wof:name":"Amoros Lician Ivan",
    "wof:placetype":"venue"
},
  "geometry": {"coordinates":[-0.889107585,38.1414985657],"type":"Point"}
}