{
  "type": "Feature",
  "properties": {
    "addr:full":"Calle de Marques De La Valdavia (del), 121 Alcobendas Madrid 28100",
    "addr:housenumber":"121",
    "addr:postcode":"28100",
    "addr:street":"Calle De Marques De La Valdavia Del",
    "iso:country":"ES",
    "sg:address":"Calle de Marques De La Valdavia (del), 121",
    "sg:city":"Alcobendas",
    "sg:orig_category":"Art\u00cdculos De Decoraci\u00d3n",
    "sg:phone":"+34 916 62 45 47",
    "sg:postcode":"28100",
    "sg:province":"Madrid",
    "wof:name":"Pilar Allegue S.l.",
    "wof:placetype":"venue"
},
  "geometry": {"coordinates":[-3.655616045,40.5468940735],"type":"Point"}
}