{
  "type": "Feature",
  "properties": {
    "addr:full":"Calle de Castello, 24 Madrid Madrid 28001",
    "addr:housenumber":"24",
    "addr:postcode":"madrid;28001",
    "addr:street":"Calle De Castello",
    "iso:country":"ES",
    "sg:address":"Calle de Castello, 24",
    "sg:city":"Madrid",
    "sg:orig_category":"Asesor\u00cda Sobre Comunicaci\u00d3n De Empresas",
    "sg:phone":"+34 914 31 98 85",
    "sg:postcode":"28001",
    "sg:province":"Madrid",
    "wof:name":"Honrado Sancho Fernando",
    "wof:placetype":"venue"
},
  "geometry": {"coordinates":[-3.6815443039,40.4246444702],"type":"Point"}
}