{
  "type": "Feature",
  "properties": {
    "iso:country":"ES",
    "sg:address":"Calle de Constitucion (de La), 65",
    "sg:city":"Alcobendas",
    "sg:orig_category":"Agencias De Viajes",
    "sg:phone":"+34 916 58 62 98",
    "sg:postcode":"28100",
    "sg:province":"Madrid",
    "wof:name":"Viajes Eroski",
    "wof:placetype":"venue"
},
  "geometry": {"coordinates":[-3.6386857033,40.5435333252],"type":"Point"}
}