{
  "type": "Feature",
  "properties": {
    "addr:full":"Calle de Nueve De Octubre, 17 Chiva Valencia 46370",
    "addr:housenumber":"17",
    "addr:postcode":"46370",
    "addr:street":"Calle De Nueve De Octubre",
    "iso:country":"ES",
    "sg:address":"Calle de Nueve De Octubre, 17",
    "sg:city":"Chiva",
    "sg:orig_category":"Agentes Generales De Seguros",
    "sg:phone":"+34 962 52 16 30",
    "sg:postcode":"46370",
    "sg:province":"Valencia",
    "wof:name":"Sanchez Salvo Maria",
    "wof:placetype":"venue"
},
  "geometry": {"coordinates":[-0.7188330293,39.4735107422],"type":"Point"}
}