{
  "type": "Feature",
  "properties": {
    "addr:full":"Calle de Miguel Hernandez, S/n Navalvillar Pela Badajoz 06760",
    "addr:postcode":"06760",
    "addr:street":"Calle De Miguel Hernandez S / N",
    "iso:country":"ES",
    "sg:address":"Calle de Miguel Hernandez, S/n",
    "sg:city":"Navalvillar Pela",
    "sg:orig_category":"Fisioterapia",
    "sg:phone":"+34 924 86 02 76",
    "sg:postcode":"06760",
    "sg:province":"Badajoz",
    "wof:name":"Serrano Moreno Maria Jose",
    "wof:placetype":"venue"
},
  "geometry": {"coordinates":[-5.4709582329,39.0937690735],"type":"Point"}
}