{
  "type": "Feature",
  "properties": {
    "iso:country":"ES",
    "sg:address":"Torrent, S/n",
    "sg:city":"Gurb",
    "sg:orig_category":"Producci\u00d3n, Comercio De Cereales",
    "sg:phone":"+34 938 86 36 68",
    "sg:postcode":"08518",
    "sg:province":"Barcelona",
    "wof:name":"Cepa-camp S.l.",
    "wof:placetype":"venue"
},
  "geometry": {"coordinates":[2.2425301075,41.9397239685],"type":"Point"}
}