{
  "type": "Feature",
  "properties": {
    "iso:country":"ES",
    "sg:address":"Avda Mediterraneo (del), 60",
    "sg:city":"Colmenar Viejo",
    "sg:orig_category":"Caf\u00c9s, Bares, Cervecer\u00cdas",
    "sg:phone":"+34 918 45 29 07",
    "sg:postcode":"28770",
    "sg:province":"Madrid",
    "wof:name":"Genova Querol Miguel",
    "wof:placetype":"venue"
},
  "geometry": {"coordinates":[-3.7851469517,40.6704597473],"type":"Point"}
}