{
  "type": "Feature",
  "properties": {
    "addr:full":"Calle de Mayor, 5 Alginet Valencia 46230",
    "addr:housenumber":"5",
    "addr:postcode":"46230",
    "addr:street":"Calle De Mayor",
    "iso:country":"ES",
    "sg:address":"Calle de Mayor, 5",
    "sg:city":"Alginet",
    "sg:orig_category":"Confecci\u00d3n (fabricaci\u00d3n, Al Por Mayor)",
    "sg:phone":"+34 961 75 05 17",
    "sg:postcode":"46230",
    "sg:province":"Valencia",
    "wof:name":"Burches Bosch Jose",
    "wof:placetype":"venue"
},
  "geometry": {"coordinates":[-0.4702340066,39.2613182068],"type":"Point"}
}