{
  "type": "Feature",
  "properties": {
    "iso:country":"ES",
    "sg:address":"Calle de Santa Eulalia, 4",
    "sg:city":"Valverde Leganes",
    "sg:orig_category":"Muebles, Minoristas",
    "sg:phone":"+34 924 49 63 54",
    "sg:postcode":"06130",
    "sg:province":"Badajoz",
    "wof:name":"Rodriguez Moreno Luis",
    "wof:placetype":"venue"
},
  "geometry": {"coordinates":[-6.9795560837,38.6695785522],"type":"Point"}
}