{
  "type": "Feature",
  "properties": {
    "iso:country":"ES",
    "sg:address":"Calle de Rafael Perez Del Alamo, 41",
    "sg:city":"Loja",
    "sg:orig_category":"Estudios, Instalaci\u00d3n De Climatizaci\u00d3n",
    "sg:phone":"+34 958 32 16 61",
    "sg:postcode":"18300",
    "sg:province":"Granada",
    "wof:name":"Vaseclima S.l.",
    "wof:placetype":"venue"
},
  "geometry": {"coordinates":[-4.1459650993,37.1672096252],"type":"Point"}
}