{
  "type": "Feature",
  "properties": {
    "addr:full":"Finca Mas D'en Calaf, S/n Maslloren\u00e7 Tarragona 43718",
    "addr:housenumber":"s / n",
    "addr:postcode":"43718",
    "iso:country":"ES",
    "sg:address":"Finca Mas D'en Calaf, S/n",
    "sg:city":"Maslloren\u00e7",
    "sg:orig_category":"Fabricaci\u00d3n De Art\u00cdculos Y Equipos Deportivos Y De Ocio",
    "sg:phone":"+34 977 62 88 02",
    "sg:postcode":"43718",
    "sg:province":"Tarragona",
    "wof:name":"Comercial Salter S.a.",
    "wof:placetype":"venue"
},
  "geometry": {"coordinates":[1.4152300358,41.2698516846],"type":"Point"}
}