{
  "type": "Feature",
  "properties": {
    "iso:country":"ES",
    "sg:address":"Carrer de Marinel.lo Bosch, 107",
    "sg:city":"Terrassa",
    "sg:orig_category":"Electricidad: Instaladores",
    "sg:phone":"+34 937 83 14 25",
    "sg:postcode":"08222",
    "sg:province":"Barcelona",
    "wof:name":"Elecma Electricidad S.c.c.l.",
    "wof:placetype":"venue"
},
  "geometry": {"coordinates":[2.0253880024,41.5600318909],"type":"Point"}
}