{
  "type": "Feature",
  "properties": {
    "addr:full":"Carrer de Cos (del), 22 Batea Tarragona 43786",
    "addr:housenumber":"22",
    "addr:postcode":"43786",
    "addr:street":"Carrer De Cos Del",
    "iso:country":"ES",
    "sg:address":"Carrer de Cos (del), 22",
    "sg:city":"Batea",
    "sg:orig_category":"Comerciantes Al Por Mayor De Vinos, Licores Y Alcoholes",
    "sg:phone":"+34 977 43 01 09",
    "sg:postcode":"43786",
    "sg:province":"Tarragona",
    "wof:name":"Cellers Tarrone S.l.",
    "wof:placetype":"venue"
},
  "geometry": {"coordinates":[0.3140549958,41.0922050476],"type":"Point"}
}