{
  "type": "Feature",
  "properties": {
    "addr:full":"Pase Lopez Mendizabal Ibiltokia, 1 Tolosa Guip\u00f9zcoa 20400",
    "addr:housenumber":"1",
    "addr:postcode":"20400",
    "addr:street":"Mendizabal Ibiltokia;Guipu\u0300Zcoa",
    "iso:country":"ES",
    "sg:address":"Pase Lopez Mendizabal Ibiltokia, 1",
    "sg:city":"Tolosa",
    "sg:orig_category":"Quincaller\u00cda (al Por Menor)",
    "sg:phone":"+34 943 65 53 29",
    "sg:postcode":"20400",
    "sg:province":"Guip\u00f9zcoa",
    "wof:name":"Moreno Gil Juan Ignacio (ferreteria Tolosa)",
    "wof:placetype":"venue"
},
  "geometry": {"coordinates":[-2.0745580196,43.1357307434],"type":"Point"}
}