{
  "type": "Feature",
  "properties": {
    "addr:full":"Calle de Alfonso X, 6 Madrid Madrid 28010",
    "addr:housenumber":"6",
    "addr:postcode":"28010",
    "addr:street":"Calle De Alfonso X",
    "iso:country":"ES",
    "sg:address":"Calle de Alfonso X, 6",
    "sg:city":"Madrid",
    "sg:orig_category":"Restaurantes",
    "sg:phone":"+34 913 10 26 11",
    "sg:postcode":"28010",
    "sg:province":"Madrid",
    "wof:name":"Soubeyrand  Margarita",
    "wof:placetype":"venue"
},
  "geometry": {"coordinates":[-3.6921257973,40.43384552],"type":"Point"}
}