{
  "type": "Feature",
  "properties": {
    "iso:country":"ES",
    "sg:address":"Rua Pascual Veiga, 21",
    "sg:city":"Ferrol",
    "sg:orig_category":"Procuradores",
    "sg:phone":"+34 981 35 06 61",
    "sg:postcode":"15403",
    "sg:province":"La Coru\u00f1a",
    "wof:name":"Garmendia Diaz Juan Fernando",
    "wof:placetype":"venue"
},
  "geometry": {"coordinates":[-8.2252759933,43.4839553833],"type":"Point"}
}