{
  "type": "Feature",
  "properties": {
    "iso:country":"ES",
    "sg:address":"Calle de Molino De Viento, 14",
    "sg:city":"Madrid",
    "sg:orig_category":"Pintores",
    "sg:phone":"+34 915 31 44 83",
    "sg:postcode":"28004",
    "sg:province":"Madrid",
    "wof:name":"Lopez Garcia Pablo",
    "wof:placetype":"venue"
},
  "geometry": {"coordinates":[-3.7031168938,40.4235954285],"type":"Point"}
}