{
  "type": "Feature",
  "properties": {
    "iso:country":"ES",
    "sg:address":"Ctra. Sabadell-granollers, Km. 0013,2",
    "sg:city":"Lli\u00e7a Vall",
    "sg:orig_category":"Cajas Y Embalajes De Pl\u00c1stico",
    "sg:phone":"+34 938 43 63 45",
    "sg:postcode":"08185",
    "sg:province":"Barcelona",
    "wof:name":"Fabri-plast S. A.",
    "wof:placetype":"venue"
},
  "geometry": {"coordinates":[2.2324490547,41.5865364075],"type":"Point"}
}