{
  "type": "Feature",
  "properties": {
    "iso:country":"ES",
    "sg:address":"Calle de Fundacion Jado, 19",
    "sg:city":"Altzaga",
    "sg:orig_category":"Molduras, Junquillos, Listones Y Molduras Perforadas",
    "sg:phone":"+34 944 67 54 55",
    "sg:postcode":"48950",
    "sg:province":"Vizcaya",
    "wof:name":"El Ancla S.l.",
    "wof:placetype":"venue"
},
  "geometry": {"coordinates":[-2.975258112,43.3038711548],"type":"Point"}
}