{
  "type": "Feature",
  "properties": {
    "iso:country":"ES",
    "sg:address":"Calle de Angel Celdran Carratala, 6",
    "sg:city":"Alacant",
    "sg:orig_category":"Papeler\u00cdas, Librer\u00cdas",
    "sg:phone":"+34 965 11 72 47",
    "sg:postcode":"03006",
    "sg:province":"Alicante",
    "wof:name":"Pascual Lazaro Luisa",
    "wof:placetype":"venue"
},
  "geometry": {"coordinates":[-0.5040526986,38.3437690735],"type":"Point"}
}