{
  "type": "Feature",
  "properties": {
    "addr:full":"Calle de Diego Benitez, S/n Sanlucar De Barrameda C\u00e1diz 11540",
    "addr:housenumber":"s / n",
    "addr:postcode":"11540",
    "addr:street":"Calle De Diego Benitez;Ca\u0301Diz",
    "iso:country":"ES",
    "sg:address":"Calle de Diego Benitez, S/n",
    "sg:city":"Sanlucar De Barrameda",
    "sg:orig_category":"Abogados",
    "sg:phone":"+34 956 38 02 13",
    "sg:postcode":"11540",
    "sg:province":"C\u00e1diz",
    "wof:name":"Guerra Faria Inmaculada",
    "wof:placetype":"venue"
},
  "geometry": {"coordinates":[-6.3516740799,36.7801780701],"type":"Point"}
}