{
  "type": "Feature",
  "properties": {
    "addr:full":"Avda Campanar, 11 Valencia Valencia 46009",
    "addr:housenumber":"11",
    "addr:postcode":"46009",
    "addr:street":"Avda Campanar",
    "iso:country":"ES",
    "sg:address":"Avda Campanar, 11",
    "sg:city":"Valencia",
    "sg:orig_category":"Librer\u00cdas",
    "sg:phone":"+34 963 48 90 24",
    "sg:postcode":"46009",
    "sg:province":"Valencia",
    "wof:name":"Borras Merli Rafael",
    "wof:placetype":"venue"
},
  "geometry": {"coordinates":[-0.3901000023,39.4868850708],"type":"Point"}
}