{
  "type": "Feature",
  "properties": {
    "addr:full":"Calle de Libertad, 30 Tias Las Palmas 35572",
    "addr:housenumber":"30",
    "addr:postcode":"35572",
    "addr:street":"Calle De Libertad",
    "iso:country":"ES",
    "sg:address":"Calle de Libertad, 30",
    "sg:city":"Tias",
    "sg:orig_category":"Asociaciones Y Clubs Deportivos",
    "sg:phone":"+34 928 83 44 32",
    "sg:postcode":"35572",
    "sg:province":"Las Palmas",
    "wof:name":"Maradentro Surf C.c.p.",
    "wof:placetype":"venue"
},
  "geometry": {"coordinates":[-13.6528682709,28.9533424377],"type":"Point"}
}