{
  "type": "Feature",
  "properties": {
    "addr:full":"Cno Aceituno, 19 Lebrija Sevilla 41740",
    "addr:housenumber":"19",
    "addr:postcode":"41740",
    "addr:street":"Cno Aceituno",
    "iso:country":"ES",
    "sg:address":"Cno Aceituno, 19",
    "sg:city":"Lebrija",
    "sg:orig_category":"Abogados",
    "sg:phone":"+34 955 97 55 32",
    "sg:postcode":"41740",
    "sg:province":"Sevilla",
    "wof:name":"Lopez Ortega Jose Fernando",
    "wof:placetype":"venue"
},
  "geometry": {"coordinates":[-6.0785388947,36.9150314331],"type":"Point"}
}