{
  "type": "Feature",
  "properties": {
    "addr:full":"Calle de Asia, 3 Fines Almer\u00eda 04869",
    "addr:housenumber":"3",
    "addr:postcode":"04869",
    "addr:street":"Calle De Asia",
    "iso:country":"ES",
    "sg:address":"Calle de Asia, 3",
    "sg:city":"Fines",
    "sg:orig_category":"Contenedores (mercanc\u00cdas)",
    "sg:phone":"+34 950 44 41 88",
    "sg:postcode":"04869",
    "sg:province":"Almer\u00eda",
    "wof:name":"Transportes Jose Abarca S.l.",
    "wof:placetype":"venue"
},
  "geometry": {"coordinates":[-2.2652449608,37.3605079651],"type":"Point"}
}