{
  "type": "Feature",
  "properties": {
    "addr:full":"Avda Rey Juan Carlos I, S/n Puerto Lumbreras Murcia 30890",
    "addr:housenumber":"s / n",
    "addr:postcode":"30890",
    "addr:street":"Avda Rey Juan Carlos I",
    "iso:country":"ES",
    "sg:address":"Avda Rey Juan Carlos I, S/n",
    "sg:city":"Puerto Lumbreras",
    "sg:orig_category":"Caf\u00c9s, Bares, Cervecer\u00cdas",
    "sg:phone":"+34 968 40 09 91",
    "sg:postcode":"30890",
    "sg:province":"Murcia",
    "wof:name":"Puertos Hosteleria S.l.l.",
    "wof:placetype":"venue"
},
  "geometry": {"coordinates":[-1.797598958,37.5728645325],"type":"Point"}
}