{
  "type": "Feature",
  "properties": {
    "addr:full":"Calle de Justicia, Del, 5 Valencia Valencia 46003",
    "addr:postcode":"46003",
    "addr:street":"Calle De;Del;Valencia",
    "iso:country":"ES",
    "sg:address":"Calle de Justicia, Del, 5",
    "sg:city":"Valencia",
    "sg:orig_category":"Agencias De Viajes",
    "sg:phone":"+34 963 52 80 68",
    "sg:postcode":"46003",
    "sg:province":"Valencia",
    "sg:website":"www.viajesiberia.com",
    "wof:name":"Viajes Iberia S.a:",
    "wof:placetype":"venue"
},
  "geometry": {"coordinates":[-0.3672789931,39.4726715088],"type":"Point"}
}