{
  "type": "Feature",
  "properties": {
    "iso:country":"ES",
    "sg:address":"Calle de Patriarca Doctor Perez Rodriguez, 37",
    "sg:city":"Algeciras",
    "sg:orig_category":"Comercio De Piezas De Recambio Y De Accesorios De Veh\u00cdculos, Veh\u00cdculos Industriales",
    "sg:phone":"+34 956 65 55 03",
    "sg:postcode":"11203",
    "sg:province":"C\u00e1diz",
    "wof:name":"Laisa Salas Jose Antonio",
    "wof:placetype":"venue"
},
  "geometry": {"coordinates":[-5.4501018524,36.1292686462],"type":"Point"}
}