{
  "type": "Feature",
  "properties": {
    "addr:full":"Carr Miracle, 14 Balaguer Lleida 25600",
    "addr:housenumber":"14",
    "addr:postcode":"25600",
    "addr:street":"Carr Miracle",
    "iso:country":"ES",
    "sg:address":"Carr Miracle, 14",
    "sg:city":"Balaguer",
    "sg:orig_category":"Casquer\u00cda (al Por Menor)",
    "sg:phone":"+34 973 44 83 33",
    "sg:postcode":"25600",
    "sg:province":"Lleida",
    "wof:name":"Bellart Lopez Alfonso",
    "wof:placetype":"venue"
},
  "geometry": {"coordinates":[0.8057720065,41.7888946533],"type":"Point"}
}