{
  "type": "Feature",
  "properties": {
    "iso:country":"ES",
    "sg:address":"Av Espanya, 1",
    "sg:city":"Eivissa",
    "sg:orig_category":"Arquitectos",
    "sg:phone":"+34 971 30 07 17",
    "sg:postcode":"07800",
    "sg:province":"Islas Baleares",
    "wof:name":"Prats Chaigneau Rafel Carles",
    "wof:placetype":"venue"
},
  "geometry": {"coordinates":[1.4320950508,38.908657074],"type":"Point"}
}