{
  "type": "Feature",
  "properties": {
    "iso:country":"ES",
    "sg:address":"Calle de Socrates, 8",
    "sg:city":"Montehermoso",
    "sg:orig_category":"Bisuter\u00cda, Joyer\u00cda, Relojer\u00cda (al Por Menor)",
    "sg:phone":"+34 927 67 55 13",
    "sg:postcode":"10810",
    "sg:province":"C\u00e1ceres",
    "wof:name":"Clemente Batuecas Jose Carlos",
    "wof:placetype":"venue"
},
  "geometry": {"coordinates":[-6.3512639999,40.0890312195],"type":"Point"}
}