{
  "type": "Feature",
  "properties": {
    "iso:country":"ES",
    "sg:address":"Fermin Calbeton Kalea, 20",
    "sg:city":"Eibar",
    "sg:orig_category":"Alimentaci\u00d3n General (al Por Menor)",
    "sg:phone":"+34 943 20 87 29",
    "sg:postcode":"20600",
    "sg:province":"Guip\u00f9zcoa",
    "wof:name":"Elizondo Agirre Eneida",
    "wof:placetype":"venue"
},
  "geometry": {"coordinates":[-2.4725339413,43.1840133667],"type":"Point"}
}