{
  "type": "Feature",
  "properties": {
    "addr:full":"Calle de Artekalea, 1 Gernika-lumo Vizcaya 48300",
    "addr:housenumber":"1",
    "addr:postcode":"48300",
    "addr:street":"Calle De Artekalea",
    "iso:country":"ES",
    "sg:address":"Calle de Artekalea, 1",
    "sg:city":"Gernika-lumo",
    "sg:orig_category":"Ense\u00d1anza, Formaci\u00d3n Profesional: Aprendizaje",
    "sg:phone":"+34 946 25 35 58",
    "sg:postcode":"48300",
    "sg:province":"Vizcaya",
    "wof:name":"Gernika Gogoratuz Cento De Investigacion Por La Paz",
    "wof:placetype":"venue"
},
  "geometry": {"coordinates":[-2.677891016,43.3147354126],"type":"Point"}
}