{
  "type": "Feature",
  "properties": {
    "iso:country":"ES",
    "sg:address":"Calle de Fuenterrabia, 9",
    "sg:city":"Madrid",
    "sg:orig_category":"Laboratorios Y Trabajos De Fotograf\u00cda, V\u00cddeo Y Cine",
    "sg:phone":"+34 915 52 70 00",
    "sg:postcode":"28014",
    "sg:province":"Madrid",
    "sg:website":"www.fotosintesis.es",
    "wof:name":"Laboratorio Fotografico Reto Color S.a.",
    "wof:placetype":"venue"
},
  "geometry": {"coordinates":[-3.6822810173,40.4063720703],"type":"Point"}
}