{
  "type": "Feature",
  "properties": {
    "iso:country":"ES",
    "sg:address":"Calle de Rio Alberche, S/n",
    "sg:city":"Poligono Sta M. De Benquerencia",
    "sg:classifiers":[
        {
            "category":"Communications",
            "type":"Services"
        }
    ],
    "sg:phone":"+34 925 28 86 70",
    "sg:postcode":"45...",
    "sg:province":"Toledo",
    "sg:tags":[
        "televisiones",
        "y",
        "radio"
    ],
    "wof:name":"Radio Television De Castilla La Mancha",
    "wof:placetype":"venue"
},
  "geometry": {"coordinates":[-3.9517960548,39.8653678894],"type":"Point"}
}