{
  "type": "Feature",
  "properties": {
    "iso:country":"ES",
    "sg:address":"Carrer de Unio, 85",
    "sg:city":"Mataro",
    "sg:orig_category":"Peluquer\u00cdas, Peluquer\u00cda Mixta",
    "sg:phone":"+34 937 99 79 54",
    "sg:postcode":"08302",
    "sg:province":"Barcelona",
    "wof:name":"Perruqueria Praxedes",
    "wof:placetype":"venue"
},
  "geometry": {"coordinates":[2.4372620583,41.5350379944],"type":"Point"}
}