{
  "type": "Feature",
  "properties": {
    "iso:country":"ES",
    "sg:address":"Pl Nord, 11",
    "sg:city":"Barcelona",
    "sg:orig_category":"M\u00c9dicos: Foniatr\u00cda Y Logopedia",
    "sg:phone":"+34 932 17 48 38",
    "sg:postcode":"08024",
    "sg:province":"Barcelona",
    "wof:name":"Trivium S.c.",
    "wof:placetype":"venue"
},
  "geometry": {"coordinates":[2.1552090645,41.4071922302],"type":"Point"}
}