{
  "type": "Feature",
  "properties": {
    "iso:country":"ES",
    "sg:address":"Calle de Mieses, 9",
    "sg:city":"Majadahonda",
    "sg:orig_category":"Negocio De Materiales De Construcci\u00d3n",
    "sg:phone":"+34 916 38 19 54",
    "sg:postcode":"28220",
    "sg:province":"Madrid",
    "wof:name":"Martin Morales Julian",
    "wof:placetype":"venue"
},
  "geometry": {"coordinates":[-3.8728880882,40.4734649658],"type":"Point"}
}