{
  "type": "Feature",
  "properties": {
    "iso:country":"ES",
    "sg:address":"Carrer de Bonaigua, 36",
    "sg:city":"Sabadell",
    "sg:classifiers":[
        {
            "category":"Personal",
            "subcategory":"Barber",
            "type":"Services"
        }
    ],
    "sg:phone":"+34 937 17 73 01",
    "sg:postcode":"08207",
    "sg:province":"Barcelona",
    "sg:tags":[
        "caballeros",
        "de",
        "peluqueros"
    ],
    "wof:name":"Villegas Valdivia Ramon",
    "wof:placetype":"venue"
},
  "geometry": {"coordinates":[2.0890910625,41.5697631836],"type":"Point"}
}