{
  "type": "Feature",
  "properties": {
    "addr:full":"Calle de Masustegi, 21 Bilbao Vizcaya 48006",
    "addr:housenumber":"21",
    "addr:postcode":"48006",
    "addr:street":"Calle De Masustegi",
    "iso:country":"ES",
    "sg:address":"Calle de Masustegi, 21",
    "sg:city":"Bilbao",
    "sg:orig_category":"Bisuteros (fabricaci\u00d3n, Al Por Mayor)",
    "sg:phone":"+34 944 11 43 58",
    "sg:postcode":"48006",
    "sg:province":"Vizcaya",
    "wof:name":"Bijou Siglo Xxi S.l.",
    "wof:placetype":"venue"
},
  "geometry": {"coordinates":[-2.9136519432,43.2575569153],"type":"Point"}
}