{
  "type": "Feature",
  "properties": {
    "addr:full":"Carrer de Victoria, 33 Portals Nous Islas Baleares 07181",
    "addr:housenumber":"33",
    "addr:postcode":"07181",
    "addr:street":"Carrer De Victoria",
    "iso:country":"ES",
    "sg:address":"Carrer de Victoria, 33",
    "sg:city":"Portals Nous",
    "sg:orig_category":"Inmobiliaria (agencias)",
    "sg:phone":"+34 971 67 68 90",
    "sg:postcode":"07181",
    "sg:province":"Islas Baleares",
    "wof:name":"Velavila S.l.",
    "wof:placetype":"venue"
},
  "geometry": {"coordinates":[2.5758359432,39.5391998291],"type":"Point"}
}