{
  "type": "Feature",
  "properties": {
    "iso:country":"ES",
    "sg:address":"Rua Ecuador, 45",
    "sg:city":"Vigo",
    "sg:orig_category":"Doctores En Medicina",
    "sg:phone":"+34 986 43 06 54",
    "sg:postcode":"36203",
    "sg:province":"Pontevedra",
    "wof:name":"Araujo Rodriguez Estanislao",
    "wof:placetype":"venue"
},
  "geometry": {"coordinates":[-8.7193183899,42.2332801819],"type":"Point"}
}