{
  "type": "Feature",
  "properties": {
    "addr:full":"Avda Joan Miro, 38 Torremolinos M\u00e1laga 29620",
    "addr:housenumber":"38",
    "addr:postcode":"29620",
    "addr:street":"Avda Joan Miro;Ma\u0301Laga",
    "iso:country":"ES",
    "sg:address":"Avda Joan Miro, 38",
    "sg:city":"Torremolinos",
    "sg:orig_category":"Par\u00cds",
    "sg:phone":"+34 952 37 39 08",
    "sg:postcode":"29620",
    "sg:province":"M\u00e1laga",
    "wof:name":"Mu\u00f1oz Arrugaeta Santiago",
    "wof:placetype":"venue"
},
  "geometry": {"coordinates":[-4.5039410591,36.6222381592],"type":"Point"}
}