{
  "type": "Feature",
  "properties": {
    "iso:country":"ES",
    "sg:address":"Plaz Azteca, S/n",
    "sg:city":"Zaragoza",
    "sg:orig_category":"Electricidad: Instaladores",
    "sg:phone":"+34 976 48 86 93",
    "sg:postcode":"50012",
    "sg:province":"Zaragoza",
    "wof:name":"Ibegar Sll",
    "wof:placetype":"venue"
},
  "geometry": {"coordinates":[-0.9173392057,41.6442832947],"type":"Point"}
}