{
  "type": "Feature",
  "properties": {
    "addr:full":"Carr Corregidor Escofet, 22 Lleida Lleida 25005",
    "addr:housenumber":"22",
    "addr:postcode":"25005",
    "addr:street":"Carr Corregidor Escofet",
    "iso:country":"ES",
    "sg:address":"Carr Corregidor Escofet, 22",
    "sg:city":"Lleida",
    "sg:orig_category":"Florister\u00cdas",
    "sg:phone":"+34 973 24 40 69",
    "sg:postcode":"25005",
    "sg:province":"Lleida",
    "wof:name":"Perez Lopez Juan Carlos",
    "wof:placetype":"venue"
},
  "geometry": {"coordinates":[0.6377679706,41.6236000061],"type":"Point"}
}