{
  "type": "Feature",
  "properties": {
    "iso:country":"ES",
    "sg:address":"Av J.a.clave, 193",
    "sg:city":"Mao",
    "sg:orig_category":"Supermercados Y Hipermercados",
    "sg:phone":"+34 971 36 25 19",
    "sg:postcode":"07703",
    "sg:province":"Islas Baleares",
    "wof:name":"Florit Borras S.c.",
    "wof:placetype":"venue"
},
  "geometry": {"coordinates":[4.2597088814,39.8794975281],"type":"Point"}
}