{
  "type": "Feature",
  "properties": {
    "iso:country":"ES",
    "sg:address":"Carr Sant Sebastia, 40",
    "sg:city":"Girona",
    "sg:orig_category":"Carnicer\u00cdas, Carnicer\u00cdas",
    "sg:phone":"+34 972 23 70 00",
    "sg:postcode":"17006",
    "sg:province":"Girona",
    "wof:name":"Jimeno Rodriguez Jose Luis",
    "wof:placetype":"venue"
},
  "geometry": {"coordinates":[2.8065969944,41.9736557007],"type":"Point"}
}