{
  "type": "Feature",
  "properties": {
    "iso:country":"ES",
    "sg:address":"Carrer de Sant Antoni, 52",
    "sg:city":"Valls",
    "sg:orig_category":"Tintorer\u00cdas, Limpieza En Seco",
    "sg:phone":"+34 977 60 02 40",
    "sg:postcode":"43800",
    "sg:province":"Tarragona",
    "wof:name":"Torne Garcia Joan",
    "wof:placetype":"venue"
},
  "geometry": {"coordinates":[1.2498879433,41.2838859558],"type":"Point"}
}