{
  "type": "Feature",
  "properties": {
    "iso:country":"ES",
    "sg:address":"C/ Cerdanya, 8",
    "sg:city":"Puigcerda",
    "sg:classifiers":[
        {
            "category":"Arts & Performance",
            "subcategory":"Art Gallery",
            "type":"Entertainment"
        }
    ],
    "sg:phone":"+34 972 14 12 42",
    "sg:postcode":"17520",
    "sg:province":"Girona",
    "sg:tags":[
        "arte",
        "de",
        "galer\u00cdas"
    ],
    "wof:name":"Puig Llinares Carolina",
    "wof:placetype":"venue"
},
  "geometry": {"coordinates":[1.926856041,42.4292449951],"type":"Point"}
}