{
  "type": "Feature",
  "properties": {
    "addr:full":"Calle de Fuente Alamo, 28 Montilla C\u00f3rdoba 14550",
    "addr:housenumber":"28",
    "addr:postcode":"14550",
    "addr:street":"Calle De Fuente Alamo;Co\u0301Rdoba",
    "iso:country":"ES",
    "sg:address":"Calle de Fuente Alamo, 28",
    "sg:city":"Montilla",
    "sg:orig_category":"Librer\u00cdas",
    "sg:phone":"+34 957 65 47 64",
    "sg:postcode":"14550",
    "sg:province":"C\u00f3rdoba",
    "wof:name":"Raya Raya Soledad",
    "wof:placetype":"venue"
},
  "geometry": {"coordinates":[-4.6387867928,37.5831604004],"type":"Point"}
}