{
  "type": "Feature",
  "properties": {
    "addr:full":"Carrer de Valls (les), 28 Sabadell Barcelona 08201",
    "addr:housenumber":"28",
    "addr:postcode":"08201",
    "addr:street":"Carrer De Valls Les",
    "iso:country":"ES",
    "sg:address":"Carrer de Valls (les), 28",
    "sg:city":"Sabadell",
    "sg:orig_category":"Institutos De Belleza",
    "sg:phone":"+34 937 27 05 21",
    "sg:postcode":"08201",
    "sg:province":"Barcelona",
    "wof:name":"Rubio Muela Fina",
    "wof:placetype":"venue"
},
  "geometry": {"coordinates":[2.1071600914,41.5485038757],"type":"Point"}
}