{
  "type": "Feature",
  "properties": {
    "iso:country":"ES",
    "sg:address":"Carretera De Andujar-puertollano, Km. 0013,0",
    "sg:city":"Pe\u00f1allana",
    "sg:orig_category":"Asesor\u00cda Fiscal Y Jur\u00cddica",
    "sg:phone":"+34 953 54 90 29",
    "sg:postcode":"23740",
    "sg:province":"Ja\u00e9n",
    "wof:name":"S.a.t.garcia Moron",
    "wof:placetype":"venue"
},
  "geometry": {"coordinates":[-4.057518959,38.0386962891],"type":"Point"}
}