{
  "type": "Feature",
  "properties": {
    "addr:full":"Avda Lope De Figueroa, 20 Alcala Henares Madrid 28804",
    "addr:housenumber":"20",
    "addr:postcode":"28804",
    "addr:street":"Avda Lope De Figueroa",
    "iso:country":"ES",
    "sg:address":"Avda Lope De Figueroa, 20",
    "sg:city":"Alcala Henares",
    "sg:orig_category":"Procuradores",
    "sg:phone":"+34 918 89 40 05",
    "sg:postcode":"28804",
    "sg:province":"Madrid",
    "wof:name":"Llamas Jimenez Manuel",
    "wof:placetype":"venue"
},
  "geometry": {"coordinates":[-3.3474490643,40.4888725281],"type":"Point"}
}