{
  "type": "Feature",
  "properties": {
    "iso:country":"ES",
    "sg:address":"Calle de Rio Henares, 3",
    "sg:city":"Guadalajara",
    "sg:orig_category":"Fabricaci\u00d3n De Muebles",
    "sg:phone":"+34 949 21 74 75",
    "sg:postcode":"19004",
    "sg:province":"Guadalajara",
    "wof:name":"Toca Madera Muebles Sociedad Limitada",
    "wof:placetype":"venue"
},
  "geometry": {"coordinates":[-3.1794126034,40.6428604126],"type":"Point"}
}