{
  "type": "Feature",
  "properties": {
    "addr:full":"Calle de Arevalo, S/n Madrigal Altas Torres \u00c1vila 05220",
    "addr:housenumber":"s / n",
    "addr:postcode":"05220",
    "addr:street":"Calle De Arevalo;A\u0301Vila",
    "iso:country":"ES",
    "sg:address":"Calle de Arevalo, S/n",
    "sg:city":"Madrigal Altas Torres",
    "sg:orig_category":"C\u00c1maras De Comercio E Industria, Oficios, Agricultura",
    "sg:phone":"+34 920 32 00 21",
    "sg:postcode":"05220",
    "sg:province":"\u00c1vila",
    "wof:name":"Camara Agraria Local De Las Altas Torres",
    "wof:placetype":"venue"
},
  "geometry": {"coordinates":[-4.9936242104,41.0870094299],"type":"Point"}
}