{
  "type": "Feature",
  "properties": {
    "iso:country":"ES",
    "sg:address":"Calle de Libertad, 5",
    "sg:city":"Madrigueras",
    "sg:orig_category":"Alimentaci\u00d3n General (al Por Menor)",
    "sg:phone":"+34 967 48 51 42",
    "sg:postcode":"02230",
    "sg:province":"Albacete",
    "wof:name":"Cuesta Martinez Luis Angel",
    "wof:placetype":"venue"
},
  "geometry": {"coordinates":[-1.799200058,39.2371368408],"type":"Point"}
}