{
  "type": "Feature",
  "properties": {
    "addr:full":"Pozos, S/n Pto. Rosario Las Palmas 35600",
    "addr:housenumber":"s / n",
    "addr:postcode":"35600",
    "addr:street":"Pozos;Pto. Rosario Las",
    "iso:country":"ES",
    "sg:address":"Pozos, S/n",
    "sg:city":"Pto. Rosario",
    "sg:orig_category":"Mec\u00c1nico Del Autom\u00d3vil",
    "sg:phone":"+34 928 85 87 58",
    "sg:postcode":"35600",
    "sg:province":"Las Palmas",
    "wof:name":"Miguel Perdomo Automoviles S.l.",
    "wof:placetype":"venue"
},
  "geometry": {"coordinates":[-13.8636493683,28.4925556183],"type":"Point"}
}