{
  "type": "Feature",
  "properties": {
    "addr:full":"Rua Franco (do), 43 Lugo Lugo 27003",
    "addr:housenumber":"43",
    "addr:postcode":"27003",
    "addr:street":"Rua Franco Do",
    "iso:country":"ES",
    "sg:address":"Rua Franco (do), 43",
    "sg:city":"Lugo",
    "sg:orig_category":"Asociaciones Y Clubs Deportivos",
    "sg:phone":"+34 982 21 23 11",
    "sg:postcode":"27003",
    "sg:province":"Lugo",
    "wof:name":"Lina Sport",
    "wof:placetype":"venue"
},
  "geometry": {"coordinates":[-7.5634388924,43.0250091553],"type":"Point"}
}