{
  "type": "Feature",
  "properties": {
    "iso:country":"ES",
    "sg:address":"Praj Barranco, S/n",
    "sg:city":"Fortuna",
    "sg:orig_category":"Arenas, Guijarros Y Granulados",
    "sg:phone":"+34 968 68 50 44",
    "sg:postcode":"30620",
    "sg:province":"Murcia",
    "wof:name":"Aridos Cutillas S.a.",
    "wof:placetype":"venue"
},
  "geometry": {"coordinates":[-1.1544963121,38.2054405212],"type":"Point"}
}