{
  "type": "Feature",
  "properties": {
    "addr:full":"Calle de Aeropuerto (del), 8 Coslada Madrid 28820",
    "addr:housenumber":"8",
    "addr:postcode":"28820",
    "addr:street":"Calle De Aeropuerto Del",
    "iso:country":"ES",
    "sg:address":"Calle de Aeropuerto (del), 8",
    "sg:city":"Coslada",
    "sg:orig_category":"Delegados, Agentes De Tr\u00c1nsito, Auxiliares De Transporte Internacional",
    "sg:phone":"+34 916 71 40 15",
    "sg:postcode":"28820",
    "sg:province":"Madrid",
    "wof:name":"Matias Jimenez Julian",
    "wof:placetype":"venue"
},
  "geometry": {"coordinates":[-3.5593633652,40.4267578125],"type":"Point"}
}