{
  "type": "Feature",
  "properties": {
    "iso:country":"ES",
    "sg:address":"Calle de San Anton, 25",
    "sg:city":"Logro\u00f1o",
    "sg:orig_category":"M\u00c9dicos: Otorrinolaringolog\u00cda",
    "sg:phone":"+34 941 26 39 04",
    "sg:postcode":"26002",
    "sg:province":"La Rioja",
    "wof:name":"Molla Ruidiez Francisco Javier",
    "wof:placetype":"venue"
},
  "geometry": {"coordinates":[-2.4462549686,42.4611053467],"type":"Point"}
}