{
  "type": "Feature",
  "properties": {
    "addr:full":"Plaz Musico Ibars, 6 Mislata Valencia 46920",
    "addr:housenumber":"6",
    "addr:postcode":"46920",
    "addr:street":"Plaz Musico Ibars",
    "iso:country":"ES",
    "sg:address":"Plaz Musico Ibars, 6",
    "sg:city":"Mislata",
    "sg:orig_category":"Cajas De Ahorro",
    "sg:phone":"+34 963 83 54 80",
    "sg:postcode":"46920",
    "sg:province":"Valencia",
    "sg:website":"www.caixacatalunya.es",
    "wof:name":"Caixa D'estalvis De Catalunya",
    "wof:placetype":"venue"
},
  "geometry": {"coordinates":[-0.4168890119,39.4759368896],"type":"Point"}
}