{
  "type": "Feature",
  "properties": {
    "addr:full":"Ctra. Sineu, Km. 0001,5 Sant Joan Islas Baleares 07240",
    "addr:postcode":"07240",
    "addr:street":"Ctra. Sineu Km. 0001,5",
    "iso:country":"ES",
    "sg:address":"Ctra. Sineu, Km. 0001,5",
    "sg:city":"Sant Joan",
    "sg:orig_category":"Cr\u00cda De Animales",
    "sg:phone":"+34 971 18 51 66",
    "sg:postcode":"07240",
    "sg:province":"Islas Baleares",
    "wof:name":"Florit Gaya Sebastian",
    "wof:placetype":"venue"
},
  "geometry": {"coordinates":[3.0475699902,39.5929298401],"type":"Point"}
}