{
  "type": "Feature",
  "properties": {
    "iso:country":"ES",
    "sg:address":"Carrer de J. Cuatrecasas I Arumi, 8",
    "sg:city":"S. Quirze Valles",
    "sg:orig_category":"Construcciones Met\u00c1licas",
    "sg:phone":"+34 937 46 43 65",
    "sg:postcode":"08192",
    "sg:province":"Barcelona",
    "wof:name":"Metalestruct-2002 S.l.",
    "wof:placetype":"venue"
},
  "geometry": {"coordinates":[2.0920031071,41.532913208],"type":"Point"}
}