{
  "type": "Feature",
  "properties": {
    "addr:full":"Calle de Colon, 13 San Vicente Del Raspeig-sant Vicent Del Raspeig Alicante 03690",
    "addr:housenumber":"13",
    "addr:postcode":"03690",
    "addr:street":"Calle De Colon",
    "iso:country":"ES",
    "sg:address":"Calle de Colon, 13",
    "sg:city":"San Vicente Del Raspeig-sant Vicent Del Raspeig",
    "sg:orig_category":"Contenedores (mercanc\u00cdas)",
    "sg:phone":"+34 965 66 00 98",
    "sg:postcode":"03690",
    "sg:province":"Alicante",
    "wof:name":"Sanchez Lopez Antonio",
    "wof:placetype":"venue"
},
  "geometry": {"coordinates":[-0.5257403851,38.3960151672],"type":"Point"}
}