{
  "type": "Feature",
  "properties": {
    "iso:country":"ES",
    "sg:address":"Alam Mazarredo, 47",
    "sg:city":"Bilbao",
    "sg:orig_category":"Empresarios",
    "sg:phone":"+34 944 24 90 79",
    "sg:postcode":"48009",
    "sg:province":"Vizcaya",
    "wof:name":"Fundacion Vicente Ferrer",
    "wof:placetype":"venue"
},
  "geometry": {"coordinates":[-2.9317979813,43.2676925659],"type":"Point"}
}