{
  "type": "Feature",
  "properties": {
    "iso:country":"ES",
    "sg:address":"Calle de Cigue\u00d1a, 12",
    "sg:city":"Valladolid",
    "sg:orig_category":"Sociedades, Compa\u00d1\u00cdas Aseguradoras",
    "sg:phone":"+34 983 39 89 79",
    "sg:postcode":"47012",
    "sg:province":"Valladolid",
    "wof:name":"Perez Rodriguez Maria Del Carmen",
    "wof:placetype":"venue"
},
  "geometry": {"coordinates":[-4.7123084068,41.644859314],"type":"Point"}
}