{
  "type": "Feature",
  "properties": {
    "iso:country":"ES",
    "sg:address":"Calle de General Ricardos, 123",
    "sg:city":"Madrid",
    "sg:orig_category":"Colchones (fabricaci\u00d3n, Al Por Mayor, Al Por Menor)",
    "sg:phone":"+34 914 71 85 50",
    "sg:postcode":"28019",
    "sg:province":"Madrid",
    "wof:name":"Ramirez Garcia Milagros",
    "wof:placetype":"venue"
},
  "geometry": {"coordinates":[-3.726911068,40.3914833069],"type":"Point"}
}