{
  "type": "Feature",
  "properties": {
    "iso:country":"ES",
    "sg:address":"Av. Monteprincipe, S/n",
    "sg:city":"Monteprincipe",
    "sg:classifiers":[
        {
            "category":"Personal",
            "subcategory":"Barber",
            "type":"Services"
        }
    ],
    "sg:phone":"+34 913 52 24 81",
    "sg:postcode":"28668",
    "sg:province":"Madrid",
    "sg:tags":[
        "caballeros",
        "de",
        "peluqueros"
    ],
    "wof:name":"Fernandez Solano Julio",
    "wof:placetype":"venue"
},
  "geometry": {"coordinates":[-3.8386409283,40.3988685608],"type":"Point"}
}