{
  "type": "Feature",
  "properties": {
    "addr:full":"Calle de Ramon Fernandez Guisasola (de), 5 Alcobendas Madrid 28100",
    "addr:postcode":"28100",
    "addr:street":"Calle De Ramon Fernandez Guisasola De 5",
    "iso:country":"ES",
    "sg:address":"Calle de Ramon Fernandez Guisasola (de), 5",
    "sg:city":"Alcobendas",
    "sg:orig_category":"Ropa Para Se\u00d1oras (al Por Menor)",
    "sg:phone":"+34 916 51 24 15",
    "sg:postcode":"28100",
    "sg:province":"Madrid",
    "wof:name":"Brox Castillo Juliana",
    "wof:placetype":"venue"
},
  "geometry": {"coordinates":[-3.6354179382,40.5418205261],"type":"Point"}
}