{
  "type": "Feature",
  "properties": {
    "iso:country":"ES",
    "sg:address":"Carrer de Pau Claris, 161",
    "sg:city":"Barcelona",
    "sg:orig_category":"Arquitectos",
    "sg:phone":"+34 934 87 13 41",
    "sg:postcode":"08037",
    "sg:province":"Barcelona",
    "wof:name":"Marimon Nieves Juan Ignacio",
    "wof:placetype":"venue"
},
  "geometry": {"coordinates":[2.1636691093,41.3951797485],"type":"Point"}
}