{
  "type": "Feature",
  "properties": {
    "iso:country":"ES",
    "sg:address":"Calle de Antonio Machado, 2",
    "sg:city":"Burgos",
    "sg:orig_category":"Molduras, Junquillos, Listones Y Molduras Perforadas",
    "sg:phone":"+34 947 22 33 96",
    "sg:postcode":"09004",
    "sg:province":"Burgos",
    "wof:name":"Miguel Martinez Raquel Maria",
    "wof:placetype":"venue"
},
  "geometry": {"coordinates":[-3.6930882931,42.3461532593],"type":"Point"}
}