{
  "type": "Feature",
  "properties": {
    "addr:full":"Av Catalunya, 14 Segur Calafell Tarragona 43882",
    "addr:housenumber":"14",
    "addr:postcode":"43882",
    "addr:street":"Av Catalunya",
    "iso:country":"ES",
    "sg:address":"Av Catalunya, 14",
    "sg:city":"Segur Calafell",
    "sg:orig_category":"Droguer\u00cdas (al Por Menor)",
    "sg:phone":"+34 977 16 32 44",
    "sg:postcode":"43882",
    "sg:province":"Tarragona",
    "wof:name":"Sanchez Diaz Olalla",
    "wof:placetype":"venue"
},
  "geometry": {"coordinates":[1.6056859493,41.194858551],"type":"Point"}
}