{
  "type": "Feature",
  "properties": {
    "iso:country":"ES",
    "sg:address":"Calle de Albaida, 4",
    "sg:city":"Valencia",
    "sg:orig_category":"Centros Empresariales",
    "sg:phone":"+34 963 85 50 08",
    "sg:postcode":"46018",
    "sg:province":"Valencia",
    "wof:name":"Asnepa",
    "wof:placetype":"venue"
},
  "geometry": {"coordinates":[-0.3910878003,39.4671211243],"type":"Point"}
}