{
  "type": "Feature",
  "properties": {
    "addr:full":"Cra Ca L'alaio, 4 Prat Llobregat Barcelona 08820",
    "addr:housenumber":"4",
    "addr:postcode":"08820",
    "addr:street":"Ca L'Alaio;Llobregat",
    "iso:country":"ES",
    "sg:address":"Cra Ca L'alaio, 4",
    "sg:city":"Prat Llobregat",
    "sg:orig_category":"Inform\u00c1tica, Ofim\u00c1tica (estudios, Asesor\u00cda, Ingenier\u00cda, Formaci\u00d3n)",
    "sg:phone":"+34 934 78 60 47",
    "sg:postcode":"08820",
    "sg:province":"Barcelona",
    "wof:name":"Moix Sala Luis",
    "wof:placetype":"venue"
},
  "geometry": {"coordinates":[2.0822968483,41.3293800354],"type":"Point"}
}