{
  "type": "Feature",
  "properties": {
    "iso:country":"ES",
    "sg:address":"Calle de Balmes, 14",
    "sg:city":"Palencia",
    "sg:orig_category":"Mercer\u00cda, Lencer\u00cda (al Por Menor)",
    "sg:phone":"+34 979 71 22 60",
    "sg:postcode":"34004",
    "sg:province":"Palencia",
    "wof:name":"Rodriguez Temprano Angelica",
    "wof:placetype":"venue"
},
  "geometry": {"coordinates":[-4.5250277519,42.0050849915],"type":"Point"}
}