{
  "type": "Feature",
  "properties": {
    "iso:country":"ES",
    "sg:address":"Carrer de Guitard, 15",
    "sg:city":"Barcelona",
    "sg:orig_category":"Centros De Adelgazamiento Y De Est\u00c9tica",
    "sg:phone":"+34 934 09 00 01",
    "sg:postcode":"08014",
    "sg:province":"Barcelona",
    "wof:name":"Distribuciones May Cosmetics S.l.",
    "wof:placetype":"venue"
},
  "geometry": {"coordinates":[2.1385979652,41.3806724548],"type":"Point"}
}