{
  "type": "Feature",
  "properties": {
    "addr:full":"Plaza Txikia, 1 Azpeitia Guip\u00f9zcoa 20730",
    "addr:housenumber":"1",
    "addr:postcode":"20730",
    "addr:street":"Txikia;Guipu\u0300Zcoa",
    "iso:country":"ES",
    "sg:address":"Plaza Txikia, 1",
    "sg:city":"Azpeitia",
    "sg:orig_category":"Bancos",
    "sg:phone":"+34 943 15 01 68",
    "sg:postcode":"20730",
    "sg:province":"Guip\u00f9zcoa",
    "sg:website":"www.bancovasconia.es",
    "wof:name":"Banco De Vasconia",
    "wof:placetype":"venue"
},
  "geometry": {"coordinates":[-2.2638750076,43.1857795715],"type":"Point"}
}