{
  "type": "Feature",
  "properties": {
    "addr:full":"Av Espanya, 107 Eixample Barcelona 08150",
    "addr:housenumber":"107",
    "addr:postcode":"08150",
    "addr:street":"Av Espanya",
    "iso:country":"ES",
    "sg:address":"Av Espanya, 107",
    "sg:city":"Eixample",
    "sg:orig_category":"Ense\u00d1anza: Idiomas",
    "sg:phone":"+34 935 62 52 51",
    "sg:postcode":"08150",
    "sg:province":"Barcelona",
    "wof:name":"Dewhirst  Mary",
    "wof:placetype":"venue"
},
  "geometry": {"coordinates":[2.2293000221,41.5678787231],"type":"Point"}
}