{
  "type": "Feature",
  "properties": {
    "addr:full":"Carr Bartomeu Vicent Ramon, 13 Eivissa Islas Baleares 07800",
    "addr:housenumber":"13",
    "addr:postcode":"07800",
    "addr:street":"Carr Bartomeu Vicent Ramon",
    "iso:country":"ES",
    "sg:address":"Carr Bartomeu Vicent Ramon, 13",
    "sg:city":"Eivissa",
    "sg:orig_category":"Asesor\u00cda Sobre Comunicaci\u00d3n De Empresas",
    "sg:phone":"+34 971 19 19 55",
    "sg:postcode":"07800",
    "sg:province":"Islas Baleares",
    "wof:name":"Asesoria Unidad S.l.",
    "wof:placetype":"venue"
},
  "geometry": {"coordinates":[1.4336022139,38.9099121094],"type":"Point"}
}