{
  "type": "Feature",
  "properties": {
    "iso:country":"ES",
    "sg:address":"Pol Ind Cotarrillo, S/n",
    "sg:city":"Cabezuela Valle",
    "sg:orig_category":"Frutos Y Legumbres",
    "sg:phone":"+34 927 47 26 47",
    "sg:postcode":"10610",
    "sg:province":"C\u00e1ceres",
    "wof:name":"Comercial Agricola Don Rufino S.l.",
    "wof:placetype":"venue"
},
  "geometry": {"coordinates":[-5.8069238663,40.1921615601],"type":"Point"}
}