{
  "type": "Feature",
  "properties": {
    "iso:country":"ES",
    "sg:address":"Calle de Norberto Pi\u00d1ango, 7",
    "sg:city":"Requena",
    "sg:orig_category":"Reposter\u00cdas",
    "sg:phone":"+34 962 30 06 94",
    "sg:postcode":"46340",
    "sg:province":"Valencia",
    "wof:name":"Perez Lopez Juan Carlos",
    "wof:placetype":"venue"
},
  "geometry": {"coordinates":[-1.0997589827,39.4884605408],"type":"Point"}
}