{
  "type": "Feature",
  "properties": {
    "iso:country":"ES",
    "sg:address":"Calle de Zaragoza, 9",
    "sg:city":"Toledo",
    "sg:orig_category":"Peluquer\u00cdas, Peluquer\u00cda Mixta",
    "sg:phone":"+34 925 25 31 55",
    "sg:postcode":"45005",
    "sg:province":"Toledo",
    "wof:name":"Hernandez Sanchez Rosa",
    "wof:placetype":"venue"
},
  "geometry": {"coordinates":[-4.0345602036,39.8748550415],"type":"Point"}
}