{
  "type": "Feature",
  "properties": {
    "iso:country":"ES",
    "sg:address":"Calle de Mayor, 16",
    "sg:city":"Albacete",
    "sg:orig_category":"Ropa Para Se\u00d1oras (al Por Menor)",
    "sg:phone":"+34 967 24 67 08",
    "sg:postcode":"02002",
    "sg:province":"Albacete",
    "wof:name":"Glocal Albacete S.l.",
    "wof:placetype":"venue"
},
  "geometry": {"coordinates":[-1.8538589478,38.9929885864],"type":"Point"}
}