{
  "type": "Feature",
  "properties": {
    "addr:full":"Av. Alella (urb Mar I Muntanya), 19 Alella Barcelona 08328",
    "addr:housenumber":"19",
    "addr:postcode":"08328",
    "addr:street":"Av.;Urb;Muntanya",
    "iso:country":"ES",
    "sg:address":"Av. Alella (urb Mar I Muntanya), 19",
    "sg:city":"Alella",
    "sg:orig_category":"Audiovisuales: Material Y Accesorios (al Por Menor)",
    "sg:phone":"+34 935 55 16 62",
    "sg:postcode":"08328",
    "sg:province":"Barcelona",
    "wof:name":"Orange Video S.l.",
    "wof:placetype":"venue"
},
  "geometry": {"coordinates":[2.2990019321,41.484085083],"type":"Point"}
}