{
  "type": "Feature",
  "properties": {
    "addr:full":"Calle de Jose Villegas, S/n Alcala Guadaira Sevilla 41500",
    "addr:housenumber":"s / n",
    "addr:postcode":"41500",
    "addr:street":"Calle De Jose Villegas",
    "iso:country":"ES",
    "sg:address":"Calle de Jose Villegas, S/n",
    "sg:city":"Alcala Guadaira",
    "sg:orig_category":"Fabricaci\u00d3n De Harinas, S\u00c9molas, Productos De Elaboraci\u00d3n Del Grano",
    "sg:phone":"+34 955 68 33 39",
    "sg:postcode":"41500",
    "sg:province":"Sevilla",
    "wof:name":"Portillo E Hijo Sl",
    "wof:placetype":"venue"
},
  "geometry": {"coordinates":[-5.8397889137,37.3364295959],"type":"Point"}
}