{
  "type": "Feature",
  "properties": {
    "iso:country":"ES",
    "sg:address":"Calle de Capitan Quesada, 39",
    "sg:city":"Galdar",
    "sg:orig_category":"\u00d3ptica: Instrumentos (fabricaci\u00d3n)",
    "sg:phone":"+34 928 88 15 74",
    "sg:postcode":"35460",
    "sg:province":"Las Palmas",
    "wof:name":"Optica Herrera Cerpa S. A.",
    "wof:placetype":"venue"
},
  "geometry": {"coordinates":[-15.6526012421,28.1454658508],"type":"Point"}
}