{
  "type": "Feature",
  "properties": {
    "addr:full":"Av Ramon I Cajal, 34 Tarragona Tarragona 43001",
    "addr:housenumber":"34",
    "addr:postcode":"43001",
    "addr:street":"Av Ramon I Cajal",
    "iso:country":"ES",
    "sg:address":"Av Ramon I Cajal, 34",
    "sg:city":"Tarragona",
    "sg:orig_category":"Molduras, Junquillos, Listones Y Molduras Perforadas",
    "sg:phone":"+34 977 22 08 94",
    "sg:postcode":"43001",
    "sg:province":"Tarragona",
    "wof:name":"Ruiz Rabadan Gerardo Luis",
    "wof:placetype":"venue"
},
  "geometry": {"coordinates":[1.2467420101,41.1163749695],"type":"Point"}
}