{
  "type": "Feature",
  "properties": {
    "addr:full":"Carrer de Font D'en Canyelles, 36 Barcelona Barcelona 08016",
    "addr:housenumber":"36",
    "addr:postcode":"08016",
    "addr:street":"Carrer De Font D'En Canyelles",
    "iso:country":"ES",
    "sg:address":"Carrer de Font D'en Canyelles, 36",
    "sg:city":"Barcelona",
    "sg:orig_category":"Regalos, Souvenires (fabricaci\u00d3n, Al Por Mayor)",
    "sg:phone":"+34 932 76 22 24",
    "sg:postcode":"08016",
    "sg:province":"Barcelona",
    "wof:name":"Over Gift S.l.",
    "wof:placetype":"venue"
},
  "geometry": {"coordinates":[2.1770248413,41.4397926331],"type":"Point"}
}