{
  "type": "Feature",
  "properties": {
    "iso:country":"ES",
    "sg:address":"Ctra. Portugal, S/n",
    "sg:city":"Trabazos",
    "sg:orig_category":"Barbacoas Y Accesorios",
    "sg:phone":"+34 980 68 10 68",
    "sg:postcode":"49516",
    "sg:province":"Zamora",
    "wof:name":"Sesnandez Terron S.l.",
    "wof:placetype":"venue"
},
  "geometry": {"coordinates":[-6.4919490814,41.7477149963],"type":"Point"}
}