{
  "type": "Feature",
  "properties": {
    "addr:full":"Calle de Coso, 11 Ejea De Los Caballeros Zaragoza 50600",
    "addr:housenumber":"11",
    "addr:postcode":"50600",
    "addr:street":"Calle De Coso",
    "iso:country":"ES",
    "sg:address":"Calle de Coso, 11",
    "sg:city":"Ejea De Los Caballeros",
    "sg:orig_category":"Estudios, Instalaci\u00d3n De Climatizaci\u00d3n",
    "sg:phone":"+34 976 66 08 66",
    "sg:postcode":"50600",
    "sg:province":"Zaragoza",
    "wof:name":"Tapia Soriano Jose",
    "wof:placetype":"venue"
},
  "geometry": {"coordinates":[-1.1399790049,42.1263999939],"type":"Point"}
}