{
  "type": "Feature",
  "properties": {
    "addr:full":"Carr Moll De Llevant, 6 Mao Islas Baleares 07703",
    "addr:housenumber":"6",
    "addr:postcode":"07703",
    "addr:street":"Carr Moll De Llevant",
    "iso:country":"ES",
    "sg:address":"Carr Moll De Llevant, 6",
    "sg:city":"Mao",
    "sg:orig_category":"Empresas Portuarias",
    "sg:phone":"+34 971 35 45 20",
    "sg:postcode":"07703",
    "sg:province":"Islas Baleares",
    "wof:name":"Practicos De Mahon S.l.",
    "wof:placetype":"venue"
},
  "geometry": {"coordinates":[4.265625,39.8903694153],"type":"Point"}
}