{
  "type": "Feature",
  "properties": {
    "iso:country":"ES",
    "sg:address":"Calle de Lagasca, 17",
    "sg:city":"Zaragoza",
    "sg:orig_category":"Asesor\u00cda De Formaci\u00d3n Y Gesti\u00d3n De Personal",
    "sg:phone":"+34 976 22 14 24",
    "sg:postcode":"50006",
    "sg:province":"Zaragoza",
    "wof:name":"Vela Gregorio Jose Antonio",
    "wof:placetype":"venue"
},
  "geometry": {"coordinates":[-0.8813189864,41.6517295837],"type":"Point"}
}