{
  "type": "Feature",
  "properties": {
    "iso:country":"ES",
    "sg:address":"Carr Planes, 19",
    "sg:city":"Viladrau",
    "sg:orig_category":"Diarios, Prensa, Revistas (al Por Menor)",
    "sg:phone":"+34 938 84 97 37",
    "sg:postcode":"17406",
    "sg:province":"Girona",
    "sg:website":"www.ochentayocho.com",
    "wof:name":"Hernandez Diaz Jose Antonio",
    "wof:placetype":"venue"
},
  "geometry": {"coordinates":[2.3917369843,41.8470344543],"type":"Point"}
}