{
  "type": "Feature",
  "properties": {
    "addr:full":"Calle de Miguel De Moncada, 12 Alcala Henares Madrid 28804",
    "addr:housenumber":"12",
    "addr:postcode":"28804",
    "addr:street":"Calle De Miguel De Moncada",
    "iso:country":"ES",
    "sg:address":"Calle de Miguel De Moncada, 12",
    "sg:city":"Alcala Henares",
    "sg:orig_category":"Electricidad: Equipos Industriales, Componentes (fabricaci\u00d3n)",
    "sg:phone":"+34 918 88 47 20",
    "sg:postcode":"28804",
    "sg:province":"Madrid",
    "wof:name":"Solaju S.l.",
    "wof:placetype":"venue"
},
  "geometry": {"coordinates":[-3.3534429073,40.4846343994],"type":"Point"}
}