{
  "type": "Feature",
  "properties": {
    "addr:full":"Calle de San Francisco, 3 Ubrique C\u00e1diz 11600",
    "addr:housenumber":"3",
    "addr:postcode":"11600",
    "addr:street":"Calle De San Francisco;Ca\u0301Diz",
    "iso:country":"ES",
    "sg:address":"Calle de San Francisco, 3",
    "sg:city":"Ubrique",
    "sg:orig_category":"Cueros Y Pieles (al Por Mayor)",
    "sg:phone":"+34 956 46 01 38",
    "sg:postcode":"11600",
    "sg:province":"C\u00e1diz",
    "wof:name":"Garcia Tardio Francisco",
    "wof:placetype":"venue"
},
  "geometry": {"coordinates":[-5.4446129799,36.6767845154],"type":"Point"}
}