{
  "type": "Feature",
  "properties": {
    "iso:country":"ES",
    "sg:address":"Calle de Ramon Gallud, 88",
    "sg:city":"Torrevieja",
    "sg:orig_category":"Cajas De Ahorro",
    "sg:phone":"+34 966 70 78 84",
    "sg:postcode":"03180",
    "sg:province":"Alicante",
    "sg:website":"www.lacaixa.es",
    "wof:name":"Caixa D'estalvis I Pensions De Barcelona",
    "wof:placetype":"venue"
},
  "geometry": {"coordinates":[-0.6778050065,37.977306366],"type":"Point"}
}