{
  "type": "Feature",
  "properties": {
    "iso:country":"ES",
    "sg:address":"Parque Corredor, Km. 0001,6",
    "sg:city":"Torrejon Ardoz",
    "sg:classifiers":[
        {
            "category":"Cinema",
            "subcategory":"Movie Theater",
            "type":"Entertainment"
        }
    ],
    "sg:phone":"+34 916 56 81 10",
    "sg:postcode":"28850",
    "sg:province":"Madrid",
    "sg:tags":[
        "salas",
        "de",
        "cine"
    ],
    "sg:website":"www.cinebox.es",
    "wof:name":"Cinebox Exhibicion S.l.",
    "wof:placetype":"venue"
},
  "geometry": {"coordinates":[-3.4763290882,40.4592514038],"type":"Point"}
}