{
  "type": "Feature",
  "properties": {
    "addr:full":"Calle de Ramon Y Cajal, 29 Poligono Industrial Los Villares Salamanca 37184",
    "addr:housenumber":"29",
    "addr:postcode":"37184",
    "addr:street":"Calle De Ramon Y Cajal;Industrial",
    "iso:country":"ES",
    "sg:address":"Calle de Ramon Y Cajal, 29",
    "sg:city":"Poligono Industrial Los Villares",
    "sg:orig_category":"Transportes Por Carretera: Lotes Completos, Mercanc\u00cdas Diversas",
    "sg:phone":"+34 923 12 50 84",
    "sg:postcode":"37184",
    "sg:province":"Salamanca",
    "wof:name":"Boyero Garcia Francisco",
    "wof:placetype":"venue"
},
  "geometry": {"coordinates":[-5.6390562057,40.9899253845],"type":"Point"}
}