{
  "type": "Feature",
  "properties": {
    "addr:full":"Rua Suecia, 14 Pontevedra Pontevedra 36162",
    "addr:housenumber":"14",
    "addr:postcode":"36162",
    "addr:street":"Rua Suecia",
    "iso:country":"ES",
    "sg:address":"Rua Suecia, 14",
    "sg:city":"Pontevedra",
    "sg:orig_category":"Pescader\u00cdas (al Por Menor)",
    "sg:phone":"+34 986 84 24 50",
    "sg:postcode":"36162",
    "sg:province":"Pontevedra",
    "wof:name":"Louzan Sabaris Camilo",
    "wof:placetype":"venue"
},
  "geometry": {"coordinates":[-8.3892097473,42.2826576233],"type":"Point"}
}