{
  "type": "Feature",
  "properties": {
    "iso:country":"ES",
    "sg:address":"Avda Valladolid, 43",
    "sg:city":"Palencia",
    "sg:orig_category":"Asesor\u00cda De Formaci\u00d3n Y Gesti\u00d3n De Personal",
    "sg:phone":"+34 979 71 04 44",
    "sg:postcode":"34004",
    "sg:province":"Palencia",
    "sg:website":"www.urracaycia.com",
    "wof:name":"Asesoria Laboral Ignacio Urraca S.l.",
    "wof:placetype":"venue"
},
  "geometry": {"coordinates":[-4.5247397423,41.9993934631],"type":"Point"}
}