{
  "type": "Feature",
  "properties": {
    "iso:country":"ES",
    "sg:address":"Calle de Huertas, 7",
    "sg:city":"Maqueda",
    "sg:classifiers":[
        {
            "category":"Taxi",
            "type":"Transportation"
        }
    ],
    "sg:phone":"+34 925 79 01 67",
    "sg:postcode":"45515",
    "sg:province":"Toledo",
    "wof:name":"Loeches Carrillo Jose Esteban",
    "wof:placetype":"venue"
},
  "geometry": {"coordinates":[-4.3737440109,40.0646934509],"type":"Point"}
}