{
  "type": "Feature",
  "properties": {
    "addr:full":"Cami Carretera, S/n Villarreal Castell\u00f3n 12540",
    "addr:postcode":"12540",
    "addr:street":"Carretera S / N;Castello\u0301N",
    "iso:country":"ES",
    "sg:address":"Cami Carretera, S/n",
    "sg:city":"Villarreal",
    "sg:orig_category":"M\u00c1rmoles, Granitos Y Piedras Naturales",
    "sg:phone":"+34 964 52 20 92",
    "sg:postcode":"12540",
    "sg:province":"Castell\u00f3n",
    "wof:name":"Piedras Villarrealense S.l.",
    "wof:placetype":"venue"
},
  "geometry": {"coordinates":[-0.1095189974,39.9327163696],"type":"Point"}
}