{
  "type": "Feature",
  "properties": {
    "iso:country":"ES",
    "sg:address":"Calle de Buen Suceso, 25",
    "sg:city":"Almansa",
    "sg:orig_category":"Empresas De Carpinter\u00cda De Madera",
    "sg:phone":"+34 967 34 17 93",
    "sg:postcode":"02640",
    "sg:province":"Albacete",
    "wof:name":"Carpinteria Mipel S.l.",
    "wof:placetype":"venue"
},
  "geometry": {"coordinates":[-1.0991841555,38.8677711487],"type":"Point"}
}