{
  "type": "Feature",
  "properties": {
    "iso:country":"ES",
    "sg:address":"Carrer de Barcelona, 99",
    "sg:city":"Segur Calafell",
    "sg:orig_category":"Electricidad: Instaladores",
    "sg:phone":"+34 977 16 36 72",
    "sg:postcode":"43882",
    "sg:province":"Tarragona",
    "wof:name":"Pisciclor S.l.",
    "wof:placetype":"venue"
},
  "geometry": {"coordinates":[1.6017500162,41.1933441162],"type":"Point"}
}