{
  "type": "Feature",
  "properties": {
    "iso:country":"ES",
    "sg:address":"Calle de Poeta Francisco Antonio Jimenez, S/n",
    "sg:city":"Yecla",
    "sg:orig_category":"Cooperativas, Uniones De Productores De Vinos",
    "sg:phone":"+34 968 79 23 52",
    "sg:postcode":"30510",
    "sg:province":"Murcia",
    "sg:website":"www.yeclavino.com",
    "wof:name":"Consejo Regulador Denominacion De Origen Yecla",
    "wof:placetype":"venue"
},
  "geometry": {"coordinates":[-1.1369190216,38.6092453003],"type":"Point"}
}