{
  "type": "Feature",
  "properties": {
    "addr:full":"Carrer de Monturiol, 4 Rubi Barcelona 08191",
    "addr:housenumber":"4",
    "addr:postcode":"08191",
    "addr:street":"Carrer De Monturiol",
    "iso:country":"ES",
    "sg:address":"Carrer de Monturiol, 4",
    "sg:city":"Rubi",
    "sg:orig_category":"M\u00c9dicos: Estomatolog\u00cda",
    "sg:phone":"+34 936 97 56 08",
    "sg:postcode":"08191",
    "sg:province":"Barcelona",
    "wof:name":"Aljanati Benedetto Myriam",
    "wof:placetype":"venue"
},
  "geometry": {"coordinates":[2.03414011,41.4879150391],"type":"Point"}
}