{
  "type": "Feature",
  "properties": {
    "addr:full":"Carr Pare Coll, 7 Girona Girona 17005",
    "addr:housenumber":"7",
    "addr:postcode":"17005",
    "addr:street":"Carr Pare Coll",
    "iso:country":"ES",
    "sg:address":"Carr Pare Coll, 7",
    "sg:city":"Girona",
    "sg:orig_category":"Reposter\u00cdas",
    "sg:phone":"+34 972 24 41 61",
    "sg:postcode":"17005",
    "sg:province":"Girona",
    "wof:name":"Fleca Sant Daniel S.a.",
    "wof:placetype":"venue"
},
  "geometry": {"coordinates":[2.8124859333,41.9777526855],"type":"Point"}
}