{
  "type": "Feature",
  "properties": {
    "iso:country":"ES",
    "sg:address":"Calle de Bidebarri, 27",
    "sg:city":"Algorta",
    "sg:orig_category":"Servicio De Salud",
    "sg:phone":"+34 944 30 76 77",
    "sg:postcode":"48991",
    "sg:province":"Vizcaya",
    "sg:website":"www.sanig.com",
    "wof:name":"Saneamientos San Ignacio S. A.",
    "wof:placetype":"venue"
},
  "geometry": {"coordinates":[-3.0055971146,43.3540000916],"type":"Point"}
}