{
  "type": "Feature",
  "properties": {
    "addr:full":"Cno Labajo Redondo, S/n Rueda Valladolid 47490",
    "addr:housenumber":"s / n",
    "addr:postcode":"47490",
    "addr:street":"Cno Labajo Redondo;Valladolid",
    "iso:country":"ES",
    "sg:address":"Cno Labajo Redondo, S/n",
    "sg:city":"Rueda",
    "sg:orig_category":"Alquiler De Casas Y Habitaciones Amuebladas",
    "sg:phone":"+34 983 86 85 09",
    "sg:postcode":"47490",
    "sg:province":"Valladolid",
    "wof:name":"Granja Escuela El Viejo Chopo S.l.",
    "wof:placetype":"venue"
},
  "geometry": {"coordinates":[-4.9597439766,41.4110107422],"type":"Point"}
}