{
  "type": "Feature",
  "properties": {
    "iso:country":"ES",
    "sg:address":"Avda Peregrina, S/n",
    "sg:city":"Bertamirans",
    "sg:orig_category":"Guarder\u00cdas",
    "sg:phone":"+34 981 89 11 11",
    "sg:postcode":"15220",
    "sg:province":"La Coru\u00f1a",
    "wof:name":"Concello De Ames",
    "wof:placetype":"venue"
},
  "geometry": {"coordinates":[-8.6506481171,42.8606719971],"type":"Point"}
}