{
  "type": "Feature",
  "properties": {
    "addr:full":"Lago (figueiro), 4 Lago Pontevedra 36792",
    "addr:housenumber":"4",
    "addr:postcode":"36792",
    "addr:street":"Lago Figueiro",
    "iso:country":"ES",
    "sg:address":"Lago (figueiro), 4",
    "sg:city":"Lago",
    "sg:orig_category":"Poller\u00cda Y Caza (al Por Menor)",
    "sg:phone":"+34 986 62 10 13",
    "sg:postcode":"36792",
    "sg:province":"Pontevedra",
    "wof:name":"Presavi 20004 S.l.",
    "wof:placetype":"venue"
},
  "geometry": {"coordinates":[-8.6973619461,42.0142478943],"type":"Point"}
}