{
  "type": "Feature",
  "properties": {
    "iso:country":"ES",
    "sg:address":"Pda Berro, S/n",
    "sg:city":"Altura",
    "sg:orig_category":"Pirotecnia (espect\u00c1culos)",
    "sg:phone":"+34 964 14 70 26",
    "sg:postcode":"12410",
    "sg:province":"Castell\u00f3n",
    "sg:website":"www.pirotecniadealtura.com",
    "wof:name":"Zarzoso Navarrete Antonio",
    "wof:placetype":"venue"
},
  "geometry": {"coordinates":[-0.5825359225,39.8358764648],"type":"Point"}
}