{
  "type": "Feature",
  "properties": {
    "addr:full":"Juan R. Jimenez, S/n Lebrija Sevilla 41740",
    "addr:postcode":"41740",
    "addr:street":"Jimenez S / N",
    "iso:country":"ES",
    "sg:address":"Juan R. Jimenez, S/n",
    "sg:city":"Lebrija",
    "sg:orig_category":"Supermercados Y Hipermercados",
    "sg:phone":"+34 955 97 38 17",
    "sg:postcode":"41740",
    "sg:province":"Sevilla",
    "wof:name":"Romero Silva Carmen",
    "wof:placetype":"venue"
},
  "geometry": {"coordinates":[-6.0892839432,36.9152030945],"type":"Point"}
}