{
  "type": "Feature",
  "properties": {
    "iso:country":"ES",
    "sg:address":"Avda Mar (del), 29",
    "sg:city":"Torreblanca",
    "sg:orig_category":"Inmobiliaria (alquileres Por Temporada Y Temporales)",
    "sg:phone":"+34 964 42 03 82",
    "sg:postcode":"12596",
    "sg:province":"Castell\u00f3n",
    "wof:name":"Tepinsa S.a.",
    "wof:placetype":"venue"
},
  "geometry": {"coordinates":[0.1961860061,40.2195587158],"type":"Point"}
}