{
  "type": "Feature",
  "properties": {
    "addr:full":"Avda Mar (del), 29 Torreblanca Castell\u00f3n 12596",
    "addr:housenumber":"29",
    "addr:postcode":"12596",
    "addr:street":"Avda Mar Del;Castello\u0301N",
    "iso:country":"ES",
    "sg:address":"Avda Mar (del), 29",
    "sg:city":"Torreblanca",
    "sg:orig_category":"Inmobiliaria (alquileres Por Temporada Y Temporales)",
    "sg:phone":"+34 964 42 03 82",
    "sg:postcode":"12596",
    "sg:province":"Castell\u00f3n",
    "wof:name":"Tepinsa S.a.",
    "wof:placetype":"venue"
},
  "geometry": {"coordinates":[0.1961860061,40.2195587158],"type":"Point"}
}