{
  "type": "Feature",
  "properties": {
    "iso:country":"ES",
    "sg:address":"Avda Jorge Vigon, 55",
    "sg:city":"Logro\u00f1o",
    "sg:orig_category":"Sociedades, Compa\u00d1\u00cdas Aseguradoras",
    "sg:phone":"+34 941 27 04 50",
    "sg:postcode":"26003",
    "sg:province":"La Rioja",
    "wof:name":"La Estrella S.a. De Seguros",
    "wof:placetype":"venue"
},
  "geometry": {"coordinates":[-2.4362590313,42.460723877],"type":"Point"}
}