{
  "type": "Feature",
  "properties": {
    "iso:country":"ES",
    "sg:address":"Avda Federico Anaya, 84",
    "sg:city":"Salamanca",
    "sg:orig_category":"Relojer\u00cda (al Por Menor, Reparaci\u00d3n)",
    "sg:phone":"+34 923 22 50 69",
    "sg:postcode":"37004",
    "sg:province":"Salamanca",
    "wof:name":"Joyeria Coria C.b.",
    "wof:placetype":"venue"
},
  "geometry": {"coordinates":[-5.653678894,40.9772186279],"type":"Point"}
}