{
  "type": "Feature",
  "properties": {
    "iso:country":"ES",
    "sg:address":"Calle de Caja De Ahorros, 6",
    "sg:city":"Getxo",
    "sg:orig_category":"Peluquer\u00cdas, Peluquer\u00cda Mixta",
    "sg:phone":"+34 944 63 01 60",
    "sg:postcode":"48930",
    "sg:province":"Vizcaya",
    "wof:name":"Maria Carmen Descalzo Pajares",
    "wof:placetype":"venue"
},
  "geometry": {"coordinates":[-3.0089488029,43.3276367188],"type":"Point"}
}