{
  "type": "Feature",
  "properties": {
    "addr:full":"Carrer de Providencia, 130 Barcelona Barcelona 08024",
    "addr:housenumber":"130",
    "addr:postcode":"08024",
    "addr:street":"Carrer De Providencia",
    "iso:country":"ES",
    "sg:address":"Carrer de Providencia, 130",
    "sg:city":"Barcelona",
    "sg:orig_category":"Importaci\u00d3n, Exportaci\u00d3n Y Comercios De Productos Textiles",
    "sg:phone":"+34 932 19 69 70",
    "sg:postcode":"08024",
    "sg:province":"Barcelona",
    "wof:name":"Rodriguez Hernandez Eugenia",
    "wof:placetype":"venue"
},
  "geometry": {"coordinates":[2.1615710258,41.4090805054],"type":"Point"}
}