{
  "type": "Feature",
  "properties": {
    "iso:country":"ES",
    "sg:address":"Ctra Escorial (de El), Km. 0015,8",
    "sg:city":"Galapagar",
    "sg:orig_category":"Refiner\u00cdas De Petr\u00d3leo",
    "sg:phone":"+34 918 58 41 36",
    "sg:postcode":"28260",
    "sg:province":"Madrid",
    "wof:name":"Magavi S. A.",
    "wof:placetype":"venue"
},
  "geometry": {"coordinates":[-3.9942770004,40.571308136],"type":"Point"}
}