{
  "type": "Feature",
  "properties": {
    "iso:country":"ES",
    "sg:address":"Calle de Empecinado, 5",
    "sg:city":"Valladolid",
    "sg:orig_category":"Promotores Constructores",
    "sg:phone":"+34 983 31 01 80",
    "sg:postcode":"47003",
    "sg:province":"Valladolid",
    "wof:name":"Arranz Revenga Juan Ignacio",
    "wof:placetype":"venue"
},
  "geometry": {"coordinates":[-4.7219634056,41.6564979553],"type":"Point"}
}