{
  "type": "Feature",
  "properties": {
    "addr:full":"Avda. De Santander-berron, 71 La Carrera Asturias 33186",
    "addr:housenumber":"71",
    "addr:postcode":"33186",
    "addr:street":"Avda. De Santander-Berron",
    "iso:country":"ES",
    "sg:address":"Avda. De Santander-berron, 71",
    "sg:city":"La Carrera",
    "sg:orig_category":"Mec\u00c1nico Del Autom\u00d3vil",
    "sg:phone":"+34 985 74 18 04",
    "sg:postcode":"33186",
    "sg:province":"Asturias",
    "wof:name":"Perez Victorero Candido",
    "wof:placetype":"venue"
},
  "geometry": {"coordinates":[-5.7012858391,43.3833732605],"type":"Point"}
}