{
  "type": "Feature",
  "properties": {
    "iso:country":"ES",
    "sg:address":"Carrer de Rossend Arus, 6",
    "sg:city":"Hospitalet Llobregat",
    "sg:orig_category":"Panader\u00cdas, Panader\u00cdas",
    "sg:phone":"+34 933 37 01 64",
    "sg:postcode":"08901",
    "sg:province":"Barcelona",
    "wof:name":"Pastelerias Pavon S.l.",
    "wof:placetype":"venue"
},
  "geometry": {"coordinates":[2.0995900631,41.3589820862],"type":"Point"}
}