{
  "type": "Feature",
  "properties": {
    "addr:full":"Calle de Manzanilla, 26 Almonte Huelva 21730",
    "addr:housenumber":"26",
    "addr:postcode":"21730",
    "addr:street":"Calle De Manzanilla",
    "iso:country":"ES",
    "sg:address":"Calle de Manzanilla, 26",
    "sg:city":"Almonte",
    "sg:orig_category":"Promotores Constructores",
    "sg:phone":"+34 959 40 66 37",
    "sg:postcode":"21730",
    "sg:province":"Huelva",
    "wof:name":"Perez Hernandez Jesus",
    "wof:placetype":"venue"
},
  "geometry": {"coordinates":[-6.5241951942,37.2626113892],"type":"Point"}
}