{
  "type": "Feature",
  "properties": {
    "iso:country":"ES",
    "sg:address":"Avda Andalucia (de), 126",
    "sg:city":"Padul",
    "sg:orig_category":"Molduras, Junquillos, Listones Y Molduras Perforadas",
    "sg:phone":"+34 958 79 01 38",
    "sg:postcode":"18640",
    "sg:province":"Granada",
    "wof:name":"Morales Hidalgo Andres",
    "wof:placetype":"venue"
},
  "geometry": {"coordinates":[-3.6200349331,37.0247688293],"type":"Point"}
}