{
  "type": "Feature",
  "properties": {
    "iso:country":"ES",
    "sg:address":"Calle de Belen, 2",
    "sg:city":"Zafra",
    "sg:orig_category":"Muebles, Minoristas",
    "sg:phone":"+34 924 55 58 71",
    "sg:postcode":"06300",
    "sg:province":"Badajoz",
    "wof:name":"Centro De Representaciones Berfer S.l.",
    "wof:placetype":"venue"
},
  "geometry": {"coordinates":[-6.4191346169,38.4174613953],"type":"Point"}
}