{
  "type": "Feature",
  "properties": {
    "iso:country":"ES",
    "sg:address":"Rua Ulpiano Villanueva (de), 5",
    "sg:city":"Santiago De Compostela",
    "sg:orig_category":"Molduras, Junquillos, Listones Y Molduras Perforadas",
    "sg:phone":"+34 981 58 37 51",
    "sg:postcode":"15705",
    "sg:province":"La Coru\u00f1a",
    "wof:name":"Nari\u00f1o Calvo Andres",
    "wof:placetype":"venue"
},
  "geometry": {"coordinates":[-8.5429811478,42.8928222656],"type":"Point"}
}