{
  "type": "Feature",
  "properties": {
    "iso:country":"ES",
    "sg:address":"Las Palmas, 9",
    "sg:city":"Fuengirola",
    "sg:orig_category":"Molduras, Junquillos, Listones Y Molduras Perforadas",
    "sg:phone":"+34 952 47 76 85",
    "sg:postcode":"29640",
    "sg:province":"M\u00e1laga",
    "wof:name":"Nu\u00f1ez Ruiz Pablo",
    "wof:placetype":"venue"
},
  "geometry": {"coordinates":[-4.6090831757,36.5682830811],"type":"Point"}
}