{
  "type": "Feature",
  "properties": {
    "iso:country":"ES",
    "sg:address":"Rua Aureliano Ferreiro, 105",
    "sg:city":"Maceda",
    "sg:orig_category":"Loter\u00cda Y T\u00d3mbola",
    "sg:phone":"+34 988 46 31 65",
    "sg:postcode":"32700",
    "sg:province":"Ourense",
    "wof:name":"Prol Fernandez Jose Luis",
    "wof:placetype":"venue"
},
  "geometry": {"coordinates":[-7.649269104,42.2692184448],"type":"Point"}
}