{
  "type": "Feature",
  "properties": {
    "iso:country":"ES",
    "sg:address":"Calle de Carmen Portones, 3",
    "sg:city":"Madrid",
    "sg:orig_category":"Bricolaje, Herramientas (al Por Menor)",
    "sg:phone":"+34 913 11 02 78",
    "sg:postcode":"28039",
    "sg:province":"Madrid",
    "wof:name":"J. Y G.s.l. Maderas Y Bricolage",
    "wof:placetype":"venue"
},
  "geometry": {"coordinates":[-3.7057709694,40.463054657],"type":"Point"}
}