{
  "type": "Feature",
  "properties": {
    "iso:country":"ES",
    "sg:address":"Carr Doctor Robert, 75",
    "sg:city":"Badalona",
    "sg:orig_category":"Carnicer\u00cdas, Carnicer\u00cdas",
    "sg:phone":"+34 933 88 56 97",
    "sg:postcode":"08915",
    "sg:province":"Barcelona",
    "wof:name":"Lobon Perez Maria De Los Angeles",
    "wof:placetype":"venue"
},
  "geometry": {"coordinates":[2.2430250645,41.4582252502],"type":"Point"}
}