{
  "type": "Feature",
  "properties": {
    "addr:full":"Calle de Pavaneras, 3 Granada Granada 18009",
    "addr:housenumber":"3",
    "addr:postcode":"18009",
    "addr:street":"Calle De Pavaneras",
    "iso:country":"ES",
    "sg:address":"Calle de Pavaneras, 3",
    "sg:city":"Granada",
    "sg:classifiers":[
        {
            "category":"Government",
            "subcategory":"Post Office",
            "type":"Public Place"
        }
    ],
    "sg:phone":"+34 958 21 01 61",
    "sg:postcode":"18009",
    "sg:province":"Granada",
    "sg:tags":[
        "de",
        "yoga",
        "clases"
    ],
    "wof:name":"Martinez Garcia Eladia",
    "wof:placetype":"venue"
},
  "geometry": {"coordinates":[-3.5962278843,37.1754875183],"type":"Point"}
}