{
  "type": "Feature",
  "properties": {
    "iso:country":"ES",
    "sg:address":"Las Barzaniellas, S/n",
    "sg:city":"Barzaniellas",
    "sg:orig_category":"Productores Recolectores, Venta Directa De Vinos",
    "sg:phone":"+34 985 81 31 03",
    "sg:postcode":"33817",
    "sg:province":"Asturias",
    "wof:name":"Bodegas Del Narcea Sl",
    "wof:placetype":"venue"
},
  "geometry": {"coordinates":[-6.55082798,43.1475296021],"type":"Point"}
}