{
  "type": "Feature",
  "properties": {
    "iso:country":"ES",
    "sg:address":"Pase Reina Sofia, 11",
    "sg:city":"Almu\u00f1ecar",
    "sg:orig_category":"Inmobiliaria (agencias)",
    "sg:phone":"+34 958 63 44 32",
    "sg:postcode":"18690",
    "sg:province":"Granada",
    "wof:name":"Sinnige  Catharina",
    "wof:placetype":"venue"
},
  "geometry": {"coordinates":[-3.6715319157,36.7361793518],"type":"Point"}
}