{
  "type": "Feature",
  "properties": {
    "iso:country":"ES",
    "sg:address":"Avgd Balmes, 30",
    "sg:city":"Lleida",
    "sg:orig_category":"Bisuter\u00cda, Joyer\u00cda, Relojer\u00cda (al Por Menor)",
    "sg:phone":"+34 973 24 34 49",
    "sg:postcode":"25006",
    "sg:province":"Lleida",
    "wof:name":"Fernando Barranco Joiers S.l",
    "wof:placetype":"venue"
},
  "geometry": {"coordinates":[0.6198239923,41.6183624268],"type":"Point"}
}