{
  "type": "Feature",
  "properties": {
    "addr:full":"Rua Venancio Senra, 28 Lugo Lugo 27003",
    "addr:housenumber":"28",
    "addr:postcode":"27003",
    "addr:street":"Rua Venancio Senra",
    "iso:country":"ES",
    "sg:address":"Rua Venancio Senra, 28",
    "sg:city":"Lugo",
    "sg:orig_category":"Molduras, Junquillos, Listones Y Molduras Perforadas",
    "sg:phone":"+34 982 22 10 52",
    "sg:postcode":"27003",
    "sg:province":"Lugo",
    "wof:name":"Rodriguez Regueiro Ermitas",
    "wof:placetype":"venue"
},
  "geometry": {"coordinates":[-7.5493988991,43.0173301697],"type":"Point"}
}