{
  "type": "Feature",
  "properties": {
    "iso:country":"ES",
    "sg:address":"Calle de Araba, 7",
    "sg:city":"Portugalete",
    "sg:orig_category":"Institutos De Belleza",
    "sg:phone":"+34 944 62 48 55",
    "sg:postcode":"48920",
    "sg:province":"Vizcaya",
    "wof:name":"Marante Roel Maria Isabel",
    "wof:placetype":"venue"
},
  "geometry": {"coordinates":[-3.0211493969,43.3190536499],"type":"Point"}
}