{
  "type": "Feature",
  "properties": {
    "iso:country":"ES",
    "sg:address":"Plaz Francisco Uriarte, S/n",
    "sg:city":"Santillana Campos",
    "sg:orig_category":"Otros Trabajos De Limpieza Y Mantenimiento (extracci\u00d3n De Polvo, Recogida De Amianto Y Desespumado)",
    "sg:phone":"+34 979 81 71 29",
    "sg:postcode":"34469",
    "sg:province":"Palencia",
    "wof:name":"Garcia Torices Valeriano",
    "wof:placetype":"venue"
},
  "geometry": {"coordinates":[-4.4619221687,42.3893737793],"type":"Point"}
}