{
  "type": "Feature",
  "properties": {
    "iso:country":"ES",
    "sg:address":"Av Catalunya, 102",
    "sg:city":"Casc Antic",
    "sg:orig_category":"Molduras, Junquillos, Listones Y Molduras Perforadas",
    "sg:phone":"+34 935 62 32 93",
    "sg:postcode":"08150",
    "sg:province":"Barcelona",
    "wof:name":"Hermosilla Castillo Trinidad",
    "wof:placetype":"venue"
},
  "geometry": {"coordinates":[2.2305819988,41.5672149658],"type":"Point"}
}