{
  "type": "Feature",
  "properties": {
    "iso:country":"ES",
    "sg:address":"Av Catalunya, 8",
    "sg:city":"Gironella",
    "sg:orig_category":"Electricidad (montaje, Ensamblaje De Componentes)",
    "sg:phone":"+34 938 25 09 77",
    "sg:postcode":"08680",
    "sg:province":"Barcelona",
    "wof:name":"Bascompte Arnaus Joan",
    "wof:placetype":"venue"
},
  "geometry": {"coordinates":[1.88063097,42.0309829712],"type":"Point"}
}