{
  "type": "Feature",
  "properties": {
    "iso:country":"ES",
    "sg:address":"Calle de Ter, 13",
    "sg:city":"Malaga",
    "sg:orig_category":"Aceros Inoxidables",
    "sg:phone":"+34 952 33 96 35",
    "sg:postcode":"29006",
    "sg:province":"M\u00e1laga",
    "wof:name":"Comainox",
    "wof:placetype":"venue"
},
  "geometry": {"coordinates":[-4.4803781509,36.7114639282],"type":"Point"}
}