{
  "type": "Feature",
  "properties": {
    "addr:full":"Urb Los Molinos, S/n Denia Alicante 03700",
    "addr:housenumber":"s",
    "addr:postcode":"03700",
    "addr:street":"Urb Los Molinos;/ N",
    "iso:country":"ES",
    "sg:address":"Urb Los Molinos, S/n",
    "sg:city":"Denia",
    "sg:orig_category":"Periodistas Profesionales",
    "sg:phone":"+34 965 78 62 14",
    "sg:postcode":"03700",
    "sg:province":"Alicante",
    "wof:name":"Bort Carbo Eduardo",
    "wof:placetype":"venue"
},
  "geometry": {"coordinates":[0.1040000021,38.8355102539],"type":"Point"}
}