{
  "type": "Feature",
  "properties": {
    "iso:country":"ES",
    "sg:address":"Rua Graduil, 5",
    "sg:city":"Cambre",
    "sg:orig_category":"Chapa Y Pintura Veh\u00cdculos",
    "sg:phone":"+34 981 65 52 43",
    "sg:postcode":"15660",
    "sg:province":"A Coru\u00f1a",
    "wof:name":"Talleres Jm De Cambre S.l.",
    "wof:placetype":"venue"
},
  "geometry": {"coordinates":[-8.3557987213,43.3154907227],"type":"Point"}
}