{
  "type": "Feature",
  "properties": {
    "iso:country":"ES",
    "sg:address":"Carrer de Pi, 16",
    "sg:city":"Barcelona",
    "sg:classifiers":[
        {
            "category":"Arts & Performance",
            "subcategory":"Art Gallery",
            "type":"Entertainment"
        }
    ],
    "sg:phone":"+34 933 02 45 79",
    "sg:postcode":"08002",
    "sg:province":"Barcelona",
    "sg:tags":[
        "arte",
        "de",
        "galer\u00cdas"
    ],
    "wof:name":"Circulo Artistico De Sant Lluc",
    "wof:placetype":"venue"
},
  "geometry": {"coordinates":[2.1740911007,41.3837852478],"type":"Point"}
}