{
  "type": "Feature",
  "properties": {
    "addr:full":"Av Verge Del Puig, 1 S. Celoni Barcelona 08470",
    "addr:housenumber":"1",
    "addr:postcode":"08470",
    "addr:street":"Av Verge Del Puig",
    "iso:country":"ES",
    "sg:address":"Av Verge Del Puig, 1",
    "sg:city":"S. Celoni",
    "sg:orig_category":"Industria Qu\u00cdmica",
    "sg:phone":"+34 938 67 11 02",
    "sg:postcode":"08470",
    "sg:province":"Barcelona",
    "wof:name":"Bergos Vilumara Magdalena",
    "wof:placetype":"venue"
},
  "geometry": {"coordinates":[2.4859380722,41.689994812],"type":"Point"}
}