{
  "type": "Feature",
  "properties": {
    "addr:full":"Plaz Constitucion, 4 Granatula De Calatrava Ciudad Real 13360",
    "addr:housenumber":"4",
    "addr:postcode":"13360",
    "addr:street":"Constitucion",
    "iso:country":"ES",
    "sg:address":"Plaz Constitucion, 4",
    "sg:city":"Granatula De Calatrava",
    "sg:orig_category":"Cajas De Ahorro",
    "sg:phone":"+34 926 86 80 06",
    "sg:postcode":"13360",
    "sg:province":"Ciudad Real",
    "sg:website":"www.unicaja.es",
    "wof:name":"Unicaja",
    "wof:placetype":"venue"
},
  "geometry": {"coordinates":[-3.7430388927,38.795879364],"type":"Point"}
}