{
  "type": "Feature",
  "properties": {
    "addr:full":"Calle de Estacion, 3 Gibraleon Huelva 21500",
    "addr:housenumber":"3",
    "addr:postcode":"21500",
    "addr:street":"Calle De Estacion",
    "iso:country":"ES",
    "sg:address":"Calle de Estacion, 3",
    "sg:city":"Gibraleon",
    "sg:orig_category":"Automatizaci\u00d3n De Procesos Industriales Y De Edificaci\u00d3n (estudios, Instalaci\u00d3n)",
    "sg:phone":"+34 959 30 22 22",
    "sg:postcode":"21500",
    "sg:province":"Huelva",
    "wof:name":"Automatismos Huelva S.l.",
    "wof:placetype":"venue"
},
  "geometry": {"coordinates":[-6.9635858536,37.3698005676],"type":"Point"}
}