{
  "type": "Feature",
  "properties": {
    "addr:full":"Calle de Carlos Iii, 69 Cartagena Murcia 30203",
    "addr:housenumber":"69",
    "addr:postcode":"30203",
    "addr:street":"Calle De Carlos Iii",
    "iso:country":"ES",
    "sg:address":"Calle de Carlos Iii, 69",
    "sg:city":"Cartagena",
    "sg:orig_category":"Zapatos (al Por Menor)",
    "sg:phone":"+34 968 52 30 56",
    "sg:postcode":"30203",
    "sg:province":"Murcia",
    "wof:name":"Guirao Lozano Vicente",
    "wof:placetype":"venue"
},
  "geometry": {"coordinates":[-0.9763650894,37.6061592102],"type":"Point"}
}