{
  "type": "Feature",
  "properties": {
    "iso:country":"ES",
    "sg:address":"Urb El Prado, S/n",
    "sg:city":"Merida",
    "sg:orig_category":"Bebidas",
    "sg:phone":"+34 924 37 34 73",
    "sg:postcode":"06800",
    "sg:province":"Badajoz",
    "wof:name":"Mendez Vega De Extremadura S.l.",
    "wof:placetype":"venue"
},
  "geometry": {"coordinates":[-6.3501191139,38.9179382324],"type":"Point"}
}