{
  "type": "Feature",
  "properties": {
    "addr:full":"Av. Onze De Setembre, 235 Prat Llobregat Barcelona 08820",
    "addr:housenumber":"235",
    "addr:postcode":"08820",
    "addr:street":"Av. Onze De Setembre;Llobregat",
    "iso:country":"ES",
    "sg:address":"Av. Onze De Setembre, 235",
    "sg:city":"Prat Llobregat",
    "sg:orig_category":"Promotores Constructores",
    "sg:phone":"+34 934 78 54 11",
    "sg:postcode":"08820",
    "sg:province":"Barcelona",
    "wof:name":"Inmobiliaria Mar Del Prat S.a",
    "wof:placetype":"venue"
},
  "geometry": {"coordinates":[2.1004428864,41.3212165833],"type":"Point"}
}