{
  "type": "Feature",
  "properties": {
    "addr:full":"Calle de Adoveras, 29 Arevalo \u00c1vila 05200",
    "addr:housenumber":"29",
    "addr:postcode":"05200",
    "addr:street":"Calle De Adoveras",
    "iso:country":"ES",
    "sg:address":"Calle de Adoveras, 29",
    "sg:city":"Arevalo",
    "sg:orig_category":"Fabricaci\u00d3n De Sobres, Bolsas Y Fundas",
    "sg:phone":"+34 920 30 01 04",
    "sg:postcode":"05200",
    "sg:province":"\u00c1vila",
    "wof:name":"Jimenez Y Gonzalez C.b.",
    "wof:placetype":"venue"
},
  "geometry": {"coordinates":[-4.7190141678,41.0593681335],"type":"Point"}
}