{
  "type": "Feature",
  "properties": {
    "addr:full":"Calle de Madrigueras, 32 Roda Albacete 02630",
    "addr:housenumber":"32",
    "addr:postcode":"02630",
    "addr:street":"Calle De Madrigueras",
    "iso:country":"ES",
    "sg:address":"Calle de Madrigueras, 32",
    "sg:city":"Roda",
    "sg:orig_category":"Empresas De Carpinter\u00cda",
    "sg:phone":"+34 967 44 35 12",
    "sg:postcode":"02630",
    "sg:province":"Albacete",
    "wof:name":"Martinez Picazo Juan",
    "wof:placetype":"venue"
},
  "geometry": {"coordinates":[-2.1501026154,39.2053108215],"type":"Point"}
}