{
  "type": "Feature",
  "properties": {
    "addr:full":"Calle de Islas Canarias (de Las), 27 Colmenar Viejo Madrid 28770",
    "addr:housenumber":"27",
    "addr:postcode":"28770",
    "addr:street":"Calle De Islas Canarias De Las",
    "iso:country":"ES",
    "sg:address":"Calle de Islas Canarias (de Las), 27",
    "sg:city":"Colmenar Viejo",
    "sg:orig_category":"M\u00c1quinas Y Herramientas Para Trabajar La Piedra",
    "sg:phone":"+34 918 45 02 18",
    "sg:postcode":"28770",
    "sg:province":"Madrid",
    "wof:name":"Maro\u00f1as Hernan Mariano",
    "wof:placetype":"venue"
},
  "geometry": {"coordinates":[-3.765714407,40.6640319824],"type":"Point"}
}