{
  "type": "Feature",
  "properties": {
    "iso:country":"ES",
    "sg:address":"Pase Habana, 6",
    "sg:city":"Madrid",
    "sg:orig_category":"Farmacias",
    "sg:phone":"+34 915 61 86 35",
    "sg:postcode":"28036",
    "sg:province":"Madrid",
    "wof:name":"Vazquez A\u00f1on De La Riva Josefina",
    "wof:placetype":"venue"
},
  "geometry": {"coordinates":[-3.6901879311,40.4474945068],"type":"Point"}
}