{
  "type": "Feature",
  "properties": {
    "iso:country":"ES",
    "sg:address":"Calle de Virgen De La Rosa, 2",
    "sg:city":"Casetas",
    "sg:classifiers":[
        {
            "category":"Autos & Motor Vehicles",
            "subcategory":"Automobile Sales",
            "type":"Retail Goods"
        }
    ],
    "sg:phone":"+34 976 77 34 03",
    "sg:postcode":"50620",
    "sg:province":"Zaragoza",
    "wof:name":"Autoescuela Catalu\u00f1a S.l.",
    "wof:placetype":"venue"
},
  "geometry": {"coordinates":[-1.027156949,41.7181243896],"type":"Point"}
}