{
  "type": "Feature",
  "properties": {
    "iso:country":"ES",
    "sg:address":"Urb Mirador Mar, 13",
    "sg:city":"Casares",
    "sg:orig_category":"Empresarios",
    "sg:phone":"+34 952 89 75 32",
    "sg:postcode":"29690",
    "sg:province":"M\u00e1laga",
    "wof:name":"Promorco S.a.",
    "wof:placetype":"venue"
},
  "geometry": {"coordinates":[-5.2729802132,36.4472236633],"type":"Point"}
}