{
  "type": "Feature",
  "properties": {
    "iso:country":"ES",
    "sg:address":"Carrer de Sant Miquel, 77",
    "sg:city":"Palma",
    "sg:orig_category":"Fabricaci\u00d3n, Venta De Cuadros, Accesorios Para Enmarcar",
    "sg:phone":"+34 971 72 14 83",
    "sg:postcode":"07002",
    "sg:province":"Islas Baleares",
    "sg:website":"www.casapomarflores.com",
    "wof:name":"Jose Manuel Pomar Y Otros Cdad",
    "wof:placetype":"venue"
},
  "geometry": {"coordinates":[2.6521968842,39.5767326355],"type":"Point"}
}