{
  "type": "Feature",
  "properties": {
    "addr:full":"Calle de Corregeria, 32 Valencia Valencia 46001",
    "addr:housenumber":"32",
    "addr:postcode":"46001",
    "addr:street":"Calle De Corregeria",
    "iso:country":"ES",
    "sg:address":"Calle de Corregeria, 32",
    "sg:city":"Valencia",
    "sg:orig_category":"Compraventa De Antig\u00dcedades",
    "sg:phone":"+34 963 92 09 87",
    "sg:postcode":"46001",
    "sg:province":"Valencia",
    "wof:name":"Arteaga Nu\u00f1ez De Haro Fernando Alberto De",
    "wof:placetype":"venue"
},
  "geometry": {"coordinates":[-0.376838088,39.4753875732],"type":"Point"}
}