{
  "type": "Feature",
  "properties": {
    "iso:country":"ES",
    "sg:address":"Avda Constitucion, 3",
    "sg:city":"Villena",
    "sg:orig_category":"Mercer\u00cda, Lencer\u00cda (al Por Menor)",
    "sg:phone":"+34 965 80 75 64",
    "sg:postcode":"03400",
    "sg:province":"Alicante",
    "wof:name":"Merceria Y Creaciones Dama S.l.",
    "wof:placetype":"venue"
},
  "geometry": {"coordinates":[-0.864546001,38.6328620911],"type":"Point"}
}