{
  "type": "Feature",
  "properties": {
    "addr:full":"Calle de Extremadura (de), 10 Algete Madrid 28110",
    "addr:housenumber":"10",
    "addr:postcode":"28110",
    "addr:street":"Calle De Extremadura De",
    "iso:country":"ES",
    "sg:address":"Calle de Extremadura (de), 10",
    "sg:city":"Algete",
    "sg:orig_category":"Cerrajer\u00cda, Ferrallista",
    "sg:phone":"+34 916 28 17 49",
    "sg:postcode":"28110",
    "sg:province":"Madrid",
    "wof:name":"Moreno Coronado Manuel",
    "wof:placetype":"venue"
},
  "geometry": {"coordinates":[-3.4996449947,40.5995292664],"type":"Point"}
}