{
  "type": "Feature",
  "properties": {
    "addr:full":"Ctra De San Juan, S/n Utiel Valencia 46300",
    "addr:housenumber":"s / n",
    "addr:postcode":"46300",
    "addr:street":"Ctra De San Juan",
    "iso:country":"ES",
    "sg:address":"Ctra De San Juan, S/n",
    "sg:city":"Utiel",
    "sg:orig_category":"Calderer\u00cda",
    "sg:phone":"+34 962 16 81 94",
    "sg:postcode":"46300",
    "sg:province":"Valencia",
    "wof:name":"Herpa Levante S.l.",
    "wof:placetype":"venue"
},
  "geometry": {"coordinates":[-1.2075486183,39.5682296753],"type":"Point"}
}