{
  "type": "Feature",
  "properties": {
    "addr:full":"Carrer de Isaac Peral, 90 Terrassa Barcelona 08224",
    "addr:housenumber":"90",
    "addr:postcode":"08224",
    "addr:street":"Carrer De Isaac Peral",
    "iso:country":"ES",
    "sg:address":"Carrer de Isaac Peral, 90",
    "sg:city":"Terrassa",
    "sg:orig_category":"Piedra Natural",
    "sg:phone":"+34 937 80 39 14",
    "sg:postcode":"08224",
    "sg:province":"Barcelona",
    "wof:name":"Martinez Rodriguez Juan",
    "wof:placetype":"venue"
},
  "geometry": {"coordinates":[1.997748971,41.5629043579],"type":"Point"}
}