{
  "type": "Feature",
  "properties": {
    "addr:full":"Calle de Guarnidos, 13 Jerez De La Frontera C\u00e1diz 11401",
    "addr:housenumber":"13",
    "addr:postcode":"11401",
    "addr:street":"Calle De Guarnidos",
    "iso:country":"ES",
    "sg:address":"Calle de Guarnidos, 13",
    "sg:city":"Jerez De La Frontera",
    "sg:orig_category":"Alimentaci\u00d3n General (al Por Menor)",
    "sg:phone":"+34 956 34 61 59",
    "sg:postcode":"11401",
    "sg:province":"C\u00e1diz",
    "wof:name":"Caballero Soler Juan",
    "wof:placetype":"venue"
},
  "geometry": {"coordinates":[-6.1383571625,36.6792526245],"type":"Point"}
}