{
  "type": "Feature",
  "properties": {
    "addr:full":"Carrer de Major, 23 S. Adria Besos Barcelona 08930",
    "addr:housenumber":"23",
    "addr:postcode":"08930",
    "addr:street":"Carrer De Major;S. Adria Besos Barcelona",
    "iso:country":"ES",
    "sg:address":"Carrer de Major, 23",
    "sg:city":"S. Adria Besos",
    "sg:orig_category":"Transporte En General",
    "sg:phone":"+34 934 62 60 90",
    "sg:postcode":"08930",
    "sg:province":"Barcelona",
    "wof:name":"Guijas Calvo Justo",
    "wof:placetype":"venue"
},
  "geometry": {"coordinates":[2.2147500515,41.4337806702],"type":"Point"}
}