{
  "type": "Feature",
  "properties": {
    "addr:full":"Polig. Ind. Proni-meres, S/n Ti\u00f1ana Asturias 33199",
    "addr:housenumber":"s",
    "addr:postcode":"33199",
    "addr:street":"Polig. Ind. Proni-Meres;/ N Tin\u0303Ana Asturias",
    "iso:country":"ES",
    "sg:address":"Polig. Ind. Proni-meres, S/n",
    "sg:city":"Ti\u00f1ana",
    "sg:orig_category":"Alimentaci\u00d3n General (al Por Mayor)",
    "sg:phone":"+34 985 79 14 22",
    "sg:postcode":"33199",
    "sg:province":"Asturias",
    "wof:name":"Sociedad Asturiana De Servicios Agropecuarios S.l.",
    "wof:placetype":"venue"
},
  "geometry": {"coordinates":[-5.7986898422,43.3584632874],"type":"Point"}
}