{
  "type": "Feature",
  "properties": {
    "iso:country":"ES",
    "sg:address":"Cmno Valdenigriales, 13",
    "sg:city":"Pozuelo De Alarcon",
    "sg:orig_category":"Cl\u00cdnicas Dentales",
    "sg:phone":"+34 917 15 92 56",
    "sg:postcode":"28223",
    "sg:province":"Madrid",
    "wof:name":"Dental Pozuelo S.l.",
    "wof:placetype":"venue"
},
  "geometry": {"coordinates":[-3.8146739006,40.4409713745],"type":"Point"}
}