{
  "type": "Feature",
  "properties": {
    "iso:country":"ES",
    "sg:address":"Calle de Azorin, 1",
    "sg:city":"Roda",
    "sg:orig_category":"Empresas De Carpinter\u00cda De Madera",
    "sg:phone":"+34 967 44 33 38",
    "sg:postcode":"02630",
    "sg:province":"Albacete",
    "wof:name":"Diser Cocinas S.l.l.",
    "wof:placetype":"venue"
},
  "geometry": {"coordinates":[-2.1625635624,39.2010192871],"type":"Point"}
}