{
  "type": "Feature",
  "properties": {
    "iso:country":"ES",
    "sg:address":"Calle de Pio Xii, 10",
    "sg:city":"Fuente El Fresno",
    "sg:orig_category":"Centros De Educaci\u00d3n Especial",
    "sg:phone":"+34 926 80 60 73",
    "sg:postcode":"13680",
    "sg:province":"Ciudad Real",
    "wof:name":"Colegio Publico Mixto Jose Antonio",
    "wof:placetype":"venue"
},
  "geometry": {"coordinates":[-3.7769839764,39.2241249084],"type":"Point"}
}