{
  "type": "Feature",
  "properties": {
    "iso:country":"ES",
    "sg:address":"Calle de Pintor Alvarez Ortega, 3",
    "sg:city":"Higueron",
    "sg:orig_category":"Supermercados Y Hipermercados",
    "sg:phone":"+34 957 32 98 46",
    "sg:postcode":"14193",
    "sg:province":"C\u00f3rdoba",
    "wof:name":"Promotora De Detallistas De Alimentacion S.a.",
    "wof:placetype":"venue"
},
  "geometry": {"coordinates":[-4.8541388512,37.8698883057],"type":"Point"}
}