{
  "type": "Feature",
  "properties": {
    "addr:full":"Calle de Uruguay, 27 Valencia Valencia 46007",
    "addr:housenumber":"27",
    "addr:postcode":"46007",
    "addr:street":"Calle De Uruguay",
    "iso:country":"ES",
    "sg:address":"Calle de Uruguay, 27",
    "sg:city":"Valencia",
    "sg:orig_category":"Supermercados Y Hipermercados",
    "sg:phone":"+34 963 80 63 01",
    "sg:postcode":"46007",
    "sg:province":"Valencia",
    "wof:name":"Consum Sociedad Cooperativa Limitada",
    "wof:placetype":"venue"
},
  "geometry": {"coordinates":[-0.3867050111,39.457775116],"type":"Point"}
}