{
  "type": "Feature",
  "properties": {
    "iso:country":"ES",
    "sg:address":"Calle de Jesus Alferez, 42",
    "sg:city":"Santa Maria Aguila",
    "sg:classifiers":[
        {
            "category":"Autos & Motor Vehicles",
            "subcategory":"Automobile Sales",
            "type":"Retail Goods"
        }
    ],
    "sg:phone":"+34 950 58 15 89",
    "sg:postcode":"04710",
    "sg:province":"Almer\u00eda",
    "wof:name":"Gomez Daza Jose",
    "wof:placetype":"venue"
},
  "geometry": {"coordinates":[-2.7761869431,36.7820968628],"type":"Point"}
}