{
  "type": "Feature",
  "properties": {
    "addr:full":"Calle de Vi\u00d1as, 53 Torrejon Ardoz Madrid 28850",
    "addr:housenumber":"53",
    "addr:postcode":"28850",
    "addr:street":"Calle De Vin\u0303As",
    "iso:country":"ES",
    "sg:address":"Calle de Vi\u00d1as, 53",
    "sg:city":"Torrejon Ardoz",
    "sg:orig_category":"Peluquer\u00cdas, Peluquer\u00cda Mixta",
    "sg:phone":"+34 916 75 48 70",
    "sg:postcode":"28850",
    "sg:province":"Madrid",
    "wof:name":"Damian Garcia-morales Sofia",
    "wof:placetype":"venue"
},
  "geometry": {"coordinates":[-3.4730548859,40.4635353088],"type":"Point"}
}