{
  "type": "Feature",
  "properties": {
    "addr:full":"Calle de Huerta De La Papachina, S/n Sevilla Sevilla 41015",
    "addr:housenumber":"s / n",
    "addr:postcode":"41015",
    "addr:street":"Calle De Huerta De La Papachina",
    "iso:country":"ES",
    "sg:address":"Calle de Huerta De La Papachina, S/n",
    "sg:city":"Sevilla",
    "sg:orig_category":"Farmacias",
    "sg:phone":"+34 954 37 34 00",
    "sg:postcode":"41015",
    "sg:province":"Sevilla",
    "wof:name":"Salas Pe\u00f1ate Jose Antonio",
    "wof:placetype":"venue"
},
  "geometry": {"coordinates":[-5.9865841866,37.4264450073],"type":"Point"}
}