{
  "type": "Feature",
  "properties": {
    "iso:country":"ES",
    "sg:address":"Bard Juan Xxiii, 10",
    "sg:city":"Burgos",
    "sg:orig_category":"Panader\u00cdas, Panader\u00cdas",
    "sg:phone":"+34 947 22 24 72",
    "sg:postcode":"09007",
    "sg:province":"Burgos",
    "sg:website":"www.paginasamarillas.es",
    "wof:name":"Maria Del Carmen Ortega Diez Y Otros Cdad.",
    "wof:placetype":"venue"
},
  "geometry": {"coordinates":[-3.6736929417,42.3510513306],"type":"Point"}
}