{
  "type": "Feature",
  "properties": {
    "addr:full":"Plaz Pablo Iglesias, 5 Camas Sevilla 41900",
    "addr:housenumber":"5",
    "addr:postcode":"41900",
    "addr:street":"Pablo Iglesias",
    "iso:country":"ES",
    "sg:address":"Plaz Pablo Iglesias, 5",
    "sg:city":"Camas",
    "sg:orig_category":"Asesor\u00cda Sobre Comunicaci\u00d3n De Empresas",
    "sg:phone":"+34 954 39 28 01",
    "sg:postcode":"41900",
    "sg:province":"Sevilla",
    "wof:name":"Optiservi Y Consultoria S.c.a.",
    "wof:placetype":"venue"
},
  "geometry": {"coordinates":[-6.0328431129,37.4028968811],"type":"Point"}
}