{
  "type": "Feature",
  "properties": {
    "addr:full":"Pl Catalunya, 22 Molins Rei Barcelona 08750",
    "addr:housenumber":"22",
    "addr:postcode":"08750",
    "addr:street":"Pl Catalunya;Barcelona",
    "iso:country":"ES",
    "sg:address":"Pl Catalunya, 22",
    "sg:city":"Molins Rei",
    "sg:orig_category":"Asociaciones Ecologistas",
    "sg:phone":"+34 936 80 27 51",
    "sg:postcode":"08750",
    "sg:province":"Barcelona",
    "wof:name":"Centre D'ecologia I Proyectes Alternatius",
    "wof:placetype":"venue"
},
  "geometry": {"coordinates":[2.0160310268,41.4142494202],"type":"Point"}
}