{
  "type": "Feature",
  "properties": {
    "iso:country":"ES",
    "sg:address":"Calle de Principal, 47",
    "sg:city":"Boiro",
    "sg:orig_category":"Bazares, Art\u00cdculos De Limpieza Y De Cocina (al Por Menor)",
    "sg:phone":"+34 981 84 76 62",
    "sg:postcode":"15930",
    "sg:province":"La Coru\u00f1a",
    "wof:name":"Lista Villa Jose Esteban",
    "wof:placetype":"venue"
},
  "geometry": {"coordinates":[-8.8820123672,42.6479873657],"type":"Point"}
}