{
  "type": "Feature",
  "properties": {
    "iso:country":"ES",
    "sg:address":"Bard Ballabona (la), Km. 0212,0",
    "sg:city":"Real",
    "sg:orig_category":"Maquinaria Para Industrias Diversas",
    "sg:phone":"+34 950 61 90 53",
    "sg:postcode":"04628",
    "sg:province":"Almer\u00eda",
    "wof:name":"Montal S.a.",
    "wof:placetype":"venue"
},
  "geometry": {"coordinates":[-1.9187179804,37.2447776794],"type":"Point"}
}