{
  "type": "Feature",
  "properties": {
    "iso:country":"ES",
    "sg:address":"Ctra Extremadura, S/n",
    "sg:city":"Camas",
    "sg:orig_category":"Maquinaria Para Industrias Diversas",
    "sg:phone":"+34 954 39 08 41",
    "sg:postcode":"41900",
    "sg:province":"Sevilla",
    "wof:name":"Naval Torres Francisco",
    "wof:placetype":"venue"
},
  "geometry": {"coordinates":[-6.0358991623,37.4129333496],"type":"Point"}
}