{
  "type": "Feature",
  "properties": {
    "iso:country":"ES",
    "sg:address":"Av Pau Casals, 14",
    "sg:city":"Tarragona",
    "sg:orig_category":"Agencias Y Agentes Comerciales, Representantes",
    "sg:phone":"+34 977 23 75 19",
    "sg:postcode":"43003",
    "sg:province":"Tarragona",
    "wof:name":"Arroyo Gomez Antonio",
    "wof:placetype":"venue"
},
  "geometry": {"coordinates":[1.2504576445,41.1174850464],"type":"Point"}
}