{
  "type": "Feature",
  "properties": {
    "addr:full":"Carrer de Dalia, 1 Cornella Llobregat Barcelona 08940",
    "addr:housenumber":"1",
    "addr:postcode":"08940",
    "addr:street":"Carrer De Dalia",
    "iso:country":"ES",
    "sg:address":"Carrer de Dalia, 1",
    "sg:city":"Cornella Llobregat",
    "sg:classifiers":[
        {
            "category":"Personal",
            "subcategory":"Barber",
            "type":"Services"
        }
    ],
    "sg:phone":"+34 933 76 83 51",
    "sg:postcode":"08940",
    "sg:province":"Barcelona",
    "sg:tags":[
        "caballeros",
        "de",
        "peluqueros"
    ],
    "wof:name":"Fernandez Funes Jose",
    "wof:placetype":"venue"
},
  "geometry": {"coordinates":[2.0824539661,41.3617286682],"type":"Point"}
}