{
  "type": "Feature",
  "properties": {
    "addr:full":"Calle de Lealtad, 22 Gijon Asturias 33212",
    "addr:housenumber":"22",
    "addr:postcode":"33212",
    "addr:street":"Calle De Lealtad",
    "iso:country":"ES",
    "sg:address":"Calle de Lealtad, 22",
    "sg:city":"Gijon",
    "sg:orig_category":"Empresas De Pintura Y Revestimientos",
    "sg:phone":"+34 985 32 37 57",
    "sg:postcode":"33212",
    "sg:province":"Asturias",
    "wof:name":"Dominguez Alcon Felipe",
    "wof:placetype":"venue"
},
  "geometry": {"coordinates":[-5.6815490723,43.5395812988],"type":"Point"}
}