{
  "type": "Feature",
  "properties": {
    "iso:country":"ES",
    "sg:address":"Paseo Carrera, 49",
    "sg:city":"Moron Frontera",
    "sg:orig_category":"Producci\u00d3n, Venta De Productos De Agricultura Biol\u00d3gica",
    "sg:phone":"+34 954 85 05 22",
    "sg:postcode":"41530",
    "sg:province":"Sevilla",
    "wof:name":"Famibasa",
    "wof:placetype":"venue"
},
  "geometry": {"coordinates":[-5.4528231621,37.1294212341],"type":"Point"}
}