{
  "type": "Feature",
  "properties": {
    "iso:country":"ES",
    "sg:address":"Ctra. Comarcal Doscientos Cuatro, Km. 0016,2",
    "sg:city":"Valdeobispo",
    "sg:orig_category":"Distribuci\u00d3n De Petr\u00d3leo Y Derivados",
    "sg:phone":"+34 927 45 60 39",
    "sg:postcode":"10672",
    "sg:province":"C\u00e1ceres",
    "wof:name":"Gonzalez Novoa Francisco Manuel",
    "wof:placetype":"venue"
},
  "geometry": {"coordinates":[-6.2269763947,40.0906677246],"type":"Point"}
}