{
  "type": "Feature",
  "properties": {
    "addr:full":"Avda Portugal, 112 Salamanca Salamanca 37005",
    "addr:housenumber":"112",
    "addr:postcode":"37005",
    "addr:street":"Avda Portugal",
    "iso:country":"ES",
    "sg:address":"Avda Portugal, 112",
    "sg:city":"Salamanca",
    "sg:orig_category":"Muebles Y Accesorios Para Cocinas Y Cuartos De Ba\u00d1o (al Por Menor)",
    "sg:phone":"+34 923 12 07 94",
    "sg:postcode":"37005",
    "sg:province":"Salamanca",
    "wof:name":"Electrodomesticos Alberto S.l.",
    "wof:placetype":"venue"
},
  "geometry": {"coordinates":[-5.6622772217,40.9724235535],"type":"Point"}
}