{
  "type": "Feature",
  "properties": {
    "addr:full":"Calle de Mesones, 2 Villanueva De Los Castillejos Huelva 21540",
    "addr:housenumber":"2",
    "addr:postcode":"21540",
    "addr:street":"Calle De Mesones",
    "iso:country":"ES",
    "sg:address":"Calle de Mesones, 2",
    "sg:city":"Villanueva De Los Castillejos",
    "sg:classifiers":[
        {
            "category":"Home & Garden",
            "subcategory":"Building Materials",
            "type":"Retail Goods"
        }
    ],
    "sg:phone":"+34 959 38 50 44",
    "sg:postcode":"21540",
    "sg:province":"Huelva",
    "sg:tags":[
        "accesorios",
        "para",
        "bares",
        "cervecer\u00cdas",
        "caf\u00c9s",
        "y"
    ],
    "wof:name":"Toronjo Maestre Sebastian",
    "wof:placetype":"venue"
},
  "geometry": {"coordinates":[-7.2722048759,37.5007324219],"type":"Point"}
}