{
  "type": "Feature",
  "properties": {
    "iso:country":"ES",
    "sg:address":"Pg Vint-i-dos De Juliol, 538",
    "sg:city":"Terrassa",
    "sg:orig_category":"Empresas De Carpinter\u00cda De Madera",
    "sg:phone":"+34 937 83 01 70",
    "sg:postcode":"08222",
    "sg:province":"Barcelona",
    "wof:name":"Sanchez Sala Ignacio",
    "wof:placetype":"venue"
},
  "geometry": {"coordinates":[2.0202050209,41.5693283081],"type":"Point"}
}