{
  "type": "Feature",
  "properties": {
    "addr:full":"Carrer de Bernat De Bell.lloc, 1 Reus Tarragona 43203",
    "addr:housenumber":"1",
    "addr:postcode":"43203",
    "addr:street":"Carrer De Bernat De Bell.Lloc",
    "iso:country":"ES",
    "sg:address":"Carrer de Bernat De Bell.lloc, 1",
    "sg:city":"Reus",
    "sg:orig_category":"Agencias Y Agentes Comerciales, Representantes",
    "sg:phone":"+34 977 31 74 20",
    "sg:postcode":"43203",
    "sg:province":"Tarragona",
    "wof:name":"Roig Capaces Jose Maria",
    "wof:placetype":"venue"
},
  "geometry": {"coordinates":[1.1061580181,41.1613388062],"type":"Point"}
}