{
  "type": "Feature",
  "properties": {
    "addr:full":"Pg Riera (la), 160 Teia Centre,sector Riera Esquerre Barcelona 08329",
    "addr:housenumber":"160",
    "addr:postcode":"08329",
    "addr:street":"Riera La;Riera Esquerre",
    "iso:country":"ES",
    "sg:address":"Pg Riera (la), 160",
    "sg:city":"Teia Centre,sector Riera Esquerre",
    "sg:orig_category":"Semiller\u00cdas",
    "sg:phone":"+34 935 40 17 38",
    "sg:postcode":"08329",
    "sg:province":"Barcelona",
    "wof:name":"Vivers Volart S.l.",
    "wof:placetype":"venue"
},
  "geometry": {"coordinates":[2.1699187756,41.3879165649],"type":"Point"}
}