{
  "type": "Feature",
  "properties": {
    "iso:country":"ES",
    "sg:address":"Carr Camp De Les Forques, S/n",
    "sg:city":"Besalu",
    "sg:orig_category":"Metalizados",
    "sg:phone":"+34 972 59 12 90",
    "sg:postcode":"17850",
    "sg:province":"Girona",
    "wof:name":"Tallers Mecanitzats Llam S.l.",
    "wof:placetype":"venue"
},
  "geometry": {"coordinates":[2.7082850933,42.1975059509],"type":"Point"}
}