{
  "type": "Feature",
  "properties": {
    "iso:country":"ES",
    "sg:address":"Carrer de Salvador Allende, 16",
    "sg:city":"S. Boi Llobregat",
    "sg:orig_category":"Reposter\u00cdas",
    "sg:phone":"+34 936 54 01 02",
    "sg:postcode":"08830",
    "sg:province":"Barcelona",
    "wof:name":"Martin Comas S.l",
    "wof:placetype":"venue"
},
  "geometry": {"coordinates":[2.0349459648,41.3497085571],"type":"Point"}
}