{
  "type": "Feature",
  "properties": {
    "addr:full":"Trva Real, 1 Villaseca Sagra Toledo 45260",
    "addr:housenumber":"1",
    "addr:postcode":"45260",
    "addr:street":"Trva Real",
    "iso:country":"ES",
    "sg:address":"Trva Real, 1",
    "sg:city":"Villaseca Sagra",
    "sg:orig_category":"Estancos",
    "sg:phone":"+34 925 27 81 57",
    "sg:postcode":"45260",
    "sg:province":"Toledo",
    "wof:name":"Aguado Juarez Francisco Javier",
    "wof:placetype":"venue"
},
  "geometry": {"coordinates":[-3.882973671,39.9601211548],"type":"Point"}
}