{
  "type": "Feature",
  "properties": {
    "iso:country":"ES",
    "sg:address":"Calle de Artes Graficas (de Las), S/n",
    "sg:city":"Huesca",
    "sg:orig_category":"Herramientas Manuales (fabricaci\u00d3n, Al Por Mayor)",
    "sg:phone":"+34 974 24 12 42",
    "sg:postcode":"22006",
    "sg:province":"Huesca",
    "wof:name":"Castan Jimenez Pascual",
    "wof:placetype":"venue"
},
  "geometry": {"coordinates":[-0.3861576021,42.1431465149],"type":"Point"}
}