{
  "type": "Feature",
  "properties": {
    "addr:full":"Calle de Santa Teresa, 1 Daimiel Ciudad Real 13250",
    "addr:housenumber":"1",
    "addr:postcode":"13250",
    "addr:street":"Calle De Santa Teresa",
    "iso:country":"ES",
    "sg:address":"Calle de Santa Teresa, 1",
    "sg:city":"Daimiel",
    "sg:orig_category":"Armas Y Municiones (fabricaci\u00d3n, Al Por Mayor)",
    "sg:phone":"+34 926 85 01 58",
    "sg:postcode":"13250",
    "sg:province":"Ciudad Real",
    "wof:name":"Aldea Jaime Maria Josefa",
    "wof:placetype":"venue"
},
  "geometry": {"coordinates":[-3.612288475,39.0695724487],"type":"Point"}
}