{
  "type": "Feature",
  "properties": {
    "iso:country":"ES",
    "sg:address":"Rua Villar, 22",
    "sg:city":"Ourense",
    "sg:orig_category":"Ropa Para Se\u00d1oras (al Por Menor)",
    "sg:phone":"+34 988 22 28 39",
    "sg:postcode":"32005",
    "sg:province":"Ourense",
    "wof:name":"Miguel Angel S.c",
    "wof:placetype":"venue"
},
  "geometry": {"coordinates":[-7.8646569252,42.3335571289],"type":"Point"}
}