{
  "type": "Feature",
  "properties": {
    "iso:country":"ES",
    "sg:address":"Plaz Espa\u00d1a, S/n",
    "sg:city":"Torrejon Ardoz",
    "sg:orig_category":"Autob\u00das (explotaci\u00d3n Y Servicios De)",
    "sg:phone":"+34 916 75 60 68",
    "sg:postcode":"28850",
    "sg:province":"Madrid",
    "sg:website":"www.continental-auto.es",
    "wof:name":"Continental Auto S.l.",
    "wof:placetype":"venue"
},
  "geometry": {"coordinates":[-3.4763290882,40.4592514038],"type":"Point"}
}