{
  "type": "Feature",
  "properties": {
    "addr:full":"Calle de Cachero, 8 Madrid Madrid 28053",
    "addr:housenumber":"8",
    "addr:postcode":"madrid;28053",
    "addr:street":"Calle De Cachero",
    "iso:country":"ES",
    "sg:address":"Calle de Cachero, 8",
    "sg:city":"Madrid",
    "sg:orig_category":"Zapatos (al Por Menor)",
    "sg:phone":"+34 914 78 89 70",
    "sg:postcode":"28053",
    "sg:province":"Madrid",
    "wof:name":"Hernandez Gutierrez Juana",
    "wof:placetype":"venue"
},
  "geometry": {"coordinates":[-3.6665482521,40.3932647705],"type":"Point"}
}