{
  "type": "Feature",
  "properties": {
    "addr:full":"Calle de Menendez Pelayo, 2 Zaragoza Zaragoza 50009",
    "addr:housenumber":"2",
    "addr:postcode":"50009",
    "addr:street":"Calle De Menendez Pelayo",
    "iso:country":"ES",
    "sg:address":"Calle de Menendez Pelayo, 2",
    "sg:city":"Zaragoza",
    "sg:orig_category":"Ingenier\u00cda, Centros De Estudios (diversos)",
    "sg:phone":"+34 976 56 30 12",
    "sg:postcode":"50009",
    "sg:province":"Zaragoza",
    "wof:name":"Heresdi S.l.",
    "wof:placetype":"venue"
},
  "geometry": {"coordinates":[-0.8959159851,41.6424064636],"type":"Point"}
}