{
  "type": "Feature",
  "properties": {
    "addr:full":"C/ Sant Eloi, 19 Alcoi Alicante 03804",
    "addr:housenumber":"19",
    "addr:postcode":"03804",
    "addr:street":"C / Sant Eloi",
    "iso:country":"ES",
    "sg:address":"C/ Sant Eloi, 19",
    "sg:city":"Alcoi",
    "sg:orig_category":"Negocio De Madera",
    "sg:phone":"+34 965 52 56 07",
    "sg:postcode":"03804",
    "sg:province":"Alicante",
    "wof:name":"Fustalegre S.l.",
    "wof:placetype":"venue"
},
  "geometry": {"coordinates":[-0.4650832117,38.7096748352],"type":"Point"}
}