{
  "type": "Feature",
  "properties": {
    "iso:country":"ES",
    "sg:address":"Calle de San Juan De Dios, 2",
    "sg:city":"Caceres",
    "sg:orig_category":"Agencias De Trabajo Temporal",
    "sg:phone":"+34 927 22 27 74",
    "sg:postcode":"10001",
    "sg:province":"C\u00e1ceres",
    "sg:website":"www.manpower.es",
    "wof:name":"Manpower Team Empresas De Trabajo Temporal",
    "wof:placetype":"venue"
},
  "geometry": {"coordinates":[-6.3801579475,39.4720420837],"type":"Point"}
}