{
  "type": "Feature",
  "properties": {
    "addr:full":"Calle de Doctor Gregorio Mara\u00d1on, 9 Cordoba C\u00f3rdoba 14004",
    "addr:housenumber":"9",
    "addr:postcode":"14004",
    "addr:street":"Calle De Doctor Gregorio Maran\u0303On;Co\u0301Rdoba",
    "iso:country":"ES",
    "sg:address":"Calle de Doctor Gregorio Mara\u00d1on, 9",
    "sg:city":"Cordoba",
    "sg:orig_category":"Panader\u00cdas, Panader\u00cdas",
    "sg:phone":"+34 957 20 01 04",
    "sg:postcode":"14004",
    "sg:province":"C\u00f3rdoba",
    "wof:name":"Pasteleria Roldan Hermanos S.l.",
    "wof:placetype":"venue"
},
  "geometry": {"coordinates":[-4.7976431847,37.8677253723],"type":"Point"}
}