{
  "type": "Feature",
  "properties": {
    "addr:full":"Calle de Maqueda, 134 Madrid Madrid 28024",
    "addr:housenumber":"134",
    "addr:postcode":"28024",
    "addr:street":"Calle De Maqueda",
    "iso:country":"ES",
    "sg:address":"Calle de Maqueda, 134",
    "sg:city":"Madrid",
    "sg:orig_category":"Empresas De Carpinter\u00cda",
    "sg:phone":"+34 917 19 38 47",
    "sg:postcode":"28024",
    "sg:province":"Madrid",
    "wof:name":"Gonzalez Barco Oscar",
    "wof:placetype":"venue"
},
  "geometry": {"coordinates":[-3.7622389793,40.3880386353],"type":"Point"}
}