{
  "type": "Feature",
  "properties": {
    "addr:full":"Carrer de Cobalt, 16 Barcelona Barcelona 08038",
    "addr:housenumber":"16",
    "addr:postcode":"08038",
    "addr:street":"Carrer De Cobalt",
    "iso:country":"ES",
    "sg:address":"Carrer de Cobalt, 16",
    "sg:city":"Barcelona",
    "sg:orig_category":"Electricidad, Electr\u00d3nica: Material Y Suministros (al Por Mayor)",
    "sg:phone":"+34 932 23 30 03",
    "sg:postcode":"08038",
    "sg:province":"Barcelona",
    "wof:name":"Eurotronix S. A.",
    "wof:placetype":"venue"
},
  "geometry": {"coordinates":[2.139647007,41.3541603088],"type":"Point"}
}