{
  "type": "Feature",
  "properties": {
    "iso:country":"ES",
    "sg:address":"Rua Rio Da Loba, S/n",
    "sg:city":"Rabu\u00d1eiro",
    "sg:orig_category":"Iglesia Cat\u00d3lica",
    "sg:phone":"+34 981 61 02 21",
    "sg:postcode":"15173",
    "sg:province":"La Coru\u00f1a",
    "wof:name":"Parroquia Santa Maria De Oleiros",
    "wof:placetype":"venue"
},
  "geometry": {"coordinates":[-8.3093490601,43.3329620361],"type":"Point"}
}