{
  "type": "Feature",
  "properties": {
    "iso:country":"ES",
    "sg:address":"Calle de Santas Flora Y Maria, 56",
    "sg:city":"Cordoba",
    "sg:orig_category":"Peluqueros: De Se\u00d1oras",
    "sg:phone":"+34 957 27 08 47",
    "sg:postcode":"14012",
    "sg:province":"C\u00f3rdoba",
    "wof:name":"Caballero Vargas Encarnacion",
    "wof:placetype":"venue"
},
  "geometry": {"coordinates":[-4.7777938843,37.9093933105],"type":"Point"}
}