{
  "type": "Feature",
  "properties": {
    "iso:country":"ES",
    "sg:address":"Calle de Independencia (la), 4",
    "sg:city":"Segovia",
    "sg:orig_category":"Peluquer\u00cdas",
    "sg:phone":"+34 921 42 38 66",
    "sg:postcode":"40002",
    "sg:province":"Segovia",
    "wof:name":"Gonzalez Bermejo Jose Alfredo",
    "wof:placetype":"venue"
},
  "geometry": {"coordinates":[-4.1180090904,40.9452400208],"type":"Point"}
}