{
  "type": "Feature",
  "properties": {
    "iso:country":"ES",
    "sg:address":"C/ Bona-sort, 11",
    "sg:city":"Cerdanyola Valles",
    "sg:orig_category":"Frutas, Legumbres Frescas Y Tempranas (al Por Menor)",
    "sg:phone":"+34 935 92 04 36",
    "sg:postcode":"08290",
    "sg:province":"Barcelona",
    "wof:name":"Fruits Ripollet S. L.",
    "wof:placetype":"venue"
},
  "geometry": {"coordinates":[2.1390030384,41.4931526184],"type":"Point"}
}