{
  "type": "Feature",
  "properties": {
    "iso:country":"ES",
    "sg:address":"Calle de Gongora, 6",
    "sg:city":"Sax",
    "sg:orig_category":"Marroquiner\u00cda (confecci\u00d3n)",
    "sg:phone":"+34 966 96 76 54",
    "sg:postcode":"03630",
    "sg:province":"Alicante",
    "wof:name":"Maria Isabel Vizcaino S.l.",
    "wof:placetype":"venue"
},
  "geometry": {"coordinates":[-0.8235769868,38.5382003784],"type":"Point"}
}