{
  "type": "Feature",
  "properties": {
    "addr:full":"Calle de Ramon Y Cajal, 6 Pilar Horadada Alicante 03190",
    "addr:housenumber":"6",
    "addr:postcode":"03190",
    "addr:street":"Calle De Ramon Y Cajal",
    "iso:country":"ES",
    "sg:address":"Calle de Ramon Y Cajal, 6",
    "sg:city":"Pilar Horadada",
    "sg:orig_category":"Inmobiliaria (agencias)",
    "sg:phone":"+34 965 35 24 84",
    "sg:postcode":"03190",
    "sg:province":"Alicante",
    "wof:name":"Torre-litbel Sl",
    "wof:placetype":"venue"
},
  "geometry": {"coordinates":[-0.7898390293,37.8640213013],"type":"Point"}
}