{
  "type": "Feature",
  "properties": {
    "iso:country":"ES",
    "sg:address":"Calle de Escuelas, 10",
    "sg:city":"Calanda",
    "sg:orig_category":"Cr\u00cda De Cerdos",
    "sg:phone":"+34 978 84 62 28",
    "sg:postcode":"44570",
    "sg:province":"Teruel",
    "wof:name":"Ganados Julian Sl",
    "wof:placetype":"venue"
},
  "geometry": {"coordinates":[-0.2265727073,40.9390411377],"type":"Point"}
}