{
  "type": "Feature",
  "properties": {
    "addr:full":"Societat De Monts, 26 Alfarp Valencia 46197",
    "addr:housenumber":"26",
    "addr:postcode":"46197",
    "addr:street":"Alfarp",
    "iso:country":"ES",
    "sg:address":"Societat De Monts, 26",
    "sg:city":"Alfarp",
    "sg:orig_category":"Peluquer\u00cdas, Peluquer\u00cda Mixta",
    "sg:phone":"+34 962 99 10 86",
    "sg:postcode":"46197",
    "sg:province":"Valencia",
    "wof:name":"Navarro Sebastian Carolina",
    "wof:placetype":"venue"
},
  "geometry": {"coordinates":[-0.5605379939,39.2754478455],"type":"Point"}
}