{
  "type": "Feature",
  "properties": {
    "iso:country":"ES",
    "sg:address":"Calle de Santa Cristeta, 14",
    "sg:city":"Talavera Reina",
    "sg:orig_category":"Instalaci\u00d3n, Reparaci\u00d3n De Ascensores Y Montacargas",
    "sg:phone":"+34 925 82 77 00",
    "sg:postcode":"45600",
    "sg:province":"Toledo",
    "wof:name":"Orona S.c.l.",
    "wof:placetype":"venue"
},
  "geometry": {"coordinates":[-4.8289670944,39.9669036865],"type":"Point"}
}