{
  "type": "Feature",
  "properties": {
    "iso:country":"ES",
    "sg:address":"Carr Pi I Margall, 22",
    "sg:city":"Lleida",
    "sg:orig_category":"Doctores En Medicina",
    "sg:phone":"+34 973 23 19 74",
    "sg:postcode":"25004",
    "sg:province":"Lleida",
    "wof:name":"Barrio Novoa Juan Luis",
    "wof:placetype":"venue"
},
  "geometry": {"coordinates":[0.6284000278,41.6204833984],"type":"Point"}
}