{
  "type": "Feature",
  "properties": {
    "addr:full":"Lakuntza Kalea, 14 Iru\u00f1a Navarra 31015",
    "addr:housenumber":"14",
    "addr:postcode":"31015",
    "addr:street":"Lakuntza Kalea",
    "iso:country":"ES",
    "sg:address":"Lakuntza Kalea, 14",
    "sg:city":"Iru\u00f1a",
    "sg:orig_category":"Promotores Constructores",
    "sg:phone":"+34 948 14 63 92",
    "sg:postcode":"31015",
    "sg:province":"Navarra",
    "wof:name":"Salathe S.l.",
    "wof:placetype":"venue"
},
  "geometry": {"coordinates":[-1.6339310408,42.8237075806],"type":"Point"}
}