{
  "type": "Feature",
  "properties": {
    "iso:country":"ES",
    "sg:address":"Polig. Ind. Melide, 42",
    "sg:city":"Melide",
    "sg:orig_category":"M\u00c1rmoles, Granitos Y Piedras Naturales",
    "sg:phone":"+34 981 50 55 18",
    "sg:postcode":"15800",
    "sg:province":"La Coru\u00f1a",
    "wof:name":"Marmoleria Melide S.l.l",
    "wof:placetype":"venue"
},
  "geometry": {"coordinates":[-8.1010923386,42.9557991028],"type":"Point"}
}