{
  "type": "Feature",
  "properties": {
    "iso:country":"ES",
    "sg:address":"Calle de Murillo, 3",
    "sg:city":"Illescas",
    "sg:orig_category":"Alimentaci\u00d3n General (al Por Menor)",
    "sg:phone":"+34 925 51 32 41",
    "sg:postcode":"45200",
    "sg:province":"Toledo",
    "wof:name":"Olmedo Segador Africa",
    "wof:placetype":"venue"
},
  "geometry": {"coordinates":[-3.8479828835,40.1215591431],"type":"Point"}
}