{
  "type": "Feature",
  "properties": {
    "addr:full":"Pase Libertad (la), 24 Almansa Albacete 02640",
    "addr:housenumber":"24",
    "addr:postcode":"02640",
    "addr:street":"Libertad La",
    "iso:country":"ES",
    "sg:address":"Pase Libertad (la), 24",
    "sg:city":"Almansa",
    "sg:orig_category":"Servicios Gsm",
    "sg:phone":"+34 967 31 02 51",
    "sg:postcode":"02640",
    "sg:province":"Albacete",
    "wof:name":"Sistelcor Comunicaciones Ab S.l.",
    "wof:placetype":"venue"
},
  "geometry": {"coordinates":[-1.0956139565,38.8690605164],"type":"Point"}
}