{
  "type": "Feature",
  "properties": {
    "iso:country":"ES",
    "sg:address":"Carretera De La Mina, 6",
    "sg:city":"Castellote",
    "sg:orig_category":"Bosques (trabajos, Asesor\u00cda, Gesti\u00d3n)",
    "sg:phone":"+34 978 88 74 55",
    "sg:postcode":"44560",
    "sg:province":"Teruel",
    "wof:name":"Diputacion General De Aragon.servicio Provincial De Agricultura",
    "wof:placetype":"venue"
},
  "geometry": {"coordinates":[-0.3181439936,40.7997589111],"type":"Point"}
}