{
  "type": "Feature",
  "properties": {
    "addr:full":"Calle de Jose Lopez Oca\u00d1a, 10 Aviles Asturias 33401",
    "addr:housenumber":"10",
    "addr:postcode":"33401",
    "addr:street":"Calle De Jose;Ocan\u0303A",
    "iso:country":"ES",
    "sg:address":"Calle de Jose Lopez Oca\u00d1a, 10",
    "sg:city":"Aviles",
    "sg:orig_category":"Ropa Para Ni\u00d1os (al Por Menor)",
    "sg:phone":"+34 985 52 22 42",
    "sg:postcode":"33401",
    "sg:province":"Asturias",
    "wof:name":"Neck Child S.a.",
    "wof:placetype":"venue"
},
  "geometry": {"coordinates":[-5.9264979362,43.5585861206],"type":"Point"}
}