{
  "type": "Feature",
  "properties": {
    "iso:country":"ES",
    "sg:address":"Ctra. Segovia-aranda, S/n",
    "sg:city":"Fuenterrebollo",
    "sg:orig_category":"Centros M\u00c9dicos Y Sociales, Dispensarios",
    "sg:phone":"+34 921 52 09 37",
    "sg:postcode":"40330",
    "sg:province":"Segovia",
    "wof:name":"Ayuntamiento-centro Rural De Higiene",
    "wof:placetype":"venue"
},
  "geometry": {"coordinates":[-3.9572374821,41.3033103943],"type":"Point"}
}