{
  "type": "Feature",
  "properties": {
    "addr:full":"Avda Explosivos, S/n Guardo Palencia 34880",
    "addr:housenumber":"s / n",
    "addr:postcode":"34880",
    "addr:street":"Avda Explosivos",
    "iso:country":"ES",
    "sg:address":"Avda Explosivos, S/n",
    "sg:city":"Guardo",
    "sg:orig_category":"Fabricaci\u00d3n, Venta, Instalaci\u00d3n De R\u00d3tulos, De R\u00d3tulos Luminosos",
    "sg:phone":"+34 979 85 20 91",
    "sg:postcode":"34880",
    "sg:province":"Palencia",
    "wof:name":"Dise\u00f1o Promeil S.l.",
    "wof:placetype":"venue"
},
  "geometry": {"coordinates":[-4.8538370132,42.7872314453],"type":"Point"}
}