{
  "type": "Feature",
  "properties": {
    "iso:country":"ES",
    "sg:address":"Calle de Corredera, 113",
    "sg:city":"Lebrija",
    "sg:orig_category":"Muebles, Minoristas",
    "sg:phone":"+34 955 97 26 66",
    "sg:postcode":"41740",
    "sg:province":"Sevilla",
    "wof:name":"Rodriguez Arriaza Jose",
    "wof:placetype":"venue"
},
  "geometry": {"coordinates":[-6.0713534355,36.9201126099],"type":"Point"}
}