{
  "type": "Feature",
  "properties": {
    "iso:country":"ES",
    "sg:address":"Avda Virgen De Las Angustias, 2",
    "sg:city":"Cuenca",
    "sg:orig_category":"Cajas De Ahorro",
    "sg:phone":"+34 969 22 64 61",
    "sg:postcode":"16003",
    "sg:province":"Cuenca",
    "wof:name":"Caja De Ahorros De Castilla La Mancha",
    "wof:placetype":"venue"
},
  "geometry": {"coordinates":[-2.1381249428,40.0651512146],"type":"Point"}
}