{
  "type": "Feature",
  "properties": {
    "iso:country":"ES",
    "sg:address":"Avda Doctor Fleming, 35",
    "sg:city":"Montoro",
    "sg:orig_category":"Mec\u00c1nico Del Autom\u00d3vil",
    "sg:phone":"+34 957 16 16 00",
    "sg:postcode":"14600",
    "sg:province":"C\u00f3rdoba",
    "wof:name":"Capet Ruiz Lorenzo",
    "wof:placetype":"venue"
},
  "geometry": {"coordinates":[-4.3795437813,38.0132064819],"type":"Point"}
}