{
  "type": "Feature",
  "properties": {
    "addr:full":"Pase Herrera De, 82 Donostia-san Sebastian Guip\u00f9zcoa 20017",
    "addr:housenumber":"82",
    "addr:postcode":"20017",
    "iso:country":"ES",
    "sg:address":"Pase Herrera De, 82",
    "sg:city":"Donostia-san Sebastian",
    "sg:orig_category":"Ropa Para Caballeros (al Por Menor)",
    "sg:phone":"+34 943 35 28 29",
    "sg:postcode":"20017",
    "sg:province":"Guip\u00f9zcoa",
    "wof:name":"Avelina Vazquez Caama\u00f1o (moda De Hombre Izarra)",
    "wof:placetype":"venue"
},
  "geometry": {"coordinates":[-1.9308949709,43.3183784485],"type":"Point"}
}