{
  "type": "Feature",
  "properties": {
    "iso:country":"ES",
    "sg:address":"Calle de Gregorio Mara\u00d1on, 31",
    "sg:city":"Oviedo",
    "sg:orig_category":"Material Y Suministros Para Fotocopiadoras, Reprograf\u00cda",
    "sg:phone":"+34 985 27 28 02",
    "sg:postcode":"33012",
    "sg:province":"Asturias",
    "wof:name":"Servicios Tecnicos Del Principado S.l.",
    "wof:placetype":"venue"
},
  "geometry": {"coordinates":[-5.8632769585,43.3685302734],"type":"Point"}
}