{
  "type": "Feature",
  "properties": {
    "iso:country":"ES",
    "sg:address":"Calle de Cronista Viravens, 38",
    "sg:city":"Alacant",
    "sg:orig_category":"Mec\u00c1nico Del Autom\u00d3vil",
    "sg:phone":"+34 965 20 54 72",
    "sg:postcode":"03012",
    "sg:province":"Alicante",
    "wof:name":"Torres Salvador Jorge",
    "wof:placetype":"venue"
},
  "geometry": {"coordinates":[-0.482010603,38.3540458679],"type":"Point"}
}