{
  "type": "Feature",
  "properties": {
    "iso:country":"ES",
    "sg:address":"Calle de Oreja Marcelino, 1",
    "sg:city":"Bilbao",
    "sg:orig_category":"Tapicer\u00cdas",
    "sg:phone":"+34 944 21 78 61",
    "sg:postcode":"48010",
    "sg:province":"Vizcaya",
    "wof:name":"Cebrian Sainz Jose Maria",
    "wof:placetype":"venue"
},
  "geometry": {"coordinates":[-2.9397919178,43.2576217651],"type":"Point"}
}