{
  "type": "Feature",
  "properties": {
    "addr:full":"Calle de Oliva De Plasencia, S/n Madrid Madrid 28044",
    "addr:housenumber":"s / n",
    "addr:postcode":"28044",
    "addr:street":"Calle De Oliva De Plasencia",
    "iso:country":"ES",
    "sg:address":"Calle de Oliva De Plasencia, S/n",
    "sg:city":"Madrid",
    "sg:orig_category":"Loter\u00cda Y T\u00d3mbola",
    "sg:phone":"+34 917 05 85 16",
    "sg:postcode":"28044",
    "sg:province":"Madrid",
    "wof:name":"Alvarez Menendez Elisa",
    "wof:placetype":"venue"
},
  "geometry": {"coordinates":[-3.7771906853,40.3790016174],"type":"Point"}
}