{
  "type": "Feature",
  "properties": {
    "iso:country":"ES",
    "sg:address":"Calle de Casimiro Hernandez, 5",
    "sg:city":"Avila",
    "sg:orig_category":"M\u00c9dicos: Foniatr\u00cda Y Logopedia",
    "sg:phone":"+34 920 22 51 97",
    "sg:postcode":"05002",
    "sg:province":"\u00c1vila",
    "wof:name":"Lopez Alvarez Mercedes",
    "wof:placetype":"venue"
},
  "geometry": {"coordinates":[-4.7003850937,40.6534919739],"type":"Point"}
}