{
  "type": "Feature",
  "properties": {
    "addr:full":"Calle de Camilo Jose Cela, 9 Alhaurin El Grande M\u00e1laga 29120",
    "addr:housenumber":"9",
    "addr:postcode":"29120",
    "addr:street":"Calle De Camilo Jose Cela",
    "iso:country":"ES",
    "sg:address":"Calle de Camilo Jose Cela, 9",
    "sg:city":"Alhaurin El Grande",
    "sg:orig_category":"Agencias Y Agentes Comerciales, Representantes",
    "sg:phone":"+34 952 49 94 82",
    "sg:postcode":"29120",
    "sg:province":"M\u00e1laga",
    "wof:name":"Vilusol S.l.",
    "wof:placetype":"venue"
},
  "geometry": {"coordinates":[-4.6784939766,36.6451187134],"type":"Point"}
}