{
  "type": "Feature",
  "properties": {
    "addr:full":"Pla\u00c7 Del Mercat, 12 Benicarlo Castell\u00f3n 12580",
    "addr:housenumber":"12",
    "addr:postcode":"12580",
    "addr:street":"Mercat",
    "iso:country":"ES",
    "sg:address":"Pla\u00c7 Del Mercat, 12",
    "sg:city":"Benicarlo",
    "sg:orig_category":"Abogados",
    "sg:phone":"+34 964 46 01 80",
    "sg:postcode":"12580",
    "sg:province":"Castell\u00f3n",
    "wof:name":"Jev B S.l",
    "wof:placetype":"venue"
},
  "geometry": {"coordinates":[0.4042100012,40.4457893372],"type":"Point"}
}