{
  "type": "Feature",
  "properties": {
    "iso:country":"ES",
    "sg:address":"Calle de Real, 139",
    "sg:city":"S. Fernando",
    "sg:orig_category":"M\u00c9dicos: Oftalmolog\u00cda",
    "sg:phone":"+34 956 59 57 70",
    "sg:postcode":"11100",
    "sg:province":"C\u00e1diz",
    "wof:name":"Manito Pagan Rafael Juan",
    "wof:placetype":"venue"
},
  "geometry": {"coordinates":[-6.1972961426,36.4647216797],"type":"Point"}
}