{
  "type": "Feature",
  "properties": {
    "iso:country":"ES",
    "sg:address":"Carrer de Xiprer, 58",
    "sg:city":"Barcelona",
    "sg:orig_category":"Comit\u00c9s De Organizaci\u00d3n De Exposiciones, Ferias, Salones",
    "sg:phone":"+34 934 36 11 23",
    "sg:postcode":"08041",
    "sg:province":"Barcelona",
    "wof:name":"Nesher S.c.p.",
    "wof:placetype":"venue"
},
  "geometry": {"coordinates":[2.1803181171,41.4184837341],"type":"Point"}
}