{
  "type": "Feature",
  "properties": {
    "addr:full":"Carr Font (la), 11 Rosell Castell\u00f3n 12511",
    "addr:housenumber":"11",
    "addr:postcode":"12511",
    "addr:street":"Carr Font La;Castello\u0301N",
    "iso:country":"ES",
    "sg:address":"Carr Font (la), 11",
    "sg:city":"Rosell",
    "sg:orig_category":"Fabricaci\u00d3n De Art\u00cdculos Y Equipos Deportivos Y De Ocio",
    "sg:phone":"+34 977 57 13 71",
    "sg:postcode":"12511",
    "sg:province":"Castell\u00f3n",
    "wof:name":"Abella Royo Vicente",
    "wof:placetype":"venue"
},
  "geometry": {"coordinates":[0.155379,40.65633],"type":"Point"}
}