{
  "type": "Feature",
  "properties": {
    "iso:country":"ES",
    "sg:address":"Calle de Costa Brava, 33",
    "sg:city":"Madrid",
    "sg:orig_category":"Embajadas, Consulados Y Otras Representaciones Diplom\u00c1ticas",
    "sg:phone":"+34 914 11 76 27",
    "sg:postcode":"28034",
    "sg:province":"Madrid",
    "wof:name":"Embajada De Malasia",
    "wof:placetype":"venue"
},
  "geometry": {"coordinates":[-3.7058045864,40.4975013733],"type":"Point"}
}