{
  "type": "Feature",
  "properties": {
    "addr:full":"Calle de Trinidad, 31 Alcazar S. Juan Ciudad Real 13600",
    "addr:housenumber":"31",
    "addr:postcode":"13600",
    "addr:street":"Calle De Trinidad;Alcazar S. Juan Ciudad Real",
    "iso:country":"ES",
    "sg:address":"Calle de Trinidad, 31",
    "sg:city":"Alcazar S. Juan",
    "sg:orig_category":"Internados & Ense\u00d1anza Privada",
    "sg:phone":"+34 926 54 07 79",
    "sg:postcode":"13600",
    "sg:province":"Ciudad Real",
    "wof:name":"Comunidad En Alcazar De San Juan Orden Sma Trinidad Provincia De Espa\u00d1a Sur",
    "wof:placetype":"venue"
},
  "geometry": {"coordinates":[-3.2099199295,39.3945045471],"type":"Point"}
}