{
  "type": "Feature",
  "properties": {
    "iso:country":"ES",
    "sg:address":"Calle de Arrozal, 43",
    "sg:city":"Puebla Del Rio",
    "sg:orig_category":"Promotores Constructores",
    "sg:phone":"+34 955 77 23 85",
    "sg:postcode":"41130",
    "sg:province":"Sevilla",
    "wof:name":"Megradeco E24 S.l",
    "wof:placetype":"venue"
},
  "geometry": {"coordinates":[-6.0644598007,37.2607116699],"type":"Point"}
}