{
  "type": "Feature",
  "properties": {
    "addr:full":"Calle de Cid, 2 Miranda Ebro Burgos 09200",
    "addr:housenumber":"2",
    "addr:postcode":"09200",
    "addr:street":"Calle De Cid",
    "iso:country":"ES",
    "sg:address":"Calle de Cid, 2",
    "sg:city":"Miranda Ebro",
    "sg:orig_category":"Arenas, Guijarros Y Granulados",
    "sg:phone":"+34 947 34 70 19",
    "sg:postcode":"09200",
    "sg:province":"Burgos",
    "wof:name":"Gomez De Cadi\u00f1anos Lopez De Silanes Elisa",
    "wof:placetype":"venue"
},
  "geometry": {"coordinates":[-2.9451828003,42.6869621277],"type":"Point"}
}