{
  "type": "Feature",
  "properties": {
    "addr:full":"Plaz Espa\u00d1a, 2 Joyosa Zaragoza 50692",
    "addr:housenumber":"2",
    "addr:postcode":"50692",
    "addr:street":"Plaz Espan\u0303A",
    "iso:country":"ES",
    "sg:address":"Plaz Espa\u00d1a, 2",
    "sg:city":"Joyosa",
    "sg:orig_category":"Centros De Educaci\u00d3n Especial",
    "sg:phone":"+34 976 65 11 55",
    "sg:postcode":"50692",
    "sg:province":"Zaragoza",
    "wof:name":"Colegio Publico Ramon Y Cajal",
    "wof:placetype":"venue"
},
  "geometry": {"coordinates":[-1.0733640194,41.744758606],"type":"Point"}
}