{
  "type": "Feature",
  "properties": {
    "addr:full":"Plaz Hispanidad (de La), 5 Cuenca Cuenca 16004",
    "addr:postcode":"16004",
    "iso:country":"ES",
    "sg:address":"Plaz Hispanidad (de La), 5",
    "sg:city":"Cuenca",
    "sg:orig_category":"Estilistas Y Estudios De Estilo De Corte Y Confecci\u00d3n",
    "sg:phone":"+34 969 21 27 39",
    "sg:postcode":"16004",
    "sg:province":"Cuenca",
    "wof:name":"Comercial Yebenes S.a.",
    "wof:placetype":"venue"
},
  "geometry": {"coordinates":[-2.1362390518,40.0720710754],"type":"Point"}
}