{
  "type": "Feature",
  "properties": {
    "addr:full":"Carr Melilla, 19 Villarreal Castell\u00f3n 12540",
    "addr:housenumber":"19",
    "addr:postcode":"12540",
    "addr:street":"Carr Melilla",
    "iso:country":"ES",
    "sg:address":"Carr Melilla, 19",
    "sg:city":"Villarreal",
    "sg:orig_category":"Calderer\u00cda",
    "sg:phone":"+34 964 52 40 93",
    "sg:postcode":"12540",
    "sg:province":"Castell\u00f3n",
    "wof:name":"Industrial Salado S.a.",
    "wof:placetype":"venue"
},
  "geometry": {"coordinates":[-0.1124465987,39.9466094971],"type":"Point"}
}