{
  "type": "Feature",
  "properties": {
    "iso:country":"ES",
    "sg:address":"Avda Mar (el), S/n",
    "sg:city":"Costa Teguise",
    "sg:orig_category":"Alquiler De Veh\u00cdculos: Turismos Y Utilitarios",
    "sg:phone":"+34 928 59 12 89",
    "sg:postcode":"35509",
    "sg:province":"Las Palmas",
    "wof:name":"A. Cabrera S.l.",
    "wof:placetype":"venue"
},
  "geometry": {"coordinates":[-13.505488,28.990215],"type":"Point"}
}