{
  "type": "Feature",
  "properties": {
    "iso:country":"ES",
    "sg:address":"Calle de Fondos De Segura, 13",
    "sg:city":"Palmas De Gran Canaria",
    "sg:orig_category":"Inform\u00c1tica, Ofim\u00c1tica (estudios, Asesor\u00cda, Ingenier\u00cda, Formaci\u00d3n)",
    "sg:phone":"+34 928 38 56 26",
    "sg:postcode":"35019",
    "sg:province":"Las Palmas",
    "sg:website":"www.teinca.com",
    "wof:name":"Tecnoinformatica Canaria S.l.",
    "wof:placetype":"venue"
},
  "geometry": {"coordinates":[-15.4545154572,28.1019592285],"type":"Point"}
}