{
  "type": "Feature",
  "properties": {
    "addr:full":"Calle de Limones, 16 Jerez De La Frontera C\u00e1diz 11403",
    "addr:housenumber":"16",
    "addr:postcode":"11403",
    "addr:street":"Calle De Limones",
    "iso:country":"ES",
    "sg:address":"Calle de Limones, 16",
    "sg:city":"Jerez De La Frontera",
    "sg:orig_category":"Fabricaci\u00d3n De Juguetes Autom\u00c1ticos",
    "sg:phone":"+34 956 32 12 63",
    "sg:postcode":"11403",
    "sg:province":"C\u00e1diz",
    "wof:name":"Recreativos Nuevo Siglo S.l.",
    "wof:placetype":"venue"
},
  "geometry": {"coordinates":[-6.1403141022,36.6835327148],"type":"Point"}
}