{
  "type": "Feature",
  "properties": {
    "iso:country":"ES",
    "sg:address":"Calle de Sierra Morena (de La), 41",
    "sg:city":"Poligono De San Fernando De Henares",
    "sg:orig_category":"Productos Qu\u00cdmicos (fabricaci\u00d3n, Al Por Mayor)",
    "sg:phone":"+34 916 77 84 56",
    "sg:postcode":"28830",
    "sg:province":"Madrid",
    "wof:name":"Disarp S.a.",
    "wof:placetype":"venue"
},
  "geometry": {"coordinates":[-3.5034461021,40.4520988464],"type":"Point"}
}