{
  "type": "Feature",
  "properties": {
    "addr:full":"Calle de San Juan, 16 Benalup C\u00e1diz 11190",
    "addr:housenumber":"16",
    "addr:postcode":"11190",
    "addr:street":"Calle De San Juan;Ca\u0301Diz",
    "iso:country":"ES",
    "sg:address":"Calle de San Juan, 16",
    "sg:city":"Benalup",
    "sg:orig_category":"Estancos",
    "sg:phone":"+34 956 42 47 61",
    "sg:postcode":"11190",
    "sg:province":"C\u00e1diz",
    "wof:name":"Roman Marin Jesus Miguel",
    "wof:placetype":"venue"
},
  "geometry": {"coordinates":[-5.8136930466,36.3427314758],"type":"Point"}
}