{
  "type": "Feature",
  "properties": {
    "addr:full":"Calle de Villalba, 38 Poligono Industrial Los Villares Salamanca 37184",
    "addr:housenumber":"38",
    "addr:postcode":"37184",
    "addr:street":"Calle De Villalba;Industrial",
    "iso:country":"ES",
    "sg:address":"Calle de Villalba, 38",
    "sg:city":"Poligono Industrial Los Villares",
    "sg:orig_category":"Construcciones E Instalaciones Agr\u00cdcolas",
    "sg:phone":"+34 923 20 43 05",
    "sg:postcode":"37184",
    "sg:province":"Salamanca",
    "sg:website":"info@industriasmangas.com",
    "wof:name":"Industrias Mangas S. L.",
    "wof:placetype":"venue"
},
  "geometry": {"coordinates":[-5.6396541595,40.9895515442],"type":"Point"}
}