{
  "type": "Feature",
  "properties": {
    "addr:full":"Calle de Ibiza, 4 Madrid Madrid 28009",
    "addr:housenumber":"4",
    "addr:postcode":"28009",
    "addr:street":"Calle De Ibiza",
    "iso:country":"ES",
    "sg:address":"Calle de Ibiza, 4",
    "sg:city":"Madrid",
    "sg:orig_category":"Abogados",
    "sg:phone":"+34 915 73 55 77",
    "sg:postcode":"28009",
    "sg:province":"Madrid",
    "wof:name":"Eskumu S.l.",
    "wof:placetype":"venue"
},
  "geometry": {"coordinates":[-3.6781458855,40.4181594849],"type":"Point"}
}