{
  "type": "Feature",
  "properties": {
    "addr:full":"Francisco Rodriguez, 3 O Temple La Coru\u00f1a 15679",
    "addr:postcode":"15679",
    "addr:street":"Corun\u0303A",
    "iso:country":"ES",
    "sg:address":"Francisco Rodriguez, 3",
    "sg:city":"O Temple",
    "sg:orig_category":"Polideportivos",
    "sg:phone":"+34 981 66 57 20",
    "sg:postcode":"15679",
    "sg:province":"La Coru\u00f1a",
    "wof:name":"Concello De Cambre",
    "wof:placetype":"venue"
},
  "geometry": {"coordinates":[-8.3567819595,43.3196105957],"type":"Point"}
}