{
  "type": "Feature",
  "properties": {
    "iso:country":"ES",
    "sg:address":"Avda Menendez Pelayo, 65",
    "sg:city":"Madrid",
    "sg:orig_category":"Asociaciones Humanitarias, De Cooperaci\u00d3n, De Acci\u00d3n Social",
    "sg:phone":"+34 915 74 38 39",
    "sg:postcode":"28009",
    "sg:province":"Madrid",
    "wof:name":"Asociacion Espa\u00f1ola Proyecto Mielina",
    "wof:placetype":"venue"
},
  "geometry": {"coordinates":[-3.6771612167,40.4137763977],"type":"Point"}
}