{
  "type": "Feature",
  "properties": {
    "addr:full":"Calle de Buenavista, 72 Almendralejo Badajoz 06200",
    "addr:housenumber":"72",
    "addr:postcode":"06200",
    "addr:street":"Calle De Buenavista",
    "iso:country":"ES",
    "sg:address":"Calle de Buenavista, 72",
    "sg:city":"Almendralejo",
    "sg:orig_category":"Contenedores (mercanc\u00cdas)",
    "sg:phone":"+34 924 66 29 19",
    "sg:postcode":"06200",
    "sg:province":"Badajoz",
    "wof:name":"Alvarez Gonzalez Agustin",
    "wof:placetype":"venue"
},
  "geometry": {"coordinates":[-6.4069232941,38.6786460876],"type":"Point"}
}