{
  "type": "Feature",
  "properties": {
    "addr:full":"Calle de Jacinto Benavente, 45 Vitoria-gasteiz \u00c1lava 01003",
    "addr:housenumber":"45",
    "addr:postcode":"01003",
    "addr:street":"Calle De Jacinto Benavente",
    "iso:country":"ES",
    "sg:address":"Calle de Jacinto Benavente, 45",
    "sg:city":"Vitoria-gasteiz",
    "sg:orig_category":"Empresas De Pintura Y Revestimientos",
    "sg:phone":"+34 945 27 85 72",
    "sg:postcode":"01003",
    "sg:province":"\u00c1lava",
    "wof:name":"Alvarez-pedrosa Arias Carolina",
    "wof:placetype":"venue"
},
  "geometry": {"coordinates":[-2.6583073139,42.841796875],"type":"Point"}
}