{
  "type": "Feature",
  "properties": {
    "iso:country":"ES",
    "sg:address":"Calle de Imprenta De La Alborada, 109",
    "sg:city":"Cordoba",
    "sg:orig_category":"Revisi\u00d3n, Reconstrucci\u00d3n De M\u00c1quinas Y Herramientas",
    "sg:phone":"+34 957 32 62 07",
    "sg:postcode":"14014",
    "sg:province":"C\u00f3rdoba",
    "sg:website":"www.wurth.es",
    "wof:name":"Wurth Espa\u00f1a S.a.",
    "wof:placetype":"venue"
},
  "geometry": {"coordinates":[-4.7129192352,37.9000778198],"type":"Point"}
}