{
  "type": "Feature",
  "properties": {
    "addr:full":"Rua Brasil, 7 Noia A Coru\u00f1a 15200",
    "addr:housenumber":"7",
    "addr:postcode":"15200",
    "addr:street":"Rua Brasil;A Corun\u0303A",
    "iso:country":"ES",
    "sg:address":"Rua Brasil, 7",
    "sg:city":"Noia",
    "sg:orig_category":"Vinos Y Licores (venta Al Por Menor)",
    "sg:phone":"+34 981 82 01 89",
    "sg:postcode":"15200",
    "sg:province":"A Coru\u00f1a",
    "wof:name":"Tramutola  Luigino",
    "wof:placetype":"venue"
},
  "geometry": {"coordinates":[-8.8867788315,42.78125],"type":"Point"}
}