{
  "type": "Feature",
  "properties": {
    "iso:country":"ES",
    "sg:address":"Calle de Sierra Toledana, 9",
    "sg:city":"Madrid",
    "sg:orig_category":"Guarder\u00cdas",
    "sg:phone":"+34 914 39 72 71",
    "sg:postcode":"28038",
    "sg:province":"Madrid",
    "wof:name":"Escuela Infantil Los Juncos S.l.",
    "wof:placetype":"venue"
},
  "geometry": {"coordinates":[-3.6607630253,40.3999214172],"type":"Point"}
}