{
  "type": "Feature",
  "properties": {
    "iso:country":"ES",
    "sg:address":"Calle de Berdigon, 32",
    "sg:city":"Huelva",
    "sg:orig_category":"Animales (al Por Menor)",
    "sg:phone":"+34 959 25 39 40",
    "sg:postcode":"21003",
    "sg:province":"Huelva",
    "wof:name":"Rosa Panduro Maria De Los Angeles De La",
    "wof:placetype":"venue"
},
  "geometry": {"coordinates":[-6.9483709335,37.2549629211],"type":"Point"}
}