{
  "type": "Feature",
  "properties": {
    "iso:country":"ES",
    "sg:address":"Calle de Federico Garcia Lorca, S/n",
    "sg:city":"Albacete",
    "sg:orig_category":"Ingeniero",
    "sg:phone":"+34 967 24 89 44",
    "sg:postcode":"02001",
    "sg:province":"Albacete",
    "wof:name":"France Telecom Espa\u00d1a S.a.",
    "wof:placetype":"venue"
},
  "geometry": {"coordinates":[-1.8463389874,38.9959106445],"type":"Point"}
}