{
  "type": "Feature",
  "properties": {
    "addr:full":"Calle de Garzas, 12 Urbanizacion Hoya De Los Patos Alicante 03111",
    "addr:housenumber":"12",
    "addr:postcode":"03111",
    "addr:street":"Calle De Garzas;Urbanizacion Hoya De Los",
    "iso:country":"ES",
    "sg:address":"Calle de Garzas, 12",
    "sg:city":"Urbanizacion Hoya De Los Patos",
    "sg:orig_category":"Inform\u00c1tica Equipo Y Programas (al Por Mayor)",
    "sg:phone":"+34 965 69 80 63",
    "sg:postcode":"03111",
    "sg:province":"Alicante",
    "sg:website":"www.adiso.com",
    "wof:name":"Esparcia Llorca Lucia",
    "wof:placetype":"venue"
},
  "geometry": {"coordinates":[-0.4394569993,38.4667434692],"type":"Point"}
}