{
  "type": "Feature",
  "properties": {
    "iso:country":"ES",
    "sg:address":"Calle de Guevara, 17",
    "sg:city":"Santander",
    "sg:orig_category":"Ropa Para Se\u00d1oras (al Por Menor)",
    "sg:phone":"+34 942 22 33 46",
    "sg:postcode":"39001",
    "sg:province":"Cantabria",
    "wof:name":"Albella Barrena Maria Dolores",
    "wof:placetype":"venue"
},
  "geometry": {"coordinates":[-3.808255434,43.4637069702],"type":"Point"}
}