{
  "type": "Feature",
  "properties": {
    "addr:full":"Deba Kalea, 8 Elgoibar Guip\u00f9zcoa 20870",
    "addr:housenumber":"8",
    "addr:postcode":"20870",
    "addr:street":"Deba Kalea;Guipu\u0300Zcoa",
    "iso:country":"ES",
    "sg:address":"Deba Kalea, 8",
    "sg:city":"Elgoibar",
    "sg:orig_category":"Aparatos De Iluminaci\u00d3n (al Por Menor)",
    "sg:phone":"+34 943 74 36 02",
    "sg:postcode":"20870",
    "sg:province":"Guip\u00f9zcoa",
    "wof:name":"Garcia Bou Santiago",
    "wof:placetype":"venue"
},
  "geometry": {"coordinates":[-2.4104480743,43.2177772522],"type":"Point"}
}