{
  "type": "Feature",
  "properties": {
    "iso:country":"ES",
    "sg:address":"Carrer de Montserrat, 118",
    "sg:city":"Sabadell",
    "sg:orig_category":"Reposter\u00cdas",
    "sg:phone":"+34 937 26 17 15",
    "sg:postcode":"08201",
    "sg:province":"Barcelona",
    "wof:name":"Roca Ferrer Pedro",
    "wof:placetype":"venue"
},
  "geometry": {"coordinates":[2.1068170071,41.5427436829],"type":"Point"}
}