{
  "type": "Feature",
  "properties": {
    "iso:country":"ES",
    "sg:address":"Calle de Reyes Catolicos, 10",
    "sg:city":"Alacant",
    "sg:orig_category":"Lencer\u00cda Femenina, Corseter\u00cda, Trajes De Ba\u00d1o (al Por Menor)",
    "sg:phone":"+34 965 13 25 70",
    "sg:postcode":"03003",
    "sg:province":"Alicante",
    "wof:name":"Sanchez Sanchez Maria Amelia",
    "wof:placetype":"venue"
},
  "geometry": {"coordinates":[-0.4894919991,38.342956543],"type":"Point"}
}