{
  "type": "Feature",
  "properties": {
    "iso:country":"ES",
    "sg:address":"Calle de Gudari, 33",
    "sg:city":"Amorebieta",
    "sg:orig_category":"Empresas De Carpinter\u00cda Met\u00c1lica",
    "sg:phone":"+34 946 30 10 15",
    "sg:postcode":"48340",
    "sg:province":"Vizcaya",
    "wof:name":"Dudea Egiturak S.l.",
    "wof:placetype":"venue"
},
  "geometry": {"coordinates":[-2.7403690815,43.2183113098],"type":"Point"}
}