{
  "type": "Feature",
  "properties": {
    "iso:country":"ES",
    "sg:address":"Calle de Niquel (pol. Ind.), 38",
    "sg:city":"Marbella",
    "sg:orig_category":"Promotores Constructores",
    "sg:phone":"+34 952 77 61 93",
    "sg:postcode":"29600",
    "sg:province":"M\u00e1laga",
    "wof:name":"Proquichel Marbella S.l.",
    "wof:placetype":"venue"
},
  "geometry": {"coordinates":[-4.8712568283,36.5117721558],"type":"Point"}
}