{
  "type": "Feature",
  "properties": {
    "addr:full":"Rio Altzania, 19 Iru\u00f1a Navarra 31005",
    "addr:housenumber":"19",
    "addr:postcode":"31005",
    "addr:street":"Rio Altzania",
    "iso:country":"ES",
    "sg:address":"Rio Altzania, 19",
    "sg:city":"Iru\u00f1a",
    "sg:orig_category":"Librer\u00cdas",
    "sg:phone":"+34 948 24 21 43",
    "sg:postcode":"31005",
    "sg:province":"Navarra",
    "wof:name":"Oyarzun Etulain Felix",
    "wof:placetype":"venue"
},
  "geometry": {"coordinates":[-1.6456090212,42.8039703369],"type":"Point"}
}