{
  "type": "Feature",
  "properties": {
    "iso:country":"ES",
    "sg:address":"Fuente Alamo, S/n",
    "sg:city":"Cuevas Almanzora",
    "sg:orig_category":"Promotores Constructores",
    "sg:phone":"+34 950 45 70 35",
    "sg:postcode":"04610",
    "sg:province":"Almer\u00eda",
    "wof:name":"Caparros Navarro Manuel",
    "wof:placetype":"venue"
},
  "geometry": {"coordinates":[-1.8824290037,37.298664093],"type":"Point"}
}