{
  "type": "Feature",
  "properties": {
    "iso:country":"ES",
    "sg:address":"Rond Sant Pere, 19",
    "sg:city":"Barcelona",
    "sg:orig_category":"Empresarios",
    "sg:phone":"+34 933 19 38 60",
    "sg:postcode":"08010",
    "sg:province":"Barcelona",
    "sg:website":"www.fundacio.org",
    "wof:name":"Fundacio Privada Industries De La Carn",
    "wof:placetype":"venue"
},
  "geometry": {"coordinates":[2.1738159657,41.3894882202],"type":"Point"}
}