{
  "type": "Feature",
  "properties": {
    "iso:country":"ES",
    "sg:address":"Carrer de Tamarit, 104",
    "sg:city":"Barcelona",
    "sg:orig_category":"Discapacitados",
    "sg:phone":"+34 934 24 27 77",
    "sg:postcode":"08015",
    "sg:province":"Barcelona",
    "wof:name":"Fundacio Esclerosis Multiple",
    "wof:placetype":"venue"
},
  "geometry": {"coordinates":[2.1578640938,41.3761291504],"type":"Point"}
}