{
  "type": "Feature",
  "properties": {
    "iso:country":"ES",
    "sg:address":"Plaz San Juan, 3",
    "sg:city":"Porcuna",
    "sg:orig_category":"Arquitectos",
    "sg:phone":"+34 953 54 44 12",
    "sg:postcode":"23790",
    "sg:province":"Ja\u00e9n",
    "wof:name":"Garcia Lopez Ana Pilar",
    "wof:placetype":"venue"
},
  "geometry": {"coordinates":[-4.2128338814,37.8397483826],"type":"Point"}
}