{
  "type": "Feature",
  "properties": {
    "iso:country":"ES",
    "sg:address":"Errotatxu Bl B, 8",
    "sg:city":"Algorta",
    "sg:orig_category":"Art\u00cdculos De Madera (fabricaci\u00d3n Y Al Por Mayor)",
    "sg:phone":"+34 944 30 06 31",
    "sg:postcode":"48993",
    "sg:province":"Vizcaya",
    "wof:name":"Decocarpi S.l.",
    "wof:placetype":"venue"
},
  "geometry": {"coordinates":[-3.0094540119,43.3488540649],"type":"Point"}
}