{
  "type": "Feature",
  "properties": {
    "addr:full":"La Barrera, 10 Tira\u00f1a Asturias 33979",
    "addr:housenumber":"10",
    "addr:postcode":"33979",
    "addr:street":"Barrera;Asturias",
    "iso:country":"ES",
    "sg:address":"La Barrera, 10",
    "sg:city":"Tira\u00f1a",
    "sg:orig_category":"Alimentaci\u00d3n Animal (fabricaci\u00d3n, Al Por Mayor)",
    "sg:phone":"+34 985 60 00 87",
    "sg:postcode":"33979",
    "sg:province":"Asturias",
    "wof:name":"Nava Garcia Camilo",
    "wof:placetype":"venue"
},
  "geometry": {"coordinates":[-5.5448679924,43.2816925049],"type":"Point"}
}