{
  "type": "Feature",
  "properties": {
    "addr:full":"Calle de Brezo (del), 10 Arganda Madrid 28500",
    "addr:housenumber":"10",
    "addr:postcode":"28500",
    "addr:street":"Calle De Brezo Del",
    "iso:country":"ES",
    "sg:address":"Calle de Brezo (del), 10",
    "sg:city":"Arganda",
    "sg:orig_category":"Cervezas, Bebidas (al Por Mayor)",
    "sg:phone":"+34 918 70 03 81",
    "sg:postcode":"28500",
    "sg:province":"Madrid",
    "wof:name":"Pecodisa S.l.",
    "wof:placetype":"venue"
},
  "geometry": {"coordinates":[-3.4662282467,40.3151550293],"type":"Point"}
}