{
  "type": "Feature",
  "properties": {
    "iso:country":"ES",
    "sg:address":"Calle de Juan Tornero, 42",
    "sg:city":"Madrid",
    "sg:orig_category":"Farmacias",
    "sg:phone":"+34 914 64 64 80",
    "sg:postcode":"28011",
    "sg:province":"Madrid",
    "wof:name":"Alvarez Blazquez Maria Del Mar",
    "wof:placetype":"venue"
},
  "geometry": {"coordinates":[-3.727686882,40.4116134644],"type":"Point"}
}