{
  "type": "Feature",
  "properties": {
    "iso:country":"ES",
    "sg:address":"Calle de Tera, 1",
    "sg:city":"Bosque",
    "sg:classifiers":[
        {
            "category":"Arts & Performance",
            "subcategory":"Art Gallery",
            "type":"Entertainment"
        }
    ],
    "sg:phone":"+34 916 16 80 54",
    "sg:postcode":"28670",
    "sg:province":"Madrid",
    "sg:tags":[
        "arte",
        "de",
        "galer\u00cdas"
    ],
    "wof:name":"De Arte Figueroa S.l.",
    "wof:placetype":"venue"
},
  "geometry": {"coordinates":[-3.9317350388,40.385055542],"type":"Point"}
}