{
  "type": "Feature",
  "properties": {
    "addr:full":"Plaz Escultor Francisco Badia, 2 Foios Valencia 46134",
    "addr:housenumber":"2",
    "addr:postcode":"46134",
    "addr:street":"Francisco Badia",
    "iso:country":"ES",
    "sg:address":"Plaz Escultor Francisco Badia, 2",
    "sg:city":"Foios",
    "sg:orig_category":"Fotograf\u00cda Y Cine: Aparatos, Pel\u00cdculas Y Accesorios (fabricaci\u00d3n, Al Por Mayor)",
    "sg:phone":"+34 961 49 04 08",
    "sg:postcode":"46134",
    "sg:province":"Valencia",
    "wof:name":"Parra Juanes Maria Del Carmen",
    "wof:placetype":"venue"
},
  "geometry": {"coordinates":[-0.3495889902,39.5365409851],"type":"Point"}
}