{
  "type": "Feature",
  "properties": {
    "iso:country":"ES",
    "sg:address":"Calle de Penyagolosa, 1",
    "sg:city":"Vall D'uixo",
    "sg:orig_category":"Servicios De Telecomunicaciones",
    "sg:phone":"+34 964 66 64 83",
    "sg:postcode":"12600",
    "sg:province":"Castell\u00f3n",
    "wof:name":"Maroto Martinez Javier",
    "wof:placetype":"venue"
},
  "geometry": {"coordinates":[-0.0396069996,39.9945373535],"type":"Point"}
}