{
  "type": "Feature",
  "properties": {
    "iso:country":"ES",
    "sg:address":"Calle de Felix Rodriguez De La Fuente, 9",
    "sg:city":"Algete",
    "sg:orig_category":"Molduras, Junquillos, Listones Y Molduras Perforadas",
    "sg:phone":"+34 916 29 25 71",
    "sg:postcode":"28110",
    "sg:province":"Madrid",
    "wof:name":"Blanco Palomo Aurelio",
    "wof:placetype":"venue"
},
  "geometry": {"coordinates":[-3.495388031,40.5938644409],"type":"Point"}
}