{
  "type": "Feature",
  "properties": {
    "iso:country":"ES",
    "sg:address":"Calle de Entredicho, 16",
    "sg:city":"Viso Marques",
    "sg:orig_category":"Empresas De Pintura Y Revestimientos",
    "sg:phone":"+34 926 33 62 23",
    "sg:postcode":"13770",
    "sg:province":"Ciudad Real",
    "wof:name":"Decoraciones Valencia Marin S.l.",
    "wof:placetype":"venue"
},
  "geometry": {"coordinates":[-3.565237999,38.5183525085],"type":"Point"}
}