{
  "type": "Feature",
  "properties": {
    "addr:full":"Calle de Duque De Lerma, 1 Sanlucar Mayor Sevilla 41800",
    "addr:housenumber":"1",
    "addr:postcode":"41800",
    "addr:street":"Calle De Duque De Lerma",
    "iso:country":"ES",
    "sg:address":"Calle de Duque De Lerma, 1",
    "sg:city":"Sanlucar Mayor",
    "sg:orig_category":"Promotores Constructores",
    "sg:phone":"+34 955 70 06 64",
    "sg:postcode":"41800",
    "sg:province":"Sevilla",
    "wof:name":"Montealjarafe S.l.",
    "wof:placetype":"venue"
},
  "geometry": {"coordinates":[-6.1996264458,37.3873748779],"type":"Point"}
}