{
  "type": "Feature",
  "properties": {
    "addr:full":"Calle de Perez Diaz, 4 Victoria Acentejo Santa Cruz De Tenerife 38380",
    "addr:housenumber":"4",
    "addr:postcode":"38380",
    "addr:street":"Calle De Perez Diaz",
    "iso:country":"ES",
    "sg:address":"Calle de Perez Diaz, 4",
    "sg:city":"Victoria Acentejo",
    "sg:orig_category":"Asesor\u00cda Sobre Comunicaci\u00d3n De Empresas",
    "sg:phone":"+34 922 58 16 27",
    "sg:postcode":"38380",
    "sg:province":"Santa Cruz De Tenerife",
    "wof:name":"Hernandez Luis Luz Mirian",
    "wof:placetype":"venue"
},
  "geometry": {"coordinates":[-16.4666500092,28.4359455109],"type":"Point"}
}