{
  "type": "Feature",
  "properties": {
    "addr:full":"Carrer de Santa Clara, 28 Vilafranca Penedes Barcelona 08720",
    "addr:housenumber":"28",
    "addr:postcode":"08720",
    "addr:street":"Carrer De Santa Clara;Penedes Barcelona",
    "iso:country":"ES",
    "sg:address":"Carrer de Santa Clara, 28",
    "sg:city":"Vilafranca Penedes",
    "sg:orig_category":"Inmobiliaria (agencias)",
    "sg:phone":"+34 938 18 22 68",
    "sg:postcode":"08720",
    "sg:province":"Barcelona",
    "wof:name":"Moncusi S.a.",
    "wof:placetype":"venue"
},
  "geometry": {"coordinates":[1.7019269466,41.346736908],"type":"Point"}
}