{
  "type": "Feature",
  "properties": {
    "iso:country":"ES",
    "sg:address":"Carrer de Santalo, 11",
    "sg:city":"Barcelona",
    "sg:orig_category":"Seguridad En El Trabajo Y Prevenci\u00d3n De Riesgos Laborales",
    "sg:phone":"+34 932 09 16 09",
    "sg:postcode":"08021",
    "sg:province":"Barcelona",
    "wof:name":"Pirretas Borras Enrique",
    "wof:placetype":"venue"
},
  "geometry": {"coordinates":[2.1465780735,41.3948364258],"type":"Point"}
}