{
  "type": "Feature",
  "properties": {
    "addr:full":"Calle de Pedro Garcia Villalba, 22 Alberca De Las Torres Murcia 30150",
    "addr:housenumber":"22",
    "addr:postcode":"30150",
    "addr:street":"Calle De Pedro;Villalba",
    "iso:country":"ES",
    "sg:address":"Calle de Pedro Garcia Villalba, 22",
    "sg:city":"Alberca De Las Torres",
    "sg:orig_category":"Asesor\u00cda, Estudio Y Control Medioambiental",
    "sg:phone":"+34 968 84 07 72",
    "sg:postcode":"30150",
    "sg:province":"Murcia",
    "wof:name":"Latizal,s.l",
    "wof:placetype":"venue"
},
  "geometry": {"coordinates":[-1.1390355825,37.9390068054],"type":"Point"}
}