{
  "type": "Feature",
  "properties": {
    "addr:full":"Cami Capellanets, 72 Mataro Barcelona 08303",
    "addr:housenumber":"72",
    "addr:postcode":"08303",
    "addr:street":"Capellanets",
    "iso:country":"ES",
    "sg:address":"Cami Capellanets, 72",
    "sg:city":"Mataro",
    "sg:orig_category":"Hilaturas, Hilos Y Actividades Relacionadas",
    "sg:phone":"+34 937 57 13 40",
    "sg:postcode":"08303",
    "sg:province":"Barcelona",
    "wof:name":"Orellana Rios Blasina",
    "wof:placetype":"venue"
},
  "geometry": {"coordinates":[2.4259340763,41.5445518494],"type":"Point"}
}