{
  "type": "Feature",
  "properties": {
    "addr:full":"Calle de San Bartolome, 7 Beas Huelva 21630",
    "addr:housenumber":"7",
    "addr:postcode":"21630",
    "addr:street":"Calle De San Bartolome;Huelva",
    "iso:country":"ES",
    "sg:address":"Calle de San Bartolome, 7",
    "sg:city":"Beas",
    "sg:orig_category":"Cajas De Ahorro",
    "sg:phone":"+34 959 30 91 54",
    "sg:postcode":"21630",
    "sg:province":"Huelva",
    "sg:website":"www.unicaja.es",
    "wof:name":"Unicaja",
    "wof:placetype":"venue"
},
  "geometry": {"coordinates":[-6.7926330566,37.425994873],"type":"Point"}
}