{
  "type": "Feature",
  "properties": {
    "iso:country":"ES",
    "sg:address":"Las Pedrizas, 2",
    "sg:city":"Cajar",
    "sg:orig_category":"Inmobiliaria (agencias)",
    "sg:phone":"+34 958 30 10 44",
    "sg:postcode":"18198",
    "sg:province":"Granada",
    "wof:name":"Ag Futuro S.l.",
    "wof:placetype":"venue"
},
  "geometry": {"coordinates":[-3.5694506168,37.1337547302],"type":"Point"}
}