{
  "type": "Feature",
  "properties": {
    "addr:full":"Calle de Alango, 7 Getxo Vizcaya 48990",
    "addr:housenumber":"7",
    "addr:postcode":"48990",
    "addr:street":"Calle De Alango",
    "iso:country":"ES",
    "sg:address":"Calle de Alango, 7",
    "sg:city":"Getxo",
    "sg:orig_category":"Art\u00cdculos De Decoraci\u00d3n",
    "sg:phone":"+34 944 91 19 78",
    "sg:postcode":"48990",
    "sg:province":"Vizcaya",
    "wof:name":"Teresa Gonzalez Barrena",
    "wof:placetype":"venue"
},
  "geometry": {"coordinates":[-3.0086569786,43.3472824097],"type":"Point"}
}