{
  "type": "Feature",
  "properties": {
    "iso:country":"ES",
    "sg:address":"Avda Paz (la), 52",
    "sg:city":"Peralta",
    "sg:orig_category":"Molduras, Junquillos, Listones Y Molduras Perforadas",
    "sg:phone":"+34 948 75 01 77",
    "sg:postcode":"31350",
    "sg:province":"Navarra",
    "wof:name":"Zorrilla Aranaz Juan Julian",
    "wof:placetype":"venue"
},
  "geometry": {"coordinates":[-1.8050130606,42.3389587402],"type":"Point"}
}