{
  "type": "Feature",
  "properties": {
    "iso:country":"ES",
    "sg:address":"Avda Andenes (de Los), 4",
    "sg:city":"Caravaca Cruz",
    "sg:orig_category":"Caf\u00c9s, Bares, Cervecer\u00cdas",
    "sg:phone":"+34 968 70 23 06",
    "sg:postcode":"30400",
    "sg:province":"Murcia",
    "wof:name":"Surtel Comunicaciones S L",
    "wof:placetype":"venue"
},
  "geometry": {"coordinates":[-1.8655209541,38.1053237915],"type":"Point"}
}