{
  "type": "Feature",
  "properties": {
    "iso:country":"ES",
    "sg:address":"Avda El Ferial, 44",
    "sg:city":"Benavente",
    "sg:orig_category":"Molduras, Junquillos, Listones Y Molduras Perforadas",
    "sg:phone":"+34 980 63 64 23",
    "sg:postcode":"49600",
    "sg:province":"Zamora",
    "wof:name":"Campo Dieguez Joaquin",
    "wof:placetype":"venue"
},
  "geometry": {"coordinates":[-5.6743888855,42.0017700195],"type":"Point"}
}