{
  "type": "Feature",
  "properties": {
    "addr:full":"Rbla Salvador Sama, 112 Vilanova I La Geltru Barcelona 08800",
    "addr:housenumber":"112",
    "addr:postcode":"08800",
    "addr:street":"Rbla Salvador Sama",
    "iso:country":"ES",
    "sg:address":"Rbla Salvador Sama, 112",
    "sg:city":"Vilanova I La Geltru",
    "sg:orig_category":"Promotores Constructores",
    "sg:phone":"+34 938 16 01 46",
    "sg:postcode":"08800",
    "sg:province":"Barcelona",
    "wof:name":"Estructuras I.vala S.l",
    "wof:placetype":"venue"
},
  "geometry": {"coordinates":[1.7245270014,41.2198905945],"type":"Point"}
}