{
  "type": "Feature",
  "properties": {
    "iso:country":"ES",
    "sg:address":"Calle de Gordillo, 43",
    "sg:city":"Palmas De Gran Canaria",
    "sg:orig_category":"Suministros Y Materiales Industriales",
    "sg:phone":"+34 928 46 19 10",
    "sg:postcode":"35009",
    "sg:province":"Las Palmas",
    "wof:name":"Comercial Franumar Canarias S.l.",
    "wof:placetype":"venue"
},
  "geometry": {"coordinates":[-15.4263238907,28.1506328583],"type":"Point"}
}