{
  "type": "Feature",
  "properties": {
    "addr:full":"C/ Major Del Pla, 5 Elche Alicante 03201",
    "addr:housenumber":"5",
    "addr:postcode":"03201",
    "addr:street":"C / Major Del Pla",
    "iso:country":"ES",
    "sg:address":"C/ Major Del Pla, 5",
    "sg:city":"Elche",
    "sg:orig_category":"Inform\u00c1tica, Ofim\u00c1tica (estudios, Asesor\u00cda, Ingenier\u00cda, Formaci\u00d3n)",
    "sg:phone":"+34 966 66 05 64",
    "sg:postcode":"03201",
    "sg:province":"Alicante",
    "sg:website":"www.tpinformatica.net",
    "wof:name":"Tp Informatica Y Servicios S.l.",
    "wof:placetype":"venue"
},
  "geometry": {"coordinates":[-0.7009819746,38.2631568909],"type":"Point"}
}