{
  "type": "Feature",
  "properties": {
    "addr:full":"Ctra Sierra Alhamilla, 292 Almeria Almer\u00eda 04009",
    "addr:housenumber":"292",
    "addr:postcode":"04009",
    "addr:street":"Ctra Sierra Alhamilla",
    "iso:country":"ES",
    "sg:address":"Ctra Sierra Alhamilla, 292",
    "sg:city":"Almeria",
    "sg:orig_category":"Negocio De Materiales De Construcci\u00d3n",
    "sg:phone":"+34 950 22 42 83",
    "sg:postcode":"04009",
    "sg:province":"Almer\u00eda",
    "wof:name":"Azulejos Iba\u00f1ez E Hijos S. A.",
    "wof:placetype":"venue"
},
  "geometry": {"coordinates":[-2.4403350353,36.8404045105],"type":"Point"}
}