{
  "type": "Feature",
  "properties": {
    "addr:full":"Pol Ind Congost, 31 Llerona Barcelona 08520",
    "addr:housenumber":"31",
    "addr:postcode":"08520",
    "addr:street":"Congost",
    "iso:country":"ES",
    "sg:address":"Pol Ind Congost, 31",
    "sg:city":"Llerona",
    "sg:orig_category":"Fabricaci\u00d3n De Bibliotecas Y Estanter\u00cdas",
    "sg:phone":"+34 938 40 45 52",
    "sg:postcode":"08520",
    "sg:province":"Barcelona",
    "wof:name":"Estanterias Metalicas Record S.l.",
    "wof:placetype":"venue"
},
  "geometry": {"coordinates":[2.2992899418,41.6361808777],"type":"Point"}
}