{
  "type": "Feature",
  "properties": {
    "iso:country":"ES",
    "sg:address":"Calle de Santo Domingo, 31",
    "sg:city":"Vitoria-gasteiz",
    "sg:orig_category":"Asociaciones, Organismos Culturales Y Socioeducativos",
    "sg:phone":"+34 945 13 23 76",
    "sg:postcode":"01001",
    "sg:province":"\u00c1lava",
    "wof:name":"Sociedad Cultural Gastronomica",
    "wof:placetype":"venue"
},
  "geometry": {"coordinates":[-2.6735041142,42.8515853882],"type":"Point"}
}