{
  "type": "Feature",
  "properties": {
    "iso:country":"ES",
    "sg:address":"Carrer de Llu\u00c7anes, 8",
    "sg:city":"Barcelona",
    "sg:orig_category":"Mec\u00c1nico Del Autom\u00d3vil",
    "sg:phone":"+34 932 12 79 31",
    "sg:postcode":"08022",
    "sg:province":"Barcelona",
    "wof:name":"Casals Taron Francisco",
    "wof:placetype":"venue"
},
  "geometry": {"coordinates":[2.1333088875,41.4073257446],"type":"Point"}
}