{
  "type": "Feature",
  "properties": {
    "addr:full":"Calle de Estacion, 28 Miranda Ebro Burgos 09200",
    "addr:housenumber":"28",
    "addr:postcode":"09200",
    "addr:street":"Calle De Estacion",
    "iso:country":"ES",
    "sg:address":"Calle de Estacion, 28",
    "sg:city":"Miranda Ebro",
    "sg:orig_category":"Ense\u00d1anza: Idiomas",
    "sg:phone":"+34 947 34 70 41",
    "sg:postcode":"09200",
    "sg:province":"Burgos",
    "wof:name":"Liceo De Idiomas Modernos S.l.",
    "wof:placetype":"venue"
},
  "geometry": {"coordinates":[-2.9451560974,42.6868782043],"type":"Point"}
}