{
  "type": "Feature",
  "properties": {
    "iso:country":"ES",
    "sg:address":"Ctra. Nacional V, 6",
    "sg:city":"Lagartera",
    "sg:orig_category":"Fabrica De Cer\u00c1micas",
    "sg:phone":"+34 925 43 05 38",
    "sg:postcode":"45567",
    "sg:province":"Toledo",
    "wof:name":"Manzano Serrano Adolfo",
    "wof:placetype":"venue"
},
  "geometry": {"coordinates":[-5.2019591331,39.9126167297],"type":"Point"}
}