{
  "type": "Feature",
  "properties": {
    "addr:full":"Calle de Luis Montoto, 88 Sevilla Sevilla 41018",
    "addr:housenumber":"88",
    "addr:postcode":"41018",
    "addr:street":"Calle De Luis Montoto",
    "iso:country":"ES",
    "sg:address":"Calle de Luis Montoto, 88",
    "sg:city":"Sevilla",
    "sg:orig_category":"Sociedades, Compa\u00d1\u00cdas Aseguradoras",
    "sg:phone":"+34 954 42 22 11",
    "sg:postcode":"41018",
    "sg:province":"Sevilla",
    "wof:name":"Sanchez Pomar Nicolas V",
    "wof:placetype":"venue"
},
  "geometry": {"coordinates":[-5.9769940376,37.3870315552],"type":"Point"}
}