{
  "type": "Feature",
  "properties": {
    "iso:country":"ES",
    "sg:address":"Calle de Miguel Zapata, 12",
    "sg:city":"San Javier",
    "sg:orig_category":"Producci\u00d3n, Venta De Productos De Agricultura Biol\u00d3gica",
    "sg:phone":"+34 968 57 34 03",
    "sg:postcode":"30730",
    "sg:province":"Murcia",
    "wof:name":"Explotaciones Agricolas Sandoval S.l.",
    "wof:placetype":"venue"
},
  "geometry": {"coordinates":[-0.8362699747,37.8059196472],"type":"Point"}
}