{
  "type": "Feature",
  "properties": {
    "iso:country":"ES",
    "sg:address":"Calle de Valdes Pumarino, 23",
    "sg:city":"Candas",
    "sg:orig_category":"\u00d3ptica: Instrumentos (fabricaci\u00d3n)",
    "sg:phone":"+34 985 87 21 23",
    "sg:postcode":"33430",
    "sg:province":"Asturias",
    "wof:name":"Mayo Garcia Maria Teresa",
    "wof:placetype":"venue"
},
  "geometry": {"coordinates":[-5.7639107704,43.5901603699],"type":"Point"}
}