{
  "type": "Feature",
  "properties": {
    "addr:full":"Concepcion Arenal(p I Garrofera), 34 Alaquas Valencia 46970",
    "addr:housenumber":"34",
    "addr:postcode":"46970",
    "addr:street":"Concepcion Arenal P;Garrofera",
    "iso:country":"ES",
    "sg:address":"Concepcion Arenal(p I Garrofera), 34",
    "sg:city":"Alaquas",
    "sg:orig_category":"Madera Para Chapado",
    "sg:phone":"+34 961 98 81 63",
    "sg:postcode":"46970",
    "sg:province":"Valencia",
    "sg:website":"www.sipwood.com",
    "wof:name":"Sipwood S.l.",
    "wof:placetype":"venue"
},
  "geometry": {"coordinates":[-0.4820590019,39.4498558044],"type":"Point"}
}