{
  "type": "Feature",
  "properties": {
    "iso:country":"ES",
    "sg:address":"Calle de Aduana, 6",
    "sg:city":"Irun",
    "sg:orig_category":"Inmobiliaria (agencias)",
    "sg:phone":"+34 943 61 48 59",
    "sg:postcode":"20303",
    "sg:province":"Guip\u00f9zcoa",
    "wof:name":"Gonzalo C. Navascues Fernandez (inmob. Bahia)",
    "wof:placetype":"venue"
},
  "geometry": {"coordinates":[-1.7972345352,43.3405570984],"type":"Point"}
}