{
  "type": "Feature",
  "properties": {
    "addr:full":"Calle de Paseo Pablo Rada, 16 Caparroso Navarra 31380",
    "addr:housenumber":"16",
    "addr:postcode":"31380",
    "addr:street":"Calle De Paseo Pablo Rada",
    "iso:country":"ES",
    "sg:address":"Calle de Paseo Pablo Rada, 16",
    "sg:city":"Caparroso",
    "sg:orig_category":"Bisuter\u00cda, Joyer\u00cda, Relojer\u00cda (al Por Menor)",
    "sg:phone":"+34 948 71 09 40",
    "sg:postcode":"31380",
    "sg:province":"Navarra",
    "wof:name":"Costa Rol Jose Antonio",
    "wof:placetype":"venue"
},
  "geometry": {"coordinates":[-1.6525110006,42.3412742615],"type":"Point"}
}