{
  "type": "Feature",
  "properties": {
    "addr:full":"Calle de Aguilas, 27 Sevilla Sevilla 41003",
    "addr:housenumber":"27",
    "addr:postcode":"41003",
    "addr:street":"Calle De Aguilas",
    "iso:country":"ES",
    "sg:address":"Calle de Aguilas, 27",
    "sg:city":"Sevilla",
    "sg:orig_category":"Abogados",
    "sg:phone":"+34 954 56 45 76",
    "sg:postcode":"41003",
    "sg:province":"Sevilla",
    "wof:name":"Moya Lebrato Maria Del Mar",
    "wof:placetype":"venue"
},
  "geometry": {"coordinates":[-5.9878845215,37.3899116516],"type":"Point"}
}