{
  "type": "Feature",
  "properties": {
    "iso:country":"ES",
    "sg:address":"Avda Miguel De Unamuno, 12",
    "sg:city":"Alcala Henares",
    "sg:orig_category":"Quincaller\u00cda (al Por Menor)",
    "sg:phone":"+34 918 80 45 74",
    "sg:postcode":"28806",
    "sg:province":"Madrid",
    "wof:name":"Hermanos Gomez Del Mazo S.a.",
    "wof:placetype":"venue"
},
  "geometry": {"coordinates":[-3.3734400272,40.4965248108],"type":"Point"}
}