{
  "type": "Feature",
  "properties": {
    "addr:full":"Cardexia, S/n Filgueira Pontevedra 36512",
    "addr:housenumber":"/ n",
    "addr:postcode":"36512",
    "addr:street":"Cardexia S",
    "iso:country":"ES",
    "sg:address":"Cardexia, S/n",
    "sg:city":"Filgueira",
    "sg:orig_category":"Agricultores, Agricultores",
    "sg:phone":"+34 986 78 49 46",
    "sg:postcode":"36512",
    "sg:province":"Pontevedra",
    "wof:name":"Sociedad Agraria De Transformacion Vila",
    "wof:placetype":"venue"
},
  "geometry": {"coordinates":[-8.119058609,42.6696968079],"type":"Point"}
}