{
  "type": "Feature",
  "properties": {
    "addr:full":"Avda Tres De Mayo, 30 Santa Cruz De Tenerife Santa Cruz De Tenerife 38005",
    "addr:housenumber":"30",
    "addr:postcode":"38005",
    "addr:street":"Avda Tres De Mayo",
    "iso:country":"ES",
    "sg:address":"Avda Tres De Mayo, 30",
    "sg:city":"Santa Cruz De Tenerife",
    "sg:orig_category":"Organizaciones Profesionales",
    "sg:phone":"+34 922 21 78 00",
    "sg:postcode":"38005",
    "sg:province":"Santa Cruz De Tenerife",
    "sg:website":"www.ahlersconsignataria.com",
    "wof:name":"Ahlers Y Rahn Consignataria S.a.",
    "wof:placetype":"venue"
},
  "geometry": {"coordinates":[-16.2576313019,28.458902359],"type":"Point"}
}