{
  "type": "Feature",
  "properties": {
    "addr:full":"Carrer de Pius Xii, 23 Mutxamel Alicante 03110",
    "addr:housenumber":"23",
    "addr:postcode":"03110",
    "addr:street":"Carrer De Pius Xii",
    "iso:country":"ES",
    "sg:address":"Carrer de Pius Xii, 23",
    "sg:city":"Mutxamel",
    "sg:orig_category":"Asociaciones, Organismos Culturales Y Socioeducativos",
    "sg:phone":"+34 965 95 19 87",
    "sg:postcode":"03110",
    "sg:province":"Alicante",
    "wof:name":"Comision Fiestas De Moros Y Cristianos",
    "wof:placetype":"venue"
},
  "geometry": {"coordinates":[-0.4418820143,38.4157676697],"type":"Point"}
}