{
  "type": "Feature",
  "properties": {
    "addr:full":"Pl Ajuntament (l'), 11 Esparreguera Barcelona 08292",
    "addr:housenumber":"11",
    "addr:postcode":"08292",
    "addr:street":"Pl Ajuntament L '",
    "iso:country":"ES",
    "sg:address":"Pl Ajuntament (l'), 11",
    "sg:city":"Esparreguera",
    "sg:orig_category":"Art\u00cdculos De Regalo (al Por Menor)",
    "sg:phone":"+34 937 77 69 87",
    "sg:postcode":"08292",
    "sg:province":"Barcelona",
    "wof:name":"Monera Puig Sl",
    "wof:placetype":"venue"
},
  "geometry": {"coordinates":[1.8705619574,41.538898468],"type":"Point"}
}