{
  "type": "Feature",
  "properties": {
    "iso:country":"ES",
    "sg:address":"Campillo, 2",
    "sg:city":"Cehegin",
    "sg:orig_category":"Frutos Y Legumbres",
    "sg:phone":"+34 968 74 18 55",
    "sg:postcode":"30430",
    "sg:province":"Murcia",
    "wof:name":"Maquinaria Industrial Cela S.l.",
    "wof:placetype":"venue"
},
  "geometry": {"coordinates":[-1.7547450066,38.1397132874],"type":"Point"}
}