{
  "type": "Feature",
  "properties": {
    "iso:country":"ES",
    "sg:address":"Calle de San Pascual (de), S/n",
    "sg:city":"Aranjuez",
    "sg:orig_category":"Promotores Constructores",
    "sg:phone":"+34 918 92 20 84",
    "sg:postcode":"28300",
    "sg:province":"Madrid",
    "wof:name":"Metroges Construcciones S.l.",
    "wof:placetype":"venue"
},
  "geometry": {"coordinates":[-3.5978589058,40.0309791565],"type":"Point"}
}