{
  "type": "Feature",
  "properties": {
    "iso:country":"ES",
    "sg:address":"Avda Andalucia, 7",
    "sg:city":"Benalup",
    "sg:orig_category":"Molduras, Junquillos, Listones Y Molduras Perforadas",
    "sg:phone":"+34 956 42 43 06",
    "sg:postcode":"11190",
    "sg:province":"C\u00e1diz",
    "wof:name":"Sanchez Tirado Manuel",
    "wof:placetype":"venue"
},
  "geometry": {"coordinates":[-5.8153948784,36.342792511],"type":"Point"}
}