{
  "type": "Feature",
  "properties": {
    "addr:full":"Calle de Calvo Sotelo, 1 Cobisa Toledo 45111",
    "addr:housenumber":"1",
    "addr:postcode":"45111",
    "addr:street":"Calle De Calvo Sotelo",
    "iso:country":"ES",
    "sg:address":"Calle de Calvo Sotelo, 1",
    "sg:city":"Cobisa",
    "sg:orig_category":"Quincaller\u00cda (al Por Menor)",
    "sg:phone":"+34 925 37 86 31",
    "sg:postcode":"45111",
    "sg:province":"Toledo",
    "wof:name":"Trad Dart Sistemas S.l.",
    "wof:placetype":"venue"
},
  "geometry": {"coordinates":[-4.0248188972,39.805606842],"type":"Point"}
}