{
  "type": "Feature",
  "properties": {
    "iso:country":"ES",
    "sg:address":"Carrer de Sant Medir, 16",
    "sg:city":"Barcelona",
    "sg:orig_category":"Juegos Y Juguetes (al Por Menor)",
    "sg:phone":"+34 933 39 51 35",
    "sg:postcode":"08028",
    "sg:province":"Barcelona",
    "wof:name":"Martinez Roca Salvador",
    "wof:placetype":"venue"
},
  "geometry": {"coordinates":[2.1327819824,41.3746452332],"type":"Point"}
}