{
  "type": "Feature",
  "properties": {
    "addr:full":"Calle de Bolivar, 5 Madrid Madrid 28045",
    "addr:housenumber":"5",
    "addr:postcode":"28045",
    "addr:street":"Calle De Bolivar",
    "iso:country":"ES",
    "sg:address":"Calle de Bolivar, 5",
    "sg:city":"Madrid",
    "sg:orig_category":"Contenedores (mercanc\u00cdas)",
    "sg:phone":"+34 914 68 09 96",
    "sg:postcode":"28045",
    "sg:province":"Madrid",
    "wof:name":"Transportes Lorenzo Casado Cordoba S.l.",
    "wof:placetype":"venue"
},
  "geometry": {"coordinates":[-3.6939210892,40.3916435242],"type":"Point"}
}