{
  "type": "Feature",
  "properties": {
    "iso:country":"ES",
    "sg:address":"Pase Eduardo Dato, 2",
    "sg:city":"Madrid",
    "sg:orig_category":"Notarios",
    "sg:phone":"+34 914 47 94 54",
    "sg:postcode":"28010",
    "sg:province":"Madrid",
    "wof:name":"Monedero Gil Francisco Javier",
    "wof:placetype":"venue"
},
  "geometry": {"coordinates":[-3.6960630417,40.4325828552],"type":"Point"}
}