{
  "type": "Feature",
  "properties": {
    "addr:full":"Ptda Masquefa, 35 Alboraya Valencia 46120",
    "addr:housenumber":"35",
    "addr:postcode":"46120",
    "addr:street":"Ptda Masquefa",
    "iso:country":"ES",
    "sg:address":"Ptda Masquefa, 35",
    "sg:city":"Alboraya",
    "sg:orig_category":"Alumbrados",
    "sg:phone":"+34 963 60 69 75",
    "sg:postcode":"46120",
    "sg:province":"Valencia",
    "wof:name":"Pradas Design S.l.",
    "wof:placetype":"venue"
},
  "geometry": {"coordinates":[-0.3405140042,39.4990692139],"type":"Point"}
}