{
  "type": "Feature",
  "properties": {
    "addr:full":"Calle de Pozo Bueno, 1 Cantalapiedra Salamanca 37400",
    "addr:housenumber":"1",
    "addr:postcode":"37400",
    "addr:street":"Calle De Pozo Bueno",
    "iso:country":"ES",
    "sg:address":"Calle de Pozo Bueno, 1",
    "sg:city":"Cantalapiedra",
    "sg:orig_category":"Supermercados Y Hipermercados",
    "sg:phone":"+34 923 53 03 68",
    "sg:postcode":"37400",
    "sg:province":"Salamanca",
    "wof:name":"Zazo Castro Miguel",
    "wof:placetype":"venue"
},
  "geometry": {"coordinates":[-5.183485508,41.1243515015],"type":"Point"}
}