{
  "type": "Feature",
  "properties": {
    "addr:full":"Carrer de Sant Lluis, 27 Pego Alicante 03780",
    "addr:housenumber":"27",
    "addr:postcode":"03780",
    "addr:street":"Carrer De Sant Lluis",
    "iso:country":"ES",
    "sg:address":"Carrer de Sant Lluis, 27",
    "sg:city":"Pego",
    "sg:orig_category":"M\u00c9dicos: An\u00c1lisis Cl\u00cdnicos",
    "sg:phone":"+34 965 57 11 83",
    "sg:postcode":"03780",
    "sg:province":"Alicante",
    "wof:name":"Pastor Perez Purificacion",
    "wof:placetype":"venue"
},
  "geometry": {"coordinates":[-0.1166789979,38.8423118591],"type":"Point"}
}