{
  "type": "Feature",
  "properties": {
    "iso:country":"ES",
    "sg:address":"Carrer de Tolra, 35",
    "sg:city":"Barcelona",
    "sg:orig_category":"Cueros Y Pieles (al Por Mayor)",
    "sg:phone":"+34 933 58 02 01",
    "sg:postcode":"08032",
    "sg:province":"Barcelona",
    "wof:name":"Plantillas Lago S.a.",
    "wof:placetype":"venue"
},
  "geometry": {"coordinates":[2.1568849087,41.4259719849],"type":"Point"}
}