{
  "type": "Feature",
  "properties": {
    "addr:full":"Calle de Hermanos Garnelo, 8 Montilla C\u00f3rdoba 14550",
    "addr:housenumber":"8",
    "addr:postcode":"14550",
    "addr:street":"Calle De Hermanos Garnelo;Co\u0301Rdoba",
    "iso:country":"ES",
    "sg:address":"Calle de Hermanos Garnelo, 8",
    "sg:city":"Montilla",
    "sg:orig_category":"Peluquer\u00cdas, Peluquer\u00cda Mixta",
    "sg:phone":"+34 957 65 47 84",
    "sg:postcode":"14550",
    "sg:province":"C\u00f3rdoba",
    "wof:name":"Millan Doncel Maribel",
    "wof:placetype":"venue"
},
  "geometry": {"coordinates":[-4.6386728287,37.5904464722],"type":"Point"}
}