{
  "type": "Feature",
  "properties": {
    "addr:full":"Calle de Juan Perez Delgado Nijota, 34 Santa Cruz De Tenerife Santa Cruz De Tenerife 38006",
    "addr:housenumber":"34",
    "addr:postcode":"38006",
    "addr:street":"Calle De Juan;Delgado Nijota",
    "iso:country":"ES",
    "sg:address":"Calle de Juan Perez Delgado Nijota, 34",
    "sg:city":"Santa Cruz De Tenerife",
    "sg:orig_category":"Importaci\u00d3n",
    "sg:phone":"+34 922 24 11 21",
    "sg:postcode":"38006",
    "sg:province":"Santa Cruz De Tenerife",
    "wof:name":"Herrera Torres Angel Custodio",
    "wof:placetype":"venue"
},
  "geometry": {"coordinates":[-16.2667636871,28.4719924927],"type":"Point"}
}