{
  "type": "Feature",
  "properties": {
    "iso:country":"ES",
    "sg:address":"P Herradores, 1",
    "sg:city":"Talavan",
    "sg:orig_category":"Administraciones Regionales, Departamentales Y Locales",
    "sg:phone":"+34 927 28 50 02",
    "sg:postcode":"10193",
    "sg:province":"C\u00e1ceres",
    "wof:name":"Ayuntamiento De Talavan",
    "wof:placetype":"venue"
},
  "geometry": {"coordinates":[-6.2814831734,39.7180404663],"type":"Point"}
}