{
  "type": "Feature",
  "properties": {
    "iso:country":"ES",
    "sg:address":"Calle de Redondo Marques, 6",
    "sg:city":"Cabra",
    "sg:orig_category":"Art\u00cdculos De Decoraci\u00d3n",
    "sg:phone":"+34 957 52 00 67",
    "sg:postcode":"14940",
    "sg:province":"C\u00f3rdoba",
    "wof:name":"Chacon Calvo Francisco",
    "wof:placetype":"venue"
},
  "geometry": {"coordinates":[-4.441836834,37.4735565186],"type":"Point"}
}