{
  "type": "Feature",
  "properties": {
    "addr:full":"Pda. Grealo, 5 Lleida Lleida 25191",
    "addr:housenumber":"5",
    "addr:postcode":"25191",
    "iso:country":"ES",
    "sg:address":"Pda. Grealo, 5",
    "sg:city":"Lleida",
    "sg:orig_category":"Producci\u00d3n, Venta De Productos De Agricultura Biol\u00d3gica",
    "sg:phone":"+34 973 23 65 38",
    "sg:postcode":"25191",
    "sg:province":"Lleida",
    "wof:name":"Tersa Domingo Ramon",
    "wof:placetype":"venue"
},
  "geometry": {"coordinates":[0.6831650138,41.5832138062],"type":"Point"}
}