{
  "type": "Feature",
  "properties": {
    "addr:full":"Calle de General Martitegui, 33 Valdemoro Madrid 28340",
    "addr:housenumber":"33",
    "addr:postcode":"28340",
    "addr:street":"Calle De General Martitegui",
    "iso:country":"ES",
    "sg:address":"Calle de General Martitegui, 33",
    "sg:city":"Valdemoro",
    "sg:orig_category":"Alimentaci\u00d3n General (al Por Menor)",
    "sg:phone":"+34 918 95 01 64",
    "sg:postcode":"28340",
    "sg:province":"Madrid",
    "wof:name":"Mazarracin Gonzalez Juan",
    "wof:placetype":"venue"
},
  "geometry": {"coordinates":[-3.6811490059,40.1923370361],"type":"Point"}
}