{
  "type": "Feature",
  "properties": {
    "addr:full":"Plaz Generalisimo, 3 Fuensalida Toledo 45510",
    "addr:housenumber":"3",
    "addr:postcode":"45510",
    "addr:street":"Plaz Generalisimo",
    "iso:country":"ES",
    "sg:address":"Plaz Generalisimo, 3",
    "sg:city":"Fuensalida",
    "sg:orig_category":"Asesor\u00cda Fiscal Y Jur\u00cddica",
    "sg:phone":"+34 925 78 47 71",
    "sg:postcode":"45510",
    "sg:province":"Toledo",
    "wof:name":"Esgilsa",
    "wof:placetype":"venue"
},
  "geometry": {"coordinates":[-4.2086939812,40.0526351929],"type":"Point"}
}