{
  "type": "Feature",
  "properties": {
    "addr:full":"Avgd L'almadrava, 48 Mediterraneo Almadraba Alicante 03570",
    "addr:housenumber":"48",
    "addr:postcode":"03570",
    "addr:street":"L'Almadrava;Almadraba",
    "iso:country":"ES",
    "sg:address":"Avgd L'almadrava, 48",
    "sg:city":"Mediterraneo Almadraba",
    "sg:classifiers":[
        {
            "category":"Tea Room",
            "subcategory":"None",
            "type":"Food & Drink"
        }
    ],
    "sg:phone":"+34 966 85 32 84",
    "sg:postcode":"03570",
    "sg:province":"Alicante",
    "sg:tags":[
        "snack"
    ],
    "wof:name":"Donoso Torres Antonio",
    "wof:placetype":"venue"
},
  "geometry": {"coordinates":[-0.4810059965,38.3452033997],"type":"Point"}
}