{
  "type": "Feature",
  "properties": {
    "addr:full":"Calle de Almanzor, 7 Coria C\u00e1ceres 10800",
    "addr:housenumber":"7",
    "addr:postcode":"10800",
    "addr:street":"Calle De Almanzor;Ca\u0301Ceres",
    "iso:country":"ES",
    "sg:address":"Calle de Almanzor, 7",
    "sg:city":"Coria",
    "sg:orig_category":"Sindicatos De Trabajadores",
    "sg:phone":"+34 927 50 06 42",
    "sg:postcode":"10800",
    "sg:province":"C\u00e1ceres",
    "wof:name":"Union Regional De Cc Oo De Extremadura",
    "wof:placetype":"venue"
},
  "geometry": {"coordinates":[-6.534154892,39.984375],"type":"Point"}
}