{
  "type": "Feature",
  "properties": {
    "iso:country":"ES",
    "sg:address":"Calle de Rufas, 1",
    "sg:city":"Zaragoza",
    "sg:orig_category":"Tintorer\u00cdas, Limpieza En Seco",
    "sg:phone":"+34 976 21 24 21",
    "sg:postcode":"50001",
    "sg:province":"Zaragoza",
    "wof:name":"Urcira S.l.",
    "wof:placetype":"venue"
},
  "geometry": {"coordinates":[-0.877358973,41.6509513855],"type":"Point"}
}