{
  "type": "Feature",
  "properties": {
    "iso:country":"ES",
    "sg:address":"Carrer de Francesc Guma, 6",
    "sg:city":"Sitges",
    "sg:classifiers":[
        {
            "category":"Casinos & Gambling",
            "type":"Entertainment"
        }
    ],
    "sg:phone":"+34 938 94 01 74",
    "sg:postcode":"08870",
    "sg:province":"Barcelona",
    "sg:tags":[
        "locale",
        "de",
        "juego"
    ],
    "sg:website":"www.casino.arrakis.es",
    "wof:name":"Casino Prado Suburense",
    "wof:placetype":"venue"
},
  "geometry": {"coordinates":[1.8106739521,41.2377510071],"type":"Point"}
}