{
  "type": "Feature",
  "properties": {
    "iso:country":"ES",
    "sg:address":"Calle de Dr Layna Serrano, 34",
    "sg:city":"Guadalajara",
    "sg:orig_category":"Producci\u00d3n De Abonos Y De Fertilizantes",
    "sg:phone":"+34 949 21 45 00",
    "sg:postcode":"19002",
    "sg:province":"Guadalajara",
    "wof:name":"Cipriano Sanchez E Hijos S.a.",
    "wof:placetype":"venue"
},
  "geometry": {"coordinates":[-3.1660504341,40.6253662109],"type":"Point"}
}