{
  "type": "Feature",
  "properties": {
    "addr:full":"Cra. Pobla (pol Ind Pla Rigat), Km. 0002,0 Vilanova Cami Barcelona 08788",
    "addr:postcode":"08788",
    "addr:street":"Ind Pla Rigat Km. 0002,0;Cami Barcelona",
    "iso:country":"ES",
    "sg:address":"Cra. Pobla (pol Ind Pla Rigat), Km. 0002,0",
    "sg:city":"Vilanova Cami",
    "sg:orig_category":"Cer\u00c1micas: Material Y Suministros",
    "sg:phone":"+34 938 06 06 06",
    "sg:postcode":"08788",
    "sg:province":"Barcelona",
    "wof:name":"Talleres Felipe Verdes S.a.",
    "wof:placetype":"venue"
},
  "geometry": {"coordinates":[1.6405899525,41.5763664246],"type":"Point"}
}