{
  "type": "Feature",
  "properties": {
    "addr:full":"Avda Hernan Cortes, 6 Caceres C\u00e1ceres 10004",
    "addr:housenumber":"6",
    "addr:postcode":"10004",
    "addr:street":"Avda Hernan Cortes;Ca\u0301Ceres",
    "iso:country":"ES",
    "sg:address":"Avda Hernan Cortes, 6",
    "sg:city":"Caceres",
    "sg:orig_category":"Ingenier\u00cda, Centros De Estudios (diversos)",
    "sg:phone":"+34 927 62 71 95",
    "sg:postcode":"10004",
    "sg:province":"C\u00e1ceres",
    "wof:name":"Rozas Lopez Jose Luis",
    "wof:placetype":"venue"
},
  "geometry": {"coordinates":[-6.3790240288,39.4730758667],"type":"Point"}
}