{
  "type": "Feature",
  "properties": {
    "addr:full":"Calle de Ramon Y Cajal, 45 Alberic Valencia 46260",
    "addr:housenumber":"45",
    "addr:postcode":"46260",
    "addr:street":"Calle De Ramon Y Cajal",
    "iso:country":"ES",
    "sg:address":"Calle de Ramon Y Cajal, 45",
    "sg:city":"Alberic",
    "sg:orig_category":"Molduras, Junquillos, Listones Y Molduras Perforadas",
    "sg:phone":"+34 962 44 15 51",
    "sg:postcode":"46260",
    "sg:province":"Valencia",
    "wof:name":"Pla Rocher Rosario",
    "wof:placetype":"venue"
},
  "geometry": {"coordinates":[-0.5201119781,39.1194229126],"type":"Point"}
}