{
  "type": "Feature",
  "properties": {
    "addr:full":"La Vega, S/n Ceceda Asturias 33582",
    "addr:housenumber":"s",
    "addr:postcode":"33582",
    "addr:street":"La Vega;/ N Ceceda Asturias",
    "iso:country":"ES",
    "sg:address":"La Vega, S/n",
    "sg:city":"Ceceda",
    "sg:orig_category":"Producci\u00d3n De Abonos Y De Fertilizantes",
    "sg:phone":"+34 985 70 40 17",
    "sg:postcode":"33582",
    "sg:province":"Asturias",
    "wof:name":"Blanco Redondo Dolores",
    "wof:placetype":"venue"
},
  "geometry": {"coordinates":[-5.4368581772,43.3726882935],"type":"Point"}
}