{
  "type": "Feature",
  "properties": {
    "addr:full":"Av Ignasi Wallis, 21 Eivissa Islas Baleares 07800",
    "addr:housenumber":"21",
    "addr:postcode":"07800",
    "addr:street":"Av Ignasi Wallis",
    "iso:country":"ES",
    "sg:address":"Av Ignasi Wallis, 21",
    "sg:city":"Eivissa",
    "sg:orig_category":"Ingenier\u00cda, Centros De Estudios (diversos)",
    "sg:phone":"+34 971 30 10 13",
    "sg:postcode":"07800",
    "sg:province":"Islas Baleares",
    "wof:name":"Indastec Asociados S.l.",
    "wof:placetype":"venue"
},
  "geometry": {"coordinates":[1.430793047,38.9111213684],"type":"Point"}
}