{
  "type": "Feature",
  "properties": {
    "iso:country":"ES",
    "sg:address":"Pedraucha, 24",
    "sg:city":"Piedraucha",
    "sg:orig_category":"Mec\u00c1nico Del Autom\u00d3vil",
    "sg:phone":"+34 986 33 87 92",
    "sg:postcode":"36416",
    "sg:province":"Pontevedra",
    "wof:name":"Doauto S.c.",
    "wof:placetype":"venue"
},
  "geometry": {"coordinates":[-8.6403799057,42.1906967163],"type":"Point"}
}