{
  "type": "Feature",
  "properties": {
    "iso:country":"ES",
    "sg:address":"Avda San Antonio, 61",
    "sg:city":"Cuarte Huerva",
    "sg:orig_category":"Muebles Y Accesorios Para Cocinas Y Cuartos De Ba\u00d1o (al Por Menor)",
    "sg:phone":"+34 976 50 42 21",
    "sg:postcode":"50410",
    "sg:province":"Zaragoza",
    "sg:website":"www.mggiro.com",
    "wof:name":"Mg Giro Mobiliario De Cocina S.l.",
    "wof:placetype":"venue"
},
  "geometry": {"coordinates":[-0.9291920066,41.5930137634],"type":"Point"}
}