{
  "type": "Feature",
  "properties": {
    "addr:full":"Carrer de Calaf, 46 Terrassa Barcelona 08227",
    "addr:housenumber":"46",
    "addr:postcode":"08227",
    "addr:street":"Carrer De Calaf",
    "iso:country":"ES",
    "sg:address":"Carrer de Calaf, 46",
    "sg:city":"Terrassa",
    "sg:orig_category":"Asociaciones, Organismos Culturales Y Socioeducativos",
    "sg:phone":"+34 937 31 78 66",
    "sg:postcode":"08227",
    "sg:province":"Barcelona",
    "wof:name":"Centro Juvenil Las Arenas",
    "wof:placetype":"venue"
},
  "geometry": {"coordinates":[2.0347659588,41.5715713501],"type":"Point"}
}