{
  "type": "Feature",
  "properties": {
    "addr:full":"Plaz Espa\u00d1a, 10 Valladolid Valladolid 47001",
    "addr:housenumber":"10",
    "addr:postcode":"47001",
    "addr:street":"Plaz Espan\u0303A",
    "iso:country":"ES",
    "sg:address":"Plaz Espa\u00d1a, 10",
    "sg:city":"Valladolid",
    "sg:orig_category":"Peluquer\u00cdas",
    "sg:phone":"+34 983 20 30 97",
    "sg:postcode":"47001",
    "sg:province":"Valladolid",
    "wof:name":"Jimenez Lozano Javier",
    "wof:placetype":"venue"
},
  "geometry": {"coordinates":[-4.7243361473,41.648891449],"type":"Point"}
}