{
  "type": "Feature",
  "properties": {
    "addr:full":"Calle de Ramon Y Cajal, 18 Coru\u00d1a La Coru\u00f1a 15006",
    "addr:housenumber":"18",
    "addr:postcode":"15006",
    "addr:street":"Calle De Ramon Y Cajal;La Corun\u0303A",
    "iso:country":"ES",
    "sg:address":"Calle de Ramon Y Cajal, 18",
    "sg:city":"Coru\u00d1a",
    "sg:orig_category":"Peluqueros: De Se\u00d1oras",
    "sg:phone":"+34 981 28 00 56",
    "sg:postcode":"15006",
    "sg:province":"La Coru\u00f1a",
    "wof:name":"Margarita Alvarez S.l.",
    "wof:placetype":"venue"
},
  "geometry": {"coordinates":[-8.4015550613,43.3565216064],"type":"Point"}
}