{
  "type": "Feature",
  "properties": {
    "addr:full":"Ctra De Coria (pi El Batan), Km. 0285,3 El Batan C\u00e1ceres 10692",
    "addr:postcode":"10692",
    "addr:street":"Ctra De Coria;El Batan Km. 0285,3 El;Ca\u0301Ceres",
    "iso:country":"ES",
    "sg:address":"Ctra De Coria (pi El Batan), Km. 0285,3",
    "sg:city":"El Batan",
    "sg:orig_category":"Armaduras De Hormig\u00d3n",
    "sg:phone":"+34 927 67 28 43",
    "sg:postcode":"10692",
    "sg:province":"C\u00e1ceres",
    "sg:website":"www.extremadura2000.com",
    "wof:name":"Extremadura 2000 De Estructuras S.a.",
    "wof:placetype":"venue"
},
  "geometry": {"coordinates":[-6.3801989555,39.97448349],"type":"Point"}
}