{
  "type": "Feature",
  "properties": {
    "addr:full":"Avda Luz, 26 Malaga M\u00e1laga 29004",
    "addr:housenumber":"26",
    "addr:postcode":"29004",
    "addr:street":"Avda Luz;Ma\u0301Laga",
    "iso:country":"ES",
    "sg:address":"Avda Luz, 26",
    "sg:city":"Malaga",
    "sg:orig_category":"Fabricaci\u00d3n, Importaci\u00d3n, Venta De Material De Telefon\u00cda, Peritelefon\u00cda",
    "sg:phone":"+34 952 24 66 60",
    "sg:postcode":"29004",
    "sg:province":"M\u00e1laga",
    "wof:name":"Alea Malaga S.l.",
    "wof:placetype":"venue"
},
  "geometry": {"coordinates":[-4.4538693428,36.6971282959],"type":"Point"}
}