{
  "type": "Feature",
  "properties": {
    "addr:full":"Carr Major, 14 Bescano Girona 17162",
    "addr:housenumber":"14",
    "addr:postcode":"17162",
    "addr:street":"Carr Major",
    "iso:country":"ES",
    "sg:address":"Carr Major, 14",
    "sg:city":"Bescano",
    "sg:orig_category":"Peluquer\u00cdas, Peluquer\u00cda Mixta",
    "sg:phone":"+34 972 44 03 57",
    "sg:postcode":"17162",
    "sg:province":"Girona",
    "wof:name":"Carreras Puig Cristina",
    "wof:placetype":"venue"
},
  "geometry": {"coordinates":[2.7401640415,41.9662437439],"type":"Point"}
}