{
  "type": "Feature",
  "properties": {
    "addr:full":"Calle de Carmen, 14 Ciudad Real Ciudad Real 13003",
    "addr:housenumber":"14",
    "addr:postcode":"13003",
    "addr:street":"Calle De Carmen",
    "iso:country":"ES",
    "sg:address":"Calle de Carmen, 14",
    "sg:city":"Ciudad Real",
    "sg:orig_category":"Asesor\u00cda Sobre Comunicaci\u00d3n De Empresas",
    "sg:phone":"+34 926 23 22 10",
    "sg:postcode":"13003",
    "sg:province":"Ciudad Real",
    "wof:name":"Asociacion De Jovenes Empresarios De Ciudad Real",
    "wof:placetype":"venue"
},
  "geometry": {"coordinates":[-3.9320349693,38.9898262024],"type":"Point"}
}