{
  "type": "Feature",
  "properties": {
    "addr:full":"Calle de Gabilondo, 24 Valladolid Valladolid 47007",
    "addr:housenumber":"24",
    "addr:postcode":"47007",
    "addr:street":"Calle De Gabilondo",
    "iso:country":"ES",
    "sg:address":"Calle de Gabilondo, 24",
    "sg:city":"Valladolid",
    "sg:orig_category":"Delegados, Agentes De Tr\u00c1nsito, Auxiliares De Transporte Internacional",
    "sg:phone":"+34 983 23 71 48",
    "sg:postcode":"47007",
    "sg:province":"Valladolid",
    "wof:name":"Puerto Luis Agustin",
    "wof:placetype":"venue"
},
  "geometry": {"coordinates":[-4.7344298363,41.6398048401],"type":"Point"}
}