{
  "type": "Feature",
  "properties": {
    "addr:full":"Urb. Manantiales, 24 Torremolinos M\u00e1laga 29620",
    "addr:housenumber":"24",
    "addr:postcode":"29620",
    "addr:street":"Manantiales;Ma\u0301Laga",
    "iso:country":"ES",
    "sg:address":"Urb. Manantiales, 24",
    "sg:city":"Torremolinos",
    "sg:orig_category":"Servicios De Telecomunicaciones",
    "sg:phone":"+34 952 37 74 39",
    "sg:postcode":"29620",
    "sg:province":"M\u00e1laga",
    "wof:name":"Momin Internacional S.l.",
    "wof:placetype":"venue"
},
  "geometry": {"coordinates":[-4.5025048256,36.6271057129],"type":"Point"}
}