{
  "type": "Feature",
  "properties": {
    "addr:full":"Avda Mediterraneo (del), S/n Almeria Almer\u00eda 04007",
    "addr:housenumber":"/ n",
    "addr:postcode":"04007",
    "addr:street":"Avda Mediterraneo Del S",
    "iso:country":"ES",
    "sg:address":"Avda Mediterraneo (del), S/n",
    "sg:city":"Almeria",
    "sg:orig_category":"\u00d3ptica: Instrumentos (fabricaci\u00d3n)",
    "sg:phone":"+34 950 14 43 85",
    "sg:postcode":"04007",
    "sg:province":"Almer\u00eda",
    "sg:website":"www.optica2000.com",
    "wof:name":"Optica 2000 S. L.",
    "wof:placetype":"venue"
},
  "geometry": {"coordinates":[-2.4460990429,36.8307914734],"type":"Point"}
}