{
  "type": "Feature",
  "properties": {
    "iso:country":"ES",
    "sg:address":"Av Sta Oliva, S/n",
    "sg:city":"Sta. Oliva",
    "sg:orig_category":"Obras Y Organismos Sociales",
    "sg:phone":"+34 977 66 71 11",
    "sg:postcode":"43710",
    "sg:province":"Tarragona",
    "wof:name":"Fundacio Privada Santa Teresa",
    "wof:placetype":"venue"
},
  "geometry": {"coordinates":[1.5532282591,41.2579460144],"type":"Point"}
}