{
  "type": "Feature",
  "properties": {
    "addr:full":"Calle de Vital Aza, 41 Madrid Madrid 28017",
    "addr:housenumber":"41",
    "addr:postcode":"madrid;28017",
    "addr:street":"Calle De Vital Aza",
    "iso:country":"ES",
    "sg:address":"Calle de Vital Aza, 41",
    "sg:city":"Madrid",
    "sg:orig_category":"Peluquer\u00cdas, Peluquer\u00cda Mixta",
    "sg:phone":"+34 913 67 87 97",
    "sg:postcode":"28017",
    "sg:province":"Madrid",
    "wof:name":"Lopez Olmo Encarnacion",
    "wof:placetype":"venue"
},
  "geometry": {"coordinates":[-3.6420469284,40.4321022034],"type":"Point"}
}