{
  "type": "Feature",
  "properties": {
    "iso:country":"ES",
    "sg:address":"Calle de Santander, 8",
    "sg:city":"Castro Urdiales",
    "sg:orig_category":"Panader\u00cdas, Panader\u00cdas",
    "sg:phone":"+34 942 86 06 41",
    "sg:postcode":"39700",
    "sg:province":"Cantabria",
    "wof:name":"Santos Iturrioz Desiderio",
    "wof:placetype":"venue"
},
  "geometry": {"coordinates":[-3.2193350792,43.3832435608],"type":"Point"}
}