{
  "type": "Feature",
  "properties": {
    "iso:country":"ES",
    "sg:address":"Av Meridiana, 192",
    "sg:city":"Barcelona",
    "sg:orig_category":"Electricidad: Instaladores",
    "sg:phone":"+34 933 40 40 53",
    "sg:postcode":"08026",
    "sg:province":"Barcelona",
    "wof:name":"Electricidad Maba S.l.",
    "wof:placetype":"venue"
},
  "geometry": {"coordinates":[2.1870179176,41.4134216309],"type":"Point"}
}