{
  "type": "Feature",
  "properties": {
    "iso:country":"ES",
    "sg:address":"Calle de Vista Alegre, 12",
    "sg:city":"Cuarte Huerva",
    "sg:orig_category":"Fabricaci\u00d3n, Venta De Cuadros, Accesorios Para Enmarcar",
    "sg:phone":"+34 976 50 32 52",
    "sg:postcode":"50410",
    "sg:province":"Zaragoza",
    "sg:website":"www.moldiber.com",
    "wof:name":"Moldiber Aragon S.l.",
    "wof:placetype":"venue"
},
  "geometry": {"coordinates":[-0.9341189861,41.594871521],"type":"Point"}
}