{
  "type": "Feature",
  "properties": {
    "addr:full":"Calle de Cid, 15 Alaquas Valencia 46970",
    "addr:housenumber":"15",
    "addr:postcode":"46970",
    "addr:street":"Calle De Cid",
    "iso:country":"ES",
    "sg:address":"Calle de Cid, 15",
    "sg:city":"Alaquas",
    "sg:orig_category":"Animales (al Por Menor)",
    "sg:phone":"+34 961 50 11 98",
    "sg:postcode":"46970",
    "sg:province":"Valencia",
    "wof:name":"Lopez Ca\u00f1ada Arturo",
    "wof:placetype":"venue"
},
  "geometry": {"coordinates":[-0.4663890898,39.4554862976],"type":"Point"}
}