{
  "type": "Feature",
  "properties": {
    "iso:country":"ES",
    "sg:address":"Avda Andalucia, 84",
    "sg:city":"Cullar-vega",
    "sg:orig_category":"Loter\u00cda Y T\u00d3mbola",
    "sg:phone":"+34 958 58 12 09",
    "sg:postcode":"18195",
    "sg:province":"Granada",
    "wof:name":"Donaire Navarro Sacramento",
    "wof:placetype":"venue"
},
  "geometry": {"coordinates":[-3.67314291,37.157081604],"type":"Point"}
}