{
  "type": "Feature",
  "properties": {
    "addr:full":"Calle de San Juan Bosco, 6 Marbella M\u00e1laga 29600",
    "addr:housenumber":"6",
    "addr:postcode":"29600",
    "addr:street":"Calle De San Juan Bosco;Ma\u0301Laga",
    "iso:country":"ES",
    "sg:address":"Calle de San Juan Bosco, 6",
    "sg:city":"Marbella",
    "sg:orig_category":"Art\u00cdculos De Decoraci\u00d3n",
    "sg:phone":"+34 952 86 16 48",
    "sg:postcode":"29600",
    "sg:province":"M\u00e1laga",
    "wof:name":"Gavi\u00f1o Escudier Rosa",
    "wof:placetype":"venue"
},
  "geometry": {"coordinates":[-4.8877921104,36.509059906],"type":"Point"}
}