{
  "type": "Feature",
  "properties": {
    "addr:full":"Calle de Tenerias, 18 Huesca Huesca 22001",
    "addr:housenumber":"18",
    "addr:postcode":"22001",
    "addr:street":"Calle De Tenerias",
    "iso:country":"ES",
    "sg:address":"Calle de Tenerias, 18",
    "sg:city":"Huesca",
    "sg:classifiers":[
        {
            "category":"Tea Room",
            "subcategory":"None",
            "type":"Food & Drink"
        }
    ],
    "sg:phone":"+34 974 22 91 20",
    "sg:postcode":"22001",
    "sg:province":"Huesca",
    "sg:tags":[
        "snack"
    ],
    "wof:name":"Criado Pardina Jesus",
    "wof:placetype":"venue"
},
  "geometry": {"coordinates":[-0.4021019936,42.1402816772],"type":"Point"}
}