{
  "type": "Feature",
  "properties": {
    "iso:country":"ES",
    "sg:address":"Carrer de Torrent De Can Mariner, 5",
    "sg:city":"Barcelona",
    "sg:orig_category":"Empresarios",
    "sg:phone":"+34 934 20 09 43",
    "sg:postcode":"08031",
    "sg:province":"Barcelona",
    "wof:name":"Reforjuto S.l.",
    "wof:placetype":"venue"
},
  "geometry": {"coordinates":[2.1629340649,41.4309082031],"type":"Point"}
}