{
  "type": "Feature",
  "properties": {
    "iso:country":"ES",
    "sg:address":"Calle de Rambla, 48",
    "sg:city":"Yecla",
    "sg:orig_category":"Platos Preparados Refrigerados (fabricaci\u00d3n, Al Por Mayor)",
    "sg:phone":"+34 968 79 58 58",
    "sg:postcode":"30510",
    "sg:province":"Murcia",
    "wof:name":"Arres Diaz Angeles",
    "wof:placetype":"venue"
},
  "geometry": {"coordinates":[-1.1091896296,38.6151390076],"type":"Point"}
}