{
  "type": "Feature",
  "properties": {
    "iso:country":"ES",
    "sg:address":"Avda Valentin Masip, 26",
    "sg:city":"Oviedo",
    "sg:orig_category":"Ense\u00d1anza: Peluquer\u00cda Est\u00c9tica",
    "sg:phone":"+34 985 27 02 81",
    "sg:postcode":"33013",
    "sg:province":"Asturias",
    "wof:name":"Comercial Grafer S.a.",
    "wof:placetype":"venue"
},
  "geometry": {"coordinates":[-5.8621168137,43.362285614],"type":"Point"}
}