{
  "type": "Feature",
  "properties": {
    "addr:full":"Calle de Puerto, 4 Malaga M\u00e1laga 29016",
    "addr:housenumber":"4",
    "addr:postcode":"29016",
    "addr:street":"Calle De Puerto;Ma\u0301Laga",
    "iso:country":"ES",
    "sg:address":"Calle de Puerto, 4",
    "sg:city":"Malaga",
    "sg:orig_category":"Promotores Constructores",
    "sg:phone":"+34 952 22 71 28",
    "sg:postcode":"29016",
    "sg:province":"M\u00e1laga",
    "wof:name":"Construcciones Esgar S.a.",
    "wof:placetype":"venue"
},
  "geometry": {"coordinates":[-4.409318924,36.7201004028],"type":"Point"}
}