{
  "type": "Feature",
  "properties": {
    "addr:full":"Calle de Llano Ponte, 48 Aviles Asturias 33402",
    "addr:housenumber":"48",
    "addr:postcode":"33402",
    "addr:street":"Calle De Llano Ponte",
    "iso:country":"ES",
    "sg:address":"Calle de Llano Ponte, 48",
    "sg:city":"Aviles",
    "sg:orig_category":"Farmacias",
    "sg:phone":"+34 985 54 39 59",
    "sg:postcode":"33402",
    "sg:province":"Asturias",
    "wof:name":"Simal Garcia Maria Jose",
    "wof:placetype":"venue"
},
  "geometry": {"coordinates":[-5.9177961349,43.5523071289],"type":"Point"}
}