{
  "type": "Feature",
  "properties": {
    "iso:country":"ES",
    "sg:address":"Calle de Bailen, 35",
    "sg:city":"San Vicente Del Raspeig-sant Vicent Del Raspeig",
    "sg:orig_category":"Estilistas Y Estudios De Estilo De Corte Y Confecci\u00d3n",
    "sg:phone":"+34 965 67 61 63",
    "sg:postcode":"03690",
    "sg:province":"Alicante",
    "wof:name":"Gloyder S.l.",
    "wof:placetype":"venue"
},
  "geometry": {"coordinates":[-0.5250936151,38.3933296204],"type":"Point"}
}