{
  "type": "Feature",
  "properties": {
    "addr:full":"Plaz Trinidad (de La), 1 Granada Granada 18001",
    "addr:housenumber":"1",
    "addr:postcode":"18001",
    "addr:street":"Plaz",
    "iso:country":"ES",
    "sg:address":"Plaz Trinidad (de La), 1",
    "sg:city":"Granada",
    "sg:orig_category":"Ropa Para Se\u00d1oras (al Por Menor)",
    "sg:phone":"+34 958 26 77 60",
    "sg:postcode":"18001",
    "sg:province":"Granada",
    "wof:name":"Leiva Sanchez Maria Angeles",
    "wof:placetype":"venue"
},
  "geometry": {"coordinates":[-3.6016569138,37.177230835],"type":"Point"}
}