{
  "type": "Feature",
  "properties": {
    "addr:full":"Ctra Granada, 48 Almeria Almer\u00eda 04009",
    "addr:housenumber":"48",
    "addr:postcode":"04009",
    "addr:street":"Ctra Granada",
    "iso:country":"ES",
    "sg:address":"Ctra Granada, 48",
    "sg:city":"Almeria",
    "sg:orig_category":"Mec\u00c1nico Del Autom\u00d3vil",
    "sg:phone":"+34 950 14 22 64",
    "sg:postcode":"04009",
    "sg:province":"Almer\u00eda",
    "wof:name":"Electromecanica Benahadus S.l.",
    "wof:placetype":"venue"
},
  "geometry": {"coordinates":[-2.4491360188,36.8555831909],"type":"Point"}
}