{
  "type": "Feature",
  "properties": {
    "iso:country":"ES",
    "sg:address":"Calle de Doctor Gomez Ferrer, 32",
    "sg:city":"Bu\u00f1ol",
    "sg:orig_category":"Promotores Constructores",
    "sg:phone":"+34 962 50 06 37",
    "sg:postcode":"46360",
    "sg:province":"Valencia",
    "wof:name":"Construcciones Matamales S.l.",
    "wof:placetype":"venue"
},
  "geometry": {"coordinates":[-0.7907729745,39.4213218689],"type":"Point"}
}