{
  "type": "Feature",
  "properties": {
    "iso:country":"ES",
    "sg:address":"Calle de Muro De Francisco De La Mata, 7",
    "sg:city":"Logro\u00f1o",
    "sg:orig_category":"Zapatos (al Por Menor)",
    "sg:phone":"+34 941 25 36 11",
    "sg:postcode":"26001",
    "sg:province":"La Rioja",
    "wof:name":"Tronchero S.l.",
    "wof:placetype":"venue"
},
  "geometry": {"coordinates":[-2.4452319145,42.4654426575],"type":"Point"}
}