{
  "type": "Feature",
  "properties": {
    "addr:full":"Av Diagonal, 463 Barcelona Barcelona 08036",
    "addr:housenumber":"463",
    "addr:postcode":"08036",
    "addr:street":"Av Diagonal",
    "iso:country":"ES",
    "sg:address":"Av Diagonal, 463",
    "sg:city":"Barcelona",
    "sg:orig_category":"Fabricaci\u00d3n, Importaci\u00d3n, Venta De Material De Telefon\u00cda, Peritelefon\u00cda",
    "sg:phone":"+34 933 21 35 18",
    "sg:postcode":"08036",
    "sg:province":"Barcelona",
    "wof:name":"Xtra Telecom S.a.",
    "wof:placetype":"venue"
},
  "geometry": {"coordinates":[2.1471672058,41.3932228088],"type":"Point"}
}