{
  "type": "Feature",
  "properties": {
    "iso:country":"ES",
    "sg:address":"Ctra D Rodrigo, Km. 0005,0",
    "sg:city":"Palacios Y Villafranca",
    "sg:orig_category":"Producci\u00d3n De Abonos Y De Fertilizantes",
    "sg:phone":"+34 955 89 83 68",
    "sg:postcode":"41720",
    "sg:province":"Sevilla",
    "wof:name":"Abonos Organicos Sevilla S. A.",
    "wof:placetype":"venue"
},
  "geometry": {"coordinates":[-5.934167,37.160633],"type":"Point"}
}