{
  "type": "Feature",
  "properties": {
    "iso:country":"ES",
    "sg:address":"Calle de Tenerife, 5",
    "sg:city":"Utebo",
    "sg:orig_category":"T\u00c9cnicos Veterinarios",
    "sg:phone":"+34 976 78 75 74",
    "sg:postcode":"50180",
    "sg:province":"Zaragoza",
    "wof:name":"Garcia Martinez Isabel",
    "wof:placetype":"venue"
},
  "geometry": {"coordinates":[-0.999382019,41.7026519775],"type":"Point"}
}