{
  "type": "Feature",
  "properties": {
    "iso:country":"ES",
    "sg:address":"Calle de Resina, 13",
    "sg:city":"Madrid",
    "sg:orig_category":"Aparatos, Sistemas De Tele",
    "sg:phone":"+34 917 10 98 35",
    "sg:postcode":"28021",
    "sg:province":"Madrid",
    "wof:name":"Porintel S.l.",
    "wof:placetype":"venue"
},
  "geometry": {"coordinates":[-3.6976959705,40.3359069824],"type":"Point"}
}