{
  "type": "Feature",
  "properties": {
    "addr:full":"Calle de Ramon Gomez De La Serna, 22 Marbella M\u00e1laga 29600",
    "addr:housenumber":"22",
    "addr:postcode":"29600",
    "addr:street":"Calle De Ramon Gomez De La Serna;Ma\u0301Laga",
    "iso:country":"ES",
    "sg:address":"Calle de Ramon Gomez De La Serna, 22",
    "sg:city":"Marbella",
    "sg:orig_category":"M\u00c9dicos: Evaluaci\u00d3n Y Tratamiento Del Dolor",
    "sg:phone":"+34 952 77 66 90",
    "sg:postcode":"29600",
    "sg:province":"M\u00e1laga",
    "wof:name":"Arco Ideal S.l",
    "wof:placetype":"venue"
},
  "geometry": {"coordinates":[-4.9011936188,36.5095481873],"type":"Point"}
}