{
  "type": "Feature",
  "properties": {
    "addr:full":"Calle de Mostoles, 44 San Juan Murcia 30740",
    "addr:housenumber":"44",
    "addr:postcode":"30740",
    "addr:street":"Calle De Mostoles",
    "iso:country":"ES",
    "sg:address":"Calle de Mostoles, 44",
    "sg:city":"San Juan",
    "sg:orig_category":"Inmobiliaria (agencias)",
    "sg:phone":"+34 968 18 31 99",
    "sg:postcode":"30740",
    "sg:province":"Murcia",
    "wof:name":"Barrero Cabezas Miguel",
    "wof:placetype":"venue"
},
  "geometry": {"coordinates":[-0.7932540178,37.8340911865],"type":"Point"}
}