{
  "type": "Feature",
  "properties": {
    "addr:full":"Calle de Casa Grande, S/n Campillo Altobuey Cuenca 16210",
    "addr:housenumber":"s / n",
    "addr:postcode":"16210",
    "addr:street":"Calle De Casa",
    "iso:country":"ES",
    "sg:address":"Calle de Casa Grande, S/n",
    "sg:city":"Campillo Altobuey",
    "sg:orig_category":"Electricidad: Instaladores",
    "sg:phone":"+34 969 33 81 08",
    "sg:postcode":"16210",
    "sg:province":"Cuenca",
    "sg:website":"www.electrosur.com",
    "wof:name":"Electrosur Xxi S.l.",
    "wof:placetype":"venue"
},
  "geometry": {"coordinates":[-1.7938790321,39.6105651855],"type":"Point"}
}