{
  "type": "Feature",
  "properties": {
    "iso:country":"ES",
    "sg:address":"Ctra. Segura, S/n",
    "sg:city":"Casas Monte",
    "sg:orig_category":"Electrodom\u00c9sticos (al Por Menor)",
    "sg:phone":"+34 927 17 91 04",
    "sg:postcode":"10730",
    "sg:province":"C\u00e1ceres",
    "wof:name":"Muebles Y Electrodomesticos Martil S.l.",
    "wof:placetype":"venue"
},
  "geometry": {"coordinates":[-5.9633669853,40.2041282654],"type":"Point"}
}