{
  "type": "Feature",
  "properties": {
    "iso:country":"ES",
    "sg:address":"Calle de Campillo, 14",
    "sg:city":"Madrid",
    "sg:orig_category":"Confecci\u00d3n De Trajes Para Se\u00d1oras",
    "sg:phone":"+34 914 64 80 10",
    "sg:postcode":"28011",
    "sg:province":"Madrid",
    "wof:name":"Oreja Manteca Eleuterio",
    "wof:placetype":"venue"
},
  "geometry": {"coordinates":[-3.7322638035,40.4071502686],"type":"Point"}
}