{
  "type": "Feature",
  "properties": {
    "iso:country":"ES",
    "sg:address":"Calle de Rio Tormes, 2",
    "sg:city":"Alcala Henares",
    "sg:orig_category":"Disfraces",
    "sg:phone":"+34 918 82 27 65",
    "sg:postcode":"28804",
    "sg:province":"Madrid",
    "wof:name":"Sanchez-ferrer Gonzalez Maria Del Mar",
    "wof:placetype":"venue"
},
  "geometry": {"coordinates":[-3.365060091,40.4781074524],"type":"Point"}
}