{
  "type": "Feature",
  "properties": {
    "addr:full":"Vilarnovo, S/n Arteixo La Coru\u00f1a 15144",
    "addr:postcode":"15144",
    "addr:street":"Vilarnovo S / N;La Corun\u0303A",
    "iso:country":"ES",
    "sg:address":"Vilarnovo, S/n",
    "sg:city":"Arteixo",
    "sg:orig_category":"Reciclaje, Desguace De Veh\u00cdculos",
    "sg:phone":"+34 981 60 08 35",
    "sg:postcode":"15144",
    "sg:province":"La Coru\u00f1a",
    "wof:name":"Esmoris Veiga Daniel",
    "wof:placetype":"venue"
},
  "geometry": {"coordinates":[-8.5324258804,43.2849884033],"type":"Point"}
}