{
  "type": "Feature",
  "properties": {
    "addr:full":"Calle de Menendez Y Pelayo, 27 Palmas De Gran Canaria Las Palmas 35006",
    "addr:postcode":"35006",
    "addr:street":"Calle De Menendez Y Pelayo",
    "iso:country":"ES",
    "sg:address":"Calle de Menendez Y Pelayo, 27",
    "sg:city":"Palmas De Gran Canaria",
    "sg:orig_category":"Psic\u00d3logos",
    "sg:phone":"+34 928 23 37 07",
    "sg:postcode":"35006",
    "sg:province":"Las Palmas",
    "wof:name":"Romero Rosas Maria Rosa",
    "wof:placetype":"venue"
},
  "geometry": {"coordinates":[-15.4326629639,28.1320304871],"type":"Point"}
}