{
  "type": "Feature",
  "properties": {
    "iso:country":"ES",
    "sg:address":"Calle de Ramon Y Cajal, 25",
    "sg:city":"Huetor-tajar",
    "sg:orig_category":"Farmacias",
    "sg:phone":"+34 958 33 22 68",
    "sg:postcode":"18360",
    "sg:province":"Granada",
    "wof:name":"Delgado Perez Maria Josefa",
    "wof:placetype":"venue"
},
  "geometry": {"coordinates":[-4.0444350243,37.1970748901],"type":"Point"}
}