{
  "type": "Feature",
  "properties": {
    "addr:full":"Avda Espa\u00d1a, 6 Caceres C\u00e1ceres 10001",
    "addr:housenumber":"6",
    "addr:postcode":"10001",
    "addr:street":"Avda Espan\u0303A;Ca\u0301Ceres",
    "iso:country":"ES",
    "sg:address":"Avda Espa\u00d1a, 6",
    "sg:city":"Caceres",
    "sg:orig_category":"M\u00c9dicos: Gastroenterolog\u00cda Y Hepatolog\u00cda (aparato Digestivo)",
    "sg:phone":"+34 927 22 48 16",
    "sg:postcode":"10001",
    "sg:province":"C\u00e1ceres",
    "wof:name":"Petron Herrera Vicente",
    "wof:placetype":"venue"
},
  "geometry": {"coordinates":[-6.3777279854,39.4714622498],"type":"Point"}
}