{
  "type": "Feature",
  "properties": {
    "iso:country":"ES",
    "sg:address":"Calle de Lisboa, 6",
    "sg:city":"Valdemoro",
    "sg:orig_category":"Fabricaci\u00d3n De Distribuidores Autom\u00c1ticos",
    "sg:phone":"+34 918 95 51 27",
    "sg:postcode":"28340",
    "sg:province":"Madrid",
    "wof:name":"J & M Vending 97 S.l.",
    "wof:placetype":"venue"
},
  "geometry": {"coordinates":[-3.6844639778,40.2088356018],"type":"Point"}
}