{
  "type": "Feature",
  "properties": {
    "iso:country":"ES",
    "sg:address":"Avda Ntra. Se\u00d1ora Del Carmen, 34",
    "sg:city":"Corralejo Playa",
    "sg:orig_category":"Inversiones",
    "sg:phone":"+34 928 53 74 37",
    "sg:postcode":"35660",
    "sg:province":"Las Palmas",
    "wof:name":"The Horizon Property Group S.l.",
    "wof:placetype":"venue"
},
  "geometry": {"coordinates":[-13.8686590195,28.7370071411],"type":"Point"}
}