{
  "type": "Feature",
  "properties": {
    "addr:full":"Avda Europa, 19 Pozuelo De Alarcon Madrid 28224",
    "addr:housenumber":"19",
    "addr:postcode":"28224",
    "addr:street":"Avda Europa",
    "iso:country":"ES",
    "sg:address":"Avda Europa, 19",
    "sg:city":"Pozuelo De Alarcon",
    "sg:classifiers":[
        {
            "category":"Banks & Credit Unions",
            "subcategory":"Bureau De Change",
            "type":"Services"
        }
    ],
    "sg:phone":"+34 913 52 18 08",
    "sg:postcode":"28224",
    "sg:province":"Madrid",
    "sg:tags":[
        "organismos",
        "control"
    ],
    "sg:website":"www.igc.es",
    "wof:name":"Socotec Iberia S.a.",
    "wof:placetype":"venue"
},
  "geometry": {"coordinates":[-3.7874910831,40.4409637451],"type":"Point"}
}