{
  "type": "Feature",
  "properties": {
    "addr:full":"Avda Brasilia, 9 Madrid Madrid 28028",
    "addr:housenumber":"9",
    "addr:postcode":"madrid;28028",
    "addr:street":"Avda Brasilia",
    "iso:country":"ES",
    "sg:address":"Avda Brasilia, 9",
    "sg:city":"Madrid",
    "sg:orig_category":"Caf\u00c9s, Bares, Cervecer\u00cdas",
    "sg:phone":"+34 913 55 48 99",
    "sg:postcode":"28028",
    "sg:province":"Madrid",
    "wof:name":"Garcia Fructuoso Luis",
    "wof:placetype":"venue"
},
  "geometry": {"coordinates":[-3.6612710953,40.4370079041],"type":"Point"}
}