{
  "type": "Feature",
  "properties": {
    "addr:full":"Calle de General Pardi\u00d1as, 104 Madrid Madrid 28006",
    "addr:housenumber":"104",
    "addr:postcode":"28006",
    "addr:street":"Calle De General Pardin\u0303As",
    "iso:country":"ES",
    "sg:address":"Calle de General Pardi\u00d1as, 104",
    "sg:city":"Madrid",
    "sg:orig_category":"Muebles, Minoristas",
    "sg:phone":"+34 915 62 36 54",
    "sg:postcode":"28006",
    "sg:province":"Madrid",
    "wof:name":"Tierz Mena Etelvina",
    "wof:placetype":"venue"
},
  "geometry": {"coordinates":[-3.6776030064,40.4351539612],"type":"Point"}
}