{
  "type": "Feature",
  "properties": {
    "iso:country":"ES",
    "sg:address":"Carrer de Mig (del), 92",
    "sg:city":"Aldea",
    "sg:orig_category":"Empresarios",
    "sg:phone":"+34 977 45 04 02",
    "sg:postcode":"43896",
    "sg:province":"Tarragona",
    "wof:name":"Cersech S.l.",
    "wof:placetype":"venue"
},
  "geometry": {"coordinates":[0.6276400089,40.7514801025],"type":"Point"}
}