{
  "type": "Feature",
  "properties": {
    "iso:country":"ES",
    "sg:address":"Avda Blas Infante, 21",
    "sg:city":"Coria Rio",
    "sg:orig_category":"Agentes, Concesionarios Y Sucursales De Veh\u00cdculos",
    "sg:phone":"+34 954 77 21 92",
    "sg:postcode":"41100",
    "sg:province":"Sevilla",
    "wof:name":"Niponsur S.a.",
    "wof:placetype":"venue"
},
  "geometry": {"coordinates":[-6.0575561523,37.2790374756],"type":"Point"}
}