{
  "type": "Feature",
  "properties": {
    "addr:full":"Carrer de Maresme, 20 Lloret Blau Girona 17310",
    "addr:housenumber":"20",
    "addr:postcode":"17310",
    "addr:street":"Carrer De Maresme",
    "iso:country":"ES",
    "sg:address":"Carrer de Maresme, 20",
    "sg:city":"Lloret Blau",
    "sg:orig_category":"Arquitectos",
    "sg:phone":"+34 972 37 81 46",
    "sg:postcode":"17310",
    "sg:province":"Girona",
    "wof:name":"Trasn Boat Union Sl",
    "wof:placetype":"venue"
},
  "geometry": {"coordinates":[2.8131411076,41.7407035828],"type":"Point"}
}