{
  "type": "Feature",
  "properties": {
    "iso:country":"ES",
    "sg:address":"Calle de Alianza, 37",
    "sg:city":"Madrid",
    "sg:orig_category":"Peluquer\u00cdas, Peluquer\u00cda Mixta",
    "sg:phone":"+34 913 17 11 99",
    "sg:postcode":"28041",
    "sg:province":"Madrid",
    "wof:name":"Molinera Fernandez Beatriz",
    "wof:placetype":"venue"
},
  "geometry": {"coordinates":[-3.6865317822,40.3577156067],"type":"Point"}
}