{
  "type": "Feature",
  "properties": {
    "addr:full":"Calle de General Casta\u00d1os, 113 Portugalete Vizcaya 48920",
    "addr:housenumber":"113",
    "addr:postcode":"48920",
    "addr:street":"Calle De General Castan\u0303Os",
    "iso:country":"ES",
    "sg:address":"Calle de General Casta\u00d1os, 113",
    "sg:city":"Portugalete",
    "sg:orig_category":"Mercer\u00cda, Lencer\u00cda (al Por Menor)",
    "sg:phone":"+34 944 61 68 98",
    "sg:postcode":"48920",
    "sg:province":"Vizcaya",
    "wof:name":"Amo Cuesta Lucio",
    "wof:placetype":"venue"
},
  "geometry": {"coordinates":[-3.0304830074,43.3246498108],"type":"Point"}
}