{
  "type": "Feature",
  "properties": {
    "iso:country":"ES",
    "sg:address":"Avda Limonar (el), S/n",
    "sg:city":"Mollina",
    "sg:orig_category":"Droguer\u00cdas (al Por Menor)",
    "sg:phone":"+34 952 74 03 09",
    "sg:postcode":"29532",
    "sg:province":"M\u00e1laga",
    "wof:name":"Drosolu S.l.",
    "wof:placetype":"venue"
},
  "geometry": {"coordinates":[-4.6613688469,37.1246490479],"type":"Point"}
}