{
  "type": "Feature",
  "properties": {
    "iso:country":"ES",
    "sg:address":"Calle de Altozano, 9",
    "sg:city":"Madrid",
    "sg:orig_category":"Inmobiliaria (agencias)",
    "sg:phone":"+34 913 57 40 98",
    "sg:postcode":"28023",
    "sg:province":"Madrid",
    "wof:name":"Cerro De Los Gamos S.l.",
    "wof:placetype":"venue"
},
  "geometry": {"coordinates":[-3.7795932293,40.4575538635],"type":"Point"}
}