{
  "type": "Feature",
  "properties": {
    "addr:full":"Calle de Acera Del Pilar, 1 Herradura Granada 18697",
    "addr:housenumber":"1",
    "addr:postcode":"18697",
    "addr:street":"Calle De Acera Del Pilar",
    "iso:country":"ES",
    "sg:address":"Calle de Acera Del Pilar, 1",
    "sg:city":"Herradura",
    "sg:orig_category":"Inmobiliaria (agencias)",
    "sg:phone":"+34 958 61 81 38",
    "sg:postcode":"18697",
    "sg:province":"Granada",
    "wof:name":"Tropicana Developments S.l.",
    "wof:placetype":"venue"
},
  "geometry": {"coordinates":[-3.7390809059,36.7353096008],"type":"Point"}
}