{
  "type": "Feature",
  "properties": {
    "iso:country":"ES",
    "sg:address":"Carr Bonavista, 7",
    "sg:city":"Bellcaire D'urgell",
    "sg:orig_category":"Peluquer\u00cdas, Peluquer\u00cda Mixta",
    "sg:phone":"+34 973 58 60 74",
    "sg:postcode":"25337",
    "sg:province":"Lleida",
    "wof:name":"Gonzalez Montane Eva",
    "wof:placetype":"venue"
},
  "geometry": {"coordinates":[0.9087305069,41.7579078674],"type":"Point"}
}