{
  "type": "Feature",
  "properties": {
    "iso:country":"ES",
    "sg:address":"Pase Conde De Sepulveda (del), 25",
    "sg:city":"Segovia",
    "sg:orig_category":"Centros Empresariales",
    "sg:phone":"+34 921 41 28 69",
    "sg:postcode":"40006",
    "sg:province":"Segovia",
    "wof:name":"Servicios Y Finanzas Piedra S.l.",
    "wof:placetype":"venue"
},
  "geometry": {"coordinates":[-4.1165308952,40.940574646],"type":"Point"}
}