{
  "type": "Feature",
  "properties": {
    "iso:country":"ES",
    "sg:address":"Grup Doctor Areilza, 13",
    "sg:city":"Gallarta",
    "sg:orig_category":"Muebles, Minoristas",
    "sg:phone":"+34 946 36 22 19",
    "sg:postcode":"48500",
    "sg:province":"Vizcaya",
    "wof:name":"Santamaria Maga\u00f1a Josefa",
    "wof:placetype":"venue"
},
  "geometry": {"coordinates":[-3.0721669197,43.3160514832],"type":"Point"}
}