{
  "type": "Feature",
  "properties": {
    "iso:country":"ES",
    "sg:address":"Pg Sant Gervasi, 65",
    "sg:city":"Barcelona",
    "sg:orig_category":"Restaurantes",
    "sg:phone":"+34 934 17 11 24",
    "sg:postcode":"08022",
    "sg:province":"Barcelona",
    "wof:name":"Molina Teruel Felix",
    "wof:placetype":"venue"
},
  "geometry": {"coordinates":[2.1380739212,41.4116668701],"type":"Point"}
}