{
  "type": "Feature",
  "properties": {
    "iso:country":"ES",
    "sg:address":"Calle de Mayor, 24",
    "sg:city":"Jaca",
    "sg:orig_category":"Administraciones Regionales, Departamentales Y Locales",
    "sg:phone":"+34 974 35 57 58",
    "sg:postcode":"22700",
    "sg:province":"Huesca",
    "sg:website":"www.aytojaca.es",
    "wof:name":"Ayuntamiento De Jaca",
    "wof:placetype":"venue"
},
  "geometry": {"coordinates":[-0.6236429811,42.5333251953],"type":"Point"}
}