{
  "type": "Feature",
  "properties": {
    "addr:full":"Luga Vista De Yaiza, S/n Yaiza Las Palmas 35570",
    "addr:housenumber":"s / n",
    "addr:postcode":"35570",
    "addr:street":"Luga Vista De Yaiza",
    "iso:country":"ES",
    "sg:address":"Luga Vista De Yaiza, S/n",
    "sg:city":"Yaiza",
    "sg:classifiers":[
        {
            "category":"Government",
            "subcategory":"Office",
            "type":"Public Place"
        }
    ],
    "sg:phone":"+34 928 83 02 25",
    "sg:postcode":"35570",
    "sg:province":"Las Palmas",
    "sg:tags":[
        "interior",
        "administraci\u00d3n",
        "en"
    ],
    "wof:name":"Ayuntamiento De Yaiza.parque Movil.",
    "wof:placetype":"venue"
},
  "geometry": {"coordinates":[-13.7652635574,28.9524669647],"type":"Point"}
}