{
  "type": "Feature",
  "properties": {
    "addr:full":"Avda Duque De Tamames, 13 Orihuela Alicante 03300",
    "addr:housenumber":"13",
    "addr:postcode":"03300",
    "addr:street":"Avda Duque De Tamames",
    "iso:country":"ES",
    "sg:address":"Avda Duque De Tamames, 13",
    "sg:city":"Orihuela",
    "sg:orig_category":"Prot\u00c9sicos Dentales",
    "sg:phone":"+34 965 30 24 99",
    "sg:postcode":"03300",
    "sg:province":"Alicante",
    "wof:name":"Pertusa Reina Jose Antonio",
    "wof:placetype":"venue"
},
  "geometry": {"coordinates":[-0.9466350079,38.0816192627],"type":"Point"}
}