{
  "type": "Feature",
  "properties": {
    "addr:full":"Plaz Estudios De Los, 9 Donostia-san Sebastian Guip\u00f9zcoa 20011",
    "addr:housenumber":"9",
    "addr:postcode":"20011",
    "iso:country":"ES",
    "sg:address":"Plaz Estudios De Los, 9",
    "sg:city":"Donostia-san Sebastian",
    "sg:orig_category":"Centros P\u00dablicos De Formaci\u00d3n Profesional Y T\u00c9cnica",
    "sg:phone":"+34 943 45 39 27",
    "sg:postcode":"20011",
    "sg:province":"Guip\u00f9zcoa",
    "wof:name":"Colegio Oficial De Delineantes De Guipuzcoa",
    "wof:placetype":"venue"
},
  "geometry": {"coordinates":[-1.9794000387,43.3173789978],"type":"Point"}
}