{
  "type": "Feature",
  "properties": {
    "iso:country":"ES",
    "sg:address":"Calle de Oidor Gregorio Tovar, 35",
    "sg:city":"Coru\u00d1a",
    "sg:orig_category":"Peluquer\u00cdas, Peluquer\u00cda Mixta",
    "sg:phone":"+34 981 23 97 40",
    "sg:postcode":"15007",
    "sg:province":"La Coru\u00f1a",
    "wof:name":"Bermudez Corral Encarnacion",
    "wof:placetype":"venue"
},
  "geometry": {"coordinates":[-8.4087562561,43.3552207947],"type":"Point"}
}