{
  "type": "Feature",
  "properties": {
    "iso:country":"ES",
    "sg:address":"Av Valencia, 24",
    "sg:city":"Gandesa",
    "sg:orig_category":"Productores Recolectores, Venta Directa De Vinos",
    "sg:phone":"+34 977 42 00 31",
    "sg:postcode":"43780",
    "sg:province":"Tarragona",
    "wof:name":"Patrimonial Galcera Tarrago",
    "wof:placetype":"venue"
},
  "geometry": {"coordinates":[0.4392670095,41.0532913208],"type":"Point"}
}