{
  "type": "Feature",
  "properties": {
    "iso:country":"ES",
    "sg:address":"Calle de Aurelio Gonzalez De Gregorio, 14",
    "sg:city":"Madrid",
    "sg:orig_category":"Muebles, Minoristas",
    "sg:phone":"+34 913 58 43 02",
    "sg:postcode":"28034",
    "sg:province":"Madrid",
    "sg:website":"www.grupoindecor.com",
    "wof:name":"Grupo Indecor S.a.",
    "wof:placetype":"venue"
},
  "geometry": {"coordinates":[-3.687002182,40.4942512512],"type":"Point"}
}