{
  "type": "Feature",
  "properties": {
    "iso:country":"ES",
    "sg:address":"Ctra Barcelona, Km. 0279,0",
    "sg:city":"Vendrell",
    "sg:orig_category":"Comercio De Hierro",
    "sg:phone":"+34 977 66 39 13",
    "sg:postcode":"43700",
    "sg:province":"Tarragona",
    "wof:name":"Hierros Prats S. A.",
    "wof:placetype":"venue"
},
  "geometry": {"coordinates":[1.5381799936,41.2216491699],"type":"Point"}
}