{
  "type": "Feature",
  "properties": {
    "iso:country":"ES",
    "sg:address":"Avda Sor Soledad Cobian, 19",
    "sg:city":"Orotava",
    "sg:orig_category":"Centros M\u00c9dicos Y Sociales, Dispensarios",
    "sg:phone":"+34 922 32 06 53",
    "sg:postcode":"38300",
    "sg:province":"Santa Cruz De Tenerife",
    "wof:name":"Wolf  Britta",
    "wof:placetype":"venue"
},
  "geometry": {"coordinates":[-16.5199489594,28.3917369843],"type":"Point"}
}