{
  "type": "Feature",
  "properties": {
    "iso:country":"ES",
    "sg:address":"Avda Pintor Antonio Fernandez Sevilla, 5",
    "sg:city":"Puerto De Santa Maria",
    "sg:orig_category":"Bisuter\u00cda, Joyer\u00cda, Relojer\u00cda (al Por Menor)",
    "sg:phone":"+34 956 85 98 08",
    "sg:postcode":"11500",
    "sg:province":"C\u00e1diz",
    "wof:name":"Vivoras Galvin Francisca",
    "wof:placetype":"venue"
},
  "geometry": {"coordinates":[-6.2366290092,36.5940170288],"type":"Point"}
}