{
  "type": "Feature",
  "properties": {
    "addr:full":"Calle de Ancha, 1 Cabezas S. Juan Sevilla 41730",
    "addr:housenumber":"1",
    "addr:postcode":"41730",
    "addr:street":"Calle De Ancha;S.",
    "iso:country":"ES",
    "sg:address":"Calle de Ancha, 1",
    "sg:city":"Cabezas S. Juan",
    "sg:orig_category":"Quincaller\u00cda (al Por Menor)",
    "sg:phone":"+34 955 87 20 98",
    "sg:postcode":"41730",
    "sg:province":"Sevilla",
    "wof:name":"Morato Paez Francisco",
    "wof:placetype":"venue"
},
  "geometry": {"coordinates":[-5.9382095337,36.9854049683],"type":"Point"}
}