{
  "type": "Feature",
  "properties": {
    "addr:full":"Plaz San Miguel, 1 Oviedo Asturias 33008",
    "addr:housenumber":"1",
    "addr:postcode":"33008",
    "addr:street":"Plaz San Miguel",
    "iso:country":"ES",
    "sg:address":"Plaz San Miguel, 1",
    "sg:city":"Oviedo",
    "sg:orig_category":"Restaurantes",
    "sg:phone":"+34 985 22 94 88",
    "sg:postcode":"33008",
    "sg:province":"Asturias",
    "wof:name":"Gomez Y Monteserin C.b.",
    "wof:placetype":"venue"
},
  "geometry": {"coordinates":[-5.8050780296,43.3564186096],"type":"Point"}
}