{
  "type": "Feature",
  "properties": {
    "addr:full":"Calle de Padre Isla, 25 Cistierna Le\u00f3n 24800",
    "addr:housenumber":"25",
    "addr:postcode":"24800",
    "addr:street":"Calle De Padre Isla;Leo\u0301N",
    "iso:country":"ES",
    "sg:address":"Calle de Padre Isla, 25",
    "sg:city":"Cistierna",
    "sg:orig_category":"Ropa Para Se\u00d1oras (al Por Menor)",
    "sg:phone":"+34 987 70 10 63",
    "sg:postcode":"24800",
    "sg:province":"Le\u00f3n",
    "wof:name":"Rodriguez Alaez Maria Isabel",
    "wof:placetype":"venue"
},
  "geometry": {"coordinates":[-5.1311020851,42.8043823242],"type":"Point"}
}