{
  "type": "Feature",
  "properties": {
    "addr:full":"Crri Navarros, 13 Puente Tocinos Murcia 30006",
    "addr:housenumber":"13",
    "addr:postcode":"30006",
    "addr:street":"Navarros",
    "iso:country":"ES",
    "sg:address":"Crri Navarros, 13",
    "sg:city":"Puente Tocinos",
    "sg:orig_category":"Electricidad: Instaladores",
    "sg:phone":"+34 968 30 40 25",
    "sg:postcode":"30006",
    "sg:province":"Murcia",
    "wof:name":"Instalaciones Electricas Saez S.l.",
    "wof:placetype":"venue"
},
  "geometry": {"coordinates":[-1.0886797905,37.9956932068],"type":"Point"}
}