{
  "type": "Feature",
  "properties": {
    "iso:country":"ES",
    "sg:address":"Carrer de Blai, 24",
    "sg:city":"Barcelona",
    "sg:orig_category":"Mec\u00c1nico Del Autom\u00d3vil",
    "sg:phone":"+34 933 29 95 54",
    "sg:postcode":"08004",
    "sg:province":"Barcelona",
    "wof:name":"Tallers Santa Madrona S.l.",
    "wof:placetype":"venue"
},
  "geometry": {"coordinates":[2.1647880077,41.3737297058],"type":"Point"}
}