{
  "type": "Feature",
  "properties": {
    "addr:full":"Carrer de Luca, 9 Barcelona Barcelona 08022",
    "addr:housenumber":"9",
    "addr:postcode":"08022",
    "addr:street":"Carrer De Luca",
    "iso:country":"ES",
    "sg:address":"Carrer de Luca, 9",
    "sg:city":"Barcelona",
    "sg:orig_category":"Estancos",
    "sg:phone":"+34 932 12 04 24",
    "sg:postcode":"08022",
    "sg:province":"Barcelona",
    "wof:name":"Ferrer Maneja Alfonso",
    "wof:placetype":"venue"
},
  "geometry": {"coordinates":[2.1389400959,41.4109153748],"type":"Point"}
}