{
  "type": "Feature",
  "properties": {
    "iso:country":"ES",
    "sg:address":"Calle de Barahona De Soto, 11",
    "sg:city":"Cabra",
    "sg:orig_category":"M\u00c9dicos: An\u00c1lisis Cl\u00cdnicos",
    "sg:phone":"+34 957 52 00 56",
    "sg:postcode":"14940",
    "sg:province":"C\u00f3rdoba",
    "wof:name":"Mu\u00f1iz Cordon Manuel",
    "wof:placetype":"venue"
},
  "geometry": {"coordinates":[-4.4419903755,37.4715080261],"type":"Point"}
}