{
  "type": "Feature",
  "properties": {
    "iso:country":"ES",
    "sg:address":"Calle de Artesanos, 4",
    "sg:city":"Ronda",
    "sg:orig_category":"Bares, Piano",
    "sg:phone":"+34 952 87 77 55",
    "sg:postcode":"29400",
    "sg:province":"M\u00e1laga",
    "wof:name":"Becerra Pe\u00f1a Juan Manuel",
    "wof:placetype":"venue"
},
  "geometry": {"coordinates":[-5.1672120094,36.7472038269],"type":"Point"}
}