{
  "type": "Feature",
  "properties": {
    "addr:full":"Carrer de Viladomat, 191 Barcelona Barcelona 08015",
    "addr:housenumber":"191",
    "addr:postcode":"08015",
    "addr:street":"Carrer De Viladomat",
    "iso:country":"ES",
    "sg:address":"Carrer de Viladomat, 191",
    "sg:city":"Barcelona",
    "sg:orig_category":"Negocio De Madera",
    "sg:phone":"+34 932 26 34 92",
    "sg:postcode":"08015",
    "sg:province":"Barcelona",
    "wof:name":"Maderas Prat Vidal S. A.",
    "wof:placetype":"venue"
},
  "geometry": {"coordinates":[2.1519548893,41.3835296631],"type":"Point"}
}