{
  "type": "Feature",
  "properties": {
    "addr:full":"Calle de Jesus Del Perdon, 75 Manzanares Ciudad Real 13200",
    "addr:housenumber":"75",
    "addr:postcode":"13200",
    "addr:street":"Calle De Jesus Del Perdon",
    "iso:country":"ES",
    "sg:address":"Calle de Jesus Del Perdon, 75",
    "sg:city":"Manzanares",
    "sg:orig_category":"Materiales De Construcci\u00d3n, Herramientas",
    "sg:phone":"+34 926 61 07 79",
    "sg:postcode":"13200",
    "sg:province":"Ciudad Real",
    "wof:name":"Hermanos Sanchez De La Serrana S.a.",
    "wof:placetype":"venue"
},
  "geometry": {"coordinates":[-3.3765070438,39.0020446777],"type":"Point"}
}