{
  "type": "Feature",
  "properties": {
    "addr:full":"Carrer de Mossen Salvador Ritort I Faus, 17 Tarragona Tarragona 43002",
    "addr:housenumber":"17",
    "addr:postcode":"43002",
    "addr:street":"Carrer De Mossen Salvador Ritort;Faus",
    "iso:country":"ES",
    "sg:address":"Carrer de Mossen Salvador Ritort I Faus, 17",
    "sg:city":"Tarragona",
    "sg:orig_category":"Peluqueros: De Se\u00d1oras",
    "sg:phone":"+34 977 22 46 13",
    "sg:postcode":"43002",
    "sg:province":"Tarragona",
    "wof:name":"Curulla Pascual Nuria",
    "wof:placetype":"venue"
},
  "geometry": {"coordinates":[1.2494260073,41.1209983826],"type":"Point"}
}