{
  "type": "Feature",
  "properties": {
    "addr:full":"Calle de Pizarro, 6 Monte Santa Cruz De Tenerife 38639",
    "addr:housenumber":"6",
    "addr:postcode":"38639",
    "addr:street":"Calle De Pizarro",
    "iso:country":"ES",
    "sg:address":"Calle de Pizarro, 6",
    "sg:city":"Monte",
    "sg:orig_category":"Carnicer\u00cdas, Carnicer\u00cdas",
    "sg:phone":"+34 922 73 06 85",
    "sg:postcode":"38639",
    "sg:province":"Santa Cruz De Tenerife",
    "wof:name":"Bechold  Ute Maria",
    "wof:placetype":"venue"
},
  "geometry": {"coordinates":[-16.6115474701,28.0350246429],"type":"Point"}
}