{
  "type": "Feature",
  "properties": {
    "addr:full":"Calle de Estanco, 4 San Martin De La Vega Del Alberche \u00c1vila 05133",
    "addr:housenumber":"4",
    "addr:postcode":"05133",
    "addr:street":"Calle De Estanco;A\u0301Vila",
    "iso:country":"ES",
    "sg:address":"Calle de Estanco, 4",
    "sg:city":"San Martin De La Vega Del Alberche",
    "sg:orig_category":"Transportes Por Carretera: Lotes Completos, Mercanc\u00cdas Diversas",
    "sg:phone":"+34 920 29 62 85",
    "sg:postcode":"05133",
    "sg:province":"\u00c1vila",
    "wof:name":"Cecilio Sanchez Maria Rosa",
    "wof:placetype":"venue"
},
  "geometry": {"coordinates":[-5.1552591324,40.4298400879],"type":"Point"}
}