{
  "type": "Feature",
  "properties": {
    "addr:full":"Calle de Artesania, 23 Mairena Aljarafe Sevilla 41927",
    "addr:housenumber":"23",
    "addr:postcode":"41927",
    "addr:street":"Calle De Artesania",
    "iso:country":"ES",
    "sg:address":"Calle de Artesania, 23",
    "sg:city":"Mairena Aljarafe",
    "sg:orig_category":"Molduras, Junquillos, Listones Y Molduras Perforadas",
    "sg:phone":"+34 955 60 04 24",
    "sg:postcode":"41927",
    "sg:province":"Sevilla",
    "wof:name":"Cafeteria Bar Zoco S.l.",
    "wof:placetype":"venue"
},
  "geometry": {"coordinates":[-6.0549926758,37.3575363159],"type":"Point"}
}