{
  "type": "Feature",
  "properties": {
    "iso:country":"ES",
    "sg:address":"Avda Rafael Alberti, 45",
    "sg:city":"Madrid",
    "sg:orig_category":"Fabricaci\u00d3n, Venta De Cuadros, Accesorios Para Enmarcar",
    "sg:phone":"+34 913 03 71 47",
    "sg:postcode":"28038",
    "sg:province":"Madrid",
    "wof:name":"Martin Sanchez Diosdada",
    "wof:placetype":"venue"
},
  "geometry": {"coordinates":[-3.6429140568,40.3837852478],"type":"Point"}
}