{
  "type": "Feature",
  "properties": {
    "addr:full":"Calle de Principado, 5 Oviedo Asturias 33007",
    "addr:housenumber":"5",
    "addr:postcode":"33007",
    "addr:street":"Calle De Principado",
    "iso:country":"ES",
    "sg:address":"Calle de Principado, 5",
    "sg:city":"Oviedo",
    "sg:orig_category":"Promotores Constructores",
    "sg:phone":"+34 985 22 45 45",
    "sg:postcode":"33007",
    "sg:province":"Asturias",
    "wof:name":"Construcciones Astusa S.l",
    "wof:placetype":"venue"
},
  "geometry": {"coordinates":[-5.8483228683,43.3606033325],"type":"Point"}
}