{
  "type": "Feature",
  "properties": {
    "addr:full":"Avda Pais Valencia, 45 Sagunt Valencia 46500",
    "addr:housenumber":"45",
    "addr:postcode":"46500",
    "addr:street":"Avda Pais Valencia",
    "iso:country":"ES",
    "sg:address":"Avda Pais Valencia, 45",
    "sg:city":"Sagunt",
    "sg:orig_category":"Transportes Por Carretera: Lotes Completos, Mercanc\u00cdas Diversas",
    "sg:phone":"+34 962 66 07 86",
    "sg:postcode":"46500",
    "sg:province":"Valencia",
    "wof:name":"Lopez Pla Emilio",
    "wof:placetype":"venue"
},
  "geometry": {"coordinates":[-0.2710970044,39.6776695251],"type":"Point"}
}