{
  "type": "Feature",
  "properties": {
    "addr:full":"Av Progreso(b Progreso), 149 Murcia Murcia 30012",
    "addr:housenumber":"149",
    "addr:postcode":"30012",
    "addr:street":"Av Progreso B Progreso",
    "iso:country":"ES",
    "sg:address":"Av Progreso(b Progreso), 149",
    "sg:city":"Murcia",
    "sg:orig_category":"Muebles Y Accesorios Para Cocinas Y Cuartos De Ba\u00d1o (al Por Menor)",
    "sg:phone":"+34 968 34 39 53",
    "sg:postcode":"30012",
    "sg:province":"Murcia",
    "wof:name":"Rose Watch S.l",
    "wof:placetype":"venue"
},
  "geometry": {"coordinates":[-1.1190229654,37.9603996277],"type":"Point"}
}