{
  "type": "Feature",
  "properties": {
    "iso:country":"ES",
    "sg:address":"Lg Santaya(codeso), S/n",
    "sg:city":"Ardesende",
    "sg:orig_category":"Asociaciones, Organismos Culturales Y Socioeducativos",
    "sg:phone":"+34 981 51 24 34",
    "sg:postcode":"15881",
    "sg:province":"La Coru\u00f1a",
    "wof:name":"Concello De Boqueixon",
    "wof:placetype":"venue"
},
  "geometry": {"coordinates":[-8.4128170013,42.8135566711],"type":"Point"}
}