{
  "type": "Feature",
  "properties": {
    "addr:full":"Carrer de Santuari, 4 Barcelona Barcelona 08032",
    "addr:housenumber":"4",
    "addr:postcode":"08032",
    "addr:street":"Carrer De Santuari",
    "iso:country":"ES",
    "sg:address":"Carrer de Santuari, 4",
    "sg:city":"Barcelona",
    "sg:orig_category":"Bisuter\u00cda, Joyer\u00cda, Relojer\u00cda (al Por Menor)",
    "sg:phone":"+34 932 10 11 55",
    "sg:postcode":"08032",
    "sg:province":"Barcelona",
    "wof:name":"Abad Bea Marina",
    "wof:placetype":"venue"
},
  "geometry": {"coordinates":[2.149496,41.420345],"type":"Point"}
}