{
  "type": "Feature",
  "properties": {
    "addr:full":"Calle de Verde Viento, S/n Madrid Madrid 28021",
    "addr:housenumber":"s / n",
    "addr:postcode":"28021",
    "addr:street":"Calle De Verde Viento",
    "iso:country":"ES",
    "sg:address":"Calle de Verde Viento, S/n",
    "sg:city":"Madrid",
    "sg:orig_category":"Centros De Educaci\u00d3n Especial",
    "sg:phone":"+34 915 05 33 17",
    "sg:postcode":"28021",
    "sg:province":"Madrid",
    "wof:name":"Comunidad Autonoma De Madrid-centros De Educacion",
    "wof:placetype":"venue"
},
  "geometry": {"coordinates":[-3.7161040306,40.3543739319],"type":"Point"}
}