{
  "type": "Feature",
  "properties": {
    "iso:country":"ES",
    "sg:address":"Calle de Mercedes Arteaga, 41",
    "sg:city":"Madrid",
    "sg:classifiers":[
        {
            "category":"Autos & Motor Vehicles",
            "subcategory":"Automobile Sales",
            "type":"Retail Goods"
        }
    ],
    "sg:phone":"+34 914 60 20 64",
    "sg:postcode":"28019",
    "sg:province":"Madrid",
    "wof:name":"Alonso Rodriguez Maria Gabriela",
    "wof:placetype":"venue"
},
  "geometry": {"coordinates":[-3.7229654789,40.3911552429],"type":"Point"}
}