{
  "type": "Feature",
  "properties": {
    "iso:country":"ES",
    "sg:address":"Calle de Marina Espa\u00d1ola, 2",
    "sg:city":"Elda",
    "sg:orig_category":"Modistas",
    "sg:phone":"+34 965 38 89 33",
    "sg:postcode":"03600",
    "sg:province":"Alicante",
    "wof:name":"Gil Cartena Francisca",
    "wof:placetype":"venue"
},
  "geometry": {"coordinates":[-0.79974401,38.4762535095],"type":"Point"}
}