{
  "type": "Feature",
  "properties": {
    "addr:full":"Calle de Agustina De Aragon, 4 Ceuta Ceuta 51001",
    "addr:housenumber":"4",
    "addr:postcode":"51001",
    "addr:street":"Calle De Agustina De Aragon",
    "iso:country":"ES",
    "sg:address":"Calle de Agustina De Aragon, 4",
    "sg:city":"Ceuta",
    "sg:orig_category":"Seguridad Social",
    "sg:phone":"+34 956 51 52 16",
    "sg:postcode":"51001",
    "sg:province":"Ceuta",
    "wof:name":"Tesoreria General De La Seguridad Social-servicios Centrales",
    "wof:placetype":"venue"
},
  "geometry": {"coordinates":[-5.306953907,35.888381958],"type":"Point"}
}