{
  "type": "Feature",
  "properties": {
    "iso:country":"ES",
    "sg:address":"Calle de Guzman El Bueno, 25",
    "sg:city":"Madrid",
    "sg:orig_category":"Aparatos, Material Y Suministros Para Laboratorios",
    "sg:phone":"+34 915 50 04 88",
    "sg:postcode":"28015",
    "sg:province":"Madrid",
    "wof:name":"Microm Laborgerate S.l.",
    "wof:placetype":"venue"
},
  "geometry": {"coordinates":[-3.7135241032,40.4324188232],"type":"Point"}
}