{
  "type": "Feature",
  "properties": {
    "addr:full":"Rua Progreso (do), 101 Ourense Ourense 32003",
    "addr:housenumber":"101",
    "addr:postcode":"32003",
    "addr:street":"Rua Progreso Do",
    "iso:country":"ES",
    "sg:address":"Rua Progreso (do), 101",
    "sg:city":"Ourense",
    "sg:orig_category":"Quincaller\u00cda (al Por Menor)",
    "sg:phone":"+34 988 22 05 97",
    "sg:postcode":"32003",
    "sg:province":"Ourense",
    "wof:name":"Manuel Y Francisco Llamas Y Compa\u00f1ia S. C. R.",
    "wof:placetype":"venue"
},
  "geometry": {"coordinates":[-7.8664598465,42.3392448425],"type":"Point"}
}