{
  "type": "Feature",
  "properties": {
    "iso:country":"ES",
    "sg:address":"Calle de Castillejos, 32",
    "sg:city":"Madrid",
    "sg:orig_category":"Empresas De Carpinter\u00cda De Madera",
    "sg:phone":"+34 913 11 59 35",
    "sg:postcode":"28039",
    "sg:province":"Madrid",
    "wof:name":"Colmenar Lopez-rey Vicente",
    "wof:placetype":"venue"
},
  "geometry": {"coordinates":[-3.7064425945,40.4561004639],"type":"Point"}
}