{
  "type": "Feature",
  "properties": {
    "iso:country":"ES",
    "sg:address":"Calle de General Primo De Rivera, 11",
    "sg:city":"Algeciras",
    "sg:orig_category":"M\u00c9dicos: Cirug\u00cda Ortop\u00c9dica Y Traumatolog\u00cda",
    "sg:phone":"+34 956 63 28 43",
    "sg:postcode":"11201",
    "sg:province":"C\u00e1diz",
    "wof:name":"Ayllon Garcia Antonio",
    "wof:placetype":"venue"
},
  "geometry": {"coordinates":[-5.4475917816,36.1312522888],"type":"Point"}
}