{
  "type": "Feature",
  "properties": {
    "iso:country":"ES",
    "sg:address":"Carrer de Pujos, 15",
    "sg:city":"Hospitalet Llobregat",
    "sg:orig_category":"Complementos De Vestir (al Por Menor)",
    "sg:phone":"+34 933 34 67 76",
    "sg:postcode":"08904",
    "sg:province":"Barcelona",
    "wof:name":"Arias Rubio Rosa Maria",
    "wof:placetype":"venue"
},
  "geometry": {"coordinates":[2.1191971302,41.3736686707],"type":"Point"}
}