{
  "type": "Feature",
  "properties": {
    "iso:country":"ES",
    "sg:address":"Cno. Ciza\u00f1a, 2",
    "sg:city":"Malaga",
    "sg:orig_category":"\u00d3ptica: Instrumentos (fabricaci\u00d3n)",
    "sg:phone":"+34 952 05 27 00",
    "sg:postcode":"29620",
    "sg:province":"M\u00e1laga",
    "wof:name":"Alboy S..",
    "wof:placetype":"venue"
},
  "geometry": {"coordinates":[-4.4763760567,36.6513900757],"type":"Point"}
}