{
  "type": "Feature",
  "properties": {
    "addr:full":"Calle de Fisicas, 62 Alcorcon Madrid 28921",
    "addr:housenumber":"62",
    "addr:postcode":"28921",
    "addr:street":"Calle De Fisicas",
    "iso:country":"ES",
    "sg:address":"Calle de Fisicas, 62",
    "sg:city":"Alcorcon",
    "sg:orig_category":"Automatizaci\u00d3n De Procesos Industriales Y De Edificaci\u00d3n (estudios, Instalaci\u00d3n)",
    "sg:phone":"+34 916 43 50 60",
    "sg:postcode":"28921",
    "sg:province":"Madrid",
    "sg:website":"www.erreka.com",
    "wof:name":"Matz-erreka S.coop.",
    "wof:placetype":"venue"
},
  "geometry": {"coordinates":[-3.8146140575,40.335395813],"type":"Point"}
}