{
  "type": "Feature",
  "properties": {
    "iso:country":"ES",
    "sg:address":"Pase Casta\u00d1os (los), 2",
    "sg:city":"Aguadulce",
    "sg:orig_category":"Promotores Constructores",
    "sg:phone":"+34 950 55 03 57",
    "sg:postcode":"04720",
    "sg:province":"Almer\u00eda",
    "wof:name":"Jimenez Jimenez Joaquin",
    "wof:placetype":"venue"
},
  "geometry": {"coordinates":[-2.5974500179,36.801410675],"type":"Point"}
}