{
  "type": "Feature",
  "properties": {
    "addr:full":"Calle de Granada, 2 Puebla Cazalla Sevilla 41540",
    "addr:housenumber":"2",
    "addr:postcode":"41540",
    "addr:street":"Calle De Granada",
    "iso:country":"ES",
    "sg:address":"Calle de Granada, 2",
    "sg:city":"Puebla Cazalla",
    "sg:orig_category":"Carnicer\u00cdas, Carnicer\u00cdas",
    "sg:phone":"+34 954 84 61 69",
    "sg:postcode":"41540",
    "sg:province":"Sevilla",
    "wof:name":"Cabello Barrera Maria Del Carmen",
    "wof:placetype":"venue"
},
  "geometry": {"coordinates":[-5.3132190704,37.2229957581],"type":"Point"}
}