{
  "type": "Feature",
  "properties": {
    "addr:full":"Plaz Corpus (del), 1 Segovia Segovia 40001",
    "addr:postcode":"40001",
    "iso:country":"ES",
    "sg:address":"Plaz Corpus (del), 1",
    "sg:city":"Segovia",
    "sg:orig_category":"Caf\u00c9s, Bares, Cervecer\u00cdas",
    "sg:phone":"+34 921 46 21 68",
    "sg:postcode":"40001",
    "sg:province":"Segovia",
    "wof:name":"Cafes Y Tes La Colonial S.l.",
    "wof:placetype":"venue"
},
  "geometry": {"coordinates":[-4.1235318184,40.9496116638],"type":"Point"}
}