{
  "type": "Feature",
  "properties": {
    "iso:country":"ES",
    "sg:address":"Carrer de Argentona (d'), 1",
    "sg:city":"Mataro",
    "sg:orig_category":"Asociaciones Y Clubs Deportivos",
    "sg:phone":"+34 937 90 53 93",
    "sg:postcode":"08302",
    "sg:province":"Barcelona",
    "wof:name":"Juventus Agrupacion Cultural",
    "wof:placetype":"venue"
},
  "geometry": {"coordinates":[2.4439020157,41.541053772],"type":"Point"}
}