{
  "type": "Feature",
  "properties": {
    "addr:full":"Rua Republica De El Salvador (da), 29 Santiago De Compostela La Coru\u00f1a 15701",
    "addr:housenumber":"29",
    "addr:postcode":"15701",
    "addr:street":"Rua Republica De El;Corun\u0303A",
    "iso:country":"ES",
    "sg:address":"Rua Republica De El Salvador (da), 29",
    "sg:city":"Santiago De Compostela",
    "sg:orig_category":"M\u00c9dicos: Cirug\u00cda Urol\u00d3gica",
    "sg:phone":"+34 981 59 56 75",
    "sg:postcode":"15701",
    "sg:province":"La Coru\u00f1a",
    "wof:name":"Martinez Couceiro Saturnino",
    "wof:placetype":"venue"
},
  "geometry": {"coordinates":[-8.5484924316,42.8743438721],"type":"Point"}
}