{
  "type": "Feature",
  "properties": {
    "iso:country":"ES",
    "sg:address":"Calle de Sevilla, 8",
    "sg:city":"Carmona",
    "sg:orig_category":"Relojer\u00cda (al Por Menor, Reparaci\u00d3n)",
    "sg:phone":"+34 954 14 33 79",
    "sg:postcode":"41410",
    "sg:province":"Sevilla",
    "wof:name":"Garcia Garcia Julio",
    "wof:placetype":"venue"
},
  "geometry": {"coordinates":[-5.6455559731,37.4696464539],"type":"Point"}
}