{
  "type": "Feature",
  "properties": {
    "addr:full":"Carrer de Colom, 581 Terrassa Barcelona 08223",
    "addr:housenumber":"581",
    "addr:postcode":"08223",
    "addr:street":"Carrer De Colom",
    "iso:country":"ES",
    "sg:address":"Carrer de Colom, 581",
    "sg:city":"Terrassa",
    "sg:orig_category":"Autob\u00das (explotaci\u00d3n Y Servicios De)",
    "sg:phone":"+34 937 84 19 66",
    "sg:postcode":"08223",
    "sg:province":"Barcelona",
    "wof:name":"Leyca Bus S. A.",
    "wof:placetype":"venue"
},
  "geometry": {"coordinates":[2.0277900696,41.5477714539],"type":"Point"}
}