{
  "type": "Feature",
  "properties": {
    "addr:full":"Calle de Manuel Pedregal, 6 Oviedo Asturias 33001",
    "addr:housenumber":"6",
    "addr:postcode":"33001",
    "addr:street":"Calle De Manuel Pedregal",
    "iso:country":"ES",
    "sg:address":"Calle de Manuel Pedregal, 6",
    "sg:city":"Oviedo",
    "sg:orig_category":"Partidos Pol\u00cdticos",
    "sg:phone":"+34 984 05 18 00",
    "sg:postcode":"33001",
    "sg:province":"Asturias",
    "wof:name":"Partido Popular",
    "wof:placetype":"venue"
},
  "geometry": {"coordinates":[-5.8522381783,43.3664970398],"type":"Point"}
}