{
  "type": "Feature",
  "properties": {
    "addr:full":"Carrer de Girona, S/n Senia Tarragona 43560",
    "addr:housenumber":"s / n",
    "addr:postcode":"43560",
    "addr:street":"Carrer De Girona",
    "iso:country":"ES",
    "sg:address":"Carrer de Girona, S/n",
    "sg:city":"Senia",
    "sg:orig_category":"M\u00c1quinas, Material Y Suministros Para Cajas Y Embalajes",
    "sg:phone":"+34 977 57 52 45",
    "sg:postcode":"43560",
    "sg:province":"Tarragona",
    "wof:name":"Stock Plus S.l.",
    "wof:placetype":"venue"
},
  "geometry": {"coordinates":[0.287315011,40.6338500977],"type":"Point"}
}