{
  "type": "Feature",
  "properties": {
    "iso:country":"ES",
    "sg:address":"Urb La Granja, 18",
    "sg:city":"El Palmar",
    "sg:orig_category":"Cervecer\u00cdas",
    "sg:phone":"+34 968 88 34 23",
    "sg:postcode":"30120",
    "sg:province":"Murcia",
    "wof:name":"Fernandez Zafra Maria",
    "wof:placetype":"venue"
},
  "geometry": {"coordinates":[-1.161689043,37.9263076782],"type":"Point"}
}