{
  "type": "Feature",
  "properties": {
    "iso:country":"ES",
    "sg:address":"Calle de Baiona, 38",
    "sg:city":"Vitoria-gasteiz",
    "sg:orig_category":"Asociaciones, Organismos Culturales Y Socioeducativos",
    "sg:phone":"+34 945 17 63 40",
    "sg:postcode":"01010",
    "sg:province":"\u00c1lava",
    "wof:name":"Asc. Cultural Conj. Mus. Orlas S.c",
    "wof:placetype":"venue"
},
  "geometry": {"coordinates":[-2.6935725212,42.8641242981],"type":"Point"}
}