{
  "type": "Feature",
  "properties": {
    "addr:full":"Camino Del Campo, 2 Sanchonu\u00d1o Segovia 40297",
    "addr:housenumber":"2",
    "addr:postcode":"40297",
    "addr:street":"Camino Del Campo;Segovia",
    "iso:country":"ES",
    "sg:address":"Camino Del Campo, 2",
    "sg:city":"Sanchonu\u00d1o",
    "sg:orig_category":"Cajas Para Embalar",
    "sg:phone":"+34 921 16 05 53",
    "sg:postcode":"40297",
    "sg:province":"Segovia",
    "sg:website":"www.cajarural.es",
    "wof:name":"Caja Rural De Segovia",
    "wof:placetype":"venue"
},
  "geometry": {"coordinates":[-4.3061652184,41.3190536499],"type":"Point"}
}