{
  "type": "Feature",
  "properties": {
    "iso:country":"ES",
    "sg:address":"Av Maresme (del), 33",
    "sg:city":"Mataro",
    "sg:orig_category":"Mec\u00c1nico Del Autom\u00d3vil",
    "sg:phone":"+34 937 99 12 54",
    "sg:postcode":"08302",
    "sg:province":"Barcelona",
    "wof:name":"Talleres Ronda 2 Exterior S. A.",
    "wof:placetype":"venue"
},
  "geometry": {"coordinates":[2.4370601177,41.5301361084],"type":"Point"}
}