{
  "type": "Feature",
  "properties": {
    "iso:country":"ES",
    "sg:address":"Carrer de Tomas De A.boada, 3",
    "sg:city":"Llagostera",
    "sg:orig_category":"Plomeros",
    "sg:phone":"+34 972 83 11 76",
    "sg:postcode":"17240",
    "sg:province":"Girona",
    "wof:name":"Rufi Comadira Jose",
    "wof:placetype":"venue"
},
  "geometry": {"coordinates":[2.9727549553,41.8591918945],"type":"Point"}
}