{
  "type": "Feature",
  "properties": {
    "iso:country":"ES",
    "sg:address":"Ctra Mendavia, Km. 0090,7",
    "sg:city":"Viana",
    "sg:orig_category":"Molinos",
    "sg:phone":"+34 948 64 51 21",
    "sg:postcode":"31230",
    "sg:province":"Navarra",
    "wof:name":"Talleres Clavijo S.l.",
    "wof:placetype":"venue"
},
  "geometry": {"coordinates":[-2.3724679947,42.5140380859],"type":"Point"}
}