{
  "type": "Feature",
  "properties": {
    "iso:country":"ES",
    "sg:address":"Carr Carril, 39",
    "sg:city":"Beniganim",
    "sg:orig_category":"Grifer\u00cda",
    "sg:phone":"+34 962 21 54 66",
    "sg:postcode":"46830",
    "sg:province":"Valencia",
    "wof:name":"Valflex Griferias S.l.",
    "wof:placetype":"venue"
},
  "geometry": {"coordinates":[-0.444671005,38.9410247803],"type":"Point"}
}