{
  "type": "Feature",
  "properties": {
    "iso:country":"ES",
    "sg:address":"San Jacinto, 16",
    "sg:city":"Mijas Costa",
    "sg:orig_category":"Mec\u00c1nico Del Autom\u00d3vil",
    "sg:phone":"+34 952 47 84 22",
    "sg:postcode":"29649",
    "sg:province":"M\u00e1laga",
    "wof:name":"Ortiz Lopez Antonio",
    "wof:placetype":"venue"
},
  "geometry": {"coordinates":[-4.6310629845,36.5238952637],"type":"Point"}
}