{
  "type": "Feature",
  "properties": {
    "iso:country":"ES",
    "sg:address":"Calle de Mar Chica, 57",
    "sg:city":"Melilla",
    "sg:orig_category":"Cervecer\u00cdas",
    "sg:phone":"+34 952 69 56 63",
    "sg:postcode":"52006",
    "sg:province":"Melilla",
    "wof:name":"Raga Mari Jose Maria",
    "wof:placetype":"venue"
},
  "geometry": {"coordinates":[-2.9455180168,35.2735366821],"type":"Point"}
}