{
  "type": "Feature",
  "properties": {
    "iso:country":"ES",
    "sg:address":"Calle de Beato Martin Martinez Pascual, S/n",
    "sg:city":"Valdealgorfa",
    "sg:orig_category":"Aceites Y Grasas Alimentarias (fabricaci\u00d3n, Al Por Mayor)",
    "sg:phone":"+34 978 85 70 08",
    "sg:postcode":"44594",
    "sg:province":"Teruel",
    "wof:name":"Blasco Burgues Maria Pilar",
    "wof:placetype":"venue"
},
  "geometry": {"coordinates":[-0.0346239991,40.9885292053],"type":"Point"}
}