{
  "type": "Feature",
  "properties": {
    "iso:country":"ES",
    "sg:address":"Calle de Imprenta De La Alborada, S/n",
    "sg:city":"Cordoba",
    "sg:orig_category":"Negocio De Materiales De Construcci\u00d3n",
    "sg:phone":"+34 957 32 65 82",
    "sg:postcode":"14014",
    "sg:province":"C\u00f3rdoba",
    "wof:name":"Suministros Trujillo C.b.",
    "wof:placetype":"venue"
},
  "geometry": {"coordinates":[-4.7258381844,37.8978843689],"type":"Point"}
}