{
  "type": "Feature",
  "properties": {
    "iso:country":"ES",
    "sg:address":"Carrer de Aleixar (cami De L'), 53",
    "sg:city":"Reus",
    "sg:orig_category":"Arquitectos",
    "sg:phone":"+34 977 31 80 76",
    "sg:postcode":"43202",
    "sg:province":"Tarragona",
    "wof:name":"Pardo Verges Antonio Maria",
    "wof:placetype":"venue"
},
  "geometry": {"coordinates":[1.1007989645,41.1573371887],"type":"Point"}
}