{
  "type": "Feature",
  "properties": {
    "iso:country":"ES",
    "sg:address":"Carr Joan Maragall, 6",
    "sg:city":"Figueres",
    "sg:orig_category":"Ropa Para Caballeros (al Por Menor)",
    "sg:phone":"+34 972 50 17 51",
    "sg:postcode":"17600",
    "sg:province":"Girona",
    "sg:website":"www.fajol.com",
    "wof:name":"Fajol-prats S.c.",
    "wof:placetype":"venue"
},
  "geometry": {"coordinates":[2.9616138935,42.2669830322],"type":"Point"}
}