{
  "type": "Feature",
  "properties": {
    "addr:full":"Calle de Paletillas, 1 Calahorra La Rioja 26500",
    "addr:housenumber":"1",
    "addr:postcode":"26500",
    "addr:street":"Calle De Paletillas",
    "iso:country":"ES",
    "sg:address":"Calle de Paletillas, 1",
    "sg:city":"Calahorra",
    "sg:orig_category":"Servicios De Higiene Y Peluquer\u00cda Para Perros Y Gatos",
    "sg:phone":"+34 941 14 71 77",
    "sg:postcode":"26500",
    "sg:province":"La Rioja",
    "wof:name":"Iba\u00f1ez Tejedor Mariano",
    "wof:placetype":"venue"
},
  "geometry": {"coordinates":[-1.9649070501,42.3039588928],"type":"Point"}
}