{
  "type": "Feature",
  "properties": {
    "addr:full":"Calle de Rogelio Nicolas Afonso Hernandez, 8 Mancha Santa Cruz De Tenerife 38430",
    "addr:housenumber":"8",
    "addr:postcode":"38430",
    "addr:street":"Calle De Rogelio Nicolas Afonso Hernandez",
    "iso:country":"ES",
    "sg:address":"Calle de Rogelio Nicolas Afonso Hernandez, 8",
    "sg:city":"Mancha",
    "sg:orig_category":"Frutas Y Legumbres Frescas (al Por Mayor)",
    "sg:phone":"+34 922 81 02 00",
    "sg:postcode":"38430",
    "sg:province":"Santa Cruz De Tenerife",
    "wof:name":"S.a.t. Agricola Icod Daute",
    "wof:placetype":"venue"
},
  "geometry": {"coordinates":[-16.7204761505,28.3677654266],"type":"Point"}
}