{
  "type": "Feature",
  "properties": {
    "addr:full":"Calle de Comarex, 1 Granada Granada 18007",
    "addr:housenumber":"1",
    "addr:postcode":"18007",
    "addr:street":"Calle De Comarex",
    "iso:country":"ES",
    "sg:address":"Calle de Comarex, 1",
    "sg:city":"Granada",
    "sg:orig_category":"Cl\u00cdnicas Dentales",
    "sg:phone":"+34 958 13 60 60",
    "sg:postcode":"18007",
    "sg:province":"Granada",
    "wof:name":"Lareo Visciarelli Celina",
    "wof:placetype":"venue"
},
  "geometry": {"coordinates":[-3.6009466648,37.1521377563],"type":"Point"}
}