{
  "type": "Feature",
  "properties": {
    "iso:country":"ES",
    "sg:address":"Ctra Collblanc, 33",
    "sg:city":"Hospitalet Llobregat",
    "sg:orig_category":"Ense\u00d1anza: Idiomas",
    "sg:phone":"+34 934 49 01 44",
    "sg:postcode":"08903",
    "sg:province":"Barcelona",
    "wof:name":"Perez Lopez Maria Del Rocio",
    "wof:placetype":"venue"
},
  "geometry": {"coordinates":[2.1199610233,41.375629425],"type":"Point"}
}