{
  "type": "Feature",
  "properties": {
    "addr:full":"Moll Adossat, S/n Barcelona Barcelona 08039",
    "addr:housenumber":"s",
    "addr:postcode":"08039",
    "addr:street":"/ N",
    "iso:country":"ES",
    "sg:address":"Moll Adossat, S/n",
    "sg:city":"Barcelona",
    "sg:orig_category":"Organizaciones Profesionales",
    "sg:phone":"+34 932 21 05 74",
    "sg:postcode":"08039",
    "sg:province":"Barcelona",
    "wof:name":"Agencia Maritima P & B S.a",
    "wof:placetype":"venue"
},
  "geometry": {"coordinates":[2.1573033333,41.3334465027],"type":"Point"}
}