{
  "type": "Feature",
  "properties": {
    "addr:full":"Calle de Fuente, 6 Escurial Sierra Salamanca 37762",
    "addr:housenumber":"6",
    "addr:postcode":"37762",
    "addr:street":"Calle De Fuente",
    "iso:country":"ES",
    "sg:address":"Calle de Fuente, 6",
    "sg:city":"Escurial Sierra",
    "sg:orig_category":"Apicultura",
    "sg:phone":"+34 923 44 20 34",
    "sg:postcode":"37762",
    "sg:province":"Salamanca",
    "wof:name":"Benito Garcia Benito",
    "wof:placetype":"venue"
},
  "geometry": {"coordinates":[-5.8640742302,40.6302833557],"type":"Point"}
}