{
  "type": "Feature",
  "properties": {
    "addr:full":"Luga Carretera De Granada, S/n Guadix Granada 18500",
    "addr:postcode":"18500",
    "addr:street":"Carretera De Granada S / N",
    "iso:country":"ES",
    "sg:address":"Luga Carretera De Granada, S/n",
    "sg:city":"Guadix",
    "sg:orig_category":"Pirotecnia (espect\u00c1culos)",
    "sg:phone":"+34 958 66 15 03",
    "sg:postcode":"18500",
    "sg:province":"Granada",
    "wof:name":"Perez Aranda Maria Angustias",
    "wof:placetype":"venue"
},
  "geometry": {"coordinates":[-3.1343688965,37.303894043],"type":"Point"}
}