{
  "type": "Feature",
  "properties": {
    "iso:country":"ES",
    "sg:address":"Carrer de Holanda, 54",
    "sg:city":"Hospitalet Llobregat",
    "sg:orig_category":"Animales (al Por Menor)",
    "sg:phone":"+34 934 31 26 29",
    "sg:postcode":"08903",
    "sg:province":"Barcelona",
    "wof:name":"Freixenet Homs Pedro",
    "wof:placetype":"venue"
},
  "geometry": {"coordinates":[2.125287056,41.3695297241],"type":"Point"}
}