{
  "type": "Feature",
  "properties": {
    "iso:country":"ES",
    "sg:address":"Calle de Justicia, Del, 1",
    "sg:city":"Valencia",
    "sg:orig_category":"Propiedad Industrial: Patentes De Inventos, Marcas, Modelos, Dise\u00d1os",
    "sg:phone":"+34 963 94 30 01",
    "sg:postcode":"46003",
    "sg:province":"Valencia",
    "wof:name":"Alzaga Aliena Enrique De",
    "wof:placetype":"venue"
},
  "geometry": {"coordinates":[-0.3695678115,39.4721107483],"type":"Point"}
}