{
  "type": "Feature",
  "properties": {
    "addr:full":"Nuevo Relleno, S/n Cee A Coru\u00f1a 15270",
    "addr:housenumber":"s / n",
    "addr:postcode":"15270",
    "iso:country":"ES",
    "sg:address":"Nuevo Relleno, S/n",
    "sg:city":"Cee",
    "sg:orig_category":"Florister\u00cdas",
    "sg:phone":"+34 981 74 52 64",
    "sg:postcode":"15270",
    "sg:province":"A Coru\u00f1a",
    "wof:name":"Toba Suarez Raquel",
    "wof:placetype":"venue"
},
  "geometry": {"coordinates":[-9.187494278,42.9554710388],"type":"Point"}
}