{
  "type": "Feature",
  "properties": {
    "addr:full":"Ctra. Merida, Km. 0017,0 Guare\u00f1a Badajoz 06470",
    "addr:postcode":"06470",
    "addr:street":"Ctra. Merida Km. 0017,0",
    "iso:country":"ES",
    "sg:address":"Ctra. Merida, Km. 0017,0",
    "sg:city":"Guare\u00f1a",
    "sg:orig_category":"Producci\u00d3n, Venta De Productos De Agricultura Biol\u00d3gica",
    "sg:phone":"+34 924 12 00 19",
    "sg:postcode":"06470",
    "sg:province":"Badajoz",
    "wof:name":"Agropecuaria La Malva S.l.",
    "wof:placetype":"venue"
},
  "geometry": {"coordinates":[-6.1084566116,38.8518066406],"type":"Point"}
}