{
  "type": "Feature",
  "properties": {
    "addr:full":"Calle de Valencia, 29 Getafe Madrid 28903",
    "addr:housenumber":"29",
    "addr:postcode":"28903",
    "addr:street":"Calle De Valencia",
    "iso:country":"ES",
    "sg:address":"Calle de Valencia, 29",
    "sg:city":"Getafe",
    "sg:orig_category":"Restaurantes",
    "sg:phone":"+34 916 95 06 95",
    "sg:postcode":"28903",
    "sg:province":"Madrid",
    "wof:name":"Pascual Garcia Angel",
    "wof:placetype":"venue"
},
  "geometry": {"coordinates":[-3.7211270332,40.3119010925],"type":"Point"}
}