{
  "type": "Feature",
  "properties": {
    "iso:country":"ES",
    "sg:address":"Avda Portugal (de), 114",
    "sg:city":"Verin",
    "sg:orig_category":"Bares, Piano",
    "sg:phone":"+34 988 41 30 79",
    "sg:postcode":"32600",
    "sg:province":"Ourense",
    "wof:name":"Dobarrio Dominguez Isaac",
    "wof:placetype":"venue"
},
  "geometry": {"coordinates":[-7.4404392242,41.9313583374],"type":"Point"}
}