{
  "type": "Feature",
  "properties": {
    "addr:full":"Carrer de Sant Pere Mes Alt, 43 Barcelona Barcelona 08003",
    "addr:housenumber":"43",
    "addr:postcode":"08003",
    "addr:street":"Carrer De Sant",
    "iso:country":"ES",
    "sg:address":"Carrer de Sant Pere Mes Alt, 43",
    "sg:city":"Barcelona",
    "sg:orig_category":"Pintores",
    "sg:phone":"+34 932 68 49 45",
    "sg:postcode":"08003",
    "sg:province":"Barcelona",
    "wof:name":"Llimos Oriol Roberto",
    "wof:placetype":"venue"
},
  "geometry": {"coordinates":[2.1768910885,41.3887786865],"type":"Point"}
}