{
  "type": "Feature",
  "properties": {
    "addr:full":"Carrer de Sant Vicent, 25 Campello Alicante 03560",
    "addr:housenumber":"25",
    "addr:postcode":"03560",
    "addr:street":"Carrer De Sant Vicent",
    "iso:country":"ES",
    "sg:address":"Carrer de Sant Vicent, 25",
    "sg:city":"Campello",
    "sg:orig_category":"Caf\u00c9s, Bares, Cervecer\u00cdas",
    "sg:phone":"+34 965 63 15 27",
    "sg:postcode":"03560",
    "sg:province":"Alicante",
    "wof:name":"El Passatge De El Campello S.l.",
    "wof:placetype":"venue"
},
  "geometry": {"coordinates":[-0.3885270059,38.4291954041],"type":"Point"}
}