{
  "type": "Feature",
  "properties": {
    "addr:full":"San Lorenzo, 7 Iru\u00f1a Navarra 31001",
    "addr:housenumber":"7",
    "addr:postcode":"31001",
    "addr:street":"San Lorenzo",
    "iso:country":"ES",
    "sg:address":"San Lorenzo, 7",
    "sg:city":"Iru\u00f1a",
    "sg:orig_category":"Alimentaci\u00d3n General (al Por Menor)",
    "sg:phone":"+34 948 22 52 15",
    "sg:postcode":"31001",
    "sg:province":"Navarra",
    "wof:name":"Urtasun Erdocia Ana Maria",
    "wof:placetype":"venue"
},
  "geometry": {"coordinates":[-1.6489759684,42.8173561096],"type":"Point"}
}