{
  "type": "Feature",
  "properties": {
    "iso:country":"ES",
    "sg:address":"Calle de Zapateria, 12",
    "sg:city":"Tarancon",
    "sg:orig_category":"Agencias De Viajes",
    "sg:phone":"+34 969 32 13 49",
    "sg:postcode":"16400",
    "sg:province":"Cuenca",
    "wof:name":"Viajes Anaycas.l.",
    "wof:placetype":"venue"
},
  "geometry": {"coordinates":[-3.0043969154,40.0113258362],"type":"Point"}
}