{
  "type": "Feature",
  "properties": {
    "addr:full":"Mercabarna (zona Franca), S/n Barcelona Barcelona 08040",
    "addr:housenumber":"s",
    "addr:postcode":"08040",
    "addr:street":"Zona Franca;/ N",
    "iso:country":"ES",
    "sg:address":"Mercabarna (zona Franca), S/n",
    "sg:city":"Barcelona",
    "sg:orig_category":"Frutas Y Legumbres Frescas (al Por Mayor)",
    "sg:phone":"+34 932 62 20 60",
    "sg:postcode":"08040",
    "sg:province":"Barcelona",
    "wof:name":"Morales E Hijos S. A.",
    "wof:placetype":"venue"
},
  "geometry": {"coordinates":[2.1687450409,41.3855895996],"type":"Point"}
}