{
  "type": "Feature",
  "properties": {
    "addr:full":"Calle de Tenor Fleta, 19 Cadrete Zaragoza 50420",
    "addr:housenumber":"19",
    "addr:postcode":"50420",
    "addr:street":"Calle De Tenor Fleta",
    "iso:country":"ES",
    "sg:address":"Calle de Tenor Fleta, 19",
    "sg:city":"Cadrete",
    "sg:orig_category":"Cajas De Ahorro",
    "sg:phone":"+34 976 12 52 51",
    "sg:postcode":"50420",
    "sg:province":"Zaragoza",
    "sg:website":"www.ibercaja.es",
    "wof:name":"Caja De Ahorros Y Monte De Piedad De Zaragoza Aragon Y Rioja",
    "wof:placetype":"venue"
},
  "geometry": {"coordinates":[-0.9603329897,41.5555534363],"type":"Point"}
}