{
  "type": "Feature",
  "properties": {
    "addr:full":"Calle de D(campollano), S/n Albacete Albacete 02006",
    "addr:housenumber":"s / n",
    "addr:postcode":"02006",
    "addr:street":"Calle De D Campollano",
    "iso:country":"ES",
    "sg:address":"Calle de D(campollano), S/n",
    "sg:city":"Albacete",
    "sg:orig_category":"Fabricaci\u00d3n De Moldes Y Modelos",
    "sg:phone":"+34 967 21 40 45",
    "sg:postcode":"02006",
    "sg:province":"Albacete",
    "wof:name":"Molina Perona Jose",
    "wof:placetype":"venue"
},
  "geometry": {"coordinates":[-1.9490209818,39.013168335],"type":"Point"}
}