{
  "type": "Feature",
  "properties": {
    "addr:full":"Carrer de Balmes, 289 Barcelona Barcelona 08006",
    "addr:housenumber":"289",
    "addr:postcode":"08006",
    "addr:street":"Carrer De Balmes",
    "iso:country":"ES",
    "sg:address":"Carrer de Balmes, 289",
    "sg:city":"Barcelona",
    "sg:orig_category":"Material Y Suministros Para Peluquer\u00cda",
    "sg:phone":"+34 932 00 61 64",
    "sg:postcode":"08006",
    "sg:province":"Barcelona",
    "sg:website":"www.cebado.es",
    "wof:name":"Entorn K-3 S.l.",
    "wof:placetype":"venue"
},
  "geometry": {"coordinates":[2.1468811035,41.4014472961],"type":"Point"}
}