{
  "type": "Feature",
  "properties": {
    "iso:country":"ES",
    "sg:address":"Carrer de Maria Aguilo, 125",
    "sg:city":"Barcelona",
    "sg:orig_category":"Farmacias",
    "sg:phone":"+34 932 25 34 73",
    "sg:postcode":"08005",
    "sg:province":"Barcelona",
    "wof:name":"Almirall Cacho Victor Manuel",
    "wof:placetype":"venue"
},
  "geometry": {"coordinates":[2.2051053047,41.4000244141],"type":"Point"}
}