{
  "type": "Feature",
  "properties": {
    "addr:full":"Carr Arraval, 15 Mao Islas Baleares 07701",
    "addr:housenumber":"15",
    "addr:postcode":"07701",
    "addr:street":"Carr Arraval",
    "iso:country":"ES",
    "sg:address":"Carr Arraval, 15",
    "sg:city":"Mao",
    "sg:orig_category":"Institutos De Belleza",
    "sg:phone":"+34 971 36 53 97",
    "sg:postcode":"07701",
    "sg:province":"Islas Baleares",
    "wof:name":"Montero Adrian Luis",
    "wof:placetype":"venue"
},
  "geometry": {"coordinates":[4.265250206,39.888420105],"type":"Point"}
}