{
  "type": "Feature",
  "properties": {
    "addr:full":"Pg Sunyer, 25 Reus Tarragona 43202",
    "addr:housenumber":"25",
    "addr:postcode":"43202",
    "addr:street":"Pg Sunyer",
    "iso:country":"ES",
    "sg:address":"Pg Sunyer, 25",
    "sg:city":"Reus",
    "sg:orig_category":"Cl\u00cdnicas Dentales",
    "sg:phone":"+34 977 31 88 62",
    "sg:postcode":"43202",
    "sg:province":"Tarragona",
    "wof:name":"Ruiz Manrique Juan Jose",
    "wof:placetype":"venue"
},
  "geometry": {"coordinates":[1.1010890007,41.1575164795],"type":"Point"}
}