{
  "type": "Feature",
  "properties": {
    "iso:country":"ES",
    "sg:address":"Calle de Doctor Civera, 6",
    "sg:city":"Jaen",
    "sg:orig_category":"Papel Pintado (al Por Menor)",
    "sg:phone":"+34 953 23 79 71",
    "sg:postcode":"23003",
    "sg:province":"Ja\u00e9n",
    "wof:name":"Lopez Barroso Jose Luis",
    "wof:placetype":"venue"
},
  "geometry": {"coordinates":[-3.7901639938,37.7675476074],"type":"Point"}
}