{
  "type": "Feature",
  "properties": {
    "addr:full":"Sbid Costa, 2 Vigo Pontevedra 36213",
    "addr:housenumber":"2",
    "addr:postcode":"36213",
    "addr:street":"Costa",
    "iso:country":"ES",
    "sg:address":"Sbid Costa, 2",
    "sg:city":"Vigo",
    "sg:orig_category":"Inmobiliaria (agencias)",
    "sg:phone":"+34 986 23 26 48",
    "sg:postcode":"36213",
    "sg:province":"Pontevedra",
    "wof:name":"Garcia-paz Pereira Maria De Los Angeles",
    "wof:placetype":"venue"
},
  "geometry": {"coordinates":[-8.7224931717,42.2141952515],"type":"Point"}
}