{
  "type": "Feature",
  "properties": {
    "addr:full":"Avda Mahia, 50 Bertamirans La Coru\u00f1a 15220",
    "addr:housenumber":"50",
    "addr:postcode":"15220",
    "addr:street":"Avda Mahia;La Corun\u0303A",
    "iso:country":"ES",
    "sg:address":"Avda Mahia, 50",
    "sg:city":"Bertamirans",
    "sg:orig_category":"Productos Qu\u00cdmicos (fabricaci\u00d3n, Al Por Mayor)",
    "sg:phone":"+34 981 89 13 02",
    "sg:postcode":"15220",
    "sg:province":"La Coru\u00f1a",
    "wof:name":"Freire Sambade Concepcion",
    "wof:placetype":"venue"
},
  "geometry": {"coordinates":[-8.6537876129,42.8589744568],"type":"Point"}
}