{
  "type": "Feature",
  "properties": {
    "iso:country":"ES",
    "sg:address":"Avda Europa (de), S/n",
    "sg:city":"San Cristobal",
    "sg:orig_category":"Quincaller\u00cda (al Por Menor)",
    "sg:phone":"+34 968 44 48 43",
    "sg:postcode":"30800",
    "sg:province":"Murcia",
    "wof:name":"Puertas Lorca S.l.",
    "wof:placetype":"venue"
},
  "geometry": {"coordinates":[-1.6905640364,37.680557251],"type":"Point"}
}