{
  "type": "Feature",
  "properties": {
    "addr:full":"Calle de Velarde, 4 Segovia Segovia 40003",
    "addr:housenumber":"4",
    "addr:postcode":"40003",
    "addr:street":"Calle De Velarde",
    "iso:country":"ES",
    "sg:address":"Calle de Velarde, 4",
    "sg:city":"Segovia",
    "sg:orig_category":"Artesanado",
    "sg:phone":"+34 921 46 08 36",
    "sg:postcode":"40003",
    "sg:province":"Segovia",
    "wof:name":"Silveira Rivas Jose Luis",
    "wof:placetype":"venue"
},
  "geometry": {"coordinates":[-4.1267709732,40.9517364502],"type":"Point"}
}