{
  "type": "Feature",
  "properties": {
    "addr:full":"Calle de Tamarindo (del), 2 Parque Coimbra Madrid 28935",
    "addr:postcode":"28935",
    "addr:street":"Calle De Tamarindo Del;Parque",
    "iso:country":"ES",
    "sg:address":"Calle de Tamarindo (del), 2",
    "sg:city":"Parque Coimbra",
    "sg:classifiers":[
        {
            "category":"Taxi",
            "type":"Transportation"
        }
    ],
    "sg:phone":"+34 916 47 05 54",
    "sg:postcode":"28935",
    "sg:province":"Madrid",
    "wof:name":"Martinez Garcia Vicente",
    "wof:placetype":"venue"
},
  "geometry": {"coordinates":[-3.9229900837,40.3092765808],"type":"Point"}
}