{
  "type": "Feature",
  "properties": {
    "iso:country":"ES",
    "sg:address":"Afueras, Km. 0012,5",
    "sg:city":"Castejon Valdejasa",
    "sg:orig_category":"Cr\u00cda De Cerdos",
    "sg:phone":"+34 976 69 70 63",
    "sg:postcode":"50613",
    "sg:province":"Zaragoza",
    "wof:name":"Pork Las Bardenas S.l.",
    "wof:placetype":"venue"
},
  "geometry": {"coordinates":[-0.9991769791,41.9803924561],"type":"Point"}
}