{
  "type": "Feature",
  "properties": {
    "iso:country":"ES",
    "sg:address":"Carr Lleida, 7",
    "sg:city":"Alcoletge",
    "sg:orig_category":"Carnicer\u00cdas, Carnicer\u00cdas",
    "sg:phone":"+34 973 19 70 13",
    "sg:postcode":"25660",
    "sg:province":"Lleida",
    "wof:name":"Re\u00f1e Cabestany Maria Teresa",
    "wof:placetype":"venue"
},
  "geometry": {"coordinates":[0.6937180161,41.6471672058],"type":"Point"}
}