{
  "type": "Feature",
  "properties": {
    "iso:country":"ES",
    "sg:address":"Calle de Montemayor De Pililla, 2",
    "sg:city":"Madrid",
    "sg:orig_category":"Electricidad: Instaladores",
    "sg:phone":"+34 913 88 14 09",
    "sg:postcode":"28043",
    "sg:province":"Madrid",
    "wof:name":"Iberolux S.l.",
    "wof:placetype":"venue"
},
  "geometry": {"coordinates":[-3.651266098,40.4607543945],"type":"Point"}
}