{
  "type": "Feature",
  "properties": {
    "addr:full":"Miravalles, 5 Iru\u00f1a Navarra 31015",
    "addr:housenumber":"5",
    "addr:postcode":"31015",
    "addr:street":"Miravalles",
    "iso:country":"ES",
    "sg:address":"Miravalles, 5",
    "sg:city":"Iru\u00f1a",
    "sg:orig_category":"Vinos Y Licores (venta Al Por Menor)",
    "sg:phone":"+34 948 14 07 81",
    "sg:postcode":"31015",
    "sg:province":"Navarra",
    "wof:name":"Egea Barberena Francisco",
    "wof:placetype":"venue"
},
  "geometry": {"coordinates":[-1.6259169579,42.8300247192],"type":"Point"}
}