{
  "type": "Feature",
  "properties": {
    "addr:full":"Avda Costa, 110 Gijon Asturias 33204",
    "addr:housenumber":"110",
    "addr:postcode":"33204",
    "addr:street":"Avda Costa",
    "iso:country":"ES",
    "sg:address":"Avda Costa, 110",
    "sg:city":"Gijon",
    "sg:orig_category":"Promotores Constructores",
    "sg:phone":"+34 985 37 17 60",
    "sg:postcode":"33204",
    "sg:province":"Asturias",
    "wof:name":"Inmobiliaria Arguero S.a.",
    "wof:placetype":"venue"
},
  "geometry": {"coordinates":[-5.6519789696,43.5373382568],"type":"Point"}
}