{
  "type": "Feature",
  "properties": {
    "iso:country":"ES",
    "sg:address":"Pase Verdiales (de Los), 4",
    "sg:city":"Cordoba",
    "sg:orig_category":"Carnicer\u00cdas, Carnicer\u00cdas",
    "sg:phone":"+34 957 46 01 04",
    "sg:postcode":"14005",
    "sg:province":"C\u00f3rdoba",
    "wof:name":"Guerra Rojas Ana Maria",
    "wof:placetype":"venue"
},
  "geometry": {"coordinates":[-4.8831849098,37.866859436],"type":"Point"}
}