{
  "type": "Feature",
  "properties": {
    "iso:country":"ES",
    "sg:address":"Calle de Doctor Esquerdo, 169",
    "sg:city":"Madrid",
    "sg:orig_category":"Inmobiliaria (agencias)",
    "sg:phone":"+34 914 09 36 77",
    "sg:postcode":"28007",
    "sg:province":"Madrid",
    "wof:name":"Aderezos Camporeal S.l.",
    "wof:placetype":"venue"
},
  "geometry": {"coordinates":[-3.6700344086,40.4075508118],"type":"Point"}
}