{
  "type": "Feature",
  "properties": {
    "iso:country":"ES",
    "sg:address":"Pagamu\u00d1o Auzoa, 15",
    "sg:city":"Elbarrena",
    "sg:orig_category":"Promotores Constructores",
    "sg:phone":"+34 943 69 17 15",
    "sg:postcode":"20159",
    "sg:province":"Guip\u00f9zcoa",
    "wof:name":"Imaz Echave Modesto",
    "wof:placetype":"venue"
},
  "geometry": {"coordinates":[-2.0742990971,43.1991958618],"type":"Point"}
}