{
  "type": "Feature",
  "properties": {
    "addr:full":"Calle de Santa Susana, 6 Madrid Madrid 28033",
    "addr:housenumber":"6",
    "addr:postcode":"28033",
    "addr:street":"Calle De Santa Susana",
    "iso:country":"ES",
    "sg:address":"Calle de Santa Susana, 6",
    "sg:city":"Madrid",
    "sg:orig_category":"Ingeniero",
    "sg:phone":"+34 917 64 31 78",
    "sg:postcode":"28033",
    "sg:province":"Madrid",
    "wof:name":"Moises Domingo Acebes",
    "wof:placetype":"venue"
},
  "geometry": {"coordinates":[-3.6460850239,40.4767570496],"type":"Point"}
}