{
  "type": "Feature",
  "properties": {
    "addr:full":"Calle de Polar, 1 Jerez De La Frontera C\u00e1diz 11407",
    "addr:housenumber":"1",
    "addr:postcode":"11407",
    "addr:street":"Calle De Polar",
    "iso:country":"ES",
    "sg:address":"Calle de Polar, 1",
    "sg:city":"Jerez De La Frontera",
    "sg:orig_category":"Electricidad: Equipos Industriales, Componentes (fabricaci\u00d3n)",
    "sg:phone":"+34 956 31 77 68",
    "sg:postcode":"11407",
    "sg:province":"C\u00e1diz",
    "sg:website":"www.schneiderelectric.es",
    "wof:name":"Schneider Electric S.a.",
    "wof:placetype":"venue"
},
  "geometry": {"coordinates":[-6.0982751846,36.7228431702],"type":"Point"}
}