{
  "type": "Feature",
  "properties": {
    "addr:full":"S. Rusinyol, S/n Polinya Barcelona 08213",
    "addr:housenumber":"s",
    "addr:postcode":"08213",
    "addr:street":"/ N Polinya",
    "iso:country":"ES",
    "sg:address":"S. Rusinyol, S/n",
    "sg:city":"Polinya",
    "sg:orig_category":"Galvanizaci\u00d3n, Esta\u00d1ado, Emplomado",
    "sg:phone":"+34 937 13 58 30",
    "sg:postcode":"08213",
    "sg:province":"Barcelona",
    "wof:name":"Comega S. A.",
    "wof:placetype":"venue"
},
  "geometry": {"coordinates":[2.1559200287,41.542301178],"type":"Point"}
}