{
  "type": "Feature",
  "properties": {
    "addr:full":"Calle de Antonio Garcia Corona, 2 Sevilla Sevilla 41010",
    "addr:housenumber":"2",
    "addr:postcode":"41010",
    "addr:street":"Calle De Antonio Garcia Corona",
    "iso:country":"ES",
    "sg:address":"Calle de Antonio Garcia Corona, 2",
    "sg:city":"Sevilla",
    "sg:orig_category":"Promotores Constructores",
    "sg:phone":"+34 954 34 72 82",
    "sg:postcode":"41010",
    "sg:province":"Sevilla",
    "wof:name":"Seriobras Servicios Y Obras S.l.",
    "wof:placetype":"venue"
},
  "geometry": {"coordinates":[-6.0065088272,37.3836135864],"type":"Point"}
}