{
  "type": "Feature",
  "properties": {
    "addr:full":"Centro Comercial Larios Center, S/n Malaga M\u00e1laga 29002",
    "addr:housenumber":"s / n",
    "addr:postcode":"29002",
    "addr:street":"Ma\u0301Laga",
    "iso:country":"ES",
    "sg:address":"Centro Comercial Larios Center, S/n",
    "sg:city":"Malaga",
    "sg:orig_category":"Ropa Para Se\u00d1oras (al Por Menor)",
    "sg:phone":"+34 952 36 90 71",
    "sg:postcode":"29002",
    "sg:province":"M\u00e1laga",
    "sg:website":"www.pullbear.com",
    "wof:name":"Pull & Bear Espa\u00f1a S.a.",
    "wof:placetype":"venue"
},
  "geometry": {"coordinates":[-4.4201588631,36.7183189392],"type":"Point"}
}