{
  "type": "Feature",
  "properties": {
    "addr:full":"Avda Cuenca, S/n Benidorm Alicante 03500",
    "addr:housenumber":"s / n",
    "addr:postcode":"03500",
    "addr:street":"Avda Cuenca",
    "iso:country":"ES",
    "sg:address":"Avda Cuenca, S/n",
    "sg:city":"Benidorm",
    "sg:orig_category":"Ropa Y Accesorios",
    "sg:phone":"+34 966 80 77 04",
    "sg:postcode":"03500",
    "sg:province":"Alicante",
    "wof:name":"Sierra Garcia Jose Luis",
    "wof:placetype":"venue"
},
  "geometry": {"coordinates":[-0.1173790023,38.5380897522],"type":"Point"}
}