{
  "type": "Feature",
  "properties": {
    "addr:full":"Errebote Plaza, 2 Orexa Guip\u00f9zcoa 20490",
    "addr:housenumber":"2",
    "addr:postcode":"20490",
    "addr:street":"Errebote Plaza;Guipu\u0300Zcoa",
    "iso:country":"ES",
    "sg:address":"Errebote Plaza, 2",
    "sg:city":"Orexa",
    "sg:orig_category":"Cooperativas Agr\u00cdcolas",
    "sg:phone":"+34 943 68 22 14",
    "sg:postcode":"20490",
    "sg:province":"Guip\u00f9zcoa",
    "wof:name":"Oihan Txiki Cop.",
    "wof:placetype":"venue"
},
  "geometry": {"coordinates":[-2.0117249489,43.0941429138],"type":"Point"}
}