{
  "type": "Feature",
  "properties": {
    "iso:country":"ES",
    "sg:address":"Calle de Bebricio, 28",
    "sg:city":"Calahorra",
    "sg:orig_category":"Complementos De Vestir (al Por Menor)",
    "sg:phone":"+34 941 14 66 60",
    "sg:postcode":"26500",
    "sg:province":"La Rioja",
    "wof:name":"Guerrero Pascual Cristina",
    "wof:placetype":"venue"
},
  "geometry": {"coordinates":[-1.9660203457,42.3040733337],"type":"Point"}
}