{
  "type": "Feature",
  "properties": {
    "iso:country":"ES",
    "sg:address":"Calle de Boggiero, 150",
    "sg:city":"Zaragoza",
    "sg:orig_category":"Transporte En General",
    "sg:phone":"+34 976 43 28 67",
    "sg:postcode":"50003",
    "sg:province":"Zaragoza",
    "wof:name":"Gracia Pe\u00f1afiel Sergio",
    "wof:placetype":"venue"
},
  "geometry": {"coordinates":[-0.8906652927,41.6562576294],"type":"Point"}
}