{
  "type": "Feature",
  "properties": {
    "addr:full":"Calle de Castello, 101 Madrid Madrid 28006",
    "addr:housenumber":"101",
    "addr:postcode":"28006",
    "addr:street":"Calle De Castello",
    "iso:country":"ES",
    "sg:address":"Calle de Castello, 101",
    "sg:city":"Madrid",
    "sg:orig_category":"Marroquiner\u00cda (confecci\u00d3n)",
    "sg:phone":"+34 915 63 67 83",
    "sg:postcode":"28006",
    "sg:province":"Madrid",
    "wof:name":"Velez Escalada Emilio",
    "wof:placetype":"venue"
},
  "geometry": {"coordinates":[-3.6809248924,40.4342918396],"type":"Point"}
}