{
  "type": "Feature",
  "properties": {
    "addr:full":"Calle de Postas, 8 Aranda Duero Burgos 09400",
    "addr:housenumber":"8",
    "addr:postcode":"09400",
    "addr:street":"Calle De Postas",
    "iso:country":"ES",
    "sg:address":"Calle de Postas, 8",
    "sg:city":"Aranda Duero",
    "sg:orig_category":"Cl\u00cdnicas Dentales",
    "sg:phone":"+34 947 51 18 08",
    "sg:postcode":"09400",
    "sg:province":"Burgos",
    "wof:name":"Clinica Dental Dr. Ordo\u00d1ez Sl",
    "wof:placetype":"venue"
},
  "geometry": {"coordinates":[-3.6875369549,41.6697006226],"type":"Point"}
}