{
  "type": "Feature",
  "properties": {
    "iso:country":"ES",
    "sg:address":"Avda Europa, 8",
    "sg:city":"Badajoz",
    "sg:orig_category":"M\u00c9dicos: Cardiolog\u00cda Y Afecciones Cardiovasculares",
    "sg:phone":"+34 924 25 95 51",
    "sg:postcode":"06004",
    "sg:province":"Badajoz",
    "wof:name":"Alvarez Suarez-barcena Jose Maria",
    "wof:placetype":"venue"
},
  "geometry": {"coordinates":[-6.9728059769,38.8741531372],"type":"Point"}
}