{
  "type": "Feature",
  "properties": {
    "addr:full":"Plaz Constitucion, S/n Ciudad Real Ciudad Real 13003",
    "addr:postcode":"13003",
    "addr:street":"Constitucion S / N",
    "iso:country":"ES",
    "sg:address":"Plaz Constitucion, S/n",
    "sg:city":"Ciudad Real",
    "sg:orig_category":"Agencias De Viajes",
    "sg:phone":"+34 926 27 45 66",
    "sg:postcode":"13003",
    "sg:province":"Ciudad Real",
    "sg:website":"www.halconviajes.com",
    "wof:name":"Viajes Halcon S.a.",
    "wof:placetype":"venue"
},
  "geometry": {"coordinates":[-3.9279088974,38.9883232117],"type":"Point"}
}