{
  "type": "Feature",
  "properties": {
    "iso:country":"ES",
    "sg:address":"Calle de Cristobal Colon, 19",
    "sg:city":"Algeciras",
    "sg:orig_category":"Ropa Para Beb\u00c9s Y Ni\u00d1os (confecci\u00d3n, Al Por Mayor)",
    "sg:phone":"+34 956 65 44 06",
    "sg:postcode":"11201",
    "sg:province":"C\u00e1diz",
    "wof:name":"Guerrero Moreno Irene",
    "wof:placetype":"venue"
},
  "geometry": {"coordinates":[-5.446949482,36.1291236877],"type":"Point"}
}