{
  "type": "Feature",
  "properties": {
    "addr:full":"Calle de Tejuela, 21 Alcala Real Ja\u00e9n 23680",
    "addr:housenumber":"21",
    "addr:postcode":"23680",
    "addr:street":"Calle De Tejuela;Jae\u0301N",
    "iso:country":"ES",
    "sg:address":"Calle de Tejuela, 21",
    "sg:city":"Alcala Real",
    "sg:orig_category":"Cristaler\u00cdas",
    "sg:phone":"+34 953 58 38 04",
    "sg:postcode":"23680",
    "sg:province":"Ja\u00e9n",
    "wof:name":"Harmaglas S.l.",
    "wof:placetype":"venue"
},
  "geometry": {"coordinates":[-3.925358057,37.4665031433],"type":"Point"}
}