{
  "type": "Feature",
  "properties": {
    "addr:full":"Avda Alcalde De Lavadores, 32 Bagunda Pontevedra 36214",
    "addr:housenumber":"32",
    "addr:postcode":"36214",
    "addr:street":"Avda Alcalde De Lavadores",
    "iso:country":"ES",
    "sg:address":"Avda Alcalde De Lavadores, 32",
    "sg:city":"Bagunda",
    "sg:orig_category":"Distribuci\u00d3n De Petr\u00d3leo Y Derivados",
    "sg:phone":"+34 986 26 50 11",
    "sg:postcode":"36214",
    "sg:province":"Pontevedra",
    "wof:name":"Galpgest Petrogal Estaciones De Servicio S.l.u.",
    "wof:placetype":"venue"
},
  "geometry": {"coordinates":[-8.7059106827,42.2124443054],"type":"Point"}
}