{
  "type": "Feature",
  "properties": {
    "addr:full":"Calle de Guadalete, 1 Viso Del Alcor Sevilla 41520",
    "addr:housenumber":"1",
    "addr:postcode":"41520",
    "addr:street":"Calle De Guadalete",
    "iso:country":"ES",
    "sg:address":"Calle de Guadalete, 1",
    "sg:city":"Viso Del Alcor",
    "sg:orig_category":"Chapister\u00cda",
    "sg:phone":"+34 955 74 21 03",
    "sg:postcode":"41520",
    "sg:province":"Sevilla",
    "wof:name":"Talleres Lito S.l.",
    "wof:placetype":"venue"
},
  "geometry": {"coordinates":[-5.7224740982,37.3872108459],"type":"Point"}
}