{
  "type": "Feature",
  "properties": {
    "iso:country":"ES",
    "sg:address":"Pol. San Sebastian, S/n",
    "sg:city":"Arganda",
    "sg:orig_category":"Empresas De Carpinter\u00cda De Madera",
    "sg:phone":"+34 918 71 48 91",
    "sg:postcode":"28500",
    "sg:province":"Madrid",
    "wof:name":"Garrido Rodriguez Julio",
    "wof:placetype":"venue"
},
  "geometry": {"coordinates":[-3.4498345852,40.2882194519],"type":"Point"}
}