{
  "type": "Feature",
  "properties": {
    "iso:country":"ES",
    "sg:address":"Carr Colon, 7",
    "sg:city":"Betera",
    "sg:orig_category":"Peluqueros: De Se\u00d1oras",
    "sg:phone":"+34 961 60 04 32",
    "sg:postcode":"46117",
    "sg:province":"Valencia",
    "wof:name":"Campos Fuster Maria Teresa",
    "wof:placetype":"venue"
},
  "geometry": {"coordinates":[-0.4594759941,39.5912857056],"type":"Point"}
}