{
  "type": "Feature",
  "properties": {
    "iso:country":"ES",
    "sg:address":"Cami Geganta (de La), 107",
    "sg:city":"Mataro",
    "sg:orig_category":"Doctores En Medicina",
    "sg:phone":"+34 937 98 74 65",
    "sg:postcode":"08302",
    "sg:province":"Barcelona",
    "wof:name":"Rivas Espejo Antonio",
    "wof:placetype":"venue"
},
  "geometry": {"coordinates":[2.4366979599,41.5411491394],"type":"Point"}
}