{
  "type": "Feature",
  "properties": {
    "addr:full":"Pg Colom, 13 Barcelona Barcelona 08002",
    "addr:housenumber":"13",
    "addr:postcode":"08002",
    "addr:street":"Pg Colom",
    "iso:country":"ES",
    "sg:address":"Pg Colom, 13",
    "sg:city":"Barcelona",
    "sg:orig_category":"Mec\u00c1nico Del Autom\u00d3vil",
    "sg:phone":"+34 933 10 26 55",
    "sg:postcode":"08002",
    "sg:province":"Barcelona",
    "wof:name":"Catalonia & Junior S.l.",
    "wof:placetype":"venue"
},
  "geometry": {"coordinates":[2.1806149483,41.379737854],"type":"Point"}
}