{
  "type": "Feature",
  "properties": {
    "iso:country":"ES",
    "sg:address":"Ctra Nal Trescientos Treinta Y Dos, Km. 0216,0",
    "sg:city":"Oliva",
    "sg:orig_category":"Producci\u00d3n, Comercio De Cereales",
    "sg:phone":"+34 962 85 86 01",
    "sg:postcode":"46780",
    "sg:province":"Valencia",
    "wof:name":"Arroces Y Cereales S.a.",
    "wof:placetype":"venue"
},
  "geometry": {"coordinates":[-0.1027180031,38.8936729431],"type":"Point"}
}