{
  "type": "Feature",
  "properties": {
    "addr:full":"Carr Santa Eugenia, 1 Girona Girona 17001",
    "addr:housenumber":"1",
    "addr:postcode":"17001",
    "addr:street":"Carr Santa Eugenia",
    "iso:country":"ES",
    "sg:address":"Carr Santa Eugenia, 1",
    "sg:city":"Girona",
    "sg:orig_category":"Abogados",
    "sg:phone":"+34 972 41 70 79",
    "sg:postcode":"17001",
    "sg:province":"Girona",
    "wof:name":"Thomas Vall-llosera Carlos",
    "wof:placetype":"venue"
},
  "geometry": {"coordinates":[2.818762064,41.9821586609],"type":"Point"}
}