{
  "type": "Feature",
  "properties": {
    "iso:country":"ES",
    "sg:address":"Avda Federico Anaya, 140",
    "sg:city":"Salamanca",
    "sg:orig_category":"Internados & Ense\u00d1anza Privada",
    "sg:phone":"+34 923 25 23 53",
    "sg:postcode":"37004",
    "sg:province":"Salamanca",
    "sg:website":"www.montessori.edu.co",
    "wof:name":"Colegio Montessori S. L.",
    "wof:placetype":"venue"
},
  "geometry": {"coordinates":[-5.6515388489,40.9801902771],"type":"Point"}
}