{
  "type": "Feature",
  "properties": {
    "iso:country":"ES",
    "sg:address":"Calle de Oidor Berriozabalbeitia, 6",
    "sg:city":"Elorrio",
    "sg:orig_category":"Serigraf\u00cda (material Y Suministros)",
    "sg:phone":"+34 946 82 05 32",
    "sg:postcode":"48230",
    "sg:province":"Vizcaya",
    "wof:name":"Serigrafia Borobil S.l.",
    "wof:placetype":"venue"
},
  "geometry": {"coordinates":[-2.5409889221,43.1262702942],"type":"Point"}
}