{
  "type": "Feature",
  "properties": {
    "addr:full":"Calle de Meson, 17 Cintruenigo Navarra 31592",
    "addr:housenumber":"17",
    "addr:postcode":"31592",
    "addr:street":"Calle De Meson",
    "iso:country":"ES",
    "sg:address":"Calle de Meson, 17",
    "sg:city":"Cintruenigo",
    "sg:orig_category":"Motocicletas (agentes, Concesionarios)",
    "sg:phone":"+34 948 81 10 18",
    "sg:postcode":"31592",
    "sg:province":"Navarra",
    "wof:name":"Bea Lopez Justo",
    "wof:placetype":"venue"
},
  "geometry": {"coordinates":[-1.8071269989,42.0822792053],"type":"Point"}
}