{
  "type": "Feature",
  "properties": {
    "iso:country":"ES",
    "sg:address":"Pl Anselm Clave, 1",
    "sg:city":"S. Andreu Barca",
    "sg:orig_category":"M\u00c9dicos: Estomatolog\u00cda",
    "sg:phone":"+34 936 53 30 78",
    "sg:postcode":"08740",
    "sg:province":"Barcelona",
    "wof:name":"Falco Aguilar Pilar",
    "wof:placetype":"venue"
},
  "geometry": {"coordinates":[1.9743160009,41.4472579956],"type":"Point"}
}