{
  "type": "Feature",
  "properties": {
    "iso:country":"ES",
    "sg:address":"Carrer de Castellvi, S/n",
    "sg:city":"S. Cugat Valles",
    "sg:orig_category":"Ense\u00d1anza: Profesiones Art\u00cdsticas",
    "sg:phone":"+34 935 89 13 82",
    "sg:postcode":"08173",
    "sg:province":"Barcelona",
    "wof:name":"Ajuntament De Sant Cugat Del Valles",
    "wof:placetype":"venue"
},
  "geometry": {"coordinates":[2.0847363472,41.4748001099],"type":"Point"}
}