{
  "type": "Feature",
  "properties": {
    "addr:full":"Ctra Rubi, 198 Terrassa Barcelona 08228",
    "addr:housenumber":"198",
    "addr:postcode":"08228",
    "addr:street":"Ctra Rubi",
    "iso:country":"ES",
    "sg:address":"Ctra Rubi, 198",
    "sg:city":"Terrassa",
    "sg:orig_category":"Venta, Colocaci\u00d3n, Reparaci\u00d3n De Radiadores Para Veh\u00cdculos",
    "sg:phone":"+34 937 85 40 16",
    "sg:postcode":"08228",
    "sg:province":"Barcelona",
    "wof:name":"Ava Cooling Iberica S. L.",
    "wof:placetype":"venue"
},
  "geometry": {"coordinates":[2.01663661,41.5528259277],"type":"Point"}
}