{
  "type": "Feature",
  "properties": {
    "iso:country":"ES",
    "sg:address":"Carr Verge Del Carme, 10",
    "sg:city":"Puerto De Pollen\u00c7a",
    "sg:orig_category":"Restaurantes",
    "sg:phone":"+34 971 86 70 11",
    "sg:postcode":"07470",
    "sg:province":"Islas Baleares",
    "wof:name":"Restaurante Tots C.b.",
    "wof:placetype":"venue"
},
  "geometry": {"coordinates":[3.0816559792,39.9060630798],"type":"Point"}
}