{
  "type": "Feature",
  "properties": {
    "addr:full":"Luga Salto Del Grillo, 7 Bonanza C\u00e1diz 11540",
    "addr:housenumber":"7",
    "addr:postcode":"11540",
    "addr:street":"Bonanza Ca\u0301Diz",
    "iso:country":"ES",
    "sg:address":"Luga Salto Del Grillo, 7",
    "sg:city":"Bonanza",
    "sg:orig_category":"Tapicer\u00cdas",
    "sg:phone":"+34 956 36 59 06",
    "sg:postcode":"11540",
    "sg:province":"C\u00e1diz",
    "wof:name":"Tejero Sanchez Juan Manuel",
    "wof:placetype":"venue"
},
  "geometry": {"coordinates":[-6.3575987816,36.777721405],"type":"Point"}
}