{
  "type": "Feature",
  "properties": {
    "addr:full":"Calle de Madrid, 96 San Jose Rinconada Sevilla 41300",
    "addr:housenumber":"96",
    "addr:postcode":"41300",
    "addr:street":"Calle De Madrid",
    "iso:country":"ES",
    "sg:address":"Calle de Madrid, 96",
    "sg:city":"San Jose Rinconada",
    "sg:orig_category":"Confecci\u00d3n De Trajes Para Se\u00d1oras",
    "sg:phone":"+34 955 79 31 05",
    "sg:postcode":"41300",
    "sg:province":"Sevilla",
    "wof:name":"Confecciones Julimar S.l.",
    "wof:placetype":"venue"
},
  "geometry": {"coordinates":[-5.945374012,37.489074707],"type":"Point"}
}