{
  "type": "Feature",
  "properties": {
    "addr:full":"Calle de Sant Antoni, 18 Lucena Cid Castell\u00f3n 12120",
    "addr:housenumber":"18",
    "addr:postcode":"12120",
    "addr:street":"Calle De Sant Antoni;Castello\u0301N",
    "iso:country":"ES",
    "sg:address":"Calle de Sant Antoni, 18",
    "sg:city":"Lucena Cid",
    "sg:orig_category":"Negocio De Materiales De Construcci\u00d3n",
    "sg:phone":"+34 964 38 02 99",
    "sg:postcode":"12120",
    "sg:province":"Castell\u00f3n",
    "wof:name":"Materiales De Construccion Rafael Vidal S.l.",
    "wof:placetype":"venue"
},
  "geometry": {"coordinates":[-0.2829880118,40.1365318298],"type":"Point"}
}