{
  "type": "Feature",
  "properties": {
    "iso:country":"ES",
    "sg:address":"Fuente Clara, 13",
    "sg:city":"Mairena Aljarafe",
    "sg:orig_category":"Psic\u00d3logos",
    "sg:phone":"+34 954 18 07 19",
    "sg:postcode":"41927",
    "sg:province":"Sevilla",
    "wof:name":"Risoto Y Ruiz S.l.",
    "wof:placetype":"venue"
},
  "geometry": {"coordinates":[-6.0378189087,37.3444671631],"type":"Point"}
}