{
  "type": "Feature",
  "properties": {
    "iso:country":"ES",
    "sg:address":"Calle de Macias De Porras, 8",
    "sg:city":"Montijo",
    "sg:orig_category":"Contables",
    "sg:phone":"+34 924 45 56 17",
    "sg:postcode":"06480",
    "sg:province":"Badajoz",
    "wof:name":"Asesoria Alvarez Gomez S.l.",
    "wof:placetype":"venue"
},
  "geometry": {"coordinates":[-6.6143546104,38.9093322754],"type":"Point"}
}