{
  "type": "Feature",
  "properties": {
    "addr:full":"Calle de Infanta Maria Teresa, 21 Madrid Madrid 28016",
    "addr:housenumber":"21",
    "addr:postcode":"madrid;28016",
    "addr:street":"Calle De Infanta Maria Teresa",
    "iso:country":"ES",
    "sg:address":"Calle de Infanta Maria Teresa, 21",
    "sg:city":"Madrid",
    "sg:orig_category":"M\u00c9dicos: Estomatolog\u00cda",
    "sg:phone":"+34 913 44 06 47",
    "sg:postcode":"28016",
    "sg:province":"Madrid",
    "wof:name":"Saiz Moran Carlos",
    "wof:placetype":"venue"
},
  "geometry": {"coordinates":[-3.6795299053,40.4541664124],"type":"Point"}
}