{
  "type": "Feature",
  "properties": {
    "iso:country":"ES",
    "sg:address":"Avda Portugal, 66",
    "sg:city":"Valencia",
    "sg:orig_category":"Peluquer\u00cdas, Peluquer\u00cda Mixta",
    "sg:phone":"+34 963 49 53 19",
    "sg:postcode":"46009",
    "sg:province":"Valencia",
    "wof:name":"Pels Pels C.b.",
    "wof:placetype":"venue"
},
  "geometry": {"coordinates":[-0.3866730034,39.4868965149],"type":"Point"}
}