{
  "type": "Feature",
  "properties": {
    "addr:full":"Calle de Eduardo Marquina, 36 Madrid Madrid 28019",
    "addr:housenumber":"36",
    "addr:postcode":"madrid;28019",
    "addr:street":"Calle De Eduardo Marquina",
    "iso:country":"ES",
    "sg:address":"Calle de Eduardo Marquina, 36",
    "sg:city":"Madrid",
    "sg:orig_category":"Empresas De Limpieza",
    "sg:phone":"+34 914 69 85 83",
    "sg:postcode":"28019",
    "sg:province":"Madrid",
    "wof:name":"Esilimp.s.l.",
    "wof:placetype":"venue"
},
  "geometry": {"coordinates":[-3.71062994,40.3923454285],"type":"Point"}
}