{
  "type": "Feature",
  "properties": {
    "iso:country":"ES",
    "sg:address":"Carrer de Tenor Vi\u00d1as, 26",
    "sg:city":"S. Fost Campsentelles",
    "sg:orig_category":"Laboratorios Farmac\u00c9uticos",
    "sg:phone":"+34 935 70 13 58",
    "sg:postcode":"08105",
    "sg:province":"Barcelona",
    "wof:name":"Colome Fuste Susana",
    "wof:placetype":"venue"
},
  "geometry": {"coordinates":[2.2360489368,41.5199623108],"type":"Point"}
}