{
  "type": "Feature",
  "properties": {
    "iso:country":"ES",
    "sg:address":"Ignacio Zuloaga Kalea, 6",
    "sg:city":"Arrasate",
    "sg:orig_category":"Pod\u00d3logos: Pedicuros",
    "sg:phone":"+34 943 79 50 75",
    "sg:postcode":"20500",
    "sg:province":"Guip\u00f9zcoa",
    "wof:name":"Barrutiabengoa Uranga Jose Angel",
    "wof:placetype":"venue"
},
  "geometry": {"coordinates":[-2.4905159473,43.0666122437],"type":"Point"}
}