{
  "type": "Feature",
  "properties": {
    "iso:country":"ES",
    "sg:address":"Calle de Maestro Lizandara, 26",
    "sg:city":"Villar Arzobispo",
    "sg:orig_category":"Pescader\u00cdas (al Por Menor)",
    "sg:phone":"+34 962 72 00 66",
    "sg:postcode":"46170",
    "sg:province":"Valencia",
    "wof:name":"Iba\u00f1ez Montero Alejandro",
    "wof:placetype":"venue"
},
  "geometry": {"coordinates":[-0.8244860172,39.7310142517],"type":"Point"}
}