{
  "type": "Feature",
  "properties": {
    "addr:full":"Ferrerias Kalea, 21 Arrasate Guip\u00f9zcoa 20500",
    "addr:housenumber":"21",
    "addr:postcode":"20500",
    "addr:street":"Ferrerias Kalea;Guipu\u0300Zcoa",
    "iso:country":"ES",
    "sg:address":"Ferrerias Kalea, 21",
    "sg:city":"Arrasate",
    "sg:orig_category":"Ropa Para Se\u00d1oras (al Por Menor)",
    "sg:phone":"+34 943 79 70 06",
    "sg:postcode":"20500",
    "sg:province":"Guip\u00f9zcoa",
    "wof:name":"Uriarte Viguri Jesus",
    "wof:placetype":"venue"
},
  "geometry": {"coordinates":[-2.4906098843,43.0662345886],"type":"Point"}
}