{
  "type": "Feature",
  "properties": {
    "addr:full":"Avda Mari\u00d1a (da), S/n San Cibrao Lugo 27890",
    "addr:housenumber":"/ n",
    "addr:postcode":"27890",
    "addr:street":"Avda Marin\u0303A Da S",
    "iso:country":"ES",
    "sg:address":"Avda Mari\u00d1a (da), S/n",
    "sg:city":"San Cibrao",
    "sg:orig_category":"Centros De Educaci\u00d3n Especial",
    "sg:phone":"+34 982 59 44 06",
    "sg:postcode":"27890",
    "sg:province":"Lugo",
    "wof:name":"Colegio Publico N 2",
    "wof:placetype":"venue"
},
  "geometry": {"coordinates":[-7.4397139549,43.6968955994],"type":"Point"}
}