{
  "type": "Feature",
  "properties": {
    "iso:country":"ES",
    "sg:address":"Extramuros, 17",
    "sg:city":"Robleda",
    "sg:orig_category":"Empresas De Carpinter\u00cda De Madera",
    "sg:phone":"+34 923 48 62 32",
    "sg:postcode":"37521",
    "sg:province":"Salamanca",
    "wof:name":"Prieto Gomez Jose",
    "wof:placetype":"venue"
},
  "geometry": {"coordinates":[-6.6071438789,40.3848495483],"type":"Point"}
}