{
  "type": "Feature",
  "properties": {
    "addr:full":"Maritima, 25 Puerto Santiago Santa Cruz De Tenerife 38683",
    "addr:housenumber":"25",
    "addr:postcode":"38683",
    "addr:street":"Maritima",
    "iso:country":"ES",
    "sg:address":"Maritima, 25",
    "sg:city":"Puerto Santiago",
    "sg:orig_category":"Peluquer\u00cdas, Peluquer\u00cda Mixta",
    "sg:phone":"+34 922 86 17 66",
    "sg:postcode":"38683",
    "sg:province":"Santa Cruz De Tenerife",
    "wof:name":"Peluqueria Siglo Xxi C.b.",
    "wof:placetype":"venue"
},
  "geometry": {"coordinates":[-16.8398971558,28.244386673],"type":"Point"}
}