{
  "type": "Feature",
  "properties": {
    "addr:full":"Avda Vilaboa, 82 Vilaboa La Coru\u00f1a 15174",
    "addr:housenumber":"82",
    "addr:postcode":"15174",
    "addr:street":"Avda Vilaboa;La Corun\u0303A",
    "iso:country":"ES",
    "sg:address":"Avda Vilaboa, 82",
    "sg:city":"Vilaboa",
    "sg:orig_category":"Peluqueros: De Se\u00d1oras",
    "sg:phone":"+34 981 65 09 32",
    "sg:postcode":"15174",
    "sg:province":"La Coru\u00f1a",
    "wof:name":"Garcia Celada Maria Teresa",
    "wof:placetype":"venue"
},
  "geometry": {"coordinates":[-8.3825883865,43.3121032715],"type":"Point"}
}