{
  "type": "Feature",
  "properties": {
    "iso:country":"ES",
    "sg:address":"Av Rivoli, S/n",
    "sg:city":"Mollet Valles",
    "sg:orig_category":"Centros De Educaci\u00d3n Especial",
    "sg:phone":"+34 935 79 43 00",
    "sg:postcode":"08100",
    "sg:province":"Barcelona",
    "wof:name":"Institut Municipal Educacio",
    "wof:placetype":"venue"
},
  "geometry": {"coordinates":[2.2090699673,41.5467681885],"type":"Point"}
}