{
  "type": "Feature",
  "properties": {
    "iso:country":"ES",
    "sg:address":"Plaz Constitucion (la), S/n",
    "sg:city":"Camponaraya",
    "sg:orig_category":"Electricidad (montaje, Ensamblaje De Componentes)",
    "sg:phone":"+34 987 46 34 10",
    "sg:postcode":"24410",
    "sg:province":"Le\u00f3n",
    "wof:name":"Taller Electrico Neira Y Vazquez S.l.",
    "wof:placetype":"venue"
},
  "geometry": {"coordinates":[-6.6715989113,42.5795783997],"type":"Point"}
}