{
  "type": "Feature",
  "properties": {
    "iso:country":"ES",
    "sg:address":"Calle de Emilio Llopis, 12",
    "sg:city":"Sagunt",
    "sg:orig_category":"Asilos De Ancianos. Centros Privados",
    "sg:phone":"+34 962 66 01 67",
    "sg:postcode":"46500",
    "sg:province":"Valencia",
    "wof:name":"Hermanitas De Ancianos Desamparados Asilo",
    "wof:placetype":"venue"
},
  "geometry": {"coordinates":[-0.2713944018,39.6824607849],"type":"Point"}
}