{
  "type": "Feature",
  "properties": {
    "addr:full":"Calle de Mayor, 17 Pilar Horadada Alicante 03190",
    "addr:housenumber":"17",
    "addr:postcode":"03190",
    "addr:street":"Calle De Mayor",
    "iso:country":"ES",
    "sg:address":"Calle de Mayor, 17",
    "sg:city":"Pilar Horadada",
    "sg:orig_category":"Farmacias",
    "sg:phone":"+34 965 35 10 10",
    "sg:postcode":"03190",
    "sg:province":"Alicante",
    "wof:name":"Espuch Llaneras Rafael",
    "wof:placetype":"venue"
},
  "geometry": {"coordinates":[-0.7934129834,37.8657836914],"type":"Point"}
}