{
  "type": "Feature",
  "properties": {
    "addr:full":"Calle de Juan Calzada Kalea, 14 Gernika-lumo Vizcaya 48300",
    "addr:housenumber":"14",
    "addr:postcode":"48300",
    "addr:street":"Calle De Juan Calzada Kalea",
    "iso:country":"ES",
    "sg:address":"Calle de Juan Calzada Kalea, 14",
    "sg:city":"Gernika-lumo",
    "sg:orig_category":"Bronceado Por Rayos Uva",
    "sg:phone":"+34 946 25 79 41",
    "sg:postcode":"48300",
    "sg:province":"Vizcaya",
    "sg:website":"www. broncearium.com",
    "wof:name":"Batis Mendoza Nagore",
    "wof:placetype":"venue"
},
  "geometry": {"coordinates":[-2.6787190437,43.312538147],"type":"Point"}
}