{
  "type": "Feature",
  "properties": {
    "addr:full":"Calle de Marrutxipi, 24 Donostia-san Sebastian Guip\u00f9zcoa 20013",
    "addr:housenumber":"24",
    "addr:postcode":"20013",
    "addr:street":"Calle De Marrutxipi",
    "iso:country":"ES",
    "sg:address":"Calle de Marrutxipi, 24",
    "sg:city":"Donostia-san Sebastian",
    "sg:orig_category":"Peluqueros: De Se\u00d1oras",
    "sg:phone":"+34 943 27 85 31",
    "sg:postcode":"20013",
    "sg:province":"Guip\u00f9zcoa",
    "wof:name":"Burgos Igareta Maria Lourdes",
    "wof:placetype":"venue"
},
  "geometry": {"coordinates":[-1.9592570066,43.3183288574],"type":"Point"}
}