{
  "type": "Feature",
  "properties": {
    "addr:full":"Calle de Jesus, 36 Zaragoza Zaragoza 50014",
    "addr:housenumber":"36",
    "addr:postcode":"50014",
    "addr:street":"Calle De Jesus",
    "iso:country":"ES",
    "sg:address":"Calle de Jesus, 36",
    "sg:city":"Zaragoza",
    "sg:orig_category":"Asilos De Ancianos. Centros Privados",
    "sg:phone":"+34 976 39 83 18",
    "sg:postcode":"50014",
    "sg:province":"Zaragoza",
    "wof:name":"Gonzalez De La Huerta Jose Jorge",
    "wof:placetype":"venue"
},
  "geometry": {"coordinates":[-0.8703590035,41.657951355],"type":"Point"}
}