{
  "type": "Feature",
  "properties": {
    "addr:full":"Calle de Fuente Del Ibon, 14 Huesca Huesca 22003",
    "addr:housenumber":"14",
    "addr:postcode":"22003",
    "addr:street":"Calle De Fuente Del Ibon",
    "iso:country":"ES",
    "sg:address":"Calle de Fuente Del Ibon, 14",
    "sg:city":"Huesca",
    "sg:orig_category":"Molduras, Junquillos, Listones Y Molduras Perforadas",
    "sg:phone":"+34 974 21 03 00",
    "sg:postcode":"22003",
    "sg:province":"Huesca",
    "wof:name":"Garcia Diaz Encarna",
    "wof:placetype":"venue"
},
  "geometry": {"coordinates":[-0.4142383039,42.1339302063],"type":"Point"}
}