{
  "type": "Feature",
  "properties": {
    "addr:full":"Carrer de Francesc Ferrer I Guardia, 30 Mollet Valles Barcelona 08100",
    "addr:housenumber":"30",
    "addr:postcode":"08100",
    "addr:street":"Carrer De Francesc Ferrer I Guardia",
    "iso:country":"ES",
    "sg:address":"Carrer de Francesc Ferrer I Guardia, 30",
    "sg:city":"Mollet Valles",
    "sg:orig_category":"Colchones (fabricaci\u00d3n, Al Por Mayor, Al Por Menor)",
    "sg:phone":"+34 935 44 52 93",
    "sg:postcode":"08100",
    "sg:province":"Barcelona",
    "sg:website":"www.moblerone.com",
    "wof:name":"Merlinmobel S.l.",
    "wof:placetype":"venue"
},
  "geometry": {"coordinates":[2.2166249752,41.5438613892],"type":"Point"}
}