{
  "type": "Feature",
  "properties": {
    "iso:country":"ES",
    "sg:address":"Avda Constitucion Espa\u00d1ola, 16",
    "sg:city":"Burgos",
    "sg:orig_category":"Fabricaci\u00d3n De Taburetes, Sillas Y Sillones",
    "sg:phone":"+34 947 22 11 28",
    "sg:postcode":"09007",
    "sg:province":"Burgos",
    "wof:name":"Pieldi International S.l.",
    "wof:placetype":"venue"
},
  "geometry": {"coordinates":[-3.6726810932,42.3479232788],"type":"Point"}
}