{
  "type": "Feature",
  "properties": {
    "iso:country":"ES",
    "sg:address":"Plaz Escamilla, 13",
    "sg:city":"Coin",
    "sg:orig_category":"Bancos",
    "sg:phone":"+34 952 45 02 50",
    "sg:postcode":"29100",
    "sg:province":"M\u00e1laga",
    "sg:website":"www.bancoandalucia.es",
    "wof:name":"Banco De Andalucia",
    "wof:placetype":"venue"
},
  "geometry": {"coordinates":[-4.7579469681,36.6595344543],"type":"Point"}
}