{
  "type": "Feature",
  "properties": {
    "addr:full":"Calle de Ferraz, 29 Madrid Madrid 28008",
    "addr:housenumber":"29",
    "addr:postcode":"madrid;28008",
    "addr:street":"Calle De Ferraz",
    "iso:country":"ES",
    "sg:address":"Calle de Ferraz, 29",
    "sg:city":"Madrid",
    "sg:orig_category":"Agencias De Viajes",
    "sg:phone":"+34 915 59 60 30",
    "sg:postcode":"28008",
    "sg:province":"Madrid",
    "wof:name":"Viajes Rolmar S.l.",
    "wof:placetype":"venue"
},
  "geometry": {"coordinates":[-3.7191469669,40.4278259277],"type":"Point"}
}