{
  "type": "Feature",
  "properties": {
    "iso:country":"ES",
    "sg:address":"Calle de Abadia, 1",
    "sg:city":"Muniesa",
    "sg:orig_category":"Iglesia Cat\u00d3lica",
    "sg:phone":"+34 978 81 02 04",
    "sg:postcode":"44780",
    "sg:province":"Teruel",
    "wof:name":"Parroquia De San Miguel Arcangel",
    "wof:placetype":"venue"
},
  "geometry": {"coordinates":[-0.811794579,41.0345153809],"type":"Point"}
}