{
  "type": "Feature",
  "properties": {
    "addr:full":"Calle de Iglesia, 6 Moraira Alicante 03724",
    "addr:housenumber":"6",
    "addr:postcode":"03724",
    "addr:street":"Calle De Iglesia",
    "iso:country":"ES",
    "sg:address":"Calle de Iglesia, 6",
    "sg:city":"Moraira",
    "sg:orig_category":"Confecci\u00d3n De Trajes Para Se\u00d1oras",
    "sg:phone":"+34 966 49 06 66",
    "sg:postcode":"03724",
    "sg:province":"Alicante",
    "wof:name":"Bertomeu Valles Maria Teresa",
    "wof:placetype":"venue"
},
  "geometry": {"coordinates":[0.134134993,38.6877632141],"type":"Point"}
}