{
  "type": "Feature",
  "properties": {
    "iso:country":"ES",
    "sg:address":"Carrer de Llull, 125",
    "sg:city":"Barcelona",
    "sg:orig_category":"M\u00c1quinas Textiles, Accesorios Y Suministros (fabricaci\u00d3n)",
    "sg:phone":"+34 934 86 45 00",
    "sg:postcode":"08005",
    "sg:province":"Barcelona",
    "wof:name":"Recambio Y Maquinaria Textil S.a.",
    "wof:placetype":"venue"
},
  "geometry": {"coordinates":[2.1980330944,41.3981132507],"type":"Point"}
}