{
  "type": "Feature",
  "properties": {
    "iso:country":"ES",
    "sg:address":"Avda Madrid, 234",
    "sg:city":"Vigo",
    "sg:orig_category":"Chapister\u00cda",
    "sg:phone":"+34 986 28 13 43",
    "sg:postcode":"36204",
    "sg:province":"Pontevedra",
    "wof:name":"Garage Enxebre S.l.",
    "wof:placetype":"venue"
},
  "geometry": {"coordinates":[-8.7110786438,42.2243003845],"type":"Point"}
}