{
  "type": "Feature",
  "properties": {
    "addr:full":"Carr Santa Barbara, 19 Alcudia Valencia 46250",
    "addr:housenumber":"19",
    "addr:postcode":"46250",
    "addr:street":"Carr Santa Barbara",
    "iso:country":"ES",
    "sg:address":"Carr Santa Barbara, 19",
    "sg:city":"Alcudia",
    "sg:orig_category":"Carnicer\u00cdas, Carnicer\u00cdas",
    "sg:phone":"+34 962 99 67 07",
    "sg:postcode":"46250",
    "sg:province":"Valencia",
    "wof:name":"Marin Ortells Vicente",
    "wof:placetype":"venue"
},
  "geometry": {"coordinates":[-0.5070289969,39.1940689087],"type":"Point"}
}