{
  "type": "Feature",
  "properties": {
    "iso:country":"ES",
    "sg:address":"Barr Escajal, S/n",
    "sg:city":"Castillo",
    "sg:orig_category":"Producci\u00d3n, Venta De Productos De Agricultura Biol\u00d3gica",
    "sg:phone":"+34 942 65 70 58",
    "sg:postcode":"39193",
    "sg:province":"Cantabria",
    "wof:name":"S A T Disama",
    "wof:placetype":"venue"
},
  "geometry": {"coordinates":[-3.5410709381,43.4605445862],"type":"Point"}
}