{
  "type": "Feature",
  "properties": {
    "addr:full":"Urb Capellania (la), 3 Tomillares M\u00e1laga 29130",
    "addr:housenumber":"3",
    "addr:postcode":"29130",
    "addr:street":"Urb Capellania La;Ma\u0301Laga",
    "iso:country":"ES",
    "sg:address":"Urb Capellania (la), 3",
    "sg:city":"Tomillares",
    "sg:orig_category":"Alquiler De V\u00cddeo",
    "sg:phone":"+34 952 42 64 86",
    "sg:postcode":"29130",
    "sg:province":"M\u00e1laga",
    "wof:name":"Carmona Do\u00f1a Maria Teresa",
    "wof:placetype":"venue"
},
  "geometry": {"coordinates":[-4.5667190552,36.6618614197],"type":"Point"}
}