{
  "type": "Feature",
  "properties": {
    "addr:full":"Calle de Turia, 34 Valencia Valencia 46008",
    "addr:housenumber":"34",
    "addr:postcode":"46008",
    "addr:street":"Calle De Turia",
    "iso:country":"ES",
    "sg:address":"Calle de Turia, 34",
    "sg:city":"Valencia",
    "sg:orig_category":"Prot\u00c9sicos Dentales",
    "sg:phone":"+34 963 91 06 97",
    "sg:postcode":"46008",
    "sg:province":"Valencia",
    "wof:name":"Minguez Rubio Bego\u00f1a",
    "wof:placetype":"venue"
},
  "geometry": {"coordinates":[-0.385307312,39.4762306213],"type":"Point"}
}