{
  "type": "Feature",
  "properties": {
    "iso:country":"ES",
    "sg:address":"Calle de Regales, 32",
    "sg:city":"Santurtzi",
    "sg:orig_category":"Promotores Constructores",
    "sg:phone":"+34 944 83 61 21",
    "sg:postcode":"48980",
    "sg:province":"Vizcaya",
    "wof:name":"Cdad Prop De La Calle Regales N\u00ba 26-28-30 Y 32",
    "wof:placetype":"venue"
},
  "geometry": {"coordinates":[-3.0428090096,43.3344116211],"type":"Point"}
}