{
  "type": "Feature",
  "properties": {
    "iso:country":"ES",
    "sg:address":"Gazta\u00d1adui Kalea, 15",
    "sg:city":"Eskoriatza",
    "sg:orig_category":"Carnicer\u00cdas, Carnicer\u00cdas",
    "sg:phone":"+34 943 71 51 97",
    "sg:postcode":"20540",
    "sg:province":"Guip\u00f9zcoa",
    "wof:name":"Pagalday Altuna Juan De Dios",
    "wof:placetype":"venue"
},
  "geometry": {"coordinates":[-2.5154209137,43.0240287781],"type":"Point"}
}