{
  "type": "Feature",
  "properties": {
    "addr:full":"Carrer de Daoiz I Velarde, 25 Barcelona Barcelona 08028",
    "addr:housenumber":"25",
    "addr:postcode":"08028",
    "addr:street":"Carrer De Daoiz I Velarde",
    "iso:country":"ES",
    "sg:address":"Carrer de Daoiz I Velarde, 25",
    "sg:city":"Barcelona",
    "sg:orig_category":"Cuchiller\u00cda (al Por Menor)",
    "sg:phone":"+34 934 90 96 99",
    "sg:postcode":"08028",
    "sg:province":"Barcelona",
    "wof:name":"Gonzalez Perez Catalina",
    "wof:placetype":"venue"
},
  "geometry": {"coordinates":[2.1323640347,41.3740463257],"type":"Point"}
}