{
  "type": "Feature",
  "properties": {
    "addr:full":"Pol Ind La Ceramica, S/n Castro Rio C\u00f3rdoba 14840",
    "addr:postcode":"14840",
    "addr:street":"S / N Castro Rio Co\u0301Rdoba",
    "iso:country":"ES",
    "sg:address":"Pol Ind La Ceramica, S/n",
    "sg:city":"Castro Rio",
    "sg:orig_category":"Mataderos De Poller\u00cda",
    "sg:phone":"+34 957 37 28 92",
    "sg:postcode":"14840",
    "sg:province":"C\u00f3rdoba",
    "wof:name":"Sada P.a. Andalucia S.a.",
    "wof:placetype":"venue"
},
  "geometry": {"coordinates":[-4.4765949249,37.6923103333],"type":"Point"}
}