{
  "type": "Feature",
  "properties": {
    "iso:country":"ES",
    "sg:address":"Avda Pio Baroja, 22",
    "sg:city":"Malaga",
    "sg:orig_category":"Platos Preparados Refrigerados (fabricaci\u00d3n, Al Por Mayor)",
    "sg:phone":"+34 952 29 66 97",
    "sg:postcode":"29017",
    "sg:province":"M\u00e1laga",
    "wof:name":"Cuevas Alfaro Victorino",
    "wof:placetype":"venue"
},
  "geometry": {"coordinates":[-4.362057209,36.7200889587],"type":"Point"}
}