{
  "type": "Feature",
  "properties": {
    "addr:full":"Plaz Hermanos Fernandez Criado, 11 Illescas Toledo 45200",
    "addr:housenumber":"11",
    "addr:postcode":"45200",
    "addr:street":"Criado",
    "iso:country":"ES",
    "sg:address":"Plaz Hermanos Fernandez Criado, 11",
    "sg:city":"Illescas",
    "sg:orig_category":"Farmacias",
    "sg:phone":"+34 925 51 10 18",
    "sg:postcode":"45200",
    "sg:province":"Toledo",
    "wof:name":"Rodriguez Esquivias Maria De Las Mercedes",
    "wof:placetype":"venue"
},
  "geometry": {"coordinates":[-3.8489980698,40.1247673035],"type":"Point"}
}