{
  "type": "Feature",
  "properties": {
    "addr:full":"Calle de Gonzalez Silva, 1 Cisterniga Valladolid 47193",
    "addr:housenumber":"1",
    "addr:postcode":"47193",
    "addr:street":"Calle De Gonzalez Silva",
    "iso:country":"ES",
    "sg:address":"Calle de Gonzalez Silva, 1",
    "sg:city":"Cisterniga",
    "sg:orig_category":"Fabricaci\u00d3n, Venta De Cuadros, Accesorios Para Enmarcar",
    "sg:phone":"+34 983 40 27 04",
    "sg:postcode":"47193",
    "sg:province":"Valladolid",
    "wof:name":"Duplain  Tony",
    "wof:placetype":"venue"
},
  "geometry": {"coordinates":[-4.6860251427,41.6115608215],"type":"Point"}
}