{
  "type": "Feature",
  "properties": {
    "addr:full":"Calle de Argentina, 1 Arrecife Las Palmas 35500",
    "addr:housenumber":"1",
    "addr:postcode":"35500",
    "addr:street":"Calle De Argentina",
    "iso:country":"ES",
    "sg:address":"Calle de Argentina, 1",
    "sg:city":"Arrecife",
    "sg:orig_category":"Inform\u00c1tica: Mantenimiento Y Reparaci\u00d3n De Ordenadores",
    "sg:phone":"+34 928 82 41 87",
    "sg:postcode":"35500",
    "sg:province":"Las Palmas",
    "sg:website":"www.vmrm.net",
    "wof:name":"Robaina Mosegue Victor",
    "wof:placetype":"venue"
},
  "geometry": {"coordinates":[-13.5531387329,28.9625263214],"type":"Point"}
}