{
  "type": "Feature",
  "properties": {
    "addr:full":"Rua Frei Rosendo Salvado (de), 8 Santiago De Compostela La Coru\u00f1a 15701",
    "addr:housenumber":"8",
    "addr:postcode":"15701",
    "addr:street":"Rua Frei Rosendo Salvado De;Corun\u0303A",
    "iso:country":"ES",
    "sg:address":"Rua Frei Rosendo Salvado (de), 8",
    "sg:city":"Santiago De Compostela",
    "sg:orig_category":"Comadronas",
    "sg:phone":"+34 981 59 06 24",
    "sg:postcode":"15701",
    "sg:province":"La Coru\u00f1a",
    "wof:name":"Couso Rivas Maria Del Carmen",
    "wof:placetype":"venue"
},
  "geometry": {"coordinates":[-8.5501537323,42.8739585876],"type":"Point"}
}