{
  "type": "Feature",
  "properties": {
    "addr:full":"Avda Plantio (del), 2 Coslada Madrid 28820",
    "addr:housenumber":"2",
    "addr:postcode":"28820",
    "addr:street":"Avda Plantio Del",
    "iso:country":"ES",
    "sg:address":"Avda Plantio (del), 2",
    "sg:city":"Coslada",
    "sg:orig_category":"Peluquer\u00cdas, Peluquer\u00cda Mixta",
    "sg:phone":"+34 916 69 60 04",
    "sg:postcode":"28820",
    "sg:province":"Madrid",
    "sg:website":"www.spejos.es",
    "wof:name":"Ortiz Centeno Maria Ramona",
    "wof:placetype":"venue"
},
  "geometry": {"coordinates":[-3.5645070076,40.4260902405],"type":"Point"}
}