{
  "type": "Feature",
  "properties": {
    "iso:country":"ES",
    "sg:address":"Calle de Obieta, 31",
    "sg:city":"Altzaga",
    "sg:orig_category":"Carnicer\u00cdas, Carnicer\u00cdas",
    "sg:phone":"+34 944 67 56 17",
    "sg:postcode":"48950",
    "sg:province":"Vizcaya",
    "wof:name":"Gomez Pereda Primitivo",
    "wof:placetype":"venue"
},
  "geometry": {"coordinates":[-2.9722559452,43.304069519],"type":"Point"}
}