{
  "type": "Feature",
  "properties": {
    "iso:country":"ES",
    "sg:address":"Calle de Conde Vallellano, 57",
    "sg:city":"Requena",
    "sg:orig_category":"Fabricaci\u00d3n De Muebles",
    "sg:phone":"+34 962 30 29 22",
    "sg:postcode":"46340",
    "sg:province":"Valencia",
    "wof:name":"Navarro Fernandez Manuel",
    "wof:placetype":"venue"
},
  "geometry": {"coordinates":[-1.1050444841,39.4871864319],"type":"Point"}
}