{
  "type": "Feature",
  "properties": {
    "iso:country":"ES",
    "sg:address":"Carr Teular, 1",
    "sg:city":"Algemesi",
    "sg:orig_category":"Asesor\u00cda Fiscal Y Jur\u00cddica",
    "sg:phone":"+34 962 48 16 58",
    "sg:postcode":"46680",
    "sg:province":"Valencia",
    "wof:name":"Belda Vicent Ricardo",
    "wof:placetype":"venue"
},
  "geometry": {"coordinates":[-0.433472991,39.1905517578],"type":"Point"}
}