{
  "type": "Feature",
  "properties": {
    "addr:full":"Carrer de Cuba, 22 Mataro Barcelona 08302",
    "addr:housenumber":"22",
    "addr:postcode":"08302",
    "addr:street":"Carrer De Cuba",
    "iso:country":"ES",
    "sg:address":"Carrer de Cuba, 22",
    "sg:city":"Mataro",
    "sg:orig_category":"Tintorer\u00cdas, Limpieza En Seco",
    "sg:phone":"+34 937 98 43 91",
    "sg:postcode":"08302",
    "sg:province":"Barcelona",
    "wof:name":"Cabezas Casas Carlos Cesar",
    "wof:placetype":"venue"
},
  "geometry": {"coordinates":[2.4398291111,41.5376358032],"type":"Point"}
}