{
  "type": "Feature",
  "properties": {
    "addr:full":"Cno Castellars, S/n Montserrat Valencia 46192",
    "addr:housenumber":"s / n",
    "addr:postcode":"46192",
    "addr:street":"Cno Castellars",
    "iso:country":"ES",
    "sg:address":"Cno Castellars, S/n",
    "sg:city":"Montserrat",
    "sg:orig_category":"Hormigonados",
    "sg:phone":"+34 962 55 53 77",
    "sg:postcode":"46192",
    "sg:province":"Valencia",
    "wof:name":"Hormicemex",
    "wof:placetype":"venue"
},
  "geometry": {"coordinates":[-0.5983390212,39.3566665649],"type":"Point"}
}