{
  "type": "Feature",
  "properties": {
    "iso:country":"ES",
    "sg:address":"Calle de Tropico, 6",
    "sg:city":"Torrejon Ardoz",
    "sg:orig_category":"Electromedicina: Servicios",
    "sg:phone":"+34 916 48 71 13",
    "sg:postcode":"28850",
    "sg:province":"Madrid",
    "wof:name":"Sanchez Molina Jesus",
    "wof:placetype":"venue"
},
  "geometry": {"coordinates":[-3.482489109,40.4441490173],"type":"Point"}
}