{
  "type": "Feature",
  "properties": {
    "addr:full":"Calle de Pedro Cabanes, 81 Valencia Valencia 46019",
    "addr:housenumber":"81",
    "addr:postcode":"46019",
    "addr:street":"Calle De Pedro Cabanes",
    "iso:country":"ES",
    "sg:address":"Calle de Pedro Cabanes, 81",
    "sg:city":"Valencia",
    "sg:orig_category":"Reposter\u00cdas",
    "sg:phone":"+34 963 65 34 89",
    "sg:postcode":"46019",
    "sg:province":"Valencia",
    "wof:name":"Lluna Llatas Jose",
    "wof:placetype":"venue"
},
  "geometry": {"coordinates":[-0.3788593113,39.4940910339],"type":"Point"}
}