{
  "type": "Feature",
  "properties": {
    "iso:country":"ES",
    "sg:address":"Palomares P I Casablanca, 33",
    "sg:city":"Laguardia-biasteri",
    "sg:orig_category":"Fabricaci\u00d3n De Moldes Y Modelos",
    "sg:phone":"+34 945 62 51 01",
    "sg:postcode":"01300",
    "sg:province":"\u00c1lava",
    "sg:website":"www.decam.es",
    "wof:name":"Decam Technology S.l.",
    "wof:placetype":"venue"
},
  "geometry": {"coordinates":[-2.5706250668,42.5470809937],"type":"Point"}
}