{
  "type": "Feature",
  "properties": {
    "addr:full":"Calle de Alarcon, 17 Picazo Cuenca 16211",
    "addr:housenumber":"17",
    "addr:postcode":"16211",
    "addr:street":"Calle De Alarcon",
    "iso:country":"ES",
    "sg:address":"Calle de Alarcon, 17",
    "sg:city":"Picazo",
    "sg:orig_category":"Farmacias",
    "sg:phone":"+34 969 38 01 22",
    "sg:postcode":"16211",
    "sg:province":"Cuenca",
    "wof:name":"Garcia Pa\u00f1os Juan Carlos",
    "wof:placetype":"venue"
},
  "geometry": {"coordinates":[-2.0880231857,39.4513282776],"type":"Point"}
}