{
  "type": "Feature",
  "properties": {
    "addr:full":"Plaz Luis Rodriguez Miguel, 4 Fuentesauco Zamora 49400",
    "addr:housenumber":"4",
    "addr:postcode":"49400",
    "addr:street":"Plaz Luis Rodriguez Miguel;Zamora",
    "iso:country":"ES",
    "sg:address":"Plaz Luis Rodriguez Miguel, 4",
    "sg:city":"Fuentesauco",
    "sg:orig_category":"Maquinaria, Instalaci\u00d3n Y Equipo Para Garajes Y Estaciones De Servicio",
    "sg:phone":"+34 980 60 00 54",
    "sg:postcode":"49400",
    "sg:province":"Zamora",
    "wof:name":"Seguin Y Diego S.l.",
    "wof:placetype":"venue"
},
  "geometry": {"coordinates":[-5.4974589348,41.2317390442],"type":"Point"}
}