{
  "type": "Feature",
  "properties": {
    "addr:full":"Calle de Aristoteles, 17 Roquetas Mar Almer\u00eda 04740",
    "addr:housenumber":"17",
    "addr:postcode":"04740",
    "addr:street":"Calle De Aristoteles",
    "iso:country":"ES",
    "sg:address":"Calle de Aristoteles, 17",
    "sg:city":"Roquetas Mar",
    "sg:orig_category":"Promotores Constructores",
    "sg:phone":"+34 950 32 85 01",
    "sg:postcode":"04740",
    "sg:province":"Almer\u00eda",
    "wof:name":"A.s. Promociones S.a.",
    "wof:placetype":"venue"
},
  "geometry": {"coordinates":[-2.6122353077,36.7650299072],"type":"Point"}
}