{
  "type": "Feature",
  "properties": {
    "iso:country":"ES",
    "sg:address":"Calle de B, 2",
    "sg:city":"Mutiloabeiti",
    "sg:orig_category":"Contenedores (mercanc\u00cdas)",
    "sg:phone":"+34 948 24 68 05",
    "sg:postcode":"31192",
    "sg:province":"Navarra",
    "wof:name":"Transportes Lizarraldea S.l.",
    "wof:placetype":"venue"
},
  "geometry": {"coordinates":[-1.6346614361,42.8071289062],"type":"Point"}
}