{
  "type": "Feature",
  "properties": {
    "addr:full":"Cust Morana La, 7 Zamora Zamora 49025",
    "addr:postcode":"49025",
    "iso:country":"ES",
    "sg:address":"Cust Morana La, 7",
    "sg:city":"Zamora",
    "sg:orig_category":"Mec\u00c1nico Del Autom\u00d3vil",
    "sg:phone":"+34 980 52 83 31",
    "sg:postcode":"49025",
    "sg:province":"Zamora",
    "wof:name":"Mata Rodriguez Ezequiel Alberto",
    "wof:placetype":"venue"
},
  "geometry": {"coordinates":[-5.7457342148,41.5033302307],"type":"Point"}
}