{
  "type": "Feature",
  "properties": {
    "addr:full":"Calle de Estudio Y Pilancon, 6 Villanueva De Los Infantes Ciudad Real 13320",
    "addr:housenumber":"6",
    "addr:postcode":"13320",
    "addr:street":"Calle De Estudio Y Pilancon;Infantes",
    "iso:country":"ES",
    "sg:address":"Calle de Estudio Y Pilancon, 6",
    "sg:city":"Villanueva De Los Infantes",
    "sg:orig_category":"Arquitectos",
    "sg:phone":"+34 926 36 15 01",
    "sg:postcode":"13320",
    "sg:province":"Ciudad Real",
    "wof:name":"Aparicio Gonzalez Jose Carlos",
    "wof:placetype":"venue"
},
  "geometry": {"coordinates":[-3.0157585144,38.7356796265],"type":"Point"}
}