{
  "type": "Feature",
  "properties": {
    "addr:full":"Miguel Asins Arbo(compositor), 16 Valencia Valencia 46013",
    "addr:housenumber":"16",
    "addr:postcode":"46013",
    "addr:street":"Compositor",
    "iso:country":"ES",
    "sg:address":"Miguel Asins Arbo(compositor), 16",
    "sg:city":"Valencia",
    "sg:orig_category":"Asesor\u00cda, Estudio Y Control Medioambiental",
    "sg:phone":"+34 963 74 63 95",
    "sg:postcode":"46013",
    "sg:province":"Valencia",
    "wof:name":"Gestion Medioambiental Consultores S.l",
    "wof:placetype":"venue"
},
  "geometry": {"coordinates":[-0.3572140038,39.4546318054],"type":"Point"}
}