{
  "type": "Feature",
  "properties": {
    "iso:country":"ES",
    "sg:address":"Tapiada, S/n",
    "sg:city":"Finestrat",
    "sg:orig_category":"Producci\u00d3n, Distribuci\u00d3n De Gas Butano Y Propano",
    "sg:phone":"+34 965 87 87 29",
    "sg:postcode":"03509",
    "sg:province":"Alicante",
    "wof:name":"Futurgas Del Mediterraneo S.l.",
    "wof:placetype":"venue"
},
  "geometry": {"coordinates":[-0.2106740028,38.5691642761],"type":"Point"}
}