{
  "type": "Feature",
  "properties": {
    "iso:country":"ES",
    "sg:address":"Cta. Prado Del Rey-arcos, Km. 0018,5",
    "sg:city":"Prado Del Rey",
    "sg:orig_category":"Producci\u00d3n, Venta De Productos De Agricultura Biol\u00d3gica",
    "sg:phone":"+34 956 23 12 72",
    "sg:postcode":"11660",
    "sg:province":"C\u00e1diz",
    "wof:name":"Los Galayos C.b.",
    "wof:placetype":"venue"
},
  "geometry": {"coordinates":[-5.5636034012,36.7670669556],"type":"Point"}
}