{
  "type": "Feature",
  "properties": {
    "addr:full":"Calle de Schultz, 5 Oviedo Asturias 33003",
    "addr:housenumber":"5",
    "addr:postcode":"33003",
    "addr:street":"Calle De Schultz",
    "iso:country":"ES",
    "sg:address":"Calle de Schultz, 5",
    "sg:city":"Oviedo",
    "sg:orig_category":"Arquitectos",
    "sg:phone":"+34 985 27 60 31",
    "sg:postcode":"33003",
    "sg:province":"Asturias",
    "wof:name":"Arquitectonia S.l.",
    "wof:placetype":"venue"
},
  "geometry": {"coordinates":[-5.8444113731,43.3628616333],"type":"Point"}
}