{
  "type": "Feature",
  "properties": {
    "addr:full":"Rua Progreso, 17 Sanxenxo Pontevedra 36960",
    "addr:housenumber":"17",
    "addr:postcode":"36960",
    "addr:street":"Rua Progreso",
    "iso:country":"ES",
    "sg:address":"Rua Progreso, 17",
    "sg:city":"Sanxenxo",
    "sg:orig_category":"Molduras, Junquillos, Listones Y Molduras Perforadas",
    "sg:phone":"+34 986 72 02 44",
    "sg:postcode":"36960",
    "sg:province":"Pontevedra",
    "wof:name":"Martinez Perez Maria Del Carmen",
    "wof:placetype":"venue"
},
  "geometry": {"coordinates":[-8.799908638,42.4011306763],"type":"Point"}
}