{
  "type": "Feature",
  "properties": {
    "addr:full":"Calle de Mesones, 15 Constantina Sevilla 41450",
    "addr:housenumber":"15",
    "addr:postcode":"41450",
    "addr:street":"Calle De Mesones",
    "iso:country":"ES",
    "sg:address":"Calle de Mesones, 15",
    "sg:city":"Constantina",
    "sg:orig_category":"Asilos De Ancianos. Centros Privados",
    "sg:phone":"+34 955 88 19 10",
    "sg:postcode":"41450",
    "sg:province":"Sevilla",
    "wof:name":"Asociacion Tercera Edad Constancia Julia",
    "wof:placetype":"venue"
},
  "geometry": {"coordinates":[-5.6202845573,37.8742599487],"type":"Point"}
}