{
  "type": "Feature",
  "properties": {
    "iso:country":"ES",
    "sg:address":"Calle de Tejedores, S/n",
    "sg:city":"Medina Campo",
    "sg:orig_category":"Muebles Y Accesorios Para Cocinas Y Cuartos De Ba\u00d1o (al Por Menor)",
    "sg:phone":"+34 983 80 35 55",
    "sg:postcode":"47400",
    "sg:province":"Valladolid",
    "wof:name":"San Cristobal Muebles De Cocina S.l.",
    "wof:placetype":"venue"
},
  "geometry": {"coordinates":[-4.9210639,41.3243560791],"type":"Point"}
}