{
  "type": "Feature",
  "properties": {
    "addr:full":"Carrer de Calvet, 11 Barcelona Barcelona 08021",
    "addr:housenumber":"11",
    "addr:postcode":"08021",
    "addr:street":"Carrer De Calvet",
    "iso:country":"ES",
    "sg:address":"Carrer de Calvet, 11",
    "sg:city":"Barcelona",
    "sg:orig_category":"Automatizaci\u00d3n De Procesos Industriales Y De Edificaci\u00d3n (estudios, Instalaci\u00d3n)",
    "sg:phone":"+34 932 00 49 08",
    "sg:postcode":"08021",
    "sg:province":"Barcelona",
    "sg:website":"www.gdconvey.com",
    "wof:name":"Gd Convey S.a.",
    "wof:placetype":"venue"
},
  "geometry": {"coordinates":[2.1444780827,41.3937492371],"type":"Point"}
}