{
  "type": "Feature",
  "properties": {
    "addr:full":"Rua Escultor Acu\u00d1a (do), 17 Pontevedra Pontevedra 36003",
    "addr:housenumber":"17",
    "addr:postcode":"36003",
    "addr:street":"Rua Escultor Acun\u0303A Do",
    "iso:country":"ES",
    "sg:address":"Rua Escultor Acu\u00d1a (do), 17",
    "sg:city":"Pontevedra",
    "sg:orig_category":"M\u00c9dicos: Cirug\u00cda General",
    "sg:phone":"+34 986 86 54 86",
    "sg:postcode":"36003",
    "sg:province":"Pontevedra",
    "wof:name":"Diaz Pereira Jesus",
    "wof:placetype":"venue"
},
  "geometry": {"coordinates":[-8.6556968689,42.4145812988],"type":"Point"}
}