{
  "type": "Feature",
  "properties": {
    "iso:country":"ES",
    "sg:address":"Calle de Menendez Pidal, 5",
    "sg:city":"Huesca",
    "sg:orig_category":"Herboristas (al Por Menor)",
    "sg:phone":"+34 974 21 41 81",
    "sg:postcode":"22003",
    "sg:province":"Huesca",
    "wof:name":"Buil Sierra Nieves",
    "wof:placetype":"venue"
},
  "geometry": {"coordinates":[-0.4155089855,42.1364364624],"type":"Point"}
}