{
  "type": "Feature",
  "properties": {
    "iso:country":"ES",
    "sg:address":"Avda Dacio Darias, 35",
    "sg:city":"Valverde",
    "sg:orig_category":"Peluquer\u00cdas, Peluquer\u00cda Mixta",
    "sg:phone":"+34 922 55 00 12",
    "sg:postcode":"38910",
    "sg:province":"Santa Cruz De Tenerife",
    "wof:name":"Martin Rodriguez Candelaria",
    "wof:placetype":"venue"
},
  "geometry": {"coordinates":[-17.8970718384,27.8238143921],"type":"Point"}
}