{
  "type": "Feature",
  "properties": {
    "addr:full":"Calle de Emilio Pino, 1 Santander Cantabria 39002",
    "addr:housenumber":"1",
    "addr:postcode":"39002",
    "addr:street":"Calle De Emilio Pino",
    "iso:country":"ES",
    "sg:address":"Calle de Emilio Pino, 1",
    "sg:city":"Santander",
    "sg:orig_category":"M\u00c9dicos: Gastroenterolog\u00cda Y Hepatolog\u00cda (aparato Digestivo)",
    "sg:phone":"+34 942 31 43 26",
    "sg:postcode":"39002",
    "sg:province":"Cantabria",
    "wof:name":"San Miguel Joglar Genaro Ramon",
    "wof:placetype":"venue"
},
  "geometry": {"coordinates":[-3.8094038963,43.4606933594],"type":"Point"}
}