{
  "type": "Feature",
  "properties": {
    "addr:full":"Ctra. Maria, S/n Puebla Don Fadrique Granada 18820",
    "addr:housenumber":"/ n",
    "addr:postcode":"18820",
    "addr:street":"Ctra. Maria S",
    "iso:country":"ES",
    "sg:address":"Ctra. Maria, S/n",
    "sg:city":"Puebla Don Fadrique",
    "sg:orig_category":"Tiendas De Grano, Frutas Y Legumbres Secas (al Por Menor)",
    "sg:phone":"+34 958 72 15 21",
    "sg:postcode":"18820",
    "sg:province":"Granada",
    "wof:name":"Frutos Secos Del Ma\u00f1an S.c.l.",
    "wof:placetype":"venue"
},
  "geometry": {"coordinates":[-2.4338490963,37.9588508606],"type":"Point"}
}