{
  "type": "Feature",
  "properties": {
    "addr:full":"Ctra Providencia De La, S/n Gijon Asturias 33203",
    "addr:postcode":"33203",
    "addr:street":"Ctra Providencia De La S / N",
    "iso:country":"ES",
    "sg:address":"Ctra Providencia De La, S/n",
    "sg:city":"Gijon",
    "sg:classifiers":[
        {
            "category":"Cinema",
            "subcategory":"Movie Theater",
            "type":"Entertainment"
        }
    ],
    "sg:phone":"+34 985 97 46 94",
    "sg:postcode":"33203",
    "sg:province":"Asturias",
    "sg:tags":[
        "salas",
        "de",
        "cine"
    ],
    "wof:name":"Autocine Gijon S.l.",
    "wof:placetype":"venue"
},
  "geometry": {"coordinates":[-5.624985218,43.5463409424],"type":"Point"}
}