{
  "type": "Feature",
  "properties": {
    "addr:full":"Pol Ind Los Arroyos, S/n Moguer Huelva 21800",
    "addr:housenumber":"s / n",
    "addr:postcode":"21800",
    "addr:street":"Los Arroyos",
    "iso:country":"ES",
    "sg:address":"Pol Ind Los Arroyos, S/n",
    "sg:city":"Moguer",
    "sg:orig_category":"Chapister\u00cda",
    "sg:phone":"+34 959 37 04 13",
    "sg:postcode":"21800",
    "sg:province":"Huelva",
    "wof:name":"Hermanos Cruz Y Garrido S.l.",
    "wof:placetype":"venue"
},
  "geometry": {"coordinates":[-6.8342490196,37.2783584595],"type":"Point"}
}