{
  "type": "Feature",
  "properties": {
    "iso:country":"ES",
    "sg:address":"Av Diagonal, 362",
    "sg:city":"Barcelona",
    "sg:orig_category":"Delegados, Agentes De Tr\u00c1nsito, Auxiliares De Transporte Internacional",
    "sg:phone":"+34 934 57 39 22",
    "sg:postcode":"08013",
    "sg:province":"Barcelona",
    "wof:name":"Transportes Monros Hermanos S.a.",
    "wof:placetype":"venue"
},
  "geometry": {"coordinates":[2.1716899872,41.3999061584],"type":"Point"}
}