{
  "type": "Feature",
  "properties": {
    "iso:country":"ES",
    "sg:address":"Avda Palma De Mallorca, 15",
    "sg:city":"Torremolinos",
    "sg:orig_category":"Centros M\u00c9dicos Y Sociales, Dispensarios",
    "sg:phone":"+34 952 37 40 05",
    "sg:postcode":"29620",
    "sg:province":"M\u00e1laga",
    "wof:name":"Lopez Heras Cristina",
    "wof:placetype":"venue"
},
  "geometry": {"coordinates":[-4.4999709129,36.6222991943],"type":"Point"}
}