{
  "type": "Feature",
  "properties": {
    "addr:full":"Calle de Viriato, 56 Madrid Madrid 28010",
    "addr:housenumber":"56",
    "addr:postcode":"madrid;28010",
    "addr:street":"Calle De Viriato",
    "iso:country":"ES",
    "sg:address":"Calle de Viriato, 56",
    "sg:city":"Madrid",
    "sg:orig_category":"Administradores De Bienes Y Delegados De Comunidades De Propietarios",
    "sg:phone":"+34 914 45 92 69",
    "sg:postcode":"28010",
    "sg:province":"Madrid",
    "wof:name":"Bermudez Alonso Maria Dolores",
    "wof:placetype":"venue"
},
  "geometry": {"coordinates":[-3.6971380711,40.4355392456],"type":"Point"}
}