{
  "type": "Feature",
  "properties": {
    "iso:country":"ES",
    "sg:address":"Avda Sevilla, 18",
    "sg:city":"Palacios Y Villafranca",
    "sg:orig_category":"Agentes, Concesionarios Y Sucursales De Veh\u00cdculos",
    "sg:phone":"+34 955 81 59 74",
    "sg:postcode":"41720",
    "sg:province":"Sevilla",
    "wof:name":"Moguer Gomez Hermanos S.l.",
    "wof:placetype":"venue"
},
  "geometry": {"coordinates":[-5.9236731529,37.1608734131],"type":"Point"}
}