{
  "type": "Feature",
  "properties": {
    "iso:country":"ES",
    "sg:address":"Calle de Marques De Teverga, 9",
    "sg:city":"Oviedo",
    "sg:orig_category":"M\u00c9dicos: Psiquiatr\u00cda",
    "sg:phone":"+34 985 25 31 05",
    "sg:postcode":"33005",
    "sg:province":"Asturias",
    "wof:name":"Bouso\u00f1o Garcia Manuel",
    "wof:placetype":"venue"
},
  "geometry": {"coordinates":[-5.8561282158,43.3618545532],"type":"Point"}
}