{
  "type": "Feature",
  "properties": {
    "iso:country":"ES",
    "sg:address":"G.v. Marques Del Turia, 62",
    "sg:city":"Valencia",
    "sg:orig_category":"Art\u00cdculos De Decoraci\u00d3n (fabricaci\u00d3n Y Al Por Mayor)",
    "sg:phone":"+34 963 33 23 49",
    "sg:postcode":"46005",
    "sg:province":"Valencia",
    "wof:name":"Garcia Trigo Trinidad",
    "wof:placetype":"venue"
},
  "geometry": {"coordinates":[-0.3671480119,39.4674072266],"type":"Point"}
}