{
  "type": "Feature",
  "properties": {
    "iso:country":"ES",
    "sg:address":"Vred Praet (el), 18",
    "sg:city":"Campaneta",
    "sg:orig_category":"Electrodom\u00c9sticos (al Por Menor)",
    "sg:phone":"+34 965 30 30 20",
    "sg:postcode":"03314",
    "sg:province":"Alicante",
    "wof:name":"Montero Belmonte Angel",
    "wof:placetype":"venue"
},
  "geometry": {"coordinates":[-0.8623440266,38.0960388184],"type":"Point"}
}