{
  "type": "Feature",
  "properties": {
    "addr:full":"Carr Mariano Benlliure, 2 Massamagrell Valencia 46130",
    "addr:housenumber":"2",
    "addr:postcode":"46130",
    "addr:street":"Carr Mariano Benlliure",
    "iso:country":"ES",
    "sg:address":"Carr Mariano Benlliure, 2",
    "sg:city":"Massamagrell",
    "sg:orig_category":"Ense\u00d1anza, Formaci\u00d3n Profesional: Aprendizaje",
    "sg:phone":"+34 961 44 49 51",
    "sg:postcode":"46130",
    "sg:province":"Valencia",
    "wof:name":"Ayuntamiento De Massamagrell",
    "wof:placetype":"venue"
},
  "geometry": {"coordinates":[-0.3324424028,39.5680503845],"type":"Point"}
}