{
  "type": "Feature",
  "properties": {
    "iso:country":"ES",
    "sg:address":"Carrer de Banys, 1",
    "sg:city":"Garriga",
    "sg:orig_category":"Frutas, Legumbres Frescas Y Tempranas (al Por Menor)",
    "sg:phone":"+34 938 71 80 22",
    "sg:postcode":"08530",
    "sg:province":"Barcelona",
    "wof:name":"Grabis Estrany Josep",
    "wof:placetype":"venue"
},
  "geometry": {"coordinates":[2.2857859135,41.6843452454],"type":"Point"}
}