{
  "type": "Feature",
  "properties": {
    "addr:full":"Calle de Veracruz, 16 Mostoles Madrid 28937",
    "addr:housenumber":"16",
    "addr:postcode":"28937",
    "addr:street":"Calle De Veracruz",
    "iso:country":"ES",
    "sg:address":"Calle de Veracruz, 16",
    "sg:city":"Mostoles",
    "sg:orig_category":"Centros Comerciales Y Grandes Tiendas",
    "sg:phone":"+34 916 47 18 10",
    "sg:postcode":"28937",
    "sg:province":"Madrid",
    "wof:name":"Hiper Euro C.b.",
    "wof:placetype":"venue"
},
  "geometry": {"coordinates":[-3.8562669754,40.3181686401],"type":"Point"}
}