{
  "type": "Feature",
  "properties": {
    "iso:country":"ES",
    "sg:address":"Calle de Amantillo, S/n",
    "sg:city":"Adeje",
    "sg:orig_category":"Centros Empresariales",
    "sg:phone":"+34 922 71 07 58",
    "sg:postcode":"38670",
    "sg:province":"Santa Cruz De Tenerife",
    "wof:name":"Meesemaecker  Liliane",
    "wof:placetype":"venue"
},
  "geometry": {"coordinates":[-16.7312259674,28.1188316345],"type":"Point"}
}