{
  "type": "Feature",
  "properties": {
    "addr:full":"Cmno Aguas, 54 Salamanca Salamanca 37003",
    "addr:housenumber":"54",
    "addr:postcode":"37003",
    "addr:street":"Cmno Aguas",
    "iso:country":"ES",
    "sg:address":"Cmno Aguas, 54",
    "sg:city":"Salamanca",
    "sg:orig_category":"Ropa Para Ni\u00d1os (al Por Menor)",
    "sg:phone":"+34 923 18 30 27",
    "sg:postcode":"37003",
    "sg:province":"Salamanca",
    "wof:name":"Hermanos Ferreres Hermoso Cdad.",
    "wof:placetype":"venue"
},
  "geometry": {"coordinates":[-5.6506938934,40.9631309509],"type":"Point"}
}