{
  "type": "Feature",
  "properties": {
    "iso:country":"ES",
    "sg:address":"Av. Albufera, 31",
    "sg:city":"Sedavi",
    "sg:orig_category":"Platos Preparados Refrigerados (fabricaci\u00d3n, Al Por Mayor)",
    "sg:phone":"+34 963 75 70 73",
    "sg:postcode":"46910",
    "sg:province":"Valencia",
    "wof:name":"Alvarez Alonso Yolanda",
    "wof:placetype":"venue"
},
  "geometry": {"coordinates":[-0.3855460882,39.4227256775],"type":"Point"}
}