{
  "type": "Feature",
  "properties": {
    "iso:country":"ES",
    "sg:address":"Circunvalacion, 28",
    "sg:city":"Granada",
    "sg:orig_category":"Deportes Diversos",
    "sg:phone":"+34 958 52 04 44",
    "sg:postcode":"18007",
    "sg:province":"Granada",
    "wof:name":"Federacion Andaluza De Atletismo",
    "wof:placetype":"venue"
},
  "geometry": {"coordinates":[-3.5975089073,37.1594314575],"type":"Point"}
}