{
  "type": "Feature",
  "properties": {
    "iso:country":"ES",
    "sg:address":"Avda Manuel Salmeron, 47",
    "sg:city":"Berja",
    "sg:orig_category":"Servicios Gsm",
    "sg:phone":"+34 950 49 09 33",
    "sg:postcode":"04760",
    "sg:province":"Almer\u00eda",
    "wof:name":"Air-adra S.r.l.",
    "wof:placetype":"venue"
},
  "geometry": {"coordinates":[-2.9474782944,36.8441581726],"type":"Point"}
}