{
  "type": "Feature",
  "properties": {
    "iso:country":"ES",
    "sg:address":"Carr Celleters, 149",
    "sg:city":"Cabaneta",
    "sg:orig_category":"Cristaler\u00cdas",
    "sg:phone":"+34 971 22 61 01",
    "sg:postcode":"07141",
    "sg:province":"Islas Baleares",
    "sg:website":"www.cristaledo.com",
    "wof:name":"Cristaledo S.a.",
    "wof:placetype":"venue"
},
  "geometry": {"coordinates":[2.7445349693,39.6195487976],"type":"Point"}
}