{
  "type": "Feature",
  "properties": {
    "iso:country":"ES",
    "sg:address":"Calle de Almeria (de), 2",
    "sg:city":"Humanes De Madrid",
    "sg:orig_category":"Ingenier\u00cda, Centros De Estudios (diversos)",
    "sg:phone":"+34 916 90 40 63",
    "sg:postcode":"28970",
    "sg:province":"Madrid",
    "sg:website":"www.vibrachoc.es",
    "wof:name":"Vibrachoc S. A",
    "wof:placetype":"venue"
},
  "geometry": {"coordinates":[-3.8175060749,40.2746963501],"type":"Point"}
}