{
  "type": "Feature",
  "properties": {
    "iso:country":"ES",
    "sg:address":"Calle de Cura, 1",
    "sg:city":"Romeral",
    "sg:orig_category":"Agencias Y Agentes Comerciales, Representantes",
    "sg:phone":"+34 925 12 61 29",
    "sg:postcode":"45770",
    "sg:province":"Toledo",
    "wof:name":"Rempal Representaciones S.l.",
    "wof:placetype":"venue"
},
  "geometry": {"coordinates":[-3.4340379238,39.7077217102],"type":"Point"}
}