{
  "type": "Feature",
  "properties": {
    "addr:full":"Ctra. Piedrahita, S/n Macotera Salamanca 37310",
    "addr:housenumber":"s",
    "addr:postcode":"37310",
    "addr:street":"Ctra. Piedrahita;/ N",
    "iso:country":"ES",
    "sg:address":"Ctra. Piedrahita, S/n",
    "sg:city":"Macotera",
    "sg:orig_category":"Electricidad Veh\u00cdculo",
    "sg:phone":"+34 923 55 53 94",
    "sg:postcode":"37310",
    "sg:province":"Salamanca",
    "wof:name":"Dosuna Sanchez Angel",
    "wof:placetype":"venue"
},
  "geometry": {"coordinates":[-5.2791008949,40.830783844],"type":"Point"}
}