{
  "type": "Feature",
  "properties": {
    "addr:full":"Calle de Jaime Esteve Cubells, 1 Valencia Valencia 46020",
    "addr:housenumber":"1",
    "addr:postcode":"46020",
    "addr:street":"Calle De Jaime Esteve Cubells",
    "iso:country":"ES",
    "sg:address":"Calle de Jaime Esteve Cubells, 1",
    "sg:city":"Valencia",
    "sg:orig_category":"\u00d3ptica: Instrumentos (fabricaci\u00d3n)",
    "sg:phone":"+34 963 61 11 55",
    "sg:postcode":"46020",
    "sg:province":"Valencia",
    "wof:name":"Cotino Solaz Mercedes",
    "wof:placetype":"venue"
},
  "geometry": {"coordinates":[-0.3589369953,39.4828948975],"type":"Point"}
}