{
  "type": "Feature",
  "properties": {
    "iso:country":"ES",
    "sg:address":"Autovia(p Campollano), 5",
    "sg:city":"Albacete",
    "sg:orig_category":"Fabricaci\u00d3n De Cervezas",
    "sg:phone":"+34 967 24 59 07",
    "sg:postcode":"02006",
    "sg:province":"Albacete",
    "wof:name":"Drinktrade S.a.",
    "wof:placetype":"venue"
},
  "geometry": {"coordinates":[-1.8381589651,39.0684165955],"type":"Point"}
}