{
  "type": "Feature",
  "properties": {
    "iso:country":"ES",
    "sg:address":"Afueras, S/n",
    "sg:city":"Almendralejo",
    "sg:orig_category":"Producci\u00d3n, Venta De Productos De Agricultura Biol\u00d3gica",
    "sg:phone":"+34 924 14 31 52",
    "sg:postcode":"06200",
    "sg:province":"Badajoz",
    "wof:name":"Valdemede S.l.",
    "wof:placetype":"venue"
},
  "geometry": {"coordinates":[-6.4068241119,38.6845092773],"type":"Point"}
}