{
  "type": "Feature",
  "properties": {
    "addr:full":"Avda Doctor Federico Rubio Y Gali, 37 Madrid Madrid 28039",
    "addr:housenumber":"37",
    "addr:postcode":"madrid;28039",
    "addr:street":"Avda Doctor Federico Rubio Y Gali",
    "iso:country":"ES",
    "sg:address":"Avda Doctor Federico Rubio Y Gali, 37",
    "sg:city":"Madrid",
    "sg:orig_category":"Empresarios Y Productoras De Espect\u00c1culos",
    "sg:phone":"+34 914 59 90 29",
    "sg:postcode":"28039",
    "sg:province":"Madrid",
    "wof:name":"Resino Fernandez Andres",
    "wof:placetype":"venue"
},
  "geometry": {"coordinates":[-3.7094869614,40.4513969421],"type":"Point"}
}