{
  "type": "Feature",
  "properties": {
    "addr:full":"Carrer de Arago, 3 Premia Mar Barcelona 08330",
    "addr:housenumber":"3",
    "addr:postcode":"08330",
    "addr:street":"Carrer De Arago",
    "iso:country":"ES",
    "sg:address":"Carrer de Arago, 3",
    "sg:city":"Premia Mar",
    "sg:orig_category":"Empresas De Carpinter\u00cda",
    "sg:phone":"+34 937 52 35 78",
    "sg:postcode":"08330",
    "sg:province":"Barcelona",
    "wof:name":"Cristalerias Corbalan Lopez S.l.",
    "wof:placetype":"venue"
},
  "geometry": {"coordinates":[2.3598690033,41.498085022],"type":"Point"}
}