{
  "type": "Feature",
  "properties": {
    "addr:full":"Pl Angel, 8 Sabadell Barcelona 08202",
    "addr:housenumber":"8",
    "addr:postcode":"08202",
    "addr:street":"Pl Angel",
    "iso:country":"ES",
    "sg:address":"Pl Angel, 8",
    "sg:city":"Sabadell",
    "sg:orig_category":"Fabricaci\u00d3n De Telas Y Sedas",
    "sg:phone":"+34 937 25 11 85",
    "sg:postcode":"08202",
    "sg:province":"Barcelona",
    "wof:name":"Bosch Pons Pedro",
    "wof:placetype":"venue"
},
  "geometry": {"coordinates":[2.1086199284,41.549282074],"type":"Point"}
}