{
  "type": "Feature",
  "properties": {
    "addr:full":"Calle de Clavel, 55 Madridejos Toledo 45710",
    "addr:housenumber":"55",
    "addr:postcode":"45710",
    "addr:street":"Calle De Clavel",
    "iso:country":"ES",
    "sg:address":"Calle de Clavel, 55",
    "sg:city":"Madridejos",
    "sg:orig_category":"Escayola Y Productos De Escayola (fabricaci\u00d3n, Al Por Mayor)",
    "sg:phone":"+34 925 46 06 29",
    "sg:postcode":"45710",
    "sg:province":"Toledo",
    "wof:name":"Moreno Martinlopez Pedro Luis",
    "wof:placetype":"venue"
},
  "geometry": {"coordinates":[-3.5291240215,39.4704666138],"type":"Point"}
}