{
  "type": "Feature",
  "properties": {
    "addr:full":"Carrer de Industria, 6 Sant Feliu Llobregat Barcelona 08980",
    "addr:housenumber":"6",
    "addr:postcode":"08980",
    "addr:street":"Carrer De Industria",
    "iso:country":"ES",
    "sg:address":"Carrer de Industria, 6",
    "sg:city":"Sant Feliu Llobregat",
    "sg:orig_category":"Chapister\u00cda",
    "sg:phone":"+34 936 66 81 64",
    "sg:postcode":"08980",
    "sg:province":"Barcelona",
    "wof:name":"Tallers Colbo S.l.",
    "wof:placetype":"venue"
},
  "geometry": {"coordinates":[2.0359499454,41.3861885071],"type":"Point"}
}