{
  "type": "Feature",
  "properties": {
    "addr:full":"Calle de Alejandro Casona, 30 Oviedo Asturias 33013",
    "addr:housenumber":"30",
    "addr:postcode":"33013",
    "addr:street":"Calle De Alejandro Casona",
    "iso:country":"ES",
    "sg:address":"Calle de Alejandro Casona, 30",
    "sg:city":"Oviedo",
    "sg:orig_category":"Material Y Suministros Para Fotocopiadoras, Reprograf\u00cda",
    "sg:phone":"+34 985 96 33 06",
    "sg:postcode":"33013",
    "sg:province":"Asturias",
    "wof:name":"Cri De Asturias S.a.",
    "wof:placetype":"venue"
},
  "geometry": {"coordinates":[-5.866332531,43.3624229431],"type":"Point"}
}