{
  "type": "Feature",
  "properties": {
    "addr:full":"Plaz Italia, S/n Avila \u00c1vila 05001",
    "addr:housenumber":"s / n",
    "addr:postcode":"05001",
    "addr:street":"A\u0301Vila",
    "iso:country":"ES",
    "sg:address":"Plaz Italia, S/n",
    "sg:city":"Avila",
    "sg:orig_category":"Museos",
    "sg:phone":"+34 920 25 67 14",
    "sg:postcode":"05001",
    "sg:province":"\u00c1vila",
    "wof:name":"Delegacion Territorial De La Junta De Castilla Y Leon-servio Te-",
    "wof:placetype":"venue"
},
  "geometry": {"coordinates":[-4.6955590248,40.6556510925],"type":"Point"}
}