{
  "type": "Feature",
  "properties": {
    "iso:country":"ES",
    "sg:address":"Calle de Pinar, 17",
    "sg:city":"Irun",
    "sg:orig_category":"Plomeros",
    "sg:phone":"+34 943 61 63 52",
    "sg:postcode":"20301",
    "sg:province":"Guip\u00f9zcoa",
    "wof:name":"Fontaneria Ernesto Villar",
    "wof:placetype":"venue"
},
  "geometry": {"coordinates":[-1.8003070354,43.3443984985],"type":"Point"}
}