{
  "type": "Feature",
  "properties": {
    "iso:country":"ES",
    "sg:address":"Calle de Colmena (la), 4",
    "sg:city":"Sotillo Adrada",
    "sg:orig_category":"Promotores Constructores",
    "sg:phone":"+34 918 66 08 43",
    "sg:postcode":"05420",
    "sg:province":"\u00c1vila",
    "wof:name":"Construcciones Calzado E Hijos S.l.",
    "wof:placetype":"venue"
},
  "geometry": {"coordinates":[-4.5892829895,40.2939071655],"type":"Point"}
}