{
  "type": "Feature",
  "properties": {
    "addr:full":"Calle de Santa Monica, 4 Bilbao Vizcaya 48006",
    "addr:housenumber":"4",
    "addr:postcode":"48006",
    "addr:street":"Calle De Santa Monica",
    "iso:country":"ES",
    "sg:address":"Calle de Santa Monica, 4",
    "sg:city":"Bilbao",
    "sg:orig_category":"Empresarios Y Productoras De Espect\u00c1culos",
    "sg:phone":"+34 944 33 00 20",
    "sg:postcode":"48006",
    "sg:province":"Vizcaya",
    "wof:name":"Ana Maria Lopez Zu\u00f1iga",
    "wof:placetype":"venue"
},
  "geometry": {"coordinates":[-2.9188439846,43.2573242188],"type":"Point"}
}