{
  "type": "Feature",
  "properties": {
    "iso:country":"ES",
    "sg:address":"Calle de Doctor Esquerdo, 89",
    "sg:city":"Madrid",
    "sg:orig_category":"Ortopedia General",
    "sg:phone":"+34 915 74 26 84",
    "sg:postcode":"28007",
    "sg:province":"Madrid",
    "wof:name":"Ortosur S.a.",
    "wof:placetype":"venue"
},
  "geometry": {"coordinates":[-3.6691889763,40.4176559448],"type":"Point"}
}