{
  "type": "Feature",
  "properties": {
    "iso:country":"ES",
    "sg:address":"Avda Beire, S/n",
    "sg:city":"Olite",
    "sg:orig_category":"Mec\u00c1nico Del Autom\u00d3vil",
    "sg:phone":"+34 948 74 01 08",
    "sg:postcode":"31390",
    "sg:province":"Navarra",
    "wof:name":"Echegoyen Ruiz Alberto",
    "wof:placetype":"venue"
},
  "geometry": {"coordinates":[-1.6481460333,42.4772644043],"type":"Point"}
}