{
  "type": "Feature",
  "properties": {
    "addr:full":"Avda Bruselas (de), 26 Jardines Del Duque Santa Cruz De Tenerife 38660",
    "addr:housenumber":"26",
    "addr:postcode":"38660",
    "addr:street":"Avda Bruselas De",
    "iso:country":"ES",
    "sg:address":"Avda Bruselas (de), 26",
    "sg:city":"Jardines Del Duque",
    "sg:orig_category":"Ropa Y Accesorios",
    "sg:phone":"+34 922 71 43 37",
    "sg:postcode":"38660",
    "sg:province":"Santa Cruz De Tenerife",
    "wof:name":"Rubimacor S.l.",
    "wof:placetype":"venue"
},
  "geometry": {"coordinates":[-16.7440872192,28.0932674408],"type":"Point"}
}