{
  "type": "Feature",
  "properties": {
    "addr:full":"Calle de Pelota, 1 Bilbao Vizcaya 48005",
    "addr:housenumber":"1",
    "addr:postcode":"48005",
    "addr:street":"Calle De Pelota",
    "iso:country":"ES",
    "sg:address":"Calle de Pelota, 1",
    "sg:city":"Bilbao",
    "sg:orig_category":"Ense\u00d1anza Variada",
    "sg:phone":"+34 944 16 08 43",
    "sg:postcode":"48005",
    "sg:province":"Vizcaya",
    "wof:name":"Zabala Montoya Miren Karmele",
    "wof:placetype":"venue"
},
  "geometry": {"coordinates":[-2.9258756638,43.2570381165],"type":"Point"}
}