{
  "type": "Feature",
  "properties": {
    "addr:full":"Rua Sabucedo, S/n Sabucedo Ourense 32813",
    "addr:housenumber":"s",
    "addr:postcode":"32813",
    "addr:street":"Rua Sabucedo;/ N",
    "iso:country":"ES",
    "sg:address":"Rua Sabucedo, S/n",
    "sg:city":"Sabucedo",
    "sg:orig_category":"Fabrica De Cer\u00c1micas",
    "sg:phone":"+34 988 43 07 51",
    "sg:postcode":"32813",
    "sg:province":"Ourense",
    "wof:name":"Cabano Montero Castor",
    "wof:placetype":"venue"
},
  "geometry": {"coordinates":[-7.922727108,42.1067810059],"type":"Point"}
}