{
  "type": "Feature",
  "properties": {
    "iso:country":"ES",
    "sg:address":"Estd Coru\u00d1a (da), Km. 0505,0",
    "sg:city":"Lugo",
    "sg:orig_category":"Distribuci\u00d3n De Petr\u00d3leo Y Derivados",
    "sg:phone":"+34 982 21 45 51",
    "sg:postcode":"27003",
    "sg:province":"Lugo",
    "sg:website":"www.cepsa.es",
    "wof:name":"Cedipsa Compa\u00d1ia Espa\u00d1ola Distribuidora De Petroleos S.a.",
    "wof:placetype":"venue"
},
  "geometry": {"coordinates":[-7.5763959885,43.0335426331],"type":"Point"}
}