{
  "type": "Feature",
  "properties": {
    "iso:country":"ES",
    "sg:address":"Rua Aira (da), 4",
    "sg:city":"Ourense",
    "sg:orig_category":"Internados & Ense\u00d1anza Privada",
    "sg:phone":"+34 988 24 00 57",
    "sg:postcode":"32005",
    "sg:province":"Ourense",
    "wof:name":"Luis Vives Orense S.l",
    "wof:placetype":"venue"
},
  "geometry": {"coordinates":[-7.8601388931,42.3320045471],"type":"Point"}
}