{
  "type": "Feature",
  "properties": {
    "addr:full":"Urb Castillo Alto, S/n Nerja M\u00e1laga 29780",
    "addr:housenumber":"s / n",
    "addr:postcode":"29780",
    "addr:street":"Urb;Alto",
    "iso:country":"ES",
    "sg:address":"Urb Castillo Alto, S/n",
    "sg:city":"Nerja",
    "sg:orig_category":"Imprenta",
    "sg:phone":"+34 952 52 41 03",
    "sg:postcode":"29780",
    "sg:province":"M\u00e1laga",
    "wof:name":"Baker Pickard S.c.",
    "wof:placetype":"venue"
},
  "geometry": {"coordinates":[-3.834997654,36.7956962585],"type":"Point"}
}