{
  "type": "Feature",
  "properties": {
    "addr:full":"Carrer de Bartrina, 22 Rubi Barcelona 08191",
    "addr:housenumber":"22",
    "addr:postcode":"08191",
    "addr:street":"Carrer De Bartrina",
    "iso:country":"ES",
    "sg:address":"Carrer de Bartrina, 22",
    "sg:city":"Rubi",
    "sg:orig_category":"Psic\u00d3logos",
    "sg:phone":"+34 935 88 12 77",
    "sg:postcode":"08191",
    "sg:province":"Barcelona",
    "wof:name":"Jorba Corbella Rosa",
    "wof:placetype":"venue"
},
  "geometry": {"coordinates":[2.0380189419,41.487991333],"type":"Point"}
}