{
  "type": "Feature",
  "properties": {
    "iso:country":"ES",
    "sg:address":"Calle de Santiago Lapuente, 4",
    "sg:city":"Zaragoza",
    "sg:orig_category":"Guarder\u00cdas",
    "sg:phone":"+34 976 29 88 45",
    "sg:postcode":"50014",
    "sg:province":"Zaragoza",
    "wof:name":"Miranda Peleato Ana Maria",
    "wof:placetype":"venue"
},
  "geometry": {"coordinates":[-0.8710952997,41.6592636108],"type":"Point"}
}