{
  "type": "Feature",
  "properties": {
    "iso:country":"ES",
    "sg:address":"Calle de Nueva, 10",
    "sg:city":"Villamuriel De Cerrato",
    "sg:orig_category":"Empresas De Carpinter\u00cda De Madera",
    "sg:phone":"+34 979 77 75 18",
    "sg:postcode":"34190",
    "sg:province":"Palencia",
    "wof:name":"Gutierrez Abril Basilio",
    "wof:placetype":"venue"
},
  "geometry": {"coordinates":[-4.5158100128,41.9474601746],"type":"Point"}
}