{
  "type": "Feature",
  "properties": {
    "addr:full":"Carrer de Major, 52 Montornes Centre Barcelona 08170",
    "addr:housenumber":"52",
    "addr:postcode":"08170",
    "addr:street":"Carrer De Major;Centre Barcelona",
    "iso:country":"ES",
    "sg:address":"Carrer de Major, 52",
    "sg:city":"Montornes Centre",
    "sg:orig_category":"Mec\u00c1nico Del Autom\u00d3vil",
    "sg:phone":"+34 935 68 46 52",
    "sg:postcode":"08170",
    "sg:province":"Barcelona",
    "wof:name":"Auto Reyve S.l",
    "wof:placetype":"venue"
},
  "geometry": {"coordinates":[2.2674899101,41.5419807434],"type":"Point"}
}