{
  "type": "Feature",
  "properties": {
    "addr:full":"Carr Sor Juana Cabanilles, S/n Cullera Valencia 46400",
    "addr:housenumber":"s / n",
    "addr:postcode":"46400",
    "addr:street":"Carr Sor Juana Cabanilles",
    "iso:country":"ES",
    "sg:address":"Carr Sor Juana Cabanilles, S/n",
    "sg:city":"Cullera",
    "sg:orig_category":"Frutos Y Legumbres",
    "sg:phone":"+34 961 72 11 40",
    "sg:postcode":"46400",
    "sg:province":"Valencia",
    "wof:name":"Cabanilles Carreres Emilio",
    "wof:placetype":"venue"
},
  "geometry": {"coordinates":[-0.25850299,39.1706581116],"type":"Point"}
}