{
  "type": "Feature",
  "properties": {
    "iso:country":"ES",
    "sg:address":"Cra. Mollet-moia, Km. 0003,0",
    "sg:city":"Palau-solita Plegamans",
    "sg:classifiers":[
        {
            "category":"Communications",
            "type":"Services"
        }
    ],
    "sg:phone":"+34 938 64 90 49",
    "sg:postcode":"08184",
    "sg:province":"Barcelona",
    "sg:tags":[
        "televisiones",
        "y",
        "radio"
    ],
    "wof:name":"Ente Publico R T V E",
    "wof:placetype":"venue"
},
  "geometry": {"coordinates":[2.181032896,41.5802307129],"type":"Point"}
}