{
  "type": "Feature",
  "properties": {
    "addr:full":"Cmno Cruces (las), 13 Aranjuez Madrid 28300",
    "addr:housenumber":"13",
    "addr:postcode":"28300",
    "addr:street":"Cmno Cruces Las",
    "iso:country":"ES",
    "sg:address":"Cmno Cruces (las), 13",
    "sg:city":"Aranjuez",
    "sg:orig_category":"Centros Empresariales",
    "sg:phone":"+34 918 92 54 73",
    "sg:postcode":"28300",
    "sg:province":"Madrid",
    "wof:name":"Romero De Avila Diaz Cano Jesus",
    "wof:placetype":"venue"
},
  "geometry": {"coordinates":[-3.6042790413,40.0360946655],"type":"Point"}
}