{
  "type": "Feature",
  "properties": {
    "addr:full":"Calle de Santa Maria, S/n Mahide Zamora 49522",
    "addr:housenumber":"/ n",
    "addr:postcode":"49522",
    "addr:street":"Calle De Santa;S",
    "iso:country":"ES",
    "sg:address":"Calle de Santa Maria, S/n",
    "sg:city":"Mahide",
    "sg:orig_category":"Bancos",
    "sg:phone":"+34 980 68 33 81",
    "sg:postcode":"49522",
    "sg:province":"Zamora",
    "wof:name":"Caja Rural De Zamora",
    "wof:placetype":"venue"
},
  "geometry": {"coordinates":[-6.377093792,41.8677215576],"type":"Point"}
}