{
  "type": "Feature",
  "properties": {
    "addr:full":"Plaza Berria, S/n Hernani Guip\u00f9zcoa 20120",
    "addr:housenumber":"s / n",
    "addr:postcode":"20120",
    "addr:street":"Berria;Guipu\u0300Zcoa",
    "iso:country":"ES",
    "sg:address":"Plaza Berria, S/n",
    "sg:city":"Hernani",
    "sg:orig_category":"Librer\u00cdas",
    "sg:phone":"+34 943 55 12 96",
    "sg:postcode":"20120",
    "sg:province":"Guip\u00f9zcoa",
    "wof:name":"Eizmendi Iparraguirre Juan Antonio",
    "wof:placetype":"venue"
},
  "geometry": {"coordinates":[-1.9745210409,43.2665061951],"type":"Point"}
}