{
  "type": "Feature",
  "properties": {
    "iso:country":"ES",
    "sg:address":"Calle de Luna, 63",
    "sg:city":"Puerto De Santa Maria",
    "sg:orig_category":"Zapater\u00cdas",
    "sg:phone":"+34 956 54 35 88",
    "sg:postcode":"11500",
    "sg:province":"C\u00e1diz",
    "wof:name":"Rosado Delgado Maria",
    "wof:placetype":"venue"
},
  "geometry": {"coordinates":[-6.22772789,36.5997581482],"type":"Point"}
}