{
  "type": "Feature",
  "properties": {
    "addr:full":"A Calle, 24 Calle Pontevedra 36750",
    "addr:postcode":"36750",
    "addr:street":"Calle 24;Pontevedra",
    "iso:country":"ES",
    "sg:address":"A Calle, 24",
    "sg:city":"Calle",
    "sg:orig_category":"Estilistas Y Estudios De Estilo De Corte Y Confecci\u00d3n",
    "sg:phone":"+34 986 62 14 02",
    "sg:postcode":"36750",
    "sg:province":"Pontevedra",
    "wof:name":"Miguel Angel Portela S.l",
    "wof:placetype":"venue"
},
  "geometry": {"coordinates":[-8.7685317993,41.9452552795],"type":"Point"}
}