{
  "type": "Feature",
  "properties": {
    "addr:full":"Calle de Ferrer Del Rio, 28 Madrid Madrid 28028",
    "addr:housenumber":"28",
    "addr:postcode":"madrid;28028",
    "addr:street":"Calle De Ferrer Del Rio",
    "iso:country":"ES",
    "sg:address":"Calle de Ferrer Del Rio, 28",
    "sg:city":"Madrid",
    "sg:orig_category":"Centros De Coordinaci\u00d3n",
    "sg:phone":"+34 913 55 90 05",
    "sg:postcode":"28028",
    "sg:province":"Madrid",
    "wof:name":"Baggiani  Federica",
    "wof:placetype":"venue"
},
  "geometry": {"coordinates":[-3.6708879471,40.4351539612],"type":"Point"}
}