{
  "type": "Feature",
  "properties": {
    "iso:country":"ES",
    "sg:address":"Calle de Aguas, 52",
    "sg:city":"Quintanar Orden",
    "sg:orig_category":"M\u00c9dicos: Estomatolog\u00cda",
    "sg:phone":"+34 925 18 05 44",
    "sg:postcode":"45800",
    "sg:province":"Toledo",
    "wof:name":"Martinez Lillo Antonio",
    "wof:placetype":"venue"
},
  "geometry": {"coordinates":[-3.044151783,39.5898971558],"type":"Point"}
}