{
  "type": "Feature",
  "properties": {
    "iso:country":"ES",
    "sg:address":"Rbla Catalunya, 54",
    "sg:city":"Barcelona",
    "sg:orig_category":"Centros Empresariales",
    "sg:phone":"+34 932 72 29 47",
    "sg:postcode":"08007",
    "sg:province":"Barcelona",
    "wof:name":"Min International Strategic Consultants Group S.l.",
    "wof:placetype":"venue"
},
  "geometry": {"coordinates":[2.1640460491,41.3909645081],"type":"Point"}
}