{
  "type": "Feature",
  "properties": {
    "addr:full":"Pase Libertad (la), 21 Albacete Albacete 02001",
    "addr:housenumber":"21",
    "addr:postcode":"02001",
    "addr:street":"Libertad La",
    "iso:country":"ES",
    "sg:address":"Pase Libertad (la), 21",
    "sg:city":"Albacete",
    "sg:orig_category":"Sociedades, Compa\u00d1\u00cdas Aseguradoras",
    "sg:phone":"+34 967 19 30 94",
    "sg:postcode":"02001",
    "sg:province":"Albacete",
    "sg:website":"www.vitalicico.es",
    "wof:name":"Banco Vitalicio De Espa\u00f1a C.a.",
    "wof:placetype":"venue"
},
  "geometry": {"coordinates":[-1.8524490595,38.996711731],"type":"Point"}
}