{
  "type": "Feature",
  "properties": {
    "iso:country":"ES",
    "sg:address":"Calle de Ramon Y Cajal, 8",
    "sg:city":"Motril",
    "sg:orig_category":"Telas Y Sedas (al Por Menor)",
    "sg:phone":"+34 958 60 26 13",
    "sg:postcode":"18600",
    "sg:province":"Granada",
    "wof:name":"Aparicio Delgado Nicolas",
    "wof:placetype":"venue"
},
  "geometry": {"coordinates":[-3.5167512894,36.7464256287],"type":"Point"}
}