{
  "type": "Feature",
  "properties": {
    "iso:country":"ES",
    "sg:address":"Calle de Arrabal Del Castillo, 7",
    "sg:city":"Casarrubios Monte",
    "sg:orig_category":"Electrodom\u00c9sticos (al Por Menor)",
    "sg:phone":"+34 918 17 28 90",
    "sg:postcode":"45950",
    "sg:province":"Toledo",
    "wof:name":"Electrodomesticos Casarrubios S.l.",
    "wof:placetype":"venue"
},
  "geometry": {"coordinates":[-4.0369477272,40.1875572205],"type":"Point"}
}