{
  "type": "Feature",
  "properties": {
    "iso:country":"ES",
    "sg:address":"Carr Mossen Reig, 20",
    "sg:city":"Lleida",
    "sg:orig_category":"Caf\u00c9s, Bares, Cervecer\u00cdas",
    "sg:phone":"+34 973 24 67 17",
    "sg:postcode":"25008",
    "sg:province":"Lleida",
    "wof:name":"Mantenimiento Y Servicios Bernal S.l.",
    "wof:placetype":"venue"
},
  "geometry": {"coordinates":[0.6224020123,41.6241416931],"type":"Point"}
}