{
  "type": "Feature",
  "properties": {
    "iso:country":"ES",
    "sg:address":"Ctra. Velilla S. Antonio, Km. 0000,6",
    "sg:city":"Mejorada Campo",
    "sg:orig_category":"Aparatos E Instalaci\u00d3n De Regad\u00cdos",
    "sg:phone":"+34 916 79 43 00",
    "sg:postcode":"28840",
    "sg:province":"Madrid",
    "wof:name":"Valmont S.a.",
    "wof:placetype":"venue"
},
  "geometry": {"coordinates":[-3.4838440418,40.3967437744],"type":"Point"}
}