{
  "type": "Feature",
  "properties": {
    "iso:country":"ES",
    "sg:address":"Calle de Valle De Tobalina, 58",
    "sg:city":"Madrid",
    "sg:orig_category":"Imprenta",
    "sg:phone":"+34 917 98 16 94",
    "sg:postcode":"28021",
    "sg:province":"Madrid",
    "wof:name":"Eden Arte Grafico S.l.",
    "wof:placetype":"venue"
},
  "geometry": {"coordinates":[-3.7107729912,40.3406677246],"type":"Point"}
}