{
  "type": "Feature",
  "properties": {
    "addr:full":"Calle de Rafael De Riego, 44 Madrid Madrid 28045",
    "addr:housenumber":"44",
    "addr:postcode":"madrid;28045",
    "addr:street":"Calle De Rafael De Riego",
    "iso:country":"ES",
    "sg:address":"Calle de Rafael De Riego, 44",
    "sg:city":"Madrid",
    "sg:orig_category":"Peluqueros: De Se\u00d1oras",
    "sg:phone":"+34 914 67 23 67",
    "sg:postcode":"28045",
    "sg:province":"Madrid",
    "wof:name":"Monet S.l.",
    "wof:placetype":"venue"
},
  "geometry": {"coordinates":[-3.6925420761,40.4016189575],"type":"Point"}
}