{
  "type": "Feature",
  "properties": {
    "addr:full":"Calle de Matadero Viejo, 3 Astorga Le\u00f3n 24700",
    "addr:housenumber":"3",
    "addr:postcode":"24700",
    "addr:street":"Calle De Matadero Viejo;Leo\u0301N",
    "iso:country":"ES",
    "sg:address":"Calle de Matadero Viejo, 3",
    "sg:city":"Astorga",
    "sg:orig_category":"Florister\u00cdas",
    "sg:phone":"+34 987 61 76 26",
    "sg:postcode":"24700",
    "sg:province":"Le\u00f3n",
    "wof:name":"Alonso De Paz Maria Luciana",
    "wof:placetype":"venue"
},
  "geometry": {"coordinates":[-6.0587854385,42.458026886],"type":"Point"}
}