{
  "type": "Feature",
  "properties": {
    "addr:full":"Calle de Pablo Molina, S/n Almagro Ciudad Real 13270",
    "addr:housenumber":"s / n",
    "addr:postcode":"13270",
    "addr:street":"Calle De Pablo Molina",
    "iso:country":"ES",
    "sg:address":"Calle de Pablo Molina, S/n",
    "sg:city":"Almagro",
    "sg:orig_category":"Asociaciones Y Clubs Deportivos",
    "sg:phone":"+34 926 86 02 91",
    "sg:postcode":"13270",
    "sg:province":"Ciudad Real",
    "wof:name":"Almagro Club De Futbol",
    "wof:placetype":"venue"
},
  "geometry": {"coordinates":[-3.7232005596,38.9076309204],"type":"Point"}
}