{
  "type": "Feature",
  "properties": {
    "iso:country":"ES",
    "sg:address":"Carr Creu Del Sud, 8",
    "sg:city":"Albir",
    "sg:classifiers":[
        {
            "category":"Utilities",
            "subcategory":"Natural Gas",
            "type":"Services"
        }
    ],
    "sg:phone":"+34 966 86 42 65",
    "sg:postcode":"03580",
    "sg:province":"Alicante",
    "sg:tags":[
        "te",
        "de",
        "salones"
    ],
    "wof:name":"Boukareva  Ekaterina",
    "wof:placetype":"venue"
},
  "geometry": {"coordinates":[-0.1017019972,38.5834732056],"type":"Point"}
}