{
  "type": "Feature",
  "properties": {
    "addr:full":"Calle de Esteban Terradas (de), 7 Leganes Madrid 28914",
    "addr:housenumber":"7",
    "addr:postcode":"28914",
    "addr:street":"Calle De Esteban Terradas De",
    "iso:country":"ES",
    "sg:address":"Calle de Esteban Terradas (de), 7",
    "sg:city":"Leganes",
    "sg:orig_category":"Lavado, Limpieza De Veh\u00cdculos",
    "sg:phone":"+34 916 80 22 11",
    "sg:postcode":"28914",
    "sg:province":"Madrid",
    "wof:name":"Autoescuela Leganes S.l.",
    "wof:placetype":"venue"
},
  "geometry": {"coordinates":[-3.7496430874,40.3273696899],"type":"Point"}
}