{
  "type": "Feature",
  "properties": {
    "iso:country":"ES",
    "sg:address":"Calle de Enrique Mari\u00d1as Romero Periodista, 14",
    "sg:city":"Coru\u00d1a",
    "sg:orig_category":"Asociaciones Y Clubs Deportivos",
    "sg:phone":"+34 981 17 07 64",
    "sg:postcode":"15009",
    "sg:province":"A Coru\u00f1a",
    "wof:name":"Sicilia Sports S.l.",
    "wof:placetype":"venue"
},
  "geometry": {"coordinates":[-8.4042072296,43.3402061462],"type":"Point"}
}