{
  "type": "Feature",
  "properties": {
    "addr:full":"Miguel Astrain, 15 Iru\u00f1a Navarra 31006",
    "addr:housenumber":"15",
    "addr:postcode":"31006",
    "addr:street":"Miguel Astrain",
    "iso:country":"ES",
    "sg:address":"Miguel Astrain, 15",
    "sg:city":"Iru\u00f1a",
    "sg:orig_category":"Asesor\u00cda Sobre Comunicaci\u00d3n De Empresas",
    "sg:phone":"+34 948 15 05 64",
    "sg:postcode":"31006",
    "sg:province":"Navarra",
    "wof:name":"Compains De Carlos Francisco Javier",
    "wof:placetype":"venue"
},
  "geometry": {"coordinates":[-1.6442439556,42.8010940552],"type":"Point"}
}