{
  "type": "Feature",
  "properties": {
    "iso:country":"ES",
    "sg:address":"Calle de Floridablanca, 17",
    "sg:city":"San Lorenzo De El Escorial",
    "sg:orig_category":"Confecci\u00d3n De Trajes Para Se\u00d1oras",
    "sg:phone":"+34 918 90 71 41",
    "sg:postcode":"28200",
    "sg:province":"Madrid",
    "wof:name":"Saenz De La Torre Maria Del Rosario",
    "wof:placetype":"venue"
},
  "geometry": {"coordinates":[-4.1498670578,40.5911636353],"type":"Point"}
}