{
  "type": "Feature",
  "properties": {
    "iso:country":"ES",
    "sg:address":"Av Pi I Margall, 15",
    "sg:city":"S. Adria Besos",
    "sg:orig_category":"Asesor\u00cda De Formaci\u00d3n Y Gesti\u00d3n De Personal",
    "sg:phone":"+34 933 81 07 87",
    "sg:postcode":"08930",
    "sg:province":"Barcelona",
    "wof:name":"Assessors Poble Nou S. L.",
    "wof:placetype":"venue"
},
  "geometry": {"coordinates":[2.2157793045,41.432559967],"type":"Point"}
}