{
  "type": "Feature",
  "properties": {
    "addr:full":"Calle de Quintanar De La Orden, S/n Malaga M\u00e1laga 29014",
    "addr:housenumber":"s",
    "addr:postcode":"29014",
    "addr:street":"Calle De Quintanar De La Orden;/ N;Ma\u0301Laga",
    "iso:country":"ES",
    "sg:address":"Calle de Quintanar De La Orden, S/n",
    "sg:city":"Malaga",
    "sg:orig_category":"Peluquer\u00cdas, Peluquer\u00cda Mixta",
    "sg:phone":"+34 952 26 90 85",
    "sg:postcode":"29014",
    "sg:province":"M\u00e1laga",
    "wof:name":"Lopez Talavera Josefa",
    "wof:placetype":"venue"
},
  "geometry": {"coordinates":[-4.4216251373,36.7518501282],"type":"Point"}
}