{
  "type": "Feature",
  "properties": {
    "addr:full":"Ctra Ramal A Sabadell, 12 Poligono Barcelona 08213",
    "addr:housenumber":"12 poligono",
    "addr:postcode":"08213",
    "addr:street":"Ctra Ramal A Sabadell;Barcelona",
    "iso:country":"ES",
    "sg:address":"Ctra Ramal A Sabadell, 12",
    "sg:city":"Poligono",
    "sg:orig_category":"Productores Recolectores, Venta Directa De Vinos",
    "sg:phone":"+34 937 13 19 68",
    "sg:postcode":"08213",
    "sg:province":"Barcelona",
    "wof:name":"D.c. Virgen Blanca Scp",
    "wof:placetype":"venue"
},
  "geometry": {"coordinates":[2.1571440697,41.5534934998],"type":"Point"}
}