{
  "type": "Feature",
  "properties": {
    "addr:full":"Ctra. Masegoso, Km. 0000,2 Torija Guadalajara 19190",
    "addr:postcode":"19190",
    "addr:street":"Ctra. Masegoso Km. 0000,2",
    "iso:country":"ES",
    "sg:address":"Ctra. Masegoso, Km. 0000,2",
    "sg:city":"Torija",
    "sg:orig_category":"Fabricaci\u00d3n De Harinas, S\u00c9molas, Productos De Elaboraci\u00d3n Del Grano",
    "sg:phone":"+34 949 32 00 08",
    "sg:postcode":"19190",
    "sg:province":"Guadalajara",
    "wof:name":"Harinas Torija S.l.",
    "wof:placetype":"venue"
},
  "geometry": {"coordinates":[-3.0314040184,40.7436447144],"type":"Point"}
}