{
  "type": "Feature",
  "properties": {
    "iso:country":"ES",
    "sg:address":"Avda Conde Campomanes, 5",
    "sg:city":"Tineo",
    "sg:orig_category":"Molduras, Junquillos, Listones Y Molduras Perforadas",
    "sg:phone":"+34 985 80 01 96",
    "sg:postcode":"33870",
    "sg:province":"Asturias",
    "wof:name":"Reguera Rodriguez Manuel",
    "wof:placetype":"venue"
},
  "geometry": {"coordinates":[-6.4159798622,43.3341140747],"type":"Point"}
}