{
  "type": "Feature",
  "properties": {
    "iso:country":"ES",
    "sg:address":"Calle de Duque De Wellington, 21",
    "sg:city":"Talavera Reina",
    "sg:orig_category":"Impuestos, Tesoro P\u00dablico",
    "sg:phone":"+34 925 82 41 57",
    "sg:postcode":"45600",
    "sg:province":"Toledo",
    "wof:name":"Tasaciones Generales S.l.",
    "wof:placetype":"venue"
},
  "geometry": {"coordinates":[-4.8295860291,39.9638061523],"type":"Point"}
}