{
  "type": "Feature",
  "properties": {
    "iso:country":"ES",
    "sg:address":"Carrer de Francesc Macia, 5",
    "sg:city":"Montblanc",
    "sg:orig_category":"Laboratorios Y Cl\u00cdnicas Veterinarias",
    "sg:phone":"+34 977 86 31 73",
    "sg:postcode":"43400",
    "sg:province":"Tarragona",
    "wof:name":"Huguet Masdeu Raquel",
    "wof:placetype":"venue"
},
  "geometry": {"coordinates":[1.1643300056,41.3753395081],"type":"Point"}
}