{
  "type": "Feature",
  "properties": {
    "addr:full":"Calle de Navarra, 18 Alsasua Navarra 31800",
    "addr:housenumber":"18",
    "addr:postcode":"31800",
    "addr:street":"Calle De Navarra",
    "iso:country":"ES",
    "sg:address":"Calle de Navarra, 18",
    "sg:city":"Alsasua",
    "sg:orig_category":"Centros Empresariales",
    "sg:phone":"+34 948 46 83 07",
    "sg:postcode":"31800",
    "sg:province":"Navarra",
    "wof:name":"Asociacion De Empresarios Sakana",
    "wof:placetype":"venue"
},
  "geometry": {"coordinates":[-2.1738004684,42.8945732117],"type":"Point"}
}