{
  "type": "Feature",
  "properties": {
    "addr:full":"Calle de Covadonga, 26 Gijon Asturias 33201",
    "addr:housenumber":"26",
    "addr:postcode":"33201",
    "addr:street":"Calle De Covadonga",
    "iso:country":"ES",
    "sg:address":"Calle de Covadonga, 26",
    "sg:city":"Gijon",
    "sg:classifiers":[
        {
            "category":"Arts & Performance",
            "subcategory":"Art Gallery",
            "type":"Entertainment"
        }
    ],
    "sg:phone":"+34 985 35 38 92",
    "sg:postcode":"33201",
    "sg:province":"Asturias",
    "sg:tags":[
        "arte",
        "de",
        "galer\u00cdas"
    ],
    "wof:name":"Fernandez Junquera Maria Victoria",
    "wof:placetype":"venue"
},
  "geometry": {"coordinates":[-5.6608138084,43.5390625],"type":"Point"}
}