{
  "type": "Feature",
  "properties": {
    "addr:full":"Rua Arcebispo Lago, 6 Vilagarcia Pontevedra 36600",
    "addr:housenumber":"6",
    "addr:postcode":"36600",
    "addr:street":"Rua Arcebispo Lago",
    "iso:country":"ES",
    "sg:address":"Rua Arcebispo Lago, 6",
    "sg:city":"Vilagarcia",
    "sg:orig_category":"Zapatos (al Por Menor)",
    "sg:phone":"+34 986 50 29 61",
    "sg:postcode":"36600",
    "sg:province":"Pontevedra",
    "wof:name":"Alegret Bouzon Maria Josefa",
    "wof:placetype":"venue"
},
  "geometry": {"coordinates":[-8.7646389008,42.5916290283],"type":"Point"}
}