{
  "type": "Feature",
  "properties": {
    "addr:full":"Calle de Ceron, 4 Pegalajar Ja\u00e9n 23110",
    "addr:housenumber":"4",
    "addr:postcode":"23110",
    "addr:street":"Calle De Ceron;Jae\u0301N",
    "iso:country":"ES",
    "sg:address":"Calle de Ceron, 4",
    "sg:city":"Pegalajar",
    "sg:orig_category":"M\u00c9dicos: Estomatolog\u00cda",
    "sg:phone":"+34 953 36 11 29",
    "sg:postcode":"23110",
    "sg:province":"Ja\u00e9n",
    "wof:name":"Clinica Dental Adames S.l",
    "wof:placetype":"venue"
},
  "geometry": {"coordinates":[-3.6396489143,37.7409286499],"type":"Point"}
}