{
  "type": "Feature",
  "properties": {
    "iso:country":"ES",
    "sg:address":"Rua Cesteiros, 3",
    "sg:city":"Vigo",
    "sg:orig_category":"Molduras, Junquillos, Listones Y Molduras Perforadas",
    "sg:phone":"+34 986 22 50 02",
    "sg:postcode":"36202",
    "sg:province":"Pontevedra",
    "wof:name":"Gomez Garcia Juan",
    "wof:placetype":"venue"
},
  "geometry": {"coordinates":[-8.7262763977,42.2387008667],"type":"Point"}
}