{
  "type": "Feature",
  "properties": {
    "iso:country":"ES",
    "sg:address":"Cmno Pereiras, 23",
    "sg:city":"Pereiras",
    "sg:orig_category":"Molduras, Junquillos, Listones Y Molduras Perforadas",
    "sg:phone":"+34 988 43 66 30",
    "sg:postcode":"32690",
    "sg:province":"Ourense",
    "wof:name":"Alvarez Gestal Josefa",
    "wof:placetype":"venue"
},
  "geometry": {"coordinates":[-7.8252038956,42.2414588928],"type":"Point"}
}