{
  "type": "Feature",
  "properties": {
    "iso:country":"ES",
    "sg:address":"Avda Madrid, 11",
    "sg:city":"Estacion",
    "sg:orig_category":"Mec\u00c1nico Del Autom\u00d3vil",
    "sg:phone":"+34 975 32 60 29",
    "sg:postcode":"42240",
    "sg:province":"Soria",
    "wof:name":"Talleres Y Gruas Vicente S.l.",
    "wof:placetype":"venue"
},
  "geometry": {"coordinates":[-2.4224789143,41.1619491577],"type":"Point"}
}