{
  "type": "Feature",
  "properties": {
    "iso:country":"ES",
    "sg:address":"Calle de Juan Carlos I, S/n",
    "sg:city":"Puerto Del Carmen",
    "sg:orig_category":"Distribuci\u00d3n De Petr\u00d3leo Y Derivados",
    "sg:phone":"+34 928 51 40 90",
    "sg:postcode":"35510",
    "sg:province":"Las Palmas",
    "wof:name":"Hijos De Rafael Ramirez C.b.",
    "wof:placetype":"venue"
},
  "geometry": {"coordinates":[-13.6651935577,28.9252700806],"type":"Point"}
}