{
  "type": "Feature",
  "properties": {
    "addr:full":"Avda Espa\u00d1a (de), 23 Coslada Madrid 28820",
    "addr:housenumber":"23",
    "addr:postcode":"28820",
    "addr:street":"Avda Espan\u0303A De",
    "iso:country":"ES",
    "sg:address":"Avda Espa\u00d1a (de), 23",
    "sg:city":"Coslada",
    "sg:orig_category":"Ingenier\u00cda, Centros De Estudios (diversos)",
    "sg:phone":"+34 916 60 12 22",
    "sg:postcode":"28820",
    "sg:province":"Madrid",
    "wof:name":"Techno Consulting S L",
    "wof:placetype":"venue"
},
  "geometry": {"coordinates":[-3.5637459755,40.4216270447],"type":"Point"}
}