{
  "type": "Feature",
  "properties": {
    "addr:full":"Pg Pau (la), 3 Berga-ciudad Barcelona 08600",
    "addr:housenumber":"3",
    "addr:postcode":"08600",
    "addr:street":"Pg Pau La;Barcelona",
    "iso:country":"ES",
    "sg:address":"Pg Pau (la), 3",
    "sg:city":"Berga-ciudad",
    "sg:orig_category":"Cajas De Ahorro",
    "sg:phone":"+34 938 21 41 51",
    "sg:postcode":"08600",
    "sg:province":"Barcelona",
    "sg:website":"www.caixapenedes.com",
    "wof:name":"Caixa D'estalvis Del Penedes",
    "wof:placetype":"venue"
},
  "geometry": {"coordinates":[1.8440099955,42.1012611389],"type":"Point"}
}