{
  "type": "Feature",
  "properties": {
    "iso:country":"ES",
    "sg:address":"Avda Ramon Y Cajal, 16",
    "sg:city":"Ubeda",
    "sg:orig_category":"Ortopedia General",
    "sg:phone":"+34 953 75 02 50",
    "sg:postcode":"23400",
    "sg:province":"Ja\u00e9n",
    "wof:name":"Cobo Arjona Nicolasa",
    "wof:placetype":"venue"
},
  "geometry": {"coordinates":[-3.3742790222,38.0142402649],"type":"Point"}
}