{
  "type": "Feature",
  "properties": {
    "addr:full":"Avda General Peron, 38 Madrid Madrid 28020",
    "addr:housenumber":"38",
    "addr:postcode":"madrid;28020",
    "addr:street":"Avda General Peron",
    "iso:country":"ES",
    "sg:address":"Avda General Peron, 38",
    "sg:city":"Madrid",
    "sg:orig_category":"Inform\u00c1tica: Material Y Suministros",
    "sg:phone":"+34 914 49 11 00",
    "sg:postcode":"28020",
    "sg:province":"Madrid",
    "sg:website":"www.hds.com",
    "wof:name":"Hitachi Data Systems",
    "wof:placetype":"venue"
},
  "geometry": {"coordinates":[-3.6928467751,40.4521903992],"type":"Point"}
}