{
  "type": "Feature",
  "properties": {
    "iso:country":"ES",
    "sg:address":"Avda Mejico (de), 4",
    "sg:city":"Jerez De La Frontera",
    "sg:orig_category":"Asesor\u00cda Fiscal Y Jur\u00cddica",
    "sg:phone":"+34 956 33 89 29",
    "sg:postcode":"11405",
    "sg:province":"C\u00e1diz",
    "wof:name":"Asesoramiento Empresarial Jerez S.l.",
    "wof:placetype":"venue"
},
  "geometry": {"coordinates":[-6.1277475357,36.6917610168],"type":"Point"}
}