{
  "type": "Feature",
  "properties": {
    "addr:full":"Kale Nagusia, 5 Idiazabal Guip\u00f9zcoa 20213",
    "addr:housenumber":"5",
    "addr:postcode":"20213",
    "addr:street":"Kale Nagusia;Guipu\u0300Zcoa",
    "iso:country":"ES",
    "sg:address":"Kale Nagusia, 5",
    "sg:city":"Idiazabal",
    "sg:orig_category":"Molduras, Junquillos, Listones Y Molduras Perforadas",
    "sg:phone":"+34 943 18 70 35",
    "sg:postcode":"20213",
    "sg:province":"Guip\u00f9zcoa",
    "wof:name":"Mendizabal Goiburu Martin",
    "wof:placetype":"venue"
},
  "geometry": {"coordinates":[-2.2322790623,43.0144882202],"type":"Point"}
}