{
  "type": "Feature",
  "properties": {
    "iso:country":"ES",
    "sg:address":"Calle de Andres Lopez Palmeiro, 10",
    "sg:city":"Ferreira",
    "sg:orig_category":"Peluquer\u00cdas, Peluquer\u00cda Mixta",
    "sg:phone":"+34 982 57 42 91",
    "sg:postcode":"27770",
    "sg:province":"Lugo",
    "wof:name":"Vazquez Folgueira Sania",
    "wof:placetype":"venue"
},
  "geometry": {"coordinates":[-7.4409780502,43.5506782532],"type":"Point"}
}