{
  "type": "Feature",
  "properties": {
    "addr:full":"Avda Valladolid, 38 Valencia Valencia 46020",
    "addr:housenumber":"38",
    "addr:postcode":"46020",
    "addr:street":"Avda Valladolid",
    "iso:country":"ES",
    "sg:address":"Avda Valladolid, 38",
    "sg:city":"Valencia",
    "sg:orig_category":"Papeler\u00cdas, Librer\u00cdas",
    "sg:phone":"+34 963 60 71 92",
    "sg:postcode":"46020",
    "sg:province":"Valencia",
    "wof:name":"Mu\u00f1oz Esteban Juan Esteban",
    "wof:placetype":"venue"
},
  "geometry": {"coordinates":[-0.3584100008,39.4885749817],"type":"Point"}
}