{
  "type": "Feature",
  "properties": {
    "iso:country":"ES",
    "sg:address":"Calle de Jilguero, 1",
    "sg:city":"Madrid",
    "sg:orig_category":"Fabricaci\u00d3n De Papel Pintado",
    "sg:phone":"+34 915 25 53 79",
    "sg:postcode":"28025",
    "sg:province":"Madrid",
    "wof:name":"Lopez Gauli,jose Ramon 000452967k S.l.n.e",
    "wof:placetype":"venue"
},
  "geometry": {"coordinates":[-3.7302999496,40.3839874268],"type":"Point"}
}