{
  "type": "Feature",
  "properties": {
    "iso:country":"ES",
    "sg:address":"Calle de Marcos Grijalvo, 18",
    "sg:city":"Sestao",
    "sg:orig_category":"Asociaciones, Organismos Culturales Y Socioeducativos",
    "sg:phone":"+34 944 01 28 83",
    "sg:postcode":"48910",
    "sg:province":"Vizcaya",
    "wof:name":"Edex Scoop Ltada",
    "wof:placetype":"venue"
},
  "geometry": {"coordinates":[-2.9989318848,43.3091773987],"type":"Point"}
}