{
  "type": "Feature",
  "properties": {
    "addr:full":"Calle de Real, 36 Valdepe\u00f1as Ciudad Real 13300",
    "addr:housenumber":"36",
    "addr:postcode":"13300",
    "addr:street":"Calle De Real",
    "iso:country":"ES",
    "sg:address":"Calle de Real, 36",
    "sg:city":"Valdepe\u00f1as",
    "sg:orig_category":"Fabricaci\u00d3n De Acumuladores Y De Pilas El\u00c9ctricas",
    "sg:phone":"+34 926 32 52 49",
    "sg:postcode":"13300",
    "sg:province":"Ciudad Real",
    "wof:name":"Barcenas Lopez Antonia",
    "wof:placetype":"venue"
},
  "geometry": {"coordinates":[-3.3827579021,38.7637901306],"type":"Point"}
}