{
  "type": "Feature",
  "properties": {
    "addr:full":"Carr Castello, 28 Figueres Girona 17600",
    "addr:housenumber":"28",
    "addr:postcode":"17600",
    "addr:street":"Carr Castello",
    "iso:country":"ES",
    "sg:address":"Carr Castello, 28",
    "sg:city":"Figueres",
    "sg:orig_category":"Agencias De Viajes",
    "sg:phone":"+34 972 51 36 10",
    "sg:postcode":"17600",
    "sg:province":"Girona",
    "sg:website":"www.barceloviajes.com",
    "wof:name":"Comer\u00d1 Viatges I Telecomunicacions S.l.",
    "wof:placetype":"venue"
},
  "geometry": {"coordinates":[2.964402914,42.2657318115],"type":"Point"}
}