{
  "type": "Feature",
  "properties": {
    "iso:country":"ES",
    "sg:address":"Calle de Salcillo, 7",
    "sg:city":"Mostoles",
    "sg:orig_category":"Art\u00cdculos De Decoraci\u00d3n (fabricaci\u00d3n Y Al Por Mayor)",
    "sg:phone":"+34 916 18 27 30",
    "sg:postcode":"28932",
    "sg:province":"Madrid",
    "wof:name":"Santos Perea Josefa",
    "wof:placetype":"venue"
},
  "geometry": {"coordinates":[-3.8647370338,40.3339309692],"type":"Point"}
}