{
  "type": "Feature",
  "properties": {
    "iso:country":"ES",
    "sg:address":"C/ Poeta Miguel Hernandez, 21",
    "sg:city":"Elche",
    "sg:orig_category":"Lencer\u00cda Femenina, Corseter\u00cda, Trajes De Ba\u00d1o (al Por Menor)",
    "sg:phone":"+34 966 66 13 07",
    "sg:postcode":"03201",
    "sg:province":"Alicante",
    "wof:name":"Clos Garcia Luisa Maria",
    "wof:placetype":"venue"
},
  "geometry": {"coordinates":[-0.7044330239,38.264289856],"type":"Point"}
}