{
  "type": "Feature",
  "properties": {
    "addr:full":"Calle de Villa De Artes, 7 Almeria Almer\u00eda 04006",
    "addr:housenumber":"7",
    "addr:postcode":"04006",
    "addr:street":"Calle De Villa De Artes",
    "iso:country":"ES",
    "sg:address":"Calle de Villa De Artes, 7",
    "sg:city":"Almeria",
    "sg:orig_category":"Puertas Y Portales",
    "sg:phone":"+34 950 22 76 28",
    "sg:postcode":"04006",
    "sg:province":"Almer\u00eda",
    "wof:name":"Morales Rodriguez Manuel",
    "wof:placetype":"venue"
},
  "geometry": {"coordinates":[-2.4463889599,36.8444595337],"type":"Point"}
}