{
  "type": "Feature",
  "properties": {
    "addr:full":"Calle de Azuela, S/n Estacion Madrid 28400",
    "addr:postcode":"28400",
    "addr:street":"Calle De Azuela S / N Estacion",
    "iso:country":"ES",
    "sg:address":"Calle de Azuela, S/n",
    "sg:city":"Estacion",
    "sg:orig_category":"Agencias De Viajes",
    "sg:phone":"+34 918 49 08 95",
    "sg:postcode":"28400",
    "sg:province":"Madrid",
    "wof:name":"Proyectos Insulares Turisticos S.l.",
    "wof:placetype":"venue"
},
  "geometry": {"coordinates":[-3.7003455162,40.4166908264],"type":"Point"}
}