{
  "type": "Feature",
  "properties": {
    "addr:full":"Calle de Urbasa, 10 Alsasua Navarra 31800",
    "addr:housenumber":"10",
    "addr:postcode":"31800",
    "addr:street":"Calle De Urbasa",
    "iso:country":"ES",
    "sg:address":"Calle de Urbasa, 10",
    "sg:city":"Alsasua",
    "sg:orig_category":"Ense\u00d1anza Variada",
    "sg:phone":"+34 948 46 71 31",
    "sg:postcode":"31800",
    "sg:province":"Navarra",
    "wof:name":"Garcia Gomez Maria De La Encarnacion",
    "wof:placetype":"venue"
},
  "geometry": {"coordinates":[-2.1732690334,42.8930206299],"type":"Point"}
}