{
  "type": "Feature",
  "properties": {
    "iso:country":"ES",
    "sg:address":"Calle de Pepe Jimenez, 40",
    "sg:city":"Rute",
    "sg:orig_category":"Muebles",
    "sg:phone":"+34 957 53 88 20",
    "sg:postcode":"14960",
    "sg:province":"C\u00f3rdoba",
    "wof:name":"Tapizados Ja S.l.",
    "wof:placetype":"venue"
},
  "geometry": {"coordinates":[-4.36434412,37.3276290894],"type":"Point"}
}