{
  "type": "Feature",
  "properties": {
    "iso:country":"ES",
    "sg:address":"Riu Ripoll, S/n",
    "sg:city":"Sabadell",
    "sg:orig_category":"Fabricaci\u00d3n De Telas Y Sedas",
    "sg:phone":"+34 937 25 53 77",
    "sg:postcode":"08202",
    "sg:province":"Barcelona",
    "wof:name":"Cincotex S.l.",
    "wof:placetype":"venue"
},
  "geometry": {"coordinates":[2.1166799068,41.5489044189],"type":"Point"}
}