{
  "type": "Feature",
  "properties": {
    "iso:country":"ES",
    "sg:address":"Calle de Torno, 16",
    "sg:city":"Gijon",
    "sg:orig_category":"Heladeros",
    "sg:phone":"+34 985 30 01 29",
    "sg:postcode":"33213",
    "sg:province":"Asturias",
    "wof:name":"Rodriguez Perez Manuel",
    "wof:placetype":"venue"
},
  "geometry": {"coordinates":[-5.7038559914,43.5403022766],"type":"Point"}
}