{
  "type": "Feature",
  "properties": {
    "addr:full":"Avda Cospeito, S/n Muimenta Lugo 27377",
    "addr:housenumber":"s / n",
    "addr:postcode":"27377",
    "addr:street":"Avda Cospeito",
    "iso:country":"ES",
    "sg:address":"Avda Cospeito, S/n",
    "sg:city":"Muimenta",
    "sg:orig_category":"Molduras, Junquillos, Listones Y Molduras Perforadas",
    "sg:phone":"+34 982 52 80 64",
    "sg:postcode":"27377",
    "sg:province":"Lugo",
    "wof:name":"Anido Perez Jose Luis",
    "wof:placetype":"venue"
},
  "geometry": {"coordinates":[-7.5558514595,43.0120849609],"type":"Point"}
}