{
  "type": "Feature",
  "properties": {
    "iso:country":"ES",
    "sg:address":"C/ Manuel Vicente Pastor, 28",
    "sg:city":"Elche",
    "sg:orig_category":"Empresarios",
    "sg:phone":"+34 965 43 50 52",
    "sg:postcode":"03206",
    "sg:province":"Alicante",
    "wof:name":"Fundacion Secretariado Gitano",
    "wof:placetype":"venue"
},
  "geometry": {"coordinates":[-0.7049970031,38.2715072632],"type":"Point"}
}