{
  "type": "Feature",
  "properties": {
    "addr:full":"C/ Jaume Armengol, 33 Inca Islas Baleares 07300",
    "addr:housenumber":"33",
    "addr:postcode":"07300",
    "addr:street":"C / Jaume Armengol",
    "iso:country":"ES",
    "sg:address":"C/ Jaume Armengol, 33",
    "sg:city":"Inca",
    "sg:orig_category":"Arquitectos",
    "sg:phone":"+34 971 50 48 00",
    "sg:postcode":"07300",
    "sg:province":"Islas Baleares",
    "wof:name":"Dentol 96 S.l.",
    "wof:placetype":"venue"
},
  "geometry": {"coordinates":[2.9096019268,39.720375061],"type":"Point"}
}