{
  "type": "Feature",
  "properties": {
    "addr:full":"Calle de Juan Xxiii, 8 Torredonjimeno Ja\u00e9n 23650",
    "addr:housenumber":"8",
    "addr:postcode":"23650",
    "addr:street":"Calle De Juan Xxiii",
    "iso:country":"ES",
    "sg:address":"Calle de Juan Xxiii, 8",
    "sg:city":"Torredonjimeno",
    "sg:orig_category":"Tapicer\u00cdas",
    "sg:phone":"+34 953 34 20 83",
    "sg:postcode":"23650",
    "sg:province":"Ja\u00e9n",
    "wof:name":"Tapizados Hogar Sofa S.l.",
    "wof:placetype":"venue"
},
  "geometry": {"coordinates":[-3.9509680271,37.7609634399],"type":"Point"}
}