{
  "type": "Feature",
  "properties": {
    "iso:country":"ES",
    "sg:address":"Calle de Coso Alto, 43",
    "sg:city":"Huesca",
    "sg:orig_category":"Molduras, Junquillos, Listones Y Molduras Perforadas",
    "sg:phone":"+34 974 22 02 72",
    "sg:postcode":"22003",
    "sg:province":"Huesca",
    "wof:name":"Sanagustin Lopez Angel",
    "wof:placetype":"venue"
},
  "geometry": {"coordinates":[-0.4104380906,42.1392211914],"type":"Point"}
}