{
  "type": "Feature",
  "properties": {
    "addr:full":"Avda Paz, 4 Martos Ja\u00e9n 23600",
    "addr:housenumber":"4",
    "addr:postcode":"23600",
    "addr:street":"Avda Paz;Jae\u0301N",
    "iso:country":"ES",
    "sg:address":"Avda Paz, 4",
    "sg:city":"Martos",
    "sg:orig_category":"Perfumer\u00cda (al Por Menor)",
    "sg:phone":"+34 953 55 47 84",
    "sg:postcode":"23600",
    "sg:province":"Ja\u00e9n",
    "wof:name":"Sociedad Cooperativa Andaluza Drogasur",
    "wof:placetype":"venue"
},
  "geometry": {"coordinates":[-3.9743449688,37.7203979492],"type":"Point"}
}