{
  "type": "Feature",
  "properties": {
    "iso:country":"ES",
    "sg:address":"Carr Castella, 26",
    "sg:city":"Eivissa",
    "sg:orig_category":"Quincaller\u00cda (al Por Menor)",
    "sg:phone":"+34 971 30 28 68",
    "sg:postcode":"07800",
    "sg:province":"Islas Baleares",
    "wof:name":"Brico-tina S.l.",
    "wof:placetype":"venue"
},
  "geometry": {"coordinates":[1.4274439812,38.9096870422],"type":"Point"}
}