{
  "type": "Feature",
  "properties": {
    "addr:full":"Calle de Alba (del), 30 Marbella M\u00e1laga 29600",
    "addr:housenumber":"30",
    "addr:postcode":"29600",
    "addr:street":"Calle De Alba Del;Ma\u0301Laga",
    "iso:country":"ES",
    "sg:address":"Calle de Alba (del), 30",
    "sg:city":"Marbella",
    "sg:orig_category":"Frutas, Legumbres Frescas Y Tempranas (al Por Menor)",
    "sg:phone":"+34 952 86 23 25",
    "sg:postcode":"29600",
    "sg:province":"M\u00e1laga",
    "wof:name":"Fernandez Fernandez Diego",
    "wof:placetype":"venue"
},
  "geometry": {"coordinates":[-4.8813419342,36.5124855042],"type":"Point"}
}