{
  "type": "Feature",
  "properties": {
    "iso:country":"ES",
    "sg:address":"Carrer de Sardenya, 116",
    "sg:city":"Barcelona",
    "sg:orig_category":"Comerciantes Al Por Mayor De Vinos, Licores Y Alcoholes",
    "sg:phone":"+34 933 00 90 90",
    "sg:postcode":"08018",
    "sg:province":"Barcelona",
    "wof:name":"Perez Lago Manuel",
    "wof:placetype":"venue"
},
  "geometry": {"coordinates":[2.1861059666,41.3939323425],"type":"Point"}
}