{
  "type": "Feature",
  "properties": {
    "iso:country":"ES",
    "sg:address":"Calle de Foncalada, 11",
    "sg:city":"Oviedo",
    "sg:orig_category":"Promotores Constructores",
    "sg:phone":"+34 985 21 10 95",
    "sg:postcode":"33002",
    "sg:province":"Asturias",
    "wof:name":"Cogarnol S.a.",
    "wof:placetype":"venue"
},
  "geometry": {"coordinates":[-5.8465628624,43.3650856018],"type":"Point"}
}