{
  "type": "Feature",
  "properties": {
    "iso:country":"ES",
    "sg:address":"Carrer de Cial Cerro De La Comadre, S/n",
    "sg:city":"Bormujos",
    "sg:orig_category":"Centros Comerciales Y Grandes Tiendas",
    "sg:phone":"+34 955 72 37 20",
    "sg:postcode":"41930",
    "sg:province":"Sevilla",
    "wof:name":"Factory Outlet Aljarafe S.l.",
    "wof:placetype":"venue"
},
  "geometry": {"coordinates":[-6.0711288452,37.3726081848],"type":"Point"}
}