{
  "type": "Feature",
  "properties": {
    "addr:full":"Calle de Nicolas Rabal, 23 Soria Soria 42003",
    "addr:housenumber":"23",
    "addr:postcode":"42003",
    "addr:street":"Calle De Nicolas Rabal",
    "iso:country":"ES",
    "sg:address":"Calle de Nicolas Rabal, 23",
    "sg:city":"Soria",
    "sg:orig_category":"Ingenier\u00cda, Centros De Estudios (diversos)",
    "sg:phone":"+34 975 22 79 80",
    "sg:postcode":"42003",
    "sg:province":"Soria",
    "wof:name":"Romo Lagunas Fidel",
    "wof:placetype":"venue"
},
  "geometry": {"coordinates":[-2.4727458954,41.7628631592],"type":"Point"}
}