{
  "type": "Feature",
  "properties": {
    "iso:country":"ES",
    "sg:address":"Calle de Jimenez Aranda, 19",
    "sg:city":"Sevilla",
    "sg:orig_category":"Fabricaci\u00d3n, Venta De Cuadros, Accesorios Para Enmarcar",
    "sg:phone":"+34 954 41 21 82",
    "sg:postcode":"41018",
    "sg:province":"Sevilla",
    "wof:name":"Rojas Alvarez Osorio Luis",
    "wof:placetype":"venue"
},
  "geometry": {"coordinates":[-5.9811959267,37.3857002258],"type":"Point"}
}