{
  "type": "Feature",
  "properties": {
    "iso:country":"ES",
    "sg:address":"Carrer de Infant Marti (l'), 175",
    "sg:city":"Terrassa",
    "sg:orig_category":"Agencias De Viajes",
    "sg:phone":"+34 937 88 86 20",
    "sg:postcode":"08224",
    "sg:province":"Barcelona",
    "sg:website":"www.giramundo.es",
    "wof:name":"Vi & Va Tarrasa S.l.",
    "wof:placetype":"venue"
},
  "geometry": {"coordinates":[2.002985239,41.5579414368],"type":"Point"}
}