{
  "type": "Feature",
  "properties": {
    "iso:country":"ES",
    "sg:address":"Ctra. Torrijos, Km. 0001,8",
    "sg:city":"Gerindote",
    "sg:orig_category":"Negocio De Materiales De Construcci\u00d3n",
    "sg:phone":"+34 925 77 10 74",
    "sg:postcode":"45518",
    "sg:province":"Toledo",
    "wof:name":"Sanchez Pinel S.l.",
    "wof:placetype":"venue"
},
  "geometry": {"coordinates":[-4.3021659851,39.9683151245],"type":"Point"}
}