{
  "type": "Feature",
  "properties": {
    "addr:full":"Avda Constitucion, 74 Villa Don Fadrique Toledo 45850",
    "addr:housenumber":"74",
    "addr:postcode":"45850",
    "addr:street":"Avda Constitucion",
    "iso:country":"ES",
    "sg:address":"Avda Constitucion, 74",
    "sg:city":"Villa Don Fadrique",
    "sg:orig_category":"Mec\u00c1nico Del Autom\u00d3vil",
    "sg:phone":"+34 925 19 52 44",
    "sg:postcode":"45850",
    "sg:province":"Toledo",
    "wof:name":"Mu\u00f1oz Izquierdo Juan",
    "wof:placetype":"venue"
},
  "geometry": {"coordinates":[-3.2279889584,39.6153907776],"type":"Point"}
}