{
  "type": "Feature",
  "properties": {
    "iso:country":"ES",
    "sg:address":"Joan Iturralde Kalea, 1",
    "sg:city":"Beasain",
    "sg:orig_category":"Arquitectos",
    "sg:phone":"+34 943 16 05 43",
    "sg:postcode":"20200",
    "sg:province":"Guip\u00f9zcoa",
    "wof:name":"Armendariz Leunda Miguel",
    "wof:placetype":"venue"
},
  "geometry": {"coordinates":[-2.1962630749,43.0464515686],"type":"Point"}
}