{
  "type": "Feature",
  "properties": {
    "iso:country":"ES",
    "sg:address":"Calle de Duquesa De La Victoria, 30",
    "sg:city":"Logro\u00f1o",
    "sg:orig_category":"Administradores De Bienes Y Delegados De Comunidades De Propietarios",
    "sg:phone":"+34 941 25 31 67",
    "sg:postcode":"26003",
    "sg:province":"La Rioja",
    "wof:name":"Gonzalez Camara Alfonso",
    "wof:placetype":"venue"
},
  "geometry": {"coordinates":[-2.4391133785,42.4647941589],"type":"Point"}
}