{
  "type": "Feature",
  "properties": {
    "addr:full":"Avda Mahia, 24 Bertamirans La Coru\u00f1a 15220",
    "addr:housenumber":"24",
    "addr:postcode":"15220",
    "addr:street":"Avda Mahia;La Corun\u0303A",
    "iso:country":"ES",
    "sg:address":"Avda Mahia, 24",
    "sg:city":"Bertamirans",
    "sg:orig_category":"Farmacias",
    "sg:phone":"+34 981 88 30 35",
    "sg:postcode":"15220",
    "sg:province":"La Coru\u00f1a",
    "wof:name":"Rodriguez Garcia Antonio",
    "wof:placetype":"venue"
},
  "geometry": {"coordinates":[-8.6575126648,42.8574981689],"type":"Point"}
}