{
  "type": "Feature",
  "properties": {
    "addr:full":"Urb Linda Vista Baja, 237 San Pedro Alcantara M\u00e1laga 29670",
    "addr:housenumber":"237",
    "addr:postcode":"29670",
    "addr:street":"Urb Linda Vista Baja",
    "iso:country":"ES",
    "sg:address":"Urb Linda Vista Baja, 237",
    "sg:city":"San Pedro Alcantara",
    "sg:orig_category":"Complementos De Vestir (al Por Menor)",
    "sg:phone":"+34 952 78 17 59",
    "sg:postcode":"29670",
    "sg:province":"M\u00e1laga",
    "wof:name":"Zudor Y Losadi S.l.",
    "wof:placetype":"venue"
},
  "geometry": {"coordinates":[-4.9894766808,36.4856033325],"type":"Point"}
}