{
  "type": "Feature",
  "properties": {
    "iso:country":"ES",
    "sg:address":"Luga Belonga, S/n",
    "sg:city":"Belonga",
    "sg:orig_category":"Autob\u00das (explotaci\u00d3n Y Servicios De)",
    "sg:phone":"+34 985 79 77 68",
    "sg:postcode":"33193",
    "sg:province":"Asturias",
    "wof:name":"Autos Vazquez Sl",
    "wof:placetype":"venue"
},
  "geometry": {"coordinates":[-5.9832577705,43.2504386902],"type":"Point"}
}