{
  "type": "Feature",
  "properties": {
    "iso:country":"ES",
    "sg:address":"Avda Sandoval, 9",
    "sg:city":"Santiago Ribera",
    "sg:orig_category":"Camiser\u00cda Y Ropa Interior Masculina (al Por Menor)",
    "sg:phone":"+34 968 57 37 93",
    "sg:postcode":"30720",
    "sg:province":"Murcia",
    "sg:website":"www.barabu.com",
    "wof:name":"Del Rio Larregui Mari Cruz",
    "wof:placetype":"venue"
},
  "geometry": {"coordinates":[-0.8055070043,37.7973518372],"type":"Point"}
}