{
  "type": "Feature",
  "properties": {
    "iso:country":"ES",
    "sg:address":"Carrer de Ribera D'ebre, S/n",
    "sg:city":"Mora Nova",
    "sg:orig_category":"Electricidad: Instaladores",
    "sg:phone":"+34 977 40 28 51",
    "sg:postcode":"43770",
    "sg:province":"Tarragona",
    "wof:name":"Maessa",
    "wof:placetype":"venue"
},
  "geometry": {"coordinates":[1.2431160212,41.1229705811],"type":"Point"}
}