{
  "type": "Feature",
  "properties": {
    "iso:country":"ES",
    "sg:address":"Pase Cementerio, 4",
    "sg:city":"Villarrobledo",
    "sg:classifiers":[
        {
            "category":"Taxi",
            "type":"Transportation"
        }
    ],
    "sg:phone":"+34 967 14 27 28",
    "sg:postcode":"02600",
    "sg:province":"Albacete",
    "wof:name":"Ossa Rubio Mariano De La",
    "wof:placetype":"venue"
},
  "geometry": {"coordinates":[-2.6100869179,39.2708854675],"type":"Point"}
}