{
  "type": "Feature",
  "properties": {
    "addr:full":"Cmno Carril, 63 Vera Santa Cruz De Tenerife 38400",
    "addr:housenumber":"63",
    "addr:postcode":"38400",
    "addr:street":"Cmno Carril",
    "iso:country":"ES",
    "sg:address":"Cmno Carril, 63",
    "sg:city":"Vera",
    "sg:orig_category":"Centros P\u00dablicos De Formaci\u00d3n Profesional Y T\u00c9cnica",
    "sg:phone":"+34 922 37 13 95",
    "sg:postcode":"38400",
    "sg:province":"Santa Cruz De Tenerife",
    "wof:name":"Gobierno De Canarias",
    "wof:placetype":"venue"
},
  "geometry": {"coordinates":[-16.5473842621,28.4141807556],"type":"Point"}
}