{
  "type": "Feature",
  "properties": {
    "addr:full":"Pase Artiga Ibilbidea, 54 Irun Guip\u00f9zcoa 20303",
    "addr:housenumber":"54",
    "addr:postcode":"20303",
    "addr:street":"Artiga Ibilbidea;Guipu\u0300Zcoa",
    "iso:country":"ES",
    "sg:address":"Pase Artiga Ibilbidea, 54",
    "sg:city":"Irun",
    "sg:orig_category":"Suministros Para Carrocer\u00cdas",
    "sg:phone":"+34 943 62 71 83",
    "sg:postcode":"20303",
    "sg:province":"Guip\u00f9zcoa",
    "wof:name":"Carrocerias Bel-bar C.b.",
    "wof:placetype":"venue"
},
  "geometry": {"coordinates":[-1.7902339697,43.3395233154],"type":"Point"}
}