{
  "type": "Feature",
  "properties": {
    "addr:full":"Calle de Escultor Viciano, 27 Castellon Castell\u00f3n 12002",
    "addr:housenumber":"27",
    "addr:postcode":"12002",
    "addr:street":"Calle De Escultor Viciano",
    "iso:country":"ES",
    "sg:address":"Calle de Escultor Viciano, 27",
    "sg:city":"Castellon",
    "sg:orig_category":"Librer\u00cdas",
    "sg:phone":"+34 964 23 95 99",
    "sg:postcode":"12002",
    "sg:province":"Castell\u00f3n",
    "wof:name":"Gonzalez Miguelez Jesus",
    "wof:placetype":"venue"
},
  "geometry": {"coordinates":[-0.0357340015,39.9838294983],"type":"Point"}
}