{
  "type": "Feature",
  "properties": {
    "iso:country":"ES",
    "sg:address":"Calle de Pablo Picasso, S/n",
    "sg:city":"Madrigueras",
    "sg:orig_category":"Centros De Educaci\u00d3n Especial",
    "sg:phone":"+34 967 48 42 05",
    "sg:postcode":"02230",
    "sg:province":"Albacete",
    "wof:name":"Colegio Publico Constitucion Espa\u00f1ola",
    "wof:placetype":"venue"
},
  "geometry": {"coordinates":[-1.7989289761,39.2405700684],"type":"Point"}
}