{
  "type": "Feature",
  "properties": {
    "iso:country":"ES",
    "sg:address":"Calle de Poligono Industrial El Pabellon, S/n",
    "sg:city":"Jerez De Los Caballeros",
    "sg:orig_category":"Fabrica De Charcuter\u00cda",
    "sg:phone":"+34 924 75 06 66",
    "sg:postcode":"06380",
    "sg:province":"Badajoz",
    "wof:name":"Industrias Carnicas El Bellotero S.a.",
    "wof:placetype":"venue"
},
  "geometry": {"coordinates":[-6.7662930489,38.3218612671],"type":"Point"}
}