{
  "type": "Feature",
  "properties": {
    "addr:full":"Avda Covibar (de), 8 Partija-santa Monica Madrid 28529",
    "addr:postcode":"28529",
    "addr:street":"Avda Covibar De 8 Partija-Santa",
    "iso:country":"ES",
    "sg:address":"Avda Covibar (de), 8",
    "sg:city":"Partija-santa Monica",
    "sg:orig_category":"Institutos De Belleza",
    "sg:phone":"+34 916 66 53 55",
    "sg:postcode":"28529",
    "sg:province":"Madrid",
    "wof:name":"Perez Encina Almudena",
    "wof:placetype":"venue"
},
  "geometry": {"coordinates":[-3.5102670193,40.314289093],"type":"Point"}
}