{
  "type": "Feature",
  "properties": {
    "iso:country":"ES",
    "sg:address":"Carrer de Barcelona (de), 62",
    "sg:city":"Salou",
    "sg:orig_category":"Mercer\u00cda, Lencer\u00cda (al Por Menor)",
    "sg:phone":"+34 977 38 31 46",
    "sg:postcode":"43840",
    "sg:province":"Tarragona",
    "wof:name":"Jimenez Barradon Maria Isabel",
    "wof:placetype":"venue"
},
  "geometry": {"coordinates":[1.1319390535,41.0825767517],"type":"Point"}
}