{
  "type": "Feature",
  "properties": {
    "addr:full":"Calle de Conde De Gondomar, 11 Cordoba C\u00f3rdoba 14003",
    "addr:housenumber":"11",
    "addr:postcode":"14003",
    "addr:street":"Calle De Conde De Gondomar;Co\u0301Rdoba",
    "iso:country":"ES",
    "sg:address":"Calle de Conde De Gondomar, 11",
    "sg:city":"Cordoba",
    "sg:orig_category":"Abogados Especialistas En Derecho Penal",
    "sg:phone":"+34 957 49 05 88",
    "sg:postcode":"14003",
    "sg:province":"C\u00f3rdoba",
    "wof:name":"Moreno Corpas Miguel",
    "wof:placetype":"venue"
},
  "geometry": {"coordinates":[-4.7811522484,37.8845977783],"type":"Point"}
}