{
  "type": "Feature",
  "properties": {
    "addr:full":"Calle de Montera, 4 Benidorm Alicante 03500",
    "addr:housenumber":"4",
    "addr:postcode":"03500",
    "addr:street":"Calle De Montera",
    "iso:country":"ES",
    "sg:address":"Calle de Montera, 4",
    "sg:city":"Benidorm",
    "sg:orig_category":"Agencias De Viajes",
    "sg:phone":"+34 966 83 10 82",
    "sg:postcode":"03500",
    "sg:province":"Alicante",
    "sg:website":"www.touristservei.com",
    "wof:name":"Benidorm Travel Services S.l.",
    "wof:placetype":"venue"
},
  "geometry": {"coordinates":[-0.1331110001,38.5429534912],"type":"Point"}
}