{
  "type": "Feature",
  "properties": {
    "iso:country":"ES",
    "sg:address":"Calle de Muza Ben Zeya, 2",
    "sg:city":"Zaragoza",
    "sg:orig_category":"Molduras, Junquillos, Listones Y Molduras Perforadas",
    "sg:phone":"+34 976 27 83 80",
    "sg:postcode":"50007",
    "sg:province":"Zaragoza",
    "wof:name":"La Esquinica S.c",
    "wof:placetype":"venue"
},
  "geometry": {"coordinates":[-0.875837028,41.6230430603],"type":"Point"}
}