{
  "type": "Feature",
  "properties": {
    "iso:country":"ES",
    "sg:address":"Calle de San Blas, 2",
    "sg:city":"Aceuchal",
    "sg:orig_category":"Contenedores (mercanc\u00cdas)",
    "sg:phone":"+34 924 68 71 50",
    "sg:postcode":"06207",
    "sg:province":"Badajoz",
    "wof:name":"Casilla Llera Avelino",
    "wof:placetype":"venue"
},
  "geometry": {"coordinates":[-6.4885759354,38.645450592],"type":"Point"}
}