{
  "type": "Feature",
  "properties": {
    "iso:country":"ES",
    "sg:address":"Ctra Ronda Este De Circunvalacion, 48",
    "sg:city":"Quintana Serena",
    "sg:orig_category":"Plomeros",
    "sg:phone":"+34 924 78 60 78",
    "sg:postcode":"06450",
    "sg:province":"Badajoz",
    "wof:name":"Lambea Gudiel Antonio",
    "wof:placetype":"venue"
},
  "geometry": {"coordinates":[-5.6712579727,38.743019104],"type":"Point"}
}