{
  "type": "Feature",
  "properties": {
    "addr:full":"Av Artur Carbonell, 12 Sitges Barcelona 08870",
    "addr:housenumber":"12",
    "addr:postcode":"08870",
    "addr:street":"Av Artur Carbonell",
    "iso:country":"ES",
    "sg:address":"Av Artur Carbonell, 12",
    "sg:city":"Sitges",
    "sg:orig_category":"Productores Recolectores, Venta Directa De Vinos",
    "sg:phone":"+34 938 94 09 13",
    "sg:postcode":"08870",
    "sg:province":"Barcelona",
    "wof:name":"Vilalta Alonso Luis",
    "wof:placetype":"venue"
},
  "geometry": {"coordinates":[1.8079390526,41.2384605408],"type":"Point"}
}