{
  "type": "Feature",
  "properties": {
    "iso:country":"ES",
    "sg:address":"Carrer de Floridablanca, 131",
    "sg:city":"Mataro",
    "sg:orig_category":"Cester\u00cda (fabricaci\u00d3n)",
    "sg:phone":"+34 937 90 58 89",
    "sg:postcode":"08301",
    "sg:province":"Barcelona",
    "wof:name":"Calls Soler Juan",
    "wof:placetype":"venue"
},
  "geometry": {"coordinates":[2.450633049,41.5443725586],"type":"Point"}
}