{
  "type": "Feature",
  "properties": {
    "addr:full":"Ptor. Sorolla, 21 Sedavi Valencia 46910",
    "addr:housenumber":"21",
    "addr:postcode":"46910",
    "addr:street":"Sorolla",
    "iso:country":"ES",
    "sg:address":"Ptor. Sorolla, 21",
    "sg:city":"Sedavi",
    "sg:orig_category":"Agencias Y Agentes Comerciales, Representantes",
    "sg:phone":"+34 963 75 27 20",
    "sg:postcode":"46910",
    "sg:province":"Valencia",
    "wof:name":"Soto Velazquez Jose",
    "wof:placetype":"venue"
},
  "geometry": {"coordinates":[-0.3858909905,39.4259338379],"type":"Point"}
}