{
  "type": "Feature",
  "properties": {
    "addr:full":"Calle de Emilio Baro, 50 Valencia Valencia 46020",
    "addr:housenumber":"50",
    "addr:postcode":"46020",
    "addr:street":"Calle De Emilio Baro",
    "iso:country":"ES",
    "sg:address":"Calle de Emilio Baro, 50",
    "sg:city":"Valencia",
    "sg:orig_category":"Electrodom\u00c9sticos (al Por Menor)",
    "sg:phone":"+34 963 93 27 83",
    "sg:postcode":"46020",
    "sg:province":"Valencia",
    "wof:name":"Electrodomesticos Jose Vidal S.l.",
    "wof:placetype":"venue"
},
  "geometry": {"coordinates":[-0.3607639968,39.487537384],"type":"Point"}
}