{
  "type": "Feature",
  "properties": {
    "iso:country":"ES",
    "sg:address":"Pg Sant Joan, 117",
    "sg:city":"Barcelona",
    "sg:orig_category":"Farmacias",
    "sg:phone":"+34 934 57 63 39",
    "sg:postcode":"08037",
    "sg:province":"Barcelona",
    "wof:name":"Farmacia Soler Y Gornals",
    "wof:placetype":"venue"
},
  "geometry": {"coordinates":[2.167979002,41.4001960754],"type":"Point"}
}