{
  "type": "Feature",
  "properties": {
    "addr:full":"Calle de Parque San Julian, 5 Cuenca Cuenca 16002",
    "addr:housenumber":"5",
    "addr:postcode":"16002",
    "addr:street":"Calle De Parque San Julian",
    "iso:country":"ES",
    "sg:address":"Calle de Parque San Julian, 5",
    "sg:city":"Cuenca",
    "sg:orig_category":"Prot\u00c9sicos Dentales",
    "sg:phone":"+34 969 21 34 16",
    "sg:postcode":"16002",
    "sg:province":"Cuenca",
    "wof:name":"Mu\u00f1oz Escribano Moises",
    "wof:placetype":"venue"
},
  "geometry": {"coordinates":[-2.135340929,40.0725898743],"type":"Point"}
}