{
  "type": "Feature",
  "properties": {
    "addr:full":"Avgd Pais Valencia, 62 Betera Valencia 46117",
    "addr:housenumber":"62",
    "addr:postcode":"46117",
    "addr:street":"Valencia",
    "iso:country":"ES",
    "sg:address":"Avgd Pais Valencia, 62",
    "sg:city":"Betera",
    "sg:orig_category":"Perfumer\u00cda (al Por Menor)",
    "sg:phone":"+34 961 60 17 05",
    "sg:postcode":"46117",
    "sg:province":"Valencia",
    "wof:name":"Molina Romero Jose Pablo",
    "wof:placetype":"venue"
},
  "geometry": {"coordinates":[-0.4635530114,39.5899963379],"type":"Point"}
}