{
  "type": "Feature",
  "properties": {
    "addr:full":"Plaz Juan Paredes, 3 Azohia Murcia 30868",
    "addr:housenumber":"3",
    "addr:postcode":"30868",
    "addr:street":"Plaz Juan Paredes",
    "iso:country":"ES",
    "sg:address":"Plaz Juan Paredes, 3",
    "sg:city":"Azohia",
    "sg:orig_category":"Venta, Instalaci\u00d3n De Cocinas",
    "sg:phone":"+34 968 15 00 80",
    "sg:postcode":"30868",
    "sg:province":"Murcia",
    "wof:name":"Pereira Campos Alfredo",
    "wof:placetype":"venue"
},
  "geometry": {"coordinates":[-1.1811829805,37.5710372925],"type":"Point"}
}