{
  "type": "Feature",
  "properties": {
    "iso:country":"ES",
    "sg:address":"Calle de Constitucion (de La), 11",
    "sg:city":"Navalcarnero",
    "sg:orig_category":"Carnicer\u00cdas, Carnicer\u00cdas",
    "sg:phone":"+34 918 11 08 56",
    "sg:postcode":"28600",
    "sg:province":"Madrid",
    "wof:name":"Perez Trevijano Miguel",
    "wof:placetype":"venue"
},
  "geometry": {"coordinates":[-4.013463974,40.2875556946],"type":"Point"}
}