{
  "type": "Feature",
  "properties": {
    "iso:country":"ES",
    "sg:address":"Calle de Cid, 4",
    "sg:city":"Le\u00f3n",
    "sg:orig_category":"Molduras, Junquillos, Listones Y Molduras Perforadas",
    "sg:phone":"+34 987 23 32 16",
    "sg:postcode":"24003",
    "sg:province":"Le\u00f3n",
    "wof:name":"Cisneros Marcos Luis Miguel",
    "wof:placetype":"venue"
},
  "geometry": {"coordinates":[-5.5716609955,42.5981369019],"type":"Point"}
}