{
  "type": "Feature",
  "properties": {
    "addr:full":"Calle de Palomar, 196 Don Benito Badajoz 06400",
    "addr:housenumber":"196",
    "addr:postcode":"06400",
    "addr:street":"Calle De Palomar",
    "iso:country":"ES",
    "sg:address":"Calle de Palomar, 196",
    "sg:city":"Don Benito",
    "sg:orig_category":"Panader\u00cdas, Pasteler\u00cdas, Boller\u00cda Industriale (fabricaci\u00d3n, Al Por Mayor)",
    "sg:phone":"+34 924 81 06 84",
    "sg:postcode":"06400",
    "sg:province":"Badajoz",
    "wof:name":"Medina Gallego Francisco Javier",
    "wof:placetype":"venue"
},
  "geometry": {"coordinates":[-5.8554291725,38.9535484314],"type":"Point"}
}