{
  "type": "Feature",
  "properties": {
    "addr:full":"Pla\u00c7 Espanya, D', 26 Casco Urbano Valencia 46760",
    "addr:postcode":"46760",
    "iso:country":"ES",
    "sg:address":"Pla\u00c7 Espanya, D', 26",
    "sg:city":"Casco Urbano",
    "sg:orig_category":"Afilado",
    "sg:phone":"+34 962 82 30 16",
    "sg:postcode":"46760",
    "sg:province":"Valencia",
    "wof:name":"Salom Marti Pedro Juan",
    "wof:placetype":"venue"
},
  "geometry": {"coordinates":[-0.3296850026,39.4636497498],"type":"Point"}
}