{
  "type": "Feature",
  "properties": {
    "addr:full":"Calle de Priorato, 105 Leganes Madrid 28915",
    "addr:housenumber":"105",
    "addr:postcode":"28915",
    "addr:street":"Calle De Priorato",
    "iso:country":"ES",
    "sg:address":"Calle de Priorato, 105",
    "sg:city":"Leganes",
    "sg:orig_category":"Asesor\u00cda Fiscal Y Jur\u00cddica",
    "sg:phone":"+34 916 86 52 96",
    "sg:postcode":"28915",
    "sg:province":"Madrid",
    "wof:name":"Consultorio Integral Carben S.l.",
    "wof:placetype":"venue"
},
  "geometry": {"coordinates":[-3.7494668961,40.3359527588],"type":"Point"}
}