{
  "type": "Feature",
  "properties": {
    "iso:country":"ES",
    "sg:address":"Calle de Angulema, 5",
    "sg:city":"Vitoria-gasteiz",
    "sg:orig_category":"Comercio De Piezas De Recambio Y De Accesorios De Veh\u00cdculos, Veh\u00cdculos Industriales",
    "sg:phone":"+34 945 25 51 66",
    "sg:postcode":"01004",
    "sg:province":"\u00c1lava",
    "wof:name":"Jesus Fernandez Rubio S. L.",
    "wof:placetype":"venue"
},
  "geometry": {"coordinates":[-2.6674277782,42.8431434631],"type":"Point"}
}