{
  "type": "Feature",
  "properties": {
    "iso:country":"ES",
    "sg:address":"Calle de Basanta Silva, S/n",
    "sg:city":"Vilalba",
    "sg:classifiers":[
        {
            "category":"Taxi",
            "type":"Transportation"
        }
    ],
    "sg:phone":"+34 982 51 07 38",
    "sg:postcode":"27800",
    "sg:province":"Lugo",
    "wof:name":"Leal Novo Tomas",
    "wof:placetype":"venue"
},
  "geometry": {"coordinates":[-7.6797327995,43.2983398438],"type":"Point"}
}