{
  "type": "Feature",
  "properties": {
    "iso:country":"ES",
    "sg:address":"Carr Francesc Camprodon, 16",
    "sg:city":"Santa Coloma De Farners",
    "sg:orig_category":"Cojinetes De Bolas, Agujas Y Rodillos (fabricaci\u00d3n, Al Por Mayor)",
    "sg:phone":"+34 972 84 36 88",
    "sg:postcode":"17430",
    "sg:province":"Girona",
    "sg:website":"www.mondo.es",
    "wof:name":"Rodamondo S.l.",
    "wof:placetype":"venue"
},
  "geometry": {"coordinates":[2.6689898968,41.8601913452],"type":"Point"}
}