{
  "type": "Feature",
  "properties": {
    "addr:full":"Pla\u00c7 De La Coronaci\u00e9, 32 Ontinyent Valencia 46870",
    "addr:housenumber":"32",
    "addr:postcode":"46870",
    "iso:country":"ES",
    "sg:address":"Pla\u00c7 De La Coronaci\u00e9, 32",
    "sg:city":"Ontinyent",
    "sg:orig_category":"Sindicatos De Trabajadores",
    "sg:phone":"+34 962 38 62 10",
    "sg:postcode":"46870",
    "sg:province":"Valencia",
    "wof:name":"Union General De Trabajadores",
    "wof:placetype":"venue"
},
  "geometry": {"coordinates":[-0.6030989885,38.8258895874],"type":"Point"}
}