{
  "type": "Feature",
  "properties": {
    "iso:country":"ES",
    "sg:address":"Calle de General Gallarza, 23",
    "sg:city":"Calahorra",
    "sg:orig_category":"Institutos De Belleza",
    "sg:phone":"+34 941 13 15 65",
    "sg:postcode":"26500",
    "sg:province":"La Rioja",
    "wof:name":"Ramirez Lopez Maria Angeles",
    "wof:placetype":"venue"
},
  "geometry": {"coordinates":[-1.9664570093,42.3052215576],"type":"Point"}
}