{
  "type": "Feature",
  "properties": {
    "iso:country":"ES",
    "sg:address":"Carretera Toledo, Km. 0161,6",
    "sg:city":"Malagon",
    "sg:orig_category":"Lavado, Limpieza De Veh\u00cdculos",
    "sg:phone":"+34 926 69 51 25",
    "sg:postcode":"13420",
    "sg:province":"Ciudad Real",
    "wof:name":"Ure\u00f1a Santos Julio",
    "wof:placetype":"venue"
},
  "geometry": {"coordinates":[-3.8537249565,39.1670913696],"type":"Point"}
}