{
  "type": "Feature",
  "properties": {
    "iso:country":"ES",
    "sg:address":"Calle de Trinidad, 31",
    "sg:city":"Yebenes",
    "sg:orig_category":"Construcciones Met\u00c1licas",
    "sg:phone":"+34 925 32 01 41",
    "sg:postcode":"45470",
    "sg:province":"Toledo",
    "wof:name":"Eugenio Atahonero S.l.",
    "wof:placetype":"venue"
},
  "geometry": {"coordinates":[-3.8690290451,39.5810890198],"type":"Point"}
}