{
  "type": "Feature",
  "properties": {
    "addr:full":"Carrer de Moreres (les), 31 Prat Llobregat Barcelona 08820",
    "addr:housenumber":"31",
    "addr:postcode":"08820",
    "addr:street":"Carrer De Moreres Les;Llobregat",
    "iso:country":"ES",
    "sg:address":"Carrer de Moreres (les), 31",
    "sg:city":"Prat Llobregat",
    "sg:orig_category":"Agentes, Concesionarios Y Sucursales De Veh\u00cdculos",
    "sg:phone":"+34 933 70 28 02",
    "sg:postcode":"08820",
    "sg:province":"Barcelona",
    "wof:name":"Llobrecar S.l.",
    "wof:placetype":"venue"
},
  "geometry": {"coordinates":[2.1022160053,41.3318748474],"type":"Point"}
}