{
  "type": "Feature",
  "properties": {
    "addr:full":"Rua General Rubin, 15 Redondela Pontevedra 36800",
    "addr:housenumber":"15",
    "addr:postcode":"36800",
    "addr:street":"Rua General Rubin",
    "iso:country":"ES",
    "sg:address":"Rua General Rubin, 15",
    "sg:city":"Redondela",
    "sg:orig_category":"Molduras, Junquillos, Listones Y Molduras Perforadas",
    "sg:phone":"+34 986 40 51 80",
    "sg:postcode":"36800",
    "sg:province":"Pontevedra",
    "wof:name":"Cernadas Miguez Jose",
    "wof:placetype":"venue"
},
  "geometry": {"coordinates":[-8.6090641022,42.2820243835],"type":"Point"}
}