{
  "type": "Feature",
  "properties": {
    "iso:country":"ES",
    "sg:address":"Avda Madrid, 5",
    "sg:city":"Moraira",
    "sg:orig_category":"Telefon\u00cda: Instaladores Varios",
    "sg:phone":"+34 965 74 53 52",
    "sg:postcode":"03724",
    "sg:province":"Alicante",
    "wof:name":"Anpirama S.l.",
    "wof:placetype":"venue"
},
  "geometry": {"coordinates":[0.1337638944,38.6877098083],"type":"Point"}
}