{
  "type": "Feature",
  "properties": {
    "iso:country":"ES",
    "sg:address":"Av Doctor Severo Ochoa, 9",
    "sg:city":"Benidorm",
    "sg:orig_category":"Internados & Ense\u00d1anza Privada",
    "sg:phone":"+34 965 86 86 41",
    "sg:postcode":"03500",
    "sg:province":"Alicante",
    "sg:website":"www.lopedevega.es",
    "wof:name":"Colegio Internacional Lope De Vega S.a.",
    "wof:placetype":"venue"
},
  "geometry": {"coordinates":[-0.1033390015,38.5428009033],"type":"Point"}
}