{
  "type": "Feature",
  "properties": {
    "iso:country":"ES",
    "sg:address":"Calle de Escritor Carrillo Lasso, 8",
    "sg:city":"Cordoba",
    "sg:orig_category":"Sociedades, Compa\u00d1\u00cdas Aseguradoras",
    "sg:phone":"+34 957 25 56 16",
    "sg:postcode":"14007",
    "sg:province":"C\u00f3rdoba",
    "wof:name":"Correduria De Seguros San Martin S.l.",
    "wof:placetype":"venue"
},
  "geometry": {"coordinates":[-4.7547869682,37.8951339722],"type":"Point"}
}