{
  "type": "Feature",
  "properties": {
    "addr:full":"Plaz Pilar (del), 2 Zaragoza Zaragoza 50...",
    "addr:housenumber":"2;50 ...",
    "addr:street":"Plaz;Del;Zaragoza",
    "iso:country":"ES",
    "sg:address":"Plaz Pilar (del), 2",
    "sg:city":"Zaragoza",
    "sg:orig_category":"Abogados",
    "sg:phone":"+34 976 20 81 12",
    "sg:postcode":"50...",
    "sg:province":"Zaragoza",
    "wof:name":"Administracion De Justicia",
    "wof:placetype":"venue"
},
  "geometry": {"coordinates":[-0.8788017035,41.6558761597],"type":"Point"}
}