{
  "type": "Feature",
  "properties": {
    "iso:country":"ES",
    "sg:address":"Plaz Fuente, S/n",
    "sg:city":"Aguilafuente",
    "sg:orig_category":"Farmacias",
    "sg:phone":"+34 921 57 24 45",
    "sg:postcode":"40340",
    "sg:province":"Segovia",
    "wof:name":"Lozares Sanchez Maria Bego\u00f1a",
    "wof:placetype":"venue"
},
  "geometry": {"coordinates":[-4.1121630669,41.2265319824],"type":"Point"}
}