{
  "type": "Feature",
  "properties": {
    "addr:full":"Avda Tirajana (de), 32 Playa Del Ingles Las Palmas 35100",
    "addr:housenumber":"32",
    "addr:postcode":"35100",
    "addr:street":"Avda Tirajana De",
    "iso:country":"ES",
    "sg:address":"Avda Tirajana (de), 32",
    "sg:city":"Playa Del Ingles",
    "sg:orig_category":"Televisi\u00d3n, V\u00cddeo: Aparatos Y Accesorios (venta)",
    "sg:phone":"+34 928 76 49 68",
    "sg:postcode":"35100",
    "sg:province":"Las Palmas",
    "wof:name":"Om Bhavish S.l.",
    "wof:placetype":"venue"
},
  "geometry": {"coordinates":[-15.578783989,27.7606468201],"type":"Point"}
}