{
  "type": "Feature",
  "properties": {
    "addr:full":"Rond Villaca\u00d1as, S/n Tembleque Toledo 45780",
    "addr:housenumber":"s",
    "addr:postcode":"45780",
    "addr:street":"/ N",
    "iso:country":"ES",
    "sg:address":"Rond Villaca\u00d1as, S/n",
    "sg:city":"Tembleque",
    "sg:orig_category":"Negocio De Materiales De Construcci\u00d3n",
    "sg:phone":"+34 925 14 55 55",
    "sg:postcode":"45780",
    "sg:province":"Toledo",
    "wof:name":"Ariza Bueno Francisco",
    "wof:placetype":"venue"
},
  "geometry": {"coordinates":[-3.5205640793,39.6605300903],"type":"Point"}
}