{
  "type": "Feature",
  "properties": {
    "addr:full":"Calle de Isaac Peral, 8 Madrid Madrid 28015",
    "addr:housenumber":"8",
    "addr:postcode":"madrid;28015",
    "addr:street":"Calle De Isaac Peral",
    "iso:country":"ES",
    "sg:address":"Calle de Isaac Peral, 8",
    "sg:city":"Madrid",
    "sg:orig_category":"Centros Empresariales",
    "sg:phone":"+34 915 43 39 98",
    "sg:postcode":"28015",
    "sg:province":"Madrid",
    "wof:name":"Enterprise Van Rean Stae S.l.",
    "wof:placetype":"venue"
},
  "geometry": {"coordinates":[-3.7180449963,40.4357337952],"type":"Point"}
}