{
  "type": "Feature",
  "properties": {
    "addr:full":"Calle de Fresnos, 102 Haro La Rioja 26200",
    "addr:housenumber":"102",
    "addr:postcode":"26200",
    "addr:street":"Calle De Fresnos",
    "iso:country":"ES",
    "sg:address":"Calle de Fresnos, 102",
    "sg:city":"Haro",
    "sg:orig_category":"Herramientas Manuales (fabricaci\u00d3n, Al Por Mayor)",
    "sg:phone":"+34 941 31 30 74",
    "sg:postcode":"26200",
    "sg:province":"La Rioja",
    "sg:website":"www.kalkumezquerra.com",
    "wof:name":"Kalkum Ezquerra S.l.",
    "wof:placetype":"venue"
},
  "geometry": {"coordinates":[-2.8351509571,42.5591964722],"type":"Point"}
}