{
  "type": "Feature",
  "properties": {
    "addr:full":"Carrer de Canvis Nous, 6 Barcelona Barcelona 08003",
    "addr:housenumber":"6",
    "addr:postcode":"08003",
    "addr:street":"Carrer De Canvis Nous",
    "iso:country":"ES",
    "sg:address":"Carrer de Canvis Nous, 6",
    "sg:city":"Barcelona",
    "sg:orig_category":"Farmacias (repartici\u00d3n Y Al Por Mayor)",
    "sg:phone":"+34 933 19 82 74",
    "sg:postcode":"08003",
    "sg:province":"Barcelona",
    "wof:name":"Comunidad De Propietarios De Canvis Nous N\u00ba 6",
    "wof:placetype":"venue"
},
  "geometry": {"coordinates":[2.1816189289,41.3827552795],"type":"Point"}
}