{
  "type": "Feature",
  "properties": {
    "iso:country":"ES",
    "sg:address":"Raiguero De Levante, S/n",
    "sg:city":"Orihuela",
    "sg:orig_category":"Molduras, Junquillos, Listones Y Molduras Perforadas",
    "sg:phone":"+34 965 30 15 63",
    "sg:postcode":"03300",
    "sg:province":"Alicante",
    "wof:name":"Marin Cabrera Angel",
    "wof:placetype":"venue"
},
  "geometry": {"coordinates":[-0.9448040128,38.0817642212],"type":"Point"}
}