{
  "type": "Feature",
  "properties": {
    "iso:country":"ES",
    "sg:address":"Plaz Margarita Valldaura, 1",
    "sg:city":"Valencia",
    "sg:orig_category":"Molduras, Junquillos, Listones Y Molduras Perforadas",
    "sg:phone":"+34 963 57 52 50",
    "sg:postcode":"46003",
    "sg:province":"Valencia",
    "wof:name":"Garcia Carnicer Luis Vicente",
    "wof:placetype":"venue"
},
  "geometry": {"coordinates":[-0.3749609888,39.4733428955],"type":"Point"}
}