{
  "type": "Feature",
  "properties": {
    "iso:country":"ES",
    "sg:address":"Avda Cristobal Colon, 112",
    "sg:city":"Guadalajara",
    "sg:orig_category":"Material Y Herramientas Agr\u00cdcolas",
    "sg:phone":"+34 949 21 24 49",
    "sg:postcode":"19004",
    "sg:province":"Guadalajara",
    "wof:name":"Julian Domarco S.l.",
    "wof:placetype":"venue"
},
  "geometry": {"coordinates":[-3.1808300018,40.651008606],"type":"Point"}
}