{
  "type": "Feature",
  "properties": {
    "addr:full":"Cmno Cementerio, 8 Valladolid Valladolid 47011",
    "addr:housenumber":"8",
    "addr:postcode":"47011",
    "addr:street":"Cmno Cementerio",
    "iso:country":"ES",
    "sg:address":"Cmno Cementerio, 8",
    "sg:city":"Valladolid",
    "sg:orig_category":"Alimentaci\u00d3n Animal (fabricaci\u00d3n, Al Por Mayor)",
    "sg:phone":"+34 983 25 26 77",
    "sg:postcode":"47011",
    "sg:province":"Valladolid",
    "wof:name":"C.p.a.arambol S.l.",
    "wof:placetype":"venue"
},
  "geometry": {"coordinates":[-4.7097978592,41.6621627808],"type":"Point"}
}