{
  "type": "Feature",
  "properties": {
    "addr:full":"Rua Ines Perez De Ceta, 5 Vigo Pontevedra 36201",
    "addr:housenumber":"5",
    "addr:postcode":"36201",
    "addr:street":"Rua Ines",
    "iso:country":"ES",
    "sg:address":"Rua Ines Perez De Ceta, 5",
    "sg:city":"Vigo",
    "sg:orig_category":"Ingenier\u00cda, Centros De Estudios (diversos)",
    "sg:phone":"+34 986 22 17 62",
    "sg:postcode":"36201",
    "sg:province":"Pontevedra",
    "wof:name":"Juan Duque Fernando",
    "wof:placetype":"venue"
},
  "geometry": {"coordinates":[-8.7186098099,42.2388038635],"type":"Point"}
}