{
  "type": "Feature",
  "properties": {
    "addr:full":"Calle de Granados, 7 Campillo Jara Toledo 45578",
    "addr:housenumber":"7",
    "addr:postcode":"45578",
    "addr:street":"Calle De Granados",
    "iso:country":"ES",
    "sg:address":"Calle de Granados, 7",
    "sg:city":"Campillo Jara",
    "sg:orig_category":"Administraciones Regionales, Departamentales Y Locales",
    "sg:phone":"+34 925 45 55 21",
    "sg:postcode":"45578",
    "sg:province":"Toledo",
    "wof:name":"Ayuntamiento De El Campillo De La Jara",
    "wof:placetype":"venue"
},
  "geometry": {"coordinates":[-5.0559048653,39.5898017883],"type":"Point"}
}