{
  "type": "Feature",
  "properties": {
    "addr:full":"Pg Gran Passeig Ronda, 152 Lleida Lleida 25008",
    "addr:housenumber":"152",
    "addr:postcode":"25008",
    "addr:street":"Pg Gran Passeig Ronda",
    "iso:country":"ES",
    "sg:address":"Pg Gran Passeig Ronda, 152",
    "sg:city":"Lleida",
    "sg:orig_category":"Alimentaci\u00d3n General (al Por Menor)",
    "sg:phone":"+34 973 24 65 58",
    "sg:postcode":"25008",
    "sg:province":"Lleida",
    "wof:name":"Velez Cura Luis Del",
    "wof:placetype":"venue"
},
  "geometry": {"coordinates":[0.6210039854,41.6237792969],"type":"Point"}
}