{
  "type": "Feature",
  "properties": {
    "addr:full":"Calle de Principe De Vergara, 1 Madrid Madrid 28001",
    "addr:housenumber":"1",
    "addr:postcode":"28001",
    "addr:street":"Calle De Principe De Vergara",
    "iso:country":"ES",
    "sg:address":"Calle de Principe De Vergara, 1",
    "sg:city":"Madrid",
    "sg:orig_category":"Loter\u00cda Y T\u00d3mbola",
    "sg:phone":"+34 915 76 81 87",
    "sg:postcode":"28001",
    "sg:province":"Madrid",
    "wof:name":"Lorenzo Moyano Jose Luis",
    "wof:placetype":"venue"
},
  "geometry": {"coordinates":[-3.6805140972,40.4228897095],"type":"Point"}
}