{
  "type": "Feature",
  "properties": {
    "addr:full":"Calle de Merindades (las), 16 Castejon Navarra 31590",
    "addr:housenumber":"16",
    "addr:postcode":"31590",
    "addr:street":"Calle De Merindades Las",
    "iso:country":"ES",
    "sg:address":"Calle de Merindades (las), 16",
    "sg:city":"Castejon",
    "sg:orig_category":"Peluqueros: De Se\u00d1oras",
    "sg:phone":"+34 948 77 06 31",
    "sg:postcode":"31590",
    "sg:province":"Navarra",
    "wof:name":"Fernandez Ramos Maria Encarnacion",
    "wof:placetype":"venue"
},
  "geometry": {"coordinates":[-1.6914080381,42.1704978943],"type":"Point"}
}