{
  "type": "Feature",
  "properties": {
    "iso:country":"ES",
    "sg:address":"Calle de Covarrubias, 1",
    "sg:city":"Madrid",
    "sg:orig_category":"Edici\u00d3n De Diarios, Revistas, Boletines",
    "sg:phone":"+34 914 47 12 02",
    "sg:postcode":"28010",
    "sg:province":"Madrid",
    "sg:website":"www.globuscom.es",
    "wof:name":"Globus Comunicacion S.a.",
    "wof:placetype":"venue"
},
  "geometry": {"coordinates":[-3.6972460747,40.4283905029],"type":"Point"}
}