{
  "type": "Feature",
  "properties": {
    "addr:full":"Carrer de Maria Cubi, 174 Barcelona Barcelona 08021",
    "addr:housenumber":"174",
    "addr:postcode":"08021",
    "addr:street":"Carrer De Maria Cubi",
    "iso:country":"ES",
    "sg:address":"Carrer de Maria Cubi, 174",
    "sg:city":"Barcelona",
    "sg:orig_category":"Deportes Y Ocio: Art\u00cdculos Y Ropas (al Por Menor Y Accesorios)",
    "sg:phone":"+34 932 02 22 25",
    "sg:postcode":"08021",
    "sg:province":"Barcelona",
    "sg:website":"www.coroneltapiocca.com",
    "wof:name":"Coronel Tapioca S.a.",
    "wof:placetype":"venue"
},
  "geometry": {"coordinates":[2.1446619034,41.3954772949],"type":"Point"}
}