{
  "type": "Feature",
  "properties": {
    "addr:full":"Avda Bierzo (do), 37 Barco Ourense 32300",
    "addr:housenumber":"37",
    "addr:postcode":"32300",
    "addr:street":"Avda Bierzo Do",
    "iso:country":"ES",
    "sg:address":"Avda Bierzo (do), 37",
    "sg:city":"Barco",
    "sg:orig_category":"Pizzer\u00cdas",
    "sg:phone":"+34 988 32 00 01",
    "sg:postcode":"32300",
    "sg:province":"Ourense",
    "wof:name":"Nu\u00f1ez Fernandez Luis",
    "wof:placetype":"venue"
},
  "geometry": {"coordinates":[-6.981069088,42.4187889099],"type":"Point"}
}