{
  "type": "Feature",
  "properties": {
    "iso:country":"ES",
    "sg:address":"Plaz Tossal, 13",
    "sg:city":"Valencia",
    "sg:orig_category":"Arquitectos",
    "sg:phone":"+34 963 91 00 98",
    "sg:postcode":"46001",
    "sg:province":"Valencia",
    "wof:name":"Montesinos Cornejo Carlos Vicente",
    "wof:placetype":"venue"
},
  "geometry": {"coordinates":[-0.3801450133,39.4764289856],"type":"Point"}
}