{
  "type": "Feature",
  "properties": {
    "iso:country":"ES",
    "sg:address":"Calle de Mayor, S/n",
    "sg:city":"Raal",
    "sg:classifiers":[
        {
            "category":"Personal",
            "subcategory":"Barber",
            "type":"Services"
        }
    ],
    "sg:phone":"+34 968 87 00 08",
    "sg:postcode":"30139",
    "sg:province":"Murcia",
    "sg:tags":[
        "caballeros",
        "de",
        "peluqueros"
    ],
    "wof:name":"Juan Marin Francisco Jose",
    "wof:placetype":"venue"
},
  "geometry": {"coordinates":[-1.014408946,38.047744751],"type":"Point"}
}