{
  "type": "Feature",
  "properties": {
    "iso:country":"ES",
    "sg:address":"Avda Castelao, 41",
    "sg:city":"Muros",
    "sg:orig_category":"Farmacias",
    "sg:phone":"+34 981 82 63 08",
    "sg:postcode":"15250",
    "sg:province":"La Coru\u00f1a",
    "wof:name":"Iglesias Leston Maria De Las Mercedes",
    "wof:placetype":"venue"
},
  "geometry": {"coordinates":[-9.058795929,42.775932312],"type":"Point"}
}