{
  "type": "Feature",
  "properties": {
    "iso:country":"ES",
    "sg:address":"Calle de Francisco Mu\u00d1oz Kalea, 1",
    "sg:city":"Zubiaur",
    "sg:orig_category":"Bosques (trabajos, Asesor\u00cda, Gesti\u00d3n)",
    "sg:phone":"+34 946 33 95 16",
    "sg:postcode":"48410",
    "sg:province":"Vizcaya",
    "wof:name":"Ajnani S.l.",
    "wof:placetype":"venue"
},
  "geometry": {"coordinates":[-2.910597086,43.1093559265],"type":"Point"}
}