{
  "type": "Feature",
  "properties": {
    "addr:full":"Calle de Antonia Diaz, 30 Dos Hermanas Sevilla 41700",
    "addr:housenumber":"30",
    "addr:postcode":"41700",
    "addr:street":"Calle De Antonia Diaz",
    "iso:country":"ES",
    "sg:address":"Calle de Antonia Diaz, 30",
    "sg:city":"Dos Hermanas",
    "sg:orig_category":"Cl\u00cdnicas M\u00c9dicas",
    "sg:phone":"+34 955 66 88 51",
    "sg:postcode":"41700",
    "sg:province":"Sevilla",
    "wof:name":"Rodriguez Garcia Antonio",
    "wof:placetype":"venue"
},
  "geometry": {"coordinates":[-5.9232392311,37.2822265625],"type":"Point"}
}