{
  "type": "Feature",
  "properties": {
    "addr:full":"Denda Kalea, 17 Alde Zaharra Guip\u00f9zcoa 20280",
    "addr:housenumber":"17",
    "addr:postcode":"20280",
    "addr:street":"Denda Kalea;Zaharra Guipu\u0300Zcoa",
    "iso:country":"ES",
    "sg:address":"Denda Kalea, 17",
    "sg:city":"Alde Zaharra",
    "sg:orig_category":"Administradores De Bienes Y Delegados De Comunidades De Propietarios",
    "sg:phone":"+34 943 64 73 63",
    "sg:postcode":"20280",
    "sg:province":"Guip\u00f9zcoa",
    "wof:name":"Aramendi Jauregui Angel Maria",
    "wof:placetype":"venue"
},
  "geometry": {"coordinates":[-1.7932364941,43.3631134033],"type":"Point"}
}