{
  "type": "Feature",
  "properties": {
    "iso:country":"ES",
    "sg:address":"Joan Martorell, 5",
    "sg:city":"Puerto Sagunto",
    "sg:orig_category":"Reposter\u00cdas",
    "sg:phone":"+34 962 67 67 41",
    "sg:postcode":"46520",
    "sg:province":"Valencia",
    "wof:name":"Perez Navarro Horneros S.l.",
    "wof:placetype":"venue"
},
  "geometry": {"coordinates":[-0.2412389964,39.6723098755],"type":"Point"}
}