{
  "type": "Feature",
  "properties": {
    "iso:country":"ES",
    "sg:address":"Rbla Egara, 112",
    "sg:city":"Terrassa",
    "sg:orig_category":"Ropa Para Ni\u00d1os (al Por Menor)",
    "sg:phone":"+34 937 88 16 87",
    "sg:postcode":"08221",
    "sg:province":"Barcelona",
    "wof:name":"Freixenet De La Iglesia Ferran",
    "wof:placetype":"venue"
},
  "geometry": {"coordinates":[2.007889986,41.5601348877],"type":"Point"}
}