{
  "type": "Feature",
  "properties": {
    "iso:country":"ES",
    "sg:address":"Calle de Reyes Catolicos, 12",
    "sg:city":"Ejido",
    "sg:orig_category":"Florister\u00cdas",
    "sg:phone":"+34 950 48 00 50",
    "sg:postcode":"04700",
    "sg:province":"Almer\u00eda",
    "wof:name":"Rodriguez Saez Emilia",
    "wof:placetype":"venue"
},
  "geometry": {"coordinates":[-2.8134710789,36.772693634],"type":"Point"}
}