{
  "type": "Feature",
  "properties": {
    "iso:country":"ES",
    "sg:address":"Rua Travesia De Vigo, 204",
    "sg:city":"Roris",
    "sg:orig_category":"Ense\u00d1anza: Profesiones Art\u00cdsticas",
    "sg:phone":"+34 986 28 08 79",
    "sg:postcode":"36207",
    "sg:province":"Pontevedra",
    "wof:name":"Minit-colors Espa\u00d1a S.a.",
    "wof:placetype":"venue"
},
  "geometry": {"coordinates":[-8.6667003632,42.25],"type":"Point"}
}