{
  "type": "Feature",
  "properties": {
    "addr:full":"Rua Fraga, 15 Fene A Coru\u00f1a 15500",
    "addr:housenumber":"15",
    "addr:postcode":"15500",
    "addr:street":"Rua Fraga;Corun\u0303A",
    "iso:country":"ES",
    "sg:address":"Rua Fraga, 15",
    "sg:city":"Fene",
    "sg:orig_category":"Peluqueros: De Se\u00d1oras",
    "sg:phone":"+34 981 34 39 12",
    "sg:postcode":"15500",
    "sg:province":"A Coru\u00f1a",
    "wof:name":"Vizoso Pi\u00f1eiro Yolanda",
    "wof:placetype":"venue"
},
  "geometry": {"coordinates":[-8.1676235199,43.4737586975],"type":"Point"}
}