{
  "type": "Feature",
  "properties": {
    "addr:full":"Calle de Arca Real, 28 Valladolid Valladolid 47013",
    "addr:housenumber":"28",
    "addr:postcode":"47013",
    "addr:street":"Calle De;Real",
    "iso:country":"ES",
    "sg:address":"Calle de Arca Real, 28",
    "sg:city":"Valladolid",
    "sg:orig_category":"Molduras, Junquillos, Listones Y Molduras Perforadas",
    "sg:phone":"+34 983 47 36 86",
    "sg:postcode":"47013",
    "sg:province":"Valladolid",
    "wof:name":"Cal Martinez Jose Maria De La",
    "wof:placetype":"venue"
},
  "geometry": {"coordinates":[-4.7237858772,41.6370620728],"type":"Point"}
}