{
  "type": "Feature",
  "properties": {
    "iso:country":"ES",
    "sg:address":"Carrer de Santa Teresa, S/n",
    "sg:city":"Viladecans",
    "sg:orig_category":"Cajas De Ahorro",
    "sg:phone":"+34 936 47 51 30",
    "sg:postcode":"08840",
    "sg:province":"Barcelona",
    "wof:name":"Caixa D'estalvis De Catalunya",
    "wof:placetype":"venue"
},
  "geometry": {"coordinates":[2.0183200836,41.3183059692],"type":"Point"}
}