{
  "type": "Feature",
  "properties": {
    "iso:country":"ES",
    "sg:address":"Calle de Santa Barbara, 3",
    "sg:city":"Donostia-san Sebastian",
    "sg:orig_category":"Partidos Pol\u00cdticos",
    "sg:phone":"+34 943 35 40 16",
    "sg:postcode":"20017",
    "sg:province":"Guip\u00f9zcoa",
    "wof:name":"Partido Socialista Obrero Espa\u00f1ol",
    "wof:placetype":"venue"
},
  "geometry": {"coordinates":[-1.9290640354,43.3166122437],"type":"Point"}
}