{
  "type": "Feature",
  "properties": {
    "iso:country":"ES",
    "sg:address":"Avda Condesa Forjas De Buelna, 12",
    "sg:city":"Corrales",
    "sg:orig_category":"Farmacias",
    "sg:phone":"+34 942 83 00 94",
    "sg:postcode":"39400",
    "sg:province":"Cantabria",
    "wof:name":"Perez Macho Ofelia",
    "wof:placetype":"venue"
},
  "geometry": {"coordinates":[-4.0680789948,43.2602615356],"type":"Point"}
}