{
  "type": "Feature",
  "properties": {
    "iso:country":"ES",
    "sg:address":"Carrer de Dolors, 7",
    "sg:city":"Ondara",
    "sg:orig_category":"Peluquer\u00cdas, Peluquer\u00cda Mixta",
    "sg:phone":"+34 965 76 66 85",
    "sg:postcode":"03760",
    "sg:province":"Alicante",
    "wof:name":"Teima C.b.",
    "wof:placetype":"venue"
},
  "geometry": {"coordinates":[0.0187420007,38.8253822327],"type":"Point"}
}