{
  "type": "Feature",
  "properties": {
    "iso:country":"ES",
    "sg:address":"Avda Almazora, 9",
    "sg:city":"Castellon",
    "sg:orig_category":"Mec\u00c1nico Del Autom\u00d3vil",
    "sg:phone":"+34 964 20 20 19",
    "sg:postcode":"12005",
    "sg:province":"Castell\u00f3n",
    "wof:name":"Herrero Dealbert Joaquin",
    "wof:placetype":"venue"
},
  "geometry": {"coordinates":[-0.0579102002,39.9600143433],"type":"Point"}
}