{
  "type": "Feature",
  "properties": {
    "addr:full":"Luga Playa De Tauro, S/n Playa De Tauro Las Palmas 35130",
    "addr:housenumber":"s / n",
    "addr:postcode":"35130",
    "iso:country":"ES",
    "sg:address":"Luga Playa De Tauro, S/n",
    "sg:city":"Playa De Tauro",
    "sg:orig_category":"Inmobiliaria (agencias)",
    "sg:phone":"+34 928 15 30 20",
    "sg:postcode":"35130",
    "sg:province":"Las Palmas",
    "wof:name":"Tauro Golf Invest S.l.",
    "wof:placetype":"venue"
},
  "geometry": {"coordinates":[-15.7144145966,27.7864627838],"type":"Point"}
}