{
  "type": "Feature",
  "properties": {
    "iso:country":"ES",
    "sg:address":"Calle de Juan Tornero, 37",
    "sg:city":"Madrid",
    "sg:orig_category":"Cerrajer\u00cda, Ferrallista",
    "sg:phone":"+34 915 26 05 29",
    "sg:postcode":"28011",
    "sg:province":"Madrid",
    "wof:name":"A.j.arpaga S.l.",
    "wof:placetype":"venue"
},
  "geometry": {"coordinates":[-3.7287864685,40.411441803],"type":"Point"}
}