{
  "type": "Feature",
  "properties": {
    "iso:country":"ES",
    "sg:address":"Carrer de Mossen Jacint Verdaguer, 65",
    "sg:city":"Premia Mar",
    "sg:orig_category":"Institutos De Belleza",
    "sg:phone":"+34 937 52 03 84",
    "sg:postcode":"08330",
    "sg:province":"Barcelona",
    "wof:name":"Maimo Ambel Ana",
    "wof:placetype":"venue"
},
  "geometry": {"coordinates":[2.3566389084,41.4928970337],"type":"Point"}
}