{
  "type": "Feature",
  "properties": {
    "addr:full":"Cno. Yuncos, S/n Illescas Toledo 45200",
    "addr:housenumber":"s / n",
    "addr:postcode":"45200",
    "addr:street":"Cno. Yuncos",
    "iso:country":"ES",
    "sg:address":"Cno. Yuncos, S/n",
    "sg:city":"Illescas",
    "sg:orig_category":"M\u00c1rmoles, Granitos Y Piedras Naturales",
    "sg:phone":"+34 925 54 05 58",
    "sg:postcode":"45200",
    "sg:province":"Toledo",
    "wof:name":"Marmoles Illescas C.b.",
    "wof:placetype":"venue"
},
  "geometry": {"coordinates":[-3.8469929695,40.1208839417],"type":"Point"}
}