{
  "type": "Feature",
  "properties": {
    "addr:full":"Plaz Llanete, 3 Martos Ja\u00e9n 23600",
    "addr:housenumber":"3",
    "addr:postcode":"23600",
    "addr:street":"Plaz Llanete;Jae\u0301N",
    "iso:country":"ES",
    "sg:address":"Plaz Llanete, 3",
    "sg:city":"Martos",
    "sg:orig_category":"Quincaller\u00cda (al Por Menor)",
    "sg:phone":"+34 953 70 02 01",
    "sg:postcode":"23600",
    "sg:province":"Ja\u00e9n",
    "wof:name":"Ferreteria Las Dos Llaves S.l.",
    "wof:placetype":"venue"
},
  "geometry": {"coordinates":[-3.9681959152,37.7196273804],"type":"Point"}
}