{
  "type": "Feature",
  "properties": {
    "addr:full":"El Marchal, S/n Abrucena Almer\u00eda 04520",
    "addr:housenumber":"s",
    "addr:postcode":"04520",
    "addr:street":"El Marchal;/ N Abrucena Almeri\u0301A",
    "iso:country":"ES",
    "sg:address":"El Marchal, S/n",
    "sg:city":"Abrucena",
    "sg:orig_category":"Empresarios",
    "sg:phone":"+34 950 35 02 85",
    "sg:postcode":"04520",
    "sg:province":"Almer\u00eda",
    "wof:name":"Fundacion Red Andalucia Emprende",
    "wof:placetype":"venue"
},
  "geometry": {"coordinates":[-2.7931981087,37.1370620728],"type":"Point"}
}