{
  "type": "Feature",
  "properties": {
    "iso:country":"ES",
    "sg:address":"Calle de Virgen Maria, 7",
    "sg:city":"Madrid",
    "sg:orig_category":"Asesor\u00cda Sobre Comunicaci\u00d3n De Empresas",
    "sg:phone":"+34 914 09 32 60",
    "sg:postcode":"28007",
    "sg:province":"Madrid",
    "wof:name":"Team Marketing S.l.",
    "wof:placetype":"venue"
},
  "geometry": {"coordinates":[-3.671489954,40.4110488892],"type":"Point"}
}