{
  "type": "Feature",
  "properties": {
    "iso:country":"ES",
    "sg:address":"Calle de Valeriano Leon, 19",
    "sg:city":"Pola De Siero",
    "sg:orig_category":"Sociedades, Compa\u00d1\u00cdas Aseguradoras",
    "sg:phone":"+34 985 72 64 90",
    "sg:postcode":"33510",
    "sg:province":"Asturias",
    "sg:website":"www.bangoseguros.com",
    "wof:name":"Bango Correduria De Seguros S.a.",
    "wof:placetype":"venue"
},
  "geometry": {"coordinates":[-5.6597008705,43.3911552429],"type":"Point"}
}