{
  "type": "Feature",
  "properties": {
    "addr:full":"Sant Andreu, 46 Porqueres Girona 17834",
    "addr:housenumber":"46",
    "addr:postcode":"17834",
    "addr:street":"Andreu",
    "iso:country":"ES",
    "sg:address":"Sant Andreu, 46",
    "sg:city":"Porqueres",
    "sg:orig_category":"Alimentaci\u00d3n General (al Por Mayor)",
    "sg:phone":"+34 972 57 05 40",
    "sg:postcode":"17834",
    "sg:province":"Girona",
    "wof:name":"Costabella Portella Jose",
    "wof:placetype":"venue"
},
  "geometry": {"coordinates":[2.7811839581,42.1068725586],"type":"Point"}
}