{
  "type": "Feature",
  "properties": {
    "iso:country":"ES",
    "sg:address":"Avda Salvador Allende, 69",
    "sg:city":"Gijon",
    "sg:orig_category":"Farmacias",
    "sg:phone":"+34 985 38 63 67",
    "sg:postcode":"33211",
    "sg:province":"Asturias",
    "wof:name":"Goyanes Riesgo Rafael Jesus",
    "wof:placetype":"venue"
},
  "geometry": {"coordinates":[-5.6779308319,43.5167274475],"type":"Point"}
}