{
  "type": "Feature",
  "properties": {
    "iso:country":"ES",
    "sg:address":"Calle de Huertas, 23",
    "sg:city":"Arnedo",
    "sg:orig_category":"Agentes Generales De Seguros",
    "sg:phone":"+34 941 38 11 51",
    "sg:postcode":"26580",
    "sg:province":"La Rioja",
    "wof:name":"Fernandez Qui\u00f1ones Maria Jesus",
    "wof:placetype":"venue"
},
  "geometry": {"coordinates":[-2.1041789055,42.2247161865],"type":"Point"}
}