{
  "type": "Feature",
  "properties": {
    "iso:country":"ES",
    "sg:address":"Calle de Hermanos De Pablo, 11",
    "sg:city":"Madrid",
    "sg:orig_category":"Muebles, Minoristas",
    "sg:phone":"+34 914 08 73 98",
    "sg:postcode":"28027",
    "sg:province":"Madrid",
    "wof:name":"Oca\u00f1a Garrido Antonio",
    "wof:placetype":"venue"
},
  "geometry": {"coordinates":[-3.645029068,40.4359054565],"type":"Point"}
}