{
  "type": "Feature",
  "properties": {
    "addr:full":"Calle de Benedicto Antequera, 36 Argamasilla Alba Ciudad Real 13710",
    "addr:housenumber":"36",
    "addr:postcode":"alba;13710",
    "addr:street":"Calle De Benedicto Antequera",
    "iso:country":"ES",
    "sg:address":"Calle de Benedicto Antequera, 36",
    "sg:city":"Argamasilla Alba",
    "sg:orig_category":"Molduras, Junquillos, Listones Y Molduras Perforadas",
    "sg:phone":"+34 926 52 22 00",
    "sg:postcode":"13710",
    "sg:province":"Ciudad Real",
    "wof:name":"Carreton Lara Severiano",
    "wof:placetype":"venue"
},
  "geometry": {"coordinates":[-3.0884444714,39.1263999939],"type":"Point"}
}