{
  "type": "Feature",
  "properties": {
    "iso:country":"ES",
    "sg:address":"Calle de Merced (de La), 35",
    "sg:city":"Almazan",
    "sg:orig_category":"Farmacias",
    "sg:phone":"+34 975 31 00 64",
    "sg:postcode":"42200",
    "sg:province":"Soria",
    "wof:name":"Blanco Perez Jose Luis",
    "wof:placetype":"venue"
},
  "geometry": {"coordinates":[-2.5320260525,41.4883956909],"type":"Point"}
}