{
  "type": "Feature",
  "properties": {
    "addr:full":"Calle de Gloria (la), 17 Gloria Almer\u00eda 04230",
    "addr:housenumber":"17",
    "addr:postcode":"04230",
    "addr:street":"Calle De Gloria La;Almeri\u0301A",
    "iso:country":"ES",
    "sg:address":"Calle de Gloria (la), 17",
    "sg:city":"Gloria",
    "sg:orig_category":"Caf\u00c9s, Bares, Cervecer\u00cdas",
    "sg:phone":"+34 950 30 14 78",
    "sg:postcode":"04230",
    "sg:province":"Almer\u00eda",
    "wof:name":"Vizcaino Gonzalez Antonio Jesus",
    "wof:placetype":"venue"
},
  "geometry": {"coordinates":[-2.4679217339,36.8401641846],"type":"Point"}
}