{
  "type": "Feature",
  "properties": {
    "addr:full":"Calle de Oca\u00d1a, 110 Madrid Madrid 28047",
    "addr:housenumber":"110",
    "addr:postcode":"28047",
    "addr:street":"Calle De Ocan\u0303A",
    "iso:country":"ES",
    "sg:address":"Calle de Oca\u00d1a, 110",
    "sg:city":"Madrid",
    "sg:orig_category":"Colchones (fabricaci\u00d3n, Al Por Mayor, Al Por Menor)",
    "sg:phone":"+34 914 66 52 82",
    "sg:postcode":"28047",
    "sg:province":"Madrid",
    "wof:name":"Leon Perez Jose Angel",
    "wof:placetype":"venue"
},
  "geometry": {"coordinates":[-3.7526218891,40.3861541748],"type":"Point"}
}