{
  "type": "Feature",
  "properties": {
    "addr:full":"Urb. Parque Avenida, 1 Jerez C\u00e1diz 11405",
    "addr:postcode":"11405",
    "addr:street":"Avenida 1",
    "iso:country":"ES",
    "sg:address":"Urb. Parque Avenida, 1",
    "sg:city":"Jerez",
    "sg:orig_category":"Peluqueros: De Se\u00d1oras",
    "sg:phone":"+34 956 31 37 66",
    "sg:postcode":"11405",
    "sg:province":"C\u00e1diz",
    "wof:name":"Peluqueria Avance S.l.",
    "wof:placetype":"venue"
},
  "geometry": {"coordinates":[-6.1180901527,36.6981887817],"type":"Point"}
}