{
  "type": "Feature",
  "properties": {
    "addr:full":"Calle de Corredera Alta De San Pablo, 15 Madrid Madrid 28004",
    "addr:housenumber":"15",
    "addr:postcode":"madrid;28004",
    "addr:street":"Calle De Corredera Alta De San Pablo",
    "iso:country":"ES",
    "sg:address":"Calle de Corredera Alta De San Pablo, 15",
    "sg:city":"Madrid",
    "sg:orig_category":"Fabricaci\u00d3n, Distribuci\u00d3n De Discos, V\u00cddeodiscos Y Musicassettes",
    "sg:phone":"+34 915 21 09 63",
    "sg:postcode":"28004",
    "sg:province":"Madrid",
    "sg:website":"www.museekshop.com",
    "wof:name":"Quantum Entertaiment, S.l.",
    "wof:placetype":"venue"
},
  "geometry": {"coordinates":[-3.7019505501,40.4253311157],"type":"Point"}
}