{
  "type": "Feature",
  "properties": {
    "addr:full":"Avda Compromiso De Caspe, 49 Zaragoza Zaragoza 50002",
    "addr:housenumber":"49",
    "addr:postcode":"50002",
    "addr:street":"Avda Compromiso De Caspe",
    "iso:country":"ES",
    "sg:address":"Avda Compromiso De Caspe, 49",
    "sg:city":"Zaragoza",
    "sg:orig_category":"Muebles Y Accesorios Para Cocinas Y Cuartos De Ba\u00d1o (al Por Menor)",
    "sg:phone":"+34 976 42 67 21",
    "sg:postcode":"50002",
    "sg:province":"Zaragoza",
    "wof:name":"Exclusivas Fecar S. Cv.",
    "wof:placetype":"venue"
},
  "geometry": {"coordinates":[-0.8679289818,41.6458206177],"type":"Point"}
}