{
  "type": "Feature",
  "properties": {
    "iso:country":"ES",
    "sg:address":"Calle de Santa Engracia, 4",
    "sg:city":"Madrid",
    "sg:orig_category":"Farmacias",
    "sg:phone":"+34 913 08 07 23",
    "sg:postcode":"28010",
    "sg:province":"Madrid",
    "wof:name":"Lastra Alonso Paloma",
    "wof:placetype":"venue"
},
  "geometry": {"coordinates":[-3.6958339214,40.4285202026],"type":"Point"}
}