{
  "type": "Feature",
  "properties": {
    "addr:full":"Carrer de Jaume I El Conqueridor, 5 Vic Barcelona 08500",
    "addr:housenumber":"5",
    "addr:postcode":"08500",
    "addr:street":"Carrer De Jaume I El Conqueridor",
    "iso:country":"ES",
    "sg:address":"Carrer de Jaume I El Conqueridor, 5",
    "sg:city":"Vic",
    "sg:orig_category":"Equitaci\u00d3n Y Centros De H\u00cdpica",
    "sg:phone":"+34 938 86 14 20",
    "sg:postcode":"08500",
    "sg:province":"Barcelona",
    "sg:website":"www.boigaltes.com",
    "wof:name":"Boi Galtes S.l",
    "wof:placetype":"venue"
},
  "geometry": {"coordinates":[2.2549340725,41.9331474304],"type":"Point"}
}