{
  "type": "Feature",
  "properties": {
    "iso:country":"ES",
    "sg:address":"Calle de Ronda D'algemesi, 33",
    "sg:city":"Alzira",
    "sg:orig_category":"Trabajos De Perforaciones, Sondeos, Construcci\u00d3n De Pozos",
    "sg:phone":"+34 962 40 59 22",
    "sg:postcode":"46600",
    "sg:province":"Valencia",
    "wof:name":"Sospedra Marin Severino",
    "wof:placetype":"venue"
},
  "geometry": {"coordinates":[-0.4420824051,39.152671814],"type":"Point"}
}