{
  "type": "Feature",
  "properties": {
    "addr:full":"Calle de Castellar, 17 Angeles C\u00e1diz 11330",
    "addr:housenumber":"17",
    "addr:postcode":"11330",
    "addr:street":"Calle De Castellar",
    "iso:country":"ES",
    "sg:address":"Calle de Castellar, 17",
    "sg:city":"Angeles",
    "sg:orig_category":"Art\u00cdculos De Madera (fabricaci\u00d3n Y Al Por Mayor)",
    "sg:phone":"+34 956 64 03 35",
    "sg:postcode":"11330",
    "sg:province":"C\u00e1diz",
    "wof:name":"Madera De Brezo Sg S.l.",
    "wof:placetype":"venue"
},
  "geometry": {"coordinates":[-5.4363894463,36.4231109619],"type":"Point"}
}