{
  "type": "Feature",
  "properties": {
    "addr:full":"Calle de Juan De Austria, 6 Mislata Valencia 46920",
    "addr:housenumber":"6",
    "addr:postcode":"46920",
    "addr:street":"Calle De Juan De Austria",
    "iso:country":"ES",
    "sg:address":"Calle de Juan De Austria, 6",
    "sg:city":"Mislata",
    "sg:orig_category":"Suministros Y Materiales Industriales",
    "sg:phone":"+34 963 79 92 31",
    "sg:postcode":"46920",
    "sg:province":"Valencia",
    "wof:name":"Ba\u00f1os Llacer Julian",
    "wof:placetype":"venue"
},
  "geometry": {"coordinates":[-0.4183650017,39.4708175659],"type":"Point"}
}