{
  "type": "Feature",
  "properties": {
    "addr:full":"Calle de Tomas Trenor, 2 Meliana Valencia 46133",
    "addr:housenumber":"2",
    "addr:postcode":"46133",
    "addr:street":"Calle De Tomas Trenor",
    "iso:country":"ES",
    "sg:address":"Calle de Tomas Trenor, 2",
    "sg:city":"Meliana",
    "sg:orig_category":"Institutos De Belleza",
    "sg:phone":"+34 961 49 11 51",
    "sg:postcode":"46133",
    "sg:province":"Valencia",
    "wof:name":"Zamit Torres Desamparados",
    "wof:placetype":"venue"
},
  "geometry": {"coordinates":[-0.3513045907,39.5282669067],"type":"Point"}
}