{
  "type": "Feature",
  "properties": {
    "addr:full":"Av. Blasco Iba\u00f1ez, 57 Massanassa Valencia 46470",
    "addr:housenumber":"57",
    "addr:postcode":"46470",
    "addr:street":"Av. Blasco Iban\u0303Ez",
    "iso:country":"ES",
    "sg:address":"Av. Blasco Iba\u00f1ez, 57",
    "sg:city":"Massanassa",
    "sg:orig_category":"Promotores Constructores",
    "sg:phone":"+34 961 25 50 55",
    "sg:postcode":"46470",
    "sg:province":"Valencia",
    "wof:name":"Promocions Edimaba S.l.",
    "wof:placetype":"venue"
},
  "geometry": {"coordinates":[-0.4006060064,39.4105758667],"type":"Point"}
}