{
  "type": "Feature",
  "properties": {
    "iso:country":"ES",
    "sg:address":"Rua Maria Berdiales, 2",
    "sg:city":"Vigo",
    "sg:orig_category":"Loter\u00cda Y T\u00d3mbola",
    "sg:phone":"+34 986 22 23 29",
    "sg:postcode":"36203",
    "sg:province":"Pontevedra",
    "wof:name":"Llauger Vazquez Miguel Angel",
    "wof:placetype":"venue"
},
  "geometry": {"coordinates":[-8.7207860947,42.2352104187],"type":"Point"}
}