{
  "type": "Feature",
  "properties": {
    "iso:country":"ES",
    "sg:address":"Calle de Mefistofeles, 11",
    "sg:city":"Malaga",
    "sg:orig_category":"Carnicer\u00cdas, Carnicer\u00cdas",
    "sg:phone":"+34 952 32 94 83",
    "sg:postcode":"29006",
    "sg:province":"M\u00e1laga",
    "wof:name":"Torres Fernandez Juan Carlos",
    "wof:placetype":"venue"
},
  "geometry": {"coordinates":[-4.463078022,36.7099342346],"type":"Point"}
}