{
  "type": "Feature",
  "properties": {
    "iso:country":"ES",
    "sg:address":"Carrer de Papa Pius Xi, 24",
    "sg:city":"Sabadell",
    "sg:orig_category":"Promotores Constructores",
    "sg:phone":"+34 937 26 56 58",
    "sg:postcode":"08208",
    "sg:province":"Barcelona",
    "wof:name":"Construcciones Redos S. A.",
    "wof:placetype":"venue"
},
  "geometry": {"coordinates":[2.104820013,41.5521736145],"type":"Point"}
}