{
  "type": "Feature",
  "properties": {
    "addr:full":"Corralinos, 8 Corralinos Asturias 33129",
    "addr:housenumber":"8",
    "addr:postcode":"33129",
    "addr:street":"Corralinos;Asturias",
    "iso:country":"ES",
    "sg:address":"Corralinos, 8",
    "sg:city":"Corralinos",
    "sg:orig_category":"Plomeros",
    "sg:phone":"+34 985 82 09 58",
    "sg:postcode":"33129",
    "sg:province":"Asturias",
    "wof:name":"Alonso Garcia Jose Luis",
    "wof:placetype":"venue"
},
  "geometry": {"coordinates":[-6.1255459785,43.4807167053],"type":"Point"}
}