{
  "type": "Feature",
  "properties": {
    "addr:full":"Avda De La Constitucion, S/n Cuacos Yuste C\u00e1ceres 10430",
    "addr:housenumber":"/ n",
    "addr:postcode":"10430",
    "addr:street":"Avda De La Constitucion S;Ca\u0301Ceres",
    "iso:country":"ES",
    "sg:address":"Avda De La Constitucion, S/n",
    "sg:city":"Cuacos Yuste",
    "sg:orig_category":"Hoteles",
    "sg:phone":"+34 927 17 21 81",
    "sg:postcode":"10430",
    "sg:province":"C\u00e1ceres",
    "wof:name":"Moreno Calle Adriano",
    "wof:placetype":"venue"
},
  "geometry": {"coordinates":[-5.7250041962,40.1045532227],"type":"Point"}
}