{
  "type": "Feature",
  "properties": {
    "addr:full":"Calle de Aneto, 25 Pedrola Zaragoza 50690",
    "addr:housenumber":"25",
    "addr:postcode":"50690",
    "addr:street":"Calle De Aneto",
    "iso:country":"ES",
    "sg:address":"Calle de Aneto, 25",
    "sg:city":"Pedrola",
    "sg:orig_category":"Agentes, Concesionarios Y Sucursales De Veh\u00cdculos",
    "sg:phone":"+34 976 65 45 12",
    "sg:postcode":"50690",
    "sg:province":"Zaragoza",
    "wof:name":"A Y S Automocion S.l.",
    "wof:placetype":"venue"
},
  "geometry": {"coordinates":[-1.1899616718,41.7426185608],"type":"Point"}
}