{
  "type": "Feature",
  "properties": {
    "iso:country":"ES",
    "sg:address":"Donostia Ibilbidea, 52",
    "sg:city":"Astigarraga",
    "sg:orig_category":"Maquinaria Para Industrias Diversas",
    "sg:phone":"+34 943 55 55 50",
    "sg:postcode":"20115",
    "sg:province":"Guip\u00f9zcoa",
    "sg:website":"www.donostisoldadura.com",
    "wof:name":"Donosti Soldadura S.l.",
    "wof:placetype":"venue"
},
  "geometry": {"coordinates":[-1.9504020214,43.2821235657],"type":"Point"}
}