{
  "type": "Feature",
  "properties": {
    "iso:country":"ES",
    "sg:address":"Calle de Ugarte, 11",
    "sg:orig_category":"Molduras, Junquillos, Listones Y Molduras Perforadas",
    "sg:phone":"+34 946 72 56 99",
    "sg:postcode":"01400",
    "sg:province":"\u00c1lava",
    "wof:name":"Florentino Arza Udaeta",
    "wof:placetype":"venue"
},
  "geometry": {"coordinates":[-2.9647090435,43.1417808533],"type":"Point"}
}