{
  "type": "Feature",
  "properties": {
    "iso:country":"ES",
    "sg:address":"Calle de Santa Maria, 48",
    "sg:city":"Magallon",
    "sg:orig_category":"Sindicatos De Trabajadores",
    "sg:phone":"+34 976 85 84 78",
    "sg:postcode":"50520",
    "sg:province":"Zaragoza",
    "wof:name":"Sindicato De Riegos",
    "wof:placetype":"venue"
},
  "geometry": {"coordinates":[-1.4592089653,41.8334083557],"type":"Point"}
}