{
  "type": "Feature",
  "properties": {
    "addr:full":"Calle de Los Arfe, 61 Madrid Madrid 28027",
    "addr:housenumber":"61",
    "addr:postcode":"madrid;28027",
    "addr:street":"Calle De Los Arfe",
    "iso:country":"ES",
    "sg:address":"Calle de Los Arfe, 61",
    "sg:city":"Madrid",
    "sg:orig_category":"Estudios, Instalaci\u00d3n De Climatizaci\u00d3n",
    "sg:phone":"+34 914 07 51 81",
    "sg:postcode":"28027",
    "sg:province":"Madrid",
    "wof:name":"Roman Guerra Justo",
    "wof:placetype":"venue"
},
  "geometry": {"coordinates":[-3.6447339058,40.4407730103],"type":"Point"}
}