{
  "type": "Feature",
  "properties": {
    "addr:full":"Carrer de Munt, 20 S. Andreu Llavaneres Barcelona 08392",
    "addr:housenumber":"20",
    "addr:postcode":"08392",
    "addr:street":"Carrer De Munt;S. Andreu Llavaneres Barcelona",
    "iso:country":"ES",
    "sg:address":"Carrer de Munt, 20",
    "sg:city":"S. Andreu Llavaneres",
    "sg:orig_category":"Perfumer\u00cda (al Por Menor)",
    "sg:phone":"+34 937 95 23 30",
    "sg:postcode":"08392",
    "sg:province":"Barcelona",
    "wof:name":"Perfumeries Ma\u00d1ach S.a.",
    "wof:placetype":"venue"
},
  "geometry": {"coordinates":[2.4824650288,41.5737686157],"type":"Point"}
}