{
  "type": "Feature",
  "properties": {
    "addr:full":"Ctra Barcelona, 6 Viladecans Barcelona 08840",
    "addr:housenumber":"6",
    "addr:postcode":"08840",
    "addr:street":"Ctra Barcelona",
    "iso:country":"ES",
    "sg:address":"Ctra Barcelona, 6",
    "sg:city":"Viladecans",
    "sg:orig_category":"Financiaci\u00d3n Y Cr\u00c9ditos",
    "sg:phone":"+34 936 59 10 34",
    "sg:postcode":"08840",
    "sg:province":"Barcelona",
    "wof:name":"Active And Services Del Baix S.l.",
    "wof:placetype":"venue"
},
  "geometry": {"coordinates":[2.0262799263,41.3205604553],"type":"Point"}
}