{
  "type": "Feature",
  "properties": {
    "iso:country":"ES",
    "sg:address":"Calle de Real, 121",
    "sg:city":"S. Fernando",
    "sg:orig_category":"Inmobiliaria (agencias)",
    "sg:phone":"+34 956 80 08 90",
    "sg:postcode":"11100",
    "sg:province":"C\u00e1diz",
    "wof:name":"Inmobiliaria Quatro Proyectos Jesanfe S.l.l.",
    "wof:placetype":"venue"
},
  "geometry": {"coordinates":[-6.196721077,36.4653587341],"type":"Point"}
}