{
  "type": "Feature",
  "properties": {
    "iso:country":"ES",
    "sg:address":"Avda Ciudad Real, 11",
    "sg:city":"Puertollano",
    "sg:orig_category":"Radiocomunicaciones, Telefon\u00cda M\u00d3vil, Radiomensajer\u00cda: Servicios, Comercializaci\u00d3n",
    "sg:phone":"+34 926 42 33 65",
    "sg:postcode":"13500",
    "sg:province":"Ciudad Real",
    "sg:website":"www.radiodifusion.tv",
    "wof:name":"Radiodifusion Telefonia Y Comunicaciones S.l.",
    "wof:placetype":"venue"
},
  "geometry": {"coordinates":[-4.1071219444,38.697227478],"type":"Point"}
}