{
  "type": "Feature",
  "properties": {
    "iso:country":"ES",
    "sg:address":"Calle de Guardia Civil, La, 21",
    "sg:city":"Valencia",
    "sg:orig_category":"M\u00c9dicos: Pediatr\u00cda. Enfermedades De Los Ni\u00d1os",
    "sg:phone":"+34 963 62 32 84",
    "sg:postcode":"46020",
    "sg:province":"Valencia",
    "wof:name":"Jimenez Perez Blanca Rosa",
    "wof:placetype":"venue"
},
  "geometry": {"coordinates":[-0.3578410149,39.4824256897],"type":"Point"}
}