{
  "type": "Feature",
  "properties": {
    "addr:full":"Pase San Francisco, 9 Badajoz Badajoz 06001",
    "addr:housenumber":"9",
    "addr:postcode":"06001",
    "addr:street":"San Francisco",
    "iso:country":"ES",
    "sg:address":"Pase San Francisco, 9",
    "sg:city":"Badajoz",
    "sg:orig_category":"Centros De Coordinaci\u00d3n",
    "sg:phone":"+34 924 26 07 06",
    "sg:postcode":"06001",
    "sg:province":"Badajoz",
    "wof:name":"Asel Asesores S.l.l.",
    "wof:placetype":"venue"
},
  "geometry": {"coordinates":[-6.9739618301,38.8766555786],"type":"Point"}
}