{
  "type": "Feature",
  "properties": {
    "addr:full":"Calle de Tiboli, 18 Bilbao Vizcaya 48007",
    "addr:housenumber":"18",
    "addr:postcode":"48007",
    "addr:street":"Calle De Tiboli",
    "iso:country":"ES",
    "sg:address":"Calle de Tiboli, 18",
    "sg:city":"Bilbao",
    "sg:orig_category":"Institutos De Belleza",
    "sg:phone":"+34 944 05 11 23",
    "sg:postcode":"48007",
    "sg:province":"Vizcaya",
    "wof:name":"Ascension Sanchez Blanco",
    "wof:placetype":"venue"
},
  "geometry": {"coordinates":[-2.9249053001,43.2674827576],"type":"Point"}
}