{
  "type": "Feature",
  "properties": {
    "iso:country":"ES",
    "sg:address":"Poli Industrial C/v, 16",
    "sg:city":"Rozas De Madrid",
    "sg:orig_category":"Edici\u00d3n De Diarios, Revistas, Boletines",
    "sg:phone":"+34 916 37 74 14",
    "sg:postcode":"28230",
    "sg:province":"Madrid",
    "sg:website":"www.norma-capitel.com",
    "wof:name":"Ediciones Norma Capitel S.l.",
    "wof:placetype":"venue"
},
  "geometry": {"coordinates":[-3.8913800716,40.5247497559],"type":"Point"}
}