{
  "type": "Feature",
  "properties": {
    "addr:full":"Carrer de Sant Cristofor, 12 Mataro Barcelona 08301",
    "addr:housenumber":"12",
    "addr:postcode":"08301",
    "addr:street":"Carrer De Sant Cristofor",
    "iso:country":"ES",
    "sg:address":"Carrer de Sant Cristofor, 12",
    "sg:city":"Mataro",
    "sg:orig_category":"Abogados",
    "sg:phone":"+34 937 96 03 37",
    "sg:postcode":"08301",
    "sg:province":"Barcelona",
    "wof:name":"Julia Blanch Carme",
    "wof:placetype":"venue"
},
  "geometry": {"coordinates":[2.4466400146,41.5400886536],"type":"Point"}
}