{
  "type": "Feature",
  "properties": {
    "iso:country":"ES",
    "sg:address":"Calle de Zeppelin, 18",
    "sg:city":"Poligono El Montalvo",
    "sg:orig_category":"Delegados, Agentes De Tr\u00c1nsito, Auxiliares De Transporte Internacional",
    "sg:phone":"+34 923 19 11 19",
    "sg:postcode":"37188",
    "sg:province":"Salamanca",
    "sg:website":"www.buytrago.es",
    "wof:name":"Tb Express Salamanca S.l.",
    "wof:placetype":"venue"
},
  "geometry": {"coordinates":[-5.6511440277,40.934211731],"type":"Point"}
}