{
  "type": "Feature",
  "properties": {
    "iso:country":"ES",
    "sg:address":"Pl Llibertat, 17",
    "sg:city":"Barcelona",
    "sg:orig_category":"Empresas De Pintura Y Revestimientos",
    "sg:phone":"+34 932 17 44 27",
    "sg:postcode":"08012",
    "sg:province":"Barcelona",
    "wof:name":"Berges Trallero Antonio",
    "wof:placetype":"venue"
},
  "geometry": {"coordinates":[2.1530499458,41.3996887207],"type":"Point"}
}