{
  "type": "Feature",
  "properties": {
    "iso:country":"ES",
    "sg:address":"Calle de San Sebastian, 4",
    "sg:city":"Alcala Henares",
    "sg:orig_category":"Inmobiliaria (agencias)",
    "sg:phone":"+34 918 81 00 02",
    "sg:postcode":"28804",
    "sg:province":"Madrid",
    "wof:name":"Eurofincas Alvarez S.l.",
    "wof:placetype":"venue"
},
  "geometry": {"coordinates":[-3.3398339748,40.4864196777],"type":"Point"}
}