{
  "type": "Feature",
  "properties": {
    "iso:country":"ES",
    "sg:address":"Rua Amor Ruibal, 5",
    "sg:city":"Ourense",
    "sg:orig_category":"Zapatos (al Por Mayor)",
    "sg:phone":"+34 988 22 82 97",
    "sg:postcode":"32005",
    "sg:province":"Ourense",
    "wof:name":"Sara Y Valente S.l.",
    "wof:placetype":"venue"
},
  "geometry": {"coordinates":[-7.8625311852,42.3288803101],"type":"Point"}
}