{
  "type": "Feature",
  "properties": {
    "iso:country":"ES",
    "sg:address":"Benjamin Franklin, S/n",
    "sg:city":"Gijon",
    "sg:orig_category":"Cajas De Ahorro",
    "sg:phone":"+34 985 30 70 56",
    "sg:postcode":"33211",
    "sg:province":"Asturias",
    "sg:website":"www.cajastur.es",
    "wof:name":"Cajastur",
    "wof:placetype":"venue"
},
  "geometry": {"coordinates":[-5.692512989,43.5058479309],"type":"Point"}
}