{
  "type": "Feature",
  "properties": {
    "addr:full":"Rua Travesia De Vigo, 4 Roris Pontevedra 36206",
    "addr:housenumber":"4",
    "addr:postcode":"36206",
    "addr:street":"Rua Travesia De Vigo",
    "iso:country":"ES",
    "sg:address":"Rua Travesia De Vigo, 4",
    "sg:city":"Roris",
    "sg:orig_category":"Mec\u00c1nico Del Autom\u00d3vil",
    "sg:phone":"+34 986 27 27 96",
    "sg:postcode":"36206",
    "sg:province":"Pontevedra",
    "wof:name":"Servicios Del Automovil Talleres Sabincar S.l.",
    "wof:placetype":"venue"
},
  "geometry": {"coordinates":[-8.7020702362,42.237651825],"type":"Point"}
}