{
  "type": "Feature",
  "properties": {
    "addr:full":"Calle de Nuestra Se\u00d1ora De La Luz, 30 Madrid Madrid 28025",
    "addr:housenumber":"30",
    "addr:postcode":"madrid;28025",
    "addr:street":"Calle De Nuestra Sen\u0303Ora De La Luz",
    "iso:country":"ES",
    "sg:address":"Calle de Nuestra Se\u00d1ora De La Luz, 30",
    "sg:city":"Madrid",
    "sg:orig_category":"Farmacias",
    "sg:phone":"+34 914 62 97 94",
    "sg:postcode":"28025",
    "sg:province":"Madrid",
    "wof:name":"San Frutos Andres Maria Dolores",
    "wof:placetype":"venue"
},
  "geometry": {"coordinates":[-3.7441809177,40.3835067749],"type":"Point"}
}