{
  "type": "Feature",
  "properties": {
    "addr:full":"Rua Canizo, 3 Seixalbo Ourense 32970",
    "addr:housenumber":"3",
    "addr:postcode":"32970",
    "addr:street":"Rua Canizo",
    "iso:country":"ES",
    "sg:address":"Rua Canizo, 3",
    "sg:city":"Seixalbo",
    "sg:orig_category":"Tapicer\u00cdas",
    "sg:phone":"+34 988 22 05 71",
    "sg:postcode":"32970",
    "sg:province":"Ourense",
    "wof:name":"Mendez Caneiro Jose",
    "wof:placetype":"venue"
},
  "geometry": {"coordinates":[-7.8508682251,42.3009872437],"type":"Point"}
}