{
  "type": "Feature",
  "properties": {
    "addr:full":"Calle de Federico Oriol, 7 Madrid Madrid 28023",
    "addr:housenumber":"7",
    "addr:postcode":"madrid;28023",
    "addr:street":"Calle De Federico Oriol",
    "iso:country":"ES",
    "sg:address":"Calle de Federico Oriol, 7",
    "sg:city":"Madrid",
    "sg:orig_category":"Empresas De Impermeabilizaci\u00d3n",
    "sg:phone":"+34 917 08 08 23",
    "sg:postcode":"28023",
    "sg:province":"Madrid",
    "sg:website":"www.humycontrol.es",
    "wof:name":"Humesystem S.l.",
    "wof:placetype":"venue"
},
  "geometry": {"coordinates":[-3.8360819817,40.4730300903],"type":"Point"}
}