{
  "type": "Feature",
  "properties": {
    "addr:full":"Carrer de Lope De Vega, 12 Palma Islas Baleares 07013",
    "addr:housenumber":"12",
    "addr:postcode":"07013",
    "addr:street":"Carrer De Lope De Vega",
    "iso:country":"ES",
    "sg:address":"Carrer de Lope De Vega, 12",
    "sg:city":"Palma",
    "sg:orig_category":"Artes Gr\u00c1ficas, Artes Pl\u00c1sticas (curso)",
    "sg:phone":"+34 971 28 26 16",
    "sg:postcode":"07013",
    "sg:province":"Islas Baleares",
    "wof:name":"Toral Rodriguez Angel",
    "wof:placetype":"venue"
},
  "geometry": {"coordinates":[2.6398630142,39.5770339966],"type":"Point"}
}