{
  "type": "Feature",
  "properties": {
    "addr:full":"Calle de Kasune, 31 Algorta Vizcaya 48991",
    "addr:housenumber":"31",
    "addr:postcode":"48991",
    "addr:street":"Calle De Kasune",
    "iso:country":"ES",
    "sg:address":"Calle de Kasune, 31",
    "sg:city":"Algorta",
    "sg:orig_category":"Pescader\u00cdas (al Por Menor)",
    "sg:phone":"+34 944 30 52 24",
    "sg:postcode":"48991",
    "sg:province":"Vizcaya",
    "wof:name":"Castellanos Gomez Rodrigo",
    "wof:placetype":"venue"
},
  "geometry": {"coordinates":[-3.0091900826,43.3553237915],"type":"Point"}
}