{
  "type": "Feature",
  "properties": {
    "addr:full":"Calle de Gomez Acebo, 80 Villanueva Gallego Zaragoza 50830",
    "addr:housenumber":"80",
    "addr:postcode":"50830",
    "addr:street":"Calle De Gomez Acebo",
    "iso:country":"ES",
    "sg:address":"Calle de Gomez Acebo, 80",
    "sg:city":"Villanueva Gallego",
    "sg:orig_category":"Molduras, Junquillos, Listones Y Molduras Perforadas",
    "sg:phone":"+34 976 18 50 93",
    "sg:postcode":"50830",
    "sg:province":"Zaragoza",
    "wof:name":"Hernandez Bernal Alfredo",
    "wof:placetype":"venue"
},
  "geometry": {"coordinates":[-0.8302239776,41.7617950439],"type":"Point"}
}