{
  "type": "Feature",
  "properties": {
    "iso:country":"ES",
    "sg:address":"Urbz La Ribera, 3",
    "sg:city":"Ota\u00f1es",
    "sg:classifiers":[
        {
            "category":"Taxi",
            "type":"Transportation"
        }
    ],
    "sg:phone":"+34 942 85 10 85",
    "sg:postcode":"39707",
    "sg:province":"Cantabria",
    "wof:name":"Barbara Ugalde Alberto",
    "wof:placetype":"venue"
},
  "geometry": {"coordinates":[-3.1923139095,43.3296279907],"type":"Point"}
}