{
  "type": "Feature",
  "properties": {
    "addr:full":"Calle de Jose Grollo, 4 Valencia Valencia 46025",
    "addr:housenumber":"4",
    "addr:postcode":"46025",
    "addr:street":"Calle De Jose Grollo",
    "iso:country":"ES",
    "sg:address":"Calle de Jose Grollo, 4",
    "sg:city":"Valencia",
    "sg:orig_category":"Heladeros",
    "sg:phone":"+34 963 49 02 82",
    "sg:postcode":"46025",
    "sg:province":"Valencia",
    "wof:name":"Barvendo S.l.",
    "wof:placetype":"venue"
},
  "geometry": {"coordinates":[-0.389248997,39.490070343],"type":"Point"}
}