{
  "type": "Feature",
  "properties": {
    "addr:full":"Avda Gasteiz, 5 Vitoria-gasteiz \u00c1lava 01008",
    "addr:housenumber":"5",
    "addr:postcode":"01008",
    "addr:street":"Avda Gasteiz",
    "iso:country":"ES",
    "sg:address":"Avda Gasteiz, 5",
    "sg:city":"Vitoria-gasteiz",
    "sg:orig_category":"Comercio, Reparaci\u00d3n De Bicicletas, De Motocicletas, De Accesorios",
    "sg:phone":"+34 945 00 45 11",
    "sg:postcode":"01008",
    "sg:province":"\u00c1lava",
    "wof:name":"Felipe Ya\u00f1ez De La Torre",
    "wof:placetype":"venue"
},
  "geometry": {"coordinates":[-2.6828598976,42.8431472778],"type":"Point"}
}