{
  "type": "Feature",
  "properties": {
    "iso:country":"ES",
    "sg:address":"Av Martin Mendez, S/n",
    "sg:city":"Estepona",
    "sg:orig_category":"Muebles, Minoristas",
    "sg:phone":"+34 952 80 65 89",
    "sg:postcode":"29680",
    "sg:province":"M\u00e1laga",
    "wof:name":"Don Ambiente Muebles Dise\u00f1o Y Decoracion S.l.",
    "wof:placetype":"venue"
},
  "geometry": {"coordinates":[-5.1580600739,36.4285812378],"type":"Point"}
}