{
  "type": "Feature",
  "properties": {
    "iso:country":"ES",
    "sg:address":"Ctra. Mora, S/n",
    "sg:city":"Orgaz",
    "sg:orig_category":"Aceites Y Grasas Alimentarias (fabricaci\u00d3n, Al Por Mayor)",
    "sg:phone":"+34 925 34 72 50",
    "sg:postcode":"45450",
    "sg:province":"Toledo",
    "wof:name":"Almazara Villa De Orgaz",
    "wof:placetype":"venue"
},
  "geometry": {"coordinates":[-3.8696951866,39.6501922607],"type":"Point"}
}