{
  "type": "Feature",
  "properties": {
    "iso:country":"ES",
    "sg:address":"Calle de Simon Ruiz, 5",
    "sg:city":"Medina Campo",
    "sg:orig_category":"Cuchiller\u00cda (al Por Menor)",
    "sg:phone":"+34 983 80 28 63",
    "sg:postcode":"47400",
    "sg:province":"Valladolid",
    "wof:name":"Conde Fernandez Antonina",
    "wof:placetype":"venue"
},
  "geometry": {"coordinates":[-4.9129090309,41.3068161011],"type":"Point"}
}