{
  "type": "Feature",
  "properties": {
    "iso:country":"ES",
    "sg:address":"Infantes, 1",
    "sg:city":"Muros",
    "sg:orig_category":"Agentes Generales De Seguros",
    "sg:phone":"+34 981 82 71 50",
    "sg:postcode":"15250",
    "sg:province":"A Coru\u00f1a",
    "wof:name":"Viajes Pi\u00f1eiros S.l.",
    "wof:placetype":"venue"
},
  "geometry": {"coordinates":[-9.0572490692,42.7736206055],"type":"Point"}
}