{
  "type": "Feature",
  "properties": {
    "iso:country":"ES",
    "sg:address":"Calle de Prim, 18",
    "sg:city":"Donostia-san Sebastian",
    "sg:orig_category":"Oficinas: Suministros Para (fabricaci\u00d3n, Al Por Mayor)",
    "sg:phone":"+34 943 46 67 23",
    "sg:postcode":"20006",
    "sg:province":"Guip\u00f9zcoa",
    "sg:website":"www.ofimaticarosana.com",
    "wof:name":"Rodilla Iglesias Jorge",
    "wof:placetype":"venue"
},
  "geometry": {"coordinates":[-1.9801059961,43.3162384033],"type":"Point"}
}