{
  "type": "Feature",
  "properties": {
    "addr:full":"Rua Frei Rosendo Salvado (de), 8 Santiago De Compostela A Coru\u00f1a 15701",
    "addr:housenumber":"8",
    "addr:postcode":"15701",
    "addr:street":"Rua Frei Rosendo Salvado De;Corun\u0303A",
    "iso:country":"ES",
    "sg:address":"Rua Frei Rosendo Salvado (de), 8",
    "sg:city":"Santiago De Compostela",
    "sg:orig_category":"Radiocomunicaciones, Telefon\u00cda M\u00d3vil, Radiomensajer\u00cda: Servicios, Comercializaci\u00d3n",
    "sg:phone":"+34 981 59 83 73",
    "sg:postcode":"15701",
    "sg:province":"A Coru\u00f1a",
    "sg:website":"www.telyco.es",
    "wof:name":"Teleinformatica Y Comunicaciones S.a.",
    "wof:placetype":"venue"
},
  "geometry": {"coordinates":[-8.5501537323,42.8739585876],"type":"Point"}
}