{
  "type": "Feature",
  "properties": {
    "iso:country":"ES",
    "sg:address":"Calle de Barquillo, 26",
    "sg:city":"Madrid",
    "sg:orig_category":"Complementos De Vestir (al Por Menor)",
    "sg:phone":"+34 915 22 49 71",
    "sg:postcode":"28004",
    "sg:province":"Madrid",
    "wof:name":"Kassen Y Zapata S L",
    "wof:placetype":"venue"
},
  "geometry": {"coordinates":[-3.6956079006,40.4224205017],"type":"Point"}
}