{
  "type": "Feature",
  "properties": {
    "addr:full":"Rua Camilo Veiga, 10 Vigo Pontevedra 36208",
    "addr:housenumber":"10",
    "addr:postcode":"36208",
    "addr:street":"Rua Camilo Veiga",
    "iso:country":"ES",
    "sg:address":"Rua Camilo Veiga, 10",
    "sg:city":"Vigo",
    "sg:orig_category":"Electricidad: Instaladores",
    "sg:phone":"+34 986 23 01 82",
    "sg:postcode":"36208",
    "sg:province":"Pontevedra",
    "wof:name":"Talleres Bahia Vigo S.l.",
    "wof:placetype":"venue"
},
  "geometry": {"coordinates":[-8.7497873306,42.223110199],"type":"Point"}
}