{
  "type": "Feature",
  "properties": {
    "addr:full":"Avda Galicia De, 23 Luarca Asturias 33700",
    "addr:housenumber":"23",
    "addr:postcode":"33700",
    "addr:street":"Avda Galicia De",
    "iso:country":"ES",
    "sg:address":"Avda Galicia De, 23",
    "sg:city":"Luarca",
    "sg:orig_category":"Peluqueros: De Se\u00d1oras",
    "sg:phone":"+34 985 64 10 71",
    "sg:postcode":"33700",
    "sg:province":"Asturias",
    "wof:name":"Perez Alvarez Sara",
    "wof:placetype":"venue"
},
  "geometry": {"coordinates":[-6.5396680832,43.5403404236],"type":"Point"}
}