{
  "type": "Feature",
  "properties": {
    "iso:country":"ES",
    "sg:address":"Calle de Amezti, 41",
    "sg:city":"Igeldo",
    "sg:orig_category":"Fotograf\u00cda Publicitaria E Industrial",
    "sg:phone":"+34 943 31 40 13",
    "sg:postcode":"20008",
    "sg:province":"Guip\u00f9zcoa",
    "wof:name":"Imagen Fx Fotografica Publicitaria Y Multimedia S.l.",
    "wof:placetype":"venue"
},
  "geometry": {"coordinates":[-2.0282042027,43.317741394],"type":"Point"}
}