{
  "type": "Feature",
  "properties": {
    "addr:full":"Avda Aragon (de), S/n San Sebastian De Los Reyes Madrid 28700",
    "addr:housenumber":"/ n",
    "addr:postcode":"28700",
    "addr:street":"Avda Aragon De S",
    "iso:country":"ES",
    "sg:address":"Avda Aragon (de), S/n",
    "sg:city":"San Sebastian De Los Reyes",
    "sg:orig_category":"Molduras, Junquillos, Listones Y Molduras Perforadas",
    "sg:phone":"+34 916 54 52 06",
    "sg:postcode":"28700",
    "sg:province":"Madrid",
    "wof:name":"Telemensaje S.a.",
    "wof:placetype":"venue"
},
  "geometry": {"coordinates":[-3.6355340481,40.5586051941],"type":"Point"}
}