{
  "type": "Feature",
  "properties": {
    "addr:full":"Calle de La Rua, 25 Benavente Zamora 49600",
    "addr:housenumber":"25",
    "addr:postcode":"49600",
    "addr:street":"Calle De La Rua",
    "iso:country":"ES",
    "sg:address":"Calle de La Rua, 25",
    "sg:city":"Benavente",
    "sg:orig_category":"Contables",
    "sg:phone":"+34 980 63 35 21",
    "sg:postcode":"49600",
    "sg:province":"Zamora",
    "wof:name":"Sancho Nu\u00f1ez Santiago",
    "wof:placetype":"venue"
},
  "geometry": {"coordinates":[-5.6792140007,42.0021514893],"type":"Point"}
}