{
  "type": "Feature",
  "properties": {
    "addr:full":"Av Antoni Maura, 129 Inca Islas Baleares 07300",
    "addr:housenumber":"129",
    "addr:postcode":"07300",
    "addr:street":"Av Antoni Maura",
    "iso:country":"ES",
    "sg:address":"Av Antoni Maura, 129",
    "sg:city":"Inca",
    "sg:orig_category":"Empresas De Portes Y Mensajer\u00cda",
    "sg:phone":"+34 971 50 37 11",
    "sg:postcode":"07300",
    "sg:province":"Islas Baleares",
    "sg:website":"www.mrw.es",
    "wof:name":"Retto Expres S.l.",
    "wof:placetype":"venue"
},
  "geometry": {"coordinates":[2.9027900696,39.72108078],"type":"Point"}
}