{
  "type": "Feature",
  "properties": {
    "addr:full":"Rua Santa Ana, 25 Ponteareas Pontevedra 36860",
    "addr:housenumber":"25",
    "addr:postcode":"36860",
    "addr:street":"Rua Santa Ana",
    "iso:country":"ES",
    "sg:address":"Rua Santa Ana, 25",
    "sg:city":"Ponteareas",
    "sg:orig_category":"Inmobiliaria (agencias)",
    "sg:phone":"+34 986 64 08 03",
    "sg:postcode":"36860",
    "sg:province":"Pontevedra",
    "sg:website":"www.inmobiliariaponteareas1.com",
    "wof:name":"Inmobiliaria Ponteareas C.b.",
    "wof:placetype":"venue"
},
  "geometry": {"coordinates":[-8.5323896408,42.1836967468],"type":"Point"}
}