{
  "type": "Feature",
  "properties": {
    "iso:country":"ES",
    "sg:address":"Av. Scho Fuerte, 26",
    "sg:city":"Iru\u00f1a",
    "sg:orig_category":"Asesor\u00cda Sobre Comunicaci\u00d3n De Empresas",
    "sg:phone":"+34 948 17 00 10",
    "sg:postcode":"31008",
    "sg:province":"Navarra",
    "wof:name":"Iturriaga Fernandez De Jauregui Jon Y Perez Carlos Oscar G.s.gestion De Sanciones",
    "wof:placetype":"venue"
},
  "geometry": {"coordinates":[-1.6687812805,42.8102302551],"type":"Point"}
}