{
  "type": "Feature",
  "properties": {
    "iso:country":"ES",
    "sg:address":"Carrer de Sant Damia, 251",
    "sg:city":"Terrassa",
    "sg:orig_category":"Molduras, Junquillos, Listones Y Molduras Perforadas",
    "sg:phone":"+34 937 85 01 06",
    "sg:postcode":"08222",
    "sg:province":"Barcelona",
    "wof:name":"Claret Ponsarnau Ramona",
    "wof:placetype":"venue"
},
  "geometry": {"coordinates":[2.0294229984,41.5673332214],"type":"Point"}
}