{
  "type": "Feature",
  "properties": {
    "addr:full":"Bda. Esglesia, 3 Avellanes Lleida 25612",
    "addr:housenumber":"3",
    "addr:postcode":"25612",
    "addr:street":"Bda. Esglesia",
    "iso:country":"ES",
    "sg:address":"Bda. Esglesia, 3",
    "sg:city":"Avellanes",
    "sg:orig_category":"Administraciones Regionales, Departamentales Y Locales",
    "sg:phone":"+34 973 45 40 04",
    "sg:postcode":"25612",
    "sg:province":"Lleida",
    "wof:name":"Ajuntament De Avellanes Y Santali\u00f1a",
    "wof:placetype":"venue"
},
  "geometry": {"coordinates":[0.6257824898,41.614151001],"type":"Point"}
}