{
  "type": "Feature",
  "properties": {
    "addr:full":"Calle de Ancha, 17 Le\u00f3n Le\u00f3n 24003",
    "addr:housenumber":"17",
    "addr:postcode":"24003",
    "addr:street":"Calle De Ancha;Leo\u0301N",
    "iso:country":"ES",
    "sg:address":"Calle de Ancha, 17",
    "sg:city":"Le\u00f3n",
    "sg:orig_category":"Electricidad, Electr\u00d3nica: Suministros (al Por Menor)",
    "sg:phone":"+34 987 25 63 26",
    "sg:postcode":"24003",
    "sg:province":"Le\u00f3n",
    "wof:name":"Sacristan Campano Federico",
    "wof:placetype":"venue"
},
  "geometry": {"coordinates":[-5.5694518089,42.5983123779],"type":"Point"}
}