{
  "type": "Feature",
  "properties": {
    "iso:country":"ES",
    "sg:address":"Calle de San Juan, 15",
    "sg:city":"Logro\u00f1o",
    "sg:orig_category":"Molduras, Junquillos, Listones Y Molduras Perforadas",
    "sg:phone":"+34 941 25 98 79",
    "sg:postcode":"26001",
    "sg:province":"La Rioja",
    "wof:name":"Cabezon Saenz Maria Del Pilar",
    "wof:placetype":"venue"
},
  "geometry": {"coordinates":[-2.4447159767,42.4659423828],"type":"Point"}
}