{
  "type": "Feature",
  "properties": {
    "iso:country":"ES",
    "sg:address":"Carr Om(de), 4",
    "sg:city":"Guissona",
    "sg:orig_category":"Reposter\u00cdas",
    "sg:phone":"+34 973 55 03 07",
    "sg:postcode":"25210",
    "sg:province":"Lleida",
    "wof:name":"Sole Codina Carlos",
    "wof:placetype":"venue"
},
  "geometry": {"coordinates":[1.2883419991,41.7851409912],"type":"Point"}
}