{
  "type": "Feature",
  "properties": {
    "iso:country":"ES",
    "sg:address":"Calle de Agustin Rodriguez Sahagun, 3",
    "sg:city":"Avila",
    "sg:orig_category":"Ense\u00d1anza Variada",
    "sg:phone":"+34 920 25 45 53",
    "sg:postcode":"05003",
    "sg:province":"\u00c1vila",
    "wof:name":"Talavera Zuil Juan Luis",
    "wof:placetype":"venue"
},
  "geometry": {"coordinates":[-4.6837248802,40.648109436],"type":"Point"}
}