{
  "type": "Feature",
  "properties": {
    "addr:full":"Calle de Baja, 2 Gallur Zaragoza 50650",
    "addr:housenumber":"2",
    "addr:postcode":"50650",
    "addr:street":"Calle De Baja",
    "iso:country":"ES",
    "sg:address":"Calle de Baja, 2",
    "sg:city":"Gallur",
    "sg:orig_category":"Asociaciones, Organismos Culturales Y Socioeducativos",
    "sg:phone":"+34 976 85 73 32",
    "sg:postcode":"50650",
    "sg:province":"Zaragoza",
    "wof:name":"Ayuntamiento De Gallur",
    "wof:placetype":"venue"
},
  "geometry": {"coordinates":[-1.3176779747,41.8689994812],"type":"Point"}
}