{
  "type": "Feature",
  "properties": {
    "addr:full":"Calle de Virgen Del Puig, 5 Alacant Alicante 03009",
    "addr:housenumber":"5",
    "addr:postcode":"03009",
    "addr:street":"Calle De Virgen Del Puig",
    "iso:country":"ES",
    "sg:address":"Calle de Virgen Del Puig, 5",
    "sg:city":"Alacant",
    "sg:orig_category":"Peluqueros: De Se\u00d1oras",
    "sg:phone":"+34 965 17 27 29",
    "sg:postcode":"03009",
    "sg:province":"Alicante",
    "wof:name":"Mu\u00f1oz Teruel Purificacion",
    "wof:placetype":"venue"
},
  "geometry": {"coordinates":[-0.4993070066,38.3684616089],"type":"Point"}
}