{
  "type": "Feature",
  "properties": {
    "addr:full":"Carrer de Cuba (de), 5 Vilassar De Mar Barcelona 08340",
    "addr:postcode":"08340",
    "addr:street":"Carrer De Cuba De",
    "iso:country":"ES",
    "sg:address":"Carrer de Cuba (de), 5",
    "sg:city":"Vilassar De Mar",
    "sg:orig_category":"Empresas De Carpinter\u00cda De Madera",
    "sg:phone":"+34 937 50 23 94",
    "sg:postcode":"08340",
    "sg:province":"Barcelona",
    "wof:name":"Ruiz Ruiz Manuel",
    "wof:placetype":"venue"
},
  "geometry": {"coordinates":[2.3881390095,41.5002403259],"type":"Point"}
}