{
  "type": "Feature",
  "properties": {
    "addr:full":"Avda Valle De Esgueva, 33 Valladolid Valladolid 47011",
    "addr:housenumber":"33",
    "addr:postcode":"47011",
    "addr:street":"Avda Valle De Esgueva",
    "iso:country":"ES",
    "sg:address":"Avda Valle De Esgueva, 33",
    "sg:city":"Valladolid",
    "sg:orig_category":"Inmobiliaria (agencias)",
    "sg:phone":"+34 983 25 06 44",
    "sg:postcode":"47011",
    "sg:province":"Valladolid",
    "wof:name":"Promociones La Caba\u00f1ina S.l.",
    "wof:placetype":"venue"
},
  "geometry": {"coordinates":[-4.7084388733,41.6595191956],"type":"Point"}
}