{
  "type": "Feature",
  "properties": {
    "addr:full":"Carrer de Bori I Fontesta, 19 Barcelona Barcelona 08021",
    "addr:housenumber":"19",
    "addr:postcode":"08021",
    "addr:street":"Carrer De Bori I Fontesta",
    "iso:country":"ES",
    "sg:address":"Carrer de Bori I Fontesta, 19",
    "sg:city":"Barcelona",
    "sg:orig_category":"Peluquer\u00cdas, Peluquer\u00cda Mixta",
    "sg:phone":"+34 932 09 84 26",
    "sg:postcode":"08021",
    "sg:province":"Barcelona",
    "sg:website":"www.cebado.es",
    "wof:name":"Peluqueria Turo Park S.a.",
    "wof:placetype":"venue"
},
  "geometry": {"coordinates":[2.1398239136,41.3931808472],"type":"Point"}
}