{
  "type": "Feature",
  "properties": {
    "iso:country":"ES",
    "sg:address":"Calle de Molino, 10",
    "sg:city":"Bu\u00f1ol",
    "sg:orig_category":"Carnicer\u00cdas, Carnicer\u00cdas",
    "sg:phone":"+34 962 50 13 64",
    "sg:postcode":"46360",
    "sg:province":"Valencia",
    "wof:name":"Valles Cervera Rafael",
    "wof:placetype":"venue"
},
  "geometry": {"coordinates":[-0.7902560234,39.4173812866],"type":"Point"}
}