{
  "type": "Feature",
  "properties": {
    "iso:country":"ES",
    "sg:address":"Pite, 4",
    "sg:city":"Pite",
    "sg:orig_category":"Venta, Instalaci\u00d3n De Calefacci\u00d3n",
    "sg:phone":"+34 981 80 95 20",
    "sg:postcode":"15883",
    "sg:province":"A Coru\u00f1a",
    "wof:name":"Seijo Fero Javier",
    "wof:placetype":"venue"
},
  "geometry": {"coordinates":[-8.5444011688,42.8382263184],"type":"Point"}
}