{
  "type": "Feature",
  "properties": {
    "iso:country":"ES",
    "sg:address":"Calle de Zubiaurre, 1",
    "sg:city":"Errenteria",
    "sg:orig_category":"Molduras, Junquillos, Listones Y Molduras Perforadas",
    "sg:phone":"+34 943 52 67 42",
    "sg:postcode":"20100",
    "sg:province":"Guip\u00f9zcoa",
    "wof:name":"Maria Josefa Otero Mujika",
    "wof:placetype":"venue"
},
  "geometry": {"coordinates":[-1.8982399702,43.3137512207],"type":"Point"}
}