{
  "type": "Feature",
  "properties": {
    "iso:country":"ES",
    "sg:address":"Carr Sant Gregori, 3",
    "sg:city":"Vilanova I La Geltru",
    "sg:orig_category":"Panader\u00cdas, Panader\u00cdas",
    "sg:phone":"+34 938 93 09 29",
    "sg:postcode":"08800",
    "sg:province":"Barcelona",
    "wof:name":"Raventos Calvo Gemma",
    "wof:placetype":"venue"
},
  "geometry": {"coordinates":[1.7251629829,41.2263298035],"type":"Point"}
}