{
  "type": "Feature",
  "properties": {
    "addr:full":"Av Selva, 2 Amer Girona 17170",
    "addr:housenumber":"2",
    "addr:postcode":"17170",
    "addr:street":"Av Selva",
    "iso:country":"ES",
    "sg:address":"Av Selva, 2",
    "sg:city":"Amer",
    "sg:orig_category":"Chapister\u00cda",
    "sg:phone":"+34 972 43 00 13",
    "sg:postcode":"17170",
    "sg:province":"Girona",
    "sg:website":"automociolluis@bicicarril.com",
    "wof:name":"Automocio Lluis S.l.",
    "wof:placetype":"venue"
},
  "geometry": {"coordinates":[2.6049439907,42.0074653625],"type":"Point"}
}