{
  "type": "Feature",
  "properties": {
    "addr:full":"Calle de Albudeite, 2 S. Pedro Pinatar Murcia 30740",
    "addr:housenumber":"2",
    "addr:postcode":"30740",
    "addr:street":"Calle De Albudeite",
    "iso:country":"ES",
    "sg:address":"Calle de Albudeite, 2",
    "sg:city":"S. Pedro Pinatar",
    "sg:orig_category":"Arquitectos",
    "sg:phone":"+34 968 17 86 77",
    "sg:postcode":"30740",
    "sg:province":"Murcia",
    "wof:name":"Martinez Martinez Valentin",
    "wof:placetype":"venue"
},
  "geometry": {"coordinates":[-0.7870572805,37.8358078003],"type":"Point"}
}