{
  "type": "Feature",
  "properties": {
    "iso:country":"ES",
    "sg:address":"Plaz Eduardo Linares, 12",
    "sg:city":"Molina Segura",
    "sg:orig_category":"Agencias Y Agentes Comerciales, Representantes",
    "sg:phone":"+34 968 61 18 07",
    "sg:postcode":"30500",
    "sg:province":"Murcia",
    "wof:name":"Ros Martinez Dolores",
    "wof:placetype":"venue"
},
  "geometry": {"coordinates":[-1.2130099535,38.0563201904],"type":"Point"}
}