{
  "type": "Feature",
  "properties": {
    "iso:country":"ES",
    "sg:address":"Heliche, 3",
    "sg:city":"Olivares",
    "sg:orig_category":"Zapatos (al Por Menor)",
    "sg:phone":"+34 955 71 89 81",
    "sg:postcode":"41804",
    "sg:province":"Sevilla",
    "wof:name":"Rodriguez Garcia Francisco Javier",
    "wof:placetype":"venue"
},
  "geometry": {"coordinates":[-6.1581602097,37.4181022644],"type":"Point"}
}