{
  "type": "Feature",
  "properties": {
    "iso:country":"ES",
    "sg:address":"Avda General Palacio, 2",
    "sg:city":"Getafe",
    "sg:orig_category":"Cajas De Ahorro",
    "sg:phone":"+34 916 01 10 25",
    "sg:postcode":"28902",
    "sg:province":"Madrid",
    "sg:website":"www.cam.es",
    "wof:name":"Caja De Ahorros Del Mediterraneo",
    "wof:placetype":"venue"
},
  "geometry": {"coordinates":[-3.7272489071,40.3086051941],"type":"Point"}
}