{
  "type": "Feature",
  "properties": {
    "iso:country":"ES",
    "sg:address":"Carrer de Pi I Gibert, 8",
    "sg:city":"S. Adria Besos",
    "sg:orig_category":"Electricidad, Electr\u00d3nica: Material Y Suministros (al Por Mayor)",
    "sg:phone":"+34 933 81 96 80",
    "sg:postcode":"08930",
    "sg:province":"Barcelona",
    "sg:website":"www.deckersoft.com",
    "wof:name":"Ruiz Sanchez Juan Carlos",
    "wof:placetype":"venue"
},
  "geometry": {"coordinates":[2.2153689861,41.4305000305],"type":"Point"}
}