{
  "type": "Feature",
  "properties": {
    "iso:country":"ES",
    "sg:address":"Calle de Canarias, 4",
    "sg:city":"Granadilla Abona",
    "sg:orig_category":"Florister\u00cdas",
    "sg:phone":"+34 922 77 18 81",
    "sg:postcode":"38600",
    "sg:province":"Santa Cruz De Tenerife",
    "wof:name":"Gaspar Gonzalez Carmen",
    "wof:placetype":"venue"
},
  "geometry": {"coordinates":[-16.576166153,28.1189479828],"type":"Point"}
}