{
  "type": "Feature",
  "properties": {
    "addr:full":"Carr Rectoria, 1 Viladrau Girona 17406",
    "addr:housenumber":"1",
    "addr:postcode":"17406",
    "addr:street":"Carr Rectoria",
    "iso:country":"ES",
    "sg:address":"Carr Rectoria, 1",
    "sg:city":"Viladrau",
    "sg:orig_category":"Comunidades Religiosas",
    "sg:phone":"+34 938 84 92 07",
    "sg:postcode":"17406",
    "sg:province":"Girona",
    "wof:name":"Bisbat De Vic",
    "wof:placetype":"venue"
},
  "geometry": {"coordinates":[2.3917369843,41.8470344543],"type":"Point"}
}