{
  "type": "Feature",
  "properties": {
    "iso:country":"ES",
    "sg:address":"Calle de Julio Burell, 9",
    "sg:city":"Linares",
    "sg:orig_category":"M\u00c1rmoles, Granitos Y Piedras Naturales",
    "sg:phone":"+34 953 69 38 60",
    "sg:postcode":"23700",
    "sg:province":"Ja\u00e9n",
    "wof:name":"Vargas Martinez Miguel",
    "wof:placetype":"venue"
},
  "geometry": {"coordinates":[-3.6341559887,38.0986671448],"type":"Point"}
}