{
  "type": "Feature",
  "properties": {
    "iso:country":"ES",
    "sg:address":"Enparan Kalea, 4",
    "sg:city":"Azpeitia",
    "sg:orig_category":"Procuradores",
    "sg:phone":"+34 943 81 12 58",
    "sg:postcode":"20730",
    "sg:province":"Guip\u00f9zcoa",
    "wof:name":"Echaniz Aizpurua Angel",
    "wof:placetype":"venue"
},
  "geometry": {"coordinates":[-2.2653200626,43.1838760376],"type":"Point"}
}