{
  "type": "Feature",
  "properties": {
    "iso:country":"ES",
    "sg:address":"Calle de Plaza (de La), 54",
    "sg:city":"Fuenlabrada",
    "sg:orig_category":"M\u00c9dicos: Medicina General",
    "sg:phone":"+34 916 06 64 05",
    "sg:postcode":"28944",
    "sg:province":"Madrid",
    "wof:name":"Centro Medico De La Plaza S.l.",
    "wof:placetype":"venue"
},
  "geometry": {"coordinates":[-3.7953510284,40.2834739685],"type":"Point"}
}