{
  "type": "Feature",
  "properties": {
    "iso:country":"ES",
    "sg:address":"Carrer de Sant Erasme, 10",
    "sg:city":"Barcelona",
    "sg:orig_category":"Venta, Instalaci\u00d3n De Calefacci\u00d3n",
    "sg:phone":"+34 934 42 76 49",
    "sg:postcode":"08001",
    "sg:province":"Barcelona",
    "wof:name":"Calefaccion Etna S.l.",
    "wof:placetype":"venue"
},
  "geometry": {"coordinates":[2.1642830372,41.381439209],"type":"Point"}
}