{
  "type": "Feature",
  "properties": {
    "iso:country":"ES",
    "sg:address":"Calle de Real, 161",
    "sg:city":"Yuncos",
    "sg:orig_category":"Antig\u00dcedades (coches Y Motos)",
    "sg:phone":"+34 925 53 60 83",
    "sg:postcode":"45210",
    "sg:province":"Toledo",
    "wof:name":"Escolar Palacios Cristian",
    "wof:placetype":"venue"
},
  "geometry": {"coordinates":[-3.8733189106,40.0875511169],"type":"Point"}
}