{
  "type": "Feature",
  "properties": {
    "addr:full":"Carr Riera Ma\u00c7ana, 69 Girona Girona 17006",
    "addr:housenumber":"69",
    "addr:postcode":"17006",
    "addr:street":"Carr Riera Mac\u0327Ana",
    "iso:country":"ES",
    "sg:address":"Carr Riera Ma\u00c7ana, 69",
    "sg:city":"Girona",
    "sg:orig_category":"Cajas De Ahorro",
    "sg:phone":"+34 972 24 92 16",
    "sg:postcode":"17006",
    "sg:province":"Girona",
    "wof:name":"Caja De Ahorros De Valencia Castellon Y Alicante",
    "wof:placetype":"venue"
},
  "geometry": {"coordinates":[2.8187448978,41.9808616638],"type":"Point"}
}