{
  "type": "Feature",
  "properties": {
    "addr:full":"Poli Industrial Berriainz, S/n Berriozar Navarra 31013",
    "addr:housenumber":"s / n",
    "addr:postcode":"31013",
    "iso:country":"ES",
    "sg:address":"Poli Industrial Berriainz, S/n",
    "sg:city":"Berriozar",
    "sg:orig_category":"Centros Empresariales",
    "sg:phone":"+34 948 35 19 47",
    "sg:postcode":"31013",
    "sg:province":"Navarra",
    "wof:name":"Leurtza Zelai, Sl",
    "wof:placetype":"venue"
},
  "geometry": {"coordinates":[-97.78224945069999,45.7040786743],"type":"Point"}
}