{
  "type": "Feature",
  "properties": {
    "addr:full":"Se\u00f1orio De Amocain, 3 Iru\u00f1a Navarra 31016",
    "addr:housenumber":"3",
    "addr:postcode":"31016",
    "addr:street":"Irun\u0303A Navarra",
    "iso:country":"ES",
    "sg:address":"Se\u00f1orio De Amocain, 3",
    "sg:city":"Iru\u00f1a",
    "sg:orig_category":"Reparaci\u00d3n De Aparatos A Gas",
    "sg:phone":"+34 948 16 28 90",
    "sg:postcode":"31016",
    "sg:province":"Navarra",
    "wof:name":"Aribe Inmuebles S.l.",
    "wof:placetype":"venue"
},
  "geometry": {"coordinates":[-1.6118886471,42.8133087158],"type":"Point"}
}