{
  "type": "Feature",
  "properties": {
    "iso:country":"ES",
    "sg:address":"Pase Echegaray Y Caballero, 124",
    "sg:city":"Zaragoza",
    "sg:orig_category":"Fabricaci\u00d3n De Etiquetas",
    "sg:phone":"+34 976 29 72 38",
    "sg:postcode":"50001",
    "sg:province":"Zaragoza",
    "wof:name":"Offisa Ecoval S.l.",
    "wof:placetype":"venue"
},
  "geometry": {"coordinates":[-0.8731960058,41.6549301147],"type":"Point"}
}