{
  "type": "Feature",
  "properties": {
    "iso:country":"ES",
    "sg:address":"Calle de Lurbeltzeta Kalea, 4",
    "sg:city":"Zizur Mayor",
    "sg:orig_category":"Carnicer\u00cdas, Carnicer\u00cdas",
    "sg:phone":"+34 948 18 95 50",
    "sg:postcode":"31180",
    "sg:province":"Navarra",
    "wof:name":"Lasterra Aranaz Victorio",
    "wof:placetype":"venue"
},
  "geometry": {"coordinates":[-1.6906483173,42.7879600525],"type":"Point"}
}