{
  "type": "Feature",
  "properties": {
    "iso:country":"ES",
    "sg:address":"Koldo Eleizalde Kalea, 1",
    "sg:city":"Bergara",
    "sg:orig_category":"Ropa Para Se\u00d1oras Y Caballeros (al Por Menor)",
    "sg:phone":"+34 943 76 09 87",
    "sg:postcode":"20570",
    "sg:province":"Guip\u00f9zcoa",
    "wof:name":"Laket Arrasate S.l.",
    "wof:placetype":"venue"
},
  "geometry": {"coordinates":[-2.4089651108,43.1194000244],"type":"Point"}
}