{
  "type": "Feature",
  "properties": {
    "iso:country":"ES",
    "sg:address":"Carrer de Cort (la), 35",
    "sg:city":"Vilafranca Penedes",
    "sg:orig_category":"Ropa Para Ni\u00d1os (al Por Menor)",
    "sg:phone":"+34 938 18 22 53",
    "sg:postcode":"08720",
    "sg:province":"Barcelona",
    "wof:name":"Marti Capdevila Maria Carmen",
    "wof:placetype":"venue"
},
  "geometry": {"coordinates":[1.6979180574,41.3460845947],"type":"Point"}
}