{
  "type": "Feature",
  "properties": {
    "iso:country":"ES",
    "sg:address":"Pg Paisos Catalans, 18",
    "sg:city":"Salt",
    "sg:orig_category":"Reposter\u00cdas",
    "sg:phone":"+34 972 24 46 52",
    "sg:postcode":"17190",
    "sg:province":"Girona",
    "wof:name":"Forn Cresell S.l.",
    "wof:placetype":"venue"
},
  "geometry": {"coordinates":[2.7874689102,41.9717559814],"type":"Point"}
}