{
  "type": "Feature",
  "properties": {
    "iso:country":"ES",
    "sg:address":"Calle de Vicente Navarro, 3",
    "sg:city":"Onil",
    "sg:orig_category":"Aguas (distribuci\u00d3n, Servicios)",
    "sg:phone":"+34 965 56 45 11",
    "sg:postcode":"03430",
    "sg:province":"Alicante",
    "wof:name":"Aquagest Levante S.a.",
    "wof:placetype":"venue"
},
  "geometry": {"coordinates":[-0.6737095714,38.6297912598],"type":"Point"}
}