{
  "type": "Feature",
  "properties": {
    "addr:full":"Ctra Nova, 7 Alcanar Tarragona 43530",
    "addr:housenumber":"7",
    "addr:postcode":"43530",
    "addr:street":"Ctra Nova",
    "iso:country":"ES",
    "sg:address":"Ctra Nova, 7",
    "sg:city":"Alcanar",
    "sg:orig_category":"Zapatos (al Por Menor)",
    "sg:phone":"+34 977 73 13 34",
    "sg:postcode":"43530",
    "sg:province":"Tarragona",
    "wof:name":"Peuets S.ll",
    "wof:placetype":"venue"
},
  "geometry": {"coordinates":[0.4806399941,40.5423088074],"type":"Point"}
}