{
  "type": "Feature",
  "properties": {
    "iso:country":"ES",
    "sg:address":"Ctra Estacion (de La), S/n",
    "sg:city":"Carretera Estacion",
    "sg:orig_category":"Papel (al Por Mayor)",
    "sg:phone":"+34 968 45 91 38",
    "sg:postcode":"30540",
    "sg:province":"Murcia",
    "wof:name":"Papelera Del Segura S.a.",
    "wof:placetype":"venue"
},
  "geometry": {"coordinates":[-1.3252439499,38.223651886],"type":"Point"}
}