{
  "type": "Feature",
  "properties": {
    "iso:country":"ES",
    "sg:address":"Cami Ral, S/n",
    "sg:city":"Serra",
    "sg:orig_category":"Galvanizaci\u00d3n, Esta\u00d1ado, Emplomado",
    "sg:phone":"+34 938 43 96 66",
    "sg:postcode":"08185",
    "sg:province":"Barcelona",
    "wof:name":"Unizinc S.a.",
    "wof:placetype":"venue"
},
  "geometry": {"coordinates":[2.2325119972,41.5866622925],"type":"Point"}
}