{
  "type": "Feature",
  "properties": {
    "addr:full":"Plaz Carlos Castel, 18 Teruel Teruel 44001",
    "addr:postcode":"18;44001",
    "addr:street":"Castel",
    "iso:country":"ES",
    "sg:address":"Plaz Carlos Castel, 18",
    "sg:city":"Teruel",
    "sg:orig_category":"Bancos",
    "sg:phone":"+34 978 61 70 16",
    "sg:postcode":"44001",
    "sg:province":"Teruel",
    "wof:name":"Bankinter S.a.",
    "wof:placetype":"venue"
},
  "geometry": {"coordinates":[-1.1071779728,40.3428688049],"type":"Point"}
}