{
  "type": "Feature",
  "properties": {
    "addr:full":"Plaz Portugal, 1 Algeciras C\u00e1diz 11205",
    "addr:housenumber":"1;ca\u0301diz",
    "addr:postcode":"11205",
    "addr:street":"Portugal",
    "iso:country":"ES",
    "sg:address":"Plaz Portugal, 1",
    "sg:city":"Algeciras",
    "sg:orig_category":"Caf\u00c9s, Bares, Cervecer\u00cdas",
    "sg:phone":"+34 956 65 05 54",
    "sg:postcode":"11205",
    "sg:province":"C\u00e1diz",
    "wof:name":"Cafe Cibola C.b.",
    "wof:placetype":"venue"
},
  "geometry": {"coordinates":[-5.4526491165,36.1276016235],"type":"Point"}
}