{
  "type": "Feature",
  "properties": {
    "iso:country":"ES",
    "sg:address":"Bard San Pablo, S/n",
    "sg:city":"Ecija",
    "sg:orig_category":"Molduras, Junquillos, Listones Y Molduras Perforadas",
    "sg:phone":"+34 955 90 16 49",
    "sg:postcode":"41400",
    "sg:province":"Sevilla",
    "wof:name":"Eurotel-sur S.l.",
    "wof:placetype":"venue"
},
  "geometry": {"coordinates":[-5.0838489532,37.545753479],"type":"Point"}
}