{
  "type": "Feature",
  "properties": {
    "iso:country":"ES",
    "sg:address":"Calle de San Gerardo, 14",
    "sg:city":"Madrid",
    "sg:orig_category":"Ingenier\u00cda, Centros De Estudios (diversos)",
    "sg:phone":"+34 913 16 05 60",
    "sg:postcode":"28035",
    "sg:province":"Madrid",
    "wof:name":"Garcia Beites Rafael",
    "wof:placetype":"venue"
},
  "geometry": {"coordinates":[-3.7214610577,40.4674987793],"type":"Point"}
}