{
  "type": "Feature",
  "properties": {
    "iso:country":"ES",
    "sg:address":"Calle de General Pintos, 5",
    "sg:city":"Madrid",
    "sg:orig_category":"Albergues",
    "sg:phone":"+34 913 15 62 91",
    "sg:postcode":"28029",
    "sg:province":"Madrid",
    "wof:name":"Pe\u00f1as Franco Maria Estrella",
    "wof:placetype":"venue"
},
  "geometry": {"coordinates":[-3.693926096,40.4698905945],"type":"Point"}
}