{
  "type": "Feature",
  "properties": {
    "iso:country":"ES",
    "sg:address":"C/ Jose Sanchez Saez, 35",
    "sg:city":"Elche",
    "sg:orig_category":"Alimentaci\u00d3n General (al Por Mayor)",
    "sg:phone":"+34 965 45 13 90",
    "sg:postcode":"03202",
    "sg:province":"Alicante",
    "wof:name":"Sumilsa",
    "wof:placetype":"venue"
},
  "geometry": {"coordinates":[-0.6844289899,38.273475647],"type":"Point"}
}