{
  "type": "Feature",
  "properties": {
    "addr:full":"Rbla Badal, 123 Barcelona Barcelona 08028",
    "addr:housenumber":"123",
    "addr:postcode":"08028",
    "addr:street":"Rbla Badal",
    "iso:country":"ES",
    "sg:address":"Rbla Badal, 123",
    "sg:city":"Barcelona",
    "sg:orig_category":"Molduras, Junquillos, Listones Y Molduras Perforadas",
    "sg:phone":"+34 934 22 12 28",
    "sg:postcode":"08028",
    "sg:province":"Barcelona",
    "wof:name":"Noray Gramunt Josefa",
    "wof:placetype":"venue"
},
  "geometry": {"coordinates":[2.1313080788,41.3724861145],"type":"Point"}
}