{
  "type": "Feature",
  "properties": {
    "iso:country":"ES",
    "sg:address":"Calle de Madre Rafols, 10",
    "sg:city":"Sevilla",
    "sg:orig_category":"Estancos",
    "sg:phone":"+34 954 45 30 46",
    "sg:postcode":"41011",
    "sg:province":"Sevilla",
    "wof:name":"Aguilar Ramos Jose Maria",
    "wof:placetype":"venue"
},
  "geometry": {"coordinates":[-5.9997038841,37.3751335144],"type":"Point"}
}