{
  "type": "Feature",
  "properties": {
    "iso:country":"ES",
    "sg:address":"Ctra Montblanc-valls, Km. 0018,0",
    "sg:city":"Picamoixons",
    "sg:orig_category":"Electricidad, Electr\u00d3nica: Material Y Suministros (al Por Mayor)",
    "sg:phone":"+34 977 60 49 06",
    "sg:postcode":"43491",
    "sg:province":"Tarragona",
    "wof:name":"Alcover Cogeneracion A.i.e.",
    "wof:placetype":"venue"
},
  "geometry": {"coordinates":[1.2014065981,41.3030090332],"type":"Point"}
}