{
  "type": "Feature",
  "properties": {
    "iso:country":"ES",
    "sg:address":"Carrer de Sant Antoni Maria Claret, 19",
    "sg:city":"Barcelona",
    "sg:orig_category":"Edici\u00d3n De Diarios, Revistas, Boletines",
    "sg:phone":"+34 932 07 17 17",
    "sg:postcode":"08037",
    "sg:province":"Barcelona",
    "wof:name":"Edicions El Camp S.l.",
    "wof:placetype":"venue"
},
  "geometry": {"coordinates":[2.1647279263,41.4040985107],"type":"Point"}
}