{
  "type": "Feature",
  "properties": {
    "iso:country":"ES",
    "sg:address":"Avda Jose Mesa Y Lopez, 9",
    "sg:city":"Palmas De Gran Canaria",
    "sg:orig_category":"Contenedores (mercanc\u00cdas)",
    "sg:phone":"+34 928 23 41 86",
    "sg:postcode":"35006",
    "sg:province":"Las Palmas",
    "wof:name":"Grupages Pe\u00f1uelas S.l.",
    "wof:placetype":"venue"
},
  "geometry": {"coordinates":[-15.4308319092,28.1345901489],"type":"Point"}
}