{
  "type": "Feature",
  "properties": {
    "iso:country":"ES",
    "sg:address":"Cami Sant Llatzet, 32",
    "sg:city":"Pont D'inca",
    "sg:orig_category":"Negocio De Materiales De Construcci\u00d3n",
    "sg:phone":"+34 971 60 71 81",
    "sg:postcode":"07009",
    "sg:province":"Islas Baleares",
    "wof:name":"Juan Sastre Roca S.l",
    "wof:placetype":"venue"
},
  "geometry": {"coordinates":[2.9117100239,39.6136398315],"type":"Point"}
}