{
  "type": "Feature",
  "properties": {
    "iso:country":"ES",
    "sg:address":"Avda Canarias, 123",
    "sg:city":"Vecindario",
    "sg:orig_category":"Agencias Y Agentes Comerciales, Representantes",
    "sg:phone":"+34 928 75 30 34",
    "sg:postcode":"35110",
    "sg:province":"Las Palmas",
    "wof:name":"Tacoronte Luzardo Ana",
    "wof:placetype":"venue"
},
  "geometry": {"coordinates":[-15.4408693314,27.8513793945],"type":"Point"}
}