{
  "type": "Feature",
  "properties": {
    "addr:full":"Avda Eduardo Dato, 22 Sevilla Sevilla 41018",
    "addr:housenumber":"22",
    "addr:postcode":"41018",
    "addr:street":"Avda Eduardo Dato",
    "iso:country":"ES",
    "sg:address":"Avda Eduardo Dato, 22",
    "sg:city":"Sevilla",
    "sg:orig_category":"Arquitectos",
    "sg:phone":"+34 954 93 39 63",
    "sg:postcode":"41018",
    "sg:province":"Sevilla",
    "wof:name":"G.a.u. Aproa Area S.l.",
    "wof:placetype":"venue"
},
  "geometry": {"coordinates":[-5.9739952087,37.3827400208],"type":"Point"}
}