{
  "type": "Feature",
  "properties": {
    "addr:full":"Calle de Cuclillo, 1 Zubia Granada 18140",
    "addr:housenumber":"1",
    "addr:postcode":"18140",
    "addr:street":"Calle De Cuclillo",
    "iso:country":"ES",
    "sg:address":"Calle de Cuclillo, 1",
    "sg:city":"Zubia",
    "sg:orig_category":"Autob\u00das (explotaci\u00d3n Y Servicios De)",
    "sg:phone":"+34 958 59 20 52",
    "sg:postcode":"18140",
    "sg:province":"Granada",
    "wof:name":"Autocares Vistabus S.l.",
    "wof:placetype":"venue"
},
  "geometry": {"coordinates":[-3.5770790577,37.1176338196],"type":"Point"}
}