{
  "type": "Feature",
  "properties": {
    "iso:country":"ES",
    "sg:address":"Calle de Mendez Nu\u00d1ez, 46",
    "sg:city":"Santa Cruz De Tenerife",
    "sg:orig_category":"Peluquer\u00cdas, Peluquer\u00cda Mixta",
    "sg:phone":"+34 922 27 37 14",
    "sg:postcode":"38002",
    "sg:province":"Santa Cruz De Tenerife",
    "wof:name":"Rodriguez Ortega Ana Esther",
    "wof:placetype":"venue"
},
  "geometry": {"coordinates":[-16.25340271,28.4707946777],"type":"Point"}
}