{
  "type": "Feature",
  "properties": {
    "iso:country":"ES",
    "sg:address":"Calle de Infanta Mercedes, 6",
    "sg:city":"Madrid",
    "sg:orig_category":"Fabricaci\u00d3n De Sobres, Bolsas Y Fundas",
    "sg:phone":"+34 915 79 12 71",
    "sg:postcode":"28020",
    "sg:province":"Madrid",
    "wof:name":"Gutierrez Cano Jose Carlos",
    "wof:placetype":"venue"
},
  "geometry": {"coordinates":[-3.699023962,40.4536094666],"type":"Point"}
}