{
  "type": "Feature",
  "properties": {
    "iso:country":"ES",
    "sg:address":"Calle de San Mateo, 12",
    "sg:city":"Almazora",
    "sg:orig_category":"Panader\u00cdas, Pasteler\u00cdas, Boller\u00cda Industriale (fabricaci\u00d3n, Al Por Mayor)",
    "sg:phone":"+34 964 56 08 81",
    "sg:postcode":"12550",
    "sg:province":"Castell\u00f3n",
    "wof:name":"Bovea Safont Jose Antonio",
    "wof:placetype":"venue"
},
  "geometry": {"coordinates":[-0.0609299988,39.9427261353],"type":"Point"}
}