{
  "type": "Feature",
  "properties": {
    "addr:full":"Avda San Pablo (de), 28 Coslada Madrid 28820",
    "addr:housenumber":"28",
    "addr:postcode":"28820",
    "addr:street":"Avda San Pablo De",
    "iso:country":"ES",
    "sg:address":"Avda San Pablo (de), 28",
    "sg:city":"Coslada",
    "sg:orig_category":"Cer\u00c1micas: Material Y Suministros",
    "sg:phone":"+34 916 69 95 05",
    "sg:postcode":"28820",
    "sg:province":"Madrid",
    "wof:name":"Eurotec Equipamientos Hoteleros S.l.",
    "wof:placetype":"venue"
},
  "geometry": {"coordinates":[-3.5327730179,40.4357872009],"type":"Point"}
}