{
  "type": "Feature",
  "properties": {
    "addr:full":"Pase Delicias, 78 Madrid Madrid 28045",
    "addr:housenumber":"78",
    "addr:postcode":"madrid;28045",
    "addr:street":"Delicias",
    "iso:country":"ES",
    "sg:address":"Pase Delicias, 78",
    "sg:city":"Madrid",
    "sg:orig_category":"Ropa Para Ni\u00d1os (al Por Menor)",
    "sg:phone":"+34 915 28 24 75",
    "sg:postcode":"28045",
    "sg:province":"Madrid",
    "sg:website":"www.amichi.com",
    "wof:name":"Disedis S.l.",
    "wof:placetype":"venue"
},
  "geometry": {"coordinates":[-3.6943500042,40.398601532],"type":"Point"}
}