{
  "type": "Feature",
  "properties": {
    "addr:full":"Calle de General Vives, 48 Palmas De Gran Canaria Las Palmas 35007",
    "addr:postcode":"35007",
    "addr:street":"Calle De General Vives 48",
    "iso:country":"ES",
    "sg:address":"Calle de General Vives, 48",
    "sg:city":"Palmas De Gran Canaria",
    "sg:orig_category":"Asociaciones Y Clubs Deportivos",
    "sg:phone":"+34 928 22 45 93",
    "sg:postcode":"35007",
    "sg:province":"Las Palmas",
    "sg:website":"www.deportesimpacto.com",
    "wof:name":"Promotora Romensa S.l.",
    "wof:placetype":"venue"
},
  "geometry": {"coordinates":[-15.4312181473,28.1376876831],"type":"Point"}
}