{
  "type": "Feature",
  "properties": {
    "addr:full":"Calle de San Ildefonso, 26 Utiel Valencia 46300",
    "addr:housenumber":"26",
    "addr:postcode":"46300",
    "addr:street":"Calle De San Ildefonso",
    "iso:country":"ES",
    "sg:address":"Calle de San Ildefonso, 26",
    "sg:city":"Utiel",
    "sg:orig_category":"Carnicer\u00cdas, Carnicer\u00cdas",
    "sg:phone":"+34 962 17 02 30",
    "sg:postcode":"46300",
    "sg:province":"Valencia",
    "wof:name":"Carnes Y Embutidos Choni Soriano",
    "wof:placetype":"venue"
},
  "geometry": {"coordinates":[-1.2009780407,39.5661048889],"type":"Point"}
}