{
  "type": "Feature",
  "properties": {
    "addr:full":"Avda Alcaldesa Maria Regla Jimenez, 36 Espartinas Sevilla 41807",
    "addr:housenumber":"36",
    "addr:postcode":"41807",
    "addr:street":"Avda Alcaldesa Maria Regla Jimenez",
    "iso:country":"ES",
    "sg:address":"Avda Alcaldesa Maria Regla Jimenez, 36",
    "sg:city":"Espartinas",
    "sg:orig_category":"Frutas Y Legumbres Frescas (al Por Mayor)",
    "sg:phone":"+34 955 71 03 06",
    "sg:postcode":"41807",
    "sg:province":"Sevilla",
    "wof:name":"Frutas Mora Espartinas S.l.",
    "wof:placetype":"venue"
},
  "geometry": {"coordinates":[-6.1316971779,37.3814849854],"type":"Point"}
}