{
  "type": "Feature",
  "properties": {
    "addr:full":"Mitarte Kalea, 10 Aretxabaleta Guip\u00f9zcoa 20550",
    "addr:housenumber":"10",
    "addr:postcode":"20550",
    "addr:street":"Mitarte Kalea;Guipu\u0300Zcoa",
    "iso:country":"ES",
    "sg:address":"Mitarte Kalea, 10",
    "sg:city":"Aretxabaleta",
    "sg:orig_category":"Montaje (empresas De)",
    "sg:phone":"+34 943 79 74 07",
    "sg:postcode":"20550",
    "sg:province":"Guip\u00f9zcoa",
    "wof:name":"Zertu S.l.",
    "wof:placetype":"venue"
},
  "geometry": {"coordinates":[-2.5041089058,43.0338821411],"type":"Point"}
}