{
  "type": "Feature",
  "properties": {
    "addr:full":"Carrer de Camp Arriassa, 96 Barcelona Barcelona 08020",
    "addr:housenumber":"96",
    "addr:postcode":"08020",
    "addr:street":"Carrer De Camp Arriassa",
    "iso:country":"ES",
    "sg:address":"Carrer de Camp Arriassa, 96",
    "sg:city":"Barcelona",
    "sg:orig_category":"Agencias Y Agentes Comerciales, Representantes",
    "sg:phone":"+34 933 13 39 01",
    "sg:postcode":"08020",
    "sg:province":"Barcelona",
    "wof:name":"Rodriguez De La Fuente Luis Mariano",
    "wof:placetype":"venue"
},
  "geometry": {"coordinates":[2.2022819519,41.4252128601],"type":"Point"}
}