{
  "type": "Feature",
  "properties": {
    "iso:country":"ES",
    "sg:address":"Carrer de Roca I Batlle, 7",
    "sg:city":"Barcelona",
    "sg:orig_category":"Agencias Y Asesores De Publicidad",
    "sg:phone":"+34 932 11 57 53",
    "sg:postcode":"08023",
    "sg:province":"Barcelona",
    "sg:website":"www.aspidasd.com",
    "wof:name":"Aspid Asd S.c.p.",
    "wof:placetype":"venue"
},
  "geometry": {"coordinates":[2.1406507492,41.409488678],"type":"Point"}
}