{
  "type": "Feature",
  "properties": {
    "iso:country":"ES",
    "sg:address":"Av Tres-cents Cinc, 37",
    "sg:city":"Castelldefels",
    "sg:orig_category":"Asesor\u00cda Fiscal Y Jur\u00cddica",
    "sg:phone":"+34 936 65 44 30",
    "sg:postcode":"08860",
    "sg:province":"Barcelona",
    "wof:name":"Asesoria Rusi\u00d1ol S.l.",
    "wof:placetype":"venue"
},
  "geometry": {"coordinates":[1.9767744541,41.2803878784],"type":"Point"}
}