{
  "type": "Feature",
  "properties": {
    "iso:country":"ES",
    "sg:address":"Ctra Torrijos, Km. 0009,0",
    "sg:city":"Bargas",
    "sg:orig_category":"Comercio De Carburantes",
    "sg:phone":"+34 925 49 34 57",
    "sg:postcode":"45593",
    "sg:province":"Toledo",
    "wof:name":"Ancomar Valle De Santiago S.l.",
    "wof:placetype":"venue"
},
  "geometry": {"coordinates":[-4.0797672272,39.9404525757],"type":"Point"}
}