{
  "type": "Feature",
  "properties": {
    "iso:country":"ES",
    "sg:address":"Calle de Baleares, 19",
    "sg:city":"Gijon",
    "sg:orig_category":"Contenedores (mercanc\u00cdas)",
    "sg:phone":"+34 985 39 01 65",
    "sg:postcode":"33208",
    "sg:province":"Asturias",
    "wof:name":"Hevia Llana Rufino",
    "wof:placetype":"venue"
},
  "geometry": {"coordinates":[-5.671128273,43.5288391113],"type":"Point"}
}