{
  "type": "Feature",
  "properties": {
    "iso:country":"ES",
    "sg:address":"Cno Ronda, S/n",
    "sg:city":"Torrevieja",
    "sg:orig_category":"Reciclaje Y Tratamiento De Desechos Varios",
    "sg:phone":"+34 966 70 05 22",
    "sg:postcode":"03180",
    "sg:province":"Alicante",
    "sg:website":"www.necsoinmobiliaria.com",
    "wof:name":"Acciona Servicios Urbanos S.l.",
    "wof:placetype":"venue"
},
  "geometry": {"coordinates":[-0.6583958864,38.0050506592],"type":"Point"}
}