{
  "type": "Feature",
  "properties": {
    "iso:country":"ES",
    "sg:address":"Calle de Concierto, 1",
    "sg:city":"Madrid",
    "sg:orig_category":"Agencias Y Asesores De Publicidad",
    "sg:phone":"+34 914 64 33 98",
    "sg:postcode":"28011",
    "sg:province":"Madrid",
    "wof:name":"Moon Han Jae Keun",
    "wof:placetype":"venue"
},
  "geometry": {"coordinates":[-3.7270839214,40.4147605896],"type":"Point"}
}