{
  "type": "Feature",
  "properties": {
    "addr:full":"Calle de Rodriguez Arias, 69 Bilbao Vizcaya 48013",
    "addr:housenumber":"69",
    "addr:postcode":"48013",
    "addr:street":"Calle De Rodriguez Arias",
    "iso:country":"ES",
    "sg:address":"Calle de Rodriguez Arias, 69",
    "sg:city":"Bilbao",
    "sg:orig_category":"Inform\u00c1tica (estudios, Servicios, Asesor\u00cda, Formaci\u00d3n)",
    "sg:phone":"+34 944 41 91 98",
    "sg:postcode":"48013",
    "sg:province":"Vizcaya",
    "wof:name":"Teletrabajo Y Movilidad S.l.",
    "wof:placetype":"venue"
},
  "geometry": {"coordinates":[-2.9444758892,43.2637863159],"type":"Point"}
}