{
  "type": "Feature",
  "properties": {
    "addr:full":"Carrer de Agricultura, 98 Sabadell Barcelona 08208",
    "addr:housenumber":"98",
    "addr:postcode":"08208",
    "addr:street":"Carrer De Agricultura",
    "iso:country":"ES",
    "sg:address":"Carrer de Agricultura, 98",
    "sg:city":"Sabadell",
    "sg:orig_category":"Caf\u00c9s, Bares, Cervecer\u00cdas",
    "sg:phone":"+34 937 23 25 83",
    "sg:postcode":"08208",
    "sg:province":"Barcelona",
    "wof:name":"Il Duomo Cafeteria S.l.",
    "wof:placetype":"venue"
},
  "geometry": {"coordinates":[2.1005499363,41.5529441833],"type":"Point"}
}