{
  "type": "Feature",
  "properties": {
    "addr:full":"Mercat Central, S/n Reus Tarragona 43201",
    "addr:housenumber":"s / n",
    "addr:postcode":"43201",
    "iso:country":"ES",
    "sg:address":"Mercat Central, S/n",
    "sg:city":"Reus",
    "sg:orig_category":"Carnicer\u00cdas, Carnicer\u00cdas",
    "sg:phone":"+34 977 31 27 87",
    "sg:postcode":"43201",
    "sg:province":"Tarragona",
    "wof:name":"Yenes Alvarez Aurora",
    "wof:placetype":"venue"
},
  "geometry": {"coordinates":[1.1077258587,41.156211853],"type":"Point"}
}