{
  "type": "Feature",
  "properties": {
    "addr:full":"Pol Ind Munic Vial A, 12 Tudela Navarra 31500",
    "addr:postcode":"31500",
    "addr:street":"A",
    "iso:country":"ES",
    "sg:address":"Pol Ind Munic Vial A, 12",
    "sg:city":"Tudela",
    "sg:orig_category":"Comercio De Piezas De Recambio Y De Accesorios De Veh\u00cdculos, Veh\u00cdculos Industriales",
    "sg:phone":"+34 948 82 01 05",
    "sg:postcode":"31500",
    "sg:province":"Navarra",
    "wof:name":"Auto-electricidad Jesus S.l.",
    "wof:placetype":"venue"
},
  "geometry": {"coordinates":[-1.6294337511,42.0647201538],"type":"Point"}
}