{
  "type": "Feature",
  "properties": {
    "addr:full":"Paseo Colon, 39 Irun Guip\u00f9zcoa 20301",
    "addr:housenumber":"39",
    "addr:postcode":"20301",
    "addr:street":"Paseo Colon;Guipu\u0300Zcoa",
    "iso:country":"ES",
    "sg:address":"Paseo Colon, 39",
    "sg:city":"Irun",
    "sg:orig_category":"Art\u00cdculos De Regalo (al Por Menor)",
    "sg:phone":"+34 943 00 46 60",
    "sg:postcode":"20301",
    "sg:province":"Guip\u00f9zcoa",
    "wof:name":"Regalos Irati",
    "wof:placetype":"venue"
},
  "geometry": {"coordinates":[-1.7959029675,43.3405914307],"type":"Point"}
}