{
  "type": "Feature",
  "properties": {
    "iso:country":"ES",
    "sg:address":"Calle de Donoso Cortes, 10",
    "sg:city":"Le\u00f3n",
    "sg:classifiers":[
        {
            "category":"Taxi",
            "type":"Transportation"
        }
    ],
    "sg:phone":"+34 987 23 06 60",
    "sg:postcode":"24008",
    "sg:province":"Le\u00f3n",
    "wof:name":"Gonzalez Martinez Agapito",
    "wof:placetype":"venue"
},
  "geometry": {"coordinates":[-5.5715837479,42.6123847961],"type":"Point"}
}