{
  "type": "Feature",
  "properties": {
    "addr:full":"Poligono Dos, 216 Porreres Islas Baleares 07260",
    "addr:housenumber":"216",
    "addr:postcode":"07260",
    "addr:street":"Poligono Dos",
    "iso:country":"ES",
    "sg:address":"Poligono Dos, 216",
    "sg:city":"Porreres",
    "sg:orig_category":"Electricidad: Instaladores",
    "sg:phone":"+34 971 64 74 08",
    "sg:postcode":"07260",
    "sg:province":"Islas Baleares",
    "wof:name":"B.i.t.instalacions C.b.",
    "wof:placetype":"venue"
},
  "geometry": {"coordinates":[3.0283200741,39.512298584],"type":"Point"}
}