{
  "type": "Feature",
  "properties": {
    "iso:country":"ES",
    "sg:address":"Calle de Garcia Ortiz, 34",
    "sg:city":"Calpe",
    "sg:classifiers":[
        {
            "category":"Recreation",
            "type":"Entertainment"
        }
    ],
    "sg:phone":"+34 965 83 79 17",
    "sg:postcode":"03710",
    "sg:province":"Alicante",
    "sg:tags":[
        "caza",
        "pr\u00c1ctica",
        "la",
        "de",
        "pesca",
        "y"
    ],
    "wof:name":"Cofradia De Pescadores De Altea",
    "wof:placetype":"venue"
},
  "geometry": {"coordinates":[0.0452409983,38.6442298889],"type":"Point"}
}