{
  "type": "Feature",
  "properties": {
    "addr:full":"Pg Til.lers, 8 Barcelona Barcelona 08034",
    "addr:housenumber":"8",
    "addr:postcode":"08034",
    "addr:street":"Pg Til.Lers",
    "iso:country":"ES",
    "sg:address":"Pg Til.lers, 8",
    "sg:city":"Barcelona",
    "sg:orig_category":"Sociedades Y Organismos Burs\u00c1tiles",
    "sg:phone":"+34 932 03 39 63",
    "sg:postcode":"08034",
    "sg:province":"Barcelona",
    "wof:name":"Viola Y Cordoba Notarios C.b.",
    "wof:placetype":"venue"
},
  "geometry": {"coordinates":[2.1178181171,41.3896713257],"type":"Point"}
}