{
  "type": "Feature",
  "properties": {
    "addr:full":"C/ Sant Joan, 21 Ripollet Barcelona 08291",
    "addr:housenumber":"21",
    "addr:postcode":"08291",
    "addr:street":"C / Sant Joan",
    "iso:country":"ES",
    "sg:address":"C/ Sant Joan, 21",
    "sg:city":"Ripollet",
    "sg:orig_category":"Organizaciones Internacionales",
    "sg:phone":"+34 935 80 09 13",
    "sg:postcode":"08291",
    "sg:province":"Barcelona",
    "wof:name":"Unio De Botiguers De Ripollet",
    "wof:placetype":"venue"
},
  "geometry": {"coordinates":[2.1591219902,41.496257782],"type":"Point"}
}