{
  "type": "Feature",
  "properties": {
    "addr:full":"Calle de Corredera, 17 Toro Zamora 49800",
    "addr:housenumber":"17",
    "addr:postcode":"49800",
    "addr:street":"Calle De Corredera",
    "iso:country":"ES",
    "sg:address":"Calle de Corredera, 17",
    "sg:city":"Toro",
    "sg:orig_category":"Zapater\u00cdas",
    "sg:phone":"+34 980 69 31 99",
    "sg:postcode":"49800",
    "sg:province":"Zamora",
    "wof:name":"Ferrerira Rodriguez Sergio",
    "wof:placetype":"venue"
},
  "geometry": {"coordinates":[-5.3925890923,41.5232810974],"type":"Point"}
}