{
  "type": "Feature",
  "properties": {
    "iso:country":"ES",
    "sg:address":"Rua Dolores, 15",
    "sg:city":"Ferrol",
    "sg:orig_category":"Agencias De Viajes",
    "sg:phone":"+34 981 35 55 05",
    "sg:postcode":"15402",
    "sg:province":"A Coru\u00f1a",
    "sg:website":"www.marsans.com",
    "wof:name":"Viajes Marsans S.a.",
    "wof:placetype":"venue"
},
  "geometry": {"coordinates":[-8.2338495255,43.4838485718],"type":"Point"}
}