{
  "type": "Feature",
  "properties": {
    "addr:full":"Carrer de Mont Caro, S/n Roquetes Tarragona 43520",
    "addr:housenumber":"s / n",
    "addr:postcode":"43520",
    "addr:street":"Carrer De Mont Caro",
    "iso:country":"ES",
    "sg:address":"Carrer de Mont Caro, S/n",
    "sg:city":"Roquetes",
    "sg:orig_category":"Agencias Y Agentes Comerciales, Representantes",
    "sg:phone":"+34 977 26 78 78",
    "sg:postcode":"43520",
    "sg:province":"Tarragona",
    "wof:name":"Altius Serveis I Recursos S. L.",
    "wof:placetype":"venue"
},
  "geometry": {"coordinates":[0.4313729107,40.7758598328],"type":"Point"}
}