{
  "type": "Feature",
  "properties": {
    "iso:country":"ES",
    "sg:address":"Calle de Donato Arguelles, 18",
    "sg:city":"Gijon",
    "sg:orig_category":"Abogados",
    "sg:phone":"+34 985 34 50 27",
    "sg:postcode":"33206",
    "sg:province":"Asturias",
    "wof:name":"Alvarez Rodriguez Horacio Joaquin",
    "wof:placetype":"venue"
},
  "geometry": {"coordinates":[-5.6645431519,43.5393600464],"type":"Point"}
}