{
  "type": "Feature",
  "properties": {
    "iso:country":"ES",
    "sg:address":"Carr Mas Vila, S/n",
    "sg:city":"S. Gregori",
    "sg:orig_category":"Promotores Constructores",
    "sg:phone":"+34 972 42 83 78",
    "sg:postcode":"17150",
    "sg:province":"Girona",
    "wof:name":"Construccions Costa Burch Sl",
    "wof:placetype":"venue"
},
  "geometry": {"coordinates":[2.7533950806,41.9914512634],"type":"Point"}
}