{
  "type": "Feature",
  "properties": {
    "iso:country":"ES",
    "sg:address":"Calle de Iberia, 6",
    "sg:city":"Sestao",
    "sg:orig_category":"Producci\u00d3n, Distribuci\u00d3n De Electricidad",
    "sg:phone":"+34 944 72 20 37",
    "sg:postcode":"48910",
    "sg:province":"Vizcaya",
    "wof:name":"Bego\u00f1a Gonzalez Prieto",
    "wof:placetype":"venue"
},
  "geometry": {"coordinates":[-3.0049450397,43.3103485107],"type":"Point"}
}