{
  "type": "Feature",
  "properties": {
    "addr:full":"Carrer de Torrent De L'olla, 68 Barcelona Barcelona 08012",
    "addr:housenumber":"68",
    "addr:postcode":"08012",
    "addr:street":"Carrer De Torrent De L'Olla",
    "iso:country":"ES",
    "sg:address":"Carrer de Torrent De L'olla, 68",
    "sg:city":"Barcelona",
    "sg:orig_category":"Bisuter\u00cda, Joyer\u00cda, Relojer\u00cda (al Por Menor)",
    "sg:phone":"+34 932 85 09 42",
    "sg:postcode":"08012",
    "sg:province":"Barcelona",
    "wof:name":"Camarillas Marimon Miriam",
    "wof:placetype":"venue"
},
  "geometry": {"coordinates":[2.1593635082,41.4004096985],"type":"Point"}
}