{
  "type": "Feature",
  "properties": {
    "iso:country":"ES",
    "sg:address":"Calle de Salado, 1",
    "sg:city":"Mairena Alcor",
    "sg:orig_category":"Transportes Urbanos Y Regionales Para Personas",
    "sg:phone":"+34 955 94 25 32",
    "sg:postcode":"41510",
    "sg:province":"Sevilla",
    "wof:name":"Jimenez Capitan Sl",
    "wof:placetype":"venue"
},
  "geometry": {"coordinates":[-5.7350549698,37.376499176],"type":"Point"}
}