{
  "type": "Feature",
  "properties": {
    "iso:country":"ES",
    "sg:address":"Calle de Tomas Romero De Castilla, S/n",
    "sg:city":"Merida",
    "sg:orig_category":"Centros De Educaci\u00d3n Especial",
    "sg:phone":"+34 924 31 20 12",
    "sg:postcode":"06800",
    "sg:province":"Badajoz",
    "wof:name":"Centro Residencia De Educacion Especial Emerita Augusta",
    "wof:placetype":"venue"
},
  "geometry": {"coordinates":[-6.3355240822,38.9089164734],"type":"Point"}
}