{
  "type": "Feature",
  "properties": {
    "addr:full":"Calle de Cedro, 7 Torrejon Ardoz Madrid 28850",
    "addr:housenumber":"7",
    "addr:postcode":"28850",
    "addr:street":"Calle De Cedro",
    "iso:country":"ES",
    "sg:address":"Calle de Cedro, 7",
    "sg:city":"Torrejon Ardoz",
    "sg:orig_category":"Molduras, Junquillos, Listones Y Molduras Perforadas",
    "sg:phone":"+34 916 75 72 37",
    "sg:postcode":"28850",
    "sg:province":"Madrid",
    "wof:name":"Blanco Martin Francisco",
    "wof:placetype":"venue"
},
  "geometry": {"coordinates":[-3.4546530247,40.454914093],"type":"Point"}
}