{
  "type": "Feature",
  "properties": {
    "iso:country":"ES",
    "sg:address":"Plaz Generalisimo, 24",
    "sg:city":"Villaviciosa",
    "sg:orig_category":"Caf\u00c9s, Bares, Cervecer\u00cdas",
    "sg:phone":"+34 985 89 19 22",
    "sg:postcode":"33300",
    "sg:province":"Asturias",
    "wof:name":"Coto Roza Laureano",
    "wof:placetype":"venue"
},
  "geometry": {"coordinates":[-5.4335007668,43.4811210632],"type":"Point"}
}