{
  "type": "Feature",
  "properties": {
    "addr:full":"Avda Montero Rios, 23 Cangas Pontevedra 36940",
    "addr:housenumber":"23",
    "addr:postcode":"36940",
    "addr:street":"Avda Montero Rios",
    "iso:country":"ES",
    "sg:address":"Avda Montero Rios, 23",
    "sg:city":"Cangas",
    "sg:orig_category":"Molduras, Junquillos, Listones Y Molduras Perforadas",
    "sg:phone":"+34 986 30 00 00",
    "sg:postcode":"36940",
    "sg:province":"Pontevedra",
    "wof:name":"Gra\u00f1a Gra\u00f1a Guillermina",
    "wof:placetype":"venue"
},
  "geometry": {"coordinates":[-8.7854270935,42.2612571716],"type":"Point"}
}