{
  "type": "Feature",
  "properties": {
    "addr:full":"Calle de Guadarrama, 30 Moralzarzal Madrid 28411",
    "addr:housenumber":"30",
    "addr:postcode":"28411",
    "addr:street":"Calle De Guadarrama",
    "iso:country":"ES",
    "sg:address":"Calle de Guadarrama, 30",
    "sg:city":"Moralzarzal",
    "sg:orig_category":"Bebidas",
    "sg:phone":"+34 918 57 87 97",
    "sg:postcode":"28411",
    "sg:province":"Madrid",
    "wof:name":"Segovia-ballesteros S.l.",
    "wof:placetype":"venue"
},
  "geometry": {"coordinates":[-3.9524788857,40.6814994812],"type":"Point"}
}