{
  "type": "Feature",
  "properties": {
    "addr:full":"Calle de Geologo Clemente Sanz Blanco, S/n San Pedro Gaillos Segovia 40389",
    "addr:housenumber":"s / n",
    "addr:postcode":"40389",
    "addr:street":"Calle De Geologo Clemente Sanz Blanco",
    "iso:country":"ES",
    "sg:address":"Calle de Geologo Clemente Sanz Blanco, S/n",
    "sg:city":"San Pedro Gaillos",
    "sg:orig_category":"Complementos De Vestir (al Por Menor)",
    "sg:phone":"+34 921 53 11 62",
    "sg:postcode":"40389",
    "sg:province":"Segovia",
    "wof:name":"Obrero Clemares Leticia",
    "wof:placetype":"venue"
},
  "geometry": {"coordinates":[-3.7909989357,41.2445411682],"type":"Point"}
}