{
  "type": "Feature",
  "properties": {
    "iso:country":"ES",
    "sg:address":"Calle de Clemencia Escobar, 12",
    "sg:city":"Bormujos",
    "sg:orig_category":"Mec\u00c1nico Del Autom\u00d3vil",
    "sg:phone":"+34 955 72 54 47",
    "sg:postcode":"41930",
    "sg:province":"Sevilla",
    "wof:name":"Automecanica E Acevedo S.l.",
    "wof:placetype":"venue"
},
  "geometry": {"coordinates":[-6.0696182251,37.3711090088],"type":"Point"}
}