{
  "type": "Feature",
  "properties": {
    "addr:full":"Plaz Esquivel (de), 1 Cadiz C\u00e1diz 11010",
    "addr:housenumber":"1",
    "addr:postcode":"11010",
    "addr:street":"Plaz Esquivel De",
    "iso:country":"ES",
    "sg:address":"Plaz Esquivel (de), 1",
    "sg:city":"Cadiz",
    "sg:orig_category":"Abogados",
    "sg:phone":"+34 956 20 12 03",
    "sg:postcode":"11010",
    "sg:province":"C\u00e1diz",
    "wof:name":"Guimera Madrid Salvador",
    "wof:placetype":"venue"
},
  "geometry": {"coordinates":[-6.275437355,36.5046234131],"type":"Point"}
}