{
  "type": "Feature",
  "properties": {
    "iso:country":"ES",
    "sg:address":"Carr Santa Teresa, 6",
    "sg:city":"Badalona",
    "sg:orig_category":"Arquitectos",
    "sg:phone":"+34 933 89 03 16",
    "sg:postcode":"08911",
    "sg:province":"Barcelona",
    "wof:name":"Ponsirenas-puig I Associats S.l.",
    "wof:placetype":"venue"
},
  "geometry": {"coordinates":[2.250246048,41.4474945068],"type":"Point"}
}