{
  "type": "Feature",
  "properties": {
    "addr:full":"Calle de Calvo Sotelo, 22 Villanueva Gallego Zaragoza 50830",
    "addr:housenumber":"22",
    "addr:postcode":"50830",
    "addr:street":"Calle De Calvo Sotelo",
    "iso:country":"ES",
    "sg:address":"Calle de Calvo Sotelo, 22",
    "sg:city":"Villanueva Gallego",
    "sg:orig_category":"Agricultores, Agricultores",
    "sg:phone":"+34 976 18 00 39",
    "sg:postcode":"50830",
    "sg:province":"Zaragoza",
    "wof:name":"Granja O\u00f1ate S.a.",
    "wof:placetype":"venue"
},
  "geometry": {"coordinates":[-0.8241943121,41.7661170959],"type":"Point"}
}