{
  "type": "Feature",
  "properties": {
    "iso:country":"ES",
    "sg:address":"Avda Santa Cruz, 122",
    "sg:city":"San Isidro",
    "sg:orig_category":"Bisuter\u00cda, Joyer\u00cda, Relojer\u00cda (al Por Menor)",
    "sg:phone":"+34 922 39 44 96",
    "sg:postcode":"38611",
    "sg:province":"Santa Cruz De Tenerife",
    "wof:name":"Reveron Reveron Pedro",
    "wof:placetype":"venue"
},
  "geometry": {"coordinates":[-16.5576858521,28.0768909454],"type":"Point"}
}