{
  "type": "Feature",
  "properties": {
    "addr:full":"Vergel, 2 Iru\u00f1a Navarra 31014",
    "addr:housenumber":"2",
    "addr:postcode":"31014",
    "addr:street":"Vergel",
    "iso:country":"ES",
    "sg:address":"Vergel, 2",
    "sg:city":"Iru\u00f1a",
    "sg:orig_category":"Centros De Educaci\u00d3n Especial",
    "sg:phone":"+34 948 22 42 00",
    "sg:postcode":"31014",
    "sg:province":"Navarra",
    "wof:name":"Fundacion Ciganda Ferrer",
    "wof:placetype":"venue"
},
  "geometry": {"coordinates":[-1.6395939589,42.82188797],"type":"Point"}
}