{
  "type": "Feature",
  "properties": {
    "iso:country":"ES",
    "sg:address":"Calle de Teulada, 47",
    "sg:city":"Alacant",
    "sg:orig_category":"Material Y Herramientas Agr\u00cdcolas",
    "sg:phone":"+34 965 17 12 65",
    "sg:postcode":"03009",
    "sg:province":"Alicante",
    "wof:name":"Bernal Luna Jose Francisco",
    "wof:placetype":"venue"
},
  "geometry": {"coordinates":[-0.4984599948,38.3643913269],"type":"Point"}
}