{
  "type": "Feature",
  "properties": {
    "iso:country":"ES",
    "sg:address":"Calle de Maestra, 28",
    "sg:city":"Esca\u00d1uela",
    "sg:orig_category":"Cajas Para Embalar",
    "sg:phone":"+34 953 34 51 56",
    "sg:postcode":"23657",
    "sg:province":"Ja\u00e9n",
    "wof:name":"Caja Rural De Jaen",
    "wof:placetype":"venue"
},
  "geometry": {"coordinates":[-4.0345220566,37.878578186],"type":"Point"}
}