{
  "type": "Feature",
  "properties": {
    "addr:full":"Calle de Plata (del), 12 Fuenlabrada Madrid 28944",
    "addr:housenumber":"12",
    "addr:postcode":"28944",
    "addr:street":"Calle De Plata Del",
    "iso:country":"ES",
    "sg:address":"Calle de Plata (del), 12",
    "sg:city":"Fuenlabrada",
    "sg:orig_category":"Empresas De Pintura Y Revestimientos",
    "sg:phone":"+34 916 09 71 67",
    "sg:postcode":"28944",
    "sg:province":"Madrid",
    "wof:name":"Hermanos Segura Valdivia S.l.",
    "wof:placetype":"venue"
},
  "geometry": {"coordinates":[-3.788091898,40.2850494385],"type":"Point"}
}