{
  "type": "Feature",
  "properties": {
    "iso:country":"ES",
    "sg:address":"Calle de Acacias (las), 13",
    "sg:city":"Cordoba",
    "sg:orig_category":"Inform\u00c1tica (estudios, Servicios, Asesor\u00cda, Formaci\u00d3n)",
    "sg:phone":"+34 957 40 22 70",
    "sg:postcode":"14006",
    "sg:province":"C\u00f3rdoba",
    "wof:name":"Ingyser S. A.",
    "wof:placetype":"venue"
},
  "geometry": {"coordinates":[-4.7828125954,37.8956069946],"type":"Point"}
}