{
  "type": "Feature",
  "properties": {
    "iso:country":"ES",
    "sg:address":"Avda Inmaculada Concepcion, 31",
    "sg:city":"Arroyo De La Miel-benalmadena Costa",
    "sg:orig_category":"Comercio, Reparaci\u00d3n De Bicicletas, De Motocicletas, De Accesorios",
    "sg:phone":"+34 952 57 84 52",
    "sg:postcode":"29631",
    "sg:province":"M\u00e1laga",
    "wof:name":"Cueto Lucena Miguel Angel",
    "wof:placetype":"venue"
},
  "geometry": {"coordinates":[-4.5335688591,36.6028213501],"type":"Point"}
}