{
  "type": "Feature",
  "properties": {
    "iso:country":"ES",
    "sg:address":"Av Cornella, 13",
    "sg:city":"Esplugues Llobregat",
    "sg:orig_category":"M\u00c9dicos: Estomatolog\u00cda",
    "sg:phone":"+34 934 73 04 84",
    "sg:postcode":"08950",
    "sg:province":"Barcelona",
    "wof:name":"Cahuana Cardenas Abel",
    "wof:placetype":"venue"
},
  "geometry": {"coordinates":[2.0842609406,41.3737335205],"type":"Point"}
}