{
  "type": "Feature",
  "properties": {
    "iso:country":"ES",
    "sg:address":"Carrer de Pou Del Gla\u00c7, 35",
    "sg:city":"Olot",
    "sg:orig_category":"Colchones (fabricaci\u00d3n, Al Por Mayor, Al Por Menor)",
    "sg:phone":"+34 972 26 48 41",
    "sg:postcode":"17800",
    "sg:province":"Girona",
    "wof:name":"Gifre Dorca Ramon",
    "wof:placetype":"venue"
},
  "geometry": {"coordinates":[2.4801199436,42.1832046509],"type":"Point"}
}