{
  "type": "Feature",
  "properties": {
    "iso:country":"ES",
    "sg:address":"Calle de Malaga, 4",
    "sg:city":"Ejido",
    "sg:orig_category":"M\u00c9dicos: Pediatr\u00cda. Enfermedades De Los Ni\u00d1os",
    "sg:phone":"+34 950 48 16 79",
    "sg:postcode":"04700",
    "sg:province":"Almer\u00eda",
    "wof:name":"Salomao Osman Armando",
    "wof:placetype":"venue"
},
  "geometry": {"coordinates":[-2.8195691109,36.7730102539],"type":"Point"}
}