{
  "type": "Feature",
  "properties": {
    "addr:full":"Rbla Nova, 15 Mollet Valles Barcelona 08100",
    "addr:housenumber":"15",
    "addr:postcode":"08100",
    "addr:street":"Rbla Nova",
    "iso:country":"ES",
    "sg:address":"Rbla Nova, 15",
    "sg:city":"Mollet Valles",
    "sg:orig_category":"Electricidad: Equipos Industriales, Componentes (fabricaci\u00d3n)",
    "sg:phone":"+34 935 93 16 06",
    "sg:postcode":"08100",
    "sg:province":"Barcelona",
    "wof:name":"Subministres Tecnics Electronics S.l.",
    "wof:placetype":"venue"
},
  "geometry": {"coordinates":[2.2106900215,41.5386810303],"type":"Point"}
}