{
  "type": "Feature",
  "properties": {
    "iso:country":"ES",
    "sg:address":"Carr Sant Jordi, 18",
    "sg:city":"Tremp",
    "sg:orig_category":"Transportes De Animales Vivos",
    "sg:phone":"+34 973 65 00 23",
    "sg:postcode":"25620",
    "sg:province":"Lleida",
    "wof:name":"Fite Parramon Pedro",
    "wof:placetype":"venue"
},
  "geometry": {"coordinates":[0.8968200088,42.164604187],"type":"Point"}
}