{
  "type": "Feature",
  "properties": {
    "iso:country":"ES",
    "sg:address":"Calle de Fundicion, 2",
    "sg:city":"Gijon",
    "sg:orig_category":"Agencias De Viajes",
    "sg:phone":"+34 985 35 43 39",
    "sg:postcode":"33206",
    "sg:province":"Asturias",
    "sg:website":"www.grupoaltamira.com",
    "wof:name":"Viajes Altamira S. L.",
    "wof:placetype":"venue"
},
  "geometry": {"coordinates":[-5.6652088165,43.53855896],"type":"Point"}
}