{
  "type": "Feature",
  "properties": {
    "addr:full":"Calle de Ripa (la), 3 Zaragoza Zaragoza 50006",
    "addr:housenumber":"3",
    "addr:postcode":"50006",
    "addr:street":"Calle De Ripa La",
    "iso:country":"ES",
    "sg:address":"Calle de Ripa (la), 3",
    "sg:city":"Zaragoza",
    "sg:orig_category":"Electricidad Veh\u00cdculo",
    "sg:phone":"+34 976 55 87 10",
    "sg:postcode":"50006",
    "sg:province":"Zaragoza",
    "wof:name":"Faycom Produccion Y Comercializacion S.a.",
    "wof:placetype":"venue"
},
  "geometry": {"coordinates":[-0.8813189864,41.6517295837],"type":"Point"}
}