{
  "type": "Feature",
  "properties": {
    "addr:full":"Velazquez, 106 Madrid Madrid 28006",
    "addr:housenumber":"106",
    "addr:postcode":"28006",
    "addr:street":"Velazquez",
    "iso:country":"ES",
    "sg:address":"Velazquez, 106",
    "sg:city":"Madrid",
    "sg:orig_category":"Producci\u00d3n, Venta De Productos De Agricultura Biol\u00d3gica",
    "sg:phone":"+34 915 62 55 21",
    "sg:postcode":"28006",
    "sg:province":"Madrid",
    "wof:name":"Worldbest Cigars Sucursal En Espa\u00d1a",
    "wof:placetype":"venue"
},
  "geometry": {"coordinates":[-3.6833424568,40.4350662231],"type":"Point"}
}