{
  "type": "Feature",
  "properties": {
    "addr:full":"Calle de Santa Maria Del Valle, S/n Jaen Ja\u00e9n 23009",
    "addr:housenumber":"s / n;jae\u0301n",
    "addr:postcode":"23009",
    "addr:street":"Calle De Santa",
    "iso:country":"ES",
    "sg:address":"Calle de Santa Maria Del Valle, S/n",
    "sg:city":"Jaen",
    "sg:orig_category":"Ense\u00d1anza Secundaria: Colegios Y Escuelas Privadas",
    "sg:phone":"+34 953 29 60 49",
    "sg:postcode":"23009",
    "sg:province":"Ja\u00e9n",
    "wof:name":"Junta De Andalucia",
    "wof:placetype":"venue"
},
  "geometry": {"coordinates":[-3.77926898,37.7836761475],"type":"Point"}
}