{
  "type": "Feature",
  "properties": {
    "addr:full":"Calle de Adriano, 45 Sevilla Sevilla 41001",
    "addr:housenumber":"45",
    "addr:postcode":"41001",
    "addr:street":"Calle De Adriano",
    "iso:country":"ES",
    "sg:address":"Calle de Adriano, 45",
    "sg:city":"Sevilla",
    "sg:orig_category":"Muebles, Minoristas",
    "sg:phone":"+34 954 22 06 78",
    "sg:postcode":"41001",
    "sg:province":"Sevilla",
    "wof:name":"Batik Decoracion S.l.",
    "wof:placetype":"venue"
},
  "geometry": {"coordinates":[-5.9998540878,37.3866500854],"type":"Point"}
}