{
  "type": "Feature",
  "properties": {
    "addr:full":"Pla\u00c7 Esplanada, De S', 26 Mao Islas Baleares 07702",
    "addr:postcode":"07702",
    "addr:street":"Islas",
    "iso:country":"ES",
    "sg:address":"Pla\u00c7 Esplanada, De S', 26",
    "sg:city":"Mao",
    "sg:orig_category":"Doctores En Medicina",
    "sg:phone":"+34 971 36 85 83",
    "sg:postcode":"07702",
    "sg:province":"Islas Baleares",
    "wof:name":"Abellan Olaya Juan",
    "wof:placetype":"venue"
},
  "geometry": {"coordinates":[4.266668,39.879871],"type":"Point"}
}