{
  "type": "Feature",
  "properties": {
    "addr:full":"Carrer de Lepant, 241 Barcelona Barcelona 08013",
    "addr:housenumber":"241",
    "addr:postcode":"08013",
    "addr:street":"Carrer De Lepant",
    "iso:country":"ES",
    "sg:address":"Carrer de Lepant, 241",
    "sg:city":"Barcelona",
    "sg:orig_category":"Empresarios",
    "sg:phone":"+34 934 50 49 70",
    "sg:postcode":"08013",
    "sg:province":"Barcelona",
    "wof:name":"Rucasa Mediterranea S.l.",
    "wof:placetype":"venue"
},
  "geometry": {"coordinates":[2.1781001091,41.4032745361],"type":"Point"}
}