{
  "type": "Feature",
  "properties": {
    "iso:country":"ES",
    "sg:address":"Plaza De La Solara, 5",
    "sg:city":"Gozon",
    "sg:orig_category":"Molduras, Junquillos, Listones Y Molduras Perforadas",
    "sg:phone":"+34 985 88 14 56",
    "sg:postcode":"33440",
    "sg:province":"Asturias",
    "wof:name":"Damaso Jose Fernandez Mendez",
    "wof:placetype":"venue"
},
  "geometry": {"coordinates":[-5.7969498634,43.6147079468],"type":"Point"}
}