{
  "type": "Feature",
  "properties": {
    "addr:full":"Calle de Nueva, 21 Aparecida Murcia 30593",
    "addr:postcode":"30593",
    "addr:street":"Calle De Nueva 21",
    "iso:country":"ES",
    "sg:address":"Calle de Nueva, 21",
    "sg:city":"Aparecida",
    "sg:orig_category":"Centros De Educaci\u00d3n Especial",
    "sg:phone":"+34 968 16 55 04",
    "sg:postcode":"30593",
    "sg:province":"Murcia",
    "wof:name":"Colegio Publico Hacim",
    "wof:placetype":"venue"
},
  "geometry": {"coordinates":[-0.9635639787,37.689781189],"type":"Point"}
}