{
  "type": "Feature",
  "properties": {
    "addr:full":"Carr Castell, 6 Solsona Lleida 25280",
    "addr:housenumber":"6",
    "addr:postcode":"25280",
    "addr:street":"Carr Castell",
    "iso:country":"ES",
    "sg:address":"Carr Castell, 6",
    "sg:city":"Solsona",
    "sg:orig_category":"Tapicer\u00cdas",
    "sg:phone":"+34 973 48 14 25",
    "sg:postcode":"25280",
    "sg:province":"Lleida",
    "wof:name":"Jose Ribalta S.l.",
    "wof:placetype":"venue"
},
  "geometry": {"coordinates":[1.5179599524,41.9945793152],"type":"Point"}
}