{
  "type": "Feature",
  "properties": {
    "iso:country":"ES",
    "sg:address":"Calle de Murga, 49",
    "sg:city":"Palmas De Gran Canaria",
    "sg:orig_category":"Asesor\u00cda Fiscal Y Jur\u00cddica",
    "sg:phone":"+34 928 37 34 50",
    "sg:postcode":"35003",
    "sg:province":"Las Palmas",
    "wof:name":"Gonzalez Gonzalez Sergio",
    "wof:placetype":"venue"
},
  "geometry": {"coordinates":[-15.4213581085,28.1103610992],"type":"Point"}
}