{
  "type": "Feature",
  "properties": {
    "iso:country":"ES",
    "sg:address":"Calle de Marques De San Esteban, 39",
    "sg:city":"Gijon",
    "sg:orig_category":"Papeler\u00cdas: Art\u00cdculos (al Por Mayor)",
    "sg:phone":"+34 985 34 17 00",
    "sg:postcode":"33206",
    "sg:province":"Asturias",
    "sg:website":"www.carlin.es",
    "wof:name":"Mercado De Papel S.l.",
    "wof:placetype":"venue"
},
  "geometry": {"coordinates":[-5.6682648659,43.5415840149],"type":"Point"}
}