{
  "type": "Feature",
  "properties": {
    "addr:full":"Calle de Iberrota, 1 Ugeraga Vizcaya 48600",
    "addr:housenumber":"1",
    "addr:postcode":"48600",
    "addr:street":"Calle De Iberrota",
    "iso:country":"ES",
    "sg:address":"Calle de Iberrota, 1",
    "sg:city":"Ugeraga",
    "sg:orig_category":"Psic\u00d3logos",
    "sg:phone":"+34 946 76 08 62",
    "sg:postcode":"48600",
    "sg:province":"Vizcaya",
    "wof:name":"Sorkari",
    "wof:placetype":"venue"
},
  "geometry": {"coordinates":[-2.9875178337,43.3771209717],"type":"Point"}
}