{
  "type": "Feature",
  "properties": {
    "iso:country":"ES",
    "sg:address":"Plaz Indautxu, 2",
    "sg:city":"Bilbao",
    "sg:orig_category":"Caf\u00c9s, Bares, Cervecer\u00cdas",
    "sg:phone":"+34 944 21 43 24",
    "sg:postcode":"48010",
    "sg:province":"Vizcaya",
    "wof:name":"Subindau S.l.",
    "wof:placetype":"venue"
},
  "geometry": {"coordinates":[-2.9401140213,43.2609367371],"type":"Point"}
}