{
  "type": "Feature",
  "properties": {
    "iso:country":"ES",
    "sg:address":"Calle de Carretera De Villena, Km. 0001,3",
    "sg:city":"Yecla",
    "sg:orig_category":"Comit\u00c9s De Organizaci\u00d3n De Exposiciones, Ferias, Salones",
    "sg:phone":"+34 968 75 12 81",
    "sg:postcode":"30510",
    "sg:province":"Murcia",
    "wof:name":"Ortu\u00f1o Y Soriano S.l.",
    "wof:placetype":"venue"
},
  "geometry": {"coordinates":[-1.173699379,38.6051635742],"type":"Point"}
}