{
  "type": "Feature",
  "properties": {
    "iso:country":"ES",
    "sg:address":"Carrer de Piereta, 63",
    "sg:city":"Piera",
    "sg:orig_category":"Supermercados Y Hipermercados",
    "sg:phone":"+34 937 78 83 31",
    "sg:postcode":"08784",
    "sg:province":"Barcelona",
    "wof:name":"Alimentaria Piermont S.l.",
    "wof:placetype":"venue"
},
  "geometry": {"coordinates":[1.7529108524,41.5229072571],"type":"Point"}
}