{
  "type": "Feature",
  "properties": {
    "iso:country":"ES",
    "sg:address":"Calle de Espronceda, 13",
    "sg:city":"Linares",
    "sg:orig_category":"Ingeniero",
    "sg:phone":"+34 953 60 05 48",
    "sg:postcode":"23700",
    "sg:province":"Ja\u00e9n",
    "wof:name":"Due\u00f1as Moreno Eduardo",
    "wof:placetype":"venue"
},
  "geometry": {"coordinates":[-3.6316618919,38.095615387],"type":"Point"}
}