{
  "type": "Feature",
  "properties": {
    "addr:full":"Rua Marquesa (la), 3 Pontevedra Pontevedra 36002",
    "addr:housenumber":"3",
    "addr:postcode":"36002",
    "addr:street":"Rua Marquesa La",
    "iso:country":"ES",
    "sg:address":"Rua Marquesa (la), 3",
    "sg:city":"Pontevedra",
    "sg:orig_category":"Arquitectos",
    "sg:phone":"+34 986 85 54 71",
    "sg:postcode":"36002",
    "sg:province":"Pontevedra",
    "wof:name":"De Pedro Quijano Gonzalo",
    "wof:placetype":"venue"
},
  "geometry": {"coordinates":[-8.6461086273,42.4313354492],"type":"Point"}
}