{
  "type": "Feature",
  "properties": {
    "iso:country":"ES",
    "sg:address":"Carrer de Turo De Monterols, 11",
    "sg:city":"Barcelona",
    "sg:orig_category":"Asesor\u00cda Sobre Comunicaci\u00d3n De Empresas",
    "sg:phone":"+34 932 00 69 39",
    "sg:postcode":"08006",
    "sg:province":"Barcelona",
    "wof:name":"Lowell And Arrow's Management Consulting Services S.l.",
    "wof:placetype":"venue"
},
  "geometry": {"coordinates":[2.1426100731,41.4021606445],"type":"Point"}
}