{
  "type": "Feature",
  "properties": {
    "iso:country":"ES",
    "sg:address":"Calle de Convento, 44",
    "sg:city":"Cartaya",
    "sg:orig_category":"Guarder\u00cdas",
    "sg:phone":"+34 959 39 15 22",
    "sg:postcode":"21450",
    "sg:province":"Huelva",
    "wof:name":"Abreu Collante Ana Isabel",
    "wof:placetype":"venue"
},
  "geometry": {"coordinates":[-7.152067,37.282619],"type":"Point"}
}