{
  "type": "Feature",
  "properties": {
    "iso:country":"ES",
    "sg:address":"Calle de Ramon Asensio, 15",
    "sg:city":"Valencia",
    "sg:orig_category":"Promotores Constructores",
    "sg:phone":"+34 963 93 01 50",
    "sg:postcode":"46020",
    "sg:province":"Valencia",
    "wof:name":"Construcciones Puchades S.l.",
    "wof:placetype":"venue"
},
  "geometry": {"coordinates":[-0.3578869998,39.4833297729],"type":"Point"}
}