{
  "type": "Feature",
  "properties": {
    "iso:country":"ES",
    "sg:address":"Calle de Castan Tobe\u00d1as, 66",
    "sg:city":"Valencia",
    "sg:orig_category":"Ropa Para Se\u00d1oras (al Por Menor)",
    "sg:phone":"+34 963 83 52 55",
    "sg:postcode":"46018",
    "sg:province":"Valencia",
    "wof:name":"Susana Modas S.l.",
    "wof:placetype":"venue"
},
  "geometry": {"coordinates":[-0.4017460048,39.4729804993],"type":"Point"}
}