{
  "type": "Feature",
  "properties": {
    "iso:country":"ES",
    "sg:address":"Carr Pou, 45",
    "sg:city":"Sant Lloren\u00c7 Des Cardassar",
    "sg:orig_category":"Inform\u00c1tica, Ofim\u00c1tica (estudios, Asesor\u00cda, Ingenier\u00cda, Formaci\u00d3n)",
    "sg:phone":"+34 971 83 86 53",
    "sg:postcode":"07530",
    "sg:province":"Islas Baleares",
    "wof:name":"Informatica Cardassar S.l.l.",
    "wof:placetype":"venue"
},
  "geometry": {"coordinates":[3.2863104343,39.6104774475],"type":"Point"}
}