{
  "type": "Feature",
  "properties": {
    "addr:full":"Carrer de Juan De La Cierva, 17 Castelldefels Barcelona 08860",
    "addr:housenumber":"17",
    "addr:postcode":"08860",
    "addr:street":"Carrer De Juan De La Cierva",
    "iso:country":"ES",
    "sg:address":"Carrer de Juan De La Cierva, 17",
    "sg:city":"Castelldefels",
    "sg:orig_category":"Distribuci\u00d3n De Petr\u00d3leo Y Derivados",
    "sg:phone":"+34 936 36 68 01",
    "sg:postcode":"08860",
    "sg:province":"Barcelona",
    "wof:name":"Upesca S.l.",
    "wof:placetype":"venue"
},
  "geometry": {"coordinates":[1.9827460051,41.2845420837],"type":"Point"}
}