{
  "type": "Feature",
  "properties": {
    "addr:full":"Calle de Juan Uria Riu, 2 Aviles Asturias 33401",
    "addr:housenumber":"2",
    "addr:postcode":"33401",
    "addr:street":"Calle De Juan Uria Riu",
    "iso:country":"ES",
    "sg:address":"Calle de Juan Uria Riu, 2",
    "sg:city":"Aviles",
    "sg:orig_category":"Molduras, Junquillos, Listones Y Molduras Perforadas",
    "sg:phone":"+34 985 52 71 15",
    "sg:postcode":"33401",
    "sg:province":"Asturias",
    "wof:name":"Fernandez Perez Luis",
    "wof:placetype":"venue"
},
  "geometry": {"coordinates":[-5.9331011772,43.5595359802],"type":"Point"}
}