{
  "type": "Feature",
  "properties": {
    "addr:full":"Calle de Principe De La Paz, 16 Aranjuez Madrid 28300",
    "addr:housenumber":"16",
    "addr:postcode":"28300",
    "addr:street":"Calle De Principe De La Paz",
    "iso:country":"ES",
    "sg:address":"Calle de Principe De La Paz, 16",
    "sg:city":"Aranjuez",
    "sg:orig_category":"Procuradores",
    "sg:phone":"+34 918 91 07 36",
    "sg:postcode":"28300",
    "sg:province":"Madrid",
    "wof:name":"Lopez Sanchez Ana Isabel",
    "wof:placetype":"venue"
},
  "geometry": {"coordinates":[-3.6080489159,40.0318565369],"type":"Point"}
}