{
  "type": "Feature",
  "properties": {
    "addr:full":"Avda Constitucion Espa\u00d1ola, 64 Burgos Burgos 09007",
    "addr:housenumber":"64",
    "addr:postcode":"09007",
    "addr:street":"Avda Constitucion Espan\u0303Ola",
    "iso:country":"ES",
    "sg:address":"Avda Constitucion Espa\u00d1ola, 64",
    "sg:city":"Burgos",
    "sg:orig_category":"Arquitectos",
    "sg:phone":"+34 947 24 18 25",
    "sg:postcode":"09007",
    "sg:province":"Burgos",
    "wof:name":"Izquierdo Nieto Juan Carlos",
    "wof:placetype":"venue"
},
  "geometry": {"coordinates":[-3.667098999,42.3472099304],"type":"Point"}
}