{
  "type": "Feature",
  "properties": {
    "iso:country":"ES",
    "sg:address":"Av Pais Valencia, 79",
    "sg:city":"Benissa",
    "sg:orig_category":"Quincaller\u00cda (al Por Menor)",
    "sg:phone":"+34 965 73 04 76",
    "sg:postcode":"03720",
    "sg:province":"Alicante",
    "wof:name":"Ribes Martinez Jose",
    "wof:placetype":"venue"
},
  "geometry": {"coordinates":[0.051008001,38.7143745422],"type":"Point"}
}