{
  "type": "Feature",
  "properties": {
    "iso:country":"ES",
    "sg:address":"Carrer de Jaume Balmes, 87",
    "sg:city":"S. Pere Ribes",
    "sg:orig_category":"Peluquer\u00cdas, Peluquer\u00cda Mixta",
    "sg:phone":"+34 938 96 25 17",
    "sg:postcode":"08810",
    "sg:province":"Barcelona",
    "wof:name":"Look Magic S.l.",
    "wof:placetype":"venue"
},
  "geometry": {"coordinates":[1.7721560001,41.2586517334],"type":"Point"}
}