{
  "type": "Feature",
  "properties": {
    "addr:full":"Calle de Santiago, 47 Llerena Badajoz 06900",
    "addr:housenumber":"47",
    "addr:postcode":"06900",
    "addr:street":"Calle De Santiago",
    "iso:country":"ES",
    "sg:address":"Calle de Santiago, 47",
    "sg:city":"Llerena",
    "sg:orig_category":"Cajas De Ahorro",
    "sg:phone":"+34 924 87 00 78",
    "sg:postcode":"06900",
    "sg:province":"Badajoz",
    "sg:website":"www.cajabadajoz.es",
    "wof:name":"Caja De Badajoz",
    "wof:placetype":"venue"
},
  "geometry": {"coordinates":[-6.0164241791,38.2372627258],"type":"Point"}
}