{
  "type": "Feature",
  "properties": {
    "iso:country":"ES",
    "sg:address":"Carrer de Girones, 9",
    "sg:city":"Residencial",
    "sg:orig_category":"Arquitectos",
    "sg:phone":"+34 977 69 90 99",
    "sg:postcode":"43820",
    "sg:province":"Tarragona",
    "wof:name":"Arquetipus S.l.",
    "wof:placetype":"venue"
},
  "geometry": {"coordinates":[1.5806473494,41.1942634583],"type":"Point"}
}