{
  "type": "Feature",
  "properties": {
    "iso:country":"ES",
    "sg:address":"Pase Alcalde Sanchez Prados, 10",
    "sg:city":"Ceuta",
    "sg:orig_category":"M\u00c9dicos: Estomatolog\u00cda",
    "sg:phone":"+34 856 20 00 01",
    "sg:postcode":"51001",
    "sg:province":"Ceuta",
    "wof:name":"Nieto Garcia Victor",
    "wof:placetype":"venue"
},
  "geometry": {"coordinates":[-5.3302302361,35.8947601318],"type":"Point"}
}