{
  "type": "Feature",
  "properties": {
    "iso:country":"ES",
    "sg:address":"Carrer de Casa Nova (de La), 5",
    "sg:city":"Montornes Nord",
    "sg:orig_category":"Comercio De Cuadros, L\u00c1minas Y Reproducciones De Obras De Arte",
    "sg:phone":"+34 935 79 93 00",
    "sg:postcode":"08170",
    "sg:province":"Barcelona",
    "wof:name":"Decor Lamina S.l.",
    "wof:placetype":"venue"
},
  "geometry": {"coordinates":[2.2673149109,41.5512161255],"type":"Point"}
}