{
  "type": "Feature",
  "properties": {
    "addr:full":"Plaz Rinconada, 8 Valladolid Valladolid 47001",
    "addr:housenumber":"8",
    "addr:postcode":"47001",
    "addr:street":"Rinconada",
    "iso:country":"ES",
    "sg:address":"Plaz Rinconada, 8",
    "sg:city":"Valladolid",
    "sg:orig_category":"Hosteler\u00cda, Empleados",
    "sg:phone":"+34 983 37 35 63",
    "sg:postcode":"47001",
    "sg:province":"Valladolid",
    "wof:name":"Asensio Centeno Jacinto",
    "wof:placetype":"venue"
},
  "geometry": {"coordinates":[-4.7289447784,41.6531639099],"type":"Point"}
}