{
  "type": "Feature",
  "properties": {
    "addr:full":"Calle de Camino Viejo Callosa, 51 Orihuela Alicante 03300",
    "addr:housenumber":"51",
    "addr:postcode":"03300",
    "addr:street":"Calle De Camino Viejo Callosa",
    "iso:country":"ES",
    "sg:address":"Calle de Camino Viejo Callosa, 51",
    "sg:city":"Orihuela",
    "sg:orig_category":"Delegados, Agentes De Tr\u00c1nsito, Auxiliares De Transporte Internacional",
    "sg:phone":"+34 965 30 10 51",
    "sg:postcode":"03300",
    "sg:province":"Alicante",
    "wof:name":"Antonio Y Puri Torres S.l.",
    "wof:placetype":"venue"
},
  "geometry": {"coordinates":[-0.9387984872,38.0897102356],"type":"Point"}
}