{
  "type": "Feature",
  "properties": {
    "iso:country":"ES",
    "sg:address":"Plaz Zorita, S/n",
    "sg:city":"Alcala Henares",
    "sg:orig_category":"Confecci\u00d3n De Trajes Para Se\u00d1oras",
    "sg:phone":"+34 918 83 62 64",
    "sg:postcode":"28805",
    "sg:province":"Madrid",
    "sg:website":"www.pimkie.com",
    "wof:name":"Dimodes S.a.",
    "wof:placetype":"venue"
},
  "geometry": {"coordinates":[-3.3307089806,40.5036354065],"type":"Point"}
}