{
  "type": "Feature",
  "properties": {
    "addr:full":"Avgd Princep D'espanya, 2 Alcudia Islas Baleares 07400",
    "addr:housenumber":"2",
    "addr:postcode":"07400",
    "addr:street":"D'Espanya",
    "iso:country":"ES",
    "sg:address":"Avgd Princep D'espanya, 2",
    "sg:city":"Alcudia",
    "sg:orig_category":"Confecci\u00d3n (fabricaci\u00d3n, Al Por Mayor)",
    "sg:phone":"+34 971 54 79 00",
    "sg:postcode":"07400",
    "sg:province":"Islas Baleares",
    "wof:name":"Lucas Diaz Maria Dolores",
    "wof:placetype":"venue"
},
  "geometry": {"coordinates":[3.1231040955,39.8517036438],"type":"Point"}
}