{
  "type": "Feature",
  "properties": {
    "addr:full":"Carr Mossen Bartomeu Barcelo, S/n Felanitx Islas Baleares 07200",
    "addr:housenumber":"s",
    "addr:postcode":"07200",
    "addr:street":"Carr Mossen Bartomeu Barcelo;/ N",
    "iso:country":"ES",
    "sg:address":"Carr Mossen Bartomeu Barcelo, S/n",
    "sg:city":"Felanitx",
    "sg:orig_category":"Productores Recolectores, Venta Directa De Vinos",
    "sg:phone":"+34 971 82 71 03",
    "sg:postcode":"07200",
    "sg:province":"Islas Baleares",
    "wof:name":"Armero Gonzalez Luis Vicente",
    "wof:placetype":"venue"
},
  "geometry": {"coordinates":[3.1444137096,39.4757232666],"type":"Point"}
}