{
  "type": "Feature",
  "properties": {
    "addr:full":"Carrer de Sant Felip, 13 Masnou Barcelona 08320",
    "addr:housenumber":"13",
    "addr:postcode":"08320",
    "addr:street":"Carrer De Sant Felip",
    "iso:country":"ES",
    "sg:address":"Carrer de Sant Felip, 13",
    "sg:city":"Masnou",
    "sg:orig_category":"Alimentaci\u00d3n General (al Por Menor)",
    "sg:phone":"+34 935 55 62 75",
    "sg:postcode":"08320",
    "sg:province":"Barcelona",
    "wof:name":"Can Mai Tanquis S.c.p.",
    "wof:placetype":"venue"
},
  "geometry": {"coordinates":[2.3202800751,41.4804039001],"type":"Point"}
}