{
  "type": "Feature",
  "properties": {
    "addr:full":"Pl Don Miquel Clariana, 2 Vic Barcelona 08500",
    "addr:housenumber":"2",
    "addr:postcode":"08500",
    "addr:street":"Pl Don Miquel Clariana",
    "iso:country":"ES",
    "sg:address":"Pl Don Miquel Clariana, 2",
    "sg:city":"Vic",
    "sg:orig_category":"Centros P\u00dablicos De Formaci\u00d3n Profesional Y T\u00c9cnica",
    "sg:phone":"+34 938 89 33 43",
    "sg:postcode":"08500",
    "sg:province":"Barcelona",
    "wof:name":"Co%egi D'advocats De Vic",
    "wof:placetype":"venue"
},
  "geometry": {"coordinates":[2.2577090263,41.9292144775],"type":"Point"}
}