{
  "type": "Feature",
  "properties": {
    "iso:country":"ES",
    "sg:address":"Av Punta Grossa, 10",
    "sg:city":"Cala D'or",
    "sg:orig_category":"Supermercados Y Hipermercados",
    "sg:phone":"+34 971 64 84 21",
    "sg:postcode":"07660",
    "sg:province":"Islas Baleares",
    "wof:name":"Antich Serra Francisco",
    "wof:placetype":"venue"
},
  "geometry": {"coordinates":[3.2335908413,39.3772201538],"type":"Point"}
}