{
  "type": "Feature",
  "properties": {
    "iso:country":"ES",
    "sg:address":"Av Lesseps, 2",
    "sg:city":"Cerdanyola Valles",
    "sg:orig_category":"Asistencia Domiciliaria",
    "sg:phone":"+34 935 86 44 54",
    "sg:postcode":"08290",
    "sg:province":"Barcelona",
    "wof:name":"Asociacion De Servicios Aser",
    "wof:placetype":"venue"
},
  "geometry": {"coordinates":[2.1442644596,41.4847488403],"type":"Point"}
}