{
  "type": "Feature",
  "properties": {
    "iso:country":"ES",
    "sg:address":"Calle de Rosalia De Castro, 1",
    "sg:city":"Antas",
    "sg:orig_category":"Transportes Por V\u00cdas Navegables",
    "sg:phone":"+34 950 45 36 79",
    "sg:postcode":"04628",
    "sg:province":"Almer\u00eda",
    "wof:name":"Translafer S.l.",
    "wof:placetype":"venue"
},
  "geometry": {"coordinates":[-1.9191410542,37.2423439026],"type":"Point"}
}