{
  "type": "Feature",
  "properties": {
    "addr:full":"Calle de Hermanos Pinzon, 29 Albacete Albacete 02006",
    "addr:housenumber":"29",
    "addr:postcode":"02006",
    "addr:street":"Calle De Hermanos Pinzon",
    "iso:country":"ES",
    "sg:address":"Calle de Hermanos Pinzon, 29",
    "sg:city":"Albacete",
    "sg:orig_category":"Carnes De Carnicer\u00cda (al Por Mayor)",
    "sg:phone":"+34 967 50 90 40",
    "sg:postcode":"02006",
    "sg:province":"Albacete",
    "wof:name":"Carnes Estelles S.a.",
    "wof:placetype":"venue"
},
  "geometry": {"coordinates":[-1.8479989767,38.986366272],"type":"Point"}
}