{
  "type": "Feature",
  "properties": {
    "addr:full":"Afueras, S/n Arroyomolinos C\u00e1ceres 10161",
    "addr:postcode":"10161",
    "addr:street":"Afueras S / N",
    "iso:country":"ES",
    "sg:address":"Afueras, S/n",
    "sg:city":"Arroyomolinos",
    "sg:orig_category":"Deportes Diversos",
    "sg:phone":"+34 927 19 60 13",
    "sg:postcode":"10161",
    "sg:province":"C\u00e1ceres",
    "wof:name":"Explotaciones Las Jarillas Oeste S.l.",
    "wof:placetype":"venue"
},
  "geometry": {"coordinates":[-6.1632142067,39.1858100891],"type":"Point"}
}