{
  "type": "Feature",
  "properties": {
    "addr:full":"Pase Amanecer, 2 Javea Alicante 03730",
    "addr:postcode":"03730",
    "iso:country":"ES",
    "sg:address":"Pase Amanecer, 2",
    "sg:city":"Javea",
    "sg:orig_category":"Bares, Piano",
    "sg:phone":"+34 965 79 41 33",
    "sg:postcode":"03730",
    "sg:province":"Alicante",
    "wof:name":"Tusk Inversiones S.l.",
    "wof:placetype":"venue"
},
  "geometry": {"coordinates":[0.1570300013,38.7885093689],"type":"Point"}
}