{
  "type": "Feature",
  "properties": {
    "addr:full":"Calle de Zarandieta, 4 Alacant Alicante 03010",
    "addr:housenumber":"4",
    "addr:postcode":"03010",
    "addr:street":"Calle De Zarandieta",
    "iso:country":"ES",
    "sg:address":"Calle de Zarandieta, 4",
    "sg:city":"Alacant",
    "sg:orig_category":"Molduras, Junquillos, Listones Y Molduras Perforadas",
    "sg:phone":"+34 965 24 38 76",
    "sg:postcode":"03010",
    "sg:province":"Alicante",
    "wof:name":"Gonzalez Pinero Ismael",
    "wof:placetype":"venue"
},
  "geometry": {"coordinates":[-0.4879980087,38.357963562],"type":"Point"}
}