{
  "type": "Feature",
  "properties": {
    "addr:full":"Carrer de Avinyo, 12 Barcelona Barcelona 08002",
    "addr:housenumber":"12",
    "addr:postcode":"08002",
    "addr:street":"Carrer De Avinyo",
    "iso:country":"ES",
    "sg:address":"Carrer de Avinyo, 12",
    "sg:city":"Barcelona",
    "sg:orig_category":"Peluquer\u00cdas, Peluquer\u00cda Mixta",
    "sg:phone":"+34 933 02 69 86",
    "sg:postcode":"08002",
    "sg:province":"Barcelona",
    "sg:website":"www.salva-g.com",
    "wof:name":"See Emily Plays Sl",
    "wof:placetype":"venue"
},
  "geometry": {"coordinates":[2.1759459972,41.381477356],"type":"Point"}
}