{
  "type": "Feature",
  "properties": {
    "iso:country":"ES",
    "sg:address":"Calle de Azahar, 3",
    "sg:city":"Huelva",
    "sg:orig_category":"Quincaller\u00cda (al Por Menor)",
    "sg:phone":"+34 959 15 36 87",
    "sg:postcode":"21005",
    "sg:province":"Huelva",
    "wof:name":"Costa Esteban Antonio",
    "wof:placetype":"venue"
},
  "geometry": {"coordinates":[-6.9338078499,37.2746963501],"type":"Point"}
}