{
  "type": "Feature",
  "properties": {
    "addr:full":"Av Catalunya, 4 Bellpuig Lleida 25250",
    "addr:housenumber":"4",
    "addr:postcode":"25250",
    "addr:street":"Av Catalunya",
    "iso:country":"ES",
    "sg:address":"Av Catalunya, 4",
    "sg:city":"Bellpuig",
    "sg:orig_category":"Agencias Y Agentes Comerciales, Representantes",
    "sg:phone":"+34 973 32 10 07",
    "sg:postcode":"25250",
    "sg:province":"Lleida",
    "wof:name":"Costa Llobera Alejandro",
    "wof:placetype":"venue"
},
  "geometry": {"coordinates":[1.0108799934,41.6270561218],"type":"Point"}
}