{
  "type": "Feature",
  "properties": {
    "addr:full":"Calle de Campi\u00d1a, 34 Martos Ja\u00e9n 23600",
    "addr:housenumber":"34",
    "addr:postcode":"23600",
    "addr:street":"Calle De Campin\u0303A;Jae\u0301N",
    "iso:country":"ES",
    "sg:address":"Calle de Campi\u00d1a, 34",
    "sg:city":"Martos",
    "sg:orig_category":"\u00d3ptica: Instrumentos (fabricaci\u00d3n)",
    "sg:phone":"+34 953 55 09 33",
    "sg:postcode":"23600",
    "sg:province":"Ja\u00e9n",
    "wof:name":"Simon Garcia Tomas",
    "wof:placetype":"venue"
},
  "geometry": {"coordinates":[-3.9684209824,37.7209739685],"type":"Point"}
}