{
  "type": "Feature",
  "properties": {
    "iso:country":"ES",
    "sg:address":"Calle de Velasquita, 1",
    "sg:city":"Le\u00f3n",
    "sg:orig_category":"Supermercados Y Hipermercados",
    "sg:phone":"+34 987 80 80 55",
    "sg:postcode":"24009",
    "sg:province":"Le\u00f3n",
    "wof:name":"Cenco S.a.",
    "wof:placetype":"venue"
},
  "geometry": {"coordinates":[-5.5872378349,42.5985069275],"type":"Point"}
}