{
  "type": "Feature",
  "properties": {
    "iso:country":"ES",
    "sg:address":"Rua Ponte (da), 7",
    "sg:city":"Lalin",
    "sg:orig_category":"Imprenta",
    "sg:phone":"+34 986 79 21 55",
    "sg:postcode":"36500",
    "sg:province":"Pontevedra",
    "wof:name":"Sanchez Corti\u00f1a Elena",
    "wof:placetype":"venue"
},
  "geometry": {"coordinates":[-8.1113786697,42.6637306213],"type":"Point"}
}