{
  "type": "Feature",
  "properties": {
    "addr:full":"Plaz Verdura (de La), 10 Ubrique C\u00e1diz 11600",
    "addr:postcode":"11600",
    "addr:street":"Ca\u0301Diz",
    "iso:country":"ES",
    "sg:address":"Plaz Verdura (de La), 10",
    "sg:city":"Ubrique",
    "sg:orig_category":"Librer\u00cdas",
    "sg:phone":"+34 956 46 37 73",
    "sg:postcode":"11600",
    "sg:province":"C\u00e1diz",
    "wof:name":"Ordo\u00f1ez Gonzalez Juan Francisco",
    "wof:placetype":"venue"
},
  "geometry": {"coordinates":[-5.4421639442,36.6773414612],"type":"Point"}
}