{
  "type": "Feature",
  "properties": {
    "addr:full":"Avda Pe\u00d1a Prieta, 11 Madrid Madrid 28038",
    "addr:housenumber":"11",
    "addr:postcode":"madrid;28038",
    "addr:street":"Avda Pen\u0303A Prieta",
    "iso:country":"ES",
    "sg:address":"Avda Pe\u00d1a Prieta, 11",
    "sg:city":"Madrid",
    "sg:orig_category":"Ropa Para Ni\u00d1os (al Por Menor)",
    "sg:phone":"+34 915 02 07 45",
    "sg:postcode":"28038",
    "sg:province":"Madrid",
    "wof:name":"Urbion Inversores S.a.",
    "wof:placetype":"venue"
},
  "geometry": {"coordinates":[-3.6673970222,40.3997840881],"type":"Point"}
}