{
  "type": "Feature",
  "properties": {
    "iso:country":"ES",
    "sg:address":"Calle de Villafranca, 4",
    "sg:city":"Le\u00f3n",
    "sg:orig_category":"Peluquer\u00cdas, Peluquer\u00cda Mixta",
    "sg:phone":"+34 987 25 64 55",
    "sg:postcode":"24001",
    "sg:province":"Le\u00f3n",
    "wof:name":"Arias Diez Fernando",
    "wof:placetype":"venue"
},
  "geometry": {"coordinates":[-5.5758953094,42.5963935852],"type":"Point"}
}