{
  "type": "Feature",
  "properties": {
    "iso:country":"ES",
    "sg:address":"Cami Ral, 377",
    "sg:city":"Mataro",
    "sg:orig_category":"Inmobiliaria (agencias)",
    "sg:phone":"+34 937 96 26 77",
    "sg:postcode":"08301",
    "sg:province":"Barcelona",
    "wof:name":"Guillen Bellan Zenon",
    "wof:placetype":"venue"
},
  "geometry": {"coordinates":[2.4446258545,41.5372161865],"type":"Point"}
}