{
  "type": "Feature",
  "properties": {
    "addr:full":"Calle de Villares Altos, 17 Tomares Sevilla 41940",
    "addr:housenumber":"17",
    "addr:postcode":"41940",
    "addr:street":"Calle De;Altos",
    "iso:country":"ES",
    "sg:address":"Calle de Villares Altos, 17",
    "sg:city":"Tomares",
    "sg:orig_category":"Inform\u00c1tica Equipo Y Programas (al Por Mayor)",
    "sg:phone":"+34 954 15 28 80",
    "sg:postcode":"41940",
    "sg:province":"Sevilla",
    "wof:name":"Ejarsoft Sl",
    "wof:placetype":"venue"
},
  "geometry": {"coordinates":[-6.037168026,37.3795433044],"type":"Point"}
}