{
  "type": "Feature",
  "properties": {
    "addr:full":"Rua Curros Enriquez, 57 Celanova Ourense 32800",
    "addr:housenumber":"57",
    "addr:postcode":"32800",
    "addr:street":"Rua Curros Enriquez",
    "iso:country":"ES",
    "sg:address":"Rua Curros Enriquez, 57",
    "sg:city":"Celanova",
    "sg:orig_category":"Abogados",
    "sg:phone":"+34 988 43 18 30",
    "sg:postcode":"32800",
    "sg:province":"Ourense",
    "wof:name":"Xurisgal S.l.",
    "wof:placetype":"venue"
},
  "geometry": {"coordinates":[-7.9587583542,42.1555976868],"type":"Point"}
}