{
  "type": "Feature",
  "properties": {
    "iso:country":"ES",
    "sg:address":"Calle de San Juan, 13",
    "sg:city":"Quintanar Orden",
    "sg:orig_category":"Inform\u00c1tica: Mantenimiento Y Reparaci\u00d3n De Ordenadores",
    "sg:phone":"+34 925 18 13 18",
    "sg:postcode":"45800",
    "sg:province":"Toledo",
    "sg:website":"www.mandisa.com",
    "wof:name":"Manchega De Informatica S.l.",
    "wof:placetype":"venue"
},
  "geometry": {"coordinates":[-3.046446085,39.5915412903],"type":"Point"}
}