{
  "type": "Feature",
  "properties": {
    "addr:full":"C/ Isabel La Catolica, 19 Alcoi Alicante 03803",
    "addr:housenumber":"19",
    "addr:postcode":"03803",
    "addr:street":"C / Isabel La Catolica",
    "iso:country":"ES",
    "sg:address":"C/ Isabel La Catolica, 19",
    "sg:city":"Alcoi",
    "sg:orig_category":"Administradores De Bienes Y Delegados De Comunidades De Propietarios",
    "sg:phone":"+34 965 52 04 98",
    "sg:postcode":"03803",
    "sg:province":"Alicante",
    "wof:name":"Domenech Lorenzo Rafael Federico",
    "wof:placetype":"venue"
},
  "geometry": {"coordinates":[-0.4812220037,38.7019271851],"type":"Point"}
}