{
  "type": "Feature",
  "properties": {
    "addr:full":"Calle de Rua Zapateria, 31 Plasencia C\u00e1ceres 10600",
    "addr:housenumber":"31",
    "addr:postcode":"10600",
    "addr:street":"Calle De Rua Zapateria;Ca\u0301Ceres",
    "iso:country":"ES",
    "sg:address":"Calle de Rua Zapateria, 31",
    "sg:city":"Plasencia",
    "sg:orig_category":"Inmobiliaria (agencias)",
    "sg:phone":"+34 927 42 64 21",
    "sg:postcode":"10600",
    "sg:province":"C\u00e1ceres",
    "wof:name":"Casta\u00f1o Villares Sonia",
    "wof:placetype":"venue"
},
  "geometry": {"coordinates":[-6.0907292366,40.0296211243],"type":"Point"}
}