{
  "type": "Feature",
  "properties": {
    "iso:country":"ES",
    "sg:address":"C/ Metge Ballester, 6",
    "sg:city":"Paterna",
    "sg:orig_category":"Quincaller\u00cda (al Por Menor)",
    "sg:phone":"+34 961 38 39 05",
    "sg:postcode":"46980",
    "sg:province":"Valencia",
    "wof:name":"Aparicio Yatas Maria",
    "wof:placetype":"venue"
},
  "geometry": {"coordinates":[-0.4405986071,39.5020637512],"type":"Point"}
}