{
  "type": "Feature",
  "properties": {
    "iso:country":"ES",
    "sg:address":"Calle de Egido, 14",
    "sg:city":"Cazalla Sierra",
    "sg:orig_category":"Art\u00cdculos De Regalo (al Por Menor)",
    "sg:phone":"+34 954 88 42 40",
    "sg:postcode":"41370",
    "sg:province":"Sevilla",
    "sg:website":"www.rabermar.com",
    "wof:name":"Beloren",
    "wof:placetype":"venue"
},
  "geometry": {"coordinates":[-5.7599191666,37.9338150024],"type":"Point"}
}