{
  "type": "Feature",
  "properties": {
    "addr:full":"Carrer de Ignasi Iglesias, 80 Barcelona Barcelona 08030",
    "addr:housenumber":"80",
    "addr:postcode":"08030",
    "addr:street":"Carrer De Ignasi Iglesias",
    "iso:country":"ES",
    "sg:address":"Carrer de Ignasi Iglesias, 80",
    "sg:city":"Barcelona",
    "sg:orig_category":"Asesores De Gesti\u00d3n Del Patrimonio",
    "sg:phone":"+34 933 46 98 57",
    "sg:postcode":"08030",
    "sg:province":"Barcelona",
    "wof:name":"Promociones Patrimoniales S.l.",
    "wof:placetype":"venue"
},
  "geometry": {"coordinates":[2.186811924,41.4338760376],"type":"Point"}
}