{
  "type": "Feature",
  "properties": {
    "iso:country":"ES",
    "sg:address":"Carrer de Arimon, 49",
    "sg:city":"Barcelona",
    "sg:orig_category":"Inmobiliaria (agencias)",
    "sg:phone":"+34 932 53 19 90",
    "sg:postcode":"08022",
    "sg:province":"Barcelona",
    "wof:name":"Agricola Industrial De Yecla S.l.",
    "wof:placetype":"venue"
},
  "geometry": {"coordinates":[2.135415554,41.4027786255],"type":"Point"}
}