{
  "type": "Feature",
  "properties": {
    "addr:full":"Calle de Colon De Larreategui, 17 Bilbao Vizcaya 48001",
    "addr:housenumber":"17",
    "addr:postcode":"48001",
    "addr:street":"Calle De Colon De Larreategui",
    "iso:country":"ES",
    "sg:address":"Calle de Colon De Larreategui, 17",
    "sg:city":"Bilbao",
    "sg:orig_category":"Fabricaci\u00d3n De Art\u00cdculos Y Ornamentos Religiosos",
    "sg:phone":"+34 944 23 13 72",
    "sg:postcode":"48001",
    "sg:province":"Vizcaya",
    "wof:name":"Pias Discipulas Del Divino Maestro",
    "wof:placetype":"venue"
},
  "geometry": {"coordinates":[-2.9295902252,43.2628974915],"type":"Point"}
}