{
  "type": "Feature",
  "properties": {
    "iso:country":"ES",
    "sg:address":"Rond Carralero, 2",
    "sg:city":"Majadahonda",
    "sg:orig_category":"Agentes, Concesionarios Y Sucursales De Veh\u00cdculos",
    "sg:phone":"+34 916 39 92 25",
    "sg:postcode":"28220",
    "sg:province":"Madrid",
    "wof:name":"Mavilsa Automoviles",
    "wof:placetype":"venue"
},
  "geometry": {"coordinates":[-3.8716540337,40.4739151001],"type":"Point"}
}