{
  "type": "Feature",
  "properties": {
    "addr:full":"Avda Federico Soto, 13 Alacant Alicante 03003",
    "addr:housenumber":"13",
    "addr:postcode":"03003",
    "addr:street":"Avda Federico Soto",
    "iso:country":"ES",
    "sg:address":"Avda Federico Soto, 13",
    "sg:city":"Alacant",
    "sg:orig_category":"Sociedades, Compa\u00d1\u00cdas Aseguradoras",
    "sg:phone":"+34 965 20 65 38",
    "sg:postcode":"03003",
    "sg:province":"Alicante",
    "wof:name":"Seguros Catalana Occidente S.a. De Seguros Y Reaseguros",
    "wof:placetype":"venue"
},
  "geometry": {"coordinates":[-0.4901970029,38.3450088501],"type":"Point"}
}