{
  "type": "Feature",
  "properties": {
    "addr:full":"Avda Miguel De Cervantes, 15 San Basilio Murcia 30009",
    "addr:housenumber":"15",
    "addr:postcode":"30009",
    "addr:street":"Avda Miguel De Cervantes",
    "iso:country":"ES",
    "sg:address":"Avda Miguel De Cervantes, 15",
    "sg:city":"San Basilio",
    "sg:orig_category":"Mec\u00c1nico Del Autom\u00d3vil",
    "sg:phone":"+34 968 28 62 03",
    "sg:postcode":"30009",
    "sg:province":"Murcia",
    "wof:name":"Talleres Autosaba S.l.l.",
    "wof:placetype":"venue"
},
  "geometry": {"coordinates":[-1.1426999569,37.9965629578],"type":"Point"}
}