{
  "type": "Feature",
  "properties": {
    "addr:full":"Praz Verdura (da), 4 Pontevedra Pontevedra 36002",
    "addr:postcode":"36002",
    "iso:country":"ES",
    "sg:address":"Praz Verdura (da), 4",
    "sg:city":"Pontevedra",
    "sg:orig_category":"Zapatos (al Por Menor)",
    "sg:phone":"+34 986 85 37 56",
    "sg:postcode":"36002",
    "sg:province":"Pontevedra",
    "wof:name":"Miguez Iglesias Fidela",
    "wof:placetype":"venue"
},
  "geometry": {"coordinates":[-8.6233987808,42.4448699951],"type":"Point"}
}