{
  "type": "Feature",
  "properties": {
    "addr:full":"Calle de Terminillo, 27 Zaragoza Zaragoza 50017",
    "addr:housenumber":"27",
    "addr:postcode":"50017",
    "addr:street":"Calle De Terminillo",
    "iso:country":"ES",
    "sg:address":"Calle de Terminillo, 27",
    "sg:city":"Zaragoza",
    "sg:orig_category":"Estancos",
    "sg:phone":"+34 976 34 09 98",
    "sg:postcode":"50017",
    "sg:province":"Zaragoza",
    "wof:name":"Sacacia Pisa Matilde",
    "wof:placetype":"venue"
},
  "geometry": {"coordinates":[-0.9073640108,41.6512565613],"type":"Point"}
}