{
  "type": "Feature",
  "properties": {
    "iso:country":"ES",
    "sg:address":"Carrer de Alberes, 40",
    "sg:city":"Barcelona",
    "sg:orig_category":"Locales Y Clases De Danza",
    "sg:phone":"+34 934 06 95 66",
    "sg:postcode":"08017",
    "sg:province":"Barcelona",
    "wof:name":"Lerin Vilardell Gloria",
    "wof:placetype":"venue"
},
  "geometry": {"coordinates":[2.1078839302,41.4145393372],"type":"Point"}
}