{
  "type": "Feature",
  "properties": {
    "addr:full":"Avda Isabel Ii De, 2 Donostia-san Sebastian Guip\u00f9zcoa 20011",
    "addr:housenumber":"2",
    "addr:postcode":"20011",
    "addr:street":"Avda Isabel Ii De",
    "iso:country":"ES",
    "sg:address":"Avda Isabel Ii De, 2",
    "sg:city":"Donostia-san Sebastian",
    "sg:orig_category":"M\u00c9dicos: Pediatr\u00cda. Enfermedades De Los Ni\u00d1os",
    "sg:phone":"+34 943 46 82 48",
    "sg:postcode":"20011",
    "sg:province":"Guip\u00f9zcoa",
    "wof:name":"Traba Rey Luis Miguel",
    "wof:placetype":"venue"
},
  "geometry": {"coordinates":[-1.9751800299,43.3051872253],"type":"Point"}
}