{
  "type": "Feature",
  "properties": {
    "addr:full":"Barr Chaos, 8 Chaos Lugo 27864",
    "addr:housenumber":"8",
    "addr:postcode":"27864",
    "addr:street":"Chaos",
    "iso:country":"ES",
    "sg:address":"Barr Chaos, 8",
    "sg:city":"Chaos",
    "sg:orig_category":"Empresas De Carpinter\u00cda Met\u00c1lica",
    "sg:phone":"+34 982 59 84 26",
    "sg:postcode":"27864",
    "sg:province":"Lugo",
    "wof:name":"Bermudez Lopez Natalia",
    "wof:placetype":"venue"
},
  "geometry": {"coordinates":[-8.6287069321,42.6321907043],"type":"Point"}
}