{
  "type": "Feature",
  "properties": {
    "iso:country":"ES",
    "sg:address":"Avda Compromiso De Caspe, 4",
    "sg:city":"Zaragoza",
    "sg:orig_category":"Notarios",
    "sg:phone":"+34 976 59 38 06",
    "sg:postcode":"50002",
    "sg:province":"Zaragoza",
    "wof:name":"Peman Melero Mariano Jesus",
    "wof:placetype":"venue"
},
  "geometry": {"coordinates":[-0.8708289862,41.6459960938],"type":"Point"}
}