{
  "type": "Feature",
  "properties": {
    "addr:full":"Plaz San Lorenzo, 4 Valencia Valencia 46...",
    "addr:housenumber":"4",
    "addr:street":"Plaz San Lorenzo;Valencia",
    "iso:country":"ES",
    "sg:address":"Plaz San Lorenzo, 4",
    "sg:city":"Valencia",
    "sg:orig_category":"Partidos Pol\u00cdticos",
    "sg:phone":"+34 963 87 63 00",
    "sg:postcode":"46...",
    "sg:province":"Valencia",
    "sg:website":"www.corts.gva.es",
    "wof:name":"Corts Valencianes",
    "wof:placetype":"venue"
},
  "geometry": {"coordinates":[-0.3769130111,39.4687919617],"type":"Point"}
}