{
  "type": "Feature",
  "properties": {
    "addr:full":"Carretera De Raigada, S/n Manzaneda Ourense 32781",
    "addr:housenumber":"s / n",
    "addr:postcode":"32781",
    "addr:street":"Carretera De Raigada",
    "iso:country":"ES",
    "sg:address":"Carretera De Raigada, S/n",
    "sg:city":"Manzaneda",
    "sg:orig_category":"Supermercados Y Hipermercados",
    "sg:phone":"+34 988 33 31 14",
    "sg:postcode":"32781",
    "sg:province":"Ourense",
    "wof:name":"Hervella Carrera S.l.",
    "wof:placetype":"venue"
},
  "geometry": {"coordinates":[-7.2340378761,42.3097381592],"type":"Point"}
}