{
  "type": "Feature",
  "properties": {
    "addr:full":"Calle de Castello, 4 Madrid Madrid 28001",
    "addr:housenumber":"4",
    "addr:postcode":"28001",
    "addr:street":"Calle De Castello",
    "iso:country":"ES",
    "sg:address":"Calle de Castello, 4",
    "sg:city":"Madrid",
    "sg:orig_category":"Caf\u00c9s, Bares, Cervecer\u00cdas",
    "sg:phone":"+34 915 76 46 98",
    "sg:postcode":"28001",
    "sg:province":"Madrid",
    "wof:name":"Eustaquio Lorenzo Palero Y Dos S.c.",
    "wof:placetype":"venue"
},
  "geometry": {"coordinates":[-3.6849496365,40.4395446777],"type":"Point"}
}