{
  "type": "Feature",
  "properties": {
    "iso:country":"ES",
    "sg:address":"Calle de Nebrija, 24",
    "sg:city":"Valladolid",
    "sg:orig_category":"Asociaciones Y Clubs Deportivos",
    "sg:phone":"+34 983 26 46 25",
    "sg:postcode":"47010",
    "sg:province":"Valladolid",
    "wof:name":"Sociedad Deportiva Rondilla",
    "wof:placetype":"venue"
},
  "geometry": {"coordinates":[-4.7224640846,41.6638069153],"type":"Point"}
}