{
  "type": "Feature",
  "properties": {
    "iso:country":"ES",
    "sg:address":"Calle de Cuesta Del Olivar, 13",
    "sg:city":"Cehegin",
    "sg:orig_category":"Transportes Por V\u00cdas Navegables",
    "sg:phone":"+34 968 74 29 30",
    "sg:postcode":"30430",
    "sg:province":"Murcia",
    "wof:name":"Lopez Fernandez Hermanos S.a.",
    "wof:placetype":"venue"
},
  "geometry": {"coordinates":[-1.788210392,38.0929794312],"type":"Point"}
}