{
  "type": "Feature",
  "properties": {
    "addr:full":"Calle de Carchena, 17 Cuellar Segovia 40200",
    "addr:housenumber":"17",
    "addr:postcode":"40200",
    "addr:street":"Calle De Carchena",
    "iso:country":"ES",
    "sg:address":"Calle de Carchena, 17",
    "sg:city":"Cuellar",
    "sg:orig_category":"Art\u00cdculos De Regalo (al Por Menor)",
    "sg:phone":"+34 921 14 02 16",
    "sg:postcode":"40200",
    "sg:province":"Segovia",
    "wof:name":"Llorente Minguez Maria Del Henar",
    "wof:placetype":"venue"
},
  "geometry": {"coordinates":[-4.3124575615,41.4009895325],"type":"Point"}
}