{
  "type": "Feature",
  "properties": {
    "iso:country":"ES",
    "sg:address":"Calle de Octavio Cuartero, 9",
    "sg:city":"Villarrobledo",
    "sg:orig_category":"Droguer\u00cdas (al Por Menor)",
    "sg:phone":"+34 967 14 55 15",
    "sg:postcode":"02600",
    "sg:province":"Albacete",
    "wof:name":"Pinturas Nieto S.a.",
    "wof:placetype":"venue"
},
  "geometry": {"coordinates":[-2.6068029404,39.2668151855],"type":"Point"}
}