{
  "type": "Feature",
  "properties": {
    "iso:country":"ES",
    "sg:address":"Calle de Arzobispo Maussona, 8",
    "sg:city":"Merida",
    "sg:orig_category":"Animales (al Por Menor)",
    "sg:phone":"+34 924 31 58 51",
    "sg:postcode":"06800",
    "sg:province":"Badajoz",
    "wof:name":"Caba\u00f1as Pe\u00f1a Montserrat",
    "wof:placetype":"venue"
},
  "geometry": {"coordinates":[-6.344520092,38.9195556641],"type":"Point"}
}