{
  "type": "Feature",
  "properties": {
    "addr:full":"Calle de Zabala Bruno Mauricio, 1 Bilbao Vizcaya 48003",
    "addr:housenumber":"1",
    "addr:postcode":"48003",
    "addr:street":"Calle De Zabala Bruno Mauricio",
    "iso:country":"ES",
    "sg:address":"Calle de Zabala Bruno Mauricio, 1",
    "sg:city":"Bilbao",
    "sg:orig_category":"Empresas De Limpieza",
    "sg:phone":"+34 944 16 32 64",
    "sg:postcode":"48003",
    "sg:province":"Vizcaya",
    "wof:name":"Limpiezas Bizman S.l.",
    "wof:placetype":"venue"
},
  "geometry": {"coordinates":[-2.9315779209,43.2568893433],"type":"Point"}
}