{
  "type": "Feature",
  "properties": {
    "iso:country":"ES",
    "sg:address":"Calle de San Ildefonso, 1",
    "sg:city":"Carmona",
    "sg:orig_category":"Ense\u00d1anza, Formaci\u00d3n Profesional: Aprendizaje",
    "sg:phone":"+34 954 14 01 28",
    "sg:postcode":"41410",
    "sg:province":"Sevilla",
    "wof:name":"Ayuntamiento De Carmona-museo De La Ciudad Casa Marques De Las Torres",
    "wof:placetype":"venue"
},
  "geometry": {"coordinates":[-5.6366620064,37.4733276367],"type":"Point"}
}