{
  "type": "Feature",
  "properties": {
    "iso:country":"ES",
    "sg:address":"Calle de Venencia (la), 25",
    "sg:city":"Chiclana De La Frontera",
    "sg:orig_category":"Imprenta",
    "sg:phone":"+34 956 53 60 73",
    "sg:postcode":"11130",
    "sg:province":"C\u00e1diz",
    "wof:name":"Industrias Graficas Olmedo S.l.",
    "wof:placetype":"venue"
},
  "geometry": {"coordinates":[-6.1381750107,36.4236183167],"type":"Point"}
}