{
  "type": "Feature",
  "properties": {
    "iso:country":"ES",
    "sg:address":"Calle de Foncalada, 7",
    "sg:city":"Oviedo",
    "sg:orig_category":"Cl\u00cdnicas Dentales",
    "sg:phone":"+34 985 20 98 21",
    "sg:postcode":"33002",
    "sg:province":"Asturias",
    "wof:name":"Centro Dental Jesus Espias S. L.",
    "wof:placetype":"venue"
},
  "geometry": {"coordinates":[-5.8468332291,43.3648719788],"type":"Point"}
}