{
  "type": "Feature",
  "properties": {
    "addr:full":"Calle de Estacion, 5 Mislata Valencia 46920",
    "addr:housenumber":"5",
    "addr:postcode":"46920",
    "addr:street":"Calle De Estacion",
    "iso:country":"ES",
    "sg:address":"Calle de Estacion, 5",
    "sg:city":"Mislata",
    "sg:orig_category":"Gases Industriales",
    "sg:phone":"+34 963 83 47 17",
    "sg:postcode":"46920",
    "sg:province":"Valencia",
    "wof:name":"Instalaciones Tudela S.l.",
    "wof:placetype":"venue"
},
  "geometry": {"coordinates":[-0.4173209965,39.4745368958],"type":"Point"}
}