{
  "type": "Feature",
  "properties": {
    "addr:full":"C/ Fra Pere Balaguer, 70 Elche Alicante 03202",
    "addr:housenumber":"70",
    "addr:postcode":"03202",
    "addr:street":"C / Fra Pere Balaguer",
    "iso:country":"ES",
    "sg:address":"C/ Fra Pere Balaguer, 70",
    "sg:city":"Elche",
    "sg:orig_category":"Centros Comerciales Y Grandes Tiendas",
    "sg:phone":"+34 965 45 90 57",
    "sg:postcode":"03202",
    "sg:province":"Alicante",
    "wof:name":"Sec 100 S.l. Laboral",
    "wof:placetype":"venue"
},
  "geometry": {"coordinates":[-0.6797590256,38.2708282471],"type":"Point"}
}