{
  "type": "Feature",
  "properties": {
    "addr:full":"Calle de Carmen Viejo, 38 Sanlucar De Barrameda C\u00e1diz 11540",
    "addr:housenumber":"38",
    "addr:postcode":"11540",
    "addr:street":"Calle De Carmen Viejo;Ca\u0301Diz",
    "iso:country":"ES",
    "sg:address":"Calle de Carmen Viejo, 38",
    "sg:city":"Sanlucar De Barrameda",
    "sg:orig_category":"Electricidad: Instaladores",
    "sg:phone":"+34 956 36 98 98",
    "sg:postcode":"11540",
    "sg:province":"C\u00e1diz",
    "wof:name":"Electrificaciones Roca S.l.",
    "wof:placetype":"venue"
},
  "geometry": {"coordinates":[-6.3512220383,36.7779655457],"type":"Point"}
}