{
  "type": "Feature",
  "properties": {
    "iso:country":"ES",
    "sg:address":"Calle de General Mayandia, 4",
    "sg:city":"Zaragoza",
    "sg:orig_category":"Ingeniero",
    "sg:phone":"+34 976 43 41 84",
    "sg:postcode":"50004",
    "sg:province":"Zaragoza",
    "wof:name":"Valero Martin Enar",
    "wof:placetype":"venue"
},
  "geometry": {"coordinates":[-0.8922550082,41.6522750854],"type":"Point"}
}