{
  "type": "Feature",
  "properties": {
    "addr:full":"Calle de Ca\u00d1o, 10 Cordoba C\u00f3rdoba 14001",
    "addr:housenumber":"10",
    "addr:postcode":"14001",
    "addr:street":"Calle De Can\u0303O;Co\u0301Rdoba",
    "iso:country":"ES",
    "sg:address":"Calle de Ca\u00d1o, 10",
    "sg:city":"Cordoba",
    "sg:orig_category":"M\u00c9dicos: Medicina Del Trabajo",
    "sg:phone":"+34 957 48 09 71",
    "sg:postcode":"14001",
    "sg:province":"C\u00f3rdoba",
    "wof:name":"Albadalejo Raez Pedro",
    "wof:placetype":"venue"
},
  "geometry": {"coordinates":[-4.7800869942,37.8881340027],"type":"Point"}
}