{
  "type": "Feature",
  "properties": {
    "addr:full":"Avda Generalisimo, 50 Feira Do Monte Lugo 27377",
    "addr:housenumber":"50",
    "addr:postcode":"27377",
    "addr:street":"Avda Generalisimo",
    "iso:country":"ES",
    "sg:address":"Avda Generalisimo, 50",
    "sg:city":"Feira Do Monte",
    "sg:orig_category":"Bancos",
    "sg:phone":"+34 982 50 57 01",
    "sg:postcode":"27377",
    "sg:province":"Lugo",
    "wof:name":"R Cable Y Telecomunicaciones Galicia S.a.",
    "wof:placetype":"venue"
},
  "geometry": {"coordinates":[-7.5530247688,43.2368125916],"type":"Point"}
}