{
  "type": "Feature",
  "properties": {
    "addr:full":"Ctra Sax, S/n Elda Alicante 03600",
    "addr:housenumber":"s",
    "addr:postcode":"03600",
    "addr:street":"Ctra Sax;/ N",
    "iso:country":"ES",
    "sg:address":"Ctra Sax, S/n",
    "sg:city":"Elda",
    "sg:orig_category":"Art\u00cdculos Funerarios (al Por Menor)",
    "sg:phone":"+34 965 39 98 47",
    "sg:postcode":"03600",
    "sg:province":"Alicante",
    "wof:name":"Tanatorio Elda-petrel S.a.",
    "wof:placetype":"venue"
},
  "geometry": {"coordinates":[-0.8027240038,38.4911804199],"type":"Point"}
}