{
  "type": "Feature",
  "properties": {
    "addr:full":"Catalu\u00f1a(plgno Industrial), S/n Torraos Murcia 30563",
    "addr:housenumber":"/ n",
    "addr:postcode":"30563",
    "addr:street":"Industrial",
    "iso:country":"ES",
    "sg:address":"Catalu\u00f1a(plgno Industrial), S/n",
    "sg:city":"Torraos",
    "sg:orig_category":"Perfumer\u00cda (al Por Menor)",
    "sg:phone":"+34 968 69 24 88",
    "sg:postcode":"30563",
    "sg:province":"Murcia",
    "wof:name":"Fragancias Mais S.l.l.",
    "wof:placetype":"venue"
},
  "geometry": {"coordinates":[-1.2888089418,38.0917434692],"type":"Point"}
}