{
  "type": "Feature",
  "properties": {
    "iso:country":"ES",
    "sg:address":"Plaz Santa Ana, 13",
    "sg:city":"Tarbena",
    "sg:orig_category":"Asesor\u00cda, Estudio Y Control Medioambiental",
    "sg:phone":"+34 965 88 40 66",
    "sg:postcode":"03518",
    "sg:province":"Alicante",
    "wof:name":"Fundacio La Mata De Jonc",
    "wof:placetype":"venue"
},
  "geometry": {"coordinates":[-0.1007189974,38.692691803],"type":"Point"}
}