{
  "type": "Feature",
  "properties": {
    "iso:country":"ES",
    "sg:address":"Avda Francisco Gonzalez Rey, 6",
    "sg:city":"Celanova",
    "sg:orig_category":"Ropa Para Se\u00d1oras Y Caballeros (al Por Menor)",
    "sg:phone":"+34 988 45 17 52",
    "sg:postcode":"32800",
    "sg:province":"Ourense",
    "wof:name":"Codias Perez Isabel",
    "wof:placetype":"venue"
},
  "geometry": {"coordinates":[-7.9560642242,42.1538848877],"type":"Point"}
}