{
  "type": "Feature",
  "properties": {
    "iso:country":"ES",
    "sg:address":"Plaz Redonda, 2",
    "sg:city":"Cartaya",
    "sg:orig_category":"Muebles, Minoristas",
    "sg:phone":"+34 959 39 00 42",
    "sg:postcode":"21450",
    "sg:province":"Huelva",
    "wof:name":"Comercial Palacios S.l.",
    "wof:placetype":"venue"
},
  "geometry": {"coordinates":[-7.154706955,37.282989502],"type":"Point"}
}