{
  "type": "Feature",
  "properties": {
    "addr:full":"Ctra Hellin, Km. 0029,5 Pozohondo Albacete 02141",
    "addr:postcode":"02141",
    "addr:street":"Ctra Hellin Km. 0029,5",
    "iso:country":"ES",
    "sg:address":"Ctra Hellin, Km. 0029,5",
    "sg:city":"Pozohondo",
    "sg:orig_category":"Distribuci\u00d3n De Petr\u00d3leo Y Derivados",
    "sg:phone":"+34 967 20 54 67",
    "sg:postcode":"02141",
    "sg:province":"Albacete",
    "wof:name":"Diaz Mu\u00f1oz S.l.",
    "wof:placetype":"venue"
},
  "geometry": {"coordinates":[-1.9087189436,38.7216567993],"type":"Point"}
}