{
  "type": "Feature",
  "properties": {
    "iso:country":"ES",
    "sg:address":"Carrer de Napols, 18",
    "sg:city":"Mataro",
    "sg:orig_category":"Mercer\u00cda, Lencer\u00cda (al Por Menor)",
    "sg:phone":"+34 937 57 51 77",
    "sg:postcode":"08303",
    "sg:province":"Barcelona",
    "wof:name":"Berrocal Robledo Antonia",
    "wof:placetype":"venue"
},
  "geometry": {"coordinates":[2.4252080917,41.5398979187],"type":"Point"}
}