{
  "type": "Feature",
  "properties": {
    "addr:full":"Afores, 19 Sta. Coloma Farners Girona 17430",
    "addr:housenumber":"19",
    "addr:postcode":"17430",
    "addr:street":"Afores",
    "iso:country":"ES",
    "sg:address":"Afores, 19",
    "sg:city":"Sta. Coloma Farners",
    "sg:orig_category":"Mec\u00c1nico Del Autom\u00d3vil",
    "sg:phone":"+34 972 84 12 80",
    "sg:postcode":"17430",
    "sg:province":"Girona",
    "wof:name":"Bou Pons Salvador",
    "wof:placetype":"venue"
},
  "geometry": {"coordinates":[2.6750700474,41.8570137024],"type":"Point"}
}