{
  "type": "Feature",
  "properties": {
    "addr:full":"Calle de Honduras, 25 Coslada Madrid 28820",
    "addr:housenumber":"25",
    "addr:postcode":"28820",
    "addr:street":"Calle De Honduras",
    "iso:country":"ES",
    "sg:address":"Calle de Honduras, 25",
    "sg:city":"Coslada",
    "sg:orig_category":"Esoterismo",
    "sg:phone":"+34 916 74 21 15",
    "sg:postcode":"28820",
    "sg:province":"Madrid",
    "wof:name":"Diaz Maiquez Julia",
    "wof:placetype":"venue"
},
  "geometry": {"coordinates":[-3.5420229435,40.4241523743],"type":"Point"}
}