{
  "type": "Feature",
  "properties": {
    "addr:full":"Calle de Julio Burell, 95 Linares Ja\u00e9n 23700",
    "addr:housenumber":"95",
    "addr:postcode":"23700",
    "addr:street":"Calle De Julio Burell;Jae\u0301N",
    "iso:country":"ES",
    "sg:address":"Calle de Julio Burell, 95",
    "sg:city":"Linares",
    "sg:orig_category":"Agentes, Concesionarios Y Sucursales De Veh\u00cdculos",
    "sg:phone":"+34 953 65 00 38",
    "sg:postcode":"23700",
    "sg:province":"Ja\u00e9n",
    "wof:name":"Garcia Carmona Jose",
    "wof:placetype":"venue"
},
  "geometry": {"coordinates":[-3.630439043,38.0959892273],"type":"Point"}
}