{
  "type": "Feature",
  "properties": {
    "iso:country":"ES",
    "sg:address":"Ctra Esplugues, 1",
    "sg:city":"Fatjo",
    "sg:orig_category":"Lencer\u00cda Femenina, Corseter\u00cda, Trajes De Ba\u00d1o (al Por Menor)",
    "sg:phone":"+34 933 77 59 65",
    "sg:postcode":"08940",
    "sg:province":"Barcelona",
    "wof:name":"Soto Abad Montserrat",
    "wof:placetype":"venue"
},
  "geometry": {"coordinates":[2.0708940029,41.3559417725],"type":"Point"}
}