{
  "type": "Feature",
  "properties": {
    "addr:full":"Calle de Reyes De Navarra, 3 Vitoria-gasteiz \u00c1lava 01013",
    "addr:housenumber":"3",
    "addr:postcode":"01013",
    "addr:street":"Calle De Reyes De Navarra",
    "iso:country":"ES",
    "sg:address":"Calle de Reyes De Navarra, 3",
    "sg:city":"Vitoria-gasteiz",
    "sg:orig_category":"Institutos De Belleza",
    "sg:phone":"+34 945 28 34 64",
    "sg:postcode":"01013",
    "sg:province":"\u00c1lava",
    "wof:name":"Centro De Belleza Mar",
    "wof:placetype":"venue"
},
  "geometry": {"coordinates":[-2.6696989536,42.8580284119],"type":"Point"}
}