{
  "type": "Feature",
  "properties": {
    "iso:country":"ES",
    "sg:address":"Plaz Santa Ana, 3",
    "sg:city":"Avila",
    "sg:orig_category":"Ingeniero",
    "sg:phone":"+34 920 25 75 37",
    "sg:postcode":"05001",
    "sg:province":"\u00c1vila",
    "wof:name":"Ibarrondo Ortega Luciano",
    "wof:placetype":"venue"
},
  "geometry": {"coordinates":[-4.7072339058,40.6581344604],"type":"Point"}
}