{
  "type": "Feature",
  "properties": {
    "iso:country":"ES",
    "sg:address":"Pl Jacint Verdaguer (d'en), 8",
    "sg:city":"Tarragona",
    "sg:orig_category":"Ropa Para Se\u00d1oras (al Por Menor)",
    "sg:phone":"+34 977 23 61 16",
    "sg:postcode":"43003",
    "sg:province":"Tarragona",
    "wof:name":"Martinez Miralles Teresa",
    "wof:placetype":"venue"
},
  "geometry": {"coordinates":[1.2551369667,41.11510849],"type":"Point"}
}