{
  "type": "Feature",
  "properties": {
    "addr:full":"Calle de Marques De Lema, 11 Alcorisa Teruel 44550",
    "addr:housenumber":"11",
    "addr:postcode":"44550",
    "addr:street":"Calle De Marques De Lema",
    "iso:country":"ES",
    "sg:address":"Calle de Marques De Lema, 11",
    "sg:city":"Alcorisa",
    "sg:orig_category":"Mercer\u00cda, Lencer\u00cda (al Por Menor)",
    "sg:phone":"+34 978 84 03 54",
    "sg:postcode":"44550",
    "sg:province":"Teruel",
    "wof:name":"Espallargas Espallargas Mercedes",
    "wof:placetype":"venue"
},
  "geometry": {"coordinates":[-0.3823609948,40.891330719],"type":"Point"}
}