{
  "type": "Feature",
  "properties": {
    "addr:full":"Ctra Aeropuerto, 1 Matorral Las Palmas 35610",
    "addr:housenumber":"1",
    "addr:postcode":"35610",
    "addr:street":"Ctra Aeropuerto",
    "iso:country":"ES",
    "sg:address":"Ctra Aeropuerto, 1",
    "sg:city":"Matorral",
    "sg:orig_category":"Transportes Internacionales",
    "sg:phone":"+34 928 54 36 71",
    "sg:postcode":"35610",
    "sg:province":"Las Palmas",
    "wof:name":"Transitos De Fuerteventura S.l.",
    "wof:placetype":"venue"
},
  "geometry": {"coordinates":[-13.863199234,28.3980941772],"type":"Point"}
}