{
  "type": "Feature",
  "properties": {
    "iso:country":"ES",
    "sg:address":"Calle de Canonigo, 7",
    "sg:city":"Dos Hermanas",
    "sg:orig_category":"Inmobiliaria (agencias)",
    "sg:phone":"+34 955 67 57 74",
    "sg:postcode":"41700",
    "sg:province":"Sevilla",
    "wof:name":"Tecproan Xxi S.l.",
    "wof:placetype":"venue"
},
  "geometry": {"coordinates":[-5.9235677719,37.2854995728],"type":"Point"}
}