{
  "type": "Feature",
  "properties": {
    "iso:country":"ES",
    "sg:address":"Carr Del Rei En Jaume, 36",
    "sg:city":"Benicarlo",
    "sg:orig_category":"Ropa Para Caballeros (al Por Menor)",
    "sg:phone":"+34 964 47 08 25",
    "sg:postcode":"12580",
    "sg:province":"Castell\u00f3n",
    "wof:name":"Gimeno Navarro Manuel",
    "wof:placetype":"venue"
},
  "geometry": {"coordinates":[0.4042100012,40.4457893372],"type":"Point"}
}