{
  "type": "Feature",
  "properties": {
    "iso:country":"ES",
    "sg:address":"Ctra Zamora, Km. 0336,5",
    "sg:city":"Helmantico",
    "sg:orig_category":"Molduras, Junquillos, Listones Y Molduras Perforadas",
    "sg:phone":"+34 923 25 01 00",
    "sg:postcode":"37184",
    "sg:province":"Salamanca",
    "wof:name":"Garcia Garcia Angel",
    "wof:placetype":"venue"
},
  "geometry": {"coordinates":[-5.6469841003,41.0071716309],"type":"Point"}
}