{
  "type": "Feature",
  "properties": {
    "addr:full":"Ter, S/n Valldoreix Barcelona 08197",
    "addr:housenumber":"s",
    "addr:postcode":"08197",
    "addr:street":"Ter;/ N Valldoreix",
    "iso:country":"ES",
    "sg:address":"Ter, S/n",
    "sg:city":"Valldoreix",
    "sg:orig_category":"Fabricaci\u00d3n De Jabones, Detergentes Y Lej\u00cdas",
    "sg:phone":"+34 935 84 30 01",
    "sg:postcode":"08197",
    "sg:province":"Barcelona",
    "wof:name":"Sallo Solids S.l.",
    "wof:placetype":"venue"
},
  "geometry": {"coordinates":[2.064950943,41.4579811096],"type":"Point"}
}