{
  "type": "Feature",
  "properties": {
    "iso:country":"ES",
    "sg:address":"Calle de San Vicente De Paul, 1",
    "sg:city":"Zaragoza",
    "sg:orig_category":"Asociaciones, Organismos Culturales Y Socioeducativos",
    "sg:phone":"+34 976 29 26 05",
    "sg:postcode":"50001",
    "sg:province":"Zaragoza",
    "wof:name":"Asociacion De Amigos Del Camino De Santiago",
    "wof:placetype":"venue"
},
  "geometry": {"coordinates":[-0.8769448996,41.6510276794],"type":"Point"}
}