{
  "type": "Feature",
  "properties": {
    "addr:full":"Calle de Cerca (la), S/n Gomara Soria 42120",
    "addr:postcode":"42120",
    "addr:street":"Calle De Cerca La S / N Gomara",
    "iso:country":"ES",
    "sg:address":"Calle de Cerca (la), S/n",
    "sg:city":"Gomara",
    "sg:orig_category":"Producci\u00d3n De Abonos Y De Fertilizantes",
    "sg:phone":"+34 975 38 03 00",
    "sg:postcode":"42120",
    "sg:province":"Soria",
    "wof:name":"Feliciano Sanz Lallana S. A.",
    "wof:placetype":"venue"
},
  "geometry": {"coordinates":[-2.226000309,41.6230545044],"type":"Point"}
}