{
  "type": "Feature",
  "properties": {
    "addr:full":"Calle de Invencion (de La), 3 Adaro Madrid 28906",
    "addr:housenumber":"3",
    "addr:postcode":"28906",
    "addr:street":"Calle De Invencion De La",
    "iso:country":"ES",
    "sg:address":"Calle de Invencion (de La), 3",
    "sg:city":"Adaro",
    "sg:orig_category":"Fabricaci\u00d3n De Correas De Transmisi\u00d3n",
    "sg:phone":"+34 916 95 20 12",
    "sg:postcode":"28906",
    "sg:province":"Madrid",
    "sg:website":"www.transmisiones.com",
    "wof:name":"Transmisiones De Potencia S.l.",
    "wof:placetype":"venue"
},
  "geometry": {"coordinates":[-3.7003455162,40.4166908264],"type":"Point"}
}