{
  "type": "Feature",
  "properties": {
    "addr:full":"Av Rei En Jaume, 153 Cardedeu Barcelona 08440",
    "addr:housenumber":"153",
    "addr:postcode":"08440",
    "addr:street":"Av Rei En Jaume",
    "iso:country":"ES",
    "sg:address":"Av Rei En Jaume, 153",
    "sg:city":"Cardedeu",
    "sg:orig_category":"Bibliotecas, Mediatecas",
    "sg:phone":"+34 938 44 40 15",
    "sg:postcode":"08440",
    "sg:province":"Barcelona",
    "wof:name":"Thesaurus Serveis Documentals S.l.",
    "wof:placetype":"venue"
},
  "geometry": {"coordinates":[2.3579499722,41.6369781494],"type":"Point"}
}