{
  "type": "Feature",
  "properties": {
    "addr:full":"Paramillo, S/n Husillos Palencia 34419",
    "addr:housenumber":"/ n",
    "addr:postcode":"34419",
    "addr:street":"Paramillo S",
    "iso:country":"ES",
    "sg:address":"Paramillo, S/n",
    "sg:city":"Husillos",
    "sg:orig_category":"Aparatos, Sistemas De Tele",
    "sg:phone":"+34 979 18 01 88",
    "sg:postcode":"34419",
    "sg:province":"Palencia",
    "wof:name":"Cierres De Seguridad Castilla Jesus Villagra S.l.",
    "wof:placetype":"venue"
},
  "geometry": {"coordinates":[-4.5461001396,42.0964775085],"type":"Point"}
}