{
  "type": "Feature",
  "properties": {
    "addr:full":"Molino, 2 Archivel Murcia 30195",
    "addr:housenumber":"2",
    "addr:postcode":"30195",
    "addr:street":"Molino",
    "iso:country":"ES",
    "sg:address":"Molino, 2",
    "sg:city":"Archivel",
    "sg:orig_category":"Relojer\u00cda (al Por Menor, Reparaci\u00d3n)",
    "sg:phone":"+34 968 72 51 26",
    "sg:postcode":"30195",
    "sg:province":"Murcia",
    "wof:name":"Garcia Martinez Pascual",
    "wof:placetype":"venue"
},
  "geometry": {"coordinates":[-2.0053288937,38.0721092224],"type":"Point"}
}