{
  "type": "Feature",
  "properties": {
    "addr:full":"Carrer de Valencia, 499 Barcelona Barcelona 08013",
    "addr:housenumber":"499",
    "addr:postcode":"08013",
    "addr:street":"Carrer De Valencia",
    "iso:country":"ES",
    "sg:address":"Carrer de Valencia, 499",
    "sg:city":"Barcelona",
    "sg:orig_category":"Alimentaci\u00d3n General (al Por Menor)",
    "sg:phone":"+34 932 45 83 92",
    "sg:postcode":"08013",
    "sg:province":"Barcelona",
    "wof:name":"Colavidas Sanz Macaria",
    "wof:placetype":"venue"
},
  "geometry": {"coordinates":[2.1795339584,41.4050674438],"type":"Point"}
}