{
  "type": "Feature",
  "properties": {
    "addr:full":"C/ Echegaray, 3 Alcoi Alicante 03801",
    "addr:housenumber":"3",
    "addr:postcode":"03801",
    "addr:street":"C / Echegaray",
    "iso:country":"ES",
    "sg:address":"C/ Echegaray, 3",
    "sg:city":"Alcoi",
    "sg:orig_category":"Hilaturas, Hilos Y Actividades Relacionadas",
    "sg:phone":"+34 965 54 50 66",
    "sg:postcode":"03801",
    "sg:province":"Alicante",
    "sg:website":"www.hilaturasjorda.com",
    "wof:name":"Hilaturas Jorda S.l.",
    "wof:placetype":"venue"
},
  "geometry": {"coordinates":[-0.4759219885,38.6926002502],"type":"Point"}
}