{
  "type": "Feature",
  "properties": {
    "iso:country":"ES",
    "sg:address":"Calle de Batalla Del Salado, 12",
    "sg:city":"Tarifa",
    "sg:orig_category":"Juegos Y Juguetes (al Por Menor)",
    "sg:phone":"+34 956 68 05 06",
    "sg:postcode":"11380",
    "sg:province":"C\u00e1diz",
    "wof:name":"Cruz Gil Juana",
    "wof:placetype":"venue"
},
  "geometry": {"coordinates":[-5.605091095,36.0148048401],"type":"Point"}
}