{
  "type": "Feature",
  "properties": {
    "addr:full":"Ctra. B-granada, S/n Cordoba C\u00f3rdoba 14013",
    "addr:housenumber":"s",
    "addr:postcode":"14013",
    "addr:street":"Ctra. B-Granada;/ N;Co\u0301Rdoba",
    "iso:country":"ES",
    "sg:address":"Ctra. B-granada, S/n",
    "sg:city":"Cordoba",
    "sg:orig_category":"Reciclaje, Desguace De Veh\u00cdculos",
    "sg:phone":"+34 957 29 60 25",
    "sg:postcode":"14013",
    "sg:province":"C\u00f3rdoba",
    "wof:name":"Castro Sepulveda Jose",
    "wof:placetype":"venue"
},
  "geometry": {"coordinates":[-4.7730388641,37.8624687195],"type":"Point"}
}