{
  "type": "Feature",
  "properties": {
    "iso:country":"ES",
    "sg:address":"Avda D\u00d1a Soledad Vega Ortiz, 107",
    "sg:city":"Jarandilla Vera",
    "sg:orig_category":"Molduras, Junquillos, Listones Y Molduras Perforadas",
    "sg:phone":"+34 927 56 02 32",
    "sg:postcode":"10450",
    "sg:province":"C\u00e1ceres",
    "wof:name":"Gonzalez Gutierrez Eusebio",
    "wof:placetype":"venue"
},
  "geometry": {"coordinates":[-6.3707604408,39.4761772156],"type":"Point"}
}