{
  "type": "Feature",
  "properties": {
    "addr:full":"Plaz Maior, 15 Cea Ourense 32130",
    "addr:housenumber":"15",
    "addr:postcode":"32130",
    "addr:street":"Plaz Maior",
    "iso:country":"ES",
    "sg:address":"Plaz Maior, 15",
    "sg:city":"Cea",
    "sg:orig_category":"Agentes Generales De Seguros",
    "sg:phone":"+34 988 28 24 64",
    "sg:postcode":"32130",
    "sg:province":"Ourense",
    "wof:name":"Mapfre Servicios De Informatica S.a.",
    "wof:placetype":"venue"
},
  "geometry": {"coordinates":[-7.9847230911,42.4748916626],"type":"Point"}
}