{
  "type": "Feature",
  "properties": {
    "iso:country":"ES",
    "sg:address":"Zona Aeroport, S/n",
    "sg:city":"Prat Llobregat",
    "sg:orig_category":"Cajas De Ahorro",
    "sg:phone":"+34 934 78 09 87",
    "sg:postcode":"08820",
    "sg:province":"Barcelona",
    "wof:name":"Caixa D'estalvis I Pensions De Barcelona",
    "wof:placetype":"venue"
},
  "geometry": {"coordinates":[2.0864720345,41.3289909363],"type":"Point"}
}