{
  "type": "Feature",
  "properties": {
    "iso:country":"ES",
    "sg:address":"Carrer de Bartomeu Rossello, 30",
    "sg:city":"Palma",
    "sg:orig_category":"Alquiler De Veh\u00cdculos: Turismos Y Utilitarios",
    "sg:phone":"+34 971 73 07 20",
    "sg:postcode":"07014",
    "sg:province":"Islas Baleares",
    "wof:name":"Avis Alquile Un Coche S.a.",
    "wof:placetype":"venue"
},
  "geometry": {"coordinates":[2.6302731037,39.5707511902],"type":"Point"}
}