{
  "type": "Feature",
  "properties": {
    "addr:full":"Carr Independencia, 31 Badalona Barcelona 08915",
    "addr:housenumber":"31",
    "addr:postcode":"08915",
    "addr:street":"Carr Independencia",
    "iso:country":"ES",
    "sg:address":"Carr Independencia, 31",
    "sg:city":"Badalona",
    "sg:orig_category":"Loter\u00cda Y T\u00d3mbola",
    "sg:phone":"+34 933 83 86 37",
    "sg:postcode":"08915",
    "sg:province":"Barcelona",
    "wof:name":"Prieto Perez Hortensia",
    "wof:placetype":"venue"
},
  "geometry": {"coordinates":[2.2431070805,41.4553604126],"type":"Point"}
}