{
  "type": "Feature",
  "properties": {
    "addr:full":"Rbla Poblenou, 117 Barcelona Barcelona 08018",
    "addr:housenumber":"117",
    "addr:postcode":"08018",
    "addr:street":"Rbla Poblenou",
    "iso:country":"ES",
    "sg:address":"Rbla Poblenou, 117",
    "sg:city":"Barcelona",
    "sg:orig_category":"Cajas De Ahorro",
    "sg:phone":"+34 934 85 20 02",
    "sg:postcode":"08018",
    "sg:province":"Barcelona",
    "sg:website":"www.caixatarragona.es",
    "wof:name":"Caixa D'estalvis De Tarragona",
    "wof:placetype":"venue"
},
  "geometry": {"coordinates":[2.1971800327,41.4040794373],"type":"Point"}
}