{
  "type": "Feature",
  "properties": {
    "iso:country":"ES",
    "sg:address":"Calle de Avenida De San Juan, S/n",
    "sg:city":"Milagro",
    "sg:orig_category":"Frutas Y Legumbres Frescas (al Por Mayor)",
    "sg:phone":"+34 948 86 10 13",
    "sg:postcode":"31320",
    "sg:province":"Navarra",
    "wof:name":"Frutas Cervera S.a.",
    "wof:placetype":"venue"
},
  "geometry": {"coordinates":[-1.7636181116,42.2325973511],"type":"Point"}
}