{
  "type": "Feature",
  "properties": {
    "addr:full":"Calle de Aviles, 9 Aviles Asturias 33460",
    "addr:housenumber":"9",
    "addr:postcode":"33460",
    "addr:street":"Calle De Aviles",
    "iso:country":"ES",
    "sg:address":"Calle de Aviles, 9",
    "sg:city":"Aviles",
    "sg:orig_category":"Iglesia Cat\u00d3lica",
    "sg:phone":"+34 985 57 04 87",
    "sg:postcode":"33460",
    "sg:province":"Asturias",
    "wof:name":"Diocesis De Oviedo",
    "wof:placetype":"venue"
},
  "geometry": {"coordinates":[-5.9031410217,43.5466804504],"type":"Point"}
}