{
  "type": "Feature",
  "properties": {
    "iso:country":"ES",
    "sg:address":"Calle de Princesa, 94",
    "sg:city":"Madrid",
    "sg:orig_category":"Doctores En Medicina",
    "sg:phone":"+34 915 49 37 19",
    "sg:postcode":"28008",
    "sg:province":"Madrid",
    "wof:name":"Vega De Mingo Luis",
    "wof:placetype":"venue"
},
  "geometry": {"coordinates":[-3.7186980247,40.4343185425],"type":"Point"}
}