{
  "type": "Feature",
  "properties": {
    "iso:country":"ES",
    "sg:address":"Carrer de Roure, 3",
    "sg:city":"Viladecans",
    "sg:orig_category":"Alumbrados",
    "sg:phone":"+34 936 47 03 28",
    "sg:postcode":"08840",
    "sg:province":"Barcelona",
    "wof:name":"Alcainees Iluminacion S.l.",
    "wof:placetype":"venue"
},
  "geometry": {"coordinates":[2.0144135952,41.3234214783],"type":"Point"}
}