{
  "type": "Feature",
  "properties": {
    "iso:country":"ES",
    "sg:address":"Calle de Rio Guadarrama, S/n",
    "sg:city":"Arroyadas",
    "sg:orig_category":"Ferreter\u00cda (diversos)",
    "sg:phone":"+34 918 14 11 43",
    "sg:postcode":"28978",
    "sg:province":"Madrid",
    "wof:name":"Recuperaciones Dermo S.l.",
    "wof:placetype":"venue"
},
  "geometry": {"coordinates":[-3.8251080513,40.2039070129],"type":"Point"}
}