{
  "type": "Feature",
  "properties": {
    "iso:country":"ES",
    "sg:address":"Ctra Pinos Puente (p I Espartero), S/n",
    "sg:city":"Atarfe",
    "sg:orig_category":"Mec\u00c1nico Del Autom\u00d3vil",
    "sg:phone":"+34 958 43 73 11",
    "sg:postcode":"18230",
    "sg:province":"Granada",
    "wof:name":"Fimsego S.a.l.",
    "wof:placetype":"venue"
},
  "geometry": {"coordinates":[-3.7151238918,37.2666282654],"type":"Point"}
}