{
  "type": "Feature",
  "properties": {
    "addr:full":"Carr Santanyi, De, 42 Campos Islas Baleares 07630",
    "addr:housenumber":"42",
    "addr:postcode":"07630",
    "addr:street":"Carr Santanyi De",
    "iso:country":"ES",
    "sg:address":"Carr Santanyi, De, 42",
    "sg:city":"Campos",
    "sg:orig_category":"Promotores Constructores",
    "sg:phone":"+34 971 16 01 01",
    "sg:postcode":"07630",
    "sg:province":"Islas Baleares",
    "wof:name":"Sa Campanera De Inversions S.l.",
    "wof:placetype":"venue"
},
  "geometry": {"coordinates":[3.0197050571,39.430480957],"type":"Point"}
}