{
  "type": "Feature",
  "properties": {
    "iso:country":"ES",
    "sg:address":"Calle de Ciudad De Melilla, 24",
    "sg:city":"Arroyo De La Miel-benalmadena Costa",
    "sg:orig_category":"Inmobiliaria (agencias)",
    "sg:phone":"+34 952 57 55 53",
    "sg:postcode":"29630",
    "sg:province":"M\u00e1laga",
    "wof:name":"Pekka S.l.",
    "wof:placetype":"venue"
},
  "geometry": {"coordinates":[-4.5341486931,36.5965957642],"type":"Point"}
}