{
  "type": "Feature",
  "properties": {
    "iso:country":"ES",
    "sg:address":"Ctra Azuel, Km. 0004,5",
    "sg:city":"Conquista",
    "sg:orig_category":"Cr\u00cda De Animales",
    "sg:phone":"+34 957 33 90 02",
    "sg:postcode":"14448",
    "sg:province":"C\u00f3rdoba",
    "wof:name":"Rodoma S.a.",
    "wof:placetype":"venue"
},
  "geometry": {"coordinates":[-4.5005660057,38.4092674255],"type":"Point"}
}