{
  "type": "Feature",
  "properties": {
    "iso:country":"ES",
    "sg:address":"Carrer de Pelai, 2",
    "sg:city":"Castelldefels",
    "sg:orig_category":"Peleter\u00cdas",
    "sg:phone":"+34 936 65 67 55",
    "sg:postcode":"08860",
    "sg:province":"Barcelona",
    "wof:name":"Cotelo Martin S.l.",
    "wof:placetype":"venue"
},
  "geometry": {"coordinates":[1.9770809412,41.2863540649],"type":"Point"}
}