{
  "type": "Feature",
  "properties": {
    "iso:country":"ES",
    "sg:address":"Calle de Doctor Gil Y Morte, 14",
    "sg:city":"Valencia",
    "sg:orig_category":"Negocio De Materiales De Construcci\u00d3n",
    "sg:phone":"+34 963 80 68 30",
    "sg:postcode":"46007",
    "sg:province":"Valencia",
    "sg:website":"www.euromac2.com",
    "wof:name":"Eurostyrene",
    "wof:placetype":"venue"
},
  "geometry": {"coordinates":[-0.3806118071,39.4622497559],"type":"Point"}
}