{
  "type": "Feature",
  "properties": {
    "iso:country":"ES",
    "sg:address":"Pase San Francisco De Sales, 32",
    "sg:city":"Madrid",
    "sg:orig_category":"Agencias Y Agentes Comerciales, Representantes",
    "sg:phone":"+34 915 54 92 31",
    "sg:postcode":"28003",
    "sg:province":"Madrid",
    "wof:name":"Anton Rodrigalvarez Luis Miguel",
    "wof:placetype":"venue"
},
  "geometry": {"coordinates":[-3.9667513371,40.4892883301],"type":"Point"}
}