{
  "type": "Feature",
  "properties": {
    "addr:full":"Calle de Galicia, 29 Madrid Madrid 28024",
    "addr:housenumber":"29",
    "addr:postcode":"madrid;28024",
    "addr:street":"Calle De Galicia",
    "iso:country":"ES",
    "sg:address":"Calle de Galicia, 29",
    "sg:city":"Madrid",
    "sg:orig_category":"Agencias Y Agentes Comerciales, Representantes",
    "sg:phone":"+34 917 11 52 96",
    "sg:postcode":"28024",
    "sg:province":"Madrid",
    "wof:name":"Jimenez Perez Carlos",
    "wof:placetype":"venue"
},
  "geometry": {"coordinates":[-3.7726290226,40.3983612061],"type":"Point"}
}