{
  "type": "Feature",
  "properties": {
    "iso:country":"ES",
    "sg:address":"Avda Peris Y Valero, 130",
    "sg:city":"Valencia",
    "sg:orig_category":"Agentes, Concesionarios Y Sucursales De Veh\u00cdculos",
    "sg:phone":"+34 963 33 32 75",
    "sg:postcode":"46006",
    "sg:province":"Valencia",
    "wof:name":"Talleres Jofran S.l.",
    "wof:placetype":"venue"
},
  "geometry": {"coordinates":[-0.3676590025,39.4601669312],"type":"Point"}
}