{
  "type": "Feature",
  "properties": {
    "addr:full":"Calle de Molares, 26 Utrera Sevilla 41710",
    "addr:housenumber":"26",
    "addr:postcode":"41710",
    "addr:street":"Calle De Molares",
    "iso:country":"ES",
    "sg:address":"Calle de Molares, 26",
    "sg:city":"Utrera",
    "sg:orig_category":"Peluquer\u00cdas, Peluquer\u00cda Mixta",
    "sg:phone":"+34 954 86 20 01",
    "sg:postcode":"41710",
    "sg:province":"Sevilla",
    "wof:name":"Dana Pacheco Juan Carlos",
    "wof:placetype":"venue"
},
  "geometry": {"coordinates":[-5.7751231194,37.1787490845],"type":"Point"}
}