{
  "type": "Feature",
  "properties": {
    "iso:country":"ES",
    "sg:address":"Ctra Huesca, Km. 0024,1",
    "sg:city":"Estacion Portazgo",
    "sg:orig_category":"Cerrajer\u00cda, Ferrallista",
    "sg:phone":"+34 976 69 01 73",
    "sg:postcode":"50800",
    "sg:province":"Zaragoza",
    "wof:name":"Metalicas Hds S.l.",
    "wof:placetype":"venue"
},
  "geometry": {"coordinates":[-0.7865840197,41.867225647],"type":"Point"}
}