{
  "type": "Feature",
  "properties": {
    "iso:country":"ES",
    "sg:address":"Calle de Serrano, 207",
    "sg:city":"Madrid",
    "sg:orig_category":"Dibujantes (diversos)",
    "sg:phone":"+34 913 44 13 08",
    "sg:postcode":"28016",
    "sg:province":"Madrid",
    "sg:website":"www.zegma.com",
    "wof:name":"Zegma Imagen S.l",
    "wof:placetype":"venue"
},
  "geometry": {"coordinates":[-3.6798813343,40.4533843994],"type":"Point"}
}