{
  "type": "Feature",
  "properties": {
    "addr:full":"Calle de Cemento, 5 Torrejon Ardoz Madrid 28850",
    "addr:housenumber":"5",
    "addr:postcode":"28850",
    "addr:street":"Calle De Cemento",
    "iso:country":"ES",
    "sg:address":"Calle de Cemento, 5",
    "sg:city":"Torrejon Ardoz",
    "sg:orig_category":"Aparatos De Medida, Control, Regulaci\u00d3n Y Detecci\u00d3n",
    "sg:phone":"+34 916 76 63 63",
    "sg:postcode":"28850",
    "sg:province":"Madrid",
    "wof:name":"Aplicaciones Tecnicas Y Control S.a.",
    "wof:placetype":"venue"
},
  "geometry": {"coordinates":[-3.4699130058,40.4522285461],"type":"Point"}
}