{
  "type": "Feature",
  "properties": {
    "iso:country":"ES",
    "sg:address":"Calle de Buenavista, 23",
    "sg:city":"Recas",
    "sg:orig_category":"Muebles, Minoristas",
    "sg:phone":"+34 925 54 70 04",
    "sg:postcode":"45211",
    "sg:province":"Toledo",
    "wof:name":"Diaz Caba\u00f1as Antonio",
    "wof:placetype":"venue"
},
  "geometry": {"coordinates":[-3.9886937141,40.051109314],"type":"Point"}
}