{
  "type": "Feature",
  "properties": {
    "iso:country":"ES",
    "sg:address":"Calle de Mayor, 13",
    "sg:city":"Ca\u00f1ada",
    "sg:orig_category":"Molduras, Junquillos, Listones Y Molduras Perforadas",
    "sg:phone":"+34 920 27 21 13",
    "sg:postcode":"05294",
    "sg:province":"\u00c1vila",
    "wof:name":"Blazquez Pozo Maria De Los Angeles",
    "wof:placetype":"venue"
},
  "geometry": {"coordinates":[-4.4955759048,40.5995140076],"type":"Point"}
}