{
  "type": "Feature",
  "properties": {
    "iso:country":"ES",
    "sg:address":"Av Vives Llull, S/n",
    "sg:city":"Mao",
    "sg:orig_category":"Iglesia Cat\u00d3lica",
    "sg:phone":"+34 971 35 06 36",
    "sg:postcode":"07703",
    "sg:province":"Islas Baleares",
    "wof:name":"Parroquia Sant Antoni Abat",
    "wof:placetype":"venue"
},
  "geometry": {"coordinates":[4.2561497688,39.8851585388],"type":"Point"}
}