{
  "type": "Feature",
  "properties": {
    "addr:full":"Carrer de Sicilia, 28 Santa Coloma De Gramenet Barcelona 08922",
    "addr:housenumber":"28",
    "addr:postcode":"08922",
    "addr:street":"Carrer De Sicilia",
    "iso:country":"ES",
    "sg:address":"Carrer de Sicilia, 28",
    "sg:city":"Santa Coloma De Gramenet",
    "sg:orig_category":"Cajas De Ahorro",
    "sg:phone":"+34 934 68 22 43",
    "sg:postcode":"08922",
    "sg:province":"Barcelona",
    "sg:website":"www.caixapenedes.es",
    "wof:name":"Caixa D'estalvis Del Penedes",
    "wof:placetype":"venue"
},
  "geometry": {"coordinates":[2.2174499035,41.4530792236],"type":"Point"}
}