{
  "type": "Feature",
  "properties": {
    "iso:country":"ES",
    "sg:address":"Ctra Matadepera, 222",
    "sg:city":"Terrassa",
    "sg:orig_category":"Ayuda En Tareas Dom\u00c9sticas, Ayuda A Domicilio",
    "sg:phone":"+34 937 35 27 33",
    "sg:postcode":"08226",
    "sg:province":"Barcelona",
    "wof:name":"Picarol Terrassa S.l.",
    "wof:placetype":"venue"
},
  "geometry": {"coordinates":[2.0179789066,41.5781326294],"type":"Point"}
}