{
  "type": "Feature",
  "properties": {
    "iso:country":"ES",
    "sg:address":"Carrer de Irineu (l'), 27",
    "sg:city":"Terrassa",
    "sg:orig_category":"Fotocopias, Reprograf\u00cda",
    "sg:phone":"+34 937 80 59 10",
    "sg:postcode":"08224",
    "sg:province":"Barcelona",
    "wof:name":"Manualitats Nova S.l.",
    "wof:placetype":"venue"
},
  "geometry": {"coordinates":[2.0066189766,41.562374115],"type":"Point"}
}