{
  "type": "Feature",
  "properties": {
    "iso:country":"ES",
    "sg:address":"Rua Capitan Eloy, 26",
    "sg:city":"Ourense",
    "sg:orig_category":"Informaci\u00d3n Financiera Y Comercial",
    "sg:phone":"+34 988 23 54 51",
    "sg:postcode":"32003",
    "sg:province":"Ourense",
    "sg:website":"www.atrioabad.com",
    "wof:name":"Atrio Abad Emilio",
    "wof:placetype":"venue"
},
  "geometry": {"coordinates":[-7.8646383286,42.3392410278],"type":"Point"}
}