{
  "type": "Feature",
  "properties": {
    "iso:country":"ES",
    "sg:address":"Calle de Marruecos, 2",
    "sg:city":"Cordoba",
    "sg:orig_category":"Farmacias",
    "sg:phone":"+34 957 23 23 30",
    "sg:postcode":"14004",
    "sg:province":"C\u00f3rdoba",
    "wof:name":"Echevarria Marquez Pilar",
    "wof:placetype":"venue"
},
  "geometry": {"coordinates":[-4.7889990807,37.8824043274],"type":"Point"}
}