{
  "type": "Feature",
  "properties": {
    "iso:country":"ES",
    "sg:address":"Avda Valladolid, 1",
    "sg:city":"Tordesillas",
    "sg:orig_category":"Laboratorios Y Trabajos De Fotograf\u00cda, V\u00cddeo Y Cine",
    "sg:phone":"+34 983 77 11 61",
    "sg:postcode":"47100",
    "sg:province":"Valladolid",
    "wof:name":"Juarez Vegas Jose Luis",
    "wof:placetype":"venue"
},
  "geometry": {"coordinates":[-4.9884839058,41.5042915344],"type":"Point"}
}