{
  "type": "Feature",
  "properties": {
    "iso:country":"ES",
    "sg:address":"Pol Ind Urbayecla, S/n",
    "sg:city":"Yecla",
    "sg:orig_category":"Plomeros",
    "sg:phone":"+34 968 79 35 12",
    "sg:postcode":"30510",
    "sg:province":"Murcia",
    "wof:name":"Calfrica S.l.",
    "wof:placetype":"venue"
},
  "geometry": {"coordinates":[-1.1149940491,38.6145591736],"type":"Point"}
}