{
  "type": "Feature",
  "properties": {
    "addr:full":"Calle de Tristana, 57 S. Pedro Martir Ii Las Palmas 35110",
    "addr:housenumber":"57",
    "addr:postcode":"35110",
    "addr:street":"Calle De Tristana",
    "iso:country":"ES",
    "sg:address":"Calle de Tristana, 57",
    "sg:city":"S. Pedro Martir Ii",
    "sg:orig_category":"Peluqueros: De Se\u00d1oras",
    "sg:phone":"+34 928 75 30 69",
    "sg:postcode":"35110",
    "sg:province":"Las Palmas",
    "wof:name":"Mayor Rivero Erica",
    "wof:placetype":"venue"
},
  "geometry": {"coordinates":[-15.4485340118,27.8392906189],"type":"Point"}
}