{
  "type": "Feature",
  "properties": {
    "iso:country":"ES",
    "sg:address":"Ctra. Antilla, Km. 0001,7",
    "sg:city":"Lepe",
    "sg:orig_category":"Distribuci\u00d3n De Petr\u00d3leo Y Derivados",
    "sg:phone":"+34 959 38 21 02",
    "sg:postcode":"21440",
    "sg:province":"Huelva",
    "wof:name":"Valdesequillo S.l.",
    "wof:placetype":"venue"
},
  "geometry": {"coordinates":[-7.2029190063,37.255241394],"type":"Point"}
}