{
  "type": "Feature",
  "properties": {
    "addr:full":"Carrer de L'estadella, 73 Barcelona Barcelona 08030",
    "addr:housenumber":"73",
    "addr:postcode":"08030",
    "addr:street":"Carrer De L'Estadella",
    "iso:country":"ES",
    "sg:address":"Carrer de L'estadella, 73",
    "sg:city":"Barcelona",
    "sg:orig_category":"Perfumer\u00cda (al Por Menor)",
    "sg:phone":"+34 933 05 05 37",
    "sg:postcode":"08030",
    "sg:province":"Barcelona",
    "wof:name":"Serveis De Distribucio De Catalunya S. A.",
    "wof:placetype":"venue"
},
  "geometry": {"coordinates":[2.2053956985,41.4354667664],"type":"Point"}
}