{
  "type": "Feature",
  "properties": {
    "addr:full":"Calle de San Sebastian (de), 7 Boadilla Del Monte Madrid 28660",
    "addr:postcode":"28660",
    "addr:street":"Calle De",
    "iso:country":"ES",
    "sg:address":"Calle de San Sebastian (de), 7",
    "sg:city":"Boadilla Del Monte",
    "sg:orig_category":"Carnicer\u00cdas, Carnicer\u00cdas",
    "sg:phone":"+34 916 33 25 23",
    "sg:postcode":"28660",
    "sg:province":"Madrid",
    "wof:name":"Multicarne S. L.",
    "wof:placetype":"venue"
},
  "geometry": {"coordinates":[-3.8775029182,40.4062538147],"type":"Point"}
}