{
  "type": "Feature",
  "properties": {
    "iso:country":"ES",
    "sg:address":"Ctra Arevalo, S/n",
    "sg:city":"Arroyo Cuellar",
    "sg:orig_category":"Cr\u00cda De Animales",
    "sg:phone":"+34 921 12 30 40",
    "sg:postcode":"40215",
    "sg:province":"Segovia",
    "wof:name":"Granja La Corredera S.l.",
    "wof:placetype":"venue"
},
  "geometry": {"coordinates":[-4.371799469,41.3332862854],"type":"Point"}
}