{
  "type": "Feature",
  "properties": {
    "iso:country":"ES",
    "sg:address":"Carrer de Jacint Verdaguer, 8",
    "sg:city":"Hospitalet Llobregat",
    "sg:classifiers":[
        {
            "category":"Casinos & Gambling",
            "type":"Entertainment"
        }
    ],
    "sg:phone":"+34 933 31 36 28",
    "sg:postcode":"08902",
    "sg:province":"Barcelona",
    "sg:tags":[
        "locale",
        "de",
        "juego"
    ],
    "wof:name":"Casino De Santa Eulalia",
    "wof:placetype":"venue"
},
  "geometry": {"coordinates":[2.1276900768,41.3666954041],"type":"Point"}
}