{
  "type": "Feature",
  "properties": {
    "addr:full":"Calle de Javier Sanz, 9 Almeria Almer\u00eda 04004",
    "addr:housenumber":"9",
    "addr:postcode":"04004",
    "addr:street":"Calle De Javier Sanz",
    "iso:country":"ES",
    "sg:address":"Calle de Javier Sanz, 9",
    "sg:city":"Almeria",
    "sg:orig_category":"Agencias Y Agentes Comerciales, Representantes",
    "sg:phone":"+34 950 23 65 89",
    "sg:postcode":"04004",
    "sg:province":"Almer\u00eda",
    "wof:name":"Miras Monedero Juan",
    "wof:placetype":"venue"
},
  "geometry": {"coordinates":[-2.4610939026,36.8387794495],"type":"Point"}
}