{
  "type": "Feature",
  "properties": {
    "addr:full":"Calle de Sol, 62 Plasencia C\u00e1ceres 10600",
    "addr:housenumber":"62",
    "addr:postcode":"10600",
    "addr:street":"Calle De Sol;Ca\u0301Ceres",
    "iso:country":"ES",
    "sg:address":"Calle de Sol, 62",
    "sg:city":"Plasencia",
    "sg:orig_category":"Zapatos (al Por Menor)",
    "sg:phone":"+34 927 42 57 96",
    "sg:postcode":"10600",
    "sg:province":"C\u00e1ceres",
    "sg:website":"www.calzadosalcon.com",
    "wof:name":"Alcon Fuentes Juan Jose",
    "wof:placetype":"venue"
},
  "geometry": {"coordinates":[-6.0873260498,40.0304832458],"type":"Point"}
}