{
  "type": "Feature",
  "properties": {
    "iso:country":"ES",
    "sg:address":"Calle de Humanista Mariner, 14",
    "sg:city":"Valencia",
    "sg:orig_category":"Lavado, Limpieza De Veh\u00cdculos",
    "sg:phone":"+34 963 57 16 24",
    "sg:postcode":"46018",
    "sg:province":"Valencia",
    "wof:name":"Lavadero La Estrella S.l",
    "wof:placetype":"venue"
},
  "geometry": {"coordinates":[-0.3933579922,39.4609451294],"type":"Point"}
}