{
  "type": "Feature",
  "properties": {
    "iso:country":"ES",
    "sg:address":"Calle de La Economia, 7",
    "sg:city":"Barakaldo",
    "sg:classifiers":[
        {
            "category":"Personal",
            "subcategory":"Barber",
            "type":"Services"
        }
    ],
    "sg:phone":"+34 944 90 19 14",
    "sg:postcode":"48902",
    "sg:province":"Vizcaya",
    "sg:tags":[
        "caballeros",
        "de",
        "peluqueros"
    ],
    "wof:name":"Jose Luis Bergado Perez (peluqueria Bergado)",
    "wof:placetype":"venue"
},
  "geometry": {"coordinates":[-2.9920427799,43.2929115295],"type":"Point"}
}