{
  "type": "Feature",
  "properties": {
    "iso:country":"ES",
    "sg:address":"Calle de Fuenfria, 29",
    "sg:city":"Navalcarnero",
    "sg:orig_category":"Inform\u00c1tica: Consultores",
    "sg:phone":"+34 918 10 12 16",
    "sg:postcode":"28600",
    "sg:province":"Madrid",
    "wof:name":"Business Information Tecnology Systems S.l",
    "wof:placetype":"venue"
},
  "geometry": {"coordinates":[-4.0172829628,40.2946472168],"type":"Point"}
}