{
  "type": "Feature",
  "properties": {
    "iso:country":"ES",
    "sg:address":"Carrer de Vint-i-set, 16",
    "sg:city":"Camarles",
    "sg:orig_category":"Mec\u00c1nico Del Autom\u00d3vil",
    "sg:phone":"+34 977 47 09 51",
    "sg:postcode":"43894",
    "sg:province":"Tarragona",
    "wof:name":"Rius Mauri Francisco Javier",
    "wof:placetype":"venue"
},
  "geometry": {"coordinates":[0.6728150249,40.7718238831],"type":"Point"}
}