{
  "type": "Feature",
  "properties": {
    "addr:full":"Ctra Porzuna (c), S/n Casas Ciudad Real 13196",
    "addr:housenumber":"/ n",
    "addr:postcode":"13196",
    "addr:street":"Ctra Porzuna C S",
    "iso:country":"ES",
    "sg:address":"Ctra Porzuna (c), S/n",
    "sg:city":"Casas",
    "sg:orig_category":"Imprenta",
    "sg:phone":"+34 926 23 09 01",
    "sg:postcode":"13196",
    "sg:province":"Ciudad Real",
    "wof:name":"Graficas Garrido S.l.",
    "wof:placetype":"venue"
},
  "geometry": {"coordinates":[-3.9856359959,39.0307540894],"type":"Point"}
}