{
  "type": "Feature",
  "properties": {
    "iso:country":"ES",
    "sg:address":"Calle de Real De Arriba, 105",
    "sg:city":"Valverde Camino",
    "sg:orig_category":"Confecci\u00d3n De Zapatos",
    "sg:phone":"+34 959 55 03 13",
    "sg:postcode":"21600",
    "sg:province":"Huelva",
    "sg:website":"www.calzadoslabor.com",
    "wof:name":"Lazo Padilla Pedro",
    "wof:placetype":"venue"
},
  "geometry": {"coordinates":[-6.7524166107,37.5770454407],"type":"Point"}
}