{
  "type": "Feature",
  "properties": {
    "addr:full":"Calle de Carreteria, 38 Malaga M\u00e1laga 29008",
    "addr:housenumber":"38",
    "addr:postcode":"29008",
    "addr:street":"Calle De Carreteria;Ma\u0301Laga",
    "iso:country":"ES",
    "sg:address":"Calle de Carreteria, 38",
    "sg:city":"Malaga",
    "sg:orig_category":"Fabricaci\u00d3n De Peines Y De Accesorios De Peluquer\u00cda",
    "sg:phone":"+34 952 21 03 49",
    "sg:postcode":"29008",
    "sg:province":"M\u00e1laga",
    "wof:name":"Ireyo S. L.",
    "wof:placetype":"venue"
},
  "geometry": {"coordinates":[-4.4242472649,36.722694397],"type":"Point"}
}