{
  "type": "Feature",
  "properties": {
    "iso:country":"ES",
    "sg:address":"Calle de Jorge Manrique, 1",
    "sg:city":"Soria",
    "sg:orig_category":"Iglesias Evang\u00c9licas",
    "sg:phone":"+34 975 22 56 58",
    "sg:postcode":"42003",
    "sg:province":"Soria",
    "wof:name":"Iglesia Evangelica-asamblea Cristiana Biblica",
    "wof:placetype":"venue"
},
  "geometry": {"coordinates":[-2.4671208858,41.7610321045],"type":"Point"}
}