{
  "type": "Feature",
  "properties": {
    "addr:full":"Cmn H Tejedores, S/n Albacete Albacete 02006",
    "addr:housenumber":"s / n",
    "addr:postcode":"02006",
    "addr:street":"Cmn;Tejedores",
    "iso:country":"ES",
    "sg:address":"Cmn H Tejedores, S/n",
    "sg:city":"Albacete",
    "sg:orig_category":"Importaci\u00d3n",
    "sg:phone":"+34 967 22 45 66",
    "sg:postcode":"02006",
    "sg:province":"Albacete",
    "wof:name":"Cebrian S.l.",
    "wof:placetype":"venue"
},
  "geometry": {"coordinates":[-1.8702989817,39.0050697327],"type":"Point"}
}