{
  "type": "Feature",
  "properties": {
    "iso:country":"ES",
    "sg:address":"Pl Mercat, 13",
    "sg:city":"Pego",
    "sg:orig_category":"Grafistas",
    "sg:phone":"+34 966 40 09 87",
    "sg:postcode":"03780",
    "sg:province":"Alicante",
    "wof:name":"Buenaletra S.l.",
    "wof:placetype":"venue"
},
  "geometry": {"coordinates":[-0.1160589978,38.8413581848],"type":"Point"}
}