{
  "type": "Feature",
  "properties": {
    "iso:country":"ES",
    "sg:address":"Calle de Torres Quevedo (de), 1",
    "sg:city":"Tres Cantos",
    "sg:orig_category":"Inform\u00c1tica (estudios, Servicios, Asesor\u00cda, Formaci\u00d3n)",
    "sg:phone":"+34 918 04 12 34",
    "sg:postcode":"28760",
    "sg:province":"Madrid",
    "sg:website":"www.paginasamarillas.es",
    "wof:name":"Suministros Sistemas Y Redes S.a",
    "wof:placetype":"venue"
},
  "geometry": {"coordinates":[-3.7066390514,40.59400177],"type":"Point"}
}