{
  "type": "Feature",
  "properties": {
    "iso:country":"ES",
    "sg:address":"Plaz Siete Villas (de Las), 1",
    "sg:city":"Pedroche",
    "sg:orig_category":"Administraciones Regionales, Departamentales Y Locales",
    "sg:phone":"+34 957 13 73 02",
    "sg:postcode":"14412",
    "sg:province":"C\u00f3rdoba",
    "wof:name":"Ayuntamiento",
    "wof:placetype":"venue"
},
  "geometry": {"coordinates":[-4.762389183,38.429359436],"type":"Point"}
}