{
  "type": "Feature",
  "properties": {
    "iso:country":"ES",
    "sg:address":"Calle de Ancha, 111",
    "sg:city":"Aguilar De La Frontera",
    "sg:orig_category":"Cer\u00c1micas: Material Y Suministros",
    "sg:phone":"+34 957 68 86 53",
    "sg:postcode":"14920",
    "sg:province":"C\u00f3rdoba",
    "wof:name":"Navarro Barranco Francisco",
    "wof:placetype":"venue"
},
  "geometry": {"coordinates":[-4.660926342,37.5084266663],"type":"Point"}
}