{
  "type": "Feature",
  "properties": {
    "addr:full":"Avda Federico Garcia Lorca, 161 Almeria Almer\u00eda 04008",
    "addr:housenumber":"161",
    "addr:postcode":"04008",
    "addr:street":"Avda Federico Garcia Lorca",
    "iso:country":"ES",
    "sg:address":"Avda Federico Garcia Lorca, 161",
    "sg:city":"Almeria",
    "sg:orig_category":"Electricidad Veh\u00cdculo",
    "sg:phone":"+34 950 23 20 48",
    "sg:postcode":"04008",
    "sg:province":"Almer\u00eda",
    "wof:name":"Electrica Usero S.l.",
    "wof:placetype":"venue"
},
  "geometry": {"coordinates":[-2.4589591026,36.8453445435],"type":"Point"}
}