{
  "type": "Feature",
  "properties": {
    "iso:country":"ES",
    "sg:address":"Calle de Alzola Pablo De, 22",
    "sg:city":"Bilbao",
    "sg:orig_category":"Delegados, Agentes De Tr\u00c1nsito, Auxiliares De Transporte Internacional",
    "sg:phone":"+34 944 27 76 89",
    "sg:postcode":"48012",
    "sg:province":"Vizcaya",
    "wof:name":"Bidezerun S.l.",
    "wof:placetype":"venue"
},
  "geometry": {"coordinates":[-2.9457960129,43.2557601929],"type":"Point"}
}