{
  "type": "Feature",
  "properties": {
    "iso:country":"ES",
    "sg:address":"Avda Justina Y Berdia, S/n",
    "sg:city":"Saron",
    "sg:orig_category":"Electrodom\u00c9sticos (al Por Menor)",
    "sg:phone":"+34 942 56 30 86",
    "sg:postcode":"39620",
    "sg:province":"Cantabria",
    "wof:name":"Chiqui Saron S. A.",
    "wof:placetype":"venue"
},
  "geometry": {"coordinates":[-3.84947896,43.3271064758],"type":"Point"}
}