{
  "type": "Feature",
  "properties": {
    "addr:full":"Avda Espa\u00d1a, 17 Caceres C\u00e1ceres 10002",
    "addr:housenumber":"17",
    "addr:postcode":"10002",
    "addr:street":"Avda Espan\u0303A;Ca\u0301Ceres",
    "iso:country":"ES",
    "sg:address":"Avda Espa\u00d1a, 17",
    "sg:city":"Caceres",
    "sg:orig_category":"Peleter\u00cdas",
    "sg:phone":"+34 927 24 23 80",
    "sg:postcode":"10002",
    "sg:province":"C\u00e1ceres",
    "wof:name":"Alviz Chanca Jesus Manuel",
    "wof:placetype":"venue"
},
  "geometry": {"coordinates":[-6.3774285316,39.4707984924],"type":"Point"}
}