{
  "type": "Feature",
  "properties": {
    "iso:country":"ES",
    "sg:address":"Avda Abelardo Algora, 20",
    "sg:city":"Pedrola",
    "sg:orig_category":"Empresas De Pintura Y Revestimientos",
    "sg:phone":"+34 976 61 52 84",
    "sg:postcode":"50690",
    "sg:province":"Zaragoza",
    "wof:name":"Ruiz Perez Angel",
    "wof:placetype":"venue"
},
  "geometry": {"coordinates":[-1.2197259665,41.7869682312],"type":"Point"}
}