{
  "type": "Feature",
  "properties": {
    "addr:full":"Calle de Ronda, 4 Donostia-san Sebastian Guip\u00f9zcoa 20001",
    "addr:housenumber":"4",
    "addr:postcode":"20001",
    "addr:street":"Calle De Ronda",
    "iso:country":"ES",
    "sg:address":"Calle de Ronda, 4",
    "sg:city":"Donostia-san Sebastian",
    "sg:orig_category":"Molduras, Junquillos, Listones Y Molduras Perforadas",
    "sg:phone":"+34 943 29 37 63",
    "sg:postcode":"20001",
    "sg:province":"Guip\u00f9zcoa",
    "wof:name":"Perez Sanchez Jose Maria",
    "wof:placetype":"venue"
},
  "geometry": {"coordinates":[-1.9763879776,43.3219947815],"type":"Point"}
}