{
  "type": "Feature",
  "properties": {
    "iso:country":"ES",
    "sg:address":"Carr Mar, 9",
    "sg:city":"Badalona",
    "sg:orig_category":"Agencias De Viajes",
    "sg:phone":"+34 933 89 47 08",
    "sg:postcode":"08911",
    "sg:province":"Barcelona",
    "sg:website":"www.barcino.com",
    "wof:name":"Viajes Barcino S. A.",
    "wof:placetype":"venue"
},
  "geometry": {"coordinates":[2.2450649738,41.4503440857],"type":"Point"}
}