{
  "type": "Feature",
  "properties": {
    "iso:country":"ES",
    "sg:address":"Carrer de Toledo, 2",
    "sg:city":"Barcelona",
    "sg:orig_category":"Mec\u00c1nico Del Autom\u00d3vil",
    "sg:phone":"+34 933 31 09 97",
    "sg:postcode":"08014",
    "sg:province":"Barcelona",
    "wof:name":"Llopart Fons Antonio",
    "wof:placetype":"venue"
},
  "geometry": {"coordinates":[2.1356201172,41.3698768616],"type":"Point"}
}