{
  "type": "Feature",
  "properties": {
    "addr:full":"Carrer de Cesar, 1 Can Pastilla Islas Baleares 07610",
    "addr:housenumber":"1",
    "addr:postcode":"07610",
    "addr:street":"Carrer De Cesar",
    "iso:country":"ES",
    "sg:address":"Carrer de Cesar, 1",
    "sg:city":"Can Pastilla",
    "sg:orig_category":"Librer\u00cdas",
    "sg:phone":"+34 971 49 25 02",
    "sg:postcode":"07610",
    "sg:province":"Islas Baleares",
    "wof:name":"Gough  Darren",
    "wof:placetype":"venue"
},
  "geometry": {"coordinates":[2.7181870937,39.5355300903],"type":"Point"}
}