{
  "type": "Feature",
  "properties": {
    "iso:country":"ES",
    "sg:address":"Calle de Santa Gema, 61",
    "sg:city":"S. Adrian",
    "sg:orig_category":"Productores Recolectores, Venta Directa De Vinos",
    "sg:phone":"+34 948 67 00 55",
    "sg:postcode":"31570",
    "sg:province":"Navarra",
    "wof:name":"Bodega Cooperativa San Adrian",
    "wof:placetype":"venue"
},
  "geometry": {"coordinates":[-1.9368699789,42.3363838196],"type":"Point"}
}