{
  "type": "Feature",
  "properties": {
    "iso:country":"ES",
    "sg:address":"Calle de Cartuja (la), 4",
    "sg:city":"Ecija",
    "sg:orig_category":"Supermercados Y Hipermercados",
    "sg:phone":"+34 954 83 40 54",
    "sg:postcode":"41400",
    "sg:province":"Sevilla",
    "wof:name":"Prieto Garcia Francisco",
    "wof:placetype":"venue"
},
  "geometry": {"coordinates":[-5.0784482956,37.5452003479],"type":"Point"}
}