{
  "type": "Feature",
  "properties": {
    "addr:full":"Calle de Infanta Mercedes, 98 Madrid Madrid 28020",
    "addr:housenumber":"98",
    "addr:postcode":"madrid;28020",
    "addr:street":"Calle De Infanta Mercedes",
    "iso:country":"ES",
    "sg:address":"Calle de Infanta Mercedes, 98",
    "sg:city":"Madrid",
    "sg:orig_category":"Peluquer\u00cdas, Peluquer\u00cda Mixta",
    "sg:phone":"+34 915 79 25 29",
    "sg:postcode":"28020",
    "sg:province":"Madrid",
    "wof:name":"Perfil Peluqueria S.a.",
    "wof:placetype":"venue"
},
  "geometry": {"coordinates":[-3.6929376125,40.4641304016],"type":"Point"}
}