{
  "type": "Feature",
  "properties": {
    "addr:full":"Carr Victoria 11 Maig, De La, 50 Soller Islas Baleares 07100",
    "addr:housenumber":"11",
    "addr:postcode":"07100",
    "addr:street":"Carr Victoria",
    "iso:country":"ES",
    "sg:address":"Carr Victoria 11 Maig, De La, 50",
    "sg:city":"Soller",
    "sg:orig_category":"Mantenimiento Y Reparaci\u00d3n De Motores Industriales",
    "sg:phone":"+34 971 63 23 71",
    "sg:postcode":"07100",
    "sg:province":"Islas Baleares",
    "wof:name":"Perez Pastor Pedro",
    "wof:placetype":"venue"
},
  "geometry": {"coordinates":[2.715775013,39.7684020996],"type":"Point"}
}