{
  "type": "Feature",
  "properties": {
    "addr:full":"Carrer de Sol, 62 Sabadell Barcelona 08201",
    "addr:housenumber":"62",
    "addr:postcode":"08201",
    "addr:street":"Carrer De Sol",
    "iso:country":"ES",
    "sg:address":"Carrer de Sol, 62",
    "sg:city":"Sabadell",
    "sg:orig_category":"Guarder\u00cdas",
    "sg:phone":"+34 937 27 27 30",
    "sg:postcode":"08201",
    "sg:province":"Barcelona",
    "wof:name":"Games And Kids S.l.",
    "wof:placetype":"venue"
},
  "geometry": {"coordinates":[2.1091179848,41.5442810059],"type":"Point"}
}