{
  "type": "Feature",
  "properties": {
    "iso:country":"ES",
    "sg:address":"Calle de Lujan Perez, 5",
    "sg:city":"Villa De Moya",
    "sg:orig_category":"Bisuter\u00cda, Joyer\u00cda, Relojer\u00cda (al Por Menor)",
    "sg:phone":"+34 928 61 10 90",
    "sg:postcode":"35420",
    "sg:province":"Las Palmas",
    "wof:name":"Santana Gonzalez Martin Manuel",
    "wof:placetype":"venue"
},
  "geometry": {"coordinates":[-15.5827293396,28.1089496613],"type":"Point"}
}