{
  "type": "Feature",
  "properties": {
    "addr:full":"Rua Rosalia De Castro, 63 Verin Ourense 32600",
    "addr:housenumber":"63",
    "addr:postcode":"32600",
    "addr:street":"Rua Rosalia De Castro",
    "iso:country":"ES",
    "sg:address":"Rua Rosalia De Castro, 63",
    "sg:city":"Verin",
    "sg:orig_category":"Ense\u00d1anza, Formaci\u00d3n Profesional: Aprendizaje",
    "sg:phone":"+34 988 41 14 51",
    "sg:postcode":"32600",
    "sg:province":"Ourense",
    "wof:name":"Xunta De Galicia",
    "wof:placetype":"venue"
},
  "geometry": {"coordinates":[-7.4310293198,41.9427070618],"type":"Point"}
}