{
  "type": "Feature",
  "properties": {
    "iso:country":"ES",
    "sg:address":"Calle de Corredera, 43",
    "sg:city":"Vejer De La Frontera",
    "sg:classifiers":[
        {
            "category":"Casinos & Gambling",
            "type":"Entertainment"
        }
    ],
    "sg:phone":"+34 956 45 00 28",
    "sg:postcode":"11150",
    "sg:province":"C\u00e1diz",
    "sg:tags":[
        "locale",
        "de",
        "juego"
    ],
    "wof:name":"Pe\u00f1a Cultural Vejeriega",
    "wof:placetype":"venue"
},
  "geometry": {"coordinates":[-5.9636101723,36.2543716431],"type":"Point"}
}