{
  "type": "Feature",
  "properties": {
    "addr:full":"Calle de Pio Baroja, S/n Mesas Cuenca 16650",
    "addr:housenumber":"s / n",
    "addr:postcode":"16650",
    "addr:street":"Calle De Pio Baroja",
    "iso:country":"ES",
    "sg:address":"Calle de Pio Baroja, S/n",
    "sg:city":"Mesas",
    "sg:orig_category":"Construcciones Navales Y Fluviales",
    "sg:phone":"+34 967 15 52 19",
    "sg:postcode":"16650",
    "sg:province":"Cuenca",
    "wof:name":"Eurolame De Transportes S.l.",
    "wof:placetype":"venue"
},
  "geometry": {"coordinates":[-2.7677569389,39.3838500977],"type":"Point"}
}