{
  "type": "Feature",
  "properties": {
    "iso:country":"ES",
    "sg:address":"Calle de Gibraltar, 6",
    "sg:city":"Huesca",
    "sg:classifiers":[
        {
            "category":"Personal",
            "subcategory":"Barber",
            "type":"Services"
        }
    ],
    "sg:phone":"+34 974 22 42 82",
    "sg:postcode":"22006",
    "sg:province":"Huesca",
    "sg:tags":[
        "caballeros",
        "de",
        "peluqueros"
    ],
    "wof:name":"Lisa Subias Miguel Angel",
    "wof:placetype":"venue"
},
  "geometry": {"coordinates":[-0.3981660008,42.1402854919],"type":"Point"}
}