{
  "type": "Feature",
  "properties": {
    "iso:country":"ES",
    "sg:address":"Ctra. De Rota, Km. 0007,0",
    "sg:city":"La Ballena",
    "sg:orig_category":"Textil",
    "sg:phone":"+34 956 84 74 21",
    "sg:postcode":"11520",
    "sg:province":"C\u00e1diz",
    "wof:name":"Nueva Desmotadora Sevillana S. A.",
    "wof:placetype":"venue"
},
  "geometry": {"coordinates":[-6.3688821793,36.6247940063],"type":"Point"}
}