{
  "type": "Feature",
  "properties": {
    "iso:country":"ES",
    "sg:address":"Calle de Honduras, 28",
    "sg:city":"Coslada",
    "sg:orig_category":"Parques De Atracciones Y Centros De Esparcimiento",
    "sg:phone":"+34 916 73 29 01",
    "sg:postcode":"28820",
    "sg:province":"Madrid",
    "wof:name":"Electronicos Colombia S.a.",
    "wof:placetype":"venue"
},
  "geometry": {"coordinates":[-3.539949894,40.4231910706],"type":"Point"}
}