{
  "type": "Feature",
  "properties": {
    "addr:full":"Calle de La Reina, 64 Almoradi Alicante 03160",
    "addr:housenumber":"64",
    "addr:postcode":"03160",
    "addr:street":"Calle De La Reina",
    "iso:country":"ES",
    "sg:address":"Calle de La Reina, 64",
    "sg:city":"Almoradi",
    "sg:orig_category":"Electricidad: Instaladores",
    "sg:phone":"+34 965 70 01 90",
    "sg:postcode":"03160",
    "sg:province":"Alicante",
    "wof:name":"Pertusa Reina Vicente",
    "wof:placetype":"venue"
},
  "geometry": {"coordinates":[-0.7956240177,38.1080551147],"type":"Point"}
}