{
  "type": "Feature",
  "properties": {
    "iso:country":"ES",
    "sg:address":"Can Devall, S/n",
    "sg:city":"Porqueres",
    "sg:orig_category":"Transporte En General",
    "sg:phone":"+34 972 58 21 73",
    "sg:postcode":"17834",
    "sg:province":"Girona",
    "wof:name":"Distribuciones Alimentarias Osedo S.l. Unipersonal",
    "wof:placetype":"venue"
},
  "geometry": {"coordinates":[2.764480114,42.0982017517],"type":"Point"}
}