{
  "type": "Feature",
  "properties": {
    "iso:country":"ES",
    "sg:address":"Calle de Belgica, 16",
    "sg:city":"Valencia",
    "sg:orig_category":"Tintes (fabricaci\u00d3n, Al Por Mayor)",
    "sg:phone":"+34 963 69 46 34",
    "sg:postcode":"46021",
    "sg:province":"Valencia",
    "wof:name":"Tintorerias Explendit S.l.",
    "wof:placetype":"venue"
},
  "geometry": {"coordinates":[-0.3554959893,39.4736938477],"type":"Point"}
}