{
  "type": "Feature",
  "properties": {
    "addr:full":"Avda Acapulco, 4 Fuengirola M\u00e1laga 29640",
    "addr:housenumber":"4",
    "addr:postcode":"29640",
    "addr:street":"Avda Acapulco;Ma\u0301Laga",
    "iso:country":"ES",
    "sg:address":"Avda Acapulco, 4",
    "sg:city":"Fuengirola",
    "sg:orig_category":"Abogados",
    "sg:phone":"+34 952 66 58 32",
    "sg:postcode":"29640",
    "sg:province":"M\u00e1laga",
    "wof:name":"Garcia Y Villar,abogadas Sc",
    "wof:placetype":"venue"
},
  "geometry": {"coordinates":[-4.619120121,36.5516014099],"type":"Point"}
}