{
  "type": "Feature",
  "properties": {
    "addr:full":"Carrer de Magdalenes, 6 Barcelona Barcelona 08002",
    "addr:housenumber":"6",
    "addr:postcode":"08002",
    "addr:street":"Carrer De Magdalenes",
    "iso:country":"ES",
    "sg:address":"Carrer de Magdalenes, 6",
    "sg:city":"Barcelona",
    "sg:orig_category":"Peluquer\u00cdas, Peluquer\u00cda Mixta",
    "sg:phone":"+34 934 12 38 42",
    "sg:postcode":"08002",
    "sg:province":"Barcelona",
    "sg:website":"www.polopelo.com",
    "wof:name":"Polo Pelo S.l.",
    "wof:placetype":"venue"
},
  "geometry": {"coordinates":[2.174808979,41.3859634399],"type":"Point"}
}