{
  "type": "Feature",
  "properties": {
    "iso:country":"ES",
    "sg:address":"Carr Enginyer Pau Agusti, 303",
    "sg:city":"Lleida",
    "sg:orig_category":"Molduras, Junquillos, Listones Y Molduras Perforadas",
    "sg:phone":"+34 973 20 28 04",
    "sg:postcode":"25191",
    "sg:province":"Lleida",
    "wof:name":"Anca Martinez Maria Matilde",
    "wof:placetype":"venue"
},
  "geometry": {"coordinates":[0.6630749702,41.6341972351],"type":"Point"}
}