{
  "type": "Feature",
  "properties": {
    "addr:full":"Calle de Malaga, 17 Berja Almer\u00eda 04760",
    "addr:housenumber":"17",
    "addr:postcode":"04760",
    "addr:street":"Calle De Malaga",
    "iso:country":"ES",
    "sg:address":"Calle de Malaga, 17",
    "sg:city":"Berja",
    "sg:orig_category":"Electricidad: Instaladores",
    "sg:phone":"+34 950 49 00 45",
    "sg:postcode":"04760",
    "sg:province":"Almer\u00eda",
    "wof:name":"Nu\u00f1ez Amo Antonio",
    "wof:placetype":"venue"
},
  "geometry": {"coordinates":[-2.9434969425,36.8390693665],"type":"Point"}
}