{
  "type": "Feature",
  "properties": {
    "iso:country":"ES",
    "sg:address":"Po. Inmaculada, 64",
    "sg:city":"Estella",
    "sg:orig_category":"Fabricaci\u00d3n De Su\u00c9ters Y Chalecos De Punto",
    "sg:phone":"+34 948 55 60 03",
    "sg:postcode":"31200",
    "sg:province":"Navarra",
    "wof:name":"Comercial Lizarra S.l.",
    "wof:placetype":"venue"
},
  "geometry": {"coordinates":[-2.0341320038,42.6717681885],"type":"Point"}
}