{
  "type": "Feature",
  "properties": {
    "addr:full":"Calle de Galiana De, 13 Aviles Asturias 33402",
    "addr:housenumber":"13",
    "addr:postcode":"33402",
    "addr:street":"Calle De Galiana De",
    "iso:country":"ES",
    "sg:address":"Calle de Galiana De, 13",
    "sg:city":"Aviles",
    "sg:orig_category":"Plomeros",
    "sg:phone":"+34 985 54 13 73",
    "sg:postcode":"33402",
    "sg:province":"Asturias",
    "wof:name":"Yurafon S.l.",
    "wof:placetype":"venue"
},
  "geometry": {"coordinates":[-5.9248151779,43.5536231995],"type":"Point"}
}