{
  "type": "Feature",
  "properties": {
    "addr:full":"Calle de De Los Herreros, 21 Benavente Zamora 49600",
    "addr:housenumber":"21",
    "addr:postcode":"49600",
    "addr:street":"Calle De De Los Herreros",
    "iso:country":"ES",
    "sg:address":"Calle de De Los Herreros, 21",
    "sg:city":"Benavente",
    "sg:orig_category":"Complementos De Vestir (al Por Menor)",
    "sg:phone":"+34 980 63 14 58",
    "sg:postcode":"49600",
    "sg:province":"Zamora",
    "wof:name":"Creaciones C.c. S.l.",
    "wof:placetype":"venue"
},
  "geometry": {"coordinates":[-5.6787691116,42.0028533936],"type":"Point"}
}