{
  "type": "Feature",
  "properties": {
    "addr:full":"Calle de Mar De Kara, 10 Madrid Madrid 28033",
    "addr:housenumber":"10",
    "addr:postcode":"madrid;28033",
    "addr:street":"Calle De Mar De Kara",
    "iso:country":"ES",
    "sg:address":"Calle de Mar De Kara, 10",
    "sg:city":"Madrid",
    "sg:orig_category":"Deportes Y Ocio: Art\u00cdculos Y Ropas (al Por Menor Y Accesorios)",
    "sg:phone":"+34 917 63 97 51",
    "sg:postcode":"28033",
    "sg:province":"Madrid",
    "wof:name":"Alam-air S.l.",
    "wof:placetype":"venue"
},
  "geometry": {"coordinates":[-3.6441171169,40.4717636108],"type":"Point"}
}