{
  "type": "Feature",
  "properties": {
    "addr:full":"Enparan Kalea, 7 Azpeitia Guip\u00f9zcoa 20730",
    "addr:housenumber":"7",
    "addr:postcode":"20730",
    "addr:street":"Enparan Kalea;Guipu\u0300Zcoa",
    "iso:country":"ES",
    "sg:address":"Enparan Kalea, 7",
    "sg:city":"Azpeitia",
    "sg:orig_category":"Arquitectos",
    "sg:phone":"+34 943 81 48 60",
    "sg:postcode":"20730",
    "sg:province":"Guip\u00f9zcoa",
    "wof:name":"Arenal Fernandez Maria Teresa",
    "wof:placetype":"venue"
},
  "geometry": {"coordinates":[-2.2650878429,43.1841049194],"type":"Point"}
}