{
  "type": "Feature",
  "properties": {
    "iso:country":"ES",
    "sg:address":"Carrer de Sant Agusti, 8",
    "sg:city":"Molins Rei",
    "sg:orig_category":"Electricidad: Instaladores",
    "sg:phone":"+34 936 80 18 79",
    "sg:postcode":"08750",
    "sg:province":"Barcelona",
    "wof:name":"Sansalvador Segui Manuel",
    "wof:placetype":"venue"
},
  "geometry": {"coordinates":[2.0255470276,41.4088363647],"type":"Point"}
}