{
  "type": "Feature",
  "properties": {
    "iso:country":"ES",
    "sg:address":"Calle de Victoria, S/n",
    "sg:city":"Valladolid",
    "sg:orig_category":"Centros De Educaci\u00d3n Especial",
    "sg:phone":"+34 983 33 73 36",
    "sg:postcode":"47009",
    "sg:province":"Valladolid",
    "wof:name":"Colegio Nacional Miguel Delibes",
    "wof:placetype":"venue"
},
  "geometry": {"coordinates":[-4.7324771881,41.6642684937],"type":"Point"}
}