{
  "type": "Feature",
  "properties": {
    "addr:full":"Calle de Arcipreste Esteban Diaz, 54 Yecla Murcia 30510",
    "addr:housenumber":"54",
    "addr:postcode":"30510",
    "addr:street":"Calle De Arcipreste Esteban Diaz",
    "iso:country":"ES",
    "sg:address":"Calle de Arcipreste Esteban Diaz, 54",
    "sg:city":"Yecla",
    "sg:orig_category":"Arquitectos",
    "sg:phone":"+34 968 71 88 28",
    "sg:postcode":"30510",
    "sg:province":"Murcia",
    "wof:name":"Abellan Aleman Asociado S.l.",
    "wof:placetype":"venue"
},
  "geometry": {"coordinates":[-1.107038,38.609871],"type":"Point"}
}