{
  "type": "Feature",
  "properties": {
    "addr:full":"Calle de Leares (las), S/n Vega Espinareda Le\u00f3n 24430",
    "addr:postcode":"24430",
    "addr:street":"Calle De Leares Las S / N;Espinareda Leo\u0301N",
    "iso:country":"ES",
    "sg:address":"Calle de Leares (las), S/n",
    "sg:city":"Vega Espinareda",
    "sg:orig_category":"Ense\u00d1anza, Formaci\u00d3n Profesional: Aprendizaje",
    "sg:phone":"+34 987 56 46 27",
    "sg:postcode":"24430",
    "sg:province":"Le\u00f3n",
    "wof:name":"Ayuntamiento De Vega De Espinareda",
    "wof:placetype":"venue"
},
  "geometry": {"coordinates":[-6.6590037346,42.7260169983],"type":"Point"}
}