{
  "type": "Feature",
  "properties": {
    "iso:country":"ES",
    "sg:address":"Cmno. Carraquintanar, 1",
    "sg:city":"Campo De San Pedro",
    "sg:orig_category":"Concepci\u00d3n Y Realizaci\u00d3n De Maquetas Profesionales Y Prototipos",
    "sg:phone":"+34 921 55 62 31",
    "sg:postcode":"40551",
    "sg:province":"Segovia",
    "wof:name":"Maquet Model S.l.",
    "wof:placetype":"venue"
},
  "geometry": {"coordinates":[-3.5485670567,41.42943573],"type":"Point"}
}