{
  "type": "Feature",
  "properties": {
    "addr:full":"Luga Pi\u00d1eiral De Abaixo, 13 Pi\u00d1eiral Ourense 32911",
    "addr:housenumber":"13",
    "addr:postcode":"32911",
    "addr:street":"Abaixo",
    "iso:country":"ES",
    "sg:address":"Luga Pi\u00d1eiral De Abaixo, 13",
    "sg:city":"Pi\u00d1eiral",
    "sg:orig_category":"Chapister\u00cda",
    "sg:phone":"+34 988 22 31 76",
    "sg:postcode":"32911",
    "sg:province":"Ourense",
    "wof:name":"Chapisteria Blanco S.l.",
    "wof:placetype":"venue"
},
  "geometry": {"coordinates":[-7.872358799,42.2972106934],"type":"Point"}
}