{
  "type": "Feature",
  "properties": {
    "iso:country":"ES",
    "sg:address":"Calle de Mon, 31",
    "sg:city":"Gijon",
    "sg:orig_category":"Pintura Y Barniz (al Por Menor)",
    "sg:phone":"+34 985 16 41 74",
    "sg:postcode":"33210",
    "sg:province":"Asturias",
    "wof:name":"Tenysol S.l.",
    "wof:placetype":"venue"
},
  "geometry": {"coordinates":[-5.669064045,43.52161026],"type":"Point"}
}