{
  "type": "Feature",
  "properties": {
    "addr:full":"Calle de Dr Gonzalez Hierro, 25 Guadalajara Guadalajara 19002",
    "addr:housenumber":"25",
    "addr:postcode":"19002",
    "addr:street":"Calle De Dr Gonzalez Hierro",
    "iso:country":"ES",
    "sg:address":"Calle de Dr Gonzalez Hierro, 25",
    "sg:city":"Guadalajara",
    "sg:orig_category":"Ropa Y Accesorios",
    "sg:phone":"+34 949 21 29 41",
    "sg:postcode":"19002",
    "sg:province":"Guadalajara",
    "wof:name":"De Diego Caballero Vicente",
    "wof:placetype":"venue"
},
  "geometry": {"coordinates":[-3.163292408,40.6238288879],"type":"Point"}
}