{
  "type": "Feature",
  "properties": {
    "iso:country":"ES",
    "sg:address":"Carr Cronista Pareja, 5",
    "sg:city":"Canals",
    "sg:orig_category":"Bisuter\u00cda, Joyer\u00cda, Relojer\u00cda (al Por Menor)",
    "sg:phone":"+34 962 24 16 70",
    "sg:postcode":"46650",
    "sg:province":"Valencia",
    "wof:name":"Vila Bolinches Salvador",
    "wof:placetype":"venue"
},
  "geometry": {"coordinates":[-0.5810639858,38.9652137756],"type":"Point"}
}