{
  "type": "Feature",
  "properties": {
    "iso:country":"ES",
    "sg:address":"Calle de San Francisco, 80",
    "sg:city":"Vinaros",
    "sg:orig_category":"Inmobiliaria (agencias)",
    "sg:phone":"+34 964 45 49 74",
    "sg:postcode":"12500",
    "sg:province":"Castell\u00f3n",
    "sg:website":"www.inverfutur.com",
    "wof:name":"Gonzalez Villaza\u00f1i Gregorio",
    "wof:placetype":"venue"
},
  "geometry": {"coordinates":[0.4749450088,40.4711990356],"type":"Point"}
}