{
  "type": "Feature",
  "properties": {
    "addr:full":"Calle de Almibar (del), 92 Aranjuez Madrid 28300",
    "addr:housenumber":"92",
    "addr:postcode":"28300",
    "addr:street":"Calle De Almibar Del",
    "iso:country":"ES",
    "sg:address":"Calle de Almibar (del), 92",
    "sg:city":"Aranjuez",
    "sg:orig_category":"Alimentaci\u00d3n General (al Por Menor)",
    "sg:phone":"+34 918 92 34 11",
    "sg:postcode":"28300",
    "sg:province":"Madrid",
    "wof:name":"Don Pollo Asador S.l.",
    "wof:placetype":"venue"
},
  "geometry": {"coordinates":[-3.6029853821,40.03125],"type":"Point"}
}