{
  "type": "Feature",
  "properties": {
    "iso:country":"ES",
    "sg:address":"Carrer de Doctor Auguet Canonge, 69",
    "sg:city":"Viladecans",
    "sg:orig_category":"Reposter\u00cdas",
    "sg:phone":"+34 936 58 47 06",
    "sg:postcode":"08840",
    "sg:province":"Barcelona",
    "wof:name":"Vilapan S. A.",
    "wof:placetype":"venue"
},
  "geometry": {"coordinates":[2.0094230175,41.3184013367],"type":"Point"}
}