{
  "type": "Feature",
  "properties": {
    "iso:country":"ES",
    "sg:address":"Calle de Alcala, 379",
    "sg:city":"Madrid",
    "sg:orig_category":"Higiene, Belleza: Art\u00cdculos (al Por Menor)",
    "sg:phone":"+34 913 67 25 63",
    "sg:postcode":"28027",
    "sg:province":"Madrid",
    "wof:name":"M.carmen Fernandez Torres S.l.",
    "wof:placetype":"venue"
},
  "geometry": {"coordinates":[-3.6432812214,40.4354553223],"type":"Point"}
}