{
  "type": "Feature",
  "properties": {
    "iso:country":"ES",
    "sg:address":"Ctr El Bonillo, Km. 0001,0",
    "sg:city":"Socuellamos",
    "sg:orig_category":"Distribuci\u00d3n De Petr\u00d3leo Y Derivados",
    "sg:phone":"+34 926 50 01 24",
    "sg:postcode":"13630",
    "sg:province":"Ciudad Real",
    "wof:name":"Combustibles San Jorge S.l.",
    "wof:placetype":"venue"
},
  "geometry": {"coordinates":[-2.7948589325,39.2849845886],"type":"Point"}
}