{
  "type": "Feature",
  "properties": {
    "addr:full":"Plaz Mayor, 1 Ejido Almer\u00eda 04700",
    "addr:housenumber":"1",
    "addr:postcode":"04700",
    "addr:street":"Plaz Mayor;Almeri\u0301A",
    "iso:country":"ES",
    "sg:address":"Plaz Mayor, 1",
    "sg:city":"Ejido",
    "sg:orig_category":"Abogados",
    "sg:phone":"+34 950 57 30 87",
    "sg:postcode":"04700",
    "sg:province":"Almer\u00eda",
    "wof:name":"Iba\u00f1ez Iba\u00f1ez Enrique",
    "wof:placetype":"venue"
},
  "geometry": {"coordinates":[-2.8176040649,36.7727012634],"type":"Point"}
}