{
  "type": "Feature",
  "properties": {
    "iso:country":"ES",
    "sg:address":"Avda Maisonnave, 33",
    "sg:city":"Alacant",
    "sg:orig_category":"Asesor\u00cda Sobre Comunicaci\u00d3n De Empresas",
    "sg:phone":"+34 965 22 84 91",
    "sg:postcode":"03003",
    "sg:province":"Alicante",
    "wof:name":"Asesoramiento Y Consulting S.l.",
    "wof:placetype":"venue"
},
  "geometry": {"coordinates":[-0.4914268851,38.3433952332],"type":"Point"}
}