{
  "type": "Feature",
  "properties": {
    "iso:country":"ES",
    "sg:address":"Carrer de Lloret De Mar, 31",
    "sg:city":"Barcelona",
    "sg:orig_category":"Electricidad: Instaladores",
    "sg:phone":"+34 934 29 63 54",
    "sg:postcode":"08032",
    "sg:province":"Barcelona",
    "wof:name":"Instalaciones Y Servicios S.c.p.",
    "wof:placetype":"venue"
},
  "geometry": {"coordinates":[2.1550600529,41.4336738586],"type":"Point"}
}