{
  "type": "Feature",
  "properties": {
    "addr:full":"Mayor, 43 Atarrabia Navarra 31610",
    "addr:housenumber":"43",
    "addr:postcode":"31610",
    "addr:street":"Mayor",
    "iso:country":"ES",
    "sg:address":"Mayor, 43",
    "sg:city":"Atarrabia",
    "sg:orig_category":"Electricidad, Electr\u00d3nica: Material Y Suministros (al Por Mayor)",
    "sg:phone":"+34 948 12 70 22",
    "sg:postcode":"31610",
    "sg:province":"Navarra",
    "sg:website":"www.ciberdaitona.com",
    "wof:name":"Promociones Recreativas Naex S.a.",
    "wof:placetype":"venue"
},
  "geometry": {"coordinates":[-1.6073729992,42.8325424194],"type":"Point"}
}