{
  "type": "Feature",
  "properties": {
    "iso:country":"ES",
    "sg:address":"Avda Ejercito, 17",
    "sg:city":"Guadalajara",
    "sg:orig_category":"Institutos De Belleza",
    "sg:phone":"+34 949 25 44 70",
    "sg:postcode":"19003",
    "sg:province":"Guadalajara",
    "wof:name":"Roldan De La Cruz Noelia",
    "wof:placetype":"venue"
},
  "geometry": {"coordinates":[-3.1801519394,40.6287956238],"type":"Point"}
}