{
  "type": "Feature",
  "properties": {
    "iso:country":"ES",
    "sg:address":"Carrer de Cervantes, 4",
    "sg:city":"Reus",
    "sg:orig_category":"Pintura Industrial (trabajos De)",
    "sg:phone":"+34 977 32 16 18",
    "sg:postcode":"43201",
    "sg:province":"Tarragona",
    "wof:name":"Pintura Industrial Reus S. A.",
    "wof:placetype":"venue"
},
  "geometry": {"coordinates":[1.1030650139,41.1635894775],"type":"Point"}
}