{
  "type": "Feature",
  "properties": {
    "iso:country":"ES",
    "sg:address":"Calle de Ucles, S/n",
    "sg:city":"Santa Cruz De La Zarza",
    "sg:orig_category":"Material Y Herramientas Agr\u00cdcolas",
    "sg:phone":"+34 925 12 51 66",
    "sg:postcode":"45370",
    "sg:province":"Toledo",
    "wof:name":"Sanchez Camara Javier",
    "wof:placetype":"venue"
},
  "geometry": {"coordinates":[-3.1800789833,39.9754638672],"type":"Point"}
}