{
  "type": "Feature",
  "properties": {
    "iso:country":"ES",
    "sg:address":"Calle de Leon Felipe, 6",
    "sg:city":"Guadalajara",
    "sg:orig_category":"Institutos De Belleza",
    "sg:phone":"+34 949 20 31 42",
    "sg:postcode":"19004",
    "sg:province":"Guadalajara",
    "wof:name":"Comunidad De Bienes Model",
    "wof:placetype":"venue"
},
  "geometry": {"coordinates":[-3.1782000065,40.6320037842],"type":"Point"}
}