{
  "type": "Feature",
  "properties": {
    "addr:full":"Carrer de Setze De Juliol, 63 Poligon Industrial De Son Castello Islas Baleares 07009",
    "addr:housenumber":"63",
    "addr:postcode":"07009",
    "addr:street":"Carrer De Setze De Juliol;Islas",
    "iso:country":"ES",
    "sg:address":"Carrer de Setze De Juliol, 63",
    "sg:city":"Poligon Industrial De Son Castello",
    "sg:orig_category":"Venta, Montaje De Neum\u00c1ticos",
    "sg:phone":"+34 971 29 22 41",
    "sg:postcode":"07009",
    "sg:province":"Islas Baleares",
    "wof:name":"Globalshop S.l.",
    "wof:placetype":"venue"
},
  "geometry": {"coordinates":[2.6741399765,39.6011390686],"type":"Point"}
}