{
  "type": "Feature",
  "properties": {
    "iso:country":"ES",
    "sg:address":"Carrer de Sant Antoni Maria Claret, 42",
    "sg:city":"Barcelona",
    "sg:orig_category":"Panader\u00cdas, Panader\u00cdas",
    "sg:phone":"+34 934 58 73 66",
    "sg:postcode":"08025",
    "sg:province":"Barcelona",
    "wof:name":"Panificadora Myrpa S.l.",
    "wof:placetype":"venue"
},
  "geometry": {"coordinates":[2.1660239697,41.4048156738],"type":"Point"}
}