{
  "type": "Feature",
  "properties": {
    "addr:full":"Calle de Real, 37 Arganda Madrid 28500",
    "addr:housenumber":"37",
    "addr:postcode":"28500",
    "addr:street":"Calle De Real",
    "iso:country":"ES",
    "sg:address":"Calle de Real, 37",
    "sg:city":"Arganda",
    "sg:orig_category":"\u00d3ptica: Instrumentos (fabricaci\u00d3n)",
    "sg:phone":"+34 918 71 78 15",
    "sg:postcode":"28500",
    "sg:province":"Madrid",
    "wof:name":"Argavision S.l.l.",
    "wof:placetype":"venue"
},
  "geometry": {"coordinates":[-3.4360597134,40.3000450134],"type":"Point"}
}