{
  "type": "Feature",
  "properties": {
    "iso:country":"ES",
    "sg:address":"Pl. Isidoro Macabich, 26",
    "sg:city":"Sta. Eularia Riu",
    "sg:orig_category":"Promotores Constructores",
    "sg:phone":"+34 971 31 95 56",
    "sg:postcode":"07840",
    "sg:province":"Islas Baleares",
    "wof:name":"Caceres Rubio Antonio",
    "wof:placetype":"venue"
},
  "geometry": {"coordinates":[1.5341850519,38.9850311279],"type":"Point"}
}