{
  "type": "Feature",
  "properties": {
    "iso:country":"ES",
    "sg:address":"Carrer de Ramon De Trinxeria, 8",
    "sg:city":"Sant Feliu Llobregat",
    "sg:orig_category":"Fabricaci\u00d3n De Papeles Especiales Y Para Usos T\u00c9cnicos",
    "sg:phone":"+34 936 85 97 00",
    "sg:postcode":"08980",
    "sg:province":"Barcelona",
    "wof:name":"Set-prat S.a.",
    "wof:placetype":"venue"
},
  "geometry": {"coordinates":[2.0352699757,41.3876152039],"type":"Point"}
}