{
  "type": "Feature",
  "properties": {
    "addr:full":"Obenerreka Kalea, 2 Arrasate Guip\u00f9zcoa 20500",
    "addr:housenumber":"2",
    "addr:postcode":"20500",
    "addr:street":"Obenerreka Kalea;Guipu\u0300Zcoa",
    "iso:country":"ES",
    "sg:address":"Obenerreka Kalea, 2",
    "sg:city":"Arrasate",
    "sg:orig_category":"Pintura, Barniz, Productos Asimilables (fabricaci\u00d3n, Al Por Mayor)",
    "sg:phone":"+34 943 79 87 00",
    "sg:postcode":"20500",
    "sg:province":"Guip\u00f9zcoa",
    "wof:name":"Juan Sanchez Romero Y Vicente Del Pozo Cuevas C.b.",
    "wof:placetype":"venue"
},
  "geometry": {"coordinates":[-2.4853789806,43.068107605],"type":"Point"}
}