{
  "type": "Feature",
  "properties": {
    "iso:country":"ES",
    "sg:address":"Calle de Parroco Fernandez Pedrera, 12",
    "sg:city":"Pola De Siero",
    "sg:orig_category":"Agencias De Viajes",
    "sg:phone":"+34 985 72 09 47",
    "sg:postcode":"33510",
    "sg:province":"Asturias",
    "sg:website":"www.viajesecudor.com",
    "wof:name":"Viajes Rosal C.b.",
    "wof:placetype":"venue"
},
  "geometry": {"coordinates":[-5.6604671478,43.389175415],"type":"Point"}
}