{
  "type": "Feature",
  "properties": {
    "addr:full":"P. Cruz S. Benedicto, S/n Medina-sidonia C\u00e1diz 11170",
    "addr:housenumber":"s / n",
    "addr:postcode":"11170",
    "addr:street":"P. Cruz S. Benedicto;Medina-Sidonia Ca\u0301Diz",
    "iso:country":"ES",
    "sg:address":"P. Cruz S. Benedicto, S/n",
    "sg:city":"Medina-sidonia",
    "sg:orig_category":"Molduras, Junquillos, Listones Y Molduras Perforadas",
    "sg:phone":"+34 956 41 00 32",
    "sg:postcode":"11170",
    "sg:province":"C\u00e1diz",
    "wof:name":"Fuentes Mu\u00f1oz Maria",
    "wof:placetype":"venue"
},
  "geometry": {"coordinates":[-5.9409708977,36.4186630249],"type":"Point"}
}