{
  "type": "Feature",
  "properties": {
    "iso:country":"ES",
    "sg:address":"Calle de Cerro Minguete, 65",
    "sg:city":"Madrid",
    "sg:orig_category":"Ingeniero",
    "sg:phone":"+34 917 30 79 52",
    "sg:postcode":"28035",
    "sg:province":"Madrid",
    "wof:name":"Martin Lopez Nieves",
    "wof:placetype":"venue"
},
  "geometry": {"coordinates":[-3.7221362591,40.4868278503],"type":"Point"}
}