{
  "type": "Feature",
  "properties": {
    "addr:full":"Luga Lances (los), 25 Tarifa C\u00e1diz 11380",
    "addr:postcode":"11380",
    "addr:street":"Los;Ca\u0301Diz",
    "iso:country":"ES",
    "sg:address":"Luga Lances (los), 25",
    "sg:city":"Tarifa",
    "sg:orig_category":"Conservas De Pescados Y Salazones Mar\u00cdtimos (fabricaci\u00d3n, Al Por Mayor)",
    "sg:phone":"+34 956 68 40 03",
    "sg:postcode":"11380",
    "sg:province":"C\u00e1diz",
    "wof:name":"Marina Real S.a.",
    "wof:placetype":"venue"
},
  "geometry": {"coordinates":[-5.613161087,36.0201072693],"type":"Point"}
}