{
  "type": "Feature",
  "properties": {
    "addr:full":"Calle de Jose Sansegundo Flores, S/n Badajoz Badajoz 06006",
    "addr:housenumber":"s",
    "addr:postcode":"06006",
    "addr:street":"Calle De Jose Sansegundo Flores;/ N",
    "iso:country":"ES",
    "sg:address":"Calle de Jose Sansegundo Flores, S/n",
    "sg:city":"Badajoz",
    "sg:orig_category":"Alimentaci\u00d3n General (al Por Menor)",
    "sg:phone":"+34 924 27 70 65",
    "sg:postcode":"06006",
    "sg:province":"Badajoz",
    "wof:name":"Gonzalez Romero Manuel Joaquin",
    "wof:placetype":"venue"
},
  "geometry": {"coordinates":[-6.9865589142,38.8823394775],"type":"Point"}
}