{
  "type": "Feature",
  "properties": {
    "addr:full":"Calle de Errebonbillo, S/n Elorrio Vizcaya 48230",
    "addr:housenumber":"s",
    "addr:postcode":"48230",
    "addr:street":"Calle De Errebonbillo;/ N",
    "iso:country":"ES",
    "sg:address":"Calle de Errebonbillo, S/n",
    "sg:city":"Elorrio",
    "sg:orig_category":"Caf\u00c9s, Bares, Cervecer\u00cdas",
    "sg:phone":"+34 946 58 27 48",
    "sg:postcode":"48230",
    "sg:province":"Vizcaya",
    "wof:name":"Salaberria Ugaldea Felix",
    "wof:placetype":"venue"
},
  "geometry": {"coordinates":[-2.5447080135,43.1308403015],"type":"Point"}
}