{
  "type": "Feature",
  "properties": {
    "addr:full":"Fusters, 10 Capdepera Islas Baleares 07580",
    "addr:housenumber":"10",
    "addr:postcode":"07580",
    "addr:street":"Fusters",
    "iso:country":"ES",
    "sg:address":"Fusters, 10",
    "sg:city":"Capdepera",
    "sg:orig_category":"Metalurgia",
    "sg:phone":"+34 971 56 32 43",
    "sg:postcode":"07580",
    "sg:province":"Islas Baleares",
    "wof:name":"Alfernox S.l.",
    "wof:placetype":"venue"
},
  "geometry": {"coordinates":[3.4200866222,39.6981964111],"type":"Point"}
}