{
  "type": "Feature",
  "properties": {
    "iso:country":"ES",
    "sg:address":"Arbidea, 1",
    "sg:city":"Bilbao",
    "sg:orig_category":"Asociaciones, Organismos Culturales Y Socioeducativos",
    "sg:phone":"+34 944 15 01 99",
    "sg:postcode":"48004",
    "sg:province":"Vizcaya",
    "sg:website":"www.bizkaie.biz",
    "wof:name":"Asociacion Bizikai Elkarte Kulturala",
    "wof:placetype":"venue"
},
  "geometry": {"coordinates":[-2.9082098007,43.2556037903],"type":"Point"}
}