{
  "type": "Feature",
  "properties": {
    "addr:full":"Calle de Alegria, 30 Moron Frontera Sevilla 41530",
    "addr:housenumber":"30",
    "addr:postcode":"41530",
    "addr:street":"Calle De Alegria",
    "iso:country":"ES",
    "sg:address":"Calle de Alegria, 30",
    "sg:city":"Moron Frontera",
    "sg:orig_category":"Papel, Reciclaje",
    "sg:phone":"+34 954 85 03 59",
    "sg:postcode":"41530",
    "sg:province":"Sevilla",
    "wof:name":"Reciclados Hermanos Ortiz S.l.",
    "wof:placetype":"venue"
},
  "geometry": {"coordinates":[-5.3150143623,37.2238044739],"type":"Point"}
}