{
  "type": "Feature",
  "properties": {
    "addr:full":"Av Jaume I, 63 Blanes Girona 17300",
    "addr:housenumber":"63",
    "addr:postcode":"17300",
    "addr:street":"Av Jaume I",
    "iso:country":"ES",
    "sg:address":"Av Jaume I, 63",
    "sg:city":"Blanes",
    "sg:orig_category":"Cl\u00cdnicas Dentales",
    "sg:phone":"+34 972 33 19 50",
    "sg:postcode":"17300",
    "sg:province":"Girona",
    "wof:name":"Piulach Clapera Jose Oriol",
    "wof:placetype":"venue"
},
  "geometry": {"coordinates":[2.7900500298,41.6777381897],"type":"Point"}
}