{
  "type": "Feature",
  "properties": {
    "iso:country":"ES",
    "sg:address":"Calle de Dalmacio Garcia Izcara, 4",
    "sg:city":"Cuenca",
    "sg:orig_category":"Artesan\u00cda",
    "sg:phone":"+34 969 22 82 78",
    "sg:postcode":"16004",
    "sg:province":"Cuenca",
    "wof:name":"Diaz-romeral Hermosilla Julia",
    "wof:placetype":"venue"
},
  "geometry": {"coordinates":[-2.1365485191,40.0688705444],"type":"Point"}
}