{
  "type": "Feature",
  "properties": {
    "iso:country":"ES",
    "sg:address":"Pl Sol, 7",
    "sg:city":"Barcelona",
    "sg:orig_category":"Caf\u00c9s, Bares, Cervecer\u00cdas",
    "sg:phone":"+34 932 18 83 88",
    "sg:postcode":"08012",
    "sg:province":"Barcelona",
    "wof:name":"Joaufer 2000 S.l.",
    "wof:placetype":"venue"
},
  "geometry": {"coordinates":[2.1559228897,41.402179718],"type":"Point"}
}