{
  "type": "Feature",
  "properties": {
    "addr:full":"Carr De Josep Melcior Gomis, 4 Ontinyent Valencia 46870",
    "addr:housenumber":"4",
    "addr:postcode":"46870",
    "addr:street":"Carr De Josep Melcior Gomis",
    "iso:country":"ES",
    "sg:address":"Carr De Josep Melcior Gomis, 4",
    "sg:city":"Ontinyent",
    "sg:orig_category":"Ropa Para Ni\u00d1os (al Por Menor)",
    "sg:phone":"+34 962 91 04 88",
    "sg:postcode":"46870",
    "sg:province":"Valencia",
    "wof:name":"Montes Ure\u00f1a Sonia",
    "wof:placetype":"venue"
},
  "geometry": {"coordinates":[-0.6030989885,38.8258895874],"type":"Point"}
}