{
  "type": "Feature",
  "properties": {
    "iso:country":"ES",
    "sg:address":"Calle de San Esteban, 1",
    "sg:city":"Pedrajas S. Esteban",
    "sg:orig_category":"Mercer\u00cda, Lencer\u00cda (al Por Menor)",
    "sg:phone":"+34 983 60 54 32",
    "sg:postcode":"47430",
    "sg:province":"Valladolid",
    "wof:name":"Pablo Herrero Francisco De",
    "wof:placetype":"venue"
},
  "geometry": {"coordinates":[-4.5837030411,41.3412399292],"type":"Point"}
}