{
  "type": "Feature",
  "properties": {
    "iso:country":"ES",
    "sg:address":"Calle de Estrella, 3",
    "sg:city":"Valencia",
    "sg:orig_category":"Sanatorios M\u00c9dico",
    "sg:phone":"+34 963 41 08 30",
    "sg:postcode":"46007",
    "sg:province":"Valencia",
    "wof:name":"Instituto Valenciano De Oncologia",
    "wof:placetype":"venue"
},
  "geometry": {"coordinates":[-0.3801679909,39.4662094116],"type":"Point"}
}