{
  "type": "Feature",
  "properties": {
    "addr:full":"Calle de Fueros De Logro\u00d1o (los), 3 Logro\u00f1o La Rioja 26006",
    "addr:housenumber":"3",
    "addr:postcode":"26006",
    "addr:street":"Calle De Fueros De Logron\u0303O Los;Rioja",
    "iso:country":"ES",
    "sg:address":"Calle de Fueros De Logro\u00d1o (los), 3",
    "sg:city":"Logro\u00f1o",
    "sg:orig_category":"Encuadernaci\u00d3n E Impresi\u00d3n De Folletos",
    "sg:phone":"+34 941 20 10 85",
    "sg:postcode":"26006",
    "sg:province":"La Rioja",
    "wof:name":"Campo Fernandez Manuel",
    "wof:placetype":"venue"
},
  "geometry": {"coordinates":[-2.475274086,42.4609336853],"type":"Point"}
}