{
  "type": "Feature",
  "properties": {
    "iso:country":"ES",
    "sg:address":"Pase Constitucion De (la), 119",
    "sg:city":"Arnedo",
    "sg:orig_category":"Zapatos: Material, Suministros, Accesorios (fabricaci\u00d3n, Al Por Mayor)",
    "sg:phone":"+34 941 38 11 90",
    "sg:postcode":"26580",
    "sg:province":"La Rioja",
    "wof:name":"Arcomalla S.cv.",
    "wof:placetype":"venue"
},
  "geometry": {"coordinates":[-2.1073498726,42.2251319885],"type":"Point"}
}