{
  "type": "Feature",
  "properties": {
    "addr:full":"Calle de Miguel Barroso, 11 Alcazar S. Juan Ciudad Real 13600",
    "addr:housenumber":"11",
    "addr:postcode":"13600",
    "addr:street":"Calle De Miguel Barroso;Alcazar S. Juan Ciudad Real",
    "iso:country":"ES",
    "sg:address":"Calle de Miguel Barroso, 11",
    "sg:city":"Alcazar S. Juan",
    "sg:orig_category":"Ropa Para Se\u00d1oras (al Por Menor)",
    "sg:phone":"+34 926 55 21 24",
    "sg:postcode":"13600",
    "sg:province":"Ciudad Real",
    "wof:name":"Pilar Prieto Gumiel S.l.",
    "wof:placetype":"venue"
},
  "geometry": {"coordinates":[-3.2082140446,39.3909683228],"type":"Point"}
}