{
  "type": "Feature",
  "properties": {
    "addr:full":"Rond Guinardo, 70 Barcelona Barcelona 08025",
    "addr:housenumber":"70",
    "addr:postcode":"08025",
    "addr:street":"Guinardo",
    "iso:country":"ES",
    "sg:address":"Rond Guinardo, 70",
    "sg:city":"Barcelona",
    "sg:orig_category":"Oficinas: Suministros Para (fabricaci\u00d3n, Al Por Mayor)",
    "sg:phone":"+34 934 55 12 12",
    "sg:postcode":"08025",
    "sg:province":"Barcelona",
    "wof:name":"Univex S. A.",
    "wof:placetype":"venue"
},
  "geometry": {"coordinates":[2.1694040298,41.4129867554],"type":"Point"}
}