{
  "type": "Feature",
  "properties": {
    "addr:full":"C/ Aurelio Coquillat Pascual, 18 Elche Alicante 03201",
    "addr:housenumber":"18",
    "addr:postcode":"03201",
    "addr:street":"C / Aurelio Coquillat Pascual",
    "iso:country":"ES",
    "sg:address":"C/ Aurelio Coquillat Pascual, 18",
    "sg:city":"Elche",
    "sg:orig_category":"Asesor\u00cda Fiscal Y Jur\u00cddica",
    "sg:phone":"+34 966 66 25 79",
    "sg:postcode":"03201",
    "sg:province":"Alicante",
    "wof:name":"Prada & Navarro Asociados S.l.",
    "wof:placetype":"venue"
},
  "geometry": {"coordinates":[-0.7119169831,38.2634048462],"type":"Point"}
}