{
  "type": "Feature",
  "properties": {
    "addr:full":"Port Torredembarra, S/n Torredembarra Tarragona 43830",
    "addr:housenumber":"s / n",
    "addr:postcode":"43830",
    "iso:country":"ES",
    "sg:address":"Port Torredembarra, S/n",
    "sg:city":"Torredembarra",
    "sg:orig_category":"Fabricaci\u00d3n, Reparaci\u00d3n Y Mantenimiento De Construcciones Navales Y Fluviales",
    "sg:phone":"+34 977 64 38 67",
    "sg:postcode":"43830",
    "sg:province":"Tarragona",
    "wof:name":"Granell Mercade Manel",
    "wof:placetype":"venue"
},
  "geometry": {"coordinates":[1.395424962,41.1436691284],"type":"Point"}
}