{
  "type": "Feature",
  "properties": {
    "iso:country":"ES",
    "sg:address":"Calle de Doctor Mara\u00d1on, 14",
    "sg:city":"Villanueva De Los Infantes",
    "sg:orig_category":"Carnicer\u00cdas, Carnicer\u00cdas",
    "sg:phone":"+34 926 36 06 36",
    "sg:postcode":"13320",
    "sg:province":"Ciudad Real",
    "wof:name":"Carrizosa Sancho Maria Teresa",
    "wof:placetype":"venue"
},
  "geometry": {"coordinates":[-3.0131208897,38.7331771851],"type":"Point"}
}