{
  "type": "Feature",
  "properties": {
    "addr:full":"Calle de Ayala, 17 Madrid Madrid 28001",
    "addr:housenumber":"17",
    "addr:postcode":"madrid;28001",
    "addr:street":"Calle De Ayala",
    "iso:country":"ES",
    "sg:address":"Calle de Ayala, 17",
    "sg:city":"Madrid",
    "sg:orig_category":"Inmobiliaria (agencias)",
    "sg:phone":"+34 915 77 93 41",
    "sg:postcode":"28001",
    "sg:province":"Madrid",
    "wof:name":"Serrano 33 S.a.",
    "wof:placetype":"venue"
},
  "geometry": {"coordinates":[-3.6860060692,40.4279251099],"type":"Point"}
}