{
  "type": "Feature",
  "properties": {
    "iso:country":"ES",
    "sg:address":"Calle de Olivar Grande, 1",
    "sg:city":"Guadamur",
    "sg:orig_category":"Trabajos De Perforaciones, Sondeos, Construcci\u00d3n De Pozos",
    "sg:phone":"+34 925 37 19 70",
    "sg:postcode":"45160",
    "sg:province":"Toledo",
    "sg:website":"www.captagua.com",
    "wof:name":"Captagua S.l.",
    "wof:placetype":"venue"
},
  "geometry": {"coordinates":[-4.1439538002,39.7991142273],"type":"Point"}
}