{
  "type": "Feature",
  "properties": {
    "addr:full":"Calle de Azeta, 2 Portugalete Vizcaya 48920",
    "addr:housenumber":"2",
    "addr:postcode":"48920",
    "addr:street":"Calle De Azeta",
    "iso:country":"ES",
    "sg:address":"Calle de Azeta, 2",
    "sg:city":"Portugalete",
    "sg:orig_category":"Mec\u00c1nico Del Autom\u00d3vil",
    "sg:phone":"+34 946 08 16 50",
    "sg:postcode":"48920",
    "sg:province":"Vizcaya",
    "wof:name":"Garaje Azeta, S.l.",
    "wof:placetype":"venue"
},
  "geometry": {"coordinates":[-3.0126502514,43.3147392273],"type":"Point"}
}