{
  "type": "Feature",
  "properties": {
    "iso:country":"ES",
    "sg:address":"Calle de Fuente Del Berro, 1",
    "sg:city":"Madrid",
    "sg:orig_category":"Inmobiliaria (agencias)",
    "sg:phone":"+34 914 02 58 98",
    "sg:postcode":"28009",
    "sg:province":"Madrid",
    "sg:website":"www.inmopazo.com",
    "wof:name":"Inmobiliaria Berenguela Pazo S.l.l.",
    "wof:placetype":"venue"
},
  "geometry": {"coordinates":[-3.6707339287,40.4270553589],"type":"Point"}
}