{
  "type": "Feature",
  "properties": {
    "addr:full":"Calle de Capitan Vigueras, 1 Sevilla Sevilla 41004",
    "addr:housenumber":"1",
    "addr:postcode":"41004",
    "addr:street":"Calle De Capitan Vigueras",
    "iso:country":"ES",
    "sg:address":"Calle de Capitan Vigueras, 1",
    "sg:city":"Sevilla",
    "sg:orig_category":"M\u00c9dicos: Ginecolog\u00cda Y Obstetricia",
    "sg:phone":"+34 954 42 46 60",
    "sg:postcode":"41004",
    "sg:province":"Sevilla",
    "wof:name":"Carranza Moreno Manuel",
    "wof:placetype":"venue"
},
  "geometry": {"coordinates":[-5.9867224693,37.3828392029],"type":"Point"}
}