{
  "type": "Feature",
  "properties": {
    "addr:full":"Prqu Nacal Do\u00f1ana, 23 Daimiel Ciudad Real 13250",
    "addr:housenumber":"23",
    "addr:postcode":"13250",
    "addr:street":"Don\u0303Ana",
    "iso:country":"ES",
    "sg:address":"Prqu Nacal Do\u00f1ana, 23",
    "sg:city":"Daimiel",
    "sg:orig_category":"Promotores Constructores",
    "sg:phone":"+34 926 85 02 51",
    "sg:postcode":"13250",
    "sg:province":"Ciudad Real",
    "wof:name":"Grupo Barbero Terrifa",
    "wof:placetype":"venue"
},
  "geometry": {"coordinates":[-3.609513998,39.076789856],"type":"Point"}
}