{
  "type": "Feature",
  "properties": {
    "iso:country":"ES",
    "sg:address":"Calle de Alcalde Guillermo Perez G, 13",
    "sg:city":"Cartaya",
    "sg:orig_category":"Reposter\u00cdas",
    "sg:phone":"+34 959 39 00 39",
    "sg:postcode":"21450",
    "sg:province":"Huelva",
    "wof:name":"Rodriguez Sobrado Luis",
    "wof:placetype":"venue"
},
  "geometry": {"coordinates":[-7.1574783325,37.3158111572],"type":"Point"}
}