{
  "type": "Feature",
  "properties": {
    "addr:full":"Calle de Hibisco, 2 Badajoz Badajoz 06011",
    "addr:housenumber":"2",
    "addr:postcode":"06011",
    "addr:street":"Calle De Hibisco",
    "iso:country":"ES",
    "sg:address":"Calle de Hibisco, 2",
    "sg:city":"Badajoz",
    "sg:orig_category":"Productos Alimentarios",
    "sg:phone":"+34 924 23 51 92",
    "sg:postcode":"06011",
    "sg:province":"Badajoz",
    "wof:name":"Agrovalladares S.l.",
    "wof:placetype":"venue"
},
  "geometry": {"coordinates":[-6.9882512093,38.8577804565],"type":"Point"}
}