{
  "type": "Feature",
  "properties": {
    "addr:full":"Calle de Gran Via, S/n Alacant Alicante 03009",
    "addr:housenumber":"/ n",
    "addr:postcode":"03009",
    "addr:street":"Calle De Gran Via S",
    "iso:country":"ES",
    "sg:address":"Calle de Gran Via, S/n",
    "sg:city":"Alacant",
    "sg:classifiers":[
        {
            "category":"Cinema",
            "subcategory":"Movie Theater",
            "type":"Entertainment"
        }
    ],
    "sg:phone":"+34 965 24 96 21",
    "sg:postcode":"03009",
    "sg:province":"Alicante",
    "sg:tags":[
        "salas",
        "de",
        "cine"
    ],
    "wof:name":"Fapecla S.a.",
    "wof:placetype":"venue"
},
  "geometry": {"coordinates":[-0.4944190085,38.3618583679],"type":"Point"}
}