{
  "type": "Feature",
  "properties": {
    "iso:country":"ES",
    "sg:address":"Kontzezino Kalea, 15",
    "sg:city":"Arrasate",
    "sg:orig_category":"Asociaciones Y Clubs Deportivos",
    "sg:phone":"+34 943 79 97 31",
    "sg:postcode":"20500",
    "sg:province":"Guip\u00f9zcoa",
    "wof:name":"Jose Ignacio Mu\u00f1oz Perez Y Otros C.b.",
    "wof:placetype":"venue"
},
  "geometry": {"coordinates":[-2.4910161495,43.0640525818],"type":"Point"}
}