{
  "type": "Feature",
  "properties": {
    "addr:full":"Avda Gran Via Rey Juan Carlos I, 14 Logro\u00f1o La Rioja 26002",
    "addr:housenumber":"14",
    "addr:postcode":"26002",
    "addr:street":"Avda Gran Via Rey Juan Carlos I;Rioja",
    "iso:country":"ES",
    "sg:address":"Avda Gran Via Rey Juan Carlos I, 14",
    "sg:city":"Logro\u00f1o",
    "sg:orig_category":"Asesor\u00cdas Y Estudios Financieros",
    "sg:phone":"+34 941 22 13 15",
    "sg:postcode":"26002",
    "sg:province":"La Rioja",
    "wof:name":"Peche Echeverria Jose",
    "wof:placetype":"venue"
},
  "geometry": {"coordinates":[-2.4474198818,42.4636077881],"type":"Point"}
}