{
  "type": "Feature",
  "properties": {
    "iso:country":"ES",
    "sg:address":"Rua Calvo Sotelo, 104",
    "sg:city":"Sarria",
    "sg:orig_category":"Pizzer\u00cdas",
    "sg:phone":"+34 982 53 16 84",
    "sg:postcode":"27600",
    "sg:province":"Lugo",
    "wof:name":"Pizarras Del Oribio S.l.",
    "wof:placetype":"venue"
},
  "geometry": {"coordinates":[-7.4119791985,42.7793312073],"type":"Point"}
}