{
  "type": "Feature",
  "properties": {
    "addr:full":"Calle de Nuestra Sra. Del Amor Hermoso (de), 7 Coslada Madrid 28820",
    "addr:housenumber":"7",
    "addr:postcode":"28820",
    "addr:street":"Calle De Nuestra Sra. Del Amor Hermoso De",
    "iso:country":"ES",
    "sg:address":"Calle de Nuestra Sra. Del Amor Hermoso (de), 7",
    "sg:city":"Coslada",
    "sg:orig_category":"Librer\u00cdas",
    "sg:phone":"+34 916 73 69 69",
    "sg:postcode":"28820",
    "sg:province":"Madrid",
    "wof:name":"Lopez Arias Antonio",
    "wof:placetype":"venue"
},
  "geometry": {"coordinates":[-3.5633904934,40.4260253906],"type":"Point"}
}