{
  "type": "Feature",
  "properties": {
    "addr:full":"Calle de Lagasca, 12 Madrid Madrid 28001",
    "addr:housenumber":"12",
    "addr:postcode":"madrid;28001",
    "addr:street":"Calle De Lagasca",
    "iso:country":"ES",
    "sg:address":"Calle de Lagasca, 12",
    "sg:city":"Madrid",
    "sg:orig_category":"Centros Empresariales",
    "sg:phone":"+34 914 31 61 75",
    "sg:postcode":"28001",
    "sg:province":"Madrid",
    "wof:name":"Lopez Lozano Miguel Angel",
    "wof:placetype":"venue"
},
  "geometry": {"coordinates":[-3.6857814789,40.4215011597],"type":"Point"}
}