{
  "type": "Feature",
  "properties": {
    "iso:country":"ES",
    "sg:address":"Plaz Tirso De Molina, 15",
    "sg:city":"Madrid",
    "sg:orig_category":"Fiesta: Art\u00cdculos De (al Por Menor)",
    "sg:phone":"+34 914 29 53 84",
    "sg:postcode":"28012",
    "sg:province":"Madrid",
    "wof:name":"Noly Fuentes S.l.",
    "wof:placetype":"venue"
},
  "geometry": {"coordinates":[-3.7049520016,40.4126243591],"type":"Point"}
}