{
  "type": "Feature",
  "properties": {
    "iso:country":"ES",
    "sg:address":"Calle de Real Allende, 42",
    "sg:city":"Miranda Ebro",
    "sg:orig_category":"Bisuter\u00cda, Joyer\u00cda, Relojer\u00cda (al Por Menor)",
    "sg:phone":"+34 947 33 32 96",
    "sg:postcode":"09200",
    "sg:province":"Burgos",
    "wof:name":"Joyeria Hugo",
    "wof:placetype":"venue"
},
  "geometry": {"coordinates":[-2.9494879246,42.6843910217],"type":"Point"}
}