{
  "type": "Feature",
  "properties": {
    "iso:country":"ES",
    "sg:address":"Calle de Camino Viejo (del), 20",
    "sg:city":"Alcobendas",
    "sg:orig_category":"Inmobiliaria (agencias)",
    "sg:phone":"+34 916 25 01 12",
    "sg:postcode":"28109",
    "sg:province":"Madrid",
    "wof:name":"Corporacion Oudaloi S.a.",
    "wof:placetype":"venue"
},
  "geometry": {"coordinates":[-3.5435080528,40.5270233154],"type":"Point"}
}