{
  "type": "Feature",
  "properties": {
    "addr:full":"Calle de Gran Via De Jose Antonio Agirre Y Lekube Sestao Vizcaya 48910",
    "addr:postcode":"48910",
    "addr:street":"Calle De Gran Via De Jose Antonio Agirre Y Lekube",
    "iso:country":"ES",
    "sg:address":"Calle de Gran Via De Jose Antonio Agirre Y Lekube",
    "sg:city":"Sestao",
    "sg:orig_category":"Sanatorios M\u00c9dico",
    "sg:phone":"+34 946 00 78 80",
    "sg:postcode":"48910",
    "sg:province":"Vizcaya",
    "wof:name":"Osakidetza",
    "wof:placetype":"venue"
},
  "geometry": {"coordinates":[-3.007666111,43.3094024658],"type":"Point"}
}