{
  "type": "Feature",
  "properties": {
    "addr:full":"Calle de Lerida, 80 Madrid Madrid 28020",
    "addr:housenumber":"80",
    "addr:postcode":"madrid;28020",
    "addr:street":"Calle De Lerida",
    "iso:country":"ES",
    "sg:address":"Calle de Lerida, 80",
    "sg:city":"Madrid",
    "sg:orig_category":"Cuartos De Ba\u00d1o: Aparatos Sanitarios (fabricaci\u00d3n)",
    "sg:phone":"+34 915 79 40 31",
    "sg:postcode":"28020",
    "sg:province":"Madrid",
    "wof:name":"Solados Y Alicatados Rohe",
    "wof:placetype":"venue"
},
  "geometry": {"coordinates":[-3.7003409863,40.455329895],"type":"Point"}
}