{
  "type": "Feature",
  "properties": {
    "addr:full":"Carrer de Lepant, 284 Barcelona Barcelona 08013",
    "addr:housenumber":"284",
    "addr:postcode":"08013",
    "addr:street":"Carrer De Lepant",
    "iso:country":"ES",
    "sg:address":"Carrer de Lepant, 284",
    "sg:city":"Barcelona",
    "sg:classifiers":[
        {
            "category":"Autos & Motor Vehicles",
            "subcategory":"Automobile Sales",
            "type":"Retail Goods"
        }
    ],
    "sg:phone":"+34 934 36 08 98",
    "sg:postcode":"08013",
    "sg:province":"Barcelona",
    "wof:name":"Garcia De La Hera Antonio",
    "wof:placetype":"venue"
},
  "geometry": {"coordinates":[2.1762609482,41.4049797058],"type":"Point"}
}