{
  "type": "Feature",
  "properties": {
    "addr:full":"Ctra Murcia (de), 102 Cehegin Murcia 30430",
    "addr:housenumber":"102",
    "addr:postcode":"30430",
    "addr:street":"Ctra Murcia De",
    "iso:country":"ES",
    "sg:address":"Ctra Murcia (de), 102",
    "sg:city":"Cehegin",
    "sg:orig_category":"Productores Recolectores, Venta Directa De Vinos",
    "sg:phone":"+34 968 74 00 27",
    "sg:postcode":"30430",
    "sg:province":"Murcia",
    "wof:name":"Garcia Zarco Antonio",
    "wof:placetype":"venue"
},
  "geometry": {"coordinates":[-1.7878390551,38.0865287781],"type":"Point"}
}