{
  "type": "Feature",
  "properties": {
    "addr:full":"Calle de Don Quijote, 4 Elda Alicante 03600",
    "addr:housenumber":"4",
    "addr:postcode":"03600",
    "addr:street":"Calle De Don Quijote",
    "iso:country":"ES",
    "sg:address":"Calle de Don Quijote, 4",
    "sg:city":"Elda",
    "sg:orig_category":"Electrodom\u00c9sticos (al Por Menor)",
    "sg:phone":"+34 965 39 47 29",
    "sg:postcode":"03600",
    "sg:province":"Alicante",
    "wof:name":"Rico Pastor Jose Luis",
    "wof:placetype":"venue"
},
  "geometry": {"coordinates":[-0.7914248705,38.4766235352],"type":"Point"}
}