{
  "type": "Feature",
  "properties": {
    "addr:full":"Ptda Capsades, 13 Denia Alicante 03700",
    "addr:housenumber":"13",
    "addr:postcode":"03700",
    "addr:street":"Ptda Capsades",
    "iso:country":"ES",
    "sg:address":"Ptda Capsades, 13",
    "sg:city":"Denia",
    "sg:orig_category":"Guarder\u00cdas",
    "sg:phone":"+34 966 42 50 65",
    "sg:postcode":"03700",
    "sg:province":"Alicante",
    "wof:name":"Martinez Martinez Araceli",
    "wof:placetype":"venue"
},
  "geometry": {"coordinates":[0.1039630026,38.8354949951],"type":"Point"}
}