{
  "type": "Feature",
  "properties": {
    "iso:country":"ES",
    "sg:address":"Pase San Frantzisko Ibiltokia, 39",
    "sg:city":"Tolosa",
    "sg:orig_category":"Tejidos (al Por Menor)",
    "sg:phone":"+34 943 65 22 38",
    "sg:postcode":"20400",
    "sg:province":"Guip\u00f9zcoa",
    "wof:name":"Amaya Rojo Garikano Y Otra C.b.",
    "wof:placetype":"venue"
},
  "geometry": {"coordinates":[-2.0779650211,43.1340827942],"type":"Point"}
}