{
  "type": "Feature",
  "properties": {
    "addr:full":"Calle de Sarrikobaso, 29 Algorta Vizcaya 48993",
    "addr:housenumber":"29",
    "addr:postcode":"48993",
    "addr:street":"Calle De Sarrikobaso",
    "iso:country":"ES",
    "sg:address":"Calle de Sarrikobaso, 29",
    "sg:city":"Algorta",
    "sg:orig_category":"Electrodom\u00c9sticos (al Por Menor)",
    "sg:phone":"+34 944 30 78 89",
    "sg:postcode":"48993",
    "sg:province":"Vizcaya",
    "wof:name":"Electrodomesticos Sarriko S.l.",
    "wof:placetype":"venue"
},
  "geometry": {"coordinates":[-3.0094490051,43.3579864502],"type":"Point"}
}