{
  "type": "Feature",
  "properties": {
    "addr:full":"Carrer de Sant Lloren\u00c7, 29 Sant Feliu Llobregat Barcelona 08980",
    "addr:housenumber":"29",
    "addr:postcode":"08980",
    "addr:street":"Carrer De Sant Llorenc\u0327",
    "iso:country":"ES",
    "sg:address":"Carrer de Sant Lloren\u00c7, 29",
    "sg:city":"Sant Feliu Llobregat",
    "sg:orig_category":"Contables",
    "sg:phone":"+34 936 85 08 37",
    "sg:postcode":"08980",
    "sg:province":"Barcelona",
    "wof:name":"Gestio I Estudis Administratius S.l.",
    "wof:placetype":"venue"
},
  "geometry": {"coordinates":[2.0493900776,41.3808822632],"type":"Point"}
}