{
  "type": "Feature",
  "properties": {
    "addr:full":"Avda Pais Valenciano, 22 Alaquas Valencia 46970",
    "addr:housenumber":"22",
    "addr:postcode":"46970",
    "addr:street":"Avda Pais Valenciano",
    "iso:country":"ES",
    "sg:address":"Avda Pais Valenciano, 22",
    "sg:city":"Alaquas",
    "sg:orig_category":"Panader\u00cdas, Panader\u00cdas",
    "sg:phone":"+34 961 50 32 57",
    "sg:postcode":"46970",
    "sg:province":"Valencia",
    "wof:name":"Marti Perales Rafael",
    "wof:placetype":"venue"
},
  "geometry": {"coordinates":[-0.4585190117,39.4553833008],"type":"Point"}
}