{
  "type": "Feature",
  "properties": {
    "iso:country":"ES",
    "sg:address":"Rua Telleiro (do), 20",
    "sg:city":"Reboredo",
    "sg:orig_category":"Empresarios Y Productoras De Espect\u00c1culos",
    "sg:phone":"+34 988 25 15 05",
    "sg:postcode":"32915",
    "sg:province":"Ourense",
    "sg:website":"www.chevereanimacion.com",
    "wof:name":"Iglesias Rodriguez Sergio",
    "wof:placetype":"venue"
},
  "geometry": {"coordinates":[-7.8368210793,42.2873077393],"type":"Point"}
}