{
  "type": "Feature",
  "properties": {
    "iso:country":"ES",
    "sg:address":"Ptda Altabix, S/n",
    "sg:city":"Elche",
    "sg:orig_category":"Asociaciones Y Clubs Deportivos",
    "sg:phone":"+34 965 45 01 66",
    "sg:postcode":"03291",
    "sg:province":"Alicante",
    "wof:name":"Club De Campo Elche",
    "wof:placetype":"venue"
},
  "geometry": {"coordinates":[-0.6765189767,38.2994346619],"type":"Point"}
}