{
  "type": "Feature",
  "properties": {
    "iso:country":"ES",
    "sg:address":"Pase Chopera, 13",
    "sg:city":"Madrid",
    "sg:orig_category":"Productos Refractarios (fabricaci\u00d3n, Al Por Mayor)",
    "sg:phone":"+34 914 73 86 64",
    "sg:postcode":"28045",
    "sg:province":"Madrid",
    "wof:name":"Arocena Mericaechevarria Ramon Maria",
    "wof:placetype":"venue"
},
  "geometry": {"coordinates":[-3.701518774,40.3963356018],"type":"Point"}
}