{
  "type": "Feature",
  "properties": {
    "addr:full":"Carrer de Bergara, 42 S. Cugat Valles Barcelona 08172",
    "addr:housenumber":"42",
    "addr:postcode":"08172",
    "addr:street":"Carrer De Bergara;S. Cugat Valles Barcelona",
    "iso:country":"ES",
    "sg:address":"Carrer de Bergara, 42",
    "sg:city":"S. Cugat Valles",
    "sg:orig_category":"Inmobiliaria (agencias)",
    "sg:phone":"+34 936 74 02 33",
    "sg:postcode":"08172",
    "sg:province":"Barcelona",
    "wof:name":"Rovibat S.l.",
    "wof:placetype":"venue"
},
  "geometry": {"coordinates":[2.0839710236,41.466468811],"type":"Point"}
}