{
  "type": "Feature",
  "properties": {
    "iso:country":"ES",
    "sg:address":"Avda Miguel De Cervantes, 17",
    "sg:city":"Tarancon",
    "sg:orig_category":"Ropa Para Se\u00d1oras Y Caballeros (al Por Menor)",
    "sg:phone":"+34 969 32 59 93",
    "sg:postcode":"16400",
    "sg:province":"Cuenca",
    "wof:name":"Riadi Moda Sl",
    "wof:placetype":"venue"
},
  "geometry": {"coordinates":[-3.0078918934,40.010559082],"type":"Point"}
}