{
  "type": "Feature",
  "properties": {
    "iso:country":"ES",
    "sg:address":"Carrer de Angel Guimera, 32",
    "sg:city":"Barcelona",
    "sg:orig_category":"Ingenier\u00cda, Centros De Estudios (diversos)",
    "sg:phone":"+34 932 06 30 33",
    "sg:postcode":"08017",
    "sg:province":"Barcelona",
    "wof:name":"I.p.ingenieria Industrial",
    "wof:placetype":"venue"
},
  "geometry": {"coordinates":[2.1321389675,41.3970489502],"type":"Point"}
}