{
  "type": "Feature",
  "properties": {
    "iso:country":"ES",
    "sg:address":"Calle de General Riera, 116",
    "sg:city":"Palma",
    "sg:orig_category":"Ropa Para Ni\u00d1os (al Por Menor)",
    "sg:phone":"+34 971 29 05 09",
    "sg:postcode":"07010",
    "sg:province":"Islas Baleares",
    "wof:name":"Jaroso Prieto Ana",
    "wof:placetype":"venue"
},
  "geometry": {"coordinates":[2.6458528042,39.5883255005],"type":"Point"}
}