{
  "type": "Feature",
  "properties": {
    "iso:country":"ES",
    "sg:address":"Carrer de Mossen Jacint Verdaguer, 125",
    "sg:city":"S. Boi Llobregat",
    "sg:orig_category":"Asesor\u00cda Sobre Comunicaci\u00d3n De Empresas",
    "sg:phone":"+34 936 52 72 89",
    "sg:postcode":"08830",
    "sg:province":"Barcelona",
    "wof:name":"Asemreca S.l.u.",
    "wof:placetype":"venue"
},
  "geometry": {"coordinates":[2.0423088074,41.3393936157],"type":"Point"}
}