{
  "type": "Feature",
  "properties": {
    "iso:country":"ES",
    "sg:address":"Rua Serra San Mamede, 36",
    "sg:city":"Ourense",
    "sg:orig_category":"Empresarios",
    "sg:phone":"+34 988 25 04 81",
    "sg:postcode":"32005",
    "sg:province":"Ourense",
    "wof:name":"Campos Salgado Maximino",
    "wof:placetype":"venue"
},
  "geometry": {"coordinates":[-7.8561477661,42.3296928406],"type":"Point"}
}