{
  "type": "Feature",
  "properties": {
    "addr:full":"Praz Maior, 21 Baralla Lugo 27680",
    "addr:housenumber":"21",
    "addr:postcode":"27680",
    "addr:street":"Praz Maior",
    "iso:country":"ES",
    "sg:address":"Praz Maior, 21",
    "sg:city":"Baralla",
    "sg:orig_category":"Molduras, Junquillos, Listones Y Molduras Perforadas",
    "sg:phone":"+34 982 36 33 41",
    "sg:postcode":"27680",
    "sg:province":"Lugo",
    "wof:name":"Fernandez Fernandez Concepcion",
    "wof:placetype":"venue"
},
  "geometry": {"coordinates":[-7.2496991158,42.8941955566],"type":"Point"}
}