{
  "type": "Feature",
  "properties": {
    "addr:full":"Carr Blasco Iba\u00d1ez, 12 Silla Valencia 46460",
    "addr:housenumber":"12",
    "addr:postcode":"46460",
    "addr:street":"Carr Blasco Iban\u0303Ez",
    "iso:country":"ES",
    "sg:address":"Carr Blasco Iba\u00d1ez, 12",
    "sg:city":"Silla",
    "sg:orig_category":"Carnicer\u00cdas, Carnicer\u00cdas",
    "sg:phone":"+34 961 20 04 66",
    "sg:postcode":"46460",
    "sg:province":"Valencia",
    "wof:name":"Lopez Ramon Jose",
    "wof:placetype":"venue"
},
  "geometry": {"coordinates":[-0.4112359881,39.365524292],"type":"Point"}
}