{
  "type": "Feature",
  "properties": {
    "iso:country":"ES",
    "sg:address":"Carrer de Mare De Les Aigues, 2",
    "sg:city":"Sabadell",
    "sg:orig_category":"Ense\u00d1anza, Formaci\u00d3n Profesional: Aprendizaje",
    "sg:phone":"+34 937 23 74 17",
    "sg:postcode":"08206",
    "sg:province":"Barcelona",
    "wof:name":"Instituto Tecnico Ense\u00f1anza Media Fernando Casablancas",
    "wof:placetype":"venue"
},
  "geometry": {"coordinates":[2.0922238827,41.5612754822],"type":"Point"}
}