{
  "type": "Feature",
  "properties": {
    "addr:full":"Carr Ferran Agullo, 3 Girona Girona 17001",
    "addr:housenumber":"3",
    "addr:postcode":"17001",
    "addr:street":"Carr Ferran Agullo",
    "iso:country":"ES",
    "sg:address":"Carr Ferran Agullo, 3",
    "sg:city":"Girona",
    "sg:orig_category":"Arquitectos",
    "sg:phone":"+34 972 41 03 84",
    "sg:postcode":"17001",
    "sg:province":"Girona",
    "wof:name":"Roca Vila Iban",
    "wof:placetype":"venue"
},
  "geometry": {"coordinates":[2.819715023,41.9811210632],"type":"Point"}
}