{
  "type": "Feature",
  "properties": {
    "addr:full":"Carrer de Pins Vens, 24 Sitges Barcelona 08870",
    "addr:housenumber":"24",
    "addr:postcode":"08870",
    "addr:street":"Carrer De Pins Vens",
    "iso:country":"ES",
    "sg:address":"Carrer de Pins Vens, 24",
    "sg:city":"Sitges",
    "sg:orig_category":"Electricidad: Instaladores",
    "sg:phone":"+34 938 94 58 36",
    "sg:postcode":"08870",
    "sg:province":"Barcelona",
    "wof:name":"Jordi Ruiz Garcia S.l.",
    "wof:placetype":"venue"
},
  "geometry": {"coordinates":[1.8120900393,41.2417831421],"type":"Point"}
}