{
  "type": "Feature",
  "properties": {
    "addr:full":"Calle de Poeta Miguel Hernandez, 20 Santa Pola Alicante 03130",
    "addr:housenumber":"20",
    "addr:postcode":"03130",
    "addr:street":"Calle De Poeta Miguel Hernandez",
    "iso:country":"ES",
    "sg:address":"Calle de Poeta Miguel Hernandez, 20",
    "sg:city":"Santa Pola",
    "sg:orig_category":"Controles De Edificaci\u00d3n (construcci\u00d3n, Seguridad)",
    "sg:phone":"+34 965 41 19 42",
    "sg:postcode":"03130",
    "sg:province":"Alicante",
    "wof:name":"Smart Build Spain S.l.",
    "wof:placetype":"venue"
},
  "geometry": {"coordinates":[-0.5570009947,38.1915779114],"type":"Point"}
}