{
  "type": "Feature",
  "properties": {
    "iso:country":"ES",
    "sg:address":"Calle de Santa Engracia, 62",
    "sg:city":"Madrid",
    "sg:orig_category":"Centros Empresariales",
    "sg:phone":"+34 914 45 47 62",
    "sg:postcode":"28010",
    "sg:province":"Madrid",
    "wof:name":"Euro Latin Sagin S.l.",
    "wof:placetype":"venue"
},
  "geometry": {"coordinates":[-3.6988289356,40.4355926514],"type":"Point"}
}