{
  "type": "Feature",
  "properties": {
    "addr:full":"Avgd Marti Pujol, 529 Badalona Barcelona 08917",
    "addr:housenumber":"529",
    "addr:postcode":"08917",
    "addr:street":"Pujol",
    "iso:country":"ES",
    "sg:address":"Avgd Marti Pujol, 529",
    "sg:city":"Badalona",
    "sg:orig_category":"Promotores Constructores",
    "sg:phone":"+34 934 65 28 38",
    "sg:postcode":"08917",
    "sg:province":"Barcelona",
    "wof:name":"Grupo De Empresa Ros S.l.",
    "wof:placetype":"venue"
},
  "geometry": {"coordinates":[2.2405500412,41.4589309692],"type":"Point"}
}