{
  "type": "Feature",
  "properties": {
    "addr:full":"Carrer de Moreres (les), 57 Prat Llobregat Barcelona 08820",
    "addr:housenumber":"57",
    "addr:postcode":"08820",
    "addr:street":"Carrer De Moreres Les;Llobregat",
    "iso:country":"ES",
    "sg:address":"Carrer de Moreres (les), 57",
    "sg:city":"Prat Llobregat",
    "sg:orig_category":"Cooperativas Agr\u00cdcolas",
    "sg:phone":"+34 933 70 88 77",
    "sg:postcode":"08820",
    "sg:province":"Barcelona",
    "wof:name":"Cooperativa Agricola Del Prat S.coop.ltda.",
    "wof:placetype":"venue"
},
  "geometry": {"coordinates":[2.1025300026,41.331489563],"type":"Point"}
}