{
  "type": "Feature",
  "properties": {
    "addr:full":"Calle de San Pedro El Verde, 49 Toledo Toledo 45004",
    "addr:housenumber":"49",
    "addr:postcode":"45004",
    "addr:street":"Calle De San Pedro El Verde",
    "iso:country":"ES",
    "sg:address":"Calle de San Pedro El Verde, 49",
    "sg:city":"Toledo",
    "sg:orig_category":"Arquitectos",
    "sg:phone":"+34 925 21 25 23",
    "sg:postcode":"45004",
    "sg:province":"Toledo",
    "wof:name":"Diaz-roncero Santiago Fernando Jose",
    "wof:placetype":"venue"
},
  "geometry": {"coordinates":[-4.040763855,39.8715553284],"type":"Point"}
}