{
  "type": "Feature",
  "properties": {
    "iso:country":"ES",
    "sg:address":"Avda La Libertad, 17",
    "sg:city":"San Vicente De Barakaldo",
    "sg:classifiers":[
        {
            "category":"Taxi",
            "type":"Transportation"
        }
    ],
    "sg:phone":"+34 944 37 11 56",
    "sg:postcode":"48901",
    "sg:province":"Vizcaya",
    "wof:name":"Ayuntamiento De Baracaldo",
    "wof:placetype":"venue"
},
  "geometry": {"coordinates":[-2.9906899929,43.2968101501],"type":"Point"}
}