{
  "type": "Feature",
  "properties": {
    "iso:country":"ES",
    "sg:address":"Pol Ind Los Alamos, 2",
    "sg:city":"Atarfe",
    "sg:orig_category":"Promotores Constructores",
    "sg:phone":"+34 958 43 49 63",
    "sg:postcode":"18230",
    "sg:province":"Granada",
    "wof:name":"Metalurgica Eurosur S.l.",
    "wof:placetype":"venue"
},
  "geometry": {"coordinates":[-3.6903159618,37.2228775024],"type":"Point"}
}