{
  "type": "Feature",
  "properties": {
    "addr:full":"Rua Doctor Moreda, 4 Ribadeo Lugo 27700",
    "addr:housenumber":"4",
    "addr:postcode":"27700",
    "addr:street":"Rua Doctor Moreda",
    "iso:country":"ES",
    "sg:address":"Rua Doctor Moreda, 4",
    "sg:city":"Ribadeo",
    "sg:orig_category":"Droguer\u00cdas (al Por Menor)",
    "sg:phone":"+34 982 12 84 72",
    "sg:postcode":"27700",
    "sg:province":"Lugo",
    "wof:name":"Veiga Diaz Armando Da",
    "wof:placetype":"venue"
},
  "geometry": {"coordinates":[-7.0432229042,43.5362472534],"type":"Point"}
}