{
  "type": "Feature",
  "properties": {
    "addr:full":"Av Lleida (de), 93 Torrefarrera Lleida 25123",
    "addr:housenumber":"93",
    "addr:postcode":"25123",
    "addr:street":"Av;De",
    "iso:country":"ES",
    "sg:address":"Av Lleida (de), 93",
    "sg:city":"Torrefarrera",
    "sg:orig_category":"Empresas De Limpieza",
    "sg:phone":"+34 973 75 04 34",
    "sg:postcode":"25123",
    "sg:province":"Lleida",
    "wof:name":"Daniel Pibrall Maria Dolors",
    "wof:placetype":"venue"
},
  "geometry": {"coordinates":[0.6065319777,41.6680831909],"type":"Point"}
}