{
  "type": "Feature",
  "properties": {
    "iso:country":"ES",
    "sg:address":"Calle de Convento De San Francisco, 5",
    "sg:city":"Valencia",
    "sg:orig_category":"Abogados",
    "sg:phone":"+34 963 60 68 36",
    "sg:postcode":"46002",
    "sg:province":"Valencia",
    "wof:name":"Ortola Frasquet Juan",
    "wof:placetype":"venue"
},
  "geometry": {"coordinates":[-0.3777298927,39.4690475464],"type":"Point"}
}