{
  "type": "Feature",
  "properties": {
    "addr:full":"Calle de Pedrera, 33 Cespedosa Salamanca 37750",
    "addr:housenumber":"33",
    "addr:postcode":"37750",
    "addr:street":"Calle De Pedrera",
    "iso:country":"ES",
    "sg:address":"Calle de Pedrera, 33",
    "sg:city":"Cespedosa",
    "sg:orig_category":"Alfarer\u00cda",
    "sg:phone":"+34 923 15 26 66",
    "sg:postcode":"37750",
    "sg:province":"Salamanca",
    "wof:name":"Alfareria Hdez S.l.",
    "wof:placetype":"venue"
},
  "geometry": {"coordinates":[-5.5778889656,40.5431404114],"type":"Point"}
}