{
  "type": "Feature",
  "properties": {
    "iso:country":"ES",
    "sg:address":"Avda Modesto Lafuente, 15",
    "sg:city":"Palencia",
    "sg:orig_category":"Inmobiliaria (agencias)",
    "sg:phone":"+34 979 72 78 27",
    "sg:postcode":"34002",
    "sg:province":"Palencia",
    "wof:name":"Previler S.l.",
    "wof:placetype":"venue"
},
  "geometry": {"coordinates":[-4.5261111259,42.0057754517],"type":"Point"}
}