{
  "type": "Feature",
  "properties": {
    "addr:full":"Calle de General Picazo, 2 Minglanilla Cuenca 16260",
    "addr:housenumber":"2",
    "addr:postcode":"16260",
    "addr:street":"Calle De General Picazo",
    "iso:country":"ES",
    "sg:address":"Calle de General Picazo, 2",
    "sg:city":"Minglanilla",
    "sg:orig_category":"Cooperativas Agr\u00cdcolas",
    "sg:phone":"+34 962 18 71 42",
    "sg:postcode":"16260",
    "sg:province":"Cuenca",
    "wof:name":"Santisimo Cristo De La Salud Sociedad Cooperativa De Castilla La Mancha",
    "wof:placetype":"venue"
},
  "geometry": {"coordinates":[-1.5937490463,39.5361099243],"type":"Point"}
}