{
  "type": "Feature",
  "properties": {
    "addr:full":"Calle de Jose Maria Haro (magistrat), 18 Valencia Valencia 46022",
    "addr:housenumber":"18",
    "addr:postcode":"46022",
    "addr:street":"Calle De Jose Maria Haro Magistrat",
    "iso:country":"ES",
    "sg:address":"Calle de Jose Maria Haro (magistrat), 18",
    "sg:city":"Valencia",
    "sg:orig_category":"Mec\u00c1nico Del Autom\u00d3vil",
    "sg:phone":"+34 963 55 37 77",
    "sg:postcode":"46022",
    "sg:province":"Valencia",
    "wof:name":"Servalauto S. A.",
    "wof:placetype":"venue"
},
  "geometry": {"coordinates":[-0.3379920125,39.4696960449],"type":"Point"}
}