{
  "type": "Feature",
  "properties": {
    "iso:country":"ES",
    "sg:address":"Calle de Nieves (las), 9",
    "sg:city":"Ampuero",
    "sg:orig_category":"Grifer\u00cda Industrial",
    "sg:phone":"+34 942 62 84 14",
    "sg:postcode":"39840",
    "sg:province":"Cantabria",
    "wof:name":"Abalcanal S.l",
    "wof:placetype":"venue"
},
  "geometry": {"coordinates":[-3.413557,43.344116],"type":"Point"}
}