{
  "type": "Feature",
  "properties": {
    "iso:country":"ES",
    "sg:address":"Calle de Nu\u00d1ez De Balboa, 25",
    "sg:city":"Madrid",
    "sg:orig_category":"Art\u00cdculos De Decoraci\u00d3n",
    "sg:phone":"+34 914 31 33 10",
    "sg:postcode":"28001",
    "sg:province":"Madrid",
    "wof:name":"Sandra Marques S.l.",
    "wof:placetype":"venue"
},
  "geometry": {"coordinates":[-3.68303895,40.424156189],"type":"Point"}
}