{
  "type": "Feature",
  "properties": {
    "addr:full":"Calle de Chile, 1 Salamanca Salamanca 37003",
    "addr:housenumber":"1",
    "addr:postcode":"37003",
    "addr:street":"Calle De Chile",
    "iso:country":"ES",
    "sg:address":"Calle de Chile, 1",
    "sg:city":"Salamanca",
    "sg:orig_category":"Instalaci\u00d3n, Reparaci\u00d3n De Ascensores Y Montacargas",
    "sg:phone":"+34 923 12 05 67",
    "sg:postcode":"37003",
    "sg:province":"Salamanca",
    "wof:name":"Ascensores Salmantinos S.l.",
    "wof:placetype":"venue"
},
  "geometry": {"coordinates":[-5.6540136337,40.9654922485],"type":"Point"}
}