{
  "type": "Feature",
  "properties": {
    "iso:country":"ES",
    "sg:address":"Carrer de Cardenal Casa\u00d1as, 16",
    "sg:city":"Barcelona",
    "sg:orig_category":"Asociaciones, Organismos Culturales Y Socioeducativos",
    "sg:phone":"+34 933 02 70 88",
    "sg:postcode":"08002",
    "sg:province":"Barcelona",
    "wof:name":"El Prego Associacio Cultural",
    "wof:placetype":"venue"
},
  "geometry": {"coordinates":[2.1737070084,41.3820533752],"type":"Point"}
}