{
  "type": "Feature",
  "properties": {
    "addr:full":"Calle de Pozo Amarillo, 11 Salamanca Salamanca 37001",
    "addr:housenumber":"11",
    "addr:postcode":"37001",
    "addr:street":"Calle De Pozo Amarillo",
    "iso:country":"ES",
    "sg:address":"Calle de Pozo Amarillo, 11",
    "sg:city":"Salamanca",
    "sg:orig_category":"M\u00c9dicos: Estomatolog\u00cda",
    "sg:phone":"+34 923 21 17 00",
    "sg:postcode":"37001",
    "sg:province":"Salamanca",
    "wof:name":"Garcia Prieto Carlos",
    "wof:placetype":"venue"
},
  "geometry": {"coordinates":[-5.6625747681,40.9654922485],"type":"Point"}
}