{
  "type": "Feature",
  "properties": {
    "iso:country":"ES",
    "sg:address":"Calle de Bizkaia, 15",
    "sg:city":"San Vicente De Barakaldo",
    "sg:orig_category":"Molduras, Junquillos, Listones Y Molduras Perforadas",
    "sg:phone":"+34 944 38 42 38",
    "sg:postcode":"48901",
    "sg:province":"Vizcaya",
    "wof:name":"Rodriguez Lopez Maria Nieves",
    "wof:placetype":"venue"
},
  "geometry": {"coordinates":[-2.9877488613,43.2951774597],"type":"Point"}
}