{
  "type": "Feature",
  "properties": {
    "iso:country":"ES",
    "sg:address":"Avda Gustavo Adolfo Becquer, 3",
    "sg:city":"Nueva Andalucia",
    "sg:orig_category":"Molduras, Junquillos, Listones Y Molduras Perforadas",
    "sg:phone":"+34 952 81 31 89",
    "sg:postcode":"29660",
    "sg:province":"M\u00e1laga",
    "wof:name":"Stayman  John Helry",
    "wof:placetype":"venue"
},
  "geometry": {"coordinates":[-4.9801530838,36.5028800964],"type":"Point"}
}