{
  "type": "Feature",
  "properties": {
    "iso:country":"ES",
    "sg:address":"Calle de Miracruz, 15",
    "sg:city":"Donostia-san Sebastian",
    "sg:orig_category":"Carnicer\u00cdas, Carnicer\u00cdas",
    "sg:phone":"+34 943 28 92 34",
    "sg:postcode":"20001",
    "sg:province":"Guip\u00f9zcoa",
    "wof:name":"Irasporza Estensoro Pedro Pablo",
    "wof:placetype":"venue"
},
  "geometry": {"coordinates":[-1.9739010334,43.3221969604],"type":"Point"}
}