{
  "type": "Feature",
  "properties": {
    "addr:full":"Valle Oro, 5 Madrid Madrid 28019",
    "addr:housenumber":"5",
    "addr:postcode":"28019",
    "iso:country":"ES",
    "sg:address":"Valle Oro, 5",
    "sg:city":"Madrid",
    "sg:orig_category":"Molduras, Junquillos, Listones Y Molduras Perforadas",
    "sg:phone":"+34 914 71 10 66",
    "sg:postcode":"28019",
    "sg:province":"Madrid",
    "wof:name":"Herrero Pascual Luis",
    "wof:placetype":"venue"
},
  "geometry": {"coordinates":[-3.7293879986,40.3882026672],"type":"Point"}
}