{
  "type": "Feature",
  "properties": {
    "iso:country":"ES",
    "sg:address":"Rua Tomas A Alonso, 160",
    "sg:city":"Vigo",
    "sg:orig_category":"Productos Qu\u00cdmicos (fabricaci\u00d3n, Al Por Mayor)",
    "sg:phone":"+34 986 24 70 83",
    "sg:postcode":"36208",
    "sg:province":"Pontevedra",
    "sg:website":"www.adkemiberia.com",
    "wof:name":"Abkem Iberia S.l",
    "wof:placetype":"venue"
},
  "geometry": {"coordinates":[-8.744232,42.225266],"type":"Point"}
}