{
  "type": "Feature",
  "properties": {
    "iso:country":"ES",
    "sg:address":"Calle de Marques De San Esteban, 61",
    "sg:city":"Gijon",
    "sg:orig_category":"Ense\u00d1anza: Comercio, Gesti\u00d3n, Inform\u00c1tica",
    "sg:phone":"+34 985 34 29 75",
    "sg:postcode":"33206",
    "sg:province":"Asturias",
    "wof:name":"Seresco S.a.",
    "wof:placetype":"venue"
},
  "geometry": {"coordinates":[-5.6709361076,43.5412712097],"type":"Point"}
}