{
  "type": "Feature",
  "properties": {
    "addr:full":"Calle de Cruz Caridad, 14 Caridad Santa Cruz De Tenerife 38350",
    "addr:housenumber":"14",
    "addr:postcode":"38350",
    "addr:street":"Calle De Cruz Caridad",
    "iso:country":"ES",
    "sg:address":"Calle de Cruz Caridad, 14",
    "sg:city":"Caridad",
    "sg:orig_category":"Asociaciones Humanitarias, De Cooperaci\u00d3n, De Acci\u00d3n Social",
    "sg:phone":"+34 922 56 00 37",
    "sg:postcode":"38350",
    "sg:province":"Santa Cruz De Tenerife",
    "wof:name":"Asociacion De Empleados De Iberia Padres De Minusvalidos",
    "wof:placetype":"venue"
},
  "geometry": {"coordinates":[-16.3903141022,28.4972648621],"type":"Point"}
}