{
  "type": "Feature",
  "properties": {
    "addr:full":"Av Castell D'aro, 90 Platja D'aro Girona 17250",
    "addr:housenumber":"90",
    "addr:postcode":"17250",
    "addr:street":"Av Castell D'Aro",
    "iso:country":"ES",
    "sg:address":"Av Castell D'aro, 90",
    "sg:city":"Platja D'aro",
    "sg:orig_category":"Confecci\u00d3n De Uniformes",
    "sg:phone":"+34 972 81 76 15",
    "sg:postcode":"17250",
    "sg:province":"Girona",
    "wof:name":"Candanedo Robles Maria Yolanda",
    "wof:placetype":"venue"
},
  "geometry": {"coordinates":[2.8271551132,41.988822937],"type":"Point"}
}