{
  "type": "Feature",
  "properties": {
    "addr:full":"Calle de Medico Vicente Reyes, 18 Alacant Alicante 03012",
    "addr:housenumber":"18",
    "addr:postcode":"03012",
    "addr:street":"Calle De Medico Vicente Reyes",
    "iso:country":"ES",
    "sg:address":"Calle de Medico Vicente Reyes, 18",
    "sg:city":"Alacant",
    "sg:orig_category":"Cerrajer\u00cda, Ferrallista",
    "sg:phone":"+34 965 25 94 98",
    "sg:postcode":"03012",
    "sg:province":"Alicante",
    "wof:name":"A. Gestion Telefonica Oficinas Y Despachos S.l.",
    "wof:placetype":"venue"
},
  "geometry": {"coordinates":[-0.4725632966,38.3641166687],"type":"Point"}
}