{
  "type": "Feature",
  "properties": {
    "addr:full":"Carretera Orense, Km. 0003,6 Ponferrada Le\u00f3n 24400",
    "addr:postcode":"24400",
    "addr:street":"Carretera Orense Km. 0003,6;Leo\u0301N",
    "iso:country":"ES",
    "sg:address":"Carretera Orense, Km. 0003,6",
    "sg:city":"Ponferrada",
    "sg:orig_category":"Mec\u00c1nico Del Autom\u00d3vil",
    "sg:phone":"+34 987 41 29 28",
    "sg:postcode":"24400",
    "sg:province":"Le\u00f3n",
    "wof:name":"Automecanica Ponferrada S.l.",
    "wof:placetype":"venue"
},
  "geometry": {"coordinates":[-6.6771621704,42.5060081482],"type":"Point"}
}