{
  "type": "Feature",
  "properties": {
    "addr:full":"Plaz Mayor, S/n Sahagun Le\u00f3n 24320",
    "addr:housenumber":"s / n",
    "addr:postcode":"24320",
    "addr:street":"Plaz Mayor;Sahagun Leo\u0301N",
    "iso:country":"ES",
    "sg:address":"Plaz Mayor, S/n",
    "sg:city":"Sahagun",
    "sg:orig_category":"Restaurantes",
    "sg:phone":"+34 987 78 10 85",
    "sg:postcode":"24320",
    "sg:province":"Le\u00f3n",
    "wof:name":"Ramos Martinez Luis",
    "wof:placetype":"venue"
},
  "geometry": {"coordinates":[-5.0310988426,42.3719558716],"type":"Point"}
}