{
  "type": "Feature",
  "properties": {
    "iso:country":"ES",
    "sg:address":"Calle de Gil De Jasa, 6",
    "sg:city":"Zaragoza",
    "sg:orig_category":"Promotores Constructores",
    "sg:phone":"+34 976 21 99 90",
    "sg:postcode":"50006",
    "sg:province":"Zaragoza",
    "wof:name":"Gescomunitas S.l.",
    "wof:placetype":"venue"
},
  "geometry": {"coordinates":[-0.8867279887,41.6444664001],"type":"Point"}
}