{
  "type": "Feature",
  "properties": {
    "addr:full":"Calle de Ignacio Aldecoa, 26 Malaga M\u00e1laga 29006",
    "addr:housenumber":"26",
    "addr:postcode":"29006",
    "addr:street":"Calle De Ignacio Aldecoa;Ma\u0301Laga",
    "iso:country":"ES",
    "sg:address":"Calle de Ignacio Aldecoa, 26",
    "sg:city":"Malaga",
    "sg:orig_category":"Cerrajer\u00cda, Ferrallista",
    "sg:phone":"+34 952 24 00 04",
    "sg:postcode":"29006",
    "sg:province":"M\u00e1laga",
    "sg:website":"www.ferpaferreterialapaz.com",
    "wof:name":"Ferreteria La Paz S.l.",
    "wof:placetype":"venue"
},
  "geometry": {"coordinates":[-4.4679398537,36.6939506531],"type":"Point"}
}