{
  "type": "Feature",
  "properties": {
    "iso:country":"ES",
    "sg:address":"Polig. Pocomaco, S/n",
    "sg:city":"A Coru\u00f1a",
    "sg:orig_category":"Explotaci\u00d3n De Canteras",
    "sg:phone":"+34 981 13 92 62",
    "sg:postcode":"15190",
    "sg:province":"La Coru\u00f1a",
    "sg:website":"www.piedraland.com",
    "wof:name":"Piedraland S.l.",
    "wof:placetype":"venue"
},
  "geometry": {"coordinates":[-8.4312744141,43.3228416443],"type":"Point"}
}