{
  "type": "Feature",
  "properties": {
    "addr:full":"Calle de Caridad, 118 S. Pedro Pinatar Murcia 30740",
    "addr:housenumber":"118",
    "addr:postcode":"30740",
    "addr:street":"Calle De Caridad;S. Pedro",
    "iso:country":"ES",
    "sg:address":"Calle de Caridad, 118",
    "sg:city":"S. Pedro Pinatar",
    "sg:orig_category":"Armaduras De Hormig\u00d3n",
    "sg:phone":"+34 968 18 25 94",
    "sg:postcode":"30740",
    "sg:province":"Murcia",
    "wof:name":"Estructuras Albacan S.l.",
    "wof:placetype":"venue"
},
  "geometry": {"coordinates":[-0.7989389896,37.8292884827],"type":"Point"}
}