{
  "type": "Feature",
  "properties": {
    "iso:country":"ES",
    "sg:address":"Avda Bilbao, 4",
    "sg:city":"Medina Pomar",
    "sg:orig_category":"Inmobiliaria (agencias)",
    "sg:phone":"+34 947 19 18 05",
    "sg:postcode":"09500",
    "sg:province":"Burgos",
    "sg:website":"www.inmobiliariagaray.com",
    "wof:name":"Martinez Gonzalez Montserrat",
    "wof:placetype":"venue"
},
  "geometry": {"coordinates":[-3.4852690697,42.9362792969],"type":"Point"}
}