{
  "type": "Feature",
  "properties": {
    "iso:country":"ES",
    "sg:address":"Carrer de Closa De Freixa, 4",
    "sg:city":"Reus",
    "sg:orig_category":"Fabricaci\u00d3n, Venta De Cuadros, Accesorios Para Enmarcar",
    "sg:phone":"+34 977 33 20 81",
    "sg:postcode":"43205",
    "sg:province":"Tarragona",
    "wof:name":"Gomez Blasco Lambert",
    "wof:placetype":"venue"
},
  "geometry": {"coordinates":[1.107929945,41.1519889832],"type":"Point"}
}