{
  "type": "Feature",
  "properties": {
    "addr:full":"Calle de Arquitecto Vandelvira, 9 Albacete Albacete 02003",
    "addr:housenumber":"9",
    "addr:postcode":"02003",
    "addr:street":"Calle De Arquitecto Vandelvira",
    "iso:country":"ES",
    "sg:address":"Calle de Arquitecto Vandelvira, 9",
    "sg:city":"Albacete",
    "sg:orig_category":"Reposter\u00cdas",
    "sg:phone":"+34 967 22 81 80",
    "sg:postcode":"02003",
    "sg:province":"Albacete",
    "wof:name":"Mohedano Padilla Juan",
    "wof:placetype":"venue"
},
  "geometry": {"coordinates":[-1.8600364923,38.9867706299],"type":"Point"}
}