{
  "type": "Feature",
  "properties": {
    "addr:full":"Carrer de Loreto, 30 Barcelona Barcelona 08029",
    "addr:housenumber":"30",
    "addr:postcode":"08029",
    "addr:street":"Carrer De Loreto",
    "iso:country":"ES",
    "sg:address":"Carrer de Loreto, 30",
    "sg:city":"Barcelona",
    "sg:orig_category":"Molduras, Junquillos, Listones Y Molduras Perforadas",
    "sg:phone":"+34 934 10 18 08",
    "sg:postcode":"08029",
    "sg:province":"Barcelona",
    "wof:name":"Dominguez Garcia Miguel",
    "wof:placetype":"venue"
},
  "geometry": {"coordinates":[2.142291069,41.3904151917],"type":"Point"}
}