{
  "type": "Feature",
  "properties": {
    "iso:country":"ES",
    "sg:address":"Carrer de Mallorca (de), 26",
    "sg:city":"Tarragona",
    "sg:orig_category":"\u00d3ptica: Instrumentos (fabricaci\u00d3n)",
    "sg:phone":"+34 977 24 84 42",
    "sg:postcode":"43005",
    "sg:province":"Tarragona",
    "wof:name":"Pe\u00f1iscola S.l.",
    "wof:placetype":"venue"
},
  "geometry": {"coordinates":[1.2434420586,41.1151542664],"type":"Point"}
}