{
  "type": "Feature",
  "properties": {
    "addr:full":"Calle de Cincel (del), 13 Partija-santa Monica Madrid 28529",
    "addr:housenumber":"13",
    "addr:postcode":"28529",
    "addr:street":"Calle De Cincel Del",
    "iso:country":"ES",
    "sg:address":"Calle de Cincel (del), 13",
    "sg:city":"Partija-santa Monica",
    "sg:orig_category":"Empresas De Vigilancia, Guardia Y Protecci\u00d3n",
    "sg:phone":"+34 916 70 20 71",
    "sg:postcode":"28529",
    "sg:province":"Madrid",
    "wof:name":"Europea De Servicios Y Vigilancia S.l.",
    "wof:placetype":"venue"
},
  "geometry": {"coordinates":[-3.7003455162,40.4166908264],"type":"Point"}
}