{
  "type": "Feature",
  "properties": {
    "addr:full":"Rua Urzaiz, 137 Vigo Pontevedra 36204",
    "addr:housenumber":"137",
    "addr:postcode":"36204",
    "addr:street":"Rua Urzaiz",
    "iso:country":"ES",
    "sg:address":"Rua Urzaiz, 137",
    "sg:city":"Vigo",
    "sg:orig_category":"Importaci\u00d3n",
    "sg:phone":"+34 986 27 02 64",
    "sg:postcode":"36204",
    "sg:province":"Pontevedra",
    "wof:name":"Imexport Cisneros S. L.",
    "wof:placetype":"venue"
},
  "geometry": {"coordinates":[-8.7092485428,42.2317008972],"type":"Point"}
}