{
  "type": "Feature",
  "properties": {
    "addr:full":"San Roman, S/n San Roman Lugo 27627",
    "addr:housenumber":"s / n",
    "addr:postcode":"27627",
    "addr:street":"San Roman",
    "iso:country":"ES",
    "sg:address":"San Roman, S/n",
    "sg:city":"San Roman",
    "sg:orig_category":"Empresarios",
    "sg:phone":"+34 982 18 70 04",
    "sg:postcode":"27627",
    "sg:province":"Lugo",
    "wof:name":"Fundacion O Noso Lar",
    "wof:placetype":"venue"
},
  "geometry": {"coordinates":[-7.0632457733,42.8730163574],"type":"Point"}
}