{
  "type": "Feature",
  "properties": {
    "iso:country":"ES",
    "sg:address":"Avda San Francisco Javier, S/n",
    "sg:city":"Sevilla",
    "sg:orig_category":"Cl\u00cdnicas M\u00c9dicas",
    "sg:phone":"+34 954 65 48 83",
    "sg:postcode":"41005",
    "sg:province":"Sevilla",
    "wof:name":"Asistencia Sanitaria Interprovincial S.a.",
    "wof:placetype":"venue"
},
  "geometry": {"coordinates":[-5.9740123749,37.3798789978],"type":"Point"}
}