{
  "type": "Feature",
  "properties": {
    "addr:full":"Calle de Bideberrieta, 3 Alegia Guip\u00f9zcoa 20260",
    "addr:housenumber":"3",
    "addr:postcode":"20260",
    "addr:street":"Calle De Bideberrieta;Guipu\u0300Zcoa",
    "iso:country":"ES",
    "sg:address":"Calle de Bideberrieta, 3",
    "sg:city":"Alegia",
    "sg:orig_category":"Lateros",
    "sg:phone":"+34 943 65 30 60",
    "sg:postcode":"20260",
    "sg:province":"Guip\u00f9zcoa",
    "wof:name":"Echeberria Irastorza Miguel Angel",
    "wof:placetype":"venue"
},
  "geometry": {"coordinates":[-2.1066689491,43.1000823975],"type":"Point"}
}