{
  "type": "Feature",
  "properties": {
    "addr:full":"Calle de Mayor, 42 Caravaca Cruz Murcia 30400",
    "addr:housenumber":"42",
    "addr:postcode":"30400",
    "addr:street":"Calle De Mayor",
    "iso:country":"ES",
    "sg:address":"Calle de Mayor, 42",
    "sg:city":"Caravaca Cruz",
    "sg:orig_category":"Inform\u00c1tica (estudios, Servicios, Asesor\u00cda, Formaci\u00d3n)",
    "sg:phone":"+34 968 70 52 60",
    "sg:postcode":"30400",
    "sg:province":"Murcia",
    "sg:website":"www.depau.com",
    "wof:name":"Olmos Vidal Salvador",
    "wof:placetype":"venue"
},
  "geometry": {"coordinates":[-1.8611459732,38.1062469482],"type":"Point"}
}