{
  "type": "Feature",
  "properties": {
    "iso:country":"ES",
    "sg:address":"Calle de Monte Carmelo, 13",
    "sg:city":"Zaragoza",
    "sg:orig_category":"Empresas De Carpinter\u00cda De Madera",
    "sg:phone":"+34 976 34 28 17",
    "sg:postcode":"50010",
    "sg:province":"Zaragoza",
    "wof:name":"Sancho Blas Francisco Javier",
    "wof:placetype":"venue"
},
  "geometry": {"coordinates":[-0.9012050033,41.6561660767],"type":"Point"}
}