{
  "type": "Feature",
  "properties": {
    "addr:full":"Calle de Jose Antonio Primo De Rivera, 84 Arrecife Las Palmas 35500",
    "addr:housenumber":"84",
    "addr:postcode":"35500",
    "addr:street":"Calle De Jose Antonio Primo De Rivera",
    "iso:country":"ES",
    "sg:address":"Calle de Jose Antonio Primo De Rivera, 84",
    "sg:city":"Arrecife",
    "sg:orig_category":"Ropa Para Se\u00d1oras (al Por Menor)",
    "sg:phone":"+34 928 81 34 26",
    "sg:postcode":"35500",
    "sg:province":"Las Palmas",
    "wof:name":"Melian Quesada Carmen Delia",
    "wof:placetype":"venue"
},
  "geometry": {"coordinates":[-13.5544185638,28.9594097137],"type":"Point"}
}