{
  "type": "Feature",
  "properties": {
    "addr:full":"Carr Duc De Lliria (del), 47 Lliria Valencia 46160",
    "addr:housenumber":"47",
    "addr:postcode":"46160",
    "addr:street":"Carr Duc De Lliria Del",
    "iso:country":"ES",
    "sg:address":"Carr Duc De Lliria (del), 47",
    "sg:city":"Lliria",
    "sg:orig_category":"Inmobiliaria (agencias)",
    "sg:phone":"+34 962 79 30 09",
    "sg:postcode":"46160",
    "sg:province":"Valencia",
    "wof:name":"Firma Urbanistica S.l.",
    "wof:placetype":"venue"
},
  "geometry": {"coordinates":[-0.5979520082,39.628528595],"type":"Point"}
}