{
  "type": "Feature",
  "properties": {
    "addr:full":"Calle de Doce De Octubre, 10 Zaragoza Zaragoza 50007",
    "addr:housenumber":"10",
    "addr:postcode":"50007",
    "addr:street":"Calle De Doce De Octubre",
    "iso:country":"ES",
    "sg:address":"Calle de Doce De Octubre, 10",
    "sg:city":"Zaragoza",
    "sg:orig_category":"Molduras, Junquillos, Listones Y Molduras Perforadas",
    "sg:phone":"+34 976 37 65 20",
    "sg:postcode":"50007",
    "sg:province":"Zaragoza",
    "wof:name":"Sanchez Y Fuentes Sociedad Civil",
    "wof:placetype":"venue"
},
  "geometry": {"coordinates":[-0.8784196973,41.6355743408],"type":"Point"}
}