{
  "type": "Feature",
  "properties": {
    "iso:country":"ES",
    "sg:address":"Calle de Isla Cabrera, 6",
    "sg:city":"Valencia",
    "sg:orig_category":"Agencias Y Agentes Comerciales, Representantes",
    "sg:phone":"+34 963 33 24 40",
    "sg:postcode":"46026",
    "sg:province":"Valencia",
    "wof:name":"Martinez Martinez Juan",
    "wof:placetype":"venue"
},
  "geometry": {"coordinates":[-0.3821060061,39.4493331909],"type":"Point"}
}