{
  "type": "Feature",
  "properties": {
    "iso:country":"ES",
    "sg:address":"Avda Mediterraneo, Km. 0014,0",
    "sg:city":"Madrid",
    "sg:orig_category":"Contenedores (mercanc\u00cdas)",
    "sg:phone":"+34 913 31 62 16",
    "sg:postcode":"28864",
    "sg:province":"Madrid",
    "wof:name":"Vahitrans Transporte Y Logistica De Maquinaria Industrial Y Obras Publicas S.l.",
    "wof:placetype":"venue"
},
  "geometry": {"coordinates":[-3.4845490456,40.5355567932],"type":"Point"}
}