{
  "type": "Feature",
  "properties": {
    "iso:country":"ES",
    "sg:address":"Calle de San Lorenzo, 14",
    "sg:city":"Santa Eulalia",
    "sg:orig_category":"Lencer\u00cda Femenina, Corseter\u00cda, Trajes De Ba\u00d1o (al Por Menor)",
    "sg:phone":"+34 971 33 65 80",
    "sg:postcode":"07840",
    "sg:province":"Islas Baleares",
    "wof:name":"Pallas Torne Francisco",
    "wof:placetype":"venue"
},
  "geometry": {"coordinates":[1.4628041983,38.9576759338],"type":"Point"}
}