{
  "type": "Feature",
  "properties": {
    "iso:country":"ES",
    "sg:address":"Calle de Don Pedro De Luna, 54",
    "sg:city":"Zaragoza",
    "sg:orig_category":"Muebles, Minoristas",
    "sg:phone":"+34 976 34 54 88",
    "sg:postcode":"50010",
    "sg:province":"Zaragoza",
    "wof:name":"Muebles El Pilar S. A.",
    "wof:placetype":"venue"
},
  "geometry": {"coordinates":[-0.904240489,41.6504707336],"type":"Point"}
}