{
  "type": "Feature",
  "properties": {
    "iso:country":"ES",
    "sg:address":"Carr Maragall, 19",
    "sg:city":"Lleida",
    "sg:orig_category":"Electricidad Veh\u00cdculo",
    "sg:phone":"+34 973 27 36 40",
    "sg:postcode":"25003",
    "sg:province":"Lleida",
    "wof:name":"Gutierrez Lopez Manuel Angel",
    "wof:placetype":"venue"
},
  "geometry": {"coordinates":[0.6178500056,41.6144332886],"type":"Point"}
}