{
  "type": "Feature",
  "properties": {
    "iso:country":"ES",
    "sg:address":"Carrer de Guardia Civil, De Sa, 1",
    "sg:city":"Santanyi",
    "sg:orig_category":"Bisuter\u00cda, Joyer\u00cda, Relojer\u00cda (al Por Menor)",
    "sg:phone":"+34 971 65 34 17",
    "sg:postcode":"07650",
    "sg:province":"Islas Baleares",
    "wof:name":"Sa Joieria Argenteria I Rellotgeria S.l.",
    "wof:placetype":"venue"
},
  "geometry": {"coordinates":[3.1281599998,39.3541412354],"type":"Point"}
}