{
  "type": "Feature",
  "properties": {
    "iso:country":"ES",
    "sg:address":"F Pol Ind Comarca I (agustinos), S/n",
    "sg:city":"Iru\u00f1a",
    "sg:orig_category":"Contenedores (mercanc\u00cdas)",
    "sg:phone":"+34 948 24 60 40",
    "sg:postcode":"31013",
    "sg:province":"Navarra",
    "wof:name":"Sambe S.l.",
    "wof:placetype":"venue"
},
  "geometry": {"coordinates":[-97.78224945069999,45.7040786743],"type":"Point"}
}