{
  "type": "Feature",
  "properties": {
    "addr:full":"Rua Tomas Maria Mosquera, 1 Carballi\u00f1o Ourense 32500",
    "addr:housenumber":"1",
    "addr:postcode":"32500",
    "addr:street":"Rua Tomas Maria Mosquera",
    "iso:country":"ES",
    "sg:address":"Rua Tomas Maria Mosquera, 1",
    "sg:city":"Carballi\u00f1o",
    "sg:orig_category":"Caf\u00c9s, Bares, Cervecer\u00cdas",
    "sg:phone":"+34 988 27 23 28",
    "sg:postcode":"32500",
    "sg:province":"Ourense",
    "wof:name":"H.w. Carballi\u00f1o, S.l.",
    "wof:placetype":"venue"
},
  "geometry": {"coordinates":[-8.0782928467,42.4299468994],"type":"Point"}
}