{
  "type": "Feature",
  "properties": {
    "iso:country":"ES",
    "sg:address":"Ctra. Monovar, 3",
    "sg:city":"Elda",
    "sg:orig_category":"Asociaciones Y Clubs Deportivos",
    "sg:phone":"+34 965 38 20 76",
    "sg:postcode":"03600",
    "sg:province":"Alicante",
    "wof:name":"Centro Excursionista Eldense",
    "wof:placetype":"venue"
},
  "geometry": {"coordinates":[-0.8014129996,38.4790496826],"type":"Point"}
}