{
  "type": "Feature",
  "properties": {
    "iso:country":"ES",
    "sg:address":"Calle de General Goded, 3",
    "sg:city":"Arrecife",
    "sg:orig_category":"Telas Y Sedas (al Por Menor)",
    "sg:phone":"+34 928 81 42 53",
    "sg:postcode":"35500",
    "sg:province":"Las Palmas",
    "wof:name":"Almacenes El Barato S.a.",
    "wof:placetype":"venue"
},
  "geometry": {"coordinates":[-13.5487318039,28.9600048065],"type":"Point"}
}