{
  "type": "Feature",
  "properties": {
    "iso:country":"ES",
    "sg:address":"Pla\u00c7 Poble, 1",
    "sg:city":"Silla",
    "sg:orig_category":"Servicios Y Funcionarios De Polic\u00cda",
    "sg:phone":"+34 961 21 17 18",
    "sg:postcode":"46460",
    "sg:province":"Valencia",
    "wof:name":"Ayuntamiento De Silla",
    "wof:placetype":"venue"
},
  "geometry": {"coordinates":[-0.417858988,39.3685531616],"type":"Point"}
}