{
  "type": "Feature",
  "properties": {
    "addr:full":"Calle de Mercado, 1 S. Clemente Cuenca 16600",
    "addr:housenumber":"1",
    "addr:postcode":"16600",
    "addr:street":"Calle De Mercado;S. Clemente Cuenca",
    "iso:country":"ES",
    "sg:address":"Calle de Mercado, 1",
    "sg:city":"S. Clemente",
    "sg:orig_category":"Aguas (distribuci\u00d3n, Servicios)",
    "sg:phone":"+34 969 30 23 76",
    "sg:postcode":"16600",
    "sg:province":"Cuenca",
    "wof:name":"Aquagest S.a.",
    "wof:placetype":"venue"
},
  "geometry": {"coordinates":[-2.425755024,39.4053955078],"type":"Point"}
}