{
  "type": "Feature",
  "properties": {
    "addr:full":"Rua Dr. Cadaval, 21 Vigo Pontevedra 36202",
    "addr:housenumber":"21",
    "addr:postcode":"36202",
    "addr:street":"Rua Dr. Cadaval",
    "iso:country":"ES",
    "sg:address":"Rua Dr. Cadaval, 21",
    "sg:city":"Vigo",
    "sg:orig_category":"Fisioterapia",
    "sg:phone":"+34 986 22 68 22",
    "sg:postcode":"36202",
    "sg:province":"Pontevedra",
    "wof:name":"Gonzalez Barbeitos Virgilio",
    "wof:placetype":"venue"
},
  "geometry": {"coordinates":[-8.7242040634,42.2363624573],"type":"Point"}
}