{
  "type": "Feature",
  "properties": {
    "addr:full":"Calle de Atilano Hernandez, 39 Bermillo Sayago Zamora 49200",
    "addr:housenumber":"39",
    "addr:postcode":"49200",
    "addr:street":"Calle De Atilano Hernandez;Zamora",
    "iso:country":"ES",
    "sg:address":"Calle de Atilano Hernandez, 39",
    "sg:city":"Bermillo Sayago",
    "sg:orig_category":"Cooperativas Agr\u00cdcolas",
    "sg:phone":"+34 980 61 01 49",
    "sg:postcode":"49200",
    "sg:province":"Zamora",
    "wof:name":"Sociedad Cooperativa De Ovino Sayaguesa S.c.l. Covisa",
    "wof:placetype":"venue"
},
  "geometry": {"coordinates":[-6.1089668274,41.3664703369],"type":"Point"}
}