{
  "type": "Feature",
  "properties": {
    "addr:full":"Plaz Constitucion, 3 Viator Almer\u00eda 04240",
    "addr:housenumber":"3",
    "addr:postcode":"04240",
    "addr:street":"Constitucion;Almeri\u0301A",
    "iso:country":"ES",
    "sg:address":"Plaz Constitucion, 3",
    "sg:city":"Viator",
    "sg:orig_category":"Farmacias",
    "sg:phone":"+34 950 30 44 37",
    "sg:postcode":"04240",
    "sg:province":"Almer\u00eda",
    "wof:name":"Eisman Moreno Maria Del Mar",
    "wof:placetype":"venue"
},
  "geometry": {"coordinates":[-2.4264919758,36.8897628784],"type":"Point"}
}