{
  "type": "Feature",
  "properties": {
    "addr:full":"Ctra Murcia, Km. 0174,5 Baza Granada 18800",
    "addr:postcode":"18800",
    "addr:street":"Ctra Murcia Km. 0174,5",
    "iso:country":"ES",
    "sg:address":"Ctra Murcia, Km. 0174,5",
    "sg:city":"Baza",
    "sg:orig_category":"Comercio De Piezas De Recambio Y De Accesorios De Veh\u00cdculos, Veh\u00cdculos Industriales",
    "sg:phone":"+34 958 70 24 54",
    "sg:postcode":"18800",
    "sg:province":"Granada",
    "wof:name":"Martinez Fernandez Jose",
    "wof:placetype":"venue"
},
  "geometry": {"coordinates":[-2.7616488934,37.4945487976],"type":"Point"}
}