{
  "type": "Feature",
  "properties": {
    "addr:full":"La Cuadriella, S/n Turon Asturias 33610",
    "addr:housenumber":"s / n",
    "addr:postcode":"33610",
    "iso:country":"ES",
    "sg:address":"La Cuadriella, S/n",
    "sg:city":"Turon",
    "sg:orig_category":"Calderer\u00cda",
    "sg:phone":"+34 985 43 27 07",
    "sg:postcode":"33610",
    "sg:province":"Asturias",
    "sg:website":"www.cm-uruena.com",
    "wof:name":"Construcciones Mecanicas Urue\u00f1a S.a.",
    "wof:placetype":"venue"
},
  "geometry": {"coordinates":[-5.6699900627,43.2162284851],"type":"Point"}
}