{
  "type": "Feature",
  "properties": {
    "addr:full":"Calle de Garcia Escamez, 22 Pto. Rosario Las Palmas 35600",
    "addr:housenumber":"22",
    "addr:postcode":"35600",
    "addr:street":"Calle De Garcia Escamez;Pto. Rosario Las",
    "iso:country":"ES",
    "sg:address":"Calle de Garcia Escamez, 22",
    "sg:city":"Pto. Rosario",
    "sg:orig_category":"Urbanistas",
    "sg:phone":"+34 928 53 24 98",
    "sg:postcode":"35600",
    "sg:province":"Las Palmas",
    "wof:name":"Cinur Consultores Urbanisticos E Inmobiliarios S.l.",
    "wof:placetype":"venue"
},
  "geometry": {"coordinates":[-13.8612718582,28.4957141876],"type":"Point"}
}