{
  "type": "Feature",
  "properties": {
    "addr:full":"Calle de Raimundo Fernandez Villaverde, 28 Madrid Madrid 28003",
    "addr:housenumber":"28",
    "addr:postcode":"madrid;28003",
    "addr:street":"Calle De Raimundo Fernandez Villaverde",
    "iso:country":"ES",
    "sg:address":"Calle de Raimundo Fernandez Villaverde, 28",
    "sg:city":"Madrid",
    "sg:orig_category":"Productos Qu\u00cdmicos (fabricaci\u00d3n, Al Por Mayor)",
    "sg:phone":"+34 915 54 74 86",
    "sg:postcode":"28003",
    "sg:province":"Madrid",
    "wof:name":"Novus Spain S.a.",
    "wof:placetype":"venue"
},
  "geometry": {"coordinates":[-3.6995530128,40.4465103149],"type":"Point"}
}