{
  "type": "Feature",
  "properties": {
    "addr:full":"Avda Inmaculada Concepcion, 7 Arroyo De La Miel-benalmadena Costa M\u00e1laga 29631",
    "addr:housenumber":"7",
    "addr:postcode":"29631",
    "addr:street":"Avda Inmaculada Concepcion;Arroyo De La Miel-Benalmadena Costa Ma\u0301Laga",
    "iso:country":"ES",
    "sg:address":"Avda Inmaculada Concepcion, 7",
    "sg:city":"Arroyo De La Miel-benalmadena Costa",
    "sg:orig_category":"Electrodom\u00c9sticos (al Por Menor)",
    "sg:phone":"+34 952 44 75 35",
    "sg:postcode":"29631",
    "sg:province":"M\u00e1laga",
    "sg:website":"www.jorgemartinez.com",
    "wof:name":"Jorge Martinez E Hijos S.l.",
    "wof:placetype":"venue"
},
  "geometry": {"coordinates":[-4.5482521057,36.6017608643],"type":"Point"}
}