{
  "type": "Feature",
  "properties": {
    "iso:country":"ES",
    "sg:address":"Calle de Iturribide, 116",
    "sg:city":"Bilbao",
    "sg:orig_category":"Molduras, Junquillos, Listones Y Molduras Perforadas",
    "sg:phone":"+34 944 32 05 99",
    "sg:postcode":"48006",
    "sg:province":"Vizcaya",
    "wof:name":"Raquel Ciudad Herraz-bar",
    "wof:placetype":"venue"
},
  "geometry": {"coordinates":[-2.9170079231,43.2553977966],"type":"Point"}
}