{
  "type": "Feature",
  "properties": {
    "iso:country":"ES",
    "sg:address":"Calle de Sierra De Corbera, 4",
    "sg:city":"Valencia",
    "sg:orig_category":"Fabricaci\u00d3n, Importaci\u00d3n De Material Y Sistemas De Telecomunicaciones",
    "sg:phone":"+34 963 65 58 14",
    "sg:postcode":"46019",
    "sg:province":"Valencia",
    "wof:name":"Zome\u00f1o Martinez Jose Miguel",
    "wof:placetype":"venue"
},
  "geometry": {"coordinates":[-0.3766331971,39.4980239868],"type":"Point"}
}