{
  "type": "Feature",
  "properties": {
    "addr:full":"Calle de Azuela, 31 Estacion Madrid 28400",
    "addr:housenumber":"31 estacion",
    "addr:postcode":"28400",
    "addr:street":"Calle De Azuela",
    "iso:country":"ES",
    "sg:address":"Calle de Azuela, 31",
    "sg:city":"Estacion",
    "sg:orig_category":"Asesor\u00cda Sobre Comunicaci\u00d3n De Empresas",
    "sg:phone":"+34 918 51 88 26",
    "sg:postcode":"28400",
    "sg:province":"Madrid",
    "wof:name":"Sr Consultores S.l.",
    "wof:placetype":"venue"
},
  "geometry": {"coordinates":[-3.7003455162,40.4166908264],"type":"Point"}
}