{
  "type": "Feature",
  "properties": {
    "addr:full":"Pase Constitucion, S/n Fregenal Sierra Badajoz 06340",
    "addr:postcode":"06340",
    "addr:street":"Constitucion S / N Fregenal Sierra",
    "iso:country":"ES",
    "sg:address":"Pase Constitucion, S/n",
    "sg:city":"Fregenal Sierra",
    "sg:orig_category":"Ense\u00d1anza, Formaci\u00d3n Profesional: Aprendizaje",
    "sg:phone":"+34 924 70 13 76",
    "sg:postcode":"06340",
    "sg:province":"Badajoz",
    "sg:website":"www.audinex.es/fregenal",
    "wof:name":"Ayuntamiento De Fregenal De La Sierra",
    "wof:placetype":"venue"
},
  "geometry": {"coordinates":[-6.6505317688,38.1659088135],"type":"Point"}
}