{
  "type": "Feature",
  "properties": {
    "addr:full":"Calle de Borox, S/n Esquivias Toledo 45221",
    "addr:housenumber":"s / n",
    "addr:postcode":"45221",
    "addr:street":"Calle De Borox",
    "iso:country":"ES",
    "sg:address":"Calle de Borox, S/n",
    "sg:city":"Esquivias",
    "sg:orig_category":"Revestimientos Diversos",
    "sg:phone":"+34 925 52 01 70",
    "sg:postcode":"45221",
    "sg:province":"Toledo",
    "wof:name":"Terrazos San Sebastian S.l.",
    "wof:placetype":"venue"
},
  "geometry": {"coordinates":[-3.7148241997,40.1270561218],"type":"Point"}
}