{
  "type": "Feature",
  "properties": {
    "addr:full":"Calle de Virgen Del Carmen, 1 Puerto Santiago Santa Cruz De Tenerife 38683",
    "addr:housenumber":"1",
    "addr:postcode":"38683",
    "addr:street":"Calle De Virgen Del Carmen",
    "iso:country":"ES",
    "sg:address":"Calle de Virgen Del Carmen, 1",
    "sg:city":"Puerto Santiago",
    "sg:orig_category":"Frutas Y Legumbres Frescas (al Por Mayor)",
    "sg:phone":"+34 922 86 01 23",
    "sg:postcode":"38683",
    "sg:province":"Santa Cruz De Tenerife",
    "wof:name":"Ruiz Toledo Jesus Salvador",
    "wof:placetype":"venue"
},
  "geometry": {"coordinates":[-16.8412456512,28.2312526703],"type":"Point"}
}