{
  "type": "Feature",
  "properties": {
    "addr:full":"Avda Atalaya Becerril, 11 Atalaya Las Palmas 35450",
    "addr:housenumber":"11",
    "addr:postcode":"35450",
    "addr:street":"Avda Atalaya Becerril",
    "iso:country":"ES",
    "sg:address":"Avda Atalaya Becerril, 11",
    "sg:city":"Atalaya",
    "sg:orig_category":"Centros De Educaci\u00d3n Especial",
    "sg:phone":"+34 928 88 06 85",
    "sg:postcode":"35450",
    "sg:province":"Las Palmas",
    "wof:name":"Gobierno De Canarias",
    "wof:placetype":"venue"
},
  "geometry": {"coordinates":[-15.636633873,28.1467494965],"type":"Point"}
}