{
  "type": "Feature",
  "properties": {
    "addr:full":"Trva San Blas, 3 Parla Madrid 28980",
    "addr:housenumber":"3",
    "addr:postcode":"28980",
    "addr:street":"Trva San Blas",
    "iso:country":"ES",
    "sg:address":"Trva San Blas, 3",
    "sg:city":"Parla",
    "sg:orig_category":"Tapiceros Y Tapiceros",
    "sg:phone":"+34 916 98 33 22",
    "sg:postcode":"28980",
    "sg:province":"Madrid",
    "wof:name":"Gomez Alonso Tirso",
    "wof:placetype":"venue"
},
  "geometry": {"coordinates":[-3.7708959579,40.240196228],"type":"Point"}
}