{
  "type": "Feature",
  "properties": {
    "iso:country":"ES",
    "sg:address":"Av M. Celayeta, 8",
    "sg:city":"Iru\u00f1a",
    "sg:orig_category":"Electrodom\u00c9sticos (fabricaci\u00d3n, Al Por Mayor)",
    "sg:phone":"+34 948 14 92 80",
    "sg:postcode":"31014",
    "sg:province":"Navarra",
    "wof:name":"Salda\u00f1a Hogar S.l.",
    "wof:placetype":"venue"
},
  "geometry": {"coordinates":[-1.6437540054,42.81275177],"type":"Point"}
}