{
  "type": "Feature",
  "properties": {
    "addr:full":"Vilanovi\u00f1a, Km. 0004,0 Meis Pontevedra 36616",
    "addr:postcode":"36616",
    "addr:street":"Vilanovin\u0303A Km. 0004,0",
    "iso:country":"ES",
    "sg:address":"Vilanovi\u00f1a, Km. 0004,0",
    "sg:city":"Meis",
    "sg:orig_category":"Carnes De Carnicer\u00cda (al Por Mayor)",
    "sg:phone":"+34 986 71 50 07",
    "sg:postcode":"36616",
    "sg:province":"Pontevedra",
    "wof:name":"Ramiro Martinez S.l.",
    "wof:placetype":"venue"
},
  "geometry": {"coordinates":[-8.7164926529,42.5487976074],"type":"Point"}
}