{
  "type": "Feature",
  "properties": {
    "addr:full":"Carrer de Muralla De Santa Tecla, 16 Montblanc Tarragona 43400",
    "addr:housenumber":"16",
    "addr:postcode":"43400",
    "addr:street":"Carrer De Muralla De Santa Tecla",
    "iso:country":"ES",
    "sg:address":"Carrer de Muralla De Santa Tecla, 16",
    "sg:city":"Montblanc",
    "sg:orig_category":"Asociaciones, Organismos Culturales Y Socioeducativos",
    "sg:phone":"+34 977 86 01 70",
    "sg:postcode":"43400",
    "sg:province":"Tarragona",
    "wof:name":"Casal Montblanc",
    "wof:placetype":"venue"
},
  "geometry": {"coordinates":[1.1643300056,41.3753395081],"type":"Point"}
}