{
  "type": "Feature",
  "properties": {
    "addr:full":"Rua Saude, 21 Lugo Lugo 27004",
    "addr:housenumber":"21",
    "addr:postcode":"27004",
    "addr:street":"Rua Saude",
    "iso:country":"ES",
    "sg:address":"Rua Saude, 21",
    "sg:city":"Lugo",
    "sg:orig_category":"Ense\u00d1anza: Peluquer\u00cda Est\u00c9tica",
    "sg:phone":"+34 982 21 07 70",
    "sg:postcode":"27004",
    "sg:province":"Lugo",
    "wof:name":"Lopez Lugilde Lorena",
    "wof:placetype":"venue"
},
  "geometry": {"coordinates":[-7.5701880455,43.0109214783],"type":"Point"}
}