{
  "type": "Feature",
  "properties": {
    "iso:country":"ES",
    "sg:address":"Calle de Parroquia, S/n",
    "sg:city":"Doneztebe",
    "sg:orig_category":"Mec\u00c1nico Del Autom\u00d3vil",
    "sg:phone":"+34 948 45 17 83",
    "sg:postcode":"31740",
    "sg:province":"Navarra",
    "wof:name":"Lacambra Juanena Miguel",
    "wof:placetype":"venue"
},
  "geometry": {"coordinates":[-1.6710619926,43.131729126],"type":"Point"}
}