{
  "type": "Feature",
  "properties": {
    "addr:full":"F. Tercio Nvo., S/n Gargantilla Y Pinilla Madrid 28739",
    "addr:housenumber":"s / n",
    "addr:postcode":"28739",
    "addr:street":"F.",
    "iso:country":"ES",
    "sg:address":"F. Tercio Nvo., S/n",
    "sg:city":"Gargantilla Y Pinilla",
    "sg:orig_category":"Zonas De Acampada, Aparcamiento Para Caravanas",
    "sg:phone":"+34 918 69 52 78",
    "sg:postcode":"28739",
    "sg:province":"Madrid",
    "wof:name":"Perez Fernandez Del Pozo Gonzalo",
    "wof:placetype":"venue"
},
  "geometry": {"coordinates":[-3.7168691158,40.965473175],"type":"Point"}
}