{
  "type": "Feature",
  "properties": {
    "addr:full":"Soto De La Barca, S/n La Barca Asturias 33876",
    "addr:housenumber":"s / n",
    "addr:postcode":"33876",
    "addr:street":"Barca",
    "iso:country":"ES",
    "sg:address":"Soto De La Barca, S/n",
    "sg:city":"La Barca",
    "sg:orig_category":"Distribuci\u00d3n De Petr\u00d3leo Y Derivados",
    "sg:phone":"+34 985 80 04 71",
    "sg:postcode":"33876",
    "sg:province":"Asturias",
    "wof:name":"Maderas Y Carburantes De La Barca S. L.",
    "wof:placetype":"venue"
},
  "geometry": {"coordinates":[-6.4057312012,43.3230934143],"type":"Point"}
}