{
  "type": "Feature",
  "properties": {
    "iso:country":"ES",
    "sg:address":"Avgd D'albaida, 2",
    "sg:city":"Ontinyent",
    "sg:orig_category":"Peluqueros: De Se\u00d1oras",
    "sg:phone":"+34 962 38 28 41",
    "sg:postcode":"46870",
    "sg:province":"Valencia",
    "wof:name":"Guijarro Utiel Milagro",
    "wof:placetype":"venue"
},
  "geometry": {"coordinates":[-0.6000919938,38.8251686096],"type":"Point"}
}