{
  "type": "Feature",
  "properties": {
    "addr:full":"Carr Alfons Xiii, 9 Ciutadella Menorca Islas Baleares 07760",
    "addr:housenumber":"9",
    "addr:postcode":"07760",
    "addr:street":"Carr Alfons Xiii",
    "iso:country":"ES",
    "sg:address":"Carr Alfons Xiii, 9",
    "sg:city":"Ciutadella Menorca",
    "sg:orig_category":"Arquitectos",
    "sg:phone":"+34 971 38 53 12",
    "sg:postcode":"07760",
    "sg:province":"Islas Baleares",
    "wof:name":"Casasnovas Anglada Jose Luis",
    "wof:placetype":"venue"
},
  "geometry": {"coordinates":[3.8397059441,40.00548172],"type":"Point"}
}