{
  "type": "Feature",
  "properties": {
    "addr:full":"Calle de Profesor Regadera, 3 Alcanadre La Rioja 26509",
    "addr:housenumber":"3",
    "addr:postcode":"26509",
    "addr:street":"Calle De Profesor Regadera;Alcanadre;Rioja",
    "iso:country":"ES",
    "sg:address":"Calle de Profesor Regadera, 3",
    "sg:city":"Alcanadre",
    "sg:orig_category":"Material Y Herramientas Agr\u00cdcolas",
    "sg:phone":"+34 941 16 50 44",
    "sg:postcode":"26509",
    "sg:province":"La Rioja",
    "wof:name":"Torres Martinez Jose Antonio",
    "wof:placetype":"venue"
},
  "geometry": {"coordinates":[-2.1211121082,42.4038505554],"type":"Point"}
}