{
  "type": "Feature",
  "properties": {
    "addr:full":"Cmno Salabosque, 94 Aljucer Murcia 30152",
    "addr:housenumber":"94",
    "addr:postcode":"30152",
    "addr:street":"Cmno Salabosque",
    "iso:country":"ES",
    "sg:address":"Cmno Salabosque, 94",
    "sg:city":"Aljucer",
    "sg:orig_category":"M\u00c1quinas Para Recortar Y Pegar",
    "sg:phone":"+34 968 34 38 08",
    "sg:postcode":"30152",
    "sg:province":"Murcia",
    "wof:name":"Salmeron Campoy Francisco",
    "wof:placetype":"venue"
},
  "geometry": {"coordinates":[-1.1452490091,37.9643058777],"type":"Point"}
}