{
  "type": "Feature",
  "properties": {
    "addr:full":"Av Marignane, 9 Figueres Girona 17600",
    "addr:housenumber":"9",
    "addr:postcode":"17600",
    "addr:street":"Av Marignane",
    "iso:country":"ES",
    "sg:address":"Av Marignane, 9",
    "sg:city":"Figueres",
    "sg:orig_category":"Prot\u00c9sicos Dentales",
    "sg:phone":"+34 972 67 52 98",
    "sg:postcode":"17600",
    "sg:province":"Girona",
    "wof:name":"Garcia Mu\u00f1oz Gloria",
    "wof:placetype":"venue"
},
  "geometry": {"coordinates":[2.9569735527,42.2714958191],"type":"Point"}
}