{
  "type": "Feature",
  "properties": {
    "addr:full":"Calle de Isaac Peral, 54 Madrid Madrid 28040",
    "addr:housenumber":"54",
    "addr:postcode":"madrid;28040",
    "addr:street":"Calle De Isaac Peral",
    "iso:country":"ES",
    "sg:address":"Calle de Isaac Peral, 54",
    "sg:city":"Madrid",
    "sg:orig_category":"Electricidad Veh\u00cdculo",
    "sg:phone":"+34 915 43 86 34",
    "sg:postcode":"28040",
    "sg:province":"Madrid",
    "wof:name":"Campos Campos Trinidad",
    "wof:placetype":"venue"
},
  "geometry": {"coordinates":[-3.7174699306,40.4399223328],"type":"Point"}
}