{
  "type": "Feature",
  "properties": {
    "iso:country":"ES",
    "sg:address":"Ctra. Zaragoza, Km. 0001,5",
    "sg:city":"Gurrea Gallego",
    "sg:orig_category":"Cueros Y Pieles (al Por Mayor)",
    "sg:phone":"+34 976 68 80 12",
    "sg:postcode":"22280",
    "sg:province":"Huesca",
    "wof:name":"Lanipiel S. A.",
    "wof:placetype":"venue"
},
  "geometry": {"coordinates":[-0.7615240216,42.0129737854],"type":"Point"}
}