{
  "type": "Feature",
  "properties": {
    "addr:full":"Avda Delfina Viudes, 15 Torrevieja Alicante 03180",
    "addr:housenumber":"15",
    "addr:postcode":"03180",
    "addr:street":"Avda Delfina Viudes",
    "iso:country":"ES",
    "sg:address":"Avda Delfina Viudes, 15",
    "sg:city":"Torrevieja",
    "sg:orig_category":"Caf\u00c9s, Bares, Cervecer\u00cdas",
    "sg:phone":"+34 965 70 75 99",
    "sg:postcode":"03180",
    "sg:province":"Alicante",
    "wof:name":"Martinez Gonzalez Florinda",
    "wof:placetype":"venue"
},
  "geometry": {"coordinates":[-0.6803280115,37.9922676086],"type":"Point"}
}