{
  "type": "Feature",
  "properties": {
    "iso:country":"ES",
    "sg:address":"Urbanizacion Las Chapas, S/n",
    "sg:city":"Elviria",
    "sg:orig_category":"Gastronom\u00cda: Especialidades Regionales (al Por Menor)",
    "sg:phone":"+34 952 83 33 28",
    "sg:postcode":"29604",
    "sg:province":"M\u00e1laga",
    "wof:name":"Augischi S.l.",
    "wof:placetype":"venue"
},
  "geometry": {"coordinates":[-4.7527151108,36.5015792847],"type":"Point"}
}