{
  "type": "Feature",
  "properties": {
    "iso:country":"ES",
    "sg:address":"Calle de Antonio Bermudez, 41",
    "sg:city":"Arrecife",
    "sg:orig_category":"Centros Empresariales",
    "sg:phone":"+34 928 80 53 73",
    "sg:postcode":"35500",
    "sg:province":"Las Palmas",
    "wof:name":"Hercio Luz Y Sonido S.l.",
    "wof:placetype":"venue"
},
  "geometry": {"coordinates":[-13.5641422272,28.9638843536],"type":"Point"}
}