{
  "type": "Feature",
  "properties": {
    "iso:country":"ES",
    "sg:address":"Calle de Felipe Vives De Ca\u00d1amas, 43",
    "sg:city":"Valencia",
    "sg:orig_category":"Internados & Ense\u00d1anza Privada",
    "sg:phone":"+34 963 71 44 63",
    "sg:postcode":"46011",
    "sg:province":"Valencia",
    "wof:name":"Colegio Chiner Villarroya",
    "wof:placetype":"venue"
},
  "geometry": {"coordinates":[-0.3330909908,39.4740104675],"type":"Point"}
}