{
  "type": "Feature",
  "properties": {
    "addr:full":"Avda Espa\u00d1a, 14 Alhaurin Torre M\u00e1laga 29130",
    "addr:housenumber":"14",
    "addr:postcode":"29130",
    "addr:street":"Avda Espan\u0303A",
    "iso:country":"ES",
    "sg:address":"Avda Espa\u00d1a, 14",
    "sg:city":"Alhaurin Torre",
    "sg:orig_category":"Fotograf\u00cda Art\u00cdstica Y Retratos",
    "sg:phone":"+34 952 96 36 28",
    "sg:postcode":"29130",
    "sg:province":"M\u00e1laga",
    "wof:name":"Carmona Aguilar Ramon",
    "wof:placetype":"venue"
},
  "geometry": {"coordinates":[-4.5631937981,36.6614379883],"type":"Point"}
}