{
  "type": "Feature",
  "properties": {
    "addr:full":"Pla\u00c7 Constitucion, 2 Turis Valencia 46389",
    "addr:housenumber":"2",
    "addr:postcode":"46389",
    "addr:street":"Constitucion",
    "iso:country":"ES",
    "sg:address":"Pla\u00c7 Constitucion, 2",
    "sg:city":"Turis",
    "sg:orig_category":"Financiaci\u00d3n Y Cr\u00c9ditos",
    "sg:phone":"+34 962 52 60 61",
    "sg:postcode":"46389",
    "sg:province":"Valencia",
    "wof:name":"Caixa Rural De Turis Coop. De Credito",
    "wof:placetype":"venue"
},
  "geometry": {"coordinates":[-0.7111030221,39.389377594],"type":"Point"}
}