{
  "type": "Feature",
  "properties": {
    "addr:full":"Carr Cami Vell D'alzira, 148 Alcudia Valencia 46250",
    "addr:housenumber":"148",
    "addr:postcode":"46250",
    "addr:street":"Carr Cami Vell D'Alzira",
    "iso:country":"ES",
    "sg:address":"Carr Cami Vell D'alzira, 148",
    "sg:city":"Alcudia",
    "sg:orig_category":"Controles De Edificaci\u00d3n (construcci\u00d3n, Seguridad)",
    "sg:phone":"+34 962 99 70 25",
    "sg:postcode":"46250",
    "sg:province":"Valencia",
    "wof:name":"Moya Procons S.l.",
    "wof:placetype":"venue"
},
  "geometry": {"coordinates":[-0.5059689879,39.1899604797],"type":"Point"}
}