{
  "type": "Feature",
  "properties": {
    "iso:country":"ES",
    "sg:address":"Avda Bilbao, 8",
    "sg:city":"Medina Pomar",
    "sg:orig_category":"\u00d3ptica: Instrumentos (fabricaci\u00d3n)",
    "sg:phone":"+34 947 19 15 15",
    "sg:postcode":"09500",
    "sg:province":"Burgos",
    "wof:name":"Gutierrez Ballesteros Maria Asuncion",
    "wof:placetype":"venue"
},
  "geometry": {"coordinates":[-3.4852690697,42.9362792969],"type":"Point"}
}