{
  "type": "Feature",
  "properties": {
    "addr:full":"Avda Madrid, 23 Don Benito Badajoz 06400",
    "addr:housenumber":"23",
    "addr:postcode":"06400",
    "addr:street":"Avda Madrid",
    "iso:country":"ES",
    "sg:address":"Avda Madrid, 23",
    "sg:city":"Don Benito",
    "sg:orig_category":"Garajes De Veh\u00cdculos",
    "sg:phone":"+34 924 80 35 32",
    "sg:postcode":"06400",
    "sg:province":"Badajoz",
    "wof:name":"Talleres Mera Villanovense S.l.",
    "wof:placetype":"venue"
},
  "geometry": {"coordinates":[-5.8557801247,38.965587616],"type":"Point"}
}