{
  "type": "Feature",
  "properties": {
    "addr:full":"Rua Real, 38 Ponteareas Pontevedra 36860",
    "addr:housenumber":"38",
    "addr:postcode":"36860",
    "addr:street":"Rua Real",
    "iso:country":"ES",
    "sg:address":"Rua Real, 38",
    "sg:city":"Ponteareas",
    "sg:orig_category":"Electricidad (montaje, Ensamblaje De Componentes)",
    "sg:phone":"+34 986 64 07 55",
    "sg:postcode":"36860",
    "sg:province":"Pontevedra",
    "wof:name":"Autos Carrera Martinez Sl",
    "wof:placetype":"venue"
},
  "geometry": {"coordinates":[-8.5056495667,42.1771125793],"type":"Point"}
}