{
  "type": "Feature",
  "properties": {
    "addr:full":"Calle de Mariano Garcia Martin, 38 Torre Esteban Hambran Toledo 45920",
    "addr:housenumber":"38",
    "addr:postcode":"45920",
    "addr:street":"Calle De Mariano Garcia Martin",
    "iso:country":"ES",
    "sg:address":"Calle de Mariano Garcia Martin, 38",
    "sg:city":"Torre Esteban Hambran",
    "sg:orig_category":"Electrodom\u00c9sticos (al Por Menor)",
    "sg:phone":"+34 925 79 53 84",
    "sg:postcode":"45920",
    "sg:province":"Toledo",
    "wof:name":"Bautista Chozas Jauret",
    "wof:placetype":"venue"
},
  "geometry": {"coordinates":[-4.025138855,39.8618774414],"type":"Point"}
}