{
  "type": "Feature",
  "properties": {
    "addr:full":"Calle de Palacio El, 47 Vegadeo Asturias 33770",
    "addr:housenumber":"47",
    "addr:postcode":"33770",
    "addr:street":"Calle De Palacio El",
    "iso:country":"ES",
    "sg:address":"Calle de Palacio El, 47",
    "sg:city":"Vegadeo",
    "sg:orig_category":"Arquitectos",
    "sg:phone":"+34 985 47 60 28",
    "sg:postcode":"33770",
    "sg:province":"Asturias",
    "wof:name":"Mendez Pinto Manuel",
    "wof:placetype":"venue"
},
  "geometry": {"coordinates":[-7.0480971336,43.4644241333],"type":"Point"}
}