{
  "type": "Feature",
  "properties": {
    "addr:full":"Ctra Sta Creu Olorda A Sarria, 18 Barcelona Barcelona 08017",
    "addr:housenumber":"18",
    "addr:postcode":"08017",
    "addr:street":"Ctra Sta Creu Olorda;Sarria",
    "iso:country":"ES",
    "sg:address":"Ctra Sta Creu Olorda A Sarria, 18",
    "sg:city":"Barcelona",
    "sg:orig_category":"Agencias Y Agentes Comerciales, Representantes",
    "sg:phone":"+34 934 06 92 00",
    "sg:postcode":"08017",
    "sg:province":"Barcelona",
    "wof:name":"Salra Guasch Salvador",
    "wof:placetype":"venue"
},
  "geometry": {"coordinates":[2.1034219265,41.409828186],"type":"Point"}
}