{
  "type": "Feature",
  "properties": {
    "iso:country":"ES",
    "sg:address":"Ctra Antigua De El Pardo A Fuencarral, Km. 0003,3",
    "sg:city":"Madrid",
    "sg:orig_category":"Negocio De Materiales De Construcci\u00d3n",
    "sg:phone":"+34 913 72 12 52",
    "sg:postcode":"28034",
    "sg:province":"Madrid",
    "wof:name":"Suministros Pedro Blanco S.l.",
    "wof:placetype":"venue"
},
  "geometry": {"coordinates":[-3.6949870586,40.5004768372],"type":"Point"}
}