{
  "type": "Feature",
  "properties": {
    "addr:full":"Avda Tres Cruces, 5 Valencia Valencia 46018",
    "addr:housenumber":"5",
    "addr:postcode":"46018",
    "addr:street":"Avda Tres Cruces",
    "iso:country":"ES",
    "sg:address":"Avda Tres Cruces, 5",
    "sg:city":"Valencia",
    "sg:orig_category":"Molduras, Junquillos, Listones Y Molduras Perforadas",
    "sg:phone":"+34 963 70 76 00",
    "sg:postcode":"46018",
    "sg:province":"Valencia",
    "wof:name":"Bar Montse S.l.l.",
    "wof:placetype":"venue"
},
  "geometry": {"coordinates":[-0.405862987,39.4678115845],"type":"Point"}
}