{
  "type": "Feature",
  "properties": {
    "iso:country":"ES",
    "sg:address":"Calle de Castilla-leon, 10",
    "sg:city":"Barakaldo",
    "sg:orig_category":"Tintorer\u00cdas, Limpieza En Seco",
    "sg:phone":"+34 944 37 43 17",
    "sg:postcode":"48901",
    "sg:province":"Vizcaya",
    "wof:name":"Eladio Gradaille Novoa (tintoreria La Rapida)",
    "wof:placetype":"venue"
},
  "geometry": {"coordinates":[-2.9857161045,43.2953262329],"type":"Point"}
}