{
  "type": "Feature",
  "properties": {
    "iso:country":"ES",
    "sg:address":"Ctra Alcora, Km. 0010,5",
    "sg:city":"Castellon De La Plana",
    "sg:orig_category":"Asociaciones Y Clubs Deportivos",
    "sg:phone":"+34 964 20 99 31",
    "sg:postcode":"12006",
    "sg:province":"Castell\u00f3n",
    "wof:name":"Club Frontenis Castellon",
    "wof:placetype":"venue"
},
  "geometry": {"coordinates":[-0.1404139996,40.0213813782],"type":"Point"}
}