{
  "type": "Feature",
  "properties": {
    "iso:country":"ES",
    "sg:address":"Calle de Belgica, 11",
    "sg:city":"Zaragoza",
    "sg:orig_category":"Asociaciones Y Clubs Deportivos",
    "sg:phone":"+34 976 53 32 96",
    "sg:postcode":"50017",
    "sg:province":"Zaragoza",
    "sg:website":"www.usuarios.com /.ib307618",
    "wof:name":"Kf Y Tc 2002 S.l.",
    "wof:placetype":"venue"
},
  "geometry": {"coordinates":[-0.9058352709,41.650932312],"type":"Point"}
}