{
  "type": "Feature",
  "properties": {
    "iso:country":"ES",
    "sg:address":"Calle de Princesa Guayarmina, 24",
    "sg:city":"Gran Tarajal",
    "sg:orig_category":"Peluqueros: De Se\u00d1oras",
    "sg:phone":"+34 928 16 20 97",
    "sg:postcode":"35620",
    "sg:province":"Las Palmas",
    "wof:name":"Rodriguez Martin Maria Del Carmen",
    "wof:placetype":"venue"
},
  "geometry": {"coordinates":[-14.0196876526,28.2130260468],"type":"Point"}
}