{
  "type": "Feature",
  "properties": {
    "iso:country":"ES",
    "sg:address":"Ronda De Pontevedra, 75",
    "sg:city":"Melide",
    "sg:orig_category":"Escayola Y Productos De Escayola (fabricaci\u00d3n, Al Por Mayor)",
    "sg:phone":"+34 981 50 59 51",
    "sg:postcode":"15800",
    "sg:province":"La Coru\u00f1a",
    "wof:name":"Escayolas Sito S.l.",
    "wof:placetype":"venue"
},
  "geometry": {"coordinates":[-8.015619278,42.910369873],"type":"Point"}
}