{
  "type": "Feature",
  "properties": {
    "addr:full":"Calle de Ramon Y Cajal, 2 Cobeja Toledo 45291",
    "addr:housenumber":"2",
    "addr:postcode":"45291",
    "addr:street":"Calle De Ramon Y Cajal",
    "iso:country":"ES",
    "sg:address":"Calle de Ramon Y Cajal, 2",
    "sg:city":"Cobeja",
    "sg:orig_category":"Construcciones Met\u00c1licas",
    "sg:phone":"+34 925 55 11 63",
    "sg:postcode":"45291",
    "sg:province":"Toledo",
    "wof:name":"Rodriguez Redondo Juan Jose",
    "wof:placetype":"venue"
},
  "geometry": {"coordinates":[-3.8577239513,40.0243034363],"type":"Point"}
}