{
  "type": "Feature",
  "properties": {
    "iso:country":"ES",
    "sg:address":"Carrer de Dante Alighieri, 55",
    "sg:city":"Barcelona",
    "sg:orig_category":"Tintes (fabricaci\u00d3n, Al Por Mayor)",
    "sg:phone":"+34 934 07 07 87",
    "sg:postcode":"08032",
    "sg:province":"Barcelona",
    "wof:name":"Miro Ysal Concepcion",
    "wof:placetype":"venue"
},
  "geometry": {"coordinates":[2.1594610214,41.4280815125],"type":"Point"}
}