{
  "type": "Feature",
  "properties": {
    "addr:full":"Carrer de Josep Ant Cabanyes, 9 Poligon Industrial De Can Valero Islas Baleares 07011",
    "addr:housenumber":"9",
    "addr:postcode":"07011",
    "addr:street":"Carrer De Josep Ant Cabanyes;Industrial;Islas",
    "iso:country":"ES",
    "sg:address":"Carrer de Josep Ant Cabanyes, 9",
    "sg:city":"Poligon Industrial De Can Valero",
    "sg:orig_category":"Delegados, Agentes De Tr\u00c1nsito, Auxiliares De Transporte Internacional",
    "sg:phone":"+34 971 49 90 46",
    "sg:postcode":"07011",
    "sg:province":"Islas Baleares",
    "wof:name":"Arbona Bernabeu Juan Francisco",
    "wof:placetype":"venue"
},
  "geometry": {"coordinates":[2.8577105999,39.5341796875],"type":"Point"}
}