{
  "type": "Feature",
  "properties": {
    "iso:country":"ES",
    "sg:address":"Calle de Reoyo, S/n",
    "sg:city":"Castromocho",
    "sg:orig_category":"Cooperativas Agr\u00cdcolas",
    "sg:phone":"+34 979 83 57 14",
    "sg:postcode":"34150",
    "sg:province":"Palencia",
    "wof:name":"Sociedad Cooperativa Agricola Ganadera Cortecam S.l.",
    "wof:placetype":"venue"
},
  "geometry": {"coordinates":[-4.8251228333,42.0321044922],"type":"Point"}
}