{
  "type": "Feature",
  "properties": {
    "addr:full":"Calle de Juan Xxiii, 6 Huercal-overa Almer\u00eda 04600",
    "addr:housenumber":"6",
    "addr:postcode":"04600",
    "addr:street":"Calle De Juan Xxiii;Almeri\u0301A",
    "iso:country":"ES",
    "sg:address":"Calle de Juan Xxiii, 6",
    "sg:city":"Huercal-overa",
    "sg:orig_category":"Electrodom\u00c9sticos (al Por Menor)",
    "sg:phone":"+34 950 47 08 86",
    "sg:postcode":"04600",
    "sg:province":"Almer\u00eda",
    "wof:name":"Montajes Gopasur S.c.",
    "wof:placetype":"venue"
},
  "geometry": {"coordinates":[-1.945152998,37.3928794861],"type":"Point"}
}