{
  "type": "Feature",
  "properties": {
    "iso:country":"ES",
    "sg:address":"Calle de Parque Ferial (del), 29",
    "sg:city":"Alcorcon",
    "sg:orig_category":"Diet\u00c9tica: Productos Biol\u00d3gicos, Naturales Y Diet\u00c9ticos (fabricaci\u00d3n, Al Por Mayor)",
    "sg:phone":"+34 916 43 70 55",
    "sg:postcode":"28923",
    "sg:province":"Madrid",
    "sg:website":"www.beverly.es",
    "wof:name":"Suplements Beverly S.a.",
    "wof:placetype":"venue"
},
  "geometry": {"coordinates":[-3.8190000057,40.3339767456],"type":"Point"}
}