{
  "type": "Feature",
  "properties": {
    "iso:country":"ES",
    "sg:address":"Ctra Villamartin, 22",
    "sg:city":"Montellano",
    "sg:orig_category":"Transportes Por V\u00cdas Navegables",
    "sg:phone":"+34 955 83 10 48",
    "sg:postcode":"41770",
    "sg:province":"Sevilla",
    "wof:name":"Barroso Luis Manuel",
    "wof:placetype":"venue"
},
  "geometry": {"coordinates":[-5.5765991211,36.9964523315],"type":"Point"}
}