{
  "type": "Feature",
  "properties": {
    "addr:full":"Calle de Casta\u00d1o, 40 Entrealamos Madrid 28220",
    "addr:housenumber":"40",
    "addr:postcode":"28220",
    "addr:street":"Calle De Castan\u0303O",
    "iso:country":"ES",
    "sg:address":"Calle de Casta\u00d1o, 40",
    "sg:city":"Entrealamos",
    "sg:orig_category":"Grafistas",
    "sg:phone":"+34 916 39 19 40",
    "sg:postcode":"28220",
    "sg:province":"Madrid",
    "sg:website":"www.gepisa.com",
    "wof:name":"Adan Perales Francisco Jose",
    "wof:placetype":"venue"
},
  "geometry": {"coordinates":[-3.9331858158,40.4829940796],"type":"Point"}
}