{
  "type": "Feature",
  "properties": {
    "iso:country":"ES",
    "sg:address":"Pol Ind Cantalgallo, 20",
    "sg:city":"Aracena",
    "sg:orig_category":"Organismos De Turismo",
    "sg:phone":"+34 959 12 70 45",
    "sg:postcode":"21200",
    "sg:province":"Huelva",
    "sg:website":"www.donana-aracena-aventura.com",
    "wof:name":"Do\u00f1anaventura-aracenaventura S.l.",
    "wof:placetype":"venue"
},
  "geometry": {"coordinates":[-6.5612440109,37.8929443359],"type":"Point"}
}