{
  "type": "Feature",
  "properties": {
    "addr:full":"Calle de Aldatseta, 4 Bermeo Vizcaya 48370",
    "addr:housenumber":"4",
    "addr:postcode":"48370",
    "addr:street":"Calle De Aldatseta",
    "iso:country":"ES",
    "sg:address":"Calle de Aldatseta, 4",
    "sg:city":"Bermeo",
    "sg:orig_category":"Librer\u00cdas",
    "sg:phone":"+34 946 88 03 64",
    "sg:postcode":"48370",
    "sg:province":"Vizcaya",
    "wof:name":"Laura Atela Garai",
    "wof:placetype":"venue"
},
  "geometry": {"coordinates":[-2.7242054939,43.4200286865],"type":"Point"}
}