{
  "type": "Feature",
  "properties": {
    "addr:full":"Calle de San Juan De La Cruz, 20 Avila \u00c1vila 05001",
    "addr:housenumber":"20",
    "addr:postcode":"05001",
    "addr:street":"Calle De San Juan;La Cruz;A\u0301Vila",
    "iso:country":"ES",
    "sg:address":"Calle de San Juan De La Cruz, 20",
    "sg:city":"Avila",
    "sg:orig_category":"Procuradores",
    "sg:phone":"+34 920 22 20 58",
    "sg:postcode":"05001",
    "sg:province":"\u00c1vila",
    "wof:name":"Sastre Legido Maria Jesus",
    "wof:placetype":"venue"
},
  "geometry": {"coordinates":[-4.6922221184,40.6542625427],"type":"Point"}
}