{
  "type": "Feature",
  "properties": {
    "iso:country":"ES",
    "sg:address":"Calle de Quijote (don), 36",
    "sg:city":"Socuellamos",
    "sg:orig_category":"Arquitectos",
    "sg:phone":"+34 926 53 28 26",
    "sg:postcode":"13630",
    "sg:province":"Ciudad Real",
    "wof:name":"Izquierdo Solana Lourdes",
    "wof:placetype":"venue"
},
  "geometry": {"coordinates":[-2.7905049324,39.2865600586],"type":"Point"}
}