{
  "type": "Feature",
  "properties": {
    "iso:country":"ES",
    "sg:address":"Carrer de Cavallada, S/n",
    "sg:city":"Prades",
    "sg:orig_category":"Centros De Educaci\u00d3n Especial",
    "sg:phone":"+34 977 86 80 11",
    "sg:postcode":"43364",
    "sg:province":"Tarragona",
    "wof:name":"Ajuntament De Prades",
    "wof:placetype":"venue"
},
  "geometry": {"coordinates":[0.9884451032,41.3087615967],"type":"Point"}
}