{
  "type": "Feature",
  "properties": {
    "addr:full":"Urb Parrita, 31 Ronquillo Sevilla 41880",
    "addr:housenumber":"31",
    "addr:postcode":"41880",
    "addr:street":"Parrita",
    "iso:country":"ES",
    "sg:address":"Urb Parrita, 31",
    "sg:city":"Ronquillo",
    "sg:orig_category":"Cr\u00cda De Animales De Caza Menor",
    "sg:phone":"+34 955 95 20 57",
    "sg:postcode":"41880",
    "sg:province":"Sevilla",
    "wof:name":"De La Cal Solis David",
    "wof:placetype":"venue"
},
  "geometry": {"coordinates":[-6.1765861511,37.7274780273],"type":"Point"}
}