{
  "type": "Feature",
  "properties": {
    "addr:full":"Carr Lluis Companys, 1 Lleida Lleida 25003",
    "addr:housenumber":"1",
    "addr:postcode":"25003",
    "addr:street":"Carr Lluis Companys",
    "iso:country":"ES",
    "sg:address":"Carr Lluis Companys, 1",
    "sg:city":"Lleida",
    "sg:orig_category":"Asesor\u00cda Sobre Comunicaci\u00d3n De Empresas",
    "sg:phone":"+34 973 28 00 53",
    "sg:postcode":"25003",
    "sg:province":"Lleida",
    "wof:name":"Clavel Vila Merce",
    "wof:placetype":"venue"
},
  "geometry": {"coordinates":[0.6160899997,41.611831665],"type":"Point"}
}