{
  "type": "Feature",
  "properties": {
    "iso:country":"ES",
    "sg:address":"Carrer de Mura, 162",
    "sg:city":"Terrassa",
    "sg:orig_category":"Promotores Constructores",
    "sg:phone":"+34 937 31 70 95",
    "sg:postcode":"08227",
    "sg:province":"Barcelona",
    "wof:name":"Construcciones Finvalex, S.l.",
    "wof:placetype":"venue"
},
  "geometry": {"coordinates":[2.0390369892,41.5728187561],"type":"Point"}
}