{
  "type": "Feature",
  "properties": {
    "iso:country":"ES",
    "sg:address":"Zapateria, 54",
    "sg:city":"Iru\u00f1a",
    "sg:orig_category":"Arquitectos",
    "sg:phone":"+34 948 22 15 20",
    "sg:postcode":"31001",
    "sg:province":"Navarra",
    "wof:name":"I\u00f1iguez Villanueva Manuel",
    "wof:placetype":"venue"
},
  "geometry": {"coordinates":[-1.6449719667,42.8170547485],"type":"Point"}
}