{
  "type": "Feature",
  "properties": {
    "iso:country":"ES",
    "sg:address":"Pg Marina, 175",
    "sg:city":"Castelldefels",
    "sg:orig_category":"Electricidad: Instaladores",
    "sg:phone":"+34 936 36 09 12",
    "sg:postcode":"08860",
    "sg:province":"Barcelona",
    "wof:name":"Instalaciones Electricas-tomas S.l.",
    "wof:placetype":"venue"
},
  "geometry": {"coordinates":[1.9705580473,41.2674865723],"type":"Point"}
}