{
  "type": "Feature",
  "properties": {
    "addr:full":"Pase Sagasta, 72 Zaragoza Zaragoza 50006",
    "addr:housenumber":"72",
    "addr:postcode":"50006",
    "iso:country":"ES",
    "sg:address":"Pase Sagasta, 72",
    "sg:city":"Zaragoza",
    "sg:classifiers":[
        {
            "category":"Professional",
            "subcategory":"Research",
            "type":"Services"
        }
    ],
    "sg:phone":"+34 976 25 27 14",
    "sg:postcode":"50006",
    "sg:province":"Zaragoza",
    "sg:tags":[
        "mercado",
        "de",
        "estudios"
    ],
    "sg:website":"www.mercadinamica.com",
    "wof:name":"Merca Dinamica S.a.",
    "wof:placetype":"venue"
},
  "geometry": {"coordinates":[-0.8866320252,41.6397781372],"type":"Point"}
}