{
  "type": "Feature",
  "properties": {
    "addr:full":"Plaz Mayor, 1 Ledesma Salamanca 37100",
    "addr:housenumber":"1",
    "addr:postcode":"37100",
    "addr:street":"Plaz Mayor",
    "iso:country":"ES",
    "sg:address":"Plaz Mayor, 1",
    "sg:city":"Ledesma",
    "sg:orig_category":"Ense\u00d1anza, Formaci\u00d3n Profesional: Aprendizaje",
    "sg:phone":"+34 923 57 00 15",
    "sg:postcode":"37100",
    "sg:province":"Salamanca",
    "wof:name":"Ayuntamiento De Ledesma",
    "wof:placetype":"venue"
},
  "geometry": {"coordinates":[-5.9984035492,41.0907211304],"type":"Point"}
}