{
  "type": "Feature",
  "properties": {
    "addr:full":"Calle de Ciudad De Mexico (de), 2 Tres Cantos Madrid 28760",
    "addr:housenumber":"2",
    "addr:postcode":"28760",
    "addr:street":"Calle De Ciudad De Mexico De",
    "iso:country":"ES",
    "sg:address":"Calle de Ciudad De Mexico (de), 2",
    "sg:city":"Tres Cantos",
    "sg:orig_category":"Agencias Y Asesores De Publicidad",
    "sg:phone":"+34 918 04 49 96",
    "sg:postcode":"28760",
    "sg:province":"Madrid",
    "wof:name":"Martin Blanco Jose Carlos",
    "wof:placetype":"venue"
},
  "geometry": {"coordinates":[-3.7051596642,40.596572876],"type":"Point"}
}