{
  "type": "Feature",
  "properties": {
    "iso:country":"ES",
    "sg:address":"Carrer de Doctor Carulla, 4",
    "sg:city":"Barcelona",
    "sg:orig_category":"Inmobiliaria (agencias)",
    "sg:phone":"+34 932 04 45 40",
    "sg:postcode":"08017",
    "sg:province":"Barcelona",
    "wof:name":"Dos Dos Dos S.l.",
    "wof:placetype":"venue"
},
  "geometry": {"coordinates":[2.127753973,41.3989334106],"type":"Point"}
}