{
  "type": "Feature",
  "properties": {
    "iso:country":"ES",
    "sg:address":"Av Granvia, S/n",
    "sg:city":"Hospitalet Llobregat",
    "sg:orig_category":"Internados & Ense\u00d1anza Privada",
    "sg:phone":"+34 933 35 16 00",
    "sg:postcode":"08...",
    "sg:province":"Barcelona",
    "wof:name":"Centro Cultural Y Deportivo Xaloc S.a.",
    "wof:placetype":"venue"
},
  "geometry": {"coordinates":[2.1222119331,41.3551559448],"type":"Point"}
}