{
  "type": "Feature",
  "properties": {
    "addr:full":"Calle de Toneleros, 19 Dos Hermanas Sevilla 41700",
    "addr:housenumber":"19",
    "addr:postcode":"41700",
    "addr:street":"Calle De Toneleros",
    "iso:country":"ES",
    "sg:address":"Calle de Toneleros, 19",
    "sg:city":"Dos Hermanas",
    "sg:orig_category":"Barnizadores",
    "sg:phone":"+34 955 66 33 12",
    "sg:postcode":"41700",
    "sg:province":"Sevilla",
    "wof:name":"Garcia Ponce Manuel",
    "wof:placetype":"venue"
},
  "geometry": {"coordinates":[-5.9263978004,37.2809066772],"type":"Point"}
}