{
  "type": "Feature",
  "properties": {
    "addr:full":"Carr Es Cos De Gracia, 19 Mao Islas Baleares 07702",
    "addr:housenumber":"19",
    "addr:postcode":"07702",
    "addr:street":"Carr Es;Gracia",
    "iso:country":"ES",
    "sg:address":"Carr Es Cos De Gracia, 19",
    "sg:city":"Mao",
    "sg:orig_category":"Fabricaci\u00d3n De Quesos",
    "sg:phone":"+34 971 35 08 64",
    "sg:postcode":"07702",
    "sg:province":"Islas Baleares",
    "wof:name":"Subaida S.l.",
    "wof:placetype":"venue"
},
  "geometry": {"coordinates":[4.2624521255,39.8873138428],"type":"Point"}
}