{
  "type": "Feature",
  "properties": {
    "addr:full":"Calle de Aragon (de), 9 Jaca Huesca 22700",
    "addr:postcode":"22700",
    "addr:street":"Calle De Aragon De 9",
    "iso:country":"ES",
    "sg:address":"Calle de Aragon (de), 9",
    "sg:city":"Jaca",
    "sg:orig_category":"Venta, Instalaci\u00d3n De Calefacci\u00d3n",
    "sg:phone":"+34 974 36 20 23",
    "sg:postcode":"22700",
    "sg:province":"Huesca",
    "wof:name":"Campo Lanuza Lorenzo",
    "wof:placetype":"venue"
},
  "geometry": {"coordinates":[-0.548856318,42.5727615356],"type":"Point"}
}