{
  "type": "Feature",
  "properties": {
    "addr:full":"San Fermin, 61 Iru\u00f1a Navarra 31003",
    "addr:housenumber":"61",
    "addr:postcode":"31003",
    "addr:street":"San Fermin",
    "iso:country":"ES",
    "sg:address":"San Fermin, 61",
    "sg:city":"Iru\u00f1a",
    "sg:orig_category":"Comercio De Piezas De Recambio Y De Accesorios De Veh\u00cdculos, Veh\u00cdculos Industriales",
    "sg:phone":"+34 948 24 36 15",
    "sg:postcode":"31003",
    "sg:province":"Navarra",
    "wof:name":"Exclusivas Fena S.l.",
    "wof:placetype":"venue"
},
  "geometry": {"coordinates":[-1.6418919563,42.8102607727],"type":"Point"}
}