{
  "type": "Feature",
  "properties": {
    "addr:full":"Calle de Carre\u00d1o Miranda, 33 Mieres Asturias 33600",
    "addr:housenumber":"33",
    "addr:postcode":"33600",
    "addr:street":"Calle De Carren\u0303O Miranda",
    "iso:country":"ES",
    "sg:address":"Calle de Carre\u00d1o Miranda, 33",
    "sg:city":"Mieres",
    "sg:orig_category":"Loter\u00cda Y T\u00d3mbola",
    "sg:phone":"+34 985 45 22 92",
    "sg:postcode":"33600",
    "sg:province":"Asturias",
    "wof:name":"Fernandez Diaz Maria Teresa",
    "wof:placetype":"venue"
},
  "geometry": {"coordinates":[-5.7759714127,43.252494812],"type":"Point"}
}