{
  "type": "Feature",
  "properties": {
    "iso:country":"ES",
    "sg:address":"Calle de San Vicente Martir, 300",
    "sg:city":"Valencia",
    "sg:orig_category":"Reparaci\u00d3n Y Restauraci\u00d3n De Objetos Diversos",
    "sg:phone":"+34 963 77 15 44",
    "sg:postcode":"46017",
    "sg:province":"Valencia",
    "wof:name":"San Juan Garcia Federico",
    "wof:placetype":"venue"
},
  "geometry": {"coordinates":[-0.3850030005,39.4514007568],"type":"Point"}
}