{
  "type": "Feature",
  "properties": {
    "addr:full":"Calle de Calera, 11 Burgos Burgos 09002",
    "addr:housenumber":"11",
    "addr:postcode":"09002",
    "addr:street":"Calle De Calera",
    "iso:country":"ES",
    "sg:address":"Calle de Calera, 11",
    "sg:city":"Burgos",
    "sg:orig_category":"Librer\u00cdas",
    "sg:phone":"+34 947 25 56 05",
    "sg:postcode":"09002",
    "sg:province":"Burgos",
    "wof:name":"Ceballos Lara Luis",
    "wof:placetype":"venue"
},
  "geometry": {"coordinates":[-3.7013521194,42.3391075134],"type":"Point"}
}