{
  "type": "Feature",
  "properties": {
    "addr:full":"Carrer de Gran, 27 Esparreguera Barcelona 08292",
    "addr:housenumber":"27",
    "addr:postcode":"08292",
    "addr:street":"Carrer De Gran",
    "iso:country":"ES",
    "sg:address":"Carrer de Gran, 27",
    "sg:city":"Esparreguera",
    "sg:orig_category":"Art\u00cdculos De Decoraci\u00d3n",
    "sg:phone":"+34 937 77 79 27",
    "sg:postcode":"08292",
    "sg:province":"Barcelona",
    "wof:name":"Majuki S.c.p.",
    "wof:placetype":"venue"
},
  "geometry": {"coordinates":[1.8689899445,41.5402984619],"type":"Point"}
}