{
  "type": "Feature",
  "properties": {
    "iso:country":"ES",
    "sg:address":"Plaz Arriaga, 1",
    "sg:city":"Bilbao",
    "sg:orig_category":"Teatros Y Salas De Espect\u00c1culos",
    "sg:phone":"+34 944 03 55 00",
    "sg:postcode":"48005",
    "sg:province":"Vizcaya",
    "sg:website":"www.teatroarriaga.com",
    "wof:name":"C.a.c. Teatro Arriaga S.a.",
    "wof:placetype":"venue"
},
  "geometry": {"coordinates":[-2.9244909286,43.2592124939],"type":"Point"}
}