{
  "type": "Feature",
  "properties": {
    "addr:full":"Calle de Miravalles, 39 Vitoria-gasteiz \u00c1lava 01013",
    "addr:housenumber":"39",
    "addr:postcode":"01013",
    "addr:street":"Calle De Miravalles",
    "iso:country":"ES",
    "sg:address":"Calle de Miravalles, 39",
    "sg:city":"Vitoria-gasteiz",
    "sg:orig_category":"Rectificaci\u00d3n, Mecanizado, Fresado",
    "sg:phone":"+34 945 27 58 48",
    "sg:postcode":"01013",
    "sg:province":"\u00c1lava",
    "wof:name":"Unceta Desarrollos Tecnicos Y Fabricacion S.l.",
    "wof:placetype":"venue"
},
  "geometry": {"coordinates":[-2.6399009228,42.8709449768],"type":"Point"}
}