{
  "type": "Feature",
  "properties": {
    "addr:full":"Calle de El Nogal, S/n Iscar Valladolid 47420",
    "addr:postcode":"47420",
    "addr:street":"Calle De El Nogal S / N Iscar",
    "iso:country":"ES",
    "sg:address":"Calle de El Nogal, S/n",
    "sg:city":"Iscar",
    "sg:orig_category":"Pintura Industrial (trabajos De)",
    "sg:phone":"+34 983 62 02 24",
    "sg:postcode":"47420",
    "sg:province":"Valladolid",
    "wof:name":"Gomez Catalina S.l.",
    "wof:placetype":"venue"
},
  "geometry": {"coordinates":[-4.545003891,41.3572006226],"type":"Point"}
}