{
  "type": "Feature",
  "properties": {
    "iso:country":"ES",
    "sg:address":"Ctra Vilches, 7",
    "sg:city":"Ubeda",
    "sg:classifiers":[
        {
            "category":"Autos & Motor Vehicles",
            "subcategory":"Automobile Sales",
            "type":"Retail Goods"
        }
    ],
    "sg:phone":"+34 953 79 07 96",
    "sg:postcode":"23400",
    "sg:province":"Ja\u00e9n",
    "wof:name":"Mahedero Cano Rogelio",
    "wof:placetype":"venue"
},
  "geometry": {"coordinates":[-3.3708982468,38.0233268738],"type":"Point"}
}