{
  "type": "Feature",
  "properties": {
    "iso:country":"ES",
    "sg:address":"Calle de Arturo Soria, 348",
    "sg:city":"Madrid",
    "sg:orig_category":"Empresarios",
    "sg:phone":"+34 917 68 03 21",
    "sg:postcode":"28033",
    "sg:province":"Madrid",
    "wof:name":"Intercivil S.a.",
    "wof:placetype":"venue"
},
  "geometry": {"coordinates":[-3.6642765999,40.4827308655],"type":"Point"}
}