{
  "type": "Feature",
  "properties": {
    "iso:country":"ES",
    "sg:address":"Av Republica Argentina, 273",
    "sg:city":"Barcelona",
    "sg:orig_category":"Zapater\u00cdas",
    "sg:phone":"+34 934 18 34 02",
    "sg:postcode":"08023",
    "sg:province":"Barcelona",
    "wof:name":"Mamys S.c.p",
    "wof:placetype":"venue"
},
  "geometry": {"coordinates":[2.1383419037,41.4134902954],"type":"Point"}
}