{
  "type": "Feature",
  "properties": {
    "iso:country":"ES",
    "sg:address":"Calle de Hermandad De Donantes De Sangre, 1",
    "sg:city":"Madrid",
    "sg:orig_category":"Molduras, Junquillos, Listones Y Molduras Perforadas",
    "sg:phone":"+34 917 95 17 76",
    "sg:postcode":"28041",
    "sg:province":"Madrid",
    "wof:name":"Gallardo Alvarez Juan Jose",
    "wof:placetype":"venue"
},
  "geometry": {"coordinates":[-3.6994841099,40.3548126221],"type":"Point"}
}