{
  "type": "Feature",
  "properties": {
    "addr:full":"Calle de Guma, 35 Caspe Zaragoza 50700",
    "addr:housenumber":"35",
    "addr:postcode":"50700",
    "addr:street":"Calle De Guma",
    "iso:country":"ES",
    "sg:address":"Calle de Guma, 35",
    "sg:city":"Caspe",
    "sg:orig_category":"Centros De Educaci\u00d3n Especial",
    "sg:phone":"+34 976 63 22 59",
    "sg:postcode":"50700",
    "sg:province":"Zaragoza",
    "wof:name":"Ayuntamiento De Caspe",
    "wof:placetype":"venue"
},
  "geometry": {"coordinates":[-0.043287199,41.2367630005],"type":"Point"}
}