{
  "type": "Feature",
  "properties": {
    "addr:full":"Trva Antonio Palacios 2, 10 Porri\u00f1o Pontevedra 36400",
    "addr:housenumber":"2 10",
    "addr:postcode":"36400",
    "addr:street":"Trva Antonio Palacios",
    "iso:country":"ES",
    "sg:address":"Trva Antonio Palacios 2, 10",
    "sg:city":"Porri\u00f1o",
    "sg:orig_category":"T\u00c9cnicos Veterinarios",
    "sg:phone":"+34 986 33 15 85",
    "sg:postcode":"36400",
    "sg:province":"Pontevedra",
    "wof:name":"Lucchini Gonzalez Victor Raul",
    "wof:placetype":"venue"
},
  "geometry": {"coordinates":[-8.6197547913,42.1615791321],"type":"Point"}
}