{
  "type": "Feature",
  "properties": {
    "iso:country":"ES",
    "sg:address":"Plaz San Pedro Nolasco, 4",
    "sg:city":"Valencia",
    "sg:orig_category":"Electrodom\u00c9sticos (al Por Menor)",
    "sg:phone":"+34 963 49 72 21",
    "sg:postcode":"46009",
    "sg:province":"Valencia",
    "wof:name":"Tortosa Pellicer Carlos Francisco",
    "wof:placetype":"venue"
},
  "geometry": {"coordinates":[-0.3742789924,39.4836044312],"type":"Point"}
}