{
  "type": "Feature",
  "properties": {
    "iso:country":"ES",
    "sg:address":"Calle de Ramon Calabuig, 44",
    "sg:city":"Madrid",
    "sg:orig_category":"Adaptaciones, Acondicionamientos Especiales Para Veh\u00cdculos, Veh\u00cdculos Industriales",
    "sg:phone":"+34 914 78 53 39",
    "sg:postcode":"28053",
    "sg:province":"Madrid",
    "wof:name":"Tapiceris Textilauto S.l.",
    "wof:placetype":"venue"
},
  "geometry": {"coordinates":[-3.668804884,40.3941574097],"type":"Point"}
}