{
  "type": "Feature",
  "properties": {
    "iso:country":"ES",
    "sg:address":"Calle de Antonio Gonzalez Flores, 4",
    "sg:city":"Jerez De La Frontera",
    "sg:orig_category":"Pescader\u00cdas (al Por Menor)",
    "sg:phone":"+34 956 33 77 09",
    "sg:postcode":"11405",
    "sg:province":"C\u00e1diz",
    "wof:name":"Cordero Suarez Luisa",
    "wof:placetype":"venue"
},
  "geometry": {"coordinates":[-6.1113677025,36.6929321289],"type":"Point"}
}