{
  "type": "Feature",
  "properties": {
    "iso:country":"ES",
    "sg:address":"Carrer de Llobregos, 105",
    "sg:city":"Barcelona",
    "sg:orig_category":"Agencias Y Agentes Comerciales, Representantes",
    "sg:phone":"+34 934 07 07 91",
    "sg:postcode":"08032",
    "sg:province":"Barcelona",
    "wof:name":"Del Pino Diaz Sandra",
    "wof:placetype":"venue"
},
  "geometry": {"coordinates":[2.1577470303,41.4251823425],"type":"Point"}
}