{
  "type": "Feature",
  "properties": {
    "addr:full":"Avgd Alcalde Porqueres, 74 Lleida Lleida 25005",
    "addr:housenumber":"74",
    "addr:postcode":"25005",
    "addr:street":"Alcalde Porqueres",
    "iso:country":"ES",
    "sg:address":"Avgd Alcalde Porqueres, 74",
    "sg:city":"Lleida",
    "sg:orig_category":"Farmacias",
    "sg:phone":"+34 973 22 87 57",
    "sg:postcode":"25005",
    "sg:province":"Lleida",
    "wof:name":"Asesores Farmaceuticos Sl",
    "wof:placetype":"venue"
},
  "geometry": {"coordinates":[0.6226481795,41.6275558472],"type":"Point"}
}