{
  "type": "Feature",
  "properties": {
    "addr:full":"C/ Sant Jaume, 51 Ripollet Barcelona 08291",
    "addr:housenumber":"51",
    "addr:postcode":"08291",
    "addr:street":"C / Sant Jaume",
    "iso:country":"ES",
    "sg:address":"C/ Sant Jaume, 51",
    "sg:city":"Ripollet",
    "sg:orig_category":"Cajas De Ahorro",
    "sg:phone":"+34 935 80 46 77",
    "sg:postcode":"08291",
    "sg:province":"Barcelona",
    "sg:website":"www.caixasabadell.es",
    "wof:name":"Caixa D'estalvis Sabadell",
    "wof:placetype":"venue"
},
  "geometry": {"coordinates":[2.1581029892,41.4984054565],"type":"Point"}
}