{
  "type": "Feature",
  "properties": {
    "addr:full":"Carrer de Mas, 93 Hospitalet Llobregat Barcelona 08904",
    "addr:housenumber":"93",
    "addr:postcode":"08904",
    "addr:street":"Carrer De Mas",
    "iso:country":"ES",
    "sg:address":"Carrer de Mas, 93",
    "sg:city":"Hospitalet Llobregat",
    "sg:orig_category":"Charcuter\u00cdas (al Por Mayor)",
    "sg:phone":"+34 934 49 87 17",
    "sg:postcode":"08904",
    "sg:province":"Barcelona",
    "wof:name":"Avis Tadeo Maria Magdalena",
    "wof:placetype":"venue"
},
  "geometry": {"coordinates":[2.1192390919,41.3709068298],"type":"Point"}
}