{
  "type": "Feature",
  "properties": {
    "iso:country":"ES",
    "sg:address":"Barr Fayas, S/n",
    "sg:city":"Proaza",
    "sg:orig_category":"Alquiler De Bicicletas Y Motocicletas",
    "sg:phone":"+34 985 76 10 29",
    "sg:postcode":"33114",
    "sg:province":"Asturias",
    "wof:name":"Zaragoza Viejo Covadonga",
    "wof:placetype":"venue"
},
  "geometry": {"coordinates":[-6.0467429161,43.2278175354],"type":"Point"}
}