{
  "type": "Feature",
  "properties": {
    "iso:country":"ES",
    "sg:address":"Rua Fernando Vi, 2",
    "sg:city":"Ferrol",
    "sg:classifiers":[
        {
            "category":"Taxi",
            "type":"Transportation"
        }
    ],
    "sg:phone":"+34 981 35 11 11",
    "sg:postcode":"15403",
    "sg:province":"La Coru\u00f1a",
    "wof:name":"Asociacion Local De Trabajadores Autonomos Del Auto Taxis",
    "wof:placetype":"venue"
},
  "geometry": {"coordinates":[-8.2260093689,43.4818267822],"type":"Point"}
}