{
  "type": "Feature",
  "properties": {
    "iso:country":"ES",
    "sg:address":"Calle de Jose Miguel Barandiaran, 1",
    "sg:city":"Santurtzi",
    "sg:orig_category":"Muebles, Minoristas",
    "sg:phone":"+34 944 61 19 12",
    "sg:postcode":"48980",
    "sg:province":"Vizcaya",
    "wof:name":"Alonso Ezquerra Francisco Javier",
    "wof:placetype":"venue"
},
  "geometry": {"coordinates":[-3.0103592873,43.3099212646],"type":"Point"}
}