{
  "type": "Feature",
  "properties": {
    "addr:full":"D'avall, 27 Amer Girona 17170",
    "addr:housenumber":"27",
    "addr:postcode":"17170",
    "addr:street":"D'Avall",
    "iso:country":"ES",
    "sg:address":"D'avall, 27",
    "sg:city":"Amer",
    "sg:orig_category":"Mercer\u00cda, Lencer\u00cda (al Por Menor)",
    "sg:phone":"+34 972 43 00 27",
    "sg:postcode":"17170",
    "sg:province":"Girona",
    "wof:name":"Nono Fontas Dolores",
    "wof:placetype":"venue"
},
  "geometry": {"coordinates":[2.6038730145,42.0091972351],"type":"Point"}
}