{
  "type": "Feature",
  "properties": {
    "addr:full":"Avda Andalucia (de), 13 Montilla C\u00f3rdoba 14550",
    "addr:housenumber":"13",
    "addr:postcode":"14550",
    "addr:street":"Avda Andalucia De;Co\u0301Rdoba",
    "iso:country":"ES",
    "sg:address":"Avda Andalucia (de), 13",
    "sg:city":"Montilla",
    "sg:orig_category":"Ense\u00d1anza, Formaci\u00d3n Profesional: Aprendizaje",
    "sg:phone":"+34 957 65 22 00",
    "sg:postcode":"14550",
    "sg:province":"C\u00f3rdoba",
    "wof:name":"Instituto Nacional De La Seguridad Social-direccion Provincial De Cordoba",
    "wof:placetype":"venue"
},
  "geometry": {"coordinates":[-4.6434531212,37.5832557678],"type":"Point"}
}