{
  "type": "Feature",
  "properties": {
    "addr:full":"Calle de Virgen Del Templo (de La), 24 San Fernando De Henares Madrid 28830",
    "addr:housenumber":"24",
    "addr:postcode":"28830",
    "addr:street":"Calle De Virgen Del Templo De La",
    "iso:country":"ES",
    "sg:address":"Calle de Virgen Del Templo (de La), 24",
    "sg:city":"San Fernando De Henares",
    "sg:orig_category":"Guarder\u00cdas",
    "sg:phone":"+34 916 71 11 38",
    "sg:postcode":"28830",
    "sg:province":"Madrid",
    "wof:name":"Abejaro Ruiz Victoria",
    "wof:placetype":"venue"
},
  "geometry": {"coordinates":[-3.53042,40.429111],"type":"Point"}
}