{
  "type": "Feature",
  "properties": {
    "iso:country":"ES",
    "sg:address":"Calle de Villablino, 16",
    "sg:city":"Fuenlabrada",
    "sg:orig_category":"Empresas De Portes Y Mensajer\u00cda",
    "sg:phone":"+34 916 00 81 99",
    "sg:postcode":"28...",
    "sg:province":"Madrid",
    "wof:name":"Endopack S.a.",
    "wof:placetype":"venue"
},
  "geometry": {"coordinates":[-3.7447888851,40.2599983215],"type":"Point"}
}