{
  "type": "Feature",
  "properties": {
    "iso:country":"ES",
    "sg:address":"Agust\u00edn Sebasti\u00e1n, 10",
    "sg:city":"Altura",
    "sg:orig_category":"Aceites Y Grasas Alimentarias (fabricaci\u00d3n, Al Por Mayor)",
    "sg:phone":"+34 964 14 62 91",
    "sg:postcode":"12410",
    "sg:province":"Castell\u00f3n",
    "wof:name":"Almazara La Ratonera Cb",
    "wof:placetype":"venue"
},
  "geometry": {"coordinates":[-0.5085967183,39.8497772217],"type":"Point"}
}