{
  "type": "Feature",
  "properties": {
    "iso:country":"ES",
    "sg:address":"Calle de Octavio Cuartero, 41",
    "sg:city":"Albacete",
    "sg:orig_category":"Soportes L\u00d3gicos, Programas Integradores De Aplicaciones (progiciels)",
    "sg:phone":"+34 967 50 36 59",
    "sg:postcode":"02003",
    "sg:province":"Albacete",
    "sg:website":"www.agm.es",
    "wof:name":"Belmonte Campos Antonio Jose",
    "wof:placetype":"venue"
},
  "geometry": {"coordinates":[-1.860394001,38.9917984009],"type":"Point"}
}