{
  "type": "Feature",
  "properties": {
    "iso:country":"ES",
    "sg:address":"Calle de Lauaxeta Olerkari, 32",
    "sg:city":"Mungia",
    "sg:orig_category":"Venta, Instalaci\u00d3n, Mantenimiento De Chimeneas De Interior Y Accesorios",
    "sg:phone":"+34 946 15 50 97",
    "sg:postcode":"48100",
    "sg:province":"Vizcaya",
    "wof:name":"Castelas Verites, S.l.",
    "wof:placetype":"venue"
},
  "geometry": {"coordinates":[-2.8526449203,43.3572921753],"type":"Point"}
}