{
  "type": "Feature",
  "properties": {
    "iso:country":"ES",
    "sg:address":"Calle de Jose Abascal, 24",
    "sg:city":"Madrid",
    "sg:orig_category":"Agencias De Viajes",
    "sg:phone":"+34 915 93 04 41",
    "sg:postcode":"28003",
    "sg:province":"Madrid",
    "sg:website":"www.haciendohuella.com",
    "wof:name":"Haciendo Huella S.l.",
    "wof:placetype":"venue"
},
  "geometry": {"coordinates":[-3.6959409714,40.4381141663],"type":"Point"}
}