{
  "type": "Feature",
  "properties": {
    "addr:full":"Calle de San Lorenzo, 24 Zaragoza Zaragoza 50001",
    "addr:housenumber":"24",
    "addr:postcode":"50001",
    "addr:street":"Calle De San Lorenzo",
    "iso:country":"ES",
    "sg:address":"Calle de San Lorenzo, 24",
    "sg:city":"Zaragoza",
    "sg:orig_category":"Animales (al Por Menor)",
    "sg:phone":"+34 976 29 46 77",
    "sg:postcode":"50001",
    "sg:province":"Zaragoza",
    "wof:name":"Almudena Compa\u00d1ia De Seguros S.a.",
    "wof:placetype":"venue"
},
  "geometry": {"coordinates":[-0.8754417896,41.6525726318],"type":"Point"}
}