{
  "type": "Feature",
  "properties": {
    "iso:country":"ES",
    "sg:address":"Carrer de Asturies, 7",
    "sg:city":"Barcelona",
    "sg:orig_category":"Cristaler\u00cdas",
    "sg:phone":"+34 932 17 67 41",
    "sg:postcode":"08012",
    "sg:province":"Barcelona",
    "wof:name":"Andreu Magri Carlos",
    "wof:placetype":"venue"
},
  "geometry": {"coordinates":[2.1530256271,41.4026641846],"type":"Point"}
}