{
  "type": "Feature",
  "properties": {
    "iso:country":"ES",
    "sg:address":"Ctra. Seara, 230",
    "sg:city":"Outomuro",
    "sg:orig_category":"Caf\u00c9s, Bares, Cervecer\u00cdas",
    "sg:phone":"+34 988 49 10 52",
    "sg:postcode":"32824",
    "sg:province":"Ourense",
    "wof:name":"Lopez Mourille Manuel",
    "wof:placetype":"venue"
},
  "geometry": {"coordinates":[-8.0225915909,42.2256698608],"type":"Point"}
}