{
  "type": "Feature",
  "properties": {
    "addr:full":"Avda Altamar, 1 Playa San Juan Santa Cruz De Tenerife 38687",
    "addr:housenumber":"1",
    "addr:postcode":"38687",
    "addr:street":"Avda Altamar",
    "iso:country":"ES",
    "sg:address":"Avda Altamar, 1",
    "sg:city":"Playa San Juan",
    "sg:orig_category":"Peluqueros: De Se\u00d1oras",
    "sg:phone":"+34 922 13 80 18",
    "sg:postcode":"38687",
    "sg:province":"Santa Cruz De Tenerife",
    "wof:name":"Caboche Ep Materka  Sylvie",
    "wof:placetype":"venue"
},
  "geometry": {"coordinates":[-16.7886390686,28.1805458069],"type":"Point"}
}