{
  "type": "Feature",
  "properties": {
    "iso:country":"ES",
    "sg:address":"Avda Guadalajara, 2",
    "sg:city":"Madrid",
    "sg:orig_category":"Ropa Y Accesorios",
    "sg:phone":"+34 917 75 77 27",
    "sg:postcode":"28032",
    "sg:province":"Madrid",
    "sg:website":"www.pepejeans.com",
    "wof:name":"Pepe Jeans S.l.",
    "wof:placetype":"venue"
},
  "geometry": {"coordinates":[-3.6208629608,40.4191017151],"type":"Point"}
}