{
  "type": "Feature",
  "properties": {
    "iso:country":"ES",
    "sg:address":"Calle de Alberto Aguilera, 31",
    "sg:city":"Madrid",
    "sg:orig_category":"Cl\u00cdnicas Dentales",
    "sg:phone":"+34 915 42 11 90",
    "sg:postcode":"28015",
    "sg:province":"Madrid",
    "wof:name":"Clinica Grosman S.l.",
    "wof:placetype":"venue"
},
  "geometry": {"coordinates":[-3.7129776478,40.4302253723],"type":"Point"}
}