{
  "type": "Feature",
  "properties": {
    "iso:country":"ES",
    "sg:address":"Calle de Plaza (la), S/n",
    "sg:city":"Secastilla",
    "sg:orig_category":"Aceites Y Grasas Alimentarias (fabricaci\u00d3n, Al Por Mayor)",
    "sg:phone":"+34 974 54 02 32",
    "sg:postcode":"22439",
    "sg:province":"Huesca",
    "wof:name":"Sociedad Agraria De Transformacion Num 1011 La Solana",
    "wof:placetype":"venue"
},
  "geometry": {"coordinates":[0.2671459913,42.1808395386],"type":"Point"}
}