{
  "type": "Feature",
  "properties": {
    "iso:country":"ES",
    "sg:address":"Calle de Gobelaurre, 13",
    "sg:city":"Getxo",
    "sg:orig_category":"Molduras, Junquillos, Listones Y Molduras Perforadas",
    "sg:phone":"+34 944 64 84 74",
    "sg:postcode":"48930",
    "sg:province":"Vizcaya",
    "wof:name":"Pedro Alberto Gonzalez Llaneza-bar Ze\u00f1e",
    "wof:placetype":"venue"
},
  "geometry": {"coordinates":[-3.0068490505,43.3258285522],"type":"Point"}
}