{
  "type": "Feature",
  "properties": {
    "iso:country":"ES",
    "sg:address":"Calle de Alfonso De Castro, 41",
    "sg:city":"Rute",
    "sg:orig_category":"Abogados",
    "sg:phone":"+34 957 53 29 45",
    "sg:postcode":"14960",
    "sg:province":"C\u00f3rdoba",
    "wof:name":"Molina Caballero Jose Maria",
    "wof:placetype":"venue"
},
  "geometry": {"coordinates":[-4.370071888,37.3255233765],"type":"Point"}
}