{
  "type": "Feature",
  "properties": {
    "iso:country":"ES",
    "sg:address":"Av Portell De Granyana, 10",
    "sg:city":"Elche",
    "sg:orig_category":"Ingenier\u00cda, Centros De Estudios (diversos)",
    "sg:phone":"+34 965 45 76 26",
    "sg:postcode":"03202",
    "sg:province":"Alicante",
    "wof:name":"Alema\u00f1 Torres Pedro",
    "wof:placetype":"venue"
},
  "geometry": {"coordinates":[-0.6965811253,38.2682762146],"type":"Point"}
}