{
  "type": "Feature",
  "properties": {
    "iso:country":"ES",
    "sg:address":"La Mina, S/n",
    "sg:city":"Rodalquilar",
    "sg:orig_category":"Bosques (trabajos, Asesor\u00cda, Gesti\u00d3n)",
    "sg:phone":"+34 950 38 97 47",
    "sg:postcode":"04115",
    "sg:province":"Almer\u00eda",
    "wof:name":"Empresa De Gestion Medio Ambiental S.a.",
    "wof:placetype":"venue"
},
  "geometry": {"coordinates":[-2.0415949821,36.8465309143],"type":"Point"}
}