{
  "type": "Feature",
  "properties": {
    "addr:full":"Carrer de Cirerer, 17 Sant Cristofol Les Fonts Girona 17800",
    "addr:housenumber":"17",
    "addr:postcode":"17800",
    "addr:street":"Carrer De Cirerer;Cristofol",
    "iso:country":"ES",
    "sg:address":"Carrer de Cirerer, 17",
    "sg:city":"Sant Cristofol Les Fonts",
    "sg:orig_category":"Bordado, Marcado A Medida",
    "sg:phone":"+34 972 26 75 02",
    "sg:postcode":"17800",
    "sg:province":"Girona",
    "wof:name":"Riera Clos Elena",
    "wof:placetype":"venue"
},
  "geometry": {"coordinates":[2.4893848896,42.1809463501],"type":"Point"}
}