{
  "type": "Feature",
  "properties": {
    "iso:country":"ES",
    "sg:address":"Elorrea Kalea, 2",
    "sg:city":"Derio",
    "sg:orig_category":"Florister\u00cdas",
    "sg:phone":"+34 944 54 12 23",
    "sg:postcode":"48160",
    "sg:province":"Vizcaya",
    "wof:name":"Amaia Rementeria Orue (liliak Loradenda)",
    "wof:placetype":"venue"
},
  "geometry": {"coordinates":[-2.884469986,43.2979164124],"type":"Point"}
}