{
  "type": "Feature",
  "properties": {
    "iso:country":"ES",
    "sg:address":"Calle de Argila, 35",
    "sg:city":"Pobla Vallbona",
    "sg:orig_category":"Producci\u00d3n De Abonos Y De Fertilizantes",
    "sg:phone":"+34 962 76 04 78",
    "sg:postcode":"46185",
    "sg:province":"Valencia",
    "wof:name":"Desco Aguilar Vicente",
    "wof:placetype":"venue"
},
  "geometry": {"coordinates":[-0.5498170257,39.5929489136],"type":"Point"}
}