{
  "type": "Feature",
  "properties": {
    "iso:country":"ES",
    "sg:address":"Avda Constitucion (la), 18",
    "sg:city":"Barruelo Santullan",
    "sg:orig_category":"Estancos",
    "sg:phone":"+34 979 60 72 11",
    "sg:postcode":"34820",
    "sg:province":"Palencia",
    "wof:name":"Alvarez Mediavilla Carmen",
    "wof:placetype":"venue"
},
  "geometry": {"coordinates":[-4.2885518074,42.9088554382],"type":"Point"}
}