{
  "type": "Feature",
  "properties": {
    "addr:full":"Carrer de Arbo\u00c7ar De Baix, 37 Arbo\u00c7ar Barcelona 08798",
    "addr:housenumber":"37",
    "addr:postcode":"08798",
    "addr:street":"Carrer De Arboc\u0327Ar De Baix;Barcelona",
    "iso:country":"ES",
    "sg:address":"Carrer de Arbo\u00c7ar De Baix, 37",
    "sg:city":"Arbo\u00c7ar",
    "sg:orig_category":"Agricultura: Abastecimiento Y Cosechado (negocio)",
    "sg:phone":"+34 938 97 03 79",
    "sg:postcode":"08798",
    "sg:province":"Barcelona",
    "wof:name":"Raims S.c.p.",
    "wof:placetype":"venue"
},
  "geometry": {"coordinates":[1.7527600527,41.3687591553],"type":"Point"}
}