{
  "type": "Feature",
  "properties": {
    "addr:full":"Calle de Martinez De Vega, 32 Mieres Asturias 33600",
    "addr:housenumber":"32",
    "addr:postcode":"33600",
    "addr:street":"Calle De Martinez De Vega",
    "iso:country":"ES",
    "sg:address":"Calle de Martinez De Vega, 32",
    "sg:city":"Mieres",
    "sg:orig_category":"Peluqueros: De Se\u00d1oras",
    "sg:phone":"+34 985 46 43 28",
    "sg:postcode":"33600",
    "sg:province":"Asturias",
    "wof:name":"Llano Martinez Ramon",
    "wof:placetype":"venue"
},
  "geometry": {"coordinates":[-5.7752251625,43.2482757568],"type":"Point"}
}