{
  "type": "Feature",
  "properties": {
    "addr:full":"Calle de Antonio Castillo, 20 Alcazar S. Juan Ciudad Real 13600",
    "addr:housenumber":"20",
    "addr:postcode":"13600",
    "addr:street":"Calle De Antonio Castillo;Alcazar S. Juan Ciudad Real",
    "iso:country":"ES",
    "sg:address":"Calle de Antonio Castillo, 20",
    "sg:city":"Alcazar S. Juan",
    "sg:orig_category":"Productores Recolectores, Venta Directa De Vinos",
    "sg:phone":"+34 926 54 11 71",
    "sg:postcode":"13600",
    "sg:province":"Ciudad Real",
    "wof:name":"Guillermo Mendieta Juan Antonio",
    "wof:placetype":"venue"
},
  "geometry": {"coordinates":[-3.2140893936,39.3925743103],"type":"Point"}
}