{
  "type": "Feature",
  "properties": {
    "addr:full":"Avda Oporto, 21 Madrid Madrid 28019",
    "addr:housenumber":"21",
    "addr:postcode":"madrid;28019",
    "addr:street":"Avda Oporto",
    "iso:country":"ES",
    "sg:address":"Avda Oporto, 21",
    "sg:city":"Madrid",
    "sg:orig_category":"Empresas De Limpieza",
    "sg:phone":"+34 915 69 95 14",
    "sg:postcode":"28019",
    "sg:province":"Madrid",
    "wof:name":"Limpiezas Madro\u00d1al S.l.",
    "wof:placetype":"venue"
},
  "geometry": {"coordinates":[-3.7229549885,40.3851852417],"type":"Point"}
}