{
  "type": "Feature",
  "properties": {
    "addr:full":"Avda Juan De Bethencourt, 39 Pto. Rosario Las Palmas 35600",
    "addr:housenumber":"39",
    "addr:postcode":"35600",
    "addr:street":"Avda Juan De Bethencourt;Pto. Rosario Las",
    "iso:country":"ES",
    "sg:address":"Avda Juan De Bethencourt, 39",
    "sg:city":"Pto. Rosario",
    "sg:orig_category":"Supermercados Y Hipermercados",
    "sg:phone":"+34 928 85 97 75",
    "sg:postcode":"35600",
    "sg:province":"Las Palmas",
    "wof:name":"Supermercados Inpescasa S.l",
    "wof:placetype":"venue"
},
  "geometry": {"coordinates":[-13.8645877838,28.5022659302],"type":"Point"}
}