{
  "type": "Feature",
  "properties": {
    "iso:country":"ES",
    "sg:address":"Calle de Mosen Domingo Agudo, 15",
    "sg:city":"Zaragoza",
    "sg:orig_category":"Perfumer\u00cda (al Por Menor)",
    "sg:phone":"+34 976 52 12 19",
    "sg:postcode":"50015",
    "sg:province":"Zaragoza",
    "wof:name":"Salvador Pinilla Angelita",
    "wof:placetype":"venue"
},
  "geometry": {"coordinates":[-0.8778499961,41.6604576111],"type":"Point"}
}