{
  "type": "Feature",
  "properties": {
    "iso:country":"ES",
    "sg:address":"Avda Club Deportivo, 39",
    "sg:city":"Logro\u00f1o",
    "sg:orig_category":"Molduras, Junquillos, Listones Y Molduras Perforadas",
    "sg:phone":"+34 941 51 12 65",
    "sg:postcode":"26007",
    "sg:province":"La Rioja",
    "wof:name":"Alonso Martinez Francisco",
    "wof:placetype":"venue"
},
  "geometry": {"coordinates":[-2.4607772827,42.4579391479],"type":"Point"}
}