{
  "type": "Feature",
  "properties": {
    "addr:full":"Calle de Hernan Cortes, 119 Villanueva Serena Badajoz 06700",
    "addr:housenumber":"119",
    "addr:postcode":"06700",
    "addr:street":"Calle De Hernan Cortes",
    "iso:country":"ES",
    "sg:address":"Calle de Hernan Cortes, 119",
    "sg:city":"Villanueva Serena",
    "sg:orig_category":"Ense\u00d1anza Variada",
    "sg:phone":"+34 924 84 32 79",
    "sg:postcode":"06700",
    "sg:province":"Badajoz",
    "wof:name":"Garcia Daza Fernando",
    "wof:placetype":"venue"
},
  "geometry": {"coordinates":[-5.7930588722,38.974609375],"type":"Point"}
}