{
  "type": "Feature",
  "properties": {
    "iso:country":"ES",
    "sg:address":"Av Catalunya, 11",
    "sg:city":"Limits",
    "sg:orig_category":"Bisuter\u00cda, Joyer\u00cda, Relojer\u00cda (al Por Menor)",
    "sg:phone":"+34 972 55 48 12",
    "sg:postcode":"17709",
    "sg:province":"Girona",
    "wof:name":"Casa Pous S. A.",
    "wof:placetype":"venue"
},
  "geometry": {"coordinates":[2.8407700062,42.4389533997],"type":"Point"}
}