{
  "type": "Feature",
  "properties": {
    "iso:country":"ES",
    "sg:address":"Calle de Dise\u00d1o, 5",
    "sg:city":"Mairena Aljarafe",
    "sg:orig_category":"C\u00c1maras De Comercio E Industria, Oficios, Agricultura",
    "sg:phone":"+34 954 18 65 02",
    "sg:postcode":"41927",
    "sg:province":"Sevilla",
    "wof:name":"Antonio Bollo S.l.",
    "wof:placetype":"venue"
},
  "geometry": {"coordinates":[-6.0605425835,37.3522262573],"type":"Point"}
}