{
  "type": "Feature",
  "properties": {
    "iso:country":"ES",
    "sg:address":"Calle de Huertas, 15",
    "sg:city":"Merida",
    "sg:classifiers":[
        {
            "category":"Personal",
            "subcategory":"Massage",
            "type":"Services"
        }
    ],
    "sg:phone":"+34 924 37 09 49",
    "sg:postcode":"06800",
    "sg:province":"Badajoz",
    "sg:tags":[
        "corporal",
        "material",
        "de",
        "cuidado",
        "y",
        "est\u00c9tica"
    ],
    "wof:name":"Metodos Tricocapilar C.b.",
    "wof:placetype":"venue"
},
  "geometry": {"coordinates":[-6.3540830612,38.911026001],"type":"Point"}
}