{
  "type": "Feature",
  "properties": {
    "iso:country":"ES",
    "sg:address":"Avda Ferrol (del), 5",
    "sg:city":"Viveiro",
    "sg:orig_category":"Ingenier\u00cda, Centros De Estudios (diversos)",
    "sg:phone":"+34 982 57 03 25",
    "sg:postcode":"27850",
    "sg:province":"Lugo",
    "wof:name":"Armados Y Construcciones 2001 S.l.",
    "wof:placetype":"venue"
},
  "geometry": {"coordinates":[-7.614815712,43.674823761],"type":"Point"}
}