{
  "type": "Feature",
  "properties": {
    "addr:full":"Calle de Doctor Perez Feliu, 12 Valencia Valencia 46014",
    "addr:housenumber":"12",
    "addr:postcode":"46014",
    "addr:street":"Calle De Doctor Perez Feliu",
    "iso:country":"ES",
    "sg:address":"Calle de Doctor Perez Feliu, 12",
    "sg:city":"Valencia",
    "sg:orig_category":"Empresas De Carpinter\u00cda De Madera",
    "sg:phone":"+34 963 57 40 59",
    "sg:postcode":"46014",
    "sg:province":"Valencia",
    "wof:name":"Zamora Galletero Jesus",
    "wof:placetype":"venue"
},
  "geometry": {"coordinates":[-0.4014975131,39.4605522156],"type":"Point"}
}