{
  "type": "Feature",
  "properties": {
    "iso:country":"ES",
    "sg:address":"Avda Talavera De Peru, 3",
    "sg:city":"Talavera Reina",
    "sg:orig_category":"Promotores Constructores",
    "sg:phone":"+34 925 81 50 64",
    "sg:postcode":"45600",
    "sg:province":"Toledo",
    "wof:name":"Comunidad Propietarios Talavera Del Peru N\u00ba 3",
    "wof:placetype":"venue"
},
  "geometry": {"coordinates":[-4.8427438736,39.9538269043],"type":"Point"}
}