{
  "type": "Feature",
  "properties": {
    "iso:country":"ES",
    "sg:address":"Calle de Prietos (los), 43",
    "sg:city":"Rambla",
    "sg:orig_category":"Cer\u00c1mica Art\u00cdstica Y Decorativa",
    "sg:phone":"+34 957 68 44 67",
    "sg:postcode":"14540",
    "sg:province":"C\u00f3rdoba",
    "sg:website":"www.almacenesserrano.com",
    "wof:name":"Ceramicas Serrano S.l.",
    "wof:placetype":"venue"
},
  "geometry": {"coordinates":[-4.7416338921,37.6080932617],"type":"Point"}
}