{
  "type": "Feature",
  "properties": {
    "addr:full":"Avda Llano Castellano, 3 Madrid Madrid 28034",
    "addr:housenumber":"3",
    "addr:postcode":"28034",
    "addr:street":"Avda Llano Castellano",
    "iso:country":"ES",
    "sg:address":"Avda Llano Castellano, 3",
    "sg:city":"Madrid",
    "sg:orig_category":"Arquitectos",
    "sg:phone":"+34 913 58 29 78",
    "sg:postcode":"28034",
    "sg:province":"Madrid",
    "wof:name":"Roldan Gomez Santiago",
    "wof:placetype":"venue"
},
  "geometry": {"coordinates":[-3.684484005,40.4836349487],"type":"Point"}
}