{
  "type": "Feature",
  "properties": {
    "iso:country":"ES",
    "sg:address":"Calle de Batalla Del Salado, 43",
    "sg:city":"Madrid",
    "sg:orig_category":"Peluqueros: De Se\u00d1oras",
    "sg:phone":"+34 915 39 44 18",
    "sg:postcode":"28045",
    "sg:province":"Madrid",
    "wof:name":"Marfil Peluqueros S.l.",
    "wof:placetype":"venue"
},
  "geometry": {"coordinates":[-3.6963999271,40.3984375],"type":"Point"}
}