{
  "type": "Feature",
  "properties": {
    "addr:full":"Carrer de Comer\u00c7, 12 Barcelona Barcelona 08003",
    "addr:housenumber":"12",
    "addr:postcode":"08003",
    "addr:street":"Carrer De Comerc\u0327",
    "iso:country":"ES",
    "sg:address":"Carrer de Comer\u00c7, 12",
    "sg:city":"Barcelona",
    "sg:orig_category":"Molduras, Junquillos, Listones Y Molduras Perforadas",
    "sg:phone":"+34 933 10 74 68",
    "sg:postcode":"08003",
    "sg:province":"Barcelona",
    "wof:name":"Trenchs Palau Jose",
    "wof:placetype":"venue"
},
  "geometry": {"coordinates":[2.1813390255,41.3888893127],"type":"Point"}
}