{
  "type": "Feature",
  "properties": {
    "addr:full":"Plaz Espa\u00d1a, 1 Albanchez Almer\u00eda 04857",
    "addr:housenumber":"1",
    "addr:postcode":"04857",
    "addr:street":"Plaz Espan\u0303A;Almeri\u0301A",
    "iso:country":"ES",
    "sg:address":"Plaz Espa\u00d1a, 1",
    "sg:city":"Albanchez",
    "sg:orig_category":"Administraciones Regionales, Departamentales Y Locales",
    "sg:phone":"+34 950 12 40 05",
    "sg:postcode":"04857",
    "sg:province":"Almer\u00eda",
    "wof:name":"Ayuntamiento De Albanchez",
    "wof:placetype":"venue"
},
  "geometry": {"coordinates":[-2.1816370487,37.287322998],"type":"Point"}
}