{
  "type": "Feature",
  "properties": {
    "iso:country":"ES",
    "sg:address":"Carrer de Tortosa, 33",
    "sg:city":"Vic",
    "sg:orig_category":"Cerrajer\u00cda, Ferrallista",
    "sg:phone":"+34 938 86 08 31",
    "sg:postcode":"08500",
    "sg:province":"Barcelona",
    "wof:name":"Vila Tio Luis",
    "wof:placetype":"venue"
},
  "geometry": {"coordinates":[2.2683300972,41.9498901367],"type":"Point"}
}