{
  "type": "Feature",
  "properties": {
    "iso:country":"ES",
    "sg:address":"Ctra Humera (de), 55",
    "sg:city":"Pozuelo De Alarcon",
    "sg:orig_category":"Inversiones",
    "sg:phone":"+34 913 51 98 61",
    "sg:postcode":"28224",
    "sg:province":"Madrid",
    "wof:name":"Arte Y Naturaleza Gespart S.l.",
    "wof:placetype":"venue"
},
  "geometry": {"coordinates":[-3.8026275635,40.44090271],"type":"Point"}
}