{
  "type": "Feature",
  "properties": {
    "iso:country":"ES",
    "sg:address":"Zas, S/n",
    "sg:city":"Zas",
    "sg:orig_category":"Congelados: Productos Alimentarios (fabricaci\u00d3n, Al Por Mayor)",
    "sg:phone":"+34 981 88 60 03",
    "sg:postcode":"15830",
    "sg:province":"La Coru\u00f1a",
    "wof:name":"Ramas Ramas Andres",
    "wof:placetype":"venue"
},
  "geometry": {"coordinates":[-8.7368841171,42.9089660645],"type":"Point"}
}