{
  "type": "Feature",
  "properties": {
    "iso:country":"ES",
    "sg:address":"Calle de Burgos, 6",
    "sg:city":"Vitoria-gasteiz",
    "sg:orig_category":"Quincaller\u00cda (al Por Menor)",
    "sg:phone":"+34 945 25 56 35",
    "sg:postcode":"01002",
    "sg:province":"\u00c1lava",
    "wof:name":"Jose Ignacio Martinez De Aguillo Lopez",
    "wof:placetype":"venue"
},
  "geometry": {"coordinates":[-2.6605141163,42.855178833],"type":"Point"}
}