{
  "type": "Feature",
  "properties": {
    "iso:country":"ES",
    "sg:address":"Calle de Chiquinquira, 6",
    "sg:city":"Madrid",
    "sg:orig_category":"Radiocomunicaciones, Telefon\u00cda M\u00d3vil, Radiomensajer\u00cda: Servicios, Comercializaci\u00d3n",
    "sg:phone":"+34 913 81 18 84",
    "sg:postcode":"28033",
    "sg:province":"Madrid",
    "sg:website":"www.unidoslatinos.com",
    "wof:name":"Ramirez Camacho Maria Cristina S.l.",
    "wof:placetype":"venue"
},
  "geometry": {"coordinates":[-3.6385846138,40.4718856812],"type":"Point"}
}