{
  "type": "Feature",
  "properties": {
    "addr:full":"Rbla Catalunya, 86 Barcelona Barcelona 08008",
    "addr:housenumber":"86",
    "addr:postcode":"08008",
    "addr:street":"Rbla Catalunya",
    "iso:country":"ES",
    "sg:address":"Rbla Catalunya, 86",
    "sg:city":"Barcelona",
    "sg:orig_category":"Cajas De Ahorro",
    "sg:phone":"+34 932 15 87 27",
    "sg:postcode":"08008",
    "sg:province":"Barcelona",
    "sg:website":"www.caixacatalunya.es",
    "wof:name":"Caixa D'estalvis De Catalunya",
    "wof:placetype":"venue"
},
  "geometry": {"coordinates":[2.1615068913,41.3927955627],"type":"Point"}
}