{
  "type": "Feature",
  "properties": {
    "addr:full":"Calle de Melchor Cano, 12 Fuente El Fresno Ciudad Real 13680",
    "addr:housenumber":"12",
    "addr:postcode":"13680",
    "addr:street":"Calle De Melchor Cano",
    "iso:country":"ES",
    "sg:address":"Calle de Melchor Cano, 12",
    "sg:city":"Fuente El Fresno",
    "sg:orig_category":"Papeler\u00cdas, Librer\u00cdas",
    "sg:phone":"+34 926 80 44 26",
    "sg:postcode":"13680",
    "sg:province":"Ciudad Real",
    "wof:name":"Peinado Navarro Pedro",
    "wof:placetype":"venue"
},
  "geometry": {"coordinates":[-3.7759270668,39.2279129028],"type":"Point"}
}