{
  "type": "Feature",
  "properties": {
    "addr:full":"Carr Muralla, 7 Blanes Girona 17300",
    "addr:housenumber":"7",
    "addr:postcode":"17300",
    "addr:street":"Carr Muralla",
    "iso:country":"ES",
    "sg:address":"Carr Muralla, 7",
    "sg:city":"Blanes",
    "sg:orig_category":"Cajas De Ahorro",
    "sg:phone":"+34 972 33 10 12",
    "sg:postcode":"17300",
    "sg:province":"Girona",
    "sg:website":"www.caixagirona.es",
    "wof:name":"Caixa De Girona",
    "wof:placetype":"venue"
},
  "geometry": {"coordinates":[2.7906730175,41.6732711792],"type":"Point"}
}