{
  "type": "Feature",
  "properties": {
    "addr:full":"Ctra Tries, Les, S/n Olot Girona 17800",
    "addr:housenumber":"s",
    "addr:postcode":"17800",
    "addr:street":"Ctra Tries Les;/ N",
    "iso:country":"ES",
    "sg:address":"Ctra Tries, Les, S/n",
    "sg:city":"Olot",
    "sg:orig_category":"Discotecas Y Salas De Baile",
    "sg:phone":"+34 972 26 75 20",
    "sg:postcode":"17800",
    "sg:province":"Girona",
    "wof:name":"Kratters S.a.",
    "wof:placetype":"venue"
},
  "geometry": {"coordinates":[2.5003499985,42.1891212463],"type":"Point"}
}