{
  "type": "Feature",
  "properties": {
    "iso:country":"ES",
    "sg:address":"Carrer de Mont Llorer, 11",
    "sg:city":"S. Celoni",
    "sg:orig_category":"Trabajos De Soldaduras",
    "sg:phone":"+34 938 67 49 07",
    "sg:postcode":"08470",
    "sg:province":"Barcelona",
    "wof:name":"Asfo 2004, S.l.",
    "wof:placetype":"venue"
},
  "geometry": {"coordinates":[2.4972939491,41.6883125305],"type":"Point"}
}