{
  "type": "Feature",
  "properties": {
    "iso:country":"ES",
    "sg:address":"Carr Major, 78",
    "sg:city":"Lleida",
    "sg:orig_category":"Fotograf\u00cda Y Cine: Aparatos, Pel\u00cdculas Y Accesorios (fabricaci\u00d3n, Al Por Mayor)",
    "sg:phone":"+34 973 26 88 29",
    "sg:postcode":"25007",
    "sg:province":"Lleida",
    "wof:name":"Foto Llorens S.l.",
    "wof:placetype":"venue"
},
  "geometry": {"coordinates":[0.627129972,41.6145210266],"type":"Point"}
}