{
  "type": "Feature",
  "properties": {
    "iso:country":"ES",
    "sg:address":"Calle de Matias Barrio Y Mier, 3",
    "sg:city":"Aguilar Campoo",
    "sg:orig_category":"Cooperativas Agr\u00cdcolas",
    "sg:phone":"+34 979 12 22 16",
    "sg:postcode":"34800",
    "sg:province":"Palencia",
    "wof:name":"Cooperativa De Consumo San Jose Obrero",
    "wof:placetype":"venue"
},
  "geometry": {"coordinates":[-4.2574658394,42.7935333252],"type":"Point"}
}