{
  "type": "Feature",
  "properties": {
    "addr:full":"Avda Sudamerica (de), 15 Jerez De La Frontera C\u00e1diz 11407",
    "addr:postcode":"11407",
    "addr:street":"Avda Sudamerica De",
    "iso:country":"ES",
    "sg:address":"Avda Sudamerica (de), 15",
    "sg:city":"Jerez De La Frontera",
    "sg:orig_category":"Impuestos, Tesoro P\u00dablico",
    "sg:phone":"+34 956 30 00 48",
    "sg:postcode":"11407",
    "sg:province":"C\u00e1diz",
    "wof:name":"Peritaciones Plievas Sociedad Limitada",
    "wof:placetype":"venue"
},
  "geometry": {"coordinates":[-6.1239709854,36.7034378052],"type":"Point"}
}