{
  "type": "Feature",
  "properties": {
    "iso:country":"ES",
    "sg:address":"Poli Almu\u00d1a-barcia, S/n",
    "sg:city":"Barcia",
    "sg:orig_category":"Empresas De Carpinter\u00cda",
    "sg:phone":"+34 985 64 16 18",
    "sg:postcode":"33787",
    "sg:province":"Asturias",
    "wof:name":"Aluminio De Valdes C.b.",
    "wof:placetype":"venue"
},
  "geometry": {"coordinates":[-6.5075626373,43.5404586792],"type":"Point"}
}