{
  "type": "Feature",
  "properties": {
    "iso:country":"ES",
    "sg:address":"Ctra Villacastin, S/n",
    "sg:city":"Segovia",
    "sg:orig_category":"Charcuter\u00cdas (al Por Mayor)",
    "sg:phone":"+34 921 42 14 62",
    "sg:postcode":"40006",
    "sg:province":"Segovia",
    "wof:name":"Gomez De Andres Gregorio",
    "wof:placetype":"venue"
},
  "geometry": {"coordinates":[-4.1246328354,40.9144744873],"type":"Point"}
}