{
  "type": "Feature",
  "properties": {
    "iso:country":"ES",
    "sg:address":"Carr Ctra Nacional Ii, Km. 0511,0",
    "sg:city":"Cervera",
    "sg:orig_category":"Mec\u00c1nico Del Autom\u00d3vil",
    "sg:phone":"+34 973 53 07 56",
    "sg:postcode":"25200",
    "sg:province":"Lleida",
    "wof:name":"Mecanica Mateu S.l.",
    "wof:placetype":"venue"
},
  "geometry": {"coordinates":[1.2714600563,41.6712989807],"type":"Point"}
}