{
  "type": "Feature",
  "properties": {
    "addr:full":"Carr Molins, Dels, 25 Cala Millor Islas Baleares 07560",
    "addr:housenumber":"25",
    "addr:postcode":"07560",
    "addr:street":"Carr Molins Dels",
    "iso:country":"ES",
    "sg:address":"Carr Molins, Dels, 25",
    "sg:city":"Cala Millor",
    "sg:classifiers":[
        {
            "category":"Autos & Motor Vehicles",
            "subcategory":"Automobile Sales",
            "type":"Retail Goods"
        }
    ],
    "sg:phone":"+34 971 58 55 26",
    "sg:postcode":"07560",
    "sg:province":"Islas Baleares",
    "sg:website":"www.todotest.com",
    "wof:name":"Autoescola Canovas S.l.",
    "wof:placetype":"venue"
},
  "geometry": {"coordinates":[3.3733510971,39.5831985474],"type":"Point"}
}