{
  "type": "Feature",
  "properties": {
    "iso:country":"ES",
    "sg:address":"Calle de Doctor Cornago, 31",
    "sg:city":"Pozuelo De Alarcon",
    "sg:orig_category":"Veh\u00cdculos De Ocasi\u00d3n",
    "sg:phone":"+34 913 52 08 14",
    "sg:postcode":"28223",
    "sg:province":"Madrid",
    "wof:name":"Automoviles La Salud S.a.",
    "wof:placetype":"venue"
},
  "geometry": {"coordinates":[-3.8142819405,40.4388465881],"type":"Point"}
}