{
  "type": "Feature",
  "properties": {
    "addr:full":"Calle de Iglesia, 13 Rus Ja\u00e9n 23430",
    "addr:housenumber":"13",
    "addr:postcode":"23430",
    "addr:street":"Calle De Iglesia;Jae\u0301N",
    "iso:country":"ES",
    "sg:address":"Calle de Iglesia, 13",
    "sg:city":"Rus",
    "sg:orig_category":"Bancos",
    "sg:phone":"+34 953 77 00 00",
    "sg:postcode":"23430",
    "sg:province":"Ja\u00e9n",
    "wof:name":"Banco Espa\u00f1ol De Credito S.a.",
    "wof:placetype":"venue"
},
  "geometry": {"coordinates":[-3.4615740776,38.0471992493],"type":"Point"}
}