{
  "type": "Feature",
  "properties": {
    "addr:full":"Pl Carles Iii (de), 41 S. Carles Rapita Tarragona 43540",
    "addr:housenumber":"41",
    "addr:postcode":"43540",
    "addr:street":"Pl Carles Iii De;S. Carles Rapita",
    "iso:country":"ES",
    "sg:address":"Pl Carles Iii (de), 41",
    "sg:city":"S. Carles Rapita",
    "sg:orig_category":"Asesor\u00cda Sobre Comunicaci\u00d3n De Empresas",
    "sg:phone":"+34 977 74 33 26",
    "sg:postcode":"43540",
    "sg:province":"Tarragona",
    "sg:website":"lakua.com/html/obranueva.php",
    "wof:name":"Lakua Asesores S.l.",
    "wof:placetype":"venue"
},
  "geometry": {"coordinates":[0.5927289724,40.6197471619],"type":"Point"}
}