{
  "type": "Feature",
  "properties": {
    "addr:full":"Plaz Bib-rambla (de), 25 Granada Granada 18001",
    "addr:postcode":"18001",
    "addr:street":"Plaz",
    "iso:country":"ES",
    "sg:address":"Plaz Bib-rambla (de), 25",
    "sg:city":"Granada",
    "sg:orig_category":"Ropa Para Se\u00d1oras (al Por Menor)",
    "sg:phone":"+34 958 22 62 31",
    "sg:postcode":"18001",
    "sg:province":"Granada",
    "wof:name":"Eduardo Y Maximino Vazquez S. R. C.",
    "wof:placetype":"venue"
},
  "geometry": {"coordinates":[-3.5996339321,37.174697876],"type":"Point"}
}