{
  "type": "Feature",
  "properties": {
    "iso:country":"ES",
    "sg:address":"Calle de Molina De Segura, 3",
    "sg:city":"Paz",
    "sg:orig_category":"Abogados",
    "sg:phone":"+34 968 20 19 89",
    "sg:postcode":"30007",
    "sg:province":"Murcia",
    "wof:name":"Sanchez Martinez Juan Antonio",
    "wof:placetype":"venue"
},
  "geometry": {"coordinates":[-1.1142389774,37.9970092773],"type":"Point"}
}