{
  "type": "Feature",
  "properties": {
    "iso:country":"ES",
    "sg:address":"C/ Bisbe Torres, De, 2",
    "sg:city":"S. Antoni Portmany",
    "sg:classifiers":[
        {
            "category":"Cinema",
            "subcategory":"Movie Theater",
            "type":"Entertainment"
        }
    ],
    "sg:phone":"+34 971 34 64 00",
    "sg:postcode":"07820",
    "sg:province":"Islas Baleares",
    "sg:tags":[
        "salas",
        "de",
        "cine"
    ],
    "wof:name":"Empresa Torres Comunidad De Bienes",
    "wof:placetype":"venue"
},
  "geometry": {"coordinates":[1.5188339949,39.1094055176],"type":"Point"}
}