{
  "type": "Feature",
  "properties": {
    "addr:full":"Ctra Sagunto-burgos, Km. 0060,3 Barracas Castell\u00f3n 12420",
    "addr:postcode":"12420",
    "addr:street":"Ctra Sagunto-Burgos Km. 0060,3;Castello\u0301N",
    "iso:country":"ES",
    "sg:address":"Ctra Sagunto-burgos, Km. 0060,3",
    "sg:city":"Barracas",
    "sg:orig_category":"Distribuci\u00d3n De Petr\u00d3leo Y Derivados",
    "sg:phone":"+34 964 12 10 64",
    "sg:postcode":"12420",
    "sg:province":"Castell\u00f3n",
    "wof:name":"Cedipsa Compa\u00d1ia Espa\u00d1ola Distribuidora De Petroleos S.a.",
    "wof:placetype":"venue"
},
  "geometry": {"coordinates":[-0.6965289712,40.0147514343],"type":"Point"}
}