{
  "type": "Feature",
  "properties": {
    "iso:country":"ES",
    "sg:address":"Calle de Medina, S/n",
    "sg:city":"Poligono Industrial Los Villares",
    "sg:orig_category":"Muebles, Minoristas",
    "sg:phone":"+34 923 23 02 22",
    "sg:postcode":"37184",
    "sg:province":"Salamanca",
    "wof:name":"Exclusivas Dominguez S.l",
    "wof:placetype":"venue"
},
  "geometry": {"coordinates":[-5.6383290291,40.9917297363],"type":"Point"}
}