{
  "type": "Feature",
  "properties": {
    "iso:country":"ES",
    "sg:address":"Avgd Fora-fora, S/n",
    "sg:city":"Albaida",
    "sg:orig_category":"Fabricaci\u00d3n De Su\u00c9ters Y Chalecos De Punto",
    "sg:phone":"+34 962 90 09 87",
    "sg:postcode":"46860",
    "sg:province":"Valencia",
    "wof:name":"Tormo Soler Alfonso",
    "wof:placetype":"venue"
},
  "geometry": {"coordinates":[-0.5203629732,38.8445243835],"type":"Point"}
}