{
  "type": "Feature",
  "properties": {
    "addr:full":"Carrer de Sindicat, 70 Palma Islas Baleares 07002",
    "addr:housenumber":"70",
    "addr:postcode":"07002",
    "addr:street":"Carrer De Sindicat",
    "iso:country":"ES",
    "sg:address":"Carrer de Sindicat, 70",
    "sg:city":"Palma",
    "sg:orig_category":"Carnicer\u00cdas, Carnicer\u00cdas",
    "sg:phone":"+34 971 72 14 11",
    "sg:postcode":"07002",
    "sg:province":"Islas Baleares",
    "wof:name":"Sistelcom-telemensaje S.a.",
    "wof:placetype":"venue"
},
  "geometry": {"coordinates":[2.656443119,39.5723953247],"type":"Point"}
}