{
  "type": "Feature",
  "properties": {
    "iso:country":"ES",
    "sg:address":"Calle de Pedro Laborde, 3",
    "sg:city":"Madrid",
    "sg:orig_category":"Zapatos (al Por Menor)",
    "sg:phone":"+34 913 03 48 44",
    "sg:postcode":"28038",
    "sg:province":"Madrid",
    "wof:name":"Calzados Moya Hermanos C.b.",
    "wof:placetype":"venue"
},
  "geometry": {"coordinates":[-3.646887064,40.3897972107],"type":"Point"}
}