{
  "type": "Feature",
  "properties": {
    "iso:country":"ES",
    "sg:address":"Avda Cesareo Alierta, 18",
    "sg:city":"Zaragoza",
    "sg:orig_category":"Loter\u00cda Y T\u00d3mbola",
    "sg:phone":"+34 976 21 01 64",
    "sg:postcode":"50008",
    "sg:province":"Zaragoza",
    "wof:name":"Alcolea Pinilla Maria Luisa",
    "wof:placetype":"venue"
},
  "geometry": {"coordinates":[-0.8785316944,41.6456756592],"type":"Point"}
}