{
  "type": "Feature",
  "properties": {
    "iso:country":"ES",
    "sg:address":"Carrer de Esport, 29",
    "sg:city":"S. Andreu Barca",
    "sg:orig_category":"Ropa Para Ni\u00d1os (al Por Menor)",
    "sg:phone":"+34 936 82 45 51",
    "sg:postcode":"08740",
    "sg:province":"Barcelona",
    "wof:name":"Mallen Segur S.l.",
    "wof:placetype":"venue"
},
  "geometry": {"coordinates":[1.9683769941,41.4477615356],"type":"Point"}
}