{
  "type": "Feature",
  "properties": {
    "addr:full":"Carrer de Consolat De Mar, 21 Barcelona Barcelona 08003",
    "addr:housenumber":"21",
    "addr:postcode":"08003",
    "addr:street":"Carrer De Consolat De Mar",
    "iso:country":"ES",
    "sg:address":"Carrer de Consolat De Mar, 21",
    "sg:city":"Barcelona",
    "sg:orig_category":"Relojer\u00cda (al Por Menor, Reparaci\u00d3n)",
    "sg:phone":"+34 933 10 27 95",
    "sg:postcode":"08003",
    "sg:province":"Barcelona",
    "wof:name":"Madue\u00f1o Jimenez Salvador",
    "wof:placetype":"venue"
},
  "geometry": {"coordinates":[2.1819300652,41.3822517395],"type":"Point"}
}