{
  "type": "Feature",
  "properties": {
    "iso:country":"ES",
    "sg:address":"Ctra Mas Del Jutge, 73",
    "sg:city":"P.i. Masia Del Juez",
    "sg:orig_category":"Cajas Y Embalajes De Cart\u00d3n Y Papel",
    "sg:phone":"+34 961 57 41 11",
    "sg:postcode":"46900",
    "sg:province":"Valencia",
    "wof:name":"Cartonajes Fas, S.l.",
    "wof:placetype":"venue"
},
  "geometry": {"coordinates":[-0.4623290002,39.441619873],"type":"Point"}
}