{
  "type": "Feature",
  "properties": {
    "addr:full":"Calle de Hiedra, 26 Botorrita Zaragoza 50441",
    "addr:housenumber":"26",
    "addr:postcode":"50441",
    "addr:street":"Calle De Hiedra",
    "iso:country":"ES",
    "sg:address":"Calle de Hiedra, 26",
    "sg:city":"Botorrita",
    "sg:orig_category":"Transportes Por Carretera: Lotes Completos, Mercanc\u00cdas Diversas",
    "sg:phone":"+34 976 14 21 58",
    "sg:postcode":"50441",
    "sg:province":"Zaragoza",
    "wof:name":"Marluca Distribuciones S.l.l.",
    "wof:placetype":"venue"
},
  "geometry": {"coordinates":[-1.0290390253,41.5060195923],"type":"Point"}
}