{
  "type": "Feature",
  "properties": {
    "addr:full":"Calle de Bernardo Mulleras, 3 Ciudad Real Ciudad Real 13001",
    "addr:housenumber":"3",
    "addr:postcode":"13001",
    "addr:street":"Calle De Bernardo Mulleras",
    "iso:country":"ES",
    "sg:address":"Calle de Bernardo Mulleras, 3",
    "sg:city":"Ciudad Real",
    "sg:orig_category":"Arquitectos",
    "sg:phone":"+34 926 27 32 44",
    "sg:postcode":"13001",
    "sg:province":"Ciudad Real",
    "wof:name":"Franco Leon Luis",
    "wof:placetype":"venue"
},
  "geometry": {"coordinates":[-3.9294872284,38.9843177795],"type":"Point"}
}