{
  "type": "Feature",
  "properties": {
    "addr:full":"Calle de Luis Claudio, 5 Madrid Madrid 28044",
    "addr:housenumber":"5",
    "addr:postcode":"28044",
    "addr:street":"Calle De Luis Claudio",
    "iso:country":"ES",
    "sg:address":"Calle de Luis Claudio, 5",
    "sg:city":"Madrid",
    "sg:orig_category":"Venta, Instalaci\u00d3n De Calefacci\u00d3n",
    "sg:phone":"+34 914 64 37 79",
    "sg:postcode":"28044",
    "sg:province":"Madrid",
    "wof:name":"Aplicaciones Y Proyectos De Energia Solar S.l.a.",
    "wof:placetype":"venue"
},
  "geometry": {"coordinates":[-3.7602713108,40.3719215393],"type":"Point"}
}