{
  "type": "Feature",
  "properties": {
    "addr:full":"Calle de Raimundo Fernandez Villaverde, 44 Madrid Madrid 28003",
    "addr:housenumber":"44",
    "addr:postcode":"madrid;28003",
    "addr:street":"Calle De Raimundo Fernandez Villaverde",
    "iso:country":"ES",
    "sg:address":"Calle de Raimundo Fernandez Villaverde, 44",
    "sg:city":"Madrid",
    "sg:orig_category":"Molduras, Junquillos, Listones Y Molduras Perforadas",
    "sg:phone":"+34 915 53 89 75",
    "sg:postcode":"28003",
    "sg:province":"Madrid",
    "wof:name":"Garrido Ruano Lorenzo",
    "wof:placetype":"venue"
},
  "geometry": {"coordinates":[-3.69739604,40.446395874],"type":"Point"}
}