{
  "type": "Feature",
  "properties": {
    "iso:country":"ES",
    "sg:address":"Calle de Santa Emilia De Rodat, 1",
    "sg:city":"Cordoba",
    "sg:orig_category":"Molduras, Junquillos, Listones Y Molduras Perforadas",
    "sg:phone":"+34 957 43 94 88",
    "sg:postcode":"14014",
    "sg:province":"C\u00f3rdoba",
    "wof:name":"Perez Sanz Ricardo",
    "wof:placetype":"venue"
},
  "geometry": {"coordinates":[-4.7566289902,37.8869781494],"type":"Point"}
}