{
  "type": "Feature",
  "properties": {
    "iso:country":"ES",
    "sg:address":"Carr Pont, 16",
    "sg:city":"Bisbal D'emporda",
    "sg:orig_category":"Promotores Constructores",
    "sg:phone":"+34 972 64 03 82",
    "sg:postcode":"17100",
    "sg:province":"Girona",
    "wof:name":"Construccions Josep Alsina S.l.",
    "wof:placetype":"venue"
},
  "geometry": {"coordinates":[2.8112609386,41.9731292725],"type":"Point"}
}