{
  "type": "Feature",
  "properties": {
    "addr:full":"Higuera, 3 Lepe Huelva 21440",
    "addr:housenumber":"3",
    "addr:postcode":"21440",
    "addr:street":"Higuera",
    "iso:country":"ES",
    "sg:address":"Higuera, 3",
    "sg:city":"Lepe",
    "sg:orig_category":"Arboricultura Y Producci\u00d3n De Frutas",
    "sg:phone":"+34 959 38 36 18",
    "sg:postcode":"21440",
    "sg:province":"Huelva",
    "wof:name":"Frutas Cimac S.l.",
    "wof:placetype":"venue"
},
  "geometry": {"coordinates":[-7.2087187767,37.2582168579],"type":"Point"}
}