{
  "type": "Feature",
  "properties": {
    "addr:full":"Calle de Pintor Sorolla, 9 Ayamonte Huelva 21400",
    "addr:housenumber":"9",
    "addr:postcode":"21400",
    "addr:street":"Calle De Pintor Sorolla",
    "iso:country":"ES",
    "sg:address":"Calle de Pintor Sorolla, 9",
    "sg:city":"Ayamonte",
    "sg:orig_category":"T\u00c9cnicos Veterinarios",
    "sg:phone":"+34 959 32 19 86",
    "sg:postcode":"21400",
    "sg:province":"Huelva",
    "wof:name":"Carro Valdes-hevia Margarita",
    "wof:placetype":"venue"
},
  "geometry": {"coordinates":[-7.4000492096,37.2158966064],"type":"Point"}
}