{
  "type": "Feature",
  "properties": {
    "iso:country":"ES",
    "sg:address":"Calle de Escalante, 232",
    "sg:city":"Valencia",
    "sg:orig_category":"Electricidad: Instaladores",
    "sg:phone":"+34 963 71 03 58",
    "sg:postcode":"46011",
    "sg:province":"Valencia",
    "wof:name":"Montajes Electricos S.llorens S.l.",
    "wof:placetype":"venue"
},
  "geometry": {"coordinates":[-0.3302969933,39.4705085754],"type":"Point"}
}