{
  "type": "Feature",
  "properties": {
    "iso:country":"ES",
    "sg:address":"Ctra Llagostera, S/n",
    "sg:city":"Caldes Malavella",
    "sg:orig_category":"Promotores Constructores",
    "sg:phone":"+34 972 47 01 12",
    "sg:postcode":"17455",
    "sg:province":"Girona",
    "wof:name":"Construccions Boadas S.a.",
    "wof:placetype":"venue"
},
  "geometry": {"coordinates":[2.8119819164,41.8396339417],"type":"Point"}
}