{
  "type": "Feature",
  "properties": {
    "iso:country":"ES",
    "sg:address":"Calle de Juan Zofio, 47",
    "sg:city":"Madrid",
    "sg:orig_category":"Chapister\u00cda",
    "sg:phone":"+34 915 69 85 92",
    "sg:postcode":"28026",
    "sg:province":"Madrid",
    "wof:name":"Luberto Gonzalez Cesar Aristobulo",
    "wof:placetype":"venue"
},
  "geometry": {"coordinates":[-3.7119090557,40.3815383911],"type":"Point"}
}