{
  "type": "Feature",
  "properties": {
    "iso:country":"ES",
    "sg:address":"Carrer de Mossen Fontanilles, 6",
    "sg:city":"Sant Sadurni D'anoia",
    "sg:orig_category":"Peluquer\u00cdas, Peluquer\u00cda Mixta",
    "sg:phone":"+34 938 91 23 20",
    "sg:postcode":"08770",
    "sg:province":"Barcelona",
    "wof:name":"Innova S.c.p.",
    "wof:placetype":"venue"
},
  "geometry": {"coordinates":[1.6083999872,41.6151885986],"type":"Point"}
}