{
  "type": "Feature",
  "properties": {
    "addr:full":"Rua Rio Sar, 5 Carballo La Coru\u00f1a 15100",
    "addr:housenumber":"5",
    "addr:postcode":"15100",
    "addr:street":"Rua Rio Sar;La Corun\u0303A",
    "iso:country":"ES",
    "sg:address":"Rua Rio Sar, 5",
    "sg:city":"Carballo",
    "sg:orig_category":"Promotores Constructores",
    "sg:phone":"+34 981 70 04 79",
    "sg:postcode":"15100",
    "sg:province":"La Coru\u00f1a",
    "wof:name":"Construcciones Mmv Jose Cotelo S.l.",
    "wof:placetype":"venue"
},
  "geometry": {"coordinates":[-8.6952943802,43.2073860168],"type":"Point"}
}