{
  "type": "Feature",
  "properties": {
    "iso:country":"ES",
    "sg:address":"Ptda Algoros, 122",
    "sg:city":"Elche",
    "sg:orig_category":"Molduras, Junquillos, Listones Y Molduras Perforadas",
    "sg:phone":"+34 966 63 51 23",
    "sg:postcode":"03293",
    "sg:province":"Alicante",
    "wof:name":"Huang  Juanmei",
    "wof:placetype":"venue"
},
  "geometry": {"coordinates":[-0.6995239854,38.2634811401],"type":"Point"}
}