{
  "type": "Feature",
  "properties": {
    "addr:full":"Calle de General Mola, 51 Miguel Esteban Toledo 45830",
    "addr:housenumber":"51",
    "addr:postcode":"45830",
    "addr:street":"Calle De General Mola",
    "iso:country":"ES",
    "sg:address":"Calle de General Mola, 51",
    "sg:city":"Miguel Esteban",
    "sg:orig_category":"Promotores Constructores",
    "sg:phone":"+34 925 56 73 74",
    "sg:postcode":"45830",
    "sg:province":"Toledo",
    "wof:name":"Profesol S.l.",
    "wof:placetype":"venue"
},
  "geometry": {"coordinates":[-3.0768489838,39.5223922729],"type":"Point"}
}