{
  "type": "Feature",
  "properties": {
    "iso:country":"ES",
    "sg:address":"Aitze Auzoa, S/n",
    "sg:city":"Aitze",
    "sg:orig_category":"Producci\u00d3n De Sidra",
    "sg:phone":"+34 943 13 01 48",
    "sg:postcode":"20800",
    "sg:province":"Guip\u00f9zcoa",
    "wof:name":"Arregui Urrestilla Juan",
    "wof:placetype":"venue"
},
  "geometry": {"coordinates":[-2.1776471138,43.2848129272],"type":"Point"}
}