{
  "type": "Feature",
  "properties": {
    "iso:country":"ES",
    "sg:address":"Avda Santa Ana, 16",
    "sg:city":"Tudela",
    "sg:orig_category":"Ropa Para Se\u00d1oras Y Caballeros (al Por Menor)",
    "sg:phone":"+34 948 84 71 78",
    "sg:postcode":"31500",
    "sg:province":"Navarra",
    "wof:name":"Auconi S. A.",
    "wof:placetype":"venue"
},
  "geometry": {"coordinates":[-1.6023019552,42.0558586121],"type":"Point"}
}