{
  "type": "Feature",
  "properties": {
    "iso:country":"ES",
    "sg:address":"Calle de Manuel Casana, 9",
    "sg:city":"Sevilla",
    "sg:orig_category":"Abogados",
    "sg:phone":"+34 954 63 07 14",
    "sg:postcode":"41005",
    "sg:province":"Sevilla",
    "wof:name":"Moreno Martinez De Azcoytia Jose Antonio",
    "wof:placetype":"venue"
},
  "geometry": {"coordinates":[-5.971414566,37.3817405701],"type":"Point"}
}