{
  "type": "Feature",
  "properties": {
    "iso:country":"ES",
    "sg:address":"Ctra Bailen Motril, Km. 0159,4",
    "sg:city":"Durcal",
    "sg:orig_category":"Construcciones Met\u00c1licas",
    "sg:phone":"+34 958 78 09 03",
    "sg:postcode":"18650",
    "sg:province":"Granada",
    "wof:name":"Montajes Metalicos Durcal S.l.",
    "wof:placetype":"venue"
},
  "geometry": {"coordinates":[-3.5704190731,36.9924316406],"type":"Point"}
}