{
  "type": "Feature",
  "properties": {
    "addr:full":"Rua Aviacion Espa\u00d1ola, 37 Lugo Lugo 27002",
    "addr:housenumber":"37",
    "addr:postcode":"27002",
    "addr:street":"Rua Aviacion Espan\u0303Ola",
    "iso:country":"ES",
    "sg:address":"Rua Aviacion Espa\u00d1ola, 37",
    "sg:city":"Lugo",
    "sg:orig_category":"Internados & Ense\u00d1anza Privada",
    "sg:phone":"+34 982 22 16 30",
    "sg:postcode":"27002",
    "sg:province":"Lugo",
    "sg:website":"www.fingoi.com",
    "wof:name":"Colegio Fingoy S.a.",
    "wof:placetype":"venue"
},
  "geometry": {"coordinates":[-7.554418087,42.9979705811],"type":"Point"}
}