{
  "type": "Feature",
  "properties": {
    "iso:country":"ES",
    "sg:address":"Calle de Jupiter, 3",
    "sg:city":"Benidorm",
    "sg:orig_category":"Asesor\u00cda De Formaci\u00d3n Y Gesti\u00d3n De Personal",
    "sg:phone":"+34 966 83 08 42",
    "sg:postcode":"03500",
    "sg:province":"Alicante",
    "wof:name":"Tramiter S.l.",
    "wof:placetype":"venue"
},
  "geometry": {"coordinates":[-0.1319876015,38.5404434204],"type":"Point"}
}