{
  "type": "Feature",
  "properties": {
    "iso:country":"ES",
    "sg:address":"Calle de Serrano, 60",
    "sg:city":"Madrid",
    "sg:orig_category":"Comit\u00c9s De Organizaci\u00d3n De Exposiciones, Ferias, Salones",
    "sg:phone":"+34 914 26 02 02",
    "sg:postcode":"28001",
    "sg:province":"Madrid",
    "sg:website":"www.fundacio.lacaixa.es",
    "wof:name":"Fundacio 'la Caixa'",
    "wof:placetype":"venue"
},
  "geometry": {"coordinates":[-3.6870288849,40.4287796021],"type":"Point"}
}