{
  "type": "Feature",
  "properties": {
    "iso:country":"ES",
    "sg:address":"Ctra Chipiona (de), Km. 0005,0",
    "sg:city":"Sanlucar De Barrameda",
    "sg:orig_category":"Arquitectos",
    "sg:phone":"+34 956 36 85 60",
    "sg:postcode":"11540",
    "sg:province":"C\u00e1diz",
    "wof:name":"Turgadi S.l.",
    "wof:placetype":"venue"
},
  "geometry": {"coordinates":[-6.3554410934,36.771686554],"type":"Point"}
}