{
  "type": "Feature",
  "properties": {
    "iso:country":"ES",
    "sg:address":"Pg Gracia, 39",
    "sg:city":"Barcelona",
    "sg:orig_category":"Abogados",
    "sg:phone":"+34 933 18 32 11",
    "sg:postcode":"08007",
    "sg:province":"Barcelona",
    "wof:name":"Outsourcing Juridic Rmb",
    "wof:placetype":"venue"
},
  "geometry": {"coordinates":[2.1653730869,41.3914413452],"type":"Point"}
}