{
  "type": "Feature",
  "properties": {
    "iso:country":"ES",
    "sg:address":"Carrer de Sant Tomas, 56",
    "sg:city":"Barcelona",
    "sg:orig_category":"Carnes De Carnicer\u00cda (al Por Mayor)",
    "sg:phone":"+34 934 29 97 90",
    "sg:postcode":"08032",
    "sg:province":"Barcelona",
    "wof:name":"Cansaladeries Grau S.l.",
    "wof:placetype":"venue"
},
  "geometry": {"coordinates":[2.1575279236,41.4321403503],"type":"Point"}
}