{
  "type": "Feature",
  "properties": {
    "addr:full":"Ctra. Toledo-avila, Km. 0062,8 Almorox Toledo 45900",
    "addr:postcode":"45900",
    "addr:street":"Ctra. Toledo-Avila Km. 0062,8",
    "iso:country":"ES",
    "sg:address":"Ctra. Toledo-avila, Km. 0062,8",
    "sg:city":"Almorox",
    "sg:orig_category":"Distribuci\u00d3n De Petr\u00d3leo Y Derivados",
    "sg:phone":"+34 918 62 40 09",
    "sg:postcode":"45900",
    "sg:province":"Toledo",
    "wof:name":"L Esteban S.l.",
    "wof:placetype":"venue"
},
  "geometry": {"coordinates":[-4.3917040825,40.2329902649],"type":"Point"}
}