{
  "type": "Feature",
  "properties": {
    "addr:full":"Av Meridiana, 408 Barcelona Barcelona 08030",
    "addr:housenumber":"408",
    "addr:postcode":"08030",
    "addr:street":"Meridiana",
    "iso:country":"ES",
    "sg:address":"Av Meridiana, 408",
    "sg:city":"Barcelona",
    "sg:orig_category":"Molduras, Junquillos, Listones Y Molduras Perforadas",
    "sg:phone":"+34 933 45 02 06",
    "sg:postcode":"08030",
    "sg:province":"Barcelona",
    "wof:name":"Barot S.c.p.",
    "wof:placetype":"venue"
},
  "geometry": {"coordinates":[2.1836259365,41.4313316345],"type":"Point"}
}