{
  "type": "Feature",
  "properties": {
    "addr:full":"Calle de Mallos De Riglos, 3 Jaca Huesca 22700",
    "addr:housenumber":"3",
    "addr:postcode":"22700",
    "addr:street":"Calle De Mallos De Riglos",
    "iso:country":"ES",
    "sg:address":"Calle de Mallos De Riglos, 3",
    "sg:city":"Jaca",
    "sg:orig_category":"Plomeros",
    "sg:phone":"+34 974 36 18 74",
    "sg:postcode":"22700",
    "sg:province":"Huesca",
    "wof:name":"Talvica S.l.",
    "wof:placetype":"venue"
},
  "geometry": {"coordinates":[-0.5483955741,42.5731964111],"type":"Point"}
}