{
  "type": "Feature",
  "properties": {
    "addr:full":"Calle de Julio Romero De Torres, 20 Argana Alta Las Palmas 35500",
    "addr:housenumber":"20",
    "addr:postcode":"35500",
    "addr:street":"Calle De Julio Romero De Torres",
    "iso:country":"ES",
    "sg:address":"Calle de Julio Romero De Torres, 20",
    "sg:city":"Argana Alta",
    "sg:orig_category":"Empresas De Carpinter\u00cda",
    "sg:phone":"+34 928 81 68 52",
    "sg:postcode":"35500",
    "sg:province":"Las Palmas",
    "wof:name":"Carpinteria Manrique S.l.",
    "wof:placetype":"venue"
},
  "geometry": {"coordinates":[-13.5699081421,28.9807739258],"type":"Point"}
}