{
  "type": "Feature",
  "properties": {
    "iso:country":"ES",
    "sg:address":"Calle de Andaluces, 22",
    "sg:city":"Malaga",
    "sg:orig_category":"Arquitectos",
    "sg:phone":"+34 952 20 13 57",
    "sg:postcode":"29018",
    "sg:province":"M\u00e1laga",
    "wof:name":"Fernandez Bordes Antonio Miguel",
    "wof:placetype":"venue"
},
  "geometry": {"coordinates":[-4.3798823357,36.729763031],"type":"Point"}
}