{
  "type": "Feature",
  "properties": {
    "addr:full":"Calle de Rosario, 92 Albacete Albacete 02003",
    "addr:housenumber":"92",
    "addr:postcode":"02003",
    "addr:street":"Calle De Rosario",
    "iso:country":"ES",
    "sg:address":"Calle de Rosario, 92",
    "sg:city":"Albacete",
    "sg:orig_category":"Peluquer\u00cdas, Peluquer\u00cda Mixta",
    "sg:phone":"+34 967 23 81 89",
    "sg:postcode":"02003",
    "sg:province":"Albacete",
    "wof:name":"Requena Herrero Juana",
    "wof:placetype":"venue"
},
  "geometry": {"coordinates":[-1.8606270552,38.9881477356],"type":"Point"}
}