{
  "type": "Feature",
  "properties": {
    "iso:country":"ES",
    "sg:address":"Calle de Ayora, 32",
    "sg:city":"Valencia",
    "sg:orig_category":"Inform\u00c1tica (estudios, Servicios, Asesor\u00cda, Formaci\u00d3n)",
    "sg:phone":"+34 963 85 98 32",
    "sg:postcode":"46018",
    "sg:province":"Valencia",
    "wof:name":"Grim Sistemas S.l.",
    "wof:placetype":"venue"
},
  "geometry": {"coordinates":[-0.3934932053,39.4645957947],"type":"Point"}
}