{
  "type": "Feature",
  "properties": {
    "addr:full":"Calle de Jose Ponte, S/n Perdoma Santa Cruz De Tenerife 38315",
    "addr:housenumber":"s",
    "addr:postcode":"38315",
    "addr:street":"Calle De Jose Ponte;/ N Perdoma",
    "iso:country":"ES",
    "sg:address":"Calle de Jose Ponte, S/n",
    "sg:city":"Perdoma",
    "sg:orig_category":"Empresas De Carpinter\u00cda De Madera",
    "sg:phone":"+34 922 30 87 89",
    "sg:postcode":"38315",
    "sg:province":"Santa Cruz De Tenerife",
    "wof:name":"Ramos Rodriguez Jose",
    "wof:placetype":"venue"
},
  "geometry": {"coordinates":[-16.5055618286,28.3659114838],"type":"Point"}
}