{
  "type": "Feature",
  "properties": {
    "iso:country":"ES",
    "sg:address":"Calle de Catedratico Alcala Santaella, 46",
    "sg:city":"Baena",
    "sg:orig_category":"Sindicatos De Trabajadores",
    "sg:phone":"+34 957 69 07 87",
    "sg:postcode":"14850",
    "sg:province":"C\u00f3rdoba",
    "wof:name":"Union General De Trabajadores",
    "wof:placetype":"venue"
},
  "geometry": {"coordinates":[-4.3192877769,37.6197319031],"type":"Point"}
}