{
  "type": "Feature",
  "properties": {
    "addr:full":"Calle de Castelar, 10 Villafranqueza - Palamo Alicante 03112",
    "addr:housenumber":"10",
    "addr:postcode":"03112",
    "addr:street":"Calle De Castelar",
    "iso:country":"ES",
    "sg:address":"Calle de Castelar, 10",
    "sg:city":"Villafranqueza - Palamo",
    "sg:orig_category":"Molduras, Junquillos, Listones Y Molduras Perforadas",
    "sg:phone":"+34 965 17 92 81",
    "sg:postcode":"03112",
    "sg:province":"Alicante",
    "wof:name":"Comunicaciones Marsol S.l.",
    "wof:placetype":"venue"
},
  "geometry": {"coordinates":[-0.4915809035,38.3866424561],"type":"Point"}
}