{
  "type": "Feature",
  "properties": {
    "iso:country":"ES",
    "sg:address":"Saa(vilavella), 22",
    "sg:city":"Pontes Garcia Rodriguez",
    "sg:orig_category":"Construcciones Met\u00c1licas",
    "sg:phone":"+34 981 44 03 05",
    "sg:postcode":"15320",
    "sg:province":"A Coru\u00f1a",
    "wof:name":"Talleres Metalicos Maceira S.l.",
    "wof:placetype":"venue"
},
  "geometry": {"coordinates":[-7.8519802094,43.4437828064],"type":"Point"}
}