{
  "type": "Feature",
  "properties": {
    "iso:country":"ES",
    "sg:address":"Calle de Alfredo Atienza, 165",
    "sg:city":"Roda",
    "sg:orig_category":"Materias Pl\u00c1sticas: Productos De Consumo Masivo (fabricaci\u00d3n, Al Por Mayor)",
    "sg:phone":"+34 967 44 24 89",
    "sg:postcode":"02630",
    "sg:province":"Albacete",
    "wof:name":"Aiplast S.l.",
    "wof:placetype":"venue"
},
  "geometry": {"coordinates":[-2.1457357407,39.1996307373],"type":"Point"}
}