{
  "type": "Feature",
  "properties": {
    "iso:country":"ES",
    "sg:address":"Calle de Sebastian Elcano, 20",
    "sg:city":"Sevilla",
    "sg:orig_category":"Farmacias",
    "sg:phone":"+34 954 27 07 85",
    "sg:postcode":"41011",
    "sg:province":"Sevilla",
    "wof:name":"Salda\u00f1a Morales Margarita",
    "wof:placetype":"venue"
},
  "geometry": {"coordinates":[-5.9715051651,37.4123764038],"type":"Point"}
}