{
  "type": "Feature",
  "properties": {
    "addr:full":"Calle de Babia, 2 Villablino Le\u00f3n 24100",
    "addr:housenumber":"2",
    "addr:postcode":"24100",
    "addr:street":"Calle De Babia",
    "iso:country":"ES",
    "sg:address":"Calle de Babia, 2",
    "sg:city":"Villablino",
    "sg:orig_category":"Fisioterapia",
    "sg:phone":"+34 987 48 00 64",
    "sg:postcode":"24100",
    "sg:province":"Le\u00f3n",
    "wof:name":"Fisiomed Laciana S.l.l.",
    "wof:placetype":"venue"
},
  "geometry": {"coordinates":[-6.3177809715,42.938243866],"type":"Point"}
}