{
  "type": "Feature",
  "properties": {
    "addr:full":"Calle de Velazquez, 16 Le\u00f3n Le\u00f3n 24004",
    "addr:housenumber":"16",
    "addr:postcode":"24004",
    "addr:street":"Calle De Velazquez;Leo\u0301N",
    "iso:country":"ES",
    "sg:address":"Calle de Velazquez, 16",
    "sg:city":"Le\u00f3n",
    "sg:orig_category":"Caf\u00c9s, Bares, Cervecer\u00cdas",
    "sg:phone":"+34 987 26 31 14",
    "sg:postcode":"24004",
    "sg:province":"Le\u00f3n",
    "wof:name":"Fernandez Matilla Juan Manuel",
    "wof:placetype":"venue"
},
  "geometry": {"coordinates":[-5.5677528381,42.5900726318],"type":"Point"}
}