{
  "type": "Feature",
  "properties": {
    "addr:full":"Iparragirre Kalea, 11 Urretxu Guip\u00f9zcoa 20700",
    "addr:housenumber":"11",
    "addr:postcode":"20700",
    "addr:street":"Iparragirre Kalea;Guipu\u0300Zcoa",
    "iso:country":"ES",
    "sg:address":"Iparragirre Kalea, 11",
    "sg:city":"Urretxu",
    "sg:orig_category":"Electricidad: Instaladores",
    "sg:phone":"+34 943 03 47 06",
    "sg:postcode":"20700",
    "sg:province":"Guip\u00f9zcoa",
    "wof:name":"Deunor Ezpeleta Plazaola",
    "wof:placetype":"venue"
},
  "geometry": {"coordinates":[-2.3141479492,43.0923995972],"type":"Point"}
}