{
  "type": "Feature",
  "properties": {
    "addr:full":"Calle de Caramuel, 21 Madrid Madrid 28011",
    "addr:housenumber":"21",
    "addr:postcode":"madrid;28011",
    "addr:street":"Calle De Caramuel",
    "iso:country":"ES",
    "sg:address":"Calle de Caramuel, 21",
    "sg:city":"Madrid",
    "sg:orig_category":"Colchones (fabricaci\u00d3n, Al Por Mayor, Al Por Menor)",
    "sg:phone":"+34 914 64 63 90",
    "sg:postcode":"28011",
    "sg:province":"Madrid",
    "wof:name":"Manguan Gutierrez Esperanza",
    "wof:placetype":"venue"
},
  "geometry": {"coordinates":[-3.7267456055,40.4118881226],"type":"Point"}
}