{
  "type": "Feature",
  "properties": {
    "iso:country":"ES",
    "sg:address":"Calle de Viera, 22",
    "sg:city":"Orotava",
    "sg:orig_category":"Quincaller\u00cda (al Por Menor)",
    "sg:phone":"+34 922 33 57 30",
    "sg:postcode":"38300",
    "sg:province":"Santa Cruz De Tenerife",
    "wof:name":"Regalado Alonso Juan",
    "wof:placetype":"venue"
},
  "geometry": {"coordinates":[-16.5259857178,28.3913345337],"type":"Point"}
}