{
  "type": "Feature",
  "properties": {
    "addr:full":"Avda Martinez De Velasco, 33 Huesca Huesca 22004",
    "addr:housenumber":"33",
    "addr:postcode":"22004",
    "addr:street":"Avda Martinez De Velasco",
    "iso:country":"ES",
    "sg:address":"Avda Martinez De Velasco, 33",
    "sg:city":"Huesca",
    "sg:orig_category":"Agentes, Concesionarios Y Sucursales De Veh\u00cdculos",
    "sg:phone":"+34 974 21 56 86",
    "sg:postcode":"22004",
    "sg:province":"Huesca",
    "wof:name":"Automoviles Cabrero Hermanos Huesca S.l.",
    "wof:placetype":"venue"
},
  "geometry": {"coordinates":[-0.4143390059,42.1329040527],"type":"Point"}
}