{
  "type": "Feature",
  "properties": {
    "iso:country":"ES",
    "sg:address":"Calle de Pi Y Margall, 7",
    "sg:city":"Roda",
    "sg:orig_category":"Materias Pl\u00c1sticas: Productos De Consumo Masivo (fabricaci\u00d3n, Al Por Mayor)",
    "sg:phone":"+34 967 44 05 63",
    "sg:postcode":"02630",
    "sg:province":"Albacete",
    "wof:name":"Escribano Martinez-herrera Jesus",
    "wof:placetype":"venue"
},
  "geometry": {"coordinates":[-2.1561770439,39.2046546936],"type":"Point"}
}