{
  "type": "Feature",
  "properties": {
    "addr:full":"Rond Bellavista, 23 Mataro Barcelona 08303",
    "addr:housenumber":"23",
    "addr:postcode":"08303",
    "addr:street":"Bellavista",
    "iso:country":"ES",
    "sg:address":"Rond Bellavista, 23",
    "sg:city":"Mataro",
    "sg:orig_category":"Perfumer\u00cda, Art\u00cdculos De Ba\u00d1o (fabricaci\u00d3n, Al Por Mayor)",
    "sg:phone":"+34 937 98 54 65",
    "sg:postcode":"08303",
    "sg:province":"Barcelona",
    "wof:name":"Displamer S.a.",
    "wof:placetype":"venue"
},
  "geometry": {"coordinates":[2.4216630459,41.5434761047],"type":"Point"}
}