{
  "type": "Feature",
  "properties": {
    "iso:country":"ES",
    "sg:address":"Calle de Tauro, 1",
    "sg:city":"Madrid",
    "sg:orig_category":"Aparcamientos (infraestructuras, Accesorios)",
    "sg:phone":"+34 913 29 27 37",
    "sg:postcode":"28042",
    "sg:province":"Madrid",
    "sg:website":"www.e-airpack.com",
    "wof:name":"Airpack Aparcacoches S.l.",
    "wof:placetype":"venue"
},
  "geometry": {"coordinates":[-3.5686423779,40.4501876831],"type":"Point"}
}