{
  "type": "Feature",
  "properties": {
    "iso:country":"ES",
    "sg:address":"Plaz Tres Parentes, 7",
    "sg:city":"Pedraja Portillo",
    "sg:orig_category":"Imprenta",
    "sg:phone":"+34 983 55 33 87",
    "sg:postcode":"47196",
    "sg:province":"Valladolid",
    "wof:name":"Graficas Las Campa\u00f1as Sociedad Cooperativa",
    "wof:placetype":"venue"
},
  "geometry": {"coordinates":[-4.6466240883,41.4722366333],"type":"Point"}
}