{
  "type": "Feature",
  "properties": {
    "addr:full":"Bo. Villachica, 59 Villachica \u00c1lava 01409",
    "addr:housenumber":"59",
    "addr:postcode":"01409",
    "addr:street":"Bo. Villachica;A\u0301Lava",
    "iso:country":"ES",
    "sg:address":"Bo. Villachica, 59",
    "sg:city":"Villachica",
    "sg:orig_category":"Estancos",
    "sg:phone":"+34 945 89 81 77",
    "sg:postcode":"01409",
    "sg:province":"\u00c1lava",
    "wof:name":"Fernandez Del Campo Maria Yolanda",
    "wof:placetype":"venue"
},
  "geometry": {"coordinates":[-3.0286810398,43.1525382996],"type":"Point"}
}