{
  "type": "Feature",
  "properties": {
    "iso:country":"ES",
    "sg:address":"Rua Doutor Gasalla, 3",
    "sg:city":"Lugo",
    "sg:orig_category":"Supermercados Y Hipermercados",
    "sg:phone":"+34 982 21 65 05",
    "sg:postcode":"27004",
    "sg:province":"Lugo",
    "wof:name":"Cemar Alimemtacion S.l.",
    "wof:placetype":"venue"
},
  "geometry": {"coordinates":[-7.5627770424,43.0131263733],"type":"Point"}
}