{
  "type": "Feature",
  "properties": {
    "iso:country":"ES",
    "sg:address":"La Vega, S/n",
    "sg:city":"Leda\u00f1a",
    "sg:orig_category":"Centros De Educaci\u00d3n Especial",
    "sg:phone":"+34 967 49 23 18",
    "sg:postcode":"16237",
    "sg:province":"Cuenca",
    "wof:name":"Colegio Publico San Roque",
    "wof:placetype":"venue"
},
  "geometry": {"coordinates":[-1.7146140337,39.3586540222],"type":"Point"}
}