{
  "type": "Feature",
  "properties": {
    "addr:full":"Carrer de Consell De Cent, 553 Barcelona Barcelona 08013",
    "addr:housenumber":"553",
    "addr:postcode":"08013",
    "addr:street":"Carrer De Consell De Cent",
    "iso:country":"ES",
    "sg:address":"Carrer de Consell De Cent, 553",
    "sg:city":"Barcelona",
    "sg:orig_category":"Servicios De Telecomunicaciones",
    "sg:phone":"+34 932 72 13 25",
    "sg:postcode":"08013",
    "sg:province":"Barcelona",
    "wof:name":"Sercomtel Comunicaciones S.l.l.",
    "wof:placetype":"venue"
},
  "geometry": {"coordinates":[2.1823649406,41.4037895203],"type":"Point"}
}