{
  "type": "Feature",
  "properties": {
    "iso:country":"ES",
    "sg:address":"Calle de Manuel Maroto, 23",
    "sg:city":"Madrid",
    "sg:orig_category":"Cerrajer\u00cda, Ferrallista",
    "sg:phone":"+34 914 77 84 48",
    "sg:postcode":"28053",
    "sg:province":"Madrid",
    "wof:name":"Zaragoza Balado Joaquin",
    "wof:placetype":"venue"
},
  "geometry": {"coordinates":[-3.6689770222,40.3881072998],"type":"Point"}
}