{
  "type": "Feature",
  "properties": {
    "iso:country":"ES",
    "sg:address":"Avda Madrid (de), 72",
    "sg:city":"Jaen",
    "sg:orig_category":"Formaci\u00d3n A Distancia, Por Correspondencia",
    "sg:phone":"+34 953 25 58 50",
    "sg:postcode":"23008",
    "sg:province":"Ja\u00e9n",
    "wof:name":"Astasio Torres Maria",
    "wof:placetype":"venue"
},
  "geometry": {"coordinates":[-3.7854092121,37.7776641846],"type":"Point"}
}