{
  "type": "Feature",
  "properties": {
    "addr:full":"Calle de Circunde, 6 Logro\u00f1o La Rioja 26006",
    "addr:housenumber":"6",
    "addr:postcode":"26006",
    "addr:street":"Calle De Circunde;Rioja",
    "iso:country":"ES",
    "sg:address":"Calle de Circunde, 6",
    "sg:city":"Logro\u00f1o",
    "sg:orig_category":"Centros Empresariales",
    "sg:phone":"+34 941 44 51 98",
    "sg:postcode":"26006",
    "sg:province":"La Rioja",
    "wof:name":"Servipremier",
    "wof:placetype":"venue"
},
  "geometry": {"coordinates":[-2.4033839703,42.456073761],"type":"Point"}
}