{
  "type": "Feature",
  "properties": {
    "addr:full":"Calle de Virgen, 17 Don Benito Badajoz 06400",
    "addr:housenumber":"17",
    "addr:postcode":"06400",
    "addr:street":"Calle De Virgen",
    "iso:country":"ES",
    "sg:address":"Calle de Virgen, 17",
    "sg:city":"Don Benito",
    "sg:orig_category":"M\u00c9dicos: Reumatolog\u00cda",
    "sg:phone":"+34 924 80 05 88",
    "sg:postcode":"06400",
    "sg:province":"Badajoz",
    "wof:name":"Paniagua Parejo Guillermo",
    "wof:placetype":"venue"
},
  "geometry": {"coordinates":[-5.8622422218,38.9530830383],"type":"Point"}
}