{
  "type": "Feature",
  "properties": {
    "iso:country":"ES",
    "sg:address":"Calle de Ancha, 13",
    "sg:city":"Solana",
    "sg:orig_category":"Producci\u00d3n, Venta De Productos De Agricultura Biol\u00d3gica",
    "sg:phone":"+34 926 63 31 45",
    "sg:postcode":"13240",
    "sg:province":"Ciudad Real",
    "wof:name":"Almacen De Abonos Los Se\u00f1oritos S.l.",
    "wof:placetype":"venue"
},
  "geometry": {"coordinates":[-3.2414269447,38.943107605],"type":"Point"}
}