{
  "type": "Feature",
  "properties": {
    "addr:full":"Calle de Marques (del), 11 Pinto Madrid 28320",
    "addr:housenumber":"11",
    "addr:postcode":"28320",
    "addr:street":"Calle De Marques Del",
    "iso:country":"ES",
    "sg:address":"Calle de Marques (del), 11",
    "sg:city":"Pinto",
    "sg:orig_category":"Confecci\u00d3n De Trajes Para Se\u00d1oras",
    "sg:phone":"+34 916 92 31 39",
    "sg:postcode":"28320",
    "sg:province":"Madrid",
    "wof:name":"La Esquina De Sindo S.l.",
    "wof:placetype":"venue"
},
  "geometry": {"coordinates":[-3.6970460415,40.2426834106],"type":"Point"}
}