{
  "type": "Feature",
  "properties": {
    "iso:country":"ES",
    "sg:address":"Pl. 19 Octubre, S/n",
    "sg:city":"Oviedo",
    "sg:orig_category":"Distribuci\u00d3n De Petr\u00d3leo Y Derivados",
    "sg:phone":"+34 985 21 07 38",
    "sg:postcode":"33009",
    "sg:province":"Asturias",
    "wof:name":"Campillo Diaz Alicia",
    "wof:placetype":"venue"
},
  "geometry": {"coordinates":[-5.8475308418,43.3626899719],"type":"Point"}
}