{
  "type": "Feature",
  "properties": {
    "addr:full":"Av Gaudi, 74 Rubi Barcelona 08191",
    "addr:housenumber":"74",
    "addr:postcode":"08191",
    "addr:street":"Av Gaudi",
    "iso:country":"ES",
    "sg:address":"Av Gaudi, 74",
    "sg:city":"Rubi",
    "sg:orig_category":"Goma: Productos De Uso Industrial (fabricaci\u00d3n, Al Por Mayor)",
    "sg:phone":"+34 936 99 76 64",
    "sg:postcode":"08191",
    "sg:province":"Barcelona",
    "wof:name":"Ubeda Serra Gonzalo",
    "wof:placetype":"venue"
},
  "geometry": {"coordinates":[2.0097749233,41.509727478],"type":"Point"}
}