{
  "type": "Feature",
  "properties": {
    "iso:country":"ES",
    "sg:address":"Calle de Velazquez, 11",
    "sg:city":"Madrid",
    "sg:orig_category":"M\u00c9dicos: Neurolog\u00cda",
    "sg:phone":"+34 915 77 69 66",
    "sg:postcode":"28001",
    "sg:province":"Madrid",
    "wof:name":"Sancel S.l.",
    "wof:placetype":"venue"
},
  "geometry": {"coordinates":[-3.6845490932,40.4221954346],"type":"Point"}
}