{
  "type": "Feature",
  "properties": {
    "iso:country":"ES",
    "sg:address":"Calle de Teresa Gil, 6",
    "sg:city":"Valladolid",
    "sg:orig_category":"M\u00c9dicos: Estomatolog\u00cda",
    "sg:phone":"+34 983 37 52 88",
    "sg:postcode":"47002",
    "sg:province":"Valladolid",
    "wof:name":"Terron Garcia Ernesto",
    "wof:placetype":"venue"
},
  "geometry": {"coordinates":[-4.7263908386,41.6516494751],"type":"Point"}
}