{
  "type": "Feature",
  "properties": {
    "addr:full":"Calle de Pintor Navarro Martin, 3 Malaga M\u00e1laga 29007",
    "addr:housenumber":"3",
    "addr:postcode":"29007",
    "addr:street":"Calle De Pintor Navarro Martin;Ma\u0301Laga",
    "iso:country":"ES",
    "sg:address":"Calle de Pintor Navarro Martin, 3",
    "sg:city":"Malaga",
    "sg:orig_category":"Tapicer\u00cdas",
    "sg:phone":"+34 952 39 64 02",
    "sg:postcode":"29007",
    "sg:province":"M\u00e1laga",
    "wof:name":"Aponte Fernandez Manuel",
    "wof:placetype":"venue"
},
  "geometry": {"coordinates":[-4.4339470863,36.7206535339],"type":"Point"}
}