{
  "type": "Feature",
  "properties": {
    "addr:full":"Calle de Embajadores, 16 Valladolid Valladolid 47013",
    "addr:housenumber":"16",
    "addr:postcode":"47013",
    "addr:street":"Calle De Embajadores",
    "iso:country":"ES",
    "sg:address":"Calle de Embajadores, 16",
    "sg:city":"Valladolid",
    "sg:orig_category":"Artes Gr\u00c1ficas, Artes Pl\u00c1sticas (curso)",
    "sg:phone":"+34 983 47 51 18",
    "sg:postcode":"47013",
    "sg:province":"Valladolid",
    "wof:name":"Casa Ambrosio Rodriguez S.a.",
    "wof:placetype":"venue"
},
  "geometry": {"coordinates":[-4.7218799591,41.6382522583],"type":"Point"}
}