{
  "type": "Feature",
  "properties": {
    "addr:full":"Calle de Garcia Pizarro, 4 Motril Granada 18600",
    "addr:housenumber":"4",
    "addr:postcode":"18600",
    "addr:street":"Calle De Garcia Pizarro",
    "iso:country":"ES",
    "sg:address":"Calle de Garcia Pizarro, 4",
    "sg:city":"Motril",
    "sg:orig_category":"Carnicer\u00cdas, Carnicer\u00cdas",
    "sg:phone":"+34 958 60 10 19",
    "sg:postcode":"18600",
    "sg:province":"Granada",
    "wof:name":"Lopez Estevez Arsenio",
    "wof:placetype":"venue"
},
  "geometry": {"coordinates":[-3.5197389126,36.7446212769],"type":"Point"}
}