{
  "type": "Feature",
  "properties": {
    "iso:country":"ES",
    "sg:address":"Calle de Lavanda, 18",
    "sg:city":"Rozas De Madrid",
    "sg:orig_category":"Servicios De Telecomunicaciones",
    "sg:phone":"+34 916 37 66 96",
    "sg:postcode":"28230",
    "sg:province":"Madrid",
    "wof:name":"Nueva Era Comunicacion S.l.",
    "wof:placetype":"venue"
},
  "geometry": {"coordinates":[-3.8671960831,40.4964256287],"type":"Point"}
}