{
  "type": "Feature",
  "properties": {
    "iso:country":"ES",
    "sg:address":"Calle de Medina, 4",
    "sg:city":"Jerez De La Frontera",
    "sg:orig_category":"Agencias De Viajes",
    "sg:phone":"+34 956 33 06 57",
    "sg:postcode":"11406",
    "sg:province":"C\u00e1diz",
    "wof:name":"Viajes Difran S.a.",
    "wof:placetype":"venue"
},
  "geometry": {"coordinates":[-6.1348481178,36.6828689575],"type":"Point"}
}