{
  "type": "Feature",
  "properties": {
    "iso:country":"ES",
    "sg:address":"Calle de Alcarria (de La), 7",
    "sg:city":"Coslada",
    "sg:orig_category":"Electrodom\u00c9sticos (fabricaci\u00d3n, Al Por Mayor)",
    "sg:phone":"+34 916 72 45 51",
    "sg:postcode":"28820",
    "sg:province":"Madrid",
    "sg:website":"www.candy.es",
    "wof:name":"Candy Hoover Electrodomesticos S.a.",
    "wof:placetype":"venue"
},
  "geometry": {"coordinates":[-3.5493452549,40.4310455322],"type":"Point"}
}