{
  "type": "Feature",
  "properties": {
    "iso:country":"ES",
    "sg:address":"Calle de Eras, 25",
    "sg:city":"Velada",
    "sg:orig_category":"Empresas De Carpinter\u00cda De Madera",
    "sg:phone":"+34 925 89 22 64",
    "sg:postcode":"45612",
    "sg:province":"Toledo",
    "wof:name":"Carpinteria Vega C.b",
    "wof:placetype":"venue"
},
  "geometry": {"coordinates":[-4.9750342369,39.9733848572],"type":"Point"}
}