{
  "type": "Feature",
  "properties": {
    "iso:country":"ES",
    "sg:address":"Plaz Salvador Ponce, S/n",
    "sg:city":"Malaga",
    "sg:orig_category":"Comit\u00c9s De Organizaci\u00d3n De Exposiciones, Ferias, Salones",
    "sg:phone":"+34 952 35 51 94",
    "sg:postcode":"29003",
    "sg:province":"M\u00e1laga",
    "wof:name":"Arquitecturas Malaka S.l.",
    "wof:placetype":"venue"
},
  "geometry": {"coordinates":[-4.4477968216,36.7004547119],"type":"Point"}
}