{
  "type": "Feature",
  "properties": {
    "iso:country":"ES",
    "sg:address":"Carrer de Tiradors, 9",
    "sg:city":"Barcelona",
    "sg:orig_category":"Maquinaria Para Industrias Diversas",
    "sg:phone":"+34 932 68 87 82",
    "sg:postcode":"08003",
    "sg:province":"Barcelona",
    "wof:name":"Rodriguez Ca\u00f1ellas David",
    "wof:placetype":"venue"
},
  "geometry": {"coordinates":[2.1812880039,41.3881454468],"type":"Point"}
}