{
  "type": "Feature",
  "properties": {
    "addr:full":"Calle de Nueva, 37 Tomelloso Ciudad Real 13700",
    "addr:housenumber":"37",
    "addr:postcode":"13700",
    "addr:street":"Calle De Nueva",
    "iso:country":"ES",
    "sg:address":"Calle de Nueva, 37",
    "sg:city":"Tomelloso",
    "sg:classifiers":[
        {
            "category":"Taxi",
            "type":"Transportation"
        }
    ],
    "sg:phone":"+34 926 51 36 16",
    "sg:postcode":"13700",
    "sg:province":"Ciudad Real",
    "wof:name":"Espinosa Moreno Evaristo",
    "wof:placetype":"venue"
},
  "geometry": {"coordinates":[-3.0271520615,39.157207489],"type":"Point"}
}