{
  "type": "Feature",
  "properties": {
    "iso:country":"ES",
    "sg:address":"Carr Doctor Combelles, 34",
    "sg:city":"Lleida",
    "sg:orig_category":"Centros Empresariales",
    "sg:phone":"+34 973 28 21 29",
    "sg:postcode":"25003",
    "sg:province":"Lleida",
    "wof:name":"Associacio Provincial D'estacio De Servei De Lleida",
    "wof:placetype":"venue"
},
  "geometry": {"coordinates":[0.6172103286,41.6150474548],"type":"Point"}
}