{
  "type": "Feature",
  "properties": {
    "iso:country":"ES",
    "sg:address":"A. Las Ca\u00f1as, S/n",
    "sg:city":"Estepona",
    "sg:orig_category":"Promotores Constructores",
    "sg:phone":"+34 952 79 64 27",
    "sg:postcode":"29680",
    "sg:province":"M\u00e1laga",
    "sg:website":"www.noriega-sa.es",
    "wof:name":"Lomas De La Resinera S.l.",
    "wof:placetype":"venue"
},
  "geometry": {"coordinates":[-5.1744904518,36.4435119629],"type":"Point"}
}