{
  "type": "Feature",
  "properties": {
    "iso:country":"ES",
    "sg:address":"Avda Miguel Gonzalez Garces, 2",
    "sg:city":"Portadego",
    "sg:orig_category":"Asesor\u00cda Sobre Comunicaci\u00d3n De Empresas",
    "sg:phone":"+34 981 61 21 70",
    "sg:postcode":"15174",
    "sg:province":"La Coru\u00f1a",
    "wof:name":"Gesem Asesoria De Empresas S.l.",
    "wof:placetype":"venue"
},
  "geometry": {"coordinates":[-8.3826389313,43.3110656738],"type":"Point"}
}