{
  "type": "Feature",
  "properties": {
    "iso:country":"ES",
    "sg:address":"Cmno Molino (el), S/n",
    "sg:city":"San Pedro De Bre\u00e7a Alta",
    "sg:orig_category":"Veh\u00cdculos De Ocasi\u00d3n",
    "sg:phone":"+34 922 43 70 11",
    "sg:postcode":"38710",
    "sg:province":"Santa Cruz De Tenerife",
    "wof:name":"Rahn La Palma S.l.",
    "wof:placetype":"venue"
},
  "geometry": {"coordinates":[-17.774597168,28.6610641479],"type":"Point"}
}