{
  "type": "Feature",
  "properties": {
    "addr:full":"Calle de Francisco Solis, 6 Mancha Real Ja\u00e9n 23100",
    "addr:housenumber":"6",
    "addr:postcode":"23100",
    "addr:street":"Calle De Francisco Solis",
    "iso:country":"ES",
    "sg:address":"Calle de Francisco Solis, 6",
    "sg:city":"Mancha Real",
    "sg:orig_category":"Asociaciones Humanitarias, De Cooperaci\u00d3n, De Acci\u00d3n Social",
    "sg:phone":"+34 953 35 07 85",
    "sg:postcode":"23100",
    "sg:province":"Ja\u00e9n",
    "wof:name":"Asociacion Provincial Pro Minusvalidos Psiquicos Jaen-aprompsi",
    "wof:placetype":"venue"
},
  "geometry": {"coordinates":[-3.6110286713,37.7883338928],"type":"Point"}
}