{
  "type": "Feature",
  "properties": {
    "addr:full":"Calle de Luisa De Guzman, 1 Sanlucar De Barrameda C\u00e1diz 11540",
    "addr:housenumber":"1",
    "addr:postcode":"11540",
    "addr:street":"Calle De Luisa De Guzman;Ca\u0301Diz",
    "iso:country":"ES",
    "sg:address":"Calle de Luisa De Guzman, 1",
    "sg:city":"Sanlucar De Barrameda",
    "sg:classifiers":[
        {
            "category":"Taxi",
            "type":"Transportation"
        }
    ],
    "sg:phone":"+34 956 36 99 07",
    "sg:postcode":"11540",
    "sg:province":"C\u00e1diz",
    "wof:name":"Garcia Garcia Rodrigo Ramon",
    "wof:placetype":"venue"
},
  "geometry": {"coordinates":[-6.3579239845,36.782661438],"type":"Point"}
}