{
  "type": "Feature",
  "properties": {
    "iso:country":"ES",
    "sg:address":"Calle de Cajal Lasala, Joaquin, S/n",
    "sg:city":"Huesca",
    "sg:orig_category":"Reparaci\u00d3n Y Restauraci\u00d3n De Objetos Diversos",
    "sg:phone":"+34 974 21 20 34",
    "sg:postcode":"22004",
    "sg:province":"Huesca",
    "wof:name":"Omnia Motor S.a.",
    "wof:placetype":"venue"
},
  "geometry": {"coordinates":[-0.4408037066,42.1070098877],"type":"Point"}
}