{
  "type": "Feature",
  "properties": {
    "iso:country":"ES",
    "sg:address":"Carrer de Malaga, 28",
    "sg:city":"Palma",
    "sg:orig_category":"Relojer\u00cda (al Por Menor, Reparaci\u00d3n)",
    "sg:phone":"+34 971 27 62 03",
    "sg:postcode":"07008",
    "sg:province":"Islas Baleares",
    "wof:name":"Cronson S.l.",
    "wof:placetype":"venue"
},
  "geometry": {"coordinates":[2.6702420712,39.5805244446],"type":"Point"}
}