{
  "type": "Feature",
  "properties": {
    "iso:country":"ES",
    "sg:address":"Avda Rodriguez De La Fuente De Illora, 10",
    "sg:city":"Illora",
    "sg:orig_category":"Arquitectos",
    "sg:phone":"+34 958 46 35 02",
    "sg:postcode":"18260",
    "sg:province":"Granada",
    "wof:name":"Valenzuela Arco Cristobal",
    "wof:placetype":"venue"
},
  "geometry": {"coordinates":[-3.8795850277,37.2847213745],"type":"Point"}
}