{
  "type": "Feature",
  "properties": {
    "iso:country":"ES",
    "sg:address":"Carrer de Alcolea, 52",
    "sg:city":"Barcelona",
    "sg:orig_category":"Reposter\u00cdas",
    "sg:phone":"+34 934 90 31 71",
    "sg:postcode":"08014",
    "sg:province":"Barcelona",
    "wof:name":"Nadal Blanch Josefa",
    "wof:placetype":"venue"
},
  "geometry": {"coordinates":[2.1362640858,41.377532959],"type":"Point"}
}