{
  "type": "Feature",
  "properties": {
    "iso:country":"ES",
    "sg:address":"Plaz Ferial (el), 3",
    "sg:city":"Urroz",
    "sg:orig_category":"Diarios, Prensa, Revistas (al Por Menor)",
    "sg:phone":"+34 948 33 81 82",
    "sg:postcode":"31420",
    "sg:province":"Navarra",
    "wof:name":"Garisoain Otero Javier",
    "wof:placetype":"venue"
},
  "geometry": {"coordinates":[-1.4608000517,42.7779083252],"type":"Point"}
}