{
  "type": "Feature",
  "properties": {
    "addr:full":"Calle de Al Andalus, 7 Salobre\u00f1a Granada 18680",
    "addr:housenumber":"7",
    "addr:postcode":"18680",
    "addr:street":"Calle De Al Andalus",
    "iso:country":"ES",
    "sg:address":"Calle de Al Andalus, 7",
    "sg:city":"Salobre\u00f1a",
    "sg:orig_category":"T\u00c9cnicos Veterinarios",
    "sg:phone":"+34 958 82 88 75",
    "sg:postcode":"18680",
    "sg:province":"Granada",
    "wof:name":"Morales Romero Jessica",
    "wof:placetype":"venue"
},
  "geometry": {"coordinates":[-3.5821313858,36.7436141968],"type":"Point"}
}