{
  "type": "Feature",
  "properties": {
    "iso:country":"ES",
    "sg:address":"Avgd Cami Nou, 129",
    "sg:city":"Benetusser",
    "sg:orig_category":"Agencias De Trabajo Temporal",
    "sg:phone":"+34 963 18 20 63",
    "sg:postcode":"46910",
    "sg:province":"Valencia",
    "sg:website":"www.activaett.com",
    "wof:name":"Activa Seleccion Valencia Ett S. L.",
    "wof:placetype":"venue"
},
  "geometry": {"coordinates":[-0.3970423937,39.4191093445],"type":"Point"}
}