{
  "type": "Feature",
  "properties": {
    "iso:country":"ES",
    "sg:address":"Calle de Doctor Horno Alcorta, 21",
    "sg:city":"Zaragoza",
    "sg:orig_category":"Laboratorios Y Trabajos De Fotograf\u00cda, V\u00cddeo Y Cine",
    "sg:phone":"+34 976 23 08 77",
    "sg:postcode":"50004",
    "sg:province":"Zaragoza",
    "wof:name":"Cortes Ponz Jose Damian",
    "wof:placetype":"venue"
},
  "geometry": {"coordinates":[-0.8905910254,41.649520874],"type":"Point"}
}