{
  "type": "Feature",
  "properties": {
    "iso:country":"ES",
    "sg:address":"Carrer de Castelao, 170",
    "sg:city":"Hospitalet Llobregat",
    "sg:orig_category":"Escotaduras, Torneados",
    "sg:phone":"+34 932 63 34 87",
    "sg:postcode":"08902",
    "sg:province":"Barcelona",
    "wof:name":"Jimenez Guerrero Francisco",
    "wof:placetype":"venue"
},
  "geometry": {"coordinates":[2.1260979176,41.3605804443],"type":"Point"}
}