{
  "type": "Feature",
  "properties": {
    "addr:full":"Avda Lerida (de), 27 Monzon Huesca 22400",
    "addr:housenumber":"27",
    "addr:postcode":"22400",
    "addr:street":"Avda Lerida De",
    "iso:country":"ES",
    "sg:address":"Avda Lerida (de), 27",
    "sg:city":"Monzon",
    "sg:orig_category":"Peluqueros: De Se\u00d1oras",
    "sg:phone":"+34 974 40 20 57",
    "sg:postcode":"22400",
    "sg:province":"Huesca",
    "wof:name":"Liesa Saludas Maria Pilar",
    "wof:placetype":"venue"
},
  "geometry": {"coordinates":[0.1951079965,41.9123306274],"type":"Point"}
}