{
  "type": "Feature",
  "properties": {
    "addr:full":"Calle de Torrejon, S/n Parla Madrid 28980",
    "addr:housenumber":"s / n",
    "addr:postcode":"28980",
    "addr:street":"Calle De Torrejon",
    "iso:country":"ES",
    "sg:address":"Calle de Torrejon, S/n",
    "sg:city":"Parla",
    "sg:orig_category":"Carnicer\u00cdas, Carnicer\u00cdas",
    "sg:phone":"+34 916 99 70 38",
    "sg:postcode":"28980",
    "sg:province":"Madrid",
    "wof:name":"Garcia Alvarez Manuel",
    "wof:placetype":"venue"
},
  "geometry": {"coordinates":[-3.7660939693,40.2371444702],"type":"Point"}
}