{
  "type": "Feature",
  "properties": {
    "addr:full":"Calle de San Jose, 7 Huelva Huelva 21002",
    "addr:housenumber":"7",
    "addr:postcode":"21002",
    "addr:street":"Calle De San Jose",
    "iso:country":"ES",
    "sg:address":"Calle de San Jose, 7",
    "sg:city":"Huelva",
    "sg:orig_category":"Ropa Para Se\u00d1oras (al Por Menor)",
    "sg:phone":"+34 959 24 66 67",
    "sg:postcode":"21002",
    "sg:province":"Huelva",
    "wof:name":"Cosuna Sociedad Limitada",
    "wof:placetype":"venue"
},
  "geometry": {"coordinates":[-6.954390049,37.2591209412],"type":"Point"}
}