{
  "type": "Feature",
  "properties": {
    "addr:full":"Calle de Joaquin Rodrigo, S/n Malaga M\u00e1laga 29004",
    "addr:housenumber":"s / n",
    "addr:postcode":"29004",
    "addr:street":"Calle De Joaquin Rodrigo;Ma\u0301Laga",
    "iso:country":"ES",
    "sg:address":"Calle de Joaquin Rodrigo, S/n",
    "sg:city":"Malaga",
    "sg:orig_category":"Mercer\u00cda, Lencer\u00cda (al Por Menor)",
    "sg:phone":"+34 952 23 16 71",
    "sg:postcode":"29004",
    "sg:province":"M\u00e1laga",
    "wof:name":"Quintero Almira Ricardo",
    "wof:placetype":"venue"
},
  "geometry": {"coordinates":[-4.4488492012,36.694229126],"type":"Point"}
}