{
  "type": "Feature",
  "properties": {
    "iso:country":"ES",
    "sg:address":"Antso Abarka Kalea, 3",
    "sg:city":"Arrasate",
    "sg:orig_category":"Mercer\u00cda, Lencer\u00cda (al Por Menor)",
    "sg:phone":"+34 943 79 27 83",
    "sg:postcode":"20500",
    "sg:province":"Guip\u00f9zcoa",
    "wof:name":"Solis Jimenez Juan",
    "wof:placetype":"venue"
},
  "geometry": {"coordinates":[-2.4945991039,43.060295105],"type":"Point"}
}