{
  "type": "Feature",
  "properties": {
    "addr:full":"Avda Alemania (de), 46 Caceres C\u00e1ceres 10005",
    "addr:housenumber":"46",
    "addr:postcode":"10005",
    "addr:street":"Avda Alemania De;Ca\u0301Ceres",
    "iso:country":"ES",
    "sg:address":"Avda Alemania (de), 46",
    "sg:city":"Caceres",
    "sg:orig_category":"Art\u00cdculos De Regalo (al Por Menor)",
    "sg:phone":"+34 927 23 42 64",
    "sg:postcode":"10005",
    "sg:province":"C\u00e1ceres",
    "wof:name":"Comercial Navarra Orbaiceta",
    "wof:placetype":"venue"
},
  "geometry": {"coordinates":[-6.382999897,39.4635734558],"type":"Point"}
}