{
  "type": "Feature",
  "properties": {
    "addr:full":"Calle de Virgen De La Cabeza, 12 Dos Hermanas Sevilla 41700",
    "addr:housenumber":"12",
    "addr:postcode":"41700",
    "addr:street":"Calle De Virgen De La Cabeza",
    "iso:country":"ES",
    "sg:address":"Calle de Virgen De La Cabeza, 12",
    "sg:city":"Dos Hermanas",
    "sg:orig_category":"Artes Gr\u00c1ficas, Artes Pl\u00c1sticas (curso)",
    "sg:phone":"+34 955 66 30 65",
    "sg:postcode":"41700",
    "sg:province":"Sevilla",
    "wof:name":"Grafivalme S.l.",
    "wof:placetype":"venue"
},
  "geometry": {"coordinates":[-5.9322738647,37.2688751221],"type":"Point"}
}