{
  "type": "Feature",
  "properties": {
    "addr:full":"Calle de Luis Doreste Silva, 91 Palmas De Gran Canaria Las Palmas 35004",
    "addr:housenumber":"91",
    "addr:postcode":"35004",
    "addr:street":"Calle De Luis Doreste Silva",
    "iso:country":"ES",
    "sg:address":"Calle de Luis Doreste Silva, 91",
    "sg:city":"Palmas De Gran Canaria",
    "sg:orig_category":"Laboratorios Y Trabajos De Fotograf\u00cda, V\u00cddeo Y Cine",
    "sg:phone":"+34 928 24 07 69",
    "sg:postcode":"35004",
    "sg:province":"Las Palmas",
    "wof:name":"Menendez Garcia Fidel",
    "wof:placetype":"venue"
},
  "geometry": {"coordinates":[-15.4243240356,28.1193447113],"type":"Point"}
}