{
  "type": "Feature",
  "properties": {
    "iso:country":"ES",
    "sg:address":"Calle de Valenzuela, 20",
    "sg:city":"Campo Criptana",
    "sg:orig_category":"Empresas De Carpinter\u00cda De Madera",
    "sg:phone":"+34 926 56 03 76",
    "sg:postcode":"13610",
    "sg:province":"Ciudad Real",
    "wof:name":"Carpinteria Diaz Hellin S.l.",
    "wof:placetype":"venue"
},
  "geometry": {"coordinates":[-3.126789093,39.4034500122],"type":"Point"}
}