{
  "type": "Feature",
  "properties": {
    "addr:full":"Calle de San Blas, 1 Alcorcon Madrid 28921",
    "addr:housenumber":"1",
    "addr:postcode":"28921",
    "addr:street":"Calle De San Blas",
    "iso:country":"ES",
    "sg:address":"Calle de San Blas, 1",
    "sg:city":"Alcorcon",
    "sg:orig_category":"Estudios, Instalaci\u00d3n De Climatizaci\u00d3n",
    "sg:phone":"+34 916 44 24 80",
    "sg:postcode":"28921",
    "sg:province":"Madrid",
    "wof:name":"M.t.r.electrica S.l.",
    "wof:placetype":"venue"
},
  "geometry": {"coordinates":[-3.8247160912,40.3448562622],"type":"Point"}
}