{
  "type": "Feature",
  "properties": {
    "addr:full":"Calle de Sor Livia Alcorta, S/n Illescas Toledo 45200",
    "addr:housenumber":"s / n",
    "addr:postcode":"45200",
    "addr:street":"Calle De Sor Livia Alcorta",
    "iso:country":"ES",
    "sg:address":"Calle de Sor Livia Alcorta, S/n",
    "sg:city":"Illescas",
    "sg:orig_category":"Bisuter\u00cda, Joyer\u00cda, Relojer\u00cda (al Por Menor)",
    "sg:phone":"+34 925 54 10 04",
    "sg:postcode":"45200",
    "sg:province":"Toledo",
    "wof:name":"Perez Sanchez Joaquin",
    "wof:placetype":"venue"
},
  "geometry": {"coordinates":[-3.8460590839,40.123916626],"type":"Point"}
}