{
  "type": "Feature",
  "properties": {
    "addr:full":"Calle de Medico Rodriguez, 2 Coru\u00d1a La Coru\u00f1a 15004",
    "addr:housenumber":"2",
    "addr:postcode":"15004",
    "addr:street":"Calle De Medico Rodriguez;La Corun\u0303A",
    "iso:country":"ES",
    "sg:address":"Calle de Medico Rodriguez, 2",
    "sg:city":"Coru\u00d1a",
    "sg:orig_category":"Comit\u00c9s De Organizaci\u00d3n De Exposiciones, Ferias, Salones",
    "sg:phone":"+34 981 27 53 50",
    "sg:postcode":"15004",
    "sg:province":"La Coru\u00f1a",
    "sg:website":"www.caixagalicia.es",
    "wof:name":"Fundacion Caixa Galicia",
    "wof:placetype":"venue"
},
  "geometry": {"coordinates":[-8.4087371826,43.366317749],"type":"Point"}
}