{
  "type": "Feature",
  "properties": {
    "iso:country":"ES",
    "sg:address":"Poli Industrial Ibarria, S/n",
    "sg:city":"Alsasua",
    "sg:orig_category":"Buzones De Correos",
    "sg:phone":"+34 948 46 83 64",
    "sg:postcode":"31800",
    "sg:province":"Navarra",
    "sg:website":"www.arfe.com",
    "wof:name":"Baton Europe S.l.",
    "wof:placetype":"venue"
},
  "geometry": {"coordinates":[-2.1696588993,42.8959083557],"type":"Point"}
}