{
  "type": "Feature",
  "properties": {
    "iso:country":"ES",
    "sg:address":"Avda Andalucia, S/n",
    "sg:city":"Sevilla",
    "sg:orig_category":"Molduras, Junquillos, Listones Y Molduras Perforadas",
    "sg:phone":"+34 954 52 74 18",
    "sg:postcode":"41006",
    "sg:province":"Sevilla",
    "wof:name":"Cantinitas S.l.",
    "wof:placetype":"venue"
},
  "geometry": {"coordinates":[-5.9590339661,37.3874053955],"type":"Point"}
}