{
  "type": "Feature",
  "properties": {
    "iso:country":"ES",
    "sg:address":"Calle de Domenico Scarlatti, 9",
    "sg:city":"Madrid",
    "sg:orig_category":"M\u00c9dicos: Ginecolog\u00cda Y Obstetricia",
    "sg:phone":"+34 915 44 73 54",
    "sg:postcode":"28003",
    "sg:province":"Madrid",
    "wof:name":"Fernandez Suarez Mario",
    "wof:placetype":"venue"
},
  "geometry": {"coordinates":[-3.7166199684,40.4412918091],"type":"Point"}
}