{
  "type": "Feature",
  "properties": {
    "iso:country":"ES",
    "sg:address":"Carr Enginyers, 4",
    "sg:city":"Figueres",
    "sg:orig_category":"Tapicer\u00cdas",
    "sg:phone":"+34 972 50 24 91",
    "sg:postcode":"17600",
    "sg:province":"Girona",
    "wof:name":"Compa\u00d1ia Singer De Maquinas Para Coser S.a.",
    "wof:placetype":"venue"
},
  "geometry": {"coordinates":[2.9581100941,42.2656898499],"type":"Point"}
}