{
  "type": "Feature",
  "properties": {
    "addr:full":"Avda Europa, 59 Malaga M\u00e1laga 29003",
    "addr:housenumber":"59",
    "addr:postcode":"29003",
    "addr:street":"Avda Europa;Ma\u0301Laga",
    "iso:country":"ES",
    "sg:address":"Avda Europa, 59",
    "sg:city":"Malaga",
    "sg:orig_category":"Caf\u00c9s, Bares, Cervecer\u00cdas",
    "sg:phone":"+34 952 34 64 75",
    "sg:postcode":"29003",
    "sg:province":"M\u00e1laga",
    "wof:name":"Gomez Gomez Jose Joaquin",
    "wof:placetype":"venue"
},
  "geometry": {"coordinates":[-4.4466638565,36.702091217],"type":"Point"}
}