{
  "type": "Feature",
  "properties": {
    "addr:full":"Plaza Alta Y Baja, 42 Lucena C\u00f3rdoba 14900",
    "addr:housenumber":"42",
    "addr:postcode":"14900",
    "addr:street":"Baja",
    "iso:country":"ES",
    "sg:address":"Plaza Alta Y Baja, 42",
    "sg:city":"Lucena",
    "sg:orig_category":"Confecci\u00d3n De Trajes Para Se\u00d1oras",
    "sg:phone":"+34 957 51 12 63",
    "sg:postcode":"14900",
    "sg:province":"C\u00f3rdoba",
    "wof:name":"Botella Ortega Antonio",
    "wof:placetype":"venue"
},
  "geometry": {"coordinates":[-4.4834098816,37.4093551636],"type":"Point"}
}