{
  "type": "Feature",
  "properties": {
    "addr:full":"Carr Ample, 39 Cassa Selva Girona 17244",
    "addr:housenumber":"39",
    "addr:postcode":"17244",
    "addr:street":"Carr Ample",
    "iso:country":"ES",
    "sg:address":"Carr Ample, 39",
    "sg:city":"Cassa Selva",
    "sg:orig_category":"Aguas (distribuci\u00d3n, Servicios)",
    "sg:phone":"+34 972 46 14 78",
    "sg:postcode":"17244",
    "sg:province":"Girona",
    "wof:name":"Aqualia Gestion Integral Del Agua S.a.",
    "wof:placetype":"venue"
},
  "geometry": {"coordinates":[2.8744783401,41.8855781555],"type":"Point"}
}