{
  "type": "Feature",
  "properties": {
    "iso:country":"ES",
    "sg:address":"Calle de Canarias (de), S/n",
    "sg:city":"G\u00fcimar",
    "sg:orig_category":"Abogados",
    "sg:phone":"+34 922 51 22 09",
    "sg:postcode":"38500",
    "sg:province":"Santa Cruz De Tenerife",
    "wof:name":"Coello Batista Manuel",
    "wof:placetype":"venue"
},
  "geometry": {"coordinates":[-16.4106235504,28.3144950867],"type":"Point"}
}