{
  "type": "Feature",
  "properties": {
    "iso:country":"ES",
    "sg:address":"Av Diagonal, 58",
    "sg:city":"Barcelona",
    "sg:orig_category":"Ropa Para Se\u00d1oras (al Por Menor)",
    "sg:phone":"+34 933 08 08 28",
    "sg:postcode":"08019",
    "sg:province":"Barcelona",
    "wof:name":"Jimenez Ropero Balbina",
    "wof:placetype":"venue"
},
  "geometry": {"coordinates":[2.2119889259,41.4098548889],"type":"Point"}
}