{
  "type": "Feature",
  "properties": {
    "addr:full":"Avda Madrid, 3 Laguna Duero Valladolid 47140",
    "addr:housenumber":"3",
    "addr:postcode":"47140",
    "addr:street":"Avda Madrid",
    "iso:country":"ES",
    "sg:address":"Avda Madrid, 3",
    "sg:city":"Laguna Duero",
    "sg:orig_category":"Asilos De Ancianos. Centros Privados",
    "sg:phone":"+34 983 54 35 50",
    "sg:postcode":"47140",
    "sg:province":"Valladolid",
    "wof:name":"Residencia De Tercera Edad Los Arces S.l.",
    "wof:placetype":"venue"
},
  "geometry": {"coordinates":[-4.7193188667,41.5835494995],"type":"Point"}
}