{
  "type": "Feature",
  "properties": {
    "addr:full":"Avda Cruz De Juarez, 14 Cordoba C\u00f3rdoba 14006",
    "addr:postcode":"14006",
    "addr:street":"Avda Cruz De Juarez 14;Co\u0301Rdoba",
    "iso:country":"ES",
    "sg:address":"Avda Cruz De Juarez, 14",
    "sg:city":"Cordoba",
    "sg:orig_category":"Administradores De Bienes Y Delegados De Comunidades De Propietarios",
    "sg:phone":"+34 957 76 73 02",
    "sg:postcode":"14006",
    "sg:province":"C\u00f3rdoba",
    "wof:name":"Herreros Villalba Angel",
    "wof:placetype":"venue"
},
  "geometry": {"coordinates":[-4.78023386,37.8964958191],"type":"Point"}
}