{
  "type": "Feature",
  "properties": {
    "addr:full":"Carr Corregidor Escofet, 8 Lleida Lleida 25005",
    "addr:housenumber":"8",
    "addr:postcode":"25005",
    "addr:street":"Carr Corregidor Escofet",
    "iso:country":"ES",
    "sg:address":"Carr Corregidor Escofet, 8",
    "sg:city":"Lleida",
    "sg:orig_category":"Panader\u00cdas, Panader\u00cdas",
    "sg:phone":"+34 973 22 31 48",
    "sg:postcode":"25005",
    "sg:province":"Lleida",
    "wof:name":"Lopez Medina Juan",
    "wof:placetype":"venue"
},
  "geometry": {"coordinates":[0.6390169859,41.6227722168],"type":"Point"}
}