{
  "type": "Feature",
  "properties": {
    "iso:country":"ES",
    "sg:address":"Carr Corregidor Escofet, 37",
    "sg:city":"Lleida",
    "sg:orig_category":"Molduras, Junquillos, Listones Y Molduras Perforadas",
    "sg:phone":"+34 973 23 28 00",
    "sg:postcode":"25005",
    "sg:province":"Lleida",
    "wof:name":"Frankfurt Guillermo S.l.",
    "wof:placetype":"venue"
},
  "geometry": {"coordinates":[0.6364139915,41.6237754822],"type":"Point"}
}