{
  "type": "Feature",
  "properties": {
    "addr:full":"Ctra Sadaba-pinsoro, S/n Pinsoro Zaragoza 50694",
    "addr:housenumber":"s",
    "addr:postcode":"50694",
    "addr:street":"Ctra Sadaba-Pinsoro;/ N Pinsoro",
    "iso:country":"ES",
    "sg:address":"Ctra Sadaba-pinsoro, S/n",
    "sg:city":"Pinsoro",
    "sg:orig_category":"Cooperativas Agr\u00cdcolas",
    "sg:phone":"+34 976 67 36 51",
    "sg:postcode":"50694",
    "sg:province":"Zaragoza",
    "wof:name":"Sociedad Cooperativa Agraria San Mateo",
    "wof:placetype":"venue"
},
  "geometry": {"coordinates":[-1.3334339857,42.1949005127],"type":"Point"}
}