{
  "type": "Feature",
  "properties": {
    "addr:full":"Carrer de Barques, 8 Cambrils Tarragona 43850",
    "addr:housenumber":"8",
    "addr:postcode":"43850",
    "addr:street":"Carrer De Barques",
    "iso:country":"ES",
    "sg:address":"Carrer de Barques, 8",
    "sg:city":"Cambrils",
    "sg:orig_category":"Notarios",
    "sg:phone":"+34 977 36 45 47",
    "sg:postcode":"43850",
    "sg:province":"Tarragona",
    "wof:name":"Rodriguez Calvo Jose",
    "wof:placetype":"venue"
},
  "geometry": {"coordinates":[1.0613650084,41.0670051575],"type":"Point"}
}