{
  "type": "Feature",
  "properties": {
    "addr:full":"Cm\u00d1o Espi\u00d1eiro, 7 Vigo Pontevedra 36207",
    "addr:housenumber":"7",
    "addr:postcode":"36207",
    "addr:street":"Espin\u0303Eiro",
    "iso:country":"ES",
    "sg:address":"Cm\u00d1o Espi\u00d1eiro, 7",
    "sg:city":"Vigo",
    "sg:orig_category":"Montaje (empresas De)",
    "sg:phone":"+34 986 28 39 00",
    "sg:postcode":"36207",
    "sg:province":"Pontevedra",
    "wof:name":"Montajes Naval Gallega S.l.",
    "wof:placetype":"venue"
},
  "geometry": {"coordinates":[-8.7016239166,42.2509155273],"type":"Point"}
}