{
  "type": "Feature",
  "properties": {
    "addr:full":"Calle de Encina, S/n Quintanar Orden Toledo 45800",
    "addr:housenumber":"s / n",
    "addr:postcode":"45800",
    "addr:street":"Calle De Encina",
    "iso:country":"ES",
    "sg:address":"Calle de Encina, S/n",
    "sg:city":"Quintanar Orden",
    "sg:orig_category":"Asociaciones Y Clubs Deportivos",
    "sg:phone":"+34 925 56 50 58",
    "sg:postcode":"45800",
    "sg:province":"Toledo",
    "wof:name":"Club Deportivo Quintanar",
    "wof:placetype":"venue"
},
  "geometry": {"coordinates":[-3.0389840603,39.5861740112],"type":"Point"}
}