{
  "type": "Feature",
  "properties": {
    "addr:full":"Calle de Doctor Aznar Molina, 15 Zaragoza Zaragoza 50002",
    "addr:housenumber":"15",
    "addr:postcode":"50002",
    "addr:street":"Calle De Doctor Aznar Molina",
    "iso:country":"ES",
    "sg:address":"Calle de Doctor Aznar Molina, 15",
    "sg:city":"Zaragoza",
    "sg:orig_category":"Buzones De Correos",
    "sg:phone":"+34 976 39 20 10",
    "sg:postcode":"50002",
    "sg:province":"Zaragoza",
    "sg:website":"www.unipost.es",
    "wof:name":"Unipost S.a.",
    "wof:placetype":"venue"
},
  "geometry": {"coordinates":[-0.8697929978,41.6487007141],"type":"Point"}
}