{
  "type": "Feature",
  "properties": {
    "addr:full":"Calle de Fronton (el), 1 Mutiloabeiti Navarra 31192",
    "addr:housenumber":"1",
    "addr:postcode":"31192",
    "addr:street":"Calle De Fronton El",
    "iso:country":"ES",
    "sg:address":"Calle de Fronton (el), 1",
    "sg:city":"Mutiloabeiti",
    "sg:classifiers":[
        {
            "category":"Community Center",
            "subcategory":"Youth",
            "type":"Public Place"
        }
    ],
    "sg:phone":"+34 948 24 11 37",
    "sg:postcode":"31192",
    "sg:province":"Navarra",
    "sg:tags":[
        "juventud",
        "administraci\u00d3n",
        "la",
        "en",
        "deporte",
        "el",
        "y"
    ],
    "wof:name":"Sanzol Salinas Andres",
    "wof:placetype":"venue"
},
  "geometry": {"coordinates":[-1.6168999672,42.7888031006],"type":"Point"}
}