{
  "type": "Feature",
  "properties": {
    "iso:country":"ES",
    "sg:address":"Carrer de Espronceda, 96",
    "sg:city":"Barcelona",
    "sg:orig_category":"Agentes Generales De Seguros",
    "sg:phone":"+34 933 07 76 22",
    "sg:postcode":"08005",
    "sg:province":"Barcelona",
    "wof:name":"Martin Izquierdo Abrahan",
    "wof:placetype":"venue"
},
  "geometry": {"coordinates":[2.2048768997,41.4053649902],"type":"Point"}
}