{
  "type": "Feature",
  "properties": {
    "iso:country":"ES",
    "sg:address":"Escuelas, S/n",
    "sg:city":"Villalbilla De Burgos",
    "sg:orig_category":"Ense\u00d1anza, Formaci\u00d3n Profesional: Aprendizaje",
    "sg:phone":"+34 947 29 12 27",
    "sg:postcode":"09197",
    "sg:province":"Burgos",
    "wof:name":"Ayuntamiento De Villalbilla De Burgos",
    "wof:placetype":"venue"
},
  "geometry": {"coordinates":[-3.8220412731,42.3106498718],"type":"Point"}
}