{
  "type": "Feature",
  "properties": {
    "addr:full":"Pol Ind La Fundicion, 38 Andujar Ja\u00e9n 23740",
    "addr:postcode":"23740",
    "addr:street":"Jae\u0301N",
    "iso:country":"ES",
    "sg:address":"Pol Ind La Fundicion, 38",
    "sg:city":"Andujar",
    "sg:orig_category":"Maquinaria Para Industrias Diversas",
    "sg:phone":"+34 953 50 03 03",
    "sg:postcode":"23740",
    "sg:province":"Ja\u00e9n",
    "wof:name":"Bolsatex S.c.a.",
    "wof:placetype":"venue"
},
  "geometry": {"coordinates":[-4.057518959,38.0386962891],"type":"Point"}
}