{
  "type": "Feature",
  "properties": {
    "addr:full":"Carretera Almeria-murcia, S/n Sorbas Almer\u00eda 04270",
    "addr:housenumber":"s / n",
    "addr:postcode":"04270",
    "addr:street":"Carretera Almeria-Murcia",
    "iso:country":"ES",
    "sg:address":"Carretera Almeria-murcia, S/n",
    "sg:city":"Sorbas",
    "sg:orig_category":"Restaurantes",
    "sg:phone":"+34 950 36 41 93",
    "sg:postcode":"04270",
    "sg:province":"Almer\u00eda",
    "wof:name":"Gastronomia Virgen De Schoenstatt S.l.",
    "wof:placetype":"venue"
},
  "geometry": {"coordinates":[-2.0861330032,37.086139679],"type":"Point"}
}