{
  "type": "Feature",
  "properties": {
    "addr:full":"Plaz El Convent, 6 Alcora Castell\u00f3n 12110",
    "addr:housenumber":"6",
    "addr:postcode":"12110",
    "addr:street":"Alcora Castello\u0301N",
    "iso:country":"ES",
    "sg:address":"Plaz El Convent, 6",
    "sg:city":"Alcora",
    "sg:orig_category":"Alimentaci\u00d3n General (al Por Menor)",
    "sg:phone":"+34 964 36 02 40",
    "sg:postcode":"12110",
    "sg:province":"Castell\u00f3n",
    "wof:name":"Dura Fores Manuel",
    "wof:placetype":"venue"
},
  "geometry": {"coordinates":[-0.2178789973,40.0734786987],"type":"Point"}
}