{
  "type": "Feature",
  "properties": {
    "iso:country":"ES",
    "sg:address":"Avda Arcadio Pardi\u00d1as, 161",
    "sg:city":"Burela",
    "sg:orig_category":"M\u00c9dicos: Estomatolog\u00cda",
    "sg:phone":"+34 982 58 10 41",
    "sg:postcode":"27880",
    "sg:province":"Lugo",
    "wof:name":"Robustillo Robustillo Manuel",
    "wof:placetype":"venue"
},
  "geometry": {"coordinates":[-7.3563251495,43.6540489197],"type":"Point"}
}