{
  "type": "Feature",
  "properties": {
    "addr:full":"Carrer de Rellotge, 10 Santa Coloma De Gramenet Barcelona 08923",
    "addr:housenumber":"10",
    "addr:postcode":"08923",
    "addr:street":"Carrer De Rellotge",
    "iso:country":"ES",
    "sg:address":"Carrer de Rellotge, 10",
    "sg:city":"Santa Coloma De Gramenet",
    "sg:orig_category":"Juegos Y Juguetes (al Por Menor)",
    "sg:phone":"+34 933 91 19 99",
    "sg:postcode":"08923",
    "sg:province":"Barcelona",
    "sg:website":"www.elosito.com",
    "wof:name":"Perguets S.l.",
    "wof:placetype":"venue"
},
  "geometry": {"coordinates":[2.2194309235,41.4495658875],"type":"Point"}
}