{
  "type": "Feature",
  "properties": {
    "addr:full":"Rbla Prim, 147 Barcelona Barcelona 08020",
    "addr:housenumber":"147",
    "addr:postcode":"08020",
    "addr:street":"Rbla Prim",
    "iso:country":"ES",
    "sg:address":"Rbla Prim, 147",
    "sg:city":"Barcelona",
    "sg:orig_category":"Empresas De Carpinter\u00cda Met\u00c1lica",
    "sg:phone":"+34 932 78 17 61",
    "sg:postcode":"08020",
    "sg:province":"Barcelona",
    "wof:name":"C.metalica Alonso S.l.",
    "wof:placetype":"venue"
},
  "geometry": {"coordinates":[2.2056450844,41.4212493896],"type":"Point"}
}