{
  "type": "Feature",
  "properties": {
    "addr:full":"Calle de Alcalde Lopez Casero, 14 Madrid Madrid 28027",
    "addr:housenumber":"14",
    "addr:postcode":"madrid;28027",
    "addr:street":"Calle De Alcalde Lopez Casero",
    "iso:country":"ES",
    "sg:address":"Calle de Alcalde Lopez Casero, 14",
    "sg:city":"Madrid",
    "sg:orig_category":"Servicio De Salud",
    "sg:phone":"+34 914 03 52 86",
    "sg:postcode":"28027",
    "sg:province":"Madrid",
    "wof:name":"Benitez Cope Alfredo",
    "wof:placetype":"venue"
},
  "geometry": {"coordinates":[-3.6556789875,40.4335136414],"type":"Point"}
}