{
  "type": "Feature",
  "properties": {
    "iso:country":"ES",
    "sg:address":"Los Huertos, 2",
    "sg:city":"Huetor-santillan",
    "sg:orig_category":"Cerrajer\u00cda, Ferrallista",
    "sg:phone":"+34 958 54 51 38",
    "sg:postcode":"18183",
    "sg:province":"Granada",
    "wof:name":"Ortega Guijarro Juan Felipe",
    "wof:placetype":"venue"
},
  "geometry": {"coordinates":[-3.5168130398,37.2160644531],"type":"Point"}
}