{
  "type": "Feature",
  "properties": {
    "addr:full":"Calle de Fuensanta, 42 Aguilas Murcia 30880",
    "addr:housenumber":"42",
    "addr:postcode":"30880",
    "addr:street":"Calle De Fuensanta",
    "iso:country":"ES",
    "sg:address":"Calle de Fuensanta, 42",
    "sg:city":"Aguilas",
    "sg:orig_category":"M\u00c9dicos: Reumatolog\u00cda",
    "sg:phone":"+34 968 41 05 37",
    "sg:postcode":"30880",
    "sg:province":"Murcia",
    "wof:name":"Ramirez Chazarra Antonio",
    "wof:placetype":"venue"
},
  "geometry": {"coordinates":[-1.5886080265,37.4060211182],"type":"Point"}
}