{
  "type": "Feature",
  "properties": {
    "iso:country":"ES",
    "sg:address":"Calle de Jerez, 10",
    "sg:city":"Linea De La Concepcion",
    "sg:orig_category":"Electricidad, Electr\u00d3nica: Suministros (al Por Menor)",
    "sg:phone":"+34 956 17 03 33",
    "sg:postcode":"11300",
    "sg:province":"C\u00e1diz",
    "wof:name":"Rodriguez Perez Angel",
    "wof:placetype":"venue"
},
  "geometry": {"coordinates":[-5.3547391891,36.1649551392],"type":"Point"}
}