{
  "type": "Feature",
  "properties": {
    "iso:country":"ES",
    "sg:address":"Ctra Aldeanueva, S/n",
    "sg:city":"Hervas",
    "sg:orig_category":"Ebanister\u00cda",
    "sg:phone":"+34 927 48 12 23",
    "sg:postcode":"10700",
    "sg:province":"C\u00e1ceres",
    "wof:name":"Hernandez Garcia Luis Miguel",
    "wof:placetype":"venue"
},
  "geometry": {"coordinates":[-5.8724212646,40.270565033],"type":"Point"}
}