{
  "type": "Feature",
  "properties": {
    "addr:full":"Calle de Extremadura, S/n Navalmoral Mata C\u00e1ceres 10300",
    "addr:postcode":"10300",
    "addr:street":"Calle De Extremadura S / N Navalmoral Mata Ca\u0301Ceres",
    "iso:country":"ES",
    "sg:address":"Calle de Extremadura, S/n",
    "sg:city":"Navalmoral Mata",
    "sg:orig_category":"Cajas De Ahorro",
    "sg:phone":"+34 927 53 54 78",
    "sg:postcode":"10300",
    "sg:province":"C\u00e1ceres",
    "wof:name":"Caja De Badajoz",
    "wof:placetype":"venue"
},
  "geometry": {"coordinates":[-5.5433068275,39.8908996582],"type":"Point"}
}