{
  "type": "Feature",
  "properties": {
    "addr:full":"Avda Andalucia (de), 7 Vejer De La Frontera C\u00e1diz 11150",
    "addr:housenumber":"7",
    "addr:postcode":"11150",
    "addr:street":"Avda Andalucia De",
    "iso:country":"ES",
    "sg:address":"Avda Andalucia (de), 7",
    "sg:city":"Vejer De La Frontera",
    "sg:orig_category":"Cajas De Ahorro",
    "sg:phone":"+34 956 45 01 33",
    "sg:postcode":"11150",
    "sg:province":"C\u00e1diz",
    "wof:name":"Unicaja",
    "wof:placetype":"venue"
},
  "geometry": {"coordinates":[-5.9687609673,36.2527809143],"type":"Point"}
}