{
  "type": "Feature",
  "properties": {
    "addr:full":"Calle de Jeronimo Falcon, 15 Palmas De Gran Canaria Las Palmas 35003",
    "addr:housenumber":"15",
    "addr:postcode":"35003",
    "addr:street":"Calle De Jeronimo Falcon",
    "iso:country":"ES",
    "sg:address":"Calle de Jeronimo Falcon, 15",
    "sg:city":"Palmas De Gran Canaria",
    "sg:orig_category":"Bricolaje, Herramientas (al Por Menor)",
    "sg:phone":"+34 928 23 18 86",
    "sg:postcode":"35003",
    "sg:province":"Las Palmas",
    "wof:name":"Juan Fricke Octavio",
    "wof:placetype":"venue"
},
  "geometry": {"coordinates":[-15.4231987,28.1134490967],"type":"Point"}
}