{
  "type": "Feature",
  "properties": {
    "addr:full":"Calle de Tejera (la), 38 Villaobispo De Las Regueras Le\u00f3n 24007",
    "addr:housenumber":"38",
    "addr:postcode":"24007",
    "addr:street":"Calle De Tejera La;Leo\u0301N",
    "iso:country":"ES",
    "sg:address":"Calle de Tejera (la), 38",
    "sg:city":"Villaobispo De Las Regueras",
    "sg:orig_category":"Institutos De Belleza",
    "sg:phone":"+34 987 30 79 17",
    "sg:postcode":"24007",
    "sg:province":"Le\u00f3n",
    "wof:name":"Varga Villafane Esther De La",
    "wof:placetype":"venue"
},
  "geometry": {"coordinates":[-5.54585886,42.6150283813],"type":"Point"}
}