{
  "type": "Feature",
  "properties": {
    "iso:country":"ES",
    "sg:address":"Calle de Historiador Diago, 14",
    "sg:city":"Valencia",
    "sg:orig_category":"Sociedades, Compa\u00d1\u00cdas Aseguradoras",
    "sg:phone":"+34 963 84 01 72",
    "sg:postcode":"46007",
    "sg:province":"Valencia",
    "wof:name":"Monferre Correduria De Seguros S.l.",
    "wof:placetype":"venue"
},
  "geometry": {"coordinates":[-0.3846890032,39.4672584534],"type":"Point"}
}