{
  "type": "Feature",
  "properties": {
    "iso:country":"ES",
    "sg:address":"C/ Major, 18",
    "sg:city":"Tarrega",
    "sg:orig_category":"Arquitectos",
    "sg:phone":"+34 973 31 47 28",
    "sg:postcode":"25300",
    "sg:province":"Lleida",
    "wof:name":"Espai D'arquitectura S.c.p.",
    "wof:placetype":"venue"
},
  "geometry": {"coordinates":[1.1390689611,41.6456642151],"type":"Point"}
}