{
  "type": "Feature",
  "properties": {
    "addr:full":"Rua Belvis De Paleo, 2 Carral La Coru\u00f1a 15175",
    "addr:housenumber":"2",
    "addr:postcode":"15175",
    "addr:street":"Rua Belvis De Paleo;La Corun\u0303A",
    "iso:country":"ES",
    "sg:address":"Rua Belvis De Paleo, 2",
    "sg:city":"Carral",
    "sg:orig_category":"Supermercados Y Hipermercados",
    "sg:phone":"+34 981 67 16 04",
    "sg:postcode":"15175",
    "sg:province":"La Coru\u00f1a",
    "wof:name":"Berigle S.l.",
    "wof:placetype":"venue"
},
  "geometry": {"coordinates":[-8.3558893204,43.2278442383],"type":"Point"}
}