{
  "type": "Feature",
  "properties": {
    "addr:full":"Plaz Martires, 7 Malaga M\u00e1laga 29008",
    "addr:housenumber":"7",
    "addr:postcode":"29008",
    "addr:street":"Plaz Martires;Ma\u0301Laga",
    "iso:country":"ES",
    "sg:address":"Plaz Martires, 7",
    "sg:city":"Malaga",
    "sg:orig_category":"Artes Gr\u00c1ficas, Artes Pl\u00c1sticas (curso)",
    "sg:phone":"+34 952 21 48 14",
    "sg:postcode":"29008",
    "sg:province":"M\u00e1laga",
    "wof:name":"Anarol S.l.",
    "wof:placetype":"venue"
},
  "geometry": {"coordinates":[-4.4227104187,36.7235832214],"type":"Point"}
}