{
  "type": "Feature",
  "properties": {
    "iso:country":"ES",
    "sg:address":"Calle de Almirante Arizmendi, 9",
    "sg:city":"Irun",
    "sg:orig_category":"Zapatos (al Por Menor)",
    "sg:phone":"+34 943 63 19 52",
    "sg:postcode":"20302",
    "sg:province":"Guip\u00f9zcoa",
    "wof:name":"Ambielle S. L.",
    "wof:placetype":"venue"
},
  "geometry": {"coordinates":[-1.7913935184,43.3403816223],"type":"Point"}
}