{
  "type": "Feature",
  "properties": {
    "iso:country":"ES",
    "sg:address":"Hoya San Gines, S/n",
    "sg:city":"Albacete",
    "sg:orig_category":"Asociaciones Humanitarias, De Cooperaci\u00d3n, De Acci\u00d3n Social",
    "sg:phone":"+34 967 50 76 02",
    "sg:postcode":"02006",
    "sg:province":"Albacete",
    "wof:name":"Asprona",
    "wof:placetype":"venue"
},
  "geometry": {"coordinates":[-1.8612508774,38.9784660339],"type":"Point"}
}