{
  "type": "Feature",
  "properties": {
    "addr:full":"Calle de Sajonia, 7 Madrid Madrid 28022",
    "addr:housenumber":"7",
    "addr:postcode":"madrid;28022",
    "addr:street":"Calle De Sajonia",
    "iso:country":"ES",
    "sg:address":"Calle de Sajonia, 7",
    "sg:city":"Madrid",
    "sg:orig_category":"Peluquer\u00cdas, Peluquer\u00cda Mixta",
    "sg:phone":"+34 913 13 41 57",
    "sg:postcode":"28022",
    "sg:province":"Madrid",
    "wof:name":"Prada Muelas Raquel",
    "wof:placetype":"venue"
},
  "geometry": {"coordinates":[-3.6064310074,40.421836853],"type":"Point"}
}