{
  "type": "Feature",
  "properties": {
    "iso:country":"ES",
    "sg:address":"Av Cortes Valencianes, 43",
    "sg:city":"Elche",
    "sg:orig_category":"Promotores Constructores",
    "sg:phone":"+34 966 66 10 92",
    "sg:postcode":"03205",
    "sg:province":"Alicante",
    "wof:name":"Promociones Pevisel S.l.",
    "wof:placetype":"venue"
},
  "geometry": {"coordinates":[-0.7171589732,38.2725486755],"type":"Point"}
}