{
  "type": "Feature",
  "properties": {
    "addr:full":"Ctra Madrid N-iv (extrarradio), Km. 0392,3 Alcolea C\u00f3rdoba 14610",
    "addr:postcode":"14610",
    "addr:street":"Ctra Madrid N-Iv Extrarradio Km. 0392,3",
    "iso:country":"ES",
    "sg:address":"Ctra Madrid N-iv (extrarradio), Km. 0392,3",
    "sg:city":"Alcolea",
    "sg:orig_category":"Alquiler De Camiones Y Veh\u00cdculos Industriales",
    "sg:phone":"+34 957 32 07 30",
    "sg:postcode":"14610",
    "sg:province":"C\u00f3rdoba",
    "wof:name":"Transgaravi S.l.",
    "wof:placetype":"venue"
},
  "geometry": {"coordinates":[-4.6719388962,37.9328689575],"type":"Point"}
}