{
  "type": "Feature",
  "properties": {
    "iso:country":"ES",
    "sg:address":"Av Francesc Macia, 23",
    "sg:city":"Santa Coloma De Gramenet",
    "sg:orig_category":"Molduras, Junquillos, Listones Y Molduras Perforadas",
    "sg:phone":"+34 934 66 49 72",
    "sg:postcode":"08921",
    "sg:province":"Barcelona",
    "sg:website":"www.fmacia.com",
    "wof:name":"Ferreteria Macia S.l.",
    "wof:placetype":"venue"
},
  "geometry": {"coordinates":[2.2055199146,41.4519729614],"type":"Point"}
}