{
  "type": "Feature",
  "properties": {
    "iso:country":"ES",
    "sg:address":"Carrer de Narcis Monturiol (de), 16",
    "sg:city":"Vilassar De Mar",
    "sg:orig_category":"Perfumer\u00cda (al Por Menor)",
    "sg:phone":"+34 937 50 21 96",
    "sg:postcode":"08340",
    "sg:province":"Barcelona",
    "wof:name":"Ronquillo Sede\u00f1o Ana",
    "wof:placetype":"venue"
},
  "geometry": {"coordinates":[2.3889799118,41.5054702759],"type":"Point"}
}