{
  "type": "Feature",
  "properties": {
    "addr:full":"Pg Winthuysen, 4 Banyoles Girona 17820",
    "addr:housenumber":"4",
    "addr:postcode":"17820",
    "addr:street":"Pg Winthuysen",
    "iso:country":"ES",
    "sg:address":"Pg Winthuysen, 4",
    "sg:city":"Banyoles",
    "sg:orig_category":"Abogados",
    "sg:phone":"+34 972 58 30 70",
    "sg:postcode":"17820",
    "sg:province":"Girona",
    "wof:name":"Multiassessors S.l.",
    "wof:placetype":"venue"
},
  "geometry": {"coordinates":[2.7649800777,42.1169548035],"type":"Point"}
}