{
  "type": "Feature",
  "properties": {
    "iso:country":"ES",
    "sg:address":"Calle de Sol, 16",
    "sg:city":"Puebla De Pedraza",
    "sg:orig_category":"Cr\u00cda De Cerdos",
    "sg:phone":"+34 921 12 15 93",
    "sg:postcode":"40184",
    "sg:province":"Segovia",
    "wof:name":"Agroporc Sat 9847",
    "wof:placetype":"venue"
},
  "geometry": {"coordinates":[-3.9127905369,41.2037811279],"type":"Point"}
}