{
  "type": "Feature",
  "properties": {
    "iso:country":"ES",
    "sg:address":"C/ Ruiz I Pablo, 15",
    "sg:city":"Alaior",
    "sg:orig_category":"Abogados",
    "sg:phone":"+34 971 37 80 95",
    "sg:postcode":"07730",
    "sg:province":"Islas Baleares",
    "wof:name":"Fortuny Esbert Frederic",
    "wof:placetype":"venue"
},
  "geometry": {"coordinates":[4.1378879547,39.9317207336],"type":"Point"}
}