{
  "type": "Feature",
  "properties": {
    "addr:full":"Carrer de Rector Ubach, 19 Barcelona Barcelona 08021",
    "addr:housenumber":"19",
    "addr:postcode":"08021",
    "addr:street":"Carrer De Rector Ubach",
    "iso:country":"ES",
    "sg:address":"Carrer de Rector Ubach, 19",
    "sg:city":"Barcelona",
    "sg:orig_category":"\u00d3ptica: Instrumentos (fabricaci\u00d3n)",
    "sg:phone":"+34 932 09 25 19",
    "sg:postcode":"08021",
    "sg:province":"Barcelona",
    "wof:name":"Dolcet Cort Maria Luisa",
    "wof:placetype":"venue"
},
  "geometry": {"coordinates":[2.1442201138,41.3984260559],"type":"Point"}
}