{
  "type": "Feature",
  "properties": {
    "iso:country":"ES",
    "sg:address":"Avda Victor Gallego, 15",
    "sg:city":"Zamora",
    "sg:orig_category":"Supermercados Y Hipermercados",
    "sg:phone":"+34 980 51 54 11",
    "sg:postcode":"49009",
    "sg:province":"Zamora",
    "wof:name":"Supermercados Champion S.a.",
    "wof:placetype":"venue"
},
  "geometry": {"coordinates":[-5.7428150177,41.5095405579],"type":"Point"}
}