{
  "type": "Feature",
  "properties": {
    "iso:country":"ES",
    "sg:address":"Carrer de Valles, 43",
    "sg:city":"Mataro",
    "sg:orig_category":"Empresarios",
    "sg:phone":"+34 937 98 28 63",
    "sg:postcode":"08303",
    "sg:province":"Barcelona",
    "wof:name":"Guillen Damaso Antonio",
    "wof:placetype":"venue"
},
  "geometry": {"coordinates":[2.423183918,41.5424156189],"type":"Point"}
}