{
  "type": "Feature",
  "properties": {
    "iso:country":"ES",
    "sg:address":"Calle de Almike, S/n",
    "sg:city":"Bermeo",
    "sg:orig_category":"Aguas (distribuci\u00d3n, Servicios)",
    "sg:phone":"+34 946 18 64 01",
    "sg:postcode":"48370",
    "sg:province":"Vizcaya",
    "wof:name":"Aguas Del Norte S. A.",
    "wof:placetype":"venue"
},
  "geometry": {"coordinates":[-2.725748539,43.41822052],"type":"Point"}
}