{
  "type": "Feature",
  "properties": {
    "addr:full":"Calle de Atocha, 44 Madrid Madrid 28012",
    "addr:housenumber":"44",
    "addr:postcode":"madrid;28012",
    "addr:street":"Calle De Atocha",
    "iso:country":"ES",
    "sg:address":"Calle de Atocha, 44",
    "sg:city":"Madrid",
    "sg:orig_category":"Librer\u00cdas",
    "sg:phone":"+34 914 29 37 49",
    "sg:postcode":"28012",
    "sg:province":"Madrid",
    "wof:name":"Heredero Sarrion Rosario",
    "wof:placetype":"venue"
},
  "geometry": {"coordinates":[-3.6998860836,40.4127464294],"type":"Point"}
}