{
  "type": "Feature",
  "properties": {
    "addr:full":"Calle de Reina Aixa, 1 Caravaca Cruz Murcia 30400",
    "addr:housenumber":"1",
    "addr:postcode":"30400",
    "addr:street":"Calle De Reina Aixa",
    "iso:country":"ES",
    "sg:address":"Calle de Reina Aixa, 1",
    "sg:city":"Caravaca Cruz",
    "sg:orig_category":"Alquiler De Apartamentos",
    "sg:phone":"+34 968 70 55 94",
    "sg:postcode":"30400",
    "sg:province":"Murcia",
    "wof:name":"Apartamentos Aixa S.l.",
    "wof:placetype":"venue"
},
  "geometry": {"coordinates":[-1.8589887619,38.10414505],"type":"Point"}
}