{
  "type": "Feature",
  "properties": {
    "addr:full":"Avda Reina Victoria Eugenia, 7 Cartagena Murcia 30204",
    "addr:housenumber":"7",
    "addr:postcode":"30204",
    "addr:street":"Avda Reina Victoria Eugenia",
    "iso:country":"ES",
    "sg:address":"Avda Reina Victoria Eugenia, 7",
    "sg:city":"Cartagena",
    "sg:orig_category":"Ingeniero",
    "sg:phone":"+34 968 50 41 47",
    "sg:postcode":"30204",
    "sg:province":"Murcia",
    "wof:name":"Villar Conesa Vicente",
    "wof:placetype":"venue"
},
  "geometry": {"coordinates":[-0.9908480048,37.6096725464],"type":"Point"}
}