{
  "type": "Feature",
  "properties": {
    "addr:full":"Avda Regimiento De Galicia, S/n Jaca Huesca 22700",
    "addr:housenumber":"s / n",
    "addr:postcode":"22700",
    "addr:street":"Avda Regimiento De Galicia",
    "iso:country":"ES",
    "sg:address":"Avda Regimiento De Galicia, S/n",
    "sg:city":"Jaca",
    "sg:orig_category":"M\u00c9dicos: An\u00c1lisis Cl\u00cdnicos",
    "sg:phone":"+34 974 36 23 71",
    "sg:postcode":"22700",
    "sg:province":"Huesca",
    "wof:name":"Lasp Laboratorios S.c.p",
    "wof:placetype":"venue"
},
  "geometry": {"coordinates":[-0.5528489947,42.5682067871],"type":"Point"}
}