{
  "type": "Feature",
  "properties": {
    "addr:full":"Calle de Luis De Morales, 1 Sevilla Sevilla 41005",
    "addr:housenumber":"1",
    "addr:postcode":"41005",
    "addr:street":"Calle De Luis De Morales",
    "iso:country":"ES",
    "sg:address":"Calle de Luis De Morales, 1",
    "sg:city":"Sevilla",
    "sg:orig_category":"Psicoterapeutas",
    "sg:phone":"+34 954 57 23 21",
    "sg:postcode":"41005",
    "sg:province":"Sevilla",
    "wof:name":"Centro Andaluz De Psicologia",
    "wof:placetype":"venue"
},
  "geometry": {"coordinates":[-5.9724378586,37.3856544495],"type":"Point"}
}