{
  "type": "Feature",
  "properties": {
    "iso:country":"ES",
    "sg:address":"Rond Sant Pere, 38",
    "sg:city":"Barcelona",
    "sg:orig_category":"Confecci\u00d3n De Trajes Para Se\u00d1oras",
    "sg:phone":"+34 932 68 26 66",
    "sg:postcode":"08010",
    "sg:province":"Barcelona",
    "sg:website":"www.albamodajoven.com",
    "wof:name":"Alba Moda Joven S.a.",
    "wof:placetype":"venue"
},
  "geometry": {"coordinates":[2.1752560139,41.3898925781],"type":"Point"}
}