{
  "type": "Feature",
  "properties": {
    "iso:country":"ES",
    "sg:address":"Avda Sudiera, 28",
    "sg:city":"Ainsa",
    "sg:orig_category":"Imprenta",
    "sg:phone":"+34 974 51 00 00",
    "sg:postcode":"22330",
    "sg:province":"Huesca",
    "wof:name":"Imprenta M.prats S.l.",
    "wof:placetype":"venue"
},
  "geometry": {"coordinates":[0.1396619976,42.4145011902],"type":"Point"}
}