{
  "type": "Feature",
  "properties": {
    "iso:country":"ES",
    "sg:address":"Calle de Feria, 118",
    "sg:city":"Sevilla",
    "sg:orig_category":"Institutos De Belleza",
    "sg:phone":"+34 954 37 95 56",
    "sg:postcode":"41002",
    "sg:province":"Sevilla",
    "wof:name":"Lara Sanchez Joaquin",
    "wof:placetype":"venue"
},
  "geometry": {"coordinates":[-5.9916667938,37.4004020691],"type":"Point"}
}