{
  "type": "Feature",
  "properties": {
    "iso:country":"ES",
    "sg:address":"Calle de Oviedo, S/n",
    "sg:city":"Linea De La Concepcion",
    "sg:orig_category":"Electricidad: Equipos Industriales, Componentes (fabricaci\u00d3n)",
    "sg:phone":"+34 956 17 17 02",
    "sg:postcode":"11300",
    "sg:province":"C\u00e1diz",
    "wof:name":"Lopez Garcia Angel",
    "wof:placetype":"venue"
},
  "geometry": {"coordinates":[-5.3481388092,36.1651268005],"type":"Point"}
}