{
  "type": "Feature",
  "properties": {
    "addr:full":"Carrer de Major (sant Celoni), 121 S. Celoni Barcelona 08470",
    "addr:housenumber":"121",
    "addr:postcode":"08470",
    "addr:street":"Carrer De Major Sant Celoni;S. Celoni Barcelona",
    "iso:country":"ES",
    "sg:address":"Carrer de Major (sant Celoni), 121",
    "sg:city":"S. Celoni",
    "sg:orig_category":"Talleres: Ropa A Medida",
    "sg:phone":"+34 938 67 02 72",
    "sg:postcode":"08470",
    "sg:province":"Barcelona",
    "wof:name":"Casadevall Leonard Marti",
    "wof:placetype":"venue"
},
  "geometry": {"coordinates":[2.4914240837,41.6899490356],"type":"Point"}
}