{
  "type": "Feature",
  "properties": {
    "iso:country":"ES",
    "sg:address":"Ctra Ajalvir, Km. 0002,2",
    "sg:city":"Alcala Henares",
    "sg:orig_category":"Imprenta",
    "sg:phone":"+34 918 79 61 63",
    "sg:postcode":"28806",
    "sg:province":"Madrid",
    "wof:name":"Indeplas Sistemas S.l.",
    "wof:placetype":"venue"
},
  "geometry": {"coordinates":[-3.4114038944,40.4938011169],"type":"Point"}
}