{
  "type": "Feature",
  "properties": {
    "iso:country":"ES",
    "sg:address":"Calle de Almenara, 18",
    "sg:city":"Vall D'uixo",
    "sg:orig_category":"Perfumer\u00cda (al Por Menor)",
    "sg:phone":"+34 964 69 19 29",
    "sg:postcode":"12600",
    "sg:province":"Castell\u00f3n",
    "wof:name":"Aura Spa C.b.",
    "wof:placetype":"venue"
},
  "geometry": {"coordinates":[-0.0350899994,39.9893875122],"type":"Point"}
}