{
  "type": "Feature",
  "properties": {
    "iso:country":"ES",
    "sg:address":"Zerradi Poligonoa, S/n",
    "sg:city":"Ugaldetxo",
    "sg:orig_category":"Fabricaci\u00d3n Y Comercio De M\u00c1quinas",
    "sg:phone":"+34 943 49 06 76",
    "sg:postcode":"20180",
    "sg:province":"Guip\u00f9zcoa",
    "sg:website":"www.bonak.com",
    "wof:name":"Maquinaria Bonak S. A.",
    "wof:placetype":"venue"
},
  "geometry": {"coordinates":[-1.8629590273,43.2992401123],"type":"Point"}
}