{
  "type": "Feature",
  "properties": {
    "iso:country":"ES",
    "sg:address":"Calle de Joaquin Costa, 14",
    "sg:city":"Graus",
    "sg:orig_category":"Mec\u00c1nico Del Autom\u00d3vil",
    "sg:phone":"+34 974 54 08 84",
    "sg:postcode":"22430",
    "sg:province":"Huesca",
    "wof:name":"Sallan Sopena Juan Antonio",
    "wof:placetype":"venue"
},
  "geometry": {"coordinates":[0.3356269896,42.1822891235],"type":"Point"}
}