{
  "type": "Feature",
  "properties": {
    "iso:country":"ES",
    "sg:address":"Calle de Carretera De Huesa, 4",
    "sg:city":"Quesada",
    "sg:orig_category":"Deportes Y Programas De Aventura",
    "sg:phone":"+34 953 71 42 18",
    "sg:postcode":"23480",
    "sg:province":"Ja\u00e9n",
    "wof:name":"Aventura Sport Xauen S.l.",
    "wof:placetype":"venue"
},
  "geometry": {"coordinates":[-3.0733759403,37.84324646],"type":"Point"}
}