{
  "type": "Feature",
  "properties": {
    "addr:full":"Avda Rio Azumara (del), 28 Mosteiro Lugo 27270",
    "addr:housenumber":"28",
    "addr:postcode":"27270",
    "addr:street":"Avda Rio Azumara Del",
    "iso:country":"ES",
    "sg:address":"Avda Rio Azumara (del), 28",
    "sg:city":"Mosteiro",
    "sg:orig_category":"Centros De Educaci\u00d3n Especial",
    "sg:phone":"+34 982 34 50 63",
    "sg:postcode":"27270",
    "sg:province":"Lugo",
    "wof:name":"Colegio De Educacion Infantil Y Primaria Rosalia De Castro",
    "wof:placetype":"venue"
},
  "geometry": {"coordinates":[-7.3522891998,43.1285438538],"type":"Point"}
}