{
  "type": "Feature",
  "properties": {
    "iso:country":"ES",
    "sg:address":"Calle de Juan De Vergara, 1",
    "sg:city":"Alcala Henares",
    "sg:orig_category":"Molduras, Junquillos, Listones Y Molduras Perforadas",
    "sg:phone":"+34 918 80 36 80",
    "sg:postcode":"28802",
    "sg:province":"Madrid",
    "wof:name":"Mochales Valdeolivas Petra",
    "wof:placetype":"venue"
},
  "geometry": {"coordinates":[-3.3740375042,40.4796981812],"type":"Point"}
}