{
  "type": "Feature",
  "properties": {
    "iso:country":"ES",
    "sg:address":"Avda Alfonso Pe\u00d1a, 7",
    "sg:city":"Zamora",
    "sg:orig_category":"Fisioterapia",
    "sg:phone":"+34 980 51 74 63",
    "sg:postcode":"49010",
    "sg:province":"Zamora",
    "wof:name":"Martin Bartolome Pedro",
    "wof:placetype":"venue"
},
  "geometry": {"coordinates":[-5.739798069,41.5138893127],"type":"Point"}
}