{
  "type": "Feature",
  "properties": {
    "addr:full":"Calle de Toledo, 2 Burguillos Toledo Toledo 45112",
    "addr:housenumber":"2",
    "addr:postcode":"45112",
    "addr:street":"Calle De Toledo",
    "iso:country":"ES",
    "sg:address":"Calle de Toledo, 2",
    "sg:city":"Burguillos Toledo",
    "sg:orig_category":"Tiendas De Grano, Frutas Y Legumbres Secas (al Por Menor)",
    "sg:phone":"+34 925 39 34 19",
    "sg:postcode":"45112",
    "sg:province":"Toledo",
    "wof:name":"Esteban Diezma Fatima",
    "wof:placetype":"venue"
},
  "geometry": {"coordinates":[-3.9930489063,39.7970237732],"type":"Point"}
}