{
  "type": "Feature",
  "properties": {
    "iso:country":"ES",
    "sg:address":"Calle de San Isidro, 9",
    "sg:city":"Gabia Grande",
    "sg:orig_category":"Panader\u00cdas, Panader\u00cdas",
    "sg:phone":"+34 958 58 45 72",
    "sg:postcode":"18110",
    "sg:province":"Granada",
    "wof:name":"Sanchez Mesa Manuel",
    "wof:placetype":"venue"
},
  "geometry": {"coordinates":[-3.6684520245,37.1321678162],"type":"Point"}
}