{
  "type": "Feature",
  "properties": {
    "addr:full":"San Miguel, S/n San Miguel De Ucio Asturias 33569",
    "addr:housenumber":"s / n",
    "addr:postcode":"33569",
    "addr:street":"San Miguel;Asturias",
    "iso:country":"ES",
    "sg:address":"San Miguel, S/n",
    "sg:city":"San Miguel De Ucio",
    "sg:orig_category":"Cerrajer\u00cda, Ferrallista",
    "sg:phone":"+34 985 86 14 49",
    "sg:postcode":"33569",
    "sg:province":"Asturias",
    "wof:name":"Compa\u00f1ia Metalurgica Del Cantabrico S.l.",
    "wof:placetype":"venue"
},
  "geometry": {"coordinates":[-5.073513031,43.4270553589],"type":"Point"}
}