{
  "type": "Feature",
  "properties": {
    "addr:full":"Pgn Cuberg, Km. 0001,0 Cuenca Cuenca 16004",
    "addr:postcode":"16004",
    "addr:street":"Cuberg Km. 0001,0",
    "iso:country":"ES",
    "sg:address":"Pgn Cuberg, Km. 0001,0",
    "sg:city":"Cuenca",
    "sg:orig_category":"Venta, Colocaci\u00d3n, Reparaci\u00d3n De Parabrisas, Techos Descapotables",
    "sg:phone":"+34 969 23 62 71",
    "sg:postcode":"16004",
    "sg:province":"Cuenca",
    "wof:name":"Auto Cristal Norte S.l.",
    "wof:placetype":"venue"
},
  "geometry": {"coordinates":[-1.9685826302,40.0261421204],"type":"Point"}
}