{
  "type": "Feature",
  "properties": {
    "iso:country":"ES",
    "sg:address":"Ctra Valencia, Km. 0254,0",
    "sg:city":"Calatayud",
    "sg:orig_category":"Venta, Alquiler De Grupos Electr\u00d3genos",
    "sg:phone":"+34 976 88 42 64",
    "sg:postcode":"50300",
    "sg:province":"Zaragoza",
    "wof:name":"Jose Gracia S.l.",
    "wof:placetype":"venue"
},
  "geometry": {"coordinates":[-1.6414079666,41.3430099487],"type":"Point"}
}