{
  "type": "Feature",
  "properties": {
    "addr:full":"Praz Maior, 10 Viana Do Bolo Ourense 32550",
    "addr:housenumber":"10",
    "addr:postcode":"32550",
    "addr:street":"Praz Maior",
    "iso:country":"ES",
    "sg:address":"Praz Maior, 10",
    "sg:city":"Viana Do Bolo",
    "sg:orig_category":"Molduras, Junquillos, Listones Y Molduras Perforadas",
    "sg:phone":"+34 988 34 04 58",
    "sg:postcode":"32550",
    "sg:province":"Ourense",
    "wof:name":"Tadin Mendez Jose",
    "wof:placetype":"venue"
},
  "geometry": {"coordinates":[-7.1098628044,42.1833190918],"type":"Point"}
}