{
  "type": "Feature",
  "properties": {
    "addr:full":"Calle de Huertas De La Villa, 15 Bilbao Vizcaya 48007",
    "addr:housenumber":"15",
    "addr:postcode":"48007",
    "addr:street":"Calle De Huertas De La Villa",
    "iso:country":"ES",
    "sg:address":"Calle de Huertas De La Villa, 15",
    "sg:city":"Bilbao",
    "sg:orig_category":"Electromec\u00c1nica",
    "sg:phone":"+34 944 46 73 47",
    "sg:postcode":"48007",
    "sg:province":"Vizcaya",
    "wof:name":"Fercu I.m.guidosimplex S.l.",
    "wof:placetype":"venue"
},
  "geometry": {"coordinates":[-2.927022934,43.267375946],"type":"Point"}
}