{
  "type": "Feature",
  "properties": {
    "iso:country":"ES",
    "sg:address":"Calle de San Antonio, 20",
    "sg:city":"Gijon",
    "sg:orig_category":"M\u00c9dicos: Estomatolog\u00cda",
    "sg:phone":"+34 985 35 14 75",
    "sg:postcode":"33201",
    "sg:province":"Asturias",
    "wof:name":"Menendez Palacio Guillermo",
    "wof:placetype":"venue"
},
  "geometry": {"coordinates":[-5.6622390747,43.5438613892],"type":"Point"}
}