{
  "type": "Feature",
  "properties": {
    "iso:country":"ES",
    "sg:address":"Carrer de Joan Fuster, 9",
    "sg:city":"Ibi",
    "sg:orig_category":"Ense\u00d1anza Variada",
    "sg:phone":"+34 966 55 14 12",
    "sg:postcode":"03440",
    "sg:province":"Alicante",
    "wof:name":"Casado Ramos Maria De La Cabeza",
    "wof:placetype":"venue"
},
  "geometry": {"coordinates":[-0.5721780062,38.6229820251],"type":"Point"}
}