{
  "type": "Feature",
  "properties": {
    "iso:country":"ES",
    "sg:address":"Bda Ntra Sra Carmen, S/n",
    "sg:city":"Cazalla Sierra",
    "sg:orig_category":"Servicios Y Funcionarios De Polic\u00cda",
    "sg:phone":"+34 954 88 40 65",
    "sg:postcode":"41370",
    "sg:province":"Sevilla",
    "wof:name":"Direccion General De La Guardia Civil",
    "wof:placetype":"venue"
},
  "geometry": {"coordinates":[-5.7596888542,37.9360046387],"type":"Point"}
}