{
  "type": "Feature",
  "properties": {
    "iso:country":"ES",
    "sg:address":"Maalako Errabala, 8",
    "sg:city":"Arrasate",
    "sg:orig_category":"Ingeniero",
    "sg:phone":"+34 943 71 27 81",
    "sg:postcode":"20500",
    "sg:province":"Guip\u00f9zcoa",
    "wof:name":"Router Comunicaciones S.l.",
    "wof:placetype":"venue"
},
  "geometry": {"coordinates":[-2.4895889759,43.0670852661],"type":"Point"}
}