{
  "type": "Feature",
  "properties": {
    "iso:country":"ES",
    "sg:address":"Avda Julian Saez, 52",
    "sg:city":"Pedro Mu\u00e7oz",
    "sg:orig_category":"Calderer\u00cda",
    "sg:phone":"+34 926 56 85 76",
    "sg:postcode":"13620",
    "sg:province":"Ciudad Real",
    "wof:name":"Talleres Mecar Cdad",
    "wof:placetype":"venue"
},
  "geometry": {"coordinates":[-2.944617033,39.3901367188],"type":"Point"}
}