{
  "type": "Feature",
  "properties": {
    "iso:country":"ES",
    "sg:address":"Psaj Platero Leiva, 1",
    "sg:city":"Cordoba",
    "sg:orig_category":"Distribuci\u00d3n De Petr\u00d3leo Y Derivados",
    "sg:phone":"+34 957 75 02 44",
    "sg:postcode":"14010",
    "sg:province":"C\u00f3rdoba",
    "wof:name":"Hermanos Nieto Guzman S.l.",
    "wof:placetype":"venue"
},
  "geometry": {"coordinates":[-4.7643518448,37.8786811829],"type":"Point"}
}