{
  "type": "Feature",
  "properties": {
    "iso:country":"ES",
    "sg:address":"Calle de Lope Diaz De Haro, 11",
    "sg:city":"Bermeo",
    "sg:orig_category":"Ropa Para Se\u00d1oras (al Por Menor)",
    "sg:phone":"+34 946 88 01 12",
    "sg:postcode":"48370",
    "sg:province":"Vizcaya",
    "wof:name":"Luis Corrales Y Saioa Arroita C.b.",
    "wof:placetype":"venue"
},
  "geometry": {"coordinates":[-2.7220799923,43.4196891785],"type":"Point"}
}