{
  "type": "Feature",
  "properties": {
    "addr:full":"Plaz Campo Verde (de), 1 Granada Granada 18001",
    "addr:postcode":"18001",
    "iso:country":"ES",
    "sg:address":"Plaz Campo Verde (de), 1",
    "sg:city":"Granada",
    "sg:orig_category":"Ingenier\u00cda, Centros De Estudios (diversos)",
    "sg:phone":"+34 958 26 32 16",
    "sg:postcode":"18001",
    "sg:province":"Granada",
    "wof:name":"Soria Contreras Alberto",
    "wof:placetype":"venue"
},
  "geometry": {"coordinates":[-3.6003549099,37.1738967896],"type":"Point"}
}