{
  "type": "Feature",
  "properties": {
    "addr:full":"Pan, 2 Villagonzalo Tormes Salamanca 37893",
    "addr:housenumber":"2",
    "addr:postcode":"37893",
    "addr:street":"Pan",
    "iso:country":"ES",
    "sg:address":"Pan, 2",
    "sg:city":"Villagonzalo Tormes",
    "sg:orig_category":"Panader\u00cdas, Panader\u00cdas",
    "sg:phone":"+34 923 37 20 36",
    "sg:postcode":"37893",
    "sg:province":"Salamanca",
    "wof:name":"Panificadora El Tormes Cdad.",
    "wof:placetype":"venue"
},
  "geometry": {"coordinates":[-5.4965429306,40.8927192688],"type":"Point"}
}