{
  "type": "Feature",
  "properties": {
    "iso:country":"ES",
    "sg:address":"Calle de Juan Morales Navarro, S/n",
    "sg:city":"Santa Brigida",
    "sg:orig_category":"Par\u00cds",
    "sg:phone":"+34 928 64 16 05",
    "sg:postcode":"35300",
    "sg:province":"Las Palmas",
    "wof:name":"Gonzalez Garcia Jorge",
    "wof:placetype":"venue"
},
  "geometry": {"coordinates":[-15.4988393784,28.0342655182],"type":"Point"}
}