{
  "type": "Feature",
  "properties": {
    "iso:country":"ES",
    "sg:address":"Calle de Caura, 2",
    "sg:city":"Coria Rio",
    "sg:orig_category":"Asociaciones Humanitarias, De Cooperaci\u00d3n, De Acci\u00d3n Social",
    "sg:phone":"+34 954 77 44 79",
    "sg:postcode":"41100",
    "sg:province":"Sevilla",
    "wof:name":"Asociacion De Mujeres Comarcal Sibroguadalquivir",
    "wof:placetype":"venue"
},
  "geometry": {"coordinates":[-6.0537185669,37.2827072144],"type":"Point"}
}