{
  "type": "Feature",
  "properties": {
    "addr:full":"Avgd Joaquim Morello, 7 Esterri D'aneu Lleida 25580",
    "addr:housenumber":"7",
    "addr:postcode":"25580",
    "addr:street":"Morello",
    "iso:country":"ES",
    "sg:address":"Avgd Joaquim Morello, 7",
    "sg:city":"Esterri D'aneu",
    "sg:orig_category":"Asesor\u00cda Sobre Comunicaci\u00d3n De Empresas",
    "sg:phone":"+34 973 62 63 37",
    "sg:postcode":"25580",
    "sg:province":"Lleida",
    "wof:name":"Assessoria Valls D'aneu",
    "wof:placetype":"venue"
},
  "geometry": {"coordinates":[1.1217758656,42.6289672852],"type":"Point"}
}