{
  "type": "Feature",
  "properties": {
    "addr:full":"Carrer de Baronia, 6 Vilafortuny Tarragona 43850",
    "addr:housenumber":"6",
    "addr:postcode":"43850",
    "addr:street":"Carrer De Baronia",
    "iso:country":"ES",
    "sg:address":"Carrer de Baronia, 6",
    "sg:city":"Vilafortuny",
    "sg:orig_category":"Asesor\u00cda Para La Organizaci\u00d3n Y Gesti\u00d3n Del Transporte",
    "sg:phone":"+34 977 79 47 27",
    "sg:postcode":"43850",
    "sg:province":"Tarragona",
    "sg:website":"www.mudanzasfmarin.com",
    "wof:name":"Marin Sanchez Josep Francesc",
    "wof:placetype":"venue"
},
  "geometry": {"coordinates":[1.0947949886,41.0734901428],"type":"Point"}
}