{
  "type": "Feature",
  "properties": {
    "addr:full":"Monasterio Tulebras, 1 Iru\u00f1a Navarra 31011",
    "addr:housenumber":"1",
    "addr:postcode":"31011",
    "addr:street":"Tulebras",
    "iso:country":"ES",
    "sg:address":"Monasterio Tulebras, 1",
    "sg:city":"Iru\u00f1a",
    "sg:orig_category":"Asociaciones, Organismos Culturales Y Socioeducativos",
    "sg:phone":"+34 948 26 63 01",
    "sg:postcode":"31011",
    "sg:province":"Navarra",
    "wof:name":"Asociacion Juvenil Club Isaba",
    "wof:placetype":"venue"
},
  "geometry": {"coordinates":[-1.6560225487,42.8142433167],"type":"Point"}
}