{
  "type": "Feature",
  "properties": {
    "addr:full":"Calle de Pelayo, 43 Madrid Madrid 28004",
    "addr:housenumber":"43",
    "addr:postcode":"madrid;28004",
    "addr:street":"Calle De Pelayo",
    "iso:country":"ES",
    "sg:address":"Calle de Pelayo, 43",
    "sg:city":"Madrid",
    "sg:orig_category":"Fabricaci\u00d3n De Tapices Y Moquetas Para Suelos Y Paredes",
    "sg:phone":"+34 913 19 64 71",
    "sg:postcode":"28004",
    "sg:province":"Madrid",
    "wof:name":"Carreres Fajardo Victoriano",
    "wof:placetype":"venue"
},
  "geometry": {"coordinates":[-3.6978580952,40.4239578247],"type":"Point"}
}