{
  "type": "Feature",
  "properties": {
    "addr:full":"Calle de Lomo Guillen, 24 Santa Maria De Guia Las Palmas 35450",
    "addr:housenumber":"24",
    "addr:postcode":"35450",
    "addr:street":"Calle De Lomo Guillen",
    "iso:country":"ES",
    "sg:address":"Calle de Lomo Guillen, 24",
    "sg:city":"Santa Maria De Guia",
    "sg:orig_category":"Distribuci\u00d3n De Petr\u00d3leo Y Derivados",
    "sg:phone":"+34 928 55 12 65",
    "sg:postcode":"35450",
    "sg:province":"Las Palmas",
    "wof:name":"Talavera Quevedo Carmelo",
    "wof:placetype":"venue"
},
  "geometry": {"coordinates":[-15.6342592239,28.1413002014],"type":"Point"}
}