{
  "type": "Feature",
  "properties": {
    "addr:full":"Av Prat, S/n Moia Barcelona 08180",
    "addr:housenumber":"s / n",
    "addr:postcode":"08180",
    "addr:street":"Av Prat",
    "iso:country":"ES",
    "sg:address":"Av Prat, S/n",
    "sg:city":"Moia",
    "sg:orig_category":"Art\u00cdculos De Pvc (fabricaci\u00d3n Y Al Por Mayor)",
    "sg:phone":"+34 938 20 81 10",
    "sg:postcode":"08180",
    "sg:province":"Barcelona",
    "wof:name":"Isami S.l.",
    "wof:placetype":"venue"
},
  "geometry": {"coordinates":[2.1097149849,41.8048095703],"type":"Point"}
}