{
  "type": "Feature",
  "properties": {
    "iso:country":"ES",
    "sg:address":"Calle de Rollo, 44",
    "sg:city":"Mayorga",
    "sg:orig_category":"Cajas Y Embalajes De Pl\u00c1stico",
    "sg:phone":"+34 983 75 11 67",
    "sg:postcode":"47680",
    "sg:province":"Valladolid",
    "wof:name":"Plastivican S.l",
    "wof:placetype":"venue"
},
  "geometry": {"coordinates":[-5.2598791122,42.1662712097],"type":"Point"}
}