{
  "type": "Feature",
  "properties": {
    "iso:country":"ES",
    "sg:address":"Pg Gracia, 53",
    "sg:city":"Barcelona",
    "sg:orig_category":"Ropa Para Se\u00d1oras (al Por Menor)",
    "sg:phone":"+34 934 87 36 31",
    "sg:postcode":"08007",
    "sg:province":"Barcelona",
    "sg:website":"www.podivm.com",
    "wof:name":"Exclusivas Podium S.a.",
    "wof:placetype":"venue"
},
  "geometry": {"coordinates":[2.1640748978,41.3924407959],"type":"Point"}
}