{
  "type": "Feature",
  "properties": {
    "iso:country":"ES",
    "sg:address":"Carrer de L'arc De Sant Marti, 85",
    "sg:city":"Barcelona",
    "sg:orig_category":"Reciclaje, Tratamiento De Tejidos",
    "sg:phone":"+34 934 55 53 50",
    "sg:postcode":"08032",
    "sg:province":"Barcelona",
    "wof:name":"Mateo Roy Rosario",
    "wof:placetype":"venue"
},
  "geometry": {"coordinates":[2.1719501019,41.4230155945],"type":"Point"}
}