{
  "type": "Feature",
  "properties": {
    "iso:country":"ES",
    "sg:address":"Carrer de Ramon J. Sender, 7",
    "sg:city":"Reus",
    "sg:orig_category":"Electrodom\u00c9sticos (al Por Menor)",
    "sg:phone":"+34 977 75 79 08",
    "sg:postcode":"43204",
    "sg:province":"Tarragona",
    "wof:name":"Electro Calbet S.a.",
    "wof:placetype":"venue"
},
  "geometry": {"coordinates":[1.1116420031,41.1505126953],"type":"Point"}
}