{
  "type": "Feature",
  "properties": {
    "iso:country":"ES",
    "sg:address":"Calle de Campomanes, 1",
    "sg:city":"Oviedo",
    "sg:orig_category":"Colchones (fabricaci\u00d3n, Al Por Mayor, Al Por Menor)",
    "sg:phone":"+34 985 22 37 75",
    "sg:postcode":"33008",
    "sg:province":"Asturias",
    "wof:name":"Rivero Morujo Antonio",
    "wof:placetype":"venue"
},
  "geometry": {"coordinates":[-5.8463215828,43.3583145142],"type":"Point"}
}