{
  "type": "Feature",
  "properties": {
    "addr:full":"Carrer de Sant Ignasi (de), 25 Vilassar De Mar Barcelona 08340",
    "addr:housenumber":"25",
    "addr:postcode":"08340",
    "addr:street":"Carrer De Sant Ignasi De",
    "iso:country":"ES",
    "sg:address":"Carrer de Sant Ignasi (de), 25",
    "sg:city":"Vilassar De Mar",
    "sg:orig_category":"Peluqueros: De Se\u00d1oras",
    "sg:phone":"+34 937 59 27 89",
    "sg:postcode":"08340",
    "sg:province":"Barcelona",
    "wof:name":"Vives Ametller Carmen",
    "wof:placetype":"venue"
},
  "geometry": {"coordinates":[2.3904321194,41.5038299561],"type":"Point"}
}