{
  "type": "Feature",
  "properties": {
    "iso:country":"ES",
    "sg:address":"Calle de Pintoreria, 74",
    "sg:city":"Vitoria-gasteiz",
    "sg:orig_category":"Clubes Y Asociaciones Deportivas Y De Actividades Invernales Y De Monta\u00d1a",
    "sg:phone":"+34 945 25 03 54",
    "sg:postcode":"01001",
    "sg:province":"\u00c1lava",
    "sg:website":"www.cmgazteiz.com",
    "wof:name":"Club De Monta\u00f1a Gazteiz",
    "wof:placetype":"venue"
},
  "geometry": {"coordinates":[-2.6705799103,42.8496131897],"type":"Point"}
}