{
  "type": "Feature",
  "properties": {
    "iso:country":"ES",
    "sg:address":"Ctra San Cucao, 1",
    "sg:city":"Posada",
    "sg:orig_category":"Peluqueros: De Se\u00d1oras",
    "sg:phone":"+34 985 77 11 81",
    "sg:postcode":"33424",
    "sg:province":"Asturias",
    "wof:name":"Alvarez Fernandez Maria Del Carmen",
    "wof:placetype":"venue"
},
  "geometry": {"coordinates":[-5.8517594337,43.439907074],"type":"Point"}
}