{
  "type": "Feature",
  "properties": {
    "addr:full":"Calle de Ramon Azorin, 2 Madrid Madrid 28047",
    "addr:housenumber":"2",
    "addr:postcode":"28047",
    "addr:street":"Calle De Ramon Azorin",
    "iso:country":"ES",
    "sg:address":"Calle de Ramon Azorin, 2",
    "sg:city":"Madrid",
    "sg:orig_category":"Agencias Y Asesores De Publicidad",
    "sg:phone":"+34 914 70 17 11",
    "sg:postcode":"28047",
    "sg:province":"Madrid",
    "wof:name":"Velecio Editores S.l.",
    "wof:placetype":"venue"
},
  "geometry": {"coordinates":[-3.7414119244,40.4033737183],"type":"Point"}
}