{
  "type": "Feature",
  "properties": {
    "addr:full":"Plaz Triunfo De Santa Marina, 14 Fernan Nu\u00e7ez C\u00f3rdoba 14520",
    "addr:housenumber":"14",
    "addr:postcode":"14520",
    "addr:street":"Plaz;Marina;Co\u0301Rdoba",
    "iso:country":"ES",
    "sg:address":"Plaz Triunfo De Santa Marina, 14",
    "sg:city":"Fernan Nu\u00e7ez",
    "sg:orig_category":"Farmacias",
    "sg:phone":"+34 957 38 00 86",
    "sg:postcode":"14520",
    "sg:province":"C\u00f3rdoba",
    "wof:name":"Caracuel Duro Benito",
    "wof:placetype":"venue"
},
  "geometry": {"coordinates":[-4.7239189148,37.6722068787],"type":"Point"}
}