{
  "type": "Feature",
  "properties": {
    "iso:country":"ES",
    "sg:address":"Carrer de Maladeta, 41",
    "sg:city":"Esplugues Llobregat",
    "sg:orig_category":"Marroquiner\u00cda (confecci\u00d3n)",
    "sg:phone":"+34 934 73 49 04",
    "sg:postcode":"08950",
    "sg:province":"Barcelona",
    "wof:name":"Leon Martin Manuel",
    "wof:placetype":"venue"
},
  "geometry": {"coordinates":[2.0995979309,41.3717689514],"type":"Point"}
}