{
  "type": "Feature",
  "properties": {
    "addr:full":"Calle de Mar (del), 13 Torrevieja Alicante 03180",
    "addr:postcode":"03180",
    "addr:street":"Calle De;Del",
    "iso:country":"ES",
    "sg:address":"Calle de Mar (del), 13",
    "sg:city":"Torrevieja",
    "sg:orig_category":"Arreglo, Reparaci\u00d3n, Piezas Sueltas De Televisi\u00d3n, V\u00cddeo, Hi",
    "sg:phone":"+34 965 71 48 10",
    "sg:postcode":"03180",
    "sg:province":"Alicante",
    "wof:name":"Tecnisat S.l.",
    "wof:placetype":"venue"
},
  "geometry": {"coordinates":[-0.6536790133,38.0173606873],"type":"Point"}
}