{
  "type": "Feature",
  "properties": {
    "iso:country":"ES",
    "sg:address":"Calle de Ruiz Hernandez, 3",
    "sg:city":"Valladolid",
    "sg:orig_category":"Estancos",
    "sg:phone":"+34 983 20 81 75",
    "sg:postcode":"47002",
    "sg:province":"Valladolid",
    "wof:name":"Escolar Ureta Carmen",
    "wof:placetype":"venue"
},
  "geometry": {"coordinates":[-4.7209439278,41.652885437],"type":"Point"}
}