{
  "type": "Feature",
  "properties": {
    "addr:full":"Avda Ausias March, 220 Valencia Valencia 46026",
    "addr:housenumber":"220",
    "addr:postcode":"46026",
    "addr:street":"Avda Ausias March",
    "iso:country":"ES",
    "sg:address":"Avda Ausias March, 220",
    "sg:city":"Valencia",
    "sg:orig_category":"Chapister\u00cda",
    "sg:phone":"+34 963 75 38 91",
    "sg:postcode":"46026",
    "sg:province":"Valencia",
    "wof:name":"Velorent S.a.",
    "wof:placetype":"venue"
},
  "geometry": {"coordinates":[-0.3730089962,39.4263305664],"type":"Point"}
}