{
  "type": "Feature",
  "properties": {
    "addr:full":"Calle de Puerta Nueva, 52 Zamora Zamora 49002",
    "addr:housenumber":"52",
    "addr:postcode":"49002",
    "addr:street":"Calle De Puerta Nueva",
    "iso:country":"ES",
    "sg:address":"Calle de Puerta Nueva, 52",
    "sg:city":"Zamora",
    "sg:orig_category":"Promotores Constructores",
    "sg:phone":"+34 980 53 42 81",
    "sg:postcode":"49002",
    "sg:province":"Zamora",
    "wof:name":"Blanco Y Fernandez S.l.",
    "wof:placetype":"venue"
},
  "geometry": {"coordinates":[-5.7409238815,41.5026168823],"type":"Point"}
}