{
  "type": "Feature",
  "properties": {
    "addr:full":"Calle de Sulfato, 1 Madrid Madrid 28021",
    "addr:housenumber":"1",
    "addr:postcode":"28021",
    "addr:street":"Calle De Sulfato",
    "iso:country":"ES",
    "sg:address":"Calle de Sulfato, 1",
    "sg:city":"Madrid",
    "sg:orig_category":"Empresas De Carpinter\u00cda Met\u00c1lica",
    "sg:phone":"+34 915 05 29 92",
    "sg:postcode":"28021",
    "sg:province":"Madrid",
    "wof:name":"Sanchez Plaza Jose",
    "wof:placetype":"venue"
},
  "geometry": {"coordinates":[-3.7136919498,40.3469619751],"type":"Point"}
}