{
  "type": "Feature",
  "properties": {
    "addr:full":"Poligono Industrial Congost, 48 Martorell Barcelona 08760",
    "addr:housenumber":"48",
    "addr:postcode":"08760",
    "iso:country":"ES",
    "sg:address":"Poligono Industrial Congost, 48",
    "sg:city":"Martorell",
    "sg:orig_category":"Transportes Por Carretera: Lotes Completos, Mercanc\u00cdas Diversas",
    "sg:phone":"+34 937 74 16 39",
    "sg:postcode":"08760",
    "sg:province":"Barcelona",
    "wof:name":"Ibero-china S.a.",
    "wof:placetype":"venue"
},
  "geometry": {"coordinates":[1.9265979528,41.474105835],"type":"Point"}
}