{
  "type": "Feature",
  "properties": {
    "addr:full":"Pg Joan Carles I, 33 Eivissa Islas Baleares 07800",
    "addr:housenumber":"33",
    "addr:postcode":"07800",
    "addr:street":"Pg Joan Carles I",
    "iso:country":"ES",
    "sg:address":"Pg Joan Carles I, 33",
    "sg:city":"Eivissa",
    "sg:orig_category":"Inmobiliaria (agencias)",
    "sg:phone":"+34 971 19 37 28",
    "sg:postcode":"07800",
    "sg:province":"Islas Baleares",
    "wof:name":"Actividades Inmobiliarias Clara Del Rey S.l",
    "wof:placetype":"venue"
},
  "geometry": {"coordinates":[1.4462658167,38.9147338867],"type":"Point"}
}