{
  "type": "Feature",
  "properties": {
    "iso:country":"ES",
    "sg:address":"Calle de Eulalia Sauquillo, 9",
    "sg:city":"Torrejon Calzada",
    "sg:orig_category":"Urbanistas",
    "sg:phone":"+34 918 16 98 79",
    "sg:postcode":"28991",
    "sg:province":"Madrid",
    "wof:name":"Yps Sociedad Urbanizadoras S.a.",
    "wof:placetype":"venue"
},
  "geometry": {"coordinates":[-3.8011720181,40.2023124695],"type":"Point"}
}