{
  "type": "Feature",
  "properties": {
    "addr:full":"Pl. Espa\u00f1a, 5 La Moheda C\u00e1ceres 10849",
    "addr:housenumber":"5",
    "addr:postcode":"10849",
    "addr:street":"Pl. Espan\u0303A",
    "iso:country":"ES",
    "sg:address":"Pl. Espa\u00f1a, 5",
    "sg:city":"La Moheda",
    "sg:orig_category":"Iglesia Cat\u00d3lica",
    "sg:phone":"+34 927 14 01 17",
    "sg:postcode":"10849",
    "sg:province":"C\u00e1ceres",
    "wof:name":"Parroquia San Isidro Labrador",
    "wof:placetype":"venue"
},
  "geometry": {"coordinates":[-6.6168889999,40.0565986633],"type":"Point"}
}