{
  "type": "Feature",
  "properties": {
    "addr:full":"Ctra Villarrobledo, S/n S. Clemente Cuenca 16600",
    "addr:housenumber":"s",
    "addr:postcode":"16600",
    "addr:street":"Ctra Villarrobledo;/ N S. Clemente Cuenca",
    "iso:country":"ES",
    "sg:address":"Ctra Villarrobledo, S/n",
    "sg:city":"S. Clemente",
    "sg:orig_category":"Animales (al Por Menor)",
    "sg:phone":"+34 969 30 24 89",
    "sg:postcode":"16600",
    "sg:province":"Cuenca",
    "wof:name":"Pofris S.l.",
    "wof:placetype":"venue"
},
  "geometry": {"coordinates":[-2.4331409931,39.3961448669],"type":"Point"}
}