{
  "type": "Feature",
  "properties": {
    "addr:full":"O. Redondo, 4 Tamames Salamanca 37600",
    "addr:housenumber":"4",
    "addr:postcode":"37600",
    "iso:country":"ES",
    "sg:address":"O. Redondo, 4",
    "sg:city":"Tamames",
    "sg:orig_category":"Asesor\u00cda Fiscal Y Jur\u00cddica",
    "sg:phone":"+34 923 44 95 01",
    "sg:postcode":"37600",
    "sg:province":"Salamanca",
    "wof:name":"Barrio Garcia Jose Luis Ignacio",
    "wof:placetype":"venue"
},
  "geometry": {"coordinates":[-6.1087841988,40.656791687],"type":"Point"}
}