{
  "type": "Feature",
  "properties": {
    "addr:full":"Av Tres-cents Trenta-sis, 15 Castelldefels Barcelona 08860",
    "addr:housenumber":"15",
    "addr:postcode":"08860",
    "addr:street":"Av Tres-Cents Trenta-Sis",
    "iso:country":"ES",
    "sg:address":"Av Tres-cents Trenta-sis, 15",
    "sg:city":"Castelldefels",
    "sg:orig_category":"Enfermeras: Consultas, Atenci\u00d3n A Domicilio",
    "sg:phone":"+34 936 64 40 02",
    "sg:postcode":"08860",
    "sg:province":"Barcelona",
    "wof:name":"Iglesias Pons Jaime",
    "wof:placetype":"venue"
},
  "geometry": {"coordinates":[1.9278570414,41.2629699707],"type":"Point"}
}