{
  "type": "Feature",
  "properties": {
    "addr:full":"Carrer de Corsega, 218 Barcelona Barcelona 08036",
    "addr:housenumber":"218",
    "addr:postcode":"08036",
    "addr:street":"Carrer De Corsega",
    "iso:country":"ES",
    "sg:address":"Carrer de Corsega, 218",
    "sg:city":"Barcelona",
    "sg:orig_category":"Agencias De Viajes",
    "sg:phone":"+34 934 19 41 03",
    "sg:postcode":"08036",
    "sg:province":"Barcelona",
    "wof:name":"Snow Travel S. A.",
    "wof:placetype":"venue"
},
  "geometry": {"coordinates":[2.1533939838,41.3918685913],"type":"Point"}
}