{
  "type": "Feature",
  "properties": {
    "iso:country":"ES",
    "sg:address":"Calle de Roque Barcia, 3",
    "sg:city":"Huelva",
    "sg:orig_category":"Abogados",
    "sg:phone":"+34 959 27 02 55",
    "sg:postcode":"21003",
    "sg:province":"Huelva",
    "wof:name":"Carde\u00f1osa Cordero Isabel Maria",
    "wof:placetype":"venue"
},
  "geometry": {"coordinates":[-6.9376120567,37.2562217712],"type":"Point"}
}