{
  "type": "Feature",
  "properties": {
    "iso:country":"ES",
    "sg:address":"Carrer de Cort (de La), 56",
    "sg:city":"Valls",
    "sg:orig_category":"Pod\u00d3logos: Pedicuros",
    "sg:phone":"+34 977 60 10 07",
    "sg:postcode":"43800",
    "sg:province":"Tarragona",
    "wof:name":"Puyuelo Calvo Antonio",
    "wof:placetype":"venue"
},
  "geometry": {"coordinates":[1.2499339581,41.2853012085],"type":"Point"}
}