{
  "type": "Feature",
  "properties": {
    "addr:full":"Calle de Luises, 22 Donostia-san Sebastian Guip\u00f9zcoa 20015",
    "addr:housenumber":"22",
    "addr:postcode":"20015",
    "addr:street":"Calle De Luises",
    "iso:country":"ES",
    "sg:address":"Calle de Luises, 22",
    "sg:city":"Donostia-san Sebastian",
    "sg:orig_category":"Farmacias",
    "sg:phone":"+34 943 28 67 82",
    "sg:postcode":"20015",
    "sg:province":"Guip\u00f9zcoa",
    "wof:name":"Telleria Gonzalez Juan Carlos",
    "wof:placetype":"venue"
},
  "geometry": {"coordinates":[-1.9552160501,43.3190422058],"type":"Point"}
}