{
  "type": "Feature",
  "properties": {
    "addr:full":"Carrer de Marques De Comillas, 120 Terrassa Barcelona 08225",
    "addr:housenumber":"120",
    "addr:postcode":"08225",
    "addr:street":"Carrer De Marques De Comillas",
    "iso:country":"ES",
    "sg:address":"Carrer de Marques De Comillas, 120",
    "sg:city":"Terrassa",
    "sg:orig_category":"Mec\u00c1nico Del Autom\u00d3vil",
    "sg:phone":"+34 937 88 27 13",
    "sg:postcode":"08225",
    "sg:province":"Barcelona",
    "wof:name":"Francisco-roger S.l",
    "wof:placetype":"venue"
},
  "geometry": {"coordinates":[2.0055301189,41.573677063],"type":"Point"}
}