{
  "type": "Feature",
  "properties": {
    "addr:full":"Carrer de Comte Borrell, 61 Barcelona Barcelona 08015",
    "addr:housenumber":"61",
    "addr:postcode":"08015",
    "addr:street":"Carrer De Comte Borrell",
    "iso:country":"ES",
    "sg:address":"Carrer de Comte Borrell, 61",
    "sg:city":"Barcelona",
    "sg:orig_category":"Molduras, Junquillos, Listones Y Molduras Perforadas",
    "sg:phone":"+34 933 25 05 78",
    "sg:postcode":"08015",
    "sg:province":"Barcelona",
    "wof:name":"Vilaro Torres Feliciano",
    "wof:placetype":"venue"
},
  "geometry": {"coordinates":[2.1617760658,41.3778152466],"type":"Point"}
}