{
  "type": "Feature",
  "properties": {
    "iso:country":"ES",
    "sg:address":"Calle de Pio Xii, 37",
    "sg:city":"Oropesa",
    "sg:orig_category":"Inmobiliaria (agencias)",
    "sg:phone":"+34 964 31 02 13",
    "sg:postcode":"12594",
    "sg:province":"Castell\u00f3n",
    "wof:name":"Bosquet Pastor Maria Eugenia",
    "wof:placetype":"venue"
},
  "geometry": {"coordinates":[0.1390410066,40.0919418335],"type":"Point"}
}