{
  "type": "Feature",
  "properties": {
    "addr:full":"Calle de Miguel De Unamuno, 8 Madrid Madrid 28017",
    "addr:housenumber":"8",
    "addr:postcode":"madrid;28017",
    "addr:street":"Calle De Miguel De Unamuno",
    "iso:country":"ES",
    "sg:address":"Calle de Miguel De Unamuno, 8",
    "sg:city":"Madrid",
    "sg:orig_category":"Material Did\u00c1ctico",
    "sg:phone":"+34 914 04 27 13",
    "sg:postcode":"28017",
    "sg:province":"Madrid",
    "wof:name":"Videplay Parral S.l.",
    "wof:placetype":"venue"
},
  "geometry": {"coordinates":[-3.6504673958,40.428276062],"type":"Point"}
}