{
  "type": "Feature",
  "properties": {
    "addr:full":"Calle de Lima, S/n Alcala Henares Madrid 28806",
    "addr:housenumber":"s",
    "addr:postcode":"28806",
    "addr:street":"Calle De Lima;/ N",
    "iso:country":"ES",
    "sg:address":"Calle de Lima, S/n",
    "sg:city":"Alcala Henares",
    "sg:orig_category":"Tintes (fabricaci\u00d3n, Al Por Mayor)",
    "sg:phone":"+34 918 02 66 98",
    "sg:postcode":"28806",
    "sg:province":"Madrid",
    "wof:name":"Sun Chemical S.a.",
    "wof:placetype":"venue"
},
  "geometry": {"coordinates":[-3.4125878811,40.5142440796],"type":"Point"}
}