{
  "type": "Feature",
  "properties": {
    "addr:full":"Av Mare Deu De Montserrat, 230 Barcelona Barcelona 08041",
    "addr:housenumber":"230",
    "addr:postcode":"08041",
    "addr:street":"Av Mare;De Montserrat",
    "iso:country":"ES",
    "sg:address":"Av Mare Deu De Montserrat, 230",
    "sg:city":"Barcelona",
    "sg:orig_category":"Art\u00cdculos De Regalo (al Por Menor)",
    "sg:phone":"+34 933 47 38 56",
    "sg:postcode":"08041",
    "sg:province":"Barcelona",
    "wof:name":"Moya Nu\u00f1ez Maria Dolores",
    "wof:placetype":"venue"
},
  "geometry": {"coordinates":[2.1745231152,41.4219284058],"type":"Point"}
}