{
  "type": "Feature",
  "properties": {
    "addr:full":"Dalies Les, 4 S. Antoni Portmany Islas Baleares 07820",
    "addr:postcode":"07820",
    "addr:street":"S. Antoni Portmany",
    "iso:country":"ES",
    "sg:address":"Dalies Les, 4",
    "sg:city":"S. Antoni Portmany",
    "sg:orig_category":"Mec\u00c1nico Del Autom\u00d3vil",
    "sg:phone":"+34 971 34 20 67",
    "sg:postcode":"07820",
    "sg:province":"Islas Baleares",
    "wof:name":"Vicens Ribas Antonio",
    "wof:placetype":"venue"
},
  "geometry": {"coordinates":[1.5188339949,39.1094055176],"type":"Point"}
}