{
  "type": "Feature",
  "properties": {
    "iso:country":"ES",
    "sg:address":"Calle de Santa Maria Del Mar, 6",
    "sg:city":"Cadiz",
    "sg:orig_category":"Doctores En Medicina",
    "sg:phone":"+34 956 27 21 41",
    "sg:postcode":"11008",
    "sg:province":"C\u00e1diz",
    "wof:name":"Bohorquez Sierra Cristobal",
    "wof:placetype":"venue"
},
  "geometry": {"coordinates":[-6.2880768776,36.5240402222],"type":"Point"}
}