{
  "type": "Feature",
  "properties": {
    "addr:full":"Avda Condes De Soto Ameno, 43 Alacant Alicante 03005",
    "addr:housenumber":"43",
    "addr:postcode":"03005",
    "addr:street":"Avda Condes;Ameno",
    "iso:country":"ES",
    "sg:address":"Avda Condes De Soto Ameno, 43",
    "sg:city":"Alacant",
    "sg:orig_category":"Inmobiliaria (agencias)",
    "sg:phone":"+34 965 13 60 06",
    "sg:postcode":"03005",
    "sg:province":"Alicante",
    "wof:name":"Servicios Inmobiliarios Las Plazas S.l.",
    "wof:placetype":"venue"
},
  "geometry": {"coordinates":[-0.4957329929,38.3496246338],"type":"Point"}
}