{
  "type": "Feature",
  "properties": {
    "addr:full":"Ctra Alcala-sevilla, Km. 0008,8 Alcala Guadaira Sevilla 41500",
    "addr:postcode":"41500",
    "addr:street":"Ctra Alcala-Sevilla Km. 0008,8",
    "iso:country":"ES",
    "sg:address":"Ctra Alcala-sevilla, Km. 0008,8",
    "sg:city":"Alcala Guadaira",
    "sg:orig_category":"Bisuter\u00cda, Joyer\u00cda, Relojer\u00cda (al Por Menor)",
    "sg:phone":"+34 954 10 17 11",
    "sg:postcode":"41500",
    "sg:province":"Sevilla",
    "wof:name":"Adolfo De Los Reyes S.l",
    "wof:placetype":"venue"
},
  "geometry": {"coordinates":[-5.8543348312,37.3395385742],"type":"Point"}
}