{
  "type": "Feature",
  "properties": {
    "iso:country":"ES",
    "sg:address":"Pg Saladar, 98",
    "sg:city":"Denia",
    "sg:orig_category":"Inmobiliaria (agencias)",
    "sg:phone":"+34 966 43 51 54",
    "sg:postcode":"03700",
    "sg:province":"Alicante",
    "sg:website":"www.inmolaimar.com",
    "wof:name":"Laimar Figueres S.l.",
    "wof:placetype":"venue"
},
  "geometry": {"coordinates":[0.1095770001,38.8382797241],"type":"Point"}
}