{
  "type": "Feature",
  "properties": {
    "iso:country":"ES",
    "sg:address":"Plaz Mayor, 10",
    "sg:city":"Guadalajara",
    "sg:orig_category":"Abogados",
    "sg:phone":"+34 949 21 83 51",
    "sg:postcode":"19001",
    "sg:province":"Guadalajara",
    "wof:name":"Martinez Atienza Javier",
    "wof:placetype":"venue"
},
  "geometry": {"coordinates":[-3.1666049957,40.6332321167],"type":"Point"}
}