{
  "type": "Feature",
  "properties": {
    "iso:country":"ES",
    "sg:address":"Plaz Mayor, 4",
    "sg:city":"Cabezon.barrio Viejo",
    "sg:orig_category":"M\u00c1quinas De Jardiner\u00cda",
    "sg:phone":"+34 983 50 06 20",
    "sg:postcode":"47260",
    "sg:province":"Valladolid",
    "wof:name":"Revilla Cernuda Francisco Javier",
    "wof:placetype":"venue"
},
  "geometry": {"coordinates":[-4.6450300217,41.7345352173],"type":"Point"}
}