{
  "type": "Feature",
  "properties": {
    "addr:full":"Carrer de Vilar Del, 8 Valls Tarragona 43800",
    "addr:housenumber":"8",
    "addr:postcode":"43800",
    "addr:street":"Carrer De Vilar Del",
    "iso:country":"ES",
    "sg:address":"Carrer de Vilar Del, 8",
    "sg:city":"Valls",
    "sg:orig_category":"Cine (distribuci\u00d3n)",
    "sg:phone":"+34 977 60 18 03",
    "sg:postcode":"43800",
    "sg:province":"Tarragona",
    "wof:name":"Propostes Creatives S.l",
    "wof:placetype":"venue"
},
  "geometry": {"coordinates":[1.2578910589,41.2878265381],"type":"Point"}
}