{
  "type": "Feature",
  "properties": {
    "addr:full":"Carrer de Girona, 81 Granollers Barcelona 08402",
    "addr:housenumber":"81",
    "addr:postcode":"08402",
    "addr:street":"Carrer De Girona",
    "iso:country":"ES",
    "sg:address":"Carrer de Girona, 81",
    "sg:city":"Granollers",
    "sg:orig_category":"Animales (al Por Menor)",
    "sg:phone":"+34 938 46 73 25",
    "sg:postcode":"08402",
    "sg:province":"Barcelona",
    "wof:name":"Aquaterrario Del Valles Iii S.l.",
    "wof:placetype":"venue"
},
  "geometry": {"coordinates":[2.2916247845,41.6128578186],"type":"Point"}
}