{
  "type": "Feature",
  "properties": {
    "addr:full":"Rua Abdon Blanco, S/n Barco Ourense 32300",
    "addr:housenumber":"s / n",
    "addr:postcode":"32300",
    "addr:street":"Rua Abdon Blanco",
    "iso:country":"ES",
    "sg:address":"Rua Abdon Blanco, S/n",
    "sg:city":"Barco",
    "sg:orig_category":"Talleres: Ropa A Medida",
    "sg:phone":"+34 988 32 27 98",
    "sg:postcode":"32300",
    "sg:province":"Ourense",
    "wof:name":"Leon Prieto Manuel",
    "wof:placetype":"venue"
},
  "geometry": {"coordinates":[-6.9879589081,42.4158744812],"type":"Point"}
}