{
  "type": "Feature",
  "properties": {
    "iso:country":"ES",
    "sg:address":"Calle de Estacion, 1",
    "sg:city":"Villalbilla De Burgos",
    "sg:orig_category":"Asilos De Ancianos. Centros Privados",
    "sg:phone":"+34 947 29 11 50",
    "sg:postcode":"09197",
    "sg:province":"Burgos",
    "sg:website":"www.leo.worldonline.es/rmgarcia",
    "wof:name":"Centro Asistencial Villalbilla",
    "wof:placetype":"venue"
},
  "geometry": {"coordinates":[-3.7806520462,42.3460083008],"type":"Point"}
}