{
  "type": "Feature",
  "properties": {
    "addr:full":"Calle de Luis Braille, 4 Granada Granada 18005",
    "addr:housenumber":"4",
    "addr:postcode":"18005",
    "addr:street":"Calle De Luis Braille",
    "iso:country":"ES",
    "sg:address":"Calle de Luis Braille, 4",
    "sg:city":"Granada",
    "sg:orig_category":"Ense\u00d1anza, Formaci\u00d3n Profesional: Aprendizaje",
    "sg:phone":"+34 958 52 26 32",
    "sg:postcode":"18005",
    "sg:province":"Granada",
    "wof:name":"Tadel Formacion S.l.",
    "wof:placetype":"venue"
},
  "geometry": {"coordinates":[-3.6033489704,37.1714515686],"type":"Point"}
}