{
  "type": "Feature",
  "properties": {
    "iso:country":"ES",
    "sg:address":"Calle de Camino Del Carmen, S/n",
    "sg:city":"Calahorra",
    "sg:orig_category":"Hormig\u00d3n (m\u00c1quinas E Instalaci\u00d3n)",
    "sg:phone":"+34 941 13 08 38",
    "sg:postcode":"26500",
    "sg:province":"La Rioja",
    "wof:name":"Hormigones Calahorra S.a.",
    "wof:placetype":"venue"
},
  "geometry": {"coordinates":[-1.9685826302,42.2785606384],"type":"Point"}
}