{
  "type": "Feature",
  "properties": {
    "iso:country":"ES",
    "sg:address":"Calle de Ca\u00d1on, 11",
    "sg:city":"Cartagena",
    "sg:orig_category":"Alimentaci\u00d3n General (al Por Menor)",
    "sg:phone":"+34 968 52 11 35",
    "sg:postcode":"30202",
    "sg:province":"Murcia",
    "wof:name":"Supermercado Ca\u00d1on S.l.",
    "wof:placetype":"venue"
},
  "geometry": {"coordinates":[-0.9850050211,37.5995864868],"type":"Point"}
}