{
  "type": "Feature",
  "properties": {
    "iso:country":"ES",
    "sg:address":"Carrer de Alcalde Sanmarti, 106",
    "sg:city":"Alcanar",
    "sg:orig_category":"Maquinaria Para Industrias Diversas",
    "sg:phone":"+34 977 73 02 95",
    "sg:postcode":"43530",
    "sg:province":"Tarragona",
    "wof:name":"Tecmosal S.l.",
    "wof:placetype":"venue"
},
  "geometry": {"coordinates":[0.4763120115,40.5443191528],"type":"Point"}
}