{
  "type": "Feature",
  "properties": {
    "iso:country":"ES",
    "sg:address":"Sto Andia, 3",
    "sg:city":"Iru\u00f1a",
    "sg:orig_category":"Art\u00cdculos De Madera (fabricaci\u00d3n Y Al Por Mayor)",
    "sg:phone":"+34 948 22 56 81",
    "sg:postcode":"31001",
    "sg:province":"Navarra",
    "wof:name":"Satrustegui Guembe Ramon Alfonso",
    "wof:placetype":"venue"
},
  "geometry": {"coordinates":[-1.6490440369,42.818069458],"type":"Point"}
}