{
  "type": "Feature",
  "properties": {
    "addr:full":"Rua Nova, 21 Veiga Ourense 32360",
    "addr:housenumber":"21",
    "addr:postcode":"32360",
    "addr:street":"Rua Nova",
    "iso:country":"ES",
    "sg:address":"Rua Nova, 21",
    "sg:city":"Veiga",
    "sg:orig_category":"Laboratorios Farmac\u00c9uticos",
    "sg:phone":"+34 988 35 00 35",
    "sg:postcode":"32360",
    "sg:province":"Ourense",
    "wof:name":"Sanchez Nieto Roberto",
    "wof:placetype":"venue"
},
  "geometry": {"coordinates":[-7.02414608,42.2512817383],"type":"Point"}
}