{
  "type": "Feature",
  "properties": {
    "addr:full":"Carrer de Marques Senia, 13 Palma Islas Baleares 07014",
    "addr:housenumber":"13",
    "addr:postcode":"07014",
    "addr:street":"Carrer De Marques Senia",
    "iso:country":"ES",
    "sg:address":"Carrer de Marques Senia, 13",
    "sg:city":"Palma",
    "sg:orig_category":"Papeler\u00cdas, Librer\u00cdas",
    "sg:phone":"+34 971 45 54 20",
    "sg:postcode":"07014",
    "sg:province":"Islas Baleares",
    "wof:name":"Bazar Escudero Hermenegilda",
    "wof:placetype":"venue"
},
  "geometry": {"coordinates":[2.631786108,39.5692405701],"type":"Point"}
}