{
  "type": "Feature",
  "properties": {
    "iso:country":"ES",
    "sg:address":"Calle de San Vicente Martir, 51",
    "sg:city":"Valencia",
    "sg:orig_category":"Lencer\u00cda Femenina, Corseter\u00cda, Trajes De Ba\u00d1o (al Por Menor)",
    "sg:phone":"+34 963 51 60 78",
    "sg:postcode":"46002",
    "sg:province":"Valencia",
    "wof:name":"Castellanos Fernandez Luisa",
    "wof:placetype":"venue"
},
  "geometry": {"coordinates":[-0.378004998,39.4704704285],"type":"Point"}
}