{
  "type": "Feature",
  "properties": {
    "addr:full":"Calle de Segundo Izpizua, 17 Donostia-san Sebastian Guip\u00f9zcoa 20001",
    "addr:housenumber":"17",
    "addr:postcode":"20001",
    "addr:street":"Calle De Segundo Izpizua",
    "iso:country":"ES",
    "sg:address":"Calle de Segundo Izpizua, 17",
    "sg:city":"Donostia-san Sebastian",
    "sg:orig_category":"Ropa Para Se\u00d1oras (al Por Menor)",
    "sg:phone":"+34 943 29 10 72",
    "sg:postcode":"20001",
    "sg:province":"Guip\u00f9zcoa",
    "wof:name":"Vergara Perez Maria Jesus",
    "wof:placetype":"venue"
},
  "geometry": {"coordinates":[-1.9711500406,43.3249473572],"type":"Point"}
}