{
  "type": "Feature",
  "properties": {
    "iso:country":"ES",
    "sg:address":"Calle de Juan Jose Lorente, 45",
    "sg:city":"Zaragoza",
    "sg:orig_category":"Ense\u00d1anza Variada",
    "sg:phone":"+34 976 56 72 81",
    "sg:postcode":"50005",
    "sg:province":"Zaragoza",
    "wof:name":"Carmen Y Victor S.cv.",
    "wof:placetype":"venue"
},
  "geometry": {"coordinates":[-0.8970659971,41.644657135],"type":"Point"}
}