{
  "type": "Feature",
  "properties": {
    "iso:country":"ES",
    "sg:address":"Ctra Canillas, 101",
    "sg:city":"Madrid",
    "sg:orig_category":"Arquitectos",
    "sg:phone":"+34 913 81 31 66",
    "sg:postcode":"28043",
    "sg:province":"Madrid",
    "wof:name":"Aguilar Romero Antonio",
    "wof:placetype":"venue"
},
  "geometry": {"coordinates":[-3.6409156322,40.4652252197],"type":"Point"}
}