{
  "type": "Feature",
  "properties": {
    "addr:full":"Avda Ferrandis Salvador, 41 Mas Dels Frares Castell\u00f3n 12560",
    "addr:housenumber":"41",
    "addr:postcode":"12560",
    "addr:street":"Avda Ferrandis Salvador;Castello\u0301N",
    "iso:country":"ES",
    "sg:address":"Avda Ferrandis Salvador, 41",
    "sg:city":"Mas Dels Frares",
    "sg:orig_category":"Asesor\u00cda Fiscal Y Jur\u00cddica",
    "sg:phone":"+34 964 30 37 29",
    "sg:postcode":"12560",
    "sg:province":"Castell\u00f3n",
    "wof:name":"Tirado Y Asociados Legali Tributario S.l.",
    "wof:placetype":"venue"
},
  "geometry": {"coordinates":[0.0590550005,40.0523414612],"type":"Point"}
}