{
  "type": "Feature",
  "properties": {
    "iso:country":"ES",
    "sg:address":"Calle de San Eudaldo, 1",
    "sg:city":"Madrid",
    "sg:orig_category":"Carpinteros",
    "sg:phone":"+34 917 76 68 20",
    "sg:postcode":"28032",
    "sg:province":"Madrid",
    "wof:name":"Carpinteria Hermanos Cabezas Pulido Cb",
    "wof:placetype":"venue"
},
  "geometry": {"coordinates":[-3.6024270058,40.4061546326],"type":"Point"}
}