{
  "type": "Feature",
  "properties": {
    "addr:full":"Avda Espa\u00d1a, 40 Plasencia C\u00e1ceres 10600",
    "addr:housenumber":"40",
    "addr:postcode":"10600",
    "addr:street":"Avda Espan\u0303A;Ca\u0301Ceres",
    "iso:country":"ES",
    "sg:address":"Avda Espa\u00d1a, 40",
    "sg:city":"Plasencia",
    "sg:orig_category":"Electricidad: Equipos Industriales, Componentes (fabricaci\u00d3n)",
    "sg:phone":"+34 927 41 40 87",
    "sg:postcode":"10600",
    "sg:province":"C\u00e1ceres",
    "wof:name":"Bueno Paredes Fermin",
    "wof:placetype":"venue"
},
  "geometry": {"coordinates":[-6.0988888741,40.0203590393],"type":"Point"}
}