{
  "type": "Feature",
  "properties": {
    "iso:country":"ES",
    "sg:address":"San Martin, S/n",
    "sg:city":"Ganzo",
    "sg:orig_category":"Centros De Educaci\u00d3n Especial",
    "sg:phone":"+34 942 88 84 61",
    "sg:postcode":"39300",
    "sg:province":"Cantabria",
    "wof:name":"Colegio Publico Matilde De La Torre",
    "wof:placetype":"venue"
},
  "geometry": {"coordinates":[-4.066339016,43.3582267761],"type":"Point"}
}