{
  "type": "Feature",
  "properties": {
    "addr:full":"Calle de Sanguino Michel, 8 Caceres C\u00e1ceres 10001",
    "addr:housenumber":"8",
    "addr:postcode":"10001",
    "addr:street":"Calle De Sanguino Michel;Ca\u0301Ceres",
    "iso:country":"ES",
    "sg:address":"Calle de Sanguino Michel, 8",
    "sg:city":"Caceres",
    "sg:orig_category":"Albergues",
    "sg:phone":"+34 927 22 17 50",
    "sg:postcode":"10001",
    "sg:province":"C\u00e1ceres",
    "wof:name":"Hostal La Rosa C.b.",
    "wof:placetype":"venue"
},
  "geometry": {"coordinates":[-6.3817248344,39.4680328369],"type":"Point"}
}