{
  "type": "Feature",
  "properties": {
    "iso:country":"ES",
    "sg:address":"Castillo Moratalla(p I San Martin), S/n",
    "sg:city":"Lorqui",
    "sg:orig_category":"Inmobiliaria (agencias)",
    "sg:phone":"+34 968 67 63 50",
    "sg:postcode":"30564",
    "sg:province":"Murcia",
    "wof:name":"Romero Y Esquer S.l.",
    "wof:placetype":"venue"
},
  "geometry": {"coordinates":[-1.232303977,38.1063766479],"type":"Point"}
}