{
  "type": "Feature",
  "properties": {
    "iso:country":"ES",
    "sg:address":"Calle de Callegilla, 14",
    "sg:city":"Laredo",
    "sg:orig_category":"Promotores Constructores",
    "sg:phone":"+34 942 60 50 00",
    "sg:postcode":"39770",
    "sg:province":"Cantabria",
    "wof:name":"Construcciones De Estructuras La Albaida S.l.",
    "wof:placetype":"venue"
},
  "geometry": {"coordinates":[-3.3943319321,43.4094390869],"type":"Point"}
}