{
  "type": "Feature",
  "properties": {
    "iso:country":"ES",
    "sg:address":"Barr San Pedro, S/n",
    "sg:city":"Puente San Miguel",
    "sg:orig_category":"Arte, Cultura, Edici\u00d3n",
    "sg:phone":"+34 942 82 01 15",
    "sg:postcode":"39530",
    "sg:province":"Cantabria",
    "wof:name":"Jardin Historico Puente San Miguel S.a.",
    "wof:placetype":"venue"
},
  "geometry": {"coordinates":[-4.0881938934,43.3580703735],"type":"Point"}
}