{
  "type": "Feature",
  "properties": {
    "iso:country":"ES",
    "sg:address":"Avda Castilla Y Leon, 7",
    "sg:city":"Burgos",
    "sg:orig_category":"Pod\u00d3logos: Pedicuros",
    "sg:phone":"+34 947 22 10 87",
    "sg:postcode":"09006",
    "sg:province":"Burgos",
    "wof:name":"Blasco Garrido Jose Luis",
    "wof:placetype":"venue"
},
  "geometry": {"coordinates":[-3.6830909252,42.3490715027],"type":"Point"}
}