{
  "type": "Feature",
  "properties": {
    "addr:full":"Avda Julio Rodriguez Soto, 4 Carballi\u00f1o Ourense 32500",
    "addr:housenumber":"4",
    "addr:postcode":"32500",
    "addr:street":"Avda Julio;Soto",
    "iso:country":"ES",
    "sg:address":"Avda Julio Rodriguez Soto, 4",
    "sg:city":"Carballi\u00f1o",
    "sg:orig_category":"Bancos",
    "sg:phone":"+34 988 27 18 91",
    "sg:postcode":"32500",
    "sg:province":"Ourense",
    "wof:name":"Banco De Galicia",
    "wof:placetype":"venue"
},
  "geometry": {"coordinates":[-8.0817527771,42.4273338318],"type":"Point"}
}