{
  "type": "Feature",
  "properties": {
    "addr:full":"Carr Anselm Clave, 44 Santa Coloma De Farners Girona 17430",
    "addr:housenumber":"44",
    "addr:postcode":"17430",
    "addr:street":"Carr Anselm Clave",
    "iso:country":"ES",
    "sg:address":"Carr Anselm Clave, 44",
    "sg:city":"Santa Coloma De Farners",
    "sg:orig_category":"Ropa Para Ni\u00d1os (al Por Menor)",
    "sg:phone":"+34 972 84 32 60",
    "sg:postcode":"17430",
    "sg:province":"Girona",
    "wof:name":"Masso Caros Maria Dolors",
    "wof:placetype":"venue"
},
  "geometry": {"coordinates":[2.6645259857,41.8629417419],"type":"Point"}
}