{
  "type": "Feature",
  "properties": {
    "addr:full":"Doctor Carulla, S/n Arbucies Girona 17401",
    "addr:housenumber":"s / n",
    "addr:postcode":"17401",
    "addr:street":"Doctor Carulla",
    "iso:country":"ES",
    "sg:address":"Doctor Carulla, S/n",
    "sg:city":"Arbucies",
    "sg:orig_category":"Ense\u00d1anza Secundaria: Colegios Y Escuelas Privadas",
    "sg:phone":"+34 972 86 01 54",
    "sg:postcode":"17401",
    "sg:province":"Girona",
    "wof:name":"Institut De Batxillerat Mixte D'arbucies",
    "wof:placetype":"venue"
},
  "geometry": {"coordinates":[2.519094944,41.8152313232],"type":"Point"}
}