{
  "type": "Feature",
  "properties": {
    "iso:country":"ES",
    "sg:address":"Carrer de Major, 4",
    "sg:city":"Sitges",
    "sg:orig_category":"Art\u00cdculos De Regalo (al Por Menor)",
    "sg:phone":"+34 938 94 65 78",
    "sg:postcode":"08870",
    "sg:province":"Barcelona",
    "wof:name":"Royo Villalonga Maria Roser",
    "wof:placetype":"venue"
},
  "geometry": {"coordinates":[1.8116379976,41.2354507446],"type":"Point"}
}