{
  "type": "Feature",
  "properties": {
    "iso:country":"ES",
    "sg:address":"Carrer de Tamarit, 129",
    "sg:city":"Barcelona",
    "sg:orig_category":"Alimentaci\u00d3n General (al Por Menor)",
    "sg:phone":"+34 934 23 28 96",
    "sg:postcode":"08015",
    "sg:province":"Barcelona",
    "wof:name":"Wang  Fen",
    "wof:placetype":"venue"
},
  "geometry": {"coordinates":[2.1586213112,41.3769073486],"type":"Point"}
}