{
  "type": "Feature",
  "properties": {
    "iso:country":"ES",
    "sg:address":"Calle de Brunete, 2",
    "sg:city":"Roda",
    "sg:orig_category":"Estancos",
    "sg:phone":"+34 967 44 34 88",
    "sg:postcode":"02630",
    "sg:province":"Albacete",
    "wof:name":"Simarro Belmonte Manuela",
    "wof:placetype":"venue"
},
  "geometry": {"coordinates":[-2.1560258865,39.2038192749],"type":"Point"}
}