{
  "type": "Feature",
  "properties": {
    "addr:full":"Real, S/n Quintanas Rubias Abajo Soria 42345",
    "addr:housenumber":"s / n",
    "addr:postcode":"42345",
    "addr:street":"Real;Quintanas Rubias",
    "iso:country":"ES",
    "sg:address":"Real, S/n",
    "sg:city":"Quintanas Rubias Abajo",
    "sg:orig_category":"Complementos De Vestir (al Por Menor)",
    "sg:phone":"+34 975 35 60 17",
    "sg:postcode":"42345",
    "sg:province":"Soria",
    "wof:name":"Nu\u00f1ez Pascual Eutimia",
    "wof:placetype":"venue"
},
  "geometry": {"coordinates":[-3.1614398956,41.4488792419],"type":"Point"}
}