{
  "type": "Feature",
  "properties": {
    "addr:full":"Avda Alicante, 21 Monforte Cid Alicante 03670",
    "addr:housenumber":"21",
    "addr:postcode":"03670",
    "addr:street":"Avda Alicante",
    "iso:country":"ES",
    "sg:address":"Avda Alicante, 21",
    "sg:city":"Monforte Cid",
    "sg:orig_category":"Reposter\u00cdas",
    "sg:phone":"+34 965 62 15 85",
    "sg:postcode":"03670",
    "sg:province":"Alicante",
    "wof:name":"Miguel Ruiz Emilio",
    "wof:placetype":"venue"
},
  "geometry": {"coordinates":[-0.7286040187,38.3802375793],"type":"Point"}
}