{
  "type": "Feature",
  "properties": {
    "iso:country":"ES",
    "sg:address":"Calle de Salvador Sastre, 4",
    "sg:city":"Valencia",
    "sg:orig_category":"Arquitectos",
    "sg:phone":"+34 963 41 34 77",
    "sg:postcode":"46007",
    "sg:province":"Valencia",
    "wof:name":"Calatrava Fons Isabel Maria",
    "wof:placetype":"venue"
},
  "geometry": {"coordinates":[-0.3816510141,39.4634780884],"type":"Point"}
}