{
  "type": "Feature",
  "properties": {
    "iso:country":"ES",
    "sg:address":"Carrer de Berlin, 105",
    "sg:city":"Barcelona",
    "sg:orig_category":"Zapatos (al Por Menor)",
    "sg:phone":"+34 934 30 10 38",
    "sg:postcode":"08029",
    "sg:province":"Barcelona",
    "wof:name":"Sanchez Gonzalez Antonio",
    "wof:placetype":"venue"
},
  "geometry": {"coordinates":[2.1417069435,41.3851089478],"type":"Point"}
}