{
  "type": "Feature",
  "properties": {
    "iso:country":"ES",
    "sg:address":"Calle de Francisco Grandmontagne, 15",
    "sg:city":"Burgos",
    "sg:orig_category":"Plomeros",
    "sg:phone":"+34 947 23 29 69",
    "sg:postcode":"09007",
    "sg:province":"Burgos",
    "wof:name":"Madrid Madrid Daniel",
    "wof:placetype":"venue"
},
  "geometry": {"coordinates":[-3.6697518826,42.3508262634],"type":"Point"}
}