{
  "type": "Feature",
  "properties": {
    "addr:full":"Calle de Barcelona, 11 Arganda Madrid 28500",
    "addr:housenumber":"11",
    "addr:postcode":"28500",
    "addr:street":"Calle De Barcelona",
    "iso:country":"ES",
    "sg:address":"Calle de Barcelona, 11",
    "sg:city":"Arganda",
    "sg:orig_category":"Papel (al Por Mayor)",
    "sg:phone":"+34 918 71 64 30",
    "sg:postcode":"28500",
    "sg:province":"Madrid",
    "wof:name":"J. Campos Manipulados Papel S.l.",
    "wof:placetype":"venue"
},
  "geometry": {"coordinates":[-3.4546301365,40.3067893982],"type":"Point"}
}