{
  "type": "Feature",
  "properties": {
    "iso:country":"ES",
    "sg:address":"Calle de Gobernador, 93",
    "sg:city":"Castellon",
    "sg:orig_category":"M\u00c9dicos: Cirug\u00cda Pl\u00c1stica, Reconstructiva Y Est\u00c9tica",
    "sg:phone":"+34 964 23 46 04",
    "sg:postcode":"12003",
    "sg:province":"Castell\u00f3n",
    "wof:name":"Pascual De La Torre Pilar",
    "wof:placetype":"venue"
},
  "geometry": {"coordinates":[-0.0339062996,39.98695755],"type":"Point"}
}