{
  "type": "Feature",
  "properties": {
    "iso:country":"ES",
    "sg:address":"Calle de Uhagon Felipe Alcalde, 1",
    "sg:city":"Bilbao",
    "sg:orig_category":"Inmobiliaria (agencias)",
    "sg:phone":"+34 944 10 33 36",
    "sg:postcode":"48010",
    "sg:province":"Vizcaya",
    "wof:name":"Brates S.l.",
    "wof:placetype":"venue"
},
  "geometry": {"coordinates":[-2.9386909008,43.2588043213],"type":"Point"}
}