{
  "type": "Feature",
  "properties": {
    "addr:full":"Avda Toreros (de Los), 16 Mejorada Campo Madrid 28840",
    "addr:housenumber":"16",
    "addr:postcode":"28840",
    "addr:street":"Avda Toreros De Los",
    "iso:country":"ES",
    "sg:address":"Avda Toreros (de Los), 16",
    "sg:city":"Mejorada Campo",
    "sg:orig_category":"Agencias Y Agentes Comerciales, Representantes",
    "sg:phone":"+34 916 68 01 14",
    "sg:postcode":"28840",
    "sg:province":"Madrid",
    "wof:name":"Matias Aznal Patricia",
    "wof:placetype":"venue"
},
  "geometry": {"coordinates":[-3.4867138863,40.3999671936],"type":"Point"}
}