{
  "type": "Feature",
  "properties": {
    "iso:country":"ES",
    "sg:address":"Rbla Sant Sebastia, 32",
    "sg:city":"Santa Coloma De Gramenet",
    "sg:orig_category":"Promotores Constructores",
    "sg:phone":"+34 934 66 53 39",
    "sg:postcode":"08922",
    "sg:province":"Barcelona",
    "wof:name":"Rambla San Sebastian 1997 S.l.",
    "wof:placetype":"venue"
},
  "geometry": {"coordinates":[2.2108180523,41.4506568909],"type":"Point"}
}