{
  "type": "Feature",
  "properties": {
    "addr:full":"Calle de Marques Del Llano, 3 Langreo Asturias 33930",
    "addr:housenumber":"3",
    "addr:postcode":"33930",
    "addr:street":"Calle De Marques Del Llano",
    "iso:country":"ES",
    "sg:address":"Calle de Marques Del Llano, 3",
    "sg:city":"Langreo",
    "sg:orig_category":"Comercio De Hierro",
    "sg:phone":"+34 985 69 18 08",
    "sg:postcode":"33930",
    "sg:province":"Asturias",
    "wof:name":"Hierros Jove Garcia S.l.",
    "wof:placetype":"venue"
},
  "geometry": {"coordinates":[-5.7000470161,43.3149986267],"type":"Point"}
}