{
  "type": "Feature",
  "properties": {
    "iso:country":"ES",
    "sg:address":"Avda Luis Movilla, 12",
    "sg:city":"Badajoz",
    "sg:orig_category":"Material Y Suministros Para Fotocopiadoras, Reprograf\u00cda",
    "sg:phone":"+34 924 23 28 12",
    "sg:postcode":"06011",
    "sg:province":"Badajoz",
    "wof:name":"Digital-repro Copiadoras S.l.u.",
    "wof:placetype":"venue"
},
  "geometry": {"coordinates":[-7.1200389862,38.803768158],"type":"Point"}
}