{
  "type": "Feature",
  "properties": {
    "addr:full":"Plaz Alberto Ballarin, 16 Albalatillo Huesca 22220",
    "addr:housenumber":"16",
    "addr:postcode":"22220",
    "addr:street":"Ballarin",
    "iso:country":"ES",
    "sg:address":"Plaz Alberto Ballarin, 16",
    "sg:city":"Albalatillo",
    "sg:orig_category":"Transportes Por Carretera: Lotes Completos, Mercanc\u00cdas Diversas",
    "sg:phone":"+34 974 57 28 58",
    "sg:postcode":"22220",
    "sg:province":"Huesca",
    "wof:name":"Pueyo Asin Maria Cruz",
    "wof:placetype":"venue"
},
  "geometry": {"coordinates":[-0.1512839943,41.7356643677],"type":"Point"}
}