{
  "type": "Feature",
  "properties": {
    "addr:full":"Psaj Ventura Feliu, 21 Valencia Valencia 46007",
    "addr:housenumber":"21",
    "addr:postcode":"46007",
    "addr:street":"Feliu",
    "iso:country":"ES",
    "sg:address":"Psaj Ventura Feliu, 21",
    "sg:city":"Valencia",
    "sg:orig_category":"M\u00c9dicos: Pediatr\u00cda. Enfermedades De Los Ni\u00d1os",
    "sg:phone":"+34 963 41 25 82",
    "sg:postcode":"46007",
    "sg:province":"Valencia",
    "wof:name":"Benedito Lopez Joaquin",
    "wof:placetype":"venue"
},
  "geometry": {"coordinates":[-0.3843759894,39.4623794556],"type":"Point"}
}