{
  "type": "Feature",
  "properties": {
    "addr:full":"Calle de Juana Elorza, 2 Madrid Madrid 28053",
    "addr:housenumber":"2",
    "addr:postcode":"28053",
    "addr:street":"Calle De Juana Elorza",
    "iso:country":"ES",
    "sg:address":"Calle de Juana Elorza, 2",
    "sg:city":"Madrid",
    "sg:orig_category":"Molduras, Junquillos, Listones Y Molduras Perforadas",
    "sg:phone":"+34 914 78 50 65",
    "sg:postcode":"28053",
    "sg:province":"Madrid",
    "wof:name":"Lopez Moire Andres Jesus",
    "wof:placetype":"venue"
},
  "geometry": {"coordinates":[-3.666476965,40.3929176331],"type":"Point"}
}