{
  "type": "Feature",
  "properties": {
    "addr:full":"La Industria (p Girasoles), 8 Camas Sevilla 41900",
    "addr:housenumber":"8",
    "addr:postcode":"41900",
    "addr:street":"Girasoles",
    "iso:country":"ES",
    "sg:address":"La Industria (p Girasoles), 8",
    "sg:city":"Camas",
    "sg:orig_category":"Panader\u00cdas, Panader\u00cdas",
    "sg:phone":"+34 954 39 00 69",
    "sg:postcode":"41900",
    "sg:province":"Sevilla",
    "wof:name":"Confiteria La Campana S.a.",
    "wof:placetype":"venue"
},
  "geometry": {"coordinates":[-6.0344491005,37.4007263184],"type":"Point"}
}