{
  "type": "Feature",
  "properties": {
    "iso:country":"ES",
    "sg:address":"Calle de Adarga, 2",
    "sg:city":"Alcala Henares",
    "sg:orig_category":"Centros De Educaci\u00d3n Especial",
    "sg:phone":"+34 918 81 18 71",
    "sg:postcode":"28805",
    "sg:province":"Madrid",
    "wof:name":"Colegio Publico Cristobal Colon",
    "wof:placetype":"venue"
},
  "geometry": {"coordinates":[-3.3584709167,40.4887390137],"type":"Point"}
}