{
  "type": "Feature",
  "properties": {
    "addr:full":"Avda Cuenca (de), 8 Quintanar Rey Cuenca 16220",
    "addr:housenumber":"8",
    "addr:postcode":"16220",
    "addr:street":"Avda Cuenca De;Rey",
    "iso:country":"ES",
    "sg:address":"Avda Cuenca (de), 8",
    "sg:city":"Quintanar Rey",
    "sg:orig_category":"Notarios",
    "sg:phone":"+34 967 49 65 43",
    "sg:postcode":"16220",
    "sg:province":"Cuenca",
    "wof:name":"Falcon Romero Antonio",
    "wof:placetype":"venue"
},
  "geometry": {"coordinates":[-1.930783987,39.343788147],"type":"Point"}
}