{
  "type": "Feature",
  "properties": {
    "addr:full":"Carrer de Verge De L'esperanca, 17 Crevillent Alicante 03330",
    "addr:housenumber":"17",
    "addr:postcode":"03330",
    "addr:street":"Carrer De Verge De L'Esperanca",
    "iso:country":"ES",
    "sg:address":"Carrer de Verge De L'esperanca, 17",
    "sg:city":"Crevillent",
    "sg:orig_category":"Inform\u00c1tica, Ofim\u00c1tica (estudios, Asesor\u00cda, Ingenier\u00cda, Formaci\u00d3n)",
    "sg:phone":"+34 965 40 46 19",
    "sg:postcode":"03330",
    "sg:province":"Alicante",
    "wof:name":"Casanova Serna Federico Bartolome",
    "wof:placetype":"venue"
},
  "geometry": {"coordinates":[-0.8073160052,38.2464752197],"type":"Point"}
}