{
  "type": "Feature",
  "properties": {
    "iso:country":"ES",
    "sg:address":"Calle de Beatriz (de), 3",
    "sg:city":"Mejorada Campo",
    "sg:orig_category":"Venta, Instalaci\u00d3n De Calefacci\u00d3n",
    "sg:phone":"+34 916 79 14 90",
    "sg:postcode":"28840",
    "sg:province":"Madrid",
    "wof:name":"Diez Y Lozano C.b.",
    "wof:placetype":"venue"
},
  "geometry": {"coordinates":[-3.4868514538,40.3989295959],"type":"Point"}
}