{
  "type": "Feature",
  "properties": {
    "addr:full":"Pque Nicolas Salmeron (de), 46 Almeria Almer\u00eda 04002",
    "addr:postcode":"04002",
    "addr:street":"Salmeron;Almeri\u0301A",
    "iso:country":"ES",
    "sg:address":"Pque Nicolas Salmeron (de), 46",
    "sg:city":"Almeria",
    "sg:orig_category":"Servicios De Telecomunicaciones",
    "sg:phone":"+34 950 25 10 00",
    "sg:postcode":"04002",
    "sg:province":"Almer\u00eda",
    "sg:website":"www.tesur.com",
    "wof:name":"Rios Beltran Miguel",
    "wof:placetype":"venue"
},
  "geometry": {"coordinates":[-2.4719970226,36.8376541138],"type":"Point"}
}