{
  "type": "Feature",
  "properties": {
    "iso:country":"ES",
    "sg:address":"Carr Quartera, 4",
    "sg:city":"Alcudia",
    "sg:orig_category":"Autob\u00das (explotaci\u00d3n Y Servicios De)",
    "sg:phone":"+34 971 54 62 60",
    "sg:postcode":"07400",
    "sg:province":"Islas Baleares",
    "wof:name":"Autocares Class Labour S.l.",
    "wof:placetype":"venue"
},
  "geometry": {"coordinates":[3.121515274,39.853515625],"type":"Point"}
}