{
  "type": "Feature",
  "properties": {
    "addr:full":"Carr Sant Antoni, 21 Borrassa Girona 17770",
    "addr:housenumber":"21",
    "addr:postcode":"17770",
    "addr:street":"Carr Sant Antoni",
    "iso:country":"ES",
    "sg:address":"Carr Sant Antoni, 21",
    "sg:city":"Borrassa",
    "sg:orig_category":"Dibujo",
    "sg:phone":"+34 972 52 58 70",
    "sg:postcode":"17770",
    "sg:province":"Girona",
    "wof:name":"Queja Leal Luis Miguel",
    "wof:placetype":"venue"
},
  "geometry": {"coordinates":[2.9224729538,42.2209815979],"type":"Point"}
}