{
  "type": "Feature",
  "properties": {
    "addr:full":"Carrer de Galceran Marquet, 4 Cambrils Tarragona 43850",
    "addr:housenumber":"4",
    "addr:postcode":"43850",
    "addr:street":"Carrer De Galceran Marquet",
    "iso:country":"ES",
    "sg:address":"Carrer de Galceran Marquet, 4",
    "sg:city":"Cambrils",
    "sg:orig_category":"Compraventa De Antig\u00dcedades",
    "sg:phone":"+34 977 79 27 57",
    "sg:postcode":"43850",
    "sg:province":"Tarragona",
    "wof:name":"Aita Tetauen S.l.",
    "wof:placetype":"venue"
},
  "geometry": {"coordinates":[1.0649296045,41.0669364929],"type":"Point"}
}