{
  "type": "Feature",
  "properties": {
    "iso:country":"ES",
    "sg:address":"Carrer de Blai, 46",
    "sg:city":"Barcelona",
    "sg:orig_category":"Carnicer\u00cdas, Carnicer\u00cdas",
    "sg:phone":"+34 934 42 48 35",
    "sg:postcode":"08004",
    "sg:province":"Barcelona",
    "wof:name":"Dukina S.l",
    "wof:placetype":"venue"
},
  "geometry": {"coordinates":[2.1633610725,41.3742675781],"type":"Point"}
}