{
  "type": "Feature",
  "properties": {
    "addr:full":"Carrer de Vistalegre, 72 Cornella Llobregat Barcelona 08940",
    "addr:housenumber":"72",
    "addr:postcode":"08940",
    "addr:street":"Carrer De Vistalegre",
    "iso:country":"ES",
    "sg:address":"Carrer de Vistalegre, 72",
    "sg:city":"Cornella Llobregat",
    "sg:orig_category":"Perfumer\u00cda (al Por Menor)",
    "sg:phone":"+34 933 76 12 98",
    "sg:postcode":"08940",
    "sg:province":"Barcelona",
    "wof:name":"Fortea Vilapri\u00f1o Jordi",
    "wof:placetype":"venue"
},
  "geometry": {"coordinates":[2.0773890018,41.3641738892],"type":"Point"}
}