{
  "type": "Feature",
  "properties": {
    "addr:full":"Calle de Labaro (el), 3 Santander Cantabria 39007",
    "addr:housenumber":"3",
    "addr:postcode":"39007",
    "addr:street":"Calle De Labaro El",
    "iso:country":"ES",
    "sg:address":"Calle de Labaro (el), 3",
    "sg:city":"Santander",
    "sg:orig_category":"Ense\u00d1anza Variada",
    "sg:phone":"+34 942 23 54 64",
    "sg:postcode":"39007",
    "sg:province":"Cantabria",
    "wof:name":"Mu\u00f1iz Barcena Francisco Javier",
    "wof:placetype":"venue"
},
  "geometry": {"coordinates":[-3.8100090027,43.4614982605],"type":"Point"}
}