{
  "type": "Feature",
  "properties": {
    "iso:country":"ES",
    "sg:address":"Calle de Santisimo Cristo, 18",
    "sg:city":"Rueda",
    "sg:orig_category":"Alimentaci\u00d3n General (al Por Menor)",
    "sg:phone":"+34 983 86 80 26",
    "sg:postcode":"47490",
    "sg:province":"Valladolid",
    "wof:name":"Crespo Rodriguez Francisco",
    "wof:placetype":"venue"
},
  "geometry": {"coordinates":[-4.9600381851,41.40832901],"type":"Point"}
}