{
  "type": "Feature",
  "properties": {
    "iso:country":"ES",
    "sg:address":"Calle de Pedro Avila, 76",
    "sg:city":"Zarza Granadilla",
    "sg:orig_category":"Quincaller\u00cda (al Por Menor)",
    "sg:phone":"+34 927 48 62 94",
    "sg:postcode":"10710",
    "sg:province":"C\u00e1ceres",
    "wof:name":"Mendez Fernandez Pilar",
    "wof:placetype":"venue"
},
  "geometry": {"coordinates":[-6.0472970009,40.2357788086],"type":"Point"}
}