{
  "type": "Feature",
  "properties": {
    "addr:full":"Calle de Meson De Paredes, 3 Madrid Madrid 28012",
    "addr:housenumber":"3",
    "addr:postcode":"28012",
    "addr:street":"Calle De Meson De Paredes",
    "iso:country":"ES",
    "sg:address":"Calle de Meson De Paredes, 3",
    "sg:city":"Madrid",
    "sg:orig_category":"Carnicer\u00cdas, Carnicer\u00cdas",
    "sg:phone":"+34 913 69 11 64",
    "sg:postcode":"28012",
    "sg:province":"Madrid",
    "wof:name":"Nieto Gomez Celestino",
    "wof:placetype":"venue"
},
  "geometry": {"coordinates":[-3.7050709724,40.411819458],"type":"Point"}
}