{
  "type": "Feature",
  "properties": {
    "iso:country":"ES",
    "sg:address":"Carr Pescadors, 54",
    "sg:city":"Cullera",
    "sg:orig_category":"M\u00c9dicos: Medicina Manual",
    "sg:phone":"+34 961 73 00 72",
    "sg:postcode":"46400",
    "sg:province":"Valencia",
    "wof:name":"Martinez Molina Juan",
    "wof:placetype":"venue"
},
  "geometry": {"coordinates":[-0.2535629869,39.1624107361],"type":"Point"}
}