{
  "type": "Feature",
  "properties": {
    "addr:full":"Calle de Gabriel Miro, 34 Linea De La Concepcion C\u00e1diz 11300",
    "addr:housenumber":"34",
    "addr:postcode":"11300",
    "addr:street":"Calle De Gabriel Miro;Ca\u0301Diz",
    "iso:country":"ES",
    "sg:address":"Calle de Gabriel Miro, 34",
    "sg:city":"Linea De La Concepcion",
    "sg:orig_category":"Empresas De Vigilancia, Guardia Y Protecci\u00d3n",
    "sg:phone":"+34 956 17 01 18",
    "sg:postcode":"11300",
    "sg:province":"C\u00e1diz",
    "wof:name":"Formacion De Seguridad Servicios & Consultoria Campo Gibraltar S.l.",
    "wof:placetype":"venue"
},
  "geometry": {"coordinates":[-5.3501310349,36.1704406738],"type":"Point"}
}