{
  "type": "Feature",
  "properties": {
    "addr:full":"Calle de San Francisco, 4 Andujar Ja\u00e9n 23740",
    "addr:housenumber":"4",
    "addr:postcode":"23740",
    "addr:street":"Calle De San Francisco",
    "iso:country":"ES",
    "sg:address":"Calle de San Francisco, 4",
    "sg:city":"Andujar",
    "sg:orig_category":"Abogados",
    "sg:phone":"+34 953 51 13 05",
    "sg:postcode":"23740",
    "sg:province":"Ja\u00e9n",
    "wof:name":"Toribio Castro Catalina",
    "wof:placetype":"venue"
},
  "geometry": {"coordinates":[-4.0552787781,38.0401496887],"type":"Point"}
}