{
  "type": "Feature",
  "properties": {
    "iso:country":"ES",
    "sg:address":"Via Dos Castillas (de Las), 11",
    "sg:city":"Pozuelo De Alarcon",
    "sg:orig_category":"Centros Empresariales",
    "sg:phone":"+34 913 51 49 60",
    "sg:postcode":"28224",
    "sg:province":"Madrid",
    "wof:name":"Carazo San Jose Julio",
    "wof:placetype":"venue"
},
  "geometry": {"coordinates":[-3.8014309406,40.4328041077],"type":"Point"}
}