{
  "type": "Feature",
  "properties": {
    "addr:full":"Avda Estacion, S/n Medina Campo Valladolid 47400",
    "addr:postcode":"47400",
    "addr:street":"Avda Estacion S / N Medina",
    "iso:country":"ES",
    "sg:address":"Avda Estacion, S/n",
    "sg:city":"Medina Campo",
    "sg:orig_category":"Electrodom\u00c9sticos (al Por Menor)",
    "sg:phone":"+34 983 81 18 45",
    "sg:postcode":"47400",
    "sg:province":"Valladolid",
    "wof:name":"Carrasco Ortega Candido Manuel",
    "wof:placetype":"venue"
},
  "geometry": {"coordinates":[-4.9101190567,41.3157539368],"type":"Point"}
}