{
  "type": "Feature",
  "properties": {
    "iso:country":"ES",
    "sg:address":"Calle de Arteaga, 9",
    "sg:city":"Sartaguda",
    "sg:orig_category":"Cr\u00cda De Animales",
    "sg:phone":"+34 948 66 71 83",
    "sg:postcode":"31589",
    "sg:province":"Navarra",
    "wof:name":"Sesma Martinez Julio",
    "wof:placetype":"venue"
},
  "geometry": {"coordinates":[-2.0594990253,42.382522583],"type":"Point"}
}