{
  "type": "Feature",
  "properties": {
    "iso:country":"ES",
    "sg:address":"Trva Bouzas Servicio Portuario, S/n",
    "sg:city":"Vigo",
    "sg:orig_category":"Ingenier\u00cda, Centros De Estudios (diversos)",
    "sg:phone":"+34 986 20 96 48",
    "sg:postcode":"36208",
    "sg:province":"Pontevedra",
    "wof:name":"Aitodetec S.l.",
    "wof:placetype":"venue"
},
  "geometry": {"coordinates":[-8.7550001144,42.2251739502],"type":"Point"}
}