{
  "type": "Feature",
  "properties": {
    "iso:country":"ES",
    "sg:address":"Calle de Fuente Del Ibon, 10",
    "sg:city":"Huesca",
    "sg:orig_category":"Electricidad: Instaladores",
    "sg:phone":"+34 974 21 33 05",
    "sg:postcode":"22003",
    "sg:province":"Huesca",
    "wof:name":"Electricidad Ibon S.l.",
    "wof:placetype":"venue"
},
  "geometry": {"coordinates":[-0.4151340127,42.1347503662],"type":"Point"}
}