{
  "type": "Feature",
  "properties": {
    "iso:country":"ES",
    "sg:address":"Prag Arbusset, S/n",
    "sg:city":"Palou",
    "sg:orig_category":"Importaci\u00d3n, Exportaci\u00d3n Y Comercios De Productos Textiles",
    "sg:phone":"+34 972 43 01 23",
    "sg:postcode":"17170",
    "sg:province":"Girona",
    "sg:website":"www.yutrensa.com",
    "wof:name":"Manufacturats Jonquera S.l.",
    "wof:placetype":"venue"
},
  "geometry": {"coordinates":[2.6044440269,42.0092544556],"type":"Point"}
}