{
  "type": "Feature",
  "properties": {
    "addr:full":"Pl Pep Ventura, 11 Badalona Barcelona 08912",
    "addr:housenumber":"11",
    "addr:postcode":"08912",
    "addr:street":"Pl;Ventura",
    "iso:country":"ES",
    "sg:address":"Pl Pep Ventura, 11",
    "sg:city":"Badalona",
    "sg:orig_category":"Bisuter\u00cda, Joyer\u00cda, Relojer\u00cda (al Por Menor)",
    "sg:phone":"+34 933 87 50 94",
    "sg:postcode":"08912",
    "sg:province":"Barcelona",
    "wof:name":"Domenech Maisanava Jose",
    "wof:placetype":"venue"
},
  "geometry": {"coordinates":[2.2402560711,41.445766449],"type":"Point"}
}