{
  "type": "Feature",
  "properties": {
    "addr:full":"Calle de Alonso Barba, 16 Alcala Henares Madrid 28806",
    "addr:housenumber":"16",
    "addr:postcode":"28806",
    "addr:street":"Calle De Alonso Barba",
    "iso:country":"ES",
    "sg:address":"Calle de Alonso Barba, 16",
    "sg:city":"Alcala Henares",
    "sg:orig_category":"Colchones (fabricaci\u00d3n, Al Por Mayor, Al Por Menor)",
    "sg:phone":"+34 918 80 26 62",
    "sg:postcode":"28806",
    "sg:province":"Madrid",
    "sg:website":"www.eurocolchon.es",
    "wof:name":"Colchonerias Alcala S. L.",
    "wof:placetype":"venue"
},
  "geometry": {"coordinates":[-3.4037153721,40.4894828796],"type":"Point"}
}