{
  "type": "Feature",
  "properties": {
    "iso:country":"ES",
    "sg:address":"Calle de Reyes Catolicos, 46",
    "sg:city":"Castalla",
    "sg:orig_category":"Contenedores (mercanc\u00cdas)",
    "sg:phone":"+34 965 56 10 32",
    "sg:postcode":"03420",
    "sg:province":"Alicante",
    "wof:name":"Trans-perkins S.l.",
    "wof:placetype":"venue"
},
  "geometry": {"coordinates":[-0.669836998,38.5926589966],"type":"Point"}
}