{
  "type": "Feature",
  "properties": {
    "iso:country":"ES",
    "sg:address":"Centro Comercial Copo, S/n",
    "sg:city":"Ejido",
    "sg:orig_category":"Muebles Y Accesorios Para Cocinas Y Cuartos De Ba\u00d1o (al Por Menor)",
    "sg:phone":"+34 950 57 02 38",
    "sg:postcode":"04700",
    "sg:province":"Almer\u00eda",
    "wof:name":"Murgi Cocinas Color Y Dise\u00f1o S.l.l.",
    "wof:placetype":"venue"
},
  "geometry": {"coordinates":[-2.8176040649,36.7727012634],"type":"Point"}
}