{
  "type": "Feature",
  "properties": {
    "addr:full":"Avda Vicente Aleixandre, 13 Segovia Segovia 40006",
    "addr:housenumber":"13",
    "addr:postcode":"40006",
    "addr:street":"Avda Vicente Aleixandre",
    "iso:country":"ES",
    "sg:address":"Avda Vicente Aleixandre, 13",
    "sg:city":"Segovia",
    "sg:orig_category":"Farmacias",
    "sg:phone":"+34 921 44 23 66",
    "sg:postcode":"40006",
    "sg:province":"Segovia",
    "wof:name":"Pi\u00f1uela Martin Maria Paz",
    "wof:placetype":"venue"
},
  "geometry": {"coordinates":[-4.1010432243,40.9299850464],"type":"Point"}
}