{
  "type": "Feature",
  "properties": {
    "addr:full":"Carr Sant Josep De Calassan\u00c7, 10 Algemesi Valencia 46680",
    "addr:housenumber":"10",
    "addr:postcode":"46680",
    "addr:street":"Carr Sant Josep De Calassanc\u0327",
    "iso:country":"ES",
    "sg:address":"Carr Sant Josep De Calassan\u00c7, 10",
    "sg:city":"Algemesi",
    "sg:orig_category":"Agencias De Viajes",
    "sg:phone":"+34 962 48 35 84",
    "sg:postcode":"46680",
    "sg:province":"Valencia",
    "wof:name":"Chambo Candel S.l.",
    "wof:placetype":"venue"
},
  "geometry": {"coordinates":[-0.4387719929,39.1892738342],"type":"Point"}
}