{
  "type": "Feature",
  "properties": {
    "addr:full":"Calle de Dionisio Ridruejo, 1 Oviedo Asturias 33008",
    "addr:housenumber":"1",
    "addr:postcode":"33008",
    "addr:street":"Calle De Dionisio Ridruejo",
    "iso:country":"ES",
    "sg:address":"Calle de Dionisio Ridruejo, 1",
    "sg:city":"Oviedo",
    "sg:orig_category":"Delineantes",
    "sg:phone":"+34 985 27 06 33",
    "sg:postcode":"33008",
    "sg:province":"Asturias",
    "wof:name":"Dise\u00f1o Y Produccion Artistica Nador S.l.",
    "wof:placetype":"venue"
},
  "geometry": {"coordinates":[-5.8472409248,43.3548736572],"type":"Point"}
}