{
  "type": "Feature",
  "properties": {
    "iso:country":"ES",
    "sg:address":"Calle de Gallo, 14",
    "sg:city":"Valladolid",
    "sg:orig_category":"Frutas, Legumbres Frescas Y Tempranas (al Por Menor)",
    "sg:phone":"+34 983 39 72 09",
    "sg:postcode":"47012",
    "sg:province":"Valladolid",
    "wof:name":"Dieguez San Jose Javier",
    "wof:placetype":"venue"
},
  "geometry": {"coordinates":[-4.7085909843,41.6461410522],"type":"Point"}
}