{
  "type": "Feature",
  "properties": {
    "iso:country":"ES",
    "sg:address":"Carrer de Gran, 70",
    "sg:city":"Esparreguera",
    "sg:orig_category":"Quincaller\u00cda (al Por Menor)",
    "sg:phone":"+34 937 77 13 38",
    "sg:postcode":"08292",
    "sg:province":"Barcelona",
    "wof:name":"Cusco Estruch Josep",
    "wof:placetype":"venue"
},
  "geometry": {"coordinates":[1.8689869642,41.5404052734],"type":"Point"}
}