{
  "type": "Feature",
  "properties": {
    "addr:full":"Pl Jacint Verdaguer (d'en), 10 Tarragona Tarragona 43003",
    "addr:housenumber":"10",
    "addr:postcode":"43003",
    "addr:street":"Pl Jacint Verdaguer D'En",
    "iso:country":"ES",
    "sg:address":"Pl Jacint Verdaguer (d'en), 10",
    "sg:city":"Tarragona",
    "sg:orig_category":"Abogados",
    "sg:phone":"+34 977 23 76 30",
    "sg:postcode":"43003",
    "sg:province":"Tarragona",
    "wof:name":"Lopez Sebastian Teodoro Ladislao",
    "wof:placetype":"venue"
},
  "geometry": {"coordinates":[1.2549020052,41.115272522],"type":"Point"}
}