{
  "type": "Feature",
  "properties": {
    "addr:full":"Prje Rubial, S/n Villena Alicante 03400",
    "addr:housenumber":"s / n",
    "addr:postcode":"03400",
    "iso:country":"ES",
    "sg:address":"Prje Rubial, S/n",
    "sg:city":"Villena",
    "sg:orig_category":"Promotores Constructores",
    "sg:phone":"+34 965 80 51 00",
    "sg:postcode":"03400",
    "sg:province":"Alicante",
    "sg:website":"www.dimasadis.com",
    "wof:name":"Dimasa S.l.",
    "wof:placetype":"venue"
},
  "geometry": {"coordinates":[-0.868753016,38.6403503418],"type":"Point"}
}