{
  "type": "Feature",
  "properties": {
    "iso:country":"ES",
    "sg:address":"Pol Ind Congost, S/n",
    "sg:city":"Llerona",
    "sg:orig_category":"Grabados Y Decoraci\u00d3n De Metales",
    "sg:phone":"+34 938 46 70 07",
    "sg:postcode":"08520",
    "sg:province":"Barcelona",
    "sg:website":"www.ctt-industrial.com",
    "wof:name":"Ctt-stronghold S.a.",
    "wof:placetype":"venue"
},
  "geometry": {"coordinates":[2.2992899418,41.6361808777],"type":"Point"}
}