{
  "type": "Feature",
  "properties": {
    "iso:country":"ES",
    "sg:address":"Calle de Sestercio, 9",
    "sg:city":"Fuente Del Rey",
    "sg:classifiers":[
        {
            "category":"Manufacturing",
            "subcategory":"Building Materials",
            "type":"Manufacturing & Wholesale Goods"
        }
    ],
    "sg:phone":"+34 954 93 16 90",
    "sg:postcode":"41700",
    "sg:province":"Sevilla",
    "sg:tags":[
        "cemento",
        "y",
        "de",
        "fabricaci\u00d3n",
        "cal"
    ],
    "sg:website":"www.weber-cemarksa.es",
    "wof:name":"Saint-gobain Weber Cemarksa S.a.",
    "wof:placetype":"venue"
},
  "geometry": {"coordinates":[-5.9756040573,37.3112182617],"type":"Point"}
}