{
  "type": "Feature",
  "properties": {
    "addr:full":"Av Matadepera, 113 Sabadell Barcelona 08207",
    "addr:housenumber":"113",
    "addr:postcode":"08207",
    "addr:street":"Av Matadepera",
    "iso:country":"ES",
    "sg:address":"Av Matadepera, 113",
    "sg:city":"Sabadell",
    "sg:classifiers":[
        {
            "category":"Autos & Motor Vehicles",
            "subcategory":"Automobile Sales",
            "type":"Retail Goods"
        }
    ],
    "sg:phone":"+34 937 23 70 18",
    "sg:postcode":"08207",
    "sg:province":"Barcelona",
    "wof:name":"Autoescuela Girbau S.l.",
    "wof:placetype":"venue"
},
  "geometry": {"coordinates":[2.088973999,41.566493988],"type":"Point"}
}