{
  "type": "Feature",
  "properties": {
    "iso:country":"ES",
    "sg:address":"Brion(leiro), S/n",
    "sg:city":"Brion",
    "sg:classifiers":[
        {
            "category":"Taxi",
            "type":"Transportation"
        }
    ],
    "sg:phone":"+34 981 86 06 87",
    "sg:postcode":"15920",
    "sg:province":"La Coru\u00f1a",
    "wof:name":"Abuin Lopez Luis",
    "wof:placetype":"venue"
},
  "geometry": {"coordinates":[-8.794599,42.645992],"type":"Point"}
}