{
  "type": "Feature",
  "properties": {
    "addr:full":"Cm Vell Vila Real-onda, 279 Vila-real Castell\u00f3n 12540",
    "addr:housenumber":"279;castello\u0301n",
    "addr:postcode":"12540",
    "addr:street":"Vila-Real",
    "iso:country":"ES",
    "sg:address":"Cm Vell Vila Real-onda, 279",
    "sg:city":"Vila-real",
    "sg:orig_category":"Inmobiliaria (agencias)",
    "sg:phone":"+34 964 52 08 33",
    "sg:postcode":"12540",
    "sg:province":"Castell\u00f3n",
    "wof:name":"Rijume Tres S.l.",
    "wof:placetype":"venue"
},
  "geometry": {"coordinates":[-0.0952899978,39.9453010559],"type":"Point"}
}