{
  "type": "Feature",
  "properties": {
    "addr:full":"Rua Padre Feijoo, 15 Ourense Ourense 32005",
    "addr:housenumber":"15",
    "addr:postcode":"32005",
    "addr:street":"Rua Padre Feijoo",
    "iso:country":"ES",
    "sg:address":"Rua Padre Feijoo, 15",
    "sg:city":"Ourense",
    "sg:orig_category":"Farmacias",
    "sg:phone":"+34 988 22 24 43",
    "sg:postcode":"32005",
    "sg:province":"Ourense",
    "wof:name":"Bayon Nieto Alfonso",
    "wof:placetype":"venue"
},
  "geometry": {"coordinates":[-7.8519001007,42.3053703308],"type":"Point"}
}