{
  "type": "Feature",
  "properties": {
    "iso:country":"ES",
    "sg:address":"Estd Ourense (de), S/n",
    "sg:city":"Pazos",
    "sg:orig_category":"Negocio De Materiales De Construcci\u00d3n",
    "sg:phone":"+34 988 41 21 30",
    "sg:postcode":"32619",
    "sg:province":"Ourense",
    "wof:name":"Atallo Verin Sociedad Anonima Laboral",
    "wof:placetype":"venue"
},
  "geometry": {"coordinates":[-7.4528098106,41.9391326904],"type":"Point"}
}