{
  "type": "Feature",
  "properties": {
    "iso:country":"ES",
    "sg:address":"Calle de Joan Miro, 1",
    "sg:city":"Pinto",
    "sg:orig_category":"Ropa Para Ni\u00d1os (al Por Menor)",
    "sg:phone":"+34 916 92 45 53",
    "sg:postcode":"28320",
    "sg:province":"Madrid",
    "wof:name":"Diaz Albarran Soledad",
    "wof:placetype":"venue"
},
  "geometry": {"coordinates":[-3.6988840103,40.2392921448],"type":"Point"}
}