{
  "type": "Feature",
  "properties": {
    "addr:full":"Avgd Diagonal Del Pais Valencia, 10 Cullera Valencia 46400",
    "addr:housenumber":"10",
    "addr:postcode":"46400",
    "addr:street":"Diagonal Del Pais Valencia",
    "iso:country":"ES",
    "sg:address":"Avgd Diagonal Del Pais Valencia, 10",
    "sg:city":"Cullera",
    "sg:orig_category":"Colchones (fabricaci\u00d3n, Al Por Mayor, Al Por Menor)",
    "sg:phone":"+34 961 72 55 20",
    "sg:postcode":"46400",
    "sg:province":"Valencia",
    "wof:name":"Ruiz Mata Salvador",
    "wof:placetype":"venue"
},
  "geometry": {"coordinates":[-0.2562240064,39.1653251648],"type":"Point"}
}