{
  "type": "Feature",
  "properties": {
    "iso:country":"ES",
    "sg:address":"Pl Vila, 11",
    "sg:city":"S. Adria Besos",
    "sg:orig_category":"Diarios, Revistas Y Boletines (distribuidores)",
    "sg:phone":"+34 933 81 93 92",
    "sg:postcode":"08930",
    "sg:province":"Barcelona",
    "wof:name":"Maurel Simon Lidia",
    "wof:placetype":"venue"
},
  "geometry": {"coordinates":[2.2185299397,41.4301795959],"type":"Point"}
}