{
  "type": "Feature",
  "properties": {
    "iso:country":"ES",
    "sg:address":"Viejo, S/n",
    "sg:city":"Puerto Lumbreras",
    "sg:orig_category":"Contenedores (mercanc\u00cdas)",
    "sg:phone":"+34 968 40 22 24",
    "sg:postcode":"30890",
    "sg:province":"Murcia",
    "wof:name":"Tradomi S.l.",
    "wof:placetype":"venue"
},
  "geometry": {"coordinates":[-1.7983789444,37.5690803528],"type":"Point"}
}