{
  "type": "Feature",
  "properties": {
    "iso:country":"ES",
    "sg:address":"Calle de Peque\u00d1a, 4",
    "sg:city":"Iscar",
    "sg:orig_category":"Panader\u00cdas, Pasteler\u00cdas, Boller\u00cda Industriale (fabricaci\u00d3n, Al Por Mayor)",
    "sg:phone":"+34 983 61 16 33",
    "sg:postcode":"47420",
    "sg:province":"Valladolid",
    "wof:name":"Alonso Sanz Vicente",
    "wof:placetype":"venue"
},
  "geometry": {"coordinates":[-4.5339565277,41.359375],"type":"Point"}
}