{
  "type": "Feature",
  "properties": {
    "iso:country":"ES",
    "sg:address":"Calle de San Deogracias, 42",
    "sg:city":"Madrid",
    "sg:orig_category":"Cervecer\u00cdas",
    "sg:phone":"+34 915 08 03 79",
    "sg:postcode":"28044",
    "sg:province":"Madrid",
    "wof:name":"Condes Ruiz Jose",
    "wof:placetype":"venue"
},
  "geometry": {"coordinates":[-3.7609410286,40.3702354431],"type":"Point"}
}