{
  "type": "Feature",
  "properties": {
    "iso:country":"ES",
    "sg:address":"Calle de Mayor, 58",
    "sg:city":"Albacete",
    "sg:orig_category":"Cajas Para Embalar",
    "sg:phone":"+34 967 21 43 97",
    "sg:postcode":"02002",
    "sg:province":"Albacete",
    "wof:name":"Caja Rural De Albacete",
    "wof:placetype":"venue"
},
  "geometry": {"coordinates":[-1.852692008,38.9926452637],"type":"Point"}
}