{
  "type": "Feature",
  "properties": {
    "iso:country":"ES",
    "sg:address":"Plaz Baron De Cortes, 24",
    "sg:city":"Valencia",
    "sg:orig_category":"Animales (al Por Menor)",
    "sg:phone":"+34 963 73 63 87",
    "sg:postcode":"46006",
    "sg:province":"Valencia",
    "wof:name":"Comiave S.l.",
    "wof:placetype":"venue"
},
  "geometry": {"coordinates":[-0.3719590008,39.4624443054],"type":"Point"}
}