{
  "type": "Feature",
  "properties": {
    "iso:country":"ES",
    "sg:address":"Pase Gran Capitan, 64",
    "sg:city":"Salamanca",
    "sg:orig_category":"Mec\u00c1nico Del Autom\u00d3vil",
    "sg:phone":"+34 923 22 63 12",
    "sg:postcode":"37006",
    "sg:province":"Salamanca",
    "wof:name":"Lucas Herrero Juan",
    "wof:placetype":"venue"
},
  "geometry": {"coordinates":[-5.6660518646,40.9758644104],"type":"Point"}
}