{
  "type": "Feature",
  "properties": {
    "addr:full":"Calle de Ibarra, 21 Barakaldo Vizcaya 48901",
    "addr:housenumber":"21",
    "addr:postcode":"48901",
    "addr:street":"Calle De Ibarra",
    "iso:country":"ES",
    "sg:address":"Calle de Ibarra, 21",
    "sg:city":"Barakaldo",
    "sg:classifiers":[
        {
            "category":"Personal",
            "subcategory":"Barber",
            "type":"Services"
        }
    ],
    "sg:phone":"+34 944 37 31 50",
    "sg:postcode":"48901",
    "sg:province":"Vizcaya",
    "sg:tags":[
        "caballeros",
        "de",
        "peluqueros"
    ],
    "wof:name":"Ruiz Trigueros Jose Miguel",
    "wof:placetype":"venue"
},
  "geometry": {"coordinates":[-2.9845609665,43.299747467],"type":"Point"}
}