{
  "type": "Feature",
  "properties": {
    "iso:country":"ES",
    "sg:address":"Poligono Industrial, S/n",
    "sg:city":"Azagra",
    "sg:orig_category":"Fabricaci\u00d3n De Pastas Alimentarias",
    "sg:phone":"+34 948 69 23 17",
    "sg:postcode":"31560",
    "sg:province":"Navarra",
    "wof:name":"Rivas Sobejano Javier",
    "wof:placetype":"venue"
},
  "geometry": {"coordinates":[-1.902402997,42.3164176941],"type":"Point"}
}