{
  "type": "Feature",
  "properties": {
    "iso:country":"ES",
    "sg:address":"Calle de Henao, 16",
    "sg:city":"Bilbao",
    "sg:orig_category":"Electricidad: Instaladores",
    "sg:phone":"+34 944 23 20 04",
    "sg:postcode":"48009",
    "sg:province":"Vizcaya",
    "wof:name":"Luis Ruiz Carretero",
    "wof:placetype":"venue"
},
  "geometry": {"coordinates":[-2.9312999249,43.264629364],"type":"Point"}
}