{
  "type": "Feature",
  "properties": {
    "iso:country":"ES",
    "sg:address":"Calle de Madrid, 7",
    "sg:city":"Majadahonda",
    "sg:orig_category":"Molduras, Junquillos, Listones Y Molduras Perforadas",
    "sg:phone":"+34 916 38 49 63",
    "sg:postcode":"28220",
    "sg:province":"Madrid",
    "wof:name":"Concepcion Caro Joaquin",
    "wof:placetype":"venue"
},
  "geometry": {"coordinates":[-3.8716759682,40.4737854004],"type":"Point"}
}