{
  "type": "Feature",
  "properties": {
    "iso:country":"ES",
    "sg:address":"Carrer de Watt, 8",
    "sg:city":"Terrassa",
    "sg:orig_category":"Inmobiliaria (agencias)",
    "sg:phone":"+34 937 80 55 81",
    "sg:postcode":"08224",
    "sg:province":"Barcelona",
    "wof:name":"Baro Vitoria Montserrat",
    "wof:placetype":"venue"
},
  "geometry": {"coordinates":[2.0071480274,41.5573234558],"type":"Point"}
}