{
  "type": "Feature",
  "properties": {
    "iso:country":"ES",
    "sg:address":"Av. Carlos Iii El Noble, 11",
    "sg:city":"Iru\u00f1a",
    "sg:orig_category":"Centros Empresariales",
    "sg:phone":"+34 948 20 67 76",
    "sg:postcode":"31002",
    "sg:province":"Navarra",
    "sg:website":"www.plantecnologico.com",
    "wof:name":"Agencia Navarra De Innovacion Tecnologica",
    "wof:placetype":"venue"
},
  "geometry": {"coordinates":[-1.6410272121,42.8148536682],"type":"Point"}
}