{
  "type": "Feature",
  "properties": {
    "addr:full":"Ctra Caba\u00d1as, S/n Oca\u00f1a Toledo 45300",
    "addr:housenumber":"s",
    "addr:postcode":"45300",
    "addr:street":"Ctra Caban\u0303As;/ N Ocan\u0303A",
    "iso:country":"ES",
    "sg:address":"Ctra Caba\u00d1as, S/n",
    "sg:city":"Oca\u00f1a",
    "sg:orig_category":"Promotores Constructores",
    "sg:phone":"+34 925 12 00 23",
    "sg:postcode":"45300",
    "sg:province":"Toledo",
    "wof:name":"Biur S.a.",
    "wof:placetype":"venue"
},
  "geometry": {"coordinates":[-3.5018639565,39.9540939331],"type":"Point"}
}