{
  "type": "Feature",
  "properties": {
    "iso:country":"ES",
    "sg:address":"Brancha, 10",
    "sg:city":"Molina Segura",
    "sg:orig_category":"Industria Qu\u00cdmica",
    "sg:phone":"+34 968 38 91 19",
    "sg:postcode":"30500",
    "sg:province":"Murcia",
    "wof:name":"Andrea Universal S.l.",
    "wof:placetype":"venue"
},
  "geometry": {"coordinates":[-1.2075797319,38.0452728271],"type":"Point"}
}