{
  "type": "Feature",
  "properties": {
    "addr:full":"Plaz Poeta Lizardi Plaza., 1 Tolosa Guip\u00f9zcoa 20400",
    "addr:housenumber":"1",
    "addr:postcode":"20400",
    "addr:street":"Plaz;Lizardi Plaza.;Guipu\u0300Zcoa",
    "iso:country":"ES",
    "sg:address":"Plaz Poeta Lizardi Plaza., 1",
    "sg:city":"Tolosa",
    "sg:orig_category":"Asesor\u00cda Sobre Comunicaci\u00d3n De Empresas",
    "sg:phone":"+34 943 65 22 20",
    "sg:postcode":"20400",
    "sg:province":"Guip\u00f9zcoa",
    "wof:name":"Asegurogintza S.l.",
    "wof:placetype":"venue"
},
  "geometry": {"coordinates":[-2.0739951134,43.1339645386],"type":"Point"}
}