{
  "type": "Feature",
  "properties": {
    "iso:country":"ES",
    "sg:address":"Cra Sevilla-p I San Diego, S/n",
    "sg:city":"Huelva",
    "sg:orig_category":"Agentes, Concesionarios Y Sucursales De Veh\u00cdculos",
    "sg:phone":"+34 959 23 50 12",
    "sg:postcode":"21007",
    "sg:province":"Huelva",
    "wof:name":"Onumovil S.a.",
    "wof:placetype":"venue"
},
  "geometry": {"coordinates":[-6.9495940208,37.256313324],"type":"Point"}
}