{
  "type": "Feature",
  "properties": {
    "iso:country":"ES",
    "sg:address":"Pl Espanya, 4",
    "sg:city":"S. Joan Despi",
    "sg:orig_category":"Cajas De Ahorro",
    "sg:phone":"+34 933 73 21 55",
    "sg:postcode":"08970",
    "sg:province":"Barcelona",
    "wof:name":"Caixa D'estalvis Del Penedes",
    "wof:placetype":"venue"
},
  "geometry": {"coordinates":[2.0706489086,41.3694610596],"type":"Point"}
}