{
  "type": "Feature",
  "properties": {
    "addr:full":"Av Levante, 32 Beniparrell Valencia 46469",
    "addr:housenumber":"32",
    "addr:postcode":"46469",
    "addr:street":"Av Levante",
    "iso:country":"ES",
    "sg:address":"Av Levante, 32",
    "sg:city":"Beniparrell",
    "sg:orig_category":"Cajas De Ahorro",
    "sg:phone":"+34 961 20 28 71",
    "sg:postcode":"46469",
    "sg:province":"Valencia",
    "sg:website":"www.lacaixa.es",
    "wof:name":"Caixa D'estalvis I Pensions De Barcelona",
    "wof:placetype":"venue"
},
  "geometry": {"coordinates":[-0.4116789997,39.383228302],"type":"Point"}
}