{
  "type": "Feature",
  "properties": {
    "iso:country":"ES",
    "sg:address":"Carrer de Mossen Jacint Verdaguer, 57",
    "sg:city":"Santa Coloma De Gramenet",
    "sg:orig_category":"Confecci\u00d3n De Ropa Para Caballeros",
    "sg:phone":"+34 933 86 15 75",
    "sg:postcode":"08922",
    "sg:province":"Barcelona",
    "wof:name":"Nieto Fernandez Jesus",
    "wof:placetype":"venue"
},
  "geometry": {"coordinates":[2.2125198841,41.4475708008],"type":"Point"}
}