{
  "type": "Feature",
  "properties": {
    "addr:full":"Calle de Miguel Iscar, 10 Valladolid Valladolid 47001",
    "addr:housenumber":"10",
    "addr:postcode":"47001",
    "addr:street":"Calle De Miguel Iscar",
    "iso:country":"ES",
    "sg:address":"Calle de Miguel Iscar, 10",
    "sg:city":"Valladolid",
    "sg:orig_category":"Fotograf\u00cda Art\u00cdstica Y Retratos",
    "sg:phone":"+34 983 39 63 47",
    "sg:postcode":"47001",
    "sg:province":"Valladolid",
    "wof:name":"Laforga Gonzalez Luis",
    "wof:placetype":"venue"
},
  "geometry": {"coordinates":[-4.7271690369,41.6483421326],"type":"Point"}
}