{
  "type": "Feature",
  "properties": {
    "iso:country":"ES",
    "sg:address":"Masti-loidi, 14 C",
    "sg:city":"Errenteria",
    "sg:orig_category":"Cristaler\u00cdas",
    "sg:phone":"+34 943 51 66 97",
    "sg:postcode":"20100",
    "sg:province":"Guip\u00f9zcoa",
    "wof:name":"Cristalerias Oarso, S.l.",
    "wof:placetype":"venue"
},
  "geometry": {"coordinates":[-1.8970370293,43.3210067749],"type":"Point"}
}