{
  "type": "Feature",
  "properties": {
    "addr:full":"Calle de Ramon Y Cajal, 12 Entrego Asturias 33940",
    "addr:housenumber":"12",
    "addr:postcode":"33940",
    "addr:street":"Calle De Ramon Y Cajal",
    "iso:country":"ES",
    "sg:address":"Calle de Ramon Y Cajal, 12",
    "sg:city":"Entrego",
    "sg:orig_category":"Art\u00cdculos De Decoraci\u00d3n",
    "sg:phone":"+34 985 66 08 78",
    "sg:postcode":"33940",
    "sg:province":"Asturias",
    "wof:name":"Garcia Suarez Joaquin",
    "wof:placetype":"venue"
},
  "geometry": {"coordinates":[-5.6388039589,43.28723526],"type":"Point"}
}