{
  "type": "Feature",
  "properties": {
    "iso:country":"ES",
    "sg:address":"Rua Evaristo Correa Calderon, S/n",
    "sg:city":"Baralla",
    "sg:orig_category":"Farmacias",
    "sg:phone":"+34 982 36 33 05",
    "sg:postcode":"27680",
    "sg:province":"Lugo",
    "wof:name":"Costa Madri\u00f1an Vanesa",
    "wof:placetype":"venue"
},
  "geometry": {"coordinates":[-7.2503142357,42.8939285278],"type":"Point"}
}