{
  "type": "Feature",
  "properties": {
    "iso:country":"ES",
    "sg:address":"Carrer de Font Vella, 92",
    "sg:city":"Terrassa",
    "sg:orig_category":"Ropa Para Se\u00d1oras Y Caballeros (al Por Menor)",
    "sg:phone":"+34 937 83 20 37",
    "sg:postcode":"08221",
    "sg:province":"Barcelona",
    "wof:name":"Penina Anfruns Nuria",
    "wof:placetype":"venue"
},
  "geometry": {"coordinates":[2.0144779682,41.5630912781],"type":"Point"}
}