{
  "type": "Feature",
  "properties": {
    "iso:country":"ES",
    "sg:address":"Calle de Jose Maria Martorell, 24",
    "sg:city":"Cordoba",
    "sg:orig_category":"Centros De Cr\u00c9dito Inmobiliario",
    "sg:phone":"+34 957 76 18 88",
    "sg:postcode":"14005",
    "sg:province":"C\u00f3rdoba",
    "wof:name":"Promovisa Grupo Inmobiliario S.l.",
    "wof:placetype":"venue"
},
  "geometry": {"coordinates":[-4.7974290848,37.8781242371],"type":"Point"}
}