{
  "type": "Feature",
  "properties": {
    "iso:country":"ES",
    "sg:address":"Calle de Demofilo, 5",
    "sg:city":"Sevilla",
    "sg:orig_category":"Empresas De Vigilancia, Guardia Y Protecci\u00d3n",
    "sg:phone":"+34 954 40 46 66",
    "sg:postcode":"41020",
    "sg:province":"Sevilla",
    "wof:name":"Servicios De Vigilancia Y Proteccion Protec S.a.",
    "wof:placetype":"venue"
},
  "geometry": {"coordinates":[-5.9272489548,37.3976707458],"type":"Point"}
}