{
  "type": "Feature",
  "properties": {
    "iso:country":"ES",
    "sg:address":"Calle de Santo Domingo, 18",
    "sg:city":"Jerez De La Frontera",
    "sg:orig_category":"Cl\u00cdnicas Dentales",
    "sg:phone":"+34 956 18 10 76",
    "sg:postcode":"11402",
    "sg:province":"C\u00e1diz",
    "wof:name":"Clinica 21 Jerez Dental S.l.",
    "wof:placetype":"venue"
},
  "geometry": {"coordinates":[-6.1303019524,36.6922149658],"type":"Point"}
}