{
  "type": "Feature",
  "properties": {
    "addr:full":"Calle de Jose Maria Mortes Lerma, 26 Valencia Valencia 46014",
    "addr:housenumber":"26",
    "addr:postcode":"46014",
    "addr:street":"Calle De Jose Maria Mortes Lerma",
    "iso:country":"ES",
    "sg:address":"Calle de Jose Maria Mortes Lerma, 26",
    "sg:city":"Valencia",
    "sg:orig_category":"Farmacias",
    "sg:phone":"+34 963 78 89 51",
    "sg:postcode":"46014",
    "sg:province":"Valencia",
    "wof:name":"Farmacia Ponce-anguix C.b.",
    "wof:placetype":"venue"
},
  "geometry": {"coordinates":[-0.4013020098,39.4631004333],"type":"Point"}
}