{
  "type": "Feature",
  "properties": {
    "addr:full":"Calle de Dehesa (de La), 69 Collado Mediano Madrid 28450",
    "addr:housenumber":"69",
    "addr:postcode":"28450",
    "addr:street":"Calle De Dehesa De La",
    "iso:country":"ES",
    "sg:address":"Calle de Dehesa (de La), 69",
    "sg:city":"Collado Mediano",
    "sg:orig_category":"Desinfecci\u00d3n, Desinsectaci\u00d3n, Desratizaci\u00d3n",
    "sg:phone":"+34 918 55 76 64",
    "sg:postcode":"28450",
    "sg:province":"Madrid",
    "wof:name":"Gonzalez Ferrari Sonsoles",
    "wof:placetype":"venue"
},
  "geometry": {"coordinates":[-4.039431572,40.6895256042],"type":"Point"}
}