{
  "type": "Feature",
  "properties": {
    "iso:country":"ES",
    "sg:address":"Alam Principal, 45",
    "sg:city":"Malaga",
    "sg:orig_category":"Promotores Constructores",
    "sg:phone":"+34 952 60 90 12",
    "sg:postcode":"29001",
    "sg:province":"M\u00e1laga",
    "wof:name":"Gomez Martin Jorge",
    "wof:placetype":"venue"
},
  "geometry": {"coordinates":[-4.424451828,36.7167854309],"type":"Point"}
}