{
  "type": "Feature",
  "properties": {
    "iso:country":"ES",
    "sg:address":"Calle de Mirlo, 62",
    "sg:city":"Valladolid",
    "sg:orig_category":"Librer\u00cdas",
    "sg:phone":"+34 983 29 46 15",
    "sg:postcode":"47011",
    "sg:province":"Valladolid",
    "wof:name":"Libreria Alicia S.l.l.",
    "wof:placetype":"venue"
},
  "geometry": {"coordinates":[-4.7018389702,41.6492118835],"type":"Point"}
}