{
  "type": "Feature",
  "properties": {
    "iso:country":"ES",
    "sg:address":"Carrer de Ponent, 2",
    "sg:city":"Vilafranca Penedes",
    "sg:orig_category":"Molduras, Junquillos, Listones Y Molduras Perforadas",
    "sg:phone":"+34 938 17 34 17",
    "sg:postcode":"08720",
    "sg:province":"Barcelona",
    "wof:name":"Tavern City Sl",
    "wof:placetype":"venue"
},
  "geometry": {"coordinates":[1.6963579655,41.348449707],"type":"Point"}
}