{
  "type": "Feature",
  "properties": {
    "iso:country":"ES",
    "sg:address":"Trva Cristal Del, 2",
    "sg:city":"Aviles",
    "sg:orig_category":"Agentes, Concesionarios Y Sucursales De Veh\u00cdculos",
    "sg:phone":"+34 985 52 27 62",
    "sg:postcode":"33401",
    "sg:province":"Asturias",
    "wof:name":"Aviles Motor S. A.",
    "wof:placetype":"venue"
},
  "geometry": {"coordinates":[-5.9286265373,43.5729255676],"type":"Point"}
}