{
  "type": "Feature",
  "properties": {
    "iso:country":"ES",
    "sg:address":"Avda Parrilla, 1",
    "sg:city":"Portillo",
    "sg:orig_category":"Importaci\u00d3n",
    "sg:phone":"+34 983 55 69 59",
    "sg:postcode":"47160",
    "sg:province":"Valladolid",
    "wof:name":"Fernandez Pasalodos S.a.t.",
    "wof:placetype":"venue"
},
  "geometry": {"coordinates":[-4.5851240158,41.4798622131],"type":"Point"}
}