{
  "type": "Feature",
  "properties": {
    "addr:full":"Carrer de Llobregat, 21 Hospitalet Llobregat Barcelona 08904",
    "addr:housenumber":"21",
    "addr:postcode":"08904",
    "addr:street":"Carrer De Llobregat",
    "iso:country":"ES",
    "sg:address":"Carrer de Llobregat, 21",
    "sg:city":"Hospitalet Llobregat",
    "sg:orig_category":"El Hogar: Amueblado, Acondicionamiento, Decoraci\u00d3n Y Mantenimiento",
    "sg:phone":"+34 934 48 34 64",
    "sg:postcode":"08904",
    "sg:province":"Barcelona",
    "wof:name":"Lopez Garcia Carlos",
    "wof:placetype":"venue"
},
  "geometry": {"coordinates":[2.1186308861,41.3750724792],"type":"Point"}
}