{
  "type": "Feature",
  "properties": {
    "iso:country":"ES",
    "sg:address":"Pase Sancha, 10",
    "sg:city":"Malaga",
    "sg:orig_category":"Peluquer\u00cdas, Peluquer\u00cda Mixta",
    "sg:phone":"+34 952 21 31 91",
    "sg:postcode":"29016",
    "sg:province":"M\u00e1laga",
    "sg:website":"www.llongueras.com",
    "wof:name":"Instituto De Belleza Ada S.l.",
    "wof:placetype":"venue"
},
  "geometry": {"coordinates":[-4.4012050629,36.7225990295],"type":"Point"}
}