{
  "type": "Feature",
  "properties": {
    "iso:country":"ES",
    "sg:address":"Carr Ponent, S/n",
    "sg:city":"Ponts",
    "sg:orig_category":"Distribuci\u00d3n De Petr\u00d3leo Y Derivados",
    "sg:phone":"+34 973 46 04 73",
    "sg:postcode":"25740",
    "sg:province":"Lleida",
    "wof:name":"Logistica Cal Riera S.c.p.",
    "wof:placetype":"venue"
},
  "geometry": {"coordinates":[1.1855200529,41.915813446],"type":"Point"}
}