{
  "type": "Feature",
  "properties": {
    "iso:country":"ES",
    "sg:address":"La Rioja Pol Ind Tarazona, S/n",
    "sg:city":"Tarazona",
    "sg:orig_category":"Charcuter\u00cdas (al Por Mayor)",
    "sg:phone":"+34 976 19 90 29",
    "sg:postcode":"50500",
    "sg:province":"Zaragoza",
    "sg:website":"www.embutidoslaseca.com",
    "wof:name":"Embutidos Laseca S.l.",
    "wof:placetype":"venue"
},
  "geometry": {"coordinates":[-1.722843051,41.9045448303],"type":"Point"}
}