{
  "type": "Feature",
  "properties": {
    "addr:full":"Calle de Zurbaran, 35 San Javier Murcia 30730",
    "addr:housenumber":"35",
    "addr:postcode":"30730",
    "addr:street":"Calle De Zurbaran",
    "iso:country":"ES",
    "sg:address":"Calle de Zurbaran, 35",
    "sg:city":"San Javier",
    "sg:orig_category":"Transportes Por V\u00cdas Navegables",
    "sg:phone":"+34 968 19 11 92",
    "sg:postcode":"30730",
    "sg:province":"Murcia",
    "wof:name":"Hermanos Alcaraz Marin S. L.",
    "wof:placetype":"venue"
},
  "geometry": {"coordinates":[-0.8377289772,37.8054389954],"type":"Point"}
}