{
  "type": "Feature",
  "properties": {
    "addr:full":"Calle de Prudencio Maria Verastegui, 18 Vitoria-gasteiz \u00c1lava 01002",
    "addr:housenumber":"18",
    "addr:postcode":"01002",
    "addr:street":"Calle De Prudencio Maria Verastegui",
    "iso:country":"ES",
    "sg:address":"Calle de Prudencio Maria Verastegui, 18",
    "sg:city":"Vitoria-gasteiz",
    "sg:orig_category":"Fotograf\u00cda Publicitaria E Industrial",
    "sg:phone":"+34 945 28 63 81",
    "sg:postcode":"01002",
    "sg:province":"\u00c1lava",
    "wof:name":"Obra Grafica Botticelli S.l.",
    "wof:placetype":"venue"
},
  "geometry": {"coordinates":[-2.6663250923,42.8490028381],"type":"Point"}
}