{
  "type": "Feature",
  "properties": {
    "addr:full":"Calle de Belorado, S/n Madrid Madrid 28034",
    "addr:housenumber":"s / n",
    "addr:postcode":"28034",
    "addr:street":"Calle De Belorado",
    "iso:country":"ES",
    "sg:address":"Calle de Belorado, S/n",
    "sg:city":"Madrid",
    "sg:orig_category":"Guarder\u00cdas",
    "sg:phone":"+34 913 58 10 32",
    "sg:postcode":"28034",
    "sg:province":"Madrid",
    "wof:name":"El Globo Rojo S.c.l",
    "wof:placetype":"venue"
},
  "geometry": {"coordinates":[-3.6846911907,40.4880905151],"type":"Point"}
}