{
  "type": "Feature",
  "properties": {
    "addr:full":"Calle de Joaquina Santander, 19 Talavera Reina Toledo 45600",
    "addr:housenumber":"19",
    "addr:postcode":"45600",
    "addr:street":"Calle De Joaquina Santander",
    "iso:country":"ES",
    "sg:address":"Calle de Joaquina Santander, 19",
    "sg:city":"Talavera Reina",
    "sg:orig_category":"Muebles, Minoristas",
    "sg:phone":"+34 925 80 61 79",
    "sg:postcode":"45600",
    "sg:province":"Toledo",
    "wof:name":"Cuevas Mirado Andres",
    "wof:placetype":"venue"
},
  "geometry": {"coordinates":[-4.8227438927,39.9630966187],"type":"Point"}
}