{
  "type": "Feature",
  "properties": {
    "addr:full":"Calle de Soto, 14 Valladolid Valladolid 47010",
    "addr:housenumber":"14",
    "addr:postcode":"47010",
    "addr:street":"Calle De Soto",
    "iso:country":"ES",
    "sg:address":"Calle de Soto, 14",
    "sg:city":"Valladolid",
    "sg:orig_category":"Bisuter\u00cda, Joyer\u00cda, Relojer\u00cda (al Por Menor)",
    "sg:phone":"+34 983 25 18 36",
    "sg:postcode":"47010",
    "sg:province":"Valladolid",
    "wof:name":"Rodriguez Rodriguez Florentino",
    "wof:placetype":"venue"
},
  "geometry": {"coordinates":[-4.7182688713,41.6619644165],"type":"Point"}
}