{
  "type": "Feature",
  "properties": {
    "addr:full":"Calle de Iglesia, 2 Valencia De Las Torres Badajoz 06444",
    "addr:housenumber":"2",
    "addr:postcode":"06444",
    "addr:street":"Calle De Iglesia",
    "iso:country":"ES",
    "sg:address":"Calle de Iglesia, 2",
    "sg:city":"Valencia De Las Torres",
    "sg:orig_category":"Transportes Por Carretera: Lotes Completos, Mercanc\u00cdas Diversas",
    "sg:phone":"+34 924 88 12 02",
    "sg:postcode":"06444",
    "sg:province":"Badajoz",
    "wof:name":"Garay Martinez Francisco",
    "wof:placetype":"venue"
},
  "geometry": {"coordinates":[-6.0041060448,38.4036521912],"type":"Point"}
}