{
  "type": "Feature",
  "properties": {
    "addr:full":"Calle de Retogenes, 5 Soria Soria 42001",
    "addr:housenumber":"5",
    "addr:postcode":"42001",
    "addr:street":"Calle De Retogenes",
    "iso:country":"ES",
    "sg:address":"Calle de Retogenes, 5",
    "sg:city":"Soria",
    "sg:orig_category":"Autob\u00das (explotaci\u00d3n Y Servicios De)",
    "sg:phone":"+34 975 23 17 44",
    "sg:postcode":"42001",
    "sg:province":"Soria",
    "wof:name":"Latorre Egido Jesus",
    "wof:placetype":"venue"
},
  "geometry": {"coordinates":[-2.4706020355,41.767074585],"type":"Point"}
}