{
  "type": "Feature",
  "properties": {
    "addr:full":"Calle de Jose Zorrilla, 1 Aguilas Murcia 30880",
    "addr:housenumber":"1",
    "addr:postcode":"30880",
    "addr:street":"Calle De Jose Zorrilla",
    "iso:country":"ES",
    "sg:address":"Calle de Jose Zorrilla, 1",
    "sg:city":"Aguilas",
    "sg:orig_category":"Plomeros",
    "sg:phone":"+34 968 49 31 22",
    "sg:postcode":"30880",
    "sg:province":"Murcia",
    "wof:name":"Fontaneria Las Lomas S.l.",
    "wof:placetype":"venue"
},
  "geometry": {"coordinates":[-1.5957380533,37.4007720947],"type":"Point"}
}