{
  "type": "Feature",
  "properties": {
    "addr:full":"Calle de Zurbano, 48 Madrid Madrid 28010",
    "addr:housenumber":"48",
    "addr:postcode":"madrid;28010",
    "addr:street":"Calle De Zurbano",
    "iso:country":"ES",
    "sg:address":"Calle de Zurbano, 48",
    "sg:city":"Madrid",
    "sg:orig_category":"M\u00c9dicos: Estomatolog\u00cda",
    "sg:phone":"+34 913 08 51 62",
    "sg:postcode":"28010",
    "sg:province":"Madrid",
    "wof:name":"Manuel Keenoy Luis",
    "wof:placetype":"venue"
},
  "geometry": {"coordinates":[-3.6930930614,40.4335365295],"type":"Point"}
}