{
  "type": "Feature",
  "properties": {
    "iso:country":"ES",
    "sg:address":"Abeto, 4",
    "sg:city":"Aljaraque",
    "sg:orig_category":"T\u00c9cnicos Veterinarios",
    "sg:phone":"+34 959 52 12 38",
    "sg:postcode":"21110",
    "sg:province":"Huelva",
    "wof:name":"Perales Pulido Feliciana",
    "wof:placetype":"venue"
},
  "geometry": {"coordinates":[-7.0092248917,37.287612915],"type":"Point"}
}