{
  "type": "Feature",
  "properties": {
    "addr:full":"Calle de Joaquin Costa, 36 Valencia Valencia 46005",
    "addr:housenumber":"36",
    "addr:postcode":"46005",
    "addr:street":"Calle De Joaquin Costa",
    "iso:country":"ES",
    "sg:address":"Calle de Joaquin Costa, 36",
    "sg:city":"Valencia",
    "sg:orig_category":"M\u00c9dicos: Cirug\u00cda General",
    "sg:phone":"+34 963 74 45 50",
    "sg:postcode":"46005",
    "sg:province":"Valencia",
    "wof:name":"Amorrortu Velayos Jorge",
    "wof:placetype":"venue"
},
  "geometry": {"coordinates":[-0.3664011061,39.4649963379],"type":"Point"}
}