{
  "type": "Feature",
  "properties": {
    "addr:full":"Guillermo Reina, 52 Huercal-overa Almer\u00eda 04600",
    "addr:housenumber":"52",
    "addr:postcode":"04600",
    "addr:street":"Guillermo Reina;Almeri\u0301A",
    "iso:country":"ES",
    "sg:address":"Guillermo Reina, 52",
    "sg:city":"Huercal-overa",
    "sg:orig_category":"Asesor\u00cda Fiscal Y Jur\u00cddica",
    "sg:phone":"+34 950 13 49 61",
    "sg:postcode":"04600",
    "sg:province":"Almer\u00eda",
    "wof:name":"Alonso Pardo Ana",
    "wof:placetype":"venue"
},
  "geometry": {"coordinates":[-1.9436843395,37.390625],"type":"Point"}
}