{
  "type": "Feature",
  "properties": {
    "iso:country":"ES",
    "sg:address":"Ctra Sant Feliu De Guixols A Sant Pol, 158",
    "sg:city":"S. Feliu Guixols",
    "sg:orig_category":"Agencias Y Agentes Comerciales, Representantes",
    "sg:phone":"+34 972 32 54 12",
    "sg:postcode":"17220",
    "sg:province":"Girona",
    "wof:name":"Mestres Brugada Nuria",
    "wof:placetype":"venue"
},
  "geometry": {"coordinates":[3.0246450901,41.7868309021],"type":"Point"}
}