{
  "type": "Feature",
  "properties": {
    "addr:full":"Ptda Alt Canons, 2 Muro Alcoy Alicante 03830",
    "addr:housenumber":"2",
    "addr:postcode":"03830",
    "addr:street":"Ptda Alt Canons",
    "iso:country":"ES",
    "sg:address":"Ptda Alt Canons, 2",
    "sg:city":"Muro Alcoy",
    "sg:orig_category":"Construcci\u00d3n Mec\u00c1nica",
    "sg:phone":"+34 966 51 69 44",
    "sg:postcode":"03830",
    "sg:province":"Alicante",
    "wof:name":"Togial S.l.",
    "wof:placetype":"venue"
},
  "geometry": {"coordinates":[-0.4414289892,38.7812538147],"type":"Point"}
}