{
  "type": "Feature",
  "properties": {
    "iso:country":"ES",
    "sg:address":"Avda Santa Cruz, 117",
    "sg:city":"San Isidro",
    "sg:orig_category":"Asesor\u00cda Sobre Comunicaci\u00d3n De Empresas",
    "sg:phone":"+34 922 39 40 76",
    "sg:postcode":"38611",
    "sg:province":"Santa Cruz De Tenerife",
    "wof:name":"Codesur Sociedad Cooperativa",
    "wof:placetype":"venue"
},
  "geometry": {"coordinates":[-16.5574264526,28.0765724182],"type":"Point"}
}