{
  "type": "Feature",
  "properties": {
    "iso:country":"ES",
    "sg:address":"Pl. Abaco, S/n",
    "sg:city":"Tres Cantos",
    "sg:orig_category":"Distribuci\u00d3n De Petr\u00d3leo Y Derivados",
    "sg:phone":"+34 918 03 45 92",
    "sg:postcode":"28760",
    "sg:province":"Madrid",
    "sg:website":"www.cepsa.es",
    "wof:name":"Lobanfi S.l.",
    "wof:placetype":"venue"
},
  "geometry": {"coordinates":[-3.7031071186,40.6147766113],"type":"Point"}
}