{
  "type": "Feature",
  "properties": {
    "addr:full":"Calle de Lago Calafate, 15 Madrid Madrid 28018",
    "addr:housenumber":"15",
    "addr:postcode":"madrid;28018",
    "addr:street":"Calle De Lago Calafate",
    "iso:country":"ES",
    "sg:address":"Calle de Lago Calafate, 15",
    "sg:city":"Madrid",
    "sg:orig_category":"Agencias Y Agentes Comerciales, Representantes",
    "sg:phone":"+34 913 03 56 43",
    "sg:postcode":"28018",
    "sg:province":"Madrid",
    "wof:name":"Sanchez Garcia Jose Antonio",
    "wof:placetype":"venue"
},
  "geometry": {"coordinates":[-3.6495299339,40.3841056824],"type":"Point"}
}