{
  "type": "Feature",
  "properties": {
    "addr:full":"Real, S/n Boveda De Amoeiro Ourense 32980",
    "addr:housenumber":"s / n",
    "addr:postcode":"32980",
    "addr:street":"Real",
    "iso:country":"ES",
    "sg:address":"Real, S/n",
    "sg:city":"Boveda De Amoeiro",
    "sg:orig_category":"Empresas De Limpieza",
    "sg:phone":"+34 988 28 77 79",
    "sg:postcode":"32980",
    "sg:province":"Ourense",
    "wof:name":"Fidalgo Gra\u00f1a Jose Maria",
    "wof:placetype":"venue"
},
  "geometry": {"coordinates":[-7.9146380424,42.3782157898],"type":"Point"}
}