{
  "type": "Feature",
  "properties": {
    "addr:full":"Calle de Primero De Mayo (del), S/n Aranjuez Madrid 28300",
    "addr:housenumber":"/ n",
    "addr:postcode":"28300",
    "addr:street":"Calle De Primero;S",
    "iso:country":"ES",
    "sg:address":"Calle de Primero De Mayo (del), S/n",
    "sg:city":"Aranjuez",
    "sg:orig_category":"Asociaciones Y Clubs Deportivos",
    "sg:phone":"+34 918 91 77 32",
    "sg:postcode":"28300",
    "sg:province":"Madrid",
    "wof:name":"Asociacion De Especialistas En Actividades Fisicas De Aranjuez",
    "wof:placetype":"venue"
},
  "geometry": {"coordinates":[-3.5923988819,40.0356674194],"type":"Point"}
}