{
  "type": "Feature",
  "properties": {
    "addr:full":"Carrer de Pi I Margall, 25 Viladecans Barcelona 08840",
    "addr:housenumber":"25",
    "addr:postcode":"08840",
    "addr:street":"Carrer De Pi I Margall",
    "iso:country":"ES",
    "sg:address":"Carrer de Pi I Margall, 25",
    "sg:city":"Viladecans",
    "sg:orig_category":"Confecci\u00d3n De Zapatos",
    "sg:phone":"+34 936 37 74 67",
    "sg:postcode":"08840",
    "sg:province":"Barcelona",
    "wof:name":"Blanco Ya\u00f1ez Isabel",
    "wof:placetype":"venue"
},
  "geometry": {"coordinates":[2.0174899101,41.3155822754],"type":"Point"}
}