{
  "type": "Feature",
  "properties": {
    "iso:country":"ES",
    "sg:address":"Par. Torre Mirona, S/n",
    "sg:city":"Palamos",
    "sg:orig_category":"Zonas De Acampada, Aparcamiento Para Caravanas",
    "sg:phone":"+34 972 31 55 75",
    "sg:postcode":"17230",
    "sg:province":"Girona",
    "wof:name":"Pineda Mirona S.l.",
    "wof:placetype":"venue"
},
  "geometry": {"coordinates":[3.1310949326,41.8468360901],"type":"Point"}
}