{
  "type": "Feature",
  "properties": {
    "iso:country":"ES",
    "sg:address":"Calle de Caldereros, 15",
    "sg:city":"Medina-sidonia",
    "sg:orig_category":"Mec\u00c1nico Del Autom\u00d3vil",
    "sg:phone":"+34 956 41 23 40",
    "sg:postcode":"11170",
    "sg:province":"C\u00e1diz",
    "wof:name":"Montero Castro Juan Alberto",
    "wof:placetype":"venue"
},
  "geometry": {"coordinates":[-5.9310355186,36.4597244263],"type":"Point"}
}