{
  "type": "Feature",
  "properties": {
    "addr:full":"Calle de Vi\u00d1uelas, 2 Cobe\u00f1a Madrid 28863",
    "addr:housenumber":"2",
    "addr:postcode":"28863",
    "addr:street":"Calle De Vin\u0303Uelas",
    "iso:country":"ES",
    "sg:address":"Calle de Vi\u00d1uelas, 2",
    "sg:city":"Cobe\u00f1a",
    "sg:orig_category":"M\u00c9dicos: Geriatr\u00cda, Gerontolog\u00cda (enfermedades De La Tercera Edad)",
    "sg:phone":"+34 916 20 83 19",
    "sg:postcode":"28863",
    "sg:province":"Madrid",
    "wof:name":"Alba Ii Residencia Geriatrica",
    "wof:placetype":"venue"
},
  "geometry": {"coordinates":[-3.4988036156,40.5695419312],"type":"Point"}
}