{
  "type": "Feature",
  "properties": {
    "iso:country":"ES",
    "sg:address":"Calle de Cobre, 2",
    "sg:city":"Humanes De Madrid",
    "sg:orig_category":"Tapiceros Y Tapiceros",
    "sg:phone":"+34 916 90 56 19",
    "sg:postcode":"28970",
    "sg:province":"Madrid",
    "wof:name":"Sanchez Vallejo Pastor",
    "wof:placetype":"venue"
},
  "geometry": {"coordinates":[-3.8262872696,40.2674827576],"type":"Point"}
}