{
  "type": "Feature",
  "properties": {
    "addr:full":"Calle de Progreso, 122 Rua De Valdeorras Ourense 32350",
    "addr:housenumber":"122",
    "addr:postcode":"32350",
    "addr:street":"Calle De Progreso;Rua De",
    "iso:country":"ES",
    "sg:address":"Calle de Progreso, 122",
    "sg:city":"Rua De Valdeorras",
    "sg:orig_category":"Bazares, Art\u00cdculos De Limpieza Y De Cocina (al Por Menor)",
    "sg:phone":"+34 988 31 03 34",
    "sg:postcode":"32350",
    "sg:province":"Ourense",
    "wof:name":"Rodriguez Arias Victoriano",
    "wof:placetype":"venue"
},
  "geometry": {"coordinates":[-7.1205739975,42.392490387],"type":"Point"}
}