{
  "type": "Feature",
  "properties": {
    "addr:full":"Calle de Luis Bu\u00d1uel, 7 Zaragoza Zaragoza 50017",
    "addr:housenumber":"7",
    "addr:postcode":"50017",
    "addr:street":"Calle De Luis Bun\u0303Uel",
    "iso:country":"ES",
    "sg:address":"Calle de Luis Bu\u00d1uel, 7",
    "sg:city":"Zaragoza",
    "sg:orig_category":"Reposter\u00cdas",
    "sg:phone":"+34 976 31 72 11",
    "sg:postcode":"50017",
    "sg:province":"Zaragoza",
    "wof:name":"Serrano Domingo Rafael",
    "wof:placetype":"venue"
},
  "geometry": {"coordinates":[-0.9200519919,41.6569328308],"type":"Point"}
}