{
  "type": "Feature",
  "properties": {
    "addr:full":"Calle de Olimpia, 37 Costa Del Silencio Santa Cruz De Tenerife 38630",
    "addr:housenumber":"37",
    "addr:postcode":"38630",
    "addr:street":"Calle De Olimpia",
    "iso:country":"ES",
    "sg:address":"Calle de Olimpia, 37",
    "sg:city":"Costa Del Silencio",
    "sg:orig_category":"Ebanistas Y Talladores De Muebles Y Objetos De Arte",
    "sg:phone":"+34 922 78 54 60",
    "sg:postcode":"38630",
    "sg:province":"Santa Cruz De Tenerife",
    "wof:name":"Navarro Chinea Carlos",
    "wof:placetype":"venue"
},
  "geometry": {"coordinates":[-16.6410999298,28.0115337372],"type":"Point"}
}