{
  "type": "Feature",
  "properties": {
    "iso:country":"ES",
    "sg:address":"Calle de Alangobarri, 2",
    "sg:city":"Algorta",
    "sg:orig_category":"Peluqueros: De Se\u00d1oras",
    "sg:phone":"+34 944 60 42 66",
    "sg:postcode":"48992",
    "sg:province":"Vizcaya",
    "wof:name":"Esteban Butron Lourdes",
    "wof:placetype":"venue"
},
  "geometry": {"coordinates":[-3.0096130371,43.3478431702],"type":"Point"}
}