{
  "type": "Feature",
  "properties": {
    "iso:country":"ES",
    "sg:address":"Rua Tomas A Alonso, 80",
    "sg:city":"Vigo",
    "sg:orig_category":"Conservas De Pescados Y Salazones Mar\u00cdtimos (fabricaci\u00d3n, Al Por Mayor)",
    "sg:phone":"+34 986 23 35 00",
    "sg:postcode":"36208",
    "sg:province":"Pontevedra",
    "sg:website":"www.paypay.es",
    "wof:name":"Conservas Cerqueira S. A.",
    "wof:placetype":"venue"
},
  "geometry": {"coordinates":[-8.739695549,42.2239227295],"type":"Point"}
}