{
  "type": "Feature",
  "properties": {
    "iso:country":"ES",
    "sg:address":"Ctra Don Benito, S/n",
    "sg:city":"Guare\u00f1a",
    "sg:orig_category":"Aceites Y Grasas Alimentarias (fabricaci\u00d3n, Al Por Mayor)",
    "sg:phone":"+34 924 35 02 78",
    "sg:postcode":"06470",
    "sg:province":"Badajoz",
    "wof:name":"Cooperativa Del Campo San Pedro",
    "wof:placetype":"venue"
},
  "geometry": {"coordinates":[-6.0951738358,38.8601036072],"type":"Point"}
}