{
  "type": "Feature",
  "properties": {
    "iso:country":"ES",
    "sg:address":"Calle de Viernes De Toros, 7",
    "sg:city":"Soria",
    "sg:orig_category":"Pintura, Barniz, Productos Asimilables (fabricaci\u00d3n, Al Por Mayor)",
    "sg:phone":"+34 975 24 09 69",
    "sg:postcode":"42002",
    "sg:province":"Soria",
    "sg:website":"www.juno.es",
    "wof:name":"Industrias Juno S. A.",
    "wof:placetype":"venue"
},
  "geometry": {"coordinates":[-2.4666240215,41.7678375244],"type":"Point"}
}