{
  "type": "Feature",
  "properties": {
    "iso:country":"ES",
    "sg:address":"Calle de Ganeta, 1",
    "sg:city":"Arenas -areeta",
    "sg:orig_category":"Molduras, Junquillos, Listones Y Molduras Perforadas",
    "sg:phone":"+34 944 63 51 19",
    "sg:postcode":"48930",
    "sg:province":"Vizcaya",
    "wof:name":"Pagador Alvarez Angel",
    "wof:placetype":"venue"
},
  "geometry": {"coordinates":[-3.0088820457,43.3288574219],"type":"Point"}
}