{
  "type": "Feature",
  "properties": {
    "iso:country":"ES",
    "sg:address":"Plaz Magnolios (los), S/n",
    "sg:city":"Durcal",
    "sg:orig_category":"Pizzer\u00cdas",
    "sg:phone":"+34 958 78 03 77",
    "sg:postcode":"18650",
    "sg:province":"Granada",
    "wof:name":"Bravo Arellano Jose Luis",
    "wof:placetype":"venue"
},
  "geometry": {"coordinates":[-3.5675089359,36.9882011414],"type":"Point"}
}