{
  "type": "Feature",
  "properties": {
    "addr:full":"Carrer de Riera De Tena, 7 Barcelona Barcelona 08014",
    "addr:housenumber":"7",
    "addr:postcode":"08014",
    "addr:street":"Carrer De Riera De Tena",
    "iso:country":"ES",
    "sg:address":"Carrer de Riera De Tena, 7",
    "sg:city":"Barcelona",
    "sg:orig_category":"Inmobiliaria (agencias)",
    "sg:phone":"+34 932 98 16 99",
    "sg:postcode":"08014",
    "sg:province":"Barcelona",
    "sg:website":"www.tecnocasa.es",
    "wof:name":"Pisos De Montjuic S. L.",
    "wof:placetype":"venue"
},
  "geometry": {"coordinates":[2.1336579323,41.3704414368],"type":"Point"}
}