{
  "type": "Feature",
  "properties": {
    "addr:full":"Rua Pascual Veiga, 7 Burela Lugo 27880",
    "addr:housenumber":"7",
    "addr:postcode":"27880",
    "addr:street":"Rua Pascual Veiga",
    "iso:country":"ES",
    "sg:address":"Rua Pascual Veiga, 7",
    "sg:city":"Burela",
    "sg:orig_category":"Reposter\u00cdas",
    "sg:phone":"+34 982 58 05 05",
    "sg:postcode":"27880",
    "sg:province":"Lugo",
    "wof:name":"Orol Orol Jose",
    "wof:placetype":"venue"
},
  "geometry": {"coordinates":[-7.3612132072,43.657749176],"type":"Point"}
}