{
  "type": "Feature",
  "properties": {
    "iso:country":"ES",
    "sg:address":"Avda Euzkadi (de), 12",
    "sg:city":"San Sebastian De Los Reyes",
    "sg:orig_category":"Institutos De Belleza",
    "sg:phone":"+34 916 54 16 71",
    "sg:postcode":"28700",
    "sg:province":"Madrid",
    "wof:name":"Belleza Soledad S.l",
    "wof:placetype":"venue"
},
  "geometry": {"coordinates":[-3.6330769062,40.5556221008],"type":"Point"}
}