{
  "type": "Feature",
  "properties": {
    "iso:country":"ES",
    "sg:address":"Calle de Pablo Picasso, 38",
    "sg:city":"Elda",
    "sg:orig_category":"Alimentaci\u00d3n General (al Por Menor)",
    "sg:phone":"+34 965 38 39 39",
    "sg:postcode":"03600",
    "sg:province":"Alicante",
    "wof:name":"Izquierdo Carballo Jonathan",
    "wof:placetype":"venue"
},
  "geometry": {"coordinates":[-0.786552012,38.4758033752],"type":"Point"}
}