{
  "type": "Feature",
  "properties": {
    "iso:country":"ES",
    "sg:address":"Calle de Clara Del Rey, 60",
    "sg:city":"Madrid",
    "sg:orig_category":"Farmacias",
    "sg:phone":"+34 914 15 06 90",
    "sg:postcode":"28002",
    "sg:province":"Madrid",
    "wof:name":"Marcos Garcia Maria Angeles",
    "wof:placetype":"venue"
},
  "geometry": {"coordinates":[-3.667873621,40.4469490051],"type":"Point"}
}