{
  "type": "Feature",
  "properties": {
    "iso:country":"ES",
    "sg:address":"Calle de Virgen De La Soledad, 17",
    "sg:city":"Guadalajara",
    "sg:orig_category":"Bancos",
    "sg:phone":"+34 949 21 15 46",
    "sg:postcode":"19003",
    "sg:province":"Guadalajara",
    "wof:name":"Banco Espa\u00f1ol De Credito S.a.",
    "wof:placetype":"venue"
},
  "geometry": {"coordinates":[-3.1655199528,40.6279525757],"type":"Point"}
}