{
  "type": "Feature",
  "properties": {
    "iso:country":"ES",
    "sg:address":"Ctra Talamanca, Km. 0033,5",
    "sg:city":"Navarcles",
    "sg:orig_category":"Construcci\u00d3n Mec\u00c1nica",
    "sg:phone":"+34 938 27 02 04",
    "sg:postcode":"08270",
    "sg:province":"Barcelona",
    "wof:name":"Luna Trenas Maria Luisa",
    "wof:placetype":"venue"
},
  "geometry": {"coordinates":[1.90546,41.7474517822],"type":"Point"}
}