{
  "type": "Feature",
  "properties": {
    "addr:full":"Calle de Doctor Gregorio Mara\u00d1on, S/n Arrecife Las Palmas 35500",
    "addr:housenumber":"s / n",
    "addr:postcode":"35500",
    "addr:street":"Calle De Doctor Gregorio Maran\u0303On",
    "iso:country":"ES",
    "sg:address":"Calle de Doctor Gregorio Mara\u00d1on, S/n",
    "sg:city":"Arrecife",
    "sg:orig_category":"Ense\u00d1anza, Formaci\u00d3n Profesional: Aprendizaje",
    "sg:phone":"+34 928 80 31 87",
    "sg:postcode":"35500",
    "sg:province":"Las Palmas",
    "wof:name":"Gobierno De Canarias",
    "wof:placetype":"venue"
},
  "geometry": {"coordinates":[-13.5573816299,28.9693050385],"type":"Point"}
}