{
  "type": "Feature",
  "properties": {
    "addr:full":"Ctra Alcantarilla, 82 Nonduermas Murcia 30166",
    "addr:housenumber":"82",
    "addr:postcode":"30166",
    "addr:street":"Ctra Alcantarilla",
    "iso:country":"ES",
    "sg:address":"Ctra Alcantarilla, 82",
    "sg:city":"Nonduermas",
    "sg:orig_category":"Extinci\u00d3n De Incendios: Material Y Suministros (fabricaci\u00d3n, Al Por Mayor)",
    "sg:phone":"+34 968 25 29 11",
    "sg:postcode":"30166",
    "sg:province":"Murcia",
    "sg:website":"www.unixsa.com",
    "wof:name":"Universal De Extintores S. A.",
    "wof:placetype":"venue"
},
  "geometry": {"coordinates":[-1.1620839834,37.9734764099],"type":"Point"}
}