{
  "type": "Feature",
  "properties": {
    "iso:country":"ES",
    "sg:address":"Calle de Pablo Picasso, S/n",
    "sg:city":"Pinto",
    "sg:orig_category":"Ropa Para Se\u00d1oras (al Por Menor)",
    "sg:phone":"+34 916 91 22 64",
    "sg:postcode":"28320",
    "sg:province":"Madrid",
    "wof:name":"Manuela Pavon S.l.",
    "wof:placetype":"venue"
},
  "geometry": {"coordinates":[-3.6949789524,40.2378349304],"type":"Point"}
}