{
  "type": "Feature",
  "properties": {
    "addr:full":"Sect H, 62 Torre De La Higuera O Matalasca\u00e7as Huelva 21760",
    "addr:housenumber":"62",
    "addr:postcode":"21760",
    "addr:street":"Sect H",
    "iso:country":"ES",
    "sg:address":"Sect H, 62",
    "sg:city":"Torre De La Higuera O Matalasca\u00e7as",
    "sg:orig_category":"Farmacias",
    "sg:phone":"+34 959 44 80 51",
    "sg:postcode":"21760",
    "sg:province":"Huelva",
    "wof:name":"Rodriguez Rios Manuel",
    "wof:placetype":"venue"
},
  "geometry": {"coordinates":[-6.9495940208,37.256313324],"type":"Point"}
}