{
  "type": "Feature",
  "properties": {
    "iso:country":"ES",
    "sg:address":"Carrer de Migdia, 43",
    "sg:city":"Vilafranca Penedes",
    "sg:orig_category":"Agentes Generales De Seguros",
    "sg:phone":"+34 938 90 25 72",
    "sg:postcode":"08720",
    "sg:province":"Barcelona",
    "wof:name":"Lacruz Batlle Lluis",
    "wof:placetype":"venue"
},
  "geometry": {"coordinates":[1.6995279789,41.3437805176],"type":"Point"}
}