{
  "type": "Feature",
  "properties": {
    "iso:country":"ES",
    "sg:address":"Carrer de Pintor Sorolla, 52",
    "sg:city":"Deltebre",
    "sg:orig_category":"Molduras, Junquillos, Listones Y Molduras Perforadas",
    "sg:phone":"+34 977 48 90 08",
    "sg:postcode":"43580",
    "sg:province":"Tarragona",
    "wof:name":"Zaragoza Franch Natividad",
    "wof:placetype":"venue"
},
  "geometry": {"coordinates":[0.694852829,40.7262458801],"type":"Point"}
}