{
  "type": "Feature",
  "properties": {
    "addr:full":"Plaz Almirante Bastarreche, S/n Aduanas Alicante 03730",
    "addr:housenumber":"s / n",
    "addr:postcode":"03730",
    "addr:street":"Bastarreche",
    "iso:country":"ES",
    "sg:address":"Plaz Almirante Bastarreche, S/n",
    "sg:city":"Aduanas",
    "sg:orig_category":"Molduras, Junquillos, Listones Y Molduras Perforadas",
    "sg:phone":"+34 965 79 34 50",
    "sg:postcode":"03730",
    "sg:province":"Alicante",
    "wof:name":"Gonzalez Molina Ignacio",
    "wof:placetype":"venue"
},
  "geometry": {"coordinates":[0.1818349957,38.7947387695],"type":"Point"}
}