{
  "type": "Feature",
  "properties": {
    "addr:full":"Calle de Luis Chamizo, 7 Valdetorres Badajoz 06474",
    "addr:housenumber":"7",
    "addr:postcode":"06474",
    "addr:street":"Calle De Luis Chamizo",
    "iso:country":"ES",
    "sg:address":"Calle de Luis Chamizo, 7",
    "sg:city":"Valdetorres",
    "sg:orig_category":"Empresas De Carpinter\u00cda De Madera",
    "sg:phone":"+34 924 36 84 31",
    "sg:postcode":"06474",
    "sg:province":"Badajoz",
    "wof:name":"Blanco Carmona Elias",
    "wof:placetype":"venue"
},
  "geometry": {"coordinates":[-6.0696959496,38.9135398865],"type":"Point"}
}