{
  "type": "Feature",
  "properties": {
    "iso:country":"ES",
    "sg:address":"Avda Doctor Gregorio Mara\u00d1on, S/n",
    "sg:city":"Salamanca",
    "sg:orig_category":"Caf\u00c9s, Bares, Cervecer\u00cdas",
    "sg:phone":"+34 923 24 43 11",
    "sg:postcode":"37007",
    "sg:province":"Salamanca",
    "wof:name":"Elyber Montero S.l",
    "wof:placetype":"venue"
},
  "geometry": {"coordinates":[-5.6762490273,40.9662513733],"type":"Point"}
}