{
  "type": "Feature",
  "properties": {
    "iso:country":"ES",
    "sg:address":"Urb Europa, S/n",
    "sg:city":"Olula Rio",
    "sg:orig_category":"Asesor\u00cda De Formaci\u00d3n Y Gesti\u00d3n De Personal",
    "sg:phone":"+34 950 44 30 22",
    "sg:postcode":"04860",
    "sg:province":"Almer\u00eda",
    "wof:name":"Asesoria Audico S.l.",
    "wof:placetype":"venue"
},
  "geometry": {"coordinates":[-2.4679217339,36.8401641846],"type":"Point"}
}