{
  "type": "Feature",
  "properties": {
    "iso:country":"ES",
    "sg:address":"Ca\u00f1os, 37",
    "sg:city":"Lucena",
    "sg:orig_category":"Muebles, Minoristas",
    "sg:phone":"+34 957 50 06 22",
    "sg:postcode":"14900",
    "sg:province":"C\u00f3rdoba",
    "wof:name":"Pino Galvez Miguel",
    "wof:placetype":"venue"
},
  "geometry": {"coordinates":[-4.4841241837,37.411895752],"type":"Point"}
}