{
  "type": "Feature",
  "properties": {
    "addr:full":"Plaz Ramon Y Cajal, 1 Altorricon Huesca 22540",
    "addr:housenumber":"1",
    "addr:postcode":"22540",
    "addr:street":"Ramon Y Cajal",
    "iso:country":"ES",
    "sg:address":"Plaz Ramon Y Cajal, 1",
    "sg:city":"Altorricon",
    "sg:orig_category":"Agricultura: Abastecimiento Y Cosechado (negocio)",
    "sg:phone":"+34 974 42 50 03",
    "sg:postcode":"22540",
    "sg:province":"Huesca",
    "wof:name":"Mola Miarnau Blas",
    "wof:placetype":"venue"
},
  "geometry": {"coordinates":[0.4131349921,41.8034210205],"type":"Point"}
}