{
  "type": "Feature",
  "properties": {
    "addr:full":"Calle de Platanos (de Los), 1 Arevalo \u00c1vila 05200",
    "addr:housenumber":"1",
    "addr:postcode":"05200",
    "addr:street":"Calle De Platanos De Los",
    "iso:country":"ES",
    "sg:address":"Calle de Platanos (de Los), 1",
    "sg:city":"Arevalo",
    "sg:orig_category":"M\u00c9dicos: Estomatolog\u00cda",
    "sg:phone":"+34 920 30 34 67",
    "sg:postcode":"05200",
    "sg:province":"\u00c1vila",
    "wof:name":"Delfino Valverde Carlos Edgardo",
    "wof:placetype":"venue"
},
  "geometry": {"coordinates":[-4.7217388153,41.0559883118],"type":"Point"}
}