{
  "type": "Feature",
  "properties": {
    "iso:country":"ES",
    "sg:address":"Carr Caritat, 35",
    "sg:city":"Badalona",
    "sg:orig_category":"Arquitectos",
    "sg:phone":"+34 933 89 11 63",
    "sg:postcode":"08911",
    "sg:province":"Barcelona",
    "wof:name":"Pujals Agusti Rafael",
    "wof:placetype":"venue"
},
  "geometry": {"coordinates":[2.2510108948,41.4510955811],"type":"Point"}
}