{
  "type": "Feature",
  "properties": {
    "iso:country":"ES",
    "sg:address":"Carr Poeta Llorente, 11",
    "sg:city":"Quart Poblet",
    "sg:orig_category":"Tintes (fabricaci\u00d3n, Al Por Mayor)",
    "sg:phone":"+34 961 53 27 89",
    "sg:postcode":"46930",
    "sg:province":"Valencia",
    "wof:name":"Sercom Net S.l.",
    "wof:placetype":"venue"
},
  "geometry": {"coordinates":[-0.4412809908,39.4818572998],"type":"Point"}
}