{
  "type": "Feature",
  "properties": {
    "iso:country":"ES",
    "sg:address":"Carrer de Mariano Viada, 4",
    "sg:city":"Palma",
    "sg:orig_category":"Confecci\u00d3n De Trajes Para Se\u00d1oras",
    "sg:phone":"+34 971 47 91 54",
    "sg:postcode":"07008",
    "sg:province":"Islas Baleares",
    "wof:name":"Confeciones Marian Mallorca C.b.",
    "wof:placetype":"venue"
},
  "geometry": {"coordinates":[2.6741859913,39.5818901062],"type":"Point"}
}