{
  "type": "Feature",
  "properties": {
    "iso:country":"ES",
    "sg:address":"Plaz Mondariz, 6",
    "sg:city":"Madrid",
    "sg:orig_category":"Artes Gr\u00c1ficas, Artes Pl\u00c1sticas (curso)",
    "sg:phone":"+34 902 19 65 81",
    "sg:postcode":"28029",
    "sg:province":"Madrid",
    "wof:name":"Masaf S.a.",
    "wof:placetype":"venue"
},
  "geometry": {"coordinates":[-3.7048239708,40.4783630371],"type":"Point"}
}