{
  "type": "Feature",
  "properties": {
    "addr:full":"Avda Constitucion De La, 20 Arroyo De La Miel-benalmadena Costa M\u00e1laga 29631",
    "addr:housenumber":"20",
    "addr:postcode":"29631",
    "addr:street":"Avda Constitucion De La;Ma\u0301Laga",
    "iso:country":"ES",
    "sg:address":"Avda Constitucion De La, 20",
    "sg:city":"Arroyo De La Miel-benalmadena Costa",
    "sg:orig_category":"Administradores De Bienes Y Delegados De Comunidades De Propietarios",
    "sg:phone":"+34 952 44 73 24",
    "sg:postcode":"29631",
    "sg:province":"M\u00e1laga",
    "wof:name":"Roman Gomez Salvador",
    "wof:placetype":"venue"
},
  "geometry": {"coordinates":[-4.5482521057,36.6017608643],"type":"Point"}
}