{
  "type": "Feature",
  "properties": {
    "addr:full":"Plaz Gabriel Miro, 9 Alacant Alicante 03001",
    "addr:postcode":"03001",
    "iso:country":"ES",
    "sg:address":"Plaz Gabriel Miro, 9",
    "sg:city":"Alacant",
    "sg:orig_category":"Centros De Coordinaci\u00d3n",
    "sg:phone":"+34 965 20 78 05",
    "sg:postcode":"03001",
    "sg:province":"Alicante",
    "wof:name":"Ruiz Fernandez-reyes Sebastian",
    "wof:placetype":"venue"
},
  "geometry": {"coordinates":[-0.4853740036,38.3433189392],"type":"Point"}
}