{
  "type": "Feature",
  "properties": {
    "addr:full":"Calle de Benigno Vazquez, 22 Monterroso Lugo 27560",
    "addr:housenumber":"22",
    "addr:postcode":"27560",
    "addr:street":"Calle De Benigno Vazquez",
    "iso:country":"ES",
    "sg:address":"Calle de Benigno Vazquez, 22",
    "sg:city":"Monterroso",
    "sg:orig_category":"Asesor\u00cda Fiscal Y Jur\u00cddica",
    "sg:phone":"+34 982 37 80 49",
    "sg:postcode":"27560",
    "sg:province":"Lugo",
    "wof:name":"Agroxest S.l.",
    "wof:placetype":"venue"
},
  "geometry": {"coordinates":[-7.835038662,42.7938270569],"type":"Point"}
}