{
  "type": "Feature",
  "properties": {
    "iso:country":"ES",
    "sg:address":"Calle de Bolos, S/n",
    "sg:city":"San Andres",
    "sg:orig_category":"Centros De Educaci\u00d3n Especial",
    "sg:phone":"+34 968 28 25 11",
    "sg:postcode":"30005",
    "sg:province":"Murcia",
    "wof:name":"Grupo Escolar Garcia Alix",
    "wof:placetype":"venue"
},
  "geometry": {"coordinates":[-1.1401462555,37.9858512878],"type":"Point"}
}