{
  "type": "Feature",
  "properties": {
    "addr:full":"Calle de Fuente Boticaria, 50 Ciudad Rodrigo Salamanca 37500",
    "addr:housenumber":"50",
    "addr:postcode":"37500",
    "addr:street":"Calle De Fuente Boticaria",
    "iso:country":"ES",
    "sg:address":"Calle de Fuente Boticaria, 50",
    "sg:city":"Ciudad Rodrigo",
    "sg:orig_category":"Equitaci\u00d3n: Guarnicioner\u00cda, Equipo (al Por Menor)",
    "sg:phone":"+34 923 46 12 55",
    "sg:postcode":"37500",
    "sg:province":"Salamanca",
    "wof:name":"Carrizo Hernandez Jose Luis",
    "wof:placetype":"venue"
},
  "geometry": {"coordinates":[-6.5386791229,40.601650238],"type":"Point"}
}