{
  "type": "Feature",
  "properties": {
    "addr:full":"Avda Castilla (de), 8 Poligono De San Fernando De Henares Madrid 28830",
    "addr:housenumber":"8",
    "addr:postcode":"28830",
    "addr:street":"Avda Castilla De",
    "iso:country":"ES",
    "sg:address":"Avda Castilla (de), 8",
    "sg:city":"Poligono De San Fernando De Henares",
    "sg:orig_category":"Fabricaci\u00d3n De Pernos, Tornillos Y Clavos",
    "sg:phone":"+34 916 77 30 21",
    "sg:postcode":"28830",
    "sg:province":"Madrid",
    "wof:name":"Lotor Logistica De Tornilleria Industrial S.a.",
    "wof:placetype":"venue"
},
  "geometry": {"coordinates":[-3.5068330765,40.4528541565],"type":"Point"}
}