{
  "type": "Feature",
  "properties": {
    "addr:full":"Calle de Jose Ortega Y Gasset, 29 Madrid Madrid 28006",
    "addr:housenumber":"29",
    "addr:postcode":"madrid;28006",
    "addr:street":"Calle De Jose Ortega Y Gasset",
    "iso:country":"ES",
    "sg:address":"Calle de Jose Ortega Y Gasset, 29",
    "sg:city":"Madrid",
    "sg:orig_category":"Inversiones",
    "sg:phone":"+34 914 26 36 00",
    "sg:postcode":"28006",
    "sg:province":"Madrid",
    "sg:website":"www.franklintempletonfondos.com",
    "wof:name":"Franklin Templeton Investment Management Ltd",
    "wof:placetype":"venue"
},
  "geometry": {"coordinates":[-3.6830120087,40.4304084778],"type":"Point"}
}