{
  "type": "Feature",
  "properties": {
    "addr:full":"Calle de Palma La, 22 Ag\u00fcimes Las Palmas 35260",
    "addr:housenumber":"22",
    "addr:postcode":"35260",
    "addr:street":"Calle De Palma La",
    "iso:country":"ES",
    "sg:address":"Calle de Palma La, 22",
    "sg:city":"Ag\u00fcimes",
    "sg:orig_category":"Bares, Piano",
    "sg:phone":"+34 928 78 70 73",
    "sg:postcode":"35260",
    "sg:province":"Las Palmas",
    "wof:name":"Hernandez Estupi\u00f1a Antonia",
    "wof:placetype":"venue"
},
  "geometry": {"coordinates":[-15.4438781738,27.8998813629],"type":"Point"}
}