{
  "type": "Feature",
  "properties": {
    "iso:country":"ES",
    "sg:address":"C/ Sant Francesc, 13",
    "sg:city":"Alcoi",
    "sg:orig_category":"Loter\u00cda Y T\u00d3mbola",
    "sg:phone":"+34 965 54 51 68",
    "sg:postcode":"03801",
    "sg:province":"Alicante",
    "wof:name":"Sanus Abad Luis",
    "wof:placetype":"venue"
},
  "geometry": {"coordinates":[-0.4738090038,38.6955337524],"type":"Point"}
}