{
  "type": "Feature",
  "properties": {
    "iso:country":"ES",
    "sg:address":"Carrer de Hermenegild Clascar, 40",
    "sg:city":"Vilafranca Penedes",
    "sg:orig_category":"Centros De Salud",
    "sg:phone":"+34 938 90 30 00",
    "sg:postcode":"08720",
    "sg:province":"Barcelona",
    "wof:name":"Ponseti Carreras Maria Jesus",
    "wof:placetype":"venue"
},
  "geometry": {"coordinates":[1.6992199421,41.3447799683],"type":"Point"}
}