{
  "type": "Feature",
  "properties": {
    "iso:country":"ES",
    "sg:address":"Carrer de Muntaner, 190",
    "sg:city":"Barcelona",
    "sg:orig_category":"Fabricaci\u00d3n De Muebles",
    "sg:phone":"+34 932 00 18 78",
    "sg:postcode":"08036",
    "sg:province":"Barcelona",
    "wof:name":"Losales S.c.p",
    "wof:placetype":"venue"
},
  "geometry": {"coordinates":[2.1515750885,41.3927345276],"type":"Point"}
}