{
  "type": "Feature",
  "properties": {
    "addr:full":"Av. Pialla, S/n Infiesto Asturias 33530",
    "addr:housenumber":"s / n",
    "addr:postcode":"33530",
    "addr:street":"Av. Pialla",
    "iso:country":"ES",
    "sg:address":"Av. Pialla, S/n",
    "sg:city":"Infiesto",
    "sg:orig_category":"Centros De Educaci\u00d3n Especial",
    "sg:phone":"+34 985 71 17 43",
    "sg:postcode":"33530",
    "sg:province":"Asturias",
    "wof:name":"Colegio Nacional Mixto",
    "wof:placetype":"venue"
},
  "geometry": {"coordinates":[-5.3591837883,43.3441810608],"type":"Point"}
}