{
  "type": "Feature",
  "properties": {
    "addr:full":"Calle de Chomas, 1 Iniesta Cuenca 16235",
    "addr:housenumber":"1",
    "addr:postcode":"16235",
    "addr:street":"Calle De Chomas",
    "iso:country":"ES",
    "sg:address":"Calle de Chomas, 1",
    "sg:city":"Iniesta",
    "sg:orig_category":"Electrodom\u00c9sticos (al Por Menor)",
    "sg:phone":"+34 967 49 01 25",
    "sg:postcode":"16235",
    "sg:province":"Cuenca",
    "wof:name":"Zamora Gomez Antonio",
    "wof:placetype":"venue"
},
  "geometry": {"coordinates":[-1.7491631508,39.444568634],"type":"Point"}
}