{
  "type": "Feature",
  "properties": {
    "addr:full":"Carrer de Salvador Espriu, 16 Casc Antic Barcelona 08150",
    "addr:housenumber":"16",
    "addr:postcode":"08150",
    "addr:street":"Carrer De Salvador Espriu",
    "iso:country":"ES",
    "sg:address":"Carrer de Salvador Espriu, 16",
    "sg:city":"Casc Antic",
    "sg:orig_category":"Ingenier\u00cda, Centros De Estudios (diversos)",
    "sg:phone":"+34 935 73 12 00",
    "sg:postcode":"08150",
    "sg:province":"Barcelona",
    "wof:name":"Luis Simoes Logistica Integrada S.a.",
    "wof:placetype":"venue"
},
  "geometry": {"coordinates":[2.2319469452,41.5694198608],"type":"Point"}
}