{
  "type": "Feature",
  "properties": {
    "iso:country":"ES",
    "sg:address":"Nirvana, 40",
    "sg:city":"Sevilla",
    "sg:orig_category":"Plomeros",
    "sg:phone":"+34 954 25 69 07",
    "sg:postcode":"41020",
    "sg:province":"Sevilla",
    "wof:name":"Baena Guillen Manuel",
    "wof:placetype":"venue"
},
  "geometry": {"coordinates":[-5.9360356331,37.4093780518],"type":"Point"}
}