{
  "type": "Feature",
  "properties": {
    "iso:country":"ES",
    "sg:address":"Calle de San Rafael, S/n",
    "sg:city":"Fuensanta -villa Ines",
    "sg:orig_category":"Mec\u00c1nico Del Autom\u00d3vil",
    "sg:phone":"+34 950 14 00 30",
    "sg:postcode":"04230",
    "sg:province":"Almer\u00eda",
    "wof:name":"Talleres Sagredo S.l.l.",
    "wof:placetype":"venue"
},
  "geometry": {"coordinates":[-2.4457089901,36.8668937683],"type":"Point"}
}