{
  "type": "Feature",
  "properties": {
    "addr:full":"Rua San Miguel, 3 Ourense Ourense 32005",
    "addr:postcode":"32005",
    "addr:street":"Rua San Miguel 3",
    "iso:country":"ES",
    "sg:address":"Rua San Miguel, 3",
    "sg:city":"Ourense",
    "sg:orig_category":"Caf\u00c9s, Bares, Cervecer\u00cdas",
    "sg:phone":"+34 988 22 19 79",
    "sg:postcode":"32005",
    "sg:province":"Ourense",
    "wof:name":"Rivero Rodriguez Ignacio",
    "wof:placetype":"venue"
},
  "geometry": {"coordinates":[-7.8635997772,42.3375320435],"type":"Point"}
}