{
  "type": "Feature",
  "properties": {
    "addr:full":"Cami Son Rapinya, 5 Vileta -son Rapinya Islas Baleares 07013",
    "addr:housenumber":"5",
    "addr:postcode":"07013",
    "addr:street":"Rapinya;Vileta Son;Islas",
    "iso:country":"ES",
    "sg:address":"Cami Son Rapinya, 5",
    "sg:city":"Vileta -son Rapinya",
    "sg:orig_category":"Bisuter\u00cda, Joyer\u00cda, Relojer\u00cda (al Por Menor)",
    "sg:phone":"+34 971 79 25 14",
    "sg:postcode":"07013",
    "sg:province":"Islas Baleares",
    "wof:name":"Sanchez Manson Juan",
    "wof:placetype":"venue"
},
  "geometry": {"coordinates":[2.617784977,39.5850982666],"type":"Point"}
}