{
  "type": "Feature",
  "properties": {
    "addr:full":"Calle de Dario De Regoyos, 23 Irun Guip\u00f9zcoa 20305",
    "addr:housenumber":"23",
    "addr:postcode":"20305",
    "addr:street":"Calle De Dario De Regoyos;Guipu\u0300Zcoa",
    "iso:country":"ES",
    "sg:address":"Calle de Dario De Regoyos, 23",
    "sg:city":"Irun",
    "sg:orig_category":"Locales Y Clases De Danza",
    "sg:phone":"+34 943 63 38 88",
    "sg:postcode":"20305",
    "sg:province":"Guip\u00f9zcoa",
    "wof:name":"Maria Mercedes Filgueira Martin",
    "wof:placetype":"venue"
},
  "geometry": {"coordinates":[-1.7710057497,43.3415145874],"type":"Point"}
}