{
  "type": "Feature",
  "properties": {
    "addr:full":"Carrer de Enric Granados (d'), 16 Vilassar De Mar Barcelona 08340",
    "addr:housenumber":"16",
    "addr:postcode":"08340",
    "addr:street":"Carrer De Enric Granados D '",
    "iso:country":"ES",
    "sg:address":"Carrer de Enric Granados (d'), 16",
    "sg:city":"Vilassar De Mar",
    "sg:orig_category":"Inmobiliaria (agencias)",
    "sg:phone":"+34 937 50 23 15",
    "sg:postcode":"08340",
    "sg:province":"Barcelona",
    "wof:name":"Nacafi S.l.",
    "wof:placetype":"venue"
},
  "geometry": {"coordinates":[2.3969399929,41.5064888],"type":"Point"}
}