{
  "type": "Feature",
  "properties": {
    "iso:country":"ES",
    "sg:address":"Av Jaume Baladia, 5",
    "sg:city":"Argentona",
    "sg:orig_category":"Organizaciones Profesionales",
    "sg:phone":"+34 937 56 13 85",
    "sg:postcode":"08310",
    "sg:province":"Barcelona",
    "wof:name":"Servitec S.c.c.l",
    "wof:placetype":"venue"
},
  "geometry": {"coordinates":[2.3961999416,41.5508995056],"type":"Point"}
}