{
  "type": "Feature",
  "properties": {
    "addr:full":"Calle de Felipe Iv, 4 Madrid Madrid 28...",
    "addr:housenumber":"4;28 ...",
    "addr:street":"Calle De Felipe Iv;Madrid",
    "iso:country":"ES",
    "sg:address":"Calle de Felipe Iv, 4",
    "sg:city":"Madrid",
    "sg:orig_category":"Ense\u00d1anza, Formaci\u00d3n Profesional: Aprendizaje",
    "sg:phone":"+34 914 20 14 78",
    "sg:postcode":"28...",
    "sg:province":"Madrid",
    "wof:name":"Real Academia Espa\u00d1ola",
    "wof:placetype":"venue"
},
  "geometry": {"coordinates":[-3.6910610199,40.4150810242],"type":"Point"}
}