{
  "type": "Feature",
  "properties": {
    "addr:full":"Calle de Alberto Bosch, 9 Madrid Madrid 28014",
    "addr:housenumber":"9",
    "addr:postcode":"madrid;28014",
    "addr:street":"Calle De Alberto Bosch",
    "iso:country":"ES",
    "sg:address":"Calle de Alberto Bosch, 9",
    "sg:city":"Madrid",
    "sg:orig_category":"Aparatos De Medida, Control, Regulaci\u00d3n Y Detecci\u00d3n",
    "sg:phone":"+34 914 20 02 32",
    "sg:postcode":"28014",
    "sg:province":"Madrid",
    "sg:website":"www.arte-lab.com",
    "wof:name":"Rayxart Investigacion S.l.",
    "wof:placetype":"venue"
},
  "geometry": {"coordinates":[-3.6902372837,40.4134521484],"type":"Point"}
}