{
  "type": "Feature",
  "properties": {
    "iso:country":"ES",
    "sg:address":"Avda Francia (de), S/n",
    "sg:city":"Playa Del Ingles",
    "sg:orig_category":"Centros Comerciales Y Grandes Tiendas",
    "sg:phone":"+34 928 76 28 43",
    "sg:postcode":"35100",
    "sg:province":"Las Palmas",
    "wof:name":"Comunidad De Propietarios Centro Comercial Cita",
    "wof:placetype":"venue"
},
  "geometry": {"coordinates":[-15.5795240402,27.7507400513],"type":"Point"}
}