{
  "type": "Feature",
  "properties": {
    "iso:country":"ES",
    "sg:address":"Carrer de Antoni Gaudi, 28",
    "sg:city":"Reus",
    "sg:orig_category":"Ingeniero",
    "sg:phone":"+34 977 31 62 76",
    "sg:postcode":"43203",
    "sg:province":"Tarragona",
    "wof:name":"Pujol Mestre Jose Javier",
    "wof:placetype":"venue"
},
  "geometry": {"coordinates":[1.1066340208,41.1604690552],"type":"Point"}
}