{
  "type": "Feature",
  "properties": {
    "iso:country":"ES",
    "sg:address":"Camino El Jano, 1",
    "sg:city":"Valverde Virgen",
    "sg:orig_category":"Muebles, Minoristas",
    "sg:phone":"+34 987 30 34 06",
    "sg:postcode":"24391",
    "sg:province":"Le\u00f3n",
    "wof:name":"Paniagua Guardo Ramon",
    "wof:placetype":"venue"
},
  "geometry": {"coordinates":[-5.6784272194,42.5716629028],"type":"Point"}
}