{
  "type": "Feature",
  "properties": {
    "addr:full":"Calle de Serafin Morales, 3 Villablino Le\u00f3n 24100",
    "addr:housenumber":"3",
    "addr:postcode":"24100",
    "addr:street":"Calle De Serafin Morales",
    "iso:country":"ES",
    "sg:address":"Calle de Serafin Morales, 3",
    "sg:city":"Villablino",
    "sg:orig_category":"Cl\u00cdnicas M\u00c9dicas",
    "sg:phone":"+34 987 48 06 89",
    "sg:postcode":"24100",
    "sg:province":"Le\u00f3n",
    "wof:name":"Clinica Omedos S.l.",
    "wof:placetype":"venue"
},
  "geometry": {"coordinates":[-6.3223991394,42.9393348694],"type":"Point"}
}