{
  "type": "Feature",
  "properties": {
    "iso:country":"ES",
    "sg:address":"Calle de Mamariga, 10",
    "sg:city":"Santurtzi",
    "sg:orig_category":"Zapatos (al Por Menor)",
    "sg:phone":"+34 944 62 26 18",
    "sg:postcode":"48980",
    "sg:province":"Vizcaya",
    "wof:name":"Gomez Urresola S.l.",
    "wof:placetype":"venue"
},
  "geometry": {"coordinates":[-3.0363669395,43.3308258057],"type":"Point"}
}