{
  "type": "Feature",
  "properties": {
    "addr:full":"Calle de Juan Ramon Jimenez, 16 Palmas De Gran Canaria Las Palmas 35011",
    "addr:postcode":"35011",
    "addr:street":"Calle De Juan Ramon Jimenez 16",
    "iso:country":"ES",
    "sg:address":"Calle de Juan Ramon Jimenez, 16",
    "sg:city":"Palmas De Gran Canaria",
    "sg:orig_category":"Pescader\u00cdas (al Por Menor)",
    "sg:phone":"+34 928 25 92 74",
    "sg:postcode":"35011",
    "sg:province":"Las Palmas",
    "wof:name":"Franquiz Calero Blas",
    "wof:placetype":"venue"
},
  "geometry": {"coordinates":[-15.4359178543,28.1148986816],"type":"Point"}
}