{
  "type": "Feature",
  "properties": {
    "addr:full":"Calle de Jardin De Las Delicias, 34 San Jose Rinconada Sevilla 41300",
    "addr:housenumber":"34",
    "addr:postcode":"41300",
    "addr:street":"Calle De Jardin De Las Delicias",
    "iso:country":"ES",
    "sg:address":"Calle de Jardin De Las Delicias, 34",
    "sg:city":"San Jose Rinconada",
    "sg:orig_category":"Asociaciones Humanitarias, De Cooperaci\u00d3n, De Acci\u00d3n Social",
    "sg:phone":"+34 954 79 06 21",
    "sg:postcode":"41300",
    "sg:province":"Sevilla",
    "wof:name":"Asociacion Familiar De Ayuda A Deficientes Intelectuales",
    "wof:placetype":"venue"
},
  "geometry": {"coordinates":[-5.9364738464,37.4902648926],"type":"Point"}
}