{
  "type": "Feature",
  "properties": {
    "addr:full":"Calle de Ram De Viu, 18 Zaragoza Zaragoza 50006",
    "addr:housenumber":"18",
    "addr:postcode":"50006",
    "addr:street":"Calle De Ram De Viu",
    "iso:country":"ES",
    "sg:address":"Calle de Ram De Viu, 18",
    "sg:city":"Zaragoza",
    "sg:orig_category":"Asilos De Ancianos. Centros Privados",
    "sg:phone":"+34 976 35 03 46",
    "sg:postcode":"50006",
    "sg:province":"Zaragoza",
    "wof:name":"Hermanos Franciscanos De La Cruz Blanca",
    "wof:placetype":"venue"
},
  "geometry": {"coordinates":[-0.8936210275,41.6394805908],"type":"Point"}
}