{
  "type": "Feature",
  "properties": {
    "iso:country":"ES",
    "sg:address":"Carrer de Verdi, 288",
    "sg:city":"Barcelona",
    "sg:orig_category":"Molduras, Junquillos, Listones Y Molduras Perforadas",
    "sg:phone":"+34 932 84 95 58",
    "sg:postcode":"08024",
    "sg:province":"Barcelona",
    "wof:name":"Fernandez Tejerina Rafael",
    "wof:placetype":"venue"
},
  "geometry": {"coordinates":[2.1495029926,41.4118156433],"type":"Point"}
}