{
  "type": "Feature",
  "properties": {
    "addr:full":"Calle de Enmedio, 52 Castellon Castell\u00f3n 12001",
    "addr:housenumber":"52",
    "addr:postcode":"12001",
    "addr:street":"Calle De Enmedio",
    "iso:country":"ES",
    "sg:address":"Calle de Enmedio, 52",
    "sg:city":"Castellon",
    "sg:classifiers":[
        {
            "category":"Professional",
            "subcategory":"Research",
            "type":"Services"
        }
    ],
    "sg:phone":"+34 964 72 30 39",
    "sg:postcode":"12001",
    "sg:province":"Castell\u00f3n",
    "sg:tags":[
        "mercado",
        "de",
        "estudios"
    ],
    "wof:name":"Westland Asesores S.l.",
    "wof:placetype":"venue"
},
  "geometry": {"coordinates":[-0.0386217982,39.9860267639],"type":"Point"}
}