{
  "type": "Feature",
  "properties": {
    "iso:country":"ES",
    "sg:address":"Barr Larretxo Auzategia, 10",
    "sg:city":"Zumaia",
    "sg:orig_category":"Electricidad: Instaladores",
    "sg:phone":"+34 943 14 34 74",
    "sg:postcode":"20750",
    "sg:province":"Guip\u00f9zcoa",
    "wof:name":"Ekin Elektrizitatea S.l.",
    "wof:placetype":"venue"
},
  "geometry": {"coordinates":[-2.2593169212,43.2994499207],"type":"Point"}
}