{
  "type": "Feature",
  "properties": {
    "iso:country":"ES",
    "sg:address":"Calle de Luis Bu\u00d1uel, 12",
    "sg:city":"Teruel",
    "sg:orig_category":"Librer\u00cdas",
    "sg:phone":"+34 978 61 22 05",
    "sg:postcode":"44002",
    "sg:province":"Teruel",
    "wof:name":"Ayc Papelerias S.l.",
    "wof:placetype":"venue"
},
  "geometry": {"coordinates":[-1.0918800831,40.3324699402],"type":"Point"}
}