{
  "type": "Feature",
  "properties": {
    "addr:full":"Calle de Alvarez Abellan, 2 Madrid Madrid 28025",
    "addr:housenumber":"2",
    "addr:postcode":"28025",
    "addr:street":"Calle De Alvarez Abellan",
    "iso:country":"ES",
    "sg:address":"Calle de Alvarez Abellan, 2",
    "sg:city":"Madrid",
    "sg:orig_category":"Molduras, Junquillos, Listones Y Molduras Perforadas",
    "sg:phone":"+34 914 65 55 99",
    "sg:postcode":"28025",
    "sg:province":"Madrid",
    "wof:name":"Rodriguez Rodriguez Jose Maria",
    "wof:placetype":"venue"
},
  "geometry": {"coordinates":[-3.7311787605,40.3844528198],"type":"Point"}
}