{
  "type": "Feature",
  "properties": {
    "addr:full":"Calle de Feria, 13 Albacete Albacete 02005",
    "addr:housenumber":"13",
    "addr:postcode":"02005",
    "addr:street":"Calle De Feria",
    "iso:country":"ES",
    "sg:address":"Calle de Feria, 13",
    "sg:city":"Albacete",
    "sg:orig_category":"Electrodom\u00c9sticos (al Por Menor)",
    "sg:phone":"+34 967 21 91 39",
    "sg:postcode":"02005",
    "sg:province":"Albacete",
    "wof:name":"Electro-imagen Feria S.l.",
    "wof:placetype":"venue"
},
  "geometry": {"coordinates":[-1.8601690531,38.9959106445],"type":"Point"}
}