{
  "type": "Feature",
  "properties": {
    "addr:full":"Calle de Fermin Caballero, 52 Madrid Madrid 28034",
    "addr:housenumber":"52",
    "addr:postcode":"madrid;28034",
    "addr:street":"Calle De Fermin Caballero",
    "iso:country":"ES",
    "sg:address":"Calle de Fermin Caballero, 52",
    "sg:city":"Madrid",
    "sg:orig_category":"Ingenier\u00cda, Centros De Estudios (diversos)",
    "sg:phone":"+34 913 78 42 59",
    "sg:postcode":"28034",
    "sg:province":"Madrid",
    "wof:name":"Norte Procesos Termicos S.l.",
    "wof:placetype":"venue"
},
  "geometry": {"coordinates":[-3.7065858841,40.4844741821],"type":"Point"}
}