{
  "type": "Feature",
  "properties": {
    "addr:full":"Calle de Lima (de), 25 Fuenlabrada Madrid 28945",
    "addr:housenumber":"25",
    "addr:postcode":"28945",
    "addr:street":"Calle De Lima De",
    "iso:country":"ES",
    "sg:address":"Calle de Lima (de), 25",
    "sg:city":"Fuenlabrada",
    "sg:orig_category":"Arreglo, Reparaci\u00d3n, Piezas Sueltas De Televisi\u00d3n, V\u00cddeo, Hi",
    "sg:phone":"+34 916 97 46 19",
    "sg:postcode":"28945",
    "sg:province":"Madrid",
    "wof:name":"Martinez Garcia Jose Antonio",
    "wof:placetype":"venue"
},
  "geometry": {"coordinates":[-3.7899880409,40.2884254456],"type":"Point"}
}