{
  "type": "Feature",
  "properties": {
    "addr:full":"Carrer de Santuari, 16 Barcelona Barcelona 08032",
    "addr:housenumber":"16",
    "addr:postcode":"08032",
    "addr:street":"Carrer De Santuari",
    "iso:country":"ES",
    "sg:address":"Carrer de Santuari, 16",
    "sg:city":"Barcelona",
    "sg:orig_category":"Radiocomunicaciones, Telefon\u00cda M\u00d3vil, Radiomensajer\u00cda: Servicios, Comercializaci\u00d3n",
    "sg:phone":"+34 932 85 30 32",
    "sg:postcode":"08032",
    "sg:province":"Barcelona",
    "wof:name":"Adainara S.l.",
    "wof:placetype":"venue"
},
  "geometry": {"coordinates":[2.1503725052,41.4202575684],"type":"Point"}
}