{
  "type": "Feature",
  "properties": {
    "addr:full":"Plaz Tenerias, 6 Valladolid Valladolid 47006",
    "addr:housenumber":"6",
    "addr:postcode":"47006",
    "addr:street":"Plaz Tenerias",
    "iso:country":"ES",
    "sg:address":"Plaz Tenerias, 6",
    "sg:city":"Valladolid",
    "sg:orig_category":"Material Y Suministros Para Fotocopiadoras, Reprograf\u00cda",
    "sg:phone":"+34 983 35 62 59",
    "sg:postcode":"47006",
    "sg:province":"Valladolid",
    "wof:name":"Compania De Reprografia E Informatica De Valladolid S.l.",
    "wof:placetype":"venue"
},
  "geometry": {"coordinates":[-4.7336778641,41.6477737427],"type":"Point"}
}