{
  "type": "Feature",
  "properties": {
    "addr:full":"Avgd Del Cami Nou, 173 Xirivella Valencia 46950",
    "addr:housenumber":"173",
    "addr:postcode":"46950",
    "addr:street":"Nou",
    "iso:country":"ES",
    "sg:address":"Avgd Del Cami Nou, 173",
    "sg:city":"Xirivella",
    "sg:orig_category":"Cajas Para Embalar",
    "sg:phone":"+34 963 13 22 04",
    "sg:postcode":"46950",
    "sg:province":"Valencia",
    "wof:name":"Caja Rural De Torrente",
    "wof:placetype":"venue"
},
  "geometry": {"coordinates":[-0.4393720031,39.4618759155],"type":"Point"}
}