{
  "type": "Feature",
  "properties": {
    "iso:country":"ES",
    "sg:address":"Calle de Quintiliano, 4",
    "sg:city":"Logro\u00f1o",
    "sg:orig_category":"Venta, Alquiler De Instrumentos Y Accesorios De M\u00dasica",
    "sg:phone":"+34 941 23 41 31",
    "sg:postcode":"26004",
    "sg:province":"La Rioja",
    "wof:name":"Sancho Ochagavia Jesus Benigno",
    "wof:placetype":"venue"
},
  "geometry": {"coordinates":[-2.4341490269,42.4678993225],"type":"Point"}
}