{
  "type": "Feature",
  "properties": {
    "iso:country":"ES",
    "sg:address":"San Cristobal, 10",
    "sg:city":"Iru\u00f1a",
    "sg:orig_category":"\u00d3ptica: Instrumentos (fabricaci\u00d3n)",
    "sg:phone":"+34 948 13 47 88",
    "sg:postcode":"31015",
    "sg:province":"Navarra",
    "wof:name":"Centro Optico Pedro Duc S.l.",
    "wof:placetype":"venue"
},
  "geometry": {"coordinates":[-1.6312129498,42.8247261047],"type":"Point"}
}