{
  "type": "Feature",
  "properties": {
    "iso:country":"ES",
    "sg:address":"Plaz Santa Catalina, 1",
    "sg:city":"San Pedro",
    "sg:orig_category":"Peluquer\u00cdas, Peluquer\u00cda Mixta",
    "sg:phone":"+34 968 22 35 00",
    "sg:postcode":"30004",
    "sg:province":"Murcia",
    "wof:name":"Javier Hernandez Perez S.l.",
    "wof:placetype":"venue"
},
  "geometry": {"coordinates":[-0.8094211221,37.8065490723],"type":"Point"}
}