{
  "type": "Feature",
  "properties": {
    "addr:full":"La Fuente, S/n Villaobispo De Las Regueras Le\u00f3n 24007",
    "addr:housenumber":"s",
    "addr:postcode":"24007",
    "addr:street":"La Fuente;/ N",
    "iso:country":"ES",
    "sg:address":"La Fuente, S/n",
    "sg:city":"Villaobispo De Las Regueras",
    "sg:orig_category":"Cajas De Ahorro",
    "sg:phone":"+34 987 30 74 69",
    "sg:postcode":"24007",
    "sg:province":"Le\u00f3n",
    "sg:website":"www.cajaespana.es",
    "wof:name":"Caja Espa\u00f1a De Inversiones Caja De Ahorros Y Monte De Piedad",
    "wof:placetype":"venue"
},
  "geometry": {"coordinates":[-5.549446106,42.6165542603],"type":"Point"}
}