{
  "type": "Feature",
  "properties": {
    "iso:country":"ES",
    "sg:address":"Calle de Echegaray, 18",
    "sg:city":"Caudete",
    "sg:orig_category":"Alquiler De V\u00cddeo",
    "sg:phone":"+34 965 82 63 76",
    "sg:postcode":"02660",
    "sg:province":"Albacete",
    "wof:name":"Septimo Arte Caudete S.l.",
    "wof:placetype":"venue"
},
  "geometry": {"coordinates":[-0.9841219783,38.7040481567],"type":"Point"}
}