{
  "type": "Feature",
  "properties": {
    "addr:full":"Fusters, 2 Ciutadella Menorca Islas Baleares 07760",
    "addr:housenumber":"2",
    "addr:postcode":"07760",
    "addr:street":"Fusters",
    "iso:country":"ES",
    "sg:address":"Fusters, 2",
    "sg:city":"Ciutadella Menorca",
    "sg:orig_category":"Muebles, Minoristas",
    "sg:phone":"+34 971 38 47 36",
    "sg:postcode":"07760",
    "sg:province":"Islas Baleares",
    "wof:name":"Saura Miret Gabriel",
    "wof:placetype":"venue"
},
  "geometry": {"coordinates":[3.8529789448,40.0083999634],"type":"Point"}
}