{
  "type": "Feature",
  "properties": {
    "iso:country":"ES",
    "sg:address":"Calle de Oceano Atlantico (del), 2",
    "sg:city":"Coslada",
    "sg:orig_category":"Barnizadores",
    "sg:phone":"+34 916 72 42 02",
    "sg:postcode":"28820",
    "sg:province":"Madrid",
    "wof:name":"Morales Parejo Ricardo",
    "wof:placetype":"venue"
},
  "geometry": {"coordinates":[-3.5722239017,40.4176597595],"type":"Point"}
}