{
  "type": "Feature",
  "properties": {
    "addr:full":"Calle de Geminis, 36 Jerez De La Frontera C\u00e1diz 11406",
    "addr:housenumber":"36",
    "addr:postcode":"11406",
    "addr:street":"Calle De Geminis",
    "iso:country":"ES",
    "sg:address":"Calle de Geminis, 36",
    "sg:city":"Jerez De La Frontera",
    "sg:orig_category":"Fabricaci\u00d3n De Juguetes Autom\u00c1ticos",
    "sg:phone":"+34 956 33 41 50",
    "sg:postcode":"11406",
    "sg:province":"C\u00e1diz",
    "wof:name":"Automaticos Florida S.l",
    "wof:placetype":"venue"
},
  "geometry": {"coordinates":[-6.1018509865,36.6843757629],"type":"Point"}
}