{
  "type": "Feature",
  "properties": {
    "addr:full":"Av Severo Ochoa, 123 Hospitalet Llobregat Barcelona 08906",
    "addr:housenumber":"123",
    "addr:postcode":"08906",
    "addr:street":"Av Severo Ochoa",
    "iso:country":"ES",
    "sg:address":"Av Severo Ochoa, 123",
    "sg:city":"Hospitalet Llobregat",
    "sg:orig_category":"Molduras, Junquillos, Listones Y Molduras Perforadas",
    "sg:phone":"+34 934 37 03 94",
    "sg:postcode":"08906",
    "sg:province":"Barcelona",
    "wof:name":"Cervantes Campos Jose Manuel",
    "wof:placetype":"venue"
},
  "geometry": {"coordinates":[2.1035559177,41.3712921143],"type":"Point"}
}