{
  "type": "Feature",
  "properties": {
    "addr:full":"Avgd Gran Via, De La, 6 Soller Islas Baleares 07100",
    "addr:housenumber":"6",
    "addr:postcode":"07100",
    "addr:street":"Gran Via De La",
    "iso:country":"ES",
    "sg:address":"Avgd Gran Via, De La, 6",
    "sg:city":"Soller",
    "sg:orig_category":"Electricidad: Instaladores",
    "sg:phone":"+34 971 63 85 48",
    "sg:postcode":"07100",
    "sg:province":"Islas Baleares",
    "wof:name":"Electrica Serra Nord S.l.",
    "wof:placetype":"venue"
},
  "geometry": {"coordinates":[2.7147779465,39.7659072876],"type":"Point"}
}