{
  "type": "Feature",
  "properties": {
    "addr:full":"Calle de Fernando Camara Galvez, 7 Cuervo De Sevilla Sevilla 41749",
    "addr:housenumber":"7",
    "addr:postcode":"41749",
    "addr:street":"Calle De Fernando Camara Galvez",
    "iso:country":"ES",
    "sg:address":"Calle de Fernando Camara Galvez, 7",
    "sg:city":"Cuervo De Sevilla",
    "sg:orig_category":"Electrodom\u00c9sticos (fabricaci\u00d3n, Al Por Mayor)",
    "sg:phone":"+34 955 97 80 56",
    "sg:postcode":"41749",
    "sg:province":"Sevilla",
    "wof:name":"Cordero Gomez Miguel Angel",
    "wof:placetype":"venue"
},
  "geometry": {"coordinates":[-6.0391559601,36.8536529541],"type":"Point"}
}