{
  "type": "Feature",
  "properties": {
    "addr:full":"Calle de Burgense, 22 Burgos Burgos 09002",
    "addr:housenumber":"22",
    "addr:postcode":"09002",
    "addr:street":"Calle De Burgense",
    "iso:country":"ES",
    "sg:address":"Calle de Burgense, 22",
    "sg:city":"Burgos",
    "sg:orig_category":"Transportes Por V\u00cdas Navegables",
    "sg:phone":"+34 947 20 92 80",
    "sg:postcode":"09002",
    "sg:province":"Burgos",
    "wof:name":"Hernando Garcia Pablo",
    "wof:placetype":"venue"
},
  "geometry": {"coordinates":[-3.695401907,42.3386878967],"type":"Point"}
}