{
  "type": "Feature",
  "properties": {
    "addr:full":"Pase Fernando El Catolico, 8 Calatayud Zaragoza 50300",
    "addr:housenumber":"8",
    "addr:postcode":"50300",
    "addr:street":"Fernando El Catolico",
    "iso:country":"ES",
    "sg:address":"Pase Fernando El Catolico, 8",
    "sg:city":"Calatayud",
    "sg:orig_category":"Frutas, Legumbres Frescas Y Tempranas (al Por Menor)",
    "sg:phone":"+34 976 88 59 84",
    "sg:postcode":"50300",
    "sg:province":"Zaragoza",
    "wof:name":"Frutalda Hermanos Urmente",
    "wof:placetype":"venue"
},
  "geometry": {"coordinates":[-1.6401870251,41.3501243591],"type":"Point"}
}