{
  "type": "Feature",
  "properties": {
    "addr:full":"Plaz Villa (de La), 5 Ajalvir Madrid 28864",
    "addr:housenumber":"5",
    "addr:postcode":"28864",
    "addr:street":"Villa De La",
    "iso:country":"ES",
    "sg:address":"Plaz Villa (de La), 5",
    "sg:city":"Ajalvir",
    "sg:orig_category":"Molduras, Junquillos, Listones Y Molduras Perforadas",
    "sg:phone":"+34 918 84 35 13",
    "sg:postcode":"28864",
    "sg:province":"Madrid",
    "wof:name":"Mu\u00f1oz Funez Manuel",
    "wof:placetype":"venue"
},
  "geometry": {"coordinates":[-3.4803910255,40.5346984863],"type":"Point"}
}