{
  "type": "Feature",
  "properties": {
    "addr:full":"Calle de Rosario, 291 Viso Del Alcor Sevilla 41520",
    "addr:housenumber":"291",
    "addr:postcode":"41520",
    "addr:street":"Calle De Rosario",
    "iso:country":"ES",
    "sg:address":"Calle de Rosario, 291",
    "sg:city":"Viso Del Alcor",
    "sg:orig_category":"Molduras, Junquillos, Listones Y Molduras Perforadas",
    "sg:phone":"+34 955 74 04 79",
    "sg:postcode":"41520",
    "sg:province":"Sevilla",
    "wof:name":"Pertel S.cv.",
    "wof:placetype":"venue"
},
  "geometry": {"coordinates":[-5.7149319649,37.3914680481],"type":"Point"}
}