{
  "type": "Feature",
  "properties": {
    "addr:full":"Calle de Barrio Santa Ana, 44 Villanueva De Los Castillejos Huelva 21540",
    "addr:housenumber":"44",
    "addr:postcode":"21540",
    "addr:street":"Calle De Barrio Santa Ana",
    "iso:country":"ES",
    "sg:address":"Calle de Barrio Santa Ana, 44",
    "sg:city":"Villanueva De Los Castillejos",
    "sg:orig_category":"Empresas De Carpinter\u00cda De Madera",
    "sg:phone":"+34 959 38 72 77",
    "sg:postcode":"21540",
    "sg:province":"Huelva",
    "wof:name":"Perez Rodriguez Luciano",
    "wof:placetype":"venue"
},
  "geometry": {"coordinates":[-7.2718577385,37.4964675903],"type":"Point"}
}