{
  "type": "Feature",
  "properties": {
    "addr:full":"Barranco Balito, S/n Arguineguin-mogan Las Palmas 35120",
    "addr:housenumber":"s",
    "addr:postcode":"35120",
    "addr:street":"/ N Arguineguin-Mogan Las Palmas",
    "iso:country":"ES",
    "sg:address":"Barranco Balito, S/n",
    "sg:city":"Arguineguin-mogan",
    "sg:orig_category":"Empresas De Hormig\u00d3n, Hormig\u00d3n Armado Y Pretensado",
    "sg:phone":"+34 928 15 14 81",
    "sg:postcode":"35120",
    "sg:province":"Las Palmas",
    "wof:name":"Canary Concrete S.a.",
    "wof:placetype":"venue"
},
  "geometry": {"coordinates":[-15.6534442902,27.7624816895],"type":"Point"}
}