{
  "type": "Feature",
  "properties": {
    "iso:country":"ES",
    "sg:address":"Carr Pare Lluis Rodes, 20",
    "sg:city":"Santa Coloma De Farners",
    "sg:orig_category":"Institutos De Belleza",
    "sg:phone":"+34 972 84 12 04",
    "sg:postcode":"17430",
    "sg:province":"Girona",
    "wof:name":"Quirocos S.l.",
    "wof:placetype":"venue"
},
  "geometry": {"coordinates":[2.6631560326,41.8628921509],"type":"Point"}
}