{
  "type": "Feature",
  "properties": {
    "iso:country":"ES",
    "sg:address":"Calle de Oreja Marcelino, 7",
    "sg:city":"Bilbao",
    "sg:orig_category":"Peluquer\u00cdas, Peluquer\u00cda Mixta",
    "sg:phone":"+34 944 44 53 84",
    "sg:postcode":"48010",
    "sg:province":"Vizcaya",
    "wof:name":"Sara Gil Abad",
    "wof:placetype":"venue"
},
  "geometry": {"coordinates":[-2.9401040077,43.258140564],"type":"Point"}
}