{
  "type": "Feature",
  "properties": {
    "addr:full":"Calle de Verano, 25 Torrejon Ardoz Madrid 28850",
    "addr:housenumber":"25",
    "addr:postcode":"28850",
    "addr:street":"Calle De Verano",
    "iso:country":"ES",
    "sg:address":"Calle de Verano, 25",
    "sg:city":"Torrejon Ardoz",
    "sg:orig_category":"Art\u00cdculos De Limpieza Y De Cocina (fabricaci\u00d3n, Al Por Mayor)",
    "sg:phone":"+34 916 76 52 61",
    "sg:postcode":"28850",
    "sg:province":"Madrid",
    "wof:name":"Madrile\u00d1a De Utiles Y Maquinaria Para La Limpieza S.a.",
    "wof:placetype":"venue"
},
  "geometry": {"coordinates":[-3.4862658978,40.446346283],"type":"Point"}
}