{
  "type": "Feature",
  "properties": {
    "addr:full":"Carr Josep Maria Quadrado, 1 Eivissa Islas Baleares 07800",
    "addr:housenumber":"1",
    "addr:postcode":"07800",
    "addr:street":"Carr Josep Maria Quadrado",
    "iso:country":"ES",
    "sg:address":"Carr Josep Maria Quadrado, 1",
    "sg:city":"Eivissa",
    "sg:orig_category":"M\u00c9dicos: Cirug\u00cda Urol\u00d3gica",
    "sg:phone":"+34 971 19 10 53",
    "sg:postcode":"07800",
    "sg:province":"Islas Baleares",
    "wof:name":"Salva Verd Antonio",
    "wof:placetype":"venue"
},
  "geometry": {"coordinates":[1.4331690073,38.9107971191],"type":"Point"}
}