{
  "type": "Feature",
  "properties": {
    "addr:full":"Pedro Mateos, 11 Fuentes O\u00f1oro Salamanca 37480",
    "addr:housenumber":"11",
    "addr:postcode":"37480",
    "addr:street":"Pedro Mateos",
    "iso:country":"ES",
    "sg:address":"Pedro Mateos, 11",
    "sg:city":"Fuentes O\u00f1oro",
    "sg:orig_category":"Centros De Educaci\u00d3n Especial",
    "sg:phone":"+34 923 47 30 38",
    "sg:postcode":"37480",
    "sg:province":"Salamanca",
    "wof:name":"Colegio Rural Agrupado Campo De Arga\u00f1an",
    "wof:placetype":"venue"
},
  "geometry": {"coordinates":[-6.8109388351,40.5948791504],"type":"Point"}
}