{
  "type": "Feature",
  "properties": {
    "iso:country":"ES",
    "sg:address":"Calle de Italia, 12",
    "sg:city":"Valladolid",
    "sg:orig_category":"Hosteler\u00cda, Empleados",
    "sg:phone":"+34 983 27 79 32",
    "sg:postcode":"47007",
    "sg:province":"Valladolid",
    "wof:name":"Zhu  Bingzun",
    "wof:placetype":"venue"
},
  "geometry": {"coordinates":[-4.7347922325,41.6414222717],"type":"Point"}
}