{
  "type": "Feature",
  "properties": {
    "addr:full":"Calle de San Bartolome, S/n Torredelcampo Ja\u00e9n 23640",
    "addr:housenumber":"s",
    "addr:postcode":"23640",
    "addr:street":"Calle De San Bartolome;/ N;Jae\u0301N",
    "iso:country":"ES",
    "sg:address":"Calle de San Bartolome, S/n",
    "sg:city":"Torredelcampo",
    "sg:orig_category":"Negocio De Materiales De Construcci\u00d3n",
    "sg:phone":"+34 953 56 73 75",
    "sg:postcode":"23640",
    "sg:province":"Ja\u00e9n",
    "wof:name":"Almacenes Hueso S.l.l.",
    "wof:placetype":"venue"
},
  "geometry": {"coordinates":[-3.9013404846,37.7722129822],"type":"Point"}
}