{
  "type": "Feature",
  "properties": {
    "addr:full":"Calle de Clavel (el), 13 Santa Cruz De Tenerife Santa Cruz De Tenerife 38003",
    "addr:housenumber":"13",
    "addr:postcode":"38003",
    "addr:street":"Calle De Clavel El",
    "iso:country":"ES",
    "sg:address":"Calle de Clavel (el), 13",
    "sg:city":"Santa Cruz De Tenerife",
    "sg:orig_category":"Inform\u00c1tica, Ofim\u00c1tica (estudios, Asesor\u00cda, Ingenier\u00cda, Formaci\u00d3n)",
    "sg:phone":"+34 922 29 64 99",
    "sg:postcode":"38003",
    "sg:province":"Santa Cruz De Tenerife",
    "wof:name":"Fundacion Tripartita Para La Formacion En El Empleo",
    "wof:placetype":"venue"
},
  "geometry": {"coordinates":[-16.2495956421,28.4661445618],"type":"Point"}
}