{
  "type": "Feature",
  "properties": {
    "iso:country":"ES",
    "sg:address":"Rua Real, 17",
    "sg:city":"Ferrol",
    "sg:orig_category":"Muebles, Minoristas",
    "sg:phone":"+34 981 32 99 16",
    "sg:postcode":"15402",
    "sg:province":"La Coru\u00f1a",
    "wof:name":"Cassa Ferrol S.c.",
    "wof:placetype":"venue"
},
  "geometry": {"coordinates":[-8.2291212082,43.4854202271],"type":"Point"}
}