{
  "type": "Feature",
  "properties": {
    "iso:country":"ES",
    "sg:address":"Rua Lugo, 5",
    "sg:city":"Barco",
    "sg:orig_category":"Delegados, Agentes De Tr\u00c1nsito, Auxiliares De Transporte Internacional",
    "sg:phone":"+34 988 32 55 78",
    "sg:postcode":"32300",
    "sg:province":"Ourense",
    "wof:name":"Santin Martinez Maria Del Mar",
    "wof:placetype":"venue"
},
  "geometry": {"coordinates":[-6.9927258492,42.416053772],"type":"Point"}
}