{
  "type": "Feature",
  "properties": {
    "addr:full":"Calle de Ronda, 36 Rincon Victoria M\u00e1laga 29730",
    "addr:housenumber":"36",
    "addr:postcode":"29730",
    "addr:street":"Calle De Ronda;Ma\u0301Laga",
    "iso:country":"ES",
    "sg:address":"Calle de Ronda, 36",
    "sg:city":"Rincon Victoria",
    "sg:orig_category":"Tapicer\u00cdas",
    "sg:phone":"+34 952 40 84 78",
    "sg:postcode":"29730",
    "sg:province":"M\u00e1laga",
    "wof:name":"Frias Iglesias Pedro",
    "wof:placetype":"venue"
},
  "geometry": {"coordinates":[-4.2829170227,36.7156295776],"type":"Point"}
}