{
  "type": "Feature",
  "properties": {
    "addr:full":"Carr Alcalde Costa, 40 Lleida Lleida 25002",
    "addr:housenumber":"40",
    "addr:postcode":"25002",
    "addr:street":"Carr Alcalde Costa",
    "iso:country":"ES",
    "sg:address":"Carr Alcalde Costa, 40",
    "sg:city":"Lleida",
    "sg:classifiers":[
        {
            "category":"Cinema",
            "subcategory":"Movie Theater",
            "type":"Entertainment"
        }
    ],
    "sg:phone":"+34 973 27 06 80",
    "sg:postcode":"25002",
    "sg:province":"Lleida",
    "sg:tags":[
        "salas",
        "de",
        "cine"
    ],
    "wof:name":"Comunidad De Propietarios Alcalde Costa 40-44",
    "wof:placetype":"venue"
},
  "geometry": {"coordinates":[0.6181560159,41.6099853516],"type":"Point"}
}