{
  "type": "Feature",
  "properties": {
    "addr:full":"Calle de Guadalquivir, 8 Fuenlabrada Madrid 28947",
    "addr:housenumber":"8",
    "addr:postcode":"28947",
    "addr:street":"Calle De Guadalquivir",
    "iso:country":"ES",
    "sg:address":"Calle de Guadalquivir, 8",
    "sg:city":"Fuenlabrada",
    "sg:orig_category":"Acero: Productos Sider\u00dargicos Y Transformados (fabricaci\u00d3n, Negocio)",
    "sg:phone":"+34 916 42 23 00",
    "sg:postcode":"28947",
    "sg:province":"Madrid",
    "wof:name":"Ingenieria Y Tecnica Del Calor S. A.",
    "wof:placetype":"venue"
},
  "geometry": {"coordinates":[-3.7549393177,40.265296936],"type":"Point"}
}