{
  "type": "Feature",
  "properties": {
    "iso:country":"ES",
    "sg:address":"Ctra Olivenza, Km. 0004,7",
    "sg:city":"Badajoz",
    "sg:orig_category":"Muebles, Minoristas",
    "sg:phone":"+34 924 14 03 74",
    "sg:postcode":"06011",
    "sg:province":"Badajoz",
    "wof:name":"Asociacion Reto A La Esperanza",
    "wof:placetype":"venue"
},
  "geometry": {"coordinates":[-7.0390005112,38.8058815002],"type":"Point"}
}