{
  "type": "Feature",
  "properties": {
    "iso:country":"ES",
    "sg:address":"Carrer de Travessia, 2",
    "sg:city":"Barcelona",
    "sg:orig_category":"Peluquer\u00cdas, Peluquer\u00cda Mixta",
    "sg:phone":"+34 934 17 51 33",
    "sg:postcode":"08023",
    "sg:province":"Barcelona",
    "wof:name":"Mariscal Rovira Concepcion",
    "wof:placetype":"venue"
},
  "geometry": {"coordinates":[2.1462569237,41.4091033936],"type":"Point"}
}