{
  "type": "Feature",
  "properties": {
    "addr:full":"Carrer de Prat De La Riba (de), 1 Montornes Centre Barcelona 08170",
    "addr:postcode":"08170",
    "addr:street":"Carrer De Prat De La Riba De 1 Montornes Centre Barcelona",
    "iso:country":"ES",
    "sg:address":"Carrer de Prat De La Riba (de), 1",
    "sg:city":"Montornes Centre",
    "sg:orig_category":"Empresas De Carpinter\u00cda",
    "sg:phone":"+34 935 72 34 21",
    "sg:postcode":"08170",
    "sg:province":"Barcelona",
    "wof:name":"Eugema S.cv.",
    "wof:placetype":"venue"
},
  "geometry": {"coordinates":[2.2646450996,41.5443496704],"type":"Point"}
}