{
  "type": "Feature",
  "properties": {
    "addr:full":"Calle de Corredera, 250 Viso Del Alcor Sevilla 41520",
    "addr:housenumber":"250",
    "addr:postcode":"41520",
    "addr:street":"Calle De Corredera",
    "iso:country":"ES",
    "sg:address":"Calle de Corredera, 250",
    "sg:city":"Viso Del Alcor",
    "sg:orig_category":"Molduras, Junquillos, Listones Y Molduras Perforadas",
    "sg:phone":"+34 955 94 57 19",
    "sg:postcode":"41520",
    "sg:province":"Sevilla",
    "wof:name":"Falcon Jimenez Emilio",
    "wof:placetype":"venue"
},
  "geometry": {"coordinates":[-5.7188110352,37.3914642334],"type":"Point"}
}