{
  "type": "Feature",
  "properties": {
    "iso:country":"ES",
    "sg:address":"Calle de Errotazar Kalea, 18",
    "sg:city":"Irun",
    "sg:orig_category":"Asociaciones Humanitarias, De Cooperaci\u00d3n, De Acci\u00d3n Social",
    "sg:phone":"+34 943 63 54 84",
    "sg:postcode":"20305",
    "sg:province":"Guip\u00f9zcoa",
    "wof:name":"Asociacion Guipuzcoana De Familiares Y Enfermos Psiquicos",
    "wof:placetype":"venue"
},
  "geometry": {"coordinates":[-1.8193949461,43.3255996704],"type":"Point"}
}