{
  "type": "Feature",
  "properties": {
    "addr:full":"Calle de Bergara, 11 Donostia-san Sebastian Guip\u00f9zcoa 20005",
    "addr:housenumber":"11",
    "addr:postcode":"20005",
    "addr:street":"Calle De Bergara",
    "iso:country":"ES",
    "sg:address":"Calle de Bergara, 11",
    "sg:city":"Donostia-san Sebastian",
    "sg:orig_category":"Asociaciones, Organismos Culturales Y Socioeducativos",
    "sg:phone":"+34 943 43 06 78",
    "sg:postcode":"20005",
    "sg:province":"Guip\u00f9zcoa",
    "wof:name":"Sociedad Cultural Benefica Los Corcones",
    "wof:placetype":"venue"
},
  "geometry": {"coordinates":[-1.9801599979,43.3191719055],"type":"Point"}
}