{
  "type": "Feature",
  "properties": {
    "iso:country":"ES",
    "sg:address":"Carr Agulla, De L', 98",
    "sg:city":"Cala Ratjada",
    "sg:orig_category":"Molduras, Junquillos, Listones Y Molduras Perforadas",
    "sg:phone":"+34 971 56 45 45",
    "sg:postcode":"07590",
    "sg:province":"Islas Baleares",
    "wof:name":"Bonsol",
    "wof:placetype":"venue"
},
  "geometry": {"coordinates":[3.4626729488,39.7110137939],"type":"Point"}
}