{
  "type": "Feature",
  "properties": {
    "iso:country":"ES",
    "sg:address":"Calle de Mayor, 9",
    "sg:city":"Tineo",
    "sg:orig_category":"Librer\u00cdas",
    "sg:phone":"+34 985 80 18 43",
    "sg:postcode":"33870",
    "sg:province":"Asturias",
    "wof:name":"Rodriguez Perez Miguel Angel",
    "wof:placetype":"venue"
},
  "geometry": {"coordinates":[-6.4157958031,43.3344650269],"type":"Point"}
}