{
  "type": "Feature",
  "properties": {
    "addr:full":"Rua Paraguai, 16 Meicende La Coru\u00f1a 15140",
    "addr:housenumber":"16",
    "addr:postcode":"15140",
    "addr:street":"Rua Paraguai;La Corun\u0303A",
    "iso:country":"ES",
    "sg:address":"Rua Paraguai, 16",
    "sg:city":"Meicende",
    "sg:orig_category":"Materiales De Aislamiento T\u00c9rmico Y Ac\u00dastico",
    "sg:phone":"+34 981 14 12 20",
    "sg:postcode":"15140",
    "sg:province":"La Coru\u00f1a",
    "wof:name":"Decoplac Galicia S.l.",
    "wof:placetype":"venue"
},
  "geometry": {"coordinates":[-8.46671772,43.3288497925],"type":"Point"}
}