{
  "type": "Feature",
  "properties": {
    "iso:country":"ES",
    "sg:address":"Santo Domingo, 19",
    "sg:city":"Iru\u00f1a",
    "sg:orig_category":"Zapatos (al Por Menor)",
    "sg:phone":"+34 948 22 30 10",
    "sg:postcode":"31001",
    "sg:province":"Navarra",
    "wof:name":"Alves Rodrigues Guillermo",
    "wof:placetype":"venue"
},
  "geometry": {"coordinates":[-1.6449739933,42.8187141418],"type":"Point"}
}