{
  "type": "Feature",
  "properties": {
    "addr:full":"Carrer de Nou, 33 Vic Barcelona 08500",
    "addr:housenumber":"33",
    "addr:postcode":"08500",
    "addr:street":"Carrer De Nou",
    "iso:country":"ES",
    "sg:address":"Carrer de Nou, 33",
    "sg:city":"Vic",
    "sg:orig_category":"Loter\u00cda Y T\u00d3mbola",
    "sg:phone":"+34 938 86 11 84",
    "sg:postcode":"08500",
    "sg:province":"Barcelona",
    "wof:name":"Dosta Vidal David",
    "wof:placetype":"venue"
},
  "geometry": {"coordinates":[2.2566239834,41.9320793152],"type":"Point"}
}