{
  "type": "Feature",
  "properties": {
    "addr:full":"Calle de Federico Garcia Lorca (de), 22 Mejorada Campo Madrid 28840",
    "addr:housenumber":"22",
    "addr:postcode":"28840",
    "addr:street":"Calle De Federico Garcia Lorca De",
    "iso:country":"ES",
    "sg:address":"Calle de Federico Garcia Lorca (de), 22",
    "sg:city":"Mejorada Campo",
    "sg:orig_category":"Poller\u00cda Y Caza (al Por Menor)",
    "sg:phone":"+34 916 79 05 57",
    "sg:postcode":"28840",
    "sg:province":"Madrid",
    "wof:name":"Guijarro Alvarez Luis",
    "wof:placetype":"venue"
},
  "geometry": {"coordinates":[-3.4857573509,40.3984451294],"type":"Point"}
}