{
  "type": "Feature",
  "properties": {
    "addr:full":"Calle de Julian Sanchez, 2 Ciudad Rodrigo Salamanca 37500",
    "addr:housenumber":"2",
    "addr:postcode":"37500",
    "addr:street":"Calle De Julian Sanchez",
    "iso:country":"ES",
    "sg:address":"Calle de Julian Sanchez, 2",
    "sg:city":"Ciudad Rodrigo",
    "sg:orig_category":"Carnicer\u00cdas, Carnicer\u00cdas",
    "sg:phone":"+34 923 46 02 44",
    "sg:postcode":"37500",
    "sg:province":"Salamanca",
    "wof:name":"Perez Martin Maria Teresa",
    "wof:placetype":"venue"
},
  "geometry": {"coordinates":[-6.5337519646,40.5977134705],"type":"Point"}
}