{
  "type": "Feature",
  "properties": {
    "addr:full":"Calle de Camino Ancho, 11 Benavente Zamora 49600",
    "addr:housenumber":"11",
    "addr:postcode":"49600",
    "addr:street":"Calle De Camino Ancho",
    "iso:country":"ES",
    "sg:address":"Calle de Camino Ancho, 11",
    "sg:city":"Benavente",
    "sg:orig_category":"Productos Alimentarios",
    "sg:phone":"+34 980 63 22 05",
    "sg:postcode":"49600",
    "sg:province":"Zamora",
    "wof:name":"Mielgo Carton Maria Del Transito",
    "wof:placetype":"venue"
},
  "geometry": {"coordinates":[-5.6868891716,42.0083427429],"type":"Point"}
}