{
  "type": "Feature",
  "properties": {
    "addr:full":"Calle de Paz, 18 Herencia Ciudad Real 13640",
    "addr:housenumber":"18",
    "addr:postcode":"13640",
    "addr:street":"Calle De Paz",
    "iso:country":"ES",
    "sg:address":"Calle de Paz, 18",
    "sg:city":"Herencia",
    "sg:orig_category":"Peluqueros: De Se\u00d1oras",
    "sg:phone":"+34 926 57 22 72",
    "sg:postcode":"13640",
    "sg:province":"Ciudad Real",
    "wof:name":"Corrales Ramos Maria Del Pilar",
    "wof:placetype":"venue"
},
  "geometry": {"coordinates":[-3.3567430973,39.3689918518],"type":"Point"}
}