{
  "type": "Feature",
  "properties": {
    "iso:country":"ES",
    "sg:address":"Calle de Arriba, 22",
    "sg:city":"Tejina",
    "sg:orig_category":"Ropa Para Se\u00d1oras (al Por Menor)",
    "sg:phone":"+34 922 54 44 07",
    "sg:postcode":"38260",
    "sg:province":"Santa Cruz De Tenerife",
    "wof:name":"Hernandez Alonso Marian",
    "wof:placetype":"venue"
},
  "geometry": {"coordinates":[-16.3612346649,28.5329780579],"type":"Point"}
}