{
  "type": "Feature",
  "properties": {
    "iso:country":"ES",
    "sg:address":"Calle de Hilario Marco, 52",
    "sg:city":"Cazorla",
    "sg:orig_category":"Empresas De Carpinter\u00cda Met\u00c1lica",
    "sg:phone":"+34 953 72 19 02",
    "sg:postcode":"23470",
    "sg:province":"Ja\u00e9n",
    "wof:name":"Vadillo Gomez Emilio",
    "wof:placetype":"venue"
},
  "geometry": {"coordinates":[-3.0047500134,37.9151268005],"type":"Point"}
}