{
  "type": "Feature",
  "properties": {
    "addr:full":"Trav Dalt, 26 Barcelona Barcelona 08024",
    "addr:housenumber":"26",
    "addr:postcode":"08024",
    "addr:street":"Trav Dalt",
    "iso:country":"ES",
    "sg:address":"Trav Dalt, 26",
    "sg:city":"Barcelona",
    "sg:orig_category":"\u00d3ptica: Instrumentos (fabricaci\u00d3n)",
    "sg:phone":"+34 932 18 65 64",
    "sg:postcode":"08024",
    "sg:province":"Barcelona",
    "wof:name":"General Optica S.a.",
    "wof:placetype":"venue"
},
  "geometry": {"coordinates":[2.1528630257,41.4085884094],"type":"Point"}
}