{
  "type": "Feature",
  "properties": {
    "iso:country":"ES",
    "sg:address":"Calle de Terbio, 20",
    "sg:city":"Sevilla",
    "sg:orig_category":"Chapister\u00cda",
    "sg:phone":"+34 954 36 20 62",
    "sg:postcode":"41007",
    "sg:province":"Sevilla",
    "wof:name":"Marquez Lebrero Marcos",
    "wof:placetype":"venue"
},
  "geometry": {"coordinates":[-5.9562196732,37.4079551697],"type":"Point"}
}