{
  "type": "Feature",
  "properties": {
    "iso:country":"ES",
    "sg:address":"Calle de Merecillas, 20",
    "sg:city":"Antequera",
    "sg:orig_category":"Sociedades, Compa\u00d1\u00cdas Aseguradoras",
    "sg:phone":"+34 952 84 17 88",
    "sg:postcode":"29200",
    "sg:province":"M\u00e1laga",
    "wof:name":"Compa\u00f1ia De Seguros Adeslas S.a.",
    "wof:placetype":"venue"
},
  "geometry": {"coordinates":[-4.5618510246,37.0211105347],"type":"Point"}
}