{
  "type": "Feature",
  "properties": {
    "iso:country":"ES",
    "sg:address":"Cmno Palma Romero, 3",
    "sg:city":"Gamonal Bajo",
    "sg:orig_category":"Inversiones",
    "sg:phone":"+34 928 64 25 92",
    "sg:postcode":"35300",
    "sg:province":"Las Palmas",
    "wof:name":"Decef S.l.",
    "wof:placetype":"venue"
},
  "geometry": {"coordinates":[-15.4988956451,28.0369472504],"type":"Point"}
}