{
  "type": "Feature",
  "properties": {
    "addr:full":"Carrer de Rafael De Casanova, 64 Molins Rei Barcelona 08750",
    "addr:housenumber":"64",
    "addr:postcode":"08750",
    "addr:street":"Carrer De Rafael De Casanova;Barcelona",
    "iso:country":"ES",
    "sg:address":"Carrer de Rafael De Casanova, 64",
    "sg:city":"Molins Rei",
    "sg:orig_category":"Inmobiliaria (agencias)",
    "sg:phone":"+34 936 80 37 90",
    "sg:postcode":"08750",
    "sg:province":"Barcelona",
    "wof:name":"Novenia Gestores Inmobiliarios S.l.",
    "wof:placetype":"venue"
},
  "geometry": {"coordinates":[2.0158619881,41.4128761292],"type":"Point"}
}