{
  "type": "Feature",
  "properties": {
    "addr:full":"Calle de Berenisa, 24 Madrid Madrid 28023",
    "addr:housenumber":"24",
    "addr:postcode":"madrid;28023",
    "addr:street":"Calle De Berenisa",
    "iso:country":"ES",
    "sg:address":"Calle de Berenisa, 24",
    "sg:city":"Madrid",
    "sg:orig_category":"Peluqueros: De Se\u00d1oras",
    "sg:phone":"+34 917 40 27 07",
    "sg:postcode":"28023",
    "sg:province":"Madrid",
    "wof:name":"Garcia Arroyo Juan Jose",
    "wof:placetype":"venue"
},
  "geometry": {"coordinates":[-3.7817234993,40.458026886],"type":"Point"}
}