{
  "type": "Feature",
  "properties": {
    "addr:full":"Calle de Del Fuerte, 26 San Martin Trevejo C\u00e1ceres 10892",
    "addr:housenumber":"26",
    "addr:postcode":"10892",
    "addr:street":"Calle De Del Fuerte;Ca\u0301Ceres",
    "iso:country":"ES",
    "sg:address":"Calle de Del Fuerte, 26",
    "sg:city":"San Martin Trevejo",
    "sg:orig_category":"Frutas, Legumbres Frescas Y Tempranas (al Por Menor)",
    "sg:phone":"+34 927 14 42 67",
    "sg:postcode":"10892",
    "sg:province":"C\u00e1ceres",
    "wof:name":"Almaraz Almaraz Esmeralda",
    "wof:placetype":"venue"
},
  "geometry": {"coordinates":[-6.7972559929,40.2131614685],"type":"Point"}
}