{
  "type": "Feature",
  "properties": {
    "addr:full":"Calle de Romero Leal, 1 Merida Badajoz 06800",
    "addr:housenumber":"1",
    "addr:postcode":"06800",
    "addr:street":"Calle De Romero Leal",
    "iso:country":"ES",
    "sg:address":"Calle de Romero Leal, 1",
    "sg:city":"Merida",
    "sg:orig_category":"Promotores Constructores",
    "sg:phone":"+34 924 30 43 12",
    "sg:postcode":"06800",
    "sg:province":"Badajoz",
    "wof:name":"Intermerida Trade S.l.",
    "wof:placetype":"venue"
},
  "geometry": {"coordinates":[-6.3458127975,38.9157409668],"type":"Point"}
}