{
  "type": "Feature",
  "properties": {
    "addr:full":"Calle de Quasimodo, 16 Malaga M\u00e1laga 29006",
    "addr:housenumber":"16",
    "addr:postcode":"29006",
    "addr:street":"Calle De Quasimodo;Ma\u0301Laga",
    "iso:country":"ES",
    "sg:address":"Calle de Quasimodo, 16",
    "sg:city":"Malaga",
    "sg:classifiers":[
        {
            "category":"Professional",
            "subcategory":"Management & Consulting",
            "type":"Services"
        }
    ],
    "sg:phone":"+34 952 31 09 19",
    "sg:postcode":"29006",
    "sg:province":"M\u00e1laga",
    "sg:tags":[
        "asesor\u00cda",
        "en",
        "marketing"
    ],
    "wof:name":"Alba Moreno Miguel Angel",
    "wof:placetype":"venue"
},
  "geometry": {"coordinates":[-4.4649195671,36.7106933594],"type":"Point"}
}