{
  "type": "Feature",
  "properties": {
    "addr:full":"Avda Jose Maria Alcaraz Y Alenda, S/n Badajoz Badajoz 06011",
    "addr:housenumber":"s / n",
    "addr:postcode":"06011",
    "addr:street":"Avda Jose Maria Alcaraz Y Alenda",
    "iso:country":"ES",
    "sg:address":"Avda Jose Maria Alcaraz Y Alenda, S/n",
    "sg:city":"Badajoz",
    "sg:orig_category":"Tiendas De Grano, Frutas Y Legumbres Secas (al Por Menor)",
    "sg:phone":"+34 924 24 13 83",
    "sg:postcode":"06011",
    "sg:province":"Badajoz",
    "wof:name":"Productos Alimenticios Belros S.a.",
    "wof:placetype":"venue"
},
  "geometry": {"coordinates":[-6.9947738647,38.8652305603],"type":"Point"}
}