{
  "type": "Feature",
  "properties": {
    "iso:country":"ES",
    "sg:address":"Calle de Cine, 5",
    "sg:city":"Madrid",
    "sg:orig_category":"Inmobiliaria (agencias)",
    "sg:phone":"+34 917 11 52 26",
    "sg:postcode":"28024",
    "sg:province":"Madrid",
    "sg:website":"www.oramba.com",
    "wof:name":"Oramba S.a.",
    "wof:placetype":"venue"
},
  "geometry": {"coordinates":[-3.7731533051,40.3936271667],"type":"Point"}
}