{
  "type": "Feature",
  "properties": {
    "addr:full":"Calle de Balejo, 7 San Vicente De Barakaldo Vizcaya 48903",
    "addr:housenumber":"7",
    "addr:postcode":"48903",
    "addr:street":"Calle De Balejo",
    "iso:country":"ES",
    "sg:address":"Calle de Balejo, 7",
    "sg:city":"San Vicente De Barakaldo",
    "sg:orig_category":"Mec\u00c1nico Del Autom\u00d3vil",
    "sg:phone":"+34 944 99 49 51",
    "sg:postcode":"48903",
    "sg:province":"Vizcaya",
    "wof:name":"Reparaciones Del Automovil S.l.l.",
    "wof:placetype":"venue"
},
  "geometry": {"coordinates":[-2.9836814404,43.2840232849],"type":"Point"}
}