{
  "type": "Feature",
  "properties": {
    "addr:full":"Calle de Ponferrada, 49 Madrid Madrid 28029",
    "addr:housenumber":"49",
    "addr:postcode":"madrid;28029",
    "addr:street":"Calle De Ponferrada",
    "iso:country":"ES",
    "sg:address":"Calle de Ponferrada, 49",
    "sg:city":"Madrid",
    "sg:orig_category":"Muebles, Minoristas",
    "sg:phone":"+34 913 86 17 45",
    "sg:postcode":"28029",
    "sg:province":"Madrid",
    "wof:name":"Gasig S.a.",
    "wof:placetype":"venue"
},
  "geometry": {"coordinates":[-3.7120599747,40.4758300781],"type":"Point"}
}