{
  "type": "Feature",
  "properties": {
    "iso:country":"ES",
    "sg:address":"Calle de Artesa De Segre, 18",
    "sg:city":"Madrid",
    "sg:orig_category":"Ingenier\u00cda, Centros De Estudios (diversos)",
    "sg:phone":"+34 913 16 90 47",
    "sg:postcode":"28035",
    "sg:province":"Madrid",
    "wof:name":"Hernando Valdizan Paulina",
    "wof:placetype":"venue"
},
  "geometry": {"coordinates":[-3.727925539,40.4708480835],"type":"Point"}
}