{
  "type": "Feature",
  "properties": {
    "iso:country":"ES",
    "sg:address":"Praj Club De Tenis, S/n",
    "sg:city":"Urbanizacion Club De Tenis",
    "sg:orig_category":"Art\u00cdculos De Aluminio",
    "sg:phone":"+34 950 30 19 67",
    "sg:postcode":"04230",
    "sg:province":"Almer\u00eda",
    "wof:name":"Almetal Carpinteria Metalica S.l.",
    "wof:placetype":"venue"
},
  "geometry": {"coordinates":[-2.4679217339,36.8401641846],"type":"Point"}
}