{
  "type": "Feature",
  "properties": {
    "iso:country":"ES",
    "sg:address":"Av El Textil, S/n",
    "sg:city":"Ontinyent",
    "sg:orig_category":"Veh\u00cdculos De Ocasi\u00d3n",
    "sg:phone":"+34 962 38 40 51",
    "sg:postcode":"46870",
    "sg:province":"Valencia",
    "wof:name":"Edit Service C.b.",
    "wof:placetype":"venue"
},
  "geometry": {"coordinates":[-0.5965790153,38.8259315491],"type":"Point"}
}