{
  "type": "Feature",
  "properties": {
    "addr:full":"Calle de Cuba, 1 Parla Madrid 28980",
    "addr:housenumber":"1",
    "addr:postcode":"28980",
    "addr:street":"Calle De Cuba",
    "iso:country":"ES",
    "sg:address":"Calle de Cuba, 1",
    "sg:city":"Parla",
    "sg:orig_category":"Caf\u00c9s, Bares, Cervecer\u00cdas",
    "sg:phone":"+34 916 98 52 57",
    "sg:postcode":"28980",
    "sg:province":"Madrid",
    "wof:name":"Sacristan Velasco Eugenio",
    "wof:placetype":"venue"
},
  "geometry": {"coordinates":[-3.7666900158,40.2298126221],"type":"Point"}
}