{
  "type": "Feature",
  "properties": {
    "addr:full":"Carretera Pandorado, S/n Sope\u00f1a Carneros Le\u00f3n 24719",
    "addr:housenumber":"s",
    "addr:postcode":"24719",
    "addr:street":"Carretera Pandorado;/ N Sopen\u0303A Carneros Leo\u0301N",
    "iso:country":"ES",
    "sg:address":"Carretera Pandorado, S/n",
    "sg:city":"Sope\u00f1a Carneros",
    "sg:orig_category":"Pompas F\u00danebres, Inhumaciones Y Cremaciones",
    "sg:phone":"+34 987 60 32 65",
    "sg:postcode":"24719",
    "sg:province":"Le\u00f3n",
    "wof:name":"Arias Martinez Angel",
    "wof:placetype":"venue"
},
  "geometry": {"coordinates":[-6.0470795631,42.4750366211],"type":"Point"}
}