{
  "type": "Feature",
  "properties": {
    "iso:country":"ES",
    "sg:address":"Calle de Palencia, 2",
    "sg:city":"Segovia",
    "sg:orig_category":"M\u00c9dicos: Estomatolog\u00cda",
    "sg:phone":"+34 921 43 00 21",
    "sg:postcode":"40004",
    "sg:province":"Segovia",
    "wof:name":"Capurro Chianale David Oscar",
    "wof:placetype":"venue"
},
  "geometry": {"coordinates":[-4.1018691063,40.9448242188],"type":"Point"}
}