{
  "type": "Feature",
  "properties": {
    "iso:country":"ES",
    "sg:address":"Avda Montevideo Etorbidea, 15",
    "sg:city":"Durango",
    "sg:orig_category":"Pintura Y Barniz (al Por Menor)",
    "sg:phone":"+34 946 20 17 52",
    "sg:postcode":"48200",
    "sg:province":"Vizcaya",
    "wof:name":"Aramburu Machain Pedro",
    "wof:placetype":"venue"
},
  "geometry": {"coordinates":[-2.6281394958,43.1696166992],"type":"Point"}
}