{
  "type": "Feature",
  "properties": {
    "iso:country":"ES",
    "sg:address":"Calle de Ramon Y Cajal, 33",
    "sg:city":"Villanueva Serena",
    "sg:orig_category":"Perfumer\u00cda (al Por Menor)",
    "sg:phone":"+34 924 84 14 79",
    "sg:postcode":"06700",
    "sg:province":"Badajoz",
    "wof:name":"Diez Ramos Alfonso",
    "wof:placetype":"venue"
},
  "geometry": {"coordinates":[-5.7978467941,38.9742050171],"type":"Point"}
}