{
  "type": "Feature",
  "properties": {
    "addr:full":"Carr Belgica, 57 Badalona Barcelona 08917",
    "addr:housenumber":"57",
    "addr:postcode":"08917",
    "addr:street":"Carr Belgica",
    "iso:country":"ES",
    "sg:address":"Carr Belgica, 57",
    "sg:city":"Badalona",
    "sg:orig_category":"Muebles, Minoristas",
    "sg:phone":"+34 934 97 01 05",
    "sg:postcode":"08917",
    "sg:province":"Barcelona",
    "wof:name":"Juirce S.l.",
    "wof:placetype":"venue"
},
  "geometry": {"coordinates":[2.2236700058,41.4585609436],"type":"Point"}
}