{
  "type": "Feature",
  "properties": {
    "addr:full":"Rua Xoan De Novoa, 12 Ourense Ourense 32004",
    "addr:housenumber":"12",
    "addr:postcode":"32004",
    "addr:street":"Rua Xoan De Novoa",
    "iso:country":"ES",
    "sg:address":"Rua Xoan De Novoa, 12",
    "sg:city":"Ourense",
    "sg:orig_category":"Inmobiliaria (agencias)",
    "sg:phone":"+34 988 24 89 80",
    "sg:postcode":"32004",
    "sg:province":"Ourense",
    "wof:name":"Lama Lama Maria Enriqueta",
    "wof:placetype":"venue"
},
  "geometry": {"coordinates":[-7.8585391045,42.341091156],"type":"Point"}
}