{
  "type": "Feature",
  "properties": {
    "iso:country":"ES",
    "sg:address":"Carrer de Pauls (de), 9",
    "sg:city":"Tortosa",
    "sg:orig_category":"Agencias Y Agentes Comerciales, Representantes",
    "sg:phone":"+34 977 50 15 66",
    "sg:postcode":"43500",
    "sg:province":"Tarragona",
    "wof:name":"Gonzalez Cerveto Regina",
    "wof:placetype":"venue"
},
  "geometry": {"coordinates":[0.5209109783,40.8127632141],"type":"Point"}
}