{
  "type": "Feature",
  "properties": {
    "iso:country":"ES",
    "sg:address":"Avda Juan Sebastian Elcano, 182",
    "sg:city":"Malaga",
    "sg:orig_category":"Centros De Coordinaci\u00d3n",
    "sg:phone":"+34 952 29 24 16",
    "sg:postcode":"29017",
    "sg:province":"M\u00e1laga",
    "wof:name":"Luis Alonso E Hijos Consulting S.l.",
    "wof:placetype":"venue"
},
  "geometry": {"coordinates":[-4.3604331017,36.7210006714],"type":"Point"}
}