{
  "type": "Feature",
  "properties": {
    "addr:full":"Moreda, S/n Lanzos Lugo 27816",
    "addr:housenumber":"s",
    "addr:postcode":"27816",
    "addr:street":"Moreda;/ N",
    "iso:country":"ES",
    "sg:address":"Moreda, S/n",
    "sg:city":"Lanzos",
    "sg:orig_category":"Centros De Educaci\u00d3n Especial",
    "sg:phone":"+34 982 51 14 04",
    "sg:postcode":"27816",
    "sg:province":"Lugo",
    "wof:name":"Ayuntamiento De Villalba Grupo Escolar De Moreda",
    "wof:placetype":"venue"
},
  "geometry": {"coordinates":[-7.5558514595,43.0120849609],"type":"Point"}
}