{
  "type": "Feature",
  "properties": {
    "addr:full":"Carretera Figueres A Roses, Km. 0029,9 Vila-sacra Girona 17485",
    "addr:postcode":"17485",
    "addr:street":"Carretera Figueres;Roses Km. 0029,9",
    "iso:country":"ES",
    "sg:address":"Carretera Figueres A Roses, Km. 0029,9",
    "sg:city":"Vila-sacra",
    "sg:orig_category":"Muebles, Minoristas",
    "sg:phone":"+34 972 67 58 34",
    "sg:postcode":"17485",
    "sg:province":"Girona",
    "wof:name":"Sanmiquel Sanchez Jose",
    "wof:placetype":"venue"
},
  "geometry": {"coordinates":[3.0190849304,42.265460968],"type":"Point"}
}