{
  "type": "Feature",
  "properties": {
    "addr:full":"Calle de Covadonga, 3 Barrio De Peral Murcia 30300",
    "addr:housenumber":"3",
    "addr:postcode":"30300",
    "addr:street":"Calle De Covadonga",
    "iso:country":"ES",
    "sg:address":"Calle de Covadonga, 3",
    "sg:city":"Barrio De Peral",
    "sg:orig_category":"Librer\u00cdas",
    "sg:phone":"+34 968 51 05 87",
    "sg:postcode":"30300",
    "sg:province":"Murcia",
    "wof:name":"Palacios Garcia Francisco Javier",
    "wof:placetype":"venue"
},
  "geometry": {"coordinates":[-1.1298867464,37.9834747314],"type":"Point"}
}