{
  "type": "Feature",
  "properties": {
    "addr:full":"Calle de Ruiz De Moros, S/n Alca\u00f1iz Teruel 44600",
    "addr:housenumber":"s",
    "addr:postcode":"44600",
    "addr:street":"Calle De Ruiz De Moros;/ N",
    "iso:country":"ES",
    "sg:address":"Calle de Ruiz De Moros, S/n",
    "sg:city":"Alca\u00f1iz",
    "sg:orig_category":"Sindicatos De Trabajadores",
    "sg:phone":"+34 978 87 05 83",
    "sg:postcode":"44600",
    "sg:province":"Teruel",
    "wof:name":"Union Sindical De Comisiones Obreras De Aragon",
    "wof:placetype":"venue"
},
  "geometry": {"coordinates":[-0.127324,41.0456466675],"type":"Point"}
}