{
  "type": "Feature",
  "properties": {
    "addr:full":"Calle de Pantano De La Serena, S/n Vaguadas Badajoz 06010",
    "addr:postcode":"06010",
    "addr:street":"Calle De Pantano De La;S / N Vaguadas",
    "iso:country":"ES",
    "sg:address":"Calle de Pantano De La Serena, S/n",
    "sg:city":"Vaguadas",
    "sg:orig_category":"Alimentaci\u00d3n General (al Por Menor)",
    "sg:phone":"+34 924 26 77 87",
    "sg:postcode":"06010",
    "sg:province":"Badajoz",
    "wof:name":"Rodriguez Gonzalez Rafael",
    "wof:placetype":"venue"
},
  "geometry": {"coordinates":[-6.9686741829,38.8466033936],"type":"Point"}
}