{
  "type": "Feature",
  "properties": {
    "iso:country":"ES",
    "sg:address":"Carr Cap Negre, Des, 9",
    "sg:city":"Poima",
    "sg:orig_category":"Transportes Por Carretera: Lotes Completos, Mercanc\u00cdas Diversas",
    "sg:phone":"+34 971 36 57 33",
    "sg:postcode":"07714",
    "sg:province":"Islas Baleares",
    "wof:name":"Transportes Y Gruas Salom S.a.",
    "wof:placetype":"venue"
},
  "geometry": {"coordinates":[2.9117100239,39.6136398315],"type":"Point"}
}