{
  "type": "Feature",
  "properties": {
    "addr:full":"Calle de Andres Bernaldez, 13 Sevilla Sevilla 41005",
    "addr:housenumber":"13",
    "addr:postcode":"41005",
    "addr:street":"Calle De Andres Bernaldez",
    "iso:country":"ES",
    "sg:address":"Calle de Andres Bernaldez, 13",
    "sg:city":"Sevilla",
    "sg:orig_category":"Farmacias",
    "sg:phone":"+34 954 57 39 05",
    "sg:postcode":"41005",
    "sg:province":"Sevilla",
    "wof:name":"Gomez Cabrera Maria Isabel",
    "wof:placetype":"venue"
},
  "geometry": {"coordinates":[-5.9631733894,37.3863487244],"type":"Point"}
}