{
  "type": "Feature",
  "properties": {
    "iso:country":"ES",
    "sg:address":"Calle de Galena, 197",
    "sg:city":"Valladolid",
    "sg:orig_category":"Material Y Herramientas Agr\u00cdcolas",
    "sg:phone":"+34 983 39 38 22",
    "sg:postcode":"47012",
    "sg:province":"Valladolid",
    "wof:name":"Agripel S.l.",
    "wof:placetype":"venue"
},
  "geometry": {"coordinates":[-4.708322525,41.6194801331],"type":"Point"}
}