{
  "type": "Feature",
  "properties": {
    "addr:full":"Calle de Rosario (del), 52 S. Martin Valdeiglesias Madrid 28680",
    "addr:housenumber":"52",
    "addr:postcode":"28680",
    "addr:street":"Calle De Rosario Del;S. Martin Valdeiglesias",
    "iso:country":"ES",
    "sg:address":"Calle de Rosario (del), 52",
    "sg:city":"S. Martin Valdeiglesias",
    "sg:orig_category":"Aguas (distribuci\u00d3n, Servicios)",
    "sg:phone":"+34 918 61 17 70",
    "sg:postcode":"28680",
    "sg:province":"Madrid",
    "sg:website":"www.dytras.es",
    "wof:name":"Dytras S.a.",
    "wof:placetype":"venue"
},
  "geometry": {"coordinates":[-4.3418397903,40.3746681213],"type":"Point"}
}