{
  "type": "Feature",
  "properties": {
    "addr:full":"Calle de Pintor Oliva, 4 Palencia Palencia 34004",
    "addr:housenumber":"4",
    "addr:postcode":"34004",
    "addr:street":"Calle De Pintor Oliva",
    "iso:country":"ES",
    "sg:address":"Calle de Pintor Oliva, 4",
    "sg:city":"Palencia",
    "sg:orig_category":"Centros P\u00dablicos De Formaci\u00d3n Profesional Y T\u00c9cnica",
    "sg:phone":"+34 979 72 10 07",
    "sg:postcode":"34004",
    "sg:province":"Palencia",
    "wof:name":"Colegio De Mediadores De Seguros Titulados",
    "wof:placetype":"venue"
},
  "geometry": {"coordinates":[-4.525826931,42.0012168884],"type":"Point"}
}