{
  "type": "Feature",
  "properties": {
    "addr:full":"Calle de San Juan De Dios, 32 Granada Granada 18001",
    "addr:housenumber":"32",
    "addr:postcode":"18001",
    "addr:street":"Calle De San Juan;Dios",
    "iso:country":"ES",
    "sg:address":"Calle de San Juan De Dios, 32",
    "sg:city":"Granada",
    "sg:orig_category":"Colchones (fabricaci\u00d3n, Al Por Mayor, Al Por Menor)",
    "sg:phone":"+34 958 27 79 87",
    "sg:postcode":"18001",
    "sg:province":"Granada",
    "wof:name":"Gonzalez Fernandez Salvador",
    "wof:placetype":"venue"
},
  "geometry": {"coordinates":[-3.602504015,37.1812057495],"type":"Point"}
}