{
  "type": "Feature",
  "properties": {
    "addr:full":"Carrer de Nou, 14 Argentona Barcelona 08310",
    "addr:housenumber":"14",
    "addr:postcode":"08310",
    "addr:street":"Carrer De Nou",
    "iso:country":"ES",
    "sg:address":"Carrer de Nou, 14",
    "sg:city":"Argentona",
    "sg:orig_category":"Mantenimiento Y Reparaci\u00d3n De Motores Industriales",
    "sg:phone":"+34 937 56 03 79",
    "sg:postcode":"08310",
    "sg:province":"Barcelona",
    "wof:name":"Castillo Benavente Vicente",
    "wof:placetype":"venue"
},
  "geometry": {"coordinates":[2.4015059471,41.5570487976],"type":"Point"}
}