{
  "type": "Feature",
  "properties": {
    "addr:full":"Carr Urgell, 46 Balaguer Lleida 25600",
    "addr:housenumber":"46",
    "addr:postcode":"25600",
    "addr:street":"Carr Urgell",
    "iso:country":"ES",
    "sg:address":"Carr Urgell, 46",
    "sg:city":"Balaguer",
    "sg:orig_category":"Mec\u00c1nico Del Autom\u00d3vil",
    "sg:phone":"+34 973 44 55 99",
    "sg:postcode":"25600",
    "sg:province":"Lleida",
    "wof:name":"Balaguer Motor S.l.l.",
    "wof:placetype":"venue"
},
  "geometry": {"coordinates":[0.8071600199,41.7896003723],"type":"Point"}
}