{
  "type": "Feature",
  "properties": {
    "iso:country":"ES",
    "sg:address":"Pg Saladar, 62",
    "sg:city":"Denia",
    "sg:orig_category":"Inmobiliaria (agencias)",
    "sg:phone":"+34 966 42 59 24",
    "sg:postcode":"03700",
    "sg:province":"Alicante",
    "wof:name":"E.m.c Invest S.l.",
    "wof:placetype":"venue"
},
  "geometry": {"coordinates":[0.1085359976,38.8376846313],"type":"Point"}
}