{
  "type": "Feature",
  "properties": {
    "iso:country":"ES",
    "sg:address":"Carrer de Major, 94",
    "sg:city":"Castellar Valles",
    "sg:orig_category":"Zapatos (al Por Menor)",
    "sg:phone":"+34 937 15 93 85",
    "sg:postcode":"08211",
    "sg:province":"Barcelona",
    "wof:name":"Mic Sabates-complements S.l.",
    "wof:placetype":"venue"
},
  "geometry": {"coordinates":[2.0857009888,41.6159553528],"type":"Point"}
}