{
  "type": "Feature",
  "properties": {
    "iso:country":"ES",
    "sg:address":"Calle de Sagunto, 11",
    "sg:city":"Madrid",
    "sg:orig_category":"Suministros Y Materiales Industriales",
    "sg:phone":"+34 914 47 12 13",
    "sg:postcode":"28010",
    "sg:province":"Madrid",
    "wof:name":"Ingenieria Y Gestion S.l.",
    "wof:placetype":"venue"
},
  "geometry": {"coordinates":[-3.6996130943,40.4338760376],"type":"Point"}
}