{
  "type": "Feature",
  "properties": {
    "addr:full":"Carrer de Casp, 80 Barcelona Barcelona 08010",
    "addr:housenumber":"80",
    "addr:postcode":"08010",
    "addr:street":"Carrer De Casp",
    "iso:country":"ES",
    "sg:address":"Carrer de Casp, 80",
    "sg:city":"Barcelona",
    "sg:orig_category":"Traductores",
    "sg:phone":"+34 932 44 81 59",
    "sg:postcode":"08010",
    "sg:province":"Barcelona",
    "wof:name":"Traducciones Anne Lacroix Sl",
    "wof:placetype":"venue"
},
  "geometry": {"coordinates":[2.1756219864,41.3928718567],"type":"Point"}
}