{
  "type": "Feature",
  "properties": {
    "addr:full":"Calle de Colon, 7 Valencia Valencia 46004",
    "addr:housenumber":"7",
    "addr:postcode":"46004",
    "addr:street":"Calle De Colon",
    "iso:country":"ES",
    "sg:address":"Calle de Colon, 7",
    "sg:city":"Valencia",
    "sg:orig_category":"Abogados",
    "sg:phone":"+34 963 51 75 20",
    "sg:postcode":"46004",
    "sg:province":"Valencia",
    "wof:name":"Vidal Pastor Jorge",
    "wof:placetype":"venue"
},
  "geometry": {"coordinates":[-0.3742670119,39.4676971436],"type":"Point"}
}