{
  "type": "Feature",
  "properties": {
    "addr:full":"Partida Carretera Ademuz, Km. 0017,0 Conarda Valencia 46185",
    "addr:postcode":"46185",
    "addr:street":"Partida Carretera Ademuz Km. 0017,0 Conarda",
    "iso:country":"ES",
    "sg:address":"Partida Carretera Ademuz, Km. 0017,0",
    "sg:city":"Conarda",
    "sg:orig_category":"Equipo Y Material Deportivo Y De Actividades Invernales Y De Monta\u00d1a",
    "sg:phone":"+34 962 76 03 39",
    "sg:postcode":"46185",
    "sg:province":"Valencia",
    "wof:name":"Gomez Marimon Raimundo",
    "wof:placetype":"venue"
},
  "geometry": {"coordinates":[-0.5534440279,39.5925750732],"type":"Point"}
}