{
  "type": "Feature",
  "properties": {
    "iso:country":"ES",
    "sg:address":"Carr Bisbe Alberti, 14",
    "sg:city":"Muro",
    "sg:orig_category":"Empresarios Y Productoras De Espect\u00c1culos",
    "sg:phone":"+34 971 86 03 71",
    "sg:postcode":"07440",
    "sg:province":"Islas Baleares",
    "wof:name":"New Romantic Central Services S.l.",
    "wof:placetype":"venue"
},
  "geometry": {"coordinates":[3.0572190285,39.7355918884],"type":"Point"}
}