{
  "type": "Feature",
  "properties": {
    "addr:full":"Plaz Constitucion (de La), 2 Totana Murcia 30850",
    "addr:postcode":"30850",
    "iso:country":"ES",
    "sg:address":"Plaz Constitucion (de La), 2",
    "sg:city":"Totana",
    "sg:orig_category":"Ense\u00d1anza, Formaci\u00d3n Profesional: Aprendizaje",
    "sg:phone":"+34 968 41 81 51",
    "sg:postcode":"30850",
    "sg:province":"Murcia",
    "wof:name":"Ayuntamiento De Totana",
    "wof:placetype":"venue"
},
  "geometry": {"coordinates":[-1.5030390024,37.7726860046],"type":"Point"}
}