{
  "type": "Feature",
  "properties": {
    "addr:full":"Rua Gagos De Mendoza (los), 4 Pontevedra Pontevedra 36001",
    "addr:housenumber":"4",
    "addr:postcode":"36001",
    "addr:street":"Rua Gagos De Mendoza Los",
    "iso:country":"ES",
    "sg:address":"Rua Gagos De Mendoza (los), 4",
    "sg:city":"Pontevedra",
    "sg:orig_category":"Expertos Contables, Revisores De Cuentas",
    "sg:phone":"+34 986 86 48 88",
    "sg:postcode":"36001",
    "sg:province":"Pontevedra",
    "wof:name":"Audygem S.l.",
    "wof:placetype":"venue"
},
  "geometry": {"coordinates":[-8.6471614838,42.4283981323],"type":"Point"}
}