{
  "type": "Feature",
  "properties": {
    "addr:full":"Calle de Montes, 50 Ronda M\u00e1laga 29400",
    "addr:housenumber":"50",
    "addr:postcode":"29400",
    "addr:street":"Calle De Montes;Ronda Ma\u0301Laga",
    "iso:country":"ES",
    "sg:address":"Calle de Montes, 50",
    "sg:city":"Ronda",
    "sg:orig_category":"Reposter\u00cdas",
    "sg:phone":"+34 952 19 05 45",
    "sg:postcode":"29400",
    "sg:province":"M\u00e1laga",
    "wof:name":"Sanchez Hidalgo Ana",
    "wof:placetype":"venue"
},
  "geometry": {"coordinates":[-5.1592020988,36.7447280884],"type":"Point"}
}