{
  "type": "Feature",
  "properties": {
    "addr:full":"Avda Estacion (de La), 7 Puente-genil C\u00f3rdoba 14500",
    "addr:housenumber":"7",
    "addr:postcode":"14500",
    "addr:street":"Avda Estacion De La;Co\u0301Rdoba",
    "iso:country":"ES",
    "sg:address":"Avda Estacion (de La), 7",
    "sg:city":"Puente-genil",
    "sg:orig_category":"Ense\u00d1anza, Formaci\u00d3n Profesional: Aprendizaje",
    "sg:phone":"+34 957 60 12 77",
    "sg:postcode":"14500",
    "sg:province":"C\u00f3rdoba",
    "wof:name":"Servicio Andaluz De Empleo",
    "wof:placetype":"venue"
},
  "geometry": {"coordinates":[-4.7624788284,37.3934669495],"type":"Point"}
}