{
  "type": "Feature",
  "properties": {
    "addr:full":"Avda Miraflores, 8 Sevilla Sevilla 41008",
    "addr:housenumber":"8",
    "addr:postcode":"41008",
    "addr:street":"Avda Miraflores",
    "iso:country":"ES",
    "sg:address":"Avda Miraflores, 8",
    "sg:city":"Sevilla",
    "sg:orig_category":"Ropa Para Ni\u00d1os (al Por Menor)",
    "sg:phone":"+34 954 35 22 41",
    "sg:postcode":"41008",
    "sg:province":"Sevilla",
    "wof:name":"Reina Mestre Juan",
    "wof:placetype":"venue"
},
  "geometry": {"coordinates":[-5.9502968788,37.4202232361],"type":"Point"}
}