{
  "type": "Feature",
  "properties": {
    "addr:full":"Carrer de Berlines, 27 Barcelona Barcelona 08022",
    "addr:housenumber":"27",
    "addr:postcode":"08022",
    "addr:street":"Carrer De Berlines",
    "iso:country":"ES",
    "sg:address":"Carrer de Berlines, 27",
    "sg:city":"Barcelona",
    "sg:orig_category":"Mec\u00c1nico Del Autom\u00d3vil",
    "sg:phone":"+34 934 17 31 48",
    "sg:postcode":"08022",
    "sg:province":"Barcelona",
    "wof:name":"Jimenez Amat Jose",
    "wof:placetype":"venue"
},
  "geometry": {"coordinates":[2.1383299828,41.4041976929],"type":"Point"}
}