{
  "type": "Feature",
  "properties": {
    "addr:full":"Avda Bruselas, 10 Alacant Alicante 03540",
    "addr:housenumber":"10",
    "addr:postcode":"03540",
    "addr:street":"Avda Bruselas",
    "iso:country":"ES",
    "sg:address":"Avda Bruselas, 10",
    "sg:city":"Alacant",
    "sg:orig_category":"Alquiler De Apartamentos",
    "sg:phone":"+34 965 16 24 22",
    "sg:postcode":"03540",
    "sg:province":"Alicante",
    "wof:name":"Citrac S. A.",
    "wof:placetype":"venue"
},
  "geometry": {"coordinates":[-0.4135760069,38.3708534241],"type":"Point"}
}