{
  "type": "Feature",
  "properties": {
    "addr:full":"Calle de Valencia, 8 Getafe Madrid 28903",
    "addr:housenumber":"8",
    "addr:postcode":"28903",
    "addr:street":"Calle De Valencia",
    "iso:country":"ES",
    "sg:address":"Calle de Valencia, 8",
    "sg:city":"Getafe",
    "sg:orig_category":"Inmobiliaria (agencias)",
    "sg:phone":"+34 916 83 37 38",
    "sg:postcode":"28903",
    "sg:province":"Madrid",
    "sg:website":"www.habiges.com",
    "wof:name":"Habirecord S.l.",
    "wof:placetype":"venue"
},
  "geometry": {"coordinates":[-3.7215809822,40.3111114502],"type":"Point"}
}