{
  "type": "Feature",
  "properties": {
    "addr:full":"G.v. Marques Del Turia, 24 Valencia Valencia 46005",
    "addr:housenumber":"24",
    "addr:postcode":"46005",
    "addr:street":"Turia",
    "iso:country":"ES",
    "sg:address":"G.v. Marques Del Turia, 24",
    "sg:city":"Valencia",
    "sg:orig_category":"Electricidad, Electr\u00d3nica: Material Y Suministros (al Por Mayor)",
    "sg:phone":"+34 963 33 01 23",
    "sg:postcode":"46005",
    "sg:province":"Valencia",
    "sg:website":"www.tiendamotorhobby.com",
    "wof:name":"Motor Hobby C.b.",
    "wof:placetype":"venue"
},
  "geometry": {"coordinates":[-0.370521009,39.4659843445],"type":"Point"}
}