{
  "type": "Feature",
  "properties": {
    "addr:full":"Carrer de Duquessa D'orleans, 24 Barcelona Barcelona 08034",
    "addr:housenumber":"24",
    "addr:postcode":"08034",
    "addr:street":"Carrer De Duquessa D'Orleans",
    "iso:country":"ES",
    "sg:address":"Carrer de Duquessa D'orleans, 24",
    "sg:city":"Barcelona",
    "sg:orig_category":"Comercio, Reparaci\u00d3n De Motocicletas, Bicicletas Y Piezas Sueltas",
    "sg:phone":"+34 932 03 07 33",
    "sg:postcode":"08034",
    "sg:province":"Barcelona",
    "wof:name":"Grandes Angulo Baltasar",
    "wof:placetype":"venue"
},
  "geometry": {"coordinates":[2.1202011108,41.3982009888],"type":"Point"}
}