{
  "type": "Feature",
  "properties": {
    "iso:country":"ES",
    "sg:address":"Plaz Constitucion, 3",
    "sg:city":"Toboso",
    "sg:orig_category":"Asesor\u00cda Fiscal Y Jur\u00cddica",
    "sg:phone":"+34 925 19 73 05",
    "sg:postcode":"45820",
    "sg:province":"Toledo",
    "wof:name":"Moreno Martinez Pedro",
    "wof:placetype":"venue"
},
  "geometry": {"coordinates":[-2.998249054,39.5184020996],"type":"Point"}
}