{
  "type": "Feature",
  "properties": {
    "iso:country":"ES",
    "sg:address":"Avda San Crispin, 11",
    "sg:city":"Fuensalida",
    "sg:orig_category":"Agentes Generales De Seguros",
    "sg:phone":"+34 925 78 56 88",
    "sg:postcode":"45510",
    "sg:province":"Toledo",
    "wof:name":"Perez-higueras Gonzalez Angel",
    "wof:placetype":"venue"
},
  "geometry": {"coordinates":[-4.1983242035,40.0570297241],"type":"Point"}
}