{
  "type": "Feature",
  "properties": {
    "addr:full":"Carrer de Miguel De Cervantes, 38 Mollet Valles Barcelona 08100",
    "addr:housenumber":"38",
    "addr:postcode":"08100",
    "addr:street":"Carrer De Miguel De Cervantes",
    "iso:country":"ES",
    "sg:address":"Carrer de Miguel De Cervantes, 38",
    "sg:city":"Mollet Valles",
    "sg:orig_category":"Molduras, Junquillos, Listones Y Molduras Perforadas",
    "sg:phone":"+34 935 70 91 67",
    "sg:postcode":"08100",
    "sg:province":"Barcelona",
    "wof:name":"Martin Rajado Vicente",
    "wof:placetype":"venue"
},
  "geometry": {"coordinates":[2.2087979317,41.5426521301],"type":"Point"}
}