{
  "type": "Feature",
  "properties": {
    "iso:country":"ES",
    "sg:address":"Av. Monteprincipe, 15",
    "sg:city":"Monteprincipe",
    "sg:classifiers":[
        {
            "category":"Professional",
            "subcategory":"Business Services",
            "type":"Services"
        }
    ],
    "sg:phone":"+34 917 15 38 44",
    "sg:postcode":"28668",
    "sg:province":"Madrid",
    "sg:tags":[
        "control",
        "asesor\u00cda",
        "organizaci\u00d3n",
        "la",
        "de",
        "gesti\u00d3n",
        "y"
    ],
    "wof:name":"Espronceda 34 S.a.",
    "wof:placetype":"venue"
},
  "geometry": {"coordinates":[-3.8420469761,40.4082946777],"type":"Point"}
}