{
  "type": "Feature",
  "properties": {
    "iso:country":"ES",
    "sg:address":"Calle de Camino Viejo De Leganes, 133",
    "sg:city":"Madrid",
    "sg:orig_category":"Inmobiliaria (agencias)",
    "sg:phone":"+34 914 22 04 30",
    "sg:postcode":"28025",
    "sg:province":"Madrid",
    "wof:name":"Fincas Corral Barcino S.l.",
    "wof:placetype":"venue"
},
  "geometry": {"coordinates":[-3.7284903526,40.3846969604],"type":"Point"}
}