{
  "type": "Feature",
  "properties": {
    "addr:full":"Carr Gregal, 20 Badalona Barcelona 08915",
    "addr:housenumber":"20",
    "addr:postcode":"08915",
    "addr:street":"Carr Gregal",
    "iso:country":"ES",
    "sg:address":"Carr Gregal, 20",
    "sg:city":"Badalona",
    "sg:orig_category":"Aparatos, Material Y Suministros Para Laboratorios",
    "sg:phone":"+34 934 65 68 18",
    "sg:postcode":"08915",
    "sg:province":"Barcelona",
    "wof:name":"Hellma Hispania S.l.",
    "wof:placetype":"venue"
},
  "geometry": {"coordinates":[2.2501969337,41.4638252258],"type":"Point"}
}