{
  "type": "Feature",
  "properties": {
    "addr:full":"Calle de Soria, 1 San Juan De Aznalfarache Sevilla 41920",
    "addr:housenumber":"1",
    "addr:postcode":"41920",
    "addr:street":"Calle De Soria",
    "iso:country":"ES",
    "sg:address":"Calle de Soria, 1",
    "sg:city":"San Juan De Aznalfarache",
    "sg:orig_category":"Bisuter\u00cda, Joyer\u00cda, Relojer\u00cda (al Por Menor)",
    "sg:phone":"+34 954 76 55 73",
    "sg:postcode":"41920",
    "sg:province":"Sevilla",
    "wof:name":"Cariciolo Guisado Rosario",
    "wof:placetype":"venue"
},
  "geometry": {"coordinates":[-6.0356559753,37.3568534851],"type":"Point"}
}