{
  "type": "Feature",
  "properties": {
    "iso:country":"ES",
    "sg:address":"Cn Viejo Ruzafa, 119",
    "sg:city":"Catarroja",
    "sg:orig_category":"Mec\u00c1nico Del Autom\u00d3vil",
    "sg:phone":"+34 961 26 75 58",
    "sg:postcode":"46470",
    "sg:province":"Valencia",
    "wof:name":"Auto Taller Catarroja S.l.",
    "wof:placetype":"venue"
},
  "geometry": {"coordinates":[-0.414440006,39.3972015381],"type":"Point"}
}