{
  "type": "Feature",
  "properties": {
    "addr:full":"Calle de Cardenal Cisneros, 16 Madrid Madrid 28010",
    "addr:housenumber":"16",
    "addr:postcode":"madrid;28010",
    "addr:street":"Calle De Cardenal Cisneros",
    "iso:country":"ES",
    "sg:address":"Calle de Cardenal Cisneros, 16",
    "sg:city":"Madrid",
    "sg:orig_category":"Alquiler De V\u00cddeo",
    "sg:phone":"+34 914 45 78 80",
    "sg:postcode":"28010",
    "sg:province":"Madrid",
    "sg:website":"www.lastradadvd.com",
    "wof:name":"Fernandez Garcia Manuel Angel",
    "wof:placetype":"venue"
},
  "geometry": {"coordinates":[-3.7018105984,40.4306602478],"type":"Point"}
}