{
  "type": "Feature",
  "properties": {
    "iso:country":"ES",
    "sg:address":"Calle de Nuestro Padre Jesus Cautivo, 7",
    "sg:city":"Dos Hermanas",
    "sg:orig_category":"Agencias Y Agentes Comerciales, Representantes",
    "sg:phone":"+34 955 67 04 33",
    "sg:postcode":"41700",
    "sg:province":"Sevilla",
    "wof:name":"Vega Sacristan Federico",
    "wof:placetype":"venue"
},
  "geometry": {"coordinates":[-5.931016922,37.2747383118],"type":"Point"}
}