{
  "type": "Feature",
  "properties": {
    "iso:country":"ES",
    "sg:address":"Ctra Aguilar, S/n",
    "sg:city":"Cervera Pisuerga",
    "sg:orig_category":"Comercio De Piezas De Recambio Y De Accesorios De Veh\u00cdculos, Veh\u00cdculos Industriales",
    "sg:phone":"+34 979 87 01 24",
    "sg:postcode":"34840",
    "sg:province":"Palencia",
    "wof:name":"Refrutos S.l.",
    "wof:placetype":"venue"
},
  "geometry": {"coordinates":[-4.4180278778,42.8575897217],"type":"Point"}
}