{
  "type": "Feature",
  "properties": {
    "addr:full":"Calle de Chopin, S/n Malaga M\u00e1laga 29004",
    "addr:housenumber":"s / n",
    "addr:postcode":"29004",
    "addr:street":"Calle De Chopin;Ma\u0301Laga",
    "iso:country":"ES",
    "sg:address":"Calle de Chopin, S/n",
    "sg:city":"Malaga",
    "sg:orig_category":"Peluqueros: De Se\u00d1oras",
    "sg:phone":"+34 952 23 96 21",
    "sg:postcode":"29004",
    "sg:province":"M\u00e1laga",
    "wof:name":"Cabeza Diaz Catalina",
    "wof:placetype":"venue"
},
  "geometry": {"coordinates":[-4.449819088,36.6944999695],"type":"Point"}
}