{
  "type": "Feature",
  "properties": {
    "iso:country":"ES",
    "sg:address":"Avda Federico Garcia Lorca, 1",
    "sg:city":"Palmas De Gran Canaria",
    "sg:orig_category":"Distribuci\u00d3n De Petr\u00d3leo Y Derivados",
    "sg:phone":"+34 928 29 84 64",
    "sg:postcode":"35011",
    "sg:province":"Las Palmas",
    "wof:name":"Costa Llano S.l.",
    "wof:placetype":"venue"
},
  "geometry": {"coordinates":[-15.4401979446,28.1258659363],"type":"Point"}
}