{
  "type": "Feature",
  "properties": {
    "iso:country":"ES",
    "sg:address":"Avda Oliva, 14",
    "sg:city":"Majadahonda",
    "sg:orig_category":"Inmobiliaria (agencias)",
    "sg:phone":"+34 916 02 97 11",
    "sg:postcode":"28220",
    "sg:province":"Madrid",
    "wof:name":"Burgos Opcion Inmobiliaria S.l.",
    "wof:placetype":"venue"
},
  "geometry": {"coordinates":[-3.8645119667,40.4476242065],"type":"Point"}
}