{
  "type": "Feature",
  "properties": {
    "addr:full":"Camino Beniparrell, 3 Silla Valencia 46460",
    "addr:housenumber":"3",
    "addr:postcode":"46460",
    "addr:street":"Camino Beniparrell",
    "iso:country":"ES",
    "sg:address":"Camino Beniparrell, 3",
    "sg:city":"Silla",
    "sg:orig_category":"Comercio De Piezas De Recambio Y De Accesorios De Veh\u00cdculos, Veh\u00cdculos Industriales",
    "sg:phone":"+34 961 21 39 50",
    "sg:postcode":"46460",
    "sg:province":"Valencia",
    "sg:website":"www.mettecno2000.com",
    "wof:name":"Met Tecno 2000 S.l.",
    "wof:placetype":"venue"
},
  "geometry": {"coordinates":[-0.4101629853,39.3753700256],"type":"Point"}
}