{
  "type": "Feature",
  "properties": {
    "iso:country":"ES",
    "sg:address":"Calle de Juan Xxiii, 45",
    "sg:city":"Alaquas",
    "sg:orig_category":"Empresarios",
    "sg:phone":"+34 961 50 00 28",
    "sg:postcode":"46970",
    "sg:province":"Valencia",
    "wof:name":"Fundacion Femeval",
    "wof:placetype":"venue"
},
  "geometry": {"coordinates":[-0.4725719988,39.4551544189],"type":"Point"}
}