{
  "type": "Feature",
  "properties": {
    "addr:full":"Av Sant Jordi, De, S/n Eivissa Islas Baleares 07800",
    "addr:postcode":"07800",
    "addr:street":"Av Sant Jordi De S / N",
    "iso:country":"ES",
    "sg:address":"Av Sant Jordi, De, S/n",
    "sg:city":"Eivissa",
    "sg:orig_category":"Caf\u00c9s, Bares, Cervecer\u00cdas",
    "sg:phone":"+34 971 39 85 74",
    "sg:postcode":"07800",
    "sg:province":"Islas Baleares",
    "wof:name":"Espinar Morales Francisca",
    "wof:placetype":"venue"
},
  "geometry": {"coordinates":[1.4198950529,38.9056243896],"type":"Point"}
}