{
  "type": "Feature",
  "properties": {
    "addr:full":"Poligono Treinta Y Seis, 59 Vilamarxant Valencia 46191",
    "addr:housenumber":"59",
    "addr:postcode":"46191",
    "addr:street":"Poligono Treinta;Seis",
    "iso:country":"ES",
    "sg:address":"Poligono Treinta Y Seis, 59",
    "sg:city":"Vilamarxant",
    "sg:orig_category":"Ropa Para Ni\u00d1os (al Por Menor)",
    "sg:phone":"+34 962 71 51 09",
    "sg:postcode":"46191",
    "sg:province":"Valencia",
    "wof:name":"Ferrer Ortega Pedro",
    "wof:placetype":"venue"
},
  "geometry": {"coordinates":[-0.6272540092,39.5677604675],"type":"Point"}
}