{
  "type": "Feature",
  "properties": {
    "addr:full":"Av Parc Logistic, 2 Barcelona Barcelona 08040",
    "addr:housenumber":"2",
    "addr:postcode":"08040",
    "addr:street":"Av Parc Logistic",
    "iso:country":"ES",
    "sg:address":"Av Parc Logistic, 2",
    "sg:city":"Barcelona",
    "sg:orig_category":"Inmobiliaria (agencias)",
    "sg:phone":"+34 932 23 91 11",
    "sg:postcode":"08040",
    "sg:province":"Barcelona",
    "sg:website":"www.parclogistic.es",
    "wof:name":"Parc Logistic De La Zona Franca",
    "wof:placetype":"venue"
},
  "geometry": {"coordinates":[2.1259040833,41.3411636353],"type":"Point"}
}