{
  "type": "Feature",
  "properties": {
    "iso:country":"ES",
    "sg:address":"Calle de Magin Calvo, 15",
    "sg:city":"Madrid",
    "sg:orig_category":"Aparatos, Sistemas De Tele",
    "sg:phone":"+34 915 26 02 32",
    "sg:postcode":"28011",
    "sg:province":"Madrid",
    "sg:website":"www.lumaxextintores.com",
    "wof:name":"Lumax Extintores S.l.",
    "wof:placetype":"venue"
},
  "geometry": {"coordinates":[-3.7342679501,40.4074935913],"type":"Point"}
}