{
  "type": "Feature",
  "properties": {
    "iso:country":"ES",
    "sg:address":"Calle de Manuel Mac Crohon (de), 1",
    "sg:city":"Morata De Taju\u00e7a",
    "sg:orig_category":"Bibliotecas, Mediatecas",
    "sg:phone":"+34 918 73 92 58",
    "sg:postcode":"28530",
    "sg:province":"Madrid",
    "sg:website":"www.obrasocialcajamadrid.org",
    "wof:name":"Gecesa Gestion De Centros Culturales S.a",
    "wof:placetype":"venue"
},
  "geometry": {"coordinates":[-3.4381349087,40.2292785645],"type":"Point"}
}