{
  "type": "Feature",
  "properties": {
    "addr:full":"Calle de Barrio Nuevo, S/n Villalba Alcor Huelva 21860",
    "addr:housenumber":"s / n",
    "addr:postcode":"21860",
    "addr:street":"Calle De Barrio Nuevo",
    "iso:country":"ES",
    "sg:address":"Calle de Barrio Nuevo, S/n",
    "sg:city":"Villalba Alcor",
    "sg:orig_category":"Promotores Constructores",
    "sg:phone":"+34 959 42 13 95",
    "sg:postcode":"21860",
    "sg:province":"Huelva",
    "wof:name":"Construcciones Dianto 4 S.l.",
    "wof:placetype":"venue"
},
  "geometry": {"coordinates":[-6.4757871628,37.392791748],"type":"Point"}
}