{
  "type": "Feature",
  "properties": {
    "addr:full":"Avda Nicolas Cora Montenegro, 76 Viveiro Lugo 27850",
    "addr:housenumber":"76",
    "addr:postcode":"27850",
    "addr:street":"Avda Nicolas Cora Montenegro",
    "iso:country":"ES",
    "sg:address":"Avda Nicolas Cora Montenegro, 76",
    "sg:city":"Viveiro",
    "sg:orig_category":"Asociaciones Y Clubs Deportivos",
    "sg:phone":"+34 982 56 27 50",
    "sg:postcode":"27850",
    "sg:province":"Lugo",
    "wof:name":"Seijo  Miguel Pedro",
    "wof:placetype":"venue"
},
  "geometry": {"coordinates":[-7.5921897888,43.6621246338],"type":"Point"}
}