{
  "type": "Feature",
  "properties": {
    "addr:full":"Els Albarders, 2 P.i. Masia Del Juez Valencia 46900",
    "addr:housenumber":"2",
    "addr:postcode":"46900",
    "addr:street":"Albarders;P.I. Masia Del Juez",
    "iso:country":"ES",
    "sg:address":"Els Albarders, 2",
    "sg:city":"P.i. Masia Del Juez",
    "sg:orig_category":"Empresas De Carpinter\u00cda Met\u00c1lica",
    "sg:phone":"+34 961 55 83 11",
    "sg:postcode":"46900",
    "sg:province":"Valencia",
    "wof:name":"Cerrajeria Masia Del Juez S.l.",
    "wof:placetype":"venue"
},
  "geometry": {"coordinates":[-0.4623290002,39.441619873],"type":"Point"}
}