{
  "type": "Feature",
  "properties": {
    "iso:country":"ES",
    "sg:address":"Magdalena, S/n",
    "sg:city":"Bisjueces",
    "sg:orig_category":"Producci\u00d3n, Venta De Productos De Agricultura Biol\u00d3gica",
    "sg:phone":"+34 947 13 05 13",
    "sg:postcode":"09554",
    "sg:province":"Burgos",
    "wof:name":"Castresana Fernandez Francisco Javier Y Otro S.c.",
    "wof:placetype":"venue"
},
  "geometry": {"coordinates":[-3.5702700615,42.8934860229],"type":"Point"}
}