{
  "type": "Feature",
  "properties": {
    "addr:full":"Calle de Lopez Castrillon, 2 Le\u00f3n Le\u00f3n 24003",
    "addr:housenumber":"2",
    "addr:postcode":"24003",
    "addr:street":"Calle De;Castrillon;Leo\u0301N",
    "iso:country":"ES",
    "sg:address":"Calle de Lopez Castrillon, 2",
    "sg:city":"Le\u00f3n",
    "sg:orig_category":"Peluquer\u00cdas, Peluquer\u00cda Mixta",
    "sg:phone":"+34 987 23 41 18",
    "sg:postcode":"24003",
    "sg:province":"Le\u00f3n",
    "wof:name":"Ordas Cachan Aurora Sagrario",
    "wof:placetype":"venue"
},
  "geometry": {"coordinates":[-5.5696501732,42.5986328125],"type":"Point"}
}