{
  "type": "Feature",
  "properties": {
    "addr:full":"Major, 49 Almacelles Lleida 25100",
    "addr:housenumber":"49",
    "addr:postcode":"25100",
    "addr:street":"Major",
    "iso:country":"ES",
    "sg:address":"Major, 49",
    "sg:city":"Almacelles",
    "sg:orig_category":"Asesor\u00cda Fiscal Y Jur\u00cddica",
    "sg:phone":"+34 973 74 17 17",
    "sg:postcode":"25100",
    "sg:province":"Lleida",
    "wof:name":"Cebollero Leris Jose Luis",
    "wof:placetype":"venue"
},
  "geometry": {"coordinates":[0.4390180111,41.7300796509],"type":"Point"}
}