{
  "type": "Feature",
  "properties": {
    "iso:country":"ES",
    "sg:address":"Avda Ejercito (del), 4",
    "sg:city":"Chipiona",
    "sg:orig_category":"Albergues",
    "sg:phone":"+34 956 37 26 80",
    "sg:postcode":"11550",
    "sg:province":"C\u00e1diz",
    "wof:name":"Torices Jimenez Ana",
    "wof:placetype":"venue"
},
  "geometry": {"coordinates":[-6.4364509583,36.7346992493],"type":"Point"}
}