{
  "type": "Feature",
  "properties": {
    "iso:country":"ES",
    "sg:address":"Pl. Dr. Jnez. D\u00edaz, S/n",
    "sg:city":"Valladolid",
    "sg:orig_category":"Ense\u00d1anza: Peluquer\u00cda Est\u00c9tica",
    "sg:phone":"+34 983 25 66 60",
    "sg:postcode":"47011",
    "sg:province":"Valladolid",
    "wof:name":"Jimenez Castilla Francisco Jose",
    "wof:placetype":"venue"
},
  "geometry": {"coordinates":[-4.7155089378,41.6593513489],"type":"Point"}
}