{
  "type": "Feature",
  "properties": {
    "iso:country":"ES",
    "sg:address":"Carrer de Bac De Roda, 95",
    "sg:city":"Barcelona",
    "sg:orig_category":"Empresarios",
    "sg:phone":"+34 933 07 72 49",
    "sg:postcode":"08005",
    "sg:province":"Barcelona",
    "wof:name":"Curto Massana Juan",
    "wof:placetype":"venue"
},
  "geometry": {"coordinates":[2.2048819065,41.4067382812],"type":"Point"}
}