{
  "type": "Feature",
  "properties": {
    "iso:country":"ES",
    "sg:address":"Carrer de Argentina, 45",
    "sg:city":"Sabadell",
    "sg:orig_category":"Centros De Educaci\u00d3n Especial",
    "sg:phone":"+34 937 26 40 10",
    "sg:postcode":"08205",
    "sg:province":"Barcelona",
    "wof:name":"Ceip Arraona",
    "wof:placetype":"venue"
},
  "geometry": {"coordinates":[2.0908238888,41.543964386],"type":"Point"}
}