{
  "type": "Feature",
  "properties": {
    "addr:full":"Rua Castelao, 1 Negreira La Coru\u00f1a 15830",
    "addr:housenumber":"1",
    "addr:postcode":"15830",
    "addr:street":"Rua Castelao;La Corun\u0303A",
    "iso:country":"ES",
    "sg:address":"Rua Castelao, 1",
    "sg:city":"Negreira",
    "sg:orig_category":"Florister\u00cdas",
    "sg:phone":"+34 981 88 58 49",
    "sg:postcode":"15830",
    "sg:province":"La Coru\u00f1a",
    "wof:name":"Agroflor Nicra Sallas S.l.",
    "wof:placetype":"venue"
},
  "geometry": {"coordinates":[-8.7351665497,42.9104232788],"type":"Point"}
}