{
  "type": "Feature",
  "properties": {
    "iso:country":"ES",
    "sg:address":"Avda Pablo Iglesias, 22",
    "sg:city":"Loranca",
    "sg:orig_category":"Muebles Y Accesorios Para Cocinas Y Cuartos De Ba\u00d1o (al Por Menor)",
    "sg:phone":"+34 916 04 67 65",
    "sg:postcode":"28942",
    "sg:province":"Madrid",
    "wof:name":"El Ba\u00f1o De Ainoha S.l.",
    "wof:placetype":"venue"
},
  "geometry": {"coordinates":[-3.8337349892,40.3034248352],"type":"Point"}
}