{
  "type": "Feature",
  "properties": {
    "addr:full":"Avd Gutierrez Segura, 10 Baza Granada 18800",
    "addr:housenumber":"10",
    "addr:postcode":"18800",
    "addr:street":"Avd Gutierrez Segura",
    "iso:country":"ES",
    "sg:address":"Avd Gutierrez Segura, 10",
    "sg:city":"Baza",
    "sg:classifiers":[
        {
            "category":"Autos & Motor Vehicles",
            "subcategory":"Automobile Sales",
            "type":"Retail Goods"
        }
    ],
    "sg:phone":"+34 958 70 32 25",
    "sg:postcode":"18800",
    "sg:province":"Granada",
    "wof:name":"Centro De Formacion Vial Mora S.c.a.",
    "wof:placetype":"venue"
},
  "geometry": {"coordinates":[-2.7752180099,37.4932289124],"type":"Point"}
}