{
  "type": "Feature",
  "properties": {
    "addr:full":"Cra Piera, 5 Martorell Barcelona 08760",
    "addr:housenumber":"5",
    "addr:postcode":"08760",
    "addr:street":"Piera",
    "iso:country":"ES",
    "sg:address":"Cra Piera, 5",
    "sg:city":"Martorell",
    "sg:orig_category":"Veh\u00cdculos De Ocasi\u00d3n",
    "sg:phone":"+34 937 74 23 84",
    "sg:postcode":"08760",
    "sg:province":"Barcelona",
    "wof:name":"Traccio Total Martorell S.l.",
    "wof:placetype":"venue"
},
  "geometry": {"coordinates":[1.9228429794,41.478351593],"type":"Point"}
}