{
  "type": "Feature",
  "properties": {
    "addr:full":"Carr Valencia, De, 1 Carcaixent Valencia 46740",
    "addr:housenumber":"1",
    "addr:postcode":"46740",
    "addr:street":"Carr Valencia De",
    "iso:country":"ES",
    "sg:address":"Carr Valencia, De, 1",
    "sg:city":"Carcaixent",
    "sg:orig_category":"Abogados",
    "sg:phone":"+34 962 46 13 75",
    "sg:postcode":"46740",
    "sg:province":"Valencia",
    "wof:name":"Navarro Ferrer Rafael",
    "wof:placetype":"venue"
},
  "geometry": {"coordinates":[-0.449225992,39.1229515076],"type":"Point"}
}