{
  "type": "Feature",
  "properties": {
    "addr:full":"Avda Cami Real, 38 Catarroja Valencia 46470",
    "addr:housenumber":"38",
    "addr:postcode":"46470",
    "addr:street":"Avda Cami Real",
    "iso:country":"ES",
    "sg:address":"Avda Cami Real, 38",
    "sg:city":"Catarroja",
    "sg:orig_category":"Ense\u00d1ante, Direcci\u00d3n",
    "sg:phone":"+34 961 26 48 13",
    "sg:postcode":"46470",
    "sg:province":"Valencia",
    "wof:name":"Vila Vila Salvador",
    "wof:placetype":"venue"
},
  "geometry": {"coordinates":[-0.414440006,39.3972015381],"type":"Point"}
}