{
  "type": "Feature",
  "properties": {
    "addr:full":"Carr Joan Alcover, 14 Santa Maria Del Cami Islas Baleares 07320",
    "addr:housenumber":"14",
    "addr:postcode":"07320",
    "addr:street":"Carr Joan Alcover;Islas",
    "iso:country":"ES",
    "sg:address":"Carr Joan Alcover, 14",
    "sg:city":"Santa Maria Del Cami",
    "sg:orig_category":"Fotograf\u00cda Art\u00cdstica Y Retratos",
    "sg:phone":"+34 971 14 00 96",
    "sg:postcode":"07320",
    "sg:province":"Islas Baleares",
    "wof:name":"De La Fuente Ordo\u00f1ez Guillermo",
    "wof:placetype":"venue"
},
  "geometry": {"coordinates":[2.7729899883,39.6510467529],"type":"Point"}
}