{
  "type": "Feature",
  "properties": {
    "iso:country":"ES",
    "sg:address":"Av Pere Vaquer, 4",
    "sg:city":"Magaluf",
    "sg:orig_category":"Agencias De Viajes",
    "sg:phone":"+34 971 13 03 77",
    "sg:postcode":"07181",
    "sg:province":"Islas Baleares",
    "wof:name":"Flash Tours S.a.",
    "wof:placetype":"venue"
},
  "geometry": {"coordinates":[2.5352399349,39.5094833374],"type":"Point"}
}