{
  "type": "Feature",
  "properties": {
    "addr:full":"Cmno Puente De Tablas, S/n Teruel Teruel 44001",
    "addr:housenumber":"s / n",
    "addr:postcode":"44001",
    "addr:street":"Cmno Puente De Tablas",
    "iso:country":"ES",
    "sg:address":"Cmno Puente De Tablas, S/n",
    "sg:city":"Teruel",
    "sg:orig_category":"Piedra, Vidrio, Cer\u00c1mica Y Porcelana",
    "sg:phone":"+34 978 60 19 31",
    "sg:postcode":"44001",
    "sg:province":"Teruel",
    "wof:name":"Torrent Garcia Fernando",
    "wof:placetype":"venue"
},
  "geometry": {"coordinates":[-1.108299017,40.3458862305],"type":"Point"}
}