{
  "type": "Feature",
  "properties": {
    "addr:full":"Luga Morti Bajo, S/n Morti Bajo Murcia 30850",
    "addr:housenumber":"s / n",
    "addr:postcode":"30850",
    "iso:country":"ES",
    "sg:address":"Luga Morti Bajo, S/n",
    "sg:city":"Morti Bajo",
    "sg:orig_category":"Arboricultura Y Producci\u00d3n De Frutas",
    "sg:phone":"+34 968 42 08 24",
    "sg:postcode":"30850",
    "sg:province":"Murcia",
    "wof:name":"Canovas Navarro Pedro",
    "wof:placetype":"venue"
},
  "geometry": {"coordinates":[-1.5030390024,37.7726860046],"type":"Point"}
}