{
  "type": "Feature",
  "properties": {
    "addr:full":"Calle de Turina, 2 Oviedo Asturias 33011",
    "addr:housenumber":"2",
    "addr:postcode":"33011",
    "addr:street":"Calle De Turina",
    "iso:country":"ES",
    "sg:address":"Calle de Turina, 2",
    "sg:city":"Oviedo",
    "sg:orig_category":"Ense\u00d1anza: Idiomas",
    "sg:phone":"+34 985 11 32 12",
    "sg:postcode":"33011",
    "sg:province":"Asturias",
    "sg:website":"www.tulaneschool.com",
    "wof:name":"Menendez Quintana Nuria",
    "wof:placetype":"venue"
},
  "geometry": {"coordinates":[-5.840531826,43.3706588745],"type":"Point"}
}