{
  "type": "Feature",
  "properties": {
    "iso:country":"ES",
    "sg:address":"Carrer de Castell De Tamarit, 26",
    "sg:city":"Mas D'en Bosch",
    "sg:orig_category":"Molduras, Junquillos, Listones Y Molduras Perforadas",
    "sg:phone":"+34 977 79 48 69",
    "sg:postcode":"43850",
    "sg:province":"Tarragona",
    "wof:name":"Fernandez Escoda Jesus",
    "wof:placetype":"venue"
},
  "geometry": {"coordinates":[10.3486604691,49.7427711487],"type":"Point"}
}