{
  "type": "Feature",
  "properties": {
    "addr:full":"Fanals, 20 Platja Aro Girona 17250",
    "addr:housenumber":"20",
    "addr:postcode":"17250",
    "addr:street":"Fanals",
    "iso:country":"ES",
    "sg:address":"Fanals, 20",
    "sg:city":"Platja Aro",
    "sg:orig_category":"Calderer\u00cda",
    "sg:phone":"+34 972 81 86 50",
    "sg:postcode":"17250",
    "sg:province":"Girona",
    "wof:name":"Ofitheg Representaciones S.l",
    "wof:placetype":"venue"
},
  "geometry": {"coordinates":[3.0636599064,41.8152084351],"type":"Point"}
}