{
  "type": "Feature",
  "properties": {
    "iso:country":"ES",
    "sg:address":"Plaz Dolores Fernandez, 3",
    "sg:city":"Sevilla",
    "sg:orig_category":"Arquitectos",
    "sg:phone":"+34 954 35 91 60",
    "sg:postcode":"41009",
    "sg:province":"Sevilla",
    "wof:name":"Morales Guisande Ana",
    "wof:placetype":"venue"
},
  "geometry": {"coordinates":[-5.9804840088,37.4061813354],"type":"Point"}
}