{
  "type": "Feature",
  "properties": {
    "iso:country":"ES",
    "sg:address":"Calle de Ecuador, 5",
    "sg:city":"Coslada",
    "sg:orig_category":"Cristaler\u00cdas",
    "sg:phone":"+34 916 71 96 78",
    "sg:postcode":"28820",
    "sg:province":"Madrid",
    "wof:name":"Perez Camara Antonio",
    "wof:placetype":"venue"
},
  "geometry": {"coordinates":[-3.5551760197,40.4259185791],"type":"Point"}
}