{
  "type": "Feature",
  "properties": {
    "iso:country":"ES",
    "sg:address":"Calle de Luis Y Carlos Pla, 6",
    "sg:city":"Badajoz",
    "sg:orig_category":"Droguer\u00cdas (al Por Menor)",
    "sg:phone":"+34 924 27 63 24",
    "sg:postcode":"06007",
    "sg:province":"Badajoz",
    "wof:name":"Rosado Zamorano Julia",
    "wof:placetype":"venue"
},
  "geometry": {"coordinates":[-6.9800958633,38.8871231079],"type":"Point"}
}