{
  "type": "Feature",
  "properties": {
    "addr:full":"Plaz Constitucion (de La), 3 S. Sebastian Gomera Santa Cruz De Tenerife 38800",
    "addr:postcode":"38800",
    "addr:street":"3 S. Sebastian Gomera",
    "iso:country":"ES",
    "sg:address":"Plaz Constitucion (de La), 3",
    "sg:city":"S. Sebastian Gomera",
    "sg:orig_category":"Asilos De Ancianos. Centros Privados",
    "sg:phone":"+34 922 87 00 70",
    "sg:postcode":"38800",
    "sg:province":"Santa Cruz De Tenerife",
    "wof:name":"Compa\u00d1ia De Las Hijas De La Caridad De San Vicente De Paul",
    "wof:placetype":"venue"
},
  "geometry": {"coordinates":[-17.1105136871,28.0907344818],"type":"Point"}
}