{
  "type": "Feature",
  "properties": {
    "addr:full":"Calle de Padre Isla, 1 Cistierna Le\u00f3n 24800",
    "addr:housenumber":"1",
    "addr:postcode":"24800",
    "addr:street":"Calle De Padre Isla;Leo\u0301N",
    "iso:country":"ES",
    "sg:address":"Calle de Padre Isla, 1",
    "sg:city":"Cistierna",
    "sg:orig_category":"Peluqueros: De Se\u00d1oras",
    "sg:phone":"+34 987 70 00 63",
    "sg:postcode":"24800",
    "sg:province":"Le\u00f3n",
    "wof:name":"Garcia Fernandez Maria Luz",
    "wof:placetype":"venue"
},
  "geometry": {"coordinates":[-5.1269187927,42.8036804199],"type":"Point"}
}