{
  "type": "Feature",
  "properties": {
    "addr:full":"Avda Baron De Carcer, 52 Valencia Valencia 46001",
    "addr:housenumber":"52",
    "addr:postcode":"46001",
    "addr:street":"Avda Baron De Carcer",
    "iso:country":"ES",
    "sg:address":"Avda Baron De Carcer, 52",
    "sg:city":"Valencia",
    "sg:orig_category":"Aceites Y Grasas Alimentarias (fabricaci\u00d3n, Al Por Mayor)",
    "sg:phone":"+34 963 94 20 13",
    "sg:postcode":"46001",
    "sg:province":"Valencia",
    "wof:name":"Transaceite S.l.",
    "wof:placetype":"venue"
},
  "geometry": {"coordinates":[-0.379783988,39.4691009521],"type":"Point"}
}