{
  "type": "Feature",
  "properties": {
    "addr:full":"Av Anselm Clave, S/n Almenar Lleida 25126",
    "addr:housenumber":"s / n",
    "addr:postcode":"25126",
    "addr:street":"Av Anselm Clave",
    "iso:country":"ES",
    "sg:address":"Av Anselm Clave, S/n",
    "sg:city":"Almenar",
    "sg:orig_category":"Producci\u00d3n, Comercio De Cereales",
    "sg:phone":"+34 973 77 01 00",
    "sg:postcode":"25126",
    "sg:province":"Lleida",
    "wof:name":"Batiste Bernat Antonio",
    "wof:placetype":"venue"
},
  "geometry": {"coordinates":[0.5701749921,41.7946853638],"type":"Point"}
}