{
  "type": "Feature",
  "properties": {
    "addr:full":"Ptda Algoros, S/n Elche Alicante 03293",
    "addr:housenumber":"s / n",
    "addr:postcode":"03293",
    "addr:street":"Ptda Algoros",
    "iso:country":"ES",
    "sg:address":"Ptda Algoros, S/n",
    "sg:city":"Elche",
    "sg:orig_category":"Propiedad Industrial: Patentes De Inventos, Marcas, Modelos, Dise\u00d1os",
    "sg:phone":"+34 966 63 06 24",
    "sg:postcode":"03293",
    "sg:province":"Alicante",
    "wof:name":"Aza Sanz Santiago",
    "wof:placetype":"venue"
},
  "geometry": {"coordinates":[-0.7218046188,38.2306518555],"type":"Point"}
}