{
  "type": "Feature",
  "properties": {
    "addr:full":"Calle de Jose Ramon Diez De Revenga, 3 Pozo Ca\u00e7ada Albacete 02510",
    "addr:housenumber":"3",
    "addr:postcode":"02510",
    "addr:street":"Calle De Jose Ramon;Revenga",
    "iso:country":"ES",
    "sg:address":"Calle de Jose Ramon Diez De Revenga, 3",
    "sg:city":"Pozo Ca\u00e7ada",
    "sg:orig_category":"Pescader\u00cdas (al Por Menor)",
    "sg:phone":"+34 967 25 03 57",
    "sg:postcode":"02510",
    "sg:province":"Albacete",
    "wof:name":"Gonzalez Martinez Francisca",
    "wof:placetype":"venue"
},
  "geometry": {"coordinates":[-1.7355890274,38.8000793457],"type":"Point"}
}