{
  "type": "Feature",
  "properties": {
    "iso:country":"ES",
    "sg:address":"Avda Del Mar, 1",
    "sg:city":"Playa",
    "sg:orig_category":"Cerrajer\u00cda, Ferrallista",
    "sg:phone":"+34 961 46 05 38",
    "sg:postcode":"46137",
    "sg:province":"Valencia",
    "wof:name":"Cerrajeros El Autonomo S.l.",
    "wof:placetype":"venue"
},
  "geometry": {"coordinates":[-0.2876740098,39.5635910034],"type":"Point"}
}