{
  "type": "Feature",
  "properties": {
    "addr:full":"Plaz Olmo, 8 Pobla Del Duc Valencia 46840",
    "addr:housenumber":"8",
    "addr:postcode":"46840",
    "addr:street":"Plaz Olmo",
    "iso:country":"ES",
    "sg:address":"Plaz Olmo, 8",
    "sg:city":"Pobla Del Duc",
    "sg:orig_category":"Molduras, Junquillos, Listones Y Molduras Perforadas",
    "sg:phone":"+34 962 25 02 50",
    "sg:postcode":"46840",
    "sg:province":"Valencia",
    "wof:name":"Villena Agudo German",
    "wof:placetype":"venue"
},
  "geometry": {"coordinates":[-0.4222159982,38.9052238464],"type":"Point"}
}