{
  "type": "Feature",
  "properties": {
    "addr:full":"Carrer de Sant Jordi, 7 Barcelona Barcelona 08028",
    "addr:housenumber":"7",
    "addr:postcode":"08028",
    "addr:street":"Carrer De Sant Jordi",
    "iso:country":"ES",
    "sg:address":"Carrer de Sant Jordi, 7",
    "sg:city":"Barcelona",
    "sg:orig_category":"Carnicer\u00cdas, Carnicer\u00cdas",
    "sg:phone":"+34 933 39 53 07",
    "sg:postcode":"08028",
    "sg:province":"Barcelona",
    "wof:name":"Niculae  Laura",
    "wof:placetype":"venue"
},
  "geometry": {"coordinates":[2.1338078976,41.3749656677],"type":"Point"}
}