{
  "type": "Feature",
  "properties": {
    "addr:full":"Carrer de Carme, 91 Malgrat Mar Barcelona 08380",
    "addr:housenumber":"91",
    "addr:postcode":"08380",
    "addr:street":"Carrer De Carme",
    "iso:country":"ES",
    "sg:address":"Carrer de Carme, 91",
    "sg:city":"Malgrat Mar",
    "sg:orig_category":"Marroquiner\u00cda Y Art\u00cdculos De Viaje (al Por Menor)",
    "sg:phone":"+34 937 61 08 38",
    "sg:postcode":"08380",
    "sg:province":"Barcelona",
    "wof:name":"Oriol Sagol Emilia",
    "wof:placetype":"venue"
},
  "geometry": {"coordinates":[2.7405240536,41.6454315186],"type":"Point"}
}