{
  "type": "Feature",
  "properties": {
    "addr:full":"Ctra Ascoy, 3 Cieza Murcia 30530",
    "addr:housenumber":"3",
    "addr:postcode":"30530",
    "addr:street":"Ctra Ascoy",
    "iso:country":"ES",
    "sg:address":"Ctra Ascoy, 3",
    "sg:city":"Cieza",
    "sg:orig_category":"Material Y Herramientas Agr\u00cdcolas",
    "sg:phone":"+34 968 76 15 62",
    "sg:postcode":"30530",
    "sg:province":"Murcia",
    "wof:name":"Lucas Ortin Juan Antonio",
    "wof:placetype":"venue"
},
  "geometry": {"coordinates":[-1.4184889793,38.2712287903],"type":"Point"}
}