{
  "type": "Feature",
  "properties": {
    "iso:country":"ES",
    "sg:address":"Calle de Mar Amarillo, 10",
    "sg:city":"Madrid",
    "sg:orig_category":"Relojer\u00cda (al Por Menor, Reparaci\u00d3n)",
    "sg:phone":"+34 917 64 30 12",
    "sg:postcode":"28033",
    "sg:province":"Madrid",
    "wof:name":"Garzon Montesinos Jose",
    "wof:placetype":"venue"
},
  "geometry": {"coordinates":[-3.6412789822,40.4743003845],"type":"Point"}
}