{
  "type": "Feature",
  "properties": {
    "iso:country":"ES",
    "sg:address":"Calle de Batalla De Brunete, 81",
    "sg:city":"Palmas De Gran Canaria",
    "sg:orig_category":"Inform\u00c1tica Equipo Y Programas (al Por Mayor)",
    "sg:phone":"+34 928 42 42 00",
    "sg:postcode":"35013",
    "sg:province":"Las Palmas",
    "sg:website":"www.sycom.es",
    "wof:name":"Suministros Y Componentes Informaticos S.l.",
    "wof:placetype":"venue"
},
  "geometry": {"coordinates":[-15.450293541,28.0958881378],"type":"Point"}
}