{
  "type": "Feature",
  "properties": {
    "iso:country":"ES",
    "sg:address":"Calle de Pintor Nicolas Massieu, 2",
    "sg:city":"Tamaraceite",
    "sg:orig_category":"Molduras, Junquillos, Listones Y Molduras Perforadas",
    "sg:phone":"+34 928 66 75 01",
    "sg:postcode":"35019",
    "sg:province":"Las Palmas",
    "wof:name":"Santiago Casa\u00f1as Antonio Moises",
    "wof:placetype":"venue"
},
  "geometry": {"coordinates":[-15.4524173737,28.1040420532],"type":"Point"}
}