{
  "type": "Feature",
  "properties": {
    "iso:country":"ES",
    "sg:address":"Rua Salvador De Madariaga, 1",
    "sg:city":"Ourense",
    "sg:orig_category":"Muebles Y Accesorios Para Cocinas Y Cuartos De Ba\u00d1o (al Por Menor)",
    "sg:phone":"+34 988 24 65 92",
    "sg:postcode":"32002",
    "sg:province":"Ourense",
    "sg:website":"www.kubika.org",
    "wof:name":"Roberto Y Javier Montes S.l.",
    "wof:placetype":"venue"
},
  "geometry": {"coordinates":[-7.8715519905,42.3403053284],"type":"Point"}
}