{
  "type": "Feature",
  "properties": {
    "iso:country":"ES",
    "sg:address":"Ctra. Mao-es Castell, S/n",
    "sg:city":"Castell",
    "sg:orig_category":"Hoteles",
    "sg:phone":"+34 971 36 27 00",
    "sg:postcode":"07720",
    "sg:province":"Islas Baleares",
    "wof:name":"Hotel Del Almirante Collingwood S.l.",
    "wof:placetype":"venue"
},
  "geometry": {"coordinates":[4.2858448029,39.879650116],"type":"Point"}
}