{
  "type": "Feature",
  "properties": {
    "addr:full":"Calle de Grupo Escolar, 3 Blancas Teruel 44314",
    "addr:housenumber":"3",
    "addr:postcode":"44314",
    "addr:street":"Calle De Grupo Escolar",
    "iso:country":"ES",
    "sg:address":"Calle de Grupo Escolar, 3",
    "sg:city":"Blancas",
    "sg:orig_category":"Sanatorios M\u00c9dico",
    "sg:phone":"+34 978 86 36 92",
    "sg:postcode":"44314",
    "sg:province":"Teruel",
    "wof:name":"Ayuntamiento-consultorio Medico",
    "wof:placetype":"venue"
},
  "geometry": {"coordinates":[-1.4811128378,40.8126487732],"type":"Point"}
}