{
  "type": "Feature",
  "properties": {
    "addr:full":"Calle de Corta, 16 Andujar Ja\u00e9n 23740",
    "addr:housenumber":"16",
    "addr:postcode":"23740",
    "addr:street":"Calle De Corta",
    "iso:country":"ES",
    "sg:address":"Calle de Corta, 16",
    "sg:city":"Andujar",
    "sg:orig_category":"Electrodom\u00c9sticos (al Por Menor)",
    "sg:phone":"+34 953 50 72 99",
    "sg:postcode":"23740",
    "sg:province":"Ja\u00e9n",
    "wof:name":"Cantudo Ortega Manuel",
    "wof:placetype":"venue"
},
  "geometry": {"coordinates":[-4.0531401634,38.0399971008],"type":"Point"}
}