{
  "type": "Feature",
  "properties": {
    "iso:country":"ES",
    "sg:address":"Calle de Abraham Lincoln, 10",
    "sg:city":"Giles",
    "sg:orig_category":"Desinfecci\u00d3n, Desinsectaci\u00d3n, Desratizaci\u00d3n",
    "sg:phone":"+34 928 67 77 89",
    "sg:postcode":"35010",
    "sg:province":"Las Palmas",
    "wof:name":"Saniplag Control De Plagas S.l",
    "wof:placetype":"venue"
},
  "geometry": {"coordinates":[-15.4750595093,28.1141262054],"type":"Point"}
}