{
  "type": "Feature",
  "properties": {
    "addr:full":"Carrer de Santa Joaquima Vedruna, 12 Cambrils Tarragona 43850",
    "addr:housenumber":"12",
    "addr:postcode":"43850",
    "addr:street":"Carrer De Santa Joaquima Vedruna",
    "iso:country":"ES",
    "sg:address":"Carrer de Santa Joaquima Vedruna, 12",
    "sg:city":"Cambrils",
    "sg:orig_category":"Asesor\u00cda De Formaci\u00d3n Y Gesti\u00d3n De Personal",
    "sg:phone":"+34 977 79 10 22",
    "sg:postcode":"43850",
    "sg:province":"Tarragona",
    "wof:name":"Estivill Serveis Administratius S.l.",
    "wof:placetype":"venue"
},
  "geometry": {"coordinates":[1.0545250177,41.0710678101],"type":"Point"}
}