{
  "type": "Feature",
  "properties": {
    "iso:country":"ES",
    "sg:address":"Calle de Jacinto Mendez, 11",
    "sg:city":"Coin",
    "sg:orig_category":"Electrodom\u00c9sticos (al Por Menor)",
    "sg:phone":"+34 952 45 26 97",
    "sg:postcode":"29100",
    "sg:province":"M\u00e1laga",
    "wof:name":"Rojas Flores Juan",
    "wof:placetype":"venue"
},
  "geometry": {"coordinates":[-4.7565579414,36.6603240967],"type":"Point"}
}