{
  "type": "Feature",
  "properties": {
    "iso:country":"ES",
    "sg:address":"Rbla Anselm Clave, 31",
    "sg:city":"Cornella Llobregat",
    "sg:orig_category":"Cajas De Ahorro",
    "sg:phone":"+34 933 77 42 52",
    "sg:postcode":"08940",
    "sg:province":"Barcelona",
    "sg:website":"www.caixasabadell.es",
    "wof:name":"Caixa D'estalvis Sabadell",
    "wof:placetype":"venue"
},
  "geometry": {"coordinates":[2.0731110573,41.3541564941],"type":"Point"}
}