{
  "type": "Feature",
  "properties": {
    "iso:country":"ES",
    "sg:address":"Calle de Cervera, 14",
    "sg:city":"Tomelloso",
    "sg:orig_category":"Vinagre Y Mostaza (fabricaci\u00d3n, Al Por Mayor)",
    "sg:phone":"+34 926 51 13 89",
    "sg:postcode":"13700",
    "sg:province":"Ciudad Real",
    "wof:name":"Vinos Y Vinagres Empe S.l.",
    "wof:placetype":"venue"
},
  "geometry": {"coordinates":[-3.0226590633,39.1615867615],"type":"Point"}
}