{
  "type": "Feature",
  "properties": {
    "iso:country":"ES",
    "sg:address":"Ibai-tarte Kalea, 7",
    "sg:city":"Elgoibar",
    "sg:orig_category":"Rectificaci\u00d3n, Mecanizado, Fresado",
    "sg:phone":"+34 943 74 15 76",
    "sg:postcode":"20870",
    "sg:province":"Guip\u00f9zcoa",
    "sg:website":"www.beitxi.com",
    "wof:name":"Beitxi S.l.",
    "wof:placetype":"venue"
},
  "geometry": {"coordinates":[-2.4091899395,43.2233505249],"type":"Point"}
}