{
  "type": "Feature",
  "properties": {
    "addr:full":"Calle de Velazquez, 15 San Vicente Del Raspeig-sant Vicent Del Raspeig Alicante 03690",
    "addr:housenumber":"15",
    "addr:postcode":"03690",
    "addr:street":"Calle De Velazquez",
    "iso:country":"ES",
    "sg:address":"Calle de Velazquez, 15",
    "sg:city":"San Vicente Del Raspeig-sant Vicent Del Raspeig",
    "sg:orig_category":"Ingeniero",
    "sg:phone":"+34 965 66 05 25",
    "sg:postcode":"03690",
    "sg:province":"Alicante",
    "wof:name":"Garcia Pastor Jose Ramon",
    "wof:placetype":"venue"
},
  "geometry": {"coordinates":[-0.5229039788,38.394657135],"type":"Point"}
}