{
  "type": "Feature",
  "properties": {
    "addr:full":"Calle de Jose Maria De Pereda, 1 Ramales Victoria Cantabria 39800",
    "addr:housenumber":"1",
    "addr:postcode":"39800",
    "addr:street":"Calle De Jose Maria De Pereda",
    "iso:country":"ES",
    "sg:address":"Calle de Jose Maria De Pereda, 1",
    "sg:city":"Ramales Victoria",
    "sg:orig_category":"Molduras, Junquillos, Listones Y Molduras Perforadas",
    "sg:phone":"+34 942 64 60 53",
    "sg:postcode":"39800",
    "sg:province":"Cantabria",
    "wof:name":"Sociedad Regional De Informatica S.a.",
    "wof:placetype":"venue"
},
  "geometry": {"coordinates":[-3.4653515816,43.2580108643],"type":"Point"}
}