{
  "type": "Feature",
  "properties": {
    "iso:country":"ES",
    "sg:address":"Calle de Carretera De Villena, Km. 0003,0",
    "sg:city":"Yecla",
    "sg:orig_category":"Muebles Y Accesorios Para Cocinas Y Cuartos De Ba\u00d1o (al Por Menor)",
    "sg:phone":"+34 968 71 87 01",
    "sg:postcode":"30510",
    "sg:province":"Murcia",
    "wof:name":"Koiner Mobiliario De Yecla S.l.",
    "wof:placetype":"venue"
},
  "geometry": {"coordinates":[-1.173699379,38.6051635742],"type":"Point"}
}