{
  "type": "Feature",
  "properties": {
    "addr:full":"Trva Uribarri C, 13 Bilbao Vizcaya 48007",
    "addr:housenumber":"13",
    "addr:postcode":"48007",
    "addr:street":"Trva Uribarri C",
    "iso:country":"ES",
    "sg:address":"Trva Uribarri C, 13",
    "sg:city":"Bilbao",
    "sg:orig_category":"Asociaciones Y Clubs Deportivos",
    "sg:phone":"+34 944 45 36 22",
    "sg:postcode":"48007",
    "sg:province":"Vizcaya",
    "wof:name":"Gimnasio Makaser, S.l.",
    "wof:placetype":"venue"
},
  "geometry": {"coordinates":[-2.9209740162,43.2684631348],"type":"Point"}
}