{
  "type": "Feature",
  "properties": {
    "addr:full":"Pase Palmeras (las), 1 S. Isidro Alicante 03349",
    "addr:housenumber":"1",
    "addr:postcode":"03349",
    "addr:street":"Las;S. Isidro Alicante",
    "iso:country":"ES",
    "sg:address":"Pase Palmeras (las), 1",
    "sg:city":"S. Isidro",
    "sg:orig_category":"Aguas (distribuci\u00d3n, Servicios)",
    "sg:phone":"+34 965 48 77 34",
    "sg:postcode":"03349",
    "sg:province":"Alicante",
    "wof:name":"Comunidad De Regantes San Isidro Y El Realengo C.b",
    "wof:placetype":"venue"
},
  "geometry": {"coordinates":[-0.8409389853,38.175239563],"type":"Point"}
}