{
  "type": "Feature",
  "properties": {
    "addr:full":"Calle de Escritor Torquemada, S/n Cordoba C\u00f3rdoba 14011",
    "addr:housenumber":"s / n",
    "addr:postcode":"14011",
    "addr:street":"Calle De Escritor Torquemada;Co\u0301Rdoba",
    "iso:country":"ES",
    "sg:address":"Calle de Escritor Torquemada, S/n",
    "sg:city":"Cordoba",
    "sg:orig_category":"Centros De Educaci\u00d3n Especial",
    "sg:phone":"+34 957 40 52 31",
    "sg:postcode":"14011",
    "sg:province":"C\u00f3rdoba",
    "wof:name":"Junta De Andalucia",
    "wof:placetype":"venue"
},
  "geometry": {"coordinates":[-4.7910289764,37.8913536072],"type":"Point"}
}