{
  "type": "Feature",
  "properties": {
    "addr:full":"Calle de Mulhacen, 25 Granada Granada 18005",
    "addr:housenumber":"25",
    "addr:postcode":"18005",
    "addr:street":"Calle De Mulhacen",
    "iso:country":"ES",
    "sg:address":"Calle de Mulhacen, 25",
    "sg:city":"Granada",
    "sg:orig_category":"Peluqueros: De Se\u00d1oras",
    "sg:phone":"+34 958 52 27 78",
    "sg:postcode":"18005",
    "sg:province":"Granada",
    "wof:name":"Merida Hernandez Rosa",
    "wof:placetype":"venue"
},
  "geometry": {"coordinates":[-3.6013600826,37.1681098938],"type":"Point"}
}