{
  "type": "Feature",
  "properties": {
    "addr:full":"Calle de Esperanza Macarena, 24 Madrid Madrid 28021",
    "addr:housenumber":"24",
    "addr:postcode":"madrid;28021",
    "addr:street":"Calle De Esperanza Macarena",
    "iso:country":"ES",
    "sg:address":"Calle de Esperanza Macarena, 24",
    "sg:city":"Madrid",
    "sg:orig_category":"Ropa Para Se\u00d1oras Y Caballeros (al Por Menor)",
    "sg:phone":"+34 917 97 31 50",
    "sg:postcode":"28021",
    "sg:province":"Madrid",
    "wof:name":"Zhou  Guiyue",
    "wof:placetype":"venue"
},
  "geometry": {"coordinates":[-3.6902766228,40.3494148254],"type":"Point"}
}