{
  "type": "Feature",
  "properties": {
    "iso:country":"ES",
    "sg:address":"Calle de Almirante Enriquez, 12",
    "sg:city":"Malaga",
    "sg:orig_category":"Arquitectos",
    "sg:phone":"+34 952 29 28 49",
    "sg:postcode":"29017",
    "sg:province":"M\u00e1laga",
    "wof:name":"Sanjuan Herreros Luis",
    "wof:placetype":"venue"
},
  "geometry": {"coordinates":[-4.3664288521,36.7208900452],"type":"Point"}
}