{
  "type": "Feature",
  "properties": {
    "addr:full":"Avda Manuel Siurot, 7 Huelva Huelva 21004",
    "addr:housenumber":"7",
    "addr:postcode":"21004",
    "addr:street":"Avda Manuel Siurot",
    "iso:country":"ES",
    "sg:address":"Avda Manuel Siurot, 7",
    "sg:city":"Huelva",
    "sg:orig_category":"Hoteles",
    "sg:phone":"+34 959 54 12 60",
    "sg:postcode":"21004",
    "sg:province":"Huelva",
    "wof:name":"Condesa Hoteles S.l.",
    "wof:placetype":"venue"
},
  "geometry": {"coordinates":[-6.948805809,37.2630462646],"type":"Point"}
}