{
  "type": "Feature",
  "properties": {
    "addr:full":"Calle de San Antonio, 36 Riba-roja Turia Valencia 46190",
    "addr:housenumber":"36",
    "addr:postcode":"46190",
    "addr:street":"Calle De San Antonio",
    "iso:country":"ES",
    "sg:address":"Calle de San Antonio, 36",
    "sg:city":"Riba-roja Turia",
    "sg:orig_category":"Confecci\u00d3n De Trajes Para Se\u00d1oras",
    "sg:phone":"+34 962 77 07 16",
    "sg:postcode":"46190",
    "sg:province":"Valencia",
    "wof:name":"Navarro Navarro Concepcion",
    "wof:placetype":"venue"
},
  "geometry": {"coordinates":[-0.5685480237,39.546497345],"type":"Point"}
}