{
  "type": "Feature",
  "properties": {
    "addr:full":"Nobel-espiritu Santo, 18 Cambre La Coru\u00f1a 15650",
    "addr:housenumber":"18",
    "addr:postcode":"15650",
    "addr:street":"Santo;La Corun\u0303A",
    "iso:country":"ES",
    "sg:address":"Nobel-espiritu Santo, 18",
    "sg:city":"Cambre",
    "sg:orig_category":"Mayoristas E Intermediarios En Alcoholes",
    "sg:phone":"+34 981 64 90 00",
    "sg:postcode":"15650",
    "sg:province":"La Coru\u00f1a",
    "wof:name":"Exclusivas Luis Limia S.l.",
    "wof:placetype":"venue"
},
  "geometry": {"coordinates":[-8.3069343567,43.2885551453],"type":"Point"}
}