{
  "type": "Feature",
  "properties": {
    "addr:full":"Calle de Infante Don Fernando, 15 Antequera M\u00e1laga 29200",
    "addr:housenumber":"15",
    "addr:postcode":"29200",
    "addr:street":"Calle De Infante Don Fernando",
    "iso:country":"ES",
    "sg:address":"Calle de Infante Don Fernando, 15",
    "sg:city":"Antequera",
    "sg:orig_category":"Ense\u00d1anza Variada",
    "sg:phone":"+34 952 84 07 56",
    "sg:postcode":"29200",
    "sg:province":"M\u00e1laga",
    "wof:name":"Galindo Becerra Jose",
    "wof:placetype":"venue"
},
  "geometry": {"coordinates":[-4.5599331856,37.0169754028],"type":"Point"}
}