{
  "type": "Feature",
  "properties": {
    "iso:country":"ES",
    "sg:address":"Av Paisos Catalans, 9",
    "sg:city":"Balaguer",
    "sg:orig_category":"Transportes Por V\u00cdas Navegables",
    "sg:phone":"+34 973 44 71 01",
    "sg:postcode":"25600",
    "sg:province":"Lleida",
    "wof:name":"Riu Badia Antonio",
    "wof:placetype":"venue"
},
  "geometry": {"coordinates":[0.807765007,41.7867584229],"type":"Point"}
}