{
  "type": "Feature",
  "properties": {
    "addr:full":"Calle de Americo Vespucio, 51 Clavellinas Las Palmas 35214",
    "addr:housenumber":"51",
    "addr:postcode":"35214",
    "addr:street":"Calle De Americo Vespucio;Las Palmas",
    "iso:country":"ES",
    "sg:address":"Calle de Americo Vespucio, 51",
    "sg:city":"Clavellinas",
    "sg:orig_category":"M\u00c9dicos: Ginecolog\u00cda Y Obstetricia",
    "sg:phone":"+34 928 13 25 98",
    "sg:postcode":"35214",
    "sg:province":"Las Palmas",
    "wof:name":"Marrero Rocha Enrique",
    "wof:placetype":"venue"
},
  "geometry": {"coordinates":[-15.378780365,27.983581543],"type":"Point"}
}