{
  "type": "Feature",
  "properties": {
    "addr:full":"Av Corts Catalanes, 12 Palafrugell Girona 17200",
    "addr:housenumber":"12",
    "addr:postcode":"17200",
    "addr:street":"Av Corts Catalanes",
    "iso:country":"ES",
    "sg:address":"Av Corts Catalanes, 12",
    "sg:city":"Palafrugell",
    "sg:orig_category":"Restaurantes",
    "sg:phone":"+34 972 30 44 28",
    "sg:postcode":"17200",
    "sg:province":"Girona",
    "wof:name":"Ortiz Fenoy Maria Josefa",
    "wof:placetype":"venue"
},
  "geometry": {"coordinates":[3.1670839787,41.9115867615],"type":"Point"}
}