{
  "type": "Feature",
  "properties": {
    "iso:country":"ES",
    "sg:address":"Calle de Real, 69",
    "sg:city":"Estacion",
    "sg:orig_category":"Centros Empresariales",
    "sg:phone":"+34 918 51 51 25",
    "sg:postcode":"28400",
    "sg:province":"Madrid",
    "sg:website":"www.aab-limpiezas.com",
    "wof:name":"Aab Limpiezas Madrile\u00f1as S.l.",
    "wof:placetype":"venue"
},
  "geometry": {"coordinates":[-3.582156,40.453995],"type":"Point"}
}