{
  "type": "Feature",
  "properties": {
    "addr:full":"Carr Sequia De Tormos, 9 Pai I Capellans Valencia 46930",
    "addr:housenumber":"9",
    "addr:postcode":"46930",
    "addr:street":"Carr Sequia De Tormos",
    "iso:country":"ES",
    "sg:address":"Carr Sequia De Tormos, 9",
    "sg:city":"Pai I Capellans",
    "sg:orig_category":"Artes Gr\u00c1ficas, Artes Pl\u00c1sticas (curso)",
    "sg:phone":"+34 961 92 08 39",
    "sg:postcode":"46930",
    "sg:province":"Valencia",
    "wof:name":"Solucions Grafiques S.c.v.",
    "wof:placetype":"venue"
},
  "geometry": {"coordinates":[-0.4419890046,39.482711792],"type":"Point"}
}