{
  "type": "Feature",
  "properties": {
    "addr:full":"Pg Manuel Girona, 65 Barcelona Barcelona 08034",
    "addr:housenumber":"65",
    "addr:postcode":"08034",
    "addr:street":"Pg Manuel Girona",
    "iso:country":"ES",
    "sg:address":"Pg Manuel Girona, 65",
    "sg:city":"Barcelona",
    "sg:orig_category":"Arquitectos",
    "sg:phone":"+34 932 05 25 17",
    "sg:postcode":"08034",
    "sg:province":"Barcelona",
    "wof:name":"Monso Celma Josep Ambros",
    "wof:placetype":"venue"
},
  "geometry": {"coordinates":[2.128123045,41.3922233582],"type":"Point"}
}