{
  "type": "Feature",
  "properties": {
    "iso:country":"ES",
    "sg:address":"Ctra Burgos Portugal, S/n",
    "sg:city":"Fuente S. Esteban",
    "sg:orig_category":"Mec\u00c1nico Del Autom\u00d3vil",
    "sg:phone":"+34 923 44 02 52",
    "sg:postcode":"37200",
    "sg:province":"Salamanca",
    "wof:name":"Garcia Matilla Eduardo",
    "wof:placetype":"venue"
},
  "geometry": {"coordinates":[-6.1650328636,40.826171875],"type":"Point"}
}