{
  "type": "Feature",
  "properties": {
    "addr:full":"Rua Alberto Vilanova (de), S/n Carballi\u00f1o Ourense 32500",
    "addr:postcode":"32500",
    "addr:street":"Rua Alberto;De S / N",
    "iso:country":"ES",
    "sg:address":"Rua Alberto Vilanova (de), S/n",
    "sg:city":"Carballi\u00f1o",
    "sg:orig_category":"Ense\u00d1anza Secundaria: Colegios Y Escuelas Privadas",
    "sg:phone":"+34 988 27 16 26",
    "sg:postcode":"32500",
    "sg:province":"Ourense",
    "wof:name":"Instituto De Bacharelato Mixto De Carballino",
    "wof:placetype":"venue"
},
  "geometry": {"coordinates":[-8.0712871552,42.4290237427],"type":"Point"}
}