{
  "type": "Feature",
  "properties": {
    "addr:full":"Aralar Kalea, 43 Lekunberri Navarra 31870",
    "addr:housenumber":"43",
    "addr:postcode":"31870",
    "addr:street":"Aralar Kalea",
    "iso:country":"ES",
    "sg:address":"Aralar Kalea, 43",
    "sg:city":"Lekunberri",
    "sg:orig_category":"Farmacias",
    "sg:phone":"+34 948 50 40 62",
    "sg:postcode":"31870",
    "sg:province":"Navarra",
    "wof:name":"Azpiroz Azpiroz Maria Angeles",
    "wof:placetype":"venue"
},
  "geometry": {"coordinates":[-1.8959610462,43.0046653748],"type":"Point"}
}