{
  "type": "Feature",
  "properties": {
    "iso:country":"ES",
    "sg:address":"Calle de Ca\u00d1averal, 15",
    "sg:city":"Madrid",
    "sg:orig_category":"Comercio De Piezas De Recambio Y De Accesorios De Veh\u00cdculos, Veh\u00cdculos Industriales",
    "sg:phone":"+34 913 14 86 47",
    "sg:postcode":"28029",
    "sg:province":"Madrid",
    "wof:name":"Repuestos Ca\u00f1averal S. A.",
    "wof:placetype":"venue"
},
  "geometry": {"coordinates":[-3.6947376728,40.4664115906],"type":"Point"}
}