{
  "type": "Feature",
  "properties": {
    "addr:full":"Avda Libertad De La, 25 Donostia-san Sebastian Guip\u00f9zcoa 20004",
    "addr:housenumber":"25",
    "addr:postcode":"20004",
    "addr:street":"Avda Libertad De La",
    "iso:country":"ES",
    "sg:address":"Avda Libertad De La, 25",
    "sg:city":"Donostia-san Sebastian",
    "sg:orig_category":"Asesor\u00cda Fiscal Y Jur\u00cddica",
    "sg:phone":"+34 943 42 66 51",
    "sg:postcode":"20004",
    "sg:province":"Guip\u00f9zcoa",
    "wof:name":"Asesoria Zulueta S.l.",
    "wof:placetype":"venue"
},
  "geometry": {"coordinates":[-1.9827903509,43.3191986084],"type":"Point"}
}