{
  "type": "Feature",
  "properties": {
    "addr:full":"Calle de Alcalde Ronquillo, 2 Arevalo \u00c1vila 05200",
    "addr:housenumber":"2",
    "addr:postcode":"05200",
    "addr:street":"Calle De Alcalde Ronquillo",
    "iso:country":"ES",
    "sg:address":"Calle de Alcalde Ronquillo, 2",
    "sg:city":"Arevalo",
    "sg:orig_category":"Abogados",
    "sg:phone":"+34 920 30 13 67",
    "sg:postcode":"05200",
    "sg:province":"\u00c1vila",
    "wof:name":"Iglesias Orgaz Pilar",
    "wof:placetype":"venue"
},
  "geometry": {"coordinates":[-4.7191948891,41.0647239685],"type":"Point"}
}