{
  "type": "Feature",
  "properties": {
    "addr:full":"Avda Vega (la), 50 Puebla Del Rio Sevilla 41130",
    "addr:housenumber":"50",
    "addr:postcode":"41130",
    "addr:street":"Avda Vega La",
    "iso:country":"ES",
    "sg:address":"Avda Vega (la), 50",
    "sg:city":"Puebla Del Rio",
    "sg:orig_category":"Estudios, Instalaci\u00d3n De Climatizaci\u00d3n",
    "sg:phone":"+34 955 77 27 01",
    "sg:postcode":"41130",
    "sg:province":"Sevilla",
    "wof:name":"Montajes Carmona S.l.",
    "wof:placetype":"venue"
},
  "geometry": {"coordinates":[-6.064743042,37.2641677856],"type":"Point"}
}