{
  "type": "Feature",
  "properties": {
    "addr:full":"Calle de Lauaxeta Olerkari, 9 Mungia Vizcaya 48100",
    "addr:housenumber":"9",
    "addr:postcode":"48100",
    "addr:street":"Calle De Lauaxeta Olerkari",
    "iso:country":"ES",
    "sg:address":"Calle de Lauaxeta Olerkari, 9",
    "sg:city":"Mungia",
    "sg:orig_category":"Molduras, Junquillos, Listones Y Molduras Perforadas",
    "sg:phone":"+34 946 74 27 09",
    "sg:postcode":"48100",
    "sg:province":"Vizcaya",
    "wof:name":"Uria Andicoechea Ignacio",
    "wof:placetype":"venue"
},
  "geometry": {"coordinates":[-2.8489570618,43.3561477661],"type":"Point"}
}