{
  "type": "Feature",
  "properties": {
    "addr:full":"Calle de Ave Maria, 2 Ponferrada Le\u00f3n 24400",
    "addr:housenumber":"2",
    "addr:postcode":"24400",
    "addr:street":"Calle De Ave Maria",
    "iso:country":"ES",
    "sg:address":"Calle de Ave Maria, 2",
    "sg:city":"Ponferrada",
    "sg:orig_category":"Agencias De Viajes",
    "sg:phone":"+34 987 41 07 62",
    "sg:postcode":"24400",
    "sg:province":"Le\u00f3n",
    "wof:name":"Viajes Rosymar S. A.",
    "wof:placetype":"venue"
},
  "geometry": {"coordinates":[-6.5997719765,42.5482673645],"type":"Point"}
}