{
  "type": "Feature",
  "properties": {
    "iso:country":"ES",
    "sg:address":"Calle de Cruz Del Estudiante, 54",
    "sg:city":"Puente-genil",
    "sg:orig_category":"Perfumer\u00cda (al Por Menor)",
    "sg:phone":"+34 957 60 68 95",
    "sg:postcode":"14500",
    "sg:province":"C\u00f3rdoba",
    "wof:name":"Alarcon Ortiz Ines",
    "wof:placetype":"venue"
},
  "geometry": {"coordinates":[-4.768725872,37.3893203735],"type":"Point"}
}