{
  "type": "Feature",
  "properties": {
    "addr:full":"Rond Coru\u00d1a, 32 Melide La Coru\u00f1a 15800",
    "addr:housenumber":"32",
    "addr:postcode":"15800",
    "addr:street":"Corun\u0303A;La Corun\u0303A",
    "iso:country":"ES",
    "sg:address":"Rond Coru\u00d1a, 32",
    "sg:city":"Melide",
    "sg:orig_category":"Fabricaci\u00d3n De Bibliotecas Y Estanter\u00cdas",
    "sg:phone":"+34 981 81 53 71",
    "sg:postcode":"15800",
    "sg:province":"La Coru\u00f1a",
    "wof:name":"Eypar S.a.",
    "wof:placetype":"venue"
},
  "geometry": {"coordinates":[-8.0153255463,42.9151649475],"type":"Point"}
}