{
  "type": "Feature",
  "properties": {
    "addr:full":"Pase Estacion, 31 Torredelcampo Ja\u00e9n 23640",
    "addr:housenumber":"31",
    "addr:postcode":"23640",
    "addr:street":"Estacion;Jae\u0301N",
    "iso:country":"ES",
    "sg:address":"Pase Estacion, 31",
    "sg:city":"Torredelcampo",
    "sg:orig_category":"Molduras, Junquillos, Listones Y Molduras Perforadas",
    "sg:phone":"+34 953 56 77 24",
    "sg:postcode":"23640",
    "sg:province":"Ja\u00e9n",
    "wof:name":"Blanca Vacas Pedro",
    "wof:placetype":"venue"
},
  "geometry": {"coordinates":[-3.8999419212,37.7725715637],"type":"Point"}
}