{
  "type": "Feature",
  "properties": {
    "iso:country":"ES",
    "sg:address":"Carrer de Jaume I, 27",
    "sg:city":"Sagrera",
    "sg:orig_category":"Sales (al Por Mayor)",
    "sg:phone":"+34 938 44 67 92",
    "sg:postcode":"08187",
    "sg:province":"Barcelona",
    "wof:name":"Gongora Representaciones S.l.",
    "wof:placetype":"venue"
},
  "geometry": {"coordinates":[2.2249970436,41.6540222168],"type":"Point"}
}