{
  "type": "Feature",
  "properties": {
    "addr:full":"Calle de Convento De Jerusalen, 57 Valencia Valencia 46007",
    "addr:housenumber":"57",
    "addr:postcode":"46007",
    "addr:street":"Calle De Convento;Valencia",
    "iso:country":"ES",
    "sg:address":"Calle de Convento De Jerusalen, 57",
    "sg:city":"Valencia",
    "sg:orig_category":"Agencias Y Agentes Comerciales, Representantes",
    "sg:phone":"+34 963 80 42 78",
    "sg:postcode":"46007",
    "sg:province":"Valencia",
    "wof:name":"Alberola Carrera Laura Victoria",
    "wof:placetype":"venue"
},
  "geometry": {"coordinates":[-0.3803530931,39.4645080566],"type":"Point"}
}