{
  "type": "Feature",
  "properties": {
    "addr:full":"Calle de Altozano, 1 Vejer De La Frontera C\u00e1diz 11150",
    "addr:housenumber":"1",
    "addr:postcode":"11150",
    "addr:street":"Calle De Altozano",
    "iso:country":"ES",
    "sg:address":"Calle de Altozano, 1",
    "sg:city":"Vejer De La Frontera",
    "sg:orig_category":"Promotores Constructores",
    "sg:phone":"+34 956 45 03 84",
    "sg:postcode":"11150",
    "sg:province":"C\u00e1diz",
    "wof:name":"Construcciones Basallote Y Mocito S.l.",
    "wof:placetype":"venue"
},
  "geometry": {"coordinates":[-5.9652161598,36.2535400391],"type":"Point"}
}