{
  "type": "Feature",
  "properties": {
    "iso:country":"ES",
    "sg:address":"Calle de Castillo De Arevalo, 15",
    "sg:city":"Rozas De Madrid",
    "sg:orig_category":"Promotores Constructores",
    "sg:phone":"+34 916 36 50 00",
    "sg:postcode":"28230",
    "sg:province":"Madrid",
    "wof:name":"Asesoria Tecnica 3000 S.l.",
    "wof:placetype":"venue"
},
  "geometry": {"coordinates":[-3.8967885971,40.5106925964],"type":"Point"}
}