{
  "type": "Feature",
  "properties": {
    "iso:country":"ES",
    "sg:address":"Rua Ecuador, 77",
    "sg:city":"Vigo",
    "sg:orig_category":"Agencias De Viajes",
    "sg:phone":"+34 986 41 96 63",
    "sg:postcode":"36204",
    "sg:province":"Pontevedra",
    "sg:website":"www.viajeselcorteingles.es",
    "wof:name":"Viajes El Corte Ingles S.a.",
    "wof:placetype":"venue"
},
  "geometry": {"coordinates":[-8.7161493301,42.2322616577],"type":"Point"}
}