{
  "type": "Feature",
  "properties": {
    "addr:full":"Av Catalunya, S/n Hospitalet Llobregat Barcelona 08905",
    "addr:housenumber":"s",
    "addr:postcode":"08905",
    "addr:street":"Av Catalunya;/ N",
    "iso:country":"ES",
    "sg:address":"Av Catalunya, S/n",
    "sg:city":"Hospitalet Llobregat",
    "sg:orig_category":"Librer\u00cdas",
    "sg:phone":"+34 934 48 32 13",
    "sg:postcode":"08905",
    "sg:province":"Barcelona",
    "wof:name":"Martinez Gomez Dolores",
    "wof:placetype":"venue"
},
  "geometry": {"coordinates":[2.1150550842,41.3686065674],"type":"Point"}
}