{
  "type": "Feature",
  "properties": {
    "addr:full":"Calle de Santa Genoveva Torres, 30 Valencia Valencia 46019",
    "addr:housenumber":"30",
    "addr:postcode":"46019",
    "addr:street":"Calle De Santa;Torres",
    "iso:country":"ES",
    "sg:address":"Calle de Santa Genoveva Torres, 30",
    "sg:city":"Valencia",
    "sg:orig_category":"Empresarios Y Productoras De Espect\u00c1culos",
    "sg:phone":"+34 963 65 91 92",
    "sg:postcode":"46019",
    "sg:province":"Valencia",
    "wof:name":"Musica Joven",
    "wof:placetype":"venue"
},
  "geometry": {"coordinates":[-0.3636650145,39.4927558899],"type":"Point"}
}