{
  "type": "Feature",
  "properties": {
    "iso:country":"ES",
    "sg:address":"Calle de Pico De Los Artilleros, 7",
    "sg:city":"Madrid",
    "sg:orig_category":"Ense\u00d1anza: Costura",
    "sg:phone":"+34 913 71 02 81",
    "sg:postcode":"28030",
    "sg:province":"Madrid",
    "wof:name":"Casta\u00f1o Albarran Juana",
    "wof:placetype":"venue"
},
  "geometry": {"coordinates":[-3.6400830746,40.4083747864],"type":"Point"}
}