{
  "type": "Feature",
  "properties": {
    "iso:country":"ES",
    "sg:address":"Calle de Gonzalo Gallas, 9",
    "sg:city":"Granada",
    "sg:orig_category":"Servicios Diversos",
    "sg:phone":"+34 958 40 09 25",
    "sg:postcode":"18003",
    "sg:province":"Granada",
    "sg:website":"www.unipost.es",
    "wof:name":"Unipost S.a.",
    "wof:placetype":"venue"
},
  "geometry": {"coordinates":[-3.6103498936,37.1790351868],"type":"Point"}
}