{
  "type": "Feature",
  "properties": {
    "addr:full":"Av Masnou, 68 Hospitalet Llobregat Barcelona 08905",
    "addr:housenumber":"68",
    "addr:postcode":"08905",
    "addr:street":"Av Masnou",
    "iso:country":"ES",
    "sg:address":"Av Masnou, 68",
    "sg:city":"Hospitalet Llobregat",
    "sg:orig_category":"Bancos",
    "sg:phone":"+34 933 34 03 00",
    "sg:postcode":"08905",
    "sg:province":"Barcelona",
    "wof:name":"Banco Bilbao Vizcaya Argentaria S.a.",
    "wof:placetype":"venue"
},
  "geometry": {"coordinates":[2.1094779968,41.3692131042],"type":"Point"}
}