{
  "type": "Feature",
  "properties": {
    "iso:country":"ES",
    "sg:address":"Pol Ind Centro De Ocio Sur, 46",
    "sg:city":"Cordoba",
    "sg:classifiers":[
        {
            "category":"Cinema",
            "subcategory":"Movie Theater",
            "type":"Entertainment"
        }
    ],
    "sg:phone":"+34 957 42 13 26",
    "sg:postcode":"14013",
    "sg:province":"C\u00f3rdoba",
    "sg:tags":[
        "salas",
        "de",
        "cine"
    ],
    "wof:name":"Segismundo Hernandez S.a.",
    "wof:placetype":"venue"
},
  "geometry": {"coordinates":[-4.7784028053,37.8779411316],"type":"Point"}
}