{
  "type": "Feature",
  "properties": {
    "iso:country":"ES",
    "sg:address":"Grup Iturribide, 5",
    "sg:city":"Iturribide",
    "sg:orig_category":"Peluquer\u00cdas, Peluquer\u00cda Mixta",
    "sg:phone":"+34 944 64 70 17",
    "sg:postcode":"48940",
    "sg:province":"Vizcaya",
    "wof:name":"Maria Isidora Gonzalez Ramos Y Maria Isabel Gonzalez Ramos Cdad.",
    "wof:placetype":"venue"
},
  "geometry": {"coordinates":[-2.9860789776,43.3275489807],"type":"Point"}
}