{
  "type": "Feature",
  "properties": {
    "iso:country":"ES",
    "sg:address":"Pl Marquilles, 2",
    "sg:city":"Sabadell",
    "sg:orig_category":"Florister\u00cdas",
    "sg:phone":"+34 937 26 07 35",
    "sg:postcode":"08201",
    "sg:province":"Barcelona",
    "wof:name":"Ramirez Medina Rosa Maria",
    "wof:placetype":"venue"
},
  "geometry": {"coordinates":[2.105741024,41.5462188721],"type":"Point"}
}