{
  "type": "Feature",
  "properties": {
    "iso:country":"ES",
    "sg:address":"Calle de Cervantes, 12",
    "sg:city":"Oviedo",
    "sg:orig_category":"Perfumer\u00cda (al Por Menor)",
    "sg:phone":"+34 985 25 11 12",
    "sg:postcode":"33004",
    "sg:province":"Asturias",
    "wof:name":"Gonzalez Miguel Alejandro Desiderio",
    "wof:placetype":"venue"
},
  "geometry": {"coordinates":[-5.855890274,43.3628883362],"type":"Point"}
}