{
  "type": "Feature",
  "properties": {
    "iso:country":"ES",
    "sg:address":"Avda Juan Carlos I, 34",
    "sg:city":"Alhama Murcia",
    "sg:orig_category":"Quincaller\u00cda (al Por Menor)",
    "sg:phone":"+34 968 63 07 80",
    "sg:postcode":"30840",
    "sg:province":"Murcia",
    "wof:name":"Belchi Sanchez Andres",
    "wof:placetype":"venue"
},
  "geometry": {"coordinates":[-1.4247200489,37.8511199951],"type":"Point"}
}