{
  "type": "Feature",
  "properties": {
    "iso:country":"ES",
    "sg:address":"Avda Andalucia, 1",
    "sg:city":"Chercos Nuevo",
    "sg:orig_category":"Molduras, Junquillos, Listones Y Molduras Perforadas",
    "sg:phone":"+34 950 12 25 49",
    "sg:postcode":"04859",
    "sg:province":"Almer\u00eda",
    "wof:name":"Mena Saez Maria",
    "wof:placetype":"venue"
},
  "geometry": {"coordinates":[-2.2588579655,37.2673110962],"type":"Point"}
}