{
  "type": "Feature",
  "properties": {
    "iso:country":"ES",
    "sg:address":"I. Peral, 40",
    "sg:city":"Sedavi",
    "sg:orig_category":"Internados & Ense\u00d1anza Privada",
    "sg:phone":"+34 963 75 54 23",
    "sg:postcode":"46910",
    "sg:province":"Valencia",
    "wof:name":"Colegio Sedavi",
    "wof:placetype":"venue"
},
  "geometry": {"coordinates":[-0.388139993,39.4270439148],"type":"Point"}
}