{
  "type": "Feature",
  "properties": {
    "iso:country":"ES",
    "sg:address":"Pg Maragall, 362",
    "sg:city":"Barcelona",
    "sg:orig_category":"Pod\u00d3logos: Pedicuros",
    "sg:phone":"+34 934 20 73 22",
    "sg:postcode":"08031",
    "sg:province":"Barcelona",
    "wof:name":"Li\u00f1an Rico Angel",
    "wof:placetype":"venue"
},
  "geometry": {"coordinates":[2.1647388935,41.4279975891],"type":"Point"}
}