{
  "type": "Feature",
  "properties": {
    "addr:full":"Calle de Cruz, 60 Alhaurin El Grande M\u00e1laga 29120",
    "addr:housenumber":"60",
    "addr:postcode":"29120",
    "addr:street":"Calle De Cruz",
    "iso:country":"ES",
    "sg:address":"Calle de Cruz, 60",
    "sg:city":"Alhaurin El Grande",
    "sg:orig_category":"Ropa Para Caballeros (al Por Menor)",
    "sg:phone":"+34 952 49 00 74",
    "sg:postcode":"29120",
    "sg:province":"M\u00e1laga",
    "wof:name":"Oliva Claros Juan Manuel",
    "wof:placetype":"venue"
},
  "geometry": {"coordinates":[-4.6894202232,36.6431007385],"type":"Point"}
}