{
  "type": "Feature",
  "properties": {
    "iso:country":"ES",
    "sg:address":"C/ Can Dureta, 31",
    "sg:city":"Inca",
    "sg:orig_category":"Abogados",
    "sg:phone":"+34 971 50 26 00",
    "sg:postcode":"07300",
    "sg:province":"Islas Baleares",
    "wof:name":"Chicote Martin Manuel Santiago",
    "wof:placetype":"venue"
},
  "geometry": {"coordinates":[2.9091899395,39.7197418213],"type":"Point"}
}