{
  "type": "Feature",
  "properties": {
    "addr:full":"Carrer de Dante Alighieri, 153 Barcelona Barcelona 08032",
    "addr:housenumber":"153",
    "addr:postcode":"08032",
    "addr:street":"Carrer De Dante Alighieri",
    "iso:country":"ES",
    "sg:address":"Carrer de Dante Alighieri, 153",
    "sg:city":"Barcelona",
    "sg:orig_category":"Comidas Por Encargo, Organizaci\u00d3n De Recepciones",
    "sg:phone":"+34 933 57 55 71",
    "sg:postcode":"08032",
    "sg:province":"Barcelona",
    "wof:name":"Callejon Sanchez Jose",
    "wof:placetype":"venue"
},
  "geometry": {"coordinates":[2.1538779736,41.4254608154],"type":"Point"}
}