{
  "type": "Feature",
  "properties": {
    "addr:full":"Carretera Mequinenza-fraga, Km. 0314,0 Mequinenza Zaragoza 50170",
    "addr:postcode":"50170",
    "addr:street":"Carretera Mequinenza-Fraga Km. 0314,0",
    "iso:country":"ES",
    "sg:address":"Carretera Mequinenza-fraga, Km. 0314,0",
    "sg:city":"Mequinenza",
    "sg:orig_category":"Clubes Y Asociaciones Deportivas Y De Actividades Invernales Y De Monta\u00d1a",
    "sg:phone":"+34 974 46 46 75",
    "sg:postcode":"50170",
    "sg:province":"Zaragoza",
    "sg:website":"www.spanishfishinlodge.com",
    "wof:name":"Spanish Fishing Lodge Sl",
    "wof:placetype":"venue"
},
  "geometry": {"coordinates":[0.306309998,41.3806304932],"type":"Point"}
}