{
  "type": "Feature",
  "properties": {
    "iso:country":"ES",
    "sg:address":"Via Alexandra, 24",
    "sg:city":"Sabadell",
    "sg:orig_category":"Cl\u00cdnicas Dentales",
    "sg:phone":"+34 937 23 30 18",
    "sg:postcode":"08206",
    "sg:province":"Barcelona",
    "wof:name":"Centro De Odontologia Sanident S.l.",
    "wof:placetype":"venue"
},
  "geometry": {"coordinates":[2.0890119076,41.5541915894],"type":"Point"}
}