{
  "type": "Feature",
  "properties": {
    "iso:country":"ES",
    "sg:address":"Calle de Roque Del Este, S/n",
    "sg:city":"San Fernando",
    "sg:orig_category":"Laboratorios Y Cl\u00cdnicas Veterinarias",
    "sg:phone":"+34 928 76 47 30",
    "sg:postcode":"35100",
    "sg:province":"Las Palmas",
    "wof:name":"Martel Mendez Manuel",
    "wof:placetype":"venue"
},
  "geometry": {"coordinates":[-15.5842504501,28.0904903412],"type":"Point"}
}