{
  "type": "Feature",
  "properties": {
    "iso:country":"ES",
    "sg:address":"Carrer de Bailen, 99",
    "sg:city":"Barcelona",
    "sg:orig_category":"Arquitectos",
    "sg:phone":"+34 934 59 00 72",
    "sg:postcode":"08009",
    "sg:province":"Barcelona",
    "wof:name":"Pedro Palomar Alfredo De",
    "wof:placetype":"venue"
},
  "geometry": {"coordinates":[2.1704349518,41.3968925476],"type":"Point"}
}