{
  "type": "Feature",
  "properties": {
    "addr:full":"Avda Almozara, 37 Zaragoza Zaragoza 50003",
    "addr:housenumber":"37",
    "addr:postcode":"50003",
    "addr:street":"Avda Almozara",
    "iso:country":"ES",
    "sg:address":"Avda Almozara, 37",
    "sg:city":"Zaragoza",
    "sg:orig_category":"Tintes (fabricaci\u00d3n, Al Por Mayor)",
    "sg:phone":"+34 976 44 04 53",
    "sg:postcode":"50003",
    "sg:province":"Zaragoza",
    "wof:name":"Lopez Ferrando Victor",
    "wof:placetype":"venue"
},
  "geometry": {"coordinates":[-0.8963879943,41.6613731384],"type":"Point"}
}