{
  "type": "Feature",
  "properties": {
    "addr:full":"Av Gaspar Bennazar, 59 Palma Islas Baleares 07004",
    "addr:housenumber":"59",
    "addr:postcode":"07004",
    "addr:street":"Av Gaspar Bennazar",
    "iso:country":"ES",
    "sg:address":"Av Gaspar Bennazar, 59",
    "sg:city":"Palma",
    "sg:orig_category":"Peluquer\u00cdas, Peluquer\u00cda Mixta",
    "sg:phone":"+34 971 75 67 77",
    "sg:postcode":"07004",
    "sg:province":"Islas Baleares",
    "wof:name":"Gonzalez Gonzalez Mercedes",
    "wof:placetype":"venue"
},
  "geometry": {"coordinates":[2.6552169323,39.5838012695],"type":"Point"}
}