{
  "type": "Feature",
  "properties": {
    "iso:country":"ES",
    "sg:address":"Calle de Zabalbide, 15",
    "sg:city":"Bilbao",
    "sg:orig_category":"Asociaciones Y Clubs Deportivos",
    "sg:phone":"+34 944 33 74 22",
    "sg:postcode":"48006",
    "sg:province":"Vizcaya",
    "wof:name":"Bilbao Alpino Club",
    "wof:placetype":"venue"
},
  "geometry": {"coordinates":[-2.9203300476,43.2552986145],"type":"Point"}
}