{
  "type": "Feature",
  "properties": {
    "iso:country":"ES",
    "sg:address":"Avgd Germanies, De Les, 31",
    "sg:city":"Casco Urbano",
    "sg:orig_category":"Molduras, Junquillos, Listones Y Molduras Perforadas",
    "sg:phone":"+34 962 82 32 13",
    "sg:postcode":"46760",
    "sg:province":"Valencia",
    "wof:name":"Princesalisimo S.l.",
    "wof:placetype":"venue"
},
  "geometry": {"coordinates":[-0.2594090104,39.0749702454],"type":"Point"}
}