{
  "type": "Feature",
  "properties": {
    "iso:country":"ES",
    "sg:address":"Avda General Sanjurjo, 238",
    "sg:city":"Coru\u00d1a",
    "sg:orig_category":"Librer\u00cdas",
    "sg:phone":"+34 981 13 52 39",
    "sg:postcode":"15006",
    "sg:province":"La Coru\u00f1a",
    "wof:name":"Sanchez Gibaja Maria Dolores",
    "wof:placetype":"venue"
},
  "geometry": {"coordinates":[-8.3887519836,43.3522796631],"type":"Point"}
}