{
  "type": "Feature",
  "properties": {
    "iso:country":"ES",
    "sg:address":"Calle de Maestro Estremiana, 8",
    "sg:city":"Zaragoza",
    "sg:orig_category":"Perfumer\u00cda Y Cosm\u00c9tica (fabricaci\u00d3n, Al Por Mayor)",
    "sg:phone":"+34 976 37 10 56",
    "sg:postcode":"50006",
    "sg:province":"Zaragoza",
    "wof:name":"Mariona Urquijo Pilar",
    "wof:placetype":"venue"
},
  "geometry": {"coordinates":[-0.8858479857,41.6354904175],"type":"Point"}
}