{
  "type": "Feature",
  "properties": {
    "iso:country":"ES",
    "sg:address":"Calle de Pasos (los), 38",
    "sg:city":"Alcantarilla",
    "sg:orig_category":"Arquitectos",
    "sg:phone":"+34 968 80 67 08",
    "sg:postcode":"30820",
    "sg:province":"Murcia",
    "wof:name":"Cano Mengual Javier",
    "wof:placetype":"venue"
},
  "geometry": {"coordinates":[-1.2148430347,37.9701728821],"type":"Point"}
}