{
  "type": "Feature",
  "properties": {
    "iso:country":"ES",
    "sg:address":"Calle de Esla, 47",
    "sg:city":"Barrio De Pinilla",
    "sg:orig_category":"Librer\u00cdas",
    "sg:phone":"+34 987 23 73 17",
    "sg:postcode":"24010",
    "sg:province":"Le\u00f3n",
    "wof:name":"Addali Addali Ahmed",
    "wof:placetype":"venue"
},
  "geometry": {"coordinates":[-5.593214035,42.6045265198],"type":"Point"}
}