{
  "type": "Feature",
  "properties": {
    "iso:country":"ES",
    "sg:address":"Calle de Tercia, 73",
    "sg:city":"Malagon",
    "sg:orig_category":"Sociedades, Compa\u00d1\u00cdas Aseguradoras",
    "sg:phone":"+34 926 80 15 21",
    "sg:postcode":"13420",
    "sg:province":"Ciudad Real",
    "sg:website":"www.santalucia.es",
    "wof:name":"Santa Lucia S.a.",
    "wof:placetype":"venue"
},
  "geometry": {"coordinates":[-3.8522589207,39.1713981628],"type":"Point"}
}