{
  "type": "Feature",
  "properties": {
    "addr:full":"Avda San Ignacio, 16 Le\u00f3n Le\u00f3n 24010",
    "addr:housenumber":"16",
    "addr:postcode":"24010",
    "addr:street":"Avda San Ignacio;Leo\u0301N",
    "iso:country":"ES",
    "sg:address":"Avda San Ignacio, 16",
    "sg:city":"Le\u00f3n",
    "sg:orig_category":"Tapicer\u00cdas",
    "sg:phone":"+34 987 23 75 45",
    "sg:postcode":"24010",
    "sg:province":"Le\u00f3n",
    "wof:name":"Garcia San Martin Jose Francisco",
    "wof:placetype":"venue"
},
  "geometry": {"coordinates":[-5.5895471573,42.6041069031],"type":"Point"}
}