{
  "type": "Feature",
  "properties": {
    "iso:country":"ES",
    "sg:address":"B. La Iglesia-berron, S/n",
    "sg:city":"La Carrera",
    "sg:orig_category":"Fabricaci\u00d3n, Instalaci\u00d3n De Saunas",
    "sg:phone":"+34 985 74 00 86",
    "sg:postcode":"33186",
    "sg:province":"Asturias",
    "sg:website":"www.toldosbarry.es",
    "wof:name":"Toldos Barry S. L.",
    "wof:placetype":"venue"
},
  "geometry": {"coordinates":[-5.7012858391,43.3833732605],"type":"Point"}
}