{
  "type": "Feature",
  "properties": {
    "iso:country":"ES",
    "sg:address":"Carrer de La Rambla, S/n",
    "sg:city":"Barcelona",
    "sg:orig_category":"Florister\u00cdas",
    "sg:phone":"+34 933 02 10 89",
    "sg:postcode":"08002",
    "sg:province":"Barcelona",
    "wof:name":"Benzal Delgado Herminio",
    "wof:placetype":"venue"
},
  "geometry": {"coordinates":[2.1710760593,41.3842277527],"type":"Point"}
}