{
  "type": "Feature",
  "properties": {
    "addr:full":"Calle de Senija, 1 Denia Alicante 03700",
    "addr:housenumber":"1",
    "addr:postcode":"03700",
    "addr:street":"Calle De Senija",
    "iso:country":"ES",
    "sg:address":"Calle de Senija, 1",
    "sg:city":"Denia",
    "sg:orig_category":"Lencer\u00cda Femenina, Corseter\u00cda, Trajes De Ba\u00d1o (al Por Menor)",
    "sg:phone":"+34 966 42 55 08",
    "sg:postcode":"03700",
    "sg:province":"Alicante",
    "wof:name":"Espruch Pulido Rosario",
    "wof:placetype":"venue"
},
  "geometry": {"coordinates":[0.103978999,38.836971283],"type":"Point"}
}