{
  "type": "Feature",
  "properties": {
    "addr:full":"Calle de Marques De Murrieta, 40 Logro\u00f1o La Rioja 26005",
    "addr:housenumber":"40",
    "addr:postcode":"26005",
    "addr:street":"Calle De Marques De Murrieta;Rioja",
    "iso:country":"ES",
    "sg:address":"Calle de Marques De Murrieta, 40",
    "sg:city":"Logro\u00f1o",
    "sg:orig_category":"Radiocomunicaciones, Telefon\u00cda M\u00d3vil, Radiomensajer\u00cda: Servicios, Comercializaci\u00d3n",
    "sg:phone":"+34 941 21 11 11",
    "sg:postcode":"26005",
    "sg:province":"La Rioja",
    "sg:website":"www.reyca.net",
    "wof:name":"Instalaciones Reyca S.l.",
    "wof:placetype":"venue"
},
  "geometry": {"coordinates":[-2.4562599659,42.4649467468],"type":"Point"}
}