{
  "type": "Feature",
  "properties": {
    "iso:country":"ES",
    "sg:address":"Ctra. Chipiona-sanlucar, Km. 0001,5",
    "sg:city":"Chipiona",
    "sg:orig_category":"Florister\u00cdas",
    "sg:phone":"+34 956 23 50 58",
    "sg:postcode":"11550",
    "sg:province":"C\u00e1diz",
    "sg:website":"www.taliflor.com",
    "wof:name":"Talifrut S.l.",
    "wof:placetype":"venue"
},
  "geometry": {"coordinates":[-6.4288592339,36.7313156128],"type":"Point"}
}