{
  "type": "Feature",
  "properties": {
    "addr:full":"Carrer de Amunt, 2 Vandellos Tarragona 43891",
    "addr:housenumber":"2",
    "addr:postcode":"43891",
    "addr:street":"Carrer De Amunt",
    "iso:country":"ES",
    "sg:address":"Carrer de Amunt, 2",
    "sg:city":"Vandellos",
    "sg:orig_category":"Desinfecci\u00d3n, Desinsectaci\u00d3n, Desratizaci\u00d3n",
    "sg:phone":"+34 977 82 43 73",
    "sg:postcode":"43891",
    "sg:province":"Tarragona",
    "wof:name":"Ambient Servei De Control De Plagues",
    "wof:placetype":"venue"
},
  "geometry": {"coordinates":[0.8311008811,41.0203704834],"type":"Point"}
}