{
  "type": "Feature",
  "properties": {
    "iso:country":"ES",
    "sg:address":"Calle de Ancha, 44",
    "sg:city":"Moron Frontera",
    "sg:orig_category":"Frutas Y Legumbres Frescas (al Por Mayor)",
    "sg:phone":"+34 954 85 00 59",
    "sg:postcode":"41530",
    "sg:province":"Sevilla",
    "wof:name":"Valle Moron S.l.",
    "wof:placetype":"venue"
},
  "geometry": {"coordinates":[-5.4512009621,37.1184692383],"type":"Point"}
}