{
  "type": "Feature",
  "properties": {
    "iso:country":"ES",
    "sg:address":"Avda America, 83",
    "sg:city":"Zaragoza",
    "sg:orig_category":"Frutas, Legumbres Frescas Y Tempranas (al Por Menor)",
    "sg:phone":"+34 976 38 18 53",
    "sg:postcode":"50007",
    "sg:province":"Zaragoza",
    "wof:name":"Isla Varela Gerardo",
    "wof:placetype":"venue"
},
  "geometry": {"coordinates":[-0.88607198,41.6286506653],"type":"Point"}
}