{
  "type": "Feature",
  "properties": {
    "iso:country":"ES",
    "sg:address":"Calle de Manuel Calvo Leal, 10",
    "sg:city":"Dos Hermanas",
    "sg:orig_category":"Comercio De Piezas De Recambio Y De Accesorios De Veh\u00cdculos, Veh\u00cdculos Industriales",
    "sg:phone":"+34 954 72 18 67",
    "sg:postcode":"41700",
    "sg:province":"Sevilla",
    "wof:name":"Leon Santiago Manuel",
    "wof:placetype":"venue"
},
  "geometry": {"coordinates":[-5.9231395721,37.2864646912],"type":"Point"}
}