{
  "type": "Feature",
  "properties": {
    "addr:full":"Carrer de Guillem Galmes, 24 Palma Islas Baleares 07004",
    "addr:housenumber":"24",
    "addr:postcode":"07004",
    "addr:street":"Carrer De Guillem Galmes",
    "iso:country":"ES",
    "sg:address":"Carrer de Guillem Galmes, 24",
    "sg:city":"Palma",
    "sg:orig_category":"Mercer\u00cda, Lencer\u00cda (al Por Menor)",
    "sg:phone":"+34 971 49 84 85",
    "sg:postcode":"07004",
    "sg:province":"Islas Baleares",
    "wof:name":"Planas Ferragut Antonia",
    "wof:placetype":"venue"
},
  "geometry": {"coordinates":[2.6558749676,39.5913391113],"type":"Point"}
}