{
  "type": "Feature",
  "properties": {
    "iso:country":"ES",
    "sg:address":"Calle de Alvaro De Bazan, 10",
    "sg:city":"Valencia",
    "sg:orig_category":"Inform\u00c1tica, Ofim\u00c1tica (estudios, Asesor\u00cda, Ingenier\u00cda, Formaci\u00d3n)",
    "sg:phone":"+34 963 62 90 62",
    "sg:postcode":"46010",
    "sg:province":"Valencia",
    "wof:name":"Qwerty Informatica S.l.",
    "wof:placetype":"venue"
},
  "geometry": {"coordinates":[-0.3628430963,39.4811630249],"type":"Point"}
}