{
  "type": "Feature",
  "properties": {
    "addr:full":"Calle de Navajeda, S/n Sancibrian Cantabria 39110",
    "addr:housenumber":"s / n",
    "addr:postcode":"39110",
    "addr:street":"Calle De Navajeda",
    "iso:country":"ES",
    "sg:address":"Calle de Navajeda, S/n",
    "sg:city":"Sancibrian",
    "sg:orig_category":"Reposter\u00cdas",
    "sg:phone":"+34 942 57 81 52",
    "sg:postcode":"39110",
    "sg:province":"Cantabria",
    "wof:name":"Puente Aja Ricardo",
    "wof:placetype":"venue"
},
  "geometry": {"coordinates":[-3.882860899,43.4630737305],"type":"Point"}
}