{
  "type": "Feature",
  "properties": {
    "addr:full":"Plaz Samuel Picaza, 11 Santa Cruz De Campezo \u00c1lava 01110",
    "addr:housenumber":"11",
    "addr:postcode":"01110",
    "addr:street":"Picaza",
    "iso:country":"ES",
    "sg:address":"Plaz Samuel Picaza, 11",
    "sg:city":"Santa Cruz De Campezo",
    "sg:orig_category":"Supermercados Y Hipermercados",
    "sg:phone":"+34 945 40 54 07",
    "sg:postcode":"01110",
    "sg:province":"\u00c1lava",
    "wof:name":"Eguzkilore S.l",
    "wof:placetype":"venue"
},
  "geometry": {"coordinates":[-2.3504619598,42.6691246033],"type":"Point"}
}