{
  "type": "Feature",
  "properties": {
    "addr:full":"Calle de Erizo, 62 Valdezorras Sevilla 41020",
    "addr:housenumber":"62",
    "addr:postcode":"41020",
    "addr:street":"Calle De Erizo",
    "iso:country":"ES",
    "sg:address":"Calle de Erizo, 62",
    "sg:city":"Valdezorras",
    "sg:orig_category":"Mercer\u00cda, Lencer\u00cda (al Por Menor)",
    "sg:phone":"+34 954 25 04 62",
    "sg:postcode":"41020",
    "sg:province":"Sevilla",
    "wof:name":"Sanchez Jimenez Antonio",
    "wof:placetype":"venue"
},
  "geometry": {"coordinates":[-5.9264888763,37.4280204773],"type":"Point"}
}