{
  "type": "Feature",
  "properties": {
    "iso:country":"ES",
    "sg:address":"Calle de Hermanos Garcia Noblejas, 39",
    "sg:city":"Madrid",
    "sg:orig_category":"Agentes, Concesionarios Y Sucursales De Veh\u00cdculos",
    "sg:phone":"+34 913 67 67 23",
    "sg:postcode":"28037",
    "sg:province":"Madrid",
    "wof:name":"Auto Ferisan S.l.",
    "wof:placetype":"venue"
},
  "geometry": {"coordinates":[-3.6336202621,40.4320373535],"type":"Point"}
}