{
  "type": "Feature",
  "properties": {
    "iso:country":"ES",
    "sg:address":"Vio\u00f1o, 2",
    "sg:city":"Renedo",
    "sg:orig_category":"Cristaler\u00cdas",
    "sg:phone":"+34 942 57 00 37",
    "sg:postcode":"39470",
    "sg:province":"Cantabria",
    "wof:name":"Saint-gobain Cristaleria",
    "wof:placetype":"venue"
},
  "geometry": {"coordinates":[-3.9539539814,43.3548316956],"type":"Point"}
}