{
  "type": "Feature",
  "properties": {
    "iso:country":"ES",
    "sg:address":"Calle de Concha General, 50",
    "sg:city":"Bilbao",
    "sg:orig_category":"Ropa Y Accesorios",
    "sg:phone":"+34 944 21 12 71",
    "sg:postcode":"48012",
    "sg:province":"Vizcaya",
    "wof:name":"Tecnicas El Abra; S.l.",
    "wof:placetype":"venue"
},
  "geometry": {"coordinates":[-2.9365038872,43.2563209534],"type":"Point"}
}