{
  "type": "Feature",
  "properties": {
    "iso:country":"ES",
    "sg:address":"Calle de Doctor Fleming, 84",
    "sg:city":"San Vicente Del Raspeig-sant Vicent Del Raspeig",
    "sg:orig_category":"Cristaler\u00cdas",
    "sg:phone":"+34 965 67 12 02",
    "sg:postcode":"03690",
    "sg:province":"Alicante",
    "wof:name":"Joaquin Salinas Lopez Y Mateo Jose Grimaldos Martinez Cdad",
    "wof:placetype":"venue"
},
  "geometry": {"coordinates":[-0.5241456032,38.4036369324],"type":"Point"}
}