{
  "type": "Feature",
  "properties": {
    "iso:country":"ES",
    "sg:address":"Calle de Jaul, 84",
    "sg:city":"Almeria",
    "sg:orig_category":"Peluquer\u00cdas, Peluquer\u00cda Mixta",
    "sg:phone":"+34 950 15 10 13",
    "sg:postcode":"04007",
    "sg:province":"Almer\u00eda",
    "wof:name":"Rodriguez Lopez Francisca",
    "wof:placetype":"venue"
},
  "geometry": {"coordinates":[-2.4466190338,36.8273391724],"type":"Point"}
}