{
  "type": "Feature",
  "properties": {
    "iso:country":"ES",
    "sg:address":"Avda San Josemaria Escriva, 10",
    "sg:city":"Barbastro",
    "sg:orig_category":"Arquitectos",
    "sg:phone":"+34 974 31 52 74",
    "sg:postcode":"22300",
    "sg:province":"Huesca",
    "wof:name":"Augusto Mora Pueyo S.l.",
    "wof:placetype":"venue"
},
  "geometry": {"coordinates":[0.1307796985,42.0187110901],"type":"Point"}
}