{
  "type": "Feature",
  "properties": {
    "iso:country":"ES",
    "sg:address":"Alam Boulevard Del, 18",
    "sg:city":"Donostia-san Sebastian",
    "sg:orig_category":"Tiendas De Grano, Frutas Y Legumbres Secas (al Por Menor)",
    "sg:phone":"+34 943 42 53 83",
    "sg:postcode":"20003",
    "sg:province":"Guip\u00f9zcoa",
    "wof:name":"Francisco Javier Gaztelua Igarzabal Y Otros Cdad",
    "wof:placetype":"venue"
},
  "geometry": {"coordinates":[-1.9845659733,43.3224029541],"type":"Point"}
}