{
  "type": "Feature",
  "properties": {
    "addr:full":"Calle de Cupido, S/n Puerto Cruz Santa Cruz De Tenerife 38400",
    "addr:housenumber":"s / n",
    "addr:postcode":"38400",
    "addr:street":"Calle De Cupido;Cruz",
    "iso:country":"ES",
    "sg:address":"Calle de Cupido, S/n",
    "sg:city":"Puerto Cruz",
    "sg:orig_category":"Supermercados Y Hipermercados",
    "sg:phone":"+34 922 37 03 67",
    "sg:postcode":"38400",
    "sg:province":"Santa Cruz De Tenerife",
    "sg:website":"www.mercadona.es",
    "wof:name":"Mercadona S.a.",
    "wof:placetype":"venue"
},
  "geometry": {"coordinates":[-16.5516109467,28.4146671295],"type":"Point"}
}