{
  "type": "Feature",
  "properties": {
    "addr:full":"Calle de San Graciano, 1 Madrid Madrid 28026",
    "addr:housenumber":"1",
    "addr:postcode":"28026",
    "addr:street":"Calle De San Graciano",
    "iso:country":"ES",
    "sg:address":"Calle de San Graciano, 1",
    "sg:city":"Madrid",
    "sg:orig_category":"Periodistas Profesionales",
    "sg:phone":"+34 914 76 25 38",
    "sg:postcode":"28026",
    "sg:province":"Madrid",
    "wof:name":"Hernandez Sanchez Maria Josefa",
    "wof:placetype":"venue"
},
  "geometry": {"coordinates":[-3.7027618885,40.3928222656],"type":"Point"}
}