{
  "type": "Feature",
  "properties": {
    "iso:country":"ES",
    "sg:address":"Carrer de Lepant, 12",
    "sg:city":"Reus",
    "sg:orig_category":"Florister\u00cdas",
    "sg:phone":"+34 977 32 27 74",
    "sg:postcode":"43202",
    "sg:province":"Tarragona",
    "wof:name":"Jove Nolla Encarnacion",
    "wof:placetype":"venue"
},
  "geometry": {"coordinates":[1.0978139639,41.1549949646],"type":"Point"}
}