{
  "type": "Feature",
  "properties": {
    "iso:country":"ES",
    "sg:address":"Calle de Luis Piernas, 43",
    "sg:city":"Madrid",
    "sg:orig_category":"Panader\u00cdas, Panader\u00cdas",
    "sg:phone":"+34 913 26 04 75",
    "sg:postcode":"28017",
    "sg:province":"Madrid",
    "wof:name":"Carvajal Moreno Jose",
    "wof:placetype":"venue"
},
  "geometry": {"coordinates":[-3.6530549526,40.4268302917],"type":"Point"}
}