{
  "type": "Feature",
  "properties": {
    "addr:full":"Camino Olivereta, S/n Nules Castell\u00f3n 12520",
    "addr:housenumber":"s / n",
    "addr:postcode":"12520",
    "addr:street":"Camino Olivereta",
    "iso:country":"ES",
    "sg:address":"Camino Olivereta, S/n",
    "sg:city":"Nules",
    "sg:orig_category":"Arboricultura Y Producci\u00d3n De Frutas",
    "sg:phone":"+34 964 67 02 42",
    "sg:postcode":"12520",
    "sg:province":"Castell\u00f3n",
    "wof:name":"Miguel Garcia E Hijos S. A.",
    "wof:placetype":"venue"
},
  "geometry": {"coordinates":[-0.1542440057,39.852596283],"type":"Point"}
}