{
  "type": "Feature",
  "properties": {
    "iso:country":"ES",
    "sg:address":"Calle de Virgen Desamparados, S/n",
    "sg:city":"Benisano",
    "sg:orig_category":"Paneles De Madera: Contrachapados, Fibras, Particulados, Estratificados (fabricaci\u00d3n, Venta)",
    "sg:phone":"+34 962 79 30 16",
    "sg:postcode":"46181",
    "sg:province":"Valencia",
    "wof:name":"Jose Gonzalez Rodriguez S.l.",
    "wof:placetype":"venue"
},
  "geometry": {"coordinates":[-0.5728290081,39.6141548157],"type":"Point"}
}