{
  "type": "Feature",
  "properties": {
    "addr:full":"Calle de San Pedro, 12 Mucientes Valladolid 47194",
    "addr:housenumber":"12",
    "addr:postcode":"47194",
    "addr:street":"Calle De San Pedro",
    "iso:country":"ES",
    "sg:address":"Calle de San Pedro, 12",
    "sg:city":"Mucientes",
    "sg:orig_category":"Productores Recolectores, Venta Directa De Vinos",
    "sg:phone":"+34 983 58 77 89",
    "sg:postcode":"47194",
    "sg:province":"Valladolid",
    "wof:name":"Vaquero Centeno Sinforiano",
    "wof:placetype":"venue"
},
  "geometry": {"coordinates":[-4.7599492073,41.7439117432],"type":"Point"}
}