{
  "type": "Feature",
  "properties": {
    "iso:country":"ES",
    "sg:address":"Plaz Tenerias, 5",
    "sg:city":"Valladolid",
    "sg:orig_category":"Centros De Coordinaci\u00d3n",
    "sg:phone":"+34 983 38 06 30",
    "sg:postcode":"47006",
    "sg:province":"Valladolid",
    "wof:name":"Valderrama Andres Maria Jesus",
    "wof:placetype":"venue"
},
  "geometry": {"coordinates":[-4.7333440781,41.6476783752],"type":"Point"}
}