{
  "type": "Feature",
  "properties": {
    "iso:country":"ES",
    "sg:address":"Calle de Marques De Cabra, 16",
    "sg:city":"Cabra",
    "sg:orig_category":"Abogados",
    "sg:phone":"+34 957 52 06 07",
    "sg:postcode":"14940",
    "sg:province":"C\u00f3rdoba",
    "wof:name":"Fernandez Ortega Arturo",
    "wof:placetype":"venue"
},
  "geometry": {"coordinates":[-4.4410481453,37.4708824158],"type":"Point"}
}