{
  "type": "Feature",
  "properties": {
    "iso:country":"ES",
    "sg:address":"Avda Carlos Vii, 3",
    "sg:city":"Portugalete",
    "sg:orig_category":"Abogados",
    "sg:phone":"+34 944 95 08 49",
    "sg:postcode":"48920",
    "sg:province":"Vizcaya",
    "wof:name":"Soriano Bello Fernando",
    "wof:placetype":"venue"
},
  "geometry": {"coordinates":[-3.0206179619,43.3199005127],"type":"Point"}
}