{
  "type": "Feature",
  "properties": {
    "iso:country":"ES",
    "sg:address":"Plaz De La Torre, 3",
    "sg:city":"Logrosan",
    "sg:orig_category":"Supermercados Y Hipermercados",
    "sg:phone":"+34 927 36 02 89",
    "sg:postcode":"10120",
    "sg:province":"C\u00e1ceres",
    "wof:name":"Triguero Pedrero Alfonso",
    "wof:placetype":"venue"
},
  "geometry": {"coordinates":[-5.4923138618,39.336769104],"type":"Point"}
}