{
  "type": "Feature",
  "properties": {
    "iso:country":"ES",
    "sg:address":"Carr Joan Baptista Ensenyat, 7",
    "sg:city":"Soller",
    "sg:orig_category":"Peluqueros: De Se\u00d1oras",
    "sg:phone":"+34 971 63 41 71",
    "sg:postcode":"07100",
    "sg:province":"Islas Baleares",
    "wof:name":"Trias Guillem Lucia Del Carmen",
    "wof:placetype":"venue"
},
  "geometry": {"coordinates":[2.7159569263,39.7658882141],"type":"Point"}
}