{
  "type": "Feature",
  "properties": {
    "iso:country":"ES",
    "sg:address":"Avda Pitagoras, 72",
    "sg:city":"Merida",
    "sg:orig_category":"Agencias Y Agentes Comerciales, Representantes",
    "sg:phone":"+34 924 31 10 59",
    "sg:postcode":"06800",
    "sg:province":"Badajoz",
    "wof:name":"Ceballo Ruz Fernando",
    "wof:placetype":"venue"
},
  "geometry": {"coordinates":[-6.3431649208,38.928478241],"type":"Point"}
}