{
  "type": "Feature",
  "properties": {
    "addr:full":"Carr Caminas Dels Homens, 17 Cullera Valencia 46400",
    "addr:housenumber":"17",
    "addr:postcode":"46400",
    "addr:street":"Carr Caminas Dels Homens",
    "iso:country":"ES",
    "sg:address":"Carr Caminas Dels Homens, 17",
    "sg:city":"Cullera",
    "sg:orig_category":"Confecci\u00d3n De Trajes De Ba\u00d1o Y De Ropa De Playa",
    "sg:phone":"+34 961 72 51 74",
    "sg:postcode":"46400",
    "sg:province":"Valencia",
    "wof:name":"Avellaneda Orts Santiago",
    "wof:placetype":"venue"
},
  "geometry": {"coordinates":[-0.2562240064,39.1653251648],"type":"Point"}
}