{
  "type": "Feature",
  "properties": {
    "iso:country":"ES",
    "sg:address":"Calle de Manuel Iradier, 8",
    "sg:city":"Vitoria-gasteiz",
    "sg:orig_category":"Cervecer\u00cdas",
    "sg:phone":"+34 945 14 83 38",
    "sg:postcode":"01005",
    "sg:province":"\u00c1lava",
    "wof:name":"Eguia Martin Juan Ignacio",
    "wof:placetype":"venue"
},
  "geometry": {"coordinates":[-2.6741509438,42.8422927856],"type":"Point"}
}