{
  "type": "Feature",
  "properties": {
    "addr:full":"Carr Mestre Josep Maria Andreu, 19 Sant Joan De Les Abadesses Girona 17860",
    "addr:housenumber":"19",
    "addr:postcode":"17860",
    "addr:street":"Carr Mestre Josep Maria Andreu",
    "iso:country":"ES",
    "sg:address":"Carr Mestre Josep Maria Andreu, 19",
    "sg:city":"Sant Joan De Les Abadesses",
    "sg:classifiers":[
        {
            "category":"Building & Trades",
            "subcategory":"Construction",
            "type":"Services"
        }
    ],
    "sg:phone":"+34 972 72 01 59",
    "sg:postcode":"17860",
    "sg:province":"Girona",
    "sg:tags":[
        "calefacci\u00d3n",
        "central",
        "para",
        "de",
        "fabricaci\u00d3n",
        "caldera"
    ],
    "wof:name":"Santel Llauners S.l.",
    "wof:placetype":"venue"
},
  "geometry": {"coordinates":[2.2882740498,42.2341079712],"type":"Point"}
}