{
  "type": "Feature",
  "properties": {
    "addr:full":"Calle de San Jose, 5 Novelda Alicante 03660",
    "addr:housenumber":"5",
    "addr:postcode":"03660",
    "addr:street":"Calle De San Jose",
    "iso:country":"ES",
    "sg:address":"Calle de San Jose, 5",
    "sg:city":"Novelda",
    "sg:orig_category":"Alimentaci\u00d3n Animal (fabricaci\u00d3n, Al Por Mayor)",
    "sg:phone":"+34 965 60 70 01",
    "sg:postcode":"03660",
    "sg:province":"Alicante",
    "wof:name":"Soria Gonzalez De Chaves Mercedes",
    "wof:placetype":"venue"
},
  "geometry": {"coordinates":[-0.7666323781,38.3852996826],"type":"Point"}
}