{
  "type": "Feature",
  "properties": {
    "iso:country":"ES",
    "sg:address":"Calle de Acetres, 1",
    "sg:city":"Sevilla",
    "sg:orig_category":"Art\u00cdculos De Regalo (al Por Menor)",
    "sg:phone":"+34 954 56 22 78",
    "sg:postcode":"41004",
    "sg:province":"Sevilla",
    "wof:name":"Husain Alsuady Husain Salman",
    "wof:placetype":"venue"
},
  "geometry": {"coordinates":[-5.993165493,37.3913726807],"type":"Point"}
}