{
  "type": "Feature",
  "properties": {
    "iso:country":"ES",
    "sg:address":"Calle de Cervantes, 1",
    "sg:city":"San Pablo De Los Montes",
    "sg:orig_category":"Empresas De Carpinter\u00cda Met\u00c1lica",
    "sg:phone":"+34 925 41 61 98",
    "sg:postcode":"45120",
    "sg:province":"Toledo",
    "wof:name":"Hermanos Castellano Martin C.b",
    "wof:placetype":"venue"
},
  "geometry": {"coordinates":[-4.3289427757,39.5407218933],"type":"Point"}
}