{
  "type": "Feature",
  "properties": {
    "iso:country":"ES",
    "sg:address":"Calle de Andra Mari, 9",
    "sg:city":"Abadi\u00f1o",
    "sg:orig_category":"Alimentaci\u00d3n General (al Por Menor)",
    "sg:phone":"+34 946 81 82 70",
    "sg:postcode":"48220",
    "sg:province":"Vizcaya",
    "wof:name":"Pilar Alzaga-miren Garitaonandia, C.b.",
    "wof:placetype":"venue"
},
  "geometry": {"coordinates":[-2.605840683,43.1458129883],"type":"Point"}
}