{
  "type": "Feature",
  "properties": {
    "iso:country":"ES",
    "sg:address":"Calle de Fruela, 12",
    "sg:city":"Oviedo",
    "sg:orig_category":"Inmobiliaria (agencias)",
    "sg:phone":"+34 985 20 56 19",
    "sg:postcode":"33007",
    "sg:province":"Asturias",
    "wof:name":"Inmobiliaria Nogales Y Del Porma S.l.",
    "wof:placetype":"venue"
},
  "geometry": {"coordinates":[-5.8467707634,43.3612670898],"type":"Point"}
}