{
  "type": "Feature",
  "properties": {
    "iso:country":"ES",
    "sg:address":"Rebordelo, S/n",
    "sg:city":"Insua",
    "sg:orig_category":"Paneles De Madera: Contrachapados, Fibras, Particulados, Estratificados (fabricaci\u00d3n, Venta)",
    "sg:phone":"+34 986 75 01 50",
    "sg:postcode":"36826",
    "sg:province":"Pontevedra",
    "wof:name":"Eucalipto De Pontevedra S.a.",
    "wof:placetype":"venue"
},
  "geometry": {"coordinates":[-8.5317935944,42.3636207581],"type":"Point"}
}