{
  "type": "Feature",
  "properties": {
    "addr:full":"Carrer de Santalo, 75 Barcelona Barcelona 08021",
    "addr:housenumber":"75",
    "addr:postcode":"08021",
    "addr:street":"Carrer De Santalo",
    "iso:country":"ES",
    "sg:address":"Carrer de Santalo, 75",
    "sg:city":"Barcelona",
    "sg:orig_category":"Alquiler De V\u00cddeo",
    "sg:phone":"+34 932 00 09 92",
    "sg:postcode":"08021",
    "sg:province":"Barcelona",
    "wof:name":"2 B Fantastic S.l.",
    "wof:placetype":"venue"
},
  "geometry": {"coordinates":[2.143553,41.397411],"type":"Point"}
}