{
  "type": "Feature",
  "properties": {
    "addr:full":"Durana Kalea, 4 Aretxabaleta Guip\u00f9zcoa 20550",
    "addr:housenumber":"4",
    "addr:postcode":"20550",
    "addr:street":"Durana Kalea;Guipu\u0300Zcoa",
    "iso:country":"ES",
    "sg:address":"Durana Kalea, 4",
    "sg:city":"Aretxabaleta",
    "sg:orig_category":"Carnicer\u00cdas, Carnicer\u00cdas",
    "sg:phone":"+34 943 79 16 61",
    "sg:postcode":"20550",
    "sg:province":"Guip\u00f9zcoa",
    "wof:name":"Etxabe Arana , Angel",
    "wof:placetype":"venue"
},
  "geometry": {"coordinates":[-2.5041909218,43.0358314514],"type":"Point"}
}