{
  "type": "Feature",
  "properties": {
    "iso:country":"ES",
    "sg:address":"Calle de Manzanares, 26",
    "sg:city":"Madrid",
    "sg:orig_category":"Alimentaci\u00d3n General (al Por Menor)",
    "sg:phone":"+34 913 65 49 02",
    "sg:postcode":"28005",
    "sg:province":"Madrid",
    "wof:name":"Chen  Chang Cui",
    "wof:placetype":"venue"
},
  "geometry": {"coordinates":[-3.7210009098,40.412815094],"type":"Point"}
}