{
  "type": "Feature",
  "properties": {
    "iso:country":"ES",
    "sg:address":"Calle de Via Galindo, 7",
    "sg:city":"Sestao",
    "sg:orig_category":"Farmacias",
    "sg:phone":"+34 944 96 04 08",
    "sg:postcode":"48910",
    "sg:province":"Vizcaya",
    "wof:name":"Eguskiza Urrestarazu Gabino",
    "wof:placetype":"venue"
},
  "geometry": {"coordinates":[-3.0080668926,43.3085021973],"type":"Point"}
}