{
  "type": "Feature",
  "properties": {
    "iso:country":"ES",
    "sg:address":"Calle de Guadalete, S/n",
    "sg:city":"Marbella",
    "sg:orig_category":"Molduras, Junquillos, Listones Y Molduras Perforadas",
    "sg:phone":"+34 952 86 75 29",
    "sg:postcode":"29600",
    "sg:province":"M\u00e1laga",
    "wof:name":"Moron Lopez Jose Manuel",
    "wof:placetype":"venue"
},
  "geometry": {"coordinates":[-4.8755970001,36.5085296631],"type":"Point"}
}