{
  "type": "Feature",
  "properties": {
    "iso:country":"ES",
    "sg:address":"Ctra. Caceres, Km. 0016,0",
    "sg:city":"Alburquerque",
    "sg:orig_category":"Producci\u00d3n, Venta De Productos De Agricultura Biol\u00d3gica",
    "sg:phone":"+34 924 14 10 52",
    "sg:postcode":"06510",
    "sg:province":"Badajoz",
    "wof:name":"Agropecuaria Ca\u00f1as Y Labrados S. A.",
    "wof:placetype":"venue"
},
  "geometry": {"coordinates":[-6.963862,39.23703],"type":"Point"}
}