{
  "type": "Feature",
  "properties": {
    "iso:country":"ES",
    "sg:address":"Ctra Benahavis, Km. 0001,5",
    "sg:city":"Nueva Atalaya",
    "sg:classifiers":[
        {
            "category":"Sports & Exercise",
            "subcategory":"Golf",
            "type":"Entertainment"
        }
    ],
    "sg:phone":"+34 952 92 88 61",
    "sg:postcode":"29680",
    "sg:province":"M\u00e1laga",
    "sg:tags":[
        "y",
        "de",
        "campos",
        "clases"
    ],
    "wof:name":"Comunidad De Propietarios La Cartuja Del Golf",
    "wof:placetype":"venue"
},
  "geometry": {"coordinates":[-5.1452140808,36.4275817871],"type":"Point"}
}