{
  "type": "Feature",
  "properties": {
    "addr:full":"Calle de Pedro Jose De Mendizabal, 11 Santa Cruz De Tenerife Santa Cruz De Tenerife 38009",
    "addr:housenumber":"11",
    "addr:postcode":"38009",
    "addr:street":"Calle De Pedro Jose De Mendizabal",
    "iso:country":"ES",
    "sg:address":"Calle de Pedro Jose De Mendizabal, 11",
    "sg:city":"Santa Cruz De Tenerife",
    "sg:orig_category":"Institutos De Belleza",
    "sg:phone":"+34 922 23 72 25",
    "sg:postcode":"38009",
    "sg:province":"Santa Cruz De Tenerife",
    "wof:name":"Cabrera Garcia Maria Fatima",
    "wof:placetype":"venue"
},
  "geometry": {"coordinates":[-16.2769412994,28.4586277008],"type":"Point"}
}