{
  "type": "Feature",
  "properties": {
    "addr:full":"Calle de Pango, 35 Costa Oeste C\u00e1diz 11500",
    "addr:housenumber":"35",
    "addr:postcode":"11500",
    "addr:street":"Calle De Pango;Costa Oeste Ca\u0301Diz",
    "iso:country":"ES",
    "sg:address":"Calle de Pango, 35",
    "sg:city":"Costa Oeste",
    "sg:orig_category":"Material Y Herramientas Agr\u00cdcolas",
    "sg:phone":"+34 956 85 19 53",
    "sg:postcode":"11500",
    "sg:province":"C\u00e1diz",
    "wof:name":"Tractores Recambios Y Suministros Agricolas S.l.",
    "wof:placetype":"venue"
},
  "geometry": {"coordinates":[-6.2197542191,36.6056632996],"type":"Point"}
}