{
  "type": "Feature",
  "properties": {
    "iso:country":"ES",
    "sg:address":"Calle de Celindas, 14",
    "sg:city":"Madrid",
    "sg:orig_category":"Grafistas",
    "sg:phone":"+34 915 10 21 43",
    "sg:postcode":"28016",
    "sg:province":"Madrid",
    "wof:name":"Compa\u00f1ia Grafica Moragraf S.l.",
    "wof:placetype":"venue"
},
  "geometry": {"coordinates":[-3.665774107,40.4538612366],"type":"Point"}
}