{
  "type": "Feature",
  "properties": {
    "iso:country":"ES",
    "sg:address":"Barr Caserio Larrazabal, 2",
    "sg:city":"Bilbao",
    "sg:orig_category":"Tapicer\u00cdas",
    "sg:phone":"+34 944 03 47 08",
    "sg:postcode":"48007",
    "sg:province":"Vizcaya",
    "wof:name":"Tapiceria Elordui",
    "wof:placetype":"venue"
},
  "geometry": {"coordinates":[-2.9157528877,43.2645111084],"type":"Point"}
}