{
  "type": "Feature",
  "properties": {
    "addr:full":"Ctra. Madrid-leon, Km. 0242,2 Berrueces Valladolid 47813",
    "addr:postcode":"47813",
    "addr:street":"Ctra. Madrid-Leon Km. 0242,2",
    "iso:country":"ES",
    "sg:address":"Ctra. Madrid-leon, Km. 0242,2",
    "sg:city":"Berrueces",
    "sg:orig_category":"Distribuci\u00d3n De Petr\u00d3leo Y Derivados",
    "sg:phone":"+34 983 70 01 27",
    "sg:postcode":"47813",
    "sg:province":"Valladolid",
    "wof:name":"Caramanzana Rey Victor Angel",
    "wof:placetype":"venue"
},
  "geometry": {"coordinates":[-5.0111289024,41.9280586243],"type":"Point"}
}