{
  "type": "Feature",
  "properties": {
    "iso:country":"ES",
    "sg:address":"Pl Olimpia, 14",
    "sg:city":"Sabadell",
    "sg:orig_category":"Asesor\u00cda Fiscal Y Jur\u00cddica",
    "sg:phone":"+34 937 23 67 57",
    "sg:postcode":"08206",
    "sg:province":"Barcelona",
    "wof:name":"Rivera Rodriguez Mercedes",
    "wof:placetype":"venue"
},
  "geometry": {"coordinates":[2.0908288956,41.5549430847],"type":"Point"}
}