{
  "type": "Feature",
  "properties": {
    "addr:full":"Avda Juan Carlos I, 7 Alcala Henares Madrid 28806",
    "addr:housenumber":"7",
    "addr:postcode":"28806",
    "addr:street":"Avda Juan Carlos I",
    "iso:country":"ES",
    "sg:address":"Avda Juan Carlos I, 7",
    "sg:city":"Alcala Henares",
    "sg:orig_category":"Arquitectos",
    "sg:phone":"+34 918 30 00 91",
    "sg:postcode":"28806",
    "sg:province":"Madrid",
    "wof:name":"Carmona Casado Juan Carlos",
    "wof:placetype":"venue"
},
  "geometry": {"coordinates":[-3.4000039101,40.4808654785],"type":"Point"}
}