{
  "type": "Feature",
  "properties": {
    "iso:country":"ES",
    "sg:address":"Calle de Valencia, 5",
    "sg:city":"Montalbo",
    "sg:orig_category":"Iglesia Cat\u00d3lica",
    "sg:phone":"+34 969 13 02 16",
    "sg:postcode":"16440",
    "sg:province":"Cuenca",
    "wof:name":"Parroquia Santo Domingo De Silos",
    "wof:placetype":"venue"
},
  "geometry": {"coordinates":[-2.6686770916,39.8778572083],"type":"Point"}
}