{
  "type": "Feature",
  "properties": {
    "iso:country":"ES",
    "sg:address":"Calle de Velarde, 19",
    "sg:city":"Albacete",
    "sg:orig_category":"Asociaciones Humanitarias, De Cooperaci\u00d3n, De Acci\u00d3n Social",
    "sg:phone":"+34 967 23 69 99",
    "sg:postcode":"02004",
    "sg:province":"Albacete",
    "wof:name":"Asociacion Espa\u00d1ola De Esclerosis Multiple",
    "wof:placetype":"venue"
},
  "geometry": {"coordinates":[-1.8679984808,38.9954681396],"type":"Point"}
}