{
  "type": "Feature",
  "properties": {
    "addr:full":"Avda Lope De Figueroa, 35 Alcala Henares Madrid 28804",
    "addr:housenumber":"35",
    "addr:postcode":"28804",
    "addr:street":"Avda Lope De Figueroa",
    "iso:country":"ES",
    "sg:address":"Avda Lope De Figueroa, 35",
    "sg:city":"Alcala Henares",
    "sg:orig_category":"M\u00c9dicos: Estomatolog\u00cda",
    "sg:phone":"+34 918 82 12 04",
    "sg:postcode":"28804",
    "sg:province":"Madrid",
    "wof:name":"Cumplido Sanchez Azucena",
    "wof:placetype":"venue"
},
  "geometry": {"coordinates":[-3.3508369923,40.4867858887],"type":"Point"}
}