{
  "type": "Feature",
  "properties": {
    "iso:country":"ES",
    "sg:address":"Calle de Lanceria, 9",
    "sg:city":"Jerez De La Frontera",
    "sg:orig_category":"Ropa Para Ni\u00d1os (al Por Menor)",
    "sg:phone":"+34 956 16 84 92",
    "sg:postcode":"11402",
    "sg:province":"C\u00e1diz",
    "sg:website":"www.bershka.com",
    "wof:name":"Bershka Bsr Espa\u00f1a S.a.",
    "wof:placetype":"venue"
},
  "geometry": {"coordinates":[-6.1372041702,36.6820793152],"type":"Point"}
}