{
  "type": "Feature",
  "properties": {
    "addr:full":"Ptge Gaspar De Portola, S/n Balaguer Lleida 25600",
    "addr:housenumber":"s / n",
    "addr:postcode":"25600",
    "addr:street":"Ptge Gaspar De Portola",
    "iso:country":"ES",
    "sg:address":"Ptge Gaspar De Portola, S/n",
    "sg:city":"Balaguer",
    "sg:orig_category":"Producci\u00d3n, Distribuci\u00d3n De Gas Butano Y Propano",
    "sg:phone":"+34 973 44 52 35",
    "sg:postcode":"25600",
    "sg:province":"Lleida",
    "wof:name":"Gine Tribo Carmen",
    "wof:placetype":"venue"
},
  "geometry": {"coordinates":[0.8061349988,41.7897453308],"type":"Point"}
}