{
  "type": "Feature",
  "properties": {
    "addr:full":"Av Catalunya, 48 Tarragona Tarragona 43002",
    "addr:housenumber":"48",
    "addr:postcode":"43002",
    "addr:street":"Av Catalunya",
    "iso:country":"ES",
    "sg:address":"Av Catalunya, 48",
    "sg:city":"Tarragona",
    "sg:orig_category":"Inform\u00c1tica: Mantenimiento Y Reparaci\u00d3n De Ordenadores",
    "sg:phone":"+34 977 22 08 15",
    "sg:postcode":"43002",
    "sg:province":"Tarragona",
    "wof:name":"Getronics Espa\u00f1a Solutions S.r.l.",
    "wof:placetype":"venue"
},
  "geometry": {"coordinates":[1.2473380566,41.1230049133],"type":"Point"}
}