{
  "type": "Feature",
  "properties": {
    "addr:full":"Carrer de Pol Arazuri-orcoyen, 9 Orkoien Navarra 31160",
    "addr:housenumber":"9",
    "addr:postcode":"31160",
    "addr:street":"Carrer De Pol Arazuri-Orcoyen",
    "iso:country":"ES",
    "sg:address":"Carrer de Pol Arazuri-orcoyen, 9",
    "sg:city":"Orkoien",
    "sg:orig_category":"Montaje (empresas De)",
    "sg:phone":"+34 948 32 47 00",
    "sg:postcode":"31160",
    "sg:province":"Navarra",
    "wof:name":"Nasermo S.l.",
    "wof:placetype":"venue"
},
  "geometry": {"coordinates":[-1.7060990334,42.8219032288],"type":"Point"}
}