{
  "type": "Feature",
  "properties": {
    "addr:full":"Carrer de Hedilla, 39 Barcelona Barcelona 08031",
    "addr:housenumber":"39",
    "addr:postcode":"08031",
    "addr:street":"Carrer De Hedilla",
    "iso:country":"ES",
    "sg:address":"Carrer de Hedilla, 39",
    "sg:city":"Barcelona",
    "sg:orig_category":"Agencias Y Agentes Comerciales, Representantes",
    "sg:phone":"+34 934 27 73 45",
    "sg:postcode":"08031",
    "sg:province":"Barcelona",
    "wof:name":"Rossa Cabrera Ernesto",
    "wof:placetype":"venue"
},
  "geometry": {"coordinates":[2.1618061066,41.4354324341],"type":"Point"}
}