{
  "type": "Feature",
  "properties": {
    "addr:full":"Plaz Mercado, 12 Valencia Valencia 46001",
    "addr:housenumber":"12",
    "addr:postcode":"46001",
    "addr:street":"Valencia",
    "iso:country":"ES",
    "sg:address":"Plaz Mercado, 12",
    "sg:city":"Valencia",
    "sg:orig_category":"Perfumer\u00cda (al Por Menor)",
    "sg:phone":"+34 963 91 07 37",
    "sg:postcode":"46001",
    "sg:province":"Valencia",
    "wof:name":"Perfumeria Lover",
    "wof:placetype":"venue"
},
  "geometry": {"coordinates":[-0.3794040084,39.47473526],"type":"Point"}
}