{
  "type": "Feature",
  "properties": {
    "iso:country":"ES",
    "sg:address":"Calle de Quemada, 6",
    "sg:city":"Fuengirola",
    "sg:orig_category":"Tintes (fabricaci\u00d3n, Al Por Mayor)",
    "sg:phone":"+34 952 58 12 82",
    "sg:postcode":"29640",
    "sg:province":"M\u00e1laga",
    "wof:name":"Charlton  Christopher",
    "wof:placetype":"venue"
},
  "geometry": {"coordinates":[-4.6241607666,36.5354537964],"type":"Point"}
}