{
  "type": "Feature",
  "properties": {
    "addr:full":"Calle de Navarro Ledesma, 6 Toledo Toledo 45002",
    "addr:housenumber":"6",
    "addr:postcode":"45002",
    "addr:street":"Calle De Navarro Ledesma",
    "iso:country":"ES",
    "sg:address":"Calle de Navarro Ledesma, 6",
    "sg:city":"Toledo",
    "sg:orig_category":"Papeler\u00cdas: Art\u00cdculos (al Por Mayor)",
    "sg:phone":"+34 925 21 22 30",
    "sg:postcode":"45002",
    "sg:province":"Toledo",
    "sg:website":"www.paginasamarillas.es",
    "wof:name":"Libro Papel Toledo S.l.",
    "wof:placetype":"venue"
},
  "geometry": {"coordinates":[-4.0257058144,39.8588905334],"type":"Point"}
}