{
  "type": "Feature",
  "properties": {
    "iso:country":"ES",
    "sg:address":"Calle de Martires, 5",
    "sg:city":"Torrecilla De Alca\u00e7iz",
    "sg:orig_category":"Ense\u00d1anza, Formaci\u00d3n Profesional: Aprendizaje",
    "sg:phone":"+34 978 85 21 90",
    "sg:postcode":"44640",
    "sg:province":"Teruel",
    "wof:name":"Instituto Aragones De Servicios Sociales",
    "wof:placetype":"venue"
},
  "geometry": {"coordinates":[-0.0895090029,40.9626846313],"type":"Point"}
}