{
  "type": "Feature",
  "properties": {
    "iso:country":"ES",
    "sg:address":"Calle de Joaquin Pano, 14",
    "sg:city":"Monzon",
    "sg:orig_category":"Quincaller\u00cda (al Por Menor)",
    "sg:phone":"+34 974 40 11 39",
    "sg:postcode":"22400",
    "sg:province":"Huesca",
    "wof:name":"Torres Cavero Jose Antonio",
    "wof:placetype":"venue"
},
  "geometry": {"coordinates":[0.1929640025,41.9118385315],"type":"Point"}
}