{
  "type": "Feature",
  "properties": {
    "addr:full":"Calle de Oslo, 8 Toledo Toledo 45005",
    "addr:housenumber":"8",
    "addr:postcode":"45005",
    "addr:street":"Calle De Oslo",
    "iso:country":"ES",
    "sg:address":"Calle de Oslo, 8",
    "sg:city":"Toledo",
    "sg:orig_category":"Peluqueros: De Se\u00d1oras",
    "sg:phone":"+34 925 21 48 04",
    "sg:postcode":"45005",
    "sg:province":"Toledo",
    "wof:name":"Tiramar S.l.",
    "wof:placetype":"venue"
},
  "geometry": {"coordinates":[-4.027326107,39.8724441528],"type":"Point"}
}