{
  "type": "Feature",
  "properties": {
    "iso:country":"ES",
    "sg:address":"Avda Agirre Lehendakaria, 19",
    "sg:city":"Urbi",
    "sg:orig_category":"Inmobiliaria (agencias)",
    "sg:phone":"+34 944 26 00 00",
    "sg:postcode":"48970",
    "sg:province":"Vizcaya",
    "wof:name":"Altozano Lu\u00f1o Mikel",
    "wof:placetype":"venue"
},
  "geometry": {"coordinates":[-2.8827011585,43.2364501953],"type":"Point"}
}