{
  "type": "Feature",
  "properties": {
    "addr:full":"Calle de San Gregorio, 2 Villanueva Cordoba C\u00f3rdoba 14440",
    "addr:housenumber":"2;cordoba co\u0301rdoba",
    "addr:postcode":"14440",
    "addr:street":"Calle De San Gregorio",
    "iso:country":"ES",
    "sg:address":"Calle de San Gregorio, 2",
    "sg:city":"Villanueva Cordoba",
    "sg:orig_category":"Supermercados Y Hipermercados",
    "sg:phone":"+34 957 12 20 95",
    "sg:postcode":"14440",
    "sg:province":"C\u00f3rdoba",
    "wof:name":"Galerias De Alimentacion De Pozoblanco S.a.",
    "wof:placetype":"venue"
},
  "geometry": {"coordinates":[-4.6253380775,38.3225631714],"type":"Point"}
}