{
  "type": "Feature",
  "properties": {
    "addr:full":"Carr Carrerada, 18 Esterri D'aneu Lleida 25580",
    "addr:housenumber":"18",
    "addr:postcode":"25580",
    "addr:street":"Carr Carrerada",
    "iso:country":"ES",
    "sg:address":"Carr Carrerada, 18",
    "sg:city":"Esterri D'aneu",
    "sg:orig_category":"Promotores Constructores",
    "sg:phone":"+34 973 62 63 78",
    "sg:postcode":"25580",
    "sg:province":"Lleida",
    "wof:name":"Salvador Suriol Construccions S.l.",
    "wof:placetype":"venue"
},
  "geometry": {"coordinates":[0.6065710187,41.625919342],"type":"Point"}
}