{
  "type": "Feature",
  "properties": {
    "iso:country":"ES",
    "sg:address":"Pol Ind Albarregas, S/n",
    "sg:city":"Merida",
    "sg:orig_category":"Reparaci\u00d3n De Aparatos A Gas",
    "sg:phone":"+34 924 33 06 61",
    "sg:postcode":"06800",
    "sg:province":"Badajoz",
    "wof:name":"Emesur Industrial Y Comercial S.l.",
    "wof:placetype":"venue"
},
  "geometry": {"coordinates":[-6.3402590752,38.9225997925],"type":"Point"}
}