{
  "type": "Feature",
  "properties": {
    "addr:full":"Carrer de Tossa De Mar, 2 Prat Llobregat Barcelona 08820",
    "addr:housenumber":"2",
    "addr:postcode":"08820",
    "addr:street":"Carrer De Tossa De Mar;Llobregat",
    "iso:country":"ES",
    "sg:address":"Carrer de Tossa De Mar, 2",
    "sg:city":"Prat Llobregat",
    "sg:orig_category":"Electricidad: Instaladores",
    "sg:phone":"+34 934 78 30 96",
    "sg:postcode":"08820",
    "sg:province":"Barcelona",
    "wof:name":"Electro M-2 S.a.",
    "wof:placetype":"venue"
},
  "geometry": {"coordinates":[2.0864720345,41.3289909363],"type":"Point"}
}