{
  "type": "Feature",
  "properties": {
    "iso:country":"ES",
    "sg:address":"Psaj Platero Heredia, 6",
    "sg:city":"Cordoba",
    "sg:orig_category":"M\u00c9dicos: Cirug\u00cda Ortop\u00c9dica Y Traumatolog\u00cda",
    "sg:phone":"+34 957 27 74 21",
    "sg:postcode":"14012",
    "sg:province":"C\u00f3rdoba",
    "wof:name":"Burgos Garcia Francisco",
    "wof:placetype":"venue"
},
  "geometry": {"coordinates":[-4.796672821,37.915222168],"type":"Point"}
}