{
  "type": "Feature",
  "properties": {
    "addr:full":"Calle de Carrera, 26 Santa Maria Del Campo Rus Cuenca 16621",
    "addr:postcode":"16621",
    "addr:street":"Calle De Carrera 26",
    "iso:country":"ES",
    "sg:address":"Calle de Carrera, 26",
    "sg:city":"Santa Maria Del Campo Rus",
    "sg:orig_category":"Obras Y Organismos Sociales",
    "sg:phone":"+34 967 18 62 88",
    "sg:postcode":"16621",
    "sg:province":"Cuenca",
    "wof:name":"Edad Dorada Castilla-la Mancha",
    "wof:placetype":"venue"
},
  "geometry": {"coordinates":[-2.4232525826,39.5607261658],"type":"Point"}
}