{
  "type": "Feature",
  "properties": {
    "iso:country":"ES",
    "sg:address":"Avda Candevania, 35",
    "sg:city":"Zuera",
    "sg:orig_category":"Caf\u00c9s, Bares, Cervecer\u00cdas",
    "sg:phone":"+34 976 68 10 67",
    "sg:postcode":"50800",
    "sg:province":"Zaragoza",
    "wof:name":"Perez Barrau S.l.",
    "wof:placetype":"venue"
},
  "geometry": {"coordinates":[-0.7897920012,41.8676071167],"type":"Point"}
}