{
  "type": "Feature",
  "properties": {
    "addr:full":"Carrer de Major, 62 Arbo\u00e7 Tarragona 43720",
    "addr:housenumber":"62",
    "addr:postcode":"43720",
    "addr:street":"Carrer De Major",
    "iso:country":"ES",
    "sg:address":"Carrer de Major, 62",
    "sg:city":"Arbo\u00e7",
    "sg:orig_category":"Supermercados Y Hipermercados",
    "sg:phone":"+34 977 67 08 18",
    "sg:postcode":"43720",
    "sg:province":"Tarragona",
    "wof:name":"Subama S.l.",
    "wof:placetype":"venue"
},
  "geometry": {"coordinates":[1.6022759676,41.2672195435],"type":"Point"}
}