{
  "type": "Feature",
  "properties": {
    "iso:country":"ES",
    "sg:address":"Carrer de Mossen Sol, 17",
    "sg:city":"Aldea",
    "sg:orig_category":"Cerrajer\u00cda, Ferrallista",
    "sg:phone":"+34 977 45 01 56",
    "sg:postcode":"43896",
    "sg:province":"Tarragona",
    "wof:name":"Falco Serrallers S.l.",
    "wof:placetype":"venue"
},
  "geometry": {"coordinates":[0.610920012,40.7403488159],"type":"Point"}
}