{
  "type": "Feature",
  "properties": {
    "addr:full":"Plaz Riego De, 7 Oviedo Asturias 33003",
    "addr:postcode":"33003",
    "iso:country":"ES",
    "sg:address":"Plaz Riego De, 7",
    "sg:city":"Oviedo",
    "sg:orig_category":"Institutos De Belleza",
    "sg:phone":"+34 985 22 19 02",
    "sg:postcode":"33003",
    "sg:province":"Asturias",
    "wof:name":"Garcia Bernardo Jose Ivan",
    "wof:placetype":"venue"
},
  "geometry": {"coordinates":[-5.8458204269,43.3611946106],"type":"Point"}
}