{
  "type": "Feature",
  "properties": {
    "addr:full":"Cami Borges (de Les), S/n Torregrossa Lleida 25141",
    "addr:postcode":"25141",
    "addr:street":"Borges;Les S / N",
    "iso:country":"ES",
    "sg:address":"Cami Borges (de Les), S/n",
    "sg:city":"Torregrossa",
    "sg:orig_category":"Contenedores (mercanc\u00cdas)",
    "sg:phone":"+34 973 17 00 51",
    "sg:postcode":"25141",
    "sg:province":"Lleida",
    "wof:name":"Capell Faura Ramon",
    "wof:placetype":"venue"
},
  "geometry": {"coordinates":[0.8335450292,41.5776901245],"type":"Point"}
}