{
  "type": "Feature",
  "properties": {
    "addr:full":"Rond Felanitx, 47 Manacor Islas Baleares 07500",
    "addr:housenumber":"47",
    "addr:postcode":"07500",
    "addr:street":"Felanitx",
    "iso:country":"ES",
    "sg:address":"Rond Felanitx, 47",
    "sg:city":"Manacor",
    "sg:orig_category":"Inform\u00c1tica: Material Y Suministros",
    "sg:phone":"+34 971 84 44 48",
    "sg:postcode":"07500",
    "sg:province":"Islas Baleares",
    "wof:name":"Galmes Matamalas Antoni",
    "wof:placetype":"venue"
},
  "geometry": {"coordinates":[3.2033638954,39.563243866],"type":"Point"}
}