{
  "type": "Feature",
  "properties": {
    "iso:country":"ES",
    "sg:address":"Ventas De Arlas, S/n",
    "sg:city":"Peralta",
    "sg:orig_category":"Mec\u00c1nico Del Autom\u00d3vil",
    "sg:phone":"+34 948 73 40 12",
    "sg:postcode":"31350",
    "sg:province":"Navarra",
    "wof:name":"Talleres Zubiri S.a.l.",
    "wof:placetype":"venue"
},
  "geometry": {"coordinates":[-1.8050489426,42.3389167786],"type":"Point"}
}