{
  "type": "Feature",
  "properties": {
    "addr:full":"Carr Joan Maragall, 36 Girona Girona 17002",
    "addr:housenumber":"36",
    "addr:postcode":"17002",
    "addr:street":"Carr Joan Maragall",
    "iso:country":"ES",
    "sg:address":"Carr Joan Maragall, 36",
    "sg:city":"Girona",
    "sg:orig_category":"Abogados",
    "sg:phone":"+34 972 21 72 84",
    "sg:postcode":"17002",
    "sg:province":"Girona",
    "wof:name":"Pallas Puigdomenech Joan",
    "wof:placetype":"venue"
},
  "geometry": {"coordinates":[2.8198809624,41.9778785706],"type":"Point"}
}