{
  "type": "Feature",
  "properties": {
    "addr:full":"Carr Pintor Pinazo, 12 Manises Valencia 46940",
    "addr:housenumber":"12",
    "addr:postcode":"46940",
    "addr:street":"Carr Pintor Pinazo",
    "iso:country":"ES",
    "sg:address":"Carr Pintor Pinazo, 12",
    "sg:city":"Manises",
    "sg:orig_category":"Papeler\u00cdas, Librer\u00cdas",
    "sg:phone":"+34 961 54 60 82",
    "sg:postcode":"46940",
    "sg:province":"Valencia",
    "wof:name":"Salvador Navarro Julia",
    "wof:placetype":"venue"
},
  "geometry": {"coordinates":[-0.4678080082,39.4970817566],"type":"Point"}
}