{
  "type": "Feature",
  "properties": {
    "addr:full":"Calle de Sanchez Toca, 9 Donostia-san Sebastian Guip\u00f9zcoa 20006",
    "addr:housenumber":"9",
    "addr:postcode":"20006",
    "addr:street":"Calle De Sanchez Toca",
    "iso:country":"ES",
    "sg:address":"Calle de Sanchez Toca, 9",
    "sg:city":"Donostia-san Sebastian",
    "sg:orig_category":"M\u00c9dicos: Ginecolog\u00cda Y Obstetricia",
    "sg:phone":"+34 943 45 56 67",
    "sg:postcode":"20006",
    "sg:province":"Guip\u00f9zcoa",
    "wof:name":"Ruiz Alonso Enrique",
    "wof:placetype":"venue"
},
  "geometry": {"coordinates":[-1.9812920094,43.315612793],"type":"Point"}
}