{
  "type": "Feature",
  "properties": {
    "iso:country":"ES",
    "sg:address":"Avda Manzanares, 84",
    "sg:city":"Madrid",
    "sg:orig_category":"Plomeros",
    "sg:phone":"+34 915 60 75 85",
    "sg:postcode":"28019",
    "sg:province":"Madrid",
    "wof:name":"Palacios Hernandez Hilario",
    "wof:placetype":"venue"
},
  "geometry": {"coordinates":[-3.7215199471,40.3999710083],"type":"Point"}
}