{
  "type": "Feature",
  "properties": {
    "addr:full":"Ptda Les Sorts, S/n Verger Alicante 03770",
    "addr:housenumber":"s / n",
    "addr:postcode":"03770",
    "addr:street":"Ptda Les Sorts",
    "iso:country":"ES",
    "sg:address":"Ptda Les Sorts, S/n",
    "sg:city":"Verger",
    "sg:orig_category":"Piedra Natural",
    "sg:phone":"+34 965 75 09 53",
    "sg:postcode":"03770",
    "sg:province":"Alicante",
    "wof:name":"Terrazos Escolano S.l.",
    "wof:placetype":"venue"
},
  "geometry": {"coordinates":[0.0091000004,38.8460693359],"type":"Point"}
}