{
  "type": "Feature",
  "properties": {
    "iso:country":"ES",
    "sg:address":"Carrer de Lopez Pelaez, 25",
    "sg:city":"Tarragona",
    "sg:orig_category":"Molduras, Junquillos, Listones Y Molduras Perforadas",
    "sg:phone":"+34 977 22 96 15",
    "sg:postcode":"43002",
    "sg:province":"Tarragona",
    "wof:name":"Sanchez Perez Juana",
    "wof:placetype":"venue"
},
  "geometry": {"coordinates":[1.2511899471,41.1189727783],"type":"Point"}
}