{
  "type": "Feature",
  "properties": {
    "addr:full":"Calle de Huerto, 9 Almendralejo Badajoz 06200",
    "addr:housenumber":"9",
    "addr:postcode":"06200",
    "addr:street":"Calle De Huerto",
    "iso:country":"ES",
    "sg:address":"Calle de Huerto, 9",
    "sg:city":"Almendralejo",
    "sg:orig_category":"Centros Empresariales",
    "sg:phone":"+34 924 66 75 78",
    "sg:postcode":"06200",
    "sg:province":"Badajoz",
    "wof:name":"Servicios Sociales Extremadura S.l.u.",
    "wof:placetype":"venue"
},
  "geometry": {"coordinates":[-6.4021091461,38.6812400818],"type":"Point"}
}