{
  "type": "Feature",
  "properties": {
    "iso:country":"ES",
    "sg:address":"Calle de Islas Malvinas, 89",
    "sg:city":"Santiago Ribera",
    "sg:orig_category":"Centros De Coordinaci\u00d3n",
    "sg:phone":"+34 968 18 72 95",
    "sg:postcode":"30720",
    "sg:province":"Murcia",
    "wof:name":"Munuera Romero Encarnacion",
    "wof:placetype":"venue"
},
  "geometry": {"coordinates":[-0.8069189787,37.8014183044],"type":"Point"}
}