{
  "type": "Feature",
  "properties": {
    "iso:country":"ES",
    "sg:address":"Calle de Autonomia, 16",
    "sg:city":"Sodupe",
    "sg:orig_category":"Electrodom\u00c9sticos (al Por Menor)",
    "sg:phone":"+34 946 69 22 45",
    "sg:postcode":"48830",
    "sg:province":"Vizcaya",
    "wof:name":"Mozo Nu\u00f1ez Maria Asuncion",
    "wof:placetype":"venue"
},
  "geometry": {"coordinates":[-3.0497956276,43.2005882263],"type":"Point"}
}