{
  "type": "Feature",
  "properties": {
    "addr:full":"Calle de Borneo, 27 Salamanca Salamanca 37003",
    "addr:housenumber":"27",
    "addr:postcode":"37003",
    "addr:street":"Calle De Borneo",
    "iso:country":"ES",
    "sg:address":"Calle de Borneo, 27",
    "sg:city":"Salamanca",
    "sg:orig_category":"Carnicer\u00cdas, Carnicer\u00cdas",
    "sg:phone":"+34 923 18 34 89",
    "sg:postcode":"37003",
    "sg:province":"Salamanca",
    "wof:name":"Sanchez Ramos Rosa Maria",
    "wof:placetype":"venue"
},
  "geometry": {"coordinates":[-5.6425814629,40.9716911316],"type":"Point"}
}