{
  "type": "Feature",
  "properties": {
    "addr:full":"Ctra. Coria, Km. 0042,0 Pinofranqueado C\u00e1ceres 10630",
    "addr:postcode":"10630",
    "addr:street":"Ctra. Coria Km. 0042,0;Ca\u0301Ceres",
    "iso:country":"ES",
    "sg:address":"Ctra. Coria, Km. 0042,0",
    "sg:city":"Pinofranqueado",
    "sg:orig_category":"Cerrajer\u00cda, Ferrallista",
    "sg:phone":"+34 927 67 41 83",
    "sg:postcode":"10630",
    "sg:province":"C\u00e1ceres",
    "wof:name":"Hierros Y Aluminios Benito C.b.",
    "wof:placetype":"venue"
},
  "geometry": {"coordinates":[-6.3322992325,40.3015785217],"type":"Point"}
}