{
  "type": "Feature",
  "properties": {
    "iso:country":"ES",
    "sg:address":"Joan Xxiii Plaza, S/n",
    "sg:city":"Bergara",
    "sg:orig_category":"Plomeros",
    "sg:phone":"+34 943 76 11 88",
    "sg:postcode":"20570",
    "sg:province":"Guip\u00f9zcoa",
    "wof:name":"Larra\u00f1aga Eguren S.l.",
    "wof:placetype":"venue"
},
  "geometry": {"coordinates":[-2.4136209488,43.1186485291],"type":"Point"}
}