{
  "type": "Feature",
  "properties": {
    "addr:full":"Ctra. C. Gata, 141 Almeria Almer\u00eda 04007",
    "addr:housenumber":"141",
    "addr:postcode":"04007",
    "addr:street":"Ctra. C. Gata",
    "iso:country":"ES",
    "sg:address":"Ctra. C. Gata, 141",
    "sg:city":"Almeria",
    "sg:orig_category":"Bancos",
    "sg:phone":"+34 950 25 17 66",
    "sg:postcode":"04007",
    "sg:province":"Almer\u00eda",
    "wof:name":"Banco De Andalucia",
    "wof:placetype":"venue"
},
  "geometry": {"coordinates":[-2.4139039516,36.8265609741],"type":"Point"}
}