{
  "type": "Feature",
  "properties": {
    "iso:country":"ES",
    "sg:address":"Pg Doctor Letamendi, 7",
    "sg:city":"Barri Maritim Sector Sanatori",
    "sg:orig_category":"Electricidad: Instaladores",
    "sg:phone":"+34 977 69 00 04",
    "sg:postcode":"43700",
    "sg:province":"Tarragona",
    "wof:name":"A. Gaya S. A.",
    "wof:placetype":"venue"
},
  "geometry": {"coordinates":[1.5595598221,41.1927642822],"type":"Point"}
}