{
  "type": "Feature",
  "properties": {
    "iso:country":"ES",
    "sg:address":"Calle de Fernandez De Los Rios, 10",
    "sg:city":"Madrid",
    "sg:orig_category":"Contables",
    "sg:phone":"+34 914 45 46 31",
    "sg:postcode":"28015",
    "sg:province":"Madrid",
    "wof:name":"Audysa Asesores Y Consultores S.a.",
    "wof:placetype":"venue"
},
  "geometry": {"coordinates":[-3.7052083015,40.4349555969],"type":"Point"}
}