{
  "type": "Feature",
  "properties": {
    "iso:country":"ES",
    "sg:address":"Cmn Salobral, S/n",
    "sg:city":"Herencia",
    "sg:orig_category":"Material Y Herramientas Agr\u00cdcolas",
    "sg:phone":"+34 926 57 11 59",
    "sg:postcode":"13640",
    "sg:province":"Ciudad Real",
    "wof:name":"Metalicas La Esperanza S.l.",
    "wof:placetype":"venue"
},
  "geometry": {"coordinates":[-3.3587589264,39.3725738525],"type":"Point"}
}