{
  "type": "Feature",
  "properties": {
    "addr:full":"Avda Carlos V (de), 46 Mostoles Madrid 28937",
    "addr:housenumber":"46",
    "addr:postcode":"28937",
    "addr:street":"Avda Carlos V De",
    "iso:country":"ES",
    "sg:address":"Avda Carlos V (de), 46",
    "sg:city":"Mostoles",
    "sg:orig_category":"Fotocopias, Reprograf\u00cda",
    "sg:phone":"+34 916 47 50 13",
    "sg:postcode":"28937",
    "sg:province":"Madrid",
    "wof:name":"Vecino Lobero Juan Pedro",
    "wof:placetype":"venue"
},
  "geometry": {"coordinates":[-3.8550488949,40.3153800964],"type":"Point"}
}