{
  "type": "Feature",
  "properties": {
    "addr:full":"Ctra Roda (la), Km. 0001,0 Casasimarro Cuenca 16239",
    "addr:postcode":"16239",
    "addr:street":"Ctra Roda La Km. 0001,0",
    "iso:country":"ES",
    "sg:address":"Ctra Roda (la), Km. 0001,0",
    "sg:city":"Casasimarro",
    "sg:orig_category":"Suministros Para Carrocer\u00cdas",
    "sg:phone":"+34 967 57 10 51",
    "sg:postcode":"16239",
    "sg:province":"Cuenca",
    "wof:name":"Metalurgicas Surco S.a.l.",
    "wof:placetype":"venue"
},
  "geometry": {"coordinates":[-2.0352840424,39.3953895569],"type":"Point"}
}