{
  "type": "Feature",
  "properties": {
    "addr:full":"Rua Oza Dos Rios, 6 Sada La Coru\u00f1a 15160",
    "addr:housenumber":"6",
    "addr:postcode":"15160",
    "addr:street":"Rua Oza Dos Rios;La",
    "iso:country":"ES",
    "sg:address":"Rua Oza Dos Rios, 6",
    "sg:city":"Sada",
    "sg:orig_category":"Ropa Para Ni\u00d1os (al Por Menor)",
    "sg:phone":"+34 981 61 90 95",
    "sg:postcode":"15160",
    "sg:province":"La Coru\u00f1a",
    "wof:name":"Garcia Busto Sara",
    "wof:placetype":"venue"
},
  "geometry": {"coordinates":[-8.2543935776,43.3506126404],"type":"Point"}
}