{
  "type": "Feature",
  "properties": {
    "iso:country":"ES",
    "sg:address":"Calle de Colon, 21",
    "sg:city":"Cumbres Mayores",
    "sg:orig_category":"Carnicer\u00cdas, Carnicer\u00cdas",
    "sg:phone":"+34 959 71 01 76",
    "sg:postcode":"21380",
    "sg:province":"Huelva",
    "wof:name":"Hermanos Casta\u00f1o Fernandez S.a.",
    "wof:placetype":"venue"
},
  "geometry": {"coordinates":[-6.6433038712,38.065032959],"type":"Point"}
}