{
  "type": "Feature",
  "properties": {
    "iso:country":"ES",
    "sg:address":"Avda Pablo Gargallo, 6",
    "sg:city":"Maella",
    "sg:orig_category":"Asesor\u00cda De Formaci\u00d3n Y Gesti\u00d3n De Personal",
    "sg:phone":"+34 976 63 87 69",
    "sg:postcode":"50710",
    "sg:province":"Zaragoza",
    "wof:name":"Tarrago Gil Maria Luisa",
    "wof:placetype":"venue"
},
  "geometry": {"coordinates":[0.1376830041,41.1222801208],"type":"Point"}
}