{
  "type": "Feature",
  "properties": {
    "iso:country":"ES",
    "sg:address":"Calle de Herreros, 20",
    "sg:city":"Rota",
    "sg:orig_category":"Alquiler De Veh\u00cdculos: Turismos Y Utilitarios",
    "sg:phone":"+34 956 81 61 21",
    "sg:postcode":"11520",
    "sg:province":"C\u00e1diz",
    "sg:website":"www.nizacars.es",
    "wof:name":"Niza Cars S.l.u.",
    "wof:placetype":"venue"
},
  "geometry": {"coordinates":[-6.3642802238,36.6314964294],"type":"Point"}
}