{
  "type": "Feature",
  "properties": {
    "iso:country":"ES",
    "sg:address":"Calle de Moratin, 8",
    "sg:city":"Madrid",
    "sg:orig_category":"Edici\u00d3n De Diarios, Revistas, Boletines",
    "sg:phone":"+34 914 20 14 51",
    "sg:postcode":"28014",
    "sg:province":"Madrid",
    "sg:website":"www.caparroseditores.com",
    "wof:name":"Caparros Editores S.l.",
    "wof:placetype":"venue"
},
  "geometry": {"coordinates":[-3.6977460384,40.4121665955],"type":"Point"}
}