{
  "type": "Feature",
  "properties": {
    "iso:country":"ES",
    "sg:address":"Carrer de Zurbaran, 10",
    "sg:city":"Ondara",
    "sg:orig_category":"Electrodom\u00c9sticos (al Por Menor)",
    "sg:phone":"+34 965 76 71 92",
    "sg:postcode":"03760",
    "sg:province":"Alicante",
    "wof:name":"Medina Martinez Jorge",
    "wof:placetype":"venue"
},
  "geometry": {"coordinates":[0.0159000009,38.8277015686],"type":"Point"}
}