{
  "type": "Feature",
  "properties": {
    "iso:country":"ES",
    "sg:address":"Calle de Bernabe Soriano, 27",
    "sg:city":"Jaen",
    "sg:orig_category":"Electrodom\u00c9sticos (al Por Menor)",
    "sg:phone":"+34 953 24 13 14",
    "sg:postcode":"23001",
    "sg:province":"Ja\u00e9n",
    "sg:website":"www.cafedeindias.com",
    "wof:name":"Cimadevilla Cafe S.l.",
    "wof:placetype":"venue"
},
  "geometry": {"coordinates":[-3.7875270844,37.7670555115],"type":"Point"}
}