{
  "type": "Feature",
  "properties": {
    "addr:full":"Calle de Alcazar, 48 Mocejon Toledo 45270",
    "addr:housenumber":"48",
    "addr:postcode":"45270",
    "addr:street":"Calle De Alcazar",
    "iso:country":"ES",
    "sg:address":"Calle de Alcazar, 48",
    "sg:city":"Mocejon",
    "sg:orig_category":"Papeler\u00cdas, Librer\u00cdas",
    "sg:phone":"+34 925 27 01 80",
    "sg:postcode":"45270",
    "sg:province":"Toledo",
    "wof:name":"Gonzalez Diaz Maria Vega",
    "wof:placetype":"venue"
},
  "geometry": {"coordinates":[-3.9205973148,39.9405860901],"type":"Point"}
}