{
  "type": "Feature",
  "properties": {
    "iso:country":"ES",
    "sg:address":"Calle de Pilar Lorengar, 15",
    "sg:city":"Madrid",
    "sg:classifiers":[
        {
            "category":"Casinos & Gambling",
            "type":"Entertainment"
        }
    ],
    "sg:phone":"+34 917 97 42 09",
    "sg:postcode":"28021",
    "sg:province":"Madrid",
    "sg:tags":[
        "locale",
        "de",
        "juego"
    ],
    "wof:name":"Ocio Joven C.b.",
    "wof:placetype":"venue"
},
  "geometry": {"coordinates":[-3.6858990192,40.3536109924],"type":"Point"}
}