{
  "type": "Feature",
  "properties": {
    "addr:full":"Calle de Tinte, 8 Ciudad Real Ciudad Real 13001",
    "addr:housenumber":"8",
    "addr:postcode":"13001",
    "addr:street":"Calle De Tinte",
    "iso:country":"ES",
    "sg:address":"Calle de Tinte, 8",
    "sg:city":"Ciudad Real",
    "sg:orig_category":"Artesan\u00cda",
    "sg:phone":"+34 926 22 64 00",
    "sg:postcode":"13001",
    "sg:province":"Ciudad Real",
    "wof:name":"Crespo Bordonaba Ismael",
    "wof:placetype":"venue"
},
  "geometry": {"coordinates":[-3.9295399189,38.9818077087],"type":"Point"}
}