{
  "type": "Feature",
  "properties": {
    "addr:full":"Calle de General Sanjurjo, 121 Fermoselle Zamora 49220",
    "addr:housenumber":"121",
    "addr:postcode":"49220",
    "addr:street":"Calle De General Sanjurjo",
    "iso:country":"ES",
    "sg:address":"Calle de General Sanjurjo, 121",
    "sg:city":"Fermoselle",
    "sg:orig_category":"Mercer\u00cda, Lencer\u00cda (al Por Menor)",
    "sg:phone":"+34 980 61 31 11",
    "sg:postcode":"49220",
    "sg:province":"Zamora",
    "wof:name":"Torre Puente Antonio De La",
    "wof:placetype":"venue"
},
  "geometry": {"coordinates":[-6.395898819,41.3174209595],"type":"Point"}
}