{
  "type": "Feature",
  "properties": {
    "iso:country":"ES",
    "sg:address":"Avda Portugal, S/n",
    "sg:city":"Aranda Duero",
    "sg:orig_category":"Mec\u00c1nico Del Autom\u00d3vil",
    "sg:phone":"+34 947 51 28 21",
    "sg:postcode":"09400",
    "sg:province":"Burgos",
    "sg:website":"www.talleresdelasheras.com",
    "wof:name":"Eusterio De Las Heras E Hijos S.l.",
    "wof:placetype":"venue"
},
  "geometry": {"coordinates":[-3.702999115,41.6691398621],"type":"Point"}
}