{
  "type": "Feature",
  "properties": {
    "addr:full":"Calle de Octavio Alvarez Carballo, 20 Le\u00f3n Le\u00f3n 24004",
    "addr:housenumber":"20",
    "addr:postcode":"24004",
    "addr:street":"Calle De Octavio Alvarez Carballo;Leo\u0301N",
    "iso:country":"ES",
    "sg:address":"Calle de Octavio Alvarez Carballo, 20",
    "sg:city":"Le\u00f3n",
    "sg:orig_category":"Mec\u00c1nico Del Autom\u00d3vil",
    "sg:phone":"+34 987 20 60 60",
    "sg:postcode":"24004",
    "sg:province":"Le\u00f3n",
    "wof:name":"Puente Ordas Maximo",
    "wof:placetype":"venue"
},
  "geometry": {"coordinates":[-5.5662989616,42.5911483765],"type":"Point"}
}