{
  "type": "Feature",
  "properties": {
    "iso:country":"ES",
    "sg:address":"Ctra. Sagunto Burgos, 3",
    "sg:city":"Calatayud",
    "sg:orig_category":"Material Y Herramientas Agr\u00cdcolas",
    "sg:phone":"+34 976 88 31 22",
    "sg:postcode":"50300",
    "sg:province":"Zaragoza",
    "wof:name":"Deza Iba\u00f1ez Mariano",
    "wof:placetype":"venue"
},
  "geometry": {"coordinates":[-1.6394540071,41.3522415161],"type":"Point"}
}