{
  "type": "Feature",
  "properties": {
    "iso:country":"ES",
    "sg:address":"Av Roma (de), 5",
    "sg:city":"Tarragona",
    "sg:orig_category":"M\u00c9dicos: Cirug\u00cda Vascular",
    "sg:phone":"+34 977 24 56 12",
    "sg:postcode":"43005",
    "sg:province":"Tarragona",
    "wof:name":"Martin Paredero Vicente",
    "wof:placetype":"venue"
},
  "geometry": {"coordinates":[1.2432899475,41.118938446],"type":"Point"}
}