{
  "type": "Feature",
  "properties": {
    "addr:full":"Euskadi Etorbidea, 21 Pasai S. Pedro Guip\u00f9zcoa 20110",
    "addr:housenumber":"21",
    "addr:postcode":"20110",
    "addr:street":"Euskadi Etorbidea;Guipu\u0300Zcoa",
    "iso:country":"ES",
    "sg:address":"Euskadi Etorbidea, 21",
    "sg:city":"Pasai S. Pedro",
    "sg:orig_category":"Cajas De Ahorro",
    "sg:phone":"+34 943 39 99 46",
    "sg:postcode":"20110",
    "sg:province":"Guip\u00f9zcoa",
    "wof:name":"Caixa D'estalvis I Pensions De Barcelona",
    "wof:placetype":"venue"
},
  "geometry": {"coordinates":[-1.9300839901,43.3229217529],"type":"Point"}
}