{
  "type": "Feature",
  "properties": {
    "iso:country":"ES",
    "sg:address":"Carrer de Arago, 141",
    "sg:city":"Barcelona",
    "sg:orig_category":"Agencias Y Agentes Comerciales, Representantes",
    "sg:phone":"+34 934 54 79 61",
    "sg:postcode":"08015",
    "sg:province":"Barcelona",
    "sg:website":"www.microsinter.com",
    "wof:name":"J & M Microsinter Sl",
    "wof:placetype":"venue"
},
  "geometry": {"coordinates":[2.1545319557,41.3845748901],"type":"Point"}
}