{
  "type": "Feature",
  "properties": {
    "iso:country":"ES",
    "sg:address":"C/ Murcia, 15",
    "sg:city":"Elche",
    "sg:orig_category":"Electricidad, Electr\u00d3nica: Material Y Suministros (al Por Mayor)",
    "sg:phone":"+34 965 42 95 26",
    "sg:postcode":"03203",
    "sg:province":"Alicante",
    "sg:website":"www.peisa.com",
    "wof:name":"Peisa Alicante S.l.",
    "wof:placetype":"venue"
},
  "geometry": {"coordinates":[-0.674398005,38.2699775696],"type":"Point"}
}