{
  "type": "Feature",
  "properties": {
    "addr:full":"Calle de Jose Bartrina, 10 Nules Castell\u00f3n 12520",
    "addr:housenumber":"10",
    "addr:postcode":"12520",
    "addr:street":"Calle De Jose Bartrina",
    "iso:country":"ES",
    "sg:address":"Calle de Jose Bartrina, 10",
    "sg:city":"Nules",
    "sg:orig_category":"Ropa Para Se\u00d1oras (al Por Menor)",
    "sg:phone":"+34 964 67 39 69",
    "sg:postcode":"12520",
    "sg:province":"Castell\u00f3n",
    "wof:name":"Confecciones Edos S.l.",
    "wof:placetype":"venue"
},
  "geometry": {"coordinates":[-0.1560499966,39.8530845642],"type":"Point"}
}