{
  "type": "Feature",
  "properties": {
    "addr:full":"Rua Soutullo (musico Mestre), 18 Lugo Lugo 27004",
    "addr:housenumber":"18",
    "addr:postcode":"27004",
    "addr:street":"Rua Soutullo Musico Mestre",
    "iso:country":"ES",
    "sg:address":"Rua Soutullo (musico Mestre), 18",
    "sg:city":"Lugo",
    "sg:orig_category":"Electrodom\u00c9sticos (al Por Menor)",
    "sg:phone":"+34 982 21 62 00",
    "sg:postcode":"27004",
    "sg:province":"Lugo",
    "wof:name":"Rodriguez Fernandez Jose",
    "wof:placetype":"venue"
},
  "geometry": {"coordinates":[-7.569381237,43.0095176697],"type":"Point"}
}