{
  "type": "Feature",
  "properties": {
    "addr:full":"Calle de Raimundo De Alos, 8 Vinaros Castell\u00f3n 12500",
    "addr:housenumber":"8",
    "addr:postcode":"12500",
    "addr:street":"Calle De Raimundo De Alos",
    "iso:country":"ES",
    "sg:address":"Calle de Raimundo De Alos, 8",
    "sg:city":"Vinaros",
    "sg:orig_category":"Distribuci\u00d3n De Petr\u00d3leo Y Derivados",
    "sg:phone":"+34 964 45 06 94",
    "sg:postcode":"12500",
    "sg:province":"Castell\u00f3n",
    "wof:name":"Andres Polo S.l.",
    "wof:placetype":"venue"
},
  "geometry": {"coordinates":[0.4717406034,40.4648628235],"type":"Point"}
}