{
  "type": "Feature",
  "properties": {
    "addr:full":"Estacion, S/n Viella Asturias 33429",
    "addr:postcode":"33429",
    "addr:street":"S / N Viella Asturias",
    "iso:country":"ES",
    "sg:address":"Estacion, S/n",
    "sg:city":"Viella",
    "sg:orig_category":"Suministros Para Carrocer\u00cdas",
    "sg:phone":"+34 985 79 35 02",
    "sg:postcode":"33429",
    "sg:province":"Asturias",
    "wof:name":"Taller Reclade S.l.n.e.",
    "wof:placetype":"venue"
},
  "geometry": {"coordinates":[-5.7704091072,43.3952407837],"type":"Point"}
}