{
  "type": "Feature",
  "properties": {
    "iso:country":"ES",
    "sg:address":"Avda 12, 10",
    "sg:city":"Vaciasilos",
    "sg:orig_category":"Forjas Y Altos Hornos",
    "sg:phone":"+34 918 16 90 51",
    "sg:postcode":"28991",
    "sg:province":"Madrid",
    "wof:name":"Inme Sociedad Cooperativa Limitada",
    "wof:placetype":"venue"
},
  "geometry": {"coordinates":[-3.7988600731,40.1880989075],"type":"Point"}
}