{
  "type": "Feature",
  "properties": {
    "addr:full":"Avda Poeta Jose Jurado Morales, 18 Linares Ja\u00e9n 23700",
    "addr:housenumber":"18",
    "addr:postcode":"23700",
    "addr:street":"Avda Poeta Jose Jurado Morales;Jae\u0301N",
    "iso:country":"ES",
    "sg:address":"Avda Poeta Jose Jurado Morales, 18",
    "sg:city":"Linares",
    "sg:orig_category":"Negocio De Materiales De Construcci\u00d3n",
    "sg:phone":"+34 953 65 62 56",
    "sg:postcode":"23700",
    "sg:province":"Ja\u00e9n",
    "wof:name":"Garay Suarez Juana",
    "wof:placetype":"venue"
},
  "geometry": {"coordinates":[-3.6223580837,38.0846252441],"type":"Point"}
}