{
  "type": "Feature",
  "properties": {
    "addr:full":"San Jose, 22 Benissa Alicante 03720",
    "addr:housenumber":"22",
    "addr:postcode":"03720",
    "addr:street":"San Jose",
    "iso:country":"ES",
    "sg:address":"San Jose, 22",
    "sg:city":"Benissa",
    "sg:orig_category":"Alimentaci\u00d3n General (al Por Menor)",
    "sg:phone":"+34 965 73 10 47",
    "sg:postcode":"03720",
    "sg:province":"Alicante",
    "wof:name":"Ivars Bertomeu, Sl",
    "wof:placetype":"venue"
},
  "geometry": {"coordinates":[0.0474510007,38.7151565552],"type":"Point"}
}