{
  "type": "Feature",
  "properties": {
    "addr:full":"Calle de Pedro Bidagor, 2 Bara\u00f1ain Navarra 31010",
    "addr:housenumber":"2",
    "addr:postcode":"31010",
    "addr:street":"Calle De Pedro Bidagor",
    "iso:country":"ES",
    "sg:address":"Calle de Pedro Bidagor, 2",
    "sg:city":"Bara\u00f1ain",
    "sg:orig_category":"Internados & Ense\u00d1anza Privada",
    "sg:phone":"+34 948 25 07 85",
    "sg:postcode":"31010",
    "sg:province":"Navarra",
    "wof:name":"Hijas De La Caridad San Vicente Paul Colegio Santa Luisa Marillac",
    "wof:placetype":"venue"
},
  "geometry": {"coordinates":[-97.78224945069999,45.7040786743],"type":"Point"}
}