{
  "type": "Feature",
  "properties": {
    "addr:full":"Calle de Superintendencia, 4 Huescar Granada 18830",
    "addr:housenumber":"4",
    "addr:postcode":"18830",
    "addr:street":"Calle De Superintendencia",
    "iso:country":"ES",
    "sg:address":"Calle de Superintendencia, 4",
    "sg:city":"Huescar",
    "sg:orig_category":"Electrodom\u00c9sticos (al Por Menor)",
    "sg:phone":"+34 958 74 12 24",
    "sg:postcode":"18830",
    "sg:province":"Granada",
    "sg:website":"www.redelite.es",
    "wof:name":"Garcia Garcia Francisco",
    "wof:placetype":"venue"
},
  "geometry": {"coordinates":[-2.5423920155,37.8083610535],"type":"Point"}
}