{
  "type": "Feature",
  "properties": {
    "addr:full":"Av Josep Tarradellas, 51 Barcelona Barcelona 08029",
    "addr:housenumber":"51",
    "addr:postcode":"08029",
    "addr:street":"Av Josep Tarradellas",
    "iso:country":"ES",
    "sg:address":"Av Josep Tarradellas, 51",
    "sg:city":"Barcelona",
    "sg:orig_category":"Papeler\u00cdas, Librer\u00cdas",
    "sg:phone":"+34 934 39 66 94",
    "sg:postcode":"08029",
    "sg:province":"Barcelona",
    "wof:name":"Nu\u00f1ez Lencero Teodora",
    "wof:placetype":"venue"
},
  "geometry": {"coordinates":[2.1423060894,41.384147644],"type":"Point"}
}