{
  "type": "Feature",
  "properties": {
    "iso:country":"ES",
    "sg:address":"Ctra. Zaragoza, S/n",
    "sg:city":"Tarazona",
    "sg:orig_category":"Hoteles",
    "sg:phone":"+34 976 64 04 00",
    "sg:postcode":"50500",
    "sg:province":"Zaragoza",
    "wof:name":"Hoteles Del Queiles S. A.",
    "wof:placetype":"venue"
},
  "geometry": {"coordinates":[-1.7197389603,41.9042663574],"type":"Point"}
}