{
  "type": "Feature",
  "properties": {
    "iso:country":"ES",
    "sg:address":"Ptda Devadillo, 2",
    "sg:city":"Picassent",
    "sg:orig_category":"Semiller\u00cdas",
    "sg:phone":"+34 961 23 05 57",
    "sg:postcode":"46220",
    "sg:province":"Valencia",
    "wof:name":"Viveros Devadillo S.l.",
    "wof:placetype":"venue"
},
  "geometry": {"coordinates":[-0.4974358976,39.3506889343],"type":"Point"}
}