{
  "type": "Feature",
  "properties": {
    "iso:country":"ES",
    "sg:address":"Calle de Ferrocarril, 3",
    "sg:city":"Valladolid",
    "sg:orig_category":"Agentes De Seguros",
    "sg:phone":"+34 983 30 94 04",
    "sg:postcode":"47004",
    "sg:province":"Valladolid",
    "wof:name":"Villanueva Cisneros Jose Luis",
    "wof:placetype":"venue"
},
  "geometry": {"coordinates":[-4.7228589058,41.6456718445],"type":"Point"}
}