{
  "type": "Feature",
  "properties": {
    "iso:country":"ES",
    "sg:address":"Calle de Zarco Del Valle, 14",
    "sg:city":"Bailen",
    "sg:orig_category":"Electrodom\u00c9sticos (al Por Menor)",
    "sg:phone":"+34 953 67 61 28",
    "sg:postcode":"23710",
    "sg:province":"Ja\u00e9n",
    "wof:name":"Mogua Nieto Francisca",
    "wof:placetype":"venue"
},
  "geometry": {"coordinates":[-3.7774391174,38.0957183838],"type":"Point"}
}