{
  "type": "Feature",
  "properties": {
    "iso:country":"ES",
    "sg:address":"Calle de Gomez Ferrer, 87",
    "sg:city":"Torrent",
    "sg:orig_category":"Agentes, Concesionarios Y Sucursales De Veh\u00cdculos",
    "sg:phone":"+34 961 57 11 02",
    "sg:postcode":"46900",
    "sg:province":"Valencia",
    "wof:name":"Auto Hugar S.a.",
    "wof:placetype":"venue"
},
  "geometry": {"coordinates":[-0.4627529979,39.4409637451],"type":"Point"}
}