{
  "type": "Feature",
  "properties": {
    "iso:country":"ES",
    "sg:address":"Calle de Catedratico Gimeno, 4",
    "sg:city":"Oviedo",
    "sg:orig_category":"Servicios De Higiene Y Peluquer\u00cda Para Perros Y Gatos",
    "sg:phone":"+34 985 24 48 54",
    "sg:postcode":"33007",
    "sg:province":"Asturias",
    "wof:name":"Pet Grooning C.b.",
    "wof:placetype":"venue"
},
  "geometry": {"coordinates":[-5.8528528214,43.355884552],"type":"Point"}
}