{
  "type": "Feature",
  "properties": {
    "addr:full":"Av Carlos Soler, 62 Mutxamel Alicante 03110",
    "addr:housenumber":"62",
    "addr:postcode":"03110",
    "addr:street":"Av Carlos Soler",
    "iso:country":"ES",
    "sg:address":"Av Carlos Soler, 62",
    "sg:city":"Mutxamel",
    "sg:orig_category":"Panader\u00cdas, Panader\u00cdas",
    "sg:phone":"+34 965 95 27 33",
    "sg:postcode":"03110",
    "sg:province":"Alicante",
    "wof:name":"Bolli Pan Mutxamel S.l.",
    "wof:placetype":"venue"
},
  "geometry": {"coordinates":[-0.4448629916,38.4154624939],"type":"Point"}
}