{
  "type": "Feature",
  "properties": {
    "iso:country":"ES",
    "sg:address":"Av Verge Montserrat, 29",
    "sg:city":"Prat Llobregat",
    "sg:orig_category":"Molduras, Junquillos, Listones Y Molduras Perforadas",
    "sg:phone":"+34 933 70 01 10",
    "sg:postcode":"08820",
    "sg:province":"Barcelona",
    "wof:name":"Bejarano Berrocoso Demetrio",
    "wof:placetype":"venue"
},
  "geometry": {"coordinates":[2.1004469395,41.3277244568],"type":"Point"}
}