{
  "type": "Feature",
  "properties": {
    "addr:full":"Calle de Marina Espa\u00d1ola, 37 Santa Olalla Del Cala Huelva 21260",
    "addr:housenumber":"37",
    "addr:postcode":"21260",
    "addr:street":"Calle De Marina Espan\u0303Ola",
    "iso:country":"ES",
    "sg:address":"Calle de Marina Espa\u00d1ola, 37",
    "sg:city":"Santa Olalla Del Cala",
    "sg:orig_category":"Vallados Y Barreras",
    "sg:phone":"+34 959 19 01 24",
    "sg:postcode":"21260",
    "sg:province":"Huelva",
    "wof:name":"Jose Mestre E Hijo S.l.",
    "wof:placetype":"venue"
},
  "geometry": {"coordinates":[-6.2234139442,37.9069366455],"type":"Point"}
}