{
  "type": "Feature",
  "properties": {
    "addr:full":"Calle de Desarrollo (del), 13 Adaro Madrid 28906",
    "addr:housenumber":"13",
    "addr:postcode":"28906",
    "addr:street":"Calle De Desarrollo Del",
    "iso:country":"ES",
    "sg:address":"Calle de Desarrollo (del), 13",
    "sg:city":"Adaro",
    "sg:orig_category":"Equipo De Refrigeraci\u00d3n Industrial",
    "sg:phone":"+34 916 82 00 41",
    "sg:postcode":"28906",
    "sg:province":"Madrid",
    "wof:name":"Castillo Blanco Equipos Para Frio S.a.",
    "wof:placetype":"venue"
},
  "geometry": {"coordinates":[-3.7003455162,40.4166908264],"type":"Point"}
}