{
  "type": "Feature",
  "properties": {
    "iso:country":"ES",
    "sg:address":"Plaz Manuel Gomez-moreno, 2",
    "sg:city":"Madrid",
    "sg:orig_category":"Financiaci\u00d3n Y Cr\u00c9ditos",
    "sg:phone":"+34 915 56 02 71",
    "sg:postcode":"28020",
    "sg:province":"Madrid",
    "wof:name":"Vega Fund Holdings Agencia De Valores S.a.",
    "wof:placetype":"venue"
},
  "geometry": {"coordinates":[-3.6950740814,40.4479103088],"type":"Point"}
}