{
  "type": "Feature",
  "properties": {
    "iso:country":"ES",
    "sg:address":"Calle de Lutxana, 3",
    "sg:city":"Bilbao",
    "sg:orig_category":"M\u00c9dicos: Estomatolog\u00cda",
    "sg:phone":"+34 944 16 66 59",
    "sg:postcode":"48008",
    "sg:province":"Vizcaya",
    "wof:name":"Innovacion Medica Y Dental S.l.",
    "wof:placetype":"venue"
},
  "geometry": {"coordinates":[-2.9304220676,43.2596511841],"type":"Point"}
}