{
  "type": "Feature",
  "properties": {
    "iso:country":"ES",
    "sg:address":"Plaz Constitucion, 9",
    "sg:city":"Mora",
    "sg:orig_category":"Notarios",
    "sg:phone":"+34 925 30 09 39",
    "sg:postcode":"45400",
    "sg:province":"Toledo",
    "wof:name":"Lopez-bra Espiau Maria Gemma",
    "wof:placetype":"venue"
},
  "geometry": {"coordinates":[-3.7732589245,39.6841201782],"type":"Point"}
}