{
  "type": "Feature",
  "properties": {
    "iso:country":"ES",
    "sg:address":"Avda Luis Moran, 2",
    "sg:city":"Benavente",
    "sg:orig_category":"Peluqueros: De Se\u00d1oras",
    "sg:phone":"+34 980 63 43 42",
    "sg:postcode":"49600",
    "sg:province":"Zamora",
    "wof:name":"Ramos Riesco Maria Amparo",
    "wof:placetype":"venue"
},
  "geometry": {"coordinates":[-5.6750488281,42.0110282898],"type":"Point"}
}