{
  "type": "Feature",
  "properties": {
    "addr:full":"Plaz Iturgain, 3 Orkoien Navarra 31160",
    "addr:housenumber":"3",
    "addr:postcode":"31160",
    "addr:street":"Plaz Iturgain",
    "iso:country":"ES",
    "sg:address":"Plaz Iturgain, 3",
    "sg:city":"Orkoien",
    "sg:orig_category":"Reposter\u00cdas",
    "sg:phone":"+34 948 32 67 82",
    "sg:postcode":"31160",
    "sg:province":"Navarra",
    "wof:name":"Palomeque Osete Pedro Maria Y Susana S.c",
    "wof:placetype":"venue"
},
  "geometry": {"coordinates":[-1.6958830357,42.8236694336],"type":"Point"}
}