{
  "type": "Feature",
  "properties": {
    "addr:full":"Calle de Francisco Cuesta, 6 Guadalajara Guadalajara 19001",
    "addr:housenumber":"6",
    "addr:postcode":"19001",
    "addr:street":"Calle De Francisco Cuesta",
    "iso:country":"ES",
    "sg:address":"Calle de Francisco Cuesta, 6",
    "sg:city":"Guadalajara",
    "sg:orig_category":"Institutos De Belleza",
    "sg:phone":"+34 949 25 55 28",
    "sg:postcode":"19001",
    "sg:province":"Guadalajara",
    "wof:name":"Plaza Garcia Lorena",
    "wof:placetype":"venue"
},
  "geometry": {"coordinates":[-3.1673119068,40.6357879639],"type":"Point"}
}