{
  "type": "Feature",
  "properties": {
    "iso:country":"ES",
    "sg:address":"Calle de Princesa, 4",
    "sg:city":"Alcorcon",
    "sg:orig_category":"Revestimientos Diversos",
    "sg:phone":"+34 916 12 76 96",
    "sg:postcode":"28921",
    "sg:province":"Madrid",
    "wof:name":"Escobar Risue\u00f1o Angel",
    "wof:placetype":"venue"
},
  "geometry": {"coordinates":[-3.8300418854,40.3470802307],"type":"Point"}
}