{
  "type": "Feature",
  "properties": {
    "iso:country":"ES",
    "sg:address":"Calle de Luz (de La), 9",
    "sg:city":"Arevalo",
    "sg:orig_category":"Panader\u00cdas, Panader\u00cdas",
    "sg:phone":"+34 920 30 02 70",
    "sg:postcode":"05200",
    "sg:province":"\u00c1vila",
    "wof:name":"Lopez Arribas Benito",
    "wof:placetype":"venue"
},
  "geometry": {"coordinates":[-4.7189779282,41.0582466125],"type":"Point"}
}