{
  "type": "Feature",
  "properties": {
    "addr:full":"Mayor, 11 Estella Navarra 31200",
    "addr:housenumber":"11",
    "addr:postcode":"31200",
    "addr:street":"Mayor",
    "iso:country":"ES",
    "sg:address":"Mayor, 11",
    "sg:city":"Estella",
    "sg:orig_category":"Lencer\u00cda Femenina, Corseter\u00cda, Trajes De Ba\u00d1o (al Por Menor)",
    "sg:phone":"+34 948 55 39 80",
    "sg:postcode":"31200",
    "sg:province":"Navarra",
    "wof:name":"Valencia Lasanta Ana Maria",
    "wof:placetype":"venue"
},
  "geometry": {"coordinates":[-2.0326509476,42.6718597412],"type":"Point"}
}