{
  "type": "Feature",
  "properties": {
    "iso:country":"ES",
    "sg:address":"Valentin Beato, 24",
    "sg:city":"Madrid",
    "sg:orig_category":"Camiser\u00cda Y Ropa Interior Masculina (al Por Menor)",
    "sg:phone":"+34 913 04 29 67",
    "sg:postcode":"28037",
    "sg:province":"Madrid",
    "wof:name":"Nazel Textil S.l.",
    "wof:placetype":"venue"
},
  "geometry": {"coordinates":[-3.6259610653,40.438785553],"type":"Point"}
}