{
  "type": "Feature",
  "properties": {
    "addr:full":"Calle de Alfonso Xii, 34 Novelda Alicante 03660",
    "addr:housenumber":"34",
    "addr:postcode":"03660",
    "addr:street":"Calle De Alfonso Xii",
    "iso:country":"ES",
    "sg:address":"Calle de Alfonso Xii, 34",
    "sg:city":"Novelda",
    "sg:orig_category":"Transportes Por Carretera: Lotes Completos, Mercanc\u00cdas Diversas",
    "sg:phone":"+34 965 60 78 63",
    "sg:postcode":"03660",
    "sg:province":"Alicante",
    "wof:name":"Novelfret Suministros Hoteleros S.l.",
    "wof:placetype":"venue"
},
  "geometry": {"coordinates":[-0.7599852085,38.3840789795],"type":"Point"}
}