{
  "type": "Feature",
  "properties": {
    "iso:country":"ES",
    "sg:address":"Carr Canaries, 6",
    "sg:city":"Eivissa",
    "sg:orig_category":"Perfumer\u00cda (al Por Menor)",
    "sg:phone":"+34 971 39 28 62",
    "sg:postcode":"07800",
    "sg:province":"Islas Baleares",
    "wof:name":"Gomez Gomez Maria Rosario",
    "wof:placetype":"venue"
},
  "geometry": {"coordinates":[1.4188899994,38.9061164856],"type":"Point"}
}