{
  "type": "Feature",
  "properties": {
    "addr:full":"Pl Esglesia, S/n Fals Barcelona 08259",
    "addr:housenumber":"s / n",
    "addr:postcode":"08259",
    "addr:street":"Pl Esglesia",
    "iso:country":"ES",
    "sg:address":"Pl Esglesia, S/n",
    "sg:city":"Fals",
    "sg:orig_category":"Cooperativas Agr\u00cdcolas",
    "sg:phone":"+34 938 36 81 01",
    "sg:postcode":"08259",
    "sg:province":"Barcelona",
    "wof:name":"Cooperativa Del Campo De Utilizacion Maquinaria Agricola En Comun",
    "wof:placetype":"venue"
},
  "geometry": {"coordinates":[1.6672199965,41.7623214722],"type":"Point"}
}