{
  "type": "Feature",
  "properties": {
    "iso:country":"ES",
    "sg:address":"Parroco Pablo Diez, 237",
    "sg:city":"Trobajo Camino",
    "sg:classifiers":[
        {
            "category":"Autos & Motor Vehicles",
            "subcategory":"Automobile Sales",
            "type":"Retail Goods"
        }
    ],
    "sg:phone":"+34 987 80 05 15",
    "sg:postcode":"24010",
    "sg:province":"Le\u00f3n",
    "wof:name":"Auto-escuela Belial S.l.",
    "wof:placetype":"venue"
},
  "geometry": {"coordinates":[-5.6066679955,42.5963592529],"type":"Point"}
}