{
  "type": "Feature",
  "properties": {
    "addr:full":"Calle de Santomera, 22 Totana Murcia 30850",
    "addr:housenumber":"22",
    "addr:postcode":"30850",
    "addr:street":"Calle De Santomera",
    "iso:country":"ES",
    "sg:address":"Calle de Santomera, 22",
    "sg:city":"Totana",
    "sg:orig_category":"Perfumer\u00cda (al Por Menor)",
    "sg:phone":"+34 968 42 20 83",
    "sg:postcode":"30850",
    "sg:province":"Murcia",
    "wof:name":"Hernandez Lopez Francisca",
    "wof:placetype":"venue"
},
  "geometry": {"coordinates":[-1.4936109781,37.7753257751],"type":"Point"}
}