{
  "type": "Feature",
  "properties": {
    "addr:full":"Calle de Obispo Climent, 12 Castellon Castell\u00f3n 12001",
    "addr:housenumber":"12",
    "addr:postcode":"12001",
    "addr:street":"Calle De Obispo Climent",
    "iso:country":"ES",
    "sg:address":"Calle de Obispo Climent, 12",
    "sg:city":"Castellon",
    "sg:orig_category":"Bricolaje, Herramientas (al Por Menor)",
    "sg:phone":"+34 964 22 34 83",
    "sg:postcode":"12001",
    "sg:province":"Castell\u00f3n",
    "wof:name":"Belles Belles Maria Del Carmen",
    "wof:placetype":"venue"
},
  "geometry": {"coordinates":[-0.0362760015,39.9853591919],"type":"Point"}
}