{
  "type": "Feature",
  "properties": {
    "iso:country":"ES",
    "sg:address":"Plaz Gernikako Enparantza, 1",
    "sg:city":"Ugao-miraballes",
    "sg:orig_category":"Molduras, Junquillos, Listones Y Molduras Perforadas",
    "sg:phone":"+34 946 48 12 54",
    "sg:postcode":"48490",
    "sg:province":"Vizcaya",
    "wof:name":"Abrisqueta Casta\u00f1eza Inmaculada",
    "wof:placetype":"venue"
},
  "geometry": {"coordinates":[-2.902778,43.181561],"type":"Point"}
}