{
  "type": "Feature",
  "properties": {
    "iso:country":"ES",
    "sg:address":"Calle de Areatza, 23",
    "sg:city":"Plentzia",
    "sg:orig_category":"Supermercados Y Hipermercados",
    "sg:phone":"+34 946 77 31 01",
    "sg:postcode":"48620",
    "sg:province":"Vizcaya",
    "wof:name":"Ruiz Gorostidi Mikel",
    "wof:placetype":"venue"
},
  "geometry": {"coordinates":[-2.9446372986,43.4080238342],"type":"Point"}
}