{
  "type": "Feature",
  "properties": {
    "iso:country":"ES",
    "sg:address":"Calle de Aragon (de), 35",
    "sg:city":"Mejorada Campo",
    "sg:orig_category":"Extinci\u00d3n De Incendios: Material Y Suministros (fabricaci\u00d3n, Al Por Mayor)",
    "sg:phone":"+34 916 79 22 33",
    "sg:postcode":"28840",
    "sg:province":"Madrid",
    "wof:name":"Mides Olid S.l.u.",
    "wof:placetype":"venue"
},
  "geometry": {"coordinates":[-3.4807934761,40.3858451843],"type":"Point"}
}