{
  "type": "Feature",
  "properties": {
    "addr:full":"Calle de Murcia (de), 3 Fuenlabrada Madrid 28945",
    "addr:housenumber":"3",
    "addr:postcode":"28945",
    "addr:street":"Calle De Murcia De",
    "iso:country":"ES",
    "sg:address":"Calle de Murcia (de), 3",
    "sg:city":"Fuenlabrada",
    "sg:orig_category":"Lencer\u00cda Femenina, Corseter\u00cda, Trajes De Ba\u00d1o (al Por Menor)",
    "sg:phone":"+34 916 15 59 65",
    "sg:postcode":"28945",
    "sg:province":"Madrid",
    "wof:name":"Gimenez Gonzalez Vicenta",
    "wof:placetype":"venue"
},
  "geometry": {"coordinates":[-3.7923159599,40.2900161743],"type":"Point"}
}