{
  "type": "Feature",
  "properties": {
    "iso:country":"ES",
    "sg:address":"La Fuente, 6",
    "sg:city":"Frontera",
    "sg:orig_category":"Alimentaci\u00d3n General (al Por Mayor)",
    "sg:phone":"+34 969 31 03 05",
    "sg:postcode":"16144",
    "sg:province":"Cuenca",
    "wof:name":"Portal De Serrania S.l.",
    "wof:placetype":"venue"
},
  "geometry": {"coordinates":[-2.2169470787,40.4018783569],"type":"Point"}
}