{
  "type": "Feature",
  "properties": {
    "iso:country":"ES",
    "sg:address":"Avda Arlanzon, 15",
    "sg:city":"Burgos",
    "sg:orig_category":"Sociedades, Compa\u00d1\u00cdas Aseguradoras",
    "sg:phone":"+34 947 20 32 29",
    "sg:postcode":"09004",
    "sg:province":"Burgos",
    "wof:name":"Arribas Lalanne Jesus Manuel",
    "wof:placetype":"venue"
},
  "geometry": {"coordinates":[-3.687568903,42.3349075317],"type":"Point"}
}