{
  "type": "Feature",
  "properties": {
    "iso:country":"ES",
    "sg:address":"Calle de Calendula (de La), 5",
    "sg:city":"Alcobendas",
    "sg:orig_category":"Ropa Para Se\u00d1oras (al Por Menor)",
    "sg:phone":"+34 916 50 00 60",
    "sg:postcode":"28109",
    "sg:province":"Madrid",
    "wof:name":"Gallovich Premus Luisa",
    "wof:placetype":"venue"
},
  "geometry": {"coordinates":[-3.6471745968,40.5243301392],"type":"Point"}
}