{
  "type": "Feature",
  "properties": {
    "addr:full":"Calle de Arroyo Fontarron, 1 Madrid Madrid 28030",
    "addr:housenumber":"1",
    "addr:postcode":"28030",
    "addr:street":"Calle De Arroyo Fontarron",
    "iso:country":"ES",
    "sg:address":"Calle de Arroyo Fontarron, 1",
    "sg:city":"Madrid",
    "sg:orig_category":"Peluqueros: De Se\u00d1oras",
    "sg:phone":"+34 914 39 30 10",
    "sg:postcode":"28030",
    "sg:province":"Madrid",
    "wof:name":"Lolitta 2005 S.l.",
    "wof:placetype":"venue"
},
  "geometry": {"coordinates":[-3.6509172916,40.4047164917],"type":"Point"}
}