{
  "type": "Feature",
  "properties": {
    "addr:full":"Calle de Cardenal Zapata, 4 Cadiz C\u00e1diz 11004",
    "addr:housenumber":"4",
    "addr:postcode":"11004",
    "addr:street":"Calle De Cardenal Zapata",
    "iso:country":"ES",
    "sg:address":"Calle de Cardenal Zapata, 4",
    "sg:city":"Cadiz",
    "sg:orig_category":"Bisuter\u00cda, Joyer\u00cda, Relojer\u00cda (al Por Menor)",
    "sg:phone":"+34 956 22 37 00",
    "sg:postcode":"11004",
    "sg:province":"C\u00e1diz",
    "wof:name":"Rodriguez Robles Esteban",
    "wof:placetype":"venue"
},
  "geometry": {"coordinates":[-6.2948651314,36.5320892334],"type":"Point"}
}