{
  "type": "Feature",
  "properties": {
    "iso:country":"ES",
    "sg:address":"Calle de Padre Basabe, 12",
    "sg:city":"Castro Urdiales",
    "sg:orig_category":"Centros Empresariales",
    "sg:phone":"+34 942 86 80 05",
    "sg:postcode":"39700",
    "sg:province":"Cantabria",
    "wof:name":"Apodaca Ugalde Zurine",
    "wof:placetype":"venue"
},
  "geometry": {"coordinates":[-3.2279603481,43.3902893066],"type":"Point"}
}