{
  "type": "Feature",
  "properties": {
    "iso:country":"ES",
    "sg:address":"Plaz Profesor Tamarit Olmos, 15",
    "sg:city":"Valencia",
    "sg:orig_category":"Ropa Para Se\u00d1oras (al Por Menor)",
    "sg:phone":"+34 963 62 81 42",
    "sg:postcode":"46010",
    "sg:province":"Valencia",
    "wof:name":"Cervantes Dalmau Josefa Laura",
    "wof:placetype":"venue"
},
  "geometry": {"coordinates":[-0.3624010086,39.4801254272],"type":"Point"}
}