{
  "type": "Feature",
  "properties": {
    "addr:full":"Luga Darsena Pesquera, S/n San Andres Santa Cruz De Tenerife 38120",
    "addr:housenumber":"s / n",
    "addr:postcode":"38120",
    "addr:street":"Pesquera",
    "iso:country":"ES",
    "sg:address":"Luga Darsena Pesquera, S/n",
    "sg:city":"San Andres",
    "sg:orig_category":"Congelados: Productos Alimentarios (fabricaci\u00d3n, Al Por Mayor)",
    "sg:phone":"+34 922 54 90 45",
    "sg:postcode":"38120",
    "sg:province":"Santa Cruz De Tenerife",
    "wof:name":"Frigorificos De Tenerife S. A.",
    "wof:placetype":"venue"
},
  "geometry": {"coordinates":[-16.2060050964,28.4980163574],"type":"Point"}
}