{
  "type": "Feature",
  "properties": {
    "addr:full":"Calle de San Cristobal, 6 Orihuela Alicante 03300",
    "addr:housenumber":"6",
    "addr:postcode":"03300",
    "addr:street":"Calle De San Cristobal",
    "iso:country":"ES",
    "sg:address":"Calle de San Cristobal, 6",
    "sg:city":"Orihuela",
    "sg:orig_category":"Mec\u00c1nico Del Autom\u00d3vil",
    "sg:phone":"+34 965 30 45 65",
    "sg:postcode":"03300",
    "sg:province":"Alicante",
    "wof:name":"Garcia Tarancon Francisco",
    "wof:placetype":"venue"
},
  "geometry": {"coordinates":[-0.9497079849,38.0831832886],"type":"Point"}
}