{
  "type": "Feature",
  "properties": {
    "iso:country":"ES",
    "sg:address":"Urb Pueblo Nuevo, 3",
    "sg:city":"Algarrobo-costa",
    "sg:orig_category":"Peritos Mar\u00cdtimos",
    "sg:phone":"+34 952 51 17 85",
    "sg:postcode":"29750",
    "sg:province":"M\u00e1laga",
    "wof:name":"Urban  Erwin",
    "wof:placetype":"venue"
},
  "geometry": {"coordinates":[-4.0544939041,36.7473487854],"type":"Point"}
}