{
  "type": "Feature",
  "properties": {
    "addr:full":"Carnoedo, 22 Sada La Coru\u00f1a 15160",
    "addr:housenumber":"22",
    "addr:postcode":"15160",
    "addr:street":"Carnoedo;La",
    "iso:country":"ES",
    "sg:address":"Carnoedo, 22",
    "sg:city":"Sada",
    "sg:orig_category":"Mec\u00c1nico Del Autom\u00d3vil",
    "sg:phone":"+34 981 62 13 62",
    "sg:postcode":"15160",
    "sg:province":"La Coru\u00f1a",
    "wof:name":"Garcia Doval Angeles",
    "wof:placetype":"venue"
},
  "geometry": {"coordinates":[-8.2548141479,43.3510665894],"type":"Point"}
}