{
  "type": "Feature",
  "properties": {
    "iso:country":"ES",
    "sg:address":"Calle de Bahia De Cadiz, 13",
    "sg:city":"Madrid",
    "sg:orig_category":"Marketing Directo",
    "sg:phone":"+34 913 29 30 96",
    "sg:postcode":"28042",
    "sg:province":"Madrid",
    "wof:name":"R.p.c. Marketing Y Publicidad S.l.",
    "wof:placetype":"venue"
},
  "geometry": {"coordinates":[-3.5946121216,40.4623184204],"type":"Point"}
}