{
  "type": "Feature",
  "properties": {
    "iso:country":"ES",
    "sg:address":"Avda Carlos Pelaez, S/n",
    "sg:city":"Navia",
    "sg:orig_category":"Complementos De Vestir (al Por Menor)",
    "sg:phone":"+34 985 47 37 50",
    "sg:postcode":"33710",
    "sg:province":"Asturias",
    "wof:name":"Mendez Martinez Oliva",
    "wof:placetype":"venue"
},
  "geometry": {"coordinates":[-6.7219052315,43.5399971008],"type":"Point"}
}