{
  "type": "Feature",
  "properties": {
    "iso:country":"ES",
    "sg:address":"Calle de Mariano Ron, 1",
    "sg:city":"Getafe",
    "sg:orig_category":"Abogados",
    "sg:phone":"+34 916 83 23 70",
    "sg:postcode":"28901",
    "sg:province":"Madrid",
    "wof:name":"Amador Donaire Camargo Juan",
    "wof:placetype":"venue"
},
  "geometry": {"coordinates":[-3.7299923897,40.306728363],"type":"Point"}
}