{
  "type": "Feature",
  "properties": {
    "iso:country":"ES",
    "sg:address":"Calle de Oporto, 18",
    "sg:city":"Torre-pacheco",
    "sg:orig_category":"Electrodom\u00c9sticos (al Por Menor)",
    "sg:phone":"+34 968 58 51 80",
    "sg:postcode":"30700",
    "sg:province":"Murcia",
    "wof:name":"Electrodomesticos J.f.torrepacheco S.l.",
    "wof:placetype":"venue"
},
  "geometry": {"coordinates":[-1.1302490234,37.9829597473],"type":"Point"}
}