{
  "type": "Feature",
  "properties": {
    "iso:country":"ES",
    "sg:address":"Montorre Kalea, S/n",
    "sg:city":"Derio",
    "sg:orig_category":"Fabricaci\u00d3n Y Comercio De M\u00c1quinas",
    "sg:phone":"+34 944 54 40 24",
    "sg:postcode":"48160",
    "sg:province":"Vizcaya",
    "wof:name":"Maquina Herramienta Bizkaia S.l",
    "wof:placetype":"venue"
},
  "geometry": {"coordinates":[-2.8869380951,43.2908973694],"type":"Point"}
}