{
  "type": "Feature",
  "properties": {
    "iso:country":"ES",
    "sg:address":"Calle de Segovia, 24",
    "sg:city":"Burgos",
    "sg:orig_category":"Fabricaci\u00d3n, Importaci\u00d3n, Venta De Material De Telefon\u00cda, Peritelefon\u00cda",
    "sg:phone":"+34 947 25 70 11",
    "sg:postcode":"09004",
    "sg:province":"Burgos",
    "wof:name":"Telycal S.l.",
    "wof:placetype":"venue"
},
  "geometry": {"coordinates":[-3.6893088818,42.3455314636],"type":"Point"}
}