{
  "type": "Feature",
  "properties": {
    "addr:full":"Calle de Rastrojo, 5 Valladolid Valladolid 47014",
    "addr:housenumber":"5",
    "addr:postcode":"47014",
    "addr:street":"Calle De Rastrojo",
    "iso:country":"ES",
    "sg:address":"Calle de Rastrojo, 5",
    "sg:city":"Valladolid",
    "sg:orig_category":"Librer\u00cdas",
    "sg:phone":"+34 983 34 40 80",
    "sg:postcode":"47014",
    "sg:province":"Valladolid",
    "wof:name":"Lopez Lopez Beatriz",
    "wof:placetype":"venue"
},
  "geometry": {"coordinates":[-4.7442884445,41.6512451172],"type":"Point"}
}