{
  "type": "Feature",
  "properties": {
    "addr:full":"Calle de Olof Palme, S/n Badajoz Badajoz 06009",
    "addr:housenumber":"s / n",
    "addr:postcode":"06009",
    "addr:street":"Calle De Olof Palme",
    "iso:country":"ES",
    "sg:address":"Calle de Olof Palme, S/n",
    "sg:city":"Badajoz",
    "sg:orig_category":"Papeler\u00cdas, Librer\u00cdas",
    "sg:phone":"+34 924 26 23 16",
    "sg:postcode":"06009",
    "sg:province":"Badajoz",
    "wof:name":"Sanchez Zamora Ines Maria",
    "wof:placetype":"venue"
},
  "geometry": {"coordinates":[-6.9546141624,38.8717498779],"type":"Point"}
}