{
  "type": "Feature",
  "properties": {
    "addr:full":"Calle de Guindos, 3 Madrid Madrid 28029",
    "addr:housenumber":"3",
    "addr:postcode":"28029",
    "addr:street":"Calle De Guindos",
    "iso:country":"ES",
    "sg:address":"Calle de Guindos, 3",
    "sg:city":"Madrid",
    "sg:orig_category":"Metacrilato: Art\u00cdculos (fabricaci\u00d3n Y Al Por Mayor)",
    "sg:phone":"+34 913 14 90 66",
    "sg:postcode":"28029",
    "sg:province":"Madrid",
    "wof:name":"Rodriguez Gonzalez Manuel",
    "wof:placetype":"venue"
},
  "geometry": {"coordinates":[-3.699819088,40.4664611816],"type":"Point"}
}