{
  "type": "Feature",
  "properties": {
    "iso:country":"ES",
    "sg:address":"Vieja, S/n",
    "sg:city":"Tapia Casariego",
    "sg:orig_category":"Mercer\u00cda, Lencer\u00cda (al Por Menor)",
    "sg:phone":"+34 985 47 28 20",
    "sg:postcode":"33740",
    "sg:province":"Asturias",
    "wof:name":"Perez Gonzalez Maria Luisa",
    "wof:placetype":"venue"
},
  "geometry": {"coordinates":[-6.9426078796,43.5692253113],"type":"Point"}
}