{
  "type": "Feature",
  "properties": {
    "iso:country":"ES",
    "sg:address":"Avda Galtzaraborda, 50",
    "sg:city":"Errenteria",
    "sg:orig_category":"Electrodom\u00c9sticos (fabricaci\u00d3n, Al Por Mayor)",
    "sg:phone":"+34 943 51 40 49",
    "sg:postcode":"20100",
    "sg:province":"Guip\u00f9zcoa",
    "wof:name":"Torre Ortega Esperanza",
    "wof:placetype":"venue"
},
  "geometry": {"coordinates":[-1.9110159874,43.3111801147],"type":"Point"}
}