{
  "type": "Feature",
  "properties": {
    "addr:full":"Calle de Teobaldo Power, 6 Santa Cruz De Tenerife Santa Cruz De Tenerife 38002",
    "addr:housenumber":"6",
    "addr:postcode":"38002",
    "addr:street":"Calle De Teobaldo Power",
    "iso:country":"ES",
    "sg:address":"Calle de Teobaldo Power, 6",
    "sg:city":"Santa Cruz De Tenerife",
    "sg:orig_category":"Abogados",
    "sg:phone":"+34 922 28 75 50",
    "sg:postcode":"38002",
    "sg:province":"Santa Cruz De Tenerife",
    "wof:name":"Reyes Alonso Araceli",
    "wof:placetype":"venue"
},
  "geometry": {"coordinates":[-16.2518615723,28.4677429199],"type":"Point"}
}