{
  "type": "Feature",
  "properties": {
    "addr:full":"Calle de Norias, 125 Majadahonda Madrid 28220",
    "addr:housenumber":"125",
    "addr:postcode":"28220",
    "addr:street":"Calle De Norias",
    "iso:country":"ES",
    "sg:address":"Calle de Norias, 125",
    "sg:city":"Majadahonda",
    "sg:orig_category":"Periodistas Profesionales",
    "sg:phone":"+34 916 34 64 08",
    "sg:postcode":"28220",
    "sg:province":"Madrid",
    "wof:name":"Rodriguez Lopez Carlos",
    "wof:placetype":"venue"
},
  "geometry": {"coordinates":[-3.8688089848,40.4712905884],"type":"Point"}
}