{
  "type": "Feature",
  "properties": {
    "addr:full":"Carrer de Barcelona, 11 Manresa Barcelona 08242",
    "addr:housenumber":"11",
    "addr:postcode":"08242",
    "addr:street":"Carrer De Barcelona",
    "iso:country":"ES",
    "sg:address":"Carrer de Barcelona, 11",
    "sg:city":"Manresa",
    "sg:orig_category":"Comercio, Reparaci\u00d3n De Bicicletas, De Motocicletas, De Accesorios",
    "sg:phone":"+34 938 74 23 58",
    "sg:postcode":"08242",
    "sg:province":"Barcelona",
    "wof:name":"Fa-sol S. A.",
    "wof:placetype":"venue"
},
  "geometry": {"coordinates":[1.822576046,41.7306442261],"type":"Point"}
}