{
  "type": "Feature",
  "properties": {
    "addr:full":"Calle de Parque Eugenia De Montijo, 46 Madrid Madrid 28047",
    "addr:housenumber":"46",
    "addr:postcode":"madrid;28047",
    "addr:street":"Calle De Parque Eugenia De Montijo",
    "iso:country":"ES",
    "sg:address":"Calle de Parque Eugenia De Montijo, 46",
    "sg:city":"Madrid",
    "sg:orig_category":"Agencias Y Agentes Comerciales, Representantes",
    "sg:phone":"+34 914 61 58 74",
    "sg:postcode":"28047",
    "sg:province":"Madrid",
    "wof:name":"Palacios Moreno Benigno",
    "wof:placetype":"venue"
},
  "geometry": {"coordinates":[-3.7532699108,40.3788375854],"type":"Point"}
}