{
  "type": "Feature",
  "properties": {
    "iso:country":"ES",
    "sg:address":"Calle de Coronacion De La Virgen Blanca, 10",
    "sg:city":"Vitoria-gasteiz",
    "sg:orig_category":"Panader\u00cdas, Panader\u00cdas",
    "sg:phone":"+34 945 14 04 51",
    "sg:postcode":"01012",
    "sg:province":"\u00c1lava",
    "wof:name":"Vermuyten Gascon Guillermo",
    "wof:placetype":"venue"
},
  "geometry": {"coordinates":[-2.6758999825,42.8523483276],"type":"Point"}
}