{
  "type": "Feature",
  "properties": {
    "addr:full":"Carr Emporda, 32 Badalona Barcelona 08917",
    "addr:housenumber":"32",
    "addr:postcode":"08917",
    "addr:street":"Carr Emporda",
    "iso:country":"ES",
    "sg:address":"Carr Emporda, 32",
    "sg:city":"Badalona",
    "sg:orig_category":"Peluqueros: De Se\u00d1oras",
    "sg:phone":"+34 934 60 03 51",
    "sg:postcode":"08917",
    "sg:province":"Barcelona",
    "wof:name":"Vazquez Perez Rosa",
    "wof:placetype":"venue"
},
  "geometry": {"coordinates":[2.2375121117,41.4526405334],"type":"Point"}
}