{
  "type": "Feature",
  "properties": {
    "addr:full":"Iberre Edificio 2, 2 Sondika Vizcaya 48150",
    "addr:housenumber":"2",
    "addr:postcode":"48150",
    "iso:country":"ES",
    "sg:address":"Iberre Edificio 2, 2",
    "sg:city":"Sondika",
    "sg:orig_category":"Empresarios",
    "sg:phone":"+34 944 06 05 35",
    "sg:postcode":"48150",
    "sg:province":"Vizcaya",
    "wof:name":"Pinturas Y Reparaciones Ferpal, S.l.",
    "wof:placetype":"venue"
},
  "geometry": {"coordinates":[-2.937153101,43.2957115173],"type":"Point"}
}