{
  "type": "Feature",
  "properties": {
    "iso:country":"ES",
    "sg:address":"Calle de General Mu\u00d1oz Arenillas, 2",
    "sg:city":"Cadiz",
    "sg:orig_category":"M\u00c9dicos: Estomatolog\u00cda",
    "sg:phone":"+34 956 25 85 54",
    "sg:postcode":"11010",
    "sg:province":"C\u00e1diz",
    "wof:name":"Abalo Rabello Francisco",
    "wof:placetype":"venue"
},
  "geometry": {"coordinates":[-6.275437,36.504623],"type":"Point"}
}