{
  "type": "Feature",
  "properties": {
    "iso:country":"ES",
    "sg:address":"Avgd President Companys, 124",
    "sg:city":"Badalona",
    "sg:orig_category":"Asesor\u00cda Sobre Comunicaci\u00d3n De Empresas",
    "sg:phone":"+34 933 84 75 30",
    "sg:postcode":"08911",
    "sg:province":"Barcelona",
    "wof:name":"Consulting Y Gestion Integral 87 S.l.",
    "wof:placetype":"venue"
},
  "geometry": {"coordinates":[2.2484390736,41.455368042],"type":"Point"}
}