{
  "type": "Feature",
  "properties": {
    "addr:full":"Avda Constitucion (la), 30 Sevilla Sevilla 41001",
    "addr:housenumber":"30",
    "addr:postcode":"41001",
    "addr:street":"Avda Constitucion La",
    "iso:country":"ES",
    "sg:address":"Avda Constitucion (la), 30",
    "sg:city":"Sevilla",
    "sg:orig_category":"Centros Empresariales",
    "sg:phone":"+34 954 22 40 63",
    "sg:postcode":"41001",
    "sg:province":"Sevilla",
    "wof:name":"Union Espa\u00d1ola De Entidades Aseguradoras Reaseguradoras",
    "wof:placetype":"venue"
},
  "geometry": {"coordinates":[-5.9939289093,37.3851890564],"type":"Point"}
}