{
  "type": "Feature",
  "properties": {
    "iso:country":"ES",
    "sg:address":"Calle de Jardines, 25",
    "sg:city":"Linea De La Concepcion",
    "sg:orig_category":"Iglesia Cat\u00d3lica",
    "sg:phone":"+34 956 76 06 22",
    "sg:postcode":"11300",
    "sg:province":"C\u00e1diz",
    "wof:name":"Parroquia Santiago Apostol",
    "wof:placetype":"venue"
},
  "geometry": {"coordinates":[-5.3473091125,36.1622772217],"type":"Point"}
}