{
  "type": "Feature",
  "properties": {
    "addr:full":"Av Verdaguer, 36 Pobla Segur Lleida 25500",
    "addr:housenumber":"36",
    "addr:postcode":"25500",
    "addr:street":"Av Verdaguer",
    "iso:country":"ES",
    "sg:address":"Av Verdaguer, 36",
    "sg:city":"Pobla Segur",
    "sg:orig_category":"Serrer\u00cdas De Madera",
    "sg:phone":"+34 973 68 02 68",
    "sg:postcode":"25500",
    "sg:province":"Lleida",
    "wof:name":"Mobles Comenje S.l.",
    "wof:placetype":"venue"
},
  "geometry": {"coordinates":[0.9664350152,42.2486915588],"type":"Point"}
}