{
  "type": "Feature",
  "properties": {
    "iso:country":"ES",
    "sg:address":"Calle de Cofa, 16",
    "sg:city":"Lepe",
    "sg:orig_category":"Muebles",
    "sg:phone":"+34 959 38 36 65",
    "sg:postcode":"21440",
    "sg:province":"Huelva",
    "wof:name":"Pabama S.l.",
    "wof:placetype":"venue"
},
  "geometry": {"coordinates":[-7.1981878281,37.2626991272],"type":"Point"}
}