{
  "type": "Feature",
  "properties": {
    "iso:country":"ES",
    "sg:address":"Carrer de Major De Sarria, 2",
    "sg:city":"Barcelona",
    "sg:orig_category":"Perfumer\u00cda (al Por Menor)",
    "sg:phone":"+34 932 03 48 85",
    "sg:postcode":"08017",
    "sg:province":"Barcelona",
    "wof:name":"Fernandez Equizabal Nuria",
    "wof:placetype":"venue"
},
  "geometry": {"coordinates":[2.1253330708,41.395942688],"type":"Point"}
}