{
  "type": "Feature",
  "properties": {
    "addr:full":"Calle de Torres (de Las), 11 Cuenca Cuenca 16001",
    "addr:housenumber":"11",
    "addr:postcode":"16001",
    "addr:street":"Calle De Torres De Las",
    "iso:country":"ES",
    "sg:address":"Calle de Torres (de Las), 11",
    "sg:city":"Cuenca",
    "sg:orig_category":"Automatizaci\u00d3n De Procesos Industriales Y De Edificaci\u00d3n (estudios, Instalaci\u00d3n)",
    "sg:phone":"+34 969 23 10 25",
    "sg:postcode":"16001",
    "sg:province":"Cuenca",
    "wof:name":"Dolz Mora Antonio",
    "wof:placetype":"venue"
},
  "geometry": {"coordinates":[-2.1322460175,40.0732536316],"type":"Point"}
}