{
  "type": "Feature",
  "properties": {
    "iso:country":"ES",
    "sg:address":"Plaz Viejo Coso, 2",
    "sg:city":"Valladolid",
    "sg:orig_category":"Arquitectos",
    "sg:phone":"+34 983 37 02 90",
    "sg:postcode":"47003",
    "sg:province":"Valladolid",
    "wof:name":"De Los Ojos Moral Jesus Angel",
    "wof:placetype":"venue"
},
  "geometry": {"coordinates":[-4.7321238518,41.6541938782],"type":"Point"}
}