{
  "type": "Feature",
  "properties": {
    "iso:country":"ES",
    "sg:address":"Calle de Pedro De Valdivia, 27",
    "sg:city":"Madrid",
    "sg:orig_category":"Centros Empresariales",
    "sg:phone":"+34 915 63 13 95",
    "sg:postcode":"28006",
    "sg:province":"Madrid",
    "wof:name":"El Soto Del Retamar S.l",
    "wof:placetype":"venue"
},
  "geometry": {"coordinates":[-3.6802220345,40.4389419556],"type":"Point"}
}