{
  "type": "Feature",
  "properties": {
    "iso:country":"ES",
    "sg:address":"Carrer de Piques, 2",
    "sg:city":"Manresa",
    "sg:orig_category":"Procuradores",
    "sg:phone":"+34 938 72 31 32",
    "sg:postcode":"08241",
    "sg:province":"Barcelona",
    "wof:name":"Comas Masana Joan",
    "wof:placetype":"venue"
},
  "geometry": {"coordinates":[1.8254779577,41.7232131958],"type":"Point"}
}