{
  "type": "Feature",
  "properties": {
    "iso:country":"ES",
    "sg:address":"Avda Marcos Redondo, 27",
    "sg:city":"Pozoblanco",
    "sg:orig_category":"Laboratorios Y Cl\u00cdnicas Veterinarias",
    "sg:phone":"+34 957 77 30 84",
    "sg:postcode":"14400",
    "sg:province":"C\u00f3rdoba",
    "wof:name":"Lopez Carpio Maria Del Carmen",
    "wof:placetype":"venue"
},
  "geometry": {"coordinates":[-4.8507671356,38.3829612732],"type":"Point"}
}