{
  "type": "Feature",
  "properties": {
    "addr:full":"Calle de Calidad (de La), 4 Adaro Madrid 28906",
    "addr:housenumber":"4",
    "addr:postcode":"28906",
    "addr:street":"Calle De Calidad De La",
    "iso:country":"ES",
    "sg:address":"Calle de Calidad (de La), 4",
    "sg:city":"Adaro",
    "sg:orig_category":"Mec\u00c1nico Del Autom\u00d3vil",
    "sg:phone":"+34 916 01 04 39",
    "sg:postcode":"28906",
    "sg:province":"Madrid",
    "wof:name":"Talleres Osvima S.a.",
    "wof:placetype":"venue"
},
  "geometry": {"coordinates":[-3.7003455162,40.4166908264],"type":"Point"}
}