{
  "type": "Feature",
  "properties": {
    "iso:country":"ES",
    "sg:address":"Av. Bayona, S/n",
    "sg:city":"Iru\u00f1a",
    "sg:orig_category":"Muebles Y Accesorios Para Cocinas Y Cuartos De Ba\u00d1o (al Por Menor)",
    "sg:phone":"+34 948 26 34 98",
    "sg:postcode":"31011",
    "sg:province":"Navarra",
    "wof:name":"Jimenez Vicente Jose Joaquin",
    "wof:placetype":"venue"
},
  "geometry": {"coordinates":[-1.6564190388,42.8148384094],"type":"Point"}
}