{
  "type": "Feature",
  "properties": {
    "addr:full":"Calle de Marques De Teverga, 16 Oviedo Asturias 33005",
    "addr:housenumber":"16",
    "addr:postcode":"33005",
    "addr:street":"Calle De Marques De Teverga",
    "iso:country":"ES",
    "sg:address":"Calle de Marques De Teverga, 16",
    "sg:city":"Oviedo",
    "sg:orig_category":"Arquitectos",
    "sg:phone":"+34 985 23 06 66",
    "sg:postcode":"33005",
    "sg:province":"Asturias",
    "wof:name":"Baldo Sierra Jose",
    "wof:placetype":"venue"
},
  "geometry": {"coordinates":[-5.856180191,43.3617210388],"type":"Point"}
}