{
  "type": "Feature",
  "properties": {
    "addr:full":"Avda Santiago, S/n Viana Navarra 31230",
    "addr:housenumber":"s",
    "addr:postcode":"31230",
    "addr:street":"Avda Santiago;/ N",
    "iso:country":"ES",
    "sg:address":"Avda Santiago, S/n",
    "sg:city":"Viana",
    "sg:orig_category":"Producci\u00d3n, Comercio De Cereales",
    "sg:phone":"+34 948 64 57 12",
    "sg:postcode":"31230",
    "sg:province":"Navarra",
    "wof:name":"Cereales Barco S.l.",
    "wof:placetype":"venue"
},
  "geometry": {"coordinates":[-2.3663990498,42.5153465271],"type":"Point"}
}