{
  "type": "Feature",
  "properties": {
    "addr:full":"Calle de Calvo Sotelo, 24 Orotava Santa Cruz De Tenerife 38300",
    "addr:housenumber":"24",
    "addr:postcode":"38300",
    "addr:street":"Calle De Calvo Sotelo",
    "iso:country":"ES",
    "sg:address":"Calle de Calvo Sotelo, 24",
    "sg:city":"Orotava",
    "sg:classifiers":[
        {
            "category":"Personal",
            "subcategory":"Barber",
            "type":"Services"
        }
    ],
    "sg:phone":"+34 922 32 00 44",
    "sg:postcode":"38300",
    "sg:province":"Santa Cruz De Tenerife",
    "sg:tags":[
        "caballeros",
        "de",
        "peluqueros"
    ],
    "wof:name":"Gonzalez Hernandez Antonio",
    "wof:placetype":"venue"
},
  "geometry": {"coordinates":[-16.5245952606,28.3857860565],"type":"Point"}
}