{
  "type": "Feature",
  "properties": {
    "addr:full":"Avda Centurion, 24 Estepa Sevilla 41560",
    "addr:housenumber":"24",
    "addr:postcode":"41560",
    "addr:street":"Avda Centurion;Sevilla",
    "iso:country":"ES",
    "sg:address":"Avda Centurion, 24",
    "sg:city":"Estepa",
    "sg:orig_category":"Pescader\u00cdas (al Por Menor)",
    "sg:phone":"+34 954 82 05 47",
    "sg:postcode":"41560",
    "sg:province":"Sevilla",
    "wof:name":"Arias Gonzalez Jose Antonio",
    "wof:placetype":"venue"
},
  "geometry": {"coordinates":[-4.885114193,37.2898712158],"type":"Point"}
}