{
  "type": "Feature",
  "properties": {
    "addr:full":"Calle de Alfares (los), 16 Alcorcon Madrid 28921",
    "addr:housenumber":"16",
    "addr:postcode":"28921",
    "addr:street":"Calle De Alfares Los",
    "iso:country":"ES",
    "sg:address":"Calle de Alfares (los), 16",
    "sg:city":"Alcorcon",
    "sg:orig_category":"Material Y Suministros Para Peluquer\u00cda",
    "sg:phone":"+34 916 44 38 03",
    "sg:postcode":"28921",
    "sg:province":"Madrid",
    "wof:name":"Romeral Frias Maria Paloma",
    "wof:placetype":"venue"
},
  "geometry": {"coordinates":[-3.8293302059,40.3467597961],"type":"Point"}
}