{
  "type": "Feature",
  "properties": {
    "iso:country":"ES",
    "sg:address":"Carr Sta Joaquima Vedruna, S/n",
    "sg:city":"Igualada",
    "sg:orig_category":"Carnicer\u00cdas, Carnicer\u00cdas",
    "sg:phone":"+34 938 04 41 07",
    "sg:postcode":"08700",
    "sg:province":"Barcelona",
    "wof:name":"Carns Clotet",
    "wof:placetype":"venue"
},
  "geometry": {"coordinates":[1.6255799532,41.5788192749],"type":"Point"}
}