{
  "type": "Feature",
  "properties": {
    "iso:country":"ES",
    "sg:address":"Calle de Salvador Allende, 16",
    "sg:city":"Torremolinos",
    "sg:orig_category":"Inmobiliaria (agencias)",
    "sg:phone":"+34 952 05 26 20",
    "sg:postcode":"29620",
    "sg:province":"M\u00e1laga",
    "wof:name":"Asesores Dives S.l.",
    "wof:placetype":"venue"
},
  "geometry": {"coordinates":[-4.5095825195,36.6033058167],"type":"Point"}
}