{
  "type": "Feature",
  "properties": {
    "addr:full":"Plaz Mayor, 5 Torrejoncillo C\u00e1ceres 10830",
    "addr:housenumber":"5",
    "addr:postcode":"10830",
    "addr:street":"Plaz Mayor;Ca\u0301Ceres",
    "iso:country":"ES",
    "sg:address":"Plaz Mayor, 5",
    "sg:city":"Torrejoncillo",
    "sg:orig_category":"Cajas De Ahorro",
    "sg:phone":"+34 927 30 30 70",
    "sg:postcode":"10830",
    "sg:province":"C\u00e1ceres",
    "wof:name":"Caja De Ahorros Y Monte De Piedad De Extremadura",
    "wof:placetype":"venue"
},
  "geometry": {"coordinates":[-6.4710850716,39.8993377686],"type":"Point"}
}