{
  "type": "Feature",
  "properties": {
    "iso:country":"ES",
    "sg:address":"Avda Andalucia (de), 85",
    "sg:city":"Alcala Rio",
    "sg:orig_category":"Zapatos (al Por Menor)",
    "sg:phone":"+34 955 65 13 58",
    "sg:postcode":"41200",
    "sg:province":"Sevilla",
    "wof:name":"Cobos Aguilera Manuel",
    "wof:placetype":"venue"
},
  "geometry": {"coordinates":[-5.9803290367,37.5207901001],"type":"Point"}
}