{
  "type": "Feature",
  "properties": {
    "iso:country":"ES",
    "sg:address":"Calle de Lanbarketa, 3",
    "sg:city":"Lambarketa",
    "sg:orig_category":"Inmobiliaria (agencias)",
    "sg:phone":"+34 946 71 04 03",
    "sg:postcode":"48480",
    "sg:province":"Vizcaya",
    "wof:name":"La\u00f1omendi S.l.",
    "wof:placetype":"venue"
},
  "geometry": {"coordinates":[-2.8896090984,43.2052345276],"type":"Point"}
}