{
  "type": "Feature",
  "properties": {
    "iso:country":"ES",
    "sg:address":"Plaz San Vicente, 17",
    "sg:city":"Vall D'uixo",
    "sg:classifiers":[
        {
            "category":"Personal",
            "subcategory":"Barber",
            "type":"Services"
        }
    ],
    "sg:phone":"+34 964 66 04 40",
    "sg:postcode":"12600",
    "sg:province":"Castell\u00f3n",
    "sg:tags":[
        "caballeros",
        "de",
        "peluqueros"
    ],
    "wof:name":"Latorre Beltran Vicente",
    "wof:placetype":"venue"
},
  "geometry": {"coordinates":[-0.0482099988,39.992477417],"type":"Point"}
}