{
  "type": "Feature",
  "properties": {
    "iso:country":"ES",
    "sg:address":"Calle de Corchito, S/n",
    "sg:city":"Torrejon El Rubio",
    "sg:orig_category":"Empresarios",
    "sg:phone":"+34 927 45 50 79",
    "sg:postcode":"10694",
    "sg:province":"C\u00e1ceres",
    "wof:name":"Fernandez Perez Vicente",
    "wof:placetype":"venue"
},
  "geometry": {"coordinates":[-6.0088200569,39.7707901001],"type":"Point"}
}