{
  "type": "Feature",
  "properties": {
    "addr:full":"Calle de Santiago Fernandez Portoles, 3 Tudela Navarra 31500",
    "addr:housenumber":"3",
    "addr:postcode":"31500",
    "addr:street":"Calle De Santiago;Portoles",
    "iso:country":"ES",
    "sg:address":"Calle de Santiago Fernandez Portoles, 3",
    "sg:city":"Tudela",
    "sg:orig_category":"Asociaciones Y Clubs Deportivos",
    "sg:phone":"+34 948 82 66 95",
    "sg:postcode":"31500",
    "sg:province":"Navarra",
    "wof:name":"Mantenimiento Electromedico S. A.",
    "wof:placetype":"venue"
},
  "geometry": {"coordinates":[-1.6015230417,42.0551147461],"type":"Point"}
}