{
  "type": "Feature",
  "properties": {
    "iso:country":"ES",
    "sg:address":"Calle de Pepe Blanco, 8",
    "sg:city":"Logro\u00f1o",
    "sg:orig_category":"Asesor\u00cda De Formaci\u00d3n Y Gesti\u00d3n De Personal",
    "sg:phone":"+34 941 21 06 69",
    "sg:postcode":"26005",
    "sg:province":"La Rioja",
    "wof:name":"Riesgo Y Trabajo S.l.",
    "wof:placetype":"venue"
},
  "geometry": {"coordinates":[-2.4600560665,42.4598503113],"type":"Point"}
}