{
  "type": "Feature",
  "properties": {
    "iso:country":"ES",
    "sg:address":"Av Constitucio, 346",
    "sg:city":"Castelldefels",
    "sg:orig_category":"Electricidad: Instaladores",
    "sg:phone":"+34 936 64 21 02",
    "sg:postcode":"08860",
    "sg:province":"Barcelona",
    "wof:name":"Francisco Beltran Sanchez S.l.",
    "wof:placetype":"venue"
},
  "geometry": {"coordinates":[1.9563770294,41.2674827576],"type":"Point"}
}