{
  "type": "Feature",
  "properties": {
    "addr:full":"C/ Vicente Blasco Iba\u00d1ez, 68 Elche Alicante 03201",
    "addr:housenumber":"68",
    "addr:postcode":"03201",
    "addr:street":"C / Vicente Blasco Iban\u0303Ez",
    "iso:country":"ES",
    "sg:address":"C/ Vicente Blasco Iba\u00d1ez, 68",
    "sg:city":"Elche",
    "sg:orig_category":"M\u00c9dicos: Estomatolog\u00cda",
    "sg:phone":"+34 966 67 43 59",
    "sg:postcode":"03201",
    "sg:province":"Alicante",
    "wof:name":"Blasco Sansano Ramon",
    "wof:placetype":"venue"
},
  "geometry": {"coordinates":[-0.7046380043,38.2681007385],"type":"Point"}
}