{
  "type": "Feature",
  "properties": {
    "addr:full":"Calle de Tenerias, 5 Brea De Aragon Zaragoza 50246",
    "addr:housenumber":"5",
    "addr:postcode":"50246",
    "addr:street":"Calle De Tenerias",
    "iso:country":"ES",
    "sg:address":"Calle de Tenerias, 5",
    "sg:city":"Brea De Aragon",
    "sg:orig_category":"Zapatos: Material, Suministros, Accesorios (fabricaci\u00d3n, Al Por Mayor)",
    "sg:phone":"+34 976 82 46 09",
    "sg:postcode":"50246",
    "sg:province":"Zaragoza",
    "wof:name":"Troquelados Aragon S.l.",
    "wof:placetype":"venue"
},
  "geometry": {"coordinates":[-1.6013419628,41.5225982666],"type":"Point"}
}