{
  "type": "Feature",
  "properties": {
    "addr:full":"Industria (pol Ind La Borda), S/n Caldes Montbui Barcelona 08140",
    "addr:housenumber":"s",
    "addr:postcode":"08140",
    "addr:street":"/ N",
    "iso:country":"ES",
    "sg:address":"Industria (pol Ind La Borda), S/n",
    "sg:city":"Caldes Montbui",
    "sg:orig_category":"Tubos Met\u00c1licos",
    "sg:phone":"+34 902 37 53 75",
    "sg:postcode":"08140",
    "sg:province":"Barcelona",
    "sg:website":"www.protubsa.com",
    "wof:name":"Proveedora De Tubos Occidental S.l.",
    "wof:placetype":"venue"
},
  "geometry": {"coordinates":[2.1757800579,41.6282310486],"type":"Point"}
}