{
  "type": "Feature",
  "properties": {
    "iso:country":"ES",
    "sg:address":"Calle de Granada, 14",
    "sg:city":"Malaga",
    "sg:orig_category":"Telas Y Sedas (al Por Menor)",
    "sg:phone":"+34 952 22 44 39",
    "sg:postcode":"29015",
    "sg:province":"M\u00e1laga",
    "wof:name":"Colores De Malaga S.l.",
    "wof:placetype":"venue"
},
  "geometry": {"coordinates":[-4.4209651947,36.7216415405],"type":"Point"}
}