{
  "type": "Feature",
  "properties": {
    "addr:full":"Calle de Nicolas Rabal, 25 Soria Soria 42003",
    "addr:housenumber":"25",
    "addr:postcode":"42003",
    "addr:street":"Calle De Nicolas Rabal",
    "iso:country":"ES",
    "sg:address":"Calle de Nicolas Rabal, 25",
    "sg:city":"Soria",
    "sg:orig_category":"Bibliotecas, Mediatecas",
    "sg:phone":"+34 975 22 18 00",
    "sg:postcode":"42003",
    "sg:province":"Soria",
    "wof:name":"Delegacion Territorial De La Junta De Castilla Y Leon En Soria",
    "wof:placetype":"venue"
},
  "geometry": {"coordinates":[-2.4736740589,41.7626342773],"type":"Point"}
}