{
  "type": "Feature",
  "properties": {
    "iso:country":"ES",
    "sg:address":"A. Golf, 13",
    "sg:city":"Nueva Andalucia",
    "sg:orig_category":"Abogados",
    "sg:phone":"+34 952 81 11 07",
    "sg:postcode":"29660",
    "sg:province":"M\u00e1laga",
    "wof:name":"Balms Abogados Marbella S.l.",
    "wof:placetype":"venue"
},
  "geometry": {"coordinates":[-4.9587249756,36.5115852356],"type":"Point"}
}