{
  "type": "Feature",
  "properties": {
    "iso:country":"ES",
    "sg:address":"Calle de Canciller Ayala, 9",
    "sg:city":"Vitoria-gasteiz",
    "sg:orig_category":"Servicios De Higiene Y Peluquer\u00cda Para Perros Y Gatos",
    "sg:phone":"+34 945 28 58 45",
    "sg:postcode":"01004",
    "sg:province":"\u00c1lava",
    "wof:name":"Francisco Javier Santamaria Agustin",
    "wof:placetype":"venue"
},
  "geometry": {"coordinates":[-2.6657412052,42.8432655334],"type":"Point"}
}