{
  "type": "Feature",
  "properties": {
    "addr:full":"Avda Martin Palomino, S/n Plasencia C\u00e1ceres 10600",
    "addr:housenumber":"s / n",
    "addr:postcode":"10600",
    "addr:street":"Avda Martin Palomino;Ca\u0301Ceres",
    "iso:country":"ES",
    "sg:address":"Avda Martin Palomino, S/n",
    "sg:city":"Plasencia",
    "sg:orig_category":"Supermercados Y Hipermercados",
    "sg:phone":"+34 927 42 20 61",
    "sg:postcode":"10600",
    "sg:province":"C\u00e1ceres",
    "wof:name":"Coaliment Castilla S.a.u.",
    "wof:placetype":"venue"
},
  "geometry": {"coordinates":[-6.1136288643,40.0063438416],"type":"Point"}
}