{
  "type": "Feature",
  "properties": {
    "iso:country":"ES",
    "sg:address":"Plaz Jose Maria Gonzalez Trevilla, 2",
    "sg:city":"Torrelavega",
    "sg:orig_category":"Molduras, Junquillos, Listones Y Molduras Perforadas",
    "sg:phone":"+34 942 89 31 97",
    "sg:postcode":"39300",
    "sg:province":"Cantabria",
    "wof:name":"Garcia Martinez Manuel",
    "wof:placetype":"venue"
},
  "geometry": {"coordinates":[-4.0503497124,43.3483848572],"type":"Point"}
}