{
  "type": "Feature",
  "properties": {
    "addr:full":"Calle de San Pio X, 2 Elorrio Vizcaya 48230",
    "addr:housenumber":"2",
    "addr:postcode":"48230",
    "addr:street":"Calle De San Pio X",
    "iso:country":"ES",
    "sg:address":"Calle de San Pio X, 2",
    "sg:city":"Elorrio",
    "sg:orig_category":"Caf\u00c9s, Bares, Cervecer\u00cdas",
    "sg:phone":"+34 946 82 03 52",
    "sg:postcode":"48230",
    "sg:province":"Vizcaya",
    "wof:name":"Gomez De Segura Gabiria Jose Carlos",
    "wof:placetype":"venue"
},
  "geometry": {"coordinates":[-2.5442380905,43.1303672791],"type":"Point"}
}