{
  "type": "Feature",
  "properties": {
    "iso:country":"ES",
    "sg:address":"Carrer de Galvani, 7",
    "sg:city":"Terrassa",
    "sg:orig_category":"Abogados",
    "sg:phone":"+34 937 33 71 55",
    "sg:postcode":"08224",
    "sg:province":"Barcelona",
    "wof:name":"Egara Advocats",
    "wof:placetype":"venue"
},
  "geometry": {"coordinates":[2.0035779476,41.5563011169],"type":"Point"}
}