{
  "type": "Feature",
  "properties": {
    "addr:full":"Calle de Alcala, 273 Madrid Madrid 28027",
    "addr:housenumber":"273",
    "addr:postcode":"28027",
    "addr:street":"Calle De Alcala",
    "iso:country":"ES",
    "sg:address":"Calle de Alcala, 273",
    "sg:city":"Madrid",
    "sg:orig_category":"Radiocomunicaciones, Telefon\u00cda M\u00d3vil, Radiomensajer\u00cda: Servicios, Comercializaci\u00d3n",
    "sg:phone":"+34 914 04 46 20",
    "sg:postcode":"28027",
    "sg:province":"Madrid",
    "wof:name":"Cebollero Jimenez Manuel",
    "wof:placetype":"venue"
},
  "geometry": {"coordinates":[-3.6559906006,40.4320335388],"type":"Point"}
}