{
  "type": "Feature",
  "properties": {
    "addr:full":"Carrer de Marti Costa, 9 Santa Perpetua De Mogoda Barcelona 08130",
    "addr:housenumber":"9",
    "addr:postcode":"08130",
    "addr:street":"Carrer De Marti Costa",
    "iso:country":"ES",
    "sg:address":"Carrer de Marti Costa, 9",
    "sg:city":"Santa Perpetua De Mogoda",
    "sg:orig_category":"Carnicer\u00cdas, Carnicer\u00cdas",
    "sg:phone":"+34 935 60 01 63",
    "sg:postcode":"08130",
    "sg:province":"Barcelona",
    "wof:name":"Subirats Vi\u00f1allonga Jaime",
    "wof:placetype":"venue"
},
  "geometry": {"coordinates":[2.1804940701,41.5352096558],"type":"Point"}
}