{
  "type": "Feature",
  "properties": {
    "iso:country":"ES",
    "sg:address":"Cmno Astui, 1",
    "sg:city":"Usansolo",
    "sg:orig_category":"Lencer\u00cda Femenina, Corseter\u00cda, Trajes De Ba\u00d1o (al Por Menor)",
    "sg:phone":"+34 944 56 76 87",
    "sg:postcode":"48960",
    "sg:province":"Vizcaya",
    "wof:name":"Arandia Artabe Esther",
    "wof:placetype":"venue"
},
  "geometry": {"coordinates":[-2.8171648979,43.2177658081],"type":"Point"}
}