{
  "type": "Feature",
  "properties": {
    "iso:country":"ES",
    "sg:address":"Plaz Guernica, S/n",
    "sg:city":"San Fernando De Henares",
    "sg:orig_category":"Organizaciones Internacionales",
    "sg:phone":"+34 916 69 44 11",
    "sg:postcode":"28830",
    "sg:province":"Madrid",
    "wof:name":"Cruz Roja Espa\u00f1ola",
    "wof:placetype":"venue"
},
  "geometry": {"coordinates":[-3.5242600441,40.4227523804],"type":"Point"}
}