{
  "type": "Feature",
  "properties": {
    "addr:full":"Calle de Medio, S/n Almeida De Sayago Zamora 49210",
    "addr:housenumber":"s / n",
    "addr:postcode":"49210",
    "addr:street":"Calle De Medio",
    "iso:country":"ES",
    "sg:address":"Calle de Medio, S/n",
    "sg:city":"Almeida De Sayago",
    "sg:orig_category":"Molduras, Junquillos, Listones Y Molduras Perforadas",
    "sg:phone":"+34 980 61 22 56",
    "sg:postcode":"49210",
    "sg:province":"Zamora",
    "wof:name":"Iglesia Hernandez Jose Luis De La",
    "wof:placetype":"venue"
},
  "geometry": {"coordinates":[-6.0782837868,41.2666816711],"type":"Point"}
}