{
  "type": "Feature",
  "properties": {
    "addr:full":"Cmno Hormigueras, 176 Madrid Madrid 28031",
    "addr:housenumber":"176",
    "addr:postcode":"28031",
    "addr:street":"Cmno Hormigueras",
    "iso:country":"ES",
    "sg:address":"Cmno Hormigueras, 176",
    "sg:city":"Madrid",
    "sg:orig_category":"Electricidad: Equipos Industriales, Componentes (fabricaci\u00d3n)",
    "sg:phone":"+34 917 77 27 82",
    "sg:postcode":"28031",
    "sg:province":"Madrid",
    "wof:name":"Maghispan Aparellaje Electrico S.l.",
    "wof:placetype":"venue"
},
  "geometry": {"coordinates":[-3.6304490566,40.3771018982],"type":"Point"}
}