{
  "type": "Feature",
  "properties": {
    "iso:country":"ES",
    "sg:address":"Pl. De Las Capeas, 7",
    "sg:city":"Jemenu\u00f1o",
    "sg:orig_category":"Iglesia Cat\u00d3lica",
    "sg:phone":"+34 921 17 70 13",
    "sg:postcode":"40135",
    "sg:province":"Segovia",
    "wof:name":"Obispado Segovia",
    "wof:placetype":"venue"
},
  "geometry": {"coordinates":[-4.4947161674,40.9477500916],"type":"Point"}
}