{
  "type": "Feature",
  "properties": {
    "iso:country":"ES",
    "sg:address":"Calle de Vi\u00d1uela La, 1",
    "sg:city":"Ag\u00fcimes",
    "sg:orig_category":"Asilos De Ancianos. Centros Privados",
    "sg:phone":"+34 928 78 41 34",
    "sg:postcode":"35260",
    "sg:province":"Las Palmas",
    "wof:name":"Mensajeros De La Paz S.c.p.",
    "wof:placetype":"venue"
},
  "geometry": {"coordinates":[-15.4478492737,27.90508461],"type":"Point"}
}