{
  "type": "Feature",
  "properties": {
    "iso:country":"ES",
    "sg:address":"Ctra. General-lece\u00f1es, 38",
    "sg:city":"Valdesoto",
    "sg:orig_category":"Bebidas",
    "sg:phone":"+34 985 73 43 08",
    "sg:postcode":"33938",
    "sg:province":"Asturias",
    "wof:name":"Vinos Somonte S.l.",
    "wof:placetype":"venue"
},
  "geometry": {"coordinates":[-5.6488599777,43.3655967712],"type":"Point"}
}