{
  "type": "Feature",
  "properties": {
    "addr:full":"Reina Sofia, 6 Llano De Brujas Murcia 30161",
    "addr:housenumber":"6",
    "addr:postcode":"30161",
    "addr:street":"Reina Sofia",
    "iso:country":"ES",
    "sg:address":"Reina Sofia, 6",
    "sg:city":"Llano De Brujas",
    "sg:orig_category":"Bazares, Art\u00cdculos De Limpieza Y De Cocina (al Por Menor)",
    "sg:phone":"+34 968 87 01 03",
    "sg:postcode":"30161",
    "sg:province":"Murcia",
    "wof:name":"Multiprecio Azahar S.l",
    "wof:placetype":"venue"
},
  "geometry": {"coordinates":[-1.0691549778,38.0071029663],"type":"Point"}
}