{
  "type": "Feature",
  "properties": {
    "iso:country":"ES",
    "sg:address":"Calle de Estacion, 17",
    "sg:city":"Miranda Ebro",
    "sg:orig_category":"Laboratorios Y Trabajos De Fotograf\u00cda, V\u00cddeo Y Cine",
    "sg:phone":"+34 947 32 14 60",
    "sg:postcode":"09200",
    "sg:province":"Burgos",
    "wof:name":"Truchuelo Ramirez Enrique",
    "wof:placetype":"venue"
},
  "geometry": {"coordinates":[-2.944986105,42.6873474121],"type":"Point"}
}