{
  "type": "Feature",
  "properties": {
    "addr:full":"Avgd Marques De Montroig, 45 Badalona Barcelona 08912",
    "addr:housenumber":"45",
    "addr:postcode":"08912",
    "addr:street":"Montroig",
    "iso:country":"ES",
    "sg:address":"Avgd Marques De Montroig, 45",
    "sg:city":"Badalona",
    "sg:orig_category":"Plomeros",
    "sg:phone":"+34 933 87 37 00",
    "sg:postcode":"08912",
    "sg:province":"Barcelona",
    "wof:name":"Suministros Generales Del Besos S.l.",
    "wof:placetype":"venue"
},
  "geometry": {"coordinates":[2.2367210388,41.4427375793],"type":"Point"}
}