{
  "type": "Feature",
  "properties": {
    "iso:country":"ES",
    "sg:address":"Carrer de El.lipse, 16",
    "sg:city":"Hospitalet Llobregat",
    "sg:orig_category":"Mec\u00c1nico Del Autom\u00d3vil",
    "sg:phone":"+34 934 40 85 92",
    "sg:postcode":"08905",
    "sg:province":"Barcelona",
    "wof:name":"Munuera Perez Fernando",
    "wof:placetype":"venue"
},
  "geometry": {"coordinates":[2.1085779667,41.3732910156],"type":"Point"}
}