{
  "type": "Feature",
  "properties": {
    "addr:full":"Matanza, 14 Jinamar Las Palmas 35220",
    "addr:housenumber":"14",
    "addr:postcode":"35220",
    "addr:street":"Matanza;Palmas",
    "iso:country":"ES",
    "sg:address":"Matanza, 14",
    "sg:city":"Jinamar",
    "sg:orig_category":"Inmobiliaria (agencias)",
    "sg:phone":"+34 928 71 18 99",
    "sg:postcode":"35220",
    "sg:province":"Las Palmas",
    "wof:name":"Explotaciones Tamatir, S.l",
    "wof:placetype":"venue"
},
  "geometry": {"coordinates":[-15.4175510406,28.0331096649],"type":"Point"}
}