{
  "type": "Feature",
  "properties": {
    "addr:full":"Dalia (z. Residencial), 2 Can Cuias Barcelona 08110",
    "addr:housenumber":"2",
    "addr:postcode":"08110",
    "addr:street":"Residencial",
    "iso:country":"ES",
    "sg:address":"Dalia (z. Residencial), 2",
    "sg:city":"Can Cuias",
    "sg:orig_category":"Molduras, Junquillos, Listones Y Molduras Perforadas",
    "sg:phone":"+34 935 75 14 23",
    "sg:postcode":"08110",
    "sg:province":"Barcelona",
    "wof:name":"Mora Rodriguez Josefa",
    "wof:placetype":"venue"
},
  "geometry": {"coordinates":[2.1817660332,41.4890899658],"type":"Point"}
}