{
  "type": "Feature",
  "properties": {
    "addr:full":"Carr Ferrocarril D'alcoi, 10 Gandia Valencia 46700",
    "addr:housenumber":"10",
    "addr:postcode":"46700",
    "addr:street":"Carr Ferrocarril D'Alcoi;Valencia",
    "iso:country":"ES",
    "sg:address":"Carr Ferrocarril D'alcoi, 10",
    "sg:city":"Gandia",
    "sg:orig_category":"Molduras, Junquillos, Listones Y Molduras Perforadas",
    "sg:phone":"+34 962 95 11 70",
    "sg:postcode":"46700",
    "sg:province":"Valencia",
    "wof:name":"Oltra Martinez Manuel",
    "wof:placetype":"venue"
},
  "geometry": {"coordinates":[-0.1855909973,38.9628982544],"type":"Point"}
}