{
  "type": "Feature",
  "properties": {
    "iso:country":"ES",
    "sg:address":"Calle de Cardillo, 36",
    "sg:city":"Benitez",
    "sg:orig_category":"Alimentaci\u00d3n General (al Por Menor)",
    "sg:phone":"+34 922 72 17 58",
    "sg:postcode":"38626",
    "sg:province":"Santa Cruz De Tenerife",
    "wof:name":"Garcia Borges Martin",
    "wof:placetype":"venue"
},
  "geometry": {"coordinates":[-16.6643543243,28.0621852875],"type":"Point"}
}