{
  "type": "Feature",
  "properties": {
    "addr:full":"Zubiaurre, 20 Ermua Vizcaya 48260",
    "addr:housenumber":"20",
    "addr:postcode":"48260",
    "addr:street":"Zubiaurre",
    "iso:country":"ES",
    "sg:address":"Zubiaurre, 20",
    "sg:city":"Ermua",
    "sg:orig_category":"Lencer\u00cda Femenina, Corseter\u00cda, Trajes De Ba\u00d1o (al Por Menor)",
    "sg:phone":"+34 943 03 01 03",
    "sg:postcode":"48260",
    "sg:province":"Vizcaya",
    "wof:name":"Huete Garcia Ainhoa",
    "wof:placetype":"venue"
},
  "geometry": {"coordinates":[-2.5029599667,43.1880149841],"type":"Point"}
}