{
  "type": "Feature",
  "properties": {
    "addr:full":"Calle de El Molino, 9 Puente Reina Jaca Huesca 22753",
    "addr:housenumber":"9",
    "addr:postcode":"22753",
    "addr:street":"Calle De El Molino;Reina",
    "iso:country":"ES",
    "sg:address":"Calle de El Molino, 9",
    "sg:city":"Puente Reina Jaca",
    "sg:orig_category":"Formaci\u00d3n Continuada (variada)",
    "sg:phone":"+34 974 37 70 00",
    "sg:postcode":"22753",
    "sg:province":"Huesca",
    "wof:name":"Mauleon Pellon Carlos",
    "wof:placetype":"venue"
},
  "geometry": {"coordinates":[-0.7877140045,42.5595741272],"type":"Point"}
}