{
  "type": "Feature",
  "properties": {
    "addr:full":"Calle de Torremolinos, 75 Churriana M\u00e1laga 29140",
    "addr:housenumber":"75",
    "addr:postcode":"29140",
    "addr:street":"Calle De Torremolinos",
    "iso:country":"ES",
    "sg:address":"Calle de Torremolinos, 75",
    "sg:city":"Churriana",
    "sg:orig_category":"Inform\u00c1tica, Ofim\u00c1tica (estudios, Asesor\u00cda, Ingenier\u00cda, Formaci\u00d3n)",
    "sg:phone":"+34 952 43 70 66",
    "sg:postcode":"29140",
    "sg:province":"M\u00e1laga",
    "wof:name":"Dinaware S.l.",
    "wof:placetype":"venue"
},
  "geometry": {"coordinates":[-4.5057020187,36.6623649597],"type":"Point"}
}