{
  "type": "Feature",
  "properties": {
    "addr:full":"Laguna De Villasinda(pol Ind), 32 Balsicas Murcia 30591",
    "addr:housenumber":"32",
    "addr:postcode":"30591",
    "addr:street":"Laguna;Ind",
    "iso:country":"ES",
    "sg:address":"Laguna De Villasinda(pol Ind), 32",
    "sg:city":"Balsicas",
    "sg:orig_category":"Hormig\u00d3n (m\u00c1quinas E Instalaci\u00d3n)",
    "sg:phone":"+34 968 58 09 24",
    "sg:postcode":"30591",
    "sg:province":"Murcia",
    "wof:name":"Holybom S L",
    "wof:placetype":"venue"
},
  "geometry": {"coordinates":[-0.9698989987,37.8170928955],"type":"Point"}
}