{
  "type": "Feature",
  "properties": {
    "addr:full":"Carrer de Emporda (l'), 7 Casc Antic Barcelona 08150",
    "addr:housenumber":"7",
    "addr:postcode":"08150",
    "addr:street":"Carrer De Emporda L '",
    "iso:country":"ES",
    "sg:address":"Carrer de Emporda (l'), 7",
    "sg:city":"Casc Antic",
    "sg:orig_category":"Alimentaci\u00d3n General (al Por Menor)",
    "sg:phone":"+34 935 62 18 27",
    "sg:postcode":"08150",
    "sg:province":"Barcelona",
    "wof:name":"Ninou Terradellas Maria Teresa",
    "wof:placetype":"venue"
},
  "geometry": {"coordinates":[2.2293000221,41.5678787231],"type":"Point"}
}