{
  "type": "Feature",
  "properties": {
    "addr:full":"Urb. Palm-mar, S/n Pal-mar Santa Cruz De Tenerife 38640",
    "addr:housenumber":"s",
    "addr:postcode":"38640",
    "addr:street":"/ N Pal-Mar",
    "iso:country":"ES",
    "sg:address":"Urb. Palm-mar, S/n",
    "sg:city":"Pal-mar",
    "sg:orig_category":"Promotores Constructores",
    "sg:phone":"+34 922 73 41 08",
    "sg:postcode":"38640",
    "sg:province":"Santa Cruz De Tenerife",
    "wof:name":"Construcciones Daltre S.l.",
    "wof:placetype":"venue"
},
  "geometry": {"coordinates":[-16.682012558,28.0987625122],"type":"Point"}
}