{
  "type": "Feature",
  "properties": {
    "iso:country":"ES",
    "sg:address":"Calle de Real, 1",
    "sg:city":"Ajalvir",
    "sg:orig_category":"Molduras, Junquillos, Listones Y Molduras Perforadas",
    "sg:phone":"+34 918 84 30 78",
    "sg:postcode":"28864",
    "sg:province":"Madrid",
    "wof:name":"Bravo Barragan Julio",
    "wof:placetype":"venue"
},
  "geometry": {"coordinates":[-3.4804298878,40.5318145752],"type":"Point"}
}