{
  "type": "Feature",
  "properties": {
    "addr:full":"Calle de Parra, 19 Salamanca Salamanca 37001",
    "addr:housenumber":"19",
    "addr:postcode":"37001",
    "addr:street":"Calle De Parra",
    "iso:country":"ES",
    "sg:address":"Calle de Parra, 19",
    "sg:city":"Salamanca",
    "sg:orig_category":"M\u00c9dicos: Neumolog\u00cda",
    "sg:phone":"+34 923 26 74 90",
    "sg:postcode":"37001",
    "sg:province":"Salamanca",
    "wof:name":"Tapia Benito Jose Ignacio",
    "wof:placetype":"venue"
},
  "geometry": {"coordinates":[-5.660902977,40.9636497498],"type":"Point"}
}