{
  "type": "Feature",
  "properties": {
    "iso:country":"ES",
    "sg:address":"Calle de Nuestra Se\u00d1ora De Fatima, 19",
    "sg:city":"Burgos",
    "sg:orig_category":"Pescader\u00cdas (al Por Menor)",
    "sg:phone":"+34 947 23 56 58",
    "sg:postcode":"09007",
    "sg:province":"Burgos",
    "wof:name":"Due\u00f1as Ilana Victor",
    "wof:placetype":"venue"
},
  "geometry": {"coordinates":[-3.6750850677,42.3526687622],"type":"Point"}
}