{
  "type": "Feature",
  "properties": {
    "addr:full":"Calle de Leon Xiii, 18 Zaragoza Zaragoza 50008",
    "addr:housenumber":"18",
    "addr:postcode":"50008",
    "addr:street":"Calle De Leon Xiii",
    "iso:country":"ES",
    "sg:address":"Calle de Leon Xiii, 18",
    "sg:city":"Zaragoza",
    "sg:orig_category":"Aguas (distribuci\u00d3n, Servicios)",
    "sg:phone":"+34 976 21 70 43",
    "sg:postcode":"50008",
    "sg:province":"Zaragoza",
    "wof:name":"Iberambiente S.l.",
    "wof:placetype":"venue"
},
  "geometry": {"coordinates":[-0.882224977,41.6460151672],"type":"Point"}
}