{
  "type": "Feature",
  "properties": {
    "addr:full":"Calle de Donostia-san Sebastian, 16 Errenteria Guip\u00f9zcoa 20100",
    "addr:postcode":"16;20100",
    "addr:street":"Calle De;Guipu\u0300Zcoa",
    "iso:country":"ES",
    "sg:address":"Calle de Donostia-san Sebastian, 16",
    "sg:city":"Errenteria",
    "sg:orig_category":"Peluqueros: De Se\u00d1oras",
    "sg:phone":"+34 943 52 23 76",
    "sg:postcode":"20100",
    "sg:province":"Guip\u00f9zcoa",
    "wof:name":"Suarez Iglesias Eva Maria",
    "wof:placetype":"venue"
},
  "geometry": {"coordinates":[-1.9032360315,43.3156433105],"type":"Point"}
}