{
  "type": "Feature",
  "properties": {
    "addr:full":"Av Goles De L'ebre, 105 Deltebre Tarragona 43580",
    "addr:housenumber":"105",
    "addr:postcode":"43580",
    "addr:street":"Av Goles De L'Ebre",
    "iso:country":"ES",
    "sg:address":"Av Goles De L'ebre, 105",
    "sg:city":"Deltebre",
    "sg:orig_category":"Mec\u00c1nico Del Autom\u00d3vil",
    "sg:phone":"+34 977 48 15 98",
    "sg:postcode":"43580",
    "sg:province":"Tarragona",
    "wof:name":"Deltagarci S. L.",
    "wof:placetype":"venue"
},
  "geometry": {"coordinates":[0.7302820086,40.719039917],"type":"Point"}
}