{
  "type": "Feature",
  "properties": {
    "iso:country":"ES",
    "sg:address":"Calle de Colon (de), 113",
    "sg:city":"San Eugenio Bajo",
    "sg:orig_category":"Doctores En Medicina",
    "sg:phone":"+34 922 71 62 03",
    "sg:postcode":"38660",
    "sg:province":"Santa Cruz De Tenerife",
    "wof:name":"Dominguez Sierra Maria",
    "wof:placetype":"venue"
},
  "geometry": {"coordinates":[-16.7354431152,28.0784606934],"type":"Point"}
}