{
  "type": "Feature",
  "properties": {
    "iso:country":"ES",
    "sg:address":"Calle de Holguera, 11",
    "sg:city":"Coria",
    "sg:orig_category":"Tiendas De Grano, Frutas Y Legumbres Secas (al Por Menor)",
    "sg:phone":"+34 927 50 30 12",
    "sg:postcode":"10800",
    "sg:province":"C\u00e1ceres",
    "wof:name":"Puerto Barroso Manuel",
    "wof:placetype":"venue"
},
  "geometry": {"coordinates":[-6.5335888863,39.9863700867],"type":"Point"}
}