{
  "type": "Feature",
  "properties": {
    "addr:full":"Calle de Miguel Servet, 2 Teruel Teruel 44002",
    "addr:housenumber":"2",
    "addr:postcode":"44002",
    "addr:street":"Calle De Miguel Servet",
    "iso:country":"ES",
    "sg:address":"Calle de Miguel Servet, 2",
    "sg:city":"Teruel",
    "sg:orig_category":"Centros Pms (psico",
    "sg:phone":"+34 978 60 26 93",
    "sg:postcode":"44002",
    "sg:province":"Teruel",
    "wof:name":"Diputacion General De Aragon",
    "wof:placetype":"venue"
},
  "geometry": {"coordinates":[-1.1061990261,40.3369674683],"type":"Point"}
}