{
  "type": "Feature",
  "properties": {
    "addr:full":"Calle de San Vicente, 13 Cheste Valencia 46380",
    "addr:housenumber":"13",
    "addr:postcode":"46380",
    "addr:street":"Calle De San Vicente",
    "iso:country":"ES",
    "sg:address":"Calle de San Vicente, 13",
    "sg:city":"Cheste",
    "sg:orig_category":"Papeler\u00cdas, Librer\u00cdas",
    "sg:phone":"+34 962 51 13 75",
    "sg:postcode":"46380",
    "sg:province":"Valencia",
    "wof:name":"Badal Garcia Ana Maria",
    "wof:placetype":"venue"
},
  "geometry": {"coordinates":[-0.6839789748,39.4946861267],"type":"Point"}
}