{
  "type": "Feature",
  "properties": {
    "iso:country":"ES",
    "sg:address":"Via Laietana, 51",
    "sg:city":"Barcelona",
    "sg:orig_category":"Asesor\u00cda Sobre Comunicaci\u00d3n De Empresas",
    "sg:phone":"+34 933 18 25 00",
    "sg:postcode":"08003",
    "sg:province":"Barcelona",
    "wof:name":"Fomento De Inversiones Y Centro Asesor Para La Empresa S.l.",
    "wof:placetype":"venue"
},
  "geometry": {"coordinates":[2.1742649078,41.3872566223],"type":"Point"}
}