{
  "type": "Feature",
  "properties": {
    "iso:country":"ES",
    "sg:address":"Pol Ind Ca\u00f1ada De La Fuente, S/n",
    "sg:city":"Martos",
    "sg:orig_category":"Porcelanas, Azulejos (fabricaci\u00d3n, Al Por Mayor)",
    "sg:phone":"+34 953 55 00 47",
    "sg:postcode":"23600",
    "sg:province":"Ja\u00e9n",
    "sg:website":"www.infonegocio.com/pavimart",
    "wof:name":"Pavimentos Martos S.l.",
    "wof:placetype":"venue"
},
  "geometry": {"coordinates":[-3.9491291046,37.601436615],"type":"Point"}
}