{
  "type": "Feature",
  "properties": {
    "addr:full":"Calle de Antonio Concha, 38 Navalmoral Mata C\u00e1ceres 10300",
    "addr:housenumber":"38",
    "addr:postcode":"10300",
    "addr:street":"Calle De Antonio Concha;Ca\u0301Ceres",
    "iso:country":"ES",
    "sg:address":"Calle de Antonio Concha, 38",
    "sg:city":"Navalmoral Mata",
    "sg:orig_category":"Peluqueros: De Se\u00d1oras",
    "sg:phone":"+34 927 53 18 91",
    "sg:postcode":"10300",
    "sg:province":"C\u00e1ceres",
    "wof:name":"Garcia Martin Luisa",
    "wof:placetype":"venue"
},
  "geometry": {"coordinates":[-5.538851738,39.8908233643],"type":"Point"}
}