{
  "type": "Feature",
  "properties": {
    "addr:full":"Calle de Mula, 14 Javali Nuevo Murcia 30832",
    "addr:housenumber":"14",
    "addr:postcode":"30832",
    "addr:street":"Calle De Mula",
    "iso:country":"ES",
    "sg:address":"Calle de Mula, 14",
    "sg:city":"Javali Nuevo",
    "sg:orig_category":"Sociedades, Compa\u00d1\u00cdas Aseguradoras",
    "sg:phone":"+34 968 80 81 80",
    "sg:postcode":"30832",
    "sg:province":"Murcia",
    "wof:name":"Almagro Hernandez Jose",
    "wof:placetype":"venue"
},
  "geometry": {"coordinates":[-1.2168090343,37.9875488281],"type":"Point"}
}