{
  "type": "Feature",
  "properties": {
    "addr:full":"Ctra Huerta Cabo, 13 Melilla Melilla 52006",
    "addr:housenumber":"13",
    "addr:postcode":"52006",
    "addr:street":"Ctra Huerta Cabo",
    "iso:country":"ES",
    "sg:address":"Ctra Huerta Cabo, 13",
    "sg:city":"Melilla",
    "sg:orig_category":"Material Y Suministros Para Peluquer\u00cda",
    "sg:phone":"+34 952 67 38 81",
    "sg:postcode":"52006",
    "sg:province":"Melilla",
    "wof:name":"Tapia Urbaneja Noelia",
    "wof:placetype":"venue"
},
  "geometry": {"coordinates":[-2.9389870167,35.2731971741],"type":"Point"}
}