{
  "type": "Feature",
  "properties": {
    "iso:country":"ES",
    "sg:address":"Calle de Plomo, 13",
    "sg:city":"Estacion",
    "sg:orig_category":"Fabricaci\u00d3n, Instalaci\u00d3n Y Reparaci\u00d3n De Bombas",
    "sg:phone":"+34 918 51 61 06",
    "sg:postcode":"28400",
    "sg:province":"Madrid",
    "wof:name":"Electromecanica Justo Yuguero S.l.",
    "wof:placetype":"venue"
},
  "geometry": {"coordinates":[-4.0209698677,40.6257591248],"type":"Point"}
}