{
  "type": "Feature",
  "properties": {
    "addr:full":"Carr Antoni Maura, 72 Santa Margalida Islas Baleares 07450",
    "addr:housenumber":"72",
    "addr:postcode":"07450",
    "addr:street":"Carr Antoni Maura",
    "iso:country":"ES",
    "sg:address":"Carr Antoni Maura, 72",
    "sg:city":"Santa Margalida",
    "sg:orig_category":"Peluquer\u00cdas, Peluquer\u00cda Mixta",
    "sg:phone":"+34 971 52 36 54",
    "sg:postcode":"07450",
    "sg:province":"Islas Baleares",
    "wof:name":"Taberner Jaume Antonia",
    "wof:placetype":"venue"
},
  "geometry": {"coordinates":[3.102380991,39.6970939636],"type":"Point"}
}