{
  "type": "Feature",
  "properties": {
    "addr:full":"Calle de Mina, 75 Aznalcollar Sevilla 41870",
    "addr:housenumber":"75",
    "addr:postcode":"41870",
    "addr:street":"Calle De Mina",
    "iso:country":"ES",
    "sg:address":"Calle de Mina, 75",
    "sg:city":"Aznalcollar",
    "sg:orig_category":"Empresas De Carpinter\u00cda",
    "sg:phone":"+34 954 13 33 59",
    "sg:postcode":"41870",
    "sg:province":"Sevilla",
    "wof:name":"Hierros Y Aluminios Andalucia S.l.",
    "wof:placetype":"venue"
},
  "geometry": {"coordinates":[-6.262597084,37.5174293518],"type":"Point"}
}