{
  "type": "Feature",
  "properties": {
    "iso:country":"ES",
    "sg:address":"Av Roureda, 21",
    "sg:city":"Viladecans",
    "sg:orig_category":"Molduras, Junquillos, Listones Y Molduras Perforadas",
    "sg:phone":"+34 936 37 34 13",
    "sg:postcode":"08840",
    "sg:province":"Barcelona",
    "wof:name":"Blanco Dominguez Francisco",
    "wof:placetype":"venue"
},
  "geometry": {"coordinates":[2.0108370781,41.3229103088],"type":"Point"}
}