{
  "type": "Feature",
  "properties": {
    "addr:full":"Avda Valladolid, 34 Tudela Duero Valladolid 47320",
    "addr:housenumber":"34;duero",
    "addr:postcode":"47320",
    "addr:street":"Avda Valladolid",
    "iso:country":"ES",
    "sg:address":"Avda Valladolid, 34",
    "sg:city":"Tudela Duero",
    "sg:orig_category":"Agencias Y Agentes Comerciales, Representantes",
    "sg:phone":"+34 983 52 06 47",
    "sg:postcode":"47320",
    "sg:province":"Valladolid",
    "wof:name":"Garcia Martin Jose",
    "wof:placetype":"venue"
},
  "geometry": {"coordinates":[-4.5835590363,41.5873718262],"type":"Point"}
}