{
  "type": "Feature",
  "properties": {
    "addr:full":"Ctra. Talavera, Km. 0055,0 Montearagon Toledo 45555",
    "addr:postcode":"45555",
    "addr:street":"Ctra. Talavera Km. 0055,0",
    "iso:country":"ES",
    "sg:address":"Ctra. Talavera, Km. 0055,0",
    "sg:city":"Montearagon",
    "sg:orig_category":"Empresas De Hormig\u00d3n, Hormig\u00d3n Armado Y Pretensado",
    "sg:phone":"+34 925 86 54 32",
    "sg:postcode":"45555",
    "sg:province":"Toledo",
    "wof:name":"Fomento Y Prefabricados Aragon S.l.",
    "wof:placetype":"venue"
},
  "geometry": {"coordinates":[-4.6330699921,39.9548797607],"type":"Point"}
}