{
  "type": "Feature",
  "properties": {
    "addr:full":"Calle de Luis Alberdi, S/n Burgos Burgos 09007",
    "addr:housenumber":"s / n",
    "addr:postcode":"09007",
    "addr:street":"Calle De Luis Alberdi",
    "iso:country":"ES",
    "sg:address":"Calle de Luis Alberdi, S/n",
    "sg:city":"Burgos",
    "sg:orig_category":"Agencias Y Agentes Comerciales, Representantes",
    "sg:phone":"+34 947 48 33 33",
    "sg:postcode":"09007",
    "sg:province":"Burgos",
    "wof:name":"Redofij",
    "wof:placetype":"venue"
},
  "geometry": {"coordinates":[-3.6660339832,42.3510093689],"type":"Point"}
}