{
  "type": "Feature",
  "properties": {
    "iso:country":"ES",
    "sg:address":"Calle de Zumaia, 7",
    "sg:city":"Bilbao",
    "sg:orig_category":"Peluquer\u00cdas, Peluquer\u00cda Mixta",
    "sg:phone":"+34 944 46 65 73",
    "sg:postcode":"48007",
    "sg:province":"Vizcaya",
    "wof:name":"Orgavelli Red Comercial",
    "wof:placetype":"venue"
},
  "geometry": {"coordinates":[-2.9153931141,43.2655067444],"type":"Point"}
}