{
  "type": "Feature",
  "properties": {
    "iso:country":"ES",
    "sg:address":"Passeig Calvari, 20",
    "sg:city":"Pego",
    "sg:orig_category":"Florister\u00cdas",
    "sg:phone":"+34 965 57 17 46",
    "sg:postcode":"03780",
    "sg:province":"Alicante",
    "wof:name":"Ivars Ferrer Jose Antonio",
    "wof:placetype":"venue"
},
  "geometry": {"coordinates":[-0.1226750016,38.8373794556],"type":"Point"}
}