{
  "type": "Feature",
  "properties": {
    "addr:full":"Av Lluis Companys, 30 S. Cugat Valles Barcelona 08172",
    "addr:housenumber":"30",
    "addr:postcode":"08172",
    "addr:street":"Av Lluis Companys;S. Cugat Valles Barcelona",
    "iso:country":"ES",
    "sg:address":"Av Lluis Companys, 30",
    "sg:city":"S. Cugat Valles",
    "sg:orig_category":"Electricidad: Instaladores",
    "sg:phone":"+34 936 74 76 65",
    "sg:postcode":"08172",
    "sg:province":"Barcelona",
    "wof:name":"Munuera Gomar Carlos",
    "wof:placetype":"venue"
},
  "geometry": {"coordinates":[2.0789859295,41.4708709717],"type":"Point"}
}