{
  "type": "Feature",
  "properties": {
    "addr:full":"Ctra. Militar, 235 Arenal Islas Baleares 07600",
    "addr:housenumber":"235",
    "addr:postcode":"07600",
    "addr:street":"Ctra. Militar",
    "iso:country":"ES",
    "sg:address":"Ctra. Militar, 235",
    "sg:city":"Arenal",
    "sg:orig_category":"Molduras, Junquillos, Listones Y Molduras Perforadas",
    "sg:phone":"+34 971 74 33 35",
    "sg:postcode":"07600",
    "sg:province":"Islas Baleares",
    "wof:name":"Rodriguez Quinta Cristina",
    "wof:placetype":"venue"
},
  "geometry": {"coordinates":[2.7547938824,39.5078659058],"type":"Point"}
}