{
  "type": "Feature",
  "properties": {
    "addr:full":"Avda Comuneros, 10 Salamanca Salamanca 37003",
    "addr:housenumber":"10",
    "addr:postcode":"37003",
    "addr:street":"Avda Comuneros",
    "iso:country":"ES",
    "sg:address":"Avda Comuneros, 10",
    "sg:city":"Salamanca",
    "sg:orig_category":"Trajes Y Adornos De Boda (confecci\u00d3n, Al Por Menor)",
    "sg:phone":"+34 923 18 70 73",
    "sg:postcode":"37003",
    "sg:province":"Salamanca",
    "wof:name":"Bellido Haro Maria Soledad",
    "wof:placetype":"venue"
},
  "geometry": {"coordinates":[-5.6519980431,40.9684944153],"type":"Point"}
}