{
  "type": "Feature",
  "properties": {
    "addr:full":"Carrer de L'atlantida, 43 Barcelona Barcelona 08003",
    "addr:housenumber":"43",
    "addr:postcode":"08003",
    "addr:street":"Carrer De L'Atlantida",
    "iso:country":"ES",
    "sg:address":"Carrer de L'atlantida, 43",
    "sg:city":"Barcelona",
    "sg:orig_category":"Papeler\u00cdas, Librer\u00cdas",
    "sg:phone":"+34 932 21 73 85",
    "sg:postcode":"08003",
    "sg:province":"Barcelona",
    "wof:name":"Torres Moreno Estrella",
    "wof:placetype":"venue"
},
  "geometry": {"coordinates":[2.1900060177,41.3792991638],"type":"Point"}
}