{
  "type": "Feature",
  "properties": {
    "iso:country":"ES",
    "sg:address":"Carrer de Santiago Apostol, 59",
    "sg:city":"Hospitalet Llobregat",
    "sg:orig_category":"Ingeniero",
    "sg:phone":"+34 934 22 55 92",
    "sg:postcode":"08903",
    "sg:province":"Barcelona",
    "wof:name":"Casanovas Llombart Pedro",
    "wof:placetype":"venue"
},
  "geometry": {"coordinates":[2.1244800091,41.3699378967],"type":"Point"}
}