{
  "type": "Feature",
  "properties": {
    "addr:full":"Avda. Libertad, 4 Velez-rubio Almer\u00eda 04820",
    "addr:housenumber":"4",
    "addr:postcode":"04820",
    "addr:street":"Avda. Libertad;Almeri\u0301A",
    "iso:country":"ES",
    "sg:address":"Avda. Libertad, 4",
    "sg:city":"Velez-rubio",
    "sg:orig_category":"Hoteles",
    "sg:phone":"+34 950 41 09 43",
    "sg:postcode":"04820",
    "sg:province":"Almer\u00eda",
    "wof:name":"Martinez Rosa Jose Antonio",
    "wof:placetype":"venue"
},
  "geometry": {"coordinates":[-2.0766999722,37.6484260559],"type":"Point"}
}