{
  "type": "Feature",
  "properties": {
    "iso:country":"ES",
    "sg:address":"Carrer de Mallorca, 272",
    "sg:city":"Barcelona",
    "sg:orig_category":"Promotores Constructores",
    "sg:phone":"+34 932 72 07 18",
    "sg:postcode":"08037",
    "sg:province":"Barcelona",
    "wof:name":"Miguel Termens S.l.",
    "wof:placetype":"venue"
},
  "geometry": {"coordinates":[2.164495945,41.3950958252],"type":"Point"}
}