{
  "type": "Feature",
  "properties": {
    "iso:country":"ES",
    "sg:address":"Calle de Santiago, 25",
    "sg:city":"Puerto",
    "sg:orig_category":"Alimentaci\u00d3n General (al Por Menor)",
    "sg:phone":"+34 962 67 66 44",
    "sg:postcode":"46520",
    "sg:province":"Valencia",
    "wof:name":"Marcos Duro Tomas",
    "wof:placetype":"venue"
},
  "geometry": {"coordinates":[-0.2293239981,39.6609725952],"type":"Point"}
}