{
  "type": "Feature",
  "properties": {
    "addr:full":"Ctra Toledo Avila, S/n Val De Santo Domingo Toledo 45519",
    "addr:postcode":"45519",
    "addr:street":"Ctra Toledo Avila S / N",
    "iso:country":"ES",
    "sg:address":"Ctra Toledo Avila, S/n",
    "sg:city":"Val De Santo Domingo",
    "sg:orig_category":"Productores Recolectores, Venta Directa De Vinos",
    "sg:phone":"+34 925 77 91 12",
    "sg:postcode":"45519",
    "sg:province":"Toledo",
    "wof:name":"Cooperativa Del Campo Sagrado Corazon De Jesus",
    "wof:placetype":"venue"
},
  "geometry": {"coordinates":[-4.2703337669,40.0481987],"type":"Point"}
}