{
  "type": "Feature",
  "properties": {
    "iso:country":"ES",
    "sg:address":"Calle de Guardia Civil, 2",
    "sg:city":"Burgos",
    "sg:orig_category":"Expertos Contables, Revisores De Cuentas",
    "sg:phone":"+34 947 23 65 60",
    "sg:postcode":"09004",
    "sg:province":"Burgos",
    "wof:name":"Fernandez-mardomingo Barriuso Miguel Jose",
    "wof:placetype":"venue"
},
  "geometry": {"coordinates":[-3.694314003,42.3449821472],"type":"Point"}
}