{
  "type": "Feature",
  "properties": {
    "iso:country":"ES",
    "sg:address":"Calle de Gerona, 11",
    "sg:city":"Valle De Los Nueve Bajo",
    "sg:orig_category":"Transportes Por V\u00cdas Navegables",
    "sg:phone":"+34 928 68 36 72",
    "sg:postcode":"35200",
    "sg:province":"Las Palmas",
    "wof:name":"Martel Martel Jose Francisco",
    "wof:placetype":"venue"
},
  "geometry": {"coordinates":[-15.4333753586,27.9903659821],"type":"Point"}
}