{
  "type": "Feature",
  "properties": {
    "iso:country":"ES",
    "sg:address":"Ctra Pinos Puente, Km. 0427,5",
    "sg:city":"Atarfe",
    "sg:orig_category":"Artesan\u00cda",
    "sg:phone":"+34 958 43 85 05",
    "sg:postcode":"18230",
    "sg:province":"Granada",
    "wof:name":"Artesania Alvarez S.l.",
    "wof:placetype":"venue"
},
  "geometry": {"coordinates":[-3.6983997822,37.2193031311],"type":"Point"}
}