{
  "type": "Feature",
  "properties": {
    "addr:full":"Calle de Sueca, 25 Valencia Valencia 46006",
    "addr:housenumber":"25",
    "addr:postcode":"46006",
    "addr:street":"Calle De Sueca",
    "iso:country":"ES",
    "sg:address":"Calle de Sueca, 25",
    "sg:city":"Valencia",
    "sg:orig_category":"Abogados",
    "sg:phone":"+34 963 80 73 02",
    "sg:postcode":"46006",
    "sg:province":"Valencia",
    "wof:name":"Villanueva Toledo Vicente",
    "wof:placetype":"venue"
},
  "geometry": {"coordinates":[-0.3752659857,39.4619827271],"type":"Point"}
}