{
  "type": "Feature",
  "properties": {
    "addr:full":"Avda Ronda De Los Tejares, 32 Cordoba C\u00f3rdoba 14001",
    "addr:housenumber":"32",
    "addr:postcode":"14001",
    "addr:street":"Avda Ronda De Los Tejares;Co\u0301Rdoba",
    "iso:country":"ES",
    "sg:address":"Avda Ronda De Los Tejares, 32",
    "sg:city":"Cordoba",
    "sg:orig_category":"Pe\u00d1as Y Asociaciones Varias",
    "sg:phone":"+34 957 47 68 01",
    "sg:postcode":"14001",
    "sg:province":"C\u00f3rdoba",
    "wof:name":"Asociacion De Empresarios De La Construccion De Cordoba",
    "wof:placetype":"venue"
},
  "geometry": {"coordinates":[-4.7828168869,37.887462616],"type":"Point"}
}