{
  "type": "Feature",
  "properties": {
    "iso:country":"ES",
    "sg:address":"Avda Eusebio Salvador Merino, 3",
    "sg:city":"Herrera Pisuerga",
    "sg:orig_category":"Abogados",
    "sg:phone":"+34 979 13 00 24",
    "sg:postcode":"34400",
    "sg:province":"Palencia",
    "wof:name":"Del Blanco Diez Maria Jesus",
    "wof:placetype":"venue"
},
  "geometry": {"coordinates":[-4.3319821358,42.5963020325],"type":"Point"}
}