{
  "type": "Feature",
  "properties": {
    "addr:full":"Carrer de Batllevell, 89 Sabadell Barcelona 08208",
    "addr:housenumber":"89",
    "addr:postcode":"08208",
    "addr:street":"Carrer De Batllevell",
    "iso:country":"ES",
    "sg:address":"Carrer de Batllevell, 89",
    "sg:city":"Sabadell",
    "sg:orig_category":"Reposter\u00cdas",
    "sg:phone":"+34 937 23 62 02",
    "sg:postcode":"08208",
    "sg:province":"Barcelona",
    "wof:name":"Paton Martin Agustina",
    "wof:placetype":"venue"
},
  "geometry": {"coordinates":[2.1092100143,41.5565071106],"type":"Point"}
}