{
  "type": "Feature",
  "properties": {
    "iso:country":"ES",
    "sg:address":"Rbla Egara, 311",
    "sg:city":"Terrassa",
    "sg:orig_category":"M\u00c9dicos: Estomatolog\u00cda",
    "sg:phone":"+34 937 80 15 47",
    "sg:postcode":"08224",
    "sg:province":"Barcelona",
    "wof:name":"Chavez Nu\u00f1ez Julio Alberto",
    "wof:placetype":"venue"
},
  "geometry": {"coordinates":[2.0056340694,41.5672111511],"type":"Point"}
}