{
  "type": "Feature",
  "properties": {
    "addr:full":"Avda Bierzo (el), 12 Bembibre Le\u00f3n 24300",
    "addr:postcode":"24300",
    "addr:street":"Avda Bierzo El;Leo\u0301N",
    "iso:country":"ES",
    "sg:address":"Avda Bierzo (el), 12",
    "sg:city":"Bembibre",
    "sg:orig_category":"Agencias De Viajes",
    "sg:phone":"+34 987 51 01 52",
    "sg:postcode":"24300",
    "sg:province":"Le\u00f3n",
    "sg:website":"www.bembibre@barcelo.com",
    "wof:name":"Bierzo Tour S.l.",
    "wof:placetype":"venue"
},
  "geometry": {"coordinates":[-6.4173088074,42.6184310913],"type":"Point"}
}