{
  "type": "Feature",
  "properties": {
    "addr:full":"Carrer de President Companys, S/n Vendrell Tarragona 43700",
    "addr:housenumber":"s / n",
    "addr:postcode":"43700",
    "addr:street":"Carrer De President Companys",
    "iso:country":"ES",
    "sg:address":"Carrer de President Companys, S/n",
    "sg:city":"Vendrell",
    "sg:orig_category":"Comerciantes Al Por Mayor De Vinos, Licores Y Alcoholes",
    "sg:phone":"+34 977 66 75 43",
    "sg:postcode":"43700",
    "sg:province":"Tarragona",
    "wof:name":"Licors Jane S.l.",
    "wof:placetype":"venue"
},
  "geometry": {"coordinates":[1.5337250233,41.2140007019],"type":"Point"}
}