{
  "type": "Feature",
  "properties": {
    "iso:country":"ES",
    "sg:address":"Calle de Arribas, 16",
    "sg:city":"Valladolid",
    "sg:orig_category":"Centros Empresariales",
    "sg:phone":"+34 983 21 11 52",
    "sg:postcode":"47002",
    "sg:province":"Valladolid",
    "wof:name":"Zazen Spa Centro Olistico S.l.n.e.",
    "wof:placetype":"venue"
},
  "geometry": {"coordinates":[-4.7228908539,41.6521720886],"type":"Point"}
}