{
  "type": "Feature",
  "properties": {
    "iso:country":"ES",
    "sg:address":"Calle de Blas De Lezo, 3",
    "sg:city":"Malaga",
    "sg:orig_category":"Bisuter\u00cda, Joyer\u00cda, Relojer\u00cda (al Por Menor)",
    "sg:phone":"+34 952 30 55 10",
    "sg:postcode":"29011",
    "sg:province":"M\u00e1laga",
    "wof:name":"Gomez Montes Salvadora",
    "wof:placetype":"venue"
},
  "geometry": {"coordinates":[-4.4348731041,36.7273635864],"type":"Point"}
}