{
  "type": "Feature",
  "properties": {
    "addr:full":"Ctra. General, Km. 0006,9 Vilaflor Santa Cruz De Tenerife 38613",
    "addr:postcode":"38613",
    "addr:street":"Ctra. General Km. 0006,9",
    "iso:country":"ES",
    "sg:address":"Ctra. General, Km. 0006,9",
    "sg:city":"Vilaflor",
    "sg:orig_category":"Cooperativas Agr\u00cdcolas",
    "sg:phone":"+34 922 70 92 75",
    "sg:postcode":"38613",
    "sg:province":"Santa Cruz De Tenerife",
    "wof:name":"Cooperativa Agricola Nuestra Se\u00f1ora Del Carmen",
    "wof:placetype":"venue"
},
  "geometry": {"coordinates":[-16.6351242065,28.1678848267],"type":"Point"}
}