{
  "type": "Feature",
  "properties": {
    "iso:country":"ES",
    "sg:address":"Calle de Armas, 6",
    "sg:city":"Toledo",
    "sg:orig_category":"Cajas De Ahorro",
    "sg:phone":"+34 925 28 42 45",
    "sg:postcode":"45001",
    "sg:province":"Toledo",
    "wof:name":"Caixa D'estalvis De Catalunya",
    "wof:placetype":"venue"
},
  "geometry": {"coordinates":[-4.0210785866,39.8602828979],"type":"Point"}
}