{
  "type": "Feature",
  "properties": {
    "addr:full":"Avgd Dr Pasteur, 49 Igualada Barcelona 08700",
    "addr:housenumber":"49",
    "addr:postcode":"08700",
    "iso:country":"ES",
    "sg:address":"Avgd Dr Pasteur, 49",
    "sg:city":"Igualada",
    "sg:orig_category":"Asociaciones Y Clubs Deportivos",
    "sg:phone":"+34 938 03 55 43",
    "sg:postcode":"08700",
    "sg:province":"Barcelona",
    "wof:name":"Martinez Gallego Jose",
    "wof:placetype":"venue"
},
  "geometry": {"coordinates":[1.6090120077,41.5883598328],"type":"Point"}
}