{
  "type": "Feature",
  "properties": {
    "addr:full":"Carrer de Francesc Bolos, 40 Barcelona Barcelona 08031",
    "addr:housenumber":"40",
    "addr:postcode":"08031",
    "addr:street":"Carrer De Francesc Bolos",
    "iso:country":"ES",
    "sg:address":"Carrer de Francesc Bolos, 40",
    "sg:city":"Barcelona",
    "sg:orig_category":"Grabados",
    "sg:phone":"+34 934 29 19 00",
    "sg:postcode":"08031",
    "sg:province":"Barcelona",
    "wof:name":"Abecedario Y Numeraciones Salicru S.l.",
    "wof:placetype":"venue"
},
  "geometry": {"coordinates":[2.172755,41.428043],"type":"Point"}
}