{
  "type": "Feature",
  "properties": {
    "addr:full":"Av Pau (de La), 20 Mollerussa Lleida 25230",
    "addr:housenumber":"20",
    "addr:postcode":"25230",
    "addr:street":"Av Pau De La",
    "iso:country":"ES",
    "sg:address":"Av Pau (de La), 20",
    "sg:city":"Mollerussa",
    "sg:orig_category":"Audiovisuales (producci\u00d3n, Edici\u00d3n, Realizaci\u00d3n)",
    "sg:phone":"+34 973 60 43 72",
    "sg:postcode":"25230",
    "sg:province":"Lleida",
    "sg:website":"www.ferranblanch.com",
    "wof:name":"Ferran Blanch S.c.p.",
    "wof:placetype":"venue"
},
  "geometry": {"coordinates":[0.8999300003,41.6279792786],"type":"Point"}
}