{
  "type": "Feature",
  "properties": {
    "addr:full":"Carrer de L'aliga, 43 Barcelona Barcelona 08014",
    "addr:housenumber":"43",
    "addr:postcode":"08014",
    "addr:street":"Carrer De L'Aliga",
    "iso:country":"ES",
    "sg:address":"Carrer de L'aliga, 43",
    "sg:city":"Barcelona",
    "sg:orig_category":"Molduras, Junquillos, Listones Y Molduras Perforadas",
    "sg:phone":"+34 934 31 89 08",
    "sg:postcode":"08014",
    "sg:province":"Barcelona",
    "wof:name":"Larraz Aisa Ernesto",
    "wof:placetype":"venue"
},
  "geometry": {"coordinates":[2.1433839798,41.3748550415],"type":"Point"}
}