{
  "type": "Feature",
  "properties": {
    "iso:country":"ES",
    "sg:address":"Avda Pais Valencia (del), 18",
    "sg:city":"Onda",
    "sg:orig_category":"Sindicatos De Trabajadores",
    "sg:phone":"+34 964 60 14 58",
    "sg:postcode":"12200",
    "sg:province":"Castell\u00f3n",
    "wof:name":"Union General De Trabajadores-pais Valenciano",
    "wof:placetype":"venue"
},
  "geometry": {"coordinates":[-0.2589620054,39.9654159546],"type":"Point"}
}