{
  "type": "Feature",
  "properties": {
    "iso:country":"ES",
    "sg:address":"Calle de Pintor Aurelio Vera-fajardo, 6",
    "sg:city":"Vitoria-gasteiz",
    "sg:orig_category":"Empresas De Limpieza",
    "sg:phone":"+34 945 01 28 59",
    "sg:postcode":"01008",
    "sg:province":"\u00c1lava",
    "wof:name":"Garbietxea, S.l.",
    "wof:placetype":"venue"
},
  "geometry": {"coordinates":[-2.6829140186,42.8487358093],"type":"Point"}
}