{
  "type": "Feature",
  "properties": {
    "iso:country":"ES",
    "sg:address":"Bda Blanes, 3",
    "sg:city":"Barcelona",
    "sg:orig_category":"Ense\u00d1ante, Direcci\u00d3n",
    "sg:phone":"+34 932 19 82 12",
    "sg:postcode":"08023",
    "sg:province":"Barcelona",
    "wof:name":"Grimm Oberkersch Maria Rosa",
    "wof:placetype":"venue"
},
  "geometry": {"coordinates":[2.1450378895,41.4109840393],"type":"Point"}
}