{
  "type": "Feature",
  "properties": {
    "addr:full":"Calle de Miravalles, 57 Torrelavega Cantabria 39300",
    "addr:housenumber":"57",
    "addr:postcode":"39300",
    "addr:street":"Calle De Miravalles",
    "iso:country":"ES",
    "sg:address":"Calle de Miravalles, 57",
    "sg:city":"Torrelavega",
    "sg:orig_category":"Cr\u00cda De Animales",
    "sg:phone":"+34 942 89 31 87",
    "sg:postcode":"39300",
    "sg:province":"Cantabria",
    "wof:name":"Garcia Horga Miguel Angel",
    "wof:placetype":"venue"
},
  "geometry": {"coordinates":[-4.0420179367,43.3480911255],"type":"Point"}
}