{
  "type": "Feature",
  "properties": {
    "addr:full":"Carrer de Roca I Roca, 69 Terrassa Barcelona 08226",
    "addr:housenumber":"69",
    "addr:postcode":"08226",
    "addr:street":"Carrer De Roca I Roca",
    "iso:country":"ES",
    "sg:address":"Carrer de Roca I Roca, 69",
    "sg:city":"Terrassa",
    "sg:orig_category":"Electricidad, Electr\u00d3nica: Suministros (al Por Menor)",
    "sg:phone":"+34 937 35 34 56",
    "sg:postcode":"08226",
    "sg:province":"Barcelona",
    "sg:website":"www.astroradio.com",
    "wof:name":"Astroradio S.l.",
    "wof:placetype":"venue"
},
  "geometry": {"coordinates":[2.0203733444,41.5739822388],"type":"Point"}
}