{
  "type": "Feature",
  "properties": {
    "addr:full":"Avda Costa Blanca, 117 Alacant Alicante 03540",
    "addr:housenumber":"117",
    "addr:postcode":"03540",
    "addr:street":"Avda Costa Blanca",
    "iso:country":"ES",
    "sg:address":"Avda Costa Blanca, 117",
    "sg:city":"Alacant",
    "sg:orig_category":"Panader\u00cdas, Panader\u00cdas",
    "sg:phone":"+34 965 16 57 70",
    "sg:postcode":"03540",
    "sg:province":"Alicante",
    "wof:name":"Confiterias La Murciana S.l.",
    "wof:placetype":"venue"
},
  "geometry": {"coordinates":[-0.412225008,38.3693122864],"type":"Point"}
}