{
  "type": "Feature",
  "properties": {
    "addr:full":"Carr Lloren\u00c7 Vilaro, S/n Mollerussa Lleida 25230",
    "addr:housenumber":"s / n",
    "addr:postcode":"25230",
    "addr:street":"Carr Llorenc\u0327 Vilaro",
    "iso:country":"ES",
    "sg:address":"Carr Lloren\u00c7 Vilaro, S/n",
    "sg:city":"Mollerussa",
    "sg:orig_category":"Pescader\u00cdas (al Por Menor)",
    "sg:phone":"+34 973 60 08 36",
    "sg:postcode":"25230",
    "sg:province":"Lleida",
    "wof:name":"Montilla Porcuna Antonio",
    "wof:placetype":"venue"
},
  "geometry": {"coordinates":[0.894659996,41.6251296997],"type":"Point"}
}