{
  "type": "Feature",
  "properties": {
    "iso:country":"ES",
    "sg:address":"Calle de Conde De Mieres, 12",
    "sg:city":"Torremolinos",
    "sg:orig_category":"Moda",
    "sg:phone":"+34 952 38 22 34",
    "sg:postcode":"29620",
    "sg:province":"M\u00e1laga",
    "wof:name":"Martinez Serra Adolfo",
    "wof:placetype":"venue"
},
  "geometry": {"coordinates":[-4.4978189468,36.6239585876],"type":"Point"}
}