{
  "type": "Feature",
  "properties": {
    "addr:full":"Carr Industria, S/n Badalona Barcelona 08912",
    "addr:housenumber":"/ n",
    "addr:postcode":"08912",
    "addr:street":"Carr Industria S",
    "iso:country":"ES",
    "sg:address":"Carr Industria, S/n",
    "sg:city":"Badalona",
    "sg:orig_category":"Distribuci\u00d3n De Petr\u00d3leo Y Derivados",
    "sg:phone":"+34 934 60 02 27",
    "sg:postcode":"08912",
    "sg:province":"Barcelona",
    "wof:name":"Estacio De Servei Industria S.l.",
    "wof:placetype":"venue"
},
  "geometry": {"coordinates":[2.2435998917,41.4420967102],"type":"Point"}
}