{
  "type": "Feature",
  "properties": {
    "iso:country":"ES",
    "sg:address":"Garaigarri Karrika, 5",
    "sg:city":"Sunbilla",
    "sg:orig_category":"Centros De Educaci\u00d3n Especial",
    "sg:phone":"+34 948 45 09 92",
    "sg:postcode":"31791",
    "sg:province":"Navarra",
    "wof:name":"Ayuntamiento De Sumbilla",
    "wof:placetype":"venue"
},
  "geometry": {"coordinates":[-1.6711839437,43.1650390625],"type":"Point"}
}