{
  "type": "Feature",
  "properties": {
    "iso:country":"ES",
    "sg:address":"Ctra Ocon, 1",
    "sg:city":"Redal",
    "sg:orig_category":"Maquinaria Para Industrias Diversas",
    "sg:phone":"+34 941 43 81 82",
    "sg:postcode":"26146",
    "sg:province":"La Rioja",
    "wof:name":"Ascacibar Maquinaria Agricola S.l.",
    "wof:placetype":"venue"
},
  "geometry": {"coordinates":[-2.1998295784,42.3362579346],"type":"Point"}
}