{
  "type": "Feature",
  "properties": {
    "addr:full":"Carr Carretera, S/n Garos Lleida 25539",
    "addr:postcode":"25539",
    "addr:street":"Carr Carretera S / N Garos",
    "iso:country":"ES",
    "sg:address":"Carr Carretera, S/n",
    "sg:city":"Garos",
    "sg:orig_category":"Centros Empresariales",
    "sg:phone":"+34 973 64 15 33",
    "sg:postcode":"25539",
    "sg:province":"Lleida",
    "wof:name":"Drexba S.l.",
    "wof:placetype":"venue"
},
  "geometry": {"coordinates":[0.8464099765,42.7000541687],"type":"Point"}
}