{
  "type": "Feature",
  "properties": {
    "addr:full":"Calle de Jose Sanchez Pescador, 2 Madrid Madrid 28007",
    "addr:housenumber":"2",
    "addr:postcode":"28007",
    "addr:street":"Calle De Jose Sanchez Pescador",
    "iso:country":"ES",
    "sg:address":"Calle de Jose Sanchez Pescador, 2",
    "sg:city":"Madrid",
    "sg:orig_category":"Fotograf\u00cda Publicitaria",
    "sg:phone":"+34 915 02 09 21",
    "sg:postcode":"28007",
    "sg:province":"Madrid",
    "wof:name":"Aulocolor Asociacion Europea Del Color S.l.",
    "wof:placetype":"venue"
},
  "geometry": {"coordinates":[-3.6784279346,40.4069404602],"type":"Point"}
}