{
  "type": "Feature",
  "properties": {
    "addr:full":"Calle de Sevilla, S/n Aduanas Alicante 03730",
    "addr:housenumber":"s / n",
    "addr:postcode":"03730",
    "addr:street":"Calle De Sevilla",
    "iso:country":"ES",
    "sg:address":"Calle de Sevilla, S/n",
    "sg:city":"Aduanas",
    "sg:orig_category":"Art\u00cdculos De Regalo (al Por Menor)",
    "sg:phone":"+34 965 79 45 35",
    "sg:postcode":"03730",
    "sg:province":"Alicante",
    "wof:name":"Yang  Zhengba",
    "wof:placetype":"venue"
},
  "geometry": {"coordinates":[0.1808405966,38.7943572998],"type":"Point"}
}