{
  "type": "Feature",
  "properties": {
    "addr:full":"Calle de Camino Real, 149 Gineta Albacete 02110",
    "addr:housenumber":"149",
    "addr:postcode":"02110",
    "addr:street":"Calle De Camino Real",
    "iso:country":"ES",
    "sg:address":"Calle de Camino Real, 149",
    "sg:city":"Gineta",
    "sg:orig_category":"Fabricaci\u00d3n De Muebles",
    "sg:phone":"+34 967 27 60 50",
    "sg:postcode":"02110",
    "sg:province":"Albacete",
    "wof:name":"Muebles Sebas S.l.",
    "wof:placetype":"venue"
},
  "geometry": {"coordinates":[-1.9962018728,39.1131401062],"type":"Point"}
}