{
  "type": "Feature",
  "properties": {
    "addr:full":"Carrer de Tarragona (de), 7 Tortosa Tarragona 43500",
    "addr:postcode":"43500",
    "addr:street":"Carrer De Tarragona De",
    "iso:country":"ES",
    "sg:address":"Carrer de Tarragona (de), 7",
    "sg:city":"Tortosa",
    "sg:orig_category":"Producci\u00d3n, Distribuci\u00d3n De Electricidad",
    "sg:phone":"+34 977 50 13 60",
    "sg:postcode":"43500",
    "sg:province":"Tarragona",
    "wof:name":"Princep Caudet Ricardo",
    "wof:placetype":"venue"
},
  "geometry": {"coordinates":[0.5161370039,40.8137016296],"type":"Point"}
}