{
  "type": "Feature",
  "properties": {
    "addr:full":"Calle de Hermanos Garcia Noblejas, 158 Madrid Madrid 28037",
    "addr:housenumber":"158",
    "addr:postcode":"28037",
    "addr:street":"Calle De Hermanos Garcia Noblejas",
    "iso:country":"ES",
    "sg:address":"Calle de Hermanos Garcia Noblejas, 158",
    "sg:city":"Madrid",
    "sg:orig_category":"Mudanzas",
    "sg:phone":"+34 913 04 95 00",
    "sg:postcode":"28037",
    "sg:province":"Madrid",
    "wof:name":"Blanco Miguel Javier",
    "wof:placetype":"venue"
},
  "geometry": {"coordinates":[-3.6290640831,40.4251251221],"type":"Point"}
}