{
  "type": "Feature",
  "properties": {
    "addr:full":"Calle de Enrique Granados (de), 125 Boadilla Del Monte Madrid 28660",
    "addr:housenumber":"125",
    "addr:postcode":"28660",
    "addr:street":"Calle De Enrique Granados De",
    "iso:country":"ES",
    "sg:address":"Calle de Enrique Granados (de), 125",
    "sg:city":"Boadilla Del Monte",
    "sg:orig_category":"Sociedades Y Organismos Burs\u00c1tiles",
    "sg:phone":"+34 916 32 47 21",
    "sg:postcode":"28660",
    "sg:province":"Madrid",
    "wof:name":"Rios Campos Aurora",
    "wof:placetype":"venue"
},
  "geometry": {"coordinates":[-3.8887219429,40.4039230347],"type":"Point"}
}