{
  "type": "Feature",
  "properties": {
    "iso:country":"ES",
    "sg:address":"Saxosa(bertola), S/n",
    "sg:city":"Sajosa",
    "sg:orig_category":"Centros Empresariales",
    "sg:phone":"+34 986 67 90 01",
    "sg:postcode":"36140",
    "sg:province":"Pontevedra",
    "wof:name":"Nueva Vida S.a.",
    "wof:placetype":"venue"
},
  "geometry": {"coordinates":[-8.6514892578,42.3227615356],"type":"Point"}
}