{
  "type": "Feature",
  "properties": {
    "iso:country":"ES",
    "sg:address":"Carrer de Salvat Papasseit, 52",
    "sg:city":"Sabadell",
    "sg:classifiers":[
        {
            "category":"Personal",
            "subcategory":"Barber",
            "type":"Services"
        }
    ],
    "sg:phone":"+34 937 10 76 03",
    "sg:postcode":"08204",
    "sg:province":"Barcelona",
    "sg:tags":[
        "caballeros",
        "de",
        "peluqueros"
    ],
    "wof:name":"Rubio Carrasco Francisco",
    "wof:placetype":"venue"
},
  "geometry": {"coordinates":[2.1178400517,41.5268096924],"type":"Point"}
}