{
  "type": "Feature",
  "properties": {
    "iso:country":"ES",
    "sg:address":"Calle de Rabida, 9",
    "sg:city":"Bollullos Par Condado",
    "sg:orig_category":"Electricidad: Instaladores",
    "sg:phone":"+34 959 41 12 45",
    "sg:postcode":"21710",
    "sg:province":"Huelva",
    "wof:name":"Construcciones W De Bollullos Del Condado, S.l.",
    "wof:placetype":"venue"
},
  "geometry": {"coordinates":[-6.5417208672,37.3409194946],"type":"Point"}
}