{
  "type": "Feature",
  "properties": {
    "addr:full":"Avda Carlos V, 7 Carrizal Las Palmas 35240",
    "addr:housenumber":"7",
    "addr:postcode":"35240",
    "addr:street":"Avda Carlos V",
    "iso:country":"ES",
    "sg:address":"Avda Carlos V, 7",
    "sg:city":"Carrizal",
    "sg:orig_category":"Caf\u00c9s, Bares, Cervecer\u00cdas",
    "sg:phone":"+34 928 12 41 91",
    "sg:postcode":"35240",
    "sg:province":"Las Palmas",
    "wof:name":"Rodriguez Monzon Matias",
    "wof:placetype":"venue"
},
  "geometry": {"coordinates":[-15.4073095322,27.9099502563],"type":"Point"}
}