{
  "type": "Feature",
  "properties": {
    "addr:full":"Ctra. Puente Blanca, 7 Cha\u00f1e Segovia 40216",
    "addr:housenumber":"7",
    "addr:postcode":"40216",
    "addr:street":"Ctra. Puente Blanca;Segovia",
    "iso:country":"ES",
    "sg:address":"Ctra. Puente Blanca, 7",
    "sg:city":"Cha\u00f1e",
    "sg:orig_category":"Paletas",
    "sg:phone":"+34 921 15 58 48",
    "sg:postcode":"40216",
    "sg:province":"Segovia",
    "wof:name":"Pallets Y Embalajes Pascual S.l.",
    "wof:placetype":"venue"
},
  "geometry": {"coordinates":[-4.4277071953,41.3387870789],"type":"Point"}
}