{
  "type": "Feature",
  "properties": {
    "iso:country":"ES",
    "sg:address":"Av Meridiana, 211",
    "sg:city":"Barcelona",
    "sg:orig_category":"Bancos",
    "sg:phone":"+34 934 08 52 84",
    "sg:postcode":"08027",
    "sg:province":"Barcelona",
    "wof:name":"Bbva Factoring S.a. E.f.c",
    "wof:placetype":"venue"
},
  "geometry": {"coordinates":[2.1866929531,41.4157829285],"type":"Point"}
}