{
  "type": "Feature",
  "properties": {
    "iso:country":"ES",
    "sg:address":"Calle de Miguel Zazo, 27",
    "sg:city":"Melilla",
    "sg:orig_category":"Administraci\u00d3n En Agricultura",
    "sg:phone":"+34 952 68 58 25",
    "sg:postcode":"52004",
    "sg:province":"Melilla",
    "wof:name":"Agromelilla S.l.",
    "wof:placetype":"venue"
},
  "geometry": {"coordinates":[-2.944157,35.291073],"type":"Point"}
}