{
  "type": "Feature",
  "properties": {
    "addr:full":"S. Paio Do Monte, S/n San Paio Do Monte A Coru\u00f1a 15898",
    "addr:housenumber":"s / n",
    "addr:postcode":"15898",
    "addr:street":"Corun\u0303A",
    "iso:country":"ES",
    "sg:address":"S. Paio Do Monte, S/n",
    "sg:city":"San Paio Do Monte",
    "sg:orig_category":"Ense\u00d1anza, Formaci\u00d3n Profesional: Aprendizaje",
    "sg:phone":"+34 981 55 20 43",
    "sg:postcode":"15898",
    "sg:province":"A Coru\u00f1a",
    "wof:name":"Xunta De Galicia",
    "wof:placetype":"venue"
},
  "geometry": {"coordinates":[-8.5558214188,42.886013031],"type":"Point"}
}