{
  "type": "Feature",
  "properties": {
    "iso:country":"ES",
    "sg:address":"Calle de Huertos, 9",
    "sg:city":"Macael",
    "sg:orig_category":"Cajas Para Embalar",
    "sg:phone":"+34 950 12 60 72",
    "sg:postcode":"04867",
    "sg:province":"Almer\u00eda",
    "wof:name":"Cajamar",
    "wof:placetype":"venue"
},
  "geometry": {"coordinates":[-2.3054089546,37.3319282532],"type":"Point"}
}