{
  "type": "Feature",
  "properties": {
    "iso:country":"ES",
    "sg:address":"Muel Martinez Catena, 6",
    "sg:city":"Isla Cristina",
    "sg:orig_category":"Fabricaci\u00d3n, Reparaci\u00d3n Y Mantenimiento De Construcciones Navales Y Fluviales",
    "sg:phone":"+34 959 33 17 94",
    "sg:postcode":"21410",
    "sg:province":"Huelva",
    "wof:name":"Reafer S.l.",
    "wof:placetype":"venue"
},
  "geometry": {"coordinates":[-7.3284139633,37.2023353577],"type":"Point"}
}