{
  "type": "Feature",
  "properties": {
    "addr:full":"Calle de Obispo Cobos, 7 Ubeda Ja\u00e9n 23400",
    "addr:housenumber":"7",
    "addr:postcode":"23400",
    "addr:street":"Calle De Obispo Cobos;Jae\u0301N",
    "iso:country":"ES",
    "sg:address":"Calle de Obispo Cobos, 7",
    "sg:city":"Ubeda",
    "sg:orig_category":"Ropa Para Ni\u00d1os (al Por Menor)",
    "sg:phone":"+34 953 75 36 94",
    "sg:postcode":"23400",
    "sg:province":"Ja\u00e9n",
    "wof:name":"Due\u00f1as Latorre Antonio",
    "wof:placetype":"venue"
},
  "geometry": {"coordinates":[-3.376899004,38.0114135742],"type":"Point"}
}