{
  "type": "Feature",
  "properties": {
    "addr:full":"Soto De La Barca, 23 La Barca Asturias 33876",
    "addr:housenumber":"23",
    "addr:postcode":"33876",
    "addr:street":"La Barca",
    "iso:country":"ES",
    "sg:address":"Soto De La Barca, 23",
    "sg:city":"La Barca",
    "sg:orig_category":"Iglesia Cat\u00d3lica",
    "sg:phone":"+34 985 80 14 46",
    "sg:postcode":"33876",
    "sg:province":"Asturias",
    "wof:name":"Diocesis De Oviedo",
    "wof:placetype":"venue"
},
  "geometry": {"coordinates":[-6.4057312012,43.3230934143],"type":"Point"}
}