{
  "type": "Feature",
  "properties": {
    "iso:country":"ES",
    "sg:address":"Carrer de Can Campaner, 5",
    "sg:city":"Palma",
    "sg:orig_category":"M\u00c9dicos: Estomatolog\u00cda",
    "sg:phone":"+34 971 72 42 49",
    "sg:postcode":"07003",
    "sg:province":"Islas Baleares",
    "wof:name":"Rotger Gelabert Juan",
    "wof:placetype":"venue"
},
  "geometry": {"coordinates":[2.6495800018,39.5722846985],"type":"Point"}
}