{
  "type": "Feature",
  "properties": {
    "iso:country":"ES",
    "sg:address":"Calle de Moreras (de Las), 44",
    "sg:city":"Aranjuez",
    "sg:orig_category":"Contenedores (mercanc\u00cdas)",
    "sg:phone":"+34 918 92 55 07",
    "sg:postcode":"28300",
    "sg:province":"Madrid",
    "wof:name":"Diaz Escribano Jose Luis",
    "wof:placetype":"venue"
},
  "geometry": {"coordinates":[-3.5891230106,40.0348548889],"type":"Point"}
}