{
  "type": "Feature",
  "properties": {
    "iso:country":"ES",
    "sg:address":"Calle de Aire, 6",
    "sg:city":"Sevilla",
    "sg:orig_category":"Goma: Materias Primas (producci\u00d3n, Distribuci\u00d3n)",
    "sg:phone":"+34 954 45 95 84",
    "sg:postcode":"41004",
    "sg:province":"Sevilla",
    "sg:website":"www.goysa.com",
    "wof:name":"Goysa 8 S.l.",
    "wof:placetype":"venue"
},
  "geometry": {"coordinates":[-5.9905190468,37.3880805969],"type":"Point"}
}