{
  "type": "Feature",
  "properties": {
    "addr:full":"Carrer de Pintor Vayreda, 16 Palau-solita I Plegamans Barcelona 08184",
    "addr:housenumber":"16",
    "addr:postcode":"08184",
    "addr:street":"Carrer De Pintor Vayreda",
    "iso:country":"ES",
    "sg:address":"Carrer de Pintor Vayreda, 16",
    "sg:city":"Palau-solita I Plegamans",
    "sg:orig_category":"Peluquer\u00cdas, Peluquer\u00cda Mixta",
    "sg:phone":"+34 938 64 94 98",
    "sg:postcode":"08184",
    "sg:province":"Barcelona",
    "wof:name":"Orihuela Gonzalez Sonia",
    "wof:placetype":"venue"
},
  "geometry": {"coordinates":[2.1764099598,41.5870246887],"type":"Point"}
}