{
  "type": "Feature",
  "properties": {
    "addr:full":"Calle de Vendeja, 12 Malaga M\u00e1laga 29001",
    "addr:housenumber":"12",
    "addr:postcode":"29001",
    "addr:street":"Calle De Vendeja;Ma\u0301Laga",
    "iso:country":"ES",
    "sg:address":"Calle de Vendeja, 12",
    "sg:city":"Malaga",
    "sg:orig_category":"Promotores Constructores",
    "sg:phone":"+34 952 22 72 39",
    "sg:postcode":"29001",
    "sg:province":"M\u00e1laga",
    "sg:website":"www.todoconstruccion.com",
    "wof:name":"T.c.campo S.l.",
    "wof:placetype":"venue"
},
  "geometry": {"coordinates":[-4.4215807915,36.7170066833],"type":"Point"}
}