{
  "type": "Feature",
  "properties": {
    "iso:country":"ES",
    "sg:address":"Ctra Molins De Rei, Km. 0013,0",
    "sg:city":"Rubi",
    "sg:orig_category":"Charcuter\u00cdas (al Por Mayor)",
    "sg:phone":"+34 935 88 12 16",
    "sg:postcode":"08191",
    "sg:province":"Barcelona",
    "wof:name":"El Bricaller S.l.",
    "wof:placetype":"venue"
},
  "geometry": {"coordinates":[2.0307109356,41.4825019836],"type":"Point"}
}