{
  "type": "Feature",
  "properties": {
    "addr:full":"Carrer de Algavira, 5 S. Feliu Guixols Girona 17220",
    "addr:housenumber":"5",
    "addr:postcode":"17220",
    "addr:street":"Carrer De Algavira;Feliu",
    "iso:country":"ES",
    "sg:address":"Carrer de Algavira, 5",
    "sg:city":"S. Feliu Guixols",
    "sg:orig_category":"Cl\u00cdnicas Dentales",
    "sg:phone":"+34 972 32 13 01",
    "sg:postcode":"17220",
    "sg:province":"Girona",
    "wof:name":"Algavida Dental Grup S.l.",
    "wof:placetype":"venue"
},
  "geometry": {"coordinates":[3.0299479961,41.7828063965],"type":"Point"}
}