{
  "type": "Feature",
  "properties": {
    "iso:country":"ES",
    "sg:address":"Calle de Jose De Vicente Mu\u00d1oz, 13",
    "sg:city":"Torrelodones",
    "sg:orig_category":"Zapatos (al Por Menor)",
    "sg:phone":"+34 918 59 05 66",
    "sg:postcode":"28250",
    "sg:province":"Madrid",
    "wof:name":"Perez Perez Celestino",
    "wof:placetype":"venue"
},
  "geometry": {"coordinates":[-3.9281868935,40.5765647888],"type":"Point"}
}