{
  "type": "Feature",
  "properties": {
    "addr:full":"Calle de Leon Y Castillo, 100 Pto. Rosario Las Palmas 35600",
    "addr:housenumber":"100",
    "addr:postcode":"35600",
    "addr:street":"Calle De Leon Y Castillo;Pto. Rosario Las",
    "iso:country":"ES",
    "sg:address":"Calle de Leon Y Castillo, 100",
    "sg:city":"Pto. Rosario",
    "sg:orig_category":"Librer\u00cdas",
    "sg:phone":"+34 928 85 84 85",
    "sg:postcode":"35600",
    "sg:province":"Las Palmas",
    "wof:name":"Calero Brito Maria Dunia",
    "wof:placetype":"venue"
},
  "geometry": {"coordinates":[-13.8651380539,28.5006694794],"type":"Point"}
}