{
  "type": "Feature",
  "properties": {
    "iso:country":"ES",
    "sg:address":"Calle de Villeneuve Les Avignon, 5",
    "sg:city":"Pe\u00f1iscola",
    "sg:orig_category":"Carnicer\u00cdas, Carnicer\u00cdas",
    "sg:phone":"+34 964 48 13 75",
    "sg:postcode":"12598",
    "sg:province":"Castell\u00f3n",
    "wof:name":"Carniceria Y Charcuteria Mari Sl",
    "wof:placetype":"venue"
},
  "geometry": {"coordinates":[-0.0456800014,39.9851417542],"type":"Point"}
}