{
  "type": "Feature",
  "properties": {
    "addr:full":"Avda Valladolid, 41 Palencia Palencia 34004",
    "addr:housenumber":"41",
    "addr:postcode":"34004",
    "addr:street":"Avda Valladolid",
    "iso:country":"ES",
    "sg:address":"Avda Valladolid, 41",
    "sg:city":"Palencia",
    "sg:orig_category":"Supermercados Y Hipermercados",
    "sg:phone":"+34 979 72 48 00",
    "sg:postcode":"34004",
    "sg:province":"Palencia",
    "wof:name":"Distribuidora Internacional De Alimentacion S.a.",
    "wof:placetype":"venue"
},
  "geometry": {"coordinates":[-4.5247468948,41.9994392395],"type":"Point"}
}