{
  "type": "Feature",
  "properties": {
    "addr:full":"Carrer de Lima, 16 Barcelona Barcelona 08030",
    "addr:housenumber":"16",
    "addr:postcode":"08030",
    "addr:street":"Carrer De Lima",
    "iso:country":"ES",
    "sg:address":"Carrer de Lima, 16",
    "sg:city":"Barcelona",
    "sg:orig_category":"Farmacias",
    "sg:phone":"+34 933 45 06 62",
    "sg:postcode":"08030",
    "sg:province":"Barcelona",
    "wof:name":"Faus Riera Nuria",
    "wof:placetype":"venue"
},
  "geometry": {"coordinates":[2.2050909996,41.4392051697],"type":"Point"}
}