{
  "type": "Feature",
  "properties": {
    "addr:full":"Carrer de Lacy, 62 Sabadell Barcelona 08202",
    "addr:housenumber":"62",
    "addr:postcode":"08202",
    "addr:street":"Carrer De Lacy",
    "iso:country":"ES",
    "sg:address":"Carrer de Lacy, 62",
    "sg:city":"Sabadell",
    "sg:orig_category":"Psicoterapeutas",
    "sg:phone":"+34 937 47 84 01",
    "sg:postcode":"08202",
    "sg:province":"Barcelona",
    "wof:name":"Ventura Pallarols Carles",
    "wof:placetype":"venue"
},
  "geometry": {"coordinates":[2.1124129295,41.5443153381],"type":"Point"}
}