{
  "type": "Feature",
  "properties": {
    "addr:full":"Calle de Alfonso Xii, 33 Mostoles Madrid 28934",
    "addr:housenumber":"33",
    "addr:postcode":"28934",
    "addr:street":"Calle De Alfonso Xii",
    "iso:country":"ES",
    "sg:address":"Calle de Alfonso Xii, 33",
    "sg:city":"Mostoles",
    "sg:orig_category":"Sociedades, Compa\u00d1\u00cdas Aseguradoras",
    "sg:phone":"+34 916 14 77 57",
    "sg:postcode":"28934",
    "sg:province":"Madrid",
    "wof:name":"Mapfre Servicios De Informatica",
    "wof:placetype":"venue"
},
  "geometry": {"coordinates":[-3.874535799,40.3178329468],"type":"Point"}
}