{
  "type": "Feature",
  "properties": {
    "addr:full":"Calle de Viena, 3 Torrejon Ardoz Madrid 28850",
    "addr:housenumber":"3",
    "addr:postcode":"28850",
    "addr:street":"Calle De Viena",
    "iso:country":"ES",
    "sg:address":"Calle de Viena, 3",
    "sg:city":"Torrejon Ardoz",
    "sg:classifiers":[
        {
            "category":"Autos & Motor Vehicles",
            "subcategory":"Automobile Sales",
            "type":"Retail Goods"
        }
    ],
    "sg:phone":"+34 916 56 17 48",
    "sg:postcode":"28850",
    "sg:province":"Madrid",
    "wof:name":"Automoviles Olivares S.l.",
    "wof:placetype":"venue"
},
  "geometry": {"coordinates":[-3.4747369289,40.460723877],"type":"Point"}
}