{
  "type": "Feature",
  "properties": {
    "addr:full":"Calle de Catalina Gibaja, 36 Ortuella Vizcaya 48530",
    "addr:housenumber":"36",
    "addr:postcode":"48530",
    "addr:street":"Calle De Catalina Gibaja",
    "iso:country":"ES",
    "sg:address":"Calle de Catalina Gibaja, 36",
    "sg:city":"Ortuella",
    "sg:orig_category":"Carnicer\u00cdas, Carnicer\u00cdas",
    "sg:phone":"+34 946 64 01 79",
    "sg:postcode":"48530",
    "sg:province":"Vizcaya",
    "wof:name":"Larrinaga Bilbao Leoncio",
    "wof:placetype":"venue"
},
  "geometry": {"coordinates":[-3.0560581684,43.3099784851],"type":"Point"}
}