{
  "type": "Feature",
  "properties": {
    "iso:country":"ES",
    "sg:address":"Calle de Occidente, S/n",
    "sg:city":"Arroyo De La Miel-benalmadena Costa",
    "sg:orig_category":"Cl\u00cdnicas M\u00c9dicas",
    "sg:phone":"+34 952 44 47 37",
    "sg:postcode":"29630",
    "sg:province":"M\u00e1laga",
    "wof:name":"Clinica Salus Benalmadena S.a.",
    "wof:placetype":"venue"
},
  "geometry": {"coordinates":[-4.5224499702,36.5992584229],"type":"Point"}
}