{
  "type": "Feature",
  "properties": {
    "addr:full":"Calle de Agra Del Orzan, 31 Coru\u00d1a La Coru\u00f1a 15010",
    "addr:housenumber":"31",
    "addr:postcode":"15010",
    "addr:street":"Calle De Agra Del Orzan;La Corun\u0303A",
    "iso:country":"ES",
    "sg:address":"Calle de Agra Del Orzan, 31",
    "sg:city":"Coru\u00d1a",
    "sg:orig_category":"Peluquer\u00cdas, Peluquer\u00cda Mixta",
    "sg:phone":"+34 981 25 53 23",
    "sg:postcode":"15010",
    "sg:province":"La Coru\u00f1a",
    "wof:name":"Destellos S.l.",
    "wof:placetype":"venue"
},
  "geometry": {"coordinates":[-8.4204177856,43.3623199463],"type":"Point"}
}