{
  "type": "Feature",
  "properties": {
    "addr:full":"Calle de Alonso Cano, 101 Madrid Madrid 28003",
    "addr:housenumber":"101",
    "addr:postcode":"28003",
    "addr:street":"Calle De Alonso Cano",
    "iso:country":"ES",
    "sg:address":"Calle de Alonso Cano, 101",
    "sg:city":"Madrid",
    "sg:orig_category":"Ropa Y Accesorios",
    "sg:phone":"+34 915 54 69 32",
    "sg:postcode":"28003",
    "sg:province":"Madrid",
    "wof:name":"Perez Gonzalez Maria Dolores",
    "wof:placetype":"venue"
},
  "geometry": {"coordinates":[-3.6971933842,40.4457931519],"type":"Point"}
}