{
  "type": "Feature",
  "properties": {
    "iso:country":"ES",
    "sg:address":"Avda Antonio Hurtado, 9",
    "sg:city":"Caceres",
    "sg:orig_category":"Herboristas (al Por Menor)",
    "sg:phone":"+34 927 24 38 53",
    "sg:postcode":"10002",
    "sg:province":"C\u00e1ceres",
    "wof:name":"Parron Trevejo Lucia",
    "wof:placetype":"venue"
},
  "geometry": {"coordinates":[-6.3777618408,39.4673500061],"type":"Point"}
}