{
  "type": "Feature",
  "properties": {
    "addr:full":"Calle de Doctor Cortezo, 17 Madrid Madrid 28012",
    "addr:housenumber":"17",
    "addr:postcode":"madrid;28012",
    "addr:street":"Calle De Doctor Cortezo",
    "iso:country":"ES",
    "sg:address":"Calle de Doctor Cortezo, 17",
    "sg:city":"Madrid",
    "sg:orig_category":"Confecci\u00d3n De Cinturones Y De Tirantes",
    "sg:phone":"+34 914 29 24 73",
    "sg:postcode":"28012",
    "sg:province":"Madrid",
    "sg:website":"www.villaryponce.com",
    "wof:name":"Villar Y Ponce S.l.",
    "wof:placetype":"venue"
},
  "geometry": {"coordinates":[-3.7036950588,40.4128684998],"type":"Point"}
}