{
  "type": "Feature",
  "properties": {
    "addr:full":"Carrer de Sinia, 2 Zona Costera Tarragona 43883",
    "addr:housenumber":"2",
    "addr:postcode":"43883",
    "addr:street":"Carrer De Sinia;Costera",
    "iso:country":"ES",
    "sg:address":"Carrer de Sinia, 2",
    "sg:city":"Zona Costera",
    "sg:orig_category":"Asociaciones Y Clubs Deportivos",
    "sg:phone":"+34 977 80 09 12",
    "sg:postcode":"43883",
    "sg:province":"Tarragona",
    "wof:name":"Deportiva Costa Dorada Las Piscinas S.a.",
    "wof:placetype":"venue"
},
  "geometry": {"coordinates":[1.4858100414,41.1724891663],"type":"Point"}
}