{
  "type": "Feature",
  "properties": {
    "addr:full":"Dis Peralta, S/n Bormujos Sevilla 41930",
    "addr:housenumber":"s / n",
    "addr:postcode":"41930",
    "addr:street":"Peralta",
    "iso:country":"ES",
    "sg:address":"Dis Peralta, S/n",
    "sg:city":"Bormujos",
    "sg:orig_category":"Empresas De Carpinter\u00cda Met\u00c1lica",
    "sg:phone":"+34 955 72 33 08",
    "sg:postcode":"41930",
    "sg:province":"Sevilla",
    "wof:name":"Olivero Caama\u00f1o Jose Luis",
    "wof:placetype":"venue"
},
  "geometry": {"coordinates":[-6.0788531303,37.3489456177],"type":"Point"}
}