{
  "type": "Feature",
  "properties": {
    "addr:full":"Calle de Nicolas Navas, 16 Roquetas Mar Almer\u00eda 04740",
    "addr:housenumber":"16",
    "addr:postcode":"04740",
    "addr:street":"Calle De Nicolas Navas",
    "iso:country":"ES",
    "sg:address":"Calle de Nicolas Navas, 16",
    "sg:city":"Roquetas Mar",
    "sg:orig_category":"Compraventa De Antig\u00dcedades",
    "sg:phone":"+34 950 32 53 53",
    "sg:postcode":"04740",
    "sg:province":"Almer\u00eda",
    "wof:name":"Manuel Amat S.l.",
    "wof:placetype":"venue"
},
  "geometry": {"coordinates":[-2.6124989986,36.7638435364],"type":"Point"}
}