{
  "type": "Feature",
  "properties": {
    "addr:full":"Calle de Bergara, 23 Donostia-san Sebastian Guip\u00f9zcoa 20005",
    "addr:housenumber":"23",
    "addr:postcode":"20005",
    "addr:street":"Calle De Bergara",
    "iso:country":"ES",
    "sg:address":"Calle de Bergara, 23",
    "sg:city":"Donostia-san Sebastian",
    "sg:orig_category":"Bordado, Marcado A Medida",
    "sg:phone":"+34 943 42 01 31",
    "sg:postcode":"20005",
    "sg:province":"Guip\u00f9zcoa",
    "wof:name":"Alonso Letona Maria Angeles",
    "wof:placetype":"venue"
},
  "geometry": {"coordinates":[-1.979820013,43.3182830811],"type":"Point"}
}