{
  "type": "Feature",
  "properties": {
    "iso:country":"ES",
    "sg:address":"Avda Mediterraneo, 18",
    "sg:city":"Madrid",
    "sg:orig_category":"Abogados",
    "sg:phone":"+34 915 51 00 03",
    "sg:postcode":"28007",
    "sg:province":"Madrid",
    "wof:name":"Alvarez Alvarez Maria Teresa",
    "wof:placetype":"venue"
},
  "geometry": {"coordinates":[-3.6754910946,40.4071769714],"type":"Point"}
}