{
  "type": "Feature",
  "properties": {
    "iso:country":"ES",
    "sg:address":"Calle de Montenebros, 16",
    "sg:city":"Marbella",
    "sg:orig_category":"Hoteles",
    "sg:phone":"+34 952 92 44 67",
    "sg:postcode":"29600",
    "sg:province":"M\u00e1laga",
    "wof:name":"Feito Rodriguez Paloma",
    "wof:placetype":"venue"
},
  "geometry": {"coordinates":[-4.8853192329,36.5115814209],"type":"Point"}
}