{
  "type": "Feature",
  "properties": {
    "iso:country":"ES",
    "sg:address":"Pla\u00c7 Porta De Mallorca, S/n",
    "sg:city":"Alcudia",
    "sg:orig_category":"Auditores De Empresas",
    "sg:phone":"+34 971 54 63 98",
    "sg:postcode":"07400",
    "sg:province":"Islas Baleares",
    "sg:website":"www.alcudia.net",
    "wof:name":"Ajuntament D'alcudia",
    "wof:placetype":"venue"
},
  "geometry": {"coordinates":[3.087678194,39.8478126526],"type":"Point"}
}