{
  "type": "Feature",
  "properties": {
    "addr:full":"Canigo, 3 Vilablareix Girona 17180",
    "addr:housenumber":"3",
    "addr:postcode":"17180",
    "addr:street":"Canigo",
    "iso:country":"ES",
    "sg:address":"Canigo, 3",
    "sg:city":"Vilablareix",
    "sg:orig_category":"Equipo De Refrigeraci\u00d3n Industrial",
    "sg:phone":"+34 972 23 19 61",
    "sg:postcode":"17180",
    "sg:province":"Girona",
    "wof:name":"Tura S.l.",
    "wof:placetype":"venue"
},
  "geometry": {"coordinates":[2.7965319157,41.9542808533],"type":"Point"}
}