{
  "type": "Feature",
  "properties": {
    "iso:country":"ES",
    "sg:address":"Calle de Padre Tomas Monta\u00d1ana, 12",
    "sg:city":"Valencia",
    "sg:orig_category":"Asesor\u00cdas Y Estudios Financieros",
    "sg:phone":"+34 963 69 92 20",
    "sg:postcode":"46023",
    "sg:province":"Valencia",
    "wof:name":"Gonzalez Recio Silvia",
    "wof:placetype":"venue"
},
  "geometry": {"coordinates":[-0.3519349992,39.464641571],"type":"Point"}
}