{
  "type": "Feature",
  "properties": {
    "iso:country":"ES",
    "sg:address":"Victor Jose Amador Purificacion, 48",
    "sg:city":"Talavera Real",
    "sg:orig_category":"Fotograf\u00cda Art\u00cdstica Y Retratos",
    "sg:phone":"+34 924 44 06 21",
    "sg:postcode":"06140",
    "sg:province":"Badajoz",
    "wof:name":"Aguilar Pina Manuel",
    "wof:placetype":"venue"
},
  "geometry": {"coordinates":[-6.9702835083,38.8785972595],"type":"Point"}
}