{
  "type": "Feature",
  "properties": {
    "iso:country":"ES",
    "sg:address":"Mar De Alboran, 28",
    "sg:city":"Puerto Mazarron",
    "sg:orig_category":"Periodistas Profesionales",
    "sg:phone":"+34 968 59 57 24",
    "sg:postcode":"30860",
    "sg:province":"Murcia",
    "wof:name":"Martinez De La Vieja Maria Dolores",
    "wof:placetype":"venue"
},
  "geometry": {"coordinates":[-1.2783590555,37.5635910034],"type":"Point"}
}