{
  "type": "Feature",
  "properties": {
    "iso:country":"ES",
    "sg:address":"Agra Da Eira, S/n",
    "sg:city":"Porto Son",
    "sg:orig_category":"Electrodom\u00c9sticos (al Por Menor)",
    "sg:phone":"+34 981 76 71 91",
    "sg:postcode":"15970",
    "sg:province":"La Coru\u00f1a",
    "wof:name":"Dominguez Santamaria Juan Jose",
    "wof:placetype":"venue"
},
  "geometry": {"coordinates":[-9.0056743622,42.7230262756],"type":"Point"}
}