{
  "type": "Feature",
  "properties": {
    "iso:country":"ES",
    "sg:address":"Cami Mig, 102",
    "sg:city":"Cabrera Mar",
    "sg:orig_category":"Flores Y Plantas Naturales (al Por Mayor)",
    "sg:phone":"+34 937 56 60 48",
    "sg:postcode":"08349",
    "sg:province":"Barcelona",
    "wof:name":"Ponflor S.l",
    "wof:placetype":"venue"
},
  "geometry": {"coordinates":[2.4098000526,41.524559021],"type":"Point"}
}