{
  "type": "Feature",
  "properties": {
    "iso:country":"ES",
    "sg:address":"Calle de Martires, 9",
    "sg:city":"Malaga",
    "sg:orig_category":"Centros Comerciales Y Grandes Tiendas",
    "sg:phone":"+34 952 60 19 36",
    "sg:postcode":"29008",
    "sg:province":"M\u00e1laga",
    "wof:name":"Gil Moreno Jose",
    "wof:placetype":"venue"
},
  "geometry": {"coordinates":[-4.4231548309,36.7217330933],"type":"Point"}
}