{
  "type": "Feature",
  "properties": {
    "addr:full":"Carr D. Juan Antonio Baldovi, 1 Benidorm Alicante 03500",
    "addr:housenumber":"1",
    "addr:postcode":"03500",
    "addr:street":"Carr D. Juan Antonio Baldovi",
    "iso:country":"ES",
    "sg:address":"Carr D. Juan Antonio Baldovi, 1",
    "sg:city":"Benidorm",
    "sg:orig_category":"Molduras, Junquillos, Listones Y Molduras Perforadas",
    "sg:phone":"+34 965 86 31 81",
    "sg:postcode":"03500",
    "sg:province":"Alicante",
    "wof:name":"La Luna C.b.",
    "wof:placetype":"venue"
},
  "geometry": {"coordinates":[-0.1743289977,38.5408058167],"type":"Point"}
}