{
  "type": "Feature",
  "properties": {
    "addr:full":"C/ Picasso, S/n Salt Girona 17190",
    "addr:housenumber":"s / n",
    "addr:postcode":"17190",
    "addr:street":"C / Picasso",
    "iso:country":"ES",
    "sg:address":"C/ Picasso, S/n",
    "sg:city":"Salt",
    "sg:orig_category":"Mec\u00c1nico Del Autom\u00d3vil",
    "sg:phone":"+34 972 23 15 18",
    "sg:postcode":"17190",
    "sg:province":"Girona",
    "wof:name":"Taller Hernando S.c.",
    "wof:placetype":"venue"
},
  "geometry": {"coordinates":[2.7876000404,41.9722633362],"type":"Point"}
}