{
  "type": "Feature",
  "properties": {
    "iso:country":"ES",
    "sg:address":"Avda Vilari\u00d1o, 118",
    "sg:city":"Cambados",
    "sg:orig_category":"Flores Y Plantas Naturales (al Por Mayor)",
    "sg:phone":"+34 986 54 27 52",
    "sg:postcode":"36630",
    "sg:province":"Pontevedra",
    "wof:name":"Vi\u00f1as Fernandez Maria Del Carmen",
    "wof:placetype":"venue"
},
  "geometry": {"coordinates":[-8.8133602142,42.515712738],"type":"Point"}
}