{
  "type": "Feature",
  "properties": {
    "addr:full":"Calle de Constantino, 9 Palmas De Gran Canaria Las Palmas 35002",
    "addr:housenumber":"9",
    "addr:postcode":"35002",
    "addr:street":"Calle De Constantino",
    "iso:country":"ES",
    "sg:address":"Calle de Constantino, 9",
    "sg:city":"Palmas De Gran Canaria",
    "sg:orig_category":"Sindicatos De Trabajadores",
    "sg:phone":"+34 928 43 32 20",
    "sg:postcode":"35002",
    "sg:province":"Las Palmas",
    "wof:name":"Convergencia Sindical Canaria",
    "wof:placetype":"venue"
},
  "geometry": {"coordinates":[-15.4168729782,28.1058444977],"type":"Point"}
}