{
  "type": "Feature",
  "properties": {
    "iso:country":"ES",
    "sg:address":"Avda Xubia, 26",
    "sg:city":"Xubia-casadelos",
    "sg:orig_category":"Cl\u00cdnicas M\u00c9dicas",
    "sg:phone":"+34 981 34 76 67",
    "sg:postcode":"15510",
    "sg:province":"La Coru\u00f1a",
    "wof:name":"Cienfuegos Diaz Maria Fernanda",
    "wof:placetype":"venue"
},
  "geometry": {"coordinates":[-8.1507492065,43.5155944824],"type":"Point"}
}