{
  "type": "Feature",
  "properties": {
    "addr:full":"Calle de Rancho, 20 Aguadulce Almer\u00eda 04720",
    "addr:housenumber":"20",
    "addr:postcode":"04720",
    "addr:street":"Calle De Rancho;Almeri\u0301A",
    "iso:country":"ES",
    "sg:address":"Calle de Rancho, 20",
    "sg:city":"Aguadulce",
    "sg:orig_category":"Agentes Generales De Seguros",
    "sg:phone":"+34 950 34 72 91",
    "sg:postcode":"04720",
    "sg:province":"Almer\u00eda",
    "wof:name":"Camps  Peter",
    "wof:placetype":"venue"
},
  "geometry": {"coordinates":[-2.5741510391,36.8138160706],"type":"Point"}
}