{
  "type": "Feature",
  "properties": {
    "iso:country":"ES",
    "sg:address":"Calle de Maestro Ricardo Lopez, 2",
    "sg:city":"Villanueva Arzobispo",
    "sg:orig_category":"Obras Y Organismos Sociales",
    "sg:phone":"+34 953 45 10 61",
    "sg:postcode":"23330",
    "sg:province":"Ja\u00e9n",
    "wof:name":"Patronato De Fundacion Jose L. Bueno",
    "wof:placetype":"venue"
},
  "geometry": {"coordinates":[-3.0110599995,38.1682434082],"type":"Point"}
}