{
  "type": "Feature",
  "properties": {
    "iso:country":"ES",
    "sg:address":"Calle de Erribera, 30",
    "sg:city":"Plentzia",
    "sg:orig_category":"Electrodom\u00c9sticos (al Por Menor)",
    "sg:phone":"+34 946 77 03 44",
    "sg:postcode":"48620",
    "sg:province":"Vizcaya",
    "wof:name":"Astorquiza Bustinza Ignacio",
    "wof:placetype":"venue"
},
  "geometry": {"coordinates":[-2.9484100342,43.4039459229],"type":"Point"}
}