{
  "type": "Feature",
  "properties": {
    "iso:country":"ES",
    "sg:address":"Carrer de Eusebi Guell, 7",
    "sg:city":"S. Boi Llobregat",
    "sg:orig_category":"Peluquer\u00cdas, Peluquer\u00cda Mixta",
    "sg:phone":"+34 936 30 49 52",
    "sg:postcode":"08830",
    "sg:province":"Barcelona",
    "wof:name":"Trejo Murillo Antonio",
    "wof:placetype":"venue"
},
  "geometry": {"coordinates":[2.0356709957,41.3477630615],"type":"Point"}
}