{
  "type": "Feature",
  "properties": {
    "iso:country":"ES",
    "sg:address":"Los Mocanes, 29",
    "sg:city":"Carrizal",
    "sg:orig_category":"Transporte En General",
    "sg:phone":"+34 928 73 40 75",
    "sg:postcode":"35240",
    "sg:province":"Las Palmas",
    "wof:name":"Canarias Ofitec S.l.",
    "wof:placetype":"venue"
},
  "geometry": {"coordinates":[-15.4088487625,27.9120388031],"type":"Point"}
}