{
  "type": "Feature",
  "properties": {
    "iso:country":"ES",
    "sg:address":"Carr Prat De La Riba, 74",
    "sg:city":"Juneda",
    "sg:orig_category":"Arquitectos",
    "sg:phone":"+34 973 15 13 71",
    "sg:postcode":"25430",
    "sg:province":"Lleida",
    "wof:name":"Sedo Sole Juan",
    "wof:placetype":"venue"
},
  "geometry": {"coordinates":[0.8235380054,41.5498733521],"type":"Point"}
}