{
  "type": "Feature",
  "properties": {
    "addr:full":"Av Sant Joan De Deu, 117 Playa De Calafell Tarragona 43820",
    "addr:housenumber":"117",
    "addr:postcode":"43820",
    "addr:street":"Av Sant Joan De Deu",
    "iso:country":"ES",
    "sg:address":"Av Sant Joan De Deu, 117",
    "sg:city":"Playa De Calafell",
    "sg:orig_category":"Inmobiliaria (agencias)",
    "sg:phone":"+34 977 69 14 35",
    "sg:postcode":"43820",
    "sg:province":"Tarragona",
    "wof:name":"Rendanau S.l.",
    "wof:placetype":"venue"
},
  "geometry": {"coordinates":[1.5797450542,41.1879425049],"type":"Point"}
}