{
  "type": "Feature",
  "properties": {
    "addr:full":"Pg Maritim, 7 Sitges Barcelona 08870",
    "addr:housenumber":"7",
    "addr:postcode":"08870",
    "addr:street":"Pg Maritim",
    "iso:country":"ES",
    "sg:address":"Pg Maritim, 7",
    "sg:city":"Sitges",
    "sg:orig_category":"Abogados",
    "sg:phone":"+34 938 94 54 62",
    "sg:postcode":"08870",
    "sg:province":"Barcelona",
    "wof:name":"Jaume-bosch Goma Ana Maria",
    "wof:placetype":"venue"
},
  "geometry": {"coordinates":[1.802932024,41.2335624695],"type":"Point"}
}