{
  "type": "Feature",
  "properties": {
    "addr:full":"Av Puig I Cadafalch, 226 Mataro Barcelona 08303",
    "addr:housenumber":"226",
    "addr:postcode":"08303",
    "addr:street":"Av Puig;Cadafalch",
    "iso:country":"ES",
    "sg:address":"Av Puig I Cadafalch, 226",
    "sg:city":"Mataro",
    "sg:orig_category":"Ropa Para Se\u00d1oras Y Caballeros (al Por Menor)",
    "sg:phone":"+34 937 98 14 14",
    "sg:postcode":"08303",
    "sg:province":"Barcelona",
    "wof:name":"Masley And Leymans S.l.",
    "wof:placetype":"venue"
},
  "geometry": {"coordinates":[2.4244201183,41.5405082703],"type":"Point"}
}