{
  "type": "Feature",
  "properties": {
    "addr:full":"Carrer de Pont Dels Estanyets (del), 6 Salou Tarragona 43840",
    "addr:housenumber":"6",
    "addr:postcode":"43840",
    "addr:street":"Carrer De Pont Dels Estanyets Del",
    "iso:country":"ES",
    "sg:address":"Carrer de Pont Dels Estanyets (del), 6",
    "sg:city":"Salou",
    "sg:orig_category":"Empresas De Carpinter\u00cda",
    "sg:phone":"+34 977 38 81 14",
    "sg:postcode":"43840",
    "sg:province":"Tarragona",
    "wof:name":"Cristaleria Salou Glass S.l.",
    "wof:placetype":"venue"
},
  "geometry": {"coordinates":[1.1319299936,41.0777511597],"type":"Point"}
}