{
  "type": "Feature",
  "properties": {
    "iso:country":"ES",
    "sg:address":"Rua Condesa Casa Barcena, 6",
    "sg:city":"Vigo",
    "sg:orig_category":"Agencias Y Agentes Comerciales, Representantes",
    "sg:phone":"+34 986 41 02 79",
    "sg:postcode":"36204",
    "sg:province":"Pontevedra",
    "wof:name":"Gonzalez Becerra Santiago Federico",
    "wof:placetype":"venue"
},
  "geometry": {"coordinates":[-8.711016655,42.2317199707],"type":"Point"}
}