{
  "type": "Feature",
  "properties": {
    "iso:country":"ES",
    "sg:address":"Carrer de Impresors Botella, 6",
    "sg:city":"Denia",
    "sg:orig_category":"Florister\u00cdas",
    "sg:phone":"+34 966 43 02 28",
    "sg:postcode":"03700",
    "sg:province":"Alicante",
    "wof:name":"Tiendas La Pinada S.l.",
    "wof:placetype":"venue"
},
  "geometry": {"coordinates":[0.0971110016,38.8395881653],"type":"Point"}
}