{
  "type": "Feature",
  "properties": {
    "iso:country":"ES",
    "sg:address":"Calle de Primautzar, 4",
    "sg:city":"Irun",
    "sg:orig_category":"Bebidas",
    "sg:phone":"+34 943 62 15 80",
    "sg:postcode":"20305",
    "sg:province":"Guip\u00f9zcoa",
    "wof:name":"Iparraguirre Aristi Jose Ignacio",
    "wof:placetype":"venue"
},
  "geometry": {"coordinates":[-1.8240770102,43.3280982971],"type":"Point"}
}