{
  "type": "Feature",
  "properties": {
    "iso:country":"ES",
    "sg:address":"La Fuente, 31",
    "sg:city":"Villaobispo De Las Regueras",
    "sg:orig_category":"Mec\u00c1nico Del Autom\u00d3vil",
    "sg:phone":"+34 987 30 70 76",
    "sg:postcode":"24007",
    "sg:province":"Le\u00f3n",
    "wof:name":"Lopez Bandera Luis Javier",
    "wof:placetype":"venue"
},
  "geometry": {"coordinates":[-5.5510334969,42.6136398315],"type":"Point"}
}