{
  "type": "Feature",
  "properties": {
    "iso:country":"ES",
    "sg:address":"Calle de Ermita, 5",
    "sg:city":"Burlada",
    "sg:orig_category":"Arreglo, Reparaci\u00d3n, Piezas Sueltas De Televisi\u00d3n, V\u00cddeo, Hi",
    "sg:phone":"+34 948 24 22 46",
    "sg:postcode":"31600",
    "sg:province":"Navarra",
    "wof:name":"Labiaga Silanes Jose",
    "wof:placetype":"venue"
},
  "geometry": {"coordinates":[-1.6164040565,42.8230323792],"type":"Point"}
}