{
  "type": "Feature",
  "properties": {
    "addr:full":"Agricultores (p I Gandul), 6 Mairena Alcor Sevilla 41510",
    "addr:housenumber":"6",
    "addr:postcode":"41510",
    "addr:street":"Gandul",
    "iso:country":"ES",
    "sg:address":"Agricultores (p I Gandul), 6",
    "sg:city":"Mairena Alcor",
    "sg:orig_category":"Electricidad: Equipos Industriales, Componentes (fabricaci\u00d3n)",
    "sg:phone":"+34 955 74 45 28",
    "sg:postcode":"41510",
    "sg:province":"Sevilla",
    "wof:name":"Comercial Electrica De Mayrena S.l.",
    "wof:placetype":"venue"
},
  "geometry": {"coordinates":[-5.7577037811,37.3626708984],"type":"Point"}
}