{
  "type": "Feature",
  "properties": {
    "addr:full":"Aita Lizarralde Kalea, 2 O\u00f1ati Guip\u00f9zcoa 20560",
    "addr:housenumber":"2",
    "addr:postcode":"20560",
    "addr:street":"Aita Lizarralde Kalea;Guipu\u0300Zcoa",
    "iso:country":"ES",
    "sg:address":"Aita Lizarralde Kalea, 2",
    "sg:city":"O\u00f1ati",
    "sg:orig_category":"Promotores Constructores",
    "sg:phone":"+34 943 78 05 54",
    "sg:postcode":"20560",
    "sg:province":"Guip\u00f9zcoa",
    "wof:name":"Ugarte Igartua Deogracias",
    "wof:placetype":"venue"
},
  "geometry": {"coordinates":[-2.4080920219,43.0313796997],"type":"Point"}
}