{
  "type": "Feature",
  "properties": {
    "addr:full":"Calle de Leon Y Castillo, 189 Palmas De Gran Canaria Las Palmas 35004",
    "addr:housenumber":"189",
    "addr:postcode":"35004",
    "addr:street":"Calle De Leon Y Castillo",
    "iso:country":"ES",
    "sg:address":"Calle de Leon Y Castillo, 189",
    "sg:city":"Palmas De Gran Canaria",
    "sg:orig_category":"Confecci\u00d3n De Trajes Para Se\u00d1oras",
    "sg:phone":"+34 928 24 02 22",
    "sg:postcode":"35004",
    "sg:province":"Las Palmas",
    "wof:name":"Hatoum Alvarez Maria Elena",
    "wof:placetype":"venue"
},
  "geometry": {"coordinates":[-15.4235563278,28.1178627014],"type":"Point"}
}