{
  "type": "Feature",
  "properties": {
    "addr:full":"Carrer de Terra Alta, 12 Premia Mar Barcelona 08330",
    "addr:housenumber":"12",
    "addr:postcode":"08330",
    "addr:street":"Carrer De Terra Alta",
    "iso:country":"ES",
    "sg:address":"Carrer de Terra Alta, 12",
    "sg:city":"Premia Mar",
    "sg:orig_category":"Platos Preparados Refrigerados (fabricaci\u00d3n, Al Por Mayor)",
    "sg:phone":"+34 937 51 39 53",
    "sg:postcode":"08330",
    "sg:province":"Barcelona",
    "wof:name":"Bec D'or S.c.p",
    "wof:placetype":"venue"
},
  "geometry": {"coordinates":[2.3694601059,41.4944572449],"type":"Point"}
}