{
  "type": "Feature",
  "properties": {
    "iso:country":"ES",
    "sg:address":"Calle de Alta, 36",
    "sg:city":"Teba",
    "sg:orig_category":"Bares, Piano",
    "sg:phone":"+34 952 74 82 45",
    "sg:postcode":"29327",
    "sg:province":"M\u00e1laga",
    "wof:name":"Maldonado Pinto Jose Alberto",
    "wof:placetype":"venue"
},
  "geometry": {"coordinates":[-4.9204134941,36.9810142517],"type":"Point"}
}