{
  "type": "Feature",
  "properties": {
    "iso:country":"ES",
    "sg:address":"Calle de Union (la), 42",
    "sg:city":"Andorra",
    "sg:orig_category":"Art\u00cdculos Funerarios (al Por Menor)",
    "sg:phone":"+34 978 88 06 34",
    "sg:postcode":"44500",
    "sg:province":"Teruel",
    "wof:name":"Funeraria San Macario S.l.",
    "wof:placetype":"venue"
},
  "geometry": {"coordinates":[-0.4497880042,40.9776992798],"type":"Point"}
}