{
  "type": "Feature",
  "properties": {
    "iso:country":"ES",
    "sg:address":"Carrer de Sant Pere, 48",
    "sg:city":"Lloret Mar",
    "sg:orig_category":"Bazares, Art\u00cdculos De Limpieza Y De Cocina (al Por Menor)",
    "sg:phone":"+34 972 36 53 20",
    "sg:postcode":"17310",
    "sg:province":"Girona",
    "wof:name":"Santafe Redon Ricardo",
    "wof:placetype":"venue"
},
  "geometry": {"coordinates":[2.846036911,41.7010803223],"type":"Point"}
}