{
  "type": "Feature",
  "properties": {
    "addr:full":"Calle de Obispo Covarrubias, 8 Zaragoza Zaragoza 50005",
    "addr:housenumber":"8",
    "addr:postcode":"50005",
    "addr:street":"Calle De Obispo Covarrubias",
    "iso:country":"ES",
    "sg:address":"Calle de Obispo Covarrubias, 8",
    "sg:city":"Zaragoza",
    "sg:orig_category":"Ebanister\u00cda",
    "sg:phone":"+34 976 35 14 16",
    "sg:postcode":"50005",
    "sg:province":"Zaragoza",
    "wof:name":"Gomez Colodrero Antonio",
    "wof:placetype":"venue"
},
  "geometry": {"coordinates":[-0.8984860182,41.6464576721],"type":"Point"}
}