{
  "type": "Feature",
  "properties": {
    "addr:full":"Barr Bengoetxe, 28 Kurtzea Vizcaya 48960",
    "addr:housenumber":"28",
    "addr:postcode":"48960",
    "addr:street":"Bengoetxe",
    "iso:country":"ES",
    "sg:address":"Barr Bengoetxe, 28",
    "sg:city":"Kurtzea",
    "sg:orig_category":"Molduras, Junquillos, Listones Y Molduras Perforadas",
    "sg:phone":"+34 944 57 24 85",
    "sg:postcode":"48960",
    "sg:province":"Vizcaya",
    "wof:name":"Phone Euskadi S. L.",
    "wof:placetype":"venue"
},
  "geometry": {"coordinates":[-2.8470389843,43.2298049927],"type":"Point"}
}