{
  "type": "Feature",
  "properties": {
    "addr:full":"Avda Andalucia, 64 Cadiz C\u00e1diz 11008",
    "addr:housenumber":"64",
    "addr:postcode":"11008",
    "addr:street":"Avda Andalucia",
    "iso:country":"ES",
    "sg:address":"Avda Andalucia, 64",
    "sg:city":"Cadiz",
    "sg:orig_category":"Ropa Para Se\u00d1oras Y Caballeros (al Por Menor)",
    "sg:phone":"+34 956 27 42 47",
    "sg:postcode":"11008",
    "sg:province":"C\u00e1diz",
    "sg:website":"www.grupocortefiel.com",
    "wof:name":"Cortefiel S.a.",
    "wof:placetype":"venue"
},
  "geometry": {"coordinates":[-6.2832632065,36.5171966553],"type":"Point"}
}