{
  "type": "Feature",
  "properties": {
    "addr:full":"Carr Rutlla, 20 Girona Girona 17002",
    "addr:housenumber":"20",
    "addr:postcode":"17002",
    "addr:street":"Carr Rutlla",
    "iso:country":"ES",
    "sg:address":"Carr Rutlla, 20",
    "sg:city":"Girona",
    "sg:orig_category":"Asociaciones, Organismos Culturales Y Socioeducativos",
    "sg:phone":"+34 972 22 82 40",
    "sg:postcode":"17002",
    "sg:province":"Girona",
    "wof:name":"Associacio Temps Per A La Gent Gran",
    "wof:placetype":"venue"
},
  "geometry": {"coordinates":[2.8234233856,41.9782104492],"type":"Point"}
}