{
  "type": "Feature",
  "properties": {
    "iso:country":"ES",
    "sg:address":"Avda Reyes Catolicos, 49",
    "sg:city":"Dos Hermanas",
    "sg:orig_category":"T\u00c9cnico",
    "sg:phone":"+34 955 67 90 03",
    "sg:postcode":"41700",
    "sg:province":"Sevilla",
    "wof:name":"Nazarena De Informatica Y Copiadoras; S.l.",
    "wof:placetype":"venue"
},
  "geometry": {"coordinates":[-5.9249000549,37.277973175],"type":"Point"}
}