{
  "type": "Feature",
  "properties": {
    "addr:full":"Calle de Navas De Tolosa, 1 Jaen Ja\u00e9n 23001",
    "addr:housenumber":"1;jae\u0301n",
    "addr:postcode":"23001",
    "addr:street":"Calle De Navas De Tolosa",
    "iso:country":"ES",
    "sg:address":"Calle de Navas De Tolosa, 1",
    "sg:city":"Jaen",
    "sg:orig_category":"Asesor\u00cda Sobre Comunicaci\u00d3n De Empresas",
    "sg:phone":"+34 953 22 59 07",
    "sg:postcode":"23001",
    "sg:province":"Ja\u00e9n",
    "wof:name":"Benavides Asesores C.b.",
    "wof:placetype":"venue"
},
  "geometry": {"coordinates":[-3.7874600887,37.7690315247],"type":"Point"}
}