{
  "type": "Feature",
  "properties": {
    "addr:full":"Calle de Escultor Gomez Del Rio, 7 Cordoba C\u00f3rdoba 14012",
    "addr:housenumber":"7",
    "addr:postcode":"14012",
    "addr:street":"Calle De Escultor Gomez Del Rio;Co\u0301Rdoba",
    "iso:country":"ES",
    "sg:address":"Calle de Escultor Gomez Del Rio, 7",
    "sg:city":"Cordoba",
    "sg:orig_category":"Comercio De Cuadros, L\u00c1minas Y Reproducciones De Obras De Arte",
    "sg:phone":"+34 957 40 40 41",
    "sg:postcode":"14012",
    "sg:province":"C\u00f3rdoba",
    "wof:name":"Bodoque Leon Juan",
    "wof:placetype":"venue"
},
  "geometry": {"coordinates":[-4.7815551758,37.9004020691],"type":"Point"}
}