{
  "type": "Feature",
  "properties": {
    "iso:country":"ES",
    "sg:address":"Avda Navia, S/n",
    "sg:city":"Becerrea",
    "sg:orig_category":"Comercio De Piezas De Recambio Y De Accesorios De Veh\u00cdculos, Veh\u00cdculos Industriales",
    "sg:phone":"+34 982 36 08 02",
    "sg:postcode":"27640",
    "sg:province":"Lugo",
    "wof:name":"T.odilo Y Delfin S.l.",
    "wof:placetype":"venue"
},
  "geometry": {"coordinates":[-7.1628661156,42.8585128784],"type":"Point"}
}