{
  "type": "Feature",
  "properties": {
    "addr:full":"Pase Ubarburu De, 15 Donostia-san Sebastian Guip\u00f9zcoa 20014",
    "addr:housenumber":"15",
    "addr:postcode":"20014",
    "iso:country":"ES",
    "sg:address":"Pase Ubarburu De, 15",
    "sg:city":"Donostia-san Sebastian",
    "sg:orig_category":"Fabricaci\u00d3n De Transformadores, De M\u00c1quinas Giratorias De Peque\u00d1a Y Media Potencia",
    "sg:phone":"+34 943 46 45 75",
    "sg:postcode":"20014",
    "sg:province":"Guip\u00f9zcoa",
    "wof:name":"Poli Transf",
    "wof:placetype":"venue"
},
  "geometry": {"coordinates":[-1.9009970427,43.2548027039],"type":"Point"}
}