{
  "type": "Feature",
  "properties": {
    "iso:country":"ES",
    "sg:address":"Pol Ind Palmera, 57",
    "sg:city":"Sevilla",
    "sg:orig_category":"Electricidad: Equipos Industriales, Componentes (fabricaci\u00d3n)",
    "sg:phone":"+34 954 69 02 61",
    "sg:postcode":"41014",
    "sg:province":"Sevilla",
    "wof:name":"Auxemec S.l.",
    "wof:placetype":"venue"
},
  "geometry": {"coordinates":[-5.9596791267,37.3278617859],"type":"Point"}
}