{
  "type": "Feature",
  "properties": {
    "iso:country":"ES",
    "sg:address":"Rier Capaspre, 10",
    "sg:city":"Calella",
    "sg:orig_category":"Molduras, Junquillos, Listones Y Molduras Perforadas",
    "sg:phone":"+34 937 66 00 14",
    "sg:postcode":"08370",
    "sg:province":"Barcelona",
    "wof:name":"Sahin  Sevket",
    "wof:placetype":"venue"
},
  "geometry": {"coordinates":[2.6551098824,41.6118736267],"type":"Point"}
}