{
  "type": "Feature",
  "properties": {
    "iso:country":"ES",
    "sg:address":"I Poligono, S/n",
    "sg:city":"Soria",
    "sg:orig_category":"Ebanistas Y Talladores De Muebles Y Objetos De Arte",
    "sg:phone":"+34 975 23 09 32",
    "sg:postcode":"42005",
    "sg:province":"Soria",
    "wof:name":"Mateo Crespo Jose Antonio",
    "wof:placetype":"venue"
},
  "geometry": {"coordinates":[-2.4691669941,41.7646598816],"type":"Point"}
}