{
  "type": "Feature",
  "properties": {
    "addr:full":"Carrer de Palet I Barba, 73 Terrassa Barcelona 08224",
    "addr:postcode":"08224",
    "addr:street":"Carrer De Palet;Barba",
    "iso:country":"ES",
    "sg:address":"Carrer de Palet I Barba, 73",
    "sg:city":"Terrassa",
    "sg:orig_category":"Zapatos (al Por Menor)",
    "sg:phone":"+34 937 88 46 90",
    "sg:postcode":"08224",
    "sg:province":"Barcelona",
    "wof:name":"Algaba Urbano Joan Carles",
    "wof:placetype":"venue"
},
  "geometry": {"coordinates":[1.9907480478,41.556842804],"type":"Point"}
}