{
  "type": "Feature",
  "properties": {
    "iso:country":"ES",
    "sg:address":"Av Lleida, 26",
    "sg:city":"Bellpuig",
    "sg:orig_category":"Caf\u00c9s, Bares, Cervecer\u00cdas",
    "sg:phone":"+34 973 32 10 49",
    "sg:postcode":"25250",
    "sg:province":"Lleida",
    "wof:name":"Vidal Querol Jordi",
    "wof:placetype":"venue"
},
  "geometry": {"coordinates":[1.0121870041,41.6319465637],"type":"Point"}
}