{
  "type": "Feature",
  "properties": {
    "addr:full":"Pg Verdaguer, 92 Igualada Barcelona 08700",
    "addr:housenumber":"92",
    "addr:postcode":"08700",
    "addr:street":"Pg Verdaguer",
    "iso:country":"ES",
    "sg:address":"Pg Verdaguer, 92",
    "sg:city":"Igualada",
    "sg:orig_category":"Administradores De Bienes Y Delegados De Comunidades De Propietarios",
    "sg:phone":"+34 938 03 07 56",
    "sg:postcode":"08700",
    "sg:province":"Barcelona",
    "wof:name":"Germans Riu Godo C.b.",
    "wof:placetype":"venue"
},
  "geometry": {"coordinates":[1.6207100153,41.5807800293],"type":"Point"}
}