{
  "type": "Feature",
  "properties": {
    "iso:country":"ES",
    "sg:address":"Ctra. Mojados, 90",
    "sg:city":"Megeces",
    "sg:orig_category":"Carros Elevadores, Carros De Operaciones Portuarias",
    "sg:phone":"+34 983 60 41 89",
    "sg:postcode":"47440",
    "sg:province":"Valladolid",
    "wof:name":"Hijos De Jacinto Sanz S.a.",
    "wof:placetype":"venue"
},
  "geometry": {"coordinates":[-4.5675888062,41.4071617126],"type":"Point"}
}