{
  "type": "Feature",
  "properties": {
    "addr:full":"Iglesia, 3 Terradillos Salamanca 37893",
    "addr:housenumber":"3",
    "addr:postcode":"37893",
    "addr:street":"Iglesia",
    "iso:country":"ES",
    "sg:address":"Iglesia, 3",
    "sg:city":"Terradillos",
    "sg:orig_category":"Cr\u00cda De Animales",
    "sg:phone":"+34 923 37 01 58",
    "sg:postcode":"37893",
    "sg:province":"Salamanca",
    "wof:name":"S.a.t. Marcos Pinto",
    "wof:placetype":"venue"
},
  "geometry": {"coordinates":[-5.5422458649,40.8392448425],"type":"Point"}
}