{
  "type": "Feature",
  "properties": {
    "iso:country":"ES",
    "sg:address":"Pl J. M. Batista I Roca, 2",
    "sg:city":"Gava",
    "sg:orig_category":"Empresas De Carpinter\u00cda De Madera",
    "sg:phone":"+34 936 62 68 52",
    "sg:postcode":"08850",
    "sg:province":"Barcelona",
    "wof:name":"Illanes Moreno Rafael",
    "wof:placetype":"venue"
},
  "geometry": {"coordinates":[2.0051929951,41.3077201843],"type":"Point"}
}