{
  "type": "Feature",
  "properties": {
    "iso:country":"ES",
    "sg:address":"Carrer de Valencia (de), 9",
    "sg:city":"Salou",
    "sg:orig_category":"Institutos De Belleza",
    "sg:phone":"+34 977 38 34 47",
    "sg:postcode":"43840",
    "sg:province":"Tarragona",
    "wof:name":"Rivero Humanes Gloria",
    "wof:placetype":"venue"
},
  "geometry": {"coordinates":[1.1305639744,41.0770606995],"type":"Point"}
}