{
  "type": "Feature",
  "properties": {
    "iso:country":"ES",
    "sg:address":"Carrer de Llan\u00c7a, 32",
    "sg:city":"Barcelona",
    "sg:orig_category":"Ingenier\u00cda, Centros De Estudios (diversos)",
    "sg:phone":"+34 933 25 20 87",
    "sg:postcode":"08015",
    "sg:province":"Barcelona",
    "wof:name":"Assessorament Industrial Agrari S.l.",
    "wof:placetype":"venue"
},
  "geometry": {"coordinates":[2.1494903564,41.3771018982],"type":"Point"}
}