{
  "type": "Feature",
  "properties": {
    "iso:country":"ES",
    "sg:address":"Agricultura (p I Ventilla), 2",
    "sg:city":"Marchena",
    "sg:orig_category":"Electricidad, Electr\u00d3nica: Material Y Suministros (al Por Mayor)",
    "sg:phone":"+34 954 84 44 15",
    "sg:postcode":"41620",
    "sg:province":"Sevilla",
    "wof:name":"Distribuciones Electricas Jacob De Guindos S.l.",
    "wof:placetype":"venue"
},
  "geometry": {"coordinates":[-5.4274511337,37.3266944885],"type":"Point"}
}