{
  "type": "Feature",
  "properties": {
    "addr:full":"Calle de Agustin De Betancourt, 19 Madrid Madrid 28003",
    "addr:housenumber":"19",
    "addr:postcode":"madrid;28003",
    "addr:street":"Calle De Agustin De Betancourt",
    "iso:country":"ES",
    "sg:address":"Calle de Agustin De Betancourt, 19",
    "sg:city":"Madrid",
    "sg:orig_category":"Psic\u00d3logos",
    "sg:phone":"+34 915 35 13 20",
    "sg:postcode":"28003",
    "sg:province":"Madrid",
    "wof:name":"De La Torre Zorrilla Concepcion",
    "wof:placetype":"venue"
},
  "geometry": {"coordinates":[-3.6951744556,40.4446792603],"type":"Point"}
}