{
  "type": "Feature",
  "properties": {
    "iso:country":"ES",
    "sg:address":"Trva Arrabales, 11",
    "sg:city":"Valverde Camino",
    "sg:orig_category":"Internados & Ense\u00d1anza Privada",
    "sg:phone":"+34 959 55 50 31",
    "sg:postcode":"21600",
    "sg:province":"Huelva",
    "wof:name":"Escuelas Profesionales Sagrada Familia",
    "wof:placetype":"venue"
},
  "geometry": {"coordinates":[-6.7513828278,37.5704574585],"type":"Point"}
}