{
  "type": "Feature",
  "properties": {
    "addr:full":"Calle de Pedro Mu\u00d1oz Seca, 23 Puerto De Santa Maria C\u00e1diz 11500",
    "addr:housenumber":"23",
    "addr:postcode":"11500",
    "addr:street":"Calle De Pedro Mun\u0303Oz Seca;Ca\u0301Diz",
    "iso:country":"ES",
    "sg:address":"Calle de Pedro Mu\u00d1oz Seca, 23",
    "sg:city":"Puerto De Santa Maria",
    "sg:orig_category":"Sociedades, Compa\u00d1\u00cdas Aseguradoras",
    "sg:phone":"+34 956 54 32 43",
    "sg:postcode":"11500",
    "sg:province":"C\u00e1diz",
    "wof:name":"Nortehispana De Seguros Y Reaseguros S.a.",
    "wof:placetype":"venue"
},
  "geometry": {"coordinates":[-6.2267351151,36.5985412598],"type":"Point"}
}