{
  "type": "Feature",
  "properties": {
    "iso:country":"ES",
    "sg:address":"G.v. Carles Iii, 74",
    "sg:city":"Barcelona",
    "sg:orig_category":"Abogados",
    "sg:phone":"+34 933 30 16 66",
    "sg:postcode":"08028",
    "sg:province":"Barcelona",
    "wof:name":"Acosta Vallino Gonzalo",
    "wof:placetype":"venue"
},
  "geometry": {"coordinates":[2.1275765896,41.3848152161],"type":"Point"}
}