{
  "type": "Feature",
  "properties": {
    "addr:full":"Camporrapado(pousada), S/n Ledesma La Coru\u00f1a 15882",
    "addr:housenumber":"s / n",
    "addr:postcode":"15882",
    "addr:street":"La Corun\u0303A",
    "iso:country":"ES",
    "sg:address":"Camporrapado(pousada), S/n",
    "sg:city":"Ledesma",
    "sg:orig_category":"Paletas",
    "sg:phone":"+34 981 51 41 08",
    "sg:postcode":"15882",
    "sg:province":"La Coru\u00f1a",
    "wof:name":"Amosa Andrade Antonio",
    "wof:placetype":"venue"
},
  "geometry": {"coordinates":[-8.3410644531,42.7965965271],"type":"Point"}
}