{
  "type": "Feature",
  "properties": {
    "addr:full":"Ria De Abaixo, 2 Ria De Abaixo Pontevedra 36154",
    "addr:housenumber":"2",
    "addr:postcode":"36154",
    "addr:street":"Abaixo",
    "iso:country":"ES",
    "sg:address":"Ria De Abaixo, 2",
    "sg:city":"Ria De Abaixo",
    "sg:orig_category":"Muebles Y Accesorios Para Cocinas Y Cuartos De Ba\u00d1o (al Por Menor)",
    "sg:phone":"+34 986 84 23 64",
    "sg:postcode":"36154",
    "sg:province":"Pontevedra",
    "wof:name":"Muebles Guerra S.l.",
    "wof:placetype":"venue"
},
  "geometry": {"coordinates":[-8.6151094437,42.4113616943],"type":"Point"}
}