{
  "type": "Feature",
  "properties": {
    "addr:full":"Calle de Santiago, 25 Parra Badajoz 06176",
    "addr:housenumber":"25",
    "addr:postcode":"06176",
    "addr:street":"Calle De Santiago",
    "iso:country":"ES",
    "sg:address":"Calle de Santiago, 25",
    "sg:city":"Parra",
    "sg:orig_category":"Cajas Para Embalar",
    "sg:phone":"+34 924 68 25 27",
    "sg:postcode":"06176",
    "sg:province":"Badajoz",
    "sg:website":"www.cajarural.com/extremadura",
    "wof:name":"Caja Rural De Extremadura",
    "wof:placetype":"venue"
},
  "geometry": {"coordinates":[-6.6217598915,38.5209579468],"type":"Point"}
}