{
  "type": "Feature",
  "properties": {
    "iso:country":"ES",
    "sg:address":"Avda Mariana Pineda, 6",
    "sg:city":"Guadix",
    "sg:orig_category":"Negocio De Materiales De Construcci\u00d3n",
    "sg:phone":"+34 958 66 44 88",
    "sg:postcode":"18500",
    "sg:province":"Granada",
    "wof:name":"Constructora Alhambra 2002 S.l.",
    "wof:placetype":"venue"
},
  "geometry": {"coordinates":[-3.1364541054,37.3026771545],"type":"Point"}
}