{
  "type": "Feature",
  "properties": {
    "iso:country":"ES",
    "sg:address":"Calle de Calvo Sotelo, 34",
    "sg:city":"Tui",
    "sg:orig_category":"Reposter\u00cdas",
    "sg:phone":"+34 986 60 15 60",
    "sg:postcode":"36700",
    "sg:province":"Pontevedra",
    "wof:name":"Panaderia Las Mercedes S.l.",
    "wof:placetype":"venue"
},
  "geometry": {"coordinates":[-8.6446847916,42.0475578308],"type":"Point"}
}