{
  "type": "Feature",
  "properties": {
    "addr:full":"D Poligono, S/n Soria Soria 42005",
    "addr:postcode":"42005",
    "addr:street":"Poligono S / N",
    "iso:country":"ES",
    "sg:address":"D Poligono, S/n",
    "sg:city":"Soria",
    "sg:orig_category":"Acero: Productos Sider\u00dargicos Y Transformados (fabricaci\u00d3n, Negocio)",
    "sg:phone":"+34 975 22 82 40",
    "sg:postcode":"42005",
    "sg:province":"Soria",
    "wof:name":"Gimenez Bravo Luis Maria",
    "wof:placetype":"venue"
},
  "geometry": {"coordinates":[-2.4691669941,41.7646598816],"type":"Point"}
}