{
  "type": "Feature",
  "properties": {
    "addr:full":"Cra Santa Creu De Calafell, 40 Gava Barcelona 08850",
    "addr:housenumber":"40",
    "addr:postcode":"08850",
    "addr:street":"Gava Barcelona",
    "iso:country":"ES",
    "sg:address":"Cra Santa Creu De Calafell, 40",
    "sg:city":"Gava",
    "sg:orig_category":"Ense\u00d1anza: Profesiones Art\u00cdsticas",
    "sg:phone":"+34 936 38 30 17",
    "sg:postcode":"08850",
    "sg:province":"Barcelona",
    "wof:name":"Fotosileva S.c.p",
    "wof:placetype":"venue"
},
  "geometry": {"coordinates":[2.0087640285,41.304069519],"type":"Point"}
}