{
  "type": "Feature",
  "properties": {
    "addr:full":"Calle de Juan Florez, 129 Coru\u00d1a A Coru\u00f1a 15005",
    "addr:housenumber":"129",
    "addr:postcode":"15005",
    "addr:street":"Calle De Juan Florez;Corun\u0303A",
    "iso:country":"ES",
    "sg:address":"Calle de Juan Florez, 129",
    "sg:city":"Coru\u00d1a",
    "sg:orig_category":"Abogados",
    "sg:phone":"+34 981 23 81 97",
    "sg:postcode":"15005",
    "sg:province":"A Coru\u00f1a",
    "wof:name":"Tarron Couto Carmen",
    "wof:placetype":"venue"
},
  "geometry": {"coordinates":[-8.4108200073,43.3608703613],"type":"Point"}
}