{
  "type": "Feature",
  "properties": {
    "iso:country":"ES",
    "sg:address":"Plaz Heroes De Espa\u00d1a, 2",
    "sg:city":"Melilla",
    "sg:orig_category":"Fabricaci\u00d3n De Juegos Y Juguetes",
    "sg:phone":"+34 952 68 48 26",
    "sg:postcode":"52001",
    "sg:province":"Melilla",
    "wof:name":"Heredia Martin Antonio Tomas",
    "wof:placetype":"venue"
},
  "geometry": {"coordinates":[-2.9388227463,35.2932281494],"type":"Point"}
}