{
  "type": "Feature",
  "properties": {
    "addr:full":"Carrer de Antonio Machado, 8 Constanti Tarragona 43120",
    "addr:housenumber":"8",
    "addr:postcode":"43120",
    "addr:street":"Carrer De Antonio Machado",
    "iso:country":"ES",
    "sg:address":"Carrer de Antonio Machado, 8",
    "sg:city":"Constanti",
    "sg:orig_category":"Empresas De Limpieza",
    "sg:phone":"+34 977 52 25 73",
    "sg:postcode":"43120",
    "sg:province":"Tarragona",
    "wof:name":"Anseda S.l.",
    "wof:placetype":"venue"
},
  "geometry": {"coordinates":[1.2206828594,41.1550788879],"type":"Point"}
}