{
  "type": "Feature",
  "properties": {
    "iso:country":"ES",
    "sg:address":"Pase Perez De Ayala, 3",
    "sg:city":"Valladolid",
    "sg:orig_category":"Guarder\u00cdas",
    "sg:phone":"+34 983 24 42 29",
    "sg:postcode":"47008",
    "sg:province":"Valladolid",
    "wof:name":"Tampico Servicios Educativos S.l.",
    "wof:placetype":"venue"
},
  "geometry": {"coordinates":[-4.7927489281,41.6193618774],"type":"Point"}
}