{
  "type": "Feature",
  "properties": {
    "iso:country":"ES",
    "sg:address":"Plaz Carlos Castel, 16",
    "sg:city":"Teruel",
    "sg:orig_category":"Relojer\u00cda (al Por Menor, Reparaci\u00d3n)",
    "sg:phone":"+34 978 60 10 68",
    "sg:postcode":"44001",
    "sg:province":"Teruel",
    "wof:name":"Oro Y Hora Vicente S.cv.",
    "wof:placetype":"venue"
},
  "geometry": {"coordinates":[-1.107164979,40.3426628113],"type":"Point"}
}