{
  "type": "Feature",
  "properties": {
    "addr:full":"Carr Nou, 16 Girona Girona 17001",
    "addr:housenumber":"16",
    "addr:postcode":"17001",
    "addr:street":"Carr Nou",
    "iso:country":"ES",
    "sg:address":"Carr Nou, 16",
    "sg:city":"Girona",
    "sg:orig_category":"Bisuter\u00cda, Joyer\u00cda, Relojer\u00cda (al Por Menor)",
    "sg:phone":"+34 972 20 48 33",
    "sg:postcode":"17001",
    "sg:province":"Girona",
    "wof:name":"Fernandez Ramirez Juan",
    "wof:placetype":"venue"
},
  "geometry": {"coordinates":[2.8187448978,41.9808616638],"type":"Point"}
}