{
  "type": "Feature",
  "properties": {
    "addr:full":"Calle de Siracusa, 9 Zaragoza Zaragoza 50010",
    "addr:housenumber":"9",
    "addr:postcode":"50010",
    "addr:street":"Calle De Siracusa",
    "iso:country":"ES",
    "sg:address":"Calle de Siracusa, 9",
    "sg:city":"Zaragoza",
    "sg:orig_category":"Cajas De Ahorro",
    "sg:phone":"+34 976 46 04 95",
    "sg:postcode":"50010",
    "sg:province":"Zaragoza",
    "wof:name":"Caja De Ahorros De La Inmaculada",
    "wof:placetype":"venue"
},
  "geometry": {"coordinates":[-0.9098160267,41.6570091248],"type":"Point"}
}