{
  "type": "Feature",
  "properties": {
    "iso:country":"ES",
    "sg:address":"Carr Hernan Cortes, 34",
    "sg:city":"Cala Ratjada",
    "sg:orig_category":"Frutas Y Legumbres Frescas (al Por Mayor)",
    "sg:phone":"+34 971 81 91 13",
    "sg:postcode":"07590",
    "sg:province":"Islas Baleares",
    "wof:name":"Fruites Y Verdures Capdepera S.l.",
    "wof:placetype":"venue"
},
  "geometry": {"coordinates":[3.4615299702,39.7145080566],"type":"Point"}
}