{
  "type": "Feature",
  "properties": {
    "iso:country":"ES",
    "sg:address":"Calle de Federico Baraibar, 28",
    "sg:city":"Vitoria-gasteiz",
    "sg:orig_category":"Inform\u00c1tica (estudios, Servicios, Asesor\u00cda, Formaci\u00d3n)",
    "sg:phone":"+34 945 12 41 92",
    "sg:postcode":"01003",
    "sg:province":"\u00c1lava",
    "wof:name":"Tele Atlas B.v.",
    "wof:placetype":"venue"
},
  "geometry": {"coordinates":[-2.6606280804,42.8420257568],"type":"Point"}
}