{
  "type": "Feature",
  "properties": {
    "iso:country":"ES",
    "sg:address":"Carrer de Prat D'en Roquer, 33",
    "sg:city":"Barcelona",
    "sg:orig_category":"Inform\u00c1tica: Soportes De Informaci\u00d3n, Suministros & Accesorios",
    "sg:phone":"+34 933 51 81 09",
    "sg:postcode":"08027",
    "sg:province":"Barcelona",
    "sg:website":"www.expertia-tecoffice.com",
    "wof:name":"Porta Almasque Sebastian",
    "wof:placetype":"venue"
},
  "geometry": {"coordinates":[2.1782193184,41.4255523682],"type":"Point"}
}