{
  "type": "Feature",
  "properties": {
    "iso:country":"ES",
    "sg:address":"Calle de Carrera, 1",
    "sg:city":"Archidona",
    "sg:orig_category":"M\u00c9dicos: Estomatolog\u00cda",
    "sg:phone":"+34 952 71 44 15",
    "sg:postcode":"29300",
    "sg:province":"M\u00e1laga",
    "wof:name":"Artacho Perez Miguel Angel",
    "wof:placetype":"venue"
},
  "geometry": {"coordinates":[-4.387401104,37.0949897766],"type":"Point"}
}