{
  "type": "Feature",
  "properties": {
    "iso:country":"ES",
    "sg:address":"Calle de Palleter, 42",
    "sg:city":"Valencia",
    "sg:orig_category":"Asociaciones Y Clubs Deportivos",
    "sg:phone":"+34 963 84 70 97",
    "sg:postcode":"46008",
    "sg:province":"Valencia",
    "sg:website":"www.sportworld.es",
    "wof:name":"Diaz Y Manero S.l.",
    "wof:placetype":"venue"
},
  "geometry": {"coordinates":[-0.3877550066,39.4714050293],"type":"Point"}
}