{
  "type": "Feature",
  "properties": {
    "iso:country":"ES",
    "sg:address":"Cami Porrassa, 6",
    "sg:city":"Magaluf",
    "sg:orig_category":"Centros De Educaci\u00d3n Especial",
    "sg:phone":"+34 971 13 13 50",
    "sg:postcode":"07181",
    "sg:province":"Islas Baleares",
    "wof:name":"Ajuntament De Calvia",
    "wof:placetype":"venue"
},
  "geometry": {"coordinates":[2.5294363499,39.5049362183],"type":"Point"}
}