{
  "type": "Feature",
  "properties": {
    "addr:full":"Pg Santa Coloma, 33 Barcelona Barcelona 08030",
    "addr:housenumber":"33",
    "addr:postcode":"08030",
    "addr:street":"Pg Santa Coloma",
    "iso:country":"ES",
    "sg:address":"Pg Santa Coloma, 33",
    "sg:city":"Barcelona",
    "sg:orig_category":"Molduras, Junquillos, Listones Y Molduras Perforadas",
    "sg:phone":"+34 933 45 54 87",
    "sg:postcode":"08030",
    "sg:province":"Barcelona",
    "wof:name":"Morales Padilla Juan Angel",
    "wof:placetype":"venue"
},
  "geometry": {"coordinates":[2.1901769638,41.4452972412],"type":"Point"}
}