{
  "type": "Feature",
  "properties": {
    "addr:full":"Calle de Escosura, 12 Madrid Madrid 28015",
    "addr:housenumber":"12",
    "addr:postcode":"madrid;28015",
    "addr:street":"Calle De Escosura",
    "iso:country":"ES",
    "sg:address":"Calle de Escosura, 12",
    "sg:city":"Madrid",
    "sg:orig_category":"Panader\u00cdas, Panader\u00cdas",
    "sg:phone":"+34 914 45 63 82",
    "sg:postcode":"28015",
    "sg:province":"Madrid",
    "wof:name":"Pan-vi S.l.",
    "wof:placetype":"venue"
},
  "geometry": {"coordinates":[-3.7068266869,40.4351119995],"type":"Point"}
}