{
  "type": "Feature",
  "properties": {
    "addr:full":"Avda Garat Txomin, 9 Bilbao Vizcaya 48004",
    "addr:housenumber":"9",
    "addr:postcode":"48004",
    "addr:street":"Avda Garat Txomin",
    "iso:country":"ES",
    "sg:address":"Avda Garat Txomin, 9",
    "sg:city":"Bilbao",
    "sg:orig_category":"Cajas De Ahorro",
    "sg:phone":"+34 944 73 17 77",
    "sg:postcode":"48004",
    "sg:province":"Vizcaya",
    "wof:name":"Caja Laboral Popular",
    "wof:placetype":"venue"
},
  "geometry": {"coordinates":[-2.9070000648,43.2573394775],"type":"Point"}
}