{
  "type": "Feature",
  "properties": {
    "addr:full":"Calle de Churruca, 21 Madrid Madrid 28004",
    "addr:housenumber":"21",
    "addr:postcode":"madrid;28004",
    "addr:street":"Calle De Churruca",
    "iso:country":"ES",
    "sg:address":"Calle de Churruca, 21",
    "sg:city":"Madrid",
    "sg:orig_category":"Cervecer\u00cdas",
    "sg:phone":"+34 915 32 14 35",
    "sg:postcode":"28004",
    "sg:province":"Madrid",
    "wof:name":"Kilsan S. L.",
    "wof:placetype":"venue"
},
  "geometry": {"coordinates":[-3.701215744,40.4281845093],"type":"Point"}
}