{
  "type": "Feature",
  "properties": {
    "iso:country":"ES",
    "sg:address":"Rua Generalisimo, 46",
    "sg:city":"Ordes",
    "sg:orig_category":"Electrodom\u00c9sticos (al Por Menor)",
    "sg:phone":"+34 981 68 04 54",
    "sg:postcode":"15680",
    "sg:province":"A Coru\u00f1a",
    "wof:name":"Veiras Gomez Joaquin",
    "wof:placetype":"venue"
},
  "geometry": {"coordinates":[-8.4072790146,43.0771408081],"type":"Point"}
}