{
  "type": "Feature",
  "properties": {
    "addr:full":"Avda Paralela, 12 Majadahonda Madrid 28220",
    "addr:housenumber":"12",
    "addr:postcode":"28220",
    "addr:street":"Avda Paralela",
    "iso:country":"ES",
    "sg:address":"Avda Paralela, 12",
    "sg:city":"Majadahonda",
    "sg:orig_category":"Ense\u00d1anza Variada",
    "sg:phone":"+34 916 39 08 95",
    "sg:postcode":"28220",
    "sg:province":"Madrid",
    "wof:name":"Atril Consultoria Y Formacion S.l.",
    "wof:placetype":"venue"
},
  "geometry": {"coordinates":[-3.8656945229,40.4747047424],"type":"Point"}
}