{
  "type": "Feature",
  "properties": {
    "iso:country":"ES",
    "sg:address":"Calle de Real, 85",
    "sg:city":"S. Fernando",
    "sg:orig_category":"Complementos De Vestir (al Por Menor)",
    "sg:phone":"+34 956 59 29 15",
    "sg:postcode":"11100",
    "sg:province":"C\u00e1diz",
    "wof:name":"Camacho Tinoco Maria Eugenia",
    "wof:placetype":"venue"
},
  "geometry": {"coordinates":[-6.1951141357,36.4662361145],"type":"Point"}
}