{
  "type": "Feature",
  "properties": {
    "addr:full":"Calle de Garbe, 4 Garbe Vizcaya 48140",
    "addr:housenumber":"4",
    "addr:postcode":"48140",
    "addr:street":"Calle De Garbe",
    "iso:country":"ES",
    "sg:address":"Calle de Garbe, 4",
    "sg:city":"Garbe",
    "sg:orig_category":"Alimentaci\u00d3n General (al Por Menor)",
    "sg:phone":"+34 946 73 71 66",
    "sg:postcode":"48140",
    "sg:province":"Vizcaya",
    "wof:name":"Saltzeder S.l.",
    "wof:placetype":"venue"
},
  "geometry": {"coordinates":[-2.777105093,43.1645507812],"type":"Point"}
}