{
  "type": "Feature",
  "properties": {
    "iso:country":"ES",
    "sg:address":"Carrer de Sant Antoni, 21",
    "sg:city":"Sabadell",
    "sg:orig_category":"Confecci\u00d3n De Trajes Para Se\u00d1oras",
    "sg:phone":"+34 937 27 08 23",
    "sg:postcode":"08201",
    "sg:province":"Barcelona",
    "wof:name":"Sabater Salvador Montserrat",
    "wof:placetype":"venue"
},
  "geometry": {"coordinates":[2.1076929569,41.547996521],"type":"Point"}
}