{
  "type": "Feature",
  "properties": {
    "addr:full":"Calle de Goya, 61 Madrid Madrid 28001",
    "addr:housenumber":"61",
    "addr:postcode":"madrid;28001",
    "addr:street":"Calle De Goya",
    "iso:country":"ES",
    "sg:address":"Calle de Goya, 61",
    "sg:city":"Madrid",
    "sg:orig_category":"Ropa Para Caballeros (al Por Menor)",
    "sg:phone":"+34 915 75 94 59",
    "sg:postcode":"28001",
    "sg:province":"Madrid",
    "sg:website":"www.spf.com",
    "wof:name":"Cortefiel S.a.",
    "wof:placetype":"venue"
},
  "geometry": {"coordinates":[-3.6806221008,40.4251670837],"type":"Point"}
}