{
  "type": "Feature",
  "properties": {
    "addr:full":"Rua Ramon Puga, 24 Ourense Ourense 32005",
    "addr:housenumber":"24",
    "addr:postcode":"32005",
    "addr:street":"Rua Ramon Puga",
    "iso:country":"ES",
    "sg:address":"Rua Ramon Puga, 24",
    "sg:city":"Ourense",
    "sg:orig_category":"Servicio De Salud",
    "sg:phone":"+34 988 36 61 51",
    "sg:postcode":"32005",
    "sg:province":"Ourense",
    "wof:name":"As Burgas Cooperativa De Ambulancias Orensanas",
    "wof:placetype":"venue"
},
  "geometry": {"coordinates":[-7.8585562706,42.3233680725],"type":"Point"}
}