{
  "type": "Feature",
  "properties": {
    "addr:full":"Plaz San Antonio, 7 Santo\u00f1a Cantabria 39740",
    "addr:housenumber":"7",
    "addr:postcode":"39740",
    "addr:street":"Plaz San Antonio",
    "iso:country":"ES",
    "sg:address":"Plaz San Antonio, 7",
    "sg:city":"Santo\u00f1a",
    "sg:orig_category":"Mercer\u00cda, Lencer\u00cda (al Por Menor)",
    "sg:phone":"+34 942 66 00 94",
    "sg:postcode":"39740",
    "sg:province":"Cantabria",
    "wof:name":"Cantero Mediavilla Emilia",
    "wof:placetype":"venue"
},
  "geometry": {"coordinates":[-3.4568510056,43.4429779053],"type":"Point"}
}