{
  "type": "Feature",
  "properties": {
    "iso:country":"ES",
    "sg:address":"Plaz Santa Eulalia, 2",
    "sg:city":"Zamora",
    "sg:orig_category":"Restaurantes",
    "sg:phone":"+34 980 53 15 53",
    "sg:postcode":"49002",
    "sg:province":"Zamora",
    "wof:name":"Rodriguez Vara Concepcion",
    "wof:placetype":"venue"
},
  "geometry": {"coordinates":[-5.744904995,41.5031547546],"type":"Point"}
}