{
  "type": "Feature",
  "properties": {
    "addr:full":"Calle de Medieras, 5 Cartagena Murcia 30201",
    "addr:housenumber":"5",
    "addr:postcode":"30201",
    "addr:street":"Calle De Medieras",
    "iso:country":"ES",
    "sg:address":"Calle de Medieras, 5",
    "sg:city":"Cartagena",
    "sg:orig_category":"Art\u00cdculos De Regalo (al Por Menor)",
    "sg:phone":"+34 968 50 68 31",
    "sg:postcode":"30201",
    "sg:province":"Murcia",
    "wof:name":"Garcia Espinosa Maria Del Carmen",
    "wof:placetype":"venue"
},
  "geometry": {"coordinates":[-0.9855279922,37.6005973816],"type":"Point"}
}