{
  "type": "Feature",
  "properties": {
    "addr:full":"Calle de Juan Ramon Jimenez, S/n Burgos Burgos 09007",
    "addr:postcode":"09007",
    "addr:street":"Calle De Juan Ramon Jimenez S / N",
    "iso:country":"ES",
    "sg:address":"Calle de Juan Ramon Jimenez, S/n",
    "sg:city":"Burgos",
    "sg:orig_category":"Suministros Para Carrocer\u00cdas",
    "sg:phone":"+34 947 48 55 67",
    "sg:postcode":"09007",
    "sg:province":"Burgos",
    "wof:name":"Alfonso Garcia Rabadan Y Jose Gil Cuesta S. Cv.",
    "wof:placetype":"venue"
},
  "geometry": {"coordinates":[-3.6618552208,42.352848053],"type":"Point"}
}