{
  "type": "Feature",
  "properties": {
    "iso:country":"ES",
    "sg:address":"Ctra Montcada, 601",
    "sg:city":"Terrassa",
    "sg:orig_category":"Delegados, Agentes De Tr\u00c1nsito, Auxiliares De Transporte Internacional",
    "sg:phone":"+34 937 36 25 25",
    "sg:postcode":"08227",
    "sg:province":"Barcelona",
    "sg:website":"www.transarexpress.com",
    "wof:name":"Transar Express S.l.",
    "wof:placetype":"venue"
},
  "geometry": {"coordinates":[2.0379550457,41.5574684143],"type":"Point"}
}