{
  "type": "Feature",
  "properties": {
    "iso:country":"ES",
    "sg:address":"Ctra Oca\u00d1a, Km. 0407,0",
    "sg:city":"Alacant",
    "sg:orig_category":"Venta, Montaje De Neum\u00c1ticos",
    "sg:phone":"+34 965 28 66 32",
    "sg:postcode":"03006",
    "sg:province":"Alicante",
    "wof:name":"Neumaticos Soledad S.l.",
    "wof:placetype":"venue"
},
  "geometry": {"coordinates":[-0.5353680253,38.3439369202],"type":"Point"}
}