{
  "type": "Feature",
  "properties": {
    "iso:country":"ES",
    "sg:address":"Carretera De Carcabuey, 2",
    "sg:city":"Rute",
    "sg:orig_category":"Empresas De Carpinter\u00cda De Madera",
    "sg:phone":"+34 957 53 89 01",
    "sg:postcode":"14960",
    "sg:province":"C\u00f3rdoba",
    "wof:name":"Gamez Garcia Antonio",
    "wof:placetype":"venue"
},
  "geometry": {"coordinates":[-4.36434412,37.3276290894],"type":"Point"}
}