{
  "type": "Feature",
  "properties": {
    "addr:full":"Ctra. Cuerva, S/n Menasalbas Toledo 45128",
    "addr:housenumber":"s / n",
    "addr:postcode":"45128",
    "addr:street":"Ctra. Cuerva",
    "iso:country":"ES",
    "sg:address":"Ctra. Cuerva, S/n",
    "sg:city":"Menasalbas",
    "sg:orig_category":"Poller\u00cda Y Caza (al Por Menor)",
    "sg:phone":"+34 925 41 30 10",
    "sg:postcode":"45128",
    "sg:province":"Toledo",
    "wof:name":"Avimena S.l.",
    "wof:placetype":"venue"
},
  "geometry": {"coordinates":[-4.2762122154,39.6458778381],"type":"Point"}
}