{
  "type": "Feature",
  "properties": {
    "iso:country":"ES",
    "sg:address":"Calle de Independencia, 12",
    "sg:city":"Elda",
    "sg:orig_category":"Imprenta",
    "sg:phone":"+34 965 39 89 50",
    "sg:postcode":"03600",
    "sg:province":"Alicante",
    "wof:name":"Graficas Azorin S.l.",
    "wof:placetype":"venue"
},
  "geometry": {"coordinates":[-0.7980870008,38.4805526733],"type":"Point"}
}