{
  "type": "Feature",
  "properties": {
    "addr:full":"Calle de Jose Ramon Diez De Revenga, 19 Pozo Ca\u00e7ada Albacete 02510",
    "addr:housenumber":"19",
    "addr:postcode":"02510",
    "addr:street":"Calle De Jose Ramon;Revenga",
    "iso:country":"ES",
    "sg:address":"Calle de Jose Ramon Diez De Revenga, 19",
    "sg:city":"Pozo Ca\u00e7ada",
    "sg:orig_category":"Droguer\u00cdas (al Por Menor)",
    "sg:phone":"+34 967 25 00 27",
    "sg:postcode":"02510",
    "sg:province":"Albacete",
    "wof:name":"Gonzalez Iniesta Jose Manuel",
    "wof:placetype":"venue"
},
  "geometry": {"coordinates":[-1.7344989777,38.8002891541],"type":"Point"}
}