{
  "type": "Feature",
  "properties": {
    "iso:country":"ES",
    "sg:address":"Calle de Almendro, 20",
    "sg:city":"Puerto",
    "sg:orig_category":"Supermercados Y Hipermercados",
    "sg:phone":"+34 962 67 75 11",
    "sg:postcode":"46520",
    "sg:province":"Valencia",
    "sg:website":"www.mercadona.es",
    "wof:name":"Mercadona S.a.",
    "wof:placetype":"venue"
},
  "geometry": {"coordinates":[-0.2327640057,39.6673049927],"type":"Point"}
}