{
  "type": "Feature",
  "properties": {
    "addr:full":"Avda Sabino Arana, 86 Elexalde Vizcaya 48940",
    "addr:housenumber":"86",
    "addr:postcode":"48940",
    "addr:street":"Avda Sabino Arana",
    "iso:country":"ES",
    "sg:address":"Avda Sabino Arana, 86",
    "sg:city":"Elexalde",
    "sg:orig_category":"Agentes Generales De Seguros",
    "sg:phone":"+34 944 63 98 33",
    "sg:postcode":"48940",
    "sg:province":"Vizcaya",
    "wof:name":"Amets 2005 Sl",
    "wof:placetype":"venue"
},
  "geometry": {"coordinates":[-2.7753472328,43.1623306274],"type":"Point"}
}