{
  "type": "Feature",
  "properties": {
    "iso:country":"ES",
    "sg:address":"Avda Doctor Artero Guirao, 50",
    "sg:city":"S. Pedro Pinatar",
    "sg:orig_category":"Muebles, Minoristas",
    "sg:phone":"+34 968 18 36 88",
    "sg:postcode":"30740",
    "sg:province":"Murcia",
    "wof:name":"Arte Forja Llor S.l.",
    "wof:placetype":"venue"
},
  "geometry": {"coordinates":[-0.7965312004,37.8320655823],"type":"Point"}
}