{
  "type": "Feature",
  "properties": {
    "addr:full":"Fca. Aldead\u00e1vila Revilla, S/n Buenamadre Salamanca 37209",
    "addr:housenumber":"s / n",
    "addr:postcode":"37209",
    "iso:country":"ES",
    "sg:address":"Fca. Aldead\u00e1vila Revilla, S/n",
    "sg:city":"Buenamadre",
    "sg:orig_category":"Cr\u00cda De Animales",
    "sg:phone":"+34 923 16 44 76",
    "sg:postcode":"37209",
    "sg:province":"Salamanca",
    "wof:name":"Ortu\u00f1o Duplaix Emilio",
    "wof:placetype":"venue"
},
  "geometry": {"coordinates":[-6.1963481903,40.861869812],"type":"Point"}
}