{
  "type": "Feature",
  "properties": {
    "addr:full":"Calle de Gomez Arnes, 13 Vilamarxant Valencia 46191",
    "addr:housenumber":"13",
    "addr:postcode":"46191",
    "addr:street":"Calle De Gomez Arnes",
    "iso:country":"ES",
    "sg:address":"Calle de Gomez Arnes, 13",
    "sg:city":"Vilamarxant",
    "sg:orig_category":"Estancos",
    "sg:phone":"+34 961 65 00 41",
    "sg:postcode":"46191",
    "sg:province":"Valencia",
    "wof:name":"Sanchis Montesinos Jose Manuel",
    "wof:placetype":"venue"
},
  "geometry": {"coordinates":[-0.6243929863,39.5688896179],"type":"Point"}
}