{
  "type": "Feature",
  "properties": {
    "iso:country":"ES",
    "sg:address":"P. Ori, 4",
    "sg:city":"Iru\u00f1a",
    "sg:orig_category":"Frutas, Legumbres Frescas Y Tempranas (al Por Menor)",
    "sg:phone":"+34 948 15 17 43",
    "sg:postcode":"31006",
    "sg:province":"Navarra",
    "wof:name":"Pe Gay Jose Ignacio",
    "wof:placetype":"venue"
},
  "geometry": {"coordinates":[-1.6344820261,42.8047637939],"type":"Point"}
}