{
  "type": "Feature",
  "properties": {
    "iso:country":"ES",
    "sg:address":"Pzo Orzan, 8",
    "sg:city":"Coru\u00d1a",
    "sg:orig_category":"Electrodom\u00c9sticos (fabricaci\u00d3n, Al Por Mayor)",
    "sg:phone":"+34 981 22 98 43",
    "sg:postcode":"15003",
    "sg:province":"La Coru\u00f1a",
    "wof:name":"Indesit Electrodomesticos S.a",
    "wof:placetype":"venue"
},
  "geometry": {"coordinates":[-8.4030942917,43.3719673157],"type":"Point"}
}