{
  "type": "Feature",
  "properties": {
    "addr:full":"Carrer de Poeta Cabanyes, 33 Barcelona Barcelona 08004",
    "addr:housenumber":"33",
    "addr:postcode":"08004",
    "addr:street":"Carrer De Poeta Cabanyes",
    "iso:country":"ES",
    "sg:address":"Carrer de Poeta Cabanyes, 33",
    "sg:city":"Barcelona",
    "sg:orig_category":"Mec\u00c1nico Del Autom\u00d3vil",
    "sg:phone":"+34 934 41 72 49",
    "sg:postcode":"08004",
    "sg:province":"Barcelona",
    "wof:name":"Ramirez Juarez Juan",
    "wof:placetype":"venue"
},
  "geometry": {"coordinates":[2.1655299664,41.373752594],"type":"Point"}
}