{
  "type": "Feature",
  "properties": {
    "addr:full":"Calle de Zapateros, 5 Marmolejo Ja\u00e9n 23770",
    "addr:housenumber":"5",
    "addr:postcode":"23770",
    "addr:street":"Calle De Zapateros;Jae\u0301N",
    "iso:country":"ES",
    "sg:address":"Calle de Zapateros, 5",
    "sg:city":"Marmolejo",
    "sg:orig_category":"Promotores Constructores",
    "sg:phone":"+34 953 54 01 30",
    "sg:postcode":"23770",
    "sg:province":"Ja\u00e9n",
    "wof:name":"Ollero Garcia Juana",
    "wof:placetype":"venue"
},
  "geometry": {"coordinates":[-4.1730232239,38.0458602905],"type":"Point"}
}