{
  "type": "Feature",
  "properties": {
    "addr:full":"Avda Libertad De La, 14 Donostia-san Sebastian Guip\u00f9zcoa 20004",
    "addr:housenumber":"14",
    "addr:postcode":"20004",
    "addr:street":"Avda Libertad De La",
    "iso:country":"ES",
    "sg:address":"Avda Libertad De La, 14",
    "sg:city":"Donostia-san Sebastian",
    "sg:orig_category":"Farmacias",
    "sg:phone":"+34 943 42 61 39",
    "sg:postcode":"20004",
    "sg:province":"Guip\u00f9zcoa",
    "wof:name":"Cabiro Alvarez Juan Manuel",
    "wof:placetype":"venue"
},
  "geometry": {"coordinates":[-1.9808189869,43.3201599121],"type":"Point"}
}