{
  "type": "Feature",
  "properties": {
    "addr:full":"Calle de Rodriguez De Valcarcel, 7 Santa Eulalia Islas Baleares 07840",
    "addr:housenumber":"7",
    "addr:postcode":"07840",
    "addr:street":"Calle De Rodriguez De Valcarcel",
    "iso:country":"ES",
    "sg:address":"Calle de Rodriguez De Valcarcel, 7",
    "sg:city":"Santa Eulalia",
    "sg:orig_category":"Ropa Para Se\u00d1oras Y Caballeros (al Por Menor)",
    "sg:phone":"+34 971 33 08 84",
    "sg:postcode":"07840",
    "sg:province":"Islas Baleares",
    "sg:website":"www.lacoste.es",
    "wof:name":"Invertodo S.l",
    "wof:placetype":"venue"
},
  "geometry": {"coordinates":[1.534989953,38.984462738],"type":"Point"}
}