{
  "type": "Feature",
  "properties": {
    "iso:country":"ES",
    "sg:address":"Calle de O\u00d1a, 95",
    "sg:city":"Madrid",
    "sg:orig_category":"Peluquer\u00cdas, Peluquer\u00cda Mixta",
    "sg:phone":"+34 913 02 93 81",
    "sg:postcode":"28050",
    "sg:province":"Madrid",
    "wof:name":"Kana's Peluqueros S.l.",
    "wof:placetype":"venue"
},
  "geometry": {"coordinates":[-3.663877964,40.4893455505],"type":"Point"}
}