{
  "type": "Feature",
  "properties": {
    "addr:full":"Avda Andres Segovia, 18 Baeza Ja\u00e9n 23440",
    "addr:housenumber":"18",
    "addr:postcode":"23440",
    "addr:street":"Avda Andres Segovia",
    "iso:country":"ES",
    "sg:address":"Avda Andres Segovia, 18",
    "sg:city":"Baeza",
    "sg:orig_category":"Molduras, Junquillos, Listones Y Molduras Perforadas",
    "sg:phone":"+34 953 74 12 25",
    "sg:postcode":"23440",
    "sg:province":"Ja\u00e9n",
    "wof:name":"Martos Cruz Antonio",
    "wof:placetype":"venue"
},
  "geometry": {"coordinates":[-3.4622869492,37.9940681458],"type":"Point"}
}