{
  "type": "Feature",
  "properties": {
    "iso:country":"ES",
    "sg:address":"Avda Constitucion De La, 15",
    "sg:city":"Aviles",
    "sg:orig_category":"Inmobiliaria (agencias)",
    "sg:phone":"+34 985 56 15 95",
    "sg:postcode":"33401",
    "sg:province":"Asturias",
    "wof:name":"Algol Gestion S.l.",
    "wof:placetype":"venue"
},
  "geometry": {"coordinates":[-5.9293856621,43.5606918335],"type":"Point"}
}