{
  "type": "Feature",
  "properties": {
    "iso:country":"ES",
    "sg:address":"Carr Rossello, 3",
    "sg:city":"Palamos",
    "sg:orig_category":"Servicios De Higiene Y Peluquer\u00cda Para Perros Y Gatos",
    "sg:phone":"+34 972 60 15 76",
    "sg:postcode":"17230",
    "sg:province":"Girona",
    "wof:name":"Patane  Sebastien Agatino",
    "wof:placetype":"venue"
},
  "geometry": {"coordinates":[3.1279499531,41.8473548889],"type":"Point"}
}