{
  "type": "Feature",
  "properties": {
    "iso:country":"ES",
    "sg:address":"Avda Gran Via, 9",
    "sg:city":"Caravaca Cruz",
    "sg:orig_category":"Electrodom\u00c9sticos (al Por Menor)",
    "sg:phone":"+34 968 70 77 08",
    "sg:postcode":"30400",
    "sg:province":"Murcia",
    "wof:name":"Electrodomesticos Morenilla S.l.",
    "wof:placetype":"venue"
},
  "geometry": {"coordinates":[-1.8620979786,38.1018943787],"type":"Point"}
}