{
  "type": "Feature",
  "properties": {
    "iso:country":"ES",
    "sg:address":"Pl. Iglesia, S/n",
    "sg:city":"Sta Gertrudis Fruitera",
    "sg:orig_category":"Caf\u00c9s, Bares, Cervecer\u00cdas",
    "sg:phone":"+34 971 19 71 76",
    "sg:postcode":"07814",
    "sg:province":"Islas Baleares",
    "wof:name":"Ulivans S.l.",
    "wof:placetype":"venue"
},
  "geometry": {"coordinates":[1.4285869598,38.9992485046],"type":"Point"}
}