{
  "type": "Feature",
  "properties": {
    "iso:country":"ES",
    "sg:address":"Carrer de Jacint Verdaguer, 4",
    "sg:city":"Martorell",
    "sg:orig_category":"Ropa Para Se\u00d1oras (al Por Menor)",
    "sg:phone":"+34 937 74 83 23",
    "sg:postcode":"08760",
    "sg:province":"Barcelona",
    "wof:name":"Eurotres S.l.",
    "wof:placetype":"venue"
},
  "geometry": {"coordinates":[1.9142889977,41.4777946472],"type":"Point"}
}