{
  "type": "Feature",
  "properties": {
    "iso:country":"ES",
    "sg:address":"Avda Jaen (de), 8",
    "sg:city":"Chipiona",
    "sg:orig_category":"Mec\u00c1nico Del Autom\u00d3vil",
    "sg:phone":"+34 956 37 20 29",
    "sg:postcode":"11550",
    "sg:province":"C\u00e1diz",
    "wof:name":"Porta Massip Fernando",
    "wof:placetype":"venue"
},
  "geometry": {"coordinates":[-6.4312648773,36.737651825],"type":"Point"}
}