{
  "type": "Feature",
  "properties": {
    "iso:country":"ES",
    "sg:address":"Carrer de Tallers, 9",
    "sg:city":"Barcelona",
    "sg:classifiers":[
        {
            "category":"Government",
            "subcategory":"Post Office",
            "type":"Public Place"
        }
    ],
    "sg:phone":"+34 933 01 62 51",
    "sg:postcode":"08001",
    "sg:province":"Barcelona",
    "sg:tags":[
        "de",
        "yoga",
        "clases"
    ],
    "wof:name":"Seijas Sanz Juan",
    "wof:placetype":"venue"
},
  "geometry": {"coordinates":[2.1697399616,41.3845863342],"type":"Point"}
}