{
  "type": "Feature",
  "properties": {
    "addr:full":"Calle de Antillano Campos, 11 Sevilla Sevilla 41010",
    "addr:housenumber":"11",
    "addr:postcode":"41010",
    "addr:street":"Calle De Antillano Campos",
    "iso:country":"ES",
    "sg:address":"Calle de Antillano Campos, 11",
    "sg:city":"Sevilla",
    "sg:orig_category":"Porcelanas, Azulejos (fabricaci\u00d3n, Al Por Mayor)",
    "sg:phone":"+34 954 33 13 90",
    "sg:postcode":"41010",
    "sg:province":"Sevilla",
    "wof:name":"Ruiz Gil S.l.",
    "wof:placetype":"venue"
},
  "geometry": {"coordinates":[-6.004881382,37.3851585388],"type":"Point"}
}