{
  "type": "Feature",
  "properties": {
    "addr:full":"Vintena, 19 Algemesi Valencia 46680",
    "addr:housenumber":"19",
    "addr:postcode":"46680",
    "addr:street":"Vintena",
    "iso:country":"ES",
    "sg:address":"Vintena, 19",
    "sg:city":"Algemesi",
    "sg:orig_category":"Construcci\u00d3n Mec\u00c1nica",
    "sg:phone":"+34 962 42 60 22",
    "sg:postcode":"46680",
    "sg:province":"Valencia",
    "wof:name":"Chen Mecanitzats",
    "wof:placetype":"venue"
},
  "geometry": {"coordinates":[-0.4423590004,39.1969833374],"type":"Point"}
}