{
  "type": "Feature",
  "properties": {
    "iso:country":"ES",
    "sg:address":"Avenida De La Fuente, 55",
    "sg:city":"Zafra",
    "sg:orig_category":"Remolques, Carretillas De Mano Para Operaciones Portuarias",
    "sg:phone":"+34 924 55 19 01",
    "sg:postcode":"06300",
    "sg:province":"Badajoz",
    "wof:name":"Sastre Plaza Roman",
    "wof:placetype":"venue"
},
  "geometry": {"coordinates":[-6.4217867851,38.4284896851],"type":"Point"}
}