{
  "type": "Feature",
  "properties": {
    "addr:full":"Las Canteras, S/n Priego Cordoba C\u00f3rdoba 14800",
    "addr:housenumber":"s",
    "addr:postcode":"14800",
    "addr:street":"Las Canteras;/ N Priego Cordoba Co\u0301Rdoba",
    "iso:country":"ES",
    "sg:address":"Las Canteras, S/n",
    "sg:city":"Priego Cordoba",
    "sg:orig_category":"Negocio De Materiales De Construcci\u00d3n",
    "sg:phone":"+34 957 54 04 68",
    "sg:postcode":"14800",
    "sg:province":"C\u00f3rdoba",
    "wof:name":"Canteras Manre S.l.",
    "wof:placetype":"venue"
},
  "geometry": {"coordinates":[-4.2099971771,37.4405784607],"type":"Point"}
}