{
  "type": "Feature",
  "properties": {
    "addr:full":"Carrer de Muralla (de La), 1 Torredembarra Tarragona 43830",
    "addr:housenumber":"1",
    "addr:postcode":"43830",
    "addr:street":"Carrer De Muralla De La",
    "iso:country":"ES",
    "sg:address":"Carrer de Muralla (de La), 1",
    "sg:city":"Torredembarra",
    "sg:orig_category":"Inmobiliaria (agencias)",
    "sg:phone":"+34 977 13 00 56",
    "sg:postcode":"43830",
    "sg:province":"Tarragona",
    "wof:name":"Belen Conesa Cano S.l.n.e.",
    "wof:placetype":"venue"
},
  "geometry": {"coordinates":[1.396821022,41.1444473267],"type":"Point"}
}