{
  "type": "Feature",
  "properties": {
    "addr:full":"Calle de Doctor Esquerdo, 48 Madrid Madrid 28007",
    "addr:housenumber":"48",
    "addr:postcode":"madrid;28007",
    "addr:street":"Calle De Doctor Esquerdo",
    "iso:country":"ES",
    "sg:address":"Calle de Doctor Esquerdo, 48",
    "sg:city":"Madrid",
    "sg:orig_category":"Ropa Para Se\u00d1oras (al Por Menor)",
    "sg:phone":"+34 915 04 29 94",
    "sg:postcode":"28007",
    "sg:province":"Madrid",
    "wof:name":"Lumar 86 S.l.",
    "wof:placetype":"venue"
},
  "geometry": {"coordinates":[-3.6694140434,40.4179840088],"type":"Point"}
}