{
  "type": "Feature",
  "properties": {
    "addr:full":"Calle de Paz De La, 6 Aviles Asturias 33402",
    "addr:housenumber":"6",
    "addr:postcode":"33402",
    "addr:street":"Calle De Paz De La",
    "iso:country":"ES",
    "sg:address":"Calle de Paz De La, 6",
    "sg:city":"Aviles",
    "sg:orig_category":"Carnicer\u00cdas, Carnicer\u00cdas",
    "sg:phone":"+34 985 54 55 48",
    "sg:postcode":"33402",
    "sg:province":"Asturias",
    "wof:name":"Fernandez Gonzalez Angeles",
    "wof:placetype":"venue"
},
  "geometry": {"coordinates":[-5.9263877869,43.534324646],"type":"Point"}
}