{
  "type": "Feature",
  "properties": {
    "iso:country":"ES",
    "sg:address":"Rua Pardi\u00d1eiros, 6",
    "sg:city":"Milladoiro",
    "sg:orig_category":"Guarder\u00cdas",
    "sg:phone":"+34 981 53 19 20",
    "sg:postcode":"15895",
    "sg:province":"La Coru\u00f1a",
    "wof:name":"Garcia Reboredo Maria Jose",
    "wof:placetype":"venue"
},
  "geometry": {"coordinates":[-8.5780572891,42.8468360901],"type":"Point"}
}