{
  "type": "Feature",
  "properties": {
    "addr:full":"Calle de Jose Cruz Conde, 18 Cordoba C\u00f3rdoba 14003",
    "addr:housenumber":"18",
    "addr:postcode":"14003",
    "addr:street":"Calle De Jose Cruz Conde;Co\u0301Rdoba",
    "iso:country":"ES",
    "sg:address":"Calle de Jose Cruz Conde, 18",
    "sg:city":"Cordoba",
    "sg:orig_category":"Confecci\u00d3n De Trajes De Ba\u00d1o Y De Ropa De Playa",
    "sg:phone":"+34 957 47 86 12",
    "sg:postcode":"14003",
    "sg:province":"C\u00f3rdoba",
    "sg:website":"www.calzedonia.com",
    "wof:name":"Franchising Calzedonia Espa\u00f1a S.a.",
    "wof:placetype":"venue"
},
  "geometry": {"coordinates":[-4.7804927826,37.8868408203],"type":"Point"}
}