{
  "type": "Feature",
  "properties": {
    "addr:full":"Pol. 4, S/n Escorca Islas Baleares 07315",
    "addr:housenumber":"s / n",
    "addr:postcode":"07315",
    "addr:street":"Pol. 4",
    "iso:country":"ES",
    "sg:address":"Pol. 4, S/n",
    "sg:city":"Escorca",
    "sg:orig_category":"Promotores Constructores",
    "sg:phone":"+34 971 51 70 90",
    "sg:postcode":"07315",
    "sg:province":"Islas Baleares",
    "wof:name":"C'an Lleig S.a.",
    "wof:placetype":"venue"
},
  "geometry": {"coordinates":[2.7793400288,39.8415184021],"type":"Point"}
}