{
  "type": "Feature",
  "properties": {
    "iso:country":"ES",
    "sg:address":"Lugar Los Alamos, S/n",
    "sg:city":"Torremolinos",
    "sg:orig_category":"Molduras, Junquillos, Listones Y Molduras Perforadas",
    "sg:phone":"+34 952 38 82 64",
    "sg:postcode":"29620",
    "sg:province":"M\u00e1laga",
    "wof:name":"Rebalae Beach S.l.",
    "wof:placetype":"venue"
},
  "geometry": {"coordinates":[-4.4998540878,36.6244087219],"type":"Point"}
}