{
  "type": "Feature",
  "properties": {
    "iso:country":"ES",
    "sg:address":"Av Catalunya, 88",
    "sg:city":"Alcanar",
    "sg:orig_category":"M\u00c9dicos: Estomatolog\u00cda",
    "sg:phone":"+34 977 73 05 65",
    "sg:postcode":"43530",
    "sg:province":"Tarragona",
    "wof:name":"Wollner  Barbara",
    "wof:placetype":"venue"
},
  "geometry": {"coordinates":[0.4828226864,40.5419616699],"type":"Point"}
}