{
  "type": "Feature",
  "properties": {
    "addr:full":"Calle de Amos Olivares, 7 Pedro Mu\u00e7oz Ciudad Real 13620",
    "addr:housenumber":"7",
    "addr:postcode":"13620",
    "addr:street":"Calle De Amos Olivares;Pedro Muc\u0327Oz",
    "iso:country":"ES",
    "sg:address":"Calle de Amos Olivares, 7",
    "sg:city":"Pedro Mu\u00e7oz",
    "sg:orig_category":"Productores Recolectores, Venta Directa De Vinos",
    "sg:phone":"+34 926 58 62 80",
    "sg:postcode":"13620",
    "sg:province":"Ciudad Real",
    "wof:name":"Montoya Giron Jesus",
    "wof:placetype":"venue"
},
  "geometry": {"coordinates":[-2.9464366436,39.4054374695],"type":"Point"}
}