{
  "type": "Feature",
  "properties": {
    "addr:full":"Rua Cornuval, S/n Carballi\u00f1o Ourense 32500",
    "addr:housenumber":"s",
    "addr:postcode":"32500",
    "addr:street":"Rua Cornuval;/ N",
    "iso:country":"ES",
    "sg:address":"Rua Cornuval, S/n",
    "sg:city":"Carballi\u00f1o",
    "sg:orig_category":"Asilos De Ancianos. Centros Privados",
    "sg:phone":"+34 988 27 02 70",
    "sg:postcode":"32500",
    "sg:province":"Ourense",
    "wof:name":"Xunta De Galicia",
    "wof:placetype":"venue"
},
  "geometry": {"coordinates":[-8.07807827,42.4357643127],"type":"Point"}
}