{
  "type": "Feature",
  "properties": {
    "iso:country":"ES",
    "sg:address":"Carrer de Nou, 16",
    "sg:city":"Manresa",
    "sg:orig_category":"\u00d3ptica: Instrumentos (fabricaci\u00d3n)",
    "sg:phone":"+34 938 72 31 42",
    "sg:postcode":"08241",
    "sg:province":"Barcelona",
    "wof:name":"Enric I Vicenc Caballe Perez S.c.p.",
    "wof:placetype":"venue"
},
  "geometry": {"coordinates":[1.8251819611,41.7245025635],"type":"Point"}
}