{
  "type": "Feature",
  "properties": {
    "iso:country":"ES",
    "sg:address":"R. Draper (pol Valldegata Draper), S/n",
    "sg:city":"Arenys Mar",
    "sg:orig_category":"Vinos (agentes)",
    "sg:phone":"+34 937 92 36 51",
    "sg:postcode":"08350",
    "sg:province":"Barcelona",
    "wof:name":"Cervera Sampera Joaquim",
    "wof:placetype":"venue"
},
  "geometry": {"coordinates":[2.5383400917,41.5795402527],"type":"Point"}
}