{
  "type": "Feature",
  "properties": {
    "iso:country":"ES",
    "sg:address":"Carrer de Setze De Juliol, 28",
    "sg:city":"Poligon Industrial De Son Castello",
    "sg:orig_category":"Madera Para Construcci\u00d3n E Industria",
    "sg:phone":"+34 971 43 42 40",
    "sg:postcode":"07009",
    "sg:province":"Islas Baleares",
    "wof:name":"Kera Gres S.l.",
    "wof:placetype":"venue"
},
  "geometry": {"coordinates":[2.6776249409,39.6072845459],"type":"Point"}
}