{
  "type": "Feature",
  "properties": {
    "addr:full":"Cmno Campo De Abajo, S/n Campo Abajo Murcia 30565",
    "addr:housenumber":"s",
    "addr:postcode":"30565",
    "addr:street":"Cmno Campo De Abajo;/ N",
    "iso:country":"ES",
    "sg:address":"Cmno Campo De Abajo, S/n",
    "sg:city":"Campo Abajo",
    "sg:orig_category":"Comercio De Hierro",
    "sg:phone":"+34 968 62 89 03",
    "sg:postcode":"30565",
    "sg:province":"Murcia",
    "wof:name":"Hierros J.olmos S.l.",
    "wof:placetype":"venue"
},
  "geometry": {"coordinates":[-1.2395490408,38.0263290405],"type":"Point"}
}