{
  "type": "Feature",
  "properties": {
    "addr:full":"Calle de Solano, 4 Madrid Madrid 28042",
    "addr:housenumber":"4",
    "addr:postcode":"28042",
    "addr:street":"Calle De Solano",
    "iso:country":"ES",
    "sg:address":"Calle de Solano, 4",
    "sg:city":"Madrid",
    "sg:orig_category":"Arquitectos",
    "sg:phone":"+34 913 05 54 54",
    "sg:postcode":"28042",
    "sg:province":"Madrid",
    "wof:name":"Jorquera Perez Julian",
    "wof:placetype":"venue"
},
  "geometry": {"coordinates":[-3.5969030857,40.4739837646],"type":"Point"}
}