{
  "type": "Feature",
  "properties": {
    "addr:full":"Plaz Alonso Martinez, 7 Burgos Burgos 09003",
    "addr:housenumber":"7",
    "addr:postcode":"09003",
    "addr:street":"Plaz;Martinez",
    "iso:country":"ES",
    "sg:address":"Plaz Alonso Martinez, 7",
    "sg:city":"Burgos",
    "sg:orig_category":"Material Y Suministros Para Fotocopiadoras, Reprograf\u00cda",
    "sg:phone":"+34 947 20 83 46",
    "sg:postcode":"09003",
    "sg:province":"Burgos",
    "wof:name":"Oficenter Burgos S.l.",
    "wof:placetype":"venue"
},
  "geometry": {"coordinates":[-3.6998100281,42.3410835266],"type":"Point"}
}