{
  "type": "Feature",
  "properties": {
    "addr:full":"Calle de Cabo Pe\u00d1as, 3 Algeciras C\u00e1diz 11205",
    "addr:housenumber":"3;ca\u0301diz",
    "addr:postcode":"11205",
    "addr:street":"Calle De Cabo Pen\u0303As",
    "iso:country":"ES",
    "sg:address":"Calle de Cabo Pe\u00d1as, 3",
    "sg:city":"Algeciras",
    "sg:orig_category":"Empresas Portuarias",
    "sg:phone":"+34 956 66 35 63",
    "sg:postcode":"11205",
    "sg:province":"C\u00e1diz",
    "wof:name":"Lopez Morales Eusebio",
    "wof:placetype":"venue"
},
  "geometry": {"coordinates":[-5.4498896599,36.1602554321],"type":"Point"}
}