{
  "type": "Feature",
  "properties": {
    "iso:country":"ES",
    "sg:address":"Calle de Vergara, 46",
    "sg:city":"San Fernando De Henares",
    "sg:orig_category":"Agencias Y Agentes Comerciales, Representantes",
    "sg:phone":"+34 916 69 86 04",
    "sg:postcode":"28830",
    "sg:province":"Madrid",
    "wof:name":"Mejia Garrido Oscar",
    "wof:placetype":"venue"
},
  "geometry": {"coordinates":[-3.5287880898,40.4209671021],"type":"Point"}
}