{
  "type": "Feature",
  "properties": {
    "addr:full":"Carr Anselm Clave, 84 Blanes Girona 17300",
    "addr:housenumber":"84",
    "addr:postcode":"17300",
    "addr:street":"Carr Anselm Clave",
    "iso:country":"ES",
    "sg:address":"Carr Anselm Clave, 84",
    "sg:city":"Blanes",
    "sg:orig_category":"Farmacias",
    "sg:phone":"+34 972 33 16 56",
    "sg:postcode":"17300",
    "sg:province":"Girona",
    "wof:name":"Adell Creixell Maria",
    "wof:placetype":"venue"
},
  "geometry": {"coordinates":[2.7843170166,41.6788864136],"type":"Point"}
}