{
  "type": "Feature",
  "properties": {
    "iso:country":"ES",
    "sg:address":"Carr Camp De Morvedre, 16",
    "sg:city":"Grau I Platja",
    "sg:orig_category":"Transporte En General",
    "sg:phone":"+34 962 84 80 24",
    "sg:postcode":"46730",
    "sg:province":"Valencia",
    "wof:name":"Vipei Hotels S.l.",
    "wof:placetype":"venue"
},
  "geometry": {"coordinates":[-0.1707569957,39.0079116821],"type":"Point"}
}