{
  "type": "Feature",
  "properties": {
    "addr:full":"Avda Andalucia, 220 Dos Hermanas Sevilla 41700",
    "addr:housenumber":"220",
    "addr:postcode":"41700",
    "addr:street":"Avda Andalucia;Sevilla",
    "iso:country":"ES",
    "sg:address":"Avda Andalucia, 220",
    "sg:city":"Dos Hermanas",
    "sg:orig_category":"Telas Y Sedas (al Por Menor)",
    "sg:phone":"+34 955 67 86 95",
    "sg:postcode":"41700",
    "sg:province":"Sevilla",
    "wof:name":"Paredes Diaz Maria Del Carmen",
    "wof:placetype":"venue"
},
  "geometry": {"coordinates":[-5.9205641747,37.2755661011],"type":"Point"}
}