{
  "type": "Feature",
  "properties": {
    "addr:full":"Egido Alto, S/n Jamilena Ja\u00e9n 23658",
    "addr:housenumber":"s / n",
    "addr:postcode":"23658",
    "addr:street":"Egido",
    "iso:country":"ES",
    "sg:address":"Egido Alto, S/n",
    "sg:city":"Jamilena",
    "sg:orig_category":"Construcciones Met\u00c1licas",
    "sg:phone":"+34 953 56 61 27",
    "sg:postcode":"23658",
    "sg:province":"Ja\u00e9n",
    "wof:name":"Peragon Gutierrez Antonio",
    "wof:placetype":"venue"
},
  "geometry": {"coordinates":[-3.9122838974,37.7490653992],"type":"Point"}
}