{
  "type": "Feature",
  "properties": {
    "addr:full":"Calle de Henry Dunant, 17 Palmas De Gran Canaria Las Palmas 35011",
    "addr:housenumber":"17",
    "addr:postcode":"35011",
    "addr:street":"Calle De Henry Dunant",
    "iso:country":"ES",
    "sg:address":"Calle de Henry Dunant, 17",
    "sg:city":"Palmas De Gran Canaria",
    "sg:orig_category":"Carnicer\u00cdas, Carnicer\u00cdas",
    "sg:phone":"+34 928 25 58 78",
    "sg:postcode":"35011",
    "sg:province":"Las Palmas",
    "wof:name":"Santana Santana Rosario Del Carmen",
    "wof:placetype":"venue"
},
  "geometry": {"coordinates":[-15.4387493134,28.1107501984],"type":"Point"}
}