{
  "type": "Feature",
  "properties": {
    "iso:country":"ES",
    "sg:address":"Av Miraflores, 98",
    "sg:city":"Hospitalet Llobregat",
    "sg:orig_category":"Pod\u00d3logos: Pedicuros",
    "sg:phone":"+34 934 40 28 47",
    "sg:postcode":"08905",
    "sg:province":"Barcelona",
    "wof:name":"Otamendi Villanueva Angel Antonio",
    "wof:placetype":"venue"
},
  "geometry": {"coordinates":[2.1065440178,41.3730125427],"type":"Point"}
}