{
  "type": "Feature",
  "properties": {
    "iso:country":"ES",
    "sg:address":"Pg Sant Antoni (de), 16",
    "sg:city":"Tarragona",
    "sg:orig_category":"Abogados",
    "sg:phone":"+34 977 23 32 22",
    "sg:postcode":"43003",
    "sg:province":"Tarragona",
    "wof:name":"Zurita Jimenez Idilio",
    "wof:placetype":"venue"
},
  "geometry": {"coordinates":[1.259223938,41.1167411804],"type":"Point"}
}