{
  "type": "Feature",
  "properties": {
    "addr:full":"Calle de Torreta De Miramar, 12 Valencia Valencia 46020",
    "addr:housenumber":"12",
    "addr:postcode":"46020",
    "addr:street":"Calle De Torreta De Miramar",
    "iso:country":"ES",
    "sg:address":"Calle de Torreta De Miramar, 12",
    "sg:city":"Valencia",
    "sg:orig_category":"Promotores Constructores",
    "sg:phone":"+34 963 60 18 47",
    "sg:postcode":"46020",
    "sg:province":"Valencia",
    "wof:name":"Expocasa S.a",
    "wof:placetype":"venue"
},
  "geometry": {"coordinates":[-0.36243999,39.4877815247],"type":"Point"}
}