{
  "type": "Feature",
  "properties": {
    "addr:full":"Calle de Pedro Maria Ric, 21 Zaragoza Zaragoza 50008",
    "addr:housenumber":"21",
    "addr:postcode":"50008",
    "addr:street":"Calle De Pedro Maria Ric",
    "iso:country":"ES",
    "sg:address":"Calle de Pedro Maria Ric, 21",
    "sg:city":"Zaragoza",
    "sg:orig_category":"Telas Y Sedas (al Por Menor)",
    "sg:phone":"+34 976 22 99 42",
    "sg:postcode":"50008",
    "sg:province":"Zaragoza",
    "wof:name":"Selecciones Blasmar S.l.laboral",
    "wof:placetype":"venue"
},
  "geometry": {"coordinates":[-0.8825809956,41.6447601318],"type":"Point"}
}