{
  "type": "Feature",
  "properties": {
    "addr:full":"Ctra Barcelona, 342 Barbera Valles Barcelona 08210",
    "addr:housenumber":"342",
    "addr:postcode":"08210",
    "addr:street":"Ctra Barcelona",
    "iso:country":"ES",
    "sg:address":"Ctra Barcelona, 342",
    "sg:city":"Barbera Valles",
    "sg:orig_category":"Agentes Generales De Seguros",
    "sg:phone":"+34 937 18 90 55",
    "sg:postcode":"08210",
    "sg:province":"Barcelona",
    "wof:name":"Muelas Fernandez Diego",
    "wof:placetype":"venue"
},
  "geometry": {"coordinates":[2.1213850975,41.5248374939],"type":"Point"}
}