{
  "type": "Feature",
  "properties": {
    "addr:full":"Carr Mestre Serrano, 5 Pu\u00e7ol Valencia 46530",
    "addr:housenumber":"5",
    "addr:postcode":"46530",
    "addr:street":"Carr Mestre Serrano",
    "iso:country":"ES",
    "sg:address":"Carr Mestre Serrano, 5",
    "sg:city":"Pu\u00e7ol",
    "sg:orig_category":"Carnicer\u00cdas, Carnicer\u00cdas",
    "sg:phone":"+34 961 42 05 07",
    "sg:postcode":"46530",
    "sg:province":"Valencia",
    "wof:name":"Adrama Sancho Adelaida",
    "wof:placetype":"venue"
},
  "geometry": {"coordinates":[-0.3083904088,39.6218986511],"type":"Point"}
}