{
  "type": "Feature",
  "properties": {
    "addr:full":"Avda Juan Carlos I, 61 Alhama Murcia Murcia 30840",
    "addr:housenumber":"61",
    "addr:postcode":"30840",
    "addr:street":"Avda Juan Carlos I",
    "iso:country":"ES",
    "sg:address":"Avda Juan Carlos I, 61",
    "sg:city":"Alhama Murcia",
    "sg:orig_category":"Ropa Para Ni\u00d1os (al Por Menor)",
    "sg:phone":"+34 968 63 33 43",
    "sg:postcode":"30840",
    "sg:province":"Murcia",
    "wof:name":"Ortiz Garcia Maria Encarnacion",
    "wof:placetype":"venue"
},
  "geometry": {"coordinates":[-1.4256830215,37.8492546082],"type":"Point"}
}