{
  "type": "Feature",
  "properties": {
    "addr:full":"Ctra. Vilafranca, Km. 0003,0 Petra Islas Baleares 07520",
    "addr:postcode":"07520",
    "addr:street":"Ctra. Vilafranca Km. 0003,0 Petra Islas",
    "iso:country":"ES",
    "sg:address":"Ctra. Vilafranca, Km. 0003,0",
    "sg:city":"Petra",
    "sg:orig_category":"Forjas Y Altos Hornos",
    "sg:phone":"+34 971 56 10 48",
    "sg:postcode":"07520",
    "sg:province":"Islas Baleares",
    "wof:name":"Bauza Ribot Pedro Jose",
    "wof:placetype":"venue"
},
  "geometry": {"coordinates":[3.1110970974,39.6068305969],"type":"Point"}
}