{
  "type": "Feature",
  "properties": {
    "iso:country":"ES",
    "sg:address":"Calle de Madre Teresa De Calcuta, 2",
    "sg:city":"Torremolinos",
    "sg:orig_category":"Maquinaria Para Industrias Diversas",
    "sg:phone":"+34 952 05 17 42",
    "sg:postcode":"29620",
    "sg:province":"M\u00e1laga",
    "wof:name":"Almuco S.l.",
    "wof:placetype":"venue"
},
  "geometry": {"coordinates":[-4.5168161392,36.6109313965],"type":"Point"}
}