{
  "type": "Feature",
  "properties": {
    "iso:country":"ES",
    "sg:address":"Carrer de Lope De Vega, 75",
    "sg:city":"Barcelona",
    "sg:orig_category":"Florister\u00cdas",
    "sg:phone":"+34 933 07 70 16",
    "sg:postcode":"08005",
    "sg:province":"Barcelona",
    "wof:name":"Benedicto Centelles Clemente",
    "wof:placetype":"venue"
},
  "geometry": {"coordinates":[2.2043170929,41.4038391113],"type":"Point"}
}