{
  "type": "Feature",
  "properties": {
    "addr:full":"Calle de San Vicente, 17 San Vicente De Barakaldo Vizcaya 48902",
    "addr:housenumber":"17",
    "addr:postcode":"48902",
    "addr:street":"Calle De San Vicente",
    "iso:country":"ES",
    "sg:address":"Calle de San Vicente, 17",
    "sg:city":"San Vicente De Barakaldo",
    "sg:orig_category":"Frutas, Legumbres Frescas Y Tempranas (al Por Menor)",
    "sg:phone":"+34 944 38 67 59",
    "sg:postcode":"48902",
    "sg:province":"Vizcaya",
    "wof:name":"Martin Fernandez Victor Manuel",
    "wof:placetype":"venue"
},
  "geometry": {"coordinates":[-2.9946939945,43.2957687378],"type":"Point"}
}