{
  "type": "Feature",
  "properties": {
    "addr:full":"Calle de Compostela, 1 Coru\u00d1a A Coru\u00f1a 15004",
    "addr:housenumber":"1",
    "addr:postcode":"15004",
    "addr:street":"Calle De Compostela;Corun\u0303A",
    "iso:country":"ES",
    "sg:address":"Calle de Compostela, 1",
    "sg:city":"Coru\u00d1a",
    "sg:orig_category":"Bisuter\u00cda, Joyer\u00cda, Relojer\u00cda (al Por Menor)",
    "sg:phone":"+34 981 20 36 86",
    "sg:postcode":"15004",
    "sg:province":"A Coru\u00f1a",
    "sg:website":"www.tous.es",
    "wof:name":"Tous Joyeros Galicia S.l.",
    "wof:placetype":"venue"
},
  "geometry": {"coordinates":[-8.4051055908,43.3660545349],"type":"Point"}
}