{
  "type": "Feature",
  "properties": {
    "addr:full":"Calle de Ruben Dario, 1 Zubia Granada 18140",
    "addr:housenumber":"1",
    "addr:postcode":"18140",
    "addr:street":"Calle De Ruben Dario",
    "iso:country":"ES",
    "sg:address":"Calle de Ruben Dario, 1",
    "sg:city":"Zubia",
    "sg:orig_category":"Muebles, Minoristas",
    "sg:phone":"+34 958 59 30 32",
    "sg:postcode":"18140",
    "sg:province":"Granada",
    "wof:name":"Rodriguez Martinez Irene",
    "wof:placetype":"venue"
},
  "geometry": {"coordinates":[-3.5841639042,37.1218681335],"type":"Point"}
}