{
  "type": "Feature",
  "properties": {
    "addr:full":"Avda Dos De Mayo (del), 51 Mostoles Madrid 28934",
    "addr:housenumber":"51",
    "addr:postcode":"28934",
    "addr:street":"Avda Dos De Mayo Del",
    "iso:country":"ES",
    "sg:address":"Avda Dos De Mayo (del), 51",
    "sg:city":"Mostoles",
    "sg:orig_category":"Pod\u00d3logos: Pedicuros",
    "sg:phone":"+34 916 14 67 70",
    "sg:postcode":"28934",
    "sg:province":"Madrid",
    "wof:name":"Monsalve Ceprian Felipe",
    "wof:placetype":"venue"
},
  "geometry": {"coordinates":[-3.8722980022,40.3197364807],"type":"Point"}
}