{
  "type": "Feature",
  "properties": {
    "addr:full":"Calle de San Juan, 2 Santa Olalla Toledo 45530",
    "addr:housenumber":"2",
    "addr:postcode":"45530",
    "addr:street":"Calle De San Juan",
    "iso:country":"ES",
    "sg:address":"Calle de San Juan, 2",
    "sg:city":"Santa Olalla",
    "sg:orig_category":"Telas Y Sedas (al Por Menor)",
    "sg:phone":"+34 925 79 71 08",
    "sg:postcode":"45530",
    "sg:province":"Toledo",
    "wof:name":"Moreno Arrogante Isidoro",
    "wof:placetype":"venue"
},
  "geometry": {"coordinates":[-4.4313101768,40.023311615],"type":"Point"}
}