{
  "type": "Feature",
  "properties": {
    "iso:country":"ES",
    "sg:address":"Canella Cega, 62",
    "sg:city":"Verin",
    "sg:orig_category":"Lavado, Limpieza De Veh\u00cdculos",
    "sg:phone":"+34 988 41 31 13",
    "sg:postcode":"32600",
    "sg:province":"Ourense",
    "wof:name":"Atanes Alvarez Jose Angel",
    "wof:placetype":"venue"
},
  "geometry": {"coordinates":[-7.4297714233,41.9357872009],"type":"Point"}
}