{
  "type": "Feature",
  "properties": {
    "iso:country":"ES",
    "sg:address":"Calle de Correillo (el), 3",
    "sg:city":"Playa Blanca",
    "sg:orig_category":"Inmobiliaria (agencias)",
    "sg:phone":"+34 928 51 88 15",
    "sg:postcode":"35580",
    "sg:province":"Las Palmas",
    "wof:name":"Cal Y Luna S.l.",
    "wof:placetype":"venue"
},
  "geometry": {"coordinates":[-13.8330440521,28.8616466522],"type":"Point"}
}