{
  "type": "Feature",
  "properties": {
    "addr:full":"Carr Fra Andreu Capella, 5 Seu D'urgell Lleida 25700",
    "addr:housenumber":"5",
    "addr:postcode":"25700",
    "addr:street":"Carr Fra Andreu Capella",
    "iso:country":"ES",
    "sg:address":"Carr Fra Andreu Capella, 5",
    "sg:city":"Seu D'urgell",
    "sg:orig_category":"Inmobiliaria (agencias)",
    "sg:phone":"+34 973 35 55 83",
    "sg:postcode":"25700",
    "sg:province":"Lleida",
    "sg:website":"www.sasi.es",
    "wof:name":"Inmobiliaria Solsona Roca Associats S.l.",
    "wof:placetype":"venue"
},
  "geometry": {"coordinates":[0.6457189918,41.6027946472],"type":"Point"}
}