{
  "type": "Feature",
  "properties": {
    "addr:full":"Calle de Gonzalo De Cordoba, 11 Madrid Madrid 28010",
    "addr:housenumber":"11",
    "addr:postcode":"madrid;28010",
    "addr:street":"Calle De Gonzalo De Cordoba",
    "iso:country":"ES",
    "sg:address":"Calle de Gonzalo De Cordoba, 11",
    "sg:city":"Madrid",
    "sg:orig_category":"Asesor\u00cda Fiscal Y Jur\u00cddica",
    "sg:phone":"+34 914 44 03 46",
    "sg:postcode":"28010",
    "sg:province":"Madrid",
    "wof:name":"Jose Luis Mu\u00f1oz Alonso Y Asociados",
    "wof:placetype":"venue"
},
  "geometry": {"coordinates":[-3.7025959492,40.432384491],"type":"Point"}
}