{
  "type": "Feature",
  "properties": {
    "iso:country":"ES",
    "sg:address":"Pla\u00c7 Camp D'en Prats, S/n",
    "sg:city":"Palafrugell",
    "sg:orig_category":"Panader\u00cdas, Panader\u00cdas",
    "sg:phone":"+34 972 30 34 23",
    "sg:postcode":"17200",
    "sg:province":"Girona",
    "wof:name":"Girbal Fuentes Luis",
    "wof:placetype":"venue"
},
  "geometry": {"coordinates":[3.1696619987,41.9163589478],"type":"Point"}
}