{
  "type": "Feature",
  "properties": {
    "addr:full":"Avda Andalucia, 3 Linares Ja\u00e9n 23700",
    "addr:housenumber":"3",
    "addr:postcode":"23700",
    "addr:street":"Avda Andalucia;Jae\u0301N",
    "iso:country":"ES",
    "sg:address":"Avda Andalucia, 3",
    "sg:city":"Linares",
    "sg:orig_category":"Doctores En Medicina",
    "sg:phone":"+34 953 65 61 92",
    "sg:postcode":"23700",
    "sg:province":"Ja\u00e9n",
    "wof:name":"Said Abosaif Kamel",
    "wof:placetype":"venue"
},
  "geometry": {"coordinates":[-3.6404509544,38.0931854248],"type":"Point"}
}