{
  "type": "Feature",
  "properties": {
    "addr:full":"Avda Coru\u00d1a (de La), 38 Monterroso Lugo 27560",
    "addr:housenumber":"38",
    "addr:postcode":"27560",
    "addr:street":"Avda Corun\u0303A De La",
    "iso:country":"ES",
    "sg:address":"Avda Coru\u00d1a (de La), 38",
    "sg:city":"Monterroso",
    "sg:orig_category":"M\u00c1rmoles, Granitos Y Piedras Naturales",
    "sg:phone":"+34 982 37 72 11",
    "sg:postcode":"27560",
    "sg:province":"Lugo",
    "wof:name":"Vazquez Albor Jesus",
    "wof:placetype":"venue"
},
  "geometry": {"coordinates":[-7.8400688171,42.794921875],"type":"Point"}
}