{
  "type": "Feature",
  "properties": {
    "addr:full":"Avda Casta\u00d1o, 88 Toledo Toledo 45005",
    "addr:housenumber":"88",
    "addr:postcode":"45005",
    "addr:street":"Avda Castan\u0303O",
    "iso:country":"ES",
    "sg:address":"Avda Casta\u00d1o, 88",
    "sg:city":"Toledo",
    "sg:orig_category":"Inform\u00c1tica, Ofim\u00c1tica (estudios, Asesor\u00cda, Ingenier\u00cda, Formaci\u00d3n)",
    "sg:phone":"+34 925 22 10 89",
    "sg:postcode":"45005",
    "sg:province":"Toledo",
    "wof:name":"Garcia-zarco Maeso Francisco Javier",
    "wof:placetype":"venue"
},
  "geometry": {"coordinates":[-4.059325695,39.9001274109],"type":"Point"}
}