{
  "type": "Feature",
  "properties": {
    "addr:full":"Calle de Hernan Cortes, 45 Monforte Cid Alicante 03670",
    "addr:housenumber":"45",
    "addr:postcode":"03670",
    "addr:street":"Calle De Hernan Cortes",
    "iso:country":"ES",
    "sg:address":"Calle de Hernan Cortes, 45",
    "sg:city":"Monforte Cid",
    "sg:orig_category":"Reposter\u00cdas",
    "sg:phone":"+34 965 62 01 06",
    "sg:postcode":"03670",
    "sg:province":"Alicante",
    "wof:name":"Hermanos Cervera C.b.",
    "wof:placetype":"venue"
},
  "geometry": {"coordinates":[-0.7302809954,38.3800697327],"type":"Point"}
}