{
  "type": "Feature",
  "properties": {
    "iso:country":"ES",
    "sg:address":"Avda San Luis, 146",
    "sg:city":"Madrid",
    "sg:orig_category":"Ingeniero",
    "sg:phone":"+34 913 83 08 24",
    "sg:postcode":"28033",
    "sg:province":"Madrid",
    "wof:name":"Colina Robledo Carlos",
    "wof:placetype":"venue"
},
  "geometry": {"coordinates":[-3.6722431183,40.4798278809],"type":"Point"}
}