{
  "type": "Feature",
  "properties": {
    "iso:country":"ES",
    "sg:address":"Carr Teatre, 29",
    "sg:city":"Cabanes",
    "sg:orig_category":"Fabricaci\u00d3n, Venta De Productos Base Farmac\u00c9uticos",
    "sg:phone":"+34 964 33 13 38",
    "sg:postcode":"12180",
    "sg:province":"Castell\u00f3n",
    "wof:name":"Colino Esteban Maria Angeles",
    "wof:placetype":"venue"
},
  "geometry": {"coordinates":[0.0448350012,40.1544303894],"type":"Point"}
}