{
  "type": "Feature",
  "properties": {
    "iso:country":"ES",
    "sg:address":"Ctra Nacional V (polig Soto), Km. 0103,4",
    "sg:city":"Cazalegas",
    "sg:orig_category":"Muebles, Minoristas",
    "sg:phone":"+34 925 87 26 32",
    "sg:postcode":"45553",
    "sg:province":"Toledo",
    "wof:name":"Zamorano Bardera Marcial",
    "wof:placetype":"venue"
},
  "geometry": {"coordinates":[-4.6774601936,40.0108451843],"type":"Point"}
}