{
  "type": "Feature",
  "properties": {
    "iso:country":"ES",
    "sg:address":"Avda Obispo Perez Caceres, 14",
    "sg:city":"G\u00fcimar",
    "sg:orig_category":"Ropa Para Se\u00d1oras Y Caballeros (al Por Menor)",
    "sg:phone":"+34 922 51 17 79",
    "sg:postcode":"38500",
    "sg:province":"Santa Cruz De Tenerife",
    "wof:name":"Garcia Arzola Carmen Reyes",
    "wof:placetype":"venue"
},
  "geometry": {"coordinates":[-16.4101371765,28.3159675598],"type":"Point"}
}