{
  "type": "Feature",
  "properties": {
    "iso:country":"ES",
    "sg:address":"Calle de Jata Monte, 3",
    "sg:city":"Bilbao",
    "sg:orig_category":"Peluqueros: De Se\u00d1oras",
    "sg:phone":"+34 944 47 33 13",
    "sg:postcode":"48014",
    "sg:province":"Vizcaya",
    "wof:name":"Fernandez Diez Maria Sagrario",
    "wof:placetype":"venue"
},
  "geometry": {"coordinates":[-2.9488229752,43.2745895386],"type":"Point"}
}