{
  "type": "Feature",
  "properties": {
    "addr:full":"Calle de Mayas (las), 6 Collado Villalba Madrid 28400",
    "addr:housenumber":"6",
    "addr:postcode":"28400",
    "addr:street":"Calle De Mayas Las",
    "iso:country":"ES",
    "sg:address":"Calle de Mayas (las), 6",
    "sg:city":"Collado Villalba",
    "sg:orig_category":"Audiovisuales: Material Y Accesorios (al Por Menor)",
    "sg:phone":"+34 918 49 02 00",
    "sg:postcode":"28400",
    "sg:province":"Madrid",
    "sg:website":"www.elenco-audiovision.es",
    "wof:name":"Elenco Audiovision S.l.",
    "wof:placetype":"venue"
},
  "geometry": {"coordinates":[-3.9993629456,40.640499115],"type":"Point"}
}