{
  "type": "Feature",
  "properties": {
    "iso:country":"ES",
    "sg:address":"Pasaje Santa Fe, 7",
    "sg:city":"Briviesca",
    "sg:orig_category":"Molduras, Junquillos, Listones Y Molduras Perforadas",
    "sg:phone":"+34 947 59 21 33",
    "sg:postcode":"09240",
    "sg:province":"Burgos",
    "wof:name":"Jose Ignacio Tejada Edeso Y Otra S.cv.",
    "wof:placetype":"venue"
},
  "geometry": {"coordinates":[-3.3249030113,42.5507316589],"type":"Point"}
}