{
  "type": "Feature",
  "properties": {
    "addr:full":"Avda Oscar Espla, 35 Alacant Alicante 03007",
    "addr:housenumber":"35",
    "addr:postcode":"03007",
    "addr:street":"Avda Oscar Espla",
    "iso:country":"ES",
    "sg:address":"Avda Oscar Espla, 35",
    "sg:city":"Alacant",
    "sg:orig_category":"Arquitectos",
    "sg:phone":"+34 965 22 78 38",
    "sg:postcode":"03007",
    "sg:province":"Alicante",
    "wof:name":"Albajar Molera Maria Elena",
    "wof:placetype":"venue"
},
  "geometry": {"coordinates":[-0.4945740998,38.3425979614],"type":"Point"}
}