{
  "type": "Feature",
  "properties": {
    "addr:full":"Alferez Rojas, 16 Navas San Juan Ja\u00e9n 23240",
    "addr:housenumber":"16",
    "addr:postcode":"23240",
    "addr:street":"Alferez Rojas",
    "iso:country":"ES",
    "sg:address":"Alferez Rojas, 16",
    "sg:city":"Navas San Juan",
    "sg:orig_category":"Caf\u00c9s, Bares, Cervecer\u00cdas",
    "sg:phone":"+34 953 68 95 50",
    "sg:postcode":"23240",
    "sg:province":"Ja\u00e9n",
    "wof:name":"Garrido Marin Juan Miguel",
    "wof:placetype":"venue"
},
  "geometry": {"coordinates":[-3.3145930767,38.1859436035],"type":"Point"}
}