{
  "type": "Feature",
  "properties": {
    "iso:country":"ES",
    "sg:address":"Av P Asturias, 36",
    "sg:city":"Murcia",
    "sg:orig_category":"Centros P\u00dablicos De Formaci\u00d3n Profesional Y T\u00c9cnica",
    "sg:phone":"+34 968 24 62 39",
    "sg:postcode":"30007",
    "sg:province":"Murcia",
    "wof:name":"Allepuz Ros Ana",
    "wof:placetype":"venue"
},
  "geometry": {"coordinates":[-1.1321803331,38.0020904541],"type":"Point"}
}