{
  "type": "Feature",
  "properties": {
    "addr:full":"Donostia Ibilbidea, 127 Astigarraga Guip\u00f9zcoa 20115",
    "addr:housenumber":"127",
    "addr:postcode":"20115",
    "addr:street":"Donostia Ibilbidea;Guipu\u0300Zcoa",
    "iso:country":"ES",
    "sg:address":"Donostia Ibilbidea, 127",
    "sg:city":"Astigarraga",
    "sg:orig_category":"Inform\u00c1tica (estudios, Servicios, Asesor\u00cda, Formaci\u00d3n)",
    "sg:phone":"+34 943 33 34 11",
    "sg:postcode":"20115",
    "sg:province":"Guip\u00f9zcoa",
    "wof:name":"Jgn Asesoria De Servicios Informaticos S.l.",
    "wof:placetype":"venue"
},
  "geometry": {"coordinates":[-1.9493430853,43.2832946777],"type":"Point"}
}