{
  "type": "Feature",
  "properties": {
    "addr:full":"Avda Monforte De Lemos, 170 Madrid Madrid 28029",
    "addr:housenumber":"170",
    "addr:postcode":"28029",
    "addr:street":"Avda Monforte De Lemos",
    "iso:country":"ES",
    "sg:address":"Avda Monforte De Lemos, 170",
    "sg:city":"Madrid",
    "sg:orig_category":"Art\u00cdculos De Decoraci\u00d3n (fabricaci\u00d3n Y Al Por Mayor)",
    "sg:phone":"+34 913 73 69 40",
    "sg:postcode":"28029",
    "sg:province":"Madrid",
    "wof:name":"Rivas Manias Jose Carlos",
    "wof:placetype":"venue"
},
  "geometry": {"coordinates":[-3.7148239613,40.4773483276],"type":"Point"}
}