{
  "type": "Feature",
  "properties": {
    "iso:country":"ES",
    "sg:address":"Ctra Enlace Doctor Morera Bravo (el Pueblo), 1",
    "sg:city":"Pueblo",
    "sg:orig_category":"Ense\u00d1anza, Formaci\u00d3n Profesional: Aprendizaje",
    "sg:phone":"+34 922 44 00 52",
    "sg:postcode":"38730",
    "sg:province":"Santa Cruz De Tenerife",
    "wof:name":"Escuela Insular De Artesania",
    "wof:placetype":"venue"
},
  "geometry": {"coordinates":[-17.7801933289,28.6060791016],"type":"Point"}
}