{
  "type": "Feature",
  "properties": {
    "addr:full":"Calle de San Mateo, 27 Alacant Alicante 03012",
    "addr:housenumber":"27",
    "addr:postcode":"03012",
    "addr:street":"Calle De San Mateo",
    "iso:country":"ES",
    "sg:address":"Calle de San Mateo, 27",
    "sg:city":"Alacant",
    "sg:orig_category":"Cl\u00cdnicas M\u00c9dicas",
    "sg:phone":"+34 965 25 40 88",
    "sg:postcode":"03012",
    "sg:province":"Alicante",
    "wof:name":"Profesalud S.l.",
    "wof:placetype":"venue"
},
  "geometry": {"coordinates":[-0.4780440927,38.3586196899],"type":"Point"}
}