{
  "type": "Feature",
  "properties": {
    "iso:country":"ES",
    "sg:address":"Calle de Federico Mayo, S/n",
    "sg:city":"Fitero",
    "sg:orig_category":"Supermercados Y Hipermercados",
    "sg:phone":"+34 948 77 60 92",
    "sg:postcode":"31593",
    "sg:province":"Navarra",
    "wof:name":"Sociedad Cooperativa Fiterana De Consumo",
    "wof:placetype":"venue"
},
  "geometry": {"coordinates":[-1.856243968,42.0581512451],"type":"Point"}
}