{
  "type": "Feature",
  "properties": {
    "iso:country":"ES",
    "sg:address":"Ctra Gilena-estepa, Km. 0001,0",
    "sg:city":"Gilena",
    "sg:orig_category":"Explotaci\u00d3n De Canteras",
    "sg:phone":"+34 954 82 61 30",
    "sg:postcode":"41565",
    "sg:province":"Sevilla",
    "wof:name":"Industrias Calizas Alvarez S.a.",
    "wof:placetype":"venue"
},
  "geometry": {"coordinates":[-4.9137740135,37.2512893677],"type":"Point"}
}