{
  "type": "Feature",
  "properties": {
    "addr:full":"Calle de Europa, 10 Macael Almer\u00eda 04867",
    "addr:housenumber":"10",
    "addr:postcode":"04867",
    "addr:street":"Calle De Europa",
    "iso:country":"ES",
    "sg:address":"Calle de Europa, 10",
    "sg:city":"Macael",
    "sg:orig_category":"Ingeniero",
    "sg:phone":"+34 950 12 61 12",
    "sg:postcode":"04867",
    "sg:province":"Almer\u00eda",
    "wof:name":"Masal Sistemas S.l.",
    "wof:placetype":"venue"
},
  "geometry": {"coordinates":[-2.3049368858,37.3332595825],"type":"Point"}
}