{
  "type": "Feature",
  "properties": {
    "iso:country":"ES",
    "sg:address":"Calle de San Gregorio, 11",
    "sg:city":"Madrid",
    "sg:orig_category":"Arquitectos",
    "sg:phone":"+34 913 08 15 38",
    "sg:postcode":"28004",
    "sg:province":"Madrid",
    "sg:website":"www.trassanet.net",
    "wof:name":"Trassa Rehabilitacion S.l.",
    "wof:placetype":"venue"
},
  "geometry": {"coordinates":[-3.6974608898,40.4236030579],"type":"Point"}
}