{
  "type": "Feature",
  "properties": {
    "iso:country":"ES",
    "sg:address":"Calle de Galicia, 5",
    "sg:city":"Torviscas Centro",
    "sg:orig_category":"Ingenier\u00cda, Centros De Estudios (diversos)",
    "sg:phone":"+34 922 71 92 76",
    "sg:postcode":"38660",
    "sg:province":"Santa Cruz De Tenerife",
    "wof:name":"Nagdev Nagdev Tahil Menghraj",
    "wof:placetype":"venue"
},
  "geometry": {"coordinates":[-16.7253551483,28.087978363],"type":"Point"}
}