{
  "type": "Feature",
  "properties": {
    "addr:full":"Calle de Duende, 14 Almagro Ciudad Real 13270",
    "addr:housenumber":"14",
    "addr:postcode":"13270",
    "addr:street":"Calle De Duende",
    "iso:country":"ES",
    "sg:address":"Calle de Duende, 14",
    "sg:city":"Almagro",
    "sg:orig_category":"Promotores Constructores",
    "sg:phone":"+34 926 88 25 45",
    "sg:postcode":"13270",
    "sg:province":"Ciudad Real",
    "wof:name":"Madrid Y Perez S.l.",
    "wof:placetype":"venue"
},
  "geometry": {"coordinates":[-3.7105278969,38.8833007812],"type":"Point"}
}