{
  "type": "Feature",
  "properties": {
    "iso:country":"ES",
    "sg:address":"Ctra. De Madrid, 19",
    "sg:city":"Albacete",
    "sg:orig_category":"Mec\u00c1nico Del Autom\u00d3vil",
    "sg:phone":"+34 967 24 64 40",
    "sg:postcode":"02006",
    "sg:province":"Albacete",
    "wof:name":"Diaz Maestro Emilio",
    "wof:placetype":"venue"
},
  "geometry": {"coordinates":[-1.8670459986,39.0047111511],"type":"Point"}
}