{
  "type": "Feature",
  "properties": {
    "addr:full":"Calle de Virgen Del Val, 56 Madrid Madrid 28027",
    "addr:housenumber":"56",
    "addr:postcode":"madrid;28027",
    "addr:street":"Calle De Virgen Del Val",
    "iso:country":"ES",
    "sg:address":"Calle de Virgen Del Val, 56",
    "sg:city":"Madrid",
    "sg:orig_category":"Servicio De Salud",
    "sg:phone":"+34 914 03 76 18",
    "sg:postcode":"28027",
    "sg:province":"Madrid",
    "wof:name":"Calleja Rubio Pedro",
    "wof:placetype":"venue"
},
  "geometry": {"coordinates":[-3.649586916,40.4401779175],"type":"Point"}
}