{
  "type": "Feature",
  "properties": {
    "iso:country":"ES",
    "sg:address":"Avda Cardenal Cisneros, 41",
    "sg:city":"Zamora",
    "sg:orig_category":"Asociaciones Humanitarias, De Cooperaci\u00d3n, De Acci\u00d3n Social",
    "sg:phone":"+34 980 51 57 72",
    "sg:postcode":"49010",
    "sg:province":"Zamora",
    "wof:name":"Asprosub",
    "wof:placetype":"venue"
},
  "geometry": {"coordinates":[-5.7406506538,41.5126342773],"type":"Point"}
}