{
  "type": "Feature",
  "properties": {
    "iso:country":"ES",
    "sg:address":"Calle de Mauricio Berecoechea, 3",
    "sg:city":"Elizondo",
    "sg:orig_category":"Panader\u00cdas, Panader\u00cdas",
    "sg:phone":"+34 948 58 03 05",
    "sg:postcode":"31700",
    "sg:province":"Navarra",
    "wof:name":"Panificadora Baztanesa S.a.",
    "wof:placetype":"venue"
},
  "geometry": {"coordinates":[-1.5159339905,43.1448783875],"type":"Point"}
}