{
  "type": "Feature",
  "properties": {
    "iso:country":"ES",
    "sg:address":"Calle de Correria, 13",
    "sg:city":"Castro Urdiales",
    "sg:orig_category":"Confecci\u00d3n (fabricaci\u00d3n, Al Por Mayor)",
    "sg:phone":"+34 942 86 10 68",
    "sg:postcode":"39700",
    "sg:province":"Cantabria",
    "wof:name":"Rodado Mellado Angel",
    "wof:placetype":"venue"
},
  "geometry": {"coordinates":[-3.2176816463,43.383972168],"type":"Point"}
}