{
  "type": "Feature",
  "properties": {
    "addr:full":"Calle de Ferrocarril, 30 Madrid Madrid 28045",
    "addr:housenumber":"30",
    "addr:postcode":"madrid;28045",
    "addr:street":"Calle De Ferrocarril",
    "iso:country":"ES",
    "sg:address":"Calle de Ferrocarril, 30",
    "sg:city":"Madrid",
    "sg:orig_category":"Importaci\u00d3n",
    "sg:phone":"+34 914 67 67 00",
    "sg:postcode":"28045",
    "sg:province":"Madrid",
    "sg:website":"www.primewood.com",
    "wof:name":"Primewood S.l.",
    "wof:placetype":"venue"
},
  "geometry": {"coordinates":[-3.6974890232,40.4010925293],"type":"Point"}
}