{
  "type": "Feature",
  "properties": {
    "iso:country":"ES",
    "sg:address":"Carr Girona, 9",
    "sg:city":"S. Lloren\u00e7 Muga",
    "sg:orig_category":"Centros De Cr\u00c9dito Inmobiliario",
    "sg:phone":"+34 972 56 93 19",
    "sg:postcode":"17732",
    "sg:province":"Girona",
    "wof:name":"Construccions La Muga Futur S.l.",
    "wof:placetype":"venue"
},
  "geometry": {"coordinates":[2.7881040573,42.321144104],"type":"Point"}
}