{
  "type": "Feature",
  "properties": {
    "iso:country":"ES",
    "sg:address":"Av Grecia, 14",
    "sg:city":"Estartit",
    "sg:orig_category":"Farmacias",
    "sg:phone":"+34 972 75 05 24",
    "sg:postcode":"17258",
    "sg:province":"Girona",
    "wof:name":"Alaball Radresa Carolina",
    "wof:placetype":"venue"
},
  "geometry": {"coordinates":[3.1946592331,42.0509262085],"type":"Point"}
}