{
  "type": "Feature",
  "properties": {
    "addr:full":"Plaz San Bartolome, 5 Astorga Le\u00f3n 24700",
    "addr:housenumber":"5",
    "addr:postcode":"24700",
    "addr:street":"Plaz San Bartolome;Leo\u0301N",
    "iso:country":"ES",
    "sg:address":"Plaz San Bartolome, 5",
    "sg:city":"Astorga",
    "sg:orig_category":"Iglesia Cat\u00d3lica",
    "sg:phone":"+34 987 61 68 48",
    "sg:postcode":"24700",
    "sg:province":"Le\u00f3n",
    "wof:name":"Parroquia De San Bartolome",
    "wof:placetype":"venue"
},
  "geometry": {"coordinates":[-6.0519361496,42.4540290833],"type":"Point"}
}