{
  "type": "Feature",
  "properties": {
    "iso:country":"ES",
    "sg:address":"Pl Constitucio (la), 12",
    "sg:city":"Vilafranca Penedes",
    "sg:orig_category":"Ropa Para Caballeros (al Por Menor)",
    "sg:phone":"+34 938 92 02 83",
    "sg:postcode":"08720",
    "sg:province":"Barcelona",
    "wof:name":"Riudalbas Soler Josep",
    "wof:placetype":"venue"
},
  "geometry": {"coordinates":[1.6981749535,41.3473167419],"type":"Point"}
}