{
  "type": "Feature",
  "properties": {
    "addr:full":"Avda Lugo De, 90 Aviles Asturias 33401",
    "addr:housenumber":"90",
    "addr:postcode":"33401",
    "addr:street":"Avda Lugo De",
    "iso:country":"ES",
    "sg:address":"Avda Lugo De, 90",
    "sg:city":"Aviles",
    "sg:orig_category":"Mec\u00c1nico Del Autom\u00d3vil",
    "sg:phone":"+34 985 56 35 60",
    "sg:postcode":"33401",
    "sg:province":"Asturias",
    "wof:name":"Avil-auto S.l.",
    "wof:placetype":"venue"
},
  "geometry": {"coordinates":[-5.9285402298,43.5723075867],"type":"Point"}
}