{
  "type": "Feature",
  "properties": {
    "addr:full":"Calle de Eduardo Dato, S/n Don Benito Badajoz 06400",
    "addr:postcode":"06400",
    "addr:street":"Calle De Eduardo Dato S / N",
    "iso:country":"ES",
    "sg:address":"Calle de Eduardo Dato, S/n",
    "sg:city":"Don Benito",
    "sg:orig_category":"Comunidades Religiosas",
    "sg:phone":"+34 924 80 15 80",
    "sg:postcode":"06400",
    "sg:province":"Badajoz",
    "wof:name":"Comunidad Religiosa Del Santo Angel",
    "wof:placetype":"venue"
},
  "geometry": {"coordinates":[-5.8728370667,38.9524154663],"type":"Point"}
}