{
  "type": "Feature",
  "properties": {
    "iso:country":"ES",
    "sg:address":"Carrer de Aribau, 184",
    "sg:city":"Barcelona",
    "sg:orig_category":"Arquitectos",
    "sg:phone":"+34 932 01 02 01",
    "sg:postcode":"08036",
    "sg:province":"Barcelona",
    "wof:name":"Peris & Vesperinas Sl.",
    "wof:placetype":"venue"
},
  "geometry": {"coordinates":[2.1527431011,41.3935699463],"type":"Point"}
}