{
  "type": "Feature",
  "properties": {
    "addr:full":"Rond Valdecarrizo (de), 25 Tres Cantos Madrid 28760",
    "addr:postcode":"28760",
    "iso:country":"ES",
    "sg:address":"Rond Valdecarrizo (de), 25",
    "sg:city":"Tres Cantos",
    "sg:orig_category":"Chapister\u00cda",
    "sg:phone":"+34 918 04 15 14",
    "sg:postcode":"28760",
    "sg:province":"Madrid",
    "wof:name":"Talleres Tres Cantos S.l.",
    "wof:placetype":"venue"
},
  "geometry": {"coordinates":[-3.6985208988,40.615032196],"type":"Point"}
}