{
  "type": "Feature",
  "properties": {
    "iso:country":"ES",
    "sg:address":"Avda Argentina, 46",
    "sg:city":"Gijon",
    "sg:orig_category":"Confecci\u00d3n (fabricaci\u00d3n, Al Por Mayor)",
    "sg:phone":"+34 985 32 27 82",
    "sg:postcode":"33213",
    "sg:province":"Asturias",
    "wof:name":"Sanjurjo Piquin Antonio",
    "wof:placetype":"venue"
},
  "geometry": {"coordinates":[-5.7014718056,43.5385475159],"type":"Point"}
}