{
  "type": "Feature",
  "properties": {
    "addr:full":"Calle de Arroyazo, 12 Don Benito Badajoz 06400",
    "addr:housenumber":"12",
    "addr:postcode":"06400",
    "addr:street":"Calle De Arroyazo",
    "iso:country":"ES",
    "sg:address":"Calle de Arroyazo, 12",
    "sg:city":"Don Benito",
    "sg:orig_category":"Alquiler De Gr\u00daas",
    "sg:phone":"+34 924 81 03 46",
    "sg:postcode":"06400",
    "sg:province":"Badajoz",
    "wof:name":"Gruas Romero S.l.",
    "wof:placetype":"venue"
},
  "geometry": {"coordinates":[-5.865685463,38.9544754028],"type":"Point"}
}