{
  "type": "Feature",
  "properties": {
    "addr:full":"Calle de Bartolome Reus, 28 Castellon Castell\u00f3n 12002",
    "addr:housenumber":"28",
    "addr:postcode":"12002",
    "addr:street":"Calle De Bartolome Reus",
    "iso:country":"ES",
    "sg:address":"Calle de Bartolome Reus, 28",
    "sg:city":"Castellon",
    "sg:orig_category":"Empresas De Pintura Y Revestimientos",
    "sg:phone":"+34 964 22 01 03",
    "sg:postcode":"12002",
    "sg:province":"Castell\u00f3n",
    "wof:name":"Llopis Peris Josefa",
    "wof:placetype":"venue"
},
  "geometry": {"coordinates":[-0.0377580002,39.9811096191],"type":"Point"}
}