{
  "type": "Feature",
  "properties": {
    "iso:country":"ES",
    "sg:address":"Carrer de Evarist Fabregas, 13",
    "sg:city":"Reus",
    "sg:orig_category":"Transporte En General",
    "sg:phone":"+34 977 75 06 08",
    "sg:postcode":"43205",
    "sg:province":"Tarragona",
    "wof:name":"Beatzone Logistic S.l.",
    "wof:placetype":"venue"
},
  "geometry": {"coordinates":[1.1027929783,41.1451187134],"type":"Point"}
}