{
  "type": "Feature",
  "properties": {
    "iso:country":"ES",
    "sg:address":"Avda Bueu, 21",
    "sg:city":"Cangas",
    "sg:orig_category":"Estancos",
    "sg:phone":"+34 986 30 08 96",
    "sg:postcode":"36940",
    "sg:province":"Pontevedra",
    "wof:name":"Corral Ferreiro Jaime",
    "wof:placetype":"venue"
},
  "geometry": {"coordinates":[-8.7867631912,42.2582893372],"type":"Point"}
}