{
  "type": "Feature",
  "properties": {
    "iso:country":"ES",
    "sg:address":"Rua Cervantes, 42",
    "sg:city":"Foz",
    "sg:orig_category":"Electricidad: Instaladores",
    "sg:phone":"+34 982 14 17 01",
    "sg:postcode":"27780",
    "sg:province":"Lugo",
    "wof:name":"Onemons S.a.",
    "wof:placetype":"venue"
},
  "geometry": {"coordinates":[-7.2613739967,43.5743751526],"type":"Point"}
}