{
  "type": "Feature",
  "properties": {
    "iso:country":"ES",
    "sg:address":"Calle de Jimios, 2",
    "sg:city":"Sevilla",
    "sg:orig_category":"Estancos",
    "sg:phone":"+34 954 22 80 32",
    "sg:postcode":"41001",
    "sg:province":"Sevilla",
    "wof:name":"Marmol Rodriguez Paloma",
    "wof:placetype":"venue"
},
  "geometry": {"coordinates":[-5.9956412315,37.3876457214],"type":"Point"}
}