{
  "type": "Feature",
  "properties": {
    "addr:full":"Psaj Zaidin, 14 Campillo Del Moro Almer\u00eda 04720",
    "addr:housenumber":"14",
    "addr:postcode":"04720",
    "addr:street":"Zaidin",
    "iso:country":"ES",
    "sg:address":"Psaj Zaidin, 14",
    "sg:city":"Campillo Del Moro",
    "sg:orig_category":"Asesor\u00cda Fiscal Y Jur\u00cddica",
    "sg:phone":"+34 950 34 00 11",
    "sg:postcode":"04720",
    "sg:province":"Almer\u00eda",
    "wof:name":"Asesoria Cuadrado S.l.",
    "wof:placetype":"venue"
},
  "geometry": {"coordinates":[-2.6005690098,36.8096733093],"type":"Point"}
}