{
  "type": "Feature",
  "properties": {
    "addr:full":"Carr Isaac Peral, 19 Port D'andratx Islas Baleares 07157",
    "addr:housenumber":"19",
    "addr:postcode":"07157",
    "addr:street":"Carr Isaac Peral",
    "iso:country":"ES",
    "sg:address":"Carr Isaac Peral, 19",
    "sg:city":"Port D'andratx",
    "sg:orig_category":"Inmobiliaria (agencias)",
    "sg:phone":"+34 971 67 47 67",
    "sg:postcode":"07157",
    "sg:province":"Islas Baleares",
    "wof:name":"Goetz  Enrique Von",
    "wof:placetype":"venue"
},
  "geometry": {"coordinates":[2.3897519112,39.54479599],"type":"Point"}
}