{
  "type": "Feature",
  "properties": {
    "addr:full":"Calle de Ramon Y Cajal, 18 Cuenca Cuenca 16004",
    "addr:housenumber":"18",
    "addr:postcode":"16004",
    "addr:street":"Calle De Ramon Y Cajal",
    "iso:country":"ES",
    "sg:address":"Calle de Ramon Y Cajal, 18",
    "sg:city":"Cuenca",
    "sg:orig_category":"Asociaciones Humanitarias, De Cooperaci\u00d3n, De Acci\u00d3n Social",
    "sg:phone":"+34 969 23 62 22",
    "sg:postcode":"16004",
    "sg:province":"Cuenca",
    "wof:name":"Organizacion Impulsora De Discapacitados O.i.d.",
    "wof:placetype":"venue"
},
  "geometry": {"coordinates":[-2.1354858875,40.0696983337],"type":"Point"}
}