{
  "type": "Feature",
  "properties": {
    "addr:full":"Ctra. Valencia, Km. 0011,2 Cadrete Zaragoza 50420",
    "addr:postcode":"50420",
    "addr:street":"Ctra. Valencia Km. 0011,2",
    "iso:country":"ES",
    "sg:address":"Ctra. Valencia, Km. 0011,2",
    "sg:city":"Cadrete",
    "sg:orig_category":"Metalurgia",
    "sg:phone":"+34 976 12 61 98",
    "sg:postcode":"50420",
    "sg:province":"Zaragoza",
    "wof:name":"L&p Springs Espa\u00d1a S.l.",
    "wof:placetype":"venue"
},
  "geometry": {"coordinates":[-0.9601830244,41.5556411743],"type":"Point"}
}