{
  "type": "Feature",
  "properties": {
    "iso:country":"ES",
    "sg:address":"Calle de Maria Encarnacion Navarro, 18",
    "sg:city":"S.gregorio",
    "sg:orig_category":"Inmobiliaria (agencias)",
    "sg:phone":"+34 928 68 39 60",
    "sg:postcode":"35200",
    "sg:province":"Las Palmas",
    "wof:name":"Izadi, A.g.s.l..u",
    "wof:placetype":"venue"
},
  "geometry": {"coordinates":[-15.4144220352,28.0029888153],"type":"Point"}
}