{
  "type": "Feature",
  "properties": {
    "iso:country":"ES",
    "sg:address":"Calle de Betania, 53",
    "sg:city":"Lomo Los Frailes",
    "sg:orig_category":"Escotaduras, Torneados",
    "sg:phone":"+34 928 67 32 41",
    "sg:postcode":"35018",
    "sg:province":"Las Palmas",
    "wof:name":"Lopez Rodriguez Juan Agustin",
    "wof:placetype":"venue"
},
  "geometry": {"coordinates":[-15.4300060272,28.1248226166],"type":"Point"}
}