{
  "type": "Feature",
  "properties": {
    "addr:full":"Calle de Mestas Las, 7 Gijon Asturias 33204",
    "addr:housenumber":"7",
    "addr:postcode":"33204",
    "addr:street":"Calle De Mestas Las",
    "iso:country":"ES",
    "sg:address":"Calle de Mestas Las, 7",
    "sg:city":"Gijon",
    "sg:orig_category":"M\u00c9dicos: Neumolog\u00cda",
    "sg:phone":"+34 985 33 14 89",
    "sg:postcode":"33204",
    "sg:province":"Asturias",
    "wof:name":"Gonzalez Panizo Alfredo",
    "wof:placetype":"venue"
},
  "geometry": {"coordinates":[-5.6410150528,43.5317573547],"type":"Point"}
}