{
  "type": "Feature",
  "properties": {
    "iso:country":"ES",
    "sg:address":"Calle de Santander, 4",
    "sg:city":"Villarcayo",
    "sg:orig_category":"Juegos Y Juguetes (al Por Menor)",
    "sg:phone":"+34 947 13 13 59",
    "sg:postcode":"09550",
    "sg:province":"Burgos",
    "wof:name":"Lopez Rojo Miguel Angel",
    "wof:placetype":"venue"
},
  "geometry": {"coordinates":[-3.5730099678,42.9387779236],"type":"Point"}
}