{
  "type": "Feature",
  "properties": {
    "addr:full":"Calle de Picayo, 12 Cenizate Albacete 02247",
    "addr:housenumber":"12",
    "addr:postcode":"02247",
    "addr:street":"Calle De Picayo",
    "iso:country":"ES",
    "sg:address":"Calle de Picayo, 12",
    "sg:city":"Cenizate",
    "sg:orig_category":"Estancos",
    "sg:phone":"+34 967 48 23 12",
    "sg:postcode":"02247",
    "sg:province":"Albacete",
    "wof:name":"Garcia Garcia Fidel",
    "wof:placetype":"venue"
},
  "geometry": {"coordinates":[-1.6626390219,39.3030700684],"type":"Point"}
}