{
  "type": "Feature",
  "properties": {
    "iso:country":"ES",
    "sg:address":"Pla\u00c7 Pilar, 6",
    "sg:city":"Igualada",
    "sg:orig_category":"Zapatos (al Por Menor)",
    "sg:phone":"+34 938 03 19 41",
    "sg:postcode":"08700",
    "sg:province":"Barcelona",
    "wof:name":"Claramunt Baliellas Ana",
    "wof:placetype":"venue"
},
  "geometry": {"coordinates":[1.6183279753,41.5790977478],"type":"Point"}
}