{
  "type": "Feature",
  "properties": {
    "addr:full":"Plaz Igrexa (da), S/n Avenida Ordo\u00e7ez Pontevedra 36750",
    "addr:housenumber":"s / n",
    "addr:postcode":"36750",
    "addr:street":"Plaz;Da;Avenida Ordoc\u0327Ez",
    "iso:country":"ES",
    "sg:address":"Plaz Igrexa (da), S/n",
    "sg:city":"Avenida Ordo\u00e7ez",
    "sg:orig_category":"Animales (al Por Menor)",
    "sg:phone":"+34 986 62 14 15",
    "sg:postcode":"36750",
    "sg:province":"Pontevedra",
    "wof:name":"Martinez Gonzalez Maria Belen",
    "wof:placetype":"venue"
},
  "geometry": {"coordinates":[-8.7706012726,41.9454116821],"type":"Point"}
}