{
  "type": "Feature",
  "properties": {
    "iso:country":"ES",
    "sg:address":"Rua Bispo Aguirre, 34",
    "sg:city":"Lugo",
    "sg:orig_category":"Asesor\u00cda Fiscal Y Jur\u00cddica",
    "sg:phone":"+34 982 25 23 01",
    "sg:postcode":"27002",
    "sg:province":"Lugo",
    "wof:name":"Lopez Ferreiro Berta",
    "wof:placetype":"venue"
},
  "geometry": {"coordinates":[-7.5564222336,43.0073204041],"type":"Point"}
}