{
  "type": "Feature",
  "properties": {
    "addr:full":"Calle de Algascar, 13 Huesca Huesca 22004",
    "addr:housenumber":"13",
    "addr:postcode":"22004",
    "addr:street":"Calle De Algascar",
    "iso:country":"ES",
    "sg:address":"Calle de Algascar, 13",
    "sg:city":"Huesca",
    "sg:orig_category":"Agentes, Concesionarios Y Sucursales De Veh\u00cdculos",
    "sg:phone":"+34 974 21 41 16",
    "sg:postcode":"22004",
    "sg:province":"Huesca",
    "wof:name":"Magia Motor S.a.",
    "wof:placetype":"venue"
},
  "geometry": {"coordinates":[-0.4149743915,42.1309585571],"type":"Point"}
}