{
  "type": "Feature",
  "properties": {
    "iso:country":"ES",
    "sg:address":"Calle de Seminario, 4",
    "sg:city":"Leganes",
    "sg:orig_category":"Doctores En Medicina",
    "sg:phone":"+34 916 94 49 91",
    "sg:postcode":"28911",
    "sg:province":"Madrid",
    "wof:name":"Arias Osuna Antonio",
    "wof:placetype":"venue"
},
  "geometry": {"coordinates":[-3.7698709965,40.3266067505],"type":"Point"}
}