{
  "type": "Feature",
  "properties": {
    "addr:full":"Ctra Rubi, 20 Mira-sol Barcelona 08173",
    "addr:housenumber":"20",
    "addr:postcode":"08173",
    "addr:street":"Ctra Rubi",
    "iso:country":"ES",
    "sg:address":"Ctra Rubi, 20",
    "sg:city":"Mira-sol",
    "sg:orig_category":"Inform\u00c1tica: Soportes De Informaci\u00d3n, Suministros & Accesorios",
    "sg:phone":"+34 935 90 80 40",
    "sg:postcode":"08173",
    "sg:province":"Barcelona",
    "wof:name":"Numeric Streaming Media S. L.",
    "wof:placetype":"venue"
},
  "geometry": {"coordinates":[2.0622999668,41.4687690735],"type":"Point"}
}