{
  "type": "Feature",
  "properties": {
    "addr:full":"Avda Guipuzcoa, 61 Berriozar Navarra 31013",
    "addr:housenumber":"61",
    "addr:postcode":"31013",
    "addr:street":"Avda Guipuzcoa",
    "iso:country":"ES",
    "sg:address":"Avda Guipuzcoa, 61",
    "sg:city":"Berriozar",
    "sg:orig_category":"Muebles, Minoristas",
    "sg:phone":"+34 948 30 17 04",
    "sg:postcode":"31013",
    "sg:province":"Navarra",
    "wof:name":"Ezkabarte 2000 S.l.",
    "wof:placetype":"venue"
},
  "geometry": {"coordinates":[-97.78224945069999,45.7040786743],"type":"Point"}
}