{
  "type": "Feature",
  "properties": {
    "iso:country":"ES",
    "sg:address":"Praza Plaza Isabel La Cat\u00f3lica, 3",
    "sg:city":"Vigo",
    "sg:orig_category":"Servidores Y Editores De Bases De Datos",
    "sg:phone":"+34 902 19 97 44",
    "sg:postcode":"36204",
    "sg:province":"Pontevedra",
    "sg:website":"www.teletronica.es",
    "wof:name":"Teletronica Comunicaciones S.l.",
    "wof:placetype":"venue"
},
  "geometry": {"coordinates":[-8.7123680115,42.231136322],"type":"Point"}
}