{
  "type": "Feature",
  "properties": {
    "addr:full":"Avda General Lopez Dominguez, S/n Marbella M\u00e1laga 29600",
    "addr:postcode":"29600",
    "addr:street":"Avda General Lopez Dominguez S / N;Ma\u0301Laga",
    "iso:country":"ES",
    "sg:address":"Avda General Lopez Dominguez, S/n",
    "sg:city":"Marbella",
    "sg:orig_category":"Art\u00cdculos De Decoraci\u00d3n",
    "sg:phone":"+34 952 92 46 12",
    "sg:postcode":"29600",
    "sg:province":"M\u00e1laga",
    "wof:name":"Garcia Diaz Ana",
    "wof:placetype":"venue"
},
  "geometry": {"coordinates":[-4.8758540154,36.5112113953],"type":"Point"}
}