{
  "type": "Feature",
  "properties": {
    "addr:full":"Calle de Europa, 1 Burgos Burgos 09001",
    "addr:housenumber":"1",
    "addr:postcode":"09001",
    "addr:street":"Calle De Europa",
    "iso:country":"ES",
    "sg:address":"Calle de Europa, 1",
    "sg:city":"Burgos",
    "sg:orig_category":"Cajas De Ahorro",
    "sg:phone":"+34 947 20 65 41",
    "sg:postcode":"09001",
    "sg:province":"Burgos",
    "wof:name":"Caja De Ahorros Del Circulo Catolico Obrero De Burgos",
    "wof:placetype":"venue"
},
  "geometry": {"coordinates":[-3.6995389462,42.3299293518],"type":"Point"}
}