{
  "type": "Feature",
  "properties": {
    "iso:country":"ES",
    "sg:address":"Principe Asturias(las Lumbreras), 53",
    "sg:city":"Monteagudo",
    "sg:orig_category":"Muebles, Minoristas",
    "sg:phone":"+34 968 85 00 86",
    "sg:postcode":"30160",
    "sg:province":"Murcia",
    "wof:name":"Rosan Mobiliario C.b.",
    "wof:placetype":"venue"
},
  "geometry": {"coordinates":[-1.0895780325,38.0278739929],"type":"Point"}
}