{
  "type": "Feature",
  "properties": {
    "addr:full":"Pase Capilla De San Bartolome, 13 Ribeira Pontevedra 36955",
    "addr:housenumber":"13",
    "addr:postcode":"36955",
    "addr:street":"San Bartolome",
    "iso:country":"ES",
    "sg:address":"Pase Capilla De San Bartolome, 13",
    "sg:city":"Ribeira",
    "sg:orig_category":"Estudios Y Construcci\u00d3n De Acuarios Y Viveros",
    "sg:phone":"+34 986 31 20 14",
    "sg:postcode":"36955",
    "sg:province":"Pontevedra",
    "wof:name":"Sequeiros Garcia Jose",
    "wof:placetype":"venue"
},
  "geometry": {"coordinates":[-8.7202234268,42.2883415222],"type":"Point"}
}