{
  "type": "Feature",
  "properties": {
    "addr:full":"Luga Loma Del Esparragal, S/n Saladavieja M\u00e1laga 29680",
    "addr:housenumber":"s",
    "addr:postcode":"29680",
    "addr:street":"Loma Del Esparragal;/ N Saladavieja Ma\u0301Laga",
    "iso:country":"ES",
    "sg:address":"Luga Loma Del Esparragal, S/n",
    "sg:city":"Saladavieja",
    "sg:orig_category":"Ense\u00d1anza, Formaci\u00d3n Profesional: Aprendizaje",
    "sg:phone":"+34 952 79 80 15",
    "sg:postcode":"29680",
    "sg:province":"M\u00e1laga",
    "wof:name":"Ayuntamiento De Estepona",
    "wof:placetype":"venue"
},
  "geometry": {"coordinates":[-5.1685113907,36.4188766479],"type":"Point"}
}