{
  "type": "Feature",
  "properties": {
    "iso:country":"ES",
    "sg:address":"Calle de Angel Guirao, 7",
    "sg:city":"San Miguel",
    "sg:orig_category":"Jefes De Obra Y Construcciones",
    "sg:phone":"+34 968 21 70 37",
    "sg:postcode":"30001",
    "sg:province":"Murcia",
    "sg:website":"www.cpv-oct.com",
    "wof:name":"Control Tecnico Y Prevencion De Riesgos S.a.",
    "wof:placetype":"venue"
},
  "geometry": {"coordinates":[-1.1310008764,37.9877166748],"type":"Point"}
}