{
  "type": "Feature",
  "properties": {
    "addr:full":"Carrer de Padilla, 248 Barcelona Barcelona 08013",
    "addr:housenumber":"248",
    "addr:postcode":"08013",
    "addr:street":"Carrer De Padilla",
    "iso:country":"ES",
    "sg:address":"Carrer de Padilla, 248",
    "sg:city":"Barcelona",
    "sg:orig_category":"Postigos, Persianas Y Celos\u00cdas",
    "sg:phone":"+34 934 50 21 52",
    "sg:postcode":"08013",
    "sg:province":"Barcelona",
    "wof:name":"Lopez Esquerdo Juan Carlos",
    "wof:placetype":"venue"
},
  "geometry": {"coordinates":[2.1770560741,41.4059906006],"type":"Point"}
}