{
  "type": "Feature",
  "properties": {
    "iso:country":"ES",
    "sg:address":"R. Frailes, S/n",
    "sg:city":"Los Morales-santa Maria",
    "sg:orig_category":"Hoteles",
    "sg:phone":"+34 952 11 40 11",
    "sg:postcode":"29400",
    "sg:province":"M\u00e1laga",
    "wof:name":"Equiarunda S.l.",
    "wof:placetype":"venue"
},
  "geometry": {"coordinates":[-5.1662788391,36.7417945862],"type":"Point"}
}