{
  "type": "Feature",
  "properties": {
    "addr:full":"Calle de Huerto, 3 Villanueva Serena Badajoz 06700",
    "addr:housenumber":"3",
    "addr:postcode":"06700",
    "addr:street":"Calle De Huerto",
    "iso:country":"ES",
    "sg:address":"Calle de Huerto, 3",
    "sg:city":"Villanueva Serena",
    "sg:orig_category":"Panader\u00cdas, Panader\u00cdas",
    "sg:phone":"+34 924 84 06 89",
    "sg:postcode":"06700",
    "sg:province":"Badajoz",
    "wof:name":"Cabezas Sanchez Micaela",
    "wof:placetype":"venue"
},
  "geometry": {"coordinates":[-5.797077179,38.9755477905],"type":"Point"}
}