{
  "type": "Feature",
  "properties": {
    "iso:country":"ES",
    "sg:address":"Avda Alfonso Xiii, 90",
    "sg:city":"Madrid",
    "sg:orig_category":"Internados & Ense\u00d1anza Privada",
    "sg:phone":"+34 914 13 52 76",
    "sg:postcode":"28016",
    "sg:province":"Madrid",
    "sg:website":"www.colegiolasnaciones.com",
    "wof:name":"Tomas Krichevsky Dolores",
    "wof:placetype":"venue"
},
  "geometry": {"coordinates":[-3.6668829918,40.4556045532],"type":"Point"}
}