{
  "type": "Feature",
  "properties": {
    "iso:country":"ES",
    "sg:address":"Avenida Del Campo Del Futbol, 10",
    "sg:city":"Campanario",
    "sg:orig_category":"Cerrajer\u00cda, Ferrallista",
    "sg:phone":"+34 924 83 10 29",
    "sg:postcode":"06460",
    "sg:province":"Badajoz",
    "wof:name":"Benitez Romero Francisco",
    "wof:placetype":"venue"
},
  "geometry": {"coordinates":[-5.6223192215,38.8609085083],"type":"Point"}
}