{
  "type": "Feature",
  "properties": {
    "iso:country":"ES",
    "sg:address":"Carrer de Boulevard D'or, 15",
    "sg:city":"Cala D'or",
    "sg:orig_category":"Peluqueros: De Se\u00d1oras",
    "sg:phone":"+34 971 65 71 09",
    "sg:postcode":"07660",
    "sg:province":"Islas Baleares",
    "wof:name":"Gil Gallego Purificacion",
    "wof:placetype":"venue"
},
  "geometry": {"coordinates":[2.9117100239,39.6136398315],"type":"Point"}
}