{
  "type": "Feature",
  "properties": {
    "addr:full":"Baris, 24 Rus La Coru\u00f1a 15109",
    "addr:housenumber":"24",
    "addr:postcode":"15109",
    "addr:street":"Baris;La Corun\u0303A",
    "iso:country":"ES",
    "sg:address":"Baris, 24",
    "sg:city":"Rus",
    "sg:orig_category":"Ferreter\u00cda (diversos)",
    "sg:phone":"+34 981 70 34 54",
    "sg:postcode":"15109",
    "sg:province":"La Coru\u00f1a",
    "wof:name":"Pombo Recarey Olegario",
    "wof:placetype":"venue"
},
  "geometry": {"coordinates":[-8.6633071899,43.2020225525],"type":"Point"}
}