{
  "type": "Feature",
  "properties": {
    "iso:country":"ES",
    "sg:address":"Carrer de Notari Nonet Escubos, 12",
    "sg:city":"Olot",
    "sg:orig_category":"Empresas De Pintura Y Revestimientos",
    "sg:phone":"+34 972 26 17 36",
    "sg:postcode":"17800",
    "sg:province":"Girona",
    "wof:name":"Puig Canal Jaime",
    "wof:placetype":"venue"
},
  "geometry": {"coordinates":[2.4824359417,42.1794471741],"type":"Point"}
}