{
  "type": "Feature",
  "properties": {
    "addr:full":"Calle de Miguel Cuervo, 4 Graus Huesca 22430",
    "addr:housenumber":"4",
    "addr:postcode":"22430",
    "addr:street":"Calle De Miguel Cuervo",
    "iso:country":"ES",
    "sg:address":"Calle de Miguel Cuervo, 4",
    "sg:city":"Graus",
    "sg:orig_category":"Promotores Constructores",
    "sg:phone":"+34 974 54 62 74",
    "sg:postcode":"22430",
    "sg:province":"Huesca",
    "wof:name":"Constructora Fuster S.l.",
    "wof:placetype":"venue"
},
  "geometry": {"coordinates":[0.3397000134,42.192024231],"type":"Point"}
}