{
  "type": "Feature",
  "properties": {
    "addr:full":"Carr Sant Sebastia, 60 Mao Islas Baleares 07701",
    "addr:housenumber":"60",
    "addr:postcode":"07701",
    "addr:street":"Carr Sant Sebastia",
    "iso:country":"ES",
    "sg:address":"Carr Sant Sebastia, 60",
    "sg:city":"Mao",
    "sg:orig_category":"Cl\u00cdnicas M\u00c9dicas",
    "sg:phone":"+34 971 36 00 33",
    "sg:postcode":"07701",
    "sg:province":"Islas Baleares",
    "wof:name":"Clinica Salus Medica",
    "wof:placetype":"venue"
},
  "geometry": {"coordinates":[4.265625,39.8903694153],"type":"Point"}
}