{
  "type": "Feature",
  "properties": {
    "addr:full":"Calle de Mendez Nu\u00d1ez, 2 Huelva Huelva 21001",
    "addr:housenumber":"2",
    "addr:postcode":"21001",
    "addr:street":"Calle De Mendez Nun\u0303Ez",
    "iso:country":"ES",
    "sg:address":"Calle de Mendez Nu\u00d1ez, 2",
    "sg:city":"Huelva",
    "sg:orig_category":"Abogados",
    "sg:phone":"+34 959 28 25 55",
    "sg:postcode":"21001",
    "sg:province":"Huelva",
    "wof:name":"Jimeno Maestre Antonio",
    "wof:placetype":"venue"
},
  "geometry": {"coordinates":[-6.9509859085,37.2584953308],"type":"Point"}
}