{
  "type": "Feature",
  "properties": {
    "iso:country":"ES",
    "sg:address":"Calle de San Pedro, 4",
    "sg:city":"Toro",
    "sg:orig_category":"Bares, Piano",
    "sg:phone":"+34 980 69 06 82",
    "sg:postcode":"49800",
    "sg:province":"Zamora",
    "wof:name":"Garrido Ortega Nicolas",
    "wof:placetype":"venue"
},
  "geometry": {"coordinates":[-5.3967089653,41.5227279663],"type":"Point"}
}