{
  "type": "Feature",
  "properties": {
    "addr:full":"Ctra Pe\u00d1as (las) (salobral (el)), 7 Salobral Albacete 02140",
    "addr:housenumber":"7",
    "addr:postcode":"02140",
    "addr:street":"Ctra Pen\u0303As Las Salobral El",
    "iso:country":"ES",
    "sg:address":"Ctra Pe\u00d1as (las) (salobral (el)), 7",
    "sg:city":"Salobral",
    "sg:orig_category":"Farmacias",
    "sg:phone":"+34 967 27 15 86",
    "sg:postcode":"02140",
    "sg:province":"Albacete",
    "wof:name":"Jimenez Torres Maria Concepcion",
    "wof:placetype":"venue"
},
  "geometry": {"coordinates":[-1.9627039433,38.8379936218],"type":"Point"}
}