{
  "type": "Feature",
  "properties": {
    "addr:full":"Carrer de Gravina, 2 Mataro Barcelona 08301",
    "addr:housenumber":"2",
    "addr:postcode":"08301",
    "addr:street":"Carrer De Gravina",
    "iso:country":"ES",
    "sg:address":"Carrer de Gravina, 2",
    "sg:city":"Mataro",
    "sg:orig_category":"Supermercados Y Hipermercados",
    "sg:phone":"+34 937 55 20 90",
    "sg:postcode":"08301",
    "sg:province":"Barcelona",
    "wof:name":"Del Rio S.l.",
    "wof:placetype":"venue"
},
  "geometry": {"coordinates":[2.4455809593,41.5355072021],"type":"Point"}
}