{
  "type": "Feature",
  "properties": {
    "addr:full":"Can Roca Poligono Industrial, S/n Esparreguera Barcelona 08292",
    "addr:postcode":"08292",
    "addr:street":"Poligono Industrial S / N",
    "iso:country":"ES",
    "sg:address":"Can Roca Poligono Industrial, S/n",
    "sg:city":"Esparreguera",
    "sg:orig_category":"Panader\u00cdas, Pasteler\u00cdas, Boller\u00cda Industriale (fabricaci\u00d3n, Al Por Mayor)",
    "sg:phone":"+34 937 77 67 95",
    "sg:postcode":"08292",
    "sg:province":"Barcelona",
    "wof:name":"Fabrica De Bolleria Y Pan S.l.",
    "wof:placetype":"venue"
},
  "geometry": {"coordinates":[1.8127340078,41.5431747437],"type":"Point"}
}