{
  "type": "Feature",
  "properties": {
    "iso:country":"ES",
    "sg:address":"Calle de Calendula (de La), 93",
    "sg:city":"Alcobendas",
    "sg:orig_category":"Urbanistas",
    "sg:phone":"+34 916 50 82 18",
    "sg:postcode":"28109",
    "sg:province":"Madrid",
    "wof:name":"Nueva Urbanizadora Residencial S.a.",
    "wof:placetype":"venue"
},
  "geometry": {"coordinates":[-3.6455962658,40.5272483826],"type":"Point"}
}