{
  "type": "Feature",
  "properties": {
    "addr:full":"Calle de Santa Elena, 14 Irun Guip\u00f9zcoa 20304",
    "addr:housenumber":"14",
    "addr:postcode":"20304",
    "addr:street":"Calle De Santa Elena;Guipu\u0300Zcoa",
    "iso:country":"ES",
    "sg:address":"Calle de Santa Elena, 14",
    "sg:city":"Irun",
    "sg:classifiers":[
        {
            "category":"Professional",
            "subcategory":"Management & Consulting",
            "type":"Services"
        }
    ],
    "sg:phone":"+34 943 63 39 37",
    "sg:postcode":"20304",
    "sg:province":"Guip\u00f9zcoa",
    "sg:tags":[
        "asesor\u00cda",
        "en",
        "marketing"
    ],
    "wof:name":"Agencia De Desarrollo Del Bidasoa-bidasoako Garapenerako Ajentzia S.",
    "wof:placetype":"venue"
},
  "geometry": {"coordinates":[-1.7855392694,43.3365974426],"type":"Point"}
}