{
  "type": "Feature",
  "properties": {
    "addr:full":"Ctra. Madrid, Km. 0024,6 Peralta Navarra 31350",
    "addr:postcode":"31350",
    "addr:street":"Ctra. Madrid Km. 0024,6",
    "iso:country":"ES",
    "sg:address":"Ctra. Madrid, Km. 0024,6",
    "sg:city":"Peralta",
    "sg:orig_category":"Distribuci\u00d3n De Petr\u00d3leo Y Derivados",
    "sg:phone":"+34 948 71 31 44",
    "sg:postcode":"31350",
    "sg:province":"Navarra",
    "wof:name":"Estacion De Servicio Atalaya S.l.",
    "wof:placetype":"venue"
},
  "geometry": {"coordinates":[-1.8050489426,42.3389167786],"type":"Point"}
}