{
  "type": "Feature",
  "properties": {
    "addr:full":"Avda El Ferial, 23 Benavente Zamora 49600",
    "addr:housenumber":"23",
    "addr:postcode":"49600",
    "addr:street":"Avda El Ferial",
    "iso:country":"ES",
    "sg:address":"Avda El Ferial, 23",
    "sg:city":"Benavente",
    "sg:orig_category":"Delegados, Agentes De Tr\u00c1nsito, Auxiliares De Transporte Internacional",
    "sg:phone":"+34 980 63 07 78",
    "sg:postcode":"49600",
    "sg:province":"Zamora",
    "wof:name":"Estebanez Vecino Mateo",
    "wof:placetype":"venue"
},
  "geometry": {"coordinates":[-5.6742949486,42.00182724],"type":"Point"}
}