{
  "type": "Feature",
  "properties": {
    "iso:country":"ES",
    "sg:address":"Calle de Hilanderos, 24",
    "sg:city":"Carmona",
    "sg:orig_category":"Empresas De Carpinter\u00cda Met\u00c1lica",
    "sg:phone":"+34 954 14 42 15",
    "sg:postcode":"41410",
    "sg:province":"Sevilla",
    "wof:name":"Ferbal S.c.",
    "wof:placetype":"venue"
},
  "geometry": {"coordinates":[-5.6497840881,37.4833641052],"type":"Point"}
}