{
  "type": "Feature",
  "properties": {
    "addr:full":"Calle de Rivas, 1 Dos Hermanas Sevilla 41700",
    "addr:housenumber":"1",
    "addr:postcode":"41700",
    "addr:street":"Calle De Rivas;Sevilla",
    "iso:country":"ES",
    "sg:address":"Calle de Rivas, 1",
    "sg:city":"Dos Hermanas",
    "sg:orig_category":"Droguer\u00cdas (al Por Menor)",
    "sg:phone":"+34 954 72 13 94",
    "sg:postcode":"41700",
    "sg:province":"Sevilla",
    "wof:name":"Electronica Rincon S.l.",
    "wof:placetype":"venue"
},
  "geometry": {"coordinates":[-5.9259119034,37.2831726074],"type":"Point"}
}