{
  "type": "Feature",
  "properties": {
    "addr:full":"Calle de Adriano, 23 Sevilla Sevilla 41001",
    "addr:housenumber":"23",
    "addr:postcode":"41001",
    "addr:street":"Calle De Adriano",
    "iso:country":"ES",
    "sg:address":"Calle de Adriano, 23",
    "sg:city":"Sevilla",
    "sg:orig_category":"Asesor\u00cda De Formaci\u00d3n Y Gesti\u00d3n De Personal",
    "sg:phone":"+34 954 56 14 75",
    "sg:postcode":"41001",
    "sg:province":"Sevilla",
    "wof:name":"Contatel Consultores S.l.",
    "wof:placetype":"venue"
},
  "geometry": {"coordinates":[-5.9980840683,37.3866348267],"type":"Point"}
}