{
  "type": "Feature",
  "properties": {
    "iso:country":"ES",
    "sg:address":"Pque Sagrado Corazon, 2",
    "sg:city":"Cedeira",
    "sg:orig_category":"Bisuter\u00cda, Joyer\u00cda, Relojer\u00cda (al Por Menor)",
    "sg:phone":"+34 981 48 04 20",
    "sg:postcode":"15350",
    "sg:province":"La Coru\u00f1a",
    "wof:name":"Dopazo Peque\u00f1o Juan Carlos",
    "wof:placetype":"venue"
},
  "geometry": {"coordinates":[-8.052989006,43.6609916687],"type":"Point"}
}