{
  "type": "Feature",
  "properties": {
    "addr:full":"Pg Maritim, 3 Pineda Mar Barcelona 08397",
    "addr:housenumber":"3",
    "addr:postcode":"08397",
    "addr:street":"Pg Maritim;Barcelona",
    "iso:country":"ES",
    "sg:address":"Pg Maritim, 3",
    "sg:city":"Pineda Mar",
    "sg:orig_category":"Heladeros",
    "sg:phone":"+34 937 67 13 32",
    "sg:postcode":"08397",
    "sg:province":"Barcelona",
    "wof:name":"Llerinos Diaz Francisco Jose",
    "wof:placetype":"venue"
},
  "geometry": {"coordinates":[2.6919600964,41.6219787598],"type":"Point"}
}