{
  "type": "Feature",
  "properties": {
    "addr:full":"Calle de Tomas Romero De Castilla, 14 Merida Badajoz 06800",
    "addr:housenumber":"14",
    "addr:postcode":"06800",
    "addr:street":"Calle De Tomas Romero De Castilla",
    "iso:country":"ES",
    "sg:address":"Calle de Tomas Romero De Castilla, 14",
    "sg:city":"Merida",
    "sg:orig_category":"Reposter\u00cdas",
    "sg:phone":"+34 924 31 19 32",
    "sg:postcode":"06800",
    "sg:province":"Badajoz",
    "wof:name":"Jose Antonio Guedejo,s.l.",
    "wof:placetype":"venue"
},
  "geometry": {"coordinates":[-6.3360443115,38.9085083008],"type":"Point"}
}