{
  "type": "Feature",
  "properties": {
    "iso:country":"ES",
    "sg:address":"Carrer de Murtal, 4",
    "sg:city":"Benidorm",
    "sg:orig_category":"Alimentaci\u00d3n General (al Por Menor)",
    "sg:phone":"+34 965 85 17 57",
    "sg:postcode":"03500",
    "sg:province":"Alicante",
    "wof:name":"Miguel Y Gonzalo S.l.",
    "wof:placetype":"venue"
},
  "geometry": {"coordinates":[-0.1574719995,38.536819458],"type":"Point"}
}