{
  "type": "Feature",
  "properties": {
    "addr:full":"Calle de Trinidad, 20 Talavera Reina Toledo 45600",
    "addr:housenumber":"20",
    "addr:postcode":"45600",
    "addr:street":"Calle De Trinidad",
    "iso:country":"ES",
    "sg:address":"Calle de Trinidad, 20",
    "sg:city":"Talavera Reina",
    "sg:orig_category":"M\u00c9dicos: Gastroenterolog\u00cda Y Hepatolog\u00cda (aparato Digestivo)",
    "sg:phone":"+34 925 80 92 03",
    "sg:postcode":"45600",
    "sg:province":"Toledo",
    "wof:name":"Guerrero Vega Enrique",
    "wof:placetype":"venue"
},
  "geometry": {"coordinates":[-4.8260860443,39.9639282227],"type":"Point"}
}