{
  "type": "Feature",
  "properties": {
    "iso:country":"ES",
    "sg:address":"Calle de Esperanza (la), 5",
    "sg:city":"Cuenca",
    "sg:orig_category":"Iglesia Cat\u00d3lica",
    "sg:phone":"+34 969 23 04 62",
    "sg:postcode":"16001",
    "sg:province":"Cuenca",
    "wof:name":"Parroquia De El Salvador",
    "wof:placetype":"venue"
},
  "geometry": {"coordinates":[-2.1337490082,40.074886322],"type":"Point"}
}