{
  "type": "Feature",
  "properties": {
    "addr:full":"Calle de San Joaquin, S/n S. Fernando C\u00e1diz 11100",
    "addr:postcode":"11100",
    "addr:street":"Calle De San Joaquin S / N S. Fernando Ca\u0301Diz",
    "iso:country":"ES",
    "sg:address":"Calle de San Joaquin, S/n",
    "sg:city":"S. Fernando",
    "sg:orig_category":"Papeler\u00cdas, Librer\u00cdas",
    "sg:phone":"+34 956 88 34 62",
    "sg:postcode":"11100",
    "sg:province":"C\u00e1diz",
    "wof:name":"Matabuena Bernal Miguel Angel",
    "wof:placetype":"venue"
},
  "geometry": {"coordinates":[-6.2029590607,36.4590682983],"type":"Point"}
}