{
  "type": "Feature",
  "properties": {
    "iso:country":"ES",
    "sg:address":"J. Ramon Jimenez, S/n",
    "sg:city":"Parque Empresarial",
    "sg:orig_category":"Ropa Para Ni\u00d1os (al Por Menor)",
    "sg:phone":"+34 916 40 14 25",
    "sg:postcode":"28232",
    "sg:province":"Madrid",
    "wof:name":"Old Ridel S.l.",
    "wof:placetype":"venue"
},
  "geometry": {"coordinates":[-3.899435997,40.5183067322],"type":"Point"}
}