{
  "type": "Feature",
  "properties": {
    "addr:full":"Calle de Trabajo, 29 Sevilla Sevilla 41010",
    "addr:housenumber":"29",
    "addr:postcode":"41010",
    "addr:street":"Calle De Trabajo",
    "iso:country":"ES",
    "sg:address":"Calle de Trabajo, 29",
    "sg:city":"Sevilla",
    "sg:classifiers":[
        {
            "category":"Personal",
            "subcategory":"Barber",
            "type":"Services"
        }
    ],
    "sg:phone":"+34 954 27 65 80",
    "sg:postcode":"41010",
    "sg:province":"Sevilla",
    "sg:tags":[
        "caballeros",
        "de",
        "peluqueros"
    ],
    "wof:name":"Boza Gonzalez Juan Jose",
    "wof:placetype":"venue"
},
  "geometry": {"coordinates":[-6.0050029755,37.3789405823],"type":"Point"}
}