{
  "type": "Feature",
  "properties": {
    "addr:full":"Forn, 39 Tremp Lleida 25620",
    "addr:postcode":"25620",
    "iso:country":"ES",
    "sg:address":"Forn, 39",
    "sg:city":"Tremp",
    "sg:orig_category":"Centros Comerciales Y Grandes Tiendas",
    "sg:phone":"+34 973 65 19 39",
    "sg:postcode":"25620",
    "sg:province":"Lleida",
    "wof:name":"Casaucau Alonso Ana",
    "wof:placetype":"venue"
},
  "geometry": {"coordinates":[0.8948199749,42.1677017212],"type":"Point"}
}