{
  "type": "Feature",
  "properties": {
    "addr:full":"Carr Riquer, 13 Lleida Lleida 25007",
    "addr:housenumber":"13",
    "addr:postcode":"25007",
    "addr:street":"Carr Riquer",
    "iso:country":"ES",
    "sg:address":"Carr Riquer, 13",
    "sg:city":"Lleida",
    "sg:orig_category":"Promotores Constructores",
    "sg:phone":"+34 973 22 27 58",
    "sg:postcode":"25007",
    "sg:province":"Lleida",
    "wof:name":"Tiresa S.l.",
    "wof:placetype":"venue"
},
  "geometry": {"coordinates":[0.6302899718,41.6161499023],"type":"Point"}
}