{
  "type": "Feature",
  "properties": {
    "iso:country":"ES",
    "sg:address":"Carr Ns La Salut, 42",
    "sg:city":"Igualada",
    "sg:orig_category":"Bisuter\u00cda, Joyer\u00cda, Relojer\u00cda (al Por Menor)",
    "sg:phone":"+34 938 03 18 84",
    "sg:postcode":"08700",
    "sg:province":"Barcelona",
    "wof:name":"Morros Fillat Jaime",
    "wof:placetype":"venue"
},
  "geometry": {"coordinates":[1.6170699596,41.5795402527],"type":"Point"}
}