{
  "type": "Feature",
  "properties": {
    "iso:country":"ES",
    "sg:address":"Via Dos Castillas (de Las), 23",
    "sg:city":"Pozuelo De Alarcon",
    "sg:orig_category":"Hielo Artificial (fabricaci\u00d3n, Distribuci\u00d3n)",
    "sg:phone":"+34 913 52 91 03",
    "sg:postcode":"28224",
    "sg:province":"Madrid",
    "wof:name":"Santamaria Carreras Gustavo",
    "wof:placetype":"venue"
},
  "geometry": {"coordinates":[-3.7936611176,40.436630249],"type":"Point"}
}