{
  "type": "Feature",
  "properties": {
    "iso:country":"ES",
    "sg:address":"Avda Fernandez Ladreda, 35",
    "sg:city":"Pontevedra",
    "sg:orig_category":"Material Y Herramientas Agr\u00cdcolas",
    "sg:phone":"+34 986 84 11 41",
    "sg:postcode":"36003",
    "sg:province":"Pontevedra",
    "wof:name":"Novo Rumbo S.l.",
    "wof:placetype":"venue"
},
  "geometry": {"coordinates":[-8.643406868,42.4250907898],"type":"Point"}
}