{
  "type": "Feature",
  "properties": {
    "iso:country":"ES",
    "sg:address":"Calle de Valdes, 1",
    "sg:city":"Marbella",
    "sg:orig_category":"Electrodom\u00c9sticos (al Por Menor)",
    "sg:phone":"+34 952 77 85 46",
    "sg:postcode":"29600",
    "sg:province":"M\u00e1laga",
    "wof:name":"Navas Perez Jose",
    "wof:placetype":"venue"
},
  "geometry": {"coordinates":[-4.8849239349,36.5099830627],"type":"Point"}
}