{
  "type": "Feature",
  "properties": {
    "addr:full":"Calle de Madre Vedruna, 3 Zaragoza Zaragoza 50008",
    "addr:housenumber":"3",
    "addr:postcode":"50008",
    "addr:street":"Calle De Madre Vedruna",
    "iso:country":"ES",
    "sg:address":"Calle de Madre Vedruna, 3",
    "sg:city":"Zaragoza",
    "sg:orig_category":"M\u00c9dicos: Medicina General Orientada A La Acupuntura",
    "sg:phone":"+34 976 23 33 32",
    "sg:postcode":"50008",
    "sg:province":"Zaragoza",
    "wof:name":"Suescun Laborda Jesus",
    "wof:placetype":"venue"
},
  "geometry": {"coordinates":[-0.8826107979,41.646812439],"type":"Point"}
}