{
  "type": "Feature",
  "properties": {
    "addr:full":"Calle de Ventilla, 11 Haro La Rioja 26200",
    "addr:housenumber":"11",
    "addr:postcode":"26200",
    "addr:street":"Calle De Ventilla",
    "iso:country":"ES",
    "sg:address":"Calle de Ventilla, 11",
    "sg:city":"Haro",
    "sg:orig_category":"Marroquiner\u00cda (confecci\u00d3n)",
    "sg:phone":"+34 941 31 00 42",
    "sg:postcode":"26200",
    "sg:province":"La Rioja",
    "wof:name":"Arnaez Garcia Maria Luisa",
    "wof:placetype":"venue"
},
  "geometry": {"coordinates":[-2.8480908871,42.5755882263],"type":"Point"}
}