{
  "type": "Feature",
  "properties": {
    "addr:full":"Rbla Principal, 9 Vilanova I La Geltru Barcelona 08800",
    "addr:housenumber":"9",
    "addr:postcode":"08800",
    "addr:street":"Rbla Principal",
    "iso:country":"ES",
    "sg:address":"Rbla Principal, 9",
    "sg:city":"Vilanova I La Geltru",
    "sg:orig_category":"Molduras, Junquillos, Listones Y Molduras Perforadas",
    "sg:phone":"+34 938 93 10 65",
    "sg:postcode":"08800",
    "sg:province":"Barcelona",
    "wof:name":"Rosell Casanova Josep",
    "wof:placetype":"venue"
},
  "geometry": {"coordinates":[1.7242360115,41.2254219055],"type":"Point"}
}