{
  "type": "Feature",
  "properties": {
    "iso:country":"ES",
    "sg:address":"Calle de Segovia, 6",
    "sg:city":"Cantalejo",
    "sg:orig_category":"Molduras, Junquillos, Listones Y Molduras Perforadas",
    "sg:phone":"+34 921 52 02 84",
    "sg:postcode":"40320",
    "sg:province":"Segovia",
    "wof:name":"Martin Martin Demetrio",
    "wof:placetype":"venue"
},
  "geometry": {"coordinates":[-3.9288899899,41.2549743652],"type":"Point"}
}