{
  "type": "Feature",
  "properties": {
    "addr:full":"Ca Zaragoza, Km. 0006,0 Logro\u00f1o La Rioja 26006",
    "addr:postcode":"26006",
    "addr:street":"Ca Zaragoza Km. 0006,0 Logron\u0303O;Rioja",
    "iso:country":"ES",
    "sg:address":"Ca Zaragoza, Km. 0006,0",
    "sg:city":"Logro\u00f1o",
    "sg:orig_category":"Productores Recolectores, Venta Directa De Vinos",
    "sg:phone":"+34 941 26 12 43",
    "sg:postcode":"26006",
    "sg:province":"La Rioja",
    "wof:name":"Bodegas Del Marques De Vargas S.l.",
    "wof:placetype":"venue"
},
  "geometry": {"coordinates":[-2.4216170311,42.4610900879],"type":"Point"}
}