{
  "type": "Feature",
  "properties": {
    "addr:full":"Carrer de Bobiles, 90 Hospitalet Llobregat Barcelona 08905",
    "addr:housenumber":"90",
    "addr:postcode":"08905",
    "addr:street":"Carrer De Bobiles",
    "iso:country":"ES",
    "sg:address":"Carrer de Bobiles, 90",
    "sg:city":"Hospitalet Llobregat",
    "sg:orig_category":"Peluquer\u00cdas, Peluquer\u00cda Mixta",
    "sg:phone":"+34 934 48 25 10",
    "sg:postcode":"08905",
    "sg:province":"Barcelona",
    "wof:name":"Arnaiz Pereiras S.c.p",
    "wof:placetype":"venue"
},
  "geometry": {"coordinates":[2.1101942062,41.3723258972],"type":"Point"}
}