{
  "type": "Feature",
  "properties": {
    "addr:full":"Calle de Capua, 21 Gijon Asturias 33202",
    "addr:housenumber":"21",
    "addr:postcode":"33202",
    "addr:street":"Calle De Capua",
    "iso:country":"ES",
    "sg:address":"Calle de Capua, 21",
    "sg:city":"Gijon",
    "sg:orig_category":"Ropa Para Se\u00d1oras (al Por Menor)",
    "sg:phone":"+34 985 34 94 48",
    "sg:postcode":"33202",
    "sg:province":"Asturias",
    "wof:name":"Visnu Fassion S.l.",
    "wof:placetype":"venue"
},
  "geometry": {"coordinates":[-5.6582250595,43.5403327942],"type":"Point"}
}