{
  "type": "Feature",
  "properties": {
    "iso:country":"ES",
    "sg:address":"Avda Federico Garcia Lorca, 3",
    "sg:city":"Salobre\u00f1a",
    "sg:orig_category":"Ense\u00d1anza: Idiomas",
    "sg:phone":"+34 958 61 26 87",
    "sg:postcode":"18680",
    "sg:province":"Granada",
    "sg:website":"www.centrosanchopanza.com",
    "wof:name":"Vazquez Hernandez Gloria",
    "wof:placetype":"venue"
},
  "geometry": {"coordinates":[-3.5834589005,36.7434501648],"type":"Point"}
}