{
  "type": "Feature",
  "properties": {
    "addr:full":"Calle de Gloria, 20 San Juan Murcia 30003",
    "addr:housenumber":"20",
    "addr:postcode":"30003",
    "addr:street":"Calle De Gloria",
    "iso:country":"ES",
    "sg:address":"Calle de Gloria, 20",
    "sg:city":"San Juan",
    "sg:orig_category":"Motocicletas (agentes, Concesionarios)",
    "sg:phone":"+34 968 25 56 10",
    "sg:postcode":"30003",
    "sg:province":"Murcia",
    "wof:name":"Martinez Dominguez Juan Jose",
    "wof:placetype":"venue"
},
  "geometry": {"coordinates":[-1.1219220161,37.9839096069],"type":"Point"}
}