{
  "type": "Feature",
  "properties": {
    "addr:full":"Calle de Atalde, S/n Bermeo Vizcaya 48370",
    "addr:housenumber":"s / n",
    "addr:postcode":"48370",
    "addr:street":"Calle De Atalde",
    "iso:country":"ES",
    "sg:address":"Calle de Atalde, S/n",
    "sg:city":"Bermeo",
    "sg:orig_category":"Muebles, Minoristas",
    "sg:phone":"+34 946 18 68 07",
    "sg:postcode":"48370",
    "sg:province":"Vizcaya",
    "wof:name":"Bilbao Goiricelaya Juan Tomas",
    "wof:placetype":"venue"
},
  "geometry": {"coordinates":[-2.7276730537,43.4213943481],"type":"Point"}
}