{
  "type": "Feature",
  "properties": {
    "iso:country":"ES",
    "sg:address":"Calle de Maximo Garcia Garrido, 2",
    "sg:city":"Santurtzi",
    "sg:orig_category":"Peluquer\u00cdas, Peluquer\u00cda Mixta",
    "sg:phone":"+34 944 83 93 72",
    "sg:postcode":"48980",
    "sg:province":"Vizcaya",
    "wof:name":"Peluqueria Alberto",
    "wof:placetype":"venue"
},
  "geometry": {"coordinates":[-3.0326581001,43.3275604248],"type":"Point"}
}