{
  "type": "Feature",
  "properties": {
    "iso:country":"ES",
    "sg:address":"Calle de Puentezuelas, 16",
    "sg:city":"Granada",
    "sg:orig_category":"Fabricaci\u00d3n, Venta, Instalaci\u00d3n De R\u00d3tulos, De R\u00d3tulos Luminosos",
    "sg:phone":"+34 958 26 58 13",
    "sg:postcode":"18002",
    "sg:province":"Granada",
    "wof:name":"Perez Garcia Carlos",
    "wof:placetype":"venue"
},
  "geometry": {"coordinates":[-3.6013360023,37.1734962463],"type":"Point"}
}