{
  "type": "Feature",
  "properties": {
    "iso:country":"ES",
    "sg:address":"Cuarteres, 5",
    "sg:city":"Sta. Coloma Queralt",
    "sg:orig_category":"Peluqueros: De Se\u00d1oras",
    "sg:phone":"+34 977 88 04 15",
    "sg:postcode":"43420",
    "sg:province":"Tarragona",
    "wof:name":"Dalmau Orga Josefa",
    "wof:placetype":"venue"
},
  "geometry": {"coordinates":[1.3842799664,41.5326690674],"type":"Point"}
}