{
  "type": "Feature",
  "properties": {
    "iso:country":"ES",
    "sg:address":"C/ General Balanzat, Del, 19",
    "sg:city":"S. Antoni Portmany",
    "sg:orig_category":"Importaci\u00d3n",
    "sg:phone":"+34 971 34 50 99",
    "sg:postcode":"07820",
    "sg:province":"Islas Baleares",
    "wof:name":"Siri Manila S.l.",
    "wof:placetype":"venue"
},
  "geometry": {"coordinates":[1.5188339949,39.1094055176],"type":"Point"}
}