{
  "type": "Feature",
  "properties": {
    "addr:full":"Carrer de Santa Eulalia, 240 Hospitalet Llobregat Barcelona 08902",
    "addr:housenumber":"240",
    "addr:postcode":"08902",
    "addr:street":"Carrer De Santa Eulalia",
    "iso:country":"ES",
    "sg:address":"Carrer de Santa Eulalia, 240",
    "sg:city":"Hospitalet Llobregat",
    "sg:orig_category":"Perfumer\u00cda Y Cosm\u00c9tica (fabricaci\u00d3n, Al Por Mayor)",
    "sg:phone":"+34 932 96 98 23",
    "sg:postcode":"08902",
    "sg:province":"Barcelona",
    "wof:name":"Natural Hairsystem Productos Y Tratamientos Capilares S.l.",
    "wof:placetype":"venue"
},
  "geometry": {"coordinates":[2.1180920601,41.365486145],"type":"Point"}
}