{
  "type": "Feature",
  "properties": {
    "iso:country":"ES",
    "sg:address":"Calle de Galena, 32",
    "sg:city":"Valladolid",
    "sg:orig_category":"Maquinaria Para Industrias Diversas",
    "sg:phone":"+34 983 39 84 43",
    "sg:postcode":"47012",
    "sg:province":"Valladolid",
    "wof:name":"Duero Manutenciones S.l.",
    "wof:placetype":"venue"
},
  "geometry": {"coordinates":[-4.7077832222,41.6186523438],"type":"Point"}
}