{
  "type": "Feature",
  "properties": {
    "addr:full":"Avenida De La Telefonica, 18 Benalmadena-costa M\u00e1laga 29630",
    "addr:housenumber":"18",
    "addr:postcode":"29630",
    "addr:street":"Avenida De La Telefonica;Ma\u0301Laga",
    "iso:country":"ES",
    "sg:address":"Avenida De La Telefonica, 18",
    "sg:city":"Benalmadena-costa",
    "sg:orig_category":"Regalos, Souvenires (fabricaci\u00d3n, Al Por Mayor)",
    "sg:phone":"+34 952 44 71 13",
    "sg:postcode":"29630",
    "sg:province":"M\u00e1laga",
    "wof:name":"Sanchez Fontalba Antonio",
    "wof:placetype":"venue"
},
  "geometry": {"coordinates":[-4.5232191086,36.5955505371],"type":"Point"}
}