{
  "type": "Feature",
  "properties": {
    "iso:country":"ES",
    "sg:address":"Avda Bruselas (de), 38",
    "sg:city":"Alcobendas",
    "sg:orig_category":"Empresarios",
    "sg:phone":"+34 914 90 31 81",
    "sg:postcode":"28108",
    "sg:province":"Madrid",
    "sg:website":"www.fundacionfitsa.org",
    "wof:name":"Fitsa (fundacion Instituto Tecnologico Para La Seguridad Del Automovil",
    "wof:placetype":"venue"
},
  "geometry": {"coordinates":[-3.6425430775,40.5304412842],"type":"Point"}
}