{
  "type": "Feature",
  "properties": {
    "addr:full":"Calle de Cuestablanca (de), 30 Alcobendas Madrid 28108",
    "addr:housenumber":"30",
    "addr:postcode":"28108",
    "addr:street":"Calle De Cuestablanca De",
    "iso:country":"ES",
    "sg:address":"Calle de Cuestablanca (de), 30",
    "sg:city":"Alcobendas",
    "sg:orig_category":"Alumbrados",
    "sg:phone":"+34 917 35 55 32",
    "sg:postcode":"28108",
    "sg:province":"Madrid",
    "sg:website":"www.dentrosol.com",
    "wof:name":"Dentrosol S.l.",
    "wof:placetype":"venue"
},
  "geometry": {"coordinates":[-3.6537868977,40.5197525024],"type":"Point"}
}