{
  "type": "Feature",
  "properties": {
    "iso:country":"ES",
    "sg:address":"Carrer de Casp, 151",
    "sg:city":"Barcelona",
    "sg:orig_category":"Psicoterapeutas",
    "sg:phone":"+34 932 32 01 15",
    "sg:postcode":"08013",
    "sg:province":"Barcelona",
    "wof:name":"Lleonart Camps Marta",
    "wof:placetype":"venue"
},
  "geometry": {"coordinates":[2.1824889183,41.3983268738],"type":"Point"}
}