{
  "type": "Feature",
  "properties": {
    "iso:country":"ES",
    "sg:address":"Calle de Rio Henares (del), 19",
    "sg:city":"Humanes De Madrid",
    "sg:orig_category":"Fabricaci\u00d3n De Bibliotecas Y Estanter\u00cdas",
    "sg:phone":"+34 916 04 83 21",
    "sg:postcode":"28970",
    "sg:province":"Madrid",
    "wof:name":"Inversiones Gestiones Y Servicios Terracota S.l.",
    "wof:placetype":"venue"
},
  "geometry": {"coordinates":[-3.8143210411,40.2640533447],"type":"Point"}
}