{
  "type": "Feature",
  "properties": {
    "iso:country":"ES",
    "sg:address":"Calle de Nogal, 104",
    "sg:city":"Puebla Alfinden",
    "sg:orig_category":"Material Hidr\u00c1ulico",
    "sg:phone":"+34 976 10 73 62",
    "sg:postcode":"50171",
    "sg:province":"Zaragoza",
    "wof:name":"Hidraulicas Ramos S.l.",
    "wof:placetype":"venue"
},
  "geometry": {"coordinates":[-0.7647240162,41.6391983032],"type":"Point"}
}