{
  "type": "Feature",
  "properties": {
    "iso:country":"ES",
    "sg:address":"Calle de General Casta\u00d1os, 83",
    "sg:city":"Portugalete",
    "sg:orig_category":"Alimentaci\u00d3n General (al Por Menor)",
    "sg:phone":"+34 944 93 78 05",
    "sg:postcode":"48920",
    "sg:province":"Vizcaya",
    "wof:name":"Vazquez Leiro Oscar",
    "wof:placetype":"venue"
},
  "geometry": {"coordinates":[-3.0266990662,43.3232498169],"type":"Point"}
}