{
  "type": "Feature",
  "properties": {
    "addr:full":"Carrer de Barcelona, 100 Amposta Tarragona 43870",
    "addr:housenumber":"100",
    "addr:postcode":"43870",
    "addr:street":"Carrer De Barcelona",
    "iso:country":"ES",
    "sg:address":"Carrer de Barcelona, 100",
    "sg:city":"Amposta",
    "sg:orig_category":"Doctores En Medicina",
    "sg:phone":"+34 977 70 34 44",
    "sg:postcode":"43870",
    "sg:province":"Tarragona",
    "wof:name":"Moreno Ari\u00f1o Maria Concepcion",
    "wof:placetype":"venue"
},
  "geometry": {"coordinates":[0.5806019902,40.7045822144],"type":"Point"}
}