{
  "type": "Feature",
  "properties": {
    "addr:full":"Praz Santo Domingo, S/n Lugo Lugo 27001",
    "addr:housenumber":"s / n",
    "addr:postcode":"27001",
    "addr:street":"Praz Santo Domingo",
    "iso:country":"ES",
    "sg:address":"Praz Santo Domingo, S/n",
    "sg:city":"Lugo",
    "sg:orig_category":"Poller\u00cda Y Caza (al Por Menor)",
    "sg:phone":"+34 982 22 07 60",
    "sg:postcode":"27001",
    "sg:province":"Lugo",
    "wof:name":"Casti\u00f1eira Modia Hermitas",
    "wof:placetype":"venue"
},
  "geometry": {"coordinates":[-7.55645895,43.0119400024],"type":"Point"}
}