{
  "type": "Feature",
  "properties": {
    "iso:country":"ES",
    "sg:address":"Calle de Manuel Alvarez Marina, 3",
    "sg:city":"Langreo",
    "sg:orig_category":"Caf\u00c9s, Bares, Cervecer\u00cdas",
    "sg:phone":"+34 985 67 43 42",
    "sg:postcode":"33900",
    "sg:province":"Asturias",
    "wof:name":"Alvarez Navarro Leticia",
    "wof:placetype":"venue"
},
  "geometry": {"coordinates":[-5.6702003479,43.2881278992],"type":"Point"}
}