{
  "type": "Feature",
  "properties": {
    "iso:country":"ES",
    "sg:address":"Calle de Santa Teresita, 29",
    "sg:city":"Zaragoza",
    "sg:orig_category":"Peluquer\u00cdas, Peluquer\u00cda Mixta",
    "sg:phone":"+34 976 32 91 97",
    "sg:postcode":"50017",
    "sg:province":"Zaragoza",
    "sg:website":"www.rizos.es",
    "wof:name":"Haynes Perez Maria Pilar",
    "wof:placetype":"venue"
},
  "geometry": {"coordinates":[-0.9113910198,41.650478363],"type":"Point"}
}