{
  "type": "Feature",
  "properties": {
    "addr:full":"Carrer de Girona, 146 Terrassa Barcelona 08226",
    "addr:housenumber":"146",
    "addr:postcode":"08226",
    "addr:street":"Carrer De Girona",
    "iso:country":"ES",
    "sg:address":"Carrer de Girona, 146",
    "sg:city":"Terrassa",
    "sg:orig_category":"Sociedades, Compa\u00d1\u00cdas Aseguradoras",
    "sg:phone":"+34 937 85 26 50",
    "sg:postcode":"08226",
    "sg:province":"Barcelona",
    "sg:website":"www.pensamiento.com",
    "wof:name":"Lopez Perez Maria Carmen",
    "wof:placetype":"venue"
},
  "geometry": {"coordinates":[2.0233519077,41.5736083984],"type":"Point"}
}