{
  "type": "Feature",
  "properties": {
    "addr:full":"Calle de Mayor, 40 Tudela Duero Valladolid 47320",
    "addr:housenumber":"40;duero",
    "addr:postcode":"47320",
    "addr:street":"Calle De Mayor",
    "iso:country":"ES",
    "sg:address":"Calle de Mayor, 40",
    "sg:city":"Tudela Duero",
    "sg:orig_category":"Asesor\u00cda Fiscal Y Jur\u00cddica",
    "sg:phone":"+34 983 52 06 69",
    "sg:postcode":"47320",
    "sg:province":"Valladolid",
    "wof:name":"Torinos Gutierrez Maria Jesus",
    "wof:placetype":"venue"
},
  "geometry": {"coordinates":[-4.5808138847,41.5862884521],"type":"Point"}
}