{
  "type": "Feature",
  "properties": {
    "addr:full":"O Bri\u00f1o, 1 Borneiro A Coru\u00f1a 15119",
    "addr:housenumber":"1",
    "addr:postcode":"15119",
    "addr:street":"Brin\u0303O;Corun\u0303A",
    "iso:country":"ES",
    "sg:address":"O Bri\u00f1o, 1",
    "sg:city":"Borneiro",
    "sg:orig_category":"Material Y Herramientas Agr\u00cdcolas",
    "sg:phone":"+34 981 71 82 70",
    "sg:postcode":"15119",
    "sg:province":"A Coru\u00f1a",
    "wof:name":"Talleres J.lema S.l.",
    "wof:placetype":"venue"
},
  "geometry": {"coordinates":[-8.9580984116,43.2077713013],"type":"Point"}
}