{
  "type": "Feature",
  "properties": {
    "iso:country":"ES",
    "sg:address":"Calle de Hermanos Machado, 14",
    "sg:city":"Vera",
    "sg:orig_category":"Inform\u00c1tica, Ofim\u00c1tica (estudios, Asesor\u00cda, Ingenier\u00cda, Formaci\u00d3n)",
    "sg:phone":"+34 950 39 21 53",
    "sg:postcode":"04620",
    "sg:province":"Almer\u00eda",
    "wof:name":"Martinez Fernandez Miguel Francisco",
    "wof:placetype":"venue"
},
  "geometry": {"coordinates":[-1.8608709574,37.2479667664],"type":"Point"}
}