{
  "type": "Feature",
  "properties": {
    "iso:country":"ES",
    "sg:address":"Calle de Castilla La Nueva, 3",
    "sg:city":"Puerto",
    "sg:orig_category":"Arquitectos",
    "sg:phone":"+34 962 67 35 82",
    "sg:postcode":"46520",
    "sg:province":"Valencia",
    "wof:name":"Juan Samper Fernando",
    "wof:placetype":"venue"
},
  "geometry": {"coordinates":[-0.2194292992,39.6625785828],"type":"Point"}
}