{
  "type": "Feature",
  "properties": {
    "iso:country":"ES",
    "sg:address":"Calle de Pinar Viejo, 16",
    "sg:city":"Coca",
    "sg:orig_category":"Agentes Generales De Seguros",
    "sg:phone":"+34 921 58 62 59",
    "sg:postcode":"40480",
    "sg:province":"Segovia",
    "wof:name":"Gomez Acosta Virginia",
    "wof:placetype":"venue"
},
  "geometry": {"coordinates":[-4.5200519562,41.2163391113],"type":"Point"}
}