{
  "type": "Feature",
  "properties": {
    "addr:full":"Avda Daroca, 58 Madrid Madrid 28017",
    "addr:housenumber":"58",
    "addr:postcode":"madrid;28017",
    "addr:street":"Avda Daroca",
    "iso:country":"ES",
    "sg:address":"Avda Daroca, 58",
    "sg:city":"Madrid",
    "sg:orig_category":"Inform\u00c1tica (estudios, Servicios, Asesor\u00cda, Formaci\u00d3n)",
    "sg:phone":"+34 913 26 00 60",
    "sg:postcode":"28017",
    "sg:province":"Madrid",
    "wof:name":"Cedin S. A.",
    "wof:placetype":"venue"
},
  "geometry": {"coordinates":[-3.6535871029,40.429397583],"type":"Point"}
}