{
  "type": "Feature",
  "properties": {
    "addr:full":"Pase Prado De La Magdalena, 4 Valladolid Valladolid 47005",
    "addr:housenumber":"4",
    "addr:postcode":"47005",
    "addr:street":"La Magdalena",
    "iso:country":"ES",
    "sg:address":"Pase Prado De La Magdalena, 4",
    "sg:city":"Valladolid",
    "sg:orig_category":"Molduras, Junquillos, Listones Y Molduras Perforadas",
    "sg:phone":"+34 983 20 88 31",
    "sg:postcode":"47005",
    "sg:province":"Valladolid",
    "wof:name":"Tu Y Yo C.b.",
    "wof:placetype":"venue"
},
  "geometry": {"coordinates":[-4.7156720161,41.6548194885],"type":"Point"}
}