{
  "type": "Feature",
  "properties": {
    "iso:country":"ES",
    "sg:address":"Carrer de Angel Guimera, 33",
    "sg:city":"Manresa",
    "sg:orig_category":"Talleres: Ropa A Medida",
    "sg:phone":"+34 938 72 03 00",
    "sg:postcode":"08241",
    "sg:province":"Barcelona",
    "wof:name":"Se\u00d1or 1961 S.l.",
    "wof:placetype":"venue"
},
  "geometry": {"coordinates":[1.8245509863,41.7271156311],"type":"Point"}
}