{
  "type": "Feature",
  "properties": {
    "iso:country":"ES",
    "sg:address":"Plaz Libertad (de La), 3",
    "sg:city":"Torre-pacheco",
    "sg:orig_category":"Inmobiliaria (agencias)",
    "sg:phone":"+34 968 57 88 04",
    "sg:postcode":"30700",
    "sg:province":"Murcia",
    "sg:website":"www.inmosegur-internacional.com",
    "wof:name":"Inmosegur Torre Pacheco S.l.",
    "wof:placetype":"venue"
},
  "geometry": {"coordinates":[-0.9538533092,37.7446899414],"type":"Point"}
}