{
  "type": "Feature",
  "properties": {
    "iso:country":"ES",
    "sg:address":"Calle de Capitan Haya, 56",
    "sg:city":"Madrid",
    "sg:orig_category":"Asesor\u00cda Sobre Comunicaci\u00d3n De Empresas",
    "sg:phone":"+34 915 70 41 38",
    "sg:postcode":"28020",
    "sg:province":"Madrid",
    "wof:name":"Carvajal Y Asociados Auditoria Y Consulting S.l.",
    "wof:placetype":"venue"
},
  "geometry": {"coordinates":[-3.6916723251,40.4626655579],"type":"Point"}
}