{
  "type": "Feature",
  "properties": {
    "iso:country":"ES",
    "sg:address":"La Soledad, S/n",
    "sg:city":"Checa",
    "sg:orig_category":"Empresas De Carpinter\u00cda De Madera",
    "sg:phone":"+34 949 83 61 67",
    "sg:postcode":"19310",
    "sg:province":"Guadalajara",
    "wof:name":"Hermanos Mansilla Perez Carpinteria S.l.",
    "wof:placetype":"venue"
},
  "geometry": {"coordinates":[-1.790004015,40.5864562988],"type":"Point"}
}