{
  "type": "Feature",
  "properties": {
    "addr:full":"Calle de Arjona, 24 Sevilla Sevilla 41001",
    "addr:housenumber":"24",
    "addr:postcode":"41001",
    "addr:street":"Calle De Arjona",
    "iso:country":"ES",
    "sg:address":"Calle de Arjona, 24",
    "sg:city":"Sevilla",
    "sg:orig_category":"Pe\u00d1as Y Asociaciones Varias",
    "sg:phone":"+34 954 29 30 48",
    "sg:postcode":"41001",
    "sg:province":"Sevilla",
    "sg:website":"www.foam.es",
    "wof:name":"Federacion De Organizaciones Andaluzas De Mayores",
    "wof:placetype":"venue"
},
  "geometry": {"coordinates":[-6.0021510124,37.388092041],"type":"Point"}
}