{
  "type": "Feature",
  "properties": {
    "iso:country":"ES",
    "sg:address":"Calle de Ramirez Figueras, 9",
    "sg:city":"Bu\u00f1uel",
    "sg:orig_category":"Alimentaci\u00d3n General (al Por Menor)",
    "sg:phone":"+34 948 83 31 08",
    "sg:postcode":"31540",
    "sg:province":"Navarra",
    "wof:name":"Osta Bordonaba Jose Luis",
    "wof:placetype":"venue"
},
  "geometry": {"coordinates":[-1.4416919947,41.9800262451],"type":"Point"}
}