{
  "type": "Feature",
  "properties": {
    "iso:country":"ES",
    "sg:address":"Calle de Ruben Dario, 49",
    "sg:city":"Casa Pastores",
    "sg:orig_category":"Empresas De Carpinter\u00cda De Madera",
    "sg:phone":"+34 928 75 46 07",
    "sg:postcode":"35110",
    "sg:province":"Las Palmas",
    "wof:name":"Bola\u00f1os Cazorla Juan Miguel",
    "wof:placetype":"venue"
},
  "geometry": {"coordinates":[-15.4485340118,27.8392906189],"type":"Point"}
}