{
  "type": "Feature",
  "properties": {
    "iso:country":"ES",
    "sg:address":"Carrer de Ticia, 6",
    "sg:city":"Barcelona",
    "sg:orig_category":"Agencias Y Agentes Comerciales, Representantes",
    "sg:phone":"+34 934 18 70 15",
    "sg:postcode":"08023",
    "sg:province":"Barcelona",
    "wof:name":"Rodriguez Sanchez Pedro",
    "wof:placetype":"venue"
},
  "geometry": {"coordinates":[2.1394679546,41.4165344238],"type":"Point"}
}