{
  "type": "Feature",
  "properties": {
    "addr:full":"Plaz Chinas (de Las), 1 Zaragoza Zaragoza 50007",
    "addr:housenumber":"1",
    "addr:postcode":"50007",
    "addr:street":"Plaz Chinas De Las",
    "iso:country":"ES",
    "sg:address":"Plaz Chinas (de Las), 1",
    "sg:city":"Zaragoza",
    "sg:orig_category":"Electricidad: Instaladores",
    "sg:phone":"+34 976 25 61 33",
    "sg:postcode":"50007",
    "sg:province":"Zaragoza",
    "wof:name":"Burillo Gracia Francisco Jesus",
    "wof:placetype":"venue"
},
  "geometry": {"coordinates":[-0.8762239814,41.6255989075],"type":"Point"}
}