{
  "type": "Feature",
  "properties": {
    "iso:country":"ES",
    "sg:address":"Calle de San Isidro, 20",
    "sg:city":"Pozo Alcon",
    "sg:orig_category":"Promotores Constructores",
    "sg:phone":"+34 953 73 80 64",
    "sg:postcode":"23485",
    "sg:province":"Ja\u00e9n",
    "wof:name":"Fernandez Mu\u00f1oz Juan Jose",
    "wof:placetype":"venue"
},
  "geometry": {"coordinates":[-2.9328410625,37.7028770447],"type":"Point"}
}