{
  "type": "Feature",
  "properties": {
    "addr:full":"Calle de Alcoy, 13 Altea Alicante 03590",
    "addr:housenumber":"13",
    "addr:postcode":"03590",
    "addr:street":"Calle De Alcoy",
    "iso:country":"ES",
    "sg:address":"Calle de Alcoy, 13",
    "sg:city":"Altea",
    "sg:orig_category":"Inmobiliaria (agencias)",
    "sg:phone":"+34 965 84 22 40",
    "sg:postcode":"03590",
    "sg:province":"Alicante",
    "wof:name":"Anclasa S.l.",
    "wof:placetype":"venue"
},
  "geometry": {"coordinates":[-0.0553781986,38.5986747742],"type":"Point"}
}