{
  "type": "Feature",
  "properties": {
    "addr:full":"Calle de Alejandro Collantes, 27 Sevilla Sevilla 41005",
    "addr:housenumber":"27",
    "addr:postcode":"41005",
    "addr:street":"Calle De Alejandro Collantes",
    "iso:country":"ES",
    "sg:address":"Calle de Alejandro Collantes, 27",
    "sg:city":"Sevilla",
    "sg:orig_category":"M\u00c1rmoles, Granitos Y Piedras Naturales",
    "sg:phone":"+34 954 57 31 85",
    "sg:postcode":"41005",
    "sg:province":"Sevilla",
    "wof:name":"Plaza Lorente Francisca",
    "wof:placetype":"venue"
},
  "geometry": {"coordinates":[-5.9656991959,37.3843994141],"type":"Point"}
}