{
  "type": "Feature",
  "properties": {
    "iso:country":"ES",
    "sg:address":"Av Aluminio(pque Emp Pcdo), S/n",
    "sg:city":"Aviles",
    "sg:orig_category":"Vulcanizado",
    "sg:phone":"+34 985 52 07 87",
    "sg:postcode":"33400",
    "sg:province":"Asturias",
    "wof:name":"Vulcanizados Aviles S. L.",
    "wof:placetype":"venue"
},
  "geometry": {"coordinates":[-5.9219918251,43.5554695129],"type":"Point"}
}