{
  "type": "Feature",
  "properties": {
    "iso:country":"ES",
    "sg:address":"Calle de Luis De Medina, 75",
    "sg:city":"Pilas",
    "sg:orig_category":"Alimentaci\u00d3n General (al Por Menor)",
    "sg:phone":"+34 954 75 02 92",
    "sg:postcode":"41840",
    "sg:province":"Sevilla",
    "wof:name":"Cruz Rodriguez Antonio",
    "wof:placetype":"venue"
},
  "geometry": {"coordinates":[-6.2986688614,37.3018302917],"type":"Point"}
}