{
  "type": "Feature",
  "properties": {
    "addr:full":"Calle de Rafael Lucenqui, 11 Badajoz Badajoz 06004",
    "addr:housenumber":"11",
    "addr:postcode":"06004",
    "addr:street":"Calle De Rafael Lucenqui",
    "iso:country":"ES",
    "sg:address":"Calle de Rafael Lucenqui, 11",
    "sg:city":"Badajoz",
    "sg:orig_category":"Pescader\u00cdas (al Por Menor)",
    "sg:phone":"+34 924 23 44 76",
    "sg:postcode":"06004",
    "sg:province":"Badajoz",
    "wof:name":"Rodriguez Regalado Manuel",
    "wof:placetype":"venue"
},
  "geometry": {"coordinates":[-6.9762358665,38.8705940247],"type":"Point"}
}