{
  "type": "Feature",
  "properties": {
    "addr:full":"Plaz Retortillo (del), 2 Chiclana De La Frontera C\u00e1diz 11130",
    "addr:postcode":"11130",
    "addr:street":"Plaz;Del",
    "iso:country":"ES",
    "sg:address":"Plaz Retortillo (del), 2",
    "sg:city":"Chiclana De La Frontera",
    "sg:orig_category":"Cajas De Ahorro",
    "sg:phone":"+34 956 40 84 06",
    "sg:postcode":"11130",
    "sg:province":"C\u00e1diz",
    "sg:website":"www.bancaja.es",
    "wof:name":"Caja De Ahorros De Valencia Castellon Y Alicante",
    "wof:placetype":"venue"
},
  "geometry": {"coordinates":[-6.1447038651,36.4212188721],"type":"Point"}
}