{
  "type": "Feature",
  "properties": {
    "iso:country":"ES",
    "sg:address":"Calle de Garcia De Vinuesa, 37",
    "sg:city":"Sevilla",
    "sg:orig_category":"Librer\u00cdas",
    "sg:phone":"+34 954 21 73 73",
    "sg:postcode":"41001",
    "sg:province":"Sevilla",
    "wof:name":"Navarro Perez Antonio",
    "wof:placetype":"venue"
},
  "geometry": {"coordinates":[-5.9957289696,37.3861885071],"type":"Point"}
}