{
  "type": "Feature",
  "properties": {
    "addr:full":"Avda Vigo, 102 Angoren Pontevedra 36320",
    "addr:housenumber":"102",
    "addr:postcode":"36320",
    "addr:street":"Avda Vigo",
    "iso:country":"ES",
    "sg:address":"Avda Vigo, 102",
    "sg:city":"Angoren",
    "sg:orig_category":"Molduras, Junquillos, Listones Y Molduras Perforadas",
    "sg:phone":"+34 986 45 10 81",
    "sg:postcode":"36320",
    "sg:province":"Pontevedra",
    "wof:name":"Pi\u00f1eiro Caldelas Jaime Alejo",
    "wof:placetype":"venue"
},
  "geometry": {"coordinates":[-8.6428003311,42.4304618835],"type":"Point"}
}