{
  "type": "Feature",
  "properties": {
    "iso:country":"ES",
    "sg:address":"Carrer de Mare De Deu De L'esperanca, 12",
    "sg:city":"Mataro",
    "sg:orig_category":"Estancos",
    "sg:phone":"+34 937 99 31 03",
    "sg:postcode":"08304",
    "sg:province":"Barcelona",
    "wof:name":"Argerich Boixados Francisco Javier",
    "wof:placetype":"venue"
},
  "geometry": {"coordinates":[2.4440610409,41.5504875183],"type":"Point"}
}