{
  "type": "Feature",
  "properties": {
    "addr:full":"Calle de Sambara, 130 Madrid Madrid 28027",
    "addr:housenumber":"130",
    "addr:postcode":"28027",
    "addr:street":"Calle De Sambara",
    "iso:country":"ES",
    "sg:address":"Calle de Sambara, 130",
    "sg:city":"Madrid",
    "sg:orig_category":"Electricidad: Instaladores",
    "sg:phone":"+34 914 08 71 73",
    "sg:postcode":"28027",
    "sg:province":"Madrid",
    "wof:name":"Cuarzo Electricidad S.l.",
    "wof:placetype":"venue"
},
  "geometry": {"coordinates":[-3.6432731152,40.4372520447],"type":"Point"}
}