{
  "type": "Feature",
  "properties": {
    "iso:country":"ES",
    "sg:address":"Calle de Greco, 29",
    "sg:city":"Salamanca",
    "sg:orig_category":"Fabricaci\u00d3n, Importaci\u00d3n, Venta De Material De Telefon\u00cda, Peritelefon\u00cda",
    "sg:phone":"+34 923 12 50 97",
    "sg:postcode":"37004",
    "sg:province":"Salamanca",
    "sg:website":"www.setelgrupo.com",
    "wof:name":"Tecnico De Servicios Multiples S.l.",
    "wof:placetype":"venue"
},
  "geometry": {"coordinates":[-5.6510281563,40.9728851318],"type":"Point"}
}