{
  "type": "Feature",
  "properties": {
    "iso:country":"ES",
    "sg:address":"Urb. Las Brisas, S/n",
    "sg:city":"Marbella",
    "sg:orig_category":"Agencias Y Asesor\u00cda En Marketing Directo",
    "sg:phone":"+34 952 92 53 00",
    "sg:postcode":"29600",
    "sg:province":"M\u00e1laga",
    "wof:name":"Desamark Kkm S.l",
    "wof:placetype":"venue"
},
  "geometry": {"coordinates":[-4.8833007812,36.5079956055],"type":"Point"}
}