{
  "type": "Feature",
  "properties": {
    "addr:full":"Avda Ciudad De Barcelona, 33 Madrid Madrid 28007",
    "addr:housenumber":"33",
    "addr:postcode":"madrid;28007",
    "addr:street":"Avda Ciudad De Barcelona",
    "iso:country":"ES",
    "sg:address":"Avda Ciudad De Barcelona, 33",
    "sg:city":"Madrid",
    "sg:orig_category":"Comercio De Minerales, F\u00d3siles Y Conchas",
    "sg:phone":"+34 915 51 31 05",
    "sg:postcode":"28007",
    "sg:province":"Madrid",
    "wof:name":"Martinez Rodrigo Doroteo",
    "wof:placetype":"venue"
},
  "geometry": {"coordinates":[-3.6798040867,40.4039344788],"type":"Point"}
}