{
  "type": "Feature",
  "properties": {
    "addr:full":"Rua Compostela, 16 Ordes La Coru\u00f1a 15680",
    "addr:housenumber":"16",
    "addr:postcode":"15680",
    "addr:street":"Rua Compostela;La Corun\u0303A",
    "iso:country":"ES",
    "sg:address":"Rua Compostela, 16",
    "sg:city":"Ordes",
    "sg:orig_category":"Bronceado Por Rayos Uva",
    "sg:phone":"+34 981 69 78 95",
    "sg:postcode":"15680",
    "sg:province":"La Coru\u00f1a",
    "wof:name":"Carrillo Fernandez Patricia",
    "wof:placetype":"venue"
},
  "geometry": {"coordinates":[-8.4081315994,43.0779342651],"type":"Point"}
}