{
  "type": "Feature",
  "properties": {
    "addr:full":"Carr Aigueta, 35 Bisbal D'emporda Girona 17100",
    "addr:housenumber":"35",
    "addr:postcode":"17100",
    "addr:street":"Carr Aigueta",
    "iso:country":"ES",
    "sg:address":"Carr Aigueta, 35",
    "sg:city":"Bisbal D'emporda",
    "sg:orig_category":"Maquinaria Para Industrias Diversas",
    "sg:phone":"+34 972 64 02 14",
    "sg:postcode":"17100",
    "sg:province":"Girona",
    "wof:name":"Massaneda Fontanella Manuel",
    "wof:placetype":"venue"
},
  "geometry": {"coordinates":[2.8378639221,41.989566803],"type":"Point"}
}