{
  "type": "Feature",
  "properties": {
    "addr:full":"Calle de Noruega, 10 Cristianos Santa Cruz De Tenerife 38650",
    "addr:housenumber":"10",
    "addr:postcode":"38650",
    "addr:street":"Calle De Noruega",
    "iso:country":"ES",
    "sg:address":"Calle de Noruega, 10",
    "sg:city":"Cristianos",
    "sg:orig_category":"Agencias Y Agentes Comerciales, Representantes",
    "sg:phone":"+34 922 75 23 98",
    "sg:postcode":"38650",
    "sg:province":"Santa Cruz De Tenerife",
    "wof:name":"Herdot S.l.",
    "wof:placetype":"venue"
},
  "geometry": {"coordinates":[-16.721950531,28.0527877808],"type":"Point"}
}