{
  "type": "Feature",
  "properties": {
    "addr:full":"Los Caidos-la Vega, S/n Santiago Asturias 33518",
    "addr:housenumber":"s / n",
    "addr:postcode":"33518",
    "iso:country":"ES",
    "sg:address":"Los Caidos-la Vega, S/n",
    "sg:city":"Santiago",
    "sg:orig_category":"Farmacias",
    "sg:phone":"+34 985 74 81 96",
    "sg:postcode":"33518",
    "sg:province":"Asturias",
    "wof:name":"Gonzalez Santamaria Eva",
    "wof:placetype":"venue"
},
  "geometry": {"coordinates":[-5.5597882271,43.4101409912],"type":"Point"}
}