{
  "type": "Feature",
  "properties": {
    "addr:full":"Avda Alicante, 14 Villena Alicante 03400",
    "addr:housenumber":"14",
    "addr:postcode":"03400",
    "addr:street":"Avda Alicante",
    "iso:country":"ES",
    "sg:address":"Avda Alicante, 14",
    "sg:city":"Villena",
    "sg:orig_category":"Ropa Y Accesorios",
    "sg:phone":"+34 965 80 67 82",
    "sg:postcode":"03400",
    "sg:province":"Alicante",
    "sg:website":"www.almoravides.com",
    "wof:name":"El Bazar De Las Fiestas S.l.",
    "wof:placetype":"venue"
},
  "geometry": {"coordinates":[-0.8568729758,38.629573822],"type":"Point"}
}