{
  "type": "Feature",
  "properties": {
    "addr:full":"Carrer de Bresquiller, 23 Montgo Alicante 03700",
    "addr:housenumber":"23",
    "addr:postcode":"03700",
    "addr:street":"Carrer De Bresquiller",
    "iso:country":"ES",
    "sg:address":"Carrer de Bresquiller, 23",
    "sg:city":"Montgo",
    "sg:orig_category":"Inmobiliaria (agencias)",
    "sg:phone":"+34 966 43 11 42",
    "sg:postcode":"03700",
    "sg:province":"Alicante",
    "sg:website":"www.paradiseinvest.net",
    "wof:name":"Paradise Invest Espa\u00f1a S.l.",
    "wof:placetype":"venue"
},
  "geometry": {"coordinates":[0.1082440019,38.8297996521],"type":"Point"}
}