{
  "type": "Feature",
  "properties": {
    "addr:full":"Avda Ramon Y Cajal, 12 Olivenza Badajoz 06100",
    "addr:housenumber":"12",
    "addr:postcode":"06100",
    "addr:street":"Avda Ramon Y Cajal",
    "iso:country":"ES",
    "sg:address":"Avda Ramon Y Cajal, 12",
    "sg:city":"Olivenza",
    "sg:orig_category":"Confecci\u00d3n (fabricaci\u00d3n, Al Por Mayor)",
    "sg:phone":"+34 924 49 04 40",
    "sg:postcode":"06100",
    "sg:province":"Badajoz",
    "wof:name":"Tome Sanchez Antonio",
    "wof:placetype":"venue"
},
  "geometry": {"coordinates":[-7.0980839729,38.6843605042],"type":"Point"}
}