{
  "type": "Feature",
  "properties": {
    "iso:country":"ES",
    "sg:address":"Carrer de Castillejos, 328",
    "sg:city":"Barcelona",
    "sg:orig_category":"Zapatos (al Por Menor)",
    "sg:phone":"+34 934 35 80 93",
    "sg:postcode":"08025",
    "sg:province":"Barcelona",
    "wof:name":"Marti Sebastia Josep",
    "wof:placetype":"venue"
},
  "geometry": {"coordinates":[2.1743619442,41.4095878601],"type":"Point"}
}