{
  "type": "Feature",
  "properties": {
    "addr:full":"Carrer de Can San\u00c7, 5 Palma Islas Baleares 07001",
    "addr:housenumber":"5",
    "addr:postcode":"07001",
    "addr:street":"Carrer De Can Sanc\u0327",
    "iso:country":"ES",
    "sg:address":"Carrer de Can San\u00c7, 5",
    "sg:city":"Palma",
    "sg:orig_category":"Teatros Y Salas De Espect\u00c1culos",
    "sg:phone":"+34 971 72 71 66",
    "sg:postcode":"07001",
    "sg:province":"Islas Baleares",
    "wof:name":"Estudi Zero Teatre S.c.l.",
    "wof:placetype":"venue"
},
  "geometry": {"coordinates":[2.6522479057,39.5701522827],"type":"Point"}
}