{
  "type": "Feature",
  "properties": {
    "iso:country":"ES",
    "sg:address":"Calle de Bonaire, 340",
    "sg:city":"Pla Olivera",
    "sg:orig_category":"Ingenier\u00cda, Centros De Estudios (diversos)",
    "sg:phone":"+34 965 67 08 32",
    "sg:postcode":"03690",
    "sg:province":"Alicante",
    "wof:name":"U.t.e. Alicante",
    "wof:placetype":"venue"
},
  "geometry": {"coordinates":[-0.5247189999,38.405040741],"type":"Point"}
}