{
  "type": "Feature",
  "properties": {
    "iso:country":"ES",
    "sg:address":"Avda Capuchinos, 29",
    "sg:city":"Castellon",
    "sg:orig_category":"Laboratorios Y Trabajos De Fotograf\u00cda, V\u00cddeo Y Cine",
    "sg:phone":"+34 964 23 94 68",
    "sg:postcode":"12004",
    "sg:province":"Castell\u00f3n",
    "wof:name":"Foto Center S.l.",
    "wof:placetype":"venue"
},
  "geometry": {"coordinates":[-0.0340839997,39.9907875061],"type":"Point"}
}