{
  "type": "Feature",
  "properties": {
    "addr:full":"Calle de Iglesia, S/n Milles Polvorosa Zamora 49699",
    "addr:housenumber":"s / n",
    "addr:postcode":"49699",
    "addr:street":"Calle De Iglesia;Zamora",
    "iso:country":"ES",
    "sg:address":"Calle de Iglesia, S/n",
    "sg:city":"Milles Polvorosa",
    "sg:classifiers":[
        {
            "category":"Communications",
            "type":"Services"
        }
    ],
    "sg:phone":"+34 980 65 40 93",
    "sg:postcode":"49699",
    "sg:province":"Zamora",
    "sg:tags":[
        "televisiones",
        "y",
        "radio"
    ],
    "wof:name":"Fidalgo Gutierrez Eulogio",
    "wof:placetype":"venue"
},
  "geometry": {"coordinates":[-5.7302041054,41.9235687256],"type":"Point"}
}