{
  "type": "Feature",
  "properties": {
    "addr:full":"Av Doctor Llanso, Del, 66 Mercadal Islas Baleares 07740",
    "addr:housenumber":"66",
    "addr:postcode":"07740",
    "addr:street":"Av Doctor Llanso Del",
    "iso:country":"ES",
    "sg:address":"Av Doctor Llanso, Del, 66",
    "sg:city":"Mercadal",
    "sg:orig_category":"Mec\u00c1nico Del Autom\u00d3vil",
    "sg:phone":"+34 971 37 51 09",
    "sg:postcode":"07740",
    "sg:province":"Islas Baleares",
    "wof:name":"Bosch Cardona Jose",
    "wof:placetype":"venue"
},
  "geometry": {"coordinates":[4.0921797752,39.9863700867],"type":"Point"}
}