{
  "type": "Feature",
  "properties": {
    "addr:full":"Calle de San Marcos, 8 Alcala Henares Madrid 28804",
    "addr:housenumber":"8",
    "addr:postcode":"28804",
    "addr:street":"Calle De San Marcos",
    "iso:country":"ES",
    "sg:address":"Calle de San Marcos, 8",
    "sg:city":"Alcala Henares",
    "sg:orig_category":"Molduras, Junquillos, Listones Y Molduras Perforadas",
    "sg:phone":"+34 918 83 59 93",
    "sg:postcode":"28804",
    "sg:province":"Madrid",
    "wof:name":"Cerrato Barrera Francisco",
    "wof:placetype":"venue"
},
  "geometry": {"coordinates":[-3.3618779182,40.477596283],"type":"Point"}
}