{
  "type": "Feature",
  "properties": {
    "addr:full":"Carrer de Muntaner, 134 Barcelona Barcelona 08036",
    "addr:housenumber":"134",
    "addr:postcode":"08036",
    "addr:street":"Carrer De Muntaner",
    "iso:country":"ES",
    "sg:address":"Carrer de Muntaner, 134",
    "sg:city":"Barcelona",
    "sg:orig_category":"Molduras, Junquillos, Listones Y Molduras Perforadas",
    "sg:phone":"+34 933 23 00 35",
    "sg:postcode":"08036",
    "sg:province":"Barcelona",
    "wof:name":"Turull Camps Jaime",
    "wof:placetype":"venue"
},
  "geometry": {"coordinates":[2.1550300121,41.3900947571],"type":"Point"}
}