{
  "type": "Feature",
  "properties": {
    "addr:full":"Avda Andalucia (de), 176 Coria Rio Sevilla 41100",
    "addr:housenumber":"176",
    "addr:postcode":"41100",
    "addr:street":"Avda Andalucia De;Rio Sevilla",
    "iso:country":"ES",
    "sg:address":"Avda Andalucia (de), 176",
    "sg:city":"Coria Rio",
    "sg:orig_category":"Inform\u00c1tica, Ofim\u00c1tica (estudios, Asesor\u00cda, Ingenier\u00cda, Formaci\u00d3n)",
    "sg:phone":"+34 954 77 30 55",
    "sg:postcode":"41100",
    "sg:province":"Sevilla",
    "wof:name":"De Los Santos Marquez Salvador",
    "wof:placetype":"venue"
},
  "geometry": {"coordinates":[-6.0516018867,37.2829170227],"type":"Point"}
}