{
  "type": "Feature",
  "properties": {
    "addr:full":"Ermita, S/n Santa Fe Granada 18320",
    "addr:housenumber":"/ n",
    "addr:postcode":"18320",
    "addr:street":"S",
    "iso:country":"ES",
    "sg:address":"Ermita, S/n",
    "sg:city":"Santa Fe",
    "sg:orig_category":"Fabricaci\u00d3n De Art\u00cdculos Y Equipos Deportivos Y De Ocio",
    "sg:phone":"+34 958 51 08 00",
    "sg:postcode":"18320",
    "sg:province":"Granada",
    "wof:name":"Deportes Santafe S.l.",
    "wof:placetype":"venue"
},
  "geometry": {"coordinates":[-3.7121560574,37.1913452148],"type":"Point"}
}