{
  "type": "Feature",
  "properties": {
    "addr:full":"Ctra Madrid-cartagena, S/n Albujon Murcia 30330",
    "addr:housenumber":"s",
    "addr:postcode":"30330",
    "addr:street":"Ctra Madrid-Cartagena;/ N",
    "iso:country":"ES",
    "sg:address":"Ctra Madrid-cartagena, S/n",
    "sg:city":"Albujon",
    "sg:orig_category":"M\u00c1rmoles, Granitos Y Piedras Naturales",
    "sg:phone":"+34 968 16 02 10",
    "sg:postcode":"30330",
    "sg:province":"Murcia",
    "wof:name":"Explocan S.l.",
    "wof:placetype":"venue"
},
  "geometry": {"coordinates":[-1.0537320375,37.7045173645],"type":"Point"}
}