{
  "type": "Feature",
  "properties": {
    "iso:country":"ES",
    "sg:address":"Calle de Leonor Elias",
    "sg:city":"Valle Trapaga",
    "sg:orig_category":"Centros De Educaci\u00d3n Especial",
    "sg:phone":"+34 944 92 05 53",
    "sg:postcode":"48510",
    "sg:province":"Vizcaya",
    "wof:name":"Colegio La Escontrilla",
    "wof:placetype":"venue"
},
  "geometry": {"coordinates":[-3.0370090008,43.3039283752],"type":"Point"}
}