{
  "type": "Feature",
  "properties": {
    "iso:country":"ES",
    "sg:address":"Av Catalunya, S/n",
    "sg:city":"Alcarras",
    "sg:orig_category":"Frutas Y Legumbres Frescas (al Por Mayor)",
    "sg:phone":"+34 973 79 00 50",
    "sg:postcode":"25180",
    "sg:province":"Lleida",
    "wof:name":"Viyefruit S. A.",
    "wof:placetype":"venue"
},
  "geometry": {"coordinates":[0.5211932063,41.5621528625],"type":"Point"}
}