{
  "type": "Feature",
  "properties": {
    "iso:country":"ES",
    "sg:address":"Avda Ejercito, 48",
    "sg:city":"Coru\u00d1a",
    "sg:orig_category":"Suministros Y Materiales Industriales",
    "sg:phone":"+34 981 28 33 91",
    "sg:postcode":"15006",
    "sg:province":"La Coru\u00f1a",
    "wof:name":"J. L. Gandara Y Cia S. A.",
    "wof:placetype":"venue"
},
  "geometry": {"coordinates":[-8.3948364258,43.354347229],"type":"Point"}
}