{
  "type": "Feature",
  "properties": {
    "iso:country":"ES",
    "sg:address":"Pl Generalitat (de La), 1",
    "sg:city":"Tarragona",
    "sg:orig_category":"Construcciones Met\u00c1licas",
    "sg:phone":"+34 977 21 22 67",
    "sg:postcode":"43005",
    "sg:province":"Tarragona",
    "wof:name":"Estudis I Construccions Metal-liques S.a.",
    "wof:placetype":"venue"
},
  "geometry": {"coordinates":[1.2541049719,41.1169281006],"type":"Point"}
}