{
  "type": "Feature",
  "properties": {
    "addr:full":"Outeiro Do Casti\u00f1eiri\u00f1o, 10 Outeiro Do Casti\u00e7eiri\u00e7o La Coru\u00f1a 15894",
    "addr:housenumber":"10",
    "addr:postcode":"15894",
    "addr:street":"Corun\u0303A",
    "iso:country":"ES",
    "sg:address":"Outeiro Do Casti\u00f1eiri\u00f1o, 10",
    "sg:city":"Outeiro Do Casti\u00e7eiri\u00e7o",
    "sg:orig_category":"Doctores En Medicina",
    "sg:phone":"+34 981 80 10 13",
    "sg:postcode":"15894",
    "sg:province":"La Coru\u00f1a",
    "wof:name":"Prieto Martinez Arturo",
    "wof:placetype":"venue"
},
  "geometry": {"coordinates":[-8.5459394455,42.8326034546],"type":"Point"}
}