{
  "type": "Feature",
  "properties": {
    "addr:full":"C\u00ba Borgas, 40 Zaragoza Zaragoza 50011",
    "addr:housenumber":"40",
    "addr:postcode":"50011",
    "addr:street":"Borgas",
    "iso:country":"ES",
    "sg:address":"C\u00ba Borgas, 40",
    "sg:city":"Zaragoza",
    "sg:orig_category":"Poller\u00cda Y Caza (al Por Menor)",
    "sg:phone":"+34 976 33 20 87",
    "sg:postcode":"50011",
    "sg:province":"Zaragoza",
    "wof:name":"Santafe Benito Serafin",
    "wof:placetype":"venue"
},
  "geometry": {"coordinates":[-0.9398409724,41.6494865417],"type":"Point"}
}