{
  "type": "Feature",
  "properties": {
    "addr:full":"Pase Extremadura, 200 Madrid Madrid 28011",
    "addr:housenumber":"200",
    "addr:postcode":"28011",
    "addr:street":"Extremadura",
    "iso:country":"ES",
    "sg:address":"Pase Extremadura, 200",
    "sg:city":"Madrid",
    "sg:orig_category":"Farmacias",
    "sg:phone":"+34 914 63 01 37",
    "sg:postcode":"28011",
    "sg:province":"Madrid",
    "wof:name":"Diaz Lopez Concepcion",
    "wof:placetype":"venue"
},
  "geometry": {"coordinates":[-3.7400569916,40.4094963074],"type":"Point"}
}