{
  "type": "Feature",
  "properties": {
    "iso:country":"ES",
    "sg:address":"Calle de Victoria, 1",
    "sg:city":"Alcala Henares",
    "sg:orig_category":"\u00d3ptica: Instrumentos (fabricaci\u00d3n)",
    "sg:phone":"+34 918 83 01 87",
    "sg:postcode":"28802",
    "sg:province":"Madrid",
    "wof:name":"Visiorama S.l",
    "wof:placetype":"venue"
},
  "geometry": {"coordinates":[-3.3696401119,40.4800186157],"type":"Point"}
}