{
  "type": "Feature",
  "properties": {
    "iso:country":"ES",
    "sg:address":"Cuartel Este, 12",
    "sg:city":"Crevillente",
    "sg:orig_category":"Electricidad, Electr\u00d3nica: Material Y Suministros (al Por Mayor)",
    "sg:phone":"+34 966 68 26 11",
    "sg:postcode":"03330",
    "sg:province":"Alicante",
    "wof:name":"Automaticos Vega Baja S. L.",
    "wof:placetype":"venue"
},
  "geometry": {"coordinates":[-0.8083227873,38.2425003052],"type":"Point"}
}