{
  "type": "Feature",
  "properties": {
    "addr:full":"Calle de Finlandia, 3 Pozuelo De Alarcon Madrid 28224",
    "addr:housenumber":"3",
    "addr:postcode":"28224",
    "addr:street":"Calle De Finlandia",
    "iso:country":"ES",
    "sg:address":"Calle de Finlandia, 3",
    "sg:city":"Pozuelo De Alarcon",
    "sg:orig_category":"Molduras, Junquillos, Listones Y Molduras Perforadas",
    "sg:phone":"+34 913 51 17 68",
    "sg:postcode":"28224",
    "sg:province":"Madrid",
    "wof:name":"Gestion De Negocios Jmp Y Asociados S.l",
    "wof:placetype":"venue"
},
  "geometry": {"coordinates":[-3.796738863,40.4352798462],"type":"Point"}
}