{
  "type": "Feature",
  "properties": {
    "iso:country":"ES",
    "sg:address":"Avda Real, 29",
    "sg:city":"Madrid",
    "sg:orig_category":"Farmacias",
    "sg:phone":"+34 917 76 36 15",
    "sg:postcode":"28032",
    "sg:province":"Madrid",
    "wof:name":"Luengo Bernal Pedro",
    "wof:placetype":"venue"
},
  "geometry": {"coordinates":[-3.6088330746,40.4032020569],"type":"Point"}
}