{
  "type": "Feature",
  "properties": {
    "iso:country":"ES",
    "sg:address":"Calle de Granada, 157",
    "sg:city":"Malagon",
    "sg:orig_category":"Carnicer\u00cdas, Carnicer\u00cdas",
    "sg:phone":"+34 926 80 24 97",
    "sg:postcode":"13420",
    "sg:province":"Ciudad Real",
    "wof:name":"Chacinas Masias S.l.",
    "wof:placetype":"venue"
},
  "geometry": {"coordinates":[-3.8513090611,39.1718101501],"type":"Point"}
}