{
  "type": "Feature",
  "properties": {
    "iso:country":"ES",
    "sg:address":"Calle de Arquitecto Urteaga, 23",
    "sg:city":"Javea",
    "sg:orig_category":"Mec\u00c1nico Del Autom\u00d3vil",
    "sg:phone":"+34 965 79 09 23",
    "sg:postcode":"03730",
    "sg:province":"Alicante",
    "wof:name":"Talleres Thiviers Cdad",
    "wof:placetype":"venue"
},
  "geometry": {"coordinates":[0.1666599959,38.7905349731],"type":"Point"}
}