{
  "type": "Feature",
  "properties": {
    "iso:country":"ES",
    "sg:address":"Luga Santa Ana, 34",
    "sg:city":"Quintes",
    "sg:orig_category":"Producci\u00d3n De Sidra",
    "sg:phone":"+34 985 89 45 76",
    "sg:postcode":"33314",
    "sg:province":"Asturias",
    "wof:name":"Llagar Casta\u00f1on S.l.",
    "wof:placetype":"venue"
},
  "geometry": {"coordinates":[-5.9832577705,43.2504386902],"type":"Point"}
}