{
  "type": "Feature",
  "properties": {
    "addr:full":"Fdez. Ladreda, 4 Llangreu Asturias 33900",
    "addr:housenumber":"4",
    "addr:postcode":"33900",
    "addr:street":"Ladreda",
    "iso:country":"ES",
    "sg:address":"Fdez. Ladreda, 4",
    "sg:city":"Llangreu",
    "sg:orig_category":"Animales (al Por Menor)",
    "sg:phone":"+34 985 69 58 39",
    "sg:postcode":"33900",
    "sg:province":"Asturias",
    "wof:name":"Escalante Lorenzo Ana Maria",
    "wof:placetype":"venue"
},
  "geometry": {"coordinates":[-5.6692090034,43.2883987427],"type":"Point"}
}