{
  "type": "Feature",
  "properties": {
    "iso:country":"ES",
    "sg:address":"Pablo Ruiz Picasso, 4",
    "sg:city":"San Pedro Alcantara",
    "sg:orig_category":"Inmobiliaria (agencias)",
    "sg:phone":"+34 952 79 96 01",
    "sg:postcode":"29670",
    "sg:province":"M\u00e1laga",
    "wof:name":"Promociones E Inversiones Lomas 2000 S.l.",
    "wof:placetype":"venue"
},
  "geometry": {"coordinates":[-4.9903998375,36.4869995117],"type":"Point"}
}