{
  "type": "Feature",
  "properties": {
    "addr:full":"Calle de Ruiz Zorrilla, 37 Castellon Castell\u00f3n 12001",
    "addr:housenumber":"37",
    "addr:postcode":"12001",
    "addr:street":"Calle De Ruiz Zorrilla",
    "iso:country":"ES",
    "sg:address":"Calle de Ruiz Zorrilla, 37",
    "sg:city":"Castellon",
    "sg:orig_category":"Ropa Para Se\u00d1oras Y Caballeros (al Por Menor)",
    "sg:phone":"+34 964 25 37 21",
    "sg:postcode":"12001",
    "sg:province":"Castell\u00f3n",
    "sg:website":"www.adolfo-dominguez.com",
    "wof:name":"A.p.v. Basico S.l.",
    "wof:placetype":"venue"
},
  "geometry": {"coordinates":[-0.0406018011,39.9850730896],"type":"Point"}
}