{
  "type": "Feature",
  "properties": {
    "iso:country":"ES",
    "sg:address":"Calle de Cebada (de La), 4",
    "sg:city":"Sese\u00f1a",
    "sg:orig_category":"Metalurgia",
    "sg:phone":"+34 918 95 79 61",
    "sg:postcode":"45223",
    "sg:province":"Toledo",
    "wof:name":"Manufacturas Jorpi S.l",
    "wof:placetype":"venue"
},
  "geometry": {"coordinates":[-3.6800527573,40.1063156128],"type":"Point"}
}