{
  "type": "Feature",
  "properties": {
    "iso:country":"ES",
    "sg:address":"Calle de Almirante Lallemand, 65",
    "sg:city":"Pto. Rosario",
    "sg:orig_category":"Loter\u00cda Y T\u00d3mbola",
    "sg:phone":"+34 928 53 10 05",
    "sg:postcode":"35600",
    "sg:province":"Las Palmas",
    "wof:name":"Rodriguez Ravelo Fernando",
    "wof:placetype":"venue"
},
  "geometry": {"coordinates":[-13.8504209518,28.5013256073],"type":"Point"}
}