{
  "type": "Feature",
  "properties": {
    "addr:full":"Avda Estacion, 38 Zafra Badajoz 06300",
    "addr:housenumber":"38",
    "addr:postcode":"06300",
    "addr:street":"Avda Estacion",
    "iso:country":"ES",
    "sg:address":"Avda Estacion, 38",
    "sg:city":"Zafra",
    "sg:orig_category":"Talleres El\u00c9ctricos Para Veh\u00cdculos",
    "sg:phone":"+34 924 55 53 30",
    "sg:postcode":"06300",
    "sg:province":"Badajoz",
    "wof:name":"Gonzalez Cruz Ventura",
    "wof:placetype":"venue"
},
  "geometry": {"coordinates":[-6.4117069244,38.4187545776],"type":"Point"}
}