{
  "type": "Feature",
  "properties": {
    "iso:country":"ES",
    "sg:address":"Av Platja, 7",
    "sg:city":"Palmanova",
    "sg:orig_category":"Molduras, Junquillos, Listones Y Molduras Perforadas",
    "sg:phone":"+34 971 68 07 84",
    "sg:postcode":"07181",
    "sg:province":"Islas Baleares",
    "wof:name":"Karens Cb.",
    "wof:placetype":"venue"
},
  "geometry": {"coordinates":[2.5388441086,39.5256690979],"type":"Point"}
}