{
  "type": "Feature",
  "properties": {
    "iso:country":"ES",
    "sg:address":"Calle de San Juan Bautista, 20",
    "sg:city":"Almodovar Campo",
    "sg:orig_category":"Producci\u00d3n, Venta De Productos De Agricultura Biol\u00d3gica",
    "sg:phone":"+34 926 48 35 74",
    "sg:postcode":"13580",
    "sg:province":"Ciudad Real",
    "wof:name":"Garcia De La Santa Acero Antonio",
    "wof:placetype":"venue"
},
  "geometry": {"coordinates":[-4.1794691086,38.7098999023],"type":"Point"}
}