{
  "type": "Feature",
  "properties": {
    "iso:country":"ES",
    "sg:address":"Carrer de Consell De Cent, 187",
    "sg:city":"Barcelona",
    "sg:orig_category":"Librer\u00cdas",
    "sg:phone":"+34 934 53 56 11",
    "sg:postcode":"08015",
    "sg:province":"Barcelona",
    "wof:name":"Els Espirals S.c.p.",
    "wof:placetype":"venue"
},
  "geometry": {"coordinates":[2.1558089256,41.383846283],"type":"Point"}
}