{
  "type": "Feature",
  "properties": {
    "addr:full":"Avda Donostiarra, 21 Madrid Madrid 28027",
    "addr:housenumber":"21",
    "addr:postcode":"madrid;28027",
    "addr:street":"Avda Donostiarra",
    "iso:country":"ES",
    "sg:address":"Avda Donostiarra, 21",
    "sg:city":"Madrid",
    "sg:orig_category":"Carnicer\u00cdas, Carnicer\u00cdas",
    "sg:phone":"+34 914 03 81 91",
    "sg:postcode":"28027",
    "sg:province":"Madrid",
    "wof:name":"Calleja Conde Anastasio",
    "wof:placetype":"venue"
},
  "geometry": {"coordinates":[-3.657143116,40.4348869324],"type":"Point"}
}