{
  "type": "Feature",
  "properties": {
    "addr:full":"Calle de Baron Del Solar, S/n Jumilla Murcia 30520",
    "addr:housenumber":"s / n",
    "addr:postcode":"30520",
    "addr:street":"Calle De Baron Del Solar",
    "iso:country":"ES",
    "sg:address":"Calle de Baron Del Solar, S/n",
    "sg:city":"Jumilla",
    "sg:orig_category":"Cooperativas Agr\u00cdcolas",
    "sg:phone":"+34 968 78 38 28",
    "sg:postcode":"30520",
    "sg:province":"Murcia",
    "wof:name":"Asociacion Independiente De Agricultores Y Ganaderos",
    "wof:placetype":"venue"
},
  "geometry": {"coordinates":[-1.3368026018,38.4775047302],"type":"Point"}
}