{
  "type": "Feature",
  "properties": {
    "addr:full":"Calle de Cervantes, 10 Montoro C\u00f3rdoba 14600",
    "addr:housenumber":"10",
    "addr:postcode":"14600",
    "addr:street":"Calle De Cervantes;Co\u0301Rdoba",
    "iso:country":"ES",
    "sg:address":"Calle de Cervantes, 10",
    "sg:city":"Montoro",
    "sg:orig_category":"Electricidad: Instaladores",
    "sg:phone":"+34 957 16 23 82",
    "sg:postcode":"14600",
    "sg:province":"C\u00f3rdoba",
    "wof:name":"Alvarez Onieva S.l.",
    "wof:placetype":"venue"
},
  "geometry": {"coordinates":[-4.383368969,38.0203742981],"type":"Point"}
}