{
  "type": "Feature",
  "properties": {
    "addr:full":"Rua Alta, 4 Pontevedra Pontevedra 36002",
    "addr:housenumber":"4",
    "addr:postcode":"36002",
    "addr:street":"Rua Alta",
    "iso:country":"ES",
    "sg:address":"Rua Alta, 4",
    "sg:city":"Pontevedra",
    "sg:orig_category":"Molduras, Junquillos, Listones Y Molduras Perforadas",
    "sg:phone":"+34 986 89 66 10",
    "sg:postcode":"36002",
    "sg:province":"Pontevedra",
    "wof:name":"Hosteleria Kalatti S.l.",
    "wof:placetype":"venue"
},
  "geometry": {"coordinates":[-8.64661026,42.4334640503],"type":"Point"}
}