{
  "type": "Feature",
  "properties": {
    "iso:country":"ES",
    "sg:address":"Carrer de Badalona, 11",
    "sg:city":"Barcelona",
    "sg:orig_category":"\u00d3ptica: Instrumentos (fabricaci\u00d3n)",
    "sg:phone":"+34 933 39 34 97",
    "sg:postcode":"08014",
    "sg:province":"Barcelona",
    "wof:name":"Deroudille Ballestero Lucia",
    "wof:placetype":"venue"
},
  "geometry": {"coordinates":[2.1363730431,41.378490448],"type":"Point"}
}