{
  "type": "Feature",
  "properties": {
    "iso:country":"ES",
    "sg:address":"C/ Nou De Sant Antoni, 3",
    "sg:city":"Elche",
    "sg:orig_category":"Zapatos (al Por Menor)",
    "sg:phone":"+34 965 45 21 93",
    "sg:postcode":"03203",
    "sg:province":"Alicante",
    "wof:name":"Calzados Bernardino S. L.",
    "wof:placetype":"venue"
},
  "geometry": {"coordinates":[-0.6973699927,38.2636871338],"type":"Point"}
}