{
  "type": "Feature",
  "properties": {
    "iso:country":"ES",
    "sg:address":"Avda Pirineos (de Los), 7",
    "sg:city":"San Sebastian De Los Reyes",
    "sg:orig_category":"Internados & Ense\u00d1anza Privada",
    "sg:phone":"+34 916 53 56 28",
    "sg:postcode":"28700",
    "sg:province":"Madrid",
    "wof:name":"School Ofloyalty",
    "wof:placetype":"venue"
},
  "geometry": {"coordinates":[-3.6103610992,40.5487136841],"type":"Point"}
}