{
  "type": "Feature",
  "properties": {
    "addr:full":"Carrer de Proven\u00c7a, 118 Barcelona Barcelona 08029",
    "addr:housenumber":"118",
    "addr:postcode":"08029",
    "addr:street":"Carrer De Provenc\u0327A",
    "iso:country":"ES",
    "sg:address":"Carrer de Proven\u00c7a, 118",
    "sg:city":"Barcelona",
    "sg:orig_category":"Agencias Y Agentes Comerciales, Representantes",
    "sg:phone":"+34 933 21 08 81",
    "sg:postcode":"08029",
    "sg:province":"Barcelona",
    "wof:name":"Conesa Sanchez Gregorio",
    "wof:placetype":"venue"
},
  "geometry": {"coordinates":[2.1498029232,41.3857574463],"type":"Point"}
}