{
  "type": "Feature",
  "properties": {
    "iso:country":"ES",
    "sg:address":"Araba Etorbidea, 3",
    "sg:city":"Arrasate",
    "sg:orig_category":"Ense\u00d1anza Variada",
    "sg:phone":"+34 943 79 35 33",
    "sg:postcode":"20500",
    "sg:province":"Guip\u00f9zcoa",
    "wof:name":"Academia Bastida S.l.",
    "wof:placetype":"venue"
},
  "geometry": {"coordinates":[-2.495092,43.057049],"type":"Point"}
}