{
  "type": "Feature",
  "properties": {
    "iso:country":"ES",
    "sg:address":"C/ Valdivia, 24",
    "sg:city":"Manacor",
    "sg:orig_category":"Ebanister\u00cda",
    "sg:phone":"+34 971 84 43 68",
    "sg:postcode":"07500",
    "sg:province":"Islas Baleares",
    "wof:name":"Ebanisteria Bordoy Sitges S.l.",
    "wof:placetype":"venue"
},
  "geometry": {"coordinates":[3.210547924,39.5745010376],"type":"Point"}
}