{
  "type": "Feature",
  "properties": {
    "addr:full":"Avda Miguel Manche\u00d1o, 1 Arcos Frontera C\u00e1diz 11630",
    "addr:housenumber":"1",
    "addr:postcode":"11630",
    "addr:street":"Avda Miguel Manchen\u0303O",
    "iso:country":"ES",
    "sg:address":"Avda Miguel Manche\u00d1o, 1",
    "sg:city":"Arcos Frontera",
    "sg:orig_category":"Asociaciones, Organismos Culturales Y Socioeducativos",
    "sg:phone":"+34 956 70 49 24",
    "sg:postcode":"11630",
    "sg:province":"C\u00e1diz",
    "wof:name":"Asociacion Socio Cultural De Jubilados Y Pensionistas Miguel Manse\u00f1o",
    "wof:placetype":"venue"
},
  "geometry": {"coordinates":[-5.8165488243,36.7507743835],"type":"Point"}
}