{
  "type": "Feature",
  "properties": {
    "addr:full":"Avda Puebla, 35 Ponferrada Le\u00f3n 24400",
    "addr:housenumber":"35",
    "addr:postcode":"24400",
    "addr:street":"Avda Puebla",
    "iso:country":"ES",
    "sg:address":"Avda Puebla, 35",
    "sg:city":"Ponferrada",
    "sg:orig_category":"Abogados",
    "sg:phone":"+34 987 40 23 22",
    "sg:postcode":"24400",
    "sg:province":"Le\u00f3n",
    "wof:name":"Gonzalez Canedo Ovidio",
    "wof:placetype":"venue"
},
  "geometry": {"coordinates":[-6.5964617729,42.5475502014],"type":"Point"}
}