{
  "type": "Feature",
  "properties": {
    "addr:full":"Calle de Pozo Aldea, 13 Hito Cuenca 16441",
    "addr:housenumber":"13",
    "addr:postcode":"16441",
    "addr:street":"Calle De Pozo Aldea",
    "iso:country":"ES",
    "sg:address":"Calle de Pozo Aldea, 13",
    "sg:city":"Hito",
    "sg:orig_category":"Centros De Educaci\u00d3n Especial",
    "sg:phone":"+34 969 13 00 04",
    "sg:postcode":"16441",
    "sg:province":"Cuenca",
    "wof:name":"Colegio Rural Agrupado San Jose De Calasanz",
    "wof:placetype":"venue"
},
  "geometry": {"coordinates":[-2.7157371044,39.859828949],"type":"Point"}
}