{
  "type": "Feature",
  "properties": {
    "addr:full":"Calle de Seminario, 4 Albacete Albacete 02006",
    "addr:housenumber":"4",
    "addr:postcode":"02006",
    "addr:street":"Calle De Seminario",
    "iso:country":"ES",
    "sg:address":"Calle de Seminario, 4",
    "sg:city":"Albacete",
    "sg:orig_category":"Sanatorios M\u00c9dico",
    "sg:phone":"+34 967 22 04 75",
    "sg:postcode":"02006",
    "sg:province":"Albacete",
    "wof:name":"Servicio De Salud De Castilla La Mancha",
    "wof:placetype":"venue"
},
  "geometry": {"coordinates":[-1.8714449406,38.990020752],"type":"Point"}
}