{
  "type": "Feature",
  "properties": {
    "iso:country":"ES",
    "sg:address":"Calle de Ermita, 17",
    "sg:city":"Huetor-vega",
    "sg:orig_category":"Loter\u00cda Y T\u00d3mbola",
    "sg:phone":"+34 958 30 36 26",
    "sg:postcode":"18198",
    "sg:province":"Granada",
    "wof:name":"Garcia Fernandez Antonio",
    "wof:placetype":"venue"
},
  "geometry": {"coordinates":[-3.5702719688,37.1453437805],"type":"Point"}
}