{
  "type": "Feature",
  "properties": {
    "iso:country":"ES",
    "sg:address":"Carrer de Albert Einstein, 25",
    "sg:city":"Almeda Mercader",
    "sg:orig_category":"Materiales De Aislamiento T\u00c9rmico Y Ac\u00dastico",
    "sg:phone":"+34 934 75 04 85",
    "sg:postcode":"08940",
    "sg:province":"Barcelona",
    "wof:name":"Idaglas S.l.",
    "wof:placetype":"venue"
},
  "geometry": {"coordinates":[2.0740599632,41.356880188],"type":"Point"}
}