{
  "type": "Feature",
  "properties": {
    "iso:country":"ES",
    "sg:address":"Carrer de Muntaner, 168",
    "sg:city":"Barcelona",
    "sg:orig_category":"Plomeros",
    "sg:phone":"+34 934 30 47 15",
    "sg:postcode":"08036",
    "sg:province":"Barcelona",
    "wof:name":"Lampisteria Y Electricidad Espu\u00f1es Scp",
    "wof:placetype":"venue"
},
  "geometry": {"coordinates":[2.1531069279,41.3915519714],"type":"Point"}
}