{
  "type": "Feature",
  "properties": {
    "iso:country":"ES",
    "sg:address":"Calle de Cervantes, S/n",
    "sg:city":"Calzada Calatrava",
    "sg:orig_category":"Ense\u00d1anza, Formaci\u00d3n Profesional: Aprendizaje",
    "sg:phone":"+34 926 87 53 46",
    "sg:postcode":"13370",
    "sg:province":"Ciudad Real",
    "wof:name":"Instituto De Bachillerato Eduardo Valencia",
    "wof:placetype":"venue"
},
  "geometry": {"coordinates":[-3.7713427544,38.7001953125],"type":"Point"}
}