{
  "type": "Feature",
  "properties": {
    "addr:full":"Calle de Fuente Canonigos, 10 Tudela Navarra 31500",
    "addr:housenumber":"10",
    "addr:postcode":"31500",
    "addr:street":"Calle De Fuente Canonigos",
    "iso:country":"ES",
    "sg:address":"Calle de Fuente Canonigos, 10",
    "sg:city":"Tudela",
    "sg:orig_category":"Alumbrados",
    "sg:phone":"+34 948 84 83 48",
    "sg:postcode":"31500",
    "sg:province":"Navarra",
    "wof:name":"Elektra S.a.",
    "wof:placetype":"venue"
},
  "geometry": {"coordinates":[-1.6073130369,42.0520744324],"type":"Point"}
}