{
  "type": "Feature",
  "properties": {
    "iso:country":"ES",
    "sg:address":"Calle de Escultor Palao, 36",
    "sg:city":"Zaragoza",
    "sg:orig_category":"Molduras, Junquillos, Listones Y Molduras Perforadas",
    "sg:phone":"+34 976 34 74 12",
    "sg:postcode":"50017",
    "sg:province":"Zaragoza",
    "wof:name":"Martin Orea Juan Jose",
    "wof:placetype":"venue"
},
  "geometry": {"coordinates":[-0.9152449965,41.6488227844],"type":"Point"}
}