{
  "type": "Feature",
  "properties": {
    "iso:country":"ES",
    "sg:address":"Avgd Serra, 39",
    "sg:city":"Massamagrell",
    "sg:orig_category":"Cajas Y Embalajes De Madera",
    "sg:phone":"+34 961 44 08 64",
    "sg:postcode":"46130",
    "sg:province":"Valencia",
    "wof:name":"Envases Gutierrez S.l.",
    "wof:placetype":"venue"
},
  "geometry": {"coordinates":[-0.3497500122,39.5820922852],"type":"Point"}
}