{
  "type": "Feature",
  "properties": {
    "iso:country":"ES",
    "sg:address":"Carr Castell, 5",
    "sg:city":"Silla",
    "sg:orig_category":"Confecci\u00d3n (fabricaci\u00d3n, Al Por Mayor)",
    "sg:phone":"+34 961 20 13 47",
    "sg:postcode":"46460",
    "sg:province":"Valencia",
    "wof:name":"Prieto Herranz Sebastian",
    "wof:placetype":"venue"
},
  "geometry": {"coordinates":[-0.412766993,39.3625297546],"type":"Point"}
}