{
  "type": "Feature",
  "properties": {
    "iso:country":"ES",
    "sg:address":"Falmuria, 6",
    "sg:city":"Falmuria",
    "sg:orig_category":"Postigos, Persianas Y Celos\u00cdas",
    "sg:phone":"+34 985 88 73 00",
    "sg:postcode":"33438",
    "sg:province":"Asturias",
    "sg:website":"www.persitronik.com",
    "wof:name":"Persitronik S.l.l.",
    "wof:placetype":"venue"
},
  "geometry": {"coordinates":[-5.8532137871,43.552028656],"type":"Point"}
}