{
  "type": "Feature",
  "properties": {
    "addr:full":"Calle de Marques De La Ensenada, 17 Logro\u00f1o La Rioja 26003",
    "addr:housenumber":"17",
    "addr:postcode":"26003",
    "addr:street":"Calle De Marques De La Ensenada;Rioja",
    "iso:country":"ES",
    "sg:address":"Calle de Marques De La Ensenada, 17",
    "sg:city":"Logro\u00f1o",
    "sg:orig_category":"Peluqueros: De Se\u00d1oras",
    "sg:phone":"+34 941 24 26 99",
    "sg:postcode":"26003",
    "sg:province":"La Rioja",
    "wof:name":"Moya Lopez Rosa Maria",
    "wof:placetype":"venue"
},
  "geometry": {"coordinates":[-2.438254118,42.4629096985],"type":"Point"}
}