{
  "type": "Feature",
  "properties": {
    "iso:country":"ES",
    "sg:address":"C/ Albatera, 1",
    "sg:city":"Elche",
    "sg:orig_category":"Arreglo, Reparaci\u00d3n, Piezas Sueltas De Televisi\u00d3n, V\u00cddeo, Hi",
    "sg:phone":"+34 965 45 63 82",
    "sg:postcode":"03203",
    "sg:province":"Alicante",
    "wof:name":"Aviles Leon Antonio",
    "wof:placetype":"venue"
},
  "geometry": {"coordinates":[-0.679279983,38.2698516846],"type":"Point"}
}