{
  "type": "Feature",
  "properties": {
    "addr:full":"Calle de Herrero, 19 Castellon Castell\u00f3n 12002",
    "addr:housenumber":"19",
    "addr:postcode":"12002",
    "addr:street":"Calle De Herrero",
    "iso:country":"ES",
    "sg:address":"Calle de Herrero, 19",
    "sg:city":"Castellon",
    "sg:orig_category":"M\u00c9dicos: Dermatolog\u00cda Y Venereolog\u00cda",
    "sg:phone":"+34 964 23 80 87",
    "sg:postcode":"12002",
    "sg:province":"Castell\u00f3n",
    "wof:name":"Calduch Rodriguez Luis Javier",
    "wof:placetype":"venue"
},
  "geometry": {"coordinates":[-0.0393779986,39.9813728333],"type":"Point"}
}