{
  "type": "Feature",
  "properties": {
    "addr:full":"Plaz Constitucion, S/n Camas Sevilla 41900",
    "addr:housenumber":"/ n",
    "addr:postcode":"41900",
    "addr:street":"Constitucion S",
    "iso:country":"ES",
    "sg:address":"Plaz Constitucion, S/n",
    "sg:city":"Camas",
    "sg:orig_category":"Administraciones Regionales, Departamentales Y Locales",
    "sg:phone":"+34 955 98 02 64",
    "sg:postcode":"41900",
    "sg:province":"Sevilla",
    "wof:name":"Ayuntamiento De Camas",
    "wof:placetype":"venue"
},
  "geometry": {"coordinates":[-6.0345740318,37.401386261],"type":"Point"}
}