{
  "type": "Feature",
  "properties": {
    "addr:full":"Calle de Almirante Lobo, 2 Sevilla Sevilla 41001",
    "addr:housenumber":"2",
    "addr:postcode":"41001",
    "addr:street":"Calle De Almirante Lobo",
    "iso:country":"ES",
    "sg:address":"Calle de Almirante Lobo, 2",
    "sg:city":"Sevilla",
    "sg:orig_category":"Asesor\u00cda Fiscal Y Jur\u00cddica",
    "sg:phone":"+34 954 56 10 56",
    "sg:postcode":"41001",
    "sg:province":"Sevilla",
    "wof:name":"Ortiz Acu\u00f1a Francisco",
    "wof:placetype":"venue"
},
  "geometry": {"coordinates":[-5.9948821068,37.3823013306],"type":"Point"}
}