{
  "type": "Feature",
  "properties": {
    "iso:country":"ES",
    "sg:address":"Carrer de Rei, 14",
    "sg:city":"Vilella Alta",
    "sg:orig_category":"Productores Recolectores, Venta Directa De Vinos",
    "sg:phone":"+34 977 83 90 93",
    "sg:postcode":"43375",
    "sg:province":"Tarragona",
    "wof:name":"Cooperativa Agricola",
    "wof:placetype":"venue"
},
  "geometry": {"coordinates":[0.7783700228,41.2249908447],"type":"Point"}
}