{
  "type": "Feature",
  "properties": {
    "addr:full":"Calle de Alcalde Santiago Valle, S/n Velez-malaga M\u00e1laga 29700",
    "addr:housenumber":"s / n",
    "addr:postcode":"29700",
    "addr:street":"Calle De Alcalde Santiago Valle",
    "iso:country":"ES",
    "sg:address":"Calle de Alcalde Santiago Valle, S/n",
    "sg:city":"Velez-malaga",
    "sg:orig_category":"Inmobiliaria (agencias)",
    "sg:phone":"+34 952 54 92 95",
    "sg:postcode":"29700",
    "sg:province":"M\u00e1laga",
    "sg:website":"www.fl4u.com",
    "wof:name":"Residencia Familiar Para Mayores S.l.",
    "wof:placetype":"venue"
},
  "geometry": {"coordinates":[-4.0988388062,36.7725410461],"type":"Point"}
}