{
  "type": "Feature",
  "properties": {
    "iso:country":"ES",
    "sg:address":"Calle de Cantarranas, 56",
    "sg:city":"Haba",
    "sg:orig_category":"Carnicer\u00cdas, Carnicer\u00cdas",
    "sg:phone":"+34 924 82 32 03",
    "sg:postcode":"06714",
    "sg:province":"Badajoz",
    "wof:name":"Perez Gallardo Victoriano",
    "wof:placetype":"venue"
},
  "geometry": {"coordinates":[-5.8557124138,38.9535827637],"type":"Point"}
}