{
  "type": "Feature",
  "properties": {
    "iso:country":"ES",
    "sg:address":"Calle de Virgen De Los Milagros, 129",
    "sg:city":"Puerto De Santa Maria",
    "sg:orig_category":"Comercios E Industrias (cesi\u00d3n Y Reactivaci\u00d3n)",
    "sg:phone":"+34 956 54 02 27",
    "sg:postcode":"11500",
    "sg:province":"C\u00e1diz",
    "wof:name":"Aranda Garcia Del Castillo Pantaleon",
    "wof:placetype":"venue"
},
  "geometry": {"coordinates":[-6.2267656326,36.5974731445],"type":"Point"}
}