{
  "type": "Feature",
  "properties": {
    "iso:country":"ES",
    "sg:address":"Calle de Ctra. Zaragoza, Km. 0104,5",
    "sg:city":"Ribaforada",
    "sg:orig_category":"Aparatos E Instalaci\u00d3n De Regad\u00cdos",
    "sg:phone":"+34 948 84 43 09",
    "sg:postcode":"31550",
    "sg:province":"Navarra",
    "wof:name":"Gil Gil Jose Maria",
    "wof:placetype":"venue"
},
  "geometry": {"coordinates":[-1.5380395651,41.9907608032],"type":"Point"}
}