{
  "type": "Feature",
  "properties": {
    "iso:country":"ES",
    "sg:address":"Tras Doctor Fleming, 24",
    "sg:city":"Aguatona",
    "sg:orig_category":"Alimentaci\u00d3n General (al Por Menor)",
    "sg:phone":"+34 928 78 15 15",
    "sg:postcode":"35250",
    "sg:province":"Las Palmas",
    "wof:name":"Caballero Garcia Blas",
    "wof:placetype":"venue"
},
  "geometry": {"coordinates":[-15.4355688095,27.922290802],"type":"Point"}
}