{
  "type": "Feature",
  "properties": {
    "iso:country":"ES",
    "sg:address":"Carr Almirall Cervera, 24",
    "sg:city":"Puerto De Pollen\u00c7a",
    "sg:orig_category":"Cajas De Ahorro",
    "sg:phone":"+34 971 86 53 18",
    "sg:postcode":"07470",
    "sg:province":"Islas Baleares",
    "sg:website":"www.bancaja.es",
    "wof:name":"Caja De Ahorros De Valencia Castellon Y Alicante",
    "wof:placetype":"venue"
},
  "geometry": {"coordinates":[3.0824160576,39.9088401794],"type":"Point"}
}