{
  "type": "Feature",
  "properties": {
    "addr:full":"Av Passeig Del Comtat, 16 Cocentaina Alicante 03820",
    "addr:housenumber":"16",
    "addr:postcode":"03820",
    "addr:street":"Av Passeig Del Comtat",
    "iso:country":"ES",
    "sg:address":"Av Passeig Del Comtat, 16",
    "sg:city":"Cocentaina",
    "sg:orig_category":"M\u00c9dicos: Estomatolog\u00cda",
    "sg:phone":"+34 965 59 28 03",
    "sg:postcode":"03820",
    "sg:province":"Alicante",
    "wof:name":"Pons Fuster Olivera Juan Carlos",
    "wof:placetype":"venue"
},
  "geometry": {"coordinates":[-0.4387629926,38.7515029907],"type":"Point"}
}