{
  "type": "Feature",
  "properties": {
    "addr:full":"Calle de Industrias, 15 Valladolid Valladolid 47005",
    "addr:housenumber":"15",
    "addr:postcode":"47005",
    "addr:street":"Calle De Industrias",
    "iso:country":"ES",
    "sg:address":"Calle de Industrias, 15",
    "sg:city":"Valladolid",
    "sg:orig_category":"Peluqueros: De Se\u00d1oras",
    "sg:phone":"+34 983 39 86 28",
    "sg:postcode":"47005",
    "sg:province":"Valladolid",
    "wof:name":"Juarez Rodriguez Margarita",
    "wof:placetype":"venue"
},
  "geometry": {"coordinates":[-4.7147860527,41.6482086182],"type":"Point"}
}