{
  "type": "Feature",
  "properties": {
    "iso:country":"ES",
    "sg:address":"Calle de Marbella, 62",
    "sg:city":"Madrid",
    "sg:orig_category":"Ingenier\u00cda, Centros De Estudios (diversos)",
    "sg:phone":"+34 917 34 56 94",
    "sg:postcode":"28034",
    "sg:province":"Madrid",
    "wof:name":"Escan S.a.",
    "wof:placetype":"venue"
},
  "geometry": {"coordinates":[-3.7076330185,40.4961662292],"type":"Point"}
}