{
  "type": "Feature",
  "properties": {
    "addr:full":"Rond Outeiro, 245 Coru\u00d1a A Coru\u00f1a 15010",
    "addr:housenumber":"245",
    "addr:postcode":"15010",
    "addr:street":"Outeiro;Corun\u0303A",
    "iso:country":"ES",
    "sg:address":"Rond Outeiro, 245",
    "sg:city":"Coru\u00d1a",
    "sg:orig_category":"Talleres: Ropa A Medida",
    "sg:phone":"+34 981 14 01 28",
    "sg:postcode":"15010",
    "sg:province":"A Coru\u00f1a",
    "wof:name":"Tome Mahia Antonio",
    "wof:placetype":"venue"
},
  "geometry": {"coordinates":[-8.4383602142,43.3564109802],"type":"Point"}
}