{
  "type": "Feature",
  "properties": {
    "iso:country":"ES",
    "sg:address":"Rua Rinlo, 22",
    "sg:city":"Rianxo",
    "sg:orig_category":"Electricidad, Electr\u00d3nica: Suministros (al Por Menor)",
    "sg:phone":"+34 981 84 36 01",
    "sg:postcode":"15920",
    "sg:province":"La Coru\u00f1a",
    "wof:name":"Conde Losada Edelmiro Juan",
    "wof:placetype":"venue"
},
  "geometry": {"coordinates":[-8.8171691895,42.6543884277],"type":"Point"}
}