{
  "type": "Feature",
  "properties": {
    "iso:country":"ES",
    "sg:address":"Carrer de Xavier Nogues, 11",
    "sg:city":"Barcelona",
    "sg:orig_category":"Radiocomunicaciones, Telefon\u00cda M\u00d3vil, Radiomensajer\u00cda: Servicios, Comercializaci\u00d3n",
    "sg:phone":"+34 933 13 01 77",
    "sg:postcode":"08019",
    "sg:province":"Barcelona",
    "wof:name":"Mahmood Awan  Tariq",
    "wof:placetype":"venue"
},
  "geometry": {"coordinates":[2.2157049179,41.4144897461],"type":"Point"}
}