{
  "type": "Feature",
  "properties": {
    "addr:full":"Calle de Villanueva, 31 Madrid Madrid 28001",
    "addr:housenumber":"31",
    "addr:postcode":"madrid;28001",
    "addr:street":"Calle De Villanueva",
    "iso:country":"ES",
    "sg:address":"Calle de Villanueva, 31",
    "sg:city":"Madrid",
    "sg:orig_category":"Centros De Coordinaci\u00d3n",
    "sg:phone":"+34 915 75 18 62",
    "sg:postcode":"28001",
    "sg:province":"Madrid",
    "wof:name":"Desarrollo Del Territorio Y Sociedad Del Conocimiento S.l.",
    "wof:placetype":"venue"
},
  "geometry": {"coordinates":[-3.6832709312,40.4224128723],"type":"Point"}
}