{
  "type": "Feature",
  "properties": {
    "iso:country":"ES",
    "sg:address":"Carr Urgell, S/n",
    "sg:city":"Vilanova Bellpuig",
    "sg:orig_category":"Alimentaci\u00d3n General (al Por Mayor)",
    "sg:phone":"+34 973 32 40 13",
    "sg:postcode":"25264",
    "sg:province":"Lleida",
    "wof:name":"Amoros Piera Maria Jose",
    "wof:placetype":"venue"
},
  "geometry": {"coordinates":[0.9624751806,41.6126327515],"type":"Point"}
}