{
  "type": "Feature",
  "properties": {
    "addr:full":"Avgd Sant Salvador, 41 Badalona Barcelona 08913",
    "addr:housenumber":"41",
    "addr:postcode":"08913",
    "addr:street":"Salvador",
    "iso:country":"ES",
    "sg:address":"Avgd Sant Salvador, 41",
    "sg:city":"Badalona",
    "sg:orig_category":"Revestimientos Diversos",
    "sg:phone":"+34 933 99 57 29",
    "sg:postcode":"08913",
    "sg:province":"Barcelona",
    "wof:name":"Zamora Asensio Ana",
    "wof:placetype":"venue"
},
  "geometry": {"coordinates":[2.2169961929,41.4346351624],"type":"Point"}
}