{
  "type": "Feature",
  "properties": {
    "addr:full":"Calle de Severo Ochoa, 24 Palmas De Gran Canaria Las Palmas 35015",
    "addr:housenumber":"24",
    "addr:postcode":"35015",
    "addr:street":"Calle De Severo Ochoa",
    "iso:country":"ES",
    "sg:address":"Calle de Severo Ochoa, 24",
    "sg:city":"Palmas De Gran Canaria",
    "sg:orig_category":"Electricidad, Electr\u00d3nica: Material Y Suministros (al Por Mayor)",
    "sg:phone":"+34 928 31 81 88",
    "sg:postcode":"35015",
    "sg:province":"Las Palmas",
    "wof:name":"Merlin Guerin Onduladores S.a.",
    "wof:placetype":"venue"
},
  "geometry": {"coordinates":[-15.4289979935,28.0920848846],"type":"Point"}
}