{
  "type": "Feature",
  "properties": {
    "iso:country":"ES",
    "sg:address":"Carr Alcudia, 3",
    "sg:city":"Pollen\u00e7a",
    "sg:orig_category":"\u00d3ptica: Instrumentos (fabricaci\u00d3n)",
    "sg:phone":"+34 971 53 05 51",
    "sg:postcode":"07460",
    "sg:province":"Islas Baleares",
    "wof:name":"Optica Alemania S. A.",
    "wof:placetype":"venue"
},
  "geometry": {"coordinates":[3.0171229839,39.8766746521],"type":"Point"}
}