{
  "type": "Feature",
  "properties": {
    "addr:full":"Pase Ronda, 45 Coru\u00d1a La Coru\u00f1a 15011",
    "addr:housenumber":"45",
    "addr:postcode":"15011",
    "addr:street":"Ronda;Corun\u0303A",
    "iso:country":"ES",
    "sg:address":"Pase Ronda, 45",
    "sg:city":"Coru\u00d1a",
    "sg:orig_category":"Sociedades, Compa\u00d1\u00cdas Aseguradoras",
    "sg:phone":"+34 981 25 95 46",
    "sg:postcode":"15011",
    "sg:province":"La Coru\u00f1a",
    "wof:name":"Helvetia Compa\u00f1ia Suiza De Seguros Y Reaseguros S.a.",
    "wof:placetype":"venue"
},
  "geometry": {"coordinates":[-8.4211454391,43.3685760498],"type":"Point"}
}