{
  "type": "Feature",
  "properties": {
    "iso:country":"ES",
    "sg:address":"Ctra. Cadiz-algeciras, Km. 0020,8",
    "sg:city":"Barrio Nuevo",
    "sg:orig_category":"Agentes, Concesionarios Y Sucursales De Veh\u00cdculos",
    "sg:phone":"+34 956 45 20 06",
    "sg:postcode":"11149",
    "sg:province":"C\u00e1diz",
    "sg:website":"talleresmelchor.com",
    "wof:name":"Talleres Melchor S.l.",
    "wof:placetype":"venue"
},
  "geometry": {"coordinates":[-6.0707631111,36.34116745],"type":"Point"}
}