{
  "type": "Feature",
  "properties": {
    "iso:country":"ES",
    "sg:address":"Rama Hoyo, S/n",
    "sg:city":"Torremolinos",
    "sg:orig_category":"Cl\u00cdnicas Dentales",
    "sg:phone":"+34 952 38 72 46",
    "sg:postcode":"29620",
    "sg:province":"M\u00e1laga",
    "wof:name":"Congreso Dental S.l.",
    "wof:placetype":"venue"
},
  "geometry": {"coordinates":[-4.499666214,36.6263847351],"type":"Point"}
}