{
  "type": "Feature",
  "properties": {
    "iso:country":"ES",
    "sg:address":"Avgd Espioca, 78",
    "sg:city":"Silla",
    "sg:orig_category":"Transportes Internacionales",
    "sg:phone":"+34 961 20 38 13",
    "sg:postcode":"46460",
    "sg:province":"Valencia",
    "sg:website":"w.w.w.grupesa.es",
    "wof:name":"W.t.grupesa S.a.",
    "wof:placetype":"venue"
},
  "geometry": {"coordinates":[-0.4249154925,39.3520317078],"type":"Point"}
}