{
  "type": "Feature",
  "properties": {
    "iso:country":"ES",
    "sg:address":"Calle de Compromiso De Caspe, 5",
    "sg:city":"Puebla Alfinden",
    "sg:orig_category":"Fabricaci\u00d3n De Distribuidores Autom\u00c1ticos",
    "sg:phone":"+34 976 45 51 57",
    "sg:postcode":"50171",
    "sg:province":"Zaragoza",
    "wof:name":"Castillo Gagias Susana",
    "wof:placetype":"venue"
},
  "geometry": {"coordinates":[-0.7493984103,41.6300735474],"type":"Point"}
}