{
  "type": "Feature",
  "properties": {
    "addr:full":"Avda Emigrantes (los), S/n Ecija Sevilla 41400",
    "addr:postcode":"41400",
    "addr:street":"Avda Emigrantes Los S / N",
    "iso:country":"ES",
    "sg:address":"Avda Emigrantes (los), S/n",
    "sg:city":"Ecija",
    "sg:orig_category":"Librer\u00cdas",
    "sg:phone":"+34 955 90 17 28",
    "sg:postcode":"41400",
    "sg:province":"Sevilla",
    "wof:name":"Rechi Gomez Gloria",
    "wof:placetype":"venue"
},
  "geometry": {"coordinates":[-5.0860238075,37.5437431335],"type":"Point"}
}