{
  "type": "Feature",
  "properties": {
    "addr:full":"Plaz San Telmo, 12 Vinaros Castell\u00f3n 12500",
    "addr:housenumber":"12",
    "addr:postcode":"12500",
    "addr:street":"Plaz San Telmo",
    "iso:country":"ES",
    "sg:address":"Plaz San Telmo, 12",
    "sg:city":"Vinaros",
    "sg:orig_category":"Arquitectos",
    "sg:phone":"+34 964 45 64 51",
    "sg:postcode":"12500",
    "sg:province":"Castell\u00f3n",
    "wof:name":"Forner Balaguer Oscar",
    "wof:placetype":"venue"
},
  "geometry": {"coordinates":[0.4749450088,40.4711990356],"type":"Point"}
}