{
  "type": "Feature",
  "properties": {
    "addr:full":"Rua Galicia (de), 45 Vilalba Lugo 27800",
    "addr:housenumber":"45",
    "addr:postcode":"27800",
    "addr:street":"Rua Galicia De",
    "iso:country":"ES",
    "sg:address":"Rua Galicia (de), 45",
    "sg:city":"Vilalba",
    "sg:classifiers":[
        {
            "category":"Personal",
            "subcategory":"Barber",
            "type":"Services"
        }
    ],
    "sg:phone":"+34 982 51 21 08",
    "sg:postcode":"27800",
    "sg:province":"Lugo",
    "sg:tags":[
        "caballeros",
        "de",
        "peluqueros"
    ],
    "wof:name":"Formoso Pardo Jesus Angel",
    "wof:placetype":"venue"
},
  "geometry": {"coordinates":[-7.6812272072,43.2957496643],"type":"Point"}
}