{
  "type": "Feature",
  "properties": {
    "iso:country":"ES",
    "sg:address":"Trva Juncarejo (de), 23",
    "sg:city":"Moralzarzal",
    "sg:orig_category":"Cooperativas Agr\u00cdcolas",
    "sg:phone":"+34 918 42 75 12",
    "sg:postcode":"28411",
    "sg:province":"Madrid",
    "sg:website":"www.troyani.com",
    "wof:name":"Aserco S.coop.ltda",
    "wof:placetype":"venue"
},
  "geometry": {"coordinates":[-3.9757657051,40.6839256287],"type":"Point"}
}