{
  "type": "Feature",
  "properties": {
    "addr:full":"Carrer de Espronceda, 226 Barcelona Barcelona 08018",
    "addr:housenumber":"226",
    "addr:postcode":"08018",
    "addr:street":"Carrer De Espronceda",
    "iso:country":"ES",
    "sg:address":"Carrer de Espronceda, 226",
    "sg:city":"Barcelona",
    "sg:orig_category":"Venta, Instalaci\u00d3n, Reparaci\u00d3n De Antenas Para Televisi\u00d3n",
    "sg:phone":"+34 933 08 06 00",
    "sg:postcode":"08018",
    "sg:province":"Barcelona",
    "sg:website":"www.artsat.es",
    "wof:name":"Monterde Jacar Isidro",
    "wof:placetype":"venue"
},
  "geometry": {"coordinates":[2.1962709427,41.4118766785],"type":"Point"}
}