{
  "type": "Feature",
  "properties": {
    "iso:country":"ES",
    "sg:address":"Carr Lepant, 9",
    "sg:city":"Vilanova I La Geltru",
    "sg:orig_category":"Construcci\u00d3n De Edificios Residenciales Y No Residenciales",
    "sg:phone":"+34 938 14 73 90",
    "sg:postcode":"08800",
    "sg:province":"Barcelona",
    "wof:name":"Domus Line Promocions I Construccions S.l.",
    "wof:placetype":"venue"
},
  "geometry": {"coordinates":[1.7152279615,41.2250976562],"type":"Point"}
}