{
  "type": "Feature",
  "properties": {
    "addr:full":"Calle de Limon, 11 Santander Cantabria 39008",
    "addr:housenumber":"11",
    "addr:postcode":"39008",
    "addr:street":"Calle De Limon",
    "iso:country":"ES",
    "sg:address":"Calle de Limon, 11",
    "sg:city":"Santander",
    "sg:orig_category":"Organizaciones Internacionales",
    "sg:phone":"+34 942 36 37 86",
    "sg:postcode":"39008",
    "sg:province":"Cantabria",
    "wof:name":"Caritas Diocesanas",
    "wof:placetype":"venue"
},
  "geometry": {"coordinates":[-3.8109738827,43.4613075256],"type":"Point"}
}