{
  "type": "Feature",
  "properties": {
    "addr:full":"Avda Pablo Neruda, S/n Madrid Madrid 28018",
    "addr:housenumber":"s / n",
    "addr:postcode":"28018",
    "addr:street":"Avda Pablo Neruda",
    "iso:country":"ES",
    "sg:address":"Avda Pablo Neruda, S/n",
    "sg:city":"Madrid",
    "sg:orig_category":"Mercer\u00cda, Lencer\u00cda (al Por Menor)",
    "sg:phone":"+34 915 07 18 24",
    "sg:postcode":"28018",
    "sg:province":"Madrid",
    "wof:name":"Guapo Gonzalez Felipe",
    "wof:placetype":"venue"
},
  "geometry": {"coordinates":[-3.6603140831,40.3815116882],"type":"Point"}
}