{
  "type": "Feature",
  "properties": {
    "iso:country":"ES",
    "sg:address":"Avda Covadonga, 43",
    "sg:city":"Cangas Onis",
    "sg:orig_category":"Turismo",
    "sg:phone":"+34 985 84 86 99",
    "sg:postcode":"33550",
    "sg:province":"Asturias",
    "sg:website":"www.infoasturias.com",
    "wof:name":"Parque Nacional De Los Picos De Europa",
    "wof:placetype":"venue"
},
  "geometry": {"coordinates":[-5.1245951653,43.3510055542],"type":"Point"}
}