{
  "type": "Feature",
  "properties": {
    "iso:country":"ES",
    "sg:address":"Avda Marques De Rozalejo, 49",
    "sg:city":"Dolores",
    "sg:orig_category":"Supermercados Y Hipermercados",
    "sg:phone":"+34 968 17 32 43",
    "sg:postcode":"30739",
    "sg:province":"Murcia",
    "wof:name":"Sanchez Cegarra Gregorio",
    "wof:placetype":"venue"
},
  "geometry": {"coordinates":[-0.8681989908,37.7773475647],"type":"Point"}
}