{
  "type": "Feature",
  "properties": {
    "addr:full":"Rua Ramon Gonzalez, 33 Porri\u00f1o Pontevedra 36400",
    "addr:housenumber":"33",
    "addr:postcode":"36400",
    "addr:street":"Rua Ramon Gonzalez",
    "iso:country":"ES",
    "sg:address":"Rua Ramon Gonzalez, 33",
    "sg:city":"Porri\u00f1o",
    "sg:orig_category":"Lencer\u00cda Femenina, Corseter\u00cda, Trajes De Ba\u00d1o (al Por Menor)",
    "sg:phone":"+34 986 33 01 92",
    "sg:postcode":"36400",
    "sg:province":"Pontevedra",
    "wof:name":"Sio Casales Josefa",
    "wof:placetype":"venue"
},
  "geometry": {"coordinates":[-8.6211004257,42.1615791321],"type":"Point"}
}