{
  "type": "Feature",
  "properties": {
    "addr:full":"Calle de Don Rodrigo Caballero, 2 Valverde Camino Huelva 21600",
    "addr:housenumber":"2",
    "addr:postcode":"21600",
    "addr:street":"Calle De Don;Caballero;Camino Huelva",
    "iso:country":"ES",
    "sg:address":"Calle de Don Rodrigo Caballero, 2",
    "sg:city":"Valverde Camino",
    "sg:orig_category":"Partidos Pol\u00cdticos",
    "sg:phone":"+34 959 55 09 06",
    "sg:postcode":"21600",
    "sg:province":"Huelva",
    "wof:name":"Partido Socialista Obrero Espa\u00f1ol",
    "wof:placetype":"venue"
},
  "geometry": {"coordinates":[-6.7538571358,37.5724258423],"type":"Point"}
}