{
  "type": "Feature",
  "properties": {
    "iso:country":"ES",
    "sg:address":"Calle de Plaza, 16",
    "sg:city":"Villanueva Del Rosario",
    "sg:orig_category":"Obras Y Organismos Sociales",
    "sg:phone":"+34 952 74 23 63",
    "sg:postcode":"29312",
    "sg:province":"M\u00e1laga",
    "wof:name":"Asociacion Nuevo Futuro",
    "wof:placetype":"venue"
},
  "geometry": {"coordinates":[-4.3648958206,36.997592926],"type":"Point"}
}