{
  "type": "Feature",
  "properties": {
    "iso:country":"ES",
    "sg:address":"Picara\u00f1a, 63",
    "sg:city":"Picara\u00d1a",
    "sg:orig_category":"Negocio De Materiales De Construcci\u00d3n",
    "sg:phone":"+34 981 50 91 18",
    "sg:postcode":"15980",
    "sg:province":"La Coru\u00f1a",
    "sg:website":"www.galicorte.com",
    "wof:name":"Galicorte S.l.",
    "wof:placetype":"venue"
},
  "geometry": {"coordinates":[-8.6362838745,42.7748756409],"type":"Point"}
}