{
  "type": "Feature",
  "properties": {
    "iso:country":"ES",
    "sg:address":"Carr Mossen Jacint Verdaguer, 38",
    "sg:city":"Arbucies",
    "sg:orig_category":"Suministros Para Carrocer\u00cdas",
    "sg:phone":"+34 972 86 02 53",
    "sg:postcode":"17401",
    "sg:province":"Girona",
    "wof:name":"Isocarr Arbucies S.l.l.",
    "wof:placetype":"venue"
},
  "geometry": {"coordinates":[2.518239975,41.8144645691],"type":"Point"}
}