{
  "type": "Feature",
  "properties": {
    "addr:full":"Carrer de Ciutadella, 2 Terrassa Barcelona 08226",
    "addr:housenumber":"2",
    "addr:postcode":"08226",
    "addr:street":"Carrer De Ciutadella",
    "iso:country":"ES",
    "sg:address":"Carrer de Ciutadella, 2",
    "sg:city":"Terrassa",
    "sg:orig_category":"Molduras, Junquillos, Listones Y Molduras Perforadas",
    "sg:phone":"+34 937 85 19 48",
    "sg:postcode":"08226",
    "sg:province":"Barcelona",
    "wof:name":"Ortiz Aldabo Casimiro",
    "wof:placetype":"venue"
},
  "geometry": {"coordinates":[2.0281450748,41.5735473633],"type":"Point"}
}