{
  "type": "Feature",
  "properties": {
    "addr:full":"Carrer de Girona, 69 Barcelona Barcelona 08009",
    "addr:housenumber":"69",
    "addr:postcode":"08009",
    "addr:street":"Carrer De Girona",
    "iso:country":"ES",
    "sg:address":"Carrer de Girona, 69",
    "sg:city":"Barcelona",
    "sg:orig_category":"Electrodom\u00c9sticos (al Por Menor)",
    "sg:phone":"+34 934 88 11 01",
    "sg:postcode":"08009",
    "sg:province":"Barcelona",
    "wof:name":"Bel Val Agustin",
    "wof:placetype":"venue"
},
  "geometry": {"coordinates":[2.1711499691,41.3946113586],"type":"Point"}
}