{
  "type": "Feature",
  "properties": {
    "iso:country":"ES",
    "sg:address":"Carr Joanot Martorell, 19",
    "sg:city":"Quart Poblet",
    "sg:orig_category":"Ortopedia General",
    "sg:phone":"+34 961 52 06 54",
    "sg:postcode":"46930",
    "sg:province":"Valencia",
    "wof:name":"Farmaorto Gasent S.l.",
    "wof:placetype":"venue"
},
  "geometry": {"coordinates":[-0.4432339966,39.4826889038],"type":"Point"}
}