{
  "type": "Feature",
  "properties": {
    "addr:full":"C/ Nord, 4 Tarrega Lleida 25300",
    "addr:housenumber":"4",
    "addr:postcode":"25300",
    "addr:street":"C / Nord",
    "iso:country":"ES",
    "sg:address":"C/ Nord, 4",
    "sg:city":"Tarrega",
    "sg:orig_category":"Molduras, Junquillos, Listones Y Molduras Perforadas",
    "sg:phone":"+34 973 31 00 13",
    "sg:postcode":"25300",
    "sg:province":"Lleida",
    "wof:name":"Campos Luque Andres",
    "wof:placetype":"venue"
},
  "geometry": {"coordinates":[1.140576005,41.6510353088],"type":"Point"}
}