{
  "type": "Feature",
  "properties": {
    "iso:country":"ES",
    "sg:address":"Calle de Muro, 2",
    "sg:city":"Palencia",
    "sg:orig_category":"Centros P\u00dablicos De Formaci\u00d3n Profesional Y T\u00c9cnica",
    "sg:phone":"+34 979 74 33 37",
    "sg:postcode":"34001",
    "sg:province":"Palencia",
    "wof:name":"Colegio Provincial Veterinarios",
    "wof:placetype":"venue"
},
  "geometry": {"coordinates":[-4.5327410698,42.0140266418],"type":"Point"}
}