{
  "type": "Feature",
  "properties": {
    "addr:full":"Avda Espinela, 8 Madrid Madrid 28021",
    "addr:housenumber":"8",
    "addr:postcode":"madrid;28021",
    "addr:street":"Avda Espinela",
    "iso:country":"ES",
    "sg:address":"Avda Espinela, 8",
    "sg:city":"Madrid",
    "sg:orig_category":"Zapatos (al Por Menor)",
    "sg:phone":"+34 917 97 11 45",
    "sg:postcode":"28021",
    "sg:province":"Madrid",
    "wof:name":"Solo Botas S.l",
    "wof:placetype":"venue"
},
  "geometry": {"coordinates":[-3.7092878819,40.3456687927],"type":"Point"}
}