{
  "type": "Feature",
  "properties": {
    "addr:full":"Carrer de Florida (la), 27 Cornella Llobregat Barcelona 08940",
    "addr:housenumber":"27",
    "addr:postcode":"08940",
    "addr:street":"Carrer De Florida La",
    "iso:country":"ES",
    "sg:address":"Carrer de Florida (la), 27",
    "sg:city":"Cornella Llobregat",
    "sg:orig_category":"Montaje (empresas De)",
    "sg:phone":"+34 933 75 13 54",
    "sg:postcode":"08940",
    "sg:province":"Barcelona",
    "wof:name":"Montajes Electricos Varios S.c.p.",
    "wof:placetype":"venue"
},
  "geometry": {"coordinates":[2.0752189159,41.3575706482],"type":"Point"}
}