{
  "type": "Feature",
  "properties": {
    "iso:country":"ES",
    "sg:address":"Calle de San Jose, 40",
    "sg:city":"Alaquas",
    "sg:orig_category":"Sonorizaci\u00d3n, Iluminaci\u00d3n Para Cine, Teatro Y Discotecas (al Por Mayor, Al Por Menor)",
    "sg:phone":"+34 961 50 35 68",
    "sg:postcode":"46970",
    "sg:province":"Valencia",
    "wof:name":"Ferrer Guzman Josep",
    "wof:placetype":"venue"
},
  "geometry": {"coordinates":[-0.4599449933,39.4596176147],"type":"Point"}
}