{
  "type": "Feature",
  "properties": {
    "iso:country":"ES",
    "sg:address":"Calle de Gabriel Celaya, 1",
    "sg:city":"Priego Cordoba",
    "sg:orig_category":"Supermercados Y Hipermercados",
    "sg:phone":"+34 957 54 18 65",
    "sg:postcode":"14800",
    "sg:province":"C\u00f3rdoba",
    "wof:name":"Dissa Seleccion S.l",
    "wof:placetype":"venue"
},
  "geometry": {"coordinates":[-4.1972708702,37.4411697388],"type":"Point"}
}