{
  "type": "Feature",
  "properties": {
    "iso:country":"ES",
    "sg:address":"Calle de Covadonga, 7",
    "sg:city":"Oviedo",
    "sg:orig_category":"Bricolaje, Herramientas (al Por Menor)",
    "sg:phone":"+34 985 21 04 51",
    "sg:postcode":"33002",
    "sg:province":"Asturias",
    "wof:name":"Suarez Rodriguez Manuel",
    "wof:placetype":"venue"
},
  "geometry": {"coordinates":[-5.8480696678,43.364151001],"type":"Point"}
}