{
  "type": "Feature",
  "properties": {
    "iso:country":"ES",
    "sg:address":"Calle de Jardi, 1",
    "sg:city":"Burriana",
    "sg:orig_category":"Bisuter\u00cda, Joyer\u00cda, Relojer\u00cda (al Por Menor)",
    "sg:phone":"+34 964 51 72 40",
    "sg:postcode":"12530",
    "sg:province":"Castell\u00f3n",
    "wof:name":"Planelles Fenollosa Enrique",
    "wof:placetype":"venue"
},
  "geometry": {"coordinates":[-0.0836770013,39.8882980347],"type":"Point"}
}