{
  "type": "Feature",
  "properties": {
    "addr:full":"Carrer de Bilbao, 9 Masnou Barcelona 08320",
    "addr:housenumber":"9",
    "addr:postcode":"08320",
    "addr:street":"Carrer De Bilbao",
    "iso:country":"ES",
    "sg:address":"Carrer de Bilbao, 9",
    "sg:city":"Masnou",
    "sg:orig_category":"Metalurgia: Maquinaria Y Equipos",
    "sg:phone":"+34 935 40 31 95",
    "sg:postcode":"08320",
    "sg:province":"Barcelona",
    "wof:name":"Mediterranean Industrial Trade S. L.",
    "wof:placetype":"venue"
},
  "geometry": {"coordinates":[2.3067278862,41.4796447754],"type":"Point"}
}