{
  "type": "Feature",
  "properties": {
    "iso:country":"ES",
    "sg:address":"Carrer de Balmes, 372",
    "sg:city":"Barcelona",
    "sg:orig_category":"M\u00c9dicos: Estomatolog\u00cda",
    "sg:phone":"+34 932 12 20 39",
    "sg:postcode":"08022",
    "sg:province":"Barcelona",
    "wof:name":"Fabregas Lobera Antonio",
    "wof:placetype":"venue"
},
  "geometry": {"coordinates":[2.1406049728,41.4046707153],"type":"Point"}
}