{
  "type": "Feature",
  "properties": {
    "addr:full":"Calle de Jaen, 13 Villanueva Cordoba C\u00f3rdoba 14440",
    "addr:housenumber":"13;cordoba co\u0301rdoba",
    "addr:postcode":"14440",
    "addr:street":"Calle De Jaen",
    "iso:country":"ES",
    "sg:address":"Calle de Jaen, 13",
    "sg:city":"Villanueva Cordoba",
    "sg:orig_category":"Plomeros",
    "sg:phone":"+34 957 12 16 28",
    "sg:postcode":"14440",
    "sg:province":"C\u00f3rdoba",
    "wof:name":"Saneamientos Y Fontaneria Tomas Blanco Moreno S.l.",
    "wof:placetype":"venue"
},
  "geometry": {"coordinates":[-4.6195788383,38.3232460022],"type":"Point"}
}