{
  "type": "Feature",
  "properties": {
    "iso:country":"ES",
    "sg:address":"Calle de Marceliano Serrano, S/n",
    "sg:city":"Villalon Campos",
    "sg:orig_category":"Carnicer\u00cdas, Carnicer\u00cdas",
    "sg:phone":"+34 983 74 09 82",
    "sg:postcode":"47600",
    "sg:province":"Valladolid",
    "wof:name":"Gutierrez De Prado Pancracio",
    "wof:placetype":"venue"
},
  "geometry": {"coordinates":[-5.034804821,42.0994338989],"type":"Point"}
}