{
  "type": "Feature",
  "properties": {
    "addr:full":"Calle de Herradores, 94 San Cristobal De La Laguna Santa Cruz De Tenerife 38201",
    "addr:housenumber":"94",
    "addr:postcode":"38201",
    "addr:street":"Calle De Herradores",
    "iso:country":"ES",
    "sg:address":"Calle de Herradores, 94",
    "sg:city":"San Cristobal De La Laguna",
    "sg:orig_category":"Telas Y Sedas (al Por Menor)",
    "sg:phone":"+34 922 25 83 47",
    "sg:postcode":"38201",
    "sg:province":"Santa Cruz De Tenerife",
    "wof:name":"Hernandez Laverny Antonio",
    "wof:placetype":"venue"
},
  "geometry": {"coordinates":[-16.3193035126,28.4897441864],"type":"Point"}
}