{
  "type": "Feature",
  "properties": {
    "addr:full":"Estd Xeral, 2 Pontenova Lugo 27720",
    "addr:housenumber":"2",
    "addr:postcode":"27720",
    "addr:street":"Xeral",
    "iso:country":"ES",
    "sg:address":"Estd Xeral, 2",
    "sg:city":"Pontenova",
    "sg:orig_category":"Molduras, Junquillos, Listones Y Molduras Perforadas",
    "sg:phone":"+34 982 34 21 60",
    "sg:postcode":"27720",
    "sg:province":"Lugo",
    "wof:name":"Marcos Fernandez Arsenio",
    "wof:placetype":"venue"
},
  "geometry": {"coordinates":[-7.1766328812,43.3744239807],"type":"Point"}
}