{
  "type": "Feature",
  "properties": {
    "addr:full":"Calle de Alfaro, 9 Santa Cruz De Tenerife Santa Cruz De Tenerife 38003",
    "addr:housenumber":"9",
    "addr:postcode":"38003",
    "addr:street":"Calle De Alfaro",
    "iso:country":"ES",
    "sg:address":"Calle de Alfaro, 9",
    "sg:city":"Santa Cruz De Tenerife",
    "sg:orig_category":"Carnicer\u00cdas, Carnicer\u00cdas",
    "sg:phone":"+34 922 28 31 14",
    "sg:postcode":"38003",
    "sg:province":"Santa Cruz De Tenerife",
    "wof:name":"Miraven S.l.",
    "wof:placetype":"venue"
},
  "geometry": {"coordinates":[-16.2547092438,28.4666500092],"type":"Point"}
}