{
  "type": "Feature",
  "properties": {
    "iso:country":"ES",
    "sg:address":"Calle de Beniferri, S/n",
    "sg:city":"Madrid",
    "sg:orig_category":"Papeler\u00cdas, Librer\u00cdas",
    "sg:phone":"+34 917 98 64 69",
    "sg:postcode":"28021",
    "sg:province":"Madrid",
    "wof:name":"Redondo De Castro Leocadia",
    "wof:placetype":"venue"
},
  "geometry": {"coordinates":[-3.690967083,40.3443641663],"type":"Point"}
}