{
  "type": "Feature",
  "properties": {
    "iso:country":"ES",
    "sg:address":"Amaya-amaia, 28",
    "sg:city":"Iru\u00f1a",
    "sg:orig_category":"Ingenier\u00cda, Centros De Estudios (diversos)",
    "sg:phone":"+34 948 23 67 08",
    "sg:postcode":"31004",
    "sg:province":"Navarra",
    "wof:name":"Garitacelaya Saldise Jesus",
    "wof:placetype":"venue"
},
  "geometry": {"coordinates":[-1.6363229752,42.8115501404],"type":"Point"}
}