{
  "type": "Feature",
  "properties": {
    "addr:full":"Ptge Farinera Teixidor, 3 Girona Girona 17005",
    "addr:housenumber":"3",
    "addr:postcode":"17005",
    "addr:street":"Ptge Farinera Teixidor",
    "iso:country":"ES",
    "sg:address":"Ptge Farinera Teixidor, 3",
    "sg:city":"Girona",
    "sg:orig_category":"Administradores De Bienes Y Delegados De Comunidades De Propietarios",
    "sg:phone":"+34 972 22 19 88",
    "sg:postcode":"17005",
    "sg:province":"Girona",
    "wof:name":"Administracions Tejada S.l.",
    "wof:placetype":"venue"
},
  "geometry": {"coordinates":[2.8158373833,41.9814987183],"type":"Point"}
}