{
  "type": "Feature",
  "properties": {
    "iso:country":"ES",
    "sg:address":"Pase Tomas Morales, 9",
    "sg:city":"Palmas De Gran Canaria",
    "sg:orig_category":"Arquitectos",
    "sg:phone":"+34 928 36 24 93",
    "sg:postcode":"35003",
    "sg:province":"Las Palmas",
    "wof:name":"Aleman Suarez Jose",
    "wof:placetype":"venue"
},
  "geometry": {"coordinates":[-15.4199867249,28.1103744507],"type":"Point"}
}