{
  "type": "Feature",
  "properties": {
    "iso:country":"ES",
    "sg:address":"Carretera, Km. 0050,5",
    "sg:city":"Atienza",
    "sg:orig_category":"Charcuter\u00cdas (al Por Mayor)",
    "sg:phone":"+34 949 39 91 69",
    "sg:postcode":"19270",
    "sg:province":"Guadalajara",
    "wof:name":"Embutidos Atienza S. A.",
    "wof:placetype":"venue"
},
  "geometry": {"coordinates":[-2.8690900803,41.1993293762],"type":"Point"}
}