{
  "type": "Feature",
  "properties": {
    "iso:country":"ES",
    "sg:address":"G.v. Lopez De Haro D. Diego, 78",
    "sg:city":"Bilbao",
    "sg:orig_category":"Molduras, Junquillos, Listones Y Molduras Perforadas",
    "sg:phone":"+34 944 42 48 53",
    "sg:postcode":"48011",
    "sg:province":"Vizcaya",
    "wof:name":"Mugarri 2000 S. L.",
    "wof:placetype":"venue"
},
  "geometry": {"coordinates":[-2.9435019493,43.2650299072],"type":"Point"}
}