{
  "type": "Feature",
  "properties": {
    "addr:full":"Escuelas, S/n Morales Vino Zamora 49190",
    "addr:housenumber":"s",
    "addr:postcode":"49190",
    "addr:street":"Escuelas;/ N Morales Vino Zamora",
    "iso:country":"ES",
    "sg:address":"Escuelas, S/n",
    "sg:city":"Morales Vino",
    "sg:orig_category":"Centros De Educaci\u00d3n Especial",
    "sg:phone":"+34 980 57 02 93",
    "sg:postcode":"49190",
    "sg:province":"Zamora",
    "wof:name":"Colegio Rural Agrupado De Moraleja Del Vino",
    "wof:placetype":"venue"
},
  "geometry": {"coordinates":[-5.7349591255,41.445602417],"type":"Point"}
}