{
  "type": "Feature",
  "properties": {
    "addr:full":"Ctra Tarragona, 2 Valls Tarragona 43800",
    "addr:housenumber":"2",
    "addr:postcode":"43800",
    "addr:street":"Ctra Tarragona",
    "iso:country":"ES",
    "sg:address":"Ctra Tarragona, 2",
    "sg:city":"Valls",
    "sg:orig_category":"Asociaciones, Organismos Culturales Y Socioeducativos",
    "sg:phone":"+34 977 60 45 55",
    "sg:postcode":"43800",
    "sg:province":"Tarragona",
    "wof:name":"Colla Vella Dels Xiquets De Valls",
    "wof:placetype":"venue"
},
  "geometry": {"coordinates":[1.2487510443,41.2907295227],"type":"Point"}
}