{
  "type": "Feature",
  "properties": {
    "iso:country":"ES",
    "sg:address":"Cno. Malatones, S/n",
    "sg:city":"Algete",
    "sg:orig_category":"Hormigonados",
    "sg:phone":"+34 916 28 08 86",
    "sg:postcode":"28110",
    "sg:province":"Madrid",
    "wof:name":"Hormicemex S.a.",
    "wof:placetype":"venue"
},
  "geometry": {"coordinates":[-3.5278704166,40.6085166931],"type":"Point"}
}