{
  "type": "Feature",
  "properties": {
    "addr:full":"Cami Sant Miquel, 33 Teulada Alicante 03725",
    "addr:housenumber":"33",
    "addr:postcode":"03725",
    "addr:street":"Sant Miquel",
    "iso:country":"ES",
    "sg:address":"Cami Sant Miquel, 33",
    "sg:city":"Teulada",
    "sg:orig_category":"Venta, Instalaci\u00d3n, Reparaci\u00d3n De Antenas Para Televisi\u00d3n",
    "sg:phone":"+34 965 74 08 52",
    "sg:postcode":"03725",
    "sg:province":"Alicante",
    "wof:name":"Prat Garrido Carlos Alberto",
    "wof:placetype":"venue"
},
  "geometry": {"coordinates":[0.1042950004,38.7289505005],"type":"Point"}
}