{
  "type": "Feature",
  "properties": {
    "iso:country":"ES",
    "sg:address":"Carr Republica Del Paraguai, 31",
    "sg:city":"Lleida",
    "sg:orig_category":"M\u00c9dicos: Medicina General",
    "sg:phone":"+34 973 28 26 00",
    "sg:postcode":"25002",
    "sg:province":"Lleida",
    "wof:name":"Corlleida S.l.",
    "wof:placetype":"venue"
},
  "geometry": {"coordinates":[0.6180599928,41.6109199524],"type":"Point"}
}