{
  "type": "Feature",
  "properties": {
    "iso:country":"ES",
    "sg:address":"Calle de Innovacion, 6",
    "sg:city":"Sevilla",
    "sg:orig_category":"Molduras, Junquillos, Listones Y Molduras Perforadas",
    "sg:phone":"+34 954 25 23 98",
    "sg:postcode":"41020",
    "sg:province":"Sevilla",
    "wof:name":"Pertel S Cv",
    "wof:placetype":"venue"
},
  "geometry": {"coordinates":[-5.92704916,37.4054985046],"type":"Point"}
}