{
  "type": "Feature",
  "properties": {
    "iso:country":"ES",
    "sg:address":"Carrer de Pujol, 3",
    "sg:city":"Mataro",
    "sg:orig_category":"Agencias Y Asesores De Publicidad",
    "sg:phone":"+34 937 55 31 00",
    "sg:postcode":"08301",
    "sg:province":"Barcelona",
    "sg:website":"www.mbpublicitat.com",
    "wof:name":"Bernal Nufrio Maite",
    "wof:placetype":"venue"
},
  "geometry": {"coordinates":[2.44511199,41.539352417],"type":"Point"}
}