{
  "type": "Feature",
  "properties": {
    "iso:country":"ES",
    "sg:address":"Avda Carlos Vii, 18",
    "sg:city":"Portugalete",
    "sg:orig_category":"Farmacias",
    "sg:phone":"+34 944 83 70 23",
    "sg:postcode":"48920",
    "sg:province":"Vizcaya",
    "wof:name":"Maria Calleja Y Otros C.b.",
    "wof:placetype":"venue"
},
  "geometry": {"coordinates":[-3.0224249363,43.3179626465],"type":"Point"}
}