{
  "type": "Feature",
  "properties": {
    "addr:full":"Calle de Tamarindo, 4 Getxo Vizcaya 48990",
    "addr:housenumber":"4",
    "addr:postcode":"48990",
    "addr:street":"Calle De Tamarindo",
    "iso:country":"ES",
    "sg:address":"Calle de Tamarindo, 4",
    "sg:city":"Getxo",
    "sg:orig_category":"Fisioterapia",
    "sg:phone":"+34 944 60 98 02",
    "sg:postcode":"48990",
    "sg:province":"Vizcaya",
    "sg:website":"www.espaciozen.com",
    "wof:name":"Espacio Zen Contemporaneo",
    "wof:placetype":"venue"
},
  "geometry": {"coordinates":[-3.016906023,43.3558349609],"type":"Point"}
}