{
  "type": "Feature",
  "properties": {
    "iso:country":"ES",
    "sg:address":"Calle de Valle De Oro, 16",
    "sg:city":"Madrid",
    "sg:orig_category":"Productos Qu\u00cdmicos (fabricaci\u00d3n, Al Por Mayor)",
    "sg:phone":"+34 914 72 12 68",
    "sg:postcode":"28019",
    "sg:province":"Madrid",
    "wof:name":"Roky Clean S.l.",
    "wof:placetype":"venue"
},
  "geometry": {"coordinates":[-3.7290608883,40.3878860474],"type":"Point"}
}