{
  "type": "Feature",
  "properties": {
    "addr:full":"Avda Habana (de La), 40 Ourense Ourense 32004",
    "addr:housenumber":"40",
    "addr:postcode":"32004",
    "addr:street":"Avda Habana De La",
    "iso:country":"ES",
    "sg:address":"Avda Habana (de La), 40",
    "sg:city":"Ourense",
    "sg:orig_category":"Caf\u00c9s, Bares, Cervecer\u00cdas",
    "sg:phone":"+34 988 24 74 16",
    "sg:postcode":"32004",
    "sg:province":"Ourense",
    "wof:name":"Cerveceria Y Cafeteria Moliere S.c.",
    "wof:placetype":"venue"
},
  "geometry": {"coordinates":[-7.8596291542,42.3408889771],"type":"Point"}
}