{
  "type": "Feature",
  "properties": {
    "iso:country":"ES",
    "sg:address":"Calle de Cuchilleria, 6",
    "sg:city":"Ciudad Real",
    "sg:orig_category":"Ropa Para Ni\u00d1os (al Por Menor)",
    "sg:phone":"+34 926 25 66 82",
    "sg:postcode":"13001",
    "sg:province":"Ciudad Real",
    "sg:website":"www.amichi.com",
    "wof:name":"Chamorro Prado Carmen",
    "wof:placetype":"venue"
},
  "geometry": {"coordinates":[-3.9278283119,38.985004425],"type":"Point"}
}