{
  "type": "Feature",
  "properties": {
    "addr:full":"Calle de General Ricardos, 31 Barbastro Huesca 22300",
    "addr:housenumber":"31",
    "addr:postcode":"22300",
    "addr:street":"Calle De General Ricardos",
    "iso:country":"ES",
    "sg:address":"Calle de General Ricardos, 31",
    "sg:city":"Barbastro",
    "sg:orig_category":"Ropa Para Se\u00d1oras Y Caballeros (al Por Menor)",
    "sg:phone":"+34 974 31 09 96",
    "sg:postcode":"22300",
    "sg:province":"Huesca",
    "wof:name":"Buil Lalueza Mariano",
    "wof:placetype":"venue"
},
  "geometry": {"coordinates":[0.1254159957,42.0358085632],"type":"Point"}
}