{
  "type": "Feature",
  "properties": {
    "iso:country":"ES",
    "sg:address":"Calle de Poniente, 2",
    "sg:city":"Iscar",
    "sg:orig_category":"T\u00c9cnicos Veterinarios",
    "sg:phone":"+34 983 62 04 44",
    "sg:postcode":"47420",
    "sg:province":"Valladolid",
    "wof:name":"Sanchez Cuellar Carlos",
    "wof:placetype":"venue"
},
  "geometry": {"coordinates":[-4.5391888618,41.3594284058],"type":"Point"}
}