{
  "type": "Feature",
  "properties": {
    "addr:full":"Carrer de Sant Just, 9 Santa Coloma De Gramenet Barcelona 08922",
    "addr:housenumber":"9",
    "addr:postcode":"08922",
    "addr:street":"Carrer De Sant Just",
    "iso:country":"ES",
    "sg:address":"Carrer de Sant Just, 9",
    "sg:city":"Santa Coloma De Gramenet",
    "sg:orig_category":"Zapatos (al Por Menor)",
    "sg:phone":"+34 934 66 13 34",
    "sg:postcode":"08922",
    "sg:province":"Barcelona",
    "wof:name":"Morilla Cuello Jose Luis",
    "wof:placetype":"venue"
},
  "geometry": {"coordinates":[2.2113969326,41.4475517273],"type":"Point"}
}