{
  "type": "Feature",
  "properties": {
    "addr:full":"Luga Poligono 42, 558 Llucmajor Islas Baleares 07620",
    "addr:housenumber":"558",
    "addr:postcode":"07620",
    "addr:street":"Poligono 42",
    "iso:country":"ES",
    "sg:address":"Luga Poligono 42, 558",
    "sg:city":"Llucmajor",
    "sg:orig_category":"Aeropuertos Y Servicios Aeroportuarios",
    "sg:phone":"+34 902 40 15 01",
    "sg:postcode":"07620",
    "sg:province":"Islas Baleares",
    "sg:website":"www.air-europa.com",
    "wof:name":"Aireuropa Lineas Aereas S.a.",
    "wof:placetype":"venue"
},
  "geometry": {"coordinates":[2.8377656937,39.4312438965],"type":"Point"}
}