{
  "type": "Feature",
  "properties": {
    "iso:country":"ES",
    "sg:address":"Calle de Emigrantes, 14",
    "sg:city":"Madrid",
    "sg:orig_category":"Abogados",
    "sg:phone":"+34 913 00 53 09",
    "sg:postcode":"28043",
    "sg:province":"Madrid",
    "wof:name":"Mylsa Multigestion Asesores S.l.",
    "wof:placetype":"venue"
},
  "geometry": {"coordinates":[-3.6368160248,40.4674987793],"type":"Point"}
}