{
  "type": "Feature",
  "properties": {
    "iso:country":"ES",
    "sg:address":"Carrer de Balaguer, 5",
    "sg:city":"Sabadell",
    "sg:classifiers":[
        {
            "category":"Autos & Motor Vehicles",
            "subcategory":"Automobile Sales",
            "type":"Retail Goods"
        }
    ],
    "sg:phone":"+34 937 16 46 83",
    "sg:postcode":"08207",
    "sg:province":"Barcelona",
    "wof:name":"Autoescola Arisa S.c.p.",
    "wof:placetype":"venue"
},
  "geometry": {"coordinates":[2.0911099911,41.5640792847],"type":"Point"}
}