{
  "type": "Feature",
  "properties": {
    "addr:full":"Carrer de Moli, 72 Barcelona Barcelona 08016",
    "addr:housenumber":"72",
    "addr:postcode":"08016",
    "addr:street":"Carrer De Moli",
    "iso:country":"ES",
    "sg:address":"Carrer de Moli, 72",
    "sg:city":"Barcelona",
    "sg:orig_category":"Carnicer\u00cdas, Carnicer\u00cdas",
    "sg:phone":"+34 933 50 27 96",
    "sg:postcode":"08016",
    "sg:province":"Barcelona",
    "wof:name":"Raso Puyol Jose Antonio",
    "wof:placetype":"venue"
},
  "geometry": {"coordinates":[2.1811571121,41.444355011],"type":"Point"}
}