{
  "type": "Feature",
  "properties": {
    "iso:country":"ES",
    "sg:address":"Calle de Hermosilla, 126",
    "sg:city":"Madrid",
    "sg:orig_category":"M\u00c9dicos: An\u00c1lisis Cl\u00cdnicos",
    "sg:phone":"+34 914 31 85 02",
    "sg:postcode":"28028",
    "sg:province":"Madrid",
    "wof:name":"Instituto Jimenez Ayala S.l.",
    "wof:placetype":"venue"
},
  "geometry": {"coordinates":[-3.6679580212,40.4253730774],"type":"Point"}
}