{
  "type": "Feature",
  "properties": {
    "iso:country":"ES",
    "sg:address":"San Martin Agirre Plaza, S/n",
    "sg:city":"Bergara",
    "sg:orig_category":"Librer\u00cdas",
    "sg:phone":"+34 943 76 53 01",
    "sg:postcode":"20570",
    "sg:province":"Guip\u00f9zcoa",
    "sg:website":"www.uned.es",
    "wof:name":"Universidad Nacional De Educacion A Distancia",
    "wof:placetype":"venue"
},
  "geometry": {"coordinates":[-2.4134049416,43.1173286438],"type":"Point"}
}