{
  "type": "Feature",
  "properties": {
    "iso:country":"ES",
    "sg:address":"Calle de Santa Maria De Ordas, 12",
    "sg:city":"Sevilla",
    "sg:orig_category":"Molduras, Junquillos, Listones Y Molduras Perforadas",
    "sg:phone":"+34 954 35 30 90",
    "sg:postcode":"41008",
    "sg:province":"Sevilla",
    "wof:name":"United Services S.l.",
    "wof:placetype":"venue"
},
  "geometry": {"coordinates":[-5.9743108749,37.4038124084],"type":"Point"}
}