{
  "type": "Feature",
  "properties": {
    "addr:full":"Carrer de Biscaia, 4 S. Boi Llobregat Barcelona 08830",
    "addr:housenumber":"4",
    "addr:postcode":"08830",
    "addr:street":"Carrer De Biscaia",
    "iso:country":"ES",
    "sg:address":"Carrer de Biscaia, 4",
    "sg:city":"S. Boi Llobregat",
    "sg:orig_category":"Cristaler\u00cdas",
    "sg:phone":"+34 936 54 10 12",
    "sg:postcode":"08830",
    "sg:province":"Barcelona",
    "wof:name":"Cristaleria Tama S.l.",
    "wof:placetype":"venue"
},
  "geometry": {"coordinates":[2.0403780937,41.3282394409],"type":"Point"}
}