{
  "type": "Feature",
  "properties": {
    "iso:country":"ES",
    "sg:address":"Calle de Joaquin Costa, 2",
    "sg:city":"Zaragoza",
    "sg:orig_category":"Asesor\u00cda Sobre Comunicaci\u00d3n De Empresas",
    "sg:phone":"+34 976 22 95 22",
    "sg:postcode":"50001",
    "sg:province":"Zaragoza",
    "wof:name":"Teca Consultores S.a.",
    "wof:placetype":"venue"
},
  "geometry": {"coordinates":[-0.8824471235,41.6491470337],"type":"Point"}
}