{
  "type": "Feature",
  "properties": {
    "addr:full":"Calle de Imeldo Seris, 64 Santa Cruz De Tenerife Santa Cruz De Tenerife 38003",
    "addr:housenumber":"64",
    "addr:postcode":"38003",
    "addr:street":"Calle De Imeldo Seris",
    "iso:country":"ES",
    "sg:address":"Calle de Imeldo Seris, 64",
    "sg:city":"Santa Cruz De Tenerife",
    "sg:orig_category":"Bazares, Art\u00cdculos De Limpieza Y De Cocina (al Por Menor)",
    "sg:phone":"+34 922 24 62 97",
    "sg:postcode":"38003",
    "sg:province":"Santa Cruz De Tenerife",
    "wof:name":"Mehtani  Ashok Kumar",
    "wof:placetype":"venue"
},
  "geometry": {"coordinates":[-16.2514801025,28.4664878845],"type":"Point"}
}