{
  "type": "Feature",
  "properties": {
    "iso:country":"ES",
    "sg:address":"Calle de Gaiteros De Caserras, S/n",
    "sg:city":"Graus",
    "sg:orig_category":"Asilos De Ancianos. Centros Privados",
    "sg:phone":"+34 974 54 08 26",
    "sg:postcode":"22430",
    "sg:province":"Huesca",
    "wof:name":"Fundacion Municipal Centro Tercera Edad",
    "wof:placetype":"venue"
},
  "geometry": {"coordinates":[0.3357340991,42.1902503967],"type":"Point"}
}