{
  "type": "Feature",
  "properties": {
    "iso:country":"ES",
    "sg:address":"Calle de Moreras, 2",
    "sg:city":"Majadahonda",
    "sg:orig_category":"Zapatos (al Por Menor)",
    "sg:phone":"+34 916 38 53 33",
    "sg:postcode":"28220",
    "sg:province":"Madrid",
    "sg:website":"www.elarmadillo.com",
    "wof:name":"The Brown Armadillo S.l.",
    "wof:placetype":"venue"
},
  "geometry": {"coordinates":[-3.861030817,40.4593772888],"type":"Point"}
}