{
  "type": "Feature",
  "properties": {
    "addr:full":"Calle de Alferez Manuel Casado, 1 Porcuna Ja\u00e9n 23790",
    "addr:housenumber":"1",
    "addr:postcode":"23790",
    "addr:street":"Calle De Alferez Manuel Casado",
    "iso:country":"ES",
    "sg:address":"Calle de Alferez Manuel Casado, 1",
    "sg:city":"Porcuna",
    "sg:orig_category":"Ingeniero",
    "sg:phone":"+34 953 54 46 13",
    "sg:postcode":"23790",
    "sg:province":"Ja\u00e9n",
    "wof:name":"Molina Salas Manuel Luis",
    "wof:placetype":"venue"
},
  "geometry": {"coordinates":[-4.1843538284,37.869392395],"type":"Point"}
}