{
  "type": "Feature",
  "properties": {
    "addr:full":"Rua Benito Corbal, 15 Pontevedra Pontevedra 36001",
    "addr:housenumber":"15",
    "addr:postcode":"36001",
    "addr:street":"Rua Benito Corbal",
    "iso:country":"ES",
    "sg:address":"Rua Benito Corbal, 15",
    "sg:city":"Pontevedra",
    "sg:orig_category":"M\u00c9dicos: Estomatolog\u00cda",
    "sg:phone":"+34 986 86 57 78",
    "sg:postcode":"36001",
    "sg:province":"Pontevedra",
    "wof:name":"Landeiro Aller Pablo",
    "wof:placetype":"venue"
},
  "geometry": {"coordinates":[-8.641960144,42.4304122925],"type":"Point"}
}