{
  "type": "Feature",
  "properties": {
    "iso:country":"ES",
    "sg:address":"Avda Juan Carlos I, 3",
    "sg:city":"Ibi",
    "sg:orig_category":"Molduras, Junquillos, Listones Y Molduras Perforadas",
    "sg:phone":"+34 966 55 20 32",
    "sg:postcode":"03440",
    "sg:province":"Alicante",
    "wof:name":"Casta\u00f1o Aranega Antonio",
    "wof:placetype":"venue"
},
  "geometry": {"coordinates":[-0.5696169734,38.6251945496],"type":"Point"}
}