{
  "type": "Feature",
  "properties": {
    "addr:full":"Ctra Caravaca, 40 Moratalla Murcia 30440",
    "addr:housenumber":"40",
    "addr:postcode":"30440",
    "addr:street":"Ctra Caravaca",
    "iso:country":"ES",
    "sg:address":"Ctra Caravaca, 40",
    "sg:city":"Moratalla",
    "sg:orig_category":"Venta, Montaje De Neum\u00c1ticos",
    "sg:phone":"+34 968 73 00 22",
    "sg:postcode":"30440",
    "sg:province":"Murcia",
    "wof:name":"Sanchez Martinez Juan Domingo",
    "wof:placetype":"venue"
},
  "geometry": {"coordinates":[-1.8907849789,38.1828155518],"type":"Point"}
}