{
  "type": "Feature",
  "properties": {
    "addr:full":"Calle de Maria Auxiliadora, 8 Salamanca Salamanca 37004",
    "addr:housenumber":"8",
    "addr:postcode":"37004",
    "addr:street":"Calle De Maria Auxiliadora",
    "iso:country":"ES",
    "sg:address":"Calle de Maria Auxiliadora, 8",
    "sg:city":"Salamanca",
    "sg:orig_category":"Tintes (fabricaci\u00d3n, Al Por Mayor)",
    "sg:phone":"+34 923 22 51 45",
    "sg:postcode":"37004",
    "sg:province":"Salamanca",
    "wof:name":"Cornejo Colella Pedro",
    "wof:placetype":"venue"
},
  "geometry": {"coordinates":[-5.6590800285,40.9693336487],"type":"Point"}
}