{
  "type": "Feature",
  "properties": {
    "iso:country":"ES",
    "sg:address":"Calle de Doctor Fleming, 4",
    "sg:city":"Churra",
    "sg:orig_category":"Escuelas De Maternidad P\u00dablicas",
    "sg:phone":"+34 968 30 70 80",
    "sg:postcode":"30110",
    "sg:province":"Murcia",
    "wof:name":"Escuela Infantil Reyes Magos",
    "wof:placetype":"venue"
},
  "geometry": {"coordinates":[-1.1366269588,38.0218505859],"type":"Point"}
}