{
  "type": "Feature",
  "properties": {
    "iso:country":"ES",
    "sg:address":"Carrer de Papa Pius Xi, 20",
    "sg:city":"Sabadell",
    "sg:orig_category":"Abogados",
    "sg:phone":"+34 937 45 07 36",
    "sg:postcode":"08208",
    "sg:province":"Barcelona",
    "wof:name":"Moreno Castillon Ferran",
    "wof:placetype":"venue"
},
  "geometry": {"coordinates":[2.1049931049,41.5521430969],"type":"Point"}
}