{
  "type": "Feature",
  "properties": {
    "iso:country":"ES",
    "sg:address":"Carr Mestral, 20",
    "sg:city":"Carlet",
    "sg:orig_category":"Perfumer\u00cda Y Cosm\u00c9tica (fabricaci\u00d3n, Al Por Mayor)",
    "sg:phone":"+34 962 53 10 46",
    "sg:postcode":"46240",
    "sg:province":"Valencia",
    "wof:name":"Madelsa Iberica S.l.",
    "wof:placetype":"venue"
},
  "geometry": {"coordinates":[-0.4866960049,39.2378845215],"type":"Point"}
}