{
  "type": "Feature",
  "properties": {
    "iso:country":"ES",
    "sg:address":"Calle de Sol, 2",
    "sg:city":"Alquerias",
    "sg:orig_category":"Artes Gr\u00c1ficas, Artes Pl\u00c1sticas: Material Y Suministros (al Por Menor)",
    "sg:phone":"+34 968 87 21 84",
    "sg:postcode":"30580",
    "sg:province":"Murcia",
    "wof:name":"Impermeabilizaciones Cortes S L",
    "wof:placetype":"venue"
},
  "geometry": {"coordinates":[-1.0397109985,38.013469696],"type":"Point"}
}