{
  "type": "Feature",
  "properties": {
    "addr:full":"Calle de Aribayos, 20 Moraleja Vino Zamora 49150",
    "addr:housenumber":"20",
    "addr:postcode":"49150",
    "addr:street":"Calle De Aribayos;Zamora",
    "iso:country":"ES",
    "sg:address":"Calle de Aribayos, 20",
    "sg:city":"Moraleja Vino",
    "sg:orig_category":"Electricidad (montaje, Ensamblaje De Componentes)",
    "sg:phone":"+34 980 57 10 31",
    "sg:postcode":"49150",
    "sg:province":"Zamora",
    "wof:name":"Bautista Perez Angel",
    "wof:placetype":"venue"
},
  "geometry": {"coordinates":[-5.6542539597,41.4596061707],"type":"Point"}
}