{
  "type": "Feature",
  "properties": {
    "iso:country":"ES",
    "sg:address":"Calle de Santiago Gallego, 22",
    "sg:city":"Tarancon",
    "sg:orig_category":"Delegados, Agentes De Tr\u00c1nsito, Auxiliares De Transporte Internacional",
    "sg:phone":"+34 969 32 26 55",
    "sg:postcode":"16400",
    "sg:province":"Cuenca",
    "wof:name":"Regidor Yunta Jose",
    "wof:placetype":"venue"
},
  "geometry": {"coordinates":[-3.019313097,40.0142326355],"type":"Point"}
}