{
  "type": "Feature",
  "properties": {
    "addr:full":"Pg Sant Joan, 1 Barcelona Barcelona 08010",
    "addr:housenumber":"1",
    "addr:postcode":"08010",
    "addr:street":"Pg Sant Joan",
    "iso:country":"ES",
    "sg:address":"Pg Sant Joan, 1",
    "sg:city":"Barcelona",
    "sg:orig_category":"Cajas De Ahorro",
    "sg:phone":"+34 932 31 08 06",
    "sg:postcode":"08010",
    "sg:province":"Barcelona",
    "wof:name":"Caixa D'estalvis I Pensions De Barcelona",
    "wof:placetype":"venue"
},
  "geometry": {"coordinates":[2.1796939373,41.3916244507],"type":"Point"}
}