{
  "type": "Feature",
  "properties": {
    "addr:full":"Sect Literatos, 13 Tres Cantos Madrid 28760",
    "addr:housenumber":"13",
    "addr:postcode":"28760",
    "addr:street":"Literatos",
    "iso:country":"ES",
    "sg:address":"Sect Literatos, 13",
    "sg:city":"Tres Cantos",
    "sg:orig_category":"Abogados",
    "sg:phone":"+34 918 03 01 88",
    "sg:postcode":"28760",
    "sg:province":"Madrid",
    "wof:name":"Casta\u00f1eira Fernandez Juan",
    "wof:placetype":"venue"
},
  "geometry": {"coordinates":[-3.7114059925,40.6071891785],"type":"Point"}
}