{
  "type": "Feature",
  "properties": {
    "iso:country":"ES",
    "sg:address":"Calle de Maria Goiri, 14",
    "sg:city":"Algorta",
    "sg:orig_category":"Locales Y Clases De Danza",
    "sg:phone":"+34 944 60 75 11",
    "sg:postcode":"48993",
    "sg:province":"Vizcaya",
    "wof:name":"Lara Fernandez Ana Maria",
    "wof:placetype":"venue"
},
  "geometry": {"coordinates":[-3.0106852055,43.353969574],"type":"Point"}
}