{
  "type": "Feature",
  "properties": {
    "iso:country":"ES",
    "sg:address":"Calle de Caverina, 29",
    "sg:city":"Calasparra",
    "sg:orig_category":"Alimentaci\u00d3n General (al Por Mayor)",
    "sg:phone":"+34 968 72 06 46",
    "sg:postcode":"30420",
    "sg:province":"Murcia",
    "wof:name":"Valero Garcia Angel",
    "wof:placetype":"venue"
},
  "geometry": {"coordinates":[-1.7027845383,38.2327156067],"type":"Point"}
}