{
  "type": "Feature",
  "properties": {
    "addr:full":"Pase Arboleda, S/n Monzon Huesca 22400",
    "addr:housenumber":"s / n",
    "addr:postcode":"22400",
    "addr:street":"Arboleda",
    "iso:country":"ES",
    "sg:address":"Pase Arboleda, S/n",
    "sg:city":"Monzon",
    "sg:orig_category":"Mataderos Y Talleres De Despiezado",
    "sg:phone":"+34 974 34 90 90",
    "sg:postcode":"22400",
    "sg:province":"Huesca",
    "wof:name":"Matadero Del Cinca S.a.",
    "wof:placetype":"venue"
},
  "geometry": {"coordinates":[0.1841550022,41.9114952087],"type":"Point"}
}