{
  "type": "Feature",
  "properties": {
    "addr:full":"Plaz Constitucion (de La), 6 Barraco \u00c1vila 05110",
    "addr:housenumber":"6",
    "addr:postcode":"05110",
    "addr:street":"Barraco A\u0301Vila",
    "iso:country":"ES",
    "sg:address":"Plaz Constitucion (de La), 6",
    "sg:city":"Barraco",
    "sg:orig_category":"Cajas De Ahorro",
    "sg:phone":"+34 920 28 10 19",
    "sg:postcode":"05110",
    "sg:province":"\u00c1vila",
    "wof:name":"Caja De Avila",
    "wof:placetype":"venue"
},
  "geometry": {"coordinates":[-4.6433930397,40.4770393372],"type":"Point"}
}