{
  "type": "Feature",
  "properties": {
    "iso:country":"ES",
    "sg:address":"Calle de Eguia General, 7",
    "sg:city":"Bilbao",
    "sg:orig_category":"Impuestos, Tesoro P\u00dablico",
    "sg:phone":"+34 944 70 18 86",
    "sg:postcode":"48010",
    "sg:province":"Vizcaya",
    "wof:name":"Tasatec S.l.",
    "wof:placetype":"venue"
},
  "geometry": {"coordinates":[-2.9462141991,43.2592010498],"type":"Point"}
}