{
  "type": "Feature",
  "properties": {
    "addr:full":"Avda Ramon Y Cajal, 110 Sevilla Sevilla 41005",
    "addr:housenumber":"110",
    "addr:postcode":"41005",
    "addr:street":"Avda Ramon Y Cajal",
    "iso:country":"ES",
    "sg:address":"Avda Ramon Y Cajal, 110",
    "sg:city":"Sevilla",
    "sg:orig_category":"Cr\u00cda De Animales",
    "sg:phone":"+34 954 92 40 10",
    "sg:postcode":"41005",
    "sg:province":"Sevilla",
    "wof:name":"Instituto Veterinario Fausto Cabrera S.l.",
    "wof:placetype":"venue"
},
  "geometry": {"coordinates":[-5.9660601616,37.3743972778],"type":"Point"}
}