{
  "type": "Feature",
  "properties": {
    "iso:country":"ES",
    "sg:address":"Calle de Bolta\u00d1a, 57",
    "sg:city":"Madrid",
    "sg:orig_category":"Molduras, Junquillos, Listones Y Molduras Perforadas",
    "sg:phone":"+34 913 20 23 82",
    "sg:postcode":"28022",
    "sg:province":"Madrid",
    "wof:name":"Rios Bermejo Lorenzo",
    "wof:placetype":"venue"
},
  "geometry": {"coordinates":[-3.6096556187,40.4476165771],"type":"Point"}
}