{
  "type": "Feature",
  "properties": {
    "addr:full":"Trav De Gracia, 449 Barcelona Barcelona 08025",
    "addr:housenumber":"449",
    "addr:postcode":"08025",
    "addr:street":"Trav De Gracia",
    "iso:country":"ES",
    "sg:address":"Trav De Gracia, 449",
    "sg:city":"Barcelona",
    "sg:orig_category":"V\u00cddeo (producci\u00d3n Y Realizaci\u00d3n)",
    "sg:phone":"+34 934 33 11 12",
    "sg:postcode":"08025",
    "sg:province":"Barcelona",
    "wof:name":"Monitor Video S.l.",
    "wof:placetype":"venue"
},
  "geometry": {"coordinates":[2.1738400459,41.4115791321],"type":"Point"}
}