{
  "type": "Feature",
  "properties": {
    "addr:full":"Avda Atlantico Del, 295 Vecindario Las Palmas 35110",
    "addr:housenumber":"295",
    "addr:postcode":"35110",
    "addr:street":"Avda Atlantico Del;Palmas",
    "iso:country":"ES",
    "sg:address":"Avda Atlantico Del, 295",
    "sg:city":"Vecindario",
    "sg:orig_category":"Caf\u00c9s, Bares, Cervecer\u00cdas",
    "sg:phone":"+34 928 17 21 18",
    "sg:postcode":"35110",
    "sg:province":"Las Palmas",
    "wof:name":"Copas Parawuan S.l.",
    "wof:placetype":"venue"
},
  "geometry": {"coordinates":[-15.4373636246,27.8569469452],"type":"Point"}
}