{
  "type": "Feature",
  "properties": {
    "addr:full":"Ctra Girona, 56 S. Feliu Guixols Girona 17220",
    "addr:housenumber":"56",
    "addr:postcode":"17220",
    "addr:street":"Ctra Girona;S. Feliu Guixols",
    "iso:country":"ES",
    "sg:address":"Ctra Girona, 56",
    "sg:city":"S. Feliu Guixols",
    "sg:orig_category":"Cueros Y Pieles (al Por Mayor)",
    "sg:phone":"+34 972 32 10 91",
    "sg:postcode":"17220",
    "sg:province":"Girona",
    "wof:name":"Martinez Garcia Trinidad",
    "wof:placetype":"venue"
},
  "geometry": {"coordinates":[3.0308470726,41.7839393616],"type":"Point"}
}