{
  "type": "Feature",
  "properties": {
    "addr:full":"Calle de Racial, 1 Santillana Cantabria 39330",
    "addr:housenumber":"1",
    "addr:postcode":"39330",
    "addr:street":"Calle De Racial",
    "iso:country":"ES",
    "sg:address":"Calle de Racial, 1",
    "sg:city":"Santillana",
    "sg:orig_category":"Fabricaci\u00d3n De Productos L\u00c1cteos Y Derivados",
    "sg:phone":"+34 942 84 01 48",
    "sg:postcode":"39330",
    "sg:province":"Cantabria",
    "wof:name":"Sanchez Caviedes Maria Luz",
    "wof:placetype":"venue"
},
  "geometry": {"coordinates":[-4.10729599,43.3913383484],"type":"Point"}
}