{
  "type": "Feature",
  "properties": {
    "addr:full":"Calle de Martinez De Leon, 1 Coria Rio Sevilla 41100",
    "addr:housenumber":"1",
    "addr:postcode":"41100",
    "addr:street":"Calle De Martinez De Leon;Rio Sevilla",
    "iso:country":"ES",
    "sg:address":"Calle de Martinez De Leon, 1",
    "sg:city":"Coria Rio",
    "sg:orig_category":"Mercer\u00cda, Lencer\u00cda (al Por Menor)",
    "sg:phone":"+34 954 77 68 29",
    "sg:postcode":"41100",
    "sg:province":"Sevilla",
    "wof:name":"Guisasola Ferrari Josefa",
    "wof:placetype":"venue"
},
  "geometry": {"coordinates":[-6.0508179665,37.2841262817],"type":"Point"}
}