{
  "type": "Feature",
  "properties": {
    "iso:country":"ES",
    "sg:address":"Calle de San Fernando, 23",
    "sg:city":"Utiel",
    "sg:orig_category":"Peluqueros: De Se\u00d1oras",
    "sg:phone":"+34 962 17 02 91",
    "sg:postcode":"46300",
    "sg:province":"Valencia",
    "wof:name":"Rodriguez Torres Tomas",
    "wof:placetype":"venue"
},
  "geometry": {"coordinates":[-1.202483058,39.56665802],"type":"Point"}
}