{
  "type": "Feature",
  "properties": {
    "iso:country":"ES",
    "sg:address":"Rua Rio Lambre, 12",
    "sg:city":"Ferrol",
    "sg:orig_category":"Abogados",
    "sg:phone":"+34 981 32 65 94",
    "sg:postcode":"15403",
    "sg:province":"La Coru\u00f1a",
    "wof:name":"Accion Lopez German",
    "wof:placetype":"venue"
},
  "geometry": {"coordinates":[-8.2265329361,43.4895362854],"type":"Point"}
}