{
  "type": "Feature",
  "properties": {
    "iso:country":"ES",
    "sg:address":"Calle de Constitucion, 10",
    "sg:city":"Pastriz",
    "sg:orig_category":"Compresores",
    "sg:phone":"+34 976 58 30 50",
    "sg:postcode":"50195",
    "sg:province":"Zaragoza",
    "wof:name":"Mulser S. A.",
    "wof:placetype":"venue"
},
  "geometry": {"coordinates":[-0.7833105922,41.6202163696],"type":"Point"}
}