{
  "type": "Feature",
  "properties": {
    "addr:full":"Avda Hermanos Bou, 102 Castellon Castell\u00f3n 12003",
    "addr:housenumber":"102",
    "addr:postcode":"12003",
    "addr:street":"Avda Hermanos Bou;Castello\u0301N",
    "iso:country":"ES",
    "sg:address":"Avda Hermanos Bou, 102",
    "sg:city":"Castellon",
    "sg:orig_category":"Venta, Instalaci\u00d3n De Calefacci\u00d3n",
    "sg:phone":"+34 964 25 24 81",
    "sg:postcode":"12003",
    "sg:province":"Castell\u00f3n",
    "wof:name":"Fluicas S.l.",
    "wof:placetype":"venue"
},
  "geometry": {"coordinates":[-0.0077,39.9836883545],"type":"Point"}
}