{
  "type": "Feature",
  "properties": {
    "iso:country":"ES",
    "sg:address":"Ctra. Madrid(poligono), S/n",
    "sg:city":"Valdelafuente",
    "sg:orig_category":"Venta, Localizaci\u00d3n, Reparaci\u00d3n De Material E Instrumental M\u00c9dico",
    "sg:phone":"+34 987 84 97 50",
    "sg:postcode":"24227",
    "sg:province":"Le\u00f3n",
    "wof:name":"Laboratorios Affar S.a.",
    "wof:placetype":"venue"
},
  "geometry": {"coordinates":[-5.5140891075,42.5692138672],"type":"Point"}
}