{
  "type": "Feature",
  "properties": {
    "iso:country":"ES",
    "sg:address":"Ctra Sevilla, 343",
    "sg:city":"Antequera",
    "sg:orig_category":"Reposter\u00cdas",
    "sg:phone":"+34 952 70 67 49",
    "sg:postcode":"29200",
    "sg:province":"M\u00e1laga",
    "wof:name":"Grupo Mariraje Andaluz De La Costa Del Sol 2004",
    "wof:placetype":"venue"
},
  "geometry": {"coordinates":[-4.5512628555,37.0212631226],"type":"Point"}
}