{
  "type": "Feature",
  "properties": {
    "addr:full":"Carrer de Uva, 34 Hospitalet Llobregat Barcelona 08902",
    "addr:housenumber":"34",
    "addr:postcode":"08902",
    "addr:street":"Carrer De Uva",
    "iso:country":"ES",
    "sg:address":"Carrer de Uva, 34",
    "sg:city":"Hospitalet Llobregat",
    "sg:orig_category":"Papel (al Por Mayor)",
    "sg:phone":"+34 934 31 44 30",
    "sg:postcode":"08902",
    "sg:province":"Barcelona",
    "wof:name":"Roldan Sabio Maria Isabel",
    "wof:placetype":"venue"
},
  "geometry": {"coordinates":[2.125164032,41.3634338379],"type":"Point"}
}