{
  "type": "Feature",
  "properties": {
    "iso:country":"ES",
    "sg:address":"Ctra Madrid-irun(oeste), Km. 0160,6",
    "sg:city":"Aranda Duero",
    "sg:orig_category":"Chapister\u00cda",
    "sg:phone":"+34 947 51 04 00",
    "sg:postcode":"09400",
    "sg:province":"Burgos",
    "wof:name":"Autocastilla-chapa S.l.",
    "wof:placetype":"venue"
},
  "geometry": {"coordinates":[-3.6997311115,42.3408737183],"type":"Point"}
}