{
  "type": "Feature",
  "properties": {
    "addr:full":"Carr Caminas, 71 Pu\u00e7ol Valencia 46530",
    "addr:housenumber":"71",
    "addr:postcode":"46530",
    "addr:street":"Carr Caminas",
    "iso:country":"ES",
    "sg:address":"Carr Caminas, 71",
    "sg:city":"Pu\u00e7ol",
    "sg:orig_category":"\u00d3ptica: Instrumentos (fabricaci\u00d3n)",
    "sg:phone":"+34 961 46 52 88",
    "sg:postcode":"46530",
    "sg:province":"Valencia",
    "wof:name":"Montalt Rodrigo Juan Carlos",
    "wof:placetype":"venue"
},
  "geometry": {"coordinates":[-0.3008790016,39.6156044006],"type":"Point"}
}