{
  "type": "Feature",
  "properties": {
    "addr:full":"Calle de Miguel De Benavides (de), 11 Palencia Palencia 34003",
    "addr:housenumber":"11",
    "addr:postcode":"34003",
    "addr:street":"Calle De Miguel De Benavides De",
    "iso:country":"ES",
    "sg:address":"Calle de Miguel De Benavides (de), 11",
    "sg:city":"Palencia",
    "sg:orig_category":"Promotores Constructores",
    "sg:phone":"+34 979 74 15 57",
    "sg:postcode":"34003",
    "sg:province":"Palencia",
    "wof:name":"Campillo Garcia Luciano",
    "wof:placetype":"venue"
},
  "geometry": {"coordinates":[-4.5300621986,42.0205001831],"type":"Point"}
}