{
  "type": "Feature",
  "properties": {
    "addr:full":"Carrer de Santes Creus, Km. 0001,0 Tarragona Tarragona 43003",
    "addr:postcode":"43003",
    "addr:street":"Carrer De;Creus Km. 0001,0",
    "iso:country":"ES",
    "sg:address":"Carrer de Santes Creus, Km. 0001,0",
    "sg:city":"Tarragona",
    "sg:orig_category":"Quincaller\u00cda (al Por Menor)",
    "sg:phone":"+34 977 25 23 75",
    "sg:postcode":"43003",
    "sg:province":"Tarragona",
    "wof:name":"Ferreteria Industrial Anguela S.a.",
    "wof:placetype":"venue"
},
  "geometry": {"coordinates":[1.2597290277,41.1183624268],"type":"Point"}
}