{
  "type": "Feature",
  "properties": {
    "iso:country":"ES",
    "sg:address":"Avda Sants De La Pedra, 49",
    "sg:city":"Sagunt",
    "sg:orig_category":"Molduras, Junquillos, Listones Y Molduras Perforadas",
    "sg:phone":"+34 962 66 49 09",
    "sg:postcode":"46500",
    "sg:province":"Valencia",
    "wof:name":"Andres Romero Jose Pedro",
    "wof:placetype":"venue"
},
  "geometry": {"coordinates":[-0.2749493122,39.6816177368],"type":"Point"}
}