{
  "type": "Feature",
  "properties": {
    "addr:full":"Compl Las Palmeras, S/n Fuengirola M\u00e1laga 29640",
    "addr:housenumber":"s / n",
    "addr:postcode":"29640",
    "addr:street":"Ma\u0301Laga",
    "iso:country":"ES",
    "sg:address":"Compl Las Palmeras, S/n",
    "sg:city":"Fuengirola",
    "sg:orig_category":"Estilistas Y Estudios De Estilo De Corte Y Confecci\u00d3n",
    "sg:phone":"+34 952 46 89 04",
    "sg:postcode":"29640",
    "sg:province":"M\u00e1laga",
    "wof:name":"Jaime Moreno Roman",
    "wof:placetype":"venue"
},
  "geometry": {"coordinates":[-4.6239790916,36.5414886475],"type":"Point"}
}