{
  "type": "Feature",
  "properties": {
    "addr:full":"Calle de Rafael Tilve Adrio, 10 Esfarrapada Pontevedra 36470",
    "addr:housenumber":"10",
    "addr:postcode":"36470",
    "addr:street":"Calle De Rafael Tilve Adrio",
    "iso:country":"ES",
    "sg:address":"Calle de Rafael Tilve Adrio, 10",
    "sg:city":"Esfarrapada",
    "sg:orig_category":"Suministros Y Materiales Industriales",
    "sg:phone":"+34 986 34 97 04",
    "sg:postcode":"36470",
    "sg:province":"Pontevedra",
    "wof:name":"Suministros Y Mantenimientos Costas S.l.",
    "wof:placetype":"venue"
},
  "geometry": {"coordinates":[-8.5608234406,42.1009101868],"type":"Point"}
}