{
  "type": "Feature",
  "properties": {
    "addr:full":"Avda Caidos, 183 Coru\u00d1a La Coru\u00f1a 15009",
    "addr:housenumber":"183",
    "addr:postcode":"15009",
    "addr:street":"Avda Caidos;La Corun\u0303A",
    "iso:country":"ES",
    "sg:address":"Avda Caidos, 183",
    "sg:city":"Coru\u00d1a",
    "sg:orig_category":"Pescader\u00cdas (al Por Menor)",
    "sg:phone":"+34 981 13 01 31",
    "sg:postcode":"15009",
    "sg:province":"La Coru\u00f1a",
    "wof:name":"Lourera Bello Pilar",
    "wof:placetype":"venue"
},
  "geometry": {"coordinates":[-8.3992347717,43.3475799561],"type":"Point"}
}