{
  "type": "Feature",
  "properties": {
    "addr:full":"Alto, 3 Fornillos Fermoselle Zamora 49232",
    "addr:housenumber":"3",
    "addr:postcode":"49232",
    "addr:street":"Alto",
    "iso:country":"ES",
    "sg:address":"Alto, 3",
    "sg:city":"Fornillos Fermoselle",
    "sg:orig_category":"Cr\u00cda De Animales",
    "sg:phone":"+34 980 61 29 14",
    "sg:postcode":"49232",
    "sg:province":"Zamora",
    "wof:name":"Cortes Fernandez Jesus",
    "wof:placetype":"venue"
},
  "geometry": {"coordinates":[-6.328745842,41.364238739],"type":"Point"}
}