{
  "type": "Feature",
  "properties": {
    "iso:country":"ES",
    "sg:address":"Rbla Guipuscoa, 137",
    "sg:city":"Barcelona",
    "sg:orig_category":"Inform\u00c1tica, Ofim\u00c1tica (estudios, Asesor\u00cda, Ingenier\u00cda, Formaci\u00d3n)",
    "sg:phone":"+34 933 13 39 49",
    "sg:postcode":"08020",
    "sg:province":"Barcelona",
    "wof:name":"Espina Mas Juan",
    "wof:placetype":"venue"
},
  "geometry": {"coordinates":[2.204253912,41.4219779968],"type":"Point"}
}