{
  "type": "Feature",
  "properties": {
    "addr:full":"Avda Pedro Mu\u00d1oz Seca, 116 Campillo Del Moro Almer\u00eda 04720",
    "addr:housenumber":"116",
    "addr:postcode":"04720",
    "addr:street":"Avda Pedro Mun\u0303Oz Seca",
    "iso:country":"ES",
    "sg:address":"Avda Pedro Mu\u00d1oz Seca, 116",
    "sg:city":"Campillo Del Moro",
    "sg:orig_category":"Peluquer\u00cdas, Peluquer\u00cda Mixta",
    "sg:phone":"+34 950 34 76 81",
    "sg:postcode":"04720",
    "sg:province":"Almer\u00eda",
    "wof:name":"Hernandez Navarro Raquel",
    "wof:placetype":"venue"
},
  "geometry": {"coordinates":[-2.5811207294,36.8174247742],"type":"Point"}
}