{
  "type": "Feature",
  "properties": {
    "iso:country":"ES",
    "sg:address":"Atseden Kalea, 18",
    "sg:city":"Hondarribia",
    "sg:orig_category":"Muebles, Minoristas",
    "sg:phone":"+34 943 64 53 39",
    "sg:postcode":"20280",
    "sg:province":"Guip\u00f9zcoa",
    "wof:name":"Gerain, S.l.",
    "wof:placetype":"venue"
},
  "geometry": {"coordinates":[-1.8021508455,43.3682556152],"type":"Point"}
}