{
  "type": "Feature",
  "properties": {
    "addr:full":"Calle de Maximo Garcia Garrido, 6 Santurtzi Vizcaya 48980",
    "addr:housenumber":"6",
    "addr:postcode":"48980",
    "addr:street":"Calle De Maximo Garcia Garrido",
    "iso:country":"ES",
    "sg:address":"Calle de Maximo Garcia Garrido, 6",
    "sg:city":"Santurtzi",
    "sg:orig_category":"Peluqueros: De Se\u00d1oras",
    "sg:phone":"+34 944 83 66 90",
    "sg:postcode":"48980",
    "sg:province":"Vizcaya",
    "wof:name":"Maria Lourdes Bermudez Vallelado",
    "wof:placetype":"venue"
},
  "geometry": {"coordinates":[-3.0330080986,43.3273887634],"type":"Point"}
}