{
  "type": "Feature",
  "properties": {
    "addr:full":"Pg Palmeres (de Les), 1 Cabrils Barcelona 08348",
    "addr:postcode":"08348",
    "addr:street":"Pg Palmeres De Les",
    "iso:country":"ES",
    "sg:address":"Pg Palmeres (de Les), 1",
    "sg:city":"Cabrils",
    "sg:orig_category":"Cajas Y Embalajes Met\u00c1licos",
    "sg:phone":"+34 937 53 00 39",
    "sg:postcode":"08348",
    "sg:province":"Barcelona",
    "wof:name":"Colepccl Navarra S.a.",
    "wof:placetype":"venue"
},
  "geometry": {"coordinates":[2.3710739613,41.5246276855],"type":"Point"}
}