{
  "type": "Feature",
  "properties": {
    "addr:full":"Calle de Santiago, 3 Alburquerque Badajoz 06510",
    "addr:housenumber":"3",
    "addr:street":"Calle De Santiago",
    "iso:country":"ES",
    "sg:address":"Calle de Santiago, 3",
    "sg:city":"Alburquerque",
    "sg:orig_category":"Mec\u00c1nico Del Autom\u00d3vil",
    "sg:phone":"+34 924 40 04 02",
    "sg:postcode":"06510",
    "sg:province":"Badajoz",
    "wof:name":"Gemio Rodriguez Antonio",
    "wof:placetype":"venue"
},
  "geometry": {"coordinates":[-6.9935212135,39.2209281921],"type":"Point"}
}