{
  "type": "Feature",
  "properties": {
    "addr:full":"Avda Libertad (la), 39 Navatejera Le\u00f3n 24008",
    "addr:housenumber":"39",
    "addr:postcode":"24008",
    "addr:street":"Avda Libertad La;Leo\u0301N",
    "iso:country":"ES",
    "sg:address":"Avda Libertad (la), 39",
    "sg:city":"Navatejera",
    "sg:orig_category":"Garajes De Veh\u00cdculos",
    "sg:phone":"+34 987 28 55 17",
    "sg:postcode":"24008",
    "sg:province":"Le\u00f3n",
    "wof:name":"Neumaticos Maxi S.l.",
    "wof:placetype":"venue"
},
  "geometry": {"coordinates":[-5.5624408722,42.6275253296],"type":"Point"}
}