{
  "type": "Feature",
  "properties": {
    "addr:full":"Av Alcoi, 17 Benidorm Alicante 03500",
    "addr:housenumber":"17",
    "addr:postcode":"03500",
    "addr:street":"Av Alcoi",
    "iso:country":"ES",
    "sg:address":"Av Alcoi, 17",
    "sg:city":"Benidorm",
    "sg:orig_category":"Caf\u00c9s, Bares, Cervecer\u00cdas",
    "sg:phone":"+34 965 86 77 71",
    "sg:postcode":"03500",
    "sg:province":"Alicante",
    "wof:name":"Madrigal Megias Carmen",
    "wof:placetype":"venue"
},
  "geometry": {"coordinates":[-0.1740590036,38.5364303589],"type":"Point"}
}