{
  "type": "Feature",
  "properties": {
    "addr:full":"Carrer de Ponent, 50 Granollers Barcelona 08401",
    "addr:housenumber":"50",
    "addr:postcode":"08401",
    "addr:street":"Carrer De Ponent",
    "iso:country":"ES",
    "sg:address":"Carrer de Ponent, 50",
    "sg:city":"Granollers",
    "sg:orig_category":"Promotores Constructores",
    "sg:phone":"+34 938 40 42 47",
    "sg:postcode":"08401",
    "sg:province":"Barcelona",
    "wof:name":"Branchat Balaguer Angel",
    "wof:placetype":"venue"
},
  "geometry": {"coordinates":[2.2867751122,41.6116409302],"type":"Point"}
}