{
  "type": "Feature",
  "properties": {
    "addr:full":"Calle de Leon Martin Granizo, 11 Le\u00f3n Le\u00f3n 24005",
    "addr:housenumber":"11",
    "addr:postcode":"24005",
    "addr:street":"Calle De Leon Martin Granizo;Leo\u0301N",
    "iso:country":"ES",
    "sg:address":"Calle de Leon Martin Granizo, 11",
    "sg:city":"Le\u00f3n",
    "sg:orig_category":"Molduras, Junquillos, Listones Y Molduras Perforadas",
    "sg:phone":"+34 987 20 01 10",
    "sg:postcode":"24005",
    "sg:province":"Le\u00f3n",
    "wof:name":"Fernandez Gonzalez Francisco",
    "wof:placetype":"venue"
},
  "geometry": {"coordinates":[-5.5675058365,42.5859909058],"type":"Point"}
}