{
  "type": "Feature",
  "properties": {
    "addr:full":"Avda Monte Igueldo, 53 Madrid Madrid 28053",
    "addr:housenumber":"53",
    "addr:postcode":"madrid;28053",
    "addr:street":"Avda Monte Igueldo",
    "iso:country":"ES",
    "sg:address":"Avda Monte Igueldo, 53",
    "sg:city":"Madrid",
    "sg:orig_category":"Molduras, Junquillos, Listones Y Molduras Perforadas",
    "sg:phone":"+34 914 78 50 66",
    "sg:postcode":"28053",
    "sg:province":"Madrid",
    "wof:name":"Alarcon Romero Mariano",
    "wof:placetype":"venue"
},
  "geometry": {"coordinates":[-3.6693716049,40.3942527771],"type":"Point"}
}