{
  "type": "Feature",
  "properties": {
    "addr:full":"Calle de Pousi\u00d1a, 36 Maside Ourense 32570",
    "addr:housenumber":"36",
    "addr:postcode":"32570",
    "addr:street":"Calle De Pousin\u0303A",
    "iso:country":"ES",
    "sg:address":"Calle de Pousi\u00d1a, 36",
    "sg:city":"Maside",
    "sg:orig_category":"Reposter\u00cdas",
    "sg:phone":"+34 988 28 83 82",
    "sg:postcode":"32570",
    "sg:province":"Ourense",
    "wof:name":"Panaderia Crespo S.l.",
    "wof:placetype":"venue"
},
  "geometry": {"coordinates":[-8.0276088715,42.4120101929],"type":"Point"}
}