{
  "type": "Feature",
  "properties": {
    "addr:full":"Pl Caserna, S/n Granollers Barcelona 08401",
    "addr:housenumber":"s",
    "addr:postcode":"08401",
    "addr:street":"Pl Caserna;/ N",
    "iso:country":"ES",
    "sg:address":"Pl Caserna, S/n",
    "sg:city":"Granollers",
    "sg:orig_category":"Negocio De Madera",
    "sg:phone":"+34 938 79 09 88",
    "sg:postcode":"08401",
    "sg:province":"Barcelona",
    "wof:name":"Associacio Venedors Mercat Sant Carles De Granollers",
    "wof:placetype":"venue"
},
  "geometry": {"coordinates":[2.2860062122,41.6089515686],"type":"Point"}
}