{
  "type": "Feature",
  "properties": {
    "addr:full":"C/ Ramon Cosp, 6 Puigcerda Girona 17520",
    "addr:housenumber":"6",
    "addr:postcode":"17520",
    "addr:street":"C / Ramon Cosp",
    "iso:country":"ES",
    "sg:address":"C/ Ramon Cosp, 6",
    "sg:city":"Puigcerda",
    "sg:orig_category":"Platos Preparados Refrigerados (fabricaci\u00d3n, Al Por Mayor)",
    "sg:phone":"+34 972 14 04 47",
    "sg:postcode":"17520",
    "sg:province":"Girona",
    "wof:name":"Casas Badia Carmen",
    "wof:placetype":"venue"
},
  "geometry": {"coordinates":[1.9275419712,42.4317321777],"type":"Point"}
}