{
  "type": "Feature",
  "properties": {
    "addr:full":"Calle de Hermanos Machado, 6 Madrid Madrid 28017",
    "addr:housenumber":"6",
    "addr:postcode":"28017",
    "addr:street":"Calle De Hermanos Machado",
    "iso:country":"ES",
    "sg:address":"Calle de Hermanos Machado, 6",
    "sg:city":"Madrid",
    "sg:orig_category":"Comercio De Piezas De Recambio Y De Accesorios De Veh\u00cdculos, Veh\u00cdculos Industriales",
    "sg:phone":"+34 913 77 17 25",
    "sg:postcode":"28017",
    "sg:province":"Madrid",
    "wof:name":"Casimiro Y Angel De La Fuente Cdad.",
    "wof:placetype":"venue"
},
  "geometry": {"coordinates":[-3.6495079994,40.4326095581],"type":"Point"}
}