{
  "type": "Feature",
  "properties": {
    "iso:country":"ES",
    "sg:address":"Calle de Juan Rodriguez Suarez, 7",
    "sg:city":"Merida",
    "sg:orig_category":"Deportes Diversos",
    "sg:phone":"+34 924 30 29 13",
    "sg:postcode":"06800",
    "sg:province":"Badajoz",
    "wof:name":"Federacion Extreme\u00f1a De Gimnasia",
    "wof:placetype":"venue"
},
  "geometry": {"coordinates":[-6.3341741562,38.9222068787],"type":"Point"}
}