{
  "type": "Feature",
  "properties": {
    "addr:full":"Carrer de Foix, 16 Cunit Tarragona 43881",
    "addr:housenumber":"16",
    "addr:postcode":"43881",
    "addr:street":"Carrer De Foix",
    "iso:country":"ES",
    "sg:address":"Carrer de Foix, 16",
    "sg:city":"Cunit",
    "sg:orig_category":"Agentes Generales De Seguros",
    "sg:phone":"+34 977 16 02 31",
    "sg:postcode":"43881",
    "sg:province":"Tarragona",
    "wof:name":"Akma Servicios Integrales Sl",
    "wof:placetype":"venue"
},
  "geometry": {"coordinates":[1.6198443174,41.1953887939],"type":"Point"}
}