{
  "type": "Feature",
  "properties": {
    "addr:full":"Avda Rigoberta Menchu, 11 Getafe Madrid 28903",
    "addr:housenumber":"11",
    "addr:postcode":"28903",
    "addr:street":"Avda Rigoberta Menchu",
    "iso:country":"ES",
    "sg:address":"Avda Rigoberta Menchu, 11",
    "sg:city":"Getafe",
    "sg:orig_category":"Molduras, Junquillos, Listones Y Molduras Perforadas",
    "sg:phone":"+34 916 01 73 02",
    "sg:postcode":"28903",
    "sg:province":"Madrid",
    "wof:name":"Rincon Del Tio Eulogio S.l.",
    "wof:placetype":"venue"
},
  "geometry": {"coordinates":[-3.7170660496,40.3235626221],"type":"Point"}
}