{
  "type": "Feature",
  "properties": {
    "addr:full":"Calle de San Sebastian, 145 Fernan Nu\u00e7ez C\u00f3rdoba 14520",
    "addr:housenumber":"145",
    "addr:postcode":"14520",
    "addr:street":"Calle De San Sebastian;Co\u0301Rdoba",
    "iso:country":"ES",
    "sg:address":"Calle de San Sebastian, 145",
    "sg:city":"Fernan Nu\u00e7ez",
    "sg:orig_category":"Molduras, Junquillos, Listones Y Molduras Perforadas",
    "sg:phone":"+34 957 37 38 88",
    "sg:postcode":"14520",
    "sg:province":"C\u00f3rdoba",
    "wof:name":"Idalgo Aguilar Maria Dolores",
    "wof:placetype":"venue"
},
  "geometry": {"coordinates":[-4.7214288712,37.6692504883],"type":"Point"}
}