{
  "type": "Feature",
  "properties": {
    "addr:full":"Calle de Licenciado Madrid, 2 Alcala Henares Madrid 28802",
    "addr:housenumber":"2",
    "addr:postcode":"28802",
    "addr:street":"Calle De Licenciado Madrid",
    "iso:country":"ES",
    "sg:address":"Calle de Licenciado Madrid, 2",
    "sg:city":"Alcala Henares",
    "sg:orig_category":"Cl\u00cdnicas Dentales",
    "sg:phone":"+34 918 89 46 17",
    "sg:postcode":"28802",
    "sg:province":"Madrid",
    "wof:name":"Clinica San Francisco De Alcala S.l.",
    "wof:placetype":"venue"
},
  "geometry": {"coordinates":[-3.3758499622,40.4765319824],"type":"Point"}
}