{
  "type": "Feature",
  "properties": {
    "addr:full":"Calle de Santa Teresa De Jesus, 10 Guadalajara Guadalajara 19003",
    "addr:postcode":"19003",
    "addr:street":"Calle De Santa Teresa De Jesus 10",
    "iso:country":"ES",
    "sg:address":"Calle de Santa Teresa De Jesus, 10",
    "sg:city":"Guadalajara",
    "sg:orig_category":"Bisuter\u00cda, Joyer\u00cda, Relojer\u00cda (al Por Menor)",
    "sg:phone":"+34 949 21 22 72",
    "sg:postcode":"19003",
    "sg:province":"Guadalajara",
    "wof:name":"Lopez Garcia Silvia",
    "wof:placetype":"venue"
},
  "geometry": {"coordinates":[-3.1660590172,40.6285209656],"type":"Point"}
}