{
  "type": "Feature",
  "properties": {
    "iso:country":"ES",
    "sg:address":"Carrer de Miquel Servet, 21",
    "sg:city":"Terrassa",
    "sg:orig_category":"Estilistas Y Estudios De Estilo De Corte Y Confecci\u00d3n",
    "sg:phone":"+34 937 86 92 10",
    "sg:postcode":"08222",
    "sg:province":"Barcelona",
    "wof:name":"Grimardi S.l.",
    "wof:placetype":"venue"
},
  "geometry": {"coordinates":[2.0219080448,41.559463501],"type":"Point"}
}