{
  "type": "Feature",
  "properties": {
    "iso:country":"ES",
    "sg:address":"Calle de Arroyo Del Olivar, 99",
    "sg:city":"Madrid",
    "sg:orig_category":"Inform\u00c1tica, Ofim\u00c1tica (estudios, Asesor\u00cda, Ingenier\u00cda, Formaci\u00d3n)",
    "sg:phone":"+34 913 80 03 58",
    "sg:postcode":"28018",
    "sg:province":"Madrid",
    "wof:name":"Mora Centelles Maria Mar",
    "wof:placetype":"venue"
},
  "geometry": {"coordinates":[-3.6490147114,40.3877868652],"type":"Point"}
}