{
  "type": "Feature",
  "properties": {
    "addr:full":"Avda Cuenca (de), 48 Villarta Cuenca 16280",
    "addr:housenumber":"48",
    "addr:postcode":"16280",
    "addr:street":"Avda Cuenca De",
    "iso:country":"ES",
    "sg:address":"Avda Cuenca (de), 48",
    "sg:city":"Villarta",
    "sg:orig_category":"M\u00c9dicos: An\u00c1lisis Cl\u00cdnicos",
    "sg:phone":"+34 962 18 90 85",
    "sg:postcode":"16280",
    "sg:province":"Cuenca",
    "wof:name":"Gomez De Quero Blat Jose Vicente",
    "wof:placetype":"venue"
},
  "geometry": {"coordinates":[-1.6516449451,39.4416885376],"type":"Point"}
}