{
  "type": "Feature",
  "properties": {
    "addr:full":"Calle de Caudal, 33 Malaga M\u00e1laga 29006",
    "addr:housenumber":"33",
    "addr:postcode":"29006",
    "addr:street":"Calle De Caudal;Ma\u0301Laga",
    "iso:country":"ES",
    "sg:address":"Calle de Caudal, 33",
    "sg:city":"Malaga",
    "sg:orig_category":"Muebles, Minoristas",
    "sg:phone":"+34 952 34 24 10",
    "sg:postcode":"29006",
    "sg:province":"M\u00e1laga",
    "wof:name":"Muebles Guadalhorce S.l.",
    "wof:placetype":"venue"
},
  "geometry": {"coordinates":[-4.4837913513,36.7124252319],"type":"Point"}
}