{
  "type": "Feature",
  "properties": {
    "addr:full":"Calle de Jose Miguel Barandiaran, 9 Santurtzi Vizcaya 48980",
    "addr:housenumber":"9",
    "addr:postcode":"48980",
    "addr:street":"Calle De Jose Miguel Barandiaran",
    "iso:country":"ES",
    "sg:address":"Calle de Jose Miguel Barandiaran, 9",
    "sg:city":"Santurtzi",
    "sg:orig_category":"Asociaciones Y Clubs Deportivos",
    "sg:phone":"+34 944 61 48 96",
    "sg:postcode":"48980",
    "sg:province":"Vizcaya",
    "wof:name":"Iba\u00f1ez Gonzalez Rafael",
    "wof:placetype":"venue"
},
  "geometry": {"coordinates":[-3.0338521004,43.327293396],"type":"Point"}
}