{
  "type": "Feature",
  "properties": {
    "iso:country":"ES",
    "sg:address":"Carrer de Gran De Sant Andreu, 202",
    "sg:city":"Barcelona",
    "sg:orig_category":"Agencias Y Agentes Comerciales, Representantes",
    "sg:phone":"+34 933 11 35 04",
    "sg:postcode":"08030",
    "sg:province":"Barcelona",
    "wof:name":"Comunidad De Propietarios Gran De Sant Andreu 202",
    "wof:placetype":"venue"
},
  "geometry": {"coordinates":[2.1895399094,41.4335899353],"type":"Point"}
}