{
  "type": "Feature",
  "properties": {
    "addr:full":"Rua Guarda (da), 3 Seijo Pontevedra 36740",
    "addr:postcode":"36740",
    "addr:street":"Rua Guarda Da 3 Seijo",
    "iso:country":"ES",
    "sg:address":"Rua Guarda (da), 3",
    "sg:city":"Seijo",
    "sg:orig_category":"Ense\u00d1anza: Profesiones Art\u00cdsticas",
    "sg:phone":"+34 986 62 28 21",
    "sg:postcode":"36740",
    "sg:province":"Pontevedra",
    "wof:name":"Alonso Pacheco Concepcion",
    "wof:placetype":"venue"
},
  "geometry": {"coordinates":[-8.7427797318,41.9920845032],"type":"Point"}
}