{
  "type": "Feature",
  "properties": {
    "addr:full":"Calle de Cardenal Cisneros, 37 Ingenio Las Palmas 35250",
    "addr:housenumber":"37",
    "addr:postcode":"35250",
    "addr:street":"Calle De Cardenal Cisneros",
    "iso:country":"ES",
    "sg:address":"Calle de Cardenal Cisneros, 37",
    "sg:city":"Ingenio",
    "sg:orig_category":"Promotores Constructores",
    "sg:phone":"+34 928 12 49 77",
    "sg:postcode":"35250",
    "sg:province":"Las Palmas",
    "wof:name":"Gran Canaria Hnos. Afonso S.l.",
    "wof:placetype":"venue"
},
  "geometry": {"coordinates":[-15.4357776642,27.9200382233],"type":"Point"}
}