{
  "type": "Feature",
  "properties": {
    "addr:full":"Via Julia, 199 Barcelona Barcelona 08042",
    "addr:housenumber":"199",
    "addr:postcode":"08042",
    "addr:street":"Via Julia",
    "iso:country":"ES",
    "sg:address":"Via Julia, 199",
    "sg:city":"Barcelona",
    "sg:orig_category":"Muebles, Minoristas",
    "sg:phone":"+34 933 59 56 71",
    "sg:postcode":"08042",
    "sg:province":"Barcelona",
    "wof:name":"Celdran Gonzalez Leandro",
    "wof:placetype":"venue"
},
  "geometry": {"coordinates":[2.1790480614,41.4455909729],"type":"Point"}
}