{
  "type": "Feature",
  "properties": {
    "addr:full":"Rbla Principal, 108 Vilanova I La Geltru Barcelona 08800",
    "addr:housenumber":"108",
    "addr:postcode":"08800",
    "addr:street":"Rbla Principal",
    "iso:country":"ES",
    "sg:address":"Rbla Principal, 108",
    "sg:city":"Vilanova I La Geltru",
    "sg:orig_category":"Obras Y Organismos Sociales",
    "sg:phone":"+34 938 14 39 60",
    "sg:postcode":"08800",
    "sg:province":"Barcelona",
    "wof:name":"Cruz Roja Espa\u00f1ola Asamblea Local",
    "wof:placetype":"venue"
},
  "geometry": {"coordinates":[1.7258559465,41.2219810486],"type":"Point"}
}