{
  "type": "Feature",
  "properties": {
    "addr:full":"Carrer de Ganduxer, 72 Barcelona Barcelona 08021",
    "addr:housenumber":"72",
    "addr:postcode":"08021",
    "addr:street":"Carrer De Ganduxer",
    "iso:country":"ES",
    "sg:address":"Carrer de Ganduxer, 72",
    "sg:city":"Barcelona",
    "sg:orig_category":"Importaci\u00d3n, Exportaci\u00d3n Y Comercios De Productos Textiles",
    "sg:phone":"+34 934 14 38 15",
    "sg:postcode":"08021",
    "sg:province":"Barcelona",
    "wof:name":"Club De La Aguja S.c.p.",
    "wof:placetype":"venue"
},
  "geometry": {"coordinates":[2.1351699829,41.3982658386],"type":"Point"}
}