{
  "type": "Feature",
  "properties": {
    "iso:country":"ES",
    "sg:address":"Pase Rey Don Juan Carlos I, 4",
    "sg:city":"Oliva",
    "sg:orig_category":"Heladeros",
    "sg:phone":"+34 962 85 14 41",
    "sg:postcode":"46780",
    "sg:province":"Valencia",
    "wof:name":"Molla Mi\u00f1ana Milagro",
    "wof:placetype":"venue"
},
  "geometry": {"coordinates":[-0.1163040027,38.9204063416],"type":"Point"}
}