{
  "type": "Feature",
  "properties": {
    "iso:country":"ES",
    "sg:address":"Calle de Delgadillo, 1",
    "sg:city":"Talavera Reina",
    "sg:orig_category":"Peluquer\u00cdas",
    "sg:phone":"+34 925 81 49 32",
    "sg:postcode":"45600",
    "sg:province":"Toledo",
    "wof:name":"Artistic Pair C.b.",
    "wof:placetype":"venue"
},
  "geometry": {"coordinates":[-4.8305721283,39.9606971741],"type":"Point"}
}