{
  "type": "Feature",
  "properties": {
    "addr:full":"Plaz San Sebastian, 5 Almeria Almer\u00eda 04003",
    "addr:housenumber":"5",
    "addr:postcode":"04003",
    "addr:street":"Plaz San Sebastian",
    "iso:country":"ES",
    "sg:address":"Plaz San Sebastian, 5",
    "sg:city":"Almeria",
    "sg:orig_category":"Sindicatos Y Colegios Profesionales",
    "sg:phone":"+34 950 26 01 41",
    "sg:postcode":"04003",
    "sg:province":"Almer\u00eda",
    "wof:name":"Asociacion De La Prensa De Almeria",
    "wof:placetype":"venue"
},
  "geometry": {"coordinates":[-2.4641234875,36.8439865112],"type":"Point"}
}