{
  "type": "Feature",
  "properties": {
    "addr:full":"Avda Rey Juan Carlos I, 51 Puerto Lumbreras Murcia 30890",
    "addr:housenumber":"51",
    "addr:postcode":"30890",
    "addr:street":"Avda Rey Juan Carlos I",
    "iso:country":"ES",
    "sg:address":"Avda Rey Juan Carlos I, 51",
    "sg:city":"Puerto Lumbreras",
    "sg:orig_category":"Peleter\u00cdas",
    "sg:phone":"+34 968 40 21 33",
    "sg:postcode":"30890",
    "sg:province":"Murcia",
    "wof:name":"Garcia Mateos Juana Maria",
    "wof:placetype":"venue"
},
  "geometry": {"coordinates":[-1.8021390438,37.568687439],"type":"Point"}
}