{
  "type": "Feature",
  "properties": {
    "iso:country":"ES",
    "sg:address":"Gimenez Reina, S/n",
    "sg:city":"Nerja",
    "sg:orig_category":"Alquiler De Veh\u00cdculos: Turismos Y Utilitarios",
    "sg:phone":"+34 952 52 15 47",
    "sg:postcode":"29780",
    "sg:province":"M\u00e1laga",
    "wof:name":"Autos Fiesta S.l.",
    "wof:placetype":"venue"
},
  "geometry": {"coordinates":[-3.834997654,36.7956962585],"type":"Point"}
}