{
  "type": "Feature",
  "properties": {
    "addr:full":"Ca\u00f1amares, S/n Sta. Marta Tormes Salamanca 37900",
    "addr:housenumber":"/ n",
    "addr:postcode":"37900",
    "addr:street":"Can\u0303Amares S;Marta",
    "iso:country":"ES",
    "sg:address":"Ca\u00f1amares, S/n",
    "sg:city":"Sta. Marta Tormes",
    "sg:orig_category":"Ense\u00d1anza, Formaci\u00d3n Profesional: Aprendizaje",
    "sg:phone":"+34 923 20 03 80",
    "sg:postcode":"37900",
    "sg:province":"Salamanca",
    "wof:name":"Colegio Publico Comarcal Miguel Hernandez",
    "wof:placetype":"venue"
},
  "geometry": {"coordinates":[-5.6265788078,40.9506187439],"type":"Point"}
}