{
  "type": "Feature",
  "properties": {
    "iso:country":"ES",
    "sg:address":"Luga Pi\u00d1eiral De Abaixo, 15",
    "sg:city":"Pi\u00d1eiral",
    "sg:orig_category":"Muebles Y Accesorios Para Cocinas Y Cuartos De Ba\u00d1o (al Por Menor)",
    "sg:phone":"+34 988 24 75 87",
    "sg:postcode":"32911",
    "sg:province":"Ourense",
    "wof:name":"M. Cocina Y Ba\u00d1o Ggg.s.l.",
    "wof:placetype":"venue"
},
  "geometry": {"coordinates":[-7.872358799,42.2972106934],"type":"Point"}
}