{
  "type": "Feature",
  "properties": {
    "addr:full":"Ctra Valencia-ademuz, Km. 0030,5 Lliria Valencia 46160",
    "addr:postcode":"46160",
    "addr:street":"Ctra Valencia-Ademuz Km. 0030,5 Lliria",
    "iso:country":"ES",
    "sg:address":"Ctra Valencia-ademuz, Km. 0030,5",
    "sg:city":"Lliria",
    "sg:orig_category":"Empresas De Carpinter\u00cda",
    "sg:phone":"+34 962 78 18 05",
    "sg:postcode":"46160",
    "sg:province":"Valencia",
    "sg:website":"www.mfaluminio.com",
    "wof:name":"M.f.v. Aluminio S.a.",
    "wof:placetype":"venue"
},
  "geometry": {"coordinates":[-0.6247159839,39.6471366882],"type":"Point"}
}