{
  "type": "Feature",
  "properties": {
    "iso:country":"ES",
    "sg:address":"Calle de Fundacion Jado Kalea, 19",
    "sg:city":"Erandio",
    "sg:classifiers":[
        {
            "category":"Autos & Motor Vehicles",
            "subcategory":"Automobile Sales",
            "type":"Retail Goods"
        }
    ],
    "sg:phone":"+34 944 67 10 35",
    "sg:postcode":"48950",
    "sg:province":"Vizcaya",
    "wof:name":"Auto Escuela Arias, S.a.",
    "wof:placetype":"venue"
},
  "geometry": {"coordinates":[-2.9752497673,43.3037757874],"type":"Point"}
}