{
  "type": "Feature",
  "properties": {
    "addr:full":"Avda Rio Cidacos, 104 Agoncillo La Rioja 26509",
    "addr:housenumber":"104",
    "addr:postcode":"26509",
    "addr:street":"Avda Rio Cidacos;Rioja",
    "iso:country":"ES",
    "sg:address":"Avda Rio Cidacos, 104",
    "sg:city":"Agoncillo",
    "sg:orig_category":"Distribuci\u00d3n De Petr\u00d3leo Y Derivados",
    "sg:phone":"+34 941 43 72 64",
    "sg:postcode":"26509",
    "sg:province":"La Rioja",
    "wof:name":"Repsol Ypf S.a.",
    "wof:placetype":"venue"
},
  "geometry": {"coordinates":[-2.1222639084,42.4031410217],"type":"Point"}
}