{
  "type": "Feature",
  "properties": {
    "addr:full":"S. Galderic (pol Ind), 23 S. Pol Mar Barcelona 08395",
    "addr:housenumber":"23",
    "addr:postcode":"08395",
    "addr:street":"Ind;Pol;Barcelona",
    "iso:country":"ES",
    "sg:address":"S. Galderic (pol Ind), 23",
    "sg:city":"S. Pol Mar",
    "sg:orig_category":"Sales (al Por Mayor)",
    "sg:phone":"+34 938 40 61 20",
    "sg:postcode":"08395",
    "sg:province":"Barcelona",
    "wof:name":"Alconed S.a.",
    "wof:placetype":"venue"
},
  "geometry": {"coordinates":[2.1699187756,41.3879165649],"type":"Point"}
}