{
  "type": "Feature",
  "properties": {
    "iso:country":"ES",
    "sg:address":"Calle de E, 20",
    "sg:city":"Mutiloabeiti",
    "sg:orig_category":"Art\u00cdculos De Aluminio",
    "sg:phone":"+34 948 23 80 94",
    "sg:postcode":"31192",
    "sg:province":"Navarra",
    "wof:name":"Aluminios Tajonar S.l.",
    "wof:placetype":"venue"
},
  "geometry": {"coordinates":[-1.6339689493,42.8063697815],"type":"Point"}
}