{
  "type": "Feature",
  "properties": {
    "iso:country":"ES",
    "sg:address":"Avda Mimosas, 66",
    "sg:city":"Bormujos",
    "sg:orig_category":"Centros Empresariales",
    "sg:phone":"+34 955 72 62 27",
    "sg:postcode":"41930",
    "sg:province":"Sevilla",
    "sg:website":"www.pacoreyes",
    "wof:name":"Paco Reyes Consultores S.l.",
    "wof:placetype":"venue"
},
  "geometry": {"coordinates":[-6.0631899834,37.3651924133],"type":"Point"}
}