{
  "type": "Feature",
  "properties": {
    "addr:full":"Carr Sant Pere, 48 Gandia Valencia 46700",
    "addr:housenumber":"48",
    "addr:postcode":"46700",
    "addr:street":"Carr Sant Pere;Valencia",
    "iso:country":"ES",
    "sg:address":"Carr Sant Pere, 48",
    "sg:city":"Gandia",
    "sg:orig_category":"Psic\u00d3logos",
    "sg:phone":"+34 962 87 88 47",
    "sg:postcode":"46700",
    "sg:province":"Valencia",
    "wof:name":"Arocas Monreal Mercedes",
    "wof:placetype":"venue"
},
  "geometry": {"coordinates":[-0.1524267942,38.9363899231],"type":"Point"}
}