{
  "type": "Feature",
  "properties": {
    "iso:country":"ES",
    "sg:address":"Carr Santa Anna, 11",
    "sg:city":"Vilanova I La Geltru",
    "sg:orig_category":"Electrodom\u00c9sticos (al Por Menor)",
    "sg:phone":"+34 938 14 14 38",
    "sg:postcode":"08800",
    "sg:province":"Barcelona",
    "wof:name":"Ferrer Artigas Jose",
    "wof:placetype":"venue"
},
  "geometry": {"coordinates":[1.7213679552,41.2254943848],"type":"Point"}
}