{
  "type": "Feature",
  "properties": {
    "addr:full":"Calle de Alonso Cano, 68 Madrid Madrid 28003",
    "addr:housenumber":"68",
    "addr:postcode":"madrid;28003",
    "addr:street":"Calle De Alonso Cano",
    "iso:country":"ES",
    "sg:address":"Calle de Alonso Cano, 68",
    "sg:city":"Madrid",
    "sg:orig_category":"Sonorizaci\u00d3n, Iluminaci\u00d3n Para Cine, Teatro Y Discotecas (al Por Mayor, Al Por Menor)",
    "sg:phone":"+34 915 35 09 74",
    "sg:postcode":"28003",
    "sg:province":"Madrid",
    "wof:name":"Media Sonund S.l.",
    "wof:placetype":"venue"
},
  "geometry": {"coordinates":[-3.6973454952,40.4436035156],"type":"Point"}
}