{
  "type": "Feature",
  "properties": {
    "addr:full":"Carr Arenal, 11 Son Moro Islas Baleares 07560",
    "addr:housenumber":"11",
    "addr:postcode":"07560",
    "addr:street":"Carr Arenal",
    "iso:country":"ES",
    "sg:address":"Carr Arenal, 11",
    "sg:city":"Son Moro",
    "sg:orig_category":"Alimentaci\u00d3n General (al Por Menor)",
    "sg:phone":"+34 971 58 59 80",
    "sg:postcode":"07560",
    "sg:province":"Islas Baleares",
    "wof:name":"Vadeill Fuster Buenaventura",
    "wof:placetype":"venue"
},
  "geometry": {"coordinates":[3.3764801025,39.5764541626],"type":"Point"}
}