{
  "type": "Feature",
  "properties": {
    "iso:country":"ES",
    "sg:address":"Calle de Nabucco, 11",
    "sg:city":"Malaga",
    "sg:orig_category":"Ropa Para Se\u00d1oras (al Por Menor)",
    "sg:phone":"+34 952 33 50 89",
    "sg:postcode":"29006",
    "sg:province":"M\u00e1laga",
    "wof:name":"Euromoda Tornay S.l.",
    "wof:placetype":"venue"
},
  "geometry": {"coordinates":[-4.4703202248,36.7081451416],"type":"Point"}
}