{
  "type": "Feature",
  "properties": {
    "iso:country":"ES",
    "sg:address":"Carrer de Antonio Ricardos, 14",
    "sg:city":"Barcelona",
    "sg:orig_category":"Empresas De Portes Y Mensajer\u00cda",
    "sg:phone":"+34 934 98 80 70",
    "sg:postcode":"08027",
    "sg:province":"Barcelona",
    "sg:website":"www.trevol.com",
    "wof:name":"Missatgers Trevol Sociedad Cooperativa Catalana Limitada",
    "wof:placetype":"venue"
},
  "geometry": {"coordinates":[2.18927598,41.425907135],"type":"Point"}
}