{
  "type": "Feature",
  "properties": {
    "addr:full":"Tv. E. Y Mina, S/n Iru\u00f1a Navarra 31002",
    "addr:postcode":"31002",
    "addr:street":"Mina S / N Irun\u0303A Navarra",
    "iso:country":"ES",
    "sg:address":"Tv. E. Y Mina, S/n",
    "sg:city":"Iru\u00f1a",
    "sg:orig_category":"Relojer\u00cda (al Por Menor, Reparaci\u00d3n)",
    "sg:phone":"+34 948 22 76 56",
    "sg:postcode":"31002",
    "sg:province":"Navarra",
    "wof:name":"Francisco Javier Sanz B. Y Jose Martin Sanz B.",
    "wof:placetype":"venue"
},
  "geometry": {"coordinates":[-1.6418540478,42.816204071],"type":"Point"}
}