{
  "type": "Feature",
  "properties": {
    "iso:country":"ES",
    "sg:address":"Calle de Isidoro De La Cierva, 24",
    "sg:city":"Aguilas",
    "sg:orig_category":"Florister\u00cdas",
    "sg:phone":"+34 968 44 79 79",
    "sg:postcode":"30880",
    "sg:province":"Murcia",
    "wof:name":"Molina Garcia Marina",
    "wof:placetype":"venue"
},
  "geometry": {"coordinates":[-1.5874778032,37.4080238342],"type":"Point"}
}