{
  "type": "Feature",
  "properties": {
    "addr:full":"Calle de Colegiata La, 12 Nava Asturias 33520",
    "addr:housenumber":"12",
    "addr:postcode":"33520",
    "addr:street":"Calle De Colegiata La",
    "iso:country":"ES",
    "sg:address":"Calle de Colegiata La, 12",
    "sg:city":"Nava",
    "sg:orig_category":"M\u00c9dicos: Estomatolog\u00cda",
    "sg:phone":"+34 985 71 71 99",
    "sg:postcode":"33520",
    "sg:province":"Asturias",
    "wof:name":"Fernandez Teran Avelino",
    "wof:placetype":"venue"
},
  "geometry": {"coordinates":[-5.5098028183,43.3586387634],"type":"Point"}
}