{
  "type": "Feature",
  "properties": {
    "addr:full":"Carrer de Maquinista, 14 Barcelona Barcelona 08003",
    "addr:housenumber":"14",
    "addr:postcode":"08003",
    "addr:street":"Carrer De Maquinista",
    "iso:country":"ES",
    "sg:address":"Carrer de Maquinista, 14",
    "sg:city":"Barcelona",
    "sg:orig_category":"Reposter\u00cdas",
    "sg:phone":"+34 932 21 87 25",
    "sg:postcode":"08003",
    "sg:province":"Barcelona",
    "wof:name":"Padro I Rusi\u00f1ol S.l.",
    "wof:placetype":"venue"
},
  "geometry": {"coordinates":[2.1884000301,41.3806343079],"type":"Point"}
}