{
  "type": "Feature",
  "properties": {
    "iso:country":"ES",
    "sg:address":"Av Juli Garreta, 11",
    "sg:city":"S. Feliu Guixols",
    "sg:orig_category":"Peluqueros: De Se\u00d1oras",
    "sg:phone":"+34 972 32 13 25",
    "sg:postcode":"17220",
    "sg:province":"Girona",
    "wof:name":"Miret Ortiz Magdalena",
    "wof:placetype":"venue"
},
  "geometry": {"coordinates":[3.0282371044,41.7796669006],"type":"Point"}
}