{
  "type": "Feature",
  "properties": {
    "addr:full":"Calle de Povoa, S/n Aranda Duero Burgos 09400",
    "addr:housenumber":"s / n",
    "addr:postcode":"09400",
    "addr:street":"Calle De Povoa",
    "iso:country":"ES",
    "sg:address":"Calle de Povoa, S/n",
    "sg:city":"Aranda Duero",
    "sg:orig_category":"Mensajer\u00cda Express, Portes Internacionales",
    "sg:phone":"+34 947 51 13 76",
    "sg:postcode":"09400",
    "sg:province":"Burgos",
    "wof:name":"Alcalde Cornejo Fernando",
    "wof:placetype":"venue"
},
  "geometry": {"coordinates":[-3.7082095146,41.6695976257],"type":"Point"}
}