{
  "type": "Feature",
  "properties": {
    "addr:full":"Avgd Vicente Blasco Iba\u00d1ez, 15 Albuixech Valencia 46550",
    "addr:housenumber":"15",
    "addr:postcode":"46550",
    "addr:street":"Vicente;Iban\u0303Ez",
    "iso:country":"ES",
    "sg:address":"Avgd Vicente Blasco Iba\u00d1ez, 15",
    "sg:city":"Albuixech",
    "sg:orig_category":"Ingenier\u00cda, Centros De Estudios (diversos)",
    "sg:phone":"+34 961 40 15 11",
    "sg:postcode":"46550",
    "sg:province":"Valencia",
    "wof:name":"Martinez Arilla Juan Carlos",
    "wof:placetype":"venue"
},
  "geometry": {"coordinates":[-0.3136780858,39.5429153442],"type":"Point"}
}