{
  "type": "Feature",
  "properties": {
    "addr:full":"Calle de San Juan (de), 6 Mejorada Campo Madrid 28840",
    "addr:housenumber":"6",
    "addr:postcode":"28840",
    "addr:street":"Calle De San Juan De",
    "iso:country":"ES",
    "sg:address":"Calle de San Juan (de), 6",
    "sg:city":"Mejorada Campo",
    "sg:orig_category":"Inmobiliaria (agencias)",
    "sg:phone":"+34 916 68 22 16",
    "sg:postcode":"28840",
    "sg:province":"Madrid",
    "wof:name":"Toleman Hart S.l.",
    "wof:placetype":"venue"
},
  "geometry": {"coordinates":[-3.4886028767,40.3962974548],"type":"Point"}
}