{
  "type": "Feature",
  "properties": {
    "iso:country":"ES",
    "sg:address":"Carrer de Beethoven, 8",
    "sg:city":"Barcelona",
    "sg:orig_category":"Abogados",
    "sg:phone":"+34 932 02 11 38",
    "sg:postcode":"08021",
    "sg:province":"Barcelona",
    "wof:name":"Tasies Beleta Ricardo",
    "wof:placetype":"venue"
},
  "geometry": {"coordinates":[2.1412799358,41.3928375244],"type":"Point"}
}