{
  "type": "Feature",
  "properties": {
    "iso:country":"ES",
    "sg:address":"Calle de Puentelarra, 44",
    "sg:city":"Madrid",
    "sg:orig_category":"Cl\u00cdnicas Dentales",
    "sg:phone":"+34 913 31 99 73",
    "sg:postcode":"28031",
    "sg:province":"Madrid",
    "wof:name":"Edental S.l.",
    "wof:placetype":"venue"
},
  "geometry": {"coordinates":[-3.6106879711,40.3802947998],"type":"Point"}
}