{
  "type": "Feature",
  "properties": {
    "addr:full":"Rua Ecuador, 64 Vigo Pontevedra 36203",
    "addr:housenumber":"64",
    "addr:postcode":"36203",
    "addr:street":"Rua Ecuador",
    "iso:country":"ES",
    "sg:address":"Rua Ecuador, 64",
    "sg:city":"Vigo",
    "sg:orig_category":"Ropa Y Accesorios",
    "sg:phone":"+34 986 43 69 40",
    "sg:postcode":"36203",
    "sg:province":"Pontevedra",
    "wof:name":"Kaota S.l.",
    "wof:placetype":"venue"
},
  "geometry": {"coordinates":[-8.7183170319,42.2327804565],"type":"Point"}
}