{
  "type": "Feature",
  "properties": {
    "iso:country":"ES",
    "sg:address":"Av Mare Deu De Montserrat, 14",
    "sg:city":"Barcelona",
    "sg:orig_category":"Restaurantes",
    "sg:phone":"+34 932 13 16 36",
    "sg:postcode":"08024",
    "sg:province":"Barcelona",
    "wof:name":"Albarral Y Nu\u00f1ez S.l.",
    "wof:placetype":"venue"
},
  "geometry": {"coordinates":[2.1609413624,41.4133834839],"type":"Point"}
}