{
  "type": "Feature",
  "properties": {
    "iso:country":"ES",
    "sg:address":"Calle de Camilo Jose Cela, 4",
    "sg:city":"Castilleja Cuesta",
    "sg:orig_category":"Patatas (al Por Mayor)",
    "sg:phone":"+34 954 16 40 10",
    "sg:postcode":"41950",
    "sg:province":"Sevilla",
    "wof:name":"Miguel Goncet S.l.",
    "wof:placetype":"venue"
},
  "geometry": {"coordinates":[-6.0530548096,37.3850059509],"type":"Point"}
}