{
  "type": "Feature",
  "properties": {
    "addr:full":"Rua Juan Bautista Andrade, 1 Pontevedra Pontevedra 36005",
    "addr:housenumber":"1",
    "addr:postcode":"36005",
    "addr:street":"Rua Juan Bautista Andrade",
    "iso:country":"ES",
    "sg:address":"Rua Juan Bautista Andrade, 1",
    "sg:city":"Pontevedra",
    "sg:orig_category":"Bancos",
    "sg:phone":"+34 986 87 20 31",
    "sg:postcode":"36005",
    "sg:province":"Pontevedra",
    "sg:website":"www.bancogalicia.es",
    "wof:name":"Banco De Galicia",
    "wof:placetype":"venue"
},
  "geometry": {"coordinates":[-8.6390886307,42.4438018799],"type":"Point"}
}