{
  "type": "Feature",
  "properties": {
    "addr:full":"Calle de Gran Canaria, 109 Fraile Santa Cruz De Tenerife 38640",
    "addr:housenumber":"109",
    "addr:postcode":"38640",
    "addr:street":"Calle De Gran Canaria",
    "iso:country":"ES",
    "sg:address":"Calle de Gran Canaria, 109",
    "sg:city":"Fraile",
    "sg:orig_category":"Importaci\u00d3n",
    "sg:phone":"+34 922 73 18 44",
    "sg:postcode":"38640",
    "sg:province":"Santa Cruz De Tenerife",
    "wof:name":"Navarro Y Chinea S.l.",
    "wof:placetype":"venue"
},
  "geometry": {"coordinates":[-16.682012558,28.0987625122],"type":"Point"}
}