{
  "type": "Feature",
  "properties": {
    "addr:full":"Carr Del Music Enric Casanova, 13 Ontinyent Valencia 46870",
    "addr:housenumber":"13",
    "addr:postcode":"46870",
    "addr:street":"Carr Del;Enric Casanova",
    "iso:country":"ES",
    "sg:address":"Carr Del Music Enric Casanova, 13",
    "sg:city":"Ontinyent",
    "sg:orig_category":"Quincaller\u00cda (al Por Menor)",
    "sg:phone":"+34 962 91 02 85",
    "sg:postcode":"46870",
    "sg:province":"Valencia",
    "wof:name":"Suministros Industriales Fersa S. L.",
    "wof:placetype":"venue"
},
  "geometry": {"coordinates":[-0.6011850238,38.8213157654],"type":"Point"}
}