{
  "type": "Feature",
  "properties": {
    "iso:country":"ES",
    "sg:address":"Calle de Nu\u00d1ez De Balboa, 92",
    "sg:city":"Madrid",
    "sg:orig_category":"Cine (producci\u00d3n, Realizaci\u00d3n)",
    "sg:phone":"+34 915 75 71 83",
    "sg:postcode":"28006",
    "sg:province":"Madrid",
    "wof:name":"On The Beach S.a.",
    "wof:placetype":"venue"
},
  "geometry": {"coordinates":[-3.6818990707,40.4336166382],"type":"Point"}
}