{
  "type": "Feature",
  "properties": {
    "addr:full":"Avda Abaran, S/n Cieza Murcia 30530",
    "addr:housenumber":"s / n",
    "addr:postcode":"30530",
    "addr:street":"Avda Abaran",
    "iso:country":"ES",
    "sg:address":"Avda Abaran, S/n",
    "sg:city":"Cieza",
    "sg:orig_category":"Hospitales",
    "sg:phone":"+34 968 76 01 25",
    "sg:postcode":"30530",
    "sg:province":"Murcia",
    "wof:name":"Servicio Murciano De Salud Centros Provinciales",
    "wof:placetype":"venue"
},
  "geometry": {"coordinates":[-1.4132039547,38.2332649231],"type":"Point"}
}