{
  "type": "Feature",
  "properties": {
    "iso:country":"ES",
    "sg:address":"Calle de Francisco Brizuela, 5",
    "sg:city":"Madrid",
    "sg:orig_category":"Confecci\u00d3n De Trajes Para Se\u00d1oras",
    "sg:phone":"+34 914 63 19 36",
    "sg:postcode":"28011",
    "sg:province":"Madrid",
    "wof:name":"Fama Shop S.l.",
    "wof:placetype":"venue"
},
  "geometry": {"coordinates":[-3.7391650677,40.4082984924],"type":"Point"}
}