{
  "type": "Feature",
  "properties": {
    "addr:full":"Calle de Estanislao Gomez, 81 Madrid Madrid 28042",
    "addr:housenumber":"81",
    "addr:postcode":"madrid;28042",
    "addr:street":"Calle De Estanislao Gomez",
    "iso:country":"ES",
    "sg:address":"Calle de Estanislao Gomez, 81",
    "sg:city":"Madrid",
    "sg:orig_category":"Abrasivos Y Superabrasivos (fabricaci\u00d3n, Al Por Mayor)",
    "sg:phone":"+34 913 20 99 90",
    "sg:postcode":"28042",
    "sg:province":"Madrid",
    "wof:name":"Hernando Vizcaino Jesus",
    "wof:placetype":"venue"
},
  "geometry": {"coordinates":[-3.6086790562,40.4532394409],"type":"Point"}
}