{
  "type": "Feature",
  "properties": {
    "iso:country":"ES",
    "sg:address":"Rond Pajares, 15",
    "sg:city":"Carpio",
    "sg:orig_category":"Empresas De Carpinter\u00cda Met\u00c1lica",
    "sg:phone":"+34 957 18 02 15",
    "sg:postcode":"14620",
    "sg:province":"C\u00f3rdoba",
    "wof:name":"Torres Plaza Rafael",
    "wof:placetype":"venue"
},
  "geometry": {"coordinates":[-4.4988470078,37.9402809143],"type":"Point"}
}