{
  "type": "Feature",
  "properties": {
    "iso:country":"ES",
    "sg:address":"Calle de Mayor, 25",
    "sg:city":"Tobarra",
    "sg:orig_category":"Artes Gr\u00c1ficas, Artes Pl\u00c1sticas (curso)",
    "sg:phone":"+34 967 32 85 90",
    "sg:postcode":"02500",
    "sg:province":"Albacete",
    "wof:name":"Imprenta Cicero Turbula S.l.",
    "wof:placetype":"venue"
},
  "geometry": {"coordinates":[-1.689046979,38.5900115967],"type":"Point"}
}