{
  "type": "Feature",
  "properties": {
    "addr:full":"Avda Jose Mesa Y Lopez, 32 Palmas De Gran Canaria Las Palmas 35007",
    "addr:postcode":"35007",
    "addr:street":"Avda Jose Mesa Y Lopez 32",
    "iso:country":"ES",
    "sg:address":"Avda Jose Mesa Y Lopez, 32",
    "sg:city":"Palmas De Gran Canaria",
    "sg:orig_category":"M\u00c9dicos: Anestesiolog\u00cda Y Reanimaci\u00d3n Quir\u00dargica",
    "sg:phone":"+34 928 26 29 21",
    "sg:postcode":"35007",
    "sg:province":"Las Palmas",
    "wof:name":"Cabrilla Reynier Sofia",
    "wof:placetype":"venue"
},
  "geometry": {"coordinates":[-15.432639122,28.134885788],"type":"Point"}
}