{
  "type": "Feature",
  "properties": {
    "addr:full":"Elosu, S/n Elosu \u00c1lava 01510",
    "addr:postcode":"01510",
    "addr:street":"Elosu S / N Elosu A\u0301Lava",
    "iso:country":"ES",
    "sg:address":"Elosu, S/n",
    "sg:city":"Elosu",
    "sg:orig_category":"Agricultores, Agricultores",
    "sg:phone":"+34 945 45 52 46",
    "sg:postcode":"01510",
    "sg:province":"\u00c1lava",
    "wof:name":"Etxalde",
    "wof:placetype":"venue"
},
  "geometry": {"coordinates":[-2.6422491074,42.9813613892],"type":"Point"}
}