{
  "type": "Feature",
  "properties": {
    "addr:full":"Avda San Jose Artesano, 3 Valencia Valencia 46025",
    "addr:housenumber":"3",
    "addr:postcode":"46025",
    "addr:street":"Avda San Jose Artesano",
    "iso:country":"ES",
    "sg:address":"Avda San Jose Artesano, 3",
    "sg:city":"Valencia",
    "sg:orig_category":"Farmacias",
    "sg:phone":"+34 963 49 04 20",
    "sg:postcode":"46025",
    "sg:province":"Valencia",
    "wof:name":"Garrido Cortina Francisco Juan",
    "wof:placetype":"venue"
},
  "geometry": {"coordinates":[-0.3943539858,39.4977836609],"type":"Point"}
}