{
  "type": "Feature",
  "properties": {
    "addr:full":"Avda Guadarranque (del), 94 Estacion Ferrea C\u00e1diz 11368",
    "addr:housenumber":"94",
    "addr:postcode":"11368",
    "addr:street":"Avda Guadarranque Del;Estacion Ferrea Ca\u0301Diz",
    "iso:country":"ES",
    "sg:address":"Avda Guadarranque (del), 94",
    "sg:city":"Estacion Ferrea",
    "sg:orig_category":"Empresas De Carpinter\u00cda Met\u00c1lica",
    "sg:phone":"+34 956 78 67 55",
    "sg:postcode":"11368",
    "sg:province":"C\u00e1diz",
    "wof:name":"Salmeron Baeza Jesus",
    "wof:placetype":"venue"
},
  "geometry": {"coordinates":[-5.4289588928,36.2092399597],"type":"Point"}
}