{
  "type": "Feature",
  "properties": {
    "addr:full":"Cmno Puente San Benito, 2 Campo Criptana Ciudad Real 13610",
    "addr:housenumber":"2",
    "addr:postcode":"13610",
    "addr:street":"Cmno Puente San Benito;Criptana",
    "iso:country":"ES",
    "sg:address":"Cmno Puente San Benito, 2",
    "sg:city":"Campo Criptana",
    "sg:orig_category":"Productores Recolectores, Venta Directa De Vinos",
    "sg:phone":"+34 926 56 10 26",
    "sg:postcode":"13610",
    "sg:province":"Ciudad Real",
    "wof:name":"Cooperativa Del Campo Vinicola Del Carmen",
    "wof:placetype":"venue"
},
  "geometry": {"coordinates":[-3.1243391037,39.403339386],"type":"Point"}
}