{
  "type": "Feature",
  "properties": {
    "addr:full":"Calle de Primavera, 19 Alacant Alicante 03012",
    "addr:housenumber":"19",
    "addr:postcode":"03012",
    "addr:street":"Calle De Primavera",
    "iso:country":"ES",
    "sg:address":"Calle de Primavera, 19",
    "sg:city":"Alacant",
    "sg:orig_category":"Farmacias",
    "sg:phone":"+34 965 24 13 16",
    "sg:postcode":"03012",
    "sg:province":"Alicante",
    "wof:name":"Galiana Garcia Maria Concepcion",
    "wof:placetype":"venue"
},
  "geometry": {"coordinates":[-0.4816730022,38.3624076843],"type":"Point"}
}