{
  "type": "Feature",
  "properties": {
    "addr:full":"Calle de Zorzales, 19 Aranjuez Madrid 28300",
    "addr:housenumber":"19",
    "addr:postcode":"28300",
    "addr:street":"Calle De Zorzales",
    "iso:country":"ES",
    "sg:address":"Calle de Zorzales, 19",
    "sg:city":"Aranjuez",
    "sg:orig_category":"Cobro De Pr\u00c9stamos",
    "sg:phone":"+34 918 75 41 63",
    "sg:postcode":"28300",
    "sg:province":"Madrid",
    "wof:name":"Hermanos Alonso Garran S.l.",
    "wof:placetype":"venue"
},
  "geometry": {"coordinates":[-3.6121349335,40.028678894],"type":"Point"}
}