{
  "type": "Feature",
  "properties": {
    "iso:country":"ES",
    "sg:address":"Calle de Mayor, 89",
    "sg:city":"Garrucha",
    "sg:orig_category":"Herboristas (al Por Menor)",
    "sg:phone":"+34 950 13 32 32",
    "sg:postcode":"04630",
    "sg:province":"Almer\u00eda",
    "wof:name":"Molina Lopez Agueda",
    "wof:placetype":"venue"
},
  "geometry": {"coordinates":[-1.8225909472,37.178894043],"type":"Point"}
}