{
  "type": "Feature",
  "properties": {
    "iso:country":"ES",
    "sg:address":"Calle de Alfonso Xii, 3",
    "sg:city":"Madrid",
    "sg:orig_category":"Ense\u00d1anza, Formaci\u00d3n Profesional: Aprendizaje",
    "sg:phone":"+34 915 89 87 26",
    "sg:postcode":"28...",
    "sg:province":"Madrid",
    "wof:name":"Junta De Construcciones Instalaciones Y Equipo Escolar",
    "wof:placetype":"venue"
},
  "geometry": {"coordinates":[-3.6885979176,40.4095306396],"type":"Point"}
}