{
  "type": "Feature",
  "properties": {
    "iso:country":"ES",
    "sg:address":"Pg Maritim, 10",
    "sg:city":"Benicarlo",
    "sg:orig_category":"Estancos",
    "sg:phone":"+34 964 47 35 10",
    "sg:postcode":"12580",
    "sg:province":"Castell\u00f3n",
    "wof:name":"Villanueva Romero Miguel",
    "wof:placetype":"venue"
},
  "geometry": {"coordinates":[0.424571991,40.415512085],"type":"Point"}
}