{
  "type": "Feature",
  "properties": {
    "addr:full":"A Ribeira Do Maio, S/n Ribeira De Maio La Coru\u00f1a 15240",
    "addr:housenumber":"s / n",
    "addr:postcode":"15240",
    "addr:street":"Corun\u0303A",
    "iso:country":"ES",
    "sg:address":"A Ribeira Do Maio, S/n",
    "sg:city":"Ribeira De Maio",
    "sg:orig_category":"Asociaciones Y Clubs Deportivos",
    "sg:phone":"+34 981 76 32 92",
    "sg:postcode":"15240",
    "sg:province":"La Coru\u00f1a",
    "wof:name":"Olveira Nu\u00f1ez Jose Angel",
    "wof:placetype":"venue"
},
  "geometry": {"coordinates":[-8.9796962738,42.7951965332],"type":"Point"}
}