{
  "type": "Feature",
  "properties": {
    "addr:full":"C/ Almansa, 36 Elche Alicante 03291",
    "addr:housenumber":"36",
    "addr:postcode":"03291",
    "addr:street":"C / Almansa",
    "iso:country":"ES",
    "sg:address":"C/ Almansa, 36",
    "sg:city":"Elche",
    "sg:orig_category":"Zapatos (al Por Mayor)",
    "sg:phone":"+34 966 67 38 83",
    "sg:postcode":"03291",
    "sg:province":"Alicante",
    "wof:name":"Shoes Lucheng S.l.",
    "wof:placetype":"venue"
},
  "geometry": {"coordinates":[-0.717854023,38.2797393799],"type":"Point"}
}