{
  "type": "Feature",
  "properties": {
    "iso:country":"ES",
    "sg:address":"Plaz Primero De Mayo, 1",
    "sg:city":"Brenes",
    "sg:orig_category":"Ense\u00d1anza, Formaci\u00d3n Profesional: Aprendizaje",
    "sg:phone":"+34 954 79 60 00",
    "sg:postcode":"41310",
    "sg:province":"Sevilla",
    "wof:name":"Ayuntamiento De Brenes Centralita",
    "wof:placetype":"venue"
},
  "geometry": {"coordinates":[-5.8730559349,37.5506134033],"type":"Point"}
}