{
  "type": "Feature",
  "properties": {
    "iso:country":"ES",
    "sg:address":"Playa De Corralejo, S/n",
    "sg:city":"Corralejo",
    "sg:orig_category":"Quiropr\u00c1cticos",
    "sg:phone":"+34 928 86 62 58",
    "sg:postcode":"35660",
    "sg:province":"Las Palmas",
    "wof:name":"Lindoso Alonso Miguel Angel",
    "wof:placetype":"venue"
},
  "geometry": {"coordinates":[-13.8716621399,28.7380809784],"type":"Point"}
}