{
  "type": "Feature",
  "properties": {
    "iso:country":"ES",
    "sg:address":"La Iglesia, 35",
    "sg:city":"Veguellina Orbigo",
    "sg:orig_category":"Comercio De Hierro",
    "sg:phone":"+34 987 37 47 44",
    "sg:postcode":"24350",
    "sg:province":"Le\u00f3n",
    "wof:name":"Martinez Acebes Anselmo Angel",
    "wof:placetype":"venue"
},
  "geometry": {"coordinates":[-5.8835787773,42.4407615662],"type":"Point"}
}