{
  "type": "Feature",
  "properties": {
    "addr:full":"Rond Muralla (da), 25 Lugo Lugo 27002",
    "addr:postcode":"27002",
    "addr:street":"Rond;Da",
    "iso:country":"ES",
    "sg:address":"Rond Muralla (da), 25",
    "sg:city":"Lugo",
    "sg:orig_category":"M\u00c9dicos: Pediatr\u00cda. Enfermedades De Los Ni\u00d1os",
    "sg:phone":"+34 982 24 29 08",
    "sg:postcode":"27002",
    "sg:province":"Lugo",
    "wof:name":"Alvez Gonzalez Eduardo Lucas",
    "wof:placetype":"venue"
},
  "geometry": {"coordinates":[-7.5301399231,42.9997177124],"type":"Point"}
}