{
  "type": "Feature",
  "properties": {
    "addr:full":"Calle de Cuesta Del Tajo, 20 Torremolinos M\u00e1laga 29620",
    "addr:housenumber":"20",
    "addr:postcode":"29620",
    "addr:street":"Calle De Cuesta Del Tajo;Ma\u0301Laga",
    "iso:country":"ES",
    "sg:address":"Calle de Cuesta Del Tajo, 20",
    "sg:city":"Torremolinos",
    "sg:orig_category":"Art\u00cdculos De Regalo (al Por Menor)",
    "sg:phone":"+34 952 05 02 61",
    "sg:postcode":"29620",
    "sg:province":"M\u00e1laga",
    "wof:name":"Brusoni Vallejo Danielle",
    "wof:placetype":"venue"
},
  "geometry": {"coordinates":[-4.4970030785,36.6219177246],"type":"Point"}
}