{
  "type": "Feature",
  "properties": {
    "iso:country":"ES",
    "sg:address":"Avda Primero De Mayo, 1",
    "sg:city":"San Vicente Del Raspeig-sant Vicent Del Raspeig",
    "sg:orig_category":"Supermercados Y Hipermercados",
    "sg:phone":"+34 965 67 24 48",
    "sg:postcode":"03690",
    "sg:province":"Alicante",
    "wof:name":"Acomar Alimentacion S.l",
    "wof:placetype":"venue"
},
  "geometry": {"coordinates":[-0.526542604,38.39661026],"type":"Point"}
}