{
  "type": "Feature",
  "properties": {
    "iso:country":"ES",
    "sg:address":"Calle de Teobaldo Power, 16",
    "sg:city":"Santa Cruz De Tenerife",
    "sg:orig_category":"Ropa Para Se\u00d1oras (al Por Menor)",
    "sg:phone":"+34 922 24 53 35",
    "sg:postcode":"38002",
    "sg:province":"Santa Cruz De Tenerife",
    "wof:name":"Zerolo Hardisson Elia",
    "wof:placetype":"venue"
},
  "geometry": {"coordinates":[-16.2516326904,28.467912674],"type":"Point"}
}