{
  "type": "Feature",
  "properties": {
    "addr:full":"Garcia Ximenez, 1 Iru\u00f1a Navarra 31002",
    "addr:housenumber":"1",
    "addr:postcode":"31002",
    "addr:street":"Garcia Ximenez",
    "iso:country":"ES",
    "sg:address":"Garcia Ximenez, 1",
    "sg:city":"Iru\u00f1a",
    "sg:orig_category":"Centros Empresariales",
    "sg:phone":"+34 948 20 79 40",
    "sg:postcode":"31002",
    "sg:province":"Navarra",
    "wof:name":"Sarasa Astrain Miguel Jesus",
    "wof:placetype":"venue"
},
  "geometry": {"coordinates":[-1.6434079409,42.8136825562],"type":"Point"}
}