{
  "type": "Feature",
  "properties": {
    "iso:country":"ES",
    "sg:address":"Cmno Viejo De Velez, 14",
    "sg:city":"Torre Benagalbon",
    "sg:orig_category":"Veh\u00cdculos De Ocasi\u00d3n",
    "sg:phone":"+34 952 97 31 33",
    "sg:postcode":"29738",
    "sg:province":"M\u00e1laga",
    "wof:name":"Gavira Quiros David",
    "wof:placetype":"venue"
},
  "geometry": {"coordinates":[-4.3440141678,36.7225036621],"type":"Point"}
}