{
  "type": "Feature",
  "properties": {
    "iso:country":"ES",
    "sg:address":"Calle de Arranegi Kalea, 28",
    "sg:city":"Lekeitio",
    "sg:orig_category":"Financiaci\u00d3n Y Cr\u00c9ditos",
    "sg:phone":"+34 946 84 28 28",
    "sg:postcode":"48280",
    "sg:province":"Vizcaya",
    "wof:name":"Salisol S. L.",
    "wof:placetype":"venue"
},
  "geometry": {"coordinates":[-2.5027422905,43.3649024963],"type":"Point"}
}