{
  "type": "Feature",
  "properties": {
    "addr:full":"Calle de Santa Fe De Bogota, 45 Santa Fe Granada 18320",
    "addr:housenumber":"45",
    "addr:postcode":"18320",
    "addr:street":"Calle De Santa;Santa",
    "iso:country":"ES",
    "sg:address":"Calle de Santa Fe De Bogota, 45",
    "sg:city":"Santa Fe",
    "sg:orig_category":"Frutas Y Legumbres Frescas (al Por Mayor)",
    "sg:phone":"+34 958 44 16 58",
    "sg:postcode":"18320",
    "sg:province":"Granada",
    "wof:name":"Verbionat Sca",
    "wof:placetype":"venue"
},
  "geometry": {"coordinates":[-3.7223091125,37.1875495911],"type":"Point"}
}