{
  "type": "Feature",
  "properties": {
    "addr:full":"Calle de Sojuela, 5 Logro\u00f1o La Rioja 26007",
    "addr:housenumber":"5",
    "addr:postcode":"26007",
    "addr:street":"Calle De Sojuela;Rioja",
    "iso:country":"ES",
    "sg:address":"Calle de Sojuela, 5",
    "sg:city":"Logro\u00f1o",
    "sg:orig_category":"Cajas De Ahorro",
    "sg:phone":"+34 941 51 17 36",
    "sg:postcode":"26007",
    "sg:province":"La Rioja",
    "wof:name":"Caja De Ahorros Y Monte De Piedad De Zaragoza Aragon Y Rioja",
    "wof:placetype":"venue"
},
  "geometry": {"coordinates":[-2.4622869492,42.4537467957],"type":"Point"}
}