{
  "type": "Feature",
  "properties": {
    "iso:country":"ES",
    "sg:address":"Pla\u00c7 Mallorca, S/n",
    "sg:city":"Lloseta",
    "sg:orig_category":"Confecci\u00d3n De Zapatos",
    "sg:phone":"+34 971 51 40 02",
    "sg:postcode":"07360",
    "sg:province":"Islas Baleares",
    "sg:website":"www.veletto.com",
    "wof:name":"Calzados Coll S. A.",
    "wof:placetype":"venue"
},
  "geometry": {"coordinates":[2.8675060272,39.7163085938],"type":"Point"}
}