{
  "type": "Feature",
  "properties": {
    "iso:country":"ES",
    "sg:address":"Calle de Goya, 7",
    "sg:city":"Madrid",
    "sg:orig_category":"Empresarios Y Productoras De Espect\u00c1culos",
    "sg:phone":"+34 915 76 45 32",
    "sg:postcode":"28001",
    "sg:province":"Madrid",
    "wof:name":"Cortijo Andres Lucia",
    "wof:placetype":"venue"
},
  "geometry": {"coordinates":[-3.6886498928,40.4256591797],"type":"Point"}
}