{
  "type": "Feature",
  "properties": {
    "addr:full":"Calle de Sancho Ramirez, 4 Jaca Huesca 22700",
    "addr:housenumber":"4",
    "addr:postcode":"22700",
    "addr:street":"Calle De Sancho Ramirez",
    "iso:country":"ES",
    "sg:address":"Calle de Sancho Ramirez, 4",
    "sg:city":"Jaca",
    "sg:orig_category":"Promotores Constructores",
    "sg:phone":"+34 974 36 40 44",
    "sg:postcode":"22700",
    "sg:province":"Huesca",
    "wof:name":"Jaca Aneto S.l.",
    "wof:placetype":"venue"
},
  "geometry": {"coordinates":[-0.5493019819,42.5683670044],"type":"Point"}
}