{
  "type": "Feature",
  "properties": {
    "iso:country":"ES",
    "sg:address":"Carr Sant Jaume, 15",
    "sg:city":"Balaguer",
    "sg:orig_category":"Inmobiliaria (agencias)",
    "sg:phone":"+34 973 44 55 61",
    "sg:postcode":"25600",
    "sg:province":"Lleida",
    "wof:name":"Torrento Capdevila Maria Del Carmen",
    "wof:placetype":"venue"
},
  "geometry": {"coordinates":[0.8063899875,41.7917366028],"type":"Point"}
}