{
  "type": "Feature",
  "properties": {
    "iso:country":"ES",
    "sg:address":"Calle de Gobernador (del), S/n",
    "sg:city":"Aranjuez",
    "sg:orig_category":"Casquer\u00cda (al Por Menor)",
    "sg:phone":"+34 918 92 11 84",
    "sg:postcode":"28300",
    "sg:province":"Madrid",
    "wof:name":"Gil Lopez Isidoro Fabian",
    "wof:placetype":"venue"
},
  "geometry": {"coordinates":[-3.6040546894,40.0324630737],"type":"Point"}
}