{
  "type": "Feature",
  "properties": {
    "addr:full":"Av Pau Casals, 8 Barcelona Barcelona 08021",
    "addr:housenumber":"8",
    "addr:postcode":"08021",
    "addr:street":"Av Pau Casals",
    "iso:country":"ES",
    "sg:address":"Av Pau Casals, 8",
    "sg:city":"Barcelona",
    "sg:orig_category":"Lencer\u00cda Femenina, Corseter\u00cda, Trajes De Ba\u00d1o (al Por Menor)",
    "sg:phone":"+34 932 02 06 93",
    "sg:postcode":"08021",
    "sg:province":"Barcelona",
    "wof:name":"Viena Barcelona S.l.",
    "wof:placetype":"venue"
},
  "geometry": {"coordinates":[2.1436669827,41.393535614],"type":"Point"}
}