{
  "type": "Feature",
  "properties": {
    "iso:country":"ES",
    "sg:address":"Calle de San Mateo, 6",
    "sg:city":"Salamanca",
    "sg:orig_category":"Caf\u00c9s, Bares, Cervecer\u00cdas",
    "sg:phone":"+34 923 21 34 60",
    "sg:postcode":"37002",
    "sg:province":"Salamanca",
    "wof:name":"Bar Miranda C.b.",
    "wof:placetype":"venue"
},
  "geometry": {"coordinates":[-5.6642842293,40.9692840576],"type":"Point"}
}