{
  "type": "Feature",
  "properties": {
    "iso:country":"ES",
    "sg:address":"Avda Ramon Ferreiro, 21",
    "sg:city":"Lugo",
    "sg:orig_category":"Inform\u00c1tica (estudios, Servicios, Asesor\u00cda, Formaci\u00d3n)",
    "sg:phone":"+34 982 24 28 65",
    "sg:postcode":"27002",
    "sg:province":"Lugo",
    "sg:website":"www.silasinformatica.com",
    "wof:name":"Barreira Martinez Celestino",
    "wof:placetype":"venue"
},
  "geometry": {"coordinates":[-7.5542149544,43.0050086975],"type":"Point"}
}