{
  "type": "Feature",
  "properties": {
    "iso:country":"ES",
    "sg:address":"Pase Castelar, 37",
    "sg:city":"Villanueva Serena",
    "sg:orig_category":"Laboratorios Y Cl\u00cdnicas Veterinarias",
    "sg:phone":"+34 924 84 71 62",
    "sg:postcode":"06700",
    "sg:province":"Badajoz",
    "wof:name":"Gomez Tejeda Jose Luis",
    "wof:placetype":"venue"
},
  "geometry": {"coordinates":[-5.7927408218,38.9731750488],"type":"Point"}
}