{
  "type": "Feature",
  "properties": {
    "addr:full":"Calle de Alcalde Nicolas Maroto, 6 Malaga M\u00e1laga 29014",
    "addr:housenumber":"6",
    "addr:postcode":"29014",
    "addr:street":"Calle De Alcalde Nicolas Maroto;Ma\u0301Laga",
    "iso:country":"ES",
    "sg:address":"Calle de Alcalde Nicolas Maroto, 6",
    "sg:city":"Malaga",
    "sg:orig_category":"Molduras, Junquillos, Listones Y Molduras Perforadas",
    "sg:phone":"+34 952 26 48 48",
    "sg:postcode":"29014",
    "sg:province":"M\u00e1laga",
    "wof:name":"Perez Suarez Angel",
    "wof:placetype":"venue"
},
  "geometry": {"coordinates":[-4.4186677933,36.7491760254],"type":"Point"}
}