{
  "type": "Feature",
  "properties": {
    "addr:full":"Calle de Bachiller, El, 26 Valencia Valencia 46010",
    "addr:housenumber":"26",
    "addr:postcode":"46010",
    "addr:street":"Calle De Bachiller El",
    "iso:country":"ES",
    "sg:address":"Calle de Bachiller, El, 26",
    "sg:city":"Valencia",
    "sg:orig_category":"Inversiones",
    "sg:phone":"+34 963 93 05 95",
    "sg:postcode":"46010",
    "sg:province":"Valencia",
    "wof:name":"Inversiones Gregal S.l.",
    "wof:placetype":"venue"
},
  "geometry": {"coordinates":[-0.3610140085,39.4813194275],"type":"Point"}
}