{
  "type": "Feature",
  "properties": {
    "addr:full":"Carrer de Sant Cugat, 72 Sabadell Barcelona 08201",
    "addr:housenumber":"72",
    "addr:postcode":"08201",
    "addr:street":"Carrer De Sant Cugat",
    "iso:country":"ES",
    "sg:address":"Carrer de Sant Cugat, 72",
    "sg:city":"Sabadell",
    "sg:orig_category":"Inmobiliaria (agencias)",
    "sg:phone":"+34 937 15 61 00",
    "sg:postcode":"08201",
    "sg:province":"Barcelona",
    "wof:name":"Arriaz S.a.",
    "wof:placetype":"venue"
},
  "geometry": {"coordinates":[2.104013443,41.544593811],"type":"Point"}
}