{
  "type": "Feature",
  "properties": {
    "iso:country":"ES",
    "sg:address":"Vi\u00f1edo Viejo, 2",
    "sg:city":"Zaragoza",
    "sg:orig_category":"Inform\u00c1tica (estudios, Servicios, Asesor\u00cda, Formaci\u00d3n)",
    "sg:phone":"+34 976 55 06 45",
    "sg:postcode":"50009",
    "sg:province":"Zaragoza",
    "wof:name":"Tiber Programacion S.l.",
    "wof:placetype":"venue"
},
  "geometry": {"coordinates":[-0.8813189864,41.6517295837],"type":"Point"}
}