{
  "type": "Feature",
  "properties": {
    "iso:country":"ES",
    "sg:address":"Rond Prado (del), S/n",
    "sg:city":"Almodovar Campo",
    "sg:orig_category":"Alimentaci\u00d3n General (al Por Mayor)",
    "sg:phone":"+34 926 48 35 64",
    "sg:postcode":"13580",
    "sg:province":"Ciudad Real",
    "wof:name":"Olmedo Murillo Francisco",
    "wof:placetype":"venue"
},
  "geometry": {"coordinates":[-4.1820688248,38.7115097046],"type":"Point"}
}