{
  "type": "Feature",
  "properties": {
    "addr:full":"Calle de Vence, 1 Cuevecitas Santa Cruz De Tenerife 38540",
    "addr:housenumber":"1",
    "addr:postcode":"38540",
    "addr:street":"Calle De Vence",
    "iso:country":"ES",
    "sg:address":"Calle de Vence, 1",
    "sg:city":"Cuevecitas",
    "sg:orig_category":"Fabricaci\u00d3n De Peines Y De Accesorios De Peluquer\u00cda",
    "sg:phone":"+34 922 50 40 85",
    "sg:postcode":"38540",
    "sg:province":"Santa Cruz De Tenerife",
    "wof:name":"Exclusivas Mabell S.l.",
    "wof:placetype":"venue"
},
  "geometry": {"coordinates":[-16.3994197845,28.3573226929],"type":"Point"}
}