{
  "type": "Feature",
  "properties": {
    "addr:full":"Calle de Arevalo, 2 Cuellar Segovia 40200",
    "addr:housenumber":"2",
    "addr:postcode":"40200",
    "addr:street":"Calle De Arevalo",
    "iso:country":"ES",
    "sg:address":"Calle de Arevalo, 2",
    "sg:city":"Cuellar",
    "sg:orig_category":"Negocio De Enlosados, Soler\u00cdas",
    "sg:phone":"+34 921 14 03 07",
    "sg:postcode":"40200",
    "sg:province":"Segovia",
    "wof:name":"Gallardo Gil Francisco Jesus",
    "wof:placetype":"venue"
},
  "geometry": {"coordinates":[-4.3129429817,41.3978652954],"type":"Point"}
}