{
  "type": "Feature",
  "properties": {
    "iso:country":"ES",
    "sg:address":"Avda Ingenieros Del Ministerio Obras Publicas, S/n",
    "sg:city":"Haro",
    "sg:orig_category":"Ba\u00d1os Y Duchas P\u00dablicos",
    "sg:phone":"+34 941 30 34 03",
    "sg:postcode":"26200",
    "sg:province":"La Rioja",
    "wof:name":"Ayuntamiento De Haro",
    "wof:placetype":"venue"
},
  "geometry": {"coordinates":[-2.8546431065,42.5757522583],"type":"Point"}
}