{
  "type": "Feature",
  "properties": {
    "addr:full":"Rbla Pompeu Fabra, 55 Mollet Valles Barcelona 08100",
    "addr:housenumber":"55",
    "addr:postcode":"08100",
    "addr:street":"Rbla Pompeu Fabra",
    "iso:country":"ES",
    "sg:address":"Rbla Pompeu Fabra, 55",
    "sg:city":"Mollet Valles",
    "sg:orig_category":"Poller\u00cda Y Caza (al Por Menor)",
    "sg:phone":"+34 935 93 87 51",
    "sg:postcode":"08100",
    "sg:province":"Barcelona",
    "wof:name":"Palaus Pages Javier",
    "wof:placetype":"venue"
},
  "geometry": {"coordinates":[2.2178039551,41.5397377014],"type":"Point"}
}