{
  "type": "Feature",
  "properties": {
    "iso:country":"ES",
    "sg:address":"Calle de Sebastian Elcano, 46",
    "sg:city":"Sevilla",
    "sg:classifiers":[
        {
            "category":"Banks & Credit Unions",
            "subcategory":"Bureau De Change",
            "type":"Services"
        }
    ],
    "sg:phone":"+34 954 28 03 53",
    "sg:postcode":"41011",
    "sg:province":"Sevilla",
    "sg:tags":[
        "organismos",
        "control"
    ],
    "wof:name":"Inspectorate Andalucia S.a.",
    "wof:placetype":"venue"
},
  "geometry": {"coordinates":[-5.9961190224,37.372718811],"type":"Point"}
}