{
  "type": "Feature",
  "properties": {
    "iso:country":"ES",
    "sg:address":"Avda Ejercito (del), 42",
    "sg:city":"Sabi\u00f1anigo",
    "sg:orig_category":"Reposter\u00cdas",
    "sg:phone":"+34 974 48 26 48",
    "sg:postcode":"22600",
    "sg:province":"Huesca",
    "wof:name":"Tahona Algueta S.l.",
    "wof:placetype":"venue"
},
  "geometry": {"coordinates":[-0.3575479984,42.5072822571],"type":"Point"}
}