{
  "type": "Feature",
  "properties": {
    "iso:country":"ES",
    "sg:address":"Calle de Santo Domingo De La Calzada, 4",
    "sg:city":"Arnedo",
    "sg:orig_category":"Inform\u00c1tica: Material Y Suministros",
    "sg:phone":"+34 941 38 50 42",
    "sg:postcode":"26580",
    "sg:province":"La Rioja",
    "sg:website":"www.ivico.com",
    "wof:name":"Ivico Comunicaciones S.l.",
    "wof:placetype":"venue"
},
  "geometry": {"coordinates":[-2.1003160477,42.2262840271],"type":"Point"}
}