{
  "type": "Feature",
  "properties": {
    "addr:full":"Calle de Lezeaga, 34 Bilbao Vizcaya 48002",
    "addr:housenumber":"34",
    "addr:postcode":"48002",
    "addr:street":"Calle De Lezeaga",
    "iso:country":"ES",
    "sg:address":"Calle de Lezeaga, 34",
    "sg:city":"Bilbao",
    "sg:orig_category":"Empresas De Vigilancia, Guardia Y Protecci\u00d3n",
    "sg:phone":"+34 944 66 14 21",
    "sg:postcode":"48002",
    "sg:province":"Vizcaya",
    "wof:name":"Gurbisa Servicios Auxiliares, S.l.",
    "wof:placetype":"venue"
},
  "geometry": {"coordinates":[-2.9552938938,43.2571792603],"type":"Point"}
}