{
  "type": "Feature",
  "properties": {
    "iso:country":"ES",
    "sg:address":"Huerto De La Fonda, 2",
    "sg:city":"Alhaurin Grande",
    "sg:orig_category":"Relojer\u00cda (al Por Menor, Reparaci\u00d3n)",
    "sg:phone":"+34 952 49 04 66",
    "sg:postcode":"29120",
    "sg:province":"M\u00e1laga",
    "wof:name":"Valderrama Cortes Jose",
    "wof:placetype":"venue"
},
  "geometry": {"coordinates":[-4.688354969,36.643409729],"type":"Point"}
}