{
  "type": "Feature",
  "properties": {
    "iso:country":"ES",
    "sg:address":"Calle de Viso (el), 8",
    "sg:city":"Soria",
    "sg:orig_category":"Promotores Constructores",
    "sg:phone":"+34 975 23 23 80",
    "sg:postcode":"42004",
    "sg:province":"Soria",
    "wof:name":"Ute Soria Norte",
    "wof:placetype":"venue"
},
  "geometry": {"coordinates":[-2.4789609909,41.7593383789],"type":"Point"}
}