{
  "type": "Feature",
  "properties": {
    "addr:full":"Carr Girona, 17 Angles Girona 17160",
    "addr:housenumber":"17",
    "addr:postcode":"17160",
    "addr:street":"Carr Girona",
    "iso:country":"ES",
    "sg:address":"Carr Girona, 17",
    "sg:city":"Angles",
    "sg:orig_category":"Reposter\u00cdas",
    "sg:phone":"+34 972 42 00 03",
    "sg:postcode":"17160",
    "sg:province":"Girona",
    "wof:name":"Font Caballe Jaume",
    "wof:placetype":"venue"
},
  "geometry": {"coordinates":[2.6347820759,41.9582252502],"type":"Point"}
}