{
  "type": "Feature",
  "properties": {
    "iso:country":"ES",
    "sg:address":"Ptge Foraste, 2",
    "sg:city":"Barcelona",
    "sg:orig_category":"Peluquer\u00cdas, Peluquer\u00cda Mixta",
    "sg:phone":"+34 934 18 67 98",
    "sg:postcode":"08022",
    "sg:province":"Barcelona",
    "wof:name":"Granados Garcia Beatriz Andrea",
    "wof:placetype":"venue"
},
  "geometry": {"coordinates":[2.1376929283,41.4101905823],"type":"Point"}
}