{
  "type": "Feature",
  "properties": {
    "iso:country":"ES",
    "sg:address":"Calle de Chapineria, 3",
    "sg:city":"Jerez De La Frontera",
    "sg:orig_category":"Abogados",
    "sg:phone":"+34 956 32 00 70",
    "sg:postcode":"11403",
    "sg:province":"C\u00e1diz",
    "wof:name":"Villa Cotilla Alfonso",
    "wof:placetype":"venue"
},
  "geometry": {"coordinates":[-6.1387290955,36.6834716797],"type":"Point"}
}