{
  "type": "Feature",
  "properties": {
    "addr:full":"Cmno San Roman, 59 Arnedo La Rioja 26580",
    "addr:housenumber":"59",
    "addr:postcode":"26580",
    "addr:street":"Cmno San Roman;Rioja",
    "iso:country":"ES",
    "sg:address":"Cmno San Roman, 59",
    "sg:city":"Arnedo",
    "sg:orig_category":"M\u00c1quinas Para Recortar Y Pegar",
    "sg:phone":"+34 941 38 41 65",
    "sg:postcode":"26580",
    "sg:province":"La Rioja",
    "wof:name":"Solana Calahorra Pedro",
    "wof:placetype":"venue"
},
  "geometry": {"coordinates":[-2.0945940018,42.229549408],"type":"Point"}
}