{
  "type": "Feature",
  "properties": {
    "addr:full":"Carrer de Marti Julia, 23 Palleja Barcelona 08780",
    "addr:housenumber":"23",
    "addr:postcode":"08780",
    "addr:street":"Carrer De Marti Julia",
    "iso:country":"ES",
    "sg:address":"Carrer de Marti Julia, 23",
    "sg:city":"Palleja",
    "sg:orig_category":"Arquitectos",
    "sg:phone":"+34 936 63 04 20",
    "sg:postcode":"08780",
    "sg:province":"Barcelona",
    "wof:name":"Carbonell Lopez Juan Enrique",
    "wof:placetype":"venue"
},
  "geometry": {"coordinates":[1.9961049557,41.4224853516],"type":"Point"}
}