{
  "type": "Feature",
  "properties": {
    "iso:country":"ES",
    "sg:address":"Cra. Nal. Tres-cents Quaranta, S/n",
    "sg:city":"Tarragona",
    "sg:orig_category":"Agentes, Concesionarios Y Sucursales De Veh\u00cdculos",
    "sg:phone":"+34 977 54 89 12",
    "sg:postcode":"43007",
    "sg:province":"Tarragona",
    "wof:name":"Auto Garau S.l.",
    "wof:placetype":"venue"
},
  "geometry": {"coordinates":[1.2959779501,41.1377334595],"type":"Point"}
}