{
  "type": "Feature",
  "properties": {
    "iso:country":"ES",
    "sg:address":"Trav Dalt, 118",
    "sg:city":"Barcelona",
    "sg:orig_category":"Fabricaci\u00d3n, Venta De Cuadros, Accesorios Para Enmarcar",
    "sg:phone":"+34 932 19 54 04",
    "sg:postcode":"08024",
    "sg:province":"Barcelona",
    "wof:name":"Llobet Paya Josefina",
    "wof:placetype":"venue"
},
  "geometry": {"coordinates":[2.1585810184,41.4115524292],"type":"Point"}
}