{
  "type": "Feature",
  "properties": {
    "iso:country":"ES",
    "sg:address":"Calle de Sabiniano Sierra, 4",
    "sg:city":"Melgar Fernamental",
    "sg:orig_category":"Internados & Ense\u00d1anza Privada",
    "sg:phone":"+34 947 37 20 65",
    "sg:postcode":"09100",
    "sg:province":"Burgos",
    "wof:name":"Religiosas Sagrada Familia De Burdeos",
    "wof:placetype":"venue"
},
  "geometry": {"coordinates":[-4.2433223724,42.4045982361],"type":"Point"}
}