{
  "type": "Feature",
  "properties": {
    "addr:full":"Carrer de Llotja, 1 Roses Girona 17480",
    "addr:housenumber":"1",
    "addr:postcode":"17480",
    "addr:street":"Carrer De Llotja",
    "iso:country":"ES",
    "sg:address":"Carrer de Llotja, 1",
    "sg:city":"Roses",
    "sg:orig_category":"Inmobiliaria (agencias)",
    "sg:phone":"+34 972 25 64 79",
    "sg:postcode":"17480",
    "sg:province":"Girona",
    "wof:name":"Vallol Inmuebles En Renta S.l.",
    "wof:placetype":"venue"
},
  "geometry": {"coordinates":[3.1788520813,42.2602043152],"type":"Point"}
}