{
  "type": "Feature",
  "properties": {
    "addr:full":"Pl. Mayor, 5 Viver Castell\u00f3n 12460",
    "addr:housenumber":"5",
    "addr:postcode":"12460",
    "addr:street":"Pl. Mayor",
    "iso:country":"ES",
    "sg:address":"Pl. Mayor, 5",
    "sg:city":"Viver",
    "sg:orig_category":"Reposter\u00cdas",
    "sg:phone":"+34 964 14 17 04",
    "sg:postcode":"12460",
    "sg:province":"Castell\u00f3n",
    "wof:name":"Aliaga Hoyo Clemente",
    "wof:placetype":"venue"
},
  "geometry": {"coordinates":[-0.5771235824,39.93491745],"type":"Point"}
}