{
  "type": "Feature",
  "properties": {
    "addr:full":"N. Hta Salud, S/n Sevilla Sevilla 41004",
    "addr:housenumber":"/ n",
    "addr:postcode":"41004",
    "iso:country":"ES",
    "sg:address":"N. Hta Salud, S/n",
    "sg:city":"Sevilla",
    "sg:orig_category":"Abogados",
    "sg:phone":"+34 954 41 63 60",
    "sg:postcode":"41004",
    "sg:province":"Sevilla",
    "wof:name":"Herraiz Sarachaga Jose Eugenio",
    "wof:placetype":"venue"
},
  "geometry": {"coordinates":[-5.9867715836,37.4100265503],"type":"Point"}
}