{
  "type": "Feature",
  "properties": {
    "addr:full":"Avda Gaiarre Julian, 52 Bilbao Vizcaya 48004",
    "addr:housenumber":"52",
    "addr:postcode":"48004",
    "addr:street":"Avda Gaiarre Julian",
    "iso:country":"ES",
    "sg:address":"Avda Gaiarre Julian, 52",
    "sg:city":"Bilbao",
    "sg:orig_category":"Partidos Pol\u00cdticos",
    "sg:phone":"+34 944 12 96 11",
    "sg:postcode":"48004",
    "sg:province":"Vizcaya",
    "wof:name":"Partido Socialista Obrero Espa\u00f1ol",
    "wof:placetype":"venue"
},
  "geometry": {"coordinates":[-2.9000940323,43.2564468384],"type":"Point"}
}