{
  "type": "Feature",
  "properties": {
    "iso:country":"ES",
    "sg:address":"Calle de Morera, 46",
    "sg:city":"Santa Marta",
    "sg:orig_category":"Contenedores (mercanc\u00cdas)",
    "sg:phone":"+34 924 69 01 42",
    "sg:postcode":"06150",
    "sg:province":"Badajoz",
    "wof:name":"Madera Calderon Pedro",
    "wof:placetype":"venue"
},
  "geometry": {"coordinates":[-6.6287989616,38.6134986877],"type":"Point"}
}