{
  "type": "Feature",
  "properties": {
    "addr:full":"Urb Manga Beach, S/n Manga Mar Menor Murcia 30380",
    "addr:housenumber":"s / n",
    "addr:postcode":"30380",
    "iso:country":"ES",
    "sg:address":"Urb Manga Beach, S/n",
    "sg:city":"Manga Mar Menor",
    "sg:orig_category":"Inmobiliaria (agencias)",
    "sg:phone":"+34 968 14 38 02",
    "sg:postcode":"30380",
    "sg:province":"Murcia",
    "wof:name":"Escudero Alejos Marcelo",
    "wof:placetype":"venue"
},
  "geometry": {"coordinates":[-0.7281540036,37.6686553955],"type":"Point"}
}