{
  "type": "Feature",
  "properties": {
    "addr:full":"Calle de Socovos, 2 Hellin Albacete 02400",
    "addr:housenumber":"2",
    "addr:postcode":"02400",
    "addr:street":"Calle De Socovos",
    "iso:country":"ES",
    "sg:address":"Calle de Socovos, 2",
    "sg:city":"Hellin",
    "sg:orig_category":"Fabricaci\u00d3n De Tejidos Para Exteriores",
    "sg:phone":"+34 967 30 44 93",
    "sg:postcode":"02400",
    "sg:province":"Albacete",
    "wof:name":"Lonas Y Toldos Hellin, S.l.",
    "wof:placetype":"venue"
},
  "geometry": {"coordinates":[-1.7026640177,38.5069732666],"type":"Point"}
}