{
  "type": "Feature",
  "properties": {
    "addr:full":"Calle de Nalon El, S/n Langreo Asturias 33934",
    "addr:postcode":"33934",
    "addr:street":"Calle De Nalon El S / N",
    "iso:country":"ES",
    "sg:address":"Calle de Nalon El, S/n",
    "sg:city":"Langreo",
    "sg:orig_category":"Productos Refractarios (fabricaci\u00d3n, Al Por Mayor)",
    "sg:phone":"+34 985 69 33 12",
    "sg:postcode":"33934",
    "sg:province":"Asturias",
    "sg:website":"www.ceramicadelnalon.com",
    "wof:name":"Ceramica Del Nalon S. A.",
    "wof:placetype":"venue"
},
  "geometry": {"coordinates":[-5.6986289024,43.3031806946],"type":"Point"}
}