{
  "type": "Feature",
  "properties": {
    "iso:country":"ES",
    "sg:address":"Carrer de Proven\u00c7a, 67",
    "sg:city":"Barcelona",
    "sg:orig_category":"Publicidad (soportes Y Gesti\u00d3n)",
    "sg:phone":"+34 934 10 09 00",
    "sg:postcode":"08029",
    "sg:province":"Barcelona",
    "wof:name":"Incoart S.l.",
    "wof:placetype":"venue"
},
  "geometry": {"coordinates":[2.1485173702,41.3849830627],"type":"Point"}
}