{
  "type": "Feature",
  "properties": {
    "iso:country":"ES",
    "sg:address":"Calle de Camino De Los Nogales, 48",
    "sg:city":"Urbanizacion La Fresneda",
    "sg:orig_category":"Electrodom\u00c9sticos (al Por Menor)",
    "sg:phone":"+34 985 26 58 17",
    "sg:postcode":"33429",
    "sg:province":"Asturias",
    "wof:name":"Electrodomesticos Roel S.l.",
    "wof:placetype":"venue"
},
  "geometry": {"coordinates":[-5.7888607979,43.4130096436],"type":"Point"}
}