{
  "type": "Feature",
  "properties": {
    "iso:country":"ES",
    "sg:address":"Plaz San Martin, 1",
    "sg:city":"Rasillo",
    "sg:orig_category":"Ense\u00d1anza, Formaci\u00d3n Profesional: Aprendizaje",
    "sg:phone":"+34 941 46 21 01",
    "sg:postcode":"26124",
    "sg:province":"La Rioja",
    "wof:name":"Ayuntamiento De El Rasillo",
    "wof:placetype":"venue"
},
  "geometry": {"coordinates":[-2.6972835064,42.1950836182],"type":"Point"}
}