{
  "type": "Feature",
  "properties": {
    "addr:full":"Calle de Sierra De Alcubierre, 30 Zaragoza Zaragoza 50014",
    "addr:housenumber":"30",
    "addr:postcode":"50014",
    "addr:street":"Calle De Sierra De Alcubierre",
    "iso:country":"ES",
    "sg:address":"Calle de Sierra De Alcubierre, 30",
    "sg:city":"Zaragoza",
    "sg:orig_category":"Fabricaci\u00d3n, Instalaci\u00d3n Y Reparaci\u00d3n De Bombas",
    "sg:phone":"+34 976 47 13 19",
    "sg:postcode":"50014",
    "sg:province":"Zaragoza",
    "wof:name":"Emica Bombas S.a.",
    "wof:placetype":"venue"
},
  "geometry": {"coordinates":[-0.8651890159,41.6636390686],"type":"Point"}
}