{
  "type": "Feature",
  "properties": {
    "iso:country":"ES",
    "sg:address":"Calle de Sierra De Segura (de La), 8",
    "sg:city":"Poligono De San Fernando De Henares",
    "sg:orig_category":"Metalurgia",
    "sg:phone":"+34 916 56 54 35",
    "sg:postcode":"28830",
    "sg:province":"Madrid",
    "wof:name":"Comercial Vasca De Conductos S.l.",
    "wof:placetype":"venue"
},
  "geometry": {"coordinates":[-3.4912650585,40.453666687],"type":"Point"}
}