{
  "type": "Feature",
  "properties": {
    "iso:country":"ES",
    "sg:address":"Calle de Pedro Iv El Ceremonioso, 11",
    "sg:city":"Zaragoza",
    "sg:orig_category":"Ingeniero",
    "sg:phone":"+34 976 56 07 56",
    "sg:postcode":"50009",
    "sg:province":"Zaragoza",
    "wof:name":"Aisa Sanz Fernando",
    "wof:placetype":"venue"
},
  "geometry": {"coordinates":[-0.907794416,41.6355209351],"type":"Point"}
}