{
  "type": "Feature",
  "properties": {
    "addr:full":"Calle de Marques De Santa Maria Del Villar, 19 Le\u00f3n Le\u00f3n 24007",
    "addr:housenumber":"19",
    "addr:postcode":"24007",
    "addr:street":"Calle De Marques De Santa;Del Villar;Leo\u0301N",
    "iso:country":"ES",
    "sg:address":"Calle de Marques De Santa Maria Del Villar, 19",
    "sg:city":"Le\u00f3n",
    "sg:orig_category":"Molduras, Junquillos, Listones Y Molduras Perforadas",
    "sg:phone":"+34 987 24 42 53",
    "sg:postcode":"24007",
    "sg:province":"Le\u00f3n",
    "wof:name":"Vidal Vidal Maria Del Carmen",
    "wof:placetype":"venue"
},
  "geometry": {"coordinates":[-5.5684127808,42.6081352234],"type":"Point"}
}