{
  "type": "Feature",
  "properties": {
    "iso:country":"ES",
    "sg:address":"Avda Galicia (de), 37",
    "sg:city":"Monforte De Lemos",
    "sg:orig_category":"Cajas De Ahorro",
    "sg:phone":"+34 982 41 60 11",
    "sg:postcode":"27400",
    "sg:province":"Lugo",
    "wof:name":"Caixa De Aforros De Vigo Ourense E Pontevedra",
    "wof:placetype":"venue"
},
  "geometry": {"coordinates":[-7.510187149,42.5177726746],"type":"Point"}
}