{
  "type": "Feature",
  "properties": {
    "addr:full":"Avda Mirat, 1 Salamanca Salamanca 37002",
    "addr:housenumber":"1",
    "addr:postcode":"37002",
    "addr:street":"Avda Mirat",
    "iso:country":"ES",
    "sg:address":"Avda Mirat, 1",
    "sg:city":"Salamanca",
    "sg:orig_category":"Cr\u00cda De Animales",
    "sg:phone":"+34 923 26 29 36",
    "sg:postcode":"37002",
    "sg:province":"Salamanca",
    "wof:name":"Diaz Ruiz Justo",
    "wof:placetype":"venue"
},
  "geometry": {"coordinates":[-5.659714222,40.9688644409],"type":"Point"}
}