{
  "type": "Feature",
  "properties": {
    "iso:country":"ES",
    "sg:address":"Av Sant Ramon Nonat, 14",
    "sg:city":"Barcelona",
    "sg:orig_category":"Zapatos (al Por Menor)",
    "sg:phone":"+34 934 40 23 88",
    "sg:postcode":"08028",
    "sg:province":"Barcelona",
    "wof:name":"Ruz Conde Francisco",
    "wof:placetype":"venue"
},
  "geometry": {"coordinates":[2.1170990467,41.3765449524],"type":"Point"}
}