{
  "type": "Feature",
  "properties": {
    "addr:full":"Calle de Gascos (los), 17 Segovia Segovia 40003",
    "addr:housenumber":"17",
    "addr:postcode":"40003",
    "addr:street":"Calle De Gascos Los",
    "iso:country":"ES",
    "sg:address":"Calle de Gascos (los), 17",
    "sg:city":"Segovia",
    "sg:orig_category":"Procuradores",
    "sg:phone":"+34 921 43 50 07",
    "sg:postcode":"40003",
    "sg:province":"Segovia",
    "wof:name":"Escorial De Frutos Belen",
    "wof:placetype":"venue"
},
  "geometry": {"coordinates":[-4.1155757904,40.9493331909],"type":"Point"}
}