{
  "type": "Feature",
  "properties": {
    "iso:country":"ES",
    "sg:address":"Calle de Granada, S/n",
    "sg:city":"Rincon Victoria",
    "sg:orig_category":"Centros De Coordinaci\u00d3n",
    "sg:phone":"+34 952 40 39 39",
    "sg:postcode":"29730",
    "sg:province":"M\u00e1laga",
    "wof:name":"Gestoria Negrillo S.l.",
    "wof:placetype":"venue"
},
  "geometry": {"coordinates":[-4.2856388092,36.7156562805],"type":"Point"}
}