{
  "type": "Feature",
  "properties": {
    "addr:full":"Carrer de Cort (de La), 5 Valls Tarragona 43800",
    "addr:housenumber":"5",
    "addr:postcode":"43800",
    "addr:street":"Carrer De Cort De La",
    "iso:country":"ES",
    "sg:address":"Carrer de Cort (de La), 5",
    "sg:city":"Valls",
    "sg:orig_category":"Estilistas Y Estudios De Estilo De Corte Y Confecci\u00d3n",
    "sg:phone":"+34 977 60 36 75",
    "sg:postcode":"43800",
    "sg:province":"Tarragona",
    "wof:name":"Pluvinet Puigvert Benito",
    "wof:placetype":"venue"
},
  "geometry": {"coordinates":[1.2476840019,41.2843894958],"type":"Point"}
}