{
  "type": "Feature",
  "properties": {
    "iso:country":"ES",
    "sg:address":"Calle de Quintiliano, 3",
    "sg:city":"Madrid",
    "sg:orig_category":"Internados & Ense\u00d1anza Privada",
    "sg:phone":"+34 915 61 72 44",
    "sg:postcode":"28002",
    "sg:province":"Madrid",
    "wof:name":"Colegio Nazaret",
    "wof:placetype":"venue"
},
  "geometry": {"coordinates":[-3.6766769886,40.4419364929],"type":"Point"}
}