{
  "type": "Feature",
  "properties": {
    "iso:country":"ES",
    "sg:address":"Calle de Lope De Vega, 6",
    "sg:city":"Valladolid",
    "sg:orig_category":"Tapiceros Y Tapiceros",
    "sg:phone":"+34 983 26 30 17",
    "sg:postcode":"47010",
    "sg:province":"Valladolid",
    "wof:name":"Lobo Caramazana Constantino",
    "wof:placetype":"venue"
},
  "geometry": {"coordinates":[-4.7233347893,41.6605300903],"type":"Point"}
}