{
  "type": "Feature",
  "properties": {
    "addr:full":"Carrer de Riber, 21 Montblanc Tarragona 43400",
    "addr:housenumber":"21",
    "addr:postcode":"43400",
    "addr:street":"Carrer De Riber",
    "iso:country":"ES",
    "sg:address":"Carrer de Riber, 21",
    "sg:city":"Montblanc",
    "sg:classifiers":[
        {
            "category":"Personal",
            "subcategory":"Barber",
            "type":"Services"
        }
    ],
    "sg:phone":"+34 977 86 22 26",
    "sg:postcode":"43400",
    "sg:province":"Tarragona",
    "sg:tags":[
        "caballeros",
        "de",
        "peluqueros"
    ],
    "wof:name":"Carta\u00f1a Sigro Juan",
    "wof:placetype":"venue"
},
  "geometry": {"coordinates":[1.1633449793,41.3764228821],"type":"Point"}
}