{
  "type": "Feature",
  "properties": {
    "addr:full":"Avda Sierra De Gata, 10 Coria C\u00e1ceres 10800",
    "addr:housenumber":"10",
    "addr:postcode":"10800",
    "addr:street":"Avda Sierra De Gata;Ca\u0301Ceres",
    "iso:country":"ES",
    "sg:address":"Avda Sierra De Gata, 10",
    "sg:city":"Coria",
    "sg:orig_category":"Asociaciones Y Clubs Deportivos",
    "sg:phone":"+34 927 50 32 36",
    "sg:postcode":"10800",
    "sg:province":"C\u00e1ceres",
    "wof:name":"Domingo Viste S.l",
    "wof:placetype":"venue"
},
  "geometry": {"coordinates":[-6.5369467735,39.9854202271],"type":"Point"}
}