{
  "type": "Feature",
  "properties": {
    "iso:country":"ES",
    "sg:address":"Calle de Covarrubias, 4",
    "sg:city":"Burgos",
    "sg:orig_category":"Peluquer\u00cdas, Peluquer\u00cda Mixta",
    "sg:phone":"+34 947 20 36 16",
    "sg:postcode":"09002",
    "sg:province":"Burgos",
    "wof:name":"Estrella Salas Congosto Y Otra S.c.",
    "wof:placetype":"venue"
},
  "geometry": {"coordinates":[-3.6724648476,42.3253631592],"type":"Point"}
}