{
  "type": "Feature",
  "properties": {
    "iso:country":"ES",
    "sg:address":"Avda Rioja De (la), 52",
    "sg:city":"Quel",
    "sg:orig_category":"Muebles, Minoristas",
    "sg:phone":"+34 941 39 20 38",
    "sg:postcode":"26570",
    "sg:province":"La Rioja",
    "wof:name":"Munilla Escalona Federico",
    "wof:placetype":"venue"
},
  "geometry": {"coordinates":[-2.0563650131,42.233341217],"type":"Point"}
}