{
  "type": "Feature",
  "properties": {
    "addr:full":"Calle de Cervantes, 117 Ejido Almer\u00eda 04700",
    "addr:housenumber":"117",
    "addr:postcode":"04700",
    "addr:street":"Calle De Cervantes;Ejido Almeri\u0301A",
    "iso:country":"ES",
    "sg:address":"Calle de Cervantes, 117",
    "sg:city":"Ejido",
    "sg:orig_category":"Zapatos (al Por Menor)",
    "sg:phone":"+34 950 48 55 44",
    "sg:postcode":"04700",
    "sg:province":"Almer\u00eda",
    "wof:name":"Villegas Palmero Francisco Gabriel",
    "wof:placetype":"venue"
},
  "geometry": {"coordinates":[-2.8140039444,36.7746620178],"type":"Point"}
}