{
  "type": "Feature",
  "properties": {
    "addr:full":"Calle de Alejandro Casona, 25 Zaragoza Zaragoza 50015",
    "addr:housenumber":"25",
    "addr:postcode":"50015",
    "addr:street":"Calle De Alejandro Casona",
    "iso:country":"ES",
    "sg:address":"Calle de Alejandro Casona, 25",
    "sg:city":"Zaragoza",
    "sg:orig_category":"Molduras, Junquillos, Listones Y Molduras Perforadas",
    "sg:phone":"+34 976 51 94 58",
    "sg:postcode":"50015",
    "sg:province":"Zaragoza",
    "wof:name":"Leria Vazquez Ismael",
    "wof:placetype":"venue"
},
  "geometry": {"coordinates":[-0.8941990733,41.6772956848],"type":"Point"}
}