{
  "type": "Feature",
  "properties": {
    "addr:full":"Calle de Medina, S/n Poligono Industrial Los Villares Salamanca 37184",
    "addr:housenumber":"s / n",
    "addr:postcode":"37184",
    "addr:street":"Calle De Medina;Industrial",
    "iso:country":"ES",
    "sg:address":"Calle de Medina, S/n",
    "sg:city":"Poligono Industrial Los Villares",
    "sg:orig_category":"Papel (al Por Mayor)",
    "sg:phone":"+34 923 23 27 03",
    "sg:postcode":"37184",
    "sg:province":"Salamanca",
    "wof:name":"Campo Navarro Jesus",
    "wof:placetype":"venue"
},
  "geometry": {"coordinates":[-5.6383290291,40.9917297363],"type":"Point"}
}