{
  "type": "Feature",
  "properties": {
    "iso:country":"ES",
    "sg:address":"Virgen De La Pe\u00f1a, 5",
    "sg:city":"Mijas",
    "sg:orig_category":"Molduras, Junquillos, Listones Y Molduras Perforadas",
    "sg:phone":"+34 952 59 06 12",
    "sg:postcode":"29650",
    "sg:province":"M\u00e1laga",
    "wof:name":"Luque Luque Juan",
    "wof:placetype":"venue"
},
  "geometry": {"coordinates":[-4.637196064,36.5970420837],"type":"Point"}
}