{
  "type": "Feature",
  "properties": {
    "iso:country":"ES",
    "sg:address":"Cm\u00d1o Rios, 90",
    "sg:city":"Vigo",
    "sg:orig_category":"Construcciones Navales Y Fluviales",
    "sg:phone":"+34 986 45 29 95",
    "sg:postcode":"36216",
    "sg:province":"Pontevedra",
    "wof:name":"Astilleros Y Varaderos Montenegro S. A.",
    "wof:placetype":"venue"
},
  "geometry": {"coordinates":[-8.6894750595,42.255771637],"type":"Point"}
}