{
  "type": "Feature",
  "properties": {
    "iso:country":"ES",
    "sg:address":"Calle de Espoz Y Mina, 50",
    "sg:city":"Santa Pola",
    "sg:orig_category":"Tapicer\u00cdas",
    "sg:phone":"+34 965 41 47 55",
    "sg:postcode":"03130",
    "sg:province":"Alicante",
    "wof:name":"Martinez Garre Jose Mariano",
    "wof:placetype":"venue"
},
  "geometry": {"coordinates":[-0.5591927171,38.1934432983],"type":"Point"}
}