{
  "type": "Feature",
  "properties": {
    "addr:full":"Ptge Argullos, 15 Barcelona Barcelona 08016",
    "addr:housenumber":"15",
    "addr:postcode":"08016",
    "addr:street":"Ptge Argullos",
    "iso:country":"ES",
    "sg:address":"Ptge Argullos, 15",
    "sg:city":"Barcelona",
    "sg:orig_category":"Empresas De Limpieza",
    "sg:phone":"+34 932 76 36 62",
    "sg:postcode":"08016",
    "sg:province":"Barcelona",
    "wof:name":"Limpiezas Integrales Diram S.l.",
    "wof:placetype":"venue"
},
  "geometry": {"coordinates":[2.1813719273,41.4413108826],"type":"Point"}
}