{
  "type": "Feature",
  "properties": {
    "addr:full":"Calle de B (p Indust), S/n Casas-iba\u00f1ez Albacete 02200",
    "addr:housenumber":"s / n",
    "addr:postcode":"02200",
    "addr:street":"Calle De;Indust",
    "iso:country":"ES",
    "sg:address":"Calle de B (p Indust), S/n",
    "sg:city":"Casas-iba\u00f1ez",
    "sg:orig_category":"Material Y Equipo Para Vinificaci\u00d3n",
    "sg:phone":"+34 967 46 21 15",
    "sg:postcode":"02200",
    "sg:province":"Albacete",
    "wof:name":"Garrido Gadea Alfonso",
    "wof:placetype":"venue"
},
  "geometry": {"coordinates":[-1.4628041983,39.2907142639],"type":"Point"}
}