{
  "type": "Feature",
  "properties": {
    "iso:country":"ES",
    "sg:address":"Carrer de Barcelona, 38",
    "sg:city":"Manresa",
    "sg:orig_category":"Peluqueros: De Se\u00d1oras",
    "sg:phone":"+34 938 73 23 98",
    "sg:postcode":"08242",
    "sg:province":"Barcelona",
    "wof:name":"Valles Buj Marisol",
    "wof:placetype":"venue"
},
  "geometry": {"coordinates":[1.8227059841,41.731754303],"type":"Point"}
}