{
  "type": "Feature",
  "properties": {
    "iso:country":"ES",
    "sg:address":"Calle de San Pedro, 16",
    "sg:city":"Pinoso",
    "sg:orig_category":"Papeler\u00cdas, Librer\u00cdas",
    "sg:phone":"+34 965 47 75 49",
    "sg:postcode":"03650",
    "sg:province":"Alicante",
    "wof:name":"Ya\u00f1ez Rico Juan Jose",
    "wof:placetype":"venue"
},
  "geometry": {"coordinates":[-1.041890502,38.4036445618],"type":"Point"}
}