{
  "type": "Feature",
  "properties": {
    "addr:full":"Pase Delicias, 38 Madrid Madrid 28045",
    "addr:housenumber":"38",
    "addr:postcode":"madrid;28045",
    "addr:street":"Delicias",
    "iso:country":"ES",
    "sg:address":"Pase Delicias, 38",
    "sg:city":"Madrid",
    "sg:orig_category":"Reparaci\u00d3n Y Restauraci\u00d3n De Objetos Diversos",
    "sg:phone":"+34 915 39 61 09",
    "sg:postcode":"28045",
    "sg:province":"Madrid",
    "wof:name":"Santos Herrero Carolina",
    "wof:placetype":"venue"
},
  "geometry": {"coordinates":[-3.6909348965,40.4038352966],"type":"Point"}
}