{
  "type": "Feature",
  "properties": {
    "iso:country":"ES",
    "sg:address":"Avda Madro\u00d1os, 2",
    "sg:city":"Madrid",
    "sg:orig_category":"Notarios",
    "sg:phone":"+34 917 59 02 11",
    "sg:postcode":"28043",
    "sg:province":"Madrid",
    "wof:name":"Martinez Gil Jose Luis",
    "wof:placetype":"venue"
},
  "geometry": {"coordinates":[-3.6467978954,40.4534454346],"type":"Point"}
}