{
  "type": "Feature",
  "properties": {
    "addr:full":"Calle de Martin Rey, 16 Cantillana Sevilla 41320",
    "addr:housenumber":"16",
    "addr:postcode":"41320",
    "addr:street":"Calle De Martin Rey",
    "iso:country":"ES",
    "sg:address":"Calle de Martin Rey, 16",
    "sg:city":"Cantillana",
    "sg:orig_category":"Ense\u00d1anza, Formaci\u00d3n Profesional: Aprendizaje",
    "sg:phone":"+34 955 73 14 36",
    "sg:postcode":"41320",
    "sg:province":"Sevilla",
    "wof:name":"Ayuntamiento De Cantillana-juzgado De Paz",
    "wof:placetype":"venue"
},
  "geometry": {"coordinates":[-5.8252658844,37.6069412231],"type":"Point"}
}