{
  "type": "Feature",
  "properties": {
    "iso:country":"ES",
    "sg:address":"Rua Canovas Del Castillo, 6",
    "sg:city":"Vigo",
    "sg:classifiers":[
        {
            "category":"Recreation",
            "type":"Entertainment"
        }
    ],
    "sg:phone":"+34 986 22 70 23",
    "sg:postcode":"36202",
    "sg:province":"Pontevedra",
    "sg:tags":[
        "caza",
        "pr\u00c1ctica",
        "la",
        "de",
        "pesca",
        "y"
    ],
    "wof:name":"Chymar S. A.",
    "wof:placetype":"venue"
},
  "geometry": {"coordinates":[-8.7282485962,42.2392272949],"type":"Point"}
}