{
  "type": "Feature",
  "properties": {
    "addr:full":"Calle de Doctor Castelo, 31 Madrid Madrid 28009",
    "addr:housenumber":"31",
    "addr:postcode":"madrid;28009",
    "addr:street":"Calle De Doctor Castelo",
    "iso:country":"ES",
    "sg:address":"Calle de Doctor Castelo, 31",
    "sg:city":"Madrid",
    "sg:orig_category":"Agencias De Viajes",
    "sg:phone":"+34 914 00 88 30",
    "sg:postcode":"28009",
    "sg:province":"Madrid",
    "wof:name":"Viajes De Negocios Y Tiempo Libre S.a.",
    "wof:placetype":"venue"
},
  "geometry": {"coordinates":[-3.6752719879,40.4204521179],"type":"Point"}
}