{
  "type": "Feature",
  "properties": {
    "addr:full":"Calle de Arcos, 29 Espera C\u00e1diz 11648",
    "addr:housenumber":"29",
    "addr:postcode":"11648",
    "addr:street":"Calle De Arcos",
    "iso:country":"ES",
    "sg:address":"Calle de Arcos, 29",
    "sg:city":"Espera",
    "sg:orig_category":"Hormig\u00d3n (m\u00c1quinas E Instalaci\u00d3n)",
    "sg:phone":"+34 956 72 00 85",
    "sg:postcode":"11648",
    "sg:province":"C\u00e1diz",
    "wof:name":"Perez Benitez Genaro",
    "wof:placetype":"venue"
},
  "geometry": {"coordinates":[-5.8059473038,36.8720588684],"type":"Point"}
}