{
  "type": "Feature",
  "properties": {
    "iso:country":"ES",
    "sg:address":"Afueras, S/n",
    "sg:city":"Majadas",
    "sg:orig_category":"Producci\u00d3n, Venta De Productos De Agricultura Biol\u00d3gica",
    "sg:phone":"+34 927 19 80 61",
    "sg:postcode":"10529",
    "sg:province":"C\u00e1ceres",
    "wof:name":"Fruticola Del Tietar S.l.",
    "wof:placetype":"venue"
},
  "geometry": {"coordinates":[-5.7826595306,39.9501075745],"type":"Point"}
}