{
  "type": "Feature",
  "properties": {
    "addr:full":"Grup Miramar, 10 Sestao Vizcaya 48910",
    "addr:housenumber":"10",
    "addr:postcode":"48910",
    "iso:country":"ES",
    "sg:address":"Grup Miramar, 10",
    "sg:city":"Sestao",
    "sg:orig_category":"Reposter\u00cdas",
    "sg:phone":"+34 944 95 66 20",
    "sg:postcode":"48910",
    "sg:province":"Vizcaya",
    "wof:name":"Jose Luis Pulgar Miranda",
    "wof:placetype":"venue"
},
  "geometry": {"coordinates":[-3.0118780136,43.3124809265],"type":"Point"}
}