{
  "type": "Feature",
  "properties": {
    "iso:country":"ES",
    "sg:address":"Avda Castilla La Mancha (de), 28",
    "sg:city":"Alameda Sagra",
    "sg:orig_category":"Bancos",
    "sg:phone":"+34 925 50 00 58",
    "sg:postcode":"45240",
    "sg:province":"Toledo",
    "wof:name":"Banco Espa\u00f1ol De Credito S.a.",
    "wof:placetype":"venue"
},
  "geometry": {"coordinates":[-3.7929849625,40.0103721619],"type":"Point"}
}