{
  "type": "Feature",
  "properties": {
    "iso:country":"ES",
    "sg:address":"Pl Estacio, 2",
    "sg:city":"Vilafranca Penedes",
    "sg:orig_category":"C\u00c1maras De Comercio E Industria, Oficios, Agricultura",
    "sg:phone":"+34 938 90 20 12",
    "sg:postcode":"08720",
    "sg:province":"Barcelona",
    "sg:website":"www.cambrabcn.es",
    "wof:name":"Cambra De Comerci Industria I Navegacio Barna",
    "wof:placetype":"venue"
},
  "geometry": {"coordinates":[1.6992199421,41.3447799683],"type":"Point"}
}