{
  "type": "Feature",
  "properties": {
    "iso:country":"ES",
    "sg:address":"Calle de Sanchez Abarca, 27",
    "sg:city":"Fuente S. Esteban",
    "sg:orig_category":"Telas Y Sedas (al Por Menor)",
    "sg:phone":"+34 923 44 01 67",
    "sg:postcode":"37200",
    "sg:province":"Salamanca",
    "wof:name":"Colmenero Moreno Jose Antonio",
    "wof:placetype":"venue"
},
  "geometry": {"coordinates":[-6.1650328636,40.826171875],"type":"Point"}
}