{
  "type": "Feature",
  "properties": {
    "iso:country":"ES",
    "sg:address":"Pase Casares De, 56",
    "sg:city":"Donostia-san Sebastian",
    "sg:orig_category":"Administradores De Bienes Y Delegados De Comunidades De Propietarios",
    "sg:phone":"+34 943 35 13 11",
    "sg:postcode":"20017",
    "sg:province":"Guip\u00f9zcoa",
    "wof:name":"Comunidad De Propietarios Paseo De Casares 46",
    "wof:placetype":"venue"
},
  "geometry": {"coordinates":[-1.9300010204,43.3199005127],"type":"Point"}
}