{
  "type": "Feature",
  "properties": {
    "iso:country":"ES",
    "sg:address":"Ctra. P. De Becerro, 8",
    "sg:city":"Sto Tome",
    "sg:orig_category":"Arquitectos",
    "sg:phone":"+34 953 73 65 07",
    "sg:postcode":"23311",
    "sg:province":"Ja\u00e9n",
    "wof:name":"Astasio Soria Pedro",
    "wof:placetype":"venue"
},
  "geometry": {"coordinates":[-3.7895176411,37.7657394409],"type":"Point"}
}