{
  "type": "Feature",
  "properties": {
    "addr:full":"Calle de Marcelo Usera, 63 Madrid Madrid 28026",
    "addr:housenumber":"63",
    "addr:postcode":"madrid;28026",
    "addr:street":"Calle De Marcelo Usera",
    "iso:country":"ES",
    "sg:address":"Calle de Marcelo Usera, 63",
    "sg:city":"Madrid",
    "sg:orig_category":"M\u00c9dicos: Estomatolog\u00cda",
    "sg:phone":"+34 915 00 00 47",
    "sg:postcode":"28026",
    "sg:province":"Madrid",
    "wof:name":"Springel Krysztal Mario Luis",
    "wof:placetype":"venue"
},
  "geometry": {"coordinates":[-3.704877615,40.3858566284],"type":"Point"}
}