{
  "type": "Feature",
  "properties": {
    "addr:full":"Calle de Maestro Sosa, S/n Valencia Valencia 46007",
    "addr:housenumber":"s / n",
    "addr:postcode":"46007",
    "addr:street":"Calle De Maestro Sosa",
    "iso:country":"ES",
    "sg:address":"Calle de Maestro Sosa, S/n",
    "sg:city":"Valencia",
    "sg:orig_category":"M\u00c9dicos: Medicina General Orientada A La Homeopat\u00cda",
    "sg:phone":"+34 963 42 06 99",
    "sg:postcode":"46007",
    "sg:province":"Valencia",
    "wof:name":"Chafer Badia Rafael",
    "wof:placetype":"venue"
},
  "geometry": {"coordinates":[-0.3857539892,39.4621543884],"type":"Point"}
}