{
  "type": "Feature",
  "properties": {
    "iso:country":"ES",
    "sg:address":"Calle de Mayor, 2",
    "sg:city":"Puente Tocinos",
    "sg:orig_category":"Electrodom\u00c9sticos (al Por Menor)",
    "sg:phone":"+34 968 23 17 58",
    "sg:postcode":"30006",
    "sg:province":"Murcia",
    "sg:website":"www.singerdistribucion.com",
    "wof:name":"Singer Distribucion S.a.",
    "wof:placetype":"venue"
},
  "geometry": {"coordinates":[-1.1097849607,37.9902229309],"type":"Point"}
}