{
  "type": "Feature",
  "properties": {
    "addr:full":"Carrer de Nou, 1 Vic Barcelona 08500",
    "addr:housenumber":"1",
    "addr:postcode":"08500",
    "addr:street":"Carrer De Nou",
    "iso:country":"ES",
    "sg:address":"Carrer de Nou, 1",
    "sg:city":"Vic",
    "sg:orig_category":"Alimentaci\u00d3n General (al Por Menor)",
    "sg:phone":"+34 938 86 19 81",
    "sg:postcode":"08500",
    "sg:province":"Barcelona",
    "wof:name":"Carnes Y Embutidos Serrat Palma S.l.",
    "wof:placetype":"venue"
},
  "geometry": {"coordinates":[2.2556140423,41.9322433472],"type":"Point"}
}