{
  "type": "Feature",
  "properties": {
    "iso:country":"ES",
    "sg:address":"Av Baix D'es Cos, S/n",
    "sg:city":"Manacor",
    "sg:orig_category":"Comercio, Reparaci\u00d3n De Bicicletas, De Motocicletas, De Accesorios",
    "sg:phone":"+34 971 55 02 48",
    "sg:postcode":"07500",
    "sg:province":"Islas Baleares",
    "wof:name":"Jaume Mascaro Bartolome",
    "wof:placetype":"venue"
},
  "geometry": {"coordinates":[3.2116498947,39.6065216064],"type":"Point"}
}