{
  "type": "Feature",
  "properties": {
    "addr:full":"Calle de Apolo, 45 Torrejon Ardoz Madrid 28850",
    "addr:housenumber":"45",
    "addr:postcode":"28850",
    "addr:street":"Calle De Apolo",
    "iso:country":"ES",
    "sg:address":"Calle de Apolo, 45",
    "sg:city":"Torrejon Ardoz",
    "sg:orig_category":"Agencias Y Agentes Comerciales, Representantes",
    "sg:phone":"+34 916 75 84 30",
    "sg:postcode":"28850",
    "sg:province":"Madrid",
    "wof:name":"Mechasa S.l.",
    "wof:placetype":"venue"
},
  "geometry": {"coordinates":[-3.4735987186,40.4474105835],"type":"Point"}
}