{
  "type": "Feature",
  "properties": {
    "addr:full":"Urb. El Chorro, S/n S. Roque C\u00e1diz 11360",
    "addr:housenumber":"s",
    "addr:postcode":"11360",
    "addr:street":"/ N S. Roque Ca\u0301Diz",
    "iso:country":"ES",
    "sg:address":"Urb. El Chorro, S/n",
    "sg:city":"S. Roque",
    "sg:orig_category":"Promotores Constructores",
    "sg:phone":"+34 956 78 03 56",
    "sg:postcode":"11360",
    "sg:province":"C\u00e1diz",
    "wof:name":"Rusticos Y Baldosas Ana S.l.",
    "wof:placetype":"venue"
},
  "geometry": {"coordinates":[-5.3897438049,36.209690094],"type":"Point"}
}