{
  "type": "Feature",
  "properties": {
    "iso:country":"ES",
    "sg:address":"Alde Rochela (a), S/n",
    "sg:city":"Rochela",
    "sg:orig_category":"Alimentaci\u00d3n General (al Por Mayor)",
    "sg:phone":"+34 982 12 34 00",
    "sg:postcode":"27795",
    "sg:province":"Lugo",
    "wof:name":"Cooperativa Os Irmandi\u00f1os",
    "wof:placetype":"venue"
},
  "geometry": {"coordinates":[-7.0910248756,43.5453109741],"type":"Point"}
}