{
  "type": "Feature",
  "properties": {
    "addr:full":"Pl Salvador Dali, S/n Alfas Pi Alicante 03580",
    "addr:housenumber":"s / n",
    "addr:postcode":"03580",
    "addr:street":"Pl Salvador Dali",
    "iso:country":"ES",
    "sg:address":"Pl Salvador Dali, S/n",
    "sg:city":"Alfas Pi",
    "sg:orig_category":"Venta De Caravanas, Casas M\u00d3viles, Camping",
    "sg:phone":"+34 966 81 43 59",
    "sg:postcode":"03580",
    "sg:province":"Alicante",
    "sg:website":"www.parquetropical.info",
    "wof:name":"Caravan Parque Tropical S. A.",
    "wof:placetype":"venue"
},
  "geometry": {"coordinates":[-0.0986189991,38.5783195496],"type":"Point"}
}