{
  "type": "Feature",
  "properties": {
    "addr:full":"Calle de Viella, 8 Madrid Madrid 28040",
    "addr:housenumber":"8",
    "addr:postcode":"madrid;28040",
    "addr:street":"Calle De Viella",
    "iso:country":"ES",
    "sg:address":"Calle de Viella, 8",
    "sg:city":"Madrid",
    "sg:orig_category":"M\u00dasica Diversa",
    "sg:phone":"+34 914 50 71 19",
    "sg:postcode":"28040",
    "sg:province":"Madrid",
    "wof:name":"Masterkit Diy Sl",
    "wof:placetype":"venue"
},
  "geometry": {"coordinates":[-3.7165400982,40.4552841187],"type":"Point"}
}