{
  "type": "Feature",
  "properties": {
    "iso:country":"ES",
    "sg:address":"Plaz Iberoamerica, 8",
    "sg:city":"Coria",
    "sg:orig_category":"Notarios",
    "sg:phone":"+34 927 50 07 72",
    "sg:postcode":"10800",
    "sg:province":"C\u00e1ceres",
    "wof:name":"Angel Avila Juan Manuel",
    "wof:placetype":"venue"
},
  "geometry": {"coordinates":[-6.5036435127,39.9937400818],"type":"Point"}
}