{
  "type": "Feature",
  "properties": {
    "iso:country":"ES",
    "sg:address":"Carrer de Rossello, 12",
    "sg:city":"S. Cugat Valles",
    "sg:orig_category":"Cables Y Hilos El\u00c9ctricos (fabricaci\u00d3n, Al Por Mayor)",
    "sg:phone":"+34 935 90 13 96",
    "sg:postcode":"08172",
    "sg:province":"Barcelona",
    "sg:website":"www.cablysa.com",
    "wof:name":"Cables Y Sistemas Electricos S.l.",
    "wof:placetype":"venue"
},
  "geometry": {"coordinates":[2.0797650814,41.4698066711],"type":"Point"}
}