{
  "type": "Feature",
  "properties": {
    "addr:full":"Praz Espa\u00d1a, 28 Ferrol La Coru\u00f1a 15403",
    "addr:housenumber":"28",
    "addr:postcode":"15403",
    "addr:street":"Praz Espan\u0303A;La Corun\u0303A",
    "iso:country":"ES",
    "sg:address":"Praz Espa\u00d1a, 28",
    "sg:city":"Ferrol",
    "sg:orig_category":"Caf\u00c9s, Bares, Cervecer\u00cdas",
    "sg:phone":"+34 981 31 97 01",
    "sg:postcode":"15403",
    "sg:province":"La Coru\u00f1a",
    "wof:name":"Avenida Ferrol S.l.",
    "wof:placetype":"venue"
},
  "geometry": {"coordinates":[-8.224032402,43.4830932617],"type":"Point"}
}