{
  "type": "Feature",
  "properties": {
    "addr:full":"Rua Gomez Ulla (de), 18 Santiago De Compostela La Coru\u00f1a 15702",
    "addr:postcode":"15702",
    "addr:street":"Rua Gomez;Corun\u0303A",
    "iso:country":"ES",
    "sg:address":"Rua Gomez Ulla (de), 18",
    "sg:city":"Santiago De Compostela",
    "sg:orig_category":"Fabricaci\u00d3n De Art\u00cdculos Para Papeler\u00cdas",
    "sg:phone":"+34 981 56 15 93",
    "sg:postcode":"15702",
    "sg:province":"La Coru\u00f1a",
    "wof:name":"Grafica De Asturias S.l.",
    "wof:placetype":"venue"
},
  "geometry": {"coordinates":[-8.5431861877,42.874546051],"type":"Point"}
}