{
  "type": "Feature",
  "properties": {
    "iso:country":"ES",
    "sg:address":"Extramundi De Abajo, S/n",
    "sg:city":"Padron",
    "sg:orig_category":"Peluqueros: De Se\u00d1oras",
    "sg:phone":"+34 981 81 00 38",
    "sg:postcode":"15900",
    "sg:province":"La Coru\u00f1a",
    "wof:name":"Martinez Lopez David Fernando",
    "wof:placetype":"venue"
},
  "geometry": {"coordinates":[-8.6658210754,42.7443656921],"type":"Point"}
}