{
  "type": "Feature",
  "properties": {
    "iso:country":"ES",
    "sg:address":"Poli Umbria (la), S/n",
    "sg:city":"Andorra",
    "sg:orig_category":"Cooperativas Agr\u00cdcolas",
    "sg:phone":"+34 978 84 21 17",
    "sg:postcode":"44500",
    "sg:province":"Teruel",
    "wof:name":"Sociedad Cooperativa Del Campo San Macario",
    "wof:placetype":"venue"
},
  "geometry": {"coordinates":[-0.4381250143,40.9736747742],"type":"Point"}
}