{
  "type": "Feature",
  "properties": {
    "iso:country":"ES",
    "sg:address":"Plaz Chica, 5",
    "sg:city":"Santos De Maimona",
    "sg:orig_category":"Abogados",
    "sg:phone":"+34 924 54 45 55",
    "sg:postcode":"06230",
    "sg:province":"Badajoz",
    "wof:name":"Gomez Galan Maria Del Carmen",
    "wof:placetype":"venue"
},
  "geometry": {"coordinates":[-6.3725099564,38.4434814453],"type":"Point"}
}