{
  "type": "Feature",
  "properties": {
    "addr:full":"Pase Ramon Y Cajal, 3 Huesca Huesca 22001",
    "addr:housenumber":"3",
    "addr:postcode":"22001",
    "addr:street":"Ramon Y Cajal",
    "iso:country":"ES",
    "sg:address":"Pase Ramon Y Cajal, 3",
    "sg:city":"Huesca",
    "sg:orig_category":"Inmobiliaria (agencias)",
    "sg:phone":"+34 974 22 75 88",
    "sg:postcode":"22001",
    "sg:province":"Huesca",
    "sg:website":"www.fincascorral.com",
    "wof:name":"Fincas Corral S.l.",
    "wof:placetype":"venue"
},
  "geometry": {"coordinates":[-0.4043270051,42.139541626],"type":"Point"}
}