{
  "type": "Feature",
  "properties": {
    "iso:country":"ES",
    "sg:address":"Calle de Virgen De La Vega, 16",
    "sg:city":"Haro",
    "sg:orig_category":"Cajas De Ahorro",
    "sg:phone":"+34 941 31 01 50",
    "sg:postcode":"26200",
    "sg:province":"La Rioja",
    "sg:website":"www.cajarioja.es",
    "wof:name":"Caja De Ahorros De La Rioja",
    "wof:placetype":"venue"
},
  "geometry": {"coordinates":[-2.8489260674,42.5771903992],"type":"Point"}
}