{
  "type": "Feature",
  "properties": {
    "addr:full":"Calle de Zaragoza, 1 Castellon Castell\u00f3n 12001",
    "addr:housenumber":"1",
    "addr:postcode":"12001",
    "addr:street":"Calle De Zaragoza;Castello\u0301N",
    "iso:country":"ES",
    "sg:address":"Calle de Zaragoza, 1",
    "sg:city":"Castellon",
    "sg:orig_category":"Estancos",
    "sg:phone":"+34 964 21 04 28",
    "sg:postcode":"12001",
    "sg:province":"Castell\u00f3n",
    "wof:name":"Diaz Calvo Fernando",
    "wof:placetype":"venue"
},
  "geometry": {"coordinates":[-0.040089,39.9870567322],"type":"Point"}
}