{
  "type": "Feature",
  "properties": {
    "addr:full":"Tajonar, 8 Iru\u00f1a Navarra 31006",
    "addr:housenumber":"8",
    "addr:postcode":"31006",
    "addr:street":"Tajonar",
    "iso:country":"ES",
    "sg:address":"Tajonar, 8",
    "sg:city":"Iru\u00f1a",
    "sg:orig_category":"Cajas Para Embalar",
    "sg:phone":"+34 948 15 28 52",
    "sg:postcode":"31006",
    "sg:province":"Navarra",
    "wof:name":"Caja Rural De Navarra",
    "wof:placetype":"venue"
},
  "geometry": {"coordinates":[-1.6352649927,42.8055152893],"type":"Point"}
}