{
  "type": "Feature",
  "properties": {
    "addr:full":"Calle de Puerto De Morcuera, 14 Madrid Madrid 28018",
    "addr:housenumber":"14",
    "addr:postcode":"madrid;28018",
    "addr:street":"Calle De Puerto De Morcuera",
    "iso:country":"ES",
    "sg:address":"Calle de Puerto De Morcuera, 14",
    "sg:city":"Madrid",
    "sg:orig_category":"Mec\u00c1nico Del Autom\u00d3vil",
    "sg:phone":"+34 915 07 52 64",
    "sg:postcode":"28018",
    "sg:province":"Madrid",
    "wof:name":"Ruedas Fermar,s.l.",
    "wof:placetype":"venue"
},
  "geometry": {"coordinates":[-3.6670560837,40.3834915161],"type":"Point"}
}