{
  "type": "Feature",
  "properties": {
    "iso:country":"ES",
    "sg:address":"Calle de Valencia, 10",
    "sg:city":"Torrent",
    "sg:orig_category":"Empresas De Carpinter\u00cda Met\u00c1lica",
    "sg:phone":"+34 961 55 03 13",
    "sg:postcode":"46900",
    "sg:province":"Valencia",
    "wof:name":"Carpintera Metalica Cerrajeria Mur Lopez S.l.",
    "wof:placetype":"venue"
},
  "geometry": {"coordinates":[-0.4630190134,39.4411201477],"type":"Point"}
}