{
  "type": "Feature",
  "properties": {
    "addr:full":"Carretera De Don Benito-miajadas, Km. 0001,7 Don Benito Badajoz 06400",
    "addr:postcode":"06400",
    "addr:street":"Carretera De Don Benito-Miajadas Km. 0001,7",
    "iso:country":"ES",
    "sg:address":"Carretera De Don Benito-miajadas, Km. 0001,7",
    "sg:city":"Don Benito",
    "sg:orig_category":"Promotores Constructores",
    "sg:phone":"+34 924 80 37 15",
    "sg:postcode":"06400",
    "sg:province":"Badajoz",
    "wof:name":"Asfaltos Los Santos S.a",
    "wof:placetype":"venue"
},
  "geometry": {"coordinates":[-5.9069247246,39.1483421326],"type":"Point"}
}