{
  "type": "Feature",
  "properties": {
    "iso:country":"ES",
    "sg:address":"Calle de Navalcarnero, 32",
    "sg:city":"Quijorna",
    "sg:orig_category":"Reposter\u00cdas",
    "sg:phone":"+34 918 16 84 82",
    "sg:postcode":"28693",
    "sg:province":"Madrid",
    "wof:name":"Tahona De Brunete S.l.",
    "wof:placetype":"venue"
},
  "geometry": {"coordinates":[-4.0583648682,40.4272651672],"type":"Point"}
}