{
  "type": "Feature",
  "properties": {
    "iso:country":"ES",
    "sg:address":"Calle de Convento Santa Clara, 11",
    "sg:city":"Valencia",
    "sg:orig_category":"Abogados",
    "sg:phone":"+34 963 51 87 11",
    "sg:postcode":"46002",
    "sg:province":"Valencia",
    "wof:name":"Pineda Costa Vicente Gabriel",
    "wof:placetype":"venue"
},
  "geometry": {"coordinates":[-0.376491189,39.4682884216],"type":"Point"}
}