{
  "type": "Feature",
  "properties": {
    "iso:country":"ES",
    "sg:address":"Calle de Mariano Catalina, 4",
    "sg:city":"Tragacete",
    "sg:orig_category":"Alimentaci\u00d3n General (al Por Menor)",
    "sg:phone":"+34 969 28 90 20",
    "sg:postcode":"16150",
    "sg:province":"Cuenca",
    "wof:name":"Torralba Perez Tomasa",
    "wof:placetype":"venue"
},
  "geometry": {"coordinates":[-1.8514809608,40.3501930237],"type":"Point"}
}