{
  "type": "Feature",
  "properties": {
    "iso:country":"ES",
    "sg:address":"Suspiro(bda H America), S/n",
    "sg:city":"Los Dolores",
    "sg:orig_category":"Hosteler\u00cda, Empleados",
    "sg:phone":"+34 968 31 33 00",
    "sg:postcode":"30310",
    "sg:province":"Murcia",
    "wof:name":"Aguera Garcia Quiteria",
    "wof:placetype":"venue"
},
  "geometry": {"coordinates":[-1.0032459497,37.6396369934],"type":"Point"}
}