{
  "type": "Feature",
  "properties": {
    "iso:country":"ES",
    "sg:address":"Calle de Doctor Severo Ochoa, 4",
    "sg:city":"Vall D'uixo",
    "sg:orig_category":"Electricidad: Instaladores",
    "sg:phone":"+34 964 66 18 45",
    "sg:postcode":"12600",
    "sg:province":"Castell\u00f3n",
    "wof:name":"Hermanos Sorribes S.l.",
    "wof:placetype":"venue"
},
  "geometry": {"coordinates":[-0.2268188,39.8226966858],"type":"Point"}
}