{
  "type": "Feature",
  "properties": {
    "iso:country":"ES",
    "sg:address":"Plaz Virgen Del Rocio, 23",
    "sg:city":"Almonte",
    "sg:orig_category":"Molduras, Junquillos, Listones Y Molduras Perforadas",
    "sg:phone":"+34 959 40 69 64",
    "sg:postcode":"21730",
    "sg:province":"Huelva",
    "wof:name":"Marquez Martin Juan",
    "wof:placetype":"venue"
},
  "geometry": {"coordinates":[-6.5180339813,37.2623176575],"type":"Point"}
}