{
  "type": "Feature",
  "properties": {
    "addr:full":"Calle de Viriato, 11 Madrid Madrid 28010",
    "addr:housenumber":"11",
    "addr:postcode":"madrid;28010",
    "addr:street":"Calle De Viriato",
    "iso:country":"ES",
    "sg:address":"Calle de Viriato, 11",
    "sg:city":"Madrid",
    "sg:orig_category":"Costureras",
    "sg:phone":"+34 914 47 76 43",
    "sg:postcode":"28010",
    "sg:province":"Madrid",
    "wof:name":"Acedo Yang\u00fcer Juliana",
    "wof:placetype":"venue"
},
  "geometry": {"coordinates":[-3.7030322552,40.4359855652],"type":"Point"}
}