{
  "type": "Feature",
  "properties": {
    "iso:country":"ES",
    "sg:address":"Poligono Industrial Congost, 18",
    "sg:city":"Martorell",
    "sg:orig_category":"Mudanzas",
    "sg:phone":"+34 937 75 52 96",
    "sg:postcode":"08760",
    "sg:province":"Barcelona",
    "sg:website":"www.controline.com",
    "wof:name":"Control En Mudanzas S.l.",
    "wof:placetype":"venue"
},
  "geometry": {"coordinates":[1.9265979528,41.474105835],"type":"Point"}
}