{
  "type": "Feature",
  "properties": {
    "iso:country":"ES",
    "sg:address":"Psaj Antonio Mu\u00d1oz Quero, 3",
    "sg:city":"Cadiz",
    "sg:orig_category":"Iglesias Cristianas Diversas",
    "sg:phone":"+34 956 26 43 76",
    "sg:postcode":"11012",
    "sg:province":"C\u00e1diz",
    "wof:name":"Testigos Cristianos De Jehova",
    "wof:placetype":"venue"
},
  "geometry": {"coordinates":[-6.2744240761,36.5108604431],"type":"Point"}
}