{
  "type": "Feature",
  "properties": {
    "iso:country":"ES",
    "sg:address":"Carr Juan Sebastian Elcano, 4",
    "sg:city":"Vilanova I La Geltru",
    "sg:orig_category":"Alquiler De Apartamentos",
    "sg:phone":"+34 938 15 06 38",
    "sg:postcode":"08800",
    "sg:province":"Barcelona",
    "wof:name":"Sanoimels S.l.",
    "wof:placetype":"venue"
},
  "geometry": {"coordinates":[1.7210279703,41.2139472961],"type":"Point"}
}