{
  "type": "Feature",
  "properties": {
    "addr:full":"Calle de Tenerife, 5 Utebo Zaragoza 50180",
    "addr:housenumber":"5",
    "addr:postcode":"50180",
    "addr:street":"Calle De Tenerife",
    "iso:country":"ES",
    "sg:address":"Calle de Tenerife, 5",
    "sg:city":"Utebo",
    "sg:orig_category":"Carnicer\u00cdas, Carnicer\u00cdas",
    "sg:phone":"+34 976 77 16 22",
    "sg:postcode":"50180",
    "sg:province":"Zaragoza",
    "wof:name":"Sierra Solanas S.c.",
    "wof:placetype":"venue"
},
  "geometry": {"coordinates":[-0.999382019,41.7026519775],"type":"Point"}
}