{
  "type": "Feature",
  "properties": {
    "iso:country":"ES",
    "sg:address":"Calle de Empedrada, 10",
    "sg:city":"Salamanca",
    "sg:orig_category":"Promotores Constructores",
    "sg:phone":"+34 923 26 74 30",
    "sg:postcode":"37007",
    "sg:province":"Salamanca",
    "wof:name":"Martin Ramos Argimiro",
    "wof:placetype":"venue"
},
  "geometry": {"coordinates":[-5.670568943,40.962688446],"type":"Point"}
}