{
  "type": "Feature",
  "properties": {
    "iso:country":"ES",
    "sg:address":"Calle de Almagro, 20",
    "sg:city":"Zaragoza",
    "sg:orig_category":"Alimentaci\u00d3n General (al Por Menor)",
    "sg:phone":"+34 976 23 06 43",
    "sg:postcode":"50004",
    "sg:province":"Zaragoza",
    "wof:name":"Arag\u00fces Sancho Gonzalo",
    "wof:placetype":"venue"
},
  "geometry": {"coordinates":[-0.8888909221,41.648059845],"type":"Point"}
}