{
  "type": "Feature",
  "properties": {
    "iso:country":"ES",
    "sg:address":"Calle de Idiakez, 9",
    "sg:city":"Donostia-san Sebastian",
    "sg:orig_category":"Centros Empresariales",
    "sg:phone":"+34 943 43 05 75",
    "sg:postcode":"20004",
    "sg:province":"Guip\u00f9zcoa",
    "wof:name":"Lizor",
    "wof:placetype":"venue"
},
  "geometry": {"coordinates":[-1.980995059,43.3203773499],"type":"Point"}
}