{
  "type": "Feature",
  "properties": {
    "addr:full":"Calle de Principal, 80 Boiro La Coru\u00f1a 15930",
    "addr:housenumber":"80",
    "addr:postcode":"15930",
    "addr:street":"Calle De Principal;La Corun\u0303A",
    "iso:country":"ES",
    "sg:address":"Calle de Principal, 80",
    "sg:city":"Boiro",
    "sg:orig_category":"Droguer\u00cdas (al Por Menor)",
    "sg:phone":"+34 981 84 54 19",
    "sg:postcode":"15930",
    "sg:province":"La Coru\u00f1a",
    "wof:name":"Chouza Garcia Ramon",
    "wof:placetype":"venue"
},
  "geometry": {"coordinates":[-8.8837032318,42.6472625732],"type":"Point"}
}