{
  "type": "Feature",
  "properties": {
    "iso:country":"ES",
    "sg:address":"Rua Telleira, 2",
    "sg:city":"Ourense",
    "sg:orig_category":"Caf\u00c9s, Bares, Cervecer\u00cdas",
    "sg:phone":"+34 988 22 93 85",
    "sg:postcode":"32004",
    "sg:province":"Ourense",
    "wof:name":"Martinez Perez Martin",
    "wof:placetype":"venue"
},
  "geometry": {"coordinates":[-7.8551878929,42.3440742493],"type":"Point"}
}