{
  "type": "Feature",
  "properties": {
    "addr:full":"Av Montserrat, 44 Pineda Mar Barcelona 08397",
    "addr:housenumber":"44",
    "addr:postcode":"08397",
    "addr:street":"Av Montserrat;Barcelona",
    "iso:country":"ES",
    "sg:address":"Av Montserrat, 44",
    "sg:city":"Pineda Mar",
    "sg:orig_category":"Material Y Suministros Para Peluquer\u00cda",
    "sg:phone":"+34 937 62 47 16",
    "sg:postcode":"08397",
    "sg:province":"Barcelona",
    "wof:name":"Fernandez Gonzalez Jose",
    "wof:placetype":"venue"
},
  "geometry": {"coordinates":[2.6894240379,41.6241607666],"type":"Point"}
}