{
  "type": "Feature",
  "properties": {
    "addr:full":"Avda Galicia, S/n Tapia Casariego Asturias 33740",
    "addr:housenumber":"s / n",
    "addr:postcode":"33740",
    "addr:street":"Avda Galicia;Casariego",
    "iso:country":"ES",
    "sg:address":"Avda Galicia, S/n",
    "sg:city":"Tapia Casariego",
    "sg:orig_category":"Molduras, Junquillos, Listones Y Molduras Perforadas",
    "sg:phone":"+34 985 47 27 94",
    "sg:postcode":"33740",
    "sg:province":"Asturias",
    "wof:name":"Mari\u00f1as Mendez Maria Dolores",
    "wof:placetype":"venue"
},
  "geometry": {"coordinates":[-6.9432191849,43.5715408325],"type":"Point"}
}