{
  "type": "Feature",
  "properties": {
    "iso:country":"ES",
    "sg:address":"Calle de Portal De Arriaga, 10",
    "sg:city":"Vitoria-gasteiz",
    "sg:orig_category":"Alimentaci\u00d3n General (al Por Menor)",
    "sg:phone":"+34 945 14 27 85",
    "sg:postcode":"01012",
    "sg:province":"\u00c1lava",
    "wof:name":"Ortiz De Zarate Lopez De Foronda Jose Alberto",
    "wof:placetype":"venue"
},
  "geometry": {"coordinates":[-2.6729810238,42.8527755737],"type":"Point"}
}