{
  "type": "Feature",
  "properties": {
    "addr:full":"Calle de Leon Felipe, 2 Utebo Zaragoza 50180",
    "addr:housenumber":"2",
    "addr:postcode":"50180",
    "addr:street":"Calle De Leon Felipe",
    "iso:country":"ES",
    "sg:address":"Calle de Leon Felipe, 2",
    "sg:city":"Utebo",
    "sg:orig_category":"Cajas De Ahorro",
    "sg:phone":"+34 976 77 13 30",
    "sg:postcode":"50180",
    "sg:province":"Zaragoza",
    "wof:name":"Caja De Ahorros Y Monte De Piedad De Zaragoza Aragon Y Rioja",
    "wof:placetype":"venue"
},
  "geometry": {"coordinates":[-1.0217499733,41.7150192261],"type":"Point"}
}