{
  "type": "Feature",
  "properties": {
    "iso:country":"ES",
    "sg:address":"Cust Corvales, 14",
    "sg:city":"Zubia",
    "sg:orig_category":"M\u00c9dicos: An\u00c1lisis Cl\u00cdnicos",
    "sg:phone":"+34 958 59 13 30",
    "sg:postcode":"18140",
    "sg:province":"Granada",
    "wof:name":"Martinez Lopez Jose",
    "wof:placetype":"venue"
},
  "geometry": {"coordinates":[-3.5853440762,37.1218338013],"type":"Point"}
}