{
  "type": "Feature",
  "properties": {
    "addr:full":"Av De Espa\u00f1a(p I La Catalana), S/n Huetor-tajar Granada 18360",
    "addr:housenumber":"s / n",
    "addr:postcode":"18360",
    "addr:street":"Av De Espan\u0303A P;La Catalana",
    "iso:country":"ES",
    "sg:address":"Av De Espa\u00f1a(p I La Catalana), S/n",
    "sg:city":"Huetor-tajar",
    "sg:orig_category":"Alimentaci\u00d3n General (al Por Menor)",
    "sg:phone":"+34 958 33 25 39",
    "sg:postcode":"18360",
    "sg:province":"Granada",
    "wof:name":"Complejo Taxara S.l.",
    "wof:placetype":"venue"
},
  "geometry": {"coordinates":[-4.0276970863,37.1944770813],"type":"Point"}
}