{
  "type": "Feature",
  "properties": {
    "iso:country":"ES",
    "sg:address":"Calle de Do\u00d1a Ana Romero, 2",
    "sg:city":"San Mateo",
    "sg:orig_category":"Asociaciones Humanitarias, De Cooperaci\u00d3n, De Acci\u00d3n Social",
    "sg:phone":"+34 968 47 32 72",
    "sg:postcode":"30800",
    "sg:province":"Murcia",
    "wof:name":"Asociacion Murcia Acoge",
    "wof:placetype":"venue"
},
  "geometry": {"coordinates":[-1.1298867464,37.9834747314],"type":"Point"}
}