{
  "type": "Feature",
  "properties": {
    "addr:full":"Calle de Martin De Espinosa, 2 Alcala Real Ja\u00e9n 23680",
    "addr:housenumber":"2",
    "addr:postcode":"23680",
    "addr:street":"Calle De Martin De Espinosa;Jae\u0301N",
    "iso:country":"ES",
    "sg:address":"Calle de Martin De Espinosa, 2",
    "sg:city":"Alcala Real",
    "sg:orig_category":"Electrodom\u00c9sticos (al Por Menor)",
    "sg:phone":"+34 953 58 13 53",
    "sg:postcode":"23680",
    "sg:province":"Ja\u00e9n",
    "wof:name":"Electro Comercial 2006 S.l.u.",
    "wof:placetype":"venue"
},
  "geometry": {"coordinates":[-3.9231550694,37.4589233398],"type":"Point"}
}