{
  "type": "Feature",
  "properties": {
    "iso:country":"ES",
    "sg:address":"Calle de Uralde, 8",
    "sg:city":"Iurreta",
    "sg:orig_category":"Promotores Constructores",
    "sg:phone":"+34 946 81 20 86",
    "sg:postcode":"48215",
    "sg:province":"Vizcaya",
    "wof:name":"Construcciones Y Reformas Alda S.l.",
    "wof:placetype":"venue"
},
  "geometry": {"coordinates":[-2.6366410255,43.1739463806],"type":"Point"}
}