{
  "type": "Feature",
  "properties": {
    "iso:country":"ES",
    "sg:address":"Calle de Libertad (de La), 9",
    "sg:city":"Alcobendas",
    "sg:orig_category":"Agencias De Viajes",
    "sg:phone":"+34 916 53 21 99",
    "sg:postcode":"28100",
    "sg:province":"Madrid",
    "sg:website":"www.barceloviajes.com",
    "wof:name":"Viajes Barcelo S.l.",
    "wof:placetype":"venue"
},
  "geometry": {"coordinates":[-3.6342554092,40.5406646729],"type":"Point"}
}