{
  "type": "Feature",
  "properties": {
    "iso:country":"ES",
    "sg:address":"Carrer de Marcel Miralles I Pallares, 6",
    "sg:city":"Ampolla",
    "sg:orig_category":"Farmacias",
    "sg:phone":"+34 977 46 01 52",
    "sg:postcode":"43895",
    "sg:province":"Tarragona",
    "wof:name":"Curto Balague Francisco",
    "wof:placetype":"venue"
},
  "geometry": {"coordinates":[0.7092880011,40.8117904663],"type":"Point"}
}