{
  "type": "Feature",
  "properties": {
    "addr:full":"Avda Arenita, S/n Palm-mar Santa Cruz De Tenerife 38640",
    "addr:housenumber":"s",
    "addr:postcode":"38640",
    "addr:street":"Avda Arenita;/ N Palm-Mar",
    "iso:country":"ES",
    "sg:address":"Avda Arenita, S/n",
    "sg:city":"Palm-mar",
    "sg:orig_category":"Promotores Constructores",
    "sg:phone":"+34 922 69 14 94",
    "sg:postcode":"38640",
    "sg:province":"Santa Cruz De Tenerife",
    "wof:name":"Construcciones Daltre S.l.",
    "wof:placetype":"venue"
},
  "geometry": {"coordinates":[-16.682012558,28.0987625122],"type":"Point"}
}