{
  "type": "Feature",
  "properties": {
    "iso:country":"ES",
    "sg:address":"Pg Doctor Moragas, 204",
    "sg:city":"Barbera Valles",
    "sg:orig_category":"Complementos De Vestir (al Por Menor)",
    "sg:phone":"+34 937 18 93 39",
    "sg:postcode":"08210",
    "sg:province":"Barcelona",
    "wof:name":"Cultura Y Moda S. A.",
    "wof:placetype":"venue"
},
  "geometry": {"coordinates":[2.1250789165,41.5147590637],"type":"Point"}
}