{
  "type": "Feature",
  "properties": {
    "iso:country":"ES",
    "sg:address":"Carrer de Bismarck, 33",
    "sg:city":"Barcelona",
    "sg:classifiers":[
        {
            "category":"Taxi",
            "type":"Transportation"
        }
    ],
    "sg:phone":"+34 932 19 09 14",
    "sg:postcode":"08024",
    "sg:province":"Barcelona",
    "wof:name":"Sanuy Franch Jose",
    "wof:placetype":"venue"
},
  "geometry": {"coordinates":[2.1626620293,41.4154586792],"type":"Point"}
}