{
  "type": "Feature",
  "properties": {
    "addr:full":"Avda Madrid (de), S/n Avila \u00c1vila 05001",
    "addr:postcode":"05001",
    "addr:street":"Avda Madrid De S / N;A\u0301Vila",
    "iso:country":"ES",
    "sg:address":"Avda Madrid (de), S/n",
    "sg:city":"Avila",
    "sg:orig_category":"Promotores Constructores",
    "sg:phone":"+34 920 35 10 53",
    "sg:postcode":"05001",
    "sg:province":"\u00c1vila",
    "wof:name":"Voladuras Controladas S. A.",
    "wof:placetype":"venue"
},
  "geometry": {"coordinates":[-4.6979169846,40.6586875916],"type":"Point"}
}