{
  "type": "Feature",
  "properties": {
    "iso:country":"ES",
    "sg:address":"Avda Doctor Clara, 11",
    "sg:city":"Castellon",
    "sg:orig_category":"Agencias De Trabajo Temporal",
    "sg:phone":"+34 964 25 05 29",
    "sg:postcode":"12002",
    "sg:province":"Castell\u00f3n",
    "wof:name":"Dalgo Grup Empresa Trabajo Temporal S.l.",
    "wof:placetype":"venue"
},
  "geometry": {"coordinates":[-0.0442599989,39.9848594666],"type":"Point"}
}