{
  "type": "Feature",
  "properties": {
    "iso:country":"ES",
    "sg:address":"Avda Carlos De Haya, 61",
    "sg:city":"Malaga",
    "sg:orig_category":"Fabricaci\u00d3n De Muebles De Cocina",
    "sg:phone":"+34 952 28 48 81",
    "sg:postcode":"29010",
    "sg:province":"M\u00e1laga",
    "wof:name":"Europea De Muebles Y Electrodomesticos S.l.",
    "wof:placetype":"venue"
},
  "geometry": {"coordinates":[-4.4478721619,36.7221488953],"type":"Point"}
}