{
  "type": "Feature",
  "properties": {
    "iso:country":"ES",
    "sg:address":"Calle de Doctor Fuster, 10",
    "sg:city":"Huercal-overa",
    "sg:orig_category":"Doctores En Medicina",
    "sg:phone":"+34 950 47 16 62",
    "sg:postcode":"04600",
    "sg:province":"Almer\u00eda",
    "wof:name":"Gamiz Jimenez Jose Maria",
    "wof:placetype":"venue"
},
  "geometry": {"coordinates":[-1.942799449,37.3955879211],"type":"Point"}
}