{
  "type": "Feature",
  "properties": {
    "addr:full":"Santa Amalia Kalea, 7 Ordizia Guip\u00f9zcoa 20240",
    "addr:housenumber":"7",
    "addr:postcode":"20240",
    "addr:street":"Santa Amalia Kalea;Guipu\u0300Zcoa",
    "iso:country":"ES",
    "sg:address":"Santa Amalia Kalea, 7",
    "sg:city":"Ordizia",
    "sg:orig_category":"Promotores Constructores",
    "sg:phone":"+34 943 16 04 65",
    "sg:postcode":"20240",
    "sg:province":"Guip\u00f9zcoa",
    "wof:name":"Tejado Aparicio Juan Jesus",
    "wof:placetype":"venue"
},
  "geometry": {"coordinates":[-2.1799440384,43.0533599854],"type":"Point"}
}