{
  "type": "Feature",
  "properties": {
    "iso:country":"ES",
    "sg:address":"Calle de Federico Garcia Lorca (de), 22",
    "sg:city":"Coslada",
    "sg:orig_category":"Inform\u00c1tica: Material Y Suministros",
    "sg:phone":"+34 916 73 11 00",
    "sg:postcode":"28820",
    "sg:province":"Madrid",
    "wof:name":"Ateo Software S.l.l",
    "wof:placetype":"venue"
},
  "geometry": {"coordinates":[-3.554233551,40.4221839905],"type":"Point"}
}