{
  "type": "Feature",
  "properties": {
    "addr:full":"Calle de Guillermo Roch, 28 Pobla Vallbona Valencia 46185",
    "addr:housenumber":"28",
    "addr:postcode":"46185",
    "addr:street":"Calle De Guillermo Roch",
    "iso:country":"ES",
    "sg:address":"Calle de Guillermo Roch, 28",
    "sg:city":"Pobla Vallbona",
    "sg:orig_category":"M\u00c1quinas De Coser Y De Hacer Punto (al Por Mayor)",
    "sg:phone":"+34 962 76 07 45",
    "sg:postcode":"46185",
    "sg:province":"Valencia",
    "wof:name":"Navarro Roldan Jose Antonio",
    "wof:placetype":"venue"
},
  "geometry": {"coordinates":[-0.5563380122,39.5956916809],"type":"Point"}
}