{
  "type": "Feature",
  "properties": {
    "iso:country":"ES",
    "sg:address":"Calle de Villabona, S/n",
    "sg:city":"Madrid",
    "sg:orig_category":"Carnicer\u00cdas, Carnicer\u00cdas",
    "sg:phone":"+34 913 41 47 06",
    "sg:postcode":"28041",
    "sg:province":"Madrid",
    "wof:name":"Blanco Villanueva Benito",
    "wof:placetype":"venue"
},
  "geometry": {"coordinates":[-3.7150940895,40.3689918518],"type":"Point"}
}