{
  "type": "Feature",
  "properties": {
    "iso:country":"ES",
    "sg:address":"Pase Autonomias (de Las), 6",
    "sg:city":"Huesca",
    "sg:orig_category":"Empresas De Vigilancia, Guardia Y Protecci\u00d3n",
    "sg:phone":"+34 974 21 82 96",
    "sg:postcode":"22004",
    "sg:province":"Huesca",
    "wof:name":"Securitas Direct Espa\u00f1a S.a.",
    "wof:placetype":"venue"
},
  "geometry": {"coordinates":[-0.417930007,42.138168335],"type":"Point"}
}