{
  "type": "Feature",
  "properties": {
    "iso:country":"ES",
    "sg:address":"Carr Rollet, (del), 14",
    "sg:city":"Carlet",
    "sg:orig_category":"Perfumer\u00cda Y Cosm\u00c9tica (fabricaci\u00d3n, Al Por Mayor)",
    "sg:phone":"+34 962 53 02 17",
    "sg:postcode":"46240",
    "sg:province":"Valencia",
    "wof:name":"Miragall Penalba Cristina",
    "wof:placetype":"venue"
},
  "geometry": {"coordinates":[-0.5249720216,39.2315101624],"type":"Point"}
}