{
  "type": "Feature",
  "properties": {
    "addr:full":"Calle de Santisimo Cristo Del Mar, 13 Aduanas Alicante 03730",
    "addr:housenumber":"13",
    "addr:postcode":"03730",
    "addr:street":"Calle De Santisimo Cristo Del Mar",
    "iso:country":"ES",
    "sg:address":"Calle de Santisimo Cristo Del Mar, 13",
    "sg:city":"Aduanas",
    "sg:orig_category":"Cajas De Ahorro",
    "sg:phone":"+34 965 79 35 44",
    "sg:postcode":"03730",
    "sg:province":"Alicante",
    "sg:website":"www.cam.es",
    "wof:name":"Caja De Ahorros Del Mediterraneo",
    "wof:placetype":"venue"
},
  "geometry": {"coordinates":[0.1809979975,38.7952613831],"type":"Point"}
}