{
  "type": "Feature",
  "properties": {
    "iso:country":"ES",
    "sg:address":"Calle de Doctor Verneau, 1",
    "sg:city":"Palmas De Gran Canaria",
    "sg:orig_category":"Inmobiliaria (agencias)",
    "sg:phone":"+34 928 33 72 05",
    "sg:postcode":"35001",
    "sg:province":"Las Palmas",
    "wof:name":"Urbanizacion Monta\u00f1a Alta S.a.",
    "wof:placetype":"venue"
},
  "geometry": {"coordinates":[-15.4150934219,28.0998287201],"type":"Point"}
}