{
  "type": "Feature",
  "properties": {
    "iso:country":"ES",
    "sg:address":"Arrufana, S/n",
    "sg:city":"Mos",
    "sg:orig_category":"Electrodom\u00c9sticos (al Por Menor)",
    "sg:phone":"+34 986 28 81 21",
    "sg:postcode":"36415",
    "sg:province":"Pontevedra",
    "sg:website":"www.mastergalicia.com",
    "wof:name":"Master De Electrodomesticos Del Noroeste",
    "wof:placetype":"venue"
},
  "geometry": {"coordinates":[-8.6026287079,42.2329483032],"type":"Point"}
}