{
  "type": "Feature",
  "properties": {
    "iso:country":"ES",
    "sg:address":"Par. Son Forner, S/n",
    "sg:city":"Begur",
    "sg:orig_category":"Fabricaci\u00d3n, Importaci\u00d3n De L\u00c1mparas Y Bombillas",
    "sg:phone":"+34 972 62 24 55",
    "sg:postcode":"17255",
    "sg:province":"Girona",
    "wof:name":"J.rallo S.cv.",
    "wof:placetype":"venue"
},
  "geometry": {"coordinates":[3.2061150074,41.9516716003],"type":"Point"}
}