{
  "type": "Feature",
  "properties": {
    "addr:full":"Calle de Andres Larrazabal, 6 Arenas -areeta Vizcaya 48930",
    "addr:housenumber":"6;areeta",
    "addr:postcode":"48930",
    "addr:street":"Calle De Andres Larrazabal",
    "iso:country":"ES",
    "sg:address":"Calle de Andres Larrazabal, 6",
    "sg:city":"Arenas -areeta",
    "sg:orig_category":"Electricidad: Instaladores",
    "sg:phone":"+34 944 63 51 90",
    "sg:postcode":"48930",
    "sg:province":"Vizcaya",
    "wof:name":"Zuazo Jauregui Maria Carmen",
    "wof:placetype":"venue"
},
  "geometry": {"coordinates":[-3.0142359734,43.3265800476],"type":"Point"}
}