{
  "type": "Feature",
  "properties": {
    "iso:country":"ES",
    "sg:address":"Calle de Gil Velez, 18",
    "sg:city":"Nerva",
    "sg:orig_category":"Cristaler\u00cdas",
    "sg:phone":"+34 959 58 01 56",
    "sg:postcode":"21670",
    "sg:province":"Huelva",
    "wof:name":"Benitez Perez Gilberto",
    "wof:placetype":"venue"
},
  "geometry": {"coordinates":[-6.5497918129,37.69506073],"type":"Point"}
}