{
  "type": "Feature",
  "properties": {
    "iso:country":"ES",
    "sg:address":"Calle de Puebla De Valverde, 2",
    "sg:city":"Valencia",
    "sg:orig_category":"Empresas De Limpieza",
    "sg:phone":"+34 963 77 89 19",
    "sg:postcode":"46014",
    "sg:province":"Valencia",
    "wof:name":"Amo Marina Concepcion",
    "wof:placetype":"venue"
},
  "geometry": {"coordinates":[-0.4013518095,39.4593429565],"type":"Point"}
}