{
  "type": "Feature",
  "properties": {
    "iso:country":"ES",
    "sg:address":"Queimadi\u00f1a, 39",
    "sg:city":"Salvaterra Mi\u00f1o",
    "sg:orig_category":"Serrer\u00cdas De Madera",
    "sg:phone":"+34 986 65 78 46",
    "sg:postcode":"36457",
    "sg:province":"Pontevedra",
    "wof:name":"Martinez Castro Maria",
    "wof:placetype":"venue"
},
  "geometry": {"coordinates":[-8.4590921402,42.1376533508],"type":"Point"}
}