{
  "type": "Feature",
  "properties": {
    "addr:full":"Via Augusta, 120 Barcelona Barcelona 08006",
    "addr:housenumber":"120",
    "addr:postcode":"08006",
    "addr:street":"Via Augusta",
    "iso:country":"ES",
    "sg:address":"Via Augusta, 120",
    "sg:city":"Barcelona",
    "sg:orig_category":"Grafistas",
    "sg:phone":"+34 932 17 68 60",
    "sg:postcode":"08006",
    "sg:province":"Barcelona",
    "wof:name":"Reverte-aguilar S.l",
    "wof:placetype":"venue"
},
  "geometry": {"coordinates":[2.1477129459,41.4013824463],"type":"Point"}
}