{
  "type": "Feature",
  "properties": {
    "iso:country":"ES",
    "sg:address":"Mcdo Sto Domingo, S/n",
    "sg:city":"Iru\u00f1a",
    "sg:orig_category":"Carnicer\u00cdas, Carnicer\u00cdas",
    "sg:phone":"+34 948 22 59 86",
    "sg:postcode":"31001",
    "sg:province":"Navarra",
    "wof:name":"Iriarte Etxauri Fermin",
    "wof:placetype":"venue"
},
  "geometry": {"coordinates":[-1.6446839571,42.8185958862],"type":"Point"}
}