{
  "type": "Feature",
  "properties": {
    "addr:full":"Gaieta Planellas, 15 El Masnou Barcelona 08320",
    "addr:housenumber":"15",
    "addr:postcode":"08320",
    "addr:street":"Planellas",
    "iso:country":"ES",
    "sg:address":"Gaieta Planellas, 15",
    "sg:city":"El Masnou",
    "sg:orig_category":"Ingenier\u00cda, Centros De Estudios (diversos)",
    "sg:phone":"+34 935 55 40 22",
    "sg:postcode":"08320",
    "sg:province":"Barcelona",
    "wof:name":"Domytec S.l.",
    "wof:placetype":"venue"
},
  "geometry": {"coordinates":[2.3085310459,41.4838638306],"type":"Point"}
}