{
  "type": "Feature",
  "properties": {
    "addr:full":"Calle de Artes Y Oficios, 37 Valencia Valencia 46021",
    "addr:housenumber":"37",
    "addr:postcode":"46021",
    "addr:street":"Calle De Artes Y Oficios",
    "iso:country":"ES",
    "sg:address":"Calle de Artes Y Oficios, 37",
    "sg:city":"Valencia",
    "sg:orig_category":"Perfumer\u00cda Y Cosm\u00c9tica (fabricaci\u00d3n, Al Por Mayor)",
    "sg:phone":"+34 963 93 02 44",
    "sg:postcode":"46021",
    "sg:province":"Valencia",
    "wof:name":"Yamena S.l.",
    "wof:placetype":"venue"
},
  "geometry": {"coordinates":[-0.352619499,39.4678726196],"type":"Point"}
}