{
  "type": "Feature",
  "properties": {
    "iso:country":"ES",
    "sg:address":"Calle de Tajo (del), 7",
    "sg:city":"Mejorada Campo",
    "sg:orig_category":"Deportes Y Ocio: Art\u00cdculos Y Equipos (al Por Mayor)",
    "sg:phone":"+34 916 79 40 01",
    "sg:postcode":"28840",
    "sg:province":"Madrid",
    "wof:name":"Davor Sports Europe S.a.",
    "wof:placetype":"venue"
},
  "geometry": {"coordinates":[-3.4873709679,40.3851165771],"type":"Point"}
}