{
  "type": "Feature",
  "properties": {
    "addr:full":"Calle de Arriba, 2 Santiago De Las Villas Le\u00f3n 24123",
    "addr:housenumber":"2",
    "addr:postcode":"24123",
    "addr:street":"Calle De Arriba;Santiago De Las;Leo\u0301N",
    "iso:country":"ES",
    "sg:address":"Calle de Arriba, 2",
    "sg:city":"Santiago De Las Villas",
    "sg:orig_category":"T\u00c9cnicos Veterinarios",
    "sg:phone":"+34 987 59 20 31",
    "sg:postcode":"24123",
    "sg:province":"Le\u00f3n",
    "wof:name":"Alonso De La Hoz Carlos",
    "wof:placetype":"venue"
},
  "geometry": {"coordinates":[-5.7362880707,42.8020439148],"type":"Point"}
}