{
  "type": "Feature",
  "properties": {
    "iso:country":"ES",
    "sg:address":"Calle de Bailen, 79",
    "sg:city":"Aspe",
    "sg:orig_category":"Ropa Y Art\u00cdculos Pre",
    "sg:phone":"+34 965 49 01 00",
    "sg:postcode":"03680",
    "sg:province":"Alicante",
    "wof:name":"Comercial Marisa S.l.",
    "wof:placetype":"venue"
},
  "geometry": {"coordinates":[-0.7630105019,38.3474807739],"type":"Point"}
}