{
  "type": "Feature",
  "properties": {
    "addr:full":"Plaz Vasco Nu\u00d1ez De Balboa, 3 Jerez De Los Caballeros Badajoz 06380",
    "addr:postcode":"06380",
    "addr:street":"Nun\u0303Ez;Balboa",
    "iso:country":"ES",
    "sg:address":"Plaz Vasco Nu\u00d1ez De Balboa, 3",
    "sg:city":"Jerez De Los Caballeros",
    "sg:orig_category":"Molduras, Junquillos, Listones Y Molduras Perforadas",
    "sg:phone":"+34 924 73 05 01",
    "sg:postcode":"06380",
    "sg:province":"Badajoz",
    "wof:name":"Castilla Moreno Francisco Jose",
    "wof:placetype":"venue"
},
  "geometry": {"coordinates":[-6.7698688507,38.3207168579],"type":"Point"}
}