{
  "type": "Feature",
  "properties": {
    "iso:country":"ES",
    "sg:address":"Ctra. D'inca, 57",
    "sg:city":"Sa Pobla",
    "sg:orig_category":"Mec\u00c1nico Del Autom\u00d3vil",
    "sg:phone":"+34 971 54 09 88",
    "sg:postcode":"07420",
    "sg:province":"Islas Baleares",
    "wof:name":"Polauto S.l.",
    "wof:placetype":"venue"
},
  "geometry": {"coordinates":[3.0163040161,39.7713813782],"type":"Point"}
}