{
  "type": "Feature",
  "properties": {
    "addr:full":"Calle de Eduardo Barriobero, S/n Entrena La Rioja 26375",
    "addr:housenumber":"s",
    "addr:postcode":"26375",
    "addr:street":"Calle De Eduardo Barriobero;/ N Entrena;Rioja",
    "iso:country":"ES",
    "sg:address":"Calle de Eduardo Barriobero, S/n",
    "sg:city":"Entrena",
    "sg:orig_category":"Transportes Frigor\u00cdficos",
    "sg:phone":"+34 941 44 61 65",
    "sg:postcode":"26375",
    "sg:province":"La Rioja",
    "wof:name":"Corral Garcia Eduardo Jose",
    "wof:placetype":"venue"
},
  "geometry": {"coordinates":[-2.5300240517,42.3865242004],"type":"Point"}
}