{
  "type": "Feature",
  "properties": {
    "addr:full":"Calle de Pozuelo, 11 Colmenar Oreja Madrid 28380",
    "addr:housenumber":"11",
    "addr:postcode":"28380",
    "addr:street":"Calle De Pozuelo",
    "iso:country":"ES",
    "sg:address":"Calle de Pozuelo, 11",
    "sg:city":"Colmenar Oreja",
    "sg:orig_category":"Ingenier\u00cda, Centros De Estudios (diversos)",
    "sg:phone":"+34 918 08 94 90",
    "sg:postcode":"28380",
    "sg:province":"Madrid",
    "wof:name":"Julian Olivas E Hijo S.l.",
    "wof:placetype":"venue"
},
  "geometry": {"coordinates":[-3.3836092949,40.1107597351],"type":"Point"}
}