{
  "type": "Feature",
  "properties": {
    "addr:full":"Carrer de Monistrol, 31 Eixample Barcelona 08150",
    "addr:housenumber":"31",
    "addr:postcode":"08150",
    "addr:street":"Carrer De Monistrol",
    "iso:country":"ES",
    "sg:address":"Carrer de Monistrol, 31",
    "sg:city":"Eixample",
    "sg:orig_category":"Sociedades, Compa\u00d1\u00cdas Aseguradoras",
    "sg:phone":"+34 935 62 27 54",
    "sg:postcode":"08150",
    "sg:province":"Barcelona",
    "wof:name":"Mapfre Servicios De Informatica",
    "wof:placetype":"venue"
},
  "geometry": {"coordinates":[2.2293000221,41.5678787231],"type":"Point"}
}