{
  "type": "Feature",
  "properties": {
    "iso:country":"ES",
    "sg:address":"Carr Vilafant, 40",
    "sg:city":"Figueres",
    "sg:orig_category":"Psic\u00d3logos",
    "sg:phone":"+34 972 67 02 18",
    "sg:postcode":"17600",
    "sg:province":"Girona",
    "wof:name":"Musquera Musquera Carme",
    "wof:placetype":"venue"
},
  "geometry": {"coordinates":[2.9589879513,42.2640533447],"type":"Point"}
}