{
  "type": "Feature",
  "properties": {
    "iso:country":"ES",
    "sg:address":"Calle de Obispo Almarcha, 43",
    "sg:city":"Le\u00f3n",
    "sg:orig_category":"Caf\u00c9s, Bares, Cervecer\u00cdas",
    "sg:phone":"+34 987 25 55 12",
    "sg:postcode":"24006",
    "sg:province":"Le\u00f3n",
    "wof:name":"Martinez Rodriguez Valerino",
    "wof:placetype":"venue"
},
  "geometry": {"coordinates":[-5.5617771149,42.5998954773],"type":"Point"}
}