{
  "type": "Feature",
  "properties": {
    "iso:country":"ES",
    "sg:address":"Carrer de Pablo Iglesias, 41",
    "sg:city":"Terrassa",
    "sg:orig_category":"Institutos De Belleza",
    "sg:phone":"+34 937 88 84 16",
    "sg:postcode":"08224",
    "sg:province":"Barcelona",
    "wof:name":"Martin Escabia Ana Maria",
    "wof:placetype":"venue"
},
  "geometry": {"coordinates":[1.9898810387,41.5578765869],"type":"Point"}
}