{
  "type": "Feature",
  "properties": {
    "addr:full":"Rua Pazos Fontenla, 37 Bueu Pontevedra 36930",
    "addr:housenumber":"37",
    "addr:postcode":"36930",
    "addr:street":"Rua Pazos Fontenla",
    "iso:country":"ES",
    "sg:address":"Rua Pazos Fontenla, 37",
    "sg:city":"Bueu",
    "sg:orig_category":"Peluquer\u00cdas",
    "sg:phone":"+34 986 32 34 07",
    "sg:postcode":"36930",
    "sg:province":"Pontevedra",
    "wof:name":"Freire Pastoriza Rosario",
    "wof:placetype":"venue"
},
  "geometry": {"coordinates":[-8.792550087,42.3265037537],"type":"Point"}
}