{
  "type": "Feature",
  "properties": {
    "iso:country":"ES",
    "sg:address":"Calle de Jazmin, 78",
    "sg:city":"Madrid",
    "sg:orig_category":"Empresarios Y Productoras De Espect\u00c1culos",
    "sg:phone":"+34 913 02 62 22",
    "sg:postcode":"28033",
    "sg:province":"Madrid",
    "sg:website":"www.serenataproductions.com",
    "wof:name":"Serenata Productions S.l.",
    "wof:placetype":"venue"
},
  "geometry": {"coordinates":[-3.6631720066,40.482006073],"type":"Point"}
}