{
  "type": "Feature",
  "properties": {
    "iso:country":"ES",
    "sg:address":"Carrer de Nobel, 10",
    "sg:city":"Barcelona",
    "sg:orig_category":"Fabricaci\u00d3n De Mobiliario De Oficina",
    "sg:phone":"+34 933 40 51 12",
    "sg:postcode":"08027",
    "sg:province":"Barcelona",
    "wof:name":"Prat Llinas Josefa",
    "wof:placetype":"venue"
},
  "geometry": {"coordinates":[2.1894109249,41.4232063293],"type":"Point"}
}