{
  "type": "Feature",
  "properties": {
    "iso:country":"ES",
    "sg:address":"Calle de Valle Del Corneja, 2",
    "sg:city":"Avila",
    "sg:classifiers":[
        {
            "category":"Autos & Motor Vehicles",
            "subcategory":"Automobile Sales",
            "type":"Retail Goods"
        }
    ],
    "sg:phone":"+34 920 22 05 68",
    "sg:postcode":"05002",
    "sg:province":"\u00c1vila",
    "wof:name":"Sociedad Cooperativa Limitada Autoescuela Picasso",
    "wof:placetype":"venue"
},
  "geometry": {"coordinates":[-4.7017149925,40.6503791809],"type":"Point"}
}