{
  "type": "Feature",
  "properties": {
    "iso:country":"ES",
    "sg:address":"Calle de Pintor Gisbert, 38",
    "sg:city":"Alacant",
    "sg:orig_category":"Encuadernaci\u00d3n E Impresi\u00d3n De Folletos",
    "sg:phone":"+34 965 13 10 71",
    "sg:postcode":"03005",
    "sg:province":"Alicante",
    "wof:name":"Diaz Martinez Juana",
    "wof:placetype":"venue"
},
  "geometry": {"coordinates":[-0.4965609908,38.3480949402],"type":"Point"}
}