{
  "type": "Feature",
  "properties": {
    "addr:full":"Av. San Ignacio, 7 Iru\u00f1a Navarra 31002",
    "addr:housenumber":"7",
    "addr:postcode":"31002",
    "addr:street":"Av. San Ignacio",
    "iso:country":"ES",
    "sg:address":"Av. San Ignacio, 7",
    "sg:city":"Iru\u00f1a",
    "sg:orig_category":"Librer\u00cdas",
    "sg:phone":"+34 948 22 73 18",
    "sg:postcode":"31002",
    "sg:province":"Navarra",
    "wof:name":"Berdonces Lafraya Jose Luis",
    "wof:placetype":"venue"
},
  "geometry": {"coordinates":[-1.6429100037,42.8140258789],"type":"Point"}
}