{
  "type": "Feature",
  "properties": {
    "iso:country":"ES",
    "sg:address":"Calle de Lerida, 9",
    "sg:city":"Valencia",
    "sg:orig_category":"Asesor\u00cdas Y Estudios Financieros",
    "sg:phone":"+34 963 47 05 27",
    "sg:postcode":"46009",
    "sg:province":"Valencia",
    "wof:name":"Fos Argente Vicente",
    "wof:placetype":"venue"
},
  "geometry": {"coordinates":[-0.3758890033,39.4835624695],"type":"Point"}
}