{
  "type": "Feature",
  "properties": {
    "addr:full":"Atalaya, 21 La Atalaya M\u00e1laga 29340",
    "addr:housenumber":"21",
    "addr:postcode":"29340",
    "addr:street":"Atalaya",
    "iso:country":"ES",
    "sg:address":"Atalaya, 21",
    "sg:city":"La Atalaya",
    "sg:orig_category":"Autob\u00das (explotaci\u00d3n Y Servicios De)",
    "sg:phone":"+34 952 18 32 45",
    "sg:postcode":"29340",
    "sg:province":"M\u00e1laga",
    "wof:name":"Autocares Lumayor S.l.",
    "wof:placetype":"venue"
},
  "geometry": {"coordinates":[-4.4516897202,37.1897277832],"type":"Point"}
}