{
  "type": "Feature",
  "properties": {
    "addr:full":"Carrer de Vallirana, 83 Barcelona Barcelona 08006",
    "addr:housenumber":"83",
    "addr:postcode":"08006",
    "addr:street":"Carrer De Vallirana",
    "iso:country":"ES",
    "sg:address":"Carrer de Vallirana, 83",
    "sg:city":"Barcelona",
    "sg:orig_category":"Asesor\u00cda Fiscal Y Jur\u00cddica",
    "sg:phone":"+34 934 18 63 99",
    "sg:postcode":"08006",
    "sg:province":"Barcelona",
    "sg:website":"labora@tiservinet.es",
    "wof:name":"Asesoria Integral Labora S. L.",
    "wof:placetype":"venue"
},
  "geometry": {"coordinates":[2.1455395222,41.4055480957],"type":"Point"}
}