{
  "type": "Feature",
  "properties": {
    "addr:full":"Calle de Poligono Industrial La Frontera 2, 71 Ugena Toledo 45217",
    "addr:housenumber":"2 71",
    "addr:postcode":"45217",
    "addr:street":"Calle De Poligono Industrial La",
    "iso:country":"ES",
    "sg:address":"Calle de Poligono Industrial La Frontera 2, 71",
    "sg:city":"Ugena",
    "sg:orig_category":"Almacenes De Venta: Muebles, Equipo Para El Hogar",
    "sg:phone":"+34 925 59 24 83",
    "sg:postcode":"45217",
    "sg:province":"Toledo",
    "wof:name":"Allwoos S.l.",
    "wof:placetype":"venue"
},
  "geometry": {"coordinates":[-3.8706207275,40.1677322388],"type":"Point"}
}