{
  "type": "Feature",
  "properties": {
    "iso:country":"ES",
    "sg:address":"Ptda Santa Ana, 86",
    "sg:city":"Guardamar Segura",
    "sg:orig_category":"Fabricaci\u00d3n, Comercio De Flores Y Plantas Artificiales",
    "sg:phone":"+34 965 72 98 30",
    "sg:postcode":"03140",
    "sg:province":"Alicante",
    "wof:name":"Mister Plant S.l.",
    "wof:placetype":"venue"
},
  "geometry": {"coordinates":[-0.6540290117,38.086681366],"type":"Point"}
}