{
  "type": "Feature",
  "properties": {
    "addr:full":"Calle de Moreras, 64 Villamiel De Toledo Toledo 45594",
    "addr:housenumber":"64",
    "addr:postcode":"45594",
    "addr:street":"Calle De Moreras",
    "iso:country":"ES",
    "sg:address":"Calle de Moreras, 64",
    "sg:city":"Villamiel De Toledo",
    "sg:orig_category":"Agencias Y Asesores De Publicidad",
    "sg:phone":"+34 925 74 03 17",
    "sg:postcode":"45594",
    "sg:province":"Toledo",
    "wof:name":"Open House Comunicacion S.l.",
    "wof:placetype":"venue"
},
  "geometry": {"coordinates":[-4.130838871,39.9813995361],"type":"Point"}
}