{
  "type": "Feature",
  "properties": {
    "iso:country":"ES",
    "sg:address":"Plce Toqueros (de), 7",
    "sg:city":"Granada",
    "sg:orig_category":"Asociaciones, Organismos Culturales Y Socioeducativos",
    "sg:phone":"+34 958 22 77 12",
    "sg:postcode":"18010",
    "sg:province":"Granada",
    "wof:name":"Pe\u00f1a La Plateria",
    "wof:placetype":"venue"
},
  "geometry": {"coordinates":[-3.5903298855,37.180480957],"type":"Point"}
}