{
  "type": "Feature",
  "properties": {
    "iso:country":"ES",
    "sg:address":"Avda Ancha De Castelar, 24",
    "sg:city":"San Vicente Del Raspeig-sant Vicent Del Raspeig",
    "sg:orig_category":"Agencias Y Agentes Comerciales, Representantes",
    "sg:phone":"+34 965 66 75 80",
    "sg:postcode":"03690",
    "sg:province":"Alicante",
    "wof:name":"Comercial Jj Raspeig L",
    "wof:placetype":"venue"
},
  "geometry": {"coordinates":[-0.5210610032,38.3958511353],"type":"Point"}
}