{
  "type": "Feature",
  "properties": {
    "addr:full":"Carrer de Josep Miret, 35 Barcelona Barcelona 08020",
    "addr:housenumber":"35",
    "addr:postcode":"08020",
    "addr:street":"Carrer De Josep Miret",
    "iso:country":"ES",
    "sg:address":"Carrer de Josep Miret, 35",
    "sg:city":"Barcelona",
    "sg:orig_category":"Electricidad: Instaladores",
    "sg:phone":"+34 933 14 17 44",
    "sg:postcode":"08020",
    "sg:province":"Barcelona",
    "wof:name":"Insermatic S.c.p.",
    "wof:placetype":"venue"
},
  "geometry": {"coordinates":[2.1997969151,41.4233436584],"type":"Point"}
}