{
  "type": "Feature",
  "properties": {
    "addr:full":"Carrer de Julia Alvarez, 3 Palma Islas Baleares 07004",
    "addr:housenumber":"3",
    "addr:postcode":"07004",
    "addr:street":"Carrer De Julia Alvarez",
    "iso:country":"ES",
    "sg:address":"Carrer de Julia Alvarez, 3",
    "sg:city":"Palma",
    "sg:orig_category":"Sindicatos Y Colegios Profesionales",
    "sg:phone":"+34 971 29 99 54",
    "sg:postcode":"07004",
    "sg:province":"Islas Baleares",
    "wof:name":"Asociacion Espa\u00d1ola De Ingenieros De Telecomunicacion",
    "wof:placetype":"venue"
},
  "geometry": {"coordinates":[2.653826952,39.5798568726],"type":"Point"}
}