{
  "type": "Feature",
  "properties": {
    "addr:full":"Av Moli, 37 Viladecans Barcelona 08840",
    "addr:housenumber":"37",
    "addr:postcode":"08840",
    "addr:street":"Av Moli",
    "iso:country":"ES",
    "sg:address":"Av Moli, 37",
    "sg:city":"Viladecans",
    "sg:orig_category":"Peleter\u00cdas",
    "sg:phone":"+34 936 58 12 58",
    "sg:postcode":"08840",
    "sg:province":"Barcelona",
    "wof:name":"Gimarpell S.l.",
    "wof:placetype":"venue"
},
  "geometry": {"coordinates":[2.0110459328,41.3218574524],"type":"Point"}
}