{
  "type": "Feature",
  "properties": {
    "iso:country":"ES",
    "sg:address":"Rond Torrassa, 86",
    "sg:city":"Hospitalet Llobregat",
    "sg:orig_category":"Asesor\u00cda Fiscal Y Jur\u00cddica",
    "sg:phone":"+34 934 31 30 71",
    "sg:postcode":"08903",
    "sg:province":"Barcelona",
    "wof:name":"Lavilla Aguilera Jose Luis",
    "wof:placetype":"venue"
},
  "geometry": {"coordinates":[2.1248500347,41.3689804077],"type":"Point"}
}