{
  "type": "Feature",
  "properties": {
    "addr:full":"Calle de Soria, 8 Torrejon Ardoz Madrid 28850",
    "addr:housenumber":"8",
    "addr:postcode":"28850",
    "addr:street":"Calle De Soria",
    "iso:country":"ES",
    "sg:address":"Calle de Soria, 8",
    "sg:city":"Torrejon Ardoz",
    "sg:orig_category":"Molduras, Junquillos, Listones Y Molduras Perforadas",
    "sg:phone":"+34 916 75 87 37",
    "sg:postcode":"28850",
    "sg:province":"Madrid",
    "wof:name":"Lanchades Herrero Luis Maria",
    "wof:placetype":"venue"
},
  "geometry": {"coordinates":[-3.4807469845,40.4549636841],"type":"Point"}
}