{
  "type": "Feature",
  "properties": {
    "iso:country":"ES",
    "sg:address":"Calle de Errementari Kalea, 1",
    "sg:city":"Tolosa",
    "sg:orig_category":"Sindicatos De Trabajadores",
    "sg:phone":"+34 943 67 16 95",
    "sg:postcode":"20400",
    "sg:province":"Guip\u00f9zcoa",
    "wof:name":"Comisiones Obreras De Euskadi",
    "wof:placetype":"venue"
},
  "geometry": {"coordinates":[-2.0730819702,43.1379127502],"type":"Point"}
}