{
  "type": "Feature",
  "properties": {
    "addr:full":"Plaz Cruz De Humilladero, 6 Malaga M\u00e1laga 29006",
    "addr:housenumber":"6",
    "addr:postcode":"29006",
    "addr:street":"Plaz Cruz De Humilladero;Ma\u0301Laga",
    "iso:country":"ES",
    "sg:address":"Plaz Cruz De Humilladero, 6",
    "sg:city":"Malaga",
    "sg:orig_category":"Cajas Para Embalar",
    "sg:phone":"+34 952 04 02 90",
    "sg:postcode":"29006",
    "sg:province":"M\u00e1laga",
    "sg:website":"www.cajamar.es",
    "wof:name":"Cajamar",
    "wof:placetype":"venue"
},
  "geometry": {"coordinates":[-4.4412140846,36.7119598389],"type":"Point"}
}