{
  "type": "Feature",
  "properties": {
    "iso:country":"ES",
    "sg:address":"Calle de Muerte Y Vida, 9",
    "sg:city":"Segovia",
    "sg:orig_category":"Fabricaci\u00d3n De Peines Y De Accesorios De Peluquer\u00cda",
    "sg:phone":"+34 921 44 34 87",
    "sg:postcode":"40005",
    "sg:province":"Segovia",
    "wof:name":"Mu\u00f1oz Miguel Rufina",
    "wof:placetype":"venue"
},
  "geometry": {"coordinates":[-4.1171565056,40.9455757141],"type":"Point"}
}