{
  "type": "Feature",
  "properties": {
    "iso:country":"ES",
    "sg:address":"Calle de Plano San Francisco, S/n",
    "sg:city":"San Pedro",
    "sg:orig_category":"Carnicer\u00cdas, Carnicer\u00cdas",
    "sg:phone":"+34 968 21 58 38",
    "sg:postcode":"30004",
    "sg:province":"Murcia",
    "wof:name":"Nicolas Campoy Carmen",
    "wof:placetype":"venue"
},
  "geometry": {"coordinates":[-0.7915859222,37.8350410461],"type":"Point"}
}