{
  "type": "Feature",
  "properties": {
    "addr:full":"Carrer de Cardaire, 32 Terrassa Barcelona 08221",
    "addr:housenumber":"32",
    "addr:postcode":"08221",
    "addr:street":"Carrer De Cardaire",
    "iso:country":"ES",
    "sg:address":"Carrer de Cardaire, 32",
    "sg:city":"Terrassa",
    "sg:orig_category":"Asociaciones, Organismos Culturales Y Socioeducativos",
    "sg:phone":"+34 937 83 93 56",
    "sg:postcode":"08221",
    "sg:province":"Barcelona",
    "wof:name":"Asociacion Valira",
    "wof:placetype":"venue"
},
  "geometry": {"coordinates":[2.0125074387,41.5638923645],"type":"Point"}
}