{
  "type": "Feature",
  "properties": {
    "addr:full":"Av Gava, 70 Viladecans Barcelona 08840",
    "addr:housenumber":"70",
    "addr:postcode":"08840",
    "addr:street":"Av Gava",
    "iso:country":"ES",
    "sg:address":"Av Gava, 70",
    "sg:city":"Viladecans",
    "sg:orig_category":"Electricidad: Instaladores",
    "sg:phone":"+34 936 58 47 29",
    "sg:postcode":"08840",
    "sg:province":"Barcelona",
    "wof:name":"Instadom S.l.",
    "wof:placetype":"venue"
},
  "geometry": {"coordinates":[2.0103030205,41.3087997437],"type":"Point"}
}