{
  "type": "Feature",
  "properties": {
    "addr:full":"Carrer de Manso, 52 Barcelona Barcelona 08015",
    "addr:housenumber":"52",
    "addr:postcode":"08015",
    "addr:street":"Carrer De Manso",
    "iso:country":"ES",
    "sg:address":"Carrer de Manso, 52",
    "sg:city":"Barcelona",
    "sg:orig_category":"Molduras, Junquillos, Listones Y Molduras Perforadas",
    "sg:phone":"+34 934 42 56 24",
    "sg:postcode":"08015",
    "sg:province":"Barcelona",
    "wof:name":"Jordana Ferrer Rafael",
    "wof:placetype":"venue"
},
  "geometry": {"coordinates":[2.1616270542,41.3772735596],"type":"Point"}
}