{
  "type": "Feature",
  "properties": {
    "addr:full":"Avda Rey Juan Carlos I, 84 Roquetas Mar Almer\u00eda 04740",
    "addr:housenumber":"84",
    "addr:postcode":"04740",
    "addr:street":"Avda Rey Juan Carlos I;Mar Almeri\u0301A",
    "iso:country":"ES",
    "sg:address":"Avda Rey Juan Carlos I, 84",
    "sg:city":"Roquetas Mar",
    "sg:orig_category":"Inmobiliaria (agencias)",
    "sg:phone":"+34 950 32 10 08",
    "sg:postcode":"04740",
    "sg:province":"Almer\u00eda",
    "wof:name":"Lopez Martin Emilio",
    "wof:placetype":"venue"
},
  "geometry": {"coordinates":[-2.61282897,36.765411377],"type":"Point"}
}