{
  "type": "Feature",
  "properties": {
    "addr:full":"Av Ignasi Wallis, 35 Eivissa Islas Baleares 07800",
    "addr:housenumber":"35",
    "addr:postcode":"07800",
    "addr:street":"Av Ignasi Wallis",
    "iso:country":"ES",
    "sg:address":"Av Ignasi Wallis, 35",
    "sg:city":"Eivissa",
    "sg:orig_category":"M\u00c9dicos: Estomatolog\u00cda",
    "sg:phone":"+34 971 31 78 26",
    "sg:postcode":"07800",
    "sg:province":"Islas Baleares",
    "wof:name":"Mayordomo Riera Miguel",
    "wof:placetype":"venue"
},
  "geometry": {"coordinates":[1.4303460121,38.9118537903],"type":"Point"}
}