{
  "type": "Feature",
  "properties": {
    "addr:full":"Av Rapita (de La), 86 Amposta Tarragona 43870",
    "addr:housenumber":"86",
    "addr:postcode":"43870",
    "addr:street":"Av Rapita De La",
    "iso:country":"ES",
    "sg:address":"Av Rapita (de La), 86",
    "sg:city":"Amposta",
    "sg:orig_category":"Peluquer\u00cdas, Peluquer\u00cda Mixta",
    "sg:phone":"+34 977 70 67 21",
    "sg:postcode":"43870",
    "sg:province":"Tarragona",
    "wof:name":"Roig Caballe Eva Maria",
    "wof:placetype":"venue"
},
  "geometry": {"coordinates":[0.5796539783,40.7078895569],"type":"Point"}
}