{
  "type": "Feature",
  "properties": {
    "addr:full":"Avda Gran Via Del Este, 1 Madrid Madrid 28032",
    "addr:housenumber":"1",
    "addr:postcode":"28032",
    "addr:street":"Avda Gran Via Del Este",
    "iso:country":"ES",
    "sg:address":"Avda Gran Via Del Este, 1",
    "sg:city":"Madrid",
    "sg:orig_category":"Marketing Directo",
    "sg:phone":"+34 915 19 32 86",
    "sg:postcode":"28032",
    "sg:province":"Madrid",
    "sg:website":"www.ibermail.es",
    "wof:name":"Iber Mail Europa S.l.",
    "wof:placetype":"venue"
},
  "geometry": {"coordinates":[-3.5958430767,40.4027099609],"type":"Point"}
}