{
  "type": "Feature",
  "properties": {
    "iso:country":"ES",
    "sg:address":"Pasaje Lucena, 37",
    "sg:city":"Antequera",
    "sg:orig_category":"Ropa Para Se\u00d1oras (al Por Menor)",
    "sg:phone":"+34 952 84 45 99",
    "sg:postcode":"29200",
    "sg:province":"M\u00e1laga",
    "wof:name":"Narbona Bravo Dolores",
    "wof:placetype":"venue"
},
  "geometry": {"coordinates":[-4.5602087975,37.0189971924],"type":"Point"}
}