{
  "type": "Feature",
  "properties": {
    "addr:full":"Ctra Barcelona, 145 Barbera Valles Barcelona 08210",
    "addr:housenumber":"145",
    "addr:postcode":"08210",
    "addr:street":"Ctra Barcelona",
    "iso:country":"ES",
    "sg:address":"Ctra Barcelona, 145",
    "sg:city":"Barbera Valles",
    "sg:orig_category":"Cerrajer\u00cda, Ferrallista",
    "sg:phone":"+34 937 18 24 57",
    "sg:postcode":"08210",
    "sg:province":"Barcelona",
    "wof:name":"Cordero Herrera Gregorio",
    "wof:placetype":"venue"
},
  "geometry": {"coordinates":[2.1267559528,41.5156135559],"type":"Point"}
}