{
  "type": "Feature",
  "properties": {
    "iso:country":"ES",
    "sg:address":"Pase Chopera (de La), 93",
    "sg:city":"Alcobendas",
    "sg:orig_category":"Empresas De Portes Y Mensajer\u00cda",
    "sg:phone":"+34 916 62 57 60",
    "sg:postcode":"28100",
    "sg:province":"Madrid",
    "wof:name":"Ramirez Acebo Jesus",
    "wof:placetype":"venue"
},
  "geometry": {"coordinates":[-3.6470708847,40.5445022583],"type":"Point"}
}