{
  "type": "Feature",
  "properties": {
    "iso:country":"ES",
    "sg:address":"Carrer de Ferrer De Blanes, 7",
    "sg:city":"Barcelona",
    "sg:orig_category":"Labores Dom\u00c9sticas",
    "sg:phone":"+34 932 18 71 09",
    "sg:postcode":"08012",
    "sg:province":"Barcelona",
    "wof:name":"Martinez Gil Andres",
    "wof:placetype":"venue"
},
  "geometry": {"coordinates":[2.1589229107,41.3984527588],"type":"Point"}
}