{
  "type": "Feature",
  "properties": {
    "iso:country":"ES",
    "sg:address":"Rbla Josep Tomas Ventosa, 13",
    "sg:city":"Vilanova I La Geltru",
    "sg:orig_category":"Restaurantes",
    "sg:phone":"+34 938 15 54 69",
    "sg:postcode":"08800",
    "sg:province":"Barcelona",
    "wof:name":"Gutierrez Aguilar Sandra",
    "wof:placetype":"venue"
},
  "geometry": {"coordinates":[1.7284749746,41.2215156555],"type":"Point"}
}