{
  "type": "Feature",
  "properties": {
    "addr:full":"Calle de Padre Mendez, 94 Torrent Valencia 46900",
    "addr:housenumber":"94",
    "addr:postcode":"46900",
    "addr:street":"Calle De Padre Mendez;Valencia",
    "iso:country":"ES",
    "sg:address":"Calle de Padre Mendez, 94",
    "sg:city":"Torrent",
    "sg:orig_category":"Transportes Por V\u00cdas Navegables",
    "sg:phone":"+34 961 57 17 12",
    "sg:postcode":"46900",
    "sg:province":"Valencia",
    "wof:name":"Sototrans S.a.",
    "wof:placetype":"venue"
},
  "geometry": {"coordinates":[-0.4770444036,39.4272651672],"type":"Point"}
}