{
  "type": "Feature",
  "properties": {
    "iso:country":"ES",
    "sg:address":"Calle de Betsaide, 9",
    "sg:city":"Elorrio",
    "sg:orig_category":"Electricidad Veh\u00cdculo",
    "sg:phone":"+34 946 58 30 60",
    "sg:postcode":"48230",
    "sg:province":"Vizcaya",
    "wof:name":"Quesada Lozano Luis",
    "wof:placetype":"venue"
},
  "geometry": {"coordinates":[-2.5431315899,43.1250686646],"type":"Point"}
}