{
  "type": "Feature",
  "properties": {
    "iso:country":"ES",
    "sg:address":"Plaz Virgen Del Mar, 5",
    "sg:city":"Santurtzi",
    "sg:orig_category":"Carnicer\u00cdas, Carnicer\u00cdas",
    "sg:phone":"+34 944 83 23 97",
    "sg:postcode":"48980",
    "sg:province":"Vizcaya",
    "wof:name":"Martin Lopez Jose Luis",
    "wof:placetype":"venue"
},
  "geometry": {"coordinates":[-3.0361790657,43.3311805725],"type":"Point"}
}