{
  "type": "Feature",
  "properties": {
    "iso:country":"ES",
    "sg:address":"Calle de Monestir De Poblet, 30",
    "sg:city":"Valencia",
    "sg:classifiers":[
        {
            "category":"Professional",
            "subcategory":"Research",
            "type":"Services"
        }
    ],
    "sg:phone":"+34 963 48 97 17",
    "sg:postcode":"46015",
    "sg:province":"Valencia",
    "sg:tags":[
        "mercado",
        "de",
        "estudios"
    ],
    "wof:name":"Pregunta Y Opinio De Mercados S.l.",
    "wof:placetype":"venue"
},
  "geometry": {"coordinates":[-0.3945789933,39.4850578308],"type":"Point"}
}