{
  "type": "Feature",
  "properties": {
    "addr:full":"Carr Major, 4 Balaguer Lleida 25600",
    "addr:housenumber":"4",
    "addr:postcode":"25600",
    "addr:street":"Carr Major",
    "iso:country":"ES",
    "sg:address":"Carr Major, 4",
    "sg:city":"Balaguer",
    "sg:orig_category":"Panader\u00cdas, Panader\u00cdas",
    "sg:phone":"+34 973 44 52 94",
    "sg:postcode":"25600",
    "sg:province":"Lleida",
    "wof:name":"Pastisseria Graells S.l.",
    "wof:placetype":"venue"
},
  "geometry": {"coordinates":[0.8056330085,41.790058136],"type":"Point"}
}