{
  "type": "Feature",
  "properties": {
    "iso:country":"ES",
    "sg:address":"Grup Sagarminaga, 30",
    "sg:city":"Bilbao",
    "sg:orig_category":"Molduras, Junquillos, Listones Y Molduras Perforadas",
    "sg:phone":"+34 944 12 92 38",
    "sg:postcode":"48004",
    "sg:province":"Vizcaya",
    "wof:name":"Antonio Cura Linares",
    "wof:placetype":"venue"
},
  "geometry": {"coordinates":[-2.9112017155,43.2492179871],"type":"Point"}
}