{
  "type": "Feature",
  "properties": {
    "addr:full":"Carr Madrid, 37 Eivissa Islas Baleares 07800",
    "addr:housenumber":"37",
    "addr:postcode":"07800",
    "addr:street":"Carr Madrid",
    "iso:country":"ES",
    "sg:address":"Carr Madrid, 37",
    "sg:city":"Eivissa",
    "sg:orig_category":"Sociedades, Compa\u00d1\u00cdas Aseguradoras",
    "sg:phone":"+34 971 19 14 38",
    "sg:postcode":"07800",
    "sg:province":"Islas Baleares",
    "wof:name":"Zurich Espa\u00d1a S.a.",
    "wof:placetype":"venue"
},
  "geometry": {"coordinates":[1.4297623634,38.9119148254],"type":"Point"}
}