{
  "type": "Feature",
  "properties": {
    "iso:country":"ES",
    "sg:address":"Calle de Malva, 56",
    "sg:city":"Lucena Puerto",
    "sg:orig_category":"Estancos",
    "sg:phone":"+34 959 36 00 33",
    "sg:postcode":"21820",
    "sg:province":"Huelva",
    "wof:name":"Moreno Regidor Maria",
    "wof:placetype":"venue"
},
  "geometry": {"coordinates":[-6.7284274101,37.3040046692],"type":"Point"}
}