{
  "type": "Feature",
  "properties": {
    "addr:full":"Calle de Lope De Vega, 5 Velez-malaga M\u00e1laga 29700",
    "addr:housenumber":"5",
    "addr:postcode":"29700",
    "addr:street":"Calle De Lope De Vega",
    "iso:country":"ES",
    "sg:address":"Calle de Lope De Vega, 5",
    "sg:city":"Velez-malaga",
    "sg:orig_category":"Farmacias",
    "sg:phone":"+34 952 50 09 52",
    "sg:postcode":"29700",
    "sg:province":"M\u00e1laga",
    "wof:name":"Zarza Moya Alfonso",
    "wof:placetype":"venue"
},
  "geometry": {"coordinates":[-4.1016626358,36.7803955078],"type":"Point"}
}