{
  "type": "Feature",
  "properties": {
    "addr:full":"Pl. Ortiz, 1 Estepona M\u00e1laga 29680",
    "addr:housenumber":"1",
    "addr:postcode":"29680",
    "addr:street":"Pl. Ortiz",
    "iso:country":"ES",
    "sg:address":"Pl. Ortiz, 1",
    "sg:city":"Estepona",
    "sg:orig_category":"Electrodom\u00c9sticos (al Por Menor)",
    "sg:phone":"+34 952 80 36 93",
    "sg:postcode":"29680",
    "sg:province":"M\u00e1laga",
    "wof:name":"Gavira Muoz Antonio",
    "wof:placetype":"venue"
},
  "geometry": {"coordinates":[-5.1408791542,36.4268417358],"type":"Point"}
}