{
  "type": "Feature",
  "properties": {
    "iso:country":"ES",
    "sg:address":"Avda Emilia Pardo Bazan, S/n",
    "sg:city":"Sanxenxo",
    "sg:orig_category":"M\u00c9dicos: Medicina General Orientada A La Acupuntura",
    "sg:phone":"+34 986 69 11 35",
    "sg:postcode":"36960",
    "sg:province":"Pontevedra",
    "wof:name":"Baquero Guiance Roman",
    "wof:placetype":"venue"
},
  "geometry": {"coordinates":[-8.8017339706,42.4024200439],"type":"Point"}
}