{
  "type": "Feature",
  "properties": {
    "iso:country":"ES",
    "sg:address":"Montgo, 3",
    "sg:city":"Escala",
    "sg:orig_category":"Platos Preparados Refrigerados (fabricaci\u00d3n, Al Por Mayor)",
    "sg:phone":"+34 972 77 00 38",
    "sg:postcode":"17130",
    "sg:province":"Girona",
    "wof:name":"Pla Miro Maria Rosa",
    "wof:placetype":"venue"
},
  "geometry": {"coordinates":[3.1374380589,42.114906311],"type":"Point"}
}