{
  "type": "Feature",
  "properties": {
    "addr:full":"Calle de Calvari, 100 Rafelbunyol Valencia 46138",
    "addr:housenumber":"100",
    "addr:postcode":"46138",
    "addr:street":"Calle De Calvari",
    "iso:country":"ES",
    "sg:address":"Calle de Calvari, 100",
    "sg:city":"Rafelbunyol",
    "sg:orig_category":"Molduras, Junquillos, Listones Y Molduras Perforadas",
    "sg:phone":"+34 961 41 20 09",
    "sg:postcode":"46138",
    "sg:province":"Valencia",
    "wof:name":"Perez Lopez Pascual",
    "wof:placetype":"venue"
},
  "geometry": {"coordinates":[-0.3017460108,39.590927124],"type":"Point"}
}