{
  "type": "Feature",
  "properties": {
    "addr:full":"Calle de Artemisa, 4 Vecindario Las Palmas 35110",
    "addr:housenumber":"4",
    "addr:postcode":"35110",
    "addr:street":"Calle De Artemisa;Palmas",
    "iso:country":"ES",
    "sg:address":"Calle de Artemisa, 4",
    "sg:city":"Vecindario",
    "sg:orig_category":"Agentes Generales De Seguros",
    "sg:phone":"+34 928 75 20 08",
    "sg:postcode":"35110",
    "sg:province":"Las Palmas",
    "wof:name":"Suarez Caceres Antonio Tomas",
    "wof:placetype":"venue"
},
  "geometry": {"coordinates":[-15.4425945282,27.8477172852],"type":"Point"}
}