{
  "type": "Feature",
  "properties": {
    "addr:full":"Cmno Pueyos, S/n Alca\u00f1iz Teruel 44600",
    "addr:housenumber":"s",
    "addr:postcode":"44600",
    "addr:street":"Cmno Pueyos;/ N",
    "iso:country":"ES",
    "sg:address":"Cmno Pueyos, S/n",
    "sg:city":"Alca\u00f1iz",
    "sg:orig_category":"Iglesia Cat\u00d3lica",
    "sg:phone":"+34 978 83 00 61",
    "sg:postcode":"44600",
    "sg:province":"Teruel",
    "wof:name":"Santuario De Nuestra Se\u00f1ora De Los Pueyos",
    "wof:placetype":"venue"
},
  "geometry": {"coordinates":[-0.1314709932,41.0490722656],"type":"Point"}
}