{
  "type": "Feature",
  "properties": {
    "iso:country":"ES",
    "sg:address":"Pg Mallorca, 10",
    "sg:city":"Palma",
    "sg:orig_category":"Abogados",
    "sg:phone":"+34 971 71 48 05",
    "sg:postcode":"07012",
    "sg:province":"Islas Baleares",
    "wof:name":"Alemany Pou Jose Luis",
    "wof:placetype":"venue"
},
  "geometry": {"coordinates":[2.64220047,39.5721054077],"type":"Point"}
}