{
  "type": "Feature",
  "properties": {
    "addr:full":"Calle de Fernando El Catolico, 7 Huescar Granada 18830",
    "addr:housenumber":"7",
    "addr:postcode":"18830",
    "addr:street":"Calle De Fernando El Catolico",
    "iso:country":"ES",
    "sg:address":"Calle de Fernando El Catolico, 7",
    "sg:city":"Huescar",
    "sg:orig_category":"Chapister\u00cda",
    "sg:phone":"+34 958 74 16 66",
    "sg:postcode":"18830",
    "sg:province":"Granada",
    "wof:name":"Mu\u00f1oz Adan Miguel Angel",
    "wof:placetype":"venue"
},
  "geometry": {"coordinates":[-2.5414800644,37.8147583008],"type":"Point"}
}