{
  "type": "Feature",
  "properties": {
    "iso:country":"ES",
    "sg:address":"Calle de Manuel Laguna, 30",
    "sg:city":"Madrid",
    "sg:orig_category":"Guarder\u00cdas",
    "sg:phone":"+34 917 86 27 74",
    "sg:postcode":"28018",
    "sg:province":"Madrid",
    "wof:name":"Arjonilla Truque Maria Victoria",
    "wof:placetype":"venue"
},
  "geometry": {"coordinates":[-3.6652543545,40.381778717],"type":"Point"}
}