{
  "type": "Feature",
  "properties": {
    "addr:full":"Ctra Ventosa (la), 8 Benavente Zamora 49600",
    "addr:housenumber":"8",
    "addr:postcode":"49600",
    "addr:street":"Ctra Ventosa La",
    "iso:country":"ES",
    "sg:address":"Ctra Ventosa (la), 8",
    "sg:city":"Benavente",
    "sg:orig_category":"Suministros Y Materiales Industriales",
    "sg:phone":"+34 980 63 12 86",
    "sg:postcode":"49600",
    "sg:province":"Zamora",
    "wof:name":"Martin Mateos Francisco",
    "wof:placetype":"venue"
},
  "geometry": {"coordinates":[-5.6803250313,41.9932060242],"type":"Point"}
}