{
  "type": "Feature",
  "properties": {
    "addr:full":"Calle de Ganivet, 49 Armilla Granada 18100",
    "addr:housenumber":"49",
    "addr:postcode":"18100",
    "addr:street":"Calle De Ganivet",
    "iso:country":"ES",
    "sg:address":"Calle de Ganivet, 49",
    "sg:city":"Armilla",
    "sg:orig_category":"Peluquer\u00cdas, Peluquer\u00cda Mixta",
    "sg:phone":"+34 958 55 16 74",
    "sg:postcode":"18100",
    "sg:province":"Granada",
    "wof:name":"Lopez Murillo Remedios",
    "wof:placetype":"venue"
},
  "geometry": {"coordinates":[-3.6303329468,37.1449165344],"type":"Point"}
}