{
  "type": "Feature",
  "properties": {
    "iso:country":"ES",
    "sg:address":"San Bartolome P I Casablanca, 3",
    "sg:city":"Laguardia-biasteri",
    "sg:orig_category":"Fabricaci\u00d3n De Ventanas",
    "sg:phone":"+34 945 62 52 31",
    "sg:postcode":"01300",
    "sg:province":"\u00c1lava",
    "wof:name":"Antonio Pinto Almeida S.l.",
    "wof:placetype":"venue"
},
  "geometry": {"coordinates":[-2.5842370987,42.5542793274],"type":"Point"}
}