{
  "type": "Feature",
  "properties": {
    "iso:country":"ES",
    "sg:address":"Rbla Rambla, 103",
    "sg:city":"Sabadell",
    "sg:orig_category":"Asesor\u00cda Fiscal Y Jur\u00cddica",
    "sg:phone":"+34 937 27 12 03",
    "sg:postcode":"08202",
    "sg:province":"Barcelona",
    "wof:name":"Poles Assessors S.l.",
    "wof:placetype":"venue"
},
  "geometry": {"coordinates":[2.1107270718,41.5435638428],"type":"Point"}
}