{
  "type": "Feature",
  "properties": {
    "addr:full":"Calle de Habana (de La), 35 Fuenlabrada Madrid 28945",
    "addr:housenumber":"35",
    "addr:postcode":"28945",
    "addr:street":"Calle De Habana De La",
    "iso:country":"ES",
    "sg:address":"Calle de Habana (de La), 35",
    "sg:city":"Fuenlabrada",
    "sg:orig_category":"Congelados: Productos Alimentarios (al Por Menor)",
    "sg:phone":"+34 916 97 83 02",
    "sg:postcode":"28945",
    "sg:province":"Madrid",
    "wof:name":"Fernandez Martinez Belarmino",
    "wof:placetype":"venue"
},
  "geometry": {"coordinates":[-3.7846090794,40.2929725647],"type":"Point"}
}