{
  "type": "Feature",
  "properties": {
    "iso:country":"ES",
    "sg:address":"Calle de Cruz (la), 58",
    "sg:city":"Nerja",
    "sg:orig_category":"Laboratorios Y Trabajos De Fotograf\u00cda, V\u00cddeo Y Cine",
    "sg:phone":"+34 952 52 18 73",
    "sg:postcode":"29780",
    "sg:province":"M\u00e1laga",
    "wof:name":"Arrabal Gonzalez Rafael",
    "wof:placetype":"venue"
},
  "geometry": {"coordinates":[-3.8785297871,36.7479133606],"type":"Point"}
}