{
  "type": "Feature",
  "properties": {
    "iso:country":"ES",
    "sg:address":"La Redonda, S/n",
    "sg:city":"Guardamar Segura",
    "sg:orig_category":"Reposter\u00cdas",
    "sg:phone":"+34 965 72 89 47",
    "sg:postcode":"03140",
    "sg:province":"Alicante",
    "wof:name":"Vidarcia S.l.",
    "wof:placetype":"venue"
},
  "geometry": {"coordinates":[-0.6574469805,38.0846862793],"type":"Point"}
}