{
  "type": "Feature",
  "properties": {
    "addr:full":"Avda Constitucion De La, 111 Sotrondio Asturias 33950",
    "addr:housenumber":"111",
    "addr:postcode":"33950",
    "addr:street":"Avda Constitucion De La",
    "iso:country":"ES",
    "sg:address":"Avda Constitucion De La, 111",
    "sg:city":"Sotrondio",
    "sg:orig_category":"Ambulancias",
    "sg:phone":"+34 985 65 65 65",
    "sg:postcode":"33950",
    "sg:province":"Asturias",
    "wof:name":"Ambulancias Del Nalon S. L.",
    "wof:placetype":"venue"
},
  "geometry": {"coordinates":[-5.6095614433,43.2731437683],"type":"Point"}
}