{
  "type": "Feature",
  "properties": {
    "iso:country":"ES",
    "sg:address":"Calle de Devesa, 1",
    "sg:city":"Alacant",
    "sg:orig_category":"Servicios Gsm",
    "sg:phone":"+34 965 24 25 25",
    "sg:postcode":"03010",
    "sg:province":"Alicante",
    "wof:name":"Sociphone S.l.",
    "wof:placetype":"venue"
},
  "geometry": {"coordinates":[-0.4839073122,38.3593978882],"type":"Point"}
}