{
  "type": "Feature",
  "properties": {
    "iso:country":"ES",
    "sg:address":"Carrer de Lleida, 61",
    "sg:city":"Prat Llobregat",
    "sg:orig_category":"Alquiler De V\u00cddeo",
    "sg:phone":"+34 933 70 72 09",
    "sg:postcode":"08820",
    "sg:province":"Barcelona",
    "wof:name":"Inmoseguros Maro S.c.p.",
    "wof:placetype":"venue"
},
  "geometry": {"coordinates":[2.096353054,41.322769165],"type":"Point"}
}