{
  "type": "Feature",
  "properties": {
    "iso:country":"ES",
    "sg:address":"Calle de Lanuza, 11",
    "sg:city":"Madrid",
    "sg:orig_category":"Librer\u00cdas",
    "sg:phone":"+34 917 25 90 72",
    "sg:postcode":"28028",
    "sg:province":"Madrid",
    "sg:website":"www.breogan.org",
    "wof:name":"Breogan S.l.",
    "wof:placetype":"venue"
},
  "geometry": {"coordinates":[-3.6652629375,40.4250259399],"type":"Point"}
}