{
  "type": "Feature",
  "properties": {
    "iso:country":"ES",
    "sg:address":"Avda Tome Taboada (de), 34",
    "sg:city":"Santa Catali\u00e7a De Armada",
    "sg:orig_category":"Art\u00cdculos Funerarios (al Por Menor)",
    "sg:phone":"+34 981 88 03 16",
    "sg:postcode":"15840",
    "sg:province":"La Coru\u00f1a",
    "wof:name":"Martinez Romar Jose",
    "wof:placetype":"venue"
},
  "geometry": {"coordinates":[-8.8163843155,43.0361595154],"type":"Point"}
}