{
  "type": "Feature",
  "properties": {
    "addr:full":"Calle de Iglesia, 1 Parla Madrid 28980",
    "addr:housenumber":"1",
    "addr:postcode":"28980",
    "addr:street":"Calle De Iglesia",
    "iso:country":"ES",
    "sg:address":"Calle de Iglesia, 1",
    "sg:city":"Parla",
    "sg:orig_category":"Iglesia Cat\u00d3lica",
    "sg:phone":"+34 916 99 03 14",
    "sg:postcode":"28980",
    "sg:province":"Madrid",
    "wof:name":"Parroquia Nuestra Se\u00f1ora De La Asuncion",
    "wof:placetype":"venue"
},
  "geometry": {"coordinates":[-3.7715480328,40.2380828857],"type":"Point"}
}