{
  "type": "Feature",
  "properties": {
    "addr:full":"Avda Camelias, 125 Vigo Pontevedra 36211",
    "addr:housenumber":"125",
    "addr:postcode":"36211",
    "addr:street":"Avda Camelias",
    "iso:country":"ES",
    "sg:address":"Avda Camelias, 125",
    "sg:city":"Vigo",
    "sg:orig_category":"Alquiler De Ropa Y Accesorios",
    "sg:phone":"+34 986 20 47 20",
    "sg:postcode":"36211",
    "sg:province":"Pontevedra",
    "wof:name":"Otero Rodriguez Emilio",
    "wof:placetype":"venue"
},
  "geometry": {"coordinates":[-8.7303361893,42.2231483459],"type":"Point"}
}