{
  "type": "Feature",
  "properties": {
    "iso:country":"ES",
    "sg:address":"Carrer de Guilleries, 28",
    "sg:city":"Sabadell",
    "sg:orig_category":"Librer\u00cdas",
    "sg:phone":"+34 937 16 02 23",
    "sg:postcode":"08207",
    "sg:province":"Barcelona",
    "wof:name":"Prieto Molina Carmen",
    "wof:placetype":"venue"
},
  "geometry": {"coordinates":[2.0936779976,41.566280365],"type":"Point"}
}