{
  "type": "Feature",
  "properties": {
    "iso:country":"ES",
    "sg:address":"Carr Camp De La Vila (del), 14",
    "sg:city":"Pont Suert",
    "sg:orig_category":"Supermercados Y Hipermercados",
    "sg:phone":"+34 973 69 00 42",
    "sg:postcode":"25520",
    "sg:province":"Lleida",
    "wof:name":"Germans Casimiro S.l.",
    "wof:placetype":"venue"
},
  "geometry": {"coordinates":[0.7413970232,42.4082183838],"type":"Point"}
}