{
  "type": "Feature",
  "properties": {
    "addr:full":"Avda Castrelos, 93 Vigo Pontevedra 36210",
    "addr:housenumber":"93",
    "addr:postcode":"36210",
    "addr:street":"Avda Castrelos",
    "iso:country":"ES",
    "sg:address":"Avda Castrelos, 93",
    "sg:city":"Vigo",
    "sg:orig_category":"Quincaller\u00cda (al Por Menor)",
    "sg:phone":"+34 986 23 15 94",
    "sg:postcode":"36210",
    "sg:province":"Pontevedra",
    "wof:name":"Orgeira Picon Manuel",
    "wof:placetype":"venue"
},
  "geometry": {"coordinates":[-8.7321929932,42.2150001526],"type":"Point"}
}