{
  "type": "Feature",
  "properties": {
    "addr:full":"Calle de Gongora, 45 Pe\u00e7arroya-pueblonuevo C\u00f3rdoba 14200",
    "addr:housenumber":"45",
    "addr:postcode":"14200",
    "addr:street":"Calle De Gongora;Co\u0301Rdoba",
    "iso:country":"ES",
    "sg:address":"Calle de Gongora, 45",
    "sg:city":"Pe\u00e7arroya-pueblonuevo",
    "sg:orig_category":"Reposter\u00cdas",
    "sg:phone":"+34 957 56 02 97",
    "sg:postcode":"14200",
    "sg:province":"C\u00f3rdoba",
    "wof:name":"Pulgarin Gonzalez Francisco Jose",
    "wof:placetype":"venue"
},
  "geometry": {"coordinates":[-5.2796378136,38.3109359741],"type":"Point"}
}