{
  "type": "Feature",
  "properties": {
    "iso:country":"ES",
    "sg:address":"Carrer de Pep Ventura, 36",
    "sg:city":"Molins Rei",
    "sg:orig_category":"Empresas De Pintura Y Revestimientos",
    "sg:phone":"+34 936 68 15 05",
    "sg:postcode":"08750",
    "sg:province":"Barcelona",
    "wof:name":"Sanchez Delgado Nemesio Julian",
    "wof:placetype":"venue"
},
  "geometry": {"coordinates":[2.0164849758,41.414604187],"type":"Point"}
}