{
  "type": "Feature",
  "properties": {
    "addr:full":"Calle de Victor De La Serna, 10 Madrid Madrid 28016",
    "addr:housenumber":"10",
    "addr:postcode":"madrid;28016",
    "addr:street":"Calle De Victor De La Serna",
    "iso:country":"ES",
    "sg:address":"Calle de Victor De La Serna, 10",
    "sg:city":"Madrid",
    "sg:orig_category":"Empresas De Portes Y Mensajer\u00cda",
    "sg:phone":"+34 915 19 54 70",
    "sg:postcode":"28016",
    "sg:province":"Madrid",
    "wof:name":"Ecogestion Express S.l.",
    "wof:placetype":"venue"
},
  "geometry": {"coordinates":[-3.6726861,40.4528427124],"type":"Point"}
}