{
  "type": "Feature",
  "properties": {
    "addr:full":"Avda Pio Xii, S/n Valencia Valencia 46015",
    "addr:housenumber":"s / n",
    "addr:postcode":"46015",
    "addr:street":"Avda Pio Xii",
    "iso:country":"ES",
    "sg:address":"Avda Pio Xii, S/n",
    "sg:city":"Valencia",
    "sg:orig_category":"Ropa Para Se\u00d1oras Y Caballeros (al Por Menor)",
    "sg:phone":"+34 963 40 05 50",
    "sg:postcode":"46015",
    "sg:province":"Valencia",
    "wof:name":"Manhathan Station C.b",
    "wof:placetype":"venue"
},
  "geometry": {"coordinates":[-0.3958959877,39.4850387573],"type":"Point"}
}