{
  "type": "Feature",
  "properties": {
    "addr:full":"Calle de San Agustin, 37 Albacete Albacete 02001",
    "addr:housenumber":"37",
    "addr:postcode":"02001",
    "addr:street":"Calle De San Agustin",
    "iso:country":"ES",
    "sg:address":"Calle de San Agustin, 37",
    "sg:city":"Albacete",
    "sg:orig_category":"Material Y Suministros Para Imprenta E Industrias Gr\u00c1ficas",
    "sg:phone":"+34 967 21 24 59",
    "sg:postcode":"02001",
    "sg:province":"Albacete",
    "wof:name":"Encarnacion Encarnacion Ignacio",
    "wof:placetype":"venue"
},
  "geometry": {"coordinates":[-1.8516700268,38.9933547974],"type":"Point"}
}