{
  "type": "Feature",
  "properties": {
    "iso:country":"ES",
    "sg:address":"C/ Oliver, S/n",
    "sg:city":"Alcoi",
    "sg:orig_category":"Distribuci\u00d3n De Petr\u00d3leo Y Derivados",
    "sg:phone":"+34 965 52 09 43",
    "sg:postcode":"03802",
    "sg:province":"Alicante",
    "wof:name":"Repsol Ypf S.a.",
    "wof:placetype":"venue"
},
  "geometry": {"coordinates":[-0.4823490083,38.6945381165],"type":"Point"}
}