{
  "type": "Feature",
  "properties": {
    "addr:full":"Joaquin Jarauta, 56 Iru\u00f1a Navarra 31001",
    "addr:housenumber":"56",
    "addr:postcode":"31001",
    "addr:street":"Joaquin Jarauta",
    "iso:country":"ES",
    "sg:address":"Joaquin Jarauta, 56",
    "sg:city":"Iru\u00f1a",
    "sg:orig_category":"Molduras, Junquillos, Listones Y Molduras Perforadas",
    "sg:phone":"+34 948 22 67 96",
    "sg:postcode":"31001",
    "sg:province":"Navarra",
    "wof:name":"Galech Ezquer Maria Angeles",
    "wof:placetype":"venue"
},
  "geometry": {"coordinates":[-1.647413969,42.8185844421],"type":"Point"}
}