{
  "type": "Feature",
  "properties": {
    "iso:country":"ES",
    "sg:address":"Carrer de Sol, 1",
    "sg:city":"Palma",
    "sg:orig_category":"Centros P\u00dablicos De Formaci\u00d3n Profesional Y T\u00c9cnica",
    "sg:phone":"+34 971 42 56 23",
    "sg:postcode":"07001",
    "sg:province":"Islas Baleares",
    "wof:name":"Decanato Provincial Colegio Nacional Registradores De La Propiedad Y Mercantiles De Les Illes Balear",
    "wof:placetype":"venue"
},
  "geometry": {"coordinates":[2.6517560482,39.5682525635],"type":"Point"}
}