{
  "type": "Feature",
  "properties": {
    "addr:full":"C/ Altimira, 48 Cerdanyola Valles Barcelona 08290",
    "addr:housenumber":"48",
    "addr:postcode":"08290",
    "addr:street":"C / Altimira;Valles Barcelona",
    "iso:country":"ES",
    "sg:address":"C/ Altimira, 48",
    "sg:city":"Cerdanyola Valles",
    "sg:orig_category":"Inform\u00c1tica Equipo Y Programas (al Por Mayor)",
    "sg:phone":"+34 935 92 25 35",
    "sg:postcode":"08290",
    "sg:province":"Barcelona",
    "wof:name":"Ancora Dual S.l",
    "wof:placetype":"venue"
},
  "geometry": {"coordinates":[2.1412913799,41.4904937744],"type":"Point"}
}