{
  "type": "Feature",
  "properties": {
    "addr:full":"Rua Peregrina (da), 23 Pontevedra Pontevedra 36001",
    "addr:housenumber":"23",
    "addr:postcode":"36001",
    "addr:street":"Rua Peregrina Da",
    "iso:country":"ES",
    "sg:address":"Rua Peregrina (da), 23",
    "sg:city":"Pontevedra",
    "sg:orig_category":"Ropa Para Se\u00d1oras (al Por Menor)",
    "sg:phone":"+34 986 86 63 61",
    "sg:postcode":"36001",
    "sg:province":"Pontevedra",
    "wof:name":"Patri Godoy S.l.",
    "wof:placetype":"venue"
},
  "geometry": {"coordinates":[-8.6433086395,42.4297981262],"type":"Point"}
}