{
  "type": "Feature",
  "properties": {
    "addr:full":"Calle de General Margallo, 28 Caceres C\u00e1ceres 10003",
    "addr:housenumber":"28",
    "addr:postcode":"10003",
    "addr:street":"Calle De General Margallo;Ca\u0301Ceres",
    "iso:country":"ES",
    "sg:address":"Calle de General Margallo, 28",
    "sg:city":"Caceres",
    "sg:orig_category":"Ense\u00d1anza Variada",
    "sg:phone":"+34 927 62 73 30",
    "sg:postcode":"10003",
    "sg:province":"C\u00e1ceres",
    "wof:name":"Educacion Tecnologia De Extremadura S.l.",
    "wof:placetype":"venue"
},
  "geometry": {"coordinates":[-6.3722610474,39.4772491455],"type":"Point"}
}