{
  "type": "Feature",
  "properties": {
    "addr:full":"Calle de Tomas Prieto, 10 Roda Albacete 02630",
    "addr:housenumber":"10",
    "addr:postcode":"02630",
    "addr:street":"Calle De Tomas Prieto",
    "iso:country":"ES",
    "sg:address":"Calle de Tomas Prieto, 10",
    "sg:city":"Roda",
    "sg:orig_category":"Transporte En General",
    "sg:phone":"+34 967 44 20 64",
    "sg:postcode":"02630",
    "sg:province":"Albacete",
    "wof:name":"Vifertextil S.l.l.",
    "wof:placetype":"venue"
},
  "geometry": {"coordinates":[-2.1559140682,39.2024765015],"type":"Point"}
}