{
  "type": "Feature",
  "properties": {
    "iso:country":"ES",
    "sg:address":"Calle de Gamonal, 19",
    "sg:city":"Madrid",
    "sg:orig_category":"Trabajos De Fotocomposici\u00d3n",
    "sg:phone":"+34 913 80 10 18",
    "sg:postcode":"28031",
    "sg:province":"Madrid",
    "wof:name":"Versal Composicion S.l.",
    "wof:placetype":"venue"
},
  "geometry": {"coordinates":[-3.6441049576,40.3729782104],"type":"Point"}
}