{
  "type": "Feature",
  "properties": {
    "addr:full":"Carretera De Huescar, S/n Fatima Granada 18816",
    "addr:housenumber":"s / n",
    "addr:postcode":"18816",
    "addr:street":"Carretera De Huescar",
    "iso:country":"ES",
    "sg:address":"Carretera De Huescar, S/n",
    "sg:city":"Fatima",
    "sg:orig_category":"Plomeros",
    "sg:phone":"+34 958 34 44 35",
    "sg:postcode":"18816",
    "sg:province":"Granada",
    "wof:name":"Rodriguez Olivares Miguel",
    "wof:placetype":"venue"
},
  "geometry": {"coordinates":[-2.7812540531,37.7978591919],"type":"Point"}
}