{
  "type": "Feature",
  "properties": {
    "iso:country":"ES",
    "sg:address":"Campolabrado(narahio), S/n",
    "sg:city":"Campolabrado",
    "sg:orig_category":"Fisioterapia",
    "sg:phone":"+34 981 49 03 40",
    "sg:postcode":"15560",
    "sg:province":"A Coru\u00f1a",
    "wof:name":"Ulloa Fraguela Esperanza",
    "wof:placetype":"venue"
},
  "geometry": {"coordinates":[-8.0724773407,43.5319709778],"type":"Point"}
}