{
  "type": "Feature",
  "properties": {
    "addr:full":"Calle de Cronista Carreres, 9 Valencia Valencia 46003",
    "addr:housenumber":"9",
    "addr:postcode":"46003",
    "addr:street":"Calle De Cronista Carreres",
    "iso:country":"ES",
    "sg:address":"Calle de Cronista Carreres, 9",
    "sg:city":"Valencia",
    "sg:classifiers":[
        {
            "category":"Manufacturing",
            "subcategory":"Building Materials",
            "type":"Manufacturing & Wholesale Goods"
        }
    ],
    "sg:phone":"+34 963 51 14 77",
    "sg:postcode":"46003",
    "sg:province":"Valencia",
    "sg:tags":[
        "cemento",
        "y",
        "de",
        "fabricaci\u00d3n",
        "cal"
    ],
    "wof:name":"Terratest Tecnicas Especiales S.a.",
    "wof:placetype":"venue"
},
  "geometry": {"coordinates":[-0.3676449955,39.4730415344],"type":"Point"}
}