{
  "type": "Feature",
  "properties": {
    "addr:full":"Avda Perez Galdos, 63 Logro\u00f1o La Rioja 26005",
    "addr:housenumber":"63",
    "addr:postcode":"26005",
    "addr:street":"Avda Perez Galdos;Rioja",
    "iso:country":"ES",
    "sg:address":"Avda Perez Galdos, 63",
    "sg:city":"Logro\u00f1o",
    "sg:orig_category":"Contenedores (mercanc\u00cdas)",
    "sg:phone":"+34 941 20 56 64",
    "sg:postcode":"26005",
    "sg:province":"La Rioja",
    "wof:name":"Martin Rodriguez Jose Manuel",
    "wof:placetype":"venue"
},
  "geometry": {"coordinates":[-2.4550158978,42.4627418518],"type":"Point"}
}