{
  "type": "Feature",
  "properties": {
    "addr:full":"Calle de Dolores Ibarruri 'pasionaria', 8 Sevilla Sevilla 41013",
    "addr:housenumber":"8",
    "addr:postcode":"41013",
    "addr:street":"Calle De Dolores Ibarruri ' Pasionaria '",
    "iso:country":"ES",
    "sg:address":"Calle de Dolores Ibarruri 'pasionaria', 8",
    "sg:city":"Sevilla",
    "sg:orig_category":"Sonorizaci\u00d3n, Iluminaci\u00d3n Para Cine, Teatro Y Discotecas (al Por Mayor, Al Por Menor)",
    "sg:phone":"+34 954 24 10 88",
    "sg:postcode":"41013",
    "sg:province":"Sevilla",
    "wof:name":"Fernandez Lopez Maria Jose",
    "wof:placetype":"venue"
},
  "geometry": {"coordinates":[-5.9628596306,37.3628425598],"type":"Point"}
}