{
  "type": "Feature",
  "properties": {
    "addr:full":"Calle de Maria Guerrero, S/n Granada Granada 18004",
    "addr:housenumber":"/ n",
    "addr:postcode":"18004",
    "addr:street":"Calle De Maria Guerrero S",
    "iso:country":"ES",
    "sg:address":"Calle de Maria Guerrero, S/n",
    "sg:city":"Granada",
    "sg:orig_category":"Comercio De Piezas De Recambio Y De Accesorios De Veh\u00cdculos, Veh\u00cdculos Industriales",
    "sg:phone":"+34 958 20 00 06",
    "sg:postcode":"18004",
    "sg:province":"Granada",
    "wof:name":"Salinas Marcos Adolfo",
    "wof:placetype":"venue"
},
  "geometry": {"coordinates":[-3.6164588928,37.1813812256],"type":"Point"}
}