{
  "type": "Feature",
  "properties": {
    "addr:full":"Carr Tints, 18 Figueres Girona 17600",
    "addr:housenumber":"18",
    "addr:postcode":"17600",
    "addr:street":"Carr Tints",
    "iso:country":"ES",
    "sg:address":"Carr Tints, 18",
    "sg:city":"Figueres",
    "sg:orig_category":"Sexshops",
    "sg:phone":"+34 972 50 59 77",
    "sg:postcode":"17600",
    "sg:province":"Girona",
    "wof:name":"Kivas S.c.",
    "wof:placetype":"venue"
},
  "geometry": {"coordinates":[2.9612379074,42.2682228088],"type":"Point"}
}