{
  "type": "Feature",
  "properties": {
    "addr:full":"Carrer de Aribau, 308 Barcelona Barcelona 08006",
    "addr:housenumber":"308",
    "addr:postcode":"08006",
    "addr:street":"Carrer De Aribau",
    "iso:country":"ES",
    "sg:address":"Carrer de Aribau, 308",
    "sg:city":"Barcelona",
    "sg:orig_category":"Metalurgia",
    "sg:phone":"+34 934 14 15 18",
    "sg:postcode":"08006",
    "sg:province":"Barcelona",
    "sg:website":"www.armstrong.es",
    "wof:name":"Armstrong Architectural Products S.l.",
    "wof:placetype":"venue"
},
  "geometry": {"coordinates":[2.1460642815,41.3989219666],"type":"Point"}
}