{
  "type": "Feature",
  "properties": {
    "iso:country":"ES",
    "sg:address":"Carrer de Casanova, 270",
    "sg:city":"Barcelona",
    "sg:orig_category":"Papeler\u00cdas, Librer\u00cdas",
    "sg:phone":"+34 932 00 23 53",
    "sg:postcode":"08021",
    "sg:province":"Barcelona",
    "wof:name":"Gonzalez Domenech Darek",
    "wof:placetype":"venue"
},
  "geometry": {"coordinates":[2.1470870972,41.3944015503],"type":"Point"}
}