{
  "type": "Feature",
  "properties": {
    "iso:country":"ES",
    "sg:address":"Av Montejurra, 8",
    "sg:city":"Sant Feliu Llobregat",
    "sg:orig_category":"Mec\u00c1nico Del Autom\u00d3vil",
    "sg:phone":"+34 936 66 74 01",
    "sg:postcode":"08980",
    "sg:province":"Barcelona",
    "wof:name":"Delgado Fatsini Manuel",
    "wof:placetype":"venue"
},
  "geometry": {"coordinates":[2.0523600578,41.3794631958],"type":"Point"}
}