{
  "type": "Feature",
  "properties": {
    "iso:country":"ES",
    "sg:address":"Calle de Cartagena, 124",
    "sg:city":"Madrid",
    "sg:orig_category":"Loter\u00cda Y T\u00d3mbola",
    "sg:phone":"+34 915 19 54 56",
    "sg:postcode":"28002",
    "sg:province":"Madrid",
    "wof:name":"Lamata Cotanda Pedro",
    "wof:placetype":"venue"
},
  "geometry": {"coordinates":[-3.6747200489,40.4410362244],"type":"Point"}
}