{
  "type": "Feature",
  "properties": {
    "iso:country":"ES",
    "sg:address":"Carrer de Arnes (d'), 4",
    "sg:city":"Tortosa",
    "sg:orig_category":"Mec\u00c1nico Del Autom\u00d3vil",
    "sg:phone":"+34 977 50 41 79",
    "sg:postcode":"43500",
    "sg:province":"Tarragona",
    "wof:name":"Roig Lleixa Juan Jose",
    "wof:placetype":"venue"
},
  "geometry": {"coordinates":[0.517655015,40.8165397644],"type":"Point"}
}