{
  "type": "Feature",
  "properties": {
    "addr:full":"Carrer de Septimania, 31 Barcelona Barcelona 08006",
    "addr:housenumber":"31",
    "addr:postcode":"08006",
    "addr:street":"Carrer De Septimania",
    "iso:country":"ES",
    "sg:address":"Carrer de Septimania, 31",
    "sg:city":"Barcelona",
    "sg:orig_category":"Organismos De Reclutamiento",
    "sg:phone":"+34 934 15 26 76",
    "sg:postcode":"08006",
    "sg:province":"Barcelona",
    "wof:name":"Mesalles Canals Lluis",
    "wof:placetype":"venue"
},
  "geometry": {"coordinates":[2.1477620602,41.405380249],"type":"Point"}
}