{
  "type": "Feature",
  "properties": {
    "iso:country":"ES",
    "sg:address":"Carrer de Sant Dalmir, 21",
    "sg:city":"Barcelona",
    "sg:orig_category":"Suministros Para Hoteles",
    "sg:phone":"+34 934 08 34 25",
    "sg:postcode":"08035",
    "sg:province":"Barcelona",
    "sg:website":"www.arrakis.es/h-d-port",
    "wof:name":"La Hojalateria De Portillo Sl",
    "wof:placetype":"venue"
},
  "geometry": {"coordinates":[2.1501939297,41.4233818054],"type":"Point"}
}