{
  "type": "Feature",
  "properties": {
    "iso:country":"ES",
    "sg:address":"C/ Prat De La Riba, 1",
    "sg:city":"Cerdanyola Valles",
    "sg:orig_category":"Peluqueros: De Se\u00d1oras",
    "sg:phone":"+34 936 92 00 66",
    "sg:postcode":"08290",
    "sg:province":"Barcelona",
    "wof:name":"Olives Martinez Francesc",
    "wof:placetype":"venue"
},
  "geometry": {"coordinates":[2.1484899521,41.4942016602],"type":"Point"}
}