{
  "type": "Feature",
  "properties": {
    "addr:full":"Calle de Maestro Lasalle, 21 Madrid Madrid 28016",
    "addr:housenumber":"21",
    "addr:postcode":"madrid;28016",
    "addr:street":"Calle De Maestro Lasalle",
    "iso:country":"ES",
    "sg:address":"Calle de Maestro Lasalle, 21",
    "sg:city":"Madrid",
    "sg:orig_category":"Cine (producci\u00d3n, Realizaci\u00d3n)",
    "sg:phone":"+34 913 45 71 39",
    "sg:postcode":"28016",
    "sg:province":"Madrid",
    "sg:website":"www.eliasquerejeta.com",
    "wof:name":"Elias Querejeta Pc S.l.",
    "wof:placetype":"venue"
},
  "geometry": {"coordinates":[-3.6726059914,40.4637794495],"type":"Point"}
}