{
  "type": "Feature",
  "properties": {
    "addr:full":"Calle de Maria De Echarri, 2 Zaragoza Zaragoza 50015",
    "addr:housenumber":"2",
    "addr:postcode":"50015",
    "addr:street":"Calle De Maria De Echarri",
    "iso:country":"ES",
    "sg:address":"Calle de Maria De Echarri, 2",
    "sg:city":"Zaragoza",
    "sg:orig_category":"Fotograf\u00cda Y Cine: Aparatos, Pel\u00cdculas Y Accesorios (fabricaci\u00d3n, Al Por Mayor)",
    "sg:phone":"+34 976 10 62 26",
    "sg:postcode":"50015",
    "sg:province":"Zaragoza",
    "wof:name":"Arpiserra S.a.",
    "wof:placetype":"venue"
},
  "geometry": {"coordinates":[-0.8920273781,41.6686210632],"type":"Point"}
}