{
  "type": "Feature",
  "properties": {
    "iso:country":"ES",
    "sg:address":"Rua Da Casti\u00f1eira, 39",
    "sg:city":"Ponteareas",
    "sg:orig_category":"Asociaciones Y Clubs Deportivos",
    "sg:phone":"+34 986 64 21 29",
    "sg:postcode":"36860",
    "sg:province":"Pontevedra",
    "wof:name":"Gimnasio David Estevez S.l.",
    "wof:placetype":"venue"
},
  "geometry": {"coordinates":[-8.5072956085,42.1732215881],"type":"Point"}
}