{
  "type": "Feature",
  "properties": {
    "iso:country":"ES",
    "sg:address":"Cami Font Pudenta, S/n",
    "sg:city":"Jonquera",
    "sg:orig_category":"Molduras, Junquillos, Listones Y Molduras Perforadas",
    "sg:phone":"+34 972 55 53 73",
    "sg:postcode":"17700",
    "sg:province":"Girona",
    "wof:name":"Castillo Martin Balbina",
    "wof:placetype":"venue"
},
  "geometry": {"coordinates":[2.8718750477,42.4159698486],"type":"Point"}
}