{
  "type": "Feature",
  "properties": {
    "iso:country":"ES",
    "sg:address":"Calle de Colon, 42",
    "sg:city":"Cuenca",
    "sg:orig_category":"Supermercados Y Hipermercados",
    "sg:phone":"+34 969 24 11 85",
    "sg:postcode":"16002",
    "sg:province":"Cuenca",
    "wof:name":"Alimentaria Conquense S. A.",
    "wof:placetype":"venue"
},
  "geometry": {"coordinates":[-2.1373887062,40.0727958679],"type":"Point"}
}