{
  "type": "Feature",
  "properties": {
    "addr:full":"Cra. Lleida, 20 Castellciutat Lleida 25710",
    "addr:housenumber":"20",
    "addr:postcode":"25710",
    "addr:street":"Lleida",
    "iso:country":"ES",
    "sg:address":"Cra. Lleida, 20",
    "sg:city":"Castellciutat",
    "sg:orig_category":"Construcciones Met\u00c1licas",
    "sg:phone":"+34 973 36 03 06",
    "sg:postcode":"25710",
    "sg:province":"Lleida",
    "wof:name":"Cortes Linde S.l.",
    "wof:placetype":"venue"
},
  "geometry": {"coordinates":[1.4350399971,42.3509483337],"type":"Point"}
}