{
  "type": "Feature",
  "properties": {
    "iso:country":"ES",
    "sg:address":"Calle de San Juan Bautista, 5",
    "sg:city":"Arroyo De La Miel-benalmadena Costa",
    "sg:classifiers":[
        {
            "category":"Autos & Motor Vehicles",
            "subcategory":"Automobile Sales",
            "type":"Retail Goods"
        }
    ],
    "sg:phone":"+34 952 56 16 00",
    "sg:postcode":"29631",
    "sg:province":"M\u00e1laga",
    "wof:name":"Autoescuelas Torcal S.l.",
    "wof:placetype":"venue"
},
  "geometry": {"coordinates":[-4.52206707,36.5950202942],"type":"Point"}
}