{
  "type": "Feature",
  "properties": {
    "addr:full":"Pase General Davila, 34 Santander Cantabria 39005",
    "addr:housenumber":"34",
    "addr:postcode":"39005",
    "addr:street":"Davila",
    "iso:country":"ES",
    "sg:address":"Pase General Davila, 34",
    "sg:city":"Santander",
    "sg:orig_category":"Comidas Por Encargo, Organizaci\u00d3n De Recepciones",
    "sg:phone":"+34 942 27 67 99",
    "sg:postcode":"39005",
    "sg:province":"Cantabria",
    "wof:name":"Pilar Gonzalez S.c.",
    "wof:placetype":"venue"
},
  "geometry": {"coordinates":[-3.7924919128,43.4686431885],"type":"Point"}
}