{
  "type": "Feature",
  "properties": {
    "iso:country":"ES",
    "sg:address":"Calle de Lentiscos (los), S/n",
    "sg:city":"Monte Lentiscal",
    "sg:orig_category":"Doctores En Medicina",
    "sg:phone":"+34 928 35 40 09",
    "sg:postcode":"35310",
    "sg:province":"Las Palmas",
    "wof:name":"Alonso Jorge Alfonso",
    "wof:placetype":"venue"
},
  "geometry": {"coordinates":[-15.4752960205,28.0484142303],"type":"Point"}
}