{
  "type": "Feature",
  "properties": {
    "iso:country":"ES",
    "sg:address":"Dsmdo Finca Ventorrillo, 19",
    "sg:city":"El Viso Alcor",
    "sg:orig_category":"Tapicer\u00cdas",
    "sg:phone":"+34 955 74 06 35",
    "sg:postcode":"41520",
    "sg:province":"Sevilla",
    "wof:name":"Sevi-confort Dise\u00f1o S.l.",
    "wof:placetype":"venue"
},
  "geometry": {"coordinates":[-5.7224740982,37.3872108459],"type":"Point"}
}