{
  "type": "Feature",
  "properties": {
    "iso:country":"ES",
    "sg:address":"Calle de Oporto, 1",
    "sg:city":"Cadiz",
    "sg:orig_category":"Abogados",
    "sg:phone":"+34 956 20 07 49",
    "sg:postcode":"11008",
    "sg:province":"C\u00e1diz",
    "wof:name":"Velasco Poyatos Blas",
    "wof:placetype":"venue"
},
  "geometry": {"coordinates":[-6.2784237862,36.515209198],"type":"Point"}
}