{
  "type": "Feature",
  "properties": {
    "iso:country":"ES",
    "sg:address":"Puente Pia, S/n",
    "sg:city":"Lorca",
    "sg:orig_category":"Sanatorios M\u00c9dico",
    "sg:phone":"+34 968 47 01 46",
    "sg:postcode":"30800",
    "sg:province":"Murcia",
    "wof:name":"Ayuntamiento De Lorca",
    "wof:placetype":"venue"
},
  "geometry": {"coordinates":[-1.7928402424,37.6676559448],"type":"Point"}
}