{
  "type": "Feature",
  "properties": {
    "addr:full":"Calle de Federico Garcia Lorca, 1 Burgos Burgos 09007",
    "addr:housenumber":"1",
    "addr:postcode":"09007",
    "addr:street":"Calle De Federico Garcia Lorca",
    "iso:country":"ES",
    "sg:address":"Calle de Federico Garcia Lorca, 1",
    "sg:city":"Burgos",
    "sg:orig_category":"Ropa Para Beb\u00c9s Y Ni\u00d1os (confecci\u00d3n, Al Por Mayor)",
    "sg:phone":"+34 947 47 06 93",
    "sg:postcode":"09007",
    "sg:province":"Burgos",
    "wof:name":"Gonzalez Diez Emiliana",
    "wof:placetype":"venue"
},
  "geometry": {"coordinates":[-3.6666903496,42.3498268127],"type":"Point"}
}