{
  "type": "Feature",
  "properties": {
    "iso:country":"ES",
    "sg:address":"Calle de Henao, 31",
    "sg:city":"Bilbao",
    "sg:orig_category":"Zapatos (al Por Menor)",
    "sg:phone":"+34 944 24 31 21",
    "sg:postcode":"48009",
    "sg:province":"Vizcaya",
    "wof:name":"Gonzalez Gonzalez Julio Cesar",
    "wof:placetype":"venue"
},
  "geometry": {"coordinates":[-2.9352529049,43.265209198],"type":"Point"}
}