{
  "type": "Feature",
  "properties": {
    "addr:full":"Carr Alcalde Costa, 49 Lleida Lleida 25002",
    "addr:housenumber":"49",
    "addr:postcode":"25002",
    "addr:street":"Carr Alcalde Costa",
    "iso:country":"ES",
    "sg:address":"Carr Alcalde Costa, 49",
    "sg:city":"Lleida",
    "sg:orig_category":"Decorados Y Accesorios De Teatro Y Cine",
    "sg:phone":"+34 973 27 02 13",
    "sg:postcode":"25002",
    "sg:province":"Lleida",
    "wof:name":"A.c.m.e.activa S.c.p.",
    "wof:placetype":"venue"
},
  "geometry": {"coordinates":[0.6182388067,41.6098480225],"type":"Point"}
}