{
  "type": "Feature",
  "properties": {
    "addr:full":"Calle de Molino, S/n Arcos De La Polvorosa Zamora 49699",
    "addr:housenumber":"s",
    "addr:postcode":"49699",
    "addr:street":"Calle De Molino;/ N;Zamora",
    "iso:country":"ES",
    "sg:address":"Calle de Molino, S/n",
    "sg:city":"Arcos De La Polvorosa",
    "sg:orig_category":"Farmacias",
    "sg:phone":"+34 980 65 42 23",
    "sg:postcode":"49699",
    "sg:province":"Zamora",
    "wof:name":"Ferrero Carbajal Maria Angeles",
    "wof:placetype":"venue"
},
  "geometry": {"coordinates":[-5.6985387802,41.943271637],"type":"Point"}
}