{
  "type": "Feature",
  "properties": {
    "iso:country":"ES",
    "sg:address":"Calle de Juanar, 3",
    "sg:city":"Marbella",
    "sg:orig_category":"Panader\u00cdas, Panader\u00cdas",
    "sg:phone":"+34 952 82 05 48",
    "sg:postcode":"29600",
    "sg:province":"M\u00e1laga",
    "wof:name":"Pasteleria Custodio",
    "wof:placetype":"venue"
},
  "geometry": {"coordinates":[-4.8803458214,36.5180587769],"type":"Point"}
}