{
  "type": "Feature",
  "properties": {
    "iso:country":"ES",
    "sg:address":"Avda Baron De Carcer, 40",
    "sg:city":"Valencia",
    "sg:orig_category":"M\u00c9dicos: Estomatolog\u00cda",
    "sg:phone":"+34 963 94 26 97",
    "sg:postcode":"46001",
    "sg:province":"Valencia",
    "wof:name":"Clinica Barjau C B.",
    "wof:placetype":"venue"
},
  "geometry": {"coordinates":[-0.3798229992,39.4704246521],"type":"Point"}
}