{
  "type": "Feature",
  "properties": {
    "addr:full":"Ctra. Estacion, S/n Quintana Serena Badajoz 06450",
    "addr:postcode":"06450",
    "addr:street":"Ctra. Estacion S / N Quintana Serena",
    "iso:country":"ES",
    "sg:address":"Ctra. Estacion, S/n",
    "sg:city":"Quintana Serena",
    "sg:orig_category":"M\u00c1rmoles, Granitos Y Piedras Naturales",
    "sg:phone":"+34 924 77 73 54",
    "sg:postcode":"06450",
    "sg:province":"Badajoz",
    "wof:name":"Granitos Delgado S.l.",
    "wof:placetype":"venue"
},
  "geometry": {"coordinates":[-5.6712579727,38.743019104],"type":"Point"}
}