{
  "type": "Feature",
  "properties": {
    "iso:country":"ES",
    "sg:address":"Calle de Ca\u00d1ada (la), 17",
    "sg:city":"Alcorcon",
    "sg:orig_category":"Empresas De Carpinter\u00cda",
    "sg:phone":"+34 916 41 40 66",
    "sg:postcode":"28922",
    "sg:province":"Madrid",
    "wof:name":"Herrero Sanz Benjamin",
    "wof:placetype":"venue"
},
  "geometry": {"coordinates":[-3.829349041,40.3433151245],"type":"Point"}
}