{
  "type": "Feature",
  "properties": {
    "iso:country":"ES",
    "sg:address":"Calle de Cerrillo, 27",
    "sg:city":"Villalba Alcor",
    "sg:orig_category":"Muebles, Minoristas",
    "sg:phone":"+34 959 42 03 26",
    "sg:postcode":"21860",
    "sg:province":"Huelva",
    "wof:name":"Vayas Del Toro S.l.",
    "wof:placetype":"venue"
},
  "geometry": {"coordinates":[-6.4774870872,37.3955764771],"type":"Point"}
}