{
  "type": "Feature",
  "properties": {
    "addr:full":"Carrer de Pau (la), 36 Manlleu Barcelona 08560",
    "addr:housenumber":"36",
    "addr:postcode":"08560",
    "addr:street":"Carrer De Pau La",
    "iso:country":"ES",
    "sg:address":"Carrer de Pau (la), 36",
    "sg:city":"Manlleu",
    "sg:orig_category":"Fabricaci\u00d3n, Importaci\u00d3n De L\u00c1mparas Y Bombillas",
    "sg:phone":"+34 938 51 15 71",
    "sg:postcode":"08560",
    "sg:province":"Barcelona",
    "wof:name":"Lampisteria Codina S.l.",
    "wof:placetype":"venue"
},
  "geometry": {"coordinates":[2.2813351154,42.0021286011],"type":"Point"}
}