{
  "type": "Feature",
  "properties": {
    "addr:full":"Cabanillas Ii, 41 Cabanillas Campo Guadalajara 19171",
    "addr:housenumber":"41",
    "addr:postcode":"19171",
    "addr:street":"Ii",
    "iso:country":"ES",
    "sg:address":"Cabanillas Ii, 41",
    "sg:city":"Cabanillas Campo",
    "sg:orig_category":"Confecci\u00d3n De Ropa Interior",
    "sg:phone":"+34 949 20 20 04",
    "sg:postcode":"19171",
    "sg:province":"Guadalajara",
    "wof:name":"Confecciones Alcarre\u00f1as Sociedad Cooperativa",
    "wof:placetype":"venue"
},
  "geometry": {"coordinates":[-3.2374420166,40.6377639771],"type":"Point"}
}