{
  "type": "Feature",
  "properties": {
    "iso:country":"ES",
    "sg:address":"Ctra Olivenza, S/n",
    "sg:city":"Badajoz",
    "sg:orig_category":"Producci\u00d3n, Distribuci\u00d3n De Gas Butano Y Propano",
    "sg:phone":"+34 924 20 56 13",
    "sg:postcode":"06011",
    "sg:province":"Badajoz",
    "wof:name":"Rodriguez Alvarez Teofilo S.a.",
    "wof:placetype":"venue"
},
  "geometry": {"coordinates":[-6.9874491692,38.8595428467],"type":"Point"}
}