{
  "type": "Feature",
  "properties": {
    "addr:full":"Carr Bellpuig, 37 Felanitx Islas Baleares 07200",
    "addr:housenumber":"37",
    "addr:postcode":"07200",
    "addr:street":"Carr Bellpuig",
    "iso:country":"ES",
    "sg:address":"Carr Bellpuig, 37",
    "sg:city":"Felanitx",
    "sg:orig_category":"Revestimiento No Met\u00c1licos (esmaltado, Pintura, Plastificado)",
    "sg:phone":"+34 971 58 07 20",
    "sg:postcode":"07200",
    "sg:province":"Islas Baleares",
    "wof:name":"Foyedo Alvarez Olga",
    "wof:placetype":"venue"
},
  "geometry": {"coordinates":[3.1532559395,39.470539093],"type":"Point"}
}