{
  "type": "Feature",
  "properties": {
    "addr:full":"Urb. Olivar, 2 Churriana M\u00e1laga 29140",
    "addr:housenumber":"2",
    "addr:postcode":"29140",
    "addr:street":"Olivar",
    "iso:country":"ES",
    "sg:address":"Urb. Olivar, 2",
    "sg:city":"Churriana",
    "sg:orig_category":"M\u00c9dicos: Cirug\u00cda Cardiovascular Y Tor\u00c1cica",
    "sg:phone":"+34 952 43 52 56",
    "sg:postcode":"29140",
    "sg:province":"M\u00e1laga",
    "wof:name":"Gonzalez De Vega San Roman Norberto",
    "wof:placetype":"venue"
},
  "geometry": {"coordinates":[-4.5047240257,36.6686935425],"type":"Point"}
}