{
  "type": "Feature",
  "properties": {
    "iso:country":"ES",
    "sg:address":"Rambla F, 11",
    "sg:city":"Mollerussa",
    "sg:orig_category":"Arquitectos",
    "sg:phone":"+34 973 71 10 84",
    "sg:postcode":"25230",
    "sg:province":"Lleida",
    "wof:name":"Ruiz Altisent Pablo",
    "wof:placetype":"venue"
},
  "geometry": {"coordinates":[0.8936949968,41.6300392151],"type":"Point"}
}