{
  "type": "Feature",
  "properties": {
    "addr:full":"Avda Generalitat, 99 Palleja Barcelona 08780",
    "addr:housenumber":"99",
    "addr:postcode":"08780",
    "addr:street":"Avda Generalitat",
    "iso:country":"ES",
    "sg:address":"Avda Generalitat, 99",
    "sg:city":"Palleja",
    "sg:orig_category":"Molduras, Junquillos, Listones Y Molduras Perforadas",
    "sg:phone":"+34 936 63 21 56",
    "sg:postcode":"08780",
    "sg:province":"Barcelona",
    "wof:name":"Toara S.c.p.",
    "wof:placetype":"venue"
},
  "geometry": {"coordinates":[1.996284008,41.4246788025],"type":"Point"}
}