{
  "type": "Feature",
  "properties": {
    "addr:full":"Calle de Gobernador, 10 Castellon Castell\u00f3n 12003",
    "addr:housenumber":"10",
    "addr:postcode":"12003",
    "addr:street":"Calle De Gobernador",
    "iso:country":"ES",
    "sg:address":"Calle de Gobernador, 10",
    "sg:city":"Castellon",
    "sg:orig_category":"Abogados",
    "sg:phone":"+34 964 22 01 74",
    "sg:postcode":"12003",
    "sg:province":"Castell\u00f3n",
    "wof:name":"Iranzo Barcelo Manuel",
    "wof:placetype":"venue"
},
  "geometry": {"coordinates":[-0.0077,39.9838409424],"type":"Point"}
}