{
  "type": "Feature",
  "properties": {
    "iso:country":"ES",
    "sg:address":"Calle de Kale Nagusia, 26",
    "sg:city":"Tolosa",
    "sg:orig_category":"Plomeros",
    "sg:phone":"+34 943 67 08 48",
    "sg:postcode":"20400",
    "sg:province":"Guip\u00f9zcoa",
    "wof:name":"Ramos Pordomingo Rafael",
    "wof:placetype":"venue"
},
  "geometry": {"coordinates":[-2.0721828938,43.1390113831],"type":"Point"}
}