{
  "type": "Feature",
  "properties": {
    "addr:full":"Calle de Curro Muela, 7 Algeciras C\u00e1diz 11206",
    "addr:housenumber":"7;ca\u0301diz",
    "addr:postcode":"11206",
    "addr:street":"Calle De Curro Muela",
    "iso:country":"ES",
    "sg:address":"Calle de Curro Muela, 7",
    "sg:city":"Algeciras",
    "sg:orig_category":"Empresas De Hormig\u00d3n, Hormig\u00d3n Armado Y Pretensado",
    "sg:phone":"+34 956 60 12 24",
    "sg:postcode":"11206",
    "sg:province":"C\u00e1diz",
    "wof:name":"Jimenez Sanchez Josefa",
    "wof:placetype":"venue"
},
  "geometry": {"coordinates":[-5.4794068336,36.1181755066],"type":"Point"}
}