{
  "type": "Feature",
  "properties": {
    "iso:country":"ES",
    "sg:address":"Calle de Potasa, 2",
    "sg:city":"Madrid",
    "sg:orig_category":"Alimentaci\u00d3n General (al Por Menor)",
    "sg:phone":"+34 917 98 11 71",
    "sg:postcode":"28021",
    "sg:province":"Madrid",
    "wof:name":"Arranz Adrados Martin Isidoro",
    "wof:placetype":"venue"
},
  "geometry": {"coordinates":[-3.6819117069,40.3531494141],"type":"Point"}
}