{
  "type": "Feature",
  "properties": {
    "iso:country":"ES",
    "sg:address":"Ctra Autopista A18, Km. 0017,8",
    "sg:city":"Terrassa",
    "sg:orig_category":"Agencias De Viajes",
    "sg:phone":"+34 937 84 52 62",
    "sg:postcode":"08228",
    "sg:province":"Barcelona",
    "sg:website":"www.carrefour.es/viajes",
    "wof:name":"Viajes Carrefour S.l.",
    "wof:placetype":"venue"
},
  "geometry": {"coordinates":[2.0389900208,41.536441803],"type":"Point"}
}