{
  "type": "Feature",
  "properties": {
    "addr:full":"Calle de Pintor Barjola, 17 Badajoz Badajoz 06007",
    "addr:housenumber":"17",
    "addr:postcode":"06007",
    "addr:street":"Calle De Pintor Barjola",
    "iso:country":"ES",
    "sg:address":"Calle de Pintor Barjola, 17",
    "sg:city":"Badajoz",
    "sg:orig_category":"Congelados: Productos Alimentarios (al Por Menor)",
    "sg:phone":"+34 924 27 26 80",
    "sg:postcode":"06007",
    "sg:province":"Badajoz",
    "wof:name":"Plataforma Distribucion Alimentos S.l.",
    "wof:placetype":"venue"
},
  "geometry": {"coordinates":[-6.9802317619,38.8873901367],"type":"Point"}
}