{
  "type": "Feature",
  "properties": {
    "addr:full":"Calle de San Antonio Maria Claret, 28 Zaragoza Zaragoza 50005",
    "addr:housenumber":"28",
    "addr:postcode":"50005",
    "addr:street":"Calle De San;Maria Claret",
    "iso:country":"ES",
    "sg:address":"Calle de San Antonio Maria Claret, 28",
    "sg:city":"Zaragoza",
    "sg:orig_category":"Molduras, Junquillos, Listones Y Molduras Perforadas",
    "sg:phone":"+34 976 55 69 03",
    "sg:postcode":"50005",
    "sg:province":"Zaragoza",
    "wof:name":"Anachuri Navarro Alex",
    "wof:placetype":"venue"
},
  "geometry": {"coordinates":[-0.8949214816,41.6449508667],"type":"Point"}
}