{
  "type": "Feature",
  "properties": {
    "addr:full":"Carrer de Maluquer, 6 Hospitalet Llobregat Barcelona 08902",
    "addr:housenumber":"6",
    "addr:postcode":"08902",
    "addr:street":"Carrer De Maluquer",
    "iso:country":"ES",
    "sg:address":"Carrer de Maluquer, 6",
    "sg:city":"Hospitalet Llobregat",
    "sg:orig_category":"Rectificaci\u00d3n, Mecanizado, Fresado",
    "sg:phone":"+34 933 32 38 14",
    "sg:postcode":"08902",
    "sg:province":"Barcelona",
    "wof:name":"Marpo S.c.p.",
    "wof:placetype":"venue"
},
  "geometry": {"coordinates":[2.1256530285,41.3672599792],"type":"Point"}
}