{
  "type": "Feature",
  "properties": {
    "addr:full":"Calle de Madro\u00d1o, 10 Arganda Madrid 28500",
    "addr:housenumber":"10",
    "addr:postcode":"28500",
    "addr:street":"Calle De Madron\u0303O",
    "iso:country":"ES",
    "sg:address":"Calle de Madro\u00d1o, 10",
    "sg:city":"Arganda",
    "sg:orig_category":"Ense\u00d1anza Variada",
    "sg:phone":"+34 918 71 51 70",
    "sg:postcode":"28500",
    "sg:province":"Madrid",
    "sg:website":"www.esculturas-soriano.com",
    "wof:name":"Edoba Bellas Artes S.l.",
    "wof:placetype":"venue"
},
  "geometry": {"coordinates":[-3.4586880207,40.3155517578],"type":"Point"}
}