{
  "type": "Feature",
  "properties": {
    "addr:full":"Calle de Antonio Zamora, 53 Madrid Madrid 28011",
    "addr:housenumber":"53",
    "addr:postcode":"madrid;28011",
    "addr:street":"Calle De Antonio Zamora",
    "iso:country":"ES",
    "sg:address":"Calle de Antonio Zamora, 53",
    "sg:city":"Madrid",
    "sg:orig_category":"Empresas De Carpinter\u00cda De Madera",
    "sg:phone":"+34 914 79 93 55",
    "sg:postcode":"28011",
    "sg:province":"Madrid",
    "wof:name":"Lozano Garcia Felipe",
    "wof:placetype":"venue"
},
  "geometry": {"coordinates":[-3.7309026718,40.4123764038],"type":"Point"}
}