{
  "type": "Feature",
  "properties": {
    "iso:country":"ES",
    "sg:address":"Calle de Pintor Oliet, 17",
    "sg:city":"Castellon",
    "sg:orig_category":"Venta, Montaje De Neum\u00c1ticos",
    "sg:phone":"+34 964 21 04 66",
    "sg:postcode":"12006",
    "sg:province":"Castell\u00f3n",
    "wof:name":"Garage Castellon S. L.",
    "wof:placetype":"venue"
},
  "geometry": {"coordinates":[-0.1292939931,40.0168533325],"type":"Point"}
}