{
  "type": "Feature",
  "properties": {
    "addr:full":"Urb. Lomas Jarama, 7 Paracuellos Madrid 28860",
    "addr:housenumber":"7",
    "addr:postcode":"28860",
    "addr:street":"Jarama",
    "iso:country":"ES",
    "sg:address":"Urb. Lomas Jarama, 7",
    "sg:city":"Paracuellos",
    "sg:orig_category":"M\u00c9dicos: Radiolog\u00cda (radiodiagn\u00d3stico E Im\u00c1genes En Medicina)",
    "sg:phone":"+34 916 58 22 41",
    "sg:postcode":"28860",
    "sg:province":"Madrid",
    "wof:name":"Imagen Radiologica Integral S.l.",
    "wof:placetype":"venue"
},
  "geometry": {"coordinates":[-3.5296940804,40.5049209595],"type":"Point"}
}