{
  "type": "Feature",
  "properties": {
    "addr:full":"Ctra Tordesillas, 42 Zamora Zamora 49022",
    "addr:housenumber":"42",
    "addr:postcode":"49022",
    "addr:street":"Ctra Tordesillas",
    "iso:country":"ES",
    "sg:address":"Ctra Tordesillas, 42",
    "sg:city":"Zamora",
    "sg:orig_category":"Mataderos Y Talleres De Despiezado",
    "sg:phone":"+34 980 51 25 28",
    "sg:postcode":"49022",
    "sg:province":"Zamora",
    "wof:name":"Baltasar Moralejo E Hijos C.b.",
    "wof:placetype":"venue"
},
  "geometry": {"coordinates":[-5.7157988548,41.5243606567],"type":"Point"}
}