{
  "type": "Feature",
  "properties": {
    "iso:country":"ES",
    "sg:address":"Cabezas De Las, S/n",
    "sg:city":"Puebla Guzman",
    "sg:orig_category":"Hormigonados",
    "sg:phone":"+34 959 50 43 70",
    "sg:postcode":"21505",
    "sg:province":"Huelva",
    "wof:name":"Aridos Y Hormigones Del Norte S.a.",
    "wof:placetype":"venue"
},
  "geometry": {"coordinates":[-7.247112751,37.6161651611],"type":"Point"}
}