{
  "type": "Feature",
  "properties": {
    "addr:full":"Ctra Granada (de), 56 Alhama Granada Granada 18120",
    "addr:housenumber":"56",
    "addr:postcode":"18120",
    "addr:street":"Ctra Granada De",
    "iso:country":"ES",
    "sg:address":"Ctra Granada (de), 56",
    "sg:city":"Alhama Granada",
    "sg:orig_category":"Mec\u00c1nico Del Autom\u00d3vil",
    "sg:phone":"+34 958 36 06 16",
    "sg:postcode":"18120",
    "sg:province":"Granada",
    "wof:name":"Espejo Lopez Ricardo",
    "wof:placetype":"venue"
},
  "geometry": {"coordinates":[-3.9870889187,37.0062599182],"type":"Point"}
}