{
  "type": "Feature",
  "properties": {
    "addr:full":"Calle de Voluntad, 2 Sevilla Sevilla 41010",
    "addr:housenumber":"2",
    "addr:postcode":"41010",
    "addr:street":"Calle De Voluntad",
    "iso:country":"ES",
    "sg:address":"Calle de Voluntad, 2",
    "sg:city":"Sevilla",
    "sg:orig_category":"Mec\u00c1nico Del Autom\u00d3vil",
    "sg:phone":"+34 954 45 23 05",
    "sg:postcode":"41010",
    "sg:province":"Sevilla",
    "wof:name":"Estevez Estevez Antonio",
    "wof:placetype":"venue"
},
  "geometry": {"coordinates":[-6.0059938431,37.3792457581],"type":"Point"}
}