{
  "type": "Feature",
  "properties": {
    "addr:full":"Cmno Cervantes, S/n Almeria Almer\u00eda 04009",
    "addr:housenumber":"s / n",
    "addr:postcode":"04009",
    "addr:street":"Cmno Cervantes",
    "iso:country":"ES",
    "sg:address":"Cmno Cervantes, S/n",
    "sg:city":"Almeria",
    "sg:orig_category":"Electrodom\u00c9sticos (fabricaci\u00d3n, Al Por Mayor)",
    "sg:phone":"+34 950 14 14 67",
    "sg:postcode":"04009",
    "sg:province":"Almer\u00eda",
    "sg:website":"www.miro.es",
    "wof:name":"Establecimientos Miro S.l.",
    "wof:placetype":"venue"
},
  "geometry": {"coordinates":[-2.4499390125,36.8543548584],"type":"Point"}
}