{
  "type": "Feature",
  "properties": {
    "addr:full":"Calle de Gil De Jaz, 9 Oviedo Asturias 33004",
    "addr:housenumber":"9",
    "addr:postcode":"33004",
    "addr:street":"Calle De Gil De Jaz",
    "iso:country":"ES",
    "sg:address":"Calle de Gil De Jaz, 9",
    "sg:city":"Oviedo",
    "sg:orig_category":"Pescader\u00cdas (al Por Menor)",
    "sg:phone":"+34 985 24 27 20",
    "sg:postcode":"33004",
    "sg:province":"Asturias",
    "wof:name":"Astorgano Garcia Andres",
    "wof:placetype":"venue"
},
  "geometry": {"coordinates":[-5.8532691002,43.363319397],"type":"Point"}
}