{
  "type": "Feature",
  "properties": {
    "addr:full":"Pg Joan Carles I, S/n Eivissa Islas Baleares 07800",
    "addr:housenumber":"s",
    "addr:postcode":"07800",
    "addr:street":"Pg Joan Carles I;/ N",
    "iso:country":"ES",
    "sg:address":"Pg Joan Carles I, S/n",
    "sg:city":"Eivissa",
    "sg:orig_category":"Inmobiliaria (agencias)",
    "sg:phone":"+34 971 31 68 42",
    "sg:postcode":"07800",
    "sg:province":"Islas Baleares",
    "wof:name":"Fredu Link Powerboats International Service S.a.",
    "wof:placetype":"venue"
},
  "geometry": {"coordinates":[1.4466700554,38.9146118164],"type":"Point"}
}