{
  "type": "Feature",
  "properties": {
    "addr:full":"Calle de Blanca Paloma, 5 Bormujos Sevilla 41930",
    "addr:housenumber":"5",
    "addr:postcode":"41930",
    "addr:street":"Calle De Blanca Paloma",
    "iso:country":"ES",
    "sg:address":"Calle de Blanca Paloma, 5",
    "sg:city":"Bormujos",
    "sg:orig_category":"Carnicer\u00cdas, Carnicer\u00cdas",
    "sg:phone":"+34 955 72 68 14",
    "sg:postcode":"41930",
    "sg:province":"Sevilla",
    "wof:name":"Moreno Caballero Pedro Antonio",
    "wof:placetype":"venue"
},
  "geometry": {"coordinates":[-6.0693540573,37.3746452332],"type":"Point"}
}