{
  "type": "Feature",
  "properties": {
    "addr:full":"Avda Gran Via, 44 Vigo Pontevedra 36203",
    "addr:housenumber":"44",
    "addr:postcode":"36203",
    "addr:street":"Avda Gran Via",
    "iso:country":"ES",
    "sg:address":"Avda Gran Via, 44",
    "sg:city":"Vigo",
    "sg:orig_category":"Ropa Para Se\u00d1oras (al Por Menor)",
    "sg:phone":"+34 986 47 05 44",
    "sg:postcode":"36203",
    "sg:province":"Pontevedra",
    "wof:name":"Vidrio Orense S.l.",
    "wof:placetype":"venue"
},
  "geometry": {"coordinates":[-8.7183666229,42.2313728333],"type":"Point"}
}