{
  "type": "Feature",
  "properties": {
    "addr:full":"Calle de Jose Yanez Matos, S/n San Fernando Las Palmas 35100",
    "addr:housenumber":"s / n",
    "addr:postcode":"35100",
    "addr:street":"Calle De Jose Yanez Matos",
    "iso:country":"ES",
    "sg:address":"Calle de Jose Yanez Matos, S/n",
    "sg:city":"San Fernando",
    "sg:orig_category":"Supermercados Y Hipermercados",
    "sg:phone":"+34 928 76 33 57",
    "sg:postcode":"35100",
    "sg:province":"Las Palmas",
    "wof:name":"Comercial Sparsur S.l.",
    "wof:placetype":"venue"
},
  "geometry": {"coordinates":[-15.5842504501,28.0904903412],"type":"Point"}
}