{
  "type": "Feature",
  "properties": {
    "iso:country":"ES",
    "sg:address":"Calle de Colon De Larreategui, 21",
    "sg:city":"Bilbao",
    "sg:orig_category":"Art\u00cdculos De Decoraci\u00d3n",
    "sg:phone":"+34 944 23 20 90",
    "sg:postcode":"48001",
    "sg:province":"Vizcaya",
    "wof:name":"Lozano Allende Maria Mercedes",
    "wof:placetype":"venue"
},
  "geometry": {"coordinates":[-2.9301562309,43.2630195618],"type":"Point"}
}