{
  "type": "Feature",
  "properties": {
    "addr:full":"Calle de Canales, 37 Poligono Industrial Salinas De San Jose C\u00e1diz 11500",
    "addr:housenumber":"37",
    "addr:postcode":"11500",
    "addr:street":"Calle De Canales;Industrial;Ca\u0301Diz",
    "iso:country":"ES",
    "sg:address":"Calle de Canales, 37",
    "sg:city":"Poligono Industrial Salinas De San Jose",
    "sg:orig_category":"Aluminio Y Aleaciones (producci\u00d3n, Transformaci\u00d3n, Negocio)",
    "sg:phone":"+34 956 85 80 30",
    "sg:postcode":"11500",
    "sg:province":"C\u00e1diz",
    "wof:name":"Galisur 2 S.l.",
    "wof:placetype":"venue"
},
  "geometry": {"coordinates":[-6.2048869133,36.6137580872],"type":"Point"}
}