{
  "type": "Feature",
  "properties": {
    "iso:country":"ES",
    "sg:address":"Barr Mendiola, S/n",
    "sg:city":"Zubiaur",
    "sg:orig_category":"Fabricaci\u00d3n De Quesos",
    "sg:phone":"+34 946 33 97 09",
    "sg:postcode":"48410",
    "sg:province":"Vizcaya",
    "wof:name":"Quesos Malatsa S.l.",
    "wof:placetype":"venue"
},
  "geometry": {"coordinates":[-2.9118039608,43.1077194214],"type":"Point"}
}