{
  "type": "Feature",
  "properties": {
    "iso:country":"ES",
    "sg:address":"Calle de Ruise\u00d1or, 2",
    "sg:city":"Utrera",
    "sg:orig_category":"Adaptaciones, Acondicionamientos Especiales Para Veh\u00cdculos, Veh\u00cdculos Industriales",
    "sg:phone":"+34 954 86 17 32",
    "sg:postcode":"41710",
    "sg:province":"Sevilla",
    "wof:name":"Quesada Garrido Jose",
    "wof:placetype":"venue"
},
  "geometry": {"coordinates":[-5.7731590271,37.1854553223],"type":"Point"}
}