{
  "type": "Feature",
  "properties": {
    "addr:full":"Calle de Padre Pandelo, 47 Linea De La Concepcion C\u00e1diz 11300",
    "addr:housenumber":"47",
    "addr:postcode":"11300",
    "addr:street":"Calle De Padre Pandelo;Ca\u0301Diz",
    "iso:country":"ES",
    "sg:address":"Calle de Padre Pandelo, 47",
    "sg:city":"Linea De La Concepcion",
    "sg:orig_category":"Peluquer\u00cdas, Peluquer\u00cda Mixta",
    "sg:phone":"+34 956 76 58 21",
    "sg:postcode":"11300",
    "sg:province":"C\u00e1diz",
    "wof:name":"Burgos Rodriguez Eva Maria",
    "wof:placetype":"venue"
},
  "geometry": {"coordinates":[-5.3449778557,36.1715240479],"type":"Point"}
}