{
  "type": "Feature",
  "properties": {
    "addr:full":"Ctra Alcover D', 10 Valls Tarragona 43800",
    "addr:housenumber":"10",
    "addr:postcode":"43800",
    "addr:street":"Ctra Alcover D '",
    "iso:country":"ES",
    "sg:address":"Ctra Alcover D', 10",
    "sg:city":"Valls",
    "sg:orig_category":"Mec\u00c1nico Del Autom\u00d3vil",
    "sg:phone":"+34 977 60 50 47",
    "sg:postcode":"43800",
    "sg:province":"Tarragona",
    "wof:name":"Rubio Barrabeig Jorge",
    "wof:placetype":"venue"
},
  "geometry": {"coordinates":[1.2525299788,41.2871513367],"type":"Point"}
}