{
  "type": "Feature",
  "properties": {
    "addr:full":"Carr Marenys, 1 Sueca Valencia 46410",
    "addr:housenumber":"1",
    "addr:postcode":"46410",
    "addr:street":"Carr Marenys",
    "iso:country":"ES",
    "sg:address":"Carr Marenys, 1",
    "sg:city":"Sueca",
    "sg:orig_category":"Maquinaria Para Industrias Diversas",
    "sg:phone":"+34 961 70 16 71",
    "sg:postcode":"46410",
    "sg:province":"Valencia",
    "wof:name":"Excavaciones Sueca S.l.",
    "wof:placetype":"venue"
},
  "geometry": {"coordinates":[-0.3078460097,39.2074508667],"type":"Point"}
}