{
  "type": "Feature",
  "properties": {
    "iso:country":"ES",
    "sg:address":"Carrer de Guitard, 79",
    "sg:city":"Barcelona",
    "sg:orig_category":"Asesor\u00cda Fiscal Y Jur\u00cddica",
    "sg:phone":"+34 934 90 10 40",
    "sg:postcode":"08014",
    "sg:province":"Barcelona",
    "wof:name":"Muvara Asesores Sl",
    "wof:placetype":"venue"
},
  "geometry": {"coordinates":[2.1358990669,41.3845596313],"type":"Point"}
}