{
  "type": "Feature",
  "properties": {
    "addr:full":"Carrer de Llull, 98 Barcelona Barcelona 08005",
    "addr:housenumber":"98",
    "addr:postcode":"08005",
    "addr:street":"Carrer De Llull",
    "iso:country":"ES",
    "sg:address":"Carrer de Llull, 98",
    "sg:city":"Barcelona",
    "sg:orig_category":"Institutos De Belleza",
    "sg:phone":"+34 933 00 04 59",
    "sg:postcode":"08005",
    "sg:province":"Barcelona",
    "wof:name":"Torra Amador Ester",
    "wof:placetype":"venue"
},
  "geometry": {"coordinates":[2.1957359314,41.3960800171],"type":"Point"}
}