{
  "type": "Feature",
  "properties": {
    "addr:full":"Calle de Alfares (los), 16 Alcorcon Madrid 28921",
    "addr:housenumber":"16",
    "addr:postcode":"28921",
    "addr:street":"Calle De Alfares Los",
    "iso:country":"ES",
    "sg:address":"Calle de Alfares (los), 16",
    "sg:city":"Alcorcon",
    "sg:orig_category":"Madera Para Construcci\u00d3n E Industria",
    "sg:phone":"+34 916 43 47 35",
    "sg:postcode":"28921",
    "sg:province":"Madrid",
    "wof:name":"Ortega Hernandez Miguel",
    "wof:placetype":"venue"
},
  "geometry": {"coordinates":[-3.8293302059,40.3467597961],"type":"Point"}
}