{
  "type": "Feature",
  "properties": {
    "iso:country":"ES",
    "sg:address":"Avda Badajoz, S/n",
    "sg:city":"Don Benito",
    "sg:orig_category":"Promotores Constructores",
    "sg:phone":"+34 924 80 42 16",
    "sg:postcode":"06400",
    "sg:province":"Badajoz",
    "wof:name":"Ute Joca-magenta",
    "wof:placetype":"venue"
},
  "geometry": {"coordinates":[-5.8750867844,38.9542579651],"type":"Point"}
}