{
  "type": "Feature",
  "properties": {
    "iso:country":"ES",
    "sg:address":"Pl. Esglesia, 2",
    "sg:city":"Sa Pobla",
    "sg:orig_category":"Iglesia Cat\u00d3lica",
    "sg:phone":"+34 971 54 02 94",
    "sg:postcode":"07420",
    "sg:province":"Islas Baleares",
    "wof:name":"Obispado De Mallorca",
    "wof:placetype":"venue"
},
  "geometry": {"coordinates":[3.0235850811,39.7697639465],"type":"Point"}
}