{
  "type": "Feature",
  "properties": {
    "iso:country":"ES",
    "sg:address":"Carrer de Joan Prim, 74",
    "sg:city":"Premia Mar",
    "sg:orig_category":"Sociedades, Compa\u00d1\u00cdas Aseguradoras",
    "sg:phone":"+34 937 51 03 34",
    "sg:postcode":"08330",
    "sg:province":"Barcelona",
    "wof:name":"Assegurances Hernando Barrio S.l.",
    "wof:placetype":"venue"
},
  "geometry": {"coordinates":[2.3577666283,41.4935417175],"type":"Point"}
}