{
  "type": "Feature",
  "properties": {
    "addr:full":"Avda Independencia, 16 Zaragoza Zaragoza 50004",
    "addr:housenumber":"16",
    "addr:postcode":"50004",
    "addr:street":"Avda Independencia",
    "iso:country":"ES",
    "sg:address":"Avda Independencia, 16",
    "sg:city":"Zaragoza",
    "sg:orig_category":"Abogados",
    "sg:phone":"+34 976 21 10 78",
    "sg:postcode":"50004",
    "sg:province":"Zaragoza",
    "wof:name":"Royo Banzo Juan Carlos",
    "wof:placetype":"venue"
},
  "geometry": {"coordinates":[-0.8826209903,41.6505279541],"type":"Point"}
}