{
  "type": "Feature",
  "properties": {
    "addr:full":"Bazarra, S/n Bazarra A Coru\u00f1a 15270",
    "addr:postcode":"15270",
    "addr:street":"Bazarra S / N;Corun\u0303A",
    "iso:country":"ES",
    "sg:address":"Bazarra, S/n",
    "sg:city":"Bazarra",
    "sg:orig_category":"Electricidad (montaje, Ensamblaje De Componentes)",
    "sg:phone":"+34 981 74 71 06",
    "sg:postcode":"15270",
    "sg:province":"A Coru\u00f1a",
    "wof:name":"Trillo Dominguez Victor Manuel",
    "wof:placetype":"venue"
},
  "geometry": {"coordinates":[-9.187494278,42.9554710388],"type":"Point"}
}