{
  "type": "Feature",
  "properties": {
    "iso:country":"ES",
    "sg:address":"Barr Rubin, 3",
    "sg:city":"Gijon",
    "sg:orig_category":"Calefacci\u00d3n Central: Material (fabricaci\u00d3n, Al Por Mayor)",
    "sg:phone":"+34 985 32 23 50",
    "sg:postcode":"33213",
    "sg:province":"Asturias",
    "wof:name":"Astureco Sociedad Limitada",
    "wof:placetype":"venue"
},
  "geometry": {"coordinates":[-5.7023448944,43.5375518799],"type":"Point"}
}