{
  "type": "Feature",
  "properties": {
    "addr:full":"Pase Canalejas, 58 Salamanca Salamanca 37001",
    "addr:housenumber":"58",
    "addr:postcode":"37001",
    "addr:street":"Canalejas",
    "iso:country":"ES",
    "sg:address":"Pase Canalejas, 58",
    "sg:city":"Salamanca",
    "sg:orig_category":"Agencias De Trabajo Temporal",
    "sg:phone":"+34 923 21 68 46",
    "sg:postcode":"37001",
    "sg:province":"Salamanca",
    "sg:website":"www.manpower.es",
    "wof:name":"Manpower Team Empresas De Trabajo Temporal",
    "wof:placetype":"venue"
},
  "geometry": {"coordinates":[-5.6580238342,40.965675354],"type":"Point"}
}