{
  "type": "Feature",
  "properties": {
    "addr:full":"Cmno Pi\u00d1era (la), S/n Cruz Santa Santa Cruz De Tenerife 38413",
    "addr:postcode":"38413",
    "addr:street":"Cmno Pin\u0303Era La S / N Cruz Santa",
    "iso:country":"ES",
    "sg:address":"Cmno Pi\u00d1era (la), S/n",
    "sg:city":"Cruz Santa",
    "sg:orig_category":"Cerrajer\u00cda, Ferrallista",
    "sg:phone":"+34 922 34 13 57",
    "sg:postcode":"38413",
    "sg:province":"Santa Cruz De Tenerife",
    "wof:name":"Cerrajeria Bencomo S.l.",
    "wof:placetype":"venue"
},
  "geometry": {"coordinates":[-16.5606460571,28.3570613861],"type":"Point"}
}