{
  "type": "Feature",
  "properties": {
    "addr:full":"Avda Antonio Trueba, 21 San Juan De Muskiz Vizcaya 48550",
    "addr:housenumber":"21",
    "addr:postcode":"48550",
    "addr:street":"Avda Antonio Trueba",
    "iso:country":"ES",
    "sg:address":"Avda Antonio Trueba, 21",
    "sg:city":"San Juan De Muskiz",
    "sg:orig_category":"Carnicer\u00cdas, Carnicer\u00cdas",
    "sg:phone":"+34 946 70 67 01",
    "sg:postcode":"48550",
    "sg:province":"Vizcaya",
    "wof:name":"Martinez Zubizarreta Fernando",
    "wof:placetype":"venue"
},
  "geometry": {"coordinates":[-3.1151490211,43.3212394714],"type":"Point"}
}