{
  "type": "Feature",
  "properties": {
    "addr:full":"Av Rei Jaume I, S/n Benidorm Alicante 03500",
    "addr:housenumber":"s / n",
    "addr:postcode":"03500",
    "addr:street":"Av Rei Jaume I",
    "iso:country":"ES",
    "sg:address":"Av Rei Jaume I, S/n",
    "sg:city":"Benidorm",
    "sg:orig_category":"Caf\u00c9s, Bares, Cervecer\u00cdas",
    "sg:phone":"+34 965 86 49 19",
    "sg:postcode":"03500",
    "sg:province":"Alicante",
    "wof:name":"Garrido Mu\u00f1oz Marcos",
    "wof:placetype":"venue"
},
  "geometry": {"coordinates":[-0.1374190003,38.5375099182],"type":"Point"}
}