{
  "type": "Feature",
  "properties": {
    "addr:full":"Calle de San Pedro, 2 Ojos Murcia 30611",
    "addr:housenumber":"2",
    "addr:postcode":"30611",
    "addr:street":"Calle De San Pedro",
    "iso:country":"ES",
    "sg:address":"Calle de San Pedro, 2",
    "sg:city":"Ojos",
    "sg:orig_category":"Iglesia Cat\u00d3lica",
    "sg:phone":"+34 968 69 80 26",
    "sg:postcode":"30611",
    "sg:province":"Murcia",
    "wof:name":"Obispado De Cartagena",
    "wof:placetype":"venue"
},
  "geometry": {"coordinates":[-1.3413239717,38.1477661133],"type":"Point"}
}