{
  "type": "Feature",
  "properties": {
    "iso:country":"ES",
    "sg:address":"Carrer de Anoia, S/n",
    "sg:city":"S. Quirze Valles",
    "sg:orig_category":"Molduras, Junquillos, Listones Y Molduras Perforadas",
    "sg:phone":"+34 937 21 39 72",
    "sg:postcode":"08192",
    "sg:province":"Barcelona",
    "wof:name":"Montero Sandoval Jose",
    "wof:placetype":"venue"
},
  "geometry": {"coordinates":[2.0754499435,41.5411834717],"type":"Point"}
}