{
  "type": "Feature",
  "properties": {
    "iso:country":"ES",
    "sg:address":"Calle de Tudela, 5",
    "sg:city":"Valladolid",
    "sg:orig_category":"T\u00c9cnicos Veterinarios",
    "sg:phone":"+34 983 29 49 02",
    "sg:postcode":"47002",
    "sg:province":"Valladolid",
    "wof:name":"Horno Lozano Antonio",
    "wof:placetype":"venue"
},
  "geometry": {"coordinates":[-4.7189249992,41.6479721069],"type":"Point"}
}