{
  "type": "Feature",
  "properties": {
    "iso:country":"ES",
    "sg:address":"Calle de Doctor Benitez, 6",
    "sg:city":"Jerez De Los Caballeros",
    "sg:orig_category":"Panader\u00cdas, Panader\u00cdas",
    "sg:phone":"+34 924 73 01 72",
    "sg:postcode":"06380",
    "sg:province":"Badajoz",
    "wof:name":"Pitel Jimenez Tomasa",
    "wof:placetype":"venue"
},
  "geometry": {"coordinates":[-6.7716803551,38.3195877075],"type":"Point"}
}