{
  "type": "Feature",
  "properties": {
    "addr:full":"Calle de Circuncision, 6 Valladolid Valladolid 47011",
    "addr:housenumber":"6",
    "addr:postcode":"47011",
    "addr:street":"Calle De Circuncision",
    "iso:country":"ES",
    "sg:address":"Calle de Circuncision, 6",
    "sg:city":"Valladolid",
    "sg:orig_category":"Transportes Por V\u00cdas Navegables",
    "sg:phone":"+34 983 25 96 36",
    "sg:postcode":"47011",
    "sg:province":"Valladolid",
    "wof:name":"Lopez Martin Felix",
    "wof:placetype":"venue"
},
  "geometry": {"coordinates":[-4.708425045,41.6600761414],"type":"Point"}
}