{
  "type": "Feature",
  "properties": {
    "addr:full":"Calle de Teniente Jose Olmo, 2 Ceuta Ceuta 51001",
    "addr:housenumber":"2",
    "addr:postcode":"51001",
    "addr:street":"Calle De Teniente Jose Olmo",
    "iso:country":"ES",
    "sg:address":"Calle de Teniente Jose Olmo, 2",
    "sg:city":"Ceuta",
    "sg:orig_category":"Molduras, Junquillos, Listones Y Molduras Perforadas",
    "sg:phone":"+34 956 51 36 20",
    "sg:postcode":"51001",
    "sg:province":"Ceuta",
    "wof:name":"Rojas Lago Jose",
    "wof:placetype":"venue"
},
  "geometry": {"coordinates":[-5.3302302361,35.8947601318],"type":"Point"}
}