{
  "type": "Feature",
  "properties": {
    "addr:full":"Carrer de Industria, 23 Barriada Nova Barcelona 08420",
    "addr:housenumber":"23",
    "addr:postcode":"08420",
    "addr:street":"Carrer De Industria;Nova Barcelona",
    "iso:country":"ES",
    "sg:address":"Carrer de Industria, 23",
    "sg:city":"Barriada Nova",
    "sg:orig_category":"M\u00c9dicos: Estomatolog\u00cda",
    "sg:phone":"+34 938 49 87 79",
    "sg:postcode":"08420",
    "sg:province":"Barcelona",
    "wof:name":"Zorita Crosas Asuncion",
    "wof:placetype":"venue"
},
  "geometry": {"coordinates":[2.2780098915,41.6220703125],"type":"Point"}
}