{
  "type": "Feature",
  "properties": {
    "addr:full":"Avda Madariaga, 20 Bilbao Vizcaya 48014",
    "addr:housenumber":"20",
    "addr:postcode":"48014",
    "addr:street":"Avda Madariaga",
    "iso:country":"ES",
    "sg:address":"Avda Madariaga, 20",
    "sg:city":"Bilbao",
    "sg:orig_category":"Perfumer\u00cda (al Por Menor)",
    "sg:phone":"+34 944 75 86 41",
    "sg:postcode":"48014",
    "sg:province":"Vizcaya",
    "sg:website":"www.marionnaud.es",
    "wof:name":"Marionnaud Perfumeries Iberica S.l.",
    "wof:placetype":"venue"
},
  "geometry": {"coordinates":[-2.948321104,43.271156311],"type":"Point"}
}