{
  "type": "Feature",
  "properties": {
    "addr:full":"Calle de Parras, 27 Almensilla Sevilla 41111",
    "addr:housenumber":"27",
    "addr:postcode":"41111",
    "addr:street":"Calle De Parras",
    "iso:country":"ES",
    "sg:address":"Calle de Parras, 27",
    "sg:city":"Almensilla",
    "sg:orig_category":"Cajas Y Embalajes De Madera",
    "sg:phone":"+34 955 76 75 00",
    "sg:postcode":"41111",
    "sg:province":"Sevilla",
    "wof:name":"Torres Caceres Maria Dolores",
    "wof:placetype":"venue"
},
  "geometry": {"coordinates":[-6.1162939072,37.3116874695],"type":"Point"}
}