{
  "type": "Feature",
  "properties": {
    "iso:country":"ES",
    "sg:address":"Crt. Guadalajara, Km. 0030,0",
    "sg:city":"Montarron",
    "sg:orig_category":"Producci\u00d3n De Abonos Y De Fertilizantes",
    "sg:phone":"+34 949 85 51 29",
    "sg:postcode":"19229",
    "sg:province":"Guadalajara",
    "wof:name":"Fertilizantes Y Mantillos De Guadalajara S.l.",
    "wof:placetype":"venue"
},
  "geometry": {"coordinates":[-3.2200291157,40.8894195557],"type":"Point"}
}