{
  "type": "Feature",
  "properties": {
    "addr:full":"Plaz Parroco Parer, 1 Ag\u00fcimes Las Palmas 35260",
    "addr:housenumber":"1",
    "addr:postcode":"35260",
    "addr:street":"Plaz;Parer",
    "iso:country":"ES",
    "sg:address":"Plaz Parroco Parer, 1",
    "sg:city":"Ag\u00fcimes",
    "sg:orig_category":"Iglesia Cat\u00d3lica",
    "sg:phone":"+34 928 78 18 46",
    "sg:postcode":"35260",
    "sg:province":"Las Palmas",
    "wof:name":"Parroquia San Sebastian",
    "wof:placetype":"venue"
},
  "geometry": {"coordinates":[-15.4447307587,27.9053421021],"type":"Point"}
}