{
  "type": "Feature",
  "properties": {
    "iso:country":"ES",
    "sg:address":"Ctra Aguilar, S/n",
    "sg:city":"Puente-genil",
    "sg:orig_category":"Mec\u00c1nico Del Autom\u00d3vil",
    "sg:phone":"+34 957 60 05 77",
    "sg:postcode":"14500",
    "sg:province":"C\u00f3rdoba",
    "wof:name":"Jimenez Sanchez Antonio",
    "wof:placetype":"venue"
},
  "geometry": {"coordinates":[-4.7720918655,37.3864707947],"type":"Point"}
}