{
  "type": "Feature",
  "properties": {
    "iso:country":"ES",
    "sg:address":"Av Miquel Utrillo, 43",
    "sg:city":"Sitges",
    "sg:orig_category":"Asesor\u00cda Sobre Comunicaci\u00d3n De Empresas",
    "sg:phone":"+34 938 94 04 56",
    "sg:postcode":"08870",
    "sg:province":"Barcelona",
    "wof:name":"Jade Management S.l.",
    "wof:placetype":"venue"
},
  "geometry": {"coordinates":[1.8018440008,41.249420166],"type":"Point"}
}