{
  "type": "Feature",
  "properties": {
    "iso:country":"ES",
    "sg:address":"Calle de Orotava La, 51",
    "sg:city":"Malaga",
    "sg:orig_category":"Carnicer\u00cdas, Carnicer\u00cdas",
    "sg:phone":"+34 952 04 07 95",
    "sg:postcode":"29006",
    "sg:province":"M\u00e1laga",
    "wof:name":"Campanillas Pizarra S.a.",
    "wof:placetype":"venue"
},
  "geometry": {"coordinates":[-4.4763870239,36.7024536133],"type":"Point"}
}