{
  "type": "Feature",
  "properties": {
    "addr:full":"Carrer de Convent Caputxins, 3 Palma Islas Baleares 07002",
    "addr:housenumber":"3",
    "addr:postcode":"07002",
    "addr:street":"Carrer De Convent Caputxins",
    "iso:country":"ES",
    "sg:address":"Carrer de Convent Caputxins, 3",
    "sg:city":"Palma",
    "sg:orig_category":"Deportes Diversos",
    "sg:phone":"+34 971 21 34 24",
    "sg:postcode":"07002",
    "sg:province":"Islas Baleares",
    "sg:website":"www.e-recalada.com",
    "wof:name":"Atoa Palma S.l.",
    "wof:placetype":"venue"
},
  "geometry": {"coordinates":[2.6527061462,39.5740242004],"type":"Point"}
}