{
  "type": "Feature",
  "properties": {
    "addr:full":"Calle de Lomillo (b), S/n Brazatortas Ciudad Real 13450",
    "addr:housenumber":"/ n",
    "addr:postcode":"13450",
    "addr:street":"Calle De Lomillo",
    "iso:country":"ES",
    "sg:address":"Calle de Lomillo (b), S/n",
    "sg:city":"Brazatortas",
    "sg:orig_category":"Trabajos De Asfalto, De Alquitr\u00c1n Y Asfalto",
    "sg:phone":"+34 926 47 10 59",
    "sg:postcode":"13450",
    "sg:province":"Ciudad Real",
    "sg:website":"www.repsolypf.com",
    "wof:name":"Repsol Ypf S.a.",
    "wof:placetype":"venue"
},
  "geometry": {"coordinates":[-4.2961387634,38.6615142822],"type":"Point"}
}