{
  "type": "Feature",
  "properties": {
    "addr:full":"Mercat Sant Antoni, S/n Barcelona Barcelona 08015",
    "addr:housenumber":"s",
    "addr:postcode":"08015",
    "addr:street":"/ N",
    "iso:country":"ES",
    "sg:address":"Mercat Sant Antoni, S/n",
    "sg:city":"Barcelona",
    "sg:orig_category":"Charcuter\u00cdas (al Por Mayor)",
    "sg:phone":"+34 934 26 07 39",
    "sg:postcode":"08015",
    "sg:province":"Barcelona",
    "wof:name":"Alemany Riu Maria De Los Angeles",
    "wof:placetype":"venue"
},
  "geometry": {"coordinates":[2.1620833874,41.3786125183],"type":"Point"}
}