{
  "type": "Feature",
  "properties": {
    "addr:full":"Calle de Domingo Arroquia, 1 Jodar Ja\u00e9n 23500",
    "addr:housenumber":"1",
    "addr:postcode":"23500",
    "addr:street":"Calle De Domingo Arroquia;Jae\u0301N",
    "iso:country":"ES",
    "sg:address":"Calle de Domingo Arroquia, 1",
    "sg:city":"Jodar",
    "sg:orig_category":"Asesor\u00cda Sobre Comunicaci\u00d3n De Empresas",
    "sg:phone":"+34 953 78 54 00",
    "sg:postcode":"23500",
    "sg:province":"Ja\u00e9n",
    "wof:name":"Garcia Caballero Francisco",
    "wof:placetype":"venue"
},
  "geometry": {"coordinates":[-3.3522901535,37.8384628296],"type":"Point"}
}