{
  "type": "Feature",
  "properties": {
    "addr:full":"Ptge. Ripoll, 3 Escala Girona 17130",
    "addr:housenumber":"3",
    "addr:postcode":"17130",
    "addr:street":"Ripoll",
    "iso:country":"ES",
    "sg:address":"Ptge. Ripoll, 3",
    "sg:city":"Escala",
    "sg:orig_category":"Asociaciones, Organismos Culturales Y Socioeducativos",
    "sg:phone":"+34 972 77 50 31",
    "sg:postcode":"17130",
    "sg:province":"Girona",
    "wof:name":"Asociacion Contact Propietarios Extranjeros",
    "wof:placetype":"venue"
},
  "geometry": {"coordinates":[3.1334762573,42.1128845215],"type":"Point"}
}