{
  "type": "Feature",
  "properties": {
    "iso:country":"ES",
    "sg:address":"Carrer de Arimon, 49",
    "sg:city":"Barcelona",
    "sg:orig_category":"Audiovisuales (producci\u00d3n, Edici\u00d3n, Realizaci\u00d3n)",
    "sg:phone":"+34 934 17 14 03",
    "sg:postcode":"08022",
    "sg:province":"Barcelona",
    "sg:website":"www.hazvisual.com",
    "wof:name":"Haz Visual S.c.p.",
    "wof:placetype":"venue"
},
  "geometry": {"coordinates":[2.135529995,41.4026756287],"type":"Point"}
}