{
  "type": "Feature",
  "properties": {
    "addr:full":"Calle de Trueba, 8 Donostia-san Sebastian Guip\u00f9zcoa 20001",
    "addr:housenumber":"8",
    "addr:postcode":"20001",
    "addr:street":"Calle De Trueba",
    "iso:country":"ES",
    "sg:address":"Calle de Trueba, 8",
    "sg:city":"Donostia-san Sebastian",
    "sg:orig_category":"Muebles, Minoristas",
    "sg:phone":"+34 943 29 20 12",
    "sg:postcode":"20001",
    "sg:province":"Guip\u00f9zcoa",
    "wof:name":"Grupo Divatto Prestige S.l.",
    "wof:placetype":"venue"
},
  "geometry": {"coordinates":[-1.9743340015,43.322555542],"type":"Point"}
}