{
  "type": "Feature",
  "properties": {
    "iso:country":"ES",
    "sg:address":"Barrio Puente Asnil, S/n",
    "sg:city":"Cabezon Liebana",
    "sg:orig_category":"Alimentaci\u00d3n General (al Por Mayor)",
    "sg:phone":"+34 942 73 50 44",
    "sg:postcode":"39571",
    "sg:province":"Cantabria",
    "wof:name":"Belsol Martinez Miguel",
    "wof:placetype":"venue"
},
  "geometry": {"coordinates":[-4.5762939453,43.1339645386],"type":"Point"}
}