{
  "type": "Feature",
  "properties": {
    "addr:full":"Send Pedro Ignacio Barrutia, 10 Vitoria-gasteiz \u00c1lava 01002",
    "addr:housenumber":"10",
    "addr:postcode":"01002",
    "addr:street":"Send Pedro Ignacio Barrutia",
    "iso:country":"ES",
    "sg:address":"Send Pedro Ignacio Barrutia, 10",
    "sg:city":"Vitoria-gasteiz",
    "sg:orig_category":"Pescader\u00cdas (al Por Menor)",
    "sg:phone":"+34 945 28 77 87",
    "sg:postcode":"01002",
    "sg:province":"\u00c1lava",
    "wof:name":"Almudena Diez Garcia",
    "wof:placetype":"venue"
},
  "geometry": {"coordinates":[-2.6623649597,42.85364151],"type":"Point"}
}