{
  "type": "Feature",
  "properties": {
    "addr:full":"Rbla General Vives, 25 Igualada Barcelona 08700",
    "addr:housenumber":"25",
    "addr:postcode":"08700",
    "addr:street":"Rbla General Vives",
    "iso:country":"ES",
    "sg:address":"Rbla General Vives, 25",
    "sg:city":"Igualada",
    "sg:orig_category":"Abogados",
    "sg:phone":"+34 938 03 68 41",
    "sg:postcode":"08700",
    "sg:province":"Barcelona",
    "wof:name":"Martinez Garcia Carles",
    "wof:placetype":"venue"
},
  "geometry": {"coordinates":[1.6195249557,41.5793533325],"type":"Point"}
}