{
  "type": "Feature",
  "properties": {
    "addr:full":"Cmno Pe\u00d1as Blancas, 4 Tias Las Palmas 35572",
    "addr:housenumber":"4",
    "addr:postcode":"35572",
    "addr:street":"Cmno Pen\u0303As Blancas",
    "iso:country":"ES",
    "sg:address":"Cmno Pe\u00d1as Blancas, 4",
    "sg:city":"Tias",
    "sg:orig_category":"Transportes Por V\u00cdas Navegables",
    "sg:phone":"+34 928 83 30 73",
    "sg:postcode":"35572",
    "sg:province":"Las Palmas",
    "wof:name":"Alvarez Bermudez Carmelo",
    "wof:placetype":"venue"
},
  "geometry": {"coordinates":[-13.6693258286,28.9573307037],"type":"Point"}
}