{
  "type": "Feature",
  "properties": {
    "addr:full":"Plaz Aragon, 3 Zaragoza Zaragoza 50004",
    "addr:housenumber":"3",
    "addr:postcode":"50004",
    "iso:country":"ES",
    "sg:address":"Plaz Aragon, 3",
    "sg:city":"Zaragoza",
    "sg:orig_category":"M\u00c9dicos: Pediatr\u00cda. Enfermedades De Los Ni\u00d1os",
    "sg:phone":"+34 976 22 19 47",
    "sg:postcode":"50004",
    "sg:province":"Zaragoza",
    "wof:name":"Ros Mar Luis",
    "wof:placetype":"venue"
},
  "geometry": {"coordinates":[-0.8844410181,41.6483421326],"type":"Point"}
}