{
  "type": "Feature",
  "properties": {
    "iso:country":"ES",
    "sg:address":"Calle de San Andres, S/n",
    "sg:city":"San Andres",
    "sg:orig_category":"Autob\u00das (explotaci\u00d3n Y Servicios De)",
    "sg:phone":"+34 968 29 22 11",
    "sg:postcode":"30005",
    "sg:province":"Murcia",
    "wof:name":"Cooperativa Interprovincial Concesionarios Servic. Regulares",
    "wof:placetype":"venue"
},
  "geometry": {"coordinates":[-1.137994051,37.9863166809],"type":"Point"}
}