{
  "type": "Feature",
  "properties": {
    "iso:country":"ES",
    "sg:address":"Rond Sant Antoni, 98",
    "sg:city":"Barcelona",
    "sg:orig_category":"Caf\u00c9s, Bares, Cervecer\u00cdas",
    "sg:phone":"+34 933 01 86 83",
    "sg:postcode":"08001",
    "sg:province":"Barcelona",
    "wof:name":"Cafes Caracas S.l.",
    "wof:placetype":"venue"
},
  "geometry": {"coordinates":[2.1640400887,41.3847160339],"type":"Point"}
}