{
  "type": "Feature",
  "properties": {
    "addr:full":"Calle de Pio Xii, 5 Arroyo Ojanco Ja\u00e9n 23340",
    "addr:housenumber":"5",
    "addr:postcode":"23340",
    "addr:street":"Calle De Pio Xii;Jae\u0301N",
    "iso:country":"ES",
    "sg:address":"Calle de Pio Xii, 5",
    "sg:city":"Arroyo Ojanco",
    "sg:classifiers":[
        {
            "category":"Taxi",
            "type":"Transportation"
        }
    ],
    "sg:phone":"+34 953 42 04 03",
    "sg:postcode":"23340",
    "sg:province":"Ja\u00e9n",
    "wof:name":"Li\u00f1an Garcia Francisco",
    "wof:placetype":"venue"
},
  "geometry": {"coordinates":[-2.895581007,38.3215484619],"type":"Point"}
}