{
  "type": "Feature",
  "properties": {
    "iso:country":"ES",
    "sg:address":"Francisco Turrell, 21",
    "sg:city":"Cretas",
    "sg:orig_category":"Reposter\u00cdas",
    "sg:phone":"+34 978 85 05 02",
    "sg:postcode":"44623",
    "sg:province":"Teruel",
    "wof:name":"Omella Llerda Jose Manuel",
    "wof:placetype":"venue"
},
  "geometry": {"coordinates":[0.2101220042,40.9278793335],"type":"Point"}
}