{
  "type": "Feature",
  "properties": {
    "addr:full":"Calle de Puerto (el), 5 Buenavista Norte Santa Cruz De Tenerife 38480",
    "addr:housenumber":"5",
    "addr:postcode":"38480",
    "addr:street":"Calle De Puerto El",
    "iso:country":"ES",
    "sg:address":"Calle de Puerto (el), 5",
    "sg:city":"Buenavista Norte",
    "sg:orig_category":"Contenedores (mercanc\u00cdas)",
    "sg:phone":"+34 922 12 73 77",
    "sg:postcode":"38480",
    "sg:province":"Santa Cruz De Tenerife",
    "wof:name":"Rodriguez Perez Jose",
    "wof:placetype":"venue"
},
  "geometry": {"coordinates":[-16.8515052795,28.370475769],"type":"Point"}
}