{
  "type": "Feature",
  "properties": {
    "addr:full":"Calle de Isaac Albeniz, 11 Padul Granada 18640",
    "addr:housenumber":"11",
    "addr:postcode":"18640",
    "addr:street":"Calle De Isaac Albeniz",
    "iso:country":"ES",
    "sg:address":"Calle de Isaac Albeniz, 11",
    "sg:city":"Padul",
    "sg:orig_category":"Promotores Constructores",
    "sg:phone":"+34 958 77 36 60",
    "sg:postcode":"18640",
    "sg:province":"Granada",
    "wof:name":"Propadul S.l.",
    "wof:placetype":"venue"
},
  "geometry": {"coordinates":[-3.6248519421,37.0216331482],"type":"Point"}
}