{
  "type": "Feature",
  "properties": {
    "iso:country":"ES",
    "sg:address":"Calle de Duplex Torre Greco, 52",
    "sg:city":"Dos Hermanas",
    "sg:orig_category":"Laboratorios De Control Sanitario Y Ambiental",
    "sg:phone":"+34 955 66 40 99",
    "sg:postcode":"41700",
    "sg:province":"Sevilla",
    "wof:name":"Alt Quality Projet Consultoria Alimentaria S.l.",
    "wof:placetype":"venue"
},
  "geometry": {"coordinates":[-5.9421758652,37.2855224609],"type":"Point"}
}