{
  "type": "Feature",
  "properties": {
    "iso:country":"ES",
    "sg:address":"Avda Manuel Rivera, 7",
    "sg:city":"Palencia",
    "sg:orig_category":"Administradores De Bienes Y Delegados De Comunidades De Propietarios",
    "sg:phone":"+34 979 72 25 32",
    "sg:postcode":"34002",
    "sg:province":"Palencia",
    "wof:name":"Rodriguez Alonso Maria Isabel",
    "wof:placetype":"venue"
},
  "geometry": {"coordinates":[-4.5274891853,42.0089302063],"type":"Point"}
}