{
  "type": "Feature",
  "properties": {
    "addr:full":"Calle de Munuza, 3 Gijon Asturias 33201",
    "addr:housenumber":"3",
    "addr:postcode":"33201",
    "addr:street":"Calle De Munuza",
    "iso:country":"ES",
    "sg:address":"Calle de Munuza, 3",
    "sg:city":"Gijon",
    "sg:orig_category":"Abogados",
    "sg:phone":"+34 985 34 22 33",
    "sg:postcode":"33201",
    "sg:province":"Asturias",
    "wof:name":"Sanchez Obaya Raquel",
    "wof:placetype":"venue"
},
  "geometry": {"coordinates":[-5.6622681618,43.5422821045],"type":"Point"}
}