{
  "type": "Feature",
  "properties": {
    "iso:country":"ES",
    "sg:address":"Av Salvatella, 122",
    "sg:city":"Barbera Valles",
    "sg:orig_category":"Fabricaci\u00d3n, Distribuci\u00d3n De Discos, V\u00cddeodiscos Y Musicassettes",
    "sg:phone":"+34 937 18 87 27",
    "sg:postcode":"08210",
    "sg:province":"Barcelona",
    "wof:name":"Multimedia Optical Disc S.l.",
    "wof:placetype":"venue"
},
  "geometry": {"coordinates":[2.1543390751,41.5182571411],"type":"Point"}
}