{
  "type": "Feature",
  "properties": {
    "iso:country":"ES",
    "sg:address":"Avda Iglesia, 3",
    "sg:city":"Rozas De Madrid",
    "sg:orig_category":"Alquiler De V\u00cddeo",
    "sg:phone":"+34 916 37 78 60",
    "sg:postcode":"28230",
    "sg:province":"Madrid",
    "wof:name":"Video Club El Jardin C.b.",
    "wof:placetype":"venue"
},
  "geometry": {"coordinates":[-3.8735721111,40.4915428162],"type":"Point"}
}