{
  "type": "Feature",
  "properties": {
    "addr:full":"Casa Del Monte, S/n Cueva Juarros Burgos 09198",
    "addr:housenumber":"s / n",
    "addr:postcode":"09198",
    "iso:country":"ES",
    "sg:address":"Casa Del Monte, S/n",
    "sg:city":"Cueva Juarros",
    "sg:orig_category":"Agricultores, Agricultores",
    "sg:phone":"+34 947 56 07 64",
    "sg:postcode":"09198",
    "sg:province":"Burgos",
    "wof:name":"Herederos De Alejandro Alameda Barbero S.l.",
    "wof:placetype":"venue"
},
  "geometry": {"coordinates":[-3.5121769905,42.2893867493],"type":"Point"}
}