{
  "type": "Feature",
  "properties": {
    "addr:full":"Calle de Marrate, 1 Labastida \u00c1lava 01330",
    "addr:housenumber":"1",
    "addr:postcode":"01330",
    "addr:street":"Calle De Marrate;A\u0301Lava",
    "iso:country":"ES",
    "sg:address":"Calle de Marrate, 1",
    "sg:city":"Labastida",
    "sg:orig_category":"Abogados",
    "sg:phone":"+34 945 33 11 87",
    "sg:postcode":"01330",
    "sg:province":"\u00c1lava",
    "wof:name":"Bajo Fanlo Ramon",
    "wof:placetype":"venue"
},
  "geometry": {"coordinates":[-2.7903842926,42.589630127],"type":"Point"}
}