{
  "type": "Feature",
  "properties": {
    "addr:full":"Calle de Murcia (de), 19 Fuenlabrada Madrid 28945",
    "addr:housenumber":"19",
    "addr:postcode":"28945",
    "addr:street":"Calle De Murcia De",
    "iso:country":"ES",
    "sg:address":"Calle de Murcia (de), 19",
    "sg:city":"Fuenlabrada",
    "sg:orig_category":"Promotores Constructores",
    "sg:phone":"+34 916 06 83 73",
    "sg:postcode":"28945",
    "sg:province":"Madrid",
    "wof:name":"Euro-maim S.l.",
    "wof:placetype":"venue"
},
  "geometry": {"coordinates":[-3.7950890064,40.2909011841],"type":"Point"}
}