{
  "type": "Feature",
  "properties": {
    "iso:country":"ES",
    "sg:address":"Calle de Jose Arcones Gil, 7",
    "sg:city":"Madrid",
    "sg:orig_category":"M\u00c9dicos: Estomatolog\u00cda",
    "sg:phone":"+34 913 77 26 74",
    "sg:postcode":"28017",
    "sg:province":"Madrid",
    "wof:name":"Queipo Miranda Gema Maria",
    "wof:placetype":"venue"
},
  "geometry": {"coordinates":[-3.6352500916,40.4301528931],"type":"Point"}
}