{
  "type": "Feature",
  "properties": {
    "addr:full":"Avda Juan Carlos I, 68 Ibi Alicante 03440",
    "addr:housenumber":"68",
    "addr:postcode":"03440",
    "addr:street":"Avda Juan Carlos I",
    "iso:country":"ES",
    "sg:address":"Avda Juan Carlos I, 68",
    "sg:city":"Ibi",
    "sg:orig_category":"Cajas De Ahorro",
    "sg:phone":"+34 966 55 37 46",
    "sg:postcode":"03440",
    "sg:province":"Alicante",
    "wof:name":"Caja De Ahorros Del Mediterraneo",
    "wof:placetype":"venue"
},
  "geometry": {"coordinates":[-0.5731660128,38.6238479614],"type":"Point"}
}