{
  "type": "Feature",
  "properties": {
    "addr:full":"Ctra Logro\u00d1o (casta\u00d1ares), Km. 0108,0 Casta\u00f1ares Burgos 09199",
    "addr:postcode":"09199",
    "addr:street":"Ctra Logron\u0303O Castan\u0303Ares Km. 0108,0 Castan\u0303Ares",
    "iso:country":"ES",
    "sg:address":"Ctra Logro\u00d1o (casta\u00d1ares), Km. 0108,0",
    "sg:city":"Casta\u00f1ares",
    "sg:orig_category":"Asociaciones, Organismos Culturales Y Socioeducativos",
    "sg:phone":"+34 947 48 66 64",
    "sg:postcode":"09199",
    "sg:province":"Burgos",
    "wof:name":"Sociedad Deportiva Recreativa Club El Soto",
    "wof:placetype":"venue"
},
  "geometry": {"coordinates":[-3.4605019093,42.3377990723],"type":"Point"}
}