{
  "type": "Feature",
  "properties": {
    "addr:full":"Pase San Gregorio, 20 Puertollano Ciudad Real 13500",
    "addr:housenumber":"20",
    "addr:postcode":"13500",
    "addr:street":"San Gregorio",
    "iso:country":"ES",
    "sg:address":"Pase San Gregorio, 20",
    "sg:city":"Puertollano",
    "sg:orig_category":"Peluquer\u00cdas, Peluquer\u00cda Mixta",
    "sg:phone":"+34 926 41 18 66",
    "sg:postcode":"13500",
    "sg:province":"Ciudad Real",
    "wof:name":"Coleto Diaz Conchi",
    "wof:placetype":"venue"
},
  "geometry": {"coordinates":[-4.1048908234,38.6887702942],"type":"Point"}
}