{
  "type": "Feature",
  "properties": {
    "addr:full":"Carrer de Ausias Marc, 1 Terrassa Barcelona 08224",
    "addr:housenumber":"1",
    "addr:postcode":"08224",
    "addr:street":"Carrer De Ausias Marc",
    "iso:country":"ES",
    "sg:address":"Carrer de Ausias Marc, 1",
    "sg:city":"Terrassa",
    "sg:orig_category":"M\u00c9dicos: Otorrinolaringolog\u00cda",
    "sg:phone":"+34 937 88 37 51",
    "sg:postcode":"08224",
    "sg:province":"Barcelona",
    "wof:name":"Rodriguez Barrio Antonio",
    "wof:placetype":"venue"
},
  "geometry": {"coordinates":[2.0050549507,41.567741394],"type":"Point"}
}