{
  "type": "Feature",
  "properties": {
    "iso:country":"ES",
    "sg:address":"Avda Castilla (de), 42",
    "sg:city":"Poligono De San Fernando De Henares",
    "sg:orig_category":"Fabricaci\u00d3n De Transformadores, De M\u00c1quinas Giratorias De Peque\u00d1a Y Media Potencia",
    "sg:phone":"+34 916 77 98 97",
    "sg:postcode":"28830",
    "sg:province":"Madrid",
    "wof:name":"Barranco Blanco Maria Jose",
    "wof:placetype":"venue"
},
  "geometry": {"coordinates":[-3.4922719002,40.4543685913],"type":"Point"}
}