{
  "type": "Feature",
  "properties": {
    "iso:country":"ES",
    "sg:address":"Carr Calvari, 22",
    "sg:city":"Alguaire",
    "sg:orig_category":"Empresarios",
    "sg:phone":"+34 973 75 64 09",
    "sg:postcode":"25125",
    "sg:province":"Lleida",
    "wof:name":"Ojeda Lopez Ramon",
    "wof:placetype":"venue"
},
  "geometry": {"coordinates":[0.5823109746,41.7359390259],"type":"Point"}
}