{
  "type": "Feature",
  "properties": {
    "iso:country":"ES",
    "sg:address":"Avda Ciudad Jardin (la), 10",
    "sg:city":"Sevilla",
    "sg:orig_category":"Papeler\u00cdas, Librer\u00cdas",
    "sg:phone":"+34 954 63 47 43",
    "sg:postcode":"41005",
    "sg:province":"Sevilla",
    "wof:name":"Mateo Jimenez Jose Antonio",
    "wof:placetype":"venue"
},
  "geometry": {"coordinates":[-5.9660592079,37.3806533813],"type":"Point"}
}