{
  "type": "Feature",
  "properties": {
    "addr:full":"Av Constitucio, 16 S. Andreu Barca Barcelona 08740",
    "addr:housenumber":"16",
    "addr:postcode":"08740",
    "addr:street":"Av Constitucio;S. Andreu;Barcelona",
    "iso:country":"ES",
    "sg:address":"Av Constitucio, 16",
    "sg:city":"S. Andreu Barca",
    "sg:orig_category":"Ense\u00d1anza: Profesiones Art\u00cdsticas",
    "sg:phone":"+34 936 82 35 61",
    "sg:postcode":"08740",
    "sg:province":"Barcelona",
    "wof:name":"Foto Estudio Montero S.l.",
    "wof:placetype":"venue"
},
  "geometry": {"coordinates":[1.9674600363,41.4490509033],"type":"Point"}
}