{
  "type": "Feature",
  "properties": {
    "iso:country":"ES",
    "sg:address":"Carr Sant Anastasi, 71",
    "sg:city":"Badalona",
    "sg:orig_category":"Internados & Ense\u00d1anza Privada",
    "sg:phone":"+34 933 84 24 06",
    "sg:postcode":"08911",
    "sg:province":"Barcelona",
    "wof:name":"Escalada S.l.",
    "wof:placetype":"venue"
},
  "geometry": {"coordinates":[2.2465369701,41.4508666992],"type":"Point"}
}