{
  "type": "Feature",
  "properties": {
    "iso:country":"ES",
    "sg:address":"Calle de Colon, 7",
    "sg:city":"Alburquerque",
    "sg:orig_category":"Electricidad: Instaladores",
    "sg:phone":"+34 924 40 00 39",
    "sg:postcode":"06510",
    "sg:province":"Badajoz",
    "wof:name":"Garcia Santos Antonio",
    "wof:placetype":"venue"
},
  "geometry": {"coordinates":[-6.999982357,39.2194480896],"type":"Point"}
}