{
  "type": "Feature",
  "properties": {
    "addr:full":"Calle de Agustin Espinosa Garcia, 3 Santa Cruz De Tenerife Santa Cruz De Tenerife 38007",
    "addr:housenumber":"3",
    "addr:postcode":"38007",
    "addr:street":"Calle De Agustin Espinosa Garcia",
    "iso:country":"ES",
    "sg:address":"Calle de Agustin Espinosa Garcia, 3",
    "sg:city":"Santa Cruz De Tenerife",
    "sg:orig_category":"Inform\u00c1tica: Mantenimiento Y Reparaci\u00d3n De Ordenadores",
    "sg:phone":"+34 922 20 03 72",
    "sg:postcode":"38007",
    "sg:province":"Santa Cruz De Tenerife",
    "wof:name":"Asinteg S.l.",
    "wof:placetype":"venue"
},
  "geometry": {"coordinates":[-16.270690918,28.4666290283],"type":"Point"}
}