{
  "type": "Feature",
  "properties": {
    "iso:country":"ES",
    "sg:address":"Avda Lourdes, 24",
    "sg:city":"Arenas San Pedro",
    "sg:orig_category":"Art\u00cdculos De Madera (fabricaci\u00d3n Y Al Por Mayor)",
    "sg:phone":"+34 920 37 07 65",
    "sg:postcode":"05400",
    "sg:province":"\u00c1vila",
    "wof:name":"Muebles Y Carpinteria La Mira S.l",
    "wof:placetype":"venue"
},
  "geometry": {"coordinates":[-5.0831289291,40.2107810974],"type":"Point"}
}