{
  "type": "Feature",
  "properties": {
    "iso:country":"ES",
    "sg:address":"Pg Mar, 4",
    "sg:city":"Palamos",
    "sg:orig_category":"Bisuter\u00cda, Joyer\u00cda, Relojer\u00cda (al Por Menor)",
    "sg:phone":"+34 972 31 50 12",
    "sg:postcode":"17230",
    "sg:province":"Girona",
    "wof:name":"Deulofeu Hugas Ramon",
    "wof:placetype":"venue"
},
  "geometry": {"coordinates":[3.1262879372,41.8479766846],"type":"Point"}
}