{
  "type": "Feature",
  "properties": {
    "iso:country":"ES",
    "sg:address":"Plaz Carlos Trias Bertran, 4",
    "sg:city":"Madrid",
    "sg:orig_category":"Centros De Coordinaci\u00d3n",
    "sg:phone":"+34 915 56 82 12",
    "sg:postcode":"28020",
    "sg:province":"Madrid",
    "sg:website":"www.cibergestion.net",
    "wof:name":"Cibergestion Hipotecaria S.l.",
    "wof:placetype":"venue"
},
  "geometry": {"coordinates":[-3.6936919689,40.4509353638],"type":"Point"}
}