{
  "type": "Feature",
  "properties": {
    "iso:country":"ES",
    "sg:address":"Calle de Monte, 21",
    "sg:city":"Barcarrota",
    "sg:orig_category":"Cajas De Ahorro",
    "sg:phone":"+34 924 73 70 40",
    "sg:postcode":"06160",
    "sg:province":"Badajoz",
    "sg:website":"www.cajabadajoz.es",
    "wof:name":"Caja De Badajoz",
    "wof:placetype":"venue"
},
  "geometry": {"coordinates":[-6.8500890732,38.5154151917],"type":"Point"}
}