{
  "type": "Feature",
  "properties": {
    "iso:country":"ES",
    "sg:address":"Calle de Antonino Vera, 21",
    "sg:city":"Elda",
    "sg:orig_category":"Grafistas",
    "sg:phone":"+34 965 38 01 08",
    "sg:postcode":"03600",
    "sg:province":"Alicante",
    "wof:name":"Taller De Ingenieria Y Dise\u00f1o De Elda S.l",
    "wof:placetype":"venue"
},
  "geometry": {"coordinates":[-0.792599082,38.4786186218],"type":"Point"}
}