{
  "type": "Feature",
  "properties": {
    "iso:country":"ES",
    "sg:address":"Paseo Arca Del Agua, 1",
    "sg:city":"Baeza",
    "sg:orig_category":"Autob\u00das (explotaci\u00d3n Y Servicios De)",
    "sg:phone":"+34 953 74 04 68",
    "sg:postcode":"23440",
    "sg:province":"Ja\u00e9n",
    "wof:name":"Alsina Graells Sur S.a.",
    "wof:placetype":"venue"
},
  "geometry": {"coordinates":[-3.480134964,37.9483451843],"type":"Point"}
}