{
  "type": "Feature",
  "properties": {
    "iso:country":"ES",
    "sg:address":"Pase Ezequiel Gonzalez, 30",
    "sg:city":"Segovia",
    "sg:orig_category":"Abogados",
    "sg:phone":"+34 921 44 09 21",
    "sg:postcode":"40002",
    "sg:province":"Segovia",
    "wof:name":"Delgado Martinez Agapito",
    "wof:placetype":"venue"
},
  "geometry": {"coordinates":[-4.1194491386,40.9429092407],"type":"Point"}
}