{
  "type": "Feature",
  "properties": {
    "addr:full":"Carr Pare Miquel Cabot, 6 Santa Maria Del Cami Islas Baleares 07320",
    "addr:housenumber":"6",
    "addr:postcode":"07320",
    "addr:street":"Carr Pare Miquel Cabot;Islas",
    "iso:country":"ES",
    "sg:address":"Carr Pare Miquel Cabot, 6",
    "sg:city":"Santa Maria Del Cami",
    "sg:orig_category":"Peluqueros: De Se\u00d1oras",
    "sg:phone":"+34 971 62 03 20",
    "sg:postcode":"07320",
    "sg:province":"Islas Baleares",
    "wof:name":"Caballero Bagur Maria Custodia",
    "wof:placetype":"venue"
},
  "geometry": {"coordinates":[2.7783761024,39.6469650269],"type":"Point"}
}