{
  "type": "Feature",
  "properties": {
    "addr:full":"Calle de Conde Aranda, 17 Zaragoza Zaragoza 50004",
    "addr:housenumber":"17",
    "addr:postcode":"50004",
    "addr:street":"Calle De Conde Aranda",
    "iso:country":"ES",
    "sg:address":"Calle de Conde Aranda, 17",
    "sg:city":"Zaragoza",
    "sg:orig_category":"Molduras, Junquillos, Listones Y Molduras Perforadas",
    "sg:phone":"+34 976 44 57 20",
    "sg:postcode":"50004",
    "sg:province":"Zaragoza",
    "wof:name":"Xu  Jianlan",
    "wof:placetype":"venue"
},
  "geometry": {"coordinates":[-0.8863132,41.6546440125],"type":"Point"}
}