{
  "type": "Feature",
  "properties": {
    "iso:country":"ES",
    "sg:address":"Calle de Comercio, 8",
    "sg:city":"Ribadesella",
    "sg:orig_category":"Ense\u00d1anza: Profesiones Art\u00cdsticas",
    "sg:phone":"+34 985 86 14 28",
    "sg:postcode":"33560",
    "sg:province":"Asturias",
    "wof:name":"Berbes Gago Eugenia Maria",
    "wof:placetype":"venue"
},
  "geometry": {"coordinates":[-5.0577421188,43.4632873535],"type":"Point"}
}