{
  "type": "Feature",
  "properties": {
    "addr:full":"Calle de Progreso, 25 Molina Segura Murcia 30500",
    "addr:housenumber":"25",
    "addr:postcode":"30500",
    "addr:street":"Calle De Progreso",
    "iso:country":"ES",
    "sg:address":"Calle de Progreso, 25",
    "sg:city":"Molina Segura",
    "sg:orig_category":"Vidrio, Fabricaci\u00d3n Y Comercio",
    "sg:phone":"+34 968 64 10 73",
    "sg:postcode":"30500",
    "sg:province":"Murcia",
    "sg:website":"www.bavidros.com",
    "wof:name":"Ba-fabrica De Envases De Vidrio Barbosa",
    "wof:placetype":"venue"
},
  "geometry": {"coordinates":[-1.2508490086,38.0802154541],"type":"Point"}
}