{
  "type": "Feature",
  "properties": {
    "iso:country":"ES",
    "sg:address":"Calle de Colon, 11",
    "sg:city":"Tarifa",
    "sg:orig_category":"Ropa Para Ni\u00d1os (al Por Menor)",
    "sg:phone":"+34 956 62 73 00",
    "sg:postcode":"11380",
    "sg:province":"C\u00e1diz",
    "wof:name":"Tio Gilito Ropa Para Ni\u00f1os S.l.u.",
    "wof:placetype":"venue"
},
  "geometry": {"coordinates":[-5.6047821045,36.0137023926],"type":"Point"}
}