{
  "type": "Feature",
  "properties": {
    "addr:full":"Bo. La Fuente, S/n Puentenansa Cantabria 39554",
    "addr:housenumber":"s",
    "addr:postcode":"39554",
    "addr:street":"Bo. La Fuente;/ N",
    "iso:country":"ES",
    "sg:address":"Bo. La Fuente, S/n",
    "sg:city":"Puentenansa",
    "sg:orig_category":"Distribuci\u00d3n De Petr\u00d3leo Y Derivados",
    "sg:phone":"+34 942 72 81 79",
    "sg:postcode":"39554",
    "sg:province":"Cantabria",
    "wof:name":"Cosio Fernandez Pedro",
    "wof:placetype":"venue"
},
  "geometry": {"coordinates":[-4.4067897797,43.2545547485],"type":"Point"}
}