{
  "type": "Feature",
  "properties": {
    "iso:country":"ES",
    "sg:address":"Otaola Hiribidea, 23",
    "sg:city":"Eibar",
    "sg:orig_category":"Rectificaci\u00d3n, Mecanizado, Fresado",
    "sg:phone":"+34 943 20 13 90",
    "sg:postcode":"20600",
    "sg:province":"Guip\u00f9zcoa",
    "sg:website":"www.alzuca.com",
    "wof:name":"Industrias Alzuca S. A.",
    "wof:placetype":"venue"
},
  "geometry": {"coordinates":[-2.4864389896,43.1802864075],"type":"Point"}
}