{
  "type": "Feature",
  "properties": {
    "addr:full":"Calle de Carretera, S/n Oliete Teruel 44548",
    "addr:postcode":"44548",
    "addr:street":"Calle De Carretera S / N",
    "iso:country":"ES",
    "sg:address":"Calle de Carretera, S/n",
    "sg:city":"Oliete",
    "sg:orig_category":"Empresas De Carpinter\u00cda",
    "sg:phone":"+34 978 81 84 76",
    "sg:postcode":"44548",
    "sg:province":"Teruel",
    "wof:name":"Moliner Sanchez Jose Luis",
    "wof:placetype":"venue"
},
  "geometry": {"coordinates":[-0.5971220732,41.0311851501],"type":"Point"}
}