{
  "type": "Feature",
  "properties": {
    "iso:country":"ES",
    "sg:address":"Calle de Oriente, 9",
    "sg:city":"Duruelo Sierra",
    "sg:orig_category":"Peluquer\u00cdas, Peluquer\u00cda Mixta",
    "sg:phone":"+34 975 37 14 07",
    "sg:postcode":"42158",
    "sg:province":"Soria",
    "wof:name":"Lafuente Izquierdo Elena",
    "wof:placetype":"venue"
},
  "geometry": {"coordinates":[-2.9321072102,41.9537773132],"type":"Point"}
}