{
  "type": "Feature",
  "properties": {
    "addr:full":"Av Corts Catalanes, 547 S. Adria Besos Barcelona 08930",
    "addr:housenumber":"547",
    "addr:postcode":"08930",
    "addr:street":"Av Corts Catalanes;S. Adria Besos Barcelona",
    "iso:country":"ES",
    "sg:address":"Av Corts Catalanes, 547",
    "sg:city":"S. Adria Besos",
    "sg:orig_category":"Artes Gr\u00c1ficas, Artes Pl\u00c1sticas (curso)",
    "sg:phone":"+34 933 81 88 81",
    "sg:postcode":"08930",
    "sg:province":"Barcelona",
    "wof:name":"Armario Miranda Jose Luis",
    "wof:placetype":"venue"
},
  "geometry": {"coordinates":[2.212600708,41.423034668],"type":"Point"}
}