{
  "type": "Feature",
  "properties": {
    "iso:country":"ES",
    "sg:address":"Ctra Sant Hipolit, S/n",
    "sg:city":"Vic",
    "sg:orig_category":"Suministros Y Materiales Industriales",
    "sg:phone":"+34 938 83 14 64",
    "sg:postcode":"08500",
    "sg:province":"Barcelona",
    "wof:name":"Comercial Nono S.a.",
    "wof:placetype":"venue"
},
  "geometry": {"coordinates":[2.2526600361,41.946105957],"type":"Point"}
}