{
  "type": "Feature",
  "properties": {
    "addr:full":"Calle de Pintor Oliva, 1 Palencia Palencia 34004",
    "addr:housenumber":"1",
    "addr:postcode":"34004",
    "addr:street":"Calle De Pintor Oliva",
    "iso:country":"ES",
    "sg:address":"Calle de Pintor Oliva, 1",
    "sg:city":"Palencia",
    "sg:orig_category":"Asociaciones Humanitarias, De Cooperaci\u00d3n, De Acci\u00d3n Social",
    "sg:phone":"+34 979 72 84 71",
    "sg:postcode":"34004",
    "sg:province":"Palencia",
    "wof:name":"Asociacion Reto",
    "wof:placetype":"venue"
},
  "geometry": {"coordinates":[-4.5260558128,42.0015792847],"type":"Point"}
}