{
  "type": "Feature",
  "properties": {
    "iso:country":"ES",
    "sg:address":"Carr Gabriel Miro, S/n",
    "sg:city":"Gandia",
    "sg:orig_category":"Fabricaci\u00d3n, Distribuci\u00d3n De Discos, V\u00cddeodiscos Y Musicassettes",
    "sg:phone":"+34 962 86 73 32",
    "sg:postcode":"46700",
    "sg:province":"Valencia",
    "wof:name":"S.ba\u00d1uls S.l.",
    "wof:placetype":"venue"
},
  "geometry": {"coordinates":[-0.1913339943,38.960735321],"type":"Point"}
}