{
  "type": "Feature",
  "properties": {
    "addr:full":"Calle de Rio, 23 Priego Cordoba C\u00f3rdoba 14800",
    "addr:housenumber":"23",
    "addr:postcode":"14800",
    "addr:street":"Calle De Rio;Cordoba Co\u0301Rdoba",
    "iso:country":"ES",
    "sg:address":"Calle de Rio, 23",
    "sg:city":"Priego Cordoba",
    "sg:orig_category":"Centros De Coordinaci\u00d3n",
    "sg:phone":"+34 957 54 08 15",
    "sg:postcode":"14800",
    "sg:province":"C\u00f3rdoba",
    "wof:name":"Asesoria Rosales Priego S.l.",
    "wof:placetype":"venue"
},
  "geometry": {"coordinates":[-4.194770813,37.437461853],"type":"Point"}
}