{
  "type": "Feature",
  "properties": {
    "iso:country":"ES",
    "sg:address":"Cnel. G. Mateo, 6",
    "sg:city":"Vega Tirados",
    "sg:orig_category":"Cerrajer\u00cda, Ferrallista",
    "sg:phone":"+34 923 32 04 76",
    "sg:postcode":"37170",
    "sg:province":"Salamanca",
    "wof:name":"Martin Hernandez Eugenio",
    "wof:placetype":"venue"
},
  "geometry": {"coordinates":[-5.8602151871,41.0336036682],"type":"Point"}
}