{
  "type": "Feature",
  "properties": {
    "iso:country":"ES",
    "sg:address":"Cam. Pto. Ronda, S/n",
    "sg:city":"Benaojan",
    "sg:orig_category":"Transportes Por Carretera: Lotes Completos, Mercanc\u00cdas Diversas",
    "sg:phone":"+34 952 16 73 62",
    "sg:postcode":"29370",
    "sg:province":"M\u00e1laga",
    "wof:name":"Central Diana S.l.",
    "wof:placetype":"venue"
},
  "geometry": {"coordinates":[-5.2538580894,36.7196846008],"type":"Point"}
}