{
  "type": "Feature",
  "properties": {
    "addr:full":"Av Illice, 21 Torrellano Alicante 03320",
    "addr:housenumber":"21",
    "addr:postcode":"03320",
    "addr:street":"Av Illice",
    "iso:country":"ES",
    "sg:address":"Av Illice, 21",
    "sg:city":"Torrellano",
    "sg:orig_category":"Comercio De Piezas De Recambio Y De Accesorios De Veh\u00cdculos, Veh\u00cdculos Industriales",
    "sg:phone":"+34 965 68 33 91",
    "sg:postcode":"03320",
    "sg:province":"Alicante",
    "wof:name":"Repuestos Torrellano S.l.",
    "wof:placetype":"venue"
},
  "geometry": {"coordinates":[-0.585909009,38.2940063477],"type":"Point"}
}