{
  "type": "Feature",
  "properties": {
    "iso:country":"ES",
    "sg:address":"Av Vidreres, 113",
    "sg:city":"Lloret Mar",
    "sg:orig_category":"Panader\u00cdas, Panader\u00cdas",
    "sg:phone":"+34 972 36 86 94",
    "sg:postcode":"17310",
    "sg:province":"Girona",
    "wof:name":"Pastisseria Paris S.l.",
    "wof:placetype":"venue"
},
  "geometry": {"coordinates":[2.8345599174,41.7093315125],"type":"Point"}
}