{
  "type": "Feature",
  "properties": {
    "addr:full":"Avda Andalucia, 58 Jaen Ja\u00e9n 23006",
    "addr:housenumber":"58;jae\u0301n",
    "addr:postcode":"23006",
    "addr:street":"Avda Andalucia",
    "iso:country":"ES",
    "sg:address":"Avda Andalucia, 58",
    "sg:city":"Jaen",
    "sg:orig_category":"Guarda",
    "sg:phone":"+34 953 22 44 05",
    "sg:postcode":"23006",
    "sg:province":"Ja\u00e9n",
    "wof:name":"Amaro Almazan Sebastian",
    "wof:placetype":"venue"
},
  "geometry": {"coordinates":[-3.8025085926,37.7781791687],"type":"Point"}
}