{
  "type": "Feature",
  "properties": {
    "iso:country":"ES",
    "sg:address":"Avda Rambleta, 20",
    "sg:city":"Catarroja",
    "sg:orig_category":"Internados & Ense\u00d1anza Privada",
    "sg:phone":"+34 961 27 43 45",
    "sg:postcode":"46470",
    "sg:province":"Valencia",
    "wof:name":"Colegio Larrode",
    "wof:placetype":"venue"
},
  "geometry": {"coordinates":[-0.4062240124,39.4038734436],"type":"Point"}
}