{
  "type": "Feature",
  "properties": {
    "addr:full":"Calle de Santo Domingo, 24 Jerez De La Frontera C\u00e1diz 11402",
    "addr:housenumber":"24",
    "addr:postcode":"11402",
    "addr:street":"Calle De Santo Domingo",
    "iso:country":"ES",
    "sg:address":"Calle de Santo Domingo, 24",
    "sg:city":"Jerez De La Frontera",
    "sg:orig_category":"Agentes, Concesionarios Y Sucursales De Veh\u00cdculos",
    "sg:phone":"+34 956 31 01 81",
    "sg:postcode":"11402",
    "sg:province":"C\u00e1diz",
    "sg:website":"www.rentmotor2000.com",
    "wof:name":"Rent Motor 2000 S.l.",
    "wof:placetype":"venue"
},
  "geometry": {"coordinates":[-6.1295590401,36.6930389404],"type":"Point"}
}