{
  "type": "Feature",
  "properties": {
    "iso:country":"ES",
    "sg:address":"Glorieta De La Cruz, 14",
    "sg:city":"Huelma",
    "sg:orig_category":"Delegados, Agentes De Tr\u00c1nsito, Auxiliares De Transporte Internacional",
    "sg:phone":"+34 953 39 10 07",
    "sg:postcode":"23560",
    "sg:province":"Ja\u00e9n",
    "wof:name":"Garcia Galiano Andres",
    "wof:placetype":"venue"
},
  "geometry": {"coordinates":[-3.4535284042,37.6487503052],"type":"Point"}
}