{
  "type": "Feature",
  "properties": {
    "iso:country":"ES",
    "sg:address":"Calle de Antonio Hernandez Gil, 22",
    "sg:city":"Navalvillar Pela",
    "sg:orig_category":"Empresas De Carpinter\u00cda De Madera",
    "sg:phone":"+34 924 86 05 27",
    "sg:postcode":"06760",
    "sg:province":"Badajoz",
    "wof:name":"Duran Corvillo Vicente",
    "wof:placetype":"venue"
},
  "geometry": {"coordinates":[-5.4692106247,39.0878181458],"type":"Point"}
}