{
  "type": "Feature",
  "properties": {
    "iso:country":"ES",
    "sg:address":"Calle de Argentina, 10",
    "sg:city":"Caceres",
    "sg:orig_category":"Panader\u00cdas, Panader\u00cdas",
    "sg:phone":"+34 927 24 53 64",
    "sg:postcode":"10001",
    "sg:province":"C\u00e1ceres",
    "wof:name":"Muriel Macias Alfonso",
    "wof:placetype":"venue"
},
  "geometry": {"coordinates":[-6.3814101219,39.4674530029],"type":"Point"}
}