{
  "type": "Feature",
  "properties": {
    "addr:full":"Calle de Constantino, 3 Ejido Almer\u00eda 04700",
    "addr:housenumber":"3",
    "addr:postcode":"04700",
    "addr:street":"Calle De Constantino;Almeri\u0301A",
    "iso:country":"ES",
    "sg:address":"Calle de Constantino, 3",
    "sg:city":"Ejido",
    "sg:orig_category":"Ingeniero",
    "sg:phone":"+34 950 48 25 78",
    "sg:postcode":"04700",
    "sg:province":"Almer\u00eda",
    "wof:name":"Francisco Davila Pedro Amalio",
    "wof:placetype":"venue"
},
  "geometry": {"coordinates":[-2.8115370274,36.7736816406],"type":"Point"}
}