{
  "type": "Feature",
  "properties": {
    "iso:country":"ES",
    "sg:address":"Carrer de Santiago Rusi\u00d1ol, S/n",
    "sg:city":"Navarcles",
    "sg:orig_category":"Costureras",
    "sg:phone":"+34 938 31 03 59",
    "sg:postcode":"08270",
    "sg:province":"Barcelona",
    "wof:name":"Estilles Altimiras Maria Gemma",
    "wof:placetype":"venue"
},
  "geometry": {"coordinates":[1.8991700411,41.7522544861],"type":"Point"}
}