{
  "type": "Feature",
  "properties": {
    "addr:full":"Pla\u00c7 Nova, 11 Ciutadella Menorca Islas Baleares 07760",
    "addr:housenumber":"11",
    "addr:postcode":"07760",
    "iso:country":"ES",
    "sg:address":"Pla\u00c7 Nova, 11",
    "sg:city":"Ciutadella Menorca",
    "sg:orig_category":"Cajas De Ahorro",
    "sg:phone":"+34 971 38 11 62",
    "sg:postcode":"07760",
    "sg:province":"Islas Baleares",
    "sg:website":"www.sanostra.es",
    "wof:name":"Caja De Ahorros Y Monte De Piedad De Las Baleares",
    "wof:placetype":"venue"
},
  "geometry": {"coordinates":[3.8416149616,40.0027542114],"type":"Point"}
}