{
  "type": "Feature",
  "properties": {
    "addr:full":"Carrer de Santa Magdalena, 23 Ulldemolins Tarragona 43363",
    "addr:housenumber":"23",
    "addr:postcode":"43363",
    "addr:street":"Carrer De Santa Magdalena",
    "iso:country":"ES",
    "sg:address":"Carrer de Santa Magdalena, 23",
    "sg:city":"Ulldemolins",
    "sg:orig_category":"Poller\u00cda Y Caza (al Por Menor)",
    "sg:phone":"+34 977 56 16 72",
    "sg:postcode":"43363",
    "sg:province":"Tarragona",
    "wof:name":"Besso Borrull Javier",
    "wof:placetype":"venue"
},
  "geometry": {"coordinates":[0.8758339882,41.3203315735],"type":"Point"}
}