{
  "type": "Feature",
  "properties": {
    "addr:full":"Calle de Purisima, 11 Velez-rubio Almer\u00eda 04820",
    "addr:housenumber":"11",
    "addr:postcode":"04820",
    "addr:street":"Calle De Purisima;Almeri\u0301A",
    "iso:country":"ES",
    "sg:address":"Calle de Purisima, 11",
    "sg:city":"Velez-rubio",
    "sg:orig_category":"Cajas De Ahorro",
    "sg:phone":"+34 950 41 06 92",
    "sg:postcode":"04820",
    "sg:province":"Almer\u00eda",
    "wof:name":"Caixa D'estalvis I Pensions De Barcelona",
    "wof:placetype":"venue"
},
  "geometry": {"coordinates":[-2.0731420517,37.6480789185],"type":"Point"}
}