{
  "type": "Feature",
  "properties": {
    "iso:country":"ES",
    "sg:address":"Calle de Algarve, 1",
    "sg:city":"Jerez De La Frontera",
    "sg:orig_category":"Inmobiliaria (agencias)",
    "sg:phone":"+34 956 34 87 42",
    "sg:postcode":"11403",
    "sg:province":"C\u00e1diz",
    "wof:name":"Huertas Gallego Maria Del Carmen",
    "wof:placetype":"venue"
},
  "geometry": {"coordinates":[-6.1368870735,36.682723999],"type":"Point"}
}