{
  "type": "Feature",
  "properties": {
    "iso:country":"ES",
    "sg:address":"Calle de Cano, 8",
    "sg:city":"Palmas De Gran Canaria",
    "sg:orig_category":"Fabricaci\u00d3n, Venta De Cuadros, Accesorios Para Enmarcar",
    "sg:phone":"+34 928 38 34 94",
    "sg:postcode":"35002",
    "sg:province":"Las Palmas",
    "wof:name":"Sayme Arte S.a.",
    "wof:placetype":"venue"
},
  "geometry": {"coordinates":[-15.4162902832,28.104101181],"type":"Point"}
}