{
  "type": "Feature",
  "properties": {
    "addr:full":"Avda Conde De Vallellano, 21 Cordoba C\u00f3rdoba 14004",
    "addr:housenumber":"21",
    "addr:postcode":"14004",
    "addr:street":"Avda Conde De Vallellano;Co\u0301Rdoba",
    "iso:country":"ES",
    "sg:address":"Avda Conde De Vallellano, 21",
    "sg:city":"Cordoba",
    "sg:orig_category":"Mec\u00c1nico Del Autom\u00d3vil",
    "sg:phone":"+34 957 29 08 61",
    "sg:postcode":"14004",
    "sg:province":"C\u00f3rdoba",
    "wof:name":"Perez Velasco Jose",
    "wof:placetype":"venue"
},
  "geometry": {"coordinates":[-4.7854280472,37.8760299683],"type":"Point"}
}