{
  "type": "Feature",
  "properties": {
    "iso:country":"ES",
    "sg:address":"Rua Cartagena, 1",
    "sg:city":"Silleda",
    "sg:orig_category":"Inmobiliaria (agencias)",
    "sg:phone":"+34 986 58 14 53",
    "sg:postcode":"36540",
    "sg:province":"Pontevedra",
    "wof:name":"Asesoria Antonio S.c.",
    "wof:placetype":"venue"
},
  "geometry": {"coordinates":[-8.2464809418,42.6997718811],"type":"Point"}
}