{
  "type": "Feature",
  "properties": {
    "iso:country":"ES",
    "sg:address":"Calle de Acibelas, S/n",
    "sg:city":"Valladolid",
    "sg:orig_category":"Muebles, Minoristas",
    "sg:phone":"+34 983 39 69 41",
    "sg:postcode":"47004",
    "sg:province":"Valladolid",
    "wof:name":"Fiocco Espa\u00d1ola S.l.",
    "wof:placetype":"venue"
},
  "geometry": {"coordinates":[-4.7203607559,41.6470413208],"type":"Point"}
}