{
  "type": "Feature",
  "properties": {
    "addr:full":"Calle de Parque De Los Angeles, 4 Loja Granada 18300",
    "addr:housenumber":"4 loja",
    "addr:postcode":"18300",
    "addr:street":"Calle De Parque De Los Angeles",
    "iso:country":"ES",
    "sg:address":"Calle de Parque De Los Angeles, 4",
    "sg:city":"Loja",
    "sg:orig_category":"Ropa Para Se\u00d1oras (al Por Menor)",
    "sg:phone":"+34 958 32 09 43",
    "sg:postcode":"18300",
    "sg:province":"Granada",
    "wof:name":"Jimenez Cruces Antonio",
    "wof:placetype":"venue"
},
  "geometry": {"coordinates":[-4.145676136,37.1631889343],"type":"Point"}
}