{
  "type": "Feature",
  "properties": {
    "addr:full":"Calle de Chancilleres, 1 Soria Soria 42001",
    "addr:housenumber":"1",
    "addr:postcode":"42001",
    "addr:street":"Calle De Chancilleres",
    "iso:country":"ES",
    "sg:address":"Calle de Chancilleres, 1",
    "sg:city":"Soria",
    "sg:orig_category":"Promotores Constructores",
    "sg:phone":"+34 975 22 28 17",
    "sg:postcode":"42001",
    "sg:province":"Soria",
    "wof:name":"Construcciones Garsan Y Cristina S.l.",
    "wof:placetype":"venue"
},
  "geometry": {"coordinates":[-2.4737064838,41.7682380676],"type":"Point"}
}