{
  "type": "Feature",
  "properties": {
    "addr:full":"Barr Riancho, S/n Riancho Cantabria 39870",
    "addr:postcode":"39870",
    "addr:street":"Riancho S / N",
    "iso:country":"ES",
    "sg:address":"Barr Riancho, S/n",
    "sg:city":"Riancho",
    "sg:orig_category":"Bares, Piano",
    "sg:phone":"+34 942 67 03 97",
    "sg:postcode":"39870",
    "sg:province":"Cantabria",
    "wof:name":"Ason-esmeralda, Sl",
    "wof:placetype":"venue"
},
  "geometry": {"coordinates":[-3.4328885078,43.2681617737],"type":"Point"}
}