{
  "type": "Feature",
  "properties": {
    "iso:country":"ES",
    "sg:address":"Calle de Toledo, 41",
    "sg:city":"Madrid",
    "sg:orig_category":"Cr\u00cda De Animales",
    "sg:phone":"+34 913 65 45 34",
    "sg:postcode":"28005",
    "sg:province":"Madrid",
    "wof:name":"Juan Manuel Gallardo S.l.",
    "wof:placetype":"venue"
},
  "geometry": {"coordinates":[-3.7076046467,40.4125595093],"type":"Point"}
}