{
  "type": "Feature",
  "properties": {
    "addr:full":"Calle de Juan Carlos I, S/n Cartama M\u00e1laga 29570",
    "addr:housenumber":"s",
    "addr:postcode":"29570",
    "addr:street":"Calle De Juan Carlos I;/ N;Ma\u0301Laga",
    "iso:country":"ES",
    "sg:address":"Calle de Juan Carlos I, S/n",
    "sg:city":"Cartama",
    "sg:orig_category":"Fabricaci\u00d3n, Importaci\u00d3n, Venta De Material De Telefon\u00cda, Peritelefon\u00cda",
    "sg:phone":"+34 952 42 85 53",
    "sg:postcode":"29570",
    "sg:province":"M\u00e1laga",
    "wof:name":"Telefonica Data Espa\u00f1a S.a.",
    "wof:placetype":"venue"
},
  "geometry": {"coordinates":[-4.6329622269,36.7101325989],"type":"Point"}
}