{
  "type": "Feature",
  "properties": {
    "iso:country":"ES",
    "sg:address":"Calle de Cuenca, 2",
    "sg:city":"Azuqueca Henares",
    "sg:orig_category":"Panader\u00cdas, Panader\u00cdas",
    "sg:phone":"+34 949 26 21 79",
    "sg:postcode":"19200",
    "sg:province":"Guadalajara",
    "wof:name":"Establecimientos Hernando S.a.",
    "wof:placetype":"venue"
},
  "geometry": {"coordinates":[-3.2642393112,40.5640296936],"type":"Point"}
}