{
  "type": "Feature",
  "properties": {
    "addr:full":"Plaz Infantas (las), 19 Albolote Granada 18220",
    "addr:housenumber":"19",
    "addr:postcode":"18220",
    "addr:street":"Plaz Infantas Las",
    "iso:country":"ES",
    "sg:address":"Plaz Infantas (las), 19",
    "sg:city":"Albolote",
    "sg:orig_category":"Farmacias",
    "sg:phone":"+34 958 46 87 32",
    "sg:postcode":"18220",
    "sg:province":"Granada",
    "wof:name":"Valero Jerez Francisco",
    "wof:placetype":"venue"
},
  "geometry": {"coordinates":[-3.6585440636,37.2332839966],"type":"Point"}
}