{
  "type": "Feature",
  "properties": {
    "addr:full":"Masia Pilar, S/n Peralejos Teruel 44162",
    "addr:housenumber":"s / n",
    "addr:postcode":"44162",
    "iso:country":"ES",
    "sg:address":"Masia Pilar, S/n",
    "sg:city":"Peralejos",
    "sg:orig_category":"Patatas (al Por Mayor)",
    "sg:phone":"+34 978 66 01 25",
    "sg:postcode":"44162",
    "sg:province":"Teruel",
    "wof:name":"Yago Gimeno Tomas",
    "wof:placetype":"venue"
},
  "geometry": {"coordinates":[-1.0331995487,40.4845581055],"type":"Point"}
}