{
  "type": "Feature",
  "properties": {
    "iso:country":"ES",
    "sg:address":"Mayor, 47",
    "sg:city":"Gares",
    "sg:orig_category":"Carnicer\u00cdas, Carnicer\u00cdas",
    "sg:phone":"+34 948 34 00 83",
    "sg:postcode":"31100",
    "sg:province":"Navarra",
    "wof:name":"Martinez Perez Jose",
    "wof:placetype":"venue"
},
  "geometry": {"coordinates":[-1.8158400059,42.6719398499],"type":"Point"}
}