{
  "type": "Feature",
  "properties": {
    "iso:country":"ES",
    "sg:address":"Calle de Real, 92",
    "sg:city":"Matanza De Acentejo",
    "sg:orig_category":"Empresas De Carpinter\u00cda De Madera",
    "sg:phone":"+34 922 57 70 21",
    "sg:postcode":"38370",
    "sg:province":"Santa Cruz De Tenerife",
    "wof:name":"Carpinteria Salvador S.l.",
    "wof:placetype":"venue"
},
  "geometry": {"coordinates":[-16.4489116669,28.4523296356],"type":"Point"}
}