{
  "type": "Feature",
  "properties": {
    "iso:country":"ES",
    "sg:address":"Av. Bayona, 38",
    "sg:city":"Iru\u00f1a",
    "sg:orig_category":"Traductores",
    "sg:phone":"+34 948 17 15 44",
    "sg:postcode":"31011",
    "sg:province":"Navarra",
    "wof:name":"Itzuliz Euskal Zerbitzuak S.l.",
    "wof:placetype":"venue"
},
  "geometry": {"coordinates":[-1.6611969471,42.813205719],"type":"Point"}
}