{
  "type": "Feature",
  "properties": {
    "iso:country":"ES",
    "sg:address":"Calle de Galicia, 29",
    "sg:city":"Fuenlabrada",
    "sg:orig_category":"Cl\u00cdnicas M\u00c9dicas",
    "sg:phone":"+34 916 08 07 11",
    "sg:postcode":"28942",
    "sg:province":"Madrid",
    "wof:name":"Plus Dental Integral S.l.",
    "wof:placetype":"venue"
},
  "geometry": {"coordinates":[-3.8103330135,40.3000259399],"type":"Point"}
}