{
  "type": "Feature",
  "properties": {
    "iso:country":"ES",
    "sg:address":"Ctr. Madrid-soria, Km. 0103,0",
    "sg:city":"Jadraque",
    "sg:orig_category":"Producci\u00d3n De Abonos Y De Fertilizantes",
    "sg:phone":"+34 949 89 01 46",
    "sg:postcode":"19240",
    "sg:province":"Guadalajara",
    "wof:name":"Fertilizantes Cesareo Sanz S.l.",
    "wof:placetype":"venue"
},
  "geometry": {"coordinates":[-2.9276280403,40.9257965088],"type":"Point"}
}