{
  "type": "Feature",
  "properties": {
    "iso:country":"ES",
    "sg:address":"Ctra. Palma-andratx, Km. 0016,0",
    "sg:city":"Sta. Pon\u00e7a",
    "sg:orig_category":"Explotaci\u00d3n De Canteras",
    "sg:phone":"+34 971 69 01 14",
    "sg:postcode":"07180",
    "sg:province":"Islas Baleares",
    "wof:name":"Son Bugadellas S.a",
    "wof:placetype":"venue"
},
  "geometry": {"coordinates":[2.4985899925,39.5253143311],"type":"Point"}
}