{
  "type": "Feature",
  "properties": {
    "addr:full":"Calle de Gran Via, 39 Hellin Albacete 02400",
    "addr:housenumber":"39",
    "addr:postcode":"02400",
    "addr:street":"Calle De Gran Via",
    "iso:country":"ES",
    "sg:address":"Calle de Gran Via, 39",
    "sg:city":"Hellin",
    "sg:orig_category":"Ropa Para Ni\u00d1os (al Por Menor)",
    "sg:phone":"+34 967 17 61 99",
    "sg:postcode":"02400",
    "sg:province":"Albacete",
    "wof:name":"Acento Moda S.l.",
    "wof:placetype":"venue"
},
  "geometry": {"coordinates":[-1.6967365742,38.5083389282],"type":"Point"}
}