{
  "type": "Feature",
  "properties": {
    "iso:country":"ES",
    "sg:address":"Carrer de Arquitecte Vives, 5",
    "sg:city":"Valls",
    "sg:orig_category":"Mercer\u00cda, Lencer\u00cda (al Por Menor)",
    "sg:phone":"+34 977 60 81 18",
    "sg:postcode":"43800",
    "sg:province":"Tarragona",
    "wof:name":"Rosa Egea Francisca",
    "wof:placetype":"venue"
},
  "geometry": {"coordinates":[1.2588889599,41.2954978943],"type":"Point"}
}