{
  "type": "Feature",
  "properties": {
    "iso:country":"ES",
    "sg:address":"Calle de Larga, S/n",
    "sg:city":"Jerez De La Frontera",
    "sg:orig_category":"Agencias De Viajes",
    "sg:phone":"+34 956 34 39 12",
    "sg:postcode":"11402",
    "sg:province":"C\u00e1diz",
    "wof:name":"Sherry Tours S.l.",
    "wof:placetype":"venue"
},
  "geometry": {"coordinates":[-6.1362338066,36.6852302551],"type":"Point"}
}