{
  "type": "Feature",
  "properties": {
    "addr:full":"Pg Riera, 54 Rubi Barcelona 08191",
    "addr:housenumber":"54",
    "addr:postcode":"08191",
    "addr:street":"Riera",
    "iso:country":"ES",
    "sg:address":"Pg Riera, 54",
    "sg:city":"Rubi",
    "sg:orig_category":"Molduras, Junquillos, Listones Y Molduras Perforadas",
    "sg:phone":"+34 936 97 06 39",
    "sg:postcode":"08191",
    "sg:province":"Barcelona",
    "wof:name":"Cortina Sabata Lorenzo",
    "wof:placetype":"venue"
},
  "geometry": {"coordinates":[2.0288469791,41.4908599854],"type":"Point"}
}