{
  "type": "Feature",
  "properties": {
    "iso:country":"ES",
    "sg:address":"Carretera El Paso, S/n",
    "sg:city":"El Paso",
    "sg:orig_category":"Ense\u00d1anza, Formaci\u00d3n Profesional: Aprendizaje",
    "sg:phone":"+34 922 49 73 44",
    "sg:postcode":"38750",
    "sg:province":"Santa Cruz De Tenerife",
    "wof:name":"Cabildo Insular De La Palma",
    "wof:placetype":"venue"
},
  "geometry": {"coordinates":[-17.8813228607,28.6505889893],"type":"Point"}
}