{
  "type": "Feature",
  "properties": {
    "iso:country":"ES",
    "sg:address":"Av Alcalde Barnils, 72",
    "sg:city":"S. Cugat Valles",
    "sg:orig_category":"\u00d3ptica: Instrumentos (fabricaci\u00d3n)",
    "sg:phone":"+34 932 98 26 00",
    "sg:postcode":"08...",
    "sg:province":"Barcelona",
    "sg:website":"www.indo.es",
    "wof:name":"Indoptica S.a.",
    "wof:placetype":"venue"
},
  "geometry": {"coordinates":[2.0775370598,41.48828125],"type":"Point"}
}