{
  "type": "Feature",
  "properties": {
    "addr:full":"Calle de Horno, 10 Huetor-santillan Granada 18183",
    "addr:housenumber":"10",
    "addr:postcode":"18183",
    "addr:street":"Calle De Horno",
    "iso:country":"ES",
    "sg:address":"Calle de Horno, 10",
    "sg:city":"Huetor-santillan",
    "sg:orig_category":"Empresas De Carpinter\u00cda De Madera",
    "sg:phone":"+34 958 54 60 18",
    "sg:postcode":"18183",
    "sg:province":"Granada",
    "wof:name":"Hita Haro Manuel",
    "wof:placetype":"venue"
},
  "geometry": {"coordinates":[-3.5111720562,37.2237510681],"type":"Point"}
}