{
  "type": "Feature",
  "properties": {
    "iso:country":"ES",
    "sg:address":"Calle de Venecia, 2",
    "sg:city":"Mayorga",
    "sg:orig_category":"Distribuci\u00d3n De Petr\u00d3leo Y Derivados",
    "sg:phone":"+34 983 75 16 19",
    "sg:postcode":"47680",
    "sg:province":"Valladolid",
    "wof:name":"Pescados Llorente S. L.",
    "wof:placetype":"venue"
},
  "geometry": {"coordinates":[-5.2661151886,42.1646347046],"type":"Point"}
}