{
  "type": "Feature",
  "properties": {
    "addr:full":"Calle de Sabino Arana, 5 Basozabal Vizcaya 48150",
    "addr:housenumber":"5",
    "addr:postcode":"48150",
    "addr:street":"Calle De Sabino Arana",
    "iso:country":"ES",
    "sg:address":"Calle de Sabino Arana, 5",
    "sg:city":"Basozabal",
    "sg:classifiers":[
        {
            "category":"Taxi",
            "type":"Transportation"
        }
    ],
    "sg:phone":"+34 944 53 16 99",
    "sg:postcode":"48150",
    "sg:province":"Vizcaya",
    "wof:name":"Fernandez Fernandez Benito",
    "wof:placetype":"venue"
},
  "geometry": {"coordinates":[-2.9258821011,43.2996902466],"type":"Point"}
}