{
  "type": "Feature",
  "properties": {
    "iso:country":"ES",
    "sg:address":"Cm\u00d1o Carrazons, 3",
    "sg:city":"Carneiras",
    "sg:orig_category":"Chapister\u00cda",
    "sg:phone":"+34 986 46 90 60",
    "sg:postcode":"36213",
    "sg:province":"Pontevedra",
    "wof:name":"Rodriguez Estevez Jose Carlos",
    "wof:placetype":"venue"
},
  "geometry": {"coordinates":[-8.7210121155,42.1948318481],"type":"Point"}
}