{
  "type": "Feature",
  "properties": {
    "iso:country":"ES",
    "sg:address":"Calle de Fermin Aranda, 1",
    "sg:city":"Jerez De La Frontera",
    "sg:orig_category":"Inmobiliaria (agencias)",
    "sg:phone":"+34 956 31 02 71",
    "sg:postcode":"11407",
    "sg:province":"C\u00e1diz",
    "wof:name":"Invervic Capital S.l.",
    "wof:placetype":"venue"
},
  "geometry": {"coordinates":[-6.1353902817,36.6918716431],"type":"Point"}
}