{
  "type": "Feature",
  "properties": {
    "iso:country":"ES",
    "sg:address":"Ctra. Jaen-a. La Real, S/n",
    "sg:city":"Los Villares",
    "sg:orig_category":"Empresas De Carpinter\u00cda Met\u00c1lica",
    "sg:phone":"+34 953 32 03 30",
    "sg:postcode":"23160",
    "sg:province":"Ja\u00e9n",
    "wof:name":"Rustimetal S.l.l.",
    "wof:placetype":"venue"
},
  "geometry": {"coordinates":[-3.8161590099,37.6935958862],"type":"Point"}
}