{
  "type": "Feature",
  "properties": {
    "iso:country":"ES",
    "sg:address":"Plaz Igrexa (da), 1",
    "sg:city":"Avenida Ordo\u00e7ez",
    "sg:orig_category":"Internados & Ense\u00d1anza Privada",
    "sg:phone":"+34 986 60 97 04",
    "sg:postcode":"36750",
    "sg:province":"Pontevedra",
    "wof:name":"Centro De Iniciativas Educativas Y Profesionales Rueiro S.l.",
    "wof:placetype":"venue"
},
  "geometry": {"coordinates":[-8.7706012726,41.9454116821],"type":"Point"}
}