{
  "type": "Feature",
  "properties": {
    "addr:full":"Calle de Urbasa, 8 Algorta Vizcaya 48993",
    "addr:housenumber":"8",
    "addr:postcode":"48993",
    "addr:street":"Calle De Urbasa",
    "iso:country":"ES",
    "sg:address":"Calle de Urbasa, 8",
    "sg:city":"Algorta",
    "sg:orig_category":"Agencias Y Asesores De Publicidad",
    "sg:phone":"+34 944 91 11 57",
    "sg:postcode":"48993",
    "sg:province":"Vizcaya",
    "wof:name":"Designia Dise\u00f1o Y Publicidad S.l.",
    "wof:placetype":"venue"
},
  "geometry": {"coordinates":[-3.0153338909,43.3555030823],"type":"Point"}
}