{
  "type": "Feature",
  "properties": {
    "iso:country":"ES",
    "sg:address":"Calle de Asensi, 14",
    "sg:city":"Castellon",
    "sg:orig_category":"Ense\u00d1anza: Peluquer\u00cda Est\u00c9tica",
    "sg:phone":"+34 964 22 00 77",
    "sg:postcode":"12002",
    "sg:province":"Castell\u00f3n",
    "wof:name":"Gimsa Estetica S.l.",
    "wof:placetype":"venue"
},
  "geometry": {"coordinates":[-0.0370252989,39.9829788208],"type":"Point"}
}