{
  "type": "Feature",
  "properties": {
    "iso:country":"ES",
    "sg:address":"Calle de Camino De La Barca, 3",
    "sg:city":"Cordoba",
    "sg:orig_category":"Frutas, Legumbres Frescas Y Tempranas (al Por Menor)",
    "sg:phone":"+34 957 75 17 07",
    "sg:postcode":"14010",
    "sg:province":"C\u00f3rdoba",
    "wof:name":"Frutas Y Verduras Hermanos Ortiz S.l.",
    "wof:placetype":"venue"
},
  "geometry": {"coordinates":[-4.7644982338,37.8791847229],"type":"Point"}
}