{
  "type": "Feature",
  "properties": {
    "iso:country":"ES",
    "sg:address":"Calle de Miguel Arredondo, 4",
    "sg:city":"Madrid",
    "sg:orig_category":"Frutas, Legumbres Frescas Y Tempranas (al Por Menor)",
    "sg:phone":"+34 914 74 95 02",
    "sg:postcode":"28045",
    "sg:province":"Madrid",
    "wof:name":"Pascual Sanchez Jose Maria",
    "wof:placetype":"venue"
},
  "geometry": {"coordinates":[-3.6960232258,40.3948402405],"type":"Point"}
}