{
  "type": "Feature",
  "properties": {
    "iso:country":"ES",
    "sg:address":"Carr Escoles, 3",
    "sg:city":"Almenar",
    "sg:orig_category":"Enfermeras: Consultas, Atenci\u00d3n A Domicilio",
    "sg:phone":"+34 973 77 11 75",
    "sg:postcode":"25126",
    "sg:province":"Lleida",
    "wof:name":"Obis Aguilar Maria Eugenia",
    "wof:placetype":"venue"
},
  "geometry": {"coordinates":[0.5701000094,41.7965431213],"type":"Point"}
}