{
  "type": "Feature",
  "properties": {
    "addr:full":"C/ Santa Agnes, De, S/n S. Antoni Portmany Islas Baleares 07820",
    "addr:postcode":"07820",
    "addr:street":"C / Santa Agnes De S / N S. Antoni Portmany",
    "iso:country":"ES",
    "sg:address":"C/ Santa Agnes, De, S/n",
    "sg:city":"S. Antoni Portmany",
    "sg:orig_category":"Polideportivos",
    "sg:phone":"+34 971 34 54 02",
    "sg:postcode":"07820",
    "sg:province":"Islas Baleares",
    "sg:website":"www.santantoni.net",
    "wof:name":"Ajuntament De Sant Antoni De Portmany",
    "wof:placetype":"venue"
},
  "geometry": {"coordinates":[1.3027873039,38.980430603],"type":"Point"}
}