{
  "type": "Feature",
  "properties": {
    "iso:country":"ES",
    "sg:address":"Rua Mato (do), S/n",
    "sg:city":"Xinzo De Limia",
    "sg:orig_category":"Poller\u00cda Y Caza (al Por Menor)",
    "sg:phone":"+34 988 40 97 87",
    "sg:postcode":"32630",
    "sg:province":"Ourense",
    "wof:name":"Gomez Marra Manuel",
    "wof:placetype":"venue"
},
  "geometry": {"coordinates":[-7.7297339439,42.0608634949],"type":"Point"}
}