{
  "type": "Feature",
  "properties": {
    "iso:country":"ES",
    "sg:address":"Calle de Damas, 17",
    "sg:city":"Medina Campo",
    "sg:orig_category":"Asilos De Ancianos. Centros Privados",
    "sg:phone":"+34 983 81 16 99",
    "sg:postcode":"47400",
    "sg:province":"Valladolid",
    "wof:name":"Gonzalez Saornil Asuncion",
    "wof:placetype":"venue"
},
  "geometry": {"coordinates":[-4.9233746529,41.3095626831],"type":"Point"}
}