{
  "type": "Feature",
  "properties": {
    "iso:country":"ES",
    "sg:address":"Ctra Nacional V Madrid-lisboa, Km. 0401,9",
    "sg:city":"Badajoz",
    "sg:orig_category":"Distribuci\u00d3n De Petr\u00d3leo Y Derivados",
    "sg:phone":"+34 924 26 17 58",
    "sg:postcode":"06008",
    "sg:province":"Badajoz",
    "wof:name":"Macrotelefonia Division Andalucia S.l.",
    "wof:placetype":"venue"
},
  "geometry": {"coordinates":[-6.9430441856,38.8723373413],"type":"Point"}
}