{
  "type": "Feature",
  "properties": {
    "iso:country":"ES",
    "sg:address":"Carrer de Biosca, 44",
    "sg:city":"Barcelona",
    "sg:orig_category":"Alimentaci\u00d3n General (al Por Menor)",
    "sg:phone":"+34 933 45 50 33",
    "sg:postcode":"08030",
    "sg:province":"Barcelona",
    "wof:name":"De Osso Ventura Jaime",
    "wof:placetype":"venue"
},
  "geometry": {"coordinates":[2.2066349983,41.4383239746],"type":"Point"}
}