{
  "type": "Feature",
  "properties": {
    "addr:full":"Calle de Cervantes, 87 Alginet Valencia 46230",
    "addr:housenumber":"87",
    "addr:postcode":"46230",
    "addr:street":"Calle De Cervantes",
    "iso:country":"ES",
    "sg:address":"Calle de Cervantes, 87",
    "sg:city":"Alginet",
    "sg:orig_category":"Frutas Y Legumbres Frescas (al Por Mayor)",
    "sg:phone":"+34 961 75 05 30",
    "sg:postcode":"46230",
    "sg:province":"Valencia",
    "wof:name":"Gimenez Climent Vicente",
    "wof:placetype":"venue"
},
  "geometry": {"coordinates":[-0.4677711129,39.2594070435],"type":"Point"}
}