{
  "type": "Feature",
  "properties": {
    "iso:country":"ES",
    "sg:address":"Rond Pais Valencia, 39",
    "sg:city":"Sueca",
    "sg:orig_category":"Frutas Y Legumbres Frescas (al Por Mayor)",
    "sg:phone":"+34 961 70 12 01",
    "sg:postcode":"46410",
    "sg:province":"Valencia",
    "wof:name":"Miralles Fuertes Damian",
    "wof:placetype":"venue"
},
  "geometry": {"coordinates":[-0.3095389903,39.1983566284],"type":"Point"}
}