{
  "type": "Feature",
  "properties": {
    "iso:country":"ES",
    "sg:address":"Plaz Picota (la), S/n",
    "sg:city":"San Miguel De Las Due\u00e7as",
    "sg:orig_category":"Alimentaci\u00d3n General (al Por Menor)",
    "sg:phone":"+34 987 46 70 18",
    "sg:postcode":"24398",
    "sg:province":"Le\u00f3n",
    "wof:name":"Rodriguez Fierro Manuel",
    "wof:placetype":"venue"
},
  "geometry": {"coordinates":[-6.5209589005,42.617225647],"type":"Point"}
}