{
  "type": "Feature",
  "properties": {
    "addr:full":"Calle de Alburquerque, 4 Madrid Madrid 28010",
    "addr:housenumber":"4",
    "addr:postcode":"28010",
    "addr:street":"Calle De Alburquerque",
    "iso:country":"ES",
    "sg:address":"Calle de Alburquerque, 4",
    "sg:city":"Madrid",
    "sg:orig_category":"Alimentaci\u00d3n General (al Por Menor)",
    "sg:phone":"+34 914 46 90 91",
    "sg:postcode":"28010",
    "sg:province":"Madrid",
    "wof:name":"Pomeda Martinez Alvaro",
    "wof:placetype":"venue"
},
  "geometry": {"coordinates":[-3.7026202679,40.4311218262],"type":"Point"}
}