{
  "type": "Feature",
  "properties": {
    "addr:full":"Carr Santiago, 1 Girona Girona 17003",
    "addr:housenumber":"1",
    "addr:postcode":"17003",
    "addr:street":"Carr Santiago",
    "iso:country":"ES",
    "sg:address":"Carr Santiago, 1",
    "sg:city":"Girona",
    "sg:orig_category":"Sindicatos De Trabajadores",
    "sg:phone":"+34 972 22 36 96",
    "sg:postcode":"17003",
    "sg:province":"Girona",
    "wof:name":"Fasga",
    "wof:placetype":"venue"
},
  "geometry": {"coordinates":[2.8143000603,41.9693107605],"type":"Point"}
}