{
  "type": "Feature",
  "properties": {
    "addr:full":"Carr Canigo, 7 Bisbal D'emporda Girona 17100",
    "addr:housenumber":"7",
    "addr:postcode":"17100",
    "addr:street":"Carr Canigo",
    "iso:country":"ES",
    "sg:address":"Carr Canigo, 7",
    "sg:city":"Bisbal D'emporda",
    "sg:orig_category":"Peluquer\u00cdas, Peluquer\u00cda Mixta",
    "sg:phone":"+34 972 64 55 67",
    "sg:postcode":"17100",
    "sg:province":"Girona",
    "wof:name":"Torro Ferrer Josep",
    "wof:placetype":"venue"
},
  "geometry": {"coordinates":[2.8268949986,41.9811706543],"type":"Point"}
}