{
  "type": "Feature",
  "properties": {
    "iso:country":"ES",
    "sg:address":"Calle de Obispo Pintado, 6",
    "sg:city":"Huesca",
    "sg:orig_category":"T\u00c9cnicos Veterinarios",
    "sg:phone":"+34 974 24 30 83",
    "sg:postcode":"22005",
    "sg:province":"Huesca",
    "wof:name":"Clinica Veterinaria Zoo",
    "wof:placetype":"venue"
},
  "geometry": {"coordinates":[-0.403290987,42.1336784363],"type":"Point"}
}