{
  "type": "Feature",
  "properties": {
    "iso:country":"ES",
    "sg:address":"Pg Cordelles, 6",
    "sg:city":"Cerdanyola Valles",
    "sg:orig_category":"Heladeros",
    "sg:phone":"+34 936 91 99 21",
    "sg:postcode":"08290",
    "sg:province":"Barcelona",
    "wof:name":"Luengo Alonso Concepcion",
    "wof:placetype":"venue"
},
  "geometry": {"coordinates":[2.1396930218,41.4923973083],"type":"Point"}
}