{
  "type": "Feature",
  "properties": {
    "addr:full":"Gta Manuel Garcia Moreno, S/n Aranjuez Madrid 28300",
    "addr:housenumber":"s / n",
    "addr:postcode":"28300",
    "addr:street":"Gta Manuel Garcia Moreno",
    "iso:country":"ES",
    "sg:address":"Gta Manuel Garcia Moreno, S/n",
    "sg:city":"Aranjuez",
    "sg:orig_category":"Lavander\u00cdas Para Particulares, Autoservicio De Lavander\u00cdas",
    "sg:phone":"+34 918 92 24 64",
    "sg:postcode":"28300",
    "sg:province":"Madrid",
    "wof:name":"Lavanderia Industrial San Antonio De Aranjuez S.l.",
    "wof:placetype":"venue"
},
  "geometry": {"coordinates":[-3.6065208912,40.0203704834],"type":"Point"}
}