{
  "type": "Feature",
  "properties": {
    "iso:country":"ES",
    "sg:address":"Avda Fragoso, 73",
    "sg:city":"Vigo",
    "sg:orig_category":"Empresarios",
    "sg:phone":"+34 986 24 28 02",
    "sg:postcode":"36210",
    "sg:province":"Pontevedra",
    "wof:name":"Martinez Gomez Maria Montserrat",
    "wof:placetype":"venue"
},
  "geometry": {"coordinates":[-8.7361021042,42.2151603699],"type":"Point"}
}