{
  "type": "Feature",
  "properties": {
    "iso:country":"ES",
    "sg:address":"Carrer de Pou De La Pina, 14",
    "sg:city":"Vilafranca Penedes",
    "sg:orig_category":"Ropa Para Caballeros (al Por Menor)",
    "sg:phone":"+34 938 18 08 29",
    "sg:postcode":"08720",
    "sg:province":"Barcelona",
    "wof:name":"Frances Montserrat Josep Lluis",
    "wof:placetype":"venue"
},
  "geometry": {"coordinates":[1.6992199421,41.3447799683],"type":"Point"}
}