{
  "type": "Feature",
  "properties": {
    "addr:full":"Carrer de Mallorca, 51 Barcelona Barcelona 08029",
    "addr:housenumber":"51",
    "addr:postcode":"08029",
    "addr:street":"Carrer De Mallorca",
    "iso:country":"ES",
    "sg:address":"Carrer de Mallorca, 51",
    "sg:city":"Barcelona",
    "sg:orig_category":"Aparcamientos (infraestructuras, Accesorios)",
    "sg:phone":"+34 934 19 73 96",
    "sg:postcode":"08029",
    "sg:province":"Barcelona",
    "wof:name":"Nu\u00f1ez Urgell Y Cia. Mallorca 51,c.b.",
    "wof:placetype":"venue"
},
  "geometry": {"coordinates":[2.1489920616,41.3838043213],"type":"Point"}
}