{
  "type": "Feature",
  "properties": {
    "addr:full":"Carrer de Pacheco, 54 Mataro Barcelona 08301",
    "addr:housenumber":"54",
    "addr:postcode":"08301",
    "addr:street":"Carrer De Pacheco",
    "iso:country":"ES",
    "sg:address":"Carrer de Pacheco, 54",
    "sg:city":"Mataro",
    "sg:orig_category":"Colorantes, Colores Y Pigmentos (fabricaci\u00d3n, Al Por Mayor)",
    "sg:phone":"+34 937 55 46 00",
    "sg:postcode":"08301",
    "sg:province":"Barcelona",
    "wof:name":"Industrial Gamacolor S. L.",
    "wof:placetype":"venue"
},
  "geometry": {"coordinates":[2.452958107,41.5430679321],"type":"Point"}
}