{
  "type": "Feature",
  "properties": {
    "addr:full":"Calle de Mayor, 37 Abarzuza Navarra 31178",
    "addr:housenumber":"37",
    "addr:postcode":"31178",
    "addr:street":"Calle De Mayor",
    "iso:country":"ES",
    "sg:address":"Calle de Mayor, 37",
    "sg:city":"Abarzuza",
    "sg:orig_category":"Explotaci\u00d3n De Bosques",
    "sg:phone":"+34 948 52 02 05",
    "sg:postcode":"31178",
    "sg:province":"Navarra",
    "wof:name":"Maderas Iriarte S.l.",
    "wof:placetype":"venue"
},
  "geometry": {"coordinates":[-2.0220561028,42.7265357971],"type":"Point"}
}