{
  "type": "Feature",
  "properties": {
    "iso:country":"ES",
    "sg:address":"Fra Francesc D'eiximenis, 18",
    "sg:city":"Parets Del Valles",
    "sg:orig_category":"Alimentaci\u00d3n General (al Por Menor)",
    "sg:phone":"+34 935 73 00 91",
    "sg:postcode":"08150",
    "sg:province":"Barcelona",
    "wof:name":"Espinar Navarro Encarnacion",
    "wof:placetype":"venue"
},
  "geometry": {"coordinates":[2.2296199799,41.5624351501],"type":"Point"}
}