{
  "type": "Feature",
  "properties": {
    "addr:full":"La Ayuela, S/n La Cavada Cantabria 39720",
    "addr:housenumber":"s / n",
    "addr:postcode":"39720",
    "iso:country":"ES",
    "sg:address":"La Ayuela, S/n",
    "sg:city":"La Cavada",
    "sg:orig_category":"Producci\u00d3n De Abonos Y De Fertilizantes",
    "sg:phone":"+34 942 53 90 36",
    "sg:postcode":"39720",
    "sg:province":"Cantabria",
    "wof:name":"Guate Cerro Angel",
    "wof:placetype":"venue"
},
  "geometry": {"coordinates":[-3.7075798512,43.3526878357],"type":"Point"}
}