{
  "type": "Feature",
  "properties": {
    "addr:full":"Calle de Juan Gris, 6 Malaga M\u00e1laga 29006",
    "addr:housenumber":"6",
    "addr:postcode":"29006",
    "addr:street":"Calle De Juan Gris;Ma\u0301Laga",
    "iso:country":"ES",
    "sg:address":"Calle de Juan Gris, 6",
    "sg:city":"Malaga",
    "sg:orig_category":"Asociaciones, Organismos Culturales Y Socioeducativos",
    "sg:phone":"+34 952 33 16 68",
    "sg:postcode":"29006",
    "sg:province":"M\u00e1laga",
    "wof:name":"Asociacion Cultural Recreativa Pe\u00f1a Cortijo De Torres",
    "wof:placetype":"venue"
},
  "geometry": {"coordinates":[-4.4547929764,36.7054786682],"type":"Point"}
}