{
  "type": "Feature",
  "properties": {
    "addr:full":"Carrer de Fluvia, 33 Barcelona Barcelona 08019",
    "addr:housenumber":"33",
    "addr:postcode":"08019",
    "addr:street":"Carrer De Fluvia",
    "iso:country":"ES",
    "sg:address":"Carrer de Fluvia, 33",
    "sg:city":"Barcelona",
    "sg:orig_category":"Agencias Y Agentes Comerciales, Representantes",
    "sg:phone":"+34 933 08 01 45",
    "sg:postcode":"08019",
    "sg:province":"Barcelona",
    "wof:name":"Nu\u00f1ez Tomas Juan Manuel",
    "wof:placetype":"venue"
},
  "geometry": {"coordinates":[2.2092700005,41.4050788879],"type":"Point"}
}