{
  "type": "Feature",
  "properties": {
    "iso:country":"ES",
    "sg:address":"Calle de Reina, 9",
    "sg:city":"Zamora",
    "sg:orig_category":"Internados & Ense\u00d1anza Privada",
    "sg:phone":"+34 980 53 18 43",
    "sg:postcode":"49004",
    "sg:province":"Zamora",
    "wof:name":"Colegio Divina Providencia",
    "wof:placetype":"venue"
},
  "geometry": {"coordinates":[-5.7480978966,41.5035743713],"type":"Point"}
}