{
  "type": "Feature",
  "properties": {
    "iso:country":"ES",
    "sg:address":"Calle de San Eugenio, 14",
    "sg:city":"Alcazares",
    "sg:orig_category":"Molduras, Junquillos, Listones Y Molduras Perforadas",
    "sg:phone":"+34 968 17 18 78",
    "sg:postcode":"30710",
    "sg:province":"Murcia",
    "wof:name":"Lopez Sanchez Josefa",
    "wof:placetype":"venue"
},
  "geometry": {"coordinates":[-0.8489990234,37.7447319031],"type":"Point"}
}