{
  "type": "Feature",
  "properties": {
    "iso:country":"ES",
    "sg:address":"Calle de Fuente Blanca, 1",
    "sg:city":"Santiago El Mayor",
    "sg:orig_category":"Arte, Cultura, Edici\u00d3n",
    "sg:phone":"+34 968 25 36 60",
    "sg:postcode":"30012",
    "sg:province":"Murcia",
    "wof:name":"Garcia Rios Josefa",
    "wof:placetype":"venue"
},
  "geometry": {"coordinates":[-1.1206640005,37.9650650024],"type":"Point"}
}