{
  "type": "Feature",
  "properties": {
    "addr:full":"Avda Poblados, 133 Madrid Madrid 28025",
    "addr:housenumber":"133",
    "addr:postcode":"28025",
    "addr:street":"Avda Poblados",
    "iso:country":"ES",
    "sg:address":"Avda Poblados, 133",
    "sg:city":"Madrid",
    "sg:orig_category":"Empresas De Vigilancia, Guardia Y Protecci\u00d3n",
    "sg:phone":"+34 913 41 17 08",
    "sg:postcode":"28025",
    "sg:province":"Madrid",
    "wof:name":"Easyurban S.l.",
    "wof:placetype":"venue"
},
  "geometry": {"coordinates":[-3.7329978943,40.3737220764],"type":"Point"}
}