{
  "type": "Feature",
  "properties": {
    "iso:country":"ES",
    "sg:address":"Avda Mari\u00d1a (da), S/n",
    "sg:city":"San Cibrao",
    "sg:orig_category":"Estancos",
    "sg:phone":"+34 982 59 42 28",
    "sg:postcode":"27890",
    "sg:province":"Lugo",
    "wof:name":"Rey Fernandez Candido",
    "wof:placetype":"venue"
},
  "geometry": {"coordinates":[-7.4397139549,43.6968955994],"type":"Point"}
}