{
  "type": "Feature",
  "properties": {
    "addr:full":"Carr Tres Marias, 6 Burjassot Valencia 46100",
    "addr:housenumber":"6",
    "addr:postcode":"46100",
    "addr:street":"Carr Tres Marias",
    "iso:country":"ES",
    "sg:address":"Carr Tres Marias, 6",
    "sg:city":"Burjassot",
    "sg:orig_category":"Hormig\u00d3n Listo Para Usar",
    "sg:phone":"+34 963 64 58 47",
    "sg:postcode":"46100",
    "sg:province":"Valencia",
    "sg:website":"www.pavimoder.com",
    "wof:name":"Pavimoder S.l.",
    "wof:placetype":"venue"
},
  "geometry": {"coordinates":[-0.4183039963,39.5166435242],"type":"Point"}
}