{
  "type": "Feature",
  "properties": {
    "iso:country":"ES",
    "sg:address":"Calle de Cueva De La Pileta, 2",
    "sg:city":"Sevilla",
    "sg:orig_category":"Inmobiliaria (agencias)",
    "sg:phone":"+34 954 52 12 80",
    "sg:postcode":"41020",
    "sg:province":"Sevilla",
    "wof:name":"Giraldilla Servicios Inmobiliarios S.l",
    "wof:placetype":"venue"
},
  "geometry": {"coordinates":[-5.9402170181,37.4021911621],"type":"Point"}
}