{
  "type": "Feature",
  "properties": {
    "iso:country":"ES",
    "sg:address":"Calle de Manuel Altolaguirre, 21",
    "sg:city":"Madrid",
    "sg:orig_category":"Art\u00cdculos De Decoraci\u00d3n",
    "sg:phone":"+34 916 25 55 07",
    "sg:postcode":"28050",
    "sg:province":"Madrid",
    "wof:name":"Changuinola S.l.",
    "wof:placetype":"venue"
},
  "geometry": {"coordinates":[-3.6329479218,40.5054893494],"type":"Point"}
}