{
  "type": "Feature",
  "properties": {
    "iso:country":"ES",
    "sg:address":"Calle de San Veremundo Abad, 18",
    "sg:city":"Ayegui",
    "sg:orig_category":"Postigos, Persianas Y Celos\u00cdas",
    "sg:phone":"+34 948 55 37 90",
    "sg:postcode":"31240",
    "sg:province":"Navarra",
    "wof:name":"Urriza Oteiza Carmen",
    "wof:placetype":"venue"
},
  "geometry": {"coordinates":[-2.041809082,42.6537399292],"type":"Point"}
}