{
  "type": "Feature",
  "properties": {
    "addr:full":"Altzutzate, 50 Huarte Navarra 31620",
    "addr:housenumber":"50",
    "addr:postcode":"31620",
    "addr:street":"Altzutzate;Navarra",
    "iso:country":"ES",
    "sg:address":"Altzutzate, 50",
    "sg:city":"Huarte",
    "sg:orig_category":"Distribuci\u00d3n De Petr\u00d3leo Y Derivados",
    "sg:phone":"+34 948 33 22 02",
    "sg:postcode":"31620",
    "sg:province":"Navarra",
    "wof:name":"Elomendi S.l.",
    "wof:placetype":"venue"
},
  "geometry": {"coordinates":[-1.604006052,42.8226280212],"type":"Point"}
}