{
  "type": "Feature",
  "properties": {
    "addr:full":"Rbla Maria Casas, 82 Gava Barcelona 08850",
    "addr:housenumber":"82",
    "addr:postcode":"08850",
    "addr:street":"Rbla Maria Casas",
    "iso:country":"ES",
    "sg:address":"Rbla Maria Casas, 82",
    "sg:city":"Gava",
    "sg:orig_category":"Cajas De Ahorro",
    "sg:phone":"+34 936 33 33 37",
    "sg:postcode":"08850",
    "sg:province":"Barcelona",
    "sg:website":"www.cam.es",
    "wof:name":"Caja De Ahorros Del Mediterraneo",
    "wof:placetype":"venue"
},
  "geometry": {"coordinates":[2.0012850761,41.3040237427],"type":"Point"}
}