{
  "type": "Feature",
  "properties": {
    "iso:country":"ES",
    "sg:address":"Rua Uruguay, 5",
    "sg:city":"Vigo",
    "sg:orig_category":"Centros Empresariales",
    "sg:phone":"+34 986 22 33 17",
    "sg:postcode":"36201",
    "sg:province":"Pontevedra",
    "wof:name":"Randstad Empleo E.t.t. S.a.",
    "wof:placetype":"venue"
},
  "geometry": {"coordinates":[-8.7187862396,42.2365722656],"type":"Point"}
}