{
  "type": "Feature",
  "properties": {
    "addr:full":"Carr Barcelona, 33 Moncada Valencia 46113",
    "addr:housenumber":"33",
    "addr:postcode":"46113",
    "addr:street":"Carr Barcelona",
    "iso:country":"ES",
    "sg:address":"Carr Barcelona, 33",
    "sg:city":"Moncada",
    "sg:orig_category":"Molduras, Junquillos, Listones Y Molduras Perforadas",
    "sg:phone":"+34 961 30 18 31",
    "sg:postcode":"46113",
    "sg:province":"Valencia",
    "wof:name":"Eurotel Sur S.l.",
    "wof:placetype":"venue"
},
  "geometry": {"coordinates":[-0.3940890133,39.5487365723],"type":"Point"}
}