{
  "type": "Feature",
  "properties": {
    "addr:full":"Barrio Villaflor, S/n Ponferrada Le\u00f3n 24400",
    "addr:housenumber":"s / n",
    "addr:postcode":"24400",
    "addr:street":"Barrio Villaflor",
    "iso:country":"ES",
    "sg:address":"Barrio Villaflor, S/n",
    "sg:city":"Ponferrada",
    "sg:orig_category":"Iglesia Cat\u00d3lica",
    "sg:phone":"+34 987 40 12 62",
    "sg:postcode":"24400",
    "sg:province":"Le\u00f3n",
    "wof:name":"Diocesis Astorga Administracion",
    "wof:placetype":"venue"
},
  "geometry": {"coordinates":[-6.5983390808,42.5483360291],"type":"Point"}
}