{
  "type": "Feature",
  "properties": {
    "addr:full":"Avda Cinca, 46 Barbastro Huesca 22300",
    "addr:housenumber":"46",
    "addr:postcode":"22300",
    "addr:street":"Avda Cinca",
    "iso:country":"ES",
    "sg:address":"Avda Cinca, 46",
    "sg:city":"Barbastro",
    "sg:orig_category":"Laboratorios Y Trabajos De Fotograf\u00cda, V\u00cddeo Y Cine",
    "sg:phone":"+34 974 31 61 52",
    "sg:postcode":"22300",
    "sg:province":"Huesca",
    "wof:name":"Sancerni Penella Celia Patricia",
    "wof:placetype":"venue"
},
  "geometry": {"coordinates":[0.1328230053,42.0320205688],"type":"Point"}
}