{
  "type": "Feature",
  "properties": {
    "iso:country":"ES",
    "sg:address":"Calle de Carretas, 2",
    "sg:city":"Navalmorales",
    "sg:orig_category":"Reposter\u00cdas",
    "sg:phone":"+34 925 40 44 13",
    "sg:postcode":"45140",
    "sg:province":"Toledo",
    "wof:name":"Martin Rocha Florencio",
    "wof:placetype":"venue"
},
  "geometry": {"coordinates":[-4.6400790215,39.7264823914],"type":"Point"}
}