{
  "type": "Feature",
  "properties": {
    "addr:full":"Avda Andalucia, 19 Alhendin Granada 18620",
    "addr:housenumber":"19",
    "addr:postcode":"18620",
    "addr:street":"Avda Andalucia",
    "iso:country":"ES",
    "sg:address":"Avda Andalucia, 19",
    "sg:city":"Alhendin",
    "sg:orig_category":"Trabajos De Topograf\u00cda",
    "sg:phone":"+34 958 55 85 41",
    "sg:postcode":"18620",
    "sg:province":"Granada",
    "wof:name":"Topografia Aplicada A La Construccion Horus,s.l.",
    "wof:placetype":"venue"
},
  "geometry": {"coordinates":[-3.6410109997,37.1050071716],"type":"Point"}
}