{
  "type": "Feature",
  "properties": {
    "addr:full":"Calle de Orilla Del Llano, 4 S. Sebastian Gomera Santa Cruz De Tenerife 38800",
    "addr:housenumber":"4",
    "addr:postcode":"38800",
    "addr:street":"Calle De Orilla Del Llano",
    "iso:country":"ES",
    "sg:address":"Calle de Orilla Del Llano, 4",
    "sg:city":"S. Sebastian Gomera",
    "sg:orig_category":"Farmacias",
    "sg:phone":"+34 922 14 16 07",
    "sg:postcode":"38800",
    "sg:province":"Santa Cruz De Tenerife",
    "wof:name":"Garcia Darias Maria Del Pilar",
    "wof:placetype":"venue"
},
  "geometry": {"coordinates":[-17.1081104279,28.092168808],"type":"Point"}
}