{
  "type": "Feature",
  "properties": {
    "iso:country":"ES",
    "sg:address":"Avda Roma, 3",
    "sg:city":"Le\u00f3n",
    "sg:orig_category":"Asociaciones Humanitarias, De Cooperaci\u00d3n, De Acci\u00d3n Social",
    "sg:phone":"+34 987 24 83 63",
    "sg:postcode":"24001",
    "sg:province":"Le\u00f3n",
    "wof:name":"Asociacion Provincial De Alcoholicos Rehabilitados",
    "wof:placetype":"venue"
},
  "geometry": {"coordinates":[-5.576333046,42.5987243652],"type":"Point"}
}