{
  "type": "Feature",
  "properties": {
    "iso:country":"ES",
    "sg:address":"Calle de Lope De Rueda, 77",
    "sg:city":"Malaga",
    "sg:orig_category":"Pintura Y Barniz (al Por Menor)",
    "sg:phone":"+34 952 43 90 64",
    "sg:postcode":"29190",
    "sg:province":"M\u00e1laga",
    "wof:name":"Pinsan Mlaga S.l.",
    "wof:placetype":"venue"
},
  "geometry": {"coordinates":[-4.4815301895,36.7391471863],"type":"Point"}
}