{
  "type": "Feature",
  "properties": {
    "addr:full":"Psaj Noblejas, 6 Malaga M\u00e1laga 29002",
    "addr:postcode":"29002",
    "addr:street":"Ma\u0301Laga",
    "iso:country":"ES",
    "sg:address":"Psaj Noblejas, 6",
    "sg:city":"Malaga",
    "sg:orig_category":"Ense\u00d1anza Variada",
    "sg:phone":"+34 952 32 03 23",
    "sg:postcode":"29002",
    "sg:province":"M\u00e1laga",
    "wof:name":"Conejo Fernandez Dolores Jesus",
    "wof:placetype":"venue"
},
  "geometry": {"coordinates":[-4.4280080795,36.7140541077],"type":"Point"}
}