{
  "type": "Feature",
  "properties": {
    "addr:full":"Julian Etxeberria Kalea, 18 Eibar Guip\u00f9zcoa 20600",
    "addr:housenumber":"18",
    "addr:postcode":"20600",
    "addr:street":"Julian Etxeberria Kalea;Guipu\u0300Zcoa",
    "iso:country":"ES",
    "sg:address":"Julian Etxeberria Kalea, 18",
    "sg:city":"Eibar",
    "sg:orig_category":"Molduras, Junquillos, Listones Y Molduras Perforadas",
    "sg:phone":"+34 943 70 03 00",
    "sg:postcode":"20600",
    "sg:province":"Guip\u00f9zcoa",
    "wof:name":"Sarasqueta Amuategi Javier",
    "wof:placetype":"venue"
},
  "geometry": {"coordinates":[-2.4692881107,43.1851844788],"type":"Point"}
}