{
  "type": "Feature",
  "properties": {
    "addr:full":"Calle de Maestro Guerrero, 10 Miguel Esteban Toledo 45830",
    "addr:housenumber":"10",
    "addr:postcode":"45830",
    "addr:street":"Calle De Maestro Guerrero;Miguel Esteban",
    "iso:country":"ES",
    "sg:address":"Calle de Maestro Guerrero, 10",
    "sg:city":"Miguel Esteban",
    "sg:orig_category":"Revestimientos Industriales",
    "sg:phone":"+34 925 17 25 27",
    "sg:postcode":"45830",
    "sg:province":"Toledo",
    "wof:name":"Revestimientos Hermanos Egido S.l.",
    "wof:placetype":"venue"
},
  "geometry": {"coordinates":[-3.0734689236,39.5211296082],"type":"Point"}
}