{
  "type": "Feature",
  "properties": {
    "iso:country":"ES",
    "sg:address":"Carr Major, 7",
    "sg:city":"Sils",
    "sg:orig_category":"Librer\u00cdas",
    "sg:phone":"+34 972 85 33 01",
    "sg:postcode":"17410",
    "sg:province":"Girona",
    "wof:name":"Ballesteros Pueyo Anna",
    "wof:placetype":"venue"
},
  "geometry": {"coordinates":[2.744492054,41.8080635071],"type":"Point"}
}