{
  "type": "Feature",
  "properties": {
    "addr:full":"Calle de Txapinene, 3 Donostia-san Sebastian Guip\u00f9zcoa 20017",
    "addr:housenumber":"3",
    "addr:postcode":"20017",
    "addr:street":"Calle De Txapinene",
    "iso:country":"ES",
    "sg:address":"Calle de Txapinene, 3",
    "sg:city":"Donostia-san Sebastian",
    "sg:orig_category":"Muebles Y Accesorios Para Cocinas Y Cuartos De Ba\u00d1o (al Por Menor)",
    "sg:phone":"+34 943 35 21 43",
    "sg:postcode":"20017",
    "sg:province":"Guip\u00f9zcoa",
    "wof:name":"Rosario Brocal Garcia",
    "wof:placetype":"venue"
},
  "geometry": {"coordinates":[-1.9343860149,43.3154182434],"type":"Point"}
}