{
  "type": "Feature",
  "properties": {
    "iso:country":"ES",
    "sg:address":"Calle de Manuel Alfaro Pereira, 2",
    "sg:city":"Badajoz",
    "sg:orig_category":"Carnicer\u00cdas, Carnicer\u00cdas",
    "sg:phone":"+34 924 25 55 44",
    "sg:postcode":"06004",
    "sg:province":"Badajoz",
    "wof:name":"Cansado Mendez Manuel",
    "wof:placetype":"venue"
},
  "geometry": {"coordinates":[-6.972413063,38.8736381531],"type":"Point"}
}