{
  "type": "Feature",
  "properties": {
    "addr:full":"Calle de Brouard Santiago, 3 Bilbao Vizcaya 48012",
    "addr:housenumber":"3",
    "addr:postcode":"48012",
    "addr:street":"Calle De Brouard Santiago",
    "iso:country":"ES",
    "sg:address":"Calle de Brouard Santiago, 3",
    "sg:city":"Bilbao",
    "sg:orig_category":"Peluquer\u00cdas, Peluquer\u00cda Mixta",
    "sg:phone":"+34 944 21 27 52",
    "sg:postcode":"48012",
    "sg:province":"Vizcaya",
    "wof:name":"Salon Charada S.l.",
    "wof:placetype":"venue"
},
  "geometry": {"coordinates":[-2.939827919,43.2547531128],"type":"Point"}
}