{
  "type": "Feature",
  "properties": {
    "addr:full":"Rua Calvo Sotelo, 25 Estrada Pontevedra 36680",
    "addr:housenumber":"25",
    "addr:postcode":"36680",
    "addr:street":"Rua Calvo Sotelo;Estrada Pontevedra",
    "iso:country":"ES",
    "sg:address":"Rua Calvo Sotelo, 25",
    "sg:city":"Estrada",
    "sg:orig_category":"Abogados",
    "sg:phone":"+34 986 57 34 44",
    "sg:postcode":"36680",
    "sg:province":"Pontevedra",
    "wof:name":"Palmou Cibeira Jose Carlos",
    "wof:placetype":"venue"
},
  "geometry": {"coordinates":[-8.4883441925,42.6899719238],"type":"Point"}
}