{
  "type": "Feature",
  "properties": {
    "iso:country":"ES",
    "sg:address":"Avda Valdecilla, S/n",
    "sg:city":"Santander",
    "sg:orig_category":"Estancos",
    "sg:phone":"+34 942 33 83 68",
    "sg:postcode":"39008",
    "sg:province":"Cantabria",
    "wof:name":"Diaz-caneja Bustamante Josefina",
    "wof:placetype":"venue"
},
  "geometry": {"coordinates":[-3.8281290531,43.4580802917],"type":"Point"}
}