{
  "type": "Feature",
  "properties": {
    "addr:full":"Avda Doctor Artero Guirao, 228 S. Pedro Pinatar Murcia 30740",
    "addr:housenumber":"228",
    "addr:postcode":"30740",
    "addr:street":"Avda Doctor Artero Guirao;S. Pedro",
    "iso:country":"ES",
    "sg:address":"Avda Doctor Artero Guirao, 228",
    "sg:city":"S. Pedro Pinatar",
    "sg:orig_category":"Agentes, Concesionarios Y Sucursales De Veh\u00cdculos",
    "sg:phone":"+34 968 18 05 78",
    "sg:postcode":"30740",
    "sg:province":"Murcia",
    "wof:name":"Costamotor S.a.",
    "wof:placetype":"venue"
},
  "geometry": {"coordinates":[-0.8111150265,37.8228874207],"type":"Point"}
}