{
  "type": "Feature",
  "properties": {
    "iso:country":"ES",
    "sg:address":"Carrer de Ausias Marc, 131",
    "sg:city":"Barcelona",
    "sg:orig_category":"Alquiler De V\u00cddeo",
    "sg:phone":"+34 932 65 59 20",
    "sg:postcode":"08013",
    "sg:province":"Barcelona",
    "wof:name":"Bonilla Almanza Maria Josefa",
    "wof:placetype":"venue"
},
  "geometry": {"coordinates":[2.1818490028,41.3962097168],"type":"Point"}
}