{
  "type": "Feature",
  "properties": {
    "addr:full":"Ctra Bollullos-aznalcazar, Km. 0003,0 Bollullos Mitacion Sevilla 41110",
    "addr:postcode":"41110",
    "addr:street":"Ctra Bollullos-Aznalcazar Km. 0003,0 Bollullos Mitacion",
    "iso:country":"ES",
    "sg:address":"Ctra Bollullos-aznalcazar, Km. 0003,0",
    "sg:city":"Bollullos Mitacion",
    "sg:orig_category":"Producci\u00d3n, Venta De Productos De Agricultura Biol\u00d3gica",
    "sg:phone":"+34 955 95 00 07",
    "sg:postcode":"41110",
    "sg:province":"Sevilla",
    "wof:name":"Indoga S.l.",
    "wof:placetype":"venue"
},
  "geometry": {"coordinates":[-6.1373138428,37.3355293274],"type":"Point"}
}