{
  "type": "Feature",
  "properties": {
    "iso:country":"ES",
    "sg:address":"Calle de Embajadores, 64",
    "sg:city":"Madrid",
    "sg:orig_category":"Radiocomunicaciones, Telefon\u00cda M\u00d3vil, Radiomensajer\u00cda: Servicios, Comercializaci\u00d3n",
    "sg:phone":"+34 915 28 58 60",
    "sg:postcode":"28012",
    "sg:province":"Madrid",
    "wof:name":"Mateo Mendez Ricardo",
    "wof:placetype":"venue"
},
  "geometry": {"coordinates":[-3.7040729523,40.407333374],"type":"Point"}
}