{
  "type": "Feature",
  "properties": {
    "iso:country":"ES",
    "sg:address":"Calle de Carretera De Almeria, 91",
    "sg:city":"Adra",
    "sg:orig_category":"Venta, Montaje De Neum\u00c1ticos",
    "sg:phone":"+34 950 40 32 69",
    "sg:postcode":"04770",
    "sg:province":"Almer\u00eda",
    "wof:name":"Argudo Ruiz Luis",
    "wof:placetype":"venue"
},
  "geometry": {"coordinates":[-3.0048041344,36.7482337952],"type":"Point"}
}