{
  "type": "Feature",
  "properties": {
    "addr:full":"Calle de Fragua, 15 Torreiglesias Segovia 40192",
    "addr:housenumber":"15",
    "addr:postcode":"40192",
    "addr:street":"Calle De Fragua;Segovia",
    "iso:country":"ES",
    "sg:address":"Calle de Fragua, 15",
    "sg:city":"Torreiglesias",
    "sg:orig_category":"Panader\u00cdas, Panader\u00cdas",
    "sg:phone":"+34 921 50 94 97",
    "sg:postcode":"40192",
    "sg:province":"Segovia",
    "wof:name":"Pastor Panaderia Bolleria S.l.",
    "wof:placetype":"venue"
},
  "geometry": {"coordinates":[-4.0501542091,41.0517349243],"type":"Point"}
}