{
  "type": "Feature",
  "properties": {
    "iso:country":"ES",
    "sg:address":"Simon Arrieta Plaza, 1",
    "sg:city":"Bergara",
    "sg:orig_category":"Abogados",
    "sg:phone":"+34 943 76 16 28",
    "sg:postcode":"20570",
    "sg:province":"Guip\u00f9zcoa",
    "wof:name":"Larra\u00f1aga Ranero , Milagros",
    "wof:placetype":"venue"
},
  "geometry": {"coordinates":[-2.4137420654,43.1195220947],"type":"Point"}
}