{
  "type": "Feature",
  "properties": {
    "addr:full":"Praz Alcalde Jose Mosquera Diaz, 5 Arteixo A Coru\u00f1a 15142",
    "addr:housenumber":"5",
    "addr:postcode":"15142",
    "addr:street":"Praz Alcalde Jose Mosquera Diaz;Corun\u0303A",
    "iso:country":"ES",
    "sg:address":"Praz Alcalde Jose Mosquera Diaz, 5",
    "sg:city":"Arteixo",
    "sg:orig_category":"Papeler\u00cdas, Librer\u00cdas",
    "sg:phone":"+34 981 64 16 03",
    "sg:postcode":"15142",
    "sg:province":"A Coru\u00f1a",
    "sg:website":"www.carlin.es",
    "wof:name":"Villasonte Y Mosquera S.l.",
    "wof:placetype":"venue"
},
  "geometry": {"coordinates":[-8.5071649551,43.3053398132],"type":"Point"}
}