{
  "type": "Feature",
  "properties": {
    "iso:country":"ES",
    "sg:address":"Avda Juan Molina, S/n",
    "sg:city":"Villanueva Del Rosario",
    "sg:orig_category":"Guarder\u00cdas",
    "sg:phone":"+34 952 74 28 88",
    "sg:postcode":"29312",
    "sg:province":"M\u00e1laga",
    "wof:name":"Ayuntamiento De Villanueva Del Rosario",
    "wof:placetype":"venue"
},
  "geometry": {"coordinates":[-4.367143631,36.9987716675],"type":"Point"}
}