{
  "type": "Feature",
  "properties": {
    "iso:country":"ES",
    "sg:address":"Plaz Abadia, 2",
    "sg:city":"Rincon Soto",
    "sg:orig_category":"Aparatos E Instalaci\u00d3n De Regad\u00cdos",
    "sg:phone":"+34 941 16 04 99",
    "sg:postcode":"26550",
    "sg:province":"La Rioja",
    "wof:name":"Comunidad De Regantes Del Rio Ebro De Rincon De Soto",
    "wof:placetype":"venue"
},
  "geometry": {"coordinates":[-1.8486180305,42.2304801941],"type":"Point"}
}