{
  "type": "Feature",
  "properties": {
    "iso:country":"ES",
    "sg:address":"La Ermita, 20",
    "sg:city":"Virgen Camino",
    "sg:orig_category":"Calefacci\u00d3n Central: Material (fabricaci\u00d3n, Al Por Mayor)",
    "sg:phone":"+34 987 30 21 32",
    "sg:postcode":"24198",
    "sg:province":"Le\u00f3n",
    "wof:name":"Representaciones Tomillo S.l.",
    "wof:placetype":"venue"
},
  "geometry": {"coordinates":[-5.6438441277,42.5845489502],"type":"Point"}
}