{
  "type": "Feature",
  "properties": {
    "addr:full":"Avda Castilla (de), 32 Poligono De San Fernando De Henares Madrid 28830",
    "addr:housenumber":"32",
    "addr:postcode":"28830",
    "addr:street":"Avda Castilla De",
    "iso:country":"ES",
    "sg:address":"Avda Castilla (de), 32",
    "sg:city":"Poligono De San Fernando De Henares",
    "sg:orig_category":"Encuadernaci\u00d3n E Impresi\u00d3n De Folletos",
    "sg:phone":"+34 916 75 62 86",
    "sg:postcode":"28830",
    "sg:province":"Madrid",
    "wof:name":"F. Soriano S. A.",
    "wof:placetype":"venue"
},
  "geometry": {"coordinates":[-3.5366938114,40.4255332947],"type":"Point"}
}