{
  "type": "Feature",
  "properties": {
    "iso:country":"ES",
    "sg:address":"Av Estatut, 22",
    "sg:city":"Rubi",
    "sg:orig_category":"Colchones (fabricaci\u00d3n, Al Por Mayor, Al Por Menor)",
    "sg:phone":"+34 935 87 40 39",
    "sg:postcode":"08191",
    "sg:province":"Barcelona",
    "wof:name":"Gonzalez Rodriguez Teresa",
    "wof:placetype":"venue"
},
  "geometry": {"coordinates":[2.0400760174,41.4878845215],"type":"Point"}
}