{
  "type": "Feature",
  "properties": {
    "addr:full":"Avda Rafael Alberti, S/n Madrid Madrid 28038",
    "addr:housenumber":"s / n",
    "addr:postcode":"28038",
    "addr:street":"Avda Rafael Alberti",
    "iso:country":"ES",
    "sg:address":"Avda Rafael Alberti, S/n",
    "sg:city":"Madrid",
    "sg:orig_category":"Supermercados Y Hipermercados",
    "sg:phone":"+34 913 80 61 45",
    "sg:postcode":"28038",
    "sg:province":"Madrid",
    "wof:name":"Distribuidora Internacional De Alimentacion S.a.",
    "wof:placetype":"venue"
},
  "geometry": {"coordinates":[-3.637319088,40.3920860291],"type":"Point"}
}