{
  "type": "Feature",
  "properties": {
    "iso:country":"ES",
    "sg:address":"Calle de General Primo De Rivera, 6",
    "sg:city":"Algeciras",
    "sg:orig_category":"Promotores Constructores",
    "sg:phone":"+34 956 66 85 02",
    "sg:postcode":"11201",
    "sg:province":"C\u00e1diz",
    "wof:name":"Cortijo De Vides S.a.",
    "wof:placetype":"venue"
},
  "geometry": {"coordinates":[-5.4480490685,36.1313285828],"type":"Point"}
}