{
  "type": "Feature",
  "properties": {
    "iso:country":"ES",
    "sg:address":"Carrer de Roger De Flor, 140",
    "sg:city":"Barcelona",
    "sg:orig_category":"Carnicer\u00cdas, Carnicer\u00cdas",
    "sg:phone":"+34 932 45 74 90",
    "sg:postcode":"08013",
    "sg:province":"Barcelona",
    "wof:name":"Gonzalez Zamorano Rafaela",
    "wof:placetype":"venue"
},
  "geometry": {"coordinates":[2.1758480072,41.3965454102],"type":"Point"}
}