{
  "type": "Feature",
  "properties": {
    "addr:full":"Calle de Ruiz De Alda, 10 Palmas De Gran Canaria Las Palmas 35007",
    "addr:housenumber":"10",
    "addr:postcode":"35007",
    "addr:street":"Calle De Ruiz De Alda",
    "iso:country":"ES",
    "sg:address":"Calle de Ruiz De Alda, 10",
    "sg:city":"Palmas De Gran Canaria",
    "sg:orig_category":"Peluqueros: De Se\u00d1oras",
    "sg:phone":"+34 928 22 02 83",
    "sg:postcode":"35007",
    "sg:province":"Las Palmas",
    "wof:name":"Salon Primi S.l.",
    "wof:placetype":"venue"
},
  "geometry": {"coordinates":[-15.4301347733,28.1357154846],"type":"Point"}
}