{
  "type": "Feature",
  "properties": {
    "iso:country":"ES",
    "sg:address":"Calle de Patricio Ferrandiz, 37",
    "sg:city":"Denia",
    "sg:orig_category":"Comercio, Reparaci\u00d3n De Motocicletas, Bicicletas Y Piezas Sueltas",
    "sg:phone":"+34 965 78 81 97",
    "sg:postcode":"03700",
    "sg:province":"Alicante",
    "wof:name":"Motos Quirro C.b.",
    "wof:placetype":"venue"
},
  "geometry": {"coordinates":[0.108198002,38.8386268616],"type":"Point"}
}