{
  "type": "Feature",
  "properties": {
    "addr:full":"Calle de Esperanza, S/n Alcantarilla Murcia 30820",
    "addr:housenumber":"s",
    "addr:postcode":"30820",
    "addr:street":"Calle De Esperanza;/ N",
    "iso:country":"ES",
    "sg:address":"Calle de Esperanza, S/n",
    "sg:city":"Alcantarilla",
    "sg:orig_category":"M\u00c1quinas Para Recortar Y Pegar",
    "sg:phone":"+34 968 80 77 54",
    "sg:postcode":"30820",
    "sg:province":"Murcia",
    "wof:name":"Taller Industrial Javija S.l.",
    "wof:placetype":"venue"
},
  "geometry": {"coordinates":[-1.2174040079,37.9738616943],"type":"Point"}
}