{
  "type": "Feature",
  "properties": {
    "iso:country":"ES",
    "sg:address":"Calle de Victor De Los Rios, S/n",
    "sg:city":"Linares",
    "sg:orig_category":"Alimentaci\u00d3n General (al Por Menor)",
    "sg:phone":"+34 953 69 49 93",
    "sg:postcode":"23700",
    "sg:province":"Ja\u00e9n",
    "wof:name":"Pedarocar S.l.u.",
    "wof:placetype":"venue"
},
  "geometry": {"coordinates":[-3.6295189857,38.0956916809],"type":"Point"}
}