{
  "type": "Feature",
  "properties": {
    "iso:country":"ES",
    "sg:address":"Carrer de Jordi De Sant Jordi, 39",
    "sg:city":"Barcelona",
    "sg:orig_category":"Bares, Piano",
    "sg:phone":"+34 933 52 35 56",
    "sg:postcode":"08027",
    "sg:province":"Barcelona",
    "wof:name":"Fernandez Martinez Manuel",
    "wof:placetype":"venue"
},
  "geometry": {"coordinates":[2.1829030514,41.4230041504],"type":"Point"}
}