{
  "type": "Feature",
  "properties": {
    "iso:country":"ES",
    "sg:address":"Calle de Mantuano, 6",
    "sg:city":"Madrid",
    "sg:orig_category":"Bazares, Art\u00cdculos De Limpieza Y De Cocina (al Por Menor)",
    "sg:phone":"+34 914 16 25 24",
    "sg:postcode":"28002",
    "sg:province":"Madrid",
    "wof:name":"Qiu  Aifen",
    "wof:placetype":"venue"
},
  "geometry": {"coordinates":[-3.6743309498,40.4450569153],"type":"Point"}
}