{
  "type": "Feature",
  "properties": {
    "iso:country":"ES",
    "sg:address":"Plaz Urdanibia, 2",
    "sg:city":"Irun",
    "sg:orig_category":"Molduras, Junquillos, Listones Y Molduras Perforadas",
    "sg:phone":"+34 943 62 16 59",
    "sg:postcode":"20304",
    "sg:province":"Guip\u00f9zcoa",
    "wof:name":"Cafe Bad Depor S.l.",
    "wof:placetype":"venue"
},
  "geometry": {"coordinates":[-1.7865840197,43.3377761841],"type":"Point"}
}