{
  "type": "Feature",
  "properties": {
    "iso:country":"ES",
    "sg:address":"Calle de Andalucia, 2",
    "sg:city":"Ajalvir",
    "sg:orig_category":"Bibliotecas, Mediatecas",
    "sg:phone":"+34 918 84 47 30",
    "sg:postcode":"28864",
    "sg:province":"Madrid",
    "wof:name":"Custodia De Archivo Documental S.l.",
    "wof:placetype":"venue"
},
  "geometry": {"coordinates":[-3.4908397198,40.5315971375],"type":"Point"}
}