{
  "type": "Feature",
  "properties": {
    "addr:full":"A (p. I. La Nevera), S/n Mendavia Navarra 31587",
    "addr:housenumber":"s / n",
    "addr:postcode":"31587",
    "iso:country":"ES",
    "sg:address":"A (p. I. La Nevera), S/n",
    "sg:city":"Mendavia",
    "sg:orig_category":"M\u00c1rmoles, Granitos Y Piedras Naturales",
    "sg:phone":"+34 948 69 53 00",
    "sg:postcode":"31587",
    "sg:province":"Navarra",
    "wof:name":"Granitos Mendavia S.l.",
    "wof:placetype":"venue"
},
  "geometry": {"coordinates":[-2.2147390842,42.4529495239],"type":"Point"}
}