{
  "type": "Feature",
  "properties": {
    "iso:country":"ES",
    "sg:address":"Calle de San Vicente, 75",
    "sg:city":"Alginet",
    "sg:orig_category":"Fabricaci\u00d3n De Pastas Alimentarias",
    "sg:phone":"+34 961 75 02 70",
    "sg:postcode":"46230",
    "sg:province":"Valencia",
    "wof:name":"Lozano Bosch Enrique",
    "wof:placetype":"venue"
},
  "geometry": {"coordinates":[-0.4658969939,39.2606582642],"type":"Point"}
}