{
  "type": "Feature",
  "properties": {
    "iso:country":"ES",
    "sg:address":"Calle de Oca\u00d1a, 12",
    "sg:city":"Madrid",
    "sg:orig_category":"Locales Y Clases De Danza",
    "sg:phone":"+34 915 25 70 05",
    "sg:postcode":"28047",
    "sg:province":"Madrid",
    "wof:name":"Terpolis S.l.",
    "wof:placetype":"venue"
},
  "geometry": {"coordinates":[-3.7536730766,40.3840103149],"type":"Point"}
}