{
  "type": "Feature",
  "properties": {
    "addr:full":"Calle de Joaquin Costa, 10 Teruel Teruel 44001",
    "addr:housenumber":"10",
    "addr:postcode":"44001",
    "addr:street":"Calle De Joaquin Costa",
    "iso:country":"ES",
    "sg:address":"Calle de Joaquin Costa, 10",
    "sg:city":"Teruel",
    "sg:orig_category":"Material Y Accesorios Para Bisuter\u00cda Y Joyer\u00cda",
    "sg:phone":"+34 978 61 23 47",
    "sg:postcode":"44001",
    "sg:province":"Teruel",
    "wof:name":"Joyeria Fabregat S.l.",
    "wof:placetype":"venue"
},
  "geometry": {"coordinates":[-1.107656002,40.341217041],"type":"Point"}
}