{
  "type": "Feature",
  "properties": {
    "iso:country":"ES",
    "sg:address":"Poli Aldea Moret, S/n",
    "sg:city":"Caceres",
    "sg:orig_category":"Agentes, Concesionarios Y Sucursales De Camiones Y Veh\u00cdculos Industriales",
    "sg:phone":"+34 927 23 35 34",
    "sg:postcode":"10003",
    "sg:province":"C\u00e1ceres",
    "wof:name":"Extreme\u00f1a De Camiones S.a.l.",
    "wof:placetype":"venue"
},
  "geometry": {"coordinates":[-6.3720030785,39.4745063782],"type":"Point"}
}