{
  "type": "Feature",
  "properties": {
    "addr:full":"Carr Sangenis Bertran, 5 Lleida Lleida 25003",
    "addr:housenumber":"5",
    "addr:postcode":"25003",
    "addr:street":"Carr Sangenis Bertran",
    "iso:country":"ES",
    "sg:address":"Carr Sangenis Bertran, 5",
    "sg:city":"Lleida",
    "sg:orig_category":"Centros Empresariales",
    "sg:phone":"+34 973 28 22 87",
    "sg:postcode":"25003",
    "sg:province":"Lleida",
    "wof:name":"Erill Serveis Lleida S.l.",
    "wof:placetype":"venue"
},
  "geometry": {"coordinates":[0.6141350269,41.6134376526],"type":"Point"}
}