{
  "type": "Feature",
  "properties": {
    "addr:full":"Calle de Santomera, 23 Totana Murcia 30850",
    "addr:housenumber":"23",
    "addr:postcode":"30850",
    "addr:street":"Calle De Santomera",
    "iso:country":"ES",
    "sg:address":"Calle de Santomera, 23",
    "sg:city":"Totana",
    "sg:orig_category":"Ropa Para Ni\u00d1os (al Por Menor)",
    "sg:phone":"+34 968 42 50 43",
    "sg:postcode":"30850",
    "sg:province":"Murcia",
    "wof:name":"Garcia Gallardo Francisco",
    "wof:placetype":"venue"
},
  "geometry": {"coordinates":[-1.4944629669,37.7747459412],"type":"Point"}
}