{
  "type": "Feature",
  "properties": {
    "addr:full":"Calle de Gonzalo Chacon (de), 7 Aranjuez Madrid 28300",
    "addr:housenumber":"7",
    "addr:postcode":"28300",
    "addr:street":"Calle De Gonzalo Chacon De",
    "iso:country":"ES",
    "sg:address":"Calle de Gonzalo Chacon (de), 7",
    "sg:city":"Aranjuez",
    "sg:orig_category":"Art\u00cdculos De Limpieza Y De Cocina (fabricaci\u00d3n, Al Por Mayor)",
    "sg:phone":"+34 918 09 02 15",
    "sg:postcode":"28300",
    "sg:province":"Madrid",
    "wof:name":"Industrias Quimicas Induquim S.l.",
    "wof:placetype":"venue"
},
  "geometry": {"coordinates":[-3.6174287796,40.0206260681],"type":"Point"}
}