{
  "type": "Feature",
  "properties": {
    "iso:country":"ES",
    "sg:address":"Calle de Farmaceutico Pedro Rivero, 30",
    "sg:city":"Palmas De Gran Canaria",
    "sg:orig_category":"Peluquer\u00cdas, Peluquer\u00cda Mixta",
    "sg:phone":"+34 928 25 28 20",
    "sg:postcode":"35013",
    "sg:province":"Las Palmas",
    "wof:name":"Ramirez Noval Maria Angeles",
    "wof:placetype":"venue"
},
  "geometry": {"coordinates":[-15.4344911575,28.1039333344],"type":"Point"}
}