{
  "type": "Feature",
  "properties": {
    "addr:full":"Bard Roman Perez, S/n Isla Cristina Huelva 21410",
    "addr:postcode":"21410",
    "addr:street":"S / N",
    "iso:country":"ES",
    "sg:address":"Bard Roman Perez, S/n",
    "sg:city":"Isla Cristina",
    "sg:orig_category":"Construcciones Navales Y Fluviales",
    "sg:phone":"+34 959 33 12 21",
    "sg:postcode":"21410",
    "sg:province":"Huelva",
    "wof:name":"Varaderos De Isla Cristina S.l.",
    "wof:placetype":"venue"
},
  "geometry": {"coordinates":[-7.329228878,37.208114624],"type":"Point"}
}