{
  "type": "Feature",
  "properties": {
    "addr:full":"Calle de Juan Xxiii, 22 Chantada Lugo 27500",
    "addr:housenumber":"22",
    "addr:postcode":"27500",
    "addr:street":"Calle De Juan Xxiii",
    "iso:country":"ES",
    "sg:address":"Calle de Juan Xxiii, 22",
    "sg:city":"Chantada",
    "sg:orig_category":"Ropa Para Se\u00d1oras Y Caballeros (al Por Menor)",
    "sg:phone":"+34 982 44 18 01",
    "sg:postcode":"27500",
    "sg:province":"Lugo",
    "wof:name":"Moda Albers C.b.",
    "wof:placetype":"venue"
},
  "geometry": {"coordinates":[-7.7692542076,42.6085395813],"type":"Point"}
}