{
  "type": "Feature",
  "properties": {
    "addr:full":"Calle de Modesto Lafuente, 4 Aguilar Campoo Palencia 34800",
    "addr:housenumber":"4",
    "addr:postcode":"34800",
    "addr:street":"Calle De Modesto Lafuente",
    "iso:country":"ES",
    "sg:address":"Calle de Modesto Lafuente, 4",
    "sg:city":"Aguilar Campoo",
    "sg:orig_category":"Abogados",
    "sg:phone":"+34 979 12 21 99",
    "sg:postcode":"34800",
    "sg:province":"Palencia",
    "wof:name":"Banco Bilbao Vizcaya Argentaria S.a.",
    "wof:placetype":"venue"
},
  "geometry": {"coordinates":[-4.2623271942,42.7942008972],"type":"Point"}
}