{
  "type": "Feature",
  "properties": {
    "iso:country":"ES",
    "sg:address":"El Rosario, S/n",
    "sg:city":"Elviria",
    "sg:orig_category":"Promotores Constructores",
    "sg:phone":"+34 952 83 07 22",
    "sg:postcode":"29604",
    "sg:province":"M\u00e1laga",
    "wof:name":"Alvarez Garmon Maximo",
    "wof:placetype":"venue"
},
  "geometry": {"coordinates":[-4.8064742088,36.5072250366],"type":"Point"}
}