{
  "type": "Feature",
  "properties": {
    "iso:country":"ES",
    "sg:address":"Plaz Mayor, 3",
    "sg:city":"Matamala Almazan",
    "sg:orig_category":"Molduras, Junquillos, Listones Y Molduras Perforadas",
    "sg:phone":"+34 975 31 24 01",
    "sg:postcode":"42211",
    "sg:province":"Soria",
    "wof:name":"Medel Lopez Yolanda",
    "wof:placetype":"venue"
},
  "geometry": {"coordinates":[-2.6415820122,41.5060691833],"type":"Point"}
}