{
  "type": "Feature",
  "properties": {
    "addr:full":"Carrer de Pujades, 426 Barcelona Barcelona 08019",
    "addr:housenumber":"426",
    "addr:postcode":"08019",
    "addr:street":"Carrer De Pujades",
    "iso:country":"ES",
    "sg:address":"Carrer de Pujades, 426",
    "sg:city":"Barcelona",
    "sg:orig_category":"Molduras, Junquillos, Listones Y Molduras Perforadas",
    "sg:phone":"+34 933 07 35 31",
    "sg:postcode":"08019",
    "sg:province":"Barcelona",
    "wof:name":"Melo Velazquez Juan Manuel",
    "wof:placetype":"venue"
},
  "geometry": {"coordinates":[2.2141449451,41.4116287231],"type":"Point"}
}