{
  "type": "Feature",
  "properties": {
    "iso:country":"ES",
    "sg:address":"Pl Josep Maluquer I Salvador, 10",
    "sg:city":"Granollers",
    "sg:orig_category":"M\u00c9dicos: Estomatolog\u00cda",
    "sg:phone":"+34 938 70 76 73",
    "sg:postcode":"08401",
    "sg:province":"Barcelona",
    "sg:website":"www.pruiz.com",
    "wof:name":"Ruiz Mirete Pedro",
    "wof:placetype":"venue"
},
  "geometry": {"coordinates":[2.2888569832,41.6090736389],"type":"Point"}
}