{
  "type": "Feature",
  "properties": {
    "iso:country":"ES",
    "sg:address":"Carr Bellcaire, S/n",
    "sg:city":"Vallfogona Balaguer",
    "sg:orig_category":"Molduras, Junquillos, Listones Y Molduras Perforadas",
    "sg:phone":"+34 973 43 22 29",
    "sg:postcode":"25680",
    "sg:province":"Lleida",
    "wof:name":"Gonzalez Hernandez Maria",
    "wof:placetype":"venue"
},
  "geometry": {"coordinates":[0.8158649802,41.7522468567],"type":"Point"}
}