{
  "type": "Feature",
  "properties": {
    "addr:full":"Carrer de Dos De Maig, 225 Barcelona Barcelona 08013",
    "addr:housenumber":"225",
    "addr:postcode":"08013",
    "addr:street":"Carrer De Dos De Maig",
    "iso:country":"ES",
    "sg:address":"Carrer de Dos De Maig, 225",
    "sg:city":"Barcelona",
    "sg:orig_category":"Compraventa De Antig\u00dcedades",
    "sg:phone":"+34 932 47 15 71",
    "sg:postcode":"08013",
    "sg:province":"Barcelona",
    "wof:name":"Tobajas Purroy Antonio",
    "wof:placetype":"venue"
},
  "geometry": {"coordinates":[2.1826570034,41.4064292908],"type":"Point"}
}