{
  "type": "Feature",
  "properties": {
    "iso:country":"ES",
    "sg:address":"Av Gaspar Bennazar, 29",
    "sg:city":"Palma",
    "sg:orig_category":"Molduras, Junquillos, Listones Y Molduras Perforadas",
    "sg:phone":"+34 971 75 15 54",
    "sg:postcode":"07004",
    "sg:province":"Islas Baleares",
    "wof:name":"Rodriguez Serrano Juan Antonio",
    "wof:placetype":"venue"
},
  "geometry": {"coordinates":[2.6592609882,39.5824317932],"type":"Point"}
}