{
  "type": "Feature",
  "properties": {
    "addr:full":"Calle de Traviesa, 49 Cubo De Don Sancho Salamanca 37281",
    "addr:housenumber":"49",
    "addr:postcode":"37281",
    "addr:street":"Calle De Traviesa",
    "iso:country":"ES",
    "sg:address":"Calle de Traviesa, 49",
    "sg:city":"Cubo De Don Sancho",
    "sg:orig_category":"Tintorer\u00cdas, Limpieza En Seco",
    "sg:phone":"+34 923 44 30 28",
    "sg:postcode":"37281",
    "sg:province":"Salamanca",
    "wof:name":"Picado Rodriguez Alberto",
    "wof:placetype":"venue"
},
  "geometry": {"coordinates":[-6.3049788475,40.8913230896],"type":"Point"}
}