{
  "type": "Feature",
  "properties": {
    "iso:country":"ES",
    "sg:address":"Calle de Francisco Bastarreche, 8",
    "sg:city":"Marin",
    "sg:orig_category":"Ropa Para Se\u00d1oras Y Caballeros (al Por Menor)",
    "sg:phone":"+34 986 89 18 58",
    "sg:postcode":"36900",
    "sg:province":"Pontevedra",
    "wof:name":"Via Pelini S.l.",
    "wof:placetype":"venue"
},
  "geometry": {"coordinates":[-8.7045783997,42.390712738],"type":"Point"}
}