{
  "type": "Feature",
  "properties": {
    "iso:country":"ES",
    "sg:address":"Sta. Magdalena, 7",
    "sg:city":"Serinya",
    "sg:orig_category":"Deportes Y Programas De Aventura",
    "sg:phone":"+34 972 59 37 04",
    "sg:postcode":"17852",
    "sg:province":"Girona",
    "wof:name":"Vives Ochoa De Echaguen Mario",
    "wof:placetype":"venue"
},
  "geometry": {"coordinates":[2.7442674637,42.1704101562],"type":"Point"}
}