{
  "type": "Feature",
  "properties": {
    "addr:full":"Plaz Espa\u00d1a, S/n Figarol Navarra 31311",
    "addr:housenumber":"s",
    "addr:postcode":"31311",
    "addr:street":"Plaz Espan\u0303A;/ N Figarol Navarra",
    "iso:country":"ES",
    "sg:address":"Plaz Espa\u00d1a, S/n",
    "sg:city":"Figarol",
    "sg:orig_category":"Iglesia Cat\u00d3lica",
    "sg:phone":"+34 948 72 60 13",
    "sg:postcode":"31311",
    "sg:province":"Navarra",
    "wof:name":"Arzobispado De Pamplona",
    "wof:placetype":"venue"
},
  "geometry": {"coordinates":[-1.3692309856,42.350643158],"type":"Point"}
}