{
  "type": "Feature",
  "properties": {
    "addr:full":"Pg Doctor Letamendi, 60 Barri Maritim Sector Sanatori Tarragona 43700",
    "addr:housenumber":"60",
    "addr:postcode":"43700",
    "addr:street":"Pg Doctor Letamendi;Maritim",
    "iso:country":"ES",
    "sg:address":"Pg Doctor Letamendi, 60",
    "sg:city":"Barri Maritim Sector Sanatori",
    "sg:orig_category":"Perfumer\u00cda Y Cosm\u00c9tica (fabricaci\u00d3n, Al Por Mayor)",
    "sg:phone":"+34 977 69 43 14",
    "sg:postcode":"43700",
    "sg:province":"Tarragona",
    "wof:name":"Bermudez Gonzalez Fuensanta",
    "wof:placetype":"venue"
},
  "geometry": {"coordinates":[1.5381799936,41.2216491699],"type":"Point"}
}