{
  "type": "Feature",
  "properties": {
    "addr:full":"Avda Nuestra Se\u00d1ora De Valvanera, 110 Madrid Madrid 28025",
    "addr:housenumber":"110",
    "addr:postcode":"28025",
    "addr:street":"Avda Nuestra Sen\u0303Ora De Valvanera",
    "iso:country":"ES",
    "sg:address":"Avda Nuestra Se\u00d1ora De Valvanera, 110",
    "sg:city":"Madrid",
    "sg:orig_category":"Inmobiliaria (agencias)",
    "sg:phone":"+34 914 62 69 72",
    "sg:postcode":"28025",
    "sg:province":"Madrid",
    "wof:name":"Meno Limia Maria Del Carmen",
    "wof:placetype":"venue"
},
  "geometry": {"coordinates":[-3.7396578789,40.3922233582],"type":"Point"}
}