{
  "type": "Feature",
  "properties": {
    "addr:full":"Calle de Vereda De Chapatales, 3 San Jose Rinconada Sevilla 41300",
    "addr:housenumber":"3",
    "addr:postcode":"41300",
    "addr:street":"Calle De Vereda De Chapatales",
    "iso:country":"ES",
    "sg:address":"Calle de Vereda De Chapatales, 3",
    "sg:city":"San Jose Rinconada",
    "sg:orig_category":"Pod\u00d3logos: Pedicuros",
    "sg:phone":"+34 954 79 32 89",
    "sg:postcode":"41300",
    "sg:province":"Sevilla",
    "wof:name":"Galindo Toucedo Inmaculada",
    "wof:placetype":"venue"
},
  "geometry": {"coordinates":[-5.9507889748,37.4823112488],"type":"Point"}
}