{
  "type": "Feature",
  "properties": {
    "iso:country":"ES",
    "sg:address":"Avda Garcia Barbon, 80",
    "sg:city":"Vigo",
    "sg:orig_category":"M\u00c9dicos: Cirug\u00cda Urol\u00d3gica",
    "sg:phone":"+34 986 22 01 12",
    "sg:postcode":"36201",
    "sg:province":"Pontevedra",
    "wof:name":"Figueiredo Godoy Luis",
    "wof:placetype":"venue"
},
  "geometry": {"coordinates":[-8.7099781036,42.238079071],"type":"Point"}
}