{
  "type": "Feature",
  "properties": {
    "addr:full":"Calle de Santisima Trinidad, 5 Maracena Granada 18200",
    "addr:housenumber":"5",
    "addr:postcode":"18200",
    "addr:street":"Calle De Santisima Trinidad",
    "iso:country":"ES",
    "sg:address":"Calle de Santisima Trinidad, 5",
    "sg:city":"Maracena",
    "sg:orig_category":"Empresas De Demolici\u00d3n",
    "sg:phone":"+34 958 41 05 54",
    "sg:postcode":"18200",
    "sg:province":"Granada",
    "wof:name":"Trasportes Y Excavaciones Marasena Sl",
    "wof:placetype":"venue"
},
  "geometry": {"coordinates":[-3.6351697445,37.2077026367],"type":"Point"}
}