{
  "type": "Feature",
  "properties": {
    "addr:full":"Calle de Sixta Barrenetxea, 26 Galdakao Vizcaya 48960",
    "addr:housenumber":"26",
    "addr:postcode":"48960",
    "addr:street":"Calle De Sixta Barrenetxea",
    "iso:country":"ES",
    "sg:address":"Calle de Sixta Barrenetxea, 26",
    "sg:city":"Galdakao",
    "sg:orig_category":"Promotores Constructores",
    "sg:phone":"+34 944 56 84 33",
    "sg:postcode":"48960",
    "sg:province":"Vizcaya",
    "wof:name":"Construcciones Zumair,s.l.",
    "wof:placetype":"venue"
},
  "geometry": {"coordinates":[-2.8557429314,43.233455658],"type":"Point"}
}