{
  "type": "Feature",
  "properties": {
    "iso:country":"ES",
    "sg:address":"Avda Pintor Joaquin Sorolla, 11",
    "sg:city":"Malaga",
    "sg:orig_category":"Restaurantes",
    "sg:phone":"+34 952 21 95 70",
    "sg:postcode":"29016",
    "sg:province":"M\u00e1laga",
    "wof:name":"Guillamundegui  Bernardo Alberto",
    "wof:placetype":"venue"
},
  "geometry": {"coordinates":[-4.3963122368,36.7234611511],"type":"Point"}
}