{
  "type": "Feature",
  "properties": {
    "iso:country":"ES",
    "sg:address":"Av Alcudia, 16",
    "sg:city":"Inca",
    "sg:orig_category":"Peluquer\u00cdas, Peluquer\u00cda Mixta",
    "sg:phone":"+34 971 50 30 26",
    "sg:postcode":"07300",
    "sg:province":"Islas Baleares",
    "wof:name":"Perez Paniza Yolanda",
    "wof:placetype":"venue"
},
  "geometry": {"coordinates":[2.9143409729,39.7227516174],"type":"Point"}
}