{
  "type": "Feature",
  "properties": {
    "addr:full":"Rua Bouza (da), 5 Lugo Lugo 27002",
    "addr:housenumber":"5",
    "addr:postcode":"27002",
    "addr:street":"Rua Bouza Da",
    "iso:country":"ES",
    "sg:address":"Rua Bouza (da), 5",
    "sg:city":"Lugo",
    "sg:orig_category":"Agencias Y Agentes Comerciales, Representantes",
    "sg:phone":"+34 982 22 20 26",
    "sg:postcode":"27002",
    "sg:province":"Lugo",
    "wof:name":"Lara Mara\u00f1on Carmen",
    "wof:placetype":"venue"
},
  "geometry": {"coordinates":[-7.5557470322,42.9948387146],"type":"Point"}
}