{
  "type": "Feature",
  "properties": {
    "iso:country":"ES",
    "sg:address":"Calle de Gremio De Los Canteros (del), S/n",
    "sg:city":"Hontoria",
    "sg:orig_category":"Semiller\u00cdas",
    "sg:phone":"+34 921 44 22 99",
    "sg:postcode":"40195",
    "sg:province":"Segovia",
    "wof:name":"Viveros Hontoria S.l.",
    "wof:placetype":"venue"
},
  "geometry": {"coordinates":[-4.1104226112,40.9057273865],"type":"Point"}
}