{
  "type": "Feature",
  "properties": {
    "iso:country":"ES",
    "sg:address":"Avda Tirajana (de), 37",
    "sg:city":"Playa Del Ingles",
    "sg:orig_category":"M\u00c9dicos: Estomatolog\u00cda",
    "sg:phone":"+34 928 76 51 21",
    "sg:postcode":"35100",
    "sg:province":"Las Palmas",
    "wof:name":"Navarro Alonso Jose Manuel",
    "wof:placetype":"venue"
},
  "geometry": {"coordinates":[-15.5769987106,27.7503967285],"type":"Point"}
}