{
  "type": "Feature",
  "properties": {
    "addr:full":"Ctra. Madrid, S/n Almazan Soria 42200",
    "addr:housenumber":"s / n",
    "addr:postcode":"42200",
    "addr:street":"Ctra. Madrid",
    "iso:country":"ES",
    "sg:address":"Ctra. Madrid, S/n",
    "sg:city":"Almazan",
    "sg:orig_category":"Material Y Herramientas Agr\u00cdcolas",
    "sg:phone":"+34 975 30 02 36",
    "sg:postcode":"42200",
    "sg:province":"Soria",
    "sg:website":"www.mateogrupo.com",
    "wof:name":"Hermanos Mateo Lorenzo S.a.",
    "wof:placetype":"venue"
},
  "geometry": {"coordinates":[-2.5288739204,41.4812850952],"type":"Point"}
}