{
  "type": "Feature",
  "properties": {
    "iso:country":"ES",
    "sg:address":"Cra Valldemossa, 45",
    "sg:city":"Palma",
    "sg:orig_category":"M\u00c1rmoles, Granitos Y Piedras Naturales",
    "sg:phone":"+34 971 75 25 97",
    "sg:postcode":"07010",
    "sg:province":"Islas Baleares",
    "wof:name":"Garrigueta S.l.",
    "wof:placetype":"venue"
},
  "geometry": {"coordinates":[2.6481339931,39.5917358398],"type":"Point"}
}