{
  "type": "Feature",
  "properties": {
    "iso:country":"ES",
    "sg:address":"Carrer de Torras I Pujalt, 12",
    "sg:city":"Barcelona",
    "sg:orig_category":"Ense\u00d1ante, Direcci\u00d3n",
    "sg:phone":"+34 934 17 23 15",
    "sg:postcode":"08022",
    "sg:province":"Barcelona",
    "wof:name":"Papio Richol Isidro",
    "wof:placetype":"venue"
},
  "geometry": {"coordinates":[2.1346199512,41.4011154175],"type":"Point"}
}