{
  "type": "Feature",
  "properties": {
    "addr:full":"Carrer de Lloret De Mar, 31 Barcelona Barcelona 08032",
    "addr:housenumber":"31",
    "addr:postcode":"08032",
    "addr:street":"Carrer De Lloret De Mar",
    "iso:country":"ES",
    "sg:address":"Carrer de Lloret De Mar, 31",
    "sg:city":"Barcelona",
    "sg:orig_category":"Papeler\u00cdas, Librer\u00cdas",
    "sg:phone":"+34 934 07 09 80",
    "sg:postcode":"08032",
    "sg:province":"Barcelona",
    "wof:name":"Rodriguez Garcia Magdalena",
    "wof:placetype":"venue"
},
  "geometry": {"coordinates":[2.1550600529,41.4336738586],"type":"Point"}
}