{
  "type": "Feature",
  "properties": {
    "iso:country":"ES",
    "sg:address":"Av Roma, 18",
    "sg:city":"Cerdanyola Valles",
    "sg:orig_category":"Inform\u00c1tica: Material Y Suministros",
    "sg:phone":"+34 935 82 15 00",
    "sg:postcode":"08...",
    "sg:province":"Barcelona",
    "sg:website":"www.epson.es",
    "wof:name":"Epson Iberica S.a.",
    "wof:placetype":"venue"
},
  "geometry": {"coordinates":[2.1279840469,41.4895439148],"type":"Point"}
}