{
  "type": "Feature",
  "properties": {
    "addr:full":"Pl Nadal, 13 Barcelona Barcelona 08030",
    "addr:housenumber":"13",
    "addr:postcode":"08030",
    "addr:street":"Pl Nadal",
    "iso:country":"ES",
    "sg:address":"Pl Nadal, 13",
    "sg:city":"Barcelona",
    "sg:orig_category":"Audiovisuales: Material Y Accesorios (al Por Menor)",
    "sg:phone":"+34 933 11 41 02",
    "sg:postcode":"08030",
    "sg:province":"Barcelona",
    "sg:website":"www.dat-audiostars.com",
    "wof:name":"Audio Stars S. A.",
    "wof:placetype":"venue"
},
  "geometry": {"coordinates":[2.1885643005,41.4286231995],"type":"Point"}
}