{
  "type": "Feature",
  "properties": {
    "addr:full":"C/ Villa Pepa, 23 Ferreries Islas Baleares 07750",
    "addr:housenumber":"23",
    "addr:postcode":"07750",
    "addr:street":"C / Villa Pepa",
    "iso:country":"ES",
    "sg:address":"C/ Villa Pepa, 23",
    "sg:city":"Ferreries",
    "sg:orig_category":"Abogados",
    "sg:phone":"+34 971 37 36 27",
    "sg:postcode":"07750",
    "sg:province":"Islas Baleares",
    "wof:name":"Meakins  Vincent",
    "wof:placetype":"venue"
},
  "geometry": {"coordinates":[4.0133800507,39.9862594604],"type":"Point"}
}