{
  "type": "Feature",
  "properties": {
    "addr:full":"Carr Francesc De Borja Moll, 11 Binissalem Islas Baleares 07350",
    "addr:housenumber":"11",
    "addr:postcode":"07350",
    "addr:street":"Carr Francesc De Borja Moll",
    "iso:country":"ES",
    "sg:address":"Carr Francesc De Borja Moll, 11",
    "sg:city":"Binissalem",
    "sg:orig_category":"Artesan\u00cda",
    "sg:phone":"+34 971 51 13 04",
    "sg:postcode":"07350",
    "sg:province":"Islas Baleares",
    "wof:name":"Moya Pons Bernardo",
    "wof:placetype":"venue"
},
  "geometry": {"coordinates":[2.8489398956,39.6879081726],"type":"Point"}
}