{
  "type": "Feature",
  "properties": {
    "addr:full":"Calle de Peru, 9 Guadalajara Guadalajara 19005",
    "addr:housenumber":"9",
    "addr:postcode":"19005",
    "addr:street":"Calle De Peru",
    "iso:country":"ES",
    "sg:address":"Calle de Peru, 9",
    "sg:city":"Guadalajara",
    "sg:orig_category":"Molduras, Junquillos, Listones Y Molduras Perforadas",
    "sg:phone":"+34 949 22 90 69",
    "sg:postcode":"19005",
    "sg:province":"Guadalajara",
    "wof:name":"Talha Talha Hassan",
    "wof:placetype":"venue"
},
  "geometry": {"coordinates":[-3.1557629108,40.6334457397],"type":"Point"}
}