{
  "type": "Feature",
  "properties": {
    "addr:full":"Ctra Soria Plasencia, Km. 0188,0 Segovia Segovia 40003",
    "addr:postcode":"40003",
    "addr:street":"Ctra Soria Plasencia Km. 0188,0",
    "iso:country":"ES",
    "sg:address":"Ctra Soria Plasencia, Km. 0188,0",
    "sg:city":"Segovia",
    "sg:orig_category":"M\u00c1rmoles, Granitos Y Piedras Naturales",
    "sg:phone":"+34 921 44 46 95",
    "sg:postcode":"40003",
    "sg:province":"Segovia",
    "wof:name":"Martin Anton Antonio",
    "wof:placetype":"venue"
},
  "geometry": {"coordinates":[-4.1163592339,40.9482116699],"type":"Point"}
}