{
  "type": "Feature",
  "properties": {
    "iso:country":"ES",
    "sg:address":"Carr Legazpi, 5",
    "sg:city":"Grau I Platja",
    "sg:orig_category":"Caf\u00c9s, Bares, Cervecer\u00cdas",
    "sg:phone":"+34 962 84 16 14",
    "sg:postcode":"46730",
    "sg:province":"Valencia",
    "wof:name":"San Jaime Almi\u00f1ana Encarnacion",
    "wof:placetype":"venue"
},
  "geometry": {"coordinates":[-0.1638360023,39.0029182434],"type":"Point"}
}