{
  "type": "Feature",
  "properties": {
    "iso:country":"ES",
    "sg:address":"Avda Andalucia (de), 42",
    "sg:city":"Montilla",
    "sg:orig_category":"Hormigonados",
    "sg:phone":"+34 957 65 18 31",
    "sg:postcode":"14550",
    "sg:province":"C\u00f3rdoba",
    "wof:name":"Hormigones Marques Marquez S.a.",
    "wof:placetype":"venue"
},
  "geometry": {"coordinates":[-4.6449837685,37.5817604065],"type":"Point"}
}