{
  "type": "Feature",
  "properties": {
    "iso:country":"ES",
    "sg:address":"Calle de Mayor, 45",
    "sg:city":"Puente Tocinos",
    "sg:orig_category":"Fabricaci\u00d3n De Acumuladores Y De Pilas El\u00c9ctricas",
    "sg:phone":"+34 968 27 16 96",
    "sg:postcode":"30006",
    "sg:province":"Murcia",
    "wof:name":"Tecnologias Electricas Mediterraneas S.l.",
    "wof:placetype":"venue"
},
  "geometry": {"coordinates":[-1.0894367695,38.0107116699],"type":"Point"}
}