{
  "type": "Feature",
  "properties": {
    "addr:full":"Calle de Doctor Castelo, 52 Madrid Madrid 28009",
    "addr:housenumber":"52",
    "addr:postcode":"madrid;28009",
    "addr:street":"Calle De Doctor Castelo",
    "iso:country":"ES",
    "sg:address":"Calle de Doctor Castelo, 52",
    "sg:city":"Madrid",
    "sg:orig_category":"\u00d3ptica: Instrumentos (fabricaci\u00d3n)",
    "sg:phone":"+34 915 04 19 46",
    "sg:postcode":"28009",
    "sg:province":"Madrid",
    "wof:name":"Corces Cordero Maria Jesus",
    "wof:placetype":"venue"
},
  "geometry": {"coordinates":[-3.6731729507,40.420085907],"type":"Point"}
}