{
  "type": "Feature",
  "properties": {
    "iso:country":"ES",
    "sg:address":"G.v. Lopez De Haro D. Diego, 4",
    "sg:city":"Bilbao",
    "sg:orig_category":"Bancos",
    "sg:phone":"+34 944 35 20 89",
    "sg:postcode":"48001",
    "sg:province":"Vizcaya",
    "wof:name":"Bt Ingite Espana Sau",
    "wof:placetype":"venue"
},
  "geometry": {"coordinates":[-2.9278559685,43.2615776062],"type":"Point"}
}