{
  "type": "Feature",
  "properties": {
    "iso:country":"ES",
    "sg:address":"Calle de Leonardo Rucabado, 6",
    "sg:city":"Castro Urdiales",
    "sg:orig_category":"Centros De Educaci\u00d3n Especial",
    "sg:phone":"+34 942 86 00 82",
    "sg:postcode":"39700",
    "sg:province":"Cantabria",
    "wof:name":"Colegio Publico Infantil Y Primaria Arturo Duo",
    "wof:placetype":"venue"
},
  "geometry": {"coordinates":[-3.2210199833,43.3806037903],"type":"Point"}
}