{
  "type": "Feature",
  "properties": {
    "iso:country":"ES",
    "sg:address":"Carrer de Gava, 91",
    "sg:city":"Barcelona",
    "sg:orig_category":"Estancos",
    "sg:phone":"+34 934 21 29 26",
    "sg:postcode":"08014",
    "sg:province":"Barcelona",
    "wof:name":"Martinez Romero Maria Luisa",
    "wof:placetype":"venue"
},
  "geometry": {"coordinates":[2.1382629871,41.3701438904],"type":"Point"}
}