{
  "type": "Feature",
  "properties": {
    "addr:full":"Pol. Ria\u00f1o(edif. Sedes), S/n Llangreu Asturias 33920",
    "addr:housenumber":"s / n",
    "addr:postcode":"33920",
    "iso:country":"ES",
    "sg:address":"Pol. Ria\u00f1o(edif. Sedes), S/n",
    "sg:city":"Llangreu",
    "sg:orig_category":"Ense\u00d1anza, Formaci\u00d3n Profesional: Aprendizaje",
    "sg:phone":"+34 985 68 09 54",
    "sg:postcode":"33920",
    "sg:province":"Asturias",
    "wof:name":"Ayuntamiento De Langreo",
    "wof:placetype":"venue"
},
  "geometry": {"coordinates":[-5.7181363106,43.3278160095],"type":"Point"}
}