{
  "type": "Feature",
  "properties": {
    "addr:full":"R. Y Cajal, 11 Antequera M\u00e1laga 29200",
    "addr:housenumber":"11",
    "addr:postcode":"29200",
    "addr:street":"Y Cajal",
    "iso:country":"ES",
    "sg:address":"R. Y Cajal, 11",
    "sg:city":"Antequera",
    "sg:orig_category":"Librer\u00cdas",
    "sg:phone":"+34 952 70 35 46",
    "sg:postcode":"29200",
    "sg:province":"M\u00e1laga",
    "wof:name":"Campos Cazorla Francisco",
    "wof:placetype":"venue"
},
  "geometry": {"coordinates":[-4.5619387627,37.0199394226],"type":"Point"}
}