{
  "type": "Feature",
  "properties": {
    "addr:full":"Parq Comerc Urbisur (pi Torno I), 9 Chiclana C\u00e1diz 11130",
    "addr:housenumber":"ca\u0301diz",
    "addr:postcode":"11130",
    "addr:street":"Chiclana",
    "iso:country":"ES",
    "sg:address":"Parq Comerc Urbisur (pi Torno I), 9",
    "sg:city":"Chiclana",
    "sg:orig_category":"Asesor\u00cdas Y Estudios Financieros",
    "sg:phone":"+34 956 40 78 33",
    "sg:postcode":"11130",
    "sg:province":"C\u00e1diz",
    "wof:name":"Estudio De Financiacion Chiclana S.l.",
    "wof:placetype":"venue"
},
  "geometry": {"coordinates":[-6.1447038651,36.4212188721],"type":"Point"}
}