{
  "type": "Feature",
  "properties": {
    "iso:country":"ES",
    "sg:address":"Plaz Pilar (el), 3",
    "sg:city":"Gelves",
    "sg:orig_category":"Cajas De Ahorro",
    "sg:phone":"+34 955 76 29 70",
    "sg:postcode":"41120",
    "sg:province":"Sevilla",
    "sg:website":"www.elmonte.es",
    "wof:name":"Monte De Piedad Y Caja De Ahorros De Huelva Y Sevilla",
    "wof:placetype":"venue"
},
  "geometry": {"coordinates":[-6.0261597633,37.3359832764],"type":"Point"}
}