{
  "type": "Feature",
  "properties": {
    "iso:country":"ES",
    "sg:address":"Calle de Melquiades Biencinto, 13",
    "sg:city":"Madrid",
    "sg:orig_category":"Cervecer\u00cdas",
    "sg:phone":"+34 915 01 36 86",
    "sg:postcode":"28053",
    "sg:province":"Madrid",
    "wof:name":"Gutierrez Roman Tomas",
    "wof:placetype":"venue"
},
  "geometry": {"coordinates":[-3.6698229313,40.3964958191],"type":"Point"}
}