{
  "type": "Feature",
  "properties": {
    "addr:full":"Plaz Duques De Miranda, 7 Cortes Navarra 31530",
    "addr:housenumber":"7",
    "addr:postcode":"31530",
    "addr:street":"Plaz Duques De Miranda",
    "iso:country":"ES",
    "sg:address":"Plaz Duques De Miranda, 7",
    "sg:city":"Cortes",
    "sg:orig_category":"Bancos",
    "sg:phone":"+34 948 80 02 35",
    "sg:postcode":"31530",
    "sg:province":"Navarra",
    "wof:name":"Banco De Vasconia",
    "wof:placetype":"venue"
},
  "geometry": {"coordinates":[-1.4198440313,41.9217453003],"type":"Point"}
}