{
  "type": "Feature",
  "properties": {
    "addr:full":"Rua Venezuela, 3 Carballi\u00f1o Ourense 32500",
    "addr:housenumber":"3",
    "addr:postcode":"32500",
    "addr:street":"Rua Venezuela",
    "iso:country":"ES",
    "sg:address":"Rua Venezuela, 3",
    "sg:city":"Carballi\u00f1o",
    "sg:orig_category":"M\u00c9dicos: Estomatolog\u00cda",
    "sg:phone":"+34 988 27 11 59",
    "sg:postcode":"32500",
    "sg:province":"Ourense",
    "wof:name":"M.d.quevedo Bisonni S.l.u.",
    "wof:placetype":"venue"
},
  "geometry": {"coordinates":[-8.0800952911,42.4300231934],"type":"Point"}
}