{
  "type": "Feature",
  "properties": {
    "addr:full":"Calle de Vicario, 28 S. Fernando C\u00e1diz 11100",
    "addr:housenumber":"28",
    "addr:postcode":"11100",
    "addr:street":"Calle De Vicario;S. Fernando Ca\u0301Diz",
    "iso:country":"ES",
    "sg:address":"Calle de Vicario, 28",
    "sg:city":"S. Fernando",
    "sg:orig_category":"Abogados",
    "sg:phone":"+34 956 89 27 26",
    "sg:postcode":"11100",
    "sg:province":"C\u00e1diz",
    "wof:name":"Martinez De Mendoza Jose Manuel Francisco",
    "wof:placetype":"venue"
},
  "geometry": {"coordinates":[-6.1966938972,36.4683532715],"type":"Point"}
}