{
  "type": "Feature",
  "properties": {
    "iso:country":"ES",
    "sg:address":"Trav Dalt, 12",
    "sg:city":"Barcelona",
    "sg:orig_category":"Institutos De Belleza",
    "sg:phone":"+34 932 18 10 48",
    "sg:postcode":"08024",
    "sg:province":"Barcelona",
    "sg:website":"www.urbea.com",
    "wof:name":"Ideal Life S. L.",
    "wof:placetype":"venue"
},
  "geometry": {"coordinates":[2.1518740654,41.4082489014],"type":"Point"}
}