{
  "type": "Feature",
  "properties": {
    "addr:full":"Carrer de Marti, 130 Barcelona Barcelona 08024",
    "addr:housenumber":"130",
    "addr:postcode":"08024",
    "addr:street":"Carrer De Marti",
    "iso:country":"ES",
    "sg:address":"Carrer de Marti, 130",
    "sg:city":"Barcelona",
    "sg:orig_category":"Electricidad: Instaladores",
    "sg:phone":"+34 932 84 36 60",
    "sg:postcode":"08024",
    "sg:province":"Barcelona",
    "wof:name":"Instaltruc S.cv.",
    "wof:placetype":"venue"
},
  "geometry": {"coordinates":[2.161272049,41.4098358154],"type":"Point"}
}