{
  "type": "Feature",
  "properties": {
    "addr:full":"Calle de Garrigues, Les, 5 Valencia Valencia 46001",
    "addr:postcode":"46001",
    "addr:street":"Calle De;Les;Valencia",
    "iso:country":"ES",
    "sg:address":"Calle de Garrigues, Les, 5",
    "sg:city":"Valencia",
    "sg:orig_category":"Centros De Coordinaci\u00d3n",
    "sg:phone":"+34 963 51 50 45",
    "sg:postcode":"46001",
    "sg:province":"Valencia",
    "wof:name":"Blay Ortells Jose Manuel",
    "wof:placetype":"venue"
},
  "geometry": {"coordinates":[-0.3784680068,39.4706306458],"type":"Point"}
}