{
  "type": "Feature",
  "properties": {
    "iso:country":"ES",
    "sg:address":"Calle de Conde De Salvatierra, 17",
    "sg:city":"Valencia",
    "sg:orig_category":"Florister\u00cdas",
    "sg:phone":"+34 963 53 24 64",
    "sg:postcode":"46004",
    "sg:province":"Valencia",
    "wof:name":"Amoa S.l.",
    "wof:placetype":"venue"
},
  "geometry": {"coordinates":[-0.3684630096,39.4701194763],"type":"Point"}
}