{
  "type": "Feature",
  "properties": {
    "iso:country":"ES",
    "sg:address":"Calle de A(campollano), 40",
    "sg:city":"Albacete",
    "sg:orig_category":"Limpieza Industrial",
    "sg:phone":"+34 967 52 14 25",
    "sg:postcode":"02006",
    "sg:province":"Albacete",
    "wof:name":"Lavanderias Lavanco S.l.l.",
    "wof:placetype":"venue"
},
  "geometry": {"coordinates":[-1.9490209818,39.013168335],"type":"Point"}
}