{
  "type": "Feature",
  "properties": {
    "addr:full":"Calle de Vera De Bidasoa, 20 Irun Guip\u00f9zcoa 20301",
    "addr:housenumber":"20",
    "addr:postcode":"20301",
    "addr:street":"Calle De Vera De Bidasoa;Guipu\u0300Zcoa",
    "iso:country":"ES",
    "sg:address":"Calle de Vera De Bidasoa, 20",
    "sg:city":"Irun",
    "sg:orig_category":"Contenedores (mercanc\u00cdas)",
    "sg:phone":"+34 943 61 06 05",
    "sg:postcode":"20301",
    "sg:province":"Guip\u00f9zcoa",
    "wof:name":"Casintra Sociedad Cooperativa Limitada",
    "wof:placetype":"venue"
},
  "geometry": {"coordinates":[-1.7997870445,43.3446121216],"type":"Point"}
}