{
  "type": "Feature",
  "properties": {
    "addr:full":"Calle de Utrillas, 16 Zaragoza Zaragoza 50013",
    "addr:housenumber":"16",
    "addr:postcode":"50013",
    "addr:street":"Calle De Utrillas",
    "iso:country":"ES",
    "sg:address":"Calle de Utrillas, 16",
    "sg:city":"Zaragoza",
    "sg:orig_category":"Ropa Para Se\u00d1oras (al Por Menor)",
    "sg:phone":"+34 976 13 42 19",
    "sg:postcode":"50013",
    "sg:province":"Zaragoza",
    "wof:name":"Marco Bariela Mercedes",
    "wof:placetype":"venue"
},
  "geometry": {"coordinates":[-0.8677700162,41.6439476013],"type":"Point"}
}