{
  "type": "Feature",
  "properties": {
    "addr:full":"Calle de Chinchon, 39 Valdemoro Madrid 28340",
    "addr:housenumber":"39",
    "addr:postcode":"28340",
    "addr:street":"Calle De Chinchon",
    "iso:country":"ES",
    "sg:address":"Calle de Chinchon, 39",
    "sg:city":"Valdemoro",
    "sg:orig_category":"Fabricaci\u00d3n Y Comercio De M\u00c1quinas",
    "sg:phone":"+34 918 95 25 59",
    "sg:postcode":"28340",
    "sg:province":"Madrid",
    "wof:name":"Mecanizados Logar S.l.",
    "wof:placetype":"venue"
},
  "geometry": {"coordinates":[-3.6781790257,40.2076759338],"type":"Point"}
}