{
  "type": "Feature",
  "properties": {
    "addr:full":"Ctra Vp Mil Treinta Y Seis, Km. 0004,0 Xativa Valencia 46800",
    "addr:postcode":"46800",
    "addr:street":"Ctra Vp;Treinta Y Seis Km. 0004,0",
    "iso:country":"ES",
    "sg:address":"Ctra Vp Mil Treinta Y Seis, Km. 0004,0",
    "sg:city":"Xativa",
    "sg:orig_category":"Reciclaje, Desguace De Veh\u00cdculos",
    "sg:phone":"+34 962 28 22 13",
    "sg:postcode":"46800",
    "sg:province":"Valencia",
    "wof:name":"Reciclados Jose Perez E Hijos S.l.",
    "wof:placetype":"venue"
},
  "geometry": {"coordinates":[-0.5200830102,38.9934272766],"type":"Point"}
}