{
  "type": "Feature",
  "properties": {
    "addr:full":"Erribera Kalea-calle De La Ribera, 9 Lasarte-oria Guip\u00f9zcoa 20160",
    "addr:housenumber":"9",
    "addr:postcode":"20160",
    "addr:street":"Ribera;Guipu\u0300Zcoa",
    "iso:country":"ES",
    "sg:address":"Erribera Kalea-calle De La Ribera, 9",
    "sg:city":"Lasarte-oria",
    "sg:orig_category":"Paneles Diversos",
    "sg:phone":"+34 943 36 55 44",
    "sg:postcode":"20160",
    "sg:province":"Guip\u00f9zcoa",
    "wof:name":"Gonzalez Renedo,florencio",
    "wof:placetype":"venue"
},
  "geometry": {"coordinates":[-2.020414114,43.2698173523],"type":"Point"}
}