{
  "type": "Feature",
  "properties": {
    "addr:full":"Calle de Marquesa De Canillejas, 32 Pola De Siero Asturias 33510",
    "addr:housenumber":"32",
    "addr:postcode":"33510",
    "addr:street":"Calle De Marquesa De Canillejas",
    "iso:country":"ES",
    "sg:address":"Calle de Marquesa De Canillejas, 32",
    "sg:city":"Pola De Siero",
    "sg:orig_category":"Agencias Y Agentes Comerciales, Representantes",
    "sg:phone":"+34 985 72 22 97",
    "sg:postcode":"33510",
    "sg:province":"Asturias",
    "wof:name":"Rodriguez Diaz Guillermo",
    "wof:placetype":"venue"
},
  "geometry": {"coordinates":[-5.6624288559,43.389175415],"type":"Point"}
}