{
  "type": "Feature",
  "properties": {
    "iso:country":"ES",
    "sg:address":"Calle de Don Juan De Austria, 33",
    "sg:city":"Campillo Del Moro",
    "sg:orig_category":"Caf\u00c9s, Bares, Cervecer\u00cdas",
    "sg:phone":"+34 950 34 83 89",
    "sg:postcode":"04720",
    "sg:province":"Almer\u00eda",
    "wof:name":"Ramos Archilla Jose Narciso",
    "wof:placetype":"venue"
},
  "geometry": {"coordinates":[-2.5877244473,36.8087120056],"type":"Point"}
}