{
  "type": "Feature",
  "properties": {
    "iso:country":"ES",
    "sg:address":"Calle de Vega La, 7",
    "sg:city":"Nava",
    "sg:orig_category":"Audiovisuales (producci\u00d3n, Edici\u00d3n, Realizaci\u00d3n)",
    "sg:phone":"+34 985 71 74 46",
    "sg:postcode":"33520",
    "sg:province":"Asturias",
    "wof:name":"La Chalga Producciones S.l.",
    "wof:placetype":"venue"
},
  "geometry": {"coordinates":[-5.5083298683,43.3597946167],"type":"Point"}
}