{
  "type": "Feature",
  "properties": {
    "addr:full":"Carrer de Dr. Fleming, 2 Poblenou Barcelona 08397",
    "addr:housenumber":"2",
    "addr:postcode":"08397",
    "addr:street":"Carrer De Dr. Fleming",
    "iso:country":"ES",
    "sg:address":"Carrer de Dr. Fleming, 2",
    "sg:city":"Poblenou",
    "sg:orig_category":"Estancos",
    "sg:phone":"+34 937 66 09 55",
    "sg:postcode":"08397",
    "sg:province":"Barcelona",
    "wof:name":"Miquel Cruells Joan",
    "wof:placetype":"venue"
},
  "geometry": {"coordinates":[2.6721498966,41.6176986694],"type":"Point"}
}