{
  "type": "Feature",
  "properties": {
    "addr:full":"Pg Passeig, 99 Garriga Barcelona 08530",
    "addr:housenumber":"99",
    "addr:postcode":"08530",
    "addr:street":"Passeig",
    "iso:country":"ES",
    "sg:address":"Pg Passeig, 99",
    "sg:city":"Garriga",
    "sg:orig_category":"Asociaciones Y Clubs Deportivos",
    "sg:phone":"+34 938 71 53 89",
    "sg:postcode":"08530",
    "sg:province":"Barcelona",
    "wof:name":"Casino De La Garriga",
    "wof:placetype":"venue"
},
  "geometry": {"coordinates":[2.2880311012,41.6770362854],"type":"Point"}
}