{
  "type": "Feature",
  "properties": {
    "addr:full":"Calle de Alcalde Jose Puertes, S/n Alfafar Valencia 46910",
    "addr:housenumber":"s / n",
    "addr:postcode":"46910",
    "addr:street":"Calle De Alcalde Jose Puertes",
    "iso:country":"ES",
    "sg:address":"Calle de Alcalde Jose Puertes, S/n",
    "sg:city":"Alfafar",
    "sg:orig_category":"Ropa Para Se\u00d1oras Y Caballeros (al Por Menor)",
    "sg:phone":"+34 963 75 31 51",
    "sg:postcode":"46910",
    "sg:province":"Valencia",
    "wof:name":"Pull & Bear Espa\u00d1a S.a.",
    "wof:placetype":"venue"
},
  "geometry": {"coordinates":[-0.3807964027,39.4168930054],"type":"Point"}
}