{
  "type": "Feature",
  "properties": {
    "addr:full":"Calle de Teniente Coronel Gautier, 4 Ceuta Ceuta 51002",
    "addr:housenumber":"4",
    "addr:postcode":"51002",
    "addr:street":"Calle De Teniente Coronel Gautier",
    "iso:country":"ES",
    "sg:address":"Calle de Teniente Coronel Gautier, 4",
    "sg:city":"Ceuta",
    "sg:orig_category":"Molduras, Junquillos, Listones Y Molduras Perforadas",
    "sg:phone":"+34 956 50 74 66",
    "sg:postcode":"51002",
    "sg:province":"Ceuta",
    "wof:name":"Dominguez Gonzalez Luis",
    "wof:placetype":"venue"
},
  "geometry": {"coordinates":[-5.3304820061,35.884979248],"type":"Point"}
}