{
  "type": "Feature",
  "properties": {
    "iso:country":"ES",
    "sg:address":"Avgd Jaume Iii, 9",
    "sg:city":"Santa Maria Del Cami",
    "sg:orig_category":"Traductores",
    "sg:phone":"+34 971 62 15 78",
    "sg:postcode":"07320",
    "sg:province":"Islas Baleares",
    "wof:name":"Vasaris Balta S.l.",
    "wof:placetype":"venue"
},
  "geometry": {"coordinates":[2.772881031,39.6485748291],"type":"Point"}
}