{
  "type": "Feature",
  "properties": {
    "iso:country":"ES",
    "sg:address":"Mcdo Pl Barcelona, S/n",
    "sg:city":"Elche",
    "sg:orig_category":"Poller\u00cda Y Caza (al Por Menor)",
    "sg:phone":"+34 965 46 10 84",
    "sg:postcode":"03206",
    "sg:province":"Alicante",
    "wof:name":"Hijos De Tomas Pascual S.l.",
    "wof:placetype":"venue"
},
  "geometry": {"coordinates":[-0.7061319947,38.2717590332],"type":"Point"}
}