{
  "type": "Feature",
  "properties": {
    "iso:country":"ES",
    "sg:address":"Carrer de Apol.lo, 27",
    "sg:city":"Terrassa",
    "sg:orig_category":"Tapicer\u00cdas",
    "sg:phone":"+34 937 84 46 08",
    "sg:postcode":"08228",
    "sg:province":"Barcelona",
    "wof:name":"Lor Marti S.l.",
    "wof:placetype":"venue"
},
  "geometry": {"coordinates":[2.0366549492,41.5418434143],"type":"Point"}
}