{
  "type": "Feature",
  "properties": {
    "addr:full":"Calle de Carre\u00d1o Miranda, 26 Mieres Asturias 33600",
    "addr:housenumber":"26",
    "addr:postcode":"33600",
    "addr:street":"Calle De Carren\u0303O Miranda",
    "iso:country":"ES",
    "sg:address":"Calle de Carre\u00d1o Miranda, 26",
    "sg:city":"Mieres",
    "sg:orig_category":"Florister\u00cdas",
    "sg:phone":"+34 985 46 75 18",
    "sg:postcode":"33600",
    "sg:province":"Asturias",
    "wof:name":"Peinado Pacheco Maria Del Carmen",
    "wof:placetype":"venue"
},
  "geometry": {"coordinates":[-5.7745919228,43.2524147034],"type":"Point"}
}