{
  "type": "Feature",
  "properties": {
    "addr:full":"Calle de La Iglesia, 20 Palomero C\u00e1ceres 10660",
    "addr:housenumber":"20",
    "addr:postcode":"10660",
    "addr:street":"Calle De La Iglesia;Ca\u0301Ceres",
    "iso:country":"ES",
    "sg:address":"Calle de La Iglesia, 20",
    "sg:city":"Palomero",
    "sg:orig_category":"Cooperativas Agr\u00cdcolas",
    "sg:phone":"+34 927 67 38 24",
    "sg:postcode":"10660",
    "sg:province":"C\u00e1ceres",
    "wof:name":"Sociedad Cooperativa Trasierra De Granadilla",
    "wof:placetype":"venue"
},
  "geometry": {"coordinates":[-6.2758588791,40.2470016479],"type":"Point"}
}