{
  "type": "Feature",
  "properties": {
    "addr:full":"Calle de Almagro, 12 Zaragoza Zaragoza 50004",
    "addr:housenumber":"12",
    "addr:postcode":"50004",
    "addr:street":"Calle De Almagro",
    "iso:country":"ES",
    "sg:address":"Calle de Almagro, 12",
    "sg:city":"Zaragoza",
    "sg:orig_category":"Molduras, Junquillos, Listones Y Molduras Perforadas",
    "sg:phone":"+34 976 23 73 32",
    "sg:postcode":"50004",
    "sg:province":"Zaragoza",
    "wof:name":"Martin Perez Julian",
    "wof:placetype":"venue"
},
  "geometry": {"coordinates":[-0.8882446885,41.648311615],"type":"Point"}
}