{
  "type": "Feature",
  "properties": {
    "addr:full":"Miquel Batlle, 7 Montgat Barcelona 08390",
    "addr:housenumber":"7",
    "addr:postcode":"08390",
    "addr:street":"Miquel Batlle",
    "iso:country":"ES",
    "sg:address":"Miquel Batlle, 7",
    "sg:city":"Montgat",
    "sg:orig_category":"Cajas De Ahorro",
    "sg:phone":"+34 934 69 24 97",
    "sg:postcode":"08390",
    "sg:province":"Barcelona",
    "wof:name":"Caixa D'estalvis Laietana",
    "wof:placetype":"venue"
},
  "geometry": {"coordinates":[2.2786819935,41.4675636292],"type":"Point"}
}