{
  "type": "Feature",
  "properties": {
    "iso:country":"ES",
    "sg:address":"Calle de Pelayo, 34",
    "sg:city":"Palmas De Gran Canaria",
    "sg:orig_category":"Abogados",
    "sg:phone":"+34 928 27 66 10",
    "sg:postcode":"35010",
    "sg:province":"Las Palmas",
    "wof:name":"Pardo Choya Demetrio Santos",
    "wof:placetype":"venue"
},
  "geometry": {"coordinates":[-15.437830925,28.1349067688],"type":"Point"}
}