{
  "type": "Feature",
  "properties": {
    "addr:full":"Calle de Mayor, 38 Burgo Osma Soria 42300",
    "addr:housenumber":"38",
    "addr:postcode":"42300",
    "addr:street":"Calle De Mayor",
    "iso:country":"ES",
    "sg:address":"Calle de Mayor, 38",
    "sg:city":"Burgo Osma",
    "sg:orig_category":"Reposter\u00cdas",
    "sg:phone":"+34 975 34 12 13",
    "sg:postcode":"42300",
    "sg:province":"Soria",
    "wof:name":"Sala Ruperez Maria Luisa",
    "wof:placetype":"venue"
},
  "geometry": {"coordinates":[-3.0692529678,41.5858039856],"type":"Point"}
}