{
  "type": "Feature",
  "properties": {
    "addr:full":"Calle de Salinas, 12 Puerto Del Carmen Las Palmas 35510",
    "addr:housenumber":"12",
    "addr:postcode":"35510",
    "addr:street":"Calle De Salinas",
    "iso:country":"ES",
    "sg:address":"Calle de Salinas, 12",
    "sg:city":"Puerto Del Carmen",
    "sg:orig_category":"Asociaciones, Organismos Culturales Y Socioeducativos",
    "sg:phone":"+34 928 51 28 42",
    "sg:postcode":"35510",
    "sg:province":"Las Palmas",
    "wof:name":"Centro De Terapia Antroposofica",
    "wof:placetype":"venue"
},
  "geometry": {"coordinates":[-13.6699676514,28.9251728058],"type":"Point"}
}