{
  "type": "Feature",
  "properties": {
    "iso:country":"ES",
    "sg:address":"Carrer de Porta S Margalida, 8",
    "sg:city":"Indioteria",
    "sg:orig_category":"Agencias Y Agentes Comerciales, Representantes",
    "sg:phone":"+34 971 43 37 75",
    "sg:postcode":"07009",
    "sg:province":"Islas Baleares",
    "wof:name":"Vigil Romero Sandra",
    "wof:placetype":"venue"
},
  "geometry": {"coordinates":[2.6771440506,39.6057357788],"type":"Point"}
}