{
  "type": "Feature",
  "properties": {
    "iso:country":"ES",
    "sg:address":"Plaz Longoria Carbajal, 2",
    "sg:city":"Oviedo",
    "sg:orig_category":"M\u00c9dicos: Estomatolog\u00cda",
    "sg:phone":"+34 985 22 36 21",
    "sg:postcode":"33002",
    "sg:province":"Asturias",
    "wof:name":"Pelaez Fernandez Pablo",
    "wof:placetype":"venue"
},
  "geometry": {"coordinates":[-5.8485121727,43.3647880554],"type":"Point"}
}