{
  "type": "Feature",
  "properties": {
    "addr:full":"Calle de Camino De Las Nieves, 6 Arcos Frontera C\u00e1diz 11630",
    "addr:housenumber":"6",
    "addr:postcode":"11630",
    "addr:street":"Calle De Camino De Las Nieves",
    "iso:country":"ES",
    "sg:address":"Calle de Camino De Las Nieves, 6",
    "sg:city":"Arcos Frontera",
    "sg:orig_category":"Pintura Y Barniz (al Por Menor)",
    "sg:phone":"+34 956 70 31 38",
    "sg:postcode":"11630",
    "sg:province":"C\u00e1diz",
    "wof:name":"Pinturas Brico S.l.",
    "wof:placetype":"venue"
},
  "geometry": {"coordinates":[-5.8109850883,36.7511863708],"type":"Point"}
}