{
  "type": "Feature",
  "properties": {
    "addr:full":"Carrer de Joaquim De Paz, 46 Terrassa Barcelona 08221",
    "addr:housenumber":"46",
    "addr:postcode":"08221",
    "addr:street":"Carrer De Joaquim De Paz",
    "iso:country":"ES",
    "sg:address":"Carrer de Joaquim De Paz, 46",
    "sg:city":"Terrassa",
    "sg:orig_category":"Electricidad: Instaladores",
    "sg:phone":"+34 937 83 29 18",
    "sg:postcode":"08221",
    "sg:province":"Barcelona",
    "wof:name":"Riera Torres Luis",
    "wof:placetype":"venue"
},
  "geometry": {"coordinates":[2.0147559643,41.565246582],"type":"Point"}
}