{
  "type": "Feature",
  "properties": {
    "iso:country":"ES",
    "sg:address":"Cno Rancho, 15",
    "sg:city":"Albujon",
    "sg:orig_category":"Empresas De Demolici\u00d3n",
    "sg:phone":"+34 968 55 03 82",
    "sg:postcode":"30330",
    "sg:province":"Murcia",
    "wof:name":"Excavaciones Miras S.l.",
    "wof:placetype":"venue"
},
  "geometry": {"coordinates":[-1.0449620485,37.7163619995],"type":"Point"}
}