{
  "type": "Feature",
  "properties": {
    "addr:full":"Calle de Getafe (de), 17 Fuenlabrada Madrid 28944",
    "addr:housenumber":"17",
    "addr:postcode":"28944",
    "addr:street":"Calle De Getafe De",
    "iso:country":"ES",
    "sg:address":"Calle de Getafe (de), 17",
    "sg:city":"Fuenlabrada",
    "sg:orig_category":"Mec\u00c1nico Del Autom\u00d3vil",
    "sg:phone":"+34 916 06 37 83",
    "sg:postcode":"28944",
    "sg:province":"Madrid",
    "wof:name":"Mu\u00f1oz Tojar Juan Carlos",
    "wof:placetype":"venue"
},
  "geometry": {"coordinates":[-3.7877004147,40.2825775146],"type":"Point"}
}