{
  "type": "Feature",
  "properties": {
    "addr:full":"Calle de Luis Lopez Oses, 14 Getxo Vizcaya 48930",
    "addr:housenumber":"14",
    "addr:postcode":"48930",
    "addr:street":"Calle De Luis;Oses",
    "iso:country":"ES",
    "sg:address":"Calle de Luis Lopez Oses, 14",
    "sg:city":"Getxo",
    "sg:orig_category":"Sociedades, Compa\u00d1\u00cdas Aseguradoras",
    "sg:phone":"+34 944 80 12 89",
    "sg:postcode":"48930",
    "sg:province":"Vizcaya",
    "wof:name":"Servicios Periciales Arrate",
    "wof:placetype":"venue"
},
  "geometry": {"coordinates":[-3.0061240196,43.3302574158],"type":"Point"}
}