{
  "type": "Feature",
  "properties": {
    "addr:full":"Ctra Valencia, 13 Betera Valencia 46117",
    "addr:housenumber":"13",
    "addr:postcode":"46117",
    "addr:street":"Ctra Valencia",
    "iso:country":"ES",
    "sg:address":"Ctra Valencia, 13",
    "sg:city":"Betera",
    "sg:orig_category":"Mec\u00c1nico Del Autom\u00d3vil",
    "sg:phone":"+34 961 69 04 79",
    "sg:postcode":"46117",
    "sg:province":"Valencia",
    "wof:name":"Talleres Aparisi S.l.",
    "wof:placetype":"venue"
},
  "geometry": {"coordinates":[-0.4653899968,39.5910301208],"type":"Point"}
}