{
  "type": "Feature",
  "properties": {
    "iso:country":"ES",
    "sg:address":"Carrer de Santander, 73",
    "sg:city":"Barcelona",
    "sg:orig_category":"Papel, Reciclaje",
    "sg:phone":"+34 933 05 52 10",
    "sg:postcode":"08020",
    "sg:province":"Barcelona",
    "wof:name":"Union De Traperos Para El Reciclaje Y Servicios S.l.",
    "wof:placetype":"venue"
},
  "geometry": {"coordinates":[2.2044000626,41.4305725098],"type":"Point"}
}