{
  "type": "Feature",
  "properties": {
    "iso:country":"ES",
    "sg:address":"Pla\u00c7 Major, 1",
    "sg:city":"Villarreal",
    "sg:orig_category":"Art\u00cdculos De Regalo (al Por Menor)",
    "sg:phone":"+34 964 53 06 51",
    "sg:postcode":"12540",
    "sg:province":"Castell\u00f3n",
    "wof:name":"Fabra Cabedo Maria Del Carmen",
    "wof:placetype":"venue"
},
  "geometry": {"coordinates":[-0.0952939987,39.9453048706],"type":"Point"}
}