{
  "type": "Feature",
  "properties": {
    "iso:country":"ES",
    "sg:address":"Avda Llano De Pablo Picasso, 36",
    "sg:city":"Archidona",
    "sg:orig_category":"Imprenta",
    "sg:phone":"+34 952 71 77 05",
    "sg:postcode":"29300",
    "sg:province":"M\u00e1laga",
    "wof:name":"Archidona Graficas S.l.",
    "wof:placetype":"venue"
},
  "geometry": {"coordinates":[-4.3789262772,37.0952148438],"type":"Point"}
}