{
  "type": "Feature",
  "properties": {
    "addr:full":"Calle de Valladolid (de), 5 Humanes De Madrid Madrid 28970",
    "addr:postcode":"28970",
    "addr:street":"Calle De Valladolid De 5",
    "iso:country":"ES",
    "sg:address":"Calle de Valladolid (de), 5",
    "sg:city":"Humanes De Madrid",
    "sg:orig_category":"Electricidad, Electr\u00d3nica: Material Y Suministros (al Por Mayor)",
    "sg:phone":"+34 914 98 90 21",
    "sg:postcode":"28970",
    "sg:province":"Madrid",
    "wof:name":"Ahuja Union S.l.",
    "wof:placetype":"venue"
},
  "geometry": {"coordinates":[-3.8146924973,40.2757911682],"type":"Point"}
}