{
  "type": "Feature",
  "properties": {
    "addr:full":"Calle de Jazmin, 120 Arges Toledo 45122",
    "addr:housenumber":"120",
    "addr:postcode":"45122",
    "addr:street":"Calle De Jazmin",
    "iso:country":"ES",
    "sg:address":"Calle de Jazmin, 120",
    "sg:city":"Arges",
    "sg:orig_category":"Prot\u00c9sicos Dentales",
    "sg:phone":"+34 925 37 67 00",
    "sg:postcode":"45122",
    "sg:province":"Toledo",
    "wof:name":"Fernando Gutierrez Castel Y Raquel Gutierrez Sanchez C.b.",
    "wof:placetype":"venue"
},
  "geometry": {"coordinates":[-4.0624389648,39.8102607727],"type":"Point"}
}