{
  "type": "Feature",
  "properties": {
    "addr:full":"Carrer de Arimon, 47 Barcelona Barcelona 08022",
    "addr:housenumber":"47",
    "addr:postcode":"08022",
    "addr:street":"Carrer De Arimon",
    "iso:country":"ES",
    "sg:address":"Carrer de Arimon, 47",
    "sg:city":"Barcelona",
    "sg:orig_category":"Tapicer\u00cdas",
    "sg:phone":"+34 934 17 75 07",
    "sg:postcode":"08022",
    "sg:province":"Barcelona",
    "wof:name":"Gutierrez Fernandez Celia",
    "wof:placetype":"venue"
},
  "geometry": {"coordinates":[2.1356248856,41.4027366638],"type":"Point"}
}