{
  "type": "Feature",
  "properties": {
    "iso:country":"ES",
    "sg:address":"Av Comunitat Valenciana, 5",
    "sg:city":"Altea",
    "sg:orig_category":"Carnicer\u00cdas, Carnicer\u00cdas",
    "sg:phone":"+34 965 84 16 93",
    "sg:postcode":"03590",
    "sg:province":"Alicante",
    "wof:name":"Cuevas Perez Juan Vicente",
    "wof:placetype":"venue"
},
  "geometry": {"coordinates":[-0.0484340005,38.60414505],"type":"Point"}
}