{
  "type": "Feature",
  "properties": {
    "addr:full":"Calle de Lepanto, 6 Irun Guip\u00f9zcoa 20301",
    "addr:housenumber":"6",
    "addr:postcode":"20301",
    "addr:street":"Calle De Lepanto;Guipu\u0300Zcoa",
    "iso:country":"ES",
    "sg:address":"Calle de Lepanto, 6",
    "sg:city":"Irun",
    "sg:orig_category":"M\u00c9dicos: Naturistas",
    "sg:phone":"+34 943 61 54 94",
    "sg:postcode":"20301",
    "sg:province":"Guip\u00f9zcoa",
    "wof:name":"Centro Alfeon C.b.",
    "wof:placetype":"venue"
},
  "geometry": {"coordinates":[-1.800868988,43.3429679871],"type":"Point"}
}