{
  "type": "Feature",
  "properties": {
    "iso:country":"ES",
    "sg:address":"Calle de Rosario, 17",
    "sg:city":"Malagon",
    "sg:orig_category":"Transportes Por Carretera: Lotes Completos, Mercanc\u00cdas Diversas",
    "sg:phone":"+34 926 80 25 98",
    "sg:postcode":"13420",
    "sg:province":"Ciudad Real",
    "wof:name":"Pardo Rodriguez Antonio",
    "wof:placetype":"venue"
},
  "geometry": {"coordinates":[-3.8554120064,39.1710662842],"type":"Point"}
}