{
  "type": "Feature",
  "properties": {
    "addr:full":"Avda Escaleritas, 36 Palmas De Gran Canaria Las Palmas 35011",
    "addr:housenumber":"36",
    "addr:postcode":"35011",
    "addr:street":"Avda Escaleritas",
    "iso:country":"ES",
    "sg:address":"Avda Escaleritas, 36",
    "sg:city":"Palmas De Gran Canaria",
    "sg:orig_category":"Agencias Y Agentes Comerciales, Representantes",
    "sg:phone":"+34 928 22 26 76",
    "sg:postcode":"35011",
    "sg:province":"Las Palmas",
    "wof:name":"Alvarez Cruz Jose",
    "wof:placetype":"venue"
},
  "geometry": {"coordinates":[-15.4362802505,28.122335434],"type":"Point"}
}