{
  "type": "Feature",
  "properties": {
    "addr:full":"Calle de Antonio Royo Villanova, 9 Valladolid Valladolid 47014",
    "addr:housenumber":"9",
    "addr:postcode":"47014",
    "addr:street":"Calle De Antonio Royo Villanova",
    "iso:country":"ES",
    "sg:address":"Calle de Antonio Royo Villanova, 9",
    "sg:city":"Valladolid",
    "sg:orig_category":"Maquinaria Para Industrias Diversas",
    "sg:phone":"+34 983 33 30 48",
    "sg:postcode":"47014",
    "sg:province":"Valladolid",
    "wof:name":"Viveros Valderaduey  S.l",
    "wof:placetype":"venue"
},
  "geometry": {"coordinates":[-4.7371435165,41.6513366699],"type":"Point"}
}