{
  "type": "Feature",
  "properties": {
    "iso:country":"ES",
    "sg:address":"C/ Colom, 9",
    "sg:city":"Banyoles",
    "sg:orig_category":"Inform\u00c1tica, Ofim\u00c1tica (estudios, Asesor\u00cda, Ingenier\u00cda, Formaci\u00d3n)",
    "sg:phone":"+34 972 57 58 77",
    "sg:postcode":"17820",
    "sg:province":"Girona",
    "wof:name":"Pujadas Delclos Montserrat",
    "wof:placetype":"venue"
},
  "geometry": {"coordinates":[2.762914896,42.1192932129],"type":"Point"}
}