{
  "type": "Feature",
  "properties": {
    "addr:full":"Avda Sabino Arana, 52 Elexalde Vizcaya 48940",
    "addr:housenumber":"52",
    "addr:postcode":"48940",
    "addr:street":"Avda Sabino Arana",
    "iso:country":"ES",
    "sg:address":"Avda Sabino Arana, 52",
    "sg:city":"Elexalde",
    "sg:orig_category":"Supermercados Y Hipermercados",
    "sg:phone":"+34 944 63 16 29",
    "sg:postcode":"48940",
    "sg:province":"Vizcaya",
    "wof:name":"Supermercados Ceal S.a.",
    "wof:placetype":"venue"
},
  "geometry": {"coordinates":[-2.9868969917,43.3223304749],"type":"Point"}
}