{
  "type": "Feature",
  "properties": {
    "addr:full":"Via Suissa, 60 Ca'n Picafort Islas Baleares 07458",
    "addr:housenumber":"60",
    "addr:postcode":"07458",
    "addr:street":"Via Suissa",
    "iso:country":"ES",
    "sg:address":"Via Suissa, 60",
    "sg:city":"Ca'n Picafort",
    "sg:orig_category":"Electrodom\u00c9sticos (al Por Menor)",
    "sg:phone":"+34 971 85 10 97",
    "sg:postcode":"07458",
    "sg:province":"Islas Baleares",
    "wof:name":"Payeras C.b.",
    "wof:placetype":"venue"
},
  "geometry": {"coordinates":[2.9117100239,39.6136398315],"type":"Point"}
}