{
  "type": "Feature",
  "properties": {
    "iso:country":"ES",
    "sg:address":"Carr Magdalena, 17",
    "sg:city":"Lleida",
    "sg:orig_category":"Ropa Para Se\u00d1oras (al Por Menor)",
    "sg:phone":"+34 973 23 79 73",
    "sg:postcode":"25007",
    "sg:province":"Lleida",
    "wof:name":"Valentines Elies Enrique",
    "wof:placetype":"venue"
},
  "geometry": {"coordinates":[0.6290900111,41.6184692383],"type":"Point"}
}