{
  "type": "Feature",
  "properties": {
    "addr:full":"Calle de Federico Garcia Lorca, 15 Albacete Albacete 02001",
    "addr:housenumber":"15",
    "addr:postcode":"02001",
    "addr:street":"Calle De Federico Garcia Lorca",
    "iso:country":"ES",
    "sg:address":"Calle de Federico Garcia Lorca, 15",
    "sg:city":"Albacete",
    "sg:orig_category":"Impuestos, Tesoro P\u00dablico",
    "sg:phone":"+34 967 24 27 61",
    "sg:postcode":"02001",
    "sg:province":"Albacete",
    "wof:name":"O C Valoraciones Y Tasaciones S.l.",
    "wof:placetype":"venue"
},
  "geometry": {"coordinates":[-1.8464820385,38.9967765808],"type":"Point"}
}