{
  "type": "Feature",
  "properties": {
    "iso:country":"ES",
    "sg:address":"Pl Reis Catolics, 37",
    "sg:city":"Elche",
    "sg:orig_category":"Asesor\u00cda Sobre Comunicaci\u00d3n De Empresas",
    "sg:phone":"+34 966 67 58 82",
    "sg:postcode":"03201",
    "sg:province":"Alicante",
    "wof:name":"Asesoria Belmar S.l.",
    "wof:placetype":"venue"
},
  "geometry": {"coordinates":[-0.7012326121,38.2612266541],"type":"Point"}
}