{
  "type": "Feature",
  "properties": {
    "addr:full":"Carr Tosqueres (les), 4 Moraira Alicante 03724",
    "addr:housenumber":"4",
    "addr:postcode":"03724",
    "addr:street":"Carr Tosqueres Les",
    "iso:country":"ES",
    "sg:address":"Carr Tosqueres (les), 4",
    "sg:city":"Moraira",
    "sg:orig_category":"Inmobiliaria (agencias)",
    "sg:phone":"+34 966 49 11 30",
    "sg:postcode":"03724",
    "sg:province":"Alicante",
    "wof:name":"Tosqueres Home S.l.",
    "wof:placetype":"venue"
},
  "geometry": {"coordinates":[0.1331350058,38.68800354],"type":"Point"}
}