{
  "type": "Feature",
  "properties": {
    "addr:full":"Calle de Comercio (del), 35 Tres Cantos Madrid 28760",
    "addr:postcode":"28760",
    "addr:street":"Calle De;Del",
    "iso:country":"ES",
    "sg:address":"Calle de Comercio (del), 35",
    "sg:city":"Tres Cantos",
    "sg:orig_category":"Ropa Para Ni\u00d1os (al Por Menor)",
    "sg:phone":"+34 918 04 71 83",
    "sg:postcode":"28760",
    "sg:province":"Madrid",
    "wof:name":"Mu\u00f1oz Prado Angela Maria",
    "wof:placetype":"venue"
},
  "geometry": {"coordinates":[-3.7103652954,40.6005210876],"type":"Point"}
}