{
  "type": "Feature",
  "properties": {
    "addr:full":"Calle de Torres, 1 Do\u00e7a Mencia C\u00f3rdoba 14860",
    "addr:housenumber":"1",
    "addr:postcode":"14860",
    "addr:street":"Calle De Torres;Co\u0301Rdoba",
    "iso:country":"ES",
    "sg:address":"Calle de Torres, 1",
    "sg:city":"Do\u00e7a Mencia",
    "sg:orig_category":"Alimentaci\u00d3n General (al Por Menor)",
    "sg:phone":"+34 957 67 62 50",
    "sg:postcode":"14860",
    "sg:province":"C\u00f3rdoba",
    "wof:name":"Urbano Moreno Manuel",
    "wof:placetype":"venue"
},
  "geometry": {"coordinates":[-4.3586421013,37.5558204651],"type":"Point"}
}