{
  "type": "Feature",
  "properties": {
    "iso:country":"ES",
    "sg:address":"Calle de Mayor, 27",
    "sg:city":"Ciempozuelos",
    "sg:orig_category":"Fiesta: Art\u00cdculos De (al Por Menor)",
    "sg:phone":"+34 918 93 37 19",
    "sg:postcode":"28350",
    "sg:province":"Madrid",
    "wof:name":"Siger Saez Y Garcia, S.l",
    "wof:placetype":"venue"
},
  "geometry": {"coordinates":[-3.6201779842,40.1582603455],"type":"Point"}
}