{
  "type": "Feature",
  "properties": {
    "iso:country":"ES",
    "sg:address":"Calle de Belmonte De Miranda, 3",
    "sg:city":"Gijon",
    "sg:orig_category":"Alimentaci\u00d3n General (al Por Menor)",
    "sg:phone":"+34 985 17 22 87",
    "sg:postcode":"33206",
    "sg:province":"Asturias",
    "wof:name":"Uria Gonzalez Maria Luisa",
    "wof:placetype":"venue"
},
  "geometry": {"coordinates":[-5.668419838,43.5412750244],"type":"Point"}
}