{
  "type": "Feature",
  "properties": {
    "iso:country":"ES",
    "sg:address":"Calle de Eliana (la), 5",
    "sg:city":"Mislata",
    "sg:orig_category":"Confecci\u00d3n (fabricaci\u00d3n, Al Por Mayor)",
    "sg:phone":"+34 963 70 72 07",
    "sg:postcode":"46920",
    "sg:province":"Valencia",
    "wof:name":"Confecciones Elegar S.l.",
    "wof:placetype":"venue"
},
  "geometry": {"coordinates":[-0.4191179872,39.4777069092],"type":"Point"}
}