{
  "type": "Feature",
  "properties": {
    "iso:country":"ES",
    "sg:address":"La Ermita, 13",
    "sg:city":"Villaquilambre",
    "sg:orig_category":"Promotores Constructores",
    "sg:phone":"+34 987 28 30 09",
    "sg:postcode":"24008",
    "sg:province":"Le\u00f3n",
    "wof:name":"Gopifersa S.l.",
    "wof:placetype":"venue"
},
  "geometry": {"coordinates":[-5.5568561554,42.6422729492],"type":"Point"}
}