{
  "type": "Feature",
  "properties": {
    "addr:full":"Calle de Cardo, S/n San Leandro Sevilla 41730",
    "addr:housenumber":"s / n",
    "addr:postcode":"41730",
    "addr:street":"Calle De Cardo",
    "iso:country":"ES",
    "sg:address":"Calle de Cardo, S/n",
    "sg:city":"San Leandro",
    "sg:orig_category":"Producci\u00d3n, Comercio De Cereales",
    "sg:phone":"+34 955 87 48 08",
    "sg:postcode":"41730",
    "sg:province":"Sevilla",
    "wof:name":"Cereales San Francisco S.l.",
    "wof:placetype":"venue"
},
  "geometry": {"coordinates":[-5.9959135056,37.0317764282],"type":"Point"}
}