{
  "type": "Feature",
  "properties": {
    "iso:country":"ES",
    "sg:address":"Calle de Puerto Alto, 1",
    "sg:city":"Madrid",
    "sg:orig_category":"Electrodom\u00c9sticos (al Por Menor)",
    "sg:phone":"+34 914 78 45 66",
    "sg:postcode":"28053",
    "sg:province":"Madrid",
    "sg:website":"www.expert.es",
    "wof:name":"Electrodomesticos Bulevar S.l.",
    "wof:placetype":"venue"
},
  "geometry": {"coordinates":[-3.6661229134,40.3950119019],"type":"Point"}
}