{
  "type": "Feature",
  "properties": {
    "iso:country":"ES",
    "sg:address":"Calle de Pascual De La Mata, 15",
    "sg:city":"Alacant",
    "sg:orig_category":"Carnicer\u00cdas, Carnicer\u00cdas",
    "sg:phone":"+34 965 25 81 37",
    "sg:postcode":"03012",
    "sg:province":"Alicante",
    "wof:name":"Torregrosa Senia Rafael",
    "wof:placetype":"venue"
},
  "geometry": {"coordinates":[-0.4819889963,38.3608398438],"type":"Point"}
}