{
  "type": "Feature",
  "properties": {
    "iso:country":"ES",
    "sg:address":"Avda Palafox, 15",
    "sg:city":"Pastriz",
    "sg:orig_category":"Cajas Para Embalar",
    "sg:phone":"+34 976 58 67 26",
    "sg:postcode":"50195",
    "sg:province":"Zaragoza",
    "sg:website":"www.cajalon.es",
    "wof:name":"Caja Rural De Aragon S.coop Credito",
    "wof:placetype":"venue"
},
  "geometry": {"coordinates":[-0.7810860276,41.6174621582],"type":"Point"}
}