{
  "type": "Feature",
  "properties": {
    "addr:full":"Carr Palol D'onyar, 5 Font De La Polvora Girona 17004",
    "addr:housenumber":"5",
    "addr:postcode":"17004",
    "addr:street":"Carr Palol D'Onyar",
    "iso:country":"ES",
    "sg:address":"Carr Palol D'onyar, 5",
    "sg:city":"Font De La Polvora",
    "sg:orig_category":"Promotores Constructores",
    "sg:phone":"+34 972 41 19 12",
    "sg:postcode":"17004",
    "sg:province":"Girona",
    "wof:name":"Cetub S.l.",
    "wof:placetype":"venue"
},
  "geometry": {"coordinates":[2.8419640064,41.9752883911],"type":"Point"}
}