{
  "type": "Feature",
  "properties": {
    "iso:country":"ES",
    "sg:address":"Plaz Emilio Diez De Revenga, 5",
    "sg:city":"San Miguel",
    "sg:orig_category":"Confecci\u00d3n (fabricaci\u00d3n, Al Por Mayor)",
    "sg:phone":"+34 968 23 29 05",
    "sg:postcode":"30008",
    "sg:province":"Murcia",
    "wof:name":"Rios Martinez Juan Antonio",
    "wof:placetype":"venue"
},
  "geometry": {"coordinates":[-1.135841012,37.9912147522],"type":"Point"}
}