{
  "type": "Feature",
  "properties": {
    "addr:full":"Calle de Unamuno, 15 Almonte Huelva 21730",
    "addr:housenumber":"15",
    "addr:postcode":"21730",
    "addr:street":"Calle De Unamuno",
    "iso:country":"ES",
    "sg:address":"Calle de Unamuno, 15",
    "sg:city":"Almonte",
    "sg:orig_category":"Restaurantes",
    "sg:phone":"+34 959 40 69 55",
    "sg:postcode":"21730",
    "sg:province":"Huelva",
    "wof:name":"Meson Rosendo S.l.",
    "wof:placetype":"venue"
},
  "geometry": {"coordinates":[-6.5151319504,37.2632751465],"type":"Point"}
}