{
  "type": "Feature",
  "properties": {
    "addr:full":"Calle de Nieves, 12 Bola\u00e7os De Calatrava Ciudad Real 13260",
    "addr:housenumber":"12",
    "addr:postcode":"13260",
    "addr:street":"Calle De Nieves",
    "iso:country":"ES",
    "sg:address":"Calle de Nieves, 12",
    "sg:city":"Bola\u00e7os De Calatrava",
    "sg:orig_category":"Telas Y Sedas (al Por Menor)",
    "sg:phone":"+34 926 87 03 55",
    "sg:postcode":"13260",
    "sg:province":"Ciudad Real",
    "wof:name":"Sanchez Ruiz Valdepe\u00f1as Elvira",
    "wof:placetype":"venue"
},
  "geometry": {"coordinates":[-3.6663589478,38.906791687],"type":"Point"}
}