{
  "type": "Feature",
  "properties": {
    "addr:full":"Avda Arcadio Pardi\u00d1as, 95 Burela Lugo 27880",
    "addr:housenumber":"95",
    "addr:postcode":"27880",
    "addr:street":"Avda Arcadio Pardin\u0303As",
    "iso:country":"ES",
    "sg:address":"Avda Arcadio Pardi\u00d1as, 95",
    "sg:city":"Burela",
    "sg:orig_category":"Centros Empresariales",
    "sg:phone":"+34 982 58 56 48",
    "sg:postcode":"27880",
    "sg:province":"Lugo",
    "wof:name":"Confederacion Empresarial De La Provincia De Lugo",
    "wof:placetype":"venue"
},
  "geometry": {"coordinates":[-7.3598661423,43.6577148438],"type":"Point"}
}