{
  "type": "Feature",
  "properties": {
    "iso:country":"ES",
    "sg:address":"Plaz Mayor, 12",
    "sg:city":"Roda",
    "sg:orig_category":"Cl\u00cdnicas Dentales",
    "sg:phone":"+34 967 44 38 49",
    "sg:postcode":"02630",
    "sg:province":"Albacete",
    "wof:name":"Clinicas Odontologicas Saludent S.l.",
    "wof:placetype":"venue"
},
  "geometry": {"coordinates":[-2.1636590958,39.1957206726],"type":"Point"}
}