{
  "type": "Feature",
  "properties": {
    "addr:full":"Pg Fabra I Puig, 431 Barcelona Barcelona 08042",
    "addr:housenumber":"431",
    "addr:postcode":"08042",
    "addr:street":"Pg Fabra I Puig",
    "iso:country":"ES",
    "sg:address":"Pg Fabra I Puig, 431",
    "sg:city":"Barcelona",
    "sg:orig_category":"Peluquer\u00cdas, Peluquer\u00cda Mixta",
    "sg:phone":"+34 934 28 30 46",
    "sg:postcode":"08042",
    "sg:province":"Barcelona",
    "wof:name":"Garcia Santos Maria Carmen",
    "wof:placetype":"venue"
},
  "geometry": {"coordinates":[2.1653590202,41.4382514954],"type":"Point"}
}