{
  "type": "Feature",
  "properties": {
    "iso:country":"ES",
    "sg:address":"Trva Sousas (de), 23",
    "sg:city":"Verin",
    "sg:orig_category":"Contenedores (mercanc\u00cdas)",
    "sg:phone":"+34 988 41 02 21",
    "sg:postcode":"32600",
    "sg:province":"Ourense",
    "wof:name":"Perez Carrajo Saturnino",
    "wof:placetype":"venue"
},
  "geometry": {"coordinates":[-7.4346041679,41.9415092468],"type":"Point"}
}