{
  "type": "Feature",
  "properties": {
    "addr:full":"Ctra Ledesma, 105 Salamanca Salamanca 37006",
    "addr:housenumber":"105",
    "addr:postcode":"37006",
    "addr:street":"Ctra Ledesma",
    "iso:country":"ES",
    "sg:address":"Ctra Ledesma, 105",
    "sg:city":"Salamanca",
    "sg:orig_category":"Autob\u00das (explotaci\u00d3n Y Servicios De)",
    "sg:phone":"+34 923 25 79 00",
    "sg:postcode":"37006",
    "sg:province":"Salamanca",
    "wof:name":"Rodriguez Vicente Andres",
    "wof:placetype":"venue"
},
  "geometry": {"coordinates":[-5.6761212349,40.9781990051],"type":"Point"}
}