{
  "type": "Feature",
  "properties": {
    "iso:country":"ES",
    "sg:address":"Calle de Trinidad, 3",
    "sg:city":"Sacramenia",
    "sg:orig_category":"Bancos",
    "sg:phone":"+34 921 52 70 94",
    "sg:postcode":"40237",
    "sg:province":"Segovia",
    "wof:name":"Banco Espa\u00f1ol De Credito S.a.",
    "wof:placetype":"venue"
},
  "geometry": {"coordinates":[-3.9627990723,41.4937171936],"type":"Point"}
}