{
  "type": "Feature",
  "properties": {
    "iso:country":"ES",
    "sg:address":"Carrer de Escoles, 8",
    "sg:city":"Malgrat Mar",
    "sg:classifiers":[
        {
            "category":"Personal",
            "subcategory":"Barber",
            "type":"Services"
        }
    ],
    "sg:phone":"+34 937 61 31 66",
    "sg:postcode":"08380",
    "sg:province":"Barcelona",
    "sg:tags":[
        "caballeros",
        "de",
        "peluqueros"
    ],
    "wof:name":"Ribas Crosas Delfin",
    "wof:placetype":"venue"
},
  "geometry": {"coordinates":[2.7391250134,41.6437187195],"type":"Point"}
}