{
  "type": "Feature",
  "properties": {
    "iso:country":"ES",
    "sg:address":"Calle de Lealtad, 16",
    "sg:city":"Gijon",
    "sg:orig_category":"Molduras, Junquillos, Listones Y Molduras Perforadas",
    "sg:phone":"+34 985 31 54 52",
    "sg:postcode":"33212",
    "sg:province":"Asturias",
    "wof:name":"Sistelcom-telemensaje S.a.",
    "wof:placetype":"venue"
},
  "geometry": {"coordinates":[-5.6814222336,43.5392036438],"type":"Point"}
}