{
  "type": "Feature",
  "properties": {
    "addr:full":"Calle de Mesones, 39 Constantina Sevilla 41450",
    "addr:housenumber":"39",
    "addr:postcode":"41450",
    "addr:street":"Calle De Mesones",
    "iso:country":"ES",
    "sg:address":"Calle de Mesones, 39",
    "sg:city":"Constantina",
    "sg:orig_category":"Caf\u00c9s, Bares, Cervecer\u00cdas",
    "sg:phone":"+34 955 88 01 89",
    "sg:postcode":"41450",
    "sg:province":"Sevilla",
    "wof:name":"Infasur S.l.",
    "wof:placetype":"venue"
},
  "geometry": {"coordinates":[-5.6196241379,37.8735771179],"type":"Point"}
}