{
  "type": "Feature",
  "properties": {
    "addr:full":"Carrer de Sas, 31 Barcelona Barcelona 08030",
    "addr:housenumber":"31",
    "addr:postcode":"08030",
    "addr:street":"Carrer De Sas",
    "iso:country":"ES",
    "sg:address":"Carrer de Sas, 31",
    "sg:city":"Barcelona",
    "sg:orig_category":"Farmacias",
    "sg:phone":"+34 933 45 50 19",
    "sg:postcode":"08030",
    "sg:province":"Barcelona",
    "wof:name":"Garcia Modrego Enrique",
    "wof:placetype":"venue"
},
  "geometry": {"coordinates":[2.2041780949,41.4375228882],"type":"Point"}
}