{
  "type": "Feature",
  "properties": {
    "iso:country":"ES",
    "sg:address":"Plaz Sol (del), 13",
    "sg:city":"Alcorcon",
    "sg:orig_category":"Cajas De Ahorro",
    "sg:phone":"+34 914 86 12 36",
    "sg:postcode":"28922",
    "sg:province":"Madrid",
    "sg:website":"www.cajamar.es",
    "wof:name":"Cajamar",
    "wof:placetype":"venue"
},
  "geometry": {"coordinates":[-3.8242239952,40.3513946533],"type":"Point"}
}