{
  "type": "Feature",
  "properties": {
    "iso:country":"ES",
    "sg:address":"Calle de Vi\u00d1a (de La), 21",
    "sg:city":"Velilla S.antonio",
    "sg:orig_category":"Tubos Y Tuber\u00cdas De Goma Y Pl\u00c1stico (fabricaci\u00d3n, Al Por Mayor)",
    "sg:phone":"+34 916 55 12 41",
    "sg:postcode":"28891",
    "sg:province":"Madrid",
    "wof:name":"Continental Tires Espa\u00f1a S.l.",
    "wof:placetype":"venue"
},
  "geometry": {"coordinates":[-3.4893369675,40.3706130981],"type":"Point"}
}