{
  "type": "Feature",
  "properties": {
    "addr:full":"Carrer de Ros De Olano, 7 Barcelona Barcelona 08012",
    "addr:housenumber":"7",
    "addr:postcode":"08012",
    "addr:street":"Carrer De Ros De Olano",
    "iso:country":"ES",
    "sg:address":"Carrer de Ros De Olano, 7",
    "sg:city":"Barcelona",
    "sg:orig_category":"Cristaler\u00cdas",
    "sg:phone":"+34 932 37 55 48",
    "sg:postcode":"08012",
    "sg:province":"Barcelona",
    "wof:name":"Lazaro Palau Maria Dolors",
    "wof:placetype":"venue"
},
  "geometry": {"coordinates":[2.1546459198,41.4011802673],"type":"Point"}
}