{
  "type": "Feature",
  "properties": {
    "iso:country":"ES",
    "sg:address":"Avda Joselito El Gallo, 157",
    "sg:city":"Dos Hermanas",
    "sg:orig_category":"Empresas De Carpinter\u00cda Met\u00c1lica",
    "sg:phone":"+34 955 66 88 80",
    "sg:postcode":"41700",
    "sg:province":"Sevilla",
    "wof:name":"Molina Alonso Alberto",
    "wof:placetype":"venue"
},
  "geometry": {"coordinates":[-5.9040169716,37.2890396118],"type":"Point"}
}