{
  "type": "Feature",
  "properties": {
    "iso:country":"ES",
    "sg:address":"Calle de Erribera, S/n",
    "sg:city":"Ondarroa",
    "sg:orig_category":"Frutas, Legumbres Frescas Y Tempranas (al Por Menor)",
    "sg:phone":"+34 946 83 02 42",
    "sg:postcode":"48700",
    "sg:province":"Vizcaya",
    "wof:name":"Urresti Bedialauneta Jose Antonio",
    "wof:placetype":"venue"
},
  "geometry": {"coordinates":[-2.4233090878,43.3203811646],"type":"Point"}
}