{
  "type": "Feature",
  "properties": {
    "addr:full":"Calle de Alicante, 12 Arganda Madrid 28500",
    "addr:housenumber":"12",
    "addr:postcode":"28500",
    "addr:street":"Calle De Alicante",
    "iso:country":"ES",
    "sg:address":"Calle de Alicante, 12",
    "sg:city":"Arganda",
    "sg:orig_category":"Artes Gr\u00c1ficas, Artes Pl\u00c1sticas (curso)",
    "sg:phone":"+34 918 71 57 76",
    "sg:postcode":"28500",
    "sg:province":"Madrid",
    "wof:name":"Rota Rent S.l.",
    "wof:placetype":"venue"
},
  "geometry": {"coordinates":[-3.4589004517,40.3074111938],"type":"Point"}
}