{
  "type": "Feature",
  "properties": {
    "iso:country":"ES",
    "sg:address":"Carretera Del Puerto, S/n",
    "sg:city":"Plasencia",
    "sg:orig_category":"Discapacitados",
    "sg:phone":"+34 927 41 98 87",
    "sg:postcode":"10600",
    "sg:province":"C\u00e1ceres",
    "wof:name":"Asociacion Familiar Y Emfermo Mental De Plasencia",
    "wof:placetype":"venue"
},
  "geometry": {"coordinates":[-6.0838937759,40.0411911011],"type":"Point"}
}