{
  "type": "Feature",
  "properties": {
    "iso:country":"ES",
    "sg:address":"Pla\u00c7 Major, 12",
    "sg:city":"Sant Marti D'empuries",
    "sg:orig_category":"Restaurantes",
    "sg:phone":"+34 972 77 33 80",
    "sg:postcode":"17130",
    "sg:province":"Girona",
    "wof:name":"Male Gardella Joan",
    "wof:placetype":"venue"
},
  "geometry": {"coordinates":[3.1180410385,42.139755249],"type":"Point"}
}