{
  "type": "Feature",
  "properties": {
    "addr:full":"Avda Alcora, 56 Castellon Castell\u00f3n 12006",
    "addr:housenumber":"56",
    "addr:postcode":"12006",
    "addr:street":"Avda Alcora",
    "iso:country":"ES",
    "sg:address":"Avda Alcora, 56",
    "sg:city":"Castellon",
    "sg:orig_category":"Autob\u00das (explotaci\u00d3n Y Servicios De)",
    "sg:phone":"+34 964 20 18 35",
    "sg:postcode":"12006",
    "sg:province":"Castell\u00f3n",
    "wof:name":"Cruz Edo Marcelo",
    "wof:placetype":"venue"
},
  "geometry": {"coordinates":[-0.1292939931,40.0168533325],"type":"Point"}
}