{
  "type": "Feature",
  "properties": {
    "iso:country":"ES",
    "sg:address":"Avda Oroel, 8",
    "sg:city":"Jaca",
    "sg:orig_category":"Agentes Generales De Seguros",
    "sg:phone":"+34 974 36 11 16",
    "sg:postcode":"22700",
    "sg:province":"Huesca",
    "wof:name":"Campo Beltran Maria Luisa",
    "wof:placetype":"venue"
},
  "geometry": {"coordinates":[-0.5466790199,42.5682296753],"type":"Point"}
}