{
  "type": "Feature",
  "properties": {
    "addr:full":"Calle de Guecho, 29 Madrid Madrid 28023",
    "addr:housenumber":"29",
    "addr:postcode":"madrid;28023",
    "addr:street":"Calle De Guecho",
    "iso:country":"ES",
    "sg:address":"Calle de Guecho, 29",
    "sg:city":"Madrid",
    "sg:orig_category":"Arquitectos",
    "sg:phone":"+34 913 07 70 39",
    "sg:postcode":"28023",
    "sg:province":"Madrid",
    "wof:name":"Cano Lasso Julio",
    "wof:placetype":"venue"
},
  "geometry": {"coordinates":[-3.8190660477,40.4738044739],"type":"Point"}
}