{
  "type": "Feature",
  "properties": {
    "iso:country":"ES",
    "sg:address":"Calle de Felix Aramburu, 10",
    "sg:city":"Oviedo",
    "sg:classifiers":[
        {
            "category":"Personal",
            "subcategory":"Barber",
            "type":"Services"
        }
    ],
    "sg:phone":"+34 985 27 73 64",
    "sg:postcode":"33007",
    "sg:province":"Asturias",
    "sg:tags":[
        "caballeros",
        "de",
        "peluqueros"
    ],
    "wof:name":"Rodriguez Fernandez Jacinto",
    "wof:placetype":"venue"
},
  "geometry": {"coordinates":[-5.8519759178,43.3562774658],"type":"Point"}
}