{
  "type": "Feature",
  "properties": {
    "iso:country":"ES",
    "sg:address":"Carr Florenci Valls, 91",
    "sg:city":"Igualada",
    "sg:orig_category":"Alimentaci\u00d3n General (al Por Menor)",
    "sg:phone":"+34 938 05 53 61",
    "sg:postcode":"08700",
    "sg:province":"Barcelona",
    "wof:name":"Supermercado Super Mas S.l.",
    "wof:placetype":"venue"
},
  "geometry": {"coordinates":[1.6258679628,41.5815544128],"type":"Point"}
}