{
  "type": "Feature",
  "properties": {
    "addr:full":"Barrio La Calle, 98 Villanueva Pe\u00f1a Cantabria 39509",
    "addr:postcode":"39509",
    "addr:street":"Barrio La Calle 98",
    "iso:country":"ES",
    "sg:address":"Barrio La Calle, 98",
    "sg:city":"Villanueva Pe\u00f1a",
    "sg:orig_category":"Molduras, Junquillos, Listones Y Molduras Perforadas",
    "sg:phone":"+34 942 70 82 94",
    "sg:postcode":"39509",
    "sg:province":"Cantabria",
    "wof:name":"Perez Cobo Jose Antonio",
    "wof:placetype":"venue"
},
  "geometry": {"coordinates":[-4.2100739479,43.2973518372],"type":"Point"}
}