{
  "type": "Feature",
  "properties": {
    "addr:full":"Calle de Zaragoza (de), 1 Humanes De Madrid Madrid 28970",
    "addr:postcode":"28970",
    "addr:street":"Calle De Zaragoza De 1",
    "iso:country":"ES",
    "sg:address":"Calle de Zaragoza (de), 1",
    "sg:city":"Humanes De Madrid",
    "sg:orig_category":"Suministros Para Exposiciones, Ferias, Salones",
    "sg:phone":"+34 916 97 32 05",
    "sg:postcode":"28970",
    "sg:province":"Madrid",
    "sg:website":"www.fejsa.com",
    "wof:name":"Fej S.a.",
    "wof:placetype":"venue"
},
  "geometry": {"coordinates":[-3.824048996,40.2761917114],"type":"Point"}
}