{
  "type": "Feature",
  "properties": {
    "addr:full":"Calle de Pico Del Aguila (del), 24 Humanes De Madrid Madrid 28970",
    "addr:postcode":"28970",
    "addr:street":"Calle De Pico Del;Del",
    "iso:country":"ES",
    "sg:address":"Calle de Pico Del Aguila (del), 24",
    "sg:city":"Humanes De Madrid",
    "sg:orig_category":"Muebles, Minoristas",
    "sg:phone":"+34 916 04 92 94",
    "sg:postcode":"28970",
    "sg:province":"Madrid",
    "wof:name":"Antonio Herraiz S.a.",
    "wof:placetype":"venue"
},
  "geometry": {"coordinates":[-3.8128190041,40.2609291077],"type":"Point"}
}