{
  "type": "Feature",
  "properties": {
    "iso:country":"ES",
    "sg:address":"Zona Afores, S/n",
    "sg:city":"Calella",
    "sg:orig_category":"Asociaciones Y Clubs Deportivos",
    "sg:phone":"+34 937 69 02 48",
    "sg:postcode":"08370",
    "sg:province":"Barcelona",
    "wof:name":"Club D'atletisme Calella",
    "wof:placetype":"venue"
},
  "geometry": {"coordinates":[2.6572299004,41.6146011353],"type":"Point"}
}