{
  "type": "Feature",
  "properties": {
    "iso:country":"ES",
    "sg:address":"Av Jaume Iii, 11",
    "sg:city":"Palma",
    "sg:orig_category":"Doctores En Medicina",
    "sg:phone":"+34 971 22 82 17",
    "sg:postcode":"07012",
    "sg:province":"Islas Baleares",
    "wof:name":"Beut Cabrera Francisco Javier",
    "wof:placetype":"venue"
},
  "geometry": {"coordinates":[2.6454091072,39.5718994141],"type":"Point"}
}