{
  "type": "Feature",
  "properties": {
    "addr:full":"Calle de Alibarra, 22 Vitoria-gasteiz \u00c1lava 01010",
    "addr:housenumber":"22",
    "addr:postcode":"01010",
    "addr:street":"Calle De Alibarra",
    "iso:country":"ES",
    "sg:address":"Calle de Alibarra, 22",
    "sg:city":"Vitoria-gasteiz",
    "sg:orig_category":"Fabricaci\u00d3n De Ventanas",
    "sg:phone":"+34 945 24 63 66",
    "sg:postcode":"01010",
    "sg:province":"\u00c1lava",
    "wof:name":"Juan Lopez E Hijos S. L.",
    "wof:placetype":"venue"
},
  "geometry": {"coordinates":[-2.7175569534,42.8610191345],"type":"Point"}
}