{
  "type": "Feature",
  "properties": {
    "addr:full":"Calle de Ramon Y Cajal, 96 Portillo Toledo Toledo 45512",
    "addr:housenumber":"96",
    "addr:postcode":"45512",
    "addr:street":"Calle De Ramon Y Cajal",
    "iso:country":"ES",
    "sg:address":"Calle de Ramon Y Cajal, 96",
    "sg:city":"Portillo Toledo",
    "sg:orig_category":"Cerrajer\u00cda, Ferrallista",
    "sg:phone":"+34 925 78 50 32",
    "sg:postcode":"45512",
    "sg:province":"Toledo",
    "wof:name":"Martin Gomez Maria Dolores Gravina",
    "wof:placetype":"venue"
},
  "geometry": {"coordinates":[-4.2271680832,40.065032959],"type":"Point"}
}