{
  "type": "Feature",
  "properties": {
    "iso:country":"ES",
    "sg:address":"Mercamurcia, S/n",
    "sg:city":"El Palmar",
    "sg:orig_category":"Distribuci\u00d3n De Petr\u00d3leo Y Derivados",
    "sg:phone":"+34 968 86 95 25",
    "sg:postcode":"30120",
    "sg:province":"Murcia",
    "wof:name":"Speed Oil S.a",
    "wof:placetype":"venue"
},
  "geometry": {"coordinates":[-1.1922440529,37.9298095703],"type":"Point"}
}