{
  "type": "Feature",
  "properties": {
    "addr:full":"Calle de Salud Tejero, 18 Ceuta Ceuta 51001",
    "addr:housenumber":"18",
    "addr:postcode":"51001",
    "addr:street":"Calle De Salud Tejero",
    "iso:country":"ES",
    "sg:address":"Calle de Salud Tejero, 18",
    "sg:city":"Ceuta",
    "sg:orig_category":"Agencias Y Asesores De Publicidad",
    "sg:phone":"+34 956 51 24 11",
    "sg:postcode":"51001",
    "sg:province":"Ceuta",
    "wof:name":"Benitez Blazquez Angel Jose",
    "wof:placetype":"venue"
},
  "geometry": {"coordinates":[-5.3036990166,35.8898506165],"type":"Point"}
}