{
  "type": "Feature",
  "properties": {
    "addr:full":"Av Madrid, 65 Terrassa Barcelona 08227",
    "addr:housenumber":"65",
    "addr:postcode":"08227",
    "addr:street":"Av Madrid",
    "iso:country":"ES",
    "sg:address":"Av Madrid, 65",
    "sg:city":"Terrassa",
    "sg:orig_category":"Laboratorios Farmac\u00c9uticos",
    "sg:phone":"+34 937 84 03 28",
    "sg:postcode":"08227",
    "sg:province":"Barcelona",
    "wof:name":"Diasorin S.a.",
    "wof:placetype":"venue"
},
  "geometry": {"coordinates":[2.0376489162,41.5606079102],"type":"Point"}
}