{
  "type": "Feature",
  "properties": {
    "addr:full":"Rbla Pompeu Fabra, 24 Mollet Valles Barcelona 08100",
    "addr:housenumber":"24",
    "addr:postcode":"08100",
    "addr:street":"Rbla Pompeu Fabra",
    "iso:country":"ES",
    "sg:address":"Rbla Pompeu Fabra, 24",
    "sg:city":"Mollet Valles",
    "sg:orig_category":"Carnicer\u00cdas, Carnicer\u00cdas",
    "sg:phone":"+34 935 93 44 52",
    "sg:postcode":"08100",
    "sg:province":"Barcelona",
    "wof:name":"El Tastet De La Rambla",
    "wof:placetype":"venue"
},
  "geometry": {"coordinates":[2.2181560993,41.5394363403],"type":"Point"}
}