{
  "type": "Feature",
  "properties": {
    "iso:country":"ES",
    "sg:address":"Sect Pueblos, 5",
    "sg:city":"Tres Cantos",
    "sg:orig_category":"Reposter\u00cdas",
    "sg:phone":"+34 918 04 49 19",
    "sg:postcode":"28760",
    "sg:province":"Madrid",
    "wof:name":"Tahona Virgen Del Rosario S.l",
    "wof:placetype":"venue"
},
  "geometry": {"coordinates":[-3.7133069038,40.6112251282],"type":"Point"}
}