{
  "type": "Feature",
  "properties": {
    "addr:full":"Pio Xii, S/n Igualeja M\u00e1laga 29440",
    "addr:housenumber":"s / n",
    "addr:postcode":"29440",
    "addr:street":"Pio Xii",
    "iso:country":"ES",
    "sg:address":"Pio Xii, S/n",
    "sg:city":"Igualeja",
    "sg:orig_category":"Iglesia Cat\u00d3lica",
    "sg:phone":"+34 952 18 15 08",
    "sg:postcode":"29440",
    "sg:province":"M\u00e1laga",
    "wof:name":"Parroquia De Santa Rosa De Lima",
    "wof:placetype":"venue"
},
  "geometry": {"coordinates":[-5.1205730438,36.6307182312],"type":"Point"}
}