{
  "type": "Feature",
  "properties": {
    "addr:full":"Calle de Carmen (del), 6 Jaca Huesca 22700",
    "addr:housenumber":"6",
    "addr:postcode":"22700",
    "addr:street":"Calle De Carmen Del",
    "iso:country":"ES",
    "sg:address":"Calle de Carmen (del), 6",
    "sg:city":"Jaca",
    "sg:classifiers":[
        {
            "category":"Casinos & Gambling",
            "type":"Entertainment"
        }
    ],
    "sg:phone":"+34 974 36 10 11",
    "sg:postcode":"22700",
    "sg:province":"Huesca",
    "sg:tags":[
        "locale",
        "de",
        "juego"
    ],
    "wof:name":"Casino Union Jaquesa",
    "wof:placetype":"venue"
},
  "geometry": {"coordinates":[-0.5504161716,42.5692253113],"type":"Point"}
}