{
  "type": "Feature",
  "properties": {
    "addr:full":"Av. Blasco Iba\u00f1ez, 28 Massanassa Valencia 46470",
    "addr:housenumber":"28",
    "addr:postcode":"46470",
    "addr:street":"Av. Blasco Iban\u0303Ez",
    "iso:country":"ES",
    "sg:address":"Av. Blasco Iba\u00f1ez, 28",
    "sg:city":"Massanassa",
    "sg:orig_category":"Loter\u00cda Y T\u00d3mbola",
    "sg:phone":"+34 961 25 15 29",
    "sg:postcode":"46470",
    "sg:province":"Valencia",
    "wof:name":"Martinez Cosme Vicente",
    "wof:placetype":"venue"
},
  "geometry": {"coordinates":[-0.4005019963,39.4099617004],"type":"Point"}
}