{
  "type": "Feature",
  "properties": {
    "addr:full":"Barr Elechino, S/n Entrambasaguas Cantabria 39715",
    "addr:housenumber":"s / n",
    "addr:postcode":"39715",
    "addr:street":"Barr Elechino",
    "iso:country":"ES",
    "sg:address":"Barr Elechino, S/n",
    "sg:city":"Entrambasaguas",
    "sg:orig_category":"Delegados, Agentes De Tr\u00c1nsito, Auxiliares De Transporte Internacional",
    "sg:phone":"+34 942 52 51 13",
    "sg:postcode":"39715",
    "sg:province":"Cantabria",
    "wof:name":"Diaz Polanco Carmelo",
    "wof:placetype":"venue"
},
  "geometry": {"coordinates":[-3.6755180359,43.3746910095],"type":"Point"}
}