{
  "type": "Feature",
  "properties": {
    "addr:full":"Calle de Melendez Valdes, 47 Madrid Madrid 28015",
    "addr:housenumber":"47",
    "addr:postcode":"madrid;28015",
    "addr:street":"Calle De Melendez Valdes",
    "iso:country":"ES",
    "sg:address":"Calle de Melendez Valdes, 47",
    "sg:city":"Madrid",
    "sg:orig_category":"Promotores Constructores",
    "sg:phone":"+34 915 49 13 03",
    "sg:postcode":"28015",
    "sg:province":"Madrid",
    "wof:name":"Bojuna S.l.",
    "wof:placetype":"venue"
},
  "geometry": {"coordinates":[-3.7142930031,40.432926178],"type":"Point"}
}