{
  "type": "Feature",
  "properties": {
    "iso:country":"ES",
    "sg:address":"Carrer de Mestre Rius, 15",
    "sg:city":"Sabadell",
    "sg:orig_category":"Fabricaci\u00d3n De Sobres, Bolsas Y Fundas",
    "sg:phone":"+34 937 27 13 03",
    "sg:postcode":"08202",
    "sg:province":"Barcelona",
    "wof:name":"Botiga Ostrell S.l.",
    "wof:placetype":"venue"
},
  "geometry": {"coordinates":[2.1096999645,41.5475387573],"type":"Point"}
}