{
  "type": "Feature",
  "properties": {
    "iso:country":"ES",
    "sg:address":"Calle de Calderon De La Barca, 24",
    "sg:city":"Cuenca",
    "sg:orig_category":"Ingeniero",
    "sg:phone":"+34 969 22 23 67",
    "sg:postcode":"16001",
    "sg:province":"Cuenca",
    "wof:name":"Gonzalez Herraiz Luis Miguel",
    "wof:placetype":"venue"
},
  "geometry": {"coordinates":[-2.1366634369,40.0758171082],"type":"Point"}
}