{
  "type": "Feature",
  "properties": {
    "addr:full":"Avda Manuel De Falla, 7 Valencia Valencia 46015",
    "addr:housenumber":"7",
    "addr:postcode":"46015",
    "addr:street":"Avda Manuel De Falla",
    "iso:country":"ES",
    "sg:address":"Avda Manuel De Falla, 7",
    "sg:city":"Valencia",
    "sg:orig_category":"Agencias Y Agentes Comerciales, Representantes",
    "sg:phone":"+34 963 49 58 70",
    "sg:postcode":"46015",
    "sg:province":"Valencia",
    "wof:name":"Romero Cebrian Juan",
    "wof:placetype":"venue"
},
  "geometry": {"coordinates":[-0.4007650018,39.4756851196],"type":"Point"}
}