{
  "type": "Feature",
  "properties": {
    "iso:country":"ES",
    "sg:address":"Hijuela Del Polo, S/n",
    "sg:city":"Jerez",
    "sg:orig_category":"Asociaciones Humanitarias, De Cooperaci\u00d3n, De Acci\u00d3n Social",
    "sg:phone":"+34 956 18 18 47",
    "sg:postcode":"11405",
    "sg:province":"C\u00e1diz",
    "wof:name":"Asociacion Brote De Vida",
    "wof:placetype":"venue"
},
  "geometry": {"coordinates":[-6.120423317,36.6925621033],"type":"Point"}
}