{
  "type": "Feature",
  "properties": {
    "addr:full":"Gta Navarra, 1 Argamasilla Calatrava Ciudad Real 13440",
    "addr:housenumber":"1",
    "addr:postcode":"13440",
    "addr:street":"Gta Navarra",
    "iso:country":"ES",
    "sg:address":"Gta Navarra, 1",
    "sg:city":"Argamasilla Calatrava",
    "sg:orig_category":"Caf\u00c9s, Bares, Cervecer\u00cdas",
    "sg:phone":"+34 926 46 02 79",
    "sg:postcode":"13440",
    "sg:province":"Ciudad Real",
    "wof:name":"Prieto Morales C.b.",
    "wof:placetype":"venue"
},
  "geometry": {"coordinates":[-4.080684185,38.7269630432],"type":"Point"}
}