{
  "type": "Feature",
  "properties": {
    "addr:full":"Avda Lugo, S/n Pontevedra Pontevedra 36004",
    "addr:housenumber":"s / n",
    "addr:postcode":"36004",
    "addr:street":"Avda Lugo",
    "iso:country":"ES",
    "sg:address":"Avda Lugo, S/n",
    "sg:city":"Pontevedra",
    "sg:orig_category":"Distribuci\u00d3n De Petr\u00d3leo Y Derivados",
    "sg:phone":"+34 986 85 60 67",
    "sg:postcode":"36004",
    "sg:province":"Pontevedra",
    "sg:website":"www.cepsa.es",
    "wof:name":"Cedipsa Compa\u00d1ia Espa\u00d1ola Distribuidora De Petroleos S.a.",
    "wof:placetype":"venue"
},
  "geometry": {"coordinates":[-8.6226139069,42.4340515137],"type":"Point"}
}