{
  "type": "Feature",
  "properties": {
    "addr:full":"Ctra Terrassa, 217 Sabadell Barcelona 08205",
    "addr:housenumber":"217",
    "addr:postcode":"08205",
    "addr:street":"Ctra Terrassa",
    "iso:country":"ES",
    "sg:address":"Ctra Terrassa, 217",
    "sg:city":"Sabadell",
    "sg:orig_category":"M\u00c1quinas Y Material Para La Industria De La Alimentaci\u00d3n",
    "sg:phone":"+34 937 45 13 30",
    "sg:postcode":"08205",
    "sg:province":"Barcelona",
    "wof:name":"Fatosa S. A.",
    "wof:placetype":"venue"
},
  "geometry": {"coordinates":[2.0962080956,41.5453033447],"type":"Point"}
}