{
  "type": "Feature",
  "properties": {
    "iso:country":"ES",
    "sg:address":"Carrer de Francesc Macia, 65",
    "sg:city":"Granollers",
    "sg:orig_category":"Importaci\u00d3n",
    "sg:phone":"+34 938 61 30 65",
    "sg:postcode":"08402",
    "sg:province":"Barcelona",
    "wof:name":"Boss Bcn Gestion Sl",
    "wof:placetype":"venue"
},
  "geometry": {"coordinates":[2.2876019478,41.6014213562],"type":"Point"}
}