{
  "type": "Feature",
  "properties": {
    "addr:full":"Calle de Castilla La Mancha, 463 Nieves Toledo 45190",
    "addr:housenumber":"463",
    "addr:postcode":"45190",
    "addr:street":"Calle De Castilla La Mancha",
    "iso:country":"ES",
    "sg:address":"Calle de Castilla La Mancha, 463",
    "sg:city":"Nieves",
    "sg:orig_category":"Carb\u00d3n, Carb\u00d3n De Madera (al Por Mayor)",
    "sg:phone":"+34 925 27 85 64",
    "sg:postcode":"45190",
    "sg:province":"Toledo",
    "wof:name":"Guardia Rodriguez Andrea",
    "wof:placetype":"venue"
},
  "geometry": {"coordinates":[-3.9588699341,39.8263816833],"type":"Point"}
}