{
  "type": "Feature",
  "properties": {
    "iso:country":"ES",
    "sg:address":"Calle de Vi\u00d1uelas, 65",
    "sg:city":"Herreruela De Oropesa",
    "sg:orig_category":"Molinos",
    "sg:phone":"+34 925 43 52 47",
    "sg:postcode":"45588",
    "sg:province":"Toledo",
    "wof:name":"Cooperativa De Piensos De Herreruela",
    "wof:placetype":"venue"
},
  "geometry": {"coordinates":[-5.2440891266,39.889919281],"type":"Point"}
}