{
  "type": "Feature",
  "properties": {
    "iso:country":"ES",
    "sg:address":"Nogueirido(senra), 20",
    "sg:city":"Ortigueira",
    "sg:orig_category":"Peluqueros: De Se\u00d1oras",
    "sg:phone":"+34 981 42 23 87",
    "sg:postcode":"15330",
    "sg:province":"La Coru\u00f1a",
    "wof:name":"Mauriz Sanjurjo David",
    "wof:placetype":"venue"
},
  "geometry": {"coordinates":[-7.8530597687,43.6817398071],"type":"Point"}
}