{
  "type": "Feature",
  "properties": {
    "iso:country":"ES",
    "sg:address":"Corro Del Cuartel, 1",
    "sg:city":"Fuentes Nava",
    "sg:orig_category":"Reposter\u00cdas",
    "sg:phone":"+34 979 84 20 39",
    "sg:postcode":"34337",
    "sg:province":"Palencia",
    "wof:name":"Productos Sevilla S.l.",
    "wof:placetype":"venue"
},
  "geometry": {"coordinates":[-4.7824568748,42.0825996399],"type":"Point"}
}