{
  "type": "Feature",
  "properties": {
    "addr:full":"Ctra Alicante-oca\u00f1a, Km. 0377,0 Petrer Alicante 03610",
    "addr:postcode":"03610",
    "addr:street":"Ctra Alicante-Ocan\u0303A Km. 0377,0",
    "iso:country":"ES",
    "sg:address":"Ctra Alicante-oca\u00f1a, Km. 0377,0",
    "sg:city":"Petrer",
    "sg:orig_category":"Cajas Y Embalajes De Cart\u00d3n Y Papel",
    "sg:phone":"+34 965 37 09 79",
    "sg:postcode":"03610",
    "sg:province":"Alicante",
    "wof:name":"Envases Poveda S.l.",
    "wof:placetype":"venue"
},
  "geometry": {"coordinates":[-0.7859489918,38.489315033],"type":"Point"}
}