{
  "type": "Feature",
  "properties": {
    "iso:country":"ES",
    "sg:address":"Calle de Autovia Del Sur, S/n",
    "sg:city":"Palmas De Gran Canaria",
    "sg:orig_category":"Empresas De Trabajos P\u00dablicos",
    "sg:phone":"+34 928 32 30 15",
    "sg:postcode":"35016",
    "sg:province":"Las Palmas",
    "wof:name":"Ute Area Metropolitana",
    "wof:placetype":"venue"
},
  "geometry": {"coordinates":[-15.4343700409,28.0745296478],"type":"Point"}
}