{
  "type": "Feature",
  "properties": {
    "addr:full":"Calle de Pintor Aparicio, 3 Alacant Alicante 03003",
    "addr:housenumber":"3",
    "addr:postcode":"03003",
    "addr:street":"Calle De Pintor Aparicio",
    "iso:country":"ES",
    "sg:address":"Calle de Pintor Aparicio, 3",
    "sg:city":"Alacant",
    "sg:classifiers":[
        {
            "category":"Recreation",
            "type":"Entertainment"
        }
    ],
    "sg:phone":"+34 965 92 87 30",
    "sg:postcode":"03003",
    "sg:province":"Alicante",
    "sg:tags":[
        "caza",
        "pr\u00c1ctica",
        "la",
        "de",
        "pesca",
        "y"
    ],
    "wof:name":"Federacion Provincial Cofradia De Pescadores",
    "wof:placetype":"venue"
},
  "geometry": {"coordinates":[-0.4898679852,38.3391571045],"type":"Point"}
}