{
  "type": "Feature",
  "properties": {
    "addr:full":"Rua Marques De Valladares, 23 Vigo Pontevedra 36201",
    "addr:housenumber":"23",
    "addr:postcode":"36201",
    "addr:street":"Rua Marques De Valladares",
    "iso:country":"ES",
    "sg:address":"Rua Marques De Valladares, 23",
    "sg:city":"Vigo",
    "sg:orig_category":"Restaurantes",
    "sg:phone":"+34 986 22 23 66",
    "sg:postcode":"36201",
    "sg:province":"Pontevedra",
    "wof:name":"Alimentaciones Escolares S.a.",
    "wof:placetype":"venue"
},
  "geometry": {"coordinates":[-8.722533226,42.2382926941],"type":"Point"}
}