{
  "type": "Feature",
  "properties": {
    "addr:full":"Carrer de Casp, 54 Barcelona Barcelona 08010",
    "addr:housenumber":"54",
    "addr:postcode":"08010",
    "addr:street":"Carrer De Casp",
    "iso:country":"ES",
    "sg:address":"Carrer de Casp, 54",
    "sg:city":"Barcelona",
    "sg:orig_category":"Arquitectos",
    "sg:phone":"+34 933 17 63 36",
    "sg:postcode":"08010",
    "sg:province":"Barcelona",
    "wof:name":"Paniagua Rucosa Carlos Manuel",
    "wof:placetype":"venue"
},
  "geometry": {"coordinates":[2.1737160683,41.3914299011],"type":"Point"}
}