{
  "type": "Feature",
  "properties": {
    "addr:full":"Barr Palacio, S/n Arnuero Cantabria 39194",
    "addr:housenumber":"s / n",
    "addr:postcode":"39194",
    "iso:country":"ES",
    "sg:address":"Barr Palacio, S/n",
    "sg:city":"Arnuero",
    "sg:orig_category":"Delegados, Agentes De Tr\u00c1nsito, Auxiliares De Transporte Internacional",
    "sg:phone":"+34 942 67 70 23",
    "sg:postcode":"39194",
    "sg:province":"Cantabria",
    "wof:name":"Pelayo Viadero Angel",
    "wof:placetype":"venue"
},
  "geometry": {"coordinates":[-3.5678329468,43.4699211121],"type":"Point"}
}