{
  "type": "Feature",
  "properties": {
    "addr:full":"Calle de Mies De Vega, 21 Torrelavega Cantabria 39300",
    "addr:housenumber":"21",
    "addr:postcode":"39300",
    "addr:street":"Calle De Mies De Vega",
    "iso:country":"ES",
    "sg:address":"Calle de Mies De Vega, 21",
    "sg:city":"Torrelavega",
    "sg:orig_category":"Transportes Por V\u00cdas Navegables",
    "sg:phone":"+34 942 89 47 02",
    "sg:postcode":"39300",
    "sg:province":"Cantabria",
    "wof:name":"Bustamante Gonzalez Araceli",
    "wof:placetype":"venue"
},
  "geometry": {"coordinates":[-4.0612611771,43.3481063843],"type":"Point"}
}