{
  "type": "Feature",
  "properties": {
    "addr:full":"Av Generalitat, 2 Campello Alicante 03560",
    "addr:housenumber":"2",
    "addr:postcode":"03560",
    "addr:street":"Av Generalitat",
    "iso:country":"ES",
    "sg:address":"Av Generalitat, 2",
    "sg:city":"Campello",
    "sg:orig_category":"Asociaciones, Organismos Culturales Y Socioeducativos",
    "sg:phone":"+34 965 63 54 53",
    "sg:postcode":"03560",
    "sg:province":"Alicante",
    "wof:name":"Junta Festera De Moros Y Cristianos",
    "wof:placetype":"venue"
},
  "geometry": {"coordinates":[-0.3981589973,38.4267692566],"type":"Point"}
}