{
  "type": "Feature",
  "properties": {
    "addr:full":"Calle de Tagarral (del), 12 Tres Cantos Madrid 28760",
    "addr:housenumber":"12",
    "addr:postcode":"28760",
    "addr:street":"Calle De Tagarral Del",
    "iso:country":"ES",
    "sg:address":"Calle de Tagarral (del), 12",
    "sg:city":"Tres Cantos",
    "sg:orig_category":"Buzones De Correos",
    "sg:phone":"+34 918 03 27 76",
    "sg:postcode":"28760",
    "sg:province":"Madrid",
    "wof:name":"Buzones Villanueva S.l.",
    "wof:placetype":"venue"
},
  "geometry": {"coordinates":[-3.7003641129,40.5944824219],"type":"Point"}
}