{
  "type": "Feature",
  "properties": {
    "addr:full":"La Foia De Bunyol, 2 P. I. La Cova Valencia 46940",
    "addr:housenumber":"2",
    "addr:postcode":"46940",
    "addr:street":"P. I. La Cova",
    "iso:country":"ES",
    "sg:address":"La Foia De Bunyol, 2",
    "sg:city":"P. I. La Cova",
    "sg:orig_category":"Fabricaci\u00d3n, Venta, Instalaci\u00d3n De R\u00d3tulos, De R\u00d3tulos Luminosos",
    "sg:phone":"+34 961 53 37 63",
    "sg:postcode":"46940",
    "sg:province":"Valencia",
    "sg:website":"www.tecmel.com",
    "wof:name":"Tecmel S.l.",
    "wof:placetype":"venue"
},
  "geometry": {"coordinates":[-0.461488992,39.4922943115],"type":"Point"}
}