{
  "type": "Feature",
  "properties": {
    "addr:full":"Cllo Ramos De, 7 Torremolinos M\u00e1laga 29620",
    "addr:postcode":"29620",
    "addr:street":"Ma\u0301Laga",
    "iso:country":"ES",
    "sg:address":"Cllo Ramos De, 7",
    "sg:city":"Torremolinos",
    "sg:orig_category":"Promotores Constructores",
    "sg:phone":"+34 952 05 80 99",
    "sg:postcode":"29620",
    "sg:province":"M\u00e1laga",
    "wof:name":"Comercial Mdq Marbella S.l.",
    "wof:placetype":"venue"
},
  "geometry": {"coordinates":[-4.5027270317,36.6123085022],"type":"Point"}
}