{
  "type": "Feature",
  "properties": {
    "iso:country":"ES",
    "sg:address":"Plaz Constitucion, 1",
    "sg:city":"Mancha Real",
    "sg:orig_category":"Ense\u00d1anza, Formaci\u00d3n Profesional: Aprendizaje",
    "sg:phone":"+34 953 35 01 57",
    "sg:postcode":"23100",
    "sg:province":"Ja\u00e9n",
    "wof:name":"Ayuntamiento De Mancha Real",
    "wof:placetype":"venue"
},
  "geometry": {"coordinates":[-3.6116495132,37.8278694153],"type":"Point"}
}