{
  "type": "Feature",
  "properties": {
    "addr:full":"Carrer de Neopatria, 107 Barcelona Barcelona 08030",
    "addr:housenumber":"107",
    "addr:postcode":"08030",
    "addr:street":"Carrer De Neopatria",
    "iso:country":"ES",
    "sg:address":"Carrer de Neopatria, 107",
    "sg:city":"Barcelona",
    "sg:orig_category":"Art\u00cdculos De Madera (fabricaci\u00d3n Y Al Por Mayor)",
    "sg:phone":"+34 932 74 09 94",
    "sg:postcode":"08030",
    "sg:province":"Barcelona",
    "wof:name":"Martinez Tarrega Montserrat",
    "wof:placetype":"venue"
},
  "geometry": {"coordinates":[2.1893959045,41.4298744202],"type":"Point"}
}