{
  "type": "Feature",
  "properties": {
    "iso:country":"ES",
    "sg:address":"Calle de Tormes, 16",
    "sg:city":"Urbanizacion El Encinar",
    "sg:orig_category":"Peluquer\u00cdas, Peluquer\u00cda Mixta",
    "sg:phone":"+34 923 37 30 96",
    "sg:postcode":"37190",
    "sg:province":"Salamanca",
    "wof:name":"Martinez Ramos Rosa Maria",
    "wof:placetype":"venue"
},
  "geometry": {"coordinates":[-5.583398819,40.8847999573],"type":"Point"}
}