{
  "type": "Feature",
  "properties": {
    "iso:country":"ES",
    "sg:address":"Calle de Redolins, 6",
    "sg:city":"Palmar",
    "sg:orig_category":"Farmacias",
    "sg:phone":"+34 961 62 01 59",
    "sg:postcode":"46012",
    "sg:province":"Valencia",
    "wof:name":"Santamaria Paulo Mercedes",
    "wof:placetype":"venue"
},
  "geometry": {"coordinates":[-0.3180580139,39.3096618652],"type":"Point"}
}