{
  "type": "Feature",
  "properties": {
    "iso:country":"ES",
    "sg:address":"Pg Acacies, 3",
    "sg:city":"Cerdanyola Valles",
    "sg:orig_category":"Mec\u00c1nico Del Autom\u00d3vil",
    "sg:phone":"+34 935 80 89 81",
    "sg:postcode":"08290",
    "sg:province":"Barcelona",
    "wof:name":"Hidalgo Gilabert Carlos",
    "wof:placetype":"venue"
},
  "geometry": {"coordinates":[2.1435470581,41.491859436],"type":"Point"}
}