{
  "type": "Feature",
  "properties": {
    "iso:country":"ES",
    "sg:address":"Ctra Nueva, 1",
    "sg:city":"Puerto De Bejar",
    "sg:orig_category":"Carnicer\u00cdas, Carnicer\u00cdas",
    "sg:phone":"+34 923 41 41 70",
    "sg:postcode":"37720",
    "sg:province":"Salamanca",
    "wof:name":"Jamones Y Embutidos La Jara S.l.",
    "wof:placetype":"venue"
},
  "geometry": {"coordinates":[-97.78224945069999,45.7040786743],"type":"Point"}
}