{
  "type": "Feature",
  "properties": {
    "addr:full":"C/ Do\u00d1a Amalia, 7 Alcoi Alicante 03801",
    "addr:housenumber":"7",
    "addr:postcode":"03801",
    "addr:street":"C / Don\u0303A Amalia",
    "iso:country":"ES",
    "sg:address":"C/ Do\u00d1a Amalia, 7",
    "sg:city":"Alcoi",
    "sg:orig_category":"Cerrajer\u00cda, Ferrallista",
    "sg:phone":"+34 965 54 11 83",
    "sg:postcode":"03801",
    "sg:province":"Alicante",
    "wof:name":"Forja Y Metal Alcoy S.l.l.",
    "wof:placetype":"venue"
},
  "geometry": {"coordinates":[-0.4775699973,38.6925354004],"type":"Point"}
}