{
  "type": "Feature",
  "properties": {
    "iso:country":"ES",
    "sg:address":"Av Alameda (l'), 39",
    "sg:city":"Alcoi",
    "sg:orig_category":"Bisuter\u00cda, Joyer\u00cda, Relojer\u00cda (al Por Menor)",
    "sg:phone":"+34 965 52 35 63",
    "sg:postcode":"03803",
    "sg:province":"Alicante",
    "wof:name":"New Progress S.l.",
    "wof:placetype":"venue"
},
  "geometry": {"coordinates":[-0.4785119891,38.7011528015],"type":"Point"}
}