{
  "type": "Feature",
  "properties": {
    "addr:full":"Calle de Lope De Vega, 23 Andujar Ja\u00e9n 23740",
    "addr:housenumber":"23",
    "addr:postcode":"23740",
    "addr:street":"Calle De Lope De Vega",
    "iso:country":"ES",
    "sg:address":"Calle de Lope De Vega, 23",
    "sg:city":"Andujar",
    "sg:orig_category":"Art\u00cdculos De Regalo (al Por Menor)",
    "sg:phone":"+34 953 50 25 55",
    "sg:postcode":"23740",
    "sg:province":"Ja\u00e9n",
    "wof:name":"Perez Cano Jose",
    "wof:placetype":"venue"
},
  "geometry": {"coordinates":[-4.0492777824,38.0427055359],"type":"Point"}
}