{
  "type": "Feature",
  "properties": {
    "addr:full":"Avda Sagunto (de), 56 Teruel Teruel 44002",
    "addr:housenumber":"56",
    "addr:postcode":"44002",
    "addr:street":"Avda Sagunto De",
    "iso:country":"ES",
    "sg:address":"Avda Sagunto (de), 56",
    "sg:city":"Teruel",
    "sg:orig_category":"Arquitectos",
    "sg:phone":"+34 978 61 74 28",
    "sg:postcode":"44002",
    "sg:province":"Teruel",
    "wof:name":"Martin Barcelon Noemi",
    "wof:placetype":"venue"
},
  "geometry": {"coordinates":[-1.1005749702,40.3329086304],"type":"Point"}
}