{
  "type": "Feature",
  "properties": {
    "iso:country":"ES",
    "sg:address":"El Chano, S/n",
    "sg:city":"Luarca",
    "sg:orig_category":"Distribuci\u00d3n De Petr\u00d3leo Y Derivados",
    "sg:phone":"+34 985 64 01 44",
    "sg:postcode":"33700",
    "sg:province":"Asturias",
    "wof:name":"Cetarea Sport S.l.",
    "wof:placetype":"venue"
},
  "geometry": {"coordinates":[-6.5366139412,43.5418891907],"type":"Point"}
}