{
  "type": "Feature",
  "properties": {
    "iso:country":"ES",
    "sg:address":"Av Europa(base Dos Mil), 4",
    "sg:city":"Lorqui",
    "sg:orig_category":"Pintura, Barniz, Productos Asimilables (fabricaci\u00d3n, Al Por Mayor)",
    "sg:phone":"+34 968 68 76 73",
    "sg:postcode":"30564",
    "sg:province":"Murcia",
    "wof:name":"Pincar Automocion S.l.",
    "wof:placetype":"venue"
},
  "geometry": {"coordinates":[-1.2295030355,38.1026611328],"type":"Point"}
}