{
  "type": "Feature",
  "properties": {
    "iso:country":"ES",
    "sg:address":"Pl Glories Catalanes, 32",
    "sg:city":"Barcelona",
    "sg:orig_category":"Cristaler\u00cda Art\u00cdstica, Vidrio Soplado (fabricaci\u00d3n, Al Por Mayor)",
    "sg:phone":"+34 933 00 31 10",
    "sg:postcode":"08018",
    "sg:province":"Barcelona",
    "wof:name":"Gradecor Barna S.l.",
    "wof:placetype":"venue"
},
  "geometry": {"coordinates":[2.1877000332,41.4033966064],"type":"Point"}
}