{
  "type": "Feature",
  "properties": {
    "addr:full":"Ctra Villalpando (de), 40 Benegiles Zamora 49123",
    "addr:housenumber":"40",
    "addr:postcode":"49123",
    "addr:street":"Ctra Villalpando De;Zamora",
    "iso:country":"ES",
    "sg:address":"Ctra Villalpando (de), 40",
    "sg:city":"Benegiles",
    "sg:orig_category":"Centros De Salud",
    "sg:phone":"+34 980 50 42 06",
    "sg:postcode":"49123",
    "sg:province":"Zamora",
    "wof:name":"Prada Garcia Eusebio",
    "wof:placetype":"venue"
},
  "geometry": {"coordinates":[-5.6345977783,41.6290359497],"type":"Point"}
}