{
  "type": "Feature",
  "properties": {
    "iso:country":"ES",
    "sg:address":"Calle de Planas De Poesia, 3",
    "sg:city":"Llano De Las Nieves",
    "sg:orig_category":"Farmacias",
    "sg:phone":"+34 928 71 63 85",
    "sg:postcode":"35229",
    "sg:province":"Las Palmas",
    "wof:name":"Miranda Sauret Maria Isabel",
    "wof:placetype":"venue"
},
  "geometry": {"coordinates":[-15.521730423,28.0814990997],"type":"Point"}
}