{
  "type": "Feature",
  "properties": {
    "iso:country":"ES",
    "sg:address":"Carretera Del Remolino, S/n",
    "sg:city":"Palma Rio",
    "sg:orig_category":"M\u00c1rmoles, Granitos Y Piedras Naturales",
    "sg:phone":"+34 957 64 35 02",
    "sg:postcode":"14700",
    "sg:province":"C\u00f3rdoba",
    "wof:name":"Barrios Hernandez Jose",
    "wof:placetype":"venue"
},
  "geometry": {"coordinates":[-5.2623238564,37.7107200623],"type":"Point"}
}