{
  "type": "Feature",
  "properties": {
    "iso:country":"ES",
    "sg:address":"Calle de Rio Bergantes, 3",
    "sg:city":"Torremolinos",
    "sg:orig_category":"Persianas Interiores, Exteriores",
    "sg:phone":"+34 952 37 11 12",
    "sg:postcode":"29620",
    "sg:province":"M\u00e1laga",
    "sg:website":"www.toldossilvia.com",
    "wof:name":"Flores Flores Maria Del Carmen",
    "wof:placetype":"venue"
},
  "geometry": {"coordinates":[-4.5027022362,36.6282119751],"type":"Point"}
}