{
  "type": "Feature",
  "properties": {
    "iso:country":"ES",
    "sg:address":"Calle de Doctor Fleming, 16",
    "sg:city":"Madrid",
    "sg:orig_category":"Propiedad Industrial: Patentes De Inventos, Marcas, Modelos, Dise\u00d1os",
    "sg:phone":"+34 913 45 96 25",
    "sg:postcode":"28036",
    "sg:province":"Madrid",
    "sg:website":"www.polopatent.es",
    "wof:name":"Polo S.l.",
    "wof:placetype":"venue"
},
  "geometry": {"coordinates":[-3.6883554459,40.455783844],"type":"Point"}
}