{
  "type": "Feature",
  "properties": {
    "iso:country":"ES",
    "sg:address":"Av Comarques Catalanes, 74",
    "sg:city":"Mora D'ebre",
    "sg:orig_category":"M\u00c9dicos: Ginecolog\u00cda Y Obstetricia",
    "sg:phone":"+34 977 40 22 91",
    "sg:postcode":"43740",
    "sg:province":"Tarragona",
    "wof:name":"Brm Previform S.l.",
    "wof:placetype":"venue"
},
  "geometry": {"coordinates":[1.2540999651,41.1169281006],"type":"Point"}
}