{
  "type": "Feature",
  "properties": {
    "addr:full":"G.v. Corts Catalanes, 763 Barcelona Barcelona 08013",
    "addr:housenumber":"763",
    "addr:postcode":"08013",
    "addr:street":"Catalanes",
    "iso:country":"ES",
    "sg:address":"G.v. Corts Catalanes, 763",
    "sg:city":"Barcelona",
    "sg:orig_category":"Farmacias",
    "sg:phone":"+34 932 31 51 05",
    "sg:postcode":"08013",
    "sg:province":"Barcelona",
    "wof:name":"Grau Gasulla Maria Isabel",
    "wof:placetype":"venue"
},
  "geometry": {"coordinates":[2.1841099262,41.4016914368],"type":"Point"}
}