{
  "type": "Feature",
  "properties": {
    "addr:full":"Carrer de Ricart, 34 S. Adria Besos Barcelona 08930",
    "addr:housenumber":"34",
    "addr:postcode":"08930",
    "addr:street":"Carrer De Ricart;S. Adria Besos Barcelona",
    "iso:country":"ES",
    "sg:address":"Carrer de Ricart, 34",
    "sg:city":"S. Adria Besos",
    "sg:orig_category":"Partidos Pol\u00cdticos",
    "sg:phone":"+34 933 81 78 53",
    "sg:postcode":"08930",
    "sg:province":"Barcelona",
    "wof:name":"Partit Dels Socialistes De Catalunya",
    "wof:placetype":"venue"
},
  "geometry": {"coordinates":[2.2189059258,41.4296340942],"type":"Point"}
}