{
  "type": "Feature",
  "properties": {
    "addr:full":"Avda Murcia (de), 47 Bullas Murcia 30180",
    "addr:housenumber":"47",
    "addr:postcode":"30180",
    "addr:street":"Avda Murcia De",
    "iso:country":"ES",
    "sg:address":"Avda Murcia (de), 47",
    "sg:city":"Bullas",
    "sg:orig_category":"Alumbrados",
    "sg:phone":"+34 968 65 46 74",
    "sg:postcode":"30180",
    "sg:province":"Murcia",
    "wof:name":"Sandoval Martinez Rosa Maria",
    "wof:placetype":"venue"
},
  "geometry": {"coordinates":[-1.6675829887,38.0504837036],"type":"Point"}
}