{
  "type": "Feature",
  "properties": {
    "iso:country":"ES",
    "sg:address":"Carr Pla De L'estany, S/n",
    "sg:city":"Cassa Selva",
    "sg:orig_category":"Aceros Inoxidables",
    "sg:phone":"+34 972 46 38 79",
    "sg:postcode":"17244",
    "sg:province":"Girona",
    "wof:name":"Cassa Aplicacions Inoxidables R.c. S.l.",
    "wof:placetype":"venue"
},
  "geometry": {"coordinates":[3.2037000656,42.336730957],"type":"Point"}
}