{
  "type": "Feature",
  "properties": {
    "addr:full":"Calle de Cura Caballero, S/n Valleseco Las Palmas 35340",
    "addr:housenumber":"s / n",
    "addr:postcode":"35340",
    "addr:street":"Calle De Cura Caballero",
    "iso:country":"ES",
    "sg:address":"Calle de Cura Caballero, S/n",
    "sg:city":"Valleseco",
    "sg:classifiers":[
        {
            "category":"Taxi",
            "type":"Transportation"
        }
    ],
    "sg:phone":"+34 928 61 80 80",
    "sg:postcode":"35340",
    "sg:province":"Las Palmas",
    "wof:name":"Perez Diaz Manuel De Jesus",
    "wof:placetype":"venue"
},
  "geometry": {"coordinates":[-15.5751419067,28.0501251221],"type":"Point"}
}