{
  "type": "Feature",
  "properties": {
    "addr:full":"Calle de Reina Sofia, S/n Campo Abajo Murcia 30510",
    "addr:housenumber":"s",
    "addr:postcode":"30510",
    "addr:street":"Calle De Reina Sofia;/ N",
    "iso:country":"ES",
    "sg:address":"Calle de Reina Sofia, S/n",
    "sg:city":"Campo Abajo",
    "sg:orig_category":"Energ\u00cda Solar Y Nuevas Energ\u00cdas (equipo, Estudios)",
    "sg:phone":"+34 968 71 91 25",
    "sg:postcode":"30510",
    "sg:province":"Murcia",
    "sg:website":"www.windeco.es",
    "wof:name":"Windeco Tecnologia Eolica S.l.",
    "wof:placetype":"venue"
},
  "geometry": {"coordinates":[-1.1298867464,37.9834747314],"type":"Point"}
}