{
  "type": "Feature",
  "properties": {
    "iso:country":"ES",
    "sg:address":"Calle de Leon Y Castillo, 11",
    "sg:city":"Ingenio",
    "sg:orig_category":"Cajas Para Embalar",
    "sg:phone":"+34 928 78 50 31",
    "sg:postcode":"35250",
    "sg:province":"Las Palmas",
    "wof:name":"Caja Rural De Canarias",
    "wof:placetype":"venue"
},
  "geometry": {"coordinates":[-15.4376296997,27.9195175171],"type":"Point"}
}