{
  "type": "Feature",
  "properties": {
    "iso:country":"ES",
    "sg:address":"Avda Ernestina Otero, 57",
    "sg:city":"Redondela",
    "sg:classifiers":[
        {
            "category":"Taxi",
            "type":"Transportation"
        }
    ],
    "sg:phone":"+34 986 40 17 24",
    "sg:postcode":"36800",
    "sg:province":"Pontevedra",
    "wof:name":"Cou\u00f1ago Veiga Angel",
    "wof:placetype":"venue"
},
  "geometry": {"coordinates":[-8.609708786,42.285118103],"type":"Point"}
}