{
  "type": "Feature",
  "properties": {
    "addr:full":"Carr Banqueta (la), 9 Balaguer Lleida 25600",
    "addr:housenumber":"9",
    "addr:postcode":"25600",
    "addr:street":"Carr Banqueta La",
    "iso:country":"ES",
    "sg:address":"Carr Banqueta (la), 9",
    "sg:city":"Balaguer",
    "sg:orig_category":"Comerciantes Al Por Mayor De Vinos, Licores Y Alcoholes",
    "sg:phone":"+34 973 44 58 43",
    "sg:postcode":"25600",
    "sg:province":"Lleida",
    "wof:name":"Moreno Torres Maria Antonia",
    "wof:placetype":"venue"
},
  "geometry": {"coordinates":[0.8071600199,41.7896003723],"type":"Point"}
}