{
  "type": "Feature",
  "properties": {
    "iso:country":"ES",
    "sg:address":"Calle de Asturias, 6",
    "sg:city":"Grado",
    "sg:orig_category":"Ropa Para Se\u00d1oras Y Caballeros (al Por Menor)",
    "sg:phone":"+34 985 75 22 32",
    "sg:postcode":"33820",
    "sg:province":"Asturias",
    "wof:name":"Sanchez Lopez Maria Amparo",
    "wof:placetype":"venue"
},
  "geometry": {"coordinates":[-6.0722441673,43.3878517151],"type":"Point"}
}