{
  "type": "Feature",
  "properties": {
    "iso:country":"ES",
    "sg:address":"Calle de Juan Carlos I, 4",
    "sg:city":"Torrecampo",
    "sg:orig_category":"Abogados",
    "sg:phone":"+34 957 15 53 40",
    "sg:postcode":"14410",
    "sg:province":"C\u00f3rdoba",
    "wof:name":"Crespo Bravo Juan Bautista",
    "wof:placetype":"venue"
},
  "geometry": {"coordinates":[-4.6767549515,38.4749755859],"type":"Point"}
}