{
  "type": "Feature",
  "properties": {
    "addr:full":"Central Electrica, S/n Orallo Le\u00f3n 24113",
    "addr:housenumber":"s",
    "addr:postcode":"24113",
    "addr:street":"/ N Orallo Leo\u0301N",
    "iso:country":"ES",
    "sg:address":"Central Electrica, S/n",
    "sg:city":"Orallo",
    "sg:orig_category":"Empresas De Electricidad En General",
    "sg:phone":"+34 987 49 00 00",
    "sg:postcode":"24113",
    "sg:province":"Le\u00f3n",
    "wof:name":"Hidroelectrica La Prohida S. A.",
    "wof:placetype":"venue"
},
  "geometry": {"coordinates":[-6.355181694,42.9712791443],"type":"Point"}
}