{
  "type": "Feature",
  "properties": {
    "iso:country":"ES",
    "sg:address":"Calle de Compostela, 8",
    "sg:city":"Coru\u00d1a",
    "sg:orig_category":"Asesor\u00cda Sobre Comunicaci\u00d3n De Empresas",
    "sg:phone":"+34 981 20 34 13",
    "sg:postcode":"15004",
    "sg:province":"La Coru\u00f1a",
    "wof:name":"Compa\u00f1ia Gestonar S.l.",
    "wof:placetype":"venue"
},
  "geometry": {"coordinates":[-8.4058256149,43.3660240173],"type":"Point"}
}