{
  "type": "Feature",
  "properties": {
    "addr:full":"Calle de Alonso El Sabio, 18 Cordoba C\u00f3rdoba 14001",
    "addr:housenumber":"18",
    "addr:postcode":"14001",
    "addr:street":"Calle De Alonso El Sabio;Co\u0301Rdoba",
    "iso:country":"ES",
    "sg:address":"Calle de Alonso El Sabio, 18",
    "sg:city":"Cordoba",
    "sg:orig_category":"Chapister\u00cda",
    "sg:phone":"+34 957 48 37 48",
    "sg:postcode":"14001",
    "sg:province":"C\u00f3rdoba",
    "wof:name":"Alvarez Yusta Enrique",
    "wof:placetype":"venue"
},
  "geometry": {"coordinates":[-4.7769255638,37.8897323608],"type":"Point"}
}