{
  "type": "Feature",
  "properties": {
    "addr:full":"Calle de Preciados, 34 Madrid Madrid 28013",
    "addr:housenumber":"34",
    "addr:postcode":"madrid;28013",
    "addr:street":"Calle De Preciados",
    "iso:country":"ES",
    "sg:address":"Calle de Preciados, 34",
    "sg:city":"Madrid",
    "sg:orig_category":"Venta, Alquiler De V\u00cddeo",
    "sg:phone":"+34 915 31 34 50",
    "sg:postcode":"28013",
    "sg:province":"Madrid",
    "sg:website":"www.confederacion.com",
    "wof:name":"Engine Technology System S.l.",
    "wof:placetype":"venue"
},
  "geometry": {"coordinates":[-3.7063660622,40.4197998047],"type":"Point"}
}