{
  "type": "Feature",
  "properties": {
    "iso:country":"ES",
    "sg:address":"Avda Castilla-la Mancha (de), 119",
    "sg:city":"San Sebastian De Los Reyes",
    "sg:orig_category":"Plomeros",
    "sg:phone":"+34 916 51 83 63",
    "sg:postcode":"28700",
    "sg:province":"Madrid",
    "wof:name":"Bastante Lazaro Mariano",
    "wof:placetype":"venue"
},
  "geometry": {"coordinates":[-3.6416349411,40.5565948486],"type":"Point"}
}