{
  "type": "Feature",
  "properties": {
    "addr:full":"Calle de Errebitarte, 7 Arenas -areeta Vizcaya 48930",
    "addr:housenumber":"7;areeta",
    "addr:postcode":"48930",
    "addr:street":"Calle De Errebitarte",
    "iso:country":"ES",
    "sg:address":"Calle de Errebitarte, 7",
    "sg:city":"Arenas -areeta",
    "sg:orig_category":"Fabricaci\u00d3n, Reparaci\u00d3n Y Mantenimiento De Construcciones Navales Y Fluviales",
    "sg:phone":"+34 944 91 50 22",
    "sg:postcode":"48930",
    "sg:province":"Vizcaya",
    "wof:name":"Guezuraga Vigo S.l.",
    "wof:placetype":"venue"
},
  "geometry": {"coordinates":[-3.0101668835,43.3217430115],"type":"Point"}
}