{
  "type": "Feature",
  "properties": {
    "addr:full":"Av Perpinya, 15 Figueres Girona 17600",
    "addr:housenumber":"15",
    "addr:postcode":"17600",
    "addr:street":"Av Perpinya",
    "iso:country":"ES",
    "sg:address":"Av Perpinya, 15",
    "sg:city":"Figueres",
    "sg:orig_category":"Empresas De Desmonte",
    "sg:phone":"+34 972 50 30 14",
    "sg:postcode":"17600",
    "sg:province":"Girona",
    "wof:name":"Excavacions Emporda S.l.",
    "wof:placetype":"venue"
},
  "geometry": {"coordinates":[2.9563450813,42.2734069824],"type":"Point"}
}