{
  "type": "Feature",
  "properties": {
    "addr:full":"Calle de Eduardo Benitez Gonzalez, 10 Palmas De Gran Canaria Las Palmas 35011",
    "addr:housenumber":"10",
    "addr:postcode":"35011",
    "addr:street":"Calle De Eduardo Benitez Gonzalez",
    "iso:country":"ES",
    "sg:address":"Calle de Eduardo Benitez Gonzalez, 10",
    "sg:city":"Palmas De Gran Canaria",
    "sg:orig_category":"Masajistas Kinesiterapeutas",
    "sg:phone":"+34 928 25 93 70",
    "sg:postcode":"35011",
    "sg:province":"Las Palmas",
    "wof:name":"Delgado Rodriguez Jose Fernando",
    "wof:placetype":"venue"
},
  "geometry": {"coordinates":[-15.4361848831,28.1150016785],"type":"Point"}
}