{
  "type": "Feature",
  "properties": {
    "addr:full":"Calle de Galera, 47 Coru\u00d1a A Coru\u00f1a 15001",
    "addr:housenumber":"47",
    "addr:postcode":"15001",
    "addr:street":"Calle De Galera;Corun\u0303A",
    "iso:country":"ES",
    "sg:address":"Calle de Galera, 47",
    "sg:city":"Coru\u00d1a",
    "sg:orig_category":"Peluquer\u00cdas, Peluquer\u00cda Mixta",
    "sg:phone":"+34 981 22 91 87",
    "sg:postcode":"15001",
    "sg:province":"A Coru\u00f1a",
    "wof:name":"Varela Blanco Paula",
    "wof:placetype":"venue"
},
  "geometry": {"coordinates":[-8.3967437744,43.3701553345],"type":"Point"}
}