{
  "type": "Feature",
  "properties": {
    "addr:full":"Carrer de Cinca, 5 Hospitalet Llobregat Barcelona 08904",
    "addr:housenumber":"5",
    "addr:postcode":"08904",
    "addr:street":"Carrer De Cinca",
    "iso:country":"ES",
    "sg:address":"Carrer de Cinca, 5",
    "sg:city":"Hospitalet Llobregat",
    "sg:orig_category":"Tapicer\u00cdas",
    "sg:phone":"+34 933 33 04 12",
    "sg:postcode":"08904",
    "sg:province":"Barcelona",
    "wof:name":"Barrachina Laleona Jesus",
    "wof:placetype":"venue"
},
  "geometry": {"coordinates":[2.1152050495,41.374332428],"type":"Point"}
}