{
  "type": "Feature",
  "properties": {
    "iso:country":"ES",
    "sg:address":"Calle de Ca\u00d1os Verdes, 1",
    "sg:city":"Hinojosa Del Duque",
    "sg:orig_category":"Arquitectos",
    "sg:phone":"+34 957 14 08 80",
    "sg:postcode":"14270",
    "sg:province":"C\u00f3rdoba",
    "wof:name":"Trivi\u00f1o Arias Luis",
    "wof:placetype":"venue"
},
  "geometry": {"coordinates":[-5.1464748383,38.4997711182],"type":"Point"}
}