{
  "type": "Feature",
  "properties": {
    "addr:full":"Calle de Albardonero, 29 S. Fernando C\u00e1diz 11100",
    "addr:housenumber":"29",
    "addr:postcode":"11100",
    "addr:street":"Calle De Albardonero;S. Fernando Ca\u0301Diz",
    "iso:country":"ES",
    "sg:address":"Calle de Albardonero, 29",
    "sg:city":"S. Fernando",
    "sg:orig_category":"Delegados, Agentes De Tr\u00c1nsito, Auxiliares De Transporte Internacional",
    "sg:phone":"+34 956 88 87 34",
    "sg:postcode":"11100",
    "sg:province":"C\u00e1diz",
    "wof:name":"Manuel Toledo Coca S.l.",
    "wof:placetype":"venue"
},
  "geometry": {"coordinates":[-6.1924037933,36.4662361145],"type":"Point"}
}