{
  "type": "Feature",
  "properties": {
    "addr:full":"Calle de Quintana, 1 Salamanca Salamanca 37002",
    "addr:housenumber":"1",
    "addr:postcode":"37002",
    "addr:street":"Calle De Quintana",
    "iso:country":"ES",
    "sg:address":"Calle de Quintana, 1",
    "sg:city":"Salamanca",
    "sg:orig_category":"Confiter\u00cdas, Chocolater\u00cdas (al Por Menor)",
    "sg:phone":"+34 923 21 62 30",
    "sg:postcode":"37002",
    "sg:province":"Salamanca",
    "wof:name":"Pombo Hernandez Natividad",
    "wof:placetype":"venue"
},
  "geometry": {"coordinates":[-5.6645789146,40.964176178],"type":"Point"}
}