{
  "type": "Feature",
  "properties": {
    "iso:country":"ES",
    "sg:address":"Calle de Marcelo Usera, 15",
    "sg:city":"Madrid",
    "sg:orig_category":"Ropa Para Se\u00d1oras (al Por Menor)",
    "sg:phone":"+34 914 76 63 22",
    "sg:postcode":"28026",
    "sg:province":"Madrid",
    "wof:name":"Olalde Gonzalez Constantino",
    "wof:placetype":"venue"
},
  "geometry": {"coordinates":[-3.7009959221,40.3870353699],"type":"Point"}
}