{
  "type": "Feature",
  "properties": {
    "addr:full":"Calle de San Diego, 3 Valladolid Valladolid 47003",
    "addr:housenumber":"3",
    "addr:postcode":"47003",
    "addr:street":"Calle De San Diego",
    "iso:country":"ES",
    "sg:address":"Calle de San Diego, 3",
    "sg:city":"Valladolid",
    "sg:orig_category":"Lencer\u00cda Femenina, Corseter\u00cda, Trajes De Ba\u00d1o (al Por Menor)",
    "sg:phone":"+34 983 35 00 40",
    "sg:postcode":"47003",
    "sg:province":"Valladolid",
    "wof:name":"Calleja Barcia Maria Esther",
    "wof:placetype":"venue"
},
  "geometry": {"coordinates":[-4.7276139259,41.656791687],"type":"Point"}
}