{
  "type": "Feature",
  "properties": {
    "addr:full":"Pol. Ind. Riambau, 55 Tarrega Lleida 25300",
    "addr:housenumber":"55",
    "addr:postcode":"25300",
    "addr:street":"Riambau",
    "iso:country":"ES",
    "sg:address":"Pol. Ind. Riambau, 55",
    "sg:city":"Tarrega",
    "sg:orig_category":"Delegados, Agentes De Tr\u00c1nsito, Auxiliares De Transporte Internacional",
    "sg:phone":"+34 973 31 05 45",
    "sg:postcode":"25300",
    "sg:province":"Lleida",
    "sg:website":"www.cave.es",
    "wof:name":"Cave Pallaresa S.l.",
    "wof:placetype":"venue"
},
  "geometry": {"coordinates":[1.1410850286,41.6482696533],"type":"Point"}
}