{
  "type": "Feature",
  "properties": {
    "iso:country":"ES",
    "sg:address":"Calle de Santo, 7",
    "sg:city":"Villafranca De Los Caballeros",
    "sg:orig_category":"Asesor\u00cda Sobre Comunicaci\u00d3n De Empresas",
    "sg:phone":"+34 926 57 82 46",
    "sg:postcode":"45730",
    "sg:province":"Toledo",
    "wof:name":"Jose Antonio Manrique Rullo S.l.",
    "wof:placetype":"venue"
},
  "geometry": {"coordinates":[-3.3642730713,39.4280853271],"type":"Point"}
}