{
  "type": "Feature",
  "properties": {
    "iso:country":"ES",
    "sg:address":"Calle de Gordoniz, 97",
    "sg:city":"Bilbao",
    "sg:orig_category":"Alimentaci\u00d3n General (al Por Menor)",
    "sg:phone":"+34 944 22 01 94",
    "sg:postcode":"48002",
    "sg:province":"Vizcaya",
    "wof:name":"Perez Fernandez Jose Luis",
    "wof:placetype":"venue"
},
  "geometry": {"coordinates":[-2.9462339878,43.2519721985],"type":"Point"}
}