{
  "type": "Feature",
  "properties": {
    "addr:full":"Pase Castellana, 259 Madrid Madrid 28046",
    "addr:housenumber":"259",
    "addr:postcode":"28046",
    "addr:street":"Castellana",
    "iso:country":"ES",
    "sg:address":"Pase Castellana, 259",
    "sg:city":"Madrid",
    "sg:orig_category":"Promotores Constructores",
    "sg:phone":"+34 913 14 13 46",
    "sg:postcode":"28046",
    "sg:province":"Madrid",
    "wof:name":"Entidad Urbanistica Colaboradora",
    "wof:placetype":"venue"
},
  "geometry": {"coordinates":[-3.6865830421,40.4777603149],"type":"Point"}
}