{
  "type": "Feature",
  "properties": {
    "iso:country":"ES",
    "sg:address":"Rua Anton De Noia, 6",
    "sg:city":"Noia",
    "sg:orig_category":"Frutas Y Legumbres Frescas (al Por Mayor)",
    "sg:phone":"+34 981 82 04 40",
    "sg:postcode":"15200",
    "sg:province":"La Coru\u00f1a",
    "wof:name":"Roberto Gomez Castro Y Otra Scv.",
    "wof:placetype":"venue"
},
  "geometry": {"coordinates":[-8.8874588013,42.7820968628],"type":"Point"}
}