{
  "type": "Feature",
  "properties": {
    "addr:full":"Rbla Xavier Cugat, 10 Girona Girona 17007",
    "addr:housenumber":"10",
    "addr:postcode":"17007",
    "addr:street":"Rbla Xavier Cugat",
    "iso:country":"ES",
    "sg:address":"Rbla Xavier Cugat, 10",
    "sg:city":"Girona",
    "sg:orig_category":"Higiene, Belleza: Art\u00cdculos (al Por Menor)",
    "sg:phone":"+34 972 22 76 06",
    "sg:postcode":"17007",
    "sg:province":"Girona",
    "wof:name":"Rubio Bernal Fabiola",
    "wof:placetype":"venue"
},
  "geometry": {"coordinates":[2.8171401024,41.9923591614],"type":"Point"}
}