{
  "type": "Feature",
  "properties": {
    "addr:full":"Calle de Ricardo Gil, 6 Carmen Murcia 30002",
    "addr:housenumber":"6",
    "addr:postcode":"30002",
    "addr:street":"Calle De Ricardo Gil",
    "iso:country":"ES",
    "sg:address":"Calle de Ricardo Gil, 6",
    "sg:city":"Carmen",
    "sg:orig_category":"Abogados",
    "sg:phone":"+34 968 21 55 41",
    "sg:postcode":"30002",
    "sg:province":"Murcia",
    "wof:name":"Ruiz Sanchez Quintiliano",
    "wof:placetype":"venue"
},
  "geometry": {"coordinates":[-1.1292330027,37.9813652039],"type":"Point"}
}