{
  "type": "Feature",
  "properties": {
    "addr:full":"Pase Glorieta, 6 Pe\u00f1ascosa Albacete 02313",
    "addr:housenumber":"6",
    "addr:postcode":"02313",
    "addr:street":"Glorieta",
    "iso:country":"ES",
    "sg:address":"Pase Glorieta, 6",
    "sg:city":"Pe\u00f1ascosa",
    "sg:orig_category":"Farmacias",
    "sg:phone":"+34 967 38 24 42",
    "sg:postcode":"02313",
    "sg:province":"Albacete",
    "wof:name":"Martinez Morcillo Jose Javier",
    "wof:placetype":"venue"
},
  "geometry": {"coordinates":[-2.4106390476,38.6744651794],"type":"Point"}
}