{
  "type": "Feature",
  "properties": {
    "iso:country":"ES",
    "sg:address":"Carrer de Angel Guimera, 15",
    "sg:city":"Manresa",
    "sg:orig_category":"Loter\u00cda Y T\u00d3mbola",
    "sg:phone":"+34 938 72 57 95",
    "sg:postcode":"08241",
    "sg:province":"Barcelona",
    "wof:name":"Oller Vilaseca Santiago",
    "wof:placetype":"venue"
},
  "geometry": {"coordinates":[1.8242080212,41.7262573242],"type":"Point"}
}