{
  "type": "Feature",
  "properties": {
    "addr:full":"Avda La Libertad, 1 Barakaldo Vizcaya 48901",
    "addr:housenumber":"1",
    "addr:postcode":"48901",
    "addr:street":"Avda La Libertad",
    "iso:country":"ES",
    "sg:address":"Avda La Libertad, 1",
    "sg:city":"Barakaldo",
    "sg:orig_category":"Supermercados Y Hipermercados",
    "sg:phone":"+34 944 00 11 37",
    "sg:postcode":"48901",
    "sg:province":"Vizcaya",
    "sg:website":"www.bideonera.es",
    "wof:name":"Bide Onera Vasca S.c.l.",
    "wof:placetype":"venue"
},
  "geometry": {"coordinates":[-2.989346981,43.2954139709],"type":"Point"}
}