{
  "type": "Feature",
  "properties": {
    "addr:full":"Teso Feria, 4 Guijuelo Salamanca 37770",
    "addr:housenumber":"4",
    "addr:postcode":"37770",
    "addr:street":"Feria",
    "iso:country":"ES",
    "sg:address":"Teso Feria, 4",
    "sg:city":"Guijuelo",
    "sg:orig_category":"Mec\u00c1nico Del Autom\u00d3vil",
    "sg:phone":"+34 923 58 09 84",
    "sg:postcode":"37770",
    "sg:province":"Salamanca",
    "wof:name":"Benito Sanchez C.b.",
    "wof:placetype":"venue"
},
  "geometry": {"coordinates":[-5.6715140343,40.5596847534],"type":"Point"}
}