{
  "type": "Feature",
  "properties": {
    "addr:full":"Ctra Confeder. Hidrograf., Km. 0013,9 San Jose Rinconada Sevilla 41300",
    "addr:postcode":"41300",
    "addr:street":"Ctra Confeder. Hidrograf. Km. 0013,9",
    "iso:country":"ES",
    "sg:address":"Ctra Confeder. Hidrograf., Km. 0013,9",
    "sg:city":"San Jose Rinconada",
    "sg:orig_category":"Producci\u00d3n, Venta De Productos De Agricultura Biol\u00d3gica",
    "sg:phone":"+34 954 79 02 84",
    "sg:postcode":"41300",
    "sg:province":"Sevilla",
    "wof:name":"Agricola San Martin S. A.",
    "wof:placetype":"venue"
},
  "geometry": {"coordinates":[-5.9962949753,37.3826408386],"type":"Point"}
}