{
  "type": "Feature",
  "properties": {
    "iso:country":"ES",
    "sg:address":"Calle de Puerta Del Mar, 1",
    "sg:city":"Almeria",
    "sg:orig_category":"Servicios De Telecomunicaciones",
    "sg:phone":"+34 950 23 56 84",
    "sg:postcode":"04002",
    "sg:province":"Almer\u00eda",
    "wof:name":"Castillo Gomez Francisca",
    "wof:placetype":"venue"
},
  "geometry": {"coordinates":[-2.467674017,36.8364486694],"type":"Point"}
}