{
  "type": "Feature",
  "properties": {
    "iso:country":"ES",
    "sg:address":"Calle de Mayor, 29",
    "sg:city":"Estacion Ferrea",
    "sg:orig_category":"Asociaciones, Organismos Culturales Y Socioeducativos",
    "sg:phone":"+34 968 77 64 74",
    "sg:postcode":"30540",
    "sg:province":"Murcia",
    "wof:name":"Ayuntamiento De Blanca",
    "wof:placetype":"venue"
},
  "geometry": {"coordinates":[-1.3253190517,38.2256813049],"type":"Point"}
}