{
  "type": "Feature",
  "properties": {
    "iso:country":"ES",
    "sg:address":"Carrer de Vicomicia, 11",
    "sg:city":"S. Joan Despi",
    "sg:orig_category":"Productores Recolectores, Venta Directa De Vinos",
    "sg:phone":"+34 933 73 15 77",
    "sg:postcode":"08970",
    "sg:province":"Barcelona",
    "wof:name":"Aguilera Milanes Jose",
    "wof:placetype":"venue"
},
  "geometry": {"coordinates":[2.0577187538,41.3658218384],"type":"Point"}
}