{
  "type": "Feature",
  "properties": {
    "iso:country":"ES",
    "sg:address":"Vieja (la Vera), 48",
    "sg:city":"Sta.ursula",
    "sg:orig_category":"Quincaller\u00cda (al Por Menor)",
    "sg:phone":"+34 922 30 00 09",
    "sg:postcode":"38390",
    "sg:province":"Santa Cruz De Tenerife",
    "wof:name":"Regalado Alonso Juan",
    "wof:placetype":"venue"
},
  "geometry": {"coordinates":[-16.4917697906,28.425359726],"type":"Point"}
}