{
  "type": "Feature",
  "properties": {
    "iso:country":"ES",
    "sg:address":"Calle de Padre Marin, 18",
    "sg:city":"Logro\u00f1o",
    "sg:orig_category":"Molduras, Junquillos, Listones Y Molduras Perforadas",
    "sg:phone":"+34 941 25 27 69",
    "sg:postcode":"26004",
    "sg:province":"La Rioja",
    "wof:name":"Capilla Serrano Angel",
    "wof:placetype":"venue"
},
  "geometry": {"coordinates":[-2.4302289486,42.4652786255],"type":"Point"}
}