{
  "type": "Feature",
  "properties": {
    "iso:country":"ES",
    "sg:address":"Carrer de Mallorca, 569",
    "sg:city":"Barcelona",
    "sg:orig_category":"Relojer\u00cda (al Por Menor, Reparaci\u00d3n)",
    "sg:phone":"+34 934 33 12 31",
    "sg:postcode":"08026",
    "sg:province":"Barcelona",
    "wof:name":"Caymel Gomez Nuria",
    "wof:placetype":"venue"
},
  "geometry": {"coordinates":[2.1845099926,41.4105072021],"type":"Point"}
}