{
  "type": "Feature",
  "properties": {
    "iso:country":"ES",
    "sg:address":"Costa Puntarro, 1",
    "sg:city":"Valls",
    "sg:orig_category":"Ropa Para Se\u00d1oras Y Caballeros (al Por Menor)",
    "sg:phone":"+34 977 60 02 19",
    "sg:postcode":"43800",
    "sg:province":"Tarragona",
    "wof:name":"Stardress S.c.c.l",
    "wof:placetype":"venue"
},
  "geometry": {"coordinates":[1.2474550009,41.282661438],"type":"Point"}
}