{
  "type": "Feature",
  "properties": {
    "addr:full":"Calle de Sol, 16 Plasencia C\u00e1ceres 10600",
    "addr:housenumber":"16",
    "addr:postcode":"10600",
    "addr:street":"Calle De Sol;Ca\u0301Ceres",
    "iso:country":"ES",
    "sg:address":"Calle de Sol, 16",
    "sg:city":"Plasencia",
    "sg:orig_category":"Cueros Y Pieles (al Por Mayor)",
    "sg:phone":"+34 927 41 12 99",
    "sg:postcode":"10600",
    "sg:province":"C\u00e1ceres",
    "wof:name":"Curto De Haro Angel",
    "wof:placetype":"venue"
},
  "geometry": {"coordinates":[-6.087460041,40.0302391052],"type":"Point"}
}