{
  "type": "Feature",
  "properties": {
    "addr:full":"Carrer de Mineria, 12 Barcelona Barcelona 08038",
    "addr:housenumber":"12",
    "addr:postcode":"08038",
    "addr:street":"Carrer De Mineria",
    "iso:country":"ES",
    "sg:address":"Carrer de Mineria, 12",
    "sg:city":"Barcelona",
    "sg:orig_category":"Peluquer\u00cdas, Peluquer\u00cda Mixta",
    "sg:phone":"+34 934 21 23 37",
    "sg:postcode":"08038",
    "sg:province":"Barcelona",
    "wof:name":"Lerchundi Lerchundi Maria Teresa",
    "wof:placetype":"venue"
},
  "geometry": {"coordinates":[2.1373810768,41.3640632629],"type":"Point"}
}