{
  "type": "Feature",
  "properties": {
    "addr:full":"Carr San Pancracio, 15 Alboraya Valencia 46120",
    "addr:housenumber":"15",
    "addr:postcode":"46120",
    "addr:street":"Carr San Pancracio",
    "iso:country":"ES",
    "sg:address":"Carr San Pancracio, 15",
    "sg:city":"Alboraya",
    "sg:orig_category":"Art\u00cdculos Funerarios (al Por Menor)",
    "sg:phone":"+34 961 85 59 92",
    "sg:postcode":"46120",
    "sg:province":"Valencia",
    "wof:name":"Hurtado-la Paz S.l.",
    "wof:placetype":"venue"
},
  "geometry": {"coordinates":[-0.3505420089,39.4996376038],"type":"Point"}
}