{
  "type": "Feature",
  "properties": {
    "addr:full":"Calle de Pozo De La Nieve, 37 Aracena Huelva 21200",
    "addr:housenumber":"37",
    "addr:postcode":"21200",
    "addr:street":"Calle De Pozo De La Nieve",
    "iso:country":"ES",
    "sg:address":"Calle de Pozo De La Nieve, 37",
    "sg:city":"Aracena",
    "sg:orig_category":"Restaurantes",
    "sg:phone":"+34 959 12 80 44",
    "sg:postcode":"21200",
    "sg:province":"Huelva",
    "wof:name":"Romero De La Osa Sanchez-barbudo Manuel",
    "wof:placetype":"venue"
},
  "geometry": {"coordinates":[-6.5666160583,37.8906898499],"type":"Point"}
}