{
  "type": "Feature",
  "properties": {
    "iso:country":"ES",
    "sg:address":"Calle de Rufino Gonzalez, 34",
    "sg:city":"Madrid",
    "sg:orig_category":"Inform\u00c1tica (estudios, Servicios, Asesor\u00cda, Formaci\u00d3n)",
    "sg:phone":"+34 913 04 05 65",
    "sg:postcode":"28037",
    "sg:province":"Madrid",
    "sg:website":"www.diusframi.es",
    "wof:name":"Diusframi S.a.",
    "wof:placetype":"venue"
},
  "geometry": {"coordinates":[-3.6269330978,40.4382591248],"type":"Point"}
}