{
  "type": "Feature",
  "properties": {
    "addr:full":"Plaz Esperanza, 2 Santander Cantabria 39001",
    "addr:housenumber":"2",
    "addr:postcode":"39001",
    "addr:street":"Plaz Esperanza",
    "iso:country":"ES",
    "sg:address":"Plaz Esperanza, 2",
    "sg:city":"Santander",
    "sg:orig_category":"Ropa Y Accesorios",
    "sg:phone":"+34 942 21 60 06",
    "sg:postcode":"39001",
    "sg:province":"Cantabria",
    "wof:name":"Casanueva Bedia S. A.",
    "wof:placetype":"venue"
},
  "geometry": {"coordinates":[-3.8101890087,43.4632606506],"type":"Point"}
}