{
  "type": "Feature",
  "properties": {
    "addr:full":"Calle de Sahuquillo, 6 Gineta Albacete 02110",
    "addr:housenumber":"6",
    "addr:postcode":"02110",
    "addr:street":"Calle De Sahuquillo",
    "iso:country":"ES",
    "sg:address":"Calle de Sahuquillo, 6",
    "sg:city":"Gineta",
    "sg:orig_category":"Empresas De Carpinter\u00cda",
    "sg:phone":"+34 967 27 51 97",
    "sg:postcode":"02110",
    "sg:province":"Albacete",
    "wof:name":"Lerma Tobarra Miguel",
    "wof:placetype":"venue"
},
  "geometry": {"coordinates":[-1.9977840185,39.113067627],"type":"Point"}
}