{
  "type": "Feature",
  "properties": {
    "iso:country":"ES",
    "sg:address":"Calle de Villalta, 2",
    "sg:city":"Daimiel",
    "sg:orig_category":"Suministros Para Hoteles",
    "sg:phone":"+34 926 85 21 47",
    "sg:postcode":"13250",
    "sg:province":"Ciudad Real",
    "wof:name":"Mu\u00f1oz De Morales Rodriguez De Guzman Jesus Reyes",
    "wof:placetype":"venue"
},
  "geometry": {"coordinates":[-3.6140170097,39.0723762512],"type":"Point"}
}