{
  "type": "Feature",
  "properties": {
    "iso:country":"ES",
    "sg:address":"Hidraulica (pol Ind Drecera), 6",
    "sg:city":"Selva Del Camp",
    "sg:orig_category":"Empresas De Carpinter\u00cda",
    "sg:phone":"+34 977 84 50 43",
    "sg:postcode":"43470",
    "sg:province":"Tarragona",
    "wof:name":"Torval S.l.",
    "wof:placetype":"venue"
},
  "geometry": {"coordinates":[1.1493749619,41.215801239],"type":"Point"}
}