{
  "type": "Feature",
  "properties": {
    "addr:full":"Botavara, S/n Puerto Mazarron Murcia 30860",
    "addr:housenumber":"s / n",
    "addr:postcode":"30860",
    "addr:street":"Botavara",
    "iso:country":"ES",
    "sg:address":"Botavara, S/n",
    "sg:city":"Puerto Mazarron",
    "sg:orig_category":"Aparatos, Sistemas De Tele",
    "sg:phone":"+34 968 59 55 88",
    "sg:postcode":"30860",
    "sg:province":"Murcia",
    "wof:name":"Valchip S.l.",
    "wof:placetype":"venue"
},
  "geometry": {"coordinates":[-1.2610340118,37.5667037964],"type":"Point"}
}