{
  "type": "Feature",
  "properties": {
    "iso:country":"ES",
    "sg:address":"Avda Terra Cha, 85",
    "sg:city":"Castro",
    "sg:orig_category":"Material Y Suministros Para Veterinarios",
    "sg:phone":"+34 982 31 02 13",
    "sg:postcode":"27260",
    "sg:province":"Lugo",
    "wof:name":"Agro Castro S.l.",
    "wof:placetype":"venue"
},
  "geometry": {"coordinates":[-7.4934411049,43.1408805847],"type":"Point"}
}