{
  "type": "Feature",
  "properties": {
    "iso:country":"ES",
    "sg:address":"Valencia, 2",
    "sg:city":"Sollana",
    "sg:orig_category":"Producci\u00d3n, Venta De Productos De Agricultura Biol\u00d3gica",
    "sg:phone":"+34 961 74 07 34",
    "sg:postcode":"46430",
    "sg:province":"Valencia",
    "wof:name":"Cooperativa Agricola",
    "wof:placetype":"venue"
},
  "geometry": {"coordinates":[-0.3797889948,39.2790260315],"type":"Point"}
}