{
  "type": "Feature",
  "properties": {
    "iso:country":"ES",
    "sg:address":"Calle de Francisco Javier De Moya, 24",
    "sg:city":"Albacete",
    "sg:orig_category":"Pescader\u00cdas (al Por Menor)",
    "sg:phone":"+34 967 24 54 01",
    "sg:postcode":"02006",
    "sg:province":"Albacete",
    "wof:name":"Ruiz Copete Emilio",
    "wof:placetype":"venue"
},
  "geometry": {"coordinates":[-1.8464529514,38.9863166809],"type":"Point"}
}