{
  "type": "Feature",
  "properties": {
    "addr:full":"Calle de Alcalde Joaquin Quiles, 9 Malaga M\u00e1laga 29014",
    "addr:housenumber":"9",
    "addr:postcode":"29014",
    "addr:street":"Calle De Alcalde Joaquin Quiles;Ma\u0301Laga",
    "iso:country":"ES",
    "sg:address":"Calle de Alcalde Joaquin Quiles, 9",
    "sg:city":"Malaga",
    "sg:orig_category":"Comercio De Piezas De Recambio Y De Accesorios De Veh\u00cdculos, Veh\u00cdculos Industriales",
    "sg:phone":"+34 952 26 72 53",
    "sg:postcode":"29014",
    "sg:province":"M\u00e1laga",
    "wof:name":"Gil Ortega Antonio Jesus",
    "wof:placetype":"venue"
},
  "geometry": {"coordinates":[-4.4206118584,36.7495536804],"type":"Point"}
}