{
  "type": "Feature",
  "properties": {
    "iso:country":"ES",
    "sg:address":"Calle de Gamazo, 20",
    "sg:city":"Valladolid",
    "sg:orig_category":"Muebles Y Accesorios Para Cocinas Y Cuartos De Ba\u00d1o (al Por Menor)",
    "sg:phone":"+34 983 30 36 87",
    "sg:postcode":"47004",
    "sg:province":"Valladolid",
    "wof:name":"Solus S.l.",
    "wof:placetype":"venue"
},
  "geometry": {"coordinates":[-4.7263035774,41.6458053589],"type":"Point"}
}