{
  "type": "Feature",
  "properties": {
    "iso:country":"ES",
    "sg:address":"Calle de Tordo, 21",
    "sg:city":"Madrid",
    "sg:orig_category":"Asesor\u00cda Fiscal Y Jur\u00cddica",
    "sg:phone":"+34 914 72 40 92",
    "sg:postcode":"28019",
    "sg:province":"Madrid",
    "wof:name":"Artio Xxi Consulting S.l",
    "wof:placetype":"venue"
},
  "geometry": {"coordinates":[-3.7339193821,40.3924560547],"type":"Point"}
}