{
  "type": "Feature",
  "properties": {
    "addr:full":"Carrer de Mare De Deu Dels Reis, 9 Barcelona Barcelona 08023",
    "addr:housenumber":"9",
    "addr:postcode":"08023",
    "addr:street":"Carrer De Mare De Deu Dels Reis",
    "iso:country":"ES",
    "sg:address":"Carrer de Mare De Deu Dels Reis, 9",
    "sg:city":"Barcelona",
    "sg:orig_category":"Estudios De Grabaci\u00d3n Sonora",
    "sg:phone":"+34 932 19 17 36",
    "sg:postcode":"08023",
    "sg:province":"Barcelona",
    "sg:website":"www.oido.net",
    "wof:name":"Oido S.l.",
    "wof:placetype":"venue"
},
  "geometry": {"coordinates":[2.1454908848,41.4133148193],"type":"Point"}
}