{
  "type": "Feature",
  "properties": {
    "addr:full":"Calle de Eulogio Diaz Miranda, 5 Grado Asturias 33820",
    "addr:housenumber":"5",
    "addr:postcode":"33820",
    "addr:street":"Calle De Eulogio Diaz Miranda",
    "iso:country":"ES",
    "sg:address":"Calle de Eulogio Diaz Miranda, 5",
    "sg:city":"Grado",
    "sg:orig_category":"Sociedades, Compa\u00d1\u00cdas Aseguradoras",
    "sg:phone":"+34 985 75 28 83",
    "sg:postcode":"33820",
    "sg:province":"Asturias",
    "wof:name":"Mapfre Servicios De Informatica S.a.",
    "wof:placetype":"venue"
},
  "geometry": {"coordinates":[-6.0691452026,43.3902397156],"type":"Point"}
}