{
  "type": "Feature",
  "properties": {
    "iso:country":"ES",
    "sg:address":"Rond Paisos Catalans (dels), 35",
    "sg:city":"Mataro",
    "sg:orig_category":"Muebles, Minoristas",
    "sg:phone":"+34 937 41 44 64",
    "sg:postcode":"08304",
    "sg:province":"Barcelona",
    "wof:name":"Axiac 2000 S.l.",
    "wof:placetype":"venue"
},
  "geometry": {"coordinates":[2.445581913,41.5602912903],"type":"Point"}
}