{
  "type": "Feature",
  "properties": {
    "iso:country":"ES",
    "sg:address":"Ctra Argamasilla De Alba, Km. 0001,2",
    "sg:city":"Tomelloso",
    "sg:orig_category":"Suministros Para Carrocer\u00cdas",
    "sg:phone":"+34 926 51 34 54",
    "sg:postcode":"13700",
    "sg:province":"Ciudad Real",
    "wof:name":"Coryal S.l.",
    "wof:placetype":"venue"
},
  "geometry": {"coordinates":[-3.0052940845,39.1665611267],"type":"Point"}
}