{
  "type": "Feature",
  "properties": {
    "addr:full":"Carrer de Major, 32 Castalla Alicante 03420",
    "addr:housenumber":"32",
    "addr:postcode":"03420",
    "addr:street":"Carrer De Major",
    "iso:country":"ES",
    "sg:address":"Carrer de Major, 32",
    "sg:city":"Castalla",
    "sg:orig_category":"M\u00c9dicos: Estomatolog\u00cda",
    "sg:phone":"+34 965 56 00 11",
    "sg:postcode":"03420",
    "sg:province":"Alicante",
    "wof:name":"Bernabeu Guill Fermin",
    "wof:placetype":"venue"
},
  "geometry": {"coordinates":[-0.6708649993,38.596206665],"type":"Point"}
}