{
  "type": "Feature",
  "properties": {
    "iso:country":"ES",
    "sg:address":"Eix-ample, 10",
    "sg:city":"Albal",
    "sg:orig_category":"Internados & Ense\u00d1anza Privada",
    "sg:phone":"+34 961 26 19 84",
    "sg:postcode":"46470",
    "sg:province":"Valencia",
    "wof:name":"Colegio Santa Ana",
    "wof:placetype":"venue"
},
  "geometry": {"coordinates":[-0.4147959948,39.3968544006],"type":"Point"}
}