{
  "type": "Feature",
  "properties": {
    "addr:full":"Calle de Monte Esquinza, 24 Madrid Madrid 28010",
    "addr:housenumber":"24",
    "addr:postcode":"madrid;28010",
    "addr:street":"Calle De Monte Esquinza",
    "iso:country":"ES",
    "sg:address":"Calle de Monte Esquinza, 24",
    "sg:city":"Madrid",
    "sg:orig_category":"Organismos De Reclutamiento",
    "sg:phone":"+34 915 77 50 44",
    "sg:postcode":"28010",
    "sg:province":"Madrid",
    "wof:name":"Latinsearch International S.a.",
    "wof:placetype":"venue"
},
  "geometry": {"coordinates":[-3.6918759346,40.4286308289],"type":"Point"}
}