{
  "type": "Feature",
  "properties": {
    "addr:full":"Calle de Rafaela De Antonio, 1 Avila \u00c1vila 05002",
    "addr:housenumber":"1",
    "addr:postcode":"05002",
    "addr:street":"Calle De Rafaela De Antonio;A\u0301Vila",
    "iso:country":"ES",
    "sg:address":"Calle de Rafaela De Antonio, 1",
    "sg:city":"Avila",
    "sg:orig_category":"Art\u00cdculos Para Fumadores (al Por Menor)",
    "sg:phone":"+34 920 21 26 19",
    "sg:postcode":"05002",
    "sg:province":"\u00c1vila",
    "wof:name":"Proven C.b.",
    "wof:placetype":"venue"
},
  "geometry": {"coordinates":[-4.6994037628,40.6488418579],"type":"Point"}
}