{
  "type": "Feature",
  "properties": {
    "iso:country":"ES",
    "sg:address":"Calle de Garcia Prieto, 12",
    "sg:city":"Luarca",
    "sg:orig_category":"Peluqueros: De Se\u00d1oras",
    "sg:phone":"+34 985 64 04 57",
    "sg:postcode":"33700",
    "sg:province":"Asturias",
    "wof:name":"Suarez Garcia Raquel",
    "wof:placetype":"venue"
},
  "geometry": {"coordinates":[-6.5354423523,43.5420188904],"type":"Point"}
}