{
  "type": "Feature",
  "properties": {
    "addr:full":"Calle de Ordesa, 1 Caceres C\u00e1ceres 10005",
    "addr:housenumber":"1",
    "addr:postcode":"10005",
    "addr:street":"Calle De Ordesa;Ca\u0301Ceres",
    "iso:country":"ES",
    "sg:address":"Calle de Ordesa, 1",
    "sg:city":"Caceres",
    "sg:orig_category":"Ingenier\u00cda, Centros De Estudios (diversos)",
    "sg:phone":"+34 927 62 66 27",
    "sg:postcode":"10005",
    "sg:province":"C\u00e1ceres",
    "wof:name":"Aristos Ingenieros Consultores S.l.",
    "wof:placetype":"venue"
},
  "geometry": {"coordinates":[-6.3902029991,39.4713058472],"type":"Point"}
}