{
  "type": "Feature",
  "properties": {
    "addr:full":"Calle de Oca\u00d1a, 22 Madrid Madrid 28047",
    "addr:housenumber":"22",
    "addr:postcode":"madrid;28047",
    "addr:street":"Calle De Ocan\u0303A",
    "iso:country":"ES",
    "sg:address":"Calle de Oca\u00d1a, 22",
    "sg:city":"Madrid",
    "sg:orig_category":"Quincaller\u00cda (al Por Menor)",
    "sg:phone":"+34 914 61 94 47",
    "sg:postcode":"28047",
    "sg:province":"Madrid",
    "wof:name":"Frias Garcia Angel",
    "wof:placetype":"venue"
},
  "geometry": {"coordinates":[-3.7542960644,40.3843078613],"type":"Point"}
}