{
  "type": "Feature",
  "properties": {
    "iso:country":"ES",
    "sg:address":"Calle de Galiano, 6",
    "sg:city":"S. Fernando",
    "sg:orig_category":"Muebles, Minoristas",
    "sg:phone":"+34 956 89 46 51",
    "sg:postcode":"11100",
    "sg:province":"C\u00e1diz",
    "wof:name":"Vimuna 2006 S.l.",
    "wof:placetype":"venue"
},
  "geometry": {"coordinates":[-6.2027587891,36.4588813782],"type":"Point"}
}