{
  "type": "Feature",
  "properties": {
    "iso:country":"ES",
    "sg:address":"Calle de San Isidro, 7",
    "sg:city":"Cuevas Campo",
    "sg:orig_category":"Sociedades, Compa\u00d1\u00cdas Aseguradoras",
    "sg:phone":"+34 958 71 84 13",
    "sg:postcode":"18813",
    "sg:province":"Granada",
    "wof:name":"Garcia Hidalgo Maria Dolores",
    "wof:placetype":"venue"
},
  "geometry": {"coordinates":[-2.9309539795,37.6091308594],"type":"Point"}
}