{
  "type": "Feature",
  "properties": {
    "addr:full":"Calle de Resolana, 43 Sevilla Sevilla 41002",
    "addr:housenumber":"43",
    "addr:postcode":"41002",
    "addr:street":"Calle De Resolana",
    "iso:country":"ES",
    "sg:address":"Calle de Resolana, 43",
    "sg:city":"Sevilla",
    "sg:orig_category":"Molduras, Junquillos, Listones Y Molduras Perforadas",
    "sg:phone":"+34 954 90 96 22",
    "sg:postcode":"41002",
    "sg:province":"Sevilla",
    "wof:name":"Mejias Gutierrez Francisco",
    "wof:placetype":"venue"
},
  "geometry": {"coordinates":[-5.9901361465,37.4029464722],"type":"Point"}
}