{
  "type": "Feature",
  "properties": {
    "iso:country":"ES",
    "sg:address":"Mcdo Av. Madrid, 1",
    "sg:city":"Zaragoza",
    "sg:orig_category":"Alimentaci\u00d3n General (al Por Menor)",
    "sg:phone":"+34 976 34 48 80",
    "sg:postcode":"50010",
    "sg:province":"Zaragoza",
    "wof:name":"Alfaro San Miguel Ramon",
    "wof:placetype":"venue"
},
  "geometry": {"coordinates":[-0.8939191103,41.6558876038],"type":"Point"}
}