{
  "type": "Feature",
  "properties": {
    "addr:full":"Calle de Villarrubia De Los Ojos, 14 Ciudad Real Ciudad Real 13004",
    "addr:housenumber":"14",
    "addr:postcode":"13004",
    "addr:street":"Calle De Villarrubia;Los Ojos",
    "iso:country":"ES",
    "sg:address":"Calle de Villarrubia De Los Ojos, 14",
    "sg:city":"Ciudad Real",
    "sg:orig_category":"Maquinaria Para Industrias Diversas",
    "sg:phone":"+34 926 21 52 21",
    "sg:postcode":"13004",
    "sg:province":"Ciudad Real",
    "wof:name":"Metsa Ciudad Real S.l.",
    "wof:placetype":"venue"
},
  "geometry": {"coordinates":[-3.9315979481,38.9745521545],"type":"Point"}
}