{
  "type": "Feature",
  "properties": {
    "addr:full":"Calle de Solana (de La), 3 Pinto Madrid 28320",
    "addr:housenumber":"3",
    "addr:postcode":"28320",
    "addr:street":"Calle De Solana De La;Pinto",
    "iso:country":"ES",
    "sg:address":"Calle de Solana (de La), 3",
    "sg:city":"Pinto",
    "sg:orig_category":"Centros Empresariales",
    "sg:phone":"+34 916 92 05 55",
    "sg:postcode":"28320",
    "sg:province":"Madrid",
    "wof:name":"Punctum Noticias Siglo Xxi",
    "wof:placetype":"venue"
},
  "geometry": {"coordinates":[-3.69769907,40.243938446],"type":"Point"}
}