{
  "type": "Feature",
  "properties": {
    "iso:country":"ES",
    "sg:address":"Ctra Oliva, S/n",
    "sg:city":"Zahinos",
    "sg:orig_category":"Negocio De Materiales De Construcci\u00d3n",
    "sg:phone":"+34 924 73 81 77",
    "sg:postcode":"06129",
    "sg:province":"Badajoz",
    "wof:name":"Rios Perera Maria Jose",
    "wof:placetype":"venue"
},
  "geometry": {"coordinates":[-6.9512190819,38.3272399902],"type":"Point"}
}