{
  "type": "Feature",
  "properties": {
    "iso:country":"ES",
    "sg:address":"Avda Playa (de La), 1",
    "sg:city":"Conil De La Frontera",
    "sg:orig_category":"Art\u00cdculos De Regalo (al Por Menor)",
    "sg:phone":"+34 956 44 29 45",
    "sg:postcode":"11140",
    "sg:province":"C\u00e1diz",
    "wof:name":"Ramirez Ureba Juan Maria",
    "wof:placetype":"venue"
},
  "geometry": {"coordinates":[-6.0898489952,36.2740211487],"type":"Point"}
}