{
  "type": "Feature",
  "properties": {
    "addr:full":"Calle de Almeria, 21 Armilla Granada 18100",
    "addr:housenumber":"21",
    "addr:postcode":"18100",
    "addr:street":"Calle De Almeria",
    "iso:country":"ES",
    "sg:address":"Calle de Almeria, 21",
    "sg:city":"Armilla",
    "sg:orig_category":"Comit\u00c9s De Organizaci\u00d3n De Exposiciones, Ferias, Salones",
    "sg:phone":"+34 958 55 16 36",
    "sg:postcode":"18100",
    "sg:province":"Granada",
    "wof:name":"Soluciones Activa S.l.",
    "wof:placetype":"venue"
},
  "geometry": {"coordinates":[-3.6250169277,37.14087677],"type":"Point"}
}