{
  "type": "Feature",
  "properties": {
    "addr:full":"Calle de Galicia, 29 Palmas De Gran Canaria Las Palmas 35007",
    "addr:postcode":"35007",
    "addr:street":"Calle De Galicia 29",
    "iso:country":"ES",
    "sg:address":"Calle de Galicia, 29",
    "sg:city":"Palmas De Gran Canaria",
    "sg:orig_category":"Cl\u00cdnicas Dentales",
    "sg:phone":"+34 928 22 93 25",
    "sg:postcode":"35007",
    "sg:province":"Las Palmas",
    "wof:name":"Cuasnicu Furst Jorge",
    "wof:placetype":"venue"
},
  "geometry": {"coordinates":[-15.4331521988,28.1349067688],"type":"Point"}
}