{
  "type": "Feature",
  "properties": {
    "iso:country":"ES",
    "sg:address":"Carrer de Abat Escarre, 20",
    "sg:city":"Rubi",
    "sg:orig_category":"Promotores Constructores",
    "sg:phone":"+34 936 97 78 96",
    "sg:postcode":"08191",
    "sg:province":"Barcelona",
    "wof:name":"Promociones Isamax S.l.",
    "wof:placetype":"venue"
},
  "geometry": {"coordinates":[2.0331470966,41.4864463806],"type":"Point"}
}