{
  "type": "Feature",
  "properties": {
    "addr:full":"Pg Ribera, 34 Sitges Barcelona 08870",
    "addr:housenumber":"34",
    "addr:postcode":"08870",
    "addr:street":"Ribera",
    "iso:country":"ES",
    "sg:address":"Pg Ribera, 34",
    "sg:city":"Sitges",
    "sg:orig_category":"Agencias Y Agentes Comerciales, Representantes",
    "sg:phone":"+34 938 94 75 02",
    "sg:postcode":"08870",
    "sg:province":"Barcelona",
    "wof:name":"Ferre Portero Josep",
    "wof:placetype":"venue"
},
  "geometry": {"coordinates":[1.8079669476,41.2351341248],"type":"Point"}
}