{
  "type": "Feature",
  "properties": {
    "iso:country":"ES",
    "sg:address":"Rua Doctor Fleming, 30",
    "sg:city":"Ourense",
    "sg:orig_category":"Producci\u00d3n, Distribuci\u00d3n De Gas Butano Y Propano",
    "sg:phone":"+34 988 22 57 40",
    "sg:postcode":"32003",
    "sg:province":"Ourense",
    "wof:name":"Burgas Distribucion S.a.",
    "wof:placetype":"venue"
},
  "geometry": {"coordinates":[-7.8673429489,42.3387908936],"type":"Point"}
}