{
  "type": "Feature",
  "properties": {
    "addr:full":"Avda Universidad, 21 Leganes Madrid 28911",
    "addr:housenumber":"21",
    "addr:postcode":"28911",
    "addr:street":"Avda Universidad",
    "iso:country":"ES",
    "sg:address":"Avda Universidad, 21",
    "sg:city":"Leganes",
    "sg:orig_category":"Zapatos (al Por Menor)",
    "sg:phone":"+34 916 80 31 75",
    "sg:postcode":"28911",
    "sg:province":"Madrid",
    "wof:name":"Calzados Carmina S. A.",
    "wof:placetype":"venue"
},
  "geometry": {"coordinates":[-3.7653999329,40.3307037354],"type":"Point"}
}