{
  "type": "Feature",
  "properties": {
    "iso:country":"ES",
    "sg:address":"Avda Inmaculada (de La), S/n",
    "sg:city":"Avila",
    "sg:orig_category":"Universidades",
    "sg:phone":"+34 920 22 19 69",
    "sg:postcode":"05005",
    "sg:province":"\u00c1vila",
    "sg:website":"www.ucavila.es",
    "wof:name":"Universidad Catolica De Avila Santa Teresa De Jesus De A.",
    "wof:placetype":"venue"
},
  "geometry": {"coordinates":[-4.6863088608,40.661151886],"type":"Point"}
}