{
  "type": "Feature",
  "properties": {
    "addr:full":"Rbla Modolell, 31 Viladecans Barcelona 08840",
    "addr:housenumber":"31",
    "addr:postcode":"08840",
    "addr:street":"Rbla Modolell",
    "iso:country":"ES",
    "sg:address":"Rbla Modolell, 31",
    "sg:city":"Viladecans",
    "sg:orig_category":"Cajas De Ahorro",
    "sg:phone":"+34 936 58 01 70",
    "sg:postcode":"08840",
    "sg:province":"Barcelona",
    "wof:name":"Caja De Ahorros De Valencia Castellon Y Alicante",
    "wof:placetype":"venue"
},
  "geometry": {"coordinates":[2.019546032,41.3177947998],"type":"Point"}
}