{
  "type": "Feature",
  "properties": {
    "addr:full":"Rua Seixedo, 4 Vilarrodis La Coru\u00f1a 15141",
    "addr:housenumber":"4",
    "addr:postcode":"15141",
    "addr:street":"Rua Seixedo;La Corun\u0303A",
    "iso:country":"ES",
    "sg:address":"Rua Seixedo, 4",
    "sg:city":"Vilarrodis",
    "sg:orig_category":"Peluqueros: De Se\u00d1oras",
    "sg:phone":"+34 981 60 21 23",
    "sg:postcode":"15141",
    "sg:province":"La Coru\u00f1a",
    "wof:name":"Balay S.l.",
    "wof:placetype":"venue"
},
  "geometry": {"coordinates":[-8.4871311188,43.3164863586],"type":"Point"}
}