{
  "type": "Feature",
  "properties": {
    "iso:country":"ES",
    "sg:address":"Calle de El Carmen, 6",
    "sg:city":"Aljaraque",
    "sg:orig_category":"Peluquer\u00cdas",
    "sg:phone":"+34 959 31 88 62",
    "sg:postcode":"21110",
    "sg:province":"Huelva",
    "wof:name":"Aljarafestil S.coop.a.",
    "wof:placetype":"venue"
},
  "geometry": {"coordinates":[-7.0221581459,37.2696800232],"type":"Point"}
}