{
  "type": "Feature",
  "properties": {
    "iso:country":"ES",
    "sg:address":"Carr Mare Nostrum, 6",
    "sg:city":"Quart Poblet",
    "sg:orig_category":"Plomeros",
    "sg:phone":"+34 961 54 90 63",
    "sg:postcode":"46930",
    "sg:province":"Valencia",
    "wof:name":"Ballesteros Arroyo Melquiades",
    "wof:placetype":"venue"
},
  "geometry": {"coordinates":[-0.4445550144,39.4805183411],"type":"Point"}
}