{
  "type": "Feature",
  "properties": {
    "addr:full":"Carr Camp Rabassa, S/n Escala Girona 17130",
    "addr:housenumber":"s / n",
    "addr:postcode":"17130",
    "addr:street":"Carr Camp Rabassa",
    "iso:country":"ES",
    "sg:address":"Carr Camp Rabassa, S/n",
    "sg:city":"Escala",
    "sg:orig_category":"Frutas, Legumbres Frescas Y Tempranas (al Por Menor)",
    "sg:phone":"+34 972 77 42 83",
    "sg:postcode":"17130",
    "sg:province":"Girona",
    "wof:name":"Fruites Nuria S.l.",
    "wof:placetype":"venue"
},
  "geometry": {"coordinates":[3.1420550346,42.1130943298],"type":"Point"}
}