{
  "type": "Feature",
  "properties": {
    "addr:full":"Ctra Tavernes Valldigna-lliria, 56 Vilamarxant Valencia 46191",
    "addr:housenumber":"56",
    "addr:postcode":"46191",
    "addr:street":"Ctra Tavernes Valldigna-Lliria",
    "iso:country":"ES",
    "sg:address":"Ctra Tavernes Valldigna-lliria, 56",
    "sg:city":"Vilamarxant",
    "sg:orig_category":"Mec\u00c1nico Del Autom\u00d3vil",
    "sg:phone":"+34 962 71 21 97",
    "sg:postcode":"46191",
    "sg:province":"Valencia",
    "wof:name":"Rodrigo Fabuel Jose",
    "wof:placetype":"venue"
},
  "geometry": {"coordinates":[-0.6272540092,39.5677604675],"type":"Point"}
}