{
  "type": "Feature",
  "properties": {
    "iso:country":"ES",
    "sg:address":"Carr Es Cos De Gracia, 19",
    "sg:city":"Mao",
    "sg:orig_category":"Centros De Coordinaci\u00d3n",
    "sg:phone":"+34 971 35 04 53",
    "sg:postcode":"07702",
    "sg:province":"Islas Baleares",
    "wof:name":"Mas Dubia Juan",
    "wof:placetype":"venue"
},
  "geometry": {"coordinates":[4.2666678429,39.8798713684],"type":"Point"}
}