{
  "type": "Feature",
  "properties": {
    "addr:full":"Av Alameda (l'), 53 Alcoi Alicante 03803",
    "addr:housenumber":"53",
    "addr:postcode":"03803",
    "addr:street":"Av Alameda L '",
    "iso:country":"ES",
    "sg:address":"Av Alameda (l'), 53",
    "sg:city":"Alcoi",
    "sg:orig_category":"Peluquer\u00cdas, Peluquer\u00cda Mixta",
    "sg:phone":"+34 966 52 13 71",
    "sg:postcode":"03803",
    "sg:province":"Alicante",
    "sg:website":"www.llongueras.com",
    "wof:name":"Frances Peluqueros S.l.",
    "wof:placetype":"venue"
},
  "geometry": {"coordinates":[-0.4766409993,38.7027931213],"type":"Point"}
}