{
  "type": "Feature",
  "properties": {
    "iso:country":"ES",
    "sg:address":"Carr Albal, 2",
    "sg:city":"Silla",
    "sg:orig_category":"Muebles Y Accesorios Para Cocinas Y Cuartos De Ba\u00d1o (al Por Menor)",
    "sg:phone":"+34 961 21 25 77",
    "sg:postcode":"46460",
    "sg:province":"Valencia",
    "wof:name":"Decocuin S.l.",
    "wof:placetype":"venue"
},
  "geometry": {"coordinates":[-0.417858988,39.3685531616],"type":"Point"}
}