{
  "type": "Feature",
  "properties": {
    "addr:full":"Calle de Real, 49 Ponferrada Le\u00f3n 24400",
    "addr:housenumber":"49",
    "addr:postcode":"24400",
    "addr:street":"Calle De Real",
    "iso:country":"ES",
    "sg:address":"Calle de Real, 49",
    "sg:city":"Ponferrada",
    "sg:orig_category":"Librer\u00cdas",
    "sg:phone":"+34 987 41 56 52",
    "sg:postcode":"24400",
    "sg:province":"Le\u00f3n",
    "wof:name":"Perez Fernandez Celso",
    "wof:placetype":"venue"
},
  "geometry": {"coordinates":[-6.5964388847,42.5470199585],"type":"Point"}
}