{
  "type": "Feature",
  "properties": {
    "iso:country":"ES",
    "sg:address":"Calle de Fuente (la), 7",
    "sg:city":"Algar",
    "sg:orig_category":"Formaci\u00d3n Continuada (variada)",
    "sg:phone":"+34 956 72 50 68",
    "sg:postcode":"11639",
    "sg:province":"C\u00e1diz",
    "wof:name":"Ayuntamiento De Algar",
    "wof:placetype":"venue"
},
  "geometry": {"coordinates":[-5.6579589844,36.655330658],"type":"Point"}
}