{
  "type": "Feature",
  "properties": {
    "iso:country":"ES",
    "sg:address":"Pase San Frantzisko Ibiltokia, 43",
    "sg:city":"Tolosa",
    "sg:orig_category":"Cl\u00cdnicas Dentales",
    "sg:phone":"+34 943 65 08 59",
    "sg:postcode":"20400",
    "sg:province":"Guip\u00f9zcoa",
    "wof:name":"C.m.q. Buccalist S.l.",
    "wof:placetype":"venue"
},
  "geometry": {"coordinates":[-2.0795431137,43.1336975098],"type":"Point"}
}