{
  "type": "Feature",
  "properties": {
    "addr:full":"Calle de Vicente Blasco Iba\u00d1ez, 7 Riba-roja Turia Valencia 46190",
    "addr:housenumber":"7",
    "addr:postcode":"46190",
    "addr:street":"Calle De Vicente Blasco Iban\u0303Ez",
    "iso:country":"ES",
    "sg:address":"Calle de Vicente Blasco Iba\u00d1ez, 7",
    "sg:city":"Riba-roja Turia",
    "sg:orig_category":"Peluqueros: De Se\u00d1oras",
    "sg:phone":"+34 962 77 00 00",
    "sg:postcode":"46190",
    "sg:province":"Valencia",
    "wof:name":"Guzman Lopez Josefa",
    "wof:placetype":"venue"
},
  "geometry": {"coordinates":[-0.5764139891,39.5464744568],"type":"Point"}
}