{
  "type": "Feature",
  "properties": {
    "iso:country":"ES",
    "sg:address":"Calle de Doctor Ramon Castroviejo, 5",
    "sg:city":"Madrid",
    "sg:orig_category":"Venta, Instalaci\u00d3n, Reparaci\u00d3n De Antenas Para Televisi\u00d3n",
    "sg:phone":"+34 913 16 46 77",
    "sg:postcode":"28035",
    "sg:province":"Madrid",
    "wof:name":"Andetel S.l.",
    "wof:placetype":"venue"
},
  "geometry": {"coordinates":[-3.7133221626,40.4798355103],"type":"Point"}
}