{
  "type": "Feature",
  "properties": {
    "addr:full":"Avda Zumalacarregui, 109 Bilbao Vizcaya 48007",
    "addr:housenumber":"109",
    "addr:postcode":"48007",
    "addr:street":"Avda Zumalacarregui",
    "iso:country":"ES",
    "sg:address":"Avda Zumalacarregui, 109",
    "sg:city":"Bilbao",
    "sg:orig_category":"Ropa De Casa (fabricaci\u00d3n, Al Por Mayor)",
    "sg:phone":"+34 944 13 02 91",
    "sg:postcode":"48007",
    "sg:province":"Vizcaya",
    "wof:name":"Lydia Textiles S.l.",
    "wof:placetype":"venue"
},
  "geometry": {"coordinates":[-2.9146869183,43.2611961365],"type":"Point"}
}