{
  "type": "Feature",
  "properties": {
    "addr:full":"Avda Rafael Onieva Ariza, 4 Baena C\u00f3rdoba 14850",
    "addr:housenumber":"4",
    "addr:postcode":"14850",
    "addr:street":"Avda Rafael Onieva Ariza",
    "iso:country":"ES",
    "sg:address":"Avda Rafael Onieva Ariza, 4",
    "sg:city":"Baena",
    "sg:orig_category":"Imprenta",
    "sg:phone":"+34 957 67 03 38",
    "sg:postcode":"14850",
    "sg:province":"C\u00f3rdoba",
    "wof:name":"Imprenta Juventud Sl",
    "wof:placetype":"venue"
},
  "geometry": {"coordinates":[-4.2948884964,37.6670646667],"type":"Point"}
}