{
  "type": "Feature",
  "properties": {
    "iso:country":"ES",
    "sg:address":"Calle de Santa Maria De Gracia, 21",
    "sg:city":"Camas",
    "sg:orig_category":"Mercer\u00cda, Lencer\u00cda (al Por Menor)",
    "sg:phone":"+34 954 39 57 00",
    "sg:postcode":"41900",
    "sg:province":"Sevilla",
    "wof:name":"Pontes Leon Maria Teresa",
    "wof:placetype":"venue"
},
  "geometry": {"coordinates":[-6.035130024,37.4024658203],"type":"Point"}
}