{
  "type": "Feature",
  "properties": {
    "iso:country":"ES",
    "sg:address":"Ctra Valencia, Km. 0089,0",
    "sg:city":"S. Juan Alicante",
    "sg:orig_category":"Art\u00cdculos De Regalo (al Por Menor)",
    "sg:phone":"+34 965 94 11 30",
    "sg:postcode":"03550",
    "sg:province":"Alicante",
    "wof:name":"Garcia Sala Cristina",
    "wof:placetype":"venue"
},
  "geometry": {"coordinates":[-0.4289290011,38.400390625],"type":"Point"}
}