{
  "type": "Feature",
  "properties": {
    "iso:country":"ES",
    "sg:address":"Avda Virgen De Los Dolores, 21",
    "sg:city":"Cordoba",
    "sg:orig_category":"Peluqueros: De Se\u00d1oras",
    "sg:phone":"+34 957 45 00 19",
    "sg:postcode":"14004",
    "sg:province":"C\u00f3rdoba",
    "wof:name":"Caro Jimenez Juan Carlos",
    "wof:placetype":"venue"
},
  "geometry": {"coordinates":[-4.7942900658,37.8737373352],"type":"Point"}
}