{
  "type": "Feature",
  "properties": {
    "addr:full":"Cami Cabana, 59 Pont D'inca Islas Baleares 07009",
    "addr:housenumber":"59",
    "addr:postcode":"07009",
    "addr:street":"Cabana;Pont D'Inca",
    "iso:country":"ES",
    "sg:address":"Cami Cabana, 59",
    "sg:city":"Pont D'inca",
    "sg:orig_category":"Promotores Constructores",
    "sg:phone":"+34 971 79 42 69",
    "sg:postcode":"07009",
    "sg:province":"Islas Baleares",
    "wof:name":"Grupo Inmo Barbeiron S L",
    "wof:placetype":"venue"
},
  "geometry": {"coordinates":[2.895553112,39.7234764099],"type":"Point"}
}