{
  "type": "Feature",
  "properties": {
    "addr:full":"Ctra. Estartit-s. Jordi, S/n Estartit Girona 17258",
    "addr:housenumber":"s",
    "addr:postcode":"17258",
    "addr:street":"Ctra. Estartit-S. Jordi;/ N",
    "iso:country":"ES",
    "sg:address":"Ctra. Estartit-s. Jordi, S/n",
    "sg:city":"Estartit",
    "sg:orig_category":"Supermercados Y Hipermercados",
    "sg:phone":"+34 972 75 13 65",
    "sg:postcode":"17258",
    "sg:province":"Girona",
    "wof:name":"Carleser S.l.",
    "wof:placetype":"venue"
},
  "geometry": {"coordinates":[3.1878299713,42.0489959717],"type":"Point"}
}