{
  "type": "Feature",
  "properties": {
    "iso:country":"ES",
    "sg:address":"Carrer de Font D'en Canyelles, 79",
    "sg:city":"Barcelona",
    "sg:orig_category":"Inmobiliaria (agencias)",
    "sg:phone":"+34 933 53 58 73",
    "sg:postcode":"08042",
    "sg:province":"Barcelona",
    "wof:name":"Fincas Corral S.l.",
    "wof:placetype":"venue"
},
  "geometry": {"coordinates":[2.1752932072,41.4406089783],"type":"Point"}
}