{
  "type": "Feature",
  "properties": {
    "iso:country":"ES",
    "sg:address":"Calle de Carmen (del), 17",
    "sg:city":"Viso",
    "sg:orig_category":"Plomeros",
    "sg:phone":"+34 957 12 71 99",
    "sg:postcode":"14470",
    "sg:province":"C\u00f3rdoba",
    "wof:name":"Risquez Lopez Alfonso",
    "wof:placetype":"venue"
},
  "geometry": {"coordinates":[-4.9554538727,38.4845504761],"type":"Point"}
}