{
  "type": "Feature",
  "properties": {
    "addr:full":"Calle de Zaragoza, 20 Binefar Huesca 22500",
    "addr:housenumber":"20",
    "addr:postcode":"22500",
    "addr:street":"Calle De Zaragoza",
    "iso:country":"ES",
    "sg:address":"Calle de Zaragoza, 20",
    "sg:city":"Binefar",
    "sg:orig_category":"Artesan\u00cda",
    "sg:phone":"+34 974 43 12 86",
    "sg:postcode":"22500",
    "sg:province":"Huesca",
    "wof:name":"Torralba Ardiaca Silvia",
    "wof:placetype":"venue"
},
  "geometry": {"coordinates":[0.2922109962,41.8505363464],"type":"Point"}
}