{
  "type": "Feature",
  "properties": {
    "iso:country":"ES",
    "sg:address":"Ctra Aeroport, Km. 0003,8",
    "sg:city":"Sant Jordi De Ses Salines",
    "sg:orig_category":"Chapister\u00cda",
    "sg:phone":"+34 971 30 00 10",
    "sg:postcode":"07817",
    "sg:province":"Islas Baleares",
    "wof:name":"Serra Palau S.l.",
    "wof:placetype":"venue"
},
  "geometry": {"coordinates":[1.4075000286,38.8912010193],"type":"Point"}
}