{
  "type": "Feature",
  "properties": {
    "iso:country":"ES",
    "sg:address":"Praz Teucro (do), 1",
    "sg:city":"Pontevedra",
    "sg:orig_category":"Centros P\u00dablicos De Formaci\u00d3n Profesional Y T\u00c9cnica",
    "sg:phone":"+34 986 84 61 79",
    "sg:postcode":"36002",
    "sg:province":"Pontevedra",
    "wof:name":"Colegio Oficial Secretarios Interventores Y Depositarios De La Administracion",
    "wof:placetype":"venue"
},
  "geometry": {"coordinates":[-8.6453056335,42.4329032898],"type":"Point"}
}