{
  "type": "Feature",
  "properties": {
    "addr:full":"Avda Buenos Aires, 60 Madrid Madrid 28018",
    "addr:housenumber":"60",
    "addr:postcode":"madrid;28018",
    "addr:street":"Avda Buenos Aires",
    "iso:country":"ES",
    "sg:address":"Avda Buenos Aires, 60",
    "sg:city":"Madrid",
    "sg:orig_category":"Molduras, Junquillos, Listones Y Molduras Perforadas",
    "sg:phone":"+34 917 78 56 15",
    "sg:postcode":"28018",
    "sg:province":"Madrid",
    "wof:name":"Manzanares Lopez Cecilio Ignacio",
    "wof:placetype":"venue"
},
  "geometry": {"coordinates":[-3.6534190178,40.3889045715],"type":"Point"}
}