{
  "type": "Feature",
  "properties": {
    "addr:full":"Calle de Sierra Carbonera, 38 Dos Hermanas Sevilla 41700",
    "addr:housenumber":"38",
    "addr:postcode":"41700",
    "addr:street":"Calle De Sierra Carbonera",
    "iso:country":"ES",
    "sg:address":"Calle de Sierra Carbonera, 38",
    "sg:city":"Dos Hermanas",
    "sg:orig_category":"Montaje (empresas De)",
    "sg:phone":"+34 955 66 42 68",
    "sg:postcode":"41700",
    "sg:province":"Sevilla",
    "wof:name":"Arquellada Cabrera David",
    "wof:placetype":"venue"
},
  "geometry": {"coordinates":[-5.9102711678,37.290348053],"type":"Point"}
}