{
  "type": "Feature",
  "properties": {
    "iso:country":"ES",
    "sg:address":"Calle de Clavellina, 2",
    "sg:city":"Caceres",
    "sg:orig_category":"Parafarmacias",
    "sg:phone":"+34 927 21 67 07",
    "sg:postcode":"10003",
    "sg:province":"C\u00e1ceres",
    "wof:name":"Optitutto S.l.",
    "wof:placetype":"venue"
},
  "geometry": {"coordinates":[-6.2800865173,39.5237045288],"type":"Point"}
}