{
  "type": "Feature",
  "properties": {
    "iso:country":"ES",
    "sg:address":"Carrer de Nord, 115",
    "sg:city":"Terrassa",
    "sg:orig_category":"Aud\u00cdfonos",
    "sg:phone":"+34 937 31 92 48",
    "sg:postcode":"08221",
    "sg:province":"Barcelona",
    "wof:name":"Tortosa Lozano Maria Dolores",
    "wof:placetype":"venue"
},
  "geometry": {"coordinates":[2.0140891075,41.5695304871],"type":"Point"}
}