{
  "type": "Feature",
  "properties": {
    "iso:country":"ES",
    "sg:address":"Plaz Seis De Agosto, 9",
    "sg:city":"Gijon",
    "sg:classifiers":[
        {
            "category":"Casinos & Gambling",
            "type":"Entertainment"
        }
    ],
    "sg:phone":"+34 985 35 34 26",
    "sg:postcode":"33205",
    "sg:province":"Asturias",
    "sg:tags":[
        "locale",
        "de",
        "juego"
    ],
    "wof:name":"Elgame S. A.",
    "wof:placetype":"venue"
},
  "geometry": {"coordinates":[-5.6627259254,43.5393600464],"type":"Point"}
}