{
  "type": "Feature",
  "properties": {
    "addr:full":"Avda Suero De Qui\u00d1ones, 17 Le\u00f3n Le\u00f3n 24002",
    "addr:housenumber":"17",
    "addr:postcode":"24002",
    "addr:street":"Avda Suero De Quin\u0303Ones;Leo\u0301N",
    "iso:country":"ES",
    "sg:address":"Avda Suero De Qui\u00d1ones, 17",
    "sg:city":"Le\u00f3n",
    "sg:orig_category":"M\u00c9dicos: Ginecolog\u00cda Y Obstetricia",
    "sg:phone":"+34 987 22 62 56",
    "sg:postcode":"24002",
    "sg:province":"Le\u00f3n",
    "wof:name":"Rodriguez Dominguez Pedro",
    "wof:placetype":"venue"
},
  "geometry": {"coordinates":[-5.5773367882,42.6016426086],"type":"Point"}
}