{
  "type": "Feature",
  "properties": {
    "addr:full":"Avda Orense, 13 Marin Pontevedra 36900",
    "addr:housenumber":"13",
    "addr:postcode":"36900",
    "addr:street":"Avda Orense",
    "iso:country":"ES",
    "sg:address":"Avda Orense, 13",
    "sg:city":"Marin",
    "sg:orig_category":"Electrodom\u00c9sticos (al Por Menor)",
    "sg:phone":"+34 986 89 15 76",
    "sg:postcode":"36900",
    "sg:province":"Pontevedra",
    "wof:name":"Sueiro Castro Angel Rodrigo",
    "wof:placetype":"venue"
},
  "geometry": {"coordinates":[-8.6998672485,42.3929786682],"type":"Point"}
}