{
  "type": "Feature",
  "properties": {
    "addr:full":"Pallares A Santa Maria, Km. 0003,6 Pallares Badajoz 06907",
    "addr:postcode":"06907",
    "addr:street":"Maria Km. 0003,6",
    "iso:country":"ES",
    "sg:address":"Pallares A Santa Maria, Km. 0003,6",
    "sg:city":"Pallares",
    "sg:orig_category":"Agricultores, Agricultores",
    "sg:phone":"+34 924 14 90 31",
    "sg:postcode":"06907",
    "sg:province":"Badajoz",
    "wof:name":"Arroyo Delgado Jose Miguel",
    "wof:placetype":"venue"
},
  "geometry": {"coordinates":[-6.135119915,38.0855979919],"type":"Point"}
}