{
  "type": "Feature",
  "properties": {
    "iso:country":"ES",
    "sg:address":"Calle de Bernabe Soriano, 29",
    "sg:city":"Jaen",
    "sg:orig_category":"M\u00c9dicos: Estomatolog\u00cda",
    "sg:phone":"+34 953 23 83 52",
    "sg:postcode":"23001",
    "sg:province":"Ja\u00e9n",
    "wof:name":"Saiz-pardo Pinos Antonio Jesus",
    "wof:placetype":"venue"
},
  "geometry": {"coordinates":[-3.7873256207,37.7670211792],"type":"Point"}
}