{
  "type": "Feature",
  "properties": {
    "addr:full":"Calle de Manuel Maroto, 2 Madrid Madrid 28053",
    "addr:housenumber":"2",
    "addr:postcode":"28053",
    "addr:street":"Calle De Manuel Maroto",
    "iso:country":"ES",
    "sg:address":"Calle de Manuel Maroto, 2",
    "sg:city":"Madrid",
    "sg:orig_category":"Ortopedia General",
    "sg:phone":"+34 914 77 70 32",
    "sg:postcode":"28053",
    "sg:province":"Madrid",
    "wof:name":"Centro Ortopedico Artesano Cb",
    "wof:placetype":"venue"
},
  "geometry": {"coordinates":[-3.6678330898,40.3894195557],"type":"Point"}
}