{
  "type": "Feature",
  "properties": {
    "addr:full":"Carr Sant Josep, 42 Almussafes Valencia 46440",
    "addr:housenumber":"42",
    "addr:postcode":"46440",
    "addr:street":"Carr Sant Josep",
    "iso:country":"ES",
    "sg:address":"Carr Sant Josep, 42",
    "sg:city":"Almussafes",
    "sg:orig_category":"Electricidad: Material Y Suministros De Instalaci\u00d3n (fabricaci\u00d3n)",
    "sg:phone":"+34 961 78 20 02",
    "sg:postcode":"46440",
    "sg:province":"Valencia",
    "wof:name":"Gomez Calatayud Inocencio",
    "wof:placetype":"venue"
},
  "geometry": {"coordinates":[-0.4111360013,39.2925300598],"type":"Point"}
}