{
  "type": "Feature",
  "properties": {
    "iso:country":"ES",
    "sg:address":"Cra. Nacional Ii, Km. 0488,0",
    "sg:city":"Soses",
    "sg:orig_category":"Empresas De Trabajos P\u00dablicos",
    "sg:phone":"+34 973 79 71 33",
    "sg:postcode":"25181",
    "sg:province":"Lleida",
    "wof:name":"Vituc S.l.",
    "wof:placetype":"venue"
},
  "geometry": {"coordinates":[0.4596720934,41.5303535461],"type":"Point"}
}