{
  "type": "Feature",
  "properties": {
    "addr:full":"Ctra Prat, 30 Barcelona Barcelona 08038",
    "addr:housenumber":"30",
    "addr:postcode":"08038",
    "addr:street":"Ctra Prat",
    "iso:country":"ES",
    "sg:address":"Ctra Prat, 30",
    "sg:city":"Barcelona",
    "sg:orig_category":"Farmacias",
    "sg:phone":"+34 932 96 75 64",
    "sg:postcode":"08038",
    "sg:province":"Barcelona",
    "wof:name":"Valls Relats Gemma",
    "wof:placetype":"venue"
},
  "geometry": {"coordinates":[2.1356201172,41.3624687195],"type":"Point"}
}