{
  "type": "Feature",
  "properties": {
    "iso:country":"ES",
    "sg:address":"Avda Kilimon, 1",
    "sg:city":"Garagartza",
    "sg:orig_category":"Centros De Educaci\u00d3n Especial",
    "sg:phone":"+34 943 75 52 36",
    "sg:postcode":"20850",
    "sg:province":"Guip\u00f9zcoa",
    "wof:name":"Gobierno Vasco-eusko Jaurlaritza",
    "wof:placetype":"venue"
},
  "geometry": {"coordinates":[-2.3869309425,43.252696991],"type":"Point"}
}