{
  "type": "Feature",
  "properties": {
    "iso:country":"ES",
    "sg:address":"Calle de Goienkalea, 28",
    "sg:city":"Durango",
    "sg:orig_category":"Arquitectos",
    "sg:phone":"+34 946 81 27 00",
    "sg:postcode":"48200",
    "sg:province":"Vizcaya",
    "wof:name":"Perez Y Sanmiguel, C.b.",
    "wof:placetype":"venue"
},
  "geometry": {"coordinates":[-2.6311709881,43.1665611267],"type":"Point"}
}