{
  "type": "Feature",
  "properties": {
    "iso:country":"ES",
    "sg:address":"Pla\u00c7 Mercat, 2",
    "sg:city":"Catarroja",
    "sg:orig_category":"M\u00c9dicos: Oftalmolog\u00cda",
    "sg:phone":"+34 961 26 26 08",
    "sg:postcode":"46470",
    "sg:province":"Valencia",
    "wof:name":"Garcia Ibor Francisca",
    "wof:placetype":"venue"
},
  "geometry": {"coordinates":[-0.4019320011,39.4028892517],"type":"Point"}
}