{
  "type": "Feature",
  "properties": {
    "iso:country":"ES",
    "sg:address":"Plaz Verduras, 3",
    "sg:city":"Yuncler",
    "sg:orig_category":"Muebles Y Accesorios Para Cocinas Y Cuartos De Ba\u00d1o (al Por Menor)",
    "sg:phone":"+34 925 53 08 71",
    "sg:postcode":"45529",
    "sg:province":"Toledo",
    "wof:name":"Ruiz Orozco Pilar",
    "wof:placetype":"venue"
},
  "geometry": {"coordinates":[-3.902162075,40.0431785583],"type":"Point"}
}