{
  "type": "Feature",
  "properties": {
    "addr:full":"Calle de Santa Barbara, S/n Guardo Palencia 34880",
    "addr:housenumber":"/ n",
    "addr:postcode":"34880",
    "addr:street":"Calle De Santa Barbara S",
    "iso:country":"ES",
    "sg:address":"Calle de Santa Barbara, S/n",
    "sg:city":"Guardo",
    "sg:orig_category":"Arte, Cultura, Edici\u00d3n",
    "sg:phone":"+34 979 85 14 03",
    "sg:postcode":"34880",
    "sg:province":"Palencia",
    "wof:name":"Coral Mixta De Guardo",
    "wof:placetype":"venue"
},
  "geometry": {"coordinates":[-4.8448691368,42.7890586853],"type":"Point"}
}