{
  "type": "Feature",
  "properties": {
    "iso:country":"ES",
    "sg:address":"Ctra Torremayor, S/n",
    "sg:city":"Montijo",
    "sg:orig_category":"Agricultura: Abastecimiento Y Cosechado (negocio)",
    "sg:phone":"+34 924 45 56 71",
    "sg:postcode":"06480",
    "sg:province":"Badajoz",
    "wof:name":"Agropecuaria Jerez Gutierrez C.b.",
    "wof:placetype":"venue"
},
  "geometry": {"coordinates":[-6.6022987366,38.9090538025],"type":"Point"}
}