{
  "type": "Feature",
  "properties": {
    "addr:full":"Calle de Getaria, 23 Donostia-san Sebastian Guip\u00f9zcoa 20005",
    "addr:housenumber":"23",
    "addr:postcode":"20005",
    "addr:street":"Calle De Getaria",
    "iso:country":"ES",
    "sg:address":"Calle de Getaria, 23",
    "sg:city":"Donostia-san Sebastian",
    "sg:orig_category":"Bisuter\u00cda, Joyer\u00cda, Relojer\u00cda (al Por Menor)",
    "sg:phone":"+34 943 42 26 80",
    "sg:postcode":"20005",
    "sg:province":"Guip\u00f9zcoa",
    "wof:name":"Bestgold S.l.",
    "wof:placetype":"venue"
},
  "geometry": {"coordinates":[-1.9801410437,43.3176879883],"type":"Point"}
}