{
  "type": "Feature",
  "properties": {
    "addr:full":"Av Cubelles, 56 Vilanova I La Geltru Barcelona 08800",
    "addr:housenumber":"56",
    "addr:postcode":"08800",
    "addr:street":"Av Cubelles",
    "iso:country":"ES",
    "sg:address":"Av Cubelles, 56",
    "sg:city":"Vilanova I La Geltru",
    "sg:orig_category":"Empresarios",
    "sg:phone":"+34 938 15 21 11",
    "sg:postcode":"08800",
    "sg:province":"Barcelona",
    "wof:name":"Jacas Hernandez Teresa",
    "wof:placetype":"venue"
},
  "geometry": {"coordinates":[1.7168049812,41.2188682556],"type":"Point"}
}