{
  "type": "Feature",
  "properties": {
    "addr:full":"Plaz Archiduque Carlos, 5 Denia Alicante 03700",
    "addr:housenumber":"5",
    "addr:postcode":"03700",
    "addr:street":"Plaz Archiduque Carlos",
    "iso:country":"ES",
    "sg:address":"Plaz Archiduque Carlos, 5",
    "sg:city":"Denia",
    "sg:orig_category":"Caf\u00c9s, Bares, Cervecer\u00cdas",
    "sg:phone":"+34 965 78 00 84",
    "sg:postcode":"03700",
    "sg:province":"Alicante",
    "wof:name":"Salort Bisquert Francisca",
    "wof:placetype":"venue"
},
  "geometry": {"coordinates":[0.1114400029,38.8428153992],"type":"Point"}
}