{
  "type": "Feature",
  "properties": {
    "iso:country":"ES",
    "sg:address":"Guajara, S/n",
    "sg:city":"San Cristobal De La Laguna",
    "sg:orig_category":"Peluqueros: De Se\u00d1oras",
    "sg:phone":"+34 922 82 03 40",
    "sg:postcode":"38205",
    "sg:province":"Santa Cruz De Tenerife",
    "wof:name":"Cabrera Darias Jose",
    "wof:placetype":"venue"
},
  "geometry": {"coordinates":[-16.298746109,28.4750785828],"type":"Point"}
}