{
  "type": "Feature",
  "properties": {
    "iso:country":"ES",
    "sg:address":"Nafarroa Etorbidea, 1",
    "sg:city":"Beasain",
    "sg:orig_category":"Ense\u00d1anza: Idiomas",
    "sg:phone":"+34 943 16 17 46",
    "sg:postcode":"20200",
    "sg:province":"Guip\u00f9zcoa",
    "wof:name":"Do's Formacion S.l.",
    "wof:placetype":"venue"
},
  "geometry": {"coordinates":[-2.2009029388,43.0467338562],"type":"Point"}
}