{
  "type": "Feature",
  "properties": {
    "iso:country":"ES",
    "sg:address":"Pol Ind Ceramica, 5",
    "sg:city":"Benejuzar",
    "sg:orig_category":"Construcciones Met\u00c1licas",
    "sg:phone":"+34 966 77 70 64",
    "sg:postcode":"03390",
    "sg:province":"Alicante",
    "wof:name":"Andreu Martinez Jose Eduardo",
    "wof:placetype":"venue"
},
  "geometry": {"coordinates":[-0.8317813277,38.0681495667],"type":"Point"}
}