{
  "type": "Feature",
  "properties": {
    "iso:country":"ES",
    "sg:address":"Pase Huertas (las), 55",
    "sg:city":"Almansa",
    "sg:orig_category":"Freidur\u00cdas: Equipos Y Suministros",
    "sg:phone":"+34 967 34 40 33",
    "sg:postcode":"02640",
    "sg:province":"Albacete",
    "wof:name":"Arnedo Contreras Jose",
    "wof:placetype":"venue"
},
  "geometry": {"coordinates":[-1.0958522558,38.8728027344],"type":"Point"}
}