{
  "type": "Feature",
  "properties": {
    "iso:country":"ES",
    "sg:address":"Calle de Javier Sanz, 7",
    "sg:city":"Almeria",
    "sg:orig_category":"Art\u00cdculos De Limpieza Y De Cocina (fabricaci\u00d3n, Al Por Mayor)",
    "sg:phone":"+34 950 25 84 12",
    "sg:postcode":"04004",
    "sg:province":"Almer\u00eda",
    "wof:name":"Siglhogar",
    "wof:placetype":"venue"
},
  "geometry": {"coordinates":[-2.4609699249,36.8390312195],"type":"Point"}
}