{
  "type": "Feature",
  "properties": {
    "addr:full":"Avda Jeronimo Roure, S/n Puerto Valencia 46520",
    "addr:housenumber":"s / n",
    "addr:postcode":"46520",
    "addr:street":"Avda Jeronimo Roure",
    "iso:country":"ES",
    "sg:address":"Avda Jeronimo Roure, S/n",
    "sg:city":"Puerto",
    "sg:orig_category":"Producci\u00d3n De Abonos Y De Fertilizantes",
    "sg:phone":"+34 962 69 10 90",
    "sg:postcode":"46520",
    "sg:province":"Valencia",
    "sg:website":"www.servalesa.es",
    "wof:name":"Servalesa S.l.",
    "wof:placetype":"venue"
},
  "geometry": {"coordinates":[-0.2249089926,39.6590118408],"type":"Point"}
}