{
  "type": "Feature",
  "properties": {
    "iso:country":"ES",
    "sg:address":"Avda Iparralde, 4",
    "sg:city":"Irun",
    "sg:orig_category":"Inform\u00c1tica (estudios, Servicios, Asesor\u00cda, Formaci\u00d3n)",
    "sg:phone":"+34 943 11 66 00",
    "sg:postcode":"20302",
    "sg:province":"Guip\u00f9zcoa",
    "wof:name":"Scheifler Telecom S.l. Unipersonal",
    "wof:placetype":"venue"
},
  "geometry": {"coordinates":[-1.790323019,43.3400306702],"type":"Point"}
}