{
  "type": "Feature",
  "properties": {
    "addr:full":"Pase Larratxo De, 24 Donostia-san Sebastian Guip\u00f9zcoa 20017",
    "addr:housenumber":"24",
    "addr:postcode":"20017",
    "iso:country":"ES",
    "sg:address":"Pase Larratxo De, 24",
    "sg:city":"Donostia-san Sebastian",
    "sg:orig_category":"Molduras, Junquillos, Listones Y Molduras Perforadas",
    "sg:phone":"+34 943 39 59 74",
    "sg:postcode":"20017",
    "sg:province":"Guip\u00f9zcoa",
    "wof:name":"Hernandez Gimeno Gabriel",
    "wof:placetype":"venue"
},
  "geometry": {"coordinates":[-1.939422965,43.3134651184],"type":"Point"}
}