{
  "type": "Feature",
  "properties": {
    "iso:country":"ES",
    "sg:address":"Carr Antoni Lazaro, 75",
    "sg:city":"Benifairo De Les Valls",
    "sg:orig_category":"Comercio, Reparaci\u00d3n De Bicicletas, De Motocicletas, De Accesorios",
    "sg:phone":"+34 962 60 02 30",
    "sg:postcode":"46511",
    "sg:province":"Valencia",
    "wof:name":"Cantin Inglada Francisca",
    "wof:placetype":"venue"
},
  "geometry": {"coordinates":[-0.2697739899,39.7283744812],"type":"Point"}
}