{
  "type": "Feature",
  "properties": {
    "iso:country":"ES",
    "sg:address":"Carrer de Doctor Fleming, 4",
    "sg:city":"Crevillent",
    "sg:orig_category":"Cerrajer\u00cda, Ferrallista",
    "sg:phone":"+34 965 40 10 75",
    "sg:postcode":"03330",
    "sg:province":"Alicante",
    "wof:name":"Belen Asencio Antonio",
    "wof:placetype":"venue"
},
  "geometry": {"coordinates":[-0.8128319979,38.2430534363],"type":"Point"}
}