{
  "type": "Feature",
  "properties": {
    "addr:full":"Calle de Sargento Provisional, S/n Valladolid Valladolid 47013",
    "addr:housenumber":"s / n",
    "addr:postcode":"47013",
    "addr:street":"Calle De Sargento Provisional",
    "iso:country":"ES",
    "sg:address":"Calle de Sargento Provisional, S/n",
    "sg:city":"Valladolid",
    "sg:orig_category":"Sanatorios M\u00c9dico",
    "sg:phone":"+34 983 22 67 67",
    "sg:postcode":"47013",
    "sg:province":"Valladolid",
    "wof:name":"Gerencia De Atencion Primaria Area Este Valladolid",
    "wof:placetype":"venue"
},
  "geometry": {"coordinates":[-4.7271590233,41.6313552856],"type":"Point"}
}