{
  "type": "Feature",
  "properties": {
    "addr:full":"Ctra Madrid, Km. 0431,0 Miranda Murcia 30319",
    "addr:postcode":"30319",
    "addr:street":"Ctra Madrid Km. 0431,0",
    "iso:country":"ES",
    "sg:address":"Ctra Madrid, Km. 0431,0",
    "sg:city":"Miranda",
    "sg:orig_category":"Motocicletas (agentes, Concesionarios)",
    "sg:phone":"+34 968 31 01 18",
    "sg:postcode":"30319",
    "sg:province":"Murcia",
    "wof:name":"Nu\u00f1ez Hernandez Fernando",
    "wof:placetype":"venue"
},
  "geometry": {"coordinates":[-1.0148609877,37.6664352417],"type":"Point"}
}