{
  "type": "Feature",
  "properties": {
    "iso:country":"ES",
    "sg:address":"Zuloagas-tarren Kalea, 3",
    "sg:city":"Eibar",
    "sg:orig_category":"Ingeniero",
    "sg:phone":"+34 943 20 26 90",
    "sg:postcode":"20600",
    "sg:province":"Guip\u00f9zcoa",
    "wof:name":"Ocamica Elorza Jose Maria",
    "wof:placetype":"venue"
},
  "geometry": {"coordinates":[-2.470459938,43.1856918335],"type":"Point"}
}