{
  "type": "Feature",
  "properties": {
    "iso:country":"ES",
    "sg:address":"Calle de Santa Ana, 27",
    "sg:city":"Castuera",
    "sg:orig_category":"Centros De Coordinaci\u00d3n",
    "sg:phone":"+34 924 76 08 82",
    "sg:postcode":"06420",
    "sg:province":"Badajoz",
    "wof:name":"Fernandez Gallego Sofia",
    "wof:placetype":"venue"
},
  "geometry": {"coordinates":[-5.5448918343,38.7232971191],"type":"Point"}
}