{
  "type": "Feature",
  "properties": {
    "iso:country":"ES",
    "sg:address":"Calle de Sanchez Pacheco, 78",
    "sg:city":"Madrid",
    "sg:orig_category":"Ropa Para Se\u00d1oras Y Caballeros (al Por Menor)",
    "sg:phone":"+34 915 19 59 52",
    "sg:postcode":"28002",
    "sg:province":"Madrid",
    "wof:name":"Raelo Textil S.l.",
    "wof:placetype":"venue"
},
  "geometry": {"coordinates":[-3.669508934,40.4482536316],"type":"Point"}
}