{
  "type": "Feature",
  "properties": {
    "iso:country":"ES",
    "sg:address":"Calle de Capitan Nolla, 4",
    "sg:city":"Castronu\u00f1o",
    "sg:orig_category":"Venta, Instalaci\u00d3n De Cocinas",
    "sg:phone":"+34 983 86 61 76",
    "sg:postcode":"47520",
    "sg:province":"Valladolid",
    "wof:name":"Alvarez Rico Amparo",
    "wof:placetype":"venue"
},
  "geometry": {"coordinates":[-5.2635121346,41.3898239136],"type":"Point"}
}