{
  "type": "Feature",
  "properties": {
    "iso:country":"ES",
    "sg:address":"Calle de Sierra Nevada, 21",
    "sg:city":"Atarfe",
    "sg:orig_category":"Alimentaci\u00d3n General (al Por Menor)",
    "sg:phone":"+34 958 43 74 67",
    "sg:postcode":"18230",
    "sg:province":"Granada",
    "wof:name":"Rodriguez Verdejo Francisco",
    "wof:placetype":"venue"
},
  "geometry": {"coordinates":[-3.6873011589,37.2210388184],"type":"Point"}
}