{
  "type": "Feature",
  "properties": {
    "addr:full":"Calle de Catalu\u00d1a, 8 Gijon Asturias 33208",
    "addr:housenumber":"8",
    "addr:postcode":"33208",
    "addr:street":"Calle De Catalun\u0303A",
    "iso:country":"ES",
    "sg:address":"Calle de Catalu\u00d1a, 8",
    "sg:city":"Gijon",
    "sg:orig_category":"Electrodom\u00c9sticos (al Por Menor)",
    "sg:phone":"+34 985 14 40 39",
    "sg:postcode":"33208",
    "sg:province":"Asturias",
    "wof:name":"Alvarez Alvarez Alberto",
    "wof:placetype":"venue"
},
  "geometry": {"coordinates":[-5.6715955734,43.5297470093],"type":"Point"}
}