{
  "type": "Feature",
  "properties": {
    "iso:country":"ES",
    "sg:address":"Carrer de Argenters, 2",
    "sg:city":"Palma",
    "sg:orig_category":"Bisuter\u00cda, Joyer\u00cda, Relojer\u00cda (al Por Menor)",
    "sg:phone":"+34 971 71 34 33",
    "sg:postcode":"07001",
    "sg:province":"Islas Baleares",
    "wof:name":"Criado Picazo Feliciano",
    "wof:placetype":"venue"
},
  "geometry": {"coordinates":[2.6515209675,39.5704345703],"type":"Point"}
}