{
  "type": "Feature",
  "properties": {
    "addr:full":"Avda Diputacion Provincial, 40 Calanda Teruel 44570",
    "addr:postcode":"44570",
    "addr:street":"Avda Diputacion Provincial 40",
    "iso:country":"ES",
    "sg:address":"Avda Diputacion Provincial, 40",
    "sg:city":"Calanda",
    "sg:orig_category":"Peluqueros: De Se\u00d1oras",
    "sg:phone":"+34 978 84 70 29",
    "sg:postcode":"44570",
    "sg:province":"Teruel",
    "wof:name":"Rodenas Ca\u00f1ada Patricia",
    "wof:placetype":"venue"
},
  "geometry": {"coordinates":[-0.2251030058,40.9400367737],"type":"Point"}
}