{
  "type": "Feature",
  "properties": {
    "iso:country":"ES",
    "sg:address":"Constitucion, 1",
    "sg:city":"Castelseras",
    "sg:orig_category":"Alimentaci\u00d3n General (al Por Menor)",
    "sg:phone":"+34 978 87 70 53",
    "sg:postcode":"44630",
    "sg:province":"Teruel",
    "wof:name":"Carceller Serrano Miguel",
    "wof:placetype":"venue"
},
  "geometry": {"coordinates":[-0.147014007,40.9825706482],"type":"Point"}
}