{
  "type": "Feature",
  "properties": {
    "addr:full":"Calle de Mar De Escocia, 20 Meloneras Las Palmas 35100",
    "addr:housenumber":"20",
    "addr:postcode":"35100",
    "addr:street":"Calle De Mar De Escocia;Las Palmas",
    "iso:country":"ES",
    "sg:address":"Calle de Mar De Escocia, 20",
    "sg:city":"Meloneras",
    "sg:orig_category":"Molduras, Junquillos, Listones Y Molduras Perforadas",
    "sg:phone":"+34 928 14 30 34",
    "sg:postcode":"35100",
    "sg:province":"Las Palmas",
    "wof:name":"Jimenez Mendoza Manuel De Los Reyes",
    "wof:placetype":"venue"
},
  "geometry": {"coordinates":[-15.5971784592,27.7599411011],"type":"Point"}
}