{
  "type": "Feature",
  "properties": {
    "addr:full":"Avda Aguirre Lehendakari, 11 Bilbao Vizcaya 48014",
    "addr:housenumber":"11",
    "addr:postcode":"48014",
    "addr:street":"Avda Aguirre Lehendakari",
    "iso:country":"ES",
    "sg:address":"Avda Aguirre Lehendakari, 11",
    "sg:city":"Bilbao",
    "sg:orig_category":"Promotores Constructores",
    "sg:phone":"+34 944 35 51 30",
    "sg:postcode":"48014",
    "sg:province":"Vizcaya",
    "wof:name":"Centro Informativo De La Construccion",
    "wof:placetype":"venue"
},
  "geometry": {"coordinates":[-2.9460270405,43.2717628479],"type":"Point"}
}