{
  "type": "Feature",
  "properties": {
    "addr:full":"Calle de Escritor Herrera Santaolalla, 20 Churriana M\u00e1laga 29140",
    "addr:housenumber":"20",
    "addr:postcode":"29140",
    "addr:street":"Calle De Escritor Herrera Santaolalla",
    "iso:country":"ES",
    "sg:address":"Calle de Escritor Herrera Santaolalla, 20",
    "sg:city":"Churriana",
    "sg:orig_category":"Contenedores (mercanc\u00cdas)",
    "sg:phone":"+34 952 43 70 47",
    "sg:postcode":"29140",
    "sg:province":"M\u00e1laga",
    "wof:name":"Nevado Jimenez Antonio",
    "wof:placetype":"venue"
},
  "geometry": {"coordinates":[-4.4950041771,36.6606140137],"type":"Point"}
}