{
  "type": "Feature",
  "properties": {
    "addr:full":"Calle de Marques De Murrieta, 28 Logro\u00f1o La Rioja 26005",
    "addr:housenumber":"28",
    "addr:postcode":"26005",
    "addr:street":"Calle De Marques De Murrieta;Rioja",
    "iso:country":"ES",
    "sg:address":"Calle de Marques De Murrieta, 28",
    "sg:city":"Logro\u00f1o",
    "sg:orig_category":"Cajas De Ahorro",
    "sg:phone":"+34 941 21 04 72",
    "sg:postcode":"26005",
    "sg:province":"La Rioja",
    "wof:name":"Caja De Ahorros De La Rioja",
    "wof:placetype":"venue"
},
  "geometry": {"coordinates":[-2.4551899433,42.4652290344],"type":"Point"}
}