{
  "type": "Feature",
  "properties": {
    "addr:full":"C/ Conrado Del Campo, 137 Elche Alicante 03204",
    "addr:housenumber":"137",
    "addr:postcode":"03204",
    "addr:street":"C / Conrado Del Campo",
    "iso:country":"ES",
    "sg:address":"C/ Conrado Del Campo, 137",
    "sg:city":"Elche",
    "sg:orig_category":"Electricidad, Electr\u00d3nica: Material Y Suministros (al Por Mayor)",
    "sg:phone":"+34 965 68 02 79",
    "sg:postcode":"03204",
    "sg:province":"Alicante",
    "wof:name":"Codere Gandia S. A.",
    "wof:placetype":"venue"
},
  "geometry": {"coordinates":[-0.7043150067,38.2554016113],"type":"Point"}
}