{
  "type": "Feature",
  "properties": {
    "addr:full":"Calle de Leon Y Castillo, 3 Ingenio Las Palmas 35250",
    "addr:housenumber":"3",
    "addr:postcode":"35250",
    "addr:street":"Calle De Leon Y Castillo",
    "iso:country":"ES",
    "sg:address":"Calle de Leon Y Castillo, 3",
    "sg:city":"Ingenio",
    "sg:orig_category":"Cajas De Ahorro",
    "sg:phone":"+34 928 78 92 07",
    "sg:postcode":"35250",
    "sg:province":"Las Palmas",
    "wof:name":"Caixa D'estalvis I Pensions De Barcelona",
    "wof:placetype":"venue"
},
  "geometry": {"coordinates":[-15.4372167587,27.9195365906],"type":"Point"}
}