{
  "type": "Feature",
  "properties": {
    "addr:full":"Carrer de Holanda, 5 Terrassa Barcelona 08228",
    "addr:housenumber":"5",
    "addr:postcode":"08228",
    "addr:street":"Carrer De Holanda",
    "iso:country":"ES",
    "sg:address":"Carrer de Holanda, 5",
    "sg:city":"Terrassa",
    "sg:orig_category":"Papeler\u00cdas, Librer\u00cdas",
    "sg:phone":"+34 937 85 82 70",
    "sg:postcode":"08228",
    "sg:province":"Barcelona",
    "wof:name":"Aljama Martinez Elisabeth",
    "wof:placetype":"venue"
},
  "geometry": {"coordinates":[2.0399098396,41.5357437134],"type":"Point"}
}