{
  "type": "Feature",
  "properties": {
    "iso:country":"ES",
    "sg:address":"Carrer de Cirerer, 16",
    "sg:city":"Palma",
    "sg:orig_category":"Contenedores (mercanc\u00cdas)",
    "sg:phone":"+34 971 47 93 02",
    "sg:postcode":"07008",
    "sg:province":"Islas Baleares",
    "wof:name":"Pons Arbona Juana Maria",
    "wof:placetype":"venue"
},
  "geometry": {"coordinates":[2.6755468845,39.5860900879],"type":"Point"}
}