{
  "type": "Feature",
  "properties": {
    "addr:full":"Calle de Consulado De Bilbao, 9 Astrabudua Vizcaya 48950",
    "addr:housenumber":"9",
    "addr:postcode":"48950",
    "addr:street":"Calle De Consulado;Bilbao",
    "iso:country":"ES",
    "sg:address":"Calle de Consulado De Bilbao, 9",
    "sg:city":"Astrabudua",
    "sg:classifiers":[
        {
            "category":"Autos & Motor Vehicles",
            "subcategory":"Automobile Sales",
            "type":"Retail Goods"
        }
    ],
    "sg:phone":"+34 944 67 54 98",
    "sg:postcode":"48950",
    "sg:province":"Vizcaya",
    "wof:name":"Fernandez Gonzalez Rosario",
    "wof:placetype":"venue"
},
  "geometry": {"coordinates":[-2.9839258194,43.3172492981],"type":"Point"}
}