{
  "type": "Feature",
  "properties": {
    "addr:full":"Rua Campo Da Estrela (do), 5 Santiago De Compostela La Coru\u00f1a 15705",
    "addr:housenumber":"5",
    "addr:postcode":"15705",
    "addr:street":"Rua Campo Da Estrela Do;Corun\u0303A",
    "iso:country":"ES",
    "sg:address":"Rua Campo Da Estrela (do), 5",
    "sg:city":"Santiago De Compostela",
    "sg:orig_category":"Abogados",
    "sg:phone":"+34 981 57 60 43",
    "sg:postcode":"15705",
    "sg:province":"La Coru\u00f1a",
    "wof:name":"Alberto Torreiro Y Abogados Asociados S.l.",
    "wof:placetype":"venue"
},
  "geometry": {"coordinates":[-8.5464687347,42.8768997192],"type":"Point"}
}