{
  "type": "Feature",
  "properties": {
    "iso:country":"ES",
    "sg:address":"Plaza Santa Teresa, 5",
    "sg:city":"Barakaldo",
    "sg:orig_category":"Institutos De Belleza",
    "sg:phone":"+34 944 37 24 99",
    "sg:postcode":"48901",
    "sg:province":"Vizcaya",
    "wof:name":"Raquel Exposito-felisa Molinero C.b",
    "wof:placetype":"venue"
},
  "geometry": {"coordinates":[-2.9934771061,43.2996101379],"type":"Point"}
}