{
  "type": "Feature",
  "properties": {
    "iso:country":"ES",
    "sg:address":"Ctra Utrera-carmona, Km. 0700,0",
    "sg:city":"Utrera",
    "sg:orig_category":"Confiter\u00cda, Galletas Y Pastas, Chocolater\u00cda (al Por Mayor)",
    "sg:phone":"+34 955 86 45 66",
    "sg:postcode":"41710",
    "sg:province":"Sevilla",
    "wof:name":"Industria Pastelera Utrerana S.l.",
    "wof:placetype":"venue"
},
  "geometry": {"coordinates":[-5.7859487534,37.1930503845],"type":"Point"}
}