{
  "type": "Feature",
  "properties": {
    "iso:country":"ES",
    "sg:address":"Calle de Dionisio Guardiola, 37",
    "sg:city":"Albacete",
    "sg:orig_category":"Agencias De Viajes",
    "sg:phone":"+34 967 23 96 30",
    "sg:postcode":"02003",
    "sg:province":"Albacete",
    "sg:website":"www.viajesiberia.com",
    "wof:name":"Viajes Iberia S.a.",
    "wof:placetype":"venue"
},
  "geometry": {"coordinates":[-1.8584109545,38.9922370911],"type":"Point"}
}