{
  "type": "Feature",
  "properties": {
    "addr:full":"Carrer de Arago, 88 Palma Islas Baleares 07008",
    "addr:housenumber":"88",
    "addr:postcode":"07008",
    "addr:street":"Carrer De Arago",
    "iso:country":"ES",
    "sg:address":"Carrer de Arago, 88",
    "sg:city":"Palma",
    "sg:orig_category":"Estancos",
    "sg:phone":"+34 971 27 10 43",
    "sg:postcode":"07008",
    "sg:province":"Islas Baleares",
    "wof:name":"Frontera Lozano Juan",
    "wof:placetype":"venue"
},
  "geometry": {"coordinates":[2.6641099453,39.5794792175],"type":"Point"}
}