{
  "type": "Feature",
  "properties": {
    "addr:full":"Piscina, 3 Mollina M\u00e1laga 29532",
    "addr:postcode":"29532",
    "addr:street":"Ma\u0301Laga",
    "iso:country":"ES",
    "sg:address":"Piscina, 3",
    "sg:city":"Mollina",
    "sg:orig_category":"Ense\u00d1anza, Formaci\u00d3n Profesional: Aprendizaje",
    "sg:phone":"+34 952 74 16 50",
    "sg:postcode":"29532",
    "sg:province":"M\u00e1laga",
    "sg:website":"www.antequeraracom.com",
    "wof:name":"Grupo De Accion Y Desarrollo Local De La Comarca De Antequera",
    "wof:placetype":"venue"
},
  "geometry": {"coordinates":[-4.6613688469,37.1246490479],"type":"Point"}
}