{
  "type": "Feature",
  "properties": {
    "iso:country":"ES",
    "sg:address":"G.v. Puig De Teix, 10",
    "sg:city":"Santa Pon\u00c7a",
    "sg:orig_category":"Bares, Piano",
    "sg:phone":"+34 971 69 13 70",
    "sg:postcode":"07180",
    "sg:province":"Islas Baleares",
    "wof:name":"Cybermania-aris S.l.",
    "wof:placetype":"venue"
},
  "geometry": {"coordinates":[2.4985899925,39.5253143311],"type":"Point"}
}