{
  "type": "Feature",
  "properties": {
    "iso:country":"ES",
    "sg:address":"Calle de Vasco Nu\u00d1ez, 57",
    "sg:city":"Monesterio",
    "sg:orig_category":"Electrodom\u00c9sticos (al Por Menor)",
    "sg:phone":"+34 924 51 73 27",
    "sg:postcode":"06260",
    "sg:province":"Badajoz",
    "wof:name":"Gonzalez Cantillo Santiago",
    "wof:placetype":"venue"
},
  "geometry": {"coordinates":[-6.2759189606,38.0878295898],"type":"Point"}
}