{
  "type": "Feature",
  "properties": {
    "addr:full":"Plaz Padron, 15 Madrid Madrid 28029",
    "addr:housenumber":"15",
    "addr:postcode":"madrid;28029",
    "addr:street":"Plaz Padron",
    "iso:country":"ES",
    "sg:address":"Plaz Padron, 15",
    "sg:city":"Madrid",
    "sg:orig_category":"Venta, Instalaci\u00d3n De Calefacci\u00d3n",
    "sg:phone":"+34 913 78 43 11",
    "sg:postcode":"28029",
    "sg:province":"Madrid",
    "wof:name":"Requena Azcarate Santiago",
    "wof:placetype":"venue"
},
  "geometry": {"coordinates":[-3.7062180042,40.4772033691],"type":"Point"}
}