{
  "type": "Feature",
  "properties": {
    "iso:country":"ES",
    "sg:address":"Avda Bilbao (de), 48",
    "sg:city":"Muriedas",
    "sg:orig_category":"Producci\u00d3n De Huevos",
    "sg:phone":"+34 942 25 25 25",
    "sg:postcode":"39600",
    "sg:province":"Cantabria",
    "wof:name":"Alimentos Del Cantabrico S.a.l.",
    "wof:placetype":"venue"
},
  "geometry": {"coordinates":[-3.8459880352,43.4187011719],"type":"Point"}
}