{
  "type": "Feature",
  "properties": {
    "iso:country":"ES",
    "sg:address":"Avda Aurora, 25",
    "sg:city":"Malaga",
    "sg:orig_category":"Ropa Para Ni\u00d1os (al Por Menor)",
    "sg:phone":"+34 952 36 97 90",
    "sg:postcode":"29002",
    "sg:province":"M\u00e1laga",
    "sg:website":"www.neckandneck.com",
    "wof:name":"Mavestitoni S.l.",
    "wof:placetype":"venue"
},
  "geometry": {"coordinates":[-4.4318518639,36.7160987854],"type":"Point"}
}