{
  "type": "Feature",
  "properties": {
    "iso:country":"ES",
    "sg:address":"Ramon Otero Pedrayo-viloria, S/n",
    "sg:city":"Barco De Valdeorras",
    "sg:orig_category":"Ense\u00d1anza, Formaci\u00d3n Profesional: Aprendizaje",
    "sg:phone":"+34 988 32 09 45",
    "sg:postcode":"32315",
    "sg:province":"Ourense",
    "wof:name":"Xunta De Galicia",
    "wof:placetype":"venue"
},
  "geometry": {"coordinates":[-7.0159082413,42.4016876221],"type":"Point"}
}