{
  "type": "Feature",
  "properties": {
    "addr:full":"Carrer de Joan Prim, 77 Premia Mar Barcelona 08330",
    "addr:housenumber":"77",
    "addr:postcode":"08330",
    "addr:street":"Carrer De Joan Prim",
    "iso:country":"ES",
    "sg:address":"Carrer de Joan Prim, 77",
    "sg:city":"Premia Mar",
    "sg:orig_category":"Librer\u00cdas",
    "sg:phone":"+34 937 51 34 49",
    "sg:postcode":"08330",
    "sg:province":"Barcelona",
    "wof:name":"Lobera Gil Luis",
    "wof:placetype":"venue"
},
  "geometry": {"coordinates":[2.357503891,41.4934806824],"type":"Point"}
}