{
  "type": "Feature",
  "properties": {
    "iso:country":"ES",
    "sg:address":"Ctra. Iberduero, S/n",
    "sg:city":"Manzaneda",
    "sg:orig_category":"Farmacias",
    "sg:phone":"+34 988 33 30 32",
    "sg:postcode":"32781",
    "sg:province":"Ourense",
    "wof:name":"Do Pazo Fernandez Luis Manuel",
    "wof:placetype":"venue"
},
  "geometry": {"coordinates":[-7.2340378761,42.3097381592],"type":"Point"}
}