{
  "type": "Feature",
  "properties": {
    "iso:country":"ES",
    "sg:address":"Carr Bailen, 35",
    "sg:city":"Vilanova I La Geltru",
    "sg:orig_category":"Agencias Y Agentes Comerciales, Representantes",
    "sg:phone":"+34 938 93 96 09",
    "sg:postcode":"08800",
    "sg:province":"Barcelona",
    "wof:name":"Ayats Demestres Juan Ignacio",
    "wof:placetype":"venue"
},
  "geometry": {"coordinates":[1.7150348425,41.2241172791],"type":"Point"}
}