{
  "type": "Feature",
  "properties": {
    "addr:full":"Calle de Quimicas, S/n Alcorcon Madrid 28922",
    "addr:housenumber":"s",
    "addr:postcode":"28922",
    "addr:street":"Calle De Quimicas;/ N Alcorcon",
    "iso:country":"ES",
    "sg:address":"Calle de Quimicas, S/n",
    "sg:city":"Alcorcon",
    "sg:orig_category":"Centros Empresariales",
    "sg:phone":"+34 916 41 22 71",
    "sg:postcode":"28922",
    "sg:province":"Madrid",
    "wof:name":"Asociacion De Empresariosde Poligonos Industriales De Urtinsa",
    "wof:placetype":"venue"
},
  "geometry": {"coordinates":[-3.8157057762,40.3355484009],"type":"Point"}
}