{
  "type": "Feature",
  "properties": {
    "iso:country":"ES",
    "sg:address":"Camino Moli, S/n",
    "sg:city":"Borriol",
    "sg:orig_category":"Negocio De Madera",
    "sg:phone":"+34 964 32 10 43",
    "sg:postcode":"12190",
    "sg:province":"Castell\u00f3n",
    "wof:name":"Palets Rubio C.b.",
    "wof:placetype":"venue"
},
  "geometry": {"coordinates":[-0.0713289976,40.0401916504],"type":"Point"}
}