{
  "type": "Feature",
  "properties": {
    "addr:full":"Calle de Francia, S/n Alcala Henares Madrid 28802",
    "addr:housenumber":"s / n",
    "addr:postcode":"28802",
    "addr:street":"Calle De Francia",
    "iso:country":"ES",
    "sg:address":"Calle de Francia, S/n",
    "sg:city":"Alcala Henares",
    "sg:orig_category":"Limpieza Industrial",
    "sg:phone":"+34 918 82 70 65",
    "sg:postcode":"28802",
    "sg:province":"Madrid",
    "wof:name":"Lavanderia Industrial Alcala S.a.l.",
    "wof:placetype":"venue"
},
  "geometry": {"coordinates":[-3.3876540661,40.479839325],"type":"Point"}
}