{
  "type": "Feature",
  "properties": {
    "addr:full":"Calle de Baja, 130 Isla Cristina Huelva 21410",
    "addr:housenumber":"130",
    "addr:postcode":"21410",
    "addr:street":"Calle De Baja",
    "iso:country":"ES",
    "sg:address":"Calle de Baja, 130",
    "sg:city":"Isla Cristina",
    "sg:orig_category":"Cristaler\u00cdas",
    "sg:phone":"+34 959 33 19 00",
    "sg:postcode":"21410",
    "sg:province":"Huelva",
    "wof:name":"Sousa Garrido Antonio",
    "wof:placetype":"venue"
},
  "geometry": {"coordinates":[-7.3247880936,37.2017402649],"type":"Point"}
}