{
  "type": "Feature",
  "properties": {
    "addr:full":"Urbanitzacio Agusti Torras, S/n Cornella Terri Girona 17844",
    "addr:housenumber":"s / n",
    "addr:postcode":"17844",
    "addr:street":"Torras",
    "iso:country":"ES",
    "sg:address":"Urbanitzacio Agusti Torras, S/n",
    "sg:city":"Cornella Terri",
    "sg:orig_category":"Electromec\u00c1nica",
    "sg:phone":"+34 972 59 46 14",
    "sg:postcode":"17844",
    "sg:province":"Girona",
    "wof:name":"Bobinatges Arme S.l.",
    "wof:placetype":"venue"
},
  "geometry": {"coordinates":[2.8163619041,42.0891227722],"type":"Point"}
}