{
  "type": "Feature",
  "properties": {
    "addr:full":"Calle de Ca\u00d1ada, 57 Torrejon Ardoz Madrid 28850",
    "addr:housenumber":"57",
    "addr:postcode":"28850",
    "addr:street":"Calle De Can\u0303Ada",
    "iso:country":"ES",
    "sg:address":"Calle de Ca\u00d1ada, 57",
    "sg:city":"Torrejon Ardoz",
    "sg:orig_category":"Artes Gr\u00c1ficas, Artes Pl\u00c1sticas: Material Y Suministros (al Por Menor)",
    "sg:phone":"+34 916 76 62 62",
    "sg:postcode":"28850",
    "sg:province":"Madrid",
    "wof:name":"Clinica Dental Garciga S.l",
    "wof:placetype":"venue"
},
  "geometry": {"coordinates":[-3.4538938999,40.4566612244],"type":"Point"}
}