{
  "type": "Feature",
  "properties": {
    "iso:country":"ES",
    "sg:address":"Avda Atlantida, 36",
    "sg:city":"Vigo",
    "sg:orig_category":"Empresas De Carpinter\u00cda",
    "sg:phone":"+34 986 20 93 51",
    "sg:postcode":"36208",
    "sg:province":"Pontevedra",
    "wof:name":"Alu-cristal Bouzas S.l.",
    "wof:placetype":"venue"
},
  "geometry": {"coordinates":[-8.7558708191,42.2231903076],"type":"Point"}
}