{
  "type": "Feature",
  "properties": {
    "addr:full":"Calle de Pozo De Las Nieves, 22 Torrejon Ardoz Madrid 28850",
    "addr:housenumber":"22",
    "addr:postcode":"28850",
    "addr:street":"Calle De Pozo De Las Nieves",
    "iso:country":"ES",
    "sg:address":"Calle de Pozo De Las Nieves, 22",
    "sg:city":"Torrejon Ardoz",
    "sg:orig_category":"Aceros Inoxidables",
    "sg:phone":"+34 916 76 71 36",
    "sg:postcode":"28850",
    "sg:province":"Madrid",
    "sg:website":"www.rohso.com",
    "wof:name":"Sistemas Rohso S. L.",
    "wof:placetype":"venue"
},
  "geometry": {"coordinates":[-3.4635810852,40.4462776184],"type":"Point"}
}