{
  "type": "Feature",
  "properties": {
    "addr:full":"Carrer de Johann Sebastian Bach, 5 Barcelona Barcelona 08021",
    "addr:housenumber":"5",
    "addr:postcode":"08021",
    "addr:street":"Carrer De Johann Sebastian Bach",
    "iso:country":"ES",
    "sg:address":"Carrer de Johann Sebastian Bach, 5",
    "sg:city":"Barcelona",
    "sg:orig_category":"Fabricaci\u00d3n, Reparaci\u00d3n Y Mantenimiento De Construcciones Navales Y Fluviales",
    "sg:phone":"+34 932 01 03 82",
    "sg:postcode":"08021",
    "sg:province":"Barcelona",
    "wof:name":"C.i.s.a.m. S.l.",
    "wof:placetype":"venue"
},
  "geometry": {"coordinates":[2.1387240887,41.3954048157],"type":"Point"}
}