{
  "type": "Feature",
  "properties": {
    "addr:full":"Carrer de Balmes, 353 Barcelona Barcelona 08006",
    "addr:housenumber":"353",
    "addr:postcode":"08006",
    "addr:street":"Carrer De Balmes",
    "iso:country":"ES",
    "sg:address":"Carrer de Balmes, 353",
    "sg:city":"Barcelona",
    "sg:orig_category":"M\u00c9dicos: Anestesiolog\u00cda Y Reanimaci\u00d3n Quir\u00dargica",
    "sg:phone":"+34 932 65 27 95",
    "sg:postcode":"08006",
    "sg:province":"Barcelona",
    "wof:name":"Guitart Vela Jordi",
    "wof:placetype":"venue"
},
  "geometry": {"coordinates":[2.1417739391,41.4038772583],"type":"Point"}
}