{
  "type": "Feature",
  "properties": {
    "addr:full":"Dr. Fleming, S/n Vilanova De Segria Lleida 25133",
    "addr:housenumber":"s",
    "addr:postcode":"25133",
    "addr:street":"Fleming;/ N",
    "iso:country":"ES",
    "sg:address":"Dr. Fleming, S/n",
    "sg:city":"Vilanova De Segria",
    "sg:orig_category":"Maquinaria Para Industrias Diversas",
    "sg:phone":"+34 973 77 71 39",
    "sg:postcode":"25133",
    "sg:province":"Lleida",
    "wof:name":"Vinos Torrelles Elias",
    "wof:placetype":"venue"
},
  "geometry": {"coordinates":[0.6172220111,41.7130432129],"type":"Point"}
}