{
  "type": "Feature",
  "properties": {
    "iso:country":"ES",
    "sg:address":"Rua Franco (do), 37",
    "sg:city":"Santiago De Compostela",
    "sg:orig_category":"Molduras, Junquillos, Listones Y Molduras Perforadas",
    "sg:phone":"+34 981 58 60 45",
    "sg:postcode":"15702",
    "sg:province":"La Coru\u00f1a",
    "wof:name":"Montes Albite Ernesto",
    "wof:placetype":"venue"
},
  "geometry": {"coordinates":[-8.5451526642,42.878112793],"type":"Point"}
}