{
  "type": "Feature",
  "properties": {
    "addr:full":"Rond General Mitre, 36 Barcelona Barcelona 08017",
    "addr:housenumber":"36",
    "addr:postcode":"08017",
    "iso:country":"ES",
    "sg:address":"Rond General Mitre, 36",
    "sg:city":"Barcelona",
    "sg:orig_category":"Abogados",
    "sg:phone":"+34 933 17 19 99",
    "sg:postcode":"08017",
    "sg:province":"Barcelona",
    "wof:name":"Campeny Fernandez Margarita",
    "wof:placetype":"venue"
},
  "geometry": {"coordinates":[2.1332890987,41.3942451477],"type":"Point"}
}