{
  "type": "Feature",
  "properties": {
    "addr:full":"Avda Navarra, 141 Zaragoza Zaragoza 50017",
    "addr:housenumber":"141",
    "addr:postcode":"50017",
    "addr:street":"Avda Navarra",
    "iso:country":"ES",
    "sg:address":"Avda Navarra, 141",
    "sg:city":"Zaragoza",
    "sg:orig_category":"Ense\u00d1anza Secundaria: Colegios Y Escuelas Privadas",
    "sg:phone":"+34 976 32 42 00",
    "sg:postcode":"50017",
    "sg:province":"Zaragoza",
    "wof:name":"Instituto De Educacion Secundaria Santiago Hernandez",
    "wof:placetype":"venue"
},
  "geometry": {"coordinates":[-0.9149670005,41.657371521],"type":"Point"}
}