{
  "type": "Feature",
  "properties": {
    "addr:full":"Calle de Marques De Pico Velasco, 60 Madrid Madrid 28027",
    "addr:housenumber":"60",
    "addr:postcode":"madrid;28027",
    "addr:street":"Calle De Marques De Pico Velasco",
    "iso:country":"ES",
    "sg:address":"Calle de Marques De Pico Velasco, 60",
    "sg:city":"Madrid",
    "sg:orig_category":"Centros Empresariales",
    "sg:phone":"+34 913 68 26 38",
    "sg:postcode":"28027",
    "sg:province":"Madrid",
    "wof:name":"Menroix S.l.",
    "wof:placetype":"venue"
},
  "geometry": {"coordinates":[-3.6449849606,40.4428863525],"type":"Point"}
}