{
  "type": "Feature",
  "properties": {
    "addr:full":"Calle de Pinto, 65 Parla Madrid 28980",
    "addr:housenumber":"65",
    "addr:postcode":"28980",
    "addr:street":"Calle De Pinto",
    "iso:country":"ES",
    "sg:address":"Calle de Pinto, 65",
    "sg:city":"Parla",
    "sg:orig_category":"Empresas De Carpinter\u00cda De Madera",
    "sg:phone":"+34 916 99 78 44",
    "sg:postcode":"28980",
    "sg:province":"Madrid",
    "wof:name":"Martinez Gomez Juan Francisco",
    "wof:placetype":"venue"
},
  "geometry": {"coordinates":[-3.762212038,40.2397460938],"type":"Point"}
}