{
  "type": "Feature",
  "properties": {
    "iso:country":"ES",
    "sg:address":"Plaz Eguzki, 4",
    "sg:city":"Mutiloagoiti",
    "sg:orig_category":"Arquitectos",
    "sg:phone":"+34 948 23 88 47",
    "sg:postcode":"31192",
    "sg:province":"Navarra",
    "wof:name":"Galbete Martinicorena Gonzalo",
    "wof:placetype":"venue"
},
  "geometry": {"coordinates":[-1.6190600395,42.7999420166],"type":"Point"}
}