{
  "type": "Feature",
  "properties": {
    "iso:country":"ES",
    "sg:address":"Calle de Iglesia, 4",
    "sg:city":"Guadalajara",
    "sg:orig_category":"Iglesia Cat\u00d3lica",
    "sg:phone":"+34 949 23 00 80",
    "sg:postcode":"19004",
    "sg:province":"Guadalajara",
    "wof:name":"Obispado De Siguenza-guadalajara",
    "wof:placetype":"venue"
},
  "geometry": {"coordinates":[-3.1812810898,40.6432342529],"type":"Point"}
}