{
  "type": "Feature",
  "properties": {
    "iso:country":"ES",
    "sg:address":"Cami Ral, 30",
    "sg:city":"Vilassar",
    "sg:orig_category":"Museos",
    "sg:phone":"+34 937 59 36 39",
    "sg:postcode":"08340",
    "sg:province":"Barcelona",
    "wof:name":"Ajuntament De Vilassar De Mar",
    "wof:placetype":"venue"
},
  "geometry": {"coordinates":[2.3948905468,41.5031394958],"type":"Point"}
}