{
  "type": "Feature",
  "properties": {
    "iso:country":"ES",
    "sg:address":"Calle de Zubiaurre, 42",
    "sg:city":"Ermua",
    "sg:orig_category":"Reposter\u00cdas",
    "sg:phone":"+34 943 17 20 73",
    "sg:postcode":"48260",
    "sg:province":"Vizcaya",
    "wof:name":"Maite Gorrotxategi O\u00f1ate Y Maria Bego\u00f1a Perez Aizpun Cdad.",
    "wof:placetype":"venue"
},
  "geometry": {"coordinates":[-2.5022408962,43.1893806458],"type":"Point"}
}