{
  "type": "Feature",
  "properties": {
    "addr:full":"Avgd Mariners De La Vila Joiosa, 4 Torres Alicante 03570",
    "addr:housenumber":"4",
    "addr:postcode":"03570",
    "addr:street":"Avgd;La Vila Joiosa;Alicante",
    "iso:country":"ES",
    "sg:address":"Avgd Mariners De La Vila Joiosa, 4",
    "sg:city":"Torres",
    "sg:orig_category":"Administradores De Bienes Y Delegados De Comunidades De Propietarios",
    "sg:phone":"+34 966 80 01 77",
    "sg:postcode":"03570",
    "sg:province":"Alicante",
    "wof:name":"Vinal Navarro Jose Emilio",
    "wof:placetype":"venue"
},
  "geometry": {"coordinates":[-0.2327190042,38.505821228],"type":"Point"}
}