{
  "type": "Feature",
  "properties": {
    "addr:full":"Barr Upomendi, S/n Kurtzea Vizcaya 48960",
    "addr:housenumber":"s",
    "addr:postcode":"48960",
    "addr:street":"/ N",
    "iso:country":"ES",
    "sg:address":"Barr Upomendi, S/n",
    "sg:city":"Kurtzea",
    "sg:orig_category":"Iglesia Cat\u00d3lica",
    "sg:phone":"+34 944 56 15 64",
    "sg:postcode":"48960",
    "sg:province":"Vizcaya",
    "wof:name":"Parroquia Santa Barbara",
    "wof:placetype":"venue"
},
  "geometry": {"coordinates":[-2.8470389843,43.2298049927],"type":"Point"}
}