{
  "type": "Feature",
  "properties": {
    "iso:country":"ES",
    "sg:address":"Av Marques D'alpens, S/n",
    "sg:city":"Pera",
    "sg:orig_category":"Fabricaci\u00d3n De Generadores De Aire Caliente",
    "sg:phone":"+34 972 48 82 35",
    "sg:postcode":"17120",
    "sg:province":"Girona",
    "wof:name":"Boldu Sole Jose Maria",
    "wof:placetype":"venue"
},
  "geometry": {"coordinates":[2.8222129345,41.9703025818],"type":"Point"}
}