{
  "type": "Feature",
  "properties": {
    "iso:country":"ES",
    "sg:address":"Calle de Vegafria, 26",
    "sg:city":"Valladolid",
    "sg:orig_category":"Electromec\u00c1nica",
    "sg:phone":"+34 983 27 11 40",
    "sg:postcode":"47013",
    "sg:province":"Valladolid",
    "wof:name":"Comercial Vegafria C.b",
    "wof:placetype":"venue"
},
  "geometry": {"coordinates":[-4.7242021561,41.6379928589],"type":"Point"}
}