{
  "type": "Feature",
  "properties": {
    "iso:country":"ES",
    "sg:address":"Calle de Virrey Del Pino, 7",
    "sg:city":"Baena",
    "sg:orig_category":"\u00c1rboles Frutales",
    "sg:phone":"+34 957 69 03 22",
    "sg:postcode":"14850",
    "sg:province":"C\u00f3rdoba",
    "wof:name":"Eguilaz De Prado Luis",
    "wof:placetype":"venue"
},
  "geometry": {"coordinates":[-4.323964119,37.6170043945],"type":"Point"}
}