{
  "type": "Feature",
  "properties": {
    "iso:country":"ES",
    "sg:address":"Calle de Cruz, 3",
    "sg:city":"Madrid",
    "sg:orig_category":"Albergues",
    "sg:phone":"+34 915 31 01 30",
    "sg:postcode":"28012",
    "sg:province":"Madrid",
    "wof:name":"Hostal Cantabrico S.l.",
    "wof:placetype":"venue"
},
  "geometry": {"coordinates":[-3.7007472515,40.4162635803],"type":"Point"}
}