{
  "type": "Feature",
  "properties": {
    "iso:country":"ES",
    "sg:address":"Calle de Gamonal, 23",
    "sg:city":"Madrid",
    "sg:orig_category":"Laboratorios De Control Sanitario Y Ambiental",
    "sg:phone":"+34 913 31 15 01",
    "sg:postcode":"28031",
    "sg:province":"Madrid",
    "wof:name":"Servicio Profesional De Higiene S.l.",
    "wof:placetype":"venue"
},
  "geometry": {"coordinates":[-3.6437559128,40.3731155396],"type":"Point"}
}