{
  "type": "Feature",
  "properties": {
    "iso:country":"ES",
    "sg:address":"Mossen Andreu Llabres, 3",
    "sg:city":"Lloseta",
    "sg:orig_category":"Confecci\u00d3n De Zapatos",
    "sg:phone":"+34 971 51 94 11",
    "sg:postcode":"07360",
    "sg:province":"Islas Baleares",
    "wof:name":"Trenzados Lloseta S.l.",
    "wof:placetype":"venue"
},
  "geometry": {"coordinates":[2.8661301136,39.7158584595],"type":"Point"}
}