{
  "type": "Feature",
  "properties": {
    "addr:full":"Avda Gasteiz, 93 Vitoria-gasteiz \u00c1lava 01009",
    "addr:housenumber":"93",
    "addr:postcode":"01009",
    "addr:street":"Avda Gasteiz",
    "iso:country":"ES",
    "sg:address":"Avda Gasteiz, 93",
    "sg:city":"Vitoria-gasteiz",
    "sg:orig_category":"Transportes Por V\u00cdas Navegables",
    "sg:phone":"+34 945 24 26 19",
    "sg:postcode":"01009",
    "sg:province":"\u00c1lava",
    "wof:name":"Fernandez De La Pe\u00f1a Lopez De Lacalle Tomas",
    "wof:placetype":"venue"
},
  "geometry": {"coordinates":[-2.6804161072,42.8541984558],"type":"Point"}
}