{
  "type": "Feature",
  "properties": {
    "addr:full":"Avda Victor Gallego, 23 Zamora Zamora 49009",
    "addr:housenumber":"23",
    "addr:postcode":"49009",
    "addr:street":"Avda Victor Gallego",
    "iso:country":"ES",
    "sg:address":"Avda Victor Gallego, 23",
    "sg:city":"Zamora",
    "sg:orig_category":"Partidos Pol\u00cdticos",
    "sg:phone":"+34 980 52 62 15",
    "sg:postcode":"49009",
    "sg:province":"Zamora",
    "wof:name":"Partido Popular",
    "wof:placetype":"venue"
},
  "geometry": {"coordinates":[-5.7429180145,41.5104217529],"type":"Point"}
}