{
  "type": "Feature",
  "properties": {
    "iso:country":"ES",
    "sg:address":"Calle de Correales, 28",
    "sg:city":"Valderas",
    "sg:orig_category":"Florister\u00cdas",
    "sg:phone":"+34 987 76 31 50",
    "sg:postcode":"24220",
    "sg:province":"Le\u00f3n",
    "wof:name":"Gonzalez Cuende Pilar",
    "wof:placetype":"venue"
},
  "geometry": {"coordinates":[-5.4436173439,42.0779304504],"type":"Point"}
}