{
  "type": "Feature",
  "properties": {
    "addr:full":"Calle de Flor, 2 Navasfrias Salamanca 37542",
    "addr:housenumber":"2",
    "addr:postcode":"37542",
    "addr:street":"Calle De Flor",
    "iso:country":"ES",
    "sg:address":"Calle de Flor, 2",
    "sg:city":"Navasfrias",
    "sg:orig_category":"Loter\u00cda Y T\u00d3mbola",
    "sg:phone":"+34 923 47 50 03",
    "sg:postcode":"37542",
    "sg:province":"Salamanca",
    "wof:name":"Paino Perez Maria",
    "wof:placetype":"venue"
},
  "geometry": {"coordinates":[-6.817920208,40.2959480286],"type":"Point"}
}