{
  "type": "Feature",
  "properties": {
    "addr:full":"Carretera, S/n Algerri Lleida 25130",
    "addr:postcode":"25130",
    "addr:street":"Carretera S / N",
    "iso:country":"ES",
    "sg:address":"Carretera, S/n",
    "sg:city":"Algerri",
    "sg:orig_category":"Cooperativas Agr\u00cdcolas",
    "sg:phone":"+34 973 42 61 01",
    "sg:postcode":"25130",
    "sg:province":"Lleida",
    "wof:name":"Cooperativa Del Campo",
    "wof:placetype":"venue"
},
  "geometry": {"coordinates":[0.6381819844,41.8139686584],"type":"Point"}
}