{
  "type": "Feature",
  "properties": {
    "iso:country":"ES",
    "sg:address":"Avda Feria De La, 42",
    "sg:city":"Palmas De Gran Canaria",
    "sg:orig_category":"Obras Y Organismos Sociales",
    "sg:phone":"+34 928 42 08 63",
    "sg:postcode":"35012",
    "sg:province":"Las Palmas",
    "wof:name":"Feafes Canarias",
    "wof:placetype":"venue"
},
  "geometry": {"coordinates":[-15.4442510605,28.1059913635],"type":"Point"}
}