{
  "type": "Feature",
  "properties": {
    "iso:country":"ES",
    "sg:address":"Calle de Ricos, 20",
    "sg:city":"Arroyo Luz",
    "sg:orig_category":"Electricidad, Electr\u00d3nica: Suministros (al Por Menor)",
    "sg:phone":"+34 927 27 05 29",
    "sg:postcode":"10900",
    "sg:province":"C\u00e1ceres",
    "wof:name":"Molano Tejado Fernando",
    "wof:placetype":"venue"
},
  "geometry": {"coordinates":[-6.5842251778,39.4834709167],"type":"Point"}
}