{
  "type": "Feature",
  "properties": {
    "addr:full":"Calle de Anton Guanche, 1 Candelaria Santa Cruz De Tenerife 38530",
    "addr:housenumber":"1",
    "addr:postcode":"38530",
    "addr:street":"Calle De Anton Guanche",
    "iso:country":"ES",
    "sg:address":"Calle de Anton Guanche, 1",
    "sg:city":"Candelaria",
    "sg:orig_category":"Institutos De Belleza",
    "sg:phone":"+34 922 50 43 52",
    "sg:postcode":"38530",
    "sg:province":"Santa Cruz De Tenerife",
    "wof:name":"Dominguez Delgado Yasmina",
    "wof:placetype":"venue"
},
  "geometry": {"coordinates":[-16.3706569672,28.3513793945],"type":"Point"}
}