{
  "type": "Feature",
  "properties": {
    "iso:country":"ES",
    "sg:address":"Calle de Valencia (de), 116",
    "sg:city":"Alcobendas",
    "sg:orig_category":"Plomeros",
    "sg:phone":"+34 916 53 99 19",
    "sg:postcode":"28100",
    "sg:province":"Madrid",
    "wof:name":"Alamillos Moya Gregorio",
    "wof:placetype":"venue"
},
  "geometry": {"coordinates":[-3.6388607025,40.5498428345],"type":"Point"}
}