{
  "type": "Feature",
  "properties": {
    "addr:full":"Av Mare Deu De Montserrat, 244 Barcelona Barcelona 08041",
    "addr:housenumber":"244",
    "addr:postcode":"08041",
    "addr:street":"Av Mare;De Montserrat",
    "iso:country":"ES",
    "sg:address":"Av Mare Deu De Montserrat, 244",
    "sg:city":"Barcelona",
    "sg:orig_category":"Supermercados Y Hipermercados",
    "sg:phone":"+34 934 56 95 14",
    "sg:postcode":"08041",
    "sg:province":"Barcelona",
    "wof:name":"Alimentacion Herber S.l.",
    "wof:placetype":"venue"
},
  "geometry": {"coordinates":[2.1748280525,41.4225463867],"type":"Point"}
}