{
  "type": "Feature",
  "properties": {
    "iso:country":"ES",
    "sg:address":"Viavelez, S/n",
    "sg:city":"Valdepares",
    "sg:classifiers":[
        {
            "category":"Recreation",
            "type":"Entertainment"
        }
    ],
    "sg:phone":"+34 985 63 70 74",
    "sg:postcode":"33746",
    "sg:province":"Asturias",
    "sg:tags":[
        "caza",
        "pr\u00c1ctica",
        "la",
        "de",
        "pesca",
        "y"
    ],
    "wof:name":"Cofradia De Pescadores Angel De La Guarda",
    "wof:placetype":"venue"
},
  "geometry": {"coordinates":[-6.8597688675,43.557849884],"type":"Point"}
}