{
  "type": "Feature",
  "properties": {
    "addr:full":"Pol Ind El Peral, S/n Nerva Huelva 21670",
    "addr:housenumber":"s / n",
    "addr:postcode":"21670",
    "addr:street":"Peral",
    "iso:country":"ES",
    "sg:address":"Pol Ind El Peral, S/n",
    "sg:city":"Nerva",
    "sg:orig_category":"Reposter\u00cdas",
    "sg:phone":"+34 959 58 01 47",
    "sg:postcode":"21670",
    "sg:province":"Huelva",
    "wof:name":"Fuentes Acemel Fernando",
    "wof:placetype":"venue"
},
  "geometry": {"coordinates":[-6.5471301079,37.6939048767],"type":"Point"}
}