{
  "type": "Feature",
  "properties": {
    "iso:country":"ES",
    "sg:address":"Calle de Juan Xxiii, 25",
    "sg:city":"Cristianos",
    "sg:orig_category":"Alquiler De Veh\u00cdculos: Turismos Y Utilitarios",
    "sg:phone":"+34 922 79 11 56",
    "sg:postcode":"38650",
    "sg:province":"Santa Cruz De Tenerife",
    "wof:name":"Pascual Alayon Sl",
    "wof:placetype":"venue"
},
  "geometry": {"coordinates":[-16.719045639,28.051612854],"type":"Point"}
}