{
  "type": "Feature",
  "properties": {
    "addr:full":"Calle de Joxe Miguel Barandiaran, 8 Kurtzea Vizcaya 48960",
    "addr:housenumber":"8",
    "addr:postcode":"48960",
    "addr:street":"Calle De Joxe Miguel Barandiaran",
    "iso:country":"ES",
    "sg:address":"Calle de Joxe Miguel Barandiaran, 8",
    "sg:city":"Kurtzea",
    "sg:orig_category":"Ense\u00d1anza: Idiomas",
    "sg:phone":"+34 944 56 41 19",
    "sg:postcode":"48960",
    "sg:province":"Vizcaya",
    "wof:name":"Euskaraz Koop. E.",
    "wof:placetype":"venue"
},
  "geometry": {"coordinates":[-2.8470389843,43.2298049927],"type":"Point"}
}