{
  "type": "Feature",
  "properties": {
    "iso:country":"ES",
    "sg:address":"Plaz Mayor, 11",
    "sg:city":"Castellanos Moriscos",
    "sg:orig_category":"Farmacias",
    "sg:phone":"+34 923 36 14 94",
    "sg:postcode":"37439",
    "sg:province":"Salamanca",
    "wof:name":"De Luis Alonso Jose Manuel",
    "wof:placetype":"venue"
},
  "geometry": {"coordinates":[-5.6178340912,41.0289802551],"type":"Point"}
}