{
  "type": "Feature",
  "properties": {
    "addr:full":"Calle de Monturque, 8 Aguilar De La Frontera C\u00f3rdoba 14920",
    "addr:housenumber":"8",
    "addr:postcode":"14920",
    "addr:street":"Calle De Monturque",
    "iso:country":"ES",
    "sg:address":"Calle de Monturque, 8",
    "sg:city":"Aguilar De La Frontera",
    "sg:orig_category":"Asesor\u00cda Fiscal Y Jur\u00cddica",
    "sg:phone":"+34 957 68 84 44",
    "sg:postcode":"14920",
    "sg:province":"C\u00f3rdoba",
    "wof:name":"Andrada Andrada Jose Antonio",
    "wof:placetype":"venue"
},
  "geometry": {"coordinates":[-4.6561546326,37.5138130188],"type":"Point"}
}