{
  "type": "Feature",
  "properties": {
    "iso:country":"ES",
    "sg:address":"Rua Alfonso Vii, 31",
    "sg:city":"Mondo\u00f1edo",
    "sg:orig_category":"Aguas (distribuci\u00d3n, Servicios)",
    "sg:phone":"+34 982 52 18 28",
    "sg:postcode":"27740",
    "sg:province":"Lugo",
    "wof:name":"Aqualia Gestion Integral Del Agua S.a.",
    "wof:placetype":"venue"
},
  "geometry": {"coordinates":[-7.3624596596,43.4486198425],"type":"Point"}
}