{
  "type": "Feature",
  "properties": {
    "iso:country":"ES",
    "sg:address":"Calle de Jorge Juan, 52",
    "sg:city":"Madrid",
    "sg:orig_category":"Molduras, Junquillos, Listones Y Molduras Perforadas",
    "sg:phone":"+34 914 35 91 71",
    "sg:postcode":"28001",
    "sg:province":"Madrid",
    "wof:name":"Jorge Juan 52 S.l.",
    "wof:placetype":"venue"
},
  "geometry": {"coordinates":[-3.6804337502,40.4236030579],"type":"Point"}
}