{
  "type": "Feature",
  "properties": {
    "iso:country":"ES",
    "sg:address":"Calle de Pilar, 14",
    "sg:city":"San Garcia Ingelmos",
    "sg:orig_category":"Cr\u00cda De Animales",
    "sg:phone":"+34 920 23 45 06",
    "sg:postcode":"05146",
    "sg:province":"\u00c1vila",
    "wof:name":"Hermanos Jimenez Garcia Cb",
    "wof:placetype":"venue"
},
  "geometry": {"coordinates":[-5.1148920059,40.7687835693],"type":"Point"}
}