{
  "type": "Feature",
  "properties": {
    "addr:full":"Carrer de Bruc, 151 Barcelona Barcelona 08037",
    "addr:housenumber":"151",
    "addr:postcode":"08037",
    "addr:street":"Carrer De Bruc",
    "iso:country":"ES",
    "sg:address":"Carrer de Bruc, 151",
    "sg:city":"Barcelona",
    "sg:orig_category":"Asilos De Ancianos. Centros Privados",
    "sg:phone":"+34 932 07 12 21",
    "sg:postcode":"08037",
    "sg:province":"Barcelona",
    "wof:name":"Residenca Nurielo Sl",
    "wof:placetype":"venue"
},
  "geometry": {"coordinates":[2.1634039879,41.3987541199],"type":"Point"}
}