{
  "type": "Feature",
  "properties": {
    "iso:country":"ES",
    "sg:address":"Rua Boulebard, 1",
    "sg:city":"Cimadevila",
    "sg:orig_category":"Aperitivos (fabricaci\u00d3n Y Al Por Mayor)",
    "sg:phone":"+34 988 36 00 41",
    "sg:postcode":"32890",
    "sg:province":"Ourense",
    "wof:name":"Distribuciones Candy Orense S.l.",
    "wof:placetype":"venue"
},
  "geometry": {"coordinates":[-7.8872189522,42.3010559082],"type":"Point"}
}