{
  "type": "Feature",
  "properties": {
    "iso:country":"ES",
    "sg:address":"Plaz Santisima Faz, 5",
    "sg:city":"Alacant",
    "sg:orig_category":"Urbanistas",
    "sg:phone":"+34 965 20 63 29",
    "sg:postcode":"03002",
    "sg:province":"Alicante",
    "wof:name":"Patronato Municipal De La Vivienda D'alacant",
    "wof:placetype":"venue"
},
  "geometry": {"coordinates":[-0.4813619852,38.3456840515],"type":"Point"}
}