{
  "type": "Feature",
  "properties": {
    "iso:country":"ES",
    "sg:address":"Calle de Cervantes, 3",
    "sg:city":"Guadix",
    "sg:orig_category":"Agencias Y Agentes Comerciales, Representantes",
    "sg:phone":"+34 958 66 05 27",
    "sg:postcode":"18500",
    "sg:province":"Granada",
    "wof:name":"Lozano Cruz Antonio",
    "wof:placetype":"venue"
},
  "geometry": {"coordinates":[-3.1383225918,37.2984733582],"type":"Point"}
}