{
  "type": "Feature",
  "properties": {
    "iso:country":"ES",
    "sg:address":"Rua Couto San Honorato, 103",
    "sg:city":"Vigo",
    "sg:orig_category":"Estancos",
    "sg:phone":"+34 986 41 88 48",
    "sg:postcode":"36204",
    "sg:province":"Pontevedra",
    "wof:name":"Garcia Fernandez Maria Elisa",
    "wof:placetype":"venue"
},
  "geometry": {"coordinates":[-8.7107868195,42.2293777466],"type":"Point"}
}