{
  "type": "Feature",
  "properties": {
    "addr:full":"Calle de Rio Jucar, 14 Lepe Huelva 21440",
    "addr:housenumber":"14",
    "addr:postcode":"21440",
    "addr:street":"Calle De Rio Jucar",
    "iso:country":"ES",
    "sg:address":"Calle de Rio Jucar, 14",
    "sg:city":"Lepe",
    "sg:orig_category":"Inmobiliaria (agencias)",
    "sg:phone":"+34 959 38 46 11",
    "sg:postcode":"21440",
    "sg:province":"Huelva",
    "wof:name":"Gestion Inmobiliaria Tryac S.l.",
    "wof:placetype":"venue"
},
  "geometry": {"coordinates":[-7.1965088844,37.2603797913],"type":"Point"}
}