{
  "type": "Feature",
  "properties": {
    "iso:country":"ES",
    "sg:address":"Pol Ind Juan Carlos I, 5",
    "sg:city":"Almussafes",
    "sg:orig_category":"Carros Elevadores, Carros De Operaciones Portuarias",
    "sg:phone":"+34 961 78 15 50",
    "sg:postcode":"46440",
    "sg:province":"Valencia",
    "wof:name":"Clemalquiler S.l.",
    "wof:placetype":"venue"
},
  "geometry": {"coordinates":[-0.4122039974,39.2929763794],"type":"Point"}
}