{
  "type": "Feature",
  "properties": {
    "iso:country":"ES",
    "sg:address":"Avda Cordoba, S/n",
    "sg:city":"Llerena",
    "sg:orig_category":"Ingeniero",
    "sg:phone":"+34 924 87 22 05",
    "sg:postcode":"06900",
    "sg:province":"Badajoz",
    "wof:name":"Pe\u00f1a Zapata Juan Manuel",
    "wof:placetype":"venue"
},
  "geometry": {"coordinates":[-6.0109591484,38.2393455505],"type":"Point"}
}