{
  "type": "Feature",
  "properties": {
    "addr:full":"Calle de Diego De Leon, 62 Madrid Madrid 28006",
    "addr:housenumber":"62",
    "addr:postcode":"madrid;28006",
    "addr:street":"Calle De Diego De Leon",
    "iso:country":"ES",
    "sg:address":"Calle de Diego De Leon, 62",
    "sg:city":"Madrid",
    "sg:orig_category":"M\u00c9dicos: Reumatolog\u00cda",
    "sg:phone":"+34 914 01 60 53",
    "sg:postcode":"28006",
    "sg:province":"Madrid",
    "wof:name":"Laffon Roca Armando",
    "wof:placetype":"venue"
},
  "geometry": {"coordinates":[-3.6761584282,40.4345741272],"type":"Point"}
}