{
  "type": "Feature",
  "properties": {
    "addr:full":"Carrer de Convent, 50 Sabadell Barcelona 08202",
    "addr:housenumber":"50",
    "addr:postcode":"08202",
    "addr:street":"Carrer De Convent",
    "iso:country":"ES",
    "sg:address":"Carrer de Convent, 50",
    "sg:city":"Sabadell",
    "sg:orig_category":"Asesor\u00cda Fiscal Y Jur\u00cddica",
    "sg:phone":"+34 937 25 69 59",
    "sg:postcode":"08202",
    "sg:province":"Barcelona",
    "wof:name":"Juste Trillas Roberto",
    "wof:placetype":"venue"
},
  "geometry": {"coordinates":[2.1086790562,41.5508308411],"type":"Point"}
}