{
  "type": "Feature",
  "properties": {
    "iso:country":"ES",
    "sg:address":"Calle de Felipe Ii, 26",
    "sg:city":"Bolnuevo",
    "sg:orig_category":"Fabricaci\u00d3n De Muebles",
    "sg:phone":"+34 968 15 83 15",
    "sg:postcode":"30877",
    "sg:province":"Murcia",
    "wof:name":"Dickinson  Carron",
    "wof:placetype":"venue"
},
  "geometry": {"coordinates":[-1.3049509525,37.5637283325],"type":"Point"}
}