{
  "type": "Feature",
  "properties": {
    "iso:country":"ES",
    "sg:address":"Calle de Ramon Y Cajal, 13",
    "sg:city":"Vitoria-gasteiz",
    "sg:orig_category":"Internados & Ense\u00d1anza Privada",
    "sg:phone":"+34 945 13 04 76",
    "sg:postcode":"01007",
    "sg:province":"\u00c1lava",
    "wof:name":"Carmelitas De La Caridad Provincia De Vitoria Curia Provincial",
    "wof:placetype":"venue"
},
  "geometry": {"coordinates":[-2.6775979996,42.8436203003],"type":"Point"}
}