{
  "type": "Feature",
  "properties": {
    "addr:full":"Calle de Cereria, 7 Talavera Reina Toledo 45600",
    "addr:housenumber":"7",
    "addr:postcode":"45600",
    "addr:street":"Calle De Cereria",
    "iso:country":"ES",
    "sg:address":"Calle de Cereria, 7",
    "sg:city":"Talavera Reina",
    "sg:orig_category":"Parques De Atracciones Y Centros De Esparcimiento",
    "sg:phone":"+34 925 81 62 17",
    "sg:postcode":"45600",
    "sg:province":"Toledo",
    "wof:name":"Rodriguez Elvira Alvaro",
    "wof:placetype":"venue"
},
  "geometry": {"coordinates":[-4.8320732117,39.9608268738],"type":"Point"}
}