{
  "type": "Feature",
  "properties": {
    "addr:full":"Mcdo Pl Barcelona, S/n Elche Alicante 03206",
    "addr:housenumber":"/ n",
    "addr:postcode":"03206",
    "addr:street":"Mcdo Pl Barcelona S",
    "iso:country":"ES",
    "sg:address":"Mcdo Pl Barcelona, S/n",
    "sg:city":"Elche",
    "sg:orig_category":"Carnicer\u00cdas, Carnicer\u00cdas",
    "sg:phone":"+34 965 44 54 11",
    "sg:postcode":"03206",
    "sg:province":"Alicante",
    "wof:name":"Gomez Paredes Francisco Javier",
    "wof:placetype":"venue"
},
  "geometry": {"coordinates":[-0.7223982811,38.29063797],"type":"Point"}
}