{
  "type": "Feature",
  "properties": {
    "addr:full":"Trav De Gracia, 122 Barcelona Barcelona 08012",
    "addr:housenumber":"122",
    "addr:postcode":"08012",
    "addr:street":"Trav De Gracia",
    "iso:country":"ES",
    "sg:address":"Trav De Gracia, 122",
    "sg:city":"Barcelona",
    "sg:orig_category":"Productos Alimentarios",
    "sg:phone":"+34 932 18 40 78",
    "sg:postcode":"08012",
    "sg:province":"Barcelona",
    "sg:website":"www.e-teashop.com",
    "wof:name":"East West Company Spain S.l.",
    "wof:placetype":"venue"
},
  "geometry": {"coordinates":[2.1559479237,41.399974823],"type":"Point"}
}