{
  "type": "Feature",
  "properties": {
    "iso:country":"ES",
    "sg:address":"Carrer de Josep Maria Juncadella, 64",
    "sg:city":"Segur Calafell",
    "sg:orig_category":"Agencias Y Agentes Comerciales, Representantes",
    "sg:phone":"+34 977 16 27 88",
    "sg:postcode":"43882",
    "sg:province":"Tarragona",
    "wof:name":"Fievet  Fernand Amedee Louis",
    "wof:placetype":"venue"
},
  "geometry": {"coordinates":[1.6018660069,41.1904602051],"type":"Point"}
}