{
  "type": "Feature",
  "properties": {
    "iso:country":"ES",
    "sg:address":"Calle de Pare Vicent Ribes, 4",
    "sg:city":"Alzira",
    "sg:orig_category":"Fotograf\u00cda Y Cine: Aparatos, Pel\u00cdculas Y Accesorios (fabricaci\u00d3n, Al Por Mayor)",
    "sg:phone":"+34 962 40 10 69",
    "sg:postcode":"46600",
    "sg:province":"Valencia",
    "wof:name":"Carrillo Ferran Francisca",
    "wof:placetype":"venue"
},
  "geometry": {"coordinates":[-0.4288589954,39.1470222473],"type":"Point"}
}