{
  "type": "Feature",
  "properties": {
    "addr:full":"Calle de Chantada, 1 Madrid Madrid 28029",
    "addr:housenumber":"1",
    "addr:postcode":"28029",
    "addr:street":"Calle De Chantada",
    "iso:country":"ES",
    "sg:address":"Calle de Chantada, 1",
    "sg:city":"Madrid",
    "sg:orig_category":"Inmobiliaria (agencias)",
    "sg:phone":"+34 917 31 42 80",
    "sg:postcode":"28029",
    "sg:province":"Madrid",
    "sg:website":"www.expofinques.es",
    "wof:name":"Expofinques S.l.",
    "wof:placetype":"venue"
},
  "geometry": {"coordinates":[-3.7108120918,40.472743988],"type":"Point"}
}