{
  "type": "Feature",
  "properties": {
    "addr:full":"Calle de Abedul, 8 Arganda Madrid 28500",
    "addr:housenumber":"8",
    "addr:postcode":"28500",
    "addr:street":"Calle De Abedul",
    "iso:country":"ES",
    "sg:address":"Calle de Abedul, 8",
    "sg:city":"Arganda",
    "sg:orig_category":"Fabricaci\u00d3n De Art\u00cdculos Y Equipos Deportivos Y De Ocio",
    "sg:phone":"+34 918 71 20 93",
    "sg:postcode":"28500",
    "sg:province":"Madrid",
    "wof:name":"Drelax S.l",
    "wof:placetype":"venue"
},
  "geometry": {"coordinates":[-3.4622673988,40.3184280396],"type":"Point"}
}