{
  "type": "Feature",
  "properties": {
    "iso:country":"ES",
    "sg:address":"Trva Juan Francisco, 1",
    "sg:city":"Madrid",
    "sg:orig_category":"Mec\u00c1nico Del Autom\u00d3vil",
    "sg:phone":"+34 915 25 53 53",
    "sg:postcode":"28025",
    "sg:province":"Madrid",
    "wof:name":"Casas Fernandez Antonio",
    "wof:placetype":"venue"
},
  "geometry": {"coordinates":[-3.7322399616,40.3870506287],"type":"Point"}
}