{
  "type": "Feature",
  "properties": {
    "iso:country":"ES",
    "sg:address":"Carrer de Eucaliptus, 15",
    "sg:city":"Esplugues Llobregat",
    "sg:orig_category":"Electricidad: Instaladores",
    "sg:phone":"+34 933 71 82 44",
    "sg:postcode":"08950",
    "sg:province":"Barcelona",
    "wof:name":"Esteban Gomez Antonio",
    "wof:placetype":"venue"
},
  "geometry": {"coordinates":[2.0993459225,41.3751564026],"type":"Point"}
}