{
  "type": "Feature",
  "properties": {
    "addr:full":"Calle de Caceres, 47 Madrid Madrid 28045",
    "addr:housenumber":"47",
    "addr:postcode":"madrid;28045",
    "addr:street":"Calle De Caceres",
    "iso:country":"ES",
    "sg:address":"Calle de Caceres, 47",
    "sg:city":"Madrid",
    "sg:orig_category":"Clases De M\u00dasica Y Canto",
    "sg:phone":"+34 915 17 67 97",
    "sg:postcode":"28045",
    "sg:province":"Madrid",
    "wof:name":"Musikanda S.l.",
    "wof:placetype":"venue"
},
  "geometry": {"coordinates":[-3.6996684074,40.3989181519],"type":"Point"}
}