{
  "type": "Feature",
  "properties": {
    "iso:country":"ES",
    "sg:address":"Trav Corts, 188",
    "sg:city":"Barcelona",
    "sg:orig_category":"Agua",
    "sg:phone":"+34 934 09 14 30",
    "sg:postcode":"08028",
    "sg:province":"Barcelona",
    "sg:website":"www.resmed.com",
    "wof:name":"Car Cardiology S.l.",
    "wof:placetype":"venue"
},
  "geometry": {"coordinates":[2.1290669441,41.3829879761],"type":"Point"}
}