{
  "type": "Feature",
  "properties": {
    "iso:country":"ES",
    "sg:address":"Pl Major, 2",
    "sg:city":"Pedreguer",
    "sg:orig_category":"Supermercados Y Hipermercados",
    "sg:phone":"+34 966 45 71 54",
    "sg:postcode":"03750",
    "sg:province":"Alicante",
    "wof:name":"Super G S.a.",
    "wof:placetype":"venue"
},
  "geometry": {"coordinates":[0.0341840014,38.7927398682],"type":"Point"}
}