{
  "type": "Feature",
  "properties": {
    "iso:country":"ES",
    "sg:address":"Calle de Caama\u00d1o, 75",
    "sg:city":"Valladolid",
    "sg:orig_category":"M\u00c9dicos: Estomatolog\u00cda",
    "sg:phone":"+34 983 23 86 98",
    "sg:postcode":"47008",
    "sg:province":"Valladolid",
    "wof:name":"Fernandez Lopez Eduardo David",
    "wof:placetype":"venue"
},
  "geometry": {"coordinates":[-4.7249336243,41.6281738281],"type":"Point"}
}