{
  "type": "Feature",
  "properties": {
    "addr:full":"Calle de Divina Pastora, 2 Jerez De La Frontera C\u00e1diz 11402",
    "addr:housenumber":"2",
    "addr:postcode":"11402",
    "addr:street":"Calle De Divina Pastora",
    "iso:country":"ES",
    "sg:address":"Calle de Divina Pastora, 2",
    "sg:city":"Jerez De La Frontera",
    "sg:orig_category":"Fabricaci\u00d3n De Material Y Sistemas De Se\u00d1alizaci\u00d3n De Carreteras, Urbanos Y De Obras",
    "sg:phone":"+34 956 33 31 12",
    "sg:postcode":"11402",
    "sg:province":"C\u00e1diz",
    "wof:name":"Lopez Avalos Antonio",
    "wof:placetype":"venue"
},
  "geometry": {"coordinates":[-6.1361174583,36.6900291443],"type":"Point"}
}