{
  "type": "Feature",
  "properties": {
    "iso:country":"ES",
    "sg:address":"Urb Princesa Yballa, S/n",
    "sg:city":"Cuesta",
    "sg:orig_category":"Mercer\u00cda, Lencer\u00cda (al Por Menor)",
    "sg:phone":"+34 922 64 20 56",
    "sg:postcode":"38320",
    "sg:province":"Santa Cruz De Tenerife",
    "wof:name":"Bugallo Edreira Maria Dolores",
    "wof:placetype":"venue"
},
  "geometry": {"coordinates":[-16.2879390717,28.4665393829],"type":"Point"}
}