{
  "type": "Feature",
  "properties": {
    "iso:country":"ES",
    "sg:address":"Pol Ind El Jardal, S/n",
    "sg:city":"Puebla Cazalla",
    "sg:orig_category":"Aluminio Y Aleaciones (producci\u00d3n, Transformaci\u00d3n, Negocio)",
    "sg:phone":"+34 954 84 69 94",
    "sg:postcode":"41540",
    "sg:province":"Sevilla",
    "wof:name":"D.d.h Sistemas De Persianas S.l.",
    "wof:placetype":"venue"
},
  "geometry": {"coordinates":[-5.3132190704,37.2229957581],"type":"Point"}
}