{
  "type": "Feature",
  "properties": {
    "iso:country":"ES",
    "sg:address":"Calle de Humilladero (del), 1",
    "sg:city":"Fuenlabrada",
    "sg:orig_category":"Ropa Para Se\u00d1oras (al Por Menor)",
    "sg:phone":"+34 916 15 77 73",
    "sg:postcode":"28945",
    "sg:province":"Madrid",
    "wof:name":"Mangas Delgado Maria",
    "wof:placetype":"venue"
},
  "geometry": {"coordinates":[-3.7952389717,40.2839813232],"type":"Point"}
}