{
  "type": "Feature",
  "properties": {
    "iso:country":"ES",
    "sg:address":"Carr Aquari, 22",
    "sg:city":"Figueres",
    "sg:orig_category":"Supermercados Y Hipermercados",
    "sg:phone":"+34 972 50 42 44",
    "sg:postcode":"17600",
    "sg:province":"Girona",
    "wof:name":"Garcia Ma\u00f1as Alicia",
    "wof:placetype":"venue"
},
  "geometry": {"coordinates":[2.9819328785,42.2674713135],"type":"Point"}
}