{
  "type": "Feature",
  "properties": {
    "iso:country":"ES",
    "sg:address":"Calle de Madre De Dios, 11",
    "sg:city":"Valladolid",
    "sg:orig_category":"Retoques De Vestidos",
    "sg:phone":"+34 983 37 79 67",
    "sg:postcode":"47011",
    "sg:province":"Valladolid",
    "wof:name":"Garcia Pe\u00f1alba Teresa",
    "wof:placetype":"venue"
},
  "geometry": {"coordinates":[-4.7165131569,41.65858078],"type":"Point"}
}