{
  "type": "Feature",
  "properties": {
    "addr:full":"Avda Onda, 36 Ribesalbes Castell\u00f3n 12210",
    "addr:housenumber":"36",
    "addr:postcode":"12210",
    "addr:street":"Avda Onda;Castello\u0301N",
    "iso:country":"ES",
    "sg:address":"Avda Onda, 36",
    "sg:city":"Ribesalbes",
    "sg:orig_category":"Venta, Colocaci\u00d3n, Tratamiento De Enlosados, Soler\u00cdas",
    "sg:phone":"+34 964 62 50 60",
    "sg:postcode":"12210",
    "sg:province":"Castell\u00f3n",
    "wof:name":"Azulejos El Mijares S. L.",
    "wof:placetype":"venue"
},
  "geometry": {"coordinates":[-0.2741251886,40.0178604126],"type":"Point"}
}