{
  "type": "Feature",
  "properties": {
    "addr:full":"Ctra Vizcaina, 72 Gijon Asturias 33207",
    "addr:housenumber":"72",
    "addr:postcode":"33207",
    "addr:street":"Ctra Vizcaina",
    "iso:country":"ES",
    "sg:address":"Ctra Vizcaina, 72",
    "sg:city":"Gijon",
    "sg:orig_category":"Agencias Y Agentes Comerciales, Representantes",
    "sg:phone":"+34 985 17 40 91",
    "sg:postcode":"33207",
    "sg:province":"Asturias",
    "wof:name":"Stein  Ulrike",
    "wof:placetype":"venue"
},
  "geometry": {"coordinates":[-5.67085886,43.5393218994],"type":"Point"}
}