{
  "type": "Feature",
  "properties": {
    "iso:country":"ES",
    "sg:address":"Avda Galtzaraborda, 61",
    "sg:city":"Errenteria",
    "sg:orig_category":"Ropa Para Ni\u00d1os (al Por Menor)",
    "sg:phone":"+34 943 52 02 85",
    "sg:postcode":"20100",
    "sg:province":"Guip\u00f9zcoa",
    "wof:name":"Juan Francisco Dominguez Fari\u00f1a",
    "wof:placetype":"venue"
},
  "geometry": {"coordinates":[-1.9126739502,43.3114852905],"type":"Point"}
}