{
  "type": "Feature",
  "properties": {
    "iso:country":"ES",
    "sg:address":"Calle de Iglesia, 31",
    "sg:city":"Palomares Del Campo",
    "sg:orig_category":"Escayola Y Productos De Escayola (fabricaci\u00d3n, Al Por Mayor)",
    "sg:phone":"+34 969 27 77 11",
    "sg:postcode":"16160",
    "sg:province":"Cuenca",
    "wof:name":"Lopez La Osa Rafael",
    "wof:placetype":"venue"
},
  "geometry": {"coordinates":[-2.597990036,39.9462661743],"type":"Point"}
}