{
  "type": "Feature",
  "properties": {
    "addr:full":"Ctra Zamora, Km. 0154,5 Onzonilla Le\u00f3n 24231",
    "addr:postcode":"24231",
    "addr:street":"Ctra Zamora Km. 0154,5;Leo\u0301N",
    "iso:country":"ES",
    "sg:address":"Ctra Zamora, Km. 0154,5",
    "sg:city":"Onzonilla",
    "sg:orig_category":"Mec\u00c1nica Y Herramientas De Precisi\u00d3n",
    "sg:phone":"+34 987 20 97 07",
    "sg:postcode":"24231",
    "sg:province":"Le\u00f3n",
    "wof:name":"Hispano Europea De Pesaje S.a.l.",
    "wof:placetype":"venue"
},
  "geometry": {"coordinates":[-5.5841016769,42.5285339355],"type":"Point"}
}