{
  "type": "Feature",
  "properties": {
    "iso:country":"ES",
    "sg:address":"Calle de San Pedro, 5",
    "sg:city":"Caceres",
    "sg:orig_category":"Ropa Para Se\u00d1oras (al Por Menor)",
    "sg:phone":"+34 927 22 41 89",
    "sg:postcode":"10003",
    "sg:province":"C\u00e1ceres",
    "wof:name":"Almeida Machuca S.a.",
    "wof:placetype":"venue"
},
  "geometry": {"coordinates":[-6.3740530014,39.4734153748],"type":"Point"}
}