{
  "type": "Feature",
  "properties": {
    "addr:full":"Calle de Padre Isla, S/n Cistierna Le\u00f3n 24800",
    "addr:postcode":"24800",
    "addr:street":"Calle De Padre Isla S / N Cistierna Leo\u0301N",
    "iso:country":"ES",
    "sg:address":"Calle de Padre Isla, S/n",
    "sg:city":"Cistierna",
    "sg:orig_category":"Carnicer\u00cdas, Carnicer\u00cdas",
    "sg:phone":"+34 987 70 11 92",
    "sg:postcode":"24800",
    "sg:province":"Le\u00f3n",
    "wof:name":"Mata Alaez Enrique",
    "wof:placetype":"venue"
},
  "geometry": {"coordinates":[-5.1272211075,42.8037528992],"type":"Point"}
}