{
  "type": "Feature",
  "properties": {
    "addr:full":"Carrer de Costablanca, 5 Altea Alicante 03590",
    "addr:housenumber":"5",
    "addr:postcode":"03590",
    "addr:street":"Carrer De Costablanca",
    "iso:country":"ES",
    "sg:address":"Carrer de Costablanca, 5",
    "sg:city":"Altea",
    "sg:orig_category":"Supermercados Y Hipermercados",
    "sg:phone":"+34 965 84 34 12",
    "sg:postcode":"03590",
    "sg:province":"Alicante",
    "wof:name":"Consum Sociedad Cooperativa Limitada",
    "wof:placetype":"venue"
},
  "geometry": {"coordinates":[-0.0478440002,38.6007957458],"type":"Point"}
}