{
  "type": "Feature",
  "properties": {
    "addr:full":"Avda Alcarria (de La), 16 Alcala Henares Madrid 28806",
    "addr:housenumber":"16",
    "addr:postcode":"28806",
    "addr:street":"Avda Alcarria De La",
    "iso:country":"ES",
    "sg:address":"Avda Alcarria (de La), 16",
    "sg:city":"Alcala Henares",
    "sg:orig_category":"Agentes Generales De Seguros",
    "sg:phone":"+34 918 82 48 26",
    "sg:postcode":"28806",
    "sg:province":"Madrid",
    "wof:name":"Gonzalez Monzon Antonio",
    "wof:placetype":"venue"
},
  "geometry": {"coordinates":[-3.3626489639,40.4948730469],"type":"Point"}
}