{
  "type": "Feature",
  "properties": {
    "addr:full":"Plaz Roma, 5 Burgos Burgos 09007",
    "addr:housenumber":"5",
    "addr:postcode":"09007",
    "addr:street":"Roma",
    "iso:country":"ES",
    "sg:address":"Plaz Roma, 5",
    "sg:city":"Burgos",
    "sg:orig_category":"Telas Y Sedas (al Por Menor)",
    "sg:phone":"+34 947 21 21 78",
    "sg:postcode":"09007",
    "sg:province":"Burgos",
    "wof:name":"Poza Andres Maria Josefa",
    "wof:placetype":"venue"
},
  "geometry": {"coordinates":[-3.6495990753,42.344959259],"type":"Point"}
}