{
  "type": "Feature",
  "properties": {
    "addr:full":"Calle de Doctor Pareja Yebenes, 18 Granada Granada 18012",
    "addr:housenumber":"18",
    "addr:postcode":"18012",
    "addr:street":"Calle De Doctor Pareja Yebenes",
    "iso:country":"ES",
    "sg:address":"Calle de Doctor Pareja Yebenes, 18",
    "sg:city":"Granada",
    "sg:orig_category":"Loter\u00cda Y T\u00d3mbola",
    "sg:phone":"+34 958 20 33 53",
    "sg:postcode":"18012",
    "sg:province":"Granada",
    "wof:name":"Carrillo Sanchez Dolores",
    "wof:placetype":"venue"
},
  "geometry": {"coordinates":[-3.6095426083,37.1897926331],"type":"Point"}
}