{
  "type": "Feature",
  "properties": {
    "addr:full":"Calle de Alcazar, 10 Valderas Le\u00f3n 24220",
    "addr:housenumber":"10",
    "addr:postcode":"24220",
    "addr:street":"Calle De Alcazar",
    "iso:country":"ES",
    "sg:address":"Calle de Alcazar, 10",
    "sg:city":"Valderas",
    "sg:orig_category":"Asociaciones Y Clubs Deportivos",
    "sg:phone":"+34 987 76 24 77",
    "sg:postcode":"24220",
    "sg:province":"Le\u00f3n",
    "wof:name":"Garcia Pastor Juan Andres",
    "wof:placetype":"venue"
},
  "geometry": {"coordinates":[-5.4462752342,42.0793838501],"type":"Point"}
}