{
  "type": "Feature",
  "properties": {
    "iso:country":"ES",
    "sg:address":"Rbla Nova, 34",
    "sg:city":"Igualada",
    "sg:orig_category":"Agencias Y Asesores De Publicidad",
    "sg:phone":"+34 938 04 45 25",
    "sg:postcode":"08700",
    "sg:province":"Barcelona",
    "wof:name":"Mosaic Collage De Menage S.l.",
    "wof:placetype":"venue"
},
  "geometry": {"coordinates":[1.6155719757,41.5796585083],"type":"Point"}
}