{
  "type": "Feature",
  "properties": {
    "iso:country":"ES",
    "sg:address":"Carrer de Pintor Fortuny, 18",
    "sg:city":"Viladecans",
    "sg:orig_category":"Centros De Coordinaci\u00d3n",
    "sg:phone":"+34 936 47 31 40",
    "sg:postcode":"08840",
    "sg:province":"Barcelona",
    "wof:name":"Ariza Garcia Marina",
    "wof:placetype":"venue"
},
  "geometry": {"coordinates":[2.0236909389,41.3196792603],"type":"Point"}
}