{
  "type": "Feature",
  "properties": {
    "addr:full":"Calle de Pintor Stolz, 13 Valencia Valencia 46018",
    "addr:housenumber":"13",
    "addr:postcode":"46018",
    "addr:street":"Calle De Pintor Stolz",
    "iso:country":"ES",
    "sg:address":"Calle de Pintor Stolz, 13",
    "sg:city":"Valencia",
    "sg:orig_category":"Comercio, Reparaci\u00d3n De Motocicletas, Bicicletas Y Piezas Sueltas",
    "sg:phone":"+34 963 79 71 69",
    "sg:postcode":"46018",
    "sg:province":"Valencia",
    "wof:name":"Valmoto S.a.",
    "wof:placetype":"venue"
},
  "geometry": {"coordinates":[-0.3978587091,39.469127655],"type":"Point"}
}