{
  "type": "Feature",
  "properties": {
    "addr:full":"Avda Amaia, 6 Lamiako Vizcaya 48940",
    "addr:housenumber":"6",
    "addr:postcode":"48940",
    "addr:street":"Avda Amaia",
    "iso:country":"ES",
    "sg:address":"Avda Amaia, 6",
    "sg:city":"Lamiako",
    "sg:orig_category":"Frutas, Legumbres Frescas Y Tempranas (al Por Menor)",
    "sg:phone":"+34 944 80 23 63",
    "sg:postcode":"48940",
    "sg:province":"Vizcaya",
    "wof:name":"Garcia Perez Jose Angel",
    "wof:placetype":"venue"
},
  "geometry": {"coordinates":[-2.9860789776,43.3275489807],"type":"Point"}
}