{
  "type": "Feature",
  "properties": {
    "iso:country":"ES",
    "sg:address":"Avda General Paramo, 38",
    "sg:city":"Totana",
    "sg:orig_category":"Carnicer\u00cdas, Carnicer\u00cdas",
    "sg:phone":"+34 968 42 08 39",
    "sg:postcode":"30850",
    "sg:province":"Murcia",
    "wof:name":"Carnicas Hermanos Fuertes S.l.",
    "wof:placetype":"venue"
},
  "geometry": {"coordinates":[-1.4953989983,37.7718391418],"type":"Point"}
}