{
  "type": "Feature",
  "properties": {
    "iso:country":"ES",
    "sg:address":"Calle de Dos De Mayo (del), 17",
    "sg:city":"San Sebastian De Los Reyes",
    "sg:orig_category":"Institutos De Belleza",
    "sg:phone":"+34 916 51 99 80",
    "sg:postcode":"28700",
    "sg:province":"Madrid",
    "wof:name":"Paniagua Rico Alexandra",
    "wof:placetype":"venue"
},
  "geometry": {"coordinates":[-3.6270451546,40.5428543091],"type":"Point"}
}