{
  "type": "Feature",
  "properties": {
    "addr:full":"Calle de Robledo, 75 Azuaga Badajoz 06920",
    "addr:housenumber":"75",
    "addr:postcode":"06920",
    "addr:street":"Calle De Robledo",
    "iso:country":"ES",
    "sg:address":"Calle de Robledo, 75",
    "sg:city":"Azuaga",
    "sg:orig_category":"T\u00c9cnicos Veterinarios",
    "sg:phone":"+34 924 89 12 28",
    "sg:postcode":"06920",
    "sg:province":"Badajoz",
    "wof:name":"Sanchez De La Vaquera Prieto Manuel",
    "wof:placetype":"venue"
},
  "geometry": {"coordinates":[-5.6799287796,38.2639884949],"type":"Point"}
}