{
  "type": "Feature",
  "properties": {
    "addr:full":"Carrer de Industries, 5 Prat Llobregat Barcelona 08820",
    "addr:housenumber":"5",
    "addr:postcode":"08820",
    "addr:street":"Carrer De Industries;Llobregat",
    "iso:country":"ES",
    "sg:address":"Carrer de Industries, 5",
    "sg:city":"Prat Llobregat",
    "sg:classifiers":[
        {
            "category":"Autos & Motor Vehicles",
            "subcategory":"Automobile Sales",
            "type":"Retail Goods"
        }
    ],
    "sg:phone":"+34 933 70 74 95",
    "sg:postcode":"08820",
    "sg:province":"Barcelona",
    "wof:name":"Autoescuela Aeropuerto S.l.",
    "wof:placetype":"venue"
},
  "geometry": {"coordinates":[2.0969069004,41.3258857727],"type":"Point"}
}