{
  "type": "Feature",
  "properties": {
    "iso:country":"ES",
    "sg:address":"Calle de Nicuesa, 9",
    "sg:city":"Granada",
    "sg:orig_category":"Aparcamientos (infraestructuras, Accesorios)",
    "sg:phone":"+34 958 22 60 61",
    "sg:postcode":"18009",
    "sg:province":"Granada",
    "wof:name":"Sanchez De Los Reyes Rafael",
    "wof:placetype":"venue"
},
  "geometry": {"coordinates":[-3.5951590538,37.1710395813],"type":"Point"}
}