{
  "type": "Feature",
  "properties": {
    "iso:country":"ES",
    "sg:address":"Carrer de Numancia, 212",
    "sg:city":"Barcelona",
    "sg:orig_category":"Servicios Gsm",
    "sg:phone":"+34 932 80 21 31",
    "sg:postcode":"08017",
    "sg:province":"Barcelona",
    "sg:website":"www.rentaphone.es",
    "wof:name":"Rent A Phone Franchising S.l.",
    "wof:placetype":"venue"
},
  "geometry": {"coordinates":[2.130656004,41.3923873901],"type":"Point"}
}