{
  "type": "Feature",
  "properties": {
    "iso:country":"ES",
    "sg:address":"Calle de Alegria De Oria, 43",
    "sg:city":"Madrid",
    "sg:orig_category":"Inform\u00c1tica (estudios, Servicios, Asesor\u00cda, Formaci\u00d3n)",
    "sg:phone":"+34 913 20 45 83",
    "sg:postcode":"28027",
    "sg:province":"Madrid",
    "sg:website":"www.cleverway.org",
    "wof:name":"Cleverway S.l.",
    "wof:placetype":"venue"
},
  "geometry": {"coordinates":[-3.6333017349,40.4440498352],"type":"Point"}
}