{
  "type": "Feature",
  "properties": {
    "iso:country":"ES",
    "sg:address":"Pl Nova, 8",
    "sg:city":"Torello",
    "sg:orig_category":"Heladeros",
    "sg:phone":"+34 938 50 41 31",
    "sg:postcode":"08570",
    "sg:province":"Barcelona",
    "wof:name":"Rovira Carbonell Jordi",
    "wof:placetype":"venue"
},
  "geometry": {"coordinates":[2.2637879848,42.0475463867],"type":"Point"}
}