{
  "type": "Feature",
  "properties": {
    "iso:country":"ES",
    "sg:address":"Calle de Se\u00d1era, La, 16",
    "sg:city":"Valencia",
    "sg:orig_category":"Tubos Y Tuber\u00cdas De Goma Y Pl\u00c1stico (fabricaci\u00d3n, Al Por Mayor)",
    "sg:phone":"+34 963 33 16 15",
    "sg:postcode":"46006",
    "sg:province":"Valencia",
    "wof:name":"Valpipe S.l.",
    "wof:placetype":"venue"
},
  "geometry": {"coordinates":[-0.3635039926,39.4581756592],"type":"Point"}
}