{
  "type": "Feature",
  "properties": {
    "addr:full":"Av Riells, 18 Escala Girona 17130",
    "addr:housenumber":"18",
    "addr:postcode":"17130",
    "addr:street":"Av Riells",
    "iso:country":"ES",
    "sg:address":"Av Riells, 18",
    "sg:city":"Escala",
    "sg:orig_category":"Farmacias",
    "sg:phone":"+34 972 77 14 73",
    "sg:postcode":"17130",
    "sg:province":"Girona",
    "wof:name":"Planas Moret Maria Rosa",
    "wof:placetype":"venue"
},
  "geometry": {"coordinates":[3.1313180923,42.117149353],"type":"Point"}
}