{
  "type": "Feature",
  "properties": {
    "iso:country":"ES",
    "sg:address":"Carr Font I Vidal, De, 13",
    "sg:city":"Mao",
    "sg:orig_category":"Inform\u00c1tica (estudios, Servicios, Asesor\u00cda, Formaci\u00d3n)",
    "sg:phone":"+34 971 35 38 81",
    "sg:postcode":"07703",
    "sg:province":"Islas Baleares",
    "wof:name":"Infotelecom Networks S.l.",
    "wof:placetype":"venue"
},
  "geometry": {"coordinates":[4.2531890869,39.8877220154],"type":"Point"}
}