{
  "type": "Feature",
  "properties": {
    "addr:full":"Pase Doctor Torres Villarroel, 2 Salamanca Salamanca 37005",
    "addr:housenumber":"2",
    "addr:postcode":"37005",
    "addr:street":"Doctor Torres Villarroel",
    "iso:country":"ES",
    "sg:address":"Pase Doctor Torres Villarroel, 2",
    "sg:city":"Salamanca",
    "sg:orig_category":"Institutos De Belleza",
    "sg:phone":"+34 923 12 28 97",
    "sg:postcode":"37005",
    "sg:province":"Salamanca",
    "wof:name":"Gorjon Notario Clara",
    "wof:placetype":"venue"
},
  "geometry": {"coordinates":[-5.6634788513,40.9706192017],"type":"Point"}
}