{
  "type": "Feature",
  "properties": {
    "addr:full":"Carrer de Mar, 9 Malgrat Mar Barcelona 08380",
    "addr:housenumber":"9",
    "addr:postcode":"08380",
    "addr:street":"Carrer De Mar",
    "iso:country":"ES",
    "sg:address":"Carrer de Mar, 9",
    "sg:city":"Malgrat Mar",
    "sg:orig_category":"Ropa Para Se\u00d1oras (al Por Menor)",
    "sg:phone":"+34 937 65 39 71",
    "sg:postcode":"08380",
    "sg:province":"Barcelona",
    "wof:name":"Pardo Ramirez Yolanda",
    "wof:placetype":"venue"
},
  "geometry": {"coordinates":[2.7417800426,41.6456375122],"type":"Point"}
}