{
  "type": "Feature",
  "properties": {
    "addr:full":"Plaz Alcalde Jose Gonzalez, 2 Bornos C\u00e1diz 11640",
    "addr:housenumber":"2",
    "addr:postcode":"11640",
    "addr:street":"Plaz Alcalde Jose Gonzalez;Ca\u0301Diz",
    "iso:country":"ES",
    "sg:address":"Plaz Alcalde Jose Gonzalez, 2",
    "sg:city":"Bornos",
    "sg:orig_category":"Ense\u00d1anza, Formaci\u00d3n Profesional: Aprendizaje",
    "sg:phone":"+34 956 71 21 79",
    "sg:postcode":"11640",
    "sg:province":"C\u00e1diz",
    "wof:name":"Ayuntamiento De Bornos",
    "wof:placetype":"venue"
},
  "geometry": {"coordinates":[-5.7194523811,36.8490219116],"type":"Point"}
}