{
  "type": "Feature",
  "properties": {
    "iso:country":"ES",
    "sg:address":"Pl Corona, 6",
    "sg:city":"Granollers",
    "sg:orig_category":"Notarios",
    "sg:phone":"+34 938 79 44 10",
    "sg:postcode":"08402",
    "sg:province":"Barcelona",
    "wof:name":"Vidal Davydoff Maria Angeles",
    "wof:placetype":"venue"
},
  "geometry": {"coordinates":[2.2887299061,41.6059188843],"type":"Point"}
}