{
  "type": "Feature",
  "properties": {
    "iso:country":"ES",
    "sg:address":"Campillo, 5",
    "sg:city":"Cehegin",
    "sg:orig_category":"Ropa De Casa (fabricaci\u00d3n, Al Por Mayor)",
    "sg:phone":"+34 968 72 36 70",
    "sg:postcode":"30430",
    "sg:province":"Murcia",
    "wof:name":"Morago Textil Hogar S.l.",
    "wof:placetype":"venue"
},
  "geometry": {"coordinates":[-1.7547450066,38.1397132874],"type":"Point"}
}