{
  "type": "Feature",
  "properties": {
    "iso:country":"ES",
    "sg:address":"Carrer de Desprats, 30",
    "sg:city":"Morell",
    "sg:orig_category":"Pensiones Familiares",
    "sg:phone":"+34 977 84 03 32",
    "sg:postcode":"43760",
    "sg:province":"Tarragona",
    "wof:name":"Rubies Vallve Josepa",
    "wof:placetype":"venue"
},
  "geometry": {"coordinates":[1.2094180584,41.1907043457],"type":"Point"}
}