{
  "type": "Feature",
  "properties": {
    "iso:country":"ES",
    "sg:address":"Calle de Corazon De Maria, 6",
    "sg:city":"Madrid",
    "sg:orig_category":"Teatro, Ballet, Danza (agrupaciones, Compa\u00d1\u00cdas)",
    "sg:phone":"+34 914 15 25 25",
    "sg:postcode":"28002",
    "sg:province":"Madrid",
    "wof:name":"La Huella Sonora S.l.",
    "wof:placetype":"venue"
},
  "geometry": {"coordinates":[-3.671022892,40.4405097961],"type":"Point"}
}