{
  "type": "Feature",
  "properties": {
    "iso:country":"ES",
    "sg:address":"Cra. Nal. Tres-cents Quaranta, Km. 1192,5",
    "sg:city":"Bellvei",
    "sg:orig_category":"Agentes, Concesionarios Y Sucursales De Camiones Y Veh\u00cdculos Industriales",
    "sg:phone":"+34 977 66 75 83",
    "sg:postcode":"43719",
    "sg:province":"Tarragona",
    "wof:name":"Auto Comercial Penedes S.l.",
    "wof:placetype":"venue"
},
  "geometry": {"coordinates":[1.5798250437,41.2386817932],"type":"Point"}
}