{
  "type": "Feature",
  "properties": {
    "iso:country":"ES",
    "sg:address":"Calle de San Juan, 9",
    "sg:city":"Burgos",
    "sg:orig_category":"Arquitectos",
    "sg:phone":"+34 947 20 40 03",
    "sg:postcode":"09003",
    "sg:province":"Burgos",
    "wof:name":"Francisco Javier Mu\u00f1oz Hernandez S.l.",
    "wof:placetype":"venue"
},
  "geometry": {"coordinates":[-3.699420929,42.3429908752],"type":"Point"}
}