{
  "type": "Feature",
  "properties": {
    "iso:country":"ES",
    "sg:address":"Calle de Romero, 4",
    "sg:city":"Barbastro",
    "sg:orig_category":"Peluquer\u00cdas, Peluquer\u00cda Mixta",
    "sg:phone":"+34 974 31 35 01",
    "sg:postcode":"22300",
    "sg:province":"Huesca",
    "wof:name":"Arg\u00fceso Salas Rosario",
    "wof:placetype":"venue"
},
  "geometry": {"coordinates":[0.1307796985,42.0187110901],"type":"Point"}
}