{
  "type": "Feature",
  "properties": {
    "addr:full":"Avda Pais Valencia (del), S/n Onda Castell\u00f3n 12200",
    "addr:housenumber":"/ n",
    "addr:postcode":"12200",
    "addr:street":"Avda Pais;Del S;Castello\u0301N",
    "iso:country":"ES",
    "sg:address":"Avda Pais Valencia (del), S/n",
    "sg:city":"Onda",
    "sg:orig_category":"Cajas De Ahorro",
    "sg:phone":"+34 964 77 22 59",
    "sg:postcode":"12200",
    "sg:province":"Castell\u00f3n",
    "wof:name":"Caixa D'estalvis I Pensions De Barcelona",
    "wof:placetype":"venue"
},
  "geometry": {"coordinates":[-0.2651939988,39.9650650024],"type":"Point"}
}