{
  "type": "Feature",
  "properties": {
    "iso:country":"ES",
    "sg:address":"Calle de Cervantes, 6",
    "sg:city":"Villanueva Gallego",
    "sg:orig_category":"Poller\u00cda Y Caza (al Por Menor)",
    "sg:phone":"+34 976 18 50 30",
    "sg:postcode":"50830",
    "sg:province":"Zaragoza",
    "wof:name":"Guillen Gracia S.l.",
    "wof:placetype":"venue"
},
  "geometry": {"coordinates":[-0.8237931132,41.7689971924],"type":"Point"}
}