{
  "type": "Feature",
  "properties": {
    "addr:full":"Afueras, S/n Gargaligas Badajoz 06711",
    "addr:postcode":"06711",
    "addr:street":"Afueras S / N Gargaligas",
    "iso:country":"ES",
    "sg:address":"Afueras, S/n",
    "sg:city":"Gargaligas",
    "sg:orig_category":"Agricultores, Agricultores",
    "sg:phone":"+34 924 83 22 52",
    "sg:postcode":"06711",
    "sg:province":"Badajoz",
    "wof:name":"Herencia Yacente De Pilar Moreno Tozer",
    "wof:placetype":"venue"
},
  "geometry": {"coordinates":[-5.6529188156,39.0546150208],"type":"Point"}
}