{
  "type": "Feature",
  "properties": {
    "addr:full":"Barr Aperribai, 11 Agirre-aperribai Vizcaya 48960",
    "addr:housenumber":"11",
    "addr:postcode":"48960",
    "addr:street":"Aperribai",
    "iso:country":"ES",
    "sg:address":"Barr Aperribai, 11",
    "sg:city":"Agirre-aperribai",
    "sg:orig_category":"Molduras, Junquillos, Listones Y Molduras Perforadas",
    "sg:phone":"+34 944 40 80 56",
    "sg:postcode":"48960",
    "sg:province":"Vizcaya",
    "wof:name":"Ramos Lopez Juan",
    "wof:placetype":"venue"
},
  "geometry": {"coordinates":[-2.8723731041,43.2396507263],"type":"Point"}
}