{
  "type": "Feature",
  "properties": {
    "iso:country":"ES",
    "sg:address":"Calle de Poeta Gerardo Diego, 9",
    "sg:city":"Santander",
    "sg:orig_category":"Doctores En Medicina",
    "sg:phone":"+34 942 33 77 08",
    "sg:postcode":"39011",
    "sg:province":"Cantabria",
    "wof:name":"Delgado Solar Estela",
    "wof:placetype":"venue"
},
  "geometry": {"coordinates":[-3.8429589272,43.4573974609],"type":"Point"}
}