{
  "type": "Feature",
  "properties": {
    "iso:country":"ES",
    "sg:address":"Calle de Sangenis, 74",
    "sg:city":"Zaragoza",
    "sg:orig_category":"Comercio De Piezas De Recambio Y De Accesorios De Veh\u00cdculos, Veh\u00cdculos Industriales",
    "sg:phone":"+34 976 33 78 54",
    "sg:postcode":"50010",
    "sg:province":"Zaragoza",
    "wof:name":"Nakra S.l.",
    "wof:placetype":"venue"
},
  "geometry": {"coordinates":[-0.9033340216,41.649684906],"type":"Point"}
}