{
  "type": "Feature",
  "properties": {
    "addr:full":"Pl. Poeta M. Naval, 1 Rota C\u00e1diz 11520",
    "addr:housenumber":"1",
    "addr:postcode":"11520",
    "addr:street":"Pl. Poeta M. Naval;Ca\u0301Diz",
    "iso:country":"ES",
    "sg:address":"Pl. Poeta M. Naval, 1",
    "sg:city":"Rota",
    "sg:orig_category":"Delegados, Agentes De Tr\u00c1nsito, Auxiliares De Transporte Internacional",
    "sg:phone":"+34 956 81 58 99",
    "sg:postcode":"11520",
    "sg:province":"C\u00e1diz",
    "wof:name":"Gonzalez Bernal Manuel",
    "wof:placetype":"venue"
},
  "geometry": {"coordinates":[-6.364177227,36.6211929321],"type":"Point"}
}