{
  "type": "Feature",
  "properties": {
    "addr:full":"Calle de Moises Alberto, S/n Taco Santa Cruz De Tenerife 38108",
    "addr:housenumber":"s / n",
    "addr:postcode":"38108",
    "addr:street":"Calle De Moises Alberto",
    "iso:country":"ES",
    "sg:address":"Calle de Moises Alberto, S/n",
    "sg:city":"Taco",
    "sg:orig_category":"Sanatorios M\u00c9dico",
    "sg:phone":"+34 922 62 96 72",
    "sg:postcode":"38108",
    "sg:province":"Santa Cruz De Tenerife",
    "wof:name":"Gobierno De Canarias",
    "wof:placetype":"venue"
},
  "geometry": {"coordinates":[-16.3006381989,28.4462852478],"type":"Point"}
}