{
  "type": "Feature",
  "properties": {
    "addr:full":"Carr Calvari, 2 Cervia De Les Garrigues Lleida 25460",
    "addr:housenumber":"2",
    "addr:postcode":"25460",
    "addr:street":"Carr Calvari",
    "iso:country":"ES",
    "sg:address":"Carr Calvari, 2",
    "sg:city":"Cervia De Les Garrigues",
    "sg:orig_category":"Farmacias",
    "sg:phone":"+34 973 17 80 33",
    "sg:postcode":"25460",
    "sg:province":"Lleida",
    "wof:name":"Reyes Moncada Maria Angeles",
    "wof:placetype":"venue"
},
  "geometry": {"coordinates":[0.8608580232,41.4247932434],"type":"Point"}
}