{
  "type": "Feature",
  "properties": {
    "addr:full":"Avda Reconquista, 6 Toledo Toledo 45004",
    "addr:housenumber":"6",
    "addr:postcode":"45004",
    "addr:street":"Avda Reconquista",
    "iso:country":"ES",
    "sg:address":"Avda Reconquista, 6",
    "sg:city":"Toledo",
    "sg:orig_category":"Doctores En Medicina",
    "sg:phone":"+34 925 22 27 46",
    "sg:postcode":"45004",
    "sg:province":"Toledo",
    "wof:name":"Jou Rivera Fernando",
    "wof:placetype":"venue"
},
  "geometry": {"coordinates":[-4.0278048515,39.8643608093],"type":"Point"}
}