{
  "type": "Feature",
  "properties": {
    "iso:country":"ES",
    "sg:address":"Carr Fluvia, 10",
    "sg:city":"Guissona",
    "sg:orig_category":"Pescader\u00cdas (al Por Menor)",
    "sg:phone":"+34 973 55 01 80",
    "sg:postcode":"25210",
    "sg:province":"Lleida",
    "wof:name":"Diaz Navarrete Meritxell",
    "wof:placetype":"venue"
},
  "geometry": {"coordinates":[1.289041996,41.7846336365],"type":"Point"}
}