{
  "type": "Feature",
  "properties": {
    "addr:full":"Carrer de Arago, 24 Palma Islas Baleares 07006",
    "addr:housenumber":"24",
    "addr:postcode":"07006",
    "addr:street":"Carrer De Arago",
    "iso:country":"ES",
    "sg:address":"Carrer de Arago, 24",
    "sg:city":"Palma",
    "sg:orig_category":"Agencias De Viajes",
    "sg:phone":"+34 971 46 87 63",
    "sg:postcode":"07006",
    "sg:province":"Islas Baleares",
    "wof:name":"Viajes Mundo Jet S.l.",
    "wof:placetype":"venue"
},
  "geometry": {"coordinates":[2.6589739323,39.5749359131],"type":"Point"}
}