{
  "type": "Feature",
  "properties": {
    "iso:country":"ES",
    "sg:address":"Carr Pla De L'arc (del), 83",
    "sg:city":"Lliria",
    "sg:orig_category":"Molduras, Junquillos, Listones Y Molduras Perforadas",
    "sg:phone":"+34 962 78 26 89",
    "sg:postcode":"46160",
    "sg:province":"Valencia",
    "wof:name":"Perez Mu\u00d1oz Amparo",
    "wof:placetype":"venue"
},
  "geometry": {"coordinates":[-0.5913758874,39.634311676],"type":"Point"}
}