{
  "type": "Feature",
  "properties": {
    "addr:full":"Carrer de Buigas, 19 Barcelona Barcelona 08017",
    "addr:housenumber":"19",
    "addr:postcode":"08017",
    "addr:street":"Carrer De Buigas",
    "iso:country":"ES",
    "sg:address":"Carrer de Buigas, 19",
    "sg:city":"Barcelona",
    "sg:orig_category":"M\u00c9dicos: Neurolog\u00cda",
    "sg:phone":"+34 932 80 04 17",
    "sg:postcode":"08017",
    "sg:province":"Barcelona",
    "wof:name":"Neurofisiologia Clinica Dr Sanso I Vila Bado S.l.",
    "wof:placetype":"venue"
},
  "geometry": {"coordinates":[2.1308660507,41.3937187195],"type":"Point"}
}