{
  "type": "Feature",
  "properties": {
    "iso:country":"ES",
    "sg:address":"Fontelas, 3",
    "sg:city":"Burres",
    "sg:orig_category":"Agricultura: Abastecimiento Y Cosechado (negocio)",
    "sg:phone":"+34 981 50 01 28",
    "sg:postcode":"15819",
    "sg:province":"A Coru\u00f1a",
    "wof:name":"Sat Fontelas",
    "wof:placetype":"venue"
},
  "geometry": {"coordinates":[-8.1643543243,42.9630203247],"type":"Point"}
}