{
  "type": "Feature",
  "properties": {
    "addr:full":"Calle de Capitan Haya, 56 Madrid Madrid 28020",
    "addr:housenumber":"56",
    "addr:postcode":"madrid;28020",
    "addr:street":"Calle De Capitan Haya",
    "iso:country":"ES",
    "sg:address":"Calle de Capitan Haya, 56",
    "sg:city":"Madrid",
    "sg:orig_category":"Arquitectos",
    "sg:phone":"+34 915 70 95 90",
    "sg:postcode":"28020",
    "sg:province":"Madrid",
    "wof:name":"Urbanizadora Olmos Aguado S.l.",
    "wof:placetype":"venue"
},
  "geometry": {"coordinates":[-3.6914999485,40.46251297],"type":"Point"}
}