{
  "type": "Feature",
  "properties": {
    "iso:country":"ES",
    "sg:address":"Calle de Sebastian, 1",
    "sg:city":"Pulpi",
    "sg:orig_category":"Alquiler De Gr\u00daas",
    "sg:phone":"+34 950 46 41 31",
    "sg:postcode":"04640",
    "sg:province":"Almer\u00eda",
    "wof:name":"Talleres Y Gruas Gonzalez S.l.",
    "wof:placetype":"venue"
},
  "geometry": {"coordinates":[-1.7501260042,37.4065856934],"type":"Point"}
}