{
  "type": "Feature",
  "properties": {
    "addr:full":"Calle de Tribulete, 27 Madrid Madrid 28012",
    "addr:housenumber":"27",
    "addr:postcode":"madrid;28012",
    "addr:street":"Calle De Tribulete",
    "iso:country":"ES",
    "sg:address":"Calle de Tribulete, 27",
    "sg:city":"Madrid",
    "sg:orig_category":"Ropa Para Se\u00d1oras (al Por Menor)",
    "sg:phone":"+34 914 68 45 04",
    "sg:postcode":"28012",
    "sg:province":"Madrid",
    "wof:name":"Salas Revilla Maria Del Carmen",
    "wof:placetype":"venue"
},
  "geometry": {"coordinates":[-3.7035689354,40.4071960449],"type":"Point"}
}