{
  "type": "Feature",
  "properties": {
    "addr:full":"Calle de Amor De Dios, 1 Valladolid Valladolid 47011",
    "addr:housenumber":"1",
    "addr:postcode":"47011",
    "addr:street":"Calle De Amor De Dios",
    "iso:country":"ES",
    "sg:address":"Calle de Amor De Dios, 1",
    "sg:city":"Valladolid",
    "sg:orig_category":"Molduras, Junquillos, Listones Y Molduras Perforadas",
    "sg:phone":"+34 983 25 55 92",
    "sg:postcode":"47011",
    "sg:province":"Valladolid",
    "wof:name":"Blanco Rico Maximo Luis",
    "wof:placetype":"venue"
},
  "geometry": {"coordinates":[-4.7143578529,41.6596183777],"type":"Point"}
}