{
  "type": "Feature",
  "properties": {
    "iso:country":"ES",
    "sg:address":"Curras, 10",
    "sg:city":"Seixo",
    "sg:orig_category":"Marketing Telef\u00d3nico",
    "sg:phone":"+34 986 70 41 53",
    "sg:postcode":"36913",
    "sg:province":"Pontevedra",
    "wof:name":"Galipack System S.l",
    "wof:placetype":"venue"
},
  "geometry": {"coordinates":[-8.7775201797,42.2642784119],"type":"Point"}
}