{
  "type": "Feature",
  "properties": {
    "iso:country":"ES",
    "sg:address":"C/ Manuel Alcaraz Mora, 11",
    "sg:city":"Elche",
    "sg:orig_category":"Propiedad Industrial: Patentes De Inventos, Marcas, Modelos, Dise\u00d1os",
    "sg:phone":"+34 966 63 19 55",
    "sg:postcode":"03204",
    "sg:province":"Alicante",
    "wof:name":"Comunidad Propietarios Manuel Alcaraz Mora",
    "wof:placetype":"venue"
},
  "geometry": {"coordinates":[-0.7024739981,38.2546386719],"type":"Point"}
}