{
  "type": "Feature",
  "properties": {
    "addr:full":"Avda Santa Cruz, 6 Montiel Ciudad Real 13326",
    "addr:housenumber":"6",
    "addr:postcode":"13326",
    "addr:street":"Avda Santa Cruz",
    "iso:country":"ES",
    "sg:address":"Avda Santa Cruz, 6",
    "sg:city":"Montiel",
    "sg:orig_category":"Negocio De Materiales De Construcci\u00d3n",
    "sg:phone":"+34 926 35 30 93",
    "sg:postcode":"13326",
    "sg:province":"Ciudad Real",
    "wof:name":"Catalan Perez Alfonso",
    "wof:placetype":"venue"
},
  "geometry": {"coordinates":[-2.8641059399,38.6960601807],"type":"Point"}
}