{
  "type": "Feature",
  "properties": {
    "iso:country":"ES",
    "sg:address":"Calle de Mar, 40",
    "sg:city":"Valencia",
    "sg:orig_category":"Asesor\u00cda Sobre Comunicaci\u00d3n De Empresas",
    "sg:phone":"+34 963 92 10 60",
    "sg:postcode":"46003",
    "sg:province":"Valencia",
    "wof:name":"Legal Reports S.l.",
    "wof:placetype":"venue"
},
  "geometry": {"coordinates":[-0.3721050024,39.4735603333],"type":"Point"}
}