{
  "type": "Feature",
  "properties": {
    "addr:full":"Calle de Catalina Gibaja, 2 Ortuella Vizcaya 48530",
    "addr:housenumber":"2",
    "addr:postcode":"48530",
    "addr:street":"Calle De Catalina Gibaja",
    "iso:country":"ES",
    "sg:address":"Calle de Catalina Gibaja, 2",
    "sg:city":"Ortuella",
    "sg:orig_category":"Molduras, Junquillos, Listones Y Molduras Perforadas",
    "sg:phone":"+34 946 35 32 87",
    "sg:postcode":"48530",
    "sg:province":"Vizcaya",
    "wof:name":"Jibaja S.l.",
    "wof:placetype":"venue"
},
  "geometry": {"coordinates":[-3.0529015064,43.3091087341],"type":"Point"}
}