{
  "type": "Feature",
  "properties": {
    "iso:country":"ES",
    "sg:address":"Calle de Alhambra, 8",
    "sg:city":"Gojar",
    "sg:orig_category":"Reposter\u00cdas",
    "sg:phone":"+34 958 59 78 01",
    "sg:postcode":"18150",
    "sg:province":"Granada",
    "wof:name":"Casas Miranda Salvador",
    "wof:placetype":"venue"
},
  "geometry": {"coordinates":[-3.6055850983,37.103061676],"type":"Point"}
}