{
  "type": "Feature",
  "properties": {
    "addr:full":"Plaz Espa\u00d1a, 6 Valladolid Valladolid 47001",
    "addr:housenumber":"6",
    "addr:postcode":"47001",
    "addr:street":"Plaz Espan\u0303A",
    "iso:country":"ES",
    "sg:address":"Plaz Espa\u00d1a, 6",
    "sg:city":"Valladolid",
    "sg:orig_category":"Notarios",
    "sg:phone":"+34 983 29 82 88",
    "sg:postcode":"47001",
    "sg:province":"Valladolid",
    "wof:name":"Sagardia Navarro Manuel",
    "wof:placetype":"venue"
},
  "geometry": {"coordinates":[-4.7247400284,41.6491508484],"type":"Point"}
}