{
  "type": "Feature",
  "properties": {
    "addr:full":"A Eirexe, S/n Ponte Dena Pontevedra 36967",
    "addr:housenumber":"s / n",
    "addr:postcode":"36967",
    "addr:street":"Eirexe",
    "iso:country":"ES",
    "sg:address":"A Eirexe, S/n",
    "sg:city":"Ponte Dena",
    "sg:orig_category":"Iglesia Cat\u00d3lica",
    "sg:phone":"+34 986 74 31 07",
    "sg:postcode":"36967",
    "sg:province":"Pontevedra",
    "wof:name":"Arzobispado De Santiago",
    "wof:placetype":"venue"
},
  "geometry": {"coordinates":[-8.8180093765,42.4482765198],"type":"Point"}
}