{
  "type": "Feature",
  "properties": {
    "addr:full":"Calle de Duque De Alba, 4 Madrid Madrid 28012",
    "addr:housenumber":"4",
    "addr:postcode":"28012",
    "addr:street":"Calle De Duque De Alba",
    "iso:country":"ES",
    "sg:address":"Calle de Duque De Alba, 4",
    "sg:city":"Madrid",
    "sg:classifiers":[
        {
            "category":"Cinema",
            "subcategory":"Movie Theater",
            "type":"Entertainment"
        }
    ],
    "sg:phone":"+34 913 69 18 65",
    "sg:postcode":"28012",
    "sg:province":"Madrid",
    "sg:tags":[
        "salas",
        "de",
        "cine"
    ],
    "wof:name":"Arrendamientos Industriales S. A.",
    "wof:placetype":"venue"
},
  "geometry": {"coordinates":[-3.7057983875,40.4119224548],"type":"Point"}
}