{
  "type": "Feature",
  "properties": {
    "iso:country":"ES",
    "sg:address":"De La Industria(p I La Vi\u00f1uela), 21",
    "sg:city":"Lucena",
    "sg:orig_category":"Electricidad: Equipos Industriales, Componentes (fabricaci\u00d3n)",
    "sg:phone":"+34 957 50 37 27",
    "sg:postcode":"14900",
    "sg:province":"C\u00f3rdoba",
    "wof:name":"Suministros Electricos Leon Perez S.l.",
    "wof:placetype":"venue"
},
  "geometry": {"coordinates":[-4.4826588631,37.4169845581],"type":"Point"}
}