{
  "type": "Feature",
  "properties": {
    "addr:full":"Calle de Jeronimo Del Moral (de), 59 Ciempozuelos Madrid 28350",
    "addr:housenumber":"59",
    "addr:postcode":"28350",
    "addr:street":"Calle De Jeronimo Del Moral De",
    "iso:country":"ES",
    "sg:address":"Calle de Jeronimo Del Moral (de), 59",
    "sg:city":"Ciempozuelos",
    "sg:orig_category":"Pintores",
    "sg:phone":"+34 918 93 28 39",
    "sg:postcode":"28350",
    "sg:province":"Madrid",
    "wof:name":"Vazquez Bartolome Antonio",
    "wof:placetype":"venue"
},
  "geometry": {"coordinates":[-3.6223421097,40.1638717651],"type":"Point"}
}