{
  "type": "Feature",
  "properties": {
    "addr:full":"Calle de Boyaca, 4 Madrid Madrid 28033",
    "addr:housenumber":"4",
    "addr:postcode":"28033",
    "addr:street":"Calle De Boyaca",
    "iso:country":"ES",
    "sg:address":"Calle de Boyaca, 4",
    "sg:city":"Madrid",
    "sg:orig_category":"Bisuter\u00cda, Joyer\u00cda, Relojer\u00cda (al Por Menor)",
    "sg:phone":"+34 913 81 07 48",
    "sg:postcode":"28033",
    "sg:province":"Madrid",
    "wof:name":"Martinez Redondo Antonio",
    "wof:placetype":"venue"
},
  "geometry": {"coordinates":[-3.6373181343,40.4721183777],"type":"Point"}
}