{
  "type": "Feature",
  "properties": {
    "addr:full":"Av Lluis Pericot, 17 Girona Girona 17003",
    "addr:housenumber":"17",
    "addr:postcode":"17003",
    "addr:street":"Av Lluis Pericot",
    "iso:country":"ES",
    "sg:address":"Av Lluis Pericot, 17",
    "sg:city":"Girona",
    "sg:orig_category":"Material Y Suministros Para Veterinarios",
    "sg:phone":"+34 972 22 71 00",
    "sg:postcode":"17003",
    "sg:province":"Girona",
    "wof:name":"Canis Complements Sc",
    "wof:placetype":"venue"
},
  "geometry": {"coordinates":[2.8247361183,41.9726715088],"type":"Point"}
}