{
  "type": "Feature",
  "properties": {
    "addr:full":"Polig Ind Dos, 27 Pu\u00e7ol Valencia 46530",
    "addr:postcode":"46530",
    "iso:country":"ES",
    "sg:address":"Polig Ind Dos, 27",
    "sg:city":"Pu\u00e7ol",
    "sg:orig_category":"Fabricaci\u00d3n, Comercio De Muebles En Ca\u00d1a, Mimbre",
    "sg:phone":"+34 961 46 48 23",
    "sg:postcode":"46530",
    "sg:province":"Valencia",
    "sg:website":"www.agricheap.com",
    "wof:name":"Agricheap, S.l.",
    "wof:placetype":"venue"
},
  "geometry": {"coordinates":[-0.3042778075,39.6152801514],"type":"Point"}
}