{
  "type": "Feature",
  "properties": {
    "iso:country":"ES",
    "sg:address":"Calle de General Mola, S/n",
    "sg:city":"Recas",
    "sg:orig_category":"Distribuci\u00d3n De Petr\u00d3leo Y Derivados",
    "sg:phone":"+34 925 52 23 33",
    "sg:postcode":"45211",
    "sg:province":"Toledo",
    "wof:name":"Zapardiel Carrasco Jose Luis",
    "wof:placetype":"venue"
},
  "geometry": {"coordinates":[-3.9900479317,40.0495033264],"type":"Point"}
}