{
  "type": "Feature",
  "properties": {
    "iso:country":"ES",
    "sg:address":"Edif Mirall Balear, S/n",
    "sg:city":"Son San Juan",
    "sg:orig_category":"Aeropuertos Y Servicios Aeroportuarios",
    "sg:phone":"+34 971 40 88 88",
    "sg:postcode":"07611",
    "sg:province":"Islas Baleares",
    "wof:name":"Aircomp S.l.",
    "wof:placetype":"venue"
},
  "geometry": {"coordinates":[3.0395543575,39.5959358215],"type":"Point"}
}