{
  "type": "Feature",
  "properties": {
    "addr:full":"Avda Jose Antonio, 10 Laredo Cantabria 39770",
    "addr:housenumber":"10",
    "addr:postcode":"39770",
    "addr:street":"Avda Jose Antonio",
    "iso:country":"ES",
    "sg:address":"Avda Jose Antonio, 10",
    "sg:city":"Laredo",
    "sg:orig_category":"Molduras, Junquillos, Listones Y Molduras Perforadas",
    "sg:phone":"+34 942 60 70 93",
    "sg:postcode":"39770",
    "sg:province":"Cantabria",
    "wof:name":"Abad Franco Jose Luis",
    "wof:placetype":"venue"
},
  "geometry": {"coordinates":[-3.415014,43.409157],"type":"Point"}
}