{
  "type": "Feature",
  "properties": {
    "iso:country":"ES",
    "sg:address":"Pase Zorrilla, 158",
    "sg:city":"Valladolid",
    "sg:orig_category":"Estancos",
    "sg:phone":"+34 983 23 58 69",
    "sg:postcode":"47006",
    "sg:province":"Valladolid",
    "wof:name":"Gonzalez Rodriguez Isaura",
    "wof:placetype":"venue"
},
  "geometry": {"coordinates":[-4.7401123047,41.6336555481],"type":"Point"}
}