{
  "type": "Feature",
  "properties": {
    "iso:country":"ES",
    "sg:address":"Iglesia, 5",
    "sg:city":"Sanxenxo",
    "sg:orig_category":"Reposter\u00cdas",
    "sg:phone":"+34 986 72 39 24",
    "sg:postcode":"36969",
    "sg:province":"Pontevedra",
    "wof:name":"Rodriguez Arosa Isidro",
    "wof:placetype":"venue"
},
  "geometry": {"coordinates":[-8.8015260696,42.4287567139],"type":"Point"}
}