{
  "type": "Feature",
  "properties": {
    "iso:country":"ES",
    "sg:address":"Calle de Navarra, 1",
    "sg:city":"Castellon",
    "sg:orig_category":"Agencias De Viajes",
    "sg:phone":"+34 964 25 14 70",
    "sg:postcode":"12002",
    "sg:province":"Castell\u00f3n",
    "sg:website":"www.viajesiberia.com",
    "wof:name":"Viajes Iberia S.a.",
    "wof:placetype":"venue"
},
  "geometry": {"coordinates":[-0.0407680012,39.9843940735],"type":"Point"}
}