{
  "type": "Feature",
  "properties": {
    "iso:country":"ES",
    "sg:address":"C/ Monserrate Guilabert Valero, 51",
    "sg:city":"Elche",
    "sg:orig_category":"Abogados",
    "sg:phone":"+34 966 67 28 03",
    "sg:postcode":"03205",
    "sg:province":"Alicante",
    "wof:name":"Olivares Sanchez Concepcion",
    "wof:placetype":"venue"
},
  "geometry": {"coordinates":[-0.7123450041,38.2687568665],"type":"Point"}
}