{
  "type": "Feature",
  "properties": {
    "addr:full":"Calle de Doctor Severo Ochoa Del, 19 Aviles Asturias 33401",
    "addr:housenumber":"19",
    "addr:postcode":"33401",
    "addr:street":"Calle De Doctor Severo Ochoa Del",
    "iso:country":"ES",
    "sg:address":"Calle de Doctor Severo Ochoa Del, 19",
    "sg:city":"Aviles",
    "sg:orig_category":"Sociedades, Compa\u00d1\u00cdas Aseguradoras",
    "sg:phone":"+34 985 56 96 13",
    "sg:postcode":"33401",
    "sg:province":"Asturias",
    "sg:website":"www.mapfre.com",
    "wof:name":"Mapfre Servicios De Informatica S.a.",
    "wof:placetype":"venue"
},
  "geometry": {"coordinates":[-5.9295954704,43.5553474426],"type":"Point"}
}