{
  "type": "Feature",
  "properties": {
    "addr:full":"Calle de Serafin Ajuria, 2 Vitoria-gasteiz \u00c1lava 01008",
    "addr:housenumber":"2",
    "addr:postcode":"01008",
    "addr:street":"Calle De Serafin Ajuria",
    "iso:country":"ES",
    "sg:address":"Calle de Serafin Ajuria, 2",
    "sg:city":"Vitoria-gasteiz",
    "sg:orig_category":"Estudios Y Construcci\u00d3n De Acuarios Y Viveros",
    "sg:phone":"+34 945 22 00 21",
    "sg:postcode":"01008",
    "sg:province":"\u00c1lava",
    "wof:name":"Eva Maria Pe\u00f1a Alfonso",
    "wof:placetype":"venue"
},
  "geometry": {"coordinates":[-2.6850390434,42.8486366272],"type":"Point"}
}