{
  "type": "Feature",
  "properties": {
    "addr:full":"Carrer de Jaume Abril, 2 Viladecans Barcelona 08840",
    "addr:housenumber":"2",
    "addr:postcode":"08840",
    "addr:street":"Carrer De Jaume Abril",
    "iso:country":"ES",
    "sg:address":"Carrer de Jaume Abril, 2",
    "sg:city":"Viladecans",
    "sg:classifiers":[
        {
            "category":"Government",
            "subcategory":"Office",
            "type":"Public Place"
        }
    ],
    "sg:phone":"+34 936 47 32 30",
    "sg:postcode":"08840",
    "sg:province":"Barcelona",
    "sg:tags":[
        "interior",
        "administraci\u00d3n",
        "en"
    ],
    "wof:name":"Direccion General De La Policia",
    "wof:placetype":"venue"
},
  "geometry": {"coordinates":[2.0198740959,41.3160629272],"type":"Point"}
}