{
  "type": "Feature",
  "properties": {
    "iso:country":"ES",
    "sg:address":"Carrer de Doctor Pi I Sunyer, 4",
    "sg:city":"Roses",
    "sg:orig_category":"Confiter\u00cdas, Chocolater\u00cdas (al Por Menor)",
    "sg:phone":"+34 972 25 62 83",
    "sg:postcode":"17480",
    "sg:province":"Girona",
    "wof:name":"Sala Comas Ramon",
    "wof:placetype":"venue"
},
  "geometry": {"coordinates":[3.1754560471,42.2627868652],"type":"Point"}
}