{
  "type": "Feature",
  "properties": {
    "iso:country":"ES",
    "sg:address":"Avda Perez Galdos, 2",
    "sg:city":"Novelda",
    "sg:orig_category":"Distribuci\u00d3n De Petr\u00d3leo Y Derivados",
    "sg:phone":"+34 965 60 67 12",
    "sg:postcode":"03660",
    "sg:province":"Alicante",
    "wof:name":"Repsol Ypf S.a.",
    "wof:placetype":"venue"
},
  "geometry": {"coordinates":[-0.757758975,38.3849487305],"type":"Point"}
}