{
  "type": "Feature",
  "properties": {
    "iso:country":"ES",
    "sg:address":"Pase Farola, 5",
    "sg:city":"Malaga",
    "sg:orig_category":"Asesor\u00cda Sobre Comunicaci\u00d3n De Empresas",
    "sg:phone":"+34 952 22 85 06",
    "sg:postcode":"29...",
    "sg:province":"M\u00e1laga",
    "wof:name":"Eyee Estudios Empresariales A.i.e.",
    "wof:placetype":"venue"
},
  "geometry": {"coordinates":[-4.4120821953,36.7186546326],"type":"Point"}
}