{
  "type": "Feature",
  "properties": {
    "addr:full":"Calle de Medina Y Galnares, 83 Sevilla Sevilla 41015",
    "addr:housenumber":"83",
    "addr:postcode":"41015",
    "addr:street":"Calle De Medina Y Galnares",
    "iso:country":"ES",
    "sg:address":"Calle de Medina Y Galnares, 83",
    "sg:city":"Sevilla",
    "sg:orig_category":"Electricidad Veh\u00cdculo",
    "sg:phone":"+34 954 38 90 00",
    "sg:postcode":"41015",
    "sg:province":"Sevilla",
    "wof:name":"Boza Ortiz Felipe",
    "wof:placetype":"venue"
},
  "geometry": {"coordinates":[-5.9823131561,37.4241828918],"type":"Point"}
}