{
  "type": "Feature",
  "properties": {
    "addr:full":"Calle de Pla Y Cancela, 17 Coru\u00d1a La Coru\u00f1a 15005",
    "addr:housenumber":"17",
    "addr:postcode":"15005",
    "addr:street":"Calle De Pla Y Cancela;La Corun\u0303A",
    "iso:country":"ES",
    "sg:address":"Calle de Pla Y Cancela, 17",
    "sg:city":"Coru\u00d1a",
    "sg:orig_category":"Art\u00cdculos De Regalo (al Por Menor)",
    "sg:phone":"+34 981 26 83 83",
    "sg:postcode":"15005",
    "sg:province":"La Coru\u00f1a",
    "wof:name":"Crespo Fraga Jose Manuel",
    "wof:placetype":"venue"
},
  "geometry": {"coordinates":[-8.4096660614,43.3611717224],"type":"Point"}
}