{
  "type": "Feature",
  "properties": {
    "iso:country":"ES",
    "sg:address":"Trva Campo Ara\u00d1uelo, S/n",
    "sg:city":"Majadas",
    "sg:orig_category":"Administraciones Regionales, Departamentales Y Locales",
    "sg:phone":"+34 927 57 71 16",
    "sg:postcode":"10529",
    "sg:province":"C\u00e1ceres",
    "wof:name":"Ayuntamiento De Majadas",
    "wof:placetype":"venue"
},
  "geometry": {"coordinates":[-5.74766922,39.9428939819],"type":"Point"}
}