{
  "type": "Feature",
  "properties": {
    "addr:full":"Carr Ateneo Musical, 48 Cullera Valencia 46400",
    "addr:housenumber":"48",
    "addr:postcode":"46400",
    "addr:street":"Carr Ateneo Musical",
    "iso:country":"ES",
    "sg:address":"Carr Ateneo Musical, 48",
    "sg:city":"Cullera",
    "sg:orig_category":"Contenedores (mercanc\u00cdas)",
    "sg:phone":"+34 961 72 27 71",
    "sg:postcode":"46400",
    "sg:province":"Valencia",
    "wof:name":"Transportes Victor Piris S.l.",
    "wof:placetype":"venue"
},
  "geometry": {"coordinates":[-0.2562240064,39.1653251648],"type":"Point"}
}