{
  "type": "Feature",
  "properties": {
    "addr:full":"Calle de Santa Feliciana, 11 Madrid Madrid 28010",
    "addr:housenumber":"11",
    "addr:postcode":"madrid;28010",
    "addr:street":"Calle De Santa Feliciana",
    "iso:country":"ES",
    "sg:address":"Calle de Santa Feliciana, 11",
    "sg:city":"Madrid",
    "sg:orig_category":"Asesor\u00cda Fiscal Y Jur\u00cddica",
    "sg:phone":"+34 914 48 14 12",
    "sg:postcode":"28010",
    "sg:province":"Madrid",
    "wof:name":"Alfisa",
    "wof:placetype":"venue"
},
  "geometry": {"coordinates":[-3.6992695332,40.4332275391],"type":"Point"}
}