{
  "type": "Feature",
  "properties": {
    "addr:full":"Carrer de Blas Fernandez Lirola, 32 Hospitalet Llobregat Barcelona 08902",
    "addr:housenumber":"32",
    "addr:postcode":"08902",
    "addr:street":"Carrer De Blas;Lirola",
    "iso:country":"ES",
    "sg:address":"Carrer de Blas Fernandez Lirola, 32",
    "sg:city":"Hospitalet Llobregat",
    "sg:orig_category":"Mec\u00c1nico Del Autom\u00d3vil",
    "sg:phone":"+34 934 31 30 08",
    "sg:postcode":"08902",
    "sg:province":"Barcelona",
    "wof:name":"Talleres Fernandez S.c.p.",
    "wof:placetype":"venue"
},
  "geometry": {"coordinates":[2.1270539761,41.3615341187],"type":"Point"}
}