{
  "type": "Feature",
  "properties": {
    "addr:full":"Carrer de Brusi, 12 Barcelona Barcelona 08006",
    "addr:housenumber":"12",
    "addr:postcode":"08006",
    "addr:street":"Carrer De Brusi",
    "iso:country":"ES",
    "sg:address":"Carrer de Brusi, 12",
    "sg:city":"Barcelona",
    "sg:orig_category":"Mec\u00c1nico Del Autom\u00d3vil",
    "sg:phone":"+34 932 00 79 66",
    "sg:postcode":"08006",
    "sg:province":"Barcelona",
    "wof:name":"Sacasa S.a.",
    "wof:placetype":"venue"
},
  "geometry": {"coordinates":[2.1475811005,41.3996505737],"type":"Point"}
}