{
  "type": "Feature",
  "properties": {
    "iso:country":"ES",
    "sg:address":"Calle de Zafra, 29",
    "sg:city":"Hornachos",
    "sg:orig_category":"Alimentaci\u00d3n General (al Por Menor)",
    "sg:phone":"+34 924 53 32 85",
    "sg:postcode":"06228",
    "sg:province":"Badajoz",
    "wof:name":"Alimentacion Pintado S.l.",
    "wof:placetype":"venue"
},
  "geometry": {"coordinates":[-6.0699572563,38.5548210144],"type":"Point"}
}