{
  "type": "Feature",
  "properties": {
    "iso:country":"ES",
    "sg:address":"Calle de Lealtad, 18",
    "sg:city":"Santander",
    "sg:orig_category":"Abogados",
    "sg:phone":"+34 942 31 26 61",
    "sg:postcode":"39002",
    "sg:province":"Cantabria",
    "wof:name":"Gorostegui Alvarez-miranda Alfredo",
    "wof:placetype":"venue"
},
  "geometry": {"coordinates":[-3.8084430695,43.4604606628],"type":"Point"}
}