{
  "type": "Feature",
  "properties": {
    "iso:country":"ES",
    "sg:address":"Calle de Oriente, 25",
    "sg:city":"Ariza",
    "sg:orig_category":"Alquiler De V\u00cddeo",
    "sg:phone":"+34 976 84 50 64",
    "sg:postcode":"50220",
    "sg:province":"Zaragoza",
    "wof:name":"Lopez Gracia Inmaculada",
    "wof:placetype":"venue"
},
  "geometry": {"coordinates":[-2.0551490784,41.3107414246],"type":"Point"}
}