{
  "type": "Feature",
  "properties": {
    "iso:country":"ES",
    "sg:address":"Carrer de Valldebanador, 14",
    "sg:city":"Calella",
    "sg:orig_category":"Promotores Constructores",
    "sg:phone":"+34 937 69 53 52",
    "sg:postcode":"08370",
    "sg:province":"Barcelona",
    "wof:name":"Promaca S.l.",
    "wof:placetype":"venue"
},
  "geometry": {"coordinates":[2.6488950253,41.618938446],"type":"Point"}
}