{
  "type": "Feature",
  "properties": {
    "addr:full":"Calle de Doctor Manuel Candela, 15 Valencia Valencia 46021",
    "addr:housenumber":"15",
    "addr:postcode":"46021",
    "addr:street":"Calle De Doctor Manuel Candela",
    "iso:country":"ES",
    "sg:address":"Calle de Doctor Manuel Candela, 15",
    "sg:city":"Valencia",
    "sg:classifiers":[
        {
            "category":"Casinos & Gambling",
            "type":"Entertainment"
        }
    ],
    "sg:phone":"+34 963 39 11 36",
    "sg:postcode":"46021",
    "sg:province":"Valencia",
    "sg:tags":[
        "locale",
        "de",
        "juego"
    ],
    "wof:name":"Gestora De Bingos Mare Nostrum S.a.",
    "wof:placetype":"venue"
},
  "geometry": {"coordinates":[-0.3506838083,39.4672889709],"type":"Point"}
}