{
  "type": "Feature",
  "properties": {
    "iso:country":"ES",
    "sg:address":"Calle de Pescado, 22",
    "sg:city":"Medina Rioseco",
    "sg:orig_category":"Electricidad: Instalaciones Industriales",
    "sg:phone":"+34 983 70 04 12",
    "sg:postcode":"47800",
    "sg:province":"Valladolid",
    "wof:name":"Elecrtomedina S.l.",
    "wof:placetype":"venue"
},
  "geometry": {"coordinates":[-5.0417990685,41.8830032349],"type":"Point"}
}