{
  "type": "Feature",
  "properties": {
    "addr:full":"Calle de Gamonal, 47 Madrid Madrid 28031",
    "addr:housenumber":"47",
    "addr:postcode":"madrid;28031",
    "addr:street":"Calle De Gamonal",
    "iso:country":"ES",
    "sg:address":"Calle de Gamonal, 47",
    "sg:city":"Madrid",
    "sg:orig_category":"Mec\u00c1nico Del Autom\u00d3vil",
    "sg:phone":"+34 913 01 32 60",
    "sg:postcode":"28031",
    "sg:province":"Madrid",
    "wof:name":"Jemercar Tecnicos Del Automovil Service S.l.",
    "wof:placetype":"venue"
},
  "geometry": {"coordinates":[-3.641108036,40.3734664917],"type":"Point"}
}