{
  "type": "Feature",
  "properties": {
    "addr:full":"Avda Gran Via Tarrega Monteblanco, 22 Castellon Castell\u00f3n 12006",
    "addr:housenumber":"22",
    "addr:postcode":"12006",
    "addr:street":"Avda Gran Via Tarrega Monteblanco",
    "iso:country":"ES",
    "sg:address":"Avda Gran Via Tarrega Monteblanco, 22",
    "sg:city":"Castellon",
    "sg:orig_category":"Cr\u00cda De Animales",
    "sg:phone":"+34 964 21 01 60",
    "sg:postcode":"12006",
    "sg:province":"Castell\u00f3n",
    "wof:name":"Fernandez Diego Manuel",
    "wof:placetype":"venue"
},
  "geometry": {"coordinates":[-0.1292939931,40.0168533325],"type":"Point"}
}