{
  "type": "Feature",
  "properties": {
    "addr:full":"Carrer de Pere Iii, 3 Cambrils Tarragona 43850",
    "addr:housenumber":"3",
    "addr:postcode":"43850",
    "addr:street":"Carrer De Pere Iii",
    "iso:country":"ES",
    "sg:address":"Carrer de Pere Iii, 3",
    "sg:city":"Cambrils",
    "sg:orig_category":"Arreglo, Reparaci\u00d3n, Piezas Sueltas De Televisi\u00d3n, V\u00cddeo, Hi",
    "sg:phone":"+34 977 36 39 24",
    "sg:postcode":"43850",
    "sg:province":"Tarragona",
    "wof:name":"Electronica Sergi S.l.",
    "wof:placetype":"venue"
},
  "geometry": {"coordinates":[1.0524400473,41.0725517273],"type":"Point"}
}