{
  "type": "Feature",
  "properties": {
    "addr:full":"Av. Barcelona, 44 Museros Valencia 46136",
    "addr:housenumber":"44",
    "addr:postcode":"46136",
    "addr:street":"Av. Barcelona",
    "iso:country":"ES",
    "sg:address":"Av. Barcelona, 44",
    "sg:city":"Museros",
    "sg:orig_category":"Marroquiner\u00cda (confecci\u00d3n)",
    "sg:phone":"+34 961 44 09 34",
    "sg:postcode":"46136",
    "sg:province":"Valencia",
    "wof:name":"Divano Piel Valencia S.l.",
    "wof:placetype":"venue"
},
  "geometry": {"coordinates":[-0.3391830027,39.5551338196],"type":"Point"}
}