{
  "type": "Feature",
  "properties": {
    "addr:full":"Avda Republica Argentina, 29 Le\u00f3n Le\u00f3n 24004",
    "addr:housenumber":"29",
    "addr:postcode":"24004",
    "addr:street":"Avda Republica Argentina;Leo\u0301N",
    "iso:country":"ES",
    "sg:address":"Avda Republica Argentina, 29",
    "sg:city":"Le\u00f3n",
    "sg:orig_category":"Arquitectos",
    "sg:phone":"+34 987 20 54 14",
    "sg:postcode":"24004",
    "sg:province":"Le\u00f3n",
    "sg:website":"www.paginasamarillas.es",
    "wof:name":"Martin-granizo Lopez Belen",
    "wof:placetype":"venue"
},
  "geometry": {"coordinates":[-5.5757331848,42.5955352783],"type":"Point"}
}