{
  "type": "Feature",
  "properties": {
    "iso:country":"ES",
    "sg:address":"Carrer de Bonaire, 16",
    "sg:city":"Palma",
    "sg:orig_category":"Abogados",
    "sg:phone":"+34 971 72 79 40",
    "sg:postcode":"07012",
    "sg:province":"Islas Baleares",
    "wof:name":"Salleras Colom Jeronimo",
    "wof:placetype":"venue"
},
  "geometry": {"coordinates":[2.645334959,39.5738639832],"type":"Point"}
}