{
  "type": "Feature",
  "properties": {
    "iso:country":"ES",
    "sg:address":"Estacion, S/n",
    "sg:city":"Coca",
    "sg:orig_category":"Tubos Y Tuber\u00cdas De Metales Ferrosos (fabricaci\u00d3n, Negocio)",
    "sg:phone":"+34 921 58 66 01",
    "sg:postcode":"40480",
    "sg:province":"Segovia",
    "wof:name":"Industrias Catalina S.a.",
    "wof:placetype":"venue"
},
  "geometry": {"coordinates":[-4.524269104,41.2145004272],"type":"Point"}
}