{
  "type": "Feature",
  "properties": {
    "iso:country":"ES",
    "sg:address":"Calle de Ramirez De Bustamante, 20",
    "sg:city":"Sevilla",
    "sg:orig_category":"Ense\u00d1anza: Profesiones Art\u00cdsticas",
    "sg:phone":"+34 954 61 29 96",
    "sg:postcode":"41013",
    "sg:province":"Sevilla",
    "wof:name":"Villalba Fernandez Ernesto",
    "wof:placetype":"venue"
},
  "geometry": {"coordinates":[-5.9763989449,37.3689613342],"type":"Point"}
}