{
  "type": "Feature",
  "properties": {
    "addr:full":"Carr Ecija, 5 Cala De Bou Islas Baleares 07839",
    "addr:housenumber":"5",
    "addr:postcode":"07839",
    "addr:street":"Carr Ecija;Baleares",
    "iso:country":"ES",
    "sg:address":"Carr Ecija, 5",
    "sg:city":"Cala De Bou",
    "sg:orig_category":"Material Y Suministros Para Perforaciones, Sondeos",
    "sg:phone":"+34 971 34 10 23",
    "sg:postcode":"07839",
    "sg:province":"Islas Baleares",
    "wof:name":"Excavaciones Portmany S.a.",
    "wof:placetype":"venue"
},
  "geometry": {"coordinates":[1.3025970459,38.8642692566],"type":"Point"}
}