{
  "type": "Feature",
  "properties": {
    "addr:full":"Calle de Alamo, 37 Torrejon Ardoz Madrid 28850",
    "addr:housenumber":"37",
    "addr:postcode":"28850",
    "addr:street":"Calle De Alamo",
    "iso:country":"ES",
    "sg:address":"Calle de Alamo, 37",
    "sg:city":"Torrejon Ardoz",
    "sg:orig_category":"Chapister\u00cda",
    "sg:phone":"+34 916 75 05 97",
    "sg:postcode":"28850",
    "sg:province":"Madrid",
    "wof:name":"Talleres Acelerauto S.a.l.",
    "wof:placetype":"venue"
},
  "geometry": {"coordinates":[-3.4567439556,40.4464111328],"type":"Point"}
}