{
  "type": "Feature",
  "properties": {
    "addr:full":"Calle de San Jose Obrero, 84 Almeria Almer\u00eda 04009",
    "addr:housenumber":"84",
    "addr:postcode":"04009",
    "addr:street":"Calle De;Obrero",
    "iso:country":"ES",
    "sg:address":"Calle de San Jose Obrero, 84",
    "sg:city":"Almeria",
    "sg:orig_category":"Pintura, Barniz, Productos Asimilables (fabricaci\u00d3n, Al Por Mayor)",
    "sg:phone":"+34 950 25 86 38",
    "sg:postcode":"04009",
    "sg:province":"Almer\u00eda",
    "wof:name":"Montes Juares Ricaro Fermin",
    "wof:placetype":"venue"
},
  "geometry": {"coordinates":[-2.4534890652,36.8474082947],"type":"Point"}
}