{
  "type": "Feature",
  "properties": {
    "addr:full":"Ctra Barcelona, 10 Almassera Valencia 46132",
    "addr:housenumber":"10",
    "addr:postcode":"46132",
    "addr:street":"Ctra Barcelona",
    "iso:country":"ES",
    "sg:address":"Ctra Barcelona, 10",
    "sg:city":"Almassera",
    "sg:orig_category":"Fabricaci\u00d3n De Bebidas No Alcoh\u00d3licas",
    "sg:phone":"+34 961 85 46 73",
    "sg:postcode":"46132",
    "sg:province":"Valencia",
    "wof:name":"Marti Rives Cristobal",
    "wof:placetype":"venue"
},
  "geometry": {"coordinates":[-0.3627769947,39.5135993958],"type":"Point"}
}