{
  "type": "Feature",
  "properties": {
    "iso:country":"ES",
    "sg:address":"Carrer de Cap Norfeu, 56",
    "sg:city":"Roses",
    "sg:orig_category":"Empresas De Pintura Y Revestimientos",
    "sg:phone":"+34 972 25 59 65",
    "sg:postcode":"17480",
    "sg:province":"Girona",
    "wof:name":"Roses Tomb S. L.",
    "wof:placetype":"venue"
},
  "geometry": {"coordinates":[3.1828520298,42.2593688965],"type":"Point"}
}