{
  "type": "Feature",
  "properties": {
    "addr:full":"Plaza, 21 Pallares Badajoz 06907",
    "addr:housenumber":"21",
    "addr:postcode":"06907",
    "iso:country":"ES",
    "sg:address":"Plaza, 21",
    "sg:city":"Pallares",
    "sg:orig_category":"Charcuter\u00cdas (al Por Mayor)",
    "sg:phone":"+34 924 51 10 35",
    "sg:postcode":"06907",
    "sg:province":"Badajoz",
    "wof:name":"Marquez Campanario Jose",
    "wof:placetype":"venue"
},
  "geometry": {"coordinates":[-6.1526489258,38.1112861633],"type":"Point"}
}