{
  "type": "Feature",
  "properties": {
    "addr:full":"Carrer de Rossello, 237 Barcelona Barcelona 08008",
    "addr:housenumber":"237",
    "addr:postcode":"08008",
    "addr:street":"Carrer De Rossello",
    "iso:country":"ES",
    "sg:address":"Carrer de Rossello, 237",
    "sg:city":"Barcelona",
    "sg:orig_category":"Art\u00cdculos De Regalo (al Por Menor)",
    "sg:phone":"+34 932 17 18 07",
    "sg:postcode":"08008",
    "sg:province":"Barcelona",
    "wof:name":"Marie Valmon S.l.",
    "wof:placetype":"venue"
},
  "geometry": {"coordinates":[2.1582129002,41.3941726685],"type":"Point"}
}