{
  "type": "Feature",
  "properties": {
    "iso:country":"ES",
    "sg:address":"Calle de Sabino Arana, 4",
    "sg:city":"Moreaga",
    "sg:orig_category":"Estancos",
    "sg:phone":"+34 946 76 17 08",
    "sg:postcode":"48600",
    "sg:province":"Vizcaya",
    "wof:name":"Aldecoa Bilbao Luis Maria",
    "wof:placetype":"venue"
},
  "geometry": {"coordinates":[-3.000297308,43.3646583557],"type":"Point"}
}