{
  "type": "Feature",
  "properties": {
    "addr:full":"Calle de Centelles, Los, 13 Valencia Valencia 46006",
    "addr:housenumber":"13",
    "addr:postcode":"46006",
    "addr:street":"Calle De Centelles Los",
    "iso:country":"ES",
    "sg:address":"Calle de Centelles, Los, 13",
    "sg:city":"Valencia",
    "sg:orig_category":"Agencias De Viajes",
    "sg:phone":"+34 963 95 10 34",
    "sg:postcode":"46006",
    "sg:province":"Valencia",
    "sg:website":"www.marsans.es",
    "wof:name":"Viajes Marsans S.a.",
    "wof:placetype":"venue"
},
  "geometry": {"coordinates":[-0.3710969985,39.4599533081],"type":"Point"}
}