{
  "type": "Feature",
  "properties": {
    "addr:full":"Zorrolleta Kalea, 3 Jundiz \u00c1lava 01015",
    "addr:housenumber":"3",
    "addr:postcode":"01015",
    "addr:street":"Zorrolleta Kalea;A\u0301Lava",
    "iso:country":"ES",
    "sg:address":"Zorrolleta Kalea, 3",
    "sg:city":"Jundiz",
    "sg:orig_category":"Maquinaria Y Herramientas Para Madera, Pvc, Aluminio Y Aperos (fabricaci\u00d3n, Comercio)",
    "sg:phone":"+34 945 29 01 30",
    "sg:postcode":"01015",
    "sg:province":"\u00c1lava",
    "wof:name":"Cerrillo Marquinez Jose Maria",
    "wof:placetype":"venue"
},
  "geometry": {"coordinates":[-2.7309451103,42.8471374512],"type":"Point"}
}