{
  "type": "Feature",
  "properties": {
    "addr:full":"Calle de Nicolas Megias, 33 Fuente Cantos Badajoz 06240",
    "addr:housenumber":"33",
    "addr:postcode":"06240",
    "addr:street":"Calle De Nicolas Megias",
    "iso:country":"ES",
    "sg:address":"Calle de Nicolas Megias, 33",
    "sg:city":"Fuente Cantos",
    "sg:orig_category":"Internados & Ense\u00d1anza Privada",
    "sg:phone":"+34 924 50 03 11",
    "sg:postcode":"06240",
    "sg:province":"Badajoz",
    "wof:name":"Colegio San Francisco Javier",
    "wof:placetype":"venue"
},
  "geometry": {"coordinates":[-6.3052000999,38.2476463318],"type":"Point"}
}