{
  "type": "Feature",
  "properties": {
    "iso:country":"ES",
    "sg:address":"Rua Arcebispo Lago, 1",
    "sg:city":"Vilagarcia",
    "sg:orig_category":"Abogados",
    "sg:phone":"+34 986 50 10 34",
    "sg:postcode":"36600",
    "sg:province":"Pontevedra",
    "wof:name":"Montenegro Gonzalez Ramon",
    "wof:placetype":"venue"
},
  "geometry": {"coordinates":[-8.7674636841,42.594783783],"type":"Point"}
}