{
  "type": "Feature",
  "properties": {
    "addr:full":"Calle de Cebreros, 23 Madrid Madrid 28011",
    "addr:housenumber":"23",
    "addr:postcode":"madrid;28011",
    "addr:street":"Calle De Cebreros",
    "iso:country":"ES",
    "sg:address":"Calle de Cebreros, 23",
    "sg:city":"Madrid",
    "sg:orig_category":"Mec\u00c1nico Del Autom\u00d3vil",
    "sg:phone":"+34 914 79 77 09",
    "sg:postcode":"28011",
    "sg:province":"Madrid",
    "wof:name":"Sancho Garcia Miguel Angel",
    "wof:placetype":"venue"
},
  "geometry": {"coordinates":[-3.7439191341,40.404876709],"type":"Point"}
}