{
  "type": "Feature",
  "properties": {
    "addr:full":"Almacenes, 6 Villares Reina Salamanca 37184",
    "addr:postcode":"37184",
    "iso:country":"ES",
    "sg:address":"Almacenes, 6",
    "sg:city":"Villares Reina",
    "sg:orig_category":"Centros Empresariales",
    "sg:phone":"+34 923 12 42 96",
    "sg:postcode":"37184",
    "sg:province":"Salamanca",
    "wof:name":"Lubri Mafer S.l.",
    "wof:placetype":"venue"
},
  "geometry": {"coordinates":[-5.6435341835,40.987411499],"type":"Point"}
}