{
  "type": "Feature",
  "properties": {
    "addr:full":"Calle de Txalaparta, 9 Vitoria-gasteiz \u00c1lava 01006",
    "addr:housenumber":"9",
    "addr:postcode":"01006",
    "addr:street":"Calle De Txalaparta",
    "iso:country":"ES",
    "sg:address":"Calle de Txalaparta, 9",
    "sg:city":"Vitoria-gasteiz",
    "sg:orig_category":"Empresas De Limpieza",
    "sg:phone":"+34 945 13 76 85",
    "sg:postcode":"01006",
    "sg:province":"\u00c1lava",
    "wof:name":"Servicio De Limpiezas  Hegoalde S C.v",
    "wof:placetype":"venue"
},
  "geometry": {"coordinates":[-2.6650400162,42.8369979858],"type":"Point"}
}