{
  "type": "Feature",
  "properties": {
    "iso:country":"ES",
    "sg:address":"Calle de Salinas De Cabo De Gata (las), S/n",
    "sg:city":"Cabo Gata",
    "sg:orig_category":"Hoteles",
    "sg:phone":"+34 950 37 01 03",
    "sg:postcode":"04150",
    "sg:province":"Almer\u00eda",
    "wof:name":"Morales C.b.",
    "wof:placetype":"venue"
},
  "geometry": {"coordinates":[-2.4608399868,36.8422698975],"type":"Point"}
}