{
  "type": "Feature",
  "properties": {
    "addr:full":"Calle de Marmoles, 11 Sevilla Sevilla 41004",
    "addr:housenumber":"11",
    "addr:postcode":"41004",
    "addr:street":"Calle De Marmoles",
    "iso:country":"ES",
    "sg:address":"Calle de Marmoles, 11",
    "sg:city":"Sevilla",
    "sg:orig_category":"Molduras, Junquillos, Listones Y Molduras Perforadas",
    "sg:phone":"+34 954 22 54 41",
    "sg:postcode":"41004",
    "sg:province":"Sevilla",
    "wof:name":"Alonso Lopez Luciano",
    "wof:placetype":"venue"
},
  "geometry": {"coordinates":[-5.9897732735,37.388507843],"type":"Point"}
}