{
  "type": "Feature",
  "properties": {
    "addr:full":"Carrer de Cultura, 52 Santa Coloma De Gramenet Barcelona 08922",
    "addr:housenumber":"52",
    "addr:postcode":"08922",
    "addr:street":"Carrer De Cultura",
    "iso:country":"ES",
    "sg:address":"Carrer de Cultura, 52",
    "sg:city":"Santa Coloma De Gramenet",
    "sg:orig_category":"Estancos",
    "sg:phone":"+34 933 86 45 34",
    "sg:postcode":"08922",
    "sg:province":"Barcelona",
    "wof:name":"Collantes Cervantes Laureano",
    "wof:placetype":"venue"
},
  "geometry": {"coordinates":[2.2074849606,41.4472503662],"type":"Point"}
}