{
  "type": "Feature",
  "properties": {
    "addr:full":"La Villa, 7 Lucena C\u00f3rdoba 14900",
    "addr:housenumber":"7",
    "addr:postcode":"14900",
    "addr:street":"Villa",
    "iso:country":"ES",
    "sg:address":"La Villa, 7",
    "sg:city":"Lucena",
    "sg:orig_category":"Centros De Cr\u00c9dito Inmobiliario",
    "sg:phone":"+34 957 50 38 69",
    "sg:postcode":"14900",
    "sg:province":"C\u00f3rdoba",
    "wof:name":"Cruso S.l.",
    "wof:placetype":"venue"
},
  "geometry": {"coordinates":[-4.4847187996,37.4150352478],"type":"Point"}
}