{
  "type": "Feature",
  "properties": {
    "addr:full":"Carr Punta (la), 80 Sueca Valencia 46410",
    "addr:housenumber":"80",
    "addr:postcode":"46410",
    "addr:street":"Carr Punta La",
    "iso:country":"ES",
    "sg:address":"Carr Punta (la), 80",
    "sg:city":"Sueca",
    "sg:orig_category":"T\u00c9cnicos Veterinarios",
    "sg:phone":"+34 961 71 19 22",
    "sg:postcode":"46410",
    "sg:province":"Valencia",
    "wof:name":"Cortes Campillo Hermelando",
    "wof:placetype":"venue"
},
  "geometry": {"coordinates":[-0.3084059954,39.2042617798],"type":"Point"}
}