{
  "type": "Feature",
  "properties": {
    "iso:country":"ES",
    "sg:address":"Av. Constitucio, 15",
    "sg:city":"Calig",
    "sg:orig_category":"Electrodom\u00c9sticos (al Por Menor)",
    "sg:phone":"+34 964 49 21 28",
    "sg:postcode":"12589",
    "sg:province":"Castell\u00f3n",
    "sg:website":"www.redelite.es",
    "wof:name":"Del Valle Meseguer S L",
    "wof:placetype":"venue"
},
  "geometry": {"coordinates":[0.3562929928,40.4626274109],"type":"Point"}
}