{
  "type": "Feature",
  "properties": {
    "addr:full":"Calle de Saint Gaudens, 27 Barbastro Huesca 22300",
    "addr:housenumber":"27",
    "addr:postcode":"22300",
    "addr:street":"Calle De Saint Gaudens",
    "iso:country":"ES",
    "sg:address":"Calle de Saint Gaudens, 27",
    "sg:city":"Barbastro",
    "sg:orig_category":"Centros Comerciales Y Grandes Tiendas",
    "sg:phone":"+34 974 31 20 52",
    "sg:postcode":"22300",
    "sg:province":"Huesca",
    "wof:name":"Alfertor S. L.",
    "wof:placetype":"venue"
},
  "geometry": {"coordinates":[0.1305269003,42.0328712463],"type":"Point"}
}