{
  "type": "Feature",
  "properties": {
    "iso:country":"ES",
    "sg:address":"Calle de Simon Sainz De Varanda, 7",
    "sg:city":"Zaragoza",
    "sg:orig_category":"Aparatos, Sistemas De Tele",
    "sg:phone":"+34 976 38 32 38",
    "sg:postcode":"50007",
    "sg:province":"Zaragoza",
    "wof:name":"Compa\u00f1ia De Vigilancia Aragonesa S.l.",
    "wof:placetype":"venue"
},
  "geometry": {"coordinates":[-0.8827450275,41.6372680664],"type":"Point"}
}