{
  "type": "Feature",
  "properties": {
    "iso:country":"ES",
    "sg:address":"Avda Oviedo De, 9",
    "sg:city":"Aviles",
    "sg:orig_category":"Ense\u00d1anza, Formaci\u00d3n Profesional: Aprendizaje",
    "sg:phone":"+34 985 12 91 10",
    "sg:postcode":"33402",
    "sg:province":"Asturias",
    "wof:name":"Ayuntamiento De Aviles",
    "wof:placetype":"venue"
},
  "geometry": {"coordinates":[-5.9263877869,43.534324646],"type":"Point"}
}