{
  "type": "Feature",
  "properties": {
    "iso:country":"ES",
    "sg:address":"A Carreira, 3",
    "sg:city":"Carreira",
    "sg:orig_category":"Ebanister\u00cda",
    "sg:phone":"+34 981 48 60 36",
    "sg:postcode":"15550",
    "sg:province":"La Coru\u00f1a",
    "wof:name":"Nunez Ebanistas S.l.",
    "wof:placetype":"venue"
},
  "geometry": {"coordinates":[-8.1737756729,43.5668754578],"type":"Point"}
}