{
  "type": "Feature",
  "properties": {
    "iso:country":"ES",
    "sg:address":"Calle de Saavedra Fajardo, 15",
    "sg:city":"Santa Eulalia",
    "sg:orig_category":"Vinos Y Licores (venta Al Por Menor)",
    "sg:phone":"+34 968 21 67 64",
    "sg:postcode":"30001",
    "sg:province":"Murcia",
    "sg:website":"www.vinotienda.com",
    "wof:name":"Casa Rambla S.l.",
    "wof:placetype":"venue"
},
  "geometry": {"coordinates":[-1.1270289421,37.9865837097],"type":"Point"}
}