{
  "type": "Feature",
  "properties": {
    "addr:full":"Plaz Gernikako Arbola, 4 Urretxu Guip\u00f9zcoa 20700",
    "addr:housenumber":"4",
    "addr:postcode":"20700",
    "addr:street":"Plaz Gernikako Arbola;Guipu\u0300Zcoa",
    "iso:country":"ES",
    "sg:address":"Plaz Gernikako Arbola, 4",
    "sg:city":"Urretxu",
    "sg:orig_category":"Artes Gr\u00c1ficas, Artes Pl\u00c1sticas (curso)",
    "sg:phone":"+34 943 72 92 46",
    "sg:postcode":"20700",
    "sg:province":"Guip\u00f9zcoa",
    "wof:name":"Armenteros Saley Elixabete",
    "wof:placetype":"venue"
},
  "geometry": {"coordinates":[-2.3146340847,43.0914649963],"type":"Point"}
}