{
  "type": "Feature",
  "properties": {
    "iso:country":"ES",
    "sg:address":"Carr Raval, 12",
    "sg:city":"Hostalric",
    "sg:orig_category":"Fabricaci\u00d3n, Venta De Cuadros, Accesorios Para Enmarcar",
    "sg:phone":"+34 972 86 42 01",
    "sg:postcode":"17450",
    "sg:province":"Girona",
    "wof:name":"Revilla Garcia Valentin",
    "wof:placetype":"venue"
},
  "geometry": {"coordinates":[2.6402380466,41.7460517883],"type":"Point"}
}