{
  "type": "Feature",
  "properties": {
    "iso:country":"ES",
    "sg:address":"Carrer de Cort (de La), 38",
    "sg:city":"Valls",
    "sg:orig_category":"Venta, Alquiler De Instrumentos Y Accesorios De M\u00dasica",
    "sg:phone":"+34 977 60 09 75",
    "sg:postcode":"43800",
    "sg:province":"Tarragona",
    "wof:name":"Batet Poblet Lluis",
    "wof:placetype":"venue"
},
  "geometry": {"coordinates":[1.2492409945,41.2847251892],"type":"Point"}
}