{
  "type": "Feature",
  "properties": {
    "addr:full":"Calle de Jardines, 6 Talavera Reina Toledo 45600",
    "addr:housenumber":"6",
    "addr:postcode":"45600",
    "addr:street":"Calle De Jardines",
    "iso:country":"ES",
    "sg:address":"Calle de Jardines, 6",
    "sg:city":"Talavera Reina",
    "sg:orig_category":"Contenedores (mercanc\u00cdas)",
    "sg:phone":"+34 925 82 31 98",
    "sg:postcode":"45600",
    "sg:province":"Toledo",
    "wof:name":"Transportes Juan Jose Martin S.l.",
    "wof:placetype":"venue"
},
  "geometry": {"coordinates":[-4.8225159645,39.9711914062],"type":"Point"}
}