{
  "type": "Feature",
  "properties": {
    "iso:country":"ES",
    "sg:address":"Calle de Mandobide, 1",
    "sg:city":"Bilbao",
    "sg:orig_category":"Frutas, Legumbres Frescas Y Tempranas (al Por Menor)",
    "sg:phone":"+34 944 13 20 46",
    "sg:postcode":"48007",
    "sg:province":"Vizcaya",
    "wof:name":"Kareaga Goikoa 30 S.l.",
    "wof:placetype":"venue"
},
  "geometry": {"coordinates":[-2.9266290665,43.2688713074],"type":"Point"}
}