{
  "type": "Feature",
  "properties": {
    "iso:country":"ES",
    "sg:address":"Calle de Caudillo, 43",
    "sg:city":"Beade",
    "sg:orig_category":"Farmacias",
    "sg:phone":"+34 988 48 00 56",
    "sg:postcode":"32431",
    "sg:province":"Ourense",
    "wof:name":"Sanmiguel Guitian Purificacion",
    "wof:placetype":"venue"
},
  "geometry": {"coordinates":[-8.1274452209,42.3287010193],"type":"Point"}
}