{
  "type": "Feature",
  "properties": {
    "addr:full":"Calle de Dinamarca, S/n Caceres C\u00e1ceres 10005",
    "addr:housenumber":"s / n",
    "addr:postcode":"10005",
    "addr:street":"Calle De Dinamarca;Ca\u0301Ceres",
    "iso:country":"ES",
    "sg:address":"Calle de Dinamarca, S/n",
    "sg:city":"Caceres",
    "sg:orig_category":"Ense\u00d1anza Variada",
    "sg:phone":"+34 927 23 89 60",
    "sg:postcode":"10005",
    "sg:province":"C\u00e1ceres",
    "wof:name":"Academia Golden Gate S.l.",
    "wof:placetype":"venue"
},
  "geometry": {"coordinates":[-6.3798522949,39.4649085999],"type":"Point"}
}