{
  "type": "Feature",
  "properties": {
    "iso:country":"ES",
    "sg:address":"Carrer de Sant Jeroni, 43",
    "sg:city":"Santa Coloma De Gramenet",
    "sg:orig_category":"Herboristas (al Por Menor)",
    "sg:phone":"+34 933 91 12 06",
    "sg:postcode":"08921",
    "sg:province":"Barcelona",
    "wof:name":"Verges Cirera Maria Manuela",
    "wof:placetype":"venue"
},
  "geometry": {"coordinates":[2.2074270248,41.454536438],"type":"Point"}
}