{
  "type": "Feature",
  "properties": {
    "addr:full":"Calle de Fuente De La Cuesta, S/n Madrid Madrid 28023",
    "addr:housenumber":"s / n",
    "addr:postcode":"28023",
    "addr:street":"Calle De Fuente De La Cuesta",
    "iso:country":"ES",
    "sg:address":"Calle de Fuente De La Cuesta, S/n",
    "sg:city":"Madrid",
    "sg:orig_category":"Ingenier\u00cda, Centros De Estudios (diversos)",
    "sg:phone":"+34 913 07 81 41",
    "sg:postcode":"28023",
    "sg:province":"Madrid",
    "wof:name":"Arana Aizpurua Jose Maria De",
    "wof:placetype":"venue"
},
  "geometry": {"coordinates":[-3.7647373676,40.4510307312],"type":"Point"}
}