{
  "type": "Feature",
  "properties": {
    "addr:full":"Plaz Capitan Boixareu Rivera, 84 Guadalajara Guadalajara 19002",
    "addr:housenumber":"84",
    "addr:postcode":"19002",
    "addr:street":"Plaz Capitan Boixareu Rivera",
    "iso:country":"ES",
    "sg:address":"Plaz Capitan Boixareu Rivera, 84",
    "sg:city":"Guadalajara",
    "sg:orig_category":"Contables",
    "sg:phone":"+34 949 24 77 60",
    "sg:postcode":"19002",
    "sg:province":"Guadalajara",
    "wof:name":"Asesoralia Guadalajara S.l.l.",
    "wof:placetype":"venue"
},
  "geometry": {"coordinates":[-3.161781311,40.630191803],"type":"Point"}
}