{
  "type": "Feature",
  "properties": {
    "iso:country":"ES",
    "sg:address":"Av Paral.lel, 61",
    "sg:city":"Barcelona",
    "sg:orig_category":"Parques De Atracciones Y Centros De Esparcimiento",
    "sg:phone":"+34 933 29 01 28",
    "sg:postcode":"08004",
    "sg:province":"Barcelona",
    "wof:name":"Autopark S.a.",
    "wof:placetype":"venue"
},
  "geometry": {"coordinates":[2.170183897,41.3748016357],"type":"Point"}
}