{
  "type": "Feature",
  "properties": {
    "addr:full":"Avgd Valencia, 11 Lleida Lleida 25001",
    "addr:housenumber":"11",
    "addr:postcode":"25001",
    "addr:street":"Valencia",
    "iso:country":"ES",
    "sg:address":"Avgd Valencia, 11",
    "sg:city":"Lleida",
    "sg:orig_category":"Molduras, Junquillos, Listones Y Molduras Perforadas",
    "sg:phone":"+34 973 20 06 91",
    "sg:postcode":"25001",
    "sg:province":"Lleida",
    "wof:name":"Luna Asensio Sergio",
    "wof:placetype":"venue"
},
  "geometry": {"coordinates":[0.6300699711,41.6121139526],"type":"Point"}
}