{
  "type": "Feature",
  "properties": {
    "addr:full":"A Ponce Leon, 1 Malaga M\u00e1laga 29004",
    "addr:housenumber":"1",
    "addr:postcode":"29004",
    "addr:street":"Leon;Ma\u0301Laga",
    "iso:country":"ES",
    "sg:address":"A Ponce Leon, 1",
    "sg:city":"Malaga",
    "sg:classifiers":[
        {
            "category":"Cinema",
            "subcategory":"Movie Theater",
            "type":"Entertainment"
        }
    ],
    "sg:phone":"+34 952 17 33 95",
    "sg:postcode":"29004",
    "sg:province":"M\u00e1laga",
    "sg:tags":[
        "salas",
        "de",
        "cine"
    ],
    "wof:name":"Yelmo Films S.l.",
    "wof:placetype":"venue"
},
  "geometry": {"coordinates":[-4.5026555061,36.666809082],"type":"Point"}
}