{
  "type": "Feature",
  "properties": {
    "addr:full":"Calle de Leo, S/n Almeria Almer\u00eda 04009",
    "addr:housenumber":"s / n",
    "addr:postcode":"04009",
    "addr:street":"Calle De Leo",
    "iso:country":"ES",
    "sg:address":"Calle de Leo, S/n",
    "sg:city":"Almeria",
    "sg:orig_category":"Lencer\u00cda Femenina, Corseter\u00cda, Trajes De Ba\u00d1o (al Por Menor)",
    "sg:phone":"+34 950 14 08 45",
    "sg:postcode":"04009",
    "sg:province":"Almer\u00eda",
    "wof:name":"Jale Construcciones S.a.",
    "wof:placetype":"venue"
},
  "geometry": {"coordinates":[-2.4392640591,36.8557662964],"type":"Point"}
}