{
  "type": "Feature",
  "properties": {
    "addr:full":"Calle de Historiador Chabas, 1 Javea Alicante 03730",
    "addr:housenumber":"1",
    "addr:postcode":"03730",
    "addr:street":"Calle De Historiador Chabas",
    "iso:country":"ES",
    "sg:address":"Calle de Historiador Chabas, 1",
    "sg:city":"Javea",
    "sg:orig_category":"Pr\u00c9stamos Personales E Hipotecarios",
    "sg:phone":"+34 965 79 16 57",
    "sg:postcode":"03730",
    "sg:province":"Alicante",
    "wof:name":"Bt Espa\u00d1a Compa\u00d1ia De Servicios Globales De Telecomunicaciones S.a.u.",
    "wof:placetype":"venue"
},
  "geometry": {"coordinates":[0.1675200015,38.7913894653],"type":"Point"}
}