{
  "type": "Feature",
  "properties": {
    "addr:full":"Areizaga Kalea, 10 Urretxu Guip\u00f9zcoa 20700",
    "addr:housenumber":"10",
    "addr:postcode":"20700",
    "addr:street":"Areizaga Kalea;Guipu\u0300Zcoa",
    "iso:country":"ES",
    "sg:address":"Areizaga Kalea, 10",
    "sg:city":"Urretxu",
    "sg:orig_category":"Colorantes, Colores Y Pigmentos (fabricaci\u00d3n, Al Por Mayor)",
    "sg:phone":"+34 943 72 08 67",
    "sg:postcode":"20700",
    "sg:province":"Guip\u00f9zcoa",
    "wof:name":"Caballero Carrasco Antonio",
    "wof:placetype":"venue"
},
  "geometry": {"coordinates":[-2.3142440319,43.091381073],"type":"Point"}
}