{
  "type": "Feature",
  "properties": {
    "addr:full":"Avda Barcelona, 2 Jaen Ja\u00e9n 23006",
    "addr:housenumber":"2;jae\u0301n",
    "addr:postcode":"23006",
    "addr:street":"Avda Barcelona",
    "iso:country":"ES",
    "sg:address":"Avda Barcelona, 2",
    "sg:city":"Jaen",
    "sg:orig_category":"Ingenier\u00cda, Centros De Estudios (diversos)",
    "sg:phone":"+34 953 29 17 74",
    "sg:postcode":"23006",
    "sg:province":"Ja\u00e9n",
    "wof:name":"Martin Alcaide Nicolas Raul",
    "wof:placetype":"venue"
},
  "geometry": {"coordinates":[-3.7980089188,37.7805480957],"type":"Point"}
}