{
  "type": "Feature",
  "properties": {
    "iso:country":"ES",
    "sg:address":"Calle de Luis Ortiz Mu\u00d1oz, S/n",
    "sg:city":"Sevilla",
    "sg:orig_category":"Reposter\u00cdas",
    "sg:phone":"+34 954 23 76 48",
    "sg:postcode":"41013",
    "sg:province":"Sevilla",
    "wof:name":"Gomez Bizcocho Maria Del Carmen",
    "wof:placetype":"venue"
},
  "geometry": {"coordinates":[-5.9689588547,37.3566360474],"type":"Point"}
}