{
  "type": "Feature",
  "properties": {
    "addr:full":"Avda Victoria, 2 Madrid Madrid 28023",
    "addr:housenumber":"2",
    "addr:postcode":"28023",
    "addr:street":"Avda Victoria",
    "iso:country":"ES",
    "sg:address":"Avda Victoria, 2",
    "sg:city":"Madrid",
    "sg:orig_category":"Retoques De Vestidos",
    "sg:phone":"+34 913 72 96 38",
    "sg:postcode":"28023",
    "sg:province":"Madrid",
    "sg:website":"www.retoucherie.com",
    "wof:name":"La Retoucherie De Manuela S.l.",
    "wof:placetype":"venue"
},
  "geometry": {"coordinates":[-3.8137290478,40.4670257568],"type":"Point"}
}