{
  "type": "Feature",
  "properties": {
    "iso:country":"ES",
    "sg:address":"Calle de Sagasta, 1",
    "sg:city":"Ubeda",
    "sg:orig_category":"Promotores Constructores",
    "sg:phone":"+34 953 75 29 00",
    "sg:postcode":"23400",
    "sg:province":"Ja\u00e9n",
    "wof:name":"Promociones Edificios Y Obras Del Sur S.a.",
    "wof:placetype":"venue"
},
  "geometry": {"coordinates":[-3.3759400845,38.011264801],"type":"Point"}
}