{
  "type": "Feature",
  "properties": {
    "addr:full":"Pla\u00c7 Catalunya, 2 Roses Girona 17480",
    "addr:housenumber":"2",
    "addr:postcode":"17480",
    "iso:country":"ES",
    "sg:address":"Pla\u00c7 Catalunya, 2",
    "sg:city":"Roses",
    "sg:orig_category":"Agencias De Viajes",
    "sg:phone":"+34 972 25 66 17",
    "sg:postcode":"17480",
    "sg:province":"Girona",
    "sg:website":"www.autocaresvinolas.com",
    "wof:name":"Viatges Vi\u00d1olas S.a.",
    "wof:placetype":"venue"
},
  "geometry": {"coordinates":[3.1743021011,42.2640228271],"type":"Point"}
}