{
  "type": "Feature",
  "properties": {
    "iso:country":"ES",
    "sg:address":"Calle de Maestro Espada, 54",
    "sg:city":"Librilla",
    "sg:orig_category":"Venta, Montaje De Neum\u00c1ticos",
    "sg:phone":"+34 968 65 85 43",
    "sg:postcode":"30892",
    "sg:province":"Murcia",
    "wof:name":"Mendez Canales Pedro",
    "wof:placetype":"venue"
},
  "geometry": {"coordinates":[-1.3552968502,37.8852767944],"type":"Point"}
}