{
  "type": "Feature",
  "properties": {
    "addr:full":"Calle de Bodegas, 6 Zamora Zamora 49027",
    "addr:housenumber":"6",
    "addr:postcode":"49027",
    "addr:street":"Calle De Bodegas",
    "iso:country":"ES",
    "sg:address":"Calle de Bodegas, 6",
    "sg:city":"Zamora",
    "sg:orig_category":"Plomeros",
    "sg:phone":"+34 980 51 41 46",
    "sg:postcode":"49027",
    "sg:province":"Zamora",
    "wof:name":"Esteban Hidalgo Francisco",
    "wof:placetype":"venue"
},
  "geometry": {"coordinates":[-5.7556018829,41.4915428162],"type":"Point"}
}