{
  "type": "Feature",
  "properties": {
    "addr:full":"Calle de Suarez De Salazar, 14 Cadiz C\u00e1diz 11006",
    "addr:housenumber":"14",
    "addr:postcode":"11006",
    "addr:street":"Calle De Suarez De Salazar",
    "iso:country":"ES",
    "sg:address":"Calle de Suarez De Salazar, 14",
    "sg:city":"Cadiz",
    "sg:orig_category":"Empresas De Carpinter\u00cda Met\u00c1lica",
    "sg:phone":"+34 956 25 69 57",
    "sg:postcode":"11006",
    "sg:province":"C\u00e1diz",
    "wof:name":"Guerra Mu\u00f1oz Francisco",
    "wof:placetype":"venue"
},
  "geometry": {"coordinates":[-6.2915410995,36.5285949707],"type":"Point"}
}