{
  "type": "Feature",
  "properties": {
    "iso:country":"ES",
    "sg:address":"Pase Parra (de), 32",
    "sg:city":"Aguilas",
    "sg:orig_category":"Reposter\u00cdas",
    "sg:phone":"+34 968 41 18 83",
    "sg:postcode":"30880",
    "sg:province":"Murcia",
    "wof:name":"Pastor Fernandez Alonso",
    "wof:placetype":"venue"
},
  "geometry": {"coordinates":[-1.5750099421,37.4077110291],"type":"Point"}
}