{
  "type": "Feature",
  "properties": {
    "addr:full":"Carr Son Pons, 1 Vilafranca Bonany Islas Baleares 07250",
    "addr:housenumber":"1",
    "addr:postcode":"07250",
    "addr:street":"Carr Son Pons;Bonany",
    "iso:country":"ES",
    "sg:address":"Carr Son Pons, 1",
    "sg:city":"Vilafranca Bonany",
    "sg:classifiers":[
        {
            "category":"Taxi",
            "type":"Transportation"
        }
    ],
    "sg:phone":"+34 971 83 21 23",
    "sg:postcode":"07250",
    "sg:province":"Islas Baleares",
    "wof:name":"Miralles Mayol Juan",
    "wof:placetype":"venue"
},
  "geometry": {"coordinates":[3.0871129036,39.5691604614],"type":"Point"}
}