{
  "type": "Feature",
  "properties": {
    "addr:full":"Carr Nou, S/n Massalcoreig Lleida 25184",
    "addr:postcode":"25184",
    "addr:street":"Carr Nou S / N Massalcoreig",
    "iso:country":"ES",
    "sg:address":"Carr Nou, S/n",
    "sg:city":"Massalcoreig",
    "sg:orig_category":"Centros De Educaci\u00d3n Especial",
    "sg:phone":"+34 973 79 35 96",
    "sg:postcode":"25184",
    "sg:province":"Lleida",
    "wof:name":"Co%egi Public",
    "wof:placetype":"venue"
},
  "geometry": {"coordinates":[0.3601050079,41.4599685669],"type":"Point"}
}