{
  "type": "Feature",
  "properties": {
    "iso:country":"ES",
    "sg:address":"Avda Andalucia, S/n",
    "sg:city":"Peligros",
    "sg:orig_category":"Cristaler\u00cdas",
    "sg:phone":"+34 958 40 02 64",
    "sg:postcode":"18210",
    "sg:province":"Granada",
    "wof:name":"La Veneciana Betica S.a.",
    "wof:placetype":"venue"
},
  "geometry": {"coordinates":[-3.6276469231,37.2251625061],"type":"Point"}
}