{
  "type": "Feature",
  "properties": {
    "iso:country":"ES",
    "sg:address":"Plaz Font (la), 6",
    "sg:city":"Borriol",
    "sg:orig_category":"Estancos",
    "sg:phone":"+34 964 32 13 02",
    "sg:postcode":"12190",
    "sg:province":"Castell\u00f3n",
    "wof:name":"Pitarch Bellmunt Benjamin",
    "wof:placetype":"venue"
},
  "geometry": {"coordinates":[-0.070262,40.0408325195],"type":"Point"}
}