{
  "type": "Feature",
  "properties": {
    "iso:country":"ES",
    "sg:address":"Calle de Santa Clara, 2",
    "sg:city":"Bilbao",
    "sg:orig_category":"Promotores Constructores",
    "sg:phone":"+34 944 12 20 86",
    "sg:postcode":"48006",
    "sg:province":"Vizcaya",
    "wof:name":"Antopar S.l.",
    "wof:placetype":"venue"
},
  "geometry": {"coordinates":[-2.9188439846,43.2573242188],"type":"Point"}
}