{
  "type": "Feature",
  "properties": {
    "addr:full":"Via Aurelia, 26 Sabadell Barcelona 08206",
    "addr:housenumber":"26",
    "addr:postcode":"08206",
    "addr:street":"Via Aurelia",
    "iso:country":"ES",
    "sg:address":"Via Aurelia, 26",
    "sg:city":"Sabadell",
    "sg:orig_category":"Peluqueros: De Se\u00d1oras",
    "sg:phone":"+34 937 23 06 93",
    "sg:postcode":"08206",
    "sg:province":"Barcelona",
    "wof:name":"Peluqueria Formans S.l.",
    "wof:placetype":"venue"
},
  "geometry": {"coordinates":[2.0946390629,41.5573348999],"type":"Point"}
}