{
  "type": "Feature",
  "properties": {
    "addr:full":"Carr Senyera (la), 1 Picanya Valencia 46210",
    "addr:housenumber":"1",
    "addr:postcode":"46210",
    "addr:street":"Carr Senyera La",
    "iso:country":"ES",
    "sg:address":"Carr Senyera (la), 1",
    "sg:city":"Picanya",
    "sg:orig_category":"Florister\u00cdas",
    "sg:phone":"+34 961 59 00 13",
    "sg:postcode":"46210",
    "sg:province":"Valencia",
    "wof:name":"Baixauli Escriva Jose",
    "wof:placetype":"venue"
},
  "geometry": {"coordinates":[-0.4341779947,39.435836792],"type":"Point"}
}