{
  "type": "Feature",
  "properties": {
    "iso:country":"ES",
    "sg:address":"Carrer de Mallorca, 565",
    "sg:city":"Barcelona",
    "sg:orig_category":"Lencer\u00cda Femenina, Corseter\u00cda, Trajes De Ba\u00d1o (al Por Menor)",
    "sg:phone":"+34 934 50 17 49",
    "sg:postcode":"08026",
    "sg:province":"Barcelona",
    "wof:name":"Bejar Saiz Elisabet",
    "wof:placetype":"venue"
},
  "geometry": {"coordinates":[2.1843450069,41.4103851318],"type":"Point"}
}