{
  "type": "Feature",
  "properties": {
    "addr:full":"F. Tirapu, 3 Atarrabia Navarra 31610",
    "addr:housenumber":"3",
    "addr:postcode":"31610",
    "addr:street":"F. Tirapu",
    "iso:country":"ES",
    "sg:address":"F. Tirapu, 3",
    "sg:city":"Atarrabia",
    "sg:orig_category":"Fabricaci\u00d3n De Papel Para Embalar",
    "sg:phone":"+34 948 13 25 01",
    "sg:postcode":"31610",
    "sg:province":"Navarra",
    "wof:name":"Larrainzar Aristu Juana Maria",
    "wof:placetype":"venue"
},
  "geometry": {"coordinates":[-1.6098489761,42.8311386108],"type":"Point"}
}