{
  "type": "Feature",
  "properties": {
    "iso:country":"ES",
    "sg:address":"Calle de Iparraguirre, 4",
    "sg:city":"Sestao",
    "sg:orig_category":"Material Y Suministros Para Peluquer\u00cda",
    "sg:phone":"+34 944 05 74 17",
    "sg:postcode":"48910",
    "sg:province":"Vizcaya",
    "wof:name":"Peluqueria Serezade",
    "wof:placetype":"venue"
},
  "geometry": {"coordinates":[-3.0077490807,43.3076019287],"type":"Point"}
}