{
  "type": "Feature",
  "properties": {
    "iso:country":"ES",
    "sg:address":"Calle de Horizonte, 7",
    "sg:city":"Mairena Aljarafe",
    "sg:orig_category":"Sociedades, Compa\u00d1\u00cdas Aseguradoras",
    "sg:phone":"+34 954 18 16 21",
    "sg:postcode":"41927",
    "sg:province":"Sevilla",
    "wof:name":"Agencia Integral De Seguros Pantoja",
    "wof:placetype":"venue"
},
  "geometry": {"coordinates":[-6.0581693649,37.3535652161],"type":"Point"}
}