{
  "type": "Feature",
  "properties": {
    "addr:full":"Calle de Ancha, 2 Chiclana De La Frontera C\u00e1diz 11130",
    "addr:housenumber":"2",
    "addr:postcode":"11130",
    "addr:street":"Calle De Ancha",
    "iso:country":"ES",
    "sg:address":"Calle de Ancha, 2",
    "sg:city":"Chiclana De La Frontera",
    "sg:orig_category":"M\u00c9dicos: Evaluaci\u00d3n Y Tratamiento Del Dolor",
    "sg:phone":"+34 956 53 13 77",
    "sg:postcode":"11130",
    "sg:province":"C\u00e1diz",
    "wof:name":"Martinez Mariscal Rafael",
    "wof:placetype":"venue"
},
  "geometry": {"coordinates":[-6.1444745064,36.4213447571],"type":"Point"}
}