{
  "type": "Feature",
  "properties": {
    "addr:full":"Calle de Anibal Gonzalez, 17 Dos Hermanas Sevilla 41700",
    "addr:housenumber":"17",
    "addr:postcode":"41700",
    "addr:street":"Calle De Anibal Gonzalez",
    "iso:country":"ES",
    "sg:address":"Calle de Anibal Gonzalez, 17",
    "sg:city":"Dos Hermanas",
    "sg:orig_category":"Enfermeras: Consultas, Atenci\u00d3n A Domicilio",
    "sg:phone":"+34 954 72 11 63",
    "sg:postcode":"41700",
    "sg:province":"Sevilla",
    "wof:name":"Gomez Roman Lucia",
    "wof:placetype":"venue"
},
  "geometry": {"coordinates":[-5.925365448,37.2834625244],"type":"Point"}
}