{
  "type": "Feature",
  "properties": {
    "iso:country":"ES",
    "sg:address":"Carrer de Manlleu, 39",
    "sg:city":"Vic",
    "sg:orig_category":"Motocicletas (agentes, Concesionarios)",
    "sg:phone":"+34 938 86 04 70",
    "sg:postcode":"08500",
    "sg:province":"Barcelona",
    "wof:name":"Roma Junoy Antonio",
    "wof:placetype":"venue"
},
  "geometry": {"coordinates":[2.2552530766,41.9325065613],"type":"Point"}
}