{
  "type": "Feature",
  "properties": {
    "iso:country":"ES",
    "sg:address":"Carr Pintor Joan Massanet, 34",
    "sg:city":"Escala",
    "sg:orig_category":"Bibliotecas, Mediatecas",
    "sg:phone":"+34 972 77 48 48",
    "sg:postcode":"17130",
    "sg:province":"Girona",
    "wof:name":"Ajuntament De L'escala",
    "wof:placetype":"venue"
},
  "geometry": {"coordinates":[3.1324105263,42.1248779297],"type":"Point"}
}