{
  "type": "Feature",
  "properties": {
    "addr:full":"Plaz De La Constitucion, 8 Vinaros Castell\u00f3n 12500",
    "addr:housenumber":"8",
    "addr:postcode":"12500",
    "addr:street":"Plaz;La Constitucion",
    "iso:country":"ES",
    "sg:address":"Plaz De La Constitucion, 8",
    "sg:city":"Vinaros",
    "sg:orig_category":"Contenedores (mercanc\u00cdas)",
    "sg:phone":"+34 964 45 09 68",
    "sg:postcode":"12500",
    "sg:province":"Castell\u00f3n",
    "wof:name":"Solsona Barreda Cristobal",
    "wof:placetype":"venue"
},
  "geometry": {"coordinates":[0.4749450088,40.4711990356],"type":"Point"}
}