{
  "type": "Feature",
  "properties": {
    "iso:country":"ES",
    "sg:address":"Carrer de Arago, 54",
    "sg:city":"Barcelona",
    "sg:orig_category":"Reposter\u00cdas",
    "sg:phone":"+34 934 23 99 56",
    "sg:postcode":"08015",
    "sg:province":"Barcelona",
    "wof:name":"Garcia Sanz Carlos",
    "wof:placetype":"venue"
},
  "geometry": {"coordinates":[2.1511869431,41.3816757202],"type":"Point"}
}