{
  "type": "Feature",
  "properties": {
    "addr:full":"Plaz Caserna (de La), 4 Fuentidue\u00e7a De Tajo Madrid 28597",
    "addr:housenumber":"4",
    "addr:postcode":"28597",
    "addr:street":"Plaz;Fuentiduec\u0327A",
    "iso:country":"ES",
    "sg:address":"Plaz Caserna (de La), 4",
    "sg:city":"Fuentidue\u00e7a De Tajo",
    "sg:orig_category":"Deportes Y Programas De Aventura",
    "sg:phone":"+34 918 72 85 31",
    "sg:postcode":"28597",
    "sg:province":"Madrid",
    "wof:name":"Gomez Moreno Maria Rosa",
    "wof:placetype":"venue"
},
  "geometry": {"coordinates":[-3.1574640274,40.1190032959],"type":"Point"}
}