{
  "type": "Feature",
  "properties": {
    "addr:full":"Luga Molino Garre, 29 Fuente Amarga Murcia 30593",
    "addr:housenumber":"29",
    "addr:postcode":"30593",
    "addr:street":"Garre",
    "iso:country":"ES",
    "sg:address":"Luga Molino Garre, 29",
    "sg:city":"Fuente Amarga",
    "sg:orig_category":"Producci\u00d3n, Venta De Productos De Agricultura Biol\u00d3gica",
    "sg:phone":"+34 968 55 41 15",
    "sg:postcode":"30593",
    "sg:province":"Murcia",
    "wof:name":"Angel C. Soto Armero S.l.",
    "wof:placetype":"venue"
},
  "geometry": {"coordinates":[-1.1298867464,37.9834747314],"type":"Point"}
}