{
  "type": "Feature",
  "properties": {
    "addr:full":"Carrer de Ventura I Gassol, 3 Reus Tarragona 43203",
    "addr:housenumber":"3",
    "addr:postcode":"43203",
    "addr:street":"Carrer De Ventura;Gassol",
    "iso:country":"ES",
    "sg:address":"Carrer de Ventura I Gassol, 3",
    "sg:city":"Reus",
    "sg:orig_category":"Agencias Y Agentes Comerciales, Representantes",
    "sg:phone":"+34 977 34 55 55",
    "sg:postcode":"43203",
    "sg:province":"Tarragona",
    "wof:name":"Josepa Gallisa S.c.p.",
    "wof:placetype":"venue"
},
  "geometry": {"coordinates":[1.1138290167,41.1621742249],"type":"Point"}
}