{
  "type": "Feature",
  "properties": {
    "iso:country":"ES",
    "sg:address":"Carrer de Fossar (el), 2",
    "sg:city":"Mutxamel",
    "sg:orig_category":"Aceites Y Grasas Alimentarias (fabricaci\u00d3n, Al Por Mayor)",
    "sg:phone":"+34 965 95 52 25",
    "sg:postcode":"03110",
    "sg:province":"Alicante",
    "wof:name":"Pastor Perez Jose",
    "wof:placetype":"venue"
},
  "geometry": {"coordinates":[-0.4448589981,38.4142990112],"type":"Point"}
}