{
  "type": "Feature",
  "properties": {
    "addr:full":"Avda Santa Marina, 8 Badajoz Badajoz 06005",
    "addr:housenumber":"8",
    "addr:postcode":"06005",
    "addr:street":"Avda Santa Marina",
    "iso:country":"ES",
    "sg:address":"Avda Santa Marina, 8",
    "sg:city":"Badajoz",
    "sg:orig_category":"Complementos De Vestir (al Por Menor)",
    "sg:phone":"+34 924 22 33 30",
    "sg:postcode":"06005",
    "sg:province":"Badajoz",
    "wof:name":"Ambrona Fernandez De Tejada Maria Elena",
    "wof:placetype":"venue"
},
  "geometry": {"coordinates":[-6.9758653641,38.8736114502],"type":"Point"}
}