{
  "type": "Feature",
  "properties": {
    "iso:country":"ES",
    "sg:address":"Calle de Ollerias, 31",
    "sg:city":"Andujar",
    "sg:orig_category":"Internados & Ense\u00d1anza Privada",
    "sg:phone":"+34 953 50 02 39",
    "sg:postcode":"23740",
    "sg:province":"Ja\u00e9n",
    "wof:name":"Colegio Virgen De La Cabeza",
    "wof:placetype":"venue"
},
  "geometry": {"coordinates":[-4.0538630486,38.0385513306],"type":"Point"}
}