{
  "type": "Feature",
  "properties": {
    "iso:country":"ES",
    "sg:address":"Pase General Davila, 204",
    "sg:city":"Santander",
    "sg:orig_category":"Edici\u00d3n De Diarios, Revistas, Boletines",
    "sg:phone":"+34 942 37 14 34",
    "sg:postcode":"39006",
    "sg:province":"Cantabria",
    "wof:name":"Fernandez-navamuel Argueso Juan Carlos",
    "wof:placetype":"venue"
},
  "geometry": {"coordinates":[-3.8112130165,43.4677047729],"type":"Point"}
}