{
  "type": "Feature",
  "properties": {
    "addr:full":"Calle de Ercilla, 4 Bilbao Vizcaya 48009",
    "addr:housenumber":"4",
    "addr:postcode":"48009",
    "addr:street":"Calle De Ercilla",
    "iso:country":"ES",
    "sg:address":"Calle de Ercilla, 4",
    "sg:city":"Bilbao",
    "sg:orig_category":"Negocio De Materiales De Construcci\u00d3n",
    "sg:phone":"+34 944 24 21 01",
    "sg:postcode":"48009",
    "sg:province":"Vizcaya",
    "wof:name":"Ecobrick 2001,s.l.",
    "wof:placetype":"venue"
},
  "geometry": {"coordinates":[-2.9302020073,43.2653961182],"type":"Point"}
}