{
  "type": "Feature",
  "properties": {
    "iso:country":"ES",
    "sg:address":"Avda Espa\u00d1a, 29",
    "sg:city":"Albacete",
    "sg:orig_category":"Supermercados Y Hipermercados",
    "sg:phone":"+34 967 22 61 51",
    "sg:postcode":"02002",
    "sg:province":"Albacete",
    "wof:name":"Caprabo S.a.",
    "wof:placetype":"venue"
},
  "geometry": {"coordinates":[-1.8538769484,38.9862785339],"type":"Point"}
}