{
  "type": "Feature",
  "properties": {
    "iso:country":"ES",
    "sg:address":"Calle de Zamacola, 92",
    "sg:city":"Bilbao",
    "sg:orig_category":"Plomeros",
    "sg:phone":"+34 944 15 39 86",
    "sg:postcode":"48003",
    "sg:province":"Vizcaya",
    "wof:name":"Valderrama Arribas Amos",
    "wof:placetype":"venue"
},
  "geometry": {"coordinates":[-2.9247100353,43.2449798584],"type":"Point"}
}