{
  "type": "Feature",
  "properties": {
    "iso:country":"ES",
    "sg:address":"Calle de F(campollano), 38",
    "sg:city":"Albacete",
    "sg:orig_category":"Panader\u00cdas, Pasteler\u00cdas, Boller\u00cda Industriale (fabricaci\u00d3n, Al Por Mayor)",
    "sg:phone":"+34 967 24 27 29",
    "sg:postcode":"02006",
    "sg:province":"Albacete",
    "sg:website":"www.imc-albacete.com",
    "wof:name":"Innovaciones Mecanicas Campollano S.a.l.",
    "wof:placetype":"venue"
},
  "geometry": {"coordinates":[-1.9356930256,39.0582275391],"type":"Point"}
}