{
  "type": "Feature",
  "properties": {
    "iso:country":"ES",
    "sg:address":"Calle de Santo Domingo, 17",
    "sg:city":"Santa Cruz De Tenerife",
    "sg:orig_category":"Bazares, Art\u00cdculos De Limpieza Y De Cocina (al Por Menor)",
    "sg:phone":"+34 922 24 17 24",
    "sg:postcode":"38003",
    "sg:province":"Santa Cruz De Tenerife",
    "wof:name":"Rony S. L.",
    "wof:placetype":"venue"
},
  "geometry": {"coordinates":[-16.2496967316,28.4655189514],"type":"Point"}
}