{
  "type": "Feature",
  "properties": {
    "addr:full":"Avda. F. Salvador, 50 Castello Plana Castell\u00f3n 12100",
    "addr:housenumber":"50",
    "addr:postcode":"12100",
    "addr:street":"Avda. F. Salvador;Castello\u0301N",
    "iso:country":"ES",
    "sg:address":"Avda. F. Salvador, 50",
    "sg:city":"Castello Plana",
    "sg:orig_category":"Alimentaci\u00d3n General (al Por Menor)",
    "sg:phone":"+34 964 28 64 06",
    "sg:postcode":"12100",
    "sg:province":"Castell\u00f3n",
    "wof:name":"Dreams Of Valencia Sl",
    "wof:placetype":"venue"
},
  "geometry": {"coordinates":[0.0176999997,39.9888801575],"type":"Point"}
}