{
  "type": "Feature",
  "properties": {
    "addr:full":"Camino De Quintanar, S/n Villanueva Jara Cuenca 16230",
    "addr:housenumber":"s",
    "addr:postcode":"16230",
    "addr:street":"Camino De Quintanar;/ N;Jara",
    "iso:country":"ES",
    "sg:address":"Camino De Quintanar, S/n",
    "sg:city":"Villanueva Jara",
    "sg:orig_category":"Piedra Natural",
    "sg:phone":"+34 967 49 80 33",
    "sg:postcode":"16230",
    "sg:province":"Cuenca",
    "wof:name":"Minaya Carretero Martin",
    "wof:placetype":"venue"
},
  "geometry": {"coordinates":[-1.9515190125,39.4365196228],"type":"Point"}
}