{
  "type": "Feature",
  "properties": {
    "iso:country":"ES",
    "sg:address":"Avda Aurora, 17",
    "sg:city":"Malaga",
    "sg:orig_category":"Muebles",
    "sg:phone":"+34 952 36 90 53",
    "sg:postcode":"29002",
    "sg:province":"M\u00e1laga",
    "sg:website":"www.natuzzi.es",
    "wof:name":"Natuzzi Iberica S. A.",
    "wof:placetype":"venue"
},
  "geometry": {"coordinates":[-4.4306488037,36.7159233093],"type":"Point"}
}