{
  "type": "Feature",
  "properties": {
    "iso:country":"ES",
    "sg:address":"Calle de Tinte, 13",
    "sg:city":"Albacete",
    "sg:orig_category":"Bisuter\u00cda, Joyer\u00cda, Relojer\u00cda (al Por Menor)",
    "sg:phone":"+34 967 24 70 75",
    "sg:postcode":"02001",
    "sg:province":"Albacete",
    "wof:name":"Iniesta Martinez Miguel",
    "wof:placetype":"venue"
},
  "geometry": {"coordinates":[-1.8557709455,38.9930114746],"type":"Point"}
}