{
  "type": "Feature",
  "properties": {
    "addr:full":"Carrer de Mar (la), 149 Altea Alicante 03590",
    "addr:housenumber":"149",
    "addr:postcode":"03590",
    "addr:street":"Carrer De Mar La",
    "iso:country":"ES",
    "sg:address":"Carrer de Mar (la), 149",
    "sg:city":"Altea",
    "sg:orig_category":"Mudanzas",
    "sg:phone":"+34 965 84 15 92",
    "sg:postcode":"03590",
    "sg:province":"Alicante",
    "wof:name":"Garcia Diaz German",
    "wof:placetype":"venue"
},
  "geometry": {"coordinates":[-0.054051999,38.594078064],"type":"Point"}
}