{
  "type": "Feature",
  "properties": {
    "addr:full":"Carr Alfons Xii, 23 Badalona Barcelona 08912",
    "addr:housenumber":"23",
    "addr:postcode":"08912",
    "addr:street":"Carr Alfons Xii",
    "iso:country":"ES",
    "sg:address":"Carr Alfons Xii, 23",
    "sg:city":"Badalona",
    "sg:orig_category":"Institutos De Belleza",
    "sg:phone":"+34 933 99 54 64",
    "sg:postcode":"08912",
    "sg:province":"Barcelona",
    "wof:name":"Sol Badalona 2 S.l.",
    "wof:placetype":"venue"
},
  "geometry": {"coordinates":[2.2427821159,41.4464149475],"type":"Point"}
}