{
  "type": "Feature",
  "properties": {
    "iso:country":"ES",
    "sg:address":"Avda Iparragirre, 62",
    "sg:city":"Elexalde",
    "sg:orig_category":"Papeler\u00cdas, Librer\u00cdas",
    "sg:phone":"+34 944 31 66 11",
    "sg:postcode":"48940",
    "sg:province":"Vizcaya",
    "wof:name":"Laseca Garcia Rosa Maria",
    "wof:placetype":"venue"
},
  "geometry": {"coordinates":[-2.9882650375,43.3259124756],"type":"Point"}
}