{
  "type": "Feature",
  "properties": {
    "iso:country":"ES",
    "sg:address":"Carrer de Cervantes, 36",
    "sg:city":"S. Just Desvern",
    "sg:orig_category":"Mec\u00c1nico Del Autom\u00d3vil",
    "sg:phone":"+34 933 72 41 45",
    "sg:postcode":"08960",
    "sg:province":"Barcelona",
    "wof:name":"Manteniment Integral Automovil Suauto S.l.",
    "wof:placetype":"venue"
},
  "geometry": {"coordinates":[2.0686230659,41.3824234009],"type":"Point"}
}