{
  "type": "Feature",
  "properties": {
    "iso:country":"ES",
    "sg:address":"Calle de Cardenal Cisneros, 49",
    "sg:city":"Rociana Condado",
    "sg:orig_category":"Negocio De Materiales De Construcci\u00d3n",
    "sg:phone":"+34 959 41 67 15",
    "sg:postcode":"21720",
    "sg:province":"Huelva",
    "wof:name":"Macomusan C.b.",
    "wof:placetype":"venue"
},
  "geometry": {"coordinates":[-6.5925168991,37.30991745],"type":"Point"}
}