{
  "type": "Feature",
  "properties": {
    "addr:full":"Calle de Ronda Norte, S/n Javea Alicante 03730",
    "addr:housenumber":"s / n",
    "addr:postcode":"03730",
    "addr:street":"Calle De Ronda Norte",
    "iso:country":"ES",
    "sg:address":"Calle de Ronda Norte, S/n",
    "sg:city":"Javea",
    "sg:orig_category":"Cajas De Ahorro",
    "sg:phone":"+34 965 79 35 71",
    "sg:postcode":"03730",
    "sg:province":"Alicante",
    "wof:name":"Caja De Ahorros De Valencia Castellon Y Alicante",
    "wof:placetype":"venue"
},
  "geometry": {"coordinates":[0.1668650061,38.7890739441],"type":"Point"}
}