{
  "type": "Feature",
  "properties": {
    "addr:full":"Carrer de Pedrell, 40 Barcelona Barcelona 08032",
    "addr:housenumber":"40",
    "addr:postcode":"08032",
    "addr:street":"Carrer De Pedrell",
    "iso:country":"ES",
    "sg:address":"Carrer de Pedrell, 40",
    "sg:city":"Barcelona",
    "sg:orig_category":"Agencias Y Agentes Comerciales, Representantes",
    "sg:phone":"+34 933 57 50 62",
    "sg:postcode":"08032",
    "sg:province":"Barcelona",
    "wof:name":"Garriga Comas Juan",
    "wof:placetype":"venue"
},
  "geometry": {"coordinates":[2.1670811176,41.424785614],"type":"Point"}
}