{
  "type": "Feature",
  "properties": {
    "addr:full":"Avenida Cedrun, 3 Revilla Cantabria 39788",
    "addr:housenumber":"3",
    "addr:postcode":"39788",
    "addr:street":"Avenida Cedrun",
    "iso:country":"ES",
    "sg:address":"Avenida Cedrun, 3",
    "sg:city":"Revilla",
    "sg:orig_category":"Empresarios",
    "sg:phone":"+34 942 85 01 50",
    "sg:postcode":"39788",
    "sg:province":"Cantabria",
    "wof:name":"Villota Sagastibelza Maria Angeles",
    "wof:placetype":"venue"
},
  "geometry": {"coordinates":[-3.3257288933,43.3466300964],"type":"Point"}
}