{
  "type": "Feature",
  "properties": {
    "iso:country":"ES",
    "sg:address":"Carrer de Enric Prat De La Riba, 158",
    "sg:city":"Hospitalet Llobregat",
    "sg:orig_category":"Negocio De Materiales De Construcci\u00d3n",
    "sg:phone":"+34 933 37 23 21",
    "sg:postcode":"08901",
    "sg:province":"Barcelona",
    "wof:name":"Arrufi Calvet Enrique",
    "wof:placetype":"venue"
},
  "geometry": {"coordinates":[2.1079037189,41.3620185852],"type":"Point"}
}