{
  "type": "Feature",
  "properties": {
    "iso:country":"ES",
    "sg:address":"Literato Padre Galiana, 8",
    "sg:city":"Ontinyent",
    "sg:orig_category":"Asesor\u00cda Sobre Comunicaci\u00d3n De Empresas",
    "sg:phone":"+34 962 91 50 88",
    "sg:postcode":"46870",
    "sg:province":"Valencia",
    "wof:name":"Ferrero Gramage Psico Asesores S.l.",
    "wof:placetype":"venue"
},
  "geometry": {"coordinates":[-0.6109780073,38.8195762634],"type":"Point"}
}