{
  "type": "Feature",
  "properties": {
    "iso:country":"ES",
    "sg:address":"Poli Industrial 1 De Mayo, S/n",
    "sg:city":"Miajadas",
    "sg:orig_category":"Empresas De Desmonte",
    "sg:phone":"+34 927 34 84 86",
    "sg:postcode":"10100",
    "sg:province":"C\u00e1ceres",
    "wof:name":"Exconsa Miajadas S.l.",
    "wof:placetype":"venue"
},
  "geometry": {"coordinates":[-5.9082989693,39.1555213928],"type":"Point"}
}