{
  "type": "Feature",
  "properties": {
    "addr:full":"Poli Poligono Industrial, S/n Montehermoso C\u00e1ceres 10810",
    "addr:postcode":"10810",
    "addr:street":"Poligono Industrial S / N;Ca\u0301Ceres",
    "iso:country":"ES",
    "sg:address":"Poli Poligono Industrial, S/n",
    "sg:city":"Montehermoso",
    "sg:orig_category":"Conservas De Legumbres (fabricaci\u00d3n, Al Por Mayor)",
    "sg:phone":"+34 927 43 03 43",
    "sg:postcode":"10810",
    "sg:province":"C\u00e1ceres",
    "sg:website":"www. acenorca.com",
    "wof:name":"Acenorca Aceitunera Del Norte De Caceres Sociedad Cooperativa Limitada",
    "wof:placetype":"venue"
},
  "geometry": {"coordinates":[-6.3487591743,40.088508606],"type":"Point"}
}