{
  "type": "Feature",
  "properties": {
    "addr:full":"Carr Ciutat De Valencia, 118 Cullera Valencia 46400",
    "addr:housenumber":"118",
    "addr:postcode":"46400",
    "addr:street":"Carr Ciutat De Valencia",
    "iso:country":"ES",
    "sg:address":"Carr Ciutat De Valencia, 118",
    "sg:city":"Cullera",
    "sg:orig_category":"Farmacias",
    "sg:phone":"+34 961 72 53 14",
    "sg:postcode":"46400",
    "sg:province":"Valencia",
    "wof:name":"Albanell Monzo Francisco Juan",
    "wof:placetype":"venue"
},
  "geometry": {"coordinates":[-0.2418356985,39.1610794067],"type":"Point"}
}