{
  "type": "Feature",
  "properties": {
    "iso:country":"ES",
    "sg:address":"Afueras, S/n",
    "sg:city":"Montu\u00efri",
    "sg:orig_category":"Materiales De Construcci\u00d3n (en General)",
    "sg:phone":"+34 971 16 15 01",
    "sg:postcode":"07230",
    "sg:province":"Islas Baleares",
    "wof:name":"Empresas Impasa A.i.e.",
    "wof:placetype":"venue"
},
  "geometry": {"coordinates":[2.9810760021,39.5683860779],"type":"Point"}
}