{
  "type": "Feature",
  "properties": {
    "addr:full":"C/ Cala Antena, 2 Cales Mallorca Islas Baleares 07689",
    "addr:housenumber":"2",
    "addr:postcode":"07689",
    "addr:street":"C / Cala Antena",
    "iso:country":"ES",
    "sg:address":"C/ Cala Antena, 2",
    "sg:city":"Cales Mallorca",
    "sg:orig_category":"Centros Empresariales",
    "sg:phone":"+34 971 83 37 91",
    "sg:postcode":"07689",
    "sg:province":"Islas Baleares",
    "wof:name":"Mantenimientos Gil S.l",
    "wof:placetype":"venue"
},
  "geometry": {"coordinates":[3.2705500126,39.4597702026],"type":"Point"}
}