{
  "type": "Feature",
  "properties": {
    "addr:full":"Calle de Santiago Ramon Y Cajal (de), 1 Humanes De Madrid Madrid 28970",
    "addr:postcode":"28970",
    "addr:street":"Calle De Santiago Ramon Y Cajal De 1",
    "iso:country":"ES",
    "sg:address":"Calle de Santiago Ramon Y Cajal (de), 1",
    "sg:city":"Humanes De Madrid",
    "sg:orig_category":"Peluquer\u00cdas, Peluquer\u00cda Mixta",
    "sg:phone":"+34 916 04 90 31",
    "sg:postcode":"28970",
    "sg:province":"Madrid",
    "wof:name":"Garcia-ochoa Perez Raquel",
    "wof:placetype":"venue"
},
  "geometry": {"coordinates":[-3.8227360249,40.2582473755],"type":"Point"}
}