{
  "type": "Feature",
  "properties": {
    "iso:country":"ES",
    "sg:address":"Ctra General Mao - Ciutadella, Km. 0041,6",
    "sg:city":"Tudons",
    "sg:orig_category":"Construcciones Met\u00c1licas",
    "sg:phone":"+34 971 48 40 34",
    "sg:postcode":"07760",
    "sg:province":"Islas Baleares",
    "wof:name":"Industrial Menorquina Prefabricados S.l.",
    "wof:placetype":"venue"
},
  "geometry": {"coordinates":[3.8416149616,40.0027542114],"type":"Point"}
}