{
  "type": "Feature",
  "properties": {
    "iso:country":"ES",
    "sg:address":"Calle de Pavia, S/n",
    "sg:city":"Sauquillo Cabezas",
    "sg:orig_category":"Carnicer\u00cdas, Carnicer\u00cdas",
    "sg:phone":"+34 921 50 96 94",
    "sg:postcode":"40351",
    "sg:province":"Segovia",
    "wof:name":"Sanz Bermejo Pedro",
    "wof:placetype":"venue"
},
  "geometry": {"coordinates":[-4.0686268806,41.1938323975],"type":"Point"}
}