{
  "type": "Feature",
  "properties": {
    "iso:country":"ES",
    "sg:address":"Carr Navegant, 3",
    "sg:city":"Grau I Platja",
    "sg:orig_category":"Molduras, Junquillos, Listones Y Molduras Perforadas",
    "sg:phone":"+34 962 84 03 22",
    "sg:postcode":"46730",
    "sg:province":"Valencia",
    "wof:name":"Martinez Lafuente Jose Antonio",
    "wof:placetype":"venue"
},
  "geometry": {"coordinates":[-0.1629489958,39.0037536621],"type":"Point"}
}