{
  "type": "Feature",
  "properties": {
    "iso:country":"ES",
    "sg:address":"Bovila, S/n",
    "sg:city":"S. Vicen\u00e7 Castellet",
    "sg:orig_category":"Cajas Y Embalajes De Pl\u00c1stico",
    "sg:phone":"+34 938 33 18 79",
    "sg:postcode":"08295",
    "sg:province":"Barcelona",
    "sg:website":"www.sanviplast.com",
    "wof:name":"Sanviplast S.a.",
    "wof:placetype":"venue"
},
  "geometry": {"coordinates":[1.8631989956,41.6670608521],"type":"Point"}
}