{
  "type": "Feature",
  "properties": {
    "iso:country":"ES",
    "sg:address":"Cra. Nal. Tres-cents Quaranta, 203",
    "sg:city":"Tarragona",
    "sg:orig_category":"Mec\u00c1nico Del Autom\u00d3vil",
    "sg:phone":"+34 977 54 94 70",
    "sg:postcode":"43006",
    "sg:province":"Tarragona",
    "wof:name":"Torres Mora Alfonso",
    "wof:placetype":"venue"
},
  "geometry": {"coordinates":[1.2002199888,41.1216697693],"type":"Point"}
}