{
  "type": "Feature",
  "properties": {
    "iso:country":"ES",
    "sg:address":"Calle de Alcalde Juan Narvaez Ortega, 1",
    "sg:city":"Jerez De La Frontera",
    "sg:orig_category":"T\u00c9cnicos Veterinarios",
    "sg:phone":"+34 956 34 03 05",
    "sg:postcode":"11405",
    "sg:province":"C\u00e1diz",
    "wof:name":"Perez Gavilan Rafael Isidoro",
    "wof:placetype":"venue"
},
  "geometry": {"coordinates":[-6.1299495697,36.6877212524],"type":"Point"}
}