{
  "type": "Feature",
  "properties": {
    "addr:full":"Calle de Barrameda, 30 Sanlucar De Barrameda C\u00e1diz 11540",
    "addr:housenumber":"30",
    "addr:postcode":"11540",
    "addr:street":"Calle De Barrameda;Ca\u0301Diz",
    "iso:country":"ES",
    "sg:address":"Calle de Barrameda, 30",
    "sg:city":"Sanlucar De Barrameda",
    "sg:orig_category":"Zapatos (al Por Menor)",
    "sg:phone":"+34 956 38 18 83",
    "sg:postcode":"11540",
    "sg:province":"C\u00e1diz",
    "wof:name":"Moreno Tejero Antonio",
    "wof:placetype":"venue"
},
  "geometry": {"coordinates":[-6.3352851868,36.80493927],"type":"Point"}
}