{
  "type": "Feature",
  "properties": {
    "addr:full":"Rua San Pedro De Mezonzo (de), 6 Santiago De Compostela A Coru\u00f1a 15701",
    "addr:housenumber":"6",
    "addr:postcode":"15701",
    "addr:street":"Rua San Pedro De Mezonzo De;Corun\u0303A",
    "iso:country":"ES",
    "sg:address":"Rua San Pedro De Mezonzo (de), 6",
    "sg:city":"Santiago De Compostela",
    "sg:orig_category":"Peluquer\u00cdas, Peluquer\u00cda Mixta",
    "sg:phone":"+34 981 59 95 67",
    "sg:postcode":"15701",
    "sg:province":"A Coru\u00f1a",
    "wof:name":"Servigal S.l.",
    "wof:placetype":"venue"
},
  "geometry": {"coordinates":[-8.5491933823,42.8738937378],"type":"Point"}
}