{
  "type": "Feature",
  "properties": {
    "addr:full":"Calle de Carmen, 25 Madrid Madrid 28013",
    "addr:housenumber":"25",
    "addr:postcode":"madrid;28013",
    "addr:street":"Calle De Carmen",
    "iso:country":"ES",
    "sg:address":"Calle de Carmen, 25",
    "sg:city":"Madrid",
    "sg:orig_category":"Bisuter\u00cda, Joyer\u00cda, Relojer\u00cda (al Por Menor)",
    "sg:phone":"+34 915 31 43 18",
    "sg:postcode":"28013",
    "sg:province":"Madrid",
    "wof:name":"Fontivilla S.l.",
    "wof:placetype":"venue"
},
  "geometry": {"coordinates":[-3.7048022747,40.4187698364],"type":"Point"}
}