{
  "type": "Feature",
  "properties": {
    "addr:full":"Calle de Mayor, 36 Beniajan Murcia 30570",
    "addr:housenumber":"36",
    "addr:postcode":"30570",
    "addr:street":"Calle De Mayor",
    "iso:country":"ES",
    "sg:address":"Calle de Mayor, 36",
    "sg:city":"Beniajan",
    "sg:orig_category":"Cajas De Ahorro",
    "sg:phone":"+34 968 83 70 53",
    "sg:postcode":"30570",
    "sg:province":"Murcia",
    "sg:website":"www.cam.es",
    "wof:name":"Caja De Ahorros Del Mediterraneo",
    "wof:placetype":"venue"
},
  "geometry": {"coordinates":[-1.0728900433,37.9755706787],"type":"Point"}
}