{
  "type": "Feature",
  "properties": {
    "addr:full":"Calle de Antonio Jose De Sucre, 6 Playa Del Hombre Las Palmas 35214",
    "addr:housenumber":"6",
    "addr:postcode":"35214",
    "addr:street":"Calle De Antonio Jose De Sucre;Del Hombre Las",
    "iso:country":"ES",
    "sg:address":"Calle de Antonio Jose De Sucre, 6",
    "sg:city":"Playa Del Hombre",
    "sg:orig_category":"Florister\u00cdas",
    "sg:phone":"+34 928 13 60 09",
    "sg:postcode":"35214",
    "sg:province":"Las Palmas",
    "wof:name":"Floridiscatel S.l.",
    "wof:placetype":"venue"
},
  "geometry": {"coordinates":[-15.3881549835,27.9987411499],"type":"Point"}
}