{
  "type": "Feature",
  "properties": {
    "iso:country":"ES",
    "sg:address":"Carrer de Saragossa, 6",
    "sg:city":"Sitges",
    "sg:orig_category":"Centros Empresariales",
    "sg:phone":"+34 938 11 20 82",
    "sg:postcode":"08870",
    "sg:province":"Barcelona",
    "wof:name":"Kling  Laurence",
    "wof:placetype":"venue"
},
  "geometry": {"coordinates":[1.7955379486,41.2325553894],"type":"Point"}
}