{
  "type": "Feature",
  "properties": {
    "addr:full":"Carrer de Cartella, 50 Barcelona Barcelona 08031",
    "addr:housenumber":"50",
    "addr:postcode":"08031",
    "addr:street":"Carrer De Cartella",
    "iso:country":"ES",
    "sg:address":"Carrer de Cartella, 50",
    "sg:city":"Barcelona",
    "sg:orig_category":"Publicidad (soportes Y Gesti\u00d3n)",
    "sg:phone":"+34 934 29 98 35",
    "sg:postcode":"08031",
    "sg:province":"Barcelona",
    "wof:name":"Li\u00f1an Serra Miguel",
    "wof:placetype":"venue"
},
  "geometry": {"coordinates":[2.171548605,41.4280319214],"type":"Point"}
}