{
  "type": "Feature",
  "properties": {
    "iso:country":"ES",
    "sg:address":"Calle de Doctor Villacian, 41",
    "sg:city":"Valladolid",
    "sg:orig_category":"Venta, Localizaci\u00d3n, Reparaci\u00d3n De Material E Instrumental M\u00c9dico",
    "sg:phone":"+34 983 38 08 77",
    "sg:postcode":"47014",
    "sg:province":"Valladolid",
    "wof:name":"Medical Instruments S.l.",
    "wof:placetype":"venue"
},
  "geometry": {"coordinates":[-4.7528715134,41.6380844116],"type":"Point"}
}