{
  "type": "Feature",
  "properties": {
    "iso:country":"ES",
    "sg:address":"Calle de Arostegieta Kalea, 6",
    "sg:city":"Tolosa",
    "sg:orig_category":"Cl\u00cdnicas Dentales",
    "sg:phone":"+34 943 67 29 99",
    "sg:postcode":"20400",
    "sg:province":"Guip\u00f9zcoa",
    "wof:name":"Juan Carlos Aguirrezabal Loyarte Cb",
    "wof:placetype":"venue"
},
  "geometry": {"coordinates":[-2.0737559795,43.1374893188],"type":"Point"}
}