{
  "type": "Feature",
  "properties": {
    "addr:full":"Sortetes, 1 Javea Alicante 03730",
    "addr:housenumber":"1",
    "addr:postcode":"03730",
    "addr:street":"Sortetes",
    "iso:country":"ES",
    "sg:address":"Sortetes, 1",
    "sg:city":"Javea",
    "sg:orig_category":"Cerrajer\u00cda, Ferrallista",
    "sg:phone":"+34 965 79 35 34",
    "sg:postcode":"03730",
    "sg:province":"Alicante",
    "wof:name":"Llido Crua\u00f1es Bartolome",
    "wof:placetype":"venue"
},
  "geometry": {"coordinates":[0.1612470001,38.7844429016],"type":"Point"}
}