{
  "type": "Feature",
  "properties": {
    "addr:full":"Calle de Rosales, 75 Piedralaves \u00c1vila 05440",
    "addr:housenumber":"75",
    "addr:postcode":"05440",
    "addr:street":"Calle De Rosales",
    "iso:country":"ES",
    "sg:address":"Calle de Rosales, 75",
    "sg:city":"Piedralaves",
    "sg:orig_category":"Iglesia Cat\u00d3lica",
    "sg:phone":"+34 918 66 51 18",
    "sg:postcode":"05440",
    "sg:province":"\u00c1vila",
    "wof:name":"Parroquia San Antonio De Padua",
    "wof:placetype":"venue"
},
  "geometry": {"coordinates":[-4.6975989342,40.3173294067],"type":"Point"}
}