{
  "type": "Feature",
  "properties": {
    "iso:country":"ES",
    "sg:address":"Calle de Antonia Diaz, 46",
    "sg:city":"Dos Hermanas",
    "sg:orig_category":"\u00d3ptica: Instrumentos (fabricaci\u00d3n)",
    "sg:phone":"+34 954 72 80 00",
    "sg:postcode":"41700",
    "sg:province":"Sevilla",
    "wof:name":"Centro Optico Camero S.l.",
    "wof:placetype":"venue"
},
  "geometry": {"coordinates":[-5.9237117767,37.2822799683],"type":"Point"}
}