{
  "type": "Feature",
  "properties": {
    "addr:full":"G.v. Puig De Teix, 7 Santa Pon\u00c7a Islas Baleares 07180",
    "addr:housenumber":"7",
    "addr:postcode":"07180",
    "addr:street":"Teix",
    "iso:country":"ES",
    "sg:address":"G.v. Puig De Teix, 7",
    "sg:city":"Santa Pon\u00c7a",
    "sg:orig_category":"Papeler\u00cdas, Librer\u00cdas",
    "sg:phone":"+34 971 69 50 16",
    "sg:postcode":"07180",
    "sg:province":"Islas Baleares",
    "wof:name":"Grondona Martinez Manuel",
    "wof:placetype":"venue"
},
  "geometry": {"coordinates":[2.4850165844,39.5175361633],"type":"Point"}
}