{
  "type": "Feature",
  "properties": {
    "addr:full":"Avda Compostilla, 34 Ponferrada Le\u00f3n 24400",
    "addr:housenumber":"34",
    "addr:postcode":"24400",
    "addr:street":"Avda Compostilla",
    "iso:country":"ES",
    "sg:address":"Avda Compostilla, 34",
    "sg:city":"Ponferrada",
    "sg:orig_category":"Internados & Ense\u00d1anza Privada",
    "sg:phone":"+34 987 41 12 50",
    "sg:postcode":"24400",
    "sg:province":"Le\u00f3n",
    "wof:name":"Diocesis Astorga Administracion",
    "wof:placetype":"venue"
},
  "geometry": {"coordinates":[-6.5974030495,42.5514907837],"type":"Point"}
}