{
  "type": "Feature",
  "properties": {
    "iso:country":"ES",
    "sg:address":"Calle de Serrallo, 3",
    "sg:city":"Linares",
    "sg:orig_category":"Farmacias",
    "sg:phone":"+34 953 69 15 56",
    "sg:postcode":"23700",
    "sg:province":"Ja\u00e9n",
    "wof:name":"Gonzalez Mu\u00f1oz Baltasar",
    "wof:placetype":"venue"
},
  "geometry": {"coordinates":[-3.636950016,38.095905304],"type":"Point"}
}