{
  "type": "Feature",
  "properties": {
    "iso:country":"ES",
    "sg:address":"Calle de Practicante Jose Toajas, 16",
    "sg:city":"Cabezas S. Juan",
    "sg:orig_category":"Bazares, Art\u00cdculos De Limpieza Y De Cocina (al Por Menor)",
    "sg:phone":"+34 955 87 05 41",
    "sg:postcode":"41730",
    "sg:province":"Sevilla",
    "wof:name":"Bazar Quiros Guisado S.l.",
    "wof:placetype":"venue"
},
  "geometry": {"coordinates":[-5.9387898445,36.984085083],"type":"Point"}
}