{
  "type": "Feature",
  "properties": {
    "iso:country":"ES",
    "sg:address":"Carr Clos (del), 16",
    "sg:city":"Agramunt",
    "sg:orig_category":"Cr\u00cda De Cerdos",
    "sg:phone":"+34 973 39 22 89",
    "sg:postcode":"25310",
    "sg:province":"Lleida",
    "wof:name":"Roca Tiurana S.l.",
    "wof:placetype":"venue"
},
  "geometry": {"coordinates":[1.0938349962,41.7863693237],"type":"Point"}
}