{
  "type": "Feature",
  "properties": {
    "iso:country":"ES",
    "sg:address":"Carrer de Illes Balears, 1",
    "sg:city":"Granja",
    "sg:orig_category":"Asesor\u00cda Fiscal Y Jur\u00cddica",
    "sg:phone":"+34 977 54 20 16",
    "sg:postcode":"43006",
    "sg:province":"Tarragona",
    "wof:name":"Asein Tarragona S.l.",
    "wof:placetype":"venue"
},
  "geometry": {"coordinates":[1.2154294252,41.1208610535],"type":"Point"}
}