{
  "type": "Feature",
  "properties": {
    "addr:full":"Calle de Santa Isabel, 6 Madrid Madrid 28012",
    "addr:housenumber":"6",
    "addr:postcode":"28012",
    "addr:street":"Calle De Santa Isabel",
    "iso:country":"ES",
    "sg:address":"Calle de Santa Isabel, 6",
    "sg:city":"Madrid",
    "sg:orig_category":"Inmobiliaria (agencias)",
    "sg:phone":"+34 913 69 29 20",
    "sg:postcode":"28012",
    "sg:province":"Madrid",
    "wof:name":"Estudio Anton Martin S.l.",
    "wof:placetype":"venue"
},
  "geometry": {"coordinates":[-3.6996650696,40.4121513367],"type":"Point"}
}