{
  "type": "Feature",
  "properties": {
    "addr:full":"Calle de Maria Josefa Segovia, 41 Sevilla Sevilla 41007",
    "addr:housenumber":"41",
    "addr:postcode":"41007",
    "addr:street":"Calle De Maria Josefa Segovia",
    "iso:country":"ES",
    "sg:address":"Calle de Maria Josefa Segovia, 41",
    "sg:city":"Sevilla",
    "sg:orig_category":"Venta, Montaje De Neum\u00c1ticos",
    "sg:phone":"+34 954 57 08 02",
    "sg:postcode":"41007",
    "sg:province":"Sevilla",
    "wof:name":"Servicios Y Neumaticos Dakar S.l.",
    "wof:placetype":"venue"
},
  "geometry": {"coordinates":[-5.9664831161,37.3892555237],"type":"Point"}
}