{
  "type": "Feature",
  "properties": {
    "addr:full":"Calle de Vinos De La Ribera Del Duero, 6 Valladolid Valladolid 47008",
    "addr:housenumber":"6",
    "addr:postcode":"47008",
    "addr:street":"Calle De Vinos De La Ribera Del Duero",
    "iso:country":"ES",
    "sg:address":"Calle de Vinos De La Ribera Del Duero, 6",
    "sg:city":"Valladolid",
    "sg:orig_category":"Electricidad: Instaladores",
    "sg:phone":"+34 983 24 56 15",
    "sg:postcode":"47008",
    "sg:province":"Valladolid",
    "wof:name":"Aguera Cantalapiedra Victor Angel",
    "wof:placetype":"venue"
},
  "geometry": {"coordinates":[-4.7499995232,41.6192703247],"type":"Point"}
}