{
  "type": "Feature",
  "properties": {
    "addr:full":"Xaloc, (de), S/n Carlet Valencia 46240",
    "addr:housenumber":"s",
    "addr:postcode":"46240",
    "addr:street":"/ N",
    "iso:country":"ES",
    "sg:address":"Xaloc, (de), S/n",
    "sg:city":"Carlet",
    "sg:orig_category":"M\u00c1rmoles, Granitos Y Piedras Naturales",
    "sg:phone":"+34 962 53 80 90",
    "sg:postcode":"46240",
    "sg:province":"Valencia",
    "wof:name":"Marmoles Pastor C.b.",
    "wof:placetype":"venue"
},
  "geometry": {"coordinates":[-0.4883629978,39.2331733704],"type":"Point"}
}