{
  "type": "Feature",
  "properties": {
    "iso:country":"ES",
    "sg:address":"Carrer de Mossen Joan Batalla, 6",
    "sg:city":"Cambrils",
    "sg:orig_category":"Ropa Para Se\u00d1oras (al Por Menor)",
    "sg:phone":"+34 977 36 32 53",
    "sg:postcode":"43850",
    "sg:province":"Tarragona",
    "wof:name":"Locri & Anne S.l.",
    "wof:placetype":"venue"
},
  "geometry": {"coordinates":[1.0582690239,41.0653114319],"type":"Point"}
}