{
  "type": "Feature",
  "properties": {
    "addr:full":"Calle de Geologicas, 37 Alcorcon Madrid 28925",
    "addr:housenumber":"37",
    "addr:postcode":"28925",
    "addr:street":"Calle De Geologicas",
    "iso:country":"ES",
    "sg:address":"Calle de Geologicas, 37",
    "sg:city":"Alcorcon",
    "sg:orig_category":"Locales Y Clases De Danza",
    "sg:phone":"+34 916 44 17 52",
    "sg:postcode":"28925",
    "sg:province":"Madrid",
    "sg:website":"www.tallerdedanza.iespana.es",
    "wof:name":"Martin Corroto Martha",
    "wof:placetype":"venue"
},
  "geometry": {"coordinates":[-3.8140749931,40.3371887207],"type":"Point"}
}