{
  "type": "Feature",
  "properties": {
    "addr:full":"Ctra Espa\u00d1a, 66 Vera Santa Cruz De Tenerife 38390",
    "addr:housenumber":"66",
    "addr:postcode":"38390",
    "addr:street":"Ctra Espan\u0303A",
    "iso:country":"ES",
    "sg:address":"Ctra Espa\u00d1a, 66",
    "sg:city":"Vera",
    "sg:orig_category":"Mec\u00c1nico Del Autom\u00d3vil",
    "sg:phone":"+34 922 30 13 03",
    "sg:postcode":"38390",
    "sg:province":"Santa Cruz De Tenerife",
    "wof:name":"Tabeauto Canarias S.l.",
    "wof:placetype":"venue"
},
  "geometry": {"coordinates":[-16.4917697906,28.425359726],"type":"Point"}
}