{
  "type": "Feature",
  "properties": {
    "addr:full":"Plaz Ronda, 2 Malaga M\u00e1laga 29014",
    "addr:housenumber":"2",
    "addr:postcode":"29014",
    "addr:street":"Ronda;Ma\u0301Laga",
    "iso:country":"ES",
    "sg:address":"Plaz Ronda, 2",
    "sg:city":"Malaga",
    "sg:orig_category":"Cajas De Ahorro",
    "sg:phone":"+34 952 25 20 93",
    "sg:postcode":"29014",
    "sg:province":"M\u00e1laga",
    "wof:name":"Unicaja",
    "wof:placetype":"venue"
},
  "geometry": {"coordinates":[-4.4232339859,36.7445983887],"type":"Point"}
}