{
  "type": "Feature",
  "properties": {
    "addr:full":"Calle de Daoiz, 14 Getafe Madrid 28903",
    "addr:housenumber":"14",
    "addr:postcode":"28903",
    "addr:street":"Calle De Daoiz",
    "iso:country":"ES",
    "sg:address":"Calle de Daoiz, 14",
    "sg:city":"Getafe",
    "sg:orig_category":"Impresi\u00d3n Digital",
    "sg:phone":"+34 916 83 66 69",
    "sg:postcode":"28903",
    "sg:province":"Madrid",
    "wof:name":"Campus Digital S.l.",
    "wof:placetype":"venue"
},
  "geometry": {"coordinates":[-3.7259058952,40.3139305115],"type":"Point"}
}