{
  "type": "Feature",
  "properties": {
    "iso:country":"ES",
    "sg:address":"Ctra Zaragoza, 34",
    "sg:city":"Hijar",
    "sg:orig_category":"Molduras, Junquillos, Listones Y Molduras Perforadas",
    "sg:phone":"+34 978 82 02 54",
    "sg:postcode":"44530",
    "sg:province":"Teruel",
    "wof:name":"Pastor Monta\u00f1es Gregorio",
    "wof:placetype":"venue"
},
  "geometry": {"coordinates":[-0.4514290094,41.1727218628],"type":"Point"}
}