{
  "type": "Feature",
  "properties": {
    "addr:full":"Calle de Trinquete, 18 Cenicero La Rioja 26350",
    "addr:housenumber":"18",
    "addr:postcode":"26350",
    "addr:street":"Calle De Trinquete;Rioja",
    "iso:country":"ES",
    "sg:address":"Calle de Trinquete, 18",
    "sg:city":"Cenicero",
    "sg:orig_category":"Hosteler\u00cda, Empleados",
    "sg:phone":"+34 941 45 43 51",
    "sg:postcode":"26350",
    "sg:province":"La Rioja",
    "wof:name":"Martinez Puertas Maria Juana",
    "wof:placetype":"venue"
},
  "geometry": {"coordinates":[-2.6430518627,42.4821395874],"type":"Point"}
}