{
  "type": "Feature",
  "properties": {
    "iso:country":"ES",
    "sg:address":"Avda Madrid, 95",
    "sg:city":"Zaragoza",
    "sg:orig_category":"Agencias Y Agentes Comerciales, Representantes",
    "sg:phone":"+34 976 31 96 99",
    "sg:postcode":"50010",
    "sg:province":"Zaragoza",
    "wof:name":"Mendive Astiz Carlos",
    "wof:placetype":"venue"
},
  "geometry": {"coordinates":[-0.9001430273,41.6545372009],"type":"Point"}
}