{
  "type": "Feature",
  "properties": {
    "iso:country":"ES",
    "sg:address":"Carretera De Badajoz-huelva, Km. 0034,5",
    "sg:city":"Almendral",
    "sg:orig_category":"Distribuci\u00d3n De Petr\u00d3leo Y Derivados",
    "sg:phone":"+34 924 48 27 89",
    "sg:postcode":"06171",
    "sg:province":"Badajoz",
    "wof:name":"Macrotelefonia Division Andalucia S.l.",
    "wof:placetype":"venue"
},
  "geometry": {"coordinates":[-6.8223757744,38.6122398376],"type":"Point"}
}