{
  "type": "Feature",
  "properties": {
    "iso:country":"ES",
    "sg:address":"Rua Paraguay, 5",
    "sg:city":"Vigo",
    "sg:orig_category":"Centros M\u00c9dicos Y Sociales, Dispensarios",
    "sg:phone":"+34 986 47 17 99",
    "sg:postcode":"36204",
    "sg:province":"Pontevedra",
    "wof:name":"Centro De Belleza Popea S.l.",
    "wof:placetype":"venue"
},
  "geometry": {"coordinates":[-8.7161207199,42.2330169678],"type":"Point"}
}