{
  "type": "Feature",
  "properties": {
    "addr:full":"Avda Isabel Manoja, 20 Torremolinos M\u00e1laga 29620",
    "addr:housenumber":"20",
    "addr:postcode":"29620",
    "addr:street":"Avda Isabel Manoja;Ma\u0301Laga",
    "iso:country":"ES",
    "sg:address":"Avda Isabel Manoja, 20",
    "sg:city":"Torremolinos",
    "sg:orig_category":"Mec\u00c1nico Del Autom\u00d3vil",
    "sg:phone":"+34 952 38 46 17",
    "sg:postcode":"29620",
    "sg:province":"M\u00e1laga",
    "wof:name":"Diestro Chapman Cristopher",
    "wof:placetype":"venue"
},
  "geometry": {"coordinates":[-4.5023732185,36.6247596741],"type":"Point"}
}