{
  "type": "Feature",
  "properties": {
    "iso:country":"ES",
    "sg:address":"Av Pare Huguet, Del, 21",
    "sg:city":"Alaior",
    "sg:orig_category":"Zapater\u00cdas",
    "sg:phone":"+34 971 37 12 57",
    "sg:postcode":"07730",
    "sg:province":"Islas Baleares",
    "wof:name":"Calzados Davo S. L.",
    "wof:placetype":"venue"
},
  "geometry": {"coordinates":[4.1386270523,39.9319763184],"type":"Point"}
}