{
  "type": "Feature",
  "properties": {
    "iso:country":"ES",
    "sg:address":"Calle de San Antonio, 27",
    "sg:city":"Lepe",
    "sg:orig_category":"Asociaciones Humanitarias, De Cooperaci\u00d3n, De Acci\u00d3n Social",
    "sg:phone":"+34 959 38 05 62",
    "sg:postcode":"21440",
    "sg:province":"Huelva",
    "wof:name":"Delegacion Local De Ciegos",
    "wof:placetype":"venue"
},
  "geometry": {"coordinates":[-7.2025518417,37.2560043335],"type":"Point"}
}