{
  "type": "Feature",
  "properties": {
    "iso:country":"ES",
    "sg:address":"Carrer de Doctor Cabanes, S/n",
    "sg:city":"Terrassa",
    "sg:orig_category":"Alquiler De Casas Y Habitaciones Amuebladas",
    "sg:phone":"+34 937 80 73 03",
    "sg:postcode":"08221",
    "sg:province":"Barcelona",
    "wof:name":"Fundacion Busquets",
    "wof:placetype":"venue"
},
  "geometry": {"coordinates":[2.0099229813,41.5597953796],"type":"Point"}
}