{
  "type": "Feature",
  "properties": {
    "addr:full":"Carrer de Torre Bovera, S/n S. Andreu Barca Barcelona 08740",
    "addr:housenumber":"s",
    "addr:postcode":"08740",
    "addr:street":"Carrer De Torre Bovera;/ N S. Andreu;Barcelona",
    "iso:country":"ES",
    "sg:address":"Carrer de Torre Bovera, S/n",
    "sg:city":"S. Andreu Barca",
    "sg:orig_category":"Reciclaje Y Tratamiento De Desechos Varios",
    "sg:phone":"+34 936 82 28 45",
    "sg:postcode":"08740",
    "sg:province":"Barcelona",
    "wof:name":"Tratamiento De Residuos Fotograficos S.l.",
    "wof:placetype":"venue"
},
  "geometry": {"coordinates":[1.973369956,41.4486236572],"type":"Point"}
}