{
  "type": "Feature",
  "properties": {
    "addr:full":"Ctra Nal Trescientos Cuarenta, S/n Xativa Valencia 46800",
    "addr:housenumber":"s",
    "addr:postcode":"46800",
    "addr:street":"Ctra Nal Trescientos Cuarenta;/ N",
    "iso:country":"ES",
    "sg:address":"Ctra Nal Trescientos Cuarenta, S/n",
    "sg:city":"Xativa",
    "sg:orig_category":"Bisuter\u00cda, Joyer\u00cda, Relojer\u00cda (al Por Menor)",
    "sg:phone":"+34 962 28 11 45",
    "sg:postcode":"46800",
    "sg:province":"Valencia",
    "wof:name":"Dominguez Joyeros S.l.",
    "wof:placetype":"venue"
},
  "geometry": {"coordinates":[-0.5200830102,38.9934272766],"type":"Point"}
}