{
  "type": "Feature",
  "properties": {
    "addr:full":"Apeadero, S/n Arboleas Almer\u00eda 04660",
    "addr:housenumber":"s",
    "addr:postcode":"04660",
    "addr:street":"Apeadero;/ N Arboleas Almeri\u0301A",
    "iso:country":"ES",
    "sg:address":"Apeadero, S/n",
    "sg:city":"Arboleas",
    "sg:orig_category":"Empresas De Hormig\u00d3n, Hormig\u00d3n Armado Y Pretensado",
    "sg:phone":"+34 950 43 15 27",
    "sg:postcode":"04660",
    "sg:province":"Almer\u00eda",
    "wof:name":"Materiales De Construccion Sola S. L.",
    "wof:placetype":"venue"
},
  "geometry": {"coordinates":[-2.075040102,37.352481842],"type":"Point"}
}