{
  "type": "Feature",
  "properties": {
    "addr:full":"Calle de Emperador, 78 Burgos Burgos 09003",
    "addr:housenumber":"78",
    "addr:postcode":"09003",
    "addr:street":"Calle De Emperador",
    "iso:country":"ES",
    "sg:address":"Calle de Emperador, 78",
    "sg:city":"Burgos",
    "sg:orig_category":"Fabricaci\u00d3n De Telas Y Sedas",
    "sg:phone":"+34 947 20 33 93",
    "sg:postcode":"09003",
    "sg:province":"Burgos",
    "wof:name":"Sederias J. Martinez S.l.",
    "wof:placetype":"venue"
},
  "geometry": {"coordinates":[-3.714359045,42.3427581787],"type":"Point"}
}