{
  "type": "Feature",
  "properties": {
    "iso:country":"ES",
    "sg:address":"Calle de Virgen Del Socorro, S/n",
    "sg:city":"Argamasilla Calatrava",
    "sg:orig_category":"Ense\u00d1anza, Formaci\u00d3n Profesional: Aprendizaje",
    "sg:phone":"+34 926 47 81 81",
    "sg:postcode":"13440",
    "sg:province":"Ciudad Real",
    "wof:name":"Ayuntamiento De Argamasilla De Calatrava",
    "wof:placetype":"venue"
},
  "geometry": {"coordinates":[-4.0740866661,38.7313079834],"type":"Point"}
}