{
  "type": "Feature",
  "properties": {
    "iso:country":"ES",
    "sg:address":"Calle de Musico Agustin Conch, 9",
    "sg:city":"Mesas",
    "sg:orig_category":"Empresas De Carpinter\u00cda De Madera",
    "sg:phone":"+34 928 67 20 07",
    "sg:postcode":"35018",
    "sg:province":"Las Palmas",
    "wof:name":"Machin Iba\u00f1ez Norberto",
    "wof:placetype":"venue"
},
  "geometry": {"coordinates":[-15.4947748184,28.1000804901],"type":"Point"}
}