{
  "type": "Feature",
  "properties": {
    "addr:full":"Cmno Valseca, 13 Lastrilla Segovia 40196",
    "addr:housenumber":"13",
    "addr:postcode":"40196",
    "addr:street":"Cmno Valseca",
    "iso:country":"ES",
    "sg:address":"Cmno Valseca, 13",
    "sg:city":"Lastrilla",
    "sg:orig_category":"Venta, Instalaci\u00d3n De Calefacci\u00d3n",
    "sg:phone":"+34 921 43 37 08",
    "sg:postcode":"40196",
    "sg:province":"Segovia",
    "wof:name":"Instalaciones Hermu-2 S.l.",
    "wof:placetype":"venue"
},
  "geometry": {"coordinates":[-4.1334600449,40.9670715332],"type":"Point"}
}