{
  "type": "Feature",
  "properties": {
    "addr:full":"La Palma, 15 Dos Hermanas Sevilla 41700",
    "addr:housenumber":"15",
    "addr:postcode":"41700",
    "addr:street":"La Palma",
    "iso:country":"ES",
    "sg:address":"La Palma, 15",
    "sg:city":"Dos Hermanas",
    "sg:orig_category":"Automatizaci\u00d3n De Procesos Industriales Y De Edificaci\u00d3n (estudios, Instalaci\u00d3n)",
    "sg:phone":"+34 954 68 92 44",
    "sg:postcode":"41700",
    "sg:province":"Sevilla",
    "wof:name":"Teisur Automatizacion Y Servicios Industriales S.coop.andaluza",
    "wof:placetype":"venue"
},
  "geometry": {"coordinates":[-5.9223780632,37.3277359009],"type":"Point"}
}