{
  "type": "Feature",
  "properties": {
    "iso:country":"ES",
    "sg:address":"Calle de Belisana, 28",
    "sg:city":"Madrid",
    "sg:orig_category":"Empresarios",
    "sg:phone":"+34 913 88 02 09",
    "sg:postcode":"28043",
    "sg:province":"Madrid",
    "wof:name":"Asociacion Anar",
    "wof:placetype":"venue"
},
  "geometry": {"coordinates":[-3.6530923843,40.4585990906],"type":"Point"}
}