{
  "type": "Feature",
  "properties": {
    "addr:full":"Calle de Alfares (los), 28 Alcorcon Madrid 28921",
    "addr:housenumber":"28",
    "addr:postcode":"28921",
    "addr:street":"Calle De Alfares Los",
    "iso:country":"ES",
    "sg:address":"Calle de Alfares (los), 28",
    "sg:city":"Alcorcon",
    "sg:orig_category":"Carnicer\u00cdas, Carnicer\u00cdas",
    "sg:phone":"+34 916 43 77 46",
    "sg:postcode":"28921",
    "sg:province":"Madrid",
    "wof:name":"Hermoso Gomez Josefa",
    "wof:placetype":"venue"
},
  "geometry": {"coordinates":[-3.8286941051,40.3464660645],"type":"Point"}
}