{
  "type": "Feature",
  "properties": {
    "iso:country":"ES",
    "sg:address":"Avda Jorge Vigon, 44",
    "sg:city":"Logro\u00f1o",
    "sg:orig_category":"Fabricaci\u00d3n De Art\u00cdculos Y Equipos Deportivos Y De Ocio",
    "sg:phone":"+34 941 25 27 23",
    "sg:postcode":"26003",
    "sg:province":"La Rioja",
    "wof:name":"Martinez Hurtado Felix",
    "wof:placetype":"venue"
},
  "geometry": {"coordinates":[-2.4389460087,42.4611740112],"type":"Point"}
}