{
  "type": "Feature",
  "properties": {
    "iso:country":"ES",
    "sg:address":"Calle de Mendez Nu\u00d1ez, 37",
    "sg:city":"Santa Cruz De Tenerife",
    "sg:orig_category":"Abogados",
    "sg:phone":"+34 922 27 88 06",
    "sg:postcode":"38001",
    "sg:province":"Santa Cruz De Tenerife",
    "wof:name":"Ballesteros Orive Jorge Francisco",
    "wof:placetype":"venue"
},
  "geometry": {"coordinates":[-16.2516975403,28.473028183],"type":"Point"}
}