{
  "type": "Feature",
  "properties": {
    "iso:country":"ES",
    "sg:address":"Carrer de Industria, 59",
    "sg:city":"Sabadell",
    "sg:orig_category":"Sociedades, Compa\u00d1\u00cdas Aseguradoras",
    "sg:phone":"+34 937 26 67 43",
    "sg:postcode":"08202",
    "sg:province":"Barcelona",
    "sg:website":"www.mutua-intercomarcal.com",
    "wof:name":"Mutua Intercomarcal",
    "wof:placetype":"venue"
},
  "geometry": {"coordinates":[2.1147329807,41.5477104187],"type":"Point"}
}