{
  "type": "Feature",
  "properties": {
    "iso:country":"ES",
    "sg:address":"Av. Iparralde",
    "sg:city":"Irun",
    "sg:orig_category":"Carnicer\u00cdas, Carnicer\u00cdas",
    "sg:phone":"+34 943 62 17 82",
    "sg:postcode":"20304",
    "sg:province":"Guip\u00f9zcoa",
    "wof:name":"Dominguez Moreno Jose",
    "wof:placetype":"venue"
},
  "geometry": {"coordinates":[-1.7877990007,43.3457832336],"type":"Point"}
}