{
  "type": "Feature",
  "properties": {
    "iso:country":"ES",
    "sg:address":"Plaz Celestino Pons, S/n",
    "sg:city":"Javea",
    "sg:orig_category":"Cajas De Ahorro",
    "sg:phone":"+34 965 79 63 54",
    "sg:postcode":"03730",
    "sg:province":"Alicante",
    "sg:website":"www.cam.es",
    "wof:name":"Caja De Ahorros Del Mediterraneo",
    "wof:placetype":"venue"
},
  "geometry": {"coordinates":[0.1634249985,38.7895393372],"type":"Point"}
}