{
  "type": "Feature",
  "properties": {
    "iso:country":"ES",
    "sg:address":"Calle de Diputacion, 9",
    "sg:city":"Ermua",
    "sg:orig_category":"Florister\u00cdas",
    "sg:phone":"+34 943 03 16 66",
    "sg:postcode":"48260",
    "sg:province":"Vizcaya",
    "wof:name":"Jose Antonio Casta\u00f1eda Olagorta-lorak Maria Asun",
    "wof:placetype":"venue"
},
  "geometry": {"coordinates":[-2.5052955151,43.187122345],"type":"Point"}
}