{
  "type": "Feature",
  "properties": {
    "iso:country":"ES",
    "sg:address":"Pla\u00c7 Constitucio (la), 3",
    "sg:city":"Borges Blanques",
    "sg:orig_category":"Institutos De Belleza",
    "sg:phone":"+34 973 14 08 78",
    "sg:postcode":"25400",
    "sg:province":"Lleida",
    "wof:name":"Armengol Farre Ines",
    "wof:placetype":"venue"
},
  "geometry": {"coordinates":[0.8865833879,41.4978752136],"type":"Point"}
}