{
  "type": "Feature",
  "properties": {
    "iso:country":"ES",
    "sg:address":"Calle de Adriano, 18",
    "sg:city":"Camas",
    "sg:orig_category":"Agencias Y Asesores De Publicidad",
    "sg:phone":"+34 954 39 10 02",
    "sg:postcode":"41900",
    "sg:province":"Sevilla",
    "wof:name":"Publicidad Carrera S.l.",
    "wof:placetype":"venue"
},
  "geometry": {"coordinates":[-6.037882328,37.4184494019],"type":"Point"}
}