{
  "type": "Feature",
  "properties": {
    "addr:full":"Avda Monforte De Lemos, 172 Madrid Madrid 28029",
    "addr:housenumber":"172",
    "addr:postcode":"28029",
    "addr:street":"Avda Monforte De Lemos",
    "iso:country":"ES",
    "sg:address":"Avda Monforte De Lemos, 172",
    "sg:city":"Madrid",
    "sg:orig_category":"Radiocomunicaciones, Telefon\u00cda M\u00d3vil, Radiomensajer\u00cda: Servicios, Comercializaci\u00d3n",
    "sg:phone":"+34 913 86 70 19",
    "sg:postcode":"28029",
    "sg:province":"Madrid",
    "wof:name":"Money Phone Service",
    "wof:placetype":"venue"
},
  "geometry": {"coordinates":[-3.7151279449,40.4773139954],"type":"Point"}
}