{
  "type": "Feature",
  "properties": {
    "addr:full":"Calle de Cuevas Del Becerro, 25 Malaga M\u00e1laga 29006",
    "addr:housenumber":"25",
    "addr:postcode":"29006",
    "addr:street":"Calle De Cuevas Del Becerro;Ma\u0301Laga",
    "iso:country":"ES",
    "sg:address":"Calle de Cuevas Del Becerro, 25",
    "sg:city":"Malaga",
    "sg:orig_category":"Negocio De Materiales De Construcci\u00d3n",
    "sg:phone":"+34 952 32 46 29",
    "sg:postcode":"29006",
    "sg:province":"M\u00e1laga",
    "wof:name":"Martin Cobos Miguel",
    "wof:placetype":"venue"
},
  "geometry": {"coordinates":[-4.4649620056,36.7025184631],"type":"Point"}
}