{
  "type": "Feature",
  "properties": {
    "iso:country":"ES",
    "sg:address":"Calle de Atanasio Goicoechea, 3",
    "sg:city":"Sestao",
    "sg:orig_category":"Mec\u00c1nico Del Autom\u00d3vil",
    "sg:phone":"+34 944 95 41 70",
    "sg:postcode":"48910",
    "sg:province":"Vizcaya",
    "wof:name":"Valencia Nu\u00f1ez Eduardo",
    "wof:placetype":"venue"
},
  "geometry": {"coordinates":[-3.0076210499,43.3057556152],"type":"Point"}
}