{
  "type": "Feature",
  "properties": {
    "addr:full":"Carr Sta Caterina, 4 Igualada Barcelona 08700",
    "addr:housenumber":"4",
    "addr:postcode":"08700",
    "addr:street":"Carr Sta Caterina",
    "iso:country":"ES",
    "sg:address":"Carr Sta Caterina, 4",
    "sg:city":"Igualada",
    "sg:orig_category":"Empresas De Carpinter\u00cda De Madera",
    "sg:phone":"+34 938 03 09 72",
    "sg:postcode":"08700",
    "sg:province":"Barcelona",
    "wof:name":"Just Farres Jaime",
    "wof:placetype":"venue"
},
  "geometry": {"coordinates":[1.6151160002,41.5802879333],"type":"Point"}
}