{
  "type": "Feature",
  "properties": {
    "addr:full":"Czo Cordeleros, 7 Estella Navarra 31200",
    "addr:housenumber":"7",
    "addr:postcode":"31200",
    "addr:street":"Cordeleros",
    "iso:country":"ES",
    "sg:address":"Czo Cordeleros, 7",
    "sg:city":"Estella",
    "sg:orig_category":"Empresas De Electricidad En General",
    "sg:phone":"+34 948 55 12 85",
    "sg:postcode":"31200",
    "sg:province":"Navarra",
    "wof:name":"Electra Iturmayor S.l.",
    "wof:placetype":"venue"
},
  "geometry": {"coordinates":[-2.0250909328,42.6714096069],"type":"Point"}
}