{
  "type": "Feature",
  "properties": {
    "addr:full":"Calle de Antonio Machado, 32 Valladolid Valladolid 47008",
    "addr:housenumber":"32",
    "addr:postcode":"47008",
    "addr:street":"Calle De Antonio Machado",
    "iso:country":"ES",
    "sg:address":"Calle de Antonio Machado, 32",
    "sg:city":"Valladolid",
    "sg:orig_category":"Asesor\u00cda, Estudio Y Control Medioambiental",
    "sg:phone":"+34 983 24 70 11",
    "sg:postcode":"47008",
    "sg:province":"Valladolid",
    "wof:name":"Ibersilva Servicios S.a.u.",
    "wof:placetype":"venue"
},
  "geometry": {"coordinates":[-4.7520661354,41.6134643555],"type":"Point"}
}