{
  "type": "Feature",
  "properties": {
    "addr:full":"Calle de Real, 265 S. Fernando C\u00e1diz 11100",
    "addr:housenumber":"265",
    "addr:postcode":"11100",
    "addr:street":"Calle De Real;S. Fernando Ca\u0301Diz",
    "iso:country":"ES",
    "sg:address":"Calle de Real, 265",
    "sg:city":"S. Fernando",
    "sg:orig_category":"Fabricaci\u00d3n, Venta De Productos Base Farmac\u00c9uticos",
    "sg:phone":"+34 956 89 15 48",
    "sg:postcode":"11100",
    "sg:province":"C\u00e1diz",
    "wof:name":"Fernandez Garcia Maria De Los Angeles",
    "wof:placetype":"venue"
},
  "geometry": {"coordinates":[-6.2013111115,36.4597969055],"type":"Point"}
}