{
  "type": "Feature",
  "properties": {
    "addr:full":"Calle de Maestre De Calatrava, 12 Malaga M\u00e1laga 29014",
    "addr:housenumber":"12",
    "addr:postcode":"29014",
    "addr:street":"Calle De Maestre De Calatrava;Ma\u0301Laga",
    "iso:country":"ES",
    "sg:address":"Calle de Maestre De Calatrava, 12",
    "sg:city":"Malaga",
    "sg:orig_category":"Confecci\u00d3n De Zapatos",
    "sg:phone":"+34 952 65 29 62",
    "sg:postcode":"29014",
    "sg:province":"M\u00e1laga",
    "wof:name":"Osuna Dorado Diego Antonio",
    "wof:placetype":"venue"
},
  "geometry": {"coordinates":[-4.4213080406,36.7344284058],"type":"Point"}
}