{
  "type": "Feature",
  "properties": {
    "addr:full":"Calle de Embarcadero, 50 Zaragoza Zaragoza 50009",
    "addr:housenumber":"50",
    "addr:postcode":"50009",
    "addr:street":"Calle De Embarcadero",
    "iso:country":"ES",
    "sg:address":"Calle de Embarcadero, 50",
    "sg:city":"Zaragoza",
    "sg:orig_category":"Molduras, Junquillos, Listones Y Molduras Perforadas",
    "sg:phone":"+34 976 55 82 92",
    "sg:postcode":"50009",
    "sg:province":"Zaragoza",
    "wof:name":"Villanueva Ruberte Pedro",
    "wof:placetype":"venue"
},
  "geometry": {"coordinates":[-0.9104760289,41.6310310364],"type":"Point"}
}