{
  "type": "Feature",
  "properties": {
    "addr:full":"Avda Villanueva De Las Cruces, S/n Cala\u00f1as Huelva 21300",
    "addr:housenumber":"s",
    "addr:postcode":"21300",
    "addr:street":"Avda Villanueva De Las Cruces;/ N Calan\u0303As",
    "iso:country":"ES",
    "sg:address":"Avda Villanueva De Las Cruces, S/n",
    "sg:city":"Cala\u00f1as",
    "sg:orig_category":"Asilos De Ancianos. Centros Privados",
    "sg:phone":"+34 959 56 52 48",
    "sg:postcode":"21300",
    "sg:province":"Huelva",
    "wof:name":"Fundacion Santa Maria De Gracia",
    "wof:placetype":"venue"
},
  "geometry": {"coordinates":[-6.8811469078,37.6526489258],"type":"Point"}
}