{
  "type": "Feature",
  "properties": {
    "iso:country":"ES",
    "sg:address":"Calle de Olta, 64",
    "sg:city":"Valencia",
    "sg:orig_category":"Supermercados Y Hipermercados",
    "sg:phone":"+34 963 33 21 64",
    "sg:postcode":"46026",
    "sg:province":"Valencia",
    "sg:website":"www.mercadona.es",
    "wof:name":"Mercadona S.a.",
    "wof:placetype":"venue"
},
  "geometry": {"coordinates":[-0.3742670119,39.4530296326],"type":"Point"}
}