{
  "type": "Feature",
  "properties": {
    "addr:full":"Luga Cibran, S/n San Xian La Coru\u00f1a 15885",
    "addr:housenumber":"s / n",
    "addr:postcode":"15885",
    "addr:street":"Corun\u0303A",
    "iso:country":"ES",
    "sg:address":"Luga Cibran, S/n",
    "sg:city":"San Xian",
    "sg:orig_category":"Iglesia Cat\u00d3lica",
    "sg:phone":"+34 981 51 15 59",
    "sg:postcode":"15885",
    "sg:province":"La Coru\u00f1a",
    "wof:name":"Arzobispado De Santiago",
    "wof:placetype":"venue"
},
  "geometry": {"coordinates":[-8.3379449844,43.244720459],"type":"Point"}
}