{
  "type": "Feature",
  "properties": {
    "iso:country":"ES",
    "sg:address":"M. De Abastos, 9",
    "sg:city":"Alhaurin Grande",
    "sg:orig_category":"Promotores Constructores",
    "sg:phone":"+34 952 49 18 72",
    "sg:postcode":"29120",
    "sg:province":"M\u00e1laga",
    "wof:name":"Eurexcav S.l.",
    "wof:placetype":"venue"
},
  "geometry": {"coordinates":[-4.6911292076,36.6420783997],"type":"Point"}
}