{
  "type": "Feature",
  "properties": {
    "iso:country":"ES",
    "sg:address":"Calle de Herrerias, 40",
    "sg:city":"Tudela",
    "sg:orig_category":"Reposter\u00cdas",
    "sg:phone":"+34 948 82 80 56",
    "sg:postcode":"31500",
    "sg:province":"Navarra",
    "wof:name":"Jesus Cordoba S.l.",
    "wof:placetype":"venue"
},
  "geometry": {"coordinates":[-1.6085580587,42.0638504028],"type":"Point"}
}