{
  "type": "Feature",
  "properties": {
    "addr:full":"Avda Ferrandis Salvador, 135 Mas Dels Frares Castell\u00f3n 12560",
    "addr:housenumber":"135",
    "addr:postcode":"12560",
    "addr:street":"Avda Ferrandis Salvador;Castello\u0301N",
    "iso:country":"ES",
    "sg:address":"Avda Ferrandis Salvador, 135",
    "sg:city":"Mas Dels Frares",
    "sg:orig_category":"Art\u00cdculos De Regalo (al Por Menor)",
    "sg:phone":"+34 964 39 31 36",
    "sg:postcode":"12560",
    "sg:province":"Castell\u00f3n",
    "wof:name":"Prieto Gonzalez Carlos",
    "wof:placetype":"venue"
},
  "geometry": {"coordinates":[0.0590550005,40.0523414612],"type":"Point"}
}