{
  "type": "Feature",
  "properties": {
    "addr:full":"Calle de Mosen Pedro Dosset, 4 Hijar Teruel 44530",
    "addr:housenumber":"4",
    "addr:postcode":"44530",
    "addr:street":"Calle De Mosen Pedro Dosset",
    "iso:country":"ES",
    "sg:address":"Calle de Mosen Pedro Dosset, 4",
    "sg:city":"Hijar",
    "sg:orig_category":"Muebles, Minoristas",
    "sg:phone":"+34 978 82 00 07",
    "sg:postcode":"44530",
    "sg:province":"Teruel",
    "wof:name":"Arbiol Vazquez Paloma",
    "wof:placetype":"venue"
},
  "geometry": {"coordinates":[-0.4521630108,41.1751708984],"type":"Point"}
}