{
  "type": "Feature",
  "properties": {
    "iso:country":"ES",
    "sg:address":"Calle de General Pardi\u00d1as, 73",
    "sg:city":"Madrid",
    "sg:orig_category":"Promotores Constructores",
    "sg:phone":"+34 914 11 63 38",
    "sg:postcode":"28006",
    "sg:province":"Madrid",
    "sg:website":"www.urbis.es",
    "wof:name":"Inmobiliaria Urbis S.a.",
    "wof:placetype":"venue"
},
  "geometry": {"coordinates":[-3.6780719757,40.4338722229],"type":"Point"}
}