{
  "type": "Feature",
  "properties": {
    "addr:full":"Plaz Alcalde Domingo Castillejo, 3 Barrax Albacete 02639",
    "addr:housenumber":"3",
    "addr:postcode":"02639",
    "addr:street":"Plaz Alcalde Domingo Castillejo",
    "iso:country":"ES",
    "sg:address":"Plaz Alcalde Domingo Castillejo, 3",
    "sg:city":"Barrax",
    "sg:orig_category":"Ense\u00d1anza, Formaci\u00d3n Profesional: Aprendizaje",
    "sg:phone":"+34 967 36 50 02",
    "sg:postcode":"02639",
    "sg:province":"Albacete",
    "wof:name":"Junta De Comunidades Castilla-la Mancha",
    "wof:placetype":"venue"
},
  "geometry": {"coordinates":[-2.2004749775,39.0463943481],"type":"Point"}
}