{
  "type": "Feature",
  "properties": {
    "addr:full":"Calle de Madre Vedruna, 12 Zaragoza Zaragoza 50008",
    "addr:housenumber":"12",
    "addr:postcode":"50008",
    "addr:street":"Calle De Madre Vedruna",
    "iso:country":"ES",
    "sg:address":"Calle de Madre Vedruna, 12",
    "sg:city":"Zaragoza",
    "sg:orig_category":"Conservas De Legumbres (fabricaci\u00d3n, Al Por Mayor)",
    "sg:phone":"+34 976 46 84 69",
    "sg:postcode":"50008",
    "sg:province":"Zaragoza",
    "sg:website":"www.bajamar-mamia.com",
    "wof:name":"Bajamar S.a.",
    "wof:placetype":"venue"
},
  "geometry": {"coordinates":[-0.8821232915,41.6462287903],"type":"Point"}
}