{
  "type": "Feature",
  "properties": {
    "addr:full":"Rua Republica Arxentina (da), 28 Santiago De Compostela La Coru\u00f1a 15706",
    "addr:housenumber":"28",
    "addr:postcode":"15706",
    "addr:street":"Rua Republica Arxentina Da;Corun\u0303A",
    "iso:country":"ES",
    "sg:address":"Rua Republica Arxentina (da), 28",
    "sg:city":"Santiago De Compostela",
    "sg:orig_category":"Inmobiliaria (agencias)",
    "sg:phone":"+34 981 59 35 31",
    "sg:postcode":"15706",
    "sg:province":"La Coru\u00f1a",
    "wof:name":"Gestoria Inmobiliaria Ginarte S.c.",
    "wof:placetype":"venue"
},
  "geometry": {"coordinates":[-8.548166275,42.8729133606],"type":"Point"}
}