{
  "type": "Feature",
  "properties": {
    "addr:full":"La Estacion, 9 Espinosa Monteros Burgos 09560",
    "addr:housenumber":"9",
    "addr:postcode":"09560",
    "addr:street":"Estacion",
    "iso:country":"ES",
    "sg:address":"La Estacion, 9",
    "sg:city":"Espinosa Monteros",
    "sg:orig_category":"Ense\u00d1anza, Formaci\u00d3n Profesional: Aprendizaje",
    "sg:phone":"+34 947 12 04 77",
    "sg:postcode":"09560",
    "sg:province":"Burgos",
    "wof:name":"Base Aerea De Villanubla Ministerio De Defensa",
    "wof:placetype":"venue"
},
  "geometry": {"coordinates":[-3.5770280361,43.0979652405],"type":"Point"}
}