{
  "type": "Feature",
  "properties": {
    "iso:country":"ES",
    "sg:address":"Ctra. La Almunia-epila, S/n",
    "sg:city":"Calatorao",
    "sg:orig_category":"Polideportivos",
    "sg:phone":"+34 976 60 77 25",
    "sg:postcode":"50280",
    "sg:province":"Zaragoza",
    "wof:name":"Ayuntamiento De Calatorao",
    "wof:placetype":"venue"
},
  "geometry": {"coordinates":[-1.3918911219,41.5450172424],"type":"Point"}
}