{
  "type": "Feature",
  "properties": {
    "addr:full":"Ptor Asarta, 4 Iru\u00f1a Navarra 31007",
    "addr:housenumber":"4",
    "addr:postcode":"31007",
    "addr:street":"Asarta",
    "iso:country":"ES",
    "sg:address":"Ptor Asarta, 4",
    "sg:city":"Iru\u00f1a",
    "sg:orig_category":"Peluqueros: De Se\u00d1oras",
    "sg:phone":"+34 948 25 33 07",
    "sg:postcode":"31007",
    "sg:province":"Navarra",
    "wof:name":"Saenz Sola Asuncion",
    "wof:placetype":"venue"
},
  "geometry": {"coordinates":[-1.6555049419,42.8054542542],"type":"Point"}
}