{
  "type": "Feature",
  "properties": {
    "addr:full":"Av Verge Montserrat, 61 Prat Llobregat Barcelona 08820",
    "addr:housenumber":"61",
    "addr:postcode":"08820",
    "addr:street":"Av Verge Montserrat;Llobregat",
    "iso:country":"ES",
    "sg:address":"Av Verge Montserrat, 61",
    "sg:city":"Prat Llobregat",
    "sg:orig_category":"Electrodom\u00c9sticos (al Por Menor)",
    "sg:phone":"+34 933 70 78 03",
    "sg:postcode":"08820",
    "sg:province":"Barcelona",
    "wof:name":"Montserrat Gustems Jaime",
    "wof:placetype":"venue"
},
  "geometry": {"coordinates":[2.0976400375,41.3266372681],"type":"Point"}
}