{
  "type": "Feature",
  "properties": {
    "iso:country":"ES",
    "sg:address":"Calle de Pozuelo, 11",
    "sg:city":"Ventorro Del Cano",
    "sg:orig_category":"Asistencia Y Seguros De Automovilistas Y Turistas",
    "sg:phone":"+34 916 32 11 01",
    "sg:postcode":"28925",
    "sg:province":"Madrid",
    "wof:name":"D.r.i.asistencia S.l.",
    "wof:placetype":"venue"
},
  "geometry": {"coordinates":[-3.8364989758,40.3952064514],"type":"Point"}
}