{
  "type": "Feature",
  "properties": {
    "iso:country":"ES",
    "sg:address":"Calle de Guen-kalea, 13",
    "sg:city":"Markina-xemein",
    "sg:orig_category":"Molduras, Junquillos, Listones Y Molduras Perforadas",
    "sg:phone":"+34 946 16 78 98",
    "sg:postcode":"48270",
    "sg:province":"Vizcaya",
    "wof:name":"Eguia Arrieta Joaquin",
    "wof:placetype":"venue"
},
  "geometry": {"coordinates":[-2.4973609447,43.2676506042],"type":"Point"}
}