{
  "type": "Feature",
  "properties": {
    "addr:full":"Avda Portugal, S/n Brenes Sevilla 41310",
    "addr:housenumber":"s / n",
    "addr:postcode":"41310",
    "addr:street":"Avda Portugal",
    "iso:country":"ES",
    "sg:address":"Avda Portugal, S/n",
    "sg:city":"Brenes",
    "sg:orig_category":"Centros De Educaci\u00d3n Especial",
    "sg:phone":"+34 954 79 65 00",
    "sg:postcode":"41310",
    "sg:province":"Sevilla",
    "wof:name":"Junta De Andalucia",
    "wof:placetype":"venue"
},
  "geometry": {"coordinates":[-5.8681440353,37.5552444458],"type":"Point"}
}