{
  "type": "Feature",
  "properties": {
    "iso:country":"ES",
    "sg:address":"Carrer de Enclusa, S/n",
    "sg:city":"Esparreguera",
    "sg:orig_category":"Veh\u00cdculos, Transporte",
    "sg:phone":"+34 937 77 58 13",
    "sg:postcode":"08292",
    "sg:province":"Barcelona",
    "sg:website":"www.ghsa.com",
    "wof:name":"G.h. Catalu\u00f1a S.l.",
    "wof:placetype":"venue"
},
  "geometry": {"coordinates":[1.8529620171,41.5514755249],"type":"Point"}
}