{
  "type": "Feature",
  "properties": {
    "addr:full":"Calle de Antonio Maria Isola, 7 Malaga M\u00e1laga 29011",
    "addr:housenumber":"7",
    "addr:postcode":"29011",
    "addr:street":"Calle De Antonio Maria Isola;Ma\u0301Laga",
    "iso:country":"ES",
    "sg:address":"Calle de Antonio Maria Isola, 7",
    "sg:city":"Malaga",
    "sg:orig_category":"Papeler\u00cdas, Librer\u00cdas",
    "sg:phone":"+34 952 28 18 48",
    "sg:postcode":"29011",
    "sg:province":"M\u00e1laga",
    "wof:name":"Recio Cabrera Juan",
    "wof:placetype":"venue"
},
  "geometry": {"coordinates":[-4.4289317131,36.7407608032],"type":"Point"}
}