{
  "type": "Feature",
  "properties": {
    "iso:country":"ES",
    "sg:address":"Ctra Cebreros (de), 12",
    "sg:city":"Tiemblo",
    "sg:orig_category":"Bares, Piano",
    "sg:phone":"+34 918 62 70 54",
    "sg:postcode":"05270",
    "sg:province":"\u00c1vila",
    "wof:name":"Diaz Rios Lucio",
    "wof:placetype":"venue"
},
  "geometry": {"coordinates":[-4.5002861023,40.4145774841],"type":"Point"}
}