{
  "type": "Feature",
  "properties": {
    "addr:full":"Carr Prim, 93 Badalona Barcelona 08911",
    "addr:housenumber":"93",
    "addr:postcode":"08911",
    "addr:street":"Carr Prim",
    "iso:country":"ES",
    "sg:address":"Carr Prim, 93",
    "sg:city":"Badalona",
    "sg:orig_category":"M\u00c9dicos: Estomatolog\u00cda",
    "sg:phone":"+34 933 84 28 46",
    "sg:postcode":"08911",
    "sg:province":"Barcelona",
    "wof:name":"Izquierdo Cuspinera Jorge",
    "wof:placetype":"venue"
},
  "geometry": {"coordinates":[2.2450649738,41.4503440857],"type":"Point"}
}