{
  "type": "Feature",
  "properties": {
    "addr:full":"Calle de Tomas Morales, 14 Arguineguin Las Palmas 35120",
    "addr:housenumber":"14",
    "addr:postcode":"35120",
    "addr:street":"Calle De Tomas Morales;Palmas",
    "iso:country":"ES",
    "sg:address":"Calle de Tomas Morales, 14",
    "sg:city":"Arguineguin",
    "sg:orig_category":"Inform\u00c1tica, Ofim\u00c1tica (estudios, Asesor\u00cda, Ingenier\u00cda, Formaci\u00d3n)",
    "sg:phone":"+34 928 15 08 40",
    "sg:postcode":"35120",
    "sg:province":"Las Palmas",
    "wof:name":"Cazorla Gutierrez Julian R.",
    "wof:placetype":"venue"
},
  "geometry": {"coordinates":[-15.6819639206,27.7599639893],"type":"Point"}
}