{
  "type": "Feature",
  "properties": {
    "iso:country":"ES",
    "sg:address":"Calle de Zuatzu, 1",
    "sg:city":"Donostia-san Sebastian",
    "sg:orig_category":"Ingeniero",
    "sg:phone":"+34 943 21 91 81",
    "sg:postcode":"20009",
    "sg:province":"Guip\u00f9zcoa",
    "sg:website":"www.athader.com",
    "wof:name":"Athader S.l.",
    "wof:placetype":"venue"
},
  "geometry": {"coordinates":[-2.0077300072,43.2976837158],"type":"Point"}
}