{
  "type": "Feature",
  "properties": {
    "addr:full":"Calle de Real, 21 Mengibar Ja\u00e9n 23620",
    "addr:housenumber":"21",
    "addr:postcode":"23620",
    "addr:street":"Calle De Real;Jae\u0301N",
    "iso:country":"ES",
    "sg:address":"Calle de Real, 21",
    "sg:city":"Mengibar",
    "sg:orig_category":"Agentes Generales De Seguros",
    "sg:phone":"+34 953 37 01 58",
    "sg:postcode":"23620",
    "sg:province":"Ja\u00e9n",
    "wof:name":"Damas Hidalgo S.l.",
    "wof:placetype":"venue"
},
  "geometry": {"coordinates":[-3.8097970486,37.9694442749],"type":"Point"}
}