{
  "type": "Feature",
  "properties": {
    "addr:full":"Avda Mar Mediterraneo (del), S/n Valdemoro Madrid 28340",
    "addr:housenumber":"/ n",
    "addr:postcode":"28340",
    "addr:street":"Avda Mar Mediterraneo Del S",
    "iso:country":"ES",
    "sg:address":"Avda Mar Mediterraneo (del), S/n",
    "sg:city":"Valdemoro",
    "sg:orig_category":"Complementos De Vestir (al Por Menor)",
    "sg:phone":"+34 918 08 26 97",
    "sg:postcode":"28340",
    "sg:province":"Madrid",
    "wof:name":"Morales Mu\u00f1oz Maria Luisa",
    "wof:placetype":"venue"
},
  "geometry": {"coordinates":[-3.6828439236,40.1825218201],"type":"Point"}
}