{
  "type": "Feature",
  "properties": {
    "iso:country":"ES",
    "sg:address":"Calle de Periodista Azzati, 7",
    "sg:city":"Valencia",
    "sg:orig_category":"Ropa De Casa (fabricaci\u00d3n, Al Por Mayor)",
    "sg:phone":"+34 963 52 90 89",
    "sg:postcode":"46002",
    "sg:province":"Valencia",
    "wof:name":"Lenceria Perking S.l.",
    "wof:placetype":"venue"
},
  "geometry": {"coordinates":[-0.3778839111,39.4695358276],"type":"Point"}
}