{
  "type": "Feature",
  "properties": {
    "iso:country":"ES",
    "sg:address":"Ctra Yecla, 6",
    "sg:city":"Villena",
    "sg:orig_category":"Cooperativas Agr\u00cdcolas",
    "sg:phone":"+34 965 80 26 85",
    "sg:postcode":"03400",
    "sg:province":"Alicante",
    "wof:name":"Coviran",
    "wof:placetype":"venue"
},
  "geometry": {"coordinates":[-0.8705040216,38.6358566284],"type":"Point"}
}