{
  "type": "Feature",
  "properties": {
    "iso:country":"ES",
    "sg:address":"Calle de Manuel Mas, 53",
    "sg:city":"Talayuela",
    "sg:orig_category":"Cajas De Ahorro",
    "sg:phone":"+34 927 55 12 53",
    "sg:postcode":"10310",
    "sg:province":"C\u00e1ceres",
    "wof:name":"Caixa D'estalvis I Pensions De Barcelona",
    "wof:placetype":"venue"
},
  "geometry": {"coordinates":[-5.6097669601,39.9866371155],"type":"Point"}
}