{
  "type": "Feature",
  "properties": {
    "iso:country":"ES",
    "sg:address":"Calle de Tenderia, 21",
    "sg:city":"Bilbao",
    "sg:orig_category":"Peleter\u00cdas",
    "sg:phone":"+34 944 16 73 48",
    "sg:postcode":"48005",
    "sg:province":"Vizcaya",
    "wof:name":"Grupo Ancla Piel Sl",
    "wof:placetype":"venue"
},
  "geometry": {"coordinates":[-2.9238359928,43.2566833496],"type":"Point"}
}