{
  "type": "Feature",
  "properties": {
    "iso:country":"ES",
    "sg:address":"Pg Cordelles, 20",
    "sg:city":"Cerdanyola Valles",
    "sg:orig_category":"Procuradores",
    "sg:phone":"+34 936 92 02 24",
    "sg:postcode":"08290",
    "sg:province":"Barcelona",
    "wof:name":"Pozo Artacho Jose",
    "wof:placetype":"venue"
},
  "geometry": {"coordinates":[2.1396930218,41.4923973083],"type":"Point"}
}