{
  "type": "Feature",
  "properties": {
    "iso:country":"ES",
    "sg:address":"Calle de Encomienda De Palacios, 332",
    "sg:city":"Madrid",
    "sg:orig_category":"Ense\u00d1anza Secundaria: Colegios Y Escuelas Privadas",
    "sg:phone":"+34 917 51 00 93",
    "sg:postcode":"28030",
    "sg:province":"Madrid",
    "wof:name":"Colegio Nacional Jose Echegaray",
    "wof:placetype":"venue"
},
  "geometry": {"coordinates":[-3.6360509396,40.3967170715],"type":"Point"}
}