{
  "type": "Feature",
  "properties": {
    "iso:country":"ES",
    "sg:address":"Calle de Castielfabib, 2",
    "sg:city":"Valencia",
    "sg:orig_category":"Mayoristas E Intermediarios En Alcoholes",
    "sg:phone":"+34 963 40 72 43",
    "sg:postcode":"46015",
    "sg:province":"Valencia",
    "wof:name":"Legends S.l.",
    "wof:placetype":"venue"
},
  "geometry": {"coordinates":[-0.3958449066,39.4784927368],"type":"Point"}
}