{
  "type": "Feature",
  "properties": {
    "iso:country":"ES",
    "sg:address":"Calle de Pablo Picasso, 45",
    "sg:city":"Elda",
    "sg:orig_category":"Agencias Y Agentes Comerciales, Representantes",
    "sg:phone":"+34 966 98 05 70",
    "sg:postcode":"03600",
    "sg:province":"Alicante",
    "wof:name":"Agentes Comisionistas Europeos S.l",
    "wof:placetype":"venue"
},
  "geometry": {"coordinates":[-0.7879818082,38.4788665771],"type":"Point"}
}