{
  "type": "Feature",
  "properties": {
    "addr:full":"Calle de Mayoral, 14 Malaga M\u00e1laga 29016",
    "addr:housenumber":"14",
    "addr:postcode":"29016",
    "addr:street":"Calle De Mayoral;Ma\u0301Laga",
    "iso:country":"ES",
    "sg:address":"Calle de Mayoral, 14",
    "sg:city":"Malaga",
    "sg:orig_category":"Ingeniero",
    "sg:phone":"+34 952 22 96 66",
    "sg:postcode":"29016",
    "sg:province":"M\u00e1laga",
    "wof:name":"Silva Moreira Esteban",
    "wof:placetype":"venue"
},
  "geometry": {"coordinates":[-4.3952651024,36.7319641113],"type":"Point"}
}