{
  "type": "Feature",
  "properties": {
    "iso:country":"ES",
    "sg:address":"Pase Doctor Mara\u00d1on, 34",
    "sg:city":"Donostia-san Sebastian",
    "sg:orig_category":"Abogados",
    "sg:phone":"+34 943 31 12 42",
    "sg:postcode":"20009",
    "sg:province":"Guip\u00f9zcoa",
    "wof:name":"Zapirain Duo Teresa",
    "wof:placetype":"venue"
},
  "geometry": {"coordinates":[-1.9949510098,43.3078804016],"type":"Point"}
}