{
  "type": "Feature",
  "properties": {
    "addr:full":"Carrer de Mare De Deu De Port, 116 Barcelona Barcelona 08038",
    "addr:housenumber":"116",
    "addr:postcode":"08038",
    "addr:street":"Carrer De Mare De Deu;Port",
    "iso:country":"ES",
    "sg:address":"Carrer de Mare De Deu De Port, 116",
    "sg:city":"Barcelona",
    "sg:orig_category":"Centros Empresariales",
    "sg:phone":"+34 932 23 01 31",
    "sg:postcode":"08038",
    "sg:province":"Barcelona",
    "wof:name":"Jimenez Fernandez-ca\u00f1adas Esther",
    "wof:placetype":"venue"
},
  "geometry": {"coordinates":[2.1444599628,41.3567276001],"type":"Point"}
}