{
  "type": "Feature",
  "properties": {
    "addr:full":"El Pocico, S/n Gor Granada 18870",
    "addr:housenumber":"s / n",
    "addr:postcode":"18870",
    "addr:street":"El Pocico;Gor Granada",
    "iso:country":"ES",
    "sg:address":"El Pocico, S/n",
    "sg:city":"Gor",
    "sg:orig_category":"Producci\u00d3n, Venta De Productos De Agricultura Biol\u00d3gica",
    "sg:phone":"+34 958 06 60 31",
    "sg:postcode":"18870",
    "sg:province":"Granada",
    "wof:name":"Josefina Tomasa Abellan Vota",
    "wof:placetype":"venue"
},
  "geometry": {"coordinates":[-2.972522974,37.3706283569],"type":"Point"}
}