{
  "type": "Feature",
  "properties": {
    "addr:full":"Avda Felipe Ii, 10 Madrid Madrid 28009",
    "addr:housenumber":"10",
    "addr:postcode":"madrid;28009",
    "addr:street":"Avda Felipe Ii",
    "iso:country":"ES",
    "sg:address":"Avda Felipe Ii, 10",
    "sg:city":"Madrid",
    "sg:orig_category":"M\u00c9dicos: Psiquiatr\u00cda",
    "sg:phone":"+34 915 75 86 02",
    "sg:postcode":"28009",
    "sg:province":"Madrid",
    "wof:name":"Alipsy S.l.",
    "wof:placetype":"venue"
},
  "geometry": {"coordinates":[-3.6763575077,40.4239616394],"type":"Point"}
}