{
  "type": "Feature",
  "properties": {
    "addr:full":"Calle de Ruiz De Alarcon, 7 Madrid Madrid 28014",
    "addr:housenumber":"7",
    "addr:postcode":"madrid;28014",
    "addr:street":"Calle De Ruiz De Alarcon",
    "iso:country":"ES",
    "sg:address":"Calle de Ruiz De Alarcon, 7",
    "sg:city":"Madrid",
    "sg:orig_category":"Aparatos, Material Y Suministros Para Laboratorios",
    "sg:phone":"+34 915 22 67 42",
    "sg:postcode":"28014",
    "sg:province":"Madrid",
    "sg:website":"www.lachambre.es",
    "wof:name":"Camara Franco-espa\u00d1ola De Comercio E Industria",
    "wof:placetype":"venue"
},
  "geometry": {"coordinates":[-3.6913480759,40.4167289734],"type":"Point"}
}