{
  "type": "Feature",
  "properties": {
    "addr:full":"Calle de Matias Fernandez Bayo, 3 Langreo Asturias 33930",
    "addr:housenumber":"3",
    "addr:postcode":"33930",
    "addr:street":"Calle De Matias Fernandez Bayo",
    "iso:country":"ES",
    "sg:address":"Calle de Matias Fernandez Bayo, 3",
    "sg:city":"Langreo",
    "sg:orig_category":"Asociaciones Y Clubs Deportivos",
    "sg:phone":"+34 985 67 58 79",
    "sg:postcode":"33930",
    "sg:province":"Asturias",
    "wof:name":"Bargados Diaz Felix",
    "wof:placetype":"venue"
},
  "geometry": {"coordinates":[-5.6899151802,43.3065681458],"type":"Point"}
}