{
  "type": "Feature",
  "properties": {
    "addr:full":"C/ Muntanyeta, De Sa, 1 Alaior Islas Baleares 07730",
    "addr:housenumber":"1",
    "addr:postcode":"07730",
    "addr:street":"C / Muntanyeta De Sa",
    "iso:country":"ES",
    "sg:address":"C/ Muntanyeta, De Sa, 1",
    "sg:city":"Alaior",
    "sg:orig_category":"Confecci\u00d3n (fabricaci\u00d3n, Al Por Mayor)",
    "sg:phone":"+34 971 37 17 96",
    "sg:postcode":"07730",
    "sg:province":"Islas Baleares",
    "wof:name":"Sintes Mir Montserrat",
    "wof:placetype":"venue"
},
  "geometry": {"coordinates":[4.1419200897,39.9265403748],"type":"Point"}
}