{
  "type": "Feature",
  "properties": {
    "addr:full":"Calle de Luis Madrona, S/n Alcala Henares Madrid 28805",
    "addr:housenumber":"s",
    "addr:postcode":"28805",
    "addr:street":"Calle De Luis Madrona;/ N",
    "iso:country":"ES",
    "sg:address":"Calle de Luis Madrona, S/n",
    "sg:city":"Alcala Henares",
    "sg:orig_category":"Librer\u00cdas",
    "sg:phone":"+34 918 84 20 72",
    "sg:postcode":"28805",
    "sg:province":"Madrid",
    "wof:name":"Diaz Ontiveiro Oscar",
    "wof:placetype":"venue"
},
  "geometry": {"coordinates":[-3.349684,40.4896087646],"type":"Point"}
}