{
  "type": "Feature",
  "properties": {
    "iso:country":"ES",
    "sg:address":"Calle de Doctor Alvira Lasierra, 2",
    "sg:city":"Zaragoza",
    "sg:orig_category":"Detectives, Agentes Investigadores Privados",
    "sg:phone":"+34 976 20 13 30",
    "sg:postcode":"50002",
    "sg:province":"Zaragoza",
    "sg:website":"www.inveszar.com",
    "wof:name":"Delgado Molina Vicente",
    "wof:placetype":"venue"
},
  "geometry": {"coordinates":[-0.8708108068,41.6491928101],"type":"Point"}
}