{
  "type": "Feature",
  "properties": {
    "addr:full":"Carrer de Sant Manuel, 11 Barcelona Barcelona 08031",
    "addr:housenumber":"11",
    "addr:postcode":"08031",
    "addr:street":"Carrer De Sant Manuel",
    "iso:country":"ES",
    "sg:address":"Carrer de Sant Manuel, 11",
    "sg:city":"Barcelona",
    "sg:orig_category":"Empresarios",
    "sg:phone":"+34 934 29 88 03",
    "sg:postcode":"08031",
    "sg:province":"Barcelona",
    "wof:name":"Gali Bernal Francisco",
    "wof:placetype":"venue"
},
  "geometry": {"coordinates":[2.1671090126,41.4296150208],"type":"Point"}
}