{
  "type": "Feature",
  "properties": {
    "addr:full":"Ctra Corregudes (les), S/n Albal Valencia 46470",
    "addr:housenumber":"s",
    "addr:postcode":"46470",
    "addr:street":"Ctra Corregudes Les;/ N",
    "iso:country":"ES",
    "sg:address":"Ctra Corregudes (les), S/n",
    "sg:city":"Albal",
    "sg:orig_category":"Confecci\u00d3n De Ropa Interior",
    "sg:phone":"+34 961 27 47 92",
    "sg:postcode":"46470",
    "sg:province":"Valencia",
    "wof:name":"Ana Castro De Cervera S.a.",
    "wof:placetype":"venue"
},
  "geometry": {"coordinates":[-0.4121969044,39.3970947266],"type":"Point"}
}