{
  "type": "Feature",
  "properties": {
    "addr:full":"Avda Menendez Pidal, 9 Valencia Valencia 46009",
    "addr:housenumber":"9",
    "addr:postcode":"46009",
    "addr:street":"Avda Menendez Pidal",
    "iso:country":"ES",
    "sg:address":"Avda Menendez Pidal, 9",
    "sg:city":"Valencia",
    "sg:orig_category":"Sociedades, Compa\u00d1\u00cdas Aseguradoras",
    "sg:phone":"+34 963 47 60 75",
    "sg:postcode":"46009",
    "sg:province":"Valencia",
    "wof:name":"Patria Hispana S.a. De Seguros Y Reaseguros",
    "wof:placetype":"venue"
},
  "geometry": {"coordinates":[-0.3861249983,39.480922699],"type":"Point"}
}