{
  "type": "Feature",
  "properties": {
    "iso:country":"ES",
    "sg:address":"Calle de Santo Domingo De Silos (del), 5",
    "sg:city":"Pinto",
    "sg:classifiers":[
        {
            "category":"Autos & Motor Vehicles",
            "subcategory":"Automobile Sales",
            "type":"Retail Goods"
        }
    ],
    "sg:phone":"+34 916 91 28 55",
    "sg:postcode":"28320",
    "sg:province":"Madrid",
    "wof:name":"Lopez Lopez Rafael",
    "wof:placetype":"venue"
},
  "geometry": {"coordinates":[-3.6997611523,40.2468605042],"type":"Point"}
}