{
  "type": "Feature",
  "properties": {
    "addr:full":"Calle de Huelgas, 14 Valladolid Valladolid 47005",
    "addr:housenumber":"14",
    "addr:postcode":"47005",
    "addr:street":"Calle De Huelgas",
    "iso:country":"ES",
    "sg:address":"Calle de Huelgas, 14",
    "sg:city":"Valladolid",
    "sg:orig_category":"Telas Y Sedas (al Por Menor)",
    "sg:phone":"+34 983 39 85 42",
    "sg:postcode":"47005",
    "sg:province":"Valladolid",
    "wof:name":"Aviles De Prada S.l.",
    "wof:placetype":"venue"
},
  "geometry": {"coordinates":[-4.7162709236,41.65234375],"type":"Point"}
}