{
  "type": "Feature",
  "properties": {
    "iso:country":"ES",
    "sg:address":"Rua D, 6",
    "sg:city":"Lalin",
    "sg:orig_category":"Transportes Por Carretera: Lotes Completos, Mercanc\u00cdas Diversas",
    "sg:phone":"+34 986 78 70 61",
    "sg:postcode":"36500",
    "sg:province":"Pontevedra",
    "wof:name":"Hiperxel S.l.",
    "wof:placetype":"venue"
},
  "geometry": {"coordinates":[-8.1094141006,42.6554260254],"type":"Point"}
}