{
  "type": "Feature",
  "properties": {
    "iso:country":"ES",
    "sg:address":"Avda San Diego, 130",
    "sg:city":"Madrid",
    "sg:orig_category":"Molduras, Junquillos, Listones Y Molduras Perforadas",
    "sg:phone":"+34 914 77 11 13",
    "sg:postcode":"28018",
    "sg:province":"Madrid",
    "wof:name":"Hervas Alonso Carmen",
    "wof:placetype":"venue"
},
  "geometry": {"coordinates":[-3.6660349369,40.38489151],"type":"Point"}
}