{
  "type": "Feature",
  "properties": {
    "iso:country":"ES",
    "sg:address":"Calle de Elcano, 22",
    "sg:city":"Bilbao",
    "sg:orig_category":"Abogados",
    "sg:phone":"+34 944 23 10 24",
    "sg:postcode":"48008",
    "sg:province":"Vizcaya",
    "wof:name":"Ca\u00f1ada Vicinay Felix",
    "wof:placetype":"venue"
},
  "geometry": {"coordinates":[-2.9334859848,43.2600402832],"type":"Point"}
}