{
  "type": "Feature",
  "properties": {
    "iso:country":"ES",
    "sg:address":"Calle de Alcalde Luis Pascual, 7",
    "sg:city":"Caudete",
    "sg:orig_category":"Cajas De Ahorro",
    "sg:phone":"+34 965 82 80 29",
    "sg:postcode":"02660",
    "sg:province":"Albacete",
    "sg:website":"www.bancaja.es",
    "wof:name":"Caja De Ahorros De Valencia Castellon Y Alicante",
    "wof:placetype":"venue"
},
  "geometry": {"coordinates":[-0.987862885,38.7055511475],"type":"Point"}
}