{
  "type": "Feature",
  "properties": {
    "iso:country":"ES",
    "sg:address":"Calle de Vitorialanda, 8",
    "sg:city":"Vitoria-gasteiz",
    "sg:orig_category":"Otros Trabajos De Limpieza Y Mantenimiento (extracci\u00d3n De Polvo, Recogida De Amianto Y Desespumado)",
    "sg:phone":"+34 945 22 98 52",
    "sg:postcode":"01010",
    "sg:province":"\u00c1lava",
    "sg:website":"www.alsatec.net",
    "wof:name":"Alsatec S.l.",
    "wof:placetype":"venue"
},
  "geometry": {"coordinates":[-2.7058076859,42.8592720032],"type":"Point"}
}