{
  "type": "Feature",
  "properties": {
    "iso:country":"ES",
    "sg:address":"Avda Santander, 24",
    "sg:city":"Solares",
    "sg:orig_category":"Carnes De Carnicer\u00cda (al Por Mayor)",
    "sg:phone":"+34 942 52 12 41",
    "sg:postcode":"39710",
    "sg:province":"Cantabria",
    "wof:name":"Carnicas El Piri S.l.",
    "wof:placetype":"venue"
},
  "geometry": {"coordinates":[-3.7418990135,43.3854522705],"type":"Point"}
}