{
  "type": "Feature",
  "properties": {
    "addr:full":"Avda Peris Y Valero, 182 Valencia Valencia 46006",
    "addr:housenumber":"182",
    "addr:postcode":"46006",
    "addr:street":"Avda Peris Y Valero",
    "iso:country":"ES",
    "sg:address":"Avda Peris Y Valero, 182",
    "sg:city":"Valencia",
    "sg:orig_category":"Chapister\u00cda",
    "sg:phone":"+34 963 33 38 86",
    "sg:postcode":"46006",
    "sg:province":"Valencia",
    "wof:name":"Martinez Izquierdo Ramon",
    "wof:placetype":"venue"
},
  "geometry": {"coordinates":[-0.3635219932,39.4619216919],"type":"Point"}
}