{
  "type": "Feature",
  "properties": {
    "iso:country":"ES",
    "sg:address":"Calle de Santa Maria Magdalena, 26",
    "sg:city":"Dos Hermanas",
    "sg:orig_category":"Bancos",
    "sg:phone":"+34 955 67 90 30",
    "sg:postcode":"41700",
    "sg:province":"Sevilla",
    "wof:name":"Bankinter S.a.",
    "wof:placetype":"venue"
},
  "geometry": {"coordinates":[-5.9243030548,37.283115387],"type":"Point"}
}