{
  "type": "Feature",
  "properties": {
    "addr:full":"Calle de Ramon Y Cajal, 6 Ibi Alicante 03440",
    "addr:housenumber":"6",
    "addr:postcode":"03440",
    "addr:street":"Calle De Ramon Y Cajal",
    "iso:country":"ES",
    "sg:address":"Calle de Ramon Y Cajal, 6",
    "sg:city":"Ibi",
    "sg:orig_category":"Asesor\u00cda Fiscal Y Jur\u00cddica",
    "sg:phone":"+34 966 55 00 13",
    "sg:postcode":"03440",
    "sg:province":"Alicante",
    "wof:name":"Asefeco S.l.",
    "wof:placetype":"venue"
},
  "geometry": {"coordinates":[-0.5741829276,38.6242027283],"type":"Point"}
}