{
  "type": "Feature",
  "properties": {
    "iso:country":"ES",
    "sg:address":"Carrer de Caceres, 2",
    "sg:city":"Barcelona",
    "sg:orig_category":"Panader\u00cdas, Panader\u00cdas",
    "sg:phone":"+34 933 39 22 30",
    "sg:postcode":"08028",
    "sg:province":"Barcelona",
    "wof:name":"Forns Enrich S.l",
    "wof:placetype":"venue"
},
  "geometry": {"coordinates":[2.133564949,41.3750801086],"type":"Point"}
}