{
  "type": "Feature",
  "properties": {
    "iso:country":"ES",
    "sg:address":"Calle de Cuba (de), 10",
    "sg:city":"Fuenlabrada",
    "sg:orig_category":"Electricidad: Instaladores",
    "sg:phone":"+34 916 90 67 52",
    "sg:postcode":"28945",
    "sg:province":"Madrid",
    "wof:name":"Orme\u00f1o Quilon Timoteo",
    "wof:placetype":"venue"
},
  "geometry": {"coordinates":[-3.7878949642,40.2911529541],"type":"Point"}
}