{
  "type": "Feature",
  "properties": {
    "iso:country":"ES",
    "sg:address":"Carrer de Navas, 62",
    "sg:city":"Sabadell",
    "sg:orig_category":"Empresas De Carpinter\u00cda De Madera",
    "sg:phone":"+34 937 16 71 62",
    "sg:postcode":"08208",
    "sg:province":"Barcelona",
    "wof:name":"Adalid Lacalle Silvino",
    "wof:placetype":"venue"
},
  "geometry": {"coordinates":[2.1028089523,41.5614547729],"type":"Point"}
}