{
  "type": "Feature",
  "properties": {
    "addr:full":"Calle de Campomanes, 6 S. Fernando C\u00e1diz 11100",
    "addr:housenumber":"6",
    "addr:postcode":"11100",
    "addr:street":"Calle De Campomanes;S. Fernando Ca\u0301Diz",
    "iso:country":"ES",
    "sg:address":"Calle de Campomanes, 6",
    "sg:city":"S. Fernando",
    "sg:orig_category":"Farmacias",
    "sg:phone":"+34 956 59 50 53",
    "sg:postcode":"11100",
    "sg:province":"C\u00e1diz",
    "wof:name":"Collantes Vazquez De Castro Tomas",
    "wof:placetype":"venue"
},
  "geometry": {"coordinates":[-6.190653801,36.4736366272],"type":"Point"}
}