{
  "type": "Feature",
  "properties": {
    "addr:full":"Plaz Colonizacion, 17 S. Agustin Almer\u00eda 04700",
    "addr:housenumber":"17",
    "addr:postcode":"04700",
    "addr:street":"Plaz Colonizacion;S. Agustin Almeri\u0301A",
    "iso:country":"ES",
    "sg:address":"Plaz Colonizacion, 17",
    "sg:city":"S. Agustin",
    "sg:orig_category":"Cajas Para Embalar",
    "sg:phone":"+34 950 60 20 05",
    "sg:postcode":"04700",
    "sg:province":"Almer\u00eda",
    "wof:name":"Cajamar",
    "wof:placetype":"venue"
},
  "geometry": {"coordinates":[-2.8176040649,36.7727012634],"type":"Point"}
}