{
  "type": "Feature",
  "properties": {
    "addr:full":"Carrer de Bon Dia, 13 Coromina Barcelona 08261",
    "addr:housenumber":"13",
    "addr:postcode":"08261",
    "addr:street":"Carrer De Bon Dia;Barcelona",
    "iso:country":"ES",
    "sg:address":"Carrer de Bon Dia, 13",
    "sg:city":"Coromina",
    "sg:orig_category":"Maquinaria Y Herramientas Para Madera, Pvc, Aluminio Y Aperos (fabricaci\u00d3n, Comercio)",
    "sg:phone":"+34 938 69 00 35",
    "sg:postcode":"08261",
    "sg:province":"Barcelona",
    "wof:name":"Catalana De Tecnicas En Madera S.l.",
    "wof:placetype":"venue"
},
  "geometry": {"coordinates":[1.6924760342,41.9075164795],"type":"Point"}
}