{
  "type": "Feature",
  "properties": {
    "iso:country":"ES",
    "sg:address":"Av Catalunya, 46",
    "sg:city":"Tarrega",
    "sg:orig_category":"Soportes L\u00d3gicos, Programas Integradores De Aplicaciones (progiciels)",
    "sg:phone":"+34 973 31 12 09",
    "sg:postcode":"25300",
    "sg:province":"Lleida",
    "sg:website":"www.matsmatica.com",
    "wof:name":"Camats Sole Josep",
    "wof:placetype":"venue"
},
  "geometry": {"coordinates":[1.1367720366,41.64793396],"type":"Point"}
}