{
  "type": "Feature",
  "properties": {
    "addr:full":"Avda Gran Via Rey Juan Carlos I, 46 Logro\u00f1o La Rioja 26005",
    "addr:housenumber":"46",
    "addr:postcode":"26005",
    "addr:street":"Avda Gran Via Rey Juan Carlos I;Rioja",
    "iso:country":"ES",
    "sg:address":"Avda Gran Via Rey Juan Carlos I, 46",
    "sg:city":"Logro\u00f1o",
    "sg:orig_category":"Contenedores (mercanc\u00cdas)",
    "sg:phone":"+34 941 20 04 76",
    "sg:postcode":"26005",
    "sg:province":"La Rioja",
    "wof:name":"Agencia De Transportes Fruticolas Rioja S.l.",
    "wof:placetype":"venue"
},
  "geometry": {"coordinates":[-2.4518063068,42.4646873474],"type":"Point"}
}