{
  "type": "Feature",
  "properties": {
    "iso:country":"ES",
    "sg:address":"Rua Costa Do Pincho, 103",
    "sg:city":"Carral",
    "sg:orig_category":"Reposter\u00cdas",
    "sg:phone":"+34 981 67 24 76",
    "sg:postcode":"15175",
    "sg:province":"La Coru\u00f1a",
    "wof:name":"Panaderia Da Cunha S.l.",
    "wof:placetype":"venue"
},
  "geometry": {"coordinates":[-8.3558893204,43.2278442383],"type":"Point"}
}