{
  "type": "Feature",
  "properties": {
    "addr:full":"Calle de Ajuriaguerra Juan, 14 Bilbao Vizcaya 48009",
    "addr:housenumber":"14",
    "addr:postcode":"48009",
    "addr:street":"Calle De Ajuriaguerra Juan",
    "iso:country":"ES",
    "sg:address":"Calle de Ajuriaguerra Juan, 14",
    "sg:city":"Bilbao",
    "sg:orig_category":"Art\u00cdculos De Decoraci\u00d3n (fabricaci\u00d3n Y Al Por Mayor)",
    "sg:phone":"+34 944 23 23 22",
    "sg:postcode":"48009",
    "sg:province":"Vizcaya",
    "wof:name":"Uccello S.l.",
    "wof:placetype":"venue"
},
  "geometry": {"coordinates":[-2.9325149059,43.265712738],"type":"Point"}
}