{
  "type": "Feature",
  "properties": {
    "addr:full":"Calle de Republica Argentina, 68 Alacant Alicante 03007",
    "addr:housenumber":"68",
    "addr:postcode":"03007",
    "addr:street":"Calle De Republica Argentina",
    "iso:country":"ES",
    "sg:address":"Calle de Republica Argentina, 68",
    "sg:city":"Alacant",
    "sg:orig_category":"Agencias Y Asesores De Publicidad",
    "sg:phone":"+34 965 28 28 08",
    "sg:postcode":"03007",
    "sg:province":"Alicante",
    "wof:name":"Buisan Estudio Multimedia S.l.u.",
    "wof:placetype":"venue"
},
  "geometry": {"coordinates":[-0.5118510127,38.3415031433],"type":"Point"}
}