{
  "type": "Feature",
  "properties": {
    "addr:full":"Calle de Alonso Nu\u00d1ez De Reinoso, 2 Guadalajara Guadalajara 19002",
    "addr:housenumber":"2",
    "addr:postcode":"19002",
    "addr:street":"Calle De Alonso Nun\u0303Ez De Reinoso",
    "iso:country":"ES",
    "sg:address":"Calle de Alonso Nu\u00d1ez De Reinoso, 2",
    "sg:city":"Guadalajara",
    "sg:orig_category":"Bazares, Art\u00cdculos De Limpieza Y De Cocina (al Por Menor)",
    "sg:phone":"+34 949 21 77 56",
    "sg:postcode":"19002",
    "sg:province":"Guadalajara",
    "wof:name":"Cobo Diaz Raquel",
    "wof:placetype":"venue"
},
  "geometry": {"coordinates":[-3.1643242836,40.6265258789],"type":"Point"}
}