{
  "type": "Feature",
  "properties": {
    "iso:country":"ES",
    "sg:address":"Pl Generalitat, 145",
    "sg:city":"S. Boi Llobregat",
    "sg:orig_category":"Sociedades, Compa\u00d1\u00cdas Aseguradoras",
    "sg:phone":"+34 936 54 41 20",
    "sg:postcode":"08830",
    "sg:province":"Barcelona",
    "wof:name":"Mapfre Servicios De Informatica",
    "wof:placetype":"venue"
},
  "geometry": {"coordinates":[2.0311999321,41.3480682373],"type":"Point"}
}