{
  "type": "Feature",
  "properties": {
    "addr:full":"Av Diagonal, 7 Gava Barcelona 08850",
    "addr:housenumber":"7",
    "addr:postcode":"08850",
    "addr:street":"Av Diagonal",
    "iso:country":"ES",
    "sg:address":"Av Diagonal, 7",
    "sg:city":"Gava",
    "sg:orig_category":"Cajas De Ahorro",
    "sg:phone":"+34 936 38 19 17",
    "sg:postcode":"08850",
    "sg:province":"Barcelona",
    "sg:website":"www.caixatarragona.es",
    "wof:name":"Caixa D'estalvis De Tarragona",
    "wof:placetype":"venue"
},
  "geometry": {"coordinates":[1.9976429939,41.3046646118],"type":"Point"}
}