{
  "type": "Feature",
  "properties": {
    "iso:country":"ES",
    "sg:address":"Carrer de Salses, 103",
    "sg:city":"Barcelona",
    "sg:orig_category":"Edici\u00d3n Fonogr\u00c1fica De M\u00dasica",
    "sg:phone":"+34 934 27 30 86",
    "sg:postcode":"08031",
    "sg:province":"Barcelona",
    "sg:website":"www.supermusics.com",
    "wof:name":"Aragall Torres Montserrat",
    "wof:placetype":"venue"
},
  "geometry": {"coordinates":[2.1554164886,41.4355049133],"type":"Point"}
}