{
  "type": "Feature",
  "properties": {
    "addr:full":"Calle de Felix Aramburu, 8 Oviedo Asturias 33007",
    "addr:housenumber":"8",
    "addr:postcode":"33007",
    "addr:street":"Calle De Felix Aramburu",
    "iso:country":"ES",
    "sg:address":"Calle de Felix Aramburu, 8",
    "sg:city":"Oviedo",
    "sg:orig_category":"Molduras, Junquillos, Listones Y Molduras Perforadas",
    "sg:phone":"+34 985 23 29 23",
    "sg:postcode":"33007",
    "sg:province":"Asturias",
    "wof:name":"Alvarez Rodriguez Almudena",
    "wof:placetype":"venue"
},
  "geometry": {"coordinates":[-5.8519191742,43.3564949036],"type":"Point"}
}