{
  "type": "Feature",
  "properties": {
    "addr:full":"Avda Constitucion (de La), 48 Mostoles Madrid 28931",
    "addr:housenumber":"48",
    "addr:postcode":"28931",
    "addr:street":"Avda Constitucion De La",
    "iso:country":"ES",
    "sg:address":"Avda Constitucion (de La), 48",
    "sg:city":"Mostoles",
    "sg:orig_category":"\u00d3ptica: Instrumentos (fabricaci\u00d3n)",
    "sg:phone":"+34 916 13 26 77",
    "sg:postcode":"28931",
    "sg:province":"Madrid",
    "wof:name":"Paysa C.b.",
    "wof:placetype":"venue"
},
  "geometry": {"coordinates":[-3.861538887,40.3258781433],"type":"Point"}
}