{
  "type": "Feature",
  "properties": {
    "addr:full":"Calle de Pablo Casal, 2 Santa Fe Granada 18320",
    "addr:housenumber":"2",
    "addr:postcode":"18320",
    "addr:street":"Calle De Pablo Casal;Fe",
    "iso:country":"ES",
    "sg:address":"Calle de Pablo Casal, 2",
    "sg:city":"Santa Fe",
    "sg:orig_category":"Laboratorios De Control Sanitario Y Ambiental",
    "sg:phone":"+34 958 44 15 47",
    "sg:postcode":"18320",
    "sg:province":"Granada",
    "wof:name":"Biomasa Del Guadalquivir S.a.",
    "wof:placetype":"venue"
},
  "geometry": {"coordinates":[-3.7119340897,37.1921005249],"type":"Point"}
}