{
  "type": "Feature",
  "properties": {
    "iso:country":"ES",
    "sg:address":"Polg I El Pilero, 3",
    "sg:city":"Carmona",
    "sg:orig_category":"Electricidad, Electr\u00d3nica: Suministros (al Por Menor)",
    "sg:phone":"+34 954 14 09 95",
    "sg:postcode":"41410",
    "sg:province":"Sevilla",
    "wof:name":"Carmoelectronica Circuito S.l.",
    "wof:placetype":"venue"
},
  "geometry": {"coordinates":[-5.6433792114,37.4708709717],"type":"Point"}
}