{
  "type": "Feature",
  "properties": {
    "iso:country":"ES",
    "sg:address":"C/ Anselm Clave, 7",
    "sg:city":"Salt",
    "sg:orig_category":"Venta, Instalaci\u00d3n De Calefacci\u00d3n",
    "sg:phone":"+34 972 23 78 57",
    "sg:postcode":"17190",
    "sg:province":"Girona",
    "wof:name":"Vicatec S.c.",
    "wof:placetype":"venue"
},
  "geometry": {"coordinates":[2.7998759747,41.9754257202],"type":"Point"}
}