{
  "type": "Feature",
  "properties": {
    "addr:full":"Mercat Mare Deu L'estel, S/n Barcelona Barcelona 08012",
    "addr:housenumber":"s",
    "addr:postcode":"08012",
    "addr:street":"/ N",
    "iso:country":"ES",
    "sg:address":"Mercat Mare Deu L'estel, S/n",
    "sg:city":"Barcelona",
    "sg:orig_category":"Carnicer\u00cdas, Carnicer\u00cdas",
    "sg:phone":"+34 932 84 20 87",
    "sg:postcode":"08012",
    "sg:province":"Barcelona",
    "wof:name":"Ormad Cabrera Francisco",
    "wof:placetype":"venue"
},
  "geometry": {"coordinates":[2.1572899818,41.4029312134],"type":"Point"}
}