{
  "type": "Feature",
  "properties": {
    "addr:full":"Ctra. Toledo, Km. 0030,0 Galvez Toledo 45164",
    "addr:housenumber":"km.",
    "addr:postcode":"45164",
    "addr:street":"Ctra. Toledo;0030,0 Galvez",
    "iso:country":"ES",
    "sg:address":"Ctra. Toledo, Km. 0030,0",
    "sg:city":"Galvez",
    "sg:orig_category":"Mec\u00c1nico Del Autom\u00d3vil",
    "sg:phone":"+34 925 40 01 24",
    "sg:postcode":"45164",
    "sg:province":"Toledo",
    "wof:name":"Sobrino Braojos Jesus",
    "wof:placetype":"venue"
},
  "geometry": {"coordinates":[-4.2757091522,39.7027244568],"type":"Point"}
}