{
  "type": "Feature",
  "properties": {
    "iso:country":"ES",
    "sg:address":"Avda Juan Carlos I Rey De Espa\u00d1a, 3",
    "sg:city":"Villarejo Salvanes",
    "sg:orig_category":"Aguas (distribuci\u00d3n, Servicios)",
    "sg:phone":"+34 918 74 23 39",
    "sg:postcode":"28590",
    "sg:province":"Madrid",
    "wof:name":"Iberdeposito S.l",
    "wof:placetype":"venue"
},
  "geometry": {"coordinates":[-3.2918949127,40.1731338501],"type":"Point"}
}