{
  "type": "Feature",
  "properties": {
    "iso:country":"ES",
    "sg:address":"Avda Reina Sofia, 66",
    "sg:city":"Merida",
    "sg:orig_category":"Asociaciones Humanitarias, De Cooperaci\u00d3n, De Acci\u00d3n Social",
    "sg:phone":"+34 924 30 16 08",
    "sg:postcode":"06800",
    "sg:province":"Badajoz",
    "wof:name":"Centro Reto La Esperanza",
    "wof:placetype":"venue"
},
  "geometry": {"coordinates":[-6.3240418434,38.9258232117],"type":"Point"}
}