{
  "type": "Feature",
  "properties": {
    "iso:country":"ES",
    "sg:address":"Pescaderia Vieja, 8",
    "sg:city":"Muros",
    "sg:orig_category":"Librer\u00cdas",
    "sg:phone":"+34 981 82 68 09",
    "sg:postcode":"15250",
    "sg:province":"La Coru\u00f1a",
    "wof:name":"Gallardo Saavedra Jose Manuel",
    "wof:placetype":"venue"
},
  "geometry": {"coordinates":[-9.059425354,42.7764053345],"type":"Point"}
}