{
  "type": "Feature",
  "properties": {
    "addr:full":"La Linea, 14 Ronda M\u00e1laga 29400",
    "addr:postcode":"29400",
    "addr:street":"Linea;Ronda Ma\u0301Laga",
    "iso:country":"ES",
    "sg:address":"La Linea, 14",
    "sg:city":"Ronda",
    "sg:orig_category":"M\u00c9dicos: Ginecolog\u00cda Y Obstetricia",
    "sg:phone":"+34 952 87 52 30",
    "sg:postcode":"29400",
    "sg:province":"M\u00e1laga",
    "wof:name":"Troncoso Grano De Oro Julio Urbano",
    "wof:placetype":"venue"
},
  "geometry": {"coordinates":[-5.1674861908,36.727973938],"type":"Point"}
}