{
  "type": "Feature",
  "properties": {
    "addr:full":"Av Paral.lel, 182 Barcelona Barcelona 08015",
    "addr:housenumber":"182",
    "addr:postcode":"08015",
    "addr:street":"Av Paral.Lel",
    "iso:country":"ES",
    "sg:address":"Av Paral.lel, 182",
    "sg:city":"Barcelona",
    "sg:orig_category":"Asesor\u00cda De Formaci\u00d3n Y Gesti\u00d3n De Personal",
    "sg:phone":"+34 934 23 28 47",
    "sg:postcode":"08015",
    "sg:province":"Barcelona",
    "wof:name":"Alvarez Landeira Jose",
    "wof:placetype":"venue"
},
  "geometry": {"coordinates":[2.153894186,41.3750305176],"type":"Point"}
}