{
  "type": "Feature",
  "properties": {
    "iso:country":"ES",
    "sg:address":"Avda Galicia, 12",
    "sg:city":"Fonsagrada",
    "sg:orig_category":"Caf\u00c9s, Bares, Cervecer\u00cdas",
    "sg:phone":"+34 982 34 01 12",
    "sg:postcode":"27100",
    "sg:province":"Lugo",
    "wof:name":"Rois De La Pe\u00f1a S.l.",
    "wof:placetype":"venue"
},
  "geometry": {"coordinates":[-7.0681400299,43.1261749268],"type":"Point"}
}