{
  "type": "Feature",
  "properties": {
    "addr:full":"Carrer de Nou, 6 Centelles Barcelona 08540",
    "addr:housenumber":"6",
    "addr:postcode":"08540",
    "addr:street":"Carrer De Nou",
    "iso:country":"ES",
    "sg:address":"Carrer de Nou, 6",
    "sg:city":"Centelles",
    "sg:orig_category":"Cajas De Ahorro",
    "sg:phone":"+34 938 81 11 51",
    "sg:postcode":"08540",
    "sg:province":"Barcelona",
    "sg:website":"www.caixademanlleu.es",
    "wof:name":"Caixa De Manlleu",
    "wof:placetype":"venue"
},
  "geometry": {"coordinates":[2.2186150551,41.7978172302],"type":"Point"}
}