{
  "type": "Feature",
  "properties": {
    "addr:full":"Calle de Alava, 35 Vitoria-gasteiz \u00c1lava 01006",
    "addr:housenumber":"35",
    "addr:postcode":"01006",
    "addr:street":"Calle De Alava",
    "iso:country":"ES",
    "sg:address":"Calle de Alava, 35",
    "sg:city":"Vitoria-gasteiz",
    "sg:orig_category":"Internados & Ense\u00d1anza Privada",
    "sg:phone":"+34 945 23 29 67",
    "sg:postcode":"01006",
    "sg:province":"\u00c1lava",
    "wof:name":"Colegio Nazaret Institut D'etudes Francaises",
    "wof:placetype":"venue"
},
  "geometry": {"coordinates":[-2.6767652035,42.8371315002],"type":"Point"}
}