{
  "type": "Feature",
  "properties": {
    "addr:full":"Ctra Santpedor, S/n Manresa Barcelona 08240",
    "addr:housenumber":"s / n",
    "addr:postcode":"08240",
    "addr:street":"Ctra Santpedor",
    "iso:country":"ES",
    "sg:address":"Ctra Santpedor, S/n",
    "sg:city":"Manresa",
    "sg:orig_category":"Producci\u00d3n, Venta De Productos De Agricultura Biol\u00d3gica",
    "sg:phone":"+34 938 73 19 67",
    "sg:postcode":"08240",
    "sg:province":"Barcelona",
    "wof:name":"Granja Colome S.l.",
    "wof:placetype":"venue"
},
  "geometry": {"coordinates":[1.8324049711,41.7369003296],"type":"Point"}
}