{
  "type": "Feature",
  "properties": {
    "addr:full":"Calle de San Francisco, 12 Alca\u00f1ices Zamora 49500",
    "addr:housenumber":"12",
    "addr:postcode":"49500",
    "addr:street":"Calle De San Francisco;Zamora",
    "iso:country":"ES",
    "sg:address":"Calle de San Francisco, 12",
    "sg:city":"Alca\u00f1ices",
    "sg:orig_category":"Alimentaci\u00d3n General (al Por Menor)",
    "sg:phone":"+34 980 68 01 58",
    "sg:postcode":"49500",
    "sg:province":"Zamora",
    "wof:name":"Ramos Gonzalez Domingo",
    "wof:placetype":"venue"
},
  "geometry": {"coordinates":[-6.3470687866,41.6990699768],"type":"Point"}
}