{
  "type": "Feature",
  "properties": {
    "addr:full":"Calle de Alfonso Vi, 43 Miranda Ebro Burgos 09200",
    "addr:housenumber":"43",
    "addr:postcode":"09200",
    "addr:street":"Calle De Alfonso Vi",
    "iso:country":"ES",
    "sg:address":"Calle de Alfonso Vi, 43",
    "sg:city":"Miranda Ebro",
    "sg:orig_category":"Ingenier\u00cda, Centros De Estudios (diversos)",
    "sg:phone":"+34 947 34 77 91",
    "sg:postcode":"09200",
    "sg:province":"Burgos",
    "sg:website":"www.astiv.net",
    "wof:name":"Astiv Ingenieria Sl",
    "wof:placetype":"venue"
},
  "geometry": {"coordinates":[-2.9428832531,42.6860122681],"type":"Point"}
}