{
  "type": "Feature",
  "properties": {
    "addr:full":"Rua Progreso (do), 135 Ourense Ourense 32003",
    "addr:housenumber":"135",
    "addr:postcode":"32003",
    "addr:street":"Rua Progreso Do",
    "iso:country":"ES",
    "sg:address":"Rua Progreso (do), 135",
    "sg:city":"Ourense",
    "sg:orig_category":"Zapatos (al Por Menor)",
    "sg:phone":"+34 988 37 01 93",
    "sg:postcode":"32003",
    "sg:province":"Ourense",
    "wof:name":"Gonzalez Perez Jose",
    "wof:placetype":"venue"
},
  "geometry": {"coordinates":[-7.8675141335,42.3415603638],"type":"Point"}
}