{
  "type": "Feature",
  "properties": {
    "addr:full":"Ctra. Jaen, 40 Albacete Albacete 02006",
    "addr:housenumber":"40",
    "addr:postcode":"02006",
    "addr:street":"Ctra. Jaen",
    "iso:country":"ES",
    "sg:address":"Ctra. Jaen, 40",
    "sg:city":"Albacete",
    "sg:orig_category":"Reposter\u00cdas",
    "sg:phone":"+34 967 22 66 58",
    "sg:postcode":"02006",
    "sg:province":"Albacete",
    "wof:name":"Anjomar Del Jucar S.l.l.",
    "wof:placetype":"venue"
},
  "geometry": {"coordinates":[-1.9391050339,38.9425926208],"type":"Point"}
}