{
  "type": "Feature",
  "properties": {
    "iso:country":"ES",
    "sg:address":"Carrer de Lluis Millet, 3",
    "sg:city":"Masnou",
    "sg:orig_category":"Agencias Y Agentes Comerciales, Representantes",
    "sg:phone":"+34 935 40 92 52",
    "sg:postcode":"08320",
    "sg:province":"Barcelona",
    "wof:name":"Verdaguer Pi Gabriel",
    "wof:placetype":"venue"
},
  "geometry": {"coordinates":[2.3169150352,41.4799385071],"type":"Point"}
}