{
  "type": "Feature",
  "properties": {
    "addr:full":"Carrer de Balmes, 383 Barcelona Barcelona 08022",
    "addr:housenumber":"383",
    "addr:postcode":"08022",
    "addr:street":"Carrer De Balmes",
    "iso:country":"ES",
    "sg:address":"Carrer de Balmes, 383",
    "sg:city":"Barcelona",
    "sg:orig_category":"Colchones (fabricaci\u00d3n, Al Por Mayor, Al Por Menor)",
    "sg:phone":"+34 934 17 37 93",
    "sg:postcode":"08022",
    "sg:province":"Barcelona",
    "wof:name":"Xicart Ciaurri Jaime",
    "wof:placetype":"venue"
},
  "geometry": {"coordinates":[2.1398348808,41.4047851562],"type":"Point"}
}