{
  "type": "Feature",
  "properties": {
    "iso:country":"ES",
    "sg:address":"Vrda Pepejos, 14",
    "sg:city":"El Raal",
    "sg:orig_category":"Frutas Y Legumbres Frescas (al Por Mayor)",
    "sg:phone":"+34 968 87 07 14",
    "sg:postcode":"30139",
    "sg:province":"Murcia",
    "wof:name":"Hortalizas Del Segura S.l.",
    "wof:placetype":"venue"
},
  "geometry": {"coordinates":[-1.0326590538,38.0375366211],"type":"Point"}
}