{
  "type": "Feature",
  "properties": {
    "addr:full":"Carrer de Muntaner, 31 Barcelona Barcelona 08011",
    "addr:housenumber":"31",
    "addr:postcode":"08011",
    "addr:street":"Carrer De Muntaner",
    "iso:country":"ES",
    "sg:address":"Carrer de Muntaner, 31",
    "sg:city":"Barcelona",
    "sg:orig_category":"Producci\u00d3n, Distribuci\u00d3n De Electricidad",
    "sg:phone":"+34 933 23 71 60",
    "sg:postcode":"08011",
    "sg:province":"Barcelona",
    "wof:name":"Muntaner Electro S.l.",
    "wof:placetype":"venue"
},
  "geometry": {"coordinates":[2.1611390114,41.3851394653],"type":"Point"}
}