{
  "type": "Feature",
  "properties": {
    "addr:full":"Calle de General Canino, 16 Sagunt Valencia 46500",
    "addr:housenumber":"16",
    "addr:postcode":"46500",
    "addr:street":"Calle De General Canino",
    "iso:country":"ES",
    "sg:address":"Calle de General Canino, 16",
    "sg:city":"Sagunt",
    "sg:orig_category":"Almacenes Para Venta: Muebles Y Varios",
    "sg:phone":"+34 962 66 59 61",
    "sg:postcode":"46500",
    "sg:province":"Valencia",
    "wof:name":"Mobiliari Decorasio Decomar S.l.",
    "wof:placetype":"venue"
},
  "geometry": {"coordinates":[-0.2769410014,39.6812400818],"type":"Point"}
}