{
  "type": "Feature",
  "properties": {
    "addr:full":"Calle de Conde De Altea, 6 Altea Alicante 03590",
    "addr:housenumber":"6",
    "addr:postcode":"03590",
    "addr:street":"Calle De Conde De Altea",
    "iso:country":"ES",
    "sg:address":"Calle de Conde De Altea, 6",
    "sg:city":"Altea",
    "sg:orig_category":"Caf\u00c9s, Bares, Cervecer\u00cdas",
    "sg:phone":"+34 965 84 43 51",
    "sg:postcode":"03590",
    "sg:province":"Alicante",
    "wof:name":"Cafe Viena S.l.",
    "wof:placetype":"venue"
},
  "geometry": {"coordinates":[-0.0445689,38.6034584045],"type":"Point"}
}