{
  "type": "Feature",
  "properties": {
    "iso:country":"ES",
    "sg:address":"Calle de Bolta\u00d1a, 41",
    "sg:city":"Madrid",
    "sg:orig_category":"Institutos De Belleza",
    "sg:phone":"+34 913 20 59 71",
    "sg:postcode":"28022",
    "sg:province":"Madrid",
    "wof:name":"On Line Estilistas S.l.",
    "wof:placetype":"venue"
},
  "geometry": {"coordinates":[-3.6106617451,40.4469413757],"type":"Point"}
}