{
  "type": "Feature",
  "properties": {
    "iso:country":"ES",
    "sg:address":"Calle de Boteros, 33",
    "sg:city":"S. Clemente",
    "sg:orig_category":"Estancos",
    "sg:phone":"+34 969 30 16 46",
    "sg:postcode":"16600",
    "sg:province":"Cuenca",
    "wof:name":"Quintanilla Requena Elvira",
    "wof:placetype":"venue"
},
  "geometry": {"coordinates":[-2.4272515774,39.4051055908],"type":"Point"}
}