{
  "type": "Feature",
  "properties": {
    "iso:country":"ES",
    "sg:address":"Avda Chile, 25",
    "sg:city":"Coru\u00d1a",
    "sg:orig_category":"Organismos De Reclutamiento",
    "sg:phone":"+34 981 23 97 96",
    "sg:postcode":"15008",
    "sg:province":"A Coru\u00f1a",
    "wof:name":"Serco S.l.",
    "wof:placetype":"venue"
},
  "geometry": {"coordinates":[-8.4041776657,43.3527946472],"type":"Point"}
}