{
  "type": "Feature",
  "properties": {
    "addr:full":"Calle de Principe De Vergara, 115 Madrid Madrid 28002",
    "addr:housenumber":"115",
    "addr:postcode":"28002",
    "addr:street":"Calle De Principe De Vergara",
    "iso:country":"ES",
    "sg:address":"Calle de Principe De Vergara, 115",
    "sg:city":"Madrid",
    "sg:orig_category":"Muebles, Minoristas",
    "sg:phone":"+34 915 61 61 91",
    "sg:postcode":"28002",
    "sg:province":"Madrid",
    "wof:name":"Sofa 10 Decoracion S.l.",
    "wof:placetype":"venue"
},
  "geometry": {"coordinates":[-3.6788818836,40.4410057068],"type":"Point"}
}