{
  "type": "Feature",
  "properties": {
    "addr:full":"Avda. Pamplona, 16 Estella Navarra 31200",
    "addr:housenumber":"16",
    "addr:postcode":"31200",
    "addr:street":"Avda. Pamplona",
    "iso:country":"ES",
    "sg:address":"Avda. Pamplona, 16",
    "sg:city":"Estella",
    "sg:orig_category":"Cueros Y Pieles (al Por Mayor)",
    "sg:phone":"+34 948 55 16 98",
    "sg:postcode":"31200",
    "sg:province":"Navarra",
    "wof:name":"Curtidos Castejon S.l.",
    "wof:placetype":"venue"
},
  "geometry": {"coordinates":[-2.0221579075,42.6684112549],"type":"Point"}
}