{
  "type": "Feature",
  "properties": {
    "addr:full":"Calle de Ciudad De Mula, 18 Valencia Valencia 46021",
    "addr:housenumber":"18",
    "addr:postcode":"46021",
    "addr:street":"Calle De Ciudad De Mula",
    "iso:country":"ES",
    "sg:address":"Calle de Ciudad De Mula, 18",
    "sg:city":"Valencia",
    "sg:orig_category":"Reparaciones Y Remolcado De Veh\u00cdculos",
    "sg:phone":"+34 963 69 30 52",
    "sg:postcode":"46021",
    "sg:province":"Valencia",
    "wof:name":"Gruas Y Talleres J.a.m.s.coop.v.",
    "wof:placetype":"venue"
},
  "geometry": {"coordinates":[-0.3533709049,39.4740791321],"type":"Point"}
}