{
  "type": "Feature",
  "properties": {
    "iso:country":"ES",
    "sg:address":"Calle de San Restituto, 49",
    "sg:city":"Madrid",
    "sg:orig_category":"Arquitectos",
    "sg:phone":"+34 913 86 69 52",
    "sg:postcode":"28039",
    "sg:province":"Madrid",
    "wof:name":"Casti\u00f1eira Etcheverria Gonzalo",
    "wof:placetype":"venue"
},
  "geometry": {"coordinates":[-3.7158238888,40.4662246704],"type":"Point"}
}