{
  "type": "Feature",
  "properties": {
    "iso:country":"ES",
    "sg:address":"Ctra. Mozoncillo, Km. 0014,0",
    "sg:city":"Aldea Real",
    "sg:orig_category":"Agricultores, Agricultores",
    "sg:phone":"+34 921 12 20 71",
    "sg:postcode":"40293",
    "sg:province":"Segovia",
    "wof:name":"Navadrian S.l.",
    "wof:placetype":"venue"
},
  "geometry": {"coordinates":[-4.1844592094,41.259979248],"type":"Point"}
}