{
  "type": "Feature",
  "properties": {
    "addr:full":"Calle de Torregorda, 24 Sevilla Sevilla 41016",
    "addr:housenumber":"24",
    "addr:postcode":"41016",
    "addr:street":"Calle De Torregorda",
    "iso:country":"ES",
    "sg:address":"Calle de Torregorda, 24",
    "sg:city":"Sevilla",
    "sg:orig_category":"Relojer\u00cda (al Por Menor, Reparaci\u00d3n)",
    "sg:phone":"+34 954 40 27 01",
    "sg:postcode":"41016",
    "sg:province":"Sevilla",
    "wof:name":"Arana Moreno Jose",
    "wof:placetype":"venue"
},
  "geometry": {"coordinates":[-5.9171977043,37.3816986084],"type":"Point"}
}