{
  "type": "Feature",
  "properties": {
    "addr:full":"Ctra Del Rocio, 217 Almonte Huelva 21730",
    "addr:housenumber":"217",
    "addr:postcode":"21730",
    "addr:street":"Ctra Del Rocio",
    "iso:country":"ES",
    "sg:address":"Ctra Del Rocio, 217",
    "sg:city":"Almonte",
    "sg:orig_category":"Venta, Montaje De Neum\u00c1ticos",
    "sg:phone":"+34 959 40 68 57",
    "sg:postcode":"21730",
    "sg:province":"Huelva",
    "wof:name":"Hernandez Solis Cristobal",
    "wof:placetype":"venue"
},
  "geometry": {"coordinates":[-6.5201101303,37.2550849915],"type":"Point"}
}