{
  "type": "Feature",
  "properties": {
    "iso:country":"ES",
    "sg:address":"Calle de Asalto, 16",
    "sg:city":"Malaga",
    "sg:orig_category":"Grabados",
    "sg:phone":"+34 952 35 67 28",
    "sg:postcode":"29006",
    "sg:province":"M\u00e1laga",
    "wof:name":"Grabados Malaga S.l.",
    "wof:placetype":"venue"
},
  "geometry": {"coordinates":[-4.4372792244,36.7137718201],"type":"Point"}
}