{
  "type": "Feature",
  "properties": {
    "iso:country":"ES",
    "sg:address":"Luga Poligono Industrial, S/n",
    "sg:city":"Cabanillas Campo",
    "sg:orig_category":"Inform\u00c1tica: Material Y Suministros",
    "sg:phone":"+34 949 20 17 12",
    "sg:postcode":"19171",
    "sg:province":"Guadalajara",
    "wof:name":"Servihenares S.l.",
    "wof:placetype":"venue"
},
  "geometry": {"coordinates":[-3.2194590569,40.5990333557],"type":"Point"}
}