{
  "type": "Feature",
  "properties": {
    "iso:country":"ES",
    "sg:address":"Calle de Empedrada, 17",
    "sg:city":"Aranda Duero",
    "sg:orig_category":"Telas Y Sedas (al Por Menor)",
    "sg:phone":"+34 947 50 47 19",
    "sg:postcode":"09400",
    "sg:province":"Burgos",
    "wof:name":"Maria Fernanda Sebastian Gonzalez C.b",
    "wof:placetype":"venue"
},
  "geometry": {"coordinates":[-3.6870748997,41.6702346802],"type":"Point"}
}