{
  "type": "Feature",
  "properties": {
    "iso:country":"ES",
    "sg:address":"Urb. Vistamar, 16",
    "sg:city":"Elviria",
    "sg:classifiers":[
        {
            "category":"Sports & Exercise",
            "subcategory":"Golf",
            "type":"Entertainment"
        }
    ],
    "sg:phone":"+34 952 83 87 52",
    "sg:postcode":"29604",
    "sg:province":"M\u00e1laga",
    "sg:tags":[
        "y",
        "de",
        "campos",
        "clases"
    ],
    "wof:name":"Wallace Golf Management S.l.",
    "wof:placetype":"venue"
},
  "geometry": {"coordinates":[-4.7839570045,36.4972267151],"type":"Point"}
}