{
  "type": "Feature",
  "properties": {
    "iso:country":"ES",
    "sg:address":"Carrer de Josep Anselm Clave, 21",
    "sg:city":"Mataro",
    "sg:orig_category":"Reposter\u00cdas",
    "sg:phone":"+34 937 41 01 15",
    "sg:postcode":"08301",
    "sg:province":"Barcelona",
    "wof:name":"Dialypa S.a.",
    "wof:placetype":"venue"
},
  "geometry": {"coordinates":[2.4468810558,41.5444602966],"type":"Point"}
}