{
  "type": "Feature",
  "properties": {
    "iso:country":"ES",
    "sg:address":"Calle de Ildefonso Fierro Ordo\u00d1ez, 1",
    "sg:city":"Le\u00f3n",
    "sg:orig_category":"Alimentaci\u00d3n General (al Por Menor)",
    "sg:phone":"+34 987 20 41 14",
    "sg:postcode":"24005",
    "sg:province":"Le\u00f3n",
    "wof:name":"Fernandez Blanco Horacio",
    "wof:placetype":"venue"
},
  "geometry": {"coordinates":[-5.5681271553,42.5855293274],"type":"Point"}
}