{
  "type": "Feature",
  "properties": {
    "addr:full":"Calle de German Galindo, 6 Calasparra Murcia 30420",
    "addr:housenumber":"6",
    "addr:postcode":"30420",
    "addr:street":"Calle De German Galindo",
    "iso:country":"ES",
    "sg:address":"Calle de German Galindo, 6",
    "sg:city":"Calasparra",
    "sg:orig_category":"Ense\u00d1anza: Profesiones Art\u00cdsticas",
    "sg:phone":"+34 968 72 03 44",
    "sg:postcode":"30420",
    "sg:province":"Murcia",
    "wof:name":"Aznar Galipienso Diego Antonio",
    "wof:placetype":"venue"
},
  "geometry": {"coordinates":[-1.6987731457,38.2306137085],"type":"Point"}
}