{
  "type": "Feature",
  "properties": {
    "addr:full":"Calle de Peinado, 31 Tomelloso Ciudad Real 13700",
    "addr:housenumber":"31",
    "addr:postcode":"13700",
    "addr:street":"Calle De Peinado",
    "iso:country":"ES",
    "sg:address":"Calle de Peinado, 31",
    "sg:city":"Tomelloso",
    "sg:orig_category":"Contenedores (mercanc\u00cdas)",
    "sg:phone":"+34 926 50 41 55",
    "sg:postcode":"13700",
    "sg:province":"Ciudad Real",
    "wof:name":"Espinosa Ortiz Juan Pedro",
    "wof:placetype":"venue"
},
  "geometry": {"coordinates":[-3.0222780704,39.1528549194],"type":"Point"}
}