{
  "type": "Feature",
  "properties": {
    "addr:full":"Calle de Cuatro Esquinas, 17 Alhama Granada Granada 18120",
    "addr:housenumber":"17",
    "addr:postcode":"18120",
    "addr:street":"Calle De Cuatro Esquinas",
    "iso:country":"ES",
    "sg:address":"Calle de Cuatro Esquinas, 17",
    "sg:city":"Alhama Granada",
    "sg:orig_category":"Inmobiliaria (agencias)",
    "sg:phone":"+34 958 35 04 84",
    "sg:postcode":"18120",
    "sg:province":"Granada",
    "sg:website":"www.highlands-estates.com",
    "wof:name":"Martin Oviedo Maria Dolores",
    "wof:placetype":"venue"
},
  "geometry": {"coordinates":[-3.9924087524,37.0012969971],"type":"Point"}
}