{
  "type": "Feature",
  "properties": {
    "addr:full":"Carretera De Pilas, S/n Hinojos Huelva 21740",
    "addr:housenumber":"s",
    "addr:postcode":"21740",
    "addr:street":"Carretera De Pilas;/ N Hinojos",
    "iso:country":"ES",
    "sg:address":"Carretera De Pilas, S/n",
    "sg:city":"Hinojos",
    "sg:orig_category":"Distribuci\u00d3n De Petr\u00d3leo Y Derivados",
    "sg:phone":"+34 959 45 97 34",
    "sg:postcode":"21740",
    "sg:province":"Huelva",
    "wof:name":"Petrowestoil S.l.",
    "wof:placetype":"venue"
},
  "geometry": {"coordinates":[-6.3758640289,37.2909317017],"type":"Point"}
}