{
  "type": "Feature",
  "properties": {
    "iso:country":"ES",
    "sg:address":"Calle de Leopoldo Alas Clarin, 18",
    "sg:city":"Zamora",
    "sg:orig_category":"Molduras, Junquillos, Listones Y Molduras Perforadas",
    "sg:phone":"+34 980 52 66 06",
    "sg:postcode":"49016",
    "sg:province":"Zamora",
    "wof:name":"Barahona Pelaez Nicolas",
    "wof:placetype":"venue"
},
  "geometry": {"coordinates":[-5.7375798225,41.5068016052],"type":"Point"}
}