{
  "type": "Feature",
  "properties": {
    "iso:country":"ES",
    "sg:address":"Av Olivera, 5",
    "sg:city":"Magaluf",
    "sg:orig_category":"Camiser\u00cda Y Ropa Interior Masculina (al Por Menor)",
    "sg:phone":"+34 971 13 03 70",
    "sg:postcode":"07181",
    "sg:province":"Islas Baleares",
    "wof:name":"Hobbs  Eva Anna",
    "wof:placetype":"venue"
},
  "geometry": {"coordinates":[2.5321600437,39.5065956116],"type":"Point"}
}