{
  "type": "Feature",
  "properties": {
    "addr:full":"Calle de Manuel Macias Miguez, 1 Sevilla Sevilla 41010",
    "addr:housenumber":"1",
    "addr:postcode":"41010",
    "addr:street":"Calle De Manuel Macias Miguez",
    "iso:country":"ES",
    "sg:address":"Calle de Manuel Macias Miguez, 1",
    "sg:city":"Sevilla",
    "sg:classifiers":[
        {
            "category":"Personal",
            "subcategory":"Barber",
            "type":"Services"
        }
    ],
    "sg:phone":"+34 954 34 44 44",
    "sg:postcode":"41010",
    "sg:province":"Sevilla",
    "sg:tags":[
        "caballeros",
        "de",
        "peluqueros"
    ],
    "wof:name":"Bernal Pe\u00f1a Jose",
    "wof:placetype":"venue"
},
  "geometry": {"coordinates":[-6.011800766,37.3861465454],"type":"Point"}
}