{
  "type": "Feature",
  "properties": {
    "addr:full":"Ctra Pantano-montellano, Km. 0015,0 Palmar De Troya Sevilla 41719",
    "addr:postcode":"41719",
    "addr:street":"Ctra Pantano-Montellano Km. 0015,0",
    "iso:country":"ES",
    "sg:address":"Ctra Pantano-montellano, Km. 0015,0",
    "sg:city":"Palmar De Troya",
    "sg:orig_category":"Agricultores, Agricultores",
    "sg:phone":"+34 955 89 83 56",
    "sg:postcode":"41719",
    "sg:province":"Sevilla",
    "wof:name":"Guajardo-fajardo Carmona Maria De Los Angeles",
    "wof:placetype":"venue"
},
  "geometry": {"coordinates":[-5.8067827225,37.0630912781],"type":"Point"}
}