{
  "type": "Feature",
  "properties": {
    "iso:country":"ES",
    "sg:address":"Calle de Rosario, 54",
    "sg:city":"Viso Del Alcor",
    "sg:orig_category":"Farmacias",
    "sg:phone":"+34 955 94 50 31",
    "sg:postcode":"41520",
    "sg:province":"Sevilla",
    "wof:name":"De Los Santos Leon Jose Luis",
    "wof:placetype":"venue"
},
  "geometry": {"coordinates":[-5.7207279205,37.3886909485],"type":"Point"}
}