{
  "type": "Feature",
  "properties": {
    "iso:country":"ES",
    "sg:address":"Calle de Pinzon, 30",
    "sg:city":"Madrid",
    "sg:orig_category":"Electrodom\u00c9sticos (al Por Menor)",
    "sg:phone":"+34 914 61 79 19",
    "sg:postcode":"28025",
    "sg:province":"Madrid",
    "sg:website":"www.menajedelhogar.com",
    "wof:name":"Electrodomesticos Menaje Del Hogar S.a.",
    "wof:placetype":"venue"
},
  "geometry": {"coordinates":[-3.7403149605,40.3890800476],"type":"Point"}
}