{
  "type": "Feature",
  "properties": {
    "addr:full":"Ctra. Palma-arta, 4 Vilafranca Bonany Islas Baleares 07250",
    "addr:housenumber":"4",
    "addr:postcode":"07250",
    "addr:street":"Ctra. Palma-Arta;Bonany",
    "iso:country":"ES",
    "sg:address":"Ctra. Palma-arta, 4",
    "sg:city":"Vilafranca Bonany",
    "sg:orig_category":"Forjas Y Altos Hornos",
    "sg:phone":"+34 971 56 00 30",
    "sg:postcode":"07250",
    "sg:province":"Islas Baleares",
    "wof:name":"Barcelo Nigorra Sebastia",
    "wof:placetype":"venue"
},
  "geometry": {"coordinates":[3.0871129036,39.5691604614],"type":"Point"}
}