{
  "type": "Feature",
  "properties": {
    "iso:country":"ES",
    "sg:address":"Calle de Padre Buenaventura Paredes, 10",
    "sg:city":"Oviedo",
    "sg:orig_category":"Empresarios",
    "sg:phone":"+34 985 11 71 86",
    "sg:postcode":"33001",
    "sg:province":"Asturias",
    "wof:name":"Diaz Otero Manuel Ernesto",
    "wof:placetype":"venue"
},
  "geometry": {"coordinates":[-5.8456931114,43.3677749634],"type":"Point"}
}