{
  "type": "Feature",
  "properties": {
    "addr:full":"Calle de Artistas Falleros, 4 San Vicente Del Raspeig-sant Vicent Del Raspeig Alicante 03690",
    "addr:housenumber":"4",
    "addr:postcode":"03690",
    "addr:street":"Calle De Artistas Falleros",
    "iso:country":"ES",
    "sg:address":"Calle de Artistas Falleros, 4",
    "sg:city":"San Vicente Del Raspeig-sant Vicent Del Raspeig",
    "sg:orig_category":"Cerrajer\u00cda, Ferrallista",
    "sg:phone":"+34 965 66 96 15",
    "sg:postcode":"03690",
    "sg:province":"Alicante",
    "wof:name":"Garcia Lopez Francisco Jose",
    "wof:placetype":"venue"
},
  "geometry": {"coordinates":[-0.5321105123,38.392162323],"type":"Point"}
}