{
  "type": "Feature",
  "properties": {
    "addr:full":"Calle de Benicarlo, 30 Valencia Valencia 46020",
    "addr:housenumber":"30",
    "addr:postcode":"46020",
    "addr:street":"Calle De Benicarlo",
    "iso:country":"ES",
    "sg:address":"Calle de Benicarlo, 30",
    "sg:city":"Valencia",
    "sg:orig_category":"Cajas De Ahorro",
    "sg:phone":"+34 963 62 22 92",
    "sg:postcode":"46020",
    "sg:province":"Valencia",
    "sg:website":"www.bancaja.es",
    "wof:name":"Caja De Ahorros De Valencia Castellon Y Alicante",
    "wof:placetype":"venue"
},
  "geometry": {"coordinates":[-0.3655500114,39.4868965149],"type":"Point"}
}