{
  "type": "Feature",
  "properties": {
    "addr:full":"Calle de Frigiliana, 4 Malaga M\u00e1laga 29003",
    "addr:housenumber":"4",
    "addr:postcode":"29003",
    "addr:street":"Calle De Frigiliana;Ma\u0301Laga",
    "iso:country":"ES",
    "sg:address":"Calle de Frigiliana, 4",
    "sg:city":"Malaga",
    "sg:orig_category":"Caf\u00c9s, Bares, Cervecer\u00cdas",
    "sg:phone":"+34 952 31 11 18",
    "sg:postcode":"29003",
    "sg:province":"M\u00e1laga",
    "wof:name":"Automaticos Salobre\u00f1a S.l.",
    "wof:placetype":"venue"
},
  "geometry": {"coordinates":[-4.4479174614,36.697555542],"type":"Point"}
}