{
  "type": "Feature",
  "properties": {
    "iso:country":"ES",
    "sg:address":"Calle de Adrian Nodal, 15",
    "sg:city":"Bargas",
    "sg:orig_category":"Abogados",
    "sg:phone":"+34 925 35 72 25",
    "sg:postcode":"45593",
    "sg:province":"Toledo",
    "wof:name":"Pantoja Alonso Manuel",
    "wof:placetype":"venue"
},
  "geometry": {"coordinates":[-4.018245697,39.9387397766],"type":"Point"}
}