{
  "type": "Feature",
  "properties": {
    "addr:full":"Avda Libertad De La, 28 Donostia-san Sebastian Guip\u00f9zcoa 20004",
    "addr:housenumber":"28",
    "addr:postcode":"20004",
    "addr:street":"Avda Libertad De La",
    "iso:country":"ES",
    "sg:address":"Avda Libertad De La, 28",
    "sg:city":"Donostia-san Sebastian",
    "sg:orig_category":"Ropa Para Se\u00d1oras (al Por Menor)",
    "sg:phone":"+34 943 43 00 98",
    "sg:postcode":"20004",
    "sg:province":"Guip\u00f9zcoa",
    "wof:name":"Campoy Camon Elena",
    "wof:placetype":"venue"
},
  "geometry": {"coordinates":[-1.9824409485,43.3195304871],"type":"Point"}
}