{
  "type": "Feature",
  "properties": {
    "iso:country":"ES",
    "sg:address":"Ctra. Sagunto-burgos, S/n",
    "sg:city":"S. Leonardo Yag\u00fce",
    "sg:orig_category":"Serrer\u00cdas De Madera",
    "sg:phone":"+34 975 37 63 24",
    "sg:postcode":"42140",
    "sg:province":"Soria",
    "wof:name":"Maderas De Miguel Carretero S.a.",
    "wof:placetype":"venue"
},
  "geometry": {"coordinates":[-3.0824711323,41.8351898193],"type":"Point"}
}