{
  "type": "Feature",
  "properties": {
    "addr:full":"Calle de Alcalde Garcia Asensio, 10 Malaga M\u00e1laga 29006",
    "addr:housenumber":"10",
    "addr:postcode":"29006",
    "addr:street":"Calle De Alcalde Garcia Asensio;Ma\u0301Laga",
    "iso:country":"ES",
    "sg:address":"Calle de Alcalde Garcia Asensio, 10",
    "sg:city":"Malaga",
    "sg:orig_category":"Congelados: Productos Alimentarios (al Por Menor)",
    "sg:phone":"+34 952 34 94 95",
    "sg:postcode":"29006",
    "sg:province":"M\u00e1laga",
    "wof:name":"Frigorificos A.gaspar E Hijos S.l.",
    "wof:placetype":"venue"
},
  "geometry": {"coordinates":[-4.4751825333,36.7090110779],"type":"Point"}
}