{
  "type": "Feature",
  "properties": {
    "addr:full":"Pol Ind El Portal, S/n Jerez C\u00e1diz 11408",
    "addr:housenumber":"s",
    "addr:postcode":"11408",
    "addr:street":"El Portal;/ N",
    "iso:country":"ES",
    "sg:address":"Pol Ind El Portal, S/n",
    "sg:city":"Jerez",
    "sg:orig_category":"Suministros Para Panader\u00cdas Y Pasteler\u00cdas",
    "sg:phone":"+34 956 14 52 88",
    "sg:postcode":"11408",
    "sg:province":"C\u00e1diz",
    "wof:name":"Precopan-jerez S.l.",
    "wof:placetype":"venue"
},
  "geometry": {"coordinates":[-6.1592831612,36.6686592102],"type":"Point"}
}