{
  "type": "Feature",
  "properties": {
    "addr:full":"Ctra Villalba, S/n Fuente Maestre Badajoz 06360",
    "addr:housenumber":"s",
    "addr:postcode":"06360",
    "addr:street":"Ctra Villalba;/ N Fuente Maestre",
    "iso:country":"ES",
    "sg:address":"Ctra Villalba, S/n",
    "sg:city":"Fuente Maestre",
    "sg:orig_category":"Aceites Y Grasas Alimentarias (fabricaci\u00d3n, Al Por Mayor)",
    "sg:phone":"+34 924 53 00 28",
    "sg:postcode":"06360",
    "sg:province":"Badajoz",
    "wof:name":"Aceites Obreo C.b.",
    "wof:placetype":"venue"
},
  "geometry": {"coordinates":[-6.4466986656,38.5331535339],"type":"Point"}
}