{
  "type": "Feature",
  "properties": {
    "addr:full":"Carr Mercat, S/n Sueca Valencia 46410",
    "addr:housenumber":"s / n",
    "addr:postcode":"46410",
    "addr:street":"Carr Mercat",
    "iso:country":"ES",
    "sg:address":"Carr Mercat, S/n",
    "sg:city":"Sueca",
    "sg:orig_category":"Carnicer\u00cdas, Carnicer\u00cdas",
    "sg:phone":"+34 961 70 60 45",
    "sg:postcode":"46410",
    "sg:province":"Valencia",
    "wof:name":"Sanjuan Garcia Amparo",
    "wof:placetype":"venue"
},
  "geometry": {"coordinates":[-0.3114530146,39.2019500732],"type":"Point"}
}