{
  "type": "Feature",
  "properties": {
    "addr:full":"Carrer de Pere Puig, 84 Martorell Barcelona 08760",
    "addr:housenumber":"84",
    "addr:postcode":"08760",
    "addr:street":"Carrer De Pere Puig",
    "iso:country":"ES",
    "sg:address":"Carrer de Pere Puig, 84",
    "sg:city":"Martorell",
    "sg:orig_category":"Ense\u00d1anza Variada",
    "sg:phone":"+34 937 74 29 35",
    "sg:postcode":"08760",
    "sg:province":"Barcelona",
    "wof:name":"Institucio E Balmes S.l.",
    "wof:placetype":"venue"
},
  "geometry": {"coordinates":[1.9361330271,41.4742469788],"type":"Point"}
}