{
  "type": "Feature",
  "properties": {
    "addr:full":"Carrer de Roser, 6 S. Just Desvern Barcelona 08960",
    "addr:housenumber":"6",
    "addr:postcode":"08960",
    "addr:street":"Carrer De Roser",
    "iso:country":"ES",
    "sg:address":"Carrer de Roser, 6",
    "sg:city":"S. Just Desvern",
    "sg:orig_category":"Arquitectos",
    "sg:phone":"+34 933 72 92 08",
    "sg:postcode":"08960",
    "sg:province":"Barcelona",
    "wof:name":"Arquitectura Tallon Y Asociados S.l",
    "wof:placetype":"venue"
},
  "geometry": {"coordinates":[2.0730297565,41.3911323547],"type":"Point"}
}