{
  "type": "Feature",
  "properties": {
    "addr:full":"Calle de Millares, 3 Valencia Valencia 46007",
    "addr:housenumber":"3",
    "addr:postcode":"46007",
    "addr:street":"Calle De Millares",
    "iso:country":"ES",
    "sg:address":"Calle de Millares, 3",
    "sg:city":"Valencia",
    "sg:orig_category":"Empresas De Vigilancia, Guardia Y Protecci\u00d3n",
    "sg:phone":"+34 963 41 13 70",
    "sg:postcode":"46007",
    "sg:province":"Valencia",
    "wof:name":"Seguriber S. A.",
    "wof:placetype":"venue"
},
  "geometry": {"coordinates":[-0.3832609951,39.4563407898],"type":"Point"}
}