{
  "type": "Feature",
  "properties": {
    "addr:full":"Bibilis, S/n S. Andres Rabanedo Le\u00f3n 24010",
    "addr:postcode":"24010",
    "addr:street":"Bibilis S / N S. Andres Rabanedo Leo\u0301N",
    "iso:country":"ES",
    "sg:address":"Bibilis, S/n",
    "sg:city":"S. Andres Rabanedo",
    "sg:orig_category":"\u00d3ptica: Instrumentos (fabricaci\u00d3n)",
    "sg:phone":"+34 987 22 73 50",
    "sg:postcode":"24010",
    "sg:province":"Le\u00f3n",
    "sg:website":"www.visionlab.com",
    "wof:name":"Visionlab",
    "wof:placetype":"venue"
},
  "geometry": {"coordinates":[-5.5717520714,42.5998764038],"type":"Point"}
}