{
  "type": "Feature",
  "properties": {
    "iso:country":"ES",
    "sg:address":"Carr Bisbe Messeguer, 1",
    "sg:city":"Lleida",
    "sg:orig_category":"Librer\u00cdas",
    "sg:phone":"+34 973 26 78 02",
    "sg:postcode":"25003",
    "sg:province":"Lleida",
    "wof:name":"Navascues Soteras Caridad",
    "wof:placetype":"venue"
},
  "geometry": {"coordinates":[0.6196150184,41.6141242981],"type":"Point"}
}