{
  "type": "Feature",
  "properties": {
    "addr:full":"Calle de Monares, 16 Mores Zaragoza 50240",
    "addr:housenumber":"16",
    "addr:postcode":"50240",
    "addr:street":"Calle De Monares",
    "iso:country":"ES",
    "sg:address":"Calle de Monares, 16",
    "sg:city":"Mores",
    "sg:orig_category":"Transportes Por Carretera: Lotes Completos, Mercanc\u00cdas Diversas",
    "sg:phone":"+34 976 82 62 30",
    "sg:postcode":"50240",
    "sg:province":"Zaragoza",
    "wof:name":"Cadenas Yarza S.cv.",
    "wof:placetype":"venue"
},
  "geometry": {"coordinates":[-1.5658479929,41.4727668762],"type":"Point"}
}