{
  "type": "Feature",
  "properties": {
    "addr:full":"C/ Vicent Andres Estelles, 28 Elche Alicante 03202",
    "addr:housenumber":"28",
    "addr:postcode":"03202",
    "addr:street":"C / Vicent Andres Estelles",
    "iso:country":"ES",
    "sg:address":"C/ Vicent Andres Estelles, 28",
    "sg:city":"Elche",
    "sg:orig_category":"Instalaci\u00d3n, Reparaci\u00d3n De Ascensores Y Montacargas",
    "sg:phone":"+34 966 61 01 02",
    "sg:postcode":"03202",
    "sg:province":"Alicante",
    "wof:name":"Ascensores Philbert S.l.",
    "wof:placetype":"venue"
},
  "geometry": {"coordinates":[-0.6805126071,38.2724533081],"type":"Point"}
}