{
  "type": "Feature",
  "properties": {
    "iso:country":"ES",
    "sg:address":"Calle de Fernando De Rojas, 18",
    "sg:city":"Salamanca",
    "sg:orig_category":"Triper\u00cdas",
    "sg:phone":"+34 923 22 31 29",
    "sg:postcode":"37005",
    "sg:province":"Salamanca",
    "wof:name":"Garcia Garcia Pedro Antonio",
    "wof:placetype":"venue"
},
  "geometry": {"coordinates":[-5.6604552269,40.9732933044],"type":"Point"}
}