{
  "type": "Feature",
  "properties": {
    "addr:full":"Carrer de Gaiter Del Llobregat (lo), 74 Prat Llobregat Barcelona 08820",
    "addr:housenumber":"74",
    "addr:postcode":"08820",
    "addr:street":"Carrer De Gaiter Del Llobregat Lo;Llobregat",
    "iso:country":"ES",
    "sg:address":"Carrer de Gaiter Del Llobregat (lo), 74",
    "sg:city":"Prat Llobregat",
    "sg:orig_category":"Suministros Para Hoteles",
    "sg:phone":"+34 934 78 41 98",
    "sg:postcode":"08820",
    "sg:province":"Barcelona",
    "wof:name":"Sarda I Abello S.l.",
    "wof:placetype":"venue"
},
  "geometry": {"coordinates":[2.0972280502,41.3289985657],"type":"Point"}
}