{
  "type": "Feature",
  "properties": {
    "iso:country":"ES",
    "sg:address":"Calle de Granados, 1",
    "sg:city":"Malaga",
    "sg:orig_category":"Calzados Ortop\u00c9dicos",
    "sg:phone":"+34 952 21 10 66",
    "sg:postcode":"29008",
    "sg:province":"M\u00e1laga",
    "wof:name":"Baeza Rico Jose",
    "wof:placetype":"venue"
},
  "geometry": {"coordinates":[-4.4201002121,36.7225227356],"type":"Point"}
}