{
  "type": "Feature",
  "properties": {
    "iso:country":"ES",
    "sg:address":"Calle de Hernan Cortes, 82",
    "sg:city":"Villanueva Serena",
    "sg:orig_category":"Peluquer\u00cdas, Peluquer\u00cda Mixta",
    "sg:phone":"+34 924 84 61 90",
    "sg:postcode":"06700",
    "sg:province":"Badajoz",
    "wof:name":"Martinez Navarro Damian",
    "wof:placetype":"venue"
},
  "geometry": {"coordinates":[-5.7930231094,38.9741897583],"type":"Point"}
}