{
  "type": "Feature",
  "properties": {
    "addr:full":"Peneiro, 16 Lians La Coru\u00f1a 15179",
    "addr:housenumber":"16",
    "addr:postcode":"15179",
    "addr:street":"Peneiro;Lians La Corun\u0303A",
    "iso:country":"ES",
    "sg:address":"Peneiro, 16",
    "sg:city":"Lians",
    "sg:orig_category":"Supermercados Y Hipermercados",
    "sg:phone":"+34 981 62 66 99",
    "sg:postcode":"15179",
    "sg:province":"La Coru\u00f1a",
    "wof:name":"Sanchez Arevalo Luis",
    "wof:placetype":"venue"
},
  "geometry": {"coordinates":[-8.3459596634,43.3464698792],"type":"Point"}
}