{
  "type": "Feature",
  "properties": {
    "addr:full":"Plaz Major, 6 Meliana Valencia 46133",
    "addr:housenumber":"6",
    "addr:postcode":"46133",
    "addr:street":"Plaz Major",
    "iso:country":"ES",
    "sg:address":"Plaz Major, 6",
    "sg:city":"Meliana",
    "sg:orig_category":"Panader\u00cdas, Panader\u00cdas",
    "sg:phone":"+34 961 49 18 83",
    "sg:postcode":"46133",
    "sg:province":"Valencia",
    "wof:name":"Gil Nicolau Vicente",
    "wof:placetype":"venue"
},
  "geometry": {"coordinates":[-0.3489159942,39.5272407532],"type":"Point"}
}