{
  "type": "Feature",
  "properties": {
    "iso:country":"ES",
    "sg:address":"Avda Vi\u00d1as, 2",
    "sg:city":"Villaviciosa Odon",
    "sg:orig_category":"Restaurantes",
    "sg:phone":"+34 916 16 10 91",
    "sg:postcode":"28670",
    "sg:province":"Madrid",
    "wof:name":"Abrisketa Martinez Amelia",
    "wof:placetype":"venue"
},
  "geometry": {"coordinates":[-3.894188,40.357258],"type":"Point"}
}