{
  "type": "Feature",
  "properties": {
    "iso:country":"ES",
    "sg:address":"Calle de Logro\u00d1o, 22",
    "sg:city":"Vitoria-gasteiz",
    "sg:orig_category":"Estancos",
    "sg:phone":"+34 945 27 23 99",
    "sg:postcode":"01002",
    "sg:province":"\u00c1lava",
    "wof:name":"Arrese Lopez De Alda Ricardo",
    "wof:placetype":"venue"
},
  "geometry": {"coordinates":[-2.6641981602,42.8493919373],"type":"Point"}
}