{
  "type": "Feature",
  "properties": {
    "iso:country":"ES",
    "sg:address":"Ctra. Lutxana A., 13",
    "sg:city":"Erandio-goikoa",
    "sg:orig_category":"Aluminio Y Aleaciones (producci\u00d3n, Transformaci\u00d3n, Negocio)",
    "sg:phone":"+34 944 53 02 00",
    "sg:postcode":"48950",
    "sg:province":"Vizcaya",
    "sg:website":"www.remetal.com",
    "wof:name":"Telvent Outsuorcing S.a,",
    "wof:placetype":"venue"
},
  "geometry": {"coordinates":[-2.9544599056,43.3035202026],"type":"Point"}
}