{
  "type": "Feature",
  "properties": {
    "iso:country":"ES",
    "sg:address":"Carrer de Pau Claris, 190",
    "sg:city":"Barcelona",
    "sg:orig_category":"Florister\u00cdas",
    "sg:phone":"+34 934 87 12 19",
    "sg:postcode":"08037",
    "sg:province":"Barcelona",
    "wof:name":"Lloveras Barcelo Enrique",
    "wof:placetype":"venue"
},
  "geometry": {"coordinates":[2.1621170044,41.3967056274],"type":"Point"}
}