{
  "type": "Feature",
  "properties": {
    "iso:country":"ES",
    "sg:address":"Avda Rosalia De Castro, 2",
    "sg:city":"Santa Uxia De Ribeira",
    "sg:orig_category":"Bisuter\u00cda, Joyer\u00cda, Relojer\u00cda (al Por Menor)",
    "sg:phone":"+34 981 87 35 59",
    "sg:postcode":"15960",
    "sg:province":"La Coru\u00f1a",
    "wof:name":"Nespereira Prada Jose Antonio",
    "wof:placetype":"venue"
},
  "geometry": {"coordinates":[-8.990811348,42.5552635193],"type":"Point"}
}