{
  "type": "Feature",
  "properties": {
    "addr:full":"Carrer de Cop, 13 Denia Alicante 03700",
    "addr:housenumber":"13",
    "addr:postcode":"03700",
    "addr:street":"Carrer De Cop",
    "iso:country":"ES",
    "sg:address":"Carrer de Cop, 13",
    "sg:city":"Denia",
    "sg:orig_category":"Perfumer\u00cda (al Por Menor)",
    "sg:phone":"+34 965 78 06 49",
    "sg:postcode":"03700",
    "sg:province":"Alicante",
    "wof:name":"Ruzafa Salort Maria Jesus",
    "wof:placetype":"venue"
},
  "geometry": {"coordinates":[0.1067439988,38.8403205872],"type":"Point"}
}