{
  "type": "Feature",
  "properties": {
    "iso:country":"ES",
    "sg:address":"Carrer de Riu Llobregat, S/n",
    "sg:city":"Prat Llobregat",
    "sg:orig_category":"Supermercados Y Hipermercados",
    "sg:phone":"+34 933 70 80 10",
    "sg:postcode":"08820",
    "sg:province":"Barcelona",
    "wof:name":"Antonio Hernandez Garcia S.l.",
    "wof:placetype":"venue"
},
  "geometry": {"coordinates":[1.9888701439,41.779335022],"type":"Point"}
}