{
  "type": "Feature",
  "properties": {
    "iso:country":"ES",
    "sg:address":"Carrer de Uetam, 15",
    "sg:city":"Palma",
    "sg:orig_category":"Agencias Y Agentes Comerciales, Representantes",
    "sg:phone":"+34 971 46 65 35",
    "sg:postcode":"07006",
    "sg:province":"Islas Baleares",
    "wof:name":"Rubi Nicolau Juan",
    "wof:placetype":"venue"
},
  "geometry": {"coordinates":[2.6592159271,39.5746917725],"type":"Point"}
}