{
  "type": "Feature",
  "properties": {
    "iso:country":"ES",
    "sg:address":"Rua Villar, 6",
    "sg:city":"Ourense",
    "sg:orig_category":"Molduras, Junquillos, Listones Y Molduras Perforadas",
    "sg:phone":"+34 988 22 19 18",
    "sg:postcode":"32005",
    "sg:province":"Ourense",
    "wof:name":"Dominguez Gonzalez Edelmiro",
    "wof:placetype":"venue"
},
  "geometry": {"coordinates":[-7.864276886,42.3342475891],"type":"Point"}
}