{
  "type": "Feature",
  "properties": {
    "addr:full":"Carrer de Monegal, 2 Barcelona Barcelona 08023",
    "addr:housenumber":"2",
    "addr:postcode":"08023",
    "addr:street":"Carrer De Monegal",
    "iso:country":"ES",
    "sg:address":"Carrer de Monegal, 2",
    "sg:city":"Barcelona",
    "sg:orig_category":"Arquitectos",
    "sg:phone":"+34 932 12 63 03",
    "sg:postcode":"08023",
    "sg:province":"Barcelona",
    "wof:name":"Gaspar Farreras Pedro",
    "wof:placetype":"venue"
},
  "geometry": {"coordinates":[2.14366889,41.4067459106],"type":"Point"}
}