{
  "type": "Feature",
  "properties": {
    "iso:country":"ES",
    "sg:address":"Carrer de Coll I Vehi, 51",
    "sg:city":"Barcelona",
    "sg:orig_category":"Cojinetes De Bolas, Agujas Y Rodillos (fabricaci\u00d3n, Al Por Mayor)",
    "sg:phone":"+34 934 56 00 98",
    "sg:postcode":"08026",
    "sg:province":"Barcelona",
    "wof:name":"Rodelem Europe S.l.",
    "wof:placetype":"venue"
},
  "geometry": {"coordinates":[2.1824541092,41.413444519],"type":"Point"}
}