{
  "type": "Feature",
  "properties": {
    "iso:country":"ES",
    "sg:address":"Calle de Nueva, 24",
    "sg:city":"Torrelodones",
    "sg:orig_category":"Contables",
    "sg:phone":"+34 918 59 64 06",
    "sg:postcode":"28250",
    "sg:province":"Madrid",
    "sg:website":"www.mr-consultores.com",
    "wof:name":"Mejias Ruiz Consultores S.l.",
    "wof:placetype":"venue"
},
  "geometry": {"coordinates":[-3.9314756393,40.5810966492],"type":"Point"}
}