{
  "type": "Feature",
  "properties": {
    "addr:full":"Avgd De Daniel Gil, 19 Ontinyent Valencia 46870",
    "addr:housenumber":"19",
    "addr:postcode":"46870",
    "addr:street":"Gil",
    "iso:country":"ES",
    "sg:address":"Avgd De Daniel Gil, 19",
    "sg:city":"Ontinyent",
    "sg:orig_category":"Estilistas Y Estudios De Estilo De Corte Y Confecci\u00d3n",
    "sg:phone":"+34 962 91 43 99",
    "sg:postcode":"46870",
    "sg:province":"Valencia",
    "wof:name":"Valls Guillem Jose Ramon",
    "wof:placetype":"venue"
},
  "geometry": {"coordinates":[-0.6025210023,38.8247413635],"type":"Point"}
}