{
  "type": "Feature",
  "properties": {
    "iso:country":"ES",
    "sg:address":"Carr Tarragona, 9",
    "sg:city":"Figueres",
    "sg:orig_category":"Frutas, Legumbres Frescas Y Tempranas (al Por Menor)",
    "sg:phone":"+34 972 50 42 55",
    "sg:postcode":"17600",
    "sg:province":"Girona",
    "wof:name":"Hurtos Gifreu Marti",
    "wof:placetype":"venue"
},
  "geometry": {"coordinates":[2.9564790726,42.2616653442],"type":"Point"}
}