{
  "type": "Feature",
  "properties": {
    "addr:full":"Carr Bisbe Irurita, 21 Lleida Lleida 25006",
    "addr:housenumber":"21",
    "addr:postcode":"25006",
    "addr:street":"Carr Bisbe Irurita",
    "iso:country":"ES",
    "sg:address":"Carr Bisbe Irurita, 21",
    "sg:city":"Lleida",
    "sg:orig_category":"Alumbrados",
    "sg:phone":"+34 973 28 17 38",
    "sg:postcode":"25006",
    "sg:province":"Lleida",
    "wof:name":"Lleida Illuminacio S.l.",
    "wof:placetype":"venue"
},
  "geometry": {"coordinates":[0.6126840115,41.616355896],"type":"Point"}
}