{
  "type": "Feature",
  "properties": {
    "iso:country":"ES",
    "sg:address":"Calle de Carmen, 2",
    "sg:city":"Burgos",
    "sg:orig_category":"Molduras, Junquillos, Listones Y Molduras Perforadas",
    "sg:phone":"+34 947 20 70 89",
    "sg:postcode":"09001",
    "sg:province":"Burgos",
    "wof:name":"Lopez Lopez Fernando Y Otros Cb.",
    "wof:placetype":"venue"
},
  "geometry": {"coordinates":[-3.7053260803,42.3368263245],"type":"Point"}
}