{
  "type": "Feature",
  "properties": {
    "addr:full":"Carrer de Vinaros, 36 Hospitalet Llobregat Barcelona 08906",
    "addr:housenumber":"36",
    "addr:postcode":"08906",
    "addr:street":"Carrer De Vinaros",
    "iso:country":"ES",
    "sg:address":"Carrer de Vinaros, 36",
    "sg:city":"Hospitalet Llobregat",
    "sg:orig_category":"Bisuter\u00cda, Joyer\u00cda, Relojer\u00cda (al Por Menor)",
    "sg:phone":"+34 934 38 21 37",
    "sg:postcode":"08906",
    "sg:province":"Barcelona",
    "wof:name":"Gutierrez Gonzalez Maria Dolores",
    "wof:placetype":"venue"
},
  "geometry": {"coordinates":[2.1020300388,41.3728179932],"type":"Point"}
}