{
  "type": "Feature",
  "properties": {
    "addr:full":"Av Verge De Montserrat, 59 Barbera Valles Barcelona 08210",
    "addr:housenumber":"59",
    "addr:postcode":"08210",
    "addr:street":"Av Verge De Montserrat",
    "iso:country":"ES",
    "sg:address":"Av Verge De Montserrat, 59",
    "sg:city":"Barbera Valles",
    "sg:orig_category":"Herboristas (al Por Menor)",
    "sg:phone":"+34 937 18 18 48",
    "sg:postcode":"08210",
    "sg:province":"Barcelona",
    "sg:website":"www.detotapreuteu.com",
    "wof:name":"Mercedes Flores Flores",
    "wof:placetype":"venue"
},
  "geometry": {"coordinates":[2.123169899,41.5141448975],"type":"Point"}
}