{
  "type": "Feature",
  "properties": {
    "iso:country":"ES",
    "sg:address":"Carrer de Pare Llaurador, 113",
    "sg:city":"Terrassa",
    "sg:orig_category":"Agencias Y Agentes Comerciales, Representantes",
    "sg:phone":"+34 937 89 47 63",
    "sg:postcode":"08224",
    "sg:province":"Barcelona",
    "wof:name":"Xics S.l.",
    "wof:placetype":"venue"
},
  "geometry": {"coordinates":[2.0039722919,41.5640563965],"type":"Point"}
}