{
  "type": "Feature",
  "properties": {
    "addr:full":"Cmno Solana, S/n Villamediana Iregua La Rioja 26142",
    "addr:housenumber":"s / n",
    "addr:postcode":"26142",
    "addr:street":"Cmno Solana;Villamediana Iregua;Rioja",
    "iso:country":"ES",
    "sg:address":"Cmno Solana, S/n",
    "sg:city":"Villamediana Iregua",
    "sg:orig_category":"Empresas De Carpinter\u00cda Met\u00c1lica",
    "sg:phone":"+34 941 43 54 75",
    "sg:postcode":"26142",
    "sg:province":"La Rioja",
    "wof:name":"Metalisteria Bear S.l.",
    "wof:placetype":"venue"
},
  "geometry": {"coordinates":[-2.417953968,42.4283485413],"type":"Point"}
}