{
  "type": "Feature",
  "properties": {
    "addr:full":"Ctra Madrid-coru\u00d1a, 43 Astorga Le\u00f3n 24700",
    "addr:housenumber":"43",
    "addr:postcode":"24700",
    "addr:street":"Ctra Madrid-Corun\u0303A;Leo\u0301N",
    "iso:country":"ES",
    "sg:address":"Ctra Madrid-coru\u00d1a, 43",
    "sg:city":"Astorga",
    "sg:orig_category":"Fabricaci\u00d3n Y Refinado De Az\u00dacares",
    "sg:phone":"+34 987 61 58 51",
    "sg:postcode":"24700",
    "sg:province":"Le\u00f3n",
    "wof:name":"Herminio Menda\u00f1a S.l.",
    "wof:placetype":"venue"
},
  "geometry": {"coordinates":[-6.0637350082,42.4592437744],"type":"Point"}
}