{
  "type": "Feature",
  "properties": {
    "iso:country":"ES",
    "sg:address":"Calle de Ebanistas (los), 5",
    "sg:city":"Alcorcon",
    "sg:orig_category":"Transportes Por Carretera: Lotes Completos, Mercanc\u00cdas Diversas",
    "sg:phone":"+34 916 43 16 04",
    "sg:postcode":"28925",
    "sg:province":"Madrid",
    "wof:name":"Sunny Opticas S.l.",
    "wof:placetype":"venue"
},
  "geometry": {"coordinates":[-3.8049871922,40.3421669006],"type":"Point"}
}