{
  "type": "Feature",
  "properties": {
    "addr:full":"Carr Cervantes, 13 Betera Valencia 46117",
    "addr:housenumber":"13",
    "addr:postcode":"46117",
    "addr:street":"Carr Cervantes",
    "iso:country":"ES",
    "sg:address":"Carr Cervantes, 13",
    "sg:city":"Betera",
    "sg:orig_category":"Mec\u00c1nico Del Autom\u00d3vil",
    "sg:phone":"+34 961 60 18 84",
    "sg:postcode":"46117",
    "sg:province":"Valencia",
    "wof:name":"Talleres Cari\u00f1ena S.l.",
    "wof:placetype":"venue"
},
  "geometry": {"coordinates":[-0.4591119885,39.5936660767],"type":"Point"}
}