{
  "type": "Feature",
  "properties": {
    "addr:full":"Avda Perez Galdos, 10 Logro\u00f1o La Rioja 26002",
    "addr:housenumber":"10",
    "addr:postcode":"26002",
    "addr:street":"Avda Perez Galdos;Rioja",
    "iso:country":"ES",
    "sg:address":"Avda Perez Galdos, 10",
    "sg:city":"Logro\u00f1o",
    "sg:orig_category":"M\u00c9dicos: Dermatolog\u00cda Y Venereolog\u00cda",
    "sg:phone":"+34 941 24 78 53",
    "sg:postcode":"26002",
    "sg:province":"La Rioja",
    "wof:name":"Cura Ortiz Eustorgio Del",
    "wof:placetype":"venue"
},
  "geometry": {"coordinates":[-2.4473071098,42.4612388611],"type":"Point"}
}