{
  "type": "Feature",
  "properties": {
    "iso:country":"ES",
    "sg:address":"Avda Aguirre Lehendakari, 75",
    "sg:city":"Bilbao",
    "sg:orig_category":"Comunidades Religiosas",
    "sg:phone":"+34 944 75 01 98",
    "sg:postcode":"48014",
    "sg:province":"Vizcaya",
    "wof:name":"Inspectoria Salesiana De San Francisco Javier",
    "wof:placetype":"venue"
},
  "geometry": {"coordinates":[-2.9507389069,43.2720489502],"type":"Point"}
}