{
  "type": "Feature",
  "properties": {
    "iso:country":"ES",
    "sg:address":"Calle de Real, 14",
    "sg:city":"S. Fernando",
    "sg:orig_category":"Farmacias",
    "sg:phone":"+34 956 88 32 95",
    "sg:postcode":"11100",
    "sg:province":"C\u00e1diz",
    "wof:name":"Guerra Castro Juan Ramon",
    "wof:placetype":"venue"
},
  "geometry": {"coordinates":[-6.1918511391,36.467754364],"type":"Point"}
}