{
  "type": "Feature",
  "properties": {
    "addr:full":"Cami Tarrera, 2 Vallbona D'anoia Barcelona 08785",
    "addr:housenumber":"2",
    "addr:postcode":"08785",
    "addr:street":"Tarrera",
    "iso:country":"ES",
    "sg:address":"Cami Tarrera, 2",
    "sg:city":"Vallbona D'anoia",
    "sg:orig_category":"Cajas Para Embalar",
    "sg:phone":"+34 937 71 80 05",
    "sg:postcode":"08785",
    "sg:province":"Barcelona",
    "wof:name":"Fermsa S.a.",
    "wof:placetype":"venue"
},
  "geometry": {"coordinates":[1.7105449438,41.5194778442],"type":"Point"}
}