{
  "type": "Feature",
  "properties": {
    "iso:country":"ES",
    "sg:address":"Carrer de Miquel Sant Oliver, 9",
    "sg:city":"Palmanova",
    "sg:orig_category":"Electrodom\u00c9sticos (al Por Menor)",
    "sg:phone":"+34 971 68 18 71",
    "sg:postcode":"07181",
    "sg:province":"Islas Baleares",
    "wof:name":"Socias Serra Rafael",
    "wof:placetype":"venue"
},
  "geometry": {"coordinates":[2.5371239185,39.5258560181],"type":"Point"}
}