{
  "type": "Feature",
  "properties": {
    "addr:full":"Pl Josep Barange, S/n Granollers Barcelona 08402",
    "addr:postcode":"08402",
    "addr:street":"Pl;Barange S / N",
    "iso:country":"ES",
    "sg:address":"Pl Josep Barange, S/n",
    "sg:city":"Granollers",
    "sg:orig_category":"Aparcamientos (infraestructuras, Accesorios)",
    "sg:phone":"+34 938 70 91 50",
    "sg:postcode":"08402",
    "sg:province":"Barcelona",
    "wof:name":"Petrobages S.l.",
    "wof:placetype":"venue"
},
  "geometry": {"coordinates":[2.2902100086,41.6082382202],"type":"Point"}
}