{
  "type": "Feature",
  "properties": {
    "addr:full":"Calle de Jose Lopez Prudencio, 10 Badajoz Badajoz 06002",
    "addr:housenumber":"10",
    "addr:postcode":"06002",
    "addr:street":"Calle De Jose Lopez Prudencio",
    "iso:country":"ES",
    "sg:address":"Calle de Jose Lopez Prudencio, 10",
    "sg:city":"Badajoz",
    "sg:orig_category":"Hormig\u00d3n Listo Para Usar",
    "sg:phone":"+34 924 25 69 02",
    "sg:postcode":"06002",
    "sg:province":"Badajoz",
    "wof:name":"Gonzalez Ambel Francisco Javier",
    "wof:placetype":"venue"
},
  "geometry": {"coordinates":[-6.9680137634,38.8781776428],"type":"Point"}
}