{
  "type": "Feature",
  "properties": {
    "iso:country":"ES",
    "sg:address":"Calle de Guadix, S/n",
    "sg:city":"Martos",
    "sg:orig_category":"Instalaci\u00d3n, Reparaci\u00d3n De Ascensores Y Montacargas",
    "sg:phone":"+34 953 55 48 64",
    "sg:postcode":"23600",
    "sg:province":"Ja\u00e9n",
    "wof:name":"Ascensores Embarba S.a.",
    "wof:placetype":"venue"
},
  "geometry": {"coordinates":[-3.9697301388,37.71509552],"type":"Point"}
}