{
  "type": "Feature",
  "properties": {
    "iso:country":"ES",
    "sg:address":"Calle de Dresde, 6",
    "sg:city":"Madrid",
    "sg:orig_category":"Alumbrados",
    "sg:phone":"+34 917 60 12 47",
    "sg:postcode":"28032",
    "sg:province":"Madrid",
    "sg:website":"www.hogarlux.es",
    "wof:name":"Hogarlux S.l.",
    "wof:placetype":"venue"
},
  "geometry": {"coordinates":[-3.6117064953,40.4213752747],"type":"Point"}
}