{
  "type": "Feature",
  "properties": {
    "addr:full":"Avda Rubians, 22 Barbeitos Pontevedra 36619",
    "addr:housenumber":"22",
    "addr:postcode":"36619",
    "addr:street":"Avda Rubians",
    "iso:country":"ES",
    "sg:address":"Avda Rubians, 22",
    "sg:city":"Barbeitos",
    "sg:orig_category":"Alimentaci\u00d3n General (al Por Menor)",
    "sg:phone":"+34 986 51 23 33",
    "sg:postcode":"36619",
    "sg:province":"Pontevedra",
    "wof:name":"Distribuciones Lorri C.b.",
    "wof:placetype":"venue"
},
  "geometry": {"coordinates":[-8.7645044327,42.5797958374],"type":"Point"}
}