{
  "type": "Feature",
  "properties": {
    "iso:country":"ES",
    "sg:address":"Calle de Quart, 97",
    "sg:city":"Valencia",
    "sg:orig_category":"Iglesia Cat\u00d3lica",
    "sg:phone":"+34 963 91 92 98",
    "sg:postcode":"46008",
    "sg:province":"Valencia",
    "wof:name":"Parroquia De San Miguel Y San Sebastian",
    "wof:placetype":"venue"
},
  "geometry": {"coordinates":[-0.386916697,39.4752388],"type":"Point"}
}