{
  "type": "Feature",
  "properties": {
    "iso:country":"ES",
    "sg:address":"Pase Arroyomolinos (de), 44",
    "sg:city":"Mostoles",
    "sg:orig_category":"Centros De Educaci\u00d3n Especial",
    "sg:phone":"+34 916 46 93 55",
    "sg:postcode":"28938",
    "sg:province":"Madrid",
    "wof:name":"Colegio Publico Benito Perez Galdos",
    "wof:placetype":"venue"
},
  "geometry": {"coordinates":[-3.8882100582,40.2945251465],"type":"Point"}
}