{
  "type": "Feature",
  "properties": {
    "addr:full":"Calle de Ramon Y Cajal, 37 Villarta S. Juan Ciudad Real 13210",
    "addr:housenumber":"37",
    "addr:postcode":"13210",
    "addr:street":"Calle De Ramon Y Cajal;S. Juan Ciudad Real",
    "iso:country":"ES",
    "sg:address":"Calle de Ramon Y Cajal, 37",
    "sg:city":"Villarta S. Juan",
    "sg:orig_category":"Negocio De Materiales De Construcci\u00d3n",
    "sg:phone":"+34 926 64 04 08",
    "sg:postcode":"13210",
    "sg:province":"Ciudad Real",
    "wof:name":"Tabasco Rodriguez Angel Jose",
    "wof:placetype":"venue"
},
  "geometry": {"coordinates":[-3.419675827,39.236038208],"type":"Point"}
}