{
  "type": "Feature",
  "properties": {
    "addr:full":"Calle de Segovia (de), 13 Humanes De Madrid Madrid 28970",
    "addr:housenumber":"13",
    "addr:postcode":"28970",
    "addr:street":"Calle De Segovia De",
    "iso:country":"ES",
    "sg:address":"Calle de Segovia (de), 13",
    "sg:city":"Humanes De Madrid",
    "sg:orig_category":"Empresas De Carpinter\u00cda De Madera",
    "sg:phone":"+34 916 06 57 75",
    "sg:postcode":"28970",
    "sg:province":"Madrid",
    "wof:name":"Modereba S.l.",
    "wof:placetype":"venue"
},
  "geometry": {"coordinates":[-3.820966959,40.272644043],"type":"Point"}
}