{
  "type": "Feature",
  "properties": {
    "iso:country":"ES",
    "sg:address":"Plaz Jose Iturbi, 3",
    "sg:city":"Burriana",
    "sg:orig_category":"Inmobiliaria (agencias)",
    "sg:phone":"+34 964 57 08 62",
    "sg:postcode":"12530",
    "sg:province":"Castell\u00f3n",
    "wof:name":"Amparo Folch S L",
    "wof:placetype":"venue"
},
  "geometry": {"coordinates":[-0.0840215012,39.8887367249],"type":"Point"}
}