{
  "type": "Feature",
  "properties": {
    "iso:country":"ES",
    "sg:address":"Ctra De Ubeda, S/n",
    "sg:city":"La Yuca",
    "sg:orig_category":"Muebles Y Accesorios Para Cocinas Y Cuartos De Ba\u00d1o (al Por Menor)",
    "sg:phone":"+34 953 32 22 49",
    "sg:postcode":"23001",
    "sg:province":"Ja\u00e9n",
    "wof:name":"Amate Gutierrez Jose",
    "wof:placetype":"venue"
},
  "geometry": {"coordinates":[-3.7895176411,37.7657394409],"type":"Point"}
}