{
  "type": "Feature",
  "properties": {
    "iso:country":"ES",
    "sg:address":"Carrer de Josep Anselm Clave, 12",
    "sg:city":"Hospitalet Llobregat",
    "sg:orig_category":"Albergues",
    "sg:phone":"+34 933 32 19 79",
    "sg:postcode":"08902",
    "sg:province":"Barcelona",
    "wof:name":"Eduvic S.c.c.l.",
    "wof:placetype":"venue"
},
  "geometry": {"coordinates":[2.1262409687,41.3665504456],"type":"Point"}
}