{
  "type": "Feature",
  "properties": {
    "addr:full":"Ctra Bajada De Las Guayarminas, 118 Galdar Las Palmas 35460",
    "addr:housenumber":"118",
    "addr:postcode":"35460",
    "addr:street":"Ctra Bajada De Las Guayarminas",
    "iso:country":"ES",
    "sg:address":"Ctra Bajada De Las Guayarminas, 118",
    "sg:city":"Galdar",
    "sg:orig_category":"Mec\u00c1nico Del Autom\u00d3vil",
    "sg:phone":"+34 928 88 01 41",
    "sg:postcode":"35460",
    "sg:province":"Las Palmas",
    "wof:name":"Falcon Castellano Manuel",
    "wof:placetype":"venue"
},
  "geometry": {"coordinates":[-15.6528720856,28.1450138092],"type":"Point"}
}