{
  "type": "Feature",
  "properties": {
    "addr:full":"Carrer de Sardana, 2 S. Andreu Barca Barcelona 08740",
    "addr:housenumber":"2",
    "addr:postcode":"08740",
    "addr:street":"Carrer De Sardana;S. Andreu;Barcelona",
    "iso:country":"ES",
    "sg:address":"Carrer de Sardana, 2",
    "sg:city":"S. Andreu Barca",
    "sg:orig_category":"Material Y Suministros Para Imprenta E Industrias Gr\u00c1ficas",
    "sg:phone":"+34 936 82 44 40",
    "sg:postcode":"08740",
    "sg:province":"Barcelona",
    "wof:name":"Tegsa S.l.",
    "wof:placetype":"venue"
},
  "geometry": {"coordinates":[1.9763909578,41.4458770752],"type":"Point"}
}