{
  "type": "Feature",
  "properties": {
    "iso:country":"ES",
    "sg:address":"Plaz San Antonio, 4",
    "sg:city":"Santo\u00f1a",
    "sg:orig_category":"Cajas De Ahorro",
    "sg:phone":"+34 942 62 85 32",
    "sg:postcode":"39740",
    "sg:province":"Cantabria",
    "sg:website":"www.bbk.es",
    "wof:name":"Bilbao Bizkaia Kutxa",
    "wof:placetype":"venue"
},
  "geometry": {"coordinates":[-3.4559640884,43.4430236816],"type":"Point"}
}