{
  "type": "Feature",
  "properties": {
    "addr:full":"Via Sergia, 33 Mataro Barcelona 08302",
    "addr:housenumber":"33",
    "addr:postcode":"08302",
    "addr:street":"Via Sergia",
    "iso:country":"ES",
    "sg:address":"Via Sergia, 33",
    "sg:city":"Mataro",
    "sg:orig_category":"Agentes, Concesionarios Y Sucursales De Veh\u00cdculos",
    "sg:phone":"+34 937 41 12 63",
    "sg:postcode":"08302",
    "sg:province":"Barcelona",
    "sg:website":"www.alviautos.com",
    "wof:name":"Alviautos Vilella S.l.",
    "wof:placetype":"venue"
},
  "geometry": {"coordinates":[2.4248344898,41.5290565491],"type":"Point"}
}