{
  "type": "Feature",
  "properties": {
    "addr:full":"Ctra. Madrid-coru\u00f1a, Km. 0268,0 Benavente Zamora 49600",
    "addr:postcode":"49600",
    "addr:street":"Ctra. Madrid-Corun\u0303A Km. 0268,0",
    "iso:country":"ES",
    "sg:address":"Ctra. Madrid-coru\u00f1a, Km. 0268,0",
    "sg:city":"Benavente",
    "sg:orig_category":"Hoteles",
    "sg:phone":"+34 980 63 64 66",
    "sg:postcode":"49600",
    "sg:province":"Zamora",
    "wof:name":"Don Zoilo S.a.",
    "wof:placetype":"venue"
},
  "geometry": {"coordinates":[-5.677795887,42.0033531189],"type":"Point"}
}