{
  "type": "Feature",
  "properties": {
    "addr:full":"Calle de Pelayo, 39 Palmas De Gran Canaria Las Palmas 35010",
    "addr:postcode":"35010",
    "addr:street":"Calle De Pelayo",
    "iso:country":"ES",
    "sg:address":"Calle de Pelayo, 39",
    "sg:city":"Palmas De Gran Canaria",
    "sg:orig_category":"Bazares, Art\u00cdculos De Limpieza Y De Cocina (al Por Menor)",
    "sg:phone":"+34 928 26 44 03",
    "sg:postcode":"35010",
    "sg:province":"Las Palmas",
    "wof:name":"Martins Nobre Marcela Edith",
    "wof:placetype":"venue"
},
  "geometry": {"coordinates":[-15.4366703033,28.1336994171],"type":"Point"}
}