{
  "type": "Feature",
  "properties": {
    "addr:full":"Calle de San Gabriel, 6 San Pedro Alcantara M\u00e1laga 29670",
    "addr:housenumber":"6",
    "addr:postcode":"29670",
    "addr:street":"Calle De San Gabriel",
    "iso:country":"ES",
    "sg:address":"Calle de San Gabriel, 6",
    "sg:city":"San Pedro Alcantara",
    "sg:orig_category":"Ropa Para Se\u00d1oras Y Caballeros (al Por Menor)",
    "sg:phone":"+34 952 92 78 43",
    "sg:postcode":"29670",
    "sg:province":"M\u00e1laga",
    "wof:name":"Lopez Rodriguez Jose Maria",
    "wof:placetype":"venue"
},
  "geometry": {"coordinates":[-4.98919487,36.4854507446],"type":"Point"}
}