{
  "type": "Feature",
  "properties": {
    "iso:country":"ES",
    "sg:address":"Santa Ana Kalea, 7",
    "sg:city":"Elgoibar",
    "sg:classifiers":[
        {
            "category":"Autos & Motor Vehicles",
            "subcategory":"Automobile Sales",
            "type":"Retail Goods"
        }
    ],
    "sg:phone":"+34 943 74 10 11",
    "sg:postcode":"20870",
    "sg:province":"Guip\u00f9zcoa",
    "wof:name":"Autoeskola Larra\u00f1aga S.l.",
    "wof:placetype":"venue"
},
  "geometry": {"coordinates":[-2.4179024696,43.2127380371],"type":"Point"}
}