{
  "type": "Feature",
  "properties": {
    "addr:full":"Calle de Codriana, 59 Villaca\u00f1as Toledo 45860",
    "addr:housenumber":"59",
    "addr:postcode":"45860",
    "addr:street":"Calle De Codriana",
    "iso:country":"ES",
    "sg:address":"Calle de Codriana, 59",
    "sg:city":"Villaca\u00f1as",
    "sg:orig_category":"Puertas Y Portales",
    "sg:phone":"+34 925 16 13 71",
    "sg:postcode":"45860",
    "sg:province":"Toledo",
    "wof:name":"Door S.a.",
    "wof:placetype":"venue"
},
  "geometry": {"coordinates":[-3.3475689888,39.611530304],"type":"Point"}
}