{
  "type": "Feature",
  "properties": {
    "addr:full":"Calle de Gadil, 11 Seron Almer\u00eda 04890",
    "addr:housenumber":"11",
    "addr:postcode":"04890",
    "addr:street":"Calle De Gadil;Almeri\u0301A",
    "iso:country":"ES",
    "sg:address":"Calle de Gadil, 11",
    "sg:city":"Seron",
    "sg:orig_category":"Frutas Y Legumbres Frescas (al Por Mayor)",
    "sg:phone":"+34 950 42 60 12",
    "sg:postcode":"04890",
    "sg:province":"Almer\u00eda",
    "wof:name":"Perez Carpintero Emrique",
    "wof:placetype":"venue"
},
  "geometry": {"coordinates":[-2.5087471008,37.3435554504],"type":"Point"}
}