{
  "type": "Feature",
  "properties": {
    "iso:country":"ES",
    "sg:address":"Czad Medina, 30",
    "sg:city":"Salamanca",
    "sg:classifiers":[
        {
            "category":"Banks & Credit Unions",
            "subcategory":"Bureau De Change",
            "type":"Services"
        }
    ],
    "sg:phone":"+34 923 23 98 38",
    "sg:postcode":"37004",
    "sg:province":"Salamanca",
    "sg:tags":[
        "organismos",
        "control"
    ],
    "wof:name":"Socotec Iberia S.a.",
    "wof:placetype":"venue"
},
  "geometry": {"coordinates":[-5.6465888023,40.973400116],"type":"Point"}
}