{
  "type": "Feature",
  "properties": {
    "iso:country":"ES",
    "sg:address":"Calle de Aniceto Coloma, 34",
    "sg:city":"Almansa",
    "sg:orig_category":"Carnicer\u00cdas, Carnicer\u00cdas",
    "sg:phone":"+34 967 34 37 99",
    "sg:postcode":"02640",
    "sg:province":"Albacete",
    "wof:name":"Carnicas German S.l.",
    "wof:placetype":"venue"
},
  "geometry": {"coordinates":[-1.0976781845,38.8694839478],"type":"Point"}
}