{
  "type": "Feature",
  "properties": {
    "iso:country":"ES",
    "sg:address":"Rua Pi Y Margall, 72",
    "sg:city":"Vigo",
    "sg:orig_category":"M\u00c9dicos: Pediatr\u00cda. Enfermedades De Los Ni\u00d1os",
    "sg:phone":"+34 986 29 30 71",
    "sg:postcode":"36202",
    "sg:province":"Pontevedra",
    "wof:name":"Antelo Cortizas Jesus",
    "wof:placetype":"venue"
},
  "geometry": {"coordinates":[-8.7309989929,42.23204422],"type":"Point"}
}