{
  "type": "Feature",
  "properties": {
    "addr:full":"Carrer de Catalunya, 2 Palma Islas Baleares 07011",
    "addr:housenumber":"2",
    "addr:postcode":"07011",
    "addr:street":"Carrer De Catalunya",
    "iso:country":"ES",
    "sg:address":"Carrer de Catalunya, 2",
    "sg:city":"Palma",
    "sg:orig_category":"M\u00c1rmoles, Granitos Y Piedras Naturales",
    "sg:phone":"+34 971 22 00 16",
    "sg:postcode":"07011",
    "sg:province":"Islas Baleares",
    "sg:website":"www.tino.es",
    "wof:name":"Tino Stone Group S. A.",
    "wof:placetype":"venue"
},
  "geometry": {"coordinates":[2.6230239868,39.5921516418],"type":"Point"}
}