{
  "type": "Feature",
  "properties": {
    "iso:country":"ES",
    "sg:address":"Ctra Nacional 340, S/n",
    "sg:city":"Hoya",
    "sg:orig_category":"Empresas De Carpinter\u00cda De Madera",
    "sg:phone":"+34 968 48 16 54",
    "sg:postcode":"30816",
    "sg:province":"Murcia",
    "wof:name":"Andreo Andreo Antonio",
    "wof:placetype":"venue"
},
  "geometry": {"coordinates":[-1.1298867464,37.9834747314],"type":"Point"}
}