{
  "type": "Feature",
  "properties": {
    "iso:country":"ES",
    "sg:address":"Avda Odon, 18",
    "sg:city":"Villaviciosa Odon",
    "sg:orig_category":"Tapicer\u00cdas",
    "sg:phone":"+34 916 16 32 56",
    "sg:postcode":"28670",
    "sg:province":"Madrid",
    "wof:name":"Platero Jimenez Manuel",
    "wof:placetype":"venue"
},
  "geometry": {"coordinates":[-3.9063119888,40.3558235168],"type":"Point"}
}