{
  "type": "Feature",
  "properties": {
    "addr:full":"Rond San Torcuato, 11 Zamora Zamora 49006",
    "addr:housenumber":"11",
    "addr:postcode":"49006",
    "addr:street":"San Torcuato",
    "iso:country":"ES",
    "sg:address":"Rond San Torcuato, 11",
    "sg:city":"Zamora",
    "sg:orig_category":"Fabricaci\u00d3n, Instalaci\u00d3n Y Reparaci\u00d3n De Bombas",
    "sg:phone":"+34 980 53 40 14",
    "sg:postcode":"49006",
    "sg:province":"Zamora",
    "wof:name":"Seisdedos Cospedal Miguel",
    "wof:placetype":"venue"
},
  "geometry": {"coordinates":[-5.7457342148,41.5033302307],"type":"Point"}
}