{
  "type": "Feature",
  "properties": {
    "addr:full":"Calle de Isaac Peral, 26 Pto. Rosario Las Palmas 35600",
    "addr:housenumber":"26",
    "addr:postcode":"35600",
    "addr:street":"Calle De Isaac Peral;Pto. Rosario Las",
    "iso:country":"ES",
    "sg:address":"Calle de Isaac Peral, 26",
    "sg:city":"Pto. Rosario",
    "sg:orig_category":"Comercio De Piezas De Recambio Y De Accesorios De Veh\u00cdculos, Veh\u00cdculos Industriales",
    "sg:phone":"+34 928 17 57 11",
    "sg:postcode":"35600",
    "sg:province":"Las Palmas",
    "wof:name":"Auto Repuestos Antonio, S.l",
    "wof:placetype":"venue"
},
  "geometry": {"coordinates":[-13.8751497269,28.5064373016],"type":"Point"}
}