{
  "type": "Feature",
  "properties": {
    "addr:full":"Granada, S/n Ortuella Vizcaya 48530",
    "addr:housenumber":"/ n",
    "addr:postcode":"48530",
    "addr:street":"Granada S",
    "iso:country":"ES",
    "sg:address":"Granada, S/n",
    "sg:city":"Ortuella",
    "sg:orig_category":"Fabricaci\u00d3n De Productos L\u00c1cteos Y Derivados",
    "sg:phone":"+34 946 64 23 54",
    "sg:postcode":"48530",
    "sg:province":"Vizcaya",
    "wof:name":"Casta\u00f1o Azcona Jose Manuel",
    "wof:placetype":"venue"
},
  "geometry": {"coordinates":[-3.0431210995,43.3051986694],"type":"Point"}
}