{
  "type": "Feature",
  "properties": {
    "addr:full":"Pg Sort (de La), 21 Torredembarra Tarragona 43830",
    "addr:postcode":"43830",
    "iso:country":"ES",
    "sg:address":"Pg Sort (de La), 21",
    "sg:city":"Torredembarra",
    "sg:orig_category":"Inmobiliaria (agencias)",
    "sg:phone":"+34 977 64 50 63",
    "sg:postcode":"43830",
    "sg:province":"Tarragona",
    "wof:name":"Gestio Inmobiliaria Ferran S.l.",
    "wof:placetype":"venue"
},
  "geometry": {"coordinates":[1.399009943,41.1433486938],"type":"Point"}
}