{
  "type": "Feature",
  "properties": {
    "addr:full":"Calle de Isla Formentera, 18 Valencia Valencia 46026",
    "addr:housenumber":"18",
    "addr:postcode":"46026",
    "addr:street":"Calle De Isla Formentera",
    "iso:country":"ES",
    "sg:address":"Calle de Isla Formentera, 18",
    "sg:city":"Valencia",
    "sg:orig_category":"Construcciones Navales Y Fluviales",
    "sg:phone":"+34 963 82 00 02",
    "sg:postcode":"46026",
    "sg:province":"Valencia",
    "wof:name":"Analaqua Labortorio De Aguas Y Consultoria Medioambiental S.l.",
    "wof:placetype":"venue"
},
  "geometry": {"coordinates":[-0.3810000122,39.4472999573],"type":"Point"}
}