{
  "type": "Feature",
  "properties": {
    "iso:country":"ES",
    "sg:address":"Calle de Muro, 20",
    "sg:city":"Valladolid",
    "sg:orig_category":"Asesor\u00cda De Formaci\u00d3n Y Gesti\u00d3n De Personal",
    "sg:phone":"+34 983 29 50 51",
    "sg:postcode":"47004",
    "sg:province":"Valladolid",
    "wof:name":"Martinez Loya S.l.",
    "wof:placetype":"venue"
},
  "geometry": {"coordinates":[-4.7255949974,41.6454849243],"type":"Point"}
}