{
  "type": "Feature",
  "properties": {
    "addr:full":"Calle de Nestor, 4 Madrid Madrid 28022",
    "addr:housenumber":"4",
    "addr:postcode":"28022",
    "addr:street":"Calle De Nestor",
    "iso:country":"ES",
    "sg:address":"Calle de Nestor, 4",
    "sg:city":"Madrid",
    "sg:orig_category":"Electricidad: Instalaciones Industriales",
    "sg:phone":"+34 917 41 71 54",
    "sg:postcode":"28022",
    "sg:province":"Madrid",
    "wof:name":"Itanel C.b.",
    "wof:placetype":"venue"
},
  "geometry": {"coordinates":[-3.6087059975,40.4475097656],"type":"Point"}
}