{
  "type": "Feature",
  "properties": {
    "addr:full":"Prje Carrichosa, S/n Cieza Murcia 30530",
    "addr:housenumber":"s / n",
    "addr:postcode":"30530",
    "iso:country":"ES",
    "sg:address":"Prje Carrichosa, S/n",
    "sg:city":"Cieza",
    "sg:orig_category":"Producci\u00d3n, Venta De Productos De Agricultura Biol\u00d3gica",
    "sg:phone":"+34 968 43 42 48",
    "sg:postcode":"30530",
    "sg:province":"Murcia",
    "wof:name":"El Puntal Agraria S.a.",
    "wof:placetype":"venue"
},
  "geometry": {"coordinates":[-1.4241739511,38.2379302979],"type":"Point"}
}