{
  "type": "Feature",
  "properties": {
    "addr:full":"Ctra Rubi, 15 Terrassa Barcelona 08228",
    "addr:housenumber":"15",
    "addr:postcode":"08228",
    "addr:street":"Ctra Rubi",
    "iso:country":"ES",
    "sg:address":"Ctra Rubi, 15",
    "sg:city":"Terrassa",
    "sg:orig_category":"Inmobiliaria (agencias)",
    "sg:phone":"+34 937 83 16 92",
    "sg:postcode":"08228",
    "sg:province":"Barcelona",
    "wof:name":"Finques Viladecavalls S.l.",
    "wof:placetype":"venue"
},
  "geometry": {"coordinates":[2.0352640152,41.5329399109],"type":"Point"}
}