{
  "type": "Feature",
  "properties": {
    "iso:country":"ES",
    "sg:address":"Calle de Marmolistas, 1",
    "sg:city":"Chiclana De La Frontera",
    "sg:orig_category":"Fabricaci\u00d3n, Importaci\u00d3n, Venta De Material De Telefon\u00cda, Peritelefon\u00cda",
    "sg:phone":"+34 956 53 59 67",
    "sg:postcode":"11130",
    "sg:province":"C\u00e1diz",
    "wof:name":"Landitel S.l.",
    "wof:placetype":"venue"
},
  "geometry": {"coordinates":[-6.1504049301,36.4274520874],"type":"Point"}
}