{
  "type": "Feature",
  "properties": {
    "addr:full":"Calle de Tetuan, 25 Santander Cantabria 39004",
    "addr:housenumber":"25",
    "addr:postcode":"39004",
    "addr:street":"Calle De Tetuan",
    "iso:country":"ES",
    "sg:address":"Calle de Tetuan, 25",
    "sg:city":"Santander",
    "sg:orig_category":"Comercio De Minerales, F\u00d3siles Y Conchas",
    "sg:phone":"+34 942 21 83 53",
    "sg:postcode":"39004",
    "sg:province":"Cantabria",
    "wof:name":"Cuartas Aguado Angel",
    "wof:placetype":"venue"
},
  "geometry": {"coordinates":[-3.7944529057,43.4659500122],"type":"Point"}
}