{
  "type": "Feature",
  "properties": {
    "addr:full":"Calle de Riego, 17 Zamora Zamora 49004",
    "addr:housenumber":"17",
    "addr:postcode":"49004",
    "addr:street":"Calle De Riego",
    "iso:country":"ES",
    "sg:address":"Calle de Riego, 17",
    "sg:city":"Zamora",
    "sg:orig_category":"Armas Y Municiones (fabricaci\u00d3n, Al Por Mayor)",
    "sg:phone":"+34 980 53 67 72",
    "sg:postcode":"49004",
    "sg:province":"Zamora",
    "wof:name":"Armeria Tomas S.l.",
    "wof:placetype":"venue"
},
  "geometry": {"coordinates":[-5.7472186089,41.5049438477],"type":"Point"}
}