{
  "type": "Feature",
  "properties": {
    "iso:country":"ES",
    "sg:address":"Poli Industrial Golparc, 30",
    "sg:city":"Codis",
    "sg:orig_category":"Construcciones Met\u00c1licas",
    "sg:phone":"+34 973 60 14 75",
    "sg:postcode":"25241",
    "sg:province":"Lleida",
    "wof:name":"Construcciones Metal Liques Salvia S.l.",
    "wof:placetype":"venue"
},
  "geometry": {"coordinates":[0.9323819876,41.6301574707],"type":"Point"}
}