{
  "type": "Feature",
  "properties": {
    "iso:country":"ES",
    "sg:address":"Carr Via Punica, 11",
    "sg:city":"Eivissa",
    "sg:orig_category":"Ense\u00d1anza Variada",
    "sg:phone":"+34 971 39 92 81",
    "sg:postcode":"07800",
    "sg:province":"Islas Baleares",
    "wof:name":"Zona 6 Atellier De Media Digital S.l.",
    "wof:placetype":"venue"
},
  "geometry": {"coordinates":[1.4316395521,38.9080848694],"type":"Point"}
}