{
  "type": "Feature",
  "properties": {
    "addr:full":"Calle de Molino, 3 Argamasilla Calatrava Ciudad Real 13440",
    "addr:housenumber":"3",
    "addr:postcode":"13440",
    "addr:street":"Calle De Molino",
    "iso:country":"ES",
    "sg:address":"Calle de Molino, 3",
    "sg:city":"Argamasilla Calatrava",
    "sg:orig_category":"Molduras, Junquillos, Listones Y Molduras Perforadas",
    "sg:phone":"+34 926 47 78 94",
    "sg:postcode":"13440",
    "sg:province":"Ciudad Real",
    "wof:name":"Garcia Carnero Adolfo",
    "wof:placetype":"venue"
},
  "geometry": {"coordinates":[-4.0809469223,38.726234436],"type":"Point"}
}