{
  "type": "Feature",
  "properties": {
    "addr:full":"Calle de Felisa Campuzano, 19 Corrales Cantabria 39400",
    "addr:housenumber":"19",
    "addr:postcode":"39400",
    "addr:street":"Calle De Felisa Campuzano",
    "iso:country":"ES",
    "sg:address":"Calle de Felisa Campuzano, 19",
    "sg:city":"Corrales",
    "sg:orig_category":"Ense\u00d1anza: Idiomas",
    "sg:phone":"+34 942 83 21 69",
    "sg:postcode":"39400",
    "sg:province":"Cantabria",
    "wof:name":"Friends School S.cv.",
    "wof:placetype":"venue"
},
  "geometry": {"coordinates":[-4.0680999756,43.262348175],"type":"Point"}
}