{
  "type": "Feature",
  "properties": {
    "addr:full":"Ronda Norte, S/n Valladolid Valladolid 47009",
    "addr:housenumber":"s / n",
    "addr:postcode":"47009",
    "addr:street":"Ronda Norte",
    "iso:country":"ES",
    "sg:address":"Ronda Norte, S/n",
    "sg:city":"Valladolid",
    "sg:orig_category":"Cooperativas Agr\u00cdcolas",
    "sg:phone":"+34 983 29 90 30",
    "sg:postcode":"47009",
    "sg:province":"Valladolid",
    "wof:name":"Cooperativa Avicola Y Ganadera De Burgos",
    "wof:placetype":"venue"
},
  "geometry": {"coordinates":[-4.7224311829,41.6785202026],"type":"Point"}
}