{
  "type": "Feature",
  "properties": {
    "iso:country":"ES",
    "sg:address":"Carrer de Pas De L'ensenyan\u00c7a, 2",
    "sg:city":"Barcelona",
    "sg:orig_category":"Caf\u00c9s, Bares, Cervecer\u00cdas",
    "sg:phone":"+34 933 02 11 31",
    "sg:postcode":"08002",
    "sg:province":"Barcelona",
    "wof:name":"Fesvi S.l.",
    "wof:placetype":"venue"
},
  "geometry": {"coordinates":[2.1769959927,41.3818092346],"type":"Point"}
}