{
  "type": "Feature",
  "properties": {
    "addr:full":"Carrer de Manuel De Falla, 40 Barcelona Barcelona 08034",
    "addr:housenumber":"40",
    "addr:postcode":"08034",
    "addr:street":"Carrer De Manuel De Falla",
    "iso:country":"ES",
    "sg:address":"Carrer de Manuel De Falla, 40",
    "sg:city":"Barcelona",
    "sg:orig_category":"Peluqueros: De Se\u00d1oras",
    "sg:phone":"+34 932 03 54 72",
    "sg:postcode":"08034",
    "sg:province":"Barcelona",
    "wof:name":"Lopez Alvarez Maria Del Carmen",
    "wof:placetype":"venue"
},
  "geometry": {"coordinates":[2.1269299984,41.3944244385],"type":"Point"}
}