{
  "type": "Feature",
  "properties": {
    "iso:country":"ES",
    "sg:address":"Plaz Corrillo, 18",
    "sg:city":"Salamanca",
    "sg:orig_category":"Charcuter\u00cdas (al Por Mayor)",
    "sg:phone":"+34 923 26 02 51",
    "sg:postcode":"37002",
    "sg:province":"Salamanca",
    "wof:name":"Ingelmo Perez Maria Del Carmen",
    "wof:placetype":"venue"
},
  "geometry": {"coordinates":[-5.664773941,40.9642105103],"type":"Point"}
}