{
  "type": "Feature",
  "properties": {
    "addr:full":"Calle de Morena, 1 Granada Granada 18015",
    "addr:housenumber":"1",
    "addr:postcode":"18015",
    "addr:street":"Calle De Morena",
    "iso:country":"ES",
    "sg:address":"Calle de Morena, 1",
    "sg:city":"Granada",
    "sg:orig_category":"Abogados",
    "sg:phone":"+34 958 20 71 13",
    "sg:postcode":"18015",
    "sg:province":"Granada",
    "wof:name":"Fernandez-figares Morales Maria Jose",
    "wof:placetype":"venue"
},
  "geometry": {"coordinates":[-3.6356139183,37.1961364746],"type":"Point"}
}