{
  "type": "Feature",
  "properties": {
    "iso:country":"ES",
    "sg:address":"Urb Vaguadas, S/n",
    "sg:city":"Vaguadas",
    "sg:orig_category":"Peluquer\u00cdas, Peluquer\u00cda Mixta",
    "sg:phone":"+34 924 26 88 08",
    "sg:postcode":"06010",
    "sg:province":"Badajoz",
    "sg:website":"www.manuelcortes.com",
    "wof:name":"Cortes Rangel Manuel",
    "wof:placetype":"venue"
},
  "geometry": {"coordinates":[-6.9729938507,38.844543457],"type":"Point"}
}