{
  "type": "Feature",
  "properties": {
    "addr:full":"Calle de Rafael Suarez, 4 Aviles Asturias 33403",
    "addr:housenumber":"4",
    "addr:postcode":"33403",
    "addr:street":"Calle De Rafael Suarez",
    "iso:country":"ES",
    "sg:address":"Calle de Rafael Suarez, 4",
    "sg:city":"Aviles",
    "sg:orig_category":"Ingenier\u00cda, Centros De Estudios (diversos)",
    "sg:phone":"+34 985 57 38 52",
    "sg:postcode":"33403",
    "sg:province":"Asturias",
    "wof:name":"Sistemas E Instrumentacion S. A.",
    "wof:placetype":"venue"
},
  "geometry": {"coordinates":[-5.9033761024,43.5396652222],"type":"Point"}
}