{
  "type": "Feature",
  "properties": {
    "iso:country":"ES",
    "sg:address":"Calle de Mar, 10",
    "sg:city":"Malaga",
    "sg:orig_category":"Electrodom\u00c9sticos (al Por Menor)",
    "sg:phone":"+34 952 20 19 15",
    "sg:postcode":"29017",
    "sg:province":"M\u00e1laga",
    "wof:name":"Bazar San Juan S.a.",
    "wof:placetype":"venue"
},
  "geometry": {"coordinates":[-4.3591189384,36.7205123901],"type":"Point"}
}