{
  "type": "Feature",
  "properties": {
    "iso:country":"ES",
    "sg:address":"Ctra Tarazona, Km. 0038,0",
    "sg:city":"Roda",
    "sg:orig_category":"Fabricaci\u00d3n De Taburetes, Sillas Y Sillones",
    "sg:phone":"+34 967 44 21 59",
    "sg:postcode":"02630",
    "sg:province":"Albacete",
    "wof:name":"Andres Saez S.l.",
    "wof:placetype":"venue"
},
  "geometry": {"coordinates":[-2.1357738972,39.2120056152],"type":"Point"}
}