{
  "type": "Feature",
  "properties": {
    "addr:full":"Mayor, 12 Estella Navarra 31200",
    "addr:housenumber":"12",
    "addr:postcode":"31200",
    "addr:street":"Mayor",
    "iso:country":"ES",
    "sg:address":"Mayor, 12",
    "sg:city":"Estella",
    "sg:orig_category":"Mercer\u00cda, Lencer\u00cda (al Por Menor)",
    "sg:phone":"+34 948 54 62 47",
    "sg:postcode":"31200",
    "sg:province":"Navarra",
    "wof:name":"Ganuza Chasco Elvira",
    "wof:placetype":"venue"
},
  "geometry": {"coordinates":[-2.032900095,42.6718444824],"type":"Point"}
}