{
  "type": "Feature",
  "properties": {
    "iso:country":"ES",
    "sg:address":"Calle de Legua, 3",
    "sg:city":"Merida",
    "sg:orig_category":"Iglesia Cat\u00d3lica",
    "sg:phone":"+34 924 31 35 06",
    "sg:postcode":"06800",
    "sg:province":"Badajoz",
    "wof:name":"Conejero Rivera Juan Antonio",
    "wof:placetype":"venue"
},
  "geometry": {"coordinates":[-6.3480930328,38.9303131104],"type":"Point"}
}