{
  "type": "Feature",
  "properties": {
    "iso:country":"ES",
    "sg:address":"Julio Romero De Torres, 25",
    "sg:city":"Lucena",
    "sg:orig_category":"M\u00c9dicos: Estomatolog\u00cda",
    "sg:phone":"+34 957 51 54 54",
    "sg:postcode":"14900",
    "sg:province":"C\u00f3rdoba",
    "wof:name":"Lopez Del Jesus Dolores",
    "wof:placetype":"venue"
},
  "geometry": {"coordinates":[-4.4857888222,37.4090194702],"type":"Point"}
}