{
  "type": "Feature",
  "properties": {
    "addr:full":"Calle de Doctor Leal Casta\u00d1os, 14 Sevilla Sevilla 41009",
    "addr:housenumber":"14",
    "addr:postcode":"41009",
    "addr:street":"Calle De Doctor Leal Castan\u0303Os",
    "iso:country":"ES",
    "sg:address":"Calle de Doctor Leal Casta\u00d1os, 14",
    "sg:city":"Sevilla",
    "sg:orig_category":"Metalurgia",
    "sg:phone":"+34 954 38 62 43",
    "sg:postcode":"41009",
    "sg:province":"Sevilla",
    "sg:website":"www.comercialvica.com",
    "wof:name":"Comercial Villalba Caro S.l.",
    "wof:placetype":"venue"
},
  "geometry": {"coordinates":[-5.9829587936,37.4073181152],"type":"Point"}
}