{
  "type": "Feature",
  "properties": {
    "iso:country":"ES",
    "sg:address":"Brea-san Juan, S/n",
    "sg:city":"Moldes",
    "sg:orig_category":"Estudios Y Construcci\u00d3n De Acuarios Y Viveros",
    "sg:phone":"+34 985 63 51 65",
    "sg:postcode":"33769",
    "sg:province":"Asturias",
    "wof:name":"Acuicultura Del Eo S.l.",
    "wof:placetype":"venue"
},
  "geometry": {"coordinates":[-5.9832577705,43.2504386902],"type":"Point"}
}