{
  "type": "Feature",
  "properties": {
    "iso:country":"ES",
    "sg:address":"Carro, 1",
    "sg:city":"Moratalla",
    "sg:orig_category":"Aceites Y Grasas Alimentarias (fabricaci\u00d3n, Al Por Mayor)",
    "sg:phone":"+34 968 43 32 42",
    "sg:postcode":"30440",
    "sg:province":"Murcia",
    "wof:name":"Aceites De Moratalla S.l.",
    "wof:placetype":"venue"
},
  "geometry": {"coordinates":[-1.8905038834,38.1864471436],"type":"Point"}
}