{
  "type": "Feature",
  "properties": {
    "addr:full":"Calle de Loreto, 39 Denia Alicante 03700",
    "addr:housenumber":"39",
    "addr:postcode":"03700",
    "addr:street":"Calle De Loreto",
    "iso:country":"ES",
    "sg:address":"Calle de Loreto, 39",
    "sg:city":"Denia",
    "sg:orig_category":"Administradores De Bienes Y Delegados De Comunidades De Propietarios",
    "sg:phone":"+34 965 78 60 70",
    "sg:postcode":"03700",
    "sg:province":"Alicante",
    "wof:name":"Juan Catala Miguel",
    "wof:placetype":"venue"
},
  "geometry": {"coordinates":[0.1039993018,38.8402862549],"type":"Point"}
}