{
  "type": "Feature",
  "properties": {
    "iso:country":"ES",
    "sg:address":"Calle de Palacio Valdes, 7",
    "sg:city":"Oviedo",
    "sg:orig_category":"Perfumer\u00cda (al Por Menor)",
    "sg:phone":"+34 985 22 43 32",
    "sg:postcode":"33002",
    "sg:province":"Asturias",
    "wof:name":"Montse Perfumeria Cosmeticos Y Complementos S.l.",
    "wof:placetype":"venue"
},
  "geometry": {"coordinates":[-5.849779129,43.3640289307],"type":"Point"}
}