{
  "type": "Feature",
  "properties": {
    "iso:country":"ES",
    "sg:address":"Calle de Turina, 26",
    "sg:city":"Santa Cruz De Tenerife",
    "sg:orig_category":"Agencias Y Agentes Comerciales, Representantes",
    "sg:phone":"+34 922 23 50 67",
    "sg:postcode":"38007",
    "sg:province":"Santa Cruz De Tenerife",
    "wof:name":"Representaciones Maybe S.l",
    "wof:placetype":"venue"
},
  "geometry": {"coordinates":[-16.2724285126,28.4639606476],"type":"Point"}
}