{
  "type": "Feature",
  "properties": {
    "addr:full":"Calle de Greco El, 18 Tafira Alta Las Palmas 35017",
    "addr:housenumber":"18",
    "addr:postcode":"35017",
    "addr:street":"Calle De Greco El;Alta",
    "iso:country":"ES",
    "sg:address":"Calle de Greco El, 18",
    "sg:city":"Tafira Alta",
    "sg:orig_category":"Abogados",
    "sg:phone":"+34 928 35 03 24",
    "sg:postcode":"35017",
    "sg:province":"Las Palmas",
    "wof:name":"Juan Gomez Castor",
    "wof:placetype":"venue"
},
  "geometry": {"coordinates":[-15.4663038254,28.0512275696],"type":"Point"}
}