{
  "type": "Feature",
  "properties": {
    "iso:country":"ES",
    "sg:address":"Plaz Virgen De Los Dolores, 6",
    "sg:city":"Sevilla",
    "sg:orig_category":"Molduras, Junquillos, Listones Y Molduras Perforadas",
    "sg:phone":"+34 954 45 09 66",
    "sg:postcode":"41010",
    "sg:province":"Sevilla",
    "wof:name":"Ruiz Pacheco Vicente",
    "wof:placetype":"venue"
},
  "geometry": {"coordinates":[-6.0087208748,37.3772239685],"type":"Point"}
}