{
  "type": "Feature",
  "properties": {
    "addr:full":"Avda Paris, 8 Benidorm Alicante 03500",
    "addr:housenumber":"8",
    "addr:postcode":"03500",
    "addr:street":"Avda Paris",
    "iso:country":"ES",
    "sg:address":"Avda Paris, 8",
    "sg:city":"Benidorm",
    "sg:orig_category":"Inmobiliaria (agencias)",
    "sg:phone":"+34 965 86 24 01",
    "sg:postcode":"03500",
    "sg:province":"Alicante",
    "wof:name":"Bain  Williaml",
    "wof:placetype":"venue"
},
  "geometry": {"coordinates":[-0.1032250002,38.5380401611],"type":"Point"}
}