{
  "type": "Feature",
  "properties": {
    "addr:full":"Calle de San Lorenzo, 5 Donostia-san Sebastian Guip\u00f9zcoa 20003",
    "addr:housenumber":"5",
    "addr:postcode":"20003",
    "addr:street":"Calle De San Lorenzo",
    "iso:country":"ES",
    "sg:address":"Calle de San Lorenzo, 5",
    "sg:city":"Donostia-san Sebastian",
    "sg:orig_category":"Molduras, Junquillos, Listones Y Molduras Perforadas",
    "sg:phone":"+34 943 42 12 51",
    "sg:postcode":"20003",
    "sg:province":"Guip\u00f9zcoa",
    "wof:name":"Call Phone S.l.",
    "wof:placetype":"venue"
},
  "geometry": {"coordinates":[-1.9832860231,43.3229904175],"type":"Point"}
}