{
  "type": "Feature",
  "properties": {
    "iso:country":"ES",
    "sg:address":"Calle de Tesifonte Gallego, 11",
    "sg:city":"Albacete",
    "sg:orig_category":"Abogados",
    "sg:phone":"+34 967 21 01 27",
    "sg:postcode":"02002",
    "sg:province":"Albacete",
    "wof:name":"Torrente Risue\u00f1o Jesus",
    "wof:placetype":"venue"
},
  "geometry": {"coordinates":[-1.8554769754,38.9921226501],"type":"Point"}
}