{
  "type": "Feature",
  "properties": {
    "iso:country":"ES",
    "sg:address":"Avda Santa Maria, 51",
    "sg:city":"Talayuela",
    "sg:orig_category":"Negocio De Materiales De Construcci\u00d3n",
    "sg:phone":"+34 927 57 81 86",
    "sg:postcode":"10310",
    "sg:province":"C\u00e1ceres",
    "wof:name":"Pe\u00f1a Lopez Antonio",
    "wof:placetype":"venue"
},
  "geometry": {"coordinates":[-5.6081881523,39.9880561829],"type":"Point"}
}