{
  "type": "Feature",
  "properties": {
    "iso:country":"ES",
    "sg:address":"Calle de Juan Ramon Jimenez, 5",
    "sg:city":"Rota",
    "sg:orig_category":"Aguas (distribuci\u00d3n, Servicios)",
    "sg:phone":"+34 956 84 16 67",
    "sg:postcode":"11520",
    "sg:province":"C\u00e1diz",
    "wof:name":"Comunidad De Regantes Zona Noroeste De Cadiz",
    "wof:placetype":"venue"
},
  "geometry": {"coordinates":[-6.3627638817,36.6211509705],"type":"Point"}
}