{
  "type": "Feature",
  "properties": {
    "addr:full":"Calle de Amad, 22 Borja Zaragoza 50540",
    "addr:housenumber":"22",
    "addr:postcode":"50540",
    "addr:street":"Calle De Amad",
    "iso:country":"ES",
    "sg:address":"Calle de Amad, 22",
    "sg:city":"Borja",
    "sg:orig_category":"Internados & Ense\u00d1anza Privada",
    "sg:phone":"+34 976 86 71 40",
    "sg:postcode":"50540",
    "sg:province":"Zaragoza",
    "wof:name":"Congregacion De Hermanas De La Caridad De Santa Ana",
    "wof:placetype":"venue"
},
  "geometry": {"coordinates":[-1.5339964628,41.8332138062],"type":"Point"}
}