{
  "type": "Feature",
  "properties": {
    "iso:country":"ES",
    "sg:address":"Avda Puerta De Hierro, S/n",
    "sg:city":"Madrid",
    "sg:orig_category":"Caf\u00c9s, Bares, Cervecer\u00cdas",
    "sg:phone":"+34 915 43 17 23",
    "sg:postcode":"28040",
    "sg:province":"Madrid",
    "wof:name":"Granados Gonzalez Maria",
    "wof:placetype":"venue"
},
  "geometry": {"coordinates":[-3.7322590351,40.4441413879],"type":"Point"}
}