{
  "type": "Feature",
  "properties": {
    "iso:country":"ES",
    "sg:address":"Ctra Plasencia, Km. 0080,0",
    "sg:city":"Adrada",
    "sg:orig_category":"Ba\u00d1os Y Duchas P\u00dablicos",
    "sg:phone":"+34 918 67 03 11",
    "sg:postcode":"05430",
    "sg:province":"\u00c1vila",
    "wof:name":"Ayuntamiento De La Adrada",
    "wof:placetype":"venue"
},
  "geometry": {"coordinates":[-4.638753891,40.3024139404],"type":"Point"}
}