{
  "type": "Feature",
  "properties": {
    "iso:country":"ES",
    "sg:address":"La Industria, 5",
    "sg:city":"Gandia",
    "sg:orig_category":"Pintura, Barniz, Productos Asimilables (fabricaci\u00d3n, Al Por Mayor)",
    "sg:phone":"+34 962 96 58 63",
    "sg:postcode":"46700",
    "sg:province":"Valencia",
    "sg:website":"www.pinturasadoral.com",
    "wof:name":"Pinturas Doralpin S.l",
    "wof:placetype":"venue"
},
  "geometry": {"coordinates":[-0.1846919954,38.9862709045],"type":"Point"}
}