{
  "type": "Feature",
  "properties": {
    "iso:country":"ES",
    "sg:address":"Rua Santa Clara, 5",
    "sg:city":"Pontevedra",
    "sg:orig_category":"Asesor\u00cda Sobre Comunicaci\u00d3n De Empresas",
    "sg:phone":"+34 986 86 60 89",
    "sg:postcode":"36002",
    "sg:province":"Pontevedra",
    "wof:name":"Codem Pontevedra S.a.",
    "wof:placetype":"venue"
},
  "geometry": {"coordinates":[-8.64087677,42.4328765869],"type":"Point"}
}