{
  "type": "Feature",
  "properties": {
    "addr:full":"Calle de Eduardo Torroja (de), 47 Fuenlabrada Madrid 28946",
    "addr:housenumber":"47",
    "addr:postcode":"28946",
    "addr:street":"Calle De Eduardo Torroja De",
    "iso:country":"ES",
    "sg:address":"Calle de Eduardo Torroja (de), 47",
    "sg:city":"Fuenlabrada",
    "sg:orig_category":"Ferreter\u00cda (diversos)",
    "sg:phone":"+34 916 90 76 97",
    "sg:postcode":"28946",
    "sg:province":"Madrid",
    "wof:name":"Producciones Mitjavila S.a.",
    "wof:placetype":"venue"
},
  "geometry": {"coordinates":[-3.7808589935,40.2841415405],"type":"Point"}
}