{
  "type": "Feature",
  "properties": {
    "addr:full":"Virgen Del Puy, 9 Iru\u00f1a Navarra 31011",
    "addr:housenumber":"9",
    "addr:postcode":"31011",
    "addr:street":"Virgen;Puy",
    "iso:country":"ES",
    "sg:address":"Virgen Del Puy, 9",
    "sg:city":"Iru\u00f1a",
    "sg:orig_category":"Sexshops",
    "sg:phone":"+34 948 25 23 19",
    "sg:postcode":"31011",
    "sg:province":"Navarra",
    "sg:website":"www.cin.es/sexmil1",
    "wof:name":"Blanco Mundin G Garcia Sanchez J J Jimenez De Luque J A Y Otamendi Oroz A S.cv.",
    "wof:placetype":"venue"
},
  "geometry": {"coordinates":[-1.659569025,42.8167915344],"type":"Point"}
}