{
  "type": "Feature",
  "properties": {
    "addr:full":"Calle de Japon, 31 Sevilla Sevilla 41020",
    "addr:housenumber":"31",
    "addr:postcode":"41020",
    "addr:street":"Calle De Japon",
    "iso:country":"ES",
    "sg:address":"Calle de Japon, 31",
    "sg:city":"Sevilla",
    "sg:orig_category":"Par\u00cds",
    "sg:phone":"+34 954 44 10 55",
    "sg:postcode":"41020",
    "sg:province":"Sevilla",
    "wof:name":"Pi\u00f1ero Barrera Manuela",
    "wof:placetype":"venue"
},
  "geometry": {"coordinates":[-5.9155468941,37.4070205688],"type":"Point"}
}