{
  "type": "Feature",
  "properties": {
    "addr:full":"Calle de General Ruiz, 4 Valladolid Valladolid 47004",
    "addr:housenumber":"4",
    "addr:postcode":"47004",
    "addr:street":"Calle De General Ruiz",
    "iso:country":"ES",
    "sg:address":"Calle de General Ruiz, 4",
    "sg:city":"Valladolid",
    "sg:orig_category":"M\u00c9dicos: Cirug\u00cda Cardiovascular Y Tor\u00c1cica",
    "sg:phone":"+34 983 30 35 35",
    "sg:postcode":"47004",
    "sg:province":"Valladolid",
    "wof:name":"Mateo Gutierrez Antonio Maria",
    "wof:placetype":"venue"
},
  "geometry": {"coordinates":[-4.7243900299,41.6464920044],"type":"Point"}
}