{
  "type": "Feature",
  "properties": {
    "addr:full":"Calle de Adriatico, 31 Radazul Bajo Santa Cruz De Tenerife 38109",
    "addr:housenumber":"31",
    "addr:postcode":"38109",
    "addr:street":"Calle De Adriatico",
    "iso:country":"ES",
    "sg:address":"Calle de Adriatico, 31",
    "sg:city":"Radazul Bajo",
    "sg:orig_category":"Textil",
    "sg:phone":"+34 922 68 82 05",
    "sg:postcode":"38109",
    "sg:province":"Santa Cruz De Tenerife",
    "wof:name":"Ifara Gestion, S.l.",
    "wof:placetype":"venue"
},
  "geometry": {"coordinates":[-16.2548561096,28.4698104858],"type":"Point"}
}