{
  "type": "Feature",
  "properties": {
    "iso:country":"ES",
    "sg:address":"Calle de Hermanos Kennedy, 11",
    "sg:city":"Monforte Cid",
    "sg:orig_category":"Mec\u00c1nico Del Autom\u00d3vil",
    "sg:phone":"+34 965 62 02 93",
    "sg:postcode":"03670",
    "sg:province":"Alicante",
    "wof:name":"Sirvent Marti Francisco",
    "wof:placetype":"venue"
},
  "geometry": {"coordinates":[-0.7293300033,38.3817520142],"type":"Point"}
}