{
  "type": "Feature",
  "properties": {
    "addr:full":"Ptda Daimes, 152 Daimes Alicante 03254",
    "addr:housenumber":"152",
    "addr:postcode":"03254",
    "addr:street":"Ptda Daimes;Alicante",
    "iso:country":"ES",
    "sg:address":"Ptda Daimes, 152",
    "sg:city":"Daimes",
    "sg:orig_category":"Metalurgia",
    "sg:phone":"+34 965 42 43 60",
    "sg:postcode":"03254",
    "sg:province":"Alicante",
    "wof:name":"Moldes Ave S.l.",
    "wof:placetype":"venue"
},
  "geometry": {"coordinates":[-0.6967599988,38.2159004211],"type":"Point"}
}