{
  "type": "Feature",
  "properties": {
    "addr:full":"Calle de Rio (del), 8 Arenas Madrid 28320",
    "addr:housenumber":"8",
    "addr:postcode":"28320",
    "addr:street":"Calle De Rio Del",
    "iso:country":"ES",
    "sg:address":"Calle de Rio (del), 8",
    "sg:city":"Arenas",
    "sg:orig_category":"M\u00c1quinas Y Material Para La Industria De La Alimentaci\u00d3n",
    "sg:phone":"+34 916 92 91 00",
    "sg:postcode":"28320",
    "sg:province":"Madrid",
    "wof:name":"Buhler S.a.",
    "wof:placetype":"venue"
},
  "geometry": {"coordinates":[-3.6837639809,40.2717285156],"type":"Point"}
}