{
  "type": "Feature",
  "properties": {
    "iso:country":"ES",
    "sg:address":"Estd Mala, 10",
    "sg:city":"Bilbao",
    "sg:orig_category":"Turismo: Lugares, Circuitos Y Curiosidades",
    "sg:phone":"+34 944 27 58 94",
    "sg:postcode":"48012",
    "sg:province":"Vizcaya",
    "wof:name":"Autocares Villa Garcia S. L.",
    "wof:placetype":"venue"
},
  "geometry": {"coordinates":[-2.9479470253,43.2555770874],"type":"Point"}
}