{
  "type": "Feature",
  "properties": {
    "iso:country":"ES",
    "sg:address":"Plaz Valdehondillo, 5",
    "sg:city":"Fuenlabrada",
    "sg:orig_category":"Guarder\u00cdas",
    "sg:phone":"+34 916 06 49 49",
    "sg:postcode":"28944",
    "sg:province":"Madrid",
    "wof:name":"Dominguez Dominguez Vicenta",
    "wof:placetype":"venue"
},
  "geometry": {"coordinates":[-3.8005349636,40.2776412964],"type":"Point"}
}