{
  "type": "Feature",
  "properties": {
    "iso:country":"ES",
    "sg:address":"Polonia Etxeberria Kalea, 13",
    "sg:city":"Eibar",
    "sg:orig_category":"Molduras, Junquillos, Listones Y Molduras Perforadas",
    "sg:phone":"+34 943 70 18 38",
    "sg:postcode":"20600",
    "sg:province":"Guip\u00f9zcoa",
    "wof:name":"Roberto Argarate Maiztegi",
    "wof:placetype":"venue"
},
  "geometry": {"coordinates":[-2.470580101,43.1815032959],"type":"Point"}
}