{
  "type": "Feature",
  "properties": {
    "iso:country":"ES",
    "sg:address":"Avda Burgos (de) (muriedas), 60",
    "sg:city":"Muriedas",
    "sg:orig_category":"Mec\u00c1nico Del Autom\u00d3vil",
    "sg:phone":"+34 942 25 03 94",
    "sg:postcode":"39600",
    "sg:province":"Cantabria",
    "wof:name":"Gervasio Y Antonio S.cv.",
    "wof:placetype":"venue"
},
  "geometry": {"coordinates":[-3.8571200371,43.4241294861],"type":"Point"}
}