{
  "type": "Feature",
  "properties": {
    "addr:full":"Avda Castilla, S/n Antilla Huelva 21449",
    "addr:housenumber":"s / n",
    "addr:postcode":"21449",
    "addr:street":"Avda Castilla",
    "iso:country":"ES",
    "sg:address":"Avda Castilla, S/n",
    "sg:city":"Antilla",
    "sg:orig_category":"Bisuter\u00cda, Joyer\u00cda, Relojer\u00cda (al Por Menor)",
    "sg:phone":"+34 959 48 00 02",
    "sg:postcode":"21449",
    "sg:province":"Huelva",
    "wof:name":"Trujillo Fernandez Rafael",
    "wof:placetype":"venue"
},
  "geometry": {"coordinates":[-7.2067580223,37.2075386047],"type":"Point"}
}