{
  "type": "Feature",
  "properties": {
    "iso:country":"ES",
    "sg:address":"Calle de Industria, S/n",
    "sg:city":"Bollullos Mitacion",
    "sg:orig_category":"Materiales De Construcci\u00d3n (en General)",
    "sg:phone":"+34 955 95 00 21",
    "sg:postcode":"41110",
    "sg:province":"Sevilla",
    "wof:name":"Hormigones Odiel S.a.",
    "wof:placetype":"venue"
},
  "geometry": {"coordinates":[-6.1403942108,37.3321037292],"type":"Point"}
}