{
  "type": "Feature",
  "properties": {
    "iso:country":"ES",
    "sg:address":"Calle de Valdes, 18",
    "sg:city":"Oviedo",
    "sg:orig_category":"Inform\u00c1tica (estudios, Servicios, Asesor\u00cda, Formaci\u00d3n)",
    "sg:phone":"+34 985 27 35 05",
    "sg:postcode":"33012",
    "sg:province":"Asturias",
    "wof:name":"Riera Garcia Fernando",
    "wof:placetype":"venue"
},
  "geometry": {"coordinates":[-5.8784589767,43.3658294678],"type":"Point"}
}