{
  "type": "Feature",
  "properties": {
    "iso:country":"ES",
    "sg:address":"Av Meridiana, 354",
    "sg:city":"Barcelona",
    "sg:orig_category":"Laboratorios Farmac\u00c9uticos",
    "sg:phone":"+34 933 45 97 95",
    "sg:postcode":"08027",
    "sg:province":"Barcelona",
    "wof:name":"Allergans.a.e.",
    "wof:placetype":"venue"
},
  "geometry": {"coordinates":[2.1856789589,41.4265670776],"type":"Point"}
}