{
  "type": "Feature",
  "properties": {
    "iso:country":"ES",
    "sg:address":"Av. Constitucion, 1",
    "sg:city":"La Solana",
    "sg:orig_category":"Cooperativas Agr\u00cdcolas",
    "sg:phone":"+34 926 63 10 32",
    "sg:postcode":"13240",
    "sg:province":"Ciudad Real",
    "wof:name":"Sociedad Cooperativa Industrial La Union",
    "wof:placetype":"venue"
},
  "geometry": {"coordinates":[-3.2348649502,38.9376220703],"type":"Point"}
}