{
  "type": "Feature",
  "properties": {
    "iso:country":"ES",
    "sg:address":"Emigrante, S/n",
    "sg:city":"Olivenza",
    "sg:orig_category":"Panader\u00cdas, Panader\u00cdas",
    "sg:phone":"+34 924 49 13 59",
    "sg:postcode":"06100",
    "sg:province":"Badajoz",
    "wof:name":"Dulceria La Chimenea S.c.",
    "wof:placetype":"venue"
},
  "geometry": {"coordinates":[-7.0992941856,38.6803703308],"type":"Point"}
}