{
  "type": "Feature",
  "properties": {
    "iso:country":"ES",
    "sg:address":"Calle de Rollo, 26",
    "sg:city":"Galvez",
    "sg:orig_category":"Agentes Generales De Seguros",
    "sg:phone":"+34 925 40 09 50",
    "sg:postcode":"45164",
    "sg:province":"Toledo",
    "wof:name":"Galvicsa Seguros E Inversion S.l.",
    "wof:placetype":"venue"
},
  "geometry": {"coordinates":[-4.2737989426,39.6999893188],"type":"Point"}
}