{
  "type": "Feature",
  "properties": {
    "iso:country":"ES",
    "sg:address":"Avda Federico Garcia Lorca, 2",
    "sg:city":"Palmas De Gran Canaria",
    "sg:orig_category":"T\u00c9cnicos Veterinarios",
    "sg:phone":"+34 928 29 86 38",
    "sg:postcode":"35011",
    "sg:province":"Las Palmas",
    "wof:name":"Gonzalez Florido Juan Carlos",
    "wof:placetype":"venue"
},
  "geometry": {"coordinates":[-15.4380598068,28.1178207397],"type":"Point"}
}