{
  "type": "Feature",
  "properties": {
    "addr:full":"Kale Nagusia, 24 Legazpi Guip\u00f9zcoa 20230",
    "addr:housenumber":"24",
    "addr:postcode":"20230",
    "addr:street":"Kale Nagusia;Guipu\u0300Zcoa",
    "iso:country":"ES",
    "sg:address":"Kale Nagusia, 24",
    "sg:city":"Legazpi",
    "sg:orig_category":"Cer\u00c1micas: Material Y Suministros",
    "sg:phone":"+34 943 73 16 68",
    "sg:postcode":"20230",
    "sg:province":"Guip\u00f9zcoa",
    "wof:name":"M.suarez S.l.",
    "wof:placetype":"venue"
},
  "geometry": {"coordinates":[-2.3315560818,43.0538253784],"type":"Point"}
}