{
  "type": "Feature",
  "properties": {
    "addr:full":"Calle de Altea, 3 Madrid Madrid 28039",
    "addr:housenumber":"3",
    "addr:postcode":"28039",
    "addr:street":"Calle De Altea",
    "iso:country":"ES",
    "sg:address":"Calle de Altea, 3",
    "sg:city":"Madrid",
    "sg:orig_category":"Ebanister\u00cda",
    "sg:phone":"+34 914 59 45 69",
    "sg:postcode":"28039",
    "sg:province":"Madrid",
    "wof:name":"Vecino Hernando Antonio",
    "wof:placetype":"venue"
},
  "geometry": {"coordinates":[-3.715544939,40.4632568359],"type":"Point"}
}