{
  "type": "Feature",
  "properties": {
    "addr:full":"Plaz Nuestra Se\u00d1ora De Vico, 4 Arnedo La Rioja 26580",
    "addr:postcode":"26580",
    "addr:street":"Vico 4 Arnedo;Rioja",
    "iso:country":"ES",
    "sg:address":"Plaz Nuestra Se\u00d1ora De Vico, 4",
    "sg:city":"Arnedo",
    "sg:orig_category":"Ropa Para Ni\u00d1os (al Por Menor)",
    "sg:phone":"+34 941 38 24 11",
    "sg:postcode":"26580",
    "sg:province":"La Rioja",
    "wof:name":"Martin Gonzalez Tomas",
    "wof:placetype":"venue"
},
  "geometry": {"coordinates":[-2.1004989147,42.2278594971],"type":"Point"}
}