{
  "type": "Feature",
  "properties": {
    "addr:full":"Calle de Doctor Comins, 35 Alginet Valencia 46230",
    "addr:housenumber":"35",
    "addr:postcode":"46230",
    "addr:street":"Calle De Doctor Comins",
    "iso:country":"ES",
    "sg:address":"Calle de Doctor Comins, 35",
    "sg:city":"Alginet",
    "sg:orig_category":"Molduras, Junquillos, Listones Y Molduras Perforadas",
    "sg:phone":"+34 961 75 24 70",
    "sg:postcode":"46230",
    "sg:province":"Valencia",
    "wof:name":"Juan Mellado Maria Mercedes",
    "wof:placetype":"venue"
},
  "geometry": {"coordinates":[-0.4733246863,39.2650985718],"type":"Point"}
}