{
  "type": "Feature",
  "properties": {
    "addr:full":"Pase Emilia Pardo Bazan, 8 Torrejon Ardoz Madrid 28850",
    "addr:housenumber":"8",
    "addr:postcode":"28850",
    "addr:street":"Emilia Pardo Bazan",
    "iso:country":"ES",
    "sg:address":"Pase Emilia Pardo Bazan, 8",
    "sg:city":"Torrejon Ardoz",
    "sg:orig_category":"Locales Y Clases De Danza",
    "sg:phone":"+34 916 77 79 18",
    "sg:postcode":"28850",
    "sg:province":"Madrid",
    "wof:name":"Valentin Petre Iordachescu",
    "wof:placetype":"venue"
},
  "geometry": {"coordinates":[-3.4843358994,40.4565353394],"type":"Point"}
}