{
  "type": "Feature",
  "properties": {
    "addr:full":"Calle de Barrera, 64 Palma Islas Baleares 07014",
    "addr:housenumber":"64",
    "addr:postcode":"07014",
    "addr:street":"Calle De Barrera",
    "iso:country":"ES",
    "sg:address":"Calle de Barrera, 64",
    "sg:city":"Palma",
    "sg:orig_category":"Prot\u00c9sicos Dentales",
    "sg:phone":"+34 971 73 03 24",
    "sg:postcode":"07014",
    "sg:province":"Islas Baleares",
    "wof:name":"Quetglas Merino David",
    "wof:placetype":"venue"
},
  "geometry": {"coordinates":[2.6323561668,39.576335907],"type":"Point"}
}