{
  "type": "Feature",
  "properties": {
    "addr:full":"Ctra Malaga, 45 Alhaurin El Grande M\u00e1laga 29120",
    "addr:housenumber":"45",
    "addr:postcode":"29120",
    "addr:street":"Ctra Malaga",
    "iso:country":"ES",
    "sg:address":"Ctra Malaga, 45",
    "sg:city":"Alhaurin El Grande",
    "sg:orig_category":"Agencias De Viajes",
    "sg:phone":"+34 952 59 59 52",
    "sg:postcode":"29120",
    "sg:province":"M\u00e1laga",
    "sg:website":"www.viajesivaliz.com",
    "wof:name":"Viajes Ivaliz S.l.",
    "wof:placetype":"venue"
},
  "geometry": {"coordinates":[-4.6911292076,36.6420783997],"type":"Point"}
}