{
  "type": "Feature",
  "properties": {
    "addr:full":"Pl Constitucion, 8 Churriana Vega Granada 18194",
    "addr:housenumber":"8",
    "addr:postcode":"18194",
    "addr:street":"Pl Constitucion",
    "iso:country":"ES",
    "sg:address":"Pl Constitucion, 8",
    "sg:city":"Churriana Vega",
    "sg:orig_category":"Reposter\u00cdas",
    "sg:phone":"+34 958 57 07 31",
    "sg:postcode":"18194",
    "sg:province":"Granada",
    "wof:name":"El Horno De Juan S.c.a",
    "wof:placetype":"venue"
},
  "geometry": {"coordinates":[-3.6461219788,37.148109436],"type":"Point"}
}