{
  "type": "Feature",
  "properties": {
    "iso:country":"ES",
    "sg:address":"Itsasargi Kalea, 16",
    "sg:city":"Portua",
    "sg:orig_category":"Caf\u00c9s, Bares, Cervecer\u00cdas",
    "sg:phone":"+34 943 64 43 62",
    "sg:postcode":"20280",
    "sg:province":"Guip\u00f9zcoa",
    "wof:name":"Aramendia Gil Ana",
    "wof:placetype":"venue"
},
  "geometry": {"coordinates":[-1.793610096,43.3704605103],"type":"Point"}
}