{
  "type": "Feature",
  "properties": {
    "iso:country":"ES",
    "sg:address":"Avda Paz De (la), 77",
    "sg:city":"Logro\u00f1o",
    "sg:orig_category":"Muebles, Minoristas",
    "sg:phone":"+34 941 24 96 48",
    "sg:postcode":"26004",
    "sg:province":"La Rioja",
    "wof:name":"Sancidrian Hervias Jose Ignacio",
    "wof:placetype":"venue"
},
  "geometry": {"coordinates":[-2.4303600788,42.463470459],"type":"Point"}
}