{
  "type": "Feature",
  "properties": {
    "addr:full":"Alam Recalde, 31 Bilbao Vizcaya 48009",
    "addr:housenumber":"31",
    "addr:postcode":"48009",
    "addr:street":"Alam Recalde",
    "iso:country":"ES",
    "sg:address":"Alam Recalde, 31",
    "sg:city":"Bilbao",
    "sg:orig_category":"Abogados",
    "sg:phone":"+34 944 23 90 40",
    "sg:postcode":"48009",
    "sg:province":"Vizcaya",
    "wof:name":"Txurruka Argarate Joseba Andoni",
    "wof:placetype":"venue"
},
  "geometry": {"coordinates":[-2.9344658852,43.2637786865],"type":"Point"}
}