{
  "type": "Feature",
  "properties": {
    "addr:full":"Avda Cami D'onda, 47 Burriana Castell\u00f3n 12530",
    "addr:housenumber":"47",
    "addr:postcode":"12530",
    "addr:street":"Avda Cami D'Onda",
    "iso:country":"ES",
    "sg:address":"Avda Cami D'onda, 47",
    "sg:city":"Burriana",
    "sg:orig_category":"Heladeros",
    "sg:phone":"+34 964 59 15 00",
    "sg:postcode":"12530",
    "sg:province":"Castell\u00f3n",
    "wof:name":"Mac Italia & Talia S.l.",
    "wof:placetype":"venue"
},
  "geometry": {"coordinates":[-0.0895060003,39.8921051025],"type":"Point"}
}