{
  "type": "Feature",
  "properties": {
    "iso:country":"ES",
    "sg:address":"Cami Mar (la), S/n",
    "sg:city":"Pu\u00e7ol",
    "sg:orig_category":"Clubes, Circuitos Y Recintos Para Deportes Mec\u00c1nicos",
    "sg:phone":"+34 961 42 41 66",
    "sg:postcode":"46530",
    "sg:province":"Valencia",
    "sg:website":"www.elplanter.com",
    "wof:name":"Escuela Deportiva El Planter S.l.",
    "wof:placetype":"venue"
},
  "geometry": {"coordinates":[-0.3092789948,39.6157417297],"type":"Point"}
}