{
  "type": "Feature",
  "properties": {
    "addr:full":"Calle de Carde\u00d1osa, 36 Madrid Madrid 28053",
    "addr:housenumber":"36",
    "addr:postcode":"madrid;28053",
    "addr:street":"Calle De Carden\u0303Osa",
    "iso:country":"ES",
    "sg:address":"Calle de Carde\u00d1osa, 36",
    "sg:city":"Madrid",
    "sg:orig_category":"Calefacci\u00d3n Central: Material (fabricaci\u00d3n, Al Por Mayor)",
    "sg:phone":"+34 915 07 09 95",
    "sg:postcode":"28053",
    "sg:province":"Madrid",
    "wof:name":"Saneamientos Garry S.a.",
    "wof:placetype":"venue"
},
  "geometry": {"coordinates":[-3.6721503735,40.3830070496],"type":"Point"}
}