{
  "type": "Feature",
  "properties": {
    "addr:full":"Carr Pau, La, 9 Ciutadella Menorca Islas Baleares 07760",
    "addr:housenumber":"9",
    "addr:postcode":"07760",
    "addr:street":"Carr Pau La",
    "iso:country":"ES",
    "sg:address":"Carr Pau, La, 9",
    "sg:city":"Ciutadella Menorca",
    "sg:orig_category":"Seguros",
    "sg:phone":"+34 971 48 18 95",
    "sg:postcode":"07760",
    "sg:province":"Islas Baleares",
    "wof:name":"Calafat Sastre S.l.",
    "wof:placetype":"venue"
},
  "geometry": {"coordinates":[3.8416149616,40.0027542114],"type":"Point"}
}