{
  "type": "Feature",
  "properties": {
    "iso:country":"ES",
    "sg:address":"Av. Zaragoza, 21",
    "sg:city":"Iru\u00f1a",
    "sg:orig_category":"Abogados",
    "sg:phone":"+34 948 24 78 17",
    "sg:postcode":"31003",
    "sg:province":"Navarra",
    "wof:name":"Arenal Cano Jose Pascual",
    "wof:placetype":"venue"
},
  "geometry": {"coordinates":[-1.6435517073,42.8105545044],"type":"Point"}
}