{
  "type": "Feature",
  "properties": {
    "addr:full":"Calle de Jardin, 7 Montemayor Pililla Valladolid 47320",
    "addr:housenumber":"7",
    "addr:postcode":"47320",
    "addr:street":"Calle De Jardin",
    "iso:country":"ES",
    "sg:address":"Calle de Jardin, 7",
    "sg:city":"Montemayor Pililla",
    "sg:orig_category":"Cajas Para Embalar",
    "sg:phone":"+34 983 69 40 37",
    "sg:postcode":"47320",
    "sg:province":"Valladolid",
    "wof:name":"Caja Rural Del Duero",
    "wof:placetype":"venue"
},
  "geometry": {"coordinates":[-4.4587268829,41.5094451904],"type":"Point"}
}