{
  "type": "Feature",
  "properties": {
    "addr:full":"Avda Justina Y Berdia, 2 Saron Cantabria 39620",
    "addr:housenumber":"2",
    "addr:postcode":"39620",
    "addr:street":"Avda Justina Y Berdia",
    "iso:country":"ES",
    "sg:address":"Avda Justina Y Berdia, 2",
    "sg:city":"Saron",
    "sg:orig_category":"\u00d3ptica: Instrumentos (fabricaci\u00d3n)",
    "sg:phone":"+34 942 56 45 53",
    "sg:postcode":"39620",
    "sg:province":"Cantabria",
    "wof:name":"Optica Saron S.l.",
    "wof:placetype":"venue"
},
  "geometry": {"coordinates":[-3.8507390022,43.3263015747],"type":"Point"}
}