{
  "type": "Feature",
  "properties": {
    "addr:full":"Avda Real De Pinto, 146 Madrid Madrid 28021",
    "addr:housenumber":"146",
    "addr:postcode":"28021",
    "addr:street":"Avda Real De Pinto",
    "iso:country":"ES",
    "sg:address":"Avda Real De Pinto, 146",
    "sg:city":"Madrid",
    "sg:orig_category":"Energ\u00cda Solar Y Nuevas Energ\u00cdas (equipo, Estudios)",
    "sg:phone":"+34 917 95 25 07",
    "sg:postcode":"28021",
    "sg:province":"Madrid",
    "sg:website":"www.solener.com",
    "wof:name":"Soluciones Energeticas S.a.",
    "wof:placetype":"venue"
},
  "geometry": {"coordinates":[-3.7128300667,40.3339385986],"type":"Point"}
}