{
  "type": "Feature",
  "properties": {
    "addr:full":"Redonda, 1 La Carlota C\u00f3rdoba 14100",
    "addr:housenumber":"1",
    "addr:postcode":"14100",
    "addr:street":"Redonda",
    "iso:country":"ES",
    "sg:address":"Redonda, 1",
    "sg:city":"La Carlota",
    "sg:orig_category":"Muebles, Minoristas",
    "sg:phone":"+34 957 30 07 09",
    "sg:postcode":"14100",
    "sg:province":"C\u00f3rdoba",
    "wof:name":"Muebles Y Decoracion Serafin S.l.",
    "wof:placetype":"venue"
},
  "geometry": {"coordinates":[-4.9885048866,37.708190918],"type":"Point"}
}