{
  "type": "Feature",
  "properties": {
    "addr:full":"Cno Vjo Torrent, 36 Aldaia Valencia 46960",
    "addr:housenumber":"36",
    "addr:postcode":"46960",
    "addr:street":"Cno Vjo Torrent",
    "iso:country":"ES",
    "sg:address":"Cno Vjo Torrent, 36",
    "sg:city":"Aldaia",
    "sg:orig_category":"Fabricaci\u00d3n De Instrumentos Y Accesorios Musicales",
    "sg:phone":"+34 961 50 11 82",
    "sg:postcode":"46960",
    "sg:province":"Valencia",
    "sg:website":"www.guitarras-azahar.com",
    "wof:name":"Guitarras Azahar S.l.",
    "wof:placetype":"venue"
},
  "geometry": {"coordinates":[-0.460878998,39.4649238586],"type":"Point"}
}