{
  "type": "Feature",
  "properties": {
    "addr:full":"Calle de Bailen, 7 Portugalete Vizcaya 48920",
    "addr:housenumber":"7",
    "addr:postcode":"48920",
    "addr:street":"Calle De Bailen",
    "iso:country":"ES",
    "sg:address":"Calle de Bailen, 7",
    "sg:city":"Portugalete",
    "sg:orig_category":"Fabricaci\u00d3n De Cortinas Y Visillos",
    "sg:phone":"+34 944 95 33 46",
    "sg:postcode":"48920",
    "sg:province":"Vizcaya",
    "wof:name":"Andoni Calvo Sarabia",
    "wof:placetype":"venue"
},
  "geometry": {"coordinates":[-3.0186247826,43.3189125061],"type":"Point"}
}