{
  "type": "Feature",
  "properties": {
    "addr:full":"Calle de Herradores, 45 San Cristobal De La Laguna Santa Cruz De Tenerife 38201",
    "addr:housenumber":"45",
    "addr:postcode":"38201",
    "addr:street":"Calle De Herradores",
    "iso:country":"ES",
    "sg:address":"Calle de Herradores, 45",
    "sg:city":"San Cristobal De La Laguna",
    "sg:orig_category":"Inmobiliaria (agencias)",
    "sg:phone":"+34 922 26 53 06",
    "sg:postcode":"38201",
    "sg:province":"Santa Cruz De Tenerife",
    "wof:name":"Reyes Criado Angeles",
    "wof:placetype":"venue"
},
  "geometry": {"coordinates":[-16.3189983368,28.489315033],"type":"Point"}
}