{
  "type": "Feature",
  "properties": {
    "addr:full":"Calle de Principe De Vergara, 287 Madrid Madrid 28016",
    "addr:housenumber":"287",
    "addr:postcode":"28016",
    "addr:street":"Calle De Principe De Vergara",
    "iso:country":"ES",
    "sg:address":"Calle de Principe De Vergara, 287",
    "sg:city":"Madrid",
    "sg:orig_category":"\u00d3ptica: Instrumentos (fabricaci\u00d3n)",
    "sg:phone":"+34 913 59 36 19",
    "sg:postcode":"28016",
    "sg:province":"Madrid",
    "wof:name":"San Roman Hurtado Maria Jose",
    "wof:placetype":"venue"
},
  "geometry": {"coordinates":[-3.6768848896,40.4594116211],"type":"Point"}
}