{
  "type": "Feature",
  "properties": {
    "iso:country":"ES",
    "sg:address":"Calle de Balbis, 2",
    "sg:city":"Cari\u00f1o",
    "sg:orig_category":"Navegaci\u00d3n (equipos Fluviales)",
    "sg:phone":"+34 981 40 58 75",
    "sg:postcode":"15360",
    "sg:province":"La Coru\u00f1a",
    "wof:name":"Pescacari\u00f1o S.a.",
    "wof:placetype":"venue"
},
  "geometry": {"coordinates":[-7.8693466187,43.7414398193],"type":"Point"}
}