{
  "type": "Feature",
  "properties": {
    "addr:full":"Av Ragull, 34 S. Cugat Valles Barcelona 08172",
    "addr:housenumber":"34",
    "addr:postcode":"08172",
    "addr:street":"Av Ragull;S. Cugat Valles Barcelona",
    "iso:country":"ES",
    "sg:address":"Av Ragull, 34",
    "sg:city":"S. Cugat Valles",
    "sg:orig_category":"Restaurantes",
    "sg:phone":"+34 936 75 41 62",
    "sg:postcode":"08172",
    "sg:province":"Barcelona",
    "wof:name":"Gomez Lucena Antonio",
    "wof:placetype":"venue"
},
  "geometry": {"coordinates":[2.0900409222,41.4765472412],"type":"Point"}
}