{
  "type": "Feature",
  "properties": {
    "addr:full":"Av Marina, 70 S. Boi Llobregat Barcelona 08830",
    "addr:housenumber":"70",
    "addr:postcode":"08830",
    "addr:street":"Av Marina",
    "iso:country":"ES",
    "sg:address":"Av Marina, 70",
    "sg:city":"S. Boi Llobregat",
    "sg:orig_category":"Aparatos, Material Y Suministros Para Laboratorios",
    "sg:phone":"+34 936 52 66 10",
    "sg:postcode":"08830",
    "sg:province":"Barcelona",
    "sg:website":"www.dycometal.com",
    "wof:name":"Dycometal Equipos De Control De Calidad S.l.",
    "wof:placetype":"venue"
},
  "geometry": {"coordinates":[2.0449779034,41.3480606079],"type":"Point"}
}