{
  "type": "Feature",
  "properties": {
    "addr:full":"Carrer de Sant Ramon, 26 Mas Rampinyo Barcelona 08110",
    "addr:housenumber":"26",
    "addr:postcode":"08110",
    "addr:street":"Carrer De Sant Ramon",
    "iso:country":"ES",
    "sg:address":"Carrer de Sant Ramon, 26",
    "sg:city":"Mas Rampinyo",
    "sg:orig_category":"Quincaller\u00cda (al Por Mayor)",
    "sg:phone":"+34 935 75 29 45",
    "sg:postcode":"08110",
    "sg:province":"Barcelona",
    "wof:name":"Catalana De Ferreteria S.l.",
    "wof:placetype":"venue"
},
  "geometry": {"coordinates":[2.1838870049,41.4973182678],"type":"Point"}
}