{
  "type": "Feature",
  "properties": {
    "addr:full":"Calle de Alibarra, 50 Vitoria-gasteiz \u00c1lava 01010",
    "addr:housenumber":"50",
    "addr:postcode":"01010",
    "addr:street":"Calle De Alibarra",
    "iso:country":"ES",
    "sg:address":"Calle de Alibarra, 50",
    "sg:city":"Vitoria-gasteiz",
    "sg:orig_category":"Cristaler\u00cdas",
    "sg:phone":"+34 945 22 66 76",
    "sg:postcode":"01010",
    "sg:province":"\u00c1lava",
    "sg:website":"www.cristaleriasanmateo.com",
    "wof:name":"Cristaleria San Mateo Vitoria S.l.",
    "wof:placetype":"venue"
},
  "geometry": {"coordinates":[-2.7092394829,42.8657684326],"type":"Point"}
}