{
  "type": "Feature",
  "properties": {
    "addr:full":"Calle de Quesada, 7 Madrid Madrid 28010",
    "addr:housenumber":"7",
    "addr:postcode":"madrid;28010",
    "addr:street":"Calle De Quesada",
    "iso:country":"ES",
    "sg:address":"Calle de Quesada, 7",
    "sg:city":"Madrid",
    "sg:orig_category":"Arquitectos",
    "sg:phone":"+34 915 93 26 26",
    "sg:postcode":"28010",
    "sg:province":"Madrid",
    "wof:name":"Rivero Fernandez Licinio",
    "wof:placetype":"venue"
},
  "geometry": {"coordinates":[-3.7005250454,40.4340057373],"type":"Point"}
}