{
  "type": "Feature",
  "properties": {
    "iso:country":"ES",
    "sg:address":"Paraje Loma Del Lentiscar, S/n",
    "sg:city":"Alfamen",
    "sg:orig_category":"T\u00c9cnicos Veterinarios",
    "sg:phone":"+34 976 62 50 40",
    "sg:postcode":"50461",
    "sg:province":"Zaragoza",
    "wof:name":"Vp Exclusivas Veterinarias S.l.",
    "wof:placetype":"venue"
},
  "geometry": {"coordinates":[-1.2313617468,41.45470047],"type":"Point"}
}