{
  "type": "Feature",
  "properties": {
    "iso:country":"ES",
    "sg:address":"Rbla Principal, 52",
    "sg:city":"Vilanova I La Geltru",
    "sg:orig_category":"Asociaciones, Organismos Culturales Y Socioeducativos",
    "sg:phone":"+34 938 93 88 71",
    "sg:postcode":"08800",
    "sg:province":"Barcelona",
    "wof:name":"Sociedad Cultural Gran Pe\u00f1a",
    "wof:placetype":"venue"
},
  "geometry": {"coordinates":[1.7248330116,41.2238464355],"type":"Point"}
}