{
  "type": "Feature",
  "properties": {
    "iso:country":"ES",
    "sg:address":"Calle de Yuste, 6",
    "sg:city":"Valdemoro",
    "sg:orig_category":"Florister\u00cdas",
    "sg:phone":"+34 918 95 54 40",
    "sg:postcode":"28340",
    "sg:province":"Madrid",
    "wof:name":"Garrido Sevilla Juan Jose",
    "wof:placetype":"venue"
},
  "geometry": {"coordinates":[-3.6738090515,40.1909751892],"type":"Point"}
}