{
  "type": "Feature",
  "properties": {
    "addr:full":"Plaz Crucero, 3 Trespaderne Burgos 09540",
    "addr:housenumber":"3",
    "addr:postcode":"09540",
    "addr:street":"Crucero",
    "iso:country":"ES",
    "sg:address":"Plaz Crucero, 3",
    "sg:city":"Trespaderne",
    "sg:orig_category":"Asociaciones, Organismos Culturales Y Socioeducativos",
    "sg:phone":"+34 947 30 85 67",
    "sg:postcode":"09540",
    "sg:province":"Burgos",
    "wof:name":"Caja De Ahorros Municipal De Burgos",
    "wof:placetype":"venue"
},
  "geometry": {"coordinates":[-3.3904190063,42.8021316528],"type":"Point"}
}