{
  "type": "Feature",
  "properties": {
    "addr:full":"Calle de Velazquez, 12 Valencia Valencia 46018",
    "addr:housenumber":"12",
    "addr:postcode":"46018",
    "addr:street":"Calle De Velazquez",
    "iso:country":"ES",
    "sg:address":"Calle de Velazquez, 12",
    "sg:city":"Valencia",
    "sg:orig_category":"Mec\u00c1nico Del Autom\u00d3vil",
    "sg:phone":"+34 963 59 97 13",
    "sg:postcode":"46018",
    "sg:province":"Valencia",
    "wof:name":"Conejero Millan Antonio",
    "wof:placetype":"venue"
},
  "geometry": {"coordinates":[-0.4016610086,39.4729957581],"type":"Point"}
}