{
  "type": "Feature",
  "properties": {
    "addr:full":"Calle de Joaquin Costa, S/n Alcala Gurrea Huesca 22282",
    "addr:housenumber":"s / n",
    "addr:postcode":"22282",
    "addr:street":"Calle De Joaquin Costa",
    "iso:country":"ES",
    "sg:address":"Calle de Joaquin Costa, S/n",
    "sg:city":"Alcala Gurrea",
    "sg:orig_category":"Carnicer\u00cdas, Carnicer\u00cdas",
    "sg:phone":"+34 974 25 03 00",
    "sg:postcode":"22282",
    "sg:province":"Huesca",
    "wof:name":"Mincholed Lanuza Jose Maria",
    "wof:placetype":"venue"
},
  "geometry": {"coordinates":[-0.6848819852,42.0656204224],"type":"Point"}
}