{
  "type": "Feature",
  "properties": {
    "addr:full":"Barr Mallabiena, 9 Mallabiena Vizcaya 48215",
    "addr:housenumber":"9",
    "addr:postcode":"48215",
    "addr:street":"Mallabiena",
    "iso:country":"ES",
    "sg:address":"Barr Mallabiena, 9",
    "sg:city":"Mallabiena",
    "sg:classifiers":[
        {
            "category":"Manufacturing",
            "subcategory":"Metals",
            "type":"Manufacturing & Wholesale Goods"
        }
    ],
    "sg:phone":"+34 946 21 56 00",
    "sg:postcode":"48215",
    "sg:province":"Vizcaya",
    "sg:tags":[
        "en",
        "fundiciones"
    ],
    "sg:website":"www.flesic.com",
    "wof:name":"Fundicion Nodular Flesic S. A.",
    "wof:placetype":"venue"
},
  "geometry": {"coordinates":[-2.631608963,43.1760597229],"type":"Point"}
}