{
  "type": "Feature",
  "properties": {
    "addr:full":"Elvira Carrera(antes Rasela), 1 Verin Ourense 32600",
    "addr:housenumber":"1",
    "addr:postcode":"32600",
    "addr:street":"Carrera Antes Rasela",
    "iso:country":"ES",
    "sg:address":"Elvira Carrera(antes Rasela), 1",
    "sg:city":"Verin",
    "sg:orig_category":"Chapister\u00cda",
    "sg:phone":"+34 988 41 31 14",
    "sg:postcode":"32600",
    "sg:province":"Ourense",
    "wof:name":"Losada Gonzalez Eduardo",
    "wof:placetype":"venue"
},
  "geometry": {"coordinates":[-7.4335598946,41.9444274902],"type":"Point"}
}