{
  "type": "Feature",
  "properties": {
    "iso:country":"ES",
    "sg:address":"Calle de Ronda, 5",
    "sg:city":"Malaga",
    "sg:orig_category":"Hielo Artificial (fabricaci\u00d3n, Distribuci\u00d3n)",
    "sg:phone":"+34 952 24 30 06",
    "sg:postcode":"29196",
    "sg:province":"M\u00e1laga",
    "wof:name":"Ertma S. A.",
    "wof:placetype":"venue"
},
  "geometry": {"coordinates":[-4.4990830421,36.6997375488],"type":"Point"}
}