{
  "type": "Feature",
  "properties": {
    "addr:full":"Calle de Mu\u00d1oz Capilla, 9 Cordoba C\u00f3rdoba 14001",
    "addr:housenumber":"9",
    "addr:postcode":"14001",
    "addr:street":"Calle De Mun\u0303Oz Capilla;Co\u0301Rdoba",
    "iso:country":"ES",
    "sg:address":"Calle de Mu\u00d1oz Capilla, 9",
    "sg:city":"Cordoba",
    "sg:orig_category":"Grafistas",
    "sg:phone":"+34 957 49 70 41",
    "sg:postcode":"14001",
    "sg:province":"C\u00f3rdoba",
    "sg:website":"www.sitographics.com",
    "wof:name":"Sito Graphics S.l.",
    "wof:placetype":"venue"
},
  "geometry": {"coordinates":[-4.7734332085,37.8878593445],"type":"Point"}
}