{
  "type": "Feature",
  "properties": {
    "iso:country":"ES",
    "sg:address":"Calle de Zurbaran, 13",
    "sg:city":"Ubrique",
    "sg:orig_category":"Confecci\u00d3n : Material, Suministros Y Accesorios",
    "sg:phone":"+34 956 46 09 58",
    "sg:postcode":"11600",
    "sg:province":"C\u00e1diz",
    "wof:name":"Medinilla Carrasco Manuel",
    "wof:placetype":"venue"
},
  "geometry": {"coordinates":[-5.446767807,36.6796951294],"type":"Point"}
}