{
  "type": "Feature",
  "properties": {
    "addr:full":"Ctra Bustarviejo, S/n Miraflores De La Sierra Madrid 28792",
    "addr:postcode":"28792",
    "addr:street":"Ctra Bustarviejo S / N",
    "iso:country":"ES",
    "sg:address":"Ctra Bustarviejo, S/n",
    "sg:city":"Miraflores De La Sierra",
    "sg:orig_category":"Barbacoas Y Accesorios",
    "sg:phone":"+34 918 44 33 83",
    "sg:postcode":"28792",
    "sg:province":"Madrid",
    "wof:name":"Frutos Chozas Manuel",
    "wof:placetype":"venue"
},
  "geometry": {"coordinates":[-3.7596590519,40.8142814636],"type":"Point"}
}