{
  "type": "Feature",
  "properties": {
    "addr:full":"Calle de Juan Bautista Uriarte, 37 Kurtzea Vizcaya 48960",
    "addr:housenumber":"37",
    "addr:postcode":"48960",
    "addr:street":"Calle De Juan Bautista Uriarte",
    "iso:country":"ES",
    "sg:address":"Calle de Juan Bautista Uriarte, 37",
    "sg:city":"Kurtzea",
    "sg:orig_category":"Sociedades, Compa\u00d1\u00cdas Aseguradoras",
    "sg:phone":"+34 944 57 11 49",
    "sg:postcode":"48960",
    "sg:province":"Vizcaya",
    "wof:name":"Seguros Lagun Aro S.a.",
    "wof:placetype":"venue"
},
  "geometry": {"coordinates":[-2.8435440063,43.23046875],"type":"Point"}
}