{
  "type": "Feature",
  "properties": {
    "addr:full":"Calle de Compostela, 3 Coru\u00d1a La Coru\u00f1a 15004",
    "addr:housenumber":"3",
    "addr:postcode":"15004",
    "addr:street":"Calle De Compostela;La Corun\u0303A",
    "iso:country":"ES",
    "sg:address":"Calle de Compostela, 3",
    "sg:city":"Coru\u00d1a",
    "sg:orig_category":"Papeler\u00cdas, Librer\u00cdas",
    "sg:phone":"+34 981 22 44 41",
    "sg:postcode":"15004",
    "sg:province":"La Coru\u00f1a",
    "wof:name":"Ruiz Dans Aurelio",
    "wof:placetype":"venue"
},
  "geometry": {"coordinates":[-8.4052762985,43.3661270142],"type":"Point"}
}