{
  "type": "Feature",
  "properties": {
    "iso:country":"ES",
    "sg:address":"Carr Sant Domenech, 21",
    "sg:city":"Sueca",
    "sg:orig_category":"Iglesia Cat\u00d3lica",
    "sg:phone":"+34 961 70 20 27",
    "sg:postcode":"46410",
    "sg:province":"Valencia",
    "wof:name":"Parroquia De San Pedro Apostol",
    "wof:placetype":"venue"
},
  "geometry": {"coordinates":[-0.3076440096,39.2027435303],"type":"Point"}
}