{
  "type": "Feature",
  "properties": {
    "addr:full":"Urb Torreones Cartaya, 90 Cartaya Huelva 21450",
    "addr:housenumber":"90",
    "addr:postcode":"21450",
    "addr:street":"Urb;Cartaya",
    "iso:country":"ES",
    "sg:address":"Urb Torreones Cartaya, 90",
    "sg:city":"Cartaya",
    "sg:orig_category":"Arquitectos",
    "sg:phone":"+34 959 52 89 17",
    "sg:postcode":"21450",
    "sg:province":"Huelva",
    "wof:name":"Navarrete Lozano Monica Maria",
    "wof:placetype":"venue"
},
  "geometry": {"coordinates":[-7.1528987885,37.2844581604],"type":"Point"}
}