{
  "type": "Feature",
  "properties": {
    "addr:full":"Calle de Cosme Blasco, 7 Zaragoza Zaragoza 50006",
    "addr:housenumber":"7",
    "addr:postcode":"50006",
    "addr:street":"Calle De Cosme Blasco",
    "iso:country":"ES",
    "sg:address":"Calle de Cosme Blasco, 7",
    "sg:city":"Zaragoza",
    "sg:orig_category":"Iluminaci\u00d3n Industrial, Alumbrado P\u00dablico: Material (fabricaci\u00d3n, Importaci\u00d3n)",
    "sg:phone":"+34 976 56 12 73",
    "sg:postcode":"50006",
    "sg:province":"Zaragoza",
    "wof:name":"Natrus S. A.",
    "wof:placetype":"venue"
},
  "geometry": {"coordinates":[-0.8910847902,41.6401596069],"type":"Point"}
}