{
  "type": "Feature",
  "properties": {
    "iso:country":"ES",
    "sg:address":"Calle de Bergantin, 8",
    "sg:city":"Torrevieja",
    "sg:orig_category":"Caf\u00c9s, Bares, Cervecer\u00cdas",
    "sg:phone":"+34 965 71 31 29",
    "sg:postcode":"03180",
    "sg:province":"Alicante",
    "wof:name":"Galindo Riquelme Jose",
    "wof:placetype":"venue"
},
  "geometry": {"coordinates":[-0.6669179797,37.9772491455],"type":"Point"}
}