{
  "type": "Feature",
  "properties": {
    "addr:full":"Calle de Olid, 14 Madrid Madrid 28010",
    "addr:housenumber":"14",
    "addr:postcode":"madrid;28010",
    "addr:street":"Calle De Olid",
    "iso:country":"ES",
    "sg:address":"Calle de Olid, 14",
    "sg:city":"Madrid",
    "sg:orig_category":"Fabricaci\u00d3n, Distribuci\u00d3n De Discos, V\u00cddeodiscos Y Musicassettes",
    "sg:phone":"+34 914 46 34 17",
    "sg:postcode":"28010",
    "sg:province":"Madrid",
    "sg:website":"www.welcomedj.com",
    "wof:name":"Welcome Deejay S.l.",
    "wof:placetype":"venue"
},
  "geometry": {"coordinates":[-3.7016620636,40.4319152832],"type":"Point"}
}