{
  "type": "Feature",
  "properties": {
    "addr:full":"Calle de Ferrol (del), 49 Pinto Madrid 28320",
    "addr:housenumber":"49",
    "addr:postcode":"28320",
    "addr:street":"Calle De Ferrol Del",
    "iso:country":"ES",
    "sg:address":"Calle de Ferrol (del), 49",
    "sg:city":"Pinto",
    "sg:orig_category":"Fabricaci\u00d3n De Moldes Y Modelos",
    "sg:phone":"+34 916 91 02 00",
    "sg:postcode":"28320",
    "sg:province":"Madrid",
    "wof:name":"Compa\u00f1ia De Utillajes Carsan S.a.",
    "wof:placetype":"venue"
},
  "geometry": {"coordinates":[-3.7045791149,40.2465209961],"type":"Point"}
}