{
  "type": "Feature",
  "properties": {
    "addr:full":"Calle de Virrey Lizana, 2 Arnedo La Rioja 26580",
    "addr:housenumber":"2",
    "addr:postcode":"26580",
    "addr:street":"Calle De Virrey Lizana;Rioja",
    "iso:country":"ES",
    "sg:address":"Calle de Virrey Lizana, 2",
    "sg:city":"Arnedo",
    "sg:orig_category":"M\u00c9dicos: Estomatolog\u00cda",
    "sg:phone":"+34 941 38 36 50",
    "sg:postcode":"26580",
    "sg:province":"La Rioja",
    "wof:name":"Revuelta Villalva Luis",
    "wof:placetype":"venue"
},
  "geometry": {"coordinates":[-2.1017739773,42.2270507812],"type":"Point"}
}