{
  "type": "Feature",
  "properties": {
    "iso:country":"ES",
    "sg:address":"Calle de Virrey Lizana, 2",
    "sg:city":"Arnedo",
    "sg:orig_category":"M\u00c9dicos: Estomatolog\u00cda",
    "sg:phone":"+34 941 38 36 50",
    "sg:postcode":"26580",
    "sg:province":"La Rioja",
    "wof:name":"Revuelta Villalva Luis",
    "wof:placetype":"venue"
},
  "geometry": {"coordinates":[-2.1017739773,42.2270507812],"type":"Point"}
}