{
  "type": "Feature",
  "properties": {
    "iso:country":"ES",
    "sg:address":"Calle de Mejico, 8",
    "sg:city":"Salamanca",
    "sg:orig_category":"Turismo: Lugares, Circuitos Y Curiosidades",
    "sg:phone":"+34 923 12 42 88",
    "sg:postcode":"37003",
    "sg:province":"Salamanca",
    "wof:name":"Martin Garcia Francisco",
    "wof:placetype":"venue"
},
  "geometry": {"coordinates":[-5.6557512283,40.9654998779],"type":"Point"}
}