{
  "type": "Feature",
  "properties": {
    "iso:country":"ES",
    "sg:address":"Carr Mossen Cinto Verdaguer, S/n",
    "sg:city":"Borges Blanques",
    "sg:orig_category":"Promotores Constructores",
    "sg:phone":"+34 973 29 09 42",
    "sg:postcode":"25400",
    "sg:province":"Lleida",
    "wof:name":"Promociones Martinez Lombardo S.l.",
    "wof:placetype":"venue"
},
  "geometry": {"coordinates":[0.8742899895,41.5139007568],"type":"Point"}
}