{
  "type": "Feature",
  "properties": {
    "addr:full":"Calle de Maestro Jose Serrano, 3 Valencia Valencia 46005",
    "addr:housenumber":"3",
    "addr:postcode":"46005",
    "addr:street":"Calle De Maestro Jose Serrano",
    "iso:country":"ES",
    "sg:address":"Calle de Maestro Jose Serrano, 3",
    "sg:city":"Valencia",
    "sg:orig_category":"Zapatos (al Por Menor)",
    "sg:phone":"+34 963 74 00 26",
    "sg:postcode":"46005",
    "sg:province":"Valencia",
    "wof:name":"Brodin Alarcon Maria De Los Angeles",
    "wof:placetype":"venue"
},
  "geometry": {"coordinates":[-0.3698790073,39.4636383057],"type":"Point"}
}