{
  "type": "Feature",
  "properties": {
    "addr:full":"Calle de Serapio Mugica, 7 Irun Guip\u00f9zcoa 20302",
    "addr:housenumber":"7",
    "addr:postcode":"20302",
    "addr:street":"Calle De Serapio Mugica;Guipu\u0300Zcoa",
    "iso:country":"ES",
    "sg:address":"Calle de Serapio Mugica, 7",
    "sg:city":"Irun",
    "sg:orig_category":"Panader\u00cdas, Panader\u00cdas",
    "sg:phone":"+34 943 61 29 00",
    "sg:postcode":"20302",
    "sg:province":"Guip\u00f9zcoa",
    "wof:name":"Ogi Beroa",
    "wof:placetype":"venue"
},
  "geometry": {"coordinates":[-1.7955889702,43.3391609192],"type":"Point"}
}