{
  "type": "Feature",
  "properties": {
    "addr:full":"Pase Zarategi De, 54 Donostia-san Sebastian Guip\u00f9zcoa 20015",
    "addr:housenumber":"54",
    "addr:postcode":"20015",
    "iso:country":"ES",
    "sg:address":"Pase Zarategi De, 54",
    "sg:city":"Donostia-san Sebastian",
    "sg:orig_category":"Panader\u00cdas, Panader\u00cdas",
    "sg:phone":"+34 943 29 26 13",
    "sg:postcode":"20015",
    "sg:province":"Guip\u00f9zcoa",
    "wof:name":"Durante Ansa Maria Antonia",
    "wof:placetype":"venue"
},
  "geometry": {"coordinates":[-1.9794000387,43.3173789978],"type":"Point"}
}