{
  "type": "Feature",
  "properties": {
    "addr:full":"Pg Vara De Rey, 22 Eivissa Islas Baleares 07800",
    "addr:housenumber":"22",
    "addr:postcode":"07800",
    "addr:street":"Pg Vara De Rey",
    "iso:country":"ES",
    "sg:address":"Pg Vara De Rey, 22",
    "sg:city":"Eivissa",
    "sg:orig_category":"Fabricaci\u00d3n De Art\u00cdculos Para Papeler\u00cdas",
    "sg:phone":"+34 971 31 18 19",
    "sg:postcode":"07800",
    "sg:province":"Islas Baleares",
    "sg:website":"www.llibreriesvaraderey.com",
    "wof:name":"Mari Bufi Jaime",
    "wof:placetype":"venue"
},
  "geometry": {"coordinates":[1.4328010082,38.909198761],"type":"Point"}
}