{
  "type": "Feature",
  "properties": {
    "iso:country":"ES",
    "sg:address":"Atseden Kalea, 1",
    "sg:city":"Hondarribia",
    "sg:orig_category":"Herboristas (al Por Menor)",
    "sg:phone":"+34 943 64 34 13",
    "sg:postcode":"20280",
    "sg:province":"Guip\u00f9zcoa",
    "wof:name":"Juncal Aguirresarobe Hidalgo  (goiz-argi)",
    "wof:placetype":"venue"
},
  "geometry": {"coordinates":[-1.8018050194,43.3682861328],"type":"Point"}
}