{
  "type": "Feature",
  "properties": {
    "addr:full":"Calle de Etxegorri Kalea, 11 Erandio Vizcaya 48950",
    "addr:housenumber":"11",
    "addr:postcode":"48950",
    "addr:street":"Calle De Etxegorri Kalea",
    "iso:country":"ES",
    "sg:address":"Calle de Etxegorri Kalea, 11",
    "sg:city":"Erandio",
    "sg:orig_category":"Empresas De Pintura Y Revestimientos",
    "sg:phone":"+34 944 17 01 82",
    "sg:postcode":"48950",
    "sg:province":"Vizcaya",
    "wof:name":"Jose Luis Y Oscar Fuentes, C.b.",
    "wof:placetype":"venue"
},
  "geometry": {"coordinates":[-2.9525632858,43.315612793],"type":"Point"}
}