{
  "type": "Feature",
  "properties": {
    "iso:country":"ES",
    "sg:address":"Av D'espanya, 22",
    "sg:city":"Tremp",
    "sg:orig_category":"Bares, Piano",
    "sg:phone":"+34 973 65 10 08",
    "sg:postcode":"25620",
    "sg:province":"Lleida",
    "wof:name":"Peixos Antoni S.l.",
    "wof:placetype":"venue"
},
  "geometry": {"coordinates":[0.8951839805,42.1648292542],"type":"Point"}
}