{
  "type": "Feature",
  "properties": {
    "iso:country":"ES",
    "sg:address":"Carrer de Higini Angles, 4",
    "sg:city":"Tarragona",
    "sg:orig_category":"Asesor\u00cda Fiscal Y Jur\u00cddica",
    "sg:phone":"+34 977 22 02 29",
    "sg:postcode":"43001",
    "sg:province":"Tarragona",
    "wof:name":"Pignatelli Garrigos Maria Cristina",
    "wof:placetype":"venue"
},
  "geometry": {"coordinates":[1.2456380129,41.1173744202],"type":"Point"}
}