{
  "type": "Feature",
  "properties": {
    "addr:full":"Calle de Carretas, 7 Pulgar Toledo 45125",
    "addr:housenumber":"7",
    "addr:postcode":"45125",
    "addr:street":"Calle De Carretas",
    "iso:country":"ES",
    "sg:address":"Calle de Carretas, 7",
    "sg:city":"Pulgar",
    "sg:orig_category":"Forjas Y Altos Hornos",
    "sg:phone":"+34 925 29 21 66",
    "sg:postcode":"45125",
    "sg:province":"Toledo",
    "wof:name":"Jusama Pulgar S.l.",
    "wof:placetype":"venue"
},
  "geometry": {"coordinates":[-4.1516246796,39.6964454651],"type":"Point"}
}