{
  "type": "Feature",
  "properties": {
    "iso:country":"ES",
    "sg:address":"Calle de Leo, 9",
    "sg:city":"Caceres",
    "sg:orig_category":"Enfermeras: Consultas, Atenci\u00d3n A Domicilio",
    "sg:phone":"+34 927 23 27 82",
    "sg:postcode":"10001",
    "sg:province":"C\u00e1ceres",
    "wof:name":"Lopez Garijo Ramon",
    "wof:placetype":"venue"
},
  "geometry": {"coordinates":[-6.3938241005,39.4743461609],"type":"Point"}
}