{
  "type": "Feature",
  "properties": {
    "iso:country":"ES",
    "sg:address":"Goyescas, 39",
    "sg:city":"Valladolid",
    "sg:orig_category":"Centros Empresariales",
    "sg:phone":"+34 983 34 99 10",
    "sg:postcode":"47009",
    "sg:province":"Valladolid",
    "wof:name":"Pardo Delgado S.l.",
    "wof:placetype":"venue"
},
  "geometry": {"coordinates":[-4.7422962189,41.6821975708],"type":"Point"}
}