{
  "type": "Feature",
  "properties": {
    "addr:full":"Calle de Doctor Molina, 45 Abaran Murcia 30550",
    "addr:housenumber":"45",
    "addr:postcode":"30550",
    "addr:street":"Calle De Doctor Molina",
    "iso:country":"ES",
    "sg:address":"Calle de Doctor Molina, 45",
    "sg:city":"Abaran",
    "sg:orig_category":"Arboricultura Y Producci\u00d3n De Frutas",
    "sg:phone":"+34 968 77 00 53",
    "sg:postcode":"30550",
    "sg:province":"Murcia",
    "wof:name":"Tornero Molina Jesus Joaquin",
    "wof:placetype":"venue"
},
  "geometry": {"coordinates":[-1.3987209797,38.2053642273],"type":"Point"}
}