{
  "type": "Feature",
  "properties": {
    "addr:full":"Psaj Marmoles, 6 Malaga M\u00e1laga 29007",
    "addr:housenumber":"6",
    "addr:postcode":"29007",
    "addr:street":"Marmoles;Ma\u0301Laga",
    "iso:country":"ES",
    "sg:address":"Psaj Marmoles, 6",
    "sg:city":"Malaga",
    "sg:orig_category":"Molduras, Junquillos, Listones Y Molduras Perforadas",
    "sg:phone":"+34 952 61 89 23",
    "sg:postcode":"29007",
    "sg:province":"M\u00e1laga",
    "wof:name":"Duran Perez Catalina Pilar",
    "wof:placetype":"venue"
},
  "geometry": {"coordinates":[-4.4265651703,36.7218170166],"type":"Point"}
}