{
  "type": "Feature",
  "properties": {
    "iso:country":"ES",
    "sg:address":"Calle de Blasco Iba\u00d1ez, 11",
    "sg:city":"Chauchina",
    "sg:orig_category":"Transportes Por V\u00cdas Navegables",
    "sg:phone":"+34 958 44 63 65",
    "sg:postcode":"18330",
    "sg:province":"Granada",
    "wof:name":"Exposito Perez Manuel",
    "wof:placetype":"venue"
},
  "geometry": {"coordinates":[-3.7722337246,37.1963424683],"type":"Point"}
}