{
  "type": "Feature",
  "properties": {
    "iso:country":"ES",
    "sg:address":"Calle de Maria Montessori, 1",
    "sg:city":"Cordoba",
    "sg:orig_category":"Automatizaci\u00d3n De Procesos Industriales Y De Edificaci\u00d3n (estudios, Instalaci\u00d3n)",
    "sg:phone":"+34 957 76 70 61",
    "sg:postcode":"14011",
    "sg:province":"C\u00f3rdoba",
    "sg:website":"www.prointegra.com",
    "wof:name":"Pro Integra S.l.",
    "wof:placetype":"venue"
},
  "geometry": {"coordinates":[-4.7961139679,37.8955039978],"type":"Point"}
}