{
  "type": "Feature",
  "properties": {
    "iso:country":"ES",
    "sg:address":"Calle de Real, 35",
    "sg:city":"Guadahortuna",
    "sg:orig_category":"Producci\u00d3n, Venta De Productos De Agricultura Biol\u00d3gica",
    "sg:phone":"+34 958 38 32 64",
    "sg:postcode":"18560",
    "sg:province":"Granada",
    "wof:name":"Navarro Hita Bernardino",
    "wof:placetype":"venue"
},
  "geometry": {"coordinates":[-3.3998830318,37.5574378967],"type":"Point"}
}