{
  "type": "Feature",
  "properties": {
    "addr:full":"Calle de Calvo Sotelo, 31 Santa Cruz De Tenerife Santa Cruz De Tenerife 38006",
    "addr:housenumber":"31",
    "addr:postcode":"38006",
    "addr:street":"Calle De Calvo Sotelo",
    "iso:country":"ES",
    "sg:address":"Calle de Calvo Sotelo, 31",
    "sg:city":"Santa Cruz De Tenerife",
    "sg:orig_category":"Madera Para Construcci\u00d3n E Industria",
    "sg:phone":"+34 922 24 74 46",
    "sg:postcode":"38006",
    "sg:province":"Santa Cruz De Tenerife",
    "wof:name":"Selecta Interiores S.l.",
    "wof:placetype":"venue"
},
  "geometry": {"coordinates":[-16.262134552,28.4689044952],"type":"Point"}
}