{
  "type": "Feature",
  "properties": {
    "iso:country":"ES",
    "sg:address":"Avda Toreros, 19",
    "sg:city":"Madrid",
    "sg:orig_category":"Librer\u00cdas",
    "sg:phone":"+34 917 25 86 10",
    "sg:postcode":"28028",
    "sg:province":"Madrid",
    "wof:name":"Sanz Garcia Rafael",
    "wof:placetype":"venue"
},
  "geometry": {"coordinates":[-3.6694400311,40.4321556091],"type":"Point"}
}