{
  "type": "Feature",
  "properties": {
    "iso:country":"ES",
    "sg:address":"Av Novelda, 10",
    "sg:city":"Elche",
    "sg:orig_category":"Peluqueros: De Se\u00d1oras",
    "sg:phone":"+34 965 43 87 19",
    "sg:postcode":"03206",
    "sg:province":"Alicante",
    "wof:name":"Carrasquilla Linero Ana Maria",
    "wof:placetype":"venue"
},
  "geometry": {"coordinates":[-0.7077329755,38.2698898315],"type":"Point"}
}