{
  "type": "Feature",
  "properties": {
    "addr:full":"Carr Monturull, 8 Seu D'urgell Lleida 25700",
    "addr:housenumber":"8",
    "addr:postcode":"25700",
    "addr:street":"Carr Monturull",
    "iso:country":"ES",
    "sg:address":"Carr Monturull, 8",
    "sg:city":"Seu D'urgell",
    "sg:orig_category":"Alquiler De Apartamentos",
    "sg:phone":"+34 973 35 40 00",
    "sg:postcode":"25700",
    "sg:province":"Lleida",
    "wof:name":"Promociones Urgellet S.a.",
    "wof:placetype":"venue"
},
  "geometry": {"coordinates":[0.6286280155,41.6175880432],"type":"Point"}
}