{
  "type": "Feature",
  "properties": {
    "iso:country":"ES",
    "sg:address":"Calle de Jesus Arambarri, 37",
    "sg:city":"Salamanca",
    "sg:orig_category":"Aguas (distribuci\u00d3n, Servicios)",
    "sg:phone":"+34 923 18 10 25",
    "sg:postcode":"37003",
    "sg:province":"Salamanca",
    "wof:name":"Vicente Benito Jose",
    "wof:placetype":"venue"
},
  "geometry": {"coordinates":[-5.6417031288,40.9710998535],"type":"Point"}
}