{
  "type": "Feature",
  "properties": {
    "addr:full":"Av Barcelona, 169 Molins Rei Barcelona 08750",
    "addr:housenumber":"169",
    "addr:postcode":"08750",
    "addr:street":"Av Barcelona;Barcelona",
    "iso:country":"ES",
    "sg:address":"Av Barcelona, 169",
    "sg:city":"Molins Rei",
    "sg:orig_category":"Laboratorios",
    "sg:phone":"+34 936 80 19 94",
    "sg:postcode":"08750",
    "sg:province":"Barcelona",
    "wof:name":"Manzanedo Sanchez Lourdes",
    "wof:placetype":"venue"
},
  "geometry": {"coordinates":[2.0320899487,41.398979187],"type":"Point"}
}