{
  "type": "Feature",
  "properties": {
    "iso:country":"ES",
    "sg:address":"Plaz Espa\u00d1a, 1",
    "sg:city":"Almeida De Sayago",
    "sg:orig_category":"Bibliotecas, Mediatecas",
    "sg:phone":"+34 980 61 20 03",
    "sg:postcode":"49210",
    "sg:province":"Zamora",
    "wof:name":"Ayuntamiento De Almeida",
    "wof:placetype":"venue"
},
  "geometry": {"coordinates":[-6.0744638443,41.2656326294],"type":"Point"}
}