{
  "type": "Feature",
  "properties": {
    "addr:full":"Ctra General Del Sur, Km. 0033,8 Cruce De Arinaga Las Palmas 35118",
    "addr:postcode":"35118",
    "addr:street":"Ctra General Del Sur Km. 0033,8 Cruce De",
    "iso:country":"ES",
    "sg:address":"Ctra General Del Sur, Km. 0033,8",
    "sg:city":"Cruce De Arinaga",
    "sg:orig_category":"Fabricaci\u00d3n, Venta, Instalaci\u00d3n De R\u00d3tulos, De R\u00d3tulos Luminosos",
    "sg:phone":"+34 928 12 20 92",
    "sg:postcode":"35118",
    "sg:province":"Las Palmas",
    "wof:name":"Mercuri Public S.l.",
    "wof:placetype":"venue"
},
  "geometry": {"coordinates":[-15.4314250946,27.8662776947],"type":"Point"}
}