{
  "type": "Feature",
  "properties": {
    "iso:country":"ES",
    "sg:address":"Avda Salinetas (de), S/n",
    "sg:city":"Petrer",
    "sg:orig_category":"Agentes, Concesionarios Y Sucursales De Veh\u00cdculos",
    "sg:phone":"+34 965 37 13 50",
    "sg:postcode":"03610",
    "sg:province":"Alicante",
    "wof:name":"Automoviles Murcia S. L.",
    "wof:placetype":"venue"
},
  "geometry": {"coordinates":[-0.7708359957,38.4771270752],"type":"Point"}
}