{
  "type": "Feature",
  "properties": {
    "iso:country":"ES",
    "sg:address":"Cant Molins, 11",
    "sg:city":"Ferrol",
    "sg:orig_category":"Fabricaci\u00d3n De Juguetes Autom\u00c1ticos",
    "sg:phone":"+34 981 35 52 43",
    "sg:postcode":"15403",
    "sg:province":"La Coru\u00f1a",
    "wof:name":"Escolante Tellado Loureda S.a.",
    "wof:placetype":"venue"
},
  "geometry": {"coordinates":[-8.2273387909,43.4868507385],"type":"Point"}
}