{
  "type": "Feature",
  "properties": {
    "addr:full":"Luga Autovia 92, Km. 0221,0 Guadix Granada 18500",
    "addr:postcode":"18500",
    "addr:street":"Autovia 92 Km. 0221,0",
    "iso:country":"ES",
    "sg:address":"Luga Autovia 92, Km. 0221,0",
    "sg:city":"Guadix",
    "sg:orig_category":"Carnicer\u00cdas, Carnicer\u00cdas",
    "sg:phone":"+34 958 66 52 08",
    "sg:postcode":"18500",
    "sg:province":"Granada",
    "sg:website":"www.jamonesgranadul.com",
    "wof:name":"Jamones Viuda De Rodriguez S.l.",
    "wof:placetype":"venue"
},
  "geometry": {"coordinates":[-3.1343688965,37.303894043],"type":"Point"}
}