{
  "type": "Feature",
  "properties": {
    "addr:full":"Cmno Cabaldos, 76 Zaragoza Zaragoza 50013",
    "addr:housenumber":"76",
    "addr:postcode":"50013",
    "addr:street":"Cmno Cabaldos",
    "iso:country":"ES",
    "sg:address":"Cmno Cabaldos, 76",
    "sg:city":"Zaragoza",
    "sg:orig_category":"Pescader\u00cdas (al Por Menor)",
    "sg:phone":"+34 976 42 42 23",
    "sg:postcode":"50013",
    "sg:province":"Zaragoza",
    "wof:name":"Lobaco Ortiz Angel",
    "wof:placetype":"venue"
},
  "geometry": {"coordinates":[-0.8690760136,41.6392669678],"type":"Point"}
}