{
  "type": "Feature",
  "properties": {
    "addr:full":"Calle de Maestro Moreno Torroba, 32 Churriana M\u00e1laga 29140",
    "addr:housenumber":"32",
    "addr:postcode":"29140",
    "addr:street":"Calle De Maestro Moreno Torroba",
    "iso:country":"ES",
    "sg:address":"Calle de Maestro Moreno Torroba, 32",
    "sg:city":"Churriana",
    "sg:orig_category":"Transportes Por V\u00cdas Navegables",
    "sg:phone":"+34 952 62 16 07",
    "sg:postcode":"29140",
    "sg:province":"M\u00e1laga",
    "wof:name":"Medina Fernandez Antonio",
    "wof:placetype":"venue"
},
  "geometry": {"coordinates":[-4.5035462379,36.6629447937],"type":"Point"}
}