{
  "type": "Feature",
  "properties": {
    "addr:full":"Avda Andalucia, 2 Estepona M\u00e1laga 29680",
    "addr:housenumber":"2",
    "addr:postcode":"29680",
    "addr:street":"Avda Andalucia",
    "iso:country":"ES",
    "sg:address":"Avda Andalucia, 2",
    "sg:city":"Estepona",
    "sg:orig_category":"Persianas Interiores, Exteriores",
    "sg:phone":"+34 952 79 47 61",
    "sg:postcode":"29680",
    "sg:province":"M\u00e1laga",
    "wof:name":"Sanchez Romero Juan",
    "wof:placetype":"venue"
},
  "geometry": {"coordinates":[-5.1400737762,36.4284553528],"type":"Point"}
}