{
  "type": "Feature",
  "properties": {
    "iso:country":"ES",
    "sg:address":"Carr Pinar (del), S/n",
    "sg:city":"Almussafes",
    "sg:orig_category":"Promotores Constructores",
    "sg:phone":"+34 961 79 42 16",
    "sg:postcode":"46440",
    "sg:province":"Valencia",
    "wof:name":"Construcciones Rafael Lopez Alepuz S.l.",
    "wof:placetype":"venue"
},
  "geometry": {"coordinates":[-0.4111840129,39.2922134399],"type":"Point"}
}