{
  "type": "Feature",
  "properties": {
    "addr:full":"C/ Vicente Blasco Iba\u00d1ez, 59 Elche Alicante 03201",
    "addr:housenumber":"59",
    "addr:postcode":"03201",
    "addr:street":"C / Vicente Blasco Iban\u0303Ez",
    "iso:country":"ES",
    "sg:address":"C/ Vicente Blasco Iba\u00d1ez, 59",
    "sg:city":"Elche",
    "sg:orig_category":"Cajas De Ahorro",
    "sg:phone":"+34 965 46 11 51",
    "sg:postcode":"03201",
    "sg:province":"Alicante",
    "sg:website":"www.cam.es",
    "wof:name":"Caja De Ahorros Del Mediterraneo",
    "wof:placetype":"venue"
},
  "geometry": {"coordinates":[-0.7060580254,38.267993927],"type":"Point"}
}