{
  "type": "Feature",
  "properties": {
    "addr:full":"Rua Curros Enriquez (poeta), 7 Lugo Lugo 27004",
    "addr:housenumber":"7",
    "addr:postcode":"27004",
    "addr:street":"Rua Curros Enriquez Poeta",
    "iso:country":"ES",
    "sg:address":"Rua Curros Enriquez (poeta), 7",
    "sg:city":"Lugo",
    "sg:orig_category":"Servicios Gsm",
    "sg:phone":"+34 982 26 50 29",
    "sg:postcode":"27004",
    "sg:province":"Lugo",
    "wof:name":"Quiroga Pozo Ana",
    "wof:placetype":"venue"
},
  "geometry": {"coordinates":[-7.5658612251,43.0194511414],"type":"Point"}
}