{
  "type": "Feature",
  "properties": {
    "addr:full":"Barr Urizar, 21 Urizar Vizcaya 48620",
    "addr:housenumber":"21",
    "addr:postcode":"48620",
    "addr:street":"Barr Urizar",
    "iso:country":"ES",
    "sg:address":"Barr Urizar, 21",
    "sg:city":"Urizar",
    "sg:orig_category":"Poller\u00cda Y Caza (al Por Menor)",
    "sg:phone":"+34 946 87 90 31",
    "sg:postcode":"48620",
    "sg:province":"Vizcaya",
    "wof:name":"Elortegui Villalabeitia Anselmo",
    "wof:placetype":"venue"
},
  "geometry": {"coordinates":[-2.9025850296,43.4118118286],"type":"Point"}
}