{
  "type": "Feature",
  "properties": {
    "iso:country":"ES",
    "sg:address":"Carrer de Julian Besteiro, 9",
    "sg:city":"Barcelona",
    "sg:orig_category":"Peluquer\u00cdas, Peluquer\u00cda Mixta",
    "sg:phone":"+34 933 08 26 08",
    "sg:postcode":"08020",
    "sg:province":"Barcelona",
    "wof:name":"Barrena Barrena Esperanza",
    "wof:placetype":"venue"
},
  "geometry": {"coordinates":[2.19759202,41.4156188965],"type":"Point"}
}