{
  "type": "Feature",
  "properties": {
    "addr:full":"Ses Germanies, 14 Binissalem Islas Baleares 07350",
    "addr:housenumber":"14",
    "addr:postcode":"07350",
    "addr:street":"Germanies",
    "iso:country":"ES",
    "sg:address":"Ses Germanies, 14",
    "sg:city":"Binissalem",
    "sg:orig_category":"Electricidad: Instaladores",
    "sg:phone":"+34 971 88 63 36",
    "sg:postcode":"07350",
    "sg:province":"Islas Baleares",
    "wof:name":"Llabres Visiedo Miguel Angel",
    "wof:placetype":"venue"
},
  "geometry": {"coordinates":[2.8486099243,39.6871185303],"type":"Point"}
}