{
  "type": "Feature",
  "properties": {
    "addr:full":"Avda Primero De Mayo, S/n Don Benito Badajoz 06400",
    "addr:housenumber":"s / n",
    "addr:postcode":"06400",
    "addr:street":"Avda Primero De Mayo",
    "iso:country":"ES",
    "sg:address":"Avda Primero De Mayo, S/n",
    "sg:city":"Don Benito",
    "sg:orig_category":"Iglesia Cat\u00d3lica",
    "sg:phone":"+34 924 80 08 91",
    "sg:postcode":"06400",
    "sg:province":"Badajoz",
    "wof:name":"Parroquia De Santa Maria",
    "wof:placetype":"venue"
},
  "geometry": {"coordinates":[-5.8581390381,38.9605102539],"type":"Point"}
}