{
  "type": "Feature",
  "properties": {
    "iso:country":"ES",
    "sg:address":"Calle de Donoso Cortes, 20",
    "sg:city":"Madrid",
    "sg:orig_category":"M\u00c9dicos: Estomatolog\u00cda",
    "sg:phone":"+34 915 94 11 15",
    "sg:postcode":"28015",
    "sg:province":"Madrid",
    "wof:name":"Salvador Parra Cesar",
    "wof:placetype":"venue"
},
  "geometry": {"coordinates":[-3.7077360153,40.4362831116],"type":"Point"}
}