{
  "type": "Feature",
  "properties": {
    "iso:country":"ES",
    "sg:address":"Pso. Maritimo, 88",
    "sg:city":"Torre Mar",
    "sg:orig_category":"Asesor\u00cda Sobre Comunicaci\u00d3n De Empresas",
    "sg:phone":"+34 952 54 06 10",
    "sg:postcode":"29740",
    "sg:province":"M\u00e1laga",
    "wof:name":"Expatriate Advisory Service Espana S.l.",
    "wof:placetype":"venue"
},
  "geometry": {"coordinates":[-4.3679728508,36.719833374],"type":"Point"}
}