{
  "type": "Feature",
  "properties": {
    "addr:full":"Calle de Julian Camarillo, 48 Madrid Madrid 28037",
    "addr:housenumber":"48",
    "addr:postcode":"madrid;28037",
    "addr:street":"Calle De Julian Camarillo",
    "iso:country":"ES",
    "sg:address":"Calle de Julian Camarillo, 48",
    "sg:city":"Madrid",
    "sg:orig_category":"Tintorer\u00cdas, Limpieza En Seco",
    "sg:phone":"+34 913 04 46 99",
    "sg:postcode":"28037",
    "sg:province":"Madrid",
    "wof:name":"Lavanderias Gr S.l.",
    "wof:placetype":"venue"
},
  "geometry": {"coordinates":[-3.618185997,40.4380989075],"type":"Point"}
}