{
  "type": "Feature",
  "properties": {
    "addr:full":"Calle de Virgen De Nuria, 13 Madrid Madrid 28027",
    "addr:housenumber":"13",
    "addr:postcode":"madrid;28027",
    "addr:street":"Calle De Virgen De Nuria",
    "iso:country":"ES",
    "sg:address":"Calle de Virgen De Nuria, 13",
    "sg:city":"Madrid",
    "sg:orig_category":"Fotocopias, Reprograf\u00cda",
    "sg:phone":"+34 914 03 79 28",
    "sg:postcode":"28027",
    "sg:province":"Madrid",
    "sg:website":"www.caverocad.com",
    "wof:name":"Reproducciones Cavero S. A.",
    "wof:placetype":"venue"
},
  "geometry": {"coordinates":[-3.6522579193,40.4365501404],"type":"Point"}
}