{
  "type": "Feature",
  "properties": {
    "addr:full":"Calle de Bergantin, 8 Palmones C\u00e1diz 11379",
    "addr:housenumber":"8",
    "addr:postcode":"11379",
    "addr:street":"Calle De Bergantin;Ca\u0301Diz",
    "iso:country":"ES",
    "sg:address":"Calle de Bergantin, 8",
    "sg:city":"Palmones",
    "sg:orig_category":"Negocio De Enlosados, Soler\u00cdas",
    "sg:phone":"+34 956 67 86 42",
    "sg:postcode":"11379",
    "sg:province":"C\u00e1diz",
    "wof:name":"Godygres S.l.",
    "wof:placetype":"venue"
},
  "geometry": {"coordinates":[-5.4433879852,36.1781768799],"type":"Point"}
}