{
  "type": "Feature",
  "properties": {
    "iso:country":"ES",
    "sg:address":"Ptda Rebalso, Km. 0032,0",
    "sg:city":"Hondon Nieves",
    "sg:orig_category":"Trabajos De Asfalto, De Alquitr\u00c1n Y Asfalto",
    "sg:phone":"+34 966 67 71 41",
    "sg:postcode":"03688",
    "sg:province":"Alicante",
    "wof:name":"Obras Y Asfaltos Ike S.l.",
    "wof:placetype":"venue"
},
  "geometry": {"coordinates":[-1.0403139591,38.3488845825],"type":"Point"}
}