{
  "type": "Feature",
  "properties": {
    "iso:country":"ES",
    "sg:address":"Avda San Telmo, 5",
    "sg:city":"Palencia",
    "sg:orig_category":"Molduras, Junquillos, Listones Y Molduras Perforadas",
    "sg:phone":"+34 979 72 04 52",
    "sg:postcode":"34004",
    "sg:province":"Palencia",
    "wof:name":"Frias Diago Ramon",
    "wof:placetype":"venue"
},
  "geometry": {"coordinates":[-4.5224218369,41.9979972839],"type":"Point"}
}