{
  "type": "Feature",
  "properties": {
    "iso:country":"ES",
    "sg:address":"Calle de Bravo Murillo, 46",
    "sg:city":"Villanueva Serena",
    "sg:orig_category":"Empresas De Carpinter\u00cda De Madera",
    "sg:phone":"+34 924 84 00 87",
    "sg:postcode":"06700",
    "sg:province":"Badajoz",
    "wof:name":"Santano Pino S.l.",
    "wof:placetype":"venue"
},
  "geometry": {"coordinates":[-5.7965798378,38.9797439575],"type":"Point"}
}