{
  "type": "Feature",
  "properties": {
    "addr:full":"Carrer de Tisso, 2 Barcelona Barcelona 08016",
    "addr:housenumber":"2",
    "addr:postcode":"08016",
    "addr:street":"Carrer De Tisso",
    "iso:country":"ES",
    "sg:address":"Carrer de Tisso, 2",
    "sg:city":"Barcelona",
    "sg:orig_category":"Cajas De Ahorro",
    "sg:phone":"+34 933 59 58 10",
    "sg:postcode":"08016",
    "sg:province":"Barcelona",
    "sg:website":"www.lacaixa.es",
    "wof:name":"Caixa D'estalvis I Pensions De Barcelona",
    "wof:placetype":"venue"
},
  "geometry": {"coordinates":[2.1853010654,41.4427871704],"type":"Point"}
}