{
  "type": "Feature",
  "properties": {
    "addr:full":"Cmno Palmita (la), 13 Tejina Santa Cruz De Tenerife 38260",
    "addr:housenumber":"13",
    "addr:postcode":"38260",
    "addr:street":"Cmno Palmita La",
    "iso:country":"ES",
    "sg:address":"Cmno Palmita (la), 13",
    "sg:city":"Tejina",
    "sg:orig_category":"Asesor\u00cda De Formaci\u00d3n Y Gesti\u00d3n De Personal",
    "sg:phone":"+34 922 54 31 55",
    "sg:postcode":"38260",
    "sg:province":"Santa Cruz De Tenerife",
    "wof:name":"Dominguez Sanchez Juana Maria",
    "wof:placetype":"venue"
},
  "geometry": {"coordinates":[-16.3658924103,28.5348052979],"type":"Point"}
}