{
  "type": "Feature",
  "properties": {
    "addr:full":"Calle de Emilio Castelar, 10 Alcazar S. Juan Ciudad Real 13600",
    "addr:housenumber":"10",
    "addr:postcode":"13600",
    "addr:street":"Calle De Emilio Castelar;Alcazar S. Juan Ciudad Real",
    "iso:country":"ES",
    "sg:address":"Calle de Emilio Castelar, 10",
    "sg:city":"Alcazar S. Juan",
    "sg:orig_category":"Lencer\u00cda Femenina, Corseter\u00cda, Trajes De Ba\u00d1o (al Por Menor)",
    "sg:phone":"+34 926 54 78 80",
    "sg:postcode":"13600",
    "sg:province":"Ciudad Real",
    "wof:name":"Parre\u00f1o Cobo Irene",
    "wof:placetype":"venue"
},
  "geometry": {"coordinates":[-3.2094430923,39.3904342651],"type":"Point"}
}