{
  "type": "Feature",
  "properties": {
    "addr:full":"Calle de Reloj, 16 Madrid Madrid 28013",
    "addr:housenumber":"16",
    "addr:postcode":"madrid;28013",
    "addr:street":"Calle De Reloj",
    "iso:country":"ES",
    "sg:address":"Calle de Reloj, 16",
    "sg:city":"Madrid",
    "sg:orig_category":"Arquitectos",
    "sg:phone":"+34 915 48 06 93",
    "sg:postcode":"28013",
    "sg:province":"Madrid",
    "wof:name":"Ripoll Garcia-mansilla Jose Ignacio",
    "wof:placetype":"venue"
},
  "geometry": {"coordinates":[-3.7114779949,40.4218444824],"type":"Point"}
}