{
  "type": "Feature",
  "properties": {
    "addr:full":"C/ Josep Balaguer, 63 Inca Islas Baleares 07300",
    "addr:housenumber":"63",
    "addr:postcode":"07300",
    "addr:street":"C / Josep Balaguer",
    "iso:country":"ES",
    "sg:address":"C/ Josep Balaguer, 63",
    "sg:city":"Inca",
    "sg:orig_category":"Molduras, Junquillos, Listones Y Molduras Perforadas",
    "sg:phone":"+34 971 50 29 45",
    "sg:postcode":"07300",
    "sg:province":"Islas Baleares",
    "wof:name":"Bodega Denis S.l.",
    "wof:placetype":"venue"
},
  "geometry": {"coordinates":[2.917361021,39.7213058472],"type":"Point"}
}