{
  "type": "Feature",
  "properties": {
    "addr:full":"Carr Barcelona, 64 Balaguer Lleida 25600",
    "addr:housenumber":"64",
    "addr:postcode":"25600",
    "addr:street":"Carr Barcelona",
    "iso:country":"ES",
    "sg:address":"Carr Barcelona, 64",
    "sg:city":"Balaguer",
    "sg:orig_category":"Caf\u00c9s, Bares, Cervecer\u00cdas",
    "sg:phone":"+34 973 44 30 48",
    "sg:postcode":"25600",
    "sg:province":"Lleida",
    "wof:name":"Barbar Cafeteria S.c.p.",
    "wof:placetype":"venue"
},
  "geometry": {"coordinates":[0.8110679984,41.7872314453],"type":"Point"}
}