{
  "type": "Feature",
  "properties": {
    "addr:full":"Av L'hospital Militar, 188 Barcelona Barcelona 08023",
    "addr:housenumber":"188",
    "addr:postcode":"08023",
    "addr:street":"Av L'Hospital Militar",
    "iso:country":"ES",
    "sg:address":"Av L'hospital Militar, 188",
    "sg:city":"Barcelona",
    "sg:orig_category":"Farmacias",
    "sg:phone":"+34 932 84 76 51",
    "sg:postcode":"08023",
    "sg:province":"Barcelona",
    "wof:name":"Armet Sampere Patricia",
    "wof:placetype":"venue"
},
  "geometry": {"coordinates":[2.1406440735,41.4200019836],"type":"Point"}
}