{
  "type": "Feature",
  "properties": {
    "iso:country":"ES",
    "sg:address":"Calle de Epalza Viuda De, 9",
    "sg:city":"Bilbao",
    "sg:orig_category":"Fabricaci\u00d3n, Distribuci\u00d3n De Discos, V\u00cddeodiscos Y Musicassettes",
    "sg:phone":"+34 946 79 03 27",
    "sg:postcode":"48005",
    "sg:province":"Vizcaya",
    "sg:website":"www.flamingo60srecords.com",
    "wof:name":"Alonso Izquierdo Jorge",
    "wof:placetype":"venue"
},
  "geometry": {"coordinates":[-2.9229972363,43.2617034912],"type":"Point"}
}