{
  "type": "Feature",
  "properties": {
    "iso:country":"ES",
    "sg:address":"Calle de Leon Moyano, 2",
    "sg:city":"Navalmoral Mata",
    "sg:orig_category":"Sociedades, Compa\u00d1\u00cdas Aseguradoras",
    "sg:phone":"+34 927 53 53 69",
    "sg:postcode":"10300",
    "sg:province":"C\u00e1ceres",
    "wof:name":"Ocaso S.a. Compa\u00f1ia De Seguros Y Reaseguros",
    "wof:placetype":"venue"
},
  "geometry": {"coordinates":[-5.5407991409,39.8906593323],"type":"Point"}
}