{
  "type": "Feature",
  "properties": {
    "addr:full":"Luga Poligono Industrial, S/n Cabanillas Campo Guadalajara 19171",
    "addr:postcode":"19171",
    "addr:street":"Poligono Industrial S / N",
    "iso:country":"ES",
    "sg:address":"Luga Poligono Industrial, S/n",
    "sg:city":"Cabanillas Campo",
    "sg:orig_category":"Art\u00cdculos De Limpieza Y De Cocina (fabricaci\u00d3n, Al Por Mayor)",
    "sg:phone":"+34 949 20 13 16",
    "sg:postcode":"19171",
    "sg:province":"Guadalajara",
    "wof:name":"Quimitec Suministros Quimicos Y Tecnicas De Mantenimiento Cb.",
    "wof:placetype":"venue"
},
  "geometry": {"coordinates":[-3.2194590569,40.5990333557],"type":"Point"}
}