{
  "type": "Feature",
  "properties": {
    "addr:full":"Avda Chapi, 63 Elda Alicante 03600",
    "addr:housenumber":"63",
    "addr:postcode":"03600",
    "addr:street":"Avda Chapi",
    "iso:country":"ES",
    "sg:address":"Avda Chapi, 63",
    "sg:city":"Elda",
    "sg:orig_category":"Peluquer\u00cdas, Peluquer\u00cda Mixta",
    "sg:phone":"+34 965 38 09 55",
    "sg:postcode":"03600",
    "sg:province":"Alicante",
    "wof:name":"Xekix Peluqueria Unisex C.b.",
    "wof:placetype":"venue"
},
  "geometry": {"coordinates":[-0.7922580242,38.4725341797],"type":"Point"}
}