{
  "type": "Feature",
  "properties": {
    "addr:full":"Calle de Jordan, 48 Lomo Los Frailes Las Palmas 35018",
    "addr:housenumber":"48",
    "addr:postcode":"35018",
    "addr:street":"Calle De Jordan;Frailes Las",
    "iso:country":"ES",
    "sg:address":"Calle de Jordan, 48",
    "sg:city":"Lomo Los Frailes",
    "sg:orig_category":"Peluqueros: De Se\u00d1oras",
    "sg:phone":"+34 928 43 74 46",
    "sg:postcode":"35018",
    "sg:province":"Las Palmas",
    "wof:name":"Alba Santana Concepcion",
    "wof:placetype":"venue"
},
  "geometry": {"coordinates":[-15.4300060272,28.1248226166],"type":"Point"}
}