{
  "type": "Feature",
  "properties": {
    "addr:full":"General Franco, 18 San Clodio Lugo 27310",
    "addr:housenumber":"18",
    "addr:postcode":"27310",
    "addr:street":"Franco",
    "iso:country":"ES",
    "sg:address":"General Franco, 18",
    "sg:city":"San Clodio",
    "sg:orig_category":"Ropa Para Se\u00d1oras Y Caballeros (al Por Menor)",
    "sg:phone":"+34 982 43 89 92",
    "sg:postcode":"27310",
    "sg:province":"Lugo",
    "wof:name":"Rodriguez Rodriguez Jose",
    "wof:placetype":"venue"
},
  "geometry": {"coordinates":[-7.2875328064,42.4658279419],"type":"Point"}
}