{
  "type": "Feature",
  "properties": {
    "iso:country":"ES",
    "sg:address":"Calle de Prado Del Rey, 1",
    "sg:city":"Ubrique",
    "sg:orig_category":"Fabricaci\u00d3n De Sobres, Bolsas Y Fundas",
    "sg:phone":"+34 956 46 09 34",
    "sg:postcode":"11600",
    "sg:province":"C\u00e1diz",
    "wof:name":"Bolsos Leip S. L.",
    "wof:placetype":"venue"
},
  "geometry": {"coordinates":[-5.4489951134,36.6771850586],"type":"Point"}
}