{
  "type": "Feature",
  "properties": {
    "addr:full":"Carrer de Torres Jordi (de), 14 Tarragona Tarragona 43005",
    "addr:housenumber":"14",
    "addr:postcode":"43005",
    "addr:street":"Carrer De Torres Jordi De",
    "iso:country":"ES",
    "sg:address":"Carrer de Torres Jordi (de), 14",
    "sg:city":"Tarragona",
    "sg:orig_category":"Farmacias",
    "sg:phone":"+34 977 21 18 78",
    "sg:postcode":"43005",
    "sg:province":"Tarragona",
    "wof:name":"Tortajada Garcia Cristina",
    "wof:placetype":"venue"
},
  "geometry": {"coordinates":[1.2407619953,41.1121520996],"type":"Point"}
}