{
  "type": "Feature",
  "properties": {
    "iso:country":"ES",
    "sg:address":"Hirigoien Kalea, 12",
    "sg:city":"Lazkao",
    "sg:orig_category":"Mercer\u00cda, Lencer\u00cda (al Por Menor)",
    "sg:phone":"+34 943 16 06 82",
    "sg:postcode":"20210",
    "sg:province":"Guip\u00f9zcoa",
    "wof:name":"Engracia Insausti Mendizabal",
    "wof:placetype":"venue"
},
  "geometry": {"coordinates":[-2.1859500408,43.0323562622],"type":"Point"}
}