{
  "type": "Feature",
  "properties": {
    "addr:full":"Calle de Barquillo, 15 Madrid Madrid 28004",
    "addr:housenumber":"15",
    "addr:postcode":"madrid;28004",
    "addr:street":"Calle De Barquillo",
    "iso:country":"ES",
    "sg:address":"Calle de Barquillo, 15",
    "sg:city":"Madrid",
    "sg:orig_category":"Caf\u00c9s, Bares, Cervecer\u00cdas",
    "sg:phone":"+34 915 22 72 77",
    "sg:postcode":"28004",
    "sg:province":"Madrid",
    "wof:name":"Lucar S.l.",
    "wof:placetype":"venue"
},
  "geometry": {"coordinates":[-3.6957056522,40.4215126038],"type":"Point"}
}