{
  "type": "Feature",
  "properties": {
    "iso:country":"ES",
    "sg:address":"Ctra Trujillo, 2",
    "sg:city":"Plasencia",
    "sg:orig_category":"Molduras, Junquillos, Listones Y Molduras Perforadas",
    "sg:phone":"+34 927 42 31 80",
    "sg:postcode":"10600",
    "sg:province":"C\u00e1ceres",
    "wof:name":"Perez Garcia Francisco",
    "wof:placetype":"venue"
},
  "geometry": {"coordinates":[-6.1018719673,40.0159111023],"type":"Point"}
}