{
  "type": "Feature",
  "properties": {
    "addr:full":"Rua Vidueiro, 42 Tilos La Coru\u00f1a 15894",
    "addr:housenumber":"42",
    "addr:postcode":"15894",
    "addr:street":"Rua Vidueiro;La Corun\u0303A",
    "iso:country":"ES",
    "sg:address":"Rua Vidueiro, 42",
    "sg:city":"Tilos",
    "sg:orig_category":"Asilos De Ancianos. Centros Privados",
    "sg:phone":"+34 981 80 10 59",
    "sg:postcode":"15894",
    "sg:province":"La Coru\u00f1a",
    "wof:name":"Pamas 3 S.l.",
    "wof:placetype":"venue"
},
  "geometry": {"coordinates":[-8.5459394455,42.8326034546],"type":"Point"}
}