{
  "type": "Feature",
  "properties": {
    "addr:full":"Plaz Gernikako Arbola, 1 Urretxu Guip\u00f9zcoa 20700",
    "addr:housenumber":"1",
    "addr:postcode":"20700",
    "addr:street":"Plaz Gernikako Arbola;Guipu\u0300Zcoa",
    "iso:country":"ES",
    "sg:address":"Plaz Gernikako Arbola, 1",
    "sg:city":"Urretxu",
    "sg:orig_category":"Bisuter\u00cda, Joyer\u00cda, Relojer\u00cda (al Por Menor)",
    "sg:phone":"+34 943 72 18 57",
    "sg:postcode":"20700",
    "sg:province":"Guip\u00f9zcoa",
    "wof:name":"Joyeria Relojeria Mazmela, Alberto Mazmela",
    "wof:placetype":"venue"
},
  "geometry": {"coordinates":[-2.3144009113,43.092010498],"type":"Point"}
}