{
  "type": "Feature",
  "properties": {
    "addr:full":"Gta Rosales, 7 Aranda Duero Burgos 09400",
    "addr:housenumber":"7",
    "addr:postcode":"09400",
    "addr:street":"Gta Rosales",
    "iso:country":"ES",
    "sg:address":"Gta Rosales, 7",
    "sg:city":"Aranda Duero",
    "sg:orig_category":"Laboratorios Y Cl\u00cdnicas Veterinarias",
    "sg:phone":"+34 947 50 17 11",
    "sg:postcode":"09400",
    "sg:province":"Burgos",
    "wof:name":"Arauzo Garcia Angel",
    "wof:placetype":"venue"
},
  "geometry": {"coordinates":[-3.6921849251,41.6659851074],"type":"Point"}
}