{
  "type": "Feature",
  "properties": {
    "addr:full":"Cmno Lonja (la), S/n Albacete Albacete 02006",
    "addr:postcode":"02006",
    "addr:street":"Cmno Lonja La S / N",
    "iso:country":"ES",
    "sg:address":"Cmno Lonja (la), S/n",
    "sg:city":"Albacete",
    "sg:orig_category":"Distribuci\u00d3n De Petr\u00d3leo Y Derivados",
    "sg:phone":"+34 967 24 43 49",
    "sg:postcode":"02006",
    "sg:province":"Albacete",
    "wof:name":"Lopez Ortega Gonzalo",
    "wof:placetype":"venue"
},
  "geometry": {"coordinates":[-2.044303894,39.0605888367],"type":"Point"}
}