{
  "type": "Feature",
  "properties": {
    "iso:country":"ES",
    "sg:address":"Calle de Amezti, 5",
    "sg:city":"Getxo",
    "sg:orig_category":"M\u00c9dicos: Medicina General",
    "sg:phone":"+34 944 60 80 35",
    "sg:postcode":"48990",
    "sg:province":"Vizcaya",
    "wof:name":"Angel Maria Astorquiza Basa\u00f1ez",
    "wof:placetype":"venue"
},
  "geometry": {"coordinates":[-3.0105407238,43.3492393494],"type":"Point"}
}