{
  "type": "Feature",
  "properties": {
    "iso:country":"ES",
    "sg:address":"Avda Santiago, 51",
    "sg:city":"Vitoria-gasteiz",
    "sg:orig_category":"Confecci\u00d3n (fabricaci\u00d3n, Al Por Mayor)",
    "sg:phone":"+34 945 26 32 65",
    "sg:postcode":"01003",
    "sg:province":"\u00c1lava",
    "wof:name":"Lucas Raya Rodriguez",
    "wof:placetype":"venue"
},
  "geometry": {"coordinates":[-2.6601750851,42.8479766846],"type":"Point"}
}