{
  "type": "Feature",
  "properties": {
    "iso:country":"ES",
    "sg:address":"Pla\u00c7 Espanya, 12",
    "sg:city":"Mao",
    "sg:orig_category":"Inmobiliaria (agencias)",
    "sg:phone":"+34 971 36 87 72",
    "sg:postcode":"07701",
    "sg:province":"Islas Baleares",
    "sg:website":"www.fincasmenorca.com",
    "wof:name":"Fincas Menorca Agencia Inmobiliaria 1990 S.l.",
    "wof:placetype":"venue"
},
  "geometry": {"coordinates":[4.265586853,39.8888778687],"type":"Point"}
}