{
  "type": "Feature",
  "properties": {
    "addr:full":"Calle de Lepe, 49 Martos Ja\u00e9n 23600",
    "addr:housenumber":"49",
    "addr:postcode":"23600",
    "addr:street":"Calle De Lepe;Jae\u0301N",
    "iso:country":"ES",
    "sg:address":"Calle de Lepe, 49",
    "sg:city":"Martos",
    "sg:orig_category":"Florister\u00cdas",
    "sg:phone":"+34 953 55 14 58",
    "sg:postcode":"23600",
    "sg:province":"Ja\u00e9n",
    "wof:name":"Rubia Molina Antonio",
    "wof:placetype":"venue"
},
  "geometry": {"coordinates":[-3.9702379704,37.7227973938],"type":"Point"}
}