{
  "type": "Feature",
  "properties": {
    "addr:full":"Calle de Pilar, 17 Fuentealbilla Albacete 02260",
    "addr:housenumber":"17",
    "addr:postcode":"02260",
    "addr:street":"Calle De Pilar",
    "iso:country":"ES",
    "sg:address":"Calle de Pilar, 17",
    "sg:city":"Fuentealbilla",
    "sg:orig_category":"Autob\u00das (explotaci\u00d3n Y Servicios De)",
    "sg:phone":"+34 967 47 21 03",
    "sg:postcode":"02260",
    "sg:province":"Albacete",
    "wof:name":"Valiente Iniesta Manuel",
    "wof:placetype":"venue"
},
  "geometry": {"coordinates":[-1.5483150482,39.2675323486],"type":"Point"}
}