{
  "type": "Feature",
  "properties": {
    "iso:country":"ES",
    "sg:address":"Calle de Carrera, 2",
    "sg:city":"Arnedo",
    "sg:orig_category":"Iglesia Cat\u00d3lica",
    "sg:phone":"+34 941 38 08 80",
    "sg:postcode":"26580",
    "sg:province":"La Rioja",
    "wof:name":"Parroquia De Santo Tomas Apostol",
    "wof:placetype":"venue"
},
  "geometry": {"coordinates":[-2.1038811207,42.2264900208],"type":"Point"}
}