{
  "type": "Feature",
  "properties": {
    "iso:country":"ES",
    "sg:address":"Pg Taga, 47",
    "sg:city":"Ribes Freser",
    "sg:orig_category":"Empresas De Pintura Y Revestimientos",
    "sg:phone":"+34 972 72 78 56",
    "sg:postcode":"17534",
    "sg:province":"Girona",
    "wof:name":"Domenech Serra Antonio",
    "wof:placetype":"venue"
},
  "geometry": {"coordinates":[2.1691350937,42.3041381836],"type":"Point"}
}