{
  "type": "Feature",
  "properties": {
    "iso:country":"ES",
    "sg:address":"Plaz San Francisco, 31",
    "sg:city":"Antequera",
    "sg:orig_category":"Agentes, Concesionarios Y Sucursales De Veh\u00cdculos",
    "sg:phone":"+34 952 84 32 34",
    "sg:postcode":"29200",
    "sg:province":"M\u00e1laga",
    "wof:name":"Romero Ruiz Rafael",
    "wof:placetype":"venue"
},
  "geometry": {"coordinates":[-4.5577487946,37.0197906494],"type":"Point"}
}