{
  "type": "Feature",
  "properties": {
    "iso:country":"ES",
    "sg:address":"Calle de Genal, 1",
    "sg:city":"Linea De La Concepcion",
    "sg:orig_category":"Agencias Y Agentes Comerciales, Representantes",
    "sg:phone":"+34 956 17 29 25",
    "sg:postcode":"11300",
    "sg:province":"C\u00e1diz",
    "wof:name":"Centeno Romero Perfecto",
    "wof:placetype":"venue"
},
  "geometry": {"coordinates":[-5.3417987823,36.1710891724],"type":"Point"}
}