{
  "type": "Feature",
  "properties": {
    "iso:country":"ES",
    "sg:address":"Calle de San Jose, 4",
    "sg:city":"Olleria",
    "sg:orig_category":"Producci\u00d3n, Distribuci\u00d3n De Electricidad",
    "sg:phone":"+34 962 20 16 42",
    "sg:postcode":"46850",
    "sg:province":"Valencia",
    "wof:name":"Comercial Electrojisma S.l.",
    "wof:placetype":"venue"
},
  "geometry": {"coordinates":[-0.5487890244,38.9125137329],"type":"Point"}
}