{
  "type": "Feature",
  "properties": {
    "addr:full":"Calle de Maria Teresa Gil De Garate, 20 Logro\u00f1o La Rioja 26002",
    "addr:housenumber":"20",
    "addr:postcode":"26002",
    "addr:street":"Calle De Maria Teresa Gil De Garate;Rioja",
    "iso:country":"ES",
    "sg:address":"Calle de Maria Teresa Gil De Garate, 20",
    "sg:city":"Logro\u00f1o",
    "sg:orig_category":"Centros P\u00dablicos De Formaci\u00d3n Profesional Y T\u00c9cnica",
    "sg:phone":"+34 941 24 70 38",
    "sg:postcode":"26002",
    "sg:province":"La Rioja",
    "wof:name":"Colegio De Mediadores De Seguros Titulados De La Rioja",
    "wof:placetype":"venue"
},
  "geometry": {"coordinates":[-2.4494318962,42.4626235962],"type":"Point"}
}