{
  "type": "Feature",
  "properties": {
    "addr:full":"Calle de Jose Mardones, 12 Vitoria-gasteiz \u00c1lava 01003",
    "addr:housenumber":"12",
    "addr:postcode":"01003",
    "addr:street":"Calle De Jose Mardones",
    "iso:country":"ES",
    "sg:address":"Calle de Jose Mardones, 12",
    "sg:city":"Vitoria-gasteiz",
    "sg:orig_category":"Molduras, Junquillos, Listones Y Molduras Perforadas",
    "sg:phone":"+34 945 25 60 12",
    "sg:postcode":"01003",
    "sg:province":"\u00c1lava",
    "wof:name":"Hermanos Sampedro Martin",
    "wof:placetype":"venue"
},
  "geometry": {"coordinates":[-2.6638319492,42.8463401794],"type":"Point"}
}