{
  "type": "Feature",
  "properties": {
    "iso:country":"ES",
    "sg:address":"Calle de Real, 31",
    "sg:city":"Lepe",
    "sg:orig_category":"Asesor\u00cda Sobre Comunicaci\u00d3n De Empresas",
    "sg:phone":"+34 959 38 14 75",
    "sg:postcode":"21440",
    "sg:province":"Huelva",
    "wof:name":"Gonzalez Gomez Maria Mercedes",
    "wof:placetype":"venue"
},
  "geometry": {"coordinates":[-7.2023382187,37.2557411194],"type":"Point"}
}