{
  "type": "Feature",
  "properties": {
    "addr:full":"Calle de Carreteros, 49 Rambla C\u00f3rdoba 14540",
    "addr:housenumber":"49",
    "addr:postcode":"14540",
    "addr:street":"Calle De Carreteros;Rambla Co\u0301Rdoba",
    "iso:country":"ES",
    "sg:address":"Calle de Carreteros, 49",
    "sg:city":"Rambla",
    "sg:orig_category":"Comercio De Hierro",
    "sg:phone":"+34 957 68 20 94",
    "sg:postcode":"14540",
    "sg:province":"C\u00f3rdoba",
    "wof:name":"Mejias Moreno Manuel",
    "wof:placetype":"venue"
},
  "geometry": {"coordinates":[-4.7349658012,37.6061401367],"type":"Point"}
}