{
  "type": "Feature",
  "properties": {
    "iso:country":"ES",
    "sg:address":"Toro-norte, S/n",
    "sg:city":"Toro",
    "sg:orig_category":"Chapister\u00cda",
    "sg:phone":"+34 980 69 06 06",
    "sg:postcode":"49800",
    "sg:province":"Zamora",
    "wof:name":"S. Tejeda E Hijos S.l.",
    "wof:placetype":"venue"
},
  "geometry": {"coordinates":[-5.4181170464,41.5279388428],"type":"Point"}
}