{
  "type": "Feature",
  "properties": {
    "iso:country":"ES",
    "sg:address":"Calle de Ayora, 8",
    "sg:city":"Valencia",
    "sg:orig_category":"Fabricaci\u00d3n, Venta De Cuadros, Accesorios Para Enmarcar",
    "sg:phone":"+34 963 84 54 57",
    "sg:postcode":"46018",
    "sg:province":"Valencia",
    "wof:name":"Marin Maestro Candido",
    "wof:placetype":"venue"
},
  "geometry": {"coordinates":[-0.3931430876,39.4650917053],"type":"Point"}
}