{
  "type": "Feature",
  "properties": {
    "addr:full":"Ctra Valencia-ademuz, Km. 0024,5 Lliria Valencia 46160",
    "addr:postcode":"46160",
    "addr:street":"Ctra Valencia-Ademuz Km. 0024,5 Lliria",
    "iso:country":"ES",
    "sg:address":"Ctra Valencia-ademuz, Km. 0024,5",
    "sg:city":"Lliria",
    "sg:orig_category":"Agentes, Concesionarios Y Sucursales De Veh\u00cdculos",
    "sg:phone":"+34 962 78 01 54",
    "sg:postcode":"46160",
    "sg:province":"Valencia",
    "wof:name":"Autodem S.a.",
    "wof:placetype":"venue"
},
  "geometry": {"coordinates":[-0.5861409903,39.6205329895],"type":"Point"}
}