{
  "type": "Feature",
  "properties": {
    "iso:country":"ES",
    "sg:address":"Calle de Marques Alonso Martinez, 17",
    "sg:city":"Alcala Henares",
    "sg:orig_category":"Florister\u00cdas",
    "sg:phone":"+34 918 88 66 51",
    "sg:postcode":"28804",
    "sg:province":"Madrid",
    "wof:name":"De Tomas Ferrero Mar Del Val",
    "wof:placetype":"venue"
},
  "geometry": {"coordinates":[-3.3568520546,40.4843711853],"type":"Point"}
}