{
  "type": "Feature",
  "properties": {
    "addr:full":"Carrer de Prim, 88 Terrassa Barcelona 08223",
    "addr:housenumber":"88",
    "addr:postcode":"08223",
    "addr:street":"Carrer De Prim",
    "iso:country":"ES",
    "sg:address":"Carrer de Prim, 88",
    "sg:city":"Terrassa",
    "sg:orig_category":"Caf\u00c9s, Bares, Cervecer\u00cdas",
    "sg:phone":"+34 937 85 03 67",
    "sg:postcode":"08223",
    "sg:province":"Barcelona",
    "wof:name":"Manelic & Amistat S.l.",
    "wof:placetype":"venue"
},
  "geometry": {"coordinates":[2.0155720711,41.5569190979],"type":"Point"}
}