{
  "type": "Feature",
  "properties": {
    "addr:full":"Carrer de Manigua, 54 Barcelona Barcelona 08027",
    "addr:housenumber":"54",
    "addr:postcode":"08027",
    "addr:street":"Carrer De Manigua",
    "iso:country":"ES",
    "sg:address":"Carrer de Manigua, 54",
    "sg:city":"Barcelona",
    "sg:orig_category":"Doctores En Medicina",
    "sg:phone":"+34 933 52 49 01",
    "sg:postcode":"08027",
    "sg:province":"Barcelona",
    "wof:name":"Gadea Garrido Benito",
    "wof:placetype":"venue"
},
  "geometry": {"coordinates":[2.1797609329,41.4243545532],"type":"Point"}
}