{
  "type": "Feature",
  "properties": {
    "addr:full":"Calle de Jaume I, 9 Poligono Ind. Mediterraneo Valencia 46560",
    "addr:housenumber":"9",
    "addr:postcode":"46560",
    "addr:street":"Calle De Jaume I;Ind.",
    "iso:country":"ES",
    "sg:address":"Calle de Jaume I, 9",
    "sg:city":"Poligono Ind. Mediterraneo",
    "sg:orig_category":"Fabricaci\u00d3n De Enlosados, Soler\u00cdas",
    "sg:phone":"+34 961 40 13 13",
    "sg:postcode":"46560",
    "sg:province":"Valencia",
    "wof:name":"Rumbomar S.a.",
    "wof:placetype":"venue"
},
  "geometry": {"coordinates":[-0.3252330124,39.5581474304],"type":"Point"}
}