{
  "type": "Feature",
  "properties": {
    "addr:full":"Calle de Mayor, 3 Almaden Ciudad Real 13400",
    "addr:housenumber":"3",
    "addr:postcode":"almaden;13400",
    "addr:street":"Calle De Mayor;Real",
    "iso:country":"ES",
    "sg:address":"Calle de Mayor, 3",
    "sg:city":"Almaden",
    "sg:orig_category":"Centros P\u00dablicos De Formaci\u00d3n Profesional Y T\u00c9cnica",
    "sg:phone":"+34 926 71 05 17",
    "sg:postcode":"13400",
    "sg:province":"Ciudad Real",
    "wof:name":"Colegio Oficial De La Ingenieria Tecnica Facultativos Y Peritos De Minas",
    "wof:placetype":"venue"
},
  "geometry": {"coordinates":[-4.8358840942,38.7758293152],"type":"Point"}
}