{
  "type": "Feature",
  "properties": {
    "addr:full":"Lusqui\u00f1os, S/n Lusqui\u00f1os Pontevedra 36158",
    "addr:postcode":"36158",
    "addr:street":"Lusquin\u0303Os S / N",
    "iso:country":"ES",
    "sg:address":"Lusqui\u00f1os, S/n",
    "sg:city":"Lusqui\u00f1os",
    "sg:orig_category":"Negocio De Materiales De Construcci\u00d3n",
    "sg:phone":"+34 986 84 03 89",
    "sg:postcode":"36158",
    "sg:province":"Pontevedra",
    "wof:name":"Boullosa Barreiro Antonio",
    "wof:placetype":"venue"
},
  "geometry": {"coordinates":[-8.601433754,42.4093666077],"type":"Point"}
}