{
  "type": "Feature",
  "properties": {
    "iso:country":"ES",
    "sg:address":"Calle de Emilio Castelar, 17",
    "sg:city":"Alcazar S. Juan",
    "sg:orig_category":"Aceites Y Grasas Alimentarias (fabricaci\u00d3n, Al Por Mayor)",
    "sg:phone":"+34 926 54 03 11",
    "sg:postcode":"13600",
    "sg:province":"Ciudad Real",
    "wof:name":"Martinez Perez Pilar",
    "wof:placetype":"venue"
},
  "geometry": {"coordinates":[-3.2092010975,39.390953064],"type":"Point"}
}