{
  "type": "Feature",
  "properties": {
    "iso:country":"ES",
    "sg:address":"Avda Granada, 73",
    "sg:city":"Huescar",
    "sg:orig_category":"Transporte En General",
    "sg:phone":"+34 958 74 16 20",
    "sg:postcode":"18830",
    "sg:province":"Granada",
    "wof:name":"Distribuidora Uribe S.a.",
    "wof:placetype":"venue"
},
  "geometry": {"coordinates":[-2.5445230007,37.8010597229],"type":"Point"}
}