{
  "type": "Feature",
  "properties": {
    "iso:country":"ES",
    "sg:address":"Calle de Virgen Del Puerto, 5",
    "sg:city":"Santo\u00f1a",
    "sg:orig_category":"Carnicer\u00cdas, Carnicer\u00cdas",
    "sg:phone":"+34 942 66 30 54",
    "sg:postcode":"39740",
    "sg:province":"Cantabria",
    "wof:name":"Perez Aguilar Alejandro",
    "wof:placetype":"venue"
},
  "geometry": {"coordinates":[-3.4531960487,43.4437255859],"type":"Point"}
}