{
  "type": "Feature",
  "properties": {
    "iso:country":"ES",
    "sg:address":"Calle de Ruta Del Peregrino, 23",
    "sg:city":"Arbas Puerto",
    "sg:orig_category":"Carb\u00d3n, Carb\u00d3n De Madera (al Por Mayor)",
    "sg:phone":"+34 987 59 85 15",
    "sg:postcode":"24690",
    "sg:province":"Le\u00f3n",
    "wof:name":"Union Minera Del Norte S.a.",
    "wof:placetype":"venue"
},
  "geometry": {"coordinates":[-5.7166428566,42.9840583801],"type":"Point"}
}