{
  "type": "Feature",
  "properties": {
    "iso:country":"ES",
    "sg:address":"Psaj Belmonte De San Jose, 5",
    "sg:city":"Alca\u00f1iz",
    "sg:orig_category":"Empresas De Limpieza",
    "sg:phone":"+34 978 83 55 45",
    "sg:postcode":"44600",
    "sg:province":"Teruel",
    "sg:website":"www.externasl.com",
    "wof:name":"Externalizacion Y Servicios 2004 S.l.",
    "wof:placetype":"venue"
},
  "geometry": {"coordinates":[-0.1288940012,41.0498924255],"type":"Point"}
}