{
  "type": "Feature",
  "properties": {
    "addr:full":"Rua Outeiro (do), 2 Castroverde Lugo 27120",
    "addr:housenumber":"2",
    "addr:postcode":"27120",
    "addr:street":"Rua Outeiro Do",
    "iso:country":"ES",
    "sg:address":"Rua Outeiro (do), 2",
    "sg:city":"Castroverde",
    "sg:orig_category":"Restaurantes",
    "sg:phone":"+34 982 31 23 52",
    "sg:postcode":"27120",
    "sg:province":"Lugo",
    "wof:name":"Pereira Vali\u00f1o Cesar",
    "wof:placetype":"venue"
},
  "geometry": {"coordinates":[-7.3264689445,43.0291442871],"type":"Point"}
}