{
  "type": "Feature",
  "properties": {
    "iso:country":"ES",
    "sg:address":"Carr Canonge Barbera Sentamans, 26",
    "sg:city":"Guadassuar",
    "sg:orig_category":"Serrer\u00cdas De Madera",
    "sg:phone":"+34 962 57 01 36",
    "sg:postcode":"46610",
    "sg:province":"Valencia",
    "wof:name":"Serreria Casani Sl",
    "wof:placetype":"venue"
},
  "geometry": {"coordinates":[-0.4778090119,39.1831245422],"type":"Point"}
}