{
  "type": "Feature",
  "properties": {
    "iso:country":"ES",
    "sg:address":"Calle de Calera, 18",
    "sg:city":"Burgos",
    "sg:orig_category":"Agentes Generales De Seguros",
    "sg:phone":"+34 947 26 65 76",
    "sg:postcode":"09002",
    "sg:province":"Burgos",
    "wof:name":"Gonzalez Barbadillo Guillermo",
    "wof:placetype":"venue"
},
  "geometry": {"coordinates":[-3.6983492374,42.3383712769],"type":"Point"}
}