{
  "type": "Feature",
  "properties": {
    "iso:country":"ES",
    "sg:address":"Calle de Pelota, 14",
    "sg:city":"Benimamet-beniferri",
    "sg:orig_category":"Mercer\u00cda, Lencer\u00cda (al Por Menor)",
    "sg:phone":"+34 963 40 04 18",
    "sg:postcode":"46035",
    "sg:province":"Valencia",
    "wof:name":"Lluna Garcia Concepcion",
    "wof:placetype":"venue"
},
  "geometry": {"coordinates":[-0.4175679982,39.4976997375],"type":"Point"}
}