{
  "type": "Feature",
  "properties": {
    "addr:full":"Calle de Antonio Burgos, 3 Castro Urdiales Cantabria 39700",
    "addr:housenumber":"3",
    "addr:postcode":"39700",
    "addr:street":"Calle De Antonio Burgos",
    "iso:country":"ES",
    "sg:address":"Calle de Antonio Burgos, 3",
    "sg:city":"Castro Urdiales",
    "sg:orig_category":"Asesor\u00cda Fiscal Y Jur\u00cddica",
    "sg:phone":"+34 942 87 11 10",
    "sg:postcode":"39700",
    "sg:province":"Cantabria",
    "wof:name":"Urquijo Serra Jose Maria",
    "wof:placetype":"venue"
},
  "geometry": {"coordinates":[-3.2192649841,43.3795127869],"type":"Point"}
}