{
  "type": "Feature",
  "properties": {
    "iso:country":"ES",
    "sg:address":"Plaz Campillo, 4",
    "sg:city":"Salamanca",
    "sg:orig_category":"Moda",
    "sg:phone":"+34 923 23 19 12",
    "sg:postcode":"37002",
    "sg:province":"Salamanca",
    "wof:name":"Tapioca C.b.",
    "wof:placetype":"venue"
},
  "geometry": {"coordinates":[-5.661429882,40.9688339233],"type":"Point"}
}