{
  "type": "Feature",
  "properties": {
    "addr:full":"Avda Zumalakarregi, 26 Llodio \u00c1lava 01400",
    "addr:housenumber":"26",
    "addr:postcode":"01400",
    "addr:street":"Avda Zumalakarregi",
    "iso:country":"ES",
    "sg:address":"Avda Zumalakarregi, 26",
    "sg:city":"Llodio",
    "sg:orig_category":"Peluquer\u00cdas, Peluquer\u00cda Mixta",
    "sg:phone":"+34 946 72 64 82",
    "sg:postcode":"01400",
    "sg:province":"\u00c1lava",
    "wof:name":"Valencia Iturriondobeitia Ane",
    "wof:placetype":"venue"
},
  "geometry": {"coordinates":[-2.9604148865,43.1456298828],"type":"Point"}
}