{
  "type": "Feature",
  "properties": {
    "addr:full":"Calle de Brieva, 2 Avila \u00c1vila 05001",
    "addr:housenumber":"2",
    "addr:postcode":"05001",
    "addr:street":"Calle De Brieva;A\u0301Vila",
    "iso:country":"ES",
    "sg:address":"Calle de Brieva, 2",
    "sg:city":"Avila",
    "sg:orig_category":"Mutuas De Seguros",
    "sg:phone":"+34 920 25 60 12",
    "sg:postcode":"05001",
    "sg:province":"\u00c1vila",
    "wof:name":"Hermandad Nacional De Arquitectos",
    "wof:placetype":"venue"
},
  "geometry": {"coordinates":[-4.699616909,40.6578559875],"type":"Point"}
}