{
  "type": "Feature",
  "properties": {
    "addr:full":"Ctra. Oropesa, Km. 0001,5 Candeleda \u00c1vila 05480",
    "addr:postcode":"05480",
    "addr:street":"Ctra. Oropesa Km. 0001,5;A\u0301Vila",
    "iso:country":"ES",
    "sg:address":"Ctra. Oropesa, Km. 0001,5",
    "sg:city":"Candeleda",
    "sg:orig_category":"Molduras, Junquillos, Listones Y Molduras Perforadas",
    "sg:phone":"+34 920 38 22 38",
    "sg:postcode":"05480",
    "sg:province":"\u00c1vila",
    "wof:name":"Sanchez Vaquero Eli Marcial",
    "wof:placetype":"venue"
},
  "geometry": {"coordinates":[-5.2349038124,40.1447029114],"type":"Point"}
}