{
  "type": "Feature",
  "properties": {
    "addr:full":"Calle de Delgado Serrano, 2 Ceuta Ceuta 51001",
    "addr:housenumber":"2",
    "addr:postcode":"51001",
    "addr:street":"Calle De Delgado Serrano",
    "iso:country":"ES",
    "sg:address":"Calle de Delgado Serrano, 2",
    "sg:city":"Ceuta",
    "sg:orig_category":"Servicios Gsm",
    "sg:phone":"+34 956 51 32 83",
    "sg:postcode":"51001",
    "sg:province":"Ceuta",
    "wof:name":"Gomez Duarte Juan Carlos",
    "wof:placetype":"venue"
},
  "geometry": {"coordinates":[-5.3095431328,35.8874359131],"type":"Point"}
}