{
  "type": "Feature",
  "properties": {
    "iso:country":"ES",
    "sg:address":"Carrer de Girona, 88",
    "sg:city":"Barcelona",
    "sg:orig_category":"Retoques De Vestidos",
    "sg:phone":"+34 932 45 50 39",
    "sg:postcode":"08009",
    "sg:province":"Barcelona",
    "wof:name":"De Marco  Maria Cristina",
    "wof:placetype":"venue"
},
  "geometry": {"coordinates":[2.1700770855,41.3958396912],"type":"Point"}
}