{
  "type": "Feature",
  "properties": {
    "addr:full":"Calle de Pasillas, 19 Antequera M\u00e1laga 29200",
    "addr:housenumber":"19",
    "addr:postcode":"29200",
    "addr:street":"Calle De Pasillas",
    "iso:country":"ES",
    "sg:address":"Calle de Pasillas, 19",
    "sg:city":"Antequera",
    "sg:orig_category":"Mec\u00c1nico Del Autom\u00d3vil",
    "sg:phone":"+34 952 84 25 92",
    "sg:postcode":"29200",
    "sg:province":"M\u00e1laga",
    "wof:name":"Ramos Perez Jose",
    "wof:placetype":"venue"
},
  "geometry": {"coordinates":[-4.5610117912,37.0149383545],"type":"Point"}
}