{
  "type": "Feature",
  "properties": {
    "addr:full":"Calle de Toledo, 2 Manzanares Ciudad Real 13200",
    "addr:housenumber":"2",
    "addr:postcode":"13200",
    "addr:street":"Calle De Toledo",
    "iso:country":"ES",
    "sg:address":"Calle de Toledo, 2",
    "sg:city":"Manzanares",
    "sg:orig_category":"Ortopedia General",
    "sg:phone":"+34 926 61 11 79",
    "sg:postcode":"13200",
    "sg:province":"Ciudad Real",
    "wof:name":"Bonillo Rodrigo Jose",
    "wof:placetype":"venue"
},
  "geometry": {"coordinates":[-3.3696689606,39.0010681152],"type":"Point"}
}