{
  "type": "Feature",
  "properties": {
    "addr:full":"Infantes, 2 Comillas Cantabria 39520",
    "addr:housenumber":"2",
    "addr:postcode":"39520",
    "addr:street":"Infantes",
    "iso:country":"ES",
    "sg:address":"Infantes, 2",
    "sg:city":"Comillas",
    "sg:orig_category":"Caf\u00c9s, Bares, Cervecer\u00cdas",
    "sg:phone":"+34 942 72 25 54",
    "sg:postcode":"39520",
    "sg:province":"Cantabria",
    "wof:name":"Cuevas Sierra Maria Del Rosario",
    "wof:placetype":"venue"
},
  "geometry": {"coordinates":[-4.2929000854,43.3871383667],"type":"Point"}
}