{
  "type": "Feature",
  "properties": {
    "addr:full":"Cmno Vega Alta, S/n Pechina Almer\u00eda 04250",
    "addr:housenumber":"s / n",
    "addr:postcode":"04250",
    "addr:street":"Cmno Vega Alta;Almeri\u0301A",
    "iso:country":"ES",
    "sg:address":"Cmno Vega Alta, S/n",
    "sg:city":"Pechina",
    "sg:orig_category":"Inform\u00c1tica (estudios, Servicios, Asesor\u00cda, Formaci\u00d3n)",
    "sg:phone":"+34 950 31 76 56",
    "sg:postcode":"04250",
    "sg:province":"Almer\u00eda",
    "wof:name":"Dsf Almarilla A.i.e.",
    "wof:placetype":"venue"
},
  "geometry": {"coordinates":[-2.4415290356,36.914730072],"type":"Point"}
}