{
  "type": "Feature",
  "properties": {
    "addr:full":"Avda Caballeria Espa\u00d1ola, 1 Alcala Henares Madrid 28805",
    "addr:housenumber":"1",
    "addr:postcode":"28805",
    "addr:street":"Avda Caballeria Espan\u0303Ola",
    "iso:country":"ES",
    "sg:address":"Avda Caballeria Espa\u00d1ola, 1",
    "sg:city":"Alcala Henares",
    "sg:orig_category":"Venta, Colocaci\u00d3n De Moquetas, Revestimiento De Suelos Y De Paredes",
    "sg:phone":"+34 918 89 81 36",
    "sg:postcode":"28805",
    "sg:province":"Madrid",
    "wof:name":"Impor 3 S. A.",
    "wof:placetype":"venue"
},
  "geometry": {"coordinates":[-3.3591239452,40.4872932434],"type":"Point"}
}