{
  "type": "Feature",
  "properties": {
    "addr:full":"Gral. Elorza, 2 Trubia Asturias 33100",
    "addr:housenumber":"2",
    "addr:postcode":"33100",
    "addr:street":"Gral. Elorza;Asturias",
    "iso:country":"ES",
    "sg:address":"Gral. Elorza, 2",
    "sg:city":"Trubia",
    "sg:orig_category":"Transportes Urbanos Y Regionales Para Personas",
    "sg:phone":"+34 985 78 61 47",
    "sg:postcode":"33100",
    "sg:province":"Asturias",
    "wof:name":"Hermanos Gonzalez Arguelles",
    "wof:placetype":"venue"
},
  "geometry": {"coordinates":[-5.9686012268,43.3453598022],"type":"Point"}
}