{
  "type": "Feature",
  "properties": {
    "iso:country":"ES",
    "sg:address":"Hospital(barreros), 57",
    "sg:city":"Cartagena",
    "sg:orig_category":"Chapister\u00cda",
    "sg:phone":"+34 968 51 08 50",
    "sg:postcode":"30310",
    "sg:province":"Murcia",
    "wof:name":"Meca-bogarra S.l.",
    "wof:placetype":"venue"
},
  "geometry": {"coordinates":[-0.9951350093,37.6279640198],"type":"Point"}
}