{
  "type": "Feature",
  "properties": {
    "addr:full":"Poli Poligon 06, S/n Picassent Valencia 46220",
    "addr:housenumber":"06 s / n",
    "addr:postcode":"46220",
    "addr:street":"Poligon",
    "iso:country":"ES",
    "sg:address":"Poli Poligon 06, S/n",
    "sg:city":"Picassent",
    "sg:orig_category":"Muebles Y Accesorios Para Cocinas Y Cuartos De Ba\u00d1o (al Por Menor)",
    "sg:phone":"+34 961 24 14 44",
    "sg:postcode":"46220",
    "sg:province":"Valencia",
    "wof:name":"Mobara S. L.",
    "wof:placetype":"venue"
},
  "geometry": {"coordinates":[-0.4595290124,39.3631401062],"type":"Point"}
}