{
  "type": "Feature",
  "properties": {
    "addr:full":"Carrer de Doctor Pi I Molist, 39 Barcelona Barcelona 08031",
    "addr:housenumber":"39",
    "addr:postcode":"08031",
    "addr:street":"Carrer De Doctor Pi I Molist",
    "iso:country":"ES",
    "sg:address":"Carrer de Doctor Pi I Molist, 39",
    "sg:city":"Barcelona",
    "sg:orig_category":"Telas Y Sedas (al Por Menor)",
    "sg:phone":"+34 933 52 63 68",
    "sg:postcode":"08031",
    "sg:province":"Barcelona",
    "wof:name":"Gallifa Faro Josep",
    "wof:placetype":"venue"
},
  "geometry": {"coordinates":[2.1733179092,41.4327468872],"type":"Point"}
}