{
  "type": "Feature",
  "properties": {
    "iso:country":"ES",
    "sg:address":"Carrer de Manresa, 222",
    "sg:city":"Terrassa",
    "sg:orig_category":"Promotores Constructores",
    "sg:phone":"+34 937 31 34 54",
    "sg:postcode":"08226",
    "sg:province":"Barcelona",
    "wof:name":"Construcciones Omycal S.l.",
    "wof:placetype":"venue"
},
  "geometry": {"coordinates":[2.0253200531,41.5758705139],"type":"Point"}
}