{
  "type": "Feature",
  "properties": {
    "iso:country":"ES",
    "sg:address":"Rua Soportais (dos), 4",
    "sg:city":"Pontevedra",
    "sg:classifiers":[
        {
            "category":"Autos & Motor Vehicles",
            "subcategory":"Automobile Sales",
            "type":"Retail Goods"
        }
    ],
    "sg:phone":"+34 986 86 07 47",
    "sg:postcode":"36002",
    "sg:province":"Pontevedra",
    "wof:name":"Auto Escuela Tambo S.l.",
    "wof:placetype":"venue"
},
  "geometry": {"coordinates":[-8.6445837021,42.4313774109],"type":"Point"}
}