{
  "type": "Feature",
  "properties": {
    "addr:full":"Calle de Hospital, 7 Ribera Fresno Badajoz 06225",
    "addr:housenumber":"7",
    "addr:postcode":"06225",
    "addr:street":"Calle De Hospital",
    "iso:country":"ES",
    "sg:address":"Calle de Hospital, 7",
    "sg:city":"Ribera Fresno",
    "sg:orig_category":"Clubes, Asociaciones De Ocio",
    "sg:phone":"+34 924 53 72 20",
    "sg:postcode":"06225",
    "sg:province":"Badajoz",
    "wof:name":"Calero Casco Manuel",
    "wof:placetype":"venue"
},
  "geometry": {"coordinates":[-6.2409601212,38.5520629883],"type":"Point"}
}