{
  "type": "Feature",
  "properties": {
    "iso:country":"ES",
    "sg:address":"Tresvalles-romadorio, 21",
    "sg:city":"Pillarno",
    "sg:orig_category":"Agricultores, Agricultores",
    "sg:phone":"+34 985 55 07 82",
    "sg:postcode":"33456",
    "sg:province":"Asturias",
    "wof:name":"Ganaderia Tresvalles S.l.",
    "wof:placetype":"venue"
},
  "geometry": {"coordinates":[-5.9890618324,43.5465087891],"type":"Point"}
}