{
  "type": "Feature",
  "properties": {
    "addr:full":"Calle de Lopez De Ayala, 13 Villanueva Serena Badajoz 06700",
    "addr:housenumber":"13",
    "addr:postcode":"06700",
    "addr:street":"Calle De Lopez De Ayala",
    "iso:country":"ES",
    "sg:address":"Calle de Lopez De Ayala, 13",
    "sg:city":"Villanueva Serena",
    "sg:orig_category":"Internados & Ense\u00d1anza Privada",
    "sg:phone":"+34 924 84 60 78",
    "sg:postcode":"06700",
    "sg:province":"Badajoz",
    "wof:name":"Fundacion Educacion Catolica",
    "wof:placetype":"venue"
},
  "geometry": {"coordinates":[-5.797118187,38.9745407104],"type":"Point"}
}