{
  "type": "Feature",
  "properties": {
    "addr:full":"Rua Mendez Nu\u00d1ez, 37 Marin Pontevedra 36900",
    "addr:housenumber":"37",
    "addr:postcode":"36900",
    "addr:street":"Rua Mendez Nun\u0303Ez",
    "iso:country":"ES",
    "sg:address":"Rua Mendez Nu\u00d1ez, 37",
    "sg:city":"Marin",
    "sg:orig_category":"Lanas (al Por Menor)",
    "sg:phone":"+34 986 88 38 88",
    "sg:postcode":"36900",
    "sg:province":"Pontevedra",
    "wof:name":"Bertolo Ballesteros Maria Del Pilar Rosa",
    "wof:placetype":"venue"
},
  "geometry": {"coordinates":[-8.6977148056,42.3921737671],"type":"Point"}
}