{
  "type": "Feature",
  "properties": {
    "iso:country":"ES",
    "sg:address":"Plaz Espa\u00d1a, 10",
    "sg:city":"Ribadeo",
    "sg:orig_category":"Sociedades, Compa\u00d1\u00cdas Aseguradoras",
    "sg:phone":"+34 982 13 00 13",
    "sg:postcode":"27700",
    "sg:province":"Lugo",
    "wof:name":"Vizoso Iglesias Pablo S.a.",
    "wof:placetype":"venue"
},
  "geometry": {"coordinates":[-7.1036396027,43.5224914551],"type":"Point"}
}