{
  "type": "Feature",
  "properties": {
    "addr:full":"Avda Mayorga, Km. 0001,0 Valencia De Don Juan Le\u00f3n 24200",
    "addr:postcode":"24200",
    "addr:street":"Avda Mayorga Km. 0001,0;Leo\u0301N",
    "iso:country":"ES",
    "sg:address":"Avda Mayorga, Km. 0001,0",
    "sg:city":"Valencia De Don Juan",
    "sg:orig_category":"Ense\u00d1anza, Formaci\u00d3n Profesional: Aprendizaje",
    "sg:phone":"+34 987 75 12 08",
    "sg:postcode":"24200",
    "sg:province":"Le\u00f3n",
    "wof:name":"Castellano Leonesa De Composites S.l.",
    "wof:placetype":"venue"
},
  "geometry": {"coordinates":[-5.5139641762,42.2898635864],"type":"Point"}
}