{
  "type": "Feature",
  "properties": {
    "addr:full":"Urb Puig-val, S/n Playa Puig Valencia 46540",
    "addr:housenumber":"s / n",
    "addr:postcode":"46540",
    "addr:street":"Urb Puig-Val;Puig",
    "iso:country":"ES",
    "sg:address":"Urb Puig-val, S/n",
    "sg:city":"Playa Puig",
    "sg:orig_category":"M\u00c9dicos: Ginecolog\u00cda Y Obstetricia",
    "sg:phone":"+34 961 46 07 53",
    "sg:postcode":"46540",
    "sg:province":"Valencia",
    "wof:name":"Martin Arenos Victor",
    "wof:placetype":"venue"
},
  "geometry": {"coordinates":[-0.3003390133,39.5875854492],"type":"Point"}
}