{
  "type": "Feature",
  "properties": {
    "iso:country":"ES",
    "sg:address":"Avda Francisco Prieto Moreno, S/n",
    "sg:city":"Herradura",
    "sg:orig_category":"Bisuter\u00cda, Joyer\u00cda, Relojer\u00cda (al Por Menor)",
    "sg:phone":"+34 958 82 78 17",
    "sg:postcode":"18697",
    "sg:province":"Granada",
    "wof:name":"Martin Morales Dolores",
    "wof:placetype":"venue"
},
  "geometry": {"coordinates":[-3.7390809059,36.7353096008],"type":"Point"}
}