{
  "type": "Feature",
  "properties": {
    "iso:country":"ES",
    "sg:address":"Avda Aeroporto, 734",
    "sg:city":"Vigo",
    "sg:orig_category":"Internados & Ense\u00d1anza Privada",
    "sg:phone":"+34 986 48 80 58",
    "sg:postcode":"36318",
    "sg:province":"Pontevedra",
    "wof:name":"Centro De Estudios Martin Codax S.a",
    "wof:placetype":"venue"
},
  "geometry": {"coordinates":[-8.6385993958,42.2308311462],"type":"Point"}
}