{
  "type": "Feature",
  "properties": {
    "addr:full":"Calle de Tronperri Kalea, 1 Durango Vizcaya 48200",
    "addr:housenumber":"1",
    "addr:postcode":"48200",
    "addr:street":"Calle De Tronperri Kalea",
    "iso:country":"ES",
    "sg:address":"Calle de Tronperri Kalea, 1",
    "sg:city":"Durango",
    "sg:orig_category":"Molduras, Junquillos, Listones Y Molduras Perforadas",
    "sg:phone":"+34 946 81 73 41",
    "sg:postcode":"48200",
    "sg:province":"Vizcaya",
    "wof:name":"Ochoa De Aspuru Pereita Fernando",
    "wof:placetype":"venue"
},
  "geometry": {"coordinates":[-2.6340808868,43.170627594],"type":"Point"}
}