{
  "type": "Feature",
  "properties": {
    "addr:full":"Calle de Juan Calzada Kalea, 5 Gernika-lumo Vizcaya 48300",
    "addr:housenumber":"5",
    "addr:postcode":"48300",
    "addr:street":"Calle De Juan Calzada Kalea",
    "iso:country":"ES",
    "sg:address":"Calle de Juan Calzada Kalea, 5",
    "sg:city":"Gernika-lumo",
    "sg:orig_category":"Fabricaci\u00d3n De Sobres, Bolsas Y Fundas",
    "sg:phone":"+34 946 25 24 25",
    "sg:postcode":"48300",
    "sg:province":"Vizcaya",
    "wof:name":"Izaskun Aberasturi Leguina",
    "wof:placetype":"venue"
},
  "geometry": {"coordinates":[-2.678098917,43.3133125305],"type":"Point"}
}