{
  "type": "Feature",
  "properties": {
    "addr:full":"Luga Curramontes, 31 Curramontes La Coru\u00f1a 15009",
    "addr:housenumber":"31",
    "addr:postcode":"15009",
    "addr:street":"Curramontes;Curramontes La Corun\u0303A",
    "iso:country":"ES",
    "sg:address":"Luga Curramontes, 31",
    "sg:city":"Curramontes",
    "sg:orig_category":"Escuelas De Maternidad P\u00dablicas",
    "sg:phone":"+34 981 13 66 47",
    "sg:postcode":"15009",
    "sg:province":"La Coru\u00f1a",
    "wof:name":"Golfi\u00f1o S.l.",
    "wof:placetype":"venue"
},
  "geometry": {"coordinates":[-8.3959693909,43.3714904785],"type":"Point"}
}