{
  "type": "Feature",
  "properties": {
    "iso:country":"ES",
    "sg:address":"Carrer de Marques De Monistrol, 21",
    "sg:city":"S. Joan Despi",
    "sg:orig_category":"Alquiler De V\u00cddeo",
    "sg:phone":"+34 934 77 38 49",
    "sg:postcode":"08970",
    "sg:province":"Barcelona",
    "wof:name":"Laborda Mena Angel Julian",
    "wof:placetype":"venue"
},
  "geometry": {"coordinates":[2.0697739124,41.372051239],"type":"Point"}
}