{
  "type": "Feature",
  "properties": {
    "addr:full":"Av Gonzalez Robles, S/n Orgiva Granada 18400",
    "addr:housenumber":"s / n",
    "addr:postcode":"18400",
    "addr:street":"Av Gonzalez Robles;Orgiva Granada",
    "iso:country":"ES",
    "sg:address":"Av Gonzalez Robles, S/n",
    "sg:city":"Orgiva",
    "sg:classifiers":[
        {
            "category":"Taxi",
            "type":"Transportation"
        }
    ],
    "sg:phone":"+34 958 78 54 87",
    "sg:postcode":"18400",
    "sg:province":"Granada",
    "wof:name":"Ramos Medina Manuel",
    "wof:placetype":"venue"
},
  "geometry": {"coordinates":[-3.4248919487,36.9006195068],"type":"Point"}
}