{
  "type": "Feature",
  "properties": {
    "iso:country":"ES",
    "sg:address":"Rua Vazquez Queipo, 9",
    "sg:city":"Sarria",
    "sg:orig_category":"Peluquer\u00cdas, Peluquer\u00cda Mixta",
    "sg:phone":"+34 982 53 38 48",
    "sg:postcode":"27600",
    "sg:province":"Lugo",
    "wof:name":"Teldelugo Comunicacion S.l.",
    "wof:placetype":"venue"
},
  "geometry": {"coordinates":[-7.4125418663,42.7816123962],"type":"Point"}
}