{
  "type": "Feature",
  "properties": {
    "iso:country":"ES",
    "sg:address":"Cmno Tejos (somio), 34",
    "sg:city":"Gijon",
    "sg:orig_category":"Alquiler De V\u00cddeo",
    "sg:phone":"+34 985 33 48 30",
    "sg:postcode":"33203",
    "sg:province":"Asturias",
    "wof:name":"Junfuer S. L.",
    "wof:placetype":"venue"
},
  "geometry": {"coordinates":[-5.6309537888,43.5466690063],"type":"Point"}
}