{
  "type": "Feature",
  "properties": {
    "iso:country":"ES",
    "sg:address":"Calle de Mayor, 69",
    "sg:city":"Soneja",
    "sg:orig_category":"Producci\u00d3n, Venta De Productos De Agricultura Biol\u00d3gica",
    "sg:phone":"+34 964 13 50 34",
    "sg:postcode":"12480",
    "sg:province":"Castell\u00f3n",
    "wof:name":"Cooperativa Agricola Nuestra Se\u00f1ora De La Asuncion Coop. V.",
    "wof:placetype":"venue"
},
  "geometry": {"coordinates":[-0.4307799935,39.8151245117],"type":"Point"}
}