{
  "type": "Feature",
  "properties": {
    "addr:full":"Ptda. Enchilagar Rullo, S/n Vilamarxant Valencia 46191",
    "addr:housenumber":"s / n",
    "addr:postcode":"46191",
    "addr:street":"Ptda. Enchilagar Rullo",
    "iso:country":"ES",
    "sg:address":"Ptda. Enchilagar Rullo, S/n",
    "sg:city":"Vilamarxant",
    "sg:orig_category":"Porcelanas, Azulejos (fabricaci\u00d3n, Al Por Mayor)",
    "sg:phone":"+34 962 71 08 69",
    "sg:postcode":"46191",
    "sg:province":"Valencia",
    "wof:name":"Folgado Huerta Daniel",
    "wof:placetype":"venue"
},
  "geometry": {"coordinates":[-0.633942008,39.559463501],"type":"Point"}
}