{
  "type": "Feature",
  "properties": {
    "addr:full":"Casanova (celeiro), 5 Viveiro Lugo 27863",
    "addr:postcode":"27863",
    "iso:country":"ES",
    "sg:address":"Casanova (celeiro), 5",
    "sg:city":"Viveiro",
    "sg:classifiers":[
        {
            "category":"Taxi",
            "type":"Transportation"
        }
    ],
    "sg:phone":"+34 982 56 10 98",
    "sg:postcode":"27863",
    "sg:province":"Lugo",
    "wof:name":"Rego Louzao Placido",
    "wof:placetype":"venue"
},
  "geometry": {"coordinates":[-7.6120882034,43.6604576111],"type":"Point"}
}