{
  "type": "Feature",
  "properties": {
    "iso:country":"ES",
    "sg:address":"Mcdo Cdad Jardin, S/n",
    "sg:city":"Cordoba",
    "sg:orig_category":"Frutas, Legumbres Frescas Y Tempranas (al Por Menor)",
    "sg:phone":"+34 957 23 01 65",
    "sg:postcode":"14005",
    "sg:province":"C\u00f3rdoba",
    "wof:name":"Lopez Ridao Gabriela",
    "wof:placetype":"venue"
},
  "geometry": {"coordinates":[-4.8831849098,37.866859436],"type":"Point"}
}