{
  "type": "Feature",
  "properties": {
    "addr:full":"Czad Romana, 15 Figueres Girona 17600",
    "addr:housenumber":"15",
    "addr:postcode":"17600",
    "addr:street":"Romana",
    "iso:country":"ES",
    "sg:address":"Czad Romana, 15",
    "sg:city":"Figueres",
    "sg:orig_category":"Mec\u00c1nico Del Autom\u00d3vil",
    "sg:phone":"+34 972 51 12 28",
    "sg:postcode":"17600",
    "sg:province":"Girona",
    "wof:name":"Su\u00f1er Su\u00f1er Santiago",
    "wof:placetype":"venue"
},
  "geometry": {"coordinates":[2.9581100941,42.2656898499],"type":"Point"}
}