{
  "type": "Feature",
  "properties": {
    "addr:full":"Carretera Vieja De Granada, S/n Guadix Granada 18500",
    "addr:postcode":"18500",
    "addr:street":"Carretera Vieja De Granada S / N",
    "iso:country":"ES",
    "sg:address":"Carretera Vieja De Granada, S/n",
    "sg:city":"Guadix",
    "sg:orig_category":"Empresas De Carpinter\u00cda De Madera",
    "sg:phone":"+34 958 66 46 68",
    "sg:postcode":"18500",
    "sg:province":"Granada",
    "wof:name":"Carpinteria Milenium S.l.",
    "wof:placetype":"venue"
},
  "geometry": {"coordinates":[-3.1343688965,37.303894043],"type":"Point"}
}