{
  "type": "Feature",
  "properties": {
    "iso:country":"ES",
    "sg:address":"Calle de Sanguino Michel, 15",
    "sg:city":"Caceres",
    "sg:orig_category":"Construcciones Met\u00c1licas",
    "sg:phone":"+34 927 21 15 70",
    "sg:postcode":"10001",
    "sg:province":"C\u00e1ceres",
    "wof:name":"Suministros Izard S.a.",
    "wof:placetype":"venue"
},
  "geometry": {"coordinates":[-6.3813490868,39.4682617188],"type":"Point"}
}