{
  "type": "Feature",
  "properties": {
    "addr:full":"Ctra. Pto. Sta. M.-sanlucar, Km. 0005,8 Menesteo C\u00e1diz 11500",
    "addr:postcode":"11500",
    "addr:street":"Pto.;M.-Sanlucar Km. 0005,8 Menesteo Ca\u0301Diz",
    "iso:country":"ES",
    "sg:address":"Ctra. Pto. Sta. M.-sanlucar, Km. 0005,8",
    "sg:city":"Menesteo",
    "sg:orig_category":"Distribuci\u00d3n De Petr\u00d3leo Y Derivados",
    "sg:phone":"+34 956 54 90 03",
    "sg:postcode":"11500",
    "sg:province":"C\u00e1diz",
    "wof:name":"Sogufesa",
    "wof:placetype":"venue"
},
  "geometry": {"coordinates":[-6.2197542191,36.6056632996],"type":"Point"}
}