{
  "type": "Feature",
  "properties": {
    "addr:full":"Calle de Barros (los), 43 Carrera Santa Cruz De Tenerife 38410",
    "addr:postcode":"38410",
    "addr:street":"Calle De Barros Los;Carrera",
    "iso:country":"ES",
    "sg:address":"Calle de Barros (los), 43",
    "sg:city":"Carrera",
    "sg:orig_category":"Droguer\u00cdas (al Por Menor)",
    "sg:phone":"+34 922 34 14 99",
    "sg:postcode":"38410",
    "sg:province":"Santa Cruz De Tenerife",
    "wof:name":"Productos Industriales De Tenerife S.a.",
    "wof:placetype":"venue"
},
  "geometry": {"coordinates":[-16.5804672241,28.3909702301],"type":"Point"}
}