{
  "type": "Feature",
  "properties": {
    "addr:full":"Av Doctor Francesc Massana, 17 Martorell Barcelona 08760",
    "addr:housenumber":"17",
    "addr:postcode":"08760",
    "addr:street":"Av Doctor Francesc Massana",
    "iso:country":"ES",
    "sg:address":"Av Doctor Francesc Massana, 17",
    "sg:city":"Martorell",
    "sg:orig_category":"Inmobiliaria (agencias)",
    "sg:phone":"+34 937 75 55 88",
    "sg:postcode":"08760",
    "sg:province":"Barcelona",
    "sg:website":"www.donpiso.com",
    "wof:name":"Ferrovial Servicios Inmobiliarios S.l.",
    "wof:placetype":"venue"
},
  "geometry": {"coordinates":[1.9182549715,41.4779434204],"type":"Point"}
}