{
  "type": "Feature",
  "properties": {
    "addr:full":"Avda Larrondo Beheko Etorbidea, S/n Elotxelerri Vizcaya 48180",
    "addr:housenumber":"s",
    "addr:postcode":"48180",
    "addr:street":"Avda Larrondo Beheko Etorbidea;/ N",
    "iso:country":"ES",
    "sg:address":"Avda Larrondo Beheko Etorbidea, S/n",
    "sg:city":"Elotxelerri",
    "sg:orig_category":"Extinci\u00d3n De Incendios: Material Y Suministros (fabricaci\u00d3n, Al Por Mayor)",
    "sg:phone":"+34 944 71 10 55",
    "sg:postcode":"48180",
    "sg:province":"Vizcaya",
    "wof:name":"Insekor S.a.",
    "wof:placetype":"venue"
},
  "geometry": {"coordinates":[-2.932158947,43.3143386841],"type":"Point"}
}