{
  "type": "Feature",
  "properties": {
    "iso:country":"ES",
    "sg:address":"Poli Ciudad Del Transporte, S/n",
    "sg:city":"San Juan De Mozarrifar",
    "sg:orig_category":"Maquinaria Para Industrias Diversas",
    "sg:phone":"+34 976 15 00 11",
    "sg:postcode":"50820",
    "sg:province":"Zaragoza",
    "sg:website":"www.hidramaq.com",
    "wof:name":"Hidramaq S.l.",
    "wof:placetype":"venue"
},
  "geometry": {"coordinates":[-0.8416489959,41.7171096802],"type":"Point"}
}