{
  "type": "Feature",
  "properties": {
    "addr:full":"Carrer de Farigola, 20 Barcelona Barcelona 08023",
    "addr:housenumber":"20",
    "addr:postcode":"08023",
    "addr:street":"Carrer De Farigola",
    "iso:country":"ES",
    "sg:address":"Carrer de Farigola, 20",
    "sg:city":"Barcelona",
    "sg:orig_category":"Energ\u00cda Solar Y Nuevas Energ\u00cdas (equipo, Estudios)",
    "sg:phone":"+34 932 19 30 37",
    "sg:postcode":"08023",
    "sg:province":"Barcelona",
    "sg:website":"www.tiendaelektron.com",
    "wof:name":"Eco-car S.c.p",
    "wof:placetype":"venue"
},
  "geometry": {"coordinates":[2.1464760303,41.4120407104],"type":"Point"}
}