{
  "type": "Feature",
  "properties": {
    "addr:full":"Carrer de Divina Pastora, 6 Manresa Barcelona 08241",
    "addr:housenumber":"6",
    "addr:postcode":"08241",
    "addr:street":"Carrer De Divina Pastora",
    "iso:country":"ES",
    "sg:address":"Carrer de Divina Pastora, 6",
    "sg:city":"Manresa",
    "sg:orig_category":"Molduras, Junquillos, Listones Y Molduras Perforadas",
    "sg:phone":"+34 938 77 02 78",
    "sg:postcode":"08241",
    "sg:province":"Barcelona",
    "wof:name":"Delgado Rubio Diego",
    "wof:placetype":"venue"
},
  "geometry": {"coordinates":[1.8345550299,41.7219467163],"type":"Point"}
}