{
  "type": "Feature",
  "properties": {
    "addr:full":"Avda Concordia, 10 Tui Pontevedra 36700",
    "addr:housenumber":"10",
    "addr:postcode":"36700",
    "addr:street":"Avda Concordia",
    "iso:country":"ES",
    "sg:address":"Avda Concordia, 10",
    "sg:city":"Tui",
    "sg:orig_category":"Comercio, Reparaci\u00d3n De Motocicletas, Bicicletas Y Piezas Sueltas",
    "sg:phone":"+34 986 60 05 31",
    "sg:postcode":"36700",
    "sg:province":"Pontevedra",
    "wof:name":"Pereira Pereira Juan Ramon",
    "wof:placetype":"venue"
},
  "geometry": {"coordinates":[-8.6448440552,42.0485496521],"type":"Point"}
}