{
  "type": "Feature",
  "properties": {
    "addr:full":"Carr Major, 5 Sudanell Lleida 25173",
    "addr:housenumber":"5",
    "addr:postcode":"25173",
    "addr:street":"Carr Major",
    "iso:country":"ES",
    "sg:address":"Carr Major, 5",
    "sg:city":"Sudanell",
    "sg:orig_category":"Escultores, Estatuarios E Imagineros",
    "sg:phone":"+34 973 25 80 20",
    "sg:postcode":"25173",
    "sg:province":"Lleida",
    "wof:name":"Pujol Torres Juan Jose",
    "wof:placetype":"venue"
},
  "geometry": {"coordinates":[0.5675039887,41.5579071045],"type":"Point"}
}