{
  "type": "Feature",
  "properties": {
    "addr:full":"Mayor, S/n Borobia Soria 42138",
    "addr:housenumber":"s / n",
    "addr:postcode":"42138",
    "addr:street":"Mayor",
    "iso:country":"ES",
    "sg:address":"Mayor, S/n",
    "sg:city":"Borobia",
    "sg:orig_category":"Asociaciones, Organismos Culturales Y Socioeducativos",
    "sg:phone":"+34 976 64 63 20",
    "sg:postcode":"42138",
    "sg:province":"Soria",
    "wof:name":"Asociacion De La Tercera Edad Virgen De Los Santos",
    "wof:placetype":"venue"
},
  "geometry": {"coordinates":[-1.8976434469,41.6655273438],"type":"Point"}
}