{
  "type": "Feature",
  "properties": {
    "iso:country":"ES",
    "sg:address":"Calle de Jose Arcones Gil, 104",
    "sg:city":"Madrid",
    "sg:orig_category":"Tapiceros Y Tapiceros",
    "sg:phone":"+34 913 04 74 13",
    "sg:postcode":"28017",
    "sg:province":"Madrid",
    "wof:name":"Lopez Chacon Pascual",
    "wof:placetype":"venue"
},
  "geometry": {"coordinates":[-3.6346240044,40.4288024902],"type":"Point"}
}