{
  "type": "Feature",
  "properties": {
    "iso:country":"ES",
    "sg:address":"Urb R.nuevo Manzanares I, 22",
    "sg:city":"Manzanares",
    "sg:orig_category":"Asesor\u00cda Sobre Comunicaci\u00d3n De Empresas",
    "sg:phone":"+34 926 62 07 62",
    "sg:postcode":"13200",
    "sg:province":"Ciudad Real",
    "wof:name":"Lahoz Asesores Correduria De Seguros S.l.",
    "wof:placetype":"venue"
},
  "geometry": {"coordinates":[-3.373128891,38.994140625],"type":"Point"}
}