{
  "type": "Feature",
  "properties": {
    "addr:full":"Muelle Fernandez Ladreda, S/n Ferrol A Coru\u00f1a 15401",
    "addr:housenumber":"/ n",
    "addr:postcode":"15401",
    "addr:street":"Ladreda S;A Corun\u0303A",
    "iso:country":"ES",
    "sg:address":"Muelle Fernandez Ladreda, S/n",
    "sg:city":"Ferrol",
    "sg:orig_category":"Barcos",
    "sg:phone":"+34 981 35 21 48",
    "sg:postcode":"15401",
    "sg:province":"A Coru\u00f1a",
    "wof:name":"Sociedad Estatal De Estiba Y Desestiba Del Puerto De Ferrol S. A.",
    "wof:placetype":"venue"
},
  "geometry": {"coordinates":[-8.2273387909,43.4868507385],"type":"Point"}
}