{
  "type": "Feature",
  "properties": {
    "addr:full":"Calle de Antonio Marquez Mu\u00d1oz, S/n Torremolinos M\u00e1laga 29620",
    "addr:housenumber":"s / n",
    "addr:postcode":"29620",
    "addr:street":"Calle De Antonio Marquez Mun\u0303Oz;Ma\u0301Laga",
    "iso:country":"ES",
    "sg:address":"Calle de Antonio Marquez Mu\u00d1oz, S/n",
    "sg:city":"Torremolinos",
    "sg:orig_category":"Conservas De Legumbres (fabricaci\u00d3n, Al Por Mayor)",
    "sg:phone":"+34 952 38 63 42",
    "sg:postcode":"29620",
    "sg:province":"M\u00e1laga",
    "wof:name":"Marmolejo Salvatiel Andres",
    "wof:placetype":"venue"
},
  "geometry": {"coordinates":[-4.5153360367,36.6109848022],"type":"Point"}
}