{
  "type": "Feature",
  "properties": {
    "addr:full":"Calle de Real Sur, 5 Fuentesauco De Fuentidue\u00e7a Segovia 40355",
    "addr:housenumber":"5",
    "addr:postcode":"40355",
    "addr:street":"Calle De Real Sur",
    "iso:country":"ES",
    "sg:address":"Calle de Real Sur, 5",
    "sg:city":"Fuentesauco De Fuentidue\u00e7a",
    "sg:orig_category":"Carnicer\u00cdas, Carnicer\u00cdas",
    "sg:phone":"+34 921 16 95 36",
    "sg:postcode":"40355",
    "sg:province":"Segovia",
    "wof:name":"Cuesta Hernando Mauro",
    "wof:placetype":"venue"
},
  "geometry": {"coordinates":[-4.0650539398,41.4260902405],"type":"Point"}
}