{
  "type": "Feature",
  "properties": {
    "addr:full":"Barr Caserio Larrazabal, 1 Bilbao Vizcaya 48007",
    "addr:housenumber":"1",
    "addr:postcode":"48007",
    "addr:street":"Larrazabal",
    "iso:country":"ES",
    "sg:address":"Barr Caserio Larrazabal, 1",
    "sg:city":"Bilbao",
    "sg:orig_category":"Iglesia Cat\u00d3lica",
    "sg:phone":"+34 944 46 13 93",
    "sg:postcode":"48007",
    "sg:province":"Vizcaya",
    "wof:name":"Parroquia El Santisimo Sacramento De Zurbaran",
    "wof:placetype":"venue"
},
  "geometry": {"coordinates":[-2.9159929752,43.2644805908],"type":"Point"}
}