{
  "type": "Feature",
  "properties": {
    "iso:country":"ES",
    "sg:address":"Ctra Cartagena, Km. 0001,0",
    "sg:city":"Torre-pacheco",
    "sg:orig_category":"Distribuci\u00d3n De Petr\u00d3leo Y Derivados",
    "sg:phone":"+34 968 57 75 06",
    "sg:postcode":"30700",
    "sg:province":"Murcia",
    "wof:name":"Estaciones De Servicio La Hita S.l.",
    "wof:placetype":"venue"
},
  "geometry": {"coordinates":[-0.952203989,37.7321853638],"type":"Point"}
}