{
  "type": "Feature",
  "properties": {
    "addr:full":"Carrer de Sant Jordi, 34 Roda De Bara Tarragona 43883",
    "addr:housenumber":"34",
    "addr:postcode":"43883",
    "addr:street":"Carrer De Sant Jordi",
    "iso:country":"ES",
    "sg:address":"Carrer de Sant Jordi, 34",
    "sg:city":"Roda De Bara",
    "sg:orig_category":"Centros De Coordinaci\u00d3n",
    "sg:phone":"+34 977 65 77 43",
    "sg:postcode":"43883",
    "sg:province":"Tarragona",
    "wof:name":"Multiconsulting Tarraco S.l.",
    "wof:placetype":"venue"
},
  "geometry": {"coordinates":[1.4565399885,41.1828346252],"type":"Point"}
}