{
  "type": "Feature",
  "properties": {
    "addr:full":"Calle de Parra, 3 Yecla De Yeltes Salamanca 37219",
    "addr:housenumber":"3",
    "addr:postcode":"37219",
    "addr:street":"Calle De Parra",
    "iso:country":"ES",
    "sg:address":"Calle de Parra, 3",
    "sg:city":"Yecla De Yeltes",
    "sg:orig_category":"Empresarios",
    "sg:phone":"+34 923 50 01 57",
    "sg:postcode":"37219",
    "sg:province":"Salamanca",
    "wof:name":"Cid Martin Belisario",
    "wof:placetype":"venue"
},
  "geometry": {"coordinates":[-6.4899201393,40.9597358704],"type":"Point"}
}