{
  "type": "Feature",
  "properties": {
    "addr:full":"Calle de Hornos (los), 70 Andujar Ja\u00e9n 23740",
    "addr:housenumber":"70",
    "addr:postcode":"23740",
    "addr:street":"Calle De Hornos Los",
    "iso:country":"ES",
    "sg:address":"Calle de Hornos (los), 70",
    "sg:city":"Andujar",
    "sg:orig_category":"Alimentaci\u00d3n General (al Por Menor)",
    "sg:phone":"+34 953 50 41 53",
    "sg:postcode":"23740",
    "sg:province":"Ja\u00e9n",
    "wof:name":"Gamero Casado Juan",
    "wof:placetype":"venue"
},
  "geometry": {"coordinates":[-4.0480909348,38.0383377075],"type":"Point"}
}