{
  "type": "Feature",
  "properties": {
    "addr:full":"Calle de Clavel, 3 Espinar Segovia 40400",
    "addr:housenumber":"3",
    "addr:postcode":"40400",
    "addr:street":"Calle De Clavel",
    "iso:country":"ES",
    "sg:address":"Calle de Clavel, 3",
    "sg:city":"Espinar",
    "sg:orig_category":"Abogados",
    "sg:phone":"+34 921 18 21 57",
    "sg:postcode":"40400",
    "sg:province":"Segovia",
    "wof:name":"Sanz Orejudo Julio Gabriel",
    "wof:placetype":"venue"
},
  "geometry": {"coordinates":[-4.2444710732,40.7178688049],"type":"Point"}
}