{
  "type": "Feature",
  "properties": {
    "addr:full":"Avgd Prat De La Riba, 23 Lleida Lleida 25006",
    "addr:housenumber":"23",
    "addr:postcode":"25006",
    "addr:street":"La Riba",
    "iso:country":"ES",
    "sg:address":"Avgd Prat De La Riba, 23",
    "sg:city":"Lleida",
    "sg:orig_category":"Cajas Para Embalar",
    "sg:phone":"+34 973 23 76 49",
    "sg:postcode":"25006",
    "sg:province":"Lleida",
    "wof:name":"Caja Rural Aragonesa Y De Los Pirineos",
    "wof:placetype":"venue"
},
  "geometry": {"coordinates":[0.5619999766,41.6497535706],"type":"Point"}
}