{
  "type": "Feature",
  "properties": {
    "iso:country":"ES",
    "sg:address":"Calle de Manifiesto (del), 8",
    "sg:city":"Manzanares",
    "sg:orig_category":"Fabricaci\u00d3n De Distribuidores Autom\u00c1ticos",
    "sg:phone":"+34 926 61 37 05",
    "sg:postcode":"13200",
    "sg:province":"Ciudad Real",
    "wof:name":"Vilches Delgado Rafael",
    "wof:placetype":"venue"
},
  "geometry": {"coordinates":[-3.3706901073,38.9957008362],"type":"Point"}
}