{
  "type": "Feature",
  "properties": {
    "iso:country":"ES",
    "sg:address":"Avda Corredera, 7",
    "sg:city":"Hinojosa Del Duque",
    "sg:orig_category":"Cajas Para Embalar",
    "sg:phone":"+34 957 14 03 90",
    "sg:postcode":"14270",
    "sg:province":"C\u00f3rdoba",
    "wof:name":"Caja Rural De Cordoba",
    "wof:placetype":"venue"
},
  "geometry": {"coordinates":[-5.1470799446,38.5002937317],"type":"Point"}
}