{
  "type": "Feature",
  "properties": {
    "iso:country":"ES",
    "sg:address":"Ptge Princep De Viana, 22",
    "sg:city":"Lleida",
    "sg:orig_category":"Chapister\u00cda",
    "sg:phone":"+34 973 23 43 52",
    "sg:postcode":"25008",
    "sg:province":"Lleida",
    "wof:name":"Adillon Ari\u00f1o Joaquin",
    "wof:placetype":"venue"
},
  "geometry": {"coordinates":[0.624225378,41.6245422363],"type":"Point"}
}