{
  "type": "Feature",
  "properties": {
    "iso:country":"ES",
    "sg:address":"Avda 6, 3",
    "sg:city":"Vaciasilos",
    "sg:orig_category":"Cajas Y Embalajes De Pl\u00c1stico",
    "sg:phone":"+34 918 16 00 88",
    "sg:postcode":"28991",
    "sg:province":"Madrid",
    "sg:website":"www paginasamarillas.es",
    "wof:name":"Dempas S.l.",
    "wof:placetype":"venue"
},
  "geometry": {"coordinates":[-3.8001420498,40.1878929138],"type":"Point"}
}