{
  "type": "Feature",
  "properties": {
    "addr:full":"Calle de Urquijo Julio, 12 Bilbao Vizcaya 48014",
    "addr:housenumber":"12",
    "addr:postcode":"48014",
    "addr:street":"Calle De Urquijo Julio",
    "iso:country":"ES",
    "sg:address":"Calle de Urquijo Julio, 12",
    "sg:city":"Bilbao",
    "sg:orig_category":"Electrodom\u00c9sticos (al Por Menor)",
    "sg:phone":"+34 944 75 37 10",
    "sg:postcode":"48014",
    "sg:province":"Vizcaya",
    "wof:name":"Ana Maria Pazos Perez",
    "wof:placetype":"venue"
},
  "geometry": {"coordinates":[-2.9530341625,43.2705459595],"type":"Point"}
}