{
  "type": "Feature",
  "properties": {
    "iso:country":"ES",
    "sg:address":"Calle de Cuesta De La Margarita, 1",
    "sg:city":"Ca\u00f1izares",
    "sg:orig_category":"Empresas De Limpieza",
    "sg:phone":"+34 969 31 32 89",
    "sg:postcode":"16891",
    "sg:province":"Cuenca",
    "wof:name":"Berlise.s.l.",
    "wof:placetype":"venue"
},
  "geometry": {"coordinates":[-2.1917619705,40.5171203613],"type":"Point"}
}