{
  "type": "Feature",
  "properties": {
    "iso:country":"ES",
    "sg:address":"Calle de Carmen Quintana, 77",
    "sg:city":"Palmas De Gran Canaria",
    "sg:orig_category":"Frutas, Legumbres Frescas Y Tempranas (al Por Menor)",
    "sg:phone":"+34 928 25 68 03",
    "sg:postcode":"35014",
    "sg:province":"Las Palmas",
    "wof:name":"Garcia Ce\u00f1era Jesus Oracio",
    "wof:placetype":"venue"
},
  "geometry": {"coordinates":[-15.4315891266,28.1025238037],"type":"Point"}
}