{
  "type": "Feature",
  "properties": {
    "addr:full":"Calle de Clara Del Rey, 10 Madrid Madrid 28002",
    "addr:housenumber":"10",
    "addr:postcode":"madrid;28002",
    "addr:street":"Calle De Clara Del Rey",
    "iso:country":"ES",
    "sg:address":"Calle de Clara Del Rey, 10",
    "sg:city":"Madrid",
    "sg:orig_category":"Electricidad, Electr\u00d3nica: Suministros (al Por Menor)",
    "sg:phone":"+34 914 13 16 11",
    "sg:postcode":"28002",
    "sg:province":"Madrid",
    "sg:website":"www.gocar.es",
    "wof:name":"Gocar S. A.",
    "wof:placetype":"venue"
},
  "geometry": {"coordinates":[-3.6717097759,40.4414901733],"type":"Point"}
}