{
  "type": "Feature",
  "properties": {
    "addr:full":"Avda Reyes Catolicos, 37 Dos Hermanas Sevilla 41700",
    "addr:housenumber":"37",
    "addr:postcode":"41700",
    "addr:street":"Avda Reyes Catolicos",
    "iso:country":"ES",
    "sg:address":"Avda Reyes Catolicos, 37",
    "sg:city":"Dos Hermanas",
    "sg:orig_category":"Sociedades, Compa\u00d1\u00cdas Aseguradoras",
    "sg:phone":"+34 955 67 51 99",
    "sg:postcode":"41700",
    "sg:province":"Sevilla",
    "wof:name":"Sanchez Venegas S.l",
    "wof:placetype":"venue"
},
  "geometry": {"coordinates":[-5.9245958328,37.2783050537],"type":"Point"}
}