{
  "type": "Feature",
  "properties": {
    "iso:country":"ES",
    "sg:address":"Calle de Lares, 9",
    "sg:city":"Villanueva Serena",
    "sg:orig_category":"Agentes Generales De Seguros",
    "sg:phone":"+34 924 84 76 69",
    "sg:postcode":"06700",
    "sg:province":"Badajoz",
    "wof:name":"Se\u00f1or Nieto Juan Pedro",
    "wof:placetype":"venue"
},
  "geometry": {"coordinates":[-5.7993988991,38.9737586975],"type":"Point"}
}