{
  "type": "Feature",
  "properties": {
    "addr:full":"Calle de Avecilla, 6 Madrid Madrid 28025",
    "addr:housenumber":"6",
    "addr:postcode":"28025",
    "addr:street":"Calle De Avecilla",
    "iso:country":"ES",
    "sg:address":"Calle de Avecilla, 6",
    "sg:city":"Madrid",
    "sg:orig_category":"Bisuter\u00cda, Joyer\u00cda, Relojer\u00cda (al Por Menor)",
    "sg:phone":"+34 914 66 45 82",
    "sg:postcode":"28025",
    "sg:province":"Madrid",
    "wof:name":"Torres Cerro Javier",
    "wof:placetype":"venue"
},
  "geometry": {"coordinates":[-3.7362480164,40.3884277344],"type":"Point"}
}