{
  "type": "Feature",
  "properties": {
    "addr:full":"Calle de Iturribide, 111 Bilbao Vizcaya 48006",
    "addr:housenumber":"111",
    "addr:postcode":"48006",
    "addr:street":"Calle De Iturribide",
    "iso:country":"ES",
    "sg:address":"Calle de Iturribide, 111",
    "sg:city":"Bilbao",
    "sg:orig_category":"Lencer\u00cda Femenina, Corseter\u00cda, Trajes De Ba\u00d1o (al Por Menor)",
    "sg:phone":"+34 944 33 07 82",
    "sg:postcode":"48006",
    "sg:province":"Vizcaya",
    "wof:name":"Calvo Terradillos Maria Angeles",
    "wof:placetype":"venue"
},
  "geometry": {"coordinates":[-2.9167668819,43.2552947998],"type":"Point"}
}