{
  "type": "Feature",
  "properties": {
    "addr:full":"Calle de Jacinto, 31 Girasoles Sevilla 41907",
    "addr:housenumber":"31",
    "addr:postcode":"41907",
    "addr:street":"Calle De Jacinto",
    "iso:country":"ES",
    "sg:address":"Calle de Jacinto, 31",
    "sg:city":"Girasoles",
    "sg:orig_category":"Suministros Para Hoteles",
    "sg:phone":"+34 955 99 96 43",
    "sg:postcode":"41907",
    "sg:province":"Sevilla",
    "sg:website":"www.chandalu.com",
    "wof:name":"Comercial Hostelera Andaluza S. A.",
    "wof:placetype":"venue"
},
  "geometry": {"coordinates":[-6.0776147842,37.4170455933],"type":"Point"}
}