{
  "type": "Feature",
  "properties": {
    "addr:full":"Rua Real, 84 Ferrol A Coru\u00f1a 15402",
    "addr:housenumber":"84",
    "addr:postcode":"15402",
    "addr:street":"Rua Real;A Corun\u0303A",
    "iso:country":"ES",
    "sg:address":"Rua Real, 84",
    "sg:city":"Ferrol",
    "sg:orig_category":"Zapater\u00cdas",
    "sg:phone":"+34 981 35 26 00",
    "sg:postcode":"15402",
    "sg:province":"A Coru\u00f1a",
    "wof:name":"Timora S.a.",
    "wof:placetype":"venue"
},
  "geometry": {"coordinates":[-8.2335577011,43.4838905334],"type":"Point"}
}