{
  "type": "Feature",
  "properties": {
    "iso:country":"ES",
    "sg:address":"Calle de Granados, 44",
    "sg:city":"Almoradi",
    "sg:orig_category":"Agencias Y Agentes Comerciales, Representantes",
    "sg:phone":"+34 965 70 17 68",
    "sg:postcode":"03160",
    "sg:province":"Alicante",
    "wof:name":"Garcia Arias Antonio",
    "wof:placetype":"venue"
},
  "geometry": {"coordinates":[-0.7951490283,38.1133499146],"type":"Point"}
}