{
  "type": "Feature",
  "properties": {
    "addr:full":"Calle de Arrabal, 34 Torrijos Toledo 45500",
    "addr:housenumber":"34",
    "addr:postcode":"45500",
    "addr:street":"Calle De Arrabal",
    "iso:country":"ES",
    "sg:address":"Calle de Arrabal, 34",
    "sg:city":"Torrijos",
    "sg:orig_category":"Molduras, Junquillos, Listones Y Molduras Perforadas",
    "sg:phone":"+34 925 77 11 36",
    "sg:postcode":"45500",
    "sg:province":"Toledo",
    "wof:name":"Fernandez Maqueda Encarna",
    "wof:placetype":"venue"
},
  "geometry": {"coordinates":[-4.2863340378,39.9847869873],"type":"Point"}
}