{
  "type": "Feature",
  "properties": {
    "iso:country":"ES",
    "sg:address":"Calle de Libreros, 24",
    "sg:city":"Alcala Henares",
    "sg:orig_category":"Centros De Coordinaci\u00d3n",
    "sg:phone":"+34 918 78 96 14",
    "sg:postcode":"28801",
    "sg:province":"Madrid",
    "wof:name":"Francis Lingerie S.l.",
    "wof:placetype":"venue"
},
  "geometry": {"coordinates":[-3.3630850315,40.4840126038],"type":"Point"}
}