{
  "type": "Feature",
  "properties": {
    "iso:country":"ES",
    "sg:address":"Rond Alfons X El Savi (d'), 20",
    "sg:city":"Mataro",
    "sg:orig_category":"Fabricaci\u00d3n De Su\u00c9ters Y Chalecos De Punto",
    "sg:phone":"+34 937 55 15 63",
    "sg:postcode":"08301",
    "sg:province":"Barcelona",
    "wof:name":"Pratdepadua Sanchez Juan",
    "wof:placetype":"venue"
},
  "geometry": {"coordinates":[2.4436058998,41.5450592041],"type":"Point"}
}