{
  "type": "Feature",
  "properties": {
    "iso:country":"ES",
    "sg:address":"Calle de Domingo Salazar, 84",
    "sg:city":"Victoria Acentejo",
    "sg:orig_category":"Empresas De Carpinter\u00cda De Madera",
    "sg:phone":"+34 922 58 13 80",
    "sg:postcode":"38380",
    "sg:province":"Santa Cruz De Tenerife",
    "wof:name":"Abreu Febles Domingo",
    "wof:placetype":"venue"
},
  "geometry": {"coordinates":[-16.473667,28.431723],"type":"Point"}
}