{
  "type": "Feature",
  "properties": {
    "iso:country":"ES",
    "sg:address":"Sierra Alto Rey, 11",
    "sg:city":"Ciudad Valgreen",
    "sg:orig_category":"Piscinas, Accesorios, Suministros (fabricaci\u00d3n, Al Por Mayor)",
    "sg:phone":"+34 949 27 35 20",
    "sg:postcode":"19209",
    "sg:province":"Guadalajara",
    "wof:name":"Mu\u00f1oz Moreno Mario Fernando",
    "wof:placetype":"venue"
},
  "geometry": {"coordinates":[-3.3041989803,40.5795516968],"type":"Point"}
}