{
  "type": "Feature",
  "properties": {
    "iso:country":"ES",
    "sg:address":"Calle de Sagasta, 1",
    "sg:city":"Sevilla",
    "sg:orig_category":"Trajes Y Adornos De Boda (confecci\u00d3n, Al Por Menor)",
    "sg:phone":"+34 954 21 91 00",
    "sg:postcode":"41004",
    "sg:province":"Sevilla",
    "wof:name":"Medina Rodriguez Cristina",
    "wof:placetype":"venue"
},
  "geometry": {"coordinates":[-5.9935173988,37.3901672363],"type":"Point"}
}