{
  "type": "Feature",
  "properties": {
    "iso:country":"ES",
    "sg:address":"Calle de Perales, 2",
    "sg:city":"Marmolejo",
    "sg:orig_category":"Cl\u00cdnicas Dentales",
    "sg:phone":"+34 953 51 74 85",
    "sg:postcode":"23770",
    "sg:province":"Ja\u00e9n",
    "wof:name":"Ruiz Jurado Clara Eugenia",
    "wof:placetype":"venue"
},
  "geometry": {"coordinates":[-4.1704931259,38.0454673767],"type":"Point"}
}