{
  "type": "Feature",
  "properties": {
    "iso:country":"ES",
    "sg:address":"Calle de Juan Diges Anton, 21",
    "sg:city":"Guadalajara",
    "sg:orig_category":"Herboristas (al Por Menor)",
    "sg:phone":"+34 949 25 42 41",
    "sg:postcode":"19003",
    "sg:province":"Guadalajara",
    "wof:name":"Romero Lobera Maria Concepcion",
    "wof:placetype":"venue"
},
  "geometry": {"coordinates":[-3.1683430672,40.6279258728],"type":"Point"}
}