{
  "type": "Feature",
  "properties": {
    "addr:full":"Calle de San Antonio, 28 Cella Teruel 44370",
    "addr:housenumber":"28",
    "addr:postcode":"44370",
    "addr:street":"Calle De San Antonio",
    "iso:country":"ES",
    "sg:address":"Calle de San Antonio, 28",
    "sg:city":"Cella",
    "sg:orig_category":"Autob\u00das (explotaci\u00d3n Y Servicios De)",
    "sg:phone":"+34 978 65 31 86",
    "sg:postcode":"44370",
    "sg:province":"Teruel",
    "wof:name":"Autobuses Pechuan S.l.",
    "wof:placetype":"venue"
},
  "geometry": {"coordinates":[-1.2785915136,40.4540786743],"type":"Point"}
}