{
  "type": "Feature",
  "properties": {
    "iso:country":"ES",
    "sg:address":"Poli Mies (la), 57",
    "sg:city":"Requejada",
    "sg:orig_category":"Fabricaci\u00d3n Y Refinado De Az\u00dacares",
    "sg:phone":"+34 942 82 47 11",
    "sg:postcode":"39312",
    "sg:province":"Cantabria",
    "wof:name":"Revuelta Abascal Urbano",
    "wof:placetype":"venue"
},
  "geometry": {"coordinates":[-4.0026488304,43.3836746216],"type":"Point"}
}