{
  "type": "Feature",
  "properties": {
    "addr:full":"Calle de Requinto (el), 4 Arrecife Las Palmas 35500",
    "addr:housenumber":"4",
    "addr:postcode":"35500",
    "addr:street":"Calle De Requinto El",
    "iso:country":"ES",
    "sg:address":"Calle de Requinto (el), 4",
    "sg:city":"Arrecife",
    "sg:orig_category":"Empresas De Carpinter\u00cda De Madera",
    "sg:phone":"+34 928 80 42 71",
    "sg:postcode":"35500",
    "sg:province":"Las Palmas",
    "wof:name":"Bola\u00f1os Martin Jose Manuel",
    "wof:placetype":"venue"
},
  "geometry": {"coordinates":[-13.5449285507,28.9622707367],"type":"Point"}
}