{
  "type": "Feature",
  "properties": {
    "iso:country":"ES",
    "sg:address":"Ctra Valtierra, 3",
    "sg:city":"Azagra",
    "sg:orig_category":"Conservas De Legumbres (fabricaci\u00d3n, Al Por Mayor)",
    "sg:phone":"+34 948 69 29 25",
    "sg:postcode":"31560",
    "sg:province":"Navarra",
    "wof:name":"Simes S.l.",
    "wof:placetype":"venue"
},
  "geometry": {"coordinates":[-1.896873951,42.3064842224],"type":"Point"}
}