{
  "type": "Feature",
  "properties": {
    "addr:full":"Calle de Arroyo Enmedio, S/n Yeste Albacete 02480",
    "addr:housenumber":"s / n",
    "addr:postcode":"02480",
    "addr:street":"Calle De Arroyo Enmedio;Yeste",
    "iso:country":"ES",
    "sg:address":"Calle de Arroyo Enmedio, S/n",
    "sg:city":"Yeste",
    "sg:orig_category":"Empresas De Carpinter\u00cda Met\u00c1lica",
    "sg:phone":"+34 967 43 12 27",
    "sg:postcode":"02480",
    "sg:province":"Albacete",
    "wof:name":"Sanchez Sanchez Mariano",
    "wof:placetype":"venue"
},
  "geometry": {"coordinates":[-2.316788435,38.3681488037],"type":"Point"}
}