{
  "type": "Feature",
  "properties": {
    "iso:country":"ES",
    "sg:address":"Pg Barcelona, 2",
    "sg:city":"Olot",
    "sg:orig_category":"Florister\u00cdas",
    "sg:phone":"+34 972 26 82 43",
    "sg:postcode":"17800",
    "sg:province":"Girona",
    "wof:name":"Batlle Matabosch Narciso",
    "wof:placetype":"venue"
},
  "geometry": {"coordinates":[2.4846289158,42.1795654297],"type":"Point"}
}