{
  "type": "Feature",
  "properties": {
    "iso:country":"ES",
    "sg:address":"Rua Pura Y Dora Vazquez, 25",
    "sg:city":"Ourense",
    "sg:orig_category":"Embalajes",
    "sg:phone":"+34 988 24 75 22",
    "sg:postcode":"32002",
    "sg:province":"Ourense",
    "wof:name":"Textil Caritas Orense S.l.u.",
    "wof:placetype":"venue"
},
  "geometry": {"coordinates":[-7.8683238029,42.3354415894],"type":"Point"}
}