{
  "type": "Feature",
  "properties": {
    "addr:full":"Av Vila Joiosa, 28 Benidorm Alicante 03500",
    "addr:housenumber":"28",
    "addr:postcode":"03500",
    "addr:street":"Av Vila Joiosa",
    "iso:country":"ES",
    "sg:address":"Av Vila Joiosa, 28",
    "sg:city":"Benidorm",
    "sg:orig_category":"Agentes, Concesionarios Y Sucursales De Veh\u00cdculos",
    "sg:phone":"+34 966 81 23 31",
    "sg:postcode":"03500",
    "sg:province":"Alicante",
    "sg:website":"www.centauro.net",
    "wof:name":"Centauro Rent A Car S.l.",
    "wof:placetype":"venue"
},
  "geometry": {"coordinates":[-0.1637690067,38.532913208],"type":"Point"}
}