{
  "type": "Feature",
  "properties": {
    "addr:full":"Calle de Gremis (els), 21 Teulada Alicante 03725",
    "addr:housenumber":"21",
    "addr:postcode":"03725",
    "addr:street":"Calle De Gremis Els",
    "iso:country":"ES",
    "sg:address":"Calle de Gremis (els), 21",
    "sg:city":"Teulada",
    "sg:orig_category":"Molduras, Junquillos, Listones Y Molduras Perforadas",
    "sg:phone":"+34 965 74 10 44",
    "sg:postcode":"03725",
    "sg:province":"Alicante",
    "wof:name":"Martinez Diaz Jose Luis",
    "wof:placetype":"venue"
},
  "geometry": {"coordinates":[0.0925548971,38.72914505],"type":"Point"}
}