{
  "type": "Feature",
  "properties": {
    "iso:country":"ES",
    "sg:address":"Carr Del Music Martinez Valls, 40",
    "sg:city":"Ontinyent",
    "sg:orig_category":"Agencias Y Agentes Comerciales, Representantes",
    "sg:phone":"+34 962 38 14 02",
    "sg:postcode":"46870",
    "sg:province":"Valencia",
    "wof:name":"Guillen Llin Enrique",
    "wof:placetype":"venue"
},
  "geometry": {"coordinates":[-0.6011719704,38.823677063],"type":"Point"}
}