{
  "type": "Feature",
  "properties": {
    "addr:full":"Urb Caba\u00f1as, 3 Denia Alicante 03700",
    "addr:housenumber":"3",
    "addr:postcode":"03700",
    "addr:street":"Urb Caban\u0303As",
    "iso:country":"ES",
    "sg:address":"Urb Caba\u00f1as, 3",
    "sg:city":"Denia",
    "sg:orig_category":"Sociedades, Compa\u00d1\u00cdas Aseguradoras",
    "sg:phone":"+34 966 47 44 18",
    "sg:postcode":"03700",
    "sg:province":"Alicante",
    "wof:name":"Aura Pascual Jose Enrique",
    "wof:placetype":"venue"
},
  "geometry": {"coordinates":[0.0840215012,38.8309745789],"type":"Point"}
}