{
  "type": "Feature",
  "properties": {
    "iso:country":"ES",
    "sg:address":"Carr Hort De Bordes, 1",
    "sg:city":"Benissa",
    "sg:orig_category":"Mercer\u00cda, Lencer\u00cda (al Por Menor)",
    "sg:phone":"+34 965 73 03 17",
    "sg:postcode":"03720",
    "sg:province":"Alicante",
    "wof:name":"Ivars Coello Maria Josefa",
    "wof:placetype":"venue"
},
  "geometry": {"coordinates":[0.0476199985,38.7148094177],"type":"Point"}
}