{
  "type": "Feature",
  "properties": {
    "iso:country":"ES",
    "sg:address":"Mercado De Abastos, S/n",
    "sg:city":"Alzira",
    "sg:orig_category":"Frutas Y Legumbres Frescas (al Por Mayor)",
    "sg:phone":"+34 962 40 43 60",
    "sg:postcode":"46600",
    "sg:province":"Valencia",
    "wof:name":"Mascarell Martinez Graciano",
    "wof:placetype":"venue"
},
  "geometry": {"coordinates":[-0.4378489852,39.1517295837],"type":"Point"}
}