{
  "type": "Feature",
  "properties": {
    "iso:country":"ES",
    "sg:address":"Calle de Montemar, 3",
    "sg:city":"Guadalajara",
    "sg:orig_category":"Zapater\u00cdas",
    "sg:phone":"+34 949 21 33 85",
    "sg:postcode":"19001",
    "sg:province":"Guadalajara",
    "wof:name":"Olmeda Carraux Juan Carlos",
    "wof:placetype":"venue"
},
  "geometry": {"coordinates":[-3.1654040813,40.6314735413],"type":"Point"}
}