{
  "type": "Feature",
  "properties": {
    "iso:country":"ES",
    "sg:address":"Carrer de Santa Maria, 17",
    "sg:city":"Mataro",
    "sg:orig_category":"Carnicer\u00cdas, Carnicer\u00cdas",
    "sg:phone":"+34 937 90 35 66",
    "sg:postcode":"08301",
    "sg:province":"Barcelona",
    "wof:name":"Cabo Rodrigo Carmen De",
    "wof:placetype":"venue"
},
  "geometry": {"coordinates":[2.4465699196,41.5402412415],"type":"Point"}
}