{
  "type": "Feature",
  "properties": {
    "addr:full":"Avda Fenar, 1 Robla Le\u00f3n 24640",
    "addr:housenumber":"1",
    "addr:postcode":"24640",
    "addr:street":"Avda Fenar;Leo\u0301N",
    "iso:country":"ES",
    "sg:address":"Avda Fenar, 1",
    "sg:city":"Robla",
    "sg:orig_category":"Panader\u00cdas, Panader\u00cdas",
    "sg:phone":"+34 987 57 04 05",
    "sg:postcode":"24640",
    "sg:province":"Le\u00f3n",
    "wof:name":"Garcia Gutierrez Jesus",
    "wof:placetype":"venue"
},
  "geometry": {"coordinates":[-5.6288585663,42.8015632629],"type":"Point"}
}