{
  "type": "Feature",
  "properties": {
    "iso:country":"ES",
    "sg:address":"Carrer de Illes Balears, 16",
    "sg:city":"Pineda Mar",
    "sg:orig_category":"Cl\u00cdnicas M\u00c9dicas",
    "sg:phone":"+34 937 62 48 07",
    "sg:postcode":"08397",
    "sg:province":"Barcelona",
    "wof:name":"Pujol Gomez Eulalia",
    "wof:placetype":"venue"
},
  "geometry": {"coordinates":[2.6982119083,41.6265220642],"type":"Point"}
}