{
  "type": "Feature",
  "properties": {
    "iso:country":"ES",
    "sg:address":"Plaz Davalos, 8",
    "sg:city":"Guadalajara",
    "sg:orig_category":"Empresarios",
    "sg:phone":"+34 949 21 31 41",
    "sg:postcode":"19001",
    "sg:province":"Guadalajara",
    "wof:name":"Abad Alejandre Urbano",
    "wof:placetype":"venue"
},
  "geometry": {"coordinates":[-3.168575,40.634167],"type":"Point"}
}