{
  "type": "Feature",
  "properties": {
    "iso:country":"ES",
    "sg:address":"Calle de Emilio Jimeno, 5",
    "sg:city":"Calatayud",
    "sg:orig_category":"Productos Qu\u00cdmicos (fabricaci\u00d3n, Al Por Mayor)",
    "sg:phone":"+34 976 88 17 67",
    "sg:postcode":"50300",
    "sg:province":"Zaragoza",
    "wof:name":"Vicente Gregorio Ricardo",
    "wof:placetype":"venue"
},
  "geometry": {"coordinates":[-1.6410779953,41.3487663269],"type":"Point"}
}