{
  "type": "Feature",
  "properties": {
    "addr:full":"Avda Enrique Mederos, 2 Llanos De Aridane Santa Cruz De Tenerife 38760",
    "addr:housenumber":"2",
    "addr:postcode":"38760",
    "addr:street":"Avda Enrique Mederos",
    "iso:country":"ES",
    "sg:address":"Avda Enrique Mederos, 2",
    "sg:city":"Llanos De Aridane",
    "sg:orig_category":"Veh\u00cdculos De Ocasi\u00d3n",
    "sg:phone":"+34 922 46 37 16",
    "sg:postcode":"38760",
    "sg:province":"Santa Cruz De Tenerife",
    "wof:name":"Autos Ericar S.l.",
    "wof:placetype":"venue"
},
  "geometry": {"coordinates":[-17.9137134552,28.6593780518],"type":"Point"}
}