{
  "type": "Feature",
  "properties": {
    "addr:full":"Calle de Juan Anton, 19 Madrid Madrid 28011",
    "addr:housenumber":"19",
    "addr:postcode":"madrid;28011",
    "addr:street":"Calle De Juan Anton",
    "iso:country":"ES",
    "sg:address":"Calle de Juan Anton, 19",
    "sg:city":"Madrid",
    "sg:orig_category":"Agentes Generales De Seguros",
    "sg:phone":"+34 914 63 75 76",
    "sg:postcode":"28011",
    "sg:province":"Madrid",
    "wof:name":"Romero Alfonso Javier",
    "wof:placetype":"venue"
},
  "geometry": {"coordinates":[-3.7365279198,40.4097557068],"type":"Point"}
}