{
  "type": "Feature",
  "properties": {
    "iso:country":"ES",
    "sg:address":"Pase Ronda, 10",
    "sg:city":"Lopera",
    "sg:orig_category":"Transportes Por V\u00cdas Navegables",
    "sg:phone":"+34 953 51 68 08",
    "sg:postcode":"23780",
    "sg:province":"Ja\u00e9n",
    "wof:name":"Romero Mu\u00f1oz Juan",
    "wof:placetype":"venue"
},
  "geometry": {"coordinates":[-4.2099790573,37.9468078613],"type":"Point"}
}