{
  "type": "Feature",
  "properties": {
    "addr:full":"Rua Murillo, 36 Ourense Ourense 32002",
    "addr:housenumber":"36",
    "addr:postcode":"32002",
    "addr:street":"Rua Murillo",
    "iso:country":"ES",
    "sg:address":"Rua Murillo, 36",
    "sg:city":"Ourense",
    "sg:orig_category":"Pizzer\u00cdas",
    "sg:phone":"+34 988 24 26 78",
    "sg:postcode":"32002",
    "sg:province":"Ourense",
    "wof:name":"Garcia Escudero Jose",
    "wof:placetype":"venue"
},
  "geometry": {"coordinates":[-7.8730998039,42.3426704407],"type":"Point"}
}