{
  "type": "Feature",
  "properties": {
    "iso:country":"ES",
    "sg:address":"Calle de Nicolas Alvarez, 1",
    "sg:city":"Zamoranos",
    "sg:orig_category":"Librer\u00cdas",
    "sg:phone":"+34 957 55 61 27",
    "sg:postcode":"14814",
    "sg:province":"C\u00f3rdoba",
    "wof:name":"Ruiz Fernandez Maria Jose",
    "wof:placetype":"venue"
},
  "geometry": {"coordinates":[-4.1611390114,37.5269050598],"type":"Point"}
}