{
  "type": "Feature",
  "properties": {
    "iso:country":"ES",
    "sg:address":"Rua Eduardo Pondal, 34",
    "sg:city":"Pontevedra",
    "sg:orig_category":"Empresas De Vigilancia, Guardia Y Protecci\u00d3n",
    "sg:phone":"+34 986 86 23 18",
    "sg:postcode":"36003",
    "sg:province":"Pontevedra",
    "sg:website":"www.grupocetssa.com",
    "wof:name":"Grupo Cetssa Seguridad S.a.",
    "wof:placetype":"venue"
},
  "geometry": {"coordinates":[-8.6339120865,42.4182281494],"type":"Point"}
}