{
  "type": "Feature",
  "properties": {
    "iso:country":"ES",
    "sg:address":"Calle de Torres Quevedo, 31",
    "sg:city":"Zaragoza",
    "sg:orig_category":"Carnicer\u00cdas, Carnicer\u00cdas",
    "sg:phone":"+34 976 31 31 11",
    "sg:postcode":"50010",
    "sg:province":"Zaragoza",
    "wof:name":"Andari S.l.",
    "wof:placetype":"venue"
},
  "geometry": {"coordinates":[-0.907125175,41.654586792],"type":"Point"}
}