{
  "type": "Feature",
  "properties": {
    "addr:full":"Calle de Comercio (el), 10 Aparecida Alicante 03311",
    "addr:postcode":"03311",
    "addr:street":"Calle De Comercio El",
    "iso:country":"ES",
    "sg:address":"Calle de Comercio (el), 10",
    "sg:city":"Aparecida",
    "sg:orig_category":"Molduras, Junquillos, Listones Y Molduras Perforadas",
    "sg:phone":"+34 965 30 32 84",
    "sg:postcode":"03311",
    "sg:province":"Alicante",
    "wof:name":"Juarez Aix Maria Encarnacion",
    "wof:placetype":"venue"
},
  "geometry": {"coordinates":[-1.0080697536,38.0797691345],"type":"Point"}
}