{
  "type": "Feature",
  "properties": {
    "addr:full":"Calle de Canteros De Trasmiera, 20 Monte Cantabria 39012",
    "addr:housenumber":"20",
    "addr:postcode":"39012",
    "addr:street":"Calle De Canteros De Trasmiera",
    "iso:country":"ES",
    "sg:address":"Calle de Canteros De Trasmiera, 20",
    "sg:city":"Monte",
    "sg:orig_category":"M\u00c9dicos: Medicina Interna",
    "sg:phone":"+34 942 34 71 14",
    "sg:postcode":"39012",
    "sg:province":"Cantabria",
    "wof:name":"Villanueva Diaz-canel Manuel",
    "wof:placetype":"venue"
},
  "geometry": {"coordinates":[-3.8265690804,43.4702301025],"type":"Point"}
}