{
  "type": "Feature",
  "properties": {
    "iso:country":"ES",
    "sg:address":"Pg Torras I Bages, 17",
    "sg:city":"Barcelona",
    "sg:orig_category":"Panader\u00cdas, Panader\u00cdas",
    "sg:phone":"+34 933 45 39 49",
    "sg:postcode":"08030",
    "sg:province":"Barcelona",
    "wof:name":"Dialypa S.l.",
    "wof:placetype":"venue"
},
  "geometry": {"coordinates":[2.1909999847,41.437122345],"type":"Point"}
}