{
  "type": "Feature",
  "properties": {
    "addr:full":"Avda Miguel Servet, 18 Utebo Zaragoza 50180",
    "addr:housenumber":"18",
    "addr:postcode":"50180",
    "addr:street":"Avda Miguel Servet",
    "iso:country":"ES",
    "sg:address":"Avda Miguel Servet, 18",
    "sg:city":"Utebo",
    "sg:orig_category":"Productos Qu\u00cdmicos (fabricaci\u00d3n, Al Por Mayor)",
    "sg:phone":"+34 976 78 74 85",
    "sg:postcode":"50180",
    "sg:province":"Zaragoza",
    "wof:name":"Ingenieria Y Servicios Consultores S. A.",
    "wof:placetype":"venue"
},
  "geometry": {"coordinates":[-1.0183470249,41.7151603699],"type":"Point"}
}