{
  "type": "Feature",
  "properties": {
    "addr:full":"Ctra Fuerte Del Rey, Km. 0003,5 Jaen Ja\u00e9n 23006",
    "addr:postcode":"23006",
    "addr:street":"Ctra Fuerte Del Rey Km. 0003,5 Jaen Jae\u0301N",
    "iso:country":"ES",
    "sg:address":"Ctra Fuerte Del Rey, Km. 0003,5",
    "sg:city":"Jaen",
    "sg:orig_category":"Muebles Y Accesorios Para Cocinas Y Cuartos De Ba\u00d1o (al Por Menor)",
    "sg:phone":"+34 953 26 51 24",
    "sg:postcode":"23006",
    "sg:province":"Ja\u00e9n",
    "wof:name":"Sanchez Iba\u00f1ez Luis",
    "wof:placetype":"venue"
},
  "geometry": {"coordinates":[-3.7975718975,37.7809104919],"type":"Point"}
}