{
  "type": "Feature",
  "properties": {
    "addr:full":"Pase Heriz De, 95 Donostia-san Sebastian Guip\u00f9zcoa 20008",
    "addr:housenumber":"95",
    "addr:postcode":"20008",
    "iso:country":"ES",
    "sg:address":"Pase Heriz De, 95",
    "sg:city":"Donostia-san Sebastian",
    "sg:orig_category":"Ense\u00d1anza, Formaci\u00d3n Profesional: Aprendizaje",
    "sg:phone":"+34 943 31 08 73",
    "sg:postcode":"20008",
    "sg:province":"Guip\u00f9zcoa",
    "wof:name":"Centro Informatico Profesional Ceinpro S.l.",
    "wof:placetype":"venue"
},
  "geometry": {"coordinates":[-2.0402700901,43.3095817566],"type":"Point"}
}