{
  "type": "Feature",
  "properties": {
    "addr:full":"Calle de San Mateo, S/n San Fernando Las Palmas 35100",
    "addr:housenumber":"s / n",
    "addr:postcode":"35100",
    "addr:street":"Calle De San",
    "iso:country":"ES",
    "sg:address":"Calle de San Mateo, S/n",
    "sg:city":"San Fernando",
    "sg:orig_category":"Ense\u00d1anza, Formaci\u00d3n Profesional: Aprendizaje",
    "sg:phone":"+34 928 76 42 01",
    "sg:postcode":"35100",
    "sg:province":"Las Palmas",
    "wof:name":"Ayuntamiento De San Bartolome De Tirajana",
    "wof:placetype":"venue"
},
  "geometry": {"coordinates":[-15.5553674698,28.0579051971],"type":"Point"}
}