{
  "type": "Feature",
  "properties": {
    "addr:full":"Carrer de Sant Josep, 26 Calella Barcelona 08370",
    "addr:housenumber":"26",
    "addr:postcode":"08370",
    "addr:street":"Carrer De Sant Josep",
    "iso:country":"ES",
    "sg:address":"Carrer de Sant Josep, 26",
    "sg:city":"Calella",
    "sg:orig_category":"Molduras, Junquillos, Listones Y Molduras Perforadas",
    "sg:phone":"+34 937 69 51 91",
    "sg:postcode":"08370",
    "sg:province":"Barcelona",
    "wof:name":"Mayo Brenya Jose Manuel",
    "wof:placetype":"venue"
},
  "geometry": {"coordinates":[2.6611709595,41.6139373779],"type":"Point"}
}