{
  "type": "Feature",
  "properties": {
    "iso:country":"ES",
    "sg:address":"Calle de Domenico Scarlatti, 5",
    "sg:city":"Madrid",
    "sg:orig_category":"Art\u00cdculos De Decoraci\u00d3n",
    "sg:phone":"+34 915 50 05 48",
    "sg:postcode":"28003",
    "sg:province":"Madrid",
    "sg:website":"www.sentiselon.com",
    "wof:name":"Galeria Selon S.l.",
    "wof:placetype":"venue"
},
  "geometry": {"coordinates":[-3.7159130573,40.4415893555],"type":"Point"}
}