{
  "type": "Feature",
  "properties": {
    "addr:full":"Carrer de Santa Anna, Km. 0004,2 Santpedor Barcelona 08251",
    "addr:postcode":"08251",
    "addr:street":"Carrer De Santa Anna Km. 0004,2",
    "iso:country":"ES",
    "sg:address":"Carrer de Santa Anna, Km. 0004,2",
    "sg:city":"Santpedor",
    "sg:orig_category":"Trabajos De Perforaciones, Sondeos, Construcci\u00d3n De Pozos",
    "sg:phone":"+34 938 36 60 11",
    "sg:postcode":"08251",
    "sg:province":"Barcelona",
    "sg:website":"www.catalanadeperforacions.com",
    "wof:name":"Catalana De Perforacions S.a.",
    "wof:placetype":"venue"
},
  "geometry": {"coordinates":[1.8402600288,41.7844352722],"type":"Point"}
}