{
  "type": "Feature",
  "properties": {
    "iso:country":"ES",
    "sg:address":"Avda Gipuzkoa, 4",
    "sg:city":"Irun",
    "sg:orig_category":"Abogados",
    "sg:phone":"+34 943 66 01 21",
    "sg:postcode":"20302",
    "sg:province":"Guip\u00f9zcoa",
    "wof:name":"Gamazo Pedrosa Inmaculada",
    "wof:placetype":"venue"
},
  "geometry": {"coordinates":[-1.7946859598,43.3400650024],"type":"Point"}
}