{
  "type": "Feature",
  "properties": {
    "addr:full":"Isaac Peral, S/n Valdemoro Madrid 28340",
    "addr:housenumber":"s / n",
    "addr:postcode":"28340",
    "addr:street":"Isaac Peral",
    "iso:country":"ES",
    "sg:address":"Isaac Peral, S/n",
    "sg:city":"Valdemoro",
    "sg:orig_category":"Laminadoras",
    "sg:phone":"+34 918 95 01 09",
    "sg:postcode":"28340",
    "sg:province":"Madrid",
    "wof:name":"Aceros Valdemoro S.a.",
    "wof:placetype":"venue"
},
  "geometry": {"coordinates":[-3.6661746502,40.1624717712],"type":"Point"}
}