{
  "type": "Feature",
  "properties": {
    "addr:full":"Cintruenigo, 9 Iru\u00f1a Navarra 31015",
    "addr:housenumber":"9",
    "addr:postcode":"31015",
    "addr:street":"Cintruenigo",
    "iso:country":"ES",
    "sg:address":"Cintruenigo, 9",
    "sg:city":"Iru\u00f1a",
    "sg:orig_category":"Promotores Constructores",
    "sg:phone":"+34 948 14 54 49",
    "sg:postcode":"31015",
    "sg:province":"Navarra",
    "wof:name":"Busto Ayerra Ignacio",
    "wof:placetype":"venue"
},
  "geometry": {"coordinates":[-1.6289499998,42.827457428],"type":"Point"}
}