{
  "type": "Feature",
  "properties": {
    "iso:country":"ES",
    "sg:address":"Rua Fontela (da), S/n",
    "sg:city":"Burela",
    "sg:orig_category":"Ense\u00d1anza, Formaci\u00d3n Profesional: Aprendizaje",
    "sg:phone":"+34 982 58 11 41",
    "sg:postcode":"27880",
    "sg:province":"Lugo",
    "wof:name":"Concello De Burela-c.xuventude.e.m.musica",
    "wof:placetype":"venue"
},
  "geometry": {"coordinates":[-7.3684840202,43.6606292725],"type":"Point"}
}