{
  "type": "Feature",
  "properties": {
    "addr:full":"Crt. Carrion, Km. 0313,0 Miguelturra Ciudad Real 13170",
    "addr:postcode":"13170",
    "addr:street":"Km. 0313,0",
    "iso:country":"ES",
    "sg:address":"Crt. Carrion, Km. 0313,0",
    "sg:city":"Miguelturra",
    "sg:orig_category":"Distribuci\u00d3n De Petr\u00d3leo Y Derivados",
    "sg:phone":"+34 926 27 16 99",
    "sg:postcode":"13170",
    "sg:province":"Ciudad Real",
    "wof:name":"Energeticos De La Mancha S.a.",
    "wof:placetype":"venue"
},
  "geometry": {"coordinates":[-3.8970448971,38.968372345],"type":"Point"}
}