{
  "type": "Feature",
  "properties": {
    "iso:country":"ES",
    "sg:address":"Calle de Labradores, 20",
    "sg:city":"Logro\u00f1o",
    "sg:orig_category":"Delegados, Agentes De Tr\u00c1nsito, Auxiliares De Transporte Internacional",
    "sg:phone":"+34 941 22 18 97",
    "sg:postcode":"26005",
    "sg:province":"La Rioja",
    "wof:name":"Jimenez Tomas Gonzalo",
    "wof:placetype":"venue"
},
  "geometry": {"coordinates":[-2.4550170898,42.4627037048],"type":"Point"}
}