{
  "type": "Feature",
  "properties": {
    "addr:full":"Carr Aitana, 2 Vila Joiosa Alicante 03570",
    "addr:housenumber":"2",
    "addr:postcode":"03570",
    "addr:street":"Carr Aitana",
    "iso:country":"ES",
    "sg:address":"Carr Aitana, 2",
    "sg:city":"Vila Joiosa",
    "sg:orig_category":"Peluqueros: De Se\u00d1oras",
    "sg:phone":"+34 965 89 12 99",
    "sg:postcode":"03570",
    "sg:province":"Alicante",
    "wof:name":"Perona Llorca Francisco Javier",
    "wof:placetype":"venue"
},
  "geometry": {"coordinates":[-0.7466139793,38.3102035522],"type":"Point"}
}