{
  "type": "Feature",
  "properties": {
    "addr:full":"Ctra. Coria, S/n Pinofranqueado C\u00e1ceres 10630",
    "addr:housenumber":"s / n",
    "addr:postcode":"10630",
    "addr:street":"Ctra. Coria;Ca\u0301Ceres",
    "iso:country":"ES",
    "sg:address":"Ctra. Coria, S/n",
    "sg:city":"Pinofranqueado",
    "sg:orig_category":"Negocio De Materiales De Construcci\u00d3n",
    "sg:phone":"+34 927 67 40 51",
    "sg:postcode":"10630",
    "sg:province":"C\u00e1ceres",
    "wof:name":"Hernandez Martin Alvaro",
    "wof:placetype":"venue"
},
  "geometry": {"coordinates":[-6.3322992325,40.3015785217],"type":"Point"}
}