{
  "type": "Feature",
  "properties": {
    "addr:full":"Seara, 27 Seara Ourense 32821",
    "addr:housenumber":"27",
    "addr:postcode":"32821",
    "addr:street":"Seara",
    "iso:country":"ES",
    "sg:address":"Seara, 27",
    "sg:city":"Seara",
    "sg:orig_category":"Marmolistas Funerarios",
    "sg:phone":"+34 988 49 13 38",
    "sg:postcode":"32821",
    "sg:province":"Ourense",
    "wof:name":"Alberte Fernandez Jose",
    "wof:placetype":"venue"
},
  "geometry": {"coordinates":[-8.0223035812,42.2273139954],"type":"Point"}
}