{
  "type": "Feature",
  "properties": {
    "iso:country":"ES",
    "sg:address":"Calle de Vi\u00d1as (las), 3",
    "sg:city":"Moriles",
    "sg:orig_category":"Transportes Por V\u00cdas Navegables",
    "sg:phone":"+34 957 53 73 55",
    "sg:postcode":"14510",
    "sg:province":"C\u00f3rdoba",
    "wof:name":"Transroli S.l.",
    "wof:placetype":"venue"
},
  "geometry": {"coordinates":[-4.6112380028,37.4366798401],"type":"Point"}
}