{
  "type": "Feature",
  "properties": {
    "addr:full":"Pase Parra (de), 38 Aguilas Murcia 30880",
    "addr:postcode":"30880",
    "iso:country":"ES",
    "sg:address":"Pase Parra (de), 38",
    "sg:city":"Aguilas",
    "sg:orig_category":"Centros Empresariales",
    "sg:phone":"+34 968 44 96 00",
    "sg:postcode":"30880",
    "sg:province":"Murcia",
    "wof:name":"Comunidad Propietarios Playa Mar",
    "wof:placetype":"venue"
},
  "geometry": {"coordinates":[-1.5735570192,37.4080200195],"type":"Point"}
}