{
  "type": "Feature",
  "properties": {
    "iso:country":"ES",
    "sg:address":"Rbla Rambla Vella, 19",
    "sg:city":"Tarragona",
    "sg:orig_category":"Cajas De Ahorro",
    "sg:phone":"+34 977 23 58 90",
    "sg:postcode":"43003",
    "sg:province":"Tarragona",
    "sg:website":"www.caixatarragona.es",
    "wof:name":"Caixa D'estalvis De Tarragona",
    "wof:placetype":"venue"
},
  "geometry": {"coordinates":[1.2541049719,41.1169281006],"type":"Point"}
}