{
  "type": "Feature",
  "properties": {
    "iso:country":"ES",
    "sg:address":"Calle de Toro, 16",
    "sg:city":"Ciudad Rodrigo",
    "sg:orig_category":"Molduras, Junquillos, Listones Y Molduras Perforadas",
    "sg:phone":"+34 923 46 00 34",
    "sg:postcode":"37500",
    "sg:province":"Salamanca",
    "wof:name":"Fraile Varas Mercedes",
    "wof:placetype":"venue"
},
  "geometry": {"coordinates":[-6.5332841873,40.5984649658],"type":"Point"}
}