{
  "type": "Feature",
  "properties": {
    "iso:country":"ES",
    "sg:address":"Pase Farola, 1",
    "sg:city":"Malaga",
    "sg:orig_category":"Bancos",
    "sg:phone":"+34 952 21 64 23",
    "sg:postcode":"29016",
    "sg:province":"M\u00e1laga",
    "wof:name":"Banco Espa\u00d1ol De Credito S.a.",
    "wof:placetype":"venue"
},
  "geometry": {"coordinates":[-4.4119358063,36.7194633484],"type":"Point"}
}