{
  "type": "Feature",
  "properties": {
    "addr:full":"Calle de Rio Beiro, 8 Cullar-vega Granada 18195",
    "addr:housenumber":"8",
    "addr:postcode":"18195",
    "addr:street":"Calle De Rio Beiro",
    "iso:country":"ES",
    "sg:address":"Calle de Rio Beiro, 8",
    "sg:city":"Cullar-vega",
    "sg:orig_category":"Agencias Y Agentes Comerciales, Representantes",
    "sg:phone":"+34 958 58 29 39",
    "sg:postcode":"18195",
    "sg:province":"Granada",
    "wof:name":"Sanchez Guindo Miguel",
    "wof:placetype":"venue"
},
  "geometry": {"coordinates":[-3.6739320755,37.1596298218],"type":"Point"}
}