{
  "type": "Feature",
  "properties": {
    "iso:country":"ES",
    "sg:address":"Carrer de Masseva, 51",
    "sg:city":"Mataro",
    "sg:orig_category":"Construcci\u00d3n Mec\u00c1nica",
    "sg:phone":"+34 937 98 89 58",
    "sg:postcode":"08302",
    "sg:province":"Barcelona",
    "wof:name":"Batlle Caballe Juan",
    "wof:placetype":"venue"
},
  "geometry": {"coordinates":[2.4415230751,41.5417366028],"type":"Point"}
}