{
  "type": "Feature",
  "properties": {
    "iso:country":"ES",
    "sg:address":"Calle de Fuente, S/n",
    "sg:city":"Robliza Cojos",
    "sg:orig_category":"Carnicer\u00cdas, Carnicer\u00cdas",
    "sg:phone":"+34 923 38 23 87",
    "sg:postcode":"37491",
    "sg:province":"Salamanca",
    "wof:name":"Salgado Martin Juan",
    "wof:placetype":"venue"
},
  "geometry": {"coordinates":[-5.9598641396,40.9042282104],"type":"Point"}
}