{
  "type": "Feature",
  "properties": {
    "addr:full":"Avda Angeles (de Los), 49 Getafe Madrid 28903",
    "addr:housenumber":"49",
    "addr:postcode":"28903",
    "addr:street":"Avda Angeles De Los",
    "iso:country":"ES",
    "sg:address":"Avda Angeles (de Los), 49",
    "sg:city":"Getafe",
    "sg:orig_category":"Alimentaci\u00d3n General (al Por Menor)",
    "sg:phone":"+34 916 96 39 13",
    "sg:postcode":"28903",
    "sg:province":"Madrid",
    "wof:name":"Fernandez Ayllon Pedro",
    "wof:placetype":"venue"
},
  "geometry": {"coordinates":[-3.7181940079,40.3095779419],"type":"Point"}
}