{
  "type": "Feature",
  "properties": {
    "iso:country":"ES",
    "sg:address":"Calle de Catalu\u00d1a, 3",
    "sg:city":"Pinto",
    "sg:orig_category":"Servicios De Telecomunicaciones",
    "sg:phone":"+34 916 91 57 54",
    "sg:postcode":"28320",
    "sg:province":"Madrid",
    "wof:name":"Simple Telecom,sl",
    "wof:placetype":"venue"
},
  "geometry": {"coordinates":[-3.694216013,40.2466621399],"type":"Point"}
}