{
  "type": "Feature",
  "properties": {
    "iso:country":"ES",
    "sg:address":"Illes Balears, 260",
    "sg:city":"Palma",
    "sg:orig_category":"Centros M\u00c9dicos Y Sociales, Dispensarios",
    "sg:phone":"+34 971 28 00 06",
    "sg:postcode":"07014",
    "sg:province":"Islas Baleares",
    "wof:name":"Moral Caballero Alejandro",
    "wof:placetype":"venue"
},
  "geometry": {"coordinates":[2.6127719879,39.5729866028],"type":"Point"}
}