{
  "type": "Feature",
  "properties": {
    "iso:country":"ES",
    "sg:address":"Calle de Excideuil, S/n",
    "sg:city":"Murillo De Rio Leza",
    "sg:orig_category":"Bancos",
    "sg:phone":"+34 941 43 20 30",
    "sg:postcode":"26143",
    "sg:province":"La Rioja",
    "sg:website":"www.bancopopular.es",
    "wof:name":"Banco Popular Espa\u00f1ol",
    "wof:placetype":"venue"
},
  "geometry": {"coordinates":[-2.3255090714,42.401058197],"type":"Point"}
}