{
  "type": "Feature",
  "properties": {
    "addr:full":"Ctra Cuenca Teruel, Km. 0153,2 Ca\u00d1ete Cuenca 16300",
    "addr:postcode":"16300",
    "addr:street":"Ctra Cuenca Teruel Km. 0153,2 Can\u0303Ete",
    "iso:country":"ES",
    "sg:address":"Ctra Cuenca Teruel, Km. 0153,2",
    "sg:city":"Ca\u00d1ete",
    "sg:orig_category":"Distribuci\u00d3n De Petr\u00d3leo Y Derivados",
    "sg:phone":"+34 969 34 60 50",
    "sg:postcode":"16300",
    "sg:province":"Cuenca",
    "wof:name":"Asensio Romero Maria",
    "wof:placetype":"venue"
},
  "geometry": {"coordinates":[-1.6454802752,40.041973114],"type":"Point"}
}