{
  "type": "Feature",
  "properties": {
    "addr:full":"Calle de Maestro Cabanes Ballester, 40 Onil Alicante 03430",
    "addr:housenumber":"40",
    "addr:postcode":"03430",
    "addr:street":"Calle De Maestro;Ballester",
    "iso:country":"ES",
    "sg:address":"Calle de Maestro Cabanes Ballester, 40",
    "sg:city":"Onil",
    "sg:orig_category":"Inmobiliaria (agencias)",
    "sg:phone":"+34 966 55 71 40",
    "sg:postcode":"03430",
    "sg:province":"Alicante",
    "wof:name":"Inmofinques Biar S.l.",
    "wof:placetype":"venue"
},
  "geometry": {"coordinates":[-0.6715599895,38.6261138916],"type":"Point"}
}