{
  "type": "Feature",
  "properties": {
    "addr:full":"Calle de Do\u00d1a Beatriz, 1 Ponferrada Le\u00f3n 24400",
    "addr:housenumber":"1",
    "addr:postcode":"24400",
    "addr:street":"Calle De Don\u0303A Beatriz",
    "iso:country":"ES",
    "sg:address":"Calle de Do\u00d1a Beatriz, 1",
    "sg:city":"Ponferrada",
    "sg:orig_category":"Promotores Constructores",
    "sg:phone":"+34 987 41 31 90",
    "sg:postcode":"24400",
    "sg:province":"Le\u00f3n",
    "wof:name":"Rodriguez Iglesias Maria Jose",
    "wof:placetype":"venue"
},
  "geometry": {"coordinates":[-6.5854039192,42.5452156067],"type":"Point"}
}