{
  "type": "Feature",
  "properties": {
    "iso:country":"ES",
    "sg:address":"Polig Industrial, S/n",
    "sg:city":"Lorqui",
    "sg:orig_category":"Fabricaci\u00d3n Y Venta De Volquetes Y Remolques",
    "sg:phone":"+34 968 69 41 05",
    "sg:postcode":"30564",
    "sg:province":"Murcia",
    "wof:name":"Montenegro Iberica",
    "wof:placetype":"venue"
},
  "geometry": {"coordinates":[-1.2350000143,38.1045875549],"type":"Point"}
}