{
  "type": "Feature",
  "properties": {
    "addr:full":"Avda Madro\u00d1os, 25 Madrid Madrid 28043",
    "addr:housenumber":"25",
    "addr:postcode":"madrid;28043",
    "addr:street":"Avda Madron\u0303Os",
    "iso:country":"ES",
    "sg:address":"Avda Madro\u00d1os, 25",
    "sg:city":"Madrid",
    "sg:orig_category":"Grafistas",
    "sg:phone":"+34 913 88 79 39",
    "sg:postcode":"28043",
    "sg:province":"Madrid",
    "wof:name":"La Luna Titra S.l.",
    "wof:placetype":"venue"
},
  "geometry": {"coordinates":[-3.6449940205,40.4555587769],"type":"Point"}
}