{
  "type": "Feature",
  "properties": {
    "addr:full":"Calle de Portuetxe, 53 Donostia-san Sebastian Guip\u00f9zcoa 20018",
    "addr:housenumber":"53",
    "addr:postcode":"20018",
    "addr:street":"Calle De Portuetxe",
    "iso:country":"ES",
    "sg:address":"Calle de Portuetxe, 53",
    "sg:city":"Donostia-san Sebastian",
    "sg:orig_category":"Albergues",
    "sg:phone":"+34 943 31 74 80",
    "sg:postcode":"20018",
    "sg:province":"Guip\u00f9zcoa",
    "wof:name":"Novo Novo Jose Rodolfo",
    "wof:placetype":"venue"
},
  "geometry": {"coordinates":[-2.0161669254,43.3012313843],"type":"Point"}
}