{
  "type": "Feature",
  "properties": {
    "addr:full":"Plaz Mayor, 20 Burgos Burgos 09003",
    "addr:housenumber":"20",
    "addr:postcode":"09003",
    "addr:street":"Plaz Mayor",
    "iso:country":"ES",
    "sg:address":"Plaz Mayor, 20",
    "sg:city":"Burgos",
    "sg:orig_category":"T\u00c9s (al Por Menor)",
    "sg:phone":"+34 947 20 99 08",
    "sg:postcode":"09003",
    "sg:province":"Burgos",
    "wof:name":"Garcia Abad,clara Maria 000527436f S.l.n.e",
    "wof:placetype":"venue"
},
  "geometry": {"coordinates":[-3.7009689808,42.3413505554],"type":"Point"}
}