{
  "type": "Feature",
  "properties": {
    "addr:full":"Cmno Sabinar (del), S/n Epila Zaragoza 50290",
    "addr:postcode":"50290",
    "addr:street":"Cmno Sabinar Del S / N Epila",
    "iso:country":"ES",
    "sg:address":"Cmno Sabinar (del), S/n",
    "sg:city":"Epila",
    "sg:orig_category":"Comercio De Piezas De Recambio Y De Accesorios De Veh\u00cdculos, Veh\u00cdculos Industriales",
    "sg:phone":"+34 976 81 61 00",
    "sg:postcode":"50290",
    "sg:province":"Zaragoza",
    "wof:name":"Lear Corporation Asientos S.l. Sociedad Unipersonal",
    "wof:placetype":"venue"
},
  "geometry": {"coordinates":[-1.2745440006,41.5973396301],"type":"Point"}
}