{
  "type": "Feature",
  "properties": {
    "addr:full":"Calle de Canonigo Sanchez Bustamante, 5 Coria C\u00e1ceres 10800",
    "addr:housenumber":"5",
    "addr:postcode":"10800",
    "addr:street":"Calle De Canonigo Sanchez Bustamante;Ca\u0301Ceres",
    "iso:country":"ES",
    "sg:address":"Calle de Canonigo Sanchez Bustamante, 5",
    "sg:city":"Coria",
    "sg:orig_category":"Ingeniero",
    "sg:phone":"+34 927 50 37 24",
    "sg:postcode":"10800",
    "sg:province":"C\u00e1ceres",
    "wof:name":"Rey Lobo Jose Del",
    "wof:placetype":"venue"
},
  "geometry": {"coordinates":[-6.5397992134,39.9892807007],"type":"Point"}
}