{
  "type": "Feature",
  "properties": {
    "addr:full":"Calle de Laguna, 64 Sevilla Sevilla 41014",
    "addr:housenumber":"64",
    "addr:postcode":"41014",
    "addr:street":"Calle De Laguna",
    "iso:country":"ES",
    "sg:address":"Calle de Laguna, 64",
    "sg:city":"Sevilla",
    "sg:orig_category":"Aperitivos (fabricaci\u00d3n Y Al Por Mayor)",
    "sg:phone":"+34 954 68 03 32",
    "sg:postcode":"41014",
    "sg:province":"Sevilla",
    "wof:name":"Papafresh S.l.l.",
    "wof:placetype":"venue"
},
  "geometry": {"coordinates":[-5.9668078423,37.3196792603],"type":"Point"}
}