{
  "type": "Feature",
  "properties": {
    "addr:full":"Carr Santa Clara, 9 Girona Girona 17001",
    "addr:housenumber":"9",
    "addr:postcode":"17001",
    "addr:street":"Carr Santa Clara",
    "iso:country":"ES",
    "sg:address":"Carr Santa Clara, 9",
    "sg:city":"Girona",
    "sg:orig_category":"M\u00c9dicos: Medicina Interna",
    "sg:phone":"+34 972 20 09 94",
    "sg:postcode":"17001",
    "sg:province":"Girona",
    "wof:name":"Mascaro Juando Jaime",
    "wof:placetype":"venue"
},
  "geometry": {"coordinates":[2.8226819038,41.9829521179],"type":"Point"}
}