{
  "type": "Feature",
  "properties": {
    "iso:country":"ES",
    "sg:address":"Calle de Noria (de La), 24",
    "sg:city":"Camarma Esteruelas",
    "sg:orig_category":"Propiedad Industrial: Patentes De Inventos, Marcas, Modelos, Dise\u00d1os",
    "sg:phone":"+34 918 86 68 59",
    "sg:postcode":"28816",
    "sg:province":"Madrid",
    "wof:name":"Benito Dia Maria Jose",
    "wof:placetype":"venue"
},
  "geometry": {"coordinates":[-3.374078989,40.5480270386],"type":"Point"}
}