{
  "type": "Feature",
  "properties": {
    "addr:full":"Via Augusta, 103 Barcelona Barcelona 08006",
    "addr:housenumber":"103",
    "addr:postcode":"08006",
    "addr:street":"Via Augusta",
    "iso:country":"ES",
    "sg:address":"Via Augusta, 103",
    "sg:city":"Barcelona",
    "sg:orig_category":"M\u00c9dicos: Ginecolog\u00cda Y Obstetricia",
    "sg:phone":"+34 932 17 19 21",
    "sg:postcode":"08006",
    "sg:province":"Barcelona",
    "wof:name":"Centro Ginecologico Esteban Altirriba I Asociados S.l.",
    "wof:placetype":"venue"
},
  "geometry": {"coordinates":[2.1488740444,41.4010772705],"type":"Point"}
}