{
  "type": "Feature",
  "properties": {
    "addr:full":"Calle de Leopoldo Alas Clarin, 15 Mieres Asturias 33600",
    "addr:housenumber":"15",
    "addr:postcode":"33600",
    "addr:street":"Calle De Leopoldo Alas Clarin",
    "iso:country":"ES",
    "sg:address":"Calle de Leopoldo Alas Clarin, 15",
    "sg:city":"Mieres",
    "sg:orig_category":"Zapatos (al Por Menor)",
    "sg:phone":"+34 985 46 50 83",
    "sg:postcode":"33600",
    "sg:province":"Asturias",
    "wof:name":"Lopez Lopez Carmen",
    "wof:placetype":"venue"
},
  "geometry": {"coordinates":[-5.7732496262,43.2492866516],"type":"Point"}
}