{
  "type": "Feature",
  "properties": {
    "addr:full":"Avda Valencia, 18 Rosell Castell\u00f3n 12511",
    "addr:housenumber":"18",
    "addr:postcode":"12511",
    "addr:street":"Avda Valencia;Castello\u0301N",
    "iso:country":"ES",
    "sg:address":"Avda Valencia, 18",
    "sg:city":"Rosell",
    "sg:orig_category":"Escayola Y Productos De Escayola (fabricaci\u00d3n, Al Por Mayor)",
    "sg:phone":"+34 977 57 12 10",
    "sg:postcode":"12511",
    "sg:province":"Castell\u00f3n",
    "wof:name":"Hilario Cervello Josefa",
    "wof:placetype":"venue"
},
  "geometry": {"coordinates":[0.2206320018,40.6170005798],"type":"Point"}
}