{
  "type": "Feature",
  "properties": {
    "iso:country":"ES",
    "sg:address":"Calle de Garcia Leon, 85",
    "sg:city":"Campo Criptana",
    "sg:orig_category":"Mec\u00c1nico Del Autom\u00d3vil",
    "sg:phone":"+34 926 56 22 45",
    "sg:postcode":"13610",
    "sg:province":"Ciudad Real",
    "wof:name":"Talleres Valls E Hijos S.l.",
    "wof:placetype":"venue"
},
  "geometry": {"coordinates":[-3.133803606,39.4017753601],"type":"Point"}
}