{
  "type": "Feature",
  "properties": {
    "addr:full":"Avda Nacional, 21 Arenal Islas Baleares 07600",
    "addr:postcode":"07600",
    "addr:street":"Avda Nacional 21 Arenal Islas",
    "iso:country":"ES",
    "sg:address":"Avda Nacional, 21",
    "sg:city":"Arenal",
    "sg:classifiers":[
        {
            "category":"Arts & Performance",
            "subcategory":"Art Gallery",
            "type":"Entertainment"
        }
    ],
    "sg:phone":"+34 971 26 29 45",
    "sg:postcode":"07600",
    "sg:province":"Islas Baleares",
    "sg:tags":[
        "obras",
        "de",
        "coleccionismo",
        "compraventa",
        "arte",
        "y"
    ],
    "wof:name":"Gonzalez Gonzalez Alfonso",
    "wof:placetype":"venue"
},
  "geometry": {"coordinates":[2.752327919,39.5086097717],"type":"Point"}
}