{
  "type": "Feature",
  "properties": {
    "iso:country":"ES",
    "sg:address":"Calle de Oaxaca, 25",
    "sg:city":"Caceres",
    "sg:orig_category":"Asesor\u00cda Sobre Comunicaci\u00d3n De Empresas",
    "sg:phone":"+34 927 23 31 50",
    "sg:postcode":"10005",
    "sg:province":"C\u00e1ceres",
    "wof:name":"Garcia Eusevia Ana Belen",
    "wof:placetype":"venue"
},
  "geometry": {"coordinates":[-6.379652977,39.4575271606],"type":"Point"}
}