{
  "type": "Feature",
  "properties": {
    "iso:country":"ES",
    "sg:address":"Carrer de Fran\u00c7a (de), 60",
    "sg:city":"Catllar",
    "sg:orig_category":"Papel, Reciclaje",
    "sg:phone":"+34 977 65 48 03",
    "sg:postcode":"43764",
    "sg:province":"Tarragona",
    "wof:name":"Ma\u00f1e Plana Jose",
    "wof:placetype":"venue"
},
  "geometry": {"coordinates":[1.3231550455,41.1741485596],"type":"Point"}
}