{
  "type": "Feature",
  "properties": {
    "iso:country":"ES",
    "sg:address":"Calle de Plateria, 38",
    "sg:city":"San Bartolome",
    "sg:orig_category":"Complementos De Vestir (al Por Menor)",
    "sg:phone":"+34 968 21 40 30",
    "sg:postcode":"30001",
    "sg:province":"Murcia",
    "wof:name":"Vives Pe\u00f1alver Maria Isabel",
    "wof:placetype":"venue"
},
  "geometry": {"coordinates":[-1.1298867464,37.9834747314],"type":"Point"}
}