{
  "type": "Feature",
  "properties": {
    "addr:full":"Avgd Ausias March, 42 Burjassot Valencia 46100",
    "addr:housenumber":"42",
    "addr:postcode":"46100",
    "addr:street":"March",
    "iso:country":"ES",
    "sg:address":"Avgd Ausias March, 42",
    "sg:city":"Burjassot",
    "sg:orig_category":"Agencias De Viajes",
    "sg:phone":"+34 963 90 52 17",
    "sg:postcode":"46100",
    "sg:province":"Valencia",
    "sg:website":"www.barceloviajes.com",
    "wof:name":"Viajes Barcelo S.l.",
    "wof:placetype":"venue"
},
  "geometry": {"coordinates":[-0.410818994,39.5142784119],"type":"Point"}
}