{
  "type": "Feature",
  "properties": {
    "addr:full":"Calle de Cristo De La Sed, 66 Sevilla Sevilla 41005",
    "addr:housenumber":"66",
    "addr:postcode":"41005",
    "addr:street":"Calle De Cristo De La Sed",
    "iso:country":"ES",
    "sg:address":"Calle de Cristo De La Sed, 66",
    "sg:city":"Sevilla",
    "sg:orig_category":"Prot\u00c9sicos Dentales",
    "sg:phone":"+34 954 57 25 16",
    "sg:postcode":"41005",
    "sg:province":"Sevilla",
    "wof:name":"Busutil Doblas Jose Antonio",
    "wof:placetype":"venue"
},
  "geometry": {"coordinates":[-5.9640789032,37.3828353882],"type":"Point"}
}