{
  "type": "Feature",
  "properties": {
    "addr:full":"Calle de Eulalia Escobet, 36 Alginet Valencia 46230",
    "addr:housenumber":"36",
    "addr:postcode":"46230",
    "addr:street":"Calle De Eulalia Escobet",
    "iso:country":"ES",
    "sg:address":"Calle de Eulalia Escobet, 36",
    "sg:city":"Alginet",
    "sg:orig_category":"Abogados",
    "sg:phone":"+34 961 75 01 72",
    "sg:postcode":"46230",
    "sg:province":"Valencia",
    "wof:name":"Mellado Espert Vicente",
    "wof:placetype":"venue"
},
  "geometry": {"coordinates":[-0.4688529968,39.2597961426],"type":"Point"}
}