{
  "type": "Feature",
  "properties": {
    "iso:country":"ES",
    "sg:address":"Carr Sant Rafael, 4",
    "sg:city":"Picanya",
    "sg:orig_category":"Carnicer\u00cdas, Carnicer\u00cdas",
    "sg:phone":"+34 961 59 26 20",
    "sg:postcode":"46210",
    "sg:province":"Valencia",
    "wof:name":"Aibar Perez Luis",
    "wof:placetype":"venue"
},
  "geometry": {"coordinates":[-0.4369409084,39.4364013672],"type":"Point"}
}