{
  "type": "Feature",
  "properties": {
    "iso:country":"ES",
    "sg:address":"Calle de Pico De Maladeta, 3",
    "sg:city":"Salamanca",
    "sg:orig_category":"Promotores Constructores",
    "sg:phone":"+34 923 19 21 98",
    "sg:postcode":"37008",
    "sg:province":"Salamanca",
    "wof:name":"Concispor S. L.",
    "wof:placetype":"venue"
},
  "geometry": {"coordinates":[-5.6704320908,40.9519805908],"type":"Point"}
}