{
  "type": "Feature",
  "properties": {
    "iso:country":"ES",
    "sg:address":"Barr Bekea, 2",
    "sg:city":"Bekea",
    "sg:orig_category":"Molduras, Junquillos, Listones Y Molduras Perforadas",
    "sg:phone":"+34 944 56 00 39",
    "sg:postcode":"48960",
    "sg:province":"Vizcaya",
    "wof:name":"Fernandez Urrutia Maria Bego\u00f1a",
    "wof:placetype":"venue"
},
  "geometry": {"coordinates":[-2.8304669857,43.229434967],"type":"Point"}
}