{
  "type": "Feature",
  "properties": {
    "addr:full":"Calle de Ramon Y Cajal, 30 Cuarte Huerva Zaragoza 50410",
    "addr:housenumber":"30",
    "addr:postcode":"50410",
    "addr:street":"Calle De Ramon Y Cajal",
    "iso:country":"ES",
    "sg:address":"Calle de Ramon Y Cajal, 30",
    "sg:city":"Cuarte Huerva",
    "sg:orig_category":"Art\u00cdculos De Regalo (al Por Menor)",
    "sg:phone":"+34 976 50 52 66",
    "sg:postcode":"50410",
    "sg:province":"Zaragoza",
    "wof:name":"Fatas Calvera Ana Luz",
    "wof:placetype":"venue"
},
  "geometry": {"coordinates":[-0.929099977,41.5914840698],"type":"Point"}
}