{
  "type": "Feature",
  "properties": {
    "addr:full":"Ctra. Militar, 227 Arenal Islas Baleares 07600",
    "addr:housenumber":"227",
    "addr:postcode":"07600",
    "addr:street":"Ctra. Militar",
    "iso:country":"ES",
    "sg:address":"Ctra. Militar, 227",
    "sg:city":"Arenal",
    "sg:orig_category":"Florister\u00cdas",
    "sg:phone":"+34 971 26 49 94",
    "sg:postcode":"07600",
    "sg:province":"Islas Baleares",
    "wof:name":"Cerda Arias Manuela",
    "wof:placetype":"venue"
},
  "geometry": {"coordinates":[2.7550530434,39.5083389282],"type":"Point"}
}