{
  "type": "Feature",
  "properties": {
    "addr:full":"Av Pompeu Fabra (de), 31 Torredembarra Tarragona 43830",
    "addr:housenumber":"31",
    "addr:postcode":"43830",
    "addr:street":"Av Pompeu Fabra De",
    "iso:country":"ES",
    "sg:address":"Av Pompeu Fabra (de), 31",
    "sg:city":"Torredembarra",
    "sg:orig_category":"T\u00c9cnicos Veterinarios",
    "sg:phone":"+34 977 64 17 64",
    "sg:postcode":"43830",
    "sg:province":"Tarragona",
    "wof:name":"Nu\u00f1ez Marti Rosalia",
    "wof:placetype":"venue"
},
  "geometry": {"coordinates":[1.395424962,41.1436691284],"type":"Point"}
}