{
  "type": "Feature",
  "properties": {
    "addr:full":"Calle de Bancales (los), 13 Toscal Santa Cruz De Tenerife 38418",
    "addr:housenumber":"13",
    "addr:postcode":"38418",
    "addr:street":"Calle De Bancales Los",
    "iso:country":"ES",
    "sg:address":"Calle de Bancales (los), 13",
    "sg:city":"Toscal",
    "sg:orig_category":"M\u00c9dicos: Salud P\u00dablica",
    "sg:phone":"+34 922 36 22 41",
    "sg:postcode":"38418",
    "sg:province":"Santa Cruz De Tenerife",
    "wof:name":"Valcarcel Lopez Rafael",
    "wof:placetype":"venue"
},
  "geometry": {"coordinates":[-16.5743808746,28.3986339569],"type":"Point"}
}