{
  "type": "Feature",
  "properties": {
    "addr:full":"Calle de Regajal, 8 Arroyo Luz C\u00e1ceres 10900",
    "addr:housenumber":"8 arroyo",
    "addr:postcode":"10900",
    "addr:street":"Calle De Regajal;Ca\u0301Ceres",
    "iso:country":"ES",
    "sg:address":"Calle de Regajal, 8",
    "sg:city":"Arroyo Luz",
    "sg:orig_category":"Molduras, Junquillos, Listones Y Molduras Perforadas",
    "sg:phone":"+34 927 27 01 79",
    "sg:postcode":"10900",
    "sg:province":"C\u00e1ceres",
    "wof:name":"Holgado Pajares Carmen",
    "wof:placetype":"venue"
},
  "geometry": {"coordinates":[-6.5818929672,39.481678009],"type":"Point"}
}