{
  "type": "Feature",
  "properties": {
    "addr:full":"Carr Vassallo, 23 Mao Islas Baleares 07703",
    "addr:housenumber":"23",
    "addr:postcode":"07703",
    "addr:street":"Carr Vassallo",
    "iso:country":"ES",
    "sg:address":"Carr Vassallo, 23",
    "sg:city":"Mao",
    "sg:orig_category":"Art\u00cdculos De Regalo (al Por Menor)",
    "sg:phone":"+34 971 36 19 02",
    "sg:postcode":"07703",
    "sg:province":"Islas Baleares",
    "sg:website":"www.partycity.com",
    "wof:name":"Party Fiesta S.a.",
    "wof:placetype":"venue"
},
  "geometry": {"coordinates":[4.2574501038,39.8873786926],"type":"Point"}
}