{
  "type": "Feature",
  "properties": {
    "addr:full":"Rua Nova, 124 Lugo Lugo 27001",
    "addr:housenumber":"124",
    "addr:postcode":"27001",
    "addr:street":"Rua Nova",
    "iso:country":"ES",
    "sg:address":"Rua Nova, 124",
    "sg:city":"Lugo",
    "sg:orig_category":"Frutas, Legumbres Frescas Y Tempranas (al Por Menor)",
    "sg:phone":"+34 982 25 12 07",
    "sg:postcode":"27001",
    "sg:province":"Lugo",
    "wof:name":"Lopez Pillado Alfredo",
    "wof:placetype":"venue"
},
  "geometry": {"coordinates":[-7.5603852272,43.0135993958],"type":"Point"}
}