{
  "type": "Feature",
  "properties": {
    "iso:country":"ES",
    "sg:address":"Barr Arandia, S/n",
    "sg:city":"Ugao-miraballes",
    "sg:orig_category":"Asociaciones Y Clubs Deportivos",
    "sg:phone":"+34 946 48 10 51",
    "sg:postcode":"48490",
    "sg:province":"Vizcaya",
    "sg:website":"www.cdugao.com",
    "wof:name":"Club Deportivo Ugao Sociedad Deportiva",
    "wof:placetype":"venue"
},
  "geometry": {"coordinates":[-2.8992340565,43.1817398071],"type":"Point"}
}