{
  "type": "Feature",
  "properties": {
    "iso:country":"ES",
    "sg:address":"Calle de Jardines, 10",
    "sg:city":"Riopar",
    "sg:orig_category":"Bebidas",
    "sg:phone":"+34 967 43 54 63",
    "sg:postcode":"02450",
    "sg:province":"Albacete",
    "wof:name":"Exclusivas Fiteni S.l.",
    "wof:placetype":"venue"
},
  "geometry": {"coordinates":[-2.4171280861,38.4996032715],"type":"Point"}
}