{
  "type": "Feature",
  "properties": {
    "addr:full":"Calle de Gran Via, 66 Salamanca Salamanca 37001",
    "addr:housenumber":"66",
    "addr:postcode":"37001",
    "addr:street":"Calle De Gran Via",
    "iso:country":"ES",
    "sg:address":"Calle de Gran Via, 66",
    "sg:city":"Salamanca",
    "sg:orig_category":"Molduras, Junquillos, Listones Y Molduras Perforadas",
    "sg:phone":"+34 923 26 54 67",
    "sg:postcode":"37001",
    "sg:province":"Salamanca",
    "wof:name":"Teprarrorro S.l.",
    "wof:placetype":"venue"
},
  "geometry": {"coordinates":[-5.6612958908,40.9636993408],"type":"Point"}
}