{
  "type": "Feature",
  "properties": {
    "addr:full":"Calle de Amadeo Vives, 42 Matas-pinar-monte Rozas Madrid 28290",
    "addr:housenumber":"42",
    "addr:postcode":"28290",
    "addr:street":"Calle De Amadeo Vives",
    "iso:country":"ES",
    "sg:address":"Calle de Amadeo Vives, 42",
    "sg:city":"Matas-pinar-monte Rozas",
    "sg:orig_category":"Fabricaci\u00d3n De Mobiliario De Oficina",
    "sg:phone":"+34 916 36 99 74",
    "sg:postcode":"28290",
    "sg:province":"Madrid",
    "wof:name":"Nv Oficinas S.l.",
    "wof:placetype":"venue"
},
  "geometry": {"coordinates":[-3.8895959854,40.5539207458],"type":"Point"}
}