{
  "type": "Feature",
  "properties": {
    "iso:country":"ES",
    "sg:address":"Calle de Punta Alta, 24",
    "sg:city":"Malaga",
    "sg:orig_category":"Materiales De Construcci\u00d3n (en General)",
    "sg:phone":"+34 952 32 10 03",
    "sg:postcode":"29006",
    "sg:province":"M\u00e1laga",
    "sg:website":"www.acedosl.com",
    "wof:name":"Acedo Azulejops Ba\u00d1os Y Ceramica Sl",
    "wof:placetype":"venue"
},
  "geometry": {"coordinates":[-4.4754033089,36.7058258057],"type":"Point"}
}