{
  "type": "Feature",
  "properties": {
    "iso:country":"ES",
    "sg:address":"Calle de Estoril, 1",
    "sg:city":"Mostoles",
    "sg:orig_category":"Panader\u00cdas, Panader\u00cdas",
    "sg:phone":"+34 916 46 18 84",
    "sg:postcode":"28936",
    "sg:province":"Madrid",
    "wof:name":"Rojas Gil Fernando",
    "wof:placetype":"venue"
},
  "geometry": {"coordinates":[-3.8499319553,40.3249473572],"type":"Point"}
}