{
  "type": "Feature",
  "properties": {
    "iso:country":"ES",
    "sg:address":"Calle de Rosalia De Castro, 13",
    "sg:city":"Zubia",
    "sg:orig_category":"Empresas De Carpinter\u00cda",
    "sg:phone":"+34 958 59 08 33",
    "sg:postcode":"18140",
    "sg:province":"Granada",
    "wof:name":"Cristaleria Gaspar S.l.",
    "wof:placetype":"venue"
},
  "geometry": {"coordinates":[-3.5822091103,37.1130752563],"type":"Point"}
}