{
  "type": "Feature",
  "properties": {
    "addr:full":"Calle de Virgen Del Carmen, 11 Alhaurin Torre M\u00e1laga 29130",
    "addr:housenumber":"11",
    "addr:postcode":"29130",
    "addr:street":"Calle De Virgen Del Carmen",
    "iso:country":"ES",
    "sg:address":"Calle de Virgen Del Carmen, 11",
    "sg:city":"Alhaurin Torre",
    "sg:orig_category":"Promotores Constructores",
    "sg:phone":"+34 952 41 57 16",
    "sg:postcode":"29130",
    "sg:province":"M\u00e1laga",
    "wof:name":"Construcciones Euromac 2001 S.l.",
    "wof:placetype":"venue"
},
  "geometry": {"coordinates":[-4.5667190552,36.6618614197],"type":"Point"}
}