{
  "type": "Feature",
  "properties": {
    "addr:full":"Avda Cosculluela, 24 Ejea De Los Caballeros Zaragoza 50600",
    "addr:housenumber":"24",
    "addr:postcode":"50600",
    "addr:street":"Avda Cosculluela",
    "iso:country":"ES",
    "sg:address":"Avda Cosculluela, 24",
    "sg:city":"Ejea De Los Caballeros",
    "sg:orig_category":"Art\u00cdculos De Regalo (al Por Menor)",
    "sg:phone":"+34 976 66 04 47",
    "sg:postcode":"50600",
    "sg:province":"Zaragoza",
    "wof:name":"Landa Otal Carmelo",
    "wof:placetype":"venue"
},
  "geometry": {"coordinates":[-1.1385600567,42.1261291504],"type":"Point"}
}