{
  "type": "Feature",
  "properties": {
    "addr:full":"A Encomenda, S/n Acevoso Ourense 32789",
    "addr:housenumber":"s",
    "addr:postcode":"32789",
    "addr:street":"/ N",
    "iso:country":"ES",
    "sg:address":"A Encomenda, S/n",
    "sg:city":"Acevoso",
    "sg:orig_category":"Reposter\u00cdas",
    "sg:phone":"+34 988 33 21 96",
    "sg:postcode":"32789",
    "sg:province":"Ourense",
    "wof:name":"Basalo Carballo Delfina",
    "wof:placetype":"venue"
},
  "geometry": {"coordinates":[-7.2312688828,42.3317604065],"type":"Point"}
}