{
  "type": "Feature",
  "properties": {
    "addr:full":"Calle de Pico De Aneto (del), 6 San Sebastian De Los Reyes Madrid 28700",
    "addr:housenumber":"6",
    "addr:postcode":"28700",
    "addr:street":"Calle De Pico De Aneto Del",
    "iso:country":"ES",
    "sg:address":"Calle de Pico De Aneto (del), 6",
    "sg:city":"San Sebastian De Los Reyes",
    "sg:orig_category":"Electrodom\u00c9sticos (al Por Menor)",
    "sg:phone":"+34 916 54 51 27",
    "sg:postcode":"28700",
    "sg:province":"Madrid",
    "wof:name":"Jimenez Merino Juan Jose",
    "wof:placetype":"venue"
},
  "geometry": {"coordinates":[-3.6366500854,40.5502052307],"type":"Point"}
}