{
  "type": "Feature",
  "properties": {
    "addr:full":"Avda Andalucia, 76 Cadiz C\u00e1diz 11008",
    "addr:housenumber":"76",
    "addr:postcode":"11008",
    "addr:street":"Avda Andalucia",
    "iso:country":"ES",
    "sg:address":"Avda Andalucia, 76",
    "sg:city":"Cadiz",
    "sg:orig_category":"Sociedades, Compa\u00d1\u00cdas Aseguradoras",
    "sg:phone":"+34 956 25 90 15",
    "sg:postcode":"11008",
    "sg:province":"C\u00e1diz",
    "wof:name":"Santa Lucia S.a.",
    "wof:placetype":"venue"
},
  "geometry": {"coordinates":[-6.2825679779,36.5159301758],"type":"Point"}
}