{
  "type": "Feature",
  "properties": {
    "iso:country":"ES",
    "sg:address":"Raval Santa Anna, 5",
    "sg:city":"Montblanc",
    "sg:orig_category":"Agentes Generales De Seguros",
    "sg:phone":"+34 977 86 32 34",
    "sg:postcode":"43400",
    "sg:province":"Tarragona",
    "wof:name":"Nieto Ramos Josep Anton",
    "wof:placetype":"venue"
},
  "geometry": {"coordinates":[1.1615730524,41.3791923523],"type":"Point"}
}