{
  "type": "Feature",
  "properties": {
    "addr:full":"Calle de Palos De La Frontera, 25 Madrid Madrid 28045",
    "addr:housenumber":"25",
    "addr:postcode":"madrid;28045",
    "addr:street":"Calle De Palos De La Frontera",
    "iso:country":"ES",
    "sg:address":"Calle de Palos De La Frontera, 25",
    "sg:city":"Madrid",
    "sg:orig_category":"Asesor\u00cda Fiscal Y Jur\u00cddica",
    "sg:phone":"+34 914 68 79 05",
    "sg:postcode":"28045",
    "sg:province":"Madrid",
    "wof:name":"Brigidano Carde\u00f1osa Pedro",
    "wof:placetype":"venue"
},
  "geometry": {"coordinates":[-3.6949729919,40.4032211304],"type":"Point"}
}