{
  "type": "Feature",
  "properties": {
    "addr:full":"Calle de Santa Pola, 29 Banyeres Mariola Alicante 03450",
    "addr:housenumber":"29",
    "addr:postcode":"03450",
    "addr:street":"Calle De Santa Pola",
    "iso:country":"ES",
    "sg:address":"Calle de Santa Pola, 29",
    "sg:city":"Banyeres Mariola",
    "sg:orig_category":"Abogados",
    "sg:phone":"+34 966 56 84 12",
    "sg:postcode":"03450",
    "sg:province":"Alicante",
    "wof:name":"Hernandez Martinez Antonio",
    "wof:placetype":"venue"
},
  "geometry": {"coordinates":[-0.6610620022,38.714012146],"type":"Point"}
}