{
  "type": "Feature",
  "properties": {
    "addr:full":"Monasterio Urdax, 21 Iru\u00f1a Navarra 31011",
    "addr:housenumber":"21",
    "addr:postcode":"31011",
    "addr:street":"Urdax",
    "iso:country":"ES",
    "sg:address":"Monasterio Urdax, 21",
    "sg:city":"Iru\u00f1a",
    "sg:orig_category":"Carnicer\u00cdas, Carnicer\u00cdas",
    "sg:phone":"+34 948 26 54 52",
    "sg:postcode":"31011",
    "sg:province":"Navarra",
    "wof:name":"Aranda Iturralde Pedro Luis",
    "wof:placetype":"venue"
},
  "geometry": {"coordinates":[-1.656953454,42.812664032],"type":"Point"}
}