{
  "type": "Feature",
  "properties": {
    "iso:country":"ES",
    "sg:address":"Pol Ind Cam Morente, S/n",
    "sg:city":"Montoro",
    "sg:orig_category":"Autob\u00das (explotaci\u00d3n Y Servicios De)",
    "sg:phone":"+34 957 16 17 13",
    "sg:postcode":"14600",
    "sg:province":"C\u00f3rdoba",
    "wof:name":"Luque Raigada E Hijos S.l.",
    "wof:placetype":"venue"
},
  "geometry": {"coordinates":[-4.3565130234,38.1094436646],"type":"Point"}
}