{
  "type": "Feature",
  "properties": {
    "iso:country":"ES",
    "sg:address":"Disseminat, S/n",
    "sg:city":"Munia",
    "sg:orig_category":"Administraci\u00d3n En Agricultura",
    "sg:phone":"+34 938 91 84 78",
    "sg:postcode":"08732",
    "sg:province":"Barcelona",
    "wof:name":"Novo Tecnivit S.l.",
    "wof:placetype":"venue"
},
  "geometry": {"coordinates":[1.6045809984,41.3177490234],"type":"Point"}
}