{
  "type": "Feature",
  "properties": {
    "iso:country":"ES",
    "sg:address":"Ctra Sant Joan Les Abadesses, 25",
    "sg:city":"Olot",
    "sg:orig_category":"Quincaller\u00cda (al Por Menor)",
    "sg:phone":"+34 972 26 44 61",
    "sg:postcode":"17800",
    "sg:province":"Girona",
    "wof:name":"Eines I Articles De Ferreteria Casadella-gardella S.c.",
    "wof:placetype":"venue"
},
  "geometry": {"coordinates":[2.4799931049,42.1857376099],"type":"Point"}
}