{
  "type": "Feature",
  "properties": {
    "addr:full":"Calle de Santo Entierro, 22 S. Fernando C\u00e1diz 11100",
    "addr:housenumber":"22",
    "addr:postcode":"11100",
    "addr:street":"Calle De Santo Entierro;S. Fernando Ca\u0301Diz",
    "iso:country":"ES",
    "sg:address":"Calle de Santo Entierro, 22",
    "sg:city":"S. Fernando",
    "sg:orig_category":"Comercio De Piezas De Recambio Y De Accesorios De Veh\u00cdculos, Veh\u00cdculos Industriales",
    "sg:phone":"+34 956 89 35 13",
    "sg:postcode":"11100",
    "sg:province":"C\u00e1diz",
    "wof:name":"Autofrenos Martin Romero S.l.",
    "wof:placetype":"venue"
},
  "geometry": {"coordinates":[-6.2062110901,36.4552497864],"type":"Point"}
}