{
  "type": "Feature",
  "properties": {
    "addr:full":"Calle de Bolta\u00d1a, 17 Madrid Madrid 28022",
    "addr:housenumber":"17",
    "addr:postcode":"madrid;28022",
    "addr:street":"Calle De Boltan\u0303A",
    "iso:country":"ES",
    "sg:address":"Calle de Bolta\u00d1a, 17",
    "sg:city":"Madrid",
    "sg:orig_category":"Poller\u00cda Y Caza (al Por Menor)",
    "sg:phone":"+34 917 42 95 03",
    "sg:postcode":"28022",
    "sg:province":"Madrid",
    "wof:name":"Delgado Lazaro Marcelo",
    "wof:placetype":"venue"
},
  "geometry": {"coordinates":[-3.6129179001,40.4455490112],"type":"Point"}
}