{
  "type": "Feature",
  "properties": {
    "addr:full":"Carr Duc De Lliria (del), 114 Lliria Valencia 46160",
    "addr:housenumber":"114",
    "addr:postcode":"46160",
    "addr:street":"Carr Duc De Lliria Del",
    "iso:country":"ES",
    "sg:address":"Carr Duc De Lliria (del), 114",
    "sg:city":"Lliria",
    "sg:orig_category":"Restaurantes",
    "sg:phone":"+34 962 78 10 10",
    "sg:postcode":"46160",
    "sg:province":"Valencia",
    "wof:name":"Martinez Arastey Manuel",
    "wof:placetype":"venue"
},
  "geometry": {"coordinates":[-0.6008290052,39.62940979],"type":"Point"}
}