{
  "type": "Feature",
  "properties": {
    "iso:country":"ES",
    "sg:address":"Calle de Ferrer Del Rio, 28",
    "sg:city":"Madrid",
    "sg:orig_category":"Coches Y Camiones (caja De Cambios, Embrague Y Frenos)",
    "sg:phone":"+34 913 55 57 38",
    "sg:postcode":"28028",
    "sg:province":"Madrid",
    "wof:name":"Lava La Jaka S.l.",
    "wof:placetype":"venue"
},
  "geometry": {"coordinates":[-3.6708879471,40.4351539612],"type":"Point"}
}