{
  "type": "Feature",
  "properties": {
    "addr:full":"C/ Jose Maria Peman, 32 Elche Alicante 03201",
    "addr:housenumber":"32",
    "addr:postcode":"03201",
    "addr:street":"C / Jose Maria Peman",
    "iso:country":"ES",
    "sg:address":"C/ Jose Maria Peman, 32",
    "sg:city":"Elche",
    "sg:orig_category":"Bisuter\u00cda, Joyer\u00cda, Relojer\u00cda (al Por Menor)",
    "sg:phone":"+34 966 66 53 61",
    "sg:postcode":"03201",
    "sg:province":"Alicante",
    "wof:name":"Hermanos Pe\u00f1a Sc",
    "wof:placetype":"venue"
},
  "geometry": {"coordinates":[-0.704087019,38.2638092041],"type":"Point"}
}