{
  "type": "Feature",
  "properties": {
    "iso:country":"ES",
    "sg:address":"Trva Doctor Jose Fari\u00d1a, 2",
    "sg:city":"Betanzos",
    "sg:orig_category":"Agentes Generales De Seguros",
    "sg:phone":"+34 981 77 31 64",
    "sg:postcode":"15300",
    "sg:province":"La Coru\u00f1a",
    "wof:name":"Mapfre Servicios De Informatica",
    "wof:placetype":"venue"
},
  "geometry": {"coordinates":[-8.2119092941,43.279914856],"type":"Point"}
}