{
  "type": "Feature",
  "properties": {
    "iso:country":"ES",
    "sg:address":"Avda Torrelaguna (de), 25",
    "sg:city":"Azuqueca Henares",
    "sg:orig_category":"Fabricaci\u00d3n, Importaci\u00d3n, Venta De Material De Telefon\u00cda, Peritelefon\u00cda",
    "sg:phone":"+34 949 26 59 40",
    "sg:postcode":"19200",
    "sg:province":"Guadalajara",
    "wof:name":"Moviphone Guadalajara",
    "wof:placetype":"venue"
},
  "geometry": {"coordinates":[-3.2653610706,40.5654792786],"type":"Point"}
}