{
  "type": "Feature",
  "properties": {
    "addr:full":"Plaz Amanecer En Mendez Alvaro, 2 Madrid Madrid 28045",
    "addr:housenumber":"2",
    "addr:postcode":"28045",
    "addr:street":"Alvaro",
    "iso:country":"ES",
    "sg:address":"Plaz Amanecer En Mendez Alvaro, 2",
    "sg:city":"Madrid",
    "sg:orig_category":"Cajas De Ahorro",
    "sg:phone":"+34 915 39 87 65",
    "sg:postcode":"28045",
    "sg:province":"Madrid",
    "sg:website":"www.cajasegovia.es",
    "wof:name":"Caja De Ahorros Y Monte De Piedad De Segovia",
    "wof:placetype":"venue"
},
  "geometry": {"coordinates":[-3.6845040321,40.3986854553],"type":"Point"}
}