{
  "type": "Feature",
  "properties": {
    "addr:full":"Palacio Real, S/n Aranjuez Madrid 28300",
    "addr:housenumber":"s / n",
    "addr:postcode":"28300",
    "iso:country":"ES",
    "sg:address":"Palacio Real, S/n",
    "sg:city":"Aranjuez",
    "sg:orig_category":"Servicios De Telecomunicaciones",
    "sg:phone":"+34 918 92 19 41",
    "sg:postcode":"28300",
    "sg:province":"Madrid",
    "wof:name":"Bt Espa\u00f1a Compa\u00f1ia De Servicios Globales De Telecomunicaciones S.a.u.",
    "wof:placetype":"venue"
},
  "geometry": {"coordinates":[-3.6100289822,40.0349998474],"type":"Point"}
}