{
  "type": "Feature",
  "properties": {
    "iso:country":"ES",
    "sg:address":"Calle de Hermana Carmen, 1",
    "sg:city":"Villanueva Serena",
    "sg:orig_category":"Abogados",
    "sg:phone":"+34 924 84 26 16",
    "sg:postcode":"06700",
    "sg:province":"Badajoz",
    "wof:name":"Ortega Mendez Santiago",
    "wof:placetype":"venue"
},
  "geometry": {"coordinates":[-5.7992310524,38.9752120972],"type":"Point"}
}