{
  "type": "Feature",
  "properties": {
    "addr:full":"Pol Ind El Pi, 21 Muro Alcoy Alicante 03830",
    "addr:postcode":"03830",
    "iso:country":"ES",
    "sg:address":"Pol Ind El Pi, 21",
    "sg:city":"Muro Alcoy",
    "sg:orig_category":"Fabricaci\u00d3n De Telas Y Sedas",
    "sg:phone":"+34 965 53 08 50",
    "sg:postcode":"03830",
    "sg:province":"Alicante",
    "wof:name":"Textilia S.a.",
    "wof:placetype":"venue"
},
  "geometry": {"coordinates":[-0.4414289892,38.7812538147],"type":"Point"}
}