{
  "type": "Feature",
  "properties": {
    "iso:country":"ES",
    "sg:address":"Pase Pereda, 7",
    "sg:city":"Santander",
    "sg:orig_category":"Arquitectos",
    "sg:phone":"+34 942 36 52 60",
    "sg:postcode":"39004",
    "sg:province":"Cantabria",
    "wof:name":"Bustamante Cabrero Joaquin",
    "wof:placetype":"venue"
},
  "geometry": {"coordinates":[-3.8041288853,43.4618034363],"type":"Point"}
}