{
  "type": "Feature",
  "properties": {
    "iso:country":"ES",
    "sg:address":"Calle de Doctor Juan Dominguez Perez, 49",
    "sg:city":"Palmas De Gran Canaria",
    "sg:orig_category":"Mec\u00c1nico Del Autom\u00d3vil",
    "sg:phone":"+34 928 46 10 25",
    "sg:postcode":"35008",
    "sg:province":"Las Palmas",
    "wof:name":"Santana Pe\u00f1a Jose Daniel",
    "wof:placetype":"venue"
},
  "geometry": {"coordinates":[-15.4161787033,28.1559295654],"type":"Point"}
}