{
  "type": "Feature",
  "properties": {
    "iso:country":"ES",
    "sg:address":"Carrer de Espronceda, 321",
    "sg:city":"Barcelona",
    "sg:orig_category":"M\u00c9dicos: Estomatolog\u00cda",
    "sg:phone":"+34 933 52 42 51",
    "sg:postcode":"08027",
    "sg:province":"Barcelona",
    "wof:name":"Garcia Bertran Juan",
    "wof:placetype":"venue"
},
  "geometry": {"coordinates":[2.1912379265,41.415271759],"type":"Point"}
}