{
  "type": "Feature",
  "properties": {
    "iso:country":"ES",
    "sg:address":"Carreteros, S/n",
    "sg:city":"Boadilla",
    "sg:orig_category":"Fabricaci\u00d3n De Muebles De Cocina",
    "sg:phone":"+34 916 32 44 41",
    "sg:postcode":"28660",
    "sg:province":"Madrid",
    "wof:name":"Imalpro Iberica S.l.",
    "wof:placetype":"venue"
},
  "geometry": {"coordinates":[-3.8433940411,40.3948097229],"type":"Point"}
}