{
  "type": "Feature",
  "properties": {
    "addr:full":"Avda Ramon Y Cajal, 2 Maella Zaragoza 50710",
    "addr:housenumber":"2",
    "addr:postcode":"50710",
    "addr:street":"Avda Ramon Y Cajal",
    "iso:country":"ES",
    "sg:address":"Avda Ramon Y Cajal, 2",
    "sg:city":"Maella",
    "sg:orig_category":"Electricidad Veh\u00cdculo",
    "sg:phone":"+34 976 63 84 98",
    "sg:postcode":"50710",
    "sg:province":"Zaragoza",
    "wof:name":"Dolz Civor S.l.",
    "wof:placetype":"venue"
},
  "geometry": {"coordinates":[0.1380330026,41.1234550476],"type":"Point"}
}