{
  "type": "Feature",
  "properties": {
    "iso:country":"ES",
    "sg:address":"Calle de Estefanita, 62",
    "sg:city":"Madrid",
    "sg:orig_category":"Ense\u00d1anza: Idiomas",
    "sg:phone":"+34 915 05 71 62",
    "sg:postcode":"28021",
    "sg:province":"Madrid",
    "wof:name":"Castellano Moreno Maria Elena",
    "wof:placetype":"venue"
},
  "geometry": {"coordinates":[-3.6740269661,40.3416748047],"type":"Point"}
}