{
  "type": "Feature",
  "properties": {
    "iso:country":"ES",
    "sg:address":"Calle de Camino, 22",
    "sg:city":"Aljorra",
    "sg:orig_category":"Alimentaci\u00d3n General (al Por Menor)",
    "sg:phone":"+34 968 55 83 44",
    "sg:postcode":"30390",
    "sg:province":"Murcia",
    "wof:name":"Vazquez Lopez Pascual",
    "wof:placetype":"venue"
},
  "geometry": {"coordinates":[-1.0652970076,37.6889076233],"type":"Point"}
}