{
  "type": "Feature",
  "properties": {
    "addr:full":"Calle de Real De La Ca\u00d1ada, 190 Ca\u00e7ada De San Urbano Almer\u00eda 04120",
    "addr:housenumber":"190",
    "addr:postcode":"04120",
    "addr:street":"Calle De Real De La Can\u0303Ada;Almeri\u0301A",
    "iso:country":"ES",
    "sg:address":"Calle de Real De La Ca\u00d1ada, 190",
    "sg:city":"Ca\u00e7ada De San Urbano",
    "sg:orig_category":"Arreglo, Reparaci\u00d3n, Piezas Sueltas De Televisi\u00d3n, V\u00cddeo, Hi",
    "sg:phone":"+34 950 29 11 26",
    "sg:postcode":"04120",
    "sg:province":"Almer\u00eda",
    "wof:name":"Electronica Montellano S.l.",
    "wof:placetype":"venue"
},
  "geometry": {"coordinates":[-2.401499033,36.8399162292],"type":"Point"}
}