{
  "type": "Feature",
  "properties": {
    "addr:full":"Calle de Joaquina Bobela, 16 Oviedo Asturias 33011",
    "addr:housenumber":"16",
    "addr:postcode":"33011",
    "addr:street":"Calle De Joaquina Bobela",
    "iso:country":"ES",
    "sg:address":"Calle de Joaquina Bobela, 16",
    "sg:city":"Oviedo",
    "sg:orig_category":"Productos Alimentarios",
    "sg:phone":"+34 985 29 96 80",
    "sg:postcode":"33011",
    "sg:province":"Asturias",
    "sg:website":"www.asturdog.com",
    "wof:name":"Gil Sanchez Maria Teresa",
    "wof:placetype":"venue"
},
  "geometry": {"coordinates":[-5.8462238312,43.3686332703],"type":"Point"}
}