{
  "type": "Feature",
  "properties": {
    "addr:full":"Finca C. Del Moral, S/n Casa Grande Albacete 02006",
    "addr:housenumber":"s / n",
    "addr:postcode":"02006",
    "addr:street":"C.;Moral",
    "iso:country":"ES",
    "sg:address":"Finca C. Del Moral, S/n",
    "sg:city":"Casa Grande",
    "sg:orig_category":"Cr\u00cda De Animales",
    "sg:phone":"+34 967 58 00 37",
    "sg:postcode":"02006",
    "sg:province":"Albacete",
    "wof:name":"Agropecuaria Cuarto Del Moral S.a.",
    "wof:placetype":"venue"
},
  "geometry": {"coordinates":[-1.86007,38.99765],"type":"Point"}
}