{
  "type": "Feature",
  "properties": {
    "addr:full":"Avda Vigo, 34 Estrada Pontevedra 36680",
    "addr:housenumber":"34",
    "addr:postcode":"36680",
    "addr:street":"Avda Vigo;Estrada Pontevedra",
    "iso:country":"ES",
    "sg:address":"Avda Vigo, 34",
    "sg:city":"Estrada",
    "sg:orig_category":"Reposter\u00cdas",
    "sg:phone":"+34 986 57 02 66",
    "sg:postcode":"36680",
    "sg:province":"Pontevedra",
    "wof:name":"Pan Artesano El Retiro S.l.",
    "wof:placetype":"venue"
},
  "geometry": {"coordinates":[-8.4974870682,42.6858177185],"type":"Point"}
}