{
  "type": "Feature",
  "properties": {
    "addr:full":"Calle de Maiquez, 50 Madrid Madrid 28009",
    "addr:housenumber":"50",
    "addr:postcode":"madrid;28009",
    "addr:street":"Calle De Maiquez",
    "iso:country":"ES",
    "sg:address":"Calle de Maiquez, 50",
    "sg:city":"Madrid",
    "sg:orig_category":"Peluquer\u00cdas, Peluquer\u00cda Mixta",
    "sg:phone":"+34 915 04 03 59",
    "sg:postcode":"28009",
    "sg:province":"Madrid",
    "wof:name":"Corrales Perez Maria Carmen",
    "wof:placetype":"venue"
},
  "geometry": {"coordinates":[-3.6733279228,40.4174995422],"type":"Point"}
}