{
  "type": "Feature",
  "properties": {
    "iso:country":"ES",
    "sg:address":"Calle de Presa (de La), 48",
    "sg:city":"San Fernando De Henares",
    "sg:orig_category":"Confecci\u00d3n De Trajes Para Se\u00d1oras",
    "sg:phone":"+34 916 69 63 63",
    "sg:postcode":"28830",
    "sg:province":"Madrid",
    "wof:name":"Mateo Rojas Maria De Los Angeles",
    "wof:placetype":"venue"
},
  "geometry": {"coordinates":[-3.5285539627,40.4295730591],"type":"Point"}
}