{
  "type": "Feature",
  "properties": {
    "iso:country":"ES",
    "sg:address":"Calle de Santa Maria, S/n",
    "sg:city":"Villarramiel",
    "sg:orig_category":"Sanatorios M\u00c9dico",
    "sg:phone":"+34 979 83 70 53",
    "sg:postcode":"34140",
    "sg:province":"Palencia",
    "wof:name":"Gerencia De Atencion Primaria De Palencia",
    "wof:placetype":"venue"
},
  "geometry": {"coordinates":[-4.9146871567,42.0462036133],"type":"Point"}
}