{
  "type": "Feature",
  "properties": {
    "addr:full":"Carrer de Sicilia, 358 Barcelona Barcelona 08025",
    "addr:housenumber":"358",
    "addr:postcode":"08025",
    "addr:street":"Carrer De Sicilia",
    "iso:country":"ES",
    "sg:address":"Carrer de Sicilia, 358",
    "sg:city":"Barcelona",
    "sg:orig_category":"Edici\u00d3n De Diarios, Revistas, Boletines",
    "sg:phone":"+34 934 58 75 72",
    "sg:postcode":"08025",
    "sg:province":"Barcelona",
    "sg:website":"www.naono.es",
    "wof:name":"Naono S.l.",
    "wof:placetype":"venue"
},
  "geometry": {"coordinates":[2.1699900627,41.4043922424],"type":"Point"}
}