{
  "type": "Feature",
  "properties": {
    "addr:full":"Carr Santanyi, De, 6 Campos Islas Baleares 07630",
    "addr:postcode":"07630",
    "addr:street":"Carr Santanyi De",
    "iso:country":"ES",
    "sg:address":"Carr Santanyi, De, 6",
    "sg:city":"Campos",
    "sg:orig_category":"Fabricaci\u00d3n De Productos Textiles Sin Tejer",
    "sg:phone":"+34 971 65 07 24",
    "sg:postcode":"07630",
    "sg:province":"Islas Baleares",
    "wof:name":"Bauza Veny Margarita",
    "wof:placetype":"venue"
},
  "geometry": {"coordinates":[3.019947052,39.4296722412],"type":"Point"}
}