{
  "type": "Feature",
  "properties": {
    "iso:country":"ES",
    "sg:address":"Avda Libia (de), 62",
    "sg:city":"Cordoba",
    "sg:orig_category":"Molduras, Junquillos, Listones Y Molduras Perforadas",
    "sg:phone":"+34 957 44 13 10",
    "sg:postcode":"14014",
    "sg:province":"C\u00f3rdoba",
    "wof:name":"Reyes Palominos Manuel",
    "wof:placetype":"venue"
},
  "geometry": {"coordinates":[-4.7565398216,37.8914756775],"type":"Point"}
}