{
  "type": "Feature",
  "properties": {
    "iso:country":"ES",
    "sg:address":"Calle de Evaristo San Miguel, 20",
    "sg:city":"Madrid",
    "sg:orig_category":"Tapiceros Y Tapiceros",
    "sg:phone":"+34 915 59 65 67",
    "sg:postcode":"28008",
    "sg:province":"Madrid",
    "wof:name":"Victor Zozaya S.l.",
    "wof:placetype":"venue"
},
  "geometry": {"coordinates":[-3.7161040306,40.4263114929],"type":"Point"}
}