{
  "type": "Feature",
  "properties": {
    "addr:full":"Carrer de Sant Lluis, 64 Barcelona Barcelona 08024",
    "addr:housenumber":"64",
    "addr:postcode":"08024",
    "addr:street":"Carrer De Sant Lluis",
    "iso:country":"ES",
    "sg:address":"Carrer de Sant Lluis, 64",
    "sg:city":"Barcelona",
    "sg:classifiers":[
        {
            "category":"Casinos & Gambling",
            "type":"Entertainment"
        }
    ],
    "sg:phone":"+34 932 85 05 36",
    "sg:postcode":"08024",
    "sg:province":"Barcelona",
    "sg:tags":[
        "locale",
        "de",
        "juego"
    ],
    "wof:name":"Fragomar S.a.",
    "wof:placetype":"venue"
},
  "geometry": {"coordinates":[2.1614849567,41.4060325623],"type":"Point"}
}