{
  "type": "Feature",
  "properties": {
    "iso:country":"ES",
    "sg:address":"Plaz Parque Reina Sofia, 7",
    "sg:city":"Javea",
    "sg:orig_category":"Venta, Instalaci\u00d3n De Calefacci\u00d3n",
    "sg:phone":"+34 965 79 31 36",
    "sg:postcode":"03730",
    "sg:province":"Alicante",
    "wof:name":"Calefaccion Y Energia Solar Pepe S.l.",
    "wof:placetype":"venue"
},
  "geometry": {"coordinates":[0.1570300013,38.7885093689],"type":"Point"}
}