{
  "type": "Feature",
  "properties": {
    "addr:full":"Rua Compostela, 34 Carballo A Coru\u00f1a 15100",
    "addr:housenumber":"34",
    "addr:postcode":"15100",
    "addr:street":"Rua Compostela;Corun\u0303A",
    "iso:country":"ES",
    "sg:address":"Rua Compostela, 34",
    "sg:city":"Carballo",
    "sg:orig_category":"Servicio De Salud",
    "sg:phone":"+34 981 70 25 64",
    "sg:postcode":"15100",
    "sg:province":"A Coru\u00f1a",
    "wof:name":"Vileco-mix S.l.",
    "wof:placetype":"venue"
},
  "geometry": {"coordinates":[-8.6861591339,43.2062568665],"type":"Point"}
}