{
  "type": "Feature",
  "properties": {
    "addr:full":"Avda Carregal, S/n Betanzos La Coru\u00f1a 15300",
    "addr:housenumber":"s / n",
    "addr:postcode":"15300",
    "addr:street":"Avda Carregal;La",
    "iso:country":"ES",
    "sg:address":"Avda Carregal, S/n",
    "sg:city":"Betanzos",
    "sg:orig_category":"Centros De Educaci\u00d3n Especial",
    "sg:phone":"+34 981 77 00 17",
    "sg:postcode":"15300",
    "sg:province":"La Coru\u00f1a",
    "wof:name":"Colegio Publico Comarcal Francisco Vales Villamarin",
    "wof:placetype":"venue"
},
  "geometry": {"coordinates":[-8.212518692,43.2795333862],"type":"Point"}
}