{
  "type": "Feature",
  "properties": {
    "iso:country":"ES",
    "sg:address":"Carrer de Proven\u00c7a, 82",
    "sg:city":"Barcelona",
    "sg:orig_category":"Distribuci\u00d3n De Petr\u00d3leo Y Derivados",
    "sg:phone":"+34 934 39 62 16",
    "sg:postcode":"08029",
    "sg:province":"Barcelona",
    "wof:name":"Galve Farre Carlos",
    "wof:placetype":"venue"
},
  "geometry": {"coordinates":[2.1477620602,41.3842048645],"type":"Point"}
}