{
  "type": "Feature",
  "properties": {
    "iso:country":"ES",
    "sg:address":"Calle de Burgo Nuevo, 2",
    "sg:city":"Le\u00f3n",
    "sg:orig_category":"Confecci\u00d3n De Trajes Para Se\u00d1oras",
    "sg:phone":"+34 987 26 41 08",
    "sg:postcode":"24001",
    "sg:province":"Le\u00f3n",
    "wof:name":"Elena Castro Rodriguez",
    "wof:placetype":"venue"
},
  "geometry": {"coordinates":[-5.571668148,42.5969047546],"type":"Point"}
}