{
  "type": "Feature",
  "properties": {
    "iso:country":"ES",
    "sg:address":"Calle de Bailen, 8",
    "sg:city":"Madrid",
    "sg:orig_category":"Promotores Constructores",
    "sg:phone":"+34 915 42 32 10",
    "sg:postcode":"28013",
    "sg:province":"Madrid",
    "wof:name":"Construcciones Angel B.beltran S.a.",
    "wof:placetype":"venue"
},
  "geometry": {"coordinates":[-3.7135357857,40.4151992798],"type":"Point"}
}