{
  "type": "Feature",
  "properties": {
    "addr:full":"Calle de Privilegio De La Union, 35 Zaragoza Zaragoza 50013",
    "addr:housenumber":"35",
    "addr:postcode":"50013",
    "addr:street":"Calle De Privilegio De La Union",
    "iso:country":"ES",
    "sg:address":"Calle de Privilegio De La Union, 35",
    "sg:city":"Zaragoza",
    "sg:orig_category":"Panader\u00cdas, Panader\u00cdas",
    "sg:phone":"+34 976 49 11 83",
    "sg:postcode":"50013",
    "sg:province":"Zaragoza",
    "sg:website":"www.pastelerianava.com",
    "wof:name":"Pasteleria Nava S.l.",
    "wof:placetype":"venue"
},
  "geometry": {"coordinates":[-0.8708530068,41.6419334412],"type":"Point"}
}