{
  "type": "Feature",
  "properties": {
    "iso:country":"ES",
    "sg:address":"Rond Muralla (da), 112",
    "sg:city":"Lugo",
    "sg:orig_category":"Art\u00cdculos De Regalo (al Por Menor)",
    "sg:phone":"+34 982 25 54 09",
    "sg:postcode":"27004",
    "sg:province":"Lugo",
    "wof:name":"Abel Taboada Olga",
    "wof:placetype":"venue"
},
  "geometry": {"coordinates":[-7.576188,43.013588],"type":"Point"}
}