{
  "type": "Feature",
  "properties": {
    "iso:country":"ES",
    "sg:address":"Avda Constitucion, S/n",
    "sg:city":"Monroy",
    "sg:orig_category":"Charcuter\u00cdas (al Por Menor)",
    "sg:phone":"+34 927 28 02 26",
    "sg:postcode":"10194",
    "sg:province":"C\u00e1ceres",
    "wof:name":"Hermanos Galea S.a.",
    "wof:placetype":"venue"
},
  "geometry": {"coordinates":[-6.2108840942,39.636882782],"type":"Point"}
}