{
  "type": "Feature",
  "properties": {
    "addr:full":"Ctra Villaverde-sevilla, Km. 0001,5 Villaverde Rio Sevilla 41318",
    "addr:postcode":"41318",
    "addr:street":"Ctra Villaverde-Sevilla Km. 0001,5;Rio Sevilla",
    "iso:country":"ES",
    "sg:address":"Ctra Villaverde-sevilla, Km. 0001,5",
    "sg:city":"Villaverde Rio",
    "sg:orig_category":"Agricultores, Agricultores",
    "sg:phone":"+34 955 73 70 00",
    "sg:postcode":"41318",
    "sg:province":"Sevilla",
    "wof:name":"Betica Agricola S. A.",
    "wof:placetype":"venue"
},
  "geometry": {"coordinates":[-5.8795042038,37.5939064026],"type":"Point"}
}