{
  "type": "Feature",
  "properties": {
    "iso:country":"ES",
    "sg:address":"Calle de Sese\u00d1a, 78",
    "sg:city":"Madrid",
    "sg:orig_category":"Estudios, Instalaci\u00d3n De Climatizaci\u00d3n",
    "sg:phone":"+34 917 11 76 05",
    "sg:postcode":"28024",
    "sg:province":"Madrid",
    "wof:name":"Dibucrae S. A.",
    "wof:placetype":"venue"
},
  "geometry": {"coordinates":[-3.7659749985,40.3965263367],"type":"Point"}
}