{
  "type": "Feature",
  "properties": {
    "addr:full":"Calle de Echegaray, S/n Barbate C\u00e1diz 11160",
    "addr:housenumber":"s / n",
    "addr:postcode":"11160",
    "addr:street":"Calle De Echegaray",
    "iso:country":"ES",
    "sg:address":"Calle de Echegaray, S/n",
    "sg:city":"Barbate",
    "sg:orig_category":"M\u00c9dicos: Estomatolog\u00cda",
    "sg:phone":"+34 956 43 30 97",
    "sg:postcode":"11160",
    "sg:province":"C\u00e1diz",
    "wof:name":"Vargas Vazquez Juan Carlos",
    "wof:placetype":"venue"
},
  "geometry": {"coordinates":[-5.9216141701,36.1912612915],"type":"Point"}
}