{
  "type": "Feature",
  "properties": {
    "iso:country":"ES",
    "sg:address":"Calle de Cuba, 9",
    "sg:city":"Torredonjimeno",
    "sg:orig_category":"Ebanister\u00cda",
    "sg:phone":"+34 953 57 21 02",
    "sg:postcode":"23650",
    "sg:province":"Ja\u00e9n",
    "wof:name":"Indelama S.l.",
    "wof:placetype":"venue"
},
  "geometry": {"coordinates":[-3.9336841106,37.7605743408],"type":"Point"}
}