{
  "type": "Feature",
  "properties": {
    "addr:full":"Calle de San Antonio, 8 Aranda Duero Burgos 09400",
    "addr:housenumber":"8",
    "addr:postcode":"09400",
    "addr:street":"Calle De San Antonio",
    "iso:country":"ES",
    "sg:address":"Calle de San Antonio, 8",
    "sg:city":"Aranda Duero",
    "sg:orig_category":"Ense\u00d1anza Variada",
    "sg:phone":"+34 947 51 10 10",
    "sg:postcode":"09400",
    "sg:province":"Burgos",
    "wof:name":"Centro De Estudios Didacticos Y Esperimentales S.l.",
    "wof:placetype":"venue"
},
  "geometry": {"coordinates":[-3.6857700348,41.6723976135],"type":"Point"}
}