{
  "type": "Feature",
  "properties": {
    "addr:full":"Plaz Espa\u00d1a, 2 Santo Domingo De La Calzada La Rioja 26250",
    "addr:housenumber":"2",
    "addr:postcode":"26250",
    "addr:street":"Plaz Espan\u0303A;Calzada;Rioja",
    "iso:country":"ES",
    "sg:address":"Plaz Espa\u00d1a, 2",
    "sg:city":"Santo Domingo De La Calzada",
    "sg:orig_category":"Teatros Y Salas De Espect\u00c1culos",
    "sg:phone":"+34 941 34 00 04",
    "sg:postcode":"26250",
    "sg:province":"La Rioja",
    "wof:name":"Ayuntamiento De Santo Domingo De La Calzada Secretaria",
    "wof:placetype":"venue"
},
  "geometry": {"coordinates":[-2.9475662708,42.424861908],"type":"Point"}
}