{
  "type": "Feature",
  "properties": {
    "iso:country":"ES",
    "sg:address":"Calle de Nardiz Tar Jon, 59",
    "sg:city":"Bermeo",
    "sg:orig_category":"Electricidad: Instaladores",
    "sg:phone":"+34 946 88 48 19",
    "sg:postcode":"48370",
    "sg:province":"Vizcaya",
    "wof:name":"Electricidad Pagay C.b.",
    "wof:placetype":"venue"
},
  "geometry": {"coordinates":[-2.7243700027,43.4201202393],"type":"Point"}
}