{
  "type": "Feature",
  "properties": {
    "iso:country":"ES",
    "sg:address":"Carrer de Joan Guell, 184",
    "sg:city":"Barcelona",
    "sg:orig_category":"Asociaciones Humanitarias, De Cooperaci\u00d3n, De Acci\u00d3n Social",
    "sg:phone":"+34 933 21 46 54",
    "sg:postcode":"08028",
    "sg:province":"Barcelona",
    "sg:website":"www.acsfcem.org",
    "wof:name":"Associacio Catalana D'afectats Per La Sindrome De Fatiga Cronica",
    "wof:placetype":"venue"
},
  "geometry": {"coordinates":[2.1306374073,41.3846054077],"type":"Point"}
}