{
  "type": "Feature",
  "properties": {
    "addr:full":"Avda Xose Solla, 37 Calle Pontevedra 36690",
    "addr:housenumber":"37",
    "addr:postcode":"36690",
    "addr:street":"Avda Xose Solla;Calle Pontevedra",
    "iso:country":"ES",
    "sg:address":"Avda Xose Solla, 37",
    "sg:city":"Calle",
    "sg:orig_category":"Bancos",
    "sg:phone":"+34 986 70 02 19",
    "sg:postcode":"36690",
    "sg:province":"Pontevedra",
    "wof:name":"Banco Espa\u00f1ol De Credito S.a.",
    "wof:placetype":"venue"
},
  "geometry": {"coordinates":[-8.606136322,42.3413925171],"type":"Point"}
}