{
  "type": "Feature",
  "properties": {
    "iso:country":"ES",
    "sg:address":"Calle de San Antonio, 48",
    "sg:city":"Almansa",
    "sg:orig_category":"Bancos",
    "sg:phone":"+34 967 34 12 15",
    "sg:postcode":"02640",
    "sg:province":"Albacete",
    "wof:name":"Banco Vitalicio De Espa\u00d1a C.a.",
    "wof:placetype":"venue"
},
  "geometry": {"coordinates":[-1.1041690111,38.8690986633],"type":"Point"}
}