{
  "type": "Feature",
  "properties": {
    "iso:country":"ES",
    "sg:address":"Calle de Julio Del Campo, 18",
    "sg:city":"Le\u00f3n",
    "sg:orig_category":"Abogados",
    "sg:phone":"+34 987 24 20 23",
    "sg:postcode":"24002",
    "sg:province":"Le\u00f3n",
    "wof:name":"Luera Diez Jose Antonio",
    "wof:placetype":"venue"
},
  "geometry": {"coordinates":[-5.575273037,42.5996932983],"type":"Point"}
}