{
  "type": "Feature",
  "properties": {
    "addr:full":"Calle de Olmos (los), 11 Villaseca Sagra Toledo 45260",
    "addr:housenumber":"11",
    "addr:postcode":"45260",
    "addr:street":"Calle De Olmos Los",
    "iso:country":"ES",
    "sg:address":"Calle de Olmos (los), 11",
    "sg:city":"Villaseca Sagra",
    "sg:orig_category":"Electricidad (montaje, Ensamblaje De Componentes)",
    "sg:phone":"+34 925 27 38 05",
    "sg:postcode":"45260",
    "sg:province":"Toledo",
    "wof:name":"Perez Rizo Jose Manuel",
    "wof:placetype":"venue"
},
  "geometry": {"coordinates":[-3.8813800812,39.9579544067],"type":"Point"}
}