{
  "type": "Feature",
  "properties": {
    "iso:country":"ES",
    "sg:address":"Calle de General San Martin, 1",
    "sg:city":"Valencia",
    "sg:orig_category":"Librer\u00cdas",
    "sg:phone":"+34 963 52 50 60",
    "sg:postcode":"46004",
    "sg:province":"Valencia",
    "wof:name":"Mora Jimenez Lorenzo",
    "wof:placetype":"venue"
},
  "geometry": {"coordinates":[-0.3760839999,39.465587616],"type":"Point"}
}