{
  "type": "Feature",
  "properties": {
    "iso:country":"ES",
    "sg:address":"Calle de General Ricardos, 138",
    "sg:city":"Madrid",
    "sg:orig_category":"Arquitectos",
    "sg:phone":"+34 914 71 10 13",
    "sg:postcode":"28019",
    "sg:province":"Madrid",
    "wof:name":"Garcia Martin Jesus Vicente",
    "wof:placetype":"venue"
},
  "geometry": {"coordinates":[-3.7286310196,40.3905830383],"type":"Point"}
}