{
  "type": "Feature",
  "properties": {
    "addr:full":"Calle de Nervion, 10 Llodio \u00c1lava 01400",
    "addr:housenumber":"10",
    "addr:postcode":"01400",
    "addr:street":"Calle De Nervion",
    "iso:country":"ES",
    "sg:address":"Calle de Nervion, 10",
    "sg:city":"Llodio",
    "sg:orig_category":"Bisuter\u00cda, Joyer\u00cda, Relojer\u00cda (al Por Menor)",
    "sg:phone":"+34 946 72 61 30",
    "sg:postcode":"01400",
    "sg:province":"\u00c1lava",
    "wof:name":"Rodriguez Cordero Juan Pedro",
    "wof:placetype":"venue"
},
  "geometry": {"coordinates":[-2.96230793,43.1422386169],"type":"Point"}
}