{
  "type": "Feature",
  "properties": {
    "addr:full":"Gandara (guillarei), 25 Gandara Pontevedra 36720",
    "addr:housenumber":"25",
    "addr:postcode":"36720",
    "addr:street":"Guillarei",
    "iso:country":"ES",
    "sg:address":"Gandara (guillarei), 25",
    "sg:city":"Gandara",
    "sg:orig_category":"Casas Con Estructura De Madera",
    "sg:phone":"+34 986 60 75 55",
    "sg:postcode":"36720",
    "sg:province":"Pontevedra",
    "sg:website":"www.galimodum.com",
    "wof:name":"Galimodul S.a.l.",
    "wof:placetype":"venue"
},
  "geometry": {"coordinates":[-8.6094818115,42.0647659302],"type":"Point"}
}