{
  "type": "Feature",
  "properties": {
    "addr:full":"Avda Independencia, 8 Zaragoza Zaragoza 50004",
    "addr:housenumber":"8",
    "addr:postcode":"50004",
    "addr:street":"Avda Independencia",
    "iso:country":"ES",
    "sg:address":"Avda Independencia, 8",
    "sg:city":"Zaragoza",
    "sg:orig_category":"Centros De Coordinaci\u00d3n",
    "sg:phone":"+34 976 22 49 02",
    "sg:postcode":"50004",
    "sg:province":"Zaragoza",
    "wof:name":"Arcas Benito Pedro",
    "wof:placetype":"venue"
},
  "geometry": {"coordinates":[-0.8811250925,41.6517829895],"type":"Point"}
}