{
  "type": "Feature",
  "properties": {
    "iso:country":"ES",
    "sg:address":"Calle de Pablo Iglesias, 1",
    "sg:city":"Torremolinos",
    "sg:orig_category":"Plomeros",
    "sg:phone":"+34 952 37 02 01",
    "sg:postcode":"29620",
    "sg:province":"M\u00e1laga",
    "wof:name":"Martin Padilla Miguel Antonio",
    "wof:placetype":"venue"
},
  "geometry": {"coordinates":[-4.5086698532,36.6189727783],"type":"Point"}
}