{
  "type": "Feature",
  "properties": {
    "addr:full":"Calle de Villarramiel, 8 Madrid Madrid 28021",
    "addr:housenumber":"8",
    "addr:postcode":"madrid;28021",
    "addr:street":"Calle De Villarramiel",
    "iso:country":"ES",
    "sg:address":"Calle de Villarramiel, 8",
    "sg:city":"Madrid",
    "sg:orig_category":"Ropa Para Se\u00d1oras Y Caballeros (al Por Menor)",
    "sg:phone":"+34 917 98 61 15",
    "sg:postcode":"28021",
    "sg:province":"Madrid",
    "wof:name":"Tubio Ces Jose Maria",
    "wof:placetype":"venue"
},
  "geometry": {"coordinates":[-3.6853013039,40.3526802063],"type":"Point"}
}