{
  "type": "Feature",
  "properties": {
    "addr:full":"Calle de Julian Garaizar, 1 Algorta Vizcaya 48992",
    "addr:housenumber":"1",
    "addr:postcode":"48992",
    "addr:street":"Calle De Julian Garaizar",
    "iso:country":"ES",
    "sg:address":"Calle de Julian Garaizar, 1",
    "sg:city":"Algorta",
    "sg:orig_category":"Agencias Y Agentes Comerciales, Representantes",
    "sg:phone":"+34 944 60 42 59",
    "sg:postcode":"48992",
    "sg:province":"Vizcaya",
    "wof:name":"San Cristobal De Lorenzo Gonzalo",
    "wof:placetype":"venue"
},
  "geometry": {"coordinates":[-3.0054280758,43.3449401855],"type":"Point"}
}