{
  "type": "Feature",
  "properties": {
    "addr:full":"Plaz Marques De Salamanca, 6 Madrid Madrid 28006",
    "addr:housenumber":"6",
    "addr:postcode":"28006",
    "addr:street":"Marques;Salamanca",
    "iso:country":"ES",
    "sg:address":"Plaz Marques De Salamanca, 6",
    "sg:city":"Madrid",
    "sg:orig_category":"Inmobiliaria (agencias)",
    "sg:phone":"+34 914 31 61 61",
    "sg:postcode":"28006",
    "sg:province":"Madrid",
    "wof:name":"Bpi S.a.",
    "wof:placetype":"venue"
},
  "geometry": {"coordinates":[-3.6876618862,40.4310531616],"type":"Point"}
}