{
  "type": "Feature",
  "properties": {
    "addr:full":"Carr Moll De Ponent, 36 Mao Islas Baleares 07703",
    "addr:housenumber":"36",
    "addr:postcode":"07703",
    "addr:street":"Carr Moll De Ponent",
    "iso:country":"ES",
    "sg:address":"Carr Moll De Ponent, 36",
    "sg:city":"Mao",
    "sg:orig_category":"Porcelanas, Azulejos (fabricaci\u00d3n, Al Por Mayor)",
    "sg:phone":"+34 971 35 03 03",
    "sg:postcode":"07703",
    "sg:province":"Islas Baleares",
    "wof:name":"Ceramica Lora S. L.",
    "wof:placetype":"venue"
},
  "geometry": {"coordinates":[4.265625,39.8903694153],"type":"Point"}
}