{
  "type": "Feature",
  "properties": {
    "addr:full":"Av Meridiana, 335 Barcelona Barcelona 08027",
    "addr:housenumber":"335",
    "addr:postcode":"08027",
    "addr:street":"Meridiana",
    "iso:country":"ES",
    "sg:address":"Av Meridiana, 335",
    "sg:city":"Barcelona",
    "sg:orig_category":"Agentes, Concesionarios Y Sucursales De Veh\u00cdculos",
    "sg:phone":"+34 933 49 19 72",
    "sg:postcode":"08027",
    "sg:province":"Barcelona",
    "wof:name":"Yawara S.a.",
    "wof:placetype":"venue"
},
  "geometry": {"coordinates":[2.1853535175,41.4267120361],"type":"Point"}
}