{
  "type": "Feature",
  "properties": {
    "addr:full":"Avda El Ferial, 82 Benavente Zamora 49600",
    "addr:housenumber":"82",
    "addr:postcode":"49600",
    "addr:street":"Avda El Ferial",
    "iso:country":"ES",
    "sg:address":"Avda El Ferial, 82",
    "sg:city":"Benavente",
    "sg:orig_category":"Inmobiliaria (agencias)",
    "sg:phone":"+34 980 63 78 87",
    "sg:postcode":"49600",
    "sg:province":"Zamora",
    "wof:name":"Caramaba Gestion S.l.",
    "wof:placetype":"venue"
},
  "geometry": {"coordinates":[-5.6798191071,41.9936103821],"type":"Point"}
}