{
  "type": "Feature",
  "properties": {
    "iso:country":"ES",
    "sg:address":"Carrer de Verges Pauli (de), 2",
    "sg:city":"Tortosa",
    "sg:orig_category":"Cl\u00cdnicas Dentales",
    "sg:phone":"+34 977 44 80 95",
    "sg:postcode":"43500",
    "sg:province":"Tarragona",
    "wof:name":"Assistencia Avancada Bcn S.l.",
    "wof:placetype":"venue"
},
  "geometry": {"coordinates":[0.5205851793,40.8047142029],"type":"Point"}
}