{
  "type": "Feature",
  "properties": {
    "iso:country":"ES",
    "sg:address":"Calle de Perales, 3",
    "sg:city":"Getafe",
    "sg:orig_category":"Ropa Y Accesorios",
    "sg:phone":"+34 916 81 86 07",
    "sg:postcode":"28902",
    "sg:province":"Madrid",
    "wof:name":"Ruiz Sanchez Dolores",
    "wof:placetype":"venue"
},
  "geometry": {"coordinates":[-3.7264389992,40.3093566895],"type":"Point"}
}