{
  "type": "Feature",
  "properties": {
    "iso:country":"ES",
    "sg:address":"Av. Libertad, S/n",
    "sg:city":"Alcorcon",
    "sg:orig_category":"Agencias De Viajes",
    "sg:phone":"+34 916 21 03 42",
    "sg:postcode":"28925",
    "sg:province":"Madrid",
    "sg:website":"www.dianatraveleurope.com",
    "wof:name":"Diana Travel Europe",
    "wof:placetype":"venue"
},
  "geometry": {"coordinates":[-3.8043038845,40.352771759],"type":"Point"}
}