{
  "type": "Feature",
  "properties": {
    "addr:full":"Calle de Fermin Caballero, 69 Madrid Madrid 28034",
    "addr:housenumber":"69",
    "addr:postcode":"madrid;28034",
    "addr:street":"Calle De Fermin Caballero",
    "iso:country":"ES",
    "sg:address":"Calle de Fermin Caballero, 69",
    "sg:city":"Madrid",
    "sg:orig_category":"Venta, Montaje De Neum\u00c1ticos",
    "sg:phone":"+34 913 78 48 23",
    "sg:postcode":"28034",
    "sg:province":"Madrid",
    "sg:website":"www.euromaster.com",
    "wof:name":"Euronet Spain S.a.",
    "wof:placetype":"venue"
},
  "geometry": {"coordinates":[-3.711509943,40.4824104309],"type":"Point"}
}