{
  "type": "Feature",
  "properties": {
    "addr:full":"Plaz Espa\u00d1a, 5 Puebla Sancho Perez Badajoz 06310",
    "addr:housenumber":"5",
    "addr:postcode":"06310",
    "addr:street":"Plaz Espan\u0303A;Sancho",
    "iso:country":"ES",
    "sg:address":"Plaz Espa\u00d1a, 5",
    "sg:city":"Puebla Sancho Perez",
    "sg:orig_category":"Caf\u00c9s, Bares, Cervecer\u00cdas",
    "sg:phone":"+34 924 57 54 75",
    "sg:postcode":"06310",
    "sg:province":"Badajoz",
    "wof:name":"Rodriguez Perez Jose Antonio",
    "wof:placetype":"venue"
},
  "geometry": {"coordinates":[-6.3967342377,38.395980835],"type":"Point"}
}