{
  "type": "Feature",
  "properties": {
    "addr:full":"Calle de Abetos (los), 1 Palencia Palencia 34003",
    "addr:postcode":"34003",
    "addr:street":"Calle De Abetos Los",
    "iso:country":"ES",
    "sg:address":"Calle de Abetos (los), 1",
    "sg:city":"Palencia",
    "sg:orig_category":"Reposter\u00cdas",
    "sg:phone":"+34 979 74 52 83",
    "sg:postcode":"34003",
    "sg:province":"Palencia",
    "wof:name":"Gonzalez Palomero Maria Luisa",
    "wof:placetype":"venue"
},
  "geometry": {"coordinates":[-4.5309324265,42.0149536133],"type":"Point"}
}