{
  "type": "Feature",
  "properties": {
    "addr:full":"Carrer de Urgell, 9 S. Andreu Barca Barcelona 08740",
    "addr:housenumber":"9",
    "addr:postcode":"08740",
    "addr:street":"Carrer De Urgell;S. Andreu;Barcelona",
    "iso:country":"ES",
    "sg:address":"Carrer de Urgell, 9",
    "sg:city":"S. Andreu Barca",
    "sg:orig_category":"Centros De Educaci\u00d3n Especial",
    "sg:phone":"+34 936 53 16 89",
    "sg:postcode":"08740",
    "sg:province":"Barcelona",
    "wof:name":"Asociacion De Padres De Alumnos C.i.p Val De Palau",
    "wof:placetype":"venue"
},
  "geometry": {"coordinates":[1.9641236067,41.4516143799],"type":"Point"}
}