{
  "type": "Feature",
  "properties": {
    "iso:country":"ES",
    "sg:address":"Calle de Doctor Ingram, 4",
    "sg:city":"Puerto Cruz",
    "sg:orig_category":"Asociaciones Y Clubs Deportivos",
    "sg:phone":"+34 922 38 47 31",
    "sg:postcode":"38400",
    "sg:province":"Santa Cruz De Tenerife",
    "wof:name":"Devora Garcia Antonio",
    "wof:placetype":"venue"
},
  "geometry": {"coordinates":[-16.5506324768,28.4154930115],"type":"Point"}
}