{
  "type": "Feature",
  "properties": {
    "addr:full":"Calle de Cervantes, 13 Malaga M\u00e1laga 29016",
    "addr:housenumber":"13",
    "addr:postcode":"29016",
    "addr:street":"Calle De Cervantes;Ma\u0301Laga",
    "iso:country":"ES",
    "sg:address":"Calle de Cervantes, 13",
    "sg:city":"Malaga",
    "sg:orig_category":"Restaurantes",
    "sg:phone":"+34 952 60 17 09",
    "sg:postcode":"29016",
    "sg:province":"M\u00e1laga",
    "wof:name":"Ruiz Moreno Adolfo",
    "wof:placetype":"venue"
},
  "geometry": {"coordinates":[-4.4100031853,36.7189254761],"type":"Point"}
}