{
  "type": "Feature",
  "properties": {
    "addr:full":"Calle de Ramon Y Cajal, 13 Miguelturra Ciudad Real 13170",
    "addr:housenumber":"13",
    "addr:postcode":"13170",
    "addr:street":"Calle De Ramon Y Cajal",
    "iso:country":"ES",
    "sg:address":"Calle de Ramon Y Cajal, 13",
    "sg:city":"Miguelturra",
    "sg:orig_category":"Panader\u00cdas, Panader\u00cdas",
    "sg:phone":"+34 926 24 03 19",
    "sg:postcode":"13170",
    "sg:province":"Ciudad Real",
    "wof:name":"Pasteleria Casas S.l.",
    "wof:placetype":"venue"
},
  "geometry": {"coordinates":[-3.8885750771,38.9671974182],"type":"Point"}
}