{
  "type": "Feature",
  "properties": {
    "iso:country":"ES",
    "sg:address":"Carr Combat, 12",
    "sg:city":"Cervera",
    "sg:orig_category":"Inmobiliaria (agencias)",
    "sg:phone":"+34 973 53 14 09",
    "sg:postcode":"25200",
    "sg:province":"Lleida",
    "wof:name":"Fincas Segarra S.l.",
    "wof:placetype":"venue"
},
  "geometry": {"coordinates":[1.2729769945,41.6707382202],"type":"Point"}
}