{
  "type": "Feature",
  "properties": {
    "addr:full":"Rua Rio (do), 1 Burela Lugo 27880",
    "addr:postcode":"27880",
    "addr:street":"Rua",
    "iso:country":"ES",
    "sg:address":"Rua Rio (do), 1",
    "sg:city":"Burela",
    "sg:orig_category":"Complementos De Vestir (al Por Menor)",
    "sg:phone":"+34 982 58 12 66",
    "sg:postcode":"27880",
    "sg:province":"Lugo",
    "wof:name":"Castro Perez Piedad",
    "wof:placetype":"venue"
},
  "geometry": {"coordinates":[-7.3575358391,43.6620674133],"type":"Point"}
}