{
  "type": "Feature",
  "properties": {
    "addr:full":"Calle de Jose Artes De Arcos, 15 Almeria Almer\u00eda 04004",
    "addr:housenumber":"15",
    "addr:postcode":"04004",
    "addr:street":"Calle De Jose Artes De Arcos",
    "iso:country":"ES",
    "sg:address":"Calle de Jose Artes De Arcos, 15",
    "sg:city":"Almeria",
    "sg:orig_category":"Cajas Para Embalar",
    "sg:phone":"+34 950 62 11 37",
    "sg:postcode":"04004",
    "sg:province":"Almer\u00eda",
    "wof:name":"Cajamar",
    "wof:placetype":"venue"
},
  "geometry": {"coordinates":[-2.4587979317,36.8356056213],"type":"Point"}
}