{
  "type": "Feature",
  "properties": {
    "iso:country":"ES",
    "sg:address":"Plaz Parque De Capuchinos, 1",
    "sg:city":"Jerez De La Frontera",
    "sg:orig_category":"Abogados",
    "sg:phone":"+34 956 30 99 49",
    "sg:postcode":"11405",
    "sg:province":"C\u00e1diz",
    "wof:name":"Calderon Rodriguez Pedro",
    "wof:placetype":"venue"
},
  "geometry": {"coordinates":[-6.1005191803,36.7067260742],"type":"Point"}
}