{
  "type": "Feature",
  "properties": {
    "addr:full":"Ctra Madrid, Km. 0306,7 Zaragoza Zaragoza 50012",
    "addr:postcode":"50012",
    "addr:street":"Ctra Madrid Km. 0306,7",
    "iso:country":"ES",
    "sg:address":"Ctra Madrid, Km. 0306,7",
    "sg:city":"Zaragoza",
    "sg:orig_category":"Distribuci\u00d3n De Petr\u00d3leo Y Derivados",
    "sg:phone":"+34 976 31 95 23",
    "sg:postcode":"50012",
    "sg:province":"Zaragoza",
    "wof:name":"Agip Espa\u00d1a S.a",
    "wof:placetype":"venue"
},
  "geometry": {"coordinates":[-0.8944001198,41.6558113098],"type":"Point"}
}