{
  "type": "Feature",
  "properties": {
    "iso:country":"ES",
    "sg:address":"Calle de Crisanta (do\u00d1a), 47",
    "sg:city":"Tomelloso",
    "sg:orig_category":"Agencias Y Asesores De Publicidad",
    "sg:phone":"+34 926 50 55 76",
    "sg:postcode":"13700",
    "sg:province":"Ciudad Real",
    "wof:name":"Ediciones Soubriet S.l.",
    "wof:placetype":"venue"
},
  "geometry": {"coordinates":[-3.015955925,39.1558876038],"type":"Point"}
}