{
  "type": "Feature",
  "properties": {
    "addr:full":"Carrer de Riereta, 1 Barcelona Barcelona 08001",
    "addr:housenumber":"1",
    "addr:postcode":"08001",
    "addr:street":"Carrer De Riereta",
    "iso:country":"ES",
    "sg:address":"Carrer de Riereta, 1",
    "sg:city":"Barcelona",
    "sg:orig_category":"Carnicer\u00cdas, Carnicer\u00cdas",
    "sg:phone":"+34 933 29 35 66",
    "sg:postcode":"08001",
    "sg:province":"Barcelona",
    "wof:name":"Novoa Alvarez Jonathan",
    "wof:placetype":"venue"
},
  "geometry": {"coordinates":[2.1671390533,41.3792533875],"type":"Point"}
}