{
  "type": "Feature",
  "properties": {
    "addr:full":"Carrer de Miquel Torello I Pages, 5 Molins Rei Barcelona 08750",
    "addr:housenumber":"5",
    "addr:postcode":"08750",
    "addr:street":"Carrer De Miquel Torello I Pages;Barcelona",
    "iso:country":"ES",
    "sg:address":"Carrer de Miquel Torello I Pages, 5",
    "sg:city":"Molins Rei",
    "sg:orig_category":"Discotecas Y Salas De Baile",
    "sg:phone":"+34 936 80 31 02",
    "sg:postcode":"08750",
    "sg:province":"Barcelona",
    "wof:name":"Kinbonpla S.l.",
    "wof:placetype":"venue"
},
  "geometry": {"coordinates":[2.0284359455,41.3991622925],"type":"Point"}
}