{
  "type": "Feature",
  "properties": {
    "addr:full":"Avda Rio Nalon (del), 13 Alcazares Murcia 30710",
    "addr:housenumber":"13",
    "addr:postcode":"30710",
    "addr:street":"Avda Rio Nalon Del",
    "iso:country":"ES",
    "sg:address":"Avda Rio Nalon (del), 13",
    "sg:city":"Alcazares",
    "sg:orig_category":"Inmobiliaria (agencias)",
    "sg:phone":"+34 968 57 44 48",
    "sg:postcode":"30710",
    "sg:province":"Murcia",
    "sg:website":"www.swinglandestates.com",
    "wof:name":"Maldonado Andreu Juan Fernando",
    "wof:placetype":"venue"
},
  "geometry": {"coordinates":[-0.8440899849,37.7543334961],"type":"Point"}
}