{
  "type": "Feature",
  "properties": {
    "addr:full":"Carrer de Coll I Agullo, S/n Mataro Barcelona 08302",
    "addr:housenumber":"s",
    "addr:postcode":"08302",
    "addr:street":"Carrer De Coll I Agullo;/ N Mataro Barcelona",
    "iso:country":"ES",
    "sg:address":"Carrer de Coll I Agullo, S/n",
    "sg:city":"Mataro",
    "sg:orig_category":"Fabricaci\u00d3n De Moldes Y Modelos",
    "sg:phone":"+34 937 98 30 00",
    "sg:postcode":"08302",
    "sg:province":"Barcelona",
    "wof:name":"Productos Transformados S.a.",
    "wof:placetype":"venue"
},
  "geometry": {"coordinates":[2.430644989,41.5349388123],"type":"Point"}
}