{
  "type": "Feature",
  "properties": {
    "addr:full":"Pase Rosa, 92 Toledo Toledo 45006",
    "addr:housenumber":"92",
    "addr:postcode":"45006",
    "addr:street":"Rosa",
    "iso:country":"ES",
    "sg:address":"Pase Rosa, 92",
    "sg:city":"Toledo",
    "sg:orig_category":"Ingenier\u00cda, Centros De Estudios (diversos)",
    "sg:phone":"+34 925 22 71 19",
    "sg:postcode":"45006",
    "sg:province":"Toledo",
    "wof:name":"Servicios Integrales De Toledo S.l.",
    "wof:placetype":"venue"
},
  "geometry": {"coordinates":[-4.0053992271,39.860748291],"type":"Point"}
}