{
  "type": "Feature",
  "properties": {
    "iso:country":"ES",
    "sg:address":"Trva Doctor Velasco, S/n",
    "sg:city":"Laredo",
    "sg:orig_category":"Edici\u00d3n De Diarios, Revistas, Boletines",
    "sg:phone":"+34 942 61 12 81",
    "sg:postcode":"39770",
    "sg:province":"Cantabria",
    "wof:name":"Yarjok S.c.",
    "wof:placetype":"venue"
},
  "geometry": {"coordinates":[-3.3943319321,43.4094390869],"type":"Point"}
}