{
  "type": "Feature",
  "properties": {
    "addr:full":"Calle de Martinete Del, 32 Aviles Asturias 33460",
    "addr:housenumber":"32",
    "addr:postcode":"33460",
    "addr:street":"Calle De Martinete Del",
    "iso:country":"ES",
    "sg:address":"Calle de Martinete Del, 32",
    "sg:city":"Aviles",
    "sg:orig_category":"Molduras, Junquillos, Listones Y Molduras Perforadas",
    "sg:phone":"+34 985 57 06 19",
    "sg:postcode":"33460",
    "sg:province":"Asturias",
    "wof:name":"Arroyo Alonso Jose Luis",
    "wof:placetype":"venue"
},
  "geometry": {"coordinates":[-5.9008321762,43.5419006348],"type":"Point"}
}