{
  "type": "Feature",
  "properties": {
    "addr:full":"Calle de San Cosme, 17 Cuenca Cuenca 16003",
    "addr:housenumber":"17",
    "addr:postcode":"16003",
    "addr:street":"Calle De San Cosme",
    "iso:country":"ES",
    "sg:address":"Calle de San Cosme, 17",
    "sg:city":"Cuenca",
    "sg:orig_category":"Aparatos, Sistemas De Tele",
    "sg:phone":"+34 969 24 09 60",
    "sg:postcode":"16003",
    "sg:province":"Cuenca",
    "sg:website":"www.novotecseguridad.es",
    "wof:name":"Novotec Sistemas De Seguridad S.a.",
    "wof:placetype":"venue"
},
  "geometry": {"coordinates":[-2.1468150616,40.0711174011],"type":"Point"}
}