{
  "type": "Feature",
  "properties": {
    "iso:country":"ES",
    "sg:address":"Calle de Blas Infante, 28",
    "sg:city":"Villa Rio",
    "sg:orig_category":"Supermercados Y Hipermercados",
    "sg:phone":"+34 957 17 71 79",
    "sg:postcode":"14640",
    "sg:province":"C\u00f3rdoba",
    "wof:name":"Luis Pi\u00d1a S.a.",
    "wof:placetype":"venue"
},
  "geometry": {"coordinates":[-4.2931756973,37.9820785522],"type":"Point"}
}