{
  "type": "Feature",
  "properties": {
    "iso:country":"ES",
    "sg:address":"Calle de Ruiz De Alarcon, 13",
    "sg:city":"Madrid",
    "sg:orig_category":"Ropa Y Accesorios",
    "sg:phone":"+34 913 60 48 50",
    "sg:postcode":"28014",
    "sg:province":"Madrid",
    "sg:website":"www.robertoverino.com",
    "wof:name":"Roberto Verino Difusion S.a.",
    "wof:placetype":"venue"
},
  "geometry": {"coordinates":[-3.6913259029,40.41563797],"type":"Point"}
}