{
  "type": "Feature",
  "properties": {
    "addr:full":"Carr Espero, De S', 110 Poima Islas Baleares 07714",
    "addr:housenumber":"110",
    "addr:postcode":"07714",
    "addr:street":"Carr Espero De S '",
    "iso:country":"ES",
    "sg:address":"Carr Espero, De S', 110",
    "sg:city":"Poima",
    "sg:orig_category":"Veh\u00cdculos De Ocasi\u00d3n",
    "sg:phone":"+34 971 35 48 78",
    "sg:postcode":"07714",
    "sg:province":"Islas Baleares",
    "wof:name":"Autos Gregal S.l.",
    "wof:placetype":"venue"
},
  "geometry": {"coordinates":[4.2437052727,39.8896369934],"type":"Point"}
}