{
  "type": "Feature",
  "properties": {
    "iso:country":"ES",
    "sg:address":"Calle de Virgen De Los Angeles, 31",
    "sg:city":"Javea",
    "sg:orig_category":"Albergues",
    "sg:phone":"+34 965 79 12 19",
    "sg:postcode":"03730",
    "sg:province":"Alicante",
    "wof:name":"Carrio Berenguer Y Otros C.b.",
    "wof:placetype":"venue"
},
  "geometry": {"coordinates":[0.1628039926,38.7914772034],"type":"Point"}
}