{
  "type": "Feature",
  "properties": {
    "addr:full":"Calle de San Hermenegildo, S/n Alquife Granada 18518",
    "addr:housenumber":"s / n",
    "addr:postcode":"18518",
    "addr:street":"Calle De San Hermenegildo",
    "iso:country":"ES",
    "sg:address":"Calle de San Hermenegildo, S/n",
    "sg:city":"Alquife",
    "sg:orig_category":"Minerales (al Por Mayor)",
    "sg:phone":"+34 958 67 30 17",
    "sg:postcode":"18518",
    "sg:province":"Granada",
    "wof:name":"Compa\u00f1ia Minera Del Marquesado",
    "wof:placetype":"venue"
},
  "geometry": {"coordinates":[-3.1148240566,37.1803398132],"type":"Point"}
}