{
  "type": "Feature",
  "properties": {
    "iso:country":"ES",
    "sg:address":"Barr Suiza, 25",
    "sg:city":"Rozas De Madrid",
    "sg:orig_category":"Asociaciones Y Clubs Deportivos",
    "sg:phone":"+34 916 37 79 67",
    "sg:postcode":"28230",
    "sg:province":"Madrid",
    "wof:name":"Lahiguera Olivar Fernando",
    "wof:placetype":"venue"
},
  "geometry": {"coordinates":[-3.8913800716,40.5247497559],"type":"Point"}
}