{
  "type": "Feature",
  "properties": {
    "addr:full":"Avda Carlota Alessandri, 46 Torremolinos M\u00e1laga 29620",
    "addr:housenumber":"46",
    "addr:postcode":"29620",
    "addr:street":"Avda Carlota Alessandri;Ma\u0301Laga",
    "iso:country":"ES",
    "sg:address":"Avda Carlota Alessandri, 46",
    "sg:city":"Torremolinos",
    "sg:orig_category":"Agencias De Viajes",
    "sg:phone":"+34 952 05 83 88",
    "sg:postcode":"29620",
    "sg:province":"M\u00e1laga",
    "wof:name":"Viajes Europalia",
    "wof:placetype":"venue"
},
  "geometry": {"coordinates":[-4.5038070679,36.6146278381],"type":"Point"}
}