{
  "type": "Feature",
  "properties": {
    "addr:full":"Plaz Lur Gorri, 16 Bara\u00f1ain Navarra 31010",
    "addr:housenumber":"16",
    "addr:postcode":"31010",
    "addr:street":"Baran\u0303Ain Navarra",
    "iso:country":"ES",
    "sg:address":"Plaz Lur Gorri, 16",
    "sg:city":"Bara\u00f1ain",
    "sg:orig_category":"Estancos",
    "sg:phone":"+34 948 18 82 99",
    "sg:postcode":"31010",
    "sg:province":"Navarra",
    "wof:name":"Sarasa Astrain Jesus",
    "wof:placetype":"venue"
},
  "geometry": {"coordinates":[-97.78224945069999,45.7040786743],"type":"Point"}
}