{
  "type": "Feature",
  "properties": {
    "addr:full":"Avda Andalucia, 32 Puebla Vicar Almer\u00eda 04738",
    "addr:housenumber":"32",
    "addr:postcode":"04738",
    "addr:street":"Avda Andalucia",
    "iso:country":"ES",
    "sg:address":"Avda Andalucia, 32",
    "sg:city":"Puebla Vicar",
    "sg:orig_category":"Cajas De Ahorro",
    "sg:phone":"+34 950 55 33 56",
    "sg:postcode":"04738",
    "sg:province":"Almer\u00eda",
    "sg:website":"www.unicaja.es",
    "wof:name":"Unicaja",
    "wof:placetype":"venue"
},
  "geometry": {"coordinates":[-2.6202991009,36.8065261841],"type":"Point"}
}