{
  "type": "Feature",
  "properties": {
    "addr:full":"Carrer de Marques Fontsanta, 16 Palma Islas Baleares 07005",
    "addr:housenumber":"16",
    "addr:postcode":"07005",
    "addr:street":"Carrer De Marques Fontsanta",
    "iso:country":"ES",
    "sg:address":"Carrer de Marques Fontsanta, 16",
    "sg:city":"Palma",
    "sg:orig_category":"Abogados",
    "sg:phone":"+34 971 46 11 97",
    "sg:postcode":"07005",
    "sg:province":"Islas Baleares",
    "wof:name":"Mateu Alvaro Cesar",
    "wof:placetype":"venue"
},
  "geometry": {"coordinates":[2.6564590931,39.5766067505],"type":"Point"}
}