{
  "type": "Feature",
  "properties": {
    "addr:full":"Rua Laracha, 11 Carballo La Coru\u00f1a 15100",
    "addr:housenumber":"11",
    "addr:postcode":"15100",
    "addr:street":"Rua Laracha;La Corun\u0303A",
    "iso:country":"ES",
    "sg:address":"Rua Laracha, 11",
    "sg:city":"Carballo",
    "sg:orig_category":"Plomeros",
    "sg:phone":"+34 981 70 10 28",
    "sg:postcode":"15100",
    "sg:province":"La Coru\u00f1a",
    "wof:name":"Regueira Pombo Jose Manuel",
    "wof:placetype":"venue"
},
  "geometry": {"coordinates":[-8.688914299,43.2188415527],"type":"Point"}
}