{
  "type": "Feature",
  "properties": {
    "iso:country":"ES",
    "sg:address":"Pla\u00c7 De L'emperador Carles I, 2",
    "sg:city":"Benicarlo",
    "sg:orig_category":"Caf\u00c9s, Bares, Cervecer\u00cdas",
    "sg:phone":"+34 964 46 18 73",
    "sg:postcode":"12580",
    "sg:province":"Castell\u00f3n",
    "wof:name":"Camacho Ca\u00f1izares Angela",
    "wof:placetype":"venue"
},
  "geometry": {"coordinates":[0.4275819957,40.4183349609],"type":"Point"}
}