{
  "type": "Feature",
  "properties": {
    "iso:country":"ES",
    "sg:address":"Calle de Ramiro Molina, 27",
    "sg:city":"Madrid",
    "sg:orig_category":"Electricidad (montaje, Ensamblaje De Componentes)",
    "sg:phone":"+34 914 63 44 49",
    "sg:postcode":"28011",
    "sg:province":"Madrid",
    "wof:name":"Conde Pernia Mariano",
    "wof:placetype":"venue"
},
  "geometry": {"coordinates":[-3.7358570099,40.409412384],"type":"Point"}
}