{
  "type": "Feature",
  "properties": {
    "addr:full":"Calle de Ronda San Antonio, 13 Remolinos Zaragoza 50637",
    "addr:housenumber":"13",
    "addr:postcode":"50637",
    "addr:street":"Calle De Ronda San Antonio",
    "iso:country":"ES",
    "sg:address":"Calle de Ronda San Antonio, 13",
    "sg:city":"Remolinos",
    "sg:classifiers":[
        {
            "category":"Taxi",
            "type":"Transportation"
        }
    ],
    "sg:phone":"+34 976 61 81 38",
    "sg:postcode":"50637",
    "sg:province":"Zaragoza",
    "wof:name":"Richart Gonzalez Francisco",
    "wof:placetype":"venue"
},
  "geometry": {"coordinates":[-1.1787090302,41.8365440369],"type":"Point"}
}