{
  "type": "Feature",
  "properties": {
    "iso:country":"ES",
    "sg:address":"Avda Carmen Miranda, S/n",
    "sg:city":"Pravia",
    "sg:orig_category":"Estancos",
    "sg:phone":"+34 985 82 00 47",
    "sg:postcode":"33120",
    "sg:province":"Asturias",
    "wof:name":"Fernandez Alvarez Maria Del Valle",
    "wof:placetype":"venue"
},
  "geometry": {"coordinates":[-6.1125969887,43.4895515442],"type":"Point"}
}