{
  "type": "Feature",
  "properties": {
    "addr:full":"Cmno Bordar, S/n Torreblanca Castell\u00f3n 12596",
    "addr:housenumber":"s / n",
    "addr:postcode":"12596",
    "addr:street":"Cmno Bordar;Castello\u0301N",
    "iso:country":"ES",
    "sg:address":"Cmno Bordar, S/n",
    "sg:city":"Torreblanca",
    "sg:orig_category":"Negocio De Materiales De Construcci\u00d3n",
    "sg:phone":"+34 964 42 00 21",
    "sg:postcode":"12596",
    "sg:province":"Castell\u00f3n",
    "wof:name":"Arturo Albalat S.l.",
    "wof:placetype":"venue"
},
  "geometry": {"coordinates":[0.1963364035,40.2167320251],"type":"Point"}
}