{
  "type": "Feature",
  "properties": {
    "addr:full":"Calle de Flores, S/n Arboleas Almer\u00eda 04660",
    "addr:housenumber":"s",
    "addr:postcode":"04660",
    "addr:street":"Calle De Flores;/ N Arboleas Almeri\u0301A",
    "iso:country":"ES",
    "sg:address":"Calle de Flores, S/n",
    "sg:city":"Arboleas",
    "sg:orig_category":"Administraciones Regionales, Departamentales Y Locales",
    "sg:phone":"+34 950 44 94 37",
    "sg:postcode":"04660",
    "sg:province":"Almer\u00eda",
    "wof:name":"Ayuntamiento De Arboleas",
    "wof:placetype":"venue"
},
  "geometry": {"coordinates":[-2.073823452,37.351348877],"type":"Point"}
}