{
  "type": "Feature",
  "properties": {
    "addr:full":"Calle de Policarpo Herrero, S/n Oviedo Asturias 33006",
    "addr:housenumber":"s / n",
    "addr:postcode":"33006",
    "addr:street":"Calle De Policarpo Herrero",
    "iso:country":"ES",
    "sg:address":"Calle de Policarpo Herrero, S/n",
    "sg:city":"Oviedo",
    "sg:orig_category":"Asociaciones Humanitarias, De Cooperaci\u00d3n, De Acci\u00d3n Social",
    "sg:phone":"+34 985 27 73 95",
    "sg:postcode":"33006",
    "sg:province":"Asturias",
    "wof:name":"Asociacion Para La Defensa De La Atencion A La Anorexia Nerviosa",
    "wof:placetype":"venue"
},
  "geometry": {"coordinates":[-5.8610572815,43.3573799133],"type":"Point"}
}