{
  "type": "Feature",
  "properties": {
    "addr:full":"Arriaga Kalea, 7 Elgoibar Guip\u00f9zcoa 20870",
    "addr:housenumber":"7",
    "addr:postcode":"20870",
    "addr:street":"Arriaga Kalea;Guipu\u0300Zcoa",
    "iso:country":"ES",
    "sg:address":"Arriaga Kalea, 7",
    "sg:city":"Elgoibar",
    "sg:orig_category":"Engranajes Y Elementos De Transmisi\u00d3n",
    "sg:phone":"+34 943 74 20 62",
    "sg:postcode":"20870",
    "sg:province":"Guip\u00f9zcoa",
    "wof:name":"Engranajes Grindel S.a.l.",
    "wof:placetype":"venue"
},
  "geometry": {"coordinates":[-2.4138290882,43.2163581848],"type":"Point"}
}