{
  "type": "Feature",
  "properties": {
    "addr:full":"Pase Herrera De, 82 Donostia-san Sebastian Guip\u00f9zcoa 20017",
    "addr:housenumber":"82",
    "addr:postcode":"20017",
    "iso:country":"ES",
    "sg:address":"Pase Herrera De, 82",
    "sg:city":"Donostia-san Sebastian",
    "sg:orig_category":"Inmobiliaria (alquileres Por Temporada Y Temporales)",
    "sg:phone":"+34 943 35 01 92",
    "sg:postcode":"20017",
    "sg:province":"Guip\u00f9zcoa",
    "wof:name":"Gonzalez Rodriguez Felix",
    "wof:placetype":"venue"
},
  "geometry": {"coordinates":[-1.9308949709,43.3183784485],"type":"Point"}
}