{
  "type": "Feature",
  "properties": {
    "iso:country":"ES",
    "sg:address":"Carrer de Angel Guimera, 9",
    "sg:city":"S. Adria Besos",
    "sg:orig_category":"Transportes Ferroviarios",
    "sg:phone":"+34 934 62 30 03",
    "sg:postcode":"08930",
    "sg:province":"Barcelona",
    "wof:name":"Conservacion De Via E Infraestructura S.a.",
    "wof:placetype":"venue"
},
  "geometry": {"coordinates":[2.2227139473,41.4291877747],"type":"Point"}
}