{
  "type": "Feature",
  "properties": {
    "iso:country":"ES",
    "sg:address":"Calle de Pablo Morillo, 22",
    "sg:city":"Zamora",
    "sg:orig_category":"Fabricaci\u00d3n, Instalaci\u00d3n De Escaleras",
    "sg:phone":"+34 980 51 14 10",
    "sg:postcode":"49013",
    "sg:province":"Zamora",
    "wof:name":"Humara Sesma Sandra",
    "wof:placetype":"venue"
},
  "geometry": {"coordinates":[-5.7400169373,41.5095443726],"type":"Point"}
}