{
  "type": "Feature",
  "properties": {
    "iso:country":"ES",
    "sg:address":"Carrer de Vilanova, 21",
    "sg:city":"Manresa",
    "sg:orig_category":"Reposter\u00cdas",
    "sg:phone":"+34 938 72 29 42",
    "sg:postcode":"08241",
    "sg:province":"Barcelona",
    "wof:name":"Portabella Purti Damian",
    "wof:placetype":"venue"
},
  "geometry": {"coordinates":[1.8238209486,41.7230415344],"type":"Point"}
}