{
  "type": "Feature",
  "properties": {
    "addr:full":"Avgd Catalunya, 17 Lleida Lleida 25002",
    "addr:housenumber":"17",
    "addr:postcode":"25002",
    "iso:country":"ES",
    "sg:address":"Avgd Catalunya, 17",
    "sg:city":"Lleida",
    "sg:orig_category":"Cajas De Ahorro",
    "sg:phone":"+34 973 26 80 28",
    "sg:postcode":"25002",
    "sg:province":"Lleida",
    "wof:name":"Caja De Ahorros Del Mediterraneo",
    "wof:placetype":"venue"
},
  "geometry": {"coordinates":[0.6198999882,41.6117591858],"type":"Point"}
}