{
  "type": "Feature",
  "properties": {
    "iso:country":"ES",
    "sg:address":"Trva Sainz Ezquerra, S/n",
    "sg:city":"Colindres",
    "sg:orig_category":"Electricidad, Electr\u00d3nica: Material Y Suministros (al Por Mayor)",
    "sg:phone":"+34 942 65 05 01",
    "sg:postcode":"39750",
    "sg:province":"Cantabria",
    "sg:website":"www.diselec.es",
    "wof:name":"Hidrodiselec S.a.",
    "wof:placetype":"venue"
},
  "geometry": {"coordinates":[-3.4482440948,43.3958396912],"type":"Point"}
}