{
  "type": "Feature",
  "properties": {
    "iso:country":"ES",
    "sg:address":"Cmno Cruces, 42",
    "sg:city":"Madrid",
    "sg:orig_category":"Mec\u00c1nico Del Autom\u00d3vil",
    "sg:phone":"+34 915 09 35 43",
    "sg:postcode":"28044",
    "sg:province":"Madrid",
    "wof:name":"Rafael Mera Rey Y Raul Irribarria Elena C.b",
    "wof:placetype":"venue"
},
  "geometry": {"coordinates":[-3.7571959496,40.3730888367],"type":"Point"}
}