{
  "type": "Feature",
  "properties": {
    "addr:full":"Ctra Cordoba-malaga, Km. 0438,0 Rambla C\u00f3rdoba 14540",
    "addr:postcode":"14540",
    "addr:street":"Ctra Cordoba-Malaga Km. 0438,0 Rambla Co\u0301Rdoba",
    "iso:country":"ES",
    "sg:address":"Ctra Cordoba-malaga, Km. 0438,0",
    "sg:city":"Rambla",
    "sg:orig_category":"Fabrica De Cer\u00c1micas",
    "sg:phone":"+34 957 68 27 26",
    "sg:postcode":"14540",
    "sg:province":"C\u00f3rdoba",
    "wof:name":"Rio Almagro Mateo Del",
    "wof:placetype":"venue"
},
  "geometry": {"coordinates":[-4.7416338921,37.6080932617],"type":"Point"}
}