{
  "type": "Feature",
  "properties": {
    "iso:country":"ES",
    "sg:address":"Av Estrella(pol Ind Estrella), S/n",
    "sg:city":"Torre-pacheco",
    "sg:orig_category":"Electricidad: Instaladores",
    "sg:phone":"+34 968 57 97 17",
    "sg:postcode":"30700",
    "sg:province":"Murcia",
    "wof:name":"Proyectos Pizarro S.l.",
    "wof:placetype":"venue"
},
  "geometry": {"coordinates":[-0.9774929881,37.7509269714],"type":"Point"}
}