{
  "type": "Feature",
  "properties": {
    "addr:full":"Rua Castelao, 10 Vilagarcia Pontevedra 36600",
    "addr:housenumber":"10",
    "addr:postcode":"36600",
    "addr:street":"Rua Castelao",
    "iso:country":"ES",
    "sg:address":"Rua Castelao, 10",
    "sg:city":"Vilagarcia",
    "sg:orig_category":"Sociedades, Compa\u00d1\u00cdas Aseguradoras",
    "sg:phone":"+34 986 50 82 85",
    "sg:postcode":"36600",
    "sg:province":"Pontevedra",
    "wof:name":"Dorgambide Y Asociados Corredores De Seguros S.l.",
    "wof:placetype":"venue"
},
  "geometry": {"coordinates":[-8.768040657,42.5932426453],"type":"Point"}
}