{
  "type": "Feature",
  "properties": {
    "iso:country":"ES",
    "sg:address":"Calle de Irun, 6",
    "sg:city":"Errenteria",
    "sg:orig_category":"Comercio De Piezas De Recambio Y De Accesorios De Veh\u00cdculos, Veh\u00cdculos Industriales",
    "sg:phone":"+34 943 52 70 07",
    "sg:postcode":"20100",
    "sg:province":"Guip\u00f9zcoa",
    "wof:name":"Recambios Ardatz S.l.",
    "wof:placetype":"venue"
},
  "geometry": {"coordinates":[-1.9034110308,43.3157348633],"type":"Point"}
}