{
  "type": "Feature",
  "properties": {
    "addr:full":"Carrer de Pirineus, S/n Sabadell Barcelona 08208",
    "addr:housenumber":"s",
    "addr:postcode":"08208",
    "addr:street":"Carrer De Pirineus;/ N",
    "iso:country":"ES",
    "sg:address":"Carrer de Pirineus, S/n",
    "sg:city":"Sabadell",
    "sg:orig_category":"Congelados: Productos Alimentarios (al Por Menor)",
    "sg:phone":"+34 937 24 01 87",
    "sg:postcode":"08208",
    "sg:province":"Barcelona",
    "wof:name":"Mayoral Pujol Santiago",
    "wof:placetype":"venue"
},
  "geometry": {"coordinates":[2.1021149158,41.5605812073],"type":"Point"}
}