{
  "type": "Feature",
  "properties": {
    "iso:country":"ES",
    "sg:address":"Calle de Mercado (del), 1",
    "sg:city":"Rute",
    "sg:orig_category":"Pescader\u00cdas (al Por Menor)",
    "sg:phone":"+34 957 53 88 92",
    "sg:postcode":"14960",
    "sg:province":"C\u00f3rdoba",
    "wof:name":"Rabasco Lopez Manuel",
    "wof:placetype":"venue"
},
  "geometry": {"coordinates":[-4.3730192184,37.3269767761],"type":"Point"}
}