{
  "type": "Feature",
  "properties": {
    "iso:country":"ES",
    "sg:address":"Carr Sant Iscle, 22",
    "sg:city":"Breda",
    "sg:orig_category":"Mercer\u00cda, Lencer\u00cda (al Por Menor)",
    "sg:phone":"+34 972 87 00 41",
    "sg:postcode":"17400",
    "sg:province":"Girona",
    "wof:name":"Polls Timonet Roser",
    "wof:placetype":"venue"
},
  "geometry": {"coordinates":[2.5579600334,41.7478637695],"type":"Point"}
}