{
  "type": "Feature",
  "properties": {
    "addr:full":"Calle de Sol, 9 Valladolid Valladolid 47007",
    "addr:housenumber":"9",
    "addr:postcode":"47007",
    "addr:street":"Calle De Sol",
    "iso:country":"ES",
    "sg:address":"Calle de Sol, 9",
    "sg:city":"Valladolid",
    "sg:orig_category":"Publicidad (soportes Y Gesti\u00d3n)",
    "sg:phone":"+34 983 47 50 89",
    "sg:postcode":"47007",
    "sg:province":"Valladolid",
    "wof:name":"Gallego Gallego Jose Antonio",
    "wof:placetype":"venue"
},
  "geometry": {"coordinates":[-4.7363348007,41.6338691711],"type":"Point"}
}