{
  "type": "Feature",
  "properties": {
    "addr:full":"Calle de Castrillo, 18 Palmas De Gran Canaria Las Palmas 35004",
    "addr:housenumber":"18",
    "addr:postcode":"35004",
    "addr:street":"Calle De Castrillo",
    "iso:country":"ES",
    "sg:address":"Calle de Castrillo, 18",
    "sg:city":"Palmas De Gran Canaria",
    "sg:orig_category":"Electrodom\u00c9sticos (al Por Menor)",
    "sg:phone":"+34 928 23 43 24",
    "sg:postcode":"35004",
    "sg:province":"Las Palmas",
    "wof:name":"Ortega Monzon Froilan",
    "wof:placetype":"venue"
},
  "geometry": {"coordinates":[-15.4327554703,28.1238460541],"type":"Point"}
}