{
  "type": "Feature",
  "properties": {
    "addr:full":"Carrer de Girona, 206 Granollers Barcelona 08402",
    "addr:housenumber":"206",
    "addr:postcode":"08402",
    "addr:street":"Carrer De Girona",
    "iso:country":"ES",
    "sg:address":"Carrer de Girona, 206",
    "sg:city":"Granollers",
    "sg:orig_category":"Escayola Y Productos De Escayola (fabricaci\u00d3n, Al Por Mayor)",
    "sg:phone":"+34 938 49 93 03",
    "sg:postcode":"08402",
    "sg:province":"Barcelona",
    "wof:name":"Navarro Navarro Jose",
    "wof:placetype":"venue"
},
  "geometry": {"coordinates":[2.2924718857,41.6151390076],"type":"Point"}
}