{
  "type": "Feature",
  "properties": {
    "iso:country":"ES",
    "sg:address":"Urb Agata Iii, S/n",
    "sg:city":"Manga Mar Menor",
    "sg:orig_category":"Inmobiliaria (agencias)",
    "sg:phone":"+34 968 14 12 21",
    "sg:postcode":"30380",
    "sg:province":"Murcia",
    "sg:website":"www.angelalarcon.com",
    "wof:name":"Angel Alarcon Sl",
    "wof:placetype":"venue"
},
  "geometry": {"coordinates":[-1.1298867464,37.9834747314],"type":"Point"}
}