{
  "type": "Feature",
  "properties": {
    "addr:full":"Carr Leonor Servera, 8 Cala Ratjada Islas Baleares 07590",
    "addr:housenumber":"8",
    "addr:postcode":"07590",
    "addr:street":"Carr Leonor Servera",
    "iso:country":"ES",
    "sg:address":"Carr Leonor Servera, 8",
    "sg:city":"Cala Ratjada",
    "sg:orig_category":"Peluquer\u00cdas, Peluquer\u00cda Mixta",
    "sg:phone":"+34 971 81 91 94",
    "sg:postcode":"07590",
    "sg:province":"Islas Baleares",
    "wof:name":"Garau Fullana Francisca",
    "wof:placetype":"venue"
},
  "geometry": {"coordinates":[3.4606449604,39.7145996094],"type":"Point"}
}