{
  "type": "Feature",
  "properties": {
    "addr:full":"Cra Fuente De San Luis, 106 Valencia Valencia 46013",
    "addr:housenumber":"106",
    "addr:postcode":"46013",
    "addr:street":"Fuente;San Luis",
    "iso:country":"ES",
    "sg:address":"Cra Fuente De San Luis, 106",
    "sg:city":"Valencia",
    "sg:orig_category":"Negocio De Materiales De Construcci\u00d3n",
    "sg:phone":"+34 963 33 26 36",
    "sg:postcode":"46013",
    "sg:province":"Valencia",
    "wof:name":"Gramuntell Rocafort Vicente Miguel",
    "wof:placetype":"venue"
},
  "geometry": {"coordinates":[-0.3706899881,39.4514274597],"type":"Point"}
}