{
  "type": "Feature",
  "properties": {
    "iso:country":"ES",
    "sg:address":"Calle de Isaac Albeniz, 16",
    "sg:city":"Parla",
    "sg:orig_category":"Peluqueros: De Se\u00d1oras",
    "sg:phone":"+34 916 99 70 83",
    "sg:postcode":"28980",
    "sg:province":"Madrid",
    "wof:name":"Molina Martinez Isabel",
    "wof:placetype":"venue"
},
  "geometry": {"coordinates":[-3.7741754055,40.2299003601],"type":"Point"}
}