{
  "type": "Feature",
  "properties": {
    "iso:country":"ES",
    "sg:address":"Calle de Francisco Paino, 13",
    "sg:city":"Madrid",
    "sg:orig_category":"Importaci\u00d3n",
    "sg:phone":"+34 914 62 66 22",
    "sg:postcode":"28025",
    "sg:province":"Madrid",
    "wof:name":"Payser Export S.l",
    "wof:placetype":"venue"
},
  "geometry": {"coordinates":[-3.7293169498,40.3821640015],"type":"Point"}
}