{
  "type": "Feature",
  "properties": {
    "addr:full":"Calle de Impresor Monfort, 23 Valencia Valencia 46018",
    "addr:housenumber":"23",
    "addr:postcode":"46018",
    "addr:street":"Calle De Impresor Monfort",
    "iso:country":"ES",
    "sg:address":"Calle de Impresor Monfort, 23",
    "sg:city":"Valencia",
    "sg:orig_category":"Molduras, Junquillos, Listones Y Molduras Perforadas",
    "sg:phone":"+34 963 77 34 21",
    "sg:postcode":"46018",
    "sg:province":"Valencia",
    "wof:name":"Herrero Morote S.l.",
    "wof:placetype":"venue"
},
  "geometry": {"coordinates":[-0.3954629898,39.4627723694],"type":"Point"}
}