{
  "type": "Feature",
  "properties": {
    "iso:country":"ES",
    "sg:address":"Pl Llibertat, 15",
    "sg:city":"Reus",
    "sg:orig_category":"Agencias Y Agentes Comerciales, Representantes",
    "sg:phone":"+34 977 34 11 92",
    "sg:postcode":"43201",
    "sg:province":"Tarragona",
    "wof:name":"Fort Fuguet Javier",
    "wof:placetype":"venue"
},
  "geometry": {"coordinates":[1.1071670055,41.1586456299],"type":"Point"}
}