{
  "type": "Feature",
  "properties": {
    "iso:country":"ES",
    "sg:address":"Carrer de Agricultura, 41",
    "sg:city":"Viladecans",
    "sg:orig_category":"Ropa Para Se\u00d1oras (al Por Menor)",
    "sg:phone":"+34 936 47 21 27",
    "sg:postcode":"08840",
    "sg:province":"Barcelona",
    "sg:website":"www.kloeshop.com",
    "wof:name":"Kloe Shop S.l.",
    "wof:placetype":"venue"
},
  "geometry": {"coordinates":[2.0242450237,41.3040885925],"type":"Point"}
}