{
  "type": "Feature",
  "properties": {
    "addr:full":"Ptge Torrent De L'estadell, 20 Barcelona Barcelona 08030",
    "addr:housenumber":"20",
    "addr:postcode":"08030",
    "addr:street":"Ptge Torrent De L'Estadell",
    "iso:country":"ES",
    "sg:address":"Ptge Torrent De L'estadell, 20",
    "sg:city":"Barcelona",
    "sg:orig_category":"Impresiones Sobre Tela",
    "sg:phone":"+34 933 45 95 26",
    "sg:postcode":"08030",
    "sg:province":"Barcelona",
    "wof:name":"Andreu Torrento Jorge",
    "wof:placetype":"venue"
},
  "geometry": {"coordinates":[2.1967580318,41.4339294434],"type":"Point"}
}