{
  "type": "Feature",
  "properties": {
    "iso:country":"ES",
    "sg:address":"Ctra Murcia, Km. 0053,0",
    "sg:city":"Elche",
    "sg:orig_category":"Zapatos: Material, Suministros, Accesorios (fabricaci\u00d3n, Al Por Mayor)",
    "sg:phone":"+34 966 66 07 08",
    "sg:postcode":"03205",
    "sg:province":"Alicante",
    "sg:website":"www.analco.com",
    "wof:name":"Analco Auxiliar Calzados S.a.",
    "wof:placetype":"venue"
},
  "geometry": {"coordinates":[-0.7339906096,38.2583427429],"type":"Point"}
}