{
  "type": "Feature",
  "properties": {
    "addr:full":"Calle de Navia, 21 Malaga M\u00e1laga 29010",
    "addr:housenumber":"21",
    "addr:postcode":"29010",
    "addr:street":"Calle De Navia;Ma\u0301Laga",
    "iso:country":"ES",
    "sg:address":"Calle de Navia, 21",
    "sg:city":"Malaga",
    "sg:orig_category":"Empresas De Carpinter\u00cda Met\u00c1lica",
    "sg:phone":"+34 952 39 63 49",
    "sg:postcode":"29010",
    "sg:province":"M\u00e1laga",
    "wof:name":"Camacho Y Santana S.l.",
    "wof:placetype":"venue"
},
  "geometry": {"coordinates":[-4.4527988434,36.7325210571],"type":"Point"}
}