{
  "type": "Feature",
  "properties": {
    "addr:full":"Cui\u00f1a, S/n Oza La Coru\u00f1a 15380",
    "addr:postcode":"15380",
    "addr:street":"Cuin\u0303A S / N Oza;Corun\u0303A",
    "iso:country":"ES",
    "sg:address":"Cui\u00f1a, S/n",
    "sg:city":"Oza",
    "sg:orig_category":"Promotores Constructores",
    "sg:phone":"+34 981 79 24 54",
    "sg:postcode":"15380",
    "sg:province":"La Coru\u00f1a",
    "wof:name":"Naveira Vazquez Emiliano",
    "wof:placetype":"venue"
},
  "geometry": {"coordinates":[-8.1878890991,43.2155342102],"type":"Point"}
}