{
  "type": "Feature",
  "properties": {
    "addr:full":"Pol Ind El Peral, 1 Nerva Huelva 21670",
    "addr:housenumber":"1",
    "addr:postcode":"21670",
    "addr:street":"El Peral",
    "iso:country":"ES",
    "sg:address":"Pol Ind El Peral, 1",
    "sg:city":"Nerva",
    "sg:orig_category":"Transportes Por Carretera: Lotes Completos, Mercanc\u00cdas Diversas",
    "sg:phone":"+34 959 58 12 50",
    "sg:postcode":"21670",
    "sg:province":"Huelva",
    "wof:name":"Sertran Olivera S.l.",
    "wof:placetype":"venue"
},
  "geometry": {"coordinates":[-6.5471301079,37.6939048767],"type":"Point"}
}