{
  "type": "Feature",
  "properties": {
    "iso:country":"ES",
    "sg:address":"Calle de Mayor, 17",
    "sg:city":"Belones",
    "sg:orig_category":"\u00d3ptica: Instrumentos (fabricaci\u00d3n)",
    "sg:phone":"+34 968 13 71 92",
    "sg:postcode":"30385",
    "sg:province":"Murcia",
    "wof:name":"Louzan Perez Carolina",
    "wof:placetype":"venue"
},
  "geometry": {"coordinates":[-0.777402997,37.6227264404],"type":"Point"}
}