{
  "type": "Feature",
  "properties": {
    "addr:full":"Acropolis, 3 Murcia Murcia 30007",
    "addr:housenumber":"3",
    "addr:postcode":"30007",
    "addr:street":"Acropolis",
    "iso:country":"ES",
    "sg:address":"Acropolis, 3",
    "sg:city":"Murcia",
    "sg:orig_category":"Asesor\u00cda Sobre Comunicaci\u00d3n De Empresas",
    "sg:phone":"+34 968 20 44 83",
    "sg:postcode":"30007",
    "sg:province":"Murcia",
    "wof:name":"Asociacion Corporativa Regional Acromur S.l.",
    "wof:placetype":"venue"
},
  "geometry": {"coordinates":[-1.1256463528,38.0000572205],"type":"Point"}
}