{
  "type": "Feature",
  "properties": {
    "iso:country":"ES",
    "sg:address":"Carrer de Francesc Alegre, 4",
    "sg:city":"Barcelona",
    "sg:orig_category":"Asilos De Ancianos. Centros Privados",
    "sg:phone":"+34 932 10 01 93",
    "sg:postcode":"08024",
    "sg:province":"Barcelona",
    "wof:name":"Residencia Geriatrica Catalu\u00f1a",
    "wof:placetype":"venue"
},
  "geometry": {"coordinates":[2.166506052,41.4165306091],"type":"Point"}
}