{
  "type": "Feature",
  "properties": {
    "addr:full":"C/ Espanya, 14 Puigcerda Girona 17520",
    "addr:housenumber":"14",
    "addr:postcode":"17520",
    "addr:street":"C / Espanya",
    "iso:country":"ES",
    "sg:address":"C/ Espanya, 14",
    "sg:city":"Puigcerda",
    "sg:orig_category":"Almacenes Para Venta: Muebles Y Varios",
    "sg:phone":"+34 972 14 06 96",
    "sg:postcode":"17520",
    "sg:province":"Girona",
    "wof:name":"Ferrer Arro Albert",
    "wof:placetype":"venue"
},
  "geometry": {"coordinates":[1.9286739826,42.4320411682],"type":"Point"}
}