{
  "type": "Feature",
  "properties": {
    "addr:full":"Carrer de Montserrat, 70 Caldes Montbui Barcelona 08140",
    "addr:housenumber":"70",
    "addr:postcode":"08140",
    "addr:street":"Carrer De Montserrat;Montbui Barcelona",
    "iso:country":"ES",
    "sg:address":"Carrer de Montserrat, 70",
    "sg:city":"Caldes Montbui",
    "sg:orig_category":"Artesan\u00cda",
    "sg:phone":"+34 938 65 05 45",
    "sg:postcode":"08140",
    "sg:province":"Barcelona",
    "wof:name":"Martinez Gilabert Jose",
    "wof:placetype":"venue"
},
  "geometry": {"coordinates":[2.1697239876,41.6319656372],"type":"Point"}
}