{
  "type": "Feature",
  "properties": {
    "addr:full":"Avda Cayetano Del Toro, 21 Cadiz C\u00e1diz 11010",
    "addr:housenumber":"21",
    "addr:postcode":"11010",
    "addr:street":"Avda Cayetano Del Toro",
    "iso:country":"ES",
    "sg:address":"Avda Cayetano Del Toro, 21",
    "sg:city":"Cadiz",
    "sg:orig_category":"M\u00c9dicos: Medicina Interna",
    "sg:phone":"+34 956 25 24 04",
    "sg:postcode":"11010",
    "sg:province":"C\u00e1diz",
    "wof:name":"Zamora Madaria Eduardo",
    "wof:placetype":"venue"
},
  "geometry": {"coordinates":[-6.2765617371,36.5057411194],"type":"Point"}
}