{
  "type": "Feature",
  "properties": {
    "addr:full":"Calle de Ramon Y Cajal, 45 Coru\u00d1a La Coru\u00f1a 15006",
    "addr:housenumber":"45",
    "addr:postcode":"15006",
    "addr:street":"Calle De Ramon Y Cajal;Corun\u0303A",
    "iso:country":"ES",
    "sg:address":"Calle de Ramon Y Cajal, 45",
    "sg:city":"Coru\u00d1a",
    "sg:orig_category":"Gastronom\u00cda: Especialidades Regionales (al Por Menor)",
    "sg:phone":"+34 981 28 20 62",
    "sg:postcode":"15006",
    "sg:province":"La Coru\u00f1a",
    "wof:name":"Linares Sanjurjo Guadalupe",
    "wof:placetype":"venue"
},
  "geometry": {"coordinates":[-8.4021558762,43.3556365967],"type":"Point"}
}