{
  "type": "Feature",
  "properties": {
    "addr:full":"Av Tres-cents U, 31 Castelldefels Barcelona 08860",
    "addr:postcode":"08860",
    "addr:street":"Av Tres-Cents",
    "iso:country":"ES",
    "sg:address":"Av Tres-cents U, 31",
    "sg:city":"Castelldefels",
    "sg:orig_category":"Arreglo E Instalaci\u00d3n De Caf\u00c9s, Hoteles Y Restaurantes",
    "sg:phone":"+34 936 65 02 13",
    "sg:postcode":"08860",
    "sg:province":"Barcelona",
    "wof:name":"Ferrate Representaciones S.l.",
    "wof:placetype":"venue"
},
  "geometry": {"coordinates":[1.9784450531,41.2793083191],"type":"Point"}
}