{
  "type": "Feature",
  "properties": {
    "iso:country":"ES",
    "sg:address":"Rua Real, 30",
    "sg:city":"Ferrol",
    "sg:orig_category":"Electrodom\u00c9sticos (al Por Menor)",
    "sg:phone":"+34 981 32 12 54",
    "sg:postcode":"15402",
    "sg:province":"La Coru\u00f1a",
    "wof:name":"Gonzalez Fernandez Remigio",
    "wof:placetype":"venue"
},
  "geometry": {"coordinates":[-8.2299156189,43.4853935242],"type":"Point"}
}