{
  "type": "Feature",
  "properties": {
    "iso:country":"ES",
    "sg:address":"Avda Joaquin Costa, 14",
    "sg:city":"Badajoz",
    "sg:orig_category":"Alimentaci\u00d3n General (al Por Mayor)",
    "sg:phone":"+34 924 22 35 36",
    "sg:postcode":"06001",
    "sg:province":"Badajoz",
    "wof:name":"Suarez Morales Manuel",
    "wof:placetype":"venue"
},
  "geometry": {"coordinates":[-6.9742841721,38.8809204102],"type":"Point"}
}