{
  "type": "Feature",
  "properties": {
    "addr:full":"Avda General Fanjul, 25 Madrid Madrid 28044",
    "addr:housenumber":"25",
    "addr:postcode":"madrid;28044",
    "addr:street":"Avda General Fanjul",
    "iso:country":"ES",
    "sg:address":"Avda General Fanjul, 25",
    "sg:city":"Madrid",
    "sg:orig_category":"Venta, Instalaci\u00d3n, Reparaci\u00d3n De Antenas Para Televisi\u00d3n",
    "sg:phone":"+34 917 05 54 02",
    "sg:postcode":"28044",
    "sg:province":"Madrid",
    "wof:name":"Via Vision S.l.",
    "wof:placetype":"venue"
},
  "geometry": {"coordinates":[-3.7659749985,40.3839645386],"type":"Point"}
}