{
  "type": "Feature",
  "properties": {
    "addr:full":"Calle de Perez De Castro, 3 Cordoba C\u00f3rdoba 14003",
    "addr:housenumber":"3",
    "addr:postcode":"14003",
    "addr:street":"Calle De Perez De Castro;Co\u0301Rdoba",
    "iso:country":"ES",
    "sg:address":"Calle de Perez De Castro, 3",
    "sg:city":"Cordoba",
    "sg:orig_category":"Ingeniero",
    "sg:phone":"+34 957 20 03 99",
    "sg:postcode":"14003",
    "sg:province":"C\u00f3rdoba",
    "wof:name":"Gil Porras Rafael",
    "wof:placetype":"venue"
},
  "geometry": {"coordinates":[-4.7831969261,37.8833580017],"type":"Point"}
}