{
  "type": "Feature",
  "properties": {
    "iso:country":"ES",
    "sg:address":"Rua Marques De Trives, 35",
    "sg:city":"Pobra Trives",
    "sg:orig_category":"Producci\u00d3n, Distribuci\u00d3n De Gas Butano Y Propano",
    "sg:phone":"+34 988 33 01 80",
    "sg:postcode":"32780",
    "sg:province":"Ourense",
    "wof:name":"Butatrives S.l.",
    "wof:placetype":"venue"
},
  "geometry": {"coordinates":[-7.2539892197,42.3392906189],"type":"Point"}
}