{
  "type": "Feature",
  "properties": {
    "iso:country":"ES",
    "sg:address":"Avda Ricardo Soriano, 13",
    "sg:city":"Marbella",
    "sg:orig_category":"M\u00c9dicos: Endocrinolog\u00cda Y Metabolismo",
    "sg:phone":"+34 952 86 04 47",
    "sg:postcode":"29600",
    "sg:province":"M\u00e1laga",
    "sg:website":"lalmagro@infonegocio.com",
    "wof:name":"Almagro Lopez Luis Fernando",
    "wof:placetype":"venue"
},
  "geometry": {"coordinates":[-4.8884396553,36.509765625],"type":"Point"}
}