{
  "type": "Feature",
  "properties": {
    "addr:full":"Urb. Las Adelfas, 11 San Pedro Alcantara M\u00e1laga 29670",
    "addr:housenumber":"11",
    "addr:postcode":"29670",
    "addr:street":"Urb. Las Adelfas",
    "iso:country":"ES",
    "sg:address":"Urb. Las Adelfas, 11",
    "sg:city":"San Pedro Alcantara",
    "sg:orig_category":"Inmobiliaria (agencias)",
    "sg:phone":"+34 952 78 01 37",
    "sg:postcode":"29670",
    "sg:province":"M\u00e1laga",
    "wof:name":"Yague Diez De Tejada Maria Teresa",
    "wof:placetype":"venue"
},
  "geometry": {"coordinates":[-4.9894766808,36.4856033325],"type":"Point"}
}