{
  "type": "Feature",
  "properties": {
    "addr:full":"Calle de Industrias, 12 Valladolid Valladolid 47005",
    "addr:housenumber":"12",
    "addr:postcode":"47005",
    "addr:street":"Calle De Industrias",
    "iso:country":"ES",
    "sg:address":"Calle de Industrias, 12",
    "sg:city":"Valladolid",
    "sg:orig_category":"Reposter\u00cdas",
    "sg:phone":"+34 983 21 07 69",
    "sg:postcode":"47005",
    "sg:province":"Valladolid",
    "wof:name":"Paz Juez Mario",
    "wof:placetype":"venue"
},
  "geometry": {"coordinates":[-4.7155718803,41.6477890015],"type":"Point"}
}