{
  "type": "Feature",
  "properties": {
    "iso:country":"ES",
    "sg:address":"Av Alfonso Puchades, 24",
    "sg:city":"Benidorm",
    "sg:orig_category":"Quincaller\u00cda (al Por Menor)",
    "sg:phone":"+34 965 86 72 27",
    "sg:postcode":"03500",
    "sg:province":"Alicante",
    "wof:name":"Sheymar Representaciones S.l.",
    "wof:placetype":"venue"
},
  "geometry": {"coordinates":[-0.1246540025,38.5417404175],"type":"Point"}
}