{
  "type": "Feature",
  "properties": {
    "addr:full":"Avda Murcia, 15 Albatera Alicante 03340",
    "addr:housenumber":"15",
    "addr:postcode":"03340",
    "addr:street":"Avda Murcia",
    "iso:country":"ES",
    "sg:address":"Avda Murcia, 15",
    "sg:city":"Albatera",
    "sg:orig_category":"Bordado, Marcado A Medida",
    "sg:phone":"+34 965 48 62 66",
    "sg:postcode":"03340",
    "sg:province":"Alicante",
    "wof:name":"Rocamora Vicente Jose Francisco",
    "wof:placetype":"venue"
},
  "geometry": {"coordinates":[-0.8756350279,38.1766586304],"type":"Point"}
}