{
  "type": "Feature",
  "properties": {
    "iso:country":"ES",
    "sg:address":"Rbla Carme, 1",
    "sg:city":"Vic",
    "sg:orig_category":"Ropa Para Se\u00d1oras Y Caballeros (al Por Menor)",
    "sg:phone":"+34 938 86 36 29",
    "sg:postcode":"08500",
    "sg:province":"Barcelona",
    "wof:name":"Bansell Furriols Joan",
    "wof:placetype":"venue"
},
  "geometry": {"coordinates":[2.2536671162,41.9313316345],"type":"Point"}
}