{
  "type": "Feature",
  "properties": {
    "iso:country":"ES",
    "sg:address":"Calle de Bernardo Del Carpio, 13",
    "sg:city":"Le\u00f3n",
    "sg:orig_category":"Cr\u00cda De Animales",
    "sg:phone":"+34 987 25 01 26",
    "sg:postcode":"24004",
    "sg:province":"Le\u00f3n",
    "wof:name":"Explotaciones Agropecuarias Mu\u00f1iz S.l.",
    "wof:placetype":"venue"
},
  "geometry": {"coordinates":[-5.5759687424,42.5943984985],"type":"Point"}
}