{
  "type": "Feature",
  "properties": {
    "addr:full":"Calle de Arturo Soria, 106 Madrid Madrid 28027",
    "addr:housenumber":"106",
    "addr:postcode":"28027",
    "addr:street":"Calle De Arturo Soria",
    "iso:country":"ES",
    "sg:address":"Calle de Arturo Soria, 106",
    "sg:city":"Madrid",
    "sg:orig_category":"Alumbrados",
    "sg:phone":"+34 914 08 60 12",
    "sg:postcode":"28027",
    "sg:province":"Madrid",
    "wof:name":"Ceproma S.a.",
    "wof:placetype":"venue"
},
  "geometry": {"coordinates":[-3.6480715275,40.4462661743],"type":"Point"}
}