{
  "type": "Feature",
  "properties": {
    "addr:full":"Calle de Emilio Alonso Ferrero, 3 Ba\u00d1eza Le\u00f3n 24750",
    "addr:housenumber":"3",
    "addr:postcode":"24750",
    "addr:street":"Calle De Emilio Alonso Ferrero;Leo\u0301N",
    "iso:country":"ES",
    "sg:address":"Calle de Emilio Alonso Ferrero, 3",
    "sg:city":"Ba\u00d1eza",
    "sg:orig_category":"Molduras, Junquillos, Listones Y Molduras Perforadas",
    "sg:phone":"+34 987 64 38 35",
    "sg:postcode":"24750",
    "sg:province":"Le\u00f3n",
    "wof:name":"Alvarez Vidal Manuel",
    "wof:placetype":"venue"
},
  "geometry": {"coordinates":[-5.8990869522,42.3019828796],"type":"Point"}
}