{
  "type": "Feature",
  "properties": {
    "addr:full":"Calle de Serapio Mugica, 9 Irun Guip\u00f9zcoa 20302",
    "addr:housenumber":"9",
    "addr:postcode":"20302",
    "addr:street":"Calle De Serapio Mugica;Guipu\u0300Zcoa",
    "iso:country":"ES",
    "sg:address":"Calle de Serapio Mugica, 9",
    "sg:city":"Irun",
    "sg:orig_category":"Ropa Para Caballeros (al Por Menor)",
    "sg:phone":"+34 943 61 26 26",
    "sg:postcode":"20302",
    "sg:province":"Guip\u00f9zcoa",
    "wof:name":"Capeletti Moda Hombre S.l.",
    "wof:placetype":"venue"
},
  "geometry": {"coordinates":[-1.7956449986,43.339012146],"type":"Point"}
}