{
  "type": "Feature",
  "properties": {
    "iso:country":"ES",
    "sg:address":"Calle de Juan Maria Coca, 17",
    "sg:city":"Mairena Alcor",
    "sg:orig_category":"Partidos Pol\u00cdticos",
    "sg:phone":"+34 955 74 54 00",
    "sg:postcode":"41510",
    "sg:province":"Sevilla",
    "wof:name":"Partido Andalucista",
    "wof:placetype":"venue"
},
  "geometry": {"coordinates":[-5.7469367981,37.3748054504],"type":"Point"}
}