{
  "type": "Feature",
  "properties": {
    "addr:full":"Calle de San Vicente Martir, 61 Valencia Valencia 46002",
    "addr:housenumber":"61",
    "addr:postcode":"46002",
    "addr:street":"Calle De San Vicente Martir",
    "iso:country":"ES",
    "sg:address":"Calle de San Vicente Martir, 61",
    "sg:city":"Valencia",
    "sg:orig_category":"Flores Y Plantas Naturales (al Por Mayor)",
    "sg:phone":"+34 963 94 41 81",
    "sg:postcode":"46002",
    "sg:province":"Valencia",
    "wof:name":"Martinez Pons Ana",
    "wof:placetype":"venue"
},
  "geometry": {"coordinates":[-0.3786090016,39.4696044922],"type":"Point"}
}