{
  "type": "Feature",
  "properties": {
    "iso:country":"ES",
    "sg:address":"Barr Peruri, 33",
    "sg:city":"Peruri",
    "sg:orig_category":"Bisuter\u00cda, Joyer\u00cda, Relojer\u00cda (al Por Menor)",
    "sg:phone":"+34 944 60 13 09",
    "sg:postcode":"48940",
    "sg:province":"Vizcaya",
    "sg:website":"www.orovivo.es",
    "wof:name":"Geria Joyeros S.l.",
    "wof:placetype":"venue"
},
  "geometry": {"coordinates":[-2.9860789776,43.3275489807],"type":"Point"}
}