{
  "type": "Feature",
  "properties": {
    "iso:country":"ES",
    "sg:address":"Calle de Reina Felicia, 4",
    "sg:city":"Zaragoza",
    "sg:orig_category":"Fabricaci\u00d3n De Ventanas",
    "sg:phone":"+34 976 43 89 65",
    "sg:postcode":"50003",
    "sg:province":"Zaragoza",
    "wof:name":"Puertas Tamar S.l.",
    "wof:placetype":"venue"
},
  "geometry": {"coordinates":[-0.8987566829,41.6604232788],"type":"Point"}
}