{
  "type": "Feature",
  "properties": {
    "iso:country":"ES",
    "sg:address":"Pg Bonanova, 77",
    "sg:city":"Barcelona",
    "sg:orig_category":"Inmobiliaria (agencias)",
    "sg:phone":"+34 934 18 17 66",
    "sg:postcode":"08017",
    "sg:province":"Barcelona",
    "wof:name":"Vila Recolons Ines",
    "wof:placetype":"venue"
},
  "geometry": {"coordinates":[2.126404047,41.4025497437],"type":"Point"}
}