{
  "type": "Feature",
  "properties": {
    "iso:country":"ES",
    "sg:address":"Afores, S/n",
    "sg:city":"Sta. Maria Merles",
    "sg:orig_category":"Alimentaci\u00d3n General (al Por Mayor)",
    "sg:phone":"+34 937 44 13 27",
    "sg:postcode":"08619",
    "sg:province":"Barcelona",
    "wof:name":"Grup Baucells Alimentacio S.a.",
    "wof:placetype":"venue"
},
  "geometry": {"coordinates":[1.9732600451,42.155418396],"type":"Point"}
}