{
  "type": "Feature",
  "properties": {
    "iso:country":"ES",
    "sg:address":"Ctra. Huelva, Km. 0700,0",
    "sg:city":"Ayamonte",
    "sg:orig_category":"Estudios Y Construcci\u00d3n De Acuarios Y Viveros",
    "sg:phone":"+34 959 50 20 92",
    "sg:postcode":"21400",
    "sg:province":"Huelva",
    "wof:name":"Acuicultores Del Sur S.c.a.",
    "wof:placetype":"venue"
},
  "geometry": {"coordinates":[-7.4042100906,37.2141723633],"type":"Point"}
}