{
  "type": "Feature",
  "properties": {
    "iso:country":"ES",
    "sg:address":"Carrer de Mar, 1",
    "sg:city":"Pego",
    "sg:orig_category":"Supermercados Y Hipermercados",
    "sg:phone":"+34 966 40 20 08",
    "sg:postcode":"03780",
    "sg:province":"Alicante",
    "sg:website":"www.aldi.es",
    "wof:name":"Aldi Supermercados S.l.",
    "wof:placetype":"venue"
},
  "geometry": {"coordinates":[-0.1170165986,38.8396568298],"type":"Point"}
}