{
  "type": "Feature",
  "properties": {
    "addr:full":"Carrer de Jaume Gras, 34 S. Feliu Guixols Girona 17220",
    "addr:housenumber":"34",
    "addr:postcode":"17220",
    "addr:street":"Carrer De Jaume Gras;S. Feliu Guixols",
    "iso:country":"ES",
    "sg:address":"Carrer de Jaume Gras, 34",
    "sg:city":"S. Feliu Guixols",
    "sg:orig_category":"Empresas De Pintura Y Revestimientos",
    "sg:phone":"+34 972 32 15 57",
    "sg:postcode":"17220",
    "sg:province":"Girona",
    "wof:name":"Pereferrer Mantes Jose",
    "wof:placetype":"venue"
},
  "geometry": {"coordinates":[3.0244851112,41.787651062],"type":"Point"}
}