{
  "type": "Feature",
  "properties": {
    "addr:full":"Avda Nocedo, 11 Le\u00f3n Le\u00f3n 24007",
    "addr:housenumber":"11",
    "addr:postcode":"24007",
    "addr:street":"Avda Nocedo;Leo\u0301N",
    "iso:country":"ES",
    "sg:address":"Avda Nocedo, 11",
    "sg:city":"Le\u00f3n",
    "sg:orig_category":"Peluquer\u00cdas, Peluquer\u00cda Mixta",
    "sg:phone":"+34 987 22 85 65",
    "sg:postcode":"24007",
    "sg:province":"Le\u00f3n",
    "wof:name":"Fernandez Tocino Sonia",
    "wof:placetype":"venue"
},
  "geometry": {"coordinates":[-5.5690751076,42.604221344],"type":"Point"}
}