{
  "type": "Feature",
  "properties": {
    "addr:full":"Paulino Caballero, 28 Iru\u00f1a Navarra 31003",
    "addr:housenumber":"28",
    "addr:postcode":"31003",
    "addr:street":"Caballero",
    "iso:country":"ES",
    "sg:address":"Paulino Caballero, 28",
    "sg:city":"Iru\u00f1a",
    "sg:orig_category":"Art\u00cdculos De Aluminio",
    "sg:phone":"+34 948 24 16 62",
    "sg:postcode":"31003",
    "sg:province":"Navarra",
    "wof:name":"Comercial Asan S. A.",
    "wof:placetype":"venue"
},
  "geometry": {"coordinates":[-1.638332963,42.8108863831],"type":"Point"}
}