{
  "type": "Feature",
  "properties": {
    "addr:full":"Calle de Legion (la), 5 Ceuta Ceuta 51001",
    "addr:housenumber":"5",
    "addr:postcode":"51001",
    "addr:street":"Calle De Legion La",
    "iso:country":"ES",
    "sg:address":"Calle de Legion (la), 5",
    "sg:city":"Ceuta",
    "sg:orig_category":"Abogados",
    "sg:phone":"+34 956 51 16 56",
    "sg:postcode":"51001",
    "sg:province":"Ceuta",
    "wof:name":"Arjandas Daryanani Dilip",
    "wof:placetype":"venue"
},
  "geometry": {"coordinates":[-5.3073334694,35.8888397217],"type":"Point"}
}