{
  "type": "Feature",
  "properties": {
    "iso:country":"ES",
    "sg:address":"Calle de Constitucion (de La), 50",
    "sg:city":"Navalcarnero",
    "sg:orig_category":"Asesor\u00cda Fiscal Y Jur\u00cddica",
    "sg:phone":"+34 918 11 10 88",
    "sg:postcode":"28600",
    "sg:province":"Madrid",
    "wof:name":"Alysco S.l.",
    "wof:placetype":"venue"
},
  "geometry": {"coordinates":[-4.0118327141,40.2871360779],"type":"Point"}
}