{
  "type": "Feature",
  "properties": {
    "addr:full":"Cmno San Andres, 27 Arroniz Navarra 31243",
    "addr:housenumber":"27",
    "addr:postcode":"31243",
    "addr:street":"Cmno San Andres",
    "iso:country":"ES",
    "sg:address":"Cmno San Andres, 27",
    "sg:city":"Arroniz",
    "sg:orig_category":"Producci\u00d3n, Comercio De Cereales",
    "sg:phone":"+34 948 53 73 16",
    "sg:postcode":"31243",
    "sg:province":"Navarra",
    "wof:name":"Sociedad Cooperativa Lda Cerealista San Isidro",
    "wof:placetype":"venue"
},
  "geometry": {"coordinates":[-2.0907959938,42.5851974487],"type":"Point"}
}