{
  "type": "Feature",
  "properties": {
    "addr:full":"Calle de Arrabal, S/n Almunia De Do\u00e7a Godina Zaragoza 50100",
    "addr:housenumber":"s / n",
    "addr:postcode":"50100",
    "addr:street":"Calle De Arrabal",
    "iso:country":"ES",
    "sg:address":"Calle de Arrabal, S/n",
    "sg:city":"Almunia De Do\u00e7a Godina",
    "sg:orig_category":"Transporte En General",
    "sg:phone":"+34 976 60 12 13",
    "sg:postcode":"50100",
    "sg:province":"Zaragoza",
    "wof:name":"Distribuciones Udamer Sl",
    "wof:placetype":"venue"
},
  "geometry": {"coordinates":[-0.8765661716,41.6563491821],"type":"Point"}
}