{
  "type": "Feature",
  "properties": {
    "addr:full":"Calle de Alava, 2 Llodio \u00c1lava 01400",
    "addr:housenumber":"2",
    "addr:postcode":"01400",
    "addr:street":"Calle De Alava",
    "iso:country":"ES",
    "sg:address":"Calle de Alava, 2",
    "sg:city":"Llodio",
    "sg:orig_category":"Sociedades, Compa\u00d1\u00cdas Aseguradoras",
    "sg:phone":"+34 946 72 27 15",
    "sg:postcode":"01400",
    "sg:province":"\u00c1lava",
    "wof:name":"Bilbao Compa\u00f1ia Anonima De Seguros",
    "wof:placetype":"venue"
},
  "geometry": {"coordinates":[-2.9675571918,43.1460380554],"type":"Point"}
}