{
  "type": "Feature",
  "properties": {
    "addr:full":"Calle de Casimiro Sainz, 2 Reinosa Cantabria 39200",
    "addr:housenumber":"2",
    "addr:postcode":"39200",
    "addr:street":"Calle De Casimiro Sainz",
    "iso:country":"ES",
    "sg:address":"Calle de Casimiro Sainz, 2",
    "sg:city":"Reinosa",
    "sg:orig_category":"Loter\u00cda Y T\u00d3mbola",
    "sg:phone":"+34 942 75 43 89",
    "sg:postcode":"39200",
    "sg:province":"Cantabria",
    "wof:name":"Martin Seco Raquel",
    "wof:placetype":"venue"
},
  "geometry": {"coordinates":[-4.1399540901,42.9964370728],"type":"Point"}
}