{
  "type": "Feature",
  "properties": {
    "iso:country":"ES",
    "sg:address":"Calle de Juan De La Cierva, S/n",
    "sg:city":"Estacion",
    "sg:classifiers":[
        {
            "category":"Autos & Motor Vehicles",
            "subcategory":"Automobile Sales",
            "type":"Retail Goods"
        }
    ],
    "sg:phone":"+34 952 42 00 58",
    "sg:postcode":"29580",
    "sg:province":"M\u00e1laga",
    "wof:name":"Autoescuela Cartama S.l.",
    "wof:placetype":"venue"
},
  "geometry": {"coordinates":[-4.6131711006,36.7330322266],"type":"Point"}
}