{
  "type": "Feature",
  "properties": {
    "iso:country":"ES",
    "sg:address":"Alam Areilza Doctor, 10",
    "sg:city":"Bilbao",
    "sg:orig_category":"Dise\u00d1o Industrial",
    "sg:phone":"+34 944 27 69 07",
    "sg:postcode":"48011",
    "sg:province":"Vizcaya",
    "wof:name":"Lopez Martinez Mercedes",
    "wof:placetype":"venue"
},
  "geometry": {"coordinates":[-2.9418449402,43.2631530762],"type":"Point"}
}