{
  "type": "Feature",
  "properties": {
    "addr:full":"Calle de Velazquez, 21 Le\u00f3n Le\u00f3n 24004",
    "addr:housenumber":"21",
    "addr:postcode":"24004",
    "addr:street":"Calle De Velazquez;Leo\u0301N",
    "iso:country":"ES",
    "sg:address":"Calle de Velazquez, 21",
    "sg:city":"Le\u00f3n",
    "sg:orig_category":"Molduras, Junquillos, Listones Y Molduras Perforadas",
    "sg:phone":"+34 987 21 30 55",
    "sg:postcode":"24004",
    "sg:province":"Le\u00f3n",
    "wof:name":"Calzado Marcos Mariano",
    "wof:placetype":"venue"
},
  "geometry": {"coordinates":[-5.5658321381,42.5903778076],"type":"Point"}
}