{
  "type": "Feature",
  "properties": {
    "addr:full":"Calle de San Bernardo, 4 Alcala Henares Madrid 28801",
    "addr:housenumber":"4",
    "addr:postcode":"28801",
    "addr:street":"Calle De San Bernardo",
    "iso:country":"ES",
    "sg:address":"Calle de San Bernardo, 4",
    "sg:city":"Alcala Henares",
    "sg:orig_category":"Asociaciones Y Clubs Deportivos",
    "sg:phone":"+34 918 80 86 47",
    "sg:postcode":"28801",
    "sg:province":"Madrid",
    "wof:name":"Casta\u00f1o De Miguel Maria Yolanda",
    "wof:placetype":"venue"
},
  "geometry": {"coordinates":[-3.3692750931,40.4831352234],"type":"Point"}
}