{
  "type": "Feature",
  "properties": {
    "iso:country":"ES",
    "sg:address":"Calle de Zeppelin, S/n",
    "sg:city":"Poligono El Montalvo",
    "sg:orig_category":"Dorados, Plater\u00cda (orfebrer\u00cda)",
    "sg:phone":"+34 923 19 03 01",
    "sg:postcode":"37188",
    "sg:province":"Salamanca",
    "wof:name":"Whiterman S. L.",
    "wof:placetype":"venue"
},
  "geometry": {"coordinates":[-5.6511440277,40.934211731],"type":"Point"}
}