{
  "type": "Feature",
  "properties": {
    "iso:country":"ES",
    "sg:address":"Calle de Sahagun, 10",
    "sg:city":"Alcorcon",
    "sg:orig_category":"Agencias Y Asesores De Publicidad",
    "sg:phone":"+34 916 10 75 54",
    "sg:postcode":"28925",
    "sg:province":"Madrid",
    "wof:name":"Homocom Comunicacion Visual S.l",
    "wof:placetype":"venue"
},
  "geometry": {"coordinates":[-3.820898056,40.3543663025],"type":"Point"}
}