{
  "type": "Feature",
  "properties": {
    "iso:country":"ES",
    "sg:address":"Plaz Nuestra Se\u00d1ora De Loreto, 6",
    "sg:city":"Madrid",
    "sg:orig_category":"Bazares, Art\u00cdculos De Limpieza Y De Cocina (al Por Menor)",
    "sg:phone":"+34 917 47 68 33",
    "sg:postcode":"28042",
    "sg:province":"Madrid",
    "wof:name":"Monescillo Moya Consuelo",
    "wof:placetype":"venue"
},
  "geometry": {"coordinates":[-3.5787711143,40.4713630676],"type":"Point"}
}