{
  "type": "Feature",
  "properties": {
    "addr:full":"Rua Inferni\u00d1o, 26 Ferrol La Coru\u00f1a 15404",
    "addr:housenumber":"26",
    "addr:postcode":"15404",
    "addr:street":"Rua Infernin\u0303O;La Corun\u0303A",
    "iso:country":"ES",
    "sg:address":"Rua Inferni\u00d1o, 26",
    "sg:city":"Ferrol",
    "sg:orig_category":"Deportes Diversos",
    "sg:phone":"+34 981 37 28 36",
    "sg:postcode":"15404",
    "sg:province":"La Coru\u00f1a",
    "wof:name":"Club Valdetires S.l.",
    "wof:placetype":"venue"
},
  "geometry": {"coordinates":[-8.2218456268,43.490852356],"type":"Point"}
}