{
  "type": "Feature",
  "properties": {
    "iso:country":"ES",
    "sg:address":"Calle de San Cristobal, 30",
    "sg:city":"Ubeda",
    "sg:orig_category":"Partidos Pol\u00cdticos",
    "sg:phone":"+34 953 75 62 02",
    "sg:postcode":"23400",
    "sg:province":"Ja\u00e9n",
    "wof:name":"Partido Socialista Obrero Espa\u00f1ol",
    "wof:placetype":"venue"
},
  "geometry": {"coordinates":[-3.376732111,38.0095024109],"type":"Point"}
}