{
  "type": "Feature",
  "properties": {
    "addr:full":"Avda Jose Leon De Carranza, S/n Jerez De La Frontera C\u00e1diz 11407",
    "addr:postcode":"11407",
    "addr:street":"Avda Jose Leon De Carranza S / N",
    "iso:country":"ES",
    "sg:address":"Avda Jose Leon De Carranza, S/n",
    "sg:city":"Jerez De La Frontera",
    "sg:orig_category":"M\u00c9dicos: Alergolog\u00cda",
    "sg:phone":"+34 956 30 51 16",
    "sg:postcode":"11407",
    "sg:province":"C\u00e1diz",
    "wof:name":"Pi\u00f1a Sanchez Jose Antonio",
    "wof:placetype":"venue"
},
  "geometry": {"coordinates":[-6.135781765,36.7017097473],"type":"Point"}
}