{
  "type": "Feature",
  "properties": {
    "addr:full":"Plaz Espa\u00d1a (de), S/n Almeria Almer\u00eda 04007",
    "addr:housenumber":"s / n",
    "addr:postcode":"04007",
    "addr:street":"Plaz",
    "iso:country":"ES",
    "sg:address":"Plaz Espa\u00d1a (de), S/n",
    "sg:city":"Almeria",
    "sg:orig_category":"Iglesia Cat\u00d3lica",
    "sg:phone":"+34 950 24 02 58",
    "sg:postcode":"04007",
    "sg:province":"Almer\u00eda",
    "wof:name":"Parroquia De San Antonio",
    "wof:placetype":"venue"
},
  "geometry": {"coordinates":[-2.4546089172,36.8320083618],"type":"Point"}
}