{
  "type": "Feature",
  "properties": {
    "addr:full":"Calle de Asensio Neila, 5 Hervas C\u00e1ceres 10700",
    "addr:housenumber":"5",
    "addr:postcode":"10700",
    "addr:street":"Calle De Asensio Neila;Ca\u0301Ceres",
    "iso:country":"ES",
    "sg:address":"Calle de Asensio Neila, 5",
    "sg:city":"Hervas",
    "sg:orig_category":"Museos",
    "sg:phone":"+34 927 48 16 55",
    "sg:postcode":"10700",
    "sg:province":"C\u00e1ceres",
    "wof:name":"Consorcio Museo Perez Comendador-leroux",
    "wof:placetype":"venue"
},
  "geometry": {"coordinates":[-5.859621048,40.2740020752],"type":"Point"}
}