{
  "type": "Feature",
  "properties": {
    "iso:country":"ES",
    "sg:address":"Carr Ciutadans, 19",
    "sg:city":"Girona",
    "sg:orig_category":"Asociaciones, Organismos Culturales Y Socioeducativos",
    "sg:phone":"+34 972 20 98 36",
    "sg:postcode":"17004",
    "sg:province":"Girona",
    "sg:website":"www.fundaciocaixadegirona.org",
    "wof:name":"Fundacio Caixa De Girona",
    "wof:placetype":"venue"
},
  "geometry": {"coordinates":[2.8255059719,41.9845161438],"type":"Point"}
}