{
  "type": "Feature",
  "properties": {
    "iso:country":"ES",
    "sg:address":"Calle de Isaac Peral, 24",
    "sg:city":"Puente-genil",
    "sg:orig_category":"Carnicer\u00cdas, Carnicer\u00cdas",
    "sg:phone":"+34 957 60 65 99",
    "sg:postcode":"14500",
    "sg:province":"C\u00f3rdoba",
    "wof:name":"Carniceria Rivero S.l.",
    "wof:placetype":"venue"
},
  "geometry": {"coordinates":[-4.7624988556,37.3897399902],"type":"Point"}
}