{
  "type": "Feature",
  "properties": {
    "addr:full":"Calle de Alcala, 583 Madrid Madrid 28022",
    "addr:housenumber":"583",
    "addr:postcode":"28022",
    "addr:street":"Calle De Alcala",
    "iso:country":"ES",
    "sg:address":"Calle de Alcala, 583",
    "sg:city":"Madrid",
    "sg:orig_category":"Quincaller\u00cda (al Por Menor)",
    "sg:phone":"+34 917 42 11 53",
    "sg:postcode":"28022",
    "sg:province":"Madrid",
    "wof:name":"Ferreteria Tomas Davila C.b.",
    "wof:placetype":"venue"
},
  "geometry": {"coordinates":[-3.6145629883,40.445186615],"type":"Point"}
}