{
  "type": "Feature",
  "properties": {
    "addr:full":"C. A. Campoo, S/n Basconcillos Tozo Burgos 09126",
    "addr:housenumber":"s / n",
    "addr:postcode":"09126",
    "iso:country":"ES",
    "sg:address":"C. A. Campoo, S/n",
    "sg:city":"Basconcillos Tozo",
    "sg:orig_category":"Material Y Herramientas Agr\u00cdcolas",
    "sg:phone":"+34 947 15 62 11",
    "sg:postcode":"09126",
    "sg:province":"Burgos",
    "wof:name":"Perez Martinez De Luna Maria Eugenia",
    "wof:placetype":"venue"
},
  "geometry": {"coordinates":[-3.9880330563,42.7012939453],"type":"Point"}
}