{
  "type": "Feature",
  "properties": {
    "addr:full":"Calle de Jazmin, 64 Madrid Madrid 28033",
    "addr:housenumber":"64",
    "addr:postcode":"madrid;28033",
    "addr:street":"Calle De Jazmin",
    "iso:country":"ES",
    "sg:address":"Calle de Jazmin, 64",
    "sg:city":"Madrid",
    "sg:orig_category":"Fotograf\u00cda Y Cine: Aparatos, Pel\u00cdculas Y Accesorios (al Por Menor)",
    "sg:phone":"+34 917 67 08 83",
    "sg:postcode":"28033",
    "sg:province":"Madrid",
    "sg:website":"www.alcicam.net",
    "wof:name":"Alcicam S.a.",
    "wof:placetype":"venue"
},
  "geometry": {"coordinates":[-3.6635713577,40.481842041],"type":"Point"}
}