{
  "type": "Feature",
  "properties": {
    "iso:country":"ES",
    "sg:address":"Carr Joana Roca, De Na, 121",
    "sg:city":"Son Servera",
    "sg:orig_category":"Suministros Para Hoteles",
    "sg:phone":"+34 971 56 73 21",
    "sg:postcode":"07550",
    "sg:province":"Islas Baleares",
    "wof:name":"Murillo Delgado Manuel Julio",
    "wof:placetype":"venue"
},
  "geometry": {"coordinates":[3.3635981083,39.6187057495],"type":"Point"}
}