{
  "type": "Feature",
  "properties": {
    "iso:country":"ES",
    "sg:address":"Carrer de L'abadessa Olzet, S/n",
    "sg:city":"Barcelona",
    "sg:orig_category":"Electrodom\u00c9sticos (al Por Menor)",
    "sg:phone":"+34 932 52 13 20",
    "sg:postcode":"08034",
    "sg:province":"Barcelona",
    "wof:name":"Aeg Aa Asistencia Tecnica Averias Servicio Tecnico Y Reparaciones C.b.",
    "wof:placetype":"venue"
},
  "geometry": {"coordinates":[2.1110618114,41.3931083679],"type":"Point"}
}