{
  "type": "Feature",
  "properties": {
    "iso:country":"ES",
    "sg:address":"Via Aurelia, 5",
    "sg:city":"Sabadell",
    "sg:orig_category":"Estancos",
    "sg:phone":"+34 937 17 27 05",
    "sg:postcode":"08206",
    "sg:province":"Barcelona",
    "wof:name":"Fructuoso Martinez Andres",
    "wof:placetype":"venue"
},
  "geometry": {"coordinates":[2.0947909355,41.5557746887],"type":"Point"}
}