{
  "type": "Feature",
  "properties": {
    "iso:country":"ES",
    "sg:address":"Calle de Limon Verde, 1",
    "sg:city":"Algete",
    "sg:orig_category":"Farmacias",
    "sg:phone":"+34 916 29 03 67",
    "sg:postcode":"28110",
    "sg:province":"Madrid",
    "wof:name":"Perez Mendez-castrillon Paloma",
    "wof:placetype":"venue"
},
  "geometry": {"coordinates":[-3.4988956451,40.596622467],"type":"Point"}
}