{
  "type": "Feature",
  "properties": {
    "addr:full":"C/ Alacant, 1 Alcoi Alicante 03801",
    "addr:housenumber":"1",
    "addr:postcode":"03801",
    "addr:street":"C / Alacant",
    "iso:country":"ES",
    "sg:address":"C/ Alacant, 1",
    "sg:city":"Alcoi",
    "sg:orig_category":"Distribuci\u00d3n De Petr\u00d3leo Y Derivados",
    "sg:phone":"+34 965 54 21 11",
    "sg:postcode":"03801",
    "sg:province":"Alicante",
    "wof:name":"Galpgest Petrogal Estaciones De Servicio S.l.u.",
    "wof:placetype":"venue"
},
  "geometry": {"coordinates":[-0.4782389998,38.6952209473],"type":"Point"}
}