{
  "type": "Feature",
  "properties": {
    "addr:full":"Urb Punta Prima, 3 Punta Prima Alicante 03189",
    "addr:housenumber":"3",
    "addr:postcode":"03189",
    "addr:street":"Urb Punta Prima",
    "iso:country":"ES",
    "sg:address":"Urb Punta Prima, 3",
    "sg:city":"Punta Prima",
    "sg:orig_category":"Inmobiliaria (agencias)",
    "sg:phone":"+34 965 32 95 88",
    "sg:postcode":"03189",
    "sg:province":"Alicante",
    "wof:name":"Clemente Nu\u00d1ez Maria Angeles",
    "wof:placetype":"venue"
},
  "geometry": {"coordinates":[-0.7374460101,37.948802948],"type":"Point"}
}