{
  "type": "Feature",
  "properties": {
    "iso:country":"ES",
    "sg:address":"Calle de Fray Martin De Murua, 41",
    "sg:city":"Gernika-lumo",
    "sg:orig_category":"Plomeros",
    "sg:phone":"+34 946 25 58 84",
    "sg:postcode":"48300",
    "sg:province":"Vizcaya",
    "wof:name":"Antonio Frece\u00f1o Romero",
    "wof:placetype":"venue"
},
  "geometry": {"coordinates":[-2.6842348576,43.3104095459],"type":"Point"}
}