{
  "type": "Feature",
  "properties": {
    "addr:full":"Calle de Gran Via, 62 Madrid Madrid 28013",
    "addr:housenumber":"62",
    "addr:postcode":"madrid;28013",
    "addr:street":"Calle De Gran Via",
    "iso:country":"ES",
    "sg:address":"Calle de Gran Via, 62",
    "sg:city":"Madrid",
    "sg:orig_category":"Bisuter\u00cda, Joyer\u00cda, Relojer\u00cda (al Por Menor)",
    "sg:phone":"+34 915 32 07 55",
    "sg:postcode":"28013",
    "sg:province":"Madrid",
    "wof:name":"Galan Alguacil Ramiro",
    "wof:placetype":"venue"
},
  "geometry": {"coordinates":[-3.7086009979,40.4219436646],"type":"Point"}
}