{
  "type": "Feature",
  "properties": {
    "iso:country":"ES",
    "sg:address":"Ctra Cuevas Del Aguila, S/n",
    "sg:city":"Ramacasta\u00d1as",
    "sg:orig_category":"Molduras, Junquillos, Listones Y Molduras Perforadas",
    "sg:phone":"+34 920 37 19 80",
    "sg:postcode":"05418",
    "sg:province":"\u00c1vila",
    "wof:name":"Marpel C.b.",
    "wof:placetype":"venue"
},
  "geometry": {"coordinates":[-5.0474801064,40.1845092773],"type":"Point"}
}