{
  "type": "Feature",
  "properties": {
    "addr:full":"Calle de Nuestra Se\u00d1ora De Los Volcanes, 3 Arrecife Las Palmas 35500",
    "addr:housenumber":"3",
    "addr:postcode":"35500",
    "addr:street":"Calle De Nuestra Sen\u0303Ora De Los Volcanes",
    "iso:country":"ES",
    "sg:address":"Calle de Nuestra Se\u00d1ora De Los Volcanes, 3",
    "sg:city":"Arrecife",
    "sg:orig_category":"Seguridad En El Trabajo Y Prevenci\u00d3n De Riesgos Laborales",
    "sg:phone":"+34 928 81 77 72",
    "sg:postcode":"35500",
    "sg:province":"Las Palmas",
    "sg:website":"www.mgo.es",
    "wof:name":"Grupo Mgo S.a.",
    "wof:placetype":"venue"
},
  "geometry": {"coordinates":[-13.5509471893,28.9637489319],"type":"Point"}
}