{
  "type": "Feature",
  "properties": {
    "addr:full":"Av Loygorri, 45 Oliva Valencia 46780",
    "addr:housenumber":"45",
    "addr:postcode":"46780",
    "addr:street":"Av Loygorri",
    "iso:country":"ES",
    "sg:address":"Av Loygorri, 45",
    "sg:city":"Oliva",
    "sg:orig_category":"Molduras, Junquillos, Listones Y Molduras Perforadas",
    "sg:phone":"+34 962 85 16 68",
    "sg:postcode":"46780",
    "sg:province":"Valencia",
    "wof:name":"Beneyto Garcia Gabriel",
    "wof:placetype":"venue"
},
  "geometry": {"coordinates":[-0.1161290035,38.9197998047],"type":"Point"}
}