{
  "type": "Feature",
  "properties": {
    "iso:country":"ES",
    "sg:address":"Avda Montecillo, 26",
    "sg:city":"Aranda Duero",
    "sg:orig_category":"Art\u00cdculos De Limpieza Y De Cocina (fabricaci\u00d3n, Al Por Mayor)",
    "sg:phone":"+34 947 50 05 38",
    "sg:postcode":"09400",
    "sg:province":"Burgos",
    "wof:name":"Productos Quimicos Del Duero S.a.l.",
    "wof:placetype":"venue"
},
  "geometry": {"coordinates":[-3.7049489021,41.6720809937],"type":"Point"}
}