{
  "type": "Feature",
  "properties": {
    "iso:country":"ES",
    "sg:address":"Calle de Colmenarico, S/n",
    "sg:city":"San Mateo",
    "sg:orig_category":"Arquitectos",
    "sg:phone":"+34 968 40 60 20",
    "sg:postcode":"30800",
    "sg:province":"Murcia",
    "wof:name":"Bayonas Vicente Alfonso",
    "wof:placetype":"venue"
},
  "geometry": {"coordinates":[-1.6905640364,37.680557251],"type":"Point"}
}