{
  "type": "Feature",
  "properties": {
    "iso:country":"ES",
    "sg:address":"Calle de Cister, 15",
    "sg:city":"Malaga",
    "sg:orig_category":"Art\u00cdculos De Decoraci\u00d3n",
    "sg:phone":"+34 952 22 03 38",
    "sg:postcode":"29015",
    "sg:province":"M\u00e1laga",
    "sg:website":"www.artevilla.es",
    "wof:name":"Arte Villa S.l.",
    "wof:placetype":"venue"
},
  "geometry": {"coordinates":[-4.4176845551,36.7204360962],"type":"Point"}
}