{
  "type": "Feature",
  "properties": {
    "iso:country":"ES",
    "sg:address":"Luga Bolonia, 41",
    "sg:city":"Bolonia",
    "sg:orig_category":"Alquiler De Apartamentos",
    "sg:phone":"+34 956 68 85 24",
    "sg:postcode":"11391",
    "sg:province":"C\u00e1diz",
    "wof:name":"Silva Roman Mateo",
    "wof:placetype":"venue"
},
  "geometry": {"coordinates":[-5.7029819489,36.1468696594],"type":"Point"}
}