{
  "type": "Feature",
  "properties": {
    "iso:country":"ES",
    "sg:address":"Avda Rosalia Castro, 54",
    "sg:city":"Milladoiro",
    "sg:orig_category":"Peluqueros: De Se\u00d1oras",
    "sg:phone":"+34 981 53 51 18",
    "sg:postcode":"15895",
    "sg:province":"La Coru\u00f1a",
    "wof:name":"Arufe Fernandez Constantino",
    "wof:placetype":"venue"
},
  "geometry": {"coordinates":[-8.5780124664,42.8428649902],"type":"Point"}
}