{
  "type": "Feature",
  "properties": {
    "addr:full":"Carrer de Torreta, 21 S. Pere Ribes Barcelona 08810",
    "addr:housenumber":"21",
    "addr:postcode":"08810",
    "addr:street":"Carrer De Torreta;S. Pere Ribes Barcelona",
    "iso:country":"ES",
    "sg:address":"Carrer de Torreta, 21",
    "sg:city":"S. Pere Ribes",
    "sg:orig_category":"Institutos De Belleza",
    "sg:phone":"+34 938 96 04 81",
    "sg:postcode":"08810",
    "sg:province":"Barcelona",
    "wof:name":"Finestres Ganduxe S.l.",
    "wof:placetype":"venue"
},
  "geometry": {"coordinates":[1.7757689953,41.2604026794],"type":"Point"}
}