{
  "type": "Feature",
  "properties": {
    "iso:country":"ES",
    "sg:address":"Calle de Cabo De Tortosa, 4",
    "sg:city":"Arganda",
    "sg:orig_category":"Empresas De Pintura Y Revestimientos",
    "sg:phone":"+34 918 72 01 61",
    "sg:postcode":"28500",
    "sg:province":"Madrid",
    "wof:name":"Lopez Latur S.l.",
    "wof:placetype":"venue"
},
  "geometry": {"coordinates":[-3.4741175175,40.3134460449],"type":"Point"}
}