{
  "type": "Feature",
  "properties": {
    "addr:full":"Calle de Eufemiano Fuentes Cabrera, 15 Palmas De Gran Canaria Las Palmas 35014",
    "addr:postcode":"35014",
    "addr:street":"Calle De Eufemiano Fuentes Cabrera 15",
    "iso:country":"ES",
    "sg:address":"Calle de Eufemiano Fuentes Cabrera, 15",
    "sg:city":"Palmas De Gran Canaria",
    "sg:orig_category":"Fabricaci\u00d3n De Ventanas",
    "sg:phone":"+34 928 42 08 21",
    "sg:postcode":"35014",
    "sg:province":"Las Palmas",
    "wof:name":"Manufacturas Canarias De La Madera S.l.",
    "wof:placetype":"venue"
},
  "geometry": {"coordinates":[-15.43891716,28.0989646912],"type":"Point"}
}