{
  "type": "Feature",
  "properties": {
    "addr:full":"Calle de Wenceslao Fdez.florez, 15 Alacant Alicante 03005",
    "addr:housenumber":"15",
    "addr:postcode":"03005",
    "addr:street":"Calle De Wenceslao Fdez.Florez",
    "iso:country":"ES",
    "sg:address":"Calle de Wenceslao Fdez.florez, 15",
    "sg:city":"Alacant",
    "sg:orig_category":"Peluqueros: De Se\u00d1oras",
    "sg:phone":"+34 965 12 61 88",
    "sg:postcode":"03005",
    "sg:province":"Alicante",
    "wof:name":"Moya Villanueva Maria Magdalena",
    "wof:placetype":"venue"
},
  "geometry": {"coordinates":[-0.49534899,38.3505096436],"type":"Point"}
}