{
  "type": "Feature",
  "properties": {
    "addr:full":"Nueva, S/n Caude Teruel 44396",
    "addr:postcode":"44396",
    "addr:street":"Nueva S / N",
    "iso:country":"ES",
    "sg:address":"Nueva, S/n",
    "sg:city":"Caude",
    "sg:orig_category":"Agricultores, Agricultores",
    "sg:phone":"+34 978 65 10 75",
    "sg:postcode":"44396",
    "sg:province":"Teruel",
    "wof:name":"Alvimar S.c.l.",
    "wof:placetype":"venue"
},
  "geometry": {"coordinates":[-1.1923433542,40.4087944031],"type":"Point"}
}