{
  "type": "Feature",
  "properties": {
    "addr:full":"Carrer de L'aliga, 27 Barcelona Barcelona 08014",
    "addr:housenumber":"27",
    "addr:postcode":"08014",
    "addr:street":"Carrer De L'Aliga",
    "iso:country":"ES",
    "sg:address":"Carrer de L'aliga, 27",
    "sg:city":"Barcelona",
    "sg:orig_category":"Charcuter\u00cdas (al Por Mayor)",
    "sg:phone":"+34 934 21 84 27",
    "sg:postcode":"08014",
    "sg:province":"Barcelona",
    "wof:name":"Elaborados Carnicos S.a.",
    "wof:placetype":"venue"
},
  "geometry": {"coordinates":[2.143345356,41.3741340637],"type":"Point"}
}