{
  "type": "Feature",
  "properties": {
    "addr:full":"Calle de Enrique Iv, 4 Trujillo C\u00e1ceres 10200",
    "addr:housenumber":"4",
    "addr:postcode":"10200",
    "addr:street":"Calle De Enrique Iv;Ca\u0301Ceres",
    "iso:country":"ES",
    "sg:address":"Calle de Enrique Iv, 4",
    "sg:city":"Trujillo",
    "sg:orig_category":"Empresas De Carpinter\u00cda De Madera",
    "sg:phone":"+34 927 32 23 27",
    "sg:postcode":"10200",
    "sg:province":"C\u00e1ceres",
    "wof:name":"Carpinteria Virgen De La Victoria Sal",
    "wof:placetype":"venue"
},
  "geometry": {"coordinates":[-5.8757691383,39.4656600952],"type":"Point"}
}