{
  "type": "Feature",
  "properties": {
    "addr:full":"Extramuros, S/n Forcall Castell\u00f3n 12310",
    "addr:postcode":"12310",
    "addr:street":"Extramuros S / N Forcall Castello\u0301N",
    "iso:country":"ES",
    "sg:address":"Extramuros, S/n",
    "sg:city":"Forcall",
    "sg:orig_category":"Centros De Educaci\u00d3n Especial",
    "sg:phone":"+34 964 17 11 38",
    "sg:postcode":"12310",
    "sg:province":"Castell\u00f3n",
    "wof:name":"Generalitat Valenciana",
    "wof:placetype":"venue"
},
  "geometry": {"coordinates":[-0.2009543926,40.6449279785],"type":"Point"}
}