{
  "type": "Feature",
  "properties": {
    "iso:country":"ES",
    "sg:address":"Pla\u00c7 Catifa, S/n",
    "sg:city":"Palamos",
    "sg:orig_category":"Molduras, Junquillos, Listones Y Molduras Perforadas",
    "sg:phone":"+34 972 31 93 47",
    "sg:postcode":"17230",
    "sg:province":"Girona",
    "wof:name":"Alguacil Fontanella Joan",
    "wof:placetype":"venue"
},
  "geometry": {"coordinates":[3.1328010559,41.8621673584],"type":"Point"}
}