{
  "type": "Feature",
  "properties": {
    "iso:country":"ES",
    "sg:address":"Calle de San Gines, 44",
    "sg:city":"Santiago Ribera",
    "sg:orig_category":"Perfumer\u00cda Y Cosm\u00c9tica (fabricaci\u00d3n, Al Por Mayor)",
    "sg:phone":"+34 968 18 76 88",
    "sg:postcode":"30720",
    "sg:province":"Murcia",
    "wof:name":"Cosmetica Ecologica Del Mar Menor S.l.",
    "wof:placetype":"venue"
},
  "geometry": {"coordinates":[-0.800418973,37.8083000183],"type":"Point"}
}