{
  "type": "Feature",
  "properties": {
    "iso:country":"ES",
    "sg:address":"Ctra Granada-murcia, Km. 0204,0",
    "sg:city":"Cenascuras",
    "sg:orig_category":"Reparaciones Y Remolcado De Veh\u00cdculos",
    "sg:phone":"+34 958 68 20 28",
    "sg:postcode":"18870",
    "sg:province":"Granada",
    "wof:name":"Talleres Arroyo De Gor S.l.",
    "wof:placetype":"venue"
},
  "geometry": {"coordinates":[-2.972522974,37.3706283569],"type":"Point"}
}