{
  "type": "Feature",
  "properties": {
    "iso:country":"ES",
    "sg:address":"Carrer de Montpeller, 33",
    "sg:city":"Barcelona",
    "sg:orig_category":"M\u00c9dicos: Cirug\u00cda Pl\u00c1stica, Reconstructiva Y Est\u00c9tica",
    "sg:phone":"+34 933 45 38 72",
    "sg:postcode":"08030",
    "sg:province":"Barcelona",
    "wof:name":"Bara Casaus Javier",
    "wof:placetype":"venue"
},
  "geometry": {"coordinates":[2.1864058971,41.434803009],"type":"Point"}
}