{
  "type": "Feature",
  "properties": {
    "iso:country":"ES",
    "sg:address":"Calle de Francisco Paino, 5",
    "sg:city":"Madrid",
    "sg:orig_category":"Ropa Para Ni\u00d1os (al Por Menor)",
    "sg:phone":"+34 915 25 55 61",
    "sg:postcode":"28025",
    "sg:province":"Madrid",
    "wof:name":"Izquierdo Ruperez Leon",
    "wof:placetype":"venue"
},
  "geometry": {"coordinates":[-3.7299540043,40.3822898865],"type":"Point"}
}