{
  "type": "Feature",
  "properties": {
    "addr:full":"Calle de Colada, 19 Ciudad Rodrigo Salamanca 37500",
    "addr:housenumber":"19",
    "addr:postcode":"37500",
    "addr:street":"Calle De Colada",
    "iso:country":"ES",
    "sg:address":"Calle de Colada, 19",
    "sg:city":"Ciudad Rodrigo",
    "sg:orig_category":"Restaurantes: Restauraci\u00d3n R\u00c1pida Y Autoservicio",
    "sg:phone":"+34 923 46 00 29",
    "sg:postcode":"37500",
    "sg:province":"Salamanca",
    "wof:name":"Piriz Nicolas Eusebio",
    "wof:placetype":"venue"
},
  "geometry": {"coordinates":[-6.5358982086,40.5974769592],"type":"Point"}
}