{
  "type": "Feature",
  "properties": {
    "iso:country":"ES",
    "sg:address":"Avda Sancho El Sabio, S/n",
    "sg:city":"Arcos",
    "sg:orig_category":"Iglesia Cat\u00d3lica",
    "sg:phone":"+34 948 64 00 79",
    "sg:postcode":"31210",
    "sg:province":"Navarra",
    "wof:name":"Parroquia Santa Maria",
    "wof:placetype":"venue"
},
  "geometry": {"coordinates":[-2.1922340393,42.568271637],"type":"Point"}
}