{
  "type": "Feature",
  "properties": {
    "addr:full":"Calle de Rua (la), 35 Castro Urdiales Cantabria 39700",
    "addr:housenumber":"35",
    "addr:postcode":"39700",
    "addr:street":"Calle De Rua La",
    "iso:country":"ES",
    "sg:address":"Calle de Rua (la), 35",
    "sg:city":"Castro Urdiales",
    "sg:orig_category":"Empresas De Carpinter\u00cda De Madera",
    "sg:phone":"+34 942 86 11 75",
    "sg:postcode":"39700",
    "sg:province":"Cantabria",
    "wof:name":"Sanz Quintana Francisco Javier",
    "wof:placetype":"venue"
},
  "geometry": {"coordinates":[-3.2171590328,43.3852233887],"type":"Point"}
}