{
  "type": "Feature",
  "properties": {
    "addr:full":"Carr Felip Ii, 19 Badalona Barcelona 08917",
    "addr:housenumber":"19",
    "addr:postcode":"08917",
    "addr:street":"Carr Felip Ii",
    "iso:country":"ES",
    "sg:address":"Carr Felip Ii, 19",
    "sg:city":"Badalona",
    "sg:orig_category":"Supermercados Y Hipermercados",
    "sg:phone":"+34 934 60 81 11",
    "sg:postcode":"08917",
    "sg:province":"Barcelona",
    "wof:name":"Del Rio S.l.",
    "wof:placetype":"venue"
},
  "geometry": {"coordinates":[2.2358748913,41.4522705078],"type":"Point"}
}