{
  "type": "Feature",
  "properties": {
    "addr:full":"Carrer de Pere Ii De Queralt, S/n Santa Coloma De Queralt Tarragona 43420",
    "addr:housenumber":"s / n",
    "addr:postcode":"43420",
    "addr:street":"Carrer De Pere Ii De Queralt",
    "iso:country":"ES",
    "sg:address":"Carrer de Pere Ii De Queralt, S/n",
    "sg:city":"Santa Coloma De Queralt",
    "sg:orig_category":"Promotores Constructores",
    "sg:phone":"+34 977 88 13 45",
    "sg:postcode":"43420",
    "sg:province":"Tarragona",
    "sg:website":"www.info@vercontres.com",
    "wof:name":"Bercontres S. A.",
    "wof:placetype":"venue"
},
  "geometry": {"coordinates":[1.3805600405,41.5327262878],"type":"Point"}
}