{
  "type": "Feature",
  "properties": {
    "addr:full":"Avgd Blasco Iba\u00d1ez, 25 Paterna Valencia 46980",
    "addr:housenumber":"25",
    "addr:postcode":"46980",
    "addr:street":"Iban\u0303Ez",
    "iso:country":"ES",
    "sg:address":"Avgd Blasco Iba\u00d1ez, 25",
    "sg:city":"Paterna",
    "sg:orig_category":"Institutos De Belleza",
    "sg:phone":"+34 961 38 71 16",
    "sg:postcode":"46980",
    "sg:province":"Valencia",
    "wof:name":"Mari Carmen Gascon S.l",
    "wof:placetype":"venue"
},
  "geometry": {"coordinates":[-0.4371519983,39.499130249],"type":"Point"}
}