{
  "type": "Feature",
  "properties": {
    "addr:full":"Calle de Sagrado Corazon De Jesus, S/n Villalbilla De Burgos Burgos 09197",
    "addr:housenumber":"s / n",
    "addr:postcode":"09197",
    "addr:street":"Calle De Sagrado Corazon",
    "iso:country":"ES",
    "sg:address":"Calle de Sagrado Corazon De Jesus, S/n",
    "sg:city":"Villalbilla De Burgos",
    "sg:orig_category":"Iglesia Cat\u00d3lica",
    "sg:phone":"+34 947 29 12 72",
    "sg:postcode":"09197",
    "sg:province":"Burgos",
    "wof:name":"Parroquia De La Asuncion De La Virgen",
    "wof:placetype":"venue"
},
  "geometry": {"coordinates":[-3.780039072,42.3461990356],"type":"Point"}
}