{
  "type": "Feature",
  "properties": {
    "iso:country":"ES",
    "sg:address":"Avda Albacete, 54",
    "sg:city":"Santa Pola",
    "sg:orig_category":"Parques De Atracciones Y Centros De Esparcimiento",
    "sg:phone":"+34 965 41 58 24",
    "sg:postcode":"03130",
    "sg:province":"Alicante",
    "wof:name":"Ruiz Perez Domingo",
    "wof:placetype":"venue"
},
  "geometry": {"coordinates":[-0.5756539702,38.193611145],"type":"Point"}
}