{
  "type": "Feature",
  "properties": {
    "addr:full":"Carrer de Bernat Metge, 55 Mollet Valles Barcelona 08100",
    "addr:housenumber":"55",
    "addr:postcode":"08100",
    "addr:street":"Carrer De Bernat Metge",
    "iso:country":"ES",
    "sg:address":"Carrer de Bernat Metge, 55",
    "sg:city":"Mollet Valles",
    "sg:orig_category":"Contenedores (mercanc\u00cdas)",
    "sg:phone":"+34 935 70 96 14",
    "sg:postcode":"08100",
    "sg:province":"Barcelona",
    "wof:name":"Sanchez Mu\u00d1oz Miriam",
    "wof:placetype":"venue"
},
  "geometry": {"coordinates":[2.2065091133,41.5380096436],"type":"Point"}
}