{
  "type": "Feature",
  "properties": {
    "iso:country":"ES",
    "sg:address":"Calle de Gabriela Mistral, 8",
    "sg:city":"Loranca",
    "sg:orig_category":"Art\u00cdculos De Regalo (al Por Menor)",
    "sg:phone":"+34 914 86 43 47",
    "sg:postcode":"28942",
    "sg:province":"Madrid",
    "wof:name":"Yin  Li",
    "wof:placetype":"venue"
},
  "geometry": {"coordinates":[-3.8331809044,40.2948379517],"type":"Point"}
}