{
  "type": "Feature",
  "properties": {
    "addr:full":"Ctra. Abenojar, S/n Pozuelos De Calatrava Ciudad Real 13191",
    "addr:housenumber":"s / n",
    "addr:postcode":"13191",
    "addr:street":"Ctra. Abenojar",
    "iso:country":"ES",
    "sg:address":"Ctra. Abenojar, S/n",
    "sg:city":"Pozuelos De Calatrava",
    "sg:orig_category":"Producci\u00d3n, Venta De Productos De Agricultura Biol\u00d3gica",
    "sg:phone":"+34 926 69 03 44",
    "sg:postcode":"13191",
    "sg:province":"Ciudad Real",
    "wof:name":"Glacar S.l.",
    "wof:placetype":"venue"
},
  "geometry": {"coordinates":[-4.1908683777,38.8962974548],"type":"Point"}
}