{
  "type": "Feature",
  "properties": {
    "addr:full":"Carrer de Barcelona, 71 Hospitalet Llobregat Barcelona 08901",
    "addr:housenumber":"71",
    "addr:postcode":"08901",
    "addr:street":"Carrer De Barcelona",
    "iso:country":"ES",
    "sg:address":"Carrer de Barcelona, 71",
    "sg:city":"Hospitalet Llobregat",
    "sg:orig_category":"M\u00c9dicos: Estomatolog\u00cda",
    "sg:phone":"+34 933 38 13 90",
    "sg:postcode":"08901",
    "sg:province":"Barcelona",
    "wof:name":"Guiu Rodrrigalvarez Manuel",
    "wof:placetype":"venue"
},
  "geometry": {"coordinates":[2.1021590233,41.3608474731],"type":"Point"}
}