{
  "type": "Feature",
  "properties": {
    "iso:country":"ES",
    "sg:address":"Calle de Vista Alegre, 40",
    "sg:city":"Victoria Acentejo",
    "sg:orig_category":"Frutas, Legumbres Frescas Y Tempranas (al Por Menor)",
    "sg:phone":"+34 922 58 05 53",
    "sg:postcode":"38380",
    "sg:province":"Santa Cruz De Tenerife",
    "wof:name":"Gonzalez Izquierdo Ana Del Carmen",
    "wof:placetype":"venue"
},
  "geometry": {"coordinates":[-16.4686985016,28.4340305328],"type":"Point"}
}