{
  "type": "Feature",
  "properties": {
    "iso:country":"ES",
    "sg:address":"Calle de Gorbea, 16",
    "sg:city":"Vitoria-gasteiz",
    "sg:orig_category":"Perfumer\u00cda (al Por Menor)",
    "sg:phone":"+34 945 22 94 97",
    "sg:postcode":"01012",
    "sg:province":"\u00c1lava",
    "wof:name":"Gamarra Carrera Rosa",
    "wof:placetype":"venue"
},
  "geometry": {"coordinates":[-2.6798839569,42.8498268127],"type":"Point"}
}