{
  "type": "Feature",
  "properties": {
    "iso:country":"ES",
    "sg:address":"Rua Polideportivo, S/n",
    "sg:city":"Lalin",
    "sg:orig_category":"Conservatorios",
    "sg:phone":"+34 986 78 70 58",
    "sg:postcode":"36500",
    "sg:province":"Pontevedra",
    "wof:name":"Patronato Cultural De Lalin",
    "wof:placetype":"venue"
},
  "geometry": {"coordinates":[-8.1086730957,42.6646652222],"type":"Point"}
}