{
  "type": "Feature",
  "properties": {
    "addr:full":"Calle de Carlos I De Espa\u00d1a, 33 Dos Hermanas Sevilla 41700",
    "addr:housenumber":"33",
    "addr:postcode":"41700",
    "addr:street":"Calle De Carlos I De Espan\u0303A",
    "iso:country":"ES",
    "sg:address":"Calle de Carlos I De Espa\u00d1a, 33",
    "sg:city":"Dos Hermanas",
    "sg:orig_category":"Carnicer\u00cdas, Carnicer\u00cdas",
    "sg:phone":"+34 955 66 31 20",
    "sg:postcode":"41700",
    "sg:province":"Sevilla",
    "wof:name":"Gonzalez Dominguez Julian",
    "wof:placetype":"venue"
},
  "geometry": {"coordinates":[-5.9271063805,37.2800369263],"type":"Point"}
}