{
  "type": "Feature",
  "properties": {
    "iso:country":"ES",
    "sg:address":"Calle de Capitan Mendizabal, 12",
    "sg:city":"Santurtzi",
    "sg:orig_category":"Caf\u00c9s, Bares, Cervecer\u00cdas",
    "sg:phone":"+34 944 61 04 44",
    "sg:postcode":"48980",
    "sg:province":"Vizcaya",
    "wof:name":"Bar Kai Berri",
    "wof:placetype":"venue"
},
  "geometry": {"coordinates":[-3.0339078903,43.331363678],"type":"Point"}
}