{
  "type": "Feature",
  "properties": {
    "iso:country":"ES",
    "sg:address":"Av Sant Julia, 40",
    "sg:city":"Granollers",
    "sg:orig_category":"Chapister\u00cda",
    "sg:phone":"+34 938 46 31 73",
    "sg:postcode":"08403",
    "sg:province":"Barcelona",
    "wof:name":"Gimenez Serna Jordo",
    "wof:placetype":"venue"
},
  "geometry": {"coordinates":[2.2757966518,41.5972824097],"type":"Point"}
}