{
  "type": "Feature",
  "properties": {
    "iso:country":"ES",
    "sg:address":"Plaz San Ignacio De Loyola, 3",
    "sg:city":"Cordoba",
    "sg:orig_category":"Formaci\u00d3n Continuada (variada)",
    "sg:phone":"+34 957 47 11 93",
    "sg:postcode":"14008",
    "sg:province":"C\u00f3rdoba",
    "wof:name":"Miranda Crespo Miguel Angel",
    "wof:placetype":"venue"
},
  "geometry": {"coordinates":[-4.7831678391,37.8855781555],"type":"Point"}
}