{
  "type": "Feature",
  "properties": {
    "addr:full":"Av President Macia, 2 Reus Tarragona 43204",
    "addr:housenumber":"2",
    "addr:postcode":"43204",
    "addr:street":"Av President Macia",
    "iso:country":"ES",
    "sg:address":"Av President Macia, 2",
    "sg:city":"Reus",
    "sg:orig_category":"Electricidad: Instaladores",
    "sg:phone":"+34 977 75 23 33",
    "sg:postcode":"43204",
    "sg:province":"Tarragona",
    "wof:name":"Serveis I Reparacions Tecniques Reus S.a.",
    "wof:placetype":"venue"
},
  "geometry": {"coordinates":[1.1135200262,41.1507415771],"type":"Point"}
}