{
  "type": "Feature",
  "properties": {
    "addr:full":"Carr Albert Ferrer I Soler, 5 Vilanova I La Geltru Barcelona 08800",
    "addr:housenumber":"5",
    "addr:postcode":"08800",
    "addr:street":"Carr Albert Ferrer I Soler",
    "iso:country":"ES",
    "sg:address":"Carr Albert Ferrer I Soler, 5",
    "sg:city":"Vilanova I La Geltru",
    "sg:orig_category":"Suministros Y Materiales Industriales",
    "sg:phone":"+34 938 14 37 98",
    "sg:postcode":"08800",
    "sg:province":"Barcelona",
    "wof:name":"Catalan Andres Carlos",
    "wof:placetype":"venue"
},
  "geometry": {"coordinates":[1.7395709753,41.229259491],"type":"Point"}
}