{
  "type": "Feature",
  "properties": {
    "addr:full":"Carr Emilio Donat, D', 27 Carcaixent Valencia 46740",
    "addr:housenumber":"27",
    "addr:postcode":"46740",
    "addr:street":"Carr Emilio Donat D '",
    "iso:country":"ES",
    "sg:address":"Carr Emilio Donat, D', 27",
    "sg:city":"Carcaixent",
    "sg:orig_category":"Carnicer\u00cdas, Carnicer\u00cdas",
    "sg:phone":"+34 962 43 11 38",
    "sg:postcode":"46740",
    "sg:province":"Valencia",
    "wof:name":"Calatayud Sendra Juan",
    "wof:placetype":"venue"
},
  "geometry": {"coordinates":[-0.4547240138,39.1157035828],"type":"Point"}
}