{
  "type": "Feature",
  "properties": {
    "iso:country":"ES",
    "sg:address":"Calle de Fuenteguinaldo, 13",
    "sg:city":"Salamanca",
    "sg:orig_category":"Venta, Instalaci\u00d3n De Calefacci\u00d3n",
    "sg:phone":"+34 923 18 55 70",
    "sg:postcode":"37003",
    "sg:province":"Salamanca",
    "wof:name":"Calefacciones Evaristo Y Jose Perez Escribano S.l.",
    "wof:placetype":"venue"
},
  "geometry": {"coordinates":[-5.6398339272,40.9732818604],"type":"Point"}
}