{
  "type": "Feature",
  "properties": {
    "addr:full":"Calle de Mayor, S/n Alloz Navarra 31292",
    "addr:housenumber":"s",
    "addr:postcode":"31292",
    "addr:street":"Calle De Mayor;/ N Alloz Navarra",
    "iso:country":"ES",
    "sg:address":"Calle de Mayor, S/n",
    "sg:city":"Alloz",
    "sg:orig_category":"Asociaciones, Organismos Culturales Y Socioeducativos",
    "sg:phone":"+34 948 54 14 52",
    "sg:postcode":"31292",
    "sg:province":"Navarra",
    "wof:name":"Sociedad Gastronomica Recreativa Burumendi",
    "wof:placetype":"venue"
},
  "geometry": {"coordinates":[-1.9998559952,42.6901283264],"type":"Point"}
}