{
  "type": "Feature",
  "properties": {
    "iso:country":"ES",
    "sg:address":"Calle de Ametzaga\u00d1a, 58",
    "sg:city":"Donostia-san Sebastian",
    "sg:orig_category":"Internados & Ense\u00d1anza Privada",
    "sg:phone":"+34 943 27 15 96",
    "sg:postcode":"20012",
    "sg:province":"Guip\u00f9zcoa",
    "wof:name":"Asociacion Catolica De Padres De Familia De Maria Reina",
    "wof:placetype":"venue"
},
  "geometry": {"coordinates":[-1.9657131433,43.31823349],"type":"Point"}
}