{
  "type": "Feature",
  "properties": {
    "iso:country":"ES",
    "sg:address":"Calle de Carmen (casetas), 26",
    "sg:city":"Casetas",
    "sg:classifiers":[
        {
            "category":"Communications",
            "type":"Services"
        }
    ],
    "sg:phone":"+34 976 77 35 15",
    "sg:postcode":"50620",
    "sg:province":"Zaragoza",
    "sg:tags":[
        "televisiones",
        "y",
        "radio"
    ],
    "sg:website":"www.rclzaragoza.com",
    "wof:name":"Actividades Radiofonicas De Aragon S.l.",
    "wof:placetype":"venue"
},
  "geometry": {"coordinates":[-1.0322844982,41.7186965942],"type":"Point"}
}