{
  "type": "Feature",
  "properties": {
    "addr:full":"Carrer de Serra, 22 Ullastrell Barcelona 08231",
    "addr:housenumber":"22",
    "addr:postcode":"08231",
    "addr:street":"Carrer De Serra;Barcelona",
    "iso:country":"ES",
    "sg:address":"Carrer de Serra, 22",
    "sg:city":"Ullastrell",
    "sg:orig_category":"Reposter\u00cdas",
    "sg:phone":"+34 937 88 81 93",
    "sg:postcode":"08231",
    "sg:province":"Barcelona",
    "wof:name":"Anglada Paloma Bartolome",
    "wof:placetype":"venue"
},
  "geometry": {"coordinates":[1.9566495419,41.5270462036],"type":"Point"}
}