{
  "type": "Feature",
  "properties": {
    "iso:country":"ES",
    "sg:address":"Calle de Tudela, 8",
    "sg:city":"Valladolid",
    "sg:orig_category":"Ingeniero",
    "sg:phone":"+34 983 39 84 05",
    "sg:postcode":"47002",
    "sg:province":"Valladolid",
    "wof:name":"Gonzalez Herguedas Jose Luis",
    "wof:placetype":"venue"
},
  "geometry": {"coordinates":[-4.718539238,41.6475791931],"type":"Point"}
}