{
  "type": "Feature",
  "properties": {
    "addr:full":"Avda Ramon Ferreiro, 24 Lugo Lugo 27002",
    "addr:housenumber":"24",
    "addr:postcode":"27002",
    "addr:street":"Avda Ramon Ferreiro",
    "iso:country":"ES",
    "sg:address":"Avda Ramon Ferreiro, 24",
    "sg:city":"Lugo",
    "sg:orig_category":"Asociaciones, Organismos Culturales Y Socioeducativos",
    "sg:phone":"+34 982 24 64 25",
    "sg:postcode":"27002",
    "sg:province":"Lugo",
    "wof:name":"Centro Difusor De Educacion Y Cultura Actualizada",
    "wof:placetype":"venue"
},
  "geometry": {"coordinates":[-7.5534710884,43.0035324097],"type":"Point"}
}