{
  "type": "Feature",
  "properties": {
    "addr:full":"Plaz Zorita, S/n Alcala Henares Madrid 28805",
    "addr:housenumber":"s / n",
    "addr:postcode":"28805",
    "iso:country":"ES",
    "sg:address":"Plaz Zorita, S/n",
    "sg:city":"Alcala Henares",
    "sg:orig_category":"Comercio De Piezas De Recambio Y De Accesorios De Veh\u00cdculos, Veh\u00cdculos Industriales",
    "sg:phone":"+34 918 83 08 75",
    "sg:postcode":"28805",
    "sg:province":"Madrid",
    "sg:website":"www.norauto.es",
    "wof:name":"Norauto S.a.",
    "wof:placetype":"venue"
},
  "geometry": {"coordinates":[-3.3307089806,40.5036354065],"type":"Point"}
}