{
  "type": "Feature",
  "properties": {
    "iso:country":"ES",
    "sg:address":"Calle de Cura Iba\u00d1ez, 3",
    "sg:city":"Yecla",
    "sg:orig_category":"Promotores Constructores",
    "sg:phone":"+34 968 79 51 56",
    "sg:postcode":"30510",
    "sg:province":"Murcia",
    "wof:name":"Construcciones Oryecla S.l.",
    "wof:placetype":"venue"
},
  "geometry": {"coordinates":[-1.1101520061,38.6109962463],"type":"Point"}
}