{
  "type": "Feature",
  "properties": {
    "iso:country":"ES",
    "sg:address":"Carrer de Pla De L'ametllera, 116",
    "sg:city":"Terrassa",
    "sg:orig_category":"Peluquer\u00cdas, Peluquer\u00cda Mixta",
    "sg:phone":"+34 937 35 80 65",
    "sg:postcode":"08225",
    "sg:province":"Barcelona",
    "wof:name":"Ortiz Centelles Judit",
    "wof:placetype":"venue"
},
  "geometry": {"coordinates":[2.0106501579,41.5732040405],"type":"Point"}
}