{
  "type": "Feature",
  "properties": {
    "iso:country":"ES",
    "sg:address":"Poife, 3",
    "sg:city":"Ferreries",
    "sg:orig_category":"Negocio De Materiales De Construcci\u00d3n",
    "sg:phone":"+34 971 37 39 07",
    "sg:postcode":"07750",
    "sg:province":"Islas Baleares",
    "wof:name":"Magatzem Ferreries S.l.",
    "wof:placetype":"venue"
},
  "geometry": {"coordinates":[4.0080771446,39.9823303223],"type":"Point"}
}