{
  "type": "Feature",
  "properties": {
    "addr:full":"Ctra Alacant (d'), 14 Callosa D'en Sarria Alicante 03510",
    "addr:postcode":"03510",
    "addr:street":"Alacant;'",
    "iso:country":"ES",
    "sg:address":"Ctra Alacant (d'), 14",
    "sg:city":"Callosa D'en Sarria",
    "sg:orig_category":"Agencias De Viajes",
    "sg:phone":"+34 965 88 21 66",
    "sg:postcode":"03510",
    "sg:province":"Alicante",
    "wof:name":"Rumini",
    "wof:placetype":"venue"
},
  "geometry": {"coordinates":[-0.121755898,38.6492500305],"type":"Point"}
}