{
  "type": "Feature",
  "properties": {
    "addr:full":"Calle de Rosario, S/n Lucillo Le\u00f3n 24723",
    "addr:housenumber":"/ n",
    "addr:postcode":"24723",
    "addr:street":"Calle De Rosario S;Leo\u0301N",
    "iso:country":"ES",
    "sg:address":"Calle de Rosario, S/n",
    "sg:city":"Lucillo",
    "sg:orig_category":"Autob\u00das (explotaci\u00d3n Y Servicios De)",
    "sg:phone":"+34 987 63 10 36",
    "sg:postcode":"24723",
    "sg:province":"Le\u00f3n",
    "wof:name":"Eladio Campano E Hijos S.l.",
    "wof:placetype":"venue"
},
  "geometry": {"coordinates":[-6.304049015,42.4095611572],"type":"Point"}
}