{
  "type": "Feature",
  "properties": {
    "iso:country":"ES",
    "sg:address":"Av Baro, 15",
    "sg:city":"Barcelona",
    "sg:orig_category":"Carnicer\u00cdas, Carnicer\u00cdas",
    "sg:phone":"+34 932 13 40 52",
    "sg:postcode":"08024",
    "sg:province":"Barcelona",
    "wof:name":"Hernandez Nayach Enrique",
    "wof:placetype":"venue"
},
  "geometry": {"coordinates":[2.1611959934,41.4155845642],"type":"Point"}
}