{
  "type": "Feature",
  "properties": {
    "addr:full":"Calle de Alcalde Jose Puertes, S/n Alfafar Valencia 46910",
    "addr:housenumber":"s / n",
    "addr:postcode":"46910",
    "addr:street":"Calle De Alcalde Jose Puertes",
    "iso:country":"ES",
    "sg:address":"Calle de Alcalde Jose Puertes, S/n",
    "sg:city":"Alfafar",
    "sg:orig_category":"Ropa Para Caballeros (al Por Menor)",
    "sg:phone":"+34 963 75 15 94",
    "sg:postcode":"46910",
    "sg:province":"Valencia",
    "wof:name":"Serman 92 S.l.",
    "wof:placetype":"venue"
},
  "geometry": {"coordinates":[-0.3803189993,39.4183387756],"type":"Point"}
}