{
  "type": "Feature",
  "properties": {
    "iso:country":"ES",
    "sg:address":"Calle de Covadonga, 3",
    "sg:city":"Tarifa",
    "sg:orig_category":"Carnicer\u00cdas, Carnicer\u00cdas",
    "sg:phone":"+34 956 68 15 16",
    "sg:postcode":"11380",
    "sg:province":"C\u00e1diz",
    "wof:name":"Diaz Santamaria Francisca",
    "wof:placetype":"venue"
},
  "geometry": {"coordinates":[-5.6060171127,36.0136222839],"type":"Point"}
}