{
  "type": "Feature",
  "properties": {
    "iso:country":"ES",
    "sg:address":"Plaz Frai Bartolome, 2",
    "sg:city":"Markina-xemein",
    "sg:orig_category":"Peluqueros: De Se\u00d1oras",
    "sg:phone":"+34 946 16 87 66",
    "sg:postcode":"48270",
    "sg:province":"Vizcaya",
    "wof:name":"Jayo Ibarlucea Cristina",
    "wof:placetype":"venue"
},
  "geometry": {"coordinates":[-2.499368906,43.270690918],"type":"Point"}
}