{
  "type": "Feature",
  "properties": {
    "iso:country":"ES",
    "sg:address":"Calle de Plaza, 95",
    "sg:city":"Puente",
    "sg:orig_category":"Telas Y Sedas (al Por Menor)",
    "sg:phone":"+34 980 62 30 58",
    "sg:postcode":"49350",
    "sg:province":"Zamora",
    "wof:name":"Fernandez Centeno Ana Maria",
    "wof:placetype":"venue"
},
  "geometry": {"coordinates":[-6.6421990395,42.0836639404],"type":"Point"}
}