{
  "type": "Feature",
  "properties": {
    "iso:country":"ES",
    "sg:address":"Avda Cortes De Aragon, 32",
    "sg:city":"Valderrobres",
    "sg:orig_category":"Cajas De Ahorro",
    "sg:phone":"+34 978 85 00 29",
    "sg:postcode":"44580",
    "sg:province":"Teruel",
    "sg:website":"www.ibercaja.es",
    "wof:name":"Caja De Ahorros Y Monte De Piedad De Zaragoza Aragon Y Rioja",
    "wof:placetype":"venue"
},
  "geometry": {"coordinates":[0.154407993,40.8725280762],"type":"Point"}
}