{
  "type": "Feature",
  "properties": {
    "iso:country":"ES",
    "sg:address":"Calle de Feria, 10",
    "sg:city":"Constantina",
    "sg:orig_category":"Serrer\u00cdas De Madera",
    "sg:phone":"+34 955 88 02 29",
    "sg:postcode":"41450",
    "sg:province":"Sevilla",
    "wof:name":"Fuentevilla Valverde Manuel",
    "wof:placetype":"venue"
},
  "geometry": {"coordinates":[-5.6206178665,37.8764648438],"type":"Point"}
}