{
  "type": "Feature",
  "properties": {
    "addr:full":"Avda Paseo De Almeria, 59 Almeria Almer\u00eda 04001",
    "addr:housenumber":"59",
    "addr:postcode":"04001",
    "addr:street":"Avda Paseo De Almeria",
    "iso:country":"ES",
    "sg:address":"Avda Paseo De Almeria, 59",
    "sg:city":"Almeria",
    "sg:orig_category":"Promotores Constructores",
    "sg:phone":"+34 950 26 21 55",
    "sg:postcode":"04001",
    "sg:province":"Almer\u00eda",
    "wof:name":"Majolpa S.l.",
    "wof:placetype":"venue"
},
  "geometry": {"coordinates":[-2.4632077217,36.8372268677],"type":"Point"}
}