{
  "type": "Feature",
  "properties": {
    "addr:full":"Calle de Garbi, Del, 24 Torrent Valencia 46900",
    "addr:housenumber":"24",
    "addr:postcode":"46900",
    "addr:street":"Calle De Garbi Del;Valencia",
    "iso:country":"ES",
    "sg:address":"Calle de Garbi, Del, 24",
    "sg:city":"Torrent",
    "sg:orig_category":"Asesor\u00cda, Estudio Y Control Medioambiental",
    "sg:phone":"+34 961 56 53 53",
    "sg:postcode":"46900",
    "sg:province":"Valencia",
    "wof:name":"Fcc Medio Ambiente S A",
    "wof:placetype":"venue"
},
  "geometry": {"coordinates":[-0.4679391086,39.4332046509],"type":"Point"}
}