{
  "type": "Feature",
  "properties": {
    "addr:full":"Fonte De Curro, 39 Curro Pontevedra 36692",
    "addr:housenumber":"39",
    "addr:postcode":"36692",
    "addr:street":"Curro",
    "iso:country":"ES",
    "sg:address":"Fonte De Curro, 39",
    "sg:city":"Curro",
    "sg:orig_category":"Guarder\u00cdas",
    "sg:phone":"+34 986 71 34 43",
    "sg:postcode":"36692",
    "sg:province":"Pontevedra",
    "wof:name":"Xunta Vecinal Mancomunidad S.maria De Curro",
    "wof:placetype":"venue"
},
  "geometry": {"coordinates":[-8.675909996,42.5060844421],"type":"Point"}
}