{
  "type": "Feature",
  "properties": {
    "addr:full":"Calle de Pozo Nuevo, 19 Nombela Toledo 45917",
    "addr:housenumber":"19",
    "addr:postcode":"45917",
    "addr:street":"Calle De Pozo Nuevo",
    "iso:country":"ES",
    "sg:address":"Calle de Pozo Nuevo, 19",
    "sg:city":"Nombela",
    "sg:orig_category":"Supermercados Y Hipermercados",
    "sg:phone":"+34 925 79 20 23",
    "sg:postcode":"45917",
    "sg:province":"Toledo",
    "wof:name":"Jimenez Palacios Juan",
    "wof:placetype":"venue"
},
  "geometry": {"coordinates":[-4.5034542084,40.1575393677],"type":"Point"}
}