{
  "type": "Feature",
  "properties": {
    "addr:full":"Carr Raval, S/n Granyena De Les Garrigues Lleida 25160",
    "addr:housenumber":"s / n",
    "addr:postcode":"25160",
    "addr:street":"Carr Raval",
    "iso:country":"ES",
    "sg:address":"Carr Raval, S/n",
    "sg:city":"Granyena De Les Garrigues",
    "sg:orig_category":"Cooperativas Agr\u00cdcolas",
    "sg:phone":"+34 973 13 63 70",
    "sg:postcode":"25160",
    "sg:province":"Lleida",
    "wof:name":"Cooperativa Del Campo",
    "wof:placetype":"venue"
},
  "geometry": {"coordinates":[0.6488999724,41.433139801],"type":"Point"}
}