{
  "type": "Feature",
  "properties": {
    "addr:full":"Avda Manuel Siurot, 81 Sevilla Sevilla 41013",
    "addr:housenumber":"81",
    "addr:postcode":"41013",
    "addr:street":"Avda Manuel Siurot",
    "iso:country":"ES",
    "sg:address":"Avda Manuel Siurot, 81",
    "sg:city":"Sevilla",
    "sg:orig_category":"Librer\u00cdas",
    "sg:phone":"+34 954 61 06 02",
    "sg:postcode":"41013",
    "sg:province":"Sevilla",
    "wof:name":"Montori Pardina Jesus",
    "wof:placetype":"venue"
},
  "geometry": {"coordinates":[-5.9791889191,37.3570213318],"type":"Point"}
}