{
  "type": "Feature",
  "properties": {
    "addr:full":"Avda Andalucia, 30 Lanjaron Granada 18420",
    "addr:housenumber":"30",
    "addr:postcode":"18420",
    "addr:street":"Avda Andalucia",
    "iso:country":"ES",
    "sg:address":"Avda Andalucia, 30",
    "sg:city":"Lanjaron",
    "sg:orig_category":"Laboratorios Farmac\u00c9uticos",
    "sg:phone":"+34 958 77 00 07",
    "sg:postcode":"18420",
    "sg:province":"Granada",
    "wof:name":"Rubio Alonso Jose",
    "wof:placetype":"venue"
},
  "geometry": {"coordinates":[-3.485033989,36.9184837341],"type":"Point"}
}