{
  "type": "Feature",
  "properties": {
    "iso:country":"ES",
    "sg:address":"Bidebarrieta Kalea, 3",
    "sg:city":"Eibar",
    "sg:orig_category":"Bancos",
    "sg:phone":"+34 943 20 19 40",
    "sg:postcode":"20600",
    "sg:province":"Guip\u00f9zcoa",
    "wof:name":"Banco Popular Espa\u00d1ol S.a.",
    "wof:placetype":"venue"
},
  "geometry": {"coordinates":[-2.4710359573,43.1851654053],"type":"Point"}
}