{
  "type": "Feature",
  "properties": {
    "iso:country":"ES",
    "sg:address":"Calle de Obra Pia, 5",
    "sg:city":"Miajadas",
    "sg:orig_category":"Producci\u00d3n, Distribuci\u00d3n De Gas Butano Y Propano",
    "sg:phone":"+34 927 34 70 18",
    "sg:postcode":"10100",
    "sg:province":"C\u00e1ceres",
    "wof:name":"Electro-gas Masa S.l.",
    "wof:placetype":"venue"
},
  "geometry": {"coordinates":[-5.9082989693,39.1555213928],"type":"Point"}
}