{
  "type": "Feature",
  "properties": {
    "iso:country":"ES",
    "sg:address":"Calle de Seijas, 4",
    "sg:city":"Tui",
    "sg:orig_category":"Pizzer\u00cdas",
    "sg:phone":"+34 986 60 36 85",
    "sg:postcode":"36700",
    "sg:province":"Pontevedra",
    "wof:name":"Diamante C.b.",
    "wof:placetype":"venue"
},
  "geometry": {"coordinates":[-8.6448440552,42.0485496521],"type":"Point"}
}