{
  "type": "Feature",
  "properties": {
    "addr:full":"Carrer de Jerusalem, 4 Barcelona Barcelona 08001",
    "addr:housenumber":"4",
    "addr:postcode":"08001",
    "addr:street":"Carrer De Jerusalem",
    "iso:country":"ES",
    "sg:address":"Carrer de Jerusalem, 4",
    "sg:city":"Barcelona",
    "sg:orig_category":"Supermercados Y Hipermercados",
    "sg:phone":"+34 934 12 27 96",
    "sg:postcode":"08001",
    "sg:province":"Barcelona",
    "sg:website":"www.consum.es",
    "wof:name":"Consum Sociedad Cooperativa Limitada",
    "wof:placetype":"venue"
},
  "geometry": {"coordinates":[2.1718280315,41.3810806274],"type":"Point"}
}