{
  "type": "Feature",
  "properties": {
    "addr:full":"Avda Raza (la), 20 Sevilla Sevilla 41012",
    "addr:housenumber":"20",
    "addr:postcode":"41012",
    "addr:street":"Avda Raza La",
    "iso:country":"ES",
    "sg:address":"Avda Raza (la), 20",
    "sg:city":"Sevilla",
    "sg:orig_category":"Transporte En General",
    "sg:phone":"+34 954 23 90 68",
    "sg:postcode":"41012",
    "sg:province":"Sevilla",
    "wof:name":"Ership S.a.",
    "wof:placetype":"venue"
},
  "geometry": {"coordinates":[-5.989636898,37.3663864136],"type":"Point"}
}