{
  "type": "Feature",
  "properties": {
    "addr:full":"Plaz Mercado (del), 23 Almaden Ciudad Real 13400",
    "addr:postcode":"13400",
    "addr:street":"Almaden;Real",
    "iso:country":"ES",
    "sg:address":"Plaz Mercado (del), 23",
    "sg:city":"Almaden",
    "sg:orig_category":"Peluquer\u00cdas, Peluquer\u00cda Mixta",
    "sg:phone":"+34 926 71 00 45",
    "sg:postcode":"13400",
    "sg:province":"Ciudad Real",
    "wof:name":"Fuentes Delgado-aguilera Maria Fatima",
    "wof:placetype":"venue"
},
  "geometry": {"coordinates":[-4.8423290253,38.7738647461],"type":"Point"}
}