{
  "type": "Feature",
  "properties": {
    "iso:country":"ES",
    "sg:address":"Calle de Santa Isabel, 6",
    "sg:city":"Zaragoza",
    "sg:orig_category":"\u00d3ptica: Instrumentos (fabricaci\u00d3n)",
    "sg:phone":"+34 976 39 29 11",
    "sg:postcode":"50003",
    "sg:province":"Zaragoza",
    "wof:name":"Sanchez Martinez Maria Visitacion",
    "wof:placetype":"venue"
},
  "geometry": {"coordinates":[-0.8812999725,41.6555786133],"type":"Point"}
}