{
  "type": "Feature",
  "properties": {
    "addr:full":"Ctra Cenicero, Km. 0005,2 Uru\u00f1uela La Rioja 26313",
    "addr:postcode":"26313",
    "addr:street":"Ctra Cenicero Km. 0005,2 Urun\u0303Uela;Rioja",
    "iso:country":"ES",
    "sg:address":"Ctra Cenicero, Km. 0005,2",
    "sg:city":"Uru\u00f1uela",
    "sg:orig_category":"Hormigonados",
    "sg:phone":"+34 941 37 11 09",
    "sg:postcode":"26313",
    "sg:province":"La Rioja",
    "wof:name":"Hormigones Najera S. A.",
    "wof:placetype":"venue"
},
  "geometry": {"coordinates":[-2.7068209648,42.4471092224],"type":"Point"}
}