{
  "type": "Feature",
  "properties": {
    "addr:full":"Carrer de Rubens, 48 Barcelona Barcelona 08023",
    "addr:housenumber":"48",
    "addr:postcode":"08023",
    "addr:street":"Carrer De Rubens",
    "iso:country":"ES",
    "sg:address":"Carrer de Rubens, 48",
    "sg:city":"Barcelona",
    "sg:orig_category":"Muebles Y Accesorios Para Cocinas Y Cuartos De Ba\u00d1o (al Por Menor)",
    "sg:phone":"+34 932 85 05 60",
    "sg:postcode":"08023",
    "sg:province":"Barcelona",
    "wof:name":"Gea Lozano Antonio",
    "wof:placetype":"venue"
},
  "geometry": {"coordinates":[2.1471159458,41.4154663086],"type":"Point"}
}