{
  "type": "Feature",
  "properties": {
    "iso:country":"ES",
    "sg:address":"Calle de Juan Bautista Uriarte, 28",
    "sg:city":"Kurtzea",
    "sg:orig_category":"Ropa Para Caballeros (al Por Menor)",
    "sg:phone":"+34 944 56 70 57",
    "sg:postcode":"48960",
    "sg:province":"Vizcaya",
    "wof:name":"Celaya Legarreta Yagoba",
    "wof:placetype":"venue"
},
  "geometry": {"coordinates":[-2.8446810246,43.2300224304],"type":"Point"}
}