{
  "type": "Feature",
  "properties": {
    "iso:country":"ES",
    "sg:address":"C/ Maestro Albeniz, 7",
    "sg:city":"Elche",
    "sg:orig_category":"Promotores Constructores",
    "sg:phone":"+34 966 61 51 62",
    "sg:postcode":"03202",
    "sg:province":"Alicante",
    "sg:website":"www.victoriaplaya.com",
    "wof:name":"Promociones Don Sento S.l.",
    "wof:placetype":"venue"
},
  "geometry": {"coordinates":[-0.6959789991,38.2685546875],"type":"Point"}
}