{
  "type": "Feature",
  "properties": {
    "iso:country":"ES",
    "sg:address":"Carrer de Portal Nou, 46",
    "sg:city":"Barcelona",
    "sg:orig_category":"Cristaler\u00cdas",
    "sg:phone":"+34 933 19 82 87",
    "sg:postcode":"08003",
    "sg:province":"Barcelona",
    "wof:name":"Martin Nebot Jaime",
    "wof:placetype":"venue"
},
  "geometry": {"coordinates":[2.1810529232,41.3892593384],"type":"Point"}
}