{
  "type": "Feature",
  "properties": {
    "iso:country":"ES",
    "sg:address":"Can Vilaro, S/n",
    "sg:city":"Vilablareix",
    "sg:orig_category":"Empresas De Carpinter\u00cda De Madera",
    "sg:phone":"+34 972 24 18 11",
    "sg:postcode":"17180",
    "sg:province":"Girona",
    "wof:name":"Taller De Fusteria S.l.",
    "wof:placetype":"venue"
},
  "geometry": {"coordinates":[2.7989549637,41.9561538696],"type":"Point"}
}