{
  "type": "Feature",
  "properties": {
    "addr:full":"Avda Jose Luis Arrese, 28 Valladolid Valladolid 47014",
    "addr:housenumber":"28",
    "addr:postcode":"47014",
    "addr:street":"Avda Jose Luis Arrese",
    "iso:country":"ES",
    "sg:address":"Avda Jose Luis Arrese, 28",
    "sg:city":"Valladolid",
    "sg:orig_category":"Ingenier\u00cda, Centros De Estudios (diversos)",
    "sg:phone":"+34 983 33 71 71",
    "sg:postcode":"47014",
    "sg:province":"Valladolid",
    "wof:name":"Terrados Galindo Javier",
    "wof:placetype":"venue"
},
  "geometry": {"coordinates":[-4.7401781082,41.6513786316],"type":"Point"}
}