{
  "type": "Feature",
  "properties": {
    "addr:full":"Ctra Moron-coripe, S/n Moron Frontera Sevilla 41530",
    "addr:housenumber":"s",
    "addr:postcode":"41530",
    "addr:street":"Ctra Moron-Coripe;/ N Moron",
    "iso:country":"ES",
    "sg:address":"Ctra Moron-coripe, S/n",
    "sg:city":"Moron Frontera",
    "sg:orig_category":"Cr\u00cda De Animales",
    "sg:phone":"+34 955 95 72 41",
    "sg:postcode":"41530",
    "sg:province":"Sevilla",
    "wof:name":"El Parroso S.a.",
    "wof:placetype":"venue"
},
  "geometry": {"coordinates":[-5.4528231621,37.1294212341],"type":"Point"}
}