{
  "type": "Feature",
  "properties": {
    "iso:country":"ES",
    "sg:address":"Carr Artesania, 32",
    "sg:city":"Barri De Porta",
    "sg:orig_category":"Triper\u00cdas",
    "sg:phone":"+34 961 52 53 20",
    "sg:postcode":"46930",
    "sg:province":"Valencia",
    "sg:website":"www.vgallent.es",
    "wof:name":"Vicente Gallent S.l.",
    "wof:placetype":"venue"
},
  "geometry": {"coordinates":[-0.4419890046,39.482711792],"type":"Point"}
}