{
  "type": "Feature",
  "properties": {
    "addr:full":"Calle de Morales Gomez, 11 Brenes Sevilla 41310",
    "addr:housenumber":"11",
    "addr:postcode":"41310",
    "addr:street":"Calle De Morales Gomez",
    "iso:country":"ES",
    "sg:address":"Calle de Morales Gomez, 11",
    "sg:city":"Brenes",
    "sg:orig_category":"Droguer\u00cdas (al Por Menor)",
    "sg:phone":"+34 954 79 69 32",
    "sg:postcode":"41310",
    "sg:province":"Sevilla",
    "wof:name":"Galan Correa Olga",
    "wof:placetype":"venue"
},
  "geometry": {"coordinates":[-5.8723630905,37.5482940674],"type":"Point"}
}