{
  "type": "Feature",
  "properties": {
    "iso:country":"ES",
    "sg:address":"Calle de Padilla, 3",
    "sg:city":"Valencia",
    "sg:orig_category":"Artes Gr\u00c1ficas, Artes Pl\u00c1sticas (curso)",
    "sg:phone":"+34 963 94 31 93",
    "sg:postcode":"46001",
    "sg:province":"Valencia",
    "wof:name":"Copiformes S.l.",
    "wof:placetype":"venue"
},
  "geometry": {"coordinates":[-0.3790499866,39.4697952271],"type":"Point"}
}