{
  "type": "Feature",
  "properties": {
    "addr:full":"Calle de Pablo Iglesias, 1 Castellon Castell\u00f3n 12003",
    "addr:housenumber":"1",
    "addr:postcode":"12003",
    "addr:street":"Calle De Pablo Iglesias;Castello\u0301N",
    "iso:country":"ES",
    "sg:address":"Calle de Pablo Iglesias, 1",
    "sg:city":"Castellon",
    "sg:orig_category":"Carnicer\u00cdas, Carnicer\u00cdas",
    "sg:phone":"+34 964 22 82 72",
    "sg:postcode":"12003",
    "sg:province":"Castell\u00f3n",
    "wof:name":"Fabregat Barreda Angel",
    "wof:placetype":"venue"
},
  "geometry": {"coordinates":[-0.029321,39.9828338623],"type":"Point"}
}