{
  "type": "Feature",
  "properties": {
    "addr:full":"Calle de Emilio Calzadilla, 23 Santa Cruz De Tenerife Santa Cruz De Tenerife 38002",
    "addr:housenumber":"23",
    "addr:postcode":"38002",
    "addr:street":"Calle De Emilio Calzadilla",
    "iso:country":"ES",
    "sg:address":"Calle de Emilio Calzadilla, 23",
    "sg:city":"Santa Cruz De Tenerife",
    "sg:orig_category":"M\u00c9dicos: Neurocirug\u00cda",
    "sg:phone":"+34 922 24 89 86",
    "sg:postcode":"38002",
    "sg:province":"Santa Cruz De Tenerife",
    "wof:name":"Ravina Cabrera Juan",
    "wof:placetype":"venue"
},
  "geometry": {"coordinates":[-17.2191944122,28.1820106506],"type":"Point"}
}