{
  "type": "Feature",
  "properties": {
    "iso:country":"ES",
    "sg:address":"Calle de Buenaventura Zapirain Kalea, 6",
    "sg:city":"Lekeitio",
    "sg:orig_category":"Puertas Y Portales",
    "sg:phone":"+34 946 84 28 55",
    "sg:postcode":"48280",
    "sg:province":"Vizcaya",
    "wof:name":"Careaga Zabala Benjamin",
    "wof:placetype":"venue"
},
  "geometry": {"coordinates":[-2.5061159134,43.3635826111],"type":"Point"}
}