{
  "type": "Feature",
  "properties": {
    "iso:country":"ES",
    "sg:address":"Calle de Salvador Sastre, 7",
    "sg:city":"Valencia",
    "sg:orig_category":"Chapister\u00cda",
    "sg:phone":"+34 963 41 30 42",
    "sg:postcode":"46007",
    "sg:province":"Valencia",
    "wof:name":"Perez Sanchez Vicente",
    "wof:placetype":"venue"
},
  "geometry": {"coordinates":[-0.3816527128,39.4636383057],"type":"Point"}
}