{
  "type": "Feature",
  "properties": {
    "addr:full":"Carrer de Dalt, 18 Maspujols Tarragona 43382",
    "addr:housenumber":"18",
    "addr:postcode":"43382",
    "addr:street":"Carrer De Dalt",
    "iso:country":"ES",
    "sg:address":"Carrer de Dalt, 18",
    "sg:city":"Maspujols",
    "sg:orig_category":"Arquitectos",
    "sg:phone":"+34 977 81 55 69",
    "sg:postcode":"43382",
    "sg:province":"Tarragona",
    "wof:name":"Canovas Sanchez Ivan",
    "wof:placetype":"venue"
},
  "geometry": {"coordinates":[1.0456570387,41.1823883057],"type":"Point"}
}