{
  "type": "Feature",
  "properties": {
    "iso:country":"ES",
    "sg:address":"Carrer de Cros, 6",
    "sg:city":"Barcelona",
    "sg:orig_category":"Arreglo E Instalaci\u00d3n De Caf\u00c9s, Hoteles Y Restaurantes",
    "sg:phone":"+34 934 22 31 51",
    "sg:postcode":"08014",
    "sg:province":"Barcelona",
    "wof:name":"Menjadors Co%ectius S.a.",
    "wof:placetype":"venue"
},
  "geometry": {"coordinates":[2.1378090382,41.3749275208],"type":"Point"}
}