{
  "type": "Feature",
  "properties": {
    "iso:country":"ES",
    "sg:address":"Avda Rafael Cabrera, 18",
    "sg:city":"Palmas De Gran Canaria",
    "sg:orig_category":"Abogados",
    "sg:phone":"+34 928 36 35 66",
    "sg:postcode":"35002",
    "sg:province":"Las Palmas",
    "wof:name":"Trujillo Perdomo Salvador",
    "wof:placetype":"venue"
},
  "geometry": {"coordinates":[-15.4147958755,28.1063613892],"type":"Point"}
}