{
  "type": "Feature",
  "properties": {
    "iso:country":"ES",
    "sg:address":"Calle de Nueva, 31",
    "sg:city":"Petres",
    "sg:orig_category":"Supermercados Y Hipermercados",
    "sg:phone":"+34 962 62 06 47",
    "sg:postcode":"46500",
    "sg:province":"Valencia",
    "wof:name":"Conejos Benet Maria",
    "wof:placetype":"venue"
},
  "geometry": {"coordinates":[-0.2783089876,39.6799659729],"type":"Point"}
}