{
  "type": "Feature",
  "properties": {
    "iso:country":"ES",
    "sg:address":"Pase Bertsol. Txirrita, 3",
    "sg:city":"Donostia-san Sebastian",
    "sg:orig_category":"Panader\u00cdas, Panader\u00cdas",
    "sg:phone":"+34 943 39 16 05",
    "sg:postcode":"20017",
    "sg:province":"Guip\u00f9zcoa",
    "wof:name":"Pasteleria Candy, C.b.",
    "wof:placetype":"venue"
},
  "geometry": {"coordinates":[-1.9390280247,43.3138046265],"type":"Point"}
}