{
  "type": "Feature",
  "properties": {
    "addr:full":"Ctra. Sagunto-burgos, S/n Cabrejas Pinar Soria 42147",
    "addr:housenumber":"s / n",
    "addr:postcode":"42147",
    "addr:street":"Ctra. Sagunto-Burgos",
    "iso:country":"ES",
    "sg:address":"Ctra. Sagunto-burgos, S/n",
    "sg:city":"Cabrejas Pinar",
    "sg:orig_category":"Vallados Y Barreras",
    "sg:phone":"+34 975 37 30 49",
    "sg:postcode":"42147",
    "sg:province":"Soria",
    "sg:website":"www.amatex.es",
    "wof:name":"Aprovechamientos Madereros Y Tratamientos Para Exteriores S.a.",
    "wof:placetype":"venue"
},
  "geometry": {"coordinates":[-2.7884440422,41.8055343628],"type":"Point"}
}