{
  "type": "Feature",
  "properties": {
    "iso:country":"ES",
    "sg:address":"Calle de Bidebarrieta, 1",
    "sg:city":"Iurreta",
    "sg:orig_category":"Fotocopias, Reprograf\u00cda",
    "sg:phone":"+34 944 66 82 60",
    "sg:postcode":"48215",
    "sg:province":"Vizcaya",
    "wof:name":"Sonia Bego\u00f1a Garcia Algar - Eduardo Bri\u00f1as Gallastegui",
    "wof:placetype":"venue"
},
  "geometry": {"coordinates":[-2.63058424,43.1752204895],"type":"Point"}
}