{
  "type": "Feature",
  "properties": {
    "addr:full":"Calle de Jorge Luis Borges, 33 Alcala Henares Madrid 28806",
    "addr:housenumber":"33",
    "addr:postcode":"28806",
    "addr:street":"Calle De Jorge Luis Borges",
    "iso:country":"ES",
    "sg:address":"Calle de Jorge Luis Borges, 33",
    "sg:city":"Alcala Henares",
    "sg:orig_category":"Ferreter\u00cda (diversos)",
    "sg:phone":"+34 918 89 21 18",
    "sg:postcode":"28806",
    "sg:province":"Madrid",
    "wof:name":"Regapal S.l.",
    "wof:placetype":"venue"
},
  "geometry": {"coordinates":[-3.374243021,40.4971237183],"type":"Point"}
}