{
  "type": "Feature",
  "properties": {
    "addr:full":"Carrer de Batllevell, 71 Sabadell Barcelona 08208",
    "addr:housenumber":"71",
    "addr:postcode":"08208",
    "addr:street":"Carrer De Batllevell",
    "iso:country":"ES",
    "sg:address":"Carrer de Batllevell, 71",
    "sg:city":"Sabadell",
    "sg:orig_category":"Molduras, Junquillos, Listones Y Molduras Perforadas",
    "sg:phone":"+34 937 23 76 09",
    "sg:postcode":"08208",
    "sg:province":"Barcelona",
    "wof:name":"Perez Granados Jose Carlos",
    "wof:placetype":"venue"
},
  "geometry": {"coordinates":[2.1080899239,41.5573387146],"type":"Point"}
}