{
  "type": "Feature",
  "properties": {
    "iso:country":"ES",
    "sg:address":"Avda Aragon De, 99",
    "sg:city":"Fraga",
    "sg:orig_category":"Agricultura: Abastecimiento Y Cosechado (negocio)",
    "sg:phone":"+34 974 47 07 27",
    "sg:postcode":"22520",
    "sg:province":"Huesca",
    "wof:name":"Benito Puch S.c.",
    "wof:placetype":"venue"
},
  "geometry": {"coordinates":[0.3334560096,41.5201873779],"type":"Point"}
}