{
  "type": "Feature",
  "properties": {
    "addr:full":"Calle de Colon, 8 Bejar Salamanca 37700",
    "addr:housenumber":"8",
    "addr:postcode":"37700",
    "addr:street":"Calle De Colon",
    "iso:country":"ES",
    "sg:address":"Calle de Colon, 8",
    "sg:city":"Bejar",
    "sg:orig_category":"Abogados",
    "sg:phone":"+34 923 40 26 95",
    "sg:postcode":"37700",
    "sg:province":"Salamanca",
    "wof:name":"Rodriguez-arias Sanchez Geronimo",
    "wof:placetype":"venue"
},
  "geometry": {"coordinates":[-5.7708086967,40.3865242004],"type":"Point"}
}