{
  "type": "Feature",
  "properties": {
    "addr:full":"Ctra. Circunvalacion, S/n Torremolinos M\u00e1laga 29620",
    "addr:postcode":"29620",
    "addr:street":"Ctra. Circunvalacion S / N;Ma\u0301Laga",
    "iso:country":"ES",
    "sg:address":"Ctra. Circunvalacion, S/n",
    "sg:city":"Torremolinos",
    "sg:orig_category":"Acondicionamiento De Terrenos Para Deporte Y Juegos",
    "sg:phone":"+34 952 38 59 00",
    "sg:postcode":"29620",
    "sg:province":"M\u00e1laga",
    "wof:name":"Ayuntamiento De Torremolinos",
    "wof:placetype":"venue"
},
  "geometry": {"coordinates":[-4.5118942261,36.6120033264],"type":"Point"}
}