{
  "type": "Feature",
  "properties": {
    "iso:country":"ES",
    "sg:address":"Carrer de Santa Marta, 44",
    "sg:city":"Mataro",
    "sg:orig_category":"Lencer\u00cda Femenina, Corseter\u00cda, Trajes De Ba\u00d1o (al Por Menor)",
    "sg:phone":"+34 937 90 13 24",
    "sg:postcode":"08302",
    "sg:province":"Barcelona",
    "wof:name":"Textil Zedesa",
    "wof:placetype":"venue"
},
  "geometry": {"coordinates":[2.4435970783,41.5374641418],"type":"Point"}
}