{
  "type": "Feature",
  "properties": {
    "addr:full":"Calle de Ramon Maria Aller, 13 Coru\u00d1a A Coru\u00f1a 15010",
    "addr:housenumber":"13",
    "addr:postcode":"15010",
    "addr:street":"Calle De Ramon Maria Aller;Corun\u0303A",
    "iso:country":"ES",
    "sg:address":"Calle de Ramon Maria Aller, 13",
    "sg:city":"Coru\u00d1a",
    "sg:orig_category":"Chapister\u00cda",
    "sg:phone":"+34 981 26 06 65",
    "sg:postcode":"15010",
    "sg:province":"A Coru\u00f1a",
    "wof:name":"Sucesores De Sobrino Roel S.l.",
    "wof:placetype":"venue"
},
  "geometry": {"coordinates":[-8.4191379547,43.362663269],"type":"Point"}
}