{
  "type": "Feature",
  "properties": {
    "iso:country":"ES",
    "sg:address":"Calle de Pedro De Axular, 6",
    "sg:city":"Elizondo",
    "sg:orig_category":"Enfermeras: Consultas, Atenci\u00d3n A Domicilio",
    "sg:phone":"+34 948 58 02 74",
    "sg:postcode":"31700",
    "sg:province":"Navarra",
    "wof:name":"Mihura Arsuaga Maria Bernadeta",
    "wof:placetype":"venue"
},
  "geometry": {"coordinates":[-1.5185049772,43.1475715637],"type":"Point"}
}