{
  "type": "Feature",
  "properties": {
    "addr:full":"Carrer de Sant Llorenc, 9 Reus Tarragona 43201",
    "addr:housenumber":"9",
    "addr:postcode":"43201",
    "addr:street":"Carrer De Sant Llorenc",
    "iso:country":"ES",
    "sg:address":"Carrer de Sant Llorenc, 9",
    "sg:city":"Reus",
    "sg:orig_category":"Institutos De Belleza",
    "sg:phone":"+34 977 31 11 07",
    "sg:postcode":"43201",
    "sg:province":"Tarragona",
    "wof:name":"Aguade Bernal Ana Maria",
    "wof:placetype":"venue"
},
  "geometry": {"coordinates":[1.1058852673,41.1555557251],"type":"Point"}
}