{
  "type": "Feature",
  "properties": {
    "iso:country":"ES",
    "sg:address":"Calle de Sagasta, 82",
    "sg:city":"Palmas De Gran Canaria",
    "sg:orig_category":"Bazares, Art\u00cdculos De Limpieza Y De Cocina (al Por Menor)",
    "sg:phone":"+34 928 27 47 15",
    "sg:postcode":"35008",
    "sg:province":"Las Palmas",
    "wof:name":"Khoury Khoury Santiago Issa",
    "wof:placetype":"venue"
},
  "geometry": {"coordinates":[-15.4302587509,28.1470489502],"type":"Point"}
}