{
  "type": "Feature",
  "properties": {
    "iso:country":"ES",
    "sg:address":"Rua Torrente Ballester, S/n",
    "sg:city":"Ramallosa",
    "sg:classifiers":[
        {
            "category":"Taxi",
            "type":"Transportation"
        }
    ],
    "sg:phone":"+34 986 35 00 09",
    "sg:postcode":"36379",
    "sg:province":"Pontevedra",
    "wof:name":"Taxis Autonomos De Nigran-a Ramallosa",
    "wof:placetype":"venue"
},
  "geometry": {"coordinates":[-8.8131189346,42.1164932251],"type":"Point"}
}