{
  "type": "Feature",
  "properties": {
    "addr:full":"Calle de Republica De Nicaragua, 11 Barrio De Pinilla Le\u00f3n 24010",
    "addr:housenumber":"11",
    "addr:postcode":"24010",
    "addr:street":"Calle De Republica De Nicaragua",
    "iso:country":"ES",
    "sg:address":"Calle de Republica De Nicaragua, 11",
    "sg:city":"Barrio De Pinilla",
    "sg:orig_category":"Iglesia Cat\u00d3lica",
    "sg:phone":"+34 987 22 88 53",
    "sg:postcode":"24010",
    "sg:province":"Le\u00f3n",
    "wof:name":"Franciscanas Misioneras De La Madre Del Divino Pastor Provincia De Leon Curia Provincial",
    "wof:placetype":"venue"
},
  "geometry": {"coordinates":[-6.0865697861,42.1935501099],"type":"Point"}
}