{
  "type": "Feature",
  "properties": {
    "addr:full":"Avda Cesar Augusto, 70 Zaragoza Zaragoza 50003",
    "addr:housenumber":"70",
    "addr:postcode":"50003",
    "addr:street":"Avda Cesar Augusto",
    "iso:country":"ES",
    "sg:address":"Avda Cesar Augusto, 70",
    "sg:city":"Zaragoza",
    "sg:orig_category":"Servicios De Telecomunicaciones",
    "sg:phone":"+34 976 20 32 00",
    "sg:postcode":"50003",
    "sg:province":"Zaragoza",
    "wof:name":"Eritel 2001 S.l.",
    "wof:placetype":"venue"
},
  "geometry": {"coordinates":[-0.8839309812,41.6549682617],"type":"Point"}
}