{
  "type": "Feature",
  "properties": {
    "iso:country":"ES",
    "sg:address":"Calle de Bartolome De Urdinso, 4",
    "sg:city":"Irun",
    "sg:orig_category":"Bazares, Art\u00cdculos De Limpieza Y De Cocina (al Por Menor)",
    "sg:phone":"+34 943 66 03 38",
    "sg:postcode":"20301",
    "sg:province":"Guip\u00f9zcoa",
    "wof:name":"Autos Goikar S.l.u.",
    "wof:placetype":"venue"
},
  "geometry": {"coordinates":[-1.8007115126,43.3423576355],"type":"Point"}
}