{
  "type": "Feature",
  "properties": {
    "iso:country":"ES",
    "sg:address":"Carr Santa Clara, 3",
    "sg:city":"Canals",
    "sg:orig_category":"Asesor\u00cda De Formaci\u00d3n Y Gesti\u00d3n De Personal",
    "sg:phone":"+34 962 24 32 14",
    "sg:postcode":"46650",
    "sg:province":"Valencia",
    "wof:name":"Sindicato Independiente Centro De Formacion",
    "wof:placetype":"venue"
},
  "geometry": {"coordinates":[-0.5834860206,38.9604911804],"type":"Point"}
}