{
  "type": "Feature",
  "properties": {
    "addr:full":"Avda Canela (de La), 40 Estepa Sevilla 41560",
    "addr:housenumber":"40",
    "addr:postcode":"41560",
    "addr:street":"Avda Canela De La;Sevilla",
    "iso:country":"ES",
    "sg:address":"Avda Canela (de La), 40",
    "sg:city":"Estepa",
    "sg:orig_category":"Materias Pl\u00c1sticas: Productos Para Industria Y Agricultura (fabricaci\u00d3n, Al Por Mayor)",
    "sg:phone":"+34 955 91 24 93",
    "sg:postcode":"41560",
    "sg:province":"Sevilla",
    "wof:name":"Moldplastica S.l",
    "wof:placetype":"venue"
},
  "geometry": {"coordinates":[-4.8818941116,37.3000946045],"type":"Point"}
}