{
  "type": "Feature",
  "properties": {
    "iso:country":"ES",
    "sg:address":"Calle de Ayuntamiento, 13",
    "sg:city":"Canicosa De La Sierra",
    "sg:orig_category":"Negocio De Madera",
    "sg:phone":"+34 947 39 16 07",
    "sg:postcode":"09692",
    "sg:province":"Burgos",
    "wof:name":"Maderas Campo Benito S.l.",
    "wof:placetype":"venue"
},
  "geometry": {"coordinates":[-3.0436682701,41.9382705688],"type":"Point"}
}