{
  "type": "Feature",
  "properties": {
    "iso:country":"ES",
    "sg:address":"Carrer de Proven\u00c7a, 383",
    "sg:city":"Barcelona",
    "sg:orig_category":"Art\u00cdculos De Regalo (al Por Menor)",
    "sg:phone":"+34 934 57 90 24",
    "sg:postcode":"08025",
    "sg:province":"Barcelona",
    "wof:name":"Pereira Martinez Jose Luis",
    "wof:placetype":"venue"
},
  "geometry": {"coordinates":[2.1711258888,41.4021492004],"type":"Point"}
}