{
  "type": "Feature",
  "properties": {
    "iso:country":"ES",
    "sg:address":"Cami Riera, 10",
    "sg:city":"Riudarenes",
    "sg:orig_category":"M\u00c1quinas De Jardiner\u00cda",
    "sg:phone":"+34 972 16 85 76",
    "sg:postcode":"17421",
    "sg:province":"Girona",
    "wof:name":"Roca Masegur Lluis",
    "wof:placetype":"venue"
},
  "geometry": {"coordinates":[2.7224509716,41.8221893311],"type":"Point"}
}