{
  "type": "Feature",
  "properties": {
    "addr:full":"Calle de General Chamorro Martinez, 3 Sevilla Sevilla 41008",
    "addr:housenumber":"3",
    "addr:postcode":"41008",
    "addr:street":"Calle De General Chamorro Martinez",
    "iso:country":"ES",
    "sg:address":"Calle de General Chamorro Martinez, 3",
    "sg:city":"Sevilla",
    "sg:orig_category":"Peluquer\u00cdas, Peluquer\u00cda Mixta",
    "sg:phone":"+34 954 36 02 98",
    "sg:postcode":"41008",
    "sg:province":"Sevilla",
    "wof:name":"Moreno Perez Gloria",
    "wof:placetype":"venue"
},
  "geometry": {"coordinates":[-5.9714078903,37.4071884155],"type":"Point"}
}