{
  "type": "Feature",
  "properties": {
    "iso:country":"ES",
    "sg:address":"Calle de Juan Florez, 3",
    "sg:city":"Coru\u00d1a",
    "sg:orig_category":"Bazares, Art\u00cdculos De Limpieza Y De Cocina (al Por Menor)",
    "sg:phone":"+34 981 20 57 77",
    "sg:postcode":"15004",
    "sg:province":"A Coru\u00f1a",
    "sg:website":"www.zarahome.com",
    "wof:name":"Zara Home Espa\u00f1a S.a.",
    "wof:placetype":"venue"
},
  "geometry": {"coordinates":[-8.4116697311,43.3660888672],"type":"Point"}
}