{
  "type": "Feature",
  "properties": {
    "iso:country":"ES",
    "sg:address":"Avda Orihuela, 49",
    "sg:city":"Redovan",
    "sg:orig_category":"Agencias Y Agentes Comerciales, Representantes",
    "sg:phone":"+34 966 75 49 32",
    "sg:postcode":"03370",
    "sg:province":"Alicante",
    "wof:name":"Centrocasa 98s.l.",
    "wof:placetype":"venue"
},
  "geometry": {"coordinates":[-0.9024689794,38.1110725403],"type":"Point"}
}