{
  "type": "Feature",
  "properties": {
    "addr:full":"Blas Infante, 2 Montoro C\u00f3rdoba 14600",
    "addr:housenumber":"2",
    "addr:postcode":"14600",
    "addr:street":"Blas Infante;Co\u0301Rdoba",
    "iso:country":"ES",
    "sg:address":"Blas Infante, 2",
    "sg:city":"Montoro",
    "sg:orig_category":"Art\u00cdculos De Decoraci\u00d3n",
    "sg:phone":"+34 957 16 28 21",
    "sg:postcode":"14600",
    "sg:province":"C\u00f3rdoba",
    "wof:name":"Aneva Decoracion S.l.",
    "wof:placetype":"venue"
},
  "geometry": {"coordinates":[-4.3824696541,38.0189170837],"type":"Point"}
}