{
  "type": "Feature",
  "properties": {
    "iso:country":"ES",
    "sg:address":"Calle de Marcelino Champagnat, 35",
    "sg:city":"Villanueva Rio Y Minas",
    "sg:classifiers":[
        {
            "category":"Taxi",
            "type":"Transportation"
        }
    ],
    "sg:phone":"+34 954 74 79 55",
    "sg:postcode":"41350",
    "sg:province":"Sevilla",
    "wof:name":"Galvez Quesada Juan Pedro",
    "wof:placetype":"venue"
},
  "geometry": {"coordinates":[-5.7085728645,37.6549758911],"type":"Point"}
}