{
  "type": "Feature",
  "properties": {
    "addr:full":"Carr Diputacio, 1 Ponts Lleida 25740",
    "addr:housenumber":"1",
    "addr:postcode":"25740",
    "addr:street":"Carr Diputacio",
    "iso:country":"ES",
    "sg:address":"Carr Diputacio, 1",
    "sg:city":"Ponts",
    "sg:classifiers":[
        {
            "category":"Taxi",
            "type":"Transportation"
        }
    ],
    "sg:phone":"+34 973 46 02 92",
    "sg:postcode":"25740",
    "sg:province":"Lleida",
    "wof:name":"Arauz Sole Jose Luis",
    "wof:placetype":"venue"
},
  "geometry": {"coordinates":[1.1833652258,41.9150543213],"type":"Point"}
}