{
  "type": "Feature",
  "properties": {
    "addr:full":"Calle de Ruben Dario, 6 Utrera Sevilla 41710",
    "addr:housenumber":"6",
    "addr:postcode":"41710",
    "addr:street":"Calle De Ruben Dario",
    "iso:country":"ES",
    "sg:address":"Calle de Ruben Dario, 6",
    "sg:city":"Utrera",
    "sg:orig_category":"M\u00c9dicos: Estomatolog\u00cda",
    "sg:phone":"+34 955 86 53 81",
    "sg:postcode":"41710",
    "sg:province":"Sevilla",
    "wof:name":"Marrero Novas Alcenia",
    "wof:placetype":"venue"
},
  "geometry": {"coordinates":[-5.7908830643,37.1811218262],"type":"Point"}
}