{
  "type": "Feature",
  "properties": {
    "addr:full":"Carr Lleida, 26 Preixana Lleida 25263",
    "addr:housenumber":"26",
    "addr:postcode":"25263",
    "addr:street":"Carr Lleida",
    "iso:country":"ES",
    "sg:address":"Carr Lleida, 26",
    "sg:city":"Preixana",
    "sg:orig_category":"Conservas De Carnes (fabricaci\u00d3n, Al Por Mayor)",
    "sg:phone":"+34 973 32 04 68",
    "sg:postcode":"25263",
    "sg:province":"Lleida",
    "wof:name":"Delicies De L'anec S.l.",
    "wof:placetype":"venue"
},
  "geometry": {"coordinates":[1.0368419886,41.607208252],"type":"Point"}
}