{
  "type": "Feature",
  "properties": {
    "iso:country":"ES",
    "sg:address":"Carrer de Pedraforca, 19",
    "sg:city":"S. Fruitos Bages",
    "sg:classifiers":[
        {
            "category":"Casinos & Gambling",
            "type":"Entertainment"
        }
    ],
    "sg:phone":"+34 938 74 54 08",
    "sg:postcode":"08272",
    "sg:province":"Barcelona",
    "sg:tags":[
        "locale",
        "de",
        "juego"
    ],
    "wof:name":"Mega Parc S.l.",
    "wof:placetype":"venue"
},
  "geometry": {"coordinates":[1.8605569601,41.7463645935],"type":"Point"}
}