{
  "type": "Feature",
  "properties": {
    "addr:full":"Calle de Goya, 21 Sevilla Sevilla 41005",
    "addr:housenumber":"21",
    "addr:postcode":"41005",
    "addr:street":"Calle De Goya",
    "iso:country":"ES",
    "sg:address":"Calle de Goya, 21",
    "sg:city":"Sevilla",
    "sg:orig_category":"Coches Y Camiones (caja De Cambios, Embrague Y Frenos)",
    "sg:phone":"+34 954 57 08 96",
    "sg:postcode":"41005",
    "sg:province":"Sevilla",
    "wof:name":"Frenos Celvi S.l.",
    "wof:placetype":"venue"
},
  "geometry": {"coordinates":[-5.9689092636,37.3849105835],"type":"Point"}
}