{
  "type": "Feature",
  "properties": {
    "addr:full":"Calle de Isaac Peral, 18 Alfafar Valencia 46910",
    "addr:housenumber":"18",
    "addr:postcode":"46910",
    "addr:street":"Calle De Isaac Peral",
    "iso:country":"ES",
    "sg:address":"Calle de Isaac Peral, 18",
    "sg:city":"Alfafar",
    "sg:orig_category":"Art\u00cdculos Funerarios (al Por Menor)",
    "sg:phone":"+34 963 75 76 33",
    "sg:postcode":"46910",
    "sg:province":"Valencia",
    "wof:name":"Bort Mico Francisco",
    "wof:placetype":"venue"
},
  "geometry": {"coordinates":[-0.3912169933,39.4225692749],"type":"Point"}
}