{
  "type": "Feature",
  "properties": {
    "addr:full":"Cami Mig, S/n Vilassar Barcelona 08340",
    "addr:postcode":"08340",
    "addr:street":"Mig S / N Vilassar Barcelona",
    "iso:country":"ES",
    "sg:address":"Cami Mig, S/n",
    "sg:city":"Vilassar",
    "sg:orig_category":"Construcci\u00d3n Mec\u00c1nica",
    "sg:phone":"+34 937 59 24 90",
    "sg:postcode":"08340",
    "sg:province":"Barcelona",
    "wof:name":"Antoni Carles S. A.",
    "wof:placetype":"venue"
},
  "geometry": {"coordinates":[2.3486421108,41.4935569763],"type":"Point"}
}