{
  "type": "Feature",
  "properties": {
    "iso:country":"ES",
    "sg:address":"Ctra Navalpino, Km. 0003,0",
    "sg:city":"Toledo",
    "sg:orig_category":"Molduras, Junquillos, Listones Y Molduras Perforadas",
    "sg:phone":"+34 925 21 40 51",
    "sg:postcode":"45004",
    "sg:province":"Toledo",
    "wof:name":"Pinilla Vidales Jose Maria",
    "wof:placetype":"venue"
},
  "geometry": {"coordinates":[-4.0412340164,39.8600196838],"type":"Point"}
}