{
  "type": "Feature",
  "properties": {
    "iso:country":"ES",
    "sg:address":"Po. Jose Maria Lacarra, 1",
    "sg:city":"Iru\u00f1a",
    "sg:orig_category":"Inmobiliaria (agencias)",
    "sg:phone":"+34 948 19 80 55",
    "sg:postcode":"31008",
    "sg:province":"Navarra",
    "wof:name":"Zyf Promocion Y Gestion Inmobiliaria S.a.",
    "wof:placetype":"venue"
},
  "geometry": {"coordinates":[-1.6687812805,42.8102302551],"type":"Point"}
}