{
  "type": "Feature",
  "properties": {
    "iso:country":"ES",
    "sg:address":"Pol Ind Plasencia, S/n",
    "sg:city":"Plasencia",
    "sg:orig_category":"Art\u00cdculos De Madera (fabricaci\u00d3n Y Al Por Mayor)",
    "sg:phone":"+34 927 41 18 10",
    "sg:postcode":"10600",
    "sg:province":"C\u00e1ceres",
    "wof:name":"Muebles Garlopa S.a.l.",
    "wof:placetype":"venue"
},
  "geometry": {"coordinates":[-6.0649971962,40.014591217],"type":"Point"}
}