{
  "type": "Feature",
  "properties": {
    "iso:country":"ES",
    "sg:address":"Calle de San Jose (de), 10",
    "sg:city":"Colmenar Viejo",
    "sg:orig_category":"Negocio De Materiales De Construcci\u00d3n",
    "sg:phone":"+34 918 45 27 45",
    "sg:postcode":"28770",
    "sg:province":"Madrid",
    "wof:name":"Rico Martin Armando",
    "wof:placetype":"venue"
},
  "geometry": {"coordinates":[-3.7670080662,40.6624908447],"type":"Point"}
}