{
  "type": "Feature",
  "properties": {
    "addr:full":"Carrer de Canonge Tarongi, 14 Coll De'n Rabassa Islas Baleares 07007",
    "addr:housenumber":"14",
    "addr:postcode":"07007",
    "addr:street":"Carrer De Canonge Tarongi",
    "iso:country":"ES",
    "sg:address":"Carrer de Canonge Tarongi, 14",
    "sg:city":"Coll De'n Rabassa",
    "sg:orig_category":"Farmacias",
    "sg:phone":"+34 971 26 34 83",
    "sg:postcode":"07007",
    "sg:province":"Islas Baleares",
    "wof:name":"Guijarro Perez Angel",
    "wof:placetype":"venue"
},
  "geometry": {"coordinates":[2.9117100239,39.6136398315],"type":"Point"}
}