{
  "type": "Feature",
  "properties": {
    "addr:full":"Plaz Progreso, 7 Badajoz Badajoz 06007",
    "addr:housenumber":"7",
    "addr:postcode":"06007",
    "addr:street":"Progreso",
    "iso:country":"ES",
    "sg:address":"Plaz Progreso, 7",
    "sg:city":"Badajoz",
    "sg:orig_category":"Estancos",
    "sg:phone":"+34 924 27 50 65",
    "sg:postcode":"06007",
    "sg:province":"Badajoz",
    "wof:name":"Carretero Miron Maria Rosa",
    "wof:placetype":"venue"
},
  "geometry": {"coordinates":[-6.9809298515,38.8909606934],"type":"Point"}
}