{
  "type": "Feature",
  "properties": {
    "addr:full":"Calle de Cristobal Colon, 2 Pantoja Toledo 45290",
    "addr:housenumber":"2",
    "addr:postcode":"45290",
    "addr:street":"Calle De Cristobal Colon",
    "iso:country":"ES",
    "sg:address":"Calle de Cristobal Colon, 2",
    "sg:city":"Pantoja",
    "sg:orig_category":"Cerrajer\u00cda, Ferrallista",
    "sg:phone":"+34 925 55 41 60",
    "sg:postcode":"45290",
    "sg:province":"Toledo",
    "wof:name":"Garcia Martin Angel",
    "wof:placetype":"venue"
},
  "geometry": {"coordinates":[-3.835474968,40.0481109619],"type":"Point"}
}