{
  "type": "Feature",
  "properties": {
    "iso:country":"ES",
    "sg:address":"Aptdo Sin Datos, 0",
    "sg:city":"Vigo",
    "sg:orig_category":"Abogados",
    "sg:phone":"+34 986 22 86 72",
    "sg:postcode":"36202",
    "sg:province":"Pontevedra",
    "wof:name":"Alvarez Garcia Ricardo",
    "wof:placetype":"venue"
},
  "geometry": {"coordinates":[-8.7274694443,42.237071991],"type":"Point"}
}