{
  "type": "Feature",
  "properties": {
    "addr:full":"Ctra. Eivissa-s. Joan, S/n S. Lloren\u00e7 Balafia Islas Baleares 07812",
    "addr:postcode":"07812",
    "addr:street":"Ctra. Eivissa-S. Joan S / N S. Llorenc\u0327;Islas",
    "iso:country":"ES",
    "sg:address":"Ctra. Eivissa-s. Joan, S/n",
    "sg:city":"S. Lloren\u00e7 Balafia",
    "sg:classifiers":[
        {
            "category":"Professional",
            "subcategory":"Management & Consulting",
            "type":"Services"
        }
    ],
    "sg:phone":"+34 971 32 50 71",
    "sg:postcode":"07812",
    "sg:province":"Islas Baleares",
    "sg:tags":[
        "asesor\u00cda",
        "en",
        "marketing"
    ],
    "wof:name":"Pflueger  Hans",
    "wof:placetype":"venue"
},
  "geometry": {"coordinates":[1.4762049913,39.0312309265],"type":"Point"}
}