{
  "type": "Feature",
  "properties": {
    "iso:country":"ES",
    "sg:address":"Calle de Panaderos, 18",
    "sg:city":"Granada",
    "sg:orig_category":"Molduras, Junquillos, Listones Y Molduras Perforadas",
    "sg:phone":"+34 958 27 34 42",
    "sg:postcode":"18010",
    "sg:province":"Granada",
    "wof:name":"Kissami  Ahmed",
    "wof:placetype":"venue"
},
  "geometry": {"coordinates":[-3.5924780369,37.1824684143],"type":"Point"}
}