{
  "type": "Feature",
  "properties": {
    "addr:full":"Carrer de Marina, 91 Barcelona Barcelona 08018",
    "addr:housenumber":"91",
    "addr:postcode":"08018",
    "addr:street":"Carrer De Marina",
    "iso:country":"ES",
    "sg:address":"Carrer de Marina, 91",
    "sg:city":"Barcelona",
    "sg:orig_category":"Cajas De Ahorro",
    "sg:phone":"+34 933 09 41 45",
    "sg:postcode":"08018",
    "sg:province":"Barcelona",
    "sg:website":"www.lacaixa.es",
    "wof:name":"Caixa D'estalvis I Pensions De Barcelona",
    "wof:placetype":"venue"
},
  "geometry": {"coordinates":[2.1880209446,41.3937492371],"type":"Point"}
}