{
  "type": "Feature",
  "properties": {
    "addr:full":"Calle de Rabadanes, 23 Rambla C\u00f3rdoba 14540",
    "addr:housenumber":"23",
    "addr:postcode":"14540",
    "addr:street":"Calle De Rabadanes;Rambla Co\u0301Rdoba",
    "iso:country":"ES",
    "sg:address":"Calle de Rabadanes, 23",
    "sg:city":"Rambla",
    "sg:orig_category":"Venta Al Preg\u00d3n",
    "sg:phone":"+34 957 68 43 77",
    "sg:postcode":"14540",
    "sg:province":"C\u00f3rdoba",
    "wof:name":"Zamorano Sotomayor Tomas",
    "wof:placetype":"venue"
},
  "geometry": {"coordinates":[-4.7370972633,37.6075706482],"type":"Point"}
}