{
  "type": "Feature",
  "properties": {
    "addr:full":"Calle de Bizkaia, 27 Barakaldo Vizcaya 48901",
    "addr:housenumber":"27",
    "addr:postcode":"48901",
    "addr:street":"Calle De Bizkaia",
    "iso:country":"ES",
    "sg:address":"Calle de Bizkaia, 27",
    "sg:city":"Barakaldo",
    "sg:orig_category":"Ropa Para Se\u00d1oras (al Por Menor)",
    "sg:phone":"+34 944 38 70 17",
    "sg:postcode":"48901",
    "sg:province":"Vizcaya",
    "wof:name":"Blanca Enrique Moreno",
    "wof:placetype":"venue"
},
  "geometry": {"coordinates":[-2.9866189957,43.2946128845],"type":"Point"}
}