{
  "type": "Feature",
  "properties": {
    "addr:full":"Avgd Segre, 10 Lleida Lleida 25007",
    "addr:housenumber":"10",
    "addr:postcode":"25007",
    "addr:street":"Avgd Segre",
    "iso:country":"ES",
    "sg:address":"Avgd Segre, 10",
    "sg:city":"Lleida",
    "sg:orig_category":"M\u00c9dicos: Nefrolog\u00cda",
    "sg:phone":"+34 973 22 24 92",
    "sg:postcode":"25007",
    "sg:province":"Lleida",
    "wof:name":"Borras Sans Mercedes",
    "wof:placetype":"venue"
},
  "geometry": {"coordinates":[0.6335679889,41.6172065735],"type":"Point"}
}