{
  "type": "Feature",
  "properties": {
    "addr:full":"Calle de Hernan Cortes, 13 Puerto Mazarron Murcia 30860",
    "addr:housenumber":"13",
    "addr:postcode":"30860",
    "addr:street":"Calle De Hernan Cortes",
    "iso:country":"ES",
    "sg:address":"Calle de Hernan Cortes, 13",
    "sg:city":"Puerto Mazarron",
    "sg:orig_category":"Inmobiliaria (agencias)",
    "sg:phone":"+34 968 59 45 30",
    "sg:postcode":"30860",
    "sg:province":"Murcia",
    "wof:name":"Sunset Casas S.l.",
    "wof:placetype":"venue"
},
  "geometry": {"coordinates":[-1.2610340118,37.5667037964],"type":"Point"}
}