{
  "type": "Feature",
  "properties": {
    "iso:country":"ES",
    "sg:address":"Calle de Puerto De Canfranc, 17",
    "sg:city":"Madrid",
    "sg:orig_category":"Servicio De Salud",
    "sg:phone":"+34 913 28 70 95",
    "sg:postcode":"28038",
    "sg:province":"Madrid",
    "wof:name":"Diaz Fernandez Juan",
    "wof:placetype":"venue"
},
  "geometry": {"coordinates":[-3.6632480621,40.3973312378],"type":"Point"}
}