{
  "type": "Feature",
  "properties": {
    "addr:full":"Avda Aresti Gabriel, 4 Bilbao Vizcaya 48004",
    "addr:housenumber":"4",
    "addr:postcode":"48004",
    "addr:street":"Avda Aresti Gabriel",
    "iso:country":"ES",
    "sg:address":"Avda Aresti Gabriel, 4",
    "sg:city":"Bilbao",
    "sg:orig_category":"M\u00c9dicos: Estomatolog\u00cda",
    "sg:phone":"+34 944 11 34 30",
    "sg:postcode":"48004",
    "sg:province":"Vizcaya",
    "wof:name":"Otaola Pereira Caridad",
    "wof:placetype":"venue"
},
  "geometry": {"coordinates":[-2.907533884,43.2533149719],"type":"Point"}
}