{
  "type": "Feature",
  "properties": {
    "iso:country":"ES",
    "sg:address":"Calle de Caleruega, 12",
    "sg:city":"Madrid",
    "sg:orig_category":"Calderer\u00cda",
    "sg:phone":"+34 917 67 02 38",
    "sg:postcode":"28033",
    "sg:province":"Madrid",
    "wof:name":"Instalaciones Prefabricadas S.l.",
    "wof:placetype":"venue"
},
  "geometry": {"coordinates":[-3.6703288555,40.4783096313],"type":"Point"}
}