{
  "type": "Feature",
  "properties": {
    "addr:full":"Avda Rodriguez De Ledesma, 10 Caceres C\u00e1ceres 10001",
    "addr:housenumber":"10",
    "addr:postcode":"10001",
    "addr:street":"Avda Rodriguez De Ledesma;Ca\u0301Ceres",
    "iso:country":"ES",
    "sg:address":"Avda Rodriguez De Ledesma, 10",
    "sg:city":"Caceres",
    "sg:orig_category":"Diplomas Diversos",
    "sg:phone":"+34 927 23 07 83",
    "sg:postcode":"10001",
    "sg:province":"C\u00e1ceres",
    "wof:name":"Solis Bermejo Fabriciano",
    "wof:placetype":"venue"
},
  "geometry": {"coordinates":[-6.3836688995,39.4704971313],"type":"Point"}
}