{
  "type": "Feature",
  "properties": {
    "iso:country":"ES",
    "sg:address":"Calle de Portugal, 26",
    "sg:city":"Fuenlabrada",
    "sg:orig_category":"Empresas De Portes Y Mensajer\u00cda",
    "sg:phone":"+34 916 07 92 88",
    "sg:postcode":"28943",
    "sg:province":"Madrid",
    "wof:name":"Vera Mansilla Jose Claudio",
    "wof:placetype":"venue"
},
  "geometry": {"coordinates":[-3.8087990284,40.2808113098],"type":"Point"}
}