{
  "type": "Feature",
  "properties": {
    "iso:country":"ES",
    "sg:address":"Pase Pintor Martinez Vazquez, 2",
    "sg:city":"Arenas San Pedro",
    "sg:orig_category":"Quincaller\u00cda (al Por Menor)",
    "sg:phone":"+34 920 37 14 14",
    "sg:postcode":"05400",
    "sg:province":"\u00c1vila",
    "wof:name":"Luis Perez Ferrero S.l.",
    "wof:placetype":"venue"
},
  "geometry": {"coordinates":[-5.0860438347,40.2103500366],"type":"Point"}
}