{
  "type": "Feature",
  "properties": {
    "addr:full":"Calle de Valle, 30 Valencia Ventoso Badajoz 06330",
    "addr:housenumber":"30",
    "addr:postcode":"06330",
    "addr:street":"Calle De Valle",
    "iso:country":"ES",
    "sg:address":"Calle de Valle, 30",
    "sg:city":"Valencia Ventoso",
    "sg:orig_category":"Confecci\u00d3n (fabricaci\u00d3n, Al Por Mayor)",
    "sg:phone":"+34 924 56 21 55",
    "sg:postcode":"06330",
    "sg:province":"Badajoz",
    "wof:name":"Baltasar Delgado Nieves",
    "wof:placetype":"venue"
},
  "geometry": {"coordinates":[-6.4714789391,38.2653198242],"type":"Point"}
}