{
  "type": "Feature",
  "properties": {
    "iso:country":"ES",
    "sg:address":"Calle de Miranda, 3",
    "sg:city":"Burgos",
    "sg:orig_category":"Cl\u00cdnicas Dentales",
    "sg:phone":"+34 947 27 68 47",
    "sg:postcode":"09002",
    "sg:province":"Burgos",
    "wof:name":"Perez Fernandez Ramon",
    "wof:placetype":"venue"
},
  "geometry": {"coordinates":[-3.7001318932,42.3382797241],"type":"Point"}
}