{
  "type": "Feature",
  "properties": {
    "addr:full":"Plaz Antiga Moreria, 3 Sagunt Valencia 46500",
    "addr:housenumber":"3",
    "addr:postcode":"46500",
    "iso:country":"ES",
    "sg:address":"Plaz Antiga Moreria, 3",
    "sg:city":"Sagunt",
    "sg:orig_category":"Procuradores",
    "sg:phone":"+34 962 65 09 08",
    "sg:postcode":"46500",
    "sg:province":"Valencia",
    "wof:name":"Gomis Sanchis Rosa Maria",
    "wof:placetype":"venue"
},
  "geometry": {"coordinates":[-0.2733780146,39.6799430847],"type":"Point"}
}