{
  "type": "Feature",
  "properties": {
    "addr:full":"Calle de Pintor Murillo, 1 Juan Xxiii Las Palmas 35400",
    "addr:housenumber":"1",
    "addr:postcode":"35400",
    "addr:street":"Calle De Pintor Murillo",
    "iso:country":"ES",
    "sg:address":"Calle de Pintor Murillo, 1",
    "sg:city":"Juan Xxiii",
    "sg:orig_category":"Empresas De Pintura Y Revestimientos",
    "sg:phone":"+34 928 63 39 89",
    "sg:postcode":"35400",
    "sg:province":"Las Palmas",
    "wof:name":"Suarez Gonzalez Juan Javier",
    "wof:placetype":"venue"
},
  "geometry": {"coordinates":[-15.515039444,28.1141109467],"type":"Point"}
}