{
  "type": "Feature",
  "properties": {
    "iso:country":"ES",
    "sg:address":"Calle de Alicante, 38",
    "sg:city":"Puerto",
    "sg:orig_category":"Alimentaci\u00d3n General (al Por Menor)",
    "sg:phone":"+34 962 67 11 38",
    "sg:postcode":"46520",
    "sg:province":"Valencia",
    "wof:name":"Crisol Lazaro Clara",
    "wof:placetype":"venue"
},
  "geometry": {"coordinates":[-0.2266748995,39.6649971008],"type":"Point"}
}