{
  "type": "Feature",
  "properties": {
    "iso:country":"ES",
    "sg:address":"Calle de Sabino Arana, 4",
    "sg:city":"Moreaga",
    "sg:orig_category":"Carnicer\u00cdas, Carnicer\u00cdas",
    "sg:phone":"+34 946 76 12 57",
    "sg:postcode":"48600",
    "sg:province":"Vizcaya",
    "wof:name":"Basa\u00f1ez Bilbao Agapito",
    "wof:placetype":"venue"
},
  "geometry": {"coordinates":[-2.980643034,43.3813362122],"type":"Point"}
}