{
  "type": "Feature",
  "properties": {
    "iso:country":"ES",
    "sg:address":"Avda Teodomiro, 35",
    "sg:city":"Orihuela",
    "sg:orig_category":"Florister\u00cdas",
    "sg:phone":"+34 966 74 42 02",
    "sg:postcode":"03300",
    "sg:province":"Alicante",
    "wof:name":"Pardines Ferrandez Jesus",
    "wof:placetype":"venue"
},
  "geometry": {"coordinates":[-0.9446550012,38.0796127319],"type":"Point"}
}