{
  "type": "Feature",
  "properties": {
    "addr:full":"Rua Rosalia De Castro, 11 Carballi\u00f1o Ourense 32500",
    "addr:housenumber":"11",
    "addr:postcode":"32500",
    "addr:street":"Rua Rosalia De Castro",
    "iso:country":"ES",
    "sg:address":"Rua Rosalia De Castro, 11",
    "sg:city":"Carballi\u00f1o",
    "sg:orig_category":"Ense\u00d1anza Variada",
    "sg:phone":"+34 988 27 15 03",
    "sg:postcode":"32500",
    "sg:province":"Ourense",
    "wof:name":"C.e Logos Carballi\u00d1o,s.l",
    "wof:placetype":"venue"
},
  "geometry": {"coordinates":[-8.0773029327,42.4310302734],"type":"Point"}
}