{
  "type": "Feature",
  "properties": {
    "iso:country":"ES",
    "sg:address":"Av Constitucio, 14",
    "sg:city":"S. Andreu Barca",
    "sg:orig_category":"Ense\u00d1anza, Formaci\u00d3n Profesional: Aprendizaje",
    "sg:phone":"+34 936 53 02 27",
    "sg:postcode":"08740",
    "sg:province":"Barcelona",
    "wof:name":"Ajuntament De Sant Andreu De La Barca",
    "wof:placetype":"venue"
},
  "geometry": {"coordinates":[1.9633054733,41.4512023926],"type":"Point"}
}