{
  "type": "Feature",
  "properties": {
    "iso:country":"ES",
    "sg:address":"Barr Jauregi-yeuri, S/n",
    "sg:city":"Jauregui-yeuri",
    "sg:orig_category":"Galvanizaci\u00d3n, Esta\u00d1ado, Emplomado",
    "sg:phone":"+34 946 31 34 14",
    "sg:postcode":"48390",
    "sg:province":"Vizcaya",
    "wof:name":"Zinbe S. L.",
    "wof:placetype":"venue"
},
  "geometry": {"coordinates":[-2.6983869076,43.2204284668],"type":"Point"}
}