{
  "type": "Feature",
  "properties": {
    "iso:country":"ES",
    "sg:address":"Poli Pol.indust. El Segre, S/n",
    "sg:city":"Lleida",
    "sg:orig_category":"Distribuci\u00d3n De Petr\u00d3leo Y Derivados",
    "sg:phone":"+34 973 21 11 25",
    "sg:postcode":"25191",
    "sg:province":"Lleida",
    "wof:name":"Cedipsa Compa\u00d1ia Espa\u00d1ola Distribuidora De Petroleos S.a.",
    "wof:placetype":"venue"
},
  "geometry": {"coordinates":[0.6831650138,41.5832138062],"type":"Point"}
}