{
  "type": "Feature",
  "properties": {
    "iso:country":"ES",
    "sg:address":"Calle de Urbano Larruzea, S/n",
    "sg:city":"Amorebieta",
    "sg:orig_category":"Teatro, Ballet, Danza (agrupaciones, Compa\u00d1\u00cdas)",
    "sg:phone":"+34 946 30 80 13",
    "sg:postcode":"48340",
    "sg:province":"Vizcaya",
    "sg:website":"www.markeline.com",
    "wof:name":"Grupo De Teatro De Mimo Markeli\u00f1e Mimo Taldea Sociedad Cooperativa Limitada",
    "wof:placetype":"venue"
},
  "geometry": {"coordinates":[-2.7333590984,43.2190704346],"type":"Point"}
}