{
  "type": "Feature",
  "properties": {
    "addr:full":"Carr Pintor Torrent, 7 Ciutadella Menorca Islas Baleares 07760",
    "addr:housenumber":"7",
    "addr:postcode":"07760",
    "addr:street":"Carr Pintor Torrent",
    "iso:country":"ES",
    "sg:address":"Carr Pintor Torrent, 7",
    "sg:city":"Ciutadella Menorca",
    "sg:orig_category":"Calcoman\u00cda, Impresi\u00d3n, Transferencia (transfert)",
    "sg:phone":"+34 971 38 29 20",
    "sg:postcode":"07760",
    "sg:province":"Islas Baleares",
    "wof:name":"Setmanaris I Revistes S.l.",
    "wof:placetype":"venue"
},
  "geometry": {"coordinates":[3.8416149616,40.0027542114],"type":"Point"}
}