{
  "type": "Feature",
  "properties": {
    "iso:country":"ES",
    "sg:address":"Calle de Jose Antonio, 2",
    "sg:city":"Seijo",
    "sg:orig_category":"M\u00c9dicos: Estomatolog\u00cda",
    "sg:phone":"+34 986 62 32 78",
    "sg:postcode":"36740",
    "sg:province":"Pontevedra",
    "wof:name":"Lopez Sousa Maria De Los Angeles",
    "wof:placetype":"venue"
},
  "geometry": {"coordinates":[-8.7447013855,41.9899673462],"type":"Point"}
}