{
  "type": "Feature",
  "properties": {
    "addr:full":"Ctra Castellar, Km. 0019,6 Terrassa Barcelona 08226",
    "addr:postcode":"08226",
    "addr:street":"Ctra Castellar Km. 0019,6",
    "iso:country":"ES",
    "sg:address":"Ctra Castellar, Km. 0019,6",
    "sg:city":"Terrassa",
    "sg:orig_category":"Bebidas",
    "sg:phone":"+34 937 87 00 83",
    "sg:postcode":"08226",
    "sg:province":"Barcelona",
    "sg:website":"www.sanmy.es",
    "wof:name":"Sanmy Sociedad Anonima",
    "wof:placetype":"venue"
},
  "geometry": {"coordinates":[2.0271019936,41.5701217651],"type":"Point"}
}