{
  "type": "Feature",
  "properties": {
    "iso:country":"ES",
    "sg:address":"Calle de Asin Y Palacios, 15",
    "sg:city":"Zaragoza",
    "sg:orig_category":"Tintes (fabricaci\u00d3n, Al Por Mayor)",
    "sg:phone":"+34 976 56 03 43",
    "sg:postcode":"50009",
    "sg:province":"Zaragoza",
    "wof:name":"Aliaga Sebastian Jose Angel",
    "wof:placetype":"venue"
},
  "geometry": {"coordinates":[-0.9055343866,41.6361427307],"type":"Point"}
}