{
  "type": "Feature",
  "properties": {
    "addr:full":"Calle de Fuenterrabia, 15 Donostia-san Sebastian Guip\u00f9zcoa 20005",
    "addr:housenumber":"15",
    "addr:postcode":"20005",
    "addr:street":"Calle De Fuenterrabia",
    "iso:country":"ES",
    "sg:address":"Calle de Fuenterrabia, 15",
    "sg:city":"Donostia-san Sebastian",
    "sg:orig_category":"Ropa Para Se\u00d1oras (al Por Menor)",
    "sg:phone":"+34 943 42 55 67",
    "sg:postcode":"20005",
    "sg:province":"Guip\u00f9zcoa",
    "sg:website":"www.mango.com",
    "wof:name":"Punto Fa S.l.",
    "wof:placetype":"venue"
},
  "geometry": {"coordinates":[-1.9813170433,43.3179473877],"type":"Point"}
}