{
  "type": "Feature",
  "properties": {
    "iso:country":"ES",
    "sg:address":"Calle de Medina Del Campo, 5",
    "sg:city":"Mojados",
    "sg:orig_category":"Laboratorios Y Trabajos De Fotograf\u00cda, V\u00cddeo Y Cine",
    "sg:phone":"+34 983 60 72 49",
    "sg:postcode":"47250",
    "sg:province":"Valladolid",
    "wof:name":"Toquero Ramiro Estefania",
    "wof:placetype":"venue"
},
  "geometry": {"coordinates":[-4.6640129089,41.4278526306],"type":"Point"}
}