{
  "type": "Feature",
  "properties": {
    "addr:full":"Carrer de Galileu, 294 Barcelona Barcelona 08028",
    "addr:housenumber":"294",
    "addr:postcode":"08028",
    "addr:street":"Carrer De Galileu",
    "iso:country":"ES",
    "sg:address":"Carrer de Galileu, 294",
    "sg:city":"Barcelona",
    "sg:orig_category":"Molduras, Junquillos, Listones Y Molduras Perforadas",
    "sg:phone":"+34 934 90 14 59",
    "sg:postcode":"08028",
    "sg:province":"Barcelona",
    "wof:name":"Flores Iba\u00f1ez Maria Del Carmen",
    "wof:placetype":"venue"
},
  "geometry": {"coordinates":[2.1322710514,41.384185791],"type":"Point"}
}