{
  "type": "Feature",
  "properties": {
    "iso:country":"ES",
    "sg:address":"Calle de Charcon (el), 13",
    "sg:city":"Cuesta",
    "sg:orig_category":"Arquitectos",
    "sg:phone":"+34 922 65 62 57",
    "sg:postcode":"38320",
    "sg:province":"Santa Cruz De Tenerife",
    "wof:name":"Estudios De Arquitectura S.l.",
    "wof:placetype":"venue"
},
  "geometry": {"coordinates":[-16.2992019653,28.470790863],"type":"Point"}
}