{
  "type": "Feature",
  "properties": {
    "iso:country":"ES",
    "sg:address":"Pase Juan De La Encina, 2",
    "sg:city":"San Sebastian De Los Reyes",
    "sg:orig_category":"Art\u00cdculos De Regalo (al Por Menor)",
    "sg:phone":"+34 916 59 50 86",
    "sg:postcode":"28700",
    "sg:province":"Madrid",
    "wof:name":"Candelas Davila Luis",
    "wof:placetype":"venue"
},
  "geometry": {"coordinates":[-3.5817000866,40.6102294922],"type":"Point"}
}