{
  "type": "Feature",
  "properties": {
    "addr:full":"Plaz Garcia Lorca, 3 Salar Granada 18310",
    "addr:housenumber":"3",
    "addr:postcode":"18310",
    "addr:street":"Lorca;Granada",
    "iso:country":"ES",
    "sg:address":"Plaz Garcia Lorca, 3",
    "sg:city":"Salar",
    "sg:orig_category":"Electrodom\u00c9sticos (al Por Menor)",
    "sg:phone":"+34 958 31 61 79",
    "sg:postcode":"18310",
    "sg:province":"Granada",
    "wof:name":"Tejero Molina Consuelo",
    "wof:placetype":"venue"
},
  "geometry": {"coordinates":[-4.0647978783,37.1503410339],"type":"Point"}
}