{
  "type": "Feature",
  "properties": {
    "iso:country":"ES",
    "sg:address":"Calle de Independencia, 4",
    "sg:city":"Potes",
    "sg:orig_category":"Florister\u00cdas",
    "sg:phone":"+34 942 73 06 58",
    "sg:postcode":"39570",
    "sg:province":"Cantabria",
    "wof:name":"Volters  Isabel",
    "wof:placetype":"venue"
},
  "geometry": {"coordinates":[-4.6235060692,43.1538658142],"type":"Point"}
}