{
  "type": "Feature",
  "properties": {
    "iso:country":"ES",
    "sg:address":"Calle de Romana, 2",
    "sg:city":"Higuera Real",
    "sg:orig_category":"Supermercados Y Hipermercados",
    "sg:phone":"+34 924 72 36 32",
    "sg:postcode":"06350",
    "sg:province":"Badajoz",
    "wof:name":"Rasero Romero Manuel",
    "wof:placetype":"venue"
},
  "geometry": {"coordinates":[-6.6909160614,38.14270401],"type":"Point"}
}