{
  "type": "Feature",
  "properties": {
    "iso:country":"ES",
    "sg:address":"Carrer de Mare De Deu De L'esperanca, 95",
    "sg:city":"Mataro",
    "sg:orig_category":"Semiller\u00cdas",
    "sg:phone":"+34 937 98 58 96",
    "sg:postcode":"08304",
    "sg:province":"Barcelona",
    "wof:name":"Sanchez Romero Carlos",
    "wof:placetype":"venue"
},
  "geometry": {"coordinates":[2.4429330826,41.550201416],"type":"Point"}
}