{
  "type": "Feature",
  "properties": {
    "iso:country":"ES",
    "sg:address":"Gudarien Etorbidea, S/n",
    "sg:city":"Ordizia",
    "sg:orig_category":"Asociaciones Humanitarias, De Cooperaci\u00d3n, De Acci\u00d3n Social",
    "sg:phone":"+34 943 88 81 69",
    "sg:postcode":"20240",
    "sg:province":"Guip\u00f9zcoa",
    "wof:name":"Organizacion Nacional De Ciegos",
    "wof:placetype":"venue"
},
  "geometry": {"coordinates":[-2.1773040295,43.0538711548],"type":"Point"}
}