{
  "type": "Feature",
  "properties": {
    "addr:full":"Av Cami Reial, 19 Poligon Industrial Riera De Caldes Barcelona 08184",
    "addr:housenumber":"19",
    "addr:postcode":"08184",
    "addr:street":"Av Cami Reial;Industrial",
    "iso:country":"ES",
    "sg:address":"Av Cami Reial, 19",
    "sg:city":"Poligon Industrial Riera De Caldes",
    "sg:orig_category":"Productos Qu\u00cdmicos (fabricaci\u00d3n, Al Por Mayor)",
    "sg:phone":"+34 938 64 46 69",
    "sg:postcode":"08184",
    "sg:province":"Barcelona",
    "sg:website":"www.sk-europe.com",
    "wof:name":"Safety-kleen Espa\u00f1a S.a.",
    "wof:placetype":"venue"
},
  "geometry": {"coordinates":[2.181032896,41.5802307129],"type":"Point"}
}