{
  "type": "Feature",
  "properties": {
    "iso:country":"ES",
    "sg:address":"Trva Monte, 14",
    "sg:city":"Coru\u00d1a",
    "sg:orig_category":"Empresarios",
    "sg:phone":"+34 981 23 80 65",
    "sg:postcode":"15005",
    "sg:province":"La Coru\u00f1a",
    "wof:name":"Lopez Barral Maria Del Carmen",
    "wof:placetype":"venue"
},
  "geometry": {"coordinates":[-8.4057674408,43.3589477539],"type":"Point"}
}