{
  "type": "Feature",
  "properties": {
    "addr:full":"Calle de Rambla De La Mancha, 56 Almansa Albacete 02640",
    "addr:housenumber":"56",
    "addr:postcode":"02640",
    "addr:street":"Calle De Rambla De La Mancha",
    "iso:country":"ES",
    "sg:address":"Calle de Rambla De La Mancha, 56",
    "sg:city":"Almansa",
    "sg:orig_category":"Electricidad: Instaladores",
    "sg:phone":"+34 967 34 19 17",
    "sg:postcode":"02640",
    "sg:province":"Albacete",
    "wof:name":"Gisber Sanchiz Camilo",
    "wof:placetype":"venue"
},
  "geometry": {"coordinates":[-1.0956139565,38.8690605164],"type":"Point"}
}