{
  "type": "Feature",
  "properties": {
    "iso:country":"ES",
    "sg:address":"Psje. Zahira, 3",
    "sg:city":"Cordoba",
    "sg:orig_category":"Centros P\u00dablicos De Formaci\u00d3n Profesional Y T\u00c9cnica",
    "sg:phone":"+34 957 47 27 37",
    "sg:postcode":"14008",
    "sg:province":"C\u00f3rdoba",
    "wof:name":"Ilustre Colegio Notarial De Sevilla",
    "wof:placetype":"venue"
},
  "geometry": {"coordinates":[-4.7784028053,37.8779411316],"type":"Point"}
}