{
  "type": "Feature",
  "properties": {
    "addr:full":"Carrer de Pintor Pau Roig, 39 Premia Mar Barcelona 08330",
    "addr:housenumber":"39",
    "addr:postcode":"08330",
    "addr:street":"Carrer De Pintor Pau Roig",
    "iso:country":"ES",
    "sg:address":"Carrer de Pintor Pau Roig, 39",
    "sg:city":"Premia Mar",
    "sg:orig_category":"M\u00c9dicos: Otorrinolaringolog\u00cda",
    "sg:phone":"+34 937 51 70 01",
    "sg:postcode":"08330",
    "sg:province":"Barcelona",
    "wof:name":"Aboujeib Dek Al Bab Mohamed Fawaz",
    "wof:placetype":"venue"
},
  "geometry": {"coordinates":[2.351505,41.508682],"type":"Point"}
}