{
  "type": "Feature",
  "properties": {
    "iso:country":"ES",
    "sg:address":"Avda Lido Del, 30",
    "sg:city":"Torremolinos",
    "sg:orig_category":"Cajas De Ahorro",
    "sg:phone":"+34 952 05 82 52",
    "sg:postcode":"29620",
    "sg:province":"M\u00e1laga",
    "sg:website":"www.cajaen.es",
    "wof:name":"Caja De Jaen",
    "wof:placetype":"venue"
},
  "geometry": {"coordinates":[-4.4952468872,36.6280021667],"type":"Point"}
}