{
  "type": "Feature",
  "properties": {
    "iso:country":"ES",
    "sg:address":"Calle de San Roque, 7",
    "sg:city":"Potes",
    "sg:orig_category":"Asociaciones De Vecinos, Centros De Juventud",
    "sg:phone":"+34 942 73 07 26",
    "sg:postcode":"39570",
    "sg:province":"Cantabria",
    "sg:website":"www.comarcadelievano.com",
    "wof:name":"Grupo De Accion Local Liebana",
    "wof:placetype":"venue"
},
  "geometry": {"coordinates":[-4.6181621552,43.1562042236],"type":"Point"}
}