{
  "type": "Feature",
  "properties": {
    "iso:country":"ES",
    "sg:address":"Rua Ribeira Do Berbes, 39",
    "sg:city":"Vigo",
    "sg:orig_category":"Carnicer\u00cdas, Carnicer\u00cdas",
    "sg:phone":"+34 986 43 37 62",
    "sg:postcode":"36202",
    "sg:province":"Pontevedra",
    "wof:name":"Diaz Rocha Benigno",
    "wof:placetype":"venue"
},
  "geometry": {"coordinates":[-8.7286891937,42.2379150391],"type":"Point"}
}