{
  "type": "Feature",
  "properties": {
    "iso:country":"ES",
    "sg:address":"Ctra. Benavente-puebla, 7",
    "sg:city":"Camarzana Tera",
    "sg:orig_category":"Agentes Generales De Seguros",
    "sg:phone":"+34 980 64 95 70",
    "sg:postcode":"49332",
    "sg:province":"Zamora",
    "wof:name":"Benitez Furones Pascual",
    "wof:placetype":"venue"
},
  "geometry": {"coordinates":[-6.0264492035,41.9957695007],"type":"Point"}
}