{
  "type": "Feature",
  "properties": {
    "iso:country":"ES",
    "sg:address":"Avda Cerrada (la), S/n",
    "sg:city":"Malia\u00d1o",
    "sg:orig_category":"Comercio De Hierro",
    "sg:phone":"+34 942 25 08 42",
    "sg:postcode":"39600",
    "sg:province":"Cantabria",
    "wof:name":"Suministros Siderurgicos Monta\u00f1eses",
    "wof:placetype":"venue"
},
  "geometry": {"coordinates":[-3.8379189968,43.4210166931],"type":"Point"}
}