{
  "type": "Feature",
  "properties": {
    "addr:full":"Calle de San Miguel, 31 Tirig Castell\u00f3n 12179",
    "addr:housenumber":"31",
    "addr:postcode":"12179",
    "addr:street":"Calle De San Miguel;Castello\u0301N",
    "iso:country":"ES",
    "sg:address":"Calle de San Miguel, 31",
    "sg:city":"Tirig",
    "sg:orig_category":"M\u00c9dicos: Oftalmolog\u00cda",
    "sg:phone":"+34 964 41 85 97",
    "sg:postcode":"12179",
    "sg:province":"Castell\u00f3n",
    "wof:name":"Puig Roda Primitivo",
    "wof:placetype":"venue"
},
  "geometry": {"coordinates":[0.0782120004,40.4241905212],"type":"Point"}
}