{
  "type": "Feature",
  "properties": {
    "iso:country":"ES",
    "sg:address":"Primero Mayo-barredos, S/n",
    "sg:city":"Tira\u00f1a",
    "sg:orig_category":"Supermercados Y Hipermercados",
    "sg:phone":"+34 985 60 07 17",
    "sg:postcode":"33970",
    "sg:province":"Asturias",
    "wof:name":"Hulleras Del Norte S.a.",
    "wof:placetype":"venue"
},
  "geometry": {"coordinates":[-5.573372364,43.2591781616],"type":"Point"}
}