{
  "type": "Feature",
  "properties": {
    "addr:full":"Calle de Ayala, 8 Don Benito Badajoz 06400",
    "addr:housenumber":"8",
    "addr:postcode":"06400",
    "addr:street":"Calle De Ayala",
    "iso:country":"ES",
    "sg:address":"Calle de Ayala, 8",
    "sg:city":"Don Benito",
    "sg:orig_category":"Bazares, Art\u00cdculos De Limpieza Y De Cocina (al Por Menor)",
    "sg:phone":"+34 924 80 29 02",
    "sg:postcode":"06400",
    "sg:province":"Badajoz",
    "wof:name":"Sanchez Prieto S.l",
    "wof:placetype":"venue"
},
  "geometry": {"coordinates":[-5.8599967957,38.9615325928],"type":"Point"}
}