{
  "type": "Feature",
  "properties": {
    "addr:full":"Rua Colon, 6 Vigo Pontevedra 36201",
    "addr:housenumber":"6",
    "addr:postcode":"36201",
    "addr:street":"Rua Colon",
    "iso:country":"ES",
    "sg:address":"Rua Colon, 6",
    "sg:city":"Vigo",
    "sg:orig_category":"Arquitectos",
    "sg:phone":"+34 986 44 33 34",
    "sg:postcode":"36201",
    "sg:province":"Pontevedra",
    "wof:name":"Ramilo Mendez Francisco Borja",
    "wof:placetype":"venue"
},
  "geometry": {"coordinates":[-8.7205562592,42.2387199402],"type":"Point"}
}