{
  "type": "Feature",
  "properties": {
    "iso:country":"ES",
    "sg:address":"Calle de Juan Bautista Zabala, 8",
    "sg:city":"Getxo",
    "sg:orig_category":"Lanas (al Por Mayor)",
    "sg:phone":"+34 944 60 95 35",
    "sg:postcode":"48990",
    "sg:province":"Vizcaya",
    "wof:name":"Lanas Monasterio",
    "wof:placetype":"venue"
},
  "geometry": {"coordinates":[-3.0109190941,43.350440979],"type":"Point"}
}