{
  "type": "Feature",
  "properties": {
    "iso:country":"ES",
    "sg:address":"Calle de Chiva, 134",
    "sg:city":"Cheste",
    "sg:orig_category":"Electricidad Veh\u00cdculo",
    "sg:phone":"+34 962 51 01 13",
    "sg:postcode":"46380",
    "sg:province":"Valencia",
    "wof:name":"Moreno Camacho Jose",
    "wof:placetype":"venue"
},
  "geometry": {"coordinates":[-0.689085722,39.498752594],"type":"Point"}
}