{
  "type": "Feature",
  "properties": {
    "iso:country":"ES",
    "sg:address":"Ctra Aguilas (de), 19",
    "sg:city":"Granja",
    "sg:orig_category":"Bricolaje, Herramientas (al Por Menor)",
    "sg:phone":"+34 968 46 29 58",
    "sg:postcode":"30800",
    "sg:province":"Murcia",
    "wof:name":"Chabolas Riegos S.l.",
    "wof:placetype":"venue"
},
  "geometry": {"coordinates":[-1.6905640364,37.680557251],"type":"Point"}
}