{
  "type": "Feature",
  "properties": {
    "addr:full":"Calle de Cabezon, 4 Tenoya Las Palmas 35018",
    "addr:housenumber":"4",
    "addr:postcode":"35018",
    "addr:street":"Calle De Cabezon;Las Palmas",
    "iso:country":"ES",
    "sg:address":"Calle de Cabezon, 4",
    "sg:city":"Tenoya",
    "sg:orig_category":"Empresarios",
    "sg:phone":"+34 928 66 74 61",
    "sg:postcode":"35018",
    "sg:province":"Las Palmas",
    "wof:name":"Cabrera Marrero Domingo",
    "wof:placetype":"venue"
},
  "geometry": {"coordinates":[-15.4949102402,28.1115379333],"type":"Point"}
}