{
  "type": "Feature",
  "properties": {
    "addr:full":"Calle de Aguilar, 4 Puente-genil C\u00f3rdoba 14500",
    "addr:housenumber":"4",
    "addr:postcode":"14500",
    "addr:street":"Calle De Aguilar;Co\u0301Rdoba",
    "iso:country":"ES",
    "sg:address":"Calle de Aguilar, 4",
    "sg:city":"Puente-genil",
    "sg:orig_category":"Florister\u00cdas",
    "sg:phone":"+34 957 60 11 89",
    "sg:postcode":"14500",
    "sg:province":"C\u00f3rdoba",
    "wof:name":"Rojas Saavedra Maria Jose",
    "wof:placetype":"venue"
},
  "geometry": {"coordinates":[-4.7766404152,37.38829422],"type":"Point"}
}