{
  "type": "Feature",
  "properties": {
    "iso:country":"ES",
    "sg:address":"Pradillo (zona Ind.), S/n",
    "sg:city":"Palacios Y Villafranca",
    "sg:orig_category":"Reposter\u00cdas",
    "sg:phone":"+34 955 81 47 97",
    "sg:postcode":"41720",
    "sg:province":"Sevilla",
    "wof:name":"Sociedad Cooperativa Limitada Panadera De Los Palacios",
    "wof:placetype":"venue"
},
  "geometry": {"coordinates":[-5.9241790771,37.1630935669],"type":"Point"}
}