{
  "type": "Feature",
  "properties": {
    "iso:country":"ES",
    "sg:address":"Ptda Pla Terol, S/n",
    "sg:city":"Polop",
    "sg:orig_category":"Hormig\u00d3n (m\u00c1quinas E Instalaci\u00d3n)",
    "sg:phone":"+34 965 87 07 48",
    "sg:postcode":"03520",
    "sg:province":"Alicante",
    "wof:name":"Holcim Hormigones",
    "wof:placetype":"venue"
},
  "geometry": {"coordinates":[-0.134149,38.6205482483],"type":"Point"}
}