{
  "type": "Feature",
  "properties": {
    "iso:country":"ES",
    "sg:address":"Carrer de Roura, 35",
    "sg:city":"Barcelona",
    "sg:orig_category":"Agencias Y Agentes Comerciales, Representantes",
    "sg:phone":"+34 934 18 14 26",
    "sg:postcode":"08017",
    "sg:province":"Barcelona",
    "wof:name":"Urtx S.l.",
    "wof:placetype":"venue"
},
  "geometry": {"coordinates":[2.1253800392,41.4090881348],"type":"Point"}
}