{
  "type": "Feature",
  "properties": {
    "iso:country":"ES",
    "sg:address":"Calle de Iglesia, 9",
    "sg:city":"Mariana",
    "sg:orig_category":"Supermercados Y Hipermercados",
    "sg:phone":"+34 969 28 81 59",
    "sg:postcode":"16143",
    "sg:province":"Cuenca",
    "wof:name":"De Marco Alvaro Raquel",
    "wof:placetype":"venue"
},
  "geometry": {"coordinates":[-2.145252943,40.1662635803],"type":"Point"}
}