{
  "type": "Feature",
  "properties": {
    "addr:full":"Carrer de Francesc Macia, 62 S. Boi Llobregat Barcelona 08830",
    "addr:housenumber":"62",
    "addr:postcode":"08830",
    "addr:street":"Carrer De Francesc Macia",
    "iso:country":"ES",
    "sg:address":"Carrer de Francesc Macia, 62",
    "sg:city":"S. Boi Llobregat",
    "sg:orig_category":"Servicios De Telecomunicaciones",
    "sg:phone":"+34 933 77 26 00",
    "sg:postcode":"08830",
    "sg:province":"Barcelona",
    "wof:name":"Vani Telecomunications S.l.",
    "wof:placetype":"venue"
},
  "geometry": {"coordinates":[2.0428950787,41.3401374817],"type":"Point"}
}