{
  "type": "Feature",
  "properties": {
    "iso:country":"ES",
    "sg:address":"Cmno Lomo Espino, 45",
    "sg:city":"Lomo Espino",
    "sg:orig_category":"Chapister\u00cda",
    "sg:phone":"+34 928 64 07 04",
    "sg:postcode":"35300",
    "sg:province":"Las Palmas",
    "wof:name":"Socorro Santana Vicente Domingo",
    "wof:placetype":"venue"
},
  "geometry": {"coordinates":[-15.4988956451,28.0369472504],"type":"Point"}
}