{
  "type": "Feature",
  "properties": {
    "addr:full":"Plaz Constitucion, 2 Otura Granada 18630",
    "addr:housenumber":"2",
    "addr:postcode":"18630",
    "addr:street":"Constitucion",
    "iso:country":"ES",
    "sg:address":"Plaz Constitucion, 2",
    "sg:city":"Otura",
    "sg:orig_category":"Inmobiliaria (agencias)",
    "sg:phone":"+34 958 55 92 72",
    "sg:postcode":"18630",
    "sg:province":"Granada",
    "wof:name":"Ros Zurita Jose",
    "wof:placetype":"venue"
},
  "geometry": {"coordinates":[-3.6341888905,37.0911445618],"type":"Point"}
}