{
  "type": "Feature",
  "properties": {
    "addr:full":"Plzl Lasso, 2 Carmona Sevilla 41410",
    "addr:housenumber":"2",
    "addr:postcode":"41410",
    "addr:street":"Plzl Lasso",
    "iso:country":"ES",
    "sg:address":"Plzl Lasso, 2",
    "sg:city":"Carmona",
    "sg:orig_category":"Centros De Reservas Hoteleras",
    "sg:phone":"+34 954 19 62 00",
    "sg:postcode":"41410",
    "sg:province":"Sevilla",
    "wof:name":"Hoteles Luxor S.l.",
    "wof:placetype":"venue"
},
  "geometry": {"coordinates":[-5.6433792114,37.4708709717],"type":"Point"}
}