{
  "type": "Feature",
  "properties": {
    "iso:country":"ES",
    "sg:address":"Calle de Jardines, 4",
    "sg:city":"Armilla",
    "sg:orig_category":"M\u00c9dicos: Estomatolog\u00cda",
    "sg:phone":"+34 958 57 03 01",
    "sg:postcode":"18100",
    "sg:province":"Granada",
    "wof:name":"Cutando Soriano Antonio",
    "wof:placetype":"venue"
},
  "geometry": {"coordinates":[-3.6283950806,37.1404647827],"type":"Point"}
}