{
  "type": "Feature",
  "properties": {
    "iso:country":"ES",
    "sg:address":"Arrabal, S/n",
    "sg:city":"Lagunilla Del Jubera",
    "sg:orig_category":"Ense\u00d1anza, Formaci\u00d3n Profesional: Aprendizaje",
    "sg:phone":"+34 941 48 20 87",
    "sg:postcode":"26131",
    "sg:province":"La Rioja",
    "wof:name":"Ayuntamiento De Lagunilla De Jubera",
    "wof:placetype":"venue"
},
  "geometry": {"coordinates":[-2.3210740089,42.3339385986],"type":"Point"}
}