{
  "type": "Feature",
  "properties": {
    "addr:full":"Calle de Jardines De La Concordia, 5 Zaragoza Zaragoza 50015",
    "addr:housenumber":"5",
    "addr:postcode":"50015",
    "addr:street":"Calle De Jardines De La Concordia",
    "iso:country":"ES",
    "sg:address":"Calle de Jardines De La Concordia, 5",
    "sg:city":"Zaragoza",
    "sg:orig_category":"Frutas, Legumbres Frescas Y Tempranas (al Por Menor)",
    "sg:phone":"+34 976 52 60 23",
    "sg:postcode":"50015",
    "sg:province":"Zaragoza",
    "wof:name":"Canales Alcantara Angel",
    "wof:placetype":"venue"
},
  "geometry": {"coordinates":[-0.8629540205,41.6912841797],"type":"Point"}
}