{
  "type": "Feature",
  "properties": {
    "iso:country":"ES",
    "sg:address":"Calle de Infanta Mercedes, 31",
    "sg:city":"Madrid",
    "sg:orig_category":"Laboratorios Y Trabajos De Fotograf\u00cda, V\u00cddeo Y Cine",
    "sg:phone":"+34 915 71 63 21",
    "sg:postcode":"28020",
    "sg:province":"Madrid",
    "sg:website":"www.borjacolor.es",
    "wof:name":"Borjacolor S. A.",
    "wof:placetype":"venue"
},
  "geometry": {"coordinates":[-3.6989729404,40.4548225403],"type":"Point"}
}