{
  "type": "Feature",
  "properties": {
    "iso:country":"ES",
    "sg:address":"Calle de Carretera, S/n",
    "sg:city":"Oliete",
    "sg:orig_category":"Delegados, Agentes De Tr\u00c1nsito, Auxiliares De Transporte Internacional",
    "sg:phone":"+34 978 81 80 30",
    "sg:postcode":"44548",
    "sg:province":"Teruel",
    "wof:name":"Villuendas Gracia Pilar",
    "wof:placetype":"venue"
},
  "geometry": {"coordinates":[-0.6741489768,40.9988670349],"type":"Point"}
}