{
  "type": "Feature",
  "properties": {
    "addr:full":"Avda General Mola (del), 22 Santa Cruz De Tenerife Santa Cruz De Tenerife 38006",
    "addr:housenumber":"22",
    "addr:postcode":"38006",
    "addr:street":"Avda General Mola Del",
    "iso:country":"ES",
    "sg:address":"Avda General Mola (del), 22",
    "sg:city":"Santa Cruz De Tenerife",
    "sg:orig_category":"Carnicer\u00cdas, Carnicer\u00cdas",
    "sg:phone":"+34 922 27 08 34",
    "sg:postcode":"38006",
    "sg:province":"Santa Cruz De Tenerife",
    "wof:name":"Morales Armas Teodoro",
    "wof:placetype":"venue"
},
  "geometry": {"coordinates":[-16.2628726959,28.4678516388],"type":"Point"}
}