{
  "type": "Feature",
  "properties": {
    "iso:country":"ES",
    "sg:address":"Carrer de Joan Maragall, 9",
    "sg:city":"Castellbisbal",
    "sg:orig_category":"Supermercados Y Hipermercados",
    "sg:phone":"+34 937 71 18 28",
    "sg:postcode":"08755",
    "sg:province":"Barcelona",
    "wof:name":"Autoservicio Castellbisbal S.l.",
    "wof:placetype":"venue"
},
  "geometry": {"coordinates":[1.9798300266,41.472530365],"type":"Point"}
}