{
  "type": "Feature",
  "properties": {
    "iso:country":"ES",
    "sg:address":"Plaza Bentako, 1",
    "sg:city":"Basauri",
    "sg:orig_category":"Librer\u00cdas",
    "sg:phone":"+34 944 49 25 88",
    "sg:postcode":"48970",
    "sg:province":"Vizcaya",
    "wof:name":"Jose Manuel Ovejano Y Maria Amparo Lastra C.b.",
    "wof:placetype":"venue"
},
  "geometry": {"coordinates":[-2.8866200447,43.2379875183],"type":"Point"}
}