{
  "type": "Feature",
  "properties": {
    "addr:full":"Calle de Batalla De Brunete, 57 Palmas De Gran Canaria Las Palmas 35013",
    "addr:housenumber":"57",
    "addr:postcode":"35013",
    "addr:street":"Calle De Batalla De Brunete",
    "iso:country":"ES",
    "sg:address":"Calle de Batalla De Brunete, 57",
    "sg:city":"Palmas De Gran Canaria",
    "sg:orig_category":"Mec\u00c1nico Del Autom\u00d3vil",
    "sg:phone":"+34 928 42 71 13",
    "sg:postcode":"35013",
    "sg:province":"Las Palmas",
    "wof:name":"Castellano Ortega Jose Ramon",
    "wof:placetype":"venue"
},
  "geometry": {"coordinates":[-15.4492683411,28.0974254608],"type":"Point"}
}