{
  "type": "Feature",
  "properties": {
    "iso:country":"ES",
    "sg:address":"San Luis, 1",
    "sg:city":"San Antonio",
    "sg:orig_category":"Toneles Y Barriles",
    "sg:phone":"+34 962 32 00 40",
    "sg:postcode":"46390",
    "sg:province":"Valencia",
    "wof:name":"Toneleria De Gabriel Coop",
    "wof:placetype":"venue"
},
  "geometry": {"coordinates":[-1.1498279572,39.5176544189],"type":"Point"}
}