{
  "type": "Feature",
  "properties": {
    "addr:full":"Carrer de Vilarrubias, 124 Sabadell Barcelona 08202",
    "addr:housenumber":"124",
    "addr:postcode":"08202",
    "addr:street":"Carrer De Vilarrubias",
    "iso:country":"ES",
    "sg:address":"Carrer de Vilarrubias, 124",
    "sg:city":"Sabadell",
    "sg:orig_category":"Agentes, Concesionarios Y Sucursales De Veh\u00cdculos",
    "sg:phone":"+34 937 27 85 00",
    "sg:postcode":"08202",
    "sg:province":"Barcelona",
    "wof:name":"Vila Umbert S.l.",
    "wof:placetype":"venue"
},
  "geometry": {"coordinates":[2.1116909981,41.5534515381],"type":"Point"}
}