{
  "type": "Feature",
  "properties": {
    "iso:country":"ES",
    "sg:address":"L. Bravo, 29",
    "sg:city":"Villalonquejar",
    "sg:orig_category":"Productos Alimentarios",
    "sg:phone":"+34 947 29 84 22",
    "sg:postcode":"09001",
    "sg:province":"Burgos",
    "wof:name":"Molienda Y Granulacion S. A.",
    "wof:placetype":"venue"
},
  "geometry": {"coordinates":[-3.7323570251,42.3703041077],"type":"Point"}
}