{
  "type": "Feature",
  "properties": {
    "iso:country":"ES",
    "sg:address":"Calle de Berangoeta Bidea, 10",
    "sg:city":"Berango",
    "sg:orig_category":"Librer\u00cdas",
    "sg:phone":"+34 946 68 12 50",
    "sg:postcode":"48640",
    "sg:province":"Vizcaya",
    "wof:name":"Vlai Archivos Y Bibliotecas S.l.",
    "wof:placetype":"venue"
},
  "geometry": {"coordinates":[-2.9985849857,43.3649864197],"type":"Point"}
}