{
  "type": "Feature",
  "properties": {
    "addr:full":"Carrer de Vinyes, S/n S. Joan Despi Barcelona 08970",
    "addr:housenumber":"s",
    "addr:postcode":"08970",
    "addr:street":"Carrer De Vinyes;/ N S. Joan Despi",
    "iso:country":"ES",
    "sg:address":"Carrer de Vinyes, S/n",
    "sg:city":"S. Joan Despi",
    "sg:orig_category":"Negocio De Madera",
    "sg:phone":"+34 933 73 34 15",
    "sg:postcode":"08970",
    "sg:province":"Barcelona",
    "wof:name":"Hijos De Domingo Sarda Coret S.l.",
    "wof:placetype":"venue"
},
  "geometry": {"coordinates":[2.0629599094,41.3767547607],"type":"Point"}
}