{
  "type": "Feature",
  "properties": {
    "iso:country":"ES",
    "sg:address":"Calle de Principe Felipe, 8",
    "sg:city":"Otura",
    "sg:orig_category":"Pizzer\u00cdas",
    "sg:phone":"+34 958 55 56 68",
    "sg:postcode":"18630",
    "sg:province":"Granada",
    "wof:name":"Izquierdo Lopez Maria Jesus",
    "wof:placetype":"venue"
},
  "geometry": {"coordinates":[-3.6331000328,37.0901985168],"type":"Point"}
}