{
  "type": "Feature",
  "properties": {
    "addr:full":"Cra Espinel, 108 Ronda M\u00e1laga 29400",
    "addr:housenumber":"108",
    "addr:postcode":"29400",
    "addr:street":"Espinel;Ronda Ma\u0301Laga",
    "iso:country":"ES",
    "sg:address":"Cra Espinel, 108",
    "sg:city":"Ronda",
    "sg:orig_category":"Panader\u00cdas, Panader\u00cdas",
    "sg:phone":"+34 952 87 12 88",
    "sg:postcode":"29400",
    "sg:province":"M\u00e1laga",
    "wof:name":"Pasteleria Patricia S.l.l.",
    "wof:placetype":"venue"
},
  "geometry": {"coordinates":[-5.1609601974,36.7450942993],"type":"Point"}
}