{
  "type": "Feature",
  "properties": {
    "iso:country":"ES",
    "sg:address":"Pol Ind Elviria, S/n",
    "sg:city":"Elviria",
    "sg:orig_category":"Mec\u00c1nico Del Autom\u00d3vil",
    "sg:phone":"+34 952 83 66 15",
    "sg:postcode":"29604",
    "sg:province":"M\u00e1laga",
    "wof:name":"Sorroche Martin Angel",
    "wof:placetype":"venue"
},
  "geometry": {"coordinates":[-4.7700138092,36.4987945557],"type":"Point"}
}