{
  "type": "Feature",
  "properties": {
    "addr:full":"Rua Xeneral Pardi\u00d1as (do), 3 Santiago De Compostela A Coru\u00f1a 15701",
    "addr:postcode":"15701",
    "addr:street":"Rua Xeneral;Corun\u0303A",
    "iso:country":"ES",
    "sg:address":"Rua Xeneral Pardi\u00d1as (do), 3",
    "sg:city":"Santiago De Compostela",
    "sg:orig_category":"Pesca Y Caza: Art\u00cdculos (al Por Menor)",
    "sg:phone":"+34 981 58 57 83",
    "sg:postcode":"15701",
    "sg:province":"A Coru\u00f1a",
    "wof:name":"Tevesa Perez-bobillo Beatriz",
    "wof:placetype":"venue"
},
  "geometry": {"coordinates":[-8.5461168289,42.8762702942],"type":"Point"}
}