{
  "type": "Feature",
  "properties": {
    "addr:full":"Calle de Diputacion, 1 Teruel Teruel 44001",
    "addr:housenumber":"1",
    "addr:postcode":"44001",
    "addr:street":"Calle De Diputacion",
    "iso:country":"ES",
    "sg:address":"Calle de Diputacion, 1",
    "sg:city":"Teruel",
    "sg:orig_category":"Bisuter\u00cda, Joyer\u00cda, Relojer\u00cda (al Por Menor)",
    "sg:phone":"+34 978 61 16 99",
    "sg:postcode":"44001",
    "sg:province":"Teruel",
    "wof:name":"Alvaro Argiles Josefina",
    "wof:placetype":"venue"
},
  "geometry": {"coordinates":[-1.1061091423,40.3404769897],"type":"Point"}
}