{
  "type": "Feature",
  "properties": {
    "iso:country":"ES",
    "sg:address":"C/ Santa Catalina, 35",
    "sg:city":"Torre",
    "sg:orig_category":"Aguas (distribuci\u00d3n, Servicios)",
    "sg:phone":"+34 971 74 97 30",
    "sg:postcode":"07609",
    "sg:province":"Islas Baleares",
    "wof:name":"Aguas De Lujo Siniva S.l.",
    "wof:placetype":"venue"
},
  "geometry": {"coordinates":[2.7600286007,39.4389152527],"type":"Point"}
}