{
  "type": "Feature",
  "properties": {
    "addr:full":"Calle de Real, 4 Llanos De Aridane Santa Cruz De Tenerife 38760",
    "addr:housenumber":"4",
    "addr:postcode":"38760",
    "addr:street":"Calle De Real",
    "iso:country":"ES",
    "sg:address":"Calle de Real, 4",
    "sg:city":"Llanos De Aridane",
    "sg:orig_category":"Ropa Para Ni\u00d1os (al Por Menor)",
    "sg:phone":"+34 922 46 11 09",
    "sg:postcode":"38760",
    "sg:province":"Santa Cruz De Tenerife",
    "sg:website":"www.donalgodon.com",
    "wof:name":"Hernandez Alvarez Anicia",
    "wof:placetype":"venue"
},
  "geometry": {"coordinates":[-17.9137458801,28.6586914062],"type":"Point"}
}