{
  "type": "Feature",
  "properties": {
    "iso:country":"ES",
    "sg:address":"Paulino Caballero, 6",
    "sg:city":"Iru\u00f1a",
    "sg:orig_category":"Zapatos (al Por Menor)",
    "sg:phone":"+34 948 22 84 96",
    "sg:postcode":"31002",
    "sg:province":"Navarra",
    "wof:name":"Go\u00f1i Labiano Pablo",
    "wof:placetype":"venue"
},
  "geometry": {"coordinates":[-1.6417930126,42.8139686584],"type":"Point"}
}