{
  "type": "Feature",
  "properties": {
    "iso:country":"ES",
    "sg:address":"Ctra Soria, 13",
    "sg:city":"Lastrilla",
    "sg:orig_category":"Chapister\u00cda",
    "sg:phone":"+34 921 43 60 96",
    "sg:postcode":"40196",
    "sg:province":"Segovia",
    "wof:name":"Martinez Bascuas Juan Carlos",
    "wof:placetype":"venue"
},
  "geometry": {"coordinates":[-4.1034941673,40.9690361023],"type":"Point"}
}