{
  "type": "Feature",
  "properties": {
    "iso:country":"ES",
    "sg:address":"Carrer de Josep Rover Motta, 20",
    "sg:city":"Palma",
    "sg:orig_category":"Molduras, Junquillos, Listones Y Molduras Perforadas",
    "sg:phone":"+34 971 46 62 55",
    "sg:postcode":"07006",
    "sg:province":"Islas Baleares",
    "wof:name":"Club De La Tercera Edad Poligono Levante",
    "wof:placetype":"venue"
},
  "geometry": {"coordinates":[2.6596438885,39.5656661987],"type":"Point"}
}