{
  "type": "Feature",
  "properties": {
    "iso:country":"ES",
    "sg:address":"Calle de Torrente, 5",
    "sg:city":"Albal",
    "sg:orig_category":"Caf\u00c9s, Bares, Cervecer\u00cdas",
    "sg:phone":"+34 961 26 82 37",
    "sg:postcode":"46470",
    "sg:province":"Valencia",
    "wof:name":"Cafe Bar Pentagono C.b.",
    "wof:placetype":"venue"
},
  "geometry": {"coordinates":[-0.4098750055,39.397354126],"type":"Point"}
}