{
  "type": "Feature",
  "properties": {
    "iso:country":"ES",
    "sg:address":"Avda Constitucion, Km. 0001,0",
    "sg:city":"Talarrubias",
    "sg:orig_category":"Ense\u00d1anza, Formaci\u00d3n Profesional: Aprendizaje",
    "sg:phone":"+34 924 63 02 71",
    "sg:postcode":"06640",
    "sg:province":"Badajoz",
    "wof:name":"Servicio Extreme\u00d1o De Salud",
    "wof:placetype":"venue"
},
  "geometry": {"coordinates":[-5.2341241837,39.0403175354],"type":"Point"}
}