{
  "type": "Feature",
  "properties": {
    "addr:full":"Calle de Jose Pons, 10 San Pedro De Bre\u00e7a Alta Santa Cruz De Tenerife 38712",
    "addr:housenumber":"10",
    "addr:postcode":"38712",
    "addr:street":"Calle De Jose Pons",
    "iso:country":"ES",
    "sg:address":"Calle de Jose Pons, 10",
    "sg:city":"San Pedro De Bre\u00e7a Alta",
    "sg:orig_category":"Confiter\u00cda, Galletas Y Pastas, Chocolater\u00cda (al Por Mayor)",
    "sg:phone":"+34 922 43 73 13",
    "sg:postcode":"38712",
    "sg:province":"Santa Cruz De Tenerife",
    "wof:name":"Remedios Rodriguez Jose Rogelio",
    "wof:placetype":"venue"
},
  "geometry": {"coordinates":[-17.7672138214,28.6476554871],"type":"Point"}
}