{
  "type": "Feature",
  "properties": {
    "iso:country":"ES",
    "sg:address":"Plaz Constitucion (de La), 1",
    "sg:city":"Conil De La Frontera",
    "sg:orig_category":"Inform\u00c1tica (estudios, Servicios, Asesor\u00cda, Formaci\u00d3n)",
    "sg:phone":"+34 956 44 22 29",
    "sg:postcode":"11140",
    "sg:province":"C\u00e1diz",
    "wof:name":"Ceginfor S.l.",
    "wof:placetype":"venue"
},
  "geometry": {"coordinates":[-6.0881857872,36.2774810791],"type":"Point"}
}