{
  "type": "Feature",
  "properties": {
    "addr:full":"Av. J Tarradellas (u Mas Sopas), 4 S. Pere Pescador Girona 17470",
    "addr:housenumber":"4",
    "addr:postcode":"17470",
    "addr:street":"Av. J Tarradellas U Mas Sopas;S. Pere Pescador",
    "iso:country":"ES",
    "sg:address":"Av. J Tarradellas (u Mas Sopas), 4",
    "sg:city":"S. Pere Pescador",
    "sg:orig_category":"Promotores Constructores",
    "sg:phone":"+34 972 55 01 55",
    "sg:postcode":"17470",
    "sg:province":"Girona",
    "wof:name":"2000 Immo Amfora Seveis S.l.",
    "wof:placetype":"venue"
},
  "geometry": {"coordinates":[2.8237,41.981796],"type":"Point"}
}