{
  "type": "Feature",
  "properties": {
    "iso:country":"ES",
    "sg:address":"Senda Granada, 3",
    "sg:city":"Espinardo",
    "sg:orig_category":"Electrodom\u00c9sticos (al Por Menor)",
    "sg:phone":"+34 968 85 85 55",
    "sg:postcode":"30100",
    "sg:province":"Murcia",
    "wof:name":"Electrodomesticos Andreu S.l.",
    "wof:placetype":"venue"
},
  "geometry": {"coordinates":[-1.1571830511,38.0081062317],"type":"Point"}
}