{
  "type": "Feature",
  "properties": {
    "iso:country":"ES",
    "sg:address":"Calle de Kandela Zubieta Kalea, 35 A",
    "sg:city":"Leioa",
    "sg:orig_category":"Electricidad: Instaladores",
    "sg:phone":"+34 944 64 60 54",
    "sg:postcode":"48940",
    "sg:province":"Vizcaya",
    "wof:name":"Electro-rilo, S. L.",
    "wof:placetype":"venue"
},
  "geometry": {"coordinates":[-2.9860789776,43.3275489807],"type":"Point"}
}