{
  "type": "Feature",
  "properties": {
    "addr:full":"Calle de Turon, 6 Ronda M\u00e1laga 29400",
    "addr:housenumber":"6",
    "addr:postcode":"29400",
    "addr:street":"Calle De Turon;Ronda Ma\u0301Laga",
    "iso:country":"ES",
    "sg:address":"Calle de Turon, 6",
    "sg:city":"Ronda",
    "sg:orig_category":"Puertas Y Portales",
    "sg:phone":"+34 952 87 07 88",
    "sg:postcode":"29400",
    "sg:province":"M\u00e1laga",
    "wof:name":"Polanco Ronda S.l",
    "wof:placetype":"venue"
},
  "geometry": {"coordinates":[-5.1625242233,36.7499160767],"type":"Point"}
}