{
  "type": "Feature",
  "properties": {
    "addr:full":"Calle de Domingo Beltran De Otazu, 19 Vitoria-gasteiz \u00c1lava 01012",
    "addr:housenumber":"19",
    "addr:postcode":"01012",
    "addr:street":"Calle De Domingo Beltran De Otazu",
    "iso:country":"ES",
    "sg:address":"Calle de Domingo Beltran De Otazu, 19",
    "sg:city":"Vitoria-gasteiz",
    "sg:orig_category":"Agencias De Viajes",
    "sg:phone":"+34 945 24 97 63",
    "sg:postcode":"01012",
    "sg:province":"\u00c1lava",
    "sg:website":"www.viajeseroski.es",
    "wof:name":"Viajes Eroski S.a.",
    "wof:placetype":"venue"
},
  "geometry": {"coordinates":[-2.6776258945,42.8515205383],"type":"Point"}
}