{
  "type": "Feature",
  "properties": {
    "addr:full":"Pl Progres, 4 Terrassa Barcelona 08224",
    "addr:housenumber":"4",
    "addr:postcode":"08224",
    "addr:street":"Progres",
    "iso:country":"ES",
    "sg:address":"Pl Progres, 4",
    "sg:city":"Terrassa",
    "sg:orig_category":"Arquitectos",
    "sg:phone":"+34 937 33 13 81",
    "sg:postcode":"08224",
    "sg:province":"Barcelona",
    "wof:name":"Puigdomenech Roca Pedro",
    "wof:placetype":"venue"
},
  "geometry": {"coordinates":[2.0062069893,41.5608329773],"type":"Point"}
}