{
  "type": "Feature",
  "properties": {
    "addr:full":"Don Felix Lorca, 18 El Provencio Cuenca 16670",
    "addr:housenumber":"18",
    "addr:postcode":"16670",
    "addr:street":"Lorca;El Provencio",
    "iso:country":"ES",
    "sg:address":"Don Felix Lorca, 18",
    "sg:city":"El Provencio",
    "sg:orig_category":"Molduras, Junquillos, Listones Y Molduras Perforadas",
    "sg:phone":"+34 967 16 61 83",
    "sg:postcode":"16670",
    "sg:province":"Cuenca",
    "wof:name":"Marti Santos Francisco Javier",
    "wof:placetype":"venue"
},
  "geometry": {"coordinates":[-2.5711688995,39.3760414124],"type":"Point"}
}