{
  "type": "Feature",
  "properties": {
    "iso:country":"ES",
    "sg:address":"Avda Prado Valdelagua, 17",
    "sg:city":"Valdelagua",
    "sg:orig_category":"Transportes Por Carretera: Lotes Completos, Mercanc\u00cdas Diversas",
    "sg:phone":"+34 923 13 90 17",
    "sg:postcode":"37194",
    "sg:province":"Salamanca",
    "wof:name":"Martin Hernandez Juan Carlos",
    "wof:placetype":"venue"
},
  "geometry": {"coordinates":[-5.6232438087,40.9325218201],"type":"Point"}
}