{
  "type": "Feature",
  "properties": {
    "addr:full":"Calle de Olaguibel, 22 Vitoria-gasteiz \u00c1lava 01004",
    "addr:housenumber":"22",
    "addr:postcode":"01004",
    "addr:street":"Calle De Olaguibel",
    "iso:country":"ES",
    "sg:address":"Calle de Olaguibel, 22",
    "sg:city":"Vitoria-gasteiz",
    "sg:orig_category":"Moda",
    "sg:phone":"+34 945 28 52 98",
    "sg:postcode":"01004",
    "sg:province":"\u00c1lava",
    "wof:name":"Harrods Men S.c.",
    "wof:placetype":"venue"
},
  "geometry": {"coordinates":[-2.6681950092,42.8460197449],"type":"Point"}
}