{
  "type": "Feature",
  "properties": {
    "addr:full":"Calle de Gran Via, 10 Almazan Soria 42200",
    "addr:housenumber":"10",
    "addr:postcode":"42200",
    "addr:street":"Calle De Gran Via",
    "iso:country":"ES",
    "sg:address":"Calle de Gran Via, 10",
    "sg:city":"Almazan",
    "sg:orig_category":"Empresas De Desmonte",
    "sg:phone":"+34 975 30 17 23",
    "sg:postcode":"42200",
    "sg:province":"Soria",
    "wof:name":"Crespo Gamarra Enrique",
    "wof:placetype":"venue"
},
  "geometry": {"coordinates":[-2.52977705,41.4874267578],"type":"Point"}
}