{
  "type": "Feature",
  "properties": {
    "iso:country":"ES",
    "sg:address":"Virgen Refugio (pi Corredor Autovia), 22",
    "sg:city":"Dos Hermanas",
    "sg:orig_category":"Fabricaci\u00d3n De Tapices Y Moquetas Para Suelos Y Paredes",
    "sg:phone":"+34 955 67 02 24",
    "sg:postcode":"41700",
    "sg:province":"Sevilla",
    "wof:name":"Mendez Moya Susana",
    "wof:placetype":"venue"
},
  "geometry": {"coordinates":[-5.9315237999,37.2690315247],"type":"Point"}
}