{
  "type": "Feature",
  "properties": {
    "iso:country":"ES",
    "sg:address":"Ibabe Pol Ind, 27",
    "sg:city":"Lazkao",
    "sg:orig_category":"Fabricaci\u00d3n, Importaci\u00d3n De L\u00c1mparas Y Bombillas",
    "sg:phone":"+34 943 16 30 91",
    "sg:postcode":"20210",
    "sg:province":"Guip\u00f9zcoa",
    "wof:name":"Zubiaurre Iluminacion C.b",
    "wof:placetype":"venue"
},
  "geometry": {"coordinates":[-2.1873590946,43.0314903259],"type":"Point"}
}