{
  "type": "Feature",
  "properties": {
    "addr:full":"Calle de Venerable Sarrio, 3 Alaquas Valencia 46970",
    "addr:housenumber":"3",
    "addr:postcode":"46970",
    "addr:street":"Calle De Venerable Sarrio",
    "iso:country":"ES",
    "sg:address":"Calle de Venerable Sarrio, 3",
    "sg:city":"Alaquas",
    "sg:orig_category":"Electrodom\u00c9sticos (al Por Menor)",
    "sg:phone":"+34 961 50 37 01",
    "sg:postcode":"46970",
    "sg:province":"Valencia",
    "wof:name":"Isern Reparaciones,s.l.",
    "wof:placetype":"venue"
},
  "geometry": {"coordinates":[-0.4589119852,39.4577445984],"type":"Point"}
}