{
  "type": "Feature",
  "properties": {
    "addr:full":"Calle de Norte, 3 Valencia Valencia 46008",
    "addr:housenumber":"3",
    "addr:postcode":"46008",
    "addr:street":"Calle De Norte",
    "iso:country":"ES",
    "sg:address":"Calle de Norte, 3",
    "sg:city":"Valencia",
    "sg:orig_category":"Venta, Alquiler De Instrumentos Y Accesorios De M\u00dasica",
    "sg:phone":"+34 963 82 05 18",
    "sg:postcode":"46008",
    "sg:province":"Valencia",
    "wof:name":"Sonido Y Luz Musical Torres S.l.",
    "wof:placetype":"venue"
},
  "geometry": {"coordinates":[-0.3904004991,39.4747581482],"type":"Point"}
}