{
  "type": "Feature",
  "properties": {
    "iso:country":"ES",
    "sg:address":"Calle de Manteria, 28",
    "sg:city":"Valladolid",
    "sg:orig_category":"Ropa De Hogar (al Por Menor)",
    "sg:phone":"+34 983 39 71 72",
    "sg:postcode":"47004",
    "sg:province":"Valladolid",
    "sg:website":"www.revitex.com",
    "wof:name":"Almacenes Revitex S.l.",
    "wof:placetype":"venue"
},
  "geometry": {"coordinates":[-4.7220082283,41.6484603882],"type":"Point"}
}