{
  "type": "Feature",
  "properties": {
    "addr:full":"Calle de Triana, 45 Palmas De Gran Canaria Las Palmas 35002",
    "addr:housenumber":"45",
    "addr:postcode":"35002",
    "addr:street":"Calle De Triana",
    "iso:country":"ES",
    "sg:address":"Calle de Triana, 45",
    "sg:city":"Palmas De Gran Canaria",
    "sg:orig_category":"Ropa Para Se\u00d1oras Y Caballeros (al Por Menor)",
    "sg:phone":"+34 928 36 57 77",
    "sg:postcode":"35002",
    "sg:province":"Las Palmas",
    "sg:website":"www.massimodutti.com",
    "wof:name":"Grupo Massimo Dutti S.a.",
    "wof:placetype":"venue"
},
  "geometry": {"coordinates":[-15.4159097672,28.1049175262],"type":"Point"}
}