{
  "type": "Feature",
  "properties": {
    "addr:full":"Avda Moya (de), S/n San Fernando Las Palmas 35100",
    "addr:housenumber":"/ n",
    "addr:postcode":"35100",
    "addr:street":"Avda Moya De S",
    "iso:country":"ES",
    "sg:address":"Avda Moya (de), S/n",
    "sg:city":"San Fernando",
    "sg:orig_category":"Imprenta",
    "sg:phone":"+34 928 72 01 38",
    "sg:postcode":"35100",
    "sg:province":"Las Palmas",
    "wof:name":"Leon Montero Alby",
    "wof:placetype":"venue"
},
  "geometry": {"coordinates":[-15.5842504501,28.0904903412],"type":"Point"}
}