{
  "type": "Feature",
  "properties": {
    "iso:country":"ES",
    "sg:address":"Calle de Geraneo, 2",
    "sg:city":"Oliva Frontera",
    "sg:orig_category":"Suministros Para Hoteles",
    "sg:phone":"+34 924 74 02 63",
    "sg:postcode":"06120",
    "sg:province":"Badajoz",
    "wof:name":"Delgado Pinilla Antonio",
    "wof:placetype":"venue"
},
  "geometry": {"coordinates":[-6.9155139923,38.2829017639],"type":"Point"}
}