{
  "type": "Feature",
  "properties": {
    "iso:country":"ES",
    "sg:address":"Calle de Santa Marta, 13",
    "sg:city":"Aceuchal",
    "sg:orig_category":"Cerrajer\u00cda, Ferrallista",
    "sg:phone":"+34 924 68 74 00",
    "sg:postcode":"06207",
    "sg:province":"Badajoz",
    "wof:name":"Perez Guerrero Antonio",
    "wof:placetype":"venue"
},
  "geometry": {"coordinates":[-6.4901947975,38.6461448669],"type":"Point"}
}