{
  "type": "Feature",
  "properties": {
    "iso:country":"ES",
    "sg:address":"Calle de San Millan, 6",
    "sg:city":"Logro\u00f1o",
    "sg:orig_category":"Bebidas",
    "sg:phone":"+34 941 27 18 50",
    "sg:postcode":"26004",
    "sg:province":"La Rioja",
    "wof:name":"Compa\u00f1ia Norte\u00f1a De Bebidas Gaseosas Norbega S. A.",
    "wof:placetype":"venue"
},
  "geometry": {"coordinates":[-2.4329359531,42.46459198],"type":"Point"}
}