{
  "type": "Feature",
  "properties": {
    "addr:full":"Calle de Hermanos Gonzalez Blanco, 11 Luanco Asturias 33440",
    "addr:housenumber":"11",
    "addr:postcode":"33440",
    "addr:street":"Calle De Hermanos Gonzalez Blanco;Luanco Asturias",
    "iso:country":"ES",
    "sg:address":"Calle de Hermanos Gonzalez Blanco, 11",
    "sg:city":"Luanco",
    "sg:orig_category":"Transportes Por Carretera: Lotes Completos, Mercanc\u00cdas Diversas",
    "sg:phone":"+34 985 88 19 03",
    "sg:postcode":"33440",
    "sg:province":"Asturias",
    "wof:name":"Grupo El Arbol Distribucion Y Supermercados S.a. Unipersonal",
    "wof:placetype":"venue"
},
  "geometry": {"coordinates":[-5.7926640511,43.6158981323],"type":"Point"}
}