{
  "type": "Feature",
  "properties": {
    "iso:country":"ES",
    "sg:address":"Calle de Limite, S/n",
    "sg:city":"Torrejon Ardoz",
    "sg:orig_category":"Electricidad: Equipos Industriales, Componentes (fabricaci\u00d3n)",
    "sg:phone":"+34 916 75 59 80",
    "sg:postcode":"28850",
    "sg:province":"Madrid",
    "sg:website":"www.foresis.es",
    "wof:name":"Foresis S.a.",
    "wof:placetype":"venue"
},
  "geometry": {"coordinates":[-3.4917879105,40.4601860046],"type":"Point"}
}