{
  "type": "Feature",
  "properties": {
    "iso:country":"ES",
    "sg:address":"Calle de Ciudad Rodrigo, 5",
    "sg:city":"Madrid",
    "sg:orig_category":"Carnicer\u00cdas, Carnicer\u00cdas",
    "sg:phone":"+34 915 48 02 23",
    "sg:postcode":"28012",
    "sg:province":"Madrid",
    "wof:name":"Ferrero Calvo Miguel",
    "wof:placetype":"venue"
},
  "geometry": {"coordinates":[-3.7086696625,40.4158172607],"type":"Point"}
}