{
  "type": "Feature",
  "properties": {
    "addr:full":"Calle de B - Poligono Industrial De Asipo, S/n Coru\u00d1o Asturias 33428",
    "addr:housenumber":"s",
    "addr:postcode":"33428",
    "addr:street":"Calle De;Poligono Industrial De Asipo;/ N Corun\u0303O Asturias",
    "iso:country":"ES",
    "sg:address":"Calle de B - Poligono Industrial De Asipo, S/n",
    "sg:city":"Coru\u00d1o",
    "sg:orig_category":"Goma: Materias Primas (producci\u00d3n, Distribuci\u00d3n)",
    "sg:phone":"+34 985 26 57 89",
    "sg:postcode":"33428",
    "sg:province":"Asturias",
    "wof:name":"Vetusplas S.l",
    "wof:placetype":"venue"
},
  "geometry": {"coordinates":[-5.8358402252,43.4143867493],"type":"Point"}
}