{
  "type": "Feature",
  "properties": {
    "addr:full":"Carrer de Pedro Cano, 13 Mutxamel Alicante 03110",
    "addr:housenumber":"13",
    "addr:postcode":"03110",
    "addr:street":"Carrer De Pedro Cano",
    "iso:country":"ES",
    "sg:address":"Carrer de Pedro Cano, 13",
    "sg:city":"Mutxamel",
    "sg:orig_category":"Organizaciones Profesionales",
    "sg:phone":"+34 965 95 09 68",
    "sg:postcode":"03110",
    "sg:province":"Alicante",
    "wof:name":"Decoexsa Mediterraneo S.a.",
    "wof:placetype":"venue"
},
  "geometry": {"coordinates":[-0.4435760081,38.4181098938],"type":"Point"}
}