{
  "type": "Feature",
  "properties": {
    "addr:full":"Avda Julian Besteiro, 94 Olvera C\u00e1diz 11690",
    "addr:housenumber":"94",
    "addr:postcode":"11690",
    "addr:street":"Avda Julian Besteiro;Ca\u0301Diz",
    "iso:country":"ES",
    "sg:address":"Avda Julian Besteiro, 94",
    "sg:city":"Olvera",
    "sg:orig_category":"Cooperativas Agr\u00cdcolas",
    "sg:phone":"+34 956 13 01 84",
    "sg:postcode":"11690",
    "sg:province":"C\u00e1diz",
    "wof:name":"Mi Super Albeyco S.a.",
    "wof:placetype":"venue"
},
  "geometry": {"coordinates":[-5.2542247772,36.9344940186],"type":"Point"}
}