{
  "type": "Feature",
  "properties": {
    "addr:full":"Avda Mediterraneo, S/n Segorbe Castell\u00f3n 12400",
    "addr:postcode":"12400",
    "addr:street":"Avda Mediterraneo S / N;Castello\u0301N",
    "iso:country":"ES",
    "sg:address":"Avda Mediterraneo, S/n",
    "sg:city":"Segorbe",
    "sg:orig_category":"Empresas De Carpinter\u00cda De Madera",
    "sg:phone":"+34 964 71 12 24",
    "sg:postcode":"12400",
    "sg:province":"Castell\u00f3n",
    "sg:website":"www.puertasdecocina.com",
    "wof:name":"Jesus De Haro S.l.",
    "wof:placetype":"venue"
},
  "geometry": {"coordinates":[-0.4825490117,39.8458900452],"type":"Point"}
}