{
  "type": "Feature",
  "properties": {
    "iso:country":"ES",
    "sg:address":"Calle de Embajador Vich, 22",
    "sg:city":"Valencia",
    "sg:orig_category":"M\u00c9dicos: Otorrinolaringolog\u00cda",
    "sg:phone":"+34 963 94 46 49",
    "sg:postcode":"46002",
    "sg:province":"Valencia",
    "wof:name":"Ferrandis Cardona Eduardo",
    "wof:placetype":"venue"
},
  "geometry": {"coordinates":[-0.375451088,39.4717063904],"type":"Point"}
}