{
  "type": "Feature",
  "properties": {
    "addr:full":"Av Prat De La Riba, 35 Reus Tarragona 43201",
    "addr:housenumber":"35",
    "addr:postcode":"43201",
    "addr:street":"Av Prat De La Riba",
    "iso:country":"ES",
    "sg:address":"Av Prat De La Riba, 35",
    "sg:city":"Reus",
    "sg:orig_category":"Cajas De Ahorro",
    "sg:phone":"+34 977 31 64 62",
    "sg:postcode":"43201",
    "sg:province":"Tarragona",
    "sg:website":"www.caixatarragona.es",
    "wof:name":"Caixa D'estalvis De Tarragona",
    "wof:placetype":"venue"
},
  "geometry": {"coordinates":[1.1034040451,41.1574897766],"type":"Point"}
}