{
  "type": "Feature",
  "properties": {
    "addr:full":"Tientos, 18 Carmona Sevilla 41410",
    "addr:housenumber":"18",
    "addr:postcode":"41410",
    "addr:street":"Tientos",
    "iso:country":"ES",
    "sg:address":"Tientos, 18",
    "sg:city":"Carmona",
    "sg:orig_category":"Guarder\u00cdas",
    "sg:phone":"+34 954 19 11 79",
    "sg:postcode":"41410",
    "sg:province":"Sevilla",
    "wof:name":"Roman Cruz Jose Luis",
    "wof:placetype":"venue"
},
  "geometry": {"coordinates":[-5.6433792114,37.4708709717],"type":"Point"}
}