{
  "type": "Feature",
  "properties": {
    "addr:full":"Calle de Baja, 23 Malaga M\u00e1laga 29018",
    "addr:housenumber":"23",
    "addr:postcode":"29018",
    "addr:street":"Calle De Baja;Ma\u0301Laga",
    "iso:country":"ES",
    "sg:address":"Calle de Baja, 23",
    "sg:city":"Malaga",
    "sg:orig_category":"Asociaciones, Organismos Culturales Y Socioeducativos",
    "sg:phone":"+34 952 29 11 48",
    "sg:postcode":"29018",
    "sg:province":"M\u00e1laga",
    "wof:name":"Colegio Platero Sdad.coop.and.",
    "wof:placetype":"venue"
},
  "geometry": {"coordinates":[-4.3460521698,36.7216262817],"type":"Point"}
}