{
  "type": "Feature",
  "properties": {
    "iso:country":"ES",
    "sg:address":"Calle de Pelinor, 2",
    "sg:city":"Punta Brava",
    "sg:orig_category":"Florister\u00cdas",
    "sg:phone":"+34 922 38 54 14",
    "sg:postcode":"38400",
    "sg:province":"Santa Cruz De Tenerife",
    "wof:name":"Dominguez Garcia Maria Milagros",
    "wof:placetype":"venue"
},
  "geometry": {"coordinates":[-16.5658817291,28.4100093842],"type":"Point"}
}