{
  "type": "Feature",
  "properties": {
    "addr:full":"Calle de Pitagoras, 44 Calero Bajo Las Palmas 35200",
    "addr:housenumber":"44",
    "addr:postcode":"35200",
    "addr:street":"Calle De Pitagoras;Las",
    "iso:country":"ES",
    "sg:address":"Calle de Pitagoras, 44",
    "sg:city":"Calero Bajo",
    "sg:orig_category":"Cristaler\u00cdas",
    "sg:phone":"+34 928 68 27 02",
    "sg:postcode":"35200",
    "sg:province":"Las Palmas",
    "wof:name":"Mendoza Santana Matias Fernando",
    "wof:placetype":"venue"
},
  "geometry": {"coordinates":[-15.4144220352,28.0029888153],"type":"Point"}
}