{
  "type": "Feature",
  "properties": {
    "iso:country":"ES",
    "sg:address":"Pase Sagasta, 44",
    "sg:city":"Zaragoza",
    "sg:orig_category":"Ense\u00d1anza Secundaria: Colegios Y Escuelas P\u00dablicas",
    "sg:phone":"+34 976 22 78 98",
    "sg:postcode":"50006",
    "sg:province":"Zaragoza",
    "wof:name":"Colegio Mayor Anunciata En Sagasta 44 Dominicas De La Anunciata Prov Santo Domingo",
    "wof:placetype":"venue"
},
  "geometry": {"coordinates":[-0.8863819838,41.6427574158],"type":"Point"}
}