{
  "type": "Feature",
  "properties": {
    "addr:full":"Av Catalunya, 58 Aldea Tarragona 43896",
    "addr:housenumber":"58",
    "addr:postcode":"43896",
    "addr:street":"Av Catalunya",
    "iso:country":"ES",
    "sg:address":"Av Catalunya, 58",
    "sg:city":"Aldea",
    "sg:orig_category":"Reposter\u00cdas",
    "sg:phone":"+34 977 45 00 98",
    "sg:postcode":"43896",
    "sg:province":"Tarragona",
    "wof:name":"Espuny Arasa Maria Rosa",
    "wof:placetype":"venue"
},
  "geometry": {"coordinates":[0.6105340123,40.7409210205],"type":"Point"}
}