{
  "type": "Feature",
  "properties": {
    "iso:country":"ES",
    "sg:address":"Calle de Capitan Mendizabal, 29",
    "sg:city":"Santurtzi",
    "sg:orig_category":"Bisuter\u00cda, Joyer\u00cda, Relojer\u00cda (al Por Menor)",
    "sg:phone":"+34 944 83 02 12",
    "sg:postcode":"48980",
    "sg:province":"Vizcaya",
    "wof:name":"A.b. Alta Bisuteria (amaia Uribe Martinez)",
    "wof:placetype":"venue"
},
  "geometry": {"coordinates":[-3.035486,43.332138],"type":"Point"}
}