{
  "type": "Feature",
  "properties": {
    "addr:full":"Calle de Menendez Pelayo, 37 Linares Ja\u00e9n 23700",
    "addr:housenumber":"37",
    "addr:postcode":"23700",
    "addr:street":"Calle De Menendez Pelayo;Jae\u0301N",
    "iso:country":"ES",
    "sg:address":"Calle de Menendez Pelayo, 37",
    "sg:city":"Linares",
    "sg:orig_category":"Herboristas (al Por Menor)",
    "sg:phone":"+34 953 65 34 53",
    "sg:postcode":"23700",
    "sg:province":"Ja\u00e9n",
    "wof:name":"Carrasco Carrasco Mateo",
    "wof:placetype":"venue"
},
  "geometry": {"coordinates":[-3.6305320263,38.0946121216],"type":"Point"}
}