{
  "type": "Feature",
  "properties": {
    "addr:full":"Calle de Andalucia, 16 Torreperogil Ja\u00e9n 23320",
    "addr:housenumber":"16",
    "addr:postcode":"23320",
    "addr:street":"Calle De Andalucia",
    "iso:country":"ES",
    "sg:address":"Calle de Andalucia, 16",
    "sg:city":"Torreperogil",
    "sg:orig_category":"Droguer\u00cdas (al Por Menor)",
    "sg:phone":"+34 953 77 80 67",
    "sg:postcode":"23320",
    "sg:province":"Ja\u00e9n",
    "wof:name":"Exposito Ruiz Juana Maria",
    "wof:placetype":"venue"
},
  "geometry": {"coordinates":[-3.2904009819,38.0350570679],"type":"Point"}
}