{
  "type": "Feature",
  "properties": {
    "addr:full":"Avda Ferrol (del), 5 Viveiro Lugo 27850",
    "addr:housenumber":"5",
    "addr:postcode":"27850",
    "addr:street":"Avda Ferrol Del",
    "iso:country":"ES",
    "sg:address":"Avda Ferrol (del), 5",
    "sg:city":"Viveiro",
    "sg:orig_category":"Peluquer\u00cdas, Peluquer\u00cda Mixta",
    "sg:phone":"+34 982 55 19 19",
    "sg:postcode":"27850",
    "sg:province":"Lugo",
    "wof:name":"Salgueiro Gomez Angeles",
    "wof:placetype":"venue"
},
  "geometry": {"coordinates":[-7.5992488861,43.6569519043],"type":"Point"}
}