{
  "type": "Feature",
  "properties": {
    "iso:country":"ES",
    "sg:address":"Calle de Santa Ana, 29",
    "sg:city":"Pedro Bernardo",
    "sg:orig_category":"Sanatorios M\u00c9dico",
    "sg:phone":"+34 920 38 74 00",
    "sg:postcode":"05470",
    "sg:province":"\u00c1vila",
    "wof:name":"Ayuntamiento De Pedro Bernardo",
    "wof:placetype":"venue"
},
  "geometry": {"coordinates":[-4.9102640152,40.2421951294],"type":"Point"}
}