{
  "type": "Feature",
  "properties": {
    "addr:full":"Calle de Rosario, 6 Albacete Albacete 02001",
    "addr:housenumber":"6",
    "addr:postcode":"02001",
    "addr:street":"Calle De Rosario",
    "iso:country":"ES",
    "sg:address":"Calle de Rosario, 6",
    "sg:city":"Albacete",
    "sg:orig_category":"Sociedades, Compa\u00d1\u00cdas Aseguradoras",
    "sg:phone":"+34 967 21 24 91",
    "sg:postcode":"02001",
    "sg:province":"Albacete",
    "sg:website":"www.agrupacionsanitaria.com",
    "wof:name":"Agrupacion Sanitaria S. A.",
    "wof:placetype":"venue"
},
  "geometry": {"coordinates":[-1.8554381132,38.9953308105],"type":"Point"}
}