{
  "type": "Feature",
  "properties": {
    "addr:full":"Avda San Jose, 176 Zaragoza Zaragoza 50007",
    "addr:housenumber":"176",
    "addr:postcode":"50007",
    "addr:street":"Avda San Jose",
    "iso:country":"ES",
    "sg:address":"Avda San Jose, 176",
    "sg:city":"Zaragoza",
    "sg:orig_category":"Centros De Coordinaci\u00d3n",
    "sg:phone":"+34 976 37 64 76",
    "sg:postcode":"50007",
    "sg:province":"Zaragoza",
    "wof:name":"Villa Gazulla Pedro",
    "wof:placetype":"venue"
},
  "geometry": {"coordinates":[-0.878715992,41.6361503601],"type":"Point"}
}