{
  "type": "Feature",
  "properties": {
    "iso:country":"ES",
    "sg:address":"Calle de Inglaterra, 2",
    "sg:city":"San Fernando",
    "sg:orig_category":"Promotores Constructores",
    "sg:phone":"+34 922 38 53 50",
    "sg:postcode":"38400",
    "sg:province":"Santa Cruz De Tenerife",
    "wof:name":"Prosa Promociones Y Edificaciones Turisticas S.a",
    "wof:placetype":"venue"
},
  "geometry": {"coordinates":[-16.5464935303,28.409406662],"type":"Point"}
}