{
  "type": "Feature",
  "properties": {
    "addr:full":"Calle de Mu\u00d1oz Grandes, S/n Almarcha Cuenca 16740",
    "addr:housenumber":"s / n",
    "addr:postcode":"16740",
    "addr:street":"Calle De Mun\u0303Oz Grandes",
    "iso:country":"ES",
    "sg:address":"Calle de Mu\u00d1oz Grandes, S/n",
    "sg:city":"Almarcha",
    "sg:orig_category":"Reposter\u00cdas",
    "sg:phone":"+34 969 29 12 95",
    "sg:postcode":"16740",
    "sg:province":"Cuenca",
    "wof:name":"Panaderia Jayla S.l.",
    "wof:placetype":"venue"
},
  "geometry": {"coordinates":[-2.3800289631,39.6852912903],"type":"Point"}
}