{
  "type": "Feature",
  "properties": {
    "addr:full":"Calle de Almeria, 42 Aguilas Murcia 30880",
    "addr:housenumber":"42",
    "addr:postcode":"30880",
    "addr:street":"Calle De Almeria",
    "iso:country":"ES",
    "sg:address":"Calle de Almeria, 42",
    "sg:city":"Aguilas",
    "sg:orig_category":"Asociaciones Y Clubs Deportivos",
    "sg:phone":"+34 968 41 01 48",
    "sg:postcode":"30880",
    "sg:province":"Murcia",
    "wof:name":"Restaurante Rosa De Los Vientos S.l",
    "wof:placetype":"venue"
},
  "geometry": {"coordinates":[-1.587302804,37.4102668762],"type":"Point"}
}