{
  "type": "Feature",
  "properties": {
    "addr:full":"Plaz Herriko Plaza, 7 San Vicente De Barakaldo Vizcaya 48901",
    "addr:housenumber":"7",
    "addr:postcode":"48901",
    "addr:street":"Herriko Plaza",
    "iso:country":"ES",
    "sg:address":"Plaz Herriko Plaza, 7",
    "sg:city":"San Vicente De Barakaldo",
    "sg:orig_category":"M\u00c9dicos: Estomatolog\u00cda",
    "sg:phone":"+34 944 38 32 67",
    "sg:postcode":"48901",
    "sg:province":"Vizcaya",
    "wof:name":"Garay Llarena Oscar",
    "wof:placetype":"venue"
},
  "geometry": {"coordinates":[-2.986330986,43.2968101501],"type":"Point"}
}