{
  "type": "Feature",
  "properties": {
    "addr:full":"Calle de Angustias (las), 2 Cacabelos Le\u00f3n 24540",
    "addr:housenumber":"2",
    "addr:postcode":"24540",
    "addr:street":"Calle De Angustias Las",
    "iso:country":"ES",
    "sg:address":"Calle de Angustias (las), 2",
    "sg:city":"Cacabelos",
    "sg:orig_category":"Productos Fitosanitarios (negocio, Aplicaci\u00d3n)",
    "sg:phone":"+34 987 54 68 99",
    "sg:postcode":"24540",
    "sg:province":"Le\u00f3n",
    "wof:name":"Defensa Del Campo S. A.",
    "wof:placetype":"venue"
},
  "geometry": {"coordinates":[-6.7302722931,42.5992660522],"type":"Point"}
}