{
  "type": "Feature",
  "properties": {
    "addr:full":"Calle de Juan Caro, 65 Fuensalida Toledo 45510",
    "addr:housenumber":"65",
    "addr:postcode":"45510",
    "addr:street":"Calle De Juan Caro",
    "iso:country":"ES",
    "sg:address":"Calle de Juan Caro, 65",
    "sg:city":"Fuensalida",
    "sg:orig_category":"Fabricaci\u00d3n De Jabones, Detergentes Y Lej\u00cdas",
    "sg:phone":"+34 925 78 44 97",
    "sg:postcode":"45510",
    "sg:province":"Toledo",
    "wof:name":"C.g. Agesi S.l.",
    "wof:placetype":"venue"
},
  "geometry": {"coordinates":[-4.2068891525,40.0551300049],"type":"Point"}
}