{
  "type": "Feature",
  "properties": {
    "iso:country":"ES",
    "sg:address":"Calle de Gonzalo De Berceo, 66",
    "sg:city":"Madrid",
    "sg:orig_category":"Contenedores (mercanc\u00cdas)",
    "sg:phone":"+34 913 77 53 42",
    "sg:postcode":"28017",
    "sg:province":"Madrid",
    "wof:name":"Gutierrez Rodriguez Francisco Javier",
    "wof:placetype":"venue"
},
  "geometry": {"coordinates":[-3.6400780678,40.4282608032],"type":"Point"}
}