{
  "type": "Feature",
  "properties": {
    "addr:full":"Carrer de Cristofor Colom, 3 Tarragona Tarragona 43001",
    "addr:housenumber":"3",
    "addr:postcode":"43001",
    "addr:street":"Carrer De Cristofor Colom",
    "iso:country":"ES",
    "sg:address":"Carrer de Cristofor Colom, 3",
    "sg:city":"Tarragona",
    "sg:orig_category":"Confiter\u00cdas, Chocolater\u00cdas (al Por Menor)",
    "sg:phone":"+34 977 24 09 64",
    "sg:postcode":"43001",
    "sg:province":"Tarragona",
    "wof:name":"Alcantara Curiel Benito",
    "wof:placetype":"venue"
},
  "geometry": {"coordinates":[1.2488181591,41.1167411804],"type":"Point"}
}