{
  "type": "Feature",
  "properties": {
    "iso:country":"ES",
    "sg:address":"Calle de Marcelino Blasco, 4",
    "sg:city":"Segorbe",
    "sg:orig_category":"Molduras, Junquillos, Listones Y Molduras Perforadas",
    "sg:phone":"+34 964 71 37 99",
    "sg:postcode":"12400",
    "sg:province":"Castell\u00f3n",
    "wof:name":"Gomez Mu\u00f1oz Jose",
    "wof:placetype":"venue"
},
  "geometry": {"coordinates":[-0.4890789986,39.8506507874],"type":"Point"}
}