{
  "type": "Feature",
  "properties": {
    "addr:full":"G.v. Lopez De Haro D. Diego, 40 Bilbao Vizcaya 48009",
    "addr:housenumber":"40",
    "addr:postcode":"48009",
    "addr:street":"Lopez De Haro D. Diego",
    "iso:country":"ES",
    "sg:address":"G.v. Lopez De Haro D. Diego, 40",
    "sg:city":"Bilbao",
    "sg:orig_category":"M\u00c9dicos: An\u00c1lisis Cl\u00cdnicos",
    "sg:phone":"+34 944 23 73 42",
    "sg:postcode":"48009",
    "sg:province":"Vizcaya",
    "wof:name":"Laboratorio Axpe S.l.",
    "wof:placetype":"venue"
},
  "geometry": {"coordinates":[-2.9339931011,43.2629127502],"type":"Point"}
}