{
  "type": "Feature",
  "properties": {
    "iso:country":"ES",
    "sg:address":"Carrer de Verger, 6",
    "sg:city":"Ondara",
    "sg:orig_category":"Animales (al Por Menor)",
    "sg:phone":"+34 965 76 70 51",
    "sg:postcode":"03760",
    "sg:province":"Alicante",
    "wof:name":"Piensos Felix S.l.",
    "wof:placetype":"venue"
},
  "geometry": {"coordinates":[0.01657,38.8288383484],"type":"Point"}
}