{
  "type": "Feature",
  "properties": {
    "addr:full":"Carrer de Nou De Santa Eulalia, 14 Barcelona Barcelona 08017",
    "addr:housenumber":"14",
    "addr:postcode":"08017",
    "addr:street":"Carrer De Nou De Santa Eulalia",
    "iso:country":"ES",
    "sg:address":"Carrer de Nou De Santa Eulalia, 14",
    "sg:city":"Barcelona",
    "sg:orig_category":"Suministros Para Exposiciones, Ferias, Salones",
    "sg:phone":"+34 932 04 00 54",
    "sg:postcode":"08017",
    "sg:province":"Barcelona",
    "wof:name":"Solina Feliu Maria Victoria",
    "wof:placetype":"venue"
},
  "geometry": {"coordinates":[2.1188519001,41.4031410217],"type":"Point"}
}