{
  "type": "Feature",
  "properties": {
    "addr:full":"Vinqui\u00f1o, 31 Vinqui\u00d1o Pontevedra 36979",
    "addr:housenumber":"31",
    "addr:postcode":"36979",
    "addr:street":"Vinquin\u0303O",
    "iso:country":"ES",
    "sg:address":"Vinqui\u00f1o, 31",
    "sg:city":"Vinqui\u00d1o",
    "sg:orig_category":"Pintura Y Barniz (al Por Menor)",
    "sg:phone":"+34 986 72 36 84",
    "sg:postcode":"36979",
    "sg:province":"Pontevedra",
    "sg:website":"www.iq-eurocolor.com",
    "wof:name":"Sueiro Vilavedra Victoriano",
    "wof:placetype":"venue"
},
  "geometry": {"coordinates":[-8.8140735626,42.416015625],"type":"Point"}
}