{
  "type": "Feature",
  "properties": {
    "iso:country":"ES",
    "sg:address":"Calle de Cuartel Nuevo, 8",
    "sg:city":"San Ildefonso O La Granja",
    "sg:orig_category":"Lencer\u00cda Femenina, Corseter\u00cda, Trajes De Ba\u00d1o (al Por Menor)",
    "sg:phone":"+34 921 47 15 63",
    "sg:postcode":"40100",
    "sg:province":"Segovia",
    "wof:name":"Alonso Perez Serafina",
    "wof:placetype":"venue"
},
  "geometry": {"coordinates":[-4.0073604584,40.9001312256],"type":"Point"}
}