{
  "type": "Feature",
  "properties": {
    "addr:full":"Avda Fernandez Latorre, 110 Coru\u00d1a La Coru\u00f1a 15006",
    "addr:housenumber":"110",
    "addr:postcode":"15006",
    "addr:street":"Avda Fernandez Latorre;Corun\u0303A",
    "iso:country":"ES",
    "sg:address":"Avda Fernandez Latorre, 110",
    "sg:city":"Coru\u00d1a",
    "sg:orig_category":"Alquiler De Veh\u00cdculos: Turismos Y Utilitarios",
    "sg:phone":"+34 981 23 86 45",
    "sg:postcode":"15006",
    "sg:province":"La Coru\u00f1a",
    "wof:name":"Autos Brea S. L.",
    "wof:placetype":"venue"
},
  "geometry": {"coordinates":[-8.404545784,43.3556938171],"type":"Point"}
}