{
  "type": "Feature",
  "properties": {
    "addr:full":"Avda Diputacion (de La), 1 Chiclana De La Frontera C\u00e1diz 11130",
    "addr:postcode":"11130",
    "addr:street":"Avda Diputacion De La 1",
    "iso:country":"ES",
    "sg:address":"Avda Diputacion (de La), 1",
    "sg:city":"Chiclana De La Frontera",
    "sg:orig_category":"Caf\u00c9s, Bares, Cervecer\u00cdas",
    "sg:phone":"+34 956 53 64 86",
    "sg:postcode":"11130",
    "sg:province":"C\u00e1diz",
    "wof:name":"Panificadora Butron S.l.",
    "wof:placetype":"venue"
},
  "geometry": {"coordinates":[-6.1584792137,36.4166145325],"type":"Point"}
}