{
  "type": "Feature",
  "properties": {
    "iso:country":"ES",
    "sg:address":"Avda Reina Sofia, 23",
    "sg:city":"Tobarra",
    "sg:orig_category":"Asesor\u00cda Fiscal Y Jur\u00cddica",
    "sg:phone":"+34 967 32 56 60",
    "sg:postcode":"02500",
    "sg:province":"Albacete",
    "wof:name":"Central Administrativa Tobarra S.l.",
    "wof:placetype":"venue"
},
  "geometry": {"coordinates":[-1.6877640486,38.593044281],"type":"Point"}
}