{
  "type": "Feature",
  "properties": {
    "addr:full":"Plaz Poligono Industrial La Torrecilla, S/n Cordoba C\u00f3rdoba 14013",
    "addr:housenumber":"s / n",
    "addr:postcode":"14013",
    "addr:street":"Plaz Poligono Industrial La Torrecilla;Co\u0301Rdoba",
    "iso:country":"ES",
    "sg:address":"Plaz Poligono Industrial La Torrecilla, S/n",
    "sg:city":"Cordoba",
    "sg:orig_category":"Autob\u00das (explotaci\u00d3n Y Servicios De)",
    "sg:phone":"+34 957 42 21 77",
    "sg:postcode":"14013",
    "sg:province":"C\u00f3rdoba",
    "sg:website":"www.autocaresr.ramirezs.l.com",
    "wof:name":"Rafael Ramirez S.l.",
    "wof:placetype":"venue"
},
  "geometry": {"coordinates":[-4.7784028053,37.8779411316],"type":"Point"}
}