{
  "type": "Feature",
  "properties": {
    "iso:country":"ES",
    "sg:address":"Calle de Pico Almanzor, 12",
    "sg:city":"Arganda",
    "sg:orig_category":"Materiales De Aislamiento T\u00c9rmico Y Ac\u00dastico",
    "sg:phone":"+34 918 71 81 62",
    "sg:postcode":"28500",
    "sg:province":"Madrid",
    "wof:name":"Distribuidora De Tubos Y Aislamientos S.a.",
    "wof:placetype":"venue"
},
  "geometry": {"coordinates":[-3.4823949337,40.3083076477],"type":"Point"}
}