{
  "type": "Feature",
  "properties": {
    "iso:country":"ES",
    "sg:address":"Portamui\u00f1o, 7",
    "sg:city":"Portamui\u00d1o",
    "sg:orig_category":"Centro De Estudios",
    "sg:phone":"+34 986 86 06 27",
    "sg:postcode":"36099",
    "sg:province":"Pontevedra",
    "wof:name":"Hifas Da Terra S.l.",
    "wof:placetype":"venue"
},
  "geometry": {"coordinates":[-8.5766801834,42.4327888489],"type":"Point"}
}