{
  "type": "Feature",
  "properties": {
    "addr:full":"Ctra Madrid-cadiz, Km. 0588,0 Utrera Sevilla 41710",
    "addr:postcode":"41710",
    "addr:street":"Ctra Madrid-Cadiz Km. 0588,0",
    "iso:country":"ES",
    "sg:address":"Ctra Madrid-cadiz, Km. 0588,0",
    "sg:city":"Utrera",
    "sg:orig_category":"Centros Empresariales",
    "sg:phone":"+34 955 89 80 25",
    "sg:postcode":"41710",
    "sg:province":"Sevilla",
    "wof:name":"Belmonte Cossio Blanca",
    "wof:placetype":"venue"
},
  "geometry": {"coordinates":[-5.779173851,37.184223175],"type":"Point"}
}