{
  "type": "Feature",
  "properties": {
    "iso:country":"ES",
    "sg:address":"Poli Talluntxe / Talluntze Industrialdea, 32",
    "sg:city":"Noain",
    "sg:orig_category":"Promotores Constructores",
    "sg:phone":"+34 948 31 24 10",
    "sg:postcode":"31110",
    "sg:province":"Navarra",
    "sg:website":"www.edegsl.com",
    "wof:name":"Construcciones Edeg S.l.",
    "wof:placetype":"venue"
},
  "geometry": {"coordinates":[-1.6338239908,42.7598800659],"type":"Point"}
}