{
  "type": "Feature",
  "properties": {
    "addr:full":"Calle de Industria, 6 Gernika-lumo Vizcaya 48300",
    "addr:housenumber":"6",
    "addr:postcode":"48300",
    "addr:street":"Calle De Industria",
    "iso:country":"ES",
    "sg:address":"Calle de Industria, 6",
    "sg:city":"Gernika-lumo",
    "sg:orig_category":"Molduras, Junquillos, Listones Y Molduras Perforadas",
    "sg:phone":"+34 946 25 19 90",
    "sg:postcode":"48300",
    "sg:province":"Vizcaya",
    "wof:name":"Onaindia Guena Jon Dunixi",
    "wof:placetype":"venue"
},
  "geometry": {"coordinates":[-2.677656889,43.3132514954],"type":"Point"}
}