{
  "type": "Feature",
  "properties": {
    "addr:full":"Calle de Trajano, 26 Almeria Almer\u00eda 04001",
    "addr:housenumber":"26",
    "addr:postcode":"04001",
    "addr:street":"Calle De Trajano",
    "iso:country":"ES",
    "sg:address":"Calle de Trajano, 26",
    "sg:city":"Almeria",
    "sg:orig_category":"Peluqueros: De Se\u00d1oras",
    "sg:phone":"+34 950 23 86 97",
    "sg:postcode":"04001",
    "sg:province":"Almer\u00eda",
    "wof:name":"Paris Arrufat Manuel",
    "wof:placetype":"venue"
},
  "geometry": {"coordinates":[-2.4652369022,36.8382720947],"type":"Point"}
}