{
  "type": "Feature",
  "properties": {
    "addr:full":"Calle de Manuel Sanchis Guarner, 8 Xirivella Valencia 46950",
    "addr:housenumber":"8",
    "addr:postcode":"46950",
    "addr:street":"Calle De Manuel Sanchis Guarner",
    "iso:country":"ES",
    "sg:address":"Calle de Manuel Sanchis Guarner, 8",
    "sg:city":"Xirivella",
    "sg:orig_category":"Fabricaci\u00d3n De Mobiliario Met\u00c1lico",
    "sg:phone":"+34 963 59 43 02",
    "sg:postcode":"46950",
    "sg:province":"Valencia",
    "wof:name":"Legua Roig Francisco",
    "wof:placetype":"venue"
},
  "geometry": {"coordinates":[-0.4353489876,39.4635658264],"type":"Point"}
}