{
  "type": "Feature",
  "properties": {
    "addr:full":"Calle de Zamacola, 150 Bilbao Vizcaya 48003",
    "addr:housenumber":"150",
    "addr:postcode":"48003",
    "addr:street":"Calle De Zamacola",
    "iso:country":"ES",
    "sg:address":"Calle de Zamacola, 150",
    "sg:city":"Bilbao",
    "sg:orig_category":"Asociaciones, Organismos Culturales Y Socioeducativos",
    "sg:phone":"+34 944 16 69 85",
    "sg:postcode":"48003",
    "sg:province":"Vizcaya",
    "wof:name":"Sociedad Cultural Meatza",
    "wof:placetype":"venue"
},
  "geometry": {"coordinates":[-2.9233241081,43.2410926819],"type":"Point"}
}