{
  "type": "Feature",
  "properties": {
    "iso:country":"ES",
    "sg:address":"Carrer de Vilamar, 42",
    "sg:city":"Playa De Calafell",
    "sg:orig_category":"Molduras, Junquillos, Listones Y Molduras Perforadas",
    "sg:phone":"+34 977 69 31 97",
    "sg:postcode":"43820",
    "sg:province":"Tarragona",
    "wof:name":"Sole Bardalet Pere",
    "wof:placetype":"venue"
},
  "geometry": {"coordinates":[1.5725500584,41.1877174377],"type":"Point"}
}