{
  "type": "Feature",
  "properties": {
    "iso:country":"ES",
    "sg:address":"Calle de Tambre, 21",
    "sg:city":"Madrid",
    "sg:orig_category":"Arquitectos",
    "sg:phone":"+34 913 56 34 86",
    "sg:postcode":"28002",
    "sg:province":"Madrid",
    "wof:name":"Puerta Lopez-cozar Antonio",
    "wof:placetype":"venue"
},
  "geometry": {"coordinates":[-3.6862900257,40.4472007751],"type":"Point"}
}