{
  "type": "Feature",
  "properties": {
    "addr:full":"Ctra. Colmenar Oreja, Km. 0007,2 Villaconejos Madrid 28360",
    "addr:postcode":"28360",
    "addr:street":"Ctra. Colmenar Oreja Km. 0007,2",
    "iso:country":"ES",
    "sg:address":"Ctra. Colmenar Oreja, Km. 0007,2",
    "sg:city":"Villaconejos",
    "sg:orig_category":"Construcciones Met\u00c1licas",
    "sg:phone":"+34 918 93 90 89",
    "sg:postcode":"28360",
    "sg:province":"Madrid",
    "wof:name":"Leduma Construcciones Metalicas S.l.",
    "wof:placetype":"venue"
},
  "geometry": {"coordinates":[-3.481924057,40.1053390503],"type":"Point"}
}