{
  "type": "Feature",
  "properties": {
    "iso:country":"ES",
    "sg:address":"Ctra Palma, Km. 0037,0",
    "sg:city":"Campos",
    "sg:orig_category":"Hormig\u00d3n (m\u00c1quinas E Instalaci\u00d3n)",
    "sg:phone":"+34 971 65 26 30",
    "sg:postcode":"07630",
    "sg:province":"Islas Baleares",
    "wof:name":"Metba Nhb S.l.",
    "wof:placetype":"venue"
},
  "geometry": {"coordinates":[3.0197050571,39.430480957],"type":"Point"}
}