{
  "type": "Feature",
  "properties": {
    "addr:full":"Calle de Albacete, 5 Povedilla Albacete 02311",
    "addr:housenumber":"5",
    "addr:postcode":"02311",
    "addr:street":"Calle De Albacete",
    "iso:country":"ES",
    "sg:address":"Calle de Albacete, 5",
    "sg:city":"Povedilla",
    "sg:orig_category":"Farmacias",
    "sg:phone":"+34 967 39 20 89",
    "sg:postcode":"02311",
    "sg:province":"Albacete",
    "wof:name":"Ruiz De La Fuente Garcia Isabel",
    "wof:placetype":"venue"
},
  "geometry": {"coordinates":[-2.602145195,38.7010116577],"type":"Point"}
}