{
  "type": "Feature",
  "properties": {
    "addr:full":"Pla\u00c7 Espanya, 1 Tossa Girona 17320",
    "addr:postcode":"17320",
    "addr:street":"Tossa",
    "iso:country":"ES",
    "sg:address":"Pla\u00c7 Espanya, 1",
    "sg:city":"Tossa",
    "sg:orig_category":"Ropa Para Se\u00d1oras Y Caballeros (al Por Menor)",
    "sg:phone":"+34 972 34 13 35",
    "sg:postcode":"17320",
    "sg:province":"Girona",
    "wof:name":"Sola Molinas Josep Maria",
    "wof:placetype":"venue"
},
  "geometry": {"coordinates":[2.9298949242,41.7226753235],"type":"Point"}
}