{
  "type": "Feature",
  "properties": {
    "addr:full":"Calle de Val De La Cueva, 3 Cadrete Zaragoza 50420",
    "addr:housenumber":"3",
    "addr:postcode":"50420",
    "addr:street":"Calle De Val De La Cueva",
    "iso:country":"ES",
    "sg:address":"Calle de Val De La Cueva, 3",
    "sg:city":"Cadrete",
    "sg:orig_category":"Poli\u00c9ster",
    "sg:phone":"+34 976 12 66 68",
    "sg:postcode":"50420",
    "sg:province":"Zaragoza",
    "wof:name":"Arpofi S.l.",
    "wof:placetype":"venue"
},
  "geometry": {"coordinates":[-0.9581751227,41.5522689819],"type":"Point"}
}