{
  "type": "Feature",
  "properties": {
    "addr:full":"Calle de Alava, 50 Barriada Cuatro Santos Murcia 30310",
    "addr:housenumber":"50",
    "addr:postcode":"30310",
    "addr:street":"Calle De Alava",
    "iso:country":"ES",
    "sg:address":"Calle de Alava, 50",
    "sg:city":"Barriada Cuatro Santos",
    "sg:orig_category":"Persianas Interiores, Exteriores",
    "sg:phone":"+34 968 53 60 68",
    "sg:postcode":"30310",
    "sg:province":"Murcia",
    "wof:name":"Zaplana Garcia Francisco Jose",
    "wof:placetype":"venue"
},
  "geometry": {"coordinates":[-1.1298867464,37.9834747314],"type":"Point"}
}