{
  "type": "Feature",
  "properties": {
    "addr:full":"Calle de Tejo, 17 Fuemblanca Sevilla 41909",
    "addr:housenumber":"17",
    "addr:postcode":"41909",
    "addr:street":"Calle De Tejo",
    "iso:country":"ES",
    "sg:address":"Calle de Tejo, 17",
    "sg:city":"Fuemblanca",
    "sg:orig_category":"Electricidad: Instaladores",
    "sg:phone":"+34 955 70 75 12",
    "sg:postcode":"41909",
    "sg:province":"Sevilla",
    "wof:name":"Nuevas Instalaciones Andaluzas S.l",
    "wof:placetype":"venue"
},
  "geometry": {"coordinates":[-6.1071691513,37.4179992676],"type":"Point"}
}