{
  "type": "Feature",
  "properties": {
    "addr:full":"Carrer de Sant Sebastia, 164 Terrassa Barcelona 08223",
    "addr:housenumber":"164",
    "addr:postcode":"08223",
    "addr:street":"Carrer De Sant Sebastia",
    "iso:country":"ES",
    "sg:address":"Carrer de Sant Sebastia, 164",
    "sg:city":"Terrassa",
    "sg:orig_category":"Audiovisuales (producci\u00d3n, Edici\u00d3n, Realizaci\u00d3n)",
    "sg:phone":"+34 937 84 16 22",
    "sg:postcode":"08223",
    "sg:province":"Barcelona",
    "sg:website":"www.neptunofilms.com",
    "wof:name":"Neptuno Films S.l.",
    "wof:placetype":"venue"
},
  "geometry": {"coordinates":[2.012583971,41.5554466248],"type":"Point"}
}