{
  "type": "Feature",
  "properties": {
    "addr:full":"Calle de Ildefonso Manuel Gil, 28 Zaragoza Zaragoza 50015",
    "addr:housenumber":"28",
    "addr:postcode":"50015",
    "addr:street":"Calle De Ildefonso Manuel Gil",
    "iso:country":"ES",
    "sg:address":"Calle de Ildefonso Manuel Gil, 28",
    "sg:city":"Zaragoza",
    "sg:orig_category":"Papeler\u00cdas, Librer\u00cdas",
    "sg:phone":"+34 976 74 30 46",
    "sg:postcode":"50015",
    "sg:province":"Zaragoza",
    "wof:name":"Vazquez Perozo Jose Antonio",
    "wof:placetype":"venue"
},
  "geometry": {"coordinates":[-0.8846656084,41.6715507507],"type":"Point"}
}