{
  "type": "Feature",
  "properties": {
    "iso:country":"ES",
    "sg:address":"Calle de Dragaminas, 32",
    "sg:city":"Palmones",
    "sg:orig_category":"Organizaciones Profesionales",
    "sg:phone":"+34 956 67 84 51",
    "sg:postcode":"11379",
    "sg:province":"C\u00e1diz",
    "sg:website":"www.itssa.es",
    "wof:name":"Integral Transport Service S.a.",
    "wof:placetype":"venue"
},
  "geometry": {"coordinates":[-5.4356474876,36.1813087463],"type":"Point"}
}