{
  "type": "Feature",
  "properties": {
    "iso:country":"ES",
    "sg:address":"Carrer de Urquinaona, 84",
    "sg:city":"Terrassa",
    "sg:orig_category":"Maquinaria Y Material Para Tiendas De Alimentaci\u00d3n",
    "sg:phone":"+34 937 36 33 30",
    "sg:postcode":"08222",
    "sg:province":"Barcelona",
    "wof:name":"Ebanisteria Orbis S.l.",
    "wof:placetype":"venue"
},
  "geometry": {"coordinates":[2.0245449543,41.568069458],"type":"Point"}
}