{
  "type": "Feature",
  "properties": {
    "iso:country":"ES",
    "sg:address":"Calle de Acebuche, S/n",
    "sg:city":"Barrera",
    "sg:orig_category":"Fabricaci\u00d3n De Bebidas No Alcoh\u00d3licas",
    "sg:phone":"+34 928 57 06 70",
    "sg:postcode":"35217",
    "sg:province":"Las Palmas",
    "sg:website":"www.aguacasa.com",
    "wof:name":"Aguas Tratadas Canarias S.l.",
    "wof:placetype":"venue"
},
  "geometry": {"coordinates":[-15.4734582901,27.9952793121],"type":"Point"}
}