{
  "type": "Feature",
  "properties": {
    "iso:country":"ES",
    "sg:address":"Ctra Madrid, Km. 0382,5",
    "sg:city":"Molina Segura",
    "sg:orig_category":"Insecticidas, Fumigaci\u00d3n",
    "sg:phone":"+34 968 64 14 57",
    "sg:postcode":"30500",
    "sg:province":"Murcia",
    "wof:name":"Probelte S.a.",
    "wof:placetype":"venue"
},
  "geometry": {"coordinates":[-1.2119740248,38.0535736084],"type":"Point"}
}