{
  "type": "Feature",
  "properties": {
    "addr:full":"Avda Real De Pinto, 54 Madrid Madrid 28021",
    "addr:housenumber":"54",
    "addr:postcode":"madrid;28021",
    "addr:street":"Avda Real De Pinto",
    "iso:country":"ES",
    "sg:address":"Avda Real De Pinto, 54",
    "sg:city":"Madrid",
    "sg:orig_category":"Electricidad (montaje, Ensamblaje De Componentes)",
    "sg:phone":"+34 917 97 14 49",
    "sg:postcode":"28021",
    "sg:province":"Madrid",
    "wof:name":"Montes Hernandez Juana",
    "wof:placetype":"venue"
},
  "geometry": {"coordinates":[-3.7071330547,40.3443107605],"type":"Point"}
}