{
  "type": "Feature",
  "properties": {
    "iso:country":"ES",
    "sg:address":"Calle de Blas Infante, 7",
    "sg:city":"Gerena",
    "sg:orig_category":"Electrodom\u00c9sticos (fabricaci\u00d3n, Al Por Mayor)",
    "sg:phone":"+34 955 78 22 48",
    "sg:postcode":"41860",
    "sg:province":"Sevilla",
    "wof:name":"Electromuebles Gutierrez S.l.",
    "wof:placetype":"venue"
},
  "geometry": {"coordinates":[-6.1582026482,37.5267219543],"type":"Point"}
}