{
  "type": "Feature",
  "properties": {
    "addr:full":"Jimenado, S/n Torre-pacheco Murcia 30700",
    "addr:postcode":"30700",
    "addr:street":"Jimenado S / N",
    "iso:country":"ES",
    "sg:address":"Jimenado, S/n",
    "sg:city":"Torre-pacheco",
    "sg:orig_category":"Arboricultura Y Producci\u00d3n De Frutas",
    "sg:phone":"+34 968 57 76 72",
    "sg:postcode":"30700",
    "sg:province":"Murcia",
    "wof:name":"Pascual Hermanos S.a.",
    "wof:placetype":"venue"
},
  "geometry": {"coordinates":[-0.9677709937,37.7491073608],"type":"Point"}
}