{
  "type": "Feature",
  "properties": {
    "addr:full":"Avda Quintanar, Km. 0109,2 Villaca\u00f1as Toledo 45860",
    "addr:postcode":"45860",
    "addr:street":"Avda Quintanar Km. 0109,2",
    "iso:country":"ES",
    "sg:address":"Avda Quintanar, Km. 0109,2",
    "sg:city":"Villaca\u00f1as",
    "sg:orig_category":"Distribuci\u00d3n De Petr\u00d3leo Y Derivados",
    "sg:phone":"+34 925 20 14 57",
    "sg:postcode":"45860",
    "sg:province":"Toledo",
    "wof:name":"Gastarays S.l.",
    "wof:placetype":"venue"
},
  "geometry": {"coordinates":[-3.339589119,39.6161231995],"type":"Point"}
}