{
  "type": "Feature",
  "properties": {
    "addr:full":"Calle de Victor Chavarri, 23 Oviedo Asturias 33001",
    "addr:housenumber":"23",
    "addr:postcode":"33001",
    "addr:street":"Calle De Victor Chavarri",
    "iso:country":"ES",
    "sg:address":"Calle de Victor Chavarri, 23",
    "sg:city":"Oviedo",
    "sg:orig_category":"Cl\u00cdnicas M\u00c9dicas",
    "sg:phone":"+34 985 21 17 50",
    "sg:postcode":"33001",
    "sg:province":"Asturias",
    "wof:name":"Servicios Medicos Del Principado De Asturias",
    "wof:placetype":"venue"
},
  "geometry": {"coordinates":[-5.8429422379,43.3655548096],"type":"Point"}
}