{
  "type": "Feature",
  "properties": {
    "iso:country":"ES",
    "sg:address":"Calle de Mayor, S/n",
    "sg:city":"Villanua",
    "sg:orig_category":"Abogados",
    "sg:phone":"+34 974 37 81 54",
    "sg:postcode":"22870",
    "sg:province":"Huesca",
    "wof:name":"Isasi Abogados S.l.",
    "wof:placetype":"venue"
},
  "geometry": {"coordinates":[-0.5305839777,42.6788787842],"type":"Point"}
}