{
  "type": "Feature",
  "properties": {
    "addr:full":"Av Magaluf, 7 Magaluf Islas Baleares 07181",
    "addr:housenumber":"7",
    "addr:postcode":"07181",
    "addr:street":"Av Magaluf",
    "iso:country":"ES",
    "sg:address":"Av Magaluf, 7",
    "sg:city":"Magaluf",
    "sg:orig_category":"Molduras, Junquillos, Listones Y Molduras Perforadas",
    "sg:phone":"+34 971 13 02 01",
    "sg:postcode":"07181",
    "sg:province":"Islas Baleares",
    "wof:name":"Saiz Sacristan Justino",
    "wof:placetype":"venue"
},
  "geometry": {"coordinates":[2.5339460373,39.5079193115],"type":"Point"}
}