{
  "type": "Feature",
  "properties": {
    "addr:full":"Carrer de Fray Luis De Leon, 78 Mataro Barcelona 08302",
    "addr:housenumber":"78",
    "addr:postcode":"08302",
    "addr:street":"Carrer De Fray Luis De Leon",
    "iso:country":"ES",
    "sg:address":"Carrer de Fray Luis De Leon, 78",
    "sg:city":"Mataro",
    "sg:orig_category":"Electrodom\u00c9sticos (al Por Menor)",
    "sg:phone":"+34 937 99 48 12",
    "sg:postcode":"08302",
    "sg:province":"Barcelona",
    "wof:name":"Sanchez Garcia Antoni",
    "wof:placetype":"venue"
},
  "geometry": {"coordinates":[2.4380409718,41.5400161743],"type":"Point"}
}