{
  "type": "Feature",
  "properties": {
    "addr:full":"Calle de Pizarro, 5 Corralejo Las Palmas 35660",
    "addr:housenumber":"5",
    "addr:postcode":"35660",
    "addr:street":"Calle De Pizarro",
    "iso:country":"ES",
    "sg:address":"Calle de Pizarro, 5",
    "sg:city":"Corralejo",
    "sg:orig_category":"Alquiler De V\u00cddeo",
    "sg:phone":"+34 928 53 58 64",
    "sg:postcode":"35660",
    "sg:province":"Las Palmas",
    "wof:name":"Gonzalez Balsera Alejandro",
    "wof:placetype":"venue"
},
  "geometry": {"coordinates":[-13.8697490692,28.7385501862],"type":"Point"}
}