{
  "type": "Feature",
  "properties": {
    "addr:full":"Calle de Alfonso Pe\u00d1a, 20 Valencia Valencia 46009",
    "addr:housenumber":"20",
    "addr:postcode":"46009",
    "addr:street":"Calle De Alfonso Pen\u0303A",
    "iso:country":"ES",
    "sg:address":"Calle de Alfonso Pe\u00d1a, 20",
    "sg:city":"Valencia",
    "sg:orig_category":"Quincaller\u00cda (al Por Menor)",
    "sg:phone":"+34 963 48 00 72",
    "sg:postcode":"46009",
    "sg:province":"Valencia",
    "wof:name":"Maquinaria Limpiezas Clemente S.l.",
    "wof:placetype":"venue"
},
  "geometry": {"coordinates":[-0.3770379126,39.4897880554],"type":"Point"}
}