{
  "type": "Feature",
  "properties": {
    "addr:full":"Calle de San Jose, 3 Santa Maria De Guia Las Palmas 35450",
    "addr:housenumber":"3",
    "addr:postcode":"35450",
    "addr:street":"Calle De San Jose",
    "iso:country":"ES",
    "sg:address":"Calle de San Jose, 3",
    "sg:city":"Santa Maria De Guia",
    "sg:orig_category":"Mercer\u00cda, Lencer\u00cda (al Por Menor)",
    "sg:phone":"+34 928 89 54 48",
    "sg:postcode":"35450",
    "sg:province":"Las Palmas",
    "wof:name":"Rios Cruz Amada",
    "wof:placetype":"venue"
},
  "geometry": {"coordinates":[-15.6324872971,28.1394863129],"type":"Point"}
}