{
  "type": "Feature",
  "properties": {
    "iso:country":"ES",
    "sg:address":"Calle de Santiago, 11",
    "sg:city":"Linares",
    "sg:orig_category":"Electricidad: Equipos Industriales, Componentes (fabricaci\u00d3n)",
    "sg:phone":"+34 953 65 03 13",
    "sg:postcode":"23700",
    "sg:province":"Ja\u00e9n",
    "wof:name":"Pla Ramos Jose",
    "wof:placetype":"venue"
},
  "geometry": {"coordinates":[-3.6366970539,38.0941696167],"type":"Point"}
}