{
  "type": "Feature",
  "properties": {
    "iso:country":"ES",
    "sg:address":"Avda Mediterraneo, 11",
    "sg:city":"Madrid",
    "sg:orig_category":"Asesor\u00cda Sobre Comunicaci\u00d3n De Empresas",
    "sg:phone":"+34 915 01 29 36",
    "sg:postcode":"28007",
    "sg:province":"Madrid",
    "wof:name":"Grupo Asesor Empresarial Sociedad Cooperativa",
    "wof:placetype":"venue"
},
  "geometry": {"coordinates":[-3.6766819954,40.4075164795],"type":"Point"}
}