{
  "type": "Feature",
  "properties": {
    "addr:full":"Calle de Arturo Soria, 191 Madrid Madrid 28043",
    "addr:housenumber":"191",
    "addr:postcode":"28043",
    "addr:street":"Calle De Arturo Soria",
    "iso:country":"ES",
    "sg:address":"Calle de Arturo Soria, 191",
    "sg:city":"Madrid",
    "sg:orig_category":"Cajas Para Embalar",
    "sg:phone":"+34 914 15 99 05",
    "sg:postcode":"28043",
    "sg:province":"Madrid",
    "sg:website":"www.cajamar.es",
    "wof:name":"Cajamar",
    "wof:placetype":"venue"
},
  "geometry": {"coordinates":[-3.6595807076,40.4587478638],"type":"Point"}
}