{
  "type": "Feature",
  "properties": {
    "addr:full":"Carrer de Ruperto Chapi, 17 Campello Alicante 03560",
    "addr:housenumber":"17",
    "addr:postcode":"03560",
    "addr:street":"Carrer De Ruperto Chapi",
    "iso:country":"ES",
    "sg:address":"Carrer de Ruperto Chapi, 17",
    "sg:city":"Campello",
    "sg:orig_category":"Inversiones",
    "sg:phone":"+34 965 63 53 41",
    "sg:postcode":"03560",
    "sg:province":"Alicante",
    "wof:name":"Pena Rodriguez Rogelio",
    "wof:placetype":"venue"
},
  "geometry": {"coordinates":[-0.3907479942,38.430770874],"type":"Point"}
}