{
  "type": "Feature",
  "properties": {
    "iso:country":"ES",
    "sg:address":"Calle de Juan Sebastian Bach, 2",
    "sg:city":"Palmas De Gran Canaria",
    "sg:classifiers":[
        {
            "category":"Taxi",
            "type":"Transportation"
        }
    ],
    "sg:phone":"+34 928 31 50 03",
    "sg:postcode":"35016",
    "sg:province":"Las Palmas",
    "wof:name":"Pe\u00f1ate Ramirez Angel",
    "wof:placetype":"venue"
},
  "geometry": {"coordinates":[-15.4193687439,28.0743560791],"type":"Point"}
}