{
  "type": "Feature",
  "properties": {
    "iso:country":"ES",
    "sg:address":"Avda Constitucion De La, S/n",
    "sg:city":"Arroyo De La Miel-benalmadena Costa",
    "sg:orig_category":"Fotograf\u00cda Y Cine: Aparatos, Pel\u00cdculas Y Accesorios (fabricaci\u00d3n, Al Por Mayor)",
    "sg:phone":"+34 952 56 79 48",
    "sg:postcode":"29630",
    "sg:province":"M\u00e1laga",
    "wof:name":"Interservicios Fotograficos S.l.",
    "wof:placetype":"venue"
},
  "geometry": {"coordinates":[-4.5284705162,36.6006584167],"type":"Point"}
}