{
  "type": "Feature",
  "properties": {
    "addr:full":"Calle de Miquel Adlert I Noguerol, Km. 0347,5 Mislata Valencia 46920",
    "addr:postcode":"46920",
    "addr:street":"Calle De Miquel Adlert;Noguerol Km. 0347,5",
    "iso:country":"ES",
    "sg:address":"Calle de Miquel Adlert I Noguerol, Km. 0347,5",
    "sg:city":"Mislata",
    "sg:orig_category":"Inmobiliaria (agencias)",
    "sg:phone":"+34 963 94 17 81",
    "sg:postcode":"46920",
    "sg:province":"Valencia",
    "wof:name":"Pomonovo S.a.",
    "wof:placetype":"venue"
},
  "geometry": {"coordinates":[-0.41425699,39.4772796631],"type":"Point"}
}