{
  "type": "Feature",
  "properties": {
    "addr:full":"Calle de Zurbano, 25 Madrid Madrid 28010",
    "addr:housenumber":"25",
    "addr:postcode":"madrid;28010",
    "addr:street":"Calle De Zurbano",
    "iso:country":"ES",
    "sg:address":"Calle de Zurbano, 25",
    "sg:city":"Madrid",
    "sg:orig_category":"Agencias Y Agentes Comerciales, Representantes",
    "sg:phone":"+34 913 19 15 82",
    "sg:postcode":"28010",
    "sg:province":"Madrid",
    "wof:name":"Martin Blazquez Elvira",
    "wof:placetype":"venue"
},
  "geometry": {"coordinates":[-3.693721056,40.4304008484],"type":"Point"}
}