{
  "type": "Feature",
  "properties": {
    "iso:country":"ES",
    "sg:address":"Calle de Jovellanos, S/n",
    "sg:city":"Alhaurin Torre",
    "sg:orig_category":"Inmobiliaria (agencias)",
    "sg:phone":"+34 952 41 01 71",
    "sg:postcode":"29130",
    "sg:province":"M\u00e1laga",
    "wof:name":"Promociones Montsan 2002 S.l.",
    "wof:placetype":"venue"
},
  "geometry": {"coordinates":[-4.5597391129,36.6610107422],"type":"Point"}
}