{
  "type": "Feature",
  "properties": {
    "iso:country":"ES",
    "sg:address":"Carrer de Onze De Setembre, 9",
    "sg:city":"Mollet Valles",
    "sg:classifiers":[
        {
            "category":"Personal",
            "subcategory":"Barber",
            "type":"Services"
        }
    ],
    "sg:phone":"+34 935 93 08 85",
    "sg:postcode":"08100",
    "sg:province":"Barcelona",
    "sg:tags":[
        "caballeros",
        "de",
        "peluqueros"
    ],
    "wof:name":"Saura Yepes Jose",
    "wof:placetype":"venue"
},
  "geometry": {"coordinates":[2.2084379196,41.5346183777],"type":"Point"}
}