{
  "type": "Feature",
  "properties": {
    "iso:country":"ES",
    "sg:address":"Lugar Estacion M (p I Pto Algeciras), S/n",
    "sg:city":"Algeciras",
    "sg:orig_category":"Agencias De Viajes",
    "sg:phone":"+34 956 65 15 61",
    "sg:postcode":"11201",
    "sg:province":"C\u00e1diz",
    "wof:name":"Viajes Avemar S.l.",
    "wof:placetype":"venue"
},
  "geometry": {"coordinates":[-5.4526491165,36.1276016235],"type":"Point"}
}