{
  "type": "Feature",
  "properties": {
    "iso:country":"ES",
    "sg:address":"Terminillo(empr.), Km. 0002,0",
    "sg:city":"Cuenca",
    "sg:orig_category":"Oficinas De Turismo, Asociaciones De Iniciativa",
    "sg:phone":"+34 969 24 01 41",
    "sg:postcode":"16003",
    "sg:province":"Cuenca",
    "wof:name":"Patronato De Desarrollo Provincial De La Excma. Diputacion Provincial",
    "wof:placetype":"venue"
},
  "geometry": {"coordinates":[-2.1362390518,40.0720710754],"type":"Point"}
}