{
  "type": "Feature",
  "properties": {
    "addr:full":"Calle de Palomera, 21 Le\u00f3n Le\u00f3n 24007",
    "addr:housenumber":"21",
    "addr:postcode":"24007",
    "addr:street":"Calle De Palomera;Leo\u0301N",
    "iso:country":"ES",
    "sg:address":"Calle de Palomera, 21",
    "sg:city":"Le\u00f3n",
    "sg:orig_category":"Ferreter\u00cda (diversos)",
    "sg:phone":"+34 987 22 20 45",
    "sg:postcode":"24007",
    "sg:province":"Le\u00f3n",
    "wof:name":"Guerrero Ordas Segundo",
    "wof:placetype":"venue"
},
  "geometry": {"coordinates":[-5.5671200752,42.6028289795],"type":"Point"}
}