{
  "type": "Feature",
  "properties": {
    "iso:country":"ES",
    "sg:address":"Carrer de Sants, 49",
    "sg:city":"Barcelona",
    "sg:orig_category":"Centros M\u00c9dicos Y Sociales, Dispensarios",
    "sg:phone":"+34 934 22 20 51",
    "sg:postcode":"08014",
    "sg:province":"Barcelona",
    "wof:name":"Saenz Rebull Julio",
    "wof:placetype":"venue"
},
  "geometry": {"coordinates":[2.1381518841,41.3753204346],"type":"Point"}
}