{
  "type": "Feature",
  "properties": {
    "iso:country":"ES",
    "sg:address":"Calle de Serreta, 1",
    "sg:city":"Cartagena",
    "sg:orig_category":"Farmacias",
    "sg:phone":"+34 968 50 37 15",
    "sg:postcode":"30201",
    "sg:province":"Murcia",
    "wof:name":"Sanchez Carrascosa Salvador",
    "wof:placetype":"venue"
},
  "geometry": {"coordinates":[-0.9837219715,37.6039886475],"type":"Point"}
}