{
  "type": "Feature",
  "properties": {
    "addr:full":"Pol Ind Les Pedreres, 3 Montgat Barcelona 08390",
    "addr:housenumber":"3",
    "addr:postcode":"08390",
    "addr:street":"Pedreres",
    "iso:country":"ES",
    "sg:address":"Pol Ind Les Pedreres, 3",
    "sg:city":"Montgat",
    "sg:orig_category":"M\u00c1quinas, Material Y Suministros Para Cajas Y Embalajes",
    "sg:phone":"+34 934 69 01 23",
    "sg:postcode":"08390",
    "sg:province":"Barcelona",
    "sg:website":"www.moscadirectspain.com",
    "wof:name":"Mosca Direct Spain S.l.",
    "wof:placetype":"venue"
},
  "geometry": {"coordinates":[2.2785899639,41.4666290283],"type":"Point"}
}