{
  "type": "Feature",
  "properties": {
    "addr:full":"Avda San Agustin De Guadalix (de), 48 Colmenar Viejo Madrid 28770",
    "addr:postcode":"28770",
    "addr:street":"Avda San Agustin De Guadalix De",
    "iso:country":"ES",
    "sg:address":"Avda San Agustin De Guadalix (de), 48",
    "sg:city":"Colmenar Viejo",
    "sg:orig_category":"Instalaci\u00d3n, Reparaci\u00d3n De Calefacci\u00d3n El\u00c9ctrica",
    "sg:phone":"+34 918 45 84 00",
    "sg:postcode":"28770",
    "sg:province":"Madrid",
    "sg:website":"www.etlsl.com",
    "wof:name":"E.t.l. Electro Tank Less S.l.",
    "wof:placetype":"venue"
},
  "geometry": {"coordinates":[-3.7594339848,40.6614112854],"type":"Point"}
}