{
  "type": "Feature",
  "properties": {
    "iso:country":"ES",
    "sg:address":"Calle de Do\u00d1ana (de), 24",
    "sg:city":"Humanes De Madrid",
    "sg:orig_category":"Ferreter\u00cda (diversos)",
    "sg:phone":"+34 916 06 53 06",
    "sg:postcode":"28970",
    "sg:province":"Madrid",
    "wof:name":"Hemader S.l.",
    "wof:placetype":"venue"
},
  "geometry": {"coordinates":[-3.8193116188,40.2697219849],"type":"Point"}
}