{
  "type": "Feature",
  "properties": {
    "addr:full":"Carrer de Proven\u00c7a, 190 Barcelona Barcelona 08036",
    "addr:housenumber":"190",
    "addr:postcode":"08036",
    "addr:street":"Carrer De Provenc\u0327A",
    "iso:country":"ES",
    "sg:address":"Carrer de Proven\u00c7a, 190",
    "sg:city":"Barcelona",
    "sg:orig_category":"Reparaci\u00d3n Y Restauraci\u00d3n De Objetos Diversos",
    "sg:phone":"+34 933 23 59 55",
    "sg:postcode":"08036",
    "sg:province":"Barcelona",
    "wof:name":"San Roman Prats Maria Josefa",
    "wof:placetype":"venue"
},
  "geometry": {"coordinates":[2.1545240879,41.3892936707],"type":"Point"}
}