{
  "type": "Feature",
  "properties": {
    "iso:country":"ES",
    "sg:address":"Calle de Mar Mediterraneo, S/n",
    "sg:city":"Sevilla",
    "sg:orig_category":"Cajas De Ahorro",
    "sg:phone":"+34 954 94 94 08",
    "sg:postcode":"41008",
    "sg:province":"Sevilla",
    "wof:name":"Caja San Fernando De Sevilla Y Jerez",
    "wof:placetype":"venue"
},
  "geometry": {"coordinates":[-5.9640088081,37.4190063477],"type":"Point"}
}