{
  "type": "Feature",
  "properties": {
    "addr:full":"Calle de Manuel Noya, 14 Madrid Madrid 28026",
    "addr:housenumber":"14",
    "addr:postcode":"madrid;28026",
    "addr:street":"Calle De Manuel Noya",
    "iso:country":"ES",
    "sg:address":"Calle de Manuel Noya, 14",
    "sg:city":"Madrid",
    "sg:orig_category":"Agentes, Concesionarios Y Sucursales De Veh\u00cdculos",
    "sg:phone":"+34 914 60 19 75",
    "sg:postcode":"28026",
    "sg:province":"Madrid",
    "wof:name":"Naranjo Peinado Tomas",
    "wof:placetype":"venue"
},
  "geometry": {"coordinates":[-3.7126750946,40.387096405],"type":"Point"}
}