{
  "type": "Feature",
  "properties": {
    "iso:country":"ES",
    "sg:address":"Pase Dolores Soria (de), 8",
    "sg:city":"Pinto",
    "sg:orig_category":"Administradores De Bienes Y Delegados De Comunidades De Propietarios",
    "sg:phone":"+34 916 92 24 30",
    "sg:postcode":"28320",
    "sg:province":"Madrid",
    "wof:name":"Fisper S.l.",
    "wof:placetype":"venue"
},
  "geometry": {"coordinates":[-3.697936058,40.2424278259],"type":"Point"}
}