{
  "type": "Feature",
  "properties": {
    "addr:full":"Calle de Tomas Ibarra, 9 Tomares Sevilla 41940",
    "addr:housenumber":"9",
    "addr:postcode":"41940",
    "addr:street":"Calle De Tomas Ibarra",
    "iso:country":"ES",
    "sg:address":"Calle de Tomas Ibarra, 9",
    "sg:city":"Tomares",
    "sg:orig_category":"Peluqueros: De Se\u00d1oras",
    "sg:phone":"+34 954 15 13 67",
    "sg:postcode":"41940",
    "sg:province":"Sevilla",
    "wof:name":"Capitan Hurtado Miguel Angel",
    "wof:placetype":"venue"
},
  "geometry": {"coordinates":[-6.0454969406,37.3759841919],"type":"Point"}
}