{
  "type": "Feature",
  "properties": {
    "addr:full":"Carrer de Pau Duran, 1 Mas D'en Gall Barcelona 08292",
    "addr:housenumber":"1",
    "addr:postcode":"08292",
    "addr:street":"Carrer De Pau Duran;Barcelona",
    "iso:country":"ES",
    "sg:address":"Carrer de Pau Duran, 1",
    "sg:city":"Mas D'en Gall",
    "sg:orig_category":"Agencias Y Asesores De Publicidad",
    "sg:phone":"+34 937 77 26 12",
    "sg:postcode":"08292",
    "sg:province":"Barcelona",
    "wof:name":"Inmax Virtual S.l.",
    "wof:placetype":"venue"
},
  "geometry": {"coordinates":[2.2131409645,41.4201316833],"type":"Point"}
}