{
  "type": "Feature",
  "properties": {
    "iso:country":"ES",
    "sg:address":"Calle de Jaen, Km. 0426,0",
    "sg:city":"Pulianas",
    "sg:orig_category":"Muebles, Minoristas",
    "sg:phone":"+34 958 41 51 08",
    "sg:postcode":"18197",
    "sg:province":"Granada",
    "sg:website":"www.domuscentral.com",
    "wof:name":"C.c.bibarrambla S.l.",
    "wof:placetype":"venue"
},
  "geometry": {"coordinates":[-3.6097240448,37.2210998535],"type":"Point"}
}