{
  "type": "Feature",
  "properties": {
    "iso:country":"ES",
    "sg:address":"Rond General Mitre, 43",
    "sg:city":"Barcelona",
    "sg:orig_category":"Panader\u00cdas, Panader\u00cdas",
    "sg:phone":"+34 932 80 17 30",
    "sg:postcode":"08017",
    "sg:province":"Barcelona",
    "wof:name":"Pasteleria Gisa S.c.c.p.",
    "wof:placetype":"venue"
},
  "geometry": {"coordinates":[2.1333260536,41.3948516846],"type":"Point"}
}