{
  "type": "Feature",
  "properties": {
    "addr:full":"Calle de Pedro Antonio De Alarcon, 57 Madrid Madrid 28017",
    "addr:housenumber":"57",
    "addr:postcode":"madrid;28017",
    "addr:street":"Calle De Pedro Antonio De Alarcon",
    "iso:country":"ES",
    "sg:address":"Calle de Pedro Antonio De Alarcon, 57",
    "sg:city":"Madrid",
    "sg:orig_category":"Agentes Generales De Seguros",
    "sg:phone":"+34 914 06 16 76",
    "sg:postcode":"28017",
    "sg:province":"Madrid",
    "wof:name":"Sanchez Gonzalez Vicente",
    "wof:placetype":"venue"
},
  "geometry": {"coordinates":[-3.6391890049,40.4284172058],"type":"Point"}
}