{
  "type": "Feature",
  "properties": {
    "addr:full":"Carr Brusel.les, S/n Platja D'aro Girona 17250",
    "addr:housenumber":"s / n",
    "addr:postcode":"17250",
    "addr:street":"Carr Brusel.Les",
    "iso:country":"ES",
    "sg:address":"Carr Brusel.les, S/n",
    "sg:city":"Platja D'aro",
    "sg:orig_category":"Molduras, Junquillos, Listones Y Molduras Perforadas",
    "sg:phone":"+34 972 82 60 77",
    "sg:postcode":"17250",
    "sg:province":"Girona",
    "wof:name":"Monge Carmona Juana",
    "wof:placetype":"venue"
},
  "geometry": {"coordinates":[2.8187398911,41.9808616638],"type":"Point"}
}