{
  "type": "Feature",
  "properties": {
    "iso:country":"ES",
    "sg:address":"Calle de Soria, 29",
    "sg:city":"Ejido",
    "sg:orig_category":"Servicios De Telecomunicaciones",
    "sg:phone":"+34 950 48 78 08",
    "sg:postcode":"04700",
    "sg:province":"Almer\u00eda",
    "wof:name":"France Telecom Espa\u00d1a S.a.",
    "wof:placetype":"venue"
},
  "geometry": {"coordinates":[-2.8127679825,36.7728271484],"type":"Point"}
}