{
  "type": "Feature",
  "properties": {
    "iso:country":"ES",
    "sg:address":"Calle de Velazquez, 11",
    "sg:city":"Benidorm",
    "sg:orig_category":"Inform\u00c1tica, Ofim\u00c1tica (estudios, Asesor\u00cda, Ingenier\u00cda, Formaci\u00d3n)",
    "sg:phone":"+34 966 80 49 88",
    "sg:postcode":"03500",
    "sg:province":"Alicante",
    "sg:website":"www.info-g.com",
    "wof:name":"Esquinas Lara Manuel",
    "wof:placetype":"venue"
},
  "geometry": {"coordinates":[-0.1337659955,38.5432243347],"type":"Point"}
}