{
  "type": "Feature",
  "properties": {
    "addr:full":"Riera Lledoners, 31 Canet Mar Barcelona 08360",
    "addr:housenumber":"31",
    "addr:postcode":"08360",
    "addr:street":"Riera Lledoners",
    "iso:country":"ES",
    "sg:address":"Riera Lledoners, 31",
    "sg:city":"Canet Mar",
    "sg:orig_category":"Supermercados Y Hipermercados",
    "sg:phone":"+34 937 95 60 95",
    "sg:postcode":"08360",
    "sg:province":"Barcelona",
    "wof:name":"Grau Verges S.c.p.",
    "wof:placetype":"venue"
},
  "geometry": {"coordinates":[2.5832009315,41.5894355774],"type":"Point"}
}