{
  "type": "Feature",
  "properties": {
    "iso:country":"ES",
    "sg:address":"Calle de Comunidad De Baleares, 9",
    "sg:city":"Valdemoro",
    "sg:orig_category":"Arquitectos",
    "sg:phone":"+34 918 95 53 86",
    "sg:postcode":"28340",
    "sg:province":"Madrid",
    "wof:name":"Tema Ingenieria Y Proyectos S.c.",
    "wof:placetype":"venue"
},
  "geometry": {"coordinates":[-3.6846630573,40.1909866333],"type":"Point"}
}