{
  "type": "Feature",
  "properties": {
    "iso:country":"ES",
    "sg:address":"Calle de Pintor Sorolla, 2",
    "sg:city":"Valencia",
    "sg:orig_category":"Bancos",
    "sg:phone":"+34 963 98 45 00",
    "sg:postcode":"46...",
    "sg:province":"Valencia",
    "wof:name":"Banco De Valencia S.a.",
    "wof:placetype":"venue"
},
  "geometry": {"coordinates":[-0.3965350091,39.4690895081],"type":"Point"}
}