{
  "type": "Feature",
  "properties": {
    "addr:full":"Calle de Doctor Carracido, 29 Almeria Almer\u00eda 04005",
    "addr:housenumber":"29",
    "addr:postcode":"04005",
    "addr:street":"Calle De Doctor Carracido",
    "iso:country":"ES",
    "sg:address":"Calle de Doctor Carracido, 29",
    "sg:city":"Almeria",
    "sg:orig_category":"Librer\u00cdas",
    "sg:phone":"+34 950 22 82 15",
    "sg:postcode":"04005",
    "sg:province":"Almer\u00eda",
    "wof:name":"Llama Sanchez Virtudes",
    "wof:placetype":"venue"
},
  "geometry": {"coordinates":[-2.4541652203,36.841091156],"type":"Point"}
}