{
  "type": "Feature",
  "properties": {
    "addr:full":"Rua Calvo Sotelo, 67 Cea Ourense 32130",
    "addr:housenumber":"67",
    "addr:postcode":"32130",
    "addr:street":"Rua Calvo Sotelo",
    "iso:country":"ES",
    "sg:address":"Rua Calvo Sotelo, 67",
    "sg:city":"Cea",
    "sg:orig_category":"Reposter\u00cdas",
    "sg:phone":"+34 988 28 20 55",
    "sg:postcode":"32130",
    "sg:province":"Ourense",
    "wof:name":"Noguerol Fernandez Jose",
    "wof:placetype":"venue"
},
  "geometry": {"coordinates":[-7.9867691994,42.475818634],"type":"Point"}
}