{
  "type": "Feature",
  "properties": {
    "addr:full":"Plaz Campo Verde (de), 3 Granada Granada 18001",
    "addr:postcode":"18001",
    "iso:country":"ES",
    "sg:address":"Plaz Campo Verde (de), 3",
    "sg:city":"Granada",
    "sg:orig_category":"Abogados",
    "sg:phone":"+34 958 80 56 80",
    "sg:postcode":"18001",
    "sg:province":"Granada",
    "sg:website":"www.garrigues.com",
    "wof:name":"J&a Garrigues S.l.",
    "wof:placetype":"venue"
},
  "geometry": {"coordinates":[-3.6003389359,37.173992157],"type":"Point"}
}