{
  "type": "Feature",
  "properties": {
    "iso:country":"ES",
    "sg:address":"Avda Andalucia, 15",
    "sg:city":"Villaharta",
    "sg:orig_category":"Bazares, Art\u00cdculos De Limpieza Y De Cocina (al Por Menor)",
    "sg:phone":"+34 957 36 71 44",
    "sg:postcode":"14210",
    "sg:province":"C\u00f3rdoba",
    "wof:name":"Paradelas Diaz Dolores",
    "wof:placetype":"venue"
},
  "geometry": {"coordinates":[-4.9025092125,38.1392784119],"type":"Point"}
}