{
  "type": "Feature",
  "properties": {
    "addr:full":"Carrer de Vapor Vell, 44 Reus Tarragona 43201",
    "addr:housenumber":"44",
    "addr:postcode":"43201",
    "addr:street":"Carrer De Vapor Vell",
    "iso:country":"ES",
    "sg:address":"Carrer de Vapor Vell, 44",
    "sg:city":"Reus",
    "sg:orig_category":"Ropa Para Se\u00d1oras (al Por Menor)",
    "sg:phone":"+34 977 33 06 19",
    "sg:postcode":"43201",
    "sg:province":"Tarragona",
    "wof:name":"Ruiz Gonzalez Jose Antonio",
    "wof:placetype":"venue"
},
  "geometry": {"coordinates":[1.1036809683,41.1521263123],"type":"Point"}
}