{
  "type": "Feature",
  "properties": {
    "addr:full":"Ptda. Planteas, 5 Vilamarxant Valencia 46191",
    "addr:housenumber":"5",
    "addr:postcode":"46191",
    "addr:street":"Ptda. Planteas",
    "iso:country":"ES",
    "sg:address":"Ptda. Planteas, 5",
    "sg:city":"Vilamarxant",
    "sg:orig_category":"Promotores Constructores",
    "sg:phone":"+34 962 71 21 38",
    "sg:postcode":"46191",
    "sg:province":"Valencia",
    "wof:name":"Zanjas Urbanas De Servicios",
    "wof:placetype":"venue"
},
  "geometry": {"coordinates":[-0.6488505006,39.5570449829],"type":"Point"}
}