{
  "type": "Feature",
  "properties": {
    "addr:full":"Calle de Panticosa, 9 Sabi\u00f1anigo Huesca 22600",
    "addr:housenumber":"9",
    "addr:postcode":"22600",
    "addr:street":"Calle De Panticosa",
    "iso:country":"ES",
    "sg:address":"Calle de Panticosa, 9",
    "sg:city":"Sabi\u00f1anigo",
    "sg:orig_category":"M\u00c9dicos: Ginecolog\u00cda Y Obstetricia",
    "sg:phone":"+34 974 48 21 51",
    "sg:postcode":"22600",
    "sg:province":"Huesca",
    "wof:name":"Numancia Andreu Pilar Bego\u00f1a",
    "wof:placetype":"venue"
},
  "geometry": {"coordinates":[-0.3673250079,42.5230255127],"type":"Point"}
}