{
  "type": "Feature",
  "properties": {
    "addr:full":"Pase Castellana, 141 Madrid Madrid 28...",
    "addr:housenumber":"141;28 ...",
    "addr:street":"Castellana;Madrid",
    "iso:country":"ES",
    "sg:address":"Pase Castellana, 141",
    "sg:city":"Madrid",
    "sg:orig_category":"Laboratorios Farmac\u00c9uticos",
    "sg:phone":"+34 913 71 78 00",
    "sg:postcode":"28...",
    "sg:province":"Madrid",
    "wof:name":"Sanofi Pasteur Msd S.a.",
    "wof:placetype":"venue"
},
  "geometry": {"coordinates":[-3.6904060841,40.4595222473],"type":"Point"}
}