{
  "type": "Feature",
  "properties": {
    "addr:full":"Avda Fernandez Balsera De, 44 Aviles Asturias 33402",
    "addr:postcode":"33402",
    "addr:street":"Avda Fernandez",
    "iso:country":"ES",
    "sg:address":"Avda Fernandez Balsera De, 44",
    "sg:city":"Aviles",
    "sg:orig_category":"Frutas, Legumbres Frescas Y Tempranas (al Por Menor)",
    "sg:phone":"+34 985 56 56 82",
    "sg:postcode":"33402",
    "sg:province":"Asturias",
    "wof:name":"Gonzalez Suarez Clara",
    "wof:placetype":"venue"
},
  "geometry": {"coordinates":[-5.9275503159,43.5541534424],"type":"Point"}
}