{
  "type": "Feature",
  "properties": {
    "iso:country":"ES",
    "sg:address":"Calle de Bermudez De Castro, 90",
    "sg:city":"Oviedo",
    "sg:orig_category":"Mec\u00c1nico Del Autom\u00d3vil",
    "sg:phone":"+34 985 28 35 38",
    "sg:postcode":"33011",
    "sg:province":"Asturias",
    "wof:name":"Sanchez Gonzalez Julia",
    "wof:placetype":"venue"
},
  "geometry": {"coordinates":[-5.8349914551,43.3743133545],"type":"Point"}
}