{
  "type": "Feature",
  "properties": {
    "addr:full":"Cmno Galicia, S/n Puebla De Soto Murcia 30836",
    "addr:housenumber":"s / n",
    "addr:postcode":"30836",
    "addr:street":"Cmno Galicia",
    "iso:country":"ES",
    "sg:address":"Cmno Galicia, S/n",
    "sg:city":"Puebla De Soto",
    "sg:orig_category":"Montaje (empresas De)",
    "sg:phone":"+34 968 89 03 01",
    "sg:postcode":"30836",
    "sg:province":"Murcia",
    "wof:name":"Cubiertas Ternifran S.l.",
    "wof:placetype":"venue"
},
  "geometry": {"coordinates":[-1.1931920052,37.9798431396],"type":"Point"}
}