{
  "type": "Feature",
  "properties": {
    "iso:country":"ES",
    "sg:address":"Pase Salon (del), 2",
    "sg:city":"Granada",
    "sg:orig_category":"Caf\u00c9s, Bares, Cervecer\u00cdas",
    "sg:phone":"+34 958 22 44 44",
    "sg:postcode":"18009",
    "sg:province":"Granada",
    "wof:name":"Mam 2003 Servicios De Restauracion S.l.",
    "wof:placetype":"venue"
},
  "geometry": {"coordinates":[-3.5959119797,37.1696853638],"type":"Point"}
}