{
  "type": "Feature",
  "properties": {
    "addr:full":"Calle de Suarez Guerra, 41 Santa Cruz De Tenerife Santa Cruz De Tenerife 38002",
    "addr:housenumber":"41",
    "addr:postcode":"38002",
    "addr:street":"Calle De Suarez Guerra",
    "iso:country":"ES",
    "sg:address":"Calle de Suarez Guerra, 41",
    "sg:city":"Santa Cruz De Tenerife",
    "sg:orig_category":"Bisuter\u00cda, Joyer\u00cda, Relojer\u00cda (al Por Menor)",
    "sg:phone":"+34 922 27 43 15",
    "sg:postcode":"38002",
    "sg:province":"Santa Cruz De Tenerife",
    "wof:name":"Gonzalez Concepcion Maria Dolores",
    "wof:placetype":"venue"
},
  "geometry": {"coordinates":[-16.2523231506,28.4683017731],"type":"Point"}
}