{
  "type": "Feature",
  "properties": {
    "iso:country":"ES",
    "sg:address":"Carrer de Teresa De Cofrents, 5",
    "sg:city":"Barcelona",
    "sg:orig_category":"Asociaciones, Organismos Culturales Y Socioeducativos",
    "sg:phone":"+34 933 50 34 85",
    "sg:postcode":"08031",
    "sg:province":"Barcelona",
    "wof:name":"Centro Cultural Garcia Lorca 9 Barrios",
    "wof:placetype":"venue"
},
  "geometry": {"coordinates":[2.1759109497,41.4426116943],"type":"Point"}
}