{
  "type": "Feature",
  "properties": {
    "addr:full":"Calle de Prado (del), S/n Campodon Madrid 28922",
    "addr:postcode":"28922",
    "addr:street":"Calle De Prado Del S / N Campodon",
    "iso:country":"ES",
    "sg:address":"Calle de Prado (del), S/n",
    "sg:city":"Campodon",
    "sg:orig_category":"Asilos De Ancianos. Centros Privados",
    "sg:phone":"+34 916 16 10 57",
    "sg:postcode":"28922",
    "sg:province":"Madrid",
    "wof:name":"Ramliz S.a.",
    "wof:placetype":"venue"
},
  "geometry": {"coordinates":[-3.8731589317,40.3623008728],"type":"Point"}
}