{
  "type": "Feature",
  "properties": {
    "iso:country":"ES",
    "sg:address":"Carrer de Montserrat, 32",
    "sg:city":"Caldes Montbui",
    "sg:orig_category":"Expertos Contables, Revisores De Cuentas",
    "sg:phone":"+34 938 65 52 42",
    "sg:postcode":"08140",
    "sg:province":"Barcelona",
    "wof:name":"Audit Network S.a.",
    "wof:placetype":"venue"
},
  "geometry": {"coordinates":[2.1671380997,41.6314430237],"type":"Point"}
}