{
  "type": "Feature",
  "properties": {
    "addr:full":"Ctra Sevilla-rosales, Km. 0013,9 San Jose Rinconada Sevilla 41300",
    "addr:postcode":"41300",
    "addr:street":"Ctra Sevilla-Rosales Km. 0013,9",
    "iso:country":"ES",
    "sg:address":"Ctra Sevilla-rosales, Km. 0013,9",
    "sg:city":"San Jose Rinconada",
    "sg:orig_category":"Producci\u00d3n, Venta De Productos De Agricultura Biol\u00d3gica",
    "sg:phone":"+34 955 95 00 17",
    "sg:postcode":"41300",
    "sg:province":"Sevilla",
    "wof:name":"Morales Lardin Leonardo",
    "wof:placetype":"venue"
},
  "geometry": {"coordinates":[-5.9507889748,37.4823112488],"type":"Point"}
}