{
  "type": "Feature",
  "properties": {
    "iso:country":"ES",
    "sg:address":"Cra Mercado (el), 11",
    "sg:city":"Doneztebe",
    "sg:orig_category":"Comercio, Reparaci\u00d3n De Motocicletas, Bicicletas Y Piezas Sueltas",
    "sg:phone":"+34 948 45 07 11",
    "sg:postcode":"31740",
    "sg:province":"Navarra",
    "wof:name":"San Miguel Alzugaray Jose Luis",
    "wof:placetype":"venue"
},
  "geometry": {"coordinates":[-1.6691839695,43.1308174133],"type":"Point"}
}