{
  "type": "Feature",
  "properties": {
    "addr:full":"Urb San Roque, 22 Cacabelos Le\u00f3n 24540",
    "addr:housenumber":"22",
    "addr:postcode":"24540",
    "addr:street":"San Roque",
    "iso:country":"ES",
    "sg:address":"Urb San Roque, 22",
    "sg:city":"Cacabelos",
    "sg:orig_category":"Asesor\u00cda Sobre Comunicaci\u00d3n De Empresas",
    "sg:phone":"+34 987 54 63 30",
    "sg:postcode":"24540",
    "sg:province":"Le\u00f3n",
    "sg:website":"www.iranon.org",
    "wof:name":"Analisis Y Desarrollo De Software S.l.",
    "wof:placetype":"venue"
},
  "geometry": {"coordinates":[-6.7226409912,42.6131362915],"type":"Point"}
}