{
  "type": "Feature",
  "properties": {
    "iso:country":"ES",
    "sg:address":"Calle de Carmen, 14",
    "sg:city":"Cazorla",
    "sg:orig_category":"Centros Empresariales",
    "sg:phone":"+34 953 71 03 60",
    "sg:postcode":"23470",
    "sg:province":"Ja\u00e9n",
    "wof:name":"Asociacion Comarcal De Empresarios De Cazorla",
    "wof:placetype":"venue"
},
  "geometry": {"coordinates":[-3.0014853477,37.9115104675],"type":"Point"}
}