{
  "type": "Feature",
  "properties": {
    "addr:full":"Carrer de Turia, 28 Pinedes Tarragona 43006",
    "addr:housenumber":"28",
    "addr:postcode":"43006",
    "addr:street":"Carrer De Turia",
    "iso:country":"ES",
    "sg:address":"Carrer de Turia, 28",
    "sg:city":"Pinedes",
    "sg:orig_category":"Chapister\u00cda",
    "sg:phone":"+34 977 54 99 60",
    "sg:postcode":"43006",
    "sg:province":"Tarragona",
    "wof:name":"Santaella Juncar Diego",
    "wof:placetype":"venue"
},
  "geometry": {"coordinates":[1.2209249735,41.1154441833],"type":"Point"}
}