{
  "type": "Feature",
  "properties": {
    "addr:full":"Calle de Alta, 2 Priego Cordoba C\u00f3rdoba 14800",
    "addr:housenumber":"2",
    "addr:postcode":"14800",
    "addr:street":"Calle De Alta;Cordoba Co\u0301Rdoba",
    "iso:country":"ES",
    "sg:address":"Calle de Alta, 2",
    "sg:city":"Priego Cordoba",
    "sg:orig_category":"Electricidad: Instaladores",
    "sg:phone":"+34 957 70 08 71",
    "sg:postcode":"14800",
    "sg:province":"C\u00f3rdoba",
    "wof:name":"Foguer Avalos Rafael",
    "wof:placetype":"venue"
},
  "geometry": {"coordinates":[-4.1472387314,37.5095252991],"type":"Point"}
}