{
  "type": "Feature",
  "properties": {
    "iso:country":"ES",
    "sg:address":"Calle de Doctor Mara\u00d1on, 5",
    "sg:city":"Caceres",
    "sg:classifiers":[
        {
            "category":"Government",
            "subcategory":"Office",
            "type":"Public Place"
        }
    ],
    "sg:phone":"+34 927 22 55 50",
    "sg:postcode":"10002",
    "sg:province":"C\u00e1ceres",
    "sg:tags":[
        "interior",
        "administraci\u00d3n",
        "en"
    ],
    "wof:name":"Direccion General De Trafico",
    "wof:placetype":"venue"
},
  "geometry": {"coordinates":[-6.3779778481,39.4689369202],"type":"Point"}
}