{
  "type": "Feature",
  "properties": {
    "iso:country":"ES",
    "sg:address":"Cha\u00f1e, S/n",
    "sg:city":"Vallelado",
    "sg:orig_category":"Negocio De Materiales De Construcci\u00d3n",
    "sg:phone":"+34 921 12 30 09",
    "sg:postcode":"40213",
    "sg:province":"Segovia",
    "wof:name":"Hermanos Alvarez Pinilla S.l.",
    "wof:placetype":"venue"
},
  "geometry": {"coordinates":[-4.4269690514,41.4046897888],"type":"Point"}
}