{
  "type": "Feature",
  "properties": {
    "iso:country":"ES",
    "sg:address":"Avgd Ramon Y Cajal, 9",
    "sg:city":"Quart Poblet",
    "sg:orig_category":"Asociaciones, Organismos Culturales Y Socioeducativos",
    "sg:phone":"+34 961 52 03 18",
    "sg:postcode":"46930",
    "sg:province":"Valencia",
    "wof:name":"Centro Cultural Andaluz",
    "wof:placetype":"venue"
},
  "geometry": {"coordinates":[-0.4419890046,39.482711792],"type":"Point"}
}