{
  "type": "Feature",
  "properties": {
    "iso:country":"ES",
    "sg:address":"Ctra. Girona Palamos, Km. 0022,5",
    "sg:city":"Cor\u00e7a",
    "sg:orig_category":"Piedra, Vidrio, Cer\u00c1mica Y Porcelana",
    "sg:phone":"+34 972 63 01 02",
    "sg:postcode":"17121",
    "sg:province":"Girona",
    "wof:name":"Argiles Colades S. A.",
    "wof:placetype":"venue"
},
  "geometry": {"coordinates":[3.0292191505,41.9727249146],"type":"Point"}
}