{
  "type": "Feature",
  "properties": {
    "iso:country":"ES",
    "sg:address":"Carrer de Cop, 17",
    "sg:city":"Denia",
    "sg:orig_category":"Panader\u00cdas, Panader\u00cdas",
    "sg:phone":"+34 965 78 01 13",
    "sg:postcode":"03700",
    "sg:province":"Alicante",
    "wof:name":"Agullo Fornes Josefa",
    "wof:placetype":"venue"
},
  "geometry": {"coordinates":[0.1067416966,38.8399963379],"type":"Point"}
}