{
  "type": "Feature",
  "properties": {
    "iso:country":"ES",
    "sg:address":"Avda Reyes Catolicos, 114",
    "sg:city":"Dos Hermanas",
    "sg:orig_category":"Librer\u00cdas",
    "sg:phone":"+34 954 72 95 43",
    "sg:postcode":"41700",
    "sg:province":"Sevilla",
    "wof:name":"Anmanova S. L.",
    "wof:placetype":"venue"
},
  "geometry": {"coordinates":[-5.9278388023,37.2759971619],"type":"Point"}
}