{
  "type": "Feature",
  "properties": {
    "iso:country":"ES",
    "sg:address":"Carrer de Marina, 229",
    "sg:city":"Barcelona",
    "sg:orig_category":"Audiovisuales: Material Y Accesorios (al Por Menor)",
    "sg:phone":"+34 932 45 91 00",
    "sg:postcode":"08013",
    "sg:province":"Barcelona",
    "sg:website":"www.ibercin.com",
    "wof:name":"Ibercin S.l.",
    "wof:placetype":"venue"
},
  "geometry": {"coordinates":[2.177218914,41.4021759033],"type":"Point"}
}