{
  "type": "Feature",
  "properties": {
    "iso:country":"ES",
    "sg:address":"Cadiz, Km. 0177,7",
    "sg:city":"San Pedro Alcantara",
    "sg:orig_category":"Distribuci\u00d3n De Petr\u00d3leo Y Derivados",
    "sg:phone":"+34 952 78 47 62",
    "sg:postcode":"29670",
    "sg:province":"M\u00e1laga",
    "sg:website":"www.cepsa.es",
    "wof:name":"Cedipsa Compa\u00d1ia Espa\u00d1ola Distribuidora De Petroleos S.a.",
    "wof:placetype":"venue"
},
  "geometry": {"coordinates":[-4.9902391434,36.4866333008],"type":"Point"}
}