{
  "type": "Feature",
  "properties": {
    "iso:country":"ES",
    "sg:address":"Avda De Castelao, 22",
    "sg:city":"Ponteareas",
    "sg:orig_category":"Postigos, Persianas Y Celos\u00cdas",
    "sg:phone":"+34 986 65 09 34",
    "sg:postcode":"36860",
    "sg:province":"Pontevedra",
    "wof:name":"Martinez Cabaleiro Carlos",
    "wof:placetype":"venue"
},
  "geometry": {"coordinates":[-8.5092916489,42.174369812],"type":"Point"}
}