{
  "type": "Feature",
  "properties": {
    "addr:full":"Calle de Colmenares, 1 Valladolid Valladolid 47004",
    "addr:housenumber":"1",
    "addr:postcode":"47004",
    "addr:street":"Calle De Colmenares",
    "iso:country":"ES",
    "sg:address":"Calle de Colmenares, 1",
    "sg:city":"Valladolid",
    "sg:orig_category":"Inversiones",
    "sg:phone":"+34 983 21 26 14",
    "sg:postcode":"47004",
    "sg:province":"Valladolid",
    "wof:name":"Analistas De Inversiones De Castilla Y Leon S.l.",
    "wof:placetype":"venue"
},
  "geometry": {"coordinates":[-4.7262692451,41.6468429565],"type":"Point"}
}