{
  "type": "Feature",
  "properties": {
    "addr:full":"Carretera De Burgos, Km. 0155,6 Aranda Duero Burgos 09400",
    "addr:postcode":"09400",
    "addr:street":"Carretera De Burgos Km. 0155,6 Aranda Duero",
    "iso:country":"ES",
    "sg:address":"Carretera De Burgos, Km. 0155,6",
    "sg:city":"Aranda Duero",
    "sg:orig_category":"Venta, Alquiler, Mantenimiento De Calderas",
    "sg:phone":"+34 947 50 45 08",
    "sg:postcode":"09400",
    "sg:province":"Burgos",
    "wof:name":"Velez Construcciones Metalicas S.l.",
    "wof:placetype":"venue"
},
  "geometry": {"coordinates":[-3.6889948845,41.6699256897],"type":"Point"}
}