{
  "type": "Feature",
  "properties": {
    "iso:country":"ES",
    "sg:address":"C/ Oscar Espla, 37",
    "sg:city":"Elche",
    "sg:orig_category":"Molduras, Junquillos, Listones Y Molduras Perforadas",
    "sg:phone":"+34 965 44 06 57",
    "sg:postcode":"03201",
    "sg:province":"Alicante",
    "wof:name":"Sanchez Gonzalez Piedad",
    "wof:placetype":"venue"
},
  "geometry": {"coordinates":[-0.7043600082,38.2687683105],"type":"Point"}
}