{
  "type": "Feature",
  "properties": {
    "iso:country":"ES",
    "sg:address":"Calle de Mayor, 12",
    "sg:city":"Belones",
    "sg:orig_category":"Electrodom\u00c9sticos (al Por Menor)",
    "sg:phone":"+34 968 56 90 24",
    "sg:postcode":"30385",
    "sg:province":"Murcia",
    "wof:name":"Muebles Y Electrodomesticos Belhogar S.l.",
    "wof:placetype":"venue"
},
  "geometry": {"coordinates":[-0.7769690156,37.6227226257],"type":"Point"}
}