{
  "type": "Feature",
  "properties": {
    "iso:country":"ES",
    "sg:address":"Calle de Berlioz, 9",
    "sg:city":"Palmas De Gran Canaria",
    "sg:orig_category":"Agencias Y Agentes Comerciales, Representantes",
    "sg:phone":"+34 928 33 24 84",
    "sg:postcode":"35016",
    "sg:province":"Las Palmas",
    "wof:name":"Guerrero Ramos Marcos Antonio",
    "wof:placetype":"venue"
},
  "geometry": {"coordinates":[-15.4209918976,28.074054718],"type":"Point"}
}