{
  "type": "Feature",
  "properties": {
    "addr:full":"Carrer de Agudes, 31 Sabadell Barcelona 08207",
    "addr:housenumber":"31",
    "addr:postcode":"08207",
    "addr:street":"Carrer De Agudes",
    "iso:country":"ES",
    "sg:address":"Carrer de Agudes, 31",
    "sg:city":"Sabadell",
    "sg:orig_category":"Electrodom\u00c9sticos (al Por Menor)",
    "sg:phone":"+34 937 23 97 22",
    "sg:postcode":"08207",
    "sg:province":"Barcelona",
    "wof:name":"Brico-dom Del Valles S.l.",
    "wof:placetype":"venue"
},
  "geometry": {"coordinates":[2.0860490799,41.5676727295],"type":"Point"}
}