{
  "type": "Feature",
  "properties": {
    "addr:full":"Polig. Pocomaco, S/n A Coru\u00f1a La Coru\u00f1a 15190",
    "addr:housenumber":"s / n",
    "addr:postcode":"15190",
    "addr:street":"Polig. Pocomaco;A Corun\u0303A La Corun\u0303A",
    "iso:country":"ES",
    "sg:address":"Polig. Pocomaco, S/n",
    "sg:city":"A Coru\u00f1a",
    "sg:orig_category":"Tubos Met\u00c1licos",
    "sg:phone":"+34 981 29 58 55",
    "sg:postcode":"15190",
    "sg:province":"La Coru\u00f1a",
    "sg:website":"www.almesa.com",
    "wof:name":"Almacenes Metalurgicos S.a.",
    "wof:placetype":"venue"
},
  "geometry": {"coordinates":[-8.4335021973,43.3301010132],"type":"Point"}
}