{
  "type": "Feature",
  "properties": {
    "addr:full":"C/ Sant Maure, 8 Alcoi Alicante 03801",
    "addr:housenumber":"8",
    "addr:postcode":"03801",
    "addr:street":"C / Sant Maure",
    "iso:country":"ES",
    "sg:address":"C/ Sant Maure, 8",
    "sg:city":"Alcoi",
    "sg:orig_category":"Compraventa De Antig\u00dcedades",
    "sg:phone":"+34 965 54 72 75",
    "sg:postcode":"03801",
    "sg:province":"Alicante",
    "wof:name":"Botella Martinez Ernesto Lidiano",
    "wof:placetype":"venue"
},
  "geometry": {"coordinates":[-0.4734570086,38.6972007751],"type":"Point"}
}