{
  "type": "Feature",
  "properties": {
    "addr:full":"Calle de Arabial, 98 Granada Granada 18003",
    "addr:housenumber":"98",
    "addr:postcode":"18003",
    "addr:street":"Calle De Arabial",
    "iso:country":"ES",
    "sg:address":"Calle de Arabial, 98",
    "sg:city":"Granada",
    "sg:orig_category":"Ense\u00d1anza: Peluquer\u00cda Est\u00c9tica",
    "sg:phone":"+34 958 28 86 14",
    "sg:postcode":"18003",
    "sg:province":"Granada",
    "wof:name":"C & C Casanova S.a.",
    "wof:placetype":"venue"
},
  "geometry": {"coordinates":[-3.6123509407,37.1782646179],"type":"Point"}
}