{
  "type": "Feature",
  "properties": {
    "addr:full":"Calle de Amargura, 7 Zamora Zamora 49013",
    "addr:housenumber":"7",
    "addr:postcode":"49013",
    "addr:street":"Calle De Amargura",
    "iso:country":"ES",
    "sg:address":"Calle de Amargura, 7",
    "sg:city":"Zamora",
    "sg:orig_category":"Agencias De Viajes",
    "sg:phone":"+34 980 51 18 00",
    "sg:postcode":"49013",
    "sg:province":"Zamora",
    "sg:website":"www.marsans.es",
    "wof:name":"Viajes Marsans S.a.",
    "wof:placetype":"venue"
},
  "geometry": {"coordinates":[-5.7408328056,41.5091934204],"type":"Point"}
}