{
  "type": "Feature",
  "properties": {
    "iso:country":"ES",
    "sg:address":"Pl. Pte Reina, 18",
    "sg:city":"Iru\u00f1a",
    "sg:orig_category":"Pescader\u00cdas (al Por Menor)",
    "sg:phone":"+34 948 12 43 84",
    "sg:postcode":"31015",
    "sg:province":"Navarra",
    "wof:name":"Robledo Nieto Juana Mari",
    "wof:placetype":"venue"
},
  "geometry": {"coordinates":[-1.6339590549,42.8247261047],"type":"Point"}
}