{
  "type": "Feature",
  "properties": {
    "iso:country":"ES",
    "sg:address":"Calle de Solera, S/n",
    "sg:city":"Mojonera",
    "sg:orig_category":"Reposter\u00cdas",
    "sg:phone":"+34 950 33 00 01",
    "sg:postcode":"04745",
    "sg:province":"Almer\u00eda",
    "wof:name":"Vega Sanchez Andres",
    "wof:placetype":"venue"
},
  "geometry": {"coordinates":[-2.6807188988,36.754119873],"type":"Point"}
}