{
  "type": "Feature",
  "properties": {
    "iso:country":"ES",
    "sg:address":"Rua Aduana, 25",
    "sg:city":"Ponteceso",
    "sg:orig_category":"Comercio De Piezas De Recambio Y De Accesorios De Veh\u00cdculos, Veh\u00cdculos Industriales",
    "sg:phone":"+34 981 71 42 78",
    "sg:postcode":"15110",
    "sg:province":"La Coru\u00f1a",
    "wof:name":"Dominguez Vareal Joaquin",
    "wof:placetype":"venue"
},
  "geometry": {"coordinates":[-8.8990907669,43.2446746826],"type":"Point"}
}