{
  "type": "Feature",
  "properties": {
    "iso:country":"ES",
    "sg:address":"Calle de Gordoniz, 6",
    "sg:city":"Bilbao",
    "sg:orig_category":"M\u00c9dicos: Ginecolog\u00cda Y Obstetricia",
    "sg:phone":"+34 944 21 28 66",
    "sg:postcode":"48010",
    "sg:province":"Vizcaya",
    "wof:name":"Apodaca Santisteban Luis Antonio",
    "wof:placetype":"venue"
},
  "geometry": {"coordinates":[-2.9384374619,43.2598266602],"type":"Point"}
}