{
  "type": "Feature",
  "properties": {
    "iso:country":"ES",
    "sg:address":"Carrer de Mairo, 15",
    "sg:city":"Roses",
    "sg:orig_category":"Confecci\u00d3n De Alpargatas",
    "sg:phone":"+34 972 15 08 55",
    "sg:postcode":"17480",
    "sg:province":"Girona",
    "wof:name":"Pujol Oliveras Maria Teresa",
    "wof:placetype":"venue"
},
  "geometry": {"coordinates":[3.1767160892,42.2619628906],"type":"Point"}
}