{
  "type": "Feature",
  "properties": {
    "addr:full":"Rond Calatrava, 20 Ciudad Real Ciudad Real 13003",
    "addr:housenumber":"20",
    "addr:postcode":"13003",
    "addr:street":"Rond Calatrava",
    "iso:country":"ES",
    "sg:address":"Rond Calatrava, 20",
    "sg:city":"Ciudad Real",
    "sg:orig_category":"Venta, Instalaci\u00d3n, Reparaci\u00d3n De Antenas Para Televisi\u00d3n",
    "sg:phone":"+34 926 27 40 01",
    "sg:postcode":"13003",
    "sg:province":"Ciudad Real",
    "wof:name":"Electronica Insatel S.l.",
    "wof:placetype":"venue"
},
  "geometry": {"coordinates":[-3.9243309498,38.9899139404],"type":"Point"}
}