{
  "type": "Feature",
  "properties": {
    "addr:full":"Carrer de Santander, 100 Barcelona Barcelona 08030",
    "addr:housenumber":"100",
    "addr:postcode":"08030",
    "addr:street":"Carrer De Santander",
    "iso:country":"ES",
    "sg:address":"Carrer de Santander, 100",
    "sg:city":"Barcelona",
    "sg:orig_category":"Refiner\u00cdas De Petr\u00d3leo",
    "sg:phone":"+34 932 78 23 80",
    "sg:postcode":"08030",
    "sg:province":"Barcelona",
    "wof:name":"Lleo Canadell Maria Gloria",
    "wof:placetype":"venue"
},
  "geometry": {"coordinates":[2.2066659927,41.4328651428],"type":"Point"}
}