{
  "type": "Feature",
  "properties": {
    "addr:full":"Rua Rosalia De Castro, 4 Gondomar Pontevedra 36380",
    "addr:housenumber":"4",
    "addr:postcode":"36380",
    "addr:street":"Rua Rosalia De Castro",
    "iso:country":"ES",
    "sg:address":"Rua Rosalia De Castro, 4",
    "sg:city":"Gondomar",
    "sg:orig_category":"Art\u00cdculos De Regalo (al Por Menor)",
    "sg:phone":"+34 986 36 01 81",
    "sg:postcode":"36380",
    "sg:province":"Pontevedra",
    "wof:name":"Gonzalez Costas Jesusa",
    "wof:placetype":"venue"
},
  "geometry": {"coordinates":[-8.7634458542,42.1106300354],"type":"Point"}
}