{
  "type": "Feature",
  "properties": {
    "addr:full":"Calle de Duquesa Villahermosa, 6 Zaragoza Zaragoza 50010",
    "addr:housenumber":"6",
    "addr:postcode":"50010",
    "addr:street":"Calle De Duquesa Villahermosa",
    "iso:country":"ES",
    "sg:address":"Calle de Duquesa Villahermosa, 6",
    "sg:city":"Zaragoza",
    "sg:orig_category":"Asesor\u00cda De Formaci\u00d3n Y Gesti\u00d3n De Personal",
    "sg:phone":"+34 976 33 61 46",
    "sg:postcode":"50010",
    "sg:province":"Zaragoza",
    "wof:name":"M Y D Metodos Y Desarrollos S.l.",
    "wof:placetype":"venue"
},
  "geometry": {"coordinates":[-0.8998038173,41.6491355896],"type":"Point"}
}