{
  "type": "Feature",
  "properties": {
    "iso:country":"ES",
    "sg:address":"Avda Francisco La Roche, 31",
    "sg:city":"Santa Cruz De Tenerife",
    "sg:orig_category":"\u00c1rboles Frutales",
    "sg:phone":"+34 922 15 11 37",
    "sg:postcode":"38001",
    "sg:province":"Santa Cruz De Tenerife",
    "wof:name":"Sat Agriten",
    "wof:placetype":"venue"
},
  "geometry": {"coordinates":[-16.2449493408,28.4773406982],"type":"Point"}
}