{
  "type": "Feature",
  "properties": {
    "addr:full":"Avda Alt Rei En Jaume I (l'), 27 Altea Alicante 03590",
    "addr:housenumber":"27",
    "addr:postcode":"03590",
    "addr:street":"Avda Alt Rei En Jaume I L '",
    "iso:country":"ES",
    "sg:address":"Avda Alt Rei En Jaume I (l'), 27",
    "sg:city":"Altea",
    "sg:orig_category":"Cl\u00cdnicas Dentales",
    "sg:phone":"+34 966 88 12 24",
    "sg:postcode":"03590",
    "sg:province":"Alicante",
    "wof:name":"Lloret Lloret Olga",
    "wof:placetype":"venue"
},
  "geometry": {"coordinates":[-0.0464590006,38.6028518677],"type":"Point"}
}