{
  "type": "Feature",
  "properties": {
    "addr:full":"Calle de Palacio, 10 Mu\u00d1overos Segovia 40183",
    "addr:housenumber":"10",
    "addr:postcode":"40183",
    "addr:street":"Calle De Palacio;Segovia",
    "iso:country":"ES",
    "sg:address":"Calle de Palacio, 10",
    "sg:city":"Mu\u00d1overos",
    "sg:orig_category":"Barbacoas Y Accesorios",
    "sg:phone":"+34 921 50 11 71",
    "sg:postcode":"40183",
    "sg:province":"Segovia",
    "wof:name":"Ajumeva S.l.",
    "wof:placetype":"venue"
},
  "geometry": {"coordinates":[-3.9506742954,41.1720237732],"type":"Point"}
}