{
  "type": "Feature",
  "properties": {
    "addr:full":"Ctra. Puerto Naos, 25 Los Llanos Aridane Santa Cruz De Tenerife 38760",
    "addr:housenumber":"25",
    "addr:postcode":"38760",
    "addr:street":"Ctra. Puerto Naos",
    "iso:country":"ES",
    "sg:address":"Ctra. Puerto Naos, 25",
    "sg:city":"Los Llanos Aridane",
    "sg:orig_category":"Venta, Montaje De Neum\u00c1ticos",
    "sg:phone":"+34 922 46 31 50",
    "sg:postcode":"38760",
    "sg:province":"Santa Cruz De Tenerife",
    "wof:name":"Gonzalez Rodriguez Lorena Amalia",
    "wof:placetype":"venue"
},
  "geometry": {"coordinates":[-17.9129085541,28.6542835236],"type":"Point"}
}