{
  "type": "Feature",
  "properties": {
    "iso:country":"ES",
    "sg:address":"Logistica, 8",
    "sg:city":"Parets Del Valles",
    "sg:orig_category":"Comercio De Piezas De Recambio Y De Accesorios De Veh\u00cdculos, Veh\u00cdculos Industriales",
    "sg:phone":"+34 935 73 52 00",
    "sg:postcode":"08150",
    "sg:province":"Barcelona",
    "wof:name":"Recambios Y Accesorios Gaudi S.l.",
    "wof:placetype":"venue"
},
  "geometry": {"coordinates":[2.2343330383,41.5637016296],"type":"Point"}
}