{
  "type": "Feature",
  "properties": {
    "iso:country":"ES",
    "sg:address":"Calle de Barrenkale, 31",
    "sg:city":"Plentzia",
    "sg:orig_category":"Venta, Colocaci\u00d3n, Tratamiento De Enlosados, Soler\u00cdas",
    "sg:phone":"+34 946 77 11 42",
    "sg:postcode":"48620",
    "sg:province":"Vizcaya",
    "wof:name":"Frances Amezaga Luciano",
    "wof:placetype":"venue"
},
  "geometry": {"coordinates":[-2.9485445023,43.4042320251],"type":"Point"}
}