{
  "type": "Feature",
  "properties": {
    "addr:full":"Avda 28 De Febrero, 26 Ca\u00d1ico Almer\u00eda 04800",
    "addr:housenumber":"26",
    "addr:postcode":"04800",
    "addr:street":"Avda 28 De Febrero;Almeri\u0301A",
    "iso:country":"ES",
    "sg:address":"Avda 28 De Febrero, 26",
    "sg:city":"Ca\u00d1ico",
    "sg:orig_category":"Asesor\u00cda Sobre Comunicaci\u00d3n De Empresas",
    "sg:phone":"+34 950 63 32 80",
    "sg:postcode":"04800",
    "sg:province":"Almer\u00eda",
    "wof:name":"Proyectos Asesoria Y Servicios S.a.",
    "wof:placetype":"venue"
},
  "geometry": {"coordinates":[-2.1398289204,37.3874435425],"type":"Point"}
}