{
  "type": "Feature",
  "properties": {
    "addr:full":"Calle de San Bernardo, 7 Onda Castell\u00f3n 12200",
    "addr:housenumber":"7",
    "addr:postcode":"12200",
    "addr:street":"Calle De San Bernardo;Castello\u0301N",
    "iso:country":"ES",
    "sg:address":"Calle de San Bernardo, 7",
    "sg:city":"Onda",
    "sg:orig_category":"Negocio De Materiales De Construcci\u00d3n",
    "sg:phone":"+34 964 77 13 01",
    "sg:postcode":"12200",
    "sg:province":"Castell\u00f3n",
    "wof:name":"Banaco Traiding S.l.",
    "wof:placetype":"venue"
},
  "geometry": {"coordinates":[-0.2633509934,39.9636497498],"type":"Point"}
}