{
  "type": "Feature",
  "properties": {
    "addr:full":"Calle de Vera Del Barranco, 4 G\u00fcimar Santa Cruz De Tenerife 38500",
    "addr:housenumber":"4",
    "addr:postcode":"38500",
    "addr:street":"Calle De Vera Del Barranco",
    "iso:country":"ES",
    "sg:address":"Calle de Vera Del Barranco, 4",
    "sg:city":"G\u00fcimar",
    "sg:orig_category":"Lavado, Limpieza De Veh\u00cdculos",
    "sg:phone":"+34 922 51 25 56",
    "sg:postcode":"38500",
    "sg:province":"Santa Cruz De Tenerife",
    "wof:name":"Diaz Bethencourt Jose Manuel",
    "wof:placetype":"venue"
},
  "geometry": {"coordinates":[-16.413608551,28.3137702942],"type":"Point"}
}