{
  "type": "Feature",
  "properties": {
    "addr:full":"Avda Paz, 15 Almendralejo Badajoz 06200",
    "addr:housenumber":"15",
    "addr:postcode":"06200",
    "addr:street":"Avda Paz",
    "iso:country":"ES",
    "sg:address":"Avda Paz, 15",
    "sg:city":"Almendralejo",
    "sg:orig_category":"Cajas Para Embalar",
    "sg:phone":"+34 924 66 60 09",
    "sg:postcode":"06200",
    "sg:province":"Badajoz",
    "wof:name":"Caja Rural De Almendralejo",
    "wof:placetype":"venue"
},
  "geometry": {"coordinates":[-6.4127140045,38.6833648682],"type":"Point"}
}