{
  "type": "Feature",
  "properties": {
    "iso:country":"ES",
    "sg:address":"Plaz Corredera, 16",
    "sg:city":"Hervas",
    "sg:orig_category":"Fotograf\u00cda Art\u00cdstica Y Retratos",
    "sg:phone":"+34 927 48 12 40",
    "sg:postcode":"10700",
    "sg:province":"C\u00e1ceres",
    "wof:name":"Martin Manuel Ana Maria",
    "wof:placetype":"venue"
},
  "geometry": {"coordinates":[-5.8459339142,40.2736587524],"type":"Point"}
}