{
  "type": "Feature",
  "properties": {
    "iso:country":"ES",
    "sg:address":"Pase Angela Rosa De Silva, 40",
    "sg:city":"Horcajo Santiago",
    "sg:orig_category":"Ense\u00d1anza Secundaria: Colegios Y Escuelas Privadas",
    "sg:phone":"+34 969 12 82 38",
    "sg:postcode":"16410",
    "sg:province":"Cuenca",
    "wof:name":"Ies Orden De Santiago",
    "wof:placetype":"venue"
},
  "geometry": {"coordinates":[-2.1340053082,40.0718345642],"type":"Point"}
}