{
  "type": "Feature",
  "properties": {
    "addr:full":"Ctra Jaen (p I Mirabueno), S/n Torredonjimeno Ja\u00e9n 23650",
    "addr:housenumber":"s / n",
    "addr:postcode":"23650",
    "addr:street":"Ctra Jaen P;Mirabueno",
    "iso:country":"ES",
    "sg:address":"Ctra Jaen (p I Mirabueno), S/n",
    "sg:city":"Torredonjimeno",
    "sg:orig_category":"Droguer\u00cdas (al Por Mayor)",
    "sg:phone":"+34 953 57 12 81",
    "sg:postcode":"23650",
    "sg:province":"Ja\u00e9n",
    "wof:name":"Mu\u00f1oz Y Molina S.a.",
    "wof:placetype":"venue"
},
  "geometry": {"coordinates":[-3.9459791183,37.7634887695],"type":"Point"}
}