{
  "type": "Feature",
  "properties": {
    "iso:country":"ES",
    "sg:address":"Plaz Gracia (de), S/n",
    "sg:city":"Albu\u00f1uelas",
    "sg:orig_category":"Iglesia Cat\u00d3lica",
    "sg:phone":"+34 958 77 60 77",
    "sg:postcode":"18659",
    "sg:province":"Granada",
    "wof:name":"Parroquia De Nuestro Salvador",
    "wof:placetype":"venue"
},
  "geometry": {"coordinates":[-3.6302039623,36.9290237427],"type":"Point"}
}