{
  "type": "Feature",
  "properties": {
    "addr:full":"Calle de Doctor Manuel Candela, 37 Valencia Valencia 46021",
    "addr:housenumber":"37",
    "addr:postcode":"46021",
    "addr:street":"Calle De Doctor Manuel Candela",
    "iso:country":"ES",
    "sg:address":"Calle de Doctor Manuel Candela, 37",
    "sg:city":"Valencia",
    "sg:orig_category":"Bisuter\u00cda, Joyer\u00cda, Relojer\u00cda (al Por Menor)",
    "sg:phone":"+34 963 62 57 08",
    "sg:postcode":"46021",
    "sg:province":"Valencia",
    "wof:name":"Domenech Frances Maria Rosario",
    "wof:placetype":"venue"
},
  "geometry": {"coordinates":[-0.3499003947,39.4691543579],"type":"Point"}
}