{
  "type": "Feature",
  "properties": {
    "addr:full":"Avda Diputacion, 8 Oyon-oion \u00c1lava 01320",
    "addr:housenumber":"8",
    "addr:postcode":"01320",
    "addr:street":"Avda Diputacion;A\u0301Lava",
    "iso:country":"ES",
    "sg:address":"Avda Diputacion, 8",
    "sg:city":"Oyon-oion",
    "sg:orig_category":"Loter\u00cda Y T\u00d3mbola",
    "sg:phone":"+34 945 60 13 52",
    "sg:postcode":"01320",
    "sg:province":"\u00c1lava",
    "wof:name":"Viana Rodriguez Luis",
    "wof:placetype":"venue"
},
  "geometry": {"coordinates":[-2.4391961098,42.5074501038],"type":"Point"}
}