{
  "type": "Feature",
  "properties": {
    "addr:full":"Calle de Pintor Velazquez, 12 Granada Granada 18002",
    "addr:housenumber":"12",
    "addr:postcode":"18002",
    "addr:street":"Calle De Pintor Velazquez",
    "iso:country":"ES",
    "sg:address":"Calle de Pintor Velazquez, 12",
    "sg:city":"Granada",
    "sg:orig_category":"Abogados",
    "sg:phone":"+34 958 27 24 93",
    "sg:postcode":"18002",
    "sg:province":"Granada",
    "wof:name":"Vives Montero Jose",
    "wof:placetype":"venue"
},
  "geometry": {"coordinates":[-3.6085431576,37.1771354675],"type":"Point"}
}