{
  "type": "Feature",
  "properties": {
    "iso:country":"ES",
    "sg:address":"Sancido, S/n",
    "sg:city":"Sancido",
    "sg:orig_category":"Producci\u00d3n, Venta De Productos De Agricultura Biol\u00d3gica",
    "sg:phone":"+34 982 36 25 45",
    "sg:postcode":"27649",
    "sg:province":"Lugo",
    "wof:name":"Cooperativa Carballeira",
    "wof:placetype":"venue"
},
  "geometry": {"coordinates":[-7.1932229996,42.8263931274],"type":"Point"}
}