{
  "type": "Feature",
  "properties": {
    "addr:full":"Calle de Real, 80 Castronu\u00f1o Valladolid 47520",
    "addr:housenumber":"80",
    "addr:postcode":"47520",
    "addr:street":"Calle De Real",
    "iso:country":"ES",
    "sg:address":"Calle de Real, 80",
    "sg:city":"Castronu\u00f1o",
    "sg:orig_category":"Oficinas De Turismo, Asociaciones De Iniciativa",
    "sg:phone":"+34 983 86 60 95",
    "sg:postcode":"47520",
    "sg:province":"Valladolid",
    "wof:name":"Ayuntamiento De Castronu\u00d1o",
    "wof:placetype":"venue"
},
  "geometry": {"coordinates":[-5.2639560699,41.3894996643],"type":"Point"}
}