{
  "type": "Feature",
  "properties": {
    "addr:full":"Plaz Santa Ana, 14 Constantina Sevilla 41450",
    "addr:housenumber":"14",
    "addr:postcode":"41450",
    "addr:street":"Santa Ana",
    "iso:country":"ES",
    "sg:address":"Plaz Santa Ana, 14",
    "sg:city":"Constantina",
    "sg:classifiers":[
        {
            "category":"Taxi",
            "type":"Transportation"
        }
    ],
    "sg:phone":"+34 955 88 07 07",
    "sg:postcode":"41450",
    "sg:province":"Sevilla",
    "wof:name":"Garcia Melendez Sebastian",
    "wof:placetype":"venue"
},
  "geometry": {"coordinates":[-5.6197562218,37.8712120056],"type":"Point"}
}