{
  "type": "Feature",
  "properties": {
    "addr:full":"Calle de Doctor Fleming, 2 Lagartera Toledo 45567",
    "addr:housenumber":"2",
    "addr:postcode":"45567",
    "addr:street":"Calle De Doctor Fleming",
    "iso:country":"ES",
    "sg:address":"Calle de Doctor Fleming, 2",
    "sg:city":"Lagartera",
    "sg:orig_category":"Bordado, Marcado A Medida",
    "sg:phone":"+34 925 43 08 81",
    "sg:postcode":"45567",
    "sg:province":"Toledo",
    "wof:name":"Herrero Lozano Francisco",
    "wof:placetype":"venue"
},
  "geometry": {"coordinates":[-5.2008714676,39.9069519043],"type":"Point"}
}