{
  "type": "Feature",
  "properties": {
    "iso:country":"ES",
    "sg:address":"Pase Longares, 35",
    "sg:city":"Zaragoza",
    "sg:orig_category":"Maquinaria Neum\u00c1tica",
    "sg:phone":"+34 976 47 59 68",
    "sg:postcode":"50014",
    "sg:province":"Zaragoza",
    "wof:name":"Lasaosa Catalan Ana Maria",
    "wof:placetype":"venue"
},
  "geometry": {"coordinates":[-0.8637300134,41.6574401855],"type":"Point"}
}