{
  "type": "Feature",
  "properties": {
    "addr:full":"Avda Aragon, 36 Getafe Madrid 28903",
    "addr:housenumber":"36",
    "addr:postcode":"28903",
    "addr:street":"Avda Aragon",
    "iso:country":"ES",
    "sg:address":"Avda Aragon, 36",
    "sg:city":"Getafe",
    "sg:orig_category":"Molduras, Junquillos, Listones Y Molduras Perforadas",
    "sg:phone":"+34 916 95 79 33",
    "sg:postcode":"28903",
    "sg:province":"Madrid",
    "wof:name":"Araque Cruzado Paudelina",
    "wof:placetype":"venue"
},
  "geometry": {"coordinates":[-3.7146008015,40.3129692078],"type":"Point"}
}