{
  "type": "Feature",
  "properties": {
    "addr:full":"Pase Muro (del), 22 Ejea De Los Caballeros Zaragoza 50600",
    "addr:postcode":"50600",
    "addr:street":"Del",
    "iso:country":"ES",
    "sg:address":"Pase Muro (del), 22",
    "sg:city":"Ejea De Los Caballeros",
    "sg:classifiers":[
        {
            "category":"Professional",
            "subcategory":"Management & Consulting",
            "type":"Services"
        }
    ],
    "sg:phone":"+34 976 66 77 10",
    "sg:postcode":"50600",
    "sg:province":"Zaragoza",
    "sg:tags":[
        "asesor\u00cda",
        "en",
        "marketing"
    ],
    "sg:website":"www.asis3021.cajarural.com",
    "wof:name":"Asociacion De Comercio Servicios E Industria",
    "wof:placetype":"venue"
},
  "geometry": {"coordinates":[-1.1365014315,42.1257247925],"type":"Point"}
}