{
  "type": "Feature",
  "properties": {
    "iso:country":"ES",
    "sg:address":"Ctra Valverde, S/n",
    "sg:city":"Badajoz",
    "sg:orig_category":"Deportes Y Ocio: Art\u00cdculos Y Ropas (al Por Menor Y Accesorios)",
    "sg:phone":"+34 924 26 02 07",
    "sg:postcode":"06010",
    "sg:province":"Badajoz",
    "sg:website":"www.decimas.es",
    "wof:name":"Tinmar Sport S.l.",
    "wof:placetype":"venue"
},
  "geometry": {"coordinates":[-6.9720201492,38.8625411987],"type":"Point"}
}