{
  "type": "Feature",
  "properties": {
    "addr:full":"Calle de O, 6 Mutiloabeiti Navarra 31192",
    "addr:housenumber":"6",
    "addr:postcode":"31192",
    "addr:street":"Calle De O",
    "iso:country":"ES",
    "sg:address":"Calle de O, 6",
    "sg:city":"Mutiloabeiti",
    "sg:orig_category":"Productos Fitosanitarios (negocio, Aplicaci\u00d3n)",
    "sg:phone":"+34 948 23 87 13",
    "sg:postcode":"31192",
    "sg:province":"Navarra",
    "wof:name":"Multiagro S. L.",
    "wof:placetype":"venue"
},
  "geometry": {"coordinates":[-1.6249040365,42.7842636108],"type":"Point"}
}