{
  "type": "Feature",
  "properties": {
    "iso:country":"ES",
    "sg:address":"Avda Cervantes (de), 11",
    "sg:city":"Guardamar Segura",
    "sg:orig_category":"Inmobiliaria (agencias)",
    "sg:phone":"+34 966 72 52 92",
    "sg:postcode":"03140",
    "sg:province":"Alicante",
    "sg:website":"www.mediterraneanalicante.com",
    "wof:name":"Mediterranea Alicante S.l.",
    "wof:placetype":"venue"
},
  "geometry": {"coordinates":[-0.6540290117,38.086681366],"type":"Point"}
}