{
  "type": "Feature",
  "properties": {
    "iso:country":"ES",
    "sg:address":"Avda Doctor Federico Rubio Y Gali, 40",
    "sg:city":"Madrid",
    "sg:orig_category":"Droguer\u00cdas (al Por Menor)",
    "sg:phone":"+34 913 11 09 53",
    "sg:postcode":"28039",
    "sg:province":"Madrid",
    "wof:name":"Aromas De Jabon C.d.",
    "wof:placetype":"venue"
},
  "geometry": {"coordinates":[-3.7093863487,40.451423645],"type":"Point"}
}