{
  "type": "Feature",
  "properties": {
    "addr:full":"Calle de General Vara De Rey, 44 Logro\u00f1o La Rioja 26002",
    "addr:housenumber":"44",
    "addr:postcode":"26002",
    "addr:street":"Calle De General Vara De Rey;Rioja",
    "iso:country":"ES",
    "sg:address":"Calle de General Vara De Rey, 44",
    "sg:city":"Logro\u00f1o",
    "sg:orig_category":"Oficinas Y Gesti\u00d3n De Inmuebles",
    "sg:phone":"+34 941 26 06 70",
    "sg:postcode":"26002",
    "sg:province":"La Rioja",
    "wof:name":"Servicios Inmobiliarios Herreros S.l.",
    "wof:placetype":"venue"
},
  "geometry": {"coordinates":[-2.4466691017,42.4585189819],"type":"Point"}
}