{
  "type": "Feature",
  "properties": {
    "addr:full":"Avda Libertad, 2 San Miguel Murcia 30009",
    "addr:housenumber":"2",
    "addr:postcode":"30009",
    "addr:street":"Avda Libertad",
    "iso:country":"ES",
    "sg:address":"Avda Libertad, 2",
    "sg:city":"San Miguel",
    "sg:orig_category":"Molinos",
    "sg:phone":"+34 968 24 95 73",
    "sg:postcode":"30009",
    "sg:province":"Murcia",
    "wof:name":"Alcantud Nicolas Jesus",
    "wof:placetype":"venue"
},
  "geometry": {"coordinates":[-1.1298867464,37.9834747314],"type":"Point"}
}