{
  "type": "Feature",
  "properties": {
    "iso:country":"ES",
    "sg:address":"Larga, 12",
    "sg:city":"Villarquemado",
    "sg:orig_category":"Cajas De Ahorro",
    "sg:phone":"+34 978 86 70 02",
    "sg:postcode":"44380",
    "sg:province":"Teruel",
    "wof:name":"Caja De Ahorros Y Monte De Piedad De Zaragoza Aragon Y Rioja",
    "wof:placetype":"venue"
},
  "geometry": {"coordinates":[-1.264893055,40.5190315247],"type":"Point"}
}