{
  "type": "Feature",
  "properties": {
    "iso:country":"ES",
    "sg:address":"Calle de Huertas (las), 1",
    "sg:city":"Santo\u00f1a",
    "sg:orig_category":"Cl\u00cdnicas Dentales",
    "sg:phone":"+34 942 66 01 51",
    "sg:postcode":"39740",
    "sg:province":"Cantabria",
    "wof:name":"Zurita Martin Gerardo",
    "wof:placetype":"venue"
},
  "geometry": {"coordinates":[-3.4552540779,43.4432601929],"type":"Point"}
}