{
  "type": "Feature",
  "properties": {
    "addr:full":"Calle de Isidoro De Antillon, 7 Zaragoza Zaragoza 50015",
    "addr:housenumber":"7",
    "addr:postcode":"50015",
    "addr:street":"Calle De Isidoro De Antillon",
    "iso:country":"ES",
    "sg:address":"Calle de Isidoro De Antillon, 7",
    "sg:city":"Zaragoza",
    "sg:orig_category":"El Hogar: Amueblado, Acondicionamiento, Decoraci\u00d3n Y Mantenimiento",
    "sg:phone":"+34 976 57 22 67",
    "sg:postcode":"50015",
    "sg:province":"Zaragoza",
    "wof:name":"Dula Iberica S.a.",
    "wof:placetype":"venue"
},
  "geometry": {"coordinates":[-0.8629540205,41.6912841797],"type":"Point"}
}