{
  "type": "Feature",
  "properties": {
    "addr:full":"Calle de Natalio Rivas, 34 Adra Almer\u00eda 04770",
    "addr:housenumber":"34",
    "addr:postcode":"04770",
    "addr:street":"Calle De Natalio Rivas;Almeri\u0301A",
    "iso:country":"ES",
    "sg:address":"Calle de Natalio Rivas, 34",
    "sg:city":"Adra",
    "sg:orig_category":"M\u00c9dicos: Oftalmolog\u00cda",
    "sg:phone":"+34 950 40 18 59",
    "sg:postcode":"04770",
    "sg:province":"Almer\u00eda",
    "wof:name":"Lopez-la Fuente Y Lopez Rafael",
    "wof:placetype":"venue"
},
  "geometry": {"coordinates":[-3.0153689384,36.7487182617],"type":"Point"}
}