{
  "type": "Feature",
  "properties": {
    "addr:full":"Calle de Doctor Gomez Ulla, 14 Madrid Madrid 28028",
    "addr:housenumber":"14",
    "addr:postcode":"madrid;28028",
    "addr:street":"Calle De Doctor Gomez Ulla",
    "iso:country":"ES",
    "sg:address":"Calle de Doctor Gomez Ulla, 14",
    "sg:city":"Madrid",
    "sg:orig_category":"M\u00c9dicos: Medicina General",
    "sg:phone":"+34 913 55 02 25",
    "sg:postcode":"28028",
    "sg:province":"Madrid",
    "wof:name":"Agerasia S.l.",
    "wof:placetype":"venue"
},
  "geometry": {"coordinates":[-3.6680593491,40.4293746948],"type":"Point"}
}