{
  "type": "Feature",
  "properties": {
    "iso:country":"ES",
    "sg:address":"Av Rapita (de La), 74",
    "sg:city":"Amposta",
    "sg:orig_category":"Notarios",
    "sg:phone":"+34 977 70 41 99",
    "sg:postcode":"43870",
    "sg:province":"Tarragona",
    "wof:name":"Roca Barrufet Miguel",
    "wof:placetype":"venue"
},
  "geometry": {"coordinates":[0.5796909928,40.7086448669],"type":"Point"}
}