{
  "type": "Feature",
  "properties": {
    "addr:full":"Adelantado P Mendoza Lujan, 5 Guadix Granada 18500",
    "addr:postcode":"18500",
    "iso:country":"ES",
    "sg:address":"Adelantado P Mendoza Lujan, 5",
    "sg:city":"Guadix",
    "sg:orig_category":"Electrodom\u00c9sticos (al Por Menor)",
    "sg:phone":"+34 958 66 22 82",
    "sg:postcode":"18500",
    "sg:province":"Granada",
    "wof:name":"Aranda Raya Francisco",
    "wof:placetype":"venue"
},
  "geometry": {"coordinates":[-3.1362349987,37.3036003113],"type":"Point"}
}