{
  "type": "Feature",
  "properties": {
    "addr:full":"Calle de Torre Gorostitzaga, 2 Bilbao Vizcaya 48004",
    "addr:housenumber":"2",
    "addr:postcode":"48004",
    "addr:street":"Calle De Torre Gorostitzaga",
    "iso:country":"ES",
    "sg:address":"Calle de Torre Gorostitzaga, 2",
    "sg:city":"Bilbao",
    "sg:orig_category":"Asilos De Ancianos. Centros Privados",
    "sg:phone":"+34 944 11 08 58",
    "sg:postcode":"48004",
    "sg:province":"Vizcaya",
    "wof:name":"Torregorostizaga, S.l.",
    "wof:placetype":"venue"
},
  "geometry": {"coordinates":[-2.900121212,43.2565917969],"type":"Point"}
}