{
  "type": "Feature",
  "properties": {
    "addr:full":"Carr Llevant, (de), 14 Carlet Valencia 46240",
    "addr:housenumber":"14",
    "addr:postcode":"46240",
    "addr:street":"Carr Llevant De",
    "iso:country":"ES",
    "sg:address":"Carr Llevant, (de), 14",
    "sg:city":"Carlet",
    "sg:orig_category":"Autob\u00das (explotaci\u00d3n Y Servicios De)",
    "sg:phone":"+34 962 53 07 09",
    "sg:postcode":"46240",
    "sg:province":"Valencia",
    "wof:name":"Franjen Sociedad Limitada",
    "wof:placetype":"venue"
},
  "geometry": {"coordinates":[-0.4922100008,39.2325515747],"type":"Point"}
}