{
  "type": "Feature",
  "properties": {
    "addr:full":"Trva Union, 1 Valdepe\u00f1as Ciudad Real 13300",
    "addr:housenumber":"1",
    "addr:postcode":"13300",
    "addr:street":"Trva Union",
    "iso:country":"ES",
    "sg:address":"Trva Union, 1",
    "sg:city":"Valdepe\u00f1as",
    "sg:orig_category":"Aperitivos (fabricaci\u00d3n Y Al Por Mayor)",
    "sg:phone":"+34 926 31 17 28",
    "sg:postcode":"13300",
    "sg:province":"Ciudad Real",
    "wof:name":"Garcia Rojo Sanchez Lorenzo",
    "wof:placetype":"venue"
},
  "geometry": {"coordinates":[-3.3870530128,38.7656898499],"type":"Point"}
}