{
  "type": "Feature",
  "properties": {
    "addr:full":"Avda Bierzo (el), 2 Ponferrada Le\u00f3n 24400",
    "addr:housenumber":"2",
    "addr:postcode":"24400",
    "addr:street":"Avda Bierzo El",
    "iso:country":"ES",
    "sg:address":"Avda Bierzo (el), 2",
    "sg:city":"Ponferrada",
    "sg:orig_category":"M\u00c9dicos: Oftalmolog\u00cda",
    "sg:phone":"+34 987 40 28 67",
    "sg:postcode":"24400",
    "sg:province":"Le\u00f3n",
    "wof:name":"Alvarez Gonzalez Juan Eusebio",
    "wof:placetype":"venue"
},
  "geometry": {"coordinates":[-6.5834679604,42.5497322083],"type":"Point"}
}