{
  "type": "Feature",
  "properties": {
    "addr:full":"Calle de San Martin, 16 Alfaro La Rioja 26540",
    "addr:housenumber":"16",
    "addr:postcode":"26540",
    "addr:street":"Calle De San Martin;Rioja",
    "iso:country":"ES",
    "sg:address":"Calle de San Martin, 16",
    "sg:city":"Alfaro",
    "sg:orig_category":"Ferreter\u00cda (diversos)",
    "sg:phone":"+34 941 18 10 58",
    "sg:postcode":"26540",
    "sg:province":"La Rioja",
    "wof:name":"Conre S. L.",
    "wof:placetype":"venue"
},
  "geometry": {"coordinates":[-1.7424759865,42.1797409058],"type":"Point"}
}