{
  "type": "Feature",
  "properties": {
    "addr:full":"Pg Jaume Brutau, 24 S. Andreu Llavaneres Barcelona 08392",
    "addr:housenumber":"24",
    "addr:postcode":"08392",
    "addr:street":"Pg Jaume Brutau;S. Andreu Llavaneres Barcelona",
    "iso:country":"ES",
    "sg:address":"Pg Jaume Brutau, 24",
    "sg:city":"S. Andreu Llavaneres",
    "sg:orig_category":"Servicios De Higiene Y Peluquer\u00cda Para Perros Y Gatos",
    "sg:phone":"+34 937 92 90 17",
    "sg:postcode":"08392",
    "sg:province":"Barcelona",
    "wof:name":"Centro Canino Susana S.l.",
    "wof:placetype":"venue"
},
  "geometry": {"coordinates":[2.4826459885,41.5758285522],"type":"Point"}
}