{
  "type": "Feature",
  "properties": {
    "iso:country":"ES",
    "sg:address":"Carrer de Pere El Gran, 14",
    "sg:city":"Granollers",
    "sg:orig_category":"Teatro, Ballet, Danza (agrupaciones, Compa\u00d1\u00cdas)",
    "sg:phone":"+34 938 49 70 33",
    "sg:postcode":"08402",
    "sg:province":"Barcelona",
    "wof:name":"Jaime Vila Bosch",
    "wof:placetype":"venue"
},
  "geometry": {"coordinates":[2.2932469845,41.6183815002],"type":"Point"}
}