{
  "type": "Feature",
  "properties": {
    "addr:full":"Ptda Colador, S/n Onda Castell\u00f3n 12200",
    "addr:housenumber":"s / n",
    "addr:postcode":"12200",
    "addr:street":"Ptda Colador;Castello\u0301N",
    "iso:country":"ES",
    "sg:address":"Ptda Colador, S/n",
    "sg:city":"Onda",
    "sg:orig_category":"Revestimiento No Met\u00c1licos (esmaltado, Pintura, Plastificado)",
    "sg:phone":"+34 964 77 12 20",
    "sg:postcode":"12200",
    "sg:province":"Castell\u00f3n",
    "sg:website":"www.cloronda.com",
    "wof:name":"Coloronda S.l.",
    "wof:placetype":"venue"
},
  "geometry": {"coordinates":[-0.2620640099,39.9651794434],"type":"Point"}
}