{
  "type": "Feature",
  "properties": {
    "iso:country":"ES",
    "sg:address":"Calle de Pintor Sorolla, 5",
    "sg:city":"Madrid",
    "sg:orig_category":"Mec\u00c1nico Del Autom\u00d3vil",
    "sg:phone":"+34 914 78 08 95",
    "sg:postcode":"28053",
    "sg:province":"Madrid",
    "wof:name":"Arevalo Fernandez Francisco Javier",
    "wof:placetype":"venue"
},
  "geometry": {"coordinates":[-3.6706094742,40.3860855103],"type":"Point"}
}