{
  "type": "Feature",
  "properties": {
    "iso:country":"ES",
    "sg:address":"Rbla Catalunya, 15",
    "sg:city":"Barcelona",
    "sg:orig_category":"Asociaciones, Organismos Culturales Y Socioeducativos",
    "sg:phone":"+34 933 17 05 85",
    "sg:postcode":"08007",
    "sg:province":"Barcelona",
    "wof:name":"Associacio Coneix Catalunya",
    "wof:placetype":"venue"
},
  "geometry": {"coordinates":[2.1672129631,41.3883247375],"type":"Point"}
}