{
  "type": "Feature",
  "properties": {
    "addr:full":"Calle de Doctor Jaime Marcos, S/n Sevilla Sevilla 41009",
    "addr:housenumber":"s / n",
    "addr:postcode":"41009",
    "addr:street":"Calle De Doctor Jaime Marcos",
    "iso:country":"ES",
    "sg:address":"Calle de Doctor Jaime Marcos, S/n",
    "sg:city":"Sevilla",
    "sg:orig_category":"Zapatos (al Por Menor)",
    "sg:phone":"+34 954 37 89 53",
    "sg:postcode":"41009",
    "sg:province":"Sevilla",
    "wof:name":"Bola\u00f1os Ruiz Lopera Manuel",
    "wof:placetype":"venue"
},
  "geometry": {"coordinates":[-5.9832987785,37.4095344543],"type":"Point"}
}