{
  "type": "Feature",
  "properties": {
    "addr:full":"Carrer de Major, 60 Ulldecona Tarragona 43550",
    "addr:postcode":"43550",
    "addr:street":"Carrer De Major 60",
    "iso:country":"ES",
    "sg:address":"Carrer de Major, 60",
    "sg:city":"Ulldecona",
    "sg:orig_category":"Laboratorios Y Trabajos De Fotograf\u00cda, V\u00cddeo Y Cine",
    "sg:phone":"+34 977 72 00 57",
    "sg:postcode":"43550",
    "sg:province":"Tarragona",
    "wof:name":"Ferrer Fabra Joaquin",
    "wof:placetype":"venue"
},
  "geometry": {"coordinates":[0.4484089911,40.5979385376],"type":"Point"}
}