{
  "type": "Feature",
  "properties": {
    "iso:country":"ES",
    "sg:address":"Calle de San Martin, 53",
    "sg:city":"Donostia-san Sebastian",
    "sg:orig_category":"Talleres De Corte Y Confecci\u00d3n",
    "sg:phone":"+34 943 46 98 73",
    "sg:postcode":"20007",
    "sg:province":"Guip\u00f9zcoa",
    "wof:name":"Chamorro Garcia Angela",
    "wof:placetype":"venue"
},
  "geometry": {"coordinates":[-1.9866449833,43.3155250549],"type":"Point"}
}