{
  "type": "Feature",
  "properties": {
    "addr:full":"Cra. Bot, S/n Gandesa Tarragona 43780",
    "addr:housenumber":"s / n",
    "addr:postcode":"43780",
    "addr:street":"Cra. Bot",
    "iso:country":"ES",
    "sg:address":"Cra. Bot, S/n",
    "sg:city":"Gandesa",
    "sg:orig_category":"Material Y Herramientas Agr\u00cdcolas",
    "sg:phone":"+34 977 42 09 59",
    "sg:postcode":"43780",
    "sg:province":"Tarragona",
    "wof:name":"Talleres Salvado Y Costa C.d.",
    "wof:placetype":"venue"
},
  "geometry": {"coordinates":[0.4384000003,41.0540313721],"type":"Point"}
}