{
  "type": "Feature",
  "properties": {
    "addr:full":"Rua Ronda Don Bosco, 2 Vigo Pontevedra 36202",
    "addr:housenumber":"2",
    "addr:postcode":"36202",
    "addr:street":"Rua Ronda Don Bosco",
    "iso:country":"ES",
    "sg:address":"Rua Ronda Don Bosco, 2",
    "sg:city":"Vigo",
    "sg:orig_category":"Abogados",
    "sg:phone":"+34 986 43 61 31",
    "sg:postcode":"36202",
    "sg:province":"Pontevedra",
    "wof:name":"Estevez Dieguez Miguel Angel",
    "wof:placetype":"venue"
},
  "geometry": {"coordinates":[-8.7247953415,42.235042572],"type":"Point"}
}