{
  "type": "Feature",
  "properties": {
    "iso:country":"ES",
    "sg:address":"Calle de Cantalejo, 5",
    "sg:city":"Madrid",
    "sg:orig_category":"Arquitectos",
    "sg:phone":"+34 913 86 58 59",
    "sg:postcode":"28035",
    "sg:province":"Madrid",
    "wof:name":"Herranz Rodriguez Ruben",
    "wof:placetype":"venue"
},
  "geometry": {"coordinates":[-3.7410087585,40.4753570557],"type":"Point"}
}