{
  "type": "Feature",
  "properties": {
    "iso:country":"ES",
    "sg:address":"Carrer de Isabel De Villena, 54",
    "sg:city":"Granollers",
    "sg:orig_category":"Centros De Coordinaci\u00d3n",
    "sg:phone":"+34 938 70 73 11",
    "sg:postcode":"08401",
    "sg:province":"Barcelona",
    "wof:name":"Area De Gestio Granollers S.l.",
    "wof:placetype":"venue"
},
  "geometry": {"coordinates":[2.283755064,41.6047477722],"type":"Point"}
}