{
  "type": "Feature",
  "properties": {
    "iso:country":"ES",
    "sg:address":"Plaz Sol (el), 1",
    "sg:city":"Andujar",
    "sg:orig_category":"M\u00c9dicos: Estomatolog\u00cda",
    "sg:phone":"+34 953 50 48 04",
    "sg:postcode":"23740",
    "sg:province":"Ja\u00e9n",
    "wof:name":"Peix Santos Claudio",
    "wof:placetype":"venue"
},
  "geometry": {"coordinates":[-4.057518959,38.0386962891],"type":"Point"}
}