{
  "type": "Feature",
  "properties": {
    "addr:full":"Calle de Poeta Llorente, S/n Pobla Vallbona Valencia 46185",
    "addr:housenumber":"s / n",
    "addr:postcode":"46185",
    "addr:street":"Calle De Poeta Llorente",
    "iso:country":"ES",
    "sg:address":"Calle de Poeta Llorente, S/n",
    "sg:city":"Pobla Vallbona",
    "sg:orig_category":"Distribuci\u00d3n De Petr\u00d3leo Y Derivados",
    "sg:phone":"+34 961 66 17 36",
    "sg:postcode":"46185",
    "sg:province":"Valencia",
    "wof:name":"Repsol Ypf S.a.",
    "wof:placetype":"venue"
},
  "geometry": {"coordinates":[-0.5534440279,39.5925750732],"type":"Point"}
}