{
  "type": "Feature",
  "properties": {
    "iso:country":"ES",
    "sg:address":"Calle de Mayor, 51",
    "sg:city":"Cangas Narcea",
    "sg:orig_category":"Relojer\u00cda (al Por Menor, Reparaci\u00d3n)",
    "sg:phone":"+34 985 81 07 19",
    "sg:postcode":"33800",
    "sg:province":"Asturias",
    "wof:name":"Berlin C.b.",
    "wof:placetype":"venue"
},
  "geometry": {"coordinates":[-6.5512938499,43.1789398193],"type":"Point"}
}