{
  "type": "Feature",
  "properties": {
    "addr:full":"Ctra Castellar, 56 Terrassa Barcelona 08222",
    "addr:housenumber":"56",
    "addr:postcode":"08222",
    "addr:street":"Ctra Castellar",
    "iso:country":"ES",
    "sg:address":"Ctra Castellar, 56",
    "sg:city":"Terrassa",
    "sg:classifiers":[
        {
            "category":"Personal",
            "subcategory":"Barber",
            "type":"Services"
        }
    ],
    "sg:phone":"+34 937 85 91 21",
    "sg:postcode":"08222",
    "sg:province":"Barcelona",
    "sg:tags":[
        "caballeros",
        "de",
        "peluqueros"
    ],
    "wof:name":"Martinez Molina Jose",
    "wof:placetype":"venue"
},
  "geometry": {"coordinates":[2.0236189365,41.5655593872],"type":"Point"}
}