{
  "type": "Feature",
  "properties": {
    "addr:full":"Calle de San Jose De Calasanz, 80 Valladolid Valladolid 47013",
    "addr:housenumber":"80",
    "addr:postcode":"47013",
    "addr:street":"Calle De San;De Calasanz",
    "iso:country":"ES",
    "sg:address":"Calle de San Jose De Calasanz, 80",
    "sg:city":"Valladolid",
    "sg:orig_category":"Agentes, Concesionarios Y Sucursales De Veh\u00cdculos",
    "sg:phone":"+34 983 47 16 08",
    "sg:postcode":"47013",
    "sg:province":"Valladolid",
    "wof:name":"Talleres Miguel De La Calle S.l.",
    "wof:placetype":"venue"
},
  "geometry": {"coordinates":[-4.7198600769,41.636882782],"type":"Point"}
}