{
  "type": "Feature",
  "properties": {
    "addr:full":"Aita Larramendi Kalea, 11 Andoain Guip\u00f9zcoa 20140",
    "addr:housenumber":"11",
    "addr:postcode":"20140",
    "addr:street":"Aita Larramendi Kalea;Guipu\u0300Zcoa",
    "iso:country":"ES",
    "sg:address":"Aita Larramendi Kalea, 11",
    "sg:city":"Andoain",
    "sg:orig_category":"Transportes Por Carretera: Lotes Completos, Mercanc\u00cdas Diversas",
    "sg:phone":"+34 943 59 07 59",
    "sg:postcode":"20140",
    "sg:province":"Guip\u00f9zcoa",
    "wof:name":"Jauregui Echeberria Jose Antonio",
    "wof:placetype":"venue"
},
  "geometry": {"coordinates":[-2.0259621143,43.2114715576],"type":"Point"}
}