{
  "type": "Feature",
  "properties": {
    "addr:full":"Calle de Ronda Magdalena, 100 Castellon Castell\u00f3n 12004",
    "addr:housenumber":"100",
    "addr:postcode":"12004",
    "addr:street":"Calle De Ronda Magdalena",
    "iso:country":"ES",
    "sg:address":"Calle de Ronda Magdalena, 100",
    "sg:city":"Castellon",
    "sg:orig_category":"Animales (al Por Menor)",
    "sg:phone":"+34 964 25 73 68",
    "sg:postcode":"12004",
    "sg:province":"Castell\u00f3n",
    "wof:name":"Pajareria Badal S.l.",
    "wof:placetype":"venue"
},
  "geometry": {"coordinates":[-0.0257600006,40.0253791809],"type":"Point"}
}