{
  "type": "Feature",
  "properties": {
    "addr:full":"Calle de Larrauri Kalea, 1 Arteaga Derio Vizcaya 48160",
    "addr:housenumber":"1",
    "addr:postcode":"48160",
    "addr:street":"Calle De Larrauri Kalea",
    "iso:country":"ES",
    "sg:address":"Calle de Larrauri Kalea, 1",
    "sg:city":"Arteaga Derio",
    "sg:orig_category":"Centros Empresariales",
    "sg:phone":"+34 944 54 42 99",
    "sg:postcode":"48160",
    "sg:province":"Vizcaya",
    "wof:name":"Management Arriortua S.l.",
    "wof:placetype":"venue"
},
  "geometry": {"coordinates":[-2.8833999634,43.293838501],"type":"Point"}
}