{
  "type": "Feature",
  "properties": {
    "addr:full":"Calle de Deposito, 17 Motril Granada 18600",
    "addr:housenumber":"17",
    "addr:postcode":"18600",
    "addr:street":"Calle De Deposito",
    "iso:country":"ES",
    "sg:address":"Calle de Deposito, 17",
    "sg:city":"Motril",
    "sg:orig_category":"Parques De Atracciones Y Centros De Esparcimiento",
    "sg:phone":"+34 958 60 94 28",
    "sg:postcode":"18600",
    "sg:province":"Granada",
    "wof:name":"Quero Correa Francisco",
    "wof:placetype":"venue"
},
  "geometry": {"coordinates":[-3.5144953728,36.747051239],"type":"Point"}
}