{
  "type": "Feature",
  "properties": {
    "iso:country":"ES",
    "sg:address":"Calle de Nueva Del Sur, 7",
    "sg:city":"Santa Maria Del Berrocal",
    "sg:orig_category":"Reposter\u00cdas",
    "sg:phone":"+34 920 36 71 94",
    "sg:postcode":"05510",
    "sg:province":"\u00c1vila",
    "wof:name":"Blazquez Casas Vicente",
    "wof:placetype":"venue"
},
  "geometry": {"coordinates":[-5.4051008224,40.5077552795],"type":"Point"}
}