{
  "type": "Feature",
  "properties": {
    "addr:full":"Calle de Mayor, 69 Almoradi Alicante 03160",
    "addr:housenumber":"69",
    "addr:postcode":"03160",
    "addr:street":"Calle De Mayor",
    "iso:country":"ES",
    "sg:address":"Calle de Mayor, 69",
    "sg:city":"Almoradi",
    "sg:orig_category":"Electricidad, Electr\u00d3nica: Suministros (al Por Menor)",
    "sg:phone":"+34 966 78 18 70",
    "sg:postcode":"03160",
    "sg:province":"Alicante",
    "wof:name":"Electronica Bailen Radio S.l.",
    "wof:placetype":"venue"
},
  "geometry": {"coordinates":[-0.7963640094,38.1062393188],"type":"Point"}
}