{
  "type": "Feature",
  "properties": {
    "addr:full":"Carr Eiximenis, 20 Girona Girona 17001",
    "addr:housenumber":"20",
    "addr:postcode":"17001",
    "addr:street":"Carr Eiximenis",
    "iso:country":"ES",
    "sg:address":"Carr Eiximenis, 20",
    "sg:city":"Girona",
    "sg:orig_category":"Abogados",
    "sg:phone":"+34 972 22 72 27",
    "sg:postcode":"17001",
    "sg:province":"Girona",
    "wof:name":"Lcp & Associats Advocats I Economistes S.l.",
    "wof:placetype":"venue"
},
  "geometry": {"coordinates":[2.8217051029,41.9848251343],"type":"Point"}
}