{
  "type": "Feature",
  "properties": {
    "iso:country":"ES",
    "sg:address":"Calle de Milicias, 16",
    "sg:city":"Logro\u00f1o",
    "sg:orig_category":"Carnicer\u00cdas, Carnicer\u00cdas",
    "sg:phone":"+34 941 24 84 60",
    "sg:postcode":"26003",
    "sg:province":"La Rioja",
    "wof:name":"Echarri Casis Gisela",
    "wof:placetype":"venue"
},
  "geometry": {"coordinates":[-2.4377129078,42.4624328613],"type":"Point"}
}