{
  "type": "Feature",
  "properties": {
    "addr:full":"C/ Fred, 39 Ferreries Islas Baleares 07750",
    "addr:housenumber":"39",
    "addr:postcode":"07750",
    "addr:street":"C / Fred",
    "iso:country":"ES",
    "sg:address":"C/ Fred, 39",
    "sg:city":"Ferreries",
    "sg:orig_category":"Ropa Para Se\u00d1oras Y Caballeros (al Por Menor)",
    "sg:phone":"+34 971 37 41 46",
    "sg:postcode":"07750",
    "sg:province":"Islas Baleares",
    "wof:name":"Taboada Febrer Sandra",
    "wof:placetype":"venue"
},
  "geometry": {"coordinates":[4.0079188347,39.9823875427],"type":"Point"}
}