{
  "type": "Feature",
  "properties": {
    "addr:full":"Calle de Cerro De Mairena, 8 Mairena Aljarafe Sevilla 41927",
    "addr:housenumber":"8",
    "addr:postcode":"41927",
    "addr:street":"Calle De Cerro De Mairena",
    "iso:country":"ES",
    "sg:address":"Calle de Cerro De Mairena, 8",
    "sg:city":"Mairena Aljarafe",
    "sg:orig_category":"Agencias Y Agentes Comerciales, Representantes",
    "sg:phone":"+34 954 76 12 01",
    "sg:postcode":"41927",
    "sg:province":"Sevilla",
    "wof:name":"Mu\u00f1iz Salazar Angel",
    "wof:placetype":"venue"
},
  "geometry": {"coordinates":[-6.0424938202,37.3542518616],"type":"Point"}
}