{
  "type": "Feature",
  "properties": {
    "iso:country":"ES",
    "sg:address":"Carr Anselm Clave, 6",
    "sg:city":"Blanes",
    "sg:classifiers":[
        {
            "category":"Autos & Motor Vehicles",
            "subcategory":"Automobile Sales",
            "type":"Retail Goods"
        }
    ],
    "sg:phone":"+34 972 33 27 87",
    "sg:postcode":"17300",
    "sg:province":"Girona",
    "wof:name":"Auto Escuela Trevejo S.l.",
    "wof:placetype":"venue"
},
  "geometry": {"coordinates":[2.7896242142,41.676235199],"type":"Point"}
}