{
  "type": "Feature",
  "properties": {
    "addr:full":"Calle de Real Alta, 28 Mu\u00d1overos Segovia 40183",
    "addr:housenumber":"28",
    "addr:postcode":"40183",
    "addr:street":"Calle De Real Alta;Segovia",
    "iso:country":"ES",
    "sg:address":"Calle de Real Alta, 28",
    "sg:city":"Mu\u00d1overos",
    "sg:orig_category":"Producci\u00d3n De Abonos Y De Fertilizantes",
    "sg:phone":"+34 921 50 05 60",
    "sg:postcode":"40183",
    "sg:province":"Segovia",
    "wof:name":"Orejana Pastor Miguel Angel",
    "wof:placetype":"venue"
},
  "geometry": {"coordinates":[-3.9515590668,41.1706047058],"type":"Point"}
}