{
  "type": "Feature",
  "properties": {
    "addr:full":"Carrer de Salva, 34 Barcelona Barcelona 08004",
    "addr:housenumber":"34",
    "addr:postcode":"08004",
    "addr:street":"Carrer De Salva",
    "iso:country":"ES",
    "sg:address":"Carrer de Salva, 34",
    "sg:city":"Barcelona",
    "sg:orig_category":"Inmobiliaria (agencias)",
    "sg:phone":"+34 934 41 31 43",
    "sg:postcode":"08004",
    "sg:province":"Barcelona",
    "wof:name":"Jadirum S.l.",
    "wof:placetype":"venue"
},
  "geometry": {"coordinates":[2.1658029556,41.3735427856],"type":"Point"}
}