{
  "type": "Feature",
  "properties": {
    "addr:full":"Avda Fonteculler, 35 Fonteculler A Coru\u00f1a 15174",
    "addr:housenumber":"35",
    "addr:postcode":"15174",
    "addr:street":"Avda Fonteculler;Corun\u0303A",
    "iso:country":"ES",
    "sg:address":"Avda Fonteculler, 35",
    "sg:city":"Fonteculler",
    "sg:orig_category":"Veh\u00cdculos De Ocasi\u00d3n",
    "sg:phone":"+34 981 13 74 10",
    "sg:postcode":"15174",
    "sg:province":"A Coru\u00f1a",
    "wof:name":"Tameba S.l.",
    "wof:placetype":"venue"
},
  "geometry": {"coordinates":[-8.3826389313,43.3110656738],"type":"Point"}
}