{
  "type": "Feature",
  "properties": {
    "iso:country":"ES",
    "sg:address":"Calle de Urbide, S/n",
    "sg:city":"Berreagamendi",
    "sg:orig_category":"Inmobiliaria (agencias)",
    "sg:phone":"+34 946 15 58 20",
    "sg:postcode":"48100",
    "sg:province":"Vizcaya",
    "wof:name":"Inmobiliaria Club De Campo De La Sociedad La Bilbaina S.a.",
    "wof:placetype":"venue"
},
  "geometry": {"coordinates":[-2.8615629673,43.3304443359],"type":"Point"}
}