{
  "type": "Feature",
  "properties": {
    "addr:full":"Carrer de Narbona, 12 Barcelona Barcelona 08019",
    "addr:housenumber":"12",
    "addr:postcode":"08019",
    "addr:street":"Carrer De Narbona",
    "iso:country":"ES",
    "sg:address":"Carrer de Narbona, 12",
    "sg:city":"Barcelona",
    "sg:orig_category":"M\u00c9dicos: Estomatolog\u00cda",
    "sg:phone":"+34 933 13 80 77",
    "sg:postcode":"08019",
    "sg:province":"Barcelona",
    "wof:name":"Alejos Algarra Fernando Enrique",
    "wof:placetype":"venue"
},
  "geometry": {"coordinates":[2.2125804424,41.4198608398],"type":"Point"}
}