{
  "type": "Feature",
  "properties": {
    "addr:full":"Carretera Mas Del Jutge, 57 Torrent Valencia 46900",
    "addr:housenumber":"57",
    "addr:postcode":"46900",
    "addr:street":"Carretera Mas Del Jutge;Valencia",
    "iso:country":"ES",
    "sg:address":"Carretera Mas Del Jutge, 57",
    "sg:city":"Torrent",
    "sg:orig_category":"Empresas De Carpinter\u00cda",
    "sg:phone":"+34 961 56 26 26",
    "sg:postcode":"46900",
    "sg:province":"Valencia",
    "wof:name":"Varri Carpinteria-cerrajeria S.l.",
    "wof:placetype":"venue"
},
  "geometry": {"coordinates":[-0.4831030071,39.4385223389],"type":"Point"}
}