{
  "type": "Feature",
  "properties": {
    "addr:full":"Av Diagonal, 208 Barcelona Barcelona 08018",
    "addr:housenumber":"208",
    "addr:postcode":"08018",
    "addr:street":"Av Diagonal",
    "iso:country":"ES",
    "sg:address":"Av Diagonal, 208",
    "sg:city":"Barcelona",
    "sg:orig_category":"Congelados: Productos Alimentarios (al Por Menor)",
    "sg:phone":"+34 934 86 01 54",
    "sg:postcode":"08018",
    "sg:province":"Barcelona",
    "sg:website":"www.lasirena.es",
    "wof:name":"La Sirena Alimentacion Congelada S.l.u.",
    "wof:placetype":"venue"
},
  "geometry": {"coordinates":[2.1925270557,41.405002594],"type":"Point"}
}