{
  "type": "Feature",
  "properties": {
    "addr:full":"Plaz San Juan, 6 Cox Alicante 03350",
    "addr:housenumber":"6",
    "addr:postcode":"03350",
    "addr:street":"Plaz San Juan",
    "iso:country":"ES",
    "sg:address":"Plaz San Juan, 6",
    "sg:city":"Cox",
    "sg:orig_category":"Formaci\u00d3n Continuada (variada)",
    "sg:phone":"+34 966 75 01 13",
    "sg:postcode":"03350",
    "sg:province":"Alicante",
    "wof:name":"Franco Nierola Maria Luisa",
    "wof:placetype":"venue"
},
  "geometry": {"coordinates":[-0.8840770125,38.1400680542],"type":"Point"}
}