{
  "type": "Feature",
  "properties": {
    "iso:country":"ES",
    "sg:address":"Calle de Agustina De Aragon, 34",
    "sg:city":"Altorricon",
    "sg:orig_category":"Cr\u00cda De Animales",
    "sg:phone":"+34 974 42 52 50",
    "sg:postcode":"22540",
    "sg:province":"Huesca",
    "wof:name":"Solari S.c.",
    "wof:placetype":"venue"
},
  "geometry": {"coordinates":[0.4150558114,41.8028869629],"type":"Point"}
}