{
  "type": "Feature",
  "properties": {
    "iso:country":"ES",
    "sg:address":"Carrer de Porto, 3",
    "sg:city":"Palma",
    "sg:orig_category":"Mec\u00c1nico Del Autom\u00d3vil",
    "sg:phone":"+34 971 45 21 12",
    "sg:postcode":"07014",
    "sg:province":"Islas Baleares",
    "wof:name":"Vi\u00f1uela Eslava Fernando",
    "wof:placetype":"venue"
},
  "geometry": {"coordinates":[2.6316802502,39.5777130127],"type":"Point"}
}