{
  "type": "Feature",
  "properties": {
    "iso:country":"ES",
    "sg:address":"Calle de Mediterraneo, 3",
    "sg:city":"Valencia",
    "sg:orig_category":"Cristaler\u00cdas",
    "sg:phone":"+34 963 71 39 11",
    "sg:postcode":"46011",
    "sg:province":"Valencia",
    "wof:name":"Lopez Lopez Jose",
    "wof:placetype":"venue"
},
  "geometry": {"coordinates":[-0.3320249915,39.4679603577],"type":"Point"}
}