{
  "type": "Feature",
  "properties": {
    "iso:country":"ES",
    "sg:address":"Calle de Emilia Menendez, S/n",
    "sg:city":"Robla",
    "sg:orig_category":"Centros De Educaci\u00d3n Especial",
    "sg:phone":"+34 987 57 01 34",
    "sg:postcode":"24640",
    "sg:province":"Le\u00f3n",
    "wof:name":"Colegio Publico Emilia Menendez",
    "wof:placetype":"venue"
},
  "geometry": {"coordinates":[-5.6305880547,42.8035430908],"type":"Point"}
}