{
  "type": "Feature",
  "properties": {
    "addr:full":"Carr S Josep, 99 Igualada Barcelona 08700",
    "addr:housenumber":"99",
    "addr:postcode":"08700",
    "addr:street":"Carr S Josep",
    "iso:country":"ES",
    "sg:address":"Carr S Josep, 99",
    "sg:city":"Igualada",
    "sg:orig_category":"Agentes Generales De Seguros",
    "sg:phone":"+34 938 05 05 37",
    "sg:postcode":"08700",
    "sg:province":"Barcelona",
    "wof:name":"Serarols Fajas Jaume",
    "wof:placetype":"venue"
},
  "geometry": {"coordinates":[1.6249200106,41.585357666],"type":"Point"}
}