{
  "type": "Feature",
  "properties": {
    "iso:country":"ES",
    "sg:address":"Calle de Jose Ortega Y Gasset, 7",
    "sg:city":"Madrid",
    "sg:orig_category":"Inmobiliaria (agencias)",
    "sg:phone":"+34 915 77 80 95",
    "sg:postcode":"28006",
    "sg:province":"Madrid",
    "wof:name":"Pontegadea-serrano 49 S.l.",
    "wof:placetype":"venue"
},
  "geometry": {"coordinates":[-3.6872119904,40.4306106567],"type":"Point"}
}