{
  "type": "Feature",
  "properties": {
    "addr:full":"Carr Tarragona, 46 Mas Aliu Girona 17181",
    "addr:housenumber":"46",
    "addr:postcode":"17181",
    "addr:street":"Carr Tarragona",
    "iso:country":"ES",
    "sg:address":"Carr Tarragona, 46",
    "sg:city":"Mas Aliu",
    "sg:orig_category":"Maquinaria Para Industrias Diversas",
    "sg:phone":"+34 972 39 41 72",
    "sg:postcode":"17181",
    "sg:province":"Girona",
    "sg:website":"www.iniciativasmecanicas.com",
    "wof:name":"Imec S.l.",
    "wof:placetype":"venue"
},
  "geometry": {"coordinates":[2.7807080746,41.9432678223],"type":"Point"}
}