{
  "type": "Feature",
  "properties": {
    "addr:full":"Carrer de Sant Elies, 5 Palma Islas Baleares 07003",
    "addr:housenumber":"5",
    "addr:postcode":"07003",
    "addr:street":"Carrer De Sant Elies",
    "iso:country":"ES",
    "sg:address":"Carrer de Sant Elies, 5",
    "sg:city":"Palma",
    "sg:orig_category":"Institutos De Belleza",
    "sg:phone":"+34 971 72 55 24",
    "sg:postcode":"07003",
    "sg:province":"Islas Baleares",
    "wof:name":"Rodriguez Munera Pilar",
    "wof:placetype":"venue"
},
  "geometry": {"coordinates":[2.6500248909,39.5745582581],"type":"Point"}
}