{
  "type": "Feature",
  "properties": {
    "addr:full":"Carr Zamora, 3 Girona Girona 17005",
    "addr:housenumber":"3",
    "addr:postcode":"17005",
    "addr:street":"Carr Zamora",
    "iso:country":"ES",
    "sg:address":"Carr Zamora, 3",
    "sg:city":"Girona",
    "sg:orig_category":"M\u00c9dicos: Estomatolog\u00cda",
    "sg:phone":"+34 972 24 25 45",
    "sg:postcode":"17005",
    "sg:province":"Girona",
    "wof:name":"Maceo Gonzalez Luis Eduardo",
    "wof:placetype":"venue"
},
  "geometry": {"coordinates":[2.8115229607,41.9711112976],"type":"Point"}
}