{
  "type": "Feature",
  "properties": {
    "iso:country":"ES",
    "sg:address":"Calle de Divino Pastor, 22",
    "sg:city":"Madrid",
    "sg:orig_category":"Venta, Alquiler De Instrumentos Y Accesorios De M\u00dasica",
    "sg:phone":"+34 914 45 72 19",
    "sg:postcode":"28004",
    "sg:province":"Madrid",
    "wof:name":"Rojo Solar Francisco Javier",
    "wof:placetype":"venue"
},
  "geometry": {"coordinates":[-3.7047963142,40.4278030396],"type":"Point"}
}