{
  "type": "Feature",
  "properties": {
    "iso:country":"ES",
    "sg:address":"Marquesa Vda Saltillo, 6",
    "sg:city":"Sanlucar Mayor",
    "sg:orig_category":"Asesor\u00cda De Formaci\u00d3n Y Gesti\u00d3n De Personal",
    "sg:phone":"+34 955 70 48 16",
    "sg:postcode":"41800",
    "sg:province":"Sevilla",
    "wof:name":"Moguer Luque Jose Carlos",
    "wof:placetype":"venue"
},
  "geometry": {"coordinates":[-6.20291996,37.384311676],"type":"Point"}
}