{
  "type": "Feature",
  "properties": {
    "iso:country":"ES",
    "sg:address":"Carr Pi I Margall, 33",
    "sg:city":"Lleida",
    "sg:orig_category":"Carnicer\u00cdas, Carnicer\u00cdas",
    "sg:phone":"+34 973 23 19 21",
    "sg:postcode":"25004",
    "sg:province":"Lleida",
    "wof:name":"Carner Vidal Josefa",
    "wof:placetype":"venue"
},
  "geometry": {"coordinates":[0.6269699931,41.6219215393],"type":"Point"}
}