{
  "type": "Feature",
  "properties": {
    "addr:full":"Calle de San Juan De Dios, 6 Sevilla Sevilla 41005",
    "addr:housenumber":"6",
    "addr:postcode":"41005",
    "addr:street":"Calle De San Juan;Dios",
    "iso:country":"ES",
    "sg:address":"Calle de San Juan De Dios, 6",
    "sg:city":"Sevilla",
    "sg:orig_category":"Farmacias",
    "sg:phone":"+34 954 63 57 98",
    "sg:postcode":"41005",
    "sg:province":"Sevilla",
    "wof:name":"Martin Sacristan Nu\u00f1ez Inmaculada",
    "wof:placetype":"venue"
},
  "geometry": {"coordinates":[-5.969824791,37.3815460205],"type":"Point"}
}