{
  "type": "Feature",
  "properties": {
    "iso:country":"ES",
    "sg:address":"Calle de General Primo De Rivera, 1",
    "sg:city":"Algeciras",
    "sg:orig_category":"Farmacias",
    "sg:phone":"+34 956 66 18 90",
    "sg:postcode":"11201",
    "sg:province":"C\u00e1diz",
    "wof:name":"Farmacia Villegas Mu\u00f1oz",
    "wof:placetype":"venue"
},
  "geometry": {"coordinates":[-5.4465317726,36.1309280396],"type":"Point"}
}