{
  "type": "Feature",
  "properties": {
    "iso:country":"ES",
    "sg:address":"Calle de Cadiz, 14",
    "sg:city":"Roda Andalucia",
    "sg:orig_category":"Producci\u00d3n, Comercio De Cereales",
    "sg:phone":"+34 954 01 65 84",
    "sg:postcode":"41590",
    "sg:province":"Sevilla",
    "wof:name":"Castillo Lopez Juan Carlos",
    "wof:placetype":"venue"
},
  "geometry": {"coordinates":[-4.7770171165,37.2080879211],"type":"Point"}
}