{
  "type": "Feature",
  "properties": {
    "iso:country":"ES",
    "sg:address":"Rua Doctor Casares, 78",
    "sg:city":"Monforte De Lemos",
    "sg:orig_category":"Negocio De Materiales De Construcci\u00d3n",
    "sg:phone":"+34 982 40 18 38",
    "sg:postcode":"27400",
    "sg:province":"Lugo",
    "wof:name":"Marcos Sanchez Manuel",
    "wof:placetype":"venue"
},
  "geometry": {"coordinates":[-7.5109372139,42.5254058838],"type":"Point"}
}