{
  "type": "Feature",
  "properties": {
    "addr:full":"Calle de Lanuza, 9 Madrid Madrid 28028",
    "addr:housenumber":"9",
    "addr:postcode":"madrid;28028",
    "addr:street":"Calle De Lanuza",
    "iso:country":"ES",
    "sg:address":"Calle de Lanuza, 9",
    "sg:city":"Madrid",
    "sg:orig_category":"Organizaciones Internacionales",
    "sg:phone":"+34 917 25 13 31",
    "sg:postcode":"28028",
    "sg:province":"Madrid",
    "sg:website":"www.medicusmundi.es/madrid",
    "wof:name":"Medicus Mundi Madrid",
    "wof:placetype":"venue"
},
  "geometry": {"coordinates":[-3.6654291153,40.4251670837],"type":"Point"}
}