{
  "type": "Feature",
  "properties": {
    "iso:country":"ES",
    "sg:address":"Bo. Pousada, 49",
    "sg:city":"Mos",
    "sg:orig_category":"Alimentaci\u00d3n General (al Por Menor)",
    "sg:phone":"+34 986 33 17 14",
    "sg:postcode":"36416",
    "sg:province":"Pontevedra",
    "wof:name":"Alvarez Rubines Alfredo",
    "wof:placetype":"venue"
},
  "geometry": {"coordinates":[-8.6382312775,42.1947174072],"type":"Point"}
}