{
  "type": "Feature",
  "properties": {
    "iso:country":"ES",
    "sg:address":"Calle de Pico Almanzor (del), 13",
    "sg:city":"Humanes De Madrid",
    "sg:orig_category":"Muebles Y Accesorios Para Cocinas Y Cuartos De Ba\u00d1o (al Por Menor)",
    "sg:phone":"+34 916 04 80 70",
    "sg:postcode":"28970",
    "sg:province":"Madrid",
    "wof:name":"Industrias Auxiliares Del Hogar S. A.",
    "wof:placetype":"venue"
},
  "geometry": {"coordinates":[-3.8124508858,40.2624893188],"type":"Point"}
}