{
  "type": "Feature",
  "properties": {
    "iso:country":"ES",
    "sg:address":"Plaz Posito (el), 18",
    "sg:city":"Jaen",
    "sg:orig_category":"Estancos",
    "sg:phone":"+34 953 24 08 01",
    "sg:postcode":"23001",
    "sg:province":"Ja\u00e9n",
    "wof:name":"Ramirez Ramirez Emilio Javier",
    "wof:placetype":"venue"
},
  "geometry": {"coordinates":[-3.7888989449,37.7667007446],"type":"Point"}
}