{
  "type": "Feature",
  "properties": {
    "addr:full":"M. De Sucre, 9 Premia De Dalt Barcelona 08338",
    "addr:housenumber":"9",
    "addr:postcode":"08338",
    "addr:street":"M.;Barcelona",
    "iso:country":"ES",
    "sg:address":"M. De Sucre, 9",
    "sg:city":"Premia De Dalt",
    "sg:orig_category":"Pintura Y Barniz (al Por Menor)",
    "sg:phone":"+34 937 51 18 57",
    "sg:postcode":"08338",
    "sg:province":"Barcelona",
    "wof:name":"Costa Raurell Montserrat",
    "wof:placetype":"venue"
},
  "geometry": {"coordinates":[2.3460769653,41.505153656],"type":"Point"}
}