{
  "type": "Feature",
  "properties": {
    "iso:country":"ES",
    "sg:address":"Calle de Abastos (de), 100",
    "sg:city":"Aranjuez",
    "sg:orig_category":"Peluquer\u00cdas, Peluquer\u00cda Mixta",
    "sg:phone":"+34 918 92 24 53",
    "sg:postcode":"28300",
    "sg:province":"Madrid",
    "wof:name":"Abarca Ballesteros Peluqueras S.l.",
    "wof:placetype":"venue"
},
  "geometry": {"coordinates":[-3.600078,40.031761],"type":"Point"}
}