{
  "type": "Feature",
  "properties": {
    "iso:country":"ES",
    "sg:address":"Poligono 4, S/n",
    "sg:city":"Pollen\u00e7a",
    "sg:orig_category":"Transportes De Material De Construcci\u00d3n",
    "sg:phone":"+34 971 53 09 44",
    "sg:postcode":"07460",
    "sg:province":"Islas Baleares",
    "wof:name":"Aigua Caen Salas S.l.",
    "wof:placetype":"venue"
},
  "geometry": {"coordinates":[3.0375914574,39.8799629211],"type":"Point"}
}