{
  "type": "Feature",
  "properties": {
    "addr:full":"Crta Jaen (zona Ind Olinda), S/n Maracena Granada 18200",
    "addr:housenumber":"s / n",
    "addr:postcode":"18200",
    "addr:street":"Crta Jaen Zona;Olinda",
    "iso:country":"ES",
    "sg:address":"Crta Jaen (zona Ind Olinda), S/n",
    "sg:city":"Maracena",
    "sg:orig_category":"Fabricaci\u00d3n, Instalaci\u00d3n Y Reparaci\u00d3n De Bombas",
    "sg:phone":"+34 958 41 51 37",
    "sg:postcode":"18200",
    "sg:province":"Granada",
    "wof:name":"Electromecanica Oncina S.l.",
    "wof:placetype":"venue"
},
  "geometry": {"coordinates":[-3.6389689445,37.2088508606],"type":"Point"}
}