{
  "type": "Feature",
  "properties": {
    "iso:country":"ES",
    "sg:address":"Patrizio Etxeberria Kalea, 2",
    "sg:city":"Legazpi",
    "sg:orig_category":"Fotocopias, Reprograf\u00cda",
    "sg:phone":"+34 943 73 19 62",
    "sg:postcode":"20230",
    "sg:province":"Guip\u00f9zcoa",
    "wof:name":"Jon Andoni Aguirre Alzuru",
    "wof:placetype":"venue"
},
  "geometry": {"coordinates":[-2.3332760334,43.0522651672],"type":"Point"}
}