{
  "type": "Feature",
  "properties": {
    "addr:full":"Calle de Francisco Pizarro, 2 Cordoba C\u00f3rdoba 14010",
    "addr:housenumber":"2",
    "addr:postcode":"14010",
    "addr:street":"Calle De Francisco Pizarro;Co\u0301Rdoba",
    "iso:country":"ES",
    "sg:address":"Calle de Francisco Pizarro, 2",
    "sg:city":"Cordoba",
    "sg:orig_category":"M\u00c9dicos: Pediatr\u00cda. Enfermedades De Los Ni\u00d1os",
    "sg:phone":"+34 957 25 76 32",
    "sg:postcode":"14010",
    "sg:province":"C\u00f3rdoba",
    "wof:name":"Cantador Casalilla Miguel Angel",
    "wof:placetype":"venue"
},
  "geometry": {"coordinates":[-4.7614479065,37.8837661743],"type":"Point"}
}