{
  "type": "Feature",
  "properties": {
    "addr:full":"Urb Miragolf, 35 Nueva Andalucia M\u00e1laga 29660",
    "addr:housenumber":"35",
    "addr:postcode":"29660",
    "addr:street":"Urb Miragolf;Ma\u0301Laga",
    "iso:country":"ES",
    "sg:address":"Urb Miragolf, 35",
    "sg:city":"Nueva Andalucia",
    "sg:orig_category":"Arquitectos",
    "sg:phone":"+34 952 81 07 00",
    "sg:postcode":"29660",
    "sg:province":"M\u00e1laga",
    "wof:name":"Taborda Britch Angel Ruben",
    "wof:placetype":"venue"
},
  "geometry": {"coordinates":[-4.9540901184,36.4891586304],"type":"Point"}
}