{
  "type": "Feature",
  "properties": {
    "iso:country":"ES",
    "sg:address":"Calle de San Marcos, 75",
    "sg:city":"Priego Cordoba",
    "sg:orig_category":"Agentes Generales De Seguros",
    "sg:phone":"+34 957 70 05 03",
    "sg:postcode":"14800",
    "sg:province":"C\u00f3rdoba",
    "wof:name":"Cano Leiva Carmen Maria",
    "wof:placetype":"venue"
},
  "geometry": {"coordinates":[-4.2020850182,37.4386482239],"type":"Point"}
}