{
  "type": "Feature",
  "properties": {
    "iso:country":"ES",
    "sg:address":"Rua Constitucion (da), 10",
    "sg:city":"Sanxenxo",
    "sg:orig_category":"Sociedades, Compa\u00d1\u00cdas Aseguradoras",
    "sg:phone":"+34 986 72 40 65",
    "sg:postcode":"36960",
    "sg:province":"Pontevedra",
    "wof:name":"Fernandez Dominguez Juan",
    "wof:placetype":"venue"
},
  "geometry": {"coordinates":[-8.8031902313,42.4017601013],"type":"Point"}
}