{
  "type": "Feature",
  "properties": {
    "addr:full":"Carrer de Corominas, 7 Sabadell Barcelona 08201",
    "addr:housenumber":"7",
    "addr:postcode":"08201",
    "addr:street":"Carrer De Corominas",
    "iso:country":"ES",
    "sg:address":"Carrer de Corominas, 7",
    "sg:city":"Sabadell",
    "sg:orig_category":"Bancos",
    "sg:phone":"+34 937 27 87 00",
    "sg:postcode":"08201",
    "sg:province":"Barcelona",
    "wof:name":"Banc Sabadell S.a.",
    "wof:placetype":"venue"
},
  "geometry": {"coordinates":[2.1045320034,41.5468215942],"type":"Point"}
}