{
  "type": "Feature",
  "properties": {
    "addr:full":"Calle de Bajada Escuelas, 3 Peralta Navarra 31350",
    "addr:housenumber":"3",
    "addr:postcode":"31350",
    "addr:street":"Calle De Bajada Escuelas",
    "iso:country":"ES",
    "sg:address":"Calle de Bajada Escuelas, 3",
    "sg:city":"Peralta",
    "sg:orig_category":"Asesor\u00cda Sobre Comunicaci\u00d3n De Empresas",
    "sg:phone":"+34 948 75 03 07",
    "sg:postcode":"31350",
    "sg:province":"Navarra",
    "wof:name":"Acceptum S.l.",
    "wof:placetype":"venue"
},
  "geometry": {"coordinates":[-1.7991571426,42.3387832642],"type":"Point"}
}