{
  "type": "Feature",
  "properties": {
    "iso:country":"ES",
    "sg:address":"Carrer de Soler (de), 24",
    "sg:city":"Tarragona",
    "sg:orig_category":"Deportes Diversos",
    "sg:phone":"+34 977 21 57 00",
    "sg:postcode":"43001",
    "sg:province":"Tarragona",
    "wof:name":"Federacion Catalana De Futbol",
    "wof:placetype":"venue"
},
  "geometry": {"coordinates":[1.2481709719,41.1136322021],"type":"Point"}
}