{
  "type": "Feature",
  "properties": {
    "iso:country":"ES",
    "sg:address":"Avda Valladolid, 6",
    "sg:city":"Tordesillas",
    "sg:orig_category":"Asesor\u00cda Fiscal Y Jur\u00cddica",
    "sg:phone":"+34 983 79 67 80",
    "sg:postcode":"47100",
    "sg:province":"Valladolid",
    "wof:name":"Asesoria Fiscal Se.ad C.b",
    "wof:placetype":"venue"
},
  "geometry": {"coordinates":[-4.9999060631,41.5030403137],"type":"Point"}
}