{
  "type": "Feature",
  "properties": {
    "addr:full":"Ctra. Espinoso, Km. 0022,8 S. Bartolome Abiertas Toledo 45654",
    "addr:postcode":"45654",
    "addr:street":"Ctra. Espinoso Km. 0022,8 S. Bartolome Abiertas",
    "iso:country":"ES",
    "sg:address":"Ctra. Espinoso, Km. 0022,8",
    "sg:city":"S. Bartolome Abiertas",
    "sg:orig_category":"Empresas De Carpinter\u00cda",
    "sg:phone":"+34 925 70 41 17",
    "sg:postcode":"45654",
    "sg:province":"Toledo",
    "wof:name":"Jose Luis Iglesias S.l.",
    "wof:placetype":"venue"
},
  "geometry": {"coordinates":[-4.7151942253,39.829864502],"type":"Point"}
}