{
  "type": "Feature",
  "properties": {
    "addr:full":"Carrer de L'agricultura, 284 Barcelona Barcelona 08020",
    "addr:housenumber":"284",
    "addr:postcode":"08020",
    "addr:street":"Carrer De L'Agricultura",
    "iso:country":"ES",
    "sg:address":"Carrer de L'agricultura, 284",
    "sg:city":"Barcelona",
    "sg:orig_category":"Inform\u00c1tica, Ofim\u00c1tica (estudios, Asesor\u00cda, Ingenier\u00cda, Formaci\u00d3n)",
    "sg:phone":"+34 933 13 54 63",
    "sg:postcode":"08020",
    "sg:province":"Barcelona",
    "wof:name":"Selas Fernandez Miguel Angel",
    "wof:placetype":"venue"
},
  "geometry": {"coordinates":[2.199221611,41.4196968079],"type":"Point"}
}