{
  "type": "Feature",
  "properties": {
    "addr:full":"Calle de Marques De Teverga, 3 Oviedo Asturias 33005",
    "addr:housenumber":"3",
    "addr:postcode":"33005",
    "addr:street":"Calle De Marques De Teverga",
    "iso:country":"ES",
    "sg:address":"Calle de Marques De Teverga, 3",
    "sg:city":"Oviedo",
    "sg:orig_category":"Abogados",
    "sg:phone":"+34 985 22 42 24",
    "sg:postcode":"33005",
    "sg:province":"Asturias",
    "wof:name":"Garcia Valtue\u00f1a Francisco",
    "wof:placetype":"venue"
},
  "geometry": {"coordinates":[-5.8565821648,43.361618042],"type":"Point"}
}