{
  "type": "Feature",
  "properties": {
    "addr:full":"Carr Belgica, S/n Badalona Barcelona 08917",
    "addr:housenumber":"s / n",
    "addr:postcode":"08917",
    "addr:street":"Carr Belgica",
    "iso:country":"ES",
    "sg:address":"Carr Belgica, S/n",
    "sg:city":"Badalona",
    "sg:orig_category":"Fabrica De Cer\u00c1micas",
    "sg:phone":"+34 934 97 25 25",
    "sg:postcode":"08917",
    "sg:province":"Barcelona",
    "wof:name":"Hipermercado Del Gres Y La Ceramica S.l.",
    "wof:placetype":"venue"
},
  "geometry": {"coordinates":[2.2236700058,41.4585609436],"type":"Point"}
}