{
  "type": "Feature",
  "properties": {
    "iso:country":"ES",
    "sg:address":"Carr Ausias March, 14",
    "sg:city":"Moncada",
    "sg:orig_category":"Inmobiliaria (agencias)",
    "sg:phone":"+34 961 39 00 87",
    "sg:postcode":"46113",
    "sg:province":"Valencia",
    "wof:name":"Pascual Tamarit Salvador",
    "wof:placetype":"venue"
},
  "geometry": {"coordinates":[-0.3922829926,39.5447273254],"type":"Point"}
}