{
  "type": "Feature",
  "properties": {
    "iso:country":"ES",
    "sg:address":"Pi, 14",
    "sg:city":"S. Miquel Sacot",
    "sg:orig_category":"Cristaler\u00cdas",
    "sg:phone":"+34 972 27 29 20",
    "sg:postcode":"17811",
    "sg:province":"Girona",
    "wof:name":"Arbusa-grabulosa S.c.",
    "wof:placetype":"venue"
},
  "geometry": {"coordinates":[2.5113213062,42.160369873],"type":"Point"}
}