{
  "type": "Feature",
  "properties": {
    "iso:country":"ES",
    "sg:address":"Calle de Trinidad, 14",
    "sg:city":"Toledo",
    "sg:orig_category":"Art\u00cdculos De Regalo (al Por Menor)",
    "sg:phone":"+34 925 22 52 87",
    "sg:postcode":"45002",
    "sg:province":"Toledo",
    "wof:name":"Artesania Trinidad C.b.",
    "wof:placetype":"venue"
},
  "geometry": {"coordinates":[-4.0257301331,39.8571166992],"type":"Point"}
}