{
  "type": "Feature",
  "properties": {
    "addr:full":"Carrer de Riera (de La), 1 Vila-seca Tarragona 43480",
    "addr:housenumber":"1",
    "addr:postcode":"43480",
    "addr:street":"Carrer De Riera De La",
    "iso:country":"ES",
    "sg:address":"Carrer de Riera (de La), 1",
    "sg:city":"Vila-seca",
    "sg:orig_category":"Cajas De Ahorro",
    "sg:phone":"+34 977 39 33 30",
    "sg:postcode":"43480",
    "sg:province":"Tarragona",
    "wof:name":"Caja De Ahorros Del Mediterraneo",
    "wof:placetype":"venue"
},
  "geometry": {"coordinates":[1.1464799643,41.108631134],"type":"Point"}
}