{
  "type": "Feature",
  "properties": {
    "iso:country":"ES",
    "sg:address":"Pase Acacias, 30",
    "sg:city":"Madrid",
    "sg:orig_category":"Ense\u00d1ante, Direcci\u00d3n",
    "sg:phone":"+34 913 64 25 04",
    "sg:postcode":"28005",
    "sg:province":"Madrid",
    "wof:name":"Flores Lecha Ruben",
    "wof:placetype":"venue"
},
  "geometry": {"coordinates":[-3.7095899582,40.4032211304],"type":"Point"}
}