{
  "type": "Feature",
  "properties": {
    "addr:full":"Avda Castilla, 164 Gangosa Almer\u00eda 04738",
    "addr:housenumber":"164",
    "addr:postcode":"04738",
    "addr:street":"Avda Castilla;Almeri\u0301A",
    "iso:country":"ES",
    "sg:address":"Avda Castilla, 164",
    "sg:city":"Gangosa",
    "sg:orig_category":"Asesor\u00cda Fiscal Y Jur\u00cddica",
    "sg:phone":"+34 950 55 40 66",
    "sg:postcode":"04738",
    "sg:province":"Almer\u00eda",
    "wof:name":"Iniesta Asesores Empresariales S.l.",
    "wof:placetype":"venue"
},
  "geometry": {"coordinates":[-2.6213440895,36.8050079346],"type":"Point"}
}