{
  "type": "Feature",
  "properties": {
    "iso:country":"ES",
    "sg:address":"Calle de Trigales (los), 11",
    "sg:city":"Palencia",
    "sg:orig_category":"Carnicer\u00cdas, Carnicer\u00cdas",
    "sg:phone":"+34 979 74 85 80",
    "sg:postcode":"34003",
    "sg:province":"Palencia",
    "wof:name":"Celis Gala Vicente De",
    "wof:placetype":"venue"
},
  "geometry": {"coordinates":[-4.5264930725,42.0149116516],"type":"Point"}
}