{
  "type": "Feature",
  "properties": {
    "iso:country":"ES",
    "sg:address":"Avda Mijas, 2",
    "sg:city":"Fuengirola",
    "sg:orig_category":"Muebles, Minoristas",
    "sg:phone":"+34 952 58 45 55",
    "sg:postcode":"29640",
    "sg:province":"M\u00e1laga",
    "wof:name":"Martin George Alejandro",
    "wof:placetype":"venue"
},
  "geometry": {"coordinates":[-4.6300301552,36.543762207],"type":"Point"}
}