{
  "type": "Feature",
  "properties": {
    "iso:country":"ES",
    "sg:address":"Calle de Higuerica, S/n",
    "sg:city":"San Cristobal",
    "sg:orig_category":"Electrodom\u00c9sticos (al Por Menor)",
    "sg:phone":"+34 968 40 67 57",
    "sg:postcode":"30800",
    "sg:province":"Murcia",
    "wof:name":"Sanchez Ruiz Daniel",
    "wof:placetype":"venue"
},
  "geometry": {"coordinates":[-1.6905640364,37.680557251],"type":"Point"}
}