{
  "type": "Feature",
  "properties": {
    "iso:country":"ES",
    "sg:address":"Ctra. Caceres, Km. 0030,0",
    "sg:city":"Plasenzuela",
    "sg:orig_category":"Cr\u00cda De Animales",
    "sg:phone":"+34 927 49 00 75",
    "sg:postcode":"10271",
    "sg:province":"C\u00e1ceres",
    "wof:name":"Francisco Santos Robledo Y Otros Cdad",
    "wof:placetype":"venue"
},
  "geometry": {"coordinates":[-6.0506291389,39.3819198608],"type":"Point"}
}