{
  "type": "Feature",
  "properties": {
    "addr:full":"Afores, S/n Castelldefels Barcelona 08860",
    "addr:housenumber":"s",
    "addr:postcode":"08860",
    "addr:street":"Afores;/ N",
    "iso:country":"ES",
    "sg:address":"Afores, S/n",
    "sg:city":"Castelldefels",
    "sg:orig_category":"Reposter\u00cdas",
    "sg:phone":"+34 936 36 49 34",
    "sg:postcode":"08860",
    "sg:province":"Barcelona",
    "wof:name":"Gavafels S.l.",
    "wof:placetype":"venue"
},
  "geometry": {"coordinates":[1.9278570414,41.2629699707],"type":"Point"}
}