{
  "type": "Feature",
  "properties": {
    "addr:full":"Paraje San Bartolome, S/n Arenas San Pedro \u00c1vila 05400",
    "addr:housenumber":"s / n",
    "addr:postcode":"05400",
    "addr:street":"Paraje San Bartolome;A\u0301Vila",
    "iso:country":"ES",
    "sg:address":"Paraje San Bartolome, S/n",
    "sg:city":"Arenas San Pedro",
    "sg:orig_category":"Empresas De Carpinter\u00cda De Madera",
    "sg:phone":"+34 920 37 11 23",
    "sg:postcode":"05400",
    "sg:province":"\u00c1vila",
    "wof:name":"Bermudez Betrian Emilio Antonio",
    "wof:placetype":"venue"
},
  "geometry": {"coordinates":[-5.0866141319,40.210231781],"type":"Point"}
}