{
  "type": "Feature",
  "properties": {
    "addr:full":"Calle de Fuente, 1 Zarza Badajoz 06830",
    "addr:housenumber":"1",
    "addr:postcode":"06830",
    "addr:street":"Calle De Fuente",
    "iso:country":"ES",
    "sg:address":"Calle de Fuente, 1",
    "sg:city":"Zarza",
    "sg:orig_category":"Cajas De Ahorro",
    "sg:phone":"+34 924 36 61 50",
    "sg:postcode":"06830",
    "sg:province":"Badajoz",
    "sg:website":"www.cajabadajoz.es",
    "wof:name":"Caja De Badajoz",
    "wof:placetype":"venue"
},
  "geometry": {"coordinates":[-6.2214231491,38.8190231323],"type":"Point"}
}