{
  "type": "Feature",
  "properties": {
    "addr:full":"Carrer de Beat Oriol, 1 Mas Rampinyo Barcelona 08110",
    "addr:housenumber":"1",
    "addr:postcode":"08110",
    "addr:street":"Carrer De;Oriol",
    "iso:country":"ES",
    "sg:address":"Carrer de Beat Oriol, 1",
    "sg:city":"Mas Rampinyo",
    "sg:orig_category":"Construcciones Met\u00c1licas",
    "sg:phone":"+34 933 11 25 61",
    "sg:postcode":"08110",
    "sg:province":"Barcelona",
    "wof:name":"Campos Navarro Jose",
    "wof:placetype":"venue"
},
  "geometry": {"coordinates":[2.1811699867,41.491191864],"type":"Point"}
}