{
  "type": "Feature",
  "properties": {
    "addr:full":"Nafarroa Etorbidea, 27 Beasain Guip\u00f9zcoa 20200",
    "addr:housenumber":"27",
    "addr:postcode":"20200",
    "addr:street":"Nafarroa Etorbidea;Guipu\u0300Zcoa",
    "iso:country":"ES",
    "sg:address":"Nafarroa Etorbidea, 27",
    "sg:city":"Beasain",
    "sg:orig_category":"Arquitectos",
    "sg:phone":"+34 943 88 77 91",
    "sg:postcode":"20200",
    "sg:province":"Guip\u00f9zcoa",
    "wof:name":"Oyarbide Antia Andres",
    "wof:placetype":"venue"
},
  "geometry": {"coordinates":[-2.2038519382,43.0467948914],"type":"Point"}
}