{
  "type": "Feature",
  "properties": {
    "addr:full":"Calle de Rios, 69 Paredilla I Las Palmas 35110",
    "addr:housenumber":"69",
    "addr:postcode":"35110",
    "addr:street":"Calle De Rios",
    "iso:country":"ES",
    "sg:address":"Calle de Rios, 69",
    "sg:city":"Paredilla I",
    "sg:orig_category":"Frutas, Legumbres Frescas Y Tempranas (al Por Menor)",
    "sg:phone":"+34 928 75 46 55",
    "sg:postcode":"35110",
    "sg:province":"Las Palmas",
    "wof:name":"Gonzalez Gonzalez Francisco",
    "wof:placetype":"venue"
},
  "geometry": {"coordinates":[-15.4485340118,27.8392906189],"type":"Point"}
}