{
  "type": "Feature",
  "properties": {
    "iso:country":"ES",
    "sg:address":"Crta Malaga-campillos, Km. 0052,3",
    "sg:city":"Cartama",
    "sg:orig_category":"Promotores Constructores",
    "sg:phone":"+34 952 48 45 58",
    "sg:postcode":"29570",
    "sg:province":"M\u00e1laga",
    "sg:website":"www.azvi.es",
    "wof:name":"Azvi S.a.",
    "wof:placetype":"venue"
},
  "geometry": {"coordinates":[-4.634704113,36.7672958374],"type":"Point"}
}