{
  "type": "Feature",
  "properties": {
    "iso:country":"ES",
    "sg:address":"Carr Muntanyeta, 21",
    "sg:city":"Sueca",
    "sg:orig_category":"Comercio, Reparaci\u00d3n De Motocicletas, Bicicletas Y Piezas Sueltas",
    "sg:phone":"+34 961 70 03 68",
    "sg:postcode":"46410",
    "sg:province":"Valencia",
    "wof:name":"Heras Sanchez Gerardo",
    "wof:placetype":"venue"
},
  "geometry": {"coordinates":[-0.3122079968,39.2076263428],"type":"Point"}
}