{
  "type": "Feature",
  "properties": {
    "addr:full":"Avgd Vicent Mortes Alfonso, 19 Paterna Valencia 46980",
    "addr:housenumber":"19",
    "addr:postcode":"46980",
    "addr:street":"Alfonso",
    "iso:country":"ES",
    "sg:address":"Avgd Vicent Mortes Alfonso, 19",
    "sg:city":"Paterna",
    "sg:orig_category":"Cajas De Ahorro",
    "sg:phone":"+34 961 38 61 61",
    "sg:postcode":"46980",
    "sg:province":"Valencia",
    "sg:website":"www.ibercaja.es",
    "wof:name":"Caja De Ahorros Y Monte De Piedad De Zaragoza Aragon Y Rioja",
    "wof:placetype":"venue"
},
  "geometry": {"coordinates":[-0.4465520084,39.5054244995],"type":"Point"}
}