{
  "type": "Feature",
  "properties": {
    "iso:country":"ES",
    "sg:address":"Barr Gerra (la), 146",
    "sg:city":"Villapresente",
    "sg:classifiers":[
        {
            "category":"Taxi",
            "type":"Transportation"
        }
    ],
    "sg:phone":"+34 942 82 01 26",
    "sg:postcode":"39539",
    "sg:province":"Cantabria",
    "wof:name":"Salgado Gonzalez Rodrigo",
    "wof:placetype":"venue"
},
  "geometry": {"coordinates":[-4.1253538132,43.3653182983],"type":"Point"}
}