{
  "type": "Feature",
  "properties": {
    "iso:country":"ES",
    "sg:address":"Calle de Luis Oliag, 49",
    "sg:city":"Valencia",
    "sg:orig_category":"Agencias De Viajes",
    "sg:phone":"+34 963 16 39 83",
    "sg:postcode":"46006",
    "sg:province":"Valencia",
    "wof:name":"Vacaciones Sierra De Irta Alcocebre 2007",
    "wof:placetype":"venue"
},
  "geometry": {"coordinates":[-0.3640240133,39.4605941772],"type":"Point"}
}