{
  "type": "Feature",
  "properties": {
    "iso:country":"ES",
    "sg:address":"Carrer de Balmes, 122",
    "sg:city":"Barcelona",
    "sg:classifiers":[
        {
            "category":"Retail",
            "subcategory":"Event Space",
            "type":"Services"
        }
    ],
    "sg:phone":"+34 934 88 18 85",
    "sg:postcode":"08008",
    "sg:province":"Barcelona",
    "sg:tags":[
        "planchas",
        "surf",
        "alquiler",
        "de",
        "vela",
        "kayak",
        "barcos",
        "canoes",
        "y"
    ],
    "wof:name":"Medina Galvez Raul",
    "wof:placetype":"venue"
},
  "geometry": {"coordinates":[2.1579389572,41.393032074],"type":"Point"}
}