{
  "type": "Feature",
  "properties": {
    "iso:country":"ES",
    "sg:address":"Calle de Tomas Nougues, 1",
    "sg:city":"Teruel",
    "sg:orig_category":"Centros Empresariales",
    "sg:phone":"+34 978 61 05 75",
    "sg:postcode":"44001",
    "sg:province":"Teruel",
    "wof:name":"Asociacion Prov. De Promotores Y Constructores De Edificios De Teruel",
    "wof:placetype":"venue"
},
  "geometry": {"coordinates":[-1.1929113865,40.3231506348],"type":"Point"}
}