{
  "type": "Feature",
  "properties": {
    "iso:country":"ES",
    "sg:address":"Poli Cantabria, S/n",
    "sg:city":"Logro\u00f1o",
    "sg:orig_category":"Fabricaci\u00d3n, Instalaci\u00d3n De Armarios",
    "sg:phone":"+34 941 24 47 77",
    "sg:postcode":"26006",
    "sg:province":"La Rioja",
    "sg:website":"www.carpinteriapaco.com",
    "wof:name":"Carpinteria Paco S.l.",
    "wof:placetype":"venue"
},
  "geometry": {"coordinates":[-2.4036989212,42.46043396],"type":"Point"}
}