{
  "type": "Feature",
  "properties": {
    "iso:country":"ES",
    "sg:address":"Calle de Antonio Machado, 30",
    "sg:city":"Chipiona",
    "sg:orig_category":"Negocio De Materiales De Construcci\u00d3n",
    "sg:phone":"+34 956 37 00 50",
    "sg:postcode":"11550",
    "sg:province":"C\u00e1diz",
    "wof:name":"Porras Moreno Jose",
    "wof:placetype":"venue"
},
  "geometry": {"coordinates":[-6.4305005074,36.7373352051],"type":"Point"}
}