{
  "type": "Feature",
  "properties": {
    "addr:full":"Calle de Francisco Pradilla, 2 Villanueva Gallego Zaragoza 50830",
    "addr:housenumber":"2",
    "addr:postcode":"50830",
    "addr:street":"Calle De Francisco Pradilla",
    "iso:country":"ES",
    "sg:address":"Calle de Francisco Pradilla, 2",
    "sg:city":"Villanueva Gallego",
    "sg:orig_category":"Garajes De Veh\u00cdculos",
    "sg:phone":"+34 976 18 62 45",
    "sg:postcode":"50830",
    "sg:province":"Zaragoza",
    "wof:name":"Manero-varela S.l.",
    "wof:placetype":"venue"
},
  "geometry": {"coordinates":[-0.8215219975,41.7683296204],"type":"Point"}
}