{
  "type": "Feature",
  "properties": {
    "iso:country":"ES",
    "sg:address":"Calle de Do\u00d1a Berenguela, 20",
    "sg:city":"Cordoba",
    "sg:orig_category":"Empresas De Impermeabilizaci\u00d3n",
    "sg:phone":"+34 957 27 38 44",
    "sg:postcode":"14011",
    "sg:province":"C\u00f3rdoba",
    "wof:name":"Sierra Huertas Carlos",
    "wof:placetype":"venue"
},
  "geometry": {"coordinates":[-4.7877421379,37.8909568787],"type":"Point"}
}