{
  "type": "Feature",
  "properties": {
    "addr:full":"Calle de Arturo Soria, 187 Madrid Madrid 28043",
    "addr:housenumber":"187",
    "addr:postcode":"28043",
    "addr:street":"Calle De Arturo Soria",
    "iso:country":"ES",
    "sg:address":"Calle de Arturo Soria, 187",
    "sg:city":"Madrid",
    "sg:orig_category":"Electricidad, Electr\u00d3nica: Material Y Suministros (al Por Mayor)",
    "sg:phone":"+34 915 10 20 61",
    "sg:postcode":"28043",
    "sg:province":"Madrid",
    "sg:website":"www.lenze.es",
    "wof:name":"Lenze Transmisiones S.a.",
    "wof:placetype":"venue"
},
  "geometry": {"coordinates":[-3.6589934826,40.4583473206],"type":"Point"}
}