{
  "type": "Feature",
  "properties": {
    "iso:country":"ES",
    "sg:address":"Avgd Raval De Valencia, 19",
    "sg:city":"Coves Vinroma",
    "sg:orig_category":"Centros De Coordinaci\u00d3n",
    "sg:phone":"+34 964 42 62 02",
    "sg:postcode":"12185",
    "sg:province":"Castell\u00f3n",
    "wof:name":"Villaplana Esteller Maria Libertad",
    "wof:placetype":"venue"
},
  "geometry": {"coordinates":[0.1131929979,40.3063316345],"type":"Point"}
}