{
  "type": "Feature",
  "properties": {
    "addr:full":"Carr Arminyana I Canut, D', 8 Carcaixent Valencia 46740",
    "addr:housenumber":"8",
    "addr:postcode":"46740",
    "addr:street":"Carr Arminyana;Canut;'",
    "iso:country":"ES",
    "sg:address":"Carr Arminyana I Canut, D', 8",
    "sg:city":"Carcaixent",
    "sg:orig_category":"Piedra Natural",
    "sg:phone":"+34 962 46 15 03",
    "sg:postcode":"46740",
    "sg:province":"Valencia",
    "wof:name":"Graniprens Carcaixent S.l.",
    "wof:placetype":"venue"
},
  "geometry": {"coordinates":[-0.4219444096,39.1015625],"type":"Point"}
}