{
  "type": "Feature",
  "properties": {
    "iso:country":"ES",
    "sg:address":"Avda Francia (de), 2",
    "sg:city":"Playa Del Ingles",
    "sg:orig_category":"Supermercados Y Hipermercados",
    "sg:phone":"+34 928 77 23 48",
    "sg:postcode":"35100",
    "sg:province":"Las Palmas",
    "wof:name":"Hermanos Daswani S. L.",
    "wof:placetype":"venue"
},
  "geometry": {"coordinates":[-15.5752439499,27.7515201569],"type":"Point"}
}