{
  "type": "Feature",
  "properties": {
    "addr:full":"Calle de La Florida, 60 Vitoria-gasteiz \u00c1lava 01005",
    "addr:housenumber":"60",
    "addr:postcode":"01005",
    "addr:street":"Calle De La Florida",
    "iso:country":"ES",
    "sg:address":"Calle de La Florida, 60",
    "sg:city":"Vitoria-gasteiz",
    "sg:orig_category":"Procuradores",
    "sg:phone":"+34 945 28 12 37",
    "sg:postcode":"01005",
    "sg:province":"\u00c1lava",
    "wof:name":"Echavarri Martinez Miguel Angel",
    "wof:placetype":"venue"
},
  "geometry": {"coordinates":[-2.6701390743,42.8428001404],"type":"Point"}
}