{
  "type": "Feature",
  "properties": {
    "addr:full":"Calle de Hilados, 26 Torrejon Ardoz Madrid 28850",
    "addr:housenumber":"26",
    "addr:postcode":"28850",
    "addr:street":"Calle De Hilados",
    "iso:country":"ES",
    "sg:address":"Calle de Hilados, 26",
    "sg:city":"Torrejon Ardoz",
    "sg:orig_category":"Comerciantes Al Por Mayor De Vinos, Licores Y Alcoholes",
    "sg:phone":"+34 916 56 10 44",
    "sg:postcode":"28850",
    "sg:province":"Madrid",
    "wof:name":"Ya\u00f1ez De Antonio Jose Maria",
    "wof:placetype":"venue"
},
  "geometry": {"coordinates":[-3.4596459866,40.4444656372],"type":"Point"}
}