{
  "type": "Feature",
  "properties": {
    "iso:country":"ES",
    "sg:address":"Calle de Alcalde Alfredo De Castro (del), 31",
    "sg:city":"Leganes",
    "sg:orig_category":"Contenedores (mercanc\u00cdas)",
    "sg:phone":"+34 916 48 51 79",
    "sg:postcode":"28914",
    "sg:province":"Madrid",
    "wof:name":"Pascual Cotarelo Jose Benito",
    "wof:placetype":"venue"
},
  "geometry": {"coordinates":[-3.7886073589,40.3178215027],"type":"Point"}
}