{
  "type": "Feature",
  "properties": {
    "addr:full":"Calle de Isaac Peral, 32 Chipiona C\u00e1diz 11550",
    "addr:housenumber":"32",
    "addr:postcode":"11550",
    "addr:street":"Calle De Isaac Peral",
    "iso:country":"ES",
    "sg:address":"Calle de Isaac Peral, 32",
    "sg:city":"Chipiona",
    "sg:orig_category":"Confecci\u00d3n (fabricaci\u00d3n, Al Por Mayor)",
    "sg:phone":"+34 956 37 50 50",
    "sg:postcode":"11550",
    "sg:province":"C\u00e1diz",
    "wof:name":"El Barato C.b.",
    "wof:placetype":"venue"
},
  "geometry": {"coordinates":[-6.4359607697,36.7397651672],"type":"Point"}
}