{
  "type": "Feature",
  "properties": {
    "iso:country":"ES",
    "sg:address":"El Cid, 10",
    "sg:city":"P.i. Masia Del Juez",
    "sg:orig_category":"Materias Pl\u00c1sticas: Art\u00cdculos Para La Industria",
    "sg:phone":"+34 961 56 74 55",
    "sg:postcode":"46900",
    "sg:province":"Valencia",
    "wof:name":"Metaval Abella S.l.",
    "wof:placetype":"venue"
},
  "geometry": {"coordinates":[-0.4623290002,39.441619873],"type":"Point"}
}