{
  "type": "Feature",
  "properties": {
    "addr:full":"Carrer de Industria, 6 Santa Perpetua De Mogoda Barcelona 08130",
    "addr:housenumber":"6",
    "addr:postcode":"08130",
    "addr:street":"Carrer De Industria",
    "iso:country":"ES",
    "sg:address":"Carrer de Industria, 6",
    "sg:city":"Santa Perpetua De Mogoda",
    "sg:orig_category":"Aparatos, Material Y Suministros Para Laboratorios",
    "sg:phone":"+34 935 60 72 74",
    "sg:postcode":"08130",
    "sg:province":"Barcelona",
    "wof:name":"Cris-mat S.a.",
    "wof:placetype":"venue"
},
  "geometry": {"coordinates":[2.1806790829,41.5387077332],"type":"Point"}
}