{
  "type": "Feature",
  "properties": {
    "addr:full":"C/ Salut (de La), 25 Ripollet Barcelona 08291",
    "addr:housenumber":"25",
    "addr:postcode":"08291",
    "addr:street":"C / Salut De La",
    "iso:country":"ES",
    "sg:address":"C/ Salut (de La), 25",
    "sg:city":"Ripollet",
    "sg:orig_category":"Electricidad, Electr\u00d3nica: Suministros (al Por Menor)",
    "sg:phone":"+34 935 80 59 79",
    "sg:postcode":"08291",
    "sg:province":"Barcelona",
    "wof:name":"Macec S.l.",
    "wof:placetype":"venue"
},
  "geometry": {"coordinates":[2.1544120312,41.4979171753],"type":"Point"}
}