{
  "type": "Feature",
  "properties": {
    "addr:full":"Els Clots, S/n Sollana Valencia 46430",
    "addr:housenumber":"s / n",
    "addr:postcode":"46430",
    "iso:country":"ES",
    "sg:address":"Els Clots, S/n",
    "sg:city":"Sollana",
    "sg:orig_category":"Negocio De Madera",
    "sg:phone":"+34 961 74 11 40",
    "sg:postcode":"46430",
    "sg:province":"Valencia",
    "sg:website":"www.remagsl.com",
    "wof:name":"Reciclajes De Maderas Aleixandre Galiana S.l.",
    "wof:placetype":"venue"
},
  "geometry": {"coordinates":[-0.3803690076,39.2788047791],"type":"Point"}
}