{
  "type": "Feature",
  "properties": {
    "addr:full":"Avda Pontevedra, 51 Estrada Pontevedra 36680",
    "addr:housenumber":"51",
    "addr:postcode":"36680",
    "addr:street":"Avda Pontevedra;Estrada Pontevedra",
    "iso:country":"ES",
    "sg:address":"Avda Pontevedra, 51",
    "sg:city":"Estrada",
    "sg:orig_category":"Comercio De Piezas De Recambio Y De Accesorios De Veh\u00cdculos, Veh\u00cdculos Industriales",
    "sg:phone":"+34 986 57 51 27",
    "sg:postcode":"36680",
    "sg:province":"Pontevedra",
    "wof:name":"Demarka Recambios S.l.",
    "wof:placetype":"venue"
},
  "geometry": {"coordinates":[-8.4986162186,42.6876068115],"type":"Point"}
}