{
  "type": "Feature",
  "properties": {
    "addr:full":"Carr Argiles, 1 Santa Coloma De Farners Girona 17430",
    "addr:housenumber":"1",
    "addr:postcode":"17430",
    "addr:street":"Carr Argiles",
    "iso:country":"ES",
    "sg:address":"Carr Argiles, 1",
    "sg:city":"Santa Coloma De Farners",
    "sg:orig_category":"Perfumer\u00cda, Art\u00cdculos De Ba\u00d1o (fabricaci\u00d3n, Al Por Mayor)",
    "sg:phone":"+34 972 84 04 40",
    "sg:postcode":"17430",
    "sg:province":"Girona",
    "wof:name":"Gascons Antonia Montserrat",
    "wof:placetype":"venue"
},
  "geometry": {"coordinates":[2.6612110138,41.8654937744],"type":"Point"}
}