{
  "type": "Feature",
  "properties": {
    "iso:country":"ES",
    "sg:address":"Avgd Jaume I, 4",
    "sg:city":"Olleria",
    "sg:orig_category":"Caf\u00c9s, Bares, Cervecer\u00cdas",
    "sg:phone":"+34 962 20 13 82",
    "sg:postcode":"46850",
    "sg:province":"Valencia",
    "wof:name":"Vidal Reig Vicente",
    "wof:placetype":"venue"
},
  "geometry": {"coordinates":[-0.5478360057,38.9096603394],"type":"Point"}
}