{
  "type": "Feature",
  "properties": {
    "addr:full":"Pl Angel, 6 Sabadell Barcelona 08202",
    "addr:housenumber":"6",
    "addr:postcode":"08202",
    "addr:street":"Pl Angel",
    "iso:country":"ES",
    "sg:address":"Pl Angel, 6",
    "sg:city":"Sabadell",
    "sg:orig_category":"Ropa Para Ni\u00d1os (al Por Menor)",
    "sg:phone":"+34 937 25 89 41",
    "sg:postcode":"08202",
    "sg:province":"Barcelona",
    "wof:name":"Fras Dosmil S.l.",
    "wof:placetype":"venue"
},
  "geometry": {"coordinates":[2.1086380482,41.5492515564],"type":"Point"}
}