{
  "type": "Feature",
  "properties": {
    "iso:country":"ES",
    "sg:address":"Avda Libertad, 20",
    "sg:city":"Puebla Almoradiel",
    "sg:orig_category":"Electricidad: Instaladores",
    "sg:phone":"+34 925 17 84 05",
    "sg:postcode":"45840",
    "sg:province":"Toledo",
    "wof:name":"Heras Mu\u00f1oz Jose Luis",
    "wof:placetype":"venue"
},
  "geometry": {"coordinates":[-3.1204380989,39.5981712341],"type":"Point"}
}