{
  "type": "Feature",
  "properties": {
    "addr:full":"Calle de Zoila, 11 Gijon Asturias 33209",
    "addr:housenumber":"11",
    "addr:postcode":"33209",
    "addr:street":"Calle De Zoila",
    "iso:country":"ES",
    "sg:address":"Calle de Zoila, 11",
    "sg:city":"Gijon",
    "sg:orig_category":"Agencias Y Agentes Comerciales, Representantes",
    "sg:phone":"+34 985 38 60 77",
    "sg:postcode":"33209",
    "sg:province":"Asturias",
    "wof:name":"Redondo Ordo\u00f1ez Ismael",
    "wof:placetype":"venue"
},
  "geometry": {"coordinates":[-5.6661410332,43.5276947021],"type":"Point"}
}