{
  "type": "Feature",
  "properties": {
    "addr:full":"Avda Malecon, 24 Santa Uxia De Ribeira La Coru\u00f1a 15960",
    "addr:housenumber":"24",
    "addr:postcode":"15960",
    "addr:street":"Avda Malecon;Corun\u0303A",
    "iso:country":"ES",
    "sg:address":"Avda Malecon, 24",
    "sg:city":"Santa Uxia De Ribeira",
    "sg:orig_category":"Bancos",
    "sg:phone":"+34 981 83 56 72",
    "sg:postcode":"15960",
    "sg:province":"La Coru\u00f1a",
    "wof:name":"Banco Etcheverria",
    "wof:placetype":"venue"
},
  "geometry": {"coordinates":[-8.9903993607,42.5550613403],"type":"Point"}
}