{
  "type": "Feature",
  "properties": {
    "iso:country":"ES",
    "sg:address":"Calle de Escotilla, S/n",
    "sg:city":"Arrecife",
    "sg:orig_category":"Alimentaci\u00d3n General (al Por Mayor)",
    "sg:phone":"+34 928 80 03 08",
    "sg:postcode":"35500",
    "sg:province":"Las Palmas",
    "sg:website":"www.torres.es",
    "wof:name":"Miguel Torres Canarias S.a.",
    "wof:placetype":"venue"
},
  "geometry": {"coordinates":[-13.541633606,28.9683856964],"type":"Point"}
}