{
  "type": "Feature",
  "properties": {
    "iso:country":"ES",
    "sg:address":"Sanduzelai, 10",
    "sg:city":"Iru\u00f1a",
    "sg:orig_category":"Automatizaci\u00d3n De Procesos Industriales Y De Edificaci\u00d3n (estudios, Instalaci\u00d3n)",
    "sg:phone":"+34 948 14 55 38",
    "sg:postcode":"31012",
    "sg:province":"Navarra",
    "wof:name":"Sarasate Sarasate Javier Ignacio",
    "wof:placetype":"venue"
},
  "geometry": {"coordinates":[-1.6654150486,42.8205070496],"type":"Point"}
}