{
  "type": "Feature",
  "properties": {
    "iso:country":"ES",
    "sg:address":"Calle de Burgos, 3",
    "sg:city":"Valencia",
    "sg:orig_category":"Bisuter\u00cda, Joyer\u00cda, Relojer\u00cda (al Por Menor)",
    "sg:phone":"+34 963 70 22 08",
    "sg:postcode":"46018",
    "sg:province":"Valencia",
    "wof:name":"Frances Llin Rafael",
    "wof:placetype":"venue"
},
  "geometry": {"coordinates":[-0.3995693028,39.4691467285],"type":"Point"}
}