{
  "type": "Feature",
  "properties": {
    "addr:full":"Calle de Reina, 1 Zamora Zamora 49004",
    "addr:housenumber":"1",
    "addr:postcode":"49004",
    "addr:street":"Calle De Reina",
    "iso:country":"ES",
    "sg:address":"Calle de Reina, 1",
    "sg:city":"Zamora",
    "sg:orig_category":"Albergues",
    "sg:phone":"+34 980 53 39 39",
    "sg:postcode":"49004",
    "sg:province":"Zamora",
    "wof:name":"Villar Anton Micaela",
    "wof:placetype":"venue"
},
  "geometry": {"coordinates":[-5.7477488518,41.5035514832],"type":"Point"}
}