{
  "type": "Feature",
  "properties": {
    "iso:country":"ES",
    "sg:address":"Avda Libertad (de La), 43",
    "sg:city":"Rus",
    "sg:orig_category":"Fabricaci\u00d3n De Su\u00c9ters Y Chalecos De Punto",
    "sg:phone":"+34 953 79 95 93",
    "sg:postcode":"23430",
    "sg:province":"Ja\u00e9n",
    "wof:name":"Ruiz Murillo Petra",
    "wof:placetype":"venue"
},
  "geometry": {"coordinates":[-3.4606699944,38.0496749878],"type":"Point"}
}