{
  "type": "Feature",
  "properties": {
    "iso:country":"ES",
    "sg:address":"Calle de Ingeniero Salinas, 41",
    "sg:city":"Palmas De Gran Canaria",
    "sg:orig_category":"Promotores Constructores",
    "sg:phone":"+34 928 23 17 34",
    "sg:postcode":"35006",
    "sg:province":"Las Palmas",
    "wof:name":"Promociones Y Construcciones Dominguez Rodriguez S.l.",
    "wof:placetype":"venue"
},
  "geometry": {"coordinates":[-15.4316167831,28.1300506592],"type":"Point"}
}