{
  "type": "Feature",
  "properties": {
    "iso:country":"ES",
    "sg:address":"Praz Maior, 25",
    "sg:city":"Ponteareas",
    "sg:orig_category":"Farmacias",
    "sg:phone":"+34 986 64 00 23",
    "sg:postcode":"36860",
    "sg:province":"Pontevedra",
    "wof:name":"Farmacia Abacuc Pe\u00f1a Y Santiago Pe\u00f1a C.b.",
    "wof:placetype":"venue"
},
  "geometry": {"coordinates":[-8.5163888931,42.1783599854],"type":"Point"}
}