{
  "type": "Feature",
  "properties": {
    "iso:country":"ES",
    "sg:address":"Pase Beltzeta, 20",
    "sg:city":"Cizur Menor",
    "sg:orig_category":"Venta, Instalaci\u00d3n De Calefacci\u00d3n",
    "sg:phone":"+34 948 28 01 32",
    "sg:postcode":"31190",
    "sg:province":"Navarra",
    "wof:name":"Cuadrado Jubia Diego",
    "wof:placetype":"venue"
},
  "geometry": {"coordinates":[-1.6754239798,42.7882118225],"type":"Point"}
}