{
  "type": "Feature",
  "properties": {
    "iso:country":"ES",
    "sg:address":"Plaz Coca De La Pi\u00d1era, S/n",
    "sg:city":"Jaen",
    "sg:orig_category":"Centros Empresariales",
    "sg:phone":"+34 953 25 73 89",
    "sg:postcode":"23001",
    "sg:province":"Ja\u00e9n",
    "wof:name":"Unibus Jaen",
    "wof:placetype":"venue"
},
  "geometry": {"coordinates":[-3.7874689102,37.7708816528],"type":"Point"}
}