{
  "type": "Feature",
  "properties": {
    "iso:country":"ES",
    "sg:address":"Calle de Molino, S/n",
    "sg:city":"Iscar",
    "sg:orig_category":"Suministros Para Carrocer\u00cdas",
    "sg:phone":"+34 983 61 21 99",
    "sg:postcode":"47420",
    "sg:province":"Valladolid",
    "wof:name":"Calvo Morin Gregorio",
    "wof:placetype":"venue"
},
  "geometry": {"coordinates":[-4.528886795,41.3652381897],"type":"Point"}
}