{
  "type": "Feature",
  "properties": {
    "addr:full":"Calle de Triunfo, 1 Donostia-san Sebastian Guip\u00f9zcoa 20007",
    "addr:housenumber":"1",
    "addr:postcode":"20007",
    "addr:street":"Calle De Triunfo",
    "iso:country":"ES",
    "sg:address":"Calle de Triunfo, 1",
    "sg:city":"Donostia-san Sebastian",
    "sg:orig_category":"M\u00c9dicos: Pediatr\u00cda. Enfermedades De Los Ni\u00d1os",
    "sg:phone":"+34 943 45 08 44",
    "sg:postcode":"20007",
    "sg:province":"Guip\u00f9zcoa",
    "wof:name":"Zubillaga Huici Pablo",
    "wof:placetype":"venue"
},
  "geometry": {"coordinates":[-1.9855544567,43.3165740967],"type":"Point"}
}