{
  "type": "Feature",
  "properties": {
    "iso:country":"ES",
    "sg:address":"Calle de Fonti\u00d1a, 9",
    "sg:city":"Guarda",
    "sg:classifiers":[
        {
            "category":"Recreation",
            "type":"Entertainment"
        }
    ],
    "sg:phone":"+34 986 61 01 78",
    "sg:postcode":"36780",
    "sg:province":"Pontevedra",
    "sg:tags":[
        "caza",
        "pr\u00c1ctica",
        "la",
        "de",
        "pesca",
        "y"
    ],
    "wof:name":"Fernando Perez Y Generoso Castro Cb",
    "wof:placetype":"venue"
},
  "geometry": {"coordinates":[-8.8780832291,41.9026679993],"type":"Point"}
}