{
  "type": "Feature",
  "properties": {
    "addr:full":"Carrer de Garcilaso, 170 Barcelona Barcelona 08027",
    "addr:housenumber":"170",
    "addr:postcode":"08027",
    "addr:street":"Carrer De Garcilaso",
    "iso:country":"ES",
    "sg:address":"Carrer de Garcilaso, 170",
    "sg:city":"Barcelona",
    "sg:orig_category":"Arquitectos",
    "sg:phone":"+34 933 52 75 53",
    "sg:postcode":"08027",
    "sg:province":"Barcelona",
    "wof:name":"Frau Subirats Juan",
    "wof:placetype":"venue"
},
  "geometry": {"coordinates":[2.1810669899,41.4236030579],"type":"Point"}
}