{
  "type": "Feature",
  "properties": {
    "addr:full":"Ctra. Madremanya, S/n S. Marti Vell Girona 17462",
    "addr:housenumber":"s",
    "addr:postcode":"17462",
    "addr:street":"Ctra. Madremanya;/ N S. Marti Vell",
    "iso:country":"ES",
    "sg:address":"Ctra. Madremanya, S/n",
    "sg:city":"S. Marti Vell",
    "sg:orig_category":"Restaurantes",
    "sg:phone":"+34 972 49 02 08",
    "sg:postcode":"17462",
    "sg:province":"Girona",
    "wof:name":"Restaurant Sant Marti S.l.",
    "wof:placetype":"venue"
},
  "geometry": {"coordinates":[2.9117949009,42.0443763733],"type":"Point"}
}