{
  "type": "Feature",
  "properties": {
    "addr:full":"Calle de Montoro, S/n Villanueva Cordoba C\u00f3rdoba 14440",
    "addr:postcode":"14440",
    "addr:street":"Calle De Montoro S / N;Cordoba Co\u0301Rdoba",
    "iso:country":"ES",
    "sg:address":"Calle de Montoro, S/n",
    "sg:city":"Villanueva Cordoba",
    "sg:orig_category":"Cr\u00cda De Animales",
    "sg:phone":"+34 957 33 90 18",
    "sg:postcode":"14440",
    "sg:province":"C\u00f3rdoba",
    "wof:name":"Jurado Capitan Miguel",
    "wof:placetype":"venue"
},
  "geometry": {"coordinates":[-4.6272788048,38.3158531189],"type":"Point"}
}