{
  "type": "Feature",
  "properties": {
    "addr:full":"C/ Esteve Vila, 1 Salt Girona 17190",
    "addr:housenumber":"1",
    "addr:postcode":"17190",
    "addr:street":"C / Esteve Vila",
    "iso:country":"ES",
    "sg:address":"C/ Esteve Vila, 1",
    "sg:city":"Salt",
    "sg:orig_category":"Agentes Generales De Seguros",
    "sg:phone":"+34 972 23 13 45",
    "sg:postcode":"17190",
    "sg:province":"Girona",
    "wof:name":"Parramon Burch Montserrat",
    "wof:placetype":"venue"
},
  "geometry": {"coordinates":[2.7847800255,41.9731674194],"type":"Point"}
}