{
  "type": "Feature",
  "properties": {
    "addr:full":"Rua Progreso (do), 37 Lugo Lugo 27001",
    "addr:housenumber":"37",
    "addr:postcode":"27001",
    "addr:street":"Rua Progreso Do",
    "iso:country":"ES",
    "sg:address":"Rua Progreso (do), 37",
    "sg:city":"Lugo",
    "sg:orig_category":"Peluquer\u00cdas, Peluquer\u00cda Mixta",
    "sg:phone":"+34 982 22 82 17",
    "sg:postcode":"27001",
    "sg:province":"Lugo",
    "wof:name":"Due Capelli S.l.",
    "wof:placetype":"venue"
},
  "geometry": {"coordinates":[-7.5556111336,43.0117378235],"type":"Point"}
}