{
  "type": "Feature",
  "properties": {
    "addr:full":"Carrer de Sant Joan D'en Coll, 47 Manresa Barcelona 08243",
    "addr:housenumber":"47",
    "addr:postcode":"08243",
    "addr:street":"Carrer De Sant;D'En Coll",
    "iso:country":"ES",
    "sg:address":"Carrer de Sant Joan D'en Coll, 47",
    "sg:city":"Manresa",
    "sg:orig_category":"Ambulancias",
    "sg:phone":"+34 938 77 46 00",
    "sg:postcode":"08243",
    "sg:province":"Barcelona",
    "sg:website":"www.ambulanciescordecatalunya-es",
    "wof:name":"Ambulancies Cor De Catalunya S.l.",
    "wof:placetype":"venue"
},
  "geometry": {"coordinates":[1.8368713856,41.7315139771],"type":"Point"}
}