{
  "type": "Feature",
  "properties": {
    "addr:full":"Calle de Mamariga, 1 Santurtzi Vizcaya 48980",
    "addr:housenumber":"1",
    "addr:postcode":"48980",
    "addr:street":"Calle De Mamariga",
    "iso:country":"ES",
    "sg:address":"Calle de Mamariga, 1",
    "sg:city":"Santurtzi",
    "sg:orig_category":"Fotograf\u00cda Y Cine: Aparatos, Pel\u00cdculas Y Accesorios (fabricaci\u00d3n, Al Por Mayor)",
    "sg:phone":"+34 944 61 28 21",
    "sg:postcode":"48980",
    "sg:province":"Vizcaya",
    "wof:name":"Bilbao Bilbao Victoriano",
    "wof:placetype":"venue"
},
  "geometry": {"coordinates":[-3.0356869698,43.3303833008],"type":"Point"}
}