{
  "type": "Feature",
  "properties": {
    "iso:country":"ES",
    "sg:address":"Carrer de Camilo Jose Cela, 20",
    "sg:city":"Palma",
    "sg:orig_category":"M\u00c9dicos: An\u00c1lisis Cl\u00cdnicos",
    "sg:phone":"+34 971 45 26 31",
    "sg:postcode":"07014",
    "sg:province":"Islas Baleares",
    "wof:name":"Gestion Hospitalaria Balear S.l.",
    "wof:placetype":"venue"
},
  "geometry": {"coordinates":[2.6247799397,39.5672264099],"type":"Point"}
}