{
  "type": "Feature",
  "properties": {
    "iso:country":"ES",
    "sg:address":"Calle de Portera (la), 10",
    "sg:city":"Mas Matas",
    "sg:orig_category":"Sanatorios M\u00c9dico",
    "sg:phone":"+34 978 84 89 45",
    "sg:postcode":"44564",
    "sg:province":"Teruel",
    "wof:name":"A.p.alca\u00f1iz",
    "wof:placetype":"venue"
},
  "geometry": {"coordinates":[-1.1069096327,40.3441085815],"type":"Point"}
}