{
  "type": "Feature",
  "properties": {
    "addr:full":"Calle de San Fernando, 67 Najera La Rioja 26300",
    "addr:housenumber":"67",
    "addr:postcode":"26300",
    "addr:street":"Calle De San Fernando;Rioja",
    "iso:country":"ES",
    "sg:address":"Calle de San Fernando, 67",
    "sg:city":"Najera",
    "sg:orig_category":"Partidos Pol\u00cdticos",
    "sg:phone":"+34 941 36 01 92",
    "sg:postcode":"26300",
    "sg:province":"La Rioja",
    "wof:name":"Partido Riojano",
    "wof:placetype":"venue"
},
  "geometry": {"coordinates":[-2.7293291092,42.4176826477],"type":"Point"}
}