{
  "type": "Feature",
  "properties": {
    "iso:country":"ES",
    "sg:address":"Calle de Lanzahita (de), 10",
    "sg:city":"Fuenlabrada",
    "sg:orig_category":"Venta, Localizaci\u00d3n, Reparaci\u00d3n De Material E Instrumental M\u00c9dico",
    "sg:phone":"+34 916 06 42 11",
    "sg:postcode":"28946",
    "sg:province":"Madrid",
    "wof:name":"Medical Iberica S. A.",
    "wof:placetype":"venue"
},
  "geometry": {"coordinates":[-3.7635500431,40.282787323],"type":"Point"}
}