{
  "type": "Feature",
  "properties": {
    "addr:full":"Ptda Prats, S/n Cabra Del Camp Tarragona 43811",
    "addr:housenumber":"s / n",
    "addr:postcode":"43811",
    "addr:street":"Ptda Prats",
    "iso:country":"ES",
    "sg:address":"Ptda Prats, S/n",
    "sg:city":"Cabra Del Camp",
    "sg:orig_category":"Serrer\u00cdas De Madera",
    "sg:phone":"+34 977 63 02 10",
    "sg:postcode":"43811",
    "sg:province":"Tarragona",
    "wof:name":"Aserradero Fontova S.a.",
    "wof:placetype":"venue"
},
  "geometry": {"coordinates":[1.2759416103,41.3949661255],"type":"Point"}
}