{
  "type": "Feature",
  "properties": {
    "iso:country":"ES",
    "sg:address":"Huerta Del Prado-adosadas, 28",
    "sg:city":"Marbella",
    "sg:orig_category":"Prot\u00c9sicos Dentales",
    "sg:phone":"+34 952 77 75 64",
    "sg:postcode":"29600",
    "sg:province":"M\u00e1laga",
    "wof:name":"Rodriguez Ramos Jose",
    "wof:placetype":"venue"
},
  "geometry": {"coordinates":[-4.8833007812,36.5079956055],"type":"Point"}
}