{
  "type": "Feature",
  "properties": {
    "iso:country":"ES",
    "sg:address":"Carr Platja, 3",
    "sg:city":"Badalona",
    "sg:orig_category":"Peluquer\u00cdas, Peluquer\u00cda Mixta",
    "sg:phone":"+34 933 89 35 09",
    "sg:postcode":"08911",
    "sg:province":"Barcelona",
    "wof:name":"Oriol Tarrats Josefa",
    "wof:placetype":"venue"
},
  "geometry": {"coordinates":[2.2498540878,41.4475402832],"type":"Point"}
}