{
  "type": "Feature",
  "properties": {
    "iso:country":"ES",
    "sg:address":"Calle de Almirante Carrero Blanco, S/n",
    "sg:city":"Carballeda Avia",
    "sg:orig_category":"Comerciantes Al Por Mayor De Vinos, Licores Y Alcoholes",
    "sg:phone":"+34 988 48 70 09",
    "sg:postcode":"32412",
    "sg:province":"Ourense",
    "wof:name":"Alonso Lorenzo Manuel",
    "wof:placetype":"venue"
},
  "geometry": {"coordinates":[-7.8646407127,42.340007782],"type":"Point"}
}