{
  "type": "Feature",
  "properties": {
    "addr:full":"Calle de Sierra De Guadarrama (de La), 86 Poligono De San Fernando De Henares Madrid 28830",
    "addr:housenumber":"86",
    "addr:postcode":"28830",
    "addr:street":"Calle De Sierra De Guadarrama De La",
    "iso:country":"ES",
    "sg:address":"Calle de Sierra De Guadarrama (de La), 86",
    "sg:city":"Poligono De San Fernando De Henares",
    "sg:orig_category":"Alumbrados",
    "sg:phone":"+34 916 76 87 02",
    "sg:postcode":"28830",
    "sg:province":"Madrid",
    "wof:name":"Gele S.a.",
    "wof:placetype":"venue"
},
  "geometry": {"coordinates":[-3.496243,40.4519462585],"type":"Point"}
}