{
  "type": "Feature",
  "properties": {
    "addr:full":"Poli Padre Anchieta, 96 San Cristobal De La Laguna Santa Cruz De Tenerife 38203",
    "addr:housenumber":"96",
    "addr:postcode":"38203",
    "iso:country":"ES",
    "sg:address":"Poli Padre Anchieta, 96",
    "sg:city":"San Cristobal De La Laguna",
    "sg:orig_category":"Sindicatos Y Colegios Profesionales",
    "sg:phone":"+34 922 25 34 32",
    "sg:postcode":"38203",
    "sg:province":"Santa Cruz De Tenerife",
    "wof:name":"A.u.g.c. Delegacion Canarias",
    "wof:placetype":"venue"
},
  "geometry": {"coordinates":[-16.3206272125,28.4865379333],"type":"Point"}
}