{
  "type": "Feature",
  "properties": {
    "iso:country":"ES",
    "sg:address":"Carrer de Brutau, 47",
    "sg:city":"Sabadell",
    "sg:orig_category":"Cl\u00cdnicas Dentales",
    "sg:phone":"+34 937 11 66 07",
    "sg:postcode":"08203",
    "sg:province":"Barcelona",
    "wof:name":"J.roige Adell S.l.",
    "wof:placetype":"venue"
},
  "geometry": {"coordinates":[2.1115849018,41.5366630554],"type":"Point"}
}