{
  "type": "Feature",
  "properties": {
    "iso:country":"ES",
    "sg:address":"Avda Habaneras (de Las), 70",
    "sg:city":"Torrevieja",
    "sg:orig_category":"Sociedades, Compa\u00d1\u00cdas Aseguradoras",
    "sg:phone":"+34 965 71 03 44",
    "sg:postcode":"03180",
    "sg:province":"Alicante",
    "wof:name":"El Ocaso S.a.",
    "wof:placetype":"venue"
},
  "geometry": {"coordinates":[-0.6667910218,37.9803962708],"type":"Point"}
}