{
  "type": "Feature",
  "properties": {
    "iso:country":"ES",
    "sg:address":"Pase San Antonio, 13",
    "sg:city":"Salamanca",
    "sg:orig_category":"Tintes (fabricaci\u00d3n, Al Por Mayor)",
    "sg:phone":"+34 923 12 17 54",
    "sg:postcode":"37003",
    "sg:province":"Salamanca",
    "wof:name":"Tintorerias Titan S.l.",
    "wof:placetype":"venue"
},
  "geometry": {"coordinates":[-5.6572589874,40.9647102356],"type":"Point"}
}