{
  "type": "Feature",
  "properties": {
    "addr:full":"Carr Martirs, 47 Muro Islas Baleares 07440",
    "addr:housenumber":"47",
    "addr:postcode":"07440",
    "addr:street":"Carr Martirs",
    "iso:country":"ES",
    "sg:address":"Carr Martirs, 47",
    "sg:city":"Muro",
    "sg:orig_category":"Inform\u00c1tica, Ofim\u00c1tica (estudios, Asesor\u00cda, Ingenier\u00cda, Formaci\u00d3n)",
    "sg:phone":"+34 971 86 10 02",
    "sg:postcode":"07440",
    "sg:province":"Islas Baleares",
    "sg:website":"www.bitsibytes.com",
    "wof:name":"Estray Mas Jaime",
    "wof:placetype":"venue"
},
  "geometry": {"coordinates":[3.05813694,39.7331962585],"type":"Point"}
}