{
  "type": "Feature",
  "properties": {
    "addr:full":"Avda Hermanos Bou, S/n Castellon Castell\u00f3n 12003",
    "addr:housenumber":"s / n",
    "addr:postcode":"12003",
    "addr:street":"Avda Hermanos Bou",
    "iso:country":"ES",
    "sg:address":"Avda Hermanos Bou, S/n",
    "sg:city":"Castellon",
    "sg:orig_category":"Electricidad: Instaladores",
    "sg:phone":"+34 964 23 91 38",
    "sg:postcode":"12003",
    "sg:province":"Castell\u00f3n",
    "sg:website":"www.isolux.es",
    "wof:name":"Isolux Wat S.a.",
    "wof:placetype":"venue"
},
  "geometry": {"coordinates":[-0.0092168003,39.9773216248],"type":"Point"}
}