{
  "type": "Feature",
  "properties": {
    "addr:full":"Crrtra De Huescar, Km. 0020,8 Galera Granada 18840",
    "addr:postcode":"18840",
    "addr:street":"Km. 0020,8 Galera",
    "iso:country":"ES",
    "sg:address":"Crrtra De Huescar, Km. 0020,8",
    "sg:city":"Galera",
    "sg:orig_category":"Distribuci\u00d3n De Petr\u00d3leo Y Derivados",
    "sg:phone":"+34 958 73 91 50",
    "sg:postcode":"18840",
    "sg:province":"Granada",
    "wof:name":"Resan Combustibles S.l.u.",
    "wof:placetype":"venue"
},
  "geometry": {"coordinates":[-2.5504388809,37.745929718],"type":"Point"}
}