{
  "type": "Feature",
  "properties": {
    "addr:full":"Plaz Gabriel Celaya, 4 Madrid Madrid 28529",
    "addr:housenumber":"4",
    "addr:postcode":"28529",
    "addr:street":"Celaya",
    "iso:country":"ES",
    "sg:address":"Plaz Gabriel Celaya, 4",
    "sg:city":"Madrid",
    "sg:orig_category":"Abogados",
    "sg:phone":"+34 916 66 84 23",
    "sg:postcode":"28529",
    "sg:province":"Madrid",
    "wof:name":"Dios Moreno Fernande De",
    "wof:placetype":"venue"
},
  "geometry": {"coordinates":[-3.5102670193,40.314289093],"type":"Point"}
}