{
  "type": "Feature",
  "properties": {
    "addr:full":"Rua Juan De Anges, 12 Ourense Ourense 32002",
    "addr:housenumber":"12",
    "addr:postcode":"32002",
    "addr:street":"Rua Juan De Anges",
    "iso:country":"ES",
    "sg:address":"Rua Juan De Anges, 12",
    "sg:city":"Ourense",
    "sg:orig_category":"Comadronas",
    "sg:phone":"+34 988 23 00 21",
    "sg:postcode":"32002",
    "sg:province":"Ourense",
    "wof:name":"Villar Lorenzo Mercedes",
    "wof:placetype":"venue"
},
  "geometry": {"coordinates":[-7.8751020432,42.3430175781],"type":"Point"}
}