{
  "type": "Feature",
  "properties": {
    "iso:country":"ES",
    "sg:address":"Calle de Everest, 17",
    "sg:city":"Fuenlabrada",
    "sg:orig_category":"Ropa Y Accesorios",
    "sg:phone":"+34 916 90 59 25",
    "sg:postcode":"28944",
    "sg:province":"Madrid",
    "wof:name":"Takhiro Clothing S.l.",
    "wof:placetype":"venue"
},
  "geometry": {"coordinates":[-3.8005490303,40.27917099],"type":"Point"}
}