{
  "type": "Feature",
  "properties": {
    "iso:country":"ES",
    "sg:address":"Calle de Enrique Amat, 32",
    "sg:city":"Montefrio",
    "sg:orig_category":"Inmobiliaria (agencias)",
    "sg:phone":"+34 958 31 02 72",
    "sg:postcode":"18270",
    "sg:province":"Granada",
    "wof:name":"Pulsar S.c",
    "wof:placetype":"venue"
},
  "geometry": {"coordinates":[-4.0084290504,37.3211708069],"type":"Point"}
}