{
  "type": "Feature",
  "properties": {
    "iso:country":"ES",
    "sg:address":"Avda Jesus Santos Rein, S/n",
    "sg:city":"Fuengirola",
    "sg:orig_category":"Alquiler De Bicicletas Y Motocicletas",
    "sg:phone":"+34 952 47 25 51",
    "sg:postcode":"29640",
    "sg:province":"M\u00e1laga",
    "wof:name":"Comercial Mountain Bikes S.l.",
    "wof:placetype":"venue"
},
  "geometry": {"coordinates":[-4.6212677956,36.5454711914],"type":"Point"}
}