{
  "type": "Feature",
  "properties": {
    "iso:country":"ES",
    "sg:address":"Ctra Agost, 23",
    "sg:city":"San Vicente Del Raspeig-sant Vicent Del Raspeig",
    "sg:orig_category":"Carnicer\u00cdas, Carnicer\u00cdas",
    "sg:phone":"+34 965 67 53 93",
    "sg:postcode":"03690",
    "sg:province":"Alicante",
    "wof:name":"Carniceria Abril S.c.",
    "wof:placetype":"venue"
},
  "geometry": {"coordinates":[-0.523845017,38.3996315002],"type":"Point"}
}