{
  "type": "Feature",
  "properties": {
    "addr:full":"Calle de Gil Y Carrasco, 4 Le\u00f3n Le\u00f3n 24001",
    "addr:housenumber":"4",
    "addr:postcode":"24001",
    "addr:street":"Calle De Gil Y Carrasco;Leo\u0301N",
    "iso:country":"ES",
    "sg:address":"Calle de Gil Y Carrasco, 4",
    "sg:city":"Le\u00f3n",
    "sg:orig_category":"Ense\u00d1anza Variada",
    "sg:phone":"+34 987 25 19 24",
    "sg:postcode":"24001",
    "sg:province":"Le\u00f3n",
    "wof:name":"Centeno Vega Victorino",
    "wof:placetype":"venue"
},
  "geometry": {"coordinates":[-5.5736517906,42.5968322754],"type":"Point"}
}