{
  "type": "Feature",
  "properties": {
    "addr:full":"Pl Triomf, 24 Terrassa Barcelona 08225",
    "addr:housenumber":"24",
    "addr:postcode":"08225",
    "addr:street":"Pl Triomf",
    "iso:country":"ES",
    "sg:address":"Pl Triomf, 24",
    "sg:city":"Terrassa",
    "sg:orig_category":"Supermercados Y Hipermercados",
    "sg:phone":"+34 937 35 78 92",
    "sg:postcode":"08225",
    "sg:province":"Barcelona",
    "wof:name":"Super Tallo S.a.",
    "wof:placetype":"venue"
},
  "geometry": {"coordinates":[2.0134088993,41.5725440979],"type":"Point"}
}