{
  "type": "Feature",
  "properties": {
    "addr:full":"Calle de Carrilejos (de Los), 70 Colmenar Viejo Madrid 28770",
    "addr:postcode":"28770",
    "addr:street":"Calle De Carrilejos De Los",
    "iso:country":"ES",
    "sg:address":"Calle de Carrilejos (de Los), 70",
    "sg:city":"Colmenar Viejo",
    "sg:orig_category":"Abogados",
    "sg:phone":"+34 918 45 16 97",
    "sg:postcode":"28770",
    "sg:province":"Madrid",
    "wof:name":"Romera Del Valle Pablo",
    "wof:placetype":"venue"
},
  "geometry": {"coordinates":[-3.7713749409,40.6639175415],"type":"Point"}
}