{
  "type": "Feature",
  "properties": {
    "addr:full":"Carr Trinquet (el), S/n Benicasim Castell\u00f3n 12560",
    "addr:housenumber":"s / n",
    "addr:postcode":"12560",
    "addr:street":"Carr Trinquet El",
    "iso:country":"ES",
    "sg:address":"Carr Trinquet (el), S/n",
    "sg:city":"Benicasim",
    "sg:orig_category":"Promotores Constructores",
    "sg:phone":"+34 964 30 24 16",
    "sg:postcode":"12560",
    "sg:province":"Castell\u00f3n",
    "wof:name":"Sat Mas De Rander",
    "wof:placetype":"venue"
},
  "geometry": {"coordinates":[0.0457400009,40.0510292053],"type":"Point"}
}