{
  "type": "Feature",
  "properties": {
    "iso:country":"ES",
    "sg:address":"Avda Estacion (da), 10",
    "sg:city":"Lalin",
    "sg:orig_category":"Asociaciones Y Clubs Deportivos",
    "sg:phone":"+34 986 78 03 99",
    "sg:postcode":"36500",
    "sg:province":"Pontevedra",
    "wof:name":"Fernandez Rodriguez Carlos",
    "wof:placetype":"venue"
},
  "geometry": {"coordinates":[-8.1149835587,42.6553497314],"type":"Point"}
}