{
  "type": "Feature",
  "properties": {
    "addr:full":"Avda Padre Huidobro, Km. 0008,0 Madrid Madrid 28023",
    "addr:postcode":"28023",
    "addr:street":"Avda Padre Huidobro Km. 0008,0",
    "iso:country":"ES",
    "sg:address":"Avda Padre Huidobro, Km. 0008,0",
    "sg:city":"Madrid",
    "sg:orig_category":"Refiner\u00cdas De Petr\u00d3leo",
    "sg:phone":"+34 913 57 46 36",
    "sg:postcode":"28023",
    "sg:province":"Madrid",
    "wof:name":"Repsol Ypf S.a.",
    "wof:placetype":"venue"
},
  "geometry": {"coordinates":[-3.7598800659,40.4611663818],"type":"Point"}
}