{
  "type": "Feature",
  "properties": {
    "iso:country":"ES",
    "sg:address":"Av Montevideo, 68",
    "sg:city":"Vilassar De Mar",
    "sg:orig_category":"Inmobiliaria (agencias)",
    "sg:phone":"+34 937 59 25 46",
    "sg:postcode":"08340",
    "sg:province":"Barcelona",
    "wof:name":"Ancora 2 Gestio Inmobiliaria S.l.",
    "wof:placetype":"venue"
},
  "geometry": {"coordinates":[2.3872776031,41.508846283],"type":"Point"}
}