{
  "type": "Feature",
  "properties": {
    "addr:full":"Calle de Pio Basanta, 43 Mojados Valladolid 47250",
    "addr:housenumber":"43",
    "addr:postcode":"47250",
    "addr:street":"Calle De Pio Basanta",
    "iso:country":"ES",
    "sg:address":"Calle de Pio Basanta, 43",
    "sg:city":"Mojados",
    "sg:orig_category":"Barbacoas Y Accesorios",
    "sg:phone":"+34 983 60 71 29",
    "sg:postcode":"47250",
    "sg:province":"Valladolid",
    "wof:name":"Cubero Castro Manuel Cristobal",
    "wof:placetype":"venue"
},
  "geometry": {"coordinates":[-4.665804863,41.4302177429],"type":"Point"}
}