{
  "type": "Feature",
  "properties": {
    "addr:full":"Calle de Aurora, 20 Llerena Badajoz 06900",
    "addr:housenumber":"20",
    "addr:postcode":"06900",
    "addr:street":"Calle De Aurora",
    "iso:country":"ES",
    "sg:address":"Calle de Aurora, 20",
    "sg:city":"Llerena",
    "sg:orig_category":"Institutos De Belleza",
    "sg:phone":"+34 924 87 11 87",
    "sg:postcode":"06900",
    "sg:province":"Badajoz",
    "wof:name":"Mu\u00f1oz Rafael Granada",
    "wof:placetype":"venue"
},
  "geometry": {"coordinates":[-6.0137968063,38.2386283875],"type":"Point"}
}