{
  "type": "Feature",
  "properties": {
    "iso:country":"ES",
    "sg:address":"Calle de Iparragirre, 17",
    "sg:city":"Donostia-san Sebastian",
    "sg:orig_category":"Peluquer\u00cdas",
    "sg:phone":"+34 943 28 38 21",
    "sg:postcode":"20001",
    "sg:province":"Guip\u00f9zcoa",
    "wof:name":"Martin Rodriguez Amparo",
    "wof:placetype":"venue"
},
  "geometry": {"coordinates":[-1.975998044,43.3230018616],"type":"Point"}
}