{
  "type": "Feature",
  "properties": {
    "iso:country":"ES",
    "sg:address":"Carrer de Francoli (del), 10",
    "sg:city":"Salou",
    "sg:orig_category":"Restaurantes",
    "sg:phone":"+34 977 38 46 43",
    "sg:postcode":"43840",
    "sg:province":"Tarragona",
    "wof:name":"Raluce S.l.",
    "wof:placetype":"venue"
},
  "geometry": {"coordinates":[1.1324750185,41.0806999207],"type":"Point"}
}