{
  "type": "Feature",
  "properties": {
    "iso:country":"ES",
    "sg:address":"Calle de Mar Baltico, 9",
    "sg:city":"Madrid",
    "sg:orig_category":"Venta, Colocaci\u00d3n, Reparaci\u00d3n De Parabrisas, Techos Descapotables",
    "sg:phone":"+34 913 81 05 23",
    "sg:postcode":"28033",
    "sg:province":"Madrid",
    "wof:name":"Vidrio Auto Dorado S.l.",
    "wof:placetype":"venue"
},
  "geometry": {"coordinates":[-3.6418719292,40.4726905823],"type":"Point"}
}