{
  "type": "Feature",
  "properties": {
    "addr:full":"Calle de Palacio, 1 Pombriego Le\u00f3n 24389",
    "addr:housenumber":"1",
    "addr:postcode":"24389",
    "addr:street":"Calle De Palacio;Leo\u0301N",
    "iso:country":"ES",
    "sg:address":"Calle de Palacio, 1",
    "sg:city":"Pombriego",
    "sg:orig_category":"Iglesia Cat\u00d3lica",
    "sg:phone":"+34 987 45 23 44",
    "sg:postcode":"24389",
    "sg:province":"Le\u00f3n",
    "wof:name":"Diocesis Astorga Administracion",
    "wof:placetype":"venue"
},
  "geometry": {"coordinates":[-6.7017521858,42.4246025085],"type":"Point"}
}