{
  "type": "Feature",
  "properties": {
    "addr:full":"Calle de Petunia, 5 Cobe\u00f1a Madrid 28863",
    "addr:housenumber":"5",
    "addr:postcode":"28863",
    "addr:street":"Calle De Petunia",
    "iso:country":"ES",
    "sg:address":"Calle de Petunia, 5",
    "sg:city":"Cobe\u00f1a",
    "sg:orig_category":"Higiene, Belleza: Art\u00cdculos (al Por Menor)",
    "sg:phone":"+34 916 20 70 66",
    "sg:postcode":"28863",
    "sg:province":"Madrid",
    "wof:name":"Samarit Mediberica S.l.l.",
    "wof:placetype":"venue"
},
  "geometry": {"coordinates":[-3.5016338825,40.5741500854],"type":"Point"}
}