{
  "type": "Feature",
  "properties": {
    "addr:full":"Carrer de Santa Eulalia, 82 Hospitalet Llobregat Barcelona 08902",
    "addr:housenumber":"82",
    "addr:postcode":"08902",
    "addr:street":"Carrer De Santa Eulalia",
    "iso:country":"ES",
    "sg:address":"Carrer de Santa Eulalia, 82",
    "sg:city":"Hospitalet Llobregat",
    "sg:orig_category":"Peluqueros: De Se\u00d1oras",
    "sg:phone":"+34 933 31 64 97",
    "sg:postcode":"08902",
    "sg:province":"Barcelona",
    "wof:name":"Pastor Marcos Laura",
    "wof:placetype":"venue"
},
  "geometry": {"coordinates":[2.127808094,41.3672790527],"type":"Point"}
}