{
  "type": "Feature",
  "properties": {
    "addr:full":"Rbla Torre De L'onclet, S/n Vilanova I La Geltru Barcelona 08800",
    "addr:housenumber":"s",
    "addr:postcode":"08800",
    "addr:street":"Rbla Torre De L'Onclet;/ N",
    "iso:country":"ES",
    "sg:address":"Rbla Torre De L'onclet, S/n",
    "sg:city":"Vilanova I La Geltru",
    "sg:orig_category":"Chapister\u00cda",
    "sg:phone":"+34 938 93 81 13",
    "sg:postcode":"08800",
    "sg:province":"Barcelona",
    "wof:name":"Segovia Ariza Juan",
    "wof:placetype":"venue"
},
  "geometry": {"coordinates":[1.7267680168,41.2384185791],"type":"Point"}
}