{
  "type": "Feature",
  "properties": {
    "iso:country":"ES",
    "sg:address":"Plaz De La Madera, 12",
    "sg:city":"Benavente",
    "sg:orig_category":"Muebles, Minoristas",
    "sg:phone":"+34 980 63 49 26",
    "sg:postcode":"49600",
    "sg:province":"Zamora",
    "wof:name":"Muebles Gala Sl.",
    "wof:placetype":"venue"
},
  "geometry": {"coordinates":[-5.677795887,42.0033531189],"type":"Point"}
}