{
  "type": "Feature",
  "properties": {
    "iso:country":"ES",
    "sg:address":"Calle de Fernando Guanarteme, 74",
    "sg:city":"Cruce I",
    "sg:orig_category":"Distribuci\u00d3n De Petr\u00d3leo Y Derivados",
    "sg:phone":"+34 928 75 64 51",
    "sg:postcode":"35110",
    "sg:province":"Las Palmas",
    "wof:name":"Castro Castro Jose Juan",
    "wof:placetype":"venue"
},
  "geometry": {"coordinates":[-15.443031311,27.8558292389],"type":"Point"}
}