{
  "type": "Feature",
  "properties": {
    "iso:country":"ES",
    "sg:address":"Calle de Embajadores, 92",
    "sg:city":"Valladolid",
    "sg:orig_category":"Farmacias",
    "sg:phone":"+34 983 27 16 76",
    "sg:postcode":"47013",
    "sg:province":"Valladolid",
    "wof:name":"Aguado Ortega Andres",
    "wof:placetype":"venue"
},
  "geometry": {"coordinates":[-4.722990036,41.6310119629],"type":"Point"}
}