{
  "type": "Feature",
  "properties": {
    "addr:full":"Ctra Alicante, Km. 0383,3 Novelda Alicante 03660",
    "addr:postcode":"03660",
    "addr:street":"Ctra Alicante Km. 0383,3",
    "iso:country":"ES",
    "sg:address":"Ctra Alicante, Km. 0383,3",
    "sg:city":"Novelda",
    "sg:orig_category":"M\u00c1rmoles, Granitos Y Piedras Naturales",
    "sg:phone":"+34 965 60 57 16",
    "sg:postcode":"03660",
    "sg:province":"Alicante",
    "wof:name":"Ingemar S. A.",
    "wof:placetype":"venue"
},
  "geometry": {"coordinates":[-0.7638189793,38.3825035095],"type":"Point"}
}