{
  "type": "Feature",
  "properties": {
    "iso:country":"ES",
    "sg:address":"Calle de Pio Del Rio Hortega, 10",
    "sg:city":"Valladolid",
    "sg:orig_category":"Contenedores (mercanc\u00cdas)",
    "sg:phone":"+34 983 34 21 27",
    "sg:postcode":"47014",
    "sg:province":"Valladolid",
    "wof:name":"Pascual Paniagua Andres",
    "wof:placetype":"venue"
},
  "geometry": {"coordinates":[-4.7411670685,41.6510429382],"type":"Point"}
}