{
  "type": "Feature",
  "properties": {
    "iso:country":"ES",
    "sg:address":"Calle de Rosales (los), 6",
    "sg:city":"Navas Oro",
    "sg:orig_category":"Ferreter\u00cda Artesanal",
    "sg:phone":"+34 921 59 10 04",
    "sg:postcode":"40470",
    "sg:province":"Segovia",
    "wof:name":"Gomez Hernandez Vicente Antonio",
    "wof:placetype":"venue"
},
  "geometry": {"coordinates":[-4.4420599937,41.1974601746],"type":"Point"}
}