{
  "type": "Feature",
  "properties": {
    "iso:country":"ES",
    "sg:address":"Carrer de Enten\u00c7a, 208",
    "sg:city":"Barcelona",
    "sg:orig_category":"Tintes (fabricaci\u00d3n, Al Por Mayor)",
    "sg:phone":"+34 934 10 42 56",
    "sg:postcode":"08029",
    "sg:province":"Barcelona",
    "wof:name":"Tintoreria Infanta Scp",
    "wof:placetype":"venue"
},
  "geometry": {"coordinates":[2.1433839798,41.3852806091],"type":"Point"}
}