{
  "type": "Feature",
  "properties": {
    "addr:full":"Avda Ordo\u00d1o Ii, 27 Le\u00f3n Le\u00f3n 24001",
    "addr:housenumber":"27",
    "addr:postcode":"24001",
    "addr:street":"Avda Ordon\u0303O Ii;Leo\u0301N",
    "iso:country":"ES",
    "sg:address":"Avda Ordo\u00d1o Ii, 27",
    "sg:city":"Le\u00f3n",
    "sg:orig_category":"Bancos",
    "sg:phone":"+34 987 25 16 10",
    "sg:postcode":"24001",
    "sg:province":"Le\u00f3n",
    "wof:name":"Bankinter S.a.",
    "wof:placetype":"venue"
},
  "geometry": {"coordinates":[-5.5752549171,42.596824646],"type":"Point"}
}