{
  "type": "Feature",
  "properties": {
    "iso:country":"ES",
    "sg:address":"Calle de Mercado, 15",
    "sg:city":"Frias",
    "sg:orig_category":"Artesan\u00cda",
    "sg:phone":"+34 947 35 86 55",
    "sg:postcode":"09211",
    "sg:province":"Burgos",
    "wof:name":"Iba\u00f1ez Ruiz Ana",
    "wof:placetype":"venue"
},
  "geometry": {"coordinates":[-3.2951550484,42.7619094849],"type":"Point"}
}