{
  "type": "Feature",
  "properties": {
    "addr:full":"Ctra Valls, Km. 0001,0 Alcover Tarragona 43460",
    "addr:postcode":"43460",
    "addr:street":"Ctra Valls Km. 0001,0",
    "iso:country":"ES",
    "sg:address":"Ctra Valls, Km. 0001,0",
    "sg:city":"Alcover",
    "sg:orig_category":"Goma: Productos De Uso Industrial (fabricaci\u00d3n, Al Por Mayor)",
    "sg:phone":"+34 977 76 03 94",
    "sg:postcode":"43460",
    "sg:province":"Tarragona",
    "wof:name":"Fons Martinez Jordi",
    "wof:placetype":"venue"
},
  "geometry": {"coordinates":[1.1718250513,41.2622566223],"type":"Point"}
}