{
  "type": "Feature",
  "properties": {
    "iso:country":"ES",
    "sg:address":"Calle de Convento Santa Clara, 1",
    "sg:city":"Valencia",
    "sg:orig_category":"Arquitectos",
    "sg:phone":"+34 963 51 15 25",
    "sg:postcode":"46002",
    "sg:province":"Valencia",
    "wof:name":"Arquitectura Y Urbanismo Singularq S.l.",
    "wof:placetype":"venue"
},
  "geometry": {"coordinates":[-0.3753474951,39.4682922363],"type":"Point"}
}