{
  "type": "Feature",
  "properties": {
    "iso:country":"ES",
    "sg:address":"Est Ferrocarril-p I Estacion, S/n",
    "sg:city":"Andujar",
    "sg:orig_category":"Charcuter\u00cdas (al Por Mayor)",
    "sg:phone":"+34 953 50 50 29",
    "sg:postcode":"23740",
    "sg:province":"Ja\u00e9n",
    "wof:name":"Jaraices Fernandez Jose Luis",
    "wof:placetype":"venue"
},
  "geometry": {"coordinates":[-4.0286779404,38.2897567749],"type":"Point"}
}