{
  "type": "Feature",
  "properties": {
    "addr:full":"Calle de Morera, S/n Poligono Industrial De Arinaga Las Palmas 35118",
    "addr:housenumber":"s / n",
    "addr:postcode":"35118",
    "addr:street":"Calle De Morera;Poligono Industrial De Arinaga Las",
    "iso:country":"ES",
    "sg:address":"Calle de Morera, S/n",
    "sg:city":"Poligono Industrial De Arinaga",
    "sg:orig_category":"Empresas De Carpinter\u00cda De Madera",
    "sg:phone":"+34 928 79 04 48",
    "sg:postcode":"35118",
    "sg:province":"Las Palmas",
    "wof:name":"Ortiz Santana Juan",
    "wof:placetype":"venue"
},
  "geometry": {"coordinates":[-15.3927698135,27.8557987213],"type":"Point"}
}