{
  "type": "Feature",
  "properties": {
    "iso:country":"ES",
    "sg:address":"Ctra Estacion, Km. 0002,7",
    "sg:city":"Pe\u00f1iscola",
    "sg:orig_category":"Zonas De Acampada, Aparcamiento Para Caravanas",
    "sg:phone":"+34 964 48 06 53",
    "sg:postcode":"12598",
    "sg:province":"Castell\u00f3n",
    "wof:name":"Camping Bungalow Soldor S.l.",
    "wof:placetype":"venue"
},
  "geometry": {"coordinates":[-0.0456800014,39.9851417542],"type":"Point"}
}