{
  "type": "Feature",
  "properties": {
    "iso:country":"ES",
    "sg:address":"Calle de Zamora, 2",
    "sg:city":"Albacete",
    "sg:orig_category":"Ingenier\u00cda, Centros De Estudios (diversos)",
    "sg:phone":"+34 967 21 12 38",
    "sg:postcode":"02006",
    "sg:province":"Albacete",
    "wof:name":"Tecnologias Y Servicios Agrarios S.a.",
    "wof:placetype":"venue"
},
  "geometry": {"coordinates":[-1.8537887335,38.9996452332],"type":"Point"}
}