{
  "type": "Feature",
  "properties": {
    "iso:country":"ES",
    "sg:address":"Calle de Castro, 23",
    "sg:city":"Castro",
    "sg:orig_category":"Producci\u00d3n De Huevos",
    "sg:phone":"+34 922 39 18 45",
    "sg:postcode":"38611",
    "sg:province":"Santa Cruz De Tenerife",
    "wof:name":"Grasuma S.a.",
    "wof:placetype":"venue"
},
  "geometry": {"coordinates":[-16.2548561096,28.4698104858],"type":"Point"}
}