{
  "type": "Feature",
  "properties": {
    "addr:full":"La Caridad, 62 Tacoronte Santa Cruz De Tenerife 38350",
    "addr:housenumber":"62",
    "addr:postcode":"38350",
    "addr:street":"Caridad",
    "iso:country":"ES",
    "sg:address":"La Caridad, 62",
    "sg:city":"Tacoronte",
    "sg:orig_category":"Teatro, Ballet, Danza (agrupaciones, Compa\u00d1\u00cdas)",
    "sg:phone":"+34 922 56 33 38",
    "sg:postcode":"38350",
    "sg:province":"Santa Cruz De Tenerife",
    "wof:name":"Espectaculos Tropicana S.l.",
    "wof:placetype":"venue"
},
  "geometry": {"coordinates":[-16.4174289703,28.4756546021],"type":"Point"}
}