{
  "type": "Feature",
  "properties": {
    "iso:country":"ES",
    "sg:address":"Avda Coru\u00d1a (da), 127",
    "sg:city":"Lugo",
    "sg:orig_category":"Asociaciones Y Clubs Deportivos",
    "sg:phone":"+34 982 26 30 72",
    "sg:postcode":"27003",
    "sg:province":"Lugo",
    "wof:name":"Souto Iglesias Jose Antonio",
    "wof:placetype":"venue"
},
  "geometry": {"coordinates":[-7.5617232323,43.018737793],"type":"Point"}
}