{
  "type": "Feature",
  "properties": {
    "iso:country":"ES",
    "sg:address":"Pl Llibertat, 17",
    "sg:city":"Reus",
    "sg:orig_category":"Centros Empresariales",
    "sg:phone":"+34 977 12 78 85",
    "sg:postcode":"43201",
    "sg:province":"Tarragona",
    "wof:name":"Induturist S.l.",
    "wof:placetype":"venue"
},
  "geometry": {"coordinates":[1.1073650122,41.1588516235],"type":"Point"}
}