{
  "type": "Feature",
  "properties": {
    "iso:country":"ES",
    "sg:address":"Calle de Dos De Mayo, 13",
    "sg:city":"Valladolid",
    "sg:orig_category":"Asistencia Social",
    "sg:phone":"+34 983 29 68 44",
    "sg:postcode":"47004",
    "sg:province":"Valladolid",
    "sg:website":"www.aprome.org",
    "wof:name":"Asociacion Para La Proteccion Del Menor",
    "wof:placetype":"venue"
},
  "geometry": {"coordinates":[-4.7243118286,41.6470947266],"type":"Point"}
}