{
  "type": "Feature",
  "properties": {
    "iso:country":"ES",
    "sg:address":"Calle de Isabel La Catolica, 1",
    "sg:city":"Alcantarilla",
    "sg:orig_category":"Carnicer\u00cdas, Carnicer\u00cdas",
    "sg:phone":"+34 968 80 00 32",
    "sg:postcode":"30820",
    "sg:province":"Murcia",
    "wof:name":"Hernandez Martinez Antonio",
    "wof:placetype":"venue"
},
  "geometry": {"coordinates":[-1.2215499878,37.9677238464],"type":"Point"}
}