{
  "type": "Feature",
  "properties": {
    "addr:full":"Calle de Cartuja, 2 Jerez De La Frontera C\u00e1diz 11401",
    "addr:housenumber":"2",
    "addr:postcode":"11401",
    "addr:street":"Calle De Cartuja",
    "iso:country":"ES",
    "sg:address":"Calle de Cartuja, 2",
    "sg:city":"Jerez De La Frontera",
    "sg:orig_category":"Ropa Para Se\u00d1oras (al Por Menor)",
    "sg:phone":"+34 956 32 42 03",
    "sg:postcode":"11401",
    "sg:province":"C\u00e1diz",
    "wof:name":"Campo Romero Carmen",
    "wof:placetype":"venue"
},
  "geometry": {"coordinates":[-6.1278381348,36.6805419922],"type":"Point"}
}