{
  "type": "Feature",
  "properties": {
    "iso:country":"ES",
    "sg:address":"Calle de Alba (de) Carretera, 14",
    "sg:city":"Cordoba",
    "sg:orig_category":"Guarder\u00cdas",
    "sg:phone":"+34 957 27 18 73",
    "sg:postcode":"14012",
    "sg:province":"C\u00f3rdoba",
    "wof:name":"Serrano Garcia Eloisa",
    "wof:placetype":"venue"
},
  "geometry": {"coordinates":[-4.7528471947,37.9300079346],"type":"Point"}
}