{
  "type": "Feature",
  "properties": {
    "iso:country":"ES",
    "sg:address":"Calle de Fermin Caballero, 57",
    "sg:city":"Madrid",
    "sg:orig_category":"Arquitectos",
    "sg:phone":"+34 917 30 33 33",
    "sg:postcode":"28034",
    "sg:province":"Madrid",
    "wof:name":"Escalona Paul Ana Maria",
    "wof:placetype":"venue"
},
  "geometry": {"coordinates":[-3.7090539932,40.482673645],"type":"Point"}
}