{
  "type": "Feature",
  "properties": {
    "addr:full":"Calle de Maria Paya, 8 Biar Alicante 03410",
    "addr:housenumber":"8",
    "addr:postcode":"03410",
    "addr:street":"Calle De Maria Paya",
    "iso:country":"ES",
    "sg:address":"Calle de Maria Paya, 8",
    "sg:city":"Biar",
    "sg:orig_category":"Peluquer\u00cdas, Peluquer\u00cda Mixta",
    "sg:phone":"+34 965 81 03 15",
    "sg:postcode":"03410",
    "sg:province":"Alicante",
    "wof:name":"Sanjuan Frances Elena",
    "wof:placetype":"venue"
},
  "geometry": {"coordinates":[-0.7649160028,38.6288757324],"type":"Point"}
}