{
  "type": "Feature",
  "properties": {
    "iso:country":"ES",
    "sg:address":"Pg Manuel Girona, 14",
    "sg:city":"Barcelona",
    "sg:orig_category":"Importaci\u00d3n",
    "sg:phone":"+34 932 00 63 61",
    "sg:postcode":"08034",
    "sg:province":"Barcelona",
    "wof:name":"Union Quesera Europea S.l.",
    "wof:placetype":"venue"
},
  "geometry": {"coordinates":[2.1211819649,41.3900527954],"type":"Point"}
}