{
  "type": "Feature",
  "properties": {
    "iso:country":"ES",
    "sg:address":"Barrio Hoyo, 166",
    "sg:city":"Campuzano",
    "sg:orig_category":"Hielo Artificial (fabricaci\u00d3n, Distribuci\u00d3n)",
    "sg:phone":"+34 942 89 14 44",
    "sg:postcode":"39300",
    "sg:province":"Cantabria",
    "wof:name":"Herreros Gomez Jaime",
    "wof:placetype":"venue"
},
  "geometry": {"coordinates":[-4.0520391464,43.34897995],"type":"Point"}
}