{
  "type": "Feature",
  "properties": {
    "iso:country":"ES",
    "sg:address":"Calle de Alameda, 1",
    "sg:city":"Sig\u00fcenza",
    "sg:orig_category":"Molduras, Junquillos, Listones Y Molduras Perforadas",
    "sg:phone":"+34 949 39 30 71",
    "sg:postcode":"19250",
    "sg:province":"Guadalajara",
    "wof:name":"Caballero Tena Juana",
    "wof:placetype":"venue"
},
  "geometry": {"coordinates":[-2.6440918446,41.0696716309],"type":"Point"}
}