{
  "type": "Feature",
  "properties": {
    "iso:country":"ES",
    "sg:address":"Carr Josep Anselm Clave, 52",
    "sg:city":"Vilanova I La Geltru",
    "sg:orig_category":"Molduras, Junquillos, Listones Y Molduras Perforadas",
    "sg:phone":"+34 938 15 48 28",
    "sg:postcode":"08800",
    "sg:province":"Barcelona",
    "wof:name":"Las Gaviotas S.c.p.",
    "wof:placetype":"venue"
},
  "geometry": {"coordinates":[1.7237620354,41.2196655273],"type":"Point"}
}