{
  "type": "Feature",
  "properties": {
    "iso:country":"ES",
    "sg:address":"Calle de Concepcion, 2",
    "sg:city":"Oviedo",
    "sg:orig_category":"Abogados",
    "sg:phone":"+34 985 21 99 80",
    "sg:postcode":"33008",
    "sg:province":"Asturias",
    "wof:name":"Cuesta Martinez Juan Miguel",
    "wof:placetype":"venue"
},
  "geometry": {"coordinates":[-5.8437018394,43.3581504822],"type":"Point"}
}