{
  "type": "Feature",
  "properties": {
    "iso:country":"ES",
    "sg:address":"Calle de Ciudad Real, 24",
    "sg:city":"Daimiel",
    "sg:orig_category":"Alimentaci\u00d3n General (al Por Menor)",
    "sg:phone":"+34 926 85 16 39",
    "sg:postcode":"13250",
    "sg:province":"Ciudad Real",
    "wof:name":"Gonzalez De La Aleja Escudero Julian Angel",
    "wof:placetype":"venue"
},
  "geometry": {"coordinates":[-3.6164534092,39.0684127808],"type":"Point"}
}