{
  "type": "Feature",
  "properties": {
    "iso:country":"ES",
    "sg:address":"La Libertad, 1",
    "sg:city":"El Real Jara",
    "sg:orig_category":"Vallados Y Barreras",
    "sg:phone":"+34 954 73 30 46",
    "sg:postcode":"41250",
    "sg:province":"Sevilla",
    "wof:name":"Mestre Gerrero Jose Eloy",
    "wof:placetype":"venue"
},
  "geometry": {"coordinates":[-6.1569814682,37.9497528076],"type":"Point"}
}