{
  "type": "Feature",
  "properties": {
    "addr:full":"Calle de Santa Ana, 11 Rozas De Madrid Madrid 28230",
    "addr:housenumber":"11",
    "addr:postcode":"28230",
    "addr:street":"Calle De Santa Ana",
    "iso:country":"ES",
    "sg:address":"Calle de Santa Ana, 11",
    "sg:city":"Rozas De Madrid",
    "sg:orig_category":"Abogados",
    "sg:phone":"+34 916 37 03 77",
    "sg:postcode":"28230",
    "sg:province":"Madrid",
    "wof:name":"Fernandez-conde Diaz Jesus Luis",
    "wof:placetype":"venue"
},
  "geometry": {"coordinates":[-3.8647511005,40.4954566956],"type":"Point"}
}