{
  "type": "Feature",
  "properties": {
    "iso:country":"ES",
    "sg:address":"Carrer de Dolors, 3",
    "sg:city":"Olot",
    "sg:classifiers":[
        {
            "category":"Arts & Performance",
            "subcategory":"Art Gallery",
            "type":"Entertainment"
        }
    ],
    "sg:phone":"+34 972 27 27 27",
    "sg:postcode":"17800",
    "sg:province":"Girona",
    "sg:tags":[
        "arte",
        "de",
        "galer\u00cdas"
    ],
    "wof:name":"Vila Estudis Ramon",
    "wof:placetype":"venue"
},
  "geometry": {"coordinates":[2.4866681099,42.1816062927],"type":"Point"}
}