{
  "type": "Feature",
  "properties": {
    "iso:country":"ES",
    "sg:address":"Calle de Miguel Bueno, 2",
    "sg:city":"Fuengirola",
    "sg:orig_category":"Ropa Para Se\u00d1oras Y Caballeros (al Por Menor)",
    "sg:phone":"+34 952 58 34 17",
    "sg:postcode":"29640",
    "sg:province":"M\u00e1laga",
    "wof:name":"Hernandez Gamez Sebastian",
    "wof:placetype":"venue"
},
  "geometry": {"coordinates":[-4.6258230209,36.5458488464],"type":"Point"}
}