{
  "type": "Feature",
  "properties": {
    "addr:full":"Carrer de Espronceda, 330 Barcelona Barcelona 08027",
    "addr:housenumber":"330",
    "addr:postcode":"08027",
    "addr:street":"Carrer De Espronceda",
    "iso:country":"ES",
    "sg:address":"Carrer de Espronceda, 330",
    "sg:city":"Barcelona",
    "sg:orig_category":"Frutas, Legumbres Frescas Y Tempranas (al Por Menor)",
    "sg:phone":"+34 933 40 37 70",
    "sg:postcode":"08027",
    "sg:province":"Barcelona",
    "wof:name":"Frutas Roura S.a.",
    "wof:placetype":"venue"
},
  "geometry": {"coordinates":[2.1889660358,41.4173736572],"type":"Point"}
}