{
  "type": "Feature",
  "properties": {
    "addr:full":"Pl. San Jose, 4 Iru\u00f1a Navarra 31001",
    "addr:housenumber":"4",
    "addr:postcode":"31001",
    "addr:street":"Pl. San Jose",
    "iso:country":"ES",
    "sg:address":"Pl. San Jose, 4",
    "sg:city":"Iru\u00f1a",
    "sg:orig_category":"Ingeniero",
    "sg:phone":"+34 948 20 67 35",
    "sg:postcode":"31001",
    "sg:province":"Navarra",
    "wof:name":"Errea Argaiz Jose Maria",
    "wof:placetype":"venue"
},
  "geometry": {"coordinates":[-1.6412210464,42.8202514648],"type":"Point"}
}