{
  "type": "Feature",
  "properties": {
    "addr:full":"Ctra Nacional Ii, Km. 0495,0 Bellpuig Lleida 25250",
    "addr:postcode":"25250",
    "addr:street":"Ctra Nacional Ii Km. 0495,0",
    "iso:country":"ES",
    "sg:address":"Ctra Nacional Ii, Km. 0495,0",
    "sg:city":"Bellpuig",
    "sg:orig_category":"Frutos Y Legumbres",
    "sg:phone":"+34 973 32 04 57",
    "sg:postcode":"25250",
    "sg:province":"Lleida",
    "wof:name":"Societat Agraria De Transformacio N 2995 Bellfruit",
    "wof:placetype":"venue"
},
  "geometry": {"coordinates":[1.0088200569,41.6270713806],"type":"Point"}
}