{
  "type": "Feature",
  "properties": {
    "iso:country":"ES",
    "sg:address":"Paso, 48",
    "sg:city":"Villamayor",
    "sg:orig_category":"Agricultores, Agricultores",
    "sg:phone":"+34 976 58 90 65",
    "sg:postcode":"50162",
    "sg:province":"Zaragoza",
    "wof:name":"Jeluiscar S.a.l.",
    "wof:placetype":"venue"
},
  "geometry": {"coordinates":[-0.7756850123,41.6835250854],"type":"Point"}
}