{
  "type": "Feature",
  "properties": {
    "addr:full":"Carrer de Sadet, 36 S. Just Desvern Barcelona 08960",
    "addr:housenumber":"36",
    "addr:postcode":"08960",
    "addr:street":"Carrer De Sadet",
    "iso:country":"ES",
    "sg:address":"Carrer de Sadet, 36",
    "sg:city":"S. Just Desvern",
    "sg:orig_category":"Fabricaci\u00d3n De Bicicletas, Motocicletas Y Piezas Sueltas",
    "sg:phone":"+34 933 72 91 53",
    "sg:postcode":"08960",
    "sg:province":"Barcelona",
    "wof:name":"Larroya Plumed Jordi",
    "wof:placetype":"venue"
},
  "geometry": {"coordinates":[2.0715699196,41.3818321228],"type":"Point"}
}