{
  "type": "Feature",
  "properties": {
    "addr:full":"Calle de Villaleal, 2 Catedral Murcia 30001",
    "addr:housenumber":"2",
    "addr:postcode":"30001",
    "addr:street":"Calle De Villaleal",
    "iso:country":"ES",
    "sg:address":"Calle de Villaleal, 2",
    "sg:city":"Catedral",
    "sg:orig_category":"Notarios",
    "sg:phone":"+34 968 21 38 72",
    "sg:postcode":"30001",
    "sg:province":"Murcia",
    "wof:name":"Navarro Nu\u00f1ez Agustin",
    "wof:placetype":"venue"
},
  "geometry": {"coordinates":[-1.1298867464,37.9834747314],"type":"Point"}
}