{
  "type": "Feature",
  "properties": {
    "iso:country":"ES",
    "sg:address":"Avda Aguirre Lehendakari, 139",
    "sg:city":"Bilbao",
    "sg:orig_category":"Madera Para Construcci\u00d3n E Industria",
    "sg:phone":"+34 944 47 14 04",
    "sg:postcode":"48015",
    "sg:province":"Vizcaya",
    "wof:name":"Carre\u00f1o Bello Evaristo",
    "wof:placetype":"venue"
},
  "geometry": {"coordinates":[-2.9602169991,43.2764930725],"type":"Point"}
}