{
  "type": "Feature",
  "properties": {
    "iso:country":"ES",
    "sg:address":"Calle de Pascual Martinez, 3",
    "sg:city":"Redovan",
    "sg:classifiers":[
        {
            "category":"Autos & Motor Vehicles",
            "subcategory":"Automobile Sales",
            "type":"Retail Goods"
        }
    ],
    "sg:phone":"+34 966 75 52 73",
    "sg:postcode":"03370",
    "sg:province":"Alicante",
    "wof:name":"Ense\u00f1auto S.l.",
    "wof:placetype":"venue"
},
  "geometry": {"coordinates":[-0.9078599811,38.1141281128],"type":"Point"}
}