{
  "type": "Feature",
  "properties": {
    "addr:full":"Calle de Santa Rita, 13 Valdefuentes C\u00e1ceres 10180",
    "addr:housenumber":"13",
    "addr:postcode":"10180",
    "addr:street":"Calle De Santa Rita;Ca\u0301Ceres",
    "iso:country":"ES",
    "sg:address":"Calle de Santa Rita, 13",
    "sg:city":"Valdefuentes",
    "sg:orig_category":"Alimentaci\u00d3n General (al Por Menor)",
    "sg:phone":"+34 927 38 85 59",
    "sg:postcode":"10180",
    "sg:province":"C\u00e1ceres",
    "wof:name":"Hidalgo Jara Rita",
    "wof:placetype":"venue"
},
  "geometry": {"coordinates":[-6.1262359619,39.2747879028],"type":"Point"}
}