{
  "type": "Feature",
  "properties": {
    "addr:full":"Ctra Sils, 34 Santa Coloma De Farners Girona 17430",
    "addr:housenumber":"34",
    "addr:postcode":"17430",
    "addr:street":"Ctra Sils",
    "iso:country":"ES",
    "sg:address":"Ctra Sils, 34",
    "sg:city":"Santa Coloma De Farners",
    "sg:orig_category":"Mec\u00c1nico Del Autom\u00d3vil",
    "sg:phone":"+34 972 84 02 74",
    "sg:postcode":"17430",
    "sg:province":"Girona",
    "wof:name":"Puba S.l.",
    "wof:placetype":"venue"
},
  "geometry": {"coordinates":[2.6743619442,41.8575630188],"type":"Point"}
}