{
  "type": "Feature",
  "properties": {
    "iso:country":"ES",
    "sg:address":"Calle de Francisco Gomez, 16",
    "sg:city":"Barakaldo",
    "sg:orig_category":"Tintorer\u00cdas, Limpieza En Seco",
    "sg:phone":"+34 944 37 96 29",
    "sg:postcode":"48902",
    "sg:province":"Vizcaya",
    "wof:name":"Antonio Galvan Gonzalez",
    "wof:placetype":"venue"
},
  "geometry": {"coordinates":[-2.9923360348,43.2958564758],"type":"Point"}
}