{
  "type": "Feature",
  "properties": {
    "addr:full":"Calle de Lorenzo Pardo, 14 Zaragoza Zaragoza 50008",
    "addr:housenumber":"14",
    "addr:postcode":"50008",
    "addr:street":"Calle De Lorenzo Pardo",
    "iso:country":"ES",
    "sg:address":"Calle de Lorenzo Pardo, 14",
    "sg:city":"Zaragoza",
    "sg:orig_category":"Garajes De Veh\u00cdculos",
    "sg:phone":"+34 976 13 34 97",
    "sg:postcode":"50008",
    "sg:province":"Zaragoza",
    "wof:name":"Talleres Otin S.l.",
    "wof:placetype":"venue"
},
  "geometry": {"coordinates":[-0.875056982,41.6434326172],"type":"Point"}
}