{
  "type": "Feature",
  "properties": {
    "addr:full":"Carr Passarell, 4 Pont D'inca Islas Baleares 07009",
    "addr:housenumber":"4",
    "addr:postcode":"07009",
    "addr:street":"Carr Passarell;Pont D'Inca",
    "iso:country":"ES",
    "sg:address":"Carr Passarell, 4",
    "sg:city":"Pont D'inca",
    "sg:orig_category":"Contenedores (mercanc\u00cdas)",
    "sg:phone":"+34 971 60 09 39",
    "sg:postcode":"07009",
    "sg:province":"Islas Baleares",
    "wof:name":"Mini Transp. Costa S.l.",
    "wof:placetype":"venue"
},
  "geometry": {"coordinates":[2.9091899395,39.7197418213],"type":"Point"}
}