{
  "type": "Feature",
  "properties": {
    "iso:country":"ES",
    "sg:address":"Calle de Puebla De Valverde, 7",
    "sg:city":"Valencia",
    "sg:orig_category":"Delegados, Agentes De Tr\u00c1nsito, Auxiliares De Transporte Internacional",
    "sg:phone":"+34 963 57 35 16",
    "sg:postcode":"46014",
    "sg:province":"Valencia",
    "wof:name":"Transportes Jose Fabra S.l.",
    "wof:placetype":"venue"
},
  "geometry": {"coordinates":[-0.4018880129,39.4599952698],"type":"Point"}
}