{
  "type": "Feature",
  "properties": {
    "iso:country":"ES",
    "sg:address":"Avda Europa (de), 10",
    "sg:city":"Alcobendas",
    "sg:orig_category":"Ingeniero",
    "sg:phone":"+34 916 62 66 76",
    "sg:postcode":"28108",
    "sg:province":"Madrid",
    "wof:name":"Systelsa S.l.",
    "wof:placetype":"venue"
},
  "geometry": {"coordinates":[-3.6594979763,40.5175857544],"type":"Point"}
}