{
  "type": "Feature",
  "properties": {
    "addr:full":"Carr Joan Burniol, 3 Mollerussa Lleida 25230",
    "addr:housenumber":"3",
    "addr:postcode":"25230",
    "addr:street":"Carr Joan Burniol",
    "iso:country":"ES",
    "sg:address":"Carr Joan Burniol, 3",
    "sg:city":"Mollerussa",
    "sg:orig_category":"Pescader\u00cdas (al Por Menor)",
    "sg:phone":"+34 973 71 18 05",
    "sg:postcode":"25230",
    "sg:province":"Lleida",
    "wof:name":"Mastermoll S.l.",
    "wof:placetype":"venue"
},
  "geometry": {"coordinates":[0.8925198913,41.6288986206],"type":"Point"}
}