{
  "type": "Feature",
  "properties": {
    "iso:country":"ES",
    "sg:address":"Av Romero(urb Montebello), 33",
    "sg:city":"Algorfa",
    "sg:orig_category":"Supermercados Y Hipermercados",
    "sg:phone":"+34 966 71 22 52",
    "sg:postcode":"03169",
    "sg:province":"Alicante",
    "wof:name":"Ellis  Elaine",
    "wof:placetype":"venue"
},
  "geometry": {"coordinates":[-0.751019001,38.0655403137],"type":"Point"}
}