{
  "type": "Feature",
  "properties": {
    "addr:full":"Calle de Pablo Rada, S/n Huelva Huelva 21004",
    "addr:housenumber":"s / n",
    "addr:postcode":"21004",
    "addr:street":"Calle De Pablo Rada",
    "iso:country":"ES",
    "sg:address":"Calle de Pablo Rada, S/n",
    "sg:city":"Huelva",
    "sg:orig_category":"Aparcamientos (infraestructuras, Accesorios)",
    "sg:phone":"+34 959 28 53 54",
    "sg:postcode":"21004",
    "sg:province":"Huelva",
    "wof:name":"Cintra Aparcamientos S.a.",
    "wof:placetype":"venue"
},
  "geometry": {"coordinates":[-6.9485812187,37.2592926025],"type":"Point"}
}