{
  "type": "Feature",
  "properties": {
    "iso:country":"ES",
    "sg:address":"Carrer de Eusebi Guell, 37",
    "sg:city":"S. Boi Llobregat",
    "sg:orig_category":"Art\u00cdculos De Decoraci\u00d3n",
    "sg:phone":"+34 936 40 94 52",
    "sg:postcode":"08830",
    "sg:province":"Barcelona",
    "wof:name":"Esmar D'art 2000 S. L.",
    "wof:placetype":"venue"
},
  "geometry": {"coordinates":[2.0337860584,41.3475112915],"type":"Point"}
}