{
  "type": "Feature",
  "properties": {
    "addr:full":"Calle de Fernandez De Oviedo, 34 Oviedo Asturias 33012",
    "addr:housenumber":"34",
    "addr:postcode":"33012",
    "addr:street":"Calle De Fernandez De Oviedo",
    "iso:country":"ES",
    "sg:address":"Calle de Fernandez De Oviedo, 34",
    "sg:city":"Oviedo",
    "sg:orig_category":"Suministros Para Hoteles",
    "sg:phone":"+34 985 11 15 71",
    "sg:postcode":"33012",
    "sg:province":"Asturias",
    "wof:name":"Asturservi",
    "wof:placetype":"venue"
},
  "geometry": {"coordinates":[-5.8558335304,43.3714561462],"type":"Point"}
}