{
  "type": "Feature",
  "properties": {
    "addr:full":"Calle de Americo Vespucio, 30 Mairena Aljarafe Sevilla 41927",
    "addr:housenumber":"30",
    "addr:postcode":"41927",
    "addr:street":"Calle De Americo Vespucio",
    "iso:country":"ES",
    "sg:address":"Calle de Americo Vespucio, 30",
    "sg:city":"Mairena Aljarafe",
    "sg:orig_category":"Chapister\u00cda",
    "sg:phone":"+34 954 18 24 81",
    "sg:postcode":"41927",
    "sg:province":"Sevilla",
    "wof:name":"Vega Caleffa Fernando De",
    "wof:placetype":"venue"
},
  "geometry": {"coordinates":[-6.0536317825,37.3506774902],"type":"Point"}
}