{
  "type": "Feature",
  "properties": {
    "addr:full":"Carrer de Dalt, 2 Sant Feliu Llobregat Barcelona 08980",
    "addr:housenumber":"2",
    "addr:postcode":"08980",
    "addr:street":"Carrer De Dalt",
    "iso:country":"ES",
    "sg:address":"Carrer de Dalt, 2",
    "sg:city":"Sant Feliu Llobregat",
    "sg:orig_category":"Asesor\u00cda Sobre Comunicaci\u00d3n De Empresas",
    "sg:phone":"+34 936 32 71 57",
    "sg:postcode":"08980",
    "sg:province":"Barcelona",
    "sg:website":"www.assessories.info",
    "wof:name":"Acosta Terron Alfonso 000693851s S.l.n.e",
    "wof:placetype":"venue"
},
  "geometry": {"coordinates":[2.0457191467,41.3831062317],"type":"Point"}
}