{
  "type": "Feature",
  "properties": {
    "iso:country":"ES",
    "sg:address":"Calle de General Artetxe, S/n",
    "sg:city":"Donostia-san Sebastian",
    "sg:orig_category":"Mec\u00c1nico Del Autom\u00d3vil",
    "sg:phone":"+34 943 27 94 48",
    "sg:postcode":"20002",
    "sg:province":"Guip\u00f9zcoa",
    "wof:name":"Talleres Easo S. L.",
    "wof:placetype":"venue"
},
  "geometry": {"coordinates":[-1.9725739956,43.3242683411],"type":"Point"}
}