{
  "type": "Feature",
  "properties": {
    "iso:country":"ES",
    "sg:address":"Pol Ind Capitana, 5",
    "sg:city":"Lebrija",
    "sg:orig_category":"Florister\u00cdas",
    "sg:phone":"+34 955 97 71 32",
    "sg:postcode":"41740",
    "sg:province":"Sevilla",
    "wof:name":"Flores De Lebrija S.l.",
    "wof:placetype":"venue"
},
  "geometry": {"coordinates":[-6.0658698082,36.9205932617],"type":"Point"}
}