{
  "type": "Feature",
  "properties": {
    "addr:full":"Avgd Reina Sofia (de La), 19 Petrer Alicante 03610",
    "addr:postcode":"03610",
    "iso:country":"ES",
    "sg:address":"Avgd Reina Sofia (de La), 19",
    "sg:city":"Petrer",
    "sg:orig_category":"Comercio, Reparaci\u00d3n De Motocicletas, Bicicletas Y Piezas Sueltas",
    "sg:phone":"+34 965 37 73 76",
    "sg:postcode":"03610",
    "sg:province":"Alicante",
    "wof:name":"Maestre Alfonso Antonio",
    "wof:placetype":"venue"
},
  "geometry": {"coordinates":[-0.7811629772,38.479095459],"type":"Point"}
}