{
  "type": "Feature",
  "properties": {
    "addr:full":"Calle de Palma (de La), 77 Pto Real C\u00e1diz 11510",
    "addr:housenumber":"77",
    "addr:postcode":"11510",
    "addr:street":"Calle De Palma De La;Ca\u0301Diz",
    "iso:country":"ES",
    "sg:address":"Calle de Palma (de La), 77",
    "sg:city":"Pto Real",
    "sg:orig_category":"Alquiler De V\u00cddeo",
    "sg:phone":"+34 956 47 42 90",
    "sg:postcode":"11510",
    "sg:province":"C\u00e1diz",
    "wof:name":"Guerrero Rodriguez Deneira Antonio",
    "wof:placetype":"venue"
},
  "geometry": {"coordinates":[-6.1890611649,36.5297737122],"type":"Point"}
}