{
  "type": "Feature",
  "properties": {
    "addr:full":"Vred Ajofrin, 5 Sonseca Toledo 45100",
    "addr:housenumber":"5",
    "addr:postcode":"45100",
    "addr:street":"Ajofrin",
    "iso:country":"ES",
    "sg:address":"Vred Ajofrin, 5",
    "sg:city":"Sonseca",
    "sg:orig_category":"Art\u00cdculos De Madera (fabricaci\u00d3n Y Al Por Mayor)",
    "sg:phone":"+34 925 38 09 58",
    "sg:postcode":"45100",
    "sg:province":"Toledo",
    "wof:name":"Cerde\u00f1o Ruiz Victor Manuel",
    "wof:placetype":"venue"
},
  "geometry": {"coordinates":[-3.9745690823,39.6818695068],"type":"Point"}
}