{
  "type": "Feature",
  "properties": {
    "addr:full":"Avda Extremadura, 108 Talavera Real Badajoz 06140",
    "addr:housenumber":"108",
    "addr:postcode":"06140",
    "addr:street":"Avda Extremadura",
    "iso:country":"ES",
    "sg:address":"Avda Extremadura, 108",
    "sg:city":"Talavera Real",
    "sg:orig_category":"Comercio De Cuadros, L\u00c1minas Y Reproducciones De Obras De Arte",
    "sg:phone":"+34 924 44 11 09",
    "sg:postcode":"06140",
    "sg:province":"Badajoz",
    "wof:name":"Caballero Quintana Jose Luis",
    "wof:placetype":"venue"
},
  "geometry": {"coordinates":[-6.7669119835,38.8750343323],"type":"Point"}
}