{
  "type": "Feature",
  "properties": {
    "addr:full":"Rua Torreira (da), 22 Santiago De Compostela La Coru\u00f1a 15898",
    "addr:housenumber":"22",
    "addr:postcode":"15898",
    "addr:street":"Rua Torreira Da;Corun\u0303A",
    "iso:country":"ES",
    "sg:address":"Rua Torreira (da), 22",
    "sg:city":"Santiago De Compostela",
    "sg:orig_category":"Molduras, Junquillos, Listones Y Molduras Perforadas",
    "sg:phone":"+34 981 57 76 69",
    "sg:postcode":"15898",
    "sg:province":"La Coru\u00f1a",
    "wof:name":"Gonzalez Vazquez Jose",
    "wof:placetype":"venue"
},
  "geometry": {"coordinates":[-8.5468139648,42.8988189697],"type":"Point"}
}