{
  "type": "Feature",
  "properties": {
    "iso:country":"ES",
    "sg:address":"Pl Esglesia, 9",
    "sg:city":"Caldes Montbui",
    "sg:orig_category":"Ropa Para Se\u00d1oras Y Caballeros (al Por Menor)",
    "sg:phone":"+34 938 65 13 51",
    "sg:postcode":"08140",
    "sg:province":"Barcelona",
    "wof:name":"Caballe Martinez Frederic",
    "wof:placetype":"venue"
},
  "geometry": {"coordinates":[2.1625039577,41.6328582764],"type":"Point"}
}