{
  "type": "Feature",
  "properties": {
    "iso:country":"ES",
    "sg:address":"Avda Zumalakarregi, 43",
    "sg:city":"Llodio",
    "sg:orig_category":"Plomeros",
    "sg:phone":"+34 946 72 10 59",
    "sg:postcode":"01400",
    "sg:province":"\u00c1lava",
    "wof:name":"Saneamientos Hermanos Fernandez S.c.",
    "wof:placetype":"venue"
},
  "geometry": {"coordinates":[-2.9639561176,43.141708374],"type":"Point"}
}