{
  "type": "Feature",
  "properties": {
    "addr:full":"Calle de San Saturnino, 5 Mutiloagoiti Navarra 31192",
    "addr:housenumber":"5",
    "addr:postcode":"31192",
    "addr:street":"Calle De San Saturnino",
    "iso:country":"ES",
    "sg:address":"Calle de San Saturnino, 5",
    "sg:city":"Mutiloagoiti",
    "sg:orig_category":"Arquitectos",
    "sg:phone":"+34 948 23 99 93",
    "sg:postcode":"31192",
    "sg:province":"Navarra",
    "wof:name":"Alcalde Cilveti Francisco Javier",
    "wof:placetype":"venue"
},
  "geometry": {"coordinates":[-1.619253993,42.8011665344],"type":"Point"}
}