{
  "type": "Feature",
  "properties": {
    "addr:full":"Calle de Ramon Y Cajal, 14 Sonseca Toledo 45100",
    "addr:housenumber":"14",
    "addr:postcode":"45100",
    "addr:street":"Calle De Ramon Y Cajal",
    "iso:country":"ES",
    "sg:address":"Calle de Ramon Y Cajal, 14",
    "sg:city":"Sonseca",
    "sg:orig_category":"Art\u00cdculos De Regalo (al Por Menor)",
    "sg:phone":"+34 925 38 15 13",
    "sg:postcode":"45100",
    "sg:province":"Toledo",
    "wof:name":"Bazar Pi\u00f1ata Cien S.a.l.",
    "wof:placetype":"venue"
},
  "geometry": {"coordinates":[-3.9812328815,39.6761016846],"type":"Point"}
}