{
  "type": "Feature",
  "properties": {
    "iso:country":"ES",
    "sg:address":"Carrer de Basilea, 11",
    "sg:city":"Barbera Valles",
    "sg:orig_category":"Cristaler\u00cdas",
    "sg:phone":"+34 937 29 51 66",
    "sg:postcode":"08210",
    "sg:province":"Barcelona",
    "wof:name":"Duaglass S.l.",
    "wof:placetype":"venue"
},
  "geometry": {"coordinates":[2.1315350533,41.5195846558],"type":"Point"}
}