{
  "type": "Feature",
  "properties": {
    "addr:full":"Carrer de Torrijos, 7 Barcelona Barcelona 08012",
    "addr:housenumber":"7",
    "addr:postcode":"08012",
    "addr:street":"Carrer De Torrijos",
    "iso:country":"ES",
    "sg:address":"Carrer de Torrijos, 7",
    "sg:city":"Barcelona",
    "sg:orig_category":"Alimentaci\u00d3n General (al Por Menor)",
    "sg:phone":"+34 932 13 56 69",
    "sg:postcode":"08012",
    "sg:province":"Barcelona",
    "wof:name":"Calvet Fite Antonio",
    "wof:placetype":"venue"
},
  "geometry": {"coordinates":[2.1593589783,41.4026756287],"type":"Point"}
}