{
  "type": "Feature",
  "properties": {
    "addr:full":"Calle de Real, 34 Santovenia Pisuerga Valladolid 47155",
    "addr:housenumber":"34",
    "addr:postcode":"47155",
    "addr:street":"Calle De Real",
    "iso:country":"ES",
    "sg:address":"Calle de Real, 34",
    "sg:city":"Santovenia Pisuerga",
    "sg:orig_category":"Cajas Para Embalar",
    "sg:phone":"+34 983 40 00 97",
    "sg:postcode":"47155",
    "sg:province":"Valladolid",
    "wof:name":"Caja Rural Del Duero",
    "wof:placetype":"venue"
},
  "geometry": {"coordinates":[-4.6883559227,41.6931877136],"type":"Point"}
}