{
  "type": "Feature",
  "properties": {
    "addr:full":"Carrer de Albacete, 10 Palma Islas Baleares 07010",
    "addr:housenumber":"10",
    "addr:postcode":"07010",
    "addr:street":"Carrer De Albacete",
    "iso:country":"ES",
    "sg:address":"Carrer de Albacete, 10",
    "sg:city":"Palma",
    "sg:orig_category":"Muebles Y Accesorios Para Cocinas Y Cuartos De Ba\u00d1o (al Por Menor)",
    "sg:phone":"+34 971 20 06 82",
    "sg:postcode":"07010",
    "sg:province":"Islas Baleares",
    "wof:name":"Komodelar S.l.",
    "wof:placetype":"venue"
},
  "geometry": {"coordinates":[2.6464951038,39.5879936218],"type":"Point"}
}