{
  "type": "Feature",
  "properties": {
    "addr:full":"Avda Hispanidad, 16 Puerto Valencia 46520",
    "addr:housenumber":"16",
    "addr:postcode":"46520",
    "addr:street":"Avda Hispanidad",
    "iso:country":"ES",
    "sg:address":"Avda Hispanidad, 16",
    "sg:city":"Puerto",
    "sg:orig_category":"Asociaciones Y Clubs Deportivos",
    "sg:phone":"+34 962 69 00 49",
    "sg:postcode":"46520",
    "sg:province":"Valencia",
    "wof:name":"Caldesidi S.a.",
    "wof:placetype":"venue"
},
  "geometry": {"coordinates":[-0.2314479947,39.6661987305],"type":"Point"}
}