{
  "type": "Feature",
  "properties": {
    "iso:country":"ES",
    "sg:address":"Calle de Velazquez, 32",
    "sg:city":"Le\u00f3n",
    "sg:orig_category":"Panader\u00cdas, Panader\u00cdas",
    "sg:phone":"+34 987 21 62 02",
    "sg:postcode":"24004",
    "sg:province":"Le\u00f3n",
    "wof:name":"Martinez Valbuena Maria De La Cruz",
    "wof:placetype":"venue"
},
  "geometry": {"coordinates":[-5.5656929016,42.5901107788],"type":"Point"}
}