{
  "type": "Feature",
  "properties": {
    "addr:full":"Carrer de Merce, 17 Premia Mar Barcelona 08330",
    "addr:housenumber":"17",
    "addr:postcode":"08330",
    "addr:street":"Carrer De Merce",
    "iso:country":"ES",
    "sg:address":"Carrer de Merce, 17",
    "sg:city":"Premia Mar",
    "sg:orig_category":"Zapatos (al Por Menor)",
    "sg:phone":"+34 937 51 10 05",
    "sg:postcode":"08330",
    "sg:province":"Barcelona",
    "wof:name":"Fernandez Mu\u00f1oz Miguel",
    "wof:placetype":"venue"
},
  "geometry": {"coordinates":[2.3539729118,41.4948120117],"type":"Point"}
}