{
  "type": "Feature",
  "properties": {
    "addr:full":"Ctra Ronda (de), 251 Almeria Almer\u00eda 04004",
    "addr:housenumber":"251",
    "addr:postcode":"04004",
    "addr:street":"Ctra Ronda De",
    "iso:country":"ES",
    "sg:address":"Ctra Ronda (de), 251",
    "sg:city":"Almeria",
    "sg:orig_category":"Lavado, Limpieza De Veh\u00cdculos",
    "sg:phone":"+34 950 25 30 05",
    "sg:postcode":"04004",
    "sg:province":"Almer\u00eda",
    "wof:name":"Berenguel Lopez Bonifacio",
    "wof:placetype":"venue"
},
  "geometry": {"coordinates":[-2.4564709663,36.8360519409],"type":"Point"}
}