{
  "type": "Feature",
  "properties": {
    "iso:country":"ES",
    "sg:address":"Calle de Delicias, 65",
    "sg:city":"Zaragoza",
    "sg:orig_category":"Perfumer\u00cda (al Por Menor)",
    "sg:phone":"+34 976 53 41 82",
    "sg:postcode":"50017",
    "sg:province":"Zaragoza",
    "wof:name":"Quilez Rodrigo S.l.",
    "wof:placetype":"venue"
},
  "geometry": {"coordinates":[-0.9044064879,41.6493911743],"type":"Point"}
}