{
  "type": "Feature",
  "properties": {
    "addr:full":"Avda Generalisimo, 47 Barbate C\u00e1diz 11160",
    "addr:housenumber":"47",
    "addr:postcode":"11160",
    "addr:street":"Avda Generalisimo",
    "iso:country":"ES",
    "sg:address":"Avda Generalisimo, 47",
    "sg:city":"Barbate",
    "sg:orig_category":"Ropa Para Se\u00d1oras (al Por Menor)",
    "sg:phone":"+34 956 43 24 01",
    "sg:postcode":"11160",
    "sg:province":"C\u00e1diz",
    "wof:name":"Reyes Romero Ana",
    "wof:placetype":"venue"
},
  "geometry": {"coordinates":[-5.920580864,36.1910247803],"type":"Point"}
}