{
  "type": "Feature",
  "properties": {
    "addr:full":"Calle de Santa Engracia, 122 Madrid Madrid 28003",
    "addr:housenumber":"122",
    "addr:postcode":"28003",
    "addr:street":"Calle De Santa Engracia",
    "iso:country":"ES",
    "sg:address":"Calle de Santa Engracia, 122",
    "sg:city":"Madrid",
    "sg:orig_category":"M\u00c9dicos: Radioterapia (radioterapia Como Opci\u00d3n Oncol\u00d3gica)",
    "sg:phone":"+34 913 99 52 10",
    "sg:postcode":"28003",
    "sg:province":"Madrid",
    "wof:name":"Ramirez Guitian Fernando",
    "wof:placetype":"venue"
},
  "geometry": {"coordinates":[-3.7012600899,40.4412155151],"type":"Point"}
}