{
  "type": "Feature",
  "properties": {
    "iso:country":"ES",
    "sg:address":"Calle de Poeta Mu\u00d1oz San Roman, 77",
    "sg:city":"Camas",
    "sg:orig_category":"Suministros Para Hoteles",
    "sg:phone":"+34 954 39 24 83",
    "sg:postcode":"41900",
    "sg:province":"Sevilla",
    "wof:name":"Hiperhosteleria Medina S.l.",
    "wof:placetype":"venue"
},
  "geometry": {"coordinates":[-6.033208847,37.392791748],"type":"Point"}
}