{
  "type": "Feature",
  "properties": {
    "addr:full":"Carr Joaquin Rodrigo, 4 Faura Valencia 46512",
    "addr:housenumber":"4",
    "addr:postcode":"46512",
    "addr:street":"Carr Joaquin Rodrigo",
    "iso:country":"ES",
    "sg:address":"Carr Joaquin Rodrigo, 4",
    "sg:city":"Faura",
    "sg:orig_category":"Fabricaci\u00d3n De Enlosados, Soler\u00cdas",
    "sg:phone":"+34 962 60 20 85",
    "sg:postcode":"46512",
    "sg:province":"Valencia",
    "wof:name":"Salvador Perez Maria Del Carmen",
    "wof:placetype":"venue"
},
  "geometry": {"coordinates":[-0.2635760009,39.7260971069],"type":"Point"}
}