{
  "type": "Feature",
  "properties": {
    "iso:country":"ES",
    "sg:address":"Calle de Bizkaia, 14",
    "sg:city":"Legizamon",
    "sg:orig_category":"Productores Recolectores, Venta Directa De Vinos",
    "sg:phone":"+34 944 49 58 39",
    "sg:postcode":"48450",
    "sg:province":"Vizcaya",
    "wof:name":"Bodegas Murillo Viteri C.b.",
    "wof:placetype":"venue"
},
  "geometry": {"coordinates":[-2.8923289776,43.2517204285],"type":"Point"}
}