{
  "type": "Feature",
  "properties": {
    "addr:full":"Avda San Julian, 1 Cuenca Cuenca 16003",
    "addr:housenumber":"1",
    "addr:postcode":"16003",
    "addr:street":"Avda San Julian",
    "iso:country":"ES",
    "sg:address":"Avda San Julian, 1",
    "sg:city":"Cuenca",
    "sg:orig_category":"M\u00c9dicos: Cirug\u00cda General",
    "sg:phone":"+34 969 22 90 75",
    "sg:postcode":"16003",
    "sg:province":"Cuenca",
    "wof:name":"Espa\u00f1a Vera C.b.",
    "wof:placetype":"venue"
},
  "geometry": {"coordinates":[-2.1448569298,40.0672950745],"type":"Point"}
}