{
  "type": "Feature",
  "properties": {
    "addr:full":"Pg Estacio, 51 Balaguer Lleida 25600",
    "addr:housenumber":"51",
    "addr:postcode":"25600",
    "addr:street":"Pg Estacio",
    "iso:country":"ES",
    "sg:address":"Pg Estacio, 51",
    "sg:city":"Balaguer",
    "sg:orig_category":"Comercio, Reparaci\u00d3n De Motocicletas, Bicicletas Y Piezas Sueltas",
    "sg:phone":"+34 973 45 14 65",
    "sg:postcode":"25600",
    "sg:province":"Lleida",
    "wof:name":"Sportmoto S.c.p.",
    "wof:placetype":"venue"
},
  "geometry": {"coordinates":[0.8111799955,41.7892417908],"type":"Point"}
}