{
  "type": "Feature",
  "properties": {
    "addr:full":"Ptge Olive, 3 Cerdanyola Valles Barcelona 08290",
    "addr:housenumber":"3",
    "addr:postcode":"08290",
    "addr:street":"Ptge Olive;Valles Barcelona",
    "iso:country":"ES",
    "sg:address":"Ptge Olive, 3",
    "sg:city":"Cerdanyola Valles",
    "sg:orig_category":"Perreras, Pensiones Para Perros, Gatos Y Otros Animales",
    "sg:phone":"+34 936 91 70 36",
    "sg:postcode":"08290",
    "sg:province":"Barcelona",
    "wof:name":"Cuenca Gomez Diego",
    "wof:placetype":"venue"
},
  "geometry": {"coordinates":[2.1321790218,41.4818267822],"type":"Point"}
}