{
  "type": "Feature",
  "properties": {
    "iso:country":"ES",
    "sg:address":"Avda Ramon Y Cajal, 38",
    "sg:city":"Fuengirola",
    "sg:orig_category":"Ambulancias",
    "sg:phone":"+34 952 46 14 44",
    "sg:postcode":"29640",
    "sg:province":"M\u00e1laga",
    "wof:name":"Angeles Nocturnos Rondamar Costa Del Sol S.l.",
    "wof:placetype":"venue"
},
  "geometry": {"coordinates":[-4.6193580627,36.5458030701],"type":"Point"}
}