{
  "type": "Feature",
  "properties": {
    "addr:full":"Calle de Timoteo Perez Rubio, 4 Madrid Madrid 28018",
    "addr:housenumber":"4",
    "addr:postcode":"28018",
    "addr:street":"Calle De Timoteo Perez Rubio",
    "iso:country":"ES",
    "sg:address":"Calle de Timoteo Perez Rubio, 4",
    "sg:city":"Madrid",
    "sg:orig_category":"Electromec\u00c1nica",
    "sg:phone":"+34 917 85 52 46",
    "sg:postcode":"28018",
    "sg:province":"Madrid",
    "wof:name":"Alston Transporte S.a.",
    "wof:placetype":"venue"
},
  "geometry": {"coordinates":[-3.6748371124,40.3851737976],"type":"Point"}
}