{
  "type": "Feature",
  "properties": {
    "addr:full":"Av Cortes Valencianas, 25 Albal Valencia 46470",
    "addr:housenumber":"25",
    "addr:postcode":"46470",
    "addr:street":"Av Cortes Valencianas",
    "iso:country":"ES",
    "sg:address":"Av Cortes Valencianas, 25",
    "sg:city":"Albal",
    "sg:orig_category":"Arquitectos",
    "sg:phone":"+34 961 26 63 78",
    "sg:postcode":"46470",
    "sg:province":"Valencia",
    "wof:name":"Porcar Mu\u00f1oz Angel",
    "wof:placetype":"venue"
},
  "geometry": {"coordinates":[-0.4115430117,39.3968582153],"type":"Point"}
}