{
  "type": "Feature",
  "properties": {
    "iso:country":"ES",
    "sg:address":"Plaz Ribadeo, 1",
    "sg:city":"Madrid",
    "sg:orig_category":"Asesor\u00cda Sobre Comunicaci\u00d3n De Empresas",
    "sg:phone":"+34 917 38 95 52",
    "sg:postcode":"28029",
    "sg:province":"Madrid",
    "wof:name":"Velasco Covaleda Antonio Angel",
    "wof:placetype":"venue"
},
  "geometry": {"coordinates":[-3.7107019424,40.477848053],"type":"Point"}
}