{
  "type": "Feature",
  "properties": {
    "addr:full":"Carrer de Camps I Fabres, 3 Barcelona Barcelona 08006",
    "addr:housenumber":"3",
    "addr:postcode":"08006",
    "addr:street":"Carrer De Camps I Fabres",
    "iso:country":"ES",
    "sg:address":"Carrer de Camps I Fabres, 3",
    "sg:city":"Barcelona",
    "sg:orig_category":"Promotores Constructores",
    "sg:phone":"+34 932 18 19 08",
    "sg:postcode":"08006",
    "sg:province":"Barcelona",
    "wof:name":"Productos Pam S.a",
    "wof:placetype":"venue"
},
  "geometry": {"coordinates":[2.1495490074,41.4034385681],"type":"Point"}
}