{
  "type": "Feature",
  "properties": {
    "iso:country":"ES",
    "sg:address":"Carrer de Calvet, 15",
    "sg:city":"Barcelona",
    "sg:orig_category":"Panader\u00cdas, Panader\u00cdas",
    "sg:phone":"+34 932 09 59 17",
    "sg:postcode":"08021",
    "sg:province":"Barcelona",
    "wof:name":"Canal Cubinsa Javier",
    "wof:placetype":"venue"
},
  "geometry": {"coordinates":[2.1442630291,41.3939170837],"type":"Point"}
}