{
  "type": "Feature",
  "properties": {
    "addr:full":"Ipar Kalea, 1 Zarautz Guip\u00f9zcoa 20800",
    "addr:housenumber":"1",
    "addr:postcode":"20800",
    "addr:street":"Ipar Kalea;Guipu\u0300Zcoa",
    "iso:country":"ES",
    "sg:address":"Ipar Kalea, 1",
    "sg:city":"Zarautz",
    "sg:orig_category":"Peluquer\u00cdas, Peluquer\u00cda Mixta",
    "sg:phone":"+34 943 13 40 96",
    "sg:postcode":"20800",
    "sg:province":"Guip\u00f9zcoa",
    "wof:name":"Trejos Campos Eusebia",
    "wof:placetype":"venue"
},
  "geometry": {"coordinates":[-2.1765229702,43.2854804993],"type":"Point"}
}