{
  "type": "Feature",
  "properties": {
    "iso:country":"ES",
    "sg:address":"Avda Navarra, 71",
    "sg:city":"Errenteria",
    "sg:orig_category":"Cl\u00cdnicas Dentales",
    "sg:phone":"+34 943 52 44 16",
    "sg:postcode":"20100",
    "sg:province":"Guip\u00f9zcoa",
    "wof:name":"Arbide Tolosa, Pedro",
    "wof:placetype":"venue"
},
  "geometry": {"coordinates":[-1.9022917747,43.3148345947],"type":"Point"}
}