{
  "type": "Feature",
  "properties": {
    "iso:country":"ES",
    "sg:address":"Avenida San Isidro, 37",
    "sg:city":"Losar Vera",
    "sg:orig_category":"Cajas De Ahorro",
    "sg:phone":"+34 927 57 02 98",
    "sg:postcode":"10460",
    "sg:province":"C\u00e1ceres",
    "wof:name":"Caja De Ahorros Y Monte De Piedad De Extremadura",
    "wof:placetype":"venue"
},
  "geometry": {"coordinates":[-5.6094250679,40.1218147278],"type":"Point"}
}