{
  "type": "Feature",
  "properties": {
    "iso:country":"ES",
    "sg:address":"Calle de Sancho Garcia, 2",
    "sg:city":"Sepulveda",
    "sg:orig_category":"Bazares, Art\u00cdculos De Limpieza Y De Cocina (al Por Menor)",
    "sg:phone":"+34 921 54 05 44",
    "sg:postcode":"40300",
    "sg:province":"Segovia",
    "wof:name":"Garcia Esteban Maria",
    "wof:placetype":"venue"
},
  "geometry": {"coordinates":[-3.748609066,41.296787262],"type":"Point"}
}