{
  "type": "Feature",
  "properties": {
    "addr:full":"R\u00edo Tajo, S/n Zorita De Los Canes Guip\u00f9zcoa 20750",
    "addr:housenumber":"s / n",
    "addr:postcode":"20750",
    "iso:country":"ES",
    "sg:address":"R\u00edo Tajo, S/n",
    "sg:city":"Zorita De Los Canes",
    "sg:orig_category":"Hormig\u00d3n Listo Para Usar",
    "sg:phone":"+34 943 14 32 37",
    "sg:postcode":"20750",
    "sg:province":"Guip\u00f9zcoa",
    "wof:name":"Pavimentos Bizkor S.l.",
    "wof:placetype":"venue"
},
  "geometry": {"coordinates":[-2.2583589554,43.2942314148],"type":"Point"}
}