{
  "type": "Feature",
  "properties": {
    "addr:full":"Cmno Viejo De Cascante, 9 Ablitas Navarra 31523",
    "addr:housenumber":"9",
    "addr:postcode":"31523",
    "addr:street":"Cmno Viejo De Cascante",
    "iso:country":"ES",
    "sg:address":"Cmno Viejo De Cascante, 9",
    "sg:city":"Ablitas",
    "sg:orig_category":"Empresas De Carpinter\u00cda De Madera",
    "sg:phone":"+34 948 81 32 71",
    "sg:postcode":"31523",
    "sg:province":"Navarra",
    "wof:name":"Construcciones Laguna De Lor S.l.",
    "wof:placetype":"venue"
},
  "geometry": {"coordinates":[-1.6414179802,41.9750175476],"type":"Point"}
}