{
  "type": "Feature",
  "properties": {
    "addr:full":"Calle de Antonio Zamora, 103 Madrid Madrid 28011",
    "addr:housenumber":"103",
    "addr:postcode":"28011",
    "addr:street":"Calle De Antonio Zamora",
    "iso:country":"ES",
    "sg:address":"Calle de Antonio Zamora, 103",
    "sg:city":"Madrid",
    "sg:orig_category":"Venta, Localizaci\u00d3n, Reparaci\u00d3n De Material E Instrumental M\u00c9dico",
    "sg:phone":"+34 914 63 70 70",
    "sg:postcode":"28011",
    "sg:province":"Madrid",
    "wof:name":"Guadarrama Quirotec S.l.l.",
    "wof:placetype":"venue"
},
  "geometry": {"coordinates":[-3.7339043617,40.4112510681],"type":"Point"}
}