{
  "type": "Feature",
  "properties": {
    "iso:country":"ES",
    "sg:address":"Calle de Mayor, 4",
    "sg:city":"Pedraza",
    "sg:orig_category":"Artesan\u00cda",
    "sg:phone":"+34 921 50 98 23",
    "sg:postcode":"40172",
    "sg:province":"Segovia",
    "wof:name":"Artesania Y Color S.l.",
    "wof:placetype":"venue"
},
  "geometry": {"coordinates":[-3.8129775524,41.1316490173],"type":"Point"}
}