{
  "type": "Feature",
  "properties": {
    "iso:country":"ES",
    "sg:address":"Carr Metge Segarra, 4",
    "sg:city":"Benicasim",
    "sg:orig_category":"Administraciones Regionales, Departamentales Y Locales",
    "sg:phone":"+34 964 30 09 62",
    "sg:postcode":"12560",
    "sg:province":"Castell\u00f3n",
    "sg:website":"www.benicassim.org",
    "wof:name":"Ayuntamiento De Benicasim",
    "wof:placetype":"venue"
},
  "geometry": {"coordinates":[0.0457400009,40.0510292053],"type":"Point"}
}