{
  "type": "Feature",
  "properties": {
    "iso:country":"ES",
    "sg:address":"Av Marignane, 6",
    "sg:city":"Figueres",
    "sg:orig_category":"Clubes, Asociaciones De Ocio",
    "sg:phone":"+34 972 51 43 38",
    "sg:postcode":"17600",
    "sg:province":"Girona",
    "wof:name":"Military Surplus S.l.u.",
    "wof:placetype":"venue"
},
  "geometry": {"coordinates":[2.9577729702,42.2707595825],"type":"Point"}
}