{
  "type": "Feature",
  "properties": {
    "iso:country":"ES",
    "sg:address":"Calle de San Carlos, 15",
    "sg:city":"Valdepe\u00f1as",
    "sg:orig_category":"Tapicer\u00cdas",
    "sg:phone":"+34 926 32 44 01",
    "sg:postcode":"13300",
    "sg:province":"Ciudad Real",
    "wof:name":"Ruiz Martin Ramon",
    "wof:placetype":"venue"
},
  "geometry": {"coordinates":[-3.3763859272,38.7676086426],"type":"Point"}
}