{
  "type": "Feature",
  "properties": {
    "addr:full":"Calle de Bravo Murillo, 19 Badajoz Badajoz 06002",
    "addr:housenumber":"19",
    "addr:postcode":"06002",
    "addr:street":"Calle De Bravo Murillo",
    "iso:country":"ES",
    "sg:address":"Calle de Bravo Murillo, 19",
    "sg:city":"Badajoz",
    "sg:orig_category":"Centros Empresariales",
    "sg:phone":"+34 924 23 47 58",
    "sg:postcode":"06002",
    "sg:province":"Badajoz",
    "wof:name":"Fernandez Aveiro Cremilde Maria",
    "wof:placetype":"venue"
},
  "geometry": {"coordinates":[-6.9674077034,38.8793144226],"type":"Point"}
}