{
  "type": "Feature",
  "properties": {
    "iso:country":"ES",
    "sg:address":"Carrer de Carme, 15",
    "sg:city":"Castelldefels",
    "sg:orig_category":"Agencias Y Asesores De Publicidad",
    "sg:phone":"+34 936 65 11 06",
    "sg:postcode":"08860",
    "sg:province":"Barcelona",
    "wof:name":"Canicio Suarez Carmen",
    "wof:placetype":"venue"
},
  "geometry": {"coordinates":[1.9714499712,41.2656593323],"type":"Point"}
}