{
  "type": "Feature",
  "properties": {
    "addr:full":"Calle de Cuatro Torres, 4 Jaen Ja\u00e9n 23001",
    "addr:housenumber":"4;jae\u0301n",
    "addr:postcode":"23001",
    "addr:street":"Calle De Cuatro Torres",
    "iso:country":"ES",
    "sg:address":"Calle de Cuatro Torres, 4",
    "sg:city":"Jaen",
    "sg:orig_category":"Muebles, Minoristas",
    "sg:phone":"+34 953 24 29 05",
    "sg:postcode":"23001",
    "sg:province":"Ja\u00e9n",
    "wof:name":"Hernandez Alvarez Inmaculada",
    "wof:placetype":"venue"
},
  "geometry": {"coordinates":[-3.7869906425,37.7675666809],"type":"Point"}
}