{
  "type": "Feature",
  "properties": {
    "iso:country":"ES",
    "sg:address":"Calle de Pedro Viruela, 24",
    "sg:city":"Vall D'uixo",
    "sg:orig_category":"Asociaciones Humanitarias, De Cooperaci\u00d3n, De Acci\u00d3n Social",
    "sg:phone":"+34 964 66 02 86",
    "sg:postcode":"12600",
    "sg:province":"Castell\u00f3n",
    "wof:name":"Afanias",
    "wof:placetype":"venue"
},
  "geometry": {"coordinates":[-0.234988302,39.8221321106],"type":"Point"}
}