{
  "type": "Feature",
  "properties": {
    "iso:country":"ES",
    "sg:address":"Avda Italia, 103",
    "sg:city":"Huelva",
    "sg:orig_category":"Peluquer\u00cdas, Peluquer\u00cda Mixta",
    "sg:phone":"+34 959 25 31 72",
    "sg:postcode":"21001",
    "sg:province":"Huelva",
    "wof:name":"Estevez Mesa Maria Del Carmen",
    "wof:placetype":"venue"
},
  "geometry": {"coordinates":[-6.9513487816,37.2536582947],"type":"Point"}
}