{
  "type": "Feature",
  "properties": {
    "iso:country":"ES",
    "sg:address":"Carrer de Alexandre Gali, 20",
    "sg:city":"Barcelona",
    "sg:orig_category":"Asociaciones, Organismos Culturales Y Socioeducativos",
    "sg:phone":"+34 933 52 37 53",
    "sg:postcode":"08027",
    "sg:province":"Barcelona",
    "wof:name":"Agrupacion Coro Y Danza Congreso",
    "wof:placetype":"venue"
},
  "geometry": {"coordinates":[2.1804432869,41.4246940613],"type":"Point"}
}