{
  "type": "Feature",
  "properties": {
    "addr:full":"Plaz Cueva Santa, 8 Altura Castell\u00f3n 12410",
    "addr:housenumber":"8",
    "addr:postcode":"12410",
    "addr:street":"Santa",
    "iso:country":"ES",
    "sg:address":"Plaz Cueva Santa, 8",
    "sg:city":"Altura",
    "sg:orig_category":"Cajas De Ahorro",
    "sg:phone":"+34 964 14 65 14",
    "sg:postcode":"12410",
    "sg:province":"Castell\u00f3n",
    "sg:website":"www.bancaja.es",
    "wof:name":"Caja De Ahorros De Valencia Castellon Y Alicante",
    "wof:placetype":"venue"
},
  "geometry": {"coordinates":[-0.5144039989,39.8478736877],"type":"Point"}
}