{
  "type": "Feature",
  "properties": {
    "addr:full":"Prim, 8 Muros La Coru\u00f1a 15250",
    "addr:housenumber":"8",
    "addr:postcode":"15250",
    "addr:street":"Prim;La Corun\u0303A",
    "iso:country":"ES",
    "sg:address":"Prim, 8",
    "sg:city":"Muros",
    "sg:orig_category":"Telas Y Sedas (al Por Menor)",
    "sg:phone":"+34 981 82 77 17",
    "sg:postcode":"15250",
    "sg:province":"La Coru\u00f1a",
    "wof:name":"Beiro Blanco Maria Del Carmen",
    "wof:placetype":"venue"
},
  "geometry": {"coordinates":[-9.0582790375,42.7751655579],"type":"Point"}
}