{
  "type": "Feature",
  "properties": {
    "addr:full":"Calle de Ollaga, 3 Astrabudua Vizcaya 48950",
    "addr:housenumber":"3",
    "addr:postcode":"48950",
    "addr:street":"Calle De Ollaga",
    "iso:country":"ES",
    "sg:address":"Calle de Ollaga, 3",
    "sg:city":"Astrabudua",
    "sg:orig_category":"Decoraci\u00d3n: Instalaci\u00d3n Y Talleres",
    "sg:phone":"+34 944 67 00 10",
    "sg:postcode":"48950",
    "sg:province":"Vizcaya",
    "wof:name":"Muebles Rivor S.l.",
    "wof:placetype":"venue"
},
  "geometry": {"coordinates":[-2.9817650318,43.3164901733],"type":"Point"}
}