{
  "type": "Feature",
  "properties": {
    "addr:full":"Avda Reina Sofia, 1 Peligros Granada 18210",
    "addr:housenumber":"1",
    "addr:postcode":"18210",
    "addr:street":"Avda Reina Sofia",
    "iso:country":"ES",
    "sg:address":"Avda Reina Sofia, 1",
    "sg:city":"Peligros",
    "sg:orig_category":"Inmobiliaria (agencias)",
    "sg:phone":"+34 958 40 10 67",
    "sg:postcode":"18210",
    "sg:province":"Granada",
    "wof:name":"Asesoria Arantave",
    "wof:placetype":"venue"
},
  "geometry": {"coordinates":[-3.6337325573,37.2319564819],"type":"Point"}
}