{
  "type": "Feature",
  "properties": {
    "iso:country":"ES",
    "sg:address":"Carr Sant Pau, 18",
    "sg:city":"Solsona",
    "sg:orig_category":"Tintes (fabricaci\u00d3n, Al Por Mayor)",
    "sg:phone":"+34 973 48 01 33",
    "sg:postcode":"25280",
    "sg:province":"Lleida",
    "wof:name":"Planas Graell Marta",
    "wof:placetype":"venue"
},
  "geometry": {"coordinates":[1.5582829714,41.9756584167],"type":"Point"}
}