{
  "type": "Feature",
  "properties": {
    "iso:country":"ES",
    "sg:address":"Rua Fray Lois Rodriguez, 8",
    "sg:city":"Noia",
    "sg:orig_category":"Tintes (fabricaci\u00d3n, Al Por Mayor)",
    "sg:phone":"+34 981 82 50 34",
    "sg:postcode":"15200",
    "sg:province":"A Coru\u00f1a",
    "wof:name":"Tintoreria Carma S.c.",
    "wof:placetype":"venue"
},
  "geometry": {"coordinates":[-8.8867359161,42.7864646912],"type":"Point"}
}