{
  "type": "Feature",
  "properties": {
    "addr:full":"Calle de Juan Ortega, 11 Pedro\u00d1eras Cuenca 16660",
    "addr:housenumber":"11",
    "addr:postcode":"16660",
    "addr:street":"Calle De Juan Ortega",
    "iso:country":"ES",
    "sg:address":"Calle de Juan Ortega, 11",
    "sg:city":"Pedro\u00d1eras",
    "sg:orig_category":"Inform\u00c1tica: Material Y Suministros",
    "sg:phone":"+34 967 16 30 48",
    "sg:postcode":"16660",
    "sg:province":"Cuenca",
    "wof:name":"Mega Informatica Pedro\u00f1eros S.l",
    "wof:placetype":"venue"
},
  "geometry": {"coordinates":[-2.6703429222,39.4458045959],"type":"Point"}
}