{
  "type": "Feature",
  "properties": {
    "iso:country":"ES",
    "sg:address":"Avda Doctor Fleming, 10",
    "sg:city":"Bujalance",
    "sg:orig_category":"Inform\u00c1tica, Ofim\u00c1tica (estudios, Asesor\u00cda, Ingenier\u00cda, Formaci\u00d3n)",
    "sg:phone":"+34 957 17 00 66",
    "sg:postcode":"14650",
    "sg:province":"C\u00f3rdoba",
    "sg:website":"www.servintel.net",
    "wof:name":"Suministros Informaticos Alto Guadalquivir S.l.l.",
    "wof:placetype":"venue"
},
  "geometry": {"coordinates":[-4.3803319931,37.8942337036],"type":"Point"}
}