{
  "type": "Feature",
  "properties": {
    "addr:full":"Calle de Sebastian Elcano, 32 Sevilla Sevilla 41011",
    "addr:housenumber":"32",
    "addr:postcode":"41011",
    "addr:street":"Calle De Sebastian Elcano",
    "iso:country":"ES",
    "sg:address":"Calle de Sebastian Elcano, 32",
    "sg:city":"Sevilla",
    "sg:orig_category":"Alimentaci\u00d3n General (al Por Menor)",
    "sg:phone":"+34 954 27 35 57",
    "sg:postcode":"41011",
    "sg:province":"Sevilla",
    "wof:name":"Montero Fernandez Maria Rosa",
    "wof:placetype":"venue"
},
  "geometry": {"coordinates":[-5.9962120056,37.3744468689],"type":"Point"}
}