{
  "type": "Feature",
  "properties": {
    "addr:full":"Calle de Jose Antonio, 9 Galvez Toledo 45164",
    "addr:housenumber":"9",
    "addr:postcode":"45164",
    "addr:street":"Calle De Jose Antonio",
    "iso:country":"ES",
    "sg:address":"Calle de Jose Antonio, 9",
    "sg:city":"Galvez",
    "sg:orig_category":"Frutas, Legumbres Frescas Y Tempranas (al Por Menor)",
    "sg:phone":"+34 925 40 07 41",
    "sg:postcode":"45164",
    "sg:province":"Toledo",
    "wof:name":"Villardon Manrique Julian",
    "wof:placetype":"venue"
},
  "geometry": {"coordinates":[-4.2743592262,39.7034187317],"type":"Point"}
}