{
  "type": "Feature",
  "properties": {
    "iso:country":"ES",
    "sg:address":"Calle de Londres, 10",
    "sg:city":"Benidorm",
    "sg:orig_category":"Molduras, Junquillos, Listones Y Molduras Perforadas",
    "sg:phone":"+34 966 80 49 32",
    "sg:postcode":"03500",
    "sg:province":"Alicante",
    "wof:name":"Ejido Garcia Jose Alberto",
    "wof:placetype":"venue"
},
  "geometry": {"coordinates":[-0.1030389965,38.5363769531],"type":"Point"}
}