{
  "type": "Feature",
  "properties": {
    "iso:country":"ES",
    "sg:address":"Bo San Carlos, S/n",
    "sg:city":"Redovan",
    "sg:orig_category":"Inmobiliaria (agencias)",
    "sg:phone":"+34 966 75 54 74",
    "sg:postcode":"03370",
    "sg:province":"Alicante",
    "wof:name":"Inmobilien Eurocostablanca S.l",
    "wof:placetype":"venue"
},
  "geometry": {"coordinates":[-0.9070389867,38.1119689941],"type":"Point"}
}