{
  "type": "Feature",
  "properties": {
    "iso:country":"ES",
    "sg:address":"Avda Bruselas (de), 13",
    "sg:city":"Alcobendas",
    "sg:orig_category":"Inform\u00c1tica Equipo Y Programas (al Por Mayor)",
    "sg:phone":"+34 916 57 55 00",
    "sg:postcode":"28...",
    "sg:province":"Madrid",
    "sg:website":"www.fujitsu-siemens.es",
    "wof:name":"Fujitsu Siemens Computers",
    "wof:placetype":"venue"
},
  "geometry": {"coordinates":[-3.6344099045,40.5313339233],"type":"Point"}
}