{
  "type": "Feature",
  "properties": {
    "addr:full":"Av Matadepera, 135 Sabadell Barcelona 08207",
    "addr:housenumber":"135",
    "addr:postcode":"08207",
    "addr:street":"Av Matadepera",
    "iso:country":"ES",
    "sg:address":"Av Matadepera, 135",
    "sg:city":"Sabadell",
    "sg:orig_category":"Bazares, Art\u00cdculos De Limpieza Y De Cocina (al Por Menor)",
    "sg:phone":"+34 937 16 87 56",
    "sg:postcode":"08207",
    "sg:province":"Barcelona",
    "wof:name":"D.m.q.t. S.l.",
    "wof:placetype":"venue"
},
  "geometry": {"coordinates":[2.0885910988,41.5670585632],"type":"Point"}
}