{
  "type": "Feature",
  "properties": {
    "iso:country":"ES",
    "sg:address":"Carr Dolors, S/n",
    "sg:city":"Ma\u00e7anet Selva",
    "sg:orig_category":"Molduras, Junquillos, Listones Y Molduras Perforadas",
    "sg:phone":"+34 972 16 51 60",
    "sg:postcode":"17412",
    "sg:province":"Girona",
    "wof:name":"Almiron Arroyo Rafael",
    "wof:placetype":"venue"
},
  "geometry": {"coordinates":[2.7333557606,41.7781105042],"type":"Point"}
}