{
  "type": "Feature",
  "properties": {
    "addr:full":"Calle de Toreros, 1 Valladolid Valladolid 47007",
    "addr:housenumber":"1",
    "addr:postcode":"47007",
    "addr:street":"Calle De Toreros",
    "iso:country":"ES",
    "sg:address":"Calle de Toreros, 1",
    "sg:city":"Valladolid",
    "sg:orig_category":"Telas Y Sedas (al Por Menor)",
    "sg:phone":"+34 983 22 25 71",
    "sg:postcode":"47007",
    "sg:province":"Valladolid",
    "wof:name":"Herrero Serrano Manuela Transito",
    "wof:placetype":"venue"
},
  "geometry": {"coordinates":[-4.7359390259,41.6365280151],"type":"Point"}
}