{
  "type": "Feature",
  "properties": {
    "addr:full":"Altamira, 17 Altamira Pontevedra 36967",
    "addr:housenumber":"17",
    "addr:postcode":"36967",
    "addr:street":"Altamira",
    "iso:country":"ES",
    "sg:address":"Altamira, 17",
    "sg:city":"Altamira",
    "sg:orig_category":"Agricultura: Abastecimiento Y Cosechado (negocio)",
    "sg:phone":"+34 986 74 42 77",
    "sg:postcode":"36967",
    "sg:province":"Pontevedra",
    "wof:name":"Sineiro Besada Maria Del Carmen",
    "wof:placetype":"venue"
},
  "geometry": {"coordinates":[-8.8113698959,42.4530296326],"type":"Point"}
}