{
  "type": "Feature",
  "properties": {
    "iso:country":"ES",
    "sg:address":"Carrer de Dega Bahi, 6",
    "sg:city":"Barcelona",
    "sg:orig_category":"Inform\u00c1tica (estudios, Servicios, Asesor\u00cda, Formaci\u00d3n)",
    "sg:phone":"+34 934 56 11 78",
    "sg:postcode":"08026",
    "sg:province":"Barcelona",
    "wof:name":"Tising S.l.(zabala",
    "wof:placetype":"venue"
},
  "geometry": {"coordinates":[2.1832060814,41.410610199],"type":"Point"}
}