{
  "type": "Feature",
  "properties": {
    "addr:full":"Calle de Salvador Dali, 7 Illescas Toledo 45200",
    "addr:housenumber":"7",
    "addr:postcode":"45200",
    "addr:street":"Calle De Salvador Dali",
    "iso:country":"ES",
    "sg:address":"Calle de Salvador Dali, 7",
    "sg:city":"Illescas",
    "sg:orig_category":"Fisioterapia",
    "sg:phone":"+34 925 59 26 54",
    "sg:postcode":"45200",
    "sg:province":"Toledo",
    "wof:name":"Macias Mora Maria Rosario",
    "wof:placetype":"venue"
},
  "geometry": {"coordinates":[-3.8489439487,40.1200065613],"type":"Point"}
}