{
  "type": "Feature",
  "properties": {
    "addr:full":"Calle de Magallanes, 11 Madrid Madrid 28015",
    "addr:housenumber":"11",
    "addr:postcode":"madrid;28015",
    "addr:street":"Calle De Magallanes",
    "iso:country":"ES",
    "sg:address":"Calle de Magallanes, 11",
    "sg:city":"Madrid",
    "sg:orig_category":"Bricolaje, Herramientas (al Por Menor)",
    "sg:phone":"+34 915 93 30 01",
    "sg:postcode":"28015",
    "sg:province":"Madrid",
    "wof:name":"Bricolaje Don Util S.l",
    "wof:placetype":"venue"
},
  "geometry": {"coordinates":[-3.7058401108,40.43409729],"type":"Point"}
}