{
  "type": "Feature",
  "properties": {
    "addr:full":"Calle de Gordoniz, 39 Bilbao Vizcaya 48012",
    "addr:housenumber":"39",
    "addr:postcode":"48012",
    "addr:street":"Calle De Gordoniz",
    "iso:country":"ES",
    "sg:address":"Calle de Gordoniz, 39",
    "sg:city":"Bilbao",
    "sg:orig_category":"Fabricaci\u00d3n, Instalaci\u00d3n De Armarios",
    "sg:phone":"+34 944 21 57 87",
    "sg:postcode":"48012",
    "sg:province":"Vizcaya",
    "wof:name":"Armarios Capape S.l.",
    "wof:placetype":"venue"
},
  "geometry": {"coordinates":[-2.9423406124,43.256690979],"type":"Point"}
}