{
  "type": "Feature",
  "properties": {
    "addr:full":"Calle de Empedrada, 7 Vegadeo Asturias 33770",
    "addr:housenumber":"7",
    "addr:postcode":"33770",
    "addr:street":"Calle De Empedrada",
    "iso:country":"ES",
    "sg:address":"Calle de Empedrada, 7",
    "sg:city":"Vegadeo",
    "sg:orig_category":"Zapatos (al Por Menor)",
    "sg:phone":"+34 985 63 40 58",
    "sg:postcode":"33770",
    "sg:province":"Asturias",
    "wof:name":"Alonso Arias Juan Antonio",
    "wof:placetype":"venue"
},
  "geometry": {"coordinates":[-7.0491576195,43.4643249512],"type":"Point"}
}