{
  "type": "Feature",
  "properties": {
    "addr:full":"Calle de Barrionuevo, 4 Madrid Madrid 28011",
    "addr:housenumber":"4",
    "addr:postcode":"28011",
    "addr:street":"Calle De Barrionuevo",
    "iso:country":"ES",
    "sg:address":"Calle de Barrionuevo, 4",
    "sg:city":"Madrid",
    "sg:orig_category":"Peluquer\u00cdas, Peluquer\u00cda Mixta",
    "sg:phone":"+34 914 79 93 56",
    "sg:postcode":"28011",
    "sg:province":"Madrid",
    "wof:name":"Pe\u00f1a Martinez Carlos",
    "wof:placetype":"venue"
},
  "geometry": {"coordinates":[-3.7399823666,40.4064559937],"type":"Point"}
}