{
  "type": "Feature",
  "properties": {
    "iso:country":"ES",
    "sg:address":"Plaz Mercado (del), 6",
    "sg:city":"Montoro",
    "sg:orig_category":"Reposter\u00cdas",
    "sg:phone":"+34 957 16 09 26",
    "sg:postcode":"14600",
    "sg:province":"C\u00f3rdoba",
    "wof:name":"Martin Romero Ruiz Y Otros Cb",
    "wof:placetype":"venue"
},
  "geometry": {"coordinates":[-4.3815989494,38.0260391235],"type":"Point"}
}