{
  "type": "Feature",
  "properties": {
    "addr:full":"Avda Alfonso El Sabio, 24 Alacant Alicante 03004",
    "addr:housenumber":"24",
    "addr:postcode":"03004",
    "addr:street":"Avda Alfonso El Sabio",
    "iso:country":"ES",
    "sg:address":"Avda Alfonso El Sabio, 24",
    "sg:city":"Alacant",
    "sg:orig_category":"Ropa Para Se\u00d1oras (al Por Menor)",
    "sg:phone":"+34 965 20 55 14",
    "sg:postcode":"03004",
    "sg:province":"Alicante",
    "wof:name":"Servicios Interbancarios De Alicante S.l.",
    "wof:placetype":"venue"
},
  "geometry": {"coordinates":[-0.4879199862,38.3471412659],"type":"Point"}
}