{
  "type": "Feature",
  "properties": {
    "addr:full":"Calle de Daroca, 10 Zaragoza Zaragoza 50017",
    "addr:housenumber":"10",
    "addr:postcode":"50017",
    "addr:street":"Calle De Daroca",
    "iso:country":"ES",
    "sg:address":"Calle de Daroca, 10",
    "sg:city":"Zaragoza",
    "sg:orig_category":"Material Y Suministros Para Imprenta E Industrias Gr\u00c1ficas",
    "sg:phone":"+34 976 39 55 09",
    "sg:postcode":"50017",
    "sg:province":"Zaragoza",
    "wof:name":"Impresora Aragonesa S.l.",
    "wof:placetype":"venue"
},
  "geometry": {"coordinates":[-0.9047783017,41.6494102478],"type":"Point"}
}