{
  "type": "Feature",
  "properties": {
    "iso:country":"ES",
    "sg:address":"Pg Catalunya, 6",
    "sg:city":"Torroella Montgri",
    "sg:orig_category":"Reposter\u00cdas",
    "sg:phone":"+34 972 76 16 01",
    "sg:postcode":"17257",
    "sg:province":"Girona",
    "wof:name":"Forn De Pa Can Frigola S.l.",
    "wof:placetype":"venue"
},
  "geometry": {"coordinates":[3.128015995,42.0388259888],"type":"Point"}
}