{
  "type": "Feature",
  "properties": {
    "addr:full":"Calle de Victoria, 11 Ventas Con Pe\u00e7a Aguilera Toledo 45127",
    "addr:housenumber":"11",
    "addr:postcode":"45127",
    "addr:street":"Calle De Victoria",
    "iso:country":"ES",
    "sg:address":"Calle de Victoria, 11",
    "sg:city":"Ventas Con Pe\u00e7a Aguilera",
    "sg:orig_category":"Droguer\u00cdas (al Por Menor)",
    "sg:phone":"+34 925 41 82 58",
    "sg:postcode":"45127",
    "sg:province":"Toledo",
    "wof:name":"Arroyo Romero Alberto",
    "wof:placetype":"venue"
},
  "geometry": {"coordinates":[-4.0244760513,39.8567771912],"type":"Point"}
}