{
  "type": "Feature",
  "properties": {
    "iso:country":"ES",
    "sg:address":"Calle de Doctor Zofio, 6",
    "sg:city":"Madrid",
    "sg:orig_category":"Negocio De Materiales De Construcci\u00d3n",
    "sg:phone":"+34 914 66 56 65",
    "sg:postcode":"28019",
    "sg:province":"Madrid",
    "wof:name":"Decoraciones Ceramicas Madrile\u00f1as S.l.",
    "wof:placetype":"venue"
},
  "geometry": {"coordinates":[-3.7381205559,40.3947944641],"type":"Point"}
}