{
  "type": "Feature",
  "properties": {
    "addr:full":"Carretera De Devanos, Km. 0000,5 Agreda Soria 42100",
    "addr:postcode":"42100",
    "addr:street":"Carretera De Devanos Km. 0000,5",
    "iso:country":"ES",
    "sg:address":"Carretera De Devanos, Km. 0000,5",
    "sg:city":"Agreda",
    "sg:orig_category":"Cooperativas Agr\u00cdcolas",
    "sg:phone":"+34 976 19 70 87",
    "sg:postcode":"42100",
    "sg:province":"Soria",
    "wof:name":"Union Comarcal Agredana S.coop.l.",
    "wof:placetype":"venue"
},
  "geometry": {"coordinates":[-1.9239610434,41.8537368774],"type":"Point"}
}