{
  "type": "Feature",
  "properties": {
    "iso:country":"ES",
    "sg:address":"Gudugarreta Auzoa, 17",
    "sg:city":"Gudugarreta",
    "sg:orig_category":"Electricidad Veh\u00cdculo",
    "sg:phone":"+34 943 88 17 00",
    "sg:postcode":"20200",
    "sg:province":"Guip\u00f9zcoa",
    "sg:website":"www.anzizar.com",
    "wof:name":"Anzizar S.a.",
    "wof:placetype":"venue"
},
  "geometry": {"coordinates":[-2.1944589615,43.0469207764],"type":"Point"}
}