{
  "type": "Feature",
  "properties": {
    "iso:country":"ES",
    "sg:address":"Av Antoni Gaudi, 25",
    "sg:city":"Olot",
    "sg:orig_category":"Charcuter\u00cdas (al Por Menor)",
    "sg:phone":"+34 972 27 20 00",
    "sg:postcode":"17800",
    "sg:province":"Girona",
    "wof:name":"Noel Alimentaria S.a.u.",
    "wof:placetype":"venue"
},
  "geometry": {"coordinates":[2.4711639881,42.1669425964],"type":"Point"}
}