{
  "type": "Feature",
  "properties": {
    "iso:country":"ES",
    "sg:address":"Calle de Vallehermoso, 77",
    "sg:city":"Madrid",
    "sg:orig_category":"Molduras, Junquillos, Listones Y Molduras Perforadas",
    "sg:phone":"+34 915 33 29 25",
    "sg:postcode":"28015",
    "sg:province":"Madrid",
    "wof:name":"Gonzalez Amago Manuel",
    "wof:placetype":"venue"
},
  "geometry": {"coordinates":[-3.7084729671,40.4384918213],"type":"Point"}
}