{
  "type": "Feature",
  "properties": {
    "addr:full":"C/ Enrique Pire Garcia, 24 Elche Alicante 03204",
    "addr:housenumber":"24",
    "addr:postcode":"03204",
    "addr:street":"C / Enrique Pire Garcia",
    "iso:country":"ES",
    "sg:address":"C/ Enrique Pire Garcia, 24",
    "sg:city":"Elche",
    "sg:orig_category":"Estancos",
    "sg:phone":"+34 966 63 63 98",
    "sg:postcode":"03204",
    "sg:province":"Alicante",
    "wof:name":"Bertomeu Javaloyes Teresa",
    "wof:placetype":"venue"
},
  "geometry": {"coordinates":[-0.7046729922,38.2566642761],"type":"Point"}
}