{
  "type": "Feature",
  "properties": {
    "addr:full":"Rua Valle Inclan, 17 Ourense Ourense 32004",
    "addr:housenumber":"17",
    "addr:postcode":"32004",
    "addr:street":"Rua Valle Inclan",
    "iso:country":"ES",
    "sg:address":"Rua Valle Inclan, 17",
    "sg:city":"Ourense",
    "sg:orig_category":"Bares, Piano",
    "sg:phone":"+34 988 25 46 76",
    "sg:postcode":"32004",
    "sg:province":"Ourense",
    "wof:name":"Gonzalez Dominguez Martin",
    "wof:placetype":"venue"
},
  "geometry": {"coordinates":[-7.8608517647,42.3417396545],"type":"Point"}
}