{
  "type": "Feature",
  "properties": {
    "addr:full":"Calle de Jacinto Verdaguer, 18 Madrid Madrid 28019",
    "addr:housenumber":"18",
    "addr:postcode":"madrid;28019",
    "addr:street":"Calle De Jacinto Verdaguer",
    "iso:country":"ES",
    "sg:address":"Calle de Jacinto Verdaguer, 18",
    "sg:city":"Madrid",
    "sg:orig_category":"Bisuter\u00cda, Joyer\u00cda, Relojer\u00cda (al Por Menor)",
    "sg:phone":"+34 914 71 00 64",
    "sg:postcode":"28019",
    "sg:province":"Madrid",
    "wof:name":"Bello Vara Juan",
    "wof:placetype":"venue"
},
  "geometry": {"coordinates":[-3.7165100574,40.3958930969],"type":"Point"}
}