{
  "type": "Feature",
  "properties": {
    "iso:country":"ES",
    "sg:address":"Rua Mato (do), S/n",
    "sg:city":"Xinzo De Limia",
    "sg:orig_category":"Reposter\u00cdas",
    "sg:phone":"+34 988 46 00 60",
    "sg:postcode":"32630",
    "sg:province":"Ourense",
    "wof:name":"Ojea Ojea Luis",
    "wof:placetype":"venue"
},
  "geometry": {"coordinates":[-7.7297339439,42.0608634949],"type":"Point"}
}