{
  "type": "Feature",
  "properties": {
    "addr:full":"Carrer de L'estadella, 71 Barcelona Barcelona 08030",
    "addr:housenumber":"71",
    "addr:postcode":"08030",
    "addr:street":"Carrer De L'Estadella",
    "iso:country":"ES",
    "sg:address":"Carrer de L'estadella, 71",
    "sg:city":"Barcelona",
    "sg:orig_category":"Droguer\u00cdas (al Por Menor)",
    "sg:phone":"+34 933 13 62 46",
    "sg:postcode":"08030",
    "sg:province":"Barcelona",
    "wof:name":"Sorribas Escorihuela Juan Antonio",
    "wof:placetype":"venue"
},
  "geometry": {"coordinates":[2.2052764893,41.435459137],"type":"Point"}
}