{
  "type": "Feature",
  "properties": {
    "iso:country":"ES",
    "sg:address":"Cra Laurea Miro, 39",
    "sg:city":"Sant Feliu Llobregat",
    "sg:orig_category":"Instalaci\u00d3n De Aspiraci\u00d3n De Gases Y Humos",
    "sg:phone":"+34 936 85 10 65",
    "sg:postcode":"08980",
    "sg:province":"Barcelona",
    "wof:name":"Parra Garcia Ramon",
    "wof:placetype":"venue"
},
  "geometry": {"coordinates":[2.0498259068,41.3796386719],"type":"Point"}
}