{
  "type": "Feature",
  "properties": {
    "iso:country":"ES",
    "sg:address":"Calle de Pilar, 9",
    "sg:city":"Riopar",
    "sg:orig_category":"Negocio De Materiales De Construcci\u00d3n",
    "sg:phone":"+34 967 43 50 27",
    "sg:postcode":"02450",
    "sg:province":"Albacete",
    "wof:name":"Quilez Alejo Conrado",
    "wof:placetype":"venue"
},
  "geometry": {"coordinates":[-2.4148840904,38.499584198],"type":"Point"}
}