{
  "type": "Feature",
  "properties": {
    "addr:full":"Avda Diputacion, 4 Palma Rio C\u00f3rdoba 14700",
    "addr:housenumber":"4",
    "addr:postcode":"14700",
    "addr:street":"Avda Diputacion;Rio Co\u0301Rdoba",
    "iso:country":"ES",
    "sg:address":"Avda Diputacion, 4",
    "sg:city":"Palma Rio",
    "sg:orig_category":"Internados & Ense\u00d1anza Privada",
    "sg:phone":"+34 957 64 43 45",
    "sg:postcode":"14700",
    "sg:province":"C\u00f3rdoba",
    "wof:name":"Reverendos Padres Salesianos",
    "wof:placetype":"venue"
},
  "geometry": {"coordinates":[-5.2795991898,37.7004241943],"type":"Point"}
}