{
  "type": "Feature",
  "properties": {
    "iso:country":"ES",
    "sg:address":"Calle de Eras, 9",
    "sg:city":"Madrid",
    "sg:orig_category":"Asociaciones Y Clubs Deportivos",
    "sg:phone":"+34 917 63 39 22",
    "sg:postcode":"28033",
    "sg:province":"Madrid",
    "wof:name":"Bernal Pardos Juan Marcos Y Hernando Benavides Rafael Cdad",
    "wof:placetype":"venue"
},
  "geometry": {"coordinates":[-3.6419138908,40.4753646851],"type":"Point"}
}