{
  "type": "Feature",
  "properties": {
    "addr:full":"Calle de Goiri Erdikoa, S/n Basozabal Vizcaya 48150",
    "addr:housenumber":"s",
    "addr:postcode":"48150",
    "addr:street":"Calle De Goiri;/ N",
    "iso:country":"ES",
    "sg:address":"Calle de Goiri Erdikoa, S/n",
    "sg:city":"Basozabal",
    "sg:orig_category":"Ense\u00d1anza, Formaci\u00d3n Profesional: Aprendizaje",
    "sg:phone":"+34 944 53 39 82",
    "sg:postcode":"48150",
    "sg:province":"Vizcaya",
    "wof:name":"Ayuntamiento De Sondica",
    "wof:placetype":"venue"
},
  "geometry": {"coordinates":[-2.9289562702,43.2998924255],"type":"Point"}
}