{
  "type": "Feature",
  "properties": {
    "addr:full":"Calle de Maximo Agirre, 4 Lamiako Vizcaya 48940",
    "addr:housenumber":"4",
    "addr:postcode":"48940",
    "addr:street":"Calle De Maximo Agirre",
    "iso:country":"ES",
    "sg:address":"Calle de Maximo Agirre, 4",
    "sg:city":"Lamiako",
    "sg:orig_category":"Transporte En General",
    "sg:phone":"+34 944 63 92 43",
    "sg:postcode":"48940",
    "sg:province":"Vizcaya",
    "wof:name":"Legarreta Echegaray Marcelino",
    "wof:placetype":"venue"
},
  "geometry": {"coordinates":[-2.9860789776,43.3275489807],"type":"Point"}
}