{
  "type": "Feature",
  "properties": {
    "iso:country":"ES",
    "sg:address":"Calle de Rector Lopez Argueta, 23",
    "sg:city":"Granada",
    "sg:orig_category":"Ense\u00d1anza, Formaci\u00d3n Profesional: Aprendizaje",
    "sg:phone":"+34 958 29 45 10",
    "sg:postcode":"18001",
    "sg:province":"Granada",
    "wof:name":"Instituto Social De Las Fuerzas Armadas",
    "wof:placetype":"venue"
},
  "geometry": {"coordinates":[-3.605479002,37.1811599731],"type":"Point"}
}