{
  "type": "Feature",
  "properties": {
    "iso:country":"ES",
    "sg:address":"Calle de Avelino Fernandez De La Poza, 6",
    "sg:city":"Madrid",
    "sg:orig_category":"Ingenier\u00cda, Centros De Estudios (diversos)",
    "sg:phone":"+34 914 77 46 25",
    "sg:postcode":"28053",
    "sg:province":"Madrid",
    "wof:name":"Sobrino Garcia Miguel Angel",
    "wof:placetype":"venue"
},
  "geometry": {"coordinates":[-3.6721849442,40.3857955933],"type":"Point"}
}