{
  "type": "Feature",
  "properties": {
    "addr:full":"Calle de Ikastola, 2 Ondarroa Vizcaya 48700",
    "addr:housenumber":"2",
    "addr:postcode":"48700",
    "addr:street":"Calle De Ikastola",
    "iso:country":"ES",
    "sg:address":"Calle de Ikastola, 2",
    "sg:city":"Ondarroa",
    "sg:orig_category":"Ense\u00d1anza Secundaria: Colegios Y Escuelas Privadas",
    "sg:phone":"+34 946 83 31 97",
    "sg:postcode":"48700",
    "sg:province":"Vizcaya",
    "wof:name":"Juan Carlos De Blas De Blas Y Otros Cdad",
    "wof:placetype":"venue"
},
  "geometry": {"coordinates":[-2.4246273041,43.3199577332],"type":"Point"}
}