{
  "type": "Feature",
  "properties": {
    "iso:country":"ES",
    "sg:address":"Calle de Cirilo Amoros, 88",
    "sg:city":"Valencia",
    "sg:orig_category":"Abogados",
    "sg:phone":"+34 963 74 98 20",
    "sg:postcode":"46004",
    "sg:province":"Valencia",
    "wof:name":"Horizontal Y Juridicos Scp",
    "wof:placetype":"venue"
},
  "geometry": {"coordinates":[-0.3657627106,39.4697113037],"type":"Point"}
}