{
  "type": "Feature",
  "properties": {
    "addr:full":"Calle de Tormes, 31 Laguna Duero Valladolid 47140",
    "addr:housenumber":"31",
    "addr:postcode":"47140",
    "addr:street":"Calle De Tormes",
    "iso:country":"ES",
    "sg:address":"Calle de Tormes, 31",
    "sg:city":"Laguna Duero",
    "sg:orig_category":"Fabricaci\u00d3n De Ventanas",
    "sg:phone":"+34 983 54 05 54",
    "sg:postcode":"47140",
    "sg:province":"Valladolid",
    "wof:name":"Tejedor Perez Jose Luis",
    "wof:placetype":"venue"
},
  "geometry": {"coordinates":[-4.729206562,41.5857429504],"type":"Point"}
}