{
  "type": "Feature",
  "properties": {
    "addr:full":"Calle de Santa Rosa, 1 Majadahonda Madrid 28220",
    "addr:housenumber":"1",
    "addr:postcode":"28220",
    "addr:street":"Calle De Santa Rosa",
    "iso:country":"ES",
    "sg:address":"Calle de Santa Rosa, 1",
    "sg:city":"Majadahonda",
    "sg:orig_category":"Mec\u00c1nico Del Autom\u00d3vil",
    "sg:phone":"+34 916 38 81 93",
    "sg:postcode":"28220",
    "sg:province":"Madrid",
    "wof:name":"Estacio Pacheco Pedro",
    "wof:placetype":"venue"
},
  "geometry": {"coordinates":[-3.8718121052,40.4704475403],"type":"Point"}
}