{
  "type": "Feature",
  "properties": {
    "addr:full":"Sect D Segunda Fase, S/n Torre De La Higuera O Matalasca\u00e7as Huelva 21760",
    "addr:postcode":"21760",
    "addr:street":"Sect;Segunda Fase S / N",
    "iso:country":"ES",
    "sg:address":"Sect D Segunda Fase, S/n",
    "sg:city":"Torre De La Higuera O Matalasca\u00e7as",
    "sg:orig_category":"Cajas De Ahorro",
    "sg:phone":"+34 959 44 01 20",
    "sg:postcode":"21760",
    "sg:province":"Huelva",
    "wof:name":"Caixa D'estalvis I Pensions De Barcelona",
    "wof:placetype":"venue"
},
  "geometry": {"coordinates":[-6.9495940208,37.256313324],"type":"Point"}
}