{
  "type": "Feature",
  "properties": {
    "addr:full":"Carrer de Gignas, 25 Barcelona Barcelona 08002",
    "addr:housenumber":"25",
    "addr:postcode":"08002",
    "addr:street":"Carrer De Gignas",
    "iso:country":"ES",
    "sg:address":"Carrer de Gignas, 25",
    "sg:city":"Barcelona",
    "sg:orig_category":"Alimentaci\u00d3n General (al Por Menor)",
    "sg:phone":"+34 933 10 79 39",
    "sg:postcode":"08002",
    "sg:province":"Barcelona",
    "wof:name":"Nebreda Gonzalez Lazaro",
    "wof:placetype":"venue"
},
  "geometry": {"coordinates":[2.1802630424,41.3815689087],"type":"Point"}
}