{
  "type": "Feature",
  "properties": {
    "addr:full":"Avda Acebo Del, 4 Cangas Narcea Asturias 33800",
    "addr:housenumber":"4",
    "addr:postcode":"33800",
    "addr:street":"Avda Acebo Del",
    "iso:country":"ES",
    "sg:address":"Avda Acebo Del, 4",
    "sg:city":"Cangas Narcea",
    "sg:orig_category":"Asociaciones Y Clubs Deportivos",
    "sg:phone":"+34 985 81 05 12",
    "sg:postcode":"33800",
    "sg:province":"Asturias",
    "wof:name":"Fernandez Mera Joaquin",
    "wof:placetype":"venue"
},
  "geometry": {"coordinates":[-6.5502290726,43.1801643372],"type":"Point"}
}