{
  "type": "Feature",
  "properties": {
    "addr:full":"Carr Gladiol, 43 Pont D'inca Islas Baleares 07009",
    "addr:housenumber":"43",
    "addr:postcode":"07009",
    "addr:street":"Carr Gladiol;Pont D'Inca",
    "iso:country":"ES",
    "sg:address":"Carr Gladiol, 43",
    "sg:city":"Pont D'inca",
    "sg:orig_category":"Alquiler De V\u00cddeo",
    "sg:phone":"+34 971 60 09 10",
    "sg:postcode":"07009",
    "sg:province":"Islas Baleares",
    "wof:name":"Carvajal Medina Manuel",
    "wof:placetype":"venue"
},
  "geometry": {"coordinates":[2.9091899395,39.7197418213],"type":"Point"}
}