{
  "type": "Feature",
  "properties": {
    "iso:country":"ES",
    "sg:address":"Campet, 9",
    "sg:city":"Novelda",
    "sg:orig_category":"M\u00c1rmoles, Granitos Y Piedras Naturales",
    "sg:phone":"+34 965 60 12 82",
    "sg:postcode":"03660",
    "sg:province":"Alicante",
    "wof:name":"Marmoles Bempe S.l.",
    "wof:placetype":"venue"
},
  "geometry": {"coordinates":[-0.7475619912,38.3806037903],"type":"Point"}
}