{
  "type": "Feature",
  "properties": {
    "addr:full":"Rua General Martitegui, 14 Pontevedra Pontevedra 36002",
    "addr:housenumber":"14",
    "addr:postcode":"36002",
    "addr:street":"Rua General Martitegui",
    "iso:country":"ES",
    "sg:address":"Rua General Martitegui, 14",
    "sg:city":"Pontevedra",
    "sg:orig_category":"Electrodom\u00c9sticos (al Por Menor)",
    "sg:phone":"+34 986 86 54 55",
    "sg:postcode":"36002",
    "sg:province":"Pontevedra",
    "wof:name":"Francisco Toucedo Miguez Y Angel Lopez Otero Cdad",
    "wof:placetype":"venue"
},
  "geometry": {"coordinates":[-8.6487236023,42.43201828],"type":"Point"}
}