{
  "type": "Feature",
  "properties": {
    "iso:country":"ES",
    "sg:address":"Calvario, 23",
    "sg:city":"Moraleja",
    "sg:orig_category":"Alimentaci\u00d3n General (al Por Menor)",
    "sg:phone":"+34 927 51 54 63",
    "sg:postcode":"10840",
    "sg:province":"C\u00e1ceres",
    "wof:name":"Gutierrez Martin Honorio",
    "wof:placetype":"venue"
},
  "geometry": {"coordinates":[-6.661149025,40.0701675415],"type":"Point"}
}