{
  "type": "Feature",
  "properties": {
    "iso:country":"ES",
    "sg:address":"Calle de San Andres, 28",
    "sg:city":"Huelva",
    "sg:orig_category":"Ortopedia General",
    "sg:phone":"+34 959 24 34 40",
    "sg:postcode":"21004",
    "sg:province":"Huelva",
    "wof:name":"Ortopedia Moreno Alcolea S.c.p",
    "wof:placetype":"venue"
},
  "geometry": {"coordinates":[-6.9490537643,37.2613143921],"type":"Point"}
}