{
  "type": "Feature",
  "properties": {
    "addr:full":"Calle de Perez Casas, 2 San Jose Murcia 30800",
    "addr:housenumber":"2",
    "addr:postcode":"30800",
    "addr:street":"Calle De Perez Casas",
    "iso:country":"ES",
    "sg:address":"Calle de Perez Casas, 2",
    "sg:city":"San Jose",
    "sg:orig_category":"Florister\u00cdas",
    "sg:phone":"+34 968 47 03 43",
    "sg:postcode":"30800",
    "sg:province":"Murcia",
    "wof:name":"Cuadrado Ponce Maria Dolores",
    "wof:placetype":"venue"
},
  "geometry": {"coordinates":[-1.6905640364,37.680557251],"type":"Point"}
}