{
  "type": "Feature",
  "properties": {
    "addr:full":"Calle de Villarrubia De Los Ojos, S/n Ciudad Real Ciudad Real 13004",
    "addr:housenumber":"s",
    "addr:postcode":"13004",
    "addr:street":"Calle De Villarrubia;Los Ojos;/ N",
    "iso:country":"ES",
    "sg:address":"Calle de Villarrubia De Los Ojos, S/n",
    "sg:city":"Ciudad Real",
    "sg:orig_category":"Muebles Y Accesorios Para Cocinas Y Cuartos De Ba\u00d1o (al Por Menor)",
    "sg:phone":"+34 926 21 59 83",
    "sg:postcode":"13004",
    "sg:province":"Ciudad Real",
    "wof:name":"Aparicio Ibarrola Joaquin",
    "wof:placetype":"venue"
},
  "geometry": {"coordinates":[-3.9311757088,38.9756698608],"type":"Point"}
}