{
  "type": "Feature",
  "properties": {
    "addr:full":"Calle de Teniente Coronel Gautier, 1 Ceuta Ceuta 51002",
    "addr:housenumber":"1",
    "addr:postcode":"51002",
    "addr:street":"Calle De Teniente Coronel Gautier",
    "iso:country":"ES",
    "sg:address":"Calle de Teniente Coronel Gautier, 1",
    "sg:city":"Ceuta",
    "sg:orig_category":"Colchones (fabricaci\u00d3n, Al Por Mayor, Al Por Menor)",
    "sg:phone":"+34 956 50 84 52",
    "sg:postcode":"51002",
    "sg:province":"Ceuta",
    "wof:name":"Ortega Bejar Maria Antonia",
    "wof:placetype":"venue"
},
  "geometry": {"coordinates":[-5.3337802887,35.8868865967],"type":"Point"}
}