{
  "type": "Feature",
  "properties": {
    "iso:country":"ES",
    "sg:address":"Plaz Espa\u00d1a, 3",
    "sg:city":"Huercanos",
    "sg:orig_category":"Farmacias",
    "sg:phone":"+34 941 37 10 28",
    "sg:postcode":"26314",
    "sg:province":"La Rioja",
    "wof:name":"Palacios De La Concepcion Angel",
    "wof:placetype":"venue"
},
  "geometry": {"coordinates":[-2.6948549747,42.4290809631],"type":"Point"}
}