{
  "type": "Feature",
  "properties": {
    "iso:country":"ES",
    "sg:address":"Luga Mesoiro, 18",
    "sg:city":"Mesoiro",
    "sg:orig_category":"M\u00c1quinas Y Herramientas Para Trabajar La Piedra",
    "sg:phone":"+34 981 28 79 01",
    "sg:postcode":"15190",
    "sg:province":"La Coru\u00f1a",
    "wof:name":"Meiras Rodriguez Miguel",
    "wof:placetype":"venue"
},
  "geometry": {"coordinates":[-8.4312744141,43.3228416443],"type":"Point"}
}