{
  "type": "Feature",
  "properties": {
    "iso:country":"ES",
    "sg:address":"Carrer de Arimon, 12",
    "sg:city":"Barcelona",
    "sg:orig_category":"Peluquer\u00cdas, Peluquer\u00cda Mixta",
    "sg:phone":"+34 934 18 69 12",
    "sg:postcode":"08022",
    "sg:province":"Barcelona",
    "wof:name":"Egea Ruiz Antonio",
    "wof:placetype":"venue"
},
  "geometry": {"coordinates":[2.137239933,41.4048080444],"type":"Point"}
}