{
  "type": "Feature",
  "properties": {
    "addr:full":"Calle de Pe\u00d1a Caballera, 9 Candeleda \u00c1vila 05480",
    "addr:housenumber":"9",
    "addr:postcode":"05480",
    "addr:street":"Calle De Pen\u0303A Caballera",
    "iso:country":"ES",
    "sg:address":"Calle de Pe\u00d1a Caballera, 9",
    "sg:city":"Candeleda",
    "sg:orig_category":"Maquinaria Para Industrias Diversas",
    "sg:phone":"+34 920 38 06 68",
    "sg:postcode":"05480",
    "sg:province":"\u00c1vila",
    "wof:name":"Fernandez Lopez Teodoro",
    "wof:placetype":"venue"
},
  "geometry": {"coordinates":[-5.2383069992,40.1565856934],"type":"Point"}
}