{
  "type": "Feature",
  "properties": {
    "iso:country":"ES",
    "sg:address":"Calle de Mister Blisse, S/n",
    "sg:city":"Estrella",
    "sg:orig_category":"Distribuci\u00d3n De Petr\u00d3leo Y Derivados",
    "sg:phone":"+34 928 13 38 41",
    "sg:postcode":"35212",
    "sg:province":"Las Palmas",
    "wof:name":"Gestion De Estaciones De Servicios Canar",
    "wof:placetype":"venue"
},
  "geometry": {"coordinates":[-15.3846387863,28.0146007538],"type":"Point"}
}