{
  "type": "Feature",
  "properties": {
    "iso:country":"ES",
    "sg:address":"Calle de Baron De La Torre, S/n",
    "sg:city":"Cintruenigo",
    "sg:orig_category":"Copas, Insignias, Trofeos",
    "sg:phone":"+34 948 81 10 57",
    "sg:postcode":"31592",
    "sg:province":"Navarra",
    "wof:name":"Alabastros Margar S. L.",
    "wof:placetype":"venue"
},
  "geometry": {"coordinates":[-1.8095582724,42.0761756897],"type":"Point"}
}