{
  "type": "Feature",
  "properties": {
    "iso:country":"ES",
    "sg:address":"Carrer de Consell De Cent, 4",
    "sg:city":"Barcelona",
    "sg:orig_category":"Reparaci\u00d3n, Mantenimiento De Instrumentos Y Accesorios De M\u00dasica",
    "sg:phone":"+34 934 31 72 99",
    "sg:postcode":"08014",
    "sg:province":"Barcelona",
    "wof:name":"Activitats Musicals Del Barri S.l.",
    "wof:placetype":"venue"
},
  "geometry": {"coordinates":[2.1435284615,41.3754806519],"type":"Point"}
}