{
  "type": "Feature",
  "properties": {
    "addr:full":"Pg Fabra I Puig, 159 Barcelona Barcelona 08016",
    "addr:housenumber":"159",
    "addr:postcode":"08016",
    "addr:street":"Pg Fabra I Puig",
    "iso:country":"ES",
    "sg:address":"Pg Fabra I Puig, 159",
    "sg:city":"Barcelona",
    "sg:orig_category":"Confecci\u00d3n (fabricaci\u00d3n, Al Por Mayor)",
    "sg:phone":"+34 933 52 41 52",
    "sg:postcode":"08016",
    "sg:province":"Barcelona",
    "wof:name":"Casado Castro Francisco",
    "wof:placetype":"venue"
},
  "geometry": {"coordinates":[2.1787629128,41.430141449],"type":"Point"}
}