{
  "type": "Feature",
  "properties": {
    "iso:country":"ES",
    "sg:address":"Calle de Real, S/n",
    "sg:city":"Santa Olaja De La Ribera",
    "sg:orig_category":"Chapister\u00cda",
    "sg:phone":"+34 987 26 11 37",
    "sg:postcode":"24199",
    "sg:province":"Le\u00f3n",
    "wof:name":"Martinez Fernandez Joaquin",
    "wof:placetype":"venue"
},
  "geometry": {"coordinates":[-5.5522909164,42.5616645813],"type":"Point"}
}