{
  "type": "Feature",
  "properties": {
    "addr:full":"Avda Temisas, 6 Arrecife Las Palmas 35500",
    "addr:housenumber":"6",
    "addr:postcode":"35500",
    "addr:street":"Avda Temisas",
    "iso:country":"ES",
    "sg:address":"Avda Temisas, 6",
    "sg:city":"Arrecife",
    "sg:orig_category":"Chapister\u00cda",
    "sg:phone":"+34 928 80 32 72",
    "sg:postcode":"35500",
    "sg:province":"Las Palmas",
    "wof:name":"Placeres Ramirez Ezequiel",
    "wof:placetype":"venue"
},
  "geometry": {"coordinates":[-13.5506353378,28.970993042],"type":"Point"}
}