{
  "type": "Feature",
  "properties": {
    "iso:country":"ES",
    "sg:address":"Carr Canonge Baranera, 4",
    "sg:city":"Badalona",
    "sg:orig_category":"Estilistas Y Estudios De Estilo De Corte Y Confecci\u00d3n",
    "sg:phone":"+34 933 89 53 21",
    "sg:postcode":"08911",
    "sg:province":"Barcelona",
    "wof:name":"Espinosa Terres Francisco",
    "wof:placetype":"venue"
},
  "geometry": {"coordinates":[2.2492439747,41.4487342834],"type":"Point"}
}