{
  "type": "Feature",
  "properties": {
    "iso:country":"ES",
    "sg:address":"Bule Indalecio Prieto, S/n",
    "sg:city":"Madrid",
    "sg:orig_category":"Molduras, Junquillos, Listones Y Molduras Perforadas",
    "sg:phone":"+34 913 71 46 98",
    "sg:postcode":"28032",
    "sg:province":"Madrid",
    "wof:name":"Ortiz Ruiz Rigoberto",
    "wof:placetype":"venue"
},
  "geometry": {"coordinates":[-3.6204240322,40.4033546448],"type":"Point"}
}