{
  "type": "Feature",
  "properties": {
    "addr:full":"Bda Capitan, 43 Pardavila Pontevedra 36214",
    "addr:housenumber":"43",
    "addr:postcode":"36214",
    "addr:street":"Capitan",
    "iso:country":"ES",
    "sg:address":"Bda Capitan, 43",
    "sg:city":"Pardavila",
    "sg:orig_category":"Chapister\u00cda",
    "sg:phone":"+34 986 37 15 10",
    "sg:postcode":"36214",
    "sg:province":"Pontevedra",
    "wof:name":"Chapisteria Estrada S.l.",
    "wof:placetype":"venue"
},
  "geometry": {"coordinates":[-8.7059106827,42.2124443054],"type":"Point"}
}