{
  "type": "Feature",
  "properties": {
    "iso:country":"ES",
    "sg:address":"Carrer de Numancia, 187",
    "sg:city":"Barcelona",
    "sg:orig_category":"Sociedades, Compa\u00d1\u00cdas Aseguradoras",
    "sg:phone":"+34 902 30 30 12",
    "sg:postcode":"08034",
    "sg:province":"Barcelona",
    "sg:website":"www.winterthur.es",
    "wof:name":"Winterthur Iberica A.e.i.e.",
    "wof:placetype":"venue"
},
  "geometry": {"coordinates":[2.1314303875,41.3908424377],"type":"Point"}
}