{
  "type": "Feature",
  "properties": {
    "addr:full":"Calle de Bernabe Cantos, 39 Albacete Albacete 02003",
    "addr:housenumber":"39",
    "addr:postcode":"02003",
    "addr:street":"Calle De Bernabe Cantos",
    "iso:country":"ES",
    "sg:address":"Calle de Bernabe Cantos, 39",
    "sg:city":"Albacete",
    "sg:orig_category":"Empresas De Pintura Y Revestimientos",
    "sg:phone":"+34 967 22 09 83",
    "sg:postcode":"02003",
    "sg:province":"Albacete",
    "wof:name":"Rodenas Serna Manuel",
    "wof:placetype":"venue"
},
  "geometry": {"coordinates":[-1.8619558811,38.9874534607],"type":"Point"}
}