{
  "type": "Feature",
  "properties": {
    "addr:full":"Avda Juan Carlos I, 114 Zeneta Murcia 30588",
    "addr:housenumber":"114",
    "addr:postcode":"30588",
    "addr:street":"Avda Juan Carlos I",
    "iso:country":"ES",
    "sg:address":"Avda Juan Carlos I, 114",
    "sg:city":"Zeneta",
    "sg:orig_category":"Estancos",
    "sg:phone":"+34 968 85 41 12",
    "sg:postcode":"30588",
    "sg:province":"Murcia",
    "wof:name":"Sanchez Pallares Santiago",
    "wof:placetype":"venue"
},
  "geometry": {"coordinates":[-0.9974390268,38.0109481812],"type":"Point"}
}