{
  "type": "Feature",
  "properties": {
    "addr:full":"Plaz De Santa Maria, 42 Benavente Zamora 49600",
    "addr:housenumber":"42",
    "addr:postcode":"49600",
    "addr:street":"Plaz;Santa Maria",
    "iso:country":"ES",
    "sg:address":"Plaz De Santa Maria, 42",
    "sg:city":"Benavente",
    "sg:orig_category":"Perfumer\u00cda (al Por Menor)",
    "sg:phone":"+34 980 63 73 91",
    "sg:postcode":"49600",
    "sg:province":"Zamora",
    "wof:name":"Colinas Polvorosa Miguel Angel",
    "wof:placetype":"venue"
},
  "geometry": {"coordinates":[-5.677795887,42.0033531189],"type":"Point"}
}