{
  "type": "Feature",
  "properties": {
    "addr:full":"Carrer de Francesc Moragas, 60 Hospitalet Llobregat Barcelona 08901",
    "addr:housenumber":"60",
    "addr:postcode":"08901",
    "addr:street":"Carrer De Francesc Moragas",
    "iso:country":"ES",
    "sg:address":"Carrer de Francesc Moragas, 60",
    "sg:city":"Hospitalet Llobregat",
    "sg:orig_category":"Aparcamientos (infraestructuras, Accesorios)",
    "sg:phone":"+34 933 38 29 35",
    "sg:postcode":"08901",
    "sg:province":"Barcelona",
    "wof:name":"Castilla Marti Antonio",
    "wof:placetype":"venue"
},
  "geometry": {"coordinates":[2.0981590748,41.3564796448],"type":"Point"}
}