{
  "type": "Feature",
  "properties": {
    "addr:full":"Carrer de Unio, 93 Mataro Barcelona 08302",
    "addr:housenumber":"93",
    "addr:postcode":"08302",
    "addr:street":"Carrer De Unio",
    "iso:country":"ES",
    "sg:address":"Carrer de Unio, 93",
    "sg:city":"Mataro",
    "sg:orig_category":"Automatizaci\u00d3n De Procesos Industriales Y De Edificaci\u00d3n (estudios, Instalaci\u00d3n)",
    "sg:phone":"+34 937 98 18 54",
    "sg:postcode":"08302",
    "sg:province":"Barcelona",
    "wof:name":"Iobox S.l.",
    "wof:placetype":"venue"
},
  "geometry": {"coordinates":[2.4370129108,41.5348358154],"type":"Point"}
}