{
  "type": "Feature",
  "properties": {
    "iso:country":"ES",
    "sg:address":"Calle de Azucenas, 11",
    "sg:city":"Madrid",
    "sg:orig_category":"Aud\u00cdfonos",
    "sg:phone":"+34 915 79 10 40",
    "sg:postcode":"28039",
    "sg:province":"Madrid",
    "wof:name":"Caballero Hidalgo Manuel",
    "wof:placetype":"venue"
},
  "geometry": {"coordinates":[-3.6982748508,40.4633483887],"type":"Point"}
}