{
  "type": "Feature",
  "properties": {
    "iso:country":"ES",
    "sg:address":"Calle de Luis Chamizo, 6",
    "sg:city":"Roca Sierra",
    "sg:orig_category":"Autob\u00das (explotaci\u00d3n Y Servicios De)",
    "sg:phone":"+34 924 40 63 52",
    "sg:postcode":"06190",
    "sg:province":"Badajoz",
    "wof:name":"Corral Martin Consuelo",
    "wof:placetype":"venue"
},
  "geometry": {"coordinates":[-6.6897292137,39.1108703613],"type":"Point"}
}