{
  "type": "Feature",
  "properties": {
    "addr:full":"Mcdo San Roque, S/n Alcoi Alicante 03801",
    "addr:housenumber":"s",
    "addr:postcode":"03801",
    "addr:street":"San Roque;/ N",
    "iso:country":"ES",
    "sg:address":"Mcdo San Roque, S/n",
    "sg:city":"Alcoi",
    "sg:orig_category":"Reposter\u00cdas",
    "sg:phone":"+34 965 33 86 49",
    "sg:postcode":"03801",
    "sg:province":"Alicante",
    "wof:name":"Ruiz Garcia Teresa",
    "wof:placetype":"venue"
},
  "geometry": {"coordinates":[-0.4732739925,38.6984100342],"type":"Point"}
}