{
  "type": "Feature",
  "properties": {
    "addr:full":"Calle de Emilio Ferrari, 46 Madrid Madrid 28017",
    "addr:housenumber":"46",
    "addr:postcode":"madrid;28017",
    "addr:street":"Calle De Emilio Ferrari",
    "iso:country":"ES",
    "sg:address":"Calle de Emilio Ferrari, 46",
    "sg:city":"Madrid",
    "sg:orig_category":"\u00d3ptica: Instrumentos (fabricaci\u00d3n)",
    "sg:phone":"+34 913 67 40 68",
    "sg:postcode":"28017",
    "sg:province":"Madrid",
    "wof:name":"Calvo Gomez Francisco Alejandro",
    "wof:placetype":"venue"
},
  "geometry": {"coordinates":[-3.6417980194,40.4317932129],"type":"Point"}
}