{
  "type": "Feature",
  "properties": {
    "iso:country":"ES",
    "sg:address":"Afores, S/n",
    "sg:city":"Sero",
    "sg:orig_category":"Comunidades Religiosas",
    "sg:phone":"+34 973 40 07 75",
    "sg:postcode":"25739",
    "sg:province":"Lleida",
    "wof:name":"Bisbat D'urgell",
    "wof:placetype":"venue"
},
  "geometry": {"coordinates":[1.0851800442,41.8682746887],"type":"Point"}
}