{
  "type": "Feature",
  "properties": {
    "iso:country":"ES",
    "sg:address":"Avda Andalucia, 41",
    "sg:city":"Jaen",
    "sg:orig_category":"Profesiones M\u00c9dicas, Param\u00c9dicas",
    "sg:phone":"+34 953 25 63 30",
    "sg:postcode":"23005",
    "sg:province":"Ja\u00e9n",
    "wof:name":"Casado Quesada Francisco",
    "wof:placetype":"venue"
},
  "geometry": {"coordinates":[-3.7952070236,37.7774238586],"type":"Point"}
}