{
  "type": "Feature",
  "properties": {
    "iso:country":"ES",
    "sg:address":"Carrer de Carrio, 12",
    "sg:city":"Manresa",
    "sg:orig_category":"Oficinas: Suministros Para (fabricaci\u00d3n, Al Por Mayor)",
    "sg:phone":"+34 938 72 06 66",
    "sg:postcode":"08242",
    "sg:province":"Barcelona",
    "sg:website":"www.controlsistemes.com",
    "wof:name":"Sistemes D'organitzacio S. A.",
    "wof:placetype":"venue"
},
  "geometry": {"coordinates":[1.8228069544,41.7280807495],"type":"Point"}
}