{
  "type": "Feature",
  "properties": {
    "iso:country":"ES",
    "sg:address":"Calle de Timoteo Padros, 31",
    "sg:city":"San Lorenzo De El Escorial",
    "sg:orig_category":"Edici\u00d3n Fonogr\u00c1fica De M\u00dasica",
    "sg:phone":"+34 918 96 14 80",
    "sg:postcode":"28200",
    "sg:province":"Madrid",
    "sg:website":"www.glossamusic.com",
    "wof:name":"Glossa Music S.l.",
    "wof:placetype":"venue"
},
  "geometry": {"coordinates":[-4.1556887627,40.5880050659],"type":"Point"}
}