{
  "type": "Feature",
  "properties": {
    "addr:full":"Calle de Salamero, 39 Graus Huesca 22430",
    "addr:housenumber":"39",
    "addr:postcode":"22430",
    "addr:street":"Calle De Salamero",
    "iso:country":"ES",
    "sg:address":"Calle de Salamero, 39",
    "sg:city":"Graus",
    "sg:orig_category":"Vinos Y Licores (venta Al Por Menor)",
    "sg:phone":"+34 974 54 01 19",
    "sg:postcode":"22430",
    "sg:province":"Huesca",
    "wof:name":"Llorens Gabas Jose Maria",
    "wof:placetype":"venue"
},
  "geometry": {"coordinates":[0.3387202024,42.1920204163],"type":"Point"}
}