{
  "type": "Feature",
  "properties": {
    "addr:full":"Avda Santa Cruz, 101 San Isidro Santa Cruz De Tenerife 38611",
    "addr:housenumber":"101",
    "addr:postcode":"38611",
    "addr:street":"Avda Santa Cruz",
    "iso:country":"ES",
    "sg:address":"Avda Santa Cruz, 101",
    "sg:city":"San Isidro",
    "sg:orig_category":"Fabricaci\u00d3n De Muebles",
    "sg:phone":"+34 922 39 06 90",
    "sg:postcode":"38611",
    "sg:province":"Santa Cruz De Tenerife",
    "wof:name":"Mendoza Hogar S.l.",
    "wof:placetype":"venue"
},
  "geometry": {"coordinates":[-16.5576953888,28.0779972076],"type":"Point"}
}