{
  "type": "Feature",
  "properties": {
    "addr:full":"Calle de La Inmaculada, 25 San Vicente De Barakaldo Vizcaya 48903",
    "addr:housenumber":"25",
    "addr:postcode":"48903",
    "addr:street":"Calle De La Inmaculada",
    "iso:country":"ES",
    "sg:address":"Calle de La Inmaculada, 25",
    "sg:city":"San Vicente De Barakaldo",
    "sg:classifiers":[
        {
            "category":"Manufacturing",
            "subcategory":"Building Materials",
            "type":"Manufacturing & Wholesale Goods"
        }
    ],
    "sg:phone":"+34 944 90 46 07",
    "sg:postcode":"48903",
    "sg:province":"Vizcaya",
    "sg:tags":[
        "de",
        "industrial",
        "alquiler"
    ],
    "wof:name":"Recreativos Gosenge S.l.",
    "wof:placetype":"venue"
},
  "geometry": {"coordinates":[-2.9848089218,43.2856063843],"type":"Point"}
}