{
  "type": "Feature",
  "properties": {
    "addr:full":"Calle de Teniente Coronel Gautier, 59 Ceuta Ceuta 51002",
    "addr:housenumber":"59",
    "addr:postcode":"51002",
    "addr:street":"Calle De Teniente Coronel Gautier",
    "iso:country":"ES",
    "sg:address":"Calle de Teniente Coronel Gautier, 59",
    "sg:city":"Ceuta",
    "sg:orig_category":"Centros De Coordinaci\u00d3n",
    "sg:phone":"+34 956 50 95 25",
    "sg:postcode":"51002",
    "sg:province":"Ceuta",
    "wof:name":"Lahasen  Fatiha",
    "wof:placetype":"venue"
},
  "geometry": {"coordinates":[-5.3337802887,35.8868865967],"type":"Point"}
}