{
  "type": "Feature",
  "properties": {
    "iso:country":"ES",
    "sg:address":"Carrer de Lluis Pascual Roca, 2",
    "sg:city":"S. Boi Llobregat",
    "sg:orig_category":"Ropa Para Se\u00d1oras (al Por Menor)",
    "sg:phone":"+34 936 52 37 88",
    "sg:postcode":"08830",
    "sg:province":"Barcelona",
    "wof:name":"Xamfra S.c.p.",
    "wof:placetype":"venue"
},
  "geometry": {"coordinates":[2.039853096,41.3434944153],"type":"Point"}
}