{
  "type": "Feature",
  "properties": {
    "addr:full":"Calle de Olivos (de Los), 13 Algete Madrid 28110",
    "addr:postcode":"28110",
    "addr:street":"Calle De Olivos De Los",
    "iso:country":"ES",
    "sg:address":"Calle de Olivos (de Los), 13",
    "sg:city":"Algete",
    "sg:orig_category":"Afiladoras, Pulidoras Y Bru\u00d1idoras",
    "sg:phone":"+34 916 29 25 03",
    "sg:postcode":"28110",
    "sg:province":"Madrid",
    "wof:name":"Sanz Jimenez Jose Luis",
    "wof:placetype":"venue"
},
  "geometry": {"coordinates":[-3.5016300678,40.5986671448],"type":"Point"}
}