{
  "type": "Feature",
  "properties": {
    "iso:country":"ES",
    "sg:address":"Carrer de Sant Joan, 32",
    "sg:city":"Reus",
    "sg:orig_category":"Centros De Coordinaci\u00d3n",
    "sg:phone":"+34 977 32 18 77",
    "sg:postcode":"43201",
    "sg:province":"Tarragona",
    "wof:name":"Jounou Tomas Jose Ramon",
    "wof:placetype":"venue"
},
  "geometry": {"coordinates":[1.1049089432,41.1559524536],"type":"Point"}
}