{
  "type": "Feature",
  "properties": {
    "addr:full":"Calle de Pio Milla Andres, 8 Angeles Madrid 28223",
    "addr:postcode":"28223",
    "addr:street":"Calle De Pio Milla Andres 8",
    "iso:country":"ES",
    "sg:address":"Calle de Pio Milla Andres, 8",
    "sg:city":"Angeles",
    "sg:orig_category":"Arquitectos",
    "sg:phone":"+34 915 18 96 80",
    "sg:postcode":"28223",
    "sg:province":"Madrid",
    "wof:name":"Gomez Ramiro Maria",
    "wof:placetype":"venue"
},
  "geometry": {"coordinates":[-3.7793300152,40.4041366577],"type":"Point"}
}