{
  "type": "Feature",
  "properties": {
    "iso:country":"ES",
    "sg:address":"Avda Tres Cruces, 20",
    "sg:city":"Zamora",
    "sg:orig_category":"Agentes Generales De Seguros",
    "sg:phone":"+34 980 67 12 66",
    "sg:postcode":"49008",
    "sg:province":"Zamora",
    "wof:name":"Duran Prieto Leandro",
    "wof:placetype":"venue"
},
  "geometry": {"coordinates":[-5.7412719727,41.51039505],"type":"Point"}
}