{
  "type": "Feature",
  "properties": {
    "iso:country":"ES",
    "sg:address":"Avda Chopo (el), 4",
    "sg:city":"Santiago",
    "sg:orig_category":"Inmobiliaria (agencias)",
    "sg:phone":"+34 942 80 80 11",
    "sg:postcode":"39311",
    "sg:province":"Cantabria",
    "wof:name":"Fernandez Rodriguez S.a.",
    "wof:placetype":"venue"
},
  "geometry": {"coordinates":[-4.0675420761,43.3316230774],"type":"Point"}
}