{
  "type": "Feature",
  "properties": {
    "iso:country":"ES",
    "sg:address":"Calle de Cava, 13",
    "sg:city":"Pe\u00e7aranda De Duero",
    "sg:orig_category":"Instalaci\u00d3n De Sanitarios",
    "sg:phone":"+34 947 55 22 66",
    "sg:postcode":"09410",
    "sg:province":"Burgos",
    "wof:name":"Ayuntamiento De Pe\u00d1aranda De Duero",
    "wof:placetype":"venue"
},
  "geometry": {"coordinates":[-3.6997311115,42.3408737183],"type":"Point"}
}