{
  "type": "Feature",
  "properties": {
    "addr:full":"Avda Juan Carlos I (de), S/n Tomelloso Ciudad Real 13700",
    "addr:postcode":"13700",
    "addr:street":"Avda Juan Carlos I De S / N",
    "iso:country":"ES",
    "sg:address":"Avda Juan Carlos I (de), S/n",
    "sg:city":"Tomelloso",
    "sg:orig_category":"Calefacci\u00d3n Central: Material (fabricaci\u00d3n, Al Por Mayor)",
    "sg:phone":"+34 926 51 29 79",
    "sg:postcode":"13700",
    "sg:province":"Ciudad Real",
    "wof:name":"Frutos Lopez Galindo Grupo S.l.",
    "wof:placetype":"venue"
},
  "geometry": {"coordinates":[-3.0085890293,39.1545295715],"type":"Point"}
}