{
  "type": "Feature",
  "properties": {
    "addr:full":"Avda Padre Villoslada, 33 Baena C\u00f3rdoba 14850",
    "addr:housenumber":"33",
    "addr:postcode":"14850",
    "addr:street":"Avda Padre Villoslada",
    "iso:country":"ES",
    "sg:address":"Avda Padre Villoslada, 33",
    "sg:city":"Baena",
    "sg:orig_category":"Inmobiliaria (agencias)",
    "sg:phone":"+34 957 69 22 47",
    "sg:postcode":"14850",
    "sg:province":"C\u00f3rdoba",
    "wof:name":"Residencial Encinares De Alcolea S.l.",
    "wof:placetype":"venue"
},
  "geometry": {"coordinates":[-4.316699028,37.6188316345],"type":"Point"}
}