{
  "type": "Feature",
  "properties": {
    "iso:country":"ES",
    "sg:address":"Calle de Menendez Pidal, 43",
    "sg:city":"Madrid",
    "sg:orig_category":"Financiaci\u00d3n Y Cr\u00c9ditos",
    "sg:phone":"+34 913 45 58 92",
    "sg:postcode":"28036",
    "sg:province":"Madrid",
    "wof:name":"Impulsa Capital S.l.",
    "wof:placetype":"venue"
},
  "geometry": {"coordinates":[-3.6801559925,40.4662666321],"type":"Point"}
}