{
  "type": "Feature",
  "properties": {
    "addr:full":"Carrer de Pintor Gimeno, 2 Barcelona Barcelona 08022",
    "addr:housenumber":"2",
    "addr:postcode":"08022",
    "addr:street":"Carrer De Pintor Gimeno",
    "iso:country":"ES",
    "sg:address":"Carrer de Pintor Gimeno, 2",
    "sg:city":"Barcelona",
    "sg:orig_category":"M\u00c9dicos: Estomatolog\u00cda",
    "sg:phone":"+34 932 11 45 16",
    "sg:postcode":"08022",
    "sg:province":"Barcelona",
    "wof:name":"Mir Llopart Juan Luis",
    "wof:placetype":"venue"
},
  "geometry": {"coordinates":[2.1391689777,41.4047203064],"type":"Point"}
}