{
  "type": "Feature",
  "properties": {
    "addr:full":"Fte Hierro, 23 Iru\u00f1a Navarra 31007",
    "addr:housenumber":"23",
    "addr:postcode":"31007",
    "addr:street":"Irun\u0303A Navarra",
    "iso:country":"ES",
    "sg:address":"Fte Hierro, 23",
    "sg:city":"Iru\u00f1a",
    "sg:orig_category":"Pescader\u00cdas (al Por Menor)",
    "sg:phone":"+34 948 17 14 85",
    "sg:postcode":"31007",
    "sg:province":"Navarra",
    "wof:name":"Ilarregui Suberviola Martin Vicente",
    "wof:placetype":"venue"
},
  "geometry": {"coordinates":[-1.65556705,42.8074073792],"type":"Point"}
}