{
  "type": "Feature",
  "properties": {
    "addr:full":"Calle de Lisboa, 16 Torrejon Ardoz Madrid 28850",
    "addr:housenumber":"16",
    "addr:postcode":"28850",
    "addr:street":"Calle De Lisboa",
    "iso:country":"ES",
    "sg:address":"Calle de Lisboa, 16",
    "sg:city":"Torrejon Ardoz",
    "sg:orig_category":"Carnicer\u00cdas, Carnicer\u00cdas",
    "sg:phone":"+34 916 76 77 50",
    "sg:postcode":"28850",
    "sg:province":"Madrid",
    "wof:name":"Gullon Mateos Vicenta",
    "wof:placetype":"venue"
},
  "geometry": {"coordinates":[-3.4701590538,40.4642601013],"type":"Point"}
}