{
  "type": "Feature",
  "properties": {
    "iso:country":"ES",
    "sg:address":"Calle de Llana, 44",
    "sg:city":"Olvera",
    "sg:orig_category":"Bisuter\u00cda, Joyer\u00cda, Relojer\u00cda (al Por Menor)",
    "sg:phone":"+34 956 13 10 05",
    "sg:postcode":"11690",
    "sg:province":"C\u00e1diz",
    "wof:name":"Joyerias Hermanos Salas S.l.",
    "wof:placetype":"venue"
},
  "geometry": {"coordinates":[-5.2651729584,36.935005188],"type":"Point"}
}