{
  "type": "Feature",
  "properties": {
    "addr:full":"Calle de Escuelas, 3 Cisterniga Valladolid 47193",
    "addr:housenumber":"3",
    "addr:postcode":"47193",
    "addr:street":"Calle De Escuelas",
    "iso:country":"ES",
    "sg:address":"Calle de Escuelas, 3",
    "sg:city":"Cisterniga",
    "sg:orig_category":"Quincaller\u00cda (fabricaci\u00d3n)",
    "sg:phone":"+34 983 40 25 56",
    "sg:postcode":"47193",
    "sg:province":"Valladolid",
    "wof:name":"Diaz Silva Maria Del Carmen",
    "wof:placetype":"venue"
},
  "geometry": {"coordinates":[-4.6868891716,41.6119194031],"type":"Point"}
}