{
  "type": "Feature",
  "properties": {
    "iso:country":"ES",
    "sg:address":"Calle de Canovas Del Castillo, 4",
    "sg:city":"Santa Eulalia",
    "sg:orig_category":"Quincaller\u00cda (al Por Menor)",
    "sg:phone":"+34 968 21 70 50",
    "sg:postcode":"30003",
    "sg:province":"Murcia",
    "wof:name":"Miguel Lopez Ariza Y Antonio Martinez Arias C.b.",
    "wof:placetype":"venue"
},
  "geometry": {"coordinates":[-1.1265408993,37.9838447571],"type":"Point"}
}