{
  "type": "Feature",
  "properties": {
    "addr:full":"Calle de Gabriel Y Galan, 17 Pesga C\u00e1ceres 10649",
    "addr:housenumber":"17",
    "addr:postcode":"10649",
    "addr:street":"Calle De Gabriel Y Galan;Ca\u0301Ceres",
    "iso:country":"ES",
    "sg:address":"Calle de Gabriel Y Galan, 17",
    "sg:city":"Pesga",
    "sg:orig_category":"Administraciones Regionales, Departamentales Y Locales",
    "sg:phone":"+34 927 67 45 62",
    "sg:postcode":"10649",
    "sg:province":"C\u00e1ceres",
    "wof:name":"Ayuntamiento De La Pesga",
    "wof:placetype":"venue"
},
  "geometry": {"coordinates":[-6.1758332253,40.3265914917],"type":"Point"}
}