{
  "type": "Feature",
  "properties": {
    "iso:country":"ES",
    "sg:address":"Prolongacion Calle de Ancha, 88",
    "sg:city":"Huetor-tajar",
    "sg:orig_category":"Electrodom\u00c9sticos (al Por Menor)",
    "sg:phone":"+34 958 33 23 05",
    "sg:postcode":"18360",
    "sg:province":"Granada",
    "wof:name":"Electronica Pe\u00f1a S.l.u.",
    "wof:placetype":"venue"
},
  "geometry": {"coordinates":[-4.046749115,37.1978111267],"type":"Point"}
}