{
  "type": "Feature",
  "properties": {
    "addr:full":"Calle de Serrano, 11 Madrid Madrid 28001",
    "addr:housenumber":"11",
    "addr:postcode":"madrid;28001",
    "addr:street":"Calle De Serrano",
    "iso:country":"ES",
    "sg:address":"Calle de Serrano, 11",
    "sg:city":"Madrid",
    "sg:orig_category":"Centros De Coordinaci\u00d3n",
    "sg:phone":"+34 915 77 92 66",
    "sg:postcode":"28001",
    "sg:province":"Madrid",
    "wof:name":"Gestoria Pradilla S.l.",
    "wof:placetype":"venue"
},
  "geometry": {"coordinates":[-3.6885340214,40.4223976135],"type":"Point"}
}