{
  "type": "Feature",
  "properties": {
    "iso:country":"ES",
    "sg:address":"Carr Marca De L'ham, 123",
    "sg:city":"Figueres",
    "sg:orig_category":"Cerrajer\u00cda, Ferrallista",
    "sg:phone":"+34 972 50 88 14",
    "sg:postcode":"17600",
    "sg:province":"Girona",
    "wof:name":"Montoro Alvarez Antonio",
    "wof:placetype":"venue"
},
  "geometry": {"coordinates":[2.9814391136,42.2672157288],"type":"Point"}
}