{
  "type": "Feature",
  "properties": {
    "iso:country":"ES",
    "sg:address":"Santa Catalina, 17",
    "sg:city":"Cangas Narcea",
    "sg:orig_category":"Mec\u00c1nico Del Autom\u00d3vil",
    "sg:phone":"+34 985 81 01 79",
    "sg:postcode":"33800",
    "sg:province":"Asturias",
    "wof:name":"Barrero Nogueiro Adolfo",
    "wof:placetype":"venue"
},
  "geometry": {"coordinates":[-6.5502290726,43.1801643372],"type":"Point"}
}