{
  "type": "Feature",
  "properties": {
    "iso:country":"ES",
    "sg:address":"Carrer de Gasometre (del), 22",
    "sg:city":"Tarragona",
    "sg:orig_category":"Arquitectos",
    "sg:phone":"+34 977 22 17 68",
    "sg:postcode":"43001",
    "sg:province":"Tarragona",
    "wof:name":"Casas Sanchez Angel",
    "wof:placetype":"venue"
},
  "geometry": {"coordinates":[1.2491780519,41.1138343811],"type":"Point"}
}