{
  "type": "Feature",
  "properties": {
    "iso:country":"ES",
    "sg:address":"Carrer de Major (sant Celoni), 94",
    "sg:city":"S. Celoni",
    "sg:orig_category":"Inmobiliaria (agencias)",
    "sg:phone":"+34 938 67 39 29",
    "sg:postcode":"08470",
    "sg:province":"Barcelona",
    "sg:website":"www.finquesmarin.com",
    "wof:name":"Finques Marin S.l.",
    "wof:placetype":"venue"
},
  "geometry": {"coordinates":[2.4899170399,41.6890869141],"type":"Point"}
}