{
  "type": "Feature",
  "properties": {
    "iso:country":"ES",
    "sg:address":"Calle de La Paz, 11",
    "sg:city":"Vitoria-gasteiz",
    "sg:orig_category":"Reposter\u00cdas",
    "sg:phone":"+34 945 14 82 37",
    "sg:postcode":"01004",
    "sg:province":"\u00c1lava",
    "wof:name":"La Vitoriana De La Alimentacion S.l.",
    "wof:placetype":"venue"
},
  "geometry": {"coordinates":[-2.6682779789,42.8453559875],"type":"Point"}
}