{
  "type": "Feature",
  "properties": {
    "addr:full":"Avda Jesus Rescatado (de), 7 Cordoba C\u00f3rdoba 14007",
    "addr:housenumber":"7",
    "addr:postcode":"14007",
    "addr:street":"Avda Jesus Rescatado De;Co\u0301Rdoba",
    "iso:country":"ES",
    "sg:address":"Avda Jesus Rescatado (de), 7",
    "sg:city":"Cordoba",
    "sg:orig_category":"Ense\u00d1anza: Idiomas",
    "sg:phone":"+34 957 76 47 34",
    "sg:postcode":"14007",
    "sg:province":"C\u00f3rdoba",
    "wof:name":"Multi-idiomas Traslation Services S.l.",
    "wof:placetype":"venue"
},
  "geometry": {"coordinates":[-4.7621889114,37.8906974792],"type":"Point"}
}