{
  "type": "Feature",
  "properties": {
    "addr:full":"Manolo Gomez Bur, 74 Bailen Ja\u00e9n 23710",
    "addr:housenumber":"74",
    "addr:postcode":"23710",
    "addr:street":"Jae\u0301N",
    "iso:country":"ES",
    "sg:address":"Manolo Gomez Bur, 74",
    "sg:city":"Bailen",
    "sg:orig_category":"Partidos Pol\u00cdticos",
    "sg:phone":"+34 953 67 08 73",
    "sg:postcode":"23710",
    "sg:province":"Ja\u00e9n",
    "wof:name":"Partido Socialista Obrero Espa\u00f1ol",
    "wof:placetype":"venue"
},
  "geometry": {"coordinates":[-3.779558897,38.0967903137],"type":"Point"}
}