{
  "type": "Feature",
  "properties": {
    "addr:full":"Calle de Beato Tomas De Zumarraga, 48 Vitoria-gasteiz \u00c1lava 01009",
    "addr:housenumber":"48",
    "addr:postcode":"01009",
    "addr:street":"Calle De Beato Tomas De Zumarraga",
    "iso:country":"ES",
    "sg:address":"Calle de Beato Tomas De Zumarraga, 48",
    "sg:city":"Vitoria-gasteiz",
    "sg:orig_category":"Molduras, Junquillos, Listones Y Molduras Perforadas",
    "sg:phone":"+34 945 22 38 94",
    "sg:postcode":"01009",
    "sg:province":"\u00c1lava",
    "wof:name":"Delgado Perez Eusebio",
    "wof:placetype":"venue"
},
  "geometry": {"coordinates":[-2.6869499683,42.854850769],"type":"Point"}
}