{
  "type": "Feature",
  "properties": {
    "iso:country":"ES",
    "sg:address":"Ctra Cadiz De, Km. 0208,0",
    "sg:city":"Cala",
    "sg:orig_category":"Inmobiliaria (agencias)",
    "sg:phone":"+34 952 49 45 17",
    "sg:postcode":"29649",
    "sg:province":"M\u00e1laga",
    "wof:name":"Promotoras Manufer S.a.",
    "wof:placetype":"venue"
},
  "geometry": {"coordinates":[-4.6790738106,36.5038642883],"type":"Point"}
}