{
  "type": "Feature",
  "properties": {
    "iso:country":"ES",
    "sg:address":"Pque. Empresarial Area 33, S/n",
    "sg:city":"Silleda",
    "sg:orig_category":"Fabrica, Negocio De Vidrieras, Productos Vidriados Y Espejos",
    "sg:phone":"+34 986 58 02 07",
    "sg:postcode":"36540",
    "sg:province":"Pontevedra",
    "wof:name":"Arte Vitral S.l.l.",
    "wof:placetype":"venue"
},
  "geometry": {"coordinates":[-8.2541151047,42.6928710938],"type":"Point"}
}