{
  "type": "Feature",
  "properties": {
    "addr:full":"Pase Colon, 11 Foz Lugo 27780",
    "addr:housenumber":"11",
    "addr:postcode":"27780",
    "addr:street":"Colon",
    "iso:country":"ES",
    "sg:address":"Pase Colon, 11",
    "sg:city":"Foz",
    "sg:orig_category":"Promotores Constructores",
    "sg:phone":"+34 982 13 21 39",
    "sg:postcode":"27780",
    "sg:province":"Lugo",
    "wof:name":"Construcciones Os Molineros S.l.",
    "wof:placetype":"venue"
},
  "geometry": {"coordinates":[-7.2613739967,43.5743751526],"type":"Point"}
}