{
  "type": "Feature",
  "properties": {
    "addr:full":"Calle de Jose Reus Garcia, 33 Alacant Alicante 03010",
    "addr:housenumber":"33",
    "addr:postcode":"03010",
    "addr:street":"Calle De Jose Reus Garcia",
    "iso:country":"ES",
    "sg:address":"Calle de Jose Reus Garcia, 33",
    "sg:city":"Alacant",
    "sg:orig_category":"Sindicatos De Trabajadores",
    "sg:phone":"+34 965 17 07 17",
    "sg:postcode":"03010",
    "sg:province":"Alicante",
    "wof:name":"Confederacion General Del Trabajo",
    "wof:placetype":"venue"
},
  "geometry": {"coordinates":[-0.492610991,38.3638458252],"type":"Point"}
}