{
  "type": "Feature",
  "properties": {
    "addr:full":"Ptge Espiell, 4 Barcelona Barcelona 08032",
    "addr:housenumber":"4",
    "addr:postcode":"08032",
    "addr:street":"Ptge Espiell",
    "iso:country":"ES",
    "sg:address":"Ptge Espiell, 4",
    "sg:city":"Barcelona",
    "sg:orig_category":"Confecci\u00d3n De Trajes Para Se\u00d1oras",
    "sg:phone":"+34 933 57 05 70",
    "sg:postcode":"08032",
    "sg:province":"Barcelona",
    "wof:name":"Garrido Martos Dolores",
    "wof:placetype":"venue"
},
  "geometry": {"coordinates":[2.1594560146,41.4250030518],"type":"Point"}
}