{
  "type": "Feature",
  "properties": {
    "addr:full":"Calle de Europa, 6 Burriana Castell\u00f3n 12530",
    "addr:housenumber":"6",
    "addr:postcode":"12530",
    "addr:street":"Calle De Europa",
    "iso:country":"ES",
    "sg:address":"Calle de Europa, 6",
    "sg:city":"Burriana",
    "sg:classifiers":[
        {
            "category":"Casinos & Gambling",
            "type":"Entertainment"
        }
    ],
    "sg:phone":"+34 964 57 12 52",
    "sg:postcode":"12530",
    "sg:province":"Castell\u00f3n",
    "sg:tags":[
        "locale",
        "de",
        "juego"
    ],
    "sg:website":"www.monmenut.es",
    "wof:name":"Ludoteca Mon Menut Buris-ana Sl",
    "wof:placetype":"venue"
},
  "geometry": {"coordinates":[-0.079696998,39.8854522705],"type":"Point"}
}