{
  "type": "Feature",
  "properties": {
    "iso:country":"ES",
    "sg:address":"Urb. Fuera Villa, 26",
    "sg:city":"Piedrahita",
    "sg:orig_category":"Doctores En Medicina",
    "sg:phone":"+34 920 36 03 84",
    "sg:postcode":"05500",
    "sg:province":"\u00c1vila",
    "wof:name":"Gonzalez Gutierrez Julian",
    "wof:placetype":"venue"
},
  "geometry": {"coordinates":[-5.3263239861,40.4657211304],"type":"Point"}
}