{
  "type": "Feature",
  "properties": {
    "addr:full":"Ctra Elche, 11 Sta. Pola Alicante 03130",
    "addr:housenumber":"11",
    "addr:postcode":"03130",
    "addr:street":"Ctra Elche;Pola",
    "iso:country":"ES",
    "sg:address":"Ctra Elche, 11",
    "sg:city":"Sta. Pola",
    "sg:orig_category":"M\u00c1rmoles, Granitos Y Piedras Naturales",
    "sg:phone":"+34 965 41 31 93",
    "sg:postcode":"03130",
    "sg:province":"Alicante",
    "wof:name":"Marmoles Juvimar S.l.",
    "wof:placetype":"venue"
},
  "geometry": {"coordinates":[-0.5565090179,38.190448761],"type":"Point"}
}