{
  "type": "Feature",
  "properties": {
    "addr:full":"Calle de Cardenal Cisneros, 58 Santander Cantabria 39007",
    "addr:housenumber":"58",
    "addr:postcode":"39007",
    "addr:street":"Calle De Cardenal Cisneros",
    "iso:country":"ES",
    "sg:address":"Calle de Cardenal Cisneros, 58",
    "sg:city":"Santander",
    "sg:orig_category":"Hielo Artificial (fabricaci\u00d3n, Distribuci\u00d3n)",
    "sg:phone":"+34 942 37 15 54",
    "sg:postcode":"39007",
    "sg:province":"Cantabria",
    "wof:name":"Salas Saiz Aquilino",
    "wof:placetype":"venue"
},
  "geometry": {"coordinates":[-3.8155355453,43.4630088806],"type":"Point"}
}