{
  "type": "Feature",
  "properties": {
    "iso:country":"ES",
    "sg:address":"Mayor, 95",
    "sg:city":"Estella",
    "sg:orig_category":"Carnicer\u00cdas, Carnicer\u00cdas",
    "sg:phone":"+34 948 55 09 35",
    "sg:postcode":"31200",
    "sg:province":"Navarra",
    "wof:name":"Chocarro Ramos Julian",
    "wof:placetype":"venue"
},
  "geometry": {"coordinates":[-2.0304489136,42.6710205078],"type":"Point"}
}