{
  "type": "Feature",
  "properties": {
    "addr:full":"Calle de Carretera De Belver, 10 Albalate Cinca Huesca 22534",
    "addr:housenumber":"10",
    "addr:postcode":"22534",
    "addr:street":"Calle De Carretera De Belver",
    "iso:country":"ES",
    "sg:address":"Calle de Carretera De Belver, 10",
    "sg:city":"Albalate Cinca",
    "sg:classifiers":[
        {
            "category":"Personal",
            "subcategory":"Barber",
            "type":"Services"
        }
    ],
    "sg:phone":"+34 974 46 87 48",
    "sg:postcode":"22534",
    "sg:province":"Huesca",
    "sg:tags":[
        "caballeros",
        "de",
        "peluqueros"
    ],
    "wof:name":"Puyol Elcacho Angel",
    "wof:placetype":"venue"
},
  "geometry": {"coordinates":[0.2257198989,42.1413002014],"type":"Point"}
}