{
  "type": "Feature",
  "properties": {
    "addr:full":"Avda Mostoles, S/n Moraleja Enmedio Madrid 28950",
    "addr:housenumber":"s / n",
    "addr:postcode":"28950",
    "addr:street":"Avda Mostoles",
    "iso:country":"ES",
    "sg:address":"Avda Mostoles, S/n",
    "sg:city":"Moraleja Enmedio",
    "sg:orig_category":"Promotores Constructores",
    "sg:phone":"+34 916 09 41 69",
    "sg:postcode":"28950",
    "sg:province":"Madrid",
    "wof:name":"Baroca S.a.",
    "wof:placetype":"venue"
},
  "geometry": {"coordinates":[-3.8653891087,40.2647399902],"type":"Point"}
}