{
  "type": "Feature",
  "properties": {
    "addr:full":"Calle de Carril Del Castillo, 6 Navahermosa Toledo 45150",
    "addr:housenumber":"6",
    "addr:postcode":"45150",
    "addr:street":"Calle De Carril Del Castillo",
    "iso:country":"ES",
    "sg:address":"Calle de Carril Del Castillo, 6",
    "sg:city":"Navahermosa",
    "sg:orig_category":"Electricidad Veh\u00cdculo",
    "sg:phone":"+34 925 41 05 40",
    "sg:postcode":"45150",
    "sg:province":"Toledo",
    "wof:name":"Fernandez-roldan Fernandez Juan Carlos",
    "wof:placetype":"venue"
},
  "geometry": {"coordinates":[-4.4651122093,39.6370124817],"type":"Point"}
}