{
  "type": "Feature",
  "properties": {
    "iso:country":"ES",
    "sg:address":"Plaz De La Constitucion, S/n",
    "sg:city":"Almoradi",
    "sg:orig_category":"Librer\u00cdas",
    "sg:phone":"+34 965 70 03 48",
    "sg:postcode":"03160",
    "sg:province":"Alicante",
    "wof:name":"Gomis Gomez Jose Eugenio",
    "wof:placetype":"venue"
},
  "geometry": {"coordinates":[-0.7920610905,38.1091079712],"type":"Point"}
}