{
  "type": "Feature",
  "properties": {
    "addr:full":"Calle de Humanes, 80 Parla Madrid 28980",
    "addr:housenumber":"80",
    "addr:postcode":"28980",
    "addr:street":"Calle De Humanes",
    "iso:country":"ES",
    "sg:address":"Calle de Humanes, 80",
    "sg:city":"Parla",
    "sg:orig_category":"Farmacias",
    "sg:phone":"+34 916 99 54 12",
    "sg:postcode":"28980",
    "sg:province":"Madrid",
    "wof:name":"Arnaez Ortiz Maria Angeles",
    "wof:placetype":"venue"
},
  "geometry": {"coordinates":[-3.7761967182,40.2388038635],"type":"Point"}
}