{
  "type": "Feature",
  "properties": {
    "addr:full":"Calle de San Quirce, 6 Valladolid Valladolid 47003",
    "addr:housenumber":"6",
    "addr:postcode":"47003",
    "addr:street":"Calle De San Quirce",
    "iso:country":"ES",
    "sg:address":"Calle de San Quirce, 6",
    "sg:city":"Valladolid",
    "sg:orig_category":"Fabricaci\u00d3n, Venta De Cuadros, Accesorios Para Enmarcar",
    "sg:phone":"+34 983 35 72 95",
    "sg:postcode":"47003",
    "sg:province":"Valladolid",
    "wof:name":"Silva Manso Javier",
    "wof:placetype":"venue"
},
  "geometry": {"coordinates":[-4.7281627655,41.6572494507],"type":"Point"}
}