{
  "type": "Feature",
  "properties": {
    "addr:full":"Rua Alfredo Bra\u00d1as, 35 Ourense Ourense 32001",
    "addr:housenumber":"35",
    "addr:postcode":"32001",
    "addr:street":"Rua Alfredo Bran\u0303As",
    "iso:country":"ES",
    "sg:address":"Rua Alfredo Bra\u00d1as, 35",
    "sg:city":"Ourense",
    "sg:orig_category":"Chapister\u00cda",
    "sg:phone":"+34 988 37 03 21",
    "sg:postcode":"32001",
    "sg:province":"Ourense",
    "wof:name":"Autoreparaciones Nareda S.l.",
    "wof:placetype":"venue"
},
  "geometry": {"coordinates":[-7.8577313423,42.3522949219],"type":"Point"}
}