{
  "type": "Feature",
  "properties": {
    "addr:full":"C/ Bisbe Tormo, 16 Elche Alicante 03202",
    "addr:housenumber":"16",
    "addr:postcode":"03202",
    "addr:street":"C / Bisbe Tormo",
    "iso:country":"ES",
    "sg:address":"C/ Bisbe Tormo, 16",
    "sg:city":"Elche",
    "sg:orig_category":"Iglesia Cat\u00d3lica",
    "sg:phone":"+34 965 45 23 93",
    "sg:postcode":"03202",
    "sg:province":"Alicante",
    "wof:name":"Parroquia De Santa Maria",
    "wof:placetype":"venue"
},
  "geometry": {"coordinates":[-0.6969019771,38.266872406],"type":"Point"}
}