{
  "type": "Feature",
  "properties": {
    "addr:full":"Calle de Doctor Champsaur Sicilia, 2 Palmas De Gran Canaria Las Palmas 35011",
    "addr:housenumber":"2",
    "addr:postcode":"35011",
    "addr:street":"Calle De Doctor Champsaur Sicilia",
    "iso:country":"ES",
    "sg:address":"Calle de Doctor Champsaur Sicilia, 2",
    "sg:city":"Palmas De Gran Canaria",
    "sg:orig_category":"Farmacias",
    "sg:phone":"+34 928 25 13 77",
    "sg:postcode":"35011",
    "sg:province":"Las Palmas",
    "wof:name":"Sabater Diaz Jose Maria",
    "wof:placetype":"venue"
},
  "geometry": {"coordinates":[-15.4384393692,28.1158046722],"type":"Point"}
}