{
  "type": "Feature",
  "properties": {
    "iso:country":"ES",
    "sg:address":"Avda Ingeniero Serrano Lloveras, 11",
    "sg:city":"Grao",
    "sg:orig_category":"Alquiler De V\u00cddeo",
    "sg:phone":"+34 964 28 61 92",
    "sg:postcode":"12100",
    "sg:province":"Castell\u00f3n",
    "wof:name":"Arcas Media Anabel",
    "wof:placetype":"venue"
},
  "geometry": {"coordinates":[0.0137817003,39.9756507874],"type":"Point"}
}