{
  "type": "Feature",
  "properties": {
    "addr:full":"Calle de Chorretones, 7 Cuellar Segovia 40200",
    "addr:housenumber":"7",
    "addr:postcode":"40200",
    "addr:street":"Calle De Chorretones",
    "iso:country":"ES",
    "sg:address":"Calle de Chorretones, 7",
    "sg:city":"Cuellar",
    "sg:orig_category":"Cajas De Ahorro",
    "sg:phone":"+34 921 14 13 62",
    "sg:postcode":"40200",
    "sg:province":"Segovia",
    "sg:website":"www.lacaixa.es",
    "wof:name":"Caixa D'estalvis I Pensions De Barcelona",
    "wof:placetype":"venue"
},
  "geometry": {"coordinates":[-4.311627388,41.3988494873],"type":"Point"}
}