{
  "type": "Feature",
  "properties": {
    "iso:country":"ES",
    "sg:address":"Pg Germanies (de Les), 48",
    "sg:city":"Gandia",
    "sg:orig_category":"Cajas De Ahorro",
    "sg:phone":"+34 962 86 93 63",
    "sg:postcode":"46700",
    "sg:province":"Valencia",
    "sg:website":"www.caixaontinyent.es",
    "wof:name":"Caja De Ahorros De Onteniente",
    "wof:placetype":"venue"
},
  "geometry": {"coordinates":[-0.1844079942,38.9660224915],"type":"Point"}
}