{
  "type": "Feature",
  "properties": {
    "iso:country":"ES",
    "sg:address":"Calle de Gremios Del Cuero (los), 102",
    "sg:city":"Hontoria",
    "sg:orig_category":"Contenedores (mercanc\u00cdas)",
    "sg:phone":"+34 921 41 31 36",
    "sg:postcode":"40195",
    "sg:province":"Segovia",
    "wof:name":"Soneurotrans S.l.",
    "wof:placetype":"venue"
},
  "geometry": {"coordinates":[-4.1221280098,40.9089508057],"type":"Point"}
}