{
  "type": "Feature",
  "properties": {
    "iso:country":"ES",
    "sg:address":"Poligono De El Raposal, S/n",
    "sg:city":"Arnedo",
    "sg:orig_category":"Confecci\u00d3n De Zapatos",
    "sg:phone":"+34 941 38 04 00",
    "sg:postcode":"26580",
    "sg:province":"La Rioja",
    "sg:website":"www.hergar.com",
    "wof:name":"Calzados H2o S.l.",
    "wof:placetype":"venue"
},
  "geometry": {"coordinates":[-2.0899488926,42.2300453186],"type":"Point"}
}