{
  "type": "Feature",
  "properties": {
    "iso:country":"ES",
    "sg:address":"Plaz Constitucion (de La), 12",
    "sg:city":"Utrera",
    "sg:orig_category":"Bisuteros (fabricaci\u00d3n, Al Por Mayor)",
    "sg:phone":"+34 954 86 17 38",
    "sg:postcode":"41710",
    "sg:province":"Sevilla",
    "wof:name":"Chacon Alvarez Jose Luis",
    "wof:placetype":"venue"
},
  "geometry": {"coordinates":[-5.7832040787,37.1815376282],"type":"Point"}
}