{
  "type": "Feature",
  "properties": {
    "addr:full":"Carr Raval Del Pont, S/n Sant Antoli I Vilanova Lleida 25213",
    "addr:housenumber":"s",
    "addr:postcode":"25213",
    "addr:street":"Carr Raval Del Pont;/ N",
    "iso:country":"ES",
    "sg:address":"Carr Raval Del Pont, S/n",
    "sg:city":"Sant Antoli I Vilanova",
    "sg:orig_category":"Centros De Educaci\u00d3n Especial",
    "sg:phone":"+34 973 54 00 86",
    "sg:postcode":"25213",
    "sg:province":"Lleida",
    "wof:name":"Ajuntament Ribera D'ondara Escuelas Nacionales",
    "wof:placetype":"venue"
},
  "geometry": {"coordinates":[1.342218399,41.6276397705],"type":"Point"}
}