{
  "type": "Feature",
  "properties": {
    "iso:country":"ES",
    "sg:address":"Ctra Orihuela-pilar Horadada, 18",
    "sg:city":"Torremendo",
    "sg:orig_category":"Forjas Y Altos Hornos",
    "sg:phone":"+34 965 36 80 09",
    "sg:postcode":"03313",
    "sg:province":"Alicante",
    "wof:name":"Pacheco Campillo Antonio",
    "wof:placetype":"venue"
},
  "geometry": {"coordinates":[-0.9217389822,38.0595855713],"type":"Point"}
}