{
  "type": "Feature",
  "properties": {
    "iso:country":"ES",
    "sg:address":"Calle de Panaderos, 8",
    "sg:city":"Valladolid",
    "sg:orig_category":"Arquitectos",
    "sg:phone":"+34 983 29 00 27",
    "sg:postcode":"47004",
    "sg:province":"Valladolid",
    "wof:name":"Feijo Mu\u00f1oz Jesus",
    "wof:placetype":"venue"
},
  "geometry": {"coordinates":[-4.7239379883,41.6478385925],"type":"Point"}
}