{
  "type": "Feature",
  "properties": {
    "iso:country":"ES",
    "sg:address":"Carrer de Secretari Coloma, 44",
    "sg:city":"Barcelona",
    "sg:orig_category":"Fabricaci\u00d3n De Juegos Y Juguetes",
    "sg:phone":"+34 932 84 23 45",
    "sg:postcode":"08025",
    "sg:province":"Barcelona",
    "sg:website":"www.bcn_bebe.com",
    "wof:name":"Bcn Bebe S.c.c.l.",
    "wof:placetype":"venue"
},
  "geometry": {"coordinates":[2.1643779278,41.4083709717],"type":"Point"}
}