{
  "type": "Feature",
  "properties": {
    "iso:country":"ES",
    "sg:address":"Plaz Cardona Vives, 11",
    "sg:city":"Castellon",
    "sg:orig_category":"Herboristas (al Por Menor)",
    "sg:phone":"+34 964 26 09 02",
    "sg:postcode":"12001",
    "sg:province":"Castell\u00f3n",
    "wof:name":"Celeplame S.l.",
    "wof:placetype":"venue"
},
  "geometry": {"coordinates":[-0.0390900001,39.9866714478],"type":"Point"}
}