{
  "type": "Feature",
  "properties": {
    "addr:full":"Calle de Bizkai, 55 Galdakao Vizcaya 48960",
    "addr:housenumber":"55",
    "addr:postcode":"48960",
    "addr:street":"Calle De Bizkai",
    "iso:country":"ES",
    "sg:address":"Calle de Bizkai, 55",
    "sg:city":"Galdakao",
    "sg:orig_category":"Cristaler\u00cdas",
    "sg:phone":"+34 944 56 50 49",
    "sg:postcode":"48960",
    "sg:province":"Vizcaya",
    "wof:name":"Cristaleria  Urreta  -  Jose M. Arenaza",
    "wof:placetype":"venue"
},
  "geometry": {"coordinates":[-2.845757246,43.2340621948],"type":"Point"}
}