{
  "type": "Feature",
  "properties": {
    "addr:full":"Cerde\u00f1o, S/n Cerde\u00d1o Asturias 33010",
    "addr:postcode":"33010",
    "addr:street":"Cerden\u0303O S / N Cerden\u0303O Asturias",
    "iso:country":"ES",
    "sg:address":"Cerde\u00f1o, S/n",
    "sg:city":"Cerde\u00d1o",
    "sg:orig_category":"Fabricaci\u00d3n De Enlosados, Soler\u00cdas",
    "sg:phone":"+34 985 11 36 96",
    "sg:postcode":"33010",
    "sg:province":"Asturias",
    "sg:website":"www.porcelanosa.com",
    "wof:name":"Garcia Millan S.a.",
    "wof:placetype":"venue"
},
  "geometry": {"coordinates":[-5.8171038628,43.3708953857],"type":"Point"}
}