{
  "type": "Feature",
  "properties": {
    "iso:country":"ES",
    "sg:address":"Calle de Greco (el), 4",
    "sg:city":"Almansa",
    "sg:orig_category":"Fabricaci\u00d3n De Muebles",
    "sg:phone":"+34 967 34 37 15",
    "sg:postcode":"02640",
    "sg:province":"Albacete",
    "wof:name":"Muebles Mayfor S. L.",
    "wof:placetype":"venue"
},
  "geometry": {"coordinates":[-1.0969400406,38.8572387695],"type":"Point"}
}