{
  "type": "Feature",
  "properties": {
    "iso:country":"ES",
    "sg:address":"Calle de Granja (la), 9",
    "sg:city":"Sese\u00e7a Nuevo",
    "sg:orig_category":"Inform\u00c1tica, Ofim\u00c1tica (estudios, Asesor\u00cda, Ingenier\u00cda, Formaci\u00d3n)",
    "sg:phone":"+34 918 93 65 54",
    "sg:postcode":"45224",
    "sg:province":"Toledo",
    "wof:name":"Barreiro Garcia Fernando",
    "wof:placetype":"venue"
},
  "geometry": {"coordinates":[-3.6494669914,40.1070709229],"type":"Point"}
}