{
  "type": "Feature",
  "properties": {
    "addr:full":"Calle de Isaac Peral, 3 Leganes Madrid 28914",
    "addr:housenumber":"3",
    "addr:postcode":"28914",
    "addr:street":"Calle De Isaac Peral",
    "iso:country":"ES",
    "sg:address":"Calle de Isaac Peral, 3",
    "sg:city":"Leganes",
    "sg:orig_category":"Metales (labores, Pulido)",
    "sg:phone":"+34 916 80 41 39",
    "sg:postcode":"28914",
    "sg:province":"Madrid",
    "wof:name":"Gestamp Toledo S.l.",
    "wof:placetype":"venue"
},
  "geometry": {"coordinates":[-3.7450668812,40.3205223083],"type":"Point"}
}