{
  "type": "Feature",
  "properties": {
    "iso:country":"ES",
    "sg:address":"Rua Rosalia De Castro, 61",
    "sg:city":"Verin",
    "sg:orig_category":"Contenedores (mercanc\u00cdas)",
    "sg:phone":"+34 988 41 36 90",
    "sg:postcode":"32600",
    "sg:province":"Ourense",
    "wof:name":"Arias Saquete Hortensia",
    "wof:placetype":"venue"
},
  "geometry": {"coordinates":[-7.4310293198,41.9427070618],"type":"Point"}
}