{
  "type": "Feature",
  "properties": {
    "addr:full":"Ctra Ribes, 205 Corro D'avall Barcelona 08520",
    "addr:housenumber":"205",
    "addr:postcode":"08520",
    "addr:street":"Ctra Ribes;D'Avall Barcelona",
    "iso:country":"ES",
    "sg:address":"Ctra Ribes, 205",
    "sg:city":"Corro D'avall",
    "sg:orig_category":"Farmacias",
    "sg:phone":"+34 938 49 37 72",
    "sg:postcode":"08520",
    "sg:province":"Barcelona",
    "wof:name":"Jimenez Ucero Maria Del Pilar",
    "wof:placetype":"venue"
},
  "geometry": {"coordinates":[2.2878687382,41.6696929932],"type":"Point"}
}