{
  "type": "Feature",
  "properties": {
    "addr:full":"Calle de Santo Domingo, 2 Avila \u00c1vila 05001",
    "addr:housenumber":"2",
    "addr:postcode":"05001",
    "addr:street":"Calle De Santo Domingo;A\u0301Vila",
    "iso:country":"ES",
    "sg:address":"Calle de Santo Domingo, 2",
    "sg:city":"Avila",
    "sg:orig_category":"Comit\u00c9s De Organizaci\u00d3n De Exposiciones, Ferias, Salones",
    "sg:phone":"+34 920 25 33 25",
    "sg:postcode":"05001",
    "sg:province":"\u00c1vila",
    "wof:name":"Avila Servicios Turisticos S.l.u.",
    "wof:placetype":"venue"
},
  "geometry": {"coordinates":[-4.7037277222,40.6580619812],"type":"Point"}
}