{
  "type": "Feature",
  "properties": {
    "addr:full":"Calle de Carta Puebla, 4 Urbanizacion La Fresneda Asturias 33429",
    "addr:housenumber":"4",
    "addr:postcode":"33429",
    "addr:street":"Calle De Carta Puebla",
    "iso:country":"ES",
    "sg:address":"Calle de Carta Puebla, 4",
    "sg:city":"Urbanizacion La Fresneda",
    "sg:orig_category":"Centros Empresariales",
    "sg:phone":"+34 985 26 68 32",
    "sg:postcode":"33429",
    "sg:province":"Asturias",
    "wof:name":"Agrupacion De Alquiladores De Gruas De Servicio Publico De Asturias",
    "wof:placetype":"venue"
},
  "geometry": {"coordinates":[-5.7888607979,43.4130096436],"type":"Point"}
}