{
  "type": "Feature",
  "properties": {
    "iso:country":"ES",
    "sg:address":"Carrer de General Mendoza, 46",
    "sg:city":"Barcelona",
    "sg:orig_category":"Electricidad Veh\u00cdculo",
    "sg:phone":"+34 934 17 15 42",
    "sg:postcode":"08035",
    "sg:province":"Barcelona",
    "wof:name":"Torra Farran Enrique",
    "wof:placetype":"venue"
},
  "geometry": {"coordinates":[2.1428289413,41.4208068848],"type":"Point"}
}