{
  "type": "Feature",
  "properties": {
    "iso:country":"ES",
    "sg:address":"Calle de Cristobal De Fonseca, 4",
    "sg:city":"Malaga",
    "sg:orig_category":"Peluquer\u00cdas, Peluquer\u00cda Mixta",
    "sg:phone":"+34 952 65 20 08",
    "sg:postcode":"29014",
    "sg:province":"M\u00e1laga",
    "wof:name":"Segarra Lima Maria Jose",
    "wof:placetype":"venue"
},
  "geometry": {"coordinates":[-4.4213471413,36.7496833801],"type":"Point"}
}