{
  "type": "Feature",
  "properties": {
    "addr:full":"Plaz Mayor, 4 Cha\u00f1e Segovia 40216",
    "addr:housenumber":"4",
    "addr:postcode":"40216",
    "addr:street":"Plaz Mayor;Segovia",
    "iso:country":"ES",
    "sg:address":"Plaz Mayor, 4",
    "sg:city":"Cha\u00f1e",
    "sg:orig_category":"Cajas De Ahorro",
    "sg:phone":"+34 921 15 50 59",
    "sg:postcode":"40216",
    "sg:province":"Segovia",
    "wof:name":"Caja De Ahorros Y Monte De Piedad De Segovia",
    "wof:placetype":"venue"
},
  "geometry": {"coordinates":[-4.4277071953,41.3387870789],"type":"Point"}
}