{
  "type": "Feature",
  "properties": {
    "addr:full":"Calle de Rubi\u00d1os, 30 Sanlucar De Barrameda C\u00e1diz 11540",
    "addr:housenumber":"30",
    "addr:postcode":"11540",
    "addr:street":"Calle De Rubin\u0303Os;Ca\u0301Diz",
    "iso:country":"ES",
    "sg:address":"Calle de Rubi\u00d1os, 30",
    "sg:city":"Sanlucar De Barrameda",
    "sg:orig_category":"Panader\u00cdas, Panader\u00cdas",
    "sg:phone":"+34 956 36 00 42",
    "sg:postcode":"11540",
    "sg:province":"C\u00e1diz",
    "wof:name":"Dulces Tarteso S.l.",
    "wof:placetype":"venue"
},
  "geometry": {"coordinates":[-6.347299099,36.7834472656],"type":"Point"}
}