{
  "type": "Feature",
  "properties": {
    "iso:country":"ES",
    "sg:address":"Plaz Mayor, S/n",
    "sg:city":"Villaviudas",
    "sg:orig_category":"Cajas De Ahorro",
    "sg:phone":"+34 979 78 80 74",
    "sg:postcode":"34249",
    "sg:province":"Palencia",
    "sg:website":"www.cajaespana.es",
    "wof:name":"Caja Espa\u00f1a De Inversiones Caja De Ahorros Y Monte De Piedad",
    "wof:placetype":"venue"
},
  "geometry": {"coordinates":[-4.3422942162,41.9610710144],"type":"Point"}
}