{
  "type": "Feature",
  "properties": {
    "addr:full":"Carrer de Santa Clara, 8 Vilafranca Penedes Barcelona 08720",
    "addr:housenumber":"8",
    "addr:postcode":"08720",
    "addr:street":"Carrer De Santa Clara;Penedes Barcelona",
    "iso:country":"ES",
    "sg:address":"Carrer de Santa Clara, 8",
    "sg:city":"Vilafranca Penedes",
    "sg:orig_category":"Agencias De Trabajo Temporal",
    "sg:phone":"+34 938 92 41 62",
    "sg:postcode":"08720",
    "sg:province":"Barcelona",
    "wof:name":"Manpower Team Empresas De Trabajo Temporal",
    "wof:placetype":"venue"
},
  "geometry": {"coordinates":[1.7015759945,41.3463592529],"type":"Point"}
}