{
  "type": "Feature",
  "properties": {
    "addr:full":"Rbla San Julian (de), 13 Teruel Teruel 44003",
    "addr:housenumber":"13",
    "addr:postcode":"44003",
    "addr:street":"Rbla San Julian De",
    "iso:country":"ES",
    "sg:address":"Rbla San Julian (de), 13",
    "sg:city":"Teruel",
    "sg:orig_category":"Cajas Para Embalar",
    "sg:phone":"+34 978 61 12 70",
    "sg:postcode":"44003",
    "sg:province":"Teruel",
    "sg:website":"www.cajarural.com",
    "wof:name":"Caja Rural De Teruel",
    "wof:placetype":"venue"
},
  "geometry": {"coordinates":[-1.104164958,40.3397674561],"type":"Point"}
}