{
  "type": "Feature",
  "properties": {
    "iso:country":"ES",
    "sg:address":"Urb Balcon Del Golf, 23",
    "sg:city":"Nueva Andalucia",
    "sg:orig_category":"Inmobiliaria (agencias)",
    "sg:phone":"+34 952 90 83 20",
    "sg:postcode":"29660",
    "sg:province":"M\u00e1laga",
    "wof:name":"Capon  Elisabet",
    "wof:placetype":"venue"
},
  "geometry": {"coordinates":[-4.9712438583,36.5208396912],"type":"Point"}
}