{
  "type": "Feature",
  "properties": {
    "addr:full":"Calle de Grillo, 11 Salamanca Salamanca 37001",
    "addr:housenumber":"11",
    "addr:postcode":"37001",
    "addr:street":"Calle De Grillo",
    "iso:country":"ES",
    "sg:address":"Calle de Grillo, 11",
    "sg:city":"Salamanca",
    "sg:orig_category":"Restaurantes",
    "sg:phone":"+34 923 21 37 18",
    "sg:postcode":"37001",
    "sg:province":"Salamanca",
    "wof:name":"Itxiar Fb S.l.",
    "wof:placetype":"venue"
},
  "geometry": {"coordinates":[-5.6598601341,40.9629859924],"type":"Point"}
}