{
  "type": "Feature",
  "properties": {
    "iso:country":"ES",
    "sg:address":"Plaz Alcalde De La Moneda, 5",
    "sg:city":"Baena",
    "sg:orig_category":"M\u00c9dicos: Ginecolog\u00cda Y Obstetricia",
    "sg:phone":"+34 957 67 06 49",
    "sg:postcode":"14850",
    "sg:province":"C\u00f3rdoba",
    "wof:name":"Zarif Cherem Mounir",
    "wof:placetype":"venue"
},
  "geometry": {"coordinates":[-4.2948884964,37.6670646667],"type":"Point"}
}