{
  "type": "Feature",
  "properties": {
    "addr:full":"Ctra Maderuelo, S/n Campo De San Pedro Segovia 40551",
    "addr:housenumber":"s / n",
    "addr:postcode":"40551",
    "addr:street":"Ctra Maderuelo",
    "iso:country":"ES",
    "sg:address":"Ctra Maderuelo, S/n",
    "sg:city":"Campo De San Pedro",
    "sg:orig_category":"Distribuci\u00d3n De Petr\u00d3leo Y Derivados",
    "sg:phone":"+34 921 55 62 06",
    "sg:postcode":"40551",
    "sg:province":"Segovia",
    "wof:name":"Buquerin Gutierrez Felix",
    "wof:placetype":"venue"
},
  "geometry": {"coordinates":[-3.5454800129,41.4315490723],"type":"Point"}
}