{
  "type": "Feature",
  "properties": {
    "iso:country":"ES",
    "sg:address":"Calle de Rocio Durcal, 58",
    "sg:city":"Durcal",
    "sg:orig_category":"Empresas De Pintura Y Revestimientos",
    "sg:phone":"+34 958 78 09 75",
    "sg:postcode":"18650",
    "sg:province":"Granada",
    "wof:name":"Perez Arroyo Juan Antonio",
    "wof:placetype":"venue"
},
  "geometry": {"coordinates":[-3.5695669651,36.9861793518],"type":"Point"}
}