{
  "type": "Feature",
  "properties": {
    "addr:full":"Carrer de Miquel Ferra, 6 Barcelona Barcelona 08031",
    "addr:housenumber":"6",
    "addr:postcode":"08031",
    "addr:street":"Carrer De Miquel Ferra",
    "iso:country":"ES",
    "sg:address":"Carrer de Miquel Ferra, 6",
    "sg:city":"Barcelona",
    "sg:orig_category":"Asesor\u00cda Fiscal Y Jur\u00cddica",
    "sg:phone":"+34 933 58 54 11",
    "sg:postcode":"08031",
    "sg:province":"Barcelona",
    "wof:name":"Serp Asesores S.l.",
    "wof:placetype":"venue"
},
  "geometry": {"coordinates":[2.1726930141,41.4299278259],"type":"Point"}
}