{
  "type": "Feature",
  "properties": {
    "iso:country":"ES",
    "sg:address":"Calle de Altamira, 3",
    "sg:city":"Almeria",
    "sg:orig_category":"Administradores De Bienes Y Delegados De Comunidades De Propietarios",
    "sg:phone":"+34 950 25 70 90",
    "sg:postcode":"04005",
    "sg:province":"Almer\u00eda",
    "wof:name":"Capel Salvador Maria Del Pilar",
    "wof:placetype":"venue"
},
  "geometry": {"coordinates":[-2.458666563,36.8379058838],"type":"Point"}
}