{
  "type": "Feature",
  "properties": {
    "addr:full":"Carr Enric Granados, 3 Miralcamp Lleida 25242",
    "addr:housenumber":"3",
    "addr:postcode":"25242",
    "addr:street":"Carr Enric Granados",
    "iso:country":"ES",
    "sg:address":"Carr Enric Granados, 3",
    "sg:city":"Miralcamp",
    "sg:orig_category":"Suministros Para Carrocer\u00cdas",
    "sg:phone":"+34 973 60 28 57",
    "sg:postcode":"25242",
    "sg:province":"Lleida",
    "wof:name":"Sole Gaya Antonio",
    "wof:placetype":"venue"
},
  "geometry": {"coordinates":[0.8803300261,41.6029663086],"type":"Point"}
}