{
  "type": "Feature",
  "properties": {
    "iso:country":"ES",
    "sg:address":"Pg Manresa, 41",
    "sg:city":"Sabadell",
    "sg:orig_category":"Bisuter\u00cda, Joyer\u00cda, Relojer\u00cda (al Por Menor)",
    "sg:phone":"+34 937 25 65 74",
    "sg:postcode":"08201",
    "sg:province":"Barcelona",
    "wof:name":"Domenech-grau Joiers S.l.",
    "wof:placetype":"venue"
},
  "geometry": {"coordinates":[2.1080880165,41.5491218567],"type":"Point"}
}