{
  "type": "Feature",
  "properties": {
    "addr:full":"Virgen De Monserrat, S/n Virgen De Monserrat Valencia 46192",
    "addr:housenumber":"s / n",
    "addr:postcode":"46192",
    "addr:street":"Virgen",
    "iso:country":"ES",
    "sg:address":"Virgen De Monserrat, S/n",
    "sg:city":"Virgen De Monserrat",
    "sg:orig_category":"Forjas Y Altos Hornos",
    "sg:phone":"+34 962 99 94 24",
    "sg:postcode":"46192",
    "sg:province":"Valencia",
    "wof:name":"Rubio Lopez Jose",
    "wof:placetype":"venue"
},
  "geometry": {"coordinates":[-0.5983390212,39.3566665649],"type":"Point"}
}