{
  "type": "Feature",
  "properties": {
    "addr:full":"Calle de Cuba, 12 Aviles Asturias 33401",
    "addr:housenumber":"12",
    "addr:postcode":"33401",
    "addr:street":"Calle De Cuba",
    "iso:country":"ES",
    "sg:address":"Calle de Cuba, 12",
    "sg:city":"Aviles",
    "sg:orig_category":"Caf\u00c9s, Bares, Cervecer\u00cdas",
    "sg:phone":"+34 985 56 92 61",
    "sg:postcode":"33401",
    "sg:province":"Asturias",
    "wof:name":"Rubio Ramos Leopoldo",
    "wof:placetype":"venue"
},
  "geometry": {"coordinates":[-5.9263854027,43.5572319031],"type":"Point"}
}