{
  "type": "Feature",
  "properties": {
    "iso:country":"ES",
    "sg:address":"Calle de Pasion, 13",
    "sg:city":"Valladolid",
    "sg:orig_category":"Promotores Constructores",
    "sg:phone":"+34 983 35 97 66",
    "sg:postcode":"47001",
    "sg:province":"Valladolid",
    "wof:name":"De La Torre Promociones Y Obras S. A.",
    "wof:placetype":"venue"
},
  "geometry": {"coordinates":[-4.7298550606,41.6512680054],"type":"Point"}
}