{
  "type": "Feature",
  "properties": {
    "addr:full":"Calle de Malaga, 3 Brenes Sevilla 41310",
    "addr:housenumber":"3",
    "addr:postcode":"41310",
    "addr:street":"Calle De Malaga",
    "iso:country":"ES",
    "sg:address":"Calle de Malaga, 3",
    "sg:city":"Brenes",
    "sg:orig_category":"Mec\u00c1nico Del Autom\u00d3vil",
    "sg:phone":"+34 954 79 71 05",
    "sg:postcode":"41310",
    "sg:province":"Sevilla",
    "wof:name":"Nofuente Serrano Rafael",
    "wof:placetype":"venue"
},
  "geometry": {"coordinates":[-5.8764958382,37.5451774597],"type":"Point"}
}