{
  "type": "Feature",
  "properties": {
    "iso:country":"ES",
    "sg:address":"Carrer de Estrasburg, 5",
    "sg:city":"Mataro",
    "sg:orig_category":"Higiene, Belleza: Art\u00cdculos (al Por Menor)",
    "sg:phone":"+34 937 57 49 82",
    "sg:postcode":"08303",
    "sg:province":"Barcelona",
    "wof:name":"Marmai S.c.p.",
    "wof:placetype":"venue"
},
  "geometry": {"coordinates":[2.4351708889,41.5547561646],"type":"Point"}
}