{
  "type": "Feature",
  "properties": {
    "addr:full":"Calle de San Andres, 19 Malaga M\u00e1laga 29002",
    "addr:housenumber":"19",
    "addr:postcode":"29002",
    "addr:street":"Calle De San Andres;Ma\u0301Laga",
    "iso:country":"ES",
    "sg:address":"Calle de San Andres, 19",
    "sg:city":"Malaga",
    "sg:orig_category":"Promotores Constructores",
    "sg:phone":"+34 952 35 76 64",
    "sg:postcode":"29002",
    "sg:province":"M\u00e1laga",
    "wof:name":"Contrat Ingenieria Y Obras S.a.",
    "wof:placetype":"venue"
},
  "geometry": {"coordinates":[-4.427959919,36.7122306824],"type":"Point"}
}