{
  "type": "Feature",
  "properties": {
    "iso:country":"ES",
    "sg:address":"Calle de Brianda De Olivera, 6",
    "sg:city":"Le\u00f3n",
    "sg:orig_category":"Juegos Y Juguetes (al Por Menor)",
    "sg:phone":"+34 987 25 19 19",
    "sg:postcode":"24005",
    "sg:province":"Le\u00f3n",
    "wof:name":"Mini Ocio Leon S.l.",
    "wof:placetype":"venue"
},
  "geometry": {"coordinates":[-5.5686984062,42.5882873535],"type":"Point"}
}