{
  "type": "Feature",
  "properties": {
    "addr:full":"Calle de Rioseco, 68 Palma Rio C\u00f3rdoba 14700",
    "addr:housenumber":"68",
    "addr:postcode":"14700",
    "addr:street":"Calle De Rioseco;Rio Co\u0301Rdoba",
    "iso:country":"ES",
    "sg:address":"Calle de Rioseco, 68",
    "sg:city":"Palma Rio",
    "sg:orig_category":"Arquitectos",
    "sg:phone":"+34 957 71 06 73",
    "sg:postcode":"14700",
    "sg:province":"C\u00f3rdoba",
    "wof:name":"Egea Nieto Cesar",
    "wof:placetype":"venue"
},
  "geometry": {"coordinates":[-5.2847008705,37.6984863281],"type":"Point"}
}