{
  "type": "Feature",
  "properties": {
    "addr:full":"Carrer de Clot, 47 Barcelona Barcelona 08018",
    "addr:housenumber":"47",
    "addr:postcode":"08018",
    "addr:street":"Carrer De Clot",
    "iso:country":"ES",
    "sg:address":"Carrer de Clot, 47",
    "sg:city":"Barcelona",
    "sg:orig_category":"Abogados",
    "sg:phone":"+34 932 45 95 26",
    "sg:postcode":"08018",
    "sg:province":"Barcelona",
    "wof:name":"Vilet Sanz Monica",
    "wof:placetype":"venue"
},
  "geometry": {"coordinates":[2.1879270077,41.4076576233],"type":"Point"}
}