{
  "type": "Feature",
  "properties": {
    "iso:country":"ES",
    "sg:address":"Psaj Platero Alcantara, 12",
    "sg:city":"Cordoba",
    "sg:orig_category":"Peluqueros: De Se\u00d1oras",
    "sg:phone":"+34 957 75 13 73",
    "sg:postcode":"14010",
    "sg:province":"C\u00f3rdoba",
    "wof:name":"Ruiz Jurado Antonio Jose",
    "wof:placetype":"venue"
},
  "geometry": {"coordinates":[-4.7650489807,37.8792991638],"type":"Point"}
}