{
  "type": "Feature",
  "properties": {
    "iso:country":"ES",
    "sg:address":"Calle de Feria, 1",
    "sg:city":"Mula",
    "sg:orig_category":"Producci\u00d3n, Distribuci\u00d3n De Gas Butano Y Propano",
    "sg:phone":"+34 968 66 02 28",
    "sg:postcode":"30170",
    "sg:province":"Murcia",
    "wof:name":"Mariana Sandoval S.l.",
    "wof:placetype":"venue"
},
  "geometry": {"coordinates":[-1.4893920422,38.0381088257],"type":"Point"}
}