{
  "type": "Feature",
  "properties": {
    "addr:full":"Carretera De Jerez, 38 Valle Sta Ana Badajoz 06178",
    "addr:housenumber":"38",
    "addr:postcode":"06178",
    "addr:street":"Carretera De Jerez;Sta",
    "iso:country":"ES",
    "sg:address":"Carretera De Jerez, 38",
    "sg:city":"Valle Sta Ana",
    "sg:classifiers":[
        {
            "category":"Autos & Motor Vehicles",
            "subcategory":"Automobile Sales",
            "type":"Retail Goods"
        }
    ],
    "sg:phone":"+34 924 75 35 26",
    "sg:postcode":"06178",
    "sg:province":"Badajoz",
    "wof:name":"Mendez Vazquez Manuel",
    "wof:placetype":"venue"
},
  "geometry": {"coordinates":[-6.7894067764,38.364490509],"type":"Point"}
}