{
  "type": "Feature",
  "properties": {
    "iso:country":"ES",
    "sg:address":"Psaj Santa Rita De Casia, 6",
    "sg:city":"Benidorm",
    "sg:orig_category":"Cl\u00cdnicas Dentales",
    "sg:phone":"+34 966 88 90 76",
    "sg:postcode":"03500",
    "sg:province":"Alicante",
    "wof:name":"Romero Weise Andres",
    "wof:placetype":"venue"
},
  "geometry": {"coordinates":[-0.1739459932,38.5365180969],"type":"Point"}
}