{
  "type": "Feature",
  "properties": {
    "addr:full":"C/ Doctor Caro, 49 Elche Alicante 03201",
    "addr:housenumber":"49",
    "addr:postcode":"03201",
    "addr:street":"C / Doctor Caro",
    "iso:country":"ES",
    "sg:address":"C/ Doctor Caro, 49",
    "sg:city":"Elche",
    "sg:orig_category":"M\u00c9dicos: Estomatolog\u00cda",
    "sg:phone":"+34 965 44 45 62",
    "sg:postcode":"03201",
    "sg:province":"Alicante",
    "wof:name":"Robledano Garcia Inmaculada Concepcion",
    "wof:placetype":"venue"
},
  "geometry": {"coordinates":[-0.7010340095,38.2679214478],"type":"Point"}
}