{
  "type": "Feature",
  "properties": {
    "addr:full":"P. Barace, 5 Iru\u00f1a Navarra 31007",
    "addr:housenumber":"5",
    "addr:postcode":"31007",
    "addr:street":"P. Barace",
    "iso:country":"ES",
    "sg:address":"P. Barace, 5",
    "sg:city":"Iru\u00f1a",
    "sg:orig_category":"Sindicatos De Trabajadores",
    "sg:phone":"+34 948 26 15 00",
    "sg:postcode":"31007",
    "sg:province":"Navarra",
    "wof:name":"Confederacion De Cuadros Y Profesionales",
    "wof:placetype":"venue"
},
  "geometry": {"coordinates":[-1.6469980478,42.8060646057],"type":"Point"}
}