{
  "type": "Feature",
  "properties": {
    "iso:country":"ES",
    "sg:address":"Calle de Cortes De La Frontera, 32",
    "sg:city":"Malaga",
    "sg:orig_category":"Centros De Coordinaci\u00d3n",
    "sg:phone":"+34 952 31 18 15",
    "sg:postcode":"29006",
    "sg:province":"M\u00e1laga",
    "wof:name":"Kripsol Intermark Malaga S.l.",
    "wof:placetype":"venue"
},
  "geometry": {"coordinates":[-4.4659442902,36.7028961182],"type":"Point"}
}