{
  "type": "Feature",
  "properties": {
    "addr:full":"H. De Rivera, 9 Puigcerda Girona 17520",
    "addr:housenumber":"9",
    "addr:postcode":"17520",
    "addr:street":"H. De Rivera",
    "iso:country":"ES",
    "sg:address":"H. De Rivera, 9",
    "sg:city":"Puigcerda",
    "sg:orig_category":"Arquitectos",
    "sg:phone":"+34 972 14 08 22",
    "sg:postcode":"17520",
    "sg:province":"Girona",
    "wof:name":"Fito Gisper Amadeo",
    "wof:placetype":"venue"
},
  "geometry": {"coordinates":[1.9278999567,42.4336547852],"type":"Point"}
}