{
  "type": "Feature",
  "properties": {
    "addr:full":"Avda Mediterraneo, 28 Madrid Madrid 28007",
    "addr:housenumber":"28",
    "addr:postcode":"madrid;28007",
    "addr:street":"Avda Mediterraneo",
    "iso:country":"ES",
    "sg:address":"Avda Mediterraneo, 28",
    "sg:city":"Madrid",
    "sg:orig_category":"Inmobiliaria (agencias)",
    "sg:phone":"+34 914 33 70 90",
    "sg:postcode":"28007",
    "sg:province":"Madrid",
    "wof:name":"Ven Activa",
    "wof:placetype":"venue"
},
  "geometry": {"coordinates":[-3.6733000278,40.406879425],"type":"Point"}
}