{
  "type": "Feature",
  "properties": {
    "addr:full":"Calle de Gabriel Paya, 20 Petrer Alicante 03610",
    "addr:housenumber":"20",
    "addr:postcode":"03610",
    "addr:street":"Calle De Gabriel Paya",
    "iso:country":"ES",
    "sg:address":"Calle de Gabriel Paya, 20",
    "sg:city":"Petrer",
    "sg:orig_category":"Cajas Para Embalar",
    "sg:phone":"+34 965 37 08 00",
    "sg:postcode":"03610",
    "sg:province":"Alicante",
    "wof:name":"Caja De Credito De Petrel",
    "wof:placetype":"venue"
},
  "geometry": {"coordinates":[-0.7737309933,38.4846992493],"type":"Point"}
}