{
  "type": "Feature",
  "properties": {
    "addr:full":"Calle de Pilar De Zaragoza, 43 Madrid Madrid 28028",
    "addr:housenumber":"43",
    "addr:postcode":"madrid;28028",
    "addr:street":"Calle De Pilar De Zaragoza",
    "iso:country":"ES",
    "sg:address":"Calle de Pilar De Zaragoza, 43",
    "sg:city":"Madrid",
    "sg:orig_category":"Relojer\u00cda Industrial",
    "sg:phone":"+34 917 26 20 01",
    "sg:postcode":"28028",
    "sg:province":"Madrid",
    "wof:name":"Graking S.l.",
    "wof:placetype":"venue"
},
  "geometry": {"coordinates":[-3.6706180573,40.4348297119],"type":"Point"}
}