{
  "type": "Feature",
  "properties": {
    "addr:full":"Calle de Antonio Rubio Torres, 3 Fuengirola M\u00e1laga 29640",
    "addr:housenumber":"3",
    "addr:postcode":"29640",
    "addr:street":"Calle De Antonio Rubio Torres;Ma\u0301Laga",
    "iso:country":"ES",
    "sg:address":"Calle de Antonio Rubio Torres, 3",
    "sg:city":"Fuengirola",
    "sg:orig_category":"Peluqueros: De Se\u00d1oras",
    "sg:phone":"+34 952 46 52 59",
    "sg:postcode":"29640",
    "sg:province":"M\u00e1laga",
    "wof:name":"Peluqueria Celi",
    "wof:placetype":"venue"
},
  "geometry": {"coordinates":[-4.6227397919,36.5422325134],"type":"Point"}
}