{
  "type": "Feature",
  "properties": {
    "addr:full":"Avda Republica Argentina, 3 Paredes Nava Palencia 34300",
    "addr:housenumber":"3",
    "addr:postcode":"34300",
    "addr:street":"Avda Republica Argentina",
    "iso:country":"ES",
    "sg:address":"Avda Republica Argentina, 3",
    "sg:city":"Paredes Nava",
    "sg:orig_category":"Asesor\u00cda Sobre Comunicaci\u00d3n De Empresas",
    "sg:phone":"+34 979 83 02 63",
    "sg:postcode":"34300",
    "sg:province":"Palencia",
    "wof:name":"Villamuza Y Pe\u00f1a S.l.",
    "wof:placetype":"venue"
},
  "geometry": {"coordinates":[-4.6880588531,42.1550292969],"type":"Point"}
}