{
  "type": "Feature",
  "properties": {
    "addr:full":"Calle de Agustina De Aragon, 3 Madrid Madrid 28006",
    "addr:housenumber":"3",
    "addr:postcode":"28006",
    "addr:street":"Calle De Agustina De Aragon",
    "iso:country":"ES",
    "sg:address":"Calle de Agustina De Aragon, 3",
    "sg:city":"Madrid",
    "sg:orig_category":"Publicidad (soportes Y Gesti\u00d3n)",
    "sg:phone":"+34 914 02 83 19",
    "sg:postcode":"28006",
    "sg:province":"Madrid",
    "wof:name":"Heredero Lozano Francisco",
    "wof:placetype":"venue"
},
  "geometry": {"coordinates":[-3.6726458073,40.4316520691],"type":"Point"}
}