{
  "type": "Feature",
  "properties": {
    "iso:country":"ES",
    "sg:address":"Ptor Antoni Gelabert, 1",
    "sg:city":"Es Figueral",
    "sg:orig_category":"Alimentaci\u00d3n General (al Por Menor)",
    "sg:phone":"+34 971 60 54 03",
    "sg:postcode":"07141",
    "sg:province":"Islas Baleares",
    "wof:name":"Alcubilla Morell Sl",
    "wof:placetype":"venue"
},
  "geometry": {"coordinates":[2.724814415,39.6188316345],"type":"Point"}
}