{
  "type": "Feature",
  "properties": {
    "iso:country":"ES",
    "sg:address":"Calle de Francisco Cubria, S/n",
    "sg:city":"Santander",
    "sg:orig_category":"Caf\u00c9s, Bares, Cervecer\u00cdas",
    "sg:phone":"+34 942 23 08 35",
    "sg:postcode":"39007",
    "sg:province":"Cantabria",
    "wof:name":"Ruigarluga S L",
    "wof:placetype":"venue"
},
  "geometry": {"coordinates":[-3.8192439079,43.4616851807],"type":"Point"}
}