{
  "type": "Feature",
  "properties": {
    "iso:country":"ES",
    "sg:address":"Calle de Estepa, 9",
    "sg:city":"Roda Andalucia",
    "sg:orig_category":"Agencias Y Agentes Comerciales, Representantes",
    "sg:phone":"+34 954 01 61 16",
    "sg:postcode":"41590",
    "sg:province":"Sevilla",
    "wof:name":"Walker  Sandra Marilynne",
    "wof:placetype":"venue"
},
  "geometry": {"coordinates":[-4.7772655487,37.2054901123],"type":"Point"}
}