{
  "type": "Feature",
  "properties": {
    "addr:full":"Calle de Escandon, 4 Madrid Madrid 28021",
    "addr:housenumber":"4",
    "addr:postcode":"28021",
    "addr:street":"Calle De Escandon",
    "iso:country":"ES",
    "sg:address":"Calle de Escandon, 4",
    "sg:city":"Madrid",
    "sg:orig_category":"Inmobiliaria (agencias)",
    "sg:phone":"+34 915 05 10 15",
    "sg:postcode":"28021",
    "sg:province":"Madrid",
    "wof:name":"Planning Home Servicios Inmobiliarios S.l.",
    "wof:placetype":"venue"
},
  "geometry": {"coordinates":[-3.7097580433,40.3452301025],"type":"Point"}
}