{
  "type": "Feature",
  "properties": {
    "addr:full":"Calle de Luis Mitjans, 28 Madrid Madrid 28007",
    "addr:housenumber":"28",
    "addr:postcode":"madrid;28007",
    "addr:street":"Calle De Luis Mitjans",
    "iso:country":"ES",
    "sg:address":"Calle de Luis Mitjans, 28",
    "sg:city":"Madrid",
    "sg:orig_category":"Perfumer\u00cda (al Por Menor)",
    "sg:phone":"+34 914 33 57 12",
    "sg:postcode":"28007",
    "sg:province":"Madrid",
    "wof:name":"La Walkiria Cia Internacional De Perfumeria S.l.",
    "wof:placetype":"venue"
},
  "geometry": {"coordinates":[-3.6705029011,40.4004859924],"type":"Point"}
}