{
  "type": "Feature",
  "properties": {
    "iso:country":"ES",
    "sg:address":"Carr Esglesia, De L', 14",
    "sg:city":"Pobla",
    "sg:orig_category":"Ropa Para Se\u00d1oras Y Caballeros (al Por Menor)",
    "sg:phone":"+34 971 86 20 23",
    "sg:postcode":"07420",
    "sg:province":"Islas Baleares",
    "wof:name":"March Muntaner Magdalena",
    "wof:placetype":"venue"
},
  "geometry": {"coordinates":[2.9117100239,39.6136398315],"type":"Point"}
}