{
  "type": "Feature",
  "properties": {
    "iso:country":"ES",
    "sg:address":"Avda Juan Pablo Ii, 13",
    "sg:city":"Pozuelo De Alarcon",
    "sg:orig_category":"Bisuter\u00cda, Joyer\u00cda, Relojer\u00cda (al Por Menor)",
    "sg:phone":"+34 913 52 01 23",
    "sg:postcode":"28224",
    "sg:province":"Madrid",
    "wof:name":"Valresa S. A.",
    "wof:placetype":"venue"
},
  "geometry": {"coordinates":[-3.8024759293,40.4468917847],"type":"Point"}
}