{
  "type": "Feature",
  "properties": {
    "iso:country":"ES",
    "sg:address":"Poligono Ind. Vincios, 8",
    "sg:city":"Vincios",
    "sg:orig_category":"Fabricaci\u00d3n, Instalaci\u00d3n Y Reparaci\u00d3n De Bombas",
    "sg:phone":"+34 986 46 81 27",
    "sg:postcode":"36316",
    "sg:province":"Pontevedra",
    "wof:name":"Macroinsa S.l.",
    "wof:placetype":"venue"
},
  "geometry": {"coordinates":[-8.7297039032,42.1394195557],"type":"Point"}
}