{
  "type": "Feature",
  "properties": {
    "addr:full":"Carrer de Pla\u00c7a, 62 Premia Mar Barcelona 08330",
    "addr:housenumber":"62",
    "addr:postcode":"08330",
    "addr:street":"Carrer De Plac\u0327A",
    "iso:country":"ES",
    "sg:address":"Carrer de Pla\u00c7a, 62",
    "sg:city":"Premia Mar",
    "sg:orig_category":"Ense\u00d1anza: Comercio, Gesti\u00d3n, Inform\u00c1tica",
    "sg:phone":"+34 937 54 70 25",
    "sg:postcode":"08330",
    "sg:province":"Barcelona",
    "wof:name":"Premia Invest S.l.",
    "wof:placetype":"venue"
},
  "geometry": {"coordinates":[2.3556408882,41.4920120239],"type":"Point"}
}