{
  "type": "Feature",
  "properties": {
    "addr:full":"Pol Ind, 1 Torroella Montgri Girona 17257",
    "addr:postcode":"17257",
    "addr:street":"Ind;Torroella",
    "iso:country":"ES",
    "sg:address":"Pol Ind, 1",
    "sg:city":"Torroella Montgri",
    "sg:orig_category":"Farmacias",
    "sg:phone":"+34 972 75 71 15",
    "sg:postcode":"17257",
    "sg:province":"Girona",
    "wof:name":"Ferrer Bartra Montserrat",
    "wof:placetype":"venue"
},
  "geometry": {"coordinates":[3.1034500599,42.0303268433],"type":"Point"}
}