{
  "type": "Feature",
  "properties": {
    "iso:country":"ES",
    "sg:address":"Afores, Km. 0060,0",
    "sg:city":"Tona",
    "sg:orig_category":"Cr\u00cda De Animales",
    "sg:phone":"+34 938 87 15 04",
    "sg:postcode":"08551",
    "sg:province":"Barcelona",
    "wof:name":"Grup Baucells Alimentacio S.a.",
    "wof:placetype":"venue"
},
  "geometry": {"coordinates":[2.229569912,41.8518257141],"type":"Point"}
}