{
  "type": "Feature",
  "properties": {
    "addr:full":"Carretera De Soano, 2 Soano Cantabria 39193",
    "addr:housenumber":"2",
    "addr:postcode":"39193",
    "addr:street":"Carretera De Soano",
    "iso:country":"ES",
    "sg:address":"Carretera De Soano, 2",
    "sg:city":"Soano",
    "sg:orig_category":"Pescader\u00cdas (al Por Menor)",
    "sg:phone":"+34 942 63 05 88",
    "sg:postcode":"39193",
    "sg:province":"Cantabria",
    "wof:name":"Pescados J.sanchez S.l.",
    "wof:placetype":"venue"
},
  "geometry": {"coordinates":[-3.5410709381,43.4605445862],"type":"Point"}
}