{
  "type": "Feature",
  "properties": {
    "addr:full":"Calle de Pintor Murillo (del), 31 Alcobendas Madrid 28100",
    "addr:postcode":"28100",
    "addr:street":"Calle De Pintor Murillo Del;Alcobendas",
    "iso:country":"ES",
    "sg:address":"Calle de Pintor Murillo (del), 31",
    "sg:city":"Alcobendas",
    "sg:orig_category":"Ropa Para Ni\u00d1os (al Por Menor)",
    "sg:phone":"+34 916 62 39 23",
    "sg:postcode":"28100",
    "sg:province":"Madrid",
    "sg:website":"www.palomaensenat.com",
    "wof:name":"Lopez Diez Rocio",
    "wof:placetype":"venue"
},
  "geometry": {"coordinates":[-3.6492269039,40.5441741943],"type":"Point"}
}