{
  "type": "Feature",
  "properties": {
    "addr:full":"Calle de Luciano Lopez Ferrer, 7 Villena Alicante 03400",
    "addr:housenumber":"7",
    "addr:postcode":"03400",
    "addr:street":"Calle De Luciano Lopez Ferrer",
    "iso:country":"ES",
    "sg:address":"Calle de Luciano Lopez Ferrer, 7",
    "sg:city":"Villena",
    "sg:orig_category":"Pintura, Barniz, Productos Asimilables (fabricaci\u00d3n, Al Por Mayor)",
    "sg:phone":"+34 965 80 62 91",
    "sg:postcode":"03400",
    "sg:province":"Alicante",
    "wof:name":"Pinturas Nieto S.a.",
    "wof:placetype":"venue"
},
  "geometry": {"coordinates":[-0.8656787872,38.6313934326],"type":"Point"}
}