{
  "type": "Feature",
  "properties": {
    "iso:country":"ES",
    "sg:address":"Calle de Santiago Ramon Y Cajal, 180",
    "sg:city":"Cartagena",
    "sg:classifiers":[
        {
            "category":"Arts & Performance",
            "subcategory":"Art Gallery",
            "type":"Entertainment"
        }
    ],
    "sg:phone":"+34 968 51 16 82",
    "sg:postcode":"30300",
    "sg:province":"Murcia",
    "sg:tags":[
        "arte",
        "de",
        "galer\u00cdas"
    ],
    "wof:name":"Garcia Perez Gines",
    "wof:placetype":"venue"
},
  "geometry": {"coordinates":[-0.9958069921,37.6217498779],"type":"Point"}
}