{
  "type": "Feature",
  "properties": {
    "addr:full":"Calle de Rafael Gonzalez Abreu, 16 Sevilla Sevilla 41001",
    "addr:housenumber":"16",
    "addr:postcode":"41001",
    "addr:street":"Calle De Rafael;Abreu",
    "iso:country":"ES",
    "sg:address":"Calle de Rafael Gonzalez Abreu, 16",
    "sg:city":"Sevilla",
    "sg:orig_category":"Notarios",
    "sg:phone":"+34 954 21 14 01",
    "sg:postcode":"41001",
    "sg:province":"Sevilla",
    "wof:name":"Lea Fernandez Rafael",
    "wof:placetype":"venue"
},
  "geometry": {"coordinates":[-5.9998841286,37.3903579712],"type":"Point"}
}