{
  "type": "Feature",
  "properties": {
    "addr:full":"Calle de San Antonio, 1 Andujar Ja\u00e9n 23740",
    "addr:housenumber":"1",
    "addr:postcode":"23740",
    "addr:street":"Calle De San Antonio",
    "iso:country":"ES",
    "sg:address":"Calle de San Antonio, 1",
    "sg:city":"Andujar",
    "sg:orig_category":"Ropa Para Se\u00d1oras Y Caballeros (al Por Menor)",
    "sg:phone":"+34 953 51 14 80",
    "sg:postcode":"23740",
    "sg:province":"Ja\u00e9n",
    "wof:name":"Antonio Molina 2000 S.l.",
    "wof:placetype":"venue"
},
  "geometry": {"coordinates":[-4.0551643372,38.0401496887],"type":"Point"}
}