{
  "type": "Feature",
  "properties": {
    "addr:full":"Avda San Cayetano, 1 Mirador Murcia 30739",
    "addr:housenumber":"1",
    "addr:postcode":"30739",
    "addr:street":"Avda San Cayetano",
    "iso:country":"ES",
    "sg:address":"Avda San Cayetano, 1",
    "sg:city":"Mirador",
    "sg:orig_category":"Delegados, Agentes De Tr\u00c1nsito, Auxiliares De Transporte Internacional",
    "sg:phone":"+34 968 17 44 01",
    "sg:postcode":"30739",
    "sg:province":"Murcia",
    "wof:name":"Transportes El Mirador Miratrans S.l.",
    "wof:placetype":"venue"
},
  "geometry": {"coordinates":[-0.8710790277,37.7799987793],"type":"Point"}
}