{
  "type": "Feature",
  "properties": {
    "iso:country":"ES",
    "sg:address":"Ctra Leon, S/n",
    "sg:city":"Palencia",
    "sg:orig_category":"Iglesia Cat\u00d3lica",
    "sg:phone":"+34 979 74 11 45",
    "sg:postcode":"34005",
    "sg:province":"Palencia",
    "wof:name":"Parroquia Allende El Rio",
    "wof:placetype":"venue"
},
  "geometry": {"coordinates":[-4.5421180725,42.0089797974],"type":"Point"}
}