{
  "type": "Feature",
  "properties": {
    "addr:full":"Calle de Palacio (de), 14 Tielmes Madrid 28550",
    "addr:housenumber":"14",
    "addr:postcode":"28550",
    "addr:street":"Calle De Palacio De",
    "iso:country":"ES",
    "sg:address":"Calle de Palacio (de), 14",
    "sg:city":"Tielmes",
    "sg:orig_category":"Relajaci\u00d3n",
    "sg:phone":"+34 918 74 60 49",
    "sg:postcode":"28550",
    "sg:province":"Madrid",
    "wof:name":"Organismo Autonomo De Informatica Y Comunicaciones De La Comunidad De Madrid",
    "wof:placetype":"venue"
},
  "geometry": {"coordinates":[-3.3163990974,40.2468833923],"type":"Point"}
}