{
  "type": "Feature",
  "properties": {
    "iso:country":"ES",
    "sg:address":"Calle de Martinez De La Rosa, 33",
    "sg:city":"Malaga",
    "sg:orig_category":"Asesor\u00cda Sobre Comunicaci\u00d3n De Empresas",
    "sg:phone":"+34 952 10 26 13",
    "sg:postcode":"29009",
    "sg:province":"M\u00e1laga",
    "wof:name":"Cocinas Madrigal S.l",
    "wof:placetype":"venue"
},
  "geometry": {"coordinates":[-4.4346542358,36.7257194519],"type":"Point"}
}