{
  "type": "Feature",
  "properties": {
    "iso:country":"ES",
    "sg:address":"Calle de Sarria, 15",
    "sg:city":"Madrid",
    "sg:orig_category":"Peluqueros: De Se\u00d1oras",
    "sg:phone":"+34 913 78 09 60",
    "sg:postcode":"28029",
    "sg:province":"Madrid",
    "wof:name":"Marin Martinez Rosa Maria",
    "wof:placetype":"venue"
},
  "geometry": {"coordinates":[-3.7143023014,40.4740104675],"type":"Point"}
}