{
  "type": "Feature",
  "properties": {
    "iso:country":"ES",
    "sg:address":"Calle de Teniente Ruiz, 24",
    "sg:city":"Hinojosa Del Duque",
    "sg:orig_category":"Asociaciones Humanitarias, De Cooperaci\u00d3n, De Acci\u00d3n Social",
    "sg:phone":"+34 957 14 21 11",
    "sg:postcode":"14270",
    "sg:province":"C\u00f3rdoba",
    "wof:name":"Moyano Mu\u00f1oz Eduardo",
    "wof:placetype":"venue"
},
  "geometry": {"coordinates":[-5.1409230232,38.5003700256],"type":"Point"}
}