{
  "type": "Feature",
  "properties": {
    "iso:country":"ES",
    "sg:address":"Carrer de Rafael Casanova, 33",
    "sg:city":"Castelldefels",
    "sg:orig_category":"Empresarios",
    "sg:phone":"+34 936 36 48 41",
    "sg:postcode":"08860",
    "sg:province":"Barcelona",
    "wof:name":"Sanlyfer 2002 Sl",
    "wof:placetype":"venue"
},
  "geometry": {"coordinates":[1.9808750153,41.2873420715],"type":"Point"}
}