{
  "type": "Feature",
  "properties": {
    "addr:full":"De Ecuador, 35 Barcelona Barcelona 08029",
    "addr:housenumber":"35",
    "addr:postcode":"08029",
    "addr:street":"Ecuador",
    "iso:country":"ES",
    "sg:address":"De Ecuador, 35",
    "sg:city":"Barcelona",
    "sg:orig_category":"Fabricaci\u00d3n, Importaci\u00d3n De L\u00c1mparas Y Bombillas",
    "sg:phone":"+34 934 10 98 66",
    "sg:postcode":"08029",
    "sg:province":"Barcelona",
    "wof:name":"Crespo Bolea Mariano",
    "wof:placetype":"venue"
},
  "geometry": {"coordinates":[2.1403069496,41.3855209351],"type":"Point"}
}