{
  "type": "Feature",
  "properties": {
    "iso:country":"ES",
    "sg:address":"Calle de Romero Pozo, 23",
    "sg:city":"Velez-malaga",
    "sg:orig_category":"Fabricaci\u00d3n, Venta De Productos Base Farmac\u00c9uticos",
    "sg:phone":"+34 952 50 68 93",
    "sg:postcode":"29700",
    "sg:province":"M\u00e1laga",
    "wof:name":"Gonzalez Bustos Matilde",
    "wof:placetype":"venue"
},
  "geometry": {"coordinates":[-4.1041288376,36.781288147],"type":"Point"}
}