{
  "type": "Feature",
  "properties": {
    "addr:full":"Carrer de Osca, 11 S. Boi Llobregat Barcelona 08830",
    "addr:housenumber":"11",
    "addr:postcode":"08830",
    "addr:street":"Carrer De Osca",
    "iso:country":"ES",
    "sg:address":"Carrer de Osca, 11",
    "sg:city":"S. Boi Llobregat",
    "sg:orig_category":"Suministros Para Hoteles",
    "sg:phone":"+34 936 40 23 27",
    "sg:postcode":"08830",
    "sg:province":"Barcelona",
    "sg:website":"www.movilfrit.com",
    "wof:name":"Movilfrit S.a.",
    "wof:placetype":"venue"
},
  "geometry": {"coordinates":[2.0483369827,41.3388633728],"type":"Point"}
}