{
  "type": "Feature",
  "properties": {
    "addr:full":"Carrer de Diputacio, 1 Rodonya Tarragona 43812",
    "addr:housenumber":"1",
    "addr:postcode":"43812",
    "addr:street":"Carrer De Diputacio",
    "iso:country":"ES",
    "sg:address":"Carrer de Diputacio, 1",
    "sg:city":"Rodonya",
    "sg:orig_category":"Cooperativas Agr\u00cdcolas",
    "sg:phone":"+34 977 62 83 09",
    "sg:postcode":"43812",
    "sg:province":"Tarragona",
    "wof:name":"Cooperativa Agricola Rodonya",
    "wof:placetype":"venue"
},
  "geometry": {"coordinates":[1.3973300457,41.2819404602],"type":"Point"}
}