{
  "type": "Feature",
  "properties": {
    "addr:full":"Granada (p I Prado), S/n Merida Badajoz 06800",
    "addr:housenumber":"s / n",
    "addr:postcode":"06800",
    "iso:country":"ES",
    "sg:address":"Granada (p I Prado), S/n",
    "sg:city":"Merida",
    "sg:orig_category":"Electricidad: Equipos Industriales, Componentes (fabricaci\u00d3n)",
    "sg:phone":"+34 924 38 90 91",
    "sg:postcode":"06800",
    "sg:province":"Badajoz",
    "wof:name":"Siemens S A",
    "wof:placetype":"venue"
},
  "geometry": {"coordinates":[-6.3765039444,38.9243888855],"type":"Point"}
}