{
  "type": "Feature",
  "properties": {
    "iso:country":"ES",
    "sg:address":"Calle de Tomas Luis De Victoria, S/n",
    "sg:city":"Avila",
    "sg:orig_category":"Poller\u00cda Y Caza (al Por Menor)",
    "sg:phone":"+34 920 22 10 85",
    "sg:postcode":"05001",
    "sg:province":"\u00c1vila",
    "wof:name":"Avicola Gimenez S.l.",
    "wof:placetype":"venue"
},
  "geometry": {"coordinates":[-4.6989226341,40.6565818787],"type":"Point"}
}