{
  "type": "Feature",
  "properties": {
    "iso:country":"ES",
    "sg:address":"Plaz Espa\u00d1a, 4",
    "sg:city":"Alcorcon",
    "sg:orig_category":"Inmobiliaria (agencias)",
    "sg:phone":"+34 916 21 15 20",
    "sg:postcode":"28921",
    "sg:province":"Madrid",
    "sg:website":"www.expofinques.com",
    "wof:name":"Expofinques 2000 S.a.",
    "wof:placetype":"venue"
},
  "geometry": {"coordinates":[-3.8279709816,40.3491325378],"type":"Point"}
}