{
  "type": "Feature",
  "properties": {
    "iso:country":"ES",
    "sg:address":"C/ Emilio Hernandez Selva, 10",
    "sg:city":"Elche",
    "sg:orig_category":"Complementos De Vestir (al Por Menor)",
    "sg:phone":"+34 966 67 44 53",
    "sg:postcode":"03205",
    "sg:province":"Alicante",
    "wof:name":"Calzados Frayma S.l.",
    "wof:placetype":"venue"
},
  "geometry": {"coordinates":[-0.7126889825,38.2732543945],"type":"Point"}
}