{
  "type": "Feature",
  "properties": {
    "addr:full":"Pla\u00c7 Vila, 30 Amer Girona 17170",
    "addr:housenumber":"30",
    "addr:postcode":"17170",
    "addr:street":"Amer Girona",
    "iso:country":"ES",
    "sg:address":"Pla\u00c7 Vila, 30",
    "sg:city":"Amer",
    "sg:orig_category":"Ense\u00d1anza, Formaci\u00d3n Profesional: Aprendizaje",
    "sg:phone":"+34 972 43 11 12",
    "sg:postcode":"17170",
    "sg:province":"Girona",
    "wof:name":"Ajuntament D'amer",
    "wof:placetype":"venue"
},
  "geometry": {"coordinates":[2.5891647339,42.0193862915],"type":"Point"}
}