{
  "type": "Feature",
  "properties": {
    "addr:full":"Calle de Costa Del Azahar, 1 Almafra Alicante 03610",
    "addr:housenumber":"1",
    "addr:postcode":"03610",
    "addr:street":"Calle De Costa Del Azahar;Alicante",
    "iso:country":"ES",
    "sg:address":"Calle de Costa Del Azahar, 1",
    "sg:city":"Almafra",
    "sg:orig_category":"Zapatos: Material, Suministros, Accesorios (fabricaci\u00d3n, Al Por Mayor)",
    "sg:phone":"+34 966 95 04 81",
    "sg:postcode":"03610",
    "sg:province":"Alicante",
    "wof:name":"Trenzados Y Laminados San Martin S.l.",
    "wof:placetype":"venue"
},
  "geometry": {"coordinates":[-0.7859489918,38.489315033],"type":"Point"}
}