{
  "type": "Feature",
  "properties": {
    "addr:full":"Carrer de Primer De Maig, 24 Masnou Barcelona 08320",
    "addr:housenumber":"24",
    "addr:postcode":"08320",
    "addr:street":"Carrer De Primer De Maig",
    "iso:country":"ES",
    "sg:address":"Carrer de Primer De Maig, 24",
    "sg:city":"Masnou",
    "sg:orig_category":"Platos Preparados Refrigerados (fabricaci\u00d3n, Al Por Mayor)",
    "sg:phone":"+34 935 55 47 06",
    "sg:postcode":"08320",
    "sg:province":"Barcelona",
    "wof:name":"Plandiura Boglio Montserrat",
    "wof:placetype":"venue"
},
  "geometry": {"coordinates":[2.3115389347,41.4789924622],"type":"Point"}
}