{
  "type": "Feature",
  "properties": {
    "addr:full":"Calle de San Pascual, 237 Torrevieja Alicante 03180",
    "addr:housenumber":"237",
    "addr:postcode":"03180",
    "addr:street":"Calle De San Pascual",
    "iso:country":"ES",
    "sg:address":"Calle de San Pascual, 237",
    "sg:city":"Torrevieja",
    "sg:orig_category":"Empresas De Carpinter\u00cda Met\u00c1lica",
    "sg:phone":"+34 965 70 98 89",
    "sg:postcode":"03180",
    "sg:province":"Alicante",
    "wof:name":"Vieyra  Hugo Armando",
    "wof:placetype":"venue"
},
  "geometry": {"coordinates":[-0.6536790133,38.0173606873],"type":"Point"}
}