{
  "type": "Feature",
  "properties": {
    "iso:country":"ES",
    "sg:address":"Calle de General Casta\u00d1os, 56",
    "sg:city":"Portugalete",
    "sg:orig_category":"Ropa De Hogar (al Por Menor)",
    "sg:phone":"+34 944 62 23 88",
    "sg:postcode":"48920",
    "sg:province":"Vizcaya",
    "wof:name":"Herur S.a.",
    "wof:placetype":"venue"
},
  "geometry": {"coordinates":[-3.0256638527,43.3229446411],"type":"Point"}
}