{
  "type": "Feature",
  "properties": {
    "addr:full":"Carrer de Roger De Lluria, 9 Mollet Valles Barcelona 08100",
    "addr:housenumber":"9",
    "addr:postcode":"08100",
    "addr:street":"Carrer De Roger De Lluria",
    "iso:country":"ES",
    "sg:address":"Carrer de Roger De Lluria, 9",
    "sg:city":"Mollet Valles",
    "sg:orig_category":"Restaurantes",
    "sg:phone":"+34 935 93 08 21",
    "sg:postcode":"08100",
    "sg:province":"Barcelona",
    "wof:name":"Beumala Frago Maria Angels",
    "wof:placetype":"venue"
},
  "geometry": {"coordinates":[2.2161920071,41.5419692993],"type":"Point"}
}