{
  "type": "Feature",
  "properties": {
    "addr:full":"Calle de Nueva, S/n Burgi Navarra 31412",
    "addr:housenumber":"s / n",
    "addr:postcode":"31412",
    "addr:street":"Calle De Nueva",
    "iso:country":"ES",
    "sg:address":"Calle de Nueva, S/n",
    "sg:city":"Burgi",
    "sg:orig_category":"Alimentaci\u00d3n General (al Por Menor)",
    "sg:phone":"+34 948 47 70 09",
    "sg:postcode":"31412",
    "sg:province":"Navarra",
    "wof:name":"Ara Urzainqui Emilio",
    "wof:placetype":"venue"
},
  "geometry": {"coordinates":[-1.0018970966,42.7210769653],"type":"Point"}
}