{
  "type": "Feature",
  "properties": {
    "addr:full":"Carr Benidoleig, 18 Benissa Alicante 03720",
    "addr:housenumber":"18",
    "addr:postcode":"03720",
    "addr:street":"Carr Benidoleig",
    "iso:country":"ES",
    "sg:address":"Carr Benidoleig, 18",
    "sg:city":"Benissa",
    "sg:orig_category":"Farmacias",
    "sg:phone":"+34 965 73 11 62",
    "sg:postcode":"03720",
    "sg:province":"Alicante",
    "wof:name":"Villanueva Albanell Carmen",
    "wof:placetype":"venue"
},
  "geometry": {"coordinates":[0.0460099988,38.7124633789],"type":"Point"}
}