{
  "type": "Feature",
  "properties": {
    "addr:full":"Carrer de Romans, 1 Barcelona Barcelona 08025",
    "addr:housenumber":"1",
    "addr:postcode":"08025",
    "addr:street":"Carrer De Romans",
    "iso:country":"ES",
    "sg:address":"Carrer de Romans, 1",
    "sg:city":"Barcelona",
    "sg:orig_category":"Farmacias",
    "sg:phone":"+34 932 13 88 96",
    "sg:postcode":"08025",
    "sg:province":"Barcelona",
    "wof:name":"Gimenez Chancho Yolanda",
    "wof:placetype":"venue"
},
  "geometry": {"coordinates":[2.1640648842,41.4071807861],"type":"Point"}
}