{
  "type": "Feature",
  "properties": {
    "addr:full":"Calle de Galiana De, 52 Aviles Asturias 33402",
    "addr:housenumber":"52",
    "addr:postcode":"33402",
    "addr:street":"Calle De Galiana De",
    "iso:country":"ES",
    "sg:address":"Calle de Galiana De, 52",
    "sg:city":"Aviles",
    "sg:orig_category":"Charcuter\u00cdas (al Por Mayor)",
    "sg:phone":"+34 985 56 16 95",
    "sg:postcode":"33402",
    "sg:province":"Asturias",
    "wof:name":"Embutidos Vallina S. A.",
    "wof:placetype":"venue"
},
  "geometry": {"coordinates":[-5.9255170822,43.5534248352],"type":"Point"}
}