{
  "type": "Feature",
  "properties": {
    "addr:full":"A Igrexa, 7 Alxen Pontevedra 36458",
    "addr:housenumber":"7",
    "addr:postcode":"36458",
    "addr:street":"A Igrexa",
    "iso:country":"ES",
    "sg:address":"A Igrexa, 7",
    "sg:city":"Alxen",
    "sg:orig_category":"Transportes Por Carretera: Lotes Completos, Mercanc\u00cdas Diversas",
    "sg:phone":"+34 986 65 83 19",
    "sg:postcode":"36458",
    "sg:province":"Pontevedra",
    "wof:name":"Electricidad Manel S.l.",
    "wof:placetype":"venue"
},
  "geometry": {"coordinates":[-8.5009155273,42.0980224609],"type":"Point"}
}