{
  "type": "Feature",
  "properties": {
    "iso:country":"ES",
    "sg:address":"Calle de Dieciocho De Julio, S/n",
    "sg:city":"Colunga",
    "sg:orig_category":"Carnicer\u00cdas, Carnicer\u00cdas",
    "sg:phone":"+34 985 85 60 09",
    "sg:postcode":"33320",
    "sg:province":"Asturias",
    "wof:name":"Peon Prieto Evangelina Maria",
    "wof:placetype":"venue"
},
  "geometry": {"coordinates":[-5.2997961044,43.4477424622],"type":"Point"}
}