{
  "type": "Feature",
  "properties": {
    "addr:full":"Calle de Doctor Cortezo, 4 Madrid Madrid 28012",
    "addr:housenumber":"4",
    "addr:postcode":"28012",
    "addr:street":"Calle De Doctor Cortezo",
    "iso:country":"ES",
    "sg:address":"Calle de Doctor Cortezo, 4",
    "sg:city":"Madrid",
    "sg:orig_category":"Empresarios",
    "sg:phone":"+34 914 29 39 97",
    "sg:postcode":"28012",
    "sg:province":"Madrid",
    "wof:name":"Real Congregacion De Esclavos Del Dulcisimo Nombre De Maria",
    "wof:placetype":"venue"
},
  "geometry": {"coordinates":[-3.7037546635,40.4135932922],"type":"Point"}
}