{
  "type": "Feature",
  "properties": {
    "addr:full":"Calle de Luis I, 4 Madrid Madrid 28031",
    "addr:housenumber":"4",
    "addr:postcode":"28031",
    "addr:street":"Calle De Luis I",
    "iso:country":"ES",
    "sg:address":"Calle de Luis I, 4",
    "sg:city":"Madrid",
    "sg:orig_category":"Artes Gr\u00c1ficas, Artes Pl\u00c1sticas (curso)",
    "sg:phone":"+34 913 80 31 36",
    "sg:postcode":"28031",
    "sg:province":"Madrid",
    "wof:name":"Olivo Coco Santiago",
    "wof:placetype":"venue"
},
  "geometry": {"coordinates":[-3.6397230625,40.3770484924],"type":"Point"}
}