{
  "type": "Feature",
  "properties": {
    "addr:full":"Ctra Zaragoza, Km. 0070,0 Alfaro La Rioja 26540",
    "addr:postcode":"26540",
    "addr:street":"Ctra Zaragoza Km. 0070,0 Alfaro;Rioja",
    "iso:country":"ES",
    "sg:address":"Ctra Zaragoza, Km. 0070,0",
    "sg:city":"Alfaro",
    "sg:orig_category":"\u00c1rboles Frutales",
    "sg:phone":"+34 941 18 36 69",
    "sg:postcode":"26540",
    "sg:province":"La Rioja",
    "wof:name":"Viveros Pedro Aguirre S.l.",
    "wof:placetype":"venue"
},
  "geometry": {"coordinates":[-1.7502743006,42.1746788025],"type":"Point"}
}