{
  "type": "Feature",
  "properties": {
    "iso:country":"ES",
    "sg:address":"Avda Portugal, 173",
    "sg:city":"Madrid",
    "sg:orig_category":"Oficinas De Turismo, Asociaciones De Iniciativa",
    "sg:phone":"+34 914 79 46 54",
    "sg:postcode":"28011",
    "sg:province":"Madrid",
    "wof:name":"Dimedinsa S.l.",
    "wof:placetype":"venue"
},
  "geometry": {"coordinates":[-3.7378339767,40.4111289978],"type":"Point"}
}