{
  "type": "Feature",
  "properties": {
    "addr:full":"Calle de Maya, 14 Badajoz Badajoz 06003",
    "addr:housenumber":"14",
    "addr:postcode":"06003",
    "addr:street":"Calle De Maya",
    "iso:country":"ES",
    "sg:address":"Calle de Maya, 14",
    "sg:city":"Badajoz",
    "sg:orig_category":"Trabajos De Soldaduras",
    "sg:phone":"+34 924 24 41 54",
    "sg:postcode":"06003",
    "sg:province":"Badajoz",
    "wof:name":"Oerlikol S.a.",
    "wof:placetype":"venue"
},
  "geometry": {"coordinates":[-6.9699621201,38.8698654175],"type":"Point"}
}