{
  "type": "Feature",
  "properties": {
    "addr:full":"Avda Rodriguez De Ledesma, 1 Caceres C\u00e1ceres 10001",
    "addr:housenumber":"1",
    "addr:postcode":"10001",
    "addr:street":"Avda Rodriguez De Ledesma;Ca\u0301Ceres",
    "iso:country":"ES",
    "sg:address":"Avda Rodriguez De Ledesma, 1",
    "sg:city":"Caceres",
    "sg:orig_category":"Supermercados Y Hipermercados",
    "sg:phone":"+34 927 22 50 22",
    "sg:postcode":"10001",
    "sg:province":"C\u00e1ceres",
    "wof:name":"Hiper Tambo S.l.",
    "wof:placetype":"venue"
},
  "geometry": {"coordinates":[-6.3815288544,39.4721717834],"type":"Point"}
}