{
  "type": "Feature",
  "properties": {
    "addr:full":"Calle de Batalla Del Ebro, 2 Corrales Cantabria 39400",
    "addr:housenumber":"2",
    "addr:postcode":"39400",
    "addr:street":"Calle De Batalla Del Ebro",
    "iso:country":"ES",
    "sg:address":"Calle de Batalla Del Ebro, 2",
    "sg:city":"Corrales",
    "sg:orig_category":"Asociaciones Y Clubs Deportivos",
    "sg:phone":"+34 942 83 10 89",
    "sg:postcode":"39400",
    "sg:province":"Cantabria",
    "wof:name":"Gutierrez Fernandez Serafin",
    "wof:placetype":"venue"
},
  "geometry": {"coordinates":[-4.069791317,43.2605857849],"type":"Point"}
}