{
  "type": "Feature",
  "properties": {
    "iso:country":"ES",
    "sg:address":"Calle de Alar Del Rey, 17",
    "sg:city":"Madrid",
    "sg:orig_category":"Empresas De Limpieza",
    "sg:phone":"+34 913 29 58 18",
    "sg:postcode":"28042",
    "sg:province":"Madrid",
    "wof:name":"Asistencia Aeroportuaria S.a.",
    "wof:placetype":"venue"
},
  "geometry": {"coordinates":[-3.5832228661,40.4711761475],"type":"Point"}
}