{
  "type": "Feature",
  "properties": {
    "addr:full":"Luz(urb Ladera), 35 Churra Murcia 30110",
    "addr:housenumber":"35",
    "addr:postcode":"30110",
    "addr:street":"Urb Ladera",
    "iso:country":"ES",
    "sg:address":"Luz(urb Ladera), 35",
    "sg:city":"Churra",
    "sg:orig_category":"Agencias Y Agentes Comerciales, Representantes",
    "sg:phone":"+34 968 85 61 01",
    "sg:postcode":"30110",
    "sg:province":"Murcia",
    "wof:name":"Basterrechea Montesinos Vicente",
    "wof:placetype":"venue"
},
  "geometry": {"coordinates":[-1.1423300505,38.0356445312],"type":"Point"}
}