{
  "type": "Feature",
  "properties": {
    "addr:full":"Calle de Salvador Pau, 38 Valencia Valencia 46021",
    "addr:housenumber":"38",
    "addr:postcode":"46021",
    "addr:street":"Calle De Salvador Pau",
    "iso:country":"ES",
    "sg:address":"Calle de Salvador Pau, 38",
    "sg:city":"Valencia",
    "sg:orig_category":"Electrodom\u00c9sticos (al Por Menor)",
    "sg:phone":"+34 963 93 06 21",
    "sg:postcode":"46021",
    "sg:province":"Valencia",
    "wof:name":"Satek C.b.",
    "wof:placetype":"venue"
},
  "geometry": {"coordinates":[-0.3521220088,39.4701652527],"type":"Point"}
}