{
  "type": "Feature",
  "properties": {
    "addr:full":"Cra. Nacional Cent Cinquanta-dos, Km. 0039,0 La Garriga Barcelona 08530",
    "addr:postcode":"08530",
    "addr:street":"Km. 0039,0",
    "iso:country":"ES",
    "sg:address":"Cra. Nacional Cent Cinquanta-dos, Km. 0039,0",
    "sg:city":"La Garriga",
    "sg:orig_category":"Muebles, Minoristas",
    "sg:phone":"+34 938 71 80 67",
    "sg:postcode":"08530",
    "sg:province":"Barcelona",
    "sg:website":"www.jorevamobles.com",
    "wof:name":"Boix Ganduxe Maria Eva",
    "wof:placetype":"venue"
},
  "geometry": {"coordinates":[2.2889399529,41.6845092773],"type":"Point"}
}