{
  "type": "Feature",
  "properties": {
    "addr:full":"Calle de Medio, 13 Hecho Huesca 22720",
    "addr:housenumber":"13",
    "addr:postcode":"22720",
    "addr:street":"Calle De Medio",
    "iso:country":"ES",
    "sg:address":"Calle de Medio, 13",
    "sg:city":"Hecho",
    "sg:orig_category":"Molduras, Junquillos, Listones Y Molduras Perforadas",
    "sg:phone":"+34 974 37 51 61",
    "sg:postcode":"22720",
    "sg:province":"Huesca",
    "wof:name":"Miguel Aisa Felipe",
    "wof:placetype":"venue"
},
  "geometry": {"coordinates":[-0.7506183982,42.7385597229],"type":"Point"}
}