{
  "type": "Feature",
  "properties": {
    "iso:country":"ES",
    "sg:address":"Calle de Ministro Fernandez Ordo\u00d1ez, 1",
    "sg:city":"Santa Marta De Tormes",
    "sg:orig_category":"Molduras, Junquillos, Listones Y Molduras Perforadas",
    "sg:phone":"+34 923 20 08 03",
    "sg:postcode":"37900",
    "sg:province":"Salamanca",
    "wof:name":"Hosteleria Canalejas S.l.",
    "wof:placetype":"venue"
},
  "geometry": {"coordinates":[-5.6386408806,40.9494438171],"type":"Point"}
}