{
  "type": "Feature",
  "properties": {
    "iso:country":"ES",
    "sg:address":"Carrer de General Palafox, 8",
    "sg:city":"Castelldefels",
    "sg:orig_category":"Inform\u00c1tica (estudios, Servicios, Asesor\u00cda, Formaci\u00d3n)",
    "sg:phone":"+34 936 36 53 72",
    "sg:postcode":"08860",
    "sg:province":"Barcelona",
    "sg:website":"www.systemtronic.com",
    "wof:name":"Systemtronic Software S.l.",
    "wof:placetype":"venue"
},
  "geometry": {"coordinates":[1.9825299978,41.286403656],"type":"Point"}
}