{
  "type": "Feature",
  "properties": {
    "iso:country":"ES",
    "sg:address":"P. Barace, 1",
    "sg:city":"Iru\u00f1a",
    "sg:orig_category":"Pescader\u00cdas (al Por Menor)",
    "sg:phone":"+34 948 27 18 55",
    "sg:postcode":"31007",
    "sg:province":"Navarra",
    "wof:name":"Arlegui Armendariz Raul",
    "wof:placetype":"venue"
},
  "geometry": {"coordinates":[-1.6464496851,42.8056983948],"type":"Point"}
}