{
  "type": "Feature",
  "properties": {
    "iso:country":"ES",
    "sg:address":"Calle de Almeria, 1",
    "sg:city":"Alcala Henares",
    "sg:orig_category":"Veh\u00cdculos De Ocasi\u00d3n",
    "sg:phone":"+34 918 81 36 90",
    "sg:postcode":"28804",
    "sg:province":"Madrid",
    "wof:name":"Herbacar Auto S.l.",
    "wof:placetype":"venue"
},
  "geometry": {"coordinates":[-3.3557422161,40.4822731018],"type":"Point"}
}