{
  "type": "Feature",
  "properties": {
    "iso:country":"ES",
    "sg:address":"Calle de Miguel Servet, 6",
    "sg:city":"Sestao",
    "sg:orig_category":"Mec\u00c1nico Del Autom\u00d3vil",
    "sg:phone":"+34 944 01 26 68",
    "sg:postcode":"48910",
    "sg:province":"Vizcaya",
    "wof:name":"Talleres Encar, S.l",
    "wof:placetype":"venue"
},
  "geometry": {"coordinates":[-2.9995360374,43.3082237244],"type":"Point"}
}