{
  "type": "Feature",
  "properties": {
    "addr:full":"Vivero, S/n Manga Mar Menor Murcia 30380",
    "addr:housenumber":"/ n",
    "addr:postcode":"30380",
    "addr:street":"S",
    "iso:country":"ES",
    "sg:address":"Vivero, S/n",
    "sg:city":"Manga Mar Menor",
    "sg:orig_category":"Centros De Educaci\u00d3n Especial",
    "sg:phone":"+34 968 56 41 24",
    "sg:postcode":"30380",
    "sg:province":"Murcia",
    "wof:name":"Colegio Publico Mediterraneo",
    "wof:placetype":"venue"
},
  "geometry": {"coordinates":[-0.7281540036,37.6686553955],"type":"Point"}
}