{
  "type": "Feature",
  "properties": {
    "iso:country":"ES",
    "sg:address":"Calle de Capitan Dema, 30",
    "sg:city":"Alacant",
    "sg:orig_category":"Marketing Telef\u00d3nico",
    "sg:phone":"+34 965 11 37 19",
    "sg:postcode":"03007",
    "sg:province":"Alicante",
    "wof:name":"Tele Gestion De Servicios De Marketing S.l.",
    "wof:placetype":"venue"
},
  "geometry": {"coordinates":[-0.5003960133,38.3401947021],"type":"Point"}
}