{
  "type": "Feature",
  "properties": {
    "addr:full":"Calle de Constitucion (de La), 88 Alcobendas Madrid 28100",
    "addr:housenumber":"88",
    "addr:postcode":"28100",
    "addr:street":"Calle De Constitucion De La",
    "iso:country":"ES",
    "sg:address":"Calle de Constitucion (de La), 88",
    "sg:city":"Alcobendas",
    "sg:orig_category":"Bancos",
    "sg:phone":"+34 916 63 69 34",
    "sg:postcode":"28100",
    "sg:province":"Madrid",
    "wof:name":"Banco Espa\u00f1ol De Credito S.a.",
    "wof:placetype":"venue"
},
  "geometry": {"coordinates":[-3.6412160397,40.5449104309],"type":"Point"}
}