{
  "type": "Feature",
  "properties": {
    "addr:full":"Calle de Maestra Felisa Lozano, 10 Madrid Madrid 28042",
    "addr:housenumber":"10",
    "addr:postcode":"madrid;28042",
    "addr:street":"Calle De Maestra Felisa Lozano",
    "iso:country":"ES",
    "sg:address":"Calle de Maestra Felisa Lozano, 10",
    "sg:city":"Madrid",
    "sg:orig_category":"Asistencia Social",
    "sg:phone":"+34 913 24 27 04",
    "sg:postcode":"28042",
    "sg:province":"Madrid",
    "wof:name":"Cervera Lucini Vicente",
    "wof:placetype":"venue"
},
  "geometry": {"coordinates":[-3.6084990501,40.4520988464],"type":"Point"}
}