{
  "type": "Feature",
  "properties": {
    "iso:country":"ES",
    "sg:address":"Calle de Virgen De Las Nieves, 1",
    "sg:city":"Novelda",
    "sg:orig_category":"Maquinaria Para Industrias Diversas",
    "sg:phone":"+34 965 60 69 41",
    "sg:postcode":"03660",
    "sg:province":"Alicante",
    "wof:name":"Lopez Sanchez Jesus",
    "wof:placetype":"venue"
},
  "geometry": {"coordinates":[-0.7705870271,38.3785667419],"type":"Point"}
}