{
  "type": "Feature",
  "properties": {
    "addr:full":"Calle de San Miguel, S/n Gaibiel Castell\u00f3n 12415",
    "addr:housenumber":"s",
    "addr:postcode":"12415",
    "addr:street":"Calle De San Miguel;/ N;Castello\u0301N",
    "iso:country":"ES",
    "sg:address":"Calle de San Miguel, S/n",
    "sg:city":"Gaibiel",
    "sg:orig_category":"Ba\u00d1os Y Duchas P\u00dablicos",
    "sg:phone":"+34 964 14 25 96",
    "sg:postcode":"12415",
    "sg:province":"Castell\u00f3n",
    "wof:name":"Ayuntamiento De Gaibiel-piscina Municipal",
    "wof:placetype":"venue"
},
  "geometry": {"coordinates":[-0.4969139993,39.9260215759],"type":"Point"}
}