{
  "type": "Feature",
  "properties": {
    "iso:country":"ES",
    "sg:address":"Calle de General Suarez Valdes, 24",
    "sg:city":"Gijon",
    "sg:orig_category":"Alimentaci\u00d3n General (al Por Menor)",
    "sg:phone":"+34 985 36 35 24",
    "sg:postcode":"33204",
    "sg:province":"Asturias",
    "wof:name":"Prado Prado Serrano",
    "wof:placetype":"venue"
},
  "geometry": {"coordinates":[-5.6487231255,43.5317955017],"type":"Point"}
}