{
  "type": "Feature",
  "properties": {
    "addr:full":"Pase Solatorre, 6 Comillas Cantabria 39520",
    "addr:housenumber":"6",
    "addr:postcode":"39520",
    "addr:street":"Solatorre",
    "iso:country":"ES",
    "sg:address":"Pase Solatorre, 6",
    "sg:city":"Comillas",
    "sg:orig_category":"Molduras, Junquillos, Listones Y Molduras Perforadas",
    "sg:phone":"+34 942 72 11 54",
    "sg:postcode":"39520",
    "sg:province":"Cantabria",
    "wof:name":"Sangermano Vallina Nausica",
    "wof:placetype":"venue"
},
  "geometry": {"coordinates":[-4.2956261635,43.3849983215],"type":"Point"}
}