{
  "type": "Feature",
  "properties": {
    "iso:country":"ES",
    "sg:address":"Calle de San Diego De Alcala, 31",
    "sg:city":"S. Fernando",
    "sg:orig_category":"Alimentaci\u00d3n General (al Por Menor)",
    "sg:phone":"+34 956 89 04 04",
    "sg:postcode":"11100",
    "sg:province":"C\u00e1diz",
    "wof:name":"Medel Saenz Rafael",
    "wof:placetype":"venue"
},
  "geometry": {"coordinates":[-6.2002091408,36.4668197632],"type":"Point"}
}