{
  "type": "Feature",
  "properties": {
    "addr:full":"Pg Segon Passeig De Ronda, 23 Lleida Lleida 25004",
    "addr:housenumber":"23",
    "addr:postcode":"25004",
    "addr:street":"Pg Segon Passeig De Ronda",
    "iso:country":"ES",
    "sg:address":"Pg Segon Passeig De Ronda, 23",
    "sg:city":"Lleida",
    "sg:orig_category":"Hoteles",
    "sg:phone":"+34 973 23 89 89",
    "sg:postcode":"25004",
    "sg:province":"Lleida",
    "wof:name":"Hoteles Haro S.l.",
    "wof:placetype":"venue"
},
  "geometry": {"coordinates":[0.6272450089,41.6242485046],"type":"Point"}
}