{
  "type": "Feature",
  "properties": {
    "addr:full":"Calle de Rio (del), 1 Arenas Madrid 28320",
    "addr:housenumber":"1",
    "addr:postcode":"28320",
    "addr:street":"Calle De Rio Del",
    "iso:country":"ES",
    "sg:address":"Calle de Rio (del), 1",
    "sg:city":"Arenas",
    "sg:orig_category":"Fabricaci\u00d3n De Mobiliario Met\u00c1lico",
    "sg:phone":"+34 916 92 15 42",
    "sg:postcode":"28320",
    "sg:province":"Madrid",
    "wof:name":"Presme S.l.",
    "wof:placetype":"venue"
},
  "geometry": {"coordinates":[-3.6862940788,40.2692337036],"type":"Point"}
}