{
  "type": "Feature",
  "properties": {
    "addr:full":"Afueras, S/n Madrigal Vera C\u00e1ceres 10480",
    "addr:postcode":"10480",
    "addr:street":"Afueras S / N Madrigal Vera Ca\u0301Ceres",
    "iso:country":"ES",
    "sg:address":"Afueras, S/n",
    "sg:city":"Madrigal Vera",
    "sg:orig_category":"Producci\u00d3n, Venta De Productos De Agricultura Biol\u00d3gica",
    "sg:phone":"+34 927 56 56 46",
    "sg:postcode":"10480",
    "sg:province":"C\u00e1ceres",
    "wof:name":"Araujo Vazquez Santiago",
    "wof:placetype":"venue"
},
  "geometry": {"coordinates":[-6.3707604408,39.4761772156],"type":"Point"}
}