{
  "type": "Feature",
  "properties": {
    "addr:full":"Carrer de Rogent, 27 Barcelona Barcelona 08026",
    "addr:housenumber":"27",
    "addr:postcode":"08026",
    "addr:street":"Carrer De Rogent",
    "iso:country":"ES",
    "sg:address":"Carrer de Rogent, 27",
    "sg:city":"Barcelona",
    "sg:orig_category":"Frutas, Legumbres Frescas Y Tempranas (al Por Menor)",
    "sg:phone":"+34 932 31 22 41",
    "sg:postcode":"08026",
    "sg:province":"Barcelona",
    "wof:name":"Fruites 2000 S. A.",
    "wof:placetype":"venue"
},
  "geometry": {"coordinates":[2.184595108,41.4091148376],"type":"Point"}
}