{
  "type": "Feature",
  "properties": {
    "iso:country":"ES",
    "sg:address":"Calle de Ricardo Caba\u00d1ero, 12",
    "sg:city":"Puertollano",
    "sg:orig_category":"Cajas De Ahorro",
    "sg:phone":"+34 926 41 58 46",
    "sg:postcode":"13500",
    "sg:province":"Ciudad Real",
    "wof:name":"Caja De Ahorros De Valencia Castellon Y Alicante",
    "wof:placetype":"venue"
},
  "geometry": {"coordinates":[-4.1076421738,38.6864814758],"type":"Point"}
}