{
  "type": "Feature",
  "properties": {
    "iso:country":"ES",
    "sg:address":"Av Lleida (de), 139",
    "sg:city":"Torrefarrera",
    "sg:orig_category":"Agencias Y Agentes Comerciales, Representantes",
    "sg:phone":"+34 973 75 09 69",
    "sg:postcode":"25123",
    "sg:province":"Lleida",
    "wof:name":"Guiu Carrio Alfredo",
    "wof:placetype":"venue"
},
  "geometry": {"coordinates":[0.6065319777,41.6680831909],"type":"Point"}
}