{
  "type": "Feature",
  "properties": {
    "addr:full":"Calle de Pintor Lorenzo Casanova, 3 Alacant Alicante 03003",
    "addr:housenumber":"3",
    "addr:postcode":"03003",
    "addr:street":"Calle De Pintor Lorenzo Casanova",
    "iso:country":"ES",
    "sg:address":"Calle de Pintor Lorenzo Casanova, 3",
    "sg:city":"Alacant",
    "sg:orig_category":"Agencias De Viajes",
    "sg:phone":"+34 965 92 26 47",
    "sg:postcode":"03003",
    "sg:province":"Alicante",
    "sg:website":"www.racc.es",
    "wof:name":"Reial Automobil Club De Catalunya",
    "wof:placetype":"venue"
},
  "geometry": {"coordinates":[-0.4884729981,38.3424301147],"type":"Point"}
}