{
  "type": "Feature",
  "properties": {
    "addr:full":"Avda Guindos De Los, 40 Malaga M\u00e1laga 29004",
    "addr:housenumber":"40",
    "addr:postcode":"29004",
    "addr:street":"Avda Guindos De Los;Ma\u0301Laga",
    "iso:country":"ES",
    "sg:address":"Avda Guindos De Los, 40",
    "sg:city":"Malaga",
    "sg:orig_category":"Panader\u00cdas, Panader\u00cdas",
    "sg:phone":"+34 952 23 80 86",
    "sg:postcode":"29004",
    "sg:province":"M\u00e1laga",
    "wof:name":"Gomez Martin Manuel",
    "wof:placetype":"venue"
},
  "geometry": {"coordinates":[-4.4480538368,36.6910018921],"type":"Point"}
}