{
  "type": "Feature",
  "properties": {
    "iso:country":"ES",
    "sg:address":"Calle de Soria, 4",
    "sg:city":"Ajalvir",
    "sg:orig_category":"Construcci\u00d3n Mec\u00c1nica",
    "sg:phone":"+34 918 84 30 62",
    "sg:postcode":"28864",
    "sg:province":"Madrid",
    "wof:name":"Mecanic-trom S.l.",
    "wof:placetype":"venue"
},
  "geometry": {"coordinates":[-3.4829649925,40.5314369202],"type":"Point"}
}