{
  "type": "Feature",
  "properties": {
    "addr:full":"Carrer de Santander, 50 Barcelona Barcelona 08020",
    "addr:housenumber":"50",
    "addr:postcode":"08020",
    "addr:street":"Carrer De Santander",
    "iso:country":"ES",
    "sg:address":"Carrer de Santander, 50",
    "sg:city":"Barcelona",
    "sg:orig_category":"Veh\u00cdculos De Ocasi\u00d3n",
    "sg:phone":"+34 934 98 70 00",
    "sg:postcode":"08020",
    "sg:province":"Barcelona",
    "sg:website":"www.catalana-auto.com",
    "wof:name":"Catalana De Automocion S.a.",
    "wof:placetype":"venue"
},
  "geometry": {"coordinates":[2.2025170326,41.4278297424],"type":"Point"}
}