{
  "type": "Feature",
  "properties": {
    "iso:country":"ES",
    "sg:address":"Calle de Rocinante (de), 18",
    "sg:city":"Humanes De Madrid",
    "sg:orig_category":"Empresas De Carpinter\u00cda De Madera",
    "sg:phone":"+34 916 04 13 68",
    "sg:postcode":"28970",
    "sg:province":"Madrid",
    "wof:name":"Gonzalez Calvo Manuel",
    "wof:placetype":"venue"
},
  "geometry": {"coordinates":[-3.8346440792,40.242816925],"type":"Point"}
}