{
  "type": "Feature",
  "properties": {
    "iso:country":"ES",
    "sg:address":"Plaz Costa, 1",
    "sg:city":"Brea De Aragon",
    "sg:orig_category":"Supermercados Y Hipermercados",
    "sg:phone":"+34 976 82 41 02",
    "sg:postcode":"50246",
    "sg:province":"Zaragoza",
    "wof:name":"Martin Castejon Iluminada",
    "wof:placetype":"venue"
},
  "geometry": {"coordinates":[-1.5998699665,41.5209693909],"type":"Point"}
}