{
  "type": "Feature",
  "properties": {
    "addr:full":"Calle de Gabilondo, 3 Valladolid Valladolid 47007",
    "addr:housenumber":"3",
    "addr:postcode":"47007",
    "addr:street":"Calle De Gabilondo",
    "iso:country":"ES",
    "sg:address":"Calle de Gabilondo, 3",
    "sg:city":"Valladolid",
    "sg:orig_category":"Asesor\u00cda Fiscal Y Jur\u00cddica",
    "sg:phone":"+34 983 27 50 02",
    "sg:postcode":"47007",
    "sg:province":"Valladolid",
    "wof:name":"Programacion Fiscal Y Contable S. A.",
    "wof:placetype":"venue"
},
  "geometry": {"coordinates":[-4.7344307899,41.6434288025],"type":"Point"}
}