{
  "type": "Feature",
  "properties": {
    "iso:country":"ES",
    "sg:address":"Avda Villanueva, 17",
    "sg:city":"Badajoz",
    "sg:orig_category":"Droguer\u00cdas (al Por Menor)",
    "sg:phone":"+34 924 23 18 83",
    "sg:postcode":"06005",
    "sg:province":"Badajoz",
    "wof:name":"Herrera Torrado Carlos",
    "wof:placetype":"venue"
},
  "geometry": {"coordinates":[-6.9778981209,38.870891571],"type":"Point"}
}