{
  "type": "Feature",
  "properties": {
    "iso:country":"ES",
    "sg:address":"Calle de Obispo Merida, 7",
    "sg:city":"Molina Segura",
    "sg:orig_category":"Empresas De Carpinter\u00cda De Madera",
    "sg:phone":"+34 968 64 43 28",
    "sg:postcode":"30500",
    "sg:province":"Murcia",
    "wof:name":"Carpinteria Aldaba S.l.",
    "wof:placetype":"venue"
},
  "geometry": {"coordinates":[-1.2056479454,38.0515594482],"type":"Point"}
}