{
  "type": "Feature",
  "properties": {
    "iso:country":"ES",
    "sg:address":"Carr Cuart, 16",
    "sg:city":"Moncada",
    "sg:orig_category":"Reposter\u00cdas",
    "sg:phone":"+34 961 39 18 80",
    "sg:postcode":"46113",
    "sg:province":"Valencia",
    "wof:name":"Arnal Arnal Jose",
    "wof:placetype":"venue"
},
  "geometry": {"coordinates":[-0.3934189081,39.5468902588],"type":"Point"}
}