{
  "type": "Feature",
  "properties": {
    "addr:full":"Avda Barcelona, 1 Jaen Ja\u00e9n 23006",
    "addr:housenumber":"1;jae\u0301n",
    "addr:postcode":"23006",
    "addr:street":"Avda Barcelona",
    "iso:country":"ES",
    "sg:address":"Avda Barcelona, 1",
    "sg:city":"Jaen",
    "sg:orig_category":"Farmacias",
    "sg:phone":"+34 953 26 74 40",
    "sg:postcode":"23006",
    "sg:province":"Ja\u00e9n",
    "wof:name":"Zorrilla Quijano Amparo",
    "wof:placetype":"venue"
},
  "geometry": {"coordinates":[-3.7969129086,37.7802352905],"type":"Point"}
}