{
  "type": "Feature",
  "properties": {
    "addr:full":"Plaz Mayor, S/n Gomara Soria 42120",
    "addr:housenumber":"s / n",
    "addr:postcode":"42120",
    "addr:street":"Plaz Mayor",
    "iso:country":"ES",
    "sg:address":"Plaz Mayor, S/n",
    "sg:city":"Gomara",
    "sg:orig_category":"Ense\u00d1anza, Formaci\u00d3n Profesional: Aprendizaje",
    "sg:phone":"+34 975 38 01 16",
    "sg:postcode":"42120",
    "sg:province":"Soria",
    "wof:name":"Delegacion Territorial De Soria",
    "wof:placetype":"venue"
},
  "geometry": {"coordinates":[-2.2252590656,41.6238365173],"type":"Point"}
}