{
  "type": "Feature",
  "properties": {
    "addr:full":"Calle de Casarrubuelos, 6 Madrid Madrid 28015",
    "addr:housenumber":"6",
    "addr:postcode":"28015",
    "addr:street":"Calle De Casarrubuelos",
    "iso:country":"ES",
    "sg:address":"Calle de Casarrubuelos, 6",
    "sg:city":"Madrid",
    "sg:orig_category":"Peleter\u00cdas",
    "sg:phone":"+34 914 45 39 00",
    "sg:postcode":"28015",
    "sg:province":"Madrid",
    "wof:name":"Inmobiliaria Allupe S.a.",
    "wof:placetype":"venue"
},
  "geometry": {"coordinates":[-3.7079622746,40.4345550537],"type":"Point"}
}