{
  "type": "Feature",
  "properties": {
    "iso:country":"ES",
    "sg:address":"Urb Molino De San Martin, S/n",
    "sg:city":"Cabez\u00f3n Sal",
    "sg:orig_category":"Promotores Constructores",
    "sg:phone":"+34 942 70 21 56",
    "sg:postcode":"39500",
    "sg:province":"Cantabria",
    "wof:name":"Rc Cotera Construcciones S.l.",
    "wof:placetype":"venue"
},
  "geometry": {"coordinates":[-4.2374691963,43.3085784912],"type":"Point"}
}