{
  "type": "Feature",
  "properties": {
    "addr:full":"Calle de Santa Adela, 24 Peligros Granada 18210",
    "addr:housenumber":"24",
    "addr:postcode":"18210",
    "addr:street":"Calle De Santa Adela",
    "iso:country":"ES",
    "sg:address":"Calle de Santa Adela, 24",
    "sg:city":"Peligros",
    "sg:orig_category":"Centros De Coordinaci\u00d3n",
    "sg:phone":"+34 958 40 01 73",
    "sg:postcode":"18210",
    "sg:province":"Granada",
    "wof:name":"Milena Milena Juan German",
    "wof:placetype":"venue"
},
  "geometry": {"coordinates":[-3.6285259724,37.2321624756],"type":"Point"}
}