{
  "type": "Feature",
  "properties": {
    "addr:full":"Avda Constitucion (la), 3 Bormujos Sevilla 41930",
    "addr:housenumber":"3",
    "addr:postcode":"41930",
    "addr:street":"Avda Constitucion La",
    "iso:country":"ES",
    "sg:address":"Avda Constitucion (la), 3",
    "sg:city":"Bormujos",
    "sg:orig_category":"Peluquer\u00cdas, Peluquer\u00cda Mixta",
    "sg:phone":"+34 954 78 82 49",
    "sg:postcode":"41930",
    "sg:province":"Sevilla",
    "wof:name":"Gutierrez Prada Estefania",
    "wof:placetype":"venue"
},
  "geometry": {"coordinates":[-6.0679769516,37.3734169006],"type":"Point"}
}