{
  "type": "Feature",
  "properties": {
    "addr:full":"Fuentespino, 25 Fuentespino Asturias 33188",
    "addr:housenumber":"25",
    "addr:postcode":"33188",
    "addr:street":"Fuentespino;Asturias",
    "iso:country":"ES",
    "sg:address":"Fuentespino, 25",
    "sg:city":"Fuentespino",
    "sg:orig_category":"Confecci\u00d3n De Chales, De Bufandas Y De Pa\u00d1uelos De Vestir",
    "sg:phone":"+34 985 74 07 91",
    "sg:postcode":"33188",
    "sg:province":"Asturias",
    "wof:name":"Unade2 Seleccion S.l.u",
    "wof:placetype":"venue"
},
  "geometry": {"coordinates":[-5.7278189659,43.3858985901],"type":"Point"}
}