{
  "type": "Feature",
  "properties": {
    "addr:full":"Plaz Trinidad, 5 Almodovar Campo Ciudad Real 13580",
    "addr:housenumber":"5",
    "addr:postcode":"13580",
    "addr:street":"Plaz Trinidad;Campo",
    "iso:country":"ES",
    "sg:address":"Plaz Trinidad, 5",
    "sg:city":"Almodovar Campo",
    "sg:orig_category":"Cajas Para Embalar",
    "sg:phone":"+34 926 48 31 68",
    "sg:postcode":"13580",
    "sg:province":"Ciudad Real",
    "wof:name":"Caja Rural De Ciudad Real",
    "wof:placetype":"venue"
},
  "geometry": {"coordinates":[-4.1820688248,38.7115097046],"type":"Point"}
}