{
  "type": "Feature",
  "properties": {
    "addr:full":"Pl Vila, 12 Santa Coloma De Gramenet Barcelona 08922",
    "addr:housenumber":"12",
    "addr:postcode":"08922",
    "addr:street":"Pl Vila",
    "iso:country":"ES",
    "sg:address":"Pl Vila, 12",
    "sg:city":"Santa Coloma De Gramenet",
    "sg:orig_category":"Relojer\u00cda (al Por Menor, Reparaci\u00d3n)",
    "sg:phone":"+34 933 86 08 09",
    "sg:postcode":"08922",
    "sg:province":"Barcelona",
    "wof:name":"Rocafort Gomez-galdon Benito",
    "wof:placetype":"venue"
},
  "geometry": {"coordinates":[2.2088730335,41.4515533447],"type":"Point"}
}