{
  "type": "Feature",
  "properties": {
    "iso:country":"ES",
    "sg:address":"Calle de Pedro El Morato, S/n",
    "sg:city":"Vera",
    "sg:orig_category":"Ense\u00d1anza Variada",
    "sg:phone":"+34 950 39 06 39",
    "sg:postcode":"04620",
    "sg:province":"Almer\u00eda",
    "sg:website":"www.cepalmeral.com",
    "wof:name":"Centro De Ense\u00f1anza El Palmeral S.l",
    "wof:placetype":"venue"
},
  "geometry": {"coordinates":[-1.8684029579,37.2491760254],"type":"Point"}
}