{
  "type": "Feature",
  "properties": {
    "addr:full":"Barr Monte Mazo, S/n Loredo Cantabria 39140",
    "addr:housenumber":"s / n",
    "addr:postcode":"39140",
    "iso:country":"ES",
    "sg:address":"Barr Monte Mazo, S/n",
    "sg:city":"Loredo",
    "sg:orig_category":"Bricolaje, Herramientas (al Por Menor)",
    "sg:phone":"+34 942 50 40 80",
    "sg:postcode":"39140",
    "sg:province":"Cantabria",
    "wof:name":"Millan Perez Rafaela",
    "wof:placetype":"venue"
},
  "geometry": {"coordinates":[-3.7197210789,43.4614562988],"type":"Point"}
}