{
  "type": "Feature",
  "properties": {
    "addr:full":"Calle de Decano Juan De Hoyos, 10 Torremolinos M\u00e1laga 29620",
    "addr:housenumber":"10",
    "addr:postcode":"29620",
    "addr:street":"Calle De Decano Juan De Hoyos;Ma\u0301Laga",
    "iso:country":"ES",
    "sg:address":"Calle de Decano Juan De Hoyos, 10",
    "sg:city":"Torremolinos",
    "sg:orig_category":"Fabricaci\u00d3n, Instalaci\u00d3n De Saunas",
    "sg:phone":"+34 952 37 59 19",
    "sg:postcode":"29620",
    "sg:province":"M\u00e1laga",
    "wof:name":"Pooderman S.a.",
    "wof:placetype":"venue"
},
  "geometry": {"coordinates":[-4.5160841942,36.6087608337],"type":"Point"}
}