{
  "type": "Feature",
  "properties": {
    "addr:full":"Plaz Costal, 9 Cangas Pontevedra 36940",
    "addr:housenumber":"9",
    "addr:postcode":"36940",
    "addr:street":"Plaz Costal",
    "iso:country":"ES",
    "sg:address":"Plaz Costal, 9",
    "sg:city":"Cangas",
    "sg:orig_category":"Arquitectos",
    "sg:phone":"+34 986 39 20 89",
    "sg:postcode":"36940",
    "sg:province":"Pontevedra",
    "wof:name":"Rial Lemos Javier",
    "wof:placetype":"venue"
},
  "geometry": {"coordinates":[-8.8184690475,42.2741928101],"type":"Point"}
}