{
  "type": "Feature",
  "properties": {
    "addr:full":"Plaz Sordo Arroyo (del), 2 Colmenar Viejo Madrid 28770",
    "addr:postcode":"28770",
    "addr:street":"Plaz Sordo Arroyo Del",
    "iso:country":"ES",
    "sg:address":"Plaz Sordo Arroyo (del), 2",
    "sg:city":"Colmenar Viejo",
    "sg:orig_category":"Caf\u00c9s, Bares, Cervecer\u00cdas",
    "sg:phone":"+34 918 45 91 88",
    "sg:postcode":"28770",
    "sg:province":"Madrid",
    "wof:name":"Tapia Diaz Antonia",
    "wof:placetype":"venue"
},
  "geometry": {"coordinates":[-3.7678771019,40.6565589905],"type":"Point"}
}