{
  "type": "Feature",
  "properties": {
    "addr:full":"Calle de Cirilo Cantero, S/n Villarrubia Santiago Toledo 45360",
    "addr:housenumber":"s / n",
    "addr:postcode":"45360",
    "addr:street":"Calle De Cirilo Cantero;Villarrubia",
    "iso:country":"ES",
    "sg:address":"Calle de Cirilo Cantero, S/n",
    "sg:city":"Villarrubia Santiago",
    "sg:orig_category":"Productores Recolectores, Venta Directa De Vinos",
    "sg:phone":"+34 925 15 00 59",
    "sg:postcode":"45360",
    "sg:province":"Toledo",
    "wof:name":"S.c.l. Nuestra Se\u00d1ora Del Castellar",
    "wof:placetype":"venue"
},
  "geometry": {"coordinates":[-3.370634079,39.980796814],"type":"Point"}
}