{
  "type": "Feature",
  "properties": {
    "iso:country":"ES",
    "sg:address":"Avda Andalucia, 35",
    "sg:city":"Santiago Espada",
    "sg:orig_category":"Producci\u00d3n, Distribuci\u00d3n De Gas Butano Y Propano",
    "sg:phone":"+34 953 43 85 63",
    "sg:postcode":"23290",
    "sg:province":"Ja\u00e9n",
    "wof:name":"Sanchez Mu\u00f1oz Luis Gabriel",
    "wof:placetype":"venue"
},
  "geometry": {"coordinates":[-2.5539550781,38.1097640991],"type":"Point"}
}