{
  "type": "Feature",
  "properties": {
    "addr:full":"Carr Pare Bartomeu Pou, 32 Algaida Islas Baleares 07210",
    "addr:housenumber":"32",
    "addr:postcode":"07210",
    "addr:street":"Carr Pare Bartomeu Pou",
    "iso:country":"ES",
    "sg:address":"Carr Pare Bartomeu Pou, 32",
    "sg:city":"Algaida",
    "sg:orig_category":"Laboratorios Y Trabajos De Fotograf\u00cda, V\u00cddeo Y Cine",
    "sg:phone":"+34 971 66 51 70",
    "sg:postcode":"07210",
    "sg:province":"Islas Baleares",
    "wof:name":"Balaguer Rotger Jaime",
    "wof:placetype":"venue"
},
  "geometry": {"coordinates":[2.9009900093,39.5650901794],"type":"Point"}
}