{
  "type": "Feature",
  "properties": {
    "iso:country":"ES",
    "sg:address":"Calle de Torre De La, 6",
    "sg:city":"Bilbao",
    "sg:orig_category":"Asesor\u00cda Sobre Comunicaci\u00d3n De Empresas",
    "sg:phone":"+34 944 15 09 76",
    "sg:postcode":"48005",
    "sg:province":"Vizcaya",
    "sg:website":"www.infopolis.es",
    "wof:name":"Infopolis 2000 S.l.",
    "wof:placetype":"venue"
},
  "geometry": {"coordinates":[-2.9461190701,43.2686500549],"type":"Point"}
}