{
  "type": "Feature",
  "properties": {
    "addr:full":"Pl. Cde Rodezno, 10 Iru\u00f1a Navarra 31003",
    "addr:housenumber":"10",
    "addr:postcode":"31003",
    "addr:street":"Pl. Cde Rodezno",
    "iso:country":"ES",
    "sg:address":"Pl. Cde Rodezno, 10",
    "sg:city":"Iru\u00f1a",
    "sg:orig_category":"Retoques De Vestidos",
    "sg:phone":"+34 948 24 76 16",
    "sg:postcode":"31003",
    "sg:province":"Navarra",
    "wof:name":"Garcia Hervas Maria Manuela",
    "wof:placetype":"venue"
},
  "geometry": {"coordinates":[-1.6437540054,42.81275177],"type":"Point"}
}