{
  "type": "Feature",
  "properties": {
    "addr:full":"Calle de Pare Vicent Ribes, 1 Alzira Valencia 46600",
    "addr:housenumber":"1",
    "addr:postcode":"46600",
    "addr:street":"Calle De Pare Vicent Ribes",
    "iso:country":"ES",
    "sg:address":"Calle de Pare Vicent Ribes, 1",
    "sg:city":"Alzira",
    "sg:orig_category":"Promotores Constructores",
    "sg:phone":"+34 962 41 43 56",
    "sg:postcode":"46600",
    "sg:province":"Valencia",
    "wof:name":"Proalzi S.l.",
    "wof:placetype":"venue"
},
  "geometry": {"coordinates":[-0.4291889966,39.1471061707],"type":"Point"}
}