{
  "type": "Feature",
  "properties": {
    "iso:country":"ES",
    "sg:address":"Calle de Feria (la), 21",
    "sg:city":"Coin",
    "sg:orig_category":"Electrodom\u00c9sticos (al Por Menor)",
    "sg:phone":"+34 952 45 00 41",
    "sg:postcode":"29100",
    "sg:province":"M\u00e1laga",
    "wof:name":"Comercial Marmolejo E Hijos S.l",
    "wof:placetype":"venue"
},
  "geometry": {"coordinates":[-4.7590289116,36.6592750549],"type":"Point"}
}