{
  "type": "Feature",
  "properties": {
    "iso:country":"ES",
    "sg:address":"Calle de San Juan, 5",
    "sg:city":"Medina Rioseco",
    "sg:orig_category":"Electrodom\u00c9sticos (al Por Menor)",
    "sg:phone":"+34 983 70 10 51",
    "sg:postcode":"47800",
    "sg:province":"Valladolid",
    "wof:name":"Gutierrez Badas Vicente",
    "wof:placetype":"venue"
},
  "geometry": {"coordinates":[-5.0455741882,41.8835868835],"type":"Point"}
}