{
  "type": "Feature",
  "properties": {
    "addr:full":"Pg Sant Joan, 17 Crevillent Alicante 03330",
    "addr:housenumber":"17",
    "addr:postcode":"03330",
    "addr:street":"Pg Sant Joan",
    "iso:country":"ES",
    "sg:address":"Pg Sant Joan, 17",
    "sg:city":"Crevillent",
    "sg:orig_category":"Promotores Constructores",
    "sg:phone":"+34 966 68 02 30",
    "sg:postcode":"03330",
    "sg:province":"Alicante",
    "wof:name":"Suinsa De Construcciones S.l.",
    "wof:placetype":"venue"
},
  "geometry": {"coordinates":[-0.8054789901,38.2465591431],"type":"Point"}
}