{
  "type": "Feature",
  "properties": {
    "addr:full":"Calle de Independencia, S/n Potes Cantabria 39570",
    "addr:housenumber":"/ n",
    "addr:postcode":"39570",
    "addr:street":"Calle De Independencia S",
    "iso:country":"ES",
    "sg:address":"Calle de Independencia, S/n",
    "sg:city":"Potes",
    "sg:orig_category":"Sanatorios M\u00c9dico",
    "sg:phone":"+34 942 73 02 92",
    "sg:postcode":"39570",
    "sg:province":"Cantabria",
    "wof:name":"Gerencia Atencion Primaria Torrelavega-reinosa",
    "wof:placetype":"venue"
},
  "geometry": {"coordinates":[-4.6240668297,43.1544952393],"type":"Point"}
}