{
  "type": "Feature",
  "properties": {
    "addr:full":"Calle de Madrid, S/n Humera-somosaguas-prado Del Rey Madrid 28223",
    "addr:housenumber":"s",
    "addr:postcode":"28223",
    "addr:street":"Calle De Madrid;/ N",
    "iso:country":"ES",
    "sg:address":"Calle de Madrid, S/n",
    "sg:city":"Humera-somosaguas-prado Del Rey",
    "sg:orig_category":"M\u00c1quinas De Jardiner\u00cda",
    "sg:phone":"+34 917 99 03 94",
    "sg:postcode":"28223",
    "sg:province":"Madrid",
    "wof:name":"Asociacion Espa\u00f1ola De Parques Y Jardines Publicos",
    "wof:placetype":"venue"
},
  "geometry": {"coordinates":[-3.7003455162,40.4166908264],"type":"Point"}
}