{
  "type": "Feature",
  "properties": {
    "iso:country":"ES",
    "sg:address":"Carrer de Pirineus, S/n",
    "sg:city":"Sabadell",
    "sg:orig_category":"Carnicer\u00cdas, Carnicer\u00cdas",
    "sg:phone":"+34 937 16 44 99",
    "sg:postcode":"08208",
    "sg:province":"Barcelona",
    "wof:name":"Medran Caballero Joan",
    "wof:placetype":"venue"
},
  "geometry": {"coordinates":[2.1021149158,41.5605812073],"type":"Point"}
}