{
  "type": "Feature",
  "properties": {
    "addr:full":"Galicia(p I El Pastoret), 20 Monovar Alicante 03640",
    "addr:housenumber":"20",
    "addr:postcode":"03640",
    "addr:street":"P;El Pastoret;Alicante",
    "iso:country":"ES",
    "sg:address":"Galicia(p I El Pastoret), 20",
    "sg:city":"Monovar",
    "sg:orig_category":"Limpieza Industrial",
    "sg:phone":"+34 965 47 14 68",
    "sg:postcode":"03640",
    "sg:province":"Alicante",
    "wof:name":"Tintoreria Eldense S.l.u.",
    "wof:placetype":"venue"
},
  "geometry": {"coordinates":[-0.8296129704,38.4449424744],"type":"Point"}
}