{
  "type": "Feature",
  "properties": {
    "addr:full":"Carrer de Coronel Sanfeliu, 77 Prat Llobregat Barcelona 08820",
    "addr:housenumber":"77",
    "addr:postcode":"08820",
    "addr:street":"Carrer De Coronel Sanfeliu;Llobregat",
    "iso:country":"ES",
    "sg:address":"Carrer de Coronel Sanfeliu, 77",
    "sg:city":"Prat Llobregat",
    "sg:orig_category":"Vestidos De Se\u00d1ora (tallas Grandes)",
    "sg:phone":"+34 934 78 70 02",
    "sg:postcode":"08820",
    "sg:province":"Barcelona",
    "wof:name":"Gomez Mu\u00f1oz Salud",
    "wof:placetype":"venue"
},
  "geometry": {"coordinates":[2.0962500572,41.3225898743],"type":"Point"}
}