{
  "type": "Feature",
  "properties": {
    "addr:full":"Carr Carles Roman Ferrer, 44 Eivissa Islas Baleares 07800",
    "addr:housenumber":"44",
    "addr:postcode":"07800",
    "addr:street":"Carr Carles Roman Ferrer",
    "iso:country":"ES",
    "sg:address":"Carr Carles Roman Ferrer, 44",
    "sg:city":"Eivissa",
    "sg:orig_category":"Supermercados Y Hipermercados",
    "sg:phone":"+34 971 39 29 16",
    "sg:postcode":"07800",
    "sg:province":"Islas Baleares",
    "wof:name":"Ribas Torres Vicente",
    "wof:placetype":"venue"
},
  "geometry": {"coordinates":[1.4176000357,38.8984909058],"type":"Point"}
}