{
  "type": "Feature",
  "properties": {
    "addr:full":"Carrer de Bertran, 126 Barcelona Barcelona 08023",
    "addr:housenumber":"126",
    "addr:postcode":"08023",
    "addr:street":"Carrer De Bertran",
    "iso:country":"ES",
    "sg:address":"Carrer de Bertran, 126",
    "sg:city":"Barcelona",
    "sg:orig_category":"Mec\u00c1nico Del Autom\u00d3vil",
    "sg:phone":"+34 932 11 89 22",
    "sg:postcode":"08023",
    "sg:province":"Barcelona",
    "wof:name":"Talleres Augusta S. Cv.",
    "wof:placetype":"venue"
},
  "geometry": {"coordinates":[2.1399040222,41.4088935852],"type":"Point"}
}