{
  "type": "Feature",
  "properties": {
    "iso:country":"ES",
    "sg:address":"Plaz Estella, 3",
    "sg:city":"Alacant",
    "sg:orig_category":"Mec\u00c1nico Del Autom\u00d3vil",
    "sg:phone":"+34 965 20 24 26",
    "sg:postcode":"03013",
    "sg:province":"Alicante",
    "wof:name":"Paya Blanquer Eduardo",
    "wof:placetype":"venue"
},
  "geometry": {"coordinates":[-0.4759350121,38.3552703857],"type":"Point"}
}