{
  "type": "Feature",
  "properties": {
    "addr:full":"Avda Damian Tellez Lafuente, 5 Badajoz Badajoz 06010",
    "addr:housenumber":"5",
    "addr:postcode":"06010",
    "addr:street":"Avda Damian Tellez Lafuente",
    "iso:country":"ES",
    "sg:address":"Avda Damian Tellez Lafuente, 5",
    "sg:city":"Badajoz",
    "sg:orig_category":"Laboratorios Y Trabajos De Fotograf\u00cda, V\u00cddeo Y Cine",
    "sg:phone":"+34 924 23 68 81",
    "sg:postcode":"06010",
    "sg:province":"Badajoz",
    "wof:name":"Interphoto S.c.",
    "wof:placetype":"venue"
},
  "geometry": {"coordinates":[-6.9731779099,38.8688774109],"type":"Point"}
}