{
  "type": "Feature",
  "properties": {
    "iso:country":"ES",
    "sg:address":"Pase Habana, 105",
    "sg:city":"Madrid",
    "sg:orig_category":"Abogados",
    "sg:phone":"+34 913 45 14 41",
    "sg:postcode":"28036",
    "sg:province":"Madrid",
    "wof:name":"Scarpa Del Castillo Jorge",
    "wof:placetype":"venue"
},
  "geometry": {"coordinates":[-3.6819679737,40.4588661194],"type":"Point"}
}