{
  "type": "Feature",
  "properties": {
    "iso:country":"ES",
    "sg:address":"Calle de Cid, 4",
    "sg:city":"Puerto",
    "sg:orig_category":"Tintes (fabricaci\u00d3n, Al Por Mayor)",
    "sg:phone":"+34 962 68 10 41",
    "sg:postcode":"46520",
    "sg:province":"Valencia",
    "wof:name":"Juan Melchor Salvador Y Rosa Salvador Alpuente Cdad",
    "wof:placetype":"venue"
},
  "geometry": {"coordinates":[-0.2198863029,39.6627120972],"type":"Point"}
}