{
  "type": "Feature",
  "properties": {
    "iso:country":"ES",
    "sg:address":"Carrer de Carretera Marina, 24",
    "sg:city":"Prat Llobregat",
    "sg:orig_category":"Ropa Para Ni\u00d1os (al Por Menor)",
    "sg:phone":"+34 934 78 11 69",
    "sg:postcode":"08820",
    "sg:province":"Barcelona",
    "wof:name":"Ria\u00f1o Segura Oscar",
    "wof:placetype":"venue"
},
  "geometry": {"coordinates":[2.0993909836,41.3278312683],"type":"Point"}
}