{
  "type": "Feature",
  "properties": {
    "addr:full":"Carrer de Vall, 59 Terrassa Barcelona 08221",
    "addr:housenumber":"59",
    "addr:postcode":"08221",
    "addr:street":"Carrer De Vall",
    "iso:country":"ES",
    "sg:address":"Carrer de Vall, 59",
    "sg:city":"Terrassa",
    "sg:orig_category":"Almacenes De Venta: Muebles, Equipo Para El Hogar",
    "sg:phone":"+34 937 89 50 06",
    "sg:postcode":"08221",
    "sg:province":"Barcelona",
    "wof:name":"Baf Barcelona S.l.",
    "wof:placetype":"venue"
},
  "geometry": {"coordinates":[2.0094795227,41.5609054565],"type":"Point"}
}