{
  "type": "Feature",
  "properties": {
    "iso:country":"ES",
    "sg:address":"Calle de Hendaya, 8",
    "sg:city":"Irun",
    "sg:orig_category":"Universidades",
    "sg:phone":"+34 943 63 91 29",
    "sg:postcode":"20301",
    "sg:province":"Guip\u00f9zcoa",
    "wof:name":"Eteo S.coop. Ltda.",
    "wof:placetype":"venue"
},
  "geometry": {"coordinates":[-1.7955440283,43.3441543579],"type":"Point"}
}