{
  "type": "Feature",
  "properties": {
    "iso:country":"ES",
    "sg:address":"Carr Luis Vives, 53",
    "sg:city":"Moncada",
    "sg:orig_category":"Empresas De Carpinter\u00cda De Madera",
    "sg:phone":"+34 961 39 15 27",
    "sg:postcode":"46113",
    "sg:province":"Valencia",
    "wof:name":"Castello Pascual Rafael",
    "wof:placetype":"venue"
},
  "geometry": {"coordinates":[-0.3974710107,39.5455551147],"type":"Point"}
}