{
  "type": "Feature",
  "properties": {
    "addr:full":"Ctra Montblanc (de), 25 Santa Coloma De Queralt Tarragona 43420",
    "addr:housenumber":"25",
    "addr:postcode":"43420",
    "addr:street":"Ctra Montblanc De",
    "iso:country":"ES",
    "sg:address":"Ctra Montblanc (de), 25",
    "sg:city":"Santa Coloma De Queralt",
    "sg:orig_category":"Caf\u00c9s, Bares, Cervecer\u00cdas",
    "sg:phone":"+34 977 88 04 02",
    "sg:postcode":"43420",
    "sg:province":"Tarragona",
    "wof:name":"Gasso Font Pablo",
    "wof:placetype":"venue"
},
  "geometry": {"coordinates":[1.380900979,41.5308990479],"type":"Point"}
}