{
  "type": "Feature",
  "properties": {
    "addr:full":"Bard Diputacion, S/n Casar Caceres C\u00e1ceres 10190",
    "addr:housenumber":"s / n",
    "addr:postcode":"10190",
    "addr:street":"Diputacion;Ca\u0301Ceres",
    "iso:country":"ES",
    "sg:address":"Bard Diputacion, S/n",
    "sg:city":"Casar Caceres",
    "sg:orig_category":"Alimentaci\u00d3n General (al Por Menor)",
    "sg:phone":"+34 927 29 02 50",
    "sg:postcode":"10190",
    "sg:province":"C\u00e1ceres",
    "wof:name":"Alamillo Manzano Purificacion",
    "wof:placetype":"venue"
},
  "geometry": {"coordinates":[-6.3707604408,39.4761772156],"type":"Point"}
}