{
  "type": "Feature",
  "properties": {
    "addr:full":"Calle de Joaquin Blume, 44 San Vicente Del Raspeig-sant Vicent Del Raspeig Alicante 03690",
    "addr:housenumber":"44",
    "addr:postcode":"03690",
    "addr:street":"Calle De Joaquin Blume",
    "iso:country":"ES",
    "sg:address":"Calle de Joaquin Blume, 44",
    "sg:city":"San Vicente Del Raspeig-sant Vicent Del Raspeig",
    "sg:orig_category":"Comercio, Reparaci\u00d3n De Motocicletas, Bicicletas Y Piezas Sueltas",
    "sg:phone":"+34 965 66 15 24",
    "sg:postcode":"03690",
    "sg:province":"Alicante",
    "wof:name":"Domenech Perez Ramon",
    "wof:placetype":"venue"
},
  "geometry": {"coordinates":[-0.5215229988,38.4020004272],"type":"Point"}
}