{
  "type": "Feature",
  "properties": {
    "addr:full":"Cno. Albadalejo, 5 Jerez C\u00e1diz 11406",
    "addr:housenumber":"5",
    "addr:postcode":"11406",
    "addr:street":"Cno. Albadalejo",
    "iso:country":"ES",
    "sg:address":"Cno. Albadalejo, 5",
    "sg:city":"Jerez",
    "sg:orig_category":"Molduras, Junquillos, Listones Y Molduras Perforadas",
    "sg:phone":"+34 956 34 96 81",
    "sg:postcode":"11406",
    "sg:province":"C\u00e1diz",
    "wof:name":"Gutierrez Romero Maria Jose",
    "wof:placetype":"venue"
},
  "geometry": {"coordinates":[-6.1144099236,36.6865272522],"type":"Point"}
}