{
  "type": "Feature",
  "properties": {
    "addr:full":"Carrer de Jovellanos, 56 Sabadell Barcelona 08201",
    "addr:housenumber":"56",
    "addr:postcode":"08201",
    "addr:street":"Carrer De Jovellanos",
    "iso:country":"ES",
    "sg:address":"Carrer de Jovellanos, 56",
    "sg:city":"Sabadell",
    "sg:orig_category":"Peluquer\u00cdas, Peluquer\u00cda Mixta",
    "sg:phone":"+34 937 27 56 15",
    "sg:postcode":"08201",
    "sg:province":"Barcelona",
    "wof:name":"Cordoba Perez Ana Isabel",
    "wof:placetype":"venue"
},
  "geometry": {"coordinates":[2.1050229073,41.5491485596],"type":"Point"}
}