{
  "type": "Feature",
  "properties": {
    "addr:full":"Carr Sant Josep De Calassan\u00c7, 7 Algemesi Valencia 46680",
    "addr:housenumber":"7",
    "addr:postcode":"46680",
    "addr:street":"Carr Sant Josep De Calassanc\u0327",
    "iso:country":"ES",
    "sg:address":"Carr Sant Josep De Calassan\u00c7, 7",
    "sg:city":"Algemesi",
    "sg:orig_category":"Peluqueros: De Se\u00d1oras",
    "sg:phone":"+34 962 42 00 89",
    "sg:postcode":"46680",
    "sg:province":"Valencia",
    "wof:name":"Maria Salud Carbonell Breso Y Vicenta Jose Barrera Llamas C.b.",
    "wof:placetype":"venue"
},
  "geometry": {"coordinates":[-0.4383220077,39.1898918152],"type":"Point"}
}