{
  "type": "Feature",
  "properties": {
    "addr:full":"Calle de Mayor, 10 Arenas -areeta Vizcaya 48930",
    "addr:housenumber":"10;areeta",
    "addr:postcode":"48930",
    "addr:street":"Calle De Mayor",
    "iso:country":"ES",
    "sg:address":"Calle de Mayor, 10",
    "sg:city":"Arenas -areeta",
    "sg:orig_category":"Notarios",
    "sg:phone":"+34 944 80 35 58",
    "sg:postcode":"48930",
    "sg:province":"Vizcaya",
    "wof:name":"Ruiz Santaflorentina Enrique Maria",
    "wof:placetype":"venue"
},
  "geometry": {"coordinates":[-3.0135939121,43.3252944946],"type":"Point"}
}