{
  "type": "Feature",
  "properties": {
    "addr:full":"C/ Sant Isidre, 19 Cerdanyola Valles Barcelona 08290",
    "addr:housenumber":"19",
    "addr:postcode":"08290",
    "addr:street":"C / Sant Isidre;Valles Barcelona",
    "iso:country":"ES",
    "sg:address":"C/ Sant Isidre, 19",
    "sg:city":"Cerdanyola Valles",
    "sg:orig_category":"Arenas, Guijarros Y Granulados",
    "sg:phone":"+34 935 80 56 80",
    "sg:postcode":"08290",
    "sg:province":"Barcelona",
    "wof:name":"Anskar Caballero Pont",
    "wof:placetype":"venue"
},
  "geometry": {"coordinates":[2.1318421364,41.483707428],"type":"Point"}
}