{
  "type": "Feature",
  "properties": {
    "addr:full":"Ctra Tacoronte Tejina, 116 Tacoronte Santa Cruz De Tenerife 38350",
    "addr:housenumber":"116",
    "addr:postcode":"38350",
    "addr:street":"Ctra Tacoronte Tejina",
    "iso:country":"ES",
    "sg:address":"Ctra Tacoronte Tejina, 116",
    "sg:city":"Tacoronte",
    "sg:orig_category":"Psic\u00d3logos",
    "sg:phone":"+34 922 56 37 16",
    "sg:postcode":"38350",
    "sg:province":"Santa Cruz De Tenerife",
    "wof:name":"Velazquez Trujillo Mariela",
    "wof:placetype":"venue"
},
  "geometry": {"coordinates":[-16.4111862183,28.4825820923],"type":"Point"}
}