{
  "type": "Feature",
  "properties": {
    "addr:full":"Xironda, 36 Xironda Ourense 32688",
    "addr:housenumber":"36",
    "addr:postcode":"32688",
    "addr:street":"Xironda",
    "iso:country":"ES",
    "sg:address":"Xironda, 36",
    "sg:city":"Xironda",
    "sg:orig_category":"Supermercados Y Hipermercados",
    "sg:phone":"+34 988 42 45 69",
    "sg:postcode":"32688",
    "sg:province":"Ourense",
    "wof:name":"Telefourense S.l.",
    "wof:placetype":"venue"
},
  "geometry": {"coordinates":[-7.6374740601,41.9027633667],"type":"Point"}
}