{
  "type": "Feature",
  "properties": {
    "iso:country":"ES",
    "sg:address":"Calle de Virgen Del Mar (de La), 19",
    "sg:city":"Coslada",
    "sg:orig_category":"Centros De Educaci\u00d3n Especial",
    "sg:phone":"+34 916 74 20 90",
    "sg:postcode":"28820",
    "sg:province":"Madrid",
    "wof:name":"Guarderia Kika S.l.",
    "wof:placetype":"venue"
},
  "geometry": {"coordinates":[-3.5645470619,40.428604126],"type":"Point"}
}