{
  "type": "Feature",
  "properties": {
    "addr:full":"Calle de Venecia, 6 Andorra Teruel 44500",
    "addr:housenumber":"6",
    "addr:postcode":"44500",
    "addr:street":"Calle De Venecia",
    "iso:country":"ES",
    "sg:address":"Calle de Venecia, 6",
    "sg:city":"Andorra",
    "sg:orig_category":"Molduras, Junquillos, Listones Y Molduras Perforadas",
    "sg:phone":"+34 978 84 40 08",
    "sg:postcode":"44500",
    "sg:province":"Teruel",
    "wof:name":"Becerra Troya Juan",
    "wof:placetype":"venue"
},
  "geometry": {"coordinates":[-0.4499259889,40.9789428711],"type":"Point"}
}