{
  "type": "Feature",
  "properties": {
    "iso:country":"ES",
    "sg:address":"Calle de Llanterners, Dels, 2",
    "sg:city":"Valencia",
    "sg:orig_category":"Acero: Productos Sider\u00dargicos Y Transformados (fabricaci\u00d3n, Negocio)",
    "sg:phone":"+34 963 79 83 00",
    "sg:postcode":"46014",
    "sg:province":"Valencia",
    "wof:name":"Arcelor Distribucion Levante S.l.",
    "wof:placetype":"venue"
},
  "geometry": {"coordinates":[-0.4155347943,39.5271606445],"type":"Point"}
}