{
  "type": "Feature",
  "properties": {
    "iso:country":"ES",
    "sg:address":"Calle de Olivos, 3",
    "sg:city":"Linares",
    "sg:orig_category":"Plomeros",
    "sg:phone":"+34 953 65 32 15",
    "sg:postcode":"23700",
    "sg:province":"Ja\u00e9n",
    "wof:name":"Fernandez Morillas Juan Manuel",
    "wof:placetype":"venue"
},
  "geometry": {"coordinates":[-3.6187438965,38.1051597595],"type":"Point"}
}