{
  "type": "Feature",
  "properties": {
    "addr:full":"Av. Generalisimo, 12 Fuentespreadas Zamora 49714",
    "addr:housenumber":"12",
    "addr:postcode":"49714",
    "addr:street":"Av. Generalisimo",
    "iso:country":"ES",
    "sg:address":"Av. Generalisimo, 12",
    "sg:city":"Fuentespreadas",
    "sg:orig_category":"Mec\u00c1nico Del Autom\u00d3vil",
    "sg:phone":"+34 980 57 57 94",
    "sg:postcode":"49714",
    "sg:province":"Zamora",
    "wof:name":"Fuentespreadas Metalicos S.l",
    "wof:placetype":"venue"
},
  "geometry": {"coordinates":[-5.6267061234,41.3261222839],"type":"Point"}
}