{
  "type": "Feature",
  "properties": {
    "iso:country":"ES",
    "sg:address":"Saliente, 11",
    "sg:city":"Montealina",
    "sg:orig_category":"Arquitectos",
    "sg:phone":"+34 913 52 81 01",
    "sg:postcode":"28223",
    "sg:province":"Madrid",
    "wof:name":"Fernandez Martin Rafael",
    "wof:placetype":"venue"
},
  "geometry": {"coordinates":[-3.8401238918,40.4249610901],"type":"Point"}
}