{
  "type": "Feature",
  "properties": {
    "addr:full":"Calle de Teruel, 19 Cordoba C\u00f3rdoba 14012",
    "addr:housenumber":"19",
    "addr:postcode":"14012",
    "addr:street":"Calle De Teruel;Co\u0301Rdoba",
    "iso:country":"ES",
    "sg:address":"Calle de Teruel, 19",
    "sg:city":"Cordoba",
    "sg:orig_category":"Cl\u00cdnicas M\u00c9dicas",
    "sg:phone":"+34 957 40 15 51",
    "sg:postcode":"14012",
    "sg:province":"C\u00f3rdoba",
    "wof:name":"Clinica La Sierra S.l.",
    "wof:placetype":"venue"
},
  "geometry": {"coordinates":[-4.7882709503,37.8985481262],"type":"Point"}
}