{
  "type": "Feature",
  "properties": {
    "iso:country":"ES",
    "sg:address":"Calle de Doctor Fleming, 12",
    "sg:city":"Baena",
    "sg:orig_category":"Oficinas: Suministros Para (fabricaci\u00d3n, Al Por Mayor)",
    "sg:phone":"+34 957 66 52 22",
    "sg:postcode":"14850",
    "sg:province":"C\u00f3rdoba",
    "wof:name":"Colodrero Y Gonzalez S.l.l",
    "wof:placetype":"venue"
},
  "geometry": {"coordinates":[-4.3181090355,37.6172599792],"type":"Point"}
}