{
  "type": "Feature",
  "properties": {
    "addr:full":"Calle de Amparo Usera, 46 Madrid Madrid 28026",
    "addr:housenumber":"46",
    "addr:postcode":"madrid;28026",
    "addr:street":"Calle De Amparo Usera",
    "iso:country":"ES",
    "sg:address":"Calle de Amparo Usera, 46",
    "sg:city":"Madrid",
    "sg:orig_category":"Poller\u00cda Y Caza (al Por Menor)",
    "sg:phone":"+34 914 76 84 86",
    "sg:postcode":"28026",
    "sg:province":"Madrid",
    "wof:name":"Tartalo Gonzalez Santiago",
    "wof:placetype":"venue"
},
  "geometry": {"coordinates":[-3.7069859505,40.3870353699],"type":"Point"}
}