{
  "type": "Feature",
  "properties": {
    "addr:full":"Avda Valencia, 7 Gangosa Almer\u00eda 04738",
    "addr:housenumber":"7",
    "addr:postcode":"04738",
    "addr:street":"Avda Valencia;Almeri\u0301A",
    "iso:country":"ES",
    "sg:address":"Avda Valencia, 7",
    "sg:city":"Gangosa",
    "sg:orig_category":"Asesor\u00cda Sobre Comunicaci\u00d3n De Empresas",
    "sg:phone":"+34 950 34 64 62",
    "sg:postcode":"04738",
    "sg:province":"Almer\u00eda",
    "wof:name":"Cervilla Ripoll Juan",
    "wof:placetype":"venue"
},
  "geometry": {"coordinates":[-2.6150989532,36.8059387207],"type":"Point"}
}