{
  "type": "Feature",
  "properties": {
    "addr:full":"Rua Gasset, 99 Pobra Do Carami\u00e7al La Coru\u00f1a 15940",
    "addr:housenumber":"99",
    "addr:postcode":"15940",
    "addr:street":"Rua Gasset;Corun\u0303A",
    "iso:country":"ES",
    "sg:address":"Rua Gasset, 99",
    "sg:city":"Pobra Do Carami\u00e7al",
    "sg:orig_category":"Agencias Y Agentes Comerciales, Representantes",
    "sg:phone":"+34 981 83 02 98",
    "sg:postcode":"15940",
    "sg:province":"La Coru\u00f1a",
    "wof:name":"Construcciones Luis Torres Laranga S.l.",
    "wof:placetype":"venue"
},
  "geometry": {"coordinates":[-8.9405622482,42.6006355286],"type":"Point"}
}