{
  "type": "Feature",
  "properties": {
    "iso:country":"ES",
    "sg:address":"Calle de Ramiro Arroyo, 4",
    "sg:city":"Bejar",
    "sg:orig_category":"Empresarios Y Productoras De Espect\u00c1culos",
    "sg:phone":"+34 923 41 09 73",
    "sg:postcode":"37700",
    "sg:province":"Salamanca",
    "wof:name":"Espectaculos Proe S.l.",
    "wof:placetype":"venue"
},
  "geometry": {"coordinates":[-5.7565250397,40.3869171143],"type":"Point"}
}