{
  "type": "Feature",
  "properties": {
    "iso:country":"ES",
    "sg:address":"Avda Diputacion (de La), 85",
    "sg:city":"Chiclana De La Frontera",
    "sg:orig_category":"Farmacias",
    "sg:phone":"+34 956 40 48 97",
    "sg:postcode":"11130",
    "sg:province":"C\u00e1diz",
    "wof:name":"Roquette Gaona Francisco Javier",
    "wof:placetype":"venue"
},
  "geometry": {"coordinates":[-6.1732931137,36.3805923462],"type":"Point"}
}