{
  "type": "Feature",
  "properties": {
    "iso:country":"ES",
    "sg:address":"Ctra Castellar, 536",
    "sg:city":"Terrassa",
    "sg:orig_category":"Suelos",
    "sg:phone":"+34 937 85 98 16",
    "sg:postcode":"08227",
    "sg:province":"Barcelona",
    "wof:name":"Pavimentos Egarenses S. A.",
    "wof:placetype":"venue"
},
  "geometry": {"coordinates":[2.0344409943,41.5781669617],"type":"Point"}
}