{
  "type": "Feature",
  "properties": {
    "addr:full":"Calle de Mayor, 64 Sanchotello Salamanca 37794",
    "addr:housenumber":"64",
    "addr:postcode":"37794",
    "addr:street":"Calle De Mayor",
    "iso:country":"ES",
    "sg:address":"Calle de Mayor, 64",
    "sg:city":"Sanchotello",
    "sg:orig_category":"Producci\u00d3n, Venta De Productos De Agricultura Biol\u00d3gica",
    "sg:phone":"+34 923 59 12 04",
    "sg:postcode":"37794",
    "sg:province":"Salamanca",
    "wof:name":"Hijos De Hilario Garcia,s.l.",
    "wof:placetype":"venue"
},
  "geometry": {"coordinates":[-5.7523589134,40.4383888245],"type":"Point"}
}