{
  "type": "Feature",
  "properties": {
    "addr:full":"Calle de Gran Via De San Marcos, 51 Le\u00f3n Le\u00f3n 24002",
    "addr:housenumber":"51",
    "addr:postcode":"24002",
    "addr:street":"Calle De Gran Via De San Marcos;Leo\u0301N",
    "iso:country":"ES",
    "sg:address":"Calle de Gran Via De San Marcos, 51",
    "sg:city":"Le\u00f3n",
    "sg:orig_category":"Alimentaci\u00d3n General (al Por Menor)",
    "sg:phone":"+34 987 23 52 86",
    "sg:postcode":"24002",
    "sg:province":"Le\u00f3n",
    "wof:name":"Juarez Garcia Marta Maria",
    "wof:placetype":"venue"
},
  "geometry": {"coordinates":[-5.5716609955,42.5981369019],"type":"Point"}
}