{
  "type": "Feature",
  "properties": {
    "iso:country":"ES",
    "sg:address":"Carr Sant Carles, 8",
    "sg:city":"Lleida",
    "sg:orig_category":"Imprenta",
    "sg:phone":"+34 973 26 80 54",
    "sg:postcode":"25002",
    "sg:province":"Lleida",
    "wof:name":"Publicacions Dels Pa Sos Catalans S.l.",
    "wof:placetype":"venue"
},
  "geometry": {"coordinates":[0.622353971,41.6167259216],"type":"Point"}
}