{
  "type": "Feature",
  "properties": {
    "iso:country":"ES",
    "sg:address":"Pg Sunyer, 45",
    "sg:city":"Reus",
    "sg:orig_category":"Arquitectos",
    "sg:phone":"+34 977 33 13 68",
    "sg:postcode":"43202",
    "sg:province":"Tarragona",
    "wof:name":"Studi D'arquitectura 98 S.l.",
    "wof:placetype":"venue"
},
  "geometry": {"coordinates":[1.1012599468,41.1582946777],"type":"Point"}
}