{
  "type": "Feature",
  "properties": {
    "iso:country":"ES",
    "sg:address":"Calle de Melchor Fernandez Almagro, S/n",
    "sg:city":"Madrid",
    "sg:orig_category":"Librer\u00cdas",
    "sg:phone":"+34 913 14 20 31",
    "sg:postcode":"28029",
    "sg:province":"Madrid",
    "wof:name":"Canseco Amor Pablo",
    "wof:placetype":"venue"
},
  "geometry": {"coordinates":[-3.6979420185,40.4778404236],"type":"Point"}
}