{
  "type": "Feature",
  "properties": {
    "iso:country":"ES",
    "sg:address":"Calle de Eduardo Barron, 1",
    "sg:city":"Zamora",
    "sg:orig_category":"M\u00c9dicos: Cirug\u00cda General",
    "sg:phone":"+34 980 52 46 18",
    "sg:postcode":"49016",
    "sg:province":"Zamora",
    "wof:name":"Gomez Blanco Jose Luis",
    "wof:placetype":"venue"
},
  "geometry": {"coordinates":[-5.7480831146,41.5016479492],"type":"Point"}
}