{
  "type": "Feature",
  "properties": {
    "iso:country":"ES",
    "sg:address":"Calle de Graham Bell, S/n",
    "sg:city":"Sevilla",
    "sg:orig_category":"Ense\u00d1anza Variada",
    "sg:phone":"+34 954 27 92 80",
    "sg:postcode":"41010",
    "sg:province":"Sevilla",
    "wof:name":"Diasoft Formacion S.l.",
    "wof:placetype":"venue"
},
  "geometry": {"coordinates":[-6.0092940331,37.3758773804],"type":"Point"}
}