{
  "type": "Feature",
  "properties": {
    "iso:country":"ES",
    "sg:address":"Calle de Fresno (el), 14",
    "sg:city":"S. Cristobal Segovia",
    "sg:orig_category":"Promotores Constructores",
    "sg:phone":"+34 921 40 69 22",
    "sg:postcode":"40197",
    "sg:province":"Segovia",
    "wof:name":"Procons Meis S.l.",
    "wof:placetype":"venue"
},
  "geometry": {"coordinates":[-4.0762438774,40.9524841309],"type":"Point"}
}