{
  "type": "Feature",
  "properties": {
    "addr:full":"Calle de Gran Via, 62 Madrid Madrid 28013",
    "addr:housenumber":"62",
    "addr:postcode":"madrid;28013",
    "addr:street":"Calle De Gran Via",
    "iso:country":"ES",
    "sg:address":"Calle de Gran Via, 62",
    "sg:city":"Madrid",
    "sg:orig_category":"Dietistas",
    "sg:phone":"+34 915 59 69 14",
    "sg:postcode":"28013",
    "sg:province":"Madrid",
    "sg:website":"www.santiveri.es",
    "wof:name":"Casa Santiveri S.l.",
    "wof:placetype":"venue"
},
  "geometry": {"coordinates":[-3.7084589005,40.4220275879],"type":"Point"}
}