{
  "type": "Feature",
  "properties": {
    "addr:full":"Canonigo Selma, 6 Traiguera Castell\u00f3n 12330",
    "addr:housenumber":"6",
    "addr:postcode":"12330",
    "addr:street":"Castello\u0301N",
    "iso:country":"ES",
    "sg:address":"Canonigo Selma, 6",
    "sg:city":"Traiguera",
    "sg:orig_category":"Empresarios",
    "sg:phone":"+34 964 49 50 80",
    "sg:postcode":"12330",
    "sg:province":"Castell\u00f3n",
    "wof:name":"Della Morera Jose",
    "wof:placetype":"venue"
},
  "geometry": {"coordinates":[0.2892799973,40.5237693787],"type":"Point"}
}