{
  "type": "Feature",
  "properties": {
    "addr:full":"Calle de Avellanos Los, 5 Oviedo Asturias 33002",
    "addr:housenumber":"5",
    "addr:postcode":"33002",
    "addr:street":"Calle De Avellanos Los",
    "iso:country":"ES",
    "sg:address":"Calle de Avellanos Los, 5",
    "sg:city":"Oviedo",
    "sg:orig_category":"Peluquer\u00cdas, Peluquer\u00cda Mixta",
    "sg:phone":"+34 985 21 96 26",
    "sg:postcode":"33002",
    "sg:province":"Asturias",
    "wof:name":"Cofi\u00f1o Peluqueros S.l.",
    "wof:placetype":"venue"
},
  "geometry": {"coordinates":[-5.8466887474,43.3661193848],"type":"Point"}
}