{
  "type": "Feature",
  "properties": {
    "iso:country":"ES",
    "sg:address":"Calle de San Leopoldo, 72",
    "sg:city":"Madrid",
    "sg:orig_category":"Ense\u00d1anza: Profesiones Art\u00cdsticas",
    "sg:phone":"+34 915 32 58 11",
    "sg:postcode":"28029",
    "sg:province":"Madrid",
    "sg:website":"www.eyestorm.wf",
    "wof:name":"The Eyestorm S.l.",
    "wof:placetype":"venue"
},
  "geometry": {"coordinates":[-3.6947472095,40.4708404541],"type":"Point"}
}