{
  "type": "Feature",
  "properties": {
    "iso:country":"ES",
    "sg:address":"Ambito Portuario, 36",
    "sg:city":"Pasai Antxo",
    "sg:classifiers":[
        {
            "category":"Manufacturing",
            "subcategory":"Building Materials",
            "type":"Manufacturing & Wholesale Goods"
        }
    ],
    "sg:phone":"+34 943 51 18 46",
    "sg:postcode":"20110",
    "sg:province":"Guip\u00f9zcoa",
    "sg:tags":[
        "cemento",
        "y",
        "de",
        "fabricaci\u00d3n",
        "cal"
    ],
    "wof:name":"Sociedad Financiera Y Minera S.a.",
    "wof:placetype":"venue"
},
  "geometry": {"coordinates":[-1.9174940586,43.3170318604],"type":"Point"}
}