{
  "type": "Feature",
  "properties": {
    "iso:country":"ES",
    "sg:address":"Calle de Blanco Coris, 12",
    "sg:city":"Malaga",
    "sg:orig_category":"Asesor\u00cda Fiscal Y Jur\u00cddica",
    "sg:phone":"+34 952 07 08 84",
    "sg:postcode":"29007",
    "sg:province":"M\u00e1laga",
    "wof:name":"Canca Vazquez Gloria",
    "wof:placetype":"venue"
},
  "geometry": {"coordinates":[-4.4335441589,36.7207298279],"type":"Point"}
}