{
  "type": "Feature",
  "properties": {
    "addr:full":"Calle de Real, 40 Fabero Le\u00f3n 24420",
    "addr:housenumber":"40",
    "addr:postcode":"24420",
    "addr:street":"Calle De Real;Leo\u0301N",
    "iso:country":"ES",
    "sg:address":"Calle de Real, 40",
    "sg:city":"Fabero",
    "sg:orig_category":"Inform\u00c1tica, Ofim\u00c1tica (estudios, Asesor\u00cda, Ingenier\u00cda, Formaci\u00d3n)",
    "sg:phone":"+34 987 55 20 09",
    "sg:postcode":"24420",
    "sg:province":"Le\u00f3n",
    "wof:name":"Procom Digital S.l.",
    "wof:placetype":"venue"
},
  "geometry": {"coordinates":[-6.6267518997,42.7668380737],"type":"Point"}
}