{
  "type": "Feature",
  "properties": {
    "iso:country":"ES",
    "sg:address":"Calle de Nueva, 5",
    "sg:city":"S. Clemente",
    "sg:orig_category":"M\u00c9dicos: Estomatolog\u00cda",
    "sg:phone":"+34 969 30 13 93",
    "sg:postcode":"16600",
    "sg:province":"Cuenca",
    "wof:name":"Lescano Didier Roberto Horacio",
    "wof:placetype":"venue"
},
  "geometry": {"coordinates":[-2.4287269115,39.4020881653],"type":"Point"}
}