{
  "type": "Feature",
  "properties": {
    "addr:full":"Calle de Santa Engracia, 36 Madrid Madrid 28010",
    "addr:housenumber":"36",
    "addr:postcode":"madrid;28010",
    "addr:street":"Calle De Santa Engracia",
    "iso:country":"ES",
    "sg:address":"Calle de Santa Engracia, 36",
    "sg:city":"Madrid",
    "sg:orig_category":"Papeler\u00cdas, Librer\u00cdas",
    "sg:phone":"+34 914 46 07 45",
    "sg:postcode":"28010",
    "sg:province":"Madrid",
    "wof:name":"Bedia Diez Antonio",
    "wof:placetype":"venue"
},
  "geometry": {"coordinates":[-3.6972260475,40.4319419861],"type":"Point"}
}