{
  "type": "Feature",
  "properties": {
    "addr:full":"C/ Amistat, 16 Manacor Islas Baleares 07500",
    "addr:housenumber":"16",
    "addr:postcode":"07500",
    "addr:street":"C / Amistat",
    "iso:country":"ES",
    "sg:address":"C/ Amistat, 16",
    "sg:city":"Manacor",
    "sg:orig_category":"Perfumer\u00cda Y Cosm\u00c9tica (fabricaci\u00d3n, Al Por Mayor)",
    "sg:phone":"+34 971 55 91 97",
    "sg:postcode":"07500",
    "sg:province":"Islas Baleares",
    "wof:name":"Maria Gonzalez Cosmetica S.l.",
    "wof:placetype":"venue"
},
  "geometry": {"coordinates":[3.2101778984,39.5703468323],"type":"Point"}
}