{
  "type": "Feature",
  "properties": {
    "iso:country":"ES",
    "sg:address":"Plaz Arenal (del), 20",
    "sg:city":"Jerez De La Frontera",
    "sg:orig_category":"Sindicatos De Trabajadores",
    "sg:phone":"+34 956 33 50 03",
    "sg:postcode":"11403",
    "sg:province":"C\u00e1diz",
    "wof:name":"Confederacion Nacional Del Trabajo",
    "wof:placetype":"venue"
},
  "geometry": {"coordinates":[-6.1375632286,36.6811676025],"type":"Point"}
}