{
  "type": "Feature",
  "properties": {
    "addr:full":"Carr Abat Oliva, 22 Bisbal D'emporda Girona 17100",
    "addr:housenumber":"22",
    "addr:postcode":"17100",
    "addr:street":"Carr Abat Oliva",
    "iso:country":"ES",
    "sg:address":"Carr Abat Oliva, 22",
    "sg:city":"Bisbal D'emporda",
    "sg:orig_category":"Electricidad: Instaladores",
    "sg:phone":"+34 972 64 38 04",
    "sg:postcode":"17100",
    "sg:province":"Girona",
    "wof:name":"Bahi Masso Gumersindo",
    "wof:placetype":"venue"
},
  "geometry": {"coordinates":[3.0425977707,41.9439201355],"type":"Point"}
}