{
  "type": "Feature",
  "properties": {
    "addr:full":"Calle de Puerta Nueva, 5 San Lorenzo Murcia 30001",
    "addr:housenumber":"5",
    "addr:postcode":"30001",
    "addr:street":"Calle De Puerta Nueva",
    "iso:country":"ES",
    "sg:address":"Calle de Puerta Nueva, 5",
    "sg:city":"San Lorenzo",
    "sg:orig_category":"Inmobiliaria (agencias)",
    "sg:phone":"+34 968 24 89 70",
    "sg:postcode":"30001",
    "sg:province":"Murcia",
    "wof:name":"Grupo Inmobiliario Carceles & Asociados S.l.",
    "wof:placetype":"venue"
},
  "geometry": {"coordinates":[-1.1272389889,37.9884033203],"type":"Point"}
}