{
  "type": "Feature",
  "properties": {
    "addr:full":"Calle de Tomas Trenor, 13 Meliana Valencia 46133",
    "addr:housenumber":"13",
    "addr:postcode":"46133",
    "addr:street":"Calle De Tomas Trenor",
    "iso:country":"ES",
    "sg:address":"Calle de Tomas Trenor, 13",
    "sg:city":"Meliana",
    "sg:orig_category":"Lencer\u00cda Femenina, Corseter\u00cda, Trajes De Ba\u00d1o (al Por Menor)",
    "sg:phone":"+34 961 48 02 08",
    "sg:postcode":"46133",
    "sg:province":"Valencia",
    "wof:name":"Maria Jose Julia Y Amparo Calabuig Ferrando Cdad",
    "wof:placetype":"venue"
},
  "geometry": {"coordinates":[-0.3507170081,39.5291404724],"type":"Point"}
}