{
  "type": "Feature",
  "properties": {
    "iso:country":"ES",
    "sg:address":"Avda Mario Spreafico, S/n",
    "sg:city":"Otro La'o",
    "sg:orig_category":"Centros De Educaci\u00d3n Especial",
    "sg:phone":"+34 968 67 12 15",
    "sg:postcode":"30600",
    "sg:province":"Murcia",
    "wof:name":"Colegio Publico Comarcal Micaela Sanz",
    "wof:placetype":"venue"
},
  "geometry": {"coordinates":[-1.1302499771,37.9829597473],"type":"Point"}
}