{
  "type": "Feature",
  "properties": {
    "iso:country":"ES",
    "sg:address":"Avda Constitucion, 8",
    "sg:city":"Rozas De Madrid",
    "sg:orig_category":"Inmobiliaria (agencias)",
    "sg:phone":"+34 916 36 01 73",
    "sg:postcode":"28230",
    "sg:province":"Madrid",
    "wof:name":"Promobel Servicios Inmobiliarios S.l.",
    "wof:placetype":"venue"
},
  "geometry": {"coordinates":[-3.8749198914,40.4924659729],"type":"Point"}
}