{
  "type": "Feature",
  "properties": {
    "addr:full":"Pg Mallorca, 34 Palma Islas Baleares 07012",
    "addr:housenumber":"34",
    "addr:postcode":"07012",
    "addr:street":"Pg Mallorca",
    "iso:country":"ES",
    "sg:address":"Pg Mallorca, 34",
    "sg:city":"Palma",
    "sg:orig_category":"Inversiones",
    "sg:phone":"+34 971 22 79 89",
    "sg:postcode":"07012",
    "sg:province":"Islas Baleares",
    "wof:name":"Fontcoberta Roger Maria Socorro",
    "wof:placetype":"venue"
},
  "geometry": {"coordinates":[2.644411087,39.5745353699],"type":"Point"}
}