{
  "type": "Feature",
  "properties": {
    "addr:full":"Carrer de Guadiana, 8 Barcelona Barcelona 08014",
    "addr:housenumber":"8",
    "addr:postcode":"08014",
    "addr:street":"Carrer De Guadiana",
    "iso:country":"ES",
    "sg:address":"Carrer de Guadiana, 8",
    "sg:city":"Barcelona",
    "sg:orig_category":"Molduras, Junquillos, Listones Y Molduras Perforadas",
    "sg:phone":"+34 934 21 87 05",
    "sg:postcode":"08014",
    "sg:province":"Barcelona",
    "wof:name":"Perez Gil Cristina",
    "wof:placetype":"venue"
},
  "geometry": {"coordinates":[2.138917923,41.3749656677],"type":"Point"}
}