{
  "type": "Feature",
  "properties": {
    "iso:country":"ES",
    "sg:address":"Pl Mare De Deu De Montserrat, 1",
    "sg:city":"Hospitalet Llobregat",
    "sg:orig_category":"Art\u00cdculos Para Fumadores (al Por Menor)",
    "sg:phone":"+34 933 37 07 87",
    "sg:postcode":"08901",
    "sg:province":"Barcelona",
    "wof:name":"Tria Tu S.l.",
    "wof:placetype":"venue"
},
  "geometry": {"coordinates":[2.1006169319,41.357219696],"type":"Point"}
}