{
  "type": "Feature",
  "properties": {
    "iso:country":"ES",
    "sg:address":"Calle de Fermin Caballero, 19",
    "sg:city":"Cuenca",
    "sg:orig_category":"Alquiler De V\u00cddeo",
    "sg:phone":"+34 969 21 41 44",
    "sg:postcode":"16004",
    "sg:province":"Cuenca",
    "sg:website":"www.galaxia.es",
    "wof:name":"Alsu Vision S.l.",
    "wof:placetype":"venue"
},
  "geometry": {"coordinates":[-2.1352107525,40.0679283142],"type":"Point"}
}