{
  "type": "Feature",
  "properties": {
    "iso:country":"ES",
    "sg:address":"Errebal Kalea, 23",
    "sg:city":"Eibar",
    "sg:orig_category":"Asociaciones Y Clubs Deportivos",
    "sg:phone":"+34 943 70 16 62",
    "sg:postcode":"20600",
    "sg:province":"Guip\u00f9zcoa",
    "wof:name":"Errebal Kirolak, C.b.",
    "wof:placetype":"venue"
},
  "geometry": {"coordinates":[-2.4696118832,43.1859359741],"type":"Point"}
}