{
  "type": "Feature",
  "properties": {
    "addr:full":"Calle de Granadera Canaria, 12 Palmas De Gran Canaria Las Palmas 35001",
    "addr:housenumber":"12",
    "addr:postcode":"35001",
    "addr:street":"Calle De Granadera Canaria",
    "iso:country":"ES",
    "sg:address":"Calle de Granadera Canaria, 12",
    "sg:city":"Palmas De Gran Canaria",
    "sg:orig_category":"Suministros Y Materiales Industriales",
    "sg:phone":"+34 928 31 96 04",
    "sg:postcode":"35001",
    "sg:province":"Las Palmas",
    "wof:name":"Rodriguez Sarmiento Luis",
    "wof:placetype":"venue"
},
  "geometry": {"coordinates":[-15.4128551483,28.0965881348],"type":"Point"}
}