{
  "type": "Feature",
  "properties": {
    "iso:country":"ES",
    "sg:address":"Oialume Bidea, 22",
    "sg:city":"Astigarraga",
    "sg:orig_category":"Metalizados",
    "sg:phone":"+34 943 55 06 05",
    "sg:postcode":"20115",
    "sg:province":"Guip\u00f9zcoa",
    "wof:name":"Meyser S.l.",
    "wof:placetype":"venue"
},
  "geometry": {"coordinates":[-1.9534660578,43.273891449],"type":"Point"}
}