{
  "type": "Feature",
  "properties": {
    "iso:country":"ES",
    "sg:address":"Calle de Embajadores, 205",
    "sg:city":"Madrid",
    "sg:orig_category":"Chapister\u00cda",
    "sg:phone":"+34 915 39 34 19",
    "sg:postcode":"28045",
    "sg:province":"Madrid",
    "wof:name":"Talleres J.l. Llorente S.a.",
    "wof:placetype":"venue"
},
  "geometry": {"coordinates":[-3.6930420399,40.3911323547],"type":"Point"}
}