{
  "type": "Feature",
  "properties": {
    "addr:full":"Ctra Alcantarilla, 146 Nonduermas Murcia 30166",
    "addr:housenumber":"146",
    "addr:postcode":"30166",
    "addr:street":"Ctra Alcantarilla",
    "iso:country":"ES",
    "sg:address":"Ctra Alcantarilla, 146",
    "sg:city":"Nonduermas",
    "sg:orig_category":"Comerciantes Al Por Mayor De Vinos, Licores Y Alcoholes",
    "sg:phone":"+34 968 25 49 78",
    "sg:postcode":"30166",
    "sg:province":"Murcia",
    "wof:name":"Belmonte Pellicer Joaquin",
    "wof:placetype":"venue"
},
  "geometry": {"coordinates":[-1.1620839834,37.9734764099],"type":"Point"}
}