{
  "type": "Feature",
  "properties": {
    "iso:country":"ES",
    "sg:address":"Carrer de Gracia, 48",
    "sg:city":"Sabadell",
    "sg:orig_category":"Fabricaci\u00d3n De Su\u00c9ters Y Chalecos De Punto",
    "sg:phone":"+34 937 26 43 19",
    "sg:postcode":"08201",
    "sg:province":"Barcelona",
    "wof:name":"Hidalgo Carmona Feliciana",
    "wof:placetype":"venue"
},
  "geometry": {"coordinates":[2.1067130566,41.5483856201],"type":"Point"}
}