{
  "type": "Feature",
  "properties": {
    "addr:full":"C/ Alcalde Juan Hernandez Rizo, 29 Elche Alicante 03203",
    "addr:housenumber":"29",
    "addr:postcode":"03203",
    "addr:street":"C / Alcalde Juan Hernandez Rizo",
    "iso:country":"ES",
    "sg:address":"C/ Alcalde Juan Hernandez Rizo, 29",
    "sg:city":"Elche",
    "sg:orig_category":"Agentes Generales De Seguros",
    "sg:phone":"+34 966 61 45 76",
    "sg:postcode":"03203",
    "sg:province":"Alicante",
    "wof:name":"Rodriguez Fluxa Enrique",
    "wof:placetype":"venue"
},
  "geometry": {"coordinates":[-0.6710489988,38.267578125],"type":"Point"}
}