{
  "type": "Feature",
  "properties": {
    "iso:country":"ES",
    "sg:address":"Avda Francisco Fernandez Ordo\u00d1ez, 29",
    "sg:city":"Getafe",
    "sg:orig_category":"Telas Para Tapizar, Cortinas, Pasamaner\u00cda (fabricaci\u00d3n, Al Por Mayor)",
    "sg:phone":"+34 916 81 73 29",
    "sg:postcode":"28903",
    "sg:province":"Madrid",
    "wof:name":"Aranzana Rico Severiano",
    "wof:placetype":"venue"
},
  "geometry": {"coordinates":[-3.7151391506,40.3153266907],"type":"Point"}
}