{
  "type": "Feature",
  "properties": {
    "addr:full":"Ctra Vall D'aran, Km. 0021,0 Almenar Lleida 25126",
    "addr:postcode":"25126",
    "addr:street":"Ctra Vall D'Aran Km. 0021,0",
    "iso:country":"ES",
    "sg:address":"Ctra Vall D'aran, Km. 0021,0",
    "sg:city":"Almenar",
    "sg:orig_category":"Hormig\u00d3n Listo Para Usar",
    "sg:phone":"+34 973 77 04 62",
    "sg:postcode":"25126",
    "sg:province":"Lleida",
    "wof:name":"Cafisol S. A.",
    "wof:placetype":"venue"
},
  "geometry": {"coordinates":[0.5701000094,41.7965507507],"type":"Point"}
}