{
  "type": "Feature",
  "properties": {
    "iso:country":"ES",
    "sg:address":"Ctra. Masegoso, 3",
    "sg:city":"Torija",
    "sg:orig_category":"Cajas De Ahorro",
    "sg:phone":"+34 949 32 01 28",
    "sg:postcode":"19190",
    "sg:province":"Guadalajara",
    "sg:website":"www.ibercaja.es",
    "wof:name":"Caja De Ahorros Y Monte De Piedad De Zaragoza Aragon Y Rioja",
    "wof:placetype":"venue"
},
  "geometry": {"coordinates":[-3.0314040184,40.7436447144],"type":"Point"}
}