{
  "type": "Feature",
  "properties": {
    "iso:country":"ES",
    "sg:address":"Carr Valenti Almirall, 12",
    "sg:city":"Lleida",
    "sg:orig_category":"Asociaciones Y Clubs Deportivos",
    "sg:phone":"+34 973 23 41 00",
    "sg:postcode":"25004",
    "sg:province":"Lleida",
    "wof:name":"Casas Vila Antonio",
    "wof:placetype":"venue"
},
  "geometry": {"coordinates":[0.6269209981,41.6217727661],"type":"Point"}
}