{
  "type": "Feature",
  "properties": {
    "addr:full":"Carrer de Verge De Montserrat, 27 Cambrils Tarragona 43850",
    "addr:housenumber":"27",
    "addr:postcode":"43850",
    "addr:street":"Carrer De Verge De Montserrat",
    "iso:country":"ES",
    "sg:address":"Carrer de Verge De Montserrat, 27",
    "sg:city":"Cambrils",
    "sg:orig_category":"Ropa De Trabajo Y Profesionales (al Por Menor)",
    "sg:phone":"+34 977 36 20 03",
    "sg:postcode":"43850",
    "sg:province":"Tarragona",
    "wof:name":"Manuel Ni\u00d1erola Grup Immobiliari S.a.",
    "wof:placetype":"venue"
},
  "geometry": {"coordinates":[1.0537699461,41.0696792603],"type":"Point"}
}