{
  "type": "Feature",
  "properties": {
    "addr:full":"Av Hispanitat, 41 Alcoi Alicante 03804",
    "addr:housenumber":"41",
    "addr:postcode":"03804",
    "addr:street":"Av Hispanitat",
    "iso:country":"ES",
    "sg:address":"Av Hispanitat, 41",
    "sg:city":"Alcoi",
    "sg:orig_category":"Molduras, Junquillos, Listones Y Molduras Perforadas",
    "sg:phone":"+34 965 52 23 66",
    "sg:postcode":"03804",
    "sg:province":"Alicante",
    "wof:name":"Hernandez Fito Antonio",
    "wof:placetype":"venue"
},
  "geometry": {"coordinates":[-0.4662089944,38.7081718445],"type":"Point"}
}