{
  "type": "Feature",
  "properties": {
    "addr:full":"Calle de Gerona, 40 Villafranca De Los Barros Badajoz 06220",
    "addr:housenumber":"40",
    "addr:postcode":"06220",
    "addr:street":"Calle De Gerona",
    "iso:country":"ES",
    "sg:address":"Calle de Gerona, 40",
    "sg:city":"Villafranca De Los Barros",
    "sg:orig_category":"Mantenimiento Y Limpieza De Carreteras",
    "sg:phone":"+34 924 52 04 77",
    "sg:postcode":"06220",
    "sg:province":"Badajoz",
    "wof:name":"Rosa Cuellar Felix",
    "wof:placetype":"venue"
},
  "geometry": {"coordinates":[-6.3354091644,38.5618515015],"type":"Point"}
}