{
  "type": "Feature",
  "properties": {
    "addr:full":"Carrer de Jaume I, 19 Castalla Alicante 03420",
    "addr:housenumber":"19",
    "addr:postcode":"03420",
    "addr:street":"Carrer De Jaume I",
    "iso:country":"ES",
    "sg:address":"Carrer de Jaume I, 19",
    "sg:city":"Castalla",
    "sg:orig_category":"Estancos",
    "sg:phone":"+34 965 56 10 05",
    "sg:postcode":"03420",
    "sg:province":"Alicante",
    "wof:name":"Rico Ribera Antonia",
    "wof:placetype":"venue"
},
  "geometry": {"coordinates":[-0.6711890101,38.5934677124],"type":"Point"}
}