{
  "type": "Feature",
  "properties": {
    "iso:country":"ES",
    "sg:address":"Calle de Reyes Catolicos, 11",
    "sg:city":"S. Pedro Pinatar",
    "sg:orig_category":"Delegados, Agentes De Tr\u00c1nsito, Auxiliares De Transporte Internacional",
    "sg:phone":"+34 968 18 06 55",
    "sg:postcode":"30740",
    "sg:province":"Murcia",
    "wof:name":"Fernandez Hernandez Pedro Jose",
    "wof:placetype":"venue"
},
  "geometry": {"coordinates":[-0.7890729904,37.834564209],"type":"Point"}
}