{
  "type": "Feature",
  "properties": {
    "addr:full":"Avda Delfina Viudes, S/n Torrevieja Alicante 03180",
    "addr:housenumber":"s / n",
    "addr:postcode":"03180",
    "addr:street":"Avda Delfina Viudes",
    "iso:country":"ES",
    "sg:address":"Avda Delfina Viudes, S/n",
    "sg:city":"Torrevieja",
    "sg:orig_category":"Autob\u00das (explotaci\u00d3n Y Servicios De)",
    "sg:phone":"+34 965 71 69 99",
    "sg:postcode":"03180",
    "sg:province":"Alicante",
    "sg:website":"www.costazul.net",
    "wof:name":"Cableuropa",
    "wof:placetype":"venue"
},
  "geometry": {"coordinates":[-0.6801660061,37.992225647],"type":"Point"}
}