{
  "type": "Feature",
  "properties": {
    "iso:country":"ES",
    "sg:address":"Calle de San Cristobal, 3",
    "sg:city":"Maracena",
    "sg:orig_category":"Laboratorios Y Trabajos De Fotograf\u00cda, V\u00cddeo Y Cine",
    "sg:phone":"+34 958 42 13 15",
    "sg:postcode":"18200",
    "sg:province":"Granada",
    "wof:name":"Ismael Romero Fotografo S.l.",
    "wof:placetype":"venue"
},
  "geometry": {"coordinates":[-3.6348330975,37.2085838318],"type":"Point"}
}