{
  "type": "Feature",
  "properties": {
    "addr:full":"Avda Segovia, 48 Valladolid Valladolid 47013",
    "addr:housenumber":"48",
    "addr:postcode":"47013",
    "addr:street":"Avda Segovia",
    "iso:country":"ES",
    "sg:address":"Avda Segovia, 48",
    "sg:city":"Valladolid",
    "sg:orig_category":"Ense\u00d1anza: Idiomas",
    "sg:phone":"+34 983 47 92 66",
    "sg:postcode":"47013",
    "sg:province":"Valladolid",
    "wof:name":"Escuela Oficial De Idiomas De Valladolid",
    "wof:placetype":"venue"
},
  "geometry": {"coordinates":[-4.7217130661,41.6368141174],"type":"Point"}
}