{
  "type": "Feature",
  "properties": {
    "iso:country":"ES",
    "sg:address":"Yerri, 8",
    "sg:city":"Estella",
    "sg:orig_category":"Estancos",
    "sg:phone":"+34 948 55 38 18",
    "sg:postcode":"31200",
    "sg:province":"Navarra",
    "wof:name":"Martinez Beruete Jose Ramon",
    "wof:placetype":"venue"
},
  "geometry": {"coordinates":[-2.0355570316,42.6739768982],"type":"Point"}
}