{
  "type": "Feature",
  "properties": {
    "addr:full":"Ctra. Madrid-barcelona, Km. 0144,0 Esteras Medinaceli Soria 42230",
    "addr:postcode":"42230",
    "addr:street":"Ctra. Madrid-Barcelona Km. 0144,0 Esteras",
    "iso:country":"ES",
    "sg:address":"Ctra. Madrid-barcelona, Km. 0144,0",
    "sg:city":"Esteras Medinaceli",
    "sg:orig_category":"Albergues",
    "sg:phone":"+34 975 32 60 07",
    "sg:postcode":"42230",
    "sg:province":"Soria",
    "wof:name":"Via Europa S.l.",
    "wof:placetype":"venue"
},
  "geometry": {"coordinates":[-2.5298569202,41.2097129822],"type":"Point"}
}