{
  "type": "Feature",
  "properties": {
    "addr:full":"Calle de Sevilla, 31 Jerez De La Frontera C\u00e1diz 11402",
    "addr:housenumber":"31",
    "addr:postcode":"11402",
    "addr:street":"Calle De Sevilla",
    "iso:country":"ES",
    "sg:address":"Calle de Sevilla, 31",
    "sg:city":"Jerez De La Frontera",
    "sg:orig_category":"M\u00c9dicos: Neurolog\u00cda",
    "sg:phone":"+34 956 16 88 54",
    "sg:postcode":"11402",
    "sg:province":"C\u00e1diz",
    "wof:name":"Pery Seco Jose Maria",
    "wof:placetype":"venue"
},
  "geometry": {"coordinates":[-6.1368150711,36.6896820068],"type":"Point"}
}