{
  "type": "Feature",
  "properties": {
    "addr:full":"Psaje Constitucion, 4 Altea Alicante 03590",
    "addr:housenumber":"4",
    "addr:postcode":"03590",
    "addr:street":"Psaje Constitucion",
    "iso:country":"ES",
    "sg:address":"Psaje Constitucion, 4",
    "sg:city":"Altea",
    "sg:orig_category":"Persianas Interiores, Exteriores",
    "sg:phone":"+34 965 84 01 10",
    "sg:postcode":"03590",
    "sg:province":"Alicante",
    "wof:name":"Toldos Lolita C.b",
    "wof:placetype":"venue"
},
  "geometry": {"coordinates":[-0.047584001,38.6018333435],"type":"Point"}
}