{
  "type": "Feature",
  "properties": {
    "iso:country":"ES",
    "sg:address":"Calle de Real, 47",
    "sg:city":"Union",
    "sg:orig_category":"Zapatos (al Por Menor)",
    "sg:phone":"+34 968 56 01 40",
    "sg:postcode":"30360",
    "sg:province":"Murcia",
    "wof:name":"Albaladejo Vazquez Jose Nicolas",
    "wof:placetype":"venue"
},
  "geometry": {"coordinates":[-0.8773247004,37.6205406189],"type":"Point"}
}