{
  "type": "Feature",
  "properties": {
    "addr:full":"Avda Madrid, 349 Calypo Fado Toledo 45950",
    "addr:housenumber":"349",
    "addr:postcode":"45950",
    "addr:street":"Avda Madrid",
    "iso:country":"ES",
    "sg:address":"Avda Madrid, 349",
    "sg:city":"Calypo Fado",
    "sg:orig_category":"Asociaciones Y Clubs Deportivos",
    "sg:phone":"+34 918 13 26 46",
    "sg:postcode":"45950",
    "sg:province":"Toledo",
    "wof:name":"Torres Perez Jose Antonio",
    "wof:placetype":"venue"
},
  "geometry": {"coordinates":[-4.0547089577,40.250125885],"type":"Point"}
}