{
  "type": "Feature",
  "properties": {
    "addr:full":"Carr Segre, 8 Girona Girona 17003",
    "addr:housenumber":"8",
    "addr:postcode":"17003",
    "addr:street":"Carr Segre",
    "iso:country":"ES",
    "sg:address":"Carr Segre, 8",
    "sg:city":"Girona",
    "sg:orig_category":"Caf\u00c9s, Bares, Cervecer\u00cdas",
    "sg:phone":"+34 972 20 46 55",
    "sg:postcode":"17003",
    "sg:province":"Girona",
    "wof:name":"Garcia Correa Nadia",
    "wof:placetype":"venue"
},
  "geometry": {"coordinates":[2.8139929771,41.9664344788],"type":"Point"}
}