{
  "type": "Feature",
  "properties": {
    "iso:country":"ES",
    "sg:address":"Avda Villafranca, 70",
    "sg:city":"Bembibre",
    "sg:orig_category":"Electricidad (montaje, Ensamblaje De Componentes)",
    "sg:phone":"+34 987 51 45 18",
    "sg:postcode":"24300",
    "sg:province":"Le\u00f3n",
    "wof:name":"Torre Alvarez Venancio",
    "wof:placetype":"venue"
},
  "geometry": {"coordinates":[-6.4179491997,42.6159896851],"type":"Point"}
}