{
  "type": "Feature",
  "properties": {
    "addr:full":"Avda Segovia, 21 Valladolid Valladolid 47013",
    "addr:housenumber":"21",
    "addr:postcode":"47013",
    "addr:street":"Avda Segovia",
    "iso:country":"ES",
    "sg:address":"Avda Segovia, 21",
    "sg:city":"Valladolid",
    "sg:orig_category":"Bisuter\u00cda, Joyer\u00cda, Relojer\u00cda (al Por Menor)",
    "sg:phone":"+34 983 29 39 25",
    "sg:postcode":"47013",
    "sg:province":"Valladolid",
    "wof:name":"Polo Represa Juan Antonio",
    "wof:placetype":"venue"
},
  "geometry": {"coordinates":[-4.721031189,41.6426963806],"type":"Point"}
}