{
  "type": "Feature",
  "properties": {
    "addr:full":"Calle de Jose Segura Torres, 1 Corralejo Las Palmas 35660",
    "addr:housenumber":"1",
    "addr:postcode":"35660",
    "addr:street":"Calle De Jose Segura Torres",
    "iso:country":"ES",
    "sg:address":"Calle de Jose Segura Torres, 1",
    "sg:city":"Corralejo",
    "sg:orig_category":"Bazares, Art\u00cdculos De Limpieza Y De Cocina (al Por Menor)",
    "sg:phone":"+34 928 53 57 55",
    "sg:postcode":"35660",
    "sg:province":"Las Palmas",
    "wof:name":"Fuentes Perez Jose Manuel",
    "wof:placetype":"venue"
},
  "geometry": {"coordinates":[-13.8684072495,28.7384471893],"type":"Point"}
}