{
  "type": "Feature",
  "properties": {
    "addr:full":"Carrer de Felip Pedrell, 17 Hospitalet Llobregat Barcelona 08905",
    "addr:housenumber":"17",
    "addr:postcode":"08905",
    "addr:street":"Carrer De Felip Pedrell",
    "iso:country":"ES",
    "sg:address":"Carrer de Felip Pedrell, 17",
    "sg:city":"Hospitalet Llobregat",
    "sg:orig_category":"Laboratorios Y Trabajos De Fotograf\u00cda, V\u00cddeo Y Cine",
    "sg:phone":"+34 934 49 62 03",
    "sg:postcode":"08905",
    "sg:province":"Barcelona",
    "wof:name":"Alvarez Garceso Francisco",
    "wof:placetype":"venue"
},
  "geometry": {"coordinates":[2.1108293533,41.3740768433],"type":"Point"}
}