{
  "type": "Feature",
  "properties": {
    "iso:country":"ES",
    "sg:address":"Cami Jesus, 72",
    "sg:city":"Poligon Industrial De Can Valero",
    "sg:orig_category":"Plomeros",
    "sg:phone":"+34 971 25 30 60",
    "sg:postcode":"07011",
    "sg:province":"Islas Baleares",
    "wof:name":"Auxiliar Aguas Alcantarillado S.a.",
    "wof:placetype":"venue"
},
  "geometry": {"coordinates":[2.8577105999,39.5341796875],"type":"Point"}
}