{
  "type": "Feature",
  "properties": {
    "addr:full":"Calle de Estafeta (de La), 6 Galapagar Madrid 28260",
    "addr:housenumber":"6",
    "addr:postcode":"28260",
    "addr:street":"Calle De Estafeta De La",
    "iso:country":"ES",
    "sg:address":"Calle de Estafeta (de La), 6",
    "sg:city":"Galapagar",
    "sg:orig_category":"Laboratorios Dentales",
    "sg:phone":"+34 918 58 08 38",
    "sg:postcode":"28260",
    "sg:province":"Madrid",
    "wof:name":"Laboratorios Metadent S.l.",
    "wof:placetype":"venue"
},
  "geometry": {"coordinates":[-4.0023641586,40.5767822266],"type":"Point"}
}