{
  "type": "Feature",
  "properties": {
    "iso:country":"ES",
    "sg:address":"Avda Oviedo, S/n",
    "sg:city":"Nore\u00f1a",
    "sg:orig_category":"Carros Elevadores, Carros De Operaciones Portuarias",
    "sg:phone":"+34 985 74 30 37",
    "sg:postcode":"33180",
    "sg:province":"Asturias",
    "wof:name":"Sanfer S.l.",
    "wof:placetype":"venue"
},
  "geometry": {"coordinates":[-5.7020292282,43.4001083374],"type":"Point"}
}