{
  "type": "Feature",
  "properties": {
    "iso:country":"ES",
    "sg:address":"C/ Sant Joan, 22",
    "sg:city":"Ripollet",
    "sg:orig_category":"Estancos",
    "sg:phone":"+34 936 92 14 11",
    "sg:postcode":"08291",
    "sg:province":"Barcelona",
    "wof:name":"Bayo Bayo Jose",
    "wof:placetype":"venue"
},
  "geometry": {"coordinates":[2.1584320068,41.496307373],"type":"Point"}
}