{
  "type": "Feature",
  "properties": {
    "iso:country":"ES",
    "sg:address":"Avda Principe Felipe (del), 22",
    "sg:city":"Rincon Soto",
    "sg:orig_category":"Molduras, Junquillos, Listones Y Molduras Perforadas",
    "sg:phone":"+34 941 14 16 04",
    "sg:postcode":"26550",
    "sg:province":"La Rioja",
    "wof:name":"Lazaro Martinez Carlos",
    "wof:placetype":"venue"
},
  "geometry": {"coordinates":[-1.8515169621,42.2347755432],"type":"Point"}
}