{
  "type": "Feature",
  "properties": {
    "iso:country":"ES",
    "sg:address":"Avda Cubells, D'es, S/n",
    "sg:city":"Sant Josep De Sa Talaia",
    "sg:orig_category":"Plomeros",
    "sg:phone":"+34 971 80 05 07",
    "sg:postcode":"07830",
    "sg:province":"Islas Baleares",
    "wof:name":"Instalaciones Hans Fink S.l.",
    "wof:placetype":"venue"
},
  "geometry": {"coordinates":[1.2400699854,38.8931312561],"type":"Point"}
}