{
  "type": "Feature",
  "properties": {
    "addr:full":"Calle de Urano, 3 Alcorcon Madrid 28925",
    "addr:housenumber":"3",
    "addr:postcode":"28925",
    "addr:street":"Calle De Urano",
    "iso:country":"ES",
    "sg:address":"Calle de Urano, 3",
    "sg:city":"Alcorcon",
    "sg:orig_category":"Suministros Y Materiales Industriales",
    "sg:phone":"+34 916 19 97 51",
    "sg:postcode":"28925",
    "sg:province":"Madrid",
    "wof:name":"Dominguez Fernandez Ana Maria",
    "wof:placetype":"venue"
},
  "geometry": {"coordinates":[-3.8099989891,40.3539390564],"type":"Point"}
}