{
  "type": "Feature",
  "properties": {
    "addr:full":"Praz Paz Novoa, 3 Ourense Ourense 32003",
    "addr:housenumber":"3",
    "addr:postcode":"32003",
    "addr:street":"Praz Paz Novoa",
    "iso:country":"ES",
    "sg:address":"Praz Paz Novoa, 3",
    "sg:city":"Ourense",
    "sg:orig_category":"Institutos De Belleza",
    "sg:phone":"+34 988 37 38 52",
    "sg:postcode":"32003",
    "sg:province":"Ourense",
    "wof:name":"Losada Mojon Maria Teresa",
    "wof:placetype":"venue"
},
  "geometry": {"coordinates":[-7.8654999733,42.3403739929],"type":"Point"}
}