{
  "type": "Feature",
  "properties": {
    "addr:full":"Avda Poeta Mariano Tomas, 43 Hellin Albacete 02400",
    "addr:housenumber":"43",
    "addr:postcode":"02400",
    "addr:street":"Avda Poeta Mariano Tomas",
    "iso:country":"ES",
    "sg:address":"Avda Poeta Mariano Tomas, 43",
    "sg:city":"Hellin",
    "sg:orig_category":"Agentes, Concesionarios Y Sucursales De Veh\u00cdculos",
    "sg:phone":"+34 967 30 56 46",
    "sg:postcode":"02400",
    "sg:province":"Albacete",
    "wof:name":"Automoviles Alce S. A.",
    "wof:placetype":"venue"
},
  "geometry": {"coordinates":[-1.6958039999,38.5107154846],"type":"Point"}
}