{
  "type": "Feature",
  "properties": {
    "addr:full":"Av Ave Maria, 15 Escala Girona 17130",
    "addr:housenumber":"15",
    "addr:postcode":"17130",
    "addr:street":"Av Ave Maria",
    "iso:country":"ES",
    "sg:address":"Av Ave Maria, 15",
    "sg:city":"Escala",
    "sg:orig_category":"Inmobiliaria (agencias)",
    "sg:phone":"+34 972 77 60 72",
    "sg:postcode":"17130",
    "sg:province":"Girona",
    "wof:name":"Promontmar L'escala S.l.",
    "wof:placetype":"venue"
},
  "geometry": {"coordinates":[3.1348669529,42.1236000061],"type":"Point"}
}