{
  "type": "Feature",
  "properties": {
    "iso:country":"ES",
    "sg:address":"Carrer de Miquel Pellisa, 4",
    "sg:city":"Maravillas",
    "sg:orig_category":"Caf\u00c9s, Bares, Cervecer\u00cdas",
    "sg:phone":"+34 971 26 40 27",
    "sg:postcode":"07610",
    "sg:province":"Islas Baleares",
    "wof:name":"Grupo Ferrer Gestion S.l.",
    "wof:placetype":"venue"
},
  "geometry": {"coordinates":[2.7243249416,39.5336914062],"type":"Point"}
}