{
  "type": "Feature",
  "properties": {
    "addr:full":"Calle de Jerez, 7 Zubia Granada 18140",
    "addr:housenumber":"7",
    "addr:postcode":"18140",
    "addr:street":"Calle De Jerez",
    "iso:country":"ES",
    "sg:address":"Calle de Jerez, 7",
    "sg:city":"Zubia",
    "sg:orig_category":"Reposter\u00cdas",
    "sg:phone":"+34 958 59 09 47",
    "sg:postcode":"18140",
    "sg:province":"Granada",
    "wof:name":"Sanchez Sanchez Encarnacion",
    "wof:placetype":"venue"
},
  "geometry": {"coordinates":[-3.5825910568,37.1143875122],"type":"Point"}
}