{
  "type": "Feature",
  "properties": {
    "iso:country":"ES",
    "sg:address":"Avda Miraflores, 76",
    "sg:city":"Sevilla",
    "sg:orig_category":"Peluqueros: De Se\u00d1oras",
    "sg:phone":"+34 954 43 34 60",
    "sg:postcode":"41008",
    "sg:province":"Sevilla",
    "wof:name":"Algarra Rubio Elisa",
    "wof:placetype":"venue"
},
  "geometry": {"coordinates":[-5.9782767296,37.4019927979],"type":"Point"}
}