{
  "type": "Feature",
  "properties": {
    "iso:country":"ES",
    "sg:address":"Carrer de Princesa, 50",
    "sg:city":"Barcelona",
    "sg:orig_category":"Suministros Para Hoteles",
    "sg:phone":"+34 932 00 25 88",
    "sg:postcode":"08003",
    "sg:province":"Barcelona",
    "wof:name":"Chic And Basic Gestion S.a.",
    "wof:placetype":"venue"
},
  "geometry": {"coordinates":[2.1824760437,41.3867607117],"type":"Point"}
}