{
  "type": "Feature",
  "properties": {
    "iso:country":"ES",
    "sg:address":"Calle de Santa Felicitas, 3",
    "sg:city":"Alacant",
    "sg:orig_category":"Diarios, Prensa, Revistas (al Por Menor)",
    "sg:phone":"+34 965 92 17 44",
    "sg:postcode":"03005",
    "sg:province":"Alicante",
    "wof:name":"Ferrandiz Belmonte Maria Concepcion",
    "wof:placetype":"venue"
},
  "geometry": {"coordinates":[-0.4948059916,38.3483963013],"type":"Point"}
}