{
  "type": "Feature",
  "properties": {
    "addr:full":"Calle de Sierra Gador, 56 Madrid Madrid 28031",
    "addr:housenumber":"56",
    "addr:postcode":"madrid;28031",
    "addr:street":"Calle De Sierra Gador",
    "iso:country":"ES",
    "sg:address":"Calle de Sierra Gador, 56",
    "sg:city":"Madrid",
    "sg:orig_category":"Agencias De Viajes",
    "sg:phone":"+34 913 32 33 15",
    "sg:postcode":"28031",
    "sg:province":"Madrid",
    "wof:name":"Centro De Viajes Zona Este S.l.",
    "wof:placetype":"venue"
},
  "geometry": {"coordinates":[-3.6177670956,40.3806686401],"type":"Point"}
}