{
  "type": "Feature",
  "properties": {
    "iso:country":"ES",
    "sg:address":"Calle de Leon Y Castillo, 1",
    "sg:city":"Villa De Moya",
    "sg:orig_category":"Sociedades, Compa\u00d1\u00cdas Aseguradoras",
    "sg:phone":"+34 928 61 02 45",
    "sg:postcode":"35420",
    "sg:province":"Las Palmas",
    "wof:name":"Mapfre Guanarteme Compa\u00d1ia De Seguros Y Reaseguros De Canarias S.a.",
    "wof:placetype":"venue"
},
  "geometry": {"coordinates":[-15.5828466415,28.1100292206],"type":"Point"}
}