{
  "type": "Feature",
  "properties": {
    "addr:full":"Carrer de Guineueta, 26 Barcelona Barcelona 08042",
    "addr:housenumber":"26",
    "addr:postcode":"08042",
    "addr:street":"Carrer De Guineueta",
    "iso:country":"ES",
    "sg:address":"Carrer de Guineueta, 26",
    "sg:city":"Barcelona",
    "sg:orig_category":"Delegados, Agentes De Tr\u00c1nsito, Auxiliares De Transporte Internacional",
    "sg:phone":"+34 934 27 91 20",
    "sg:postcode":"08042",
    "sg:province":"Barcelona",
    "wof:name":"Alvarez  Juan Alfibiares",
    "wof:placetype":"venue"
},
  "geometry": {"coordinates":[2.1667981148,41.4404029846],"type":"Point"}
}