{
  "type": "Feature",
  "properties": {
    "iso:country":"ES",
    "sg:address":"Praz Rodrigas (das), 29",
    "sg:city":"Rodrigas",
    "sg:orig_category":"Iglesia Cat\u00d3lica",
    "sg:phone":"+34 982 34 61 20",
    "sg:postcode":"27744",
    "sg:province":"Lugo",
    "wof:name":"Parroquia San Pedro De Riotorto",
    "wof:placetype":"venue"
},
  "geometry": {"coordinates":[-7.2607097626,43.3403701782],"type":"Point"}
}