{
  "type": "Feature",
  "properties": {
    "iso:country":"ES",
    "sg:address":"Calle de Alonso De Burgos, 5",
    "sg:city":"Cordoba",
    "sg:orig_category":"Electrodom\u00c9sticos (al Por Menor)",
    "sg:phone":"+34 957 47 53 39",
    "sg:postcode":"14008",
    "sg:province":"C\u00f3rdoba",
    "wof:name":"Fernandez Vazquez Manuel",
    "wof:placetype":"venue"
},
  "geometry": {"coordinates":[-4.7841272354,37.8865852356],"type":"Point"}
}