{
  "type": "Feature",
  "properties": {
    "addr:full":"Calle de Algeciras, S/n Cadiz C\u00e1diz 11011",
    "addr:housenumber":"s / n",
    "addr:postcode":"11011",
    "addr:street":"Calle De Algeciras",
    "iso:country":"ES",
    "sg:address":"Calle de Algeciras, S/n",
    "sg:city":"Cadiz",
    "sg:orig_category":"Aguas (distribuci\u00d3n, Servicios)",
    "sg:phone":"+34 956 26 30 21",
    "sg:postcode":"11011",
    "sg:province":"C\u00e1diz",
    "wof:name":"Aguas De Cadiz",
    "wof:placetype":"venue"
},
  "geometry": {"coordinates":[-6.2664961815,36.4964408875],"type":"Point"}
}