{
  "type": "Feature",
  "properties": {
    "iso:country":"ES",
    "sg:address":"Calle de Antonio Machado, 23",
    "sg:city":"Dos Hermanas",
    "sg:orig_category":"Pescader\u00cdas (al Por Menor)",
    "sg:phone":"+34 955 66 00 94",
    "sg:postcode":"41700",
    "sg:province":"Sevilla",
    "wof:name":"Fuello Suria Jose Francisco",
    "wof:placetype":"venue"
},
  "geometry": {"coordinates":[-5.9301319122,37.296421051],"type":"Point"}
}