{
  "type": "Feature",
  "properties": {
    "iso:country":"ES",
    "sg:address":"Plaz Iglesia (de La), 3",
    "sg:city":"Pozo-estrecho",
    "sg:orig_category":"Papel, Reciclaje",
    "sg:phone":"+34 968 55 62 25",
    "sg:postcode":"30594",
    "sg:province":"Murcia",
    "wof:name":"Hermanos Ingles-vidal S.l.",
    "wof:placetype":"venue"
},
  "geometry": {"coordinates":[-0.9930009842,37.7116966248],"type":"Point"}
}