{
  "type": "Feature",
  "properties": {
    "iso:country":"ES",
    "sg:address":"Carrer de Bartomeu Amat, 9",
    "sg:city":"Terrassa",
    "sg:orig_category":"Inform\u00c1tica (estudios, Servicios, Asesor\u00cda, Formaci\u00d3n)",
    "sg:phone":"+34 937 35 94 86",
    "sg:postcode":"08225",
    "sg:province":"Barcelona",
    "wof:name":"Funciones De Recursos Informaticos S.l.",
    "wof:placetype":"venue"
},
  "geometry": {"coordinates":[2.012114048,41.5704879761],"type":"Point"}
}