{
  "type": "Feature",
  "properties": {
    "iso:country":"ES",
    "sg:address":"Carr Juli Cesar, 10",
    "sg:city":"Lleida",
    "sg:orig_category":"Imprenta",
    "sg:phone":"+34 973 27 53 66",
    "sg:postcode":"25003",
    "sg:province":"Lleida",
    "wof:name":"Jorge Mayor Saura S.l.",
    "wof:placetype":"venue"
},
  "geometry": {"coordinates":[0.6151390076,41.6127357483],"type":"Point"}
}