{
  "type": "Feature",
  "properties": {
    "iso:country":"ES",
    "sg:address":"Ctra Vic, 217",
    "sg:city":"Manresa",
    "sg:orig_category":"Material Y Herramientas Agr\u00cdcolas",
    "sg:phone":"+34 938 73 03 36",
    "sg:postcode":"08243",
    "sg:province":"Barcelona",
    "wof:name":"Torras Cdad",
    "wof:placetype":"venue"
},
  "geometry": {"coordinates":[1.8392590284,41.7336616516],"type":"Point"}
}