{
  "type": "Feature",
  "properties": {
    "addr:full":"Pg Paisos Catalans, 58 Salt Girona 17190",
    "addr:housenumber":"58",
    "addr:postcode":"17190",
    "addr:street":"Pg Paisos Catalans",
    "iso:country":"ES",
    "sg:address":"Pg Paisos Catalans, 58",
    "sg:city":"Salt",
    "sg:orig_category":"Audiovisuales: Material Y Accesorios (al Por Menor)",
    "sg:phone":"+34 972 40 20 35",
    "sg:postcode":"17190",
    "sg:province":"Girona",
    "wof:name":"Tecnics S.l.",
    "wof:placetype":"venue"
},
  "geometry": {"coordinates":[2.7894220352,41.9720916748],"type":"Point"}
}