{
  "type": "Feature",
  "properties": {
    "iso:country":"ES",
    "sg:address":"Carrer de Torello, 17",
    "sg:city":"Vic",
    "sg:orig_category":"Ingenier\u00cda, Centros De Estudios (diversos)",
    "sg:phone":"+34 938 89 14 94",
    "sg:postcode":"08500",
    "sg:province":"Barcelona",
    "wof:name":"Tavic S.l.",
    "wof:placetype":"venue"
},
  "geometry": {"coordinates":[2.2654249668,41.9298286438],"type":"Point"}
}