{
  "type": "Feature",
  "properties": {
    "iso:country":"ES",
    "sg:address":"Calle de Esquimo, 28",
    "sg:city":"Mairena Alcor",
    "sg:orig_category":"Arquitectos",
    "sg:phone":"+34 955 74 56 67",
    "sg:postcode":"41510",
    "sg:province":"Sevilla",
    "wof:name":"Jimenez Jimenez Jose Manuel",
    "wof:placetype":"venue"
},
  "geometry": {"coordinates":[-5.7476949692,37.3759613037],"type":"Point"}
}