{
  "type": "Feature",
  "properties": {
    "iso:country":"ES",
    "sg:address":"Calle de Peso (el), 27",
    "sg:city":"Lucena",
    "sg:orig_category":"Ingenier\u00cda, Centros De Estudios (industria)",
    "sg:phone":"+34 957 51 51 99",
    "sg:postcode":"14900",
    "sg:province":"C\u00f3rdoba",
    "wof:name":"Procorsan Cb",
    "wof:placetype":"venue"
},
  "geometry": {"coordinates":[-4.4878511429,37.4089736938],"type":"Point"}
}