{
  "type": "Feature",
  "properties": {
    "iso:country":"ES",
    "sg:address":"Avgd Cami Nou, 45",
    "sg:city":"Benetusser",
    "sg:orig_category":"Bancos",
    "sg:phone":"+34 963 96 30 83",
    "sg:postcode":"46910",
    "sg:province":"Valencia",
    "wof:name":"Banco Espa\u00d1ol De Credito S A",
    "wof:placetype":"venue"
},
  "geometry": {"coordinates":[-0.3950789869,39.4239654541],"type":"Point"}
}