{
  "type": "Feature",
  "properties": {
    "iso:country":"ES",
    "sg:address":"Urb Nueva Estebbuna, S/n",
    "sg:city":"Estepona",
    "sg:orig_category":"Equipo De Refrigeraci\u00d3n Industrial",
    "sg:phone":"+34 952 80 89 89",
    "sg:postcode":"29680",
    "sg:province":"M\u00e1laga",
    "sg:website":"www.campoglass.com",
    "wof:name":"Campoglass S.l.",
    "wof:placetype":"venue"
},
  "geometry": {"coordinates":[-5.1591339111,36.4292182922],"type":"Point"}
}