{
  "type": "Feature",
  "properties": {
    "addr:full":"Calle de Greco (el), 14 Arrecife Las Palmas 35500",
    "addr:housenumber":"14",
    "addr:postcode":"35500",
    "addr:street":"Calle De Greco El",
    "iso:country":"ES",
    "sg:address":"Calle de Greco (el), 14",
    "sg:city":"Arrecife",
    "sg:orig_category":"Ropa Para Se\u00d1oras Y Caballeros (al Por Menor)",
    "sg:phone":"+34 928 80 69 12",
    "sg:postcode":"35500",
    "sg:province":"Las Palmas",
    "wof:name":"Braathen  Christian",
    "wof:placetype":"venue"
},
  "geometry": {"coordinates":[-13.5570850372,28.9588375092],"type":"Point"}
}