{
  "type": "Feature",
  "properties": {
    "addr:full":"Carrer de Pablo Iglesias, 33 Terrassa Barcelona 08224",
    "addr:housenumber":"33",
    "addr:postcode":"08224",
    "addr:street":"Carrer De Pablo Iglesias",
    "iso:country":"ES",
    "sg:address":"Carrer de Pablo Iglesias, 33",
    "sg:city":"Terrassa",
    "sg:orig_category":"Almacenes Frigor\u00cdficos",
    "sg:phone":"+34 937 89 90 30",
    "sg:postcode":"08224",
    "sg:province":"Barcelona",
    "wof:name":"Instalaciones Fred Y Refrigeracion Industrial Y Cial.l.l.",
    "wof:placetype":"venue"
},
  "geometry": {"coordinates":[1.9897869825,41.5575408936],"type":"Point"}
}