{
  "type": "Feature",
  "properties": {
    "iso:country":"ES",
    "sg:address":"Carrer de Numero 5 Zona Franca, S/n",
    "sg:city":"Barcelona",
    "sg:orig_category":"Delegados, Agentes De Tr\u00c1nsito, Auxiliares De Transporte Internacional",
    "sg:phone":"+34 932 64 03 81",
    "sg:postcode":"08040",
    "sg:province":"Barcelona",
    "wof:name":"Intercoex S.a.",
    "wof:placetype":"venue"
},
  "geometry": {"coordinates":[2.131469965,41.3239212036],"type":"Point"}
}