{
  "type": "Feature",
  "properties": {
    "iso:country":"ES",
    "sg:address":"Carr Isaac Peral, 52",
    "sg:city":"Port D'andratx",
    "sg:orig_category":"Ebanister\u00cda",
    "sg:phone":"+34 971 67 32 60",
    "sg:postcode":"07157",
    "sg:province":"Islas Baleares",
    "wof:name":"Vincent Welch Mark Robert",
    "wof:placetype":"venue"
},
  "geometry": {"coordinates":[2.388258934,39.5433082581],"type":"Point"}
}