{
  "type": "Feature",
  "properties": {
    "addr:full":"Calle de Chimidas, 20 Playa Honda Las Palmas 35509",
    "addr:housenumber":"20",
    "addr:postcode":"35509",
    "addr:street":"Calle De Chimidas",
    "iso:country":"ES",
    "sg:address":"Calle de Chimidas, 20",
    "sg:city":"Playa Honda",
    "sg:orig_category":"Ropa Para Ni\u00d1os (al Por Menor)",
    "sg:phone":"+34 928 82 15 17",
    "sg:postcode":"35509",
    "sg:province":"Las Palmas",
    "sg:website":"www.e-stradivarius.com",
    "wof:name":"Depositos Y Almacenes Numero 1 S.a.",
    "wof:placetype":"venue"
},
  "geometry": {"coordinates":[-13.5917158127,28.9558792114],"type":"Point"}
}