{
  "type": "Feature",
  "properties": {
    "iso:country":"ES",
    "sg:address":"Carrer de Reina Victoria, 27",
    "sg:city":"Barcelona",
    "sg:orig_category":"Agencias Y Asesores De Publicidad",
    "sg:phone":"+34 932 01 61 53",
    "sg:postcode":"08021",
    "sg:province":"Barcelona",
    "wof:name":"Durany Mansilla Isabel",
    "wof:placetype":"venue"
},
  "geometry": {"coordinates":[2.1370820999,41.3968467712],"type":"Point"}
}