{
  "type": "Feature",
  "properties": {
    "addr:full":"Calle de San Isidro, 1 Aceuchal Badajoz 06207",
    "addr:housenumber":"1",
    "addr:postcode":"06207",
    "addr:street":"Calle De San Isidro",
    "iso:country":"ES",
    "sg:address":"Calle de San Isidro, 1",
    "sg:city":"Aceuchal",
    "sg:orig_category":"Empresas De Pintura Y Revestimientos",
    "sg:phone":"+34 924 68 07 80",
    "sg:postcode":"06207",
    "sg:province":"Badajoz",
    "wof:name":"Robles De La Cruz Diego",
    "wof:placetype":"venue"
},
  "geometry": {"coordinates":[-6.4896039963,38.6473922729],"type":"Point"}
}