{
  "type": "Feature",
  "properties": {
    "addr:full":"Carrer de Jacint Verdaguer, 22 Martorell Barcelona 08760",
    "addr:housenumber":"22",
    "addr:postcode":"08760",
    "addr:street":"Carrer De Jacint Verdaguer",
    "iso:country":"ES",
    "sg:address":"Carrer de Jacint Verdaguer, 22",
    "sg:city":"Martorell",
    "sg:classifiers":[
        {
            "category":"Casinos & Gambling",
            "type":"Entertainment"
        }
    ],
    "sg:phone":"+34 937 76 57 45",
    "sg:postcode":"08760",
    "sg:province":"Barcelona",
    "sg:tags":[
        "locale",
        "de",
        "juego"
    ],
    "wof:name":"Pareja De Los Santos Amaia",
    "wof:placetype":"venue"
},
  "geometry": {"coordinates":[1.914585948,41.4760398865],"type":"Point"}
}