{
  "type": "Feature",
  "properties": {
    "addr:full":"Carrer de Acacies, 45 Barcelona Barcelona 08027",
    "addr:housenumber":"45",
    "addr:postcode":"08027",
    "addr:street":"Carrer De Acacies",
    "iso:country":"ES",
    "sg:address":"Carrer de Acacies, 45",
    "sg:city":"Barcelona",
    "sg:orig_category":"Psic\u00d3logos",
    "sg:phone":"+34 934 08 47 53",
    "sg:postcode":"08027",
    "sg:province":"Barcelona",
    "wof:name":"Dinna S.c.c.l.",
    "wof:placetype":"venue"
},
  "geometry": {"coordinates":[2.1780641079,41.4254112244],"type":"Point"}
}