{
  "type": "Feature",
  "properties": {
    "iso:country":"ES",
    "sg:address":"Calle de Marques De Comillas, 7",
    "sg:city":"Almeria",
    "sg:orig_category":"Complementos De Vestir (al Por Menor)",
    "sg:phone":"+34 950 25 64 31",
    "sg:postcode":"04004",
    "sg:province":"Almer\u00eda",
    "wof:name":"Mir Martinez Lidia",
    "wof:placetype":"venue"
},
  "geometry": {"coordinates":[-2.4623260498,36.8373069763],"type":"Point"}
}