{
  "type": "Feature",
  "properties": {
    "iso:country":"ES",
    "sg:address":"Carrer de Montserrat, 41",
    "sg:city":"Vic",
    "sg:orig_category":"Distribuci\u00d3n De Petr\u00d3leo Y Derivados",
    "sg:phone":"+34 938 86 13 08",
    "sg:postcode":"08500",
    "sg:province":"Barcelona",
    "wof:name":"Planella Morato Mateo",
    "wof:placetype":"venue"
},
  "geometry": {"coordinates":[2.2649309635,41.9277954102],"type":"Point"}
}