{
  "type": "Feature",
  "properties": {
    "iso:country":"ES",
    "sg:address":"Rua Alhondiga (da), 5",
    "sg:city":"Pontevedra",
    "sg:orig_category":"Muebles, Minoristas",
    "sg:phone":"+34 986 85 24 18",
    "sg:postcode":"36002",
    "sg:province":"Pontevedra",
    "wof:name":"Miron Estevez Benito",
    "wof:placetype":"venue"
},
  "geometry": {"coordinates":[-8.6463441849,42.4322547913],"type":"Point"}
}