{
  "type": "Feature",
  "properties": {
    "addr:full":"Ctra Soller(p I Son Rosinyol), Km. 0004,0 Palma Islas Baleares 07120",
    "addr:postcode":"07120",
    "addr:street":"Ctra Soller P I Son Rosinyol Km. 0004,0",
    "iso:country":"ES",
    "sg:address":"Ctra Soller(p I Son Rosinyol), Km. 0004,0",
    "sg:city":"Palma",
    "sg:orig_category":"Empresarios",
    "sg:phone":"+34 971 76 06 46",
    "sg:postcode":"07120",
    "sg:province":"Islas Baleares",
    "wof:name":"Fundacio Illes Balears",
    "wof:placetype":"venue"
},
  "geometry": {"coordinates":[2.6557290554,39.6079864502],"type":"Point"}
}