{
  "type": "Feature",
  "properties": {
    "addr:full":"Avda Playas (las), 4 Puerto Del Carmen Las Palmas 35510",
    "addr:housenumber":"4",
    "addr:postcode":"35510",
    "addr:street":"Avda Playas Las",
    "iso:country":"ES",
    "sg:address":"Avda Playas (las), 4",
    "sg:city":"Puerto Del Carmen",
    "sg:orig_category":"Heladeros",
    "sg:phone":"+34 928 51 05 44",
    "sg:postcode":"35510",
    "sg:province":"Las Palmas",
    "wof:name":"Suarez Betancor Cristobal",
    "wof:placetype":"venue"
},
  "geometry": {"coordinates":[-13.6662149429,28.9237804413],"type":"Point"}
}