{
  "type": "Feature",
  "properties": {
    "addr:full":"Plaz Marques, 10 Ubeda Ja\u00e9n 23400",
    "addr:housenumber":"10",
    "addr:postcode":"23400",
    "addr:street":"Marques;Jae\u0301N",
    "iso:country":"ES",
    "sg:address":"Plaz Marques, 10",
    "sg:city":"Ubeda",
    "sg:orig_category":"Droguer\u00cdas (al Por Menor)",
    "sg:phone":"+34 953 75 08 11",
    "sg:postcode":"23400",
    "sg:province":"Ja\u00e9n",
    "wof:name":"Chamorro Pulido Joaquin",
    "wof:placetype":"venue"
},
  "geometry": {"coordinates":[-3.3693890572,38.008140564],"type":"Point"}
}