{
  "type": "Feature",
  "properties": {
    "iso:country":"ES",
    "sg:address":"Calle de Itsasbide Kalea, 11",
    "sg:city":"Elexalde Auzoa",
    "sg:orig_category":"Partidos Pol\u00cdticos",
    "sg:phone":"+34 946 77 25 09",
    "sg:postcode":"48630",
    "sg:province":"Vizcaya",
    "wof:name":"Partido Nacionalista Vasco De Gorliz",
    "wof:placetype":"venue"
},
  "geometry": {"coordinates":[-2.9338502884,43.4144515991],"type":"Point"}
}