{
  "type": "Feature",
  "properties": {
    "addr:full":"C/ Doctor Piguillem, 6 Puigcerda Girona 17520",
    "addr:housenumber":"6",
    "addr:postcode":"17520",
    "addr:street":"C / Doctor Piguillem",
    "iso:country":"ES",
    "sg:address":"C/ Doctor Piguillem, 6",
    "sg:city":"Puigcerda",
    "sg:orig_category":"Inform\u00c1tica (estudios, Servicios, Asesor\u00cda, Formaci\u00d3n)",
    "sg:phone":"+34 972 14 01 00",
    "sg:postcode":"17520",
    "sg:province":"Girona",
    "wof:name":"Inology Cerdanya S.l.",
    "wof:placetype":"venue"
},
  "geometry": {"coordinates":[1.9270299673,42.4343223572],"type":"Point"}
}