{
  "type": "Feature",
  "properties": {
    "iso:country":"ES",
    "sg:address":"Calle de Ronda Mijares, 28",
    "sg:city":"Castellon",
    "sg:orig_category":"Peritos En Seguros",
    "sg:phone":"+34 964 25 27 52",
    "sg:postcode":"12001",
    "sg:province":"Castell\u00f3n",
    "wof:name":"Alcecasegur Correduria De Seguros S.l.",
    "wof:placetype":"venue"
},
  "geometry": {"coordinates":[-0.0430349,39.9863090515],"type":"Point"}
}