{
  "type": "Feature",
  "properties": {
    "addr:full":"Plaz San Juan De La Cruz, 30 Umbrete Sevilla 41806",
    "addr:housenumber":"30",
    "addr:postcode":"41806",
    "addr:street":"Plaz San Juan;La Cruz",
    "iso:country":"ES",
    "sg:address":"Plaz San Juan De La Cruz, 30",
    "sg:city":"Umbrete",
    "sg:orig_category":"M\u00c9dicos: Cirug\u00cda Pl\u00c1stica, Reconstructiva Y Est\u00c9tica",
    "sg:phone":"+34 955 71 51 94",
    "sg:postcode":"41806",
    "sg:province":"Sevilla",
    "wof:name":"Estetica Medica Quirurjica Hispalense S.l",
    "wof:placetype":"venue"
},
  "geometry": {"coordinates":[-6.1535339355,37.3670158386],"type":"Point"}
}