{
  "type": "Feature",
  "properties": {
    "iso:country":"ES",
    "sg:address":"Calle de Anega, 17",
    "sg:city":"Manzanares",
    "sg:orig_category":"Asesor\u00cda Fiscal Y Jur\u00cddica",
    "sg:phone":"+34 926 62 08 80",
    "sg:postcode":"13200",
    "sg:province":"Ciudad Real",
    "wof:name":"Asesoria Anega S.l.",
    "wof:placetype":"venue"
},
  "geometry": {"coordinates":[-3.3679993153,38.9979553223],"type":"Point"}
}