{
  "type": "Feature",
  "properties": {
    "iso:country":"ES",
    "sg:address":"Calle de Jesus Y Maria, 28",
    "sg:city":"Madrid",
    "sg:orig_category":"Electricidad, Electr\u00d3nica: Suministros (al Por Menor)",
    "sg:phone":"+34 915 06 06 64",
    "sg:postcode":"28012",
    "sg:province":"Madrid",
    "wof:name":"Alom  Khorshed",
    "wof:placetype":"venue"
},
  "geometry": {"coordinates":[-3.7030029297,40.4106445312],"type":"Point"}
}