{
  "type": "Feature",
  "properties": {
    "addr:full":"Calle de Pedro Garcia Rubio, 39 Puerto Lumbreras Murcia 30890",
    "addr:housenumber":"39",
    "addr:postcode":"30890",
    "addr:street":"Calle De Pedro;Rubio",
    "iso:country":"ES",
    "sg:address":"Calle de Pedro Garcia Rubio, 39",
    "sg:city":"Puerto Lumbreras",
    "sg:orig_category":"Ingeniero",
    "sg:phone":"+34 968 40 31 53",
    "sg:postcode":"30890",
    "sg:province":"Murcia",
    "wof:name":"Ruiz Martinez Bartolome",
    "wof:placetype":"venue"
},
  "geometry": {"coordinates":[-1.8061389923,37.5649414062],"type":"Point"}
}