{
  "type": "Feature",
  "properties": {
    "addr:full":"Avda Campoamor, 30 Salamanca Salamanca 37003",
    "addr:housenumber":"30",
    "addr:postcode":"37003",
    "addr:street":"Avda Campoamor",
    "iso:country":"ES",
    "sg:address":"Avda Campoamor, 30",
    "sg:city":"Salamanca",
    "sg:orig_category":"Ropa Para Se\u00d1oras Y Caballeros (al Por Menor)",
    "sg:phone":"+34 923 23 44 52",
    "sg:postcode":"37003",
    "sg:province":"Salamanca",
    "wof:name":"Gil Jimenez Jantiple",
    "wof:placetype":"venue"
},
  "geometry": {"coordinates":[-5.6549072266,40.9650726318],"type":"Point"}
}