{
  "type": "Feature",
  "properties": {
    "addr:full":"Calle de Estadio, 59 Almeria Almer\u00eda 04007",
    "addr:housenumber":"59",
    "addr:postcode":"04007",
    "addr:street":"Calle De Estadio",
    "iso:country":"ES",
    "sg:address":"Calle de Estadio, 59",
    "sg:city":"Almeria",
    "sg:orig_category":"Producci\u00d3n, Distribuci\u00d3n De Electricidad",
    "sg:phone":"+34 950 26 10 45",
    "sg:postcode":"04007",
    "sg:province":"Almer\u00eda",
    "wof:name":"Mondejar Garcia Ana",
    "wof:placetype":"venue"
},
  "geometry": {"coordinates":[-2.4492490292,36.8296813965],"type":"Point"}
}