{
  "type": "Feature",
  "properties": {
    "addr:full":"Pico, S/n Pico Lugo 27369",
    "addr:housenumber":"s / n",
    "addr:postcode":"27369",
    "addr:street":"Pico",
    "iso:country":"ES",
    "sg:address":"Pico, S/n",
    "sg:city":"Pico",
    "sg:orig_category":"Material Y Herramientas Agr\u00cdcolas",
    "sg:phone":"+34 982 54 33 09",
    "sg:postcode":"27369",
    "sg:province":"Lugo",
    "wof:name":"Lopez Fernandez Concepcion",
    "wof:placetype":"venue"
},
  "geometry": {"coordinates":[-7.4166898727,42.8401069641],"type":"Point"}
}