{
  "type": "Feature",
  "properties": {
    "iso:country":"ES",
    "sg:address":"Calle de Conde De Lemos, 2",
    "sg:city":"Madrid",
    "sg:orig_category":"Plomeros",
    "sg:phone":"+34 915 47 17 24",
    "sg:postcode":"28013",
    "sg:province":"Madrid",
    "wof:name":"Garcia Castro Angel",
    "wof:placetype":"venue"
},
  "geometry": {"coordinates":[-3.7099072933,40.4166679382],"type":"Point"}
}