{
  "type": "Feature",
  "properties": {
    "addr:full":"Carrer de Salvador Barone, 88 Viladecans Barcelona 08840",
    "addr:housenumber":"88",
    "addr:postcode":"08840",
    "addr:street":"Carrer De Salvador Barone",
    "iso:country":"ES",
    "sg:address":"Carrer de Salvador Barone, 88",
    "sg:city":"Viladecans",
    "sg:orig_category":"Empresas De Carpinter\u00cda Met\u00c1lica",
    "sg:phone":"+34 936 59 01 99",
    "sg:postcode":"08840",
    "sg:province":"Barcelona",
    "wof:name":"Aludecans S.l.",
    "wof:placetype":"venue"
},
  "geometry": {"coordinates":[2.009980917,41.3180656433],"type":"Point"}
}