{
  "type": "Feature",
  "properties": {
    "addr:full":"Calle de Marques De Nervion, 10 Sevilla Sevilla 41005",
    "addr:housenumber":"10",
    "addr:postcode":"41005",
    "addr:street":"Calle De Marques De Nervion",
    "iso:country":"ES",
    "sg:address":"Calle de Marques De Nervion, 10",
    "sg:city":"Sevilla",
    "sg:orig_category":"Abogados",
    "sg:phone":"+34 954 58 19 66",
    "sg:postcode":"41005",
    "sg:province":"Sevilla",
    "wof:name":"Fernandez Diaz Juan Isidro",
    "wof:placetype":"venue"
},
  "geometry": {"coordinates":[-5.9680161476,37.3866615295],"type":"Point"}
}