{
  "type": "Feature",
  "properties": {
    "addr:full":"Calle de Angeles Los, 33 Gijon Asturias 33209",
    "addr:housenumber":"33",
    "addr:postcode":"33209",
    "addr:street":"Calle De Angeles Los",
    "iso:country":"ES",
    "sg:address":"Calle de Angeles Los, 33",
    "sg:city":"Gijon",
    "sg:orig_category":"Masajistas Kinesiterapeutas",
    "sg:phone":"+34 985 15 56 08",
    "sg:postcode":"33209",
    "sg:province":"Asturias",
    "wof:name":"Rodriguez Rendueles Marisol",
    "wof:placetype":"venue"
},
  "geometry": {"coordinates":[-5.658821106,43.5323219299],"type":"Point"}
}