{
  "type": "Feature",
  "properties": {
    "iso:country":"ES",
    "sg:address":"Carrer de Coronel Sanfeliu, 41",
    "sg:city":"Prat Llobregat",
    "sg:orig_category":"Inmobiliaria (agencias)",
    "sg:phone":"+34 933 70 18 18",
    "sg:postcode":"08820",
    "sg:province":"Barcelona",
    "wof:name":"Asesoria Inmobiliaria Solpisos S.l.",
    "wof:placetype":"venue"
},
  "geometry": {"coordinates":[2.0952351093,41.3239822388],"type":"Point"}
}