{
  "type": "Feature",
  "properties": {
    "iso:country":"ES",
    "sg:address":"Calle de Estrella (la), 9",
    "sg:city":"Almansa",
    "sg:orig_category":"Organizaciones Internacionales",
    "sg:phone":"+34 967 34 25 58",
    "sg:postcode":"02640",
    "sg:province":"Albacete",
    "wof:name":"Caritas Diocesana",
    "wof:placetype":"venue"
},
  "geometry": {"coordinates":[-1.0945320129,38.8719558716],"type":"Point"}
}