{
  "type": "Feature",
  "properties": {
    "iso:country":"ES",
    "sg:address":"Avda Arcentales, 20",
    "sg:city":"Madrid",
    "sg:orig_category":"Electricidad, Electr\u00d3nica: Suministros (al Por Menor)",
    "sg:phone":"+34 917 60 06 64",
    "sg:postcode":"28022",
    "sg:province":"Madrid",
    "wof:name":"Orfila Mata Jose Luis",
    "wof:placetype":"venue"
},
  "geometry": {"coordinates":[-3.6101660728,40.4346466064],"type":"Point"}
}