{
  "type": "Feature",
  "properties": {
    "iso:country":"ES",
    "sg:address":"G.v. Marques Del Turia, 14",
    "sg:city":"Valencia",
    "sg:orig_category":"Ropa Para Se\u00d1oras (al Por Menor)",
    "sg:phone":"+34 963 74 02 59",
    "sg:postcode":"46005",
    "sg:province":"Valencia",
    "wof:name":"Carpe Diem Cb",
    "wof:placetype":"venue"
},
  "geometry": {"coordinates":[-0.371457994,39.4655838013],"type":"Point"}
}