{
  "type": "Feature",
  "properties": {
    "addr:full":"Calle de Alvarez Garaya, 6 Gijon Asturias 33206",
    "addr:housenumber":"6",
    "addr:postcode":"33206",
    "addr:street":"Calle De Alvarez Garaya",
    "iso:country":"ES",
    "sg:address":"Calle de Alvarez Garaya, 6",
    "sg:city":"Gijon",
    "sg:orig_category":"Abogados",
    "sg:phone":"+34 985 35 20 16",
    "sg:postcode":"33206",
    "sg:province":"Asturias",
    "wof:name":"Morilla Mu\u00f1iz Joaquin",
    "wof:placetype":"venue"
},
  "geometry": {"coordinates":[-5.6652460098,43.5416145325],"type":"Point"}
}