{
  "type": "Feature",
  "properties": {
    "iso:country":"ES",
    "sg:address":"Calle de Plateria, 5",
    "sg:city":"Mucientes",
    "sg:orig_category":"Ingeniero",
    "sg:phone":"+34 983 58 78 23",
    "sg:postcode":"47194",
    "sg:province":"Valladolid",
    "wof:name":"Burgos Gil Carlos",
    "wof:placetype":"venue"
},
  "geometry": {"coordinates":[-4.7623319626,41.7424430847],"type":"Point"}
}