{
  "type": "Feature",
  "properties": {
    "iso:country":"ES",
    "sg:address":"Calle de Lujan Perez, S/n",
    "sg:city":"Tablero",
    "sg:orig_category":"Centros De Educaci\u00d3n Especial",
    "sg:phone":"+34 928 14 17 13",
    "sg:postcode":"35100",
    "sg:province":"Las Palmas",
    "sg:website":"www.educacanarias.org",
    "wof:name":"Colegio Publico Pepe Monagas-gobierno De Canarias",
    "wof:placetype":"venue"
},
  "geometry": {"coordinates":[-15.6032943726,27.7694454193],"type":"Point"}
}