{
  "type": "Feature",
  "properties": {
    "addr:full":"Calle de Sierpes, 8 Sevilla Sevilla 41004",
    "addr:housenumber":"8",
    "addr:postcode":"41004",
    "addr:street":"Calle De Sierpes",
    "iso:country":"ES",
    "sg:address":"Calle de Sierpes, 8",
    "sg:city":"Sevilla",
    "sg:orig_category":"Droguer\u00cdas (al Por Menor)",
    "sg:phone":"+34 954 50 15 49",
    "sg:postcode":"41004",
    "sg:province":"Sevilla",
    "sg:website":"www.bodybell.com",
    "wof:name":"Iberica De Drogueria Y Perfumeria S.a.",
    "wof:placetype":"venue"
},
  "geometry": {"coordinates":[-5.9949498177,37.3922538757],"type":"Point"}
}