{
  "type": "Feature",
  "properties": {
    "addr:full":"Carrer de Copernic, 9 Barcelona Barcelona 08021",
    "addr:housenumber":"9",
    "addr:postcode":"08021",
    "addr:street":"Carrer De Copernic",
    "iso:country":"ES",
    "sg:address":"Carrer de Copernic, 9",
    "sg:city":"Barcelona",
    "sg:orig_category":"Arquitectos",
    "sg:phone":"+34 932 00 99 29",
    "sg:postcode":"08021",
    "sg:province":"Barcelona",
    "wof:name":"De La Guardia Conte Francisco",
    "wof:placetype":"venue"
},
  "geometry": {"coordinates":[2.1362988949,41.400138855],"type":"Point"}
}