{
  "type": "Feature",
  "properties": {
    "addr:full":"Poligono Segarra, 20 Vall Uixo Castell\u00f3n 12600",
    "addr:housenumber":"20",
    "addr:postcode":"12600",
    "addr:street":"Poligono Segarra;Castello\u0301N",
    "iso:country":"ES",
    "sg:address":"Poligono Segarra, 20",
    "sg:city":"Vall Uixo",
    "sg:orig_category":"Zapatos: Material, Suministros, Accesorios (fabricaci\u00d3n, Al Por Mayor)",
    "sg:phone":"+34 964 69 11 13",
    "sg:postcode":"12600",
    "sg:province":"Castell\u00f3n",
    "wof:name":"Jose Monzonis S.a.",
    "wof:placetype":"venue"
},
  "geometry": {"coordinates":[-0.2323790044,39.8148918152],"type":"Point"}
}