{
  "type": "Feature",
  "properties": {
    "addr:full":"Calle de Arturo Campion, 16 Ansoain Navarra 31013",
    "addr:housenumber":"16",
    "addr:postcode":"31013",
    "addr:street":"Calle De Arturo Campion",
    "iso:country":"ES",
    "sg:address":"Calle de Arturo Campion, 16",
    "sg:city":"Ansoain",
    "sg:orig_category":"Pescader\u00cdas (al Por Menor)",
    "sg:phone":"+34 948 14 63 74",
    "sg:postcode":"31013",
    "sg:province":"Navarra",
    "wof:name":"Echeverria Balda Martin Jose",
    "wof:placetype":"venue"
},
  "geometry": {"coordinates":[-1.6376318932,42.8326530457],"type":"Point"}
}