{
  "type": "Feature",
  "properties": {
    "addr:full":"Avda Calvo Sotelo, 3 Beniel Murcia 30130",
    "addr:housenumber":"3",
    "addr:postcode":"30130",
    "addr:street":"Avda Calvo Sotelo",
    "iso:country":"ES",
    "sg:address":"Avda Calvo Sotelo, 3",
    "sg:city":"Beniel",
    "sg:orig_category":"Abogados",
    "sg:phone":"+34 968 60 09 09",
    "sg:postcode":"30130",
    "sg:province":"Murcia",
    "wof:name":"Garcia Navarro Roberto",
    "wof:placetype":"venue"
},
  "geometry": {"coordinates":[-1.0018650293,38.0456504822],"type":"Point"}
}