{
  "type": "Feature",
  "properties": {
    "iso:country":"ES",
    "sg:address":"Calle de Mieses, 2",
    "sg:city":"Majadahonda",
    "sg:orig_category":"Inform\u00c1tica (estudios, Servicios, Asesor\u00cda, Formaci\u00d3n)",
    "sg:phone":"+34 916 38 04 15",
    "sg:postcode":"28220",
    "sg:province":"Madrid",
    "sg:website":"www.domiciliosocial.com",
    "wof:name":"Abba.servicios Auxiliares.s.l.l.",
    "wof:placetype":"venue"
},
  "geometry": {"coordinates":[-3.872636,40.473621],"type":"Point"}
}