{
  "type": "Feature",
  "properties": {
    "addr:full":"Av. Serapio Huici, 19 Atarrabia Navarra 31610",
    "addr:housenumber":"19",
    "addr:postcode":"31610",
    "addr:street":"Av. Serapio Huici",
    "iso:country":"ES",
    "sg:address":"Av. Serapio Huici, 19",
    "sg:city":"Atarrabia",
    "sg:orig_category":"Guarder\u00cdas",
    "sg:phone":"+34 948 14 69 57",
    "sg:postcode":"31610",
    "sg:province":"Navarra",
    "wof:name":"Colegio De Educacion Infantil Angel De Aralar",
    "wof:placetype":"venue"
},
  "geometry": {"coordinates":[-1.6118489504,42.828830719],"type":"Point"}
}