{
  "type": "Feature",
  "properties": {
    "iso:country":"ES",
    "sg:address":"Avda Merced, 52",
    "sg:city":"Salamanca",
    "sg:orig_category":"Internados & Ense\u00d1anza Privada",
    "sg:phone":"+34 923 22 60 04",
    "sg:postcode":"37005",
    "sg:province":"Salamanca",
    "wof:name":"Colegio San Jose De Salamanca-hijas De Maria Madre De La Iglesia-prov Dep Curia General",
    "wof:placetype":"venue"
},
  "geometry": {"coordinates":[-5.6608848572,40.9803085327],"type":"Point"}
}