{
  "type": "Feature",
  "properties": {
    "addr:full":"Carr Sant Mori, 28 Empuriabrava Girona 17487",
    "addr:housenumber":"28",
    "addr:postcode":"17487",
    "addr:street":"Carr Sant Mori",
    "iso:country":"ES",
    "sg:address":"Carr Sant Mori, 28",
    "sg:city":"Empuriabrava",
    "sg:orig_category":"Supermercados Y Hipermercados",
    "sg:phone":"+34 972 45 01 14",
    "sg:postcode":"17487",
    "sg:province":"Girona",
    "wof:name":"Salo Viusa Juana",
    "wof:placetype":"venue"
},
  "geometry": {"coordinates":[3.1070549488,42.2568092346],"type":"Point"}
}