{
  "type": "Feature",
  "properties": {
    "addr:full":"Av Puigcerda, Km. 0023,6 Pla Barcelona 08185",
    "addr:postcode":"08185",
    "addr:street":"Av Puigcerda Km. 0023,6 Pla Barcelona",
    "iso:country":"ES",
    "sg:address":"Av Puigcerda, Km. 0023,6",
    "sg:city":"Pla",
    "sg:orig_category":"Alimentaci\u00d3n: Aditivos, Esencias Alimentarias, Levaduras (fabricaci\u00d3n, Al Por Mayor)",
    "sg:phone":"+34 938 43 65 45",
    "sg:postcode":"08185",
    "sg:province":"Barcelona",
    "wof:name":"Super's Diana S.l.",
    "wof:placetype":"venue"
},
  "geometry": {"coordinates":[2.2406799793,41.5862312317],"type":"Point"}
}