{
  "type": "Feature",
  "properties": {
    "iso:country":"ES",
    "sg:address":"Carrer de Montbrio, Km. 0003,0",
    "sg:city":"Cambrils Badia",
    "sg:orig_category":"Promotores Constructores",
    "sg:phone":"+34 977 79 50 24",
    "sg:postcode":"43850",
    "sg:province":"Tarragona",
    "wof:name":"Inversions Morpu S.l.",
    "wof:placetype":"venue"
},
  "geometry": {"coordinates":[1.0733499527,41.0666542053],"type":"Point"}
}