{
  "type": "Feature",
  "properties": {
    "addr:full":"Calle de Mayor, S/n Vertavillo Palencia 34219",
    "addr:housenumber":"s",
    "addr:postcode":"34219",
    "addr:street":"Calle De Mayor;/ N",
    "iso:country":"ES",
    "sg:address":"Calle de Mayor, S/n",
    "sg:city":"Vertavillo",
    "sg:orig_category":"Iglesia Cat\u00d3lica",
    "sg:phone":"+34 979 78 31 18",
    "sg:postcode":"34219",
    "sg:province":"Palencia",
    "wof:name":"Parroquia San Miguel",
    "wof:placetype":"venue"
},
  "geometry": {"coordinates":[-4.3277640343,41.8320198059],"type":"Point"}
}