{
  "type": "Feature",
  "properties": {
    "addr:full":"Cruceiro, S/n Val La Coru\u00f1a 15541",
    "addr:housenumber":"s / n",
    "addr:postcode":"15541",
    "addr:street":"Cruceiro;Val La Corun\u0303A",
    "iso:country":"ES",
    "sg:address":"Cruceiro, S/n",
    "sg:city":"Val",
    "sg:orig_category":"Asociaciones Humanitarias, De Cooperaci\u00d3n, De Acci\u00d3n Social",
    "sg:phone":"+34 981 36 34 27",
    "sg:postcode":"15541",
    "sg:province":"La Coru\u00f1a",
    "wof:name":"Asociacion Nuestra Se\u00d1ora De Chamorro-protectora Minusv. Psiquicos",
    "wof:placetype":"venue"
},
  "geometry": {"coordinates":[-8.2055883408,43.5655326843],"type":"Point"}
}