{
  "type": "Feature",
  "properties": {
    "addr:full":"Av. Zaragoza, 68 Iru\u00f1a Navarra 31006",
    "addr:housenumber":"68",
    "addr:postcode":"31006",
    "addr:street":"Av. Zaragoza",
    "iso:country":"ES",
    "sg:address":"Av. Zaragoza, 68",
    "sg:city":"Iru\u00f1a",
    "sg:orig_category":"Relojer\u00cda (al Por Menor, Reparaci\u00d3n)",
    "sg:phone":"+34 948 23 03 10",
    "sg:postcode":"31006",
    "sg:province":"Navarra",
    "wof:name":"Larrayoz Ezpeleta Juan Luis",
    "wof:placetype":"venue"
},
  "geometry": {"coordinates":[-1.6441709995,42.8025283813],"type":"Point"}
}