{
  "type": "Feature",
  "properties": {
    "addr:full":"Barria, 8 Urdu\u00f1a-ordu\u00f1a Vizcaya 48460",
    "addr:housenumber":"8",
    "addr:postcode":"48460",
    "addr:street":"Barria",
    "iso:country":"ES",
    "sg:address":"Barria, 8",
    "sg:city":"Urdu\u00f1a-ordu\u00f1a",
    "sg:orig_category":"Librer\u00cdas",
    "sg:phone":"+34 945 38 38 79",
    "sg:postcode":"48460",
    "sg:province":"Vizcaya",
    "wof:name":"Fuente Fernandez De Aguirre Pedro De La",
    "wof:placetype":"venue"
},
  "geometry": {"coordinates":[-3.0069389343,42.9948730469],"type":"Point"}
}