{
  "type": "Feature",
  "properties": {
    "iso:country":"ES",
    "sg:address":"Avgd Serra, 29",
    "sg:city":"Massamagrell",
    "sg:orig_category":"Ferreter\u00cda (diversos)",
    "sg:phone":"+34 961 45 03 35",
    "sg:postcode":"46130",
    "sg:province":"Valencia",
    "wof:name":"Mercametal S.l.",
    "wof:placetype":"venue"
},
  "geometry": {"coordinates":[-0.3329139948,39.5671310425],"type":"Point"}
}