{
  "type": "Feature",
  "properties": {
    "iso:country":"ES",
    "sg:address":"C/ Joan Segura, 13",
    "sg:city":"Manacor",
    "sg:orig_category":"Ropa Para Se\u00d1oras (al Por Menor)",
    "sg:phone":"+34 971 55 49 67",
    "sg:postcode":"07500",
    "sg:province":"Islas Baleares",
    "wof:name":"Fernandez Gelabert Josefa Maria",
    "wof:placetype":"venue"
},
  "geometry": {"coordinates":[3.2094950676,39.5687561035],"type":"Point"}
}