{
  "type": "Feature",
  "properties": {
    "iso:country":"ES",
    "sg:address":"Av Italia(las Atalayas), 37",
    "sg:city":"Pe\u00f1iscola",
    "sg:classifiers":[
        {
            "category":"Communications",
            "subcategory":"Radio Station",
            "type":"Services"
        }
    ],
    "sg:phone":"+34 964 48 99 88",
    "sg:postcode":"12598",
    "sg:province":"Castell\u00f3n",
    "sg:tags":[
        "de",
        "electr\u00d3nica",
        "material",
        "fabricaci\u00d3n",
        "y",
        "profesional"
    ],
    "wof:name":"Apparate Systeme Wolf S L",
    "wof:placetype":"venue"
},
  "geometry": {"coordinates":[-0.0360242017,39.9860687256],"type":"Point"}
}