{
  "type": "Feature",
  "properties": {
    "iso:country":"ES",
    "sg:address":"Calle de Vista Alegre, 29",
    "sg:city":"Alcossebre",
    "sg:orig_category":"Art\u00cdculos De Regalo (al Por Menor)",
    "sg:phone":"+34 964 41 22 49",
    "sg:postcode":"12579",
    "sg:province":"Castell\u00f3n",
    "wof:name":"Regalos Dana S.l.",
    "wof:placetype":"venue"
},
  "geometry": {"coordinates":[0.2850950062,40.2547187805],"type":"Point"}
}