{
  "type": "Feature",
  "properties": {
    "addr:full":"Carr Camprodon, 57 Arbucies Girona 17401",
    "addr:housenumber":"57",
    "addr:postcode":"17401",
    "addr:street":"Carr Camprodon",
    "iso:country":"ES",
    "sg:address":"Carr Camprodon, 57",
    "sg:city":"Arbucies",
    "sg:orig_category":"Empleado Administrativo",
    "sg:phone":"+34 972 86 00 36",
    "sg:postcode":"17401",
    "sg:province":"Girona",
    "wof:name":"Lopez Medina Miguel",
    "wof:placetype":"venue"
},
  "geometry": {"coordinates":[2.5160269737,41.8154373169],"type":"Point"}
}