{
  "type": "Feature",
  "properties": {
    "iso:country":"ES",
    "sg:address":"Calle de Oro (del), 37",
    "sg:city":"Navarrosillos-poligono Sur",
    "sg:orig_category":"Electrodom\u00c9sticos (fabricaci\u00d3n, Al Por Mayor)",
    "sg:phone":"+34 918 46 51 07",
    "sg:postcode":"28770",
    "sg:province":"Madrid",
    "wof:name":"Proselco S.a.",
    "wof:placetype":"venue"
},
  "geometry": {"coordinates":[-3.7699229717,40.6656646729],"type":"Point"}
}