{
  "type": "Feature",
  "properties": {
    "addr:full":"Calle de Alfonso Ix, 20 Caceres C\u00e1ceres 10004",
    "addr:housenumber":"20",
    "addr:postcode":"10004",
    "addr:street":"Calle De Alfonso Ix;Ca\u0301Ceres",
    "iso:country":"ES",
    "sg:address":"Calle de Alfonso Ix, 20",
    "sg:city":"Caceres",
    "sg:orig_category":"Clubes, Asociaciones De Ocio",
    "sg:phone":"+34 927 22 29 49",
    "sg:postcode":"10004",
    "sg:province":"C\u00e1ceres",
    "sg:website":"www.aerocaceres.com",
    "wof:name":"Andrada Mateos Diego",
    "wof:placetype":"venue"
},
  "geometry": {"coordinates":[-6.3760166168,39.4739646912],"type":"Point"}
}