{
  "type": "Feature",
  "properties": {
    "iso:country":"ES",
    "sg:address":"Calle de Marquesa De Canillejas, 38",
    "sg:city":"Siero",
    "sg:orig_category":"Cajas De Ahorro",
    "sg:phone":"+34 985 72 54 78",
    "sg:postcode":"33510",
    "sg:province":"Asturias",
    "wof:name":"Caja De Ahorros De Asturias",
    "wof:placetype":"venue"
},
  "geometry": {"coordinates":[-5.6623001099,43.3900108337],"type":"Point"}
}