{
  "type": "Feature",
  "properties": {
    "iso:country":"ES",
    "sg:address":"Pase San Nicolas De Francia, 16",
    "sg:city":"Calatayud",
    "sg:orig_category":"Empresas De Carpinter\u00cda",
    "sg:phone":"+34 976 88 75 75",
    "sg:postcode":"50300",
    "sg:province":"Zaragoza",
    "wof:name":"Bilbilitana De Aluminios S.l.l.",
    "wof:placetype":"venue"
},
  "geometry": {"coordinates":[-1.6388039589,41.3530960083],"type":"Point"}
}