{
  "type": "Feature",
  "properties": {
    "iso:country":"ES",
    "sg:address":"Calle de Solana (la), 3",
    "sg:city":"Sorlada",
    "sg:orig_category":"Cr\u00cda De Animales",
    "sg:phone":"+34 948 54 51 11",
    "sg:postcode":"31219",
    "sg:province":"Navarra",
    "wof:name":"Granja Joar S.c.",
    "wof:placetype":"venue"
},
  "geometry": {"coordinates":[-2.2151799202,42.615688324],"type":"Point"}
}