{
  "type": "Feature",
  "properties": {
    "iso:country":"ES",
    "sg:address":"Calle de Belvis De La Jara, 17",
    "sg:city":"Madrid",
    "sg:orig_category":"Cl\u00cdnicas Dentales",
    "sg:phone":"+34 914 61 80 81",
    "sg:postcode":"28025",
    "sg:province":"Madrid",
    "wof:name":"Arfodental S.l.",
    "wof:placetype":"venue"
},
  "geometry": {"coordinates":[-3.7436485291,40.3750724792],"type":"Point"}
}