{
  "type": "Feature",
  "properties": {
    "addr:full":"Calle de Camilo Jose Cela, 1 Merida Badajoz 06800",
    "addr:housenumber":"1",
    "addr:postcode":"06800",
    "addr:street":"Calle De Camilo Jose Cela",
    "iso:country":"ES",
    "sg:address":"Calle de Camilo Jose Cela, 1",
    "sg:city":"Merida",
    "sg:orig_category":"Agencias De Prensa E Informaci\u00d3n",
    "sg:phone":"+34 924 30 40 92",
    "sg:postcode":"06800",
    "sg:province":"Badajoz",
    "wof:name":"Europa Press De Andalucia S.a.",
    "wof:placetype":"venue"
},
  "geometry": {"coordinates":[-6.3439235687,38.918384552],"type":"Point"}
}