{
  "type": "Feature",
  "properties": {
    "iso:country":"ES",
    "sg:address":"Carrer de Muntaner, 434",
    "sg:city":"Barcelona",
    "sg:orig_category":"Arquitectos",
    "sg:phone":"+34 932 00 10 90",
    "sg:postcode":"08006",
    "sg:province":"Barcelona",
    "wof:name":"Corominas Rovira Xavier",
    "wof:placetype":"venue"
},
  "geometry": {"coordinates":[2.1403150558,41.4012184143],"type":"Point"}
}