{
  "type": "Feature",
  "properties": {
    "iso:country":"ES",
    "sg:address":"Rio Hondillo, S/n",
    "sg:city":"Laguardia-biasteri",
    "sg:orig_category":"Productores Recolectores, Venta Directa De Vinos",
    "sg:phone":"+34 945 62 12 20",
    "sg:postcode":"01300",
    "sg:province":"\u00c1lava",
    "wof:name":"Bodegas Ubide S.a.",
    "wof:placetype":"venue"
},
  "geometry": {"coordinates":[-2.5707108974,42.5471076965],"type":"Point"}
}