{
  "type": "Feature",
  "properties": {
    "iso:country":"ES",
    "sg:address":"Calle de Saint Gaudens, 26",
    "sg:city":"Barbastro",
    "sg:orig_category":"Alquiler De V\u00cddeo",
    "sg:phone":"+34 974 31 19 09",
    "sg:postcode":"22300",
    "sg:province":"Huesca",
    "wof:name":"Gonzalez Alcaide Eva Maria",
    "wof:placetype":"venue"
},
  "geometry": {"coordinates":[0.1306910068,42.0327224731],"type":"Point"}
}