{
  "type": "Feature",
  "properties": {
    "iso:country":"ES",
    "sg:address":"Calle de Tomas Redondo, 1",
    "sg:city":"Madrid",
    "sg:orig_category":"Importaci\u00d3n",
    "sg:phone":"+34 916 69 25 30",
    "sg:postcode":"28033",
    "sg:province":"Madrid",
    "wof:name":"Telalia S.l.",
    "wof:placetype":"venue"
},
  "geometry": {"coordinates":[-3.6314098835,40.4728736877],"type":"Point"}
}