{
  "type": "Feature",
  "properties": {
    "iso:country":"ES",
    "sg:address":"Pase Habana, 54",
    "sg:city":"Madrid",
    "sg:orig_category":"Ropa Para Se\u00d1oras (al Por Menor)",
    "sg:phone":"+34 915 63 43 37",
    "sg:postcode":"28036",
    "sg:province":"Madrid",
    "sg:website":"www.benetton.com",
    "wof:name":"Bencom Retail Susursal En Espa\u00d1a",
    "wof:placetype":"venue"
},
  "geometry": {"coordinates":[-3.6862900257,40.4511680603],"type":"Point"}
}