{
  "type": "Feature",
  "properties": {
    "addr:full":"Calle de Higuereta, 57 Rota C\u00e1diz 11520",
    "addr:housenumber":"57",
    "addr:postcode":"11520",
    "addr:street":"Calle De Higuereta;Ca\u0301Diz",
    "iso:country":"ES",
    "sg:address":"Calle de Higuereta, 57",
    "sg:city":"Rota",
    "sg:orig_category":"Molduras, Junquillos, Listones Y Molduras Perforadas",
    "sg:phone":"+34 956 81 37 31",
    "sg:postcode":"11520",
    "sg:province":"C\u00e1diz",
    "wof:name":"Rotabasi",
    "wof:placetype":"venue"
},
  "geometry": {"coordinates":[-6.3620438576,36.6197395325],"type":"Point"}
}