{
  "type": "Feature",
  "properties": {
    "iso:country":"ES",
    "sg:address":"Calle de Magallanes, 1",
    "sg:city":"Barakaldo",
    "sg:orig_category":"Reposter\u00cdas",
    "sg:phone":"+34 944 66 08 39",
    "sg:postcode":"48903",
    "sg:province":"Vizcaya",
    "wof:name":"Panaderia Saiz",
    "wof:placetype":"venue"
},
  "geometry": {"coordinates":[-2.981317997,43.2820968628],"type":"Point"}
}