{
  "type": "Feature",
  "properties": {
    "addr:full":"Carrer de Aribau, 160 Barcelona Barcelona 08036",
    "addr:housenumber":"160",
    "addr:postcode":"08036",
    "addr:street":"Carrer De Aribau",
    "iso:country":"ES",
    "sg:address":"Carrer de Aribau, 160",
    "sg:city":"Barcelona",
    "sg:orig_category":"M\u00c9dicos: Estomatolog\u00cda",
    "sg:phone":"+34 932 37 86 75",
    "sg:postcode":"08036",
    "sg:province":"Barcelona",
    "wof:name":"Com. Va. Tu. Dent S.l.",
    "wof:placetype":"venue"
},
  "geometry": {"coordinates":[2.1542370319,41.39245224],"type":"Point"}
}