{
  "type": "Feature",
  "properties": {
    "iso:country":"ES",
    "sg:address":"Rond Ponent, 27",
    "sg:city":"Sabadell",
    "sg:orig_category":"Servidores Y Editores De Bases De Datos",
    "sg:phone":"+34 937 45 15 54",
    "sg:postcode":"08206",
    "sg:province":"Barcelona",
    "wof:name":"C Girones & Associats,sl",
    "wof:placetype":"venue"
},
  "geometry": {"coordinates":[2.0747048855,41.5592803955],"type":"Point"}
}