{
  "type": "Feature",
  "properties": {
    "iso:country":"ES",
    "sg:address":"Carr Enric Prat De La Riba, 16",
    "sg:city":"Blanes",
    "sg:orig_category":"Caf\u00c9s, Bares, Cervecer\u00cdas",
    "sg:phone":"+34 972 33 34 24",
    "sg:postcode":"17300",
    "sg:province":"Girona",
    "wof:name":"Blink Anlobra S.l.",
    "wof:placetype":"venue"
},
  "geometry": {"coordinates":[2.7836000919,41.6667175293],"type":"Point"}
}