{
  "type": "Feature",
  "properties": {
    "iso:country":"ES",
    "sg:address":"Calle de Serrano Jover, 5",
    "sg:city":"Madrid",
    "sg:orig_category":"Cervecer\u00cdas",
    "sg:phone":"+34 915 41 32 30",
    "sg:postcode":"28015",
    "sg:province":"Madrid",
    "wof:name":"Becerril Y Benitez S.l.",
    "wof:placetype":"venue"
},
  "geometry": {"coordinates":[-3.7143440247,40.4302215576],"type":"Point"}
}