{
  "type": "Feature",
  "properties": {
    "addr:full":"Rbla Passeig, 14 Vic Barcelona 08500",
    "addr:housenumber":"14",
    "addr:postcode":"08500",
    "addr:street":"Passeig",
    "iso:country":"ES",
    "sg:address":"Rbla Passeig, 14",
    "sg:city":"Vic",
    "sg:orig_category":"Comercio, Reparaci\u00d3n De Bicicletas, De Motocicletas, De Accesorios",
    "sg:phone":"+34 938 86 36 58",
    "sg:postcode":"08500",
    "sg:province":"Barcelona",
    "wof:name":"Vila Ors Juan",
    "wof:placetype":"venue"
},
  "geometry": {"coordinates":[2.2560460567,41.9302520752],"type":"Point"}
}