{
  "type": "Feature",
  "properties": {
    "addr:full":"Calle de Rosamunda, S/n Malaga M\u00e1laga 29006",
    "addr:housenumber":"s",
    "addr:postcode":"29006",
    "addr:street":"Calle De Rosamunda;/ N;Ma\u0301Laga",
    "iso:country":"ES",
    "sg:address":"Calle de Rosamunda, S/n",
    "sg:city":"Malaga",
    "sg:orig_category":"Distribuci\u00d3n De Petr\u00d3leo Y Derivados",
    "sg:phone":"+34 952 32 67 51",
    "sg:postcode":"29006",
    "sg:province":"M\u00e1laga",
    "wof:name":"Battivila S.l.",
    "wof:placetype":"venue"
},
  "geometry": {"coordinates":[-4.4720988274,36.7094764709],"type":"Point"}
}