{
  "type": "Feature",
  "properties": {
    "iso:country":"ES",
    "sg:address":"Calle de Inmaculada Concepcion, 41",
    "sg:city":"Madrid",
    "sg:orig_category":"Asociaciones, Organismos Culturales Y Socioeducativos",
    "sg:phone":"+34 915 60 29 30",
    "sg:postcode":"28019",
    "sg:province":"Madrid",
    "wof:name":"Asociacion Grupo De Mujeres De Comillas",
    "wof:placetype":"venue"
},
  "geometry": {"coordinates":[-3.7125179768,40.3910980225],"type":"Point"}
}