{
  "type": "Feature",
  "properties": {
    "iso:country":"ES",
    "sg:address":"Carrer de Bruc, 129",
    "sg:city":"Barcelona",
    "sg:orig_category":"Centros P\u00dablicos De Formaci\u00d3n Profesional Y T\u00c9cnica",
    "sg:phone":"+34 934 57 77 04",
    "sg:postcode":"08037",
    "sg:province":"Barcelona",
    "wof:name":"Colegio Catalan De Arbitros De Futbol",
    "wof:placetype":"venue"
},
  "geometry": {"coordinates":[2.1656839848,41.3970451355],"type":"Point"}
}