{
  "type": "Feature",
  "properties": {
    "iso:country":"ES",
    "sg:address":"Calle de Santiago, 87",
    "sg:city":"Almeria",
    "sg:orig_category":"Dietistas",
    "sg:phone":"+34 950 17 02 00",
    "sg:postcode":"04006",
    "sg:province":"Almer\u00eda",
    "wof:name":"Bodywork C.b",
    "wof:placetype":"venue"
},
  "geometry": {"coordinates":[-2.450109005,36.8433799744],"type":"Point"}
}