{
  "type": "Feature",
  "properties": {
    "iso:country":"ES",
    "sg:address":"Luis Morondo Urra, S/n",
    "sg:city":"Iru\u00f1a",
    "sg:orig_category":"Iglesia Cat\u00d3lica",
    "sg:phone":"+34 948 15 18 75",
    "sg:postcode":"31006",
    "sg:province":"Navarra",
    "wof:name":"Parroquia De San Raimundo",
    "wof:placetype":"venue"
},
  "geometry": {"coordinates":[-1.6459079981,42.8012390137],"type":"Point"}
}