{
  "type": "Feature",
  "properties": {
    "iso:country":"ES",
    "sg:address":"Calle de Carpinteros, 12",
    "sg:city":"Malaga",
    "sg:orig_category":"Explotaci\u00d3n De Aparcamientos",
    "sg:phone":"+34 952 31 41 41",
    "sg:postcode":"29006",
    "sg:province":"M\u00e1laga",
    "wof:name":"Maria Del Pilar Garcia Luque S. L.",
    "wof:placetype":"venue"
},
  "geometry": {"coordinates":[-4.4461693764,36.7079353333],"type":"Point"}
}