{
  "type": "Feature",
  "properties": {
    "addr:full":"Carrer de Queralt, 4 Barcelona Barcelona 08017",
    "addr:housenumber":"4",
    "addr:postcode":"08017",
    "addr:street":"Carrer De Queralt",
    "iso:country":"ES",
    "sg:address":"Carrer de Queralt, 4",
    "sg:city":"Barcelona",
    "sg:orig_category":"Florister\u00cdas",
    "sg:phone":"+34 934 06 84 50",
    "sg:postcode":"08017",
    "sg:province":"Barcelona",
    "wof:name":"Adam Sala Pedro",
    "wof:placetype":"venue"
},
  "geometry": {"coordinates":[2.1048491001,41.4132919312],"type":"Point"}
}