{
  "type": "Feature",
  "properties": {
    "iso:country":"ES",
    "sg:address":"Ribeira-noia, Km. 0043,0",
    "sg:city":"Ribeira-santa Uxia",
    "sg:orig_category":"Fabricaci\u00d3n De Muebles",
    "sg:phone":"+34 981 87 60 17",
    "sg:postcode":"15960",
    "sg:province":"La Coru\u00f1a",
    "wof:name":"Muebles Gonzalez Diz S.l.",
    "wof:placetype":"venue"
},
  "geometry": {"coordinates":[-8.9908485413,42.5553665161],"type":"Point"}
}