{
  "type": "Feature",
  "properties": {
    "iso:country":"ES",
    "sg:address":"Calle de Conde Guillen, 2",
    "sg:city":"Le\u00f3n",
    "sg:orig_category":"Abogados",
    "sg:phone":"+34 987 20 31 15",
    "sg:postcode":"24004",
    "sg:province":"Le\u00f3n",
    "wof:name":"Quiroga Y Modino Aser-pharma S.l.",
    "wof:placetype":"venue"
},
  "geometry": {"coordinates":[-5.574886322,42.5952835083],"type":"Point"}
}