{
  "type": "Feature",
  "properties": {
    "addr:full":"Avda De Los Emigrantes, 14 Navia Asturias 33710",
    "addr:housenumber":"14",
    "addr:postcode":"33710",
    "addr:street":"Avda De Los Emigrantes",
    "iso:country":"ES",
    "sg:address":"Avda De Los Emigrantes, 14",
    "sg:city":"Navia",
    "sg:orig_category":"Florister\u00cdas",
    "sg:phone":"+34 985 47 37 51",
    "sg:postcode":"33710",
    "sg:province":"Asturias",
    "wof:name":"Floristeria Stais",
    "wof:placetype":"venue"
},
  "geometry": {"coordinates":[-6.7245988846,43.5380935669],"type":"Point"}
}