{
  "type": "Feature",
  "properties": {
    "iso:country":"ES",
    "sg:address":"Rond Buenavista, 15",
    "sg:city":"Toledo",
    "sg:orig_category":"Asociaciones Y Clubs Deportivos",
    "sg:phone":"+34 925 22 32 33",
    "sg:postcode":"45005",
    "sg:province":"Toledo",
    "wof:name":"Juvi Seguridad Modular S.l",
    "wof:placetype":"venue"
},
  "geometry": {"coordinates":[-4.0406126976,39.8757095337],"type":"Point"}
}