{
  "type": "Feature",
  "properties": {
    "iso:country":"ES",
    "sg:address":"Calle de San Anton, 39",
    "sg:city":"Parla",
    "sg:orig_category":"Librer\u00cdas",
    "sg:phone":"+34 916 99 05 91",
    "sg:postcode":"28980",
    "sg:province":"Madrid",
    "wof:name":"Tarasur Sl",
    "wof:placetype":"venue"
},
  "geometry": {"coordinates":[-3.7686889172,40.2397613525],"type":"Point"}
}