{
  "type": "Feature",
  "properties": {
    "addr:full":"Av Palma, S/n Calvia Islas Baleares 07184",
    "addr:housenumber":"s",
    "addr:postcode":"07184",
    "addr:street":"Av Palma;/ N",
    "iso:country":"ES",
    "sg:address":"Av Palma, S/n",
    "sg:city":"Calvia",
    "sg:orig_category":"Distribuci\u00d3n De Petr\u00d3leo Y Derivados",
    "sg:phone":"+34 971 67 07 39",
    "sg:postcode":"07184",
    "sg:province":"Islas Baleares",
    "sg:website":"www.cepsa.es",
    "wof:name":"Suministros Y Servicios Calvia S.l.",
    "wof:placetype":"venue"
},
  "geometry": {"coordinates":[2.5044250488,39.564163208],"type":"Point"}
}