{
  "type": "Feature",
  "properties": {
    "iso:country":"ES",
    "sg:address":"Plaz Espa\u00d1a, 2",
    "sg:city":"Talavera Real",
    "sg:orig_category":"Ense\u00d1anza, Formaci\u00d3n Profesional: Aprendizaje",
    "sg:phone":"+34 924 44 00 61",
    "sg:postcode":"06140",
    "sg:province":"Badajoz",
    "wof:name":"Ayuntamiento De Talavera La Real",
    "wof:placetype":"venue"
},
  "geometry": {"coordinates":[-6.7671589851,38.8753318787],"type":"Point"}
}