{
  "type": "Feature",
  "properties": {
    "addr:full":"Carr Major, 13 Hostalric Girona 17450",
    "addr:housenumber":"13",
    "addr:postcode":"17450",
    "addr:street":"Carr Major",
    "iso:country":"ES",
    "sg:address":"Carr Major, 13",
    "sg:city":"Hostalric",
    "sg:orig_category":"Carnicer\u00cdas, Carnicer\u00cdas",
    "sg:phone":"+34 972 86 40 34",
    "sg:postcode":"17450",
    "sg:province":"Girona",
    "wof:name":"Llach Masanella Jaime",
    "wof:placetype":"venue"
},
  "geometry": {"coordinates":[2.638520956,41.7458343506],"type":"Point"}
}