{
  "type": "Feature",
  "properties": {
    "iso:country":"ES",
    "sg:address":"Carrer de Bombers Madern I Clariana, 8",
    "sg:city":"Mataro",
    "sg:orig_category":"Organizaciones Internacionales",
    "sg:phone":"+34 937 96 24 96",
    "sg:postcode":"08304",
    "sg:province":"Barcelona",
    "wof:name":"Caritas Diocesana De Barcelona",
    "wof:placetype":"venue"
},
  "geometry": {"coordinates":[2.4512279034,41.5459136963],"type":"Point"}
}