{
  "type": "Feature",
  "properties": {
    "iso:country":"ES",
    "sg:address":"Carrer de Pintor Fortuny, 33",
    "sg:city":"Barcelona",
    "sg:orig_category":"Mec\u00c1nico Del Autom\u00d3vil",
    "sg:phone":"+34 934 12 35 29",
    "sg:postcode":"08001",
    "sg:province":"Barcelona",
    "wof:name":"Castilla Molina Joaquin",
    "wof:placetype":"venue"
},
  "geometry": {"coordinates":[2.1686730385,41.3821144104],"type":"Point"}
}