{
  "type": "Feature",
  "properties": {
    "addr:full":"Avda Alfonso Vii, 1 Coria C\u00e1ceres 10800",
    "addr:postcode":"10800",
    "addr:street":"Avda Alfonso Vii",
    "iso:country":"ES",
    "sg:address":"Avda Alfonso Vii, 1",
    "sg:city":"Coria",
    "sg:orig_category":"Florister\u00cdas",
    "sg:phone":"+34 927 50 61 32",
    "sg:postcode":"10800",
    "sg:province":"C\u00e1ceres",
    "sg:website":"www.floristas.com",
    "wof:name":"Flores Aguilar Eugenia",
    "wof:placetype":"venue"
},
  "geometry": {"coordinates":[-6.5382370949,39.9893379211],"type":"Point"}
}