{
  "type": "Feature",
  "properties": {
    "iso:country":"ES",
    "sg:address":"Avda Constitucion De La, S/n",
    "sg:city":"Arroyo De La Miel-benalmadena Costa",
    "sg:orig_category":"Librer\u00cdas",
    "sg:phone":"+34 952 56 61 94",
    "sg:postcode":"29631",
    "sg:province":"M\u00e1laga",
    "wof:name":"Peinado Carre\u00f1o Yolanda",
    "wof:placetype":"venue"
},
  "geometry": {"coordinates":[-4.5482521057,36.6017608643],"type":"Point"}
}