{
  "type": "Feature",
  "properties": {
    "iso:country":"ES",
    "sg:address":"Calle de Grande, 12",
    "sg:city":"Calahorra",
    "sg:orig_category":"Quincaller\u00cda (al Por Menor)",
    "sg:phone":"+34 941 13 01 39",
    "sg:postcode":"26500",
    "sg:province":"La Rioja",
    "wof:name":"Brocal Pascual Jose Luis",
    "wof:placetype":"venue"
},
  "geometry": {"coordinates":[-1.9620139599,42.3016891479],"type":"Point"}
}