{
  "type": "Feature",
  "properties": {
    "addr:full":"Cmno Huerta, 127 Madrid Madrid 28050",
    "addr:housenumber":"127",
    "addr:postcode":"28050",
    "addr:street":"Cmno Huerta",
    "iso:country":"ES",
    "sg:address":"Cmno Huerta, 127",
    "sg:city":"Madrid",
    "sg:orig_category":"Centros Empresariales",
    "sg:phone":"+34 916 25 51 22",
    "sg:postcode":"28050",
    "sg:province":"Madrid",
    "sg:website":"www.impactwsiweb.com",
    "wof:name":"Martinez Pi\u00d1eiro Asesores S L",
    "wof:placetype":"venue"
},
  "geometry": {"coordinates":[-3.6388890743,40.5049438477],"type":"Point"}
}