{
  "type": "Feature",
  "properties": {
    "iso:country":"ES",
    "sg:address":"Avda Perez Galdos, 25",
    "sg:city":"Santander",
    "sg:orig_category":"Productos Qu\u00cdmicos (fabricaci\u00d3n, Al Por Mayor)",
    "sg:phone":"+34 942 27 66 33",
    "sg:postcode":"39005",
    "sg:province":"Cantabria",
    "wof:name":"Juan Jose Alonso Grijalba S.a.",
    "wof:placetype":"venue"
},
  "geometry": {"coordinates":[-3.7830169201,43.4666671753],"type":"Point"}
}