{
  "type": "Feature",
  "properties": {
    "iso:country":"ES",
    "sg:address":"Calle de Leones (los), S/n",
    "sg:city":"Berlanga Duero",
    "sg:orig_category":"Alquiler De Casas Y Habitaciones Amuebladas",
    "sg:phone":"+34 975 34 32 75",
    "sg:postcode":"42360",
    "sg:province":"Soria",
    "wof:name":"Maria Luisa Navas Y Jose Martinez Cb",
    "wof:placetype":"venue"
},
  "geometry": {"coordinates":[-2.8619589806,41.4668045044],"type":"Point"}
}