{
  "type": "Feature",
  "properties": {
    "addr:full":"Carrer de Albert Santo, 5 Banyeres Penedes Tarragona 43711",
    "addr:housenumber":"5",
    "addr:postcode":"43711",
    "addr:street":"Carrer De Albert Santo",
    "iso:country":"ES",
    "sg:address":"Carrer de Albert Santo, 5",
    "sg:city":"Banyeres Penedes",
    "sg:orig_category":"Transportes Por Carretera: Lotes Completos, Mercanc\u00cdas Diversas",
    "sg:phone":"+34 977 67 07 57",
    "sg:postcode":"43711",
    "sg:province":"Tarragona",
    "wof:name":"Rull Montserrat Aurelia",
    "wof:placetype":"venue"
},
  "geometry": {"coordinates":[1.5812779665,41.2796707153],"type":"Point"}
}