{
  "type": "Feature",
  "properties": {
    "iso:country":"ES",
    "sg:address":"Calle de Cuevas, S/n",
    "sg:city":"Fuente-alamo",
    "sg:orig_category":"Torrefactado De Caf\u00c9",
    "sg:phone":"+34 967 32 17 20",
    "sg:postcode":"02651",
    "sg:province":"Albacete",
    "wof:name":"Comercial Calpe De Cafes S.l.",
    "wof:placetype":"venue"
},
  "geometry": {"coordinates":[-1.4297039509,38.6897315979],"type":"Point"}
}