{
  "type": "Feature",
  "properties": {
    "iso:country":"ES",
    "sg:address":"Calle de General Lacy, 12",
    "sg:city":"Alacant",
    "sg:orig_category":"Tatuajes",
    "sg:phone":"+34 965 13 14 75",
    "sg:postcode":"03003",
    "sg:province":"Alicante",
    "wof:name":"Nguyen  Rose Elisabet",
    "wof:placetype":"venue"
},
  "geometry": {"coordinates":[-0.4921000004,38.3449554443],"type":"Point"}
}