{
  "type": "Feature",
  "properties": {
    "iso:country":"ES",
    "sg:address":"Calle de Candelario, 30",
    "sg:city":"Salamanca",
    "sg:orig_category":"Agentes Generales De Seguros",
    "sg:phone":"+34 923 12 47 65",
    "sg:postcode":"37007",
    "sg:province":"Salamanca",
    "wof:name":"Sanchez Matas Andres",
    "wof:placetype":"venue"
},
  "geometry": {"coordinates":[-5.6729898453,40.9713859558],"type":"Point"}
}