{
  "type": "Feature",
  "properties": {
    "addr:full":"Ctra San Miguel, S/n Belorado Burgos 09250",
    "addr:housenumber":"s / n",
    "addr:postcode":"09250",
    "addr:street":"Ctra San Miguel",
    "iso:country":"ES",
    "sg:address":"Ctra San Miguel, S/n",
    "sg:city":"Belorado",
    "sg:orig_category":"Fabricaci\u00d3n De Su\u00c9ters Y Chalecos De Punto",
    "sg:phone":"+34 947 58 05 00",
    "sg:postcode":"09250",
    "sg:province":"Burgos",
    "wof:name":"Calcetines Hernando S.a.",
    "wof:placetype":"venue"
},
  "geometry": {"coordinates":[-3.2142190933,42.3949890137],"type":"Point"}
}