{
  "type": "Feature",
  "properties": {
    "iso:country":"ES",
    "sg:address":"Avda Erillas (las), 1",
    "sg:city":"Camas",
    "sg:orig_category":"Estancos",
    "sg:phone":"+34 954 39 49 58",
    "sg:postcode":"41900",
    "sg:province":"Sevilla",
    "wof:name":"Mellado Centeno Maria Del Monte",
    "wof:placetype":"venue"
},
  "geometry": {"coordinates":[-6.031088829,37.3882293701],"type":"Point"}
}