{
  "type": "Feature",
  "properties": {
    "iso:country":"ES",
    "sg:address":"Calle de Reyes Catolicos, 17",
    "sg:city":"Alacant",
    "sg:orig_category":"Abogados",
    "sg:phone":"+34 965 92 91 76",
    "sg:postcode":"03003",
    "sg:province":"Alicante",
    "wof:name":"Andres Fuertes Mariano",
    "wof:placetype":"venue"
},
  "geometry": {"coordinates":[-0.4897496104,38.3426704407],"type":"Point"}
}