{
  "type": "Feature",
  "properties": {
    "iso:country":"ES",
    "sg:address":"Calle de Mayor Principal, 2",
    "sg:city":"Palencia",
    "sg:orig_category":"Pr\u00c9stamos Personales E Hipotecarios",
    "sg:phone":"+34 979 70 09 61",
    "sg:postcode":"34001",
    "sg:province":"Palencia",
    "wof:name":"Olaya Garcia,ricardo",
    "wof:placetype":"venue"
},
  "geometry": {"coordinates":[-4.5392618179,42.010433197],"type":"Point"}
}