{
  "type": "Feature",
  "properties": {
    "addr:full":"Avda Benito Vigo, 68 Estrada Pontevedra 36680",
    "addr:housenumber":"68",
    "addr:postcode":"36680",
    "addr:street":"Avda Benito Vigo;Estrada Pontevedra",
    "iso:country":"ES",
    "sg:address":"Avda Benito Vigo, 68",
    "sg:city":"Estrada",
    "sg:orig_category":"Bares, Piano",
    "sg:phone":"+34 986 57 51 75",
    "sg:postcode":"36680",
    "sg:province":"Pontevedra",
    "wof:name":"Sotoblanco S.c.",
    "wof:placetype":"venue"
},
  "geometry": {"coordinates":[-8.4907169342,42.6883506775],"type":"Point"}
}