{
  "type": "Feature",
  "properties": {
    "iso:country":"ES",
    "sg:address":"Calle de Urbina, 7",
    "sg:city":"Vitoria-gasteiz",
    "sg:orig_category":"Peluqueros: De Se\u00d1oras",
    "sg:phone":"+34 945 28 75 87",
    "sg:postcode":"01002",
    "sg:province":"\u00c1lava",
    "wof:name":"Martinez Rojas Mercedes",
    "wof:placetype":"venue"
},
  "geometry": {"coordinates":[-2.6697568893,42.8538589478],"type":"Point"}
}