{
  "type": "Feature",
  "properties": {
    "addr:full":"Carr S Pere, 1 Igualada Barcelona 08700",
    "addr:housenumber":"1",
    "addr:postcode":"08700",
    "addr:street":"Carr S Pere",
    "iso:country":"ES",
    "sg:address":"Carr S Pere, 1",
    "sg:city":"Igualada",
    "sg:orig_category":"Perfumer\u00cda (al Por Menor)",
    "sg:phone":"+34 938 03 62 33",
    "sg:postcode":"08700",
    "sg:province":"Barcelona",
    "wof:name":"Castells Roig Maria Angeles",
    "wof:placetype":"venue"
},
  "geometry": {"coordinates":[1.6248070002,41.5822372437],"type":"Point"}
}