{
  "type": "Feature",
  "properties": {
    "addr:full":"Barr Udondo, S/n Udondo Vizcaya 48940",
    "addr:housenumber":"s",
    "addr:postcode":"48940",
    "addr:street":"/ N",
    "iso:country":"ES",
    "sg:address":"Barr Udondo, S/n",
    "sg:city":"Udondo",
    "sg:orig_category":"Ingenier\u00cda, Centros De Estudios (diversos)",
    "sg:phone":"+34 944 63 87 02",
    "sg:postcode":"48940",
    "sg:province":"Vizcaya",
    "sg:website":"www.lantec.es",
    "wof:name":"Lantec Estudios Y Proyectos S.l.",
    "wof:placetype":"venue"
},
  "geometry": {"coordinates":[-2.9860789776,43.3275489807],"type":"Point"}
}