{
  "type": "Feature",
  "properties": {
    "addr:full":"Cmno Valhondo, S/n Monterrubio De Armu\u00e7a Salamanca 37184",
    "addr:housenumber":"s / n",
    "addr:postcode":"37184",
    "addr:street":"Cmno Valhondo",
    "iso:country":"ES",
    "sg:address":"Cmno Valhondo, S/n",
    "sg:city":"Monterrubio De Armu\u00e7a",
    "sg:orig_category":"Promotores Constructores",
    "sg:phone":"+34 923 28 70 08",
    "sg:postcode":"37184",
    "sg:province":"Salamanca",
    "wof:name":"Construcciones Capesa S.l.",
    "wof:placetype":"venue"
},
  "geometry": {"coordinates":[-5.6469841003,41.0071716309],"type":"Point"}
}