{
  "type": "Feature",
  "properties": {
    "iso:country":"ES",
    "sg:address":"Pesqueira(castro), S/n",
    "sg:city":"Boiro",
    "sg:orig_category":"Reposter\u00cdas",
    "sg:phone":"+34 981 84 57 05",
    "sg:postcode":"15930",
    "sg:province":"La Coru\u00f1a",
    "wof:name":"Lomba Castro Jose Manuel",
    "wof:placetype":"venue"
},
  "geometry": {"coordinates":[-8.8843259811,42.6167602539],"type":"Point"}
}