{
  "type": "Feature",
  "properties": {
    "iso:country":"ES",
    "sg:address":"Carrer de Major De Sarria, 190",
    "sg:city":"Barcelona",
    "sg:orig_category":"Comerciantes Al Por Mayor De Vinos, Licores Y Alcoholes",
    "sg:phone":"+34 932 04 11 23",
    "sg:postcode":"08017",
    "sg:province":"Barcelona",
    "wof:name":"Barrio Baques Jose",
    "wof:placetype":"venue"
},
  "geometry": {"coordinates":[2.1192820072,41.4024162292],"type":"Point"}
}