{
  "type": "Feature",
  "properties": {
    "addr:full":"Reino, 5 Alzira Valencia 46600",
    "addr:housenumber":"5",
    "addr:postcode":"46600",
    "addr:street":"Reino",
    "iso:country":"ES",
    "sg:address":"Reino, 5",
    "sg:city":"Alzira",
    "sg:orig_category":"Caf\u00c9s, Bares, Cervecer\u00cdas",
    "sg:phone":"+34 962 41 01 12",
    "sg:postcode":"46600",
    "sg:province":"Valencia",
    "wof:name":"Eurotel Sur S.l.",
    "wof:placetype":"venue"
},
  "geometry": {"coordinates":[-0.4378489852,39.1517295837],"type":"Point"}
}