{
  "type": "Feature",
  "properties": {
    "addr:full":"Calle de Rocio, 6 Velez-malaga M\u00e1laga 29700",
    "addr:housenumber":"6",
    "addr:postcode":"29700",
    "addr:street":"Calle De Rocio",
    "iso:country":"ES",
    "sg:address":"Calle de Rocio, 6",
    "sg:city":"Velez-malaga",
    "sg:orig_category":"Discapacitados",
    "sg:phone":"+34 952 50 73 30",
    "sg:postcode":"29700",
    "sg:province":"M\u00e1laga",
    "wof:name":"Amivel",
    "wof:placetype":"venue"
},
  "geometry": {"coordinates":[-4.1073970795,36.7880096436],"type":"Point"}
}