{
  "type": "Feature",
  "properties": {
    "iso:country":"ES",
    "sg:address":"Calle de Mayor, 28",
    "sg:city":"Almaden",
    "sg:orig_category":"Bares, Piano",
    "sg:phone":"+34 926 71 07 53",
    "sg:postcode":"13400",
    "sg:province":"Ciudad Real",
    "wof:name":"Mayoral Mu\u00f1oz Sotero",
    "wof:placetype":"venue"
},
  "geometry": {"coordinates":[-4.8353252411,38.7756500244],"type":"Point"}
}