{
  "type": "Feature",
  "properties": {
    "addr:full":"Calle de Juan Xxiii, 1 Sestao Vizcaya 48910",
    "addr:housenumber":"1",
    "addr:postcode":"48910",
    "addr:street":"Calle De Juan Xxiii",
    "iso:country":"ES",
    "sg:address":"Calle de Juan Xxiii, 1",
    "sg:city":"Sestao",
    "sg:orig_category":"Asociaciones Y Clubs Deportivos",
    "sg:phone":"+34 944 95 65 31",
    "sg:postcode":"48910",
    "sg:province":"Vizcaya",
    "wof:name":"Jose Caro Gallardo",
    "wof:placetype":"venue"
},
  "geometry": {"coordinates":[-3.0060760975,43.3111495972],"type":"Point"}
}