{
  "type": "Feature",
  "properties": {
    "iso:country":"ES",
    "sg:address":"Calle de Iberia, 20",
    "sg:city":"Yecla",
    "sg:orig_category":"Peluqueros: De Se\u00d1oras",
    "sg:phone":"+34 968 79 54 18",
    "sg:postcode":"30510",
    "sg:province":"Murcia",
    "wof:name":"Albert Ortu\u00f1o Maria Teresa",
    "wof:placetype":"venue"
},
  "geometry": {"coordinates":[-1.1118131876,38.6130828857],"type":"Point"}
}