{
  "type": "Feature",
  "properties": {
    "iso:country":"ES",
    "sg:address":"Agerrealde Etxadia, 9",
    "sg:city":"Altzibar",
    "sg:orig_category":"Asociaciones Humanitarias, De Cooperaci\u00d3n, De Acci\u00d3n Social",
    "sg:phone":"+34 943 49 01 84",
    "sg:postcode":"20180",
    "sg:province":"Guip\u00f9zcoa",
    "wof:name":"Asociacion Guipuzcoana De Familiares Y Enfermos Psiquicos",
    "wof:placetype":"venue"
},
  "geometry": {"coordinates":[-1.8629590273,43.2992401123],"type":"Point"}
}