{
  "type": "Feature",
  "properties": {
    "addr:full":"Carrer de Lletres, 2 Barcelona Barcelona 08032",
    "addr:housenumber":"2",
    "addr:postcode":"08032",
    "addr:street":"Carrer De Lletres",
    "iso:country":"ES",
    "sg:address":"Carrer de Lletres, 2",
    "sg:city":"Barcelona",
    "sg:orig_category":"Pod\u00d3logos: Pedicuros",
    "sg:phone":"+34 933 57 30 54",
    "sg:postcode":"08032",
    "sg:province":"Barcelona",
    "wof:name":"Fernandez Carrera Manuel",
    "wof:placetype":"venue"
},
  "geometry": {"coordinates":[2.1580519676,41.4277915955],"type":"Point"}
}