{
  "type": "Feature",
  "properties": {
    "addr:full":"Cno. Eriete, S/n Paternain Navarra 31190",
    "addr:housenumber":"s / n",
    "addr:postcode":"31190",
    "addr:street":"Cno. Eriete",
    "iso:country":"ES",
    "sg:address":"Cno. Eriete, S/n",
    "sg:city":"Paternain",
    "sg:orig_category":"Empresas De Carpinter\u00cda Met\u00c1lica",
    "sg:phone":"+34 948 35 32 60",
    "sg:postcode":"31190",
    "sg:province":"Navarra",
    "wof:name":"Iraizoz Vizcar Jesus Ignacio",
    "wof:placetype":"venue"
},
  "geometry": {"coordinates":[-1.6754239798,42.7882118225],"type":"Point"}
}