{
  "type": "Feature",
  "properties": {
    "addr:full":"Parra, 1 Ponts Lleida 25740",
    "addr:housenumber":"1",
    "addr:postcode":"25740",
    "addr:street":"Parra",
    "iso:country":"ES",
    "sg:address":"Parra, 1",
    "sg:city":"Ponts",
    "sg:orig_category":"Electricidad: Instaladores",
    "sg:phone":"+34 973 46 09 08",
    "sg:postcode":"25740",
    "sg:province":"Lleida",
    "wof:name":"Tugues Masana Juan",
    "wof:placetype":"venue"
},
  "geometry": {"coordinates":[1.1869549751,41.915145874],"type":"Point"}
}