{
  "type": "Feature",
  "properties": {
    "addr:full":"Calle de Corazon De Jesus, 6 Riba-roja Turia Valencia 46190",
    "addr:housenumber":"6",
    "addr:postcode":"46190",
    "addr:street":"Calle De Corazon;Jesus",
    "iso:country":"ES",
    "sg:address":"Calle de Corazon De Jesus, 6",
    "sg:city":"Riba-roja Turia",
    "sg:orig_category":"Arboricultura Y Producci\u00d3n De Frutas",
    "sg:phone":"+34 962 77 04 16",
    "sg:postcode":"46190",
    "sg:province":"Valencia",
    "wof:name":"Peris Paredes Federico",
    "wof:placetype":"venue"
},
  "geometry": {"coordinates":[-0.5698940158,39.5458450317],"type":"Point"}
}