{
  "type": "Feature",
  "properties": {
    "addr:full":"Carrer de Roure, 10 Viladecans Barcelona 08840",
    "addr:housenumber":"10",
    "addr:postcode":"08840",
    "addr:street":"Carrer De Roure",
    "iso:country":"ES",
    "sg:address":"Carrer de Roure, 10",
    "sg:city":"Viladecans",
    "sg:orig_category":"Reposter\u00cdas",
    "sg:phone":"+34 936 37 61 52",
    "sg:postcode":"08840",
    "sg:province":"Barcelona",
    "wof:name":"Martin Comas S.l.",
    "wof:placetype":"venue"
},
  "geometry": {"coordinates":[2.0142960548,41.323589325],"type":"Point"}
}