{
  "type": "Feature",
  "properties": {
    "iso:country":"ES",
    "sg:address":"Mercabarna (zona Franca), 7",
    "sg:city":"Barcelona",
    "sg:orig_category":"Transportes Por Carretera: Lotes Completos, Mercanc\u00cdas Diversas",
    "sg:phone":"+34 932 63 26 41",
    "sg:postcode":"08040",
    "sg:province":"Barcelona",
    "wof:name":"Almacenes Barluenga S.a.",
    "wof:placetype":"venue"
},
  "geometry": {"coordinates":[2.130294323,41.3364562988],"type":"Point"}
}