{
  "type": "Feature",
  "properties": {
    "addr:full":"Calle de Camichi, 18 Madrid Madrid 28025",
    "addr:housenumber":"18",
    "addr:postcode":"madrid;28025",
    "addr:street":"Calle De Camichi",
    "iso:country":"ES",
    "sg:address":"Calle de Camichi, 18",
    "sg:city":"Madrid",
    "sg:orig_category":"Puertas Y Portales",
    "sg:phone":"+34 914 66 10 06",
    "sg:postcode":"28025",
    "sg:province":"Madrid",
    "wof:name":"Fernandez Martin Maria Isabel",
    "wof:placetype":"venue"
},
  "geometry": {"coordinates":[-3.7412264347,40.3908157349],"type":"Point"}
}