{
  "type": "Feature",
  "properties": {
    "addr:full":"Avda Virgen De Gracia, 91 Caudete Albacete 02660",
    "addr:housenumber":"91",
    "addr:postcode":"02660",
    "addr:street":"Avda Virgen De Gracia",
    "iso:country":"ES",
    "sg:address":"Avda Virgen De Gracia, 91",
    "sg:city":"Caudete",
    "sg:orig_category":"Internados & Ense\u00d1anza Privada",
    "sg:phone":"+34 965 82 70 68",
    "sg:postcode":"02660",
    "sg:province":"Albacete",
    "wof:name":"Colegio Amor De Dios",
    "wof:placetype":"venue"
},
  "geometry": {"coordinates":[-0.9835559726,38.7008743286],"type":"Point"}
}