{
  "type": "Feature",
  "properties": {
    "addr:full":"Calle de Mariano Riquer Wallis, S/n Santa Eulalia Islas Baleares 07840",
    "addr:postcode":"07840",
    "addr:street":"Calle De Mariano Riquer Wallis S / N",
    "iso:country":"ES",
    "sg:address":"Calle de Mariano Riquer Wallis, S/n",
    "sg:city":"Santa Eulalia",
    "sg:orig_category":"Art\u00cdculos De Regalo (al Por Menor)",
    "sg:phone":"+34 971 33 13 16",
    "sg:postcode":"07840",
    "sg:province":"Islas Baleares",
    "wof:name":"Guasch Mari Antonio",
    "wof:placetype":"venue"
},
  "geometry": {"coordinates":[2.9117100239,39.6136398315],"type":"Point"}
}