{
  "type": "Feature",
  "properties": {
    "addr:full":"C/ Joan Canto, 6 Alcoi Alicante 03801",
    "addr:housenumber":"6",
    "addr:postcode":"03801",
    "addr:street":"C / Joan Canto",
    "iso:country":"ES",
    "sg:address":"C/ Joan Canto, 6",
    "sg:city":"Alcoi",
    "sg:orig_category":"Restaurantes",
    "sg:phone":"+34 965 54 24 18",
    "sg:postcode":"03801",
    "sg:province":"Alicante",
    "wof:name":"Tena Torres Diego",
    "wof:placetype":"venue"
},
  "geometry": {"coordinates":[-0.4768399894,38.6955184937],"type":"Point"}
}