{
  "type": "Feature",
  "properties": {
    "iso:country":"ES",
    "sg:address":"Ctr. Cuenca, S/n",
    "sg:city":"Valverde Jucar",
    "sg:orig_category":"Agencias Y Agentes Comerciales, Representantes",
    "sg:phone":"+34 969 20 10 09",
    "sg:postcode":"16100",
    "sg:province":"Cuenca",
    "wof:name":"Garcia Rubio Pedro",
    "wof:placetype":"venue"
},
  "geometry": {"coordinates":[-2.2227609158,39.7200164795],"type":"Point"}
}