{
  "type": "Feature",
  "properties": {
    "iso:country":"ES",
    "sg:address":"Calle de Marques De Canillejas, S/n",
    "sg:city":"Llanes",
    "sg:orig_category":"Fabricaci\u00d3n De Bolsos Y Bolsos De Tela",
    "sg:phone":"+34 985 40 22 29",
    "sg:postcode":"33500",
    "sg:province":"Asturias",
    "wof:name":"Alvarez Garcia Dorotea",
    "wof:placetype":"venue"
},
  "geometry": {"coordinates":[-4.7527527809,43.41954422],"type":"Point"}
}