{
  "type": "Feature",
  "properties": {
    "iso:country":"ES",
    "sg:address":"Rua San Lazaro (de), 5",
    "sg:city":"Santiago De Compostela",
    "sg:orig_category":"Frutas Y Legumbres Frescas (al Por Mayor)",
    "sg:phone":"+34 981 58 67 51",
    "sg:postcode":"15703",
    "sg:province":"La Coru\u00f1a",
    "wof:name":"Gomez Ramos Antonio",
    "wof:placetype":"venue"
},
  "geometry": {"coordinates":[-8.5208263397,42.8870429993],"type":"Point"}
}