{
  "type": "Feature",
  "properties": {
    "iso:country":"ES",
    "sg:address":"Av Cardenal Tarancon, 15",
    "sg:city":"Solsona",
    "sg:orig_category":"Producci\u00d3n, Comercio De Cereales",
    "sg:phone":"+34 973 48 13 54",
    "sg:postcode":"25280",
    "sg:province":"Lleida",
    "wof:name":"Calcoll 1935 Solsona S.l.",
    "wof:placetype":"venue"
},
  "geometry": {"coordinates":[1.5206480026,41.9950942993],"type":"Point"}
}