{
  "type": "Feature",
  "properties": {
    "iso:country":"ES",
    "sg:address":"Casas Nuevas, 2",
    "sg:city":"Vezdemarban",
    "sg:orig_category":"Construcci\u00d3n De Edificios Residenciales Y No Residenciales",
    "sg:phone":"+34 980 69 52 50",
    "sg:postcode":"49840",
    "sg:province":"Zamora",
    "wof:name":"Alfageme Gutierrez Francisco",
    "wof:placetype":"venue"
},
  "geometry": {"coordinates":[-5.3625516891,41.6656532288],"type":"Point"}
}