{
  "type": "Feature",
  "properties": {
    "iso:country":"ES",
    "sg:address":"Calle de Panaderos, 2",
    "sg:city":"Valladolid",
    "sg:orig_category":"Panader\u00cdas, Panader\u00cdas",
    "sg:phone":"+34 983 30 81 89",
    "sg:postcode":"47004",
    "sg:province":"Valladolid",
    "wof:name":"Zorita Simon Jose Luis",
    "wof:placetype":"venue"
},
  "geometry": {"coordinates":[-4.7242131233,41.6483459473],"type":"Point"}
}