{
  "type": "Feature",
  "properties": {
    "addr:full":"Calle de Juan Alvarez Mendizabal, 51 Madrid Madrid 28008",
    "addr:housenumber":"51",
    "addr:postcode":"madrid;28008",
    "addr:street":"Calle De Juan Alvarez Mendizabal",
    "iso:country":"ES",
    "sg:address":"Calle de Juan Alvarez Mendizabal, 51",
    "sg:city":"Madrid",
    "sg:orig_category":"M\u00c9dicos: Psiquiatr\u00cda",
    "sg:phone":"+34 915 48 35 16",
    "sg:postcode":"28008",
    "sg:province":"Madrid",
    "wof:name":"Blanco Caravaca Felix",
    "wof:placetype":"venue"
},
  "geometry": {"coordinates":[-3.7175440788,40.4274406433],"type":"Point"}
}