{
  "type": "Feature",
  "properties": {
    "iso:country":"ES",
    "sg:address":"Rbla General Franco, 3",
    "sg:city":"Santa Cruz De Tenerife",
    "sg:orig_category":"Moda",
    "sg:phone":"+34 922 28 83 79",
    "sg:postcode":"38006",
    "sg:province":"Santa Cruz De Tenerife",
    "wof:name":"Ramos Fernandez Antonio M",
    "wof:placetype":"venue"
},
  "geometry": {"coordinates":[-16.2612533569,28.4683113098],"type":"Point"}
}