{
  "type": "Feature",
  "properties": {
    "addr:full":"Calle de Barriada, S/n Cubo De Benavente Zamora 49327",
    "addr:housenumber":"s",
    "addr:postcode":"49327",
    "addr:street":"Calle De Barriada;/ N Cubo De Benavente Zamora",
    "iso:country":"ES",
    "sg:address":"Calle de Barriada, S/n",
    "sg:city":"Cubo De Benavente",
    "sg:orig_category":"Alimentaci\u00d3n General (al Por Menor)",
    "sg:phone":"+34 980 64 56 19",
    "sg:postcode":"49327",
    "sg:province":"Zamora",
    "wof:name":"Andres Lopez Ascension",
    "wof:placetype":"venue"
},
  "geometry": {"coordinates":[-6.163693428,42.1252479553],"type":"Point"}
}