{
  "type": "Feature",
  "properties": {
    "iso:country":"ES",
    "sg:address":"Barrio Tejares, S/n",
    "sg:city":"Tejares Fuentidue\u00f1a",
    "sg:orig_category":"Cr\u00cda De Animales",
    "sg:phone":"+34 921 12 17 93",
    "sg:postcode":"40314",
    "sg:province":"Segovia",
    "wof:name":"Josvi C.b.",
    "wof:placetype":"venue"
},
  "geometry": {"coordinates":[-3.9804477692,41.4425239563],"type":"Point"}
}