{
  "type": "Feature",
  "properties": {
    "addr:full":"L. Bravo, 26 Villalonquejar Burgos 09001",
    "addr:housenumber":"26",
    "addr:postcode":"09001",
    "addr:street":"L. Bravo",
    "iso:country":"ES",
    "sg:address":"L. Bravo, 26",
    "sg:city":"Villalonquejar",
    "sg:orig_category":"Estudios, Instalaci\u00d3n De Climatizaci\u00d3n",
    "sg:phone":"+34 947 29 88 80",
    "sg:postcode":"09001",
    "sg:province":"Burgos",
    "wof:name":"Ifrinor Frio Y Clima S.l.l.",
    "wof:placetype":"venue"
},
  "geometry": {"coordinates":[-3.7314391136,42.3709831238],"type":"Point"}
}