{
  "type": "Feature",
  "properties": {
    "iso:country":"ES",
    "sg:address":"Pase Direccion, 117",
    "sg:city":"Madrid",
    "sg:orig_category":"Empresas De Carpinter\u00cda",
    "sg:phone":"+34 913 11 52 69",
    "sg:postcode":"28039",
    "sg:province":"Madrid",
    "wof:name":"Alumundi S.l.",
    "wof:placetype":"venue"
},
  "geometry": {"coordinates":[-3.7063019276,40.4617004395],"type":"Point"}
}