{
  "type": "Feature",
  "properties": {
    "addr:full":"Afores, 1 La Senia Tarragona 43560",
    "addr:housenumber":"1",
    "addr:postcode":"43560",
    "addr:street":"Afores;La Senia",
    "iso:country":"ES",
    "sg:address":"Afores, 1",
    "sg:city":"La Senia",
    "sg:orig_category":"Fabricaci\u00d3n De Muebles",
    "sg:phone":"+34 977 71 38 70",
    "sg:postcode":"43560",
    "sg:province":"Tarragona",
    "sg:website":"www.tobisamuebles.com",
    "wof:name":"Tobisa Fabrica De Muebles S.l.",
    "wof:placetype":"venue"
},
  "geometry": {"coordinates":[0.284525007,40.63306427],"type":"Point"}
}