{
  "type": "Feature",
  "properties": {
    "iso:country":"ES",
    "sg:address":"Rua Numero 8, S/n",
    "sg:city":"Poligono Industrial",
    "sg:orig_category":"Transporte En General",
    "sg:phone":"+34 988 24 76 14",
    "sg:postcode":"32901",
    "sg:province":"Ourense",
    "wof:name":"Marra Santana Antonio",
    "wof:placetype":"venue"
},
  "geometry": {"coordinates":[-7.8334488869,42.2905006409],"type":"Point"}
}