{
  "type": "Feature",
  "properties": {
    "iso:country":"ES",
    "sg:address":"Avgd Del Cami Nou, 227",
    "sg:city":"Xirivella",
    "sg:orig_category":"Fabricaci\u00d3n De Enlosados, Soler\u00cdas",
    "sg:phone":"+34 963 83 14 07",
    "sg:postcode":"46950",
    "sg:province":"Valencia",
    "wof:name":"Azulejos Chaparro Imperial S.l.",
    "wof:placetype":"venue"
},
  "geometry": {"coordinates":[-0.4277937114,39.4666862488],"type":"Point"}
}