{
  "type": "Feature",
  "properties": {
    "addr:full":"Calle de Caserio Ibarre, S/n San Vicente De Barakaldo Vizcaya 48903",
    "addr:housenumber":"s / n",
    "addr:postcode":"48903",
    "addr:street":"Calle De Caserio Ibarre",
    "iso:country":"ES",
    "sg:address":"Calle de Caserio Ibarre, S/n",
    "sg:city":"San Vicente De Barakaldo",
    "sg:orig_category":"Negocio De Madera",
    "sg:phone":"+34 944 82 09 33",
    "sg:postcode":"48903",
    "sg:province":"Vizcaya",
    "wof:name":"Maderas Y Puertas Marquina S.l.",
    "wof:placetype":"venue"
},
  "geometry": {"coordinates":[-2.9822225571,43.2905387878],"type":"Point"}
}