{
  "type": "Feature",
  "properties": {
    "addr:full":"Rua Progreso, 36 Vigo Pontevedra 36202",
    "addr:housenumber":"36",
    "addr:postcode":"36202",
    "addr:street":"Rua Progreso",
    "iso:country":"ES",
    "sg:address":"Rua Progreso, 36",
    "sg:city":"Vigo",
    "sg:orig_category":"Inmobiliaria (agencias)",
    "sg:phone":"+34 986 43 68 00",
    "sg:postcode":"36202",
    "sg:province":"Pontevedra",
    "wof:name":"Edificaciones Poligono De Balaidos S. A.",
    "wof:placetype":"venue"
},
  "geometry": {"coordinates":[-8.7213230133,42.2353134155],"type":"Point"}
}