{
  "type": "Feature",
  "properties": {
    "iso:country":"ES",
    "sg:address":"Ponferrada-la Espina, S/n",
    "sg:city":"Villablino",
    "sg:orig_category":"Agentes, Concesionarios Y Sucursales De Veh\u00cdculos",
    "sg:phone":"+34 987 47 13 51",
    "sg:postcode":"24100",
    "sg:province":"Le\u00f3n",
    "wof:name":"Talleres Rafael Laiz Sl",
    "wof:placetype":"venue"
},
  "geometry": {"coordinates":[-6.3228092194,42.9407958984],"type":"Point"}
}