{
  "type": "Feature",
  "properties": {
    "addr:full":"Carrer de Villarroel, 15 Barcelona Barcelona 08011",
    "addr:housenumber":"15",
    "addr:postcode":"08011",
    "addr:street":"Carrer De Villarroel",
    "iso:country":"ES",
    "sg:address":"Carrer de Villarroel, 15",
    "sg:city":"Barcelona",
    "sg:orig_category":"Abogados",
    "sg:phone":"+34 933 25 14 22",
    "sg:postcode":"08011",
    "sg:province":"Barcelona",
    "wof:name":"Buruaga Puertas Vicente",
    "wof:placetype":"venue"
},
  "geometry": {"coordinates":[2.1622309685,41.3808937073],"type":"Point"}
}