{
  "type": "Feature",
  "properties": {
    "addr:full":"Av Can Boada Del Pi, 3 Terrassa Barcelona 08225",
    "addr:housenumber":"3",
    "addr:postcode":"08225",
    "addr:street":"Av;Pi",
    "iso:country":"ES",
    "sg:address":"Av Can Boada Del Pi, 3",
    "sg:city":"Terrassa",
    "sg:orig_category":"Centros De Educaci\u00d3n Especial",
    "sg:phone":"+34 937 88 73 94",
    "sg:postcode":"08225",
    "sg:province":"Barcelona",
    "wof:name":"Patronat Municipal D'educacio De Terrassa",
    "wof:placetype":"venue"
},
  "geometry": {"coordinates":[1.9988019466,41.5715827942],"type":"Point"}
}