{
  "type": "Feature",
  "properties": {
    "iso:country":"ES",
    "sg:address":"Carrer de Muntaner, 476",
    "sg:city":"Barcelona",
    "sg:orig_category":"Centros Empresariales",
    "sg:phone":"+34 932 02 09 01",
    "sg:postcode":"08006",
    "sg:province":"Barcelona",
    "sg:website":"www.groupagm.com",
    "wof:name":"Assets General Management S.l.",
    "wof:placetype":"venue"
},
  "geometry": {"coordinates":[2.1384992599,41.4024124146],"type":"Point"}
}