{
  "type": "Feature",
  "properties": {
    "iso:country":"ES",
    "sg:address":"Avda Encarnacion (de La), S/n",
    "sg:city":"Herencia",
    "sg:orig_category":"Centros De Educaci\u00d3n Especial",
    "sg:phone":"+34 926 57 34 29",
    "sg:postcode":"13640",
    "sg:province":"Ciudad Real",
    "wof:name":"Colegio Publico Carrasco Alcalde",
    "wof:placetype":"venue"
},
  "geometry": {"coordinates":[-3.3527989388,39.3737716675],"type":"Point"}
}