{
  "type": "Feature",
  "properties": {
    "iso:country":"ES",
    "sg:address":"Calle de Bellido, 1",
    "sg:city":"Jaca",
    "sg:orig_category":"Reciclaje, Tratamiento De Tejidos",
    "sg:phone":"+34 974 36 44 53",
    "sg:postcode":"22700",
    "sg:province":"Huesca",
    "wof:name":"Betran Izuel Angela",
    "wof:placetype":"venue"
},
  "geometry": {"coordinates":[-0.5477290154,42.5695991516],"type":"Point"}
}