{
  "type": "Feature",
  "properties": {
    "iso:country":"ES",
    "sg:address":"Calle de Goya, 25",
    "sg:city":"Cordoba",
    "sg:orig_category":"Bisuteros (fabricaci\u00d3n, Al Por Mayor)",
    "sg:phone":"+34 957 27 31 28",
    "sg:postcode":"14006",
    "sg:province":"C\u00f3rdoba",
    "wof:name":"Hermanos Raya Martinez Cdab.",
    "wof:placetype":"venue"
},
  "geometry": {"coordinates":[-4.7872133255,37.8932685852],"type":"Point"}
}