{
  "type": "Feature",
  "properties": {
    "addr:full":"Pase Victoria (de La), 31 Cordoba C\u00f3rdoba 14004",
    "addr:postcode":"14004",
    "addr:street":"Co\u0301Rdoba",
    "iso:country":"ES",
    "sg:address":"Pase Victoria (de La), 31",
    "sg:city":"Cordoba",
    "sg:orig_category":"M\u00c9dicos: Otorrinolaringolog\u00cda",
    "sg:phone":"+34 957 29 03 50",
    "sg:postcode":"14004",
    "sg:province":"C\u00f3rdoba",
    "wof:name":"Tortosa Lorenzo Joaquin Ignacio",
    "wof:placetype":"venue"
},
  "geometry": {"coordinates":[-4.784430027,37.8837814331],"type":"Point"}
}