{
  "type": "Feature",
  "properties": {
    "iso:country":"ES",
    "sg:address":"Calle de Ronda De Capuchinos, 1",
    "sg:city":"Sevilla",
    "sg:orig_category":"Doctores En Medicina",
    "sg:phone":"+34 954 35 84 01",
    "sg:postcode":"41009",
    "sg:province":"Sevilla",
    "wof:name":"Mata Maderuelo Francisco",
    "wof:placetype":"venue"
},
  "geometry": {"coordinates":[-5.9842329025,37.4000968933],"type":"Point"}
}