{
  "type": "Feature",
  "properties": {
    "addr:full":"Calle de Recodos, 6 Alcorcon Madrid 28921",
    "addr:housenumber":"6",
    "addr:postcode":"28921",
    "addr:street":"Calle De Recodos",
    "iso:country":"ES",
    "sg:address":"Calle de Recodos, 6",
    "sg:city":"Alcorcon",
    "sg:orig_category":"Mercer\u00cda, Lencer\u00cda (al Por Menor)",
    "sg:phone":"+34 916 43 14 05",
    "sg:postcode":"28921",
    "sg:province":"Madrid",
    "wof:name":"Pedro Pascual David De",
    "wof:placetype":"venue"
},
  "geometry": {"coordinates":[-3.8269250393,40.3451423645],"type":"Point"}
}