{
  "type": "Feature",
  "properties": {
    "iso:country":"ES",
    "sg:address":"Calle de Amancio Renes, 5",
    "sg:city":"Dos Hermanas",
    "sg:orig_category":"Congelados: Productos Alimentarios (fabricaci\u00d3n, Al Por Mayor)",
    "sg:phone":"+34 954 72 12 41",
    "sg:postcode":"41700",
    "sg:province":"Sevilla",
    "wof:name":"Pescavalme S.l.",
    "wof:placetype":"venue"
},
  "geometry": {"coordinates":[-5.9284601212,37.2823982239],"type":"Point"}
}