{
  "type": "Feature",
  "properties": {
    "addr:full":"Carretera Tanxil, 47 Rianxo La Coru\u00f1a 15920",
    "addr:housenumber":"47",
    "addr:postcode":"15920",
    "addr:street":"Carretera Tanxil;La Corun\u0303A",
    "iso:country":"ES",
    "sg:address":"Carretera Tanxil, 47",
    "sg:city":"Rianxo",
    "sg:orig_category":"Molduras, Junquillos, Listones Y Molduras Perforadas",
    "sg:phone":"+34 981 86 04 54",
    "sg:postcode":"15920",
    "sg:province":"La Coru\u00f1a",
    "wof:name":"Bravo Gago Angel",
    "wof:placetype":"venue"
},
  "geometry": {"coordinates":[-8.8172187805,42.6528091431],"type":"Point"}
}