{
  "type": "Feature",
  "properties": {
    "addr:full":"Plaz Alberto Acero, 5 Llodio \u00c1lava 01400",
    "addr:housenumber":"5",
    "addr:postcode":"01400",
    "addr:street":"Acero",
    "iso:country":"ES",
    "sg:address":"Plaz Alberto Acero, 5",
    "sg:city":"Llodio",
    "sg:orig_category":"Molduras, Junquillos, Listones Y Molduras Perforadas",
    "sg:phone":"+34 946 72 10 08",
    "sg:postcode":"01400",
    "sg:province":"\u00c1lava",
    "wof:name":"Perez Amoros Angel",
    "wof:placetype":"venue"
},
  "geometry": {"coordinates":[-2.964247942,43.1413459778],"type":"Point"}
}