{
  "type": "Feature",
  "properties": {
    "addr:full":"Avda Arcos (de), 5 Villamartin C\u00e1diz 11650",
    "addr:housenumber":"5",
    "addr:postcode":"11650",
    "addr:street":"Avda Arcos De;Ca\u0301Diz",
    "iso:country":"ES",
    "sg:address":"Avda Arcos (de), 5",
    "sg:city":"Villamartin",
    "sg:orig_category":"Material Y Herramientas Agr\u00cdcolas",
    "sg:phone":"+34 956 73 15 43",
    "sg:postcode":"11650",
    "sg:province":"C\u00e1diz",
    "wof:name":"Bernal Tinajero Juan",
    "wof:placetype":"venue"
},
  "geometry": {"coordinates":[-5.6490888596,36.8568687439],"type":"Point"}
}