{
  "type": "Feature",
  "properties": {
    "iso:country":"ES",
    "sg:address":"Calle de Martinez Monta\u00d1es, 28",
    "sg:city":"Sevilla",
    "sg:orig_category":"Procuradores",
    "sg:phone":"+34 954 38 13 30",
    "sg:postcode":"41002",
    "sg:province":"Sevilla",
    "wof:name":"Lopez-arza Nu\u00f1ez Miguel",
    "wof:placetype":"venue"
},
  "geometry": {"coordinates":[-5.9973487854,37.3962211609],"type":"Point"}
}