{
  "type": "Feature",
  "properties": {
    "addr:full":"Rua Rio Sil, 57 Carballo La Coru\u00f1a 15100",
    "addr:housenumber":"57",
    "addr:postcode":"15100",
    "addr:street":"Rua Rio Sil;La Corun\u0303A",
    "iso:country":"ES",
    "sg:address":"Rua Rio Sil, 57",
    "sg:city":"Carballo",
    "sg:orig_category":"Librer\u00cdas",
    "sg:phone":"+34 981 70 15 85",
    "sg:postcode":"15100",
    "sg:province":"La Coru\u00f1a",
    "wof:name":"Barral Li\u00f1ares Maria Del Carmen",
    "wof:placetype":"venue"
},
  "geometry": {"coordinates":[-8.6889438629,43.2079353333],"type":"Point"}
}