{
  "type": "Feature",
  "properties": {
    "iso:country":"ES",
    "sg:address":"Calle de San Sebastian, 10",
    "sg:city":"Utiel",
    "sg:orig_category":"Institutos De Belleza",
    "sg:phone":"+34 962 17 01 12",
    "sg:postcode":"46300",
    "sg:province":"Valencia",
    "wof:name":"Perez Ruiz Carmen",
    "wof:placetype":"venue"
},
  "geometry": {"coordinates":[-1.20264709,39.5676727295],"type":"Point"}
}