{
  "type": "Feature",
  "properties": {
    "addr:full":"Calle de Gravina, 76 Fuente Cantos Badajoz 06240",
    "addr:housenumber":"76",
    "addr:postcode":"06240",
    "addr:street":"Calle De Gravina",
    "iso:country":"ES",
    "sg:address":"Calle de Gravina, 76",
    "sg:city":"Fuente Cantos",
    "sg:orig_category":"Agencias Y Agentes Comerciales, Representantes",
    "sg:phone":"+34 924 50 00 15",
    "sg:postcode":"06240",
    "sg:province":"Badajoz",
    "wof:name":"Rodriguez Rosales Antonio",
    "wof:placetype":"venue"
},
  "geometry": {"coordinates":[-6.304336071,38.2498855591],"type":"Point"}
}