{
  "type": "Feature",
  "properties": {
    "iso:country":"ES",
    "sg:address":"Rbla Egara, 182",
    "sg:city":"Terrassa",
    "sg:orig_category":"Cajas De Ahorro",
    "sg:phone":"+34 937 33 68 87",
    "sg:postcode":"08221",
    "sg:province":"Barcelona",
    "sg:website":"www.d'estalvis.es",
    "wof:name":"Caixa D'estalvis Sabadell",
    "wof:placetype":"venue"
},
  "geometry": {"coordinates":[2.0104300976,41.5638504028],"type":"Point"}
}