{
  "type": "Feature",
  "properties": {
    "iso:country":"ES",
    "sg:address":"Calle de Rey Carlos Iii, 9",
    "sg:city":"Aguilas",
    "sg:orig_category":"Arquitectos",
    "sg:phone":"+34 968 41 18 34",
    "sg:postcode":"30880",
    "sg:province":"Murcia",
    "wof:name":"Gutierrez Pulido Francisco",
    "wof:placetype":"venue"
},
  "geometry": {"coordinates":[-1.584463954,37.4039039612],"type":"Point"}
}