{
  "type": "Feature",
  "properties": {
    "addr:full":"Carrer de Sant Joan Baptista De La Salle, 30 Manresa Barcelona 08241",
    "addr:housenumber":"30",
    "addr:postcode":"08241",
    "addr:street":"Carrer De Sant Joan Baptista De La Salle",
    "iso:country":"ES",
    "sg:address":"Carrer de Sant Joan Baptista De La Salle, 30",
    "sg:city":"Manresa",
    "sg:orig_category":"Talleres: Ropa A Medida",
    "sg:phone":"+34 938 72 05 78",
    "sg:postcode":"08241",
    "sg:province":"Barcelona",
    "wof:name":"Se\u00d1or 1961 S.l.",
    "wof:placetype":"venue"
},
  "geometry": {"coordinates":[1.825232029,41.7264213562],"type":"Point"}
}