{
  "type": "Feature",
  "properties": {
    "addr:full":"Calle de Desamparados, 6 Vinaros Castell\u00f3n 12500",
    "addr:housenumber":"6",
    "addr:postcode":"12500",
    "addr:street":"Calle De Desamparados",
    "iso:country":"ES",
    "sg:address":"Calle de Desamparados, 6",
    "sg:city":"Vinaros",
    "sg:orig_category":"Agricultores, Agricultores",
    "sg:phone":"+34 964 45 12 60",
    "sg:postcode":"12500",
    "sg:province":"Castell\u00f3n",
    "wof:name":"Fontanet Pla Juan Jose",
    "wof:placetype":"venue"
},
  "geometry": {"coordinates":[0.4742563963,40.4721298218],"type":"Point"}
}