{
  "type": "Feature",
  "properties": {
    "iso:country":"ES",
    "sg:address":"Julian Gayarre, 40",
    "sg:city":"Iru\u00f1a",
    "sg:orig_category":"Impuestos, Tesoro P\u00dablico",
    "sg:phone":"+34 948 15 39 11",
    "sg:postcode":"31005",
    "sg:province":"Navarra",
    "sg:website":"www.remirezperitos.com",
    "wof:name":"Remirez Peritos S.l.",
    "wof:placetype":"venue"
},
  "geometry": {"coordinates":[-1.6394120455,42.8054237366],"type":"Point"}
}