{
  "type": "Feature",
  "properties": {
    "iso:country":"ES",
    "sg:address":"Calle de Camino De Murcia, 73",
    "sg:city":"Cieza",
    "sg:orig_category":"\u00d3ptica: Instrumentos (fabricaci\u00d3n)",
    "sg:phone":"+34 968 76 31 11",
    "sg:postcode":"30530",
    "sg:province":"Murcia",
    "wof:name":"Rolopticas S.l.",
    "wof:placetype":"venue"
},
  "geometry": {"coordinates":[-1.413844347,38.2368812561],"type":"Point"}
}