{
  "type": "Feature",
  "properties": {
    "iso:country":"ES",
    "sg:address":"Calle de Cozar, 14",
    "sg:city":"Baeza",
    "sg:orig_category":"Abogados",
    "sg:phone":"+34 953 74 46 29",
    "sg:postcode":"23440",
    "sg:province":"Ja\u00e9n",
    "wof:name":"Moreno Cornejo Juan Jose",
    "wof:placetype":"venue"
},
  "geometry": {"coordinates":[-3.4669833183,37.9930877686],"type":"Point"}
}