{
  "type": "Feature",
  "properties": {
    "addr:full":"Calle de Doctor Molina Lopez, 1 Iznajar C\u00f3rdoba 14970",
    "addr:housenumber":"1",
    "addr:postcode":"14970",
    "addr:street":"Calle De Doctor Molina Lopez;Co\u0301Rdoba",
    "iso:country":"ES",
    "sg:address":"Calle de Doctor Molina Lopez, 1",
    "sg:city":"Iznajar",
    "sg:orig_category":"Molduras, Junquillos, Listones Y Molduras Perforadas",
    "sg:phone":"+34 957 53 44 82",
    "sg:postcode":"14970",
    "sg:province":"C\u00f3rdoba",
    "wof:name":"Cobo Herrera Teodoro",
    "wof:placetype":"venue"
},
  "geometry": {"coordinates":[-4.3041291237,37.2569160461],"type":"Point"}
}