{
  "type": "Feature",
  "properties": {
    "addr:full":"Carr Baro D'eroles, 9 Lleida Lleida 25008",
    "addr:housenumber":"9",
    "addr:postcode":"25008",
    "addr:street":"Carr Baro D'Eroles",
    "iso:country":"ES",
    "sg:address":"Carr Baro D'eroles, 9",
    "sg:city":"Lleida",
    "sg:orig_category":"Molduras, Junquillos, Listones Y Molduras Perforadas",
    "sg:phone":"+34 973 23 13 21",
    "sg:postcode":"25008",
    "sg:province":"Lleida",
    "wof:name":"Tordecillas Valdivia Isidro",
    "wof:placetype":"venue"
},
  "geometry": {"coordinates":[0.618663013,41.6233634949],"type":"Point"}
}