{
  "type": "Feature",
  "properties": {
    "addr:full":"Carrer de Santiago Rusi\u00d1ol, 1 Palma Islas Baleares 07012",
    "addr:housenumber":"1",
    "addr:postcode":"07012",
    "addr:street":"Carrer De Santiago Rusin\u0303Ol",
    "iso:country":"ES",
    "sg:address":"Carrer de Santiago Rusi\u00d1ol, 1",
    "sg:city":"Palma",
    "sg:orig_category":"Librer\u00cdas",
    "sg:phone":"+34 971 72 54 46",
    "sg:postcode":"07012",
    "sg:province":"Islas Baleares",
    "wof:name":"Apad S.a.",
    "wof:placetype":"venue"
},
  "geometry": {"coordinates":[2.6484949589,39.5760726929],"type":"Point"}
}