{
  "type": "Feature",
  "properties": {
    "iso:country":"ES",
    "sg:address":"Cmno Cordoba, Km. 0049,0",
    "sg:city":"Ca\u00e7ete De Las Torres",
    "sg:orig_category":"Chapister\u00cda",
    "sg:phone":"+34 957 18 36 11",
    "sg:postcode":"14660",
    "sg:province":"C\u00f3rdoba",
    "wof:name":"Gonzalez Gonzalez Jose",
    "wof:placetype":"venue"
},
  "geometry": {"coordinates":[-4.7791519165,37.884727478],"type":"Point"}
}