{
  "type": "Feature",
  "properties": {
    "iso:country":"ES",
    "sg:address":"Calle de Lauaxeta Olerkari, 33",
    "sg:city":"Mungia",
    "sg:orig_category":"Centros M\u00c9dicos Y Sociales, Dispensarios",
    "sg:phone":"+34 946 15 65 37",
    "sg:postcode":"48100",
    "sg:province":"Vizcaya",
    "wof:name":"Centro Medico Urig\u00dcen",
    "wof:placetype":"venue"
},
  "geometry": {"coordinates":[-2.8518009186,43.3571853638],"type":"Point"}
}