{
  "type": "Feature",
  "properties": {
    "addr:full":"Calle de Vicente Blasco Iba\u00d1ez, 107 Torrevieja Alicante 03180",
    "addr:housenumber":"107",
    "addr:postcode":"03180",
    "addr:street":"Calle De Vicente Blasco Iban\u0303Ez",
    "iso:country":"ES",
    "sg:address":"Calle de Vicente Blasco Iba\u00d1ez, 107",
    "sg:city":"Torrevieja",
    "sg:orig_category":"Muebles, Minoristas",
    "sg:phone":"+34 966 70 83 97",
    "sg:postcode":"03180",
    "sg:province":"Alicante",
    "wof:name":"Noi Mobiliario Europeo S.l.",
    "wof:placetype":"venue"
},
  "geometry": {"coordinates":[-0.6739919782,37.9793624878],"type":"Point"}
}