{
  "type": "Feature",
  "properties": {
    "addr:full":"Calle de Covadonga, 23 Lugo De Llanera Asturias 33690",
    "addr:housenumber":"23",
    "addr:postcode":"33690",
    "addr:street":"Calle De Covadonga",
    "iso:country":"ES",
    "sg:address":"Calle de Covadonga, 23",
    "sg:city":"Lugo De Llanera",
    "sg:orig_category":"Estudios De Grabaci\u00d3n Sonora",
    "sg:phone":"+34 985 77 14 87",
    "sg:postcode":"33690",
    "sg:province":"Asturias",
    "sg:website":"www.lunaestudios.com",
    "wof:name":"Junquera Ferreira Jose Roberto",
    "wof:placetype":"venue"
},
  "geometry": {"coordinates":[-5.8177218437,43.4435539246],"type":"Point"}
}