{
  "type": "Feature",
  "properties": {
    "addr:full":"Ctra Esplugues, 32 Fatjo Barcelona 08940",
    "addr:housenumber":"32",
    "addr:postcode":"08940",
    "addr:street":"Ctra Esplugues;Barcelona",
    "iso:country":"ES",
    "sg:address":"Ctra Esplugues, 32",
    "sg:city":"Fatjo",
    "sg:orig_category":"Farmacias",
    "sg:phone":"+34 933 77 36 48",
    "sg:postcode":"08940",
    "sg:province":"Barcelona",
    "wof:name":"Burdeus Reverter Cristina",
    "wof:placetype":"venue"
},
  "geometry": {"coordinates":[2.0740599632,41.356880188],"type":"Point"}
}