{
  "type": "Feature",
  "properties": {
    "iso:country":"ES",
    "sg:address":"Avda Virgen De Fatima (de), 45",
    "sg:city":"Cordoba",
    "sg:orig_category":"Inmobiliaria (agencias)",
    "sg:phone":"+34 957 43 33 33",
    "sg:postcode":"14014",
    "sg:province":"C\u00f3rdoba",
    "sg:website":"www.inmobiliariabarin.com",
    "wof:name":"Barin Centro Inmobiliario S.l.",
    "wof:placetype":"venue"
},
  "geometry": {"coordinates":[-4.7540688515,37.8979721069],"type":"Point"}
}