{
  "type": "Feature",
  "properties": {
    "iso:country":"ES",
    "sg:address":"Rua Cuba, 25",
    "sg:city":"Vigo",
    "sg:orig_category":"Institutos De Belleza",
    "sg:phone":"+34 986 41 46 48",
    "sg:postcode":"36204",
    "sg:province":"Pontevedra",
    "wof:name":"Centro De Belleza Popea S.l.",
    "wof:placetype":"venue"
},
  "geometry": {"coordinates":[-8.7166557312,42.2323646545],"type":"Point"}
}