{
  "type": "Feature",
  "properties": {
    "iso:country":"ES",
    "sg:address":"Leyre-leire Kalea, 16",
    "sg:city":"Iru\u00f1a",
    "sg:orig_category":"Perfumer\u00cda (al Por Menor)",
    "sg:phone":"+34 948 21 33 14",
    "sg:postcode":"31002",
    "sg:province":"Navarra",
    "wof:name":"Perfumeria Salvia S.l.",
    "wof:placetype":"venue"
},
  "geometry": {"coordinates":[-1.6402050257,42.8136367798],"type":"Point"}
}