{
  "type": "Feature",
  "properties": {
    "addr:full":"Carrer de Salva, 89 Barcelona Barcelona 08004",
    "addr:housenumber":"89",
    "addr:postcode":"08004",
    "addr:street":"Carrer De Salva",
    "iso:country":"ES",
    "sg:address":"Carrer de Salva, 89",
    "sg:city":"Barcelona",
    "sg:orig_category":"Agencias Y Asesores De Publicidad",
    "sg:phone":"+34 933 19 97 98",
    "sg:postcode":"08004",
    "sg:province":"Barcelona",
    "sg:website":"www.sinocomunicacion.com",
    "wof:name":"Sino Comunicacio Y Publicitat S.l.",
    "wof:placetype":"venue"
},
  "geometry": {"coordinates":[2.1650850773,41.3713111877],"type":"Point"}
}