{
  "type": "Feature",
  "properties": {
    "iso:country":"ES",
    "sg:address":"Calle de Ronda De Capuchinos, 31",
    "sg:city":"Sevilla",
    "sg:orig_category":"Supermercados Y Hipermercados",
    "sg:phone":"+34 954 98 91 22",
    "sg:postcode":"41008",
    "sg:province":"Sevilla",
    "wof:name":"Tiendas De Conveniencia S.a.",
    "wof:placetype":"venue"
},
  "geometry": {"coordinates":[-5.981552124,37.3982925415],"type":"Point"}
}