{
  "type": "Feature",
  "properties": {
    "addr:full":"Calle de Askao, 2 Bilbao Vizcaya 48005",
    "addr:housenumber":"2",
    "addr:postcode":"48005",
    "addr:street":"Calle De Askao",
    "iso:country":"ES",
    "sg:address":"Calle de Askao, 2",
    "sg:city":"Bilbao",
    "sg:orig_category":"Molduras, Junquillos, Listones Y Molduras Perforadas",
    "sg:phone":"+34 944 15 07 52",
    "sg:postcode":"48005",
    "sg:province":"Vizcaya",
    "wof:name":"Gonzalez Valle Enrique",
    "wof:placetype":"venue"
},
  "geometry": {"coordinates":[-2.9220542908,43.2594528198],"type":"Point"}
}