{
  "type": "Feature",
  "properties": {
    "iso:country":"ES",
    "sg:address":"Calle de Buenavista, 9",
    "sg:city":"Majadahonda",
    "sg:orig_category":"Flores Y Plantas Naturales (al Por Mayor)",
    "sg:phone":"+34 916 34 07 01",
    "sg:postcode":"28220",
    "sg:province":"Madrid",
    "wof:name":"Montero Salgado Alberto",
    "wof:placetype":"venue"
},
  "geometry": {"coordinates":[-3.8708674908,40.4718284607],"type":"Point"}
}