{
  "type": "Feature",
  "properties": {
    "addr:full":"Rua Rosalia De Castro, 50 Vigo Pontevedra 36201",
    "addr:housenumber":"50",
    "addr:postcode":"36201",
    "addr:street":"Rua Rosalia De Castro",
    "iso:country":"ES",
    "sg:address":"Rua Rosalia De Castro, 50",
    "sg:city":"Vigo",
    "sg:orig_category":"Institutos De Belleza",
    "sg:phone":"+34 986 22 98 95",
    "sg:postcode":"36201",
    "sg:province":"Pontevedra",
    "wof:name":"Helga Rivera S.l.",
    "wof:placetype":"venue"
},
  "geometry": {"coordinates":[-8.7150373459,42.237651825],"type":"Point"}
}