{
  "type": "Feature",
  "properties": {
    "iso:country":"ES",
    "sg:address":"Ctra Sagunto-burgos, Km. 0164,5",
    "sg:city":"Villafranca Campo",
    "sg:orig_category":"Distribuci\u00d3n De Petr\u00d3leo Y Derivados",
    "sg:phone":"+34 978 86 33 21",
    "sg:postcode":"44394",
    "sg:province":"Teruel",
    "wof:name":"Cedipsa Compa\u00d1ia Espa\u00d1ola Distribuidora De Petroleos S.a.",
    "wof:placetype":"venue"
},
  "geometry": {"coordinates":[-1.3459689617,40.6945953369],"type":"Point"}
}