{
  "type": "Feature",
  "properties": {
    "addr:full":"Ptge Pau, 8 Barcelona Barcelona 08002",
    "addr:housenumber":"8",
    "addr:postcode":"08002",
    "addr:street":"Ptge Pau",
    "iso:country":"ES",
    "sg:address":"Ptge Pau, 8",
    "sg:city":"Barcelona",
    "sg:orig_category":"Arquitectos",
    "sg:phone":"+34 933 18 32 83",
    "sg:postcode":"08002",
    "sg:province":"Barcelona",
    "wof:name":"Genis Soler Arquitectes, Scp",
    "wof:placetype":"venue"
},
  "geometry": {"coordinates":[2.1771190166,41.3782844543],"type":"Point"}
}