{
  "type": "Feature",
  "properties": {
    "iso:country":"ES",
    "sg:address":"Ptda Colina Del Sol, 4",
    "sg:city":"San Carlos",
    "sg:orig_category":"Agencias Y Agentes Comerciales, Representantes",
    "sg:phone":"+34 965 87 52 48",
    "sg:postcode":"03710",
    "sg:province":"Alicante",
    "wof:name":"Edward Cowtan Albert",
    "wof:placetype":"venue"
},
  "geometry": {"coordinates":[0.0535200015,38.6515808105],"type":"Point"}
}