{
  "type": "Feature",
  "properties": {
    "iso:country":"ES",
    "sg:address":"Finc Prado Del Arca, 184",
    "sg:city":"Pepino",
    "sg:orig_category":"Alimentaci\u00d3n Animal (fabricaci\u00d3n, Al Por Mayor)",
    "sg:phone":"+34 925 81 24 74",
    "sg:postcode":"45638",
    "sg:province":"Toledo",
    "wof:name":"Ramos Moreno Ana Rosa",
    "wof:placetype":"venue"
},
  "geometry": {"coordinates":[-4.803000927,40.0316200256],"type":"Point"}
}