{
  "type": "Feature",
  "properties": {
    "addr:full":"Calle de Heras, 1 Pozuelo De Alarcon Madrid 28224",
    "addr:housenumber":"1",
    "addr:postcode":"28224",
    "addr:street":"Calle De Heras",
    "iso:country":"ES",
    "sg:address":"Calle de Heras, 1",
    "sg:city":"Pozuelo De Alarcon",
    "sg:orig_category":"Abogados",
    "sg:phone":"+34 913 51 80 80",
    "sg:postcode":"28224",
    "sg:province":"Madrid",
    "wof:name":"Garrido Garcia Cesar",
    "wof:placetype":"venue"
},
  "geometry": {"coordinates":[-3.7995231152,40.4466094971],"type":"Point"}
}