{
  "type": "Feature",
  "properties": {
    "iso:country":"ES",
    "sg:address":"Media Luna, 2",
    "sg:city":"Iru\u00f1a",
    "sg:orig_category":"Transportes Por V\u00cdas Navegables",
    "sg:phone":"+34 948 22 94 59",
    "sg:postcode":"31002",
    "sg:province":"Navarra",
    "wof:name":"La Muguiroarra S.l.",
    "wof:placetype":"venue"
},
  "geometry": {"coordinates":[-1.6350073814,42.8145484924],"type":"Point"}
}