{
  "type": "Feature",
  "properties": {
    "addr:full":"Ca Tajonar, Km. 0002,0 Mutiloabeiti Navarra 31192",
    "addr:postcode":"31192",
    "addr:street":"Ca Tajonar Km. 0002,0",
    "iso:country":"ES",
    "sg:address":"Ca Tajonar, Km. 0002,0",
    "sg:city":"Mutiloabeiti",
    "sg:orig_category":"Muebles Y Accesorios Para Cocinas Y Cuartos De Ba\u00d1o (al Por Menor)",
    "sg:phone":"+34 948 23 90 65",
    "sg:postcode":"31192",
    "sg:province":"Navarra",
    "wof:name":"Montejo Ceramicas S.a.",
    "wof:placetype":"venue"
},
  "geometry": {"coordinates":[-1.6151809692,42.7892303467],"type":"Point"}
}