{
  "type": "Feature",
  "properties": {
    "addr:full":"Avda Gijon, 92 Valladolid Valladolid 47009",
    "addr:housenumber":"92",
    "addr:postcode":"47009",
    "addr:street":"Avda Gijon",
    "iso:country":"ES",
    "sg:address":"Avda Gijon, 92",
    "sg:city":"Valladolid",
    "sg:orig_category":"Agentes, Concesionarios Y Sucursales De Veh\u00cdculos",
    "sg:phone":"+34 983 34 02 12",
    "sg:postcode":"47009",
    "sg:province":"Valladolid",
    "wof:name":"Nissan Motor Espa\u00d1a S.a.",
    "wof:placetype":"venue"
},
  "geometry": {"coordinates":[-4.7545809746,41.6607475281],"type":"Point"}
}