{
  "type": "Feature",
  "properties": {
    "addr:full":"Carrer de Sant Oleguer, 75 Sabadell Barcelona 08202",
    "addr:housenumber":"75",
    "addr:postcode":"08202",
    "addr:street":"Carrer De Sant Oleguer",
    "iso:country":"ES",
    "sg:address":"Carrer de Sant Oleguer, 75",
    "sg:city":"Sabadell",
    "sg:orig_category":"Teatros Y Salas De Espect\u00c1culos",
    "sg:phone":"+34 937 45 05 15",
    "sg:postcode":"08202",
    "sg:province":"Barcelona",
    "wof:name":"Ajuntament De Sabadell",
    "wof:placetype":"venue"
},
  "geometry": {"coordinates":[2.1124341488,41.5419311523],"type":"Point"}
}