{
  "type": "Feature",
  "properties": {
    "iso:country":"ES",
    "sg:address":"Avda Facultad De Veterinaria, 35",
    "sg:city":"Le\u00f3n",
    "sg:orig_category":"Comercio De Piezas De Recambio Y De Accesorios De Veh\u00cdculos, Veh\u00cdculos Industriales",
    "sg:phone":"+34 987 20 13 11",
    "sg:postcode":"24004",
    "sg:province":"Le\u00f3n",
    "wof:name":"Gobartt Amor Fernando",
    "wof:placetype":"venue"
},
  "geometry": {"coordinates":[-5.5748848915,42.5911445618],"type":"Point"}
}