{
  "type": "Feature",
  "properties": {
    "addr:full":"Ctra Sabadell, 18 Rubi Barcelona 08191",
    "addr:housenumber":"18",
    "addr:postcode":"08191",
    "addr:street":"Ctra Sabadell",
    "iso:country":"ES",
    "sg:address":"Ctra Sabadell, 18",
    "sg:city":"Rubi",
    "sg:orig_category":"Confecci\u00d3n (fabricaci\u00d3n, Al Por Mayor)",
    "sg:phone":"+34 935 88 65 16",
    "sg:postcode":"08191",
    "sg:province":"Barcelona",
    "wof:name":"Confeccion Convimar S.l.",
    "wof:placetype":"venue"
},
  "geometry": {"coordinates":[2.0323150158,41.4975128174],"type":"Point"}
}