{
  "type": "Feature",
  "properties": {
    "iso:country":"ES",
    "sg:address":"Praz Galicia, 7",
    "sg:city":"Estrada",
    "sg:orig_category":"Autob\u00das (explotaci\u00d3n Y Servicios De)",
    "sg:phone":"+34 986 57 00 18",
    "sg:postcode":"36680",
    "sg:province":"Pontevedra",
    "wof:name":"Donado Bueno Gaspar",
    "wof:placetype":"venue"
},
  "geometry": {"coordinates":[-8.4910736084,42.6887664795],"type":"Point"}
}