{
  "type": "Feature",
  "properties": {
    "iso:country":"ES",
    "sg:address":"Ctra Santpedor, 29",
    "sg:city":"Manresa",
    "sg:orig_category":"Mantenimiento Y Reparaci\u00d3n De Motores Industriales",
    "sg:phone":"+34 938 73 20 73",
    "sg:postcode":"08242",
    "sg:province":"Barcelona",
    "wof:name":"Bobinatges Manresas.l.",
    "wof:placetype":"venue"
},
  "geometry": {"coordinates":[1.8313310146,41.7313728333],"type":"Point"}
}