{
  "type": "Feature",
  "properties": {
    "addr:full":"Avda Antonio Machado, 92 Peal Becerro Ja\u00e9n 23460",
    "addr:housenumber":"92",
    "addr:postcode":"23460",
    "addr:street":"Avda Antonio Machado",
    "iso:country":"ES",
    "sg:address":"Avda Antonio Machado, 92",
    "sg:city":"Peal Becerro",
    "sg:orig_category":"Bisuter\u00cda, Joyer\u00cda, Relojer\u00cda (al Por Menor)",
    "sg:phone":"+34 953 71 62 33",
    "sg:postcode":"23460",
    "sg:province":"Ja\u00e9n",
    "wof:name":"Martinez Garcia Agapito",
    "wof:placetype":"venue"
},
  "geometry": {"coordinates":[-3.126749754,37.9136047363],"type":"Point"}
}