{
  "type": "Feature",
  "properties": {
    "iso:country":"ES",
    "sg:address":"Calle de Luis Velasco, 7",
    "sg:city":"Playa De Arinaga",
    "sg:orig_category":"Mercer\u00cda, Lencer\u00cda (al Por Menor)",
    "sg:phone":"+34 928 18 00 74",
    "sg:postcode":"35118",
    "sg:province":"Las Palmas",
    "wof:name":"Abrante Trujillo Cristobal",
    "wof:placetype":"venue"
},
  "geometry": {"coordinates":[-15.39277,27.855799],"type":"Point"}
}