{
  "type": "Feature",
  "properties": {
    "addr:full":"Rua Mestre Chane, 7 Vigo Pontevedra 36206",
    "addr:housenumber":"7",
    "addr:postcode":"36206",
    "addr:street":"Rua Mestre Chane",
    "iso:country":"ES",
    "sg:address":"Rua Mestre Chane, 7",
    "sg:city":"Vigo",
    "sg:orig_category":"Contenedores (mercanc\u00cdas)",
    "sg:phone":"+34 986 37 39 40",
    "sg:postcode":"36206",
    "sg:province":"Pontevedra",
    "wof:name":"Acciona Forwarding S.a.",
    "wof:placetype":"venue"
},
  "geometry": {"coordinates":[-8.7040681839,42.2395553589],"type":"Point"}
}