{
  "type": "Feature",
  "properties": {
    "addr:full":"Plaz Coronacion (de La), 11 Quesada Ja\u00e9n 23480",
    "addr:postcode":"23480",
    "addr:street":"Plaz",
    "iso:country":"ES",
    "sg:address":"Plaz Coronacion (de La), 11",
    "sg:city":"Quesada",
    "sg:orig_category":"Cajas Para Embalar",
    "sg:phone":"+34 953 73 32 55",
    "sg:postcode":"23480",
    "sg:province":"Ja\u00e9n",
    "wof:name":"Caja Rural De Jaen",
    "wof:placetype":"venue"
},
  "geometry": {"coordinates":[-3.0667910576,37.8456687927],"type":"Point"}
}