{
  "type": "Feature",
  "properties": {
    "iso:country":"ES",
    "sg:address":"Avgd Major, 160",
    "sg:city":"Massamagrell",
    "sg:orig_category":"Empresas De Carpinter\u00cda Met\u00c1lica",
    "sg:phone":"+34 961 44 42 74",
    "sg:postcode":"46130",
    "sg:province":"Valencia",
    "wof:name":"Eulogio Eres Jose Maria",
    "wof:placetype":"venue"
},
  "geometry": {"coordinates":[-0.3329139948,39.5671310425],"type":"Point"}
}