{
  "type": "Feature",
  "properties": {
    "iso:country":"ES",
    "sg:address":"Rua Basilio Alvarez, 16",
    "sg:city":"Ourense",
    "sg:orig_category":"Promotores Constructores",
    "sg:phone":"+34 988 21 41 20",
    "sg:postcode":"32001",
    "sg:province":"Ourense",
    "wof:name":"Benito R. Bailon Y Manuel G. Borrajo S.l.",
    "wof:placetype":"venue"
},
  "geometry": {"coordinates":[-7.873237133,42.347202301],"type":"Point"}
}