{
  "type": "Feature",
  "properties": {
    "addr:full":"Calle de Corredera, 110 Almansa Albacete 02640",
    "addr:housenumber":"110",
    "addr:postcode":"02640",
    "addr:street":"Calle De Corredera",
    "iso:country":"ES",
    "sg:address":"Calle de Corredera, 110",
    "sg:city":"Almansa",
    "sg:orig_category":"Confecci\u00d3n De Zapatos",
    "sg:phone":"+34 967 34 30 15",
    "sg:postcode":"02640",
    "sg:province":"Albacete",
    "wof:name":"Taller De Montado Gavi S. L.",
    "wof:placetype":"venue"
},
  "geometry": {"coordinates":[-1.0937913656,38.8654327393],"type":"Point"}
}