{
  "type": "Feature",
  "properties": {
    "addr:full":"Calle de Arenas, 36 Daimiel Ciudad Real 13250",
    "addr:housenumber":"36",
    "addr:postcode":"13250",
    "addr:street":"Calle De Arenas",
    "iso:country":"ES",
    "sg:address":"Calle de Arenas, 36",
    "sg:city":"Daimiel",
    "sg:orig_category":"Institutos De Belleza",
    "sg:phone":"+34 926 85 53 69",
    "sg:postcode":"13250",
    "sg:province":"Ciudad Real",
    "wof:name":"Gigante Baeza Maria Jose",
    "wof:placetype":"venue"
},
  "geometry": {"coordinates":[-3.6102640629,39.0712089539],"type":"Point"}
}