{
  "type": "Feature",
  "properties": {
    "addr:full":"Barr Salom, 85 Salom Girona 17246",
    "addr:housenumber":"85",
    "addr:postcode":"17246",
    "addr:street":"Salom Girona",
    "iso:country":"ES",
    "sg:address":"Barr Salom, 85",
    "sg:city":"Salom",
    "sg:orig_category":"Electricidad: Instaladores",
    "sg:phone":"+34 972 83 73 15",
    "sg:postcode":"17246",
    "sg:province":"Girona",
    "wof:name":"Mora Parareda Jose",
    "wof:placetype":"venue"
},
  "geometry": {"coordinates":[2.9987950325,41.8115959167],"type":"Point"}
}