{
  "type": "Feature",
  "properties": {
    "addr:full":"Calle de Carboneros, 17 Linea De La Concepcion C\u00e1diz 11300",
    "addr:housenumber":"17",
    "addr:postcode":"11300",
    "addr:street":"Calle De Carboneros;Ca\u0301Diz",
    "iso:country":"ES",
    "sg:address":"Calle de Carboneros, 17",
    "sg:city":"Linea De La Concepcion",
    "sg:orig_category":"M\u00c9dicos: Oftalmolog\u00cda",
    "sg:phone":"+34 956 17 41 47",
    "sg:postcode":"11300",
    "sg:province":"C\u00e1diz",
    "wof:name":"Romero Toscaano Pedro",
    "wof:placetype":"venue"
},
  "geometry": {"coordinates":[-5.3505802155,36.1610603333],"type":"Point"}
}