{
  "type": "Feature",
  "properties": {
    "iso:country":"ES",
    "sg:address":"Carrer de Calvet, 86",
    "sg:city":"Barcelona",
    "sg:orig_category":"Inmobiliaria (agencias)",
    "sg:phone":"+34 932 09 14 09",
    "sg:postcode":"08021",
    "sg:province":"Barcelona",
    "wof:name":"Fin Inversiones Inmobiliarias",
    "wof:placetype":"venue"
},
  "geometry": {"coordinates":[2.1404850483,41.3975486755],"type":"Point"}
}