{
  "type": "Feature",
  "properties": {
    "iso:country":"ES",
    "sg:address":"Av. Generalisimo, 37",
    "sg:city":"Sada",
    "sg:orig_category":"Fabricaci\u00d3n De Productos Textiles Sin Tejer",
    "sg:phone":"+34 981 62 27 85",
    "sg:postcode":"15160",
    "sg:province":"La Coru\u00f1a",
    "wof:name":"Boutureira Mosquera Maria Josefa",
    "wof:placetype":"venue"
},
  "geometry": {"coordinates":[-8.2543287277,43.3532409668],"type":"Point"}
}