{
  "type": "Feature",
  "properties": {
    "addr:full":"Sant Roc, 2 Vilablareix Girona 17180",
    "addr:housenumber":"2",
    "addr:postcode":"17180",
    "iso:country":"ES",
    "sg:address":"Sant Roc, 2",
    "sg:city":"Vilablareix",
    "sg:orig_category":"T\u00c9cnicos Veterinarios",
    "sg:phone":"+34 972 40 18 56",
    "sg:postcode":"17180",
    "sg:province":"Girona",
    "wof:name":"Vila Puigdevall Carles",
    "wof:placetype":"venue"
},
  "geometry": {"coordinates":[2.7989549637,41.9561538696],"type":"Point"}
}