{
  "type": "Feature",
  "properties": {
    "iso:country":"ES",
    "sg:address":"Ctra Gilena-estepa, S/n",
    "sg:city":"Gilena",
    "sg:orig_category":"M\u00c1rmoles, Granitos Y Piedras Naturales",
    "sg:phone":"+34 955 82 69 01",
    "sg:postcode":"41565",
    "sg:province":"Sevilla",
    "wof:name":"Marmoles Nuestra Se\u00f1ora De La Salud S.l.",
    "wof:placetype":"venue"
},
  "geometry": {"coordinates":[-4.9302191734,37.251121521],"type":"Point"}
}