{
  "type": "Feature",
  "properties": {
    "addr:full":"Calle de Llama (la), 24 Torrelavega Cantabria 39300",
    "addr:housenumber":"24",
    "addr:postcode":"39300",
    "addr:street":"Calle De Llama La",
    "iso:country":"ES",
    "sg:address":"Calle de Llama (la), 24",
    "sg:city":"Torrelavega",
    "sg:orig_category":"Estudios, Instalaci\u00d3n De Climatizaci\u00d3n",
    "sg:phone":"+34 942 88 00 81",
    "sg:postcode":"39300",
    "sg:province":"Cantabria",
    "wof:name":"Clima Cantabria S.l.",
    "wof:placetype":"venue"
},
  "geometry": {"coordinates":[-4.0448479652,43.3493003845],"type":"Point"}
}