{
  "type": "Feature",
  "properties": {
    "addr:full":"Ctra General, S/n Carre\u00d1a Asturias 33555",
    "addr:postcode":"33555",
    "addr:street":"Ctra General S / N Carren\u0303A Asturias",
    "iso:country":"ES",
    "sg:address":"Ctra General, S/n",
    "sg:city":"Carre\u00d1a",
    "sg:orig_category":"Centros Empresariales",
    "sg:phone":"+34 985 84 53 35",
    "sg:postcode":"33555",
    "sg:province":"Asturias",
    "wof:name":"Consejo Regulador De La Denominacion De Origen Cabrales",
    "wof:placetype":"venue"
},
  "geometry": {"coordinates":[-4.9030542374,43.3285713196],"type":"Point"}
}