{
  "type": "Feature",
  "properties": {
    "addr:full":"Calle de Doctor Carracido, 14 Almeria Almer\u00eda 04005",
    "addr:housenumber":"14",
    "addr:postcode":"04005",
    "addr:street":"Calle De Doctor Carracido",
    "iso:country":"ES",
    "sg:address":"Calle de Doctor Carracido, 14",
    "sg:city":"Almeria",
    "sg:orig_category":"Tapicer\u00cdas",
    "sg:phone":"+34 950 26 31 97",
    "sg:postcode":"04005",
    "sg:province":"Almer\u00eda",
    "wof:name":"Vicente Montoro Maria Soledad",
    "wof:placetype":"venue"
},
  "geometry": {"coordinates":[-2.4564399719,36.8419189453],"type":"Point"}
}