{
  "type": "Feature",
  "properties": {
    "addr:full":"Calle de Linares Rivas, 26 Sada La Coru\u00f1a 15160",
    "addr:housenumber":"26",
    "addr:postcode":"15160",
    "addr:street":"Calle De Linares Rivas;La",
    "iso:country":"ES",
    "sg:address":"Calle de Linares Rivas, 26",
    "sg:city":"Sada",
    "sg:orig_category":"Electrodom\u00c9sticos (al Por Menor)",
    "sg:phone":"+34 981 62 13 77",
    "sg:postcode":"15160",
    "sg:province":"La Coru\u00f1a",
    "wof:name":"Novoa Rodriguez Juan",
    "wof:placetype":"venue"
},
  "geometry": {"coordinates":[-8.2529697418,43.3493461609],"type":"Point"}
}