{
  "type": "Feature",
  "properties": {
    "iso:country":"ES",
    "sg:address":"Calle de Loizaga Kalea, 10",
    "sg:city":"Gernika-lumo",
    "sg:orig_category":"Peluquer\u00cdas, Peluquer\u00cda Mixta",
    "sg:phone":"+34 946 25 61 33",
    "sg:postcode":"48300",
    "sg:province":"Vizcaya",
    "wof:name":"Ainhoa Monasterio Zubicaray",
    "wof:placetype":"venue"
},
  "geometry": {"coordinates":[-2.6766357422,43.3140830994],"type":"Point"}
}