{
  "type": "Feature",
  "properties": {
    "addr:full":"Buiguetes (pol Torrentfondo), S/n S. Lloren\u00e7 Hortons Barcelona 08791",
    "addr:housenumber":"s",
    "addr:postcode":"08791",
    "addr:street":"/ N S.",
    "iso:country":"ES",
    "sg:address":"Buiguetes (pol Torrentfondo), S/n",
    "sg:city":"S. Lloren\u00e7 Hortons",
    "sg:orig_category":"Puertas De Acorde\u00d3n Y Flexibles",
    "sg:phone":"+34 937 71 70 37",
    "sg:postcode":"08791",
    "sg:province":"Barcelona",
    "wof:name":"Rolan Interiorismo S.l.",
    "wof:placetype":"venue"
},
  "geometry": {"coordinates":[1.8163950443,41.4726333618],"type":"Point"}
}