{
  "type": "Feature",
  "properties": {
    "addr:full":"Rua Nova, S/n Rubian Lugo 27350",
    "addr:housenumber":"s / n",
    "addr:postcode":"27350",
    "addr:street":"Rua Nova",
    "iso:country":"ES",
    "sg:address":"Rua Nova, S/n",
    "sg:city":"Rubian",
    "sg:orig_category":"Cr\u00cda De Poller\u00cda Y De Conejos",
    "sg:phone":"+34 982 42 41 53",
    "sg:postcode":"27350",
    "sg:province":"Lugo",
    "wof:name":"Gonzalez Vazquez Jesus",
    "wof:placetype":"venue"
},
  "geometry": {"coordinates":[-7.4779639244,42.6528358459],"type":"Point"}
}