{
  "type": "Feature",
  "properties": {
    "iso:country":"ES",
    "sg:address":"Calle de Maria De Molina, 39",
    "sg:city":"Madrid",
    "sg:orig_category":"Inmobiliaria (agencias)",
    "sg:phone":"+34 913 56 66 49",
    "sg:postcode":"28006",
    "sg:province":"Madrid",
    "wof:name":"Tombano S.a.",
    "wof:placetype":"venue"
},
  "geometry": {"coordinates":[-3.6798713207,40.4375724792],"type":"Point"}
}