{
  "type": "Feature",
  "properties": {
    "addr:full":"Calle de Rosa Felices, 130 Almeria Almer\u00eda 04006",
    "addr:housenumber":"130",
    "addr:postcode":"04006",
    "addr:street":"Calle De Rosa Felices",
    "iso:country":"ES",
    "sg:address":"Calle de Rosa Felices, 130",
    "sg:city":"Almeria",
    "sg:orig_category":"Carnicer\u00cdas, Carnicer\u00cdas",
    "sg:phone":"+34 950 22 64 83",
    "sg:postcode":"04006",
    "sg:province":"Almer\u00eda",
    "wof:name":"Miras Alonso Mercedes",
    "wof:placetype":"venue"
},
  "geometry": {"coordinates":[-2.4431269169,36.8436813354],"type":"Point"}
}