{
  "type": "Feature",
  "properties": {
    "iso:country":"ES",
    "sg:address":"Calle de Canovas Del Castillo, 46",
    "sg:city":"Jumilla",
    "sg:orig_category":"Agencias De Viajes",
    "sg:phone":"+34 968 75 60 60",
    "sg:postcode":"30520",
    "sg:province":"Murcia",
    "wof:name":"Viajes Pilar Garcia S.l.",
    "wof:placetype":"venue"
},
  "geometry": {"coordinates":[-1.3280930519,38.4747428894],"type":"Point"}
}