{
  "type": "Feature",
  "properties": {
    "iso:country":"ES",
    "sg:address":"Calle de Calatrava, 14",
    "sg:city":"Madrid",
    "sg:orig_category":"Molduras, Junquillos, Listones Y Molduras Perforadas",
    "sg:phone":"+34 913 64 02 59",
    "sg:postcode":"28005",
    "sg:province":"Madrid",
    "wof:name":"Gonzalez Moreno Maria Luz",
    "wof:placetype":"venue"
},
  "geometry": {"coordinates":[-3.7115280628,40.4092712402],"type":"Point"}
}