{
  "type": "Feature",
  "properties": {
    "iso:country":"ES",
    "sg:address":"Avda Pino Montano, 122",
    "sg:city":"Sevilla",
    "sg:orig_category":"Relojer\u00cda (al Por Menor, Reparaci\u00d3n)",
    "sg:phone":"+34 954 94 39 44",
    "sg:postcode":"41008",
    "sg:province":"Sevilla",
    "wof:name":"Vazquez Valverde Juan Luis",
    "wof:placetype":"venue"
},
  "geometry": {"coordinates":[-5.9722571373,37.4093322754],"type":"Point"}
}