{
  "type": "Feature",
  "properties": {
    "addr:full":"Calle de Toledillo, 3 Moral Calatrava Ciudad Real 13350",
    "addr:housenumber":"3",
    "addr:postcode":"13350",
    "addr:street":"Calle De Toledillo;Calatrava",
    "iso:country":"ES",
    "sg:address":"Calle de Toledillo, 3",
    "sg:city":"Moral Calatrava",
    "sg:orig_category":"Reposter\u00cdas",
    "sg:phone":"+34 926 33 02 73",
    "sg:postcode":"13350",
    "sg:province":"Ciudad Real",
    "wof:name":"Marquez Arroyo Cristobal",
    "wof:placetype":"venue"
},
  "geometry": {"coordinates":[-3.5817170143,38.831035614],"type":"Point"}
}