{
  "type": "Feature",
  "properties": {
    "addr:full":"Calle de Zubiaur Tar Kepa, S/n Bermeo Vizcaya 48370",
    "addr:housenumber":"s / n",
    "addr:postcode":"48370",
    "addr:street":"Calle De Zubiaur;Kepa",
    "iso:country":"ES",
    "sg:address":"Calle de Zubiaur Tar Kepa, S/n",
    "sg:city":"Bermeo",
    "sg:orig_category":"Mec\u00c1nico Del Autom\u00d3vil",
    "sg:phone":"+34 946 88 47 13",
    "sg:postcode":"48370",
    "sg:province":"Vizcaya",
    "wof:name":"Talleres Almike C.b.",
    "wof:placetype":"venue"
},
  "geometry": {"coordinates":[-2.7481176853,43.4026641846],"type":"Point"}
}