{
  "type": "Feature",
  "properties": {
    "iso:country":"ES",
    "sg:address":"Carr Pere Gil, 10",
    "sg:city":"Villarreal",
    "sg:orig_category":"Inform\u00c1tica (estudios, Servicios, Asesor\u00cda, Formaci\u00d3n)",
    "sg:phone":"+34 964 53 86 50",
    "sg:postcode":"12540",
    "sg:province":"Castell\u00f3n",
    "sg:website":"www.padiserv.com",
    "wof:name":"Padiserv Iberica S.l.",
    "wof:placetype":"venue"
},
  "geometry": {"coordinates":[-0.0952939987,39.9453048706],"type":"Point"}
}