{
  "type": "Feature",
  "properties": {
    "iso:country":"ES",
    "sg:address":"Avda Done Erroke Etorbidea, 24",
    "sg:city":"Amurrio",
    "sg:orig_category":"Empresas De Pintura Y Revestimientos",
    "sg:phone":"+34 945 39 36 30",
    "sg:postcode":"01470",
    "sg:province":"\u00c1lava",
    "wof:name":"Ussia Aprais Juan Carlos",
    "wof:placetype":"venue"
},
  "geometry": {"coordinates":[-3.0217339993,43.0432891846],"type":"Point"}
}