{
  "type": "Feature",
  "properties": {
    "addr:full":"Plaz Mayor, 14 Roda Albacete 02630",
    "addr:housenumber":"14",
    "addr:postcode":"02630",
    "addr:street":"Plaz Mayor",
    "iso:country":"ES",
    "sg:address":"Plaz Mayor, 14",
    "sg:city":"Roda",
    "sg:orig_category":"Zapater\u00cdas",
    "sg:phone":"+34 967 44 12 33",
    "sg:postcode":"02630",
    "sg:province":"Albacete",
    "wof:name":"Donate Lucas Felix",
    "wof:placetype":"venue"
},
  "geometry": {"coordinates":[-2.1636590958,39.1957206726],"type":"Point"}
}