{
  "type": "Feature",
  "properties": {
    "addr:full":"Calle de San Pablo, 21 Cordoba C\u00f3rdoba 14002",
    "addr:housenumber":"21",
    "addr:postcode":"14002",
    "addr:street":"Calle De San Pablo;Co\u0301Rdoba",
    "iso:country":"ES",
    "sg:address":"Calle de San Pablo, 21",
    "sg:city":"Cordoba",
    "sg:orig_category":"Caf\u00c9s, Bares, Cervecer\u00cdas",
    "sg:phone":"+34 957 48 01 08",
    "sg:postcode":"14002",
    "sg:province":"C\u00f3rdoba",
    "wof:name":"Montes Pontes German",
    "wof:placetype":"venue"
},
  "geometry": {"coordinates":[-4.774148941,37.8860092163],"type":"Point"}
}