{
  "type": "Feature",
  "properties": {
    "addr:full":"Av Santa Coloma, 59 Santa Coloma De Gramenet Barcelona 08922",
    "addr:housenumber":"59",
    "addr:postcode":"08922",
    "addr:street":"Av Santa Coloma",
    "iso:country":"ES",
    "sg:address":"Av Santa Coloma, 59",
    "sg:city":"Santa Coloma De Gramenet",
    "sg:orig_category":"Carnicer\u00cdas, Carnicer\u00cdas",
    "sg:phone":"+34 934 66 13 28",
    "sg:postcode":"08922",
    "sg:province":"Barcelona",
    "wof:name":"Aguilar Barajas Jose Luis",
    "wof:placetype":"venue"
},
  "geometry": {"coordinates":[2.2083559036,41.4474182129],"type":"Point"}
}