{
  "type": "Feature",
  "properties": {
    "addr:full":"Zubierreka Industri Poligonoa, 47 Zubierreka Guip\u00f9zcoa 20210",
    "addr:housenumber":"47",
    "addr:postcode":"20210",
    "addr:street":"Zubierreka Industri Poligonoa;Guipu\u0300Zcoa",
    "iso:country":"ES",
    "sg:address":"Zubierreka Industri Poligonoa, 47",
    "sg:city":"Zubierreka",
    "sg:orig_category":"Reposter\u00cdas",
    "sg:phone":"+34 943 16 20 22",
    "sg:postcode":"20210",
    "sg:province":"Guip\u00f9zcoa",
    "wof:name":"Errotaundi S.l.",
    "wof:placetype":"venue"
},
  "geometry": {"coordinates":[-2.1873590946,43.0314903259],"type":"Point"}
}