{
  "type": "Feature",
  "properties": {
    "iso:country":"ES",
    "sg:address":"Calle de Chile, 2",
    "sg:city":"Vitoria-gasteiz",
    "sg:orig_category":"Transportes Por V\u00cdas Navegables",
    "sg:phone":"+34 945 24 16 47",
    "sg:postcode":"01009",
    "sg:province":"\u00c1lava",
    "wof:name":"Velez Valencia Jesus",
    "wof:placetype":"venue"
},
  "geometry": {"coordinates":[-2.6848909855,42.852142334],"type":"Point"}
}