{
  "type": "Feature",
  "properties": {
    "addr:full":"Calle de Cuesta Del Puente, 31 Molina Segura Murcia 30500",
    "addr:housenumber":"31",
    "addr:postcode":"30500",
    "addr:street":"Calle De Cuesta Del Puente",
    "iso:country":"ES",
    "sg:address":"Calle de Cuesta Del Puente, 31",
    "sg:city":"Molina Segura",
    "sg:orig_category":"Cueros Y Pieles (al Por Mayor)",
    "sg:phone":"+34 968 64 01 14",
    "sg:postcode":"30500",
    "sg:province":"Murcia",
    "wof:name":"Puche Garcia Jose Luis",
    "wof:placetype":"venue"
},
  "geometry": {"coordinates":[-1.1298867464,37.9834747314],"type":"Point"}
}