{
  "type": "Feature",
  "properties": {
    "iso:country":"ES",
    "sg:address":"Carr Oscar Espla, 2",
    "sg:city":"Massamagrell",
    "sg:orig_category":"Electricidad Veh\u00cdculo",
    "sg:phone":"+34 961 44 56 50",
    "sg:postcode":"46130",
    "sg:province":"Valencia",
    "wof:name":"Sertiauto S.l.",
    "wof:placetype":"venue"
},
  "geometry": {"coordinates":[-0.3345800042,39.5741462708],"type":"Point"}
}