{
  "type": "Feature",
  "properties": {
    "addr:full":"Calle de Villaespesa, 27 Laujar Andarax Almer\u00eda 04470",
    "addr:housenumber":"27",
    "addr:postcode":"04470",
    "addr:street":"Calle De Villaespesa;Almeri\u0301A",
    "iso:country":"ES",
    "sg:address":"Calle de Villaespesa, 27",
    "sg:city":"Laujar Andarax",
    "sg:orig_category":"Pensiones Familiares",
    "sg:phone":"+34 950 51 31 13",
    "sg:postcode":"04470",
    "sg:province":"Almer\u00eda",
    "wof:name":"Garcia Godoy Jose",
    "wof:placetype":"venue"
},
  "geometry": {"coordinates":[-2.8938889503,36.9929962158],"type":"Point"}
}