{
  "type": "Feature",
  "properties": {
    "iso:country":"ES",
    "sg:address":"Carrer de Barcelona, 40",
    "sg:city":"Caldes Montbui",
    "sg:orig_category":"Alimentaci\u00d3n General (al Por Mayor)",
    "sg:phone":"+34 938 65 01 96",
    "sg:postcode":"08140",
    "sg:province":"Barcelona",
    "wof:name":"Pastes Sanmarti S.l.",
    "wof:placetype":"venue"
},
  "geometry": {"coordinates":[2.1624610424,41.6329727173],"type":"Point"}
}