{
  "type": "Feature",
  "properties": {
    "addr:full":"Carr Mossen Anton, 57 Badalona Barcelona 08912",
    "addr:housenumber":"57",
    "addr:postcode":"08912",
    "addr:street":"Carr Mossen Anton",
    "iso:country":"ES",
    "sg:address":"Carr Mossen Anton, 57",
    "sg:city":"Badalona",
    "sg:orig_category":"Asesor\u00cda Fiscal Y Jur\u00cddica",
    "sg:phone":"+34 934 64 64 16",
    "sg:postcode":"08912",
    "sg:province":"Barcelona",
    "wof:name":"Asesteco-asesoria Tecnica Contable Y Tributaria S.l.",
    "wof:placetype":"venue"
},
  "geometry": {"coordinates":[2.2469203472,41.4452552795],"type":"Point"}
}