{
  "type": "Feature",
  "properties": {
    "addr:full":"Avda Elizatxo, 4 Irun Guip\u00f9zcoa 20303",
    "addr:housenumber":"4",
    "addr:postcode":"20303",
    "addr:street":"Avda Elizatxo;Guipu\u0300Zcoa",
    "iso:country":"ES",
    "sg:address":"Avda Elizatxo, 4",
    "sg:city":"Irun",
    "sg:orig_category":"Empresas De Desmonte",
    "sg:phone":"+34 943 02 04 25",
    "sg:postcode":"20303",
    "sg:province":"Guip\u00f9zcoa",
    "wof:name":"Delfines Irun S.l.",
    "wof:placetype":"venue"
},
  "geometry": {"coordinates":[-1.7962299585,43.336856842],"type":"Point"}
}