{
  "type": "Feature",
  "properties": {
    "addr:full":"Carrer de Vinaters, 5 Monovar Alicante 03640",
    "addr:housenumber":"5",
    "addr:postcode":"03640",
    "addr:street":"Carrer De Vinaters;Alicante",
    "iso:country":"ES",
    "sg:address":"Carrer de Vinaters, 5",
    "sg:city":"Monovar",
    "sg:orig_category":"Confecci\u00d3n De Zapatos",
    "sg:phone":"+34 966 96 04 29",
    "sg:postcode":"03640",
    "sg:province":"Alicante",
    "wof:name":"Fervis Coop. V.",
    "wof:placetype":"venue"
},
  "geometry": {"coordinates":[-0.831749022,38.4374885559],"type":"Point"}
}