{
  "type": "Feature",
  "properties": {
    "addr:full":"Avda Juan Carlos I, 47 Villanueva Fresno Badajoz 06110",
    "addr:housenumber":"47",
    "addr:postcode":"06110",
    "addr:street":"Avda Juan Carlos I",
    "iso:country":"ES",
    "sg:address":"Avda Juan Carlos I, 47",
    "sg:city":"Villanueva Fresno",
    "sg:orig_category":"Alimentaci\u00d3n General (al Por Mayor)",
    "sg:phone":"+34 924 42 76 14",
    "sg:postcode":"06110",
    "sg:province":"Badajoz",
    "wof:name":"Cereales Y Piensos Villanueva S.a.l.",
    "wof:placetype":"venue"
},
  "geometry": {"coordinates":[-7.1644258499,38.3783569336],"type":"Point"}
}