{
  "type": "Feature",
  "properties": {
    "addr:full":"Avda Maria Cristina, 7 Valencia Valencia 46001",
    "addr:housenumber":"7",
    "addr:postcode":"46001",
    "addr:street":"Avda Maria Cristina",
    "iso:country":"ES",
    "sg:address":"Avda Maria Cristina, 7",
    "sg:city":"Valencia",
    "sg:orig_category":"M\u00c9dicos: Pediatr\u00cda. Enfermedades De Los Ni\u00d1os",
    "sg:phone":"+34 963 52 73 86",
    "sg:postcode":"46001",
    "sg:province":"Valencia",
    "wof:name":"Canovas Martinez Andres",
    "wof:placetype":"venue"
},
  "geometry": {"coordinates":[-0.3774000108,39.4726676941],"type":"Point"}
}