{
  "type": "Feature",
  "properties": {
    "addr:full":"Plaz Mayor, 1 Castilruiz Soria 42113",
    "addr:housenumber":"1",
    "addr:postcode":"42113",
    "addr:street":"Plaz Mayor",
    "iso:country":"ES",
    "sg:address":"Plaz Mayor, 1",
    "sg:city":"Castilruiz",
    "sg:orig_category":"Farmacias",
    "sg:phone":"+34 975 38 31 38",
    "sg:postcode":"42113",
    "sg:province":"Soria",
    "wof:name":"Braojos Braojos Marco Antonio",
    "wof:placetype":"venue"
},
  "geometry": {"coordinates":[-2.0593049526,41.8769645691],"type":"Point"}
}