{
  "type": "Feature",
  "properties": {
    "iso:country":"ES",
    "sg:address":"Carrer de America, 1",
    "sg:city":"Barcelona",
    "sg:orig_category":"Molduras, Junquillos, Listones Y Molduras Perforadas",
    "sg:phone":"+34 934 36 32 47",
    "sg:postcode":"08041",
    "sg:province":"Barcelona",
    "wof:name":"Dominguez Fernandez Dario",
    "wof:placetype":"venue"
},
  "geometry": {"coordinates":[2.1787660122,41.4147224426],"type":"Point"}
}