{
  "type": "Feature",
  "properties": {
    "addr:full":"Calle de Ebro (el), 2 Arcos Jalon Soria 42250",
    "addr:postcode":"42250",
    "addr:street":"Calle De Ebro El",
    "iso:country":"ES",
    "sg:address":"Calle de Ebro (el), 2",
    "sg:city":"Arcos Jalon",
    "sg:orig_category":"Inform\u00c1tica: Material Y Suministros",
    "sg:phone":"+34 975 32 03 91",
    "sg:postcode":"42250",
    "sg:province":"Soria",
    "wof:name":"Jaime Torrejon Jose Ignacio",
    "wof:placetype":"venue"
},
  "geometry": {"coordinates":[-2.2958910465,41.2045516968],"type":"Point"}
}