{
  "type": "Feature",
  "properties": {
    "iso:country":"ES",
    "sg:address":"Rua Progreso (do), S/n",
    "sg:city":"Ourense",
    "sg:orig_category":"Abogados",
    "sg:phone":"+34 988 37 07 21",
    "sg:postcode":"32003",
    "sg:province":"Ourense",
    "wof:name":"Juzgado De Primera Instancia E Instruccion N\u00ba 4",
    "wof:placetype":"venue"
},
  "geometry": {"coordinates":[-7.8682937622,42.3431015015],"type":"Point"}
}