{
  "type": "Feature",
  "properties": {
    "addr:full":"Calle de Leon, 2 Azuqueca Henares Guadalajara 19200",
    "addr:housenumber":"2",
    "addr:postcode":"19200",
    "addr:street":"Calle De Leon",
    "iso:country":"ES",
    "sg:address":"Calle de Leon, 2",
    "sg:city":"Azuqueca Henares",
    "sg:orig_category":"Institutos De Belleza",
    "sg:phone":"+34 949 26 58 13",
    "sg:postcode":"19200",
    "sg:province":"Guadalajara",
    "wof:name":"Garcia Gamo Maria Del Carmen",
    "wof:placetype":"venue"
},
  "geometry": {"coordinates":[-3.2644169331,40.5629768372],"type":"Point"}
}