{
  "type": "Feature",
  "properties": {
    "iso:country":"ES",
    "sg:address":"Calle de Montes Universales, 20",
    "sg:city":"Arganda",
    "sg:orig_category":"Trabajos De Soldaduras",
    "sg:phone":"+34 918 71 93 58",
    "sg:postcode":"28500",
    "sg:province":"Madrid",
    "wof:name":"Martinez Bachiller Antonio",
    "wof:placetype":"venue"
},
  "geometry": {"coordinates":[-3.4782390594,40.3080787659],"type":"Point"}
}