{
  "type": "Feature",
  "properties": {
    "iso:country":"ES",
    "sg:address":"Av Mallorca, 17",
    "sg:city":"Castell Bendinat",
    "sg:orig_category":"Urbanistas",
    "sg:phone":"+34 971 40 56 27",
    "sg:postcode":"07181",
    "sg:province":"Islas Baleares",
    "wof:name":"Open Gp Consulting S.l.",
    "wof:placetype":"venue"
},
  "geometry": {"coordinates":[2.5352098942,39.5245780945],"type":"Point"}
}