{
  "type": "Feature",
  "properties": {
    "iso:country":"ES",
    "sg:address":"Av Meridiana, 19",
    "sg:city":"Barcelona",
    "sg:orig_category":"Aguas (distribuci\u00d3n, Servicios)",
    "sg:phone":"+34 933 09 73 31",
    "sg:postcode":"08018",
    "sg:province":"Barcelona",
    "wof:name":"Fontdor S.a.",
    "wof:placetype":"venue"
},
  "geometry": {"coordinates":[2.186727047,41.3933410645],"type":"Point"}
}