{
  "type": "Feature",
  "properties": {
    "iso:country":"ES",
    "sg:address":"Ctra Arta, 46",
    "sg:city":"Platja D'alcudia",
    "sg:orig_category":"Inmobiliaria (agencias)",
    "sg:phone":"+34 971 89 07 00",
    "sg:postcode":"07408",
    "sg:province":"Islas Baleares",
    "wof:name":"Romani Nord De Mallorca S.l.",
    "wof:placetype":"venue"
},
  "geometry": {"coordinates":[3.120937109,39.8396034241],"type":"Point"}
}