{
  "type": "Feature",
  "properties": {
    "addr:full":"Calle de Cardenal Cisneros, 2 Santander Cantabria 39007",
    "addr:housenumber":"2",
    "addr:postcode":"39007",
    "addr:street":"Calle De Cardenal Cisneros",
    "iso:country":"ES",
    "sg:address":"Calle de Cardenal Cisneros, 2",
    "sg:city":"Santander",
    "sg:orig_category":"Ense\u00d1anza, Formaci\u00d3n Profesional: Aprendizaje",
    "sg:phone":"+34 942 22 89 60",
    "sg:postcode":"39007",
    "sg:province":"Cantabria",
    "wof:name":"Ayuntamiento De Santander",
    "wof:placetype":"venue"
},
  "geometry": {"coordinates":[-3.8190217018,43.4621734619],"type":"Point"}
}