{
  "type": "Feature",
  "properties": {
    "iso:country":"ES",
    "sg:address":"Plaz Italia, 7",
    "sg:city":"Avila",
    "sg:orig_category":"Empresarios Y Productoras De Espect\u00c1culos",
    "sg:phone":"+34 920 21 38 39",
    "sg:postcode":"05001",
    "sg:province":"\u00c1vila",
    "wof:name":"Cachet Producciones Artisticas S.l.",
    "wof:placetype":"venue"
},
  "geometry": {"coordinates":[-4.6956119537,40.6555633545],"type":"Point"}
}