{
  "type": "Feature",
  "properties": {
    "addr:full":"Carrer de Santa Eulalia, 14 Hospitalet Llobregat Barcelona 08902",
    "addr:housenumber":"14",
    "addr:postcode":"08902",
    "addr:street":"Carrer De Santa Eulalia",
    "iso:country":"ES",
    "sg:address":"Carrer de Santa Eulalia, 14",
    "sg:city":"Hospitalet Llobregat",
    "sg:orig_category":"Establecimientos De Cura, Prevenci\u00d3n Y Readaptaci\u00d3n",
    "sg:phone":"+34 933 31 76 16",
    "sg:postcode":"08902",
    "sg:province":"Barcelona",
    "wof:name":"Ajuntament De L'hospitalet De Llobregat",
    "wof:placetype":"venue"
},
  "geometry": {"coordinates":[2.1279947758,41.3676300049],"type":"Point"}
}