{
  "type": "Feature",
  "properties": {
    "addr:full":"Grijalba-las Cruces, S/n Cruces La Coru\u00f1a 15816",
    "addr:housenumber":"s / n",
    "addr:postcode":"15816",
    "addr:street":"Grijalba-Las Cruces;Cruces La Corun\u0303A",
    "iso:country":"ES",
    "sg:address":"Grijalba-las Cruces, S/n",
    "sg:city":"Cruces",
    "sg:orig_category":"Cr\u00cda De Bovinos",
    "sg:phone":"+34 981 19 54 26",
    "sg:postcode":"15816",
    "sg:province":"La Coru\u00f1a",
    "wof:name":"Ganaderia De Ra\u00f1on S.l.",
    "wof:placetype":"venue"
},
  "geometry": {"coordinates":[-8.0124197006,43.0780715942],"type":"Point"}
}