{
  "type": "Feature",
  "properties": {
    "addr:full":"Calle de San Miguel, S/n Poyo Del Cid Teruel 44392",
    "addr:housenumber":"s",
    "addr:postcode":"44392",
    "addr:street":"Calle De San Miguel;/ N",
    "iso:country":"ES",
    "sg:address":"Calle de San Miguel, S/n",
    "sg:city":"Poyo Del Cid",
    "sg:orig_category":"Centros De Educaci\u00d3n Especial",
    "sg:phone":"+34 978 73 15 04",
    "sg:postcode":"44392",
    "sg:province":"Teruel",
    "wof:name":"C.r.a.de El Poyo Del Cid-d.g.a.-el Poyo Del Cid",
    "wof:placetype":"venue"
},
  "geometry": {"coordinates":[-1.3323450089,40.8843078613],"type":"Point"}
}