{
  "type": "Feature",
  "properties": {
    "iso:country":"ES",
    "sg:address":"Av Pais Valenciano, 92",
    "sg:city":"Guardamar Segura",
    "sg:orig_category":"C\u00c1maras De Comercio E Industria, Oficios, Agricultura",
    "sg:phone":"+34 966 72 57 84",
    "sg:postcode":"03140",
    "sg:province":"Alicante",
    "wof:name":"Rodriguez Pamies Fulgencio",
    "wof:placetype":"venue"
},
  "geometry": {"coordinates":[-0.6545140147,38.0852928162],"type":"Point"}
}