{
  "type": "Feature",
  "properties": {
    "addr:full":"Carrer de Bogatell, 14 Montcada Centre Barcelona 08110",
    "addr:housenumber":"14",
    "addr:postcode":"08110",
    "addr:street":"Carrer De Bogatell",
    "iso:country":"ES",
    "sg:address":"Carrer de Bogatell, 14",
    "sg:city":"Montcada Centre",
    "sg:orig_category":"Cajas De Ahorro",
    "sg:phone":"+34 935 65 14 80",
    "sg:postcode":"08110",
    "sg:province":"Barcelona",
    "sg:website":"www.bancaja.es",
    "wof:name":"Caja De Ahorros De Valencia Castellon Y Alicante",
    "wof:placetype":"venue"
},
  "geometry": {"coordinates":[2.1817660332,41.4890899658],"type":"Point"}
}