{
  "type": "Feature",
  "properties": {
    "addr:full":"Calle de Agreda, 4 Madrid Madrid 28033",
    "addr:housenumber":"4",
    "addr:postcode":"28033",
    "addr:street":"Calle De Agreda",
    "iso:country":"ES",
    "sg:address":"Calle de Agreda, 4",
    "sg:city":"Madrid",
    "sg:orig_category":"Edici\u00d3n, Venta De Partituras Musicales",
    "sg:phone":"+34 917 66 56 14",
    "sg:postcode":"28033",
    "sg:province":"Madrid",
    "wof:name":"Yogi Songs S.l",
    "wof:placetype":"venue"
},
  "geometry": {"coordinates":[-3.6623950005,40.4664497375],"type":"Point"}
}