{
  "type": "Feature",
  "properties": {
    "iso:country":"ES",
    "sg:address":"Calle de Jose Del Pino, 70",
    "sg:city":"Madrid",
    "sg:orig_category":"Frutas, Legumbres Frescas Y Tempranas (al Por Menor)",
    "sg:phone":"+34 917 97 94 63",
    "sg:postcode":"28021",
    "sg:province":"Madrid",
    "wof:name":"Cepeda Bermejo Carlos",
    "wof:placetype":"venue"
},
  "geometry": {"coordinates":[-3.688188076,40.3508682251],"type":"Point"}
}