{
  "type": "Feature",
  "properties": {
    "iso:country":"ES",
    "sg:address":"Bidebarrieta Kalea, 12",
    "sg:city":"Eibar",
    "sg:orig_category":"Carnicer\u00cdas, Carnicer\u00cdas",
    "sg:phone":"+34 943 20 13 40",
    "sg:postcode":"20600",
    "sg:province":"Guip\u00f9zcoa",
    "wof:name":"Ignacio Mugica Catarain",
    "wof:placetype":"venue"
},
  "geometry": {"coordinates":[-2.4662730694,43.1855545044],"type":"Point"}
}