{
  "type": "Feature",
  "properties": {
    "addr:full":"Plaz Concepcion Arenal, 2 Huesca Huesca 22002",
    "addr:housenumber":"2",
    "addr:postcode":"22002",
    "addr:street":"Plaz Concepcion Arenal",
    "iso:country":"ES",
    "sg:address":"Plaz Concepcion Arenal, 2",
    "sg:city":"Huesca",
    "sg:orig_category":"Agentes Generales De Seguros",
    "sg:phone":"+34 974 24 53 11",
    "sg:postcode":"22002",
    "sg:province":"Huesca",
    "wof:name":"Sabadell Betran Maria Angeles",
    "wof:placetype":"venue"
},
  "geometry": {"coordinates":[-0.408291012,42.1360092163],"type":"Point"}
}