{
  "type": "Feature",
  "properties": {
    "addr:full":"Francesc F Andreu, 2 Mao Islas Baleares 07702",
    "addr:housenumber":"2",
    "addr:postcode":"07702",
    "addr:street":"Andreu",
    "iso:country":"ES",
    "sg:address":"Francesc F Andreu, 2",
    "sg:city":"Mao",
    "sg:orig_category":"Ense\u00d1anza: Idiomas",
    "sg:phone":"+34 971 35 31 04",
    "sg:postcode":"07702",
    "sg:province":"Islas Baleares",
    "wof:name":"Escola Oficial D'idiomes De Mao",
    "wof:placetype":"venue"
},
  "geometry": {"coordinates":[4.2698302269,39.8846244812],"type":"Point"}
}