{
  "type": "Feature",
  "properties": {
    "iso:country":"ES",
    "sg:address":"Calle de Huerto Don Rodrigo, 1",
    "sg:city":"Illora",
    "sg:orig_category":"Servicio De Salud",
    "sg:phone":"+34 958 46 35 70",
    "sg:postcode":"18260",
    "sg:province":"Granada",
    "wof:name":"Ceramica Y Fontaneria Parapanda S.l.",
    "wof:placetype":"venue"
},
  "geometry": {"coordinates":[-3.8792939186,37.2863349915],"type":"Point"}
}