{
  "type": "Feature",
  "properties": {
    "addr:full":"Cllo Frailes (de Los), S/n Adeje Santa Cruz De Tenerife 38670",
    "addr:postcode":"38670",
    "addr:street":"Los S / N",
    "iso:country":"ES",
    "sg:address":"Cllo Frailes (de Los), S/n",
    "sg:city":"Adeje",
    "sg:orig_category":"Ropa Para Se\u00d1oras Y Caballeros (al Por Menor)",
    "sg:phone":"+34 922 78 09 47",
    "sg:postcode":"38670",
    "sg:province":"Santa Cruz De Tenerife",
    "wof:name":"Rodriguez Quintero Sebastian",
    "wof:placetype":"venue"
},
  "geometry": {"coordinates":[-16.7241630554,28.1223106384],"type":"Point"}
}