{
  "type": "Feature",
  "properties": {
    "iso:country":"ES",
    "sg:address":"Calle de Francisco Fernandez Ordo\u00d1ez, 4",
    "sg:city":"Miguelturra",
    "sg:orig_category":"Farmacias",
    "sg:phone":"+34 926 27 21 73",
    "sg:postcode":"13170",
    "sg:province":"Ciudad Real",
    "wof:name":"Arevalo Romero Antonio",
    "wof:placetype":"venue"
},
  "geometry": {"coordinates":[-3.8853576183,38.9574813843],"type":"Point"}
}