{
  "type": "Feature",
  "properties": {
    "iso:country":"ES",
    "sg:address":"Plaz Santa Catalina, 2",
    "sg:city":"Valencia",
    "sg:orig_category":"Fabricaci\u00d3n, Importaci\u00d3n, Venta De Material De Telefon\u00cda, Peritelefon\u00cda",
    "sg:phone":"+34 963 15 62 62",
    "sg:postcode":"46001",
    "sg:province":"Valencia",
    "wof:name":"Valcirnet S.l.",
    "wof:placetype":"venue"
},
  "geometry": {"coordinates":[-0.3757460117,39.4739227295],"type":"Point"}
}