{
  "type": "Feature",
  "properties": {
    "addr:full":"Av Maria Fortuny, 87 Reus Tarragona 43204",
    "addr:housenumber":"87",
    "addr:postcode":"43204",
    "addr:street":"Av Maria Fortuny",
    "iso:country":"ES",
    "sg:address":"Av Maria Fortuny, 87",
    "sg:city":"Reus",
    "sg:orig_category":"Peritos En C\u00c1lculo Inmobiliario, Industrial Y De Fondos De Comercio",
    "sg:phone":"+34 977 34 18 97",
    "sg:postcode":"43204",
    "sg:province":"Tarragona",
    "wof:name":"Guerrero Llera Rafael",
    "wof:placetype":"venue"
},
  "geometry": {"coordinates":[1.1172100306,41.1588401794],"type":"Point"}
}