{
  "type": "Feature",
  "properties": {
    "addr:full":"Avda Baleares, 11 Valencia Valencia 46023",
    "addr:housenumber":"11",
    "addr:postcode":"46023",
    "addr:street":"Avda Baleares",
    "iso:country":"ES",
    "sg:address":"Avda Baleares, 11",
    "sg:city":"Valencia",
    "sg:orig_category":"Empresas De Vigilancia, Guardia Y Protecci\u00d3n",
    "sg:phone":"+34 963 16 90 66",
    "sg:postcode":"46023",
    "sg:province":"Valencia",
    "wof:name":"Guilmain  Pierre",
    "wof:placetype":"venue"
},
  "geometry": {"coordinates":[-0.3563500047,39.4636230469],"type":"Point"}
}