{
  "type": "Feature",
  "properties": {
    "iso:country":"ES",
    "sg:address":"Calle de Xativa, 10",
    "sg:city":"Valencia",
    "sg:orig_category":"Albergues",
    "sg:phone":"+34 963 51 72 47",
    "sg:postcode":"46002",
    "sg:province":"Valencia",
    "wof:name":"Abalos Contreras Milagros Mercedes",
    "wof:placetype":"venue"
},
  "geometry": {"coordinates":[-0.378745,39.467957],"type":"Point"}
}