{
  "type": "Feature",
  "properties": {
    "addr:full":"Calle de Otero Blas De, 28 Bilbao Vizcaya 48014",
    "addr:housenumber":"28",
    "addr:postcode":"48014",
    "addr:street":"Calle De Otero Blas De",
    "iso:country":"ES",
    "sg:address":"Calle de Otero Blas De, 28",
    "sg:city":"Bilbao",
    "sg:orig_category":"Molduras, Junquillos, Listones Y Molduras Perforadas",
    "sg:phone":"+34 944 75 11 37",
    "sg:postcode":"48014",
    "sg:province":"Vizcaya",
    "wof:name":"Maria Esther Olea Fernandez",
    "wof:placetype":"venue"
},
  "geometry": {"coordinates":[-2.9459071159,43.2702102661],"type":"Point"}
}