{
  "type": "Feature",
  "properties": {
    "iso:country":"ES",
    "sg:address":"Carrer de Gremi De Tintorers, 17",
    "sg:city":"Poligon Industrial De Son Castello",
    "sg:orig_category":"Fotograf\u00cda Y Cine: Aparatos, Pel\u00cdculas Y Accesorios (al Por Menor)",
    "sg:phone":"+34 971 43 43 82",
    "sg:postcode":"07009",
    "sg:province":"Islas Baleares",
    "wof:name":"The Balearic Ligthouse S.l.",
    "wof:placetype":"venue"
},
  "geometry": {"coordinates":[2.6776249409,39.6072845459],"type":"Point"}
}