{
  "type": "Feature",
  "properties": {
    "iso:country":"ES",
    "sg:address":"Calle de Gran Via, 5",
    "sg:city":"Zaragoza",
    "sg:orig_category":"Abogados",
    "sg:phone":"+34 976 22 95 04",
    "sg:postcode":"50006",
    "sg:province":"Zaragoza",
    "wof:name":"Aznar Alonso Angel",
    "wof:placetype":"venue"
},
  "geometry": {"coordinates":[-0.8861470222,41.6465301514],"type":"Point"}
}