{
  "type": "Feature",
  "properties": {
    "iso:country":"ES",
    "sg:address":"Avda Juan Gris (de), 4",
    "sg:city":"Mejorada Campo",
    "sg:orig_category":"Molduras, Junquillos, Listones Y Molduras Perforadas",
    "sg:phone":"+34 916 68 22 92",
    "sg:postcode":"28840",
    "sg:province":"Madrid",
    "wof:name":"Vizcaino Nieto Joaquin",
    "wof:placetype":"venue"
},
  "geometry": {"coordinates":[-3.4838366508,40.3934326172],"type":"Point"}
}