{
  "type": "Feature",
  "properties": {
    "addr:full":"Av Diputacio, 162 Cambrils Tarragona 43850",
    "addr:housenumber":"162",
    "addr:postcode":"43850",
    "addr:street":"Av Diputacio",
    "iso:country":"ES",
    "sg:address":"Av Diputacio, 162",
    "sg:city":"Cambrils",
    "sg:orig_category":"Supermercados Y Hipermercados",
    "sg:phone":"+34 977 38 20 56",
    "sg:postcode":"43850",
    "sg:province":"Tarragona",
    "wof:name":"Porqueras Marine Jordi",
    "wof:placetype":"venue"
},
  "geometry": {"coordinates":[1.1078599691,41.072429657],"type":"Point"}
}