{
  "type": "Feature",
  "properties": {
    "iso:country":"ES",
    "sg:address":"Calle de Pura Gutierrez, 2",
    "sg:city":"Malaga",
    "sg:orig_category":"Mec\u00c1nico Del Autom\u00d3vil",
    "sg:phone":"+34 952 26 72 49",
    "sg:postcode":"29014",
    "sg:province":"M\u00e1laga",
    "wof:name":"Blanco Martinez Rafael",
    "wof:placetype":"venue"
},
  "geometry": {"coordinates":[-4.4211068153,36.7446174622],"type":"Point"}
}