{
  "type": "Feature",
  "properties": {
    "iso:country":"ES",
    "sg:address":"Carrer de Consell De Cent, 490",
    "sg:city":"Barcelona",
    "sg:orig_category":"Impresi\u00d3n Digital",
    "sg:phone":"+34 932 44 47 66",
    "sg:postcode":"08013",
    "sg:province":"Barcelona",
    "wof:name":"Abast Serveis Grafics S.l.",
    "wof:placetype":"venue"
},
  "geometry": {"coordinates":[2.17826,41.400501],"type":"Point"}
}