{
  "type": "Feature",
  "properties": {
    "addr:full":"Calle de Cervantes, 10 S. Nicolas Tolentino Las Palmas 35470",
    "addr:housenumber":"10",
    "addr:postcode":"35470",
    "addr:street":"Calle De Cervantes;Nicolas Tolentino Las",
    "iso:country":"ES",
    "sg:address":"Calle de Cervantes, 10",
    "sg:city":"S. Nicolas Tolentino",
    "sg:orig_category":"Arquitectos",
    "sg:phone":"+34 928 89 10 12",
    "sg:postcode":"35470",
    "sg:province":"Las Palmas",
    "wof:name":"Suarez Ruiz Hector",
    "wof:placetype":"venue"
},
  "geometry": {"coordinates":[-15.7804841995,27.9842662811],"type":"Point"}
}