{
  "type": "Feature",
  "properties": {
    "addr:full":"Calle de Damasco, 8 Cordoba C\u00f3rdoba 14004",
    "addr:housenumber":"8",
    "addr:postcode":"14004",
    "addr:street":"Calle De Damasco;Co\u0301Rdoba",
    "iso:country":"ES",
    "sg:address":"Calle de Damasco, 8",
    "sg:city":"Cordoba",
    "sg:orig_category":"Confecci\u00d3n De Trajes Para Se\u00d1oras",
    "sg:phone":"+34 957 45 63 14",
    "sg:postcode":"14004",
    "sg:province":"C\u00f3rdoba",
    "wof:name":"Anguita Morales Manuela",
    "wof:placetype":"venue"
},
  "geometry": {"coordinates":[-4.7903356552,37.8810195923],"type":"Point"}
}