{
  "type": "Feature",
  "properties": {
    "iso:country":"ES",
    "sg:address":"Calle de Dr Fleming (del), 23",
    "sg:city":"Coslada",
    "sg:orig_category":"Droguer\u00cdas (al Por Menor)",
    "sg:phone":"+34 916 71 18 03",
    "sg:postcode":"28820",
    "sg:province":"Madrid",
    "wof:name":"Elujada S.l",
    "wof:placetype":"venue"
},
  "geometry": {"coordinates":[-3.5664374828,40.4237480164],"type":"Point"}
}