{
  "type": "Feature",
  "properties": {
    "addr:full":"Ctra Camposancos, 347 Verdeal Pontevedra 36390",
    "addr:housenumber":"347",
    "addr:postcode":"36390",
    "addr:street":"Ctra Camposancos",
    "iso:country":"ES",
    "sg:address":"Ctra Camposancos, 347",
    "sg:city":"Verdeal",
    "sg:orig_category":"Restaurantes",
    "sg:phone":"+34 986 46 09 13",
    "sg:postcode":"36390",
    "sg:province":"Pontevedra",
    "sg:website":"www.cateringdonpepe.com",
    "wof:name":"Gonzalez Fernandez Jose Domingo",
    "wof:placetype":"venue"
},
  "geometry": {"coordinates":[-8.798915863,42.1908302307],"type":"Point"}
}