{
  "type": "Feature",
  "properties": {
    "addr:full":"Calle de Colibri (del), 2 Puerto De Santa Maria C\u00e1diz 11500",
    "addr:postcode":"11500",
    "addr:street":"Calle De Colibri Del 2;Ca\u0301Diz",
    "iso:country":"ES",
    "sg:address":"Calle de Colibri (del), 2",
    "sg:city":"Puerto De Santa Maria",
    "sg:orig_category":"Guarder\u00cdas",
    "sg:phone":"+34 956 85 42 52",
    "sg:postcode":"11500",
    "sg:province":"C\u00e1diz",
    "wof:name":"Mu\u00f1oz Leyva Agustin",
    "wof:placetype":"venue"
},
  "geometry": {"coordinates":[-6.2316474915,36.5934486389],"type":"Point"}
}