{
  "type": "Feature",
  "properties": {
    "iso:country":"ES",
    "sg:address":"Calle de Quejigos, 11",
    "sg:city":"Ciudad Real",
    "sg:orig_category":"Agencias Y Agentes Comerciales, Representantes",
    "sg:phone":"+34 926 21 49 00",
    "sg:postcode":"13002",
    "sg:province":"Ciudad Real",
    "wof:name":"Gallego Soto Antolin",
    "wof:placetype":"venue"
},
  "geometry": {"coordinates":[-3.9367170334,38.9801521301],"type":"Point"}
}