{
  "type": "Feature",
  "properties": {
    "addr:full":"Avda Marcelino Suarez, 2 Barco Ourense 32300",
    "addr:housenumber":"2",
    "addr:postcode":"32300",
    "addr:street":"Avda Marcelino Suarez",
    "iso:country":"ES",
    "sg:address":"Avda Marcelino Suarez, 2",
    "sg:city":"Barco",
    "sg:orig_category":"Cajas De Ahorro",
    "sg:phone":"+34 988 34 74 32",
    "sg:postcode":"32300",
    "sg:province":"Ourense",
    "sg:website":"www.cajaespana.es",
    "wof:name":"Caja Espa\u00f1a De Inversiones Caja De Ahorros Y Monte De Piedad",
    "wof:placetype":"venue"
},
  "geometry": {"coordinates":[-6.9837059975,42.4104614258],"type":"Point"}
}