{
  "type": "Feature",
  "properties": {
    "iso:country":"ES",
    "sg:address":"Avda Ejercito, 29",
    "sg:city":"Coru\u00d1a",
    "sg:orig_category":"Bazares, Art\u00cdculos De Limpieza Y De Cocina (al Por Menor)",
    "sg:phone":"+34 981 29 48 91",
    "sg:postcode":"15006",
    "sg:province":"La Coru\u00f1a",
    "wof:name":"Mundicien S.l.",
    "wof:placetype":"venue"
},
  "geometry": {"coordinates":[-8.3904466629,43.353012085],"type":"Point"}
}