{
  "type": "Feature",
  "properties": {
    "iso:country":"ES",
    "sg:address":"Avda Miguel De Cervantes, 118",
    "sg:city":"Tarancon",
    "sg:orig_category":"Peluquer\u00cdas, Peluquer\u00cda Mixta",
    "sg:phone":"+34 969 32 58 91",
    "sg:postcode":"16400",
    "sg:province":"Cuenca",
    "wof:name":"Lopez Lopez Santiago",
    "wof:placetype":"venue"
},
  "geometry": {"coordinates":[-3.0179569721,40.0112686157],"type":"Point"}
}