{
  "type": "Feature",
  "properties": {
    "iso:country":"ES",
    "sg:address":"Calle de Carrion, 37",
    "sg:city":"Pilas",
    "sg:orig_category":"Poli\u00c9ster",
    "sg:phone":"+34 955 75 22 40",
    "sg:postcode":"41840",
    "sg:province":"Sevilla",
    "sg:website":"www.fabricadosmaraver.es",
    "wof:name":"Fabricados De Poliester Maraver Lara S.l.",
    "wof:placetype":"venue"
},
  "geometry": {"coordinates":[-6.3051953316,37.3103065491],"type":"Point"}
}