{
  "type": "Feature",
  "properties": {
    "iso:country":"ES",
    "sg:address":"Calle de Santiago Amon, 4",
    "sg:city":"Aguilar Campoo",
    "sg:orig_category":"Institutos De Belleza",
    "sg:phone":"+34 979 12 30 83",
    "sg:postcode":"34800",
    "sg:province":"Palencia",
    "wof:name":"Diez Cajigal Elizabeth",
    "wof:placetype":"venue"
},
  "geometry": {"coordinates":[-4.2648310661,42.7943954468],"type":"Point"}
}