{
  "type": "Feature",
  "properties": {
    "addr:full":"Afueras, S/n Las Huertas Cansa C\u00e1ceres 10514",
    "addr:postcode":"10514",
    "addr:street":"Afueras S / N Las Huertas Cansa Ca\u0301Ceres",
    "iso:country":"ES",
    "sg:address":"Afueras, S/n",
    "sg:city":"Las Huertas Cansa",
    "sg:orig_category":"Iglesia Cat\u00d3lica",
    "sg:phone":"+34 927 58 40 21",
    "sg:postcode":"10514",
    "sg:province":"C\u00e1ceres",
    "wof:name":"Parroquia De La Concepcion Del Pino",
    "wof:placetype":"venue"
},
  "geometry": {"coordinates":[-7.2795028687,39.3322639465],"type":"Point"}
}