{
  "type": "Feature",
  "properties": {
    "addr:full":"Calle de Cruz De Marmol, S/n Aracena Huelva 21200",
    "addr:housenumber":"s / n",
    "addr:postcode":"21200",
    "addr:street":"Calle De Cruz De Marmol",
    "iso:country":"ES",
    "sg:address":"Calle de Cruz De Marmol, S/n",
    "sg:city":"Aracena",
    "sg:orig_category":"Mec\u00c1nico Del Autom\u00d3vil",
    "sg:phone":"+34 959 12 89 56",
    "sg:postcode":"21200",
    "sg:province":"Huelva",
    "wof:name":"Delgado Lanne Jose Luis",
    "wof:placetype":"venue"
},
  "geometry": {"coordinates":[-6.5661730766,37.8974494934],"type":"Point"}
}