{
  "type": "Feature",
  "properties": {
    "addr:full":"Avda Santa Isabel, 72 Zaragoza Zaragoza 50016",
    "addr:housenumber":"72",
    "addr:postcode":"50016",
    "addr:street":"Avda Santa Isabel",
    "iso:country":"ES",
    "sg:address":"Avda Santa Isabel, 72",
    "sg:city":"Zaragoza",
    "sg:orig_category":"Comerciantes Al Por Mayor De Vinos, Licores Y Alcoholes",
    "sg:phone":"+34 976 57 05 30",
    "sg:postcode":"50016",
    "sg:province":"Zaragoza",
    "wof:name":"Perdiguer Pallares Fernando",
    "wof:placetype":"venue"
},
  "geometry": {"coordinates":[-0.8327299953,41.667011261],"type":"Point"}
}