{
  "type": "Feature",
  "properties": {
    "addr:full":"Calle de Real Utrera, 138 Dos Hermanas Sevilla 41700",
    "addr:housenumber":"138",
    "addr:postcode":"41700",
    "addr:street":"Calle De;Utrera;Sevilla",
    "iso:country":"ES",
    "sg:address":"Calle de Real Utrera, 138",
    "sg:city":"Dos Hermanas",
    "sg:orig_category":"Reposter\u00cdas",
    "sg:phone":"+34 954 72 07 13",
    "sg:postcode":"41700",
    "sg:province":"Sevilla",
    "wof:name":"Franco Jimenez Juan",
    "wof:placetype":"venue"
},
  "geometry": {"coordinates":[-5.9180679321,37.2801780701],"type":"Point"}
}