{
  "type": "Feature",
  "properties": {
    "addr:full":"Calle de Martin Frago, 2 Barbastro Huesca 22300",
    "addr:housenumber":"2",
    "addr:postcode":"22300",
    "addr:street":"Calle De Martin Frago",
    "iso:country":"ES",
    "sg:address":"Calle de Martin Frago, 2",
    "sg:city":"Barbastro",
    "sg:orig_category":"Electricidad: Instaladores",
    "sg:phone":"+34 974 31 30 51",
    "sg:postcode":"22300",
    "sg:province":"Huesca",
    "wof:name":"Electricidad Barra-naval S.l.",
    "wof:placetype":"venue"
},
  "geometry": {"coordinates":[0.130824998,42.0317459106],"type":"Point"}
}