{
  "type": "Feature",
  "properties": {
    "addr:full":"Ctra Cadiz De, Km. 0235,0 Torremolinos M\u00e1laga 29620",
    "addr:postcode":"29620",
    "addr:street":"Ctra Cadiz De Km. 0235,0;Ma\u0301Laga",
    "iso:country":"ES",
    "sg:address":"Ctra Cadiz De, Km. 0235,0",
    "sg:city":"Torremolinos",
    "sg:orig_category":"Distribuci\u00d3n De Petr\u00d3leo Y Derivados",
    "sg:phone":"+34 952 37 51 54",
    "sg:postcode":"29620",
    "sg:province":"M\u00e1laga",
    "wof:name":"Anher S. L.",
    "wof:placetype":"venue"
},
  "geometry": {"coordinates":[-4.4979224205,36.6372871399],"type":"Point"}
}