{
  "type": "Feature",
  "properties": {
    "addr:full":"Centro Comercial Dendaraba, S/n Vitoria-gasteiz \u00c1lava 01004",
    "addr:housenumber":"s",
    "addr:postcode":"01004",
    "addr:street":"/ N",
    "iso:country":"ES",
    "sg:address":"Centro Comercial Dendaraba, S/n",
    "sg:city":"Vitoria-gasteiz",
    "sg:orig_category":"Trajes Y Adornos De Boda (confecci\u00d3n, Al Por Menor)",
    "sg:phone":"+34 945 23 43 92",
    "sg:postcode":"01004",
    "sg:province":"\u00c1lava",
    "wof:name":"Borgia C.b.",
    "wof:placetype":"venue"
},
  "geometry": {"coordinates":[-2.6666500568,42.8437004089],"type":"Point"}
}