{
  "type": "Feature",
  "properties": {
    "iso:country":"ES",
    "sg:address":"Plaz San Juan Bautista, 19",
    "sg:city":"Abenojar",
    "sg:orig_category":"Asesor\u00cda Sobre Comunicaci\u00d3n De Empresas",
    "sg:phone":"+34 926 83 50 58",
    "sg:postcode":"13180",
    "sg:province":"Ciudad Real",
    "wof:name":"Alcalde Rodriguez Elena",
    "wof:placetype":"venue"
},
  "geometry": {"coordinates":[-4.3575663567,38.8796768188],"type":"Point"}
}