{
  "type": "Feature",
  "properties": {
    "addr:full":"Calle de Mayor, 3 Moratalla Murcia 30440",
    "addr:housenumber":"3",
    "addr:postcode":"30440",
    "addr:street":"Calle De Mayor",
    "iso:country":"ES",
    "sg:address":"Calle de Mayor, 3",
    "sg:city":"Moratalla",
    "sg:orig_category":"Iglesia Cat\u00d3lica",
    "sg:phone":"+34 968 73 01 60",
    "sg:postcode":"30440",
    "sg:province":"Murcia",
    "wof:name":"Obispado De Cartagena",
    "wof:placetype":"venue"
},
  "geometry": {"coordinates":[-1.8935279846,38.1908340454],"type":"Point"}
}