{
  "type": "Feature",
  "properties": {
    "iso:country":"ES",
    "sg:address":"Calle de Antonia Merce, 2",
    "sg:city":"Madrid",
    "sg:orig_category":"Arquitectos",
    "sg:phone":"+34 915 76 35 26",
    "sg:postcode":"28009",
    "sg:province":"Madrid",
    "wof:name":"Olive Bonafe Jesus",
    "wof:placetype":"venue"
},
  "geometry": {"coordinates":[-3.673032999,40.4233627319],"type":"Point"}
}