{
  "type": "Feature",
  "properties": {
    "addr:full":"Calle de Ramon Y Cajal, 43 Escairon Lugo 27540",
    "addr:housenumber":"43",
    "addr:postcode":"27540",
    "addr:street":"Calle De Ramon Y Cajal",
    "iso:country":"ES",
    "sg:address":"Calle de Ramon Y Cajal, 43",
    "sg:city":"Escairon",
    "sg:orig_category":"Fabricaci\u00d3n De Quesos",
    "sg:phone":"+34 982 45 30 02",
    "sg:postcode":"27540",
    "sg:province":"Lugo",
    "wof:name":"Escairon S.l.",
    "wof:placetype":"venue"
},
  "geometry": {"coordinates":[-7.6367201805,42.584236145],"type":"Point"}
}