{
  "type": "Feature",
  "properties": {
    "addr:full":"Ctra. Andalucia, Km. 0081,0 Guardia Toledo 45760",
    "addr:postcode":"45760",
    "addr:street":"Ctra. Andalucia Km. 0081,0 Guardia",
    "iso:country":"ES",
    "sg:address":"Ctra. Andalucia, Km. 0081,0",
    "sg:city":"Guardia",
    "sg:orig_category":"Refiner\u00cdas De Petr\u00d3leo",
    "sg:phone":"+34 925 13 83 52",
    "sg:postcode":"45760",
    "sg:province":"Toledo",
    "wof:name":"Distribuciones Petroliferas Magdalena S.l.",
    "wof:placetype":"venue"
},
  "geometry": {"coordinates":[-3.4772589207,39.7863616943],"type":"Point"}
}