{
  "type": "Feature",
  "properties": {
    "addr:full":"Calle de Huertas, 48 Membrilla Ciudad Real 13230",
    "addr:housenumber":"48",
    "addr:postcode":"13230",
    "addr:street":"Calle De Huertas",
    "iso:country":"ES",
    "sg:address":"Calle de Huertas, 48",
    "sg:city":"Membrilla",
    "sg:orig_category":"Promotores Constructores",
    "sg:phone":"+34 926 63 62 35",
    "sg:postcode":"13230",
    "sg:province":"Ciudad Real",
    "wof:name":"Marquez Jimenez Alfonso",
    "wof:placetype":"venue"
},
  "geometry": {"coordinates":[-3.3457918167,38.9672660828],"type":"Point"}
}