{
  "type": "Feature",
  "properties": {
    "addr:full":"Calle de Manuel Junquera, 10 Gijon Asturias 33204",
    "addr:housenumber":"10",
    "addr:postcode":"33204",
    "addr:street":"Calle De Manuel Junquera",
    "iso:country":"ES",
    "sg:address":"Calle de Manuel Junquera, 10",
    "sg:city":"Gijon",
    "sg:orig_category":"Reparaciones Y Remolcado De Veh\u00cdculos",
    "sg:phone":"+34 985 36 71 57",
    "sg:postcode":"33204",
    "sg:province":"Asturias",
    "wof:name":"Costales Meana Jose Ramon",
    "wof:placetype":"venue"
},
  "geometry": {"coordinates":[-5.6536641121,43.5303344727],"type":"Point"}
}