{
  "type": "Feature",
  "properties": {
    "iso:country":"ES",
    "sg:address":"Carr Torras I Bages, 10",
    "sg:city":"Figueres",
    "sg:orig_category":"Asesor\u00cdas",
    "sg:phone":"+34 972 67 48 29",
    "sg:postcode":"17600",
    "sg:province":"Girona",
    "wof:name":"Federal Serveis Auxiliars S.l.",
    "wof:placetype":"venue"
},
  "geometry": {"coordinates":[2.9642050266,42.2590866089],"type":"Point"}
}