{
  "type": "Feature",
  "properties": {
    "addr:full":"Calle de Zizeruena, 12 Bilbao Vizcaya 48004",
    "addr:housenumber":"12",
    "addr:postcode":"48004",
    "addr:street":"Calle De Zizeruena",
    "iso:country":"ES",
    "sg:address":"Calle de Zizeruena, 12",
    "sg:city":"Bilbao",
    "sg:orig_category":"Frutas, Legumbres Frescas Y Tempranas (al Por Menor)",
    "sg:phone":"+34 944 12 93 57",
    "sg:postcode":"48004",
    "sg:province":"Vizcaya",
    "wof:name":"Martin Fernandez Juana",
    "wof:placetype":"venue"
},
  "geometry": {"coordinates":[-2.900603056,43.2613105774],"type":"Point"}
}