{
  "type": "Feature",
  "properties": {
    "addr:full":"Calle de Valencia, 27 Placa Le\u00f3n 24400",
    "addr:housenumber":"27",
    "addr:postcode":"24400",
    "addr:street":"Calle De Valencia;Placa Leo\u0301N",
    "iso:country":"ES",
    "sg:address":"Calle de Valencia, 27",
    "sg:city":"Placa",
    "sg:orig_category":"Empresas De Carpinter\u00cda Met\u00c1lica",
    "sg:phone":"+34 987 42 72 03",
    "sg:postcode":"24400",
    "sg:province":"Le\u00f3n",
    "wof:name":"Talleres La Placa S.l.",
    "wof:placetype":"venue"
},
  "geometry": {"coordinates":[-6.6296749115,42.5503044128],"type":"Point"}
}