{
  "type": "Feature",
  "properties": {
    "iso:country":"ES",
    "sg:address":"Afueras, Km. 0031,0",
    "sg:city":"Acehuche",
    "sg:orig_category":"T\u00c9cnicos Veterinarios",
    "sg:phone":"+34 927 19 10 30",
    "sg:postcode":"10879",
    "sg:province":"C\u00e1ceres",
    "wof:name":"Martin Perez Santiago",
    "wof:placetype":"venue"
},
  "geometry": {"coordinates":[-6.6282792091,39.8044509888],"type":"Point"}
}