{
  "type": "Feature",
  "properties": {
    "addr:full":"Carrer de Joanot Martorell, 14 Novelda Alicante 03660",
    "addr:housenumber":"14",
    "addr:postcode":"03660",
    "addr:street":"Carrer De Joanot Martorell",
    "iso:country":"ES",
    "sg:address":"Carrer de Joanot Martorell, 14",
    "sg:city":"Novelda",
    "sg:orig_category":"Estancos",
    "sg:phone":"+34 965 60 08 83",
    "sg:postcode":"03660",
    "sg:province":"Alicante",
    "wof:name":"Torreblanca Fernandez David",
    "wof:placetype":"venue"
},
  "geometry": {"coordinates":[-0.7616580129,38.3870010376],"type":"Point"}
}