{
  "type": "Feature",
  "properties": {
    "addr:full":"Calle de San Miguel, 33 Armilla Granada 18100",
    "addr:housenumber":"33",
    "addr:postcode":"18100",
    "addr:street":"Calle De San Miguel",
    "iso:country":"ES",
    "sg:address":"Calle de San Miguel, 33",
    "sg:city":"Armilla",
    "sg:orig_category":"Art\u00cdculos Para Fumadores (al Por Menor)",
    "sg:phone":"+34 958 55 18 84",
    "sg:postcode":"18100",
    "sg:province":"Granada",
    "wof:name":"Fernandez Mochon Antonio",
    "wof:placetype":"venue"
},
  "geometry": {"coordinates":[-3.6220450401,37.1452980042],"type":"Point"}
}