{
  "type": "Feature",
  "properties": {
    "addr:full":"Carrer de Industria, 83 Barcelona Barcelona 08025",
    "addr:housenumber":"83",
    "addr:postcode":"08025",
    "addr:street":"Carrer De Industria",
    "iso:country":"ES",
    "sg:address":"Carrer de Industria, 83",
    "sg:city":"Barcelona",
    "sg:orig_category":"Plomeros",
    "sg:phone":"+34 932 07 12 92",
    "sg:postcode":"08025",
    "sg:province":"Barcelona",
    "wof:name":"Alonso Pelegrin Diego",
    "wof:placetype":"venue"
},
  "geometry": {"coordinates":[2.1693739891,41.4058036804],"type":"Point"}
}