{
  "type": "Feature",
  "properties": {
    "iso:country":"ES",
    "sg:address":"Carrer de Major (sant Celoni), 221",
    "sg:city":"S. Celoni",
    "sg:orig_category":"Empresarios",
    "sg:phone":"+34 938 67 55 82",
    "sg:postcode":"08470",
    "sg:province":"Barcelona",
    "wof:name":"Comunidad De Propietarios Major 221",
    "wof:placetype":"venue"
},
  "geometry": {"coordinates":[2.4957919121,41.6918907166],"type":"Point"}
}