{
  "type": "Feature",
  "properties": {
    "iso:country":"ES",
    "sg:address":"Calle de Malague\u00d1a, 86",
    "sg:city":"Argana Alta",
    "sg:orig_category":"Supermercados Y Hipermercados",
    "sg:phone":"+34 928 81 67 73",
    "sg:postcode":"35500",
    "sg:province":"Las Palmas",
    "wof:name":"Garcia Tejera Teodoro Alfredo",
    "wof:placetype":"venue"
},
  "geometry": {"coordinates":[-13.5668649673,28.978603363],"type":"Point"}
}