{
  "type": "Feature",
  "properties": {
    "addr:full":"Ctra Sierra (de La), 130 Granada Granada 18008",
    "addr:housenumber":"130",
    "addr:postcode":"18008",
    "addr:street":"Ctra Sierra De La",
    "iso:country":"ES",
    "sg:address":"Ctra Sierra (de La), 130",
    "sg:city":"Granada",
    "sg:orig_category":"Confecci\u00d3n De Trajes Para Se\u00d1oras",
    "sg:phone":"+34 958 22 25 21",
    "sg:postcode":"18008",
    "sg:province":"Granada",
    "wof:name":"A.s.seleccion S.l.",
    "wof:placetype":"venue"
},
  "geometry": {"coordinates":[-3.5700581074,37.1627006531],"type":"Point"}
}