{
  "type": "Feature",
  "properties": {
    "iso:country":"ES",
    "sg:address":"Barr Cinca (del), S/n",
    "sg:city":"Grado",
    "sg:orig_category":"Oficinas De Turismo, Asociaciones De Iniciativa",
    "sg:phone":"+34 974 30 40 21",
    "sg:postcode":"22390",
    "sg:province":"Huesca",
    "wof:name":"Ayuntamiento De El Grado",
    "wof:placetype":"venue"
},
  "geometry": {"coordinates":[-0.4088979959,42.1401023865],"type":"Point"}
}