{
  "type": "Feature",
  "properties": {
    "iso:country":"ES",
    "sg:address":"Calle de Marques De Urquijo, 47",
    "sg:city":"Madrid",
    "sg:orig_category":"Arquitectos",
    "sg:phone":"+34 915 47 78 54",
    "sg:postcode":"28008",
    "sg:province":"Madrid",
    "wof:name":"Rubio Abad Pedro Rafael",
    "wof:placetype":"venue"
},
  "geometry": {"coordinates":[-3.7213690281,40.4288444519],"type":"Point"}
}