{
  "type": "Feature",
  "properties": {
    "addr:full":"Plaz Generalisimo, 4 Sanchidrian \u00c1vila 05290",
    "addr:housenumber":"4",
    "addr:postcode":"05290",
    "addr:street":"Plaz Generalisimo;A\u0301Vila",
    "iso:country":"ES",
    "sg:address":"Plaz Generalisimo, 4",
    "sg:city":"Sanchidrian",
    "sg:orig_category":"Pescader\u00cdas (al Por Menor)",
    "sg:phone":"+34 920 31 82 53",
    "sg:postcode":"05290",
    "sg:province":"\u00c1vila",
    "wof:name":"Martinez Lopez Juan Antonio",
    "wof:placetype":"venue"
},
  "geometry": {"coordinates":[-4.5814862251,40.8933258057],"type":"Point"}
}