{
  "type": "Feature",
  "properties": {
    "addr:full":"Calle de Manuel Iradier, 86 Vitoria-gasteiz \u00c1lava 01005",
    "addr:housenumber":"86",
    "addr:postcode":"01005",
    "addr:street":"Calle De Manuel Iradier",
    "iso:country":"ES",
    "sg:address":"Calle de Manuel Iradier, 86",
    "sg:city":"Vitoria-gasteiz",
    "sg:orig_category":"Venta, Instalaci\u00d3n, Reparaci\u00d3n De Antenas Para Televisi\u00d3n",
    "sg:phone":"+34 945 25 48 83",
    "sg:postcode":"01005",
    "sg:province":"\u00c1lava",
    "wof:name":"Instalaciones Electricas Teleantena S.l.",
    "wof:placetype":"venue"
},
  "geometry": {"coordinates":[-2.6673049927,42.8410797119],"type":"Point"}
}