{
  "type": "Feature",
  "properties": {
    "addr:full":"Calle de Cadiz, 48 Ibi Alicante 03440",
    "addr:housenumber":"48",
    "addr:postcode":"03440",
    "addr:street":"Calle De Cadiz",
    "iso:country":"ES",
    "sg:address":"Calle de Cadiz, 48",
    "sg:city":"Ibi",
    "sg:orig_category":"Pintura Industrial (trabajos De)",
    "sg:phone":"+34 966 55 20 71",
    "sg:postcode":"03440",
    "sg:province":"Alicante",
    "wof:name":"Teocolor S.l.",
    "wof:placetype":"venue"
},
  "geometry": {"coordinates":[-0.5930190086,38.6157608032],"type":"Point"}
}