{
  "type": "Feature",
  "properties": {
    "iso:country":"ES",
    "sg:address":"Av President Companys, 20",
    "sg:city":"Reus",
    "sg:orig_category":"Peluquer\u00cdas, Peluquer\u00cda Mixta",
    "sg:phone":"+34 977 31 78 46",
    "sg:postcode":"43201",
    "sg:province":"Tarragona",
    "wof:name":"Amat Carrillo Mireia",
    "wof:placetype":"venue"
},
  "geometry": {"coordinates":[1.1028602123,41.1547698975],"type":"Point"}
}