{
  "type": "Feature",
  "properties": {
    "iso:country":"ES",
    "sg:address":"Avda Mariano Andres, 64",
    "sg:city":"Le\u00f3n",
    "sg:orig_category":"Quincaller\u00cda (al Por Menor)",
    "sg:phone":"+34 987 22 72 88",
    "sg:postcode":"24008",
    "sg:province":"Le\u00f3n",
    "wof:name":"Redondo Sanz Leonardo",
    "wof:placetype":"venue"
},
  "geometry": {"coordinates":[-5.5720758438,42.608795166],"type":"Point"}
}