{
  "type": "Feature",
  "properties": {
    "iso:country":"ES",
    "sg:address":"Carrer de Jaume I, 11",
    "sg:city":"Montcada Centre",
    "sg:orig_category":"Cr\u00cda De Animales",
    "sg:phone":"+34 935 64 25 36",
    "sg:postcode":"08110",
    "sg:province":"Barcelona",
    "wof:name":"Lopez Hernandez Manuel",
    "wof:placetype":"venue"
},
  "geometry": {"coordinates":[2.1817660332,41.4890899658],"type":"Point"}
}