{
  "type": "Feature",
  "properties": {
    "addr:full":"Calle de Nueva Monta\u00d1a, 56 Campo Criptana Ciudad Real 13610",
    "addr:housenumber":"56",
    "addr:postcode":"13610",
    "addr:street":"Calle De Nueva Montan\u0303A;Criptana",
    "iso:country":"ES",
    "sg:address":"Calle de Nueva Monta\u00d1a, 56",
    "sg:city":"Campo Criptana",
    "sg:orig_category":"Chapister\u00cda",
    "sg:phone":"+34 926 56 05 61",
    "sg:postcode":"13610",
    "sg:province":"Ciudad Real",
    "wof:name":"Palomino Martin Jose",
    "wof:placetype":"venue"
},
  "geometry": {"coordinates":[-3.1264090538,39.401550293],"type":"Point"}
}