{
  "type": "Feature",
  "properties": {
    "addr:full":"Cami Nou, 3 Agramunt Lleida 25310",
    "addr:housenumber":"3",
    "addr:postcode":"25310",
    "addr:street":"Nou",
    "iso:country":"ES",
    "sg:address":"Cami Nou, 3",
    "sg:city":"Agramunt",
    "sg:orig_category":"Fabricaci\u00d3n Y Venta De Volquetes Y Remolques",
    "sg:phone":"+34 973 39 23 53",
    "sg:postcode":"25310",
    "sg:province":"Lleida",
    "wof:name":"Canigo Remolcs S.l.",
    "wof:placetype":"venue"
},
  "geometry": {"coordinates":[1.1011699438,41.7841110229],"type":"Point"}
}