{
  "type": "Feature",
  "properties": {
    "iso:country":"ES",
    "sg:address":"Calle de Se\u00d1era, 7",
    "sg:city":"Albal",
    "sg:orig_category":"Ingeniero",
    "sg:phone":"+34 961 27 31 17",
    "sg:postcode":"46470",
    "sg:province":"Valencia",
    "wof:name":"Inteval Del Mediterrani",
    "wof:placetype":"venue"
},
  "geometry": {"coordinates":[-0.4118449986,39.3983802795],"type":"Point"}
}