{
  "type": "Feature",
  "properties": {
    "addr:full":"Pol Ind El Monete, 80 Valverde Camino Huelva 21600",
    "addr:housenumber":"80",
    "addr:postcode":"21600",
    "addr:street":"Monete;Camino Huelva",
    "iso:country":"ES",
    "sg:address":"Pol Ind El Monete, 80",
    "sg:city":"Valverde Camino",
    "sg:orig_category":"Materias Pl\u00c1sticas: Productos De Consumo Masivo (fabricaci\u00d3n, Al Por Mayor)",
    "sg:phone":"+34 959 55 58 80",
    "sg:postcode":"21600",
    "sg:province":"Huelva",
    "wof:name":"Plasticos Carrillo S.l.",
    "wof:placetype":"venue"
},
  "geometry": {"coordinates":[-6.7534661293,37.576335907],"type":"Point"}
}