{
  "type": "Feature",
  "properties": {
    "addr:full":"Poligono 1, S/n Pollen\u00e7a Islas Baleares 07460",
    "addr:housenumber":"s / n",
    "addr:postcode":"07460",
    "addr:street":"Poligono 1",
    "iso:country":"ES",
    "sg:address":"Poligono 1, S/n",
    "sg:city":"Pollen\u00e7a",
    "sg:orig_category":"Agencias Y Agentes Comerciales, Representantes",
    "sg:phone":"+34 971 53 39 01",
    "sg:postcode":"07460",
    "sg:province":"Islas Baleares",
    "wof:name":"Moore  Christopher",
    "wof:placetype":"venue"
},
  "geometry": {"coordinates":[3.0375914574,39.8799629211],"type":"Point"}
}