{
  "type": "Feature",
  "properties": {
    "addr:full":"Calle de Corredera, 34 Vejer De La Frontera C\u00e1diz 11150",
    "addr:housenumber":"34",
    "addr:postcode":"11150",
    "addr:street":"Calle De Corredera",
    "iso:country":"ES",
    "sg:address":"Calle de Corredera, 34",
    "sg:city":"Vejer De La Frontera",
    "sg:orig_category":"Producci\u00d3n, Venta De Productos De Agricultura Biol\u00d3gica",
    "sg:phone":"+34 956 45 02 82",
    "sg:postcode":"11150",
    "sg:province":"C\u00e1diz",
    "wof:name":"Morillo Crespo Luis",
    "wof:placetype":"venue"
},
  "geometry": {"coordinates":[-5.9636101723,36.2543716431],"type":"Point"}
}