{
  "type": "Feature",
  "properties": {
    "addr:full":"Calle de Dos De Mayo, 18 Valladolid Valladolid 47004",
    "addr:housenumber":"18",
    "addr:postcode":"47004",
    "addr:street":"Calle De Dos;Mayo",
    "iso:country":"ES",
    "sg:address":"Calle de Dos De Mayo, 18",
    "sg:city":"Valladolid",
    "sg:orig_category":"M\u00c1quinas De Coser Y De Hacer Punto (al Por Mayor)",
    "sg:phone":"+34 983 30 98 64",
    "sg:postcode":"47004",
    "sg:province":"Valladolid",
    "wof:name":"Gomez Ruiz Jose Luis",
    "wof:placetype":"venue"
},
  "geometry": {"coordinates":[-4.7231502533,41.6460266113],"type":"Point"}
}