{
  "type": "Feature",
  "properties": {
    "iso:country":"ES",
    "sg:address":"Carrer de Salut, 91",
    "sg:city":"Palma",
    "sg:orig_category":"Arquitectos",
    "sg:phone":"+34 971 73 16 19",
    "sg:postcode":"07015",
    "sg:province":"Islas Baleares",
    "wof:name":"Puigfervet Mulet Francisca",
    "wof:placetype":"venue"
},
  "geometry": {"coordinates":[2.6220901012,39.5588264465],"type":"Point"}
}