{
  "type": "Feature",
  "properties": {
    "iso:country":"ES",
    "sg:address":"Calle de Sacristan Salvador Dominguez, 4",
    "sg:city":"Tocina",
    "sg:orig_category":"Ambulancias",
    "sg:phone":"+34 954 74 07 49",
    "sg:postcode":"41340",
    "sg:province":"Sevilla",
    "wof:name":"Guerrero Contreras Miguel",
    "wof:placetype":"venue"
},
  "geometry": {"coordinates":[-5.7342581749,37.611289978],"type":"Point"}
}