{
  "type": "Feature",
  "properties": {
    "iso:country":"ES",
    "sg:address":"Ptda Patar Aliaga, S/n",
    "sg:city":"Cheste",
    "sg:orig_category":"Agricultores, Agricultores",
    "sg:phone":"+34 962 51 02 34",
    "sg:postcode":"46380",
    "sg:province":"Valencia",
    "wof:name":"Sociedad Agricola Y Ganadera",
    "wof:placetype":"venue"
},
  "geometry": {"coordinates":[-0.6874480247,39.4945602417],"type":"Point"}
}