{
  "type": "Feature",
  "properties": {
    "addr:full":"Carrer de Gran De Sant Andreu, 456 Barcelona Barcelona 08030",
    "addr:housenumber":"456",
    "addr:postcode":"08030",
    "addr:street":"Carrer De Gran De Sant Andreu",
    "iso:country":"ES",
    "sg:address":"Carrer de Gran De Sant Andreu, 456",
    "sg:city":"Barcelona",
    "sg:orig_category":"Supermercados Y Hipermercados",
    "sg:phone":"+34 933 12 05 35",
    "sg:postcode":"08030",
    "sg:province":"Barcelona",
    "sg:website":"www.capraboacasa.com",
    "wof:name":"Caprabo S.a.",
    "wof:placetype":"venue"
},
  "geometry": {"coordinates":[2.1883859634,41.4415435791],"type":"Point"}
}