{
  "type": "Feature",
  "properties": {
    "addr:full":"Pla\u00c7 Pintor Segrelles (del), 13 Albaida Valencia 46860",
    "addr:postcode":"46860",
    "addr:street":"Pintor;Del",
    "iso:country":"ES",
    "sg:address":"Pla\u00c7 Pintor Segrelles (del), 13",
    "sg:city":"Albaida",
    "sg:orig_category":"Museos",
    "sg:phone":"+34 962 39 00 40",
    "sg:postcode":"46860",
    "sg:province":"Valencia",
    "wof:name":"Segrelles Tormo-martinez Concepcion",
    "wof:placetype":"venue"
},
  "geometry": {"coordinates":[-0.5197989941,38.8421478271],"type":"Point"}
}