{
  "type": "Feature",
  "properties": {
    "addr:full":"Rbla Egara, 151 Terrassa Barcelona 08224",
    "addr:housenumber":"151",
    "addr:postcode":"08224",
    "addr:street":"Rbla Egara",
    "iso:country":"ES",
    "sg:address":"Rbla Egara, 151",
    "sg:city":"Terrassa",
    "sg:orig_category":"Agencias De Viajes",
    "sg:phone":"+34 937 33 66 00",
    "sg:postcode":"08224",
    "sg:province":"Barcelona",
    "sg:website":"www.viajesiberia.com",
    "wof:name":"Viajes Iberia S.a.",
    "wof:placetype":"venue"
},
  "geometry": {"coordinates":[2.007486105,41.5616722107],"type":"Point"}
}