{
  "type": "Feature",
  "properties": {
    "addr:full":"Calle de General Benavides, 3 Ba\u00d1eza Le\u00f3n 24750",
    "addr:housenumber":"3",
    "addr:postcode":"24750",
    "addr:street":"Calle De General Benavides;Leo\u0301N",
    "iso:country":"ES",
    "sg:address":"Calle de General Benavides, 3",
    "sg:city":"Ba\u00d1eza",
    "sg:orig_category":"Panader\u00cdas, Panader\u00cdas",
    "sg:phone":"+34 987 64 02 80",
    "sg:postcode":"24750",
    "sg:province":"Le\u00f3n",
    "wof:name":"Mak & Vill S.l.",
    "wof:placetype":"venue"
},
  "geometry": {"coordinates":[-5.9242091179,42.3069114685],"type":"Point"}
}