{
  "type": "Feature",
  "properties": {
    "addr:full":"Carrer de Nou, 24 S. Boi Llobregat Barcelona 08830",
    "addr:housenumber":"24",
    "addr:postcode":"08830",
    "addr:street":"Carrer De Nou",
    "iso:country":"ES",
    "sg:address":"Carrer de Nou, 24",
    "sg:city":"S. Boi Llobregat",
    "sg:orig_category":"Contenedores (mercanc\u00cdas)",
    "sg:phone":"+34 936 40 74 53",
    "sg:postcode":"08830",
    "sg:province":"Barcelona",
    "wof:name":"Alemany Rebordosa Amadeu",
    "wof:placetype":"venue"
},
  "geometry": {"coordinates":[2.0399720669,41.347782135],"type":"Point"}
}