{
  "type": "Feature",
  "properties": {
    "addr:full":"Calle de Teatro, 13 Estepona M\u00e1laga 29680",
    "addr:housenumber":"13",
    "addr:postcode":"29680",
    "addr:street":"Calle De Teatro",
    "iso:country":"ES",
    "sg:address":"Calle de Teatro, 13",
    "sg:city":"Estepona",
    "sg:classifiers":[
        {
            "category":"Tea Room",
            "subcategory":"None",
            "type":"Food & Drink"
        }
    ],
    "sg:phone":"+34 952 79 43 54",
    "sg:postcode":"29680",
    "sg:province":"M\u00e1laga",
    "sg:tags":[
        "snack"
    ],
    "wof:name":"Barron  Francis",
    "wof:placetype":"venue"
},
  "geometry": {"coordinates":[-5.1420588493,36.4268875122],"type":"Point"}
}