{
  "type": "Feature",
  "properties": {
    "iso:country":"ES",
    "sg:address":"Alamos, 55",
    "sg:city":"Medina-sidonia",
    "sg:orig_category":"Distribuci\u00d3n De Petr\u00d3leo Y Derivados",
    "sg:phone":"+34 956 41 08 55",
    "sg:postcode":"11170",
    "sg:province":"C\u00e1diz",
    "wof:name":"Guerrero Sanchez Manuel",
    "wof:placetype":"venue"
},
  "geometry": {"coordinates":[-5.8074030876,36.3430709839],"type":"Point"}
}