{
  "type": "Feature",
  "properties": {
    "addr:full":"Calle de Aguilar, 70 Puente-genil C\u00f3rdoba 14500",
    "addr:housenumber":"70",
    "addr:postcode":"14500",
    "addr:street":"Calle De Aguilar;Co\u0301Rdoba",
    "iso:country":"ES",
    "sg:address":"Calle de Aguilar, 70",
    "sg:city":"Puente-genil",
    "sg:orig_category":"Agricultura: Abastecimiento Y Cosechado (negocio)",
    "sg:phone":"+34 957 60 30 12",
    "sg:postcode":"14500",
    "sg:province":"C\u00f3rdoba",
    "wof:name":"Rivas Rivas Francisco Domingo",
    "wof:placetype":"venue"
},
  "geometry": {"coordinates":[-4.77389431,37.3887672424],"type":"Point"}
}