{
  "type": "Feature",
  "properties": {
    "addr:full":"Calle de Zamakoa, 8 Kurtzea Vizcaya 48960",
    "addr:housenumber":"8",
    "addr:postcode":"48960",
    "addr:street":"Calle De Zamakoa",
    "iso:country":"ES",
    "sg:address":"Calle de Zamakoa, 8",
    "sg:city":"Kurtzea",
    "sg:orig_category":"Fabricaci\u00d3n De Ventanas",
    "sg:phone":"+34 944 57 05 03",
    "sg:postcode":"48960",
    "sg:province":"Vizcaya",
    "wof:name":"Persianas Y Ventanas Akelarre S.l.",
    "wof:placetype":"venue"
},
  "geometry": {"coordinates":[-2.6983869076,43.2204284668],"type":"Point"}
}