{
  "type": "Feature",
  "properties": {
    "addr:full":"Carrer de Anselm Clave, 173 Olesa Montserrat Barcelona 08640",
    "addr:housenumber":"173",
    "addr:postcode":"08640",
    "addr:street":"Carrer De Anselm Clave;Barcelona",
    "iso:country":"ES",
    "sg:address":"Carrer de Anselm Clave, 173",
    "sg:city":"Olesa Montserrat",
    "sg:orig_category":"Molduras, Junquillos, Listones Y Molduras Perforadas",
    "sg:phone":"+34 937 78 33 62",
    "sg:postcode":"08640",
    "sg:province":"Barcelona",
    "wof:name":"Adamuz Miranda Francisco",
    "wof:placetype":"venue"
},
  "geometry": {"coordinates":[1.8929442167,41.5442008972],"type":"Point"}
}