{
  "type": "Feature",
  "properties": {
    "addr:full":"Calle de Pe\u00d1uelas, 7 Antequera M\u00e1laga 29200",
    "addr:housenumber":"7",
    "addr:postcode":"29200",
    "addr:street":"Calle De Pen\u0303Uelas",
    "iso:country":"ES",
    "sg:address":"Calle de Pe\u00d1uelas, 7",
    "sg:city":"Antequera",
    "sg:orig_category":"Pescader\u00cdas (al Por Menor)",
    "sg:phone":"+34 952 70 35 41",
    "sg:postcode":"29200",
    "sg:province":"M\u00e1laga",
    "wof:name":"Pescados Hijano S.l.",
    "wof:placetype":"venue"
},
  "geometry": {"coordinates":[-4.5617489815,37.0148544312],"type":"Point"}
}