{
  "type": "Feature",
  "properties": {
    "addr:full":"Avda Navarra, S/n Tarazona Zaragoza 50500",
    "addr:postcode":"50500",
    "addr:street":"Avda Navarra S / N",
    "iso:country":"ES",
    "sg:address":"Avda Navarra, S/n",
    "sg:city":"Tarazona",
    "sg:orig_category":"Reciclaje Y Tratamiento De Desechos Varios",
    "sg:phone":"+34 976 64 41 58",
    "sg:postcode":"50500",
    "sg:province":"Zaragoza",
    "wof:name":"Fomento De Construcciones Y Contratas S.a.",
    "wof:placetype":"venue"
},
  "geometry": {"coordinates":[-1.7246769667,41.9085273743],"type":"Point"}
}