{
  "type": "Feature",
  "properties": {
    "addr:full":"Calle de Jose Abascal, 35 Madrid Madrid 28003",
    "addr:housenumber":"35",
    "addr:postcode":"madrid;28003",
    "addr:street":"Calle De Jose Abascal",
    "iso:country":"ES",
    "sg:address":"Calle de Jose Abascal, 35",
    "sg:city":"Madrid",
    "sg:orig_category":"M\u00c9dicos: Cirug\u00cda Pl\u00c1stica, Reconstructiva Y Est\u00c9tica",
    "sg:phone":"+34 914 41 40 48",
    "sg:postcode":"28003",
    "sg:province":"Madrid",
    "wof:name":"Chamosa Martin Miguel",
    "wof:placetype":"venue"
},
  "geometry": {"coordinates":[-3.6980888844,40.4384994507],"type":"Point"}
}