{
  "type": "Feature",
  "properties": {
    "iso:country":"ES",
    "sg:address":"Avda Europa, 7",
    "sg:city":"Pozuelo De Alarcon",
    "sg:orig_category":"Notarios",
    "sg:phone":"+34 913 51 58 68",
    "sg:postcode":"28224",
    "sg:province":"Madrid",
    "wof:name":"Bernal Gonzalez Jose Antonio",
    "wof:placetype":"venue"
},
  "geometry": {"coordinates":[-3.7968349457,40.4367675781],"type":"Point"}
}