{
  "type": "Feature",
  "properties": {
    "iso:country":"ES",
    "sg:address":"Calle de Cristo De La Epidemia, 1",
    "sg:city":"Malaga",
    "sg:orig_category":"Promotores Constructores",
    "sg:phone":"+34 952 65 38 00",
    "sg:postcode":"29013",
    "sg:province":"M\u00e1laga",
    "wof:name":"Jose Antonio Jimenez Gomez S.l.",
    "wof:placetype":"venue"
},
  "geometry": {"coordinates":[-4.4142003059,36.7270736694],"type":"Point"}
}