{
  "type": "Feature",
  "properties": {
    "iso:country":"ES",
    "sg:address":"Carrer de Rosa Ribas I Parellada, 30",
    "sg:city":"Prat Llobregat",
    "sg:orig_category":"Parafarmacias",
    "sg:phone":"+34 933 79 03 85",
    "sg:postcode":"08820",
    "sg:province":"Barcelona",
    "wof:name":"Yague Parellada Magdalena",
    "wof:placetype":"venue"
},
  "geometry": {"coordinates":[2.090280056,41.3233184814],"type":"Point"}
}