{
  "type": "Feature",
  "properties": {
    "iso:country":"ES",
    "sg:address":"Calle de Concarera, S/n",
    "sg:city":"Tudela",
    "sg:orig_category":"Carnicer\u00cdas, Carnicer\u00cdas",
    "sg:phone":"+34 948 82 10 60",
    "sg:postcode":"31500",
    "sg:province":"Navarra",
    "wof:name":"Echave Perez Rafael",
    "wof:placetype":"venue"
},
  "geometry": {"coordinates":[-1.6060267687,42.0625305176],"type":"Point"}
}