{
  "type": "Feature",
  "properties": {
    "addr:full":"Calle de Ayala, 67 Malaga M\u00e1laga 29002",
    "addr:housenumber":"67",
    "addr:postcode":"29002",
    "addr:street":"Calle De Ayala;Ma\u0301Laga",
    "iso:country":"ES",
    "sg:address":"Calle de Ayala, 67",
    "sg:city":"Malaga",
    "sg:orig_category":"\u00d3ptica: Instrumentos (fabricaci\u00d3n)",
    "sg:phone":"+34 952 33 97 67",
    "sg:postcode":"29002",
    "sg:province":"M\u00e1laga",
    "wof:name":"Natural Vision Malaga S.l.",
    "wof:placetype":"venue"
},
  "geometry": {"coordinates":[-4.4363918304,36.7054252625],"type":"Point"}
}