{
  "type": "Feature",
  "properties": {
    "addr:full":"Calle de Moncayo, 5 Santa Maria Aguila Almer\u00eda 04710",
    "addr:housenumber":"5",
    "addr:postcode":"04710",
    "addr:street":"Calle De Moncayo;Almeri\u0301A",
    "iso:country":"ES",
    "sg:address":"Calle de Moncayo, 5",
    "sg:city":"Santa Maria Aguila",
    "sg:orig_category":"Reciclaje, Desguace De Veh\u00cdculos",
    "sg:phone":"+34 950 58 21 92",
    "sg:postcode":"04710",
    "sg:province":"Almer\u00eda",
    "wof:name":"Navarro Arcos Rogelio",
    "wof:placetype":"venue"
},
  "geometry": {"coordinates":[-2.7759139538,36.7795753479],"type":"Point"}
}