{
  "type": "Feature",
  "properties": {
    "iso:country":"ES",
    "sg:address":"Calle de Natero (el), 51",
    "sg:city":"Cruz Santa",
    "sg:orig_category":"Alimentaci\u00d3n General (al Por Menor)",
    "sg:phone":"+34 922 34 04 42",
    "sg:postcode":"38413",
    "sg:province":"Santa Cruz De Tenerife",
    "wof:name":"Yanes Sosa Teodoro",
    "wof:placetype":"venue"
},
  "geometry": {"coordinates":[-16.5606460571,28.3570613861],"type":"Point"}
}