{
  "type": "Feature",
  "properties": {
    "iso:country":"ES",
    "sg:address":"Calle de Paco Miranda, 20",
    "sg:city":"Malaga",
    "sg:orig_category":"Caf\u00c9s, Bares, Cervecer\u00cdas",
    "sg:phone":"+34 952 26 75 70",
    "sg:postcode":"29013",
    "sg:province":"M\u00e1laga",
    "wof:name":"Juegos Costasol Montecarlo S.a",
    "wof:placetype":"venue"
},
  "geometry": {"coordinates":[-4.416533947,36.7309379578],"type":"Point"}
}