{
  "type": "Feature",
  "properties": {
    "addr:full":"Avda Almendros, 16 Benidorm Alicante 03500",
    "addr:housenumber":"16",
    "addr:postcode":"03500",
    "addr:street":"Avda Almendros",
    "iso:country":"ES",
    "sg:address":"Avda Almendros, 16",
    "sg:city":"Benidorm",
    "sg:orig_category":"Telefon\u00cda: Instaladores Varios",
    "sg:phone":"+34 965 85 26 18",
    "sg:postcode":"03500",
    "sg:province":"Alicante",
    "wof:name":"Landirel  Laura Mabel",
    "wof:placetype":"venue"
},
  "geometry": {"coordinates":[-0.1326494068,38.5387229919],"type":"Point"}
}