{
  "type": "Feature",
  "properties": {
    "iso:country":"ES",
    "sg:address":"Ctra Seu D'urgell(la), 13",
    "sg:city":"Ponts",
    "sg:orig_category":"Reposter\u00cdas",
    "sg:phone":"+34 973 46 02 37",
    "sg:postcode":"25740",
    "sg:province":"Lleida",
    "wof:name":"Benet Vives Marta",
    "wof:placetype":"venue"
},
  "geometry": {"coordinates":[1.1860079765,41.9162445068],"type":"Point"}
}