{
  "type": "Feature",
  "properties": {
    "iso:country":"ES",
    "sg:address":"Carrer de Major, 47",
    "sg:city":"Roca Valles",
    "sg:orig_category":"Carnicer\u00cdas, Carnicer\u00cdas",
    "sg:phone":"+34 938 42 20 65",
    "sg:postcode":"08430",
    "sg:province":"Barcelona",
    "wof:name":"Masso Pueo Joaquin",
    "wof:placetype":"venue"
},
  "geometry": {"coordinates":[2.3257100582,41.5888328552],"type":"Point"}
}