{
  "type": "Feature",
  "properties": {
    "iso:country":"ES",
    "sg:address":"Calle de Alicante, 38",
    "sg:city":"Zaragoza",
    "sg:orig_category":"Alimentaci\u00d3n General (al Por Menor)",
    "sg:phone":"+34 976 38 62 50",
    "sg:postcode":"50007",
    "sg:province":"Zaragoza",
    "wof:name":"La Aragonense S.c.",
    "wof:placetype":"venue"
},
  "geometry": {"coordinates":[-0.8877615929,41.6315956116],"type":"Point"}
}