{
  "type": "Feature",
  "properties": {
    "addr:full":"Carrer de Salvador Olivella, 13 Sitges Barcelona 08870",
    "addr:housenumber":"13",
    "addr:postcode":"08870",
    "addr:street":"Carrer De Salvador Olivella",
    "iso:country":"ES",
    "sg:address":"Carrer de Salvador Olivella, 13",
    "sg:city":"Sitges",
    "sg:orig_category":"Confecci\u00d3n De Zapatos",
    "sg:phone":"+34 938 94 17 47",
    "sg:postcode":"08870",
    "sg:province":"Barcelona",
    "wof:name":"Britte S. L.",
    "wof:placetype":"venue"
},
  "geometry": {"coordinates":[1.8111799955,41.2409744263],"type":"Point"}
}