{
  "type": "Feature",
  "properties": {
    "addr:full":"Calle de Escritor Carretero Narbona, 21 Malaga M\u00e1laga 29018",
    "addr:housenumber":"21",
    "addr:postcode":"29018",
    "addr:street":"Calle De Escritor Carretero Narbona;Ma\u0301Laga",
    "iso:country":"ES",
    "sg:address":"Calle de Escritor Carretero Narbona, 21",
    "sg:city":"Malaga",
    "sg:orig_category":"Decoradores",
    "sg:phone":"+34 952 29 53 87",
    "sg:postcode":"29018",
    "sg:province":"M\u00e1laga",
    "wof:name":"Vimorfer S.l.",
    "wof:placetype":"venue"
},
  "geometry": {"coordinates":[-4.3426570892,36.7192420959],"type":"Point"}
}