{
  "type": "Feature",
  "properties": {
    "iso:country":"ES",
    "sg:address":"Calle de Marques De La Ensenada, 44",
    "sg:city":"Logro\u00f1o",
    "sg:classifiers":[
        {
            "category":"Banks & Credit Unions",
            "subcategory":"Bureau De Change",
            "type":"Services"
        }
    ],
    "sg:phone":"+34 941 24 05 40",
    "sg:postcode":"26003",
    "sg:province":"La Rioja",
    "sg:tags":[
        "organismos",
        "control"
    ],
    "sg:website":"www.eca.es",
    "wof:name":"Eca Entitat Colaboradora De L'administracio",
    "wof:placetype":"venue"
},
  "geometry": {"coordinates":[-2.4386711121,42.4592666626],"type":"Point"}
}