{
  "type": "Feature",
  "properties": {
    "addr:full":"Calle de Monte Busquil, 8 Tafalla Navarra 31300",
    "addr:housenumber":"8",
    "addr:postcode":"31300",
    "addr:street":"Calle De Monte Busquil",
    "iso:country":"ES",
    "sg:address":"Calle de Monte Busquil, 8",
    "sg:city":"Tafalla",
    "sg:orig_category":"Material Y Suministros Para Imprenta E Industrias Gr\u00c1ficas",
    "sg:phone":"+34 948 70 03 46",
    "sg:postcode":"31300",
    "sg:province":"Navarra",
    "wof:name":"Arzoz Ciaurriz Jesus Maria",
    "wof:placetype":"venue"
},
  "geometry": {"coordinates":[-1.6797773838,42.5280075073],"type":"Point"}
}