{
  "type": "Feature",
  "properties": {
    "iso:country":"ES",
    "sg:address":"Plaz Arenal (del), 22",
    "sg:city":"Jerez De La Frontera",
    "sg:orig_category":"Parafarmacias",
    "sg:phone":"+34 956 34 13 84",
    "sg:postcode":"11403",
    "sg:province":"C\u00e1diz",
    "wof:name":"Fontade Mu\u00f1oz Milagros",
    "wof:placetype":"venue"
},
  "geometry": {"coordinates":[-6.1375632286,36.6811676025],"type":"Point"}
}