{
  "type": "Feature",
  "properties": {
    "iso:country":"ES",
    "sg:address":"Freixido, S/n",
    "sg:city":"Larouco",
    "sg:orig_category":"Art\u00cdculos De Madera (fabricaci\u00d3n Y Al Por Mayor)",
    "sg:phone":"+34 988 34 80 47",
    "sg:postcode":"32358",
    "sg:province":"Ourense",
    "wof:name":"Blanco Gonzalez Joaquin",
    "wof:placetype":"venue"
},
  "geometry": {"coordinates":[-7.1407017708,42.3552398682],"type":"Point"}
}