{
  "type": "Feature",
  "properties": {
    "addr:full":"Calle de Carretera De Soria, S/n Riaza Segovia 40500",
    "addr:housenumber":"s / n",
    "addr:postcode":"40500",
    "addr:street":"Calle De Carretera De Soria",
    "iso:country":"ES",
    "sg:address":"Calle de Carretera De Soria, S/n",
    "sg:city":"Riaza",
    "sg:orig_category":"Mataderos Y Talleres De Despiezado",
    "sg:phone":"+34 921 55 05 21",
    "sg:postcode":"40500",
    "sg:province":"Segovia",
    "wof:name":"Carnes De Riaza S. A.",
    "wof:placetype":"venue"
},
  "geometry": {"coordinates":[-3.3892893791,41.3013458252],"type":"Point"}
}