{
  "type": "Feature",
  "properties": {
    "iso:country":"ES",
    "sg:address":"Pla\u00c7 Joan Sansa, 9",
    "sg:city":"Seu D'urgell",
    "sg:orig_category":"Peluquer\u00cdas, Peluquer\u00cda Mixta",
    "sg:phone":"+34 973 35 49 32",
    "sg:postcode":"25700",
    "sg:province":"Lleida",
    "wof:name":"Ruiz Mir Silvia",
    "wof:placetype":"venue"
},
  "geometry": {"coordinates":[0.6457189918,41.6027946472],"type":"Point"}
}