{
  "type": "Feature",
  "properties": {
    "addr:full":"Calle de Constitucion, 7 Brozas C\u00e1ceres 10950",
    "addr:housenumber":"7",
    "addr:postcode":"10950",
    "addr:street":"Calle De Constitucion;Ca\u0301Ceres",
    "iso:country":"ES",
    "sg:address":"Calle de Constitucion, 7",
    "sg:city":"Brozas",
    "sg:orig_category":"Alimentaci\u00d3n General (al Por Menor)",
    "sg:phone":"+34 927 39 54 12",
    "sg:postcode":"10950",
    "sg:province":"C\u00e1ceres",
    "wof:name":"Duran Carrasco Manuel",
    "wof:placetype":"venue"
},
  "geometry": {"coordinates":[-6.7790489197,39.6115264893],"type":"Point"}
}