{
  "type": "Feature",
  "properties": {
    "iso:country":"ES",
    "sg:address":"Rua Fermin Bouza Brei, 17",
    "sg:city":"Estrada",
    "sg:orig_category":"Tapiceros Y Tapiceros",
    "sg:phone":"+34 986 57 12 50",
    "sg:postcode":"36680",
    "sg:province":"Pontevedra",
    "wof:name":"Fernandez Vali\u00f1as Candido",
    "wof:placetype":"venue"
},
  "geometry": {"coordinates":[-8.4939651489,42.6872024536],"type":"Point"}
}