{
  "type": "Feature",
  "properties": {
    "iso:country":"ES",
    "sg:address":"Calle de Pintor Murillo, 17",
    "sg:city":"Alacant",
    "sg:orig_category":"Promotores Constructores",
    "sg:phone":"+34 965 14 21 55",
    "sg:postcode":"03004",
    "sg:province":"Alicante",
    "wof:name":"Tailhandier Gea Brigida Ana",
    "wof:placetype":"venue"
},
  "geometry": {"coordinates":[-0.48595801,38.351726532],"type":"Point"}
}