{
  "type": "Feature",
  "properties": {
    "addr:full":"Calle de Fuente Alamo, 46 Montilla C\u00f3rdoba 14550",
    "addr:housenumber":"46",
    "addr:postcode":"14550",
    "addr:street":"Calle De Fuente Alamo;Co\u0301Rdoba",
    "iso:country":"ES",
    "sg:address":"Calle de Fuente Alamo, 46",
    "sg:city":"Montilla",
    "sg:orig_category":"Automatizaci\u00d3n De Procesos Industriales Y De Edificaci\u00d3n (estudios, Instalaci\u00d3n)",
    "sg:phone":"+34 957 66 40 47",
    "sg:postcode":"14550",
    "sg:province":"C\u00f3rdoba",
    "wof:name":"Manuel Martinez Automatizacion Y Pesaje Industrial S.l.",
    "wof:placetype":"venue"
},
  "geometry": {"coordinates":[-4.6389398575,37.5823135376],"type":"Point"}
}