{
  "type": "Feature",
  "properties": {
    "addr:full":"Avda Rio Guadarrama, 7 Poligono Sta M. De Benquerencia Toledo 45007",
    "addr:housenumber":"7 poligono",
    "addr:postcode":"45007",
    "addr:street":"Avda Rio Guadarrama;Sta M. De Benquerencia",
    "iso:country":"ES",
    "sg:address":"Avda Rio Guadarrama, 7",
    "sg:city":"Poligono Sta M. De Benquerencia",
    "sg:orig_category":"Distribuci\u00d3n De Petr\u00d3leo Y Derivados",
    "sg:phone":"+34 925 24 13 61",
    "sg:postcode":"45007",
    "sg:province":"Toledo",
    "wof:name":"Perez Gamero S.l.",
    "wof:placetype":"venue"
},
  "geometry": {"coordinates":[-3.9430189133,39.8598937988],"type":"Point"}
}