{
  "type": "Feature",
  "properties": {
    "addr:full":"Calle de Eras De San Francisco, 10 Torrijos Toledo 45500",
    "addr:housenumber":"10",
    "addr:postcode":"45500",
    "addr:street":"Calle De Eras De San Francisco",
    "iso:country":"ES",
    "sg:address":"Calle de Eras De San Francisco, 10",
    "sg:city":"Torrijos",
    "sg:orig_category":"Abogados",
    "sg:phone":"+34 925 76 03 75",
    "sg:postcode":"45500",
    "sg:province":"Toledo",
    "wof:name":"Plasencia Sanchez-caro Felix",
    "wof:placetype":"venue"
},
  "geometry": {"coordinates":[-4.2817001343,39.9795303345],"type":"Point"}
}