{
  "type": "Feature",
  "properties": {
    "addr:full":"Calle de Belorado, 5 Burgos Burgos 09004",
    "addr:housenumber":"5",
    "addr:postcode":"09004",
    "addr:street":"Calle De Belorado",
    "iso:country":"ES",
    "sg:address":"Calle de Belorado, 5",
    "sg:city":"Burgos",
    "sg:orig_category":"Carnicer\u00cdas, Carnicer\u00cdas",
    "sg:phone":"+34 947 27 13 67",
    "sg:postcode":"09004",
    "sg:province":"Burgos",
    "wof:name":"Castrillo Diez Isidro",
    "wof:placetype":"venue"
},
  "geometry": {"coordinates":[-3.6918261051,42.3443489075],"type":"Point"}
}