{
  "type": "Feature",
  "properties": {
    "addr:full":"Carrer de Juan Sebastian Elcano, 19 Mataro Barcelona 08302",
    "addr:housenumber":"19",
    "addr:postcode":"08302",
    "addr:street":"Carrer De Juan Sebastian Elcano",
    "iso:country":"ES",
    "sg:address":"Carrer de Juan Sebastian Elcano, 19",
    "sg:city":"Mataro",
    "sg:classifiers":[
        {
            "category":"Personal",
            "subcategory":"Barber",
            "type":"Services"
        }
    ],
    "sg:phone":"+34 937 57 31 49",
    "sg:postcode":"08302",
    "sg:province":"Barcelona",
    "sg:tags":[
        "caballeros",
        "de",
        "peluqueros"
    ],
    "wof:name":"Gordillo Sanchez Enrique",
    "wof:placetype":"venue"
},
  "geometry": {"coordinates":[2.4353189468,41.5355072021],"type":"Point"}
}