{
  "type": "Feature",
  "properties": {
    "iso:country":"ES",
    "sg:address":"Carrer de Constitucio, 11",
    "sg:city":"Ibi",
    "sg:orig_category":"Zapatos (al Por Menor)",
    "sg:phone":"+34 966 55 00 68",
    "sg:postcode":"03440",
    "sg:province":"Alicante",
    "wof:name":"Martinez Valenciano Rebeca",
    "wof:placetype":"venue"
},
  "geometry": {"coordinates":[-0.5750399828,38.624797821],"type":"Point"}
}