{
  "type": "Feature",
  "properties": {
    "iso:country":"ES",
    "sg:address":"Calle de Juan Pedro Gutierrez Higueras, 7",
    "sg:city":"Jaen",
    "sg:orig_category":"Empresas De Impermeabilizaci\u00d3n",
    "sg:phone":"+34 953 22 50 07",
    "sg:postcode":"23005",
    "sg:province":"Ja\u00e9n",
    "wof:name":"Perez Parras Antonio",
    "wof:placetype":"venue"
},
  "geometry": {"coordinates":[-3.7979860306,37.7763290405],"type":"Point"}
}