{
  "type": "Feature",
  "properties": {
    "iso:country":"ES",
    "sg:address":"Calle de Arco, 16",
    "sg:city":"Palmas De Gran Canaria",
    "sg:orig_category":"Fabricaci\u00d3n, Instalaci\u00d3n Y Reparaci\u00d3n De Bombas",
    "sg:phone":"+34 928 24 11 35",
    "sg:postcode":"35004",
    "sg:province":"Las Palmas",
    "wof:name":"Yuba S. L.",
    "wof:placetype":"venue"
},
  "geometry": {"coordinates":[-15.4261226654,28.113817215],"type":"Point"}
}