{
  "type": "Feature",
  "properties": {
    "iso:country":"ES",
    "sg:address":"Pl Carmen, 2",
    "sg:city":"Lepe",
    "sg:orig_category":"Reposter\u00cdas",
    "sg:phone":"+34 959 38 43 58",
    "sg:postcode":"21440",
    "sg:province":"Huelva",
    "wof:name":"Panaderia La Bella S.l.",
    "wof:placetype":"venue"
},
  "geometry": {"coordinates":[-7.198404789,37.2603492737],"type":"Point"}
}