{
  "type": "Feature",
  "properties": {
    "addr:full":"Gabiria Kalea, 3 Bergara Guip\u00f9zcoa 20570",
    "addr:housenumber":"3",
    "addr:postcode":"20570",
    "addr:street":"Gabiria Kalea;Guipu\u0300Zcoa",
    "iso:country":"ES",
    "sg:address":"Gabiria Kalea, 3",
    "sg:city":"Bergara",
    "sg:orig_category":"Fabricaci\u00d3n De Telas Y Sedas",
    "sg:phone":"+34 943 76 59 40",
    "sg:postcode":"20570",
    "sg:province":"Guip\u00f9zcoa",
    "sg:website":"www.tavex.com",
    "wof:name":"Tavex Algodonera S.a.",
    "wof:placetype":"venue"
},
  "geometry": {"coordinates":[-2.4165360928,43.110786438],"type":"Point"}
}