{
  "type": "Feature",
  "properties": {
    "addr:full":"Calle de Historiador Manuel Cancela, 1 Jerez De La Frontera C\u00e1diz 11408",
    "addr:housenumber":"1",
    "addr:postcode":"11408",
    "addr:street":"Calle De Historiador Manuel Cancela",
    "iso:country":"ES",
    "sg:address":"Calle de Historiador Manuel Cancela, 1",
    "sg:city":"Jerez De La Frontera",
    "sg:orig_category":"Cajas De Ahorro",
    "sg:phone":"+34 956 14 41 47",
    "sg:postcode":"11408",
    "sg:province":"C\u00e1diz",
    "sg:website":"www.cajasanfernando.es",
    "wof:name":"Caja San Fernando De Sevilla Y Jerez",
    "wof:placetype":"venue"
},
  "geometry": {"coordinates":[-6.1445112228,36.673789978],"type":"Point"}
}