{
  "type": "Feature",
  "properties": {
    "addr:full":"Calle de V, 8 Balazote Albacete 02320",
    "addr:housenumber":"8",
    "addr:postcode":"02320",
    "addr:street":"Calle De V",
    "iso:country":"ES",
    "sg:address":"Calle de V, 8",
    "sg:city":"Balazote",
    "sg:orig_category":"Empresas De Carpinter\u00cda",
    "sg:phone":"+34 967 36 70 25",
    "sg:postcode":"02320",
    "sg:province":"Albacete",
    "wof:name":"Simon Diaz Jose Angel",
    "wof:placetype":"venue"
},
  "geometry": {"coordinates":[-2.1536619663,38.883480072],"type":"Point"}
}