{
  "type": "Feature",
  "properties": {
    "addr:full":"Pase San Roque (de), 5 Avila \u00c1vila 05003",
    "addr:postcode":"05003",
    "addr:street":"A\u0301Vila",
    "iso:country":"ES",
    "sg:address":"Pase San Roque (de), 5",
    "sg:city":"Avila",
    "sg:orig_category":"Ingenier\u00cda, Centros De Estudios (diversos)",
    "sg:phone":"+34 920 25 02 85",
    "sg:postcode":"05003",
    "sg:province":"\u00c1vila",
    "sg:website":"www.ingenieriaproyecta.com",
    "wof:name":"Proyectarenovables S.l.",
    "wof:placetype":"venue"
},
  "geometry": {"coordinates":[-4.6917080879,40.6541252136],"type":"Point"}
}