{
  "type": "Feature",
  "properties": {
    "addr:full":"Avgd Del Cami Nou, 221 Xirivella Valencia 46950",
    "addr:housenumber":"221",
    "addr:postcode":"46950",
    "addr:street":"Nou",
    "iso:country":"ES",
    "sg:address":"Avgd Del Cami Nou, 221",
    "sg:city":"Xirivella",
    "sg:orig_category":"Agentes, Concesionarios Y Sucursales De Camiones Y Veh\u00cdculos Industriales",
    "sg:phone":"+34 963 13 45 59",
    "sg:postcode":"46950",
    "sg:province":"Valencia",
    "wof:name":"Componentes De La Carretera S.l.",
    "wof:placetype":"venue"
},
  "geometry": {"coordinates":[-0.4408749938,39.4617004395],"type":"Point"}
}