{
  "type": "Feature",
  "properties": {
    "addr:full":"Calle de Aguayo, 2 Baeza Ja\u00e9n 23440",
    "addr:housenumber":"2",
    "addr:postcode":"23440",
    "addr:street":"Calle De Aguayo",
    "iso:country":"ES",
    "sg:address":"Calle de Aguayo, 2",
    "sg:city":"Baeza",
    "sg:orig_category":"Asesor\u00cda Fiscal Y Jur\u00cddica",
    "sg:phone":"+34 953 74 06 64",
    "sg:postcode":"23440",
    "sg:province":"Ja\u00e9n",
    "wof:name":"Cozar Lopez Angel Gabriel",
    "wof:placetype":"venue"
},
  "geometry": {"coordinates":[-3.4665350914,37.9933547974],"type":"Point"}
}