{
  "type": "Feature",
  "properties": {
    "addr:full":"Calle de Poeta Llorente, 38 Pobla Vallbona Valencia 46185",
    "addr:housenumber":"38",
    "addr:postcode":"46185",
    "addr:street":"Calle De Poeta Llorente",
    "iso:country":"ES",
    "sg:address":"Calle de Poeta Llorente, 38",
    "sg:city":"Pobla Vallbona",
    "sg:orig_category":"Inmobiliaria (agencias)",
    "sg:phone":"+34 962 76 18 62",
    "sg:postcode":"46185",
    "sg:province":"Valencia",
    "wof:name":"Marti I Montesinos S.l",
    "wof:placetype":"venue"
},
  "geometry": {"coordinates":[-0.5522570014,39.5921630859],"type":"Point"}
}