{
  "type": "Feature",
  "properties": {
    "iso:country":"ES",
    "sg:address":"Calle de Gabriel Lobo, 12",
    "sg:city":"Madrid",
    "sg:orig_category":"Tintes (fabricaci\u00d3n, Al Por Mayor)",
    "sg:phone":"+34 915 61 02 91",
    "sg:postcode":"28002",
    "sg:province":"Madrid",
    "wof:name":"Vidueira Fernandez Alejandro",
    "wof:placetype":"venue"
},
  "geometry": {"coordinates":[-3.6800429821,40.4432411194],"type":"Point"}
}