{
  "type": "Feature",
  "properties": {
    "iso:country":"ES",
    "sg:address":"Calle de Moradas, 6",
    "sg:city":"Valladolid",
    "sg:orig_category":"Ense\u00d1anza P\u00dablica Primaria",
    "sg:phone":"+34 983 25 55 56",
    "sg:postcode":"47010",
    "sg:province":"Valladolid",
    "wof:name":"Barrio Cuellar Maria Jesus",
    "wof:placetype":"venue"
},
  "geometry": {"coordinates":[-4.7232141495,41.6593475342],"type":"Point"}
}