{
  "type": "Feature",
  "properties": {
    "iso:country":"ES",
    "sg:address":"Calle de Argos, 9",
    "sg:city":"Madrid",
    "sg:orig_category":"Chapister\u00cda",
    "sg:phone":"+34 917 42 47 06",
    "sg:postcode":"28037",
    "sg:province":"Madrid",
    "wof:name":"Sanchez Sanchez Esteban",
    "wof:placetype":"venue"
},
  "geometry": {"coordinates":[-3.6355884075,40.4364738464],"type":"Point"}
}