{
  "type": "Feature",
  "properties": {
    "addr:full":"Calle de Elorduigoitia, 16 Mungia Vizcaya 48100",
    "addr:housenumber":"16",
    "addr:postcode":"48100",
    "addr:street":"Calle De Elorduigoitia",
    "iso:country":"ES",
    "sg:address":"Calle de Elorduigoitia, 16",
    "sg:city":"Mungia",
    "sg:orig_category":"Audiovisuales, Tv, Hi",
    "sg:phone":"+34 946 15 54 92",
    "sg:postcode":"48100",
    "sg:province":"Vizcaya",
    "sg:website":"www.digitalsiv.com",
    "wof:name":"Martinez Martin Pedro",
    "wof:placetype":"venue"
},
  "geometry": {"coordinates":[-2.8458890915,43.3564987183],"type":"Point"}
}