{
  "type": "Feature",
  "properties": {
    "addr:full":"Calle de Libertad (la), 4 Cox Alicante 03350",
    "addr:housenumber":"4",
    "addr:postcode":"03350",
    "addr:street":"Calle De Libertad La",
    "iso:country":"ES",
    "sg:address":"Calle de Libertad (la), 4",
    "sg:city":"Cox",
    "sg:orig_category":"Molduras, Junquillos, Listones Y Molduras Perforadas",
    "sg:phone":"+34 966 75 03 16",
    "sg:postcode":"03350",
    "sg:province":"Alicante",
    "wof:name":"Cuartero Anta Manuel",
    "wof:placetype":"venue"
},
  "geometry": {"coordinates":[-0.8913760185,38.1428985596],"type":"Point"}
}