{
  "type": "Feature",
  "properties": {
    "iso:country":"ES",
    "sg:address":"Calle de Antonio Eulate, 9",
    "sg:city":"Lucena",
    "sg:orig_category":"Laboratorios Farmac\u00c9uticos",
    "sg:phone":"+34 957 50 13 28",
    "sg:postcode":"14900",
    "sg:province":"C\u00f3rdoba",
    "wof:name":"Palma Robles Luis Fernando",
    "wof:placetype":"venue"
},
  "geometry": {"coordinates":[-4.4853653908,37.4067611694],"type":"Point"}
}