{
  "type": "Feature",
  "properties": {
    "iso:country":"ES",
    "sg:address":"Pl Llibertat, 1",
    "sg:city":"Reus",
    "sg:orig_category":"Cl\u00cdnicas Dentales",
    "sg:phone":"+34 977 34 14 98",
    "sg:postcode":"43201",
    "sg:province":"Tarragona",
    "wof:name":"Borras Colome Joan Josep",
    "wof:placetype":"venue"
},
  "geometry": {"coordinates":[1.1059759855,41.158164978],"type":"Point"}
}