{
  "type": "Feature",
  "properties": {
    "iso:country":"ES",
    "sg:address":"Calle de Real, 79",
    "sg:city":"Iscar",
    "sg:orig_category":"Comercio De Muebles De Estilo Y Contempor\u00c1neos",
    "sg:phone":"+34 983 61 24 32",
    "sg:postcode":"47420",
    "sg:province":"Valladolid",
    "wof:name":"Mundo Rustico S.l.",
    "wof:placetype":"venue"
},
  "geometry": {"coordinates":[-4.5307540894,41.3635215759],"type":"Point"}
}