{
  "type": "Feature",
  "properties": {
    "addr:full":"Carrer de Torrijos, 16 Barcelona Barcelona 08012",
    "addr:housenumber":"16",
    "addr:postcode":"08012",
    "addr:street":"Carrer De Torrijos",
    "iso:country":"ES",
    "sg:address":"Carrer de Torrijos, 16",
    "sg:city":"Barcelona",
    "sg:orig_category":"Peluquer\u00cdas, Peluquer\u00cda Mixta",
    "sg:phone":"+34 932 19 85 14",
    "sg:postcode":"08012",
    "sg:province":"Barcelona",
    "wof:name":"Raventos Garcia Vinyet",
    "wof:placetype":"venue"
},
  "geometry": {"coordinates":[2.1596090794,41.4028739929],"type":"Point"}
}