{
  "type": "Feature",
  "properties": {
    "addr:full":"Calle de Don Cipriano Gonzalez, 21 Puebla Alfinden Zaragoza 50171",
    "addr:housenumber":"21",
    "addr:postcode":"50171",
    "addr:street":"Calle De Don;Gonzalez;Alfinden",
    "iso:country":"ES",
    "sg:address":"Calle de Don Cipriano Gonzalez, 21",
    "sg:city":"Puebla Alfinden",
    "sg:orig_category":"Negocio De Materiales De Construcci\u00d3n",
    "sg:phone":"+34 976 10 72 65",
    "sg:postcode":"50171",
    "sg:province":"Zaragoza",
    "wof:name":"Abos Murillo Luis",
    "wof:placetype":"venue"
},
  "geometry": {"coordinates":[-0.876566,41.656349],"type":"Point"}
}