{
  "type": "Feature",
  "properties": {
    "iso:country":"ES",
    "sg:address":"Resid El Molino, S/n",
    "sg:city":"Torrevieja",
    "sg:orig_category":"Asilos De Ancianos. Centros Privados",
    "sg:phone":"+34 965 71 18 74",
    "sg:postcode":"03180",
    "sg:province":"Alicante",
    "wof:name":"Hospital Residencia Carmelitas Misioneras Teresianas",
    "wof:placetype":"venue"
},
  "geometry": {"coordinates":[-0.6536790133,38.0173606873],"type":"Point"}
}