{
  "type": "Feature",
  "properties": {
    "iso:country":"ES",
    "sg:address":"Cxon Loureiro, 7",
    "sg:city":"Barrantes",
    "sg:orig_category":"Peluqueros: De Se\u00d1oras",
    "sg:phone":"+34 986 71 04 83",
    "sg:postcode":"36636",
    "sg:province":"Pontevedra",
    "wof:name":"Barral Serantes Parisina",
    "wof:placetype":"venue"
},
  "geometry": {"coordinates":[-8.7683343887,42.5012207031],"type":"Point"}
}