{
  "type": "Feature",
  "properties": {
    "iso:country":"ES",
    "sg:address":"Pase San Roque (de), 13",
    "sg:city":"Avila",
    "sg:orig_category":"Frutas Y Legumbres Frescas (al Por Mayor)",
    "sg:phone":"+34 920 22 14 05",
    "sg:postcode":"05003",
    "sg:province":"\u00c1vila",
    "wof:name":"Juan Jose Perez Garcia C.b.",
    "wof:placetype":"venue"
},
  "geometry": {"coordinates":[-4.6605348587,40.6271286011],"type":"Point"}
}