{
  "type": "Feature",
  "properties": {
    "iso:country":"ES",
    "sg:address":"Calle de Corredera, S/n",
    "sg:city":"Arcos Frontera",
    "sg:orig_category":"Asociaciones, Organismos Culturales Y Socioeducativos",
    "sg:phone":"+34 956 70 39 09",
    "sg:postcode":"11630",
    "sg:province":"C\u00e1diz",
    "wof:name":"Ayuntamiento De Arcos De La Frontera",
    "wof:placetype":"venue"
},
  "geometry": {"coordinates":[-5.8119587898,36.7510490417],"type":"Point"}
}