{
  "type": "Feature",
  "properties": {
    "iso:country":"ES",
    "sg:address":"Carrer de Ramon Albo, 68",
    "sg:city":"Barcelona",
    "sg:orig_category":"Persianas Interiores, Exteriores",
    "sg:phone":"+34 933 40 33 66",
    "sg:postcode":"08027",
    "sg:province":"Barcelona",
    "wof:name":"Toldos Ademar S.c.p.",
    "wof:placetype":"venue"
},
  "geometry": {"coordinates":[2.177478075,41.4265785217],"type":"Point"}
}