{
  "type": "Feature",
  "properties": {
    "addr:full":"Carrer de Damia Forment, 4 Sabadell Barcelona 08205",
    "addr:housenumber":"4",
    "addr:postcode":"08205",
    "addr:street":"Carrer De Damia Forment",
    "iso:country":"ES",
    "sg:address":"Carrer de Damia Forment, 4",
    "sg:city":"Sabadell",
    "sg:orig_category":"Confecci\u00d3n De Trajes Para Se\u00d1oras",
    "sg:phone":"+34 937 27 42 41",
    "sg:postcode":"08205",
    "sg:province":"Barcelona",
    "wof:name":"Neslpe 2010 S.l.",
    "wof:placetype":"venue"
},
  "geometry": {"coordinates":[2.0956919193,41.5405693054],"type":"Point"}
}