{
  "type": "Feature",
  "properties": {
    "addr:full":"Carrer de Catalunya, 21 Llerona Barcelona 08520",
    "addr:housenumber":"21",
    "addr:postcode":"08520",
    "addr:street":"Carrer De Catalunya",
    "iso:country":"ES",
    "sg:address":"Carrer de Catalunya, 21",
    "sg:city":"Llerona",
    "sg:orig_category":"Comercio De Piezas De Recambio Y De Accesorios De Veh\u00cdculos, Veh\u00cdculos Industriales",
    "sg:phone":"+34 938 40 56 25",
    "sg:postcode":"08520",
    "sg:province":"Barcelona",
    "sg:website":"www.alf`apasts-tuning.com",
    "wof:name":"Alfaparts S.l.",
    "wof:placetype":"venue"
},
  "geometry": {"coordinates":[2.2976236343,41.6471214294],"type":"Point"}
}