{
  "type": "Feature",
  "properties": {
    "addr:full":"Calle de Aparicio Y Ruiz, 3 Burgos Burgos 09003",
    "addr:housenumber":"3",
    "addr:postcode":"09003",
    "addr:street":"Calle De Aparicio Y Ruiz",
    "iso:country":"ES",
    "sg:address":"Calle de Aparicio Y Ruiz, 3",
    "sg:city":"Burgos",
    "sg:orig_category":"Agencias Y Asesores De Publicidad",
    "sg:phone":"+34 947 20 01 25",
    "sg:postcode":"09003",
    "sg:province":"Burgos",
    "wof:name":"Estudio Eurolaser S.l.",
    "wof:placetype":"venue"
},
  "geometry": {"coordinates":[-3.7071766853,42.3385238647],"type":"Point"}
}