{
  "type": "Feature",
  "properties": {
    "addr:full":"Carr Carretera De Lliria, 113 Burjassot Valencia 46100",
    "addr:housenumber":"113",
    "addr:postcode":"46100",
    "addr:street":"Carr Carretera De Lliria",
    "iso:country":"ES",
    "sg:address":"Carr Carretera De Lliria, 113",
    "sg:city":"Burjassot",
    "sg:orig_category":"Peluquer\u00cdas, Peluquer\u00cda Mixta",
    "sg:phone":"+34 963 63 85 94",
    "sg:postcode":"46100",
    "sg:province":"Valencia",
    "wof:name":"Martinez Cortes Antonio",
    "wof:placetype":"venue"
},
  "geometry": {"coordinates":[-0.4105490148,39.5093688965],"type":"Point"}
}