{
  "type": "Feature",
  "properties": {
    "iso:country":"ES",
    "sg:address":"Avda Bouza Martin, 16",
    "sg:city":"Barrantes",
    "sg:orig_category":"Alimentaci\u00d3n General (al Por Menor)",
    "sg:phone":"+34 986 71 00 04",
    "sg:postcode":"36636",
    "sg:province":"Pontevedra",
    "wof:name":"Cui\u00f1as Cui\u00f1as Amadeo",
    "wof:placetype":"venue"
},
  "geometry": {"coordinates":[-8.7683343887,42.5012207031],"type":"Point"}
}