{
  "type": "Feature",
  "properties": {
    "addr:full":"Pl. Espanya, 9 Riba-roja Ebre Tarragona 43790",
    "addr:housenumber":"9",
    "addr:postcode":"43790",
    "addr:street":"Pl. Espanya",
    "iso:country":"ES",
    "sg:address":"Pl. Espanya, 9",
    "sg:city":"Riba-roja Ebre",
    "sg:orig_category":"Iglesia Cat\u00d3lica",
    "sg:phone":"+34 977 41 60 31",
    "sg:postcode":"43790",
    "sg:province":"Tarragona",
    "wof:name":"Bisbat De Tortosa",
    "wof:placetype":"venue"
},
  "geometry": {"coordinates":[0.4865599871,41.2503013611],"type":"Point"}
}