{
  "type": "Feature",
  "properties": {
    "addr:full":"Calle de San Sebastian, 2 Majadahonda Madrid 28220",
    "addr:housenumber":"2",
    "addr:postcode":"28220",
    "addr:street":"Calle De San Sebastian",
    "iso:country":"ES",
    "sg:address":"Calle de San Sebastian, 2",
    "sg:city":"Majadahonda",
    "sg:orig_category":"Panader\u00cdas, Panader\u00cdas",
    "sg:phone":"+34 916 39 53 28",
    "sg:postcode":"28220",
    "sg:province":"Madrid",
    "wof:name":"Toledano Marin Juan",
    "wof:placetype":"venue"
},
  "geometry": {"coordinates":[-3.8760545254,40.4724731445],"type":"Point"}
}