{
  "type": "Feature",
  "properties": {
    "addr:full":"Calle de Tomillo (del), 53 Alderete Madrid 28440",
    "addr:housenumber":"53",
    "addr:postcode":"28440",
    "addr:street":"Calle De Tomillo Del",
    "iso:country":"ES",
    "sg:address":"Calle de Tomillo (del), 53",
    "sg:city":"Alderete",
    "sg:orig_category":"Galvanizaci\u00d3n, Esta\u00d1ado, Emplomado",
    "sg:phone":"+34 918 54 81 76",
    "sg:postcode":"28440",
    "sg:province":"Madrid",
    "wof:name":"Soportes Metalicos Tubulares S.l.",
    "wof:placetype":"venue"
},
  "geometry": {"coordinates":[-3.7003455162,40.4166908264],"type":"Point"}
}