{
  "type": "Feature",
  "properties": {
    "addr:full":"Carrer de Pare Rodes, 26 Barcelona Barcelona 08042",
    "addr:housenumber":"26",
    "addr:postcode":"08042",
    "addr:street":"Carrer De Pare Rodes",
    "iso:country":"ES",
    "sg:address":"Carrer de Pare Rodes, 26",
    "sg:city":"Barcelona",
    "sg:orig_category":"Ropa Para Se\u00d1oras (al Por Menor)",
    "sg:phone":"+34 933 53 15 32",
    "sg:postcode":"08042",
    "sg:province":"Barcelona",
    "wof:name":"Escala 4 S.cv.",
    "wof:placetype":"venue"
},
  "geometry": {"coordinates":[2.1753499508,41.4402694702],"type":"Point"}
}