{
  "type": "Feature",
  "properties": {
    "iso:country":"ES",
    "sg:address":"Calle de Marques De Montortal, 36",
    "sg:city":"Valencia",
    "sg:orig_category":"Farmacias",
    "sg:phone":"+34 963 65 29 72",
    "sg:postcode":"46019",
    "sg:province":"Valencia",
    "wof:name":"Diaz Jimenez Solas Mercedes",
    "wof:placetype":"venue"
},
  "geometry": {"coordinates":[-0.3752360046,39.4942855835],"type":"Point"}
}