{
  "type": "Feature",
  "properties": {
    "addr:full":"Carrer de Pau Casals, S/n Mas Rampinyo Barcelona 08110",
    "addr:housenumber":"s",
    "addr:postcode":"08110",
    "addr:street":"Carrer De Pau Casals;/ N Mas Rampinyo",
    "iso:country":"ES",
    "sg:address":"Carrer de Pau Casals, S/n",
    "sg:city":"Mas Rampinyo",
    "sg:orig_category":"Molduras, Junquillos, Listones Y Molduras Perforadas",
    "sg:phone":"+34 935 64 00 44",
    "sg:postcode":"08110",
    "sg:province":"Barcelona",
    "wof:name":"Casado Carrascosa Leoncia",
    "wof:placetype":"venue"
},
  "geometry": {"coordinates":[2.1793019772,41.495262146],"type":"Point"}
}