{
  "type": "Feature",
  "properties": {
    "addr:full":"Carrer de Consell De Cent, 159 Barcelona Barcelona 08015",
    "addr:housenumber":"159",
    "addr:postcode":"08015",
    "addr:street":"Carrer De Consell De Cent",
    "iso:country":"ES",
    "sg:address":"Carrer de Consell De Cent, 159",
    "sg:city":"Barcelona",
    "sg:orig_category":"Venta, Colocaci\u00d3n, Reparaci\u00d3n De Radiadores Para Veh\u00cdculos",
    "sg:phone":"+34 934 54 50 92",
    "sg:postcode":"08015",
    "sg:province":"Barcelona",
    "wof:name":"Bru Cortell Tomas",
    "wof:placetype":"venue"
},
  "geometry": {"coordinates":[2.154417038,41.3827896118],"type":"Point"}
}