{
  "type": "Feature",
  "properties": {
    "addr:full":"Afores, S/n Cadaques Girona 17488",
    "addr:housenumber":"s / n",
    "addr:postcode":"17488",
    "addr:street":"Afores",
    "iso:country":"ES",
    "sg:address":"Afores, S/n",
    "sg:city":"Cadaques",
    "sg:orig_category":"Inmobiliaria (agencias)",
    "sg:phone":"+34 972 25 84 51",
    "sg:postcode":"17488",
    "sg:province":"Girona",
    "wof:name":"Pell Baro Ubaldo",
    "wof:placetype":"venue"
},
  "geometry": {"coordinates":[3.2777349949,42.2890510559],"type":"Point"}
}