{
  "type": "Feature",
  "properties": {
    "iso:country":"ES",
    "sg:address":"Carrer de Madiroles, 2",
    "sg:city":"Manlleu",
    "sg:orig_category":"Peluquer\u00cdas, Peluquer\u00cda Mixta",
    "sg:phone":"+34 938 51 38 00",
    "sg:postcode":"08560",
    "sg:province":"Barcelona",
    "wof:name":"Planas Masramon Ramon",
    "wof:placetype":"venue"
},
  "geometry": {"coordinates":[2.2850060463,42.0060882568],"type":"Point"}
}