{
  "type": "Feature",
  "properties": {
    "iso:country":"ES",
    "sg:address":"Carrer de Padilla, 208",
    "sg:city":"Barcelona",
    "sg:orig_category":"Negocio De Madera",
    "sg:phone":"+34 932 32 60 94",
    "sg:postcode":"08013",
    "sg:province":"Barcelona",
    "wof:name":"Distribuidoras Exclusivas De La Construccion S.l.",
    "wof:placetype":"venue"
},
  "geometry": {"coordinates":[2.1795799732,41.4040603638],"type":"Point"}
}