{
  "type": "Feature",
  "properties": {
    "addr:full":"Carrer de Carme, 68 Barcelona Barcelona 08001",
    "addr:housenumber":"68",
    "addr:postcode":"08001",
    "addr:street":"Carrer De Carme",
    "iso:country":"ES",
    "sg:address":"Carrer de Carme, 68",
    "sg:city":"Barcelona",
    "sg:orig_category":"Bazares, Art\u00cdculos De Limpieza Y De Cocina (al Por Menor)",
    "sg:phone":"+34 934 42 07 36",
    "sg:postcode":"08001",
    "sg:province":"Barcelona",
    "wof:name":"Uddin  Jasin",
    "wof:placetype":"venue"
},
  "geometry": {"coordinates":[2.1679370403,41.3810653687],"type":"Point"}
}