{
  "type": "Feature",
  "properties": {
    "addr:full":"Calle de Sagunto, 18 Pozuelo De Alarcon Madrid 28223",
    "addr:housenumber":"18",
    "addr:postcode":"28223",
    "addr:street":"Calle De Sagunto",
    "iso:country":"ES",
    "sg:address":"Calle de Sagunto, 18",
    "sg:city":"Pozuelo De Alarcon",
    "sg:orig_category":"Confecci\u00d3n De Trajes Para Se\u00d1oras",
    "sg:phone":"+34 913 52 92 98",
    "sg:postcode":"28223",
    "sg:province":"Madrid",
    "wof:name":"Rey Redon Matilde",
    "wof:placetype":"venue"
},
  "geometry": {"coordinates":[-3.8118081093,40.4355125427],"type":"Point"}
}