{
  "type": "Feature",
  "properties": {
    "iso:country":"ES",
    "sg:address":"Calle de Magdalena, 5",
    "sg:city":"Oviedo",
    "sg:orig_category":"Muebles, Minoristas",
    "sg:phone":"+34 985 73 80 30",
    "sg:postcode":"33009",
    "sg:province":"Asturias",
    "wof:name":"Garcia Mu\u00f1iz Cristina",
    "wof:placetype":"venue"
},
  "geometry": {"coordinates":[-5.8446731567,43.3599700928],"type":"Point"}
}