{
  "type": "Feature",
  "properties": {
    "addr:full":"Calle de Virgen De La Paloma, 26 Torrevieja Alicante 03180",
    "addr:housenumber":"26",
    "addr:postcode":"03180",
    "addr:street":"Calle De Virgen De La Paloma",
    "iso:country":"ES",
    "sg:address":"Calle de Virgen De La Paloma, 26",
    "sg:city":"Torrevieja",
    "sg:orig_category":"Quincaller\u00cda (al Por Menor)",
    "sg:phone":"+34 965 71 75 36",
    "sg:postcode":"03180",
    "sg:province":"Alicante",
    "wof:name":"Andres 6 S.l.",
    "wof:placetype":"venue"
},
  "geometry": {"coordinates":[-0.6712707281,37.9806442261],"type":"Point"}
}