{
  "type": "Feature",
  "properties": {
    "iso:country":"ES",
    "sg:address":"Pase Reina Cristina, 16",
    "sg:city":"Madrid",
    "sg:orig_category":"Asociaciones, Organismos Culturales Y Socioeducativos",
    "sg:phone":"+34 914 33 67 91",
    "sg:postcode":"28014",
    "sg:province":"Madrid",
    "wof:name":"Asoc. G. Scout 217 Matterhorn",
    "wof:placetype":"venue"
},
  "geometry": {"coordinates":[-3.682169199,40.4069252014],"type":"Point"}
}