{
  "type": "Feature",
  "properties": {
    "addr:full":"Rua Pedregal, 6 Bertamirans La Coru\u00f1a 15220",
    "addr:housenumber":"6",
    "addr:postcode":"15220",
    "addr:street":"Rua Pedregal;La Corun\u0303A",
    "iso:country":"ES",
    "sg:address":"Rua Pedregal, 6",
    "sg:city":"Bertamirans",
    "sg:orig_category":"Tintorer\u00cdas, Limpieza En Seco",
    "sg:phone":"+34 981 89 10 50",
    "sg:postcode":"15220",
    "sg:province":"La Coru\u00f1a",
    "wof:name":"Lavanderia Tintoreria 2000 S.l.",
    "wof:placetype":"venue"
},
  "geometry": {"coordinates":[-8.6583547592,42.8581771851],"type":"Point"}
}