{
  "type": "Feature",
  "properties": {
    "addr:full":"Calle de Mesones, 11 Herencia Ciudad Real 13640",
    "addr:housenumber":"11",
    "addr:postcode":"13640",
    "addr:street":"Calle De Mesones",
    "iso:country":"ES",
    "sg:address":"Calle de Mesones, 11",
    "sg:city":"Herencia",
    "sg:orig_category":"Sales (al Por Mayor)",
    "sg:phone":"+34 926 57 10 31",
    "sg:postcode":"13640",
    "sg:province":"Ciudad Real",
    "wof:name":"Harinas Palmero S.l.",
    "wof:placetype":"venue"
},
  "geometry": {"coordinates":[-3.3539988995,39.3678512573],"type":"Point"}
}