{
  "type": "Feature",
  "properties": {
    "addr:full":"Avda Andalucia (de), 113 Estacion M\u00e1laga 29580",
    "addr:housenumber":"113",
    "addr:postcode":"29580",
    "addr:street":"Avda Andalucia De;Ma\u0301Laga",
    "iso:country":"ES",
    "sg:address":"Avda Andalucia (de), 113",
    "sg:city":"Estacion",
    "sg:orig_category":"Inform\u00c1tica, Ofim\u00c1tica (estudios, Asesor\u00cda, Ingenier\u00cda, Formaci\u00d3n)",
    "sg:phone":"+34 952 42 70 04",
    "sg:postcode":"29580",
    "sg:province":"M\u00e1laga",
    "wof:name":"Prinsoft S.l.",
    "wof:placetype":"venue"
},
  "geometry": {"coordinates":[-4.6123180389,36.7342414856],"type":"Point"}
}