{
  "type": "Feature",
  "properties": {
    "addr:full":"Calle de Do\u00d1a Perfecta, 247 Palmas De Gran Canaria Las Palmas 35012",
    "addr:housenumber":"247",
    "addr:postcode":"35012",
    "addr:street":"Calle De Don\u0303A Perfecta",
    "iso:country":"ES",
    "sg:address":"Calle de Do\u00d1a Perfecta, 247",
    "sg:city":"Palmas De Gran Canaria",
    "sg:orig_category":"Electromec\u00c1nica",
    "sg:phone":"+34 928 28 06 43",
    "sg:postcode":"35012",
    "sg:province":"Las Palmas",
    "wof:name":"Delgado Perez Manuel",
    "wof:placetype":"venue"
},
  "geometry": {"coordinates":[-15.439655304,28.1066703796],"type":"Point"}
}