{
  "type": "Feature",
  "properties": {
    "addr:full":"Calle de Pizarro, 1 S. Fernando C\u00e1diz 11100",
    "addr:housenumber":"1",
    "addr:postcode":"11100",
    "addr:street":"Calle De Pizarro;S. Fernando Ca\u0301Diz",
    "iso:country":"ES",
    "sg:address":"Calle de Pizarro, 1",
    "sg:city":"S. Fernando",
    "sg:orig_category":"Abogados",
    "sg:phone":"+34 956 88 22 99",
    "sg:postcode":"11100",
    "sg:province":"C\u00e1diz",
    "wof:name":"Aparicio Mota Angel",
    "wof:placetype":"venue"
},
  "geometry": {"coordinates":[-6.2008161545,36.4605827332],"type":"Point"}
}