{
  "type": "Feature",
  "properties": {
    "iso:country":"ES",
    "sg:address":"Calle de Orly, 1",
    "sg:city":"Pozuelo De Alarcon",
    "sg:orig_category":"Asesor\u00cda Sobre Comunicaci\u00d3n De Empresas",
    "sg:phone":"+34 913 51 36 56",
    "sg:postcode":"28224",
    "sg:province":"Madrid",
    "wof:name":"Ingenieria Y Consultoria Electrica S.l.",
    "wof:placetype":"venue"
},
  "geometry": {"coordinates":[-3.7945430279,40.4494132996],"type":"Point"}
}