{
  "type": "Feature",
  "properties": {
    "iso:country":"ES",
    "sg:address":"Carrer de Girona, 5",
    "sg:city":"Sant Feliu Llobregat",
    "sg:orig_category":"Ense\u00d1anza: Profesiones Art\u00cdsticas",
    "sg:phone":"+34 936 85 09 88",
    "sg:postcode":"08980",
    "sg:province":"Barcelona",
    "wof:name":"Foto Poli S.l.",
    "wof:placetype":"venue"
},
  "geometry": {"coordinates":[2.0435750484,41.3816261292],"type":"Point"}
}