{
  "type": "Feature",
  "properties": {
    "addr:full":"C/ Antonio Garcia Cayuelas, 48 Elche Alicante 03206",
    "addr:housenumber":"48",
    "addr:postcode":"03206",
    "addr:street":"C / Antonio Garcia Cayuelas",
    "iso:country":"ES",
    "sg:address":"C/ Antonio Garcia Cayuelas, 48",
    "sg:city":"Elche",
    "sg:orig_category":"Iglesias Evang\u00c9licas",
    "sg:phone":"+34 965 46 06 10",
    "sg:postcode":"03206",
    "sg:province":"Alicante",
    "wof:name":"Iglesia Bautista Emanuel De Elche",
    "wof:placetype":"venue"
},
  "geometry": {"coordinates":[-0.71192801,38.2752304077],"type":"Point"}
}