{
  "type": "Feature",
  "properties": {
    "iso:country":"ES",
    "sg:address":"Calle de Santa Cruz, S/n",
    "sg:city":"Burgos",
    "sg:orig_category":"Institutos De Belleza",
    "sg:phone":"+34 947 25 03 50",
    "sg:postcode":"09002",
    "sg:province":"Burgos",
    "wof:name":"Arnaiz Pascual Maria Soledad",
    "wof:placetype":"venue"
},
  "geometry": {"coordinates":[-3.6969146729,42.3374443054],"type":"Point"}
}