{
  "type": "Feature",
  "properties": {
    "iso:country":"ES",
    "sg:address":"Calle de Jose Franchy Roca, 5",
    "sg:city":"Palmas De Gran Canaria",
    "sg:orig_category":"Formaci\u00d3n Continuada (variada)",
    "sg:phone":"+34 928 22 01 67",
    "sg:postcode":"35007",
    "sg:province":"Las Palmas",
    "sg:website":"www.fundescan.es",
    "wof:name":"Fundacion Para El Desarrollo Social De Canarias",
    "wof:placetype":"venue"
},
  "geometry": {"coordinates":[-15.431186676,28.1390190125],"type":"Point"}
}