{
  "type": "Feature",
  "properties": {
    "addr:full":"Carrer de Federico Garcia Lorca (de), 22 Montornes Nord Barcelona 08170",
    "addr:housenumber":"22",
    "addr:postcode":"08170",
    "addr:street":"Carrer De Federico Garcia Lorca De",
    "iso:country":"ES",
    "sg:address":"Carrer de Federico Garcia Lorca (de), 22",
    "sg:city":"Montornes Nord",
    "sg:orig_category":"Electricidad: Instaladores",
    "sg:phone":"+34 935 72 09 61",
    "sg:postcode":"08170",
    "sg:province":"Barcelona",
    "wof:name":"Bailon Instalaciones S.l.",
    "wof:placetype":"venue"
},
  "geometry": {"coordinates":[2.2679901123,41.5543708801],"type":"Point"}
}