{
  "type": "Feature",
  "properties": {
    "addr:full":"Pla\u00c7 Coma (de La), 15 Cassa Selva Girona 17244",
    "addr:postcode":"17244",
    "addr:street":"Cassa;Girona",
    "iso:country":"ES",
    "sg:address":"Pla\u00c7 Coma (de La), 15",
    "sg:city":"Cassa Selva",
    "sg:orig_category":"Pizzer\u00cdas",
    "sg:phone":"+34 972 46 22 03",
    "sg:postcode":"17244",
    "sg:province":"Girona",
    "wof:name":"Aragon Torres David",
    "wof:placetype":"venue"
},
  "geometry": {"coordinates":[2.8236999512,41.9817962646],"type":"Point"}
}