{
  "type": "Feature",
  "properties": {
    "addr:full":"Praz Jose Otero, 6 Barco Ourense 32300",
    "addr:housenumber":"6",
    "addr:postcode":"32300",
    "addr:street":"Jose Otero",
    "iso:country":"ES",
    "sg:address":"Praz Jose Otero, 6",
    "sg:city":"Barco",
    "sg:orig_category":"M\u00c9dicos: Estomatolog\u00cda",
    "sg:phone":"+34 988 32 18 18",
    "sg:postcode":"32300",
    "sg:province":"Ourense",
    "wof:name":"Cobo Arias Ramiro",
    "wof:placetype":"venue"
},
  "geometry": {"coordinates":[-6.9837059975,42.4104614258],"type":"Point"}
}