{
  "type": "Feature",
  "properties": {
    "addr:full":"Calle de Capitan Bermejo, 53 Mata Toledo 45534",
    "addr:housenumber":"53",
    "addr:postcode":"45534",
    "addr:street":"Calle De Capitan Bermejo",
    "iso:country":"ES",
    "sg:address":"Calle de Capitan Bermejo, 53",
    "sg:city":"Mata",
    "sg:orig_category":"Negocio De Granos Y Harinas",
    "sg:phone":"+34 925 74 72 04",
    "sg:postcode":"45534",
    "sg:province":"Toledo",
    "wof:name":"Campotrigal S.l",
    "wof:placetype":"venue"
},
  "geometry": {"coordinates":[-4.4382195473,39.9458007812],"type":"Point"}
}