{
  "type": "Feature",
  "properties": {
    "iso:country":"ES",
    "sg:address":"Cmno San Rafael, 40",
    "sg:city":"Malaga",
    "sg:orig_category":"Centros Empresariales",
    "sg:phone":"+34 952 31 50 43",
    "sg:postcode":"29006",
    "sg:province":"M\u00e1laga",
    "wof:name":"Molina Perez Maria",
    "wof:placetype":"venue"
},
  "geometry": {"coordinates":[-4.4464378357,36.7089347839],"type":"Point"}
}