{
  "type": "Feature",
  "properties": {
    "addr:full":"Avda Miajadas, 57 Trujillo C\u00e1ceres 10200",
    "addr:housenumber":"57",
    "addr:postcode":"10200",
    "addr:street":"Avda Miajadas;Ca\u0301Ceres",
    "iso:country":"ES",
    "sg:address":"Avda Miajadas, 57",
    "sg:city":"Trujillo",
    "sg:orig_category":"Chapa Y Pintura Veh\u00cdculos",
    "sg:phone":"+34 927 32 09 11",
    "sg:postcode":"10200",
    "sg:province":"C\u00e1ceres",
    "wof:name":"Godoy Blanco Arturo",
    "wof:placetype":"venue"
},
  "geometry": {"coordinates":[-5.8807587624,39.4546508789],"type":"Point"}
}