{
  "type": "Feature",
  "properties": {
    "iso:country":"ES",
    "sg:address":"Pl Bages, 14",
    "sg:city":"Manresa",
    "sg:classifiers":[
        {
            "category":"Autos & Motor Vehicles",
            "subcategory":"Automobile Sales",
            "type":"Retail Goods"
        }
    ],
    "sg:phone":"+34 938 74 38 57",
    "sg:postcode":"08242",
    "sg:province":"Barcelona",
    "sg:website":"www.autoescolafont.com",
    "wof:name":"Autoescola Font S.l.",
    "wof:placetype":"venue"
},
  "geometry": {"coordinates":[1.83111763,41.7337760925],"type":"Point"}
}