{
  "type": "Feature",
  "properties": {
    "iso:country":"ES",
    "sg:address":"Avda America, 24",
    "sg:city":"Zaragoza",
    "sg:orig_category":"Cl\u00cdnicas Dentales",
    "sg:phone":"+34 976 25 93 10",
    "sg:postcode":"50007",
    "sg:province":"Zaragoza",
    "wof:name":"Clinica Dental Zaragoza S.l.",
    "wof:placetype":"venue"
},
  "geometry": {"coordinates":[-0.8856679797,41.6312217712],"type":"Point"}
}