{
  "type": "Feature",
  "properties": {
    "iso:country":"ES",
    "sg:address":"Carretera De Freila, S/n",
    "sg:city":"Zujar",
    "sg:orig_category":"Negocio De Materiales De Construcci\u00d3n",
    "sg:phone":"+34 958 71 64 50",
    "sg:postcode":"18811",
    "sg:province":"Granada",
    "wof:name":"Corral Gomez Miguel",
    "wof:placetype":"venue"
},
  "geometry": {"coordinates":[-2.8475248814,37.5380592346],"type":"Point"}
}