{
  "type": "Feature",
  "properties": {
    "iso:country":"ES",
    "sg:address":"Calle de Abastos (de), 68",
    "sg:city":"Aranjuez",
    "sg:orig_category":"Librer\u00cdas",
    "sg:phone":"+34 918 91 28 50",
    "sg:postcode":"28300",
    "sg:province":"Madrid",
    "wof:name":"Libreria Aranjuez S. A.",
    "wof:placetype":"venue"
},
  "geometry": {"coordinates":[-3.6028034687,40.0318717957],"type":"Point"}
}