{
  "type": "Feature",
  "properties": {
    "iso:country":"ES",
    "sg:address":"A Achadiza, 46",
    "sg:city":"Beluso",
    "sg:orig_category":"Piedra Natural",
    "sg:phone":"+34 986 32 06 68",
    "sg:postcode":"36939",
    "sg:province":"Pontevedra",
    "wof:name":"Granigal Sanmartin S.l",
    "wof:placetype":"venue"
},
  "geometry": {"coordinates":[-8.7823858261,42.3033218384],"type":"Point"}
}