{
  "type": "Feature",
  "properties": {
    "iso:country":"ES",
    "sg:address":"Carr Joan Benejam, 5",
    "sg:city":"Blanes",
    "sg:orig_category":"Centros De Educaci\u00d3n Especial",
    "sg:phone":"+34 972 33 07 01",
    "sg:postcode":"17300",
    "sg:province":"Girona",
    "wof:name":"Centre D'educacio Especial Ventijol",
    "wof:placetype":"venue"
},
  "geometry": {"coordinates":[2.7906849384,41.6724243164],"type":"Point"}
}