{
  "type": "Feature",
  "properties": {
    "addr:full":"Calle de Pablo Picasso, 19 Hellin Albacete 02400",
    "addr:housenumber":"19",
    "addr:postcode":"02400",
    "addr:street":"Calle De Pablo Picasso",
    "iso:country":"ES",
    "sg:address":"Calle de Pablo Picasso, 19",
    "sg:city":"Hellin",
    "sg:orig_category":"Chapister\u00cda",
    "sg:phone":"+34 967 30 23 49",
    "sg:postcode":"02400",
    "sg:province":"Albacete",
    "wof:name":"Martinez Esparcia Juan Jose",
    "wof:placetype":"venue"
},
  "geometry": {"coordinates":[-1.6922789812,38.5079078674],"type":"Point"}
}