{
  "type": "Feature",
  "properties": {
    "addr:full":"Ctra Serranillos, 36 Estacion Toledo 45220",
    "addr:housenumber":"36",
    "addr:postcode":"45220",
    "addr:street":"Ctra Serranillos",
    "iso:country":"ES",
    "sg:address":"Ctra Serranillos, 36",
    "sg:city":"Estacion",
    "sg:orig_category":"Fabricaci\u00d3n Y Distribuci\u00d3n De Colas, Masillas Y Encoladoras",
    "sg:phone":"+34 925 54 52 63",
    "sg:postcode":"45220",
    "sg:province":"Toledo",
    "wof:name":"Maxit S.l.",
    "wof:placetype":"venue"
},
  "geometry": {"coordinates":[-3.8059339523,40.1223945618],"type":"Point"}
}