{
  "type": "Feature",
  "properties": {
    "iso:country":"ES",
    "sg:address":"Calle de San Jose De Calasanz, 13",
    "sg:city":"Huesca",
    "sg:orig_category":"Asesor\u00cdas Y Estudios Financieros",
    "sg:phone":"+34 974 21 16 16",
    "sg:postcode":"22002",
    "sg:province":"Huesca",
    "wof:name":"Rivas Anoro Fernando",
    "wof:placetype":"venue"
},
  "geometry": {"coordinates":[-0.4105480015,42.1359024048],"type":"Point"}
}