{
  "type": "Feature",
  "properties": {
    "addr:full":"Carrer de Florencia, 7 Barcelona Barcelona 08041",
    "addr:housenumber":"7",
    "addr:postcode":"08041",
    "addr:street":"Carrer De Florencia",
    "iso:country":"ES",
    "sg:address":"Carrer de Florencia, 7",
    "sg:city":"Barcelona",
    "sg:orig_category":"Electricidad: Instaladores",
    "sg:phone":"+34 934 35 41 17",
    "sg:postcode":"08041",
    "sg:province":"Barcelona",
    "wof:name":"Fap Moreno S.l",
    "wof:placetype":"venue"
},
  "geometry": {"coordinates":[2.1712579727,41.418384552],"type":"Point"}
}