{
  "type": "Feature",
  "properties": {
    "iso:country":"ES",
    "sg:address":"Carrer de Martinez Oriola, 16",
    "sg:city":"Benidorm",
    "sg:orig_category":"Bazares, Art\u00cdculos De Limpieza Y De Cocina (al Por Menor)",
    "sg:phone":"+34 965 85 93 25",
    "sg:postcode":"03500",
    "sg:province":"Alicante",
    "wof:name":"Sebastian Marimon Jaime",
    "wof:placetype":"venue"
},
  "geometry": {"coordinates":[-0.1307920069,38.5357971191],"type":"Point"}
}