{
  "type": "Feature",
  "properties": {
    "addr:full":"Plaz Puerta De Zamora, 2 Salamanca Salamanca 37005",
    "addr:housenumber":"2",
    "addr:postcode":"37005",
    "addr:street":"Puerta;Zamora",
    "iso:country":"ES",
    "sg:address":"Plaz Puerta De Zamora, 2",
    "sg:city":"Salamanca",
    "sg:orig_category":"Loter\u00cda Y T\u00d3mbola",
    "sg:phone":"+34 923 22 23 46",
    "sg:postcode":"37005",
    "sg:province":"Salamanca",
    "wof:name":"Sanchez Malaga Maria Luisa",
    "wof:placetype":"venue"
},
  "geometry": {"coordinates":[-5.6583042145,40.9937133789],"type":"Point"}
}