{
  "type": "Feature",
  "properties": {
    "iso:country":"ES",
    "sg:address":"Barr Cobranes, 18",
    "sg:city":"Langreo",
    "sg:orig_category":"Afiladoras, Pulidoras Y Bru\u00d1idoras",
    "sg:phone":"+34 985 68 37 45",
    "sg:postcode":"33920",
    "sg:province":"Asturias",
    "wof:name":"Gonzalez Calvo Jose Ramon",
    "wof:placetype":"venue"
},
  "geometry": {"coordinates":[-5.7203388214,43.3307266235],"type":"Point"}
}