{
  "type": "Feature",
  "properties": {
    "addr:full":"Avda Esla (el), 31 Santa Maria Del Paramo Le\u00f3n 24240",
    "addr:housenumber":"31",
    "addr:postcode":"24240",
    "addr:street":"Avda Esla El",
    "iso:country":"ES",
    "sg:address":"Avda Esla (el), 31",
    "sg:city":"Santa Maria Del Paramo",
    "sg:orig_category":"Negocio De Materiales De Construcci\u00d3n",
    "sg:phone":"+34 987 35 02 24",
    "sg:postcode":"24240",
    "sg:province":"Le\u00f3n",
    "sg:website":"www.paginasamarillas.es",
    "wof:name":"Francisco Gonzalez Jose Miguel",
    "wof:placetype":"venue"
},
  "geometry": {"coordinates":[-5.7478938103,42.3557701111],"type":"Point"}
}