{
  "type": "Feature",
  "properties": {
    "iso:country":"ES",
    "sg:address":"Calle de Redonda, 8",
    "sg:city":"Rambla",
    "sg:orig_category":"Fabrica De Cer\u00c1micas",
    "sg:phone":"+34 957 68 20 31",
    "sg:postcode":"14540",
    "sg:province":"C\u00f3rdoba",
    "wof:name":"Urbano Peinado Joaquin",
    "wof:placetype":"venue"
},
  "geometry": {"coordinates":[-4.7444868088,37.6043624878],"type":"Point"}
}