{
  "type": "Feature",
  "properties": {
    "iso:country":"ES",
    "sg:address":"Calle de Bouza Brey, 54",
    "sg:city":"Cortegada",
    "sg:orig_category":"Bancos",
    "sg:phone":"+34 988 48 35 00",
    "sg:postcode":"32200",
    "sg:province":"Ourense",
    "sg:website":"www.bancopastor.es",
    "wof:name":"Francisco Fernandez Maria Praxedes",
    "wof:placetype":"venue"
},
  "geometry": {"coordinates":[-8.1639022827,42.203994751],"type":"Point"}
}