{
  "type": "Feature",
  "properties": {
    "addr:full":"Plaz Luis Hauzeur, 2 Torrelavega Cantabria 39300",
    "addr:housenumber":"2",
    "addr:postcode":"39300",
    "addr:street":"Plaz Luis Hauzeur",
    "iso:country":"ES",
    "sg:address":"Plaz Luis Hauzeur, 2",
    "sg:city":"Torrelavega",
    "sg:orig_category":"Arquitectos",
    "sg:phone":"+34 942 88 22 67",
    "sg:postcode":"39300",
    "sg:province":"Cantabria",
    "wof:name":"Tejeria Saiz Pedro",
    "wof:placetype":"venue"
},
  "geometry": {"coordinates":[-4.0534219742,43.3485183716],"type":"Point"}
}