{
  "type": "Feature",
  "properties": {
    "addr:full":"Calle de Valdenebro, 24 Coca Segovia 40480",
    "addr:housenumber":"24",
    "addr:postcode":"40480",
    "addr:street":"Calle De Valdenebro",
    "iso:country":"ES",
    "sg:address":"Calle de Valdenebro, 24",
    "sg:city":"Coca",
    "sg:orig_category":"Alimentaci\u00d3n General (al Por Menor)",
    "sg:phone":"+34 921 58 64 27",
    "sg:postcode":"40480",
    "sg:province":"Segovia",
    "wof:name":"Autoservicio Coca S.l.",
    "wof:placetype":"venue"
},
  "geometry": {"coordinates":[-4.5217132568,41.217502594],"type":"Point"}
}