{
  "type": "Feature",
  "properties": {
    "iso:country":"ES",
    "sg:address":"Carrer de Cooperativa, 12",
    "sg:city":"Galera",
    "sg:orig_category":"Cooperativas Agr\u00cdcolas",
    "sg:phone":"+34 977 71 87 89",
    "sg:postcode":"43515",
    "sg:province":"Tarragona",
    "wof:name":"Sociedad Cooperativa Agraria",
    "wof:placetype":"venue"
},
  "geometry": {"coordinates":[0.464733988,40.6832962036],"type":"Point"}
}