{
  "type": "Feature",
  "properties": {
    "iso:country":"ES",
    "sg:address":"Calle de Agustin Vi\u00d1uales Pardo, 7",
    "sg:city":"Huesca",
    "sg:orig_category":"Caf\u00c9s, Bares, Cervecer\u00cdas",
    "sg:phone":"+34 974 21 84 21",
    "sg:postcode":"22004",
    "sg:province":"Huesca",
    "wof:name":"Lobera Zamora Juan Carmelo",
    "wof:placetype":"venue"
},
  "geometry": {"coordinates":[-0.4195739031,42.1391830444],"type":"Point"}
}