{
  "type": "Feature",
  "properties": {
    "iso:country":"ES",
    "sg:address":"Carr Castellar, S/n",
    "sg:city":"Casc Urba",
    "sg:orig_category":"Oficinas De Turismo, Asociaciones De Iniciativa",
    "sg:phone":"+34 972 12 09 44",
    "sg:postcode":"17490",
    "sg:province":"Girona",
    "wof:name":"Ajuntament De Llanca",
    "wof:placetype":"venue"
},
  "geometry": {"coordinates":[2.8236999512,41.9817962646],"type":"Point"}
}