{
  "type": "Feature",
  "properties": {
    "addr:full":"Carr Estacio, 5 Vallfogona Balaguer Lleida 25680",
    "addr:housenumber":"5",
    "addr:postcode":"25680",
    "addr:street":"Carr Estacio",
    "iso:country":"ES",
    "sg:address":"Carr Estacio, 5",
    "sg:city":"Vallfogona Balaguer",
    "sg:orig_category":"Peluqueros: De Se\u00d1oras",
    "sg:phone":"+34 973 43 21 27",
    "sg:postcode":"25680",
    "sg:province":"Lleida",
    "wof:name":"Clariso Sabanes Maria Teresa",
    "wof:placetype":"venue"
},
  "geometry": {"coordinates":[0.8158649802,41.7522468567],"type":"Point"}
}