{
  "type": "Feature",
  "properties": {
    "iso:country":"ES",
    "sg:address":"Calle de Galicia, 38",
    "sg:city":"Ciudad Real",
    "sg:orig_category":"Molduras, Junquillos, Listones Y Molduras Perforadas",
    "sg:phone":"+34 926 25 23 47",
    "sg:postcode":"13004",
    "sg:province":"Ciudad Real",
    "wof:name":"Ortega Garcia Emilio",
    "wof:placetype":"venue"
},
  "geometry": {"coordinates":[-3.9197831154,38.9801368713],"type":"Point"}
}