{
  "type": "Feature",
  "properties": {
    "iso:country":"ES",
    "sg:address":"Calle de Ancha, 118",
    "sg:city":"Montalban De Cordoba",
    "sg:orig_category":"Zapatos (al Por Menor)",
    "sg:phone":"+34 957 31 01 08",
    "sg:postcode":"14548",
    "sg:province":"C\u00f3rdoba",
    "wof:name":"Salces Jimenez Juan",
    "wof:placetype":"venue"
},
  "geometry": {"coordinates":[-4.7507448196,37.5805091858],"type":"Point"}
}