{
  "type": "Feature",
  "properties": {
    "iso:country":"ES",
    "sg:address":"Calle de Julian Perate Barroeta, 9",
    "sg:city":"Caceres",
    "sg:orig_category":"Alimentaci\u00d3n General (al Por Menor)",
    "sg:phone":"+34 927 18 19 92",
    "sg:postcode":"10004",
    "sg:province":"C\u00e1ceres",
    "wof:name":"Malato De Tena Davila Ricardo",
    "wof:placetype":"venue"
},
  "geometry": {"coordinates":[-6.3626742363,39.4866294861],"type":"Point"}
}