{
  "type": "Feature",
  "properties": {
    "iso:country":"ES",
    "sg:address":"Partida Recreo, 13",
    "sg:city":"Riudoms",
    "sg:orig_category":"Agricultores, Agricultores",
    "sg:phone":"+34 977 85 04 06",
    "sg:postcode":"43330",
    "sg:province":"Tarragona",
    "wof:name":"Gili-ferre Scp",
    "wof:placetype":"venue"
},
  "geometry": {"coordinates":[1.0541909933,41.1382713318],"type":"Point"}
}