{
  "type": "Feature",
  "properties": {
    "addr:full":"Avda Luis Bu\u00d1uel, 8 Malaga M\u00e1laga 29011",
    "addr:housenumber":"8",
    "addr:postcode":"29011",
    "addr:street":"Avda Luis Bun\u0303Uel;Ma\u0301Laga",
    "iso:country":"ES",
    "sg:address":"Avda Luis Bu\u00d1uel, 8",
    "sg:city":"Malaga",
    "sg:orig_category":"Alquiler De Casas Y Habitaciones Amuebladas",
    "sg:phone":"+34 952 30 52 12",
    "sg:postcode":"29011",
    "sg:province":"M\u00e1laga",
    "wof:name":"Telefonia Saltele Marbella S.l.",
    "wof:placetype":"venue"
},
  "geometry": {"coordinates":[-4.4285931587,36.7332458496],"type":"Point"}
}