{
  "type": "Feature",
  "properties": {
    "addr:full":"Calle de Viera Y Clavijo, 16 Palmas De Gran Canaria Las Palmas 35002",
    "addr:housenumber":"16",
    "addr:postcode":"35002",
    "addr:street":"Calle De Viera Y Clavijo",
    "iso:country":"ES",
    "sg:address":"Calle de Viera Y Clavijo, 16",
    "sg:city":"Palmas De Gran Canaria",
    "sg:orig_category":"\u00d3ptica: Instrumentos (fabricaci\u00d3n)",
    "sg:phone":"+34 928 36 61 87",
    "sg:postcode":"35002",
    "sg:province":"Las Palmas",
    "wof:name":"Martin Mu\u00f1oz Sebastian",
    "wof:placetype":"venue"
},
  "geometry": {"coordinates":[-15.4175987244,28.1063537598],"type":"Point"}
}