{
  "type": "Feature",
  "properties": {
    "addr:full":"Carrer de Llibertat, 38 S. Boi Llobregat Barcelona 08830",
    "addr:housenumber":"38",
    "addr:postcode":"08830",
    "addr:street":"Carrer De Llibertat",
    "iso:country":"ES",
    "sg:address":"Carrer de Llibertat, 38",
    "sg:city":"S. Boi Llobregat",
    "sg:orig_category":"Ropa De Casa (fabricaci\u00d3n, Al Por Mayor)",
    "sg:phone":"+34 936 30 77 83",
    "sg:postcode":"08830",
    "sg:province":"Barcelona",
    "wof:name":"Noriega Diaz Trinidad",
    "wof:placetype":"venue"
},
  "geometry": {"coordinates":[2.0308890343,41.3501205444],"type":"Point"}
}