{
  "type": "Feature",
  "properties": {
    "iso:country":"ES",
    "sg:address":"Carrer de Doctor Fleming, 12",
    "sg:city":"Premia Mar",
    "sg:orig_category":"Peluqueros: De Se\u00d1oras",
    "sg:phone":"+34 937 52 27 95",
    "sg:postcode":"08330",
    "sg:province":"Barcelona",
    "wof:name":"Roca Fuentes Ernestina",
    "wof:placetype":"venue"
},
  "geometry": {"coordinates":[2.3571259975,41.4932479858],"type":"Point"}
}