{
  "type": "Feature",
  "properties": {
    "addr:full":"Calle de Romana, 11 Sevilla Sevilla 41020",
    "addr:housenumber":"11",
    "addr:postcode":"41020",
    "addr:street":"Calle De Romana",
    "iso:country":"ES",
    "sg:address":"Calle de Romana, 11",
    "sg:city":"Sevilla",
    "sg:orig_category":"Ropa Para Caballeros Y Se\u00d1oras (al Por Mayor)",
    "sg:phone":"+34 954 67 00 73",
    "sg:postcode":"41020",
    "sg:province":"Sevilla",
    "wof:name":"Quality Wear S.l.",
    "wof:placetype":"venue"
},
  "geometry": {"coordinates":[-5.9398851395,37.3937416077],"type":"Point"}
}