{
  "type": "Feature",
  "properties": {
    "iso:country":"ES",
    "sg:address":"Calle de San Bartolome, 2",
    "sg:city":"Antequera",
    "sg:orig_category":"Cajas De Ahorro",
    "sg:phone":"+34 952 70 50 01",
    "sg:postcode":"29200",
    "sg:province":"M\u00e1laga",
    "wof:name":"Caja De Ahorros De Valencia Castellon Y Alicante",
    "wof:placetype":"venue"
},
  "geometry": {"coordinates":[-4.5632472038,37.0197525024],"type":"Point"}
}