{
  "type": "Feature",
  "properties": {
    "addr:full":"Carr Girona, 13 Figueres Girona 17600",
    "addr:housenumber":"13",
    "addr:postcode":"17600",
    "addr:street":"Carr Girona",
    "iso:country":"ES",
    "sg:address":"Carr Girona, 13",
    "sg:city":"Figueres",
    "sg:orig_category":"Fabricaci\u00d3n De Quesos",
    "sg:phone":"+34 972 50 42 31",
    "sg:postcode":"17600",
    "sg:province":"Girona",
    "wof:name":"Bosch Estany Maria Angeles",
    "wof:placetype":"venue"
},
  "geometry": {"coordinates":[2.9614748955,42.2669487],"type":"Point"}
}