{
  "type": "Feature",
  "properties": {
    "iso:country":"ES",
    "sg:address":"Carr Sant Pere, 108",
    "sg:city":"Badalona",
    "sg:orig_category":"Sexshops",
    "sg:phone":"+34 933 84 16 76",
    "sg:postcode":"08911",
    "sg:province":"Barcelona",
    "sg:website":"www.noespecat.com",
    "wof:name":"Perez De Leon Rodriguez Salvador",
    "wof:placetype":"venue"
},
  "geometry": {"coordinates":[2.2511770725,41.4496040344],"type":"Point"}
}