{
  "type": "Feature",
  "properties": {
    "iso:country":"ES",
    "sg:address":"Carr Joan Miro, 4",
    "sg:city":"Santa Cristina D'aro",
    "sg:orig_category":"Aguas (distribuci\u00d3n, Servicios)",
    "sg:phone":"+34 972 83 52 96",
    "sg:postcode":"17246",
    "sg:province":"Girona",
    "wof:name":"Aqualia Gestion Integral Del Agua S.a.",
    "wof:placetype":"venue"
},
  "geometry": {"coordinates":[2.9986116886,41.8134918213],"type":"Point"}
}