{
  "type": "Feature",
  "properties": {
    "addr:full":"Alam Cables (de), 13 Aranjuez Madrid 28300",
    "addr:postcode":"28300",
    "addr:street":"Alam",
    "iso:country":"ES",
    "sg:address":"Alam Cables (de), 13",
    "sg:city":"Aranjuez",
    "sg:orig_category":"Papel (al Por Mayor)",
    "sg:phone":"+34 918 91 28 45",
    "sg:postcode":"28300",
    "sg:province":"Madrid",
    "wof:name":"Temasa S.l.",
    "wof:placetype":"venue"
},
  "geometry": {"coordinates":[-3.617552042,40.0289916992],"type":"Point"}
}