{
  "type": "Feature",
  "properties": {
    "iso:country":"ES",
    "sg:address":"Cami Can Bros, 3",
    "sg:city":"Can Bros",
    "sg:orig_category":"Maquinaria Para Industrias Diversas",
    "sg:phone":"+34 937 76 98 11",
    "sg:postcode":"08760",
    "sg:province":"Barcelona",
    "wof:name":"Mecanica Can Bros S.l.",
    "wof:placetype":"venue"
},
  "geometry": {"coordinates":[1.9265979528,41.474105835],"type":"Point"}
}