{
  "type": "Feature",
  "properties": {
    "addr:full":"Calle de Ramon Y Cajal, 40 Garrovillas De Alconetar C\u00e1ceres 10940",
    "addr:housenumber":"40",
    "addr:postcode":"10940",
    "addr:street":"Calle De Ramon Y Cajal;Ca\u0301Ceres",
    "iso:country":"ES",
    "sg:address":"Calle de Ramon Y Cajal, 40",
    "sg:city":"Garrovillas De Alconetar",
    "sg:orig_category":"Asociaciones, Organismos Culturales Y Socioeducativos",
    "sg:phone":"+34 927 30 93 25",
    "sg:postcode":"10940",
    "sg:province":"C\u00e1ceres",
    "wof:name":"Hogar Club Tercera Edad",
    "wof:placetype":"venue"
},
  "geometry": {"coordinates":[-6.5487241745,39.7117080688],"type":"Point"}
}