{
  "type": "Feature",
  "properties": {
    "addr:full":"Calle de San Jose, 3 Graja Iniesta Cuenca 16251",
    "addr:housenumber":"3",
    "addr:postcode":"16251",
    "addr:street":"Calle De San Jose",
    "iso:country":"ES",
    "sg:address":"Calle de San Jose, 3",
    "sg:city":"Graja Iniesta",
    "sg:orig_category":"Cajas Para Embalar",
    "sg:phone":"+34 962 18 81 66",
    "sg:postcode":"16251",
    "sg:province":"Cuenca",
    "wof:name":"Caja Rural De Cuenca",
    "wof:placetype":"venue"
},
  "geometry": {"coordinates":[-1.6720240116,39.5176963806],"type":"Point"}
}