{
  "type": "Feature",
  "properties": {
    "addr:full":"Calle de Zurbano, 57 Madrid Madrid 28010",
    "addr:housenumber":"57",
    "addr:postcode":"madrid;28010",
    "addr:street":"Calle De Zurbano",
    "iso:country":"ES",
    "sg:address":"Calle de Zurbano, 57",
    "sg:city":"Madrid",
    "sg:orig_category":"Centros Empresariales",
    "sg:phone":"+34 913 19 56 04",
    "sg:postcode":"28010",
    "sg:province":"Madrid",
    "wof:name":"Gil-turner Arquitectos S.l.",
    "wof:placetype":"venue"
},
  "geometry": {"coordinates":[-3.6932609081,40.4357070923],"type":"Point"}
}