{
  "type": "Feature",
  "properties": {
    "addr:full":"Calle de Tronera, 13 Fuente Maestre Badajoz 06360",
    "addr:housenumber":"13",
    "addr:postcode":"06360",
    "addr:street":"Calle De Tronera",
    "iso:country":"ES",
    "sg:address":"Calle de Tronera, 13",
    "sg:city":"Fuente Maestre",
    "sg:orig_category":"Alimentaci\u00d3n General (al Por Menor)",
    "sg:phone":"+34 924 53 00 10",
    "sg:postcode":"06360",
    "sg:province":"Badajoz",
    "wof:name":"Autoservicio Descuento La Fuente S.l.",
    "wof:placetype":"venue"
},
  "geometry": {"coordinates":[-6.4500365257,38.5260887146],"type":"Point"}
}