{
  "type": "Feature",
  "properties": {
    "iso:country":"ES",
    "sg:address":"Luga Arboledas (las), S/n",
    "sg:city":"Arboledas",
    "sg:orig_category":"Droguer\u00cdas (al Por Mayor)",
    "sg:phone":"+34 968 67 14 12",
    "sg:postcode":"30600",
    "sg:province":"Murcia",
    "wof:name":"Suministros Eva S.l.",
    "wof:placetype":"venue"
},
  "geometry": {"coordinates":[-1.2987289429,38.117401123],"type":"Point"}
}