{
  "type": "Feature",
  "properties": {
    "addr:full":"Calle de Manuel De Falla, 12 Granada Granada 18005",
    "addr:housenumber":"12",
    "addr:postcode":"18005",
    "addr:street":"Calle De Manuel De Falla",
    "iso:country":"ES",
    "sg:address":"Calle de Manuel De Falla, 12",
    "sg:city":"Granada",
    "sg:orig_category":"Procuradores",
    "sg:phone":"+34 958 26 06 73",
    "sg:postcode":"18005",
    "sg:province":"Granada",
    "wof:name":"Clavarana Caballero Adolfo",
    "wof:placetype":"venue"
},
  "geometry": {"coordinates":[-3.604624033,37.1696929932],"type":"Point"}
}