{
  "type": "Feature",
  "properties": {
    "iso:country":"ES",
    "sg:address":"Calle de Zeharkale, 9",
    "sg:city":"Ermua",
    "sg:orig_category":"Juegos Y Juguetes (al Por Menor)",
    "sg:phone":"+34 943 17 20 52",
    "sg:postcode":"48260",
    "sg:province":"Vizcaya",
    "wof:name":"Rosa Maria Gil - Jugueteria Cabo",
    "wof:placetype":"venue"
},
  "geometry": {"coordinates":[-2.5081369877,43.1871452332],"type":"Point"}
}