{
  "type": "Feature",
  "properties": {
    "iso:country":"ES",
    "sg:address":"Avda America, 23",
    "sg:city":"Ponferrada",
    "sg:orig_category":"Equipo De Refrigeraci\u00d3n Industrial",
    "sg:phone":"+34 987 42 50 70",
    "sg:postcode":"24400",
    "sg:province":"Le\u00f3n",
    "sg:website":"www.friger.es",
    "wof:name":"Mercantil Espa\u00d1ola De Refrigeracion S.l.",
    "wof:placetype":"venue"
},
  "geometry": {"coordinates":[-6.5904841423,42.5483169556],"type":"Point"}
}