{
  "type": "Feature",
  "properties": {
    "iso:country":"ES",
    "sg:address":"Carrer de Aribau, 168",
    "sg:city":"Barcelona",
    "sg:orig_category":"Financiaci\u00d3n Y Cr\u00c9ditos",
    "sg:phone":"+34 902 40 50 51",
    "sg:postcode":"08036",
    "sg:province":"Barcelona",
    "wof:name":"Area Financiera Torres Fuixet S.l.",
    "wof:placetype":"venue"
},
  "geometry": {"coordinates":[2.1535692215,41.3927764893],"type":"Point"}
}