{
  "type": "Feature",
  "properties": {
    "addr:full":"Calle de Mayor, 53 Castellon Castell\u00f3n 12001",
    "addr:housenumber":"53",
    "addr:postcode":"12001",
    "addr:street":"Calle De Mayor",
    "iso:country":"ES",
    "sg:address":"Calle de Mayor, 53",
    "sg:city":"Castellon",
    "sg:orig_category":"Ropa De Casa (fabricaci\u00d3n, Al Por Mayor)",
    "sg:phone":"+34 964 22 39 53",
    "sg:postcode":"12001",
    "sg:province":"Castell\u00f3n",
    "sg:website":"www.textura-interiors.com",
    "wof:name":"Textil Textura S.l.",
    "wof:placetype":"venue"
},
  "geometry": {"coordinates":[-0.0390900001,39.9866714478],"type":"Point"}
}