{
  "type": "Feature",
  "properties": {
    "iso:country":"ES",
    "sg:address":"Calle de Arbe, 3",
    "sg:city":"Biku\u00e7a",
    "sg:orig_category":"Equitaci\u00d3n Y Centros De H\u00cdpica",
    "sg:phone":"+34 945 31 22 89",
    "sg:postcode":"01260",
    "sg:province":"\u00c1lava",
    "wof:name":"Soto Hernandez Carmen",
    "wof:placetype":"venue"
},
  "geometry": {"coordinates":[-2.3072710037,42.8752784729],"type":"Point"}
}