{
  "type": "Feature",
  "properties": {
    "iso:country":"ES",
    "sg:address":"Calle de Curtidurias, 12",
    "sg:city":"Sevilla",
    "sg:orig_category":"Cristaler\u00cdas",
    "sg:phone":"+34 954 38 64 09",
    "sg:postcode":"41002",
    "sg:province":"Sevilla",
    "wof:name":"Laguens Jimenez S. C.",
    "wof:placetype":"venue"
},
  "geometry": {"coordinates":[-5.9999742508,37.3983268738],"type":"Point"}
}