{
  "type": "Feature",
  "properties": {
    "addr:full":"Rond General Mitre, 160 Barcelona Barcelona 08006",
    "addr:housenumber":"160",
    "addr:postcode":"08006",
    "addr:street":"Mitre",
    "iso:country":"ES",
    "sg:address":"Rond General Mitre, 160",
    "sg:city":"Barcelona",
    "sg:orig_category":"Estancos",
    "sg:phone":"+34 934 17 34 21",
    "sg:postcode":"08006",
    "sg:province":"Barcelona",
    "wof:name":"Ferre Margalef Juan",
    "wof:placetype":"venue"
},
  "geometry": {"coordinates":[2.1401751041,41.4040374756],"type":"Point"}
}