{
  "type": "Feature",
  "properties": {
    "iso:country":"ES",
    "sg:address":"Calle de Alcalde Sainz De Baranda, 18",
    "sg:city":"Madrid",
    "sg:orig_category":"Frutas, Legumbres Frescas Y Tempranas (al Por Menor)",
    "sg:phone":"+34 915 73 60 68",
    "sg:postcode":"28009",
    "sg:province":"Madrid",
    "wof:name":"Autoservicios De La Fruta S.r.l.",
    "wof:placetype":"venue"
},
  "geometry": {"coordinates":[-3.6762676239,40.416847229],"type":"Point"}
}