{
  "type": "Feature",
  "properties": {
    "addr:full":"Calle de Hermanos Lopez Dieguez, 15 Cordoba C\u00f3rdoba 14001",
    "addr:housenumber":"15",
    "addr:postcode":"14001",
    "addr:street":"Calle De Hermanos Lopez Dieguez;Co\u0301Rdoba",
    "iso:country":"ES",
    "sg:address":"Calle de Hermanos Lopez Dieguez, 15",
    "sg:city":"Cordoba",
    "sg:orig_category":"Asesor\u00cda Sobre Comunicaci\u00d3n De Empresas",
    "sg:phone":"+34 957 45 00 80",
    "sg:postcode":"14001",
    "sg:province":"C\u00f3rdoba",
    "wof:name":"Eurocontrol S.a.",
    "wof:placetype":"venue"
},
  "geometry": {"coordinates":[-4.7734718323,37.8872184753],"type":"Point"}
}