{
  "type": "Feature",
  "properties": {
    "addr:full":"Avda Rafael Puig Llivina, S/n Playa Americas Santa Cruz De Tenerife 38660",
    "addr:housenumber":"s / n",
    "addr:postcode":"38660",
    "addr:street":"Avda Rafael Puig Llivina;Americas",
    "iso:country":"ES",
    "sg:address":"Avda Rafael Puig Llivina, S/n",
    "sg:city":"Playa Americas",
    "sg:orig_category":"Agencias De Viajes",
    "sg:phone":"+34 922 75 04 22",
    "sg:postcode":"38660",
    "sg:province":"Santa Cruz De Tenerife",
    "sg:website":"www.viajesposeidon.com",
    "wof:name":"Poseidon Travel Group S.l.",
    "wof:placetype":"venue"
},
  "geometry": {"coordinates":[-16.7317714691,28.0760765076],"type":"Point"}
}