{
  "type": "Feature",
  "properties": {
    "addr:full":"Carrer de Garraf, 33 Vendrell Tarragona 43700",
    "addr:housenumber":"33",
    "addr:postcode":"43700",
    "addr:street":"Carrer De Garraf",
    "iso:country":"ES",
    "sg:address":"Carrer de Garraf, 33",
    "sg:city":"Vendrell",
    "sg:orig_category":"Promotores Constructores",
    "sg:phone":"+34 977 18 19 20",
    "sg:postcode":"43700",
    "sg:province":"Tarragona",
    "wof:name":"Teruel Rosario Sergio",
    "wof:placetype":"venue"
},
  "geometry": {"coordinates":[1.5250879526,41.2208023071],"type":"Point"}
}