{
  "type": "Feature",
  "properties": {
    "iso:country":"ES",
    "sg:address":"Los Tomillares, S/n",
    "sg:city":"Ventas Huelma",
    "sg:orig_category":"Aceites Y Grasas Alimentarias (fabricaci\u00d3n, Al Por Mayor)",
    "sg:phone":"+34 958 58 80 18",
    "sg:postcode":"18131",
    "sg:province":"Granada",
    "wof:name":"Venchipa S.l.",
    "wof:placetype":"venue"
},
  "geometry": {"coordinates":[-3.817209959,37.0675506592],"type":"Point"}
}