{
  "type": "Feature",
  "properties": {
    "iso:country":"ES",
    "sg:address":"Ptge Sant Ramon, 8",
    "sg:city":"S. Celoni",
    "sg:orig_category":"M\u00c9dicos: Dermatolog\u00cda Y Venereolog\u00cda",
    "sg:phone":"+34 938 67 52 89",
    "sg:postcode":"08470",
    "sg:province":"Barcelona",
    "wof:name":"Oliveras Fradera Francesc",
    "wof:placetype":"venue"
},
  "geometry": {"coordinates":[2.4918448925,41.6894607544],"type":"Point"}
}