{
  "type": "Feature",
  "properties": {
    "iso:country":"ES",
    "sg:address":"Carr Major, 49",
    "sg:city":"Seu D'urgell",
    "sg:orig_category":"Ropa Para Se\u00d1oras (al Por Menor)",
    "sg:phone":"+34 973 35 52 27",
    "sg:postcode":"25700",
    "sg:province":"Lleida",
    "wof:name":"Marti Segarra Carles",
    "wof:placetype":"venue"
},
  "geometry": {"coordinates":[0.6243119836,41.6130256653],"type":"Point"}
}