{
  "type": "Feature",
  "properties": {
    "iso:country":"ES",
    "sg:address":"Calle de Fortuny, 21",
    "sg:city":"Alacant",
    "sg:orig_category":"M\u00c1rmoles, Granitos Y Piedras Naturales",
    "sg:phone":"+34 965 17 18 20",
    "sg:postcode":"03009",
    "sg:province":"Alicante",
    "wof:name":"Marmoles Y Granitos Enrique S.l.",
    "wof:placetype":"venue"
},
  "geometry": {"coordinates":[-0.5031290054,38.3748817444],"type":"Point"}
}