{
  "type": "Feature",
  "properties": {
    "addr:full":"Ctra Villaverde, Km. 0000,8 Pedrajas S. Esteban Valladolid 47430",
    "addr:postcode":"47430",
    "addr:street":"Ctra Villaverde Km. 0000,8 Pedrajas S. Esteban Valladolid",
    "iso:country":"ES",
    "sg:address":"Ctra Villaverde, Km. 0000,8",
    "sg:city":"Pedrajas S. Esteban",
    "sg:orig_category":"Empresas De Carpinter\u00cda De Madera",
    "sg:phone":"+34 983 62 58 96",
    "sg:postcode":"47430",
    "sg:province":"Valladolid",
    "wof:name":"Hijos De Julio Fraile S.l.",
    "wof:placetype":"venue"
},
  "geometry": {"coordinates":[-4.5724196434,41.3396644592],"type":"Point"}
}