{
  "type": "Feature",
  "properties": {
    "iso:country":"ES",
    "sg:address":"Carrer de Anselm Clave, 15",
    "sg:city":"S. Feliu Guixols",
    "sg:orig_category":"Centros Comerciales Y Grandes Tiendas",
    "sg:phone":"+34 972 32 04 00",
    "sg:postcode":"17220",
    "sg:province":"Girona",
    "wof:name":"Catoon's Studios S.l.",
    "wof:placetype":"venue"
},
  "geometry": {"coordinates":[3.0294280052,41.7812194824],"type":"Point"}
}