{
  "type": "Feature",
  "properties": {
    "addr:full":"Carr D'hernan Cortes, 43 Benicarlo Castell\u00f3n 12580",
    "addr:housenumber":"43",
    "addr:postcode":"12580",
    "addr:street":"Carr D'Hernan Cortes",
    "iso:country":"ES",
    "sg:address":"Carr D'hernan Cortes, 43",
    "sg:city":"Benicarlo",
    "sg:orig_category":"Formaci\u00d3n Continuada (variada)",
    "sg:phone":"+34 964 46 12 00",
    "sg:postcode":"12580",
    "sg:province":"Castell\u00f3n",
    "wof:name":"Marza Consultores S.l.",
    "wof:placetype":"venue"
},
  "geometry": {"coordinates":[0.4277229905,40.4163665771],"type":"Point"}
}