{
  "type": "Feature",
  "properties": {
    "iso:country":"ES",
    "sg:address":"Calle de B Franklin, S/n",
    "sg:city":"Chorrillo",
    "sg:orig_category":"Bordado, Marcado A Medida",
    "sg:phone":"+34 922 61 86 03",
    "sg:postcode":"38108",
    "sg:province":"Santa Cruz De Tenerife",
    "wof:name":"Artesania Celsa S.a.",
    "wof:placetype":"venue"
},
  "geometry": {"coordinates":[-16.3177928925,28.4123001099],"type":"Point"}
}