{
  "type": "Feature",
  "properties": {
    "addr:full":"G.v. Lopez De Haro D. Diego, 58 Bilbao Vizcaya 48011",
    "addr:housenumber":"58",
    "addr:postcode":"48011",
    "addr:street":"Lopez De Haro D. Diego",
    "iso:country":"ES",
    "sg:address":"G.v. Lopez De Haro D. Diego, 58",
    "sg:city":"Bilbao",
    "sg:orig_category":"Inmobiliaria (agencias)",
    "sg:phone":"+34 944 42 20 58",
    "sg:postcode":"48011",
    "sg:province":"Vizcaya",
    "wof:name":"Ortuondo Muguruza Antonio",
    "wof:placetype":"venue"
},
  "geometry": {"coordinates":[-2.9394829273,43.2641334534],"type":"Point"}
}