{
  "type": "Feature",
  "properties": {
    "addr:full":"Carrer de Barcelona (de), 56 Salou Tarragona 43840",
    "addr:housenumber":"56",
    "addr:postcode":"43840",
    "addr:street":"Carrer De Barcelona De",
    "iso:country":"ES",
    "sg:address":"Carrer de Barcelona (de), 56",
    "sg:city":"Salou",
    "sg:orig_category":"Cajas De Ahorro",
    "sg:phone":"+34 977 38 50 21",
    "sg:postcode":"43840",
    "sg:province":"Tarragona",
    "wof:name":"Caixa D'estalvis De Manresa",
    "wof:placetype":"venue"
},
  "geometry": {"coordinates":[1.1316000223,41.0817565918],"type":"Point"}
}