{
  "type": "Feature",
  "properties": {
    "iso:country":"ES",
    "sg:address":"Carretera Monfero, S/n",
    "sg:city":"Pontedeume",
    "sg:orig_category":"Edici\u00d3n De Diarios, Revistas, Boletines",
    "sg:phone":"+34 981 45 40 00",
    "sg:postcode":"15600",
    "sg:province":"La Coru\u00f1a",
    "sg:website":"www.einsamultimedia.com",
    "wof:name":"Einsa Multimedia S.a.",
    "wof:placetype":"venue"
},
  "geometry": {"coordinates":[-8.1642742157,43.4046707153],"type":"Point"}
}