{
  "type": "Feature",
  "properties": {
    "iso:country":"ES",
    "sg:address":"Sanguesa, 4",
    "sg:city":"Iru\u00f1a",
    "sg:orig_category":"Ingeniero",
    "sg:phone":"+34 948 29 06 73",
    "sg:postcode":"31003",
    "sg:province":"Navarra",
    "sg:website":"www.grupojg.com",
    "wof:name":"Inco Ingenieros Consultores S.l.",
    "wof:placetype":"venue"
},
  "geometry": {"coordinates":[-1.6422249079,42.8121833801],"type":"Point"}
}