{
  "type": "Feature",
  "properties": {
    "iso:country":"ES",
    "sg:address":"Rua Galeras (das), 16",
    "sg:city":"Santiago De Compostela",
    "sg:orig_category":"Caf\u00c9s, Bares, Cervecer\u00cdas",
    "sg:phone":"+34 981 58 16 38",
    "sg:postcode":"15705",
    "sg:province":"La Coru\u00f1a",
    "wof:name":"Mosquera Gomez Jesus",
    "wof:placetype":"venue"
},
  "geometry": {"coordinates":[-8.5490894318,42.8811302185],"type":"Point"}
}