{
  "type": "Feature",
  "properties": {
    "iso:country":"ES",
    "sg:address":"Carrer de Pere Badia (de), 30",
    "sg:city":"Torredembarra",
    "sg:orig_category":"Agentes, Concesionarios Y Sucursales De Veh\u00cdculos",
    "sg:phone":"+34 977 64 00 28",
    "sg:postcode":"43830",
    "sg:province":"Tarragona",
    "wof:name":"Torven S.a.",
    "wof:placetype":"venue"
},
  "geometry": {"coordinates":[1.4039200544,41.1444511414],"type":"Point"}
}