{
  "type": "Feature",
  "properties": {
    "addr:full":"Rond Trinidad (la), 2 Moron Frontera Sevilla 41530",
    "addr:housenumber":"2",
    "addr:postcode":"41530",
    "addr:street":"Rond Trinidad La",
    "iso:country":"ES",
    "sg:address":"Rond Trinidad (la), 2",
    "sg:city":"Moron Frontera",
    "sg:orig_category":"Mec\u00c1nico Del Autom\u00d3vil",
    "sg:phone":"+34 955 85 26 77",
    "sg:postcode":"41530",
    "sg:province":"Sevilla",
    "wof:name":"Hurtado Rodriguez Manuel",
    "wof:placetype":"venue"
},
  "geometry": {"coordinates":[-5.4528231621,37.1294212341],"type":"Point"}
}