{
  "type": "Feature",
  "properties": {
    "addr:full":"Calle de Legazpi, 4 Donostia-san Sebastian Guip\u00f9zcoa 20004",
    "addr:housenumber":"4",
    "addr:postcode":"20004",
    "addr:street":"Calle De Legazpi",
    "iso:country":"ES",
    "sg:address":"Calle de Legazpi, 4",
    "sg:city":"Donostia-san Sebastian",
    "sg:orig_category":"Institutos De Belleza",
    "sg:phone":"+34 943 42 42 93",
    "sg:postcode":"20004",
    "sg:province":"Guip\u00f9zcoa",
    "wof:name":"Ortiz Marcos Susana",
    "wof:placetype":"venue"
},
  "geometry": {"coordinates":[-1.9826270342,43.3221626282],"type":"Point"}
}