{
  "type": "Feature",
  "properties": {
    "iso:country":"ES",
    "sg:address":"Calle de Robledo, 39",
    "sg:city":"Pola De Lena",
    "sg:orig_category":"Molduras, Junquillos, Listones Y Molduras Perforadas",
    "sg:phone":"+34 985 49 33 17",
    "sg:postcode":"33630",
    "sg:province":"Asturias",
    "wof:name":"Fernandez Alvarez Marta Isabel",
    "wof:placetype":"venue"
},
  "geometry": {"coordinates":[-5.8264298439,43.1504402161],"type":"Point"}
}