{
  "type": "Feature",
  "properties": {
    "iso:country":"ES",
    "sg:address":"Calle de Puerto De Pajares, 23",
    "sg:city":"Prado Overa",
    "sg:classifiers":[
        {
            "category":"Wholesale",
            "subcategory":"Construction Materials",
            "type":"Manufacturing & Wholesale Goods"
        }
    ],
    "sg:phone":"+34 913 41 91 19",
    "sg:postcode":"28919",
    "sg:province":"Madrid",
    "sg:tags":[
        "de",
        "embotellado"
    ],
    "sg:website":"www.cervetecnica.com",
    "wof:name":"Cervetecnica S.l.",
    "wof:placetype":"venue"
},
  "geometry": {"coordinates":[-3.7468049526,40.3435096741],"type":"Point"}
}