{
  "type": "Feature",
  "properties": {
    "addr:full":"Rua Galicia, 29 Guarda Pontevedra 36780",
    "addr:housenumber":"29",
    "addr:postcode":"36780",
    "addr:street":"Rua Galicia",
    "iso:country":"ES",
    "sg:address":"Rua Galicia, 29",
    "sg:city":"Guarda",
    "sg:orig_category":"Inmobiliaria (agencias)",
    "sg:phone":"+34 986 60 90 48",
    "sg:postcode":"36780",
    "sg:province":"Pontevedra",
    "wof:name":"Martinez Rodriguez Felicita",
    "wof:placetype":"venue"
},
  "geometry": {"coordinates":[-8.8719043732,41.9026679993],"type":"Point"}
}