{
  "type": "Feature",
  "properties": {
    "iso:country":"ES",
    "sg:address":"Calle de Domiciano Olivares, 1",
    "sg:city":"Estacion Linares-baeza",
    "sg:orig_category":"Electrodom\u00c9sticos (al Por Menor)",
    "sg:phone":"+34 953 69 12 45",
    "sg:postcode":"23490",
    "sg:province":"Ja\u00e9n",
    "wof:name":"Ruiz Muelas Juan Francisco",
    "wof:placetype":"venue"
},
  "geometry": {"coordinates":[-3.5905356407,38.0695075989],"type":"Point"}
}