{
  "type": "Feature",
  "properties": {
    "addr:full":"Carrer de Sant Maties, 130 Sabadell Barcelona 08208",
    "addr:housenumber":"130",
    "addr:postcode":"08208",
    "addr:street":"Carrer De Sant Maties",
    "iso:country":"ES",
    "sg:address":"Carrer de Sant Maties, 130",
    "sg:city":"Sabadell",
    "sg:orig_category":"Doctores En Medicina",
    "sg:phone":"+34 937 16 34 20",
    "sg:postcode":"08208",
    "sg:province":"Barcelona",
    "wof:name":"Ze\u00f1a Castillo Patricia",
    "wof:placetype":"venue"
},
  "geometry": {"coordinates":[2.10958004,41.5562667847],"type":"Point"}
}