{
  "type": "Feature",
  "properties": {
    "addr:full":"Calle de Carrera De Jesus, 49 Jaen Ja\u00e9n 23002",
    "addr:housenumber":"49;jae\u0301n",
    "addr:postcode":"23002",
    "addr:street":"Calle De Carrera De Jesus",
    "iso:country":"ES",
    "sg:address":"Calle de Carrera De Jesus, 49",
    "sg:city":"Jaen",
    "sg:orig_category":"Explotaci\u00d3n De Aparcamientos",
    "sg:phone":"+34 953 23 10 05",
    "sg:postcode":"23002",
    "sg:province":"Ja\u00e9n",
    "wof:name":"Madera Caballero Francisco",
    "wof:placetype":"venue"
},
  "geometry": {"coordinates":[-3.7940816879,37.7630081177],"type":"Point"}
}