{
  "type": "Feature",
  "properties": {
    "addr:full":"Calle de Cervantes, 31 Pozoblanco C\u00f3rdoba 14400",
    "addr:housenumber":"31",
    "addr:postcode":"14400",
    "addr:street":"Calle De Cervantes",
    "iso:country":"ES",
    "sg:address":"Calle de Cervantes, 31",
    "sg:city":"Pozoblanco",
    "sg:orig_category":"Cr\u00cda De Animales",
    "sg:phone":"+34 957 77 01 26",
    "sg:postcode":"14400",
    "sg:province":"C\u00f3rdoba",
    "wof:name":"Francisco Aguado Serrano E Hijos S.c.p.",
    "wof:placetype":"venue"
},
  "geometry": {"coordinates":[-4.8530583382,38.3792915344],"type":"Point"}
}