{
  "type": "Feature",
  "properties": {
    "iso:country":"ES",
    "sg:address":"Plaz Rabasa, 7",
    "sg:city":"Madrid",
    "sg:orig_category":"Molduras, Junquillos, Listones Y Molduras Perforadas",
    "sg:phone":"+34 917 05 54 71",
    "sg:postcode":"28044",
    "sg:province":"Madrid",
    "wof:name":"Gomez De Barreda Antonio",
    "wof:placetype":"venue"
},
  "geometry": {"coordinates":[-3.7652769089,40.3754005432],"type":"Point"}
}