{
  "type": "Feature",
  "properties": {
    "iso:country":"ES",
    "sg:address":"El Santo, 7",
    "sg:city":"Saelices",
    "sg:orig_category":"Mec\u00c1nico Del Autom\u00d3vil",
    "sg:phone":"+34 969 13 20 29",
    "sg:postcode":"16430",
    "sg:province":"Cuenca",
    "wof:name":"Batanero Martinez Pedro",
    "wof:placetype":"venue"
},
  "geometry": {"coordinates":[-2.8031320572,39.919670105],"type":"Point"}
}