{
  "type": "Feature",
  "properties": {
    "iso:country":"ES",
    "sg:address":"Calle de Caballeros, 21",
    "sg:city":"Sanlucar De Barrameda",
    "sg:orig_category":"Empresarios",
    "sg:phone":"+34 956 36 17 55",
    "sg:postcode":"11540",
    "sg:province":"C\u00e1diz",
    "wof:name":"Grado Antunez Jose",
    "wof:placetype":"venue"
},
  "geometry": {"coordinates":[-6.3551101685,36.7753829956],"type":"Point"}
}