{
  "type": "Feature",
  "properties": {
    "addr:full":"Golf Del Sur, S/n Golf Sur Santa Cruz De Tenerife 38639",
    "addr:housenumber":"s / n",
    "addr:postcode":"38639",
    "addr:street":"Golf Sur",
    "iso:country":"ES",
    "sg:address":"Golf Del Sur, S/n",
    "sg:city":"Golf Sur",
    "sg:orig_category":"Agentes, Concesionarios Y Sucursales De Veh\u00cdculos",
    "sg:phone":"+34 922 73 80 60",
    "sg:postcode":"38639",
    "sg:province":"Santa Cruz De Tenerife",
    "sg:website":"www.nicasars.com",
    "wof:name":"Vallecid S.a.",
    "wof:placetype":"venue"
},
  "geometry": {"coordinates":[-16.6115474701,28.0350246429],"type":"Point"}
}