{
  "type": "Feature",
  "properties": {
    "addr:full":"Pol Ind Fadrell, 75 Castello Plana Castell\u00f3n 12005",
    "addr:housenumber":"75",
    "addr:postcode":"12005",
    "addr:street":"Fadrell;Castello\u0301N",
    "iso:country":"ES",
    "sg:address":"Pol Ind Fadrell, 75",
    "sg:city":"Castello Plana",
    "sg:orig_category":"Artes Gr\u00c1ficas, Artes Pl\u00c1sticas (curso)",
    "sg:phone":"+34 964 24 52 91",
    "sg:postcode":"12005",
    "sg:province":"Castell\u00f3n",
    "wof:name":"Grafiques Color Impres S.l.u..",
    "wof:placetype":"venue"
},
  "geometry": {"coordinates":[-0.0360242017,39.9860687256],"type":"Point"}
}