{
  "type": "Feature",
  "properties": {
    "addr:full":"Calle de Covadonga, 21 Mieres Asturias 33600",
    "addr:housenumber":"21",
    "addr:postcode":"33600",
    "addr:street":"Calle De Covadonga",
    "iso:country":"ES",
    "sg:address":"Calle de Covadonga, 21",
    "sg:city":"Mieres",
    "sg:orig_category":"Cervecer\u00cdas",
    "sg:phone":"+34 985 46 62 78",
    "sg:postcode":"33600",
    "sg:province":"Asturias",
    "wof:name":"Sociedad Regional De Informatica S. A.",
    "wof:placetype":"venue"
},
  "geometry": {"coordinates":[-5.7739677429,43.246887207],"type":"Point"}
}