{
  "type": "Feature",
  "properties": {
    "addr:full":"Caoli, S/n Burriana Castell\u00f3n 12530",
    "addr:postcode":"12530",
    "addr:street":"Caoli S / N;Castello\u0301N",
    "iso:country":"ES",
    "sg:address":"Caoli, S/n",
    "sg:city":"Burriana",
    "sg:orig_category":"Molduras, Junquillos, Listones Y Molduras Perforadas",
    "sg:phone":"+34 964 51 20 71",
    "sg:postcode":"12530",
    "sg:province":"Castell\u00f3n",
    "wof:name":"Nova Hosteleria Azahar S.l.",
    "wof:placetype":"venue"
},
  "geometry": {"coordinates":[-0.0994789973,39.8809013367],"type":"Point"}
}