{
  "type": "Feature",
  "properties": {
    "addr:full":"Calle de Portugalete (de), 8 Pozuelo De Alarcon Madrid 28223",
    "addr:housenumber":"8",
    "addr:postcode":"28223",
    "addr:street":"Calle De Portugalete De",
    "iso:country":"ES",
    "sg:address":"Calle de Portugalete (de), 8",
    "sg:city":"Pozuelo De Alarcon",
    "sg:orig_category":"Guarder\u00cdas",
    "sg:phone":"+34 913 52 71 29",
    "sg:postcode":"28223",
    "sg:province":"Madrid",
    "wof:name":"Blanco Callejas Alicia",
    "wof:placetype":"venue"
},
  "geometry": {"coordinates":[-3.8115639687,40.4375991821],"type":"Point"}
}