{
  "type": "Feature",
  "properties": {
    "addr:full":"Avda Primado Reig, 19 Valencia Valencia 46019",
    "addr:housenumber":"19",
    "addr:postcode":"46019",
    "addr:street":"Avda Primado Reig",
    "iso:country":"ES",
    "sg:address":"Avda Primado Reig, 19",
    "sg:city":"Valencia",
    "sg:orig_category":"Enfermeras: Consultas, Atenci\u00d3n A Domicilio",
    "sg:phone":"+34 963 65 80 29",
    "sg:postcode":"46019",
    "sg:province":"Valencia",
    "wof:name":"Donato Aznar Enrique",
    "wof:placetype":"venue"
},
  "geometry": {"coordinates":[-0.3724089861,39.4912796021],"type":"Point"}
}