{
  "type": "Feature",
  "properties": {
    "iso:country":"ES",
    "sg:address":"Av Ports D'europa, 52",
    "sg:city":"Barcelona",
    "sg:orig_category":"Organizaciones Profesionales",
    "sg:phone":"+34 932 98 30 00",
    "sg:postcode":"08...",
    "sg:province":"Barcelona",
    "sg:website":"www.lotrans.es",
    "wof:name":"Lotrans Logistica Y Transporte S.a.",
    "wof:placetype":"venue"
},
  "geometry": {"coordinates":[2.1429057121,41.3219146729],"type":"Point"}
}