{
  "type": "Feature",
  "properties": {
    "addr:full":"Calle de Jardin De Santa Eufemia, 60 Tomares Sevilla 41940",
    "addr:housenumber":"60",
    "addr:postcode":"41940",
    "addr:street":"Calle De Jardin De Santa Eufemia",
    "iso:country":"ES",
    "sg:address":"Calle de Jardin De Santa Eufemia, 60",
    "sg:city":"Tomares",
    "sg:orig_category":"Asesor\u00cda De Formaci\u00d3n Y Gesti\u00d3n De Personal",
    "sg:phone":"+34 954 15 64 65",
    "sg:postcode":"41940",
    "sg:province":"Sevilla",
    "wof:name":"Atecsan S.l.",
    "wof:placetype":"venue"
},
  "geometry": {"coordinates":[-6.0445585251,37.3800811768],"type":"Point"}
}