{
  "type": "Feature",
  "properties": {
    "iso:country":"ES",
    "sg:address":"Calle de Jardines, 1",
    "sg:city":"Salas De Los Infantes",
    "sg:orig_category":"Talleres: Ropa A Medida",
    "sg:phone":"+34 947 38 02 35",
    "sg:postcode":"09600",
    "sg:province":"Burgos",
    "wof:name":"Cabrito Camarero Alfredo Tomas",
    "wof:placetype":"venue"
},
  "geometry": {"coordinates":[-3.2864089012,42.0221328735],"type":"Point"}
}