{
  "type": "Feature",
  "properties": {
    "iso:country":"ES",
    "sg:address":"Carrer de Antoni Roig (d'), 72",
    "sg:city":"Torredembarra",
    "sg:orig_category":"Ropa Para Se\u00d1oras (al Por Menor)",
    "sg:phone":"+34 977 64 39 36",
    "sg:postcode":"43830",
    "sg:province":"Tarragona",
    "wof:name":"Coronado  Miguel Angel",
    "wof:placetype":"venue"
},
  "geometry": {"coordinates":[1.400053978,41.1443786621],"type":"Point"}
}