{
  "type": "Feature",
  "properties": {
    "addr:full":"Plaz Jose Maria Orense, 10 Valencia Valencia 46022",
    "addr:housenumber":"10",
    "addr:postcode":"46022",
    "addr:street":"Maria Orense",
    "iso:country":"ES",
    "sg:address":"Plaz Jose Maria Orense, 10",
    "sg:city":"Valencia",
    "sg:orig_category":"Arquitectos",
    "sg:phone":"+34 963 55 30 92",
    "sg:postcode":"46022",
    "sg:province":"Valencia",
    "wof:name":"202 Enternet S.l.",
    "wof:placetype":"venue"
},
  "geometry": {"coordinates":[-0.341893,39.470413],"type":"Point"}
}