{
  "type": "Feature",
  "properties": {
    "addr:full":"Avda Doctor Martinez Pardo - Teixeiro, 39 Teijeiro La Coru\u00f1a 15310",
    "addr:housenumber":"39",
    "addr:postcode":"15310",
    "addr:street":"Avda Doctor Martinez Pardo Teixeiro;La Corun\u0303A",
    "iso:country":"ES",
    "sg:address":"Avda Doctor Martinez Pardo - Teixeiro, 39",
    "sg:city":"Teijeiro",
    "sg:orig_category":"Talleres: Ropa A Medida",
    "sg:phone":"+34 981 78 90 62",
    "sg:postcode":"15310",
    "sg:province":"La Coru\u00f1a",
    "wof:name":"Diaz Sanchez Enrique",
    "wof:placetype":"venue"
},
  "geometry": {"coordinates":[-8.1450586319,43.1260108948],"type":"Point"}
}