{
  "type": "Feature",
  "properties": {
    "addr:full":"Calle de Caballero De Rodas, 211 Torrevieja Alicante 03180",
    "addr:housenumber":"211",
    "addr:postcode":"03180",
    "addr:street":"Calle De Caballero De Rodas",
    "iso:country":"ES",
    "sg:address":"Calle de Caballero De Rodas, 211",
    "sg:city":"Torrevieja",
    "sg:orig_category":"Molduras, Junquillos, Listones Y Molduras Perforadas",
    "sg:phone":"+34 965 70 32 39",
    "sg:postcode":"03180",
    "sg:province":"Alicante",
    "wof:name":"Ayc Vime S.l.",
    "wof:placetype":"venue"
},
  "geometry": {"coordinates":[-0.6775231957,37.9780731201],"type":"Point"}
}