{
  "type": "Feature",
  "properties": {
    "iso:country":"ES",
    "sg:address":"Plaz Espa\u00d1a, 1",
    "sg:city":"Almedinilla",
    "sg:orig_category":"Administraciones Regionales, Departamentales Y Locales",
    "sg:phone":"+34 957 70 30 85",
    "sg:postcode":"14812",
    "sg:province":"C\u00f3rdoba",
    "wof:name":"Ayuntamiento De Almedinilla",
    "wof:placetype":"venue"
},
  "geometry": {"coordinates":[-4.0912837982,37.4391403198],"type":"Point"}
}