{
  "type": "Feature",
  "properties": {
    "addr:full":"Cmno Ibarsusibidea, S/n Bilbao Vizcaya 48004",
    "addr:housenumber":"s / n",
    "addr:postcode":"48004",
    "addr:street":"Cmno Ibarsusibidea",
    "iso:country":"ES",
    "sg:address":"Cmno Ibarsusibidea, S/n",
    "sg:city":"Bilbao",
    "sg:orig_category":"Marketing Directo",
    "sg:phone":"+34 944 11 14 50",
    "sg:postcode":"48004",
    "sg:province":"Vizcaya",
    "wof:name":"Agencia De Marketing Integral Consulting Sl",
    "wof:placetype":"venue"
},
  "geometry": {"coordinates":[-2.900121212,43.2565917969],"type":"Point"}
}