{
  "type": "Feature",
  "properties": {
    "iso:country":"ES",
    "sg:address":"Alde Salgueiras, S/n",
    "sg:city":"Caridad",
    "sg:orig_category":"Negocio De Materiales De Construcci\u00d3n",
    "sg:phone":"+34 985 63 71 27",
    "sg:postcode":"33750",
    "sg:province":"Asturias",
    "wof:name":"Materiales De Construccion Salgueiras Sl",
    "wof:placetype":"venue"
},
  "geometry": {"coordinates":[-6.8270339966,43.5506744385],"type":"Point"}
}