{
  "type": "Feature",
  "properties": {
    "iso:country":"ES",
    "sg:address":"Calle de Gerald Brenan, 84",
    "sg:city":"Malaga",
    "sg:orig_category":"Agentes, Concesionarios Y Sucursales De Camiones Y Veh\u00cdculos Industriales",
    "sg:phone":"+34 952 23 99 37",
    "sg:postcode":"29005",
    "sg:province":"M\u00e1laga",
    "wof:name":"Camimalaga S.a.",
    "wof:placetype":"venue"
},
  "geometry": {"coordinates":[-4.479777813,36.6922340393],"type":"Point"}
}