{
  "type": "Feature",
  "properties": {
    "iso:country":"ES",
    "sg:address":"Avda Jose Mesa Y Lopez, 86",
    "sg:city":"Palmas De Gran Canaria",
    "sg:orig_category":"Compraventa De Antig\u00dcedades",
    "sg:phone":"+34 928 49 12 55",
    "sg:postcode":"35010",
    "sg:province":"Las Palmas",
    "wof:name":"Garcia Ramirez Antonia",
    "wof:placetype":"venue"
},
  "geometry": {"coordinates":[-15.4376249313,28.1326618195],"type":"Point"}
}