{
  "type": "Feature",
  "properties": {
    "addr:full":"Calle de San Jose, 7 Valladolid Valladolid 47007",
    "addr:housenumber":"7",
    "addr:postcode":"47007",
    "addr:street":"Calle De San Jose",
    "iso:country":"ES",
    "sg:address":"Calle de San Jose, 7",
    "sg:city":"Valladolid",
    "sg:orig_category":"Teatros Y Salas De Espect\u00c1culos",
    "sg:phone":"+34 983 22 21 27",
    "sg:postcode":"47007",
    "sg:province":"Valladolid",
    "wof:name":"El Templo Romano S.l.",
    "wof:placetype":"venue"
},
  "geometry": {"coordinates":[-4.7326631546,41.6418571472],"type":"Point"}
}