{
  "type": "Feature",
  "properties": {
    "iso:country":"ES",
    "sg:address":"Rua Luis Cadarso, 55",
    "sg:city":"Noia",
    "sg:orig_category":"Peluquer\u00cdas, Peluquer\u00cda Mixta",
    "sg:phone":"+34 981 82 52 10",
    "sg:postcode":"15200",
    "sg:province":"La Coru\u00f1a",
    "wof:name":"Barbanz-hair S.c.",
    "wof:placetype":"venue"
},
  "geometry": {"coordinates":[-8.8847875595,42.7849273682],"type":"Point"}
}