{
  "type": "Feature",
  "properties": {
    "addr:full":"Plaz San Cayetano, 4 Roquetas Mar Almer\u00eda 04740",
    "addr:housenumber":"4",
    "addr:postcode":"04740",
    "addr:street":"Plaz San Cayetano",
    "iso:country":"ES",
    "sg:address":"Plaz San Cayetano, 4",
    "sg:city":"Roquetas Mar",
    "sg:orig_category":"Arquitectos",
    "sg:phone":"+34 950 32 88 16",
    "sg:postcode":"04740",
    "sg:province":"Almer\u00eda",
    "wof:name":"Rosillo Arquitectos S.l.u.",
    "wof:placetype":"venue"
},
  "geometry": {"coordinates":[-2.6124989986,36.7638435364],"type":"Point"}
}