{
  "type": "Feature",
  "properties": {
    "addr:full":"Avda Cristo Rey, 15 Ubeda Ja\u00e9n 23400",
    "addr:housenumber":"15",
    "addr:postcode":"23400",
    "addr:street":"Avda Cristo Rey;Jae\u0301N",
    "iso:country":"ES",
    "sg:address":"Avda Cristo Rey, 15",
    "sg:city":"Ubeda",
    "sg:orig_category":"Art\u00cdculos Funerarios (al Por Menor)",
    "sg:phone":"+34 953 79 30 80",
    "sg:postcode":"23400",
    "sg:province":"Ja\u00e9n",
    "wof:name":"Serrano Martinez Francisco Javier",
    "wof:placetype":"venue"
},
  "geometry": {"coordinates":[-3.3779499531,38.0115394592],"type":"Point"}
}