{
  "type": "Feature",
  "properties": {
    "addr:full":"Carrer de Igualada, 7 Vilafranca Penedes Barcelona 08720",
    "addr:housenumber":"7",
    "addr:postcode":"08720",
    "addr:street":"Carrer De Igualada;Penedes Barcelona",
    "iso:country":"ES",
    "sg:address":"Carrer de Igualada, 7",
    "sg:city":"Vilafranca Penedes",
    "sg:orig_category":"Art\u00cdculos De Decoraci\u00d3n (fabricaci\u00d3n Y Al Por Mayor)",
    "sg:phone":"+34 938 92 34 11",
    "sg:postcode":"08720",
    "sg:province":"Barcelona",
    "sg:website":"www.window-disseny.com",
    "wof:name":"Window Imatge I Disseny S.l.",
    "wof:placetype":"venue"
},
  "geometry": {"coordinates":[1.7026916742,41.3478126526],"type":"Point"}
}