{
  "type": "Feature",
  "properties": {
    "addr:full":"Calle de Padre Aller, 7 Oviedo Asturias 33012",
    "addr:housenumber":"7",
    "addr:postcode":"33012",
    "addr:street":"Calle De Padre Aller",
    "iso:country":"ES",
    "sg:address":"Calle de Padre Aller, 7",
    "sg:city":"Oviedo",
    "sg:orig_category":"Mec\u00c1nico Del Autom\u00d3vil",
    "sg:phone":"+34 985 25 11 42",
    "sg:postcode":"33012",
    "sg:province":"Asturias",
    "wof:name":"Garcia Alonso Jose Aurelio",
    "wof:placetype":"venue"
},
  "geometry": {"coordinates":[-5.8650021553,43.3686256409],"type":"Point"}
}