{
  "type": "Feature",
  "properties": {
    "addr:full":"Av Caixa D'estalvis, 2 Mora Nova Tarragona 43770",
    "addr:housenumber":"2",
    "addr:postcode":"43770",
    "addr:street":"Av Caixa D'Estalvis",
    "iso:country":"ES",
    "sg:address":"Av Caixa D'estalvis, 2",
    "sg:city":"Mora Nova",
    "sg:orig_category":"Caf\u00c9s, Bares, Cervecer\u00cdas",
    "sg:phone":"+34 977 40 05 15",
    "sg:postcode":"43770",
    "sg:province":"Tarragona",
    "wof:name":"Bar Stop C.b.",
    "wof:placetype":"venue"
},
  "geometry": {"coordinates":[1.2540999651,41.1169281006],"type":"Point"}
}