{
  "type": "Feature",
  "properties": {
    "addr:full":"Avda Badajoz, 46 San Vicente Alcantara Badajoz 06500",
    "addr:housenumber":"46",
    "addr:postcode":"06500",
    "addr:street":"Avda Badajoz",
    "iso:country":"ES",
    "sg:address":"Avda Badajoz, 46",
    "sg:city":"San Vicente Alcantara",
    "sg:orig_category":"Electricidad: Instaladores",
    "sg:phone":"+34 924 41 09 56",
    "sg:postcode":"06500",
    "sg:province":"Badajoz",
    "wof:name":"Pajero Madera Rafael",
    "wof:placetype":"venue"
},
  "geometry": {"coordinates":[-7.1372151375,39.3637466431],"type":"Point"}
}