{
  "type": "Feature",
  "properties": {
    "iso:country":"ES",
    "sg:address":"Rua Arcedianos, 13",
    "sg:city":"Ourense",
    "sg:orig_category":"Partidos Pol\u00cdticos",
    "sg:phone":"+34 988 22 29 07",
    "sg:postcode":"32005",
    "sg:province":"Ourense",
    "wof:name":"Partido Comunista De Espa\u00f1a",
    "wof:placetype":"venue"
},
  "geometry": {"coordinates":[-7.8640217781,42.336566925],"type":"Point"}
}