{
  "type": "Feature",
  "properties": {
    "addr:full":"Calle de Luis Valenzuela, 4 Cordoba C\u00f3rdoba 14007",
    "addr:housenumber":"4",
    "addr:postcode":"14007",
    "addr:street":"Calle De Luis Valenzuela;Co\u0301Rdoba",
    "iso:country":"ES",
    "sg:address":"Calle de Luis Valenzuela, 4",
    "sg:city":"Cordoba",
    "sg:orig_category":"Ense\u00d1anza Variada",
    "sg:phone":"+34 957 25 10 11",
    "sg:postcode":"14007",
    "sg:province":"C\u00f3rdoba",
    "wof:name":"Academias Roma Calderon S.l. Unipersonal",
    "wof:placetype":"venue"
},
  "geometry": {"coordinates":[-4.7609090805,37.89087677],"type":"Point"}
}