{
  "type": "Feature",
  "properties": {
    "iso:country":"ES",
    "sg:address":"Avda Juan Carlos I, 53",
    "sg:city":"Merida",
    "sg:orig_category":"Agentes, Concesionarios Y Sucursales De Veh\u00cdculos",
    "sg:phone":"+34 924 31 53 76",
    "sg:postcode":"06800",
    "sg:province":"Badajoz",
    "wof:name":"Antonio Bravo S.a.",
    "wof:placetype":"venue"
},
  "geometry": {"coordinates":[-6.3349409103,38.9199104309],"type":"Point"}
}