{
  "type": "Feature",
  "properties": {
    "iso:country":"ES",
    "sg:address":"Calle de Huerta Del Obispo, 5",
    "sg:city":"Cadiz",
    "sg:orig_category":"M\u00c9dicos: Cirug\u00cda Ortop\u00c9dica Y Traumatolog\u00cda",
    "sg:phone":"+34 956 28 47 14",
    "sg:postcode":"11008",
    "sg:province":"C\u00e1diz",
    "wof:name":"Martin Del Toro Julian Rafael",
    "wof:placetype":"venue"
},
  "geometry": {"coordinates":[-6.2817797661,36.5162086487],"type":"Point"}
}