{
  "type": "Feature",
  "properties": {
    "addr:full":"Calle de Calderon De La Barca, 12 Albacete Albacete 02002",
    "addr:housenumber":"12",
    "addr:postcode":"02002",
    "addr:street":"Calle De Calderon De La Barca",
    "iso:country":"ES",
    "sg:address":"Calle de Calderon De La Barca, 12",
    "sg:city":"Albacete",
    "sg:orig_category":"Procuradores",
    "sg:phone":"+34 967 23 97 00",
    "sg:postcode":"02002",
    "sg:province":"Albacete",
    "wof:name":"Malagon Fuertes Francisco Javier",
    "wof:placetype":"venue"
},
  "geometry": {"coordinates":[-1.8541910648,38.9888267517],"type":"Point"}
}