{
  "type": "Feature",
  "properties": {
    "addr:full":"Calle de Italia, 232 Palencia Palencia 34004",
    "addr:housenumber":"232",
    "addr:postcode":"34004",
    "addr:street":"Calle De Italia",
    "iso:country":"ES",
    "sg:address":"Calle de Italia, 232",
    "sg:city":"Palencia",
    "sg:classifiers":[
        {
            "category":"Banks & Credit Unions",
            "subcategory":"Bureau De Change",
            "type":"Services"
        }
    ],
    "sg:phone":"+34 979 71 37 01",
    "sg:postcode":"34004",
    "sg:province":"Palencia",
    "sg:tags":[
        "organismos",
        "control"
    ],
    "wof:name":"Inzamac Asistencias Tecnicas S.a.",
    "wof:placetype":"venue"
},
  "geometry": {"coordinates":[-4.5129990578,42.0043296814],"type":"Point"}
}