{
  "type": "Feature",
  "properties": {
    "iso:country":"ES",
    "sg:address":"Po Ind Petroquimico, S/n",
    "sg:city":"Palos Frontera",
    "sg:orig_category":"Montaje (empresas De)",
    "sg:phone":"+34 959 36 91 13",
    "sg:postcode":"21810",
    "sg:province":"Huelva",
    "wof:name":"Masa Huelva S.a.",
    "wof:placetype":"venue"
},
  "geometry": {"coordinates":[-6.9495549202,37.2570991516],"type":"Point"}
}