{
  "type": "Feature",
  "properties": {
    "addr:full":"Barr Elguero, 5 Elguero Vizcaya 48510",
    "addr:housenumber":"5",
    "addr:postcode":"48510",
    "addr:street":"Elguero",
    "iso:country":"ES",
    "sg:address":"Barr Elguero, 5",
    "sg:city":"Elguero",
    "sg:orig_category":"Empresarios",
    "sg:phone":"+34 944 72 20 25",
    "sg:postcode":"48510",
    "sg:province":"Vizcaya",
    "sg:website":"www.garibaldi.com",
    "wof:name":"Garbialdi S. A. L.",
    "wof:placetype":"venue"
},
  "geometry": {"coordinates":[-3.0369338989,43.3047294617],"type":"Point"}
}