{
  "type": "Feature",
  "properties": {
    "iso:country":"ES",
    "sg:address":"Carrer de Comte D'urgell, 47",
    "sg:city":"Barcelona",
    "sg:orig_category":"Arquitectos",
    "sg:phone":"+34 934 53 50 90",
    "sg:postcode":"08011",
    "sg:province":"Barcelona",
    "wof:name":"Rio Torres Manel",
    "wof:placetype":"venue"
},
  "geometry": {"coordinates":[2.1594376564,41.3814620972],"type":"Point"}
}