{
  "type": "Feature",
  "properties": {
    "iso:country":"ES",
    "sg:address":"Ctra Palmar, S/n",
    "sg:city":"Murcia",
    "sg:orig_category":"Alimentaci\u00d3n General (al Por Mayor)",
    "sg:phone":"+34 968 26 80 17",
    "sg:postcode":"30010",
    "sg:province":"Murcia",
    "wof:name":"Detallistas De Alimentacion Del Segura S. Coop. Ltda.",
    "wof:placetype":"venue"
},
  "geometry": {"coordinates":[-1.1345529556,37.9744987488],"type":"Point"}
}