{
  "type": "Feature",
  "properties": {
    "iso:country":"ES",
    "sg:address":"P. I. Los Charcones, S/n",
    "sg:city":"Cobeja",
    "sg:orig_category":"Ferreter\u00cda (diversos)",
    "sg:phone":"+34 925 55 10 72",
    "sg:postcode":"45291",
    "sg:province":"Toledo",
    "wof:name":"Ferrabar S.l.",
    "wof:placetype":"venue"
},
  "geometry": {"coordinates":[-3.8580191135,40.0248947144],"type":"Point"}
}