{
  "type": "Feature",
  "properties": {
    "addr:full":"Pase Zorrilla, 22 Valladolid Valladolid 47006",
    "addr:housenumber":"22",
    "addr:postcode":"47006",
    "addr:street":"Zorrilla",
    "iso:country":"ES",
    "sg:address":"Pase Zorrilla, 22",
    "sg:city":"Valladolid",
    "sg:orig_category":"Trajes Y Adornos De Boda (confecci\u00d3n, Al Por Menor)",
    "sg:phone":"+34 983 33 42 88",
    "sg:postcode":"47006",
    "sg:province":"Valladolid",
    "sg:website":"www.rosaclara.es",
    "wof:name":"Vallnovias S.l.",
    "wof:placetype":"venue"
},
  "geometry": {"coordinates":[-4.7327637672,41.6461677551],"type":"Point"}
}