{
  "type": "Feature",
  "properties": {
    "iso:country":"ES",
    "sg:address":"Calle de Gonzalez Hontoria, 2",
    "sg:city":"S. Fernando",
    "sg:orig_category":"Ropa Para Se\u00d1oras (al Por Menor)",
    "sg:phone":"+34 956 59 28 72",
    "sg:postcode":"11100",
    "sg:province":"C\u00e1diz",
    "wof:name":"Celop Mujer Modas S.l.",
    "wof:placetype":"venue"
},
  "geometry": {"coordinates":[-6.1963820457,36.46641922],"type":"Point"}
}