{
  "type": "Feature",
  "properties": {
    "iso:country":"ES",
    "sg:address":"Calle de Fontanilla, 22",
    "sg:city":"Aldeacentenera",
    "sg:classifiers":[
        {
            "category":"Communications",
            "type":"Services"
        }
    ],
    "sg:phone":"+34 927 31 42 43",
    "sg:postcode":"10251",
    "sg:province":"C\u00e1ceres",
    "sg:tags":[
        "televisiones",
        "y",
        "radio"
    ],
    "wof:name":"Ayuntamiento De Aldeacentenera",
    "wof:placetype":"venue"
},
  "geometry": {"coordinates":[-5.6289391518,39.5263290405],"type":"Point"}
}