{
  "type": "Feature",
  "properties": {
    "iso:country":"ES",
    "sg:address":"Mas De Tous, 22",
    "sg:city":"Pobla Vallbona",
    "sg:orig_category":"Plomeros",
    "sg:phone":"+34 962 76 18 90",
    "sg:postcode":"46185",
    "sg:province":"Valencia",
    "wof:name":"Dura Alonso Maria Angeles Montiel",
    "wof:placetype":"venue"
},
  "geometry": {"coordinates":[-0.5409290195,39.5874328613],"type":"Point"}
}