{
  "type": "Feature",
  "properties": {
    "addr:full":"Orugo, 1 Trobajo Camino Le\u00f3n 24010",
    "addr:housenumber":"1",
    "addr:postcode":"24010",
    "addr:street":"Orugo;Camino Leo\u0301N",
    "iso:country":"ES",
    "sg:address":"Orugo, 1",
    "sg:city":"Trobajo Camino",
    "sg:orig_category":"Agencias Y Agentes Comerciales, Representantes",
    "sg:phone":"+34 987 24 78 54",
    "sg:postcode":"24010",
    "sg:province":"Le\u00f3n",
    "wof:name":"Garcia Fernandez Rafael",
    "wof:placetype":"venue"
},
  "geometry": {"coordinates":[-5.5914011002,42.6045455933],"type":"Point"}
}