{
  "type": "Feature",
  "properties": {
    "iso:country":"ES",
    "sg:address":"Calle de Cardenal Benlloch, 5",
    "sg:city":"Salas De Los Infantes",
    "sg:orig_category":"Cajas Para Embalar",
    "sg:phone":"+34 947 38 07 06",
    "sg:postcode":"09600",
    "sg:province":"Burgos",
    "wof:name":"Caja Rural De Burgos",
    "wof:placetype":"venue"
},
  "geometry": {"coordinates":[-3.2883911133,42.0219192505],"type":"Point"}
}