{
  "type": "Feature",
  "properties": {
    "iso:country":"ES",
    "sg:address":"Carrer de Genova, 25",
    "sg:city":"Barcelona",
    "sg:orig_category":"Confecci\u00d3n De Botones",
    "sg:phone":"+34 934 55 84 02",
    "sg:postcode":"08041",
    "sg:province":"Barcelona",
    "wof:name":"Btc Line S.l.",
    "wof:placetype":"venue"
},
  "geometry": {"coordinates":[2.169262886,41.4176712036],"type":"Point"}
}