{
  "type": "Feature",
  "properties": {
    "iso:country":"ES",
    "sg:address":"Calle de San Vicente Ferrer, 4",
    "sg:city":"Madrid",
    "sg:orig_category":"Centros Comerciales Y Grandes Tiendas",
    "sg:phone":"+34 914 47 91 91",
    "sg:postcode":"28004",
    "sg:province":"Madrid",
    "wof:name":"Chen  Xuerong",
    "wof:placetype":"venue"
},
  "geometry": {"coordinates":[-3.7020919323,40.4257202148],"type":"Point"}
}