{
  "type": "Feature",
  "properties": {
    "addr:full":"Calle de Do\u00d1a Pura Bascaran, 5 Palmas De Gran Canaria Las Palmas 35004",
    "addr:housenumber":"5",
    "addr:postcode":"35004",
    "addr:street":"Calle De Don\u0303A Pura Bascaran",
    "iso:country":"ES",
    "sg:address":"Calle de Do\u00d1a Pura Bascaran, 5",
    "sg:city":"Palmas De Gran Canaria",
    "sg:orig_category":"Asociaciones Y Clubs Deportivos",
    "sg:phone":"+34 928 23 04 91",
    "sg:postcode":"35004",
    "sg:province":"Las Palmas",
    "wof:name":"Medina Sanchez Jorge Javier",
    "wof:placetype":"venue"
},
  "geometry": {"coordinates":[-15.4258060455,28.1168937683],"type":"Point"}
}