{
  "type": "Feature",
  "properties": {
    "addr:full":"Ctra Pe\u00d1afiel, 26 Cuellar Segovia 40200",
    "addr:housenumber":"26",
    "addr:postcode":"40200",
    "addr:street":"Ctra Pen\u0303Afiel",
    "iso:country":"ES",
    "sg:address":"Ctra Pe\u00d1afiel, 26",
    "sg:city":"Cuellar",
    "sg:orig_category":"Muebles, Minoristas",
    "sg:phone":"+34 921 14 20 75",
    "sg:postcode":"40200",
    "sg:province":"Segovia",
    "wof:name":"Avellon Muebles Aries S.l.",
    "wof:placetype":"venue"
},
  "geometry": {"coordinates":[-4.3057990074,41.4048194885],"type":"Point"}
}