{
  "type": "Feature",
  "properties": {
    "addr:full":"Calle de Rodriguez San Pedro, 25 Madrid Madrid 28015",
    "addr:housenumber":"25",
    "addr:postcode":"madrid;28015",
    "addr:street":"Calle De Rodriguez San Pedro",
    "iso:country":"ES",
    "sg:address":"Calle de Rodriguez San Pedro, 25",
    "sg:city":"Madrid",
    "sg:classifiers":[
        {
            "category":"Personal",
            "subcategory":"Barber",
            "type":"Services"
        }
    ],
    "sg:phone":"+34 914 46 95 28",
    "sg:postcode":"28015",
    "sg:province":"Madrid",
    "sg:tags":[
        "caballeros",
        "de",
        "peluqueros"
    ],
    "wof:name":"Del Pozo Delgado Francisco Jose",
    "wof:placetype":"venue"
},
  "geometry": {"coordinates":[-3.7112300396,40.4315872192],"type":"Point"}
}