{
  "type": "Feature",
  "properties": {
    "iso:country":"ES",
    "sg:address":"Est. Atocha, 10",
    "sg:city":"Madrid",
    "sg:orig_category":"Herboristas (al Por Menor)",
    "sg:phone":"+34 915 39 18 97",
    "sg:postcode":"28045",
    "sg:province":"Madrid",
    "wof:name":"Auge 2000 S.l.",
    "wof:placetype":"venue"
},
  "geometry": {"coordinates":[-3.6902165413,40.3954772949],"type":"Point"}
}