{
  "type": "Feature",
  "properties": {
    "iso:country":"ES",
    "sg:address":"Calle de Colon De Larreategui, 23",
    "sg:city":"Bilbao",
    "sg:orig_category":"Art\u00cdculos De Decoraci\u00d3n (fabricaci\u00d3n Y Al Por Mayor)",
    "sg:phone":"+34 944 24 74 05",
    "sg:postcode":"48001",
    "sg:province":"Vizcaya",
    "wof:name":"Bego\u00f1a Mesanza",
    "wof:placetype":"venue"
},
  "geometry": {"coordinates":[-2.9285399914,43.2625274658],"type":"Point"}
}