{
  "type": "Feature",
  "properties": {
    "addr:full":"Plaz Convento, 6 Denia Alicante 03700",
    "addr:housenumber":"6",
    "addr:postcode":"03700",
    "addr:street":"Convento",
    "iso:country":"ES",
    "sg:address":"Plaz Convento, 6",
    "sg:city":"Denia",
    "sg:orig_category":"Oficinas: Suministros Para (fabricaci\u00d3n, Al Por Mayor)",
    "sg:phone":"+34 966 42 59 36",
    "sg:postcode":"03700",
    "sg:province":"Alicante",
    "wof:name":"Costa Serra Antonio",
    "wof:placetype":"venue"
},
  "geometry": {"coordinates":[0.1039630026,38.8354949951],"type":"Point"}
}