{
  "type": "Feature",
  "properties": {
    "addr:full":"Calle de Estatuto De Galicia, 30 Boiro A Coru\u00f1a 15930",
    "addr:housenumber":"30",
    "addr:postcode":"15930",
    "addr:street":"Calle De Estatuto De Galicia;Corun\u0303A",
    "iso:country":"ES",
    "sg:address":"Calle de Estatuto De Galicia, 30",
    "sg:city":"Boiro",
    "sg:orig_category":"Ropa Para Se\u00d1oras Y Caballeros (al Por Menor)",
    "sg:phone":"+34 981 84 88 03",
    "sg:postcode":"15930",
    "sg:province":"A Coru\u00f1a",
    "wof:name":"Super Textil El Tejano S.l.",
    "wof:placetype":"venue"
},
  "geometry": {"coordinates":[-8.8847093582,42.6471214294],"type":"Point"}
}