{
  "type": "Feature",
  "properties": {
    "addr:full":"Plaz Puerta De Purchena, 2 Almeria Almer\u00eda 04003",
    "addr:housenumber":"2",
    "addr:postcode":"04003",
    "addr:street":"Puerta;Purchena",
    "iso:country":"ES",
    "sg:address":"Plaz Puerta De Purchena, 2",
    "sg:city":"Almeria",
    "sg:orig_category":"Centros De Coordinaci\u00d3n",
    "sg:phone":"+34 950 62 11 00",
    "sg:postcode":"04003",
    "sg:province":"Almer\u00eda",
    "wof:name":"Almeria Gestoria Arcos, S.l.u.",
    "wof:placetype":"venue"
},
  "geometry": {"coordinates":[-2.4638097286,36.8418121338],"type":"Point"}
}