{
  "type": "Feature",
  "properties": {
    "iso:country":"ES",
    "sg:address":"Pol. Ind. Castilla, 6",
    "sg:city":"Pol. Ind. Castilla",
    "sg:orig_category":"Ferreter\u00cda (diversos)",
    "sg:phone":"+34 962 51 40 14",
    "sg:postcode":"46380",
    "sg:province":"Valencia",
    "wof:name":"Metales Mongil S.a.",
    "wof:placetype":"venue"
},
  "geometry": {"coordinates":[-0.6874480247,39.4945602417],"type":"Point"}
}