{
  "type": "Feature",
  "properties": {
    "addr:full":"Avda Luis Gonzalez Taboada, 22 Lalin Pontevedra 36500",
    "addr:housenumber":"22",
    "addr:postcode":"36500",
    "addr:street":"Avda Luis Gonzalez Taboada",
    "iso:country":"ES",
    "sg:address":"Avda Luis Gonzalez Taboada, 22",
    "sg:city":"Lalin",
    "sg:orig_category":"Plomeros",
    "sg:phone":"+34 986 78 12 52",
    "sg:postcode":"36500",
    "sg:province":"Pontevedra",
    "wof:name":"Diaz Gomez Ricardo",
    "wof:placetype":"venue"
},
  "geometry": {"coordinates":[-8.1124048233,42.6579055786],"type":"Point"}
}