{
  "type": "Feature",
  "properties": {
    "addr:full":"Calle de Mirto, 11 Huetor-vega Granada 18198",
    "addr:housenumber":"11",
    "addr:postcode":"18198",
    "addr:street":"Calle De Mirto",
    "iso:country":"ES",
    "sg:address":"Calle de Mirto, 11",
    "sg:city":"Huetor-vega",
    "sg:orig_category":"Contenedores (mercanc\u00cdas)",
    "sg:phone":"+34 958 30 41 60",
    "sg:postcode":"18198",
    "sg:province":"Granada",
    "wof:name":"Jimenez Fernandez Angel",
    "wof:placetype":"venue"
},
  "geometry": {"coordinates":[-3.5752727985,37.1507606506],"type":"Point"}
}