{
  "type": "Feature",
  "properties": {
    "iso:country":"ES",
    "sg:address":"Calle de Isabel La Catolica, 5",
    "sg:city":"Cadiz",
    "sg:orig_category":"Asesor\u00cda De Formaci\u00d3n Y Gesti\u00d3n De Personal",
    "sg:phone":"+34 956 22 02 43",
    "sg:postcode":"11004",
    "sg:province":"C\u00e1diz",
    "wof:name":"Carvajal Cembrano Inmaculada",
    "wof:placetype":"venue"
},
  "geometry": {"coordinates":[-6.2949309349,36.535194397],"type":"Point"}
}