{
  "type": "Feature",
  "properties": {
    "iso:country":"ES",
    "sg:address":"Av Industria (de), 3",
    "sg:city":"Castellgali",
    "sg:orig_category":"Fabricaci\u00d3n De Bolsos Y Bolsos De Tela",
    "sg:phone":"+34 938 33 08 26",
    "sg:postcode":"08297",
    "sg:province":"Barcelona",
    "wof:name":"Clime S. A.",
    "wof:placetype":"venue"
},
  "geometry": {"coordinates":[1.8473449945,41.6786499023],"type":"Point"}
}