{
  "type": "Feature",
  "properties": {
    "addr:full":"Poligono Industrial, S/n Vicolozano \u00c1vila 05194",
    "addr:postcode":"05194",
    "addr:street":"Industrial S / N Vicolozano A\u0301Vila",
    "iso:country":"ES",
    "sg:address":"Poligono Industrial, S/n",
    "sg:city":"Vicolozano",
    "sg:orig_category":"Maquinaria Para Industrias Diversas",
    "sg:phone":"+34 920 25 90 88",
    "sg:postcode":"05194",
    "sg:province":"\u00c1vila",
    "wof:name":"Alquileres Abulenses S.l.",
    "wof:placetype":"venue"
},
  "geometry": {"coordinates":[-4.6319680214,40.6813316345],"type":"Point"}
}