{
  "type": "Feature",
  "properties": {
    "iso:country":"ES",
    "sg:address":"Calle de Doctor Fleming, 3",
    "sg:city":"Villablino",
    "sg:orig_category":"Alimentaci\u00d3n General (al Por Menor)",
    "sg:phone":"+34 987 47 03 94",
    "sg:postcode":"24100",
    "sg:province":"Le\u00f3n",
    "wof:name":"Guerra Puerto Rosa",
    "wof:placetype":"venue"
},
  "geometry": {"coordinates":[-6.3215918541,42.9385795593],"type":"Point"}
}