{
  "type": "Feature",
  "properties": {
    "iso:country":"ES",
    "sg:address":"Calle de Bernardas, 2",
    "sg:city":"Almagro",
    "sg:orig_category":"Turismo",
    "sg:phone":"+34 926 26 12 68",
    "sg:postcode":"13270",
    "sg:province":"Ciudad Real",
    "sg:website":"www.tierradecaballeros.com",
    "wof:name":"Mancomunidad Tierras De Caballeros Y Tablas Daimiel Plan De Dinamizacion",
    "wof:placetype":"venue"
},
  "geometry": {"coordinates":[-3.7120859623,38.88722229],"type":"Point"}
}