{
  "type": "Feature",
  "properties": {
    "iso:country":"ES",
    "sg:address":"Avda Doctor Federico Rubio Y Gali, 8",
    "sg:city":"Madrid",
    "sg:orig_category":"Restaurantes",
    "sg:phone":"+34 915 34 51 67",
    "sg:postcode":"28039",
    "sg:province":"Madrid",
    "wof:name":"Toribio Lopez Enrique",
    "wof:placetype":"venue"
},
  "geometry": {"coordinates":[-3.7080850601,40.448474884],"type":"Point"}
}