{
  "type": "Feature",
  "properties": {
    "addr:full":"El Cruce, S/n Marbella M\u00e1laga 29600",
    "addr:housenumber":"s / n",
    "addr:postcode":"29600",
    "addr:street":"El Cruce;Ma\u0301Laga",
    "iso:country":"ES",
    "sg:address":"El Cruce, S/n",
    "sg:city":"Marbella",
    "sg:orig_category":"Centros De Educaci\u00d3n Especial",
    "sg:phone":"+34 952 77 15 67",
    "sg:postcode":"29600",
    "sg:province":"M\u00e1laga",
    "wof:name":"Junta De Andalucia",
    "wof:placetype":"venue"
},
  "geometry": {"coordinates":[-4.8833007812,36.5079956055],"type":"Point"}
}