{
  "type": "Feature",
  "properties": {
    "iso:country":"ES",
    "sg:address":"Carrer de Sugranyes, 62",
    "sg:city":"Barcelona",
    "sg:orig_category":"Molduras, Junquillos, Listones Y Molduras Perforadas",
    "sg:phone":"+34 934 22 26 28",
    "sg:postcode":"08028",
    "sg:province":"Barcelona",
    "wof:name":"Monge Bola\u00f1os Jose",
    "wof:placetype":"venue"
},
  "geometry": {"coordinates":[2.1287260056,41.3735160828],"type":"Point"}
}