{
  "type": "Feature",
  "properties": {
    "iso:country":"ES",
    "sg:address":"Calle de Mostoles (de), 62",
    "sg:city":"Fuenlabrada",
    "sg:orig_category":"Mec\u00c1nico Del Autom\u00d3vil",
    "sg:phone":"+34 916 00 06 17",
    "sg:postcode":"28942",
    "sg:province":"Madrid",
    "wof:name":"Sano Y Cinda S.l.",
    "wof:placetype":"venue"
},
  "geometry": {"coordinates":[-3.8073089123,40.2924690247],"type":"Point"}
}