{
  "type": "Feature",
  "properties": {
    "addr:full":"Avda Doctor Garcia Tapia, 129 Madrid Madrid 28030",
    "addr:housenumber":"129",
    "addr:postcode":"28030",
    "addr:street":"Avda Doctor Garcia Tapia",
    "iso:country":"ES",
    "sg:address":"Avda Doctor Garcia Tapia, 129",
    "sg:city":"Madrid",
    "sg:orig_category":"Ense\u00d1anza Variada",
    "sg:phone":"+34 913 01 40 15",
    "sg:postcode":"28030",
    "sg:province":"Madrid",
    "wof:name":"Academia Edison S.l.",
    "wof:placetype":"venue"
},
  "geometry": {"coordinates":[-3.6395146847,40.4093894958],"type":"Point"}
}