{
  "type": "Feature",
  "properties": {
    "iso:country":"ES",
    "sg:address":"Calle de Ramiro El Monje, 2",
    "sg:city":"Sotogrande",
    "sg:orig_category":"Inmobiliaria (agencias)",
    "sg:phone":"+34 956 79 68 68",
    "sg:postcode":"11310",
    "sg:province":"C\u00e1diz",
    "wof:name":"Amiri Development S.l.",
    "wof:placetype":"venue"
},
  "geometry": {"coordinates":[-5.2944898605,36.2862243652],"type":"Point"}
}