{
  "type": "Feature",
  "properties": {
    "addr:full":"Urb. La Estrella, S/n Miguelturra Ciudad Real 13170",
    "addr:housenumber":"s",
    "addr:postcode":"13170",
    "addr:street":"/ N Miguelturra",
    "iso:country":"ES",
    "sg:address":"Urb. La Estrella, S/n",
    "sg:city":"Miguelturra",
    "sg:orig_category":"Aparatos E Instalaci\u00d3n De Regad\u00cdos",
    "sg:phone":"+34 926 24 04 13",
    "sg:postcode":"13170",
    "sg:province":"Ciudad Real",
    "wof:name":"Fomento Tecnologico E Inmobiliario S.l.",
    "wof:placetype":"venue"
},
  "geometry": {"coordinates":[-3.885874033,38.9622154236],"type":"Point"}
}