{
  "type": "Feature",
  "properties": {
    "addr:full":"Calle de Paulino Vicente, 6 Lugones Asturias 33420",
    "addr:housenumber":"6",
    "addr:postcode":"33420",
    "addr:street":"Calle De Paulino Vicente",
    "iso:country":"ES",
    "sg:address":"Calle de Paulino Vicente, 6",
    "sg:city":"Lugones",
    "sg:orig_category":"Prot\u00c9sicos Dentales",
    "sg:phone":"+34 985 26 77 39",
    "sg:postcode":"33420",
    "sg:province":"Asturias",
    "wof:name":"Rodriguez Diaz Javier",
    "wof:placetype":"venue"
},
  "geometry": {"coordinates":[-5.8046522141,43.3990745544],"type":"Point"}
}