{
  "type": "Feature",
  "properties": {
    "addr:full":"Calle de Canalejas, 60 Palmas De Gran Canaria Las Palmas 35003",
    "addr:housenumber":"60",
    "addr:postcode":"35003",
    "addr:street":"Calle De Canalejas",
    "iso:country":"ES",
    "sg:address":"Calle de Canalejas, 60",
    "sg:city":"Palmas De Gran Canaria",
    "sg:orig_category":"Asociaciones, Organismos Culturales Y Socioeducativos",
    "sg:phone":"+34 928 38 26 87",
    "sg:postcode":"35003",
    "sg:province":"Las Palmas",
    "wof:name":"Asociacion Juvenil Scout Acaicate",
    "wof:placetype":"venue"
},
  "geometry": {"coordinates":[-15.4207696915,28.1113700867],"type":"Point"}
}