{
  "type": "Feature",
  "properties": {
    "iso:country":"ES",
    "sg:address":"Carrer de Almacelles, 1",
    "sg:city":"Barcelona",
    "sg:orig_category":"Centros De Educaci\u00d3n Especial",
    "sg:phone":"+34 933 14 17 76",
    "sg:postcode":"08020",
    "sg:province":"Barcelona",
    "wof:name":"Ajuntament De Barcelona",
    "wof:placetype":"venue"
},
  "geometry": {"coordinates":[2.1992118359,41.4222602844],"type":"Point"}
}