{
  "type": "Feature",
  "properties": {
    "iso:country":"ES",
    "sg:address":"Carrer de Pablo Iglesias, 1",
    "sg:city":"Viladecans",
    "sg:orig_category":"Empresas De Carpinter\u00cda De Madera",
    "sg:phone":"+34 936 37 49 71",
    "sg:postcode":"08840",
    "sg:province":"Barcelona",
    "wof:name":"Serrano Caballero Juana",
    "wof:placetype":"venue"
},
  "geometry": {"coordinates":[2.0106010437,41.3140907288],"type":"Point"}
}