{
  "type": "Feature",
  "properties": {
    "addr:full":"Calle de Capitan Claudio Vazquez, 77 Ceuta Ceuta 51002",
    "addr:housenumber":"77",
    "addr:postcode":"51002",
    "addr:street":"Calle De Capitan;Vazquez",
    "iso:country":"ES",
    "sg:address":"Calle de Capitan Claudio Vazquez, 77",
    "sg:city":"Ceuta",
    "sg:orig_category":"Farmacias",
    "sg:phone":"+34 956 50 17 52",
    "sg:postcode":"51002",
    "sg:province":"Ceuta",
    "wof:name":"Rodriguez Cans Maria Jesus",
    "wof:placetype":"venue"
},
  "geometry": {"coordinates":[-5.3404970169,35.8849411011],"type":"Point"}
}