{
  "type": "Feature",
  "properties": {
    "addr:full":"Calle de Maiquez, 28 Madrid Madrid 28009",
    "addr:housenumber":"28",
    "addr:postcode":"madrid;28009",
    "addr:street":"Calle De Maiquez",
    "iso:country":"ES",
    "sg:address":"Calle de Maiquez, 28",
    "sg:city":"Madrid",
    "sg:orig_category":"Molduras, Junquillos, Listones Y Molduras Perforadas",
    "sg:phone":"+34 914 09 10 80",
    "sg:postcode":"28009",
    "sg:province":"Madrid",
    "wof:name":"Parrondo Arias Luis Florentino",
    "wof:placetype":"venue"
},
  "geometry": {"coordinates":[-3.6731469631,40.4198455811],"type":"Point"}
}