{
  "type": "Feature",
  "properties": {
    "addr:full":"Calle de Rioja, 17 Vitoria-gasteiz \u00c1lava 01005",
    "addr:housenumber":"17",
    "addr:postcode":"01005",
    "addr:street":"Calle De Rioja",
    "iso:country":"ES",
    "sg:address":"Calle de Rioja, 17",
    "sg:city":"Vitoria-gasteiz",
    "sg:orig_category":"Empresas De Carpinter\u00cda Met\u00c1lica",
    "sg:phone":"+34 945 25 88 92",
    "sg:postcode":"01005",
    "sg:province":"\u00c1lava",
    "wof:name":"Ventanas Vitoria S.l.",
    "wof:placetype":"venue"
},
  "geometry": {"coordinates":[-2.6681489944,42.8425102234],"type":"Point"}
}