{
  "type": "Feature",
  "properties": {
    "iso:country":"ES",
    "sg:address":"Rua Real, 203",
    "sg:city":"Ferrol",
    "sg:orig_category":"M\u00c9dicos: Ginecolog\u00cda Y Obstetricia",
    "sg:phone":"+34 981 35 82 22",
    "sg:postcode":"15402",
    "sg:province":"La Coru\u00f1a",
    "wof:name":"Alvarez Gomez Manuel",
    "wof:placetype":"venue"
},
  "geometry": {"coordinates":[-8.2375669479,43.4820556641],"type":"Point"}
}