{
  "type": "Feature",
  "properties": {
    "iso:country":"ES",
    "sg:address":"Carrer de Jacint Verdaguer, 18",
    "sg:city":"Ametlla Mar",
    "sg:orig_category":"Distribuci\u00d3n De Petr\u00d3leo Y Derivados",
    "sg:phone":"+34 977 49 36 20",
    "sg:postcode":"43860",
    "sg:province":"Tarragona",
    "wof:name":"Peixos Guzman Cdad.",
    "wof:placetype":"venue"
},
  "geometry": {"coordinates":[0.8024939895,40.8863182068],"type":"Point"}
}