{
  "type": "Feature",
  "properties": {
    "iso:country":"ES",
    "sg:address":"Pl Marsans, S/n",
    "sg:city":"Cornella Llobregat",
    "sg:orig_category":"Carnicer\u00cdas, Carnicer\u00cdas",
    "sg:phone":"+34 933 76 70 50",
    "sg:postcode":"08940",
    "sg:province":"Barcelona",
    "wof:name":"Almagro Castillo Maria",
    "wof:placetype":"venue"
},
  "geometry": {"coordinates":[2.0754694939,41.3613204956],"type":"Point"}
}