{
  "type": "Feature",
  "properties": {
    "iso:country":"ES",
    "sg:address":"Carrer de Doctor Mas, 3",
    "sg:city":"Monovar",
    "sg:orig_category":"Reposter\u00cdas",
    "sg:phone":"+34 965 47 03 96",
    "sg:postcode":"03640",
    "sg:province":"Alicante",
    "wof:name":"Revert Frances Juan",
    "wof:placetype":"venue"
},
  "geometry": {"coordinates":[-0.8358389735,38.4373207092],"type":"Point"}
}