{
  "type": "Feature",
  "properties": {
    "addr:full":"Calle de Ximen Perez D'arenos, 17 Borriol Castell\u00f3n 12190",
    "addr:housenumber":"17",
    "addr:postcode":"12190",
    "addr:street":"Calle De Ximen;D'Arenos",
    "iso:country":"ES",
    "sg:address":"Calle de Ximen Perez D'arenos, 17",
    "sg:city":"Borriol",
    "sg:orig_category":"Papeler\u00cdas, Librer\u00cdas",
    "sg:phone":"+34 964 32 17 14",
    "sg:postcode":"12190",
    "sg:province":"Castell\u00f3n",
    "wof:name":"Personat Safont Teresa Rosario",
    "wof:placetype":"venue"
},
  "geometry": {"coordinates":[-0.0709149987,40.0426750183],"type":"Point"}
}