{
  "type": "Feature",
  "properties": {
    "addr:full":"Estacion, S/n El Astillero Cantabria 39610",
    "addr:postcode":"39610",
    "addr:street":"S / N",
    "iso:country":"ES",
    "sg:address":"Estacion, S/n",
    "sg:city":"El Astillero",
    "sg:orig_category":"Transportes Ferroviarios",
    "sg:phone":"+34 942 54 07 23",
    "sg:postcode":"39610",
    "sg:province":"Cantabria",
    "wof:name":"Ferrocarriles De Via Estrecha",
    "wof:placetype":"venue"
},
  "geometry": {"coordinates":[-3.821928978,43.4001655579],"type":"Point"}
}