{
  "type": "Feature",
  "properties": {
    "iso:country":"ES",
    "sg:address":"Calle de Bailen, 4",
    "sg:city":"Coru\u00d1a",
    "sg:orig_category":"Ropa Para Ni\u00d1os (al Por Menor)",
    "sg:phone":"+34 981 21 27 96",
    "sg:postcode":"15001",
    "sg:province":"A Coru\u00f1a",
    "wof:name":"Stradivarius Espa\u00d1a S.a",
    "wof:placetype":"venue"
},
  "geometry": {"coordinates":[-8.3967437744,43.3701553345],"type":"Point"}
}