{
  "type": "Feature",
  "properties": {
    "addr:full":"Alberite, Km. 0001,5 Alberite La Rioja 26141",
    "addr:postcode":"26141",
    "addr:street":"Alberite Km. 0001,5 Alberite;Rioja",
    "iso:country":"ES",
    "sg:address":"Alberite, Km. 0001,5",
    "sg:city":"Alberite",
    "sg:orig_category":"Distribuci\u00d3n De Petr\u00d3leo Y Derivados",
    "sg:phone":"+34 941 43 64 95",
    "sg:postcode":"26141",
    "sg:province":"La Rioja",
    "wof:name":"Praluc S.l.",
    "wof:placetype":"venue"
},
  "geometry": {"coordinates":[-2.4261200428,42.404045105],"type":"Point"}
}