{
  "type": "Feature",
  "properties": {
    "addr:full":"Carrer de Vazquez Diaz, 15 Monovar Alicante 03640",
    "addr:housenumber":"15",
    "addr:postcode":"03640",
    "addr:street":"Carrer De Vazquez Diaz;Alicante",
    "iso:country":"ES",
    "sg:address":"Carrer de Vazquez Diaz, 15",
    "sg:city":"Monovar",
    "sg:orig_category":"M\u00c1quinas Para Recortar Y Pegar",
    "sg:phone":"+34 965 47 01 66",
    "sg:postcode":"03640",
    "sg:province":"Alicante",
    "wof:name":"Troquelnovar S.l.",
    "wof:placetype":"venue"
},
  "geometry": {"coordinates":[-0.8357030153,38.437538147],"type":"Point"}
}