{
  "type": "Feature",
  "properties": {
    "iso:country":"ES",
    "sg:address":"Carrer de Mont Llorer, 1",
    "sg:city":"S. Celoni",
    "sg:orig_category":"Alimentaci\u00d3n General (al Por Mayor)",
    "sg:phone":"+34 938 67 56 55",
    "sg:postcode":"08470",
    "sg:province":"Barcelona",
    "wof:name":"Productos De Alimentacion Tecnica S.l.",
    "wof:placetype":"venue"
},
  "geometry": {"coordinates":[2.497989893,41.6877403259],"type":"Point"}
}