{
  "type": "Feature",
  "properties": {
    "iso:country":"ES",
    "sg:address":"Carrer de Pare Rodamilans, 61",
    "sg:city":"Sabadell",
    "sg:orig_category":"Fabricaci\u00d3n De Telas Y Sedas",
    "sg:phone":"+34 937 27 00 19",
    "sg:postcode":"08205",
    "sg:province":"Barcelona",
    "wof:name":"Lanitex S. A.",
    "wof:placetype":"venue"
},
  "geometry": {"coordinates":[2.0977780819,41.5440254211],"type":"Point"}
}