{
  "type": "Feature",
  "properties": {
    "addr:full":"Av Elies Pages, 26 Barcelona Barcelona 08035",
    "addr:housenumber":"26",
    "addr:postcode":"08035",
    "addr:street":"Av Elies Pages",
    "iso:country":"ES",
    "sg:address":"Av Elies Pages, 26",
    "sg:city":"Barcelona",
    "sg:orig_category":"Empresas De Carpinter\u00cda De Madera",
    "sg:phone":"+34 934 17 65 40",
    "sg:postcode":"08035",
    "sg:province":"Barcelona",
    "wof:name":"Lopez Fernandez Camilo",
    "wof:placetype":"venue"
},
  "geometry": {"coordinates":[2.1333079338,41.4282608032],"type":"Point"}
}