{
  "type": "Feature",
  "properties": {
    "iso:country":"ES",
    "sg:address":"Po Ind Petroquimico, S/n",
    "sg:city":"Palos Frontera",
    "sg:orig_category":"Industria Qu\u00cdmica",
    "sg:phone":"+34 959 49 24 00",
    "sg:postcode":"21810",
    "sg:province":"Huelva",
    "wof:name":"Fertiberia S.a.",
    "wof:placetype":"venue"
},
  "geometry": {"coordinates":[-6.8923411369,37.2240829468],"type":"Point"}
}