{
  "type": "Feature",
  "properties": {
    "iso:country":"ES",
    "sg:address":"Carr Raval De Sant Roc, 43",
    "sg:city":"Raval",
    "sg:orig_category":"Farmacias",
    "sg:phone":"+34 962 42 39 23",
    "sg:postcode":"46680",
    "sg:province":"Valencia",
    "wof:name":"Soler Montejano Aurora",
    "wof:placetype":"venue"
},
  "geometry": {"coordinates":[-0.4383490086,39.1962852478],"type":"Point"}
}