{
  "type": "Feature",
  "properties": {
    "addr:full":"Avda Las Cortes De Cadiz, 6 Cadiz C\u00e1diz 11012",
    "addr:housenumber":"6",
    "addr:postcode":"11012",
    "addr:street":"Avda Las Cortes De Cadiz",
    "iso:country":"ES",
    "sg:address":"Avda Las Cortes De Cadiz, 6",
    "sg:city":"Cadiz",
    "sg:orig_category":"Ropa Para Ni\u00d1os (al Por Menor)",
    "sg:phone":"+34 956 20 53 99",
    "sg:postcode":"11012",
    "sg:province":"C\u00e1diz",
    "sg:website":"www.bershka.com",
    "wof:name":"Bershka Bsr Espa\u00f1a S.a.",
    "wof:placetype":"venue"
},
  "geometry": {"coordinates":[-6.2761001587,36.5218276978],"type":"Point"}
}