{
  "type": "Feature",
  "properties": {
    "addr:full":"Calle de La Reina, 35 Almoradi Alicante 03160",
    "addr:housenumber":"35",
    "addr:postcode":"03160",
    "addr:street":"Calle De La Reina",
    "iso:country":"ES",
    "sg:address":"Calle de La Reina, 35",
    "sg:city":"Almoradi",
    "sg:orig_category":"Hormig\u00d3n (m\u00c1quinas E Instalaci\u00d3n)",
    "sg:phone":"+34 966 78 20 25",
    "sg:postcode":"03160",
    "sg:province":"Alicante",
    "wof:name":"Hormigoneras Andreval S.l.",
    "wof:placetype":"venue"
},
  "geometry": {"coordinates":[-0.7940760255,38.1086921692],"type":"Point"}
}