{
  "type": "Feature",
  "properties": {
    "iso:country":"ES",
    "sg:address":"Pla\u00c7 Enric Cristofol Ricart, 24",
    "sg:city":"Vilanova I La Geltru",
    "sg:orig_category":"Peluquer\u00cdas, Peluquer\u00cda Mixta",
    "sg:phone":"+34 938 15 50 42",
    "sg:postcode":"08800",
    "sg:province":"Barcelona",
    "wof:name":"Mena Puga Maria Del Mar",
    "wof:placetype":"venue"
},
  "geometry": {"coordinates":[1.705232501,41.2381515503],"type":"Point"}
}