{
  "type": "Feature",
  "properties": {
    "addr:full":"Barr Monte San Miguel, S/n Monte Cantabria 39012",
    "addr:housenumber":"s",
    "addr:postcode":"39012",
    "addr:street":"San Miguel;/ N",
    "iso:country":"ES",
    "sg:address":"Barr Monte San Miguel, S/n",
    "sg:city":"Monte",
    "sg:orig_category":"Chapister\u00cda",
    "sg:phone":"+34 942 33 45 69",
    "sg:postcode":"39012",
    "sg:province":"Cantabria",
    "wof:name":"Cobo Gomez Francisco Manuel",
    "wof:placetype":"venue"
},
  "geometry": {"coordinates":[-3.8324849606,43.4710655212],"type":"Point"}
}