{
  "type": "Feature",
  "properties": {
    "iso:country":"ES",
    "sg:address":"Carr Reina De La, 31",
    "sg:city":"Xativa",
    "sg:orig_category":"Art\u00cdculos De Decoraci\u00d3n",
    "sg:phone":"+34 962 27 11 13",
    "sg:postcode":"46800",
    "sg:province":"Valencia",
    "wof:name":"Drogueria El Barco C.b.",
    "wof:placetype":"venue"
},
  "geometry": {"coordinates":[-0.5200830102,38.9934272766],"type":"Point"}
}