{
  "type": "Feature",
  "properties": {
    "iso:country":"ES",
    "sg:address":"Av Gaspar Bennazar, 8",
    "sg:city":"Palma",
    "sg:orig_category":"Transporte En General",
    "sg:phone":"+34 971 49 82 96",
    "sg:postcode":"07004",
    "sg:province":"Islas Baleares",
    "wof:name":"Fcc Logistica S.a.",
    "wof:placetype":"venue"
},
  "geometry": {"coordinates":[2.6615390778,39.5820045471],"type":"Point"}
}