{
  "type": "Feature",
  "properties": {
    "addr:full":"Entrada, 3 Benaguasil Valencia 46180",
    "addr:postcode":"46180",
    "iso:country":"ES",
    "sg:address":"Entrada, 3",
    "sg:city":"Benaguasil",
    "sg:orig_category":"Farmacias",
    "sg:phone":"+34 962 73 01 32",
    "sg:postcode":"46180",
    "sg:province":"Valencia",
    "wof:name":"Herraez Blasco Ines",
    "wof:placetype":"venue"
},
  "geometry": {"coordinates":[-0.5862720013,39.5938949585],"type":"Point"}
}