{
  "type": "Feature",
  "properties": {
    "addr:full":"Calle de Hermosilla, 108 Madrid Madrid 28009",
    "addr:housenumber":"108",
    "addr:postcode":"28009",
    "addr:street":"Calle De Hermosilla",
    "iso:country":"ES",
    "sg:address":"Calle de Hermosilla, 108",
    "sg:city":"Madrid",
    "sg:orig_category":"Asociaciones Humanitarias, De Cooperaci\u00d3n, De Acci\u00d3n Social",
    "sg:phone":"+34 914 02 70 06",
    "sg:postcode":"28009",
    "sg:province":"Madrid",
    "wof:name":"Ayuda A Domicilio Nuestra Se\u00d1ora De La Esperanza",
    "wof:placetype":"venue"
},
  "geometry": {"coordinates":[-3.6714179516,40.4255714417],"type":"Point"}
}