{
  "type": "Feature",
  "properties": {
    "addr:full":"Calle de Trevedes, 2 Cosuenda Zaragoza 50409",
    "addr:housenumber":"2",
    "addr:postcode":"50409",
    "addr:street":"Calle De Trevedes",
    "iso:country":"ES",
    "sg:address":"Calle de Trevedes, 2",
    "sg:city":"Cosuenda",
    "sg:orig_category":"Semiller\u00cdas",
    "sg:phone":"+34 976 62 71 01",
    "sg:postcode":"50409",
    "sg:province":"Zaragoza",
    "wof:name":"Arnal Lorente Silverio",
    "wof:placetype":"venue"
},
  "geometry": {"coordinates":[-1.298563242,41.3661689758],"type":"Point"}
}