{
  "type": "Feature",
  "properties": {
    "addr:full":"Fermin Calbeton Kalea, 21 Eibar Guip\u00f9zcoa 20600",
    "addr:housenumber":"21",
    "addr:postcode":"20600",
    "addr:street":"Fermin Calbeton Kalea;Guipu\u0300Zcoa",
    "iso:country":"ES",
    "sg:address":"Fermin Calbeton Kalea, 21",
    "sg:city":"Eibar",
    "sg:orig_category":"Asociaciones Y Clubs Deportivos",
    "sg:phone":"+34 943 82 04 52",
    "sg:postcode":"20600",
    "sg:province":"Guip\u00f9zcoa",
    "wof:name":"Ugan Klub, S.l.",
    "wof:placetype":"venue"
},
  "geometry": {"coordinates":[-2.4704298973,43.1852684021],"type":"Point"}
}