{
  "type": "Feature",
  "properties": {
    "addr:full":"Avda Paso (el), 25 Taco Santa Cruz De Tenerife 38108",
    "addr:postcode":"38108",
    "addr:street":"Avda Paso El",
    "iso:country":"ES",
    "sg:address":"Avda Paso (el), 25",
    "sg:city":"Taco",
    "sg:orig_category":"Confecci\u00d3n (fabricaci\u00d3n, Al Por Mayor)",
    "sg:phone":"+34 922 31 02 64",
    "sg:postcode":"38108",
    "sg:province":"Santa Cruz De Tenerife",
    "wof:name":"Amador Sosa Oscar",
    "wof:placetype":"venue"
},
  "geometry": {"coordinates":[-16.3014831543,28.4585266113],"type":"Point"}
}