{
  "type": "Feature",
  "properties": {
    "addr:full":"Calle de Francisco De Rojas, 6 Madrid Madrid 28010",
    "addr:housenumber":"6",
    "addr:postcode":"28010",
    "addr:street":"Calle De Francisco De Rojas",
    "iso:country":"ES",
    "sg:address":"Calle de Francisco De Rojas, 6",
    "sg:city":"Madrid",
    "sg:orig_category":"Muebles Y Accesorios Para Cocinas Y Cuartos De Ba\u00d1o (al Por Menor)",
    "sg:phone":"+34 914 45 49 11",
    "sg:postcode":"28010",
    "sg:province":"Madrid",
    "wof:name":"Cinalux S.a.",
    "wof:placetype":"venue"
},
  "geometry": {"coordinates":[-3.699395895,40.4290542603],"type":"Point"}
}