{
  "type": "Feature",
  "properties": {
    "iso:country":"ES",
    "sg:address":"Avda Padre Garcia Tejero, 21",
    "sg:city":"Sevilla",
    "sg:orig_category":"Asilos De Ancianos. Centros Privados",
    "sg:phone":"+34 954 62 16 12",
    "sg:postcode":"41012",
    "sg:province":"Sevilla",
    "wof:name":"Daigea S.l.",
    "wof:placetype":"venue"
},
  "geometry": {"coordinates":[-5.9863171577,37.3557319641],"type":"Point"}
}