{
  "type": "Feature",
  "properties": {
    "addr:full":"Avda Palomares, 16 Mairena Aljarafe Sevilla 41927",
    "addr:housenumber":"16",
    "addr:postcode":"41927",
    "addr:street":"Avda Palomares",
    "iso:country":"ES",
    "sg:address":"Avda Palomares, 16",
    "sg:city":"Mairena Aljarafe",
    "sg:orig_category":"Plomeros",
    "sg:phone":"+34 954 76 89 07",
    "sg:postcode":"41927",
    "sg:province":"Sevilla",
    "wof:name":"Font-meco S. L.",
    "wof:placetype":"venue"
},
  "geometry": {"coordinates":[-6.0353398323,37.3544387817],"type":"Point"}
}