{
  "type": "Feature",
  "properties": {
    "addr:full":"Rua Travesia De Vigo, 5 Roris Pontevedra 36206",
    "addr:housenumber":"5",
    "addr:postcode":"36206",
    "addr:street":"Rua Travesia De Vigo",
    "iso:country":"ES",
    "sg:address":"Rua Travesia De Vigo, 5",
    "sg:city":"Roris",
    "sg:orig_category":"Institutos De Belleza",
    "sg:phone":"+34 986 37 60 31",
    "sg:postcode":"36206",
    "sg:province":"Pontevedra",
    "wof:name":"Abal Iglesias Oliva",
    "wof:placetype":"venue"
},
  "geometry": {"coordinates":[-7.146372,42.385574],"type":"Point"}
}