{
  "type": "Feature",
  "properties": {
    "iso:country":"ES",
    "sg:address":"Calle de Vidal De Noya, 48",
    "sg:city":"Sevilla",
    "sg:orig_category":"Reposter\u00cdas",
    "sg:phone":"+34 954 57 62 06",
    "sg:postcode":"41005",
    "sg:province":"Sevilla",
    "wof:name":"Benitez Moreno Miguel",
    "wof:placetype":"venue"
},
  "geometry": {"coordinates":[-5.9599351883,37.3849182129],"type":"Point"}
}