{
  "type": "Feature",
  "properties": {
    "iso:country":"ES",
    "sg:address":"Carrer de Jesus, 44",
    "sg:city":"Sitges",
    "sg:orig_category":"Pescader\u00cdas (al Por Menor)",
    "sg:phone":"+34 938 94 66 78",
    "sg:postcode":"08870",
    "sg:province":"Barcelona",
    "wof:name":"Rubi Magan Sergio",
    "wof:placetype":"venue"
},
  "geometry": {"coordinates":[1.8110239506,41.2375106812],"type":"Point"}
}