{
  "type": "Feature",
  "properties": {
    "addr:full":"Calle de Mantente, 1 Navahermosa Toledo 45150",
    "addr:housenumber":"1",
    "addr:postcode":"45150",
    "addr:street":"Calle De Mantente",
    "iso:country":"ES",
    "sg:address":"Calle de Mantente, 1",
    "sg:city":"Navahermosa",
    "sg:orig_category":"Reposter\u00cdas",
    "sg:phone":"+34 925 41 02 94",
    "sg:postcode":"45150",
    "sg:province":"Toledo",
    "wof:name":"Uceta Martin Fidel Angel",
    "wof:placetype":"venue"
},
  "geometry": {"coordinates":[-4.4687280655,39.6319122314],"type":"Point"}
}