{
  "type": "Feature",
  "properties": {
    "addr:full":"Calle de Magdalena, 6 Arrabal De Portillo Valladolid 47160",
    "addr:housenumber":"6",
    "addr:postcode":"47160",
    "addr:street":"Calle De Magdalena",
    "iso:country":"ES",
    "sg:address":"Calle de Magdalena, 6",
    "sg:city":"Arrabal De Portillo",
    "sg:orig_category":"Panader\u00cdas, Panader\u00cdas",
    "sg:phone":"+34 983 55 62 35",
    "sg:postcode":"47160",
    "sg:province":"Valladolid",
    "wof:name":"Garrote San Martin Carlos",
    "wof:placetype":"venue"
},
  "geometry": {"coordinates":[-4.5970897675,41.4746322632],"type":"Point"}
}