{
  "type": "Feature",
  "properties": {
    "addr:full":"Pl. San J. Cadena, 4 Iru\u00f1a Navarra 31008",
    "addr:housenumber":"4",
    "addr:postcode":"31008",
    "addr:street":"Pl. San J. Cadena",
    "iso:country":"ES",
    "sg:address":"Pl. San J. Cadena, 4",
    "sg:city":"Iru\u00f1a",
    "sg:orig_category":"Arreglo, Reparaci\u00d3n, Piezas Sueltas De Televisi\u00d3n, V\u00cddeo, Hi",
    "sg:phone":"+34 948 27 46 57",
    "sg:postcode":"31008",
    "sg:province":"Navarra",
    "wof:name":"Gaston Munarriz Jose Luis",
    "wof:placetype":"venue"
},
  "geometry": {"coordinates":[-1.6577452421,42.8109931946],"type":"Point"}
}