{
  "type": "Feature",
  "properties": {
    "addr:full":"Ctra. General, Km. 0024,0 La Matanza Acentejo Santa Cruz De Tenerife 38370",
    "addr:postcode":"38370",
    "addr:street":"Ctra. General Km. 0024,0",
    "iso:country":"ES",
    "sg:address":"Ctra. General, Km. 0024,0",
    "sg:city":"La Matanza Acentejo",
    "sg:orig_category":"Comercio, Reparaci\u00d3n De Motocicletas, Bicicletas Y Piezas Sueltas",
    "sg:phone":"+34 922 57 74 38",
    "sg:postcode":"38370",
    "sg:province":"Santa Cruz De Tenerife",
    "wof:name":"Mb Trujillo Racing Team S.l.",
    "wof:placetype":"venue"
},
  "geometry": {"coordinates":[-16.2645397186,28.4603805542],"type":"Point"}
}