{
  "type": "Feature",
  "properties": {
    "addr:full":"Rond Alfons X El Savi (d'), 15 Mataro Barcelona 08304",
    "addr:postcode":"08304",
    "addr:street":"Mataro Barcelona",
    "iso:country":"ES",
    "sg:address":"Rond Alfons X El Savi (d'), 15",
    "sg:city":"Mataro",
    "sg:orig_category":"Fabricaci\u00d3n, Importaci\u00d3n, Venta De Material De Telefon\u00cda, Peritelefon\u00cda",
    "sg:phone":"+34 937 41 40 50",
    "sg:postcode":"08304",
    "sg:province":"Barcelona",
    "sg:website":"www.paginas-amarillas.es",
    "wof:name":"Phonworld S.l.",
    "wof:placetype":"venue"
},
  "geometry": {"coordinates":[2.4432899952,41.545249939],"type":"Point"}
}