{
  "type": "Feature",
  "properties": {
    "iso:country":"ES",
    "sg:address":"Carrer de Sant Felix, 4",
    "sg:city":"Caldes Montbui",
    "sg:orig_category":"Fisioterapia",
    "sg:phone":"+34 938 65 45 26",
    "sg:postcode":"08140",
    "sg:province":"Barcelona",
    "wof:name":"Campeny Pinto Marixell",
    "wof:placetype":"venue"
},
  "geometry": {"coordinates":[2.1664059162,41.6305236816],"type":"Point"}
}