{
  "type": "Feature",
  "properties": {
    "addr:full":"Calle de Carretera De Carmona, 34 Sevilla Sevilla 41008",
    "addr:housenumber":"34",
    "addr:postcode":"41008",
    "addr:street":"Calle De Carretera De Carmona",
    "iso:country":"ES",
    "sg:address":"Calle de Carretera De Carmona, 34",
    "sg:city":"Sevilla",
    "sg:orig_category":"Ense\u00d1anza: Idiomas",
    "sg:phone":"+34 954 41 64 01",
    "sg:postcode":"41008",
    "sg:province":"Sevilla",
    "wof:name":"Casta\u00f1o Urende Catalina",
    "wof:placetype":"venue"
},
  "geometry": {"coordinates":[-5.8550591469,37.4141998291],"type":"Point"}
}