{
  "type": "Feature",
  "properties": {
    "addr:full":"Calle de Toledo, 148 Sonseca Toledo 45100",
    "addr:housenumber":"148",
    "addr:postcode":"45100",
    "addr:street":"Calle De Toledo",
    "iso:country":"ES",
    "sg:address":"Calle de Toledo, 148",
    "sg:city":"Sonseca",
    "sg:orig_category":"Creaci\u00d3n De Sitios, Hosting Internet",
    "sg:phone":"+34 925 38 33 35",
    "sg:postcode":"45100",
    "sg:province":"Toledo",
    "wof:name":"Moreno Martin Victoriano",
    "wof:placetype":"venue"
},
  "geometry": {"coordinates":[-3.9769890308,39.6818313599],"type":"Point"}
}