{
  "type": "Feature",
  "properties": {
    "iso:country":"ES",
    "sg:address":"Calle de Tribaldos, 11",
    "sg:city":"Madrid",
    "sg:orig_category":"Masajistas Kinesiterapeutas",
    "sg:phone":"+34 913 88 01 05",
    "sg:postcode":"28043",
    "sg:province":"Madrid",
    "wof:name":"Carranco Molina Antonio",
    "wof:placetype":"venue"
},
  "geometry": {"coordinates":[-3.6332778931,40.4675445557],"type":"Point"}
}