{
  "type": "Feature",
  "properties": {
    "addr:full":"Trva Orense, S/n Astillero Cantabria 39610",
    "addr:housenumber":"s",
    "addr:postcode":"39610",
    "addr:street":"Trva Orense;/ N",
    "iso:country":"ES",
    "sg:address":"Trva Orense, S/n",
    "sg:city":"Astillero",
    "sg:orig_category":"Peluquer\u00cdas, Peluquer\u00cda Mixta",
    "sg:phone":"+34 942 54 02 70",
    "sg:postcode":"39610",
    "sg:province":"Cantabria",
    "wof:name":"Jorrin Allende Ana Isabel",
    "wof:placetype":"venue"
},
  "geometry": {"coordinates":[-3.8205389977,43.3996810913],"type":"Point"}
}