{
  "type": "Feature",
  "properties": {
    "iso:country":"ES",
    "sg:address":"Av Jaume I, 57",
    "sg:city":"Mollet Valles",
    "sg:orig_category":"Molduras, Junquillos, Listones Y Molduras Perforadas",
    "sg:phone":"+34 935 93 26 81",
    "sg:postcode":"08100",
    "sg:province":"Barcelona",
    "wof:name":"Restauracion La Pera S.l.",
    "wof:placetype":"venue"
},
  "geometry": {"coordinates":[2.2128379345,41.5397644043],"type":"Point"}
}