{
  "type": "Feature",
  "properties": {
    "addr:full":"Pg Almogavers, 26 Sabadell Barcelona 08204",
    "addr:housenumber":"26",
    "addr:postcode":"08204",
    "addr:street":"Pg Almogavers",
    "iso:country":"ES",
    "sg:address":"Pg Almogavers, 26",
    "sg:city":"Sabadell",
    "sg:orig_category":"Zapatos (al Por Menor)",
    "sg:phone":"+34 937 10 33 73",
    "sg:postcode":"08204",
    "sg:province":"Barcelona",
    "wof:name":"Barragan Y Jimenez S.c.p.",
    "wof:placetype":"venue"
},
  "geometry": {"coordinates":[2.1183741093,41.5293273926],"type":"Point"}
}