{
  "type": "Feature",
  "properties": {
    "iso:country":"ES",
    "sg:address":"Calle de Resina, 37",
    "sg:city":"Madrid",
    "sg:orig_category":"Alquiler De Veh\u00cdculos: Turismos Y Utilitarios",
    "sg:phone":"+34 917 23 01 22",
    "sg:postcode":"28021",
    "sg:province":"Madrid",
    "sg:website":"www.logicaplaniservi.com.es",
    "wof:name":"Logica Planificacionyservicios Sl",
    "wof:placetype":"venue"
},
  "geometry": {"coordinates":[-3.7048370838,40.3353309631],"type":"Point"}
}