{
  "type": "Feature",
  "properties": {
    "iso:country":"ES",
    "sg:address":"Plaz Galicia (de), 37",
    "sg:city":"Mosteiro",
    "sg:orig_category":"Empresarios",
    "sg:phone":"+34 982 34 51 56",
    "sg:postcode":"27270",
    "sg:province":"Lugo",
    "wof:name":"Lopez Rodriguez Manuel",
    "wof:placetype":"venue"
},
  "geometry": {"coordinates":[-7.3522891998,43.1285438538],"type":"Point"}
}