{
  "type": "Feature",
  "properties": {
    "iso:country":"ES",
    "sg:address":"Trva Plaza, 11",
    "sg:city":"Ojos Negros",
    "sg:orig_category":"Restaurantes",
    "sg:phone":"+34 978 86 52 12",
    "sg:postcode":"44313",
    "sg:province":"Teruel",
    "wof:name":"Sanchez Majuelos Juan Antonio",
    "wof:placetype":"venue"
},
  "geometry": {"coordinates":[-1.4996789694,40.7374191284],"type":"Point"}
}