{
  "type": "Feature",
  "properties": {
    "iso:country":"ES",
    "sg:address":"Calle de Doctor Pio Del Rio Hortega, 6",
    "sg:city":"Portillo",
    "sg:orig_category":"Reposter\u00cdas",
    "sg:phone":"+34 983 55 60 13",
    "sg:postcode":"47160",
    "sg:province":"Valladolid",
    "wof:name":"Sanz Velasco Deodoro",
    "wof:placetype":"venue"
},
  "geometry": {"coordinates":[-4.5893688202,41.4790802002],"type":"Point"}
}