{
  "type": "Feature",
  "properties": {
    "iso:country":"ES",
    "sg:address":"Carrer de Nacio, 24",
    "sg:city":"Barcelona",
    "sg:orig_category":"Iglesias Evang\u00c9licas",
    "sg:phone":"+34 934 35 17 63",
    "sg:postcode":"08026",
    "sg:province":"Barcelona",
    "wof:name":"Iglesia Evangelica Espa\u00f1ola",
    "wof:placetype":"venue"
},
  "geometry": {"coordinates":[2.1855590343,41.413028717],"type":"Point"}
}