{
  "type": "Feature",
  "properties": {
    "iso:country":"ES",
    "sg:address":"Carrer de Riera Baixa, 12",
    "sg:city":"Barcelona",
    "sg:orig_category":"Complementos De Vestir (al Por Menor)",
    "sg:phone":"+34 934 41 01 94",
    "sg:postcode":"08001",
    "sg:province":"Barcelona",
    "sg:website":"www.zerobcn.com",
    "wof:name":"Ruiz Cubillo Miguel Angel",
    "wof:placetype":"venue"
},
  "geometry": {"coordinates":[2.1683120728,41.3803710938],"type":"Point"}
}