{
  "type": "Feature",
  "properties": {
    "addr:full":"Urb. Isla, S/n Nueva Andalucia M\u00e1laga 29660",
    "addr:postcode":"29660",
    "addr:street":"Isla S / N;Ma\u0301Laga",
    "iso:country":"ES",
    "sg:address":"Urb. Isla, S/n",
    "sg:city":"Nueva Andalucia",
    "sg:orig_category":"Centros Empresariales",
    "sg:phone":"+34 952 81 60 08",
    "sg:postcode":"29660",
    "sg:province":"M\u00e1laga",
    "wof:name":"Mercuri Business Partner Oy",
    "wof:placetype":"venue"
},
  "geometry": {"coordinates":[-4.9572491646,36.4902381897],"type":"Point"}
}