{
  "type": "Feature",
  "properties": {
    "addr:full":"Calle de Salvador Cardells, 11 Vall D'uixo Castell\u00f3n 12600",
    "addr:housenumber":"11",
    "addr:postcode":"12600",
    "addr:street":"Calle De Salvador Cardells",
    "iso:country":"ES",
    "sg:address":"Calle de Salvador Cardells, 11",
    "sg:city":"Vall D'uixo",
    "sg:orig_category":"Institutos De Belleza",
    "sg:phone":"+34 964 69 13 88",
    "sg:postcode":"12600",
    "sg:province":"Castell\u00f3n",
    "wof:name":"Rodriguez Gonzalez Maria Del Rosario",
    "wof:placetype":"venue"
},
  "geometry": {"coordinates":[-0.0482099988,39.992477417],"type":"Point"}
}