{
  "type": "Feature",
  "properties": {
    "addr:full":"Rbla Rambla, 25 Figueres Girona 17600",
    "addr:housenumber":"25",
    "addr:postcode":"17600",
    "addr:street":"Rambla",
    "iso:country":"ES",
    "sg:address":"Rbla Rambla, 25",
    "sg:city":"Figueres",
    "sg:orig_category":"Abogados",
    "sg:phone":"+34 972 67 32 56",
    "sg:postcode":"17600",
    "sg:province":"Girona",
    "wof:name":"Junyer & Ramis, Associats C.b.",
    "wof:placetype":"venue"
},
  "geometry": {"coordinates":[2.9608099461,42.266040802],"type":"Point"}
}