{
  "type": "Feature",
  "properties": {
    "addr:full":"Av Paisos Catalans, 160 Reus Tarragona 43205",
    "addr:housenumber":"160",
    "addr:postcode":"43205",
    "addr:street":"Av Paisos Catalans",
    "iso:country":"ES",
    "sg:address":"Av Paisos Catalans, 160",
    "sg:city":"Reus",
    "sg:orig_category":"Reposter\u00cdas",
    "sg:phone":"+34 977 31 26 03",
    "sg:postcode":"43205",
    "sg:province":"Tarragona",
    "wof:name":"Morales Linares Soledad",
    "wof:placetype":"venue"
},
  "geometry": {"coordinates":[1.0988260508,41.1484565735],"type":"Point"}
}