{
  "type": "Feature",
  "properties": {
    "addr:full":"Calle de Camareros (los), S/n San Lorenzo De El Escorial Madrid 28200",
    "addr:housenumber":"s / n",
    "addr:postcode":"28200",
    "addr:street":"Calle De Camareros Los",
    "iso:country":"ES",
    "sg:address":"Calle de Camareros (los), S/n",
    "sg:city":"San Lorenzo De El Escorial",
    "sg:orig_category":"Transportes Por Carretera: Lotes Completos, Mercanc\u00cdas Diversas",
    "sg:phone":"+34 918 90 30 11",
    "sg:postcode":"28200",
    "sg:province":"Madrid",
    "wof:name":"Prodesco S.a.",
    "wof:placetype":"venue"
},
  "geometry": {"coordinates":[-4.1295104027,40.6018981934],"type":"Point"}
}