{
  "type": "Feature",
  "properties": {
    "addr:full":"H. Soto, 3 Valdesalor C\u00e1ceres 10164",
    "addr:postcode":"10164",
    "addr:street":"Ca\u0301Ceres",
    "iso:country":"ES",
    "sg:address":"H. Soto, 3",
    "sg:city":"Valdesalor",
    "sg:orig_category":"Agencias Y Agentes Comerciales, Representantes",
    "sg:phone":"+34 927 12 97 47",
    "sg:postcode":"10164",
    "sg:province":"C\u00e1ceres",
    "wof:name":"Polo Casares Pedro",
    "wof:placetype":"venue"
},
  "geometry": {"coordinates":[-6.3476691246,39.3777618408],"type":"Point"}
}