{
  "type": "Feature",
  "properties": {
    "addr:full":"Partida Michanet, 40 Torres Alicante 03570",
    "addr:housenumber":"40",
    "addr:postcode":"03570",
    "addr:street":"Partida Michanet",
    "iso:country":"ES",
    "sg:address":"Partida Michanet, 40",
    "sg:city":"Torres",
    "sg:orig_category":"Promotores Constructores",
    "sg:phone":"+34 966 85 13 44",
    "sg:postcode":"03570",
    "sg:province":"Alicante",
    "wof:name":"Ferrandiz Ferrandiz Miguel",
    "wof:placetype":"venue"
},
  "geometry": {"coordinates":[-0.2327190042,38.505821228],"type":"Point"}
}