{
  "type": "Feature",
  "properties": {
    "iso:country":"ES",
    "sg:address":"Rua Principe, 42",
    "sg:city":"Vigo",
    "sg:orig_category":"Ingenier\u00cda, Centros De Estudios (diversos)",
    "sg:phone":"+34 986 44 24 05",
    "sg:postcode":"36202",
    "sg:province":"Pontevedra",
    "wof:name":"Cnv Naval Architects S.l.",
    "wof:placetype":"venue"
},
  "geometry": {"coordinates":[-8.7221288681,42.2364807129],"type":"Point"}
}