{
  "type": "Feature",
  "properties": {
    "iso:country":"ES",
    "sg:address":"Plaz Principes De Espa\u00d1a, 32",
    "sg:city":"Alcorcon",
    "sg:orig_category":"Importaci\u00d3n",
    "sg:phone":"+34 916 19 13 62",
    "sg:postcode":"28924",
    "sg:province":"Madrid",
    "wof:name":"Fidalgo Perez Carlos",
    "wof:placetype":"venue"
},
  "geometry": {"coordinates":[-3.818846941,40.3506736755],"type":"Point"}
}