{
  "type": "Feature",
  "properties": {
    "iso:country":"ES",
    "sg:address":"Carrer de Mascaro, 4",
    "sg:city":"Barcelona",
    "sg:orig_category":"Molduras, Junquillos, Listones Y Molduras Perforadas",
    "sg:phone":"+34 934 35 50 62",
    "sg:postcode":"08032",
    "sg:province":"Barcelona",
    "wof:name":"Morena Garcia Gregorio De La",
    "wof:placetype":"venue"
},
  "geometry": {"coordinates":[2.1753070354,41.4253616333],"type":"Point"}
}