{
  "type": "Feature",
  "properties": {
    "iso:country":"ES",
    "sg:address":"Calle de Hilarion Eslava, 55",
    "sg:city":"Madrid",
    "sg:orig_category":"M\u00c9dicos: Cardiolog\u00cda Y Afecciones Cardiovasculares",
    "sg:phone":"+34 915 44 21 85",
    "sg:postcode":"28015",
    "sg:province":"Madrid",
    "wof:name":"Batlle Perez Maurice",
    "wof:placetype":"venue"
},
  "geometry": {"coordinates":[-3.7165780067,40.4387893677],"type":"Point"}
}