{
  "type": "Feature",
  "properties": {
    "addr:full":"Pl. Parterre, 1 Madrid Madrid 28044",
    "addr:housenumber":"1",
    "addr:postcode":"28044",
    "addr:street":"Parterre",
    "iso:country":"ES",
    "sg:address":"Pl. Parterre, 1",
    "sg:city":"Madrid",
    "sg:orig_category":"Librer\u00cdas",
    "sg:phone":"+34 915 25 26 24",
    "sg:postcode":"28044",
    "sg:province":"Madrid",
    "wof:name":"Tierno Ropero Felipe",
    "wof:placetype":"venue"
},
  "geometry": {"coordinates":[-3.7498130798,40.37657547],"type":"Point"}
}