{
  "type": "Feature",
  "properties": {
    "iso:country":"ES",
    "sg:address":"Calle de Pedro Menendez De, 8",
    "sg:city":"Aviles",
    "sg:orig_category":"Confecci\u00d3n : Material, Suministros Y Accesorios",
    "sg:phone":"+34 985 56 27 27",
    "sg:postcode":"33401",
    "sg:province":"Asturias",
    "wof:name":"Tres Riera C.b.",
    "wof:placetype":"venue"
},
  "geometry": {"coordinates":[-5.9234528542,43.5584907532],"type":"Point"}
}