{
  "type": "Feature",
  "properties": {
    "addr:full":"Calle de Veracruz, 12 Ogijares Granada 18151",
    "addr:housenumber":"12",
    "addr:postcode":"18151",
    "addr:street":"Calle De Veracruz",
    "iso:country":"ES",
    "sg:address":"Calle de Veracruz, 12",
    "sg:city":"Ogijares",
    "sg:orig_category":"Congelados: Productos Alimentarios (al Por Menor)",
    "sg:phone":"+34 958 50 33 59",
    "sg:postcode":"18151",
    "sg:province":"Granada",
    "wof:name":"Congelados El Veleta S.l.",
    "wof:placetype":"venue"
},
  "geometry": {"coordinates":[-3.6075749397,37.1199302673],"type":"Point"}
}