{
  "type": "Feature",
  "properties": {
    "addr:full":"Ctra Barcelona, 58 Centre Urba Girona 17500",
    "addr:housenumber":"58",
    "addr:postcode":"17500",
    "addr:street":"Ctra Barcelona;Centre Urba",
    "iso:country":"ES",
    "sg:address":"Ctra Barcelona, 58",
    "sg:city":"Centre Urba",
    "sg:orig_category":"Alquiler De V\u00cddeo",
    "sg:phone":"+34 972 70 25 08",
    "sg:postcode":"17500",
    "sg:province":"Girona",
    "wof:name":"Ziga-zaga Ripolles Slu",
    "wof:placetype":"venue"
},
  "geometry": {"coordinates":[2.8236999512,41.9817962646],"type":"Point"}
}