{
  "type": "Feature",
  "properties": {
    "addr:full":"Calle de Hernan Cortes, 40 Santander Cantabria 39003",
    "addr:housenumber":"40",
    "addr:postcode":"39003",
    "addr:street":"Calle De Hernan Cortes",
    "iso:country":"ES",
    "sg:address":"Calle de Hernan Cortes, 40",
    "sg:city":"Santander",
    "sg:orig_category":"Hoteles",
    "sg:phone":"+34 942 31 47 69",
    "sg:postcode":"39003",
    "sg:province":"Cantabria",
    "wof:name":"Revuelta Campos Santiago",
    "wof:placetype":"venue"
},
  "geometry": {"coordinates":[-3.7974009514,43.4629898071],"type":"Point"}
}