{
  "type": "Feature",
  "properties": {
    "addr:full":"Mas Pla, S/n Vilamari Girona 17468",
    "addr:postcode":"17468",
    "addr:street":"Pla S / N Vilamari",
    "iso:country":"ES",
    "sg:address":"Mas Pla, S/n",
    "sg:city":"Vilamari",
    "sg:orig_category":"Agricultores, Agricultores",
    "sg:phone":"+34 972 56 01 07",
    "sg:postcode":"17468",
    "sg:province":"Girona",
    "wof:name":"Modulargrcsystems Mgs S.l.",
    "wof:placetype":"venue"
},
  "geometry": {"coordinates":[2.8884160519,42.1389427185],"type":"Point"}
}