{
  "type": "Feature",
  "properties": {
    "iso:country":"ES",
    "sg:address":"Carretera De Jatar, Km. 0002,0",
    "sg:city":"Alhama Granada",
    "sg:orig_category":"Alquiler De Casas Y Habitaciones Amuebladas",
    "sg:phone":"+34 958 35 04 38",
    "sg:postcode":"18120",
    "sg:province":"Granada",
    "wof:name":"El Ventorro Turismo Rural S.c.a.",
    "wof:placetype":"venue"
},
  "geometry": {"coordinates":[-3.9909889698,37.0056495667],"type":"Point"}
}