{
  "type": "Feature",
  "properties": {
    "addr:full":"Calle de Gran Via, 45 Madrid Madrid 28013",
    "addr:housenumber":"45",
    "addr:postcode":"madrid;28013",
    "addr:street":"Calle De Gran Via",
    "iso:country":"ES",
    "sg:address":"Calle de Gran Via, 45",
    "sg:city":"Madrid",
    "sg:orig_category":"Contables",
    "sg:phone":"+34 915 59 46 63",
    "sg:postcode":"28013",
    "sg:province":"Madrid",
    "wof:name":"Latorre Revilla Maria Isabel",
    "wof:placetype":"venue"
},
  "geometry": {"coordinates":[-3.7073578835,40.4210510254],"type":"Point"}
}