{
  "type": "Feature",
  "properties": {
    "addr:full":"Calle de Cerrada, 14 Valladolid Valladolid 47010",
    "addr:housenumber":"14",
    "addr:postcode":"47010",
    "addr:street":"Calle De Cerrada",
    "iso:country":"ES",
    "sg:address":"Calle de Cerrada, 14",
    "sg:city":"Valladolid",
    "sg:orig_category":"Zapatos (al Por Menor)",
    "sg:phone":"+34 983 26 81 78",
    "sg:postcode":"47010",
    "sg:province":"Valladolid",
    "wof:name":"Libertad 4 Sport S.l.",
    "wof:placetype":"venue"
},
  "geometry": {"coordinates":[-4.7208170891,41.6604194641],"type":"Point"}
}