{
  "type": "Feature",
  "properties": {
    "addr:full":"Santa Marina, 3 Vandellos Tarragona 43891",
    "addr:housenumber":"3",
    "addr:postcode":"43891",
    "addr:street":"Santa Marina",
    "iso:country":"ES",
    "sg:address":"Santa Marina, 3",
    "sg:city":"Vandellos",
    "sg:orig_category":"Aceites Y Grasas Alimentarias (fabricaci\u00d3n, Al Por Mayor)",
    "sg:phone":"+34 977 82 40 16",
    "sg:postcode":"43891",
    "sg:province":"Tarragona",
    "wof:name":"Gil Castellvi Jose",
    "wof:placetype":"venue"
},
  "geometry": {"coordinates":[0.8332380056,41.0206413269],"type":"Point"}
}