{
  "type": "Feature",
  "properties": {
    "iso:country":"ES",
    "sg:address":"Calle de Camarena, 106",
    "sg:city":"Madrid",
    "sg:orig_category":"Electricidad: Instaladores",
    "sg:phone":"+34 915 09 98 87",
    "sg:postcode":"28047",
    "sg:province":"Madrid",
    "wof:name":"Instalaciones Electricas Juan Carlos Sanz S.l.",
    "wof:placetype":"venue"
},
  "geometry": {"coordinates":[-3.7572584152,40.3925361633],"type":"Point"}
}