{
  "type": "Feature",
  "properties": {
    "iso:country":"ES",
    "sg:address":"Calle de Puentes (los), 6",
    "sg:city":"Arenas -areeta",
    "sg:orig_category":"Fabricaci\u00d3n, Venta De Cuadros, Accesorios Para Enmarcar",
    "sg:phone":"+34 944 64 19 14",
    "sg:postcode":"48930",
    "sg:province":"Vizcaya",
    "wof:name":"Ibarrondo Berasaluce Miguel Angel",
    "wof:placetype":"venue"
},
  "geometry": {"coordinates":[-3.0080509186,43.3294906616],"type":"Point"}
}