{
  "type": "Feature",
  "properties": {
    "addr:full":"Cra Espinel, 7 Ronda M\u00e1laga 29400",
    "addr:postcode":"29400",
    "addr:street":"Espinel;Ronda Ma\u0301Laga",
    "iso:country":"ES",
    "sg:address":"Cra Espinel, 7",
    "sg:city":"Ronda",
    "sg:orig_category":"Electrodom\u00c9sticos (al Por Menor)",
    "sg:phone":"+34 952 87 19 83",
    "sg:postcode":"29400",
    "sg:province":"M\u00e1laga",
    "wof:name":"Comercial Electrica Ronde\u00f1a S. L.",
    "wof:placetype":"venue"
},
  "geometry": {"coordinates":[-5.1659297943,36.7424812317],"type":"Point"}
}