{
  "type": "Feature",
  "properties": {
    "iso:country":"ES",
    "sg:address":"Calle de San Francisco, 3",
    "sg:city":"Cartagena",
    "sg:orig_category":"Asesor\u00cda Fiscal Y Jur\u00cddica",
    "sg:phone":"+34 968 12 22 48",
    "sg:postcode":"30202",
    "sg:province":"Murcia",
    "wof:name":"Torres Del Rey Jorge",
    "wof:placetype":"venue"
},
  "geometry": {"coordinates":[-0.9844049811,37.6017379761],"type":"Point"}
}