{
  "type": "Feature",
  "properties": {
    "iso:country":"ES",
    "sg:address":"Plaz Puente De Ronda, 6",
    "sg:city":"Marbella",
    "sg:orig_category":"Servicios De Telecomunicaciones",
    "sg:phone":"+34 952 82 44 88",
    "sg:postcode":"29600",
    "sg:province":"M\u00e1laga",
    "wof:name":"Alvarez Logullo Marian Nazareth",
    "wof:placetype":"venue"
},
  "geometry": {"coordinates":[-4.8853793144,36.5109214783],"type":"Point"}
}