{
  "type": "Feature",
  "properties": {
    "addr:full":"Carrer de Carrer de Pto Rico, 18 Puerto Rico Las Palmas 35130",
    "addr:housenumber":"18",
    "addr:postcode":"35130",
    "addr:street":"Carrer;Carrer De;Puerto Rico Las",
    "iso:country":"ES",
    "sg:address":"Carrer de Carrer de Pto Rico, 18",
    "sg:city":"Puerto Rico",
    "sg:orig_category":"Molduras, Junquillos, Listones Y Molduras Perforadas",
    "sg:phone":"+34 928 56 21 85",
    "sg:postcode":"35130",
    "sg:province":"Las Palmas",
    "wof:name":"Cambell  Joseph",
    "wof:placetype":"venue"
},
  "geometry": {"coordinates":[-13.9036235809,28.6303958893],"type":"Point"}
}