{
  "type": "Feature",
  "properties": {
    "iso:country":"ES",
    "sg:address":"Calle de San Andres, 8",
    "sg:city":"Zaragoza",
    "sg:orig_category":"Granos Y Semillas (producci\u00d3n, Al Por Mayor)",
    "sg:phone":"+34 976 39 96 43",
    "sg:postcode":"50001",
    "sg:province":"Zaragoza",
    "wof:name":"Perulan Gracia Felix Segundo",
    "wof:placetype":"venue"
},
  "geometry": {"coordinates":[-0.8788501024,41.6522979736],"type":"Point"}
}