{
  "type": "Feature",
  "properties": {
    "addr:full":"Avda Dolores Mosquera, 18 Caldas De Reis Pontevedra 36650",
    "addr:housenumber":"18",
    "addr:postcode":"36650",
    "addr:street":"Avda Dolores Mosquera",
    "iso:country":"ES",
    "sg:address":"Avda Dolores Mosquera, 18",
    "sg:city":"Caldas De Reis",
    "sg:orig_category":"Transportes Por Carretera: Lotes Completos, Mercanc\u00cdas Diversas",
    "sg:phone":"+34 986 53 00 97",
    "sg:postcode":"36650",
    "sg:province":"Pontevedra",
    "wof:name":"Supermercado Chayan S.l.",
    "wof:placetype":"venue"
},
  "geometry": {"coordinates":[-8.6451597214,42.6077156067],"type":"Point"}
}