{
  "type": "Feature",
  "properties": {
    "addr:full":"Avda Juan Carlos I, 55 Merida Badajoz 06800",
    "addr:housenumber":"55",
    "addr:postcode":"06800",
    "addr:street":"Avda Juan Carlos I",
    "iso:country":"ES",
    "sg:address":"Avda Juan Carlos I, 55",
    "sg:city":"Merida",
    "sg:orig_category":"Carnicer\u00cdas, Carnicer\u00cdas",
    "sg:phone":"+34 924 31 19 81",
    "sg:postcode":"06800",
    "sg:province":"Badajoz",
    "wof:name":"Yuste Padin Miguel Angel",
    "wof:placetype":"venue"
},
  "geometry": {"coordinates":[-6.3349409103,38.9199104309],"type":"Point"}
}