{
  "type": "Feature",
  "properties": {
    "addr:full":"Carr Alacant, 6 Girona Girona 17005",
    "addr:housenumber":"6",
    "addr:postcode":"17005",
    "addr:street":"Carr Alacant",
    "iso:country":"ES",
    "sg:address":"Carr Alacant, 6",
    "sg:city":"Girona",
    "sg:orig_category":"Ambulancias",
    "sg:phone":"+34 972 24 49 67",
    "sg:postcode":"17005",
    "sg:province":"Girona",
    "wof:name":"Consorci Del Transport Sanitari Regio Girona S.a.",
    "wof:placetype":"venue"
},
  "geometry": {"coordinates":[2.8116340637,41.9680633545],"type":"Point"}
}