{
  "type": "Feature",
  "properties": {
    "addr:full":"Calle de Paz, 18 Valencia Valencia 46003",
    "addr:housenumber":"18",
    "addr:postcode":"46003",
    "addr:street":"Calle De Paz",
    "iso:country":"ES",
    "sg:address":"Calle de Paz, 18",
    "sg:city":"Valencia",
    "sg:orig_category":"Caf\u00c9s, Bares, Cervecer\u00cdas",
    "sg:phone":"+34 963 52 72 61",
    "sg:postcode":"46003",
    "sg:province":"Valencia",
    "wof:name":"Fast Cargo De Mexico S.l.",
    "wof:placetype":"venue"
},
  "geometry": {"coordinates":[-0.3769130111,39.4687919617],"type":"Point"}
}