{
  "type": "Feature",
  "properties": {
    "iso:country":"ES",
    "sg:address":"Ctra Santa Pola, Km. 0023,0",
    "sg:city":"Elche",
    "sg:orig_category":"Fabrica De Cer\u00c1micas",
    "sg:phone":"+34 966 63 80 72",
    "sg:postcode":"03203",
    "sg:province":"Alicante",
    "wof:name":"Alameda Garcia Jesus",
    "wof:placetype":"venue"
},
  "geometry": {"coordinates":[-0.6848735213,38.2665252686],"type":"Point"}
}