{
  "type": "Feature",
  "properties": {
    "iso:country":"ES",
    "sg:address":"Avda Real De Pinto, 87",
    "sg:city":"Madrid",
    "sg:orig_category":"Soportes L\u00d3gicos, Programas Integradores De Aplicaciones (progiciels)",
    "sg:phone":"+34 917 96 34 92",
    "sg:postcode":"28021",
    "sg:province":"Madrid",
    "wof:name":"Alarcon Jimenez Miguel",
    "wof:placetype":"venue"
},
  "geometry": {"coordinates":[-3.7113289833,40.3362083435],"type":"Point"}
}