{
  "type": "Feature",
  "properties": {
    "addr:full":"Pase Sherry (del), S/n Costa Oeste C\u00e1diz 11500",
    "addr:housenumber":"s / n",
    "addr:postcode":"11500",
    "addr:street":"Costa Oeste Ca\u0301Diz",
    "iso:country":"ES",
    "sg:address":"Pase Sherry (del), S/n",
    "sg:city":"Costa Oeste",
    "sg:orig_category":"Farmacias",
    "sg:phone":"+34 956 87 28 03",
    "sg:postcode":"11500",
    "sg:province":"C\u00e1diz",
    "wof:name":"Ordo\u00f1ez Morejon Maria Victoria",
    "wof:placetype":"venue"
},
  "geometry": {"coordinates":[-6.2197542191,36.6056632996],"type":"Point"}
}