{
  "type": "Feature",
  "properties": {
    "addr:full":"Rbla Rambla Nova, 37 Tarragona Tarragona 43003",
    "addr:housenumber":"37",
    "addr:postcode":"43003",
    "addr:street":"Rambla Nova",
    "iso:country":"ES",
    "sg:address":"Rbla Rambla Nova, 37",
    "sg:city":"Tarragona",
    "sg:orig_category":"Cajas De Ahorro",
    "sg:phone":"+34 977 24 96 57",
    "sg:postcode":"43003",
    "sg:province":"Tarragona",
    "wof:name":"Caixa D'estalvis De Catalunya",
    "wof:placetype":"venue"
},
  "geometry": {"coordinates":[1.2541049719,41.1169281006],"type":"Point"}
}