{
  "type": "Feature",
  "properties": {
    "iso:country":"ES",
    "sg:address":"Ctra N-iv Madrid-cadiz, Km. 0118,0",
    "sg:city":"Madridejos",
    "sg:orig_category":"Muebles, Minoristas",
    "sg:phone":"+34 925 46 36 26",
    "sg:postcode":"45710",
    "sg:province":"Toledo",
    "wof:name":"Almena Decoracion S.l.",
    "wof:placetype":"venue"
},
  "geometry": {"coordinates":[-3.5205640793,39.4953804016],"type":"Point"}
}