{
  "type": "Feature",
  "properties": {
    "iso:country":"ES",
    "sg:address":"Carrer de Castello, 15",
    "sg:city":"S. Boi Llobregat",
    "sg:orig_category":"Fabricaci\u00d3n De Quesos",
    "sg:phone":"+34 936 52 17 50",
    "sg:postcode":"08830",
    "sg:province":"Barcelona",
    "wof:name":"Industrial Quesera Cuquerella S.l.",
    "wof:placetype":"venue"
},
  "geometry": {"coordinates":[2.0440518856,41.3456344604],"type":"Point"}
}