{
  "type": "Feature",
  "properties": {
    "iso:country":"ES",
    "sg:address":"Cra. Vall D'aran, S/n",
    "sg:city":"Alguaire",
    "sg:orig_category":"Frutas Y Legumbres Frescas (al Por Mayor)",
    "sg:phone":"+34 973 75 61 68",
    "sg:postcode":"25125",
    "sg:province":"Lleida",
    "wof:name":"Eurofruit S.c.c.l.",
    "wof:placetype":"venue"
},
  "geometry": {"coordinates":[0.5604199767,41.7382888794],"type":"Point"}
}