{
  "type": "Feature",
  "properties": {
    "iso:country":"ES",
    "sg:address":"Plaz Mayor, 6",
    "sg:city":"Segovia",
    "sg:orig_category":"Oficinas De Turismo, Asociaciones De Iniciativa",
    "sg:phone":"+34 921 46 04 92",
    "sg:postcode":"40001",
    "sg:province":"Segovia",
    "sg:website":"www.infosegovia.com",
    "wof:name":"Patronato Provincial De Turismo",
    "wof:placetype":"venue"
},
  "geometry": {"coordinates":[-4.1239271164,40.9505958557],"type":"Point"}
}