{
  "type": "Feature",
  "properties": {
    "addr:full":"El Mohino, S/n La Jara C\u00f3rdoba 14700",
    "addr:housenumber":"s / n",
    "addr:postcode":"14700",
    "addr:street":"El Mohino",
    "iso:country":"ES",
    "sg:address":"El Mohino, S/n",
    "sg:city":"La Jara",
    "sg:orig_category":"Ense\u00d1anza, Formaci\u00d3n Profesional: Aprendizaje",
    "sg:phone":"+34 957 64 34 91",
    "sg:postcode":"14700",
    "sg:province":"C\u00f3rdoba",
    "wof:name":"Junta De Andalucia-consejeria De Cultura",
    "wof:placetype":"venue"
},
  "geometry": {"coordinates":[-5.2795991898,37.7004241943],"type":"Point"}
}