{
  "type": "Feature",
  "properties": {
    "addr:full":"Calle de San Pol De Mar, 6 Madrid Madrid 28008",
    "addr:housenumber":"6",
    "addr:postcode":"28008",
    "addr:street":"Calle De San Pol De Mar",
    "iso:country":"ES",
    "sg:address":"Calle de San Pol De Mar, 6",
    "sg:city":"Madrid",
    "sg:orig_category":"Perfumer\u00cda (al Por Menor)",
    "sg:phone":"+34 915 47 31 93",
    "sg:postcode":"28008",
    "sg:province":"Madrid",
    "wof:name":"Colas Julian Miguel",
    "wof:placetype":"venue"
},
  "geometry": {"coordinates":[-3.7275578976,40.4240531921],"type":"Point"}
}