{
  "type": "Feature",
  "properties": {
    "addr:full":"Avda Almozara, 14 Zaragoza Zaragoza 50003",
    "addr:housenumber":"14",
    "addr:postcode":"50003",
    "addr:street":"Avda Almozara",
    "iso:country":"ES",
    "sg:address":"Avda Almozara, 14",
    "sg:city":"Zaragoza",
    "sg:orig_category":"Peluqueros: De Se\u00d1oras",
    "sg:phone":"+34 976 44 43 55",
    "sg:postcode":"50003",
    "sg:province":"Zaragoza",
    "wof:name":"Garrido Busto Isabel",
    "wof:placetype":"venue"
},
  "geometry": {"coordinates":[-0.8949580789,41.6602783203],"type":"Point"}
}