{
  "type": "Feature",
  "properties": {
    "addr:full":"Calle de Cardenal Mendoza, 44 Madrid Madrid 28011",
    "addr:housenumber":"44",
    "addr:postcode":"madrid;28011",
    "addr:street":"Calle De Cardenal Mendoza",
    "iso:country":"ES",
    "sg:address":"Calle de Cardenal Mendoza, 44",
    "sg:city":"Madrid",
    "sg:orig_category":"Peluquer\u00cdas, Peluquer\u00cda Mixta",
    "sg:phone":"+34 914 79 17 03",
    "sg:postcode":"28011",
    "sg:province":"Madrid",
    "wof:name":"Ruescas Ruiz-enen Jose Luis",
    "wof:placetype":"venue"
},
  "geometry": {"coordinates":[-3.7286164761,40.4119720459],"type":"Point"}
}