{
  "type": "Feature",
  "properties": {
    "iso:country":"ES",
    "sg:address":"Carrer de Valencia, 25",
    "sg:city":"Barcelona",
    "sg:orig_category":"Construcciones Met\u00c1licas",
    "sg:phone":"+34 932 26 48 83",
    "sg:postcode":"08015",
    "sg:province":"Barcelona",
    "wof:name":"Art.bm S.c.p.",
    "wof:placetype":"venue"
},
  "geometry": {"coordinates":[2.1476643085,41.3809242249],"type":"Point"}
}