{
  "type": "Feature",
  "properties": {
    "addr:full":"Calle de Carrera (la), 21 Santillana Cantabria 39330",
    "addr:housenumber":"21",
    "addr:postcode":"39330",
    "addr:street":"Calle De Carrera La",
    "iso:country":"ES",
    "sg:address":"Calle de Carrera (la), 21",
    "sg:city":"Santillana",
    "sg:orig_category":"Artesan\u00cda",
    "sg:phone":"+34 942 84 03 72",
    "sg:postcode":"39330",
    "sg:province":"Cantabria",
    "wof:name":"Michelena Marquina Miguel Angel",
    "wof:placetype":"venue"
},
  "geometry": {"coordinates":[-4.1087207794,43.3895492554],"type":"Point"}
}