{
  "type": "Feature",
  "properties": {
    "iso:country":"ES",
    "sg:address":"Cno. Casatejada, S/n",
    "sg:city":"Talayuela",
    "sg:orig_category":"Serrer\u00cdas De Madera",
    "sg:phone":"+34 927 55 10 72",
    "sg:postcode":"10310",
    "sg:province":"C\u00e1ceres",
    "wof:name":"Mu\u00f1oz Suarez Jesus",
    "wof:placetype":"venue"
},
  "geometry": {"coordinates":[-5.610019207,39.9897003174],"type":"Point"}
}