{
  "type": "Feature",
  "properties": {
    "iso:country":"ES",
    "sg:address":"Calle de Famara, 67",
    "sg:city":"Union",
    "sg:orig_category":"Chapister\u00cda",
    "sg:phone":"+34 928 75 12 26",
    "sg:postcode":"35110",
    "sg:province":"Las Palmas",
    "wof:name":"Cabrera Caballero Eligio",
    "wof:placetype":"venue"
},
  "geometry": {"coordinates":[-15.4485340118,27.8392906189],"type":"Point"}
}