{
  "type": "Feature",
  "properties": {
    "iso:country":"ES",
    "sg:address":"Carrer de Valencia, 188",
    "sg:city":"Barcelona",
    "sg:orig_category":"Perfumer\u00cda, Art\u00cdculos De Ba\u00d1o (fabricaci\u00d3n, Al Por Mayor)",
    "sg:phone":"+34 933 23 00 93",
    "sg:postcode":"08011",
    "sg:province":"Barcelona",
    "wof:name":"Hermanos Martin Carbo S.l.",
    "wof:placetype":"venue"
},
  "geometry": {"coordinates":[2.1571478844,41.3878707886],"type":"Point"}
}