{
  "type": "Feature",
  "properties": {
    "iso:country":"ES",
    "sg:address":"Rua Amil, 13",
    "sg:city":"Cambre",
    "sg:orig_category":"Mataderos Y Talleres De Despiezado",
    "sg:phone":"+34 981 67 45 41",
    "sg:postcode":"15660",
    "sg:province":"La Coru\u00f1a",
    "wof:name":"Gallega De Carnes S.a.",
    "wof:placetype":"venue"
},
  "geometry": {"coordinates":[-8.3466682434,43.2938461304],"type":"Point"}
}