{
  "type": "Feature",
  "properties": {
    "addr:full":"Calle de Francisco Merino, 21 Nueva-carteya C\u00f3rdoba 14857",
    "addr:housenumber":"21",
    "addr:postcode":"14857",
    "addr:street":"Calle De Francisco Merino;Co\u0301Rdoba",
    "iso:country":"ES",
    "sg:address":"Calle de Francisco Merino, 21",
    "sg:city":"Nueva-carteya",
    "sg:orig_category":"Droguer\u00cdas (al Por Menor)",
    "sg:phone":"+34 957 67 81 38",
    "sg:postcode":"14857",
    "sg:province":"C\u00f3rdoba",
    "wof:name":"Torres Moros Juan",
    "wof:placetype":"venue"
},
  "geometry": {"coordinates":[-4.4681091309,37.5838851929],"type":"Point"}
}