{
  "type": "Feature",
  "properties": {
    "addr:full":"Calle de Garcia Cabrelles, 71 Melilla Melilla 52002",
    "addr:housenumber":"71",
    "addr:postcode":"52002",
    "addr:street":"Calle De Garcia Cabrelles",
    "iso:country":"ES",
    "sg:address":"Calle de Garcia Cabrelles, 71",
    "sg:city":"Melilla",
    "sg:orig_category":"Transportes Por Carretera: Lotes Completos, Mercanc\u00cdas Diversas",
    "sg:phone":"+34 952 68 40 43",
    "sg:postcode":"52002",
    "sg:province":"Melilla",
    "wof:name":"Al-lal Hach Moh Mohamed",
    "wof:placetype":"venue"
},
  "geometry": {"coordinates":[-2.947201252,35.2975006104],"type":"Point"}
}