{
  "type": "Feature",
  "properties": {
    "addr:full":"Calle de Barbate, 5 Algeciras C\u00e1diz 11206",
    "addr:housenumber":"5;ca\u0301diz",
    "addr:postcode":"11206",
    "addr:street":"Calle De Barbate",
    "iso:country":"ES",
    "sg:address":"Calle de Barbate, 5",
    "sg:city":"Algeciras",
    "sg:orig_category":"M\u00c1quinas Y Herramientas Para Trabajar La Piedra",
    "sg:phone":"+34 956 57 00 78",
    "sg:postcode":"11206",
    "sg:province":"C\u00e1diz",
    "wof:name":"Morando Ruiz Angel",
    "wof:placetype":"venue"
},
  "geometry": {"coordinates":[-5.4536933899,36.1180381775],"type":"Point"}
}