{
  "type": "Feature",
  "properties": {
    "addr:full":"Calle de Juan Espa\u00d1ol, 52 Madrid Madrid 28026",
    "addr:housenumber":"52",
    "addr:postcode":"madrid;28026",
    "addr:street":"Calle De Juan Espan\u0303Ol",
    "iso:country":"ES",
    "sg:address":"Calle de Juan Espa\u00d1ol, 52",
    "sg:city":"Madrid",
    "sg:orig_category":"Peluqueros: De Se\u00d1oras",
    "sg:phone":"+34 915 69 31 89",
    "sg:postcode":"28026",
    "sg:province":"Madrid",
    "wof:name":"Martin Saez Julia",
    "wof:placetype":"venue"
},
  "geometry": {"coordinates":[-3.7140159607,40.3865280151],"type":"Point"}
}