{
  "type": "Feature",
  "properties": {
    "iso:country":"ES",
    "sg:address":"Avda Murcia (de), 2",
    "sg:city":"San Sebastian De Los Reyes",
    "sg:orig_category":"Persianas Interiores, Exteriores",
    "sg:phone":"+34 916 23 97 30",
    "sg:postcode":"28700",
    "sg:province":"Madrid",
    "wof:name":"Malmor Piquelme Enrique",
    "wof:placetype":"venue"
},
  "geometry": {"coordinates":[-3.6253190041,40.5473556519],"type":"Point"}
}