{
  "type": "Feature",
  "properties": {
    "addr:full":"Calle de Marques De Murrieta, 35 Logro\u00f1o La Rioja 26005",
    "addr:housenumber":"35",
    "addr:postcode":"26005",
    "addr:street":"Calle De Marques De Murrieta;Rioja",
    "iso:country":"ES",
    "sg:address":"Calle de Marques De Murrieta, 35",
    "sg:city":"Logro\u00f1o",
    "sg:orig_category":"Financiaci\u00d3n Y Cr\u00c9ditos",
    "sg:phone":"+34 941 20 03 78",
    "sg:postcode":"26005",
    "sg:province":"La Rioja",
    "wof:name":"Ascaso Jimenez Jesus",
    "wof:placetype":"venue"
},
  "geometry": {"coordinates":[-2.4567654133,42.4647903442],"type":"Point"}
}