{
  "type": "Feature",
  "properties": {
    "addr:full":"Viella, S/n Viella Asturias 33429",
    "addr:housenumber":"s / n",
    "addr:postcode":"33429",
    "addr:street":"Viella",
    "iso:country":"ES",
    "sg:address":"Viella, S/n",
    "sg:city":"Viella",
    "sg:orig_category":"Chapister\u00cda",
    "sg:phone":"+34 985 26 13 34",
    "sg:postcode":"33429",
    "sg:province":"Asturias",
    "wof:name":"Rellan Alvarez Jesus",
    "wof:placetype":"venue"
},
  "geometry": {"coordinates":[-5.9347338676,43.3889541626],"type":"Point"}
}