{
  "type": "Feature",
  "properties": {
    "iso:country":"ES",
    "sg:address":"Calle de Higinio Mangas, 1",
    "sg:city":"Valladolid",
    "sg:orig_category":"Peluquer\u00cdas, Peluquer\u00cda Mixta",
    "sg:phone":"+34 983 29 48 48",
    "sg:postcode":"47005",
    "sg:province":"Valladolid",
    "wof:name":"Gonzalez Pino Pedro",
    "wof:placetype":"venue"
},
  "geometry": {"coordinates":[-4.7126841545,41.6506156921],"type":"Point"}
}