{
  "type": "Feature",
  "properties": {
    "addr:full":"Carrer de Sant Honorat, 2 Terrassa Barcelona 08222",
    "addr:housenumber":"2",
    "addr:postcode":"08222",
    "addr:street":"Carrer De Sant Honorat",
    "iso:country":"ES",
    "sg:address":"Carrer de Sant Honorat, 2",
    "sg:city":"Terrassa",
    "sg:orig_category":"Librer\u00cdas",
    "sg:phone":"+34 937 85 87 38",
    "sg:postcode":"08222",
    "sg:province":"Barcelona",
    "wof:name":"Cayuela Mira Luis",
    "wof:placetype":"venue"
},
  "geometry": {"coordinates":[2.0273940563,41.5635261536],"type":"Point"}
}