{
  "type": "Feature",
  "properties": {
    "iso:country":"ES",
    "sg:address":"Pg Sant Joan, 25",
    "sg:city":"Barcelona",
    "sg:orig_category":"Estancos",
    "sg:phone":"+34 932 65 05 48",
    "sg:postcode":"08010",
    "sg:province":"Barcelona",
    "wof:name":"Permanyer Martinez Rosa Maria",
    "wof:placetype":"venue"
},
  "geometry": {"coordinates":[2.1776258945,41.3931274414],"type":"Point"}
}