{
  "type": "Feature",
  "properties": {
    "iso:country":"ES",
    "sg:address":"Calle de Iglesia, 6",
    "sg:city":"Barruecopardo",
    "sg:orig_category":"Iglesia Cat\u00d3lica",
    "sg:phone":"+34 923 50 80 96",
    "sg:postcode":"37255",
    "sg:province":"Salamanca",
    "wof:name":"Obispado De Ciudad Rodrigo",
    "wof:placetype":"venue"
},
  "geometry": {"coordinates":[-6.66670084,41.0725021362],"type":"Point"}
}