{
  "type": "Feature",
  "properties": {
    "iso:country":"ES",
    "sg:address":"G.v. Corts Catalanes, 684",
    "sg:city":"Barcelona",
    "sg:orig_category":"Abogados",
    "sg:phone":"+34 933 18 60 74",
    "sg:postcode":"08010",
    "sg:province":"Barcelona",
    "wof:name":"Pl-emp.i Fiscal S.l.",
    "wof:placetype":"venue"
},
  "geometry": {"coordinates":[2.173238039,41.3927192688],"type":"Point"}
}