{
  "type": "Feature",
  "properties": {
    "addr:full":"Paseo Cirilo Sagastagoitia, 14 Barakaldo Vizcaya 48903",
    "addr:housenumber":"14",
    "addr:postcode":"48903",
    "addr:street":"Paseo Cirilo Sagastagoitia",
    "iso:country":"ES",
    "sg:address":"Paseo Cirilo Sagastagoitia, 14",
    "sg:city":"Barakaldo",
    "sg:orig_category":"Contenedores (mercanc\u00cdas)",
    "sg:phone":"+34 944 85 09 59",
    "sg:postcode":"48903",
    "sg:province":"Vizcaya",
    "wof:name":"Trajema, S.c.l.",
    "wof:placetype":"venue"
},
  "geometry": {"coordinates":[-2.9816920757,43.2859573364],"type":"Point"}
}