{
  "type": "Feature",
  "properties": {
    "iso:country":"ES",
    "sg:address":"Rua Real, 11",
    "sg:city":"Ferrol",
    "sg:orig_category":"Librer\u00cdas",
    "sg:phone":"+34 981 32 81 08",
    "sg:postcode":"15402",
    "sg:province":"A Coru\u00f1a",
    "wof:name":"Santalla Vazquez Jose Luis",
    "wof:placetype":"venue"
},
  "geometry": {"coordinates":[-8.228890419,43.4855155945],"type":"Point"}
}