{
  "type": "Feature",
  "properties": {
    "iso:country":"ES",
    "sg:address":"Calle de Mar Jonico, 39",
    "sg:city":"Utrera",
    "sg:orig_category":"Quincaller\u00cda (al Por Menor)",
    "sg:phone":"+34 954 87 32 67",
    "sg:postcode":"41710",
    "sg:province":"Sevilla",
    "wof:name":"Ferreteria Y Fundiciones Rejola S.l.",
    "wof:placetype":"venue"
},
  "geometry": {"coordinates":[-5.7689981461,37.1902732849],"type":"Point"}
}