{
  "type": "Feature",
  "properties": {
    "iso:country":"ES",
    "sg:address":"Calle de San Leopoldo, 8",
    "sg:city":"Madrid",
    "sg:orig_category":"Molduras, Junquillos, Listones Y Molduras Perforadas",
    "sg:phone":"+34 917 33 93 54",
    "sg:postcode":"28029",
    "sg:province":"Madrid",
    "wof:name":"Fernandez Pastor Ramona Carmen",
    "wof:placetype":"venue"
},
  "geometry": {"coordinates":[-3.6901550293,40.4694404602],"type":"Point"}
}