{
  "type": "Feature",
  "properties": {
    "addr:full":"Avda Yeseros (de Los), 9 Valmor-rompecubas Madrid 28340",
    "addr:housenumber":"9",
    "addr:postcode":"28340",
    "addr:street":"Avda Yeseros De Los",
    "iso:country":"ES",
    "sg:address":"Avda Yeseros (de Los), 9",
    "sg:city":"Valmor-rompecubas",
    "sg:orig_category":"Fabricaci\u00d3n De Mobiliario Met\u00c1lico",
    "sg:phone":"+34 918 95 12 68",
    "sg:postcode":"28340",
    "sg:province":"Madrid",
    "wof:name":"Ceimolab S.l.",
    "wof:placetype":"venue"
},
  "geometry": {"coordinates":[-3.6677899361,40.1646308899],"type":"Point"}
}