{
  "type": "Feature",
  "properties": {
    "iso:country":"ES",
    "sg:address":"Rio Mero, 2",
    "sg:city":"Culleredo",
    "sg:orig_category":"Bebidas",
    "sg:phone":"+34 981 65 45 36",
    "sg:postcode":"15180",
    "sg:province":"La Coru\u00f1a",
    "wof:name":"Discoru\u00f1a S L",
    "wof:placetype":"venue"
},
  "geometry": {"coordinates":[-8.3645238876,43.2897491455],"type":"Point"}
}