{
  "type": "Feature",
  "properties": {
    "iso:country":"ES",
    "sg:address":"Avgd Comarques Del Pais Valencia, 62",
    "sg:city":"Pai I Capellans",
    "sg:orig_category":"Venta, Instalaci\u00d3n De Calefacci\u00d3n",
    "sg:phone":"+34 902 43 12 72",
    "sg:postcode":"46930",
    "sg:province":"Valencia",
    "wof:name":"Immergas Hispania S.a.",
    "wof:placetype":"venue"
},
  "geometry": {"coordinates":[-0.4419890046,39.482711792],"type":"Point"}
}