{
  "type": "Feature",
  "properties": {
    "iso:country":"ES",
    "sg:address":"Calle de Ibiza, 25",
    "sg:city":"Matagorda",
    "sg:orig_category":"Asesor\u00cda De Formaci\u00d3n Y Gesti\u00d3n De Personal",
    "sg:phone":"+34 950 49 87 44",
    "sg:postcode":"04715",
    "sg:province":"Almer\u00eda",
    "wof:name":"Ufarte Sanchez Maria",
    "wof:placetype":"venue"
},
  "geometry": {"coordinates":[-2.8399789333,36.7235107422],"type":"Point"}
}