{
  "type": "Feature",
  "properties": {
    "addr:full":"Pg Maragall, 156 Barcelona Barcelona 08027",
    "addr:housenumber":"156",
    "addr:postcode":"08027",
    "addr:street":"Pg Maragall",
    "iso:country":"ES",
    "sg:address":"Pg Maragall, 156",
    "sg:city":"Barcelona",
    "sg:orig_category":"Pod\u00d3logos: Pedicuros",
    "sg:phone":"+34 933 51 11 40",
    "sg:postcode":"08027",
    "sg:province":"Barcelona",
    "wof:name":"Pinar-palome C.b.",
    "wof:placetype":"venue"
},
  "geometry": {"coordinates":[2.1776208878,41.423915863],"type":"Point"}
}