{
  "type": "Feature",
  "properties": {
    "addr:full":"Calle de Hernani, 6 Donostia-san Sebastian Guip\u00f9zcoa 20004",
    "addr:housenumber":"6",
    "addr:postcode":"20004",
    "addr:street":"Calle De Hernani",
    "iso:country":"ES",
    "sg:address":"Calle de Hernani, 6",
    "sg:city":"Donostia-san Sebastian",
    "sg:orig_category":"Ropa Para Se\u00d1oras (al Por Menor)",
    "sg:phone":"+34 943 42 53 77",
    "sg:postcode":"20004",
    "sg:province":"Guip\u00f9zcoa",
    "wof:name":"Bordenave Azconegui Rosa",
    "wof:placetype":"venue"
},
  "geometry": {"coordinates":[-1.9837850332,43.3195457458],"type":"Point"}
}