{
  "type": "Feature",
  "properties": {
    "iso:country":"ES",
    "sg:address":"Calle de San Blas, 36",
    "sg:city":"Fuenteguinaldo",
    "sg:orig_category":"T\u00c9cnicos Veterinarios",
    "sg:phone":"+34 923 47 10 73",
    "sg:postcode":"37540",
    "sg:province":"Salamanca",
    "wof:name":"Fernandez Simon Juan Carlos",
    "wof:placetype":"venue"
},
  "geometry": {"coordinates":[-6.6766090393,40.4293899536],"type":"Point"}
}