{
  "type": "Feature",
  "properties": {
    "iso:country":"ES",
    "sg:address":"Pl. S. Juan, S/n",
    "sg:city":"Laguna Negrillos",
    "sg:orig_category":"Cajas De Ahorro",
    "sg:phone":"+34 987 75 50 43",
    "sg:postcode":"24234",
    "sg:province":"Le\u00f3n",
    "sg:website":"www.cajaespa\u00f1a.es",
    "wof:name":"Caja Espa\u00f1a De Inversiones Caja De Ahorros Y Monte De Piedad",
    "wof:placetype":"venue"
},
  "geometry": {"coordinates":[-5.6617040634,42.2405090332],"type":"Point"}
}