{
  "type": "Feature",
  "properties": {
    "addr:full":"Ctra Loja (de), S/n Alhama Granada Granada 18120",
    "addr:postcode":"18120",
    "addr:street":"Ctra Loja De S / N Alhama",
    "iso:country":"ES",
    "sg:address":"Ctra Loja (de), S/n",
    "sg:city":"Alhama Granada",
    "sg:orig_category":"Ense\u00d1anza, Formaci\u00d3n Profesional: Aprendizaje",
    "sg:phone":"+34 958 36 04 33",
    "sg:postcode":"18120",
    "sg:province":"Granada",
    "wof:name":"Mancomunidad De Municipios Alhama-temple",
    "wof:placetype":"venue"
},
  "geometry": {"coordinates":[-3.9905490875,37.0071258545],"type":"Point"}
}