{
  "type": "Feature",
  "properties": {
    "iso:country":"ES",
    "sg:address":"Carrer de Arimon, 18",
    "sg:city":"Barcelona",
    "sg:orig_category":"Colchones (fabricaci\u00d3n, Al Por Mayor, Al Por Menor)",
    "sg:phone":"+34 934 17 98 45",
    "sg:postcode":"08022",
    "sg:province":"Barcelona",
    "wof:name":"Paz Garcia Vicente",
    "wof:placetype":"venue"
},
  "geometry": {"coordinates":[2.1370010376,41.4046554565],"type":"Point"}
}