{
  "type": "Feature",
  "properties": {
    "addr:full":"Ctra Nacional 340, Km. 0146,0 Vinaros Castell\u00f3n 12500",
    "addr:postcode":"12500",
    "addr:street":"Ctra Nacional 340 Km. 0146,0;Castello\u0301N",
    "iso:country":"ES",
    "sg:address":"Ctra Nacional 340, Km. 0146,0",
    "sg:city":"Vinaros",
    "sg:orig_category":"Cr\u00cda De Poller\u00cda Y De Conejos",
    "sg:phone":"+34 964 45 62 01",
    "sg:postcode":"12500",
    "sg:province":"Castell\u00f3n",
    "wof:name":"Tecnicas Ganaderas Roca S.l.",
    "wof:placetype":"venue"
},
  "geometry": {"coordinates":[0.4749450088,40.4711990356],"type":"Point"}
}