{
  "type": "Feature",
  "properties": {
    "addr:full":"Calle de Leon Y Castillo, 246 Palmas De Gran Canaria Las Palmas 35005",
    "addr:housenumber":"246",
    "addr:postcode":"35005",
    "addr:street":"Calle De Leon Y Castillo",
    "iso:country":"ES",
    "sg:address":"Calle de Leon Y Castillo, 246",
    "sg:city":"Palmas De Gran Canaria",
    "sg:orig_category":"M\u00c9dicos: Endocrinolog\u00cda Y Metabolismo",
    "sg:phone":"+34 928 24 60 45",
    "sg:postcode":"35005",
    "sg:province":"Las Palmas",
    "wof:name":"Funcaendo S.l.",
    "wof:placetype":"venue"
},
  "geometry": {"coordinates":[-15.4262199402,28.1208400726],"type":"Point"}
}