{
  "type": "Feature",
  "properties": {
    "iso:country":"ES",
    "sg:address":"Plaz Santa Isabel, 2",
    "sg:city":"Santa Catalina",
    "sg:orig_category":"Mataderos De Poller\u00cda",
    "sg:phone":"+34 968 22 70 71",
    "sg:postcode":"30004",
    "sg:province":"Murcia",
    "wof:name":"Avimed S.a.",
    "wof:placetype":"venue"
},
  "geometry": {"coordinates":[-1.1298867464,37.9834747314],"type":"Point"}
}