{
  "type": "Feature",
  "properties": {
    "iso:country":"ES",
    "sg:address":"Carrer de Mallorca, 121",
    "sg:city":"Barcelona",
    "sg:orig_category":"Centros Pms (psico",
    "sg:phone":"+34 934 51 53 36",
    "sg:postcode":"08036",
    "sg:province":"Barcelona",
    "wof:name":"Centre De Telecomunicaciones De Catalunya",
    "wof:placetype":"venue"
},
  "geometry": {"coordinates":[2.1531550884,41.3869361877],"type":"Point"}
}