{
  "type": "Feature",
  "properties": {
    "iso:country":"ES",
    "sg:address":"Calle de Colon, 8",
    "sg:city":"Valencia",
    "sg:orig_category":"Cooperativas Agr\u00cdcolas",
    "sg:phone":"+34 963 53 37 66",
    "sg:postcode":"46004",
    "sg:province":"Valencia",
    "wof:name":"Tecaral S.a.",
    "wof:placetype":"venue"
},
  "geometry": {"coordinates":[-0.3742629886,39.4673233032],"type":"Point"}
}