{
  "type": "Feature",
  "properties": {
    "iso:country":"ES",
    "sg:address":"Calle de Marva, 19",
    "sg:city":"Valencia",
    "sg:orig_category":"Bater\u00cdas",
    "sg:phone":"+34 963 41 82 28",
    "sg:postcode":"46007",
    "sg:province":"Valencia",
    "wof:name":"Peiro Garcia Enrique",
    "wof:placetype":"venue"
},
  "geometry": {"coordinates":[-0.3836787939,39.4636573792],"type":"Point"}
}