{
  "type": "Feature",
  "properties": {
    "iso:country":"ES",
    "sg:address":"Calle de Cuenca, 3",
    "sg:city":"Medina Campo",
    "sg:orig_category":"Heladeros",
    "sg:phone":"+34 983 80 01 16",
    "sg:postcode":"47400",
    "sg:province":"Valladolid",
    "wof:name":"La Flor Medinense Cb.",
    "wof:placetype":"venue"
},
  "geometry": {"coordinates":[-4.916580677,41.3115921021],"type":"Point"}
}