{
  "type": "Feature",
  "properties": {
    "addr:full":"Calle de Salda\u00d1a, 30 Madrid Madrid 28019",
    "addr:housenumber":"30",
    "addr:postcode":"madrid;28019",
    "addr:street":"Calle De Saldan\u0303A",
    "iso:country":"ES",
    "sg:address":"Calle de Salda\u00d1a, 30",
    "sg:city":"Madrid",
    "sg:orig_category":"Centros De Educaci\u00d3n Especial",
    "sg:phone":"+34 914 71 50 93",
    "sg:postcode":"28019",
    "sg:province":"Madrid",
    "wof:name":"Comunidad Autonoma De Madrid-centros De Educacion",
    "wof:placetype":"venue"
},
  "geometry": {"coordinates":[-3.7260301113,40.3899497986],"type":"Point"}
}