{
  "type": "Feature",
  "properties": {
    "iso:country":"ES",
    "sg:address":"Calle de Parroco Antonio Pardo, 30",
    "sg:city":"Santa Cruz De Mudela",
    "sg:orig_category":"Reposter\u00cdas",
    "sg:phone":"+34 926 34 21 64",
    "sg:postcode":"13730",
    "sg:province":"Ciudad Real",
    "wof:name":"Lamo Del Rio Antonio De",
    "wof:placetype":"venue"
},
  "geometry": {"coordinates":[-3.4599590302,38.6394271851],"type":"Point"}
}