{
  "type": "Feature",
  "properties": {
    "iso:country":"ES",
    "sg:address":"Carrer de Sant Pere, 46",
    "sg:city":"Gava",
    "sg:orig_category":"Farmacias",
    "sg:phone":"+34 936 62 05 77",
    "sg:postcode":"08850",
    "sg:province":"Barcelona",
    "wof:name":"Farmacia Si\u00f1ol Poch Maria Teresa",
    "wof:placetype":"venue"
},
  "geometry": {"coordinates":[1.9996860027,41.3068656921],"type":"Point"}
}