{
  "type": "Feature",
  "properties": {
    "addr:full":"Calle de Francisco Madariaga, 4 Madrid Madrid 28017",
    "addr:housenumber":"4",
    "addr:postcode":"28017",
    "addr:street":"Calle De Francisco Madariaga",
    "iso:country":"ES",
    "sg:address":"Calle de Francisco Madariaga, 4",
    "sg:city":"Madrid",
    "sg:orig_category":"Contenedores (mercanc\u00cdas)",
    "sg:phone":"+34 914 07 11 53",
    "sg:postcode":"28017",
    "sg:province":"Madrid",
    "wof:name":"Bravo Rios Nemesio",
    "wof:placetype":"venue"
},
  "geometry": {"coordinates":[-3.6422140598,40.4344673157],"type":"Point"}
}