{
  "type": "Feature",
  "properties": {
    "iso:country":"ES",
    "sg:address":"Carrer de Ermita De Bellvitge, 45",
    "sg:city":"Hospitalet Llobregat",
    "sg:orig_category":"Alimentaci\u00d3n General (al Por Menor)",
    "sg:phone":"+34 933 35 57 88",
    "sg:postcode":"08907",
    "sg:province":"Barcelona",
    "wof:name":"Alvarez Fernandez Alfonso",
    "wof:placetype":"venue"
},
  "geometry": {"coordinates":[2.1090347767,41.3484916687],"type":"Point"}
}