{
  "type": "Feature",
  "properties": {
    "addr:full":"Av Gaudi, 43 Barcelona Barcelona 08025",
    "addr:housenumber":"43",
    "addr:postcode":"08025",
    "addr:street":"Av Gaudi",
    "iso:country":"ES",
    "sg:address":"Av Gaudi, 43",
    "sg:city":"Barcelona",
    "sg:orig_category":"Mercer\u00cda, Lencer\u00cda (al Por Menor)",
    "sg:phone":"+34 934 55 62 61",
    "sg:postcode":"08025",
    "sg:province":"Barcelona",
    "wof:name":"Complementos Galdon Ramos S.l",
    "wof:placetype":"venue"
},
  "geometry": {"coordinates":[2.17415905,41.4068565369],"type":"Point"}
}