{
  "type": "Feature",
  "properties": {
    "addr:full":"Carrer de Diputacio, 416 Barcelona Barcelona 08013",
    "addr:housenumber":"416",
    "addr:postcode":"08013",
    "addr:street":"Carrer De Diputacio",
    "iso:country":"ES",
    "sg:address":"Carrer de Diputacio, 416",
    "sg:city":"Barcelona",
    "sg:orig_category":"Cervecer\u00cdas",
    "sg:phone":"+34 932 45 62 96",
    "sg:postcode":"08013",
    "sg:province":"Barcelona",
    "wof:name":"Berja Cortijo Miguel",
    "wof:placetype":"venue"
},
  "geometry": {"coordinates":[2.1791460514,41.399269104],"type":"Point"}
}