{
  "type": "Feature",
  "properties": {
    "iso:country":"ES",
    "sg:address":"Ctra Cuenca Teruel, Km. 0152,0",
    "sg:city":"Ca\u00d1ete",
    "sg:orig_category":"Electricidad: Equipos Industriales, Componentes (fabricaci\u00d3n)",
    "sg:phone":"+34 969 34 60 17",
    "sg:postcode":"16300",
    "sg:province":"Cuenca",
    "wof:name":"Solera Cavermon S.a.",
    "wof:placetype":"venue"
},
  "geometry": {"coordinates":[-1.6472690105,40.0406913757],"type":"Point"}
}