{
  "type": "Feature",
  "properties": {
    "iso:country":"ES",
    "sg:address":"Calle de Colombia, 11",
    "sg:city":"Sevilla",
    "sg:orig_category":"Procuradores",
    "sg:phone":"+34 954 23 59 64",
    "sg:postcode":"41013",
    "sg:province":"Sevilla",
    "wof:name":"Venegas Carrasco Ines",
    "wof:placetype":"venue"
},
  "geometry": {"coordinates":[-5.9831700325,37.3698730469],"type":"Point"}
}