{
  "type": "Feature",
  "properties": {
    "addr:full":"Pase Pintor Rosales, 54 Madrid Madrid 28008",
    "addr:housenumber":"54",
    "addr:postcode":"madrid;28008",
    "addr:street":"Pintor Rosales",
    "iso:country":"ES",
    "sg:address":"Pase Pintor Rosales, 54",
    "sg:city":"Madrid",
    "sg:orig_category":"Inmobiliaria (agencias)",
    "sg:phone":"+34 915 43 49 40",
    "sg:postcode":"28008",
    "sg:province":"Madrid",
    "wof:name":"Estaciones Y Arrendamientos S.a.",
    "wof:placetype":"venue"
},
  "geometry": {"coordinates":[-3.7222590446,40.4296722412],"type":"Point"}
}