{
  "type": "Feature",
  "properties": {
    "iso:country":"ES",
    "sg:address":"Calle de Cristo (el), 1",
    "sg:city":"Logro\u00f1o",
    "sg:orig_category":"Seguros",
    "sg:phone":"+34 941 26 35 16",
    "sg:postcode":"26001",
    "sg:province":"La Rioja",
    "wof:name":"Miguel Royo Lucas",
    "wof:placetype":"venue"
},
  "geometry": {"coordinates":[-2.4445021152,42.466381073],"type":"Point"}
}