{
  "type": "Feature",
  "properties": {
    "addr:full":"Calle de Cartama, 3 Cala M\u00e1laga 29649",
    "addr:housenumber":"3",
    "addr:postcode":"29649",
    "addr:street":"Calle De Cartama;Ma\u0301Laga",
    "iso:country":"ES",
    "sg:address":"Calle de Cartama, 3",
    "sg:city":"Cala",
    "sg:orig_category":"Caf\u00c9s, Bares, Cervecer\u00cdas",
    "sg:phone":"+34 952 49 48 03",
    "sg:postcode":"29649",
    "sg:province":"M\u00e1laga",
    "wof:name":"Telefonia Saltele Marbella S.l.",
    "wof:placetype":"venue"
},
  "geometry": {"coordinates":[-4.679169178,36.5040016174],"type":"Point"}
}