{
  "type": "Feature",
  "properties": {
    "iso:country":"ES",
    "sg:address":"Calle de Estacion, S/n",
    "sg:city":"Molina Segura",
    "sg:orig_category":"Albergues Sociales",
    "sg:phone":"+34 968 61 47 82",
    "sg:postcode":"30500",
    "sg:province":"Murcia",
    "sg:website":"www.promocionesmengual.com",
    "wof:name":"Promociones Diego Mengual S.a.",
    "wof:placetype":"venue"
},
  "geometry": {"coordinates":[-1.2125040293,38.0538482666],"type":"Point"}
}