{
  "type": "Feature",
  "properties": {
    "addr:full":"Carrer de Calaf, 14 Barcelona Barcelona 08021",
    "addr:housenumber":"14",
    "addr:postcode":"08021",
    "addr:street":"Carrer De Calaf",
    "iso:country":"ES",
    "sg:address":"Carrer de Calaf, 14",
    "sg:city":"Barcelona",
    "sg:orig_category":"Carnicer\u00cdas, Carnicer\u00cdas",
    "sg:phone":"+34 932 09 33 90",
    "sg:postcode":"08021",
    "sg:province":"Barcelona",
    "wof:name":"Masferrer Galbany Juan",
    "wof:placetype":"venue"
},
  "geometry": {"coordinates":[2.1441171169,41.3975982666],"type":"Point"}
}