{
  "type": "Feature",
  "properties": {
    "addr:full":"Carrer de Muntaner, 279 Barcelona Barcelona 08021",
    "addr:housenumber":"279",
    "addr:postcode":"08021",
    "addr:street":"Carrer De Muntaner",
    "iso:country":"ES",
    "sg:address":"Carrer de Muntaner, 279",
    "sg:city":"Barcelona",
    "sg:orig_category":"Sociedades, Compa\u00d1\u00cdas Aseguradoras",
    "sg:phone":"+34 933 17 83 87",
    "sg:postcode":"08021",
    "sg:province":"Barcelona",
    "wof:name":"Rodolfo Servan Correduria De Seguros S.a.",
    "wof:placetype":"venue"
},
  "geometry": {"coordinates":[2.1467928886,41.3960113525],"type":"Point"}
}