{
  "type": "Feature",
  "properties": {
    "addr:full":"Calle de Sol, 88 Sevilla Sevilla 41003",
    "addr:housenumber":"88",
    "addr:postcode":"41003",
    "addr:street":"Calle De Sol",
    "iso:country":"ES",
    "sg:address":"Calle de Sol, 88",
    "sg:city":"Sevilla",
    "sg:orig_category":"Cine (distribuci\u00d3n)",
    "sg:phone":"+34 954 54 10 21",
    "sg:postcode":"41003",
    "sg:province":"Sevilla",
    "wof:name":"Pelimex Almacen C.b.",
    "wof:placetype":"venue"
},
  "geometry": {"coordinates":[-5.9836921692,37.3960647583],"type":"Point"}
}