{
  "type": "Feature",
  "properties": {
    "addr:full":"Calle de Manuel Romano, 1 Llanes Asturias 33500",
    "addr:housenumber":"1",
    "addr:postcode":"33500",
    "addr:street":"Calle De Manuel Romano",
    "iso:country":"ES",
    "sg:address":"Calle de Manuel Romano, 1",
    "sg:city":"Llanes",
    "sg:orig_category":"Cl\u00cdnicas Dentales",
    "sg:phone":"+34 985 40 17 87",
    "sg:postcode":"33500",
    "sg:province":"Asturias",
    "wof:name":"Tora\u00f1o Clinica Dental S.c.",
    "wof:placetype":"venue"
},
  "geometry": {"coordinates":[-4.7567338943,43.4207077026],"type":"Point"}
}