{
  "type": "Feature",
  "properties": {
    "iso:country":"ES",
    "sg:address":"Carrer de Conca De Tremp, 7",
    "sg:city":"Barcelona",
    "sg:orig_category":"Bazares, Art\u00cdculos De Limpieza Y De Cocina (al Por Menor)",
    "sg:phone":"+34 934 20 22 27",
    "sg:postcode":"08032",
    "sg:province":"Barcelona",
    "wof:name":"Agrupacion Bazar El Regalo S.a.",
    "wof:placetype":"venue"
},
  "geometry": {"coordinates":[2.1549427509,41.4241294861],"type":"Point"}
}