{
  "type": "Feature",
  "properties": {
    "addr:full":"Carrer de Rocafort, 50 Barcelona Barcelona 08015",
    "addr:housenumber":"50",
    "addr:postcode":"08015",
    "addr:street":"Carrer De Rocafort",
    "iso:country":"ES",
    "sg:address":"Carrer de Rocafort, 50",
    "sg:city":"Barcelona",
    "sg:orig_category":"Perfumer\u00cda (al Por Menor)",
    "sg:phone":"+34 934 24 32 96",
    "sg:postcode":"08015",
    "sg:province":"Barcelona",
    "wof:name":"Crisanmar Perfums, S.l.",
    "wof:placetype":"venue"
},
  "geometry": {"coordinates":[2.1552810669,41.3780021667],"type":"Point"}
}