{
  "type": "Feature",
  "properties": {
    "addr:full":"Antonio Arrillaga Kalea, 8 Elgoibar Guip\u00f9zcoa 20870",
    "addr:housenumber":"8",
    "addr:postcode":"20870",
    "addr:street":"Antonio Arrillaga Kalea;Guipu\u0300Zcoa",
    "iso:country":"ES",
    "sg:address":"Antonio Arrillaga Kalea, 8",
    "sg:city":"Elgoibar",
    "sg:orig_category":"Peluquer\u00cdas, Peluquer\u00cda Mixta",
    "sg:phone":"+34 943 74 40 26",
    "sg:postcode":"20870",
    "sg:province":"Guip\u00f9zcoa",
    "wof:name":"Idoia Pe\u00f1agarikano Mugarza Y Otras, C.b",
    "wof:placetype":"venue"
},
  "geometry": {"coordinates":[-2.4175999165,43.2133293152],"type":"Point"}
}