{
  "type": "Feature",
  "properties": {
    "iso:country":"ES",
    "sg:address":"Calle de Solana, Km. 0003,0",
    "sg:city":"Langa Duero",
    "sg:orig_category":"Aguas (distribuci\u00d3n, Servicios)",
    "sg:phone":"+34 975 35 30 65",
    "sg:postcode":"42320",
    "sg:province":"Soria",
    "wof:name":"Langa De Duero Enercorr Xxi S.l.",
    "wof:placetype":"venue"
},
  "geometry": {"coordinates":[-3.2616660595,41.621799469],"type":"Point"}
}