{
  "type": "Feature",
  "properties": {
    "addr:full":"Carrer de Mestre Antich, 5 Vendrell Tarragona 43700",
    "addr:housenumber":"5",
    "addr:postcode":"43700",
    "addr:street":"Carrer De Mestre Antich",
    "iso:country":"ES",
    "sg:address":"Carrer de Mestre Antich, 5",
    "sg:city":"Vendrell",
    "sg:orig_category":"Radiocomunicaciones, Telefon\u00cda M\u00d3vil, Radiomensajer\u00cda: Servicios, Comercializaci\u00d3n",
    "sg:phone":"+34 977 66 04 03",
    "sg:postcode":"43700",
    "sg:province":"Tarragona",
    "wof:name":"Knitre  Ahmad",
    "wof:placetype":"venue"
},
  "geometry": {"coordinates":[1.5337870121,41.2153129578],"type":"Point"}
}