{
  "type": "Feature",
  "properties": {
    "iso:country":"ES",
    "sg:address":"C/ Sureda, D'en, 1",
    "sg:city":"Porto Cristo",
    "sg:orig_category":"Restaurantes",
    "sg:phone":"+34 971 82 14 42",
    "sg:postcode":"07680",
    "sg:province":"Islas Baleares",
    "wof:name":"Cabrer Fullana Salvador",
    "wof:placetype":"venue"
},
  "geometry": {"coordinates":[3.3348650932,39.5417861938],"type":"Point"}
}