{
  "type": "Feature",
  "properties": {
    "addr:full":"Carr Aeroclub, 14 Empuriabrava Girona 17487",
    "addr:housenumber":"14",
    "addr:postcode":"17487",
    "addr:street":"Carr Aeroclub",
    "iso:country":"ES",
    "sg:address":"Carr Aeroclub, 14",
    "sg:city":"Empuriabrava",
    "sg:orig_category":"Construcciones Navales Y Fluviales",
    "sg:phone":"+34 972 45 08 10",
    "sg:postcode":"17487",
    "sg:province":"Girona",
    "sg:website":"www.nautibrava.com",
    "wof:name":"Nautibrava S.l.",
    "wof:placetype":"venue"
},
  "geometry": {"coordinates":[3.1070549488,42.2568092346],"type":"Point"}
}