{
  "type": "Feature",
  "properties": {
    "addr:full":"Cro Purissima Sang, 12 Reus Tarragona 43201",
    "addr:postcode":"43201",
    "iso:country":"ES",
    "sg:address":"Cro Purissima Sang, 12",
    "sg:city":"Reus",
    "sg:orig_category":"Comunidades Religiosas",
    "sg:phone":"+34 977 34 31 96",
    "sg:postcode":"43201",
    "sg:province":"Tarragona",
    "wof:name":"Real Congregacion De La Purisima Sangre De Nuestro Se\u00f1or Jesucristo",
    "wof:placetype":"venue"
},
  "geometry": {"coordinates":[1.1119719744,41.1562232971],"type":"Point"}
}