{
  "type": "Feature",
  "properties": {
    "iso:country":"ES",
    "sg:address":"Plaz Ponce De Leon, 9",
    "sg:city":"Sevilla",
    "sg:orig_category":"Empresarios",
    "sg:phone":"+34 954 21 58 21",
    "sg:postcode":"41003",
    "sg:province":"Sevilla",
    "sg:website":"www.mezquitadesevilla.com",
    "wof:name":"Fundacion Mezquita De Sevilla",
    "wof:placetype":"venue"
},
  "geometry": {"coordinates":[-5.98711586,37.39320755],"type":"Point"}
}