{
  "type": "Feature",
  "properties": {
    "iso:country":"ES",
    "sg:address":"Labradores, 16",
    "sg:city":"Boadilla",
    "sg:orig_category":"Producci\u00d3n, Venta De Productos De Agricultura Biol\u00d3gica",
    "sg:phone":"+34 916 33 00 34",
    "sg:postcode":"28660",
    "sg:province":"Madrid",
    "wof:name":"Agricola Garcia Bergas S.a.",
    "wof:placetype":"venue"
},
  "geometry": {"coordinates":[-3.849417448,40.3950271606],"type":"Point"}
}