{
  "type": "Feature",
  "properties": {
    "addr:full":"Ctra Rabaza, 1 Codosera Badajoz 06518",
    "addr:housenumber":"1",
    "addr:postcode":"06518",
    "addr:street":"Ctra Rabaza",
    "iso:country":"ES",
    "sg:address":"Ctra Rabaza, 1",
    "sg:city":"Codosera",
    "sg:orig_category":"Quincaller\u00cda (al Por Menor)",
    "sg:phone":"+34 924 40 41 64",
    "sg:postcode":"06518",
    "sg:province":"Badajoz",
    "wof:name":"Borrega Matin Francisca",
    "wof:placetype":"venue"
},
  "geometry": {"coordinates":[-7.1718940735,39.2077064514],"type":"Point"}
}