{
  "type": "Feature",
  "properties": {
    "addr:full":"Calle de Calzada Romana, 20 Valdelacalzada Badajoz 06185",
    "addr:housenumber":"20",
    "addr:postcode":"06185",
    "addr:street":"Calle De Calzada Romana",
    "iso:country":"ES",
    "sg:address":"Calle de Calzada Romana, 20",
    "sg:city":"Valdelacalzada",
    "sg:orig_category":"Albergues",
    "sg:phone":"+34 924 44 71 09",
    "sg:postcode":"06185",
    "sg:province":"Badajoz",
    "wof:name":"Hostal Velasco S.l.",
    "wof:placetype":"venue"
},
  "geometry": {"coordinates":[-6.7013888359,38.8872833252],"type":"Point"}
}