{
  "type": "Feature",
  "properties": {
    "addr:full":"Calle de Lagasca, 95 Madrid Madrid 28006",
    "addr:housenumber":"95",
    "addr:postcode":"madrid;28006",
    "addr:street":"Calle De Lagasca",
    "iso:country":"ES",
    "sg:address":"Calle de Lagasca, 95",
    "sg:city":"Madrid",
    "sg:orig_category":"Muebles, Minoristas",
    "sg:phone":"+34 915 76 53 11",
    "sg:postcode":"28006",
    "sg:province":"Madrid",
    "sg:website":"www.roche-bobois.com",
    "wof:name":"Formas Internacionales S. A.",
    "wof:placetype":"venue"
},
  "geometry": {"coordinates":[-3.6847949028,40.4324607849],"type":"Point"}
}