{
  "type": "Feature",
  "properties": {
    "iso:country":"ES",
    "sg:address":"Carrer de Ametllers (els), 4",
    "sg:city":"Masnou",
    "sg:orig_category":"Institutos De Belleza",
    "sg:phone":"+34 935 40 00 19",
    "sg:postcode":"08320",
    "sg:province":"Barcelona",
    "wof:name":"Garcia Moreno Esperanza",
    "wof:placetype":"venue"
},
  "geometry": {"coordinates":[2.309292078,41.4870262146],"type":"Point"}
}