{
  "type": "Feature",
  "properties": {
    "iso:country":"ES",
    "sg:address":"Avda Juan Garcia Navia Castrillon, 3",
    "sg:city":"Viveiro",
    "sg:orig_category":"Contables",
    "sg:phone":"+34 982 55 10 47",
    "sg:postcode":"27850",
    "sg:province":"Lugo",
    "wof:name":"Caridad Mui\u00f1o Luis",
    "wof:placetype":"venue"
},
  "geometry": {"coordinates":[-7.5970988274,43.6591758728],"type":"Point"}
}