{
  "type": "Feature",
  "properties": {
    "addr:full":"Calle de Hermosilla, 144 Madrid Madrid 28028",
    "addr:housenumber":"144",
    "addr:postcode":"28028",
    "addr:street":"Calle De Hermosilla",
    "iso:country":"ES",
    "sg:address":"Calle de Hermosilla, 144",
    "sg:city":"Madrid",
    "sg:orig_category":"Peluqueros: De Se\u00d1oras",
    "sg:phone":"+34 913 56 05 76",
    "sg:postcode":"28028",
    "sg:province":"Madrid",
    "wof:name":"Gomez Gonzalez Susana",
    "wof:placetype":"venue"
},
  "geometry": {"coordinates":[-3.665678978,40.4253005981],"type":"Point"}
}