{
  "type": "Feature",
  "properties": {
    "addr:full":"Calle de Landako Kalea, 2 Amurrio \u00c1lava 01470",
    "addr:housenumber":"2",
    "addr:postcode":"01470",
    "addr:street":"Calle De Landako Kalea",
    "iso:country":"ES",
    "sg:address":"Calle de Landako Kalea, 2",
    "sg:city":"Amurrio",
    "sg:orig_category":"Procuradores",
    "sg:phone":"+34 945 89 13 83",
    "sg:postcode":"01470",
    "sg:province":"\u00c1lava",
    "wof:name":"Buron Morilla Soledad",
    "wof:placetype":"venue"
},
  "geometry": {"coordinates":[-3.00126791,43.0515098572],"type":"Point"}
}