{
  "type": "Feature",
  "properties": {
    "iso:country":"ES",
    "sg:address":"Calle de Agua, 30",
    "sg:city":"Buenache Alarcon",
    "sg:orig_category":"Farmacias",
    "sg:phone":"+34 969 20 90 26",
    "sg:postcode":"16114",
    "sg:province":"Cuenca",
    "wof:name":"Alarcon Gazcuena Rocio",
    "wof:placetype":"venue"
},
  "geometry": {"coordinates":[-2.1599993706,39.656539917],"type":"Point"}
}