{
  "type": "Feature",
  "properties": {
    "iso:country":"ES",
    "sg:address":"Ctra Almagro, Km. 0001,5",
    "sg:city":"Bola\u00e7os De Calatrava",
    "sg:orig_category":"Ense\u00d1anza, Formaci\u00d3n Profesional: Aprendizaje",
    "sg:phone":"+34 926 87 03 35",
    "sg:postcode":"13260",
    "sg:province":"Ciudad Real",
    "wof:name":"Centro De Iniciativas Para La Formacion Agraria S.a.",
    "wof:placetype":"venue"
},
  "geometry": {"coordinates":[-3.6656041145,38.9035949707],"type":"Point"}
}