{
  "type": "Feature",
  "properties": {
    "iso:country":"ES",
    "sg:address":"Calle de Alejandre, 14",
    "sg:city":"Alca\u00f1iz",
    "sg:orig_category":"Farmacias",
    "sg:phone":"+34 978 83 40 36",
    "sg:postcode":"44600",
    "sg:province":"Teruel",
    "wof:name":"Crono Sport Bajo Aragon S.l.",
    "wof:placetype":"venue"
},
  "geometry": {"coordinates":[-0.1312578022,41.0502662659],"type":"Point"}
}