{
  "type": "Feature",
  "properties": {
    "addr:full":"Avda Feria, S/n Yecla Murcia 30510",
    "addr:housenumber":"s / n",
    "addr:postcode":"30510",
    "addr:street":"Avda Feria",
    "iso:country":"ES",
    "sg:address":"Avda Feria, S/n",
    "sg:city":"Yecla",
    "sg:orig_category":"Fabricaci\u00d3n De Mobiliario Met\u00c1lico",
    "sg:phone":"+34 968 75 21 31",
    "sg:postcode":"30510",
    "sg:province":"Murcia",
    "wof:name":"Metalyecla S.l.",
    "wof:placetype":"venue"
},
  "geometry": {"coordinates":[-1.1085540056,38.6167602539],"type":"Point"}
}