{
  "type": "Feature",
  "properties": {
    "addr:full":"Avda. Blas Infante, S/n Palomares Almer\u00eda 04618",
    "addr:housenumber":"/ n",
    "addr:postcode":"04618",
    "addr:street":"Avda. Blas Infante S;Almeri\u0301A",
    "iso:country":"ES",
    "sg:address":"Avda. Blas Infante, S/n",
    "sg:city":"Palomares",
    "sg:orig_category":"Contenedores (mercanc\u00cdas)",
    "sg:phone":"+34 950 46 75 28",
    "sg:postcode":"04618",
    "sg:province":"Almer\u00eda",
    "wof:name":"Valero Latorre Diego",
    "wof:placetype":"venue"
},
  "geometry": {"coordinates":[-1.797680974,37.2479629517],"type":"Point"}
}