{
  "type": "Feature",
  "properties": {
    "iso:country":"ES",
    "sg:address":"Calle de Plaza De La, 29",
    "sg:city":"Cartaya",
    "sg:orig_category":"Hoteles",
    "sg:phone":"+34 959 39 03 30",
    "sg:postcode":"21450",
    "sg:province":"Huelva",
    "wof:name":"Vazquez Mora Dolores",
    "wof:placetype":"venue"
},
  "geometry": {"coordinates":[-7.1533727646,37.2841110229],"type":"Point"}
}