{
  "type": "Feature",
  "properties": {
    "addr:full":"Ctra. Torres, S/n Lazagurria Navarra 31588",
    "addr:postcode":"31588",
    "addr:street":"Ctra. Torres S / N Lazagurria Navarra",
    "iso:country":"ES",
    "sg:address":"Ctra. Torres, S/n",
    "sg:city":"Lazagurria",
    "sg:orig_category":"Poller\u00cda Y Caza (al Por Menor)",
    "sg:phone":"+34 948 44 30 04",
    "sg:postcode":"31588",
    "sg:province":"Navarra",
    "wof:name":"Mayayo Sanz Jesus",
    "wof:placetype":"venue"
},
  "geometry": {"coordinates":[-2.2381260395,42.491645813],"type":"Point"}
}