{
  "type": "Feature",
  "properties": {
    "iso:country":"ES",
    "sg:address":"Calle de Carmen, S/n",
    "sg:city":"Villafranca De Los Barros",
    "sg:orig_category":"Alimentaci\u00d3n General (al Por Menor)",
    "sg:phone":"+34 924 52 46 15",
    "sg:postcode":"06220",
    "sg:province":"Badajoz",
    "wof:name":"Perez Carrasco Juliana",
    "wof:placetype":"venue"
},
  "geometry": {"coordinates":[-6.338973999,38.5590934753],"type":"Point"}
}