{
  "type": "Feature",
  "properties": {
    "addr:full":"C/ Blas Selva Mendiola, 11 Elche Alicante 03202",
    "addr:housenumber":"11",
    "addr:postcode":"03202",
    "addr:street":"C / Blas Selva Mendiola",
    "iso:country":"ES",
    "sg:address":"C/ Blas Selva Mendiola, 11",
    "sg:city":"Elche",
    "sg:orig_category":"Carnicer\u00cdas, Carnicer\u00cdas",
    "sg:phone":"+34 965 45 07 89",
    "sg:postcode":"03202",
    "sg:province":"Alicante",
    "wof:name":"Carnes Y Embutidos J. Martinez S.l.",
    "wof:placetype":"venue"
},
  "geometry": {"coordinates":[-0.6867349744,38.2709541321],"type":"Point"}
}