{
  "type": "Feature",
  "properties": {
    "addr:full":"San Franzisko Kalea, 35 Elgoibar Guip\u00f9zcoa 20870",
    "addr:housenumber":"35",
    "addr:postcode":"20870",
    "addr:street":"San Franzisko Kalea;Guipu\u0300Zcoa",
    "iso:country":"ES",
    "sg:address":"San Franzisko Kalea, 35",
    "sg:city":"Elgoibar",
    "sg:orig_category":"Molduras, Junquillos, Listones Y Molduras Perforadas",
    "sg:phone":"+34 943 74 02 10",
    "sg:postcode":"20870",
    "sg:province":"Guip\u00f9zcoa",
    "wof:name":"Casares Alarcia Kaiet",
    "wof:placetype":"venue"
},
  "geometry": {"coordinates":[-2.4130530357,43.2159118652],"type":"Point"}
}