{
  "type": "Feature",
  "properties": {
    "iso:country":"ES",
    "sg:address":"Carrer de Carril, 6",
    "sg:city":"Molins Rei",
    "sg:orig_category":"Comercio De Piezas De Recambio Y De Accesorios De Veh\u00cdculos, Veh\u00cdculos Industriales",
    "sg:phone":"+34 936 68 89 29",
    "sg:postcode":"08750",
    "sg:province":"Barcelona",
    "wof:name":"Rivero Franco Jose",
    "wof:placetype":"venue"
},
  "geometry": {"coordinates":[2.0208289623,41.409526825],"type":"Point"}
}