{
  "type": "Feature",
  "properties": {
    "iso:country":"ES",
    "sg:address":"Calle de Diego De Leon, 62",
    "sg:city":"Madrid",
    "sg:orig_category":"Hospitales",
    "sg:phone":"+34 914 01 19 84",
    "sg:postcode":"28006",
    "sg:province":"Madrid",
    "wof:name":"Quintiles S.l.",
    "wof:placetype":"venue"
},
  "geometry": {"coordinates":[-3.6761584282,40.4345741272],"type":"Point"}
}