{
  "type": "Feature",
  "properties": {
    "iso:country":"ES",
    "sg:address":"Avda Paz, 2",
    "sg:city":"Almendralejo",
    "sg:classifiers":[
        {
            "category":"Autos & Motor Vehicles",
            "subcategory":"Automobile Sales",
            "type":"Retail Goods"
        }
    ],
    "sg:phone":"+34 924 67 16 74",
    "sg:postcode":"06200",
    "sg:province":"Badajoz",
    "wof:name":"Escuela De Conductores Almendralejo S.l.",
    "wof:placetype":"venue"
},
  "geometry": {"coordinates":[-6.4127140045,38.6833648682],"type":"Point"}
}