{
  "type": "Feature",
  "properties": {
    "iso:country":"ES",
    "sg:address":"Artesano Jose M. Silva, S/n",
    "sg:city":"S. Fernando",
    "sg:orig_category":"Carnicer\u00cdas, Carnicer\u00cdas",
    "sg:phone":"+34 956 48 75 87",
    "sg:postcode":"11100",
    "sg:province":"C\u00e1diz",
    "wof:name":"Carniceria Y Charcuteria Antonio Vaca Cauto E Hijos S.l.",
    "wof:placetype":"venue"
},
  "geometry": {"coordinates":[-6.208876133,36.447555542],"type":"Point"}
}