{
  "type": "Feature",
  "properties": {
    "iso:country":"ES",
    "sg:address":"Calle de L'horta, 5",
    "sg:city":"Torrent",
    "sg:orig_category":"Empresarios",
    "sg:phone":"+34 961 56 28 98",
    "sg:postcode":"46900",
    "sg:province":"Valencia",
    "wof:name":"Reformas Saiz S.l.",
    "wof:placetype":"venue"
},
  "geometry": {"coordinates":[-0.4729323983,39.4338645935],"type":"Point"}
}