{
  "type": "Feature",
  "properties": {
    "addr:full":"Calle de Violetas Del Teide, 20 Agua Dulce Santa Cruz De Tenerife 38687",
    "addr:housenumber":"20",
    "addr:postcode":"38687",
    "addr:street":"Calle De Violetas Del Teide",
    "iso:country":"ES",
    "sg:address":"Calle de Violetas Del Teide, 20",
    "sg:city":"Agua Dulce",
    "sg:orig_category":"Supermercados Y Hipermercados",
    "sg:phone":"+34 922 86 55 70",
    "sg:postcode":"38687",
    "sg:province":"Santa Cruz De Tenerife",
    "wof:name":"Palenzuela Cruz Remedios",
    "wof:placetype":"venue"
},
  "geometry": {"coordinates":[-16.7886390686,28.1805458069],"type":"Point"}
}