{
  "type": "Feature",
  "properties": {
    "iso:country":"ES",
    "sg:address":"Calle de Ermita, 22",
    "sg:city":"Abengibre",
    "sg:orig_category":"Negocio De Madera",
    "sg:phone":"+34 967 47 44 45",
    "sg:postcode":"02250",
    "sg:province":"Albacete",
    "wof:name":"Maderas Abengibre S.l.",
    "wof:placetype":"venue"
},
  "geometry": {"coordinates":[-1.5378160477,39.2101135254],"type":"Point"}
}