{
  "type": "Feature",
  "properties": {
    "addr:full":"Calle de Mesones, 1 Marchena Sevilla 41620",
    "addr:housenumber":"1",
    "addr:postcode":"41620",
    "addr:street":"Calle De Mesones",
    "iso:country":"ES",
    "sg:address":"Calle de Mesones, 1",
    "sg:city":"Marchena",
    "sg:orig_category":"Inform\u00c1tica (estudios, Servicios, Asesor\u00cda, Formaci\u00d3n)",
    "sg:phone":"+34 954 84 46 18",
    "sg:postcode":"41620",
    "sg:province":"Sevilla",
    "wof:name":"Lebron Carmona Francisco",
    "wof:placetype":"venue"
},
  "geometry": {"coordinates":[-5.4183568954,37.3308639526],"type":"Point"}
}