{
  "type": "Feature",
  "properties": {
    "iso:country":"ES",
    "sg:address":"Calle de Juan Xxiii, S/n",
    "sg:city":"Jumilla",
    "sg:orig_category":"Carnicer\u00cdas, Carnicer\u00cdas",
    "sg:phone":"+34 968 78 23 50",
    "sg:postcode":"30520",
    "sg:province":"Murcia",
    "wof:name":"Frutas Todoagricola S.l.",
    "wof:placetype":"venue"
},
  "geometry": {"coordinates":[-1.3244539499,38.4754333496],"type":"Point"}
}