{
  "type": "Feature",
  "properties": {
    "iso:country":"ES",
    "sg:address":"Coronel Borbon, 2",
    "sg:city":"Estepona",
    "sg:orig_category":"Abogados",
    "sg:phone":"+34 952 79 63 54",
    "sg:postcode":"29680",
    "sg:province":"M\u00e1laga",
    "wof:name":"Fernandez Abogados Y Asociados S.l.",
    "wof:placetype":"venue"
},
  "geometry": {"coordinates":[-5.1452140808,36.4275817871],"type":"Point"}
}