{
  "type": "Feature",
  "properties": {
    "addr:full":"Calle de Martin Perez Zaballa, 4 Portugalete Vizcaya 48920",
    "addr:housenumber":"4",
    "addr:postcode":"48920",
    "addr:street":"Calle De Martin Perez Zaballa",
    "iso:country":"ES",
    "sg:address":"Calle de Martin Perez Zaballa, 4",
    "sg:city":"Portugalete",
    "sg:orig_category":"Cerrajer\u00cda, Ferrallista",
    "sg:phone":"+34 944 83 51 70",
    "sg:postcode":"48920",
    "sg:province":"Vizcaya",
    "wof:name":"Bustamante Gonzalez S.l.",
    "wof:placetype":"venue"
},
  "geometry": {"coordinates":[-3.0235440731,43.3173599243],"type":"Point"}
}