{
  "type": "Feature",
  "properties": {
    "iso:country":"ES",
    "sg:address":"Rua Pontevedra, S/n",
    "sg:city":"Noia",
    "sg:orig_category":"Molduras, Junquillos, Listones Y Molduras Perforadas",
    "sg:phone":"+34 981 82 41 22",
    "sg:postcode":"15200",
    "sg:province":"La Coru\u00f1a",
    "wof:name":"Carreira Cambeiro Manuel",
    "wof:placetype":"venue"
},
  "geometry": {"coordinates":[-8.8856830597,42.7873649597],"type":"Point"}
}