{
  "type": "Feature",
  "properties": {
    "iso:country":"ES",
    "sg:address":"Calle de Buen Aire, 3",
    "sg:city":"Ejea De Los Caballeros",
    "sg:orig_category":"Suministros Para Carrocer\u00cdas",
    "sg:phone":"+34 976 66 01 87",
    "sg:postcode":"50600",
    "sg:province":"Zaragoza",
    "wof:name":"Judez Racaj Jose Luis",
    "wof:placetype":"venue"
},
  "geometry": {"coordinates":[-1.137830019,42.1298370361],"type":"Point"}
}