{
  "type": "Feature",
  "properties": {
    "addr:full":"Calle de Sacramento, 20 Aspe Alicante 03680",
    "addr:housenumber":"20",
    "addr:postcode":"03680",
    "addr:street":"Calle De Sacramento",
    "iso:country":"ES",
    "sg:address":"Calle de Sacramento, 20",
    "sg:city":"Aspe",
    "sg:orig_category":"\u00d3ptica: Instrumentos (fabricaci\u00d3n)",
    "sg:phone":"+34 965 49 25 22",
    "sg:postcode":"03680",
    "sg:province":"Alicante",
    "wof:name":"Gimenez Llorens Maria Teresa",
    "wof:placetype":"venue"
},
  "geometry": {"coordinates":[-0.7674790025,38.3461494446],"type":"Point"}
}