{
  "type": "Feature",
  "properties": {
    "iso:country":"ES",
    "sg:address":"Calle de Pozo Hilera, 12",
    "sg:city":"Salamanca",
    "sg:orig_category":"Quincaller\u00cda (al Por Menor)",
    "sg:phone":"+34 923 26 29 71",
    "sg:postcode":"37002",
    "sg:province":"Salamanca",
    "wof:name":"Puertas Perez Faustino",
    "wof:placetype":"venue"
},
  "geometry": {"coordinates":[-5.6603298187,40.9690208435],"type":"Point"}
}