{
  "type": "Feature",
  "properties": {
    "addr:full":"Vivente, 43 Vivente A Coru\u00f1a 15109",
    "addr:housenumber":"43",
    "addr:postcode":"15109",
    "addr:street":"Vivente;Corun\u0303A",
    "iso:country":"ES",
    "sg:address":"Vivente, 43",
    "sg:city":"Vivente",
    "sg:orig_category":"Venta, Montaje De Neum\u00c1ticos",
    "sg:phone":"+34 981 70 20 99",
    "sg:postcode":"15109",
    "sg:province":"A Coru\u00f1a",
    "wof:name":"Varela Belmonte Josefina",
    "wof:placetype":"venue"
},
  "geometry": {"coordinates":[-8.6633071899,43.2020225525],"type":"Point"}
}