{
  "type": "Feature",
  "properties": {
    "addr:full":"Calle de Candido Mateos, 18 Madrid Madrid 28035",
    "addr:housenumber":"18",
    "addr:postcode":"madrid;28035",
    "addr:street":"Calle De Candido Mateos",
    "iso:country":"ES",
    "sg:address":"Calle de Candido Mateos, 18",
    "sg:city":"Madrid",
    "sg:orig_category":"Sociedades, Compa\u00d1\u00cdas Aseguradoras",
    "sg:phone":"+34 913 16 76 28",
    "sg:postcode":"28035",
    "sg:province":"Madrid",
    "wof:name":"Madrid Mercasegur Correduria De Seguros S.l.",
    "wof:placetype":"venue"
},
  "geometry": {"coordinates":[-3.7192735672,40.4759101868],"type":"Point"}
}