{
  "type": "Feature",
  "properties": {
    "iso:country":"ES",
    "sg:address":"Calle de Fuentenebro, 2",
    "sg:city":"Madrid",
    "sg:orig_category":"Artes Gr\u00c1ficas, Artes Pl\u00c1sticas: Material Y Suministros (al Por Menor)",
    "sg:phone":"+34 917 47 06 96",
    "sg:postcode":"28042",
    "sg:province":"Madrid",
    "sg:website":"www.amillo.com",
    "wof:name":"Amillo S. L.",
    "wof:placetype":"venue"
},
  "geometry": {"coordinates":[-3.5829555988,40.4516143799],"type":"Point"}
}