{
  "type": "Feature",
  "properties": {
    "iso:country":"ES",
    "sg:address":"Av Mediterrani, 53",
    "sg:city":"Poblenou",
    "sg:orig_category":"Molduras, Junquillos, Listones Y Molduras Perforadas",
    "sg:phone":"+34 937 66 00 64",
    "sg:postcode":"08397",
    "sg:province":"Barcelona",
    "wof:name":"Garrido Martinez Pedro",
    "wof:placetype":"venue"
},
  "geometry": {"coordinates":[2.6724812984,41.6196975708],"type":"Point"}
}