{
  "type": "Feature",
  "properties": {
    "addr:full":"Carr Albert Vives, 12 Seu D'urgell Lleida 25700",
    "addr:housenumber":"12",
    "addr:postcode":"25700",
    "addr:street":"Carr Albert Vives",
    "iso:country":"ES",
    "sg:address":"Carr Albert Vives, 12",
    "sg:city":"Seu D'urgell",
    "sg:orig_category":"Centros De Educaci\u00d3n Especial",
    "sg:phone":"+34 973 35 10 14",
    "sg:postcode":"25700",
    "sg:province":"Lleida",
    "wof:name":"Co%egi Public Mossen Albert Vives",
    "wof:placetype":"venue"
},
  "geometry": {"coordinates":[0.6439359784,41.5972938538],"type":"Point"}
}