{
  "type": "Feature",
  "properties": {
    "iso:country":"ES",
    "sg:address":"Calle de San Miguel, 32",
    "sg:city":"Chiva",
    "sg:orig_category":"Reposter\u00cdas",
    "sg:phone":"+34 962 52 25 83",
    "sg:postcode":"46370",
    "sg:province":"Valencia",
    "wof:name":"Martinez Navarro Maria Eugenia",
    "wof:placetype":"venue"
},
  "geometry": {"coordinates":[-0.7151563168,39.4723625183],"type":"Point"}
}