{
  "type": "Feature",
  "properties": {
    "addr:full":"Navarro Villoslada, 1 Iru\u00f1a Navarra 31004",
    "addr:housenumber":"1",
    "addr:postcode":"31004",
    "addr:street":"Villoslada",
    "iso:country":"ES",
    "sg:address":"Navarro Villoslada, 1",
    "sg:city":"Iru\u00f1a",
    "sg:classifiers":[
        {
            "category":"Government",
            "subcategory":"Post Office",
            "type":"Public Place"
        }
    ],
    "sg:phone":"+34 948 23 82 45",
    "sg:postcode":"31004",
    "sg:province":"Navarra",
    "sg:tags":[
        "de",
        "yoga",
        "clases"
    ],
    "wof:name":"Heather 2",
    "wof:placetype":"venue"
},
  "geometry": {"coordinates":[-1.6395599842,42.8127174377],"type":"Point"}
}