{
  "type": "Feature",
  "properties": {
    "addr:full":"Calle de Betanzos, 4 Coru\u00d1a La Coru\u00f1a 15004",
    "addr:housenumber":"4",
    "addr:postcode":"15004",
    "addr:street":"Calle De Betanzos;La Corun\u0303A",
    "iso:country":"ES",
    "sg:address":"Calle de Betanzos, 4",
    "sg:city":"Coru\u00d1a",
    "sg:orig_category":"M\u00c9dicos: Ginecolog\u00cda Y Obstetricia",
    "sg:phone":"+34 981 22 40 76",
    "sg:postcode":"15004",
    "sg:province":"La Coru\u00f1a",
    "wof:name":"Puente Diaz-santamarina Pelayo",
    "wof:placetype":"venue"
},
  "geometry": {"coordinates":[-8.4082012177,43.3661117554],"type":"Point"}
}