{
  "type": "Feature",
  "properties": {
    "addr:full":"Carrer de Muntaner, 87 Barcelona Barcelona 08036",
    "addr:housenumber":"87",
    "addr:postcode":"08036",
    "addr:street":"Carrer De Muntaner",
    "iso:country":"ES",
    "sg:address":"Carrer de Muntaner, 87",
    "sg:city":"Barcelona",
    "sg:orig_category":"Pintores",
    "sg:phone":"+34 934 54 90 94",
    "sg:postcode":"08036",
    "sg:province":"Barcelona",
    "wof:name":"Alert Doval Eliseo",
    "wof:placetype":"venue"
},
  "geometry": {"coordinates":[2.157197237,41.3882789612],"type":"Point"}
}