{
  "type": "Feature",
  "properties": {
    "iso:country":"ES",
    "sg:address":"Palo Blanco, 2",
    "sg:city":"Realejos, Los",
    "sg:orig_category":"T\u00c9cnicos Veterinarios",
    "sg:phone":"+34 922 35 59 07",
    "sg:postcode":"38410",
    "sg:province":"Santa Cruz De Tenerife",
    "wof:name":"Garcia Garcia Jose Enrique",
    "wof:placetype":"venue"
},
  "geometry": {"coordinates":[-16.5846748352,28.3677654266],"type":"Point"}
}