{
  "type": "Feature",
  "properties": {
    "addr:full":"Carrer de Cervantes, 2 S. Just Desvern Barcelona 08960",
    "addr:housenumber":"2",
    "addr:postcode":"08960",
    "addr:street":"Carrer De Cervantes",
    "iso:country":"ES",
    "sg:address":"Carrer de Cervantes, 2",
    "sg:city":"S. Just Desvern",
    "sg:orig_category":"Marroquiner\u00cda (confecci\u00d3n)",
    "sg:phone":"+34 933 72 17 51",
    "sg:postcode":"08960",
    "sg:province":"Barcelona",
    "wof:name":"Campos Delgado Antonio",
    "wof:placetype":"venue"
},
  "geometry": {"coordinates":[2.0671839714,41.3812522888],"type":"Point"}
}