{
  "type": "Feature",
  "properties": {
    "addr:full":"Av Paisos Catalans, 15 Balaguer Lleida 25600",
    "addr:housenumber":"15",
    "addr:postcode":"25600",
    "addr:street":"Av Paisos Catalans",
    "iso:country":"ES",
    "sg:address":"Av Paisos Catalans, 15",
    "sg:city":"Balaguer",
    "sg:orig_category":"Ropa De Casa (fabricaci\u00d3n, Al Por Mayor)",
    "sg:phone":"+34 973 45 13 19",
    "sg:postcode":"25600",
    "sg:province":"Lleida",
    "wof:name":"Camarasa Ramells Lourdes",
    "wof:placetype":"venue"
},
  "geometry": {"coordinates":[0.807765007,41.7867584229],"type":"Point"}
}