{
  "type": "Feature",
  "properties": {
    "iso:country":"ES",
    "sg:address":"Calle de Lagasca, 115",
    "sg:city":"Madrid",
    "sg:orig_category":"Financiaci\u00d3n Y Cr\u00c9ditos",
    "sg:phone":"+34 915 61 47 71",
    "sg:postcode":"28006",
    "sg:province":"Madrid",
    "wof:name":"Hossain Perez Isabel Maria",
    "wof:placetype":"venue"
},
  "geometry": {"coordinates":[-3.684525013,40.4356117249],"type":"Point"}
}