{
  "type": "Feature",
  "properties": {
    "iso:country":"ES",
    "sg:address":"Carrer de Varsovia, 135",
    "sg:city":"Barcelona",
    "sg:classifiers":[
        {
            "category":"Autos & Motor Vehicles",
            "subcategory":"Automobile Sales",
            "type":"Retail Goods"
        }
    ],
    "sg:phone":"+34 933 47 91 38",
    "sg:postcode":"08041",
    "sg:province":"Barcelona",
    "wof:name":"Santamaria Gomez Jose Luis",
    "wof:placetype":"venue"
},
  "geometry": {"coordinates":[2.1725950241,41.41796875],"type":"Point"}
}