{
  "type": "Feature",
  "properties": {
    "addr:full":"Praz Pedro Monteagudo, 3 Ourense Ourense 32002",
    "addr:housenumber":"3",
    "addr:postcode":"32002",
    "addr:street":"Praz Pedro Monteagudo",
    "iso:country":"ES",
    "sg:address":"Praz Pedro Monteagudo, 3",
    "sg:city":"Ourense",
    "sg:orig_category":"Lavado, Limpieza De Veh\u00cdculos",
    "sg:phone":"+34 988 24 46 13",
    "sg:postcode":"32002",
    "sg:province":"Ourense",
    "wof:name":"Fernandez Gomez Jose Luis",
    "wof:placetype":"venue"
},
  "geometry": {"coordinates":[-7.8724598885,42.342010498],"type":"Point"}
}