{
  "type": "Feature",
  "properties": {
    "iso:country":"ES",
    "sg:address":"Calle de Rosalinda, S/n",
    "sg:city":"Sangonera La Verde O Ermita Nueva",
    "sg:orig_category":"Asilos De Ancianos. Centros Privados",
    "sg:phone":"+34 968 86 89 55",
    "sg:postcode":"30833",
    "sg:province":"Murcia",
    "wof:name":"Club De La Tercera Edad",
    "wof:placetype":"venue"
},
  "geometry": {"coordinates":[-1.2103639841,37.9291381836],"type":"Point"}
}