{
  "type": "Feature",
  "properties": {
    "addr:full":"Carrer de Bailen, 71 Terrassa Barcelona 08224",
    "addr:housenumber":"71",
    "addr:postcode":"08224",
    "addr:street":"Carrer De Bailen",
    "iso:country":"ES",
    "sg:address":"Carrer de Bailen, 71",
    "sg:city":"Terrassa",
    "sg:orig_category":"Sales (al Por Mayor)",
    "sg:phone":"+34 937 80 59 87",
    "sg:postcode":"08224",
    "sg:province":"Barcelona",
    "wof:name":"Gutierrez Sanchez Lidia",
    "wof:placetype":"venue"
},
  "geometry": {"coordinates":[1.9879499674,41.558719635],"type":"Point"}
}