{
  "type": "Feature",
  "properties": {
    "addr:full":"Calle de Korreo Kalea, 32 Tolosa Guip\u00f9zcoa 20400",
    "addr:housenumber":"32",
    "addr:postcode":"20400",
    "addr:street":"Calle De Korreo Kalea;Guipu\u0300Zcoa",
    "iso:country":"ES",
    "sg:address":"Calle de Korreo Kalea, 32",
    "sg:city":"Tolosa",
    "sg:orig_category":"Art\u00cdculos De Regalo (al Por Menor)",
    "sg:phone":"+34 943 67 32 39",
    "sg:postcode":"20400",
    "sg:province":"Guip\u00f9zcoa",
    "wof:name":"Altuna Zubelzu Maria Luisa",
    "wof:placetype":"venue"
},
  "geometry": {"coordinates":[-2.0729539394,43.1383934021],"type":"Point"}
}