{
  "type": "Feature",
  "properties": {
    "addr:full":"Carrer de Hug De Mataplana, 5 Santa Pon\u00c7a Islas Baleares 07180",
    "addr:housenumber":"5",
    "addr:postcode":"07180",
    "addr:street":"Carrer De Hug De Mataplana",
    "iso:country":"ES",
    "sg:address":"Carrer de Hug De Mataplana, 5",
    "sg:city":"Santa Pon\u00c7a",
    "sg:orig_category":"Iglesias Evang\u00c9licas",
    "sg:phone":"+34 971 69 50 90",
    "sg:postcode":"07180",
    "sg:province":"Islas Baleares",
    "wof:name":"Comunidad Evangelica De Habla Alemana De Baleares",
    "wof:placetype":"venue"
},
  "geometry": {"coordinates":[2.4700100422,39.5212135315],"type":"Point"}
}