{
  "type": "Feature",
  "properties": {
    "addr:full":"Luga Eirasvedras, 3 Eirasvedras Ourense 32001",
    "addr:housenumber":"3",
    "addr:postcode":"32001",
    "addr:street":"Eirasvedras",
    "iso:country":"ES",
    "sg:address":"Luga Eirasvedras, 3",
    "sg:city":"Eirasvedras",
    "sg:orig_category":"Alimentaci\u00d3n General (al Por Menor)",
    "sg:phone":"+34 988 21 68 34",
    "sg:postcode":"32001",
    "sg:province":"Ourense",
    "wof:name":"Vazquez Vazquez Antonio",
    "wof:placetype":"venue"
},
  "geometry": {"coordinates":[-7.9139170647,42.3556938171],"type":"Point"}
}