{
  "type": "Feature",
  "properties": {
    "iso:country":"ES",
    "sg:address":"Av Catalunya, S/n",
    "sg:city":"Vilanova D'escornalbou",
    "sg:orig_category":"Empresas De Desmonte",
    "sg:phone":"+34 977 83 74 23",
    "sg:postcode":"43311",
    "sg:province":"Tarragona",
    "wof:name":"Excavacions Mestral S.l.",
    "wof:placetype":"venue"
},
  "geometry": {"coordinates":[1.2549170256,41.1184883118],"type":"Point"}
}