{
  "type": "Feature",
  "properties": {
    "addr:full":"Calle de Petit, S/n Calpe Alicante 03710",
    "addr:housenumber":"/ n",
    "addr:postcode":"03710",
    "addr:street":"Calle De Petit S",
    "iso:country":"ES",
    "sg:address":"Calle de Petit, S/n",
    "sg:city":"Calpe",
    "sg:orig_category":"Centros De Coordinaci\u00d3n",
    "sg:phone":"+34 965 83 41 24",
    "sg:postcode":"03710",
    "sg:province":"Alicante",
    "wof:name":"Buigues Soler Antonio Jose",
    "wof:placetype":"venue"
},
  "geometry": {"coordinates":[0.0412949994,38.6450843811],"type":"Point"}
}