{
  "type": "Feature",
  "properties": {
    "iso:country":"ES",
    "sg:address":"Los Yelsos, S/n",
    "sg:city":"Monta\u00d1ana",
    "sg:orig_category":"Explotaci\u00d3n De Canteras",
    "sg:phone":"+34 947 35 90 28",
    "sg:postcode":"09219",
    "sg:province":"Burgos",
    "wof:name":"Gomez De Cadi\u00f1anos Lopez De Silanes Elisa",
    "wof:placetype":"venue"
},
  "geometry": {"coordinates":[-3.0773189068,42.6026649475],"type":"Point"}
}