{
  "type": "Feature",
  "properties": {
    "iso:country":"ES",
    "sg:address":"Calle de Jerusalen, 2",
    "sg:city":"Parla",
    "sg:orig_category":"Empresarios",
    "sg:phone":"+34 916 98 32 91",
    "sg:postcode":"28980",
    "sg:province":"Madrid",
    "wof:name":"Calero Fernandez Jose",
    "wof:placetype":"venue"
},
  "geometry": {"coordinates":[-3.7733020782,40.2360115051],"type":"Point"}
}