{
  "type": "Feature",
  "properties": {
    "addr:full":"Pio Xii, 12 Setenil C\u00e1diz 11692",
    "addr:housenumber":"12",
    "addr:postcode":"11692",
    "addr:street":"Pio Xii;Ca\u0301Diz",
    "iso:country":"ES",
    "sg:address":"Pio Xii, 12",
    "sg:city":"Setenil",
    "sg:orig_category":"Frutas, Legumbres Frescas Y Tempranas (al Por Menor)",
    "sg:phone":"+34 956 13 42 51",
    "sg:postcode":"11692",
    "sg:province":"C\u00e1diz",
    "wof:name":"Super Pedrin S.l.",
    "wof:placetype":"venue"
},
  "geometry": {"coordinates":[-5.1807961464,36.8622322083],"type":"Point"}
}