{
  "type": "Feature",
  "properties": {
    "addr:full":"Carrer de Puig Del Ravell, 21 Martorell Barcelona 08760",
    "addr:housenumber":"21",
    "addr:postcode":"08760",
    "addr:street":"Carrer De Puig Del Ravell",
    "iso:country":"ES",
    "sg:address":"Carrer de Puig Del Ravell, 21",
    "sg:city":"Martorell",
    "sg:orig_category":"Comercio De Piezas De Recambio Y De Accesorios De Veh\u00cdculos, Veh\u00cdculos Industriales",
    "sg:phone":"+34 937 76 98 08",
    "sg:postcode":"08760",
    "sg:province":"Barcelona",
    "wof:name":"Soto Requejo Oscar",
    "wof:placetype":"venue"
},
  "geometry": {"coordinates":[1.9142489433,41.4780006409],"type":"Point"}
}