{
  "type": "Feature",
  "properties": {
    "iso:country":"ES",
    "sg:address":"Calle de Triana, 4",
    "sg:city":"Palmas De Gran Canaria",
    "sg:orig_category":"Asesor\u00cda De Formaci\u00d3n Y Gesti\u00d3n De Personal",
    "sg:phone":"+34 928 36 07 64",
    "sg:postcode":"35002",
    "sg:province":"Las Palmas",
    "wof:name":"Guerra Y Asociados S.c.p.",
    "wof:placetype":"venue"
},
  "geometry": {"coordinates":[-15.414317131,28.1030921936],"type":"Point"}
}