{
  "type": "Feature",
  "properties": {
    "iso:country":"ES",
    "sg:address":"Ctra. Valmojado, 19",
    "sg:city":"Cedillo Condado",
    "sg:orig_category":"Muebles, Minoristas",
    "sg:phone":"+34 925 50 84 27",
    "sg:postcode":"45214",
    "sg:province":"Toledo",
    "wof:name":"Martin Gonzalez Concepcion",
    "wof:placetype":"venue"
},
  "geometry": {"coordinates":[-3.9259839058,40.1141433716],"type":"Point"}
}