{
  "type": "Feature",
  "properties": {
    "addr:full":"Calle de Pedreguer, 22 Denia Alicante 03700",
    "addr:housenumber":"22",
    "addr:postcode":"03700",
    "addr:street":"Calle De Pedreguer",
    "iso:country":"ES",
    "sg:address":"Calle de Pedreguer, 22",
    "sg:city":"Denia",
    "sg:orig_category":"Muebles, Minoristas",
    "sg:phone":"+34 965 78 38 74",
    "sg:postcode":"03700",
    "sg:province":"Alicante",
    "wof:name":"Cavibersa Hogar S.l.",
    "wof:placetype":"venue"
},
  "geometry": {"coordinates":[0.1074099988,38.8348999023],"type":"Point"}
}