{
  "type": "Feature",
  "properties": {
    "addr:full":"Calle de Torres (de Las), 1 Cuenca Cuenca 16001",
    "addr:housenumber":"1",
    "addr:postcode":"16001",
    "addr:street":"Calle De Torres De Las",
    "iso:country":"ES",
    "sg:address":"Calle de Torres (de Las), 1",
    "sg:city":"Cuenca",
    "sg:orig_category":"Hoteles",
    "sg:phone":"+34 969 21 17 04",
    "sg:postcode":"16001",
    "sg:province":"Cuenca",
    "wof:name":"Alvarez Collado Eva",
    "wof:placetype":"venue"
},
  "geometry": {"coordinates":[-2.1333050728,40.0725708008],"type":"Point"}
}