{
  "type": "Feature",
  "properties": {
    "iso:country":"ES",
    "sg:address":"Calle de San Lorenzo, 2",
    "sg:city":"Huesca",
    "sg:orig_category":"Institutos De Belleza",
    "sg:phone":"+34 974 24 48 80",
    "sg:postcode":"22002",
    "sg:province":"Huesca",
    "wof:name":"Catalan Craver Maria Angeles",
    "wof:placetype":"venue"
},
  "geometry": {"coordinates":[-0.4063979983,42.1366233826],"type":"Point"}
}