{
  "type": "Feature",
  "properties": {
    "iso:country":"ES",
    "sg:address":"Calle de Laguna, 4",
    "sg:city":"Conil De La Frontera",
    "sg:orig_category":"Cajas De Ahorro",
    "sg:phone":"+34 956 44 33 47",
    "sg:postcode":"11140",
    "sg:province":"C\u00e1diz",
    "wof:name":"Cajagranada",
    "wof:placetype":"venue"
},
  "geometry": {"coordinates":[-6.0875921249,36.2777519226],"type":"Point"}
}