{
  "type": "Feature",
  "properties": {
    "addr:full":"Avda Ramon Y Cajal, 1 Borja Zaragoza 50540",
    "addr:housenumber":"1",
    "addr:postcode":"50540",
    "addr:street":"Avda Ramon Y Cajal",
    "iso:country":"ES",
    "sg:address":"Avda Ramon Y Cajal, 1",
    "sg:city":"Borja",
    "sg:classifiers":[
        {
            "category":"Cinema",
            "subcategory":"Movie Theater",
            "type":"Entertainment"
        }
    ],
    "sg:phone":"+34 976 85 29 33",
    "sg:postcode":"50540",
    "sg:province":"Zaragoza",
    "sg:tags":[
        "salas",
        "de",
        "cine"
    ],
    "wof:name":"Ayuntamiento De Borja",
    "wof:placetype":"venue"
},
  "geometry": {"coordinates":[-1.5334830284,41.8316497803],"type":"Point"}
}