{
  "type": "Feature",
  "properties": {
    "iso:country":"ES",
    "sg:address":"Carrer de Miquel Servet, 86",
    "sg:city":"Manresa",
    "sg:orig_category":"Ebanister\u00cda",
    "sg:phone":"+34 938 74 53 58",
    "sg:postcode":"08243",
    "sg:province":"Barcelona",
    "wof:name":"Rosado Gil Manuel",
    "wof:placetype":"venue"
},
  "geometry": {"coordinates":[1.8466000557,41.7087898254],"type":"Point"}
}