{
  "type": "Feature",
  "properties": {
    "addr:full":"Rua De Arriba, 36 Cee La Coru\u00f1a 15270",
    "addr:housenumber":"36",
    "addr:postcode":"15270",
    "addr:street":"Rua De Arriba;La",
    "iso:country":"ES",
    "sg:address":"Rua De Arriba, 36",
    "sg:city":"Cee",
    "sg:orig_category":"Supermercados Y Hipermercados",
    "sg:phone":"+34 981 74 71 07",
    "sg:postcode":"15270",
    "sg:province":"La Coru\u00f1a",
    "sg:website":"www.froiz.com",
    "wof:name":"Distribuciones Froiz S.a.",
    "wof:placetype":"venue"
},
  "geometry": {"coordinates":[-9.1878881454,42.9546318054],"type":"Point"}
}