{
  "type": "Feature",
  "properties": {
    "iso:country":"ES",
    "sg:address":"Calle de Doctor Chil, 26",
    "sg:city":"Becerril",
    "sg:orig_category":"Alimentaci\u00d3n General (al Por Menor)",
    "sg:phone":"+34 928 88 20 97",
    "sg:postcode":"35450",
    "sg:province":"Las Palmas",
    "wof:name":"Santana Brito Maria Isabel",
    "wof:placetype":"venue"
},
  "geometry": {"coordinates":[-15.6319208145,28.1403903961],"type":"Point"}
}