{
  "type": "Feature",
  "properties": {
    "iso:country":"ES",
    "sg:address":"Calle de Barberia, 8",
    "sg:city":"S.gregorio",
    "sg:orig_category":"Psic\u00d3logos",
    "sg:phone":"+34 928 68 23 97",
    "sg:postcode":"35200",
    "sg:province":"Las Palmas",
    "wof:name":"Romero Deniz Miguel",
    "wof:placetype":"venue"
},
  "geometry": {"coordinates":[-15.4300060272,28.1248226166],"type":"Point"}
}