{
  "type": "Feature",
  "properties": {
    "iso:country":"ES",
    "sg:address":"Calle de Alcalde Luis Pascual, 47",
    "sg:city":"Caudete",
    "sg:orig_category":"Farmacias",
    "sg:phone":"+34 965 82 74 37",
    "sg:postcode":"02660",
    "sg:province":"Albacete",
    "wof:name":"Ramon Vidal Fernando",
    "wof:placetype":"venue"
},
  "geometry": {"coordinates":[-0.9853494763,38.7029380798],"type":"Point"}
}