{
  "type": "Feature",
  "properties": {
    "iso:country":"ES",
    "sg:address":"Avda Ferrocarril, 7",
    "sg:city":"Bilbao",
    "sg:orig_category":"Mec\u00c1nico Del Autom\u00d3vil",
    "sg:phone":"+34 944 43 52 86",
    "sg:postcode":"48012",
    "sg:province":"Vizcaya",
    "wof:name":"Gomez Ansual Francisco Javier",
    "wof:placetype":"venue"
},
  "geometry": {"coordinates":[-2.9456501007,43.2565155029],"type":"Point"}
}