{
  "type": "Feature",
  "properties": {
    "iso:country":"ES",
    "sg:address":"Ctra. De Villagonzalo, Km. 0006,0",
    "sg:city":"Valverde Merida",
    "sg:orig_category":"Ferreter\u00cda (diversos)",
    "sg:phone":"+34 924 12 31 61",
    "sg:postcode":"06890",
    "sg:province":"Badajoz",
    "wof:name":"Chatarreria Fu-manchu S.l.",
    "wof:placetype":"venue"
},
  "geometry": {"coordinates":[-6.2238101959,38.9112167358],"type":"Point"}
}