{
  "type": "Feature",
  "properties": {
    "iso:country":"ES",
    "sg:address":"Calle de Alberique, 23",
    "sg:city":"Valencia",
    "sg:orig_category":"Transportes Por Carretera: Lotes Completos, Mercanc\u00cdas Diversas",
    "sg:phone":"+34 963 13 04 94",
    "sg:postcode":"46008",
    "sg:province":"Valencia",
    "wof:name":"Transportes Logistica Volval S.l.",
    "wof:placetype":"venue"
},
  "geometry": {"coordinates":[-0.3886210024,39.467048645],"type":"Point"}
}