{
  "type": "Feature",
  "properties": {
    "addr:full":"Calle de Garcia Prieto, 7 Astorga Le\u00f3n 24700",
    "addr:housenumber":"7",
    "addr:postcode":"24700",
    "addr:street":"Calle De Garcia Prieto;Leo\u0301N",
    "iso:country":"ES",
    "sg:address":"Calle de Garcia Prieto, 7",
    "sg:city":"Astorga",
    "sg:orig_category":"Bisuter\u00cda, Joyer\u00cda, Relojer\u00cda (al Por Menor)",
    "sg:phone":"+34 987 61 67 61",
    "sg:postcode":"24700",
    "sg:province":"Le\u00f3n",
    "wof:name":"Ja\u00f1ez S.l.",
    "wof:placetype":"venue"
},
  "geometry": {"coordinates":[-6.0547480583,42.455745697],"type":"Point"}
}