{
  "type": "Feature",
  "properties": {
    "iso:country":"ES",
    "sg:address":"Pg Can Mora, S/n",
    "sg:city":"S. Cugat Valles",
    "sg:classifiers":[
        {
            "category":"Sports & Exercise",
            "subcategory":"Golf",
            "type":"Entertainment"
        }
    ],
    "sg:phone":"+34 936 75 30 50",
    "sg:postcode":"08173",
    "sg:province":"Barcelona",
    "sg:tags":[
        "y",
        "de",
        "campos",
        "clases"
    ],
    "wof:name":"Can Sant Joan S.a.",
    "wof:placetype":"venue"
},
  "geometry": {"coordinates":[2.0768899918,41.4623985291],"type":"Point"}
}