{
  "type": "Feature",
  "properties": {
    "iso:country":"ES",
    "sg:address":"Carrer de L'escorial, 47",
    "sg:city":"Barcelona",
    "sg:orig_category":"Molduras, Junquillos, Listones Y Molduras Perforadas",
    "sg:phone":"+34 932 13 10 70",
    "sg:postcode":"08024",
    "sg:province":"Barcelona",
    "wof:name":"Escude Romeu Jaime",
    "wof:placetype":"venue"
},
  "geometry": {"coordinates":[2.1605839729,41.4080886841],"type":"Point"}
}