{
  "type": "Feature",
  "properties": {
    "iso:country":"ES",
    "sg:address":"Cmno Monte (del), S/n",
    "sg:city":"Moraleja Enmedio",
    "sg:orig_category":"Art\u00cdculos De Madera (fabricaci\u00d3n Y Al Por Mayor)",
    "sg:phone":"+34 916 09 40 13",
    "sg:postcode":"28950",
    "sg:province":"Madrid",
    "wof:name":"Marhopal S.l.",
    "wof:placetype":"venue"
},
  "geometry": {"coordinates":[-3.8522839546,40.2605247498],"type":"Point"}
}