{
  "type": "Feature",
  "properties": {
    "iso:country":"ES",
    "sg:address":"Calle de Iglesia, 37",
    "sg:city":"Madrid",
    "sg:orig_category":"M\u00c9dicos: Fisioterapia Y Rehabilitaci\u00d3n",
    "sg:phone":"+34 912 97 79 62",
    "sg:postcode":"28039",
    "sg:province":"Madrid",
    "wof:name":"Alberto Gallego De Belaunde",
    "wof:placetype":"venue"
},
  "geometry": {"coordinates":[-3.7178821564,40.3959007263],"type":"Point"}
}