{
  "type": "Feature",
  "properties": {
    "iso:country":"ES",
    "sg:address":"Carrer de Ballester, 22",
    "sg:city":"Barcelona",
    "sg:orig_category":"Inmobiliaria (agencias)",
    "sg:phone":"+34 934 17 05 63",
    "sg:postcode":"08023",
    "sg:province":"Barcelona",
    "wof:name":"Gemric Inmobiliaria S.l.",
    "wof:placetype":"venue"
},
  "geometry": {"coordinates":[2.1458730698,41.4066925049],"type":"Point"}
}