{
  "type": "Feature",
  "properties": {
    "iso:country":"ES",
    "sg:address":"Ctra Martorell, 224",
    "sg:city":"Terrassa",
    "sg:orig_category":"M\u00c1quinas Textiles, Accesorios Y Suministros (fabricaci\u00d3n)",
    "sg:phone":"+34 937 80 60 26",
    "sg:postcode":"08224",
    "sg:province":"Barcelona",
    "sg:website":"www.peymartex.com",
    "wof:name":"Peymartex S.l.",
    "wof:placetype":"venue"
},
  "geometry": {"coordinates":[2.0001499653,41.5548248291],"type":"Point"}
}