{
  "type": "Feature",
  "properties": {
    "iso:country":"ES",
    "sg:address":"Avda Daroca, 90",
    "sg:city":"Madrid",
    "sg:orig_category":"Cementerios",
    "sg:phone":"+34 915 10 84 64",
    "sg:postcode":"28...",
    "sg:province":"Madrid",
    "wof:name":"Empresa Mixta De Servicios Funerarios De Madrid S.a.",
    "wof:placetype":"venue"
},
  "geometry": {"coordinates":[-3.6486608982,40.4277038574],"type":"Point"}
}