{
  "type": "Feature",
  "properties": {
    "iso:country":"ES",
    "sg:address":"Fuero Del Trabajo, 11",
    "sg:city":"Burgos",
    "sg:classifiers":[
        {
            "category":"Professional",
            "subcategory":"Management & Consulting",
            "type":"Services"
        }
    ],
    "sg:phone":"+34 947 48 28 71",
    "sg:postcode":"09007",
    "sg:province":"Burgos",
    "sg:tags":[
        "asesor\u00cda",
        "en",
        "marketing"
    ],
    "wof:name":"Moneo Solas Alberto",
    "wof:placetype":"venue"
},
  "geometry": {"coordinates":[-3.6432430744,42.3629989624],"type":"Point"}
}