{
  "type": "Feature",
  "properties": {
    "iso:country":"ES",
    "sg:address":"Calle de San Juan Bautista, S/n",
    "sg:city":"S. Fernando",
    "sg:orig_category":"Asociaciones, Organismos Culturales Y Socioeducativos",
    "sg:phone":"+34 956 59 57 40",
    "sg:postcode":"11100",
    "sg:province":"C\u00e1diz",
    "wof:name":"Pe\u00f1a Carnavalesca Los Pollitos Mi Compare",
    "wof:placetype":"venue"
},
  "geometry": {"coordinates":[-6.193089962,36.4725456238],"type":"Point"}
}