{
  "type": "Feature",
  "properties": {
    "iso:country":"ES",
    "sg:address":"Calle de Zapateria, 22",
    "sg:city":"Vitoria-gasteiz",
    "sg:orig_category":"Pintores",
    "sg:phone":"+34 945 25 41 06",
    "sg:postcode":"01001",
    "sg:province":"\u00c1lava",
    "wof:name":"Ugarte Bejega Victor",
    "wof:placetype":"venue"
},
  "geometry": {"coordinates":[-2.6737880707,42.8475646973],"type":"Point"}
}