{
  "type": "Feature",
  "properties": {
    "addr:full":"Carrer de Consolat De Mar, 11 Pineda Mar Barcelona 08397",
    "addr:housenumber":"11",
    "addr:postcode":"08397",
    "addr:street":"Carrer De Consolat De Mar;Barcelona",
    "iso:country":"ES",
    "sg:address":"Carrer de Consolat De Mar, 11",
    "sg:city":"Pineda Mar",
    "sg:orig_category":"Doctores En Medicina",
    "sg:phone":"+34 937 62 34 40",
    "sg:postcode":"08397",
    "sg:province":"Barcelona",
    "wof:name":"Tusell Andreu Javier",
    "wof:placetype":"venue"
},
  "geometry": {"coordinates":[2.695909977,41.623249054],"type":"Point"}
}