{
  "type": "Feature",
  "properties": {
    "addr:full":"Calle de Carmen, 1 Villafranco Guadiana Badajoz 06195",
    "addr:housenumber":"1",
    "addr:postcode":"06195",
    "addr:street":"Calle De Carmen",
    "iso:country":"ES",
    "sg:address":"Calle de Carmen, 1",
    "sg:city":"Villafranco Guadiana",
    "sg:orig_category":"Discotecas Y Salas De Baile",
    "sg:phone":"+34 924 44 37 46",
    "sg:postcode":"06195",
    "sg:province":"Badajoz",
    "wof:name":"Perez Garcia Francisco",
    "wof:placetype":"venue"
},
  "geometry": {"coordinates":[-6.8581442833,38.8843650818],"type":"Point"}
}