{
  "type": "Feature",
  "properties": {
    "iso:country":"ES",
    "sg:address":"Calle de Padre Salvador Barri, 6",
    "sg:city":"Onda",
    "sg:orig_category":"Inmobiliaria (agencias)",
    "sg:phone":"+34 964 60 07 03",
    "sg:postcode":"12200",
    "sg:province":"Castell\u00f3n",
    "wof:name":"Eryja S.l.",
    "wof:placetype":"venue"
},
  "geometry": {"coordinates":[-0.2638989985,39.9632225037],"type":"Point"}
}