{
  "type": "Feature",
  "properties": {
    "addr:full":"Carrer de Permanyer, 205 Sabadell Barcelona 08205",
    "addr:housenumber":"205",
    "addr:postcode":"08205",
    "addr:street":"Carrer De Permanyer",
    "iso:country":"ES",
    "sg:address":"Carrer de Permanyer, 205",
    "sg:city":"Sabadell",
    "sg:orig_category":"Rectificaci\u00d3n, Mecanizado, Fresado",
    "sg:phone":"+34 937 11 93 84",
    "sg:postcode":"08205",
    "sg:province":"Barcelona",
    "sg:website":"www.erosionfil.com",
    "wof:name":"Erosionfil S.l.",
    "wof:placetype":"venue"
},
  "geometry": {"coordinates":[2.1023790836,41.5352706909],"type":"Point"}
}