{
  "type": "Feature",
  "properties": {
    "iso:country":"ES",
    "sg:address":"Calle de Puerto Serrano, 9",
    "sg:city":"Madrid",
    "sg:orig_category":"Prot\u00c9sicos Dentales",
    "sg:phone":"+34 915 27 36 49",
    "sg:postcode":"28045",
    "sg:province":"Madrid",
    "wof:name":"Guzman Llanten Luis Enrique",
    "wof:placetype":"venue"
},
  "geometry": {"coordinates":[-3.6873219013,40.3862800598],"type":"Point"}
}