{
  "type": "Feature",
  "properties": {
    "iso:country":"ES",
    "sg:address":"Calle de Tartago, 3",
    "sg:city":"Palmas De Gran Canaria",
    "sg:orig_category":"Int\u00c9rpretes",
    "sg:phone":"+34 928 33 39 64",
    "sg:postcode":"35015",
    "sg:province":"Las Palmas",
    "wof:name":"Rodriguez Santana Jacobo",
    "wof:placetype":"venue"
},
  "geometry": {"coordinates":[-15.4196901321,28.0965862274],"type":"Point"}
}