{
  "type": "Feature",
  "properties": {
    "iso:country":"ES",
    "sg:address":"Calle de Iglesia, S/n",
    "sg:city":"Algadefe",
    "sg:orig_category":"Centros De Educaci\u00d3n Especial",
    "sg:phone":"+34 987 76 05 76",
    "sg:postcode":"24238",
    "sg:province":"Le\u00f3n",
    "wof:name":"Colegio Publico Rural Agrupado Vega Del Esla",
    "wof:placetype":"venue"
},
  "geometry": {"coordinates":[-5.5880742073,42.1794967651],"type":"Point"}
}