{
  "type": "Feature",
  "properties": {
    "iso:country":"ES",
    "sg:address":"Calle de Baja Del Mar, 25",
    "sg:city":"Almu\u00f1ecar",
    "sg:orig_category":"Zapatos (al Por Menor)",
    "sg:phone":"+34 958 63 47 00",
    "sg:postcode":"18690",
    "sg:province":"Granada",
    "wof:name":"Molero Ruiz Maria Encarnacion",
    "wof:placetype":"venue"
},
  "geometry": {"coordinates":[-3.6896622181,36.7321777344],"type":"Point"}
}