{
  "type": "Feature",
  "properties": {
    "iso:country":"ES",
    "sg:address":"Carretera Las Negras, 43",
    "sg:city":"Campohermoso",
    "sg:orig_category":"Asesor\u00cda De Formaci\u00d3n Y Gesti\u00d3n De Personal",
    "sg:phone":"+34 950 38 54 37",
    "sg:postcode":"04110",
    "sg:province":"Almer\u00eda",
    "wof:name":"Gestoria Mediterraneo S.c.a.",
    "wof:placetype":"venue"
},
  "geometry": {"coordinates":[-2.1384088993,36.9406242371],"type":"Point"}
}