{
  "type": "Feature",
  "properties": {
    "iso:country":"ES",
    "sg:address":"Calle de Tres De Agosto, 4",
    "sg:city":"Huelva",
    "sg:orig_category":"Arquitectos",
    "sg:phone":"+34 959 25 18 33",
    "sg:postcode":"21003",
    "sg:province":"Huelva",
    "wof:name":"Arquitarbe 1 S.l.",
    "wof:placetype":"venue"
},
  "geometry": {"coordinates":[-6.950489521,37.2579803467],"type":"Point"}
}