{
  "type": "Feature",
  "properties": {
    "addr:full":"Calle de Iglesia, S/n Codesal Zamora 49594",
    "addr:housenumber":"s / n",
    "addr:postcode":"49594",
    "addr:street":"Calle De Iglesia",
    "iso:country":"ES",
    "sg:address":"Calle de Iglesia, S/n",
    "sg:city":"Codesal",
    "sg:orig_category":"Centros De Educaci\u00d3n Especial",
    "sg:phone":"+34 980 65 49 56",
    "sg:postcode":"49594",
    "sg:province":"Zamora",
    "wof:name":"Colegio Rural Agrupado",
    "wof:placetype":"venue"
},
  "geometry": {"coordinates":[-6.3811092377,41.9697647095],"type":"Point"}
}