{
  "type": "Feature",
  "properties": {
    "iso:country":"ES",
    "sg:address":"Avda Francisco Gonzalez Rey, 64",
    "sg:city":"Celanova",
    "sg:classifiers":[
        {
            "category":"Taxi",
            "type":"Transportation"
        }
    ],
    "sg:phone":"+34 988 45 12 25",
    "sg:postcode":"32800",
    "sg:province":"Ourense",
    "wof:name":"Suarez Gonzalez Antonio",
    "wof:placetype":"venue"
},
  "geometry": {"coordinates":[-7.9546689987,42.1540718079],"type":"Point"}
}