{
  "type": "Feature",
  "properties": {
    "addr:full":"Rua Montero Rios (de), 39 Santiago De Compostela La Coru\u00f1a 15706",
    "addr:housenumber":"39",
    "addr:postcode":"15706",
    "addr:street":"Rua Montero Rios De;Corun\u0303A",
    "iso:country":"ES",
    "sg:address":"Rua Montero Rios (de), 39",
    "sg:city":"Santiago De Compostela",
    "sg:orig_category":"Caf\u00c9s, Bares, Cervecer\u00cdas",
    "sg:phone":"+34 981 59 36 36",
    "sg:postcode":"15706",
    "sg:province":"La Coru\u00f1a",
    "wof:name":"Carlos Monta\u00f1a Mosquera Y Miguel Via\u00f1o Illodo S.c.",
    "wof:placetype":"venue"
},
  "geometry": {"coordinates":[-8.5497617722,42.8753547668],"type":"Point"}
}