{
  "type": "Feature",
  "properties": {
    "addr:full":"Ctra Quintanar-alc., Km. 0006,5 Miguel Esteban Toledo 45830",
    "addr:postcode":"45830",
    "addr:street":"Ctra Quintanar-Alc. Km. 0006,5",
    "iso:country":"ES",
    "sg:address":"Ctra Quintanar-alc., Km. 0006,5",
    "sg:city":"Miguel Esteban",
    "sg:orig_category":"Mec\u00c1nico Del Autom\u00d3vil",
    "sg:phone":"+34 925 17 29 77",
    "sg:postcode":"45830",
    "sg:province":"Toledo",
    "wof:name":"Sanz Sanchez Tomas",
    "wof:placetype":"venue"
},
  "geometry": {"coordinates":[-3.0778141022,39.5287094116],"type":"Point"}
}