{
  "type": "Feature",
  "properties": {
    "addr:full":"Calle de Malaga, 5 Palmas De Gran Canaria Las Palmas 35016",
    "addr:housenumber":"5",
    "addr:postcode":"35016",
    "addr:street":"Calle De Malaga",
    "iso:country":"ES",
    "sg:address":"Calle de Malaga, 5",
    "sg:city":"Palmas De Gran Canaria",
    "sg:orig_category":"Quincaller\u00cda (al Por Menor)",
    "sg:phone":"+34 928 31 87 91",
    "sg:postcode":"35016",
    "sg:province":"Las Palmas",
    "wof:name":"Mejias Diaz Antolin",
    "wof:placetype":"venue"
},
  "geometry": {"coordinates":[-15.4149570465,28.0921325684],"type":"Point"}
}