{
  "type": "Feature",
  "properties": {
    "iso:country":"ES",
    "sg:address":"Calle de Lope De Vega, 2",
    "sg:city":"Rozas De Madrid",
    "sg:orig_category":"Arquitectos",
    "sg:phone":"+34 917 10 30 86",
    "sg:postcode":"28230",
    "sg:province":"Madrid",
    "wof:name":"Tecnica Arquitectonica Profesional S.a.",
    "wof:placetype":"venue"
},
  "geometry": {"coordinates":[-4.4442811012,40.3002128601],"type":"Point"}
}