{
  "type": "Feature",
  "properties": {
    "iso:country":"ES",
    "sg:address":"Avda Covadonga, 9",
    "sg:city":"Cangas Onis",
    "sg:orig_category":"Ropa Para Se\u00d1oras (al Por Menor)",
    "sg:phone":"+34 985 84 83 28",
    "sg:postcode":"33550",
    "sg:province":"Asturias",
    "wof:name":"Cayarga Suarez Gaspar",
    "wof:placetype":"venue"
},
  "geometry": {"coordinates":[-5.1302847862,43.350894928],"type":"Point"}
}