{
  "type": "Feature",
  "properties": {
    "addr:full":"Av. J. Barnola Basols, S/n Martorell Barcelona 08760",
    "addr:housenumber":"s / n",
    "addr:postcode":"08760",
    "addr:street":"Av. J. Barnola Basols",
    "iso:country":"ES",
    "sg:address":"Av. J. Barnola Basols, S/n",
    "sg:city":"Martorell",
    "sg:orig_category":"Colocaci\u00d3n, Mantenimiento, Vitrificaci\u00d3n De Parquets",
    "sg:phone":"+34 937 75 37 58",
    "sg:postcode":"08760",
    "sg:province":"Barcelona",
    "wof:name":"Pinturas Mabaper S.l.",
    "wof:placetype":"venue"
},
  "geometry": {"coordinates":[1.9264099598,41.4822044373],"type":"Point"}
}