{
  "type": "Feature",
  "properties": {
    "iso:country":"ES",
    "sg:address":"Calle de Eraso General, 1",
    "sg:city":"Bilbao",
    "sg:orig_category":"Suministros Para Carrocer\u00cdas",
    "sg:phone":"+34 944 75 93 16",
    "sg:postcode":"48014",
    "sg:province":"Vizcaya",
    "wof:name":"Rodriguez Garcia Isidro",
    "wof:placetype":"venue"
},
  "geometry": {"coordinates":[-2.9461190701,43.2686500549],"type":"Point"}
}