{
  "type": "Feature",
  "properties": {
    "addr:full":"Pol Ind Alfares, S/n Rambla C\u00f3rdoba 14540",
    "addr:housenumber":"s / n",
    "addr:postcode":"14540",
    "addr:street":"Rambla Co\u0301Rdoba",
    "iso:country":"ES",
    "sg:address":"Pol Ind Alfares, S/n",
    "sg:city":"Rambla",
    "sg:orig_category":"Cer\u00c1mica Art\u00cdstica Y Decorativa",
    "sg:phone":"+34 957 68 24 02",
    "sg:postcode":"14540",
    "sg:province":"C\u00f3rdoba",
    "wof:name":"Nadales Lucena Juan",
    "wof:placetype":"venue"
},
  "geometry": {"coordinates":[-4.7416338921,37.6080932617],"type":"Point"}
}