{
  "type": "Feature",
  "properties": {
    "addr:full":"Ctra Cortiguera, S/n Barcena Bierzo Le\u00f3n 24491",
    "addr:housenumber":"s / n",
    "addr:postcode":"24491",
    "addr:street":"Ctra Cortiguera",
    "iso:country":"ES",
    "sg:address":"Ctra Cortiguera, S/n",
    "sg:city":"Barcena Bierzo",
    "sg:orig_category":"Maquinaria Para Industrias Diversas",
    "sg:phone":"+34 987 45 80 31",
    "sg:postcode":"24491",
    "sg:province":"Le\u00f3n",
    "wof:name":"Rodriguez Castro Jose Manuel",
    "wof:placetype":"venue"
},
  "geometry": {"coordinates":[-6.5996789932,42.587146759],"type":"Point"}
}