{
  "type": "Feature",
  "properties": {
    "addr:full":"Calle de Juan Miro (de), 2 Colmenar Viejo Madrid 28770",
    "addr:postcode":"28770",
    "addr:street":"Calle De Juan Miro De",
    "iso:country":"ES",
    "sg:address":"Calle de Juan Miro (de), 2",
    "sg:city":"Colmenar Viejo",
    "sg:orig_category":"Agencias De Viajes",
    "sg:phone":"+34 918 45 68 57",
    "sg:postcode":"28770",
    "sg:province":"Madrid",
    "wof:name":"Zaes Link S.l.",
    "wof:placetype":"venue"
},
  "geometry": {"coordinates":[-3.7740569115,40.6713676453],"type":"Point"}
}