{
  "type": "Feature",
  "properties": {
    "addr:full":"Avda Principe De Asturias, S/n Gijon Asturias 33212",
    "addr:housenumber":"s",
    "addr:postcode":"33212",
    "addr:street":"Avda Principe De Asturias;/ N",
    "iso:country":"ES",
    "sg:address":"Avda Principe De Asturias, S/n",
    "sg:city":"Gijon",
    "sg:orig_category":"Metalurgia",
    "sg:phone":"+34 985 30 80 60",
    "sg:postcode":"33212",
    "sg:province":"Asturias",
    "wof:name":"Moreda Riviere Trefilerias S.a.",
    "wof:placetype":"venue"
},
  "geometry": {"coordinates":[-5.6924958229,43.5392379761],"type":"Point"}
}