{
  "type": "Feature",
  "properties": {
    "addr:full":"Pino Central (p I El Pino), 51 Sevilla Sevilla 41017",
    "addr:housenumber":"51",
    "addr:postcode":"41017",
    "addr:street":"El Pino",
    "iso:country":"ES",
    "sg:address":"Pino Central (p I El Pino), 51",
    "sg:city":"Sevilla",
    "sg:orig_category":"Postigos, Persianas Y Celos\u00cdas",
    "sg:phone":"+34 954 07 05 00",
    "sg:postcode":"41017",
    "sg:province":"Sevilla",
    "wof:name":"Mosquisur S.l.",
    "wof:placetype":"venue"
},
  "geometry": {"coordinates":[-5.9250087738,37.3796195984],"type":"Point"}
}