{
  "type": "Feature",
  "properties": {
    "iso:country":"ES",
    "sg:address":"Ctra Salamanca Caceres, Km. 0419,1",
    "sg:city":"Cantagallo",
    "sg:orig_category":"Carnicer\u00cdas, Carnicer\u00cdas",
    "sg:phone":"+34 923 41 17 16",
    "sg:postcode":"37792",
    "sg:province":"Salamanca",
    "wof:name":"Pedro Diego S.a.",
    "wof:placetype":"venue"
},
  "geometry": {"coordinates":[-5.6813669205,40.6881637573],"type":"Point"}
}