{
  "type": "Feature",
  "properties": {
    "addr:full":"C. Morcillo, S/n Gojar Granada 18150",
    "addr:housenumber":"s / n",
    "addr:postcode":"18150",
    "addr:street":"Morcillo",
    "iso:country":"ES",
    "sg:address":"C. Morcillo, S/n",
    "sg:city":"Gojar",
    "sg:orig_category":"Art\u00cdculos De Regalo (al Por Menor)",
    "sg:phone":"+34 958 50 36 89",
    "sg:postcode":"18150",
    "sg:province":"Granada",
    "wof:name":"Rodriguez Huertas Inmaculada",
    "wof:placetype":"venue"
},
  "geometry": {"coordinates":[-3.6035039425,37.0992965698],"type":"Point"}
}