{
  "type": "Feature",
  "properties": {
    "iso:country":"ES",
    "sg:address":"Carr Arquitecte Celles, 4",
    "sg:city":"Lleida",
    "sg:orig_category":"Arquitectos",
    "sg:phone":"+34 973 24 44 60",
    "sg:postcode":"25196",
    "sg:province":"Lleida",
    "wof:name":"Sarrate Boneu Jesus",
    "wof:placetype":"venue"
},
  "geometry": {"coordinates":[0.6073960066,41.6286964417],"type":"Point"}
}