{
  "type": "Feature",
  "properties": {
    "addr:full":"Calle de Monte Carmelo, 45 Sevilla Sevilla 41011",
    "addr:housenumber":"45",
    "addr:postcode":"41011",
    "addr:street":"Calle De Monte Carmelo",
    "iso:country":"ES",
    "sg:address":"Calle de Monte Carmelo, 45",
    "sg:city":"Sevilla",
    "sg:orig_category":"Institutos De Belleza",
    "sg:phone":"+34 954 27 49 00",
    "sg:postcode":"41011",
    "sg:province":"Sevilla",
    "wof:name":"Vitabel 2000 S.l.",
    "wof:placetype":"venue"
},
  "geometry": {"coordinates":[-5.9967536926,37.3755645752],"type":"Point"}
}