{
  "type": "Feature",
  "properties": {
    "iso:country":"ES",
    "sg:address":"Calle de Do\u00d1a Fausta Elorz, 8",
    "sg:city":"Falces",
    "sg:orig_category":"Asilos De Ancianos. Centros Privados",
    "sg:phone":"+34 948 71 47 81",
    "sg:postcode":"31370",
    "sg:province":"Navarra",
    "wof:name":"Fundacion D.fausta Elorz Residencia San Francisco Javier",
    "wof:placetype":"venue"
},
  "geometry": {"coordinates":[-1.8025852442,42.4288673401],"type":"Point"}
}