{
  "type": "Feature",
  "properties": {
    "addr:full":"Avda Cami D'onda, 21 Burriana Castell\u00f3n 12530",
    "addr:housenumber":"21",
    "addr:postcode":"12530",
    "addr:street":"Avda Cami D'Onda",
    "iso:country":"ES",
    "sg:address":"Avda Cami D'onda, 21",
    "sg:city":"Burriana",
    "sg:orig_category":"Ingenier\u00cda, Centros De Estudios (diversos)",
    "sg:phone":"+34 964 51 27 56",
    "sg:postcode":"12530",
    "sg:province":"Castell\u00f3n",
    "wof:name":"Vidal Safont Vicente",
    "wof:placetype":"venue"
},
  "geometry": {"coordinates":[-0.0895060003,39.8921051025],"type":"Point"}
}