{
  "type": "Feature",
  "properties": {
    "addr:full":"Avda Marques De Santillana, 145 Hinojosa Del Duque C\u00f3rdoba 14270",
    "addr:housenumber":"145",
    "addr:postcode":"14270",
    "addr:street":"Avda Marques De Santillana;Co\u0301Rdoba",
    "iso:country":"ES",
    "sg:address":"Avda Marques De Santillana, 145",
    "sg:city":"Hinojosa Del Duque",
    "sg:orig_category":"Mec\u00c1nico Del Autom\u00d3vil",
    "sg:phone":"+34 957 14 07 26",
    "sg:postcode":"14270",
    "sg:province":"C\u00f3rdoba",
    "wof:name":"Fernandez Rico Diego",
    "wof:placetype":"venue"
},
  "geometry": {"coordinates":[-5.1362380981,38.4951515198],"type":"Point"}
}