{
  "type": "Feature",
  "properties": {
    "iso:country":"ES",
    "sg:address":"Avda Blas Infante, 3",
    "sg:city":"Arroyo De La Miel-benalmadena Costa",
    "sg:orig_category":"Inmobiliaria (agencias)",
    "sg:phone":"+34 952 44 52 52",
    "sg:postcode":"29631",
    "sg:province":"M\u00e1laga",
    "wof:name":"Antonio Pastor Maria Angeles",
    "wof:placetype":"venue"
},
  "geometry": {"coordinates":[-4.5350546837,36.5987167358],"type":"Point"}
}