{
  "type": "Feature",
  "properties": {
    "addr:full":"Ctra Pe\u00d1aranda, 12 Alba Tormes Salamanca 37800",
    "addr:housenumber":"12",
    "addr:postcode":"37800",
    "addr:street":"Ctra Pen\u0303Aranda",
    "iso:country":"ES",
    "sg:address":"Ctra Pe\u00d1aranda, 12",
    "sg:city":"Alba Tormes",
    "sg:orig_category":"Empresas De Pintura Y Revestimientos",
    "sg:phone":"+34 923 37 03 44",
    "sg:postcode":"37800",
    "sg:province":"Salamanca",
    "wof:name":"Gonzalez Mesonero Santiago",
    "wof:placetype":"venue"
},
  "geometry": {"coordinates":[-5.5093283653,40.8254318237],"type":"Point"}
}