{
  "type": "Feature",
  "properties": {
    "addr:full":"Calle de Cueva De Pe\u00d1arrubia, 9 Lora De Estepa Sevilla 41564",
    "addr:housenumber":"9",
    "addr:postcode":"41564",
    "addr:street":"Calle De Cueva De Pen\u0303Arrubia",
    "iso:country":"ES",
    "sg:address":"Calle de Cueva De Pe\u00d1arrubia, 9",
    "sg:city":"Lora De Estepa",
    "sg:orig_category":"Freidur\u00cdas: Equipos Y Suministros",
    "sg:phone":"+34 954 82 91 79",
    "sg:postcode":"41564",
    "sg:province":"Sevilla",
    "wof:name":"Productos Hermanos Sojo S.l.l.",
    "wof:placetype":"venue"
},
  "geometry": {"coordinates":[-4.8169431686,37.2733535767],"type":"Point"}
}