{
  "type": "Feature",
  "properties": {
    "addr:full":"Calle de Era, 7 Torreblanca Castell\u00f3n 12596",
    "addr:housenumber":"7",
    "addr:postcode":"12596",
    "addr:street":"Calle De Era;Castello\u0301N",
    "iso:country":"ES",
    "sg:address":"Calle de Era, 7",
    "sg:city":"Torreblanca",
    "sg:orig_category":"Cerrajer\u00cda, Ferrallista",
    "sg:phone":"+34 964 42 01 20",
    "sg:postcode":"12596",
    "sg:province":"Castell\u00f3n",
    "wof:name":"Belles Traver Torreblanca S.l.",
    "wof:placetype":"venue"
},
  "geometry": {"coordinates":[0.1924960017,40.2183952332],"type":"Point"}
}