{
  "type": "Feature",
  "properties": {
    "addr:full":"Calle de San Enrique De Osso, 49 Madrid Madrid 28050",
    "addr:housenumber":"49",
    "addr:postcode":"madrid;28050",
    "addr:street":"Calle De San Enrique De Osso",
    "iso:country":"ES",
    "sg:address":"Calle de San Enrique De Osso, 49",
    "sg:city":"Madrid",
    "sg:orig_category":"Inmobiliaria (agencias)",
    "sg:phone":"+34 916 50 43 43",
    "sg:postcode":"28050",
    "sg:province":"Madrid",
    "wof:name":"Beimpa Inversiones S.l.",
    "wof:placetype":"venue"
},
  "geometry": {"coordinates":[-3.6448559761,40.5059394836],"type":"Point"}
}