{
  "type": "Feature",
  "properties": {
    "addr:full":"Calle de Legazpi, 1 Donostia-san Sebastian Guip\u00f9zcoa 20004",
    "addr:housenumber":"1",
    "addr:postcode":"20004",
    "addr:street":"Calle De Legazpi",
    "iso:country":"ES",
    "sg:address":"Calle de Legazpi, 1",
    "sg:city":"Donostia-san Sebastian",
    "sg:orig_category":"Ropa Para Ni\u00d1os (al Por Menor)",
    "sg:phone":"+34 943 42 52 12",
    "sg:postcode":"20004",
    "sg:province":"Guip\u00f9zcoa",
    "wof:name":"Vivar Lopez Esther",
    "wof:placetype":"venue"
},
  "geometry": {"coordinates":[-1.9824949503,43.322353363],"type":"Point"}
}