{
  "type": "Feature",
  "properties": {
    "addr:full":"C/ Barcelona, De, S/n S. Antoni Portmany Islas Baleares 07820",
    "addr:postcode":"07820",
    "addr:street":"C / Barcelona De S / N S. Antoni Portmany",
    "iso:country":"ES",
    "sg:address":"C/ Barcelona, De, S/n",
    "sg:city":"S. Antoni Portmany",
    "sg:orig_category":"Perfumer\u00cda (al Por Menor)",
    "sg:phone":"+34 971 34 23 21",
    "sg:postcode":"07820",
    "sg:province":"Islas Baleares",
    "wof:name":"Mari Pijuan Baldomero",
    "wof:placetype":"venue"
},
  "geometry": {"coordinates":[1.5188339949,39.1094055176],"type":"Point"}
}