{
  "type": "Feature",
  "properties": {
    "addr:full":"Calle de Lealtad, 3 Burgos Burgos 09001",
    "addr:housenumber":"3",
    "addr:postcode":"09001",
    "addr:street":"Calle De Lealtad",
    "iso:country":"ES",
    "sg:address":"Calle de Lealtad, 3",
    "sg:city":"Burgos",
    "sg:orig_category":"Electrodom\u00c9sticos (al Por Menor)",
    "sg:phone":"+34 947 20 22 65",
    "sg:postcode":"09001",
    "sg:province":"Burgos",
    "wof:name":"Catalan I\u00f1iguez Domingo",
    "wof:placetype":"venue"
},
  "geometry": {"coordinates":[-3.6985840797,42.3328094482],"type":"Point"}
}