{
  "type": "Feature",
  "properties": {
    "iso:country":"ES",
    "sg:address":"Avda Constitucion (la), 27",
    "sg:city":"Segovia",
    "sg:orig_category":"Carnicer\u00cdas, Carnicer\u00cdas",
    "sg:phone":"+34 921 43 04 03",
    "sg:postcode":"40006",
    "sg:province":"Segovia",
    "wof:name":"Suministros Carnicos Rueda S.l.",
    "wof:placetype":"venue"
},
  "geometry": {"coordinates":[-4.1084508896,40.9334602356],"type":"Point"}
}