{
  "type": "Feature",
  "properties": {
    "iso:country":"ES",
    "sg:address":"Ctra Doctor Robert, 28",
    "sg:city":"Vendrell",
    "sg:classifiers":[
        {
            "category":"Autos & Motor Vehicles",
            "subcategory":"Automobile Sales",
            "type":"Retail Goods"
        }
    ],
    "sg:phone":"+34 977 66 07 13",
    "sg:postcode":"43700",
    "sg:province":"Tarragona",
    "wof:name":"Conde Parra Diego",
    "wof:placetype":"venue"
},
  "geometry": {"coordinates":[1.536996007,41.2213897705],"type":"Point"}
}