{
  "type": "Feature",
  "properties": {
    "iso:country":"ES",
    "sg:address":"Avda Lopez Abente, 1",
    "sg:city":"Muxia",
    "sg:orig_category":"Notarios",
    "sg:phone":"+34 981 74 23 52",
    "sg:postcode":"15124",
    "sg:province":"La Coru\u00f1a",
    "wof:name":"Elbo Ferrant Javier Manuel",
    "wof:placetype":"venue"
},
  "geometry": {"coordinates":[-9.2152175903,43.1029205322],"type":"Point"}
}