{
  "type": "Feature",
  "properties": {
    "addr:full":"Calle de San Roque, 53 Esquivias Toledo 45221",
    "addr:housenumber":"53",
    "addr:postcode":"45221",
    "addr:street":"Calle De San Roque",
    "iso:country":"ES",
    "sg:address":"Calle de San Roque, 53",
    "sg:city":"Esquivias",
    "sg:orig_category":"Electricidad: Instaladores",
    "sg:phone":"+34 925 52 00 57",
    "sg:postcode":"45221",
    "sg:province":"Toledo",
    "wof:name":"Montajes Electricos Torrejon Hermanos C.b.",
    "wof:placetype":"venue"
},
  "geometry": {"coordinates":[-3.7714591026,40.1042709351],"type":"Point"}
}