{
  "type": "Feature",
  "properties": {
    "addr:full":"P. Maritimo, 8 S'algar Islas Baleares 07713",
    "addr:housenumber":"8",
    "addr:postcode":"07713",
    "addr:street":"P. Maritimo;Islas",
    "iso:country":"ES",
    "sg:address":"P. Maritimo, 8",
    "sg:city":"S'algar",
    "sg:orig_category":"Agentes, Concesionarios Y Sucursales De Veh\u00cdculos",
    "sg:phone":"+34 971 15 06 87",
    "sg:postcode":"07713",
    "sg:province":"Islas Baleares",
    "wof:name":"Biesa-concesionario Suzuki Santana",
    "wof:placetype":"venue"
},
  "geometry": {"coordinates":[2.9117100239,39.6136398315],"type":"Point"}
}