{
  "type": "Feature",
  "properties": {
    "addr:full":"Av J.a.clave, 167 Mao Islas Baleares 07703",
    "addr:housenumber":"167",
    "addr:postcode":"07703",
    "addr:street":"Av J.A.Clave",
    "iso:country":"ES",
    "sg:address":"Av J.a.clave, 167",
    "sg:city":"Mao",
    "sg:orig_category":"Agencias Y Agentes Comerciales, Representantes",
    "sg:phone":"+34 971 36 15 98",
    "sg:postcode":"07703",
    "sg:province":"Islas Baleares",
    "wof:name":"Perez-chuecos Canales Salvador",
    "wof:placetype":"venue"
},
  "geometry": {"coordinates":[4.2597899437,39.8804016113],"type":"Point"}
}