{
  "type": "Feature",
  "properties": {
    "addr:full":"Av Ovidi Montllor, 26 Aldaia Valencia 46960",
    "addr:housenumber":"26",
    "addr:postcode":"46960",
    "addr:street":"Av Ovidi Montllor",
    "iso:country":"ES",
    "sg:address":"Av Ovidi Montllor, 26",
    "sg:city":"Aldaia",
    "sg:orig_category":"Maquinaria Y Herramientas Para Madera, Pvc, Aluminio Y Aperos (fabricaci\u00d3n, Comercio)",
    "sg:phone":"+34 961 98 82 06",
    "sg:postcode":"46960",
    "sg:province":"Valencia",
    "sg:website":"www.lopez-roca.com",
    "wof:name":"Lopez-roca S.l.",
    "wof:placetype":"venue"
},
  "geometry": {"coordinates":[-0.4636000097,39.4708824158],"type":"Point"}
}