{
  "type": "Feature",
  "properties": {
    "iso:country":"ES",
    "sg:address":"Avda Estacion, 31",
    "sg:city":"Estacion",
    "sg:orig_category":"Cr\u00cda De Cerdos",
    "sg:phone":"+34 950 46 44 01",
    "sg:postcode":"04640",
    "sg:province":"Almer\u00eda",
    "wof:name":"Sociedad Agraria De Transformacion Numero 5311",
    "wof:placetype":"venue"
},
  "geometry": {"coordinates":[-1.7254290581,37.3880081177],"type":"Point"}
}