{
  "type": "Feature",
  "properties": {
    "iso:country":"ES",
    "sg:address":"Calle de Santa Ana, 30",
    "sg:city":"Vitigudino",
    "sg:orig_category":"Inform\u00c1tica (estudios, Servicios, Asesor\u00cda, Formaci\u00d3n)",
    "sg:phone":"+34 923 52 02 21",
    "sg:postcode":"37210",
    "sg:province":"Salamanca",
    "wof:name":"Reyconet S.l.",
    "wof:placetype":"venue"
},
  "geometry": {"coordinates":[-6.4362850189,41.0066375732],"type":"Point"}
}