{
  "type": "Feature",
  "properties": {
    "iso:country":"ES",
    "sg:address":"Avda Vilari\u00d1o, 5",
    "sg:city":"Cambados",
    "sg:orig_category":"Caf\u00c9s, Bares, Cervecer\u00cdas",
    "sg:phone":"+34 986 54 20 28",
    "sg:postcode":"36630",
    "sg:province":"Pontevedra",
    "wof:name":"Obelisco C.b. Cambados",
    "wof:placetype":"venue"
},
  "geometry": {"coordinates":[-8.810464859,42.5161590576],"type":"Point"}
}