{
  "type": "Feature",
  "properties": {
    "iso:country":"ES",
    "sg:address":"Calle de Rubio, S/n",
    "sg:city":"Santander",
    "sg:orig_category":"Zapatos (al Por Menor)",
    "sg:phone":"+34 942 23 12 88",
    "sg:postcode":"39007",
    "sg:province":"Cantabria",
    "wof:name":"Inversiones Hh De Cantabria S.l.",
    "wof:placetype":"venue"
},
  "geometry": {"coordinates":[-3.813049078,43.4621734619],"type":"Point"}
}