{
  "type": "Feature",
  "properties": {
    "iso:country":"ES",
    "sg:address":"Carrer de Bonaire, 11",
    "sg:city":"Olot",
    "sg:orig_category":"Molduras, Junquillos, Listones Y Molduras Perforadas",
    "sg:phone":"+34 972 26 15 26",
    "sg:postcode":"17800",
    "sg:province":"Girona",
    "wof:name":"Mir Rafales Ines",
    "wof:placetype":"venue"
},
  "geometry": {"coordinates":[2.490350008,42.1829795837],"type":"Point"}
}