{
  "type": "Feature",
  "properties": {
    "addr:full":"Ctra. Colloto-santander, 134 Colloto-oviedo Asturias 33010",
    "addr:housenumber":"134",
    "addr:postcode":"33010",
    "addr:street":"Ctra. Colloto-Santander;Asturias",
    "iso:country":"ES",
    "sg:address":"Ctra. Colloto-santander, 134",
    "sg:city":"Colloto-oviedo",
    "sg:orig_category":"Agencias Y Agentes Comerciales, Representantes",
    "sg:phone":"+34 985 79 24 61",
    "sg:postcode":"33010",
    "sg:province":"Asturias",
    "wof:name":"Santos Alvarez Jose Antonio De Los",
    "wof:placetype":"venue"
},
  "geometry": {"coordinates":[-5.815808773,43.3714408875],"type":"Point"}
}