{
  "type": "Feature",
  "properties": {
    "iso:country":"ES",
    "sg:address":"Calle de Perez Galdos, 10",
    "sg:city":"Palmas De Gran Canaria",
    "sg:orig_category":"M\u00c9dicos: Gastroenterolog\u00cda Y Hepatolog\u00cda (aparato Digestivo)",
    "sg:phone":"+34 928 36 87 64",
    "sg:postcode":"35002",
    "sg:province":"Las Palmas",
    "wof:name":"Guerra Manrique De Lara Cayetano",
    "wof:placetype":"venue"
},
  "geometry": {"coordinates":[-15.4188690186,28.1061840057],"type":"Point"}
}