{
  "type": "Feature",
  "properties": {
    "iso:country":"ES",
    "sg:address":"Avda De Bara\u00f1ain, 10",
    "sg:city":"Iru\u00f1a",
    "sg:orig_category":"Asociaciones, Organismos Culturales Y Socioeducativos",
    "sg:phone":"+34 948 27 53 02",
    "sg:postcode":"31011",
    "sg:province":"Navarra",
    "wof:name":"Ateneo Navarro-nafar Atenoa",
    "wof:placetype":"venue"
},
  "geometry": {"coordinates":[-1.6554483175,42.8145256042],"type":"Point"}
}