{
  "type": "Feature",
  "properties": {
    "iso:country":"ES",
    "sg:address":"Calle de Almendros, 4",
    "sg:city":"Consuegra",
    "sg:orig_category":"Limpieza Con Chorro De Arena Y Con Granalla, Pulido",
    "sg:phone":"+34 925 48 18 48",
    "sg:postcode":"45700",
    "sg:province":"Toledo",
    "wof:name":"Fernandez Gallego De Lerma Timoteo",
    "wof:placetype":"venue"
},
  "geometry": {"coordinates":[-3.614667654,39.4660491943],"type":"Point"}
}