{
  "type": "Feature",
  "properties": {
    "iso:country":"ES",
    "sg:address":"Avda Generalisimo, 38",
    "sg:city":"Meira",
    "sg:orig_category":"M\u00c9dicos: Estomatolog\u00cda",
    "sg:phone":"+34 982 33 02 01",
    "sg:postcode":"27240",
    "sg:province":"Lugo",
    "wof:name":"Rafael Campo Andion Y Otro Cdad.",
    "wof:placetype":"venue"
},
  "geometry": {"coordinates":[-7.2951989174,43.2131614685],"type":"Point"}
}