{
  "type": "Feature",
  "properties": {
    "addr:full":"Avda Santa Cruz (de), 30 G\u00fcimar Santa Cruz De Tenerife 38500",
    "addr:housenumber":"30",
    "addr:postcode":"38500",
    "addr:street":"Avda Santa Cruz De",
    "iso:country":"ES",
    "sg:address":"Avda Santa Cruz (de), 30",
    "sg:city":"G\u00fcimar",
    "sg:orig_category":"Papeler\u00cdas, Librer\u00cdas",
    "sg:phone":"+34 922 51 23 55",
    "sg:postcode":"38500",
    "sg:province":"Santa Cruz De Tenerife",
    "wof:name":"Ramirez Gonzalez Esther",
    "wof:placetype":"venue"
},
  "geometry": {"coordinates":[-16.4084587097,28.3175621033],"type":"Point"}
}