{
  "type": "Feature",
  "properties": {
    "addr:full":"Calle de Enmedio, 120 Castellon Castell\u00f3n 12001",
    "addr:housenumber":"120",
    "addr:postcode":"12001",
    "addr:street":"Calle De Enmedio;Castello\u0301N",
    "iso:country":"ES",
    "sg:address":"Calle de Enmedio, 120",
    "sg:city":"Castellon",
    "sg:orig_category":"Centros De Coordinaci\u00d3n",
    "sg:phone":"+34 964 22 64 50",
    "sg:postcode":"12001",
    "sg:province":"Castell\u00f3n",
    "wof:name":"Monfort Catala Jose",
    "wof:placetype":"venue"
},
  "geometry": {"coordinates":[-0.0374700017,39.9878540039],"type":"Point"}
}