{
  "type": "Feature",
  "properties": {
    "addr:full":"Calle de Rafael Asin, 26 Alacant Alicante 03010",
    "addr:housenumber":"26",
    "addr:postcode":"03010",
    "addr:street":"Calle De Rafael Asin",
    "iso:country":"ES",
    "sg:address":"Calle de Rafael Asin, 26",
    "sg:city":"Alacant",
    "sg:orig_category":"Oficinas: Suministros Para (al Por Menor)",
    "sg:phone":"+34 965 25 22 55",
    "sg:postcode":"03010",
    "sg:province":"Alicante",
    "wof:name":"Euroficina S.l.",
    "wof:placetype":"venue"
},
  "geometry": {"coordinates":[-0.4862720072,38.3582954407],"type":"Point"}
}