{
  "type": "Feature",
  "properties": {
    "iso:country":"ES",
    "sg:address":"Calle de Paraguay, 22",
    "sg:city":"Toscal",
    "sg:orig_category":"Doctores En Medicina",
    "sg:phone":"+34 922 36 24 53",
    "sg:postcode":"38418",
    "sg:province":"Santa Cruz De Tenerife",
    "wof:name":"Cornejo Rodriguez Jesus Roberto",
    "wof:placetype":"venue"
},
  "geometry": {"coordinates":[-16.5713596344,28.4000415802],"type":"Point"}
}