{
  "type": "Feature",
  "properties": {
    "addr:full":"Carrer de Arx Lluis Salvador, 75 Palma Islas Baleares 07004",
    "addr:housenumber":"75",
    "addr:postcode":"07004",
    "addr:street":"Carrer De Arx Lluis Salvador",
    "iso:country":"ES",
    "sg:address":"Carrer de Arx Lluis Salvador, 75",
    "sg:city":"Palma",
    "sg:orig_category":"Guarder\u00cdas",
    "sg:phone":"+34 971 75 06 88",
    "sg:postcode":"07004",
    "sg:province":"Islas Baleares",
    "wof:name":"Guarderia Ninin S.l.",
    "wof:placetype":"venue"
},
  "geometry": {"coordinates":[2.6566269398,39.5837402344],"type":"Point"}
}