{
  "type": "Feature",
  "properties": {
    "addr:full":"Calle de Luis Daoiz, 20 Moron Frontera Sevilla 41530",
    "addr:housenumber":"20",
    "addr:postcode":"41530",
    "addr:street":"Calle De Luis Daoiz",
    "iso:country":"ES",
    "sg:address":"Calle de Luis Daoiz, 20",
    "sg:city":"Moron Frontera",
    "sg:orig_category":"Laboratorios Y Trabajos De Fotograf\u00cda, V\u00cddeo Y Cine",
    "sg:phone":"+34 954 85 07 46",
    "sg:postcode":"41530",
    "sg:province":"Sevilla",
    "wof:name":"Foto Estudio Angel S.l.",
    "wof:placetype":"venue"
},
  "geometry": {"coordinates":[-5.4512209892,37.1231575012],"type":"Point"}
}