{
  "type": "Feature",
  "properties": {
    "addr:full":"Calle de Plateria, 12 San Bartolome Murcia 30004",
    "addr:housenumber":"12",
    "addr:postcode":"30004",
    "addr:street":"Calle De Plateria",
    "iso:country":"ES",
    "sg:address":"Calle de Plateria, 12",
    "sg:city":"San Bartolome",
    "sg:orig_category":"Confecci\u00d3n De Trajes Para Se\u00d1oras",
    "sg:phone":"+34 968 21 66 64",
    "sg:postcode":"30004",
    "sg:province":"Murcia",
    "wof:name":"Talla 42 S.l.",
    "wof:placetype":"venue"
},
  "geometry": {"coordinates":[-1.1315749884,37.9854469299],"type":"Point"}
}