{
  "type": "Feature",
  "properties": {
    "addr:full":"Esquiroz-ezkirotz Kalea, 41 Iru\u00f1a Navarra 31007",
    "addr:housenumber":"41",
    "addr:postcode":"31007",
    "addr:street":"Esquiroz-Ezkirotz Kalea",
    "iso:country":"ES",
    "sg:address":"Esquiroz-ezkirotz Kalea, 41",
    "sg:city":"Iru\u00f1a",
    "sg:orig_category":"Transportes Por V\u00cdas Navegables",
    "sg:phone":"+34 948 25 08 32",
    "sg:postcode":"31007",
    "sg:province":"Navarra",
    "wof:name":"Anciano Ruiz Maria Angeles",
    "wof:placetype":"venue"
},
  "geometry": {"coordinates":[-1.6516338587,42.8033332825],"type":"Point"}
}