{
  "type": "Feature",
  "properties": {
    "iso:country":"ES",
    "sg:address":"Rua Dona Urraca, 33",
    "sg:city":"Lugo",
    "sg:orig_category":"Muebles, Minoristas",
    "sg:phone":"+34 982 21 59 60",
    "sg:postcode":"27004",
    "sg:province":"Lugo",
    "wof:name":"Tecalo S.l.",
    "wof:placetype":"venue"
},
  "geometry": {"coordinates":[-7.5686049461,43.0173721313],"type":"Point"}
}