{
  "type": "Feature",
  "properties": {
    "addr:full":"Carrer de Escola Pia, 94 Sabadell Barcelona 08201",
    "addr:housenumber":"94",
    "addr:postcode":"08201",
    "addr:street":"Carrer De Escola Pia",
    "iso:country":"ES",
    "sg:address":"Carrer de Escola Pia, 94",
    "sg:city":"Sabadell",
    "sg:orig_category":"Laboratorios Y Cl\u00cdnicas Veterinarias",
    "sg:phone":"+34 937 25 99 83",
    "sg:postcode":"08201",
    "sg:province":"Barcelona",
    "wof:name":"Reig Puigbertran Josep",
    "wof:placetype":"venue"
},
  "geometry": {"coordinates":[2.1028780937,41.5486755371],"type":"Point"}
}