{
  "type": "Feature",
  "properties": {
    "addr:full":"Comedias, 14 Iru\u00f1a Navarra 31001",
    "addr:housenumber":"14",
    "addr:postcode":"31001",
    "addr:street":"Comedias",
    "iso:country":"ES",
    "sg:address":"Comedias, 14",
    "sg:city":"Iru\u00f1a",
    "sg:orig_category":"Centros M\u00c9dicos Y Sociales, Dispensarios",
    "sg:phone":"+34 948 22 36 87",
    "sg:postcode":"31001",
    "sg:province":"Navarra",
    "wof:name":"Elizari Flamarique Imelda",
    "wof:placetype":"venue"
},
  "geometry": {"coordinates":[-1.6437369585,42.8162574768],"type":"Point"}
}