{
  "type": "Feature",
  "properties": {
    "addr:full":"Cra. Nacional Ii, Km. 0209,0 Caldes Malavella Girona 17455",
    "addr:postcode":"17455",
    "addr:street":"Km. 0209,0",
    "iso:country":"ES",
    "sg:address":"Cra. Nacional Ii, Km. 0209,0",
    "sg:city":"Caldes Malavella",
    "sg:orig_category":"Distribuci\u00d3n De Petr\u00d3leo Y Derivados",
    "sg:phone":"+34 972 47 05 03",
    "sg:postcode":"17455",
    "sg:province":"Girona",
    "wof:name":"Cedipsa Compa\u00d1ia Espa\u00d1ola Distribuidora De Petroleos S.a.",
    "wof:placetype":"venue"
},
  "geometry": {"coordinates":[2.8256690502,41.8730735779],"type":"Point"}
}