{
  "type": "Feature",
  "properties": {
    "addr:full":"Avda Jose Antonio, 14 Laredo Cantabria 39770",
    "addr:housenumber":"14",
    "addr:postcode":"39770",
    "addr:street":"Avda Jose Antonio",
    "iso:country":"ES",
    "sg:address":"Avda Jose Antonio, 14",
    "sg:city":"Laredo",
    "sg:orig_category":"Colchones (fabricaci\u00d3n, Al Por Mayor, Al Por Menor)",
    "sg:phone":"+34 942 60 81 37",
    "sg:postcode":"39770",
    "sg:province":"Cantabria",
    "wof:name":"Nomada S.c",
    "wof:placetype":"venue"
},
  "geometry": {"coordinates":[-3.4159209728,43.4083557129],"type":"Point"}
}