{
  "type": "Feature",
  "properties": {
    "iso:country":"ES",
    "sg:address":"Calle de Ricardo De La Vega, 1",
    "sg:city":"Getafe",
    "sg:orig_category":"Abogados",
    "sg:phone":"+34 916 83 26 27",
    "sg:postcode":"28901",
    "sg:province":"Madrid",
    "wof:name":"Garcia Extremera Maria De Los Reyes",
    "wof:placetype":"venue"
},
  "geometry": {"coordinates":[-3.7302100658,40.3069000244],"type":"Point"}
}