{
  "type": "Feature",
  "properties": {
    "addr:full":"Calle de Reina Regente, 2 Donostia-san Sebastian Guip\u00f9zcoa 20003",
    "addr:housenumber":"2",
    "addr:postcode":"20003",
    "addr:street":"Calle De Reina Regente",
    "iso:country":"ES",
    "sg:address":"Calle de Reina Regente, 2",
    "sg:city":"Donostia-san Sebastian",
    "sg:orig_category":"Frutas, Legumbres Frescas Y Tempranas (al Por Menor)",
    "sg:phone":"+34 943 42 12 13",
    "sg:postcode":"20003",
    "sg:province":"Guip\u00f9zcoa",
    "wof:name":"Carvajal Diez Fernando",
    "wof:placetype":"venue"
},
  "geometry": {"coordinates":[-1.9815859795,43.3228111267],"type":"Point"}
}