{
  "type": "Feature",
  "properties": {
    "iso:country":"ES",
    "sg:address":"Carrer de Gavatxons, 20",
    "sg:city":"Terrassa",
    "sg:orig_category":"Librer\u00cdas",
    "sg:phone":"+34 937 88 55 61",
    "sg:postcode":"08221",
    "sg:province":"Barcelona",
    "wof:name":"Diaz Datzira Magda",
    "wof:placetype":"venue"
},
  "geometry": {"coordinates":[2.0112369061,41.5627708435],"type":"Point"}
}