{
  "type": "Feature",
  "properties": {
    "addr:full":"Calle de Jose De Anchieta, 2 Vitoria-gasteiz \u00c1lava 01003",
    "addr:housenumber":"2",
    "addr:postcode":"01003",
    "addr:street":"Calle De Jose De Anchieta",
    "iso:country":"ES",
    "sg:address":"Calle de Jose De Anchieta, 2",
    "sg:city":"Vitoria-gasteiz",
    "sg:orig_category":"Molduras, Junquillos, Listones Y Molduras Perforadas",
    "sg:phone":"+34 945 27 84 19",
    "sg:postcode":"01003",
    "sg:province":"\u00c1lava",
    "wof:name":"Union 84 S. A.",
    "wof:placetype":"venue"
},
  "geometry": {"coordinates":[-2.6617250443,42.848072052],"type":"Point"}
}