{
  "type": "Feature",
  "properties": {
    "iso:country":"ES",
    "sg:address":"Av Barcelona, 51",
    "sg:city":"Vilafranca Penedes",
    "sg:orig_category":"Impresores",
    "sg:phone":"+34 938 92 04 30",
    "sg:postcode":"08720",
    "sg:province":"Barcelona",
    "wof:name":"Disset-zero-set S.l.",
    "wof:placetype":"venue"
},
  "geometry": {"coordinates":[1.7028870583,41.3463058472],"type":"Point"}
}