{
  "type": "Feature",
  "properties": {
    "iso:country":"ES",
    "sg:address":"Calle de Teso Nuevo (del), 6",
    "sg:city":"Arevalo",
    "sg:orig_category":"Farmacias",
    "sg:phone":"+34 920 30 05 00",
    "sg:postcode":"05200",
    "sg:province":"\u00c1vila",
    "wof:name":"Blasco Villa Javier",
    "wof:placetype":"venue"
},
  "geometry": {"coordinates":[-4.7188467979,41.0583305359],"type":"Point"}
}