{
  "type": "Feature",
  "properties": {
    "iso:country":"ES",
    "sg:address":"Rava Santa Anna, 41",
    "sg:city":"Reus",
    "sg:orig_category":"Diarios, Revistas Y Boletines (distribuidores)",
    "sg:phone":"+34 977 34 04 23",
    "sg:postcode":"43201",
    "sg:province":"Tarragona",
    "wof:name":"Anuntis Segundamano Espana S.l.",
    "wof:placetype":"venue"
},
  "geometry": {"coordinates":[1.1077258587,41.156211853],"type":"Point"}
}