{
  "type": "Feature",
  "properties": {
    "addr:full":"Calle de Oreitiasolo, 6 Vitoria-gasteiz \u00c1lava 01006",
    "addr:housenumber":"6",
    "addr:postcode":"01006",
    "addr:street":"Calle De Oreitiasolo",
    "iso:country":"ES",
    "sg:address":"Calle de Oreitiasolo, 6",
    "sg:city":"Vitoria-gasteiz",
    "sg:orig_category":"Imprenta",
    "sg:phone":"+34 945 13 61 79",
    "sg:postcode":"01006",
    "sg:province":"\u00c1lava",
    "wof:name":"Garcia Larrechi Cayo",
    "wof:placetype":"venue"
},
  "geometry": {"coordinates":[-2.6564199924,42.8390769958],"type":"Point"}
}