{
  "type": "Feature",
  "properties": {
    "iso:country":"ES",
    "sg:address":"Praz Concello, 5",
    "sg:city":"Bertamirans",
    "sg:orig_category":"Bisuter\u00cda, Joyer\u00cda, Relojer\u00cda (al Por Menor)",
    "sg:phone":"+34 981 81 58 05",
    "sg:postcode":"15220",
    "sg:province":"La Coru\u00f1a",
    "wof:name":"Mirabe Joyeros S.l.",
    "wof:placetype":"venue"
},
  "geometry": {"coordinates":[-8.6529092789,42.8592033386],"type":"Point"}
}