{
  "type": "Feature",
  "properties": {
    "addr:full":"Ctra. Villamuelas, 48 Villasequilla Toledo 45740",
    "addr:housenumber":"48",
    "addr:postcode":"45740",
    "addr:street":"Ctra. Villamuelas",
    "iso:country":"ES",
    "sg:address":"Ctra. Villamuelas, 48",
    "sg:city":"Villasequilla",
    "sg:orig_category":"Cooperativas Agr\u00cdcolas",
    "sg:phone":"+34 925 31 00 41",
    "sg:postcode":"45740",
    "sg:province":"Toledo",
    "wof:name":"Cooperativa Vinicola San Isidro",
    "wof:placetype":"venue"
},
  "geometry": {"coordinates":[-3.7288589478,39.8753967285],"type":"Point"}
}