{
  "type": "Feature",
  "properties": {
    "addr:full":"Carr Llanterners, S/n Godella Valencia 46110",
    "addr:housenumber":"s / n",
    "addr:postcode":"46110",
    "addr:street":"Carr Llanterners",
    "iso:country":"ES",
    "sg:address":"Carr Llanterners, S/n",
    "sg:city":"Godella",
    "sg:orig_category":"Comidas Por Encargo, Organizaci\u00d3n De Recepciones",
    "sg:phone":"+34 963 63 50 03",
    "sg:postcode":"46110",
    "sg:province":"Valencia",
    "wof:name":"Pinturas J. Sevilla S. L.",
    "wof:placetype":"venue"
},
  "geometry": {"coordinates":[-0.4135290086,39.5277786255],"type":"Point"}
}