{
  "type": "Feature",
  "properties": {
    "addr:full":"Plaz Zorrilla, 3 Zamora Zamora 49003",
    "addr:housenumber":"3",
    "addr:postcode":"49003",
    "addr:street":"Plaz Zorrilla",
    "iso:country":"ES",
    "sg:address":"Plaz Zorrilla, 3",
    "sg:city":"Zamora",
    "sg:orig_category":"Zapatos (al Por Menor)",
    "sg:phone":"+34 980 53 38 14",
    "sg:postcode":"49003",
    "sg:province":"Zamora",
    "wof:name":"Angel Seisdedos S. L.",
    "wof:placetype":"venue"
},
  "geometry": {"coordinates":[-5.7453374863,41.5045700073],"type":"Point"}
}