{
  "type": "Feature",
  "properties": {
    "iso:country":"ES",
    "sg:address":"Carrer de Marti I Blasi, 27",
    "sg:city":"Hospitalet Llobregat",
    "sg:orig_category":"Mec\u00c1nico Del Autom\u00d3vil",
    "sg:phone":"+34 934 40 91 31",
    "sg:postcode":"08905",
    "sg:province":"Barcelona",
    "wof:name":"Garcia Ya\u00f1ez Luis",
    "wof:placetype":"venue"
},
  "geometry": {"coordinates":[2.1142339706,41.3698616028],"type":"Point"}
}