{
  "type": "Feature",
  "properties": {
    "iso:country":"ES",
    "sg:address":"Ptor. Sorolla, S/n",
    "sg:city":"Bonrepos Mirambell",
    "sg:classifiers":[
        {
            "category":"Manufacturing",
            "subcategory":"Metals",
            "type":"Manufacturing & Wholesale Goods"
        }
    ],
    "sg:phone":"+34 961 86 27 28",
    "sg:postcode":"46131",
    "sg:province":"Valencia",
    "sg:tags":[
        "en",
        "fundiciones"
    ],
    "wof:name":"Industrias J.ferrer S.a.",
    "wof:placetype":"venue"
},
  "geometry": {"coordinates":[-0.3632790148,39.5160102844],"type":"Point"}
}