{
  "type": "Feature",
  "properties": {
    "iso:country":"ES",
    "sg:address":"Calle de Merced, 60",
    "sg:city":"Coru\u00d1a",
    "sg:orig_category":"Mec\u00c1nico Del Autom\u00d3vil",
    "sg:phone":"+34 981 28 74 81",
    "sg:postcode":"15009",
    "sg:province":"A Coru\u00f1a",
    "wof:name":"Talleres Casmar S.l.",
    "wof:placetype":"venue"
},
  "geometry": {"coordinates":[-8.3934326172,43.352596283],"type":"Point"}
}