{
  "type": "Feature",
  "properties": {
    "iso:country":"ES",
    "sg:address":"Carrer de Sant Sebastia, 79",
    "sg:city":"Roses",
    "sg:orig_category":"Loter\u00cda Y T\u00d3mbola",
    "sg:phone":"+34 972 25 63 64",
    "sg:postcode":"17480",
    "sg:province":"Girona",
    "wof:name":"Serra Trulls Salvador",
    "wof:placetype":"venue"
},
  "geometry": {"coordinates":[3.1793899536,42.2611274719],"type":"Point"}
}