{
  "type": "Feature",
  "properties": {
    "iso:country":"ES",
    "sg:address":"Calle de Constitucion (de La), 5",
    "sg:city":"Navalcarnero",
    "sg:orig_category":"Abogados",
    "sg:phone":"+34 918 11 00 72",
    "sg:postcode":"28600",
    "sg:province":"Madrid",
    "wof:name":"Sanchez-cid Garcia-tenorio Soledad Pilar",
    "wof:placetype":"venue"
},
  "geometry": {"coordinates":[-4.0139112473,40.2875404358],"type":"Point"}
}