{
  "type": "Feature",
  "properties": {
    "iso:country":"ES",
    "sg:address":"Avda Primero De Mayo, 98",
    "sg:city":"Coria Rio",
    "sg:orig_category":"Carnicer\u00cdas, Carnicer\u00cdas",
    "sg:phone":"+34 954 77 35 05",
    "sg:postcode":"41100",
    "sg:province":"Sevilla",
    "wof:name":"Alfonso Japon Antonio",
    "wof:placetype":"venue"
},
  "geometry": {"coordinates":[-6.052344799,37.2920761108],"type":"Point"}
}