{
  "type": "Feature",
  "properties": {
    "iso:country":"ES",
    "sg:address":"Calle de Bogas, 8",
    "sg:city":"Carmona",
    "sg:orig_category":"Centros Empresariales",
    "sg:phone":"+34 954 14 11 20",
    "sg:postcode":"41410",
    "sg:province":"Sevilla",
    "wof:name":"Mendez Garceso Maria Del Carmen",
    "wof:placetype":"venue"
},
  "geometry": {"coordinates":[-5.6369624138,37.4715003967],"type":"Point"}
}