{
  "type": "Feature",
  "properties": {
    "addr:full":"Av Espanya, 11 Eivissa Islas Baleares 07800",
    "addr:housenumber":"11",
    "addr:postcode":"07800",
    "addr:street":"Av Espanya",
    "iso:country":"ES",
    "sg:address":"Av Espanya, 11",
    "sg:city":"Eivissa",
    "sg:orig_category":"Peluquer\u00cdas",
    "sg:phone":"+34 971 39 44 05",
    "sg:postcode":"07800",
    "sg:province":"Islas Baleares",
    "wof:name":"Mela Fabi Baleares S.l.",
    "wof:placetype":"venue"
},
  "geometry": {"coordinates":[1.4308949709,38.9084014893],"type":"Point"}
}