{
  "type": "Feature",
  "properties": {
    "addr:full":"Diseminados, S/n Sta Olaja Varga Le\u00f3n 24813",
    "addr:housenumber":"s / n",
    "addr:postcode":"24813",
    "addr:street":"Diseminados;Sta Olaja;Leo\u0301N",
    "iso:country":"ES",
    "sg:address":"Diseminados, S/n",
    "sg:city":"Sta Olaja Varga",
    "sg:orig_category":"Hormigonados",
    "sg:phone":"+34 987 70 03 26",
    "sg:postcode":"24813",
    "sg:province":"Le\u00f3n",
    "wof:name":"Voladuras Y Movimientos De Tierras Robles S.l.",
    "wof:placetype":"venue"
},
  "geometry": {"coordinates":[-5.5717520714,42.5998764038],"type":"Point"}
}