{
  "type": "Feature",
  "properties": {
    "addr:full":"Calle de Feria, 4 Sevilla Sevilla 41003",
    "addr:housenumber":"4",
    "addr:postcode":"41003",
    "addr:street":"Calle De Feria",
    "iso:country":"ES",
    "sg:address":"Calle de Feria, 4",
    "sg:city":"Sevilla",
    "sg:orig_category":"Encuadernaci\u00d3n E Impresi\u00d3n De Folletos",
    "sg:phone":"+34 954 22 46 63",
    "sg:postcode":"41003",
    "sg:province":"Sevilla",
    "wof:name":"Padilla Berdejo Manuel",
    "wof:placetype":"venue"
},
  "geometry": {"coordinates":[-5.9915690422,37.398059845],"type":"Point"}
}