{
  "type": "Feature",
  "properties": {
    "addr:full":"Calle de Ruda, 16 Madrid Madrid 28005",
    "addr:housenumber":"16",
    "addr:postcode":"madrid;28005",
    "addr:street":"Calle De Ruda",
    "iso:country":"ES",
    "sg:address":"Calle de Ruda, 16",
    "sg:city":"Madrid",
    "sg:orig_category":"Confecci\u00d3n De Ropa Interior",
    "sg:phone":"+34 913 65 54 77",
    "sg:postcode":"28005",
    "sg:province":"Madrid",
    "wof:name":"Ismael Y Jesus Textil S.l.",
    "wof:placetype":"venue"
},
  "geometry": {"coordinates":[-3.7084050179,40.4107704163],"type":"Point"}
}