{
  "type": "Feature",
  "properties": {
    "addr:full":"Avda Santa Maria (de), 24 Pontevedra Pontevedra 36002",
    "addr:housenumber":"24",
    "addr:postcode":"36002",
    "addr:street":"Avda Santa Maria De",
    "iso:country":"ES",
    "sg:address":"Avda Santa Maria (de), 24",
    "sg:city":"Pontevedra",
    "sg:orig_category":"Iglesia Cat\u00d3lica",
    "sg:phone":"+34 986 86 61 85",
    "sg:postcode":"36002",
    "sg:province":"Pontevedra",
    "wof:name":"Parroquia De Santa Maria La Mayor De Pontevedra",
    "wof:placetype":"venue"
},
  "geometry": {"coordinates":[-8.647151947,42.4332237244],"type":"Point"}
}