{
  "type": "Feature",
  "properties": {
    "addr:full":"Carrer de Carreras I Candi, 22 Barcelona Barcelona 08028",
    "addr:housenumber":"22",
    "addr:postcode":"08028",
    "addr:street":"Carrer De Carreras I Candi",
    "iso:country":"ES",
    "sg:address":"Carrer de Carreras I Candi, 22",
    "sg:city":"Barcelona",
    "sg:orig_category":"Bisuteros (fabricaci\u00d3n, Al Por Mayor)",
    "sg:phone":"+34 934 40 39 42",
    "sg:postcode":"08028",
    "sg:province":"Barcelona",
    "wof:name":"Villanueva Boix Oscar",
    "wof:placetype":"venue"
},
  "geometry": {"coordinates":[2.1264359951,41.3746376038],"type":"Point"}
}