{
  "type": "Feature",
  "properties": {
    "iso:country":"ES",
    "sg:address":"Calle de Novoa Santos, 42",
    "sg:city":"Coru\u00d1a",
    "sg:orig_category":"M\u00c9dicos: Estomatolog\u00cda",
    "sg:phone":"+34 981 13 02 49",
    "sg:postcode":"15006",
    "sg:province":"La Coru\u00f1a",
    "wof:name":"Parga Garcia Maria Jesus",
    "wof:placetype":"venue"
},
  "geometry": {"coordinates":[-8.4010601044,43.3558578491],"type":"Point"}
}