{
  "type": "Feature",
  "properties": {
    "addr:full":"Uzbina Kalea, 14 Jundiz \u00c1lava 01015",
    "addr:housenumber":"14",
    "addr:postcode":"01015",
    "addr:street":"Uzbina Kalea;A\u0301Lava",
    "iso:country":"ES",
    "sg:address":"Uzbina Kalea, 14",
    "sg:city":"Jundiz",
    "sg:orig_category":"Fabricaci\u00d3n De Revestimientos De Suelos Pl\u00c1sticos Y De Goma",
    "sg:phone":"+34 945 22 60 98",
    "sg:postcode":"01015",
    "sg:province":"\u00c1lava",
    "wof:name":"Retansa Coat S.l.",
    "wof:placetype":"venue"
},
  "geometry": {"coordinates":[-6.1999697685,43.3617782593],"type":"Point"}
}