{
  "type": "Feature",
  "properties": {
    "addr:full":"Avda Pirralos (los), 63 Dos Hermanas Sevilla 41700",
    "addr:housenumber":"63",
    "addr:postcode":"41700",
    "addr:street":"Avda Pirralos Los",
    "iso:country":"ES",
    "sg:address":"Avda Pirralos (los), 63",
    "sg:city":"Dos Hermanas",
    "sg:orig_category":"Multimedia: Servicios En L\u00cdnea, Acceso En L\u00cdnea, Cd",
    "sg:phone":"+34 955 66 53 59",
    "sg:postcode":"41700",
    "sg:province":"Sevilla",
    "sg:website":"www.autor-multimedia.com",
    "wof:name":"Autor Multimedia S.l.",
    "wof:placetype":"venue"
},
  "geometry": {"coordinates":[-5.9282631874,37.2760391235],"type":"Point"}
}