{
  "type": "Feature",
  "properties": {
    "addr:full":"Rua Paseo (do), 7 Ourense Ourense 32003",
    "addr:housenumber":"7",
    "addr:postcode":"32003",
    "addr:street":"Rua Paseo Do",
    "iso:country":"ES",
    "sg:address":"Rua Paseo (do), 7",
    "sg:city":"Ourense",
    "sg:classifiers":[
        {
            "category":"Banks & Credit Unions",
            "subcategory":"Bureau De Change",
            "type":"Services"
        }
    ],
    "sg:phone":"+34 988 37 30 10",
    "sg:postcode":"32003",
    "sg:province":"Ourense",
    "sg:tags":[
        "organismos",
        "control"
    ],
    "wof:name":"Asistencia Tecnica Industrial S. A. E.",
    "wof:placetype":"venue"
},
  "geometry": {"coordinates":[-7.8648309708,42.3382949829],"type":"Point"}
}