{
  "type": "Feature",
  "properties": {
    "iso:country":"ES",
    "sg:address":"Avda Maria Auxiliadora, 60",
    "sg:city":"Rota",
    "sg:orig_category":"Animales (al Por Menor)",
    "sg:phone":"+34 956 81 16 62",
    "sg:postcode":"11520",
    "sg:province":"C\u00e1diz",
    "wof:name":"Corrales Hernandez Jesus",
    "wof:placetype":"venue"
},
  "geometry": {"coordinates":[-6.3613290787,36.620891571],"type":"Point"}
}