{
  "type": "Feature",
  "properties": {
    "iso:country":"ES",
    "sg:address":"Calle de Doctor Ramon Castroviejo, 17",
    "sg:city":"Madrid",
    "sg:orig_category":"Trabajos De Revestimiento De Fachadas",
    "sg:phone":"+34 913 73 59 03",
    "sg:postcode":"28035",
    "sg:province":"Madrid",
    "wof:name":"Espalu S.a.",
    "wof:placetype":"venue"
},
  "geometry": {"coordinates":[-3.7147727013,40.4791145325],"type":"Point"}
}