{
  "type": "Feature",
  "properties": {
    "addr:full":"Carrer de Fortuny, 12 S. Feliu Guixols Girona 17220",
    "addr:housenumber":"12",
    "addr:postcode":"17220",
    "addr:street":"Carrer De Fortuny;S. Feliu Guixols",
    "iso:country":"ES",
    "sg:address":"Carrer de Fortuny, 12",
    "sg:city":"S. Feliu Guixols",
    "sg:orig_category":"Postigos, Persianas Y Celos\u00cdas",
    "sg:phone":"+34 972 32 61 85",
    "sg:postcode":"17220",
    "sg:province":"Girona",
    "wof:name":"Vila Domingo Xavier",
    "wof:placetype":"venue"
},
  "geometry": {"coordinates":[3.034334898,41.7846107483],"type":"Point"}
}