{
  "type": "Feature",
  "properties": {
    "iso:country":"ES",
    "sg:address":"Avda Picos De Europa, S/n",
    "sg:city":"Mansilla Mulas",
    "sg:orig_category":"Promotores Constructores",
    "sg:phone":"+34 987 31 18 24",
    "sg:postcode":"24210",
    "sg:province":"Le\u00f3n",
    "sg:website":"www.solmelia.com",
    "wof:name":"Asociacion Edad Dorada Mensajeros De La Paz Castilla Y Leon",
    "wof:placetype":"venue"
},
  "geometry": {"coordinates":[-5.4131960869,42.499042511],"type":"Point"}
}