{
  "type": "Feature",
  "properties": {
    "iso:country":"ES",
    "sg:address":"Cr Madrid-cartagena, S/n",
    "sg:city":"Casas De Roldan",
    "sg:orig_category":"Agricultores, Agricultores",
    "sg:phone":"+34 969 38 50 71",
    "sg:postcode":"16612",
    "sg:province":"Cuenca",
    "wof:name":"Agropecuaria Casa El Angel S.l.",
    "wof:placetype":"venue"
},
  "geometry": {"coordinates":[-2.376815,39.287956],"type":"Point"}
}