{
  "type": "Feature",
  "properties": {
    "addr:full":"Calle de Santa Angela De La Cruz, 14 Fuentes De Andalucia Sevilla 41420",
    "addr:housenumber":"14",
    "addr:postcode":"41420",
    "addr:street":"Calle De Santa Angela De La Cruz",
    "iso:country":"ES",
    "sg:address":"Calle de Santa Angela De La Cruz, 14",
    "sg:city":"Fuentes De Andalucia",
    "sg:orig_category":"Estancos",
    "sg:phone":"+34 954 83 76 17",
    "sg:postcode":"41420",
    "sg:province":"Sevilla",
    "wof:name":"Leon Martin Gertrudis",
    "wof:placetype":"venue"
},
  "geometry": {"coordinates":[-5.3451609612,37.4666671753],"type":"Point"}
}