{
  "type": "Feature",
  "properties": {
    "addr:full":"Plaz Conde Aranda, 1 Epila Zaragoza 50290",
    "addr:housenumber":"1",
    "addr:postcode":"50290",
    "addr:street":"Aranda",
    "iso:country":"ES",
    "sg:address":"Plaz Conde Aranda, 1",
    "sg:city":"Epila",
    "sg:orig_category":"Empresas De Escayolas",
    "sg:phone":"+34 976 81 72 88",
    "sg:postcode":"50290",
    "sg:province":"Zaragoza",
    "wof:name":"Medrano Ariza Tomas",
    "wof:placetype":"venue"
},
  "geometry": {"coordinates":[-1.2849140167,41.6030502319],"type":"Point"}
}