{
  "type": "Feature",
  "properties": {
    "addr:full":"Calle de Fuentezuela, 62 Rus Ja\u00e9n 23430",
    "addr:housenumber":"62",
    "addr:postcode":"23430",
    "addr:street":"Calle De Fuentezuela;Jae\u0301N",
    "iso:country":"ES",
    "sg:address":"Calle de Fuentezuela, 62",
    "sg:city":"Rus",
    "sg:orig_category":"Alimentaci\u00d3n General (al Por Menor)",
    "sg:phone":"+34 953 77 05 92",
    "sg:postcode":"23430",
    "sg:province":"Ja\u00e9n",
    "wof:name":"Chiclana Lopez Diego",
    "wof:placetype":"venue"
},
  "geometry": {"coordinates":[-3.460078001,38.0495567322],"type":"Point"}
}