{
  "type": "Feature",
  "properties": {
    "iso:country":"ES",
    "sg:address":"Calle de Cronista Matias De Haro, 31",
    "sg:city":"Bailen",
    "sg:orig_category":"Panader\u00cdas, Panader\u00cdas",
    "sg:phone":"+34 953 67 22 96",
    "sg:postcode":"23710",
    "sg:province":"Ja\u00e9n",
    "wof:name":"Garcia Davias Jose",
    "wof:placetype":"venue"
},
  "geometry": {"coordinates":[-3.7797527313,38.0941467285],"type":"Point"}
}