{
  "type": "Feature",
  "properties": {
    "iso:country":"ES",
    "sg:address":"Calle de Ancha Del Carmen, 39",
    "sg:city":"Malaga",
    "sg:orig_category":"Droguer\u00cdas (al Por Menor)",
    "sg:phone":"+34 952 31 39 45",
    "sg:postcode":"29002",
    "sg:province":"M\u00e1laga",
    "wof:name":"Martin Martin Juan Miguel",
    "wof:placetype":"venue"
},
  "geometry": {"coordinates":[-4.4285535812,36.7144088745],"type":"Point"}
}