{
  "type": "Feature",
  "properties": {
    "addr:full":"Avda Santander, 14 Aguilar Campoo Palencia 34800",
    "addr:housenumber":"14",
    "addr:postcode":"34800",
    "addr:street":"Avda Santander",
    "iso:country":"ES",
    "sg:address":"Avda Santander, 14",
    "sg:city":"Aguilar Campoo",
    "sg:orig_category":"Alimentaci\u00d3n General (al Por Menor)",
    "sg:phone":"+34 979 12 28 33",
    "sg:postcode":"34800",
    "sg:province":"Palencia",
    "wof:name":"Malanda Calderon Jesus",
    "wof:placetype":"venue"
},
  "geometry": {"coordinates":[-4.2540512085,42.7932090759],"type":"Point"}
}