{
  "type": "Feature",
  "properties": {
    "addr:full":"M. Rodoreda, 2 Tarragona Tarragona 43007",
    "addr:housenumber":"2",
    "addr:postcode":"43007",
    "addr:street":"M. Rodoreda",
    "iso:country":"ES",
    "sg:address":"M. Rodoreda, 2",
    "sg:city":"Tarragona",
    "sg:orig_category":"Inform\u00c1tica (estudios, Servicios, Asesor\u00cda, Formaci\u00d3n)",
    "sg:phone":"+34 977 29 20 43",
    "sg:postcode":"43007",
    "sg:province":"Tarragona",
    "wof:name":"Ribera Systems S.l.",
    "wof:placetype":"venue"
},
  "geometry": {"coordinates":[1.2746829987,41.1222076416],"type":"Point"}
}