{
  "type": "Feature",
  "properties": {
    "iso:country":"ES",
    "sg:address":"Calle de Primavera, 25",
    "sg:city":"Granada",
    "sg:orig_category":"Inmobiliaria (agencias)",
    "sg:phone":"+34 958 12 00 62",
    "sg:postcode":"18008",
    "sg:province":"Granada",
    "wof:name":"Rolabrysa S.l.",
    "wof:placetype":"venue"
},
  "geometry": {"coordinates":[-3.5938940048,37.1624755859],"type":"Point"}
}