{
  "type": "Feature",
  "properties": {
    "iso:country":"ES",
    "sg:address":"Carrer de Saragossa, 14",
    "sg:city":"S. Boi Llobregat",
    "sg:orig_category":"Suministros Y Materiales Industriales",
    "sg:phone":"+34 936 52 59 08",
    "sg:postcode":"08830",
    "sg:province":"Barcelona",
    "wof:name":"Digoine Automocion S.l.",
    "wof:placetype":"venue"
},
  "geometry": {"coordinates":[2.0518729687,41.3358078003],"type":"Point"}
}