{
  "type": "Feature",
  "properties": {
    "iso:country":"ES",
    "sg:address":"Calle de Amor Hermoso, 17",
    "sg:city":"Santomera",
    "sg:orig_category":"Asociaciones Y Clubs Deportivos",
    "sg:phone":"+34 968 86 04 69",
    "sg:postcode":"30140",
    "sg:province":"Murcia",
    "wof:name":"Perez Castellon Carmelo",
    "wof:placetype":"venue"
},
  "geometry": {"coordinates":[-1.0479687452,38.0611915588],"type":"Point"}
}