{
  "type": "Feature",
  "properties": {
    "addr:full":"Carrer de Pere Iv, 462 Barcelona Barcelona 08019",
    "addr:housenumber":"462",
    "addr:postcode":"08019",
    "addr:street":"Carrer De Pere Iv",
    "iso:country":"ES",
    "sg:address":"Carrer de Pere Iv, 462",
    "sg:city":"Barcelona",
    "sg:orig_category":"Suministros Para Hoteles",
    "sg:phone":"+34 933 08 09 97",
    "sg:postcode":"08019",
    "sg:province":"Barcelona",
    "wof:name":"Fornieles Marquez Cristobal",
    "wof:placetype":"venue"
},
  "geometry": {"coordinates":[2.206469059,41.4140472412],"type":"Point"}
}