{
  "type": "Feature",
  "properties": {
    "iso:country":"ES",
    "sg:address":"Calle de San Juan, 10",
    "sg:city":"Cudillero",
    "sg:orig_category":"Distribuci\u00d3n De Petr\u00d3leo Y Derivados",
    "sg:phone":"+34 985 59 05 70",
    "sg:postcode":"33150",
    "sg:province":"Asturias",
    "wof:name":"Albuerne Marques Ricardo",
    "wof:placetype":"venue"
},
  "geometry": {"coordinates":[-6.1468257904,43.5624198914],"type":"Point"}
}