{
  "type": "Feature",
  "properties": {
    "iso:country":"ES",
    "sg:address":"Cami Baix, De, 63",
    "sg:city":"Ciutadella Menorca",
    "sg:orig_category":"Arquitectos",
    "sg:phone":"+34 971 38 36 02",
    "sg:postcode":"07760",
    "sg:province":"Islas Baleares",
    "wof:name":"Agustin Petschen I Jordi Pons Arquitectos C. De B.",
    "wof:placetype":"venue"
},
  "geometry": {"coordinates":[3.8291351795,39.9985809326],"type":"Point"}
}