{
  "type": "Feature",
  "properties": {
    "addr:full":"Carrer de Industria, 2 Martorell Barcelona 08760",
    "addr:housenumber":"2",
    "addr:postcode":"08760",
    "addr:street":"Carrer De Industria",
    "iso:country":"ES",
    "sg:address":"Carrer de Industria, 2",
    "sg:city":"Martorell",
    "sg:orig_category":"Materias Pl\u00c1sticas: Productos De Consumo Masivo (fabricaci\u00d3n, Al Por Mayor)",
    "sg:phone":"+34 937 79 35 11",
    "sg:postcode":"08760",
    "sg:province":"Barcelona",
    "wof:name":"Basesa S.a.",
    "wof:placetype":"venue"
},
  "geometry": {"coordinates":[1.926699996,41.4809417725],"type":"Point"}
}