{
  "type": "Feature",
  "properties": {
    "iso:country":"ES",
    "sg:address":"Iturriotz Kalea, 4",
    "sg:city":"Arrasate",
    "sg:orig_category":"Lencer\u00cda Femenina, Corseter\u00cda, Trajes De Ba\u00d1o (al Por Menor)",
    "sg:phone":"+34 943 79 12 05",
    "sg:postcode":"20500",
    "sg:province":"Guip\u00f9zcoa",
    "wof:name":"Beatriz Etxabe Otady Y Otros C.b.",
    "wof:placetype":"venue"
},
  "geometry": {"coordinates":[-2.4893209934,43.0659866333],"type":"Point"}
}