{
  "type": "Feature",
  "properties": {
    "addr:full":"Carrer de Pi I Margall, 31 Barcelona Barcelona 08024",
    "addr:housenumber":"31",
    "addr:postcode":"08024",
    "addr:street":"Carrer De Pi I Margall",
    "iso:country":"ES",
    "sg:address":"Carrer de Pi I Margall, 31",
    "sg:city":"Barcelona",
    "sg:orig_category":"Panader\u00cdas, Panader\u00cdas",
    "sg:phone":"+34 932 85 69 49",
    "sg:postcode":"08024",
    "sg:province":"Barcelona",
    "wof:name":"Ignasi Castello S.a.",
    "wof:placetype":"venue"
},
  "geometry": {"coordinates":[2.1634879112,41.4079704285],"type":"Point"}
}