{
  "type": "Feature",
  "properties": {
    "iso:country":"ES",
    "sg:address":"Carrer de Mestral, S/n",
    "sg:city":"Llagostera",
    "sg:orig_category":"Tapones Y Art\u00cdculos De Corcho",
    "sg:phone":"+34 972 80 56 61",
    "sg:postcode":"17240",
    "sg:province":"Girona",
    "sg:website":"www.comercialcorcheracatalana.com",
    "wof:name":"Comercial Corchera Catalana S.l.",
    "wof:placetype":"venue"
},
  "geometry": {"coordinates":[2.9727549553,41.8591918945],"type":"Point"}
}