{
  "type": "Feature",
  "properties": {
    "addr:full":"Calle de Tercia, 7 Castro Rio C\u00f3rdoba 14840",
    "addr:housenumber":"7",
    "addr:postcode":"14840",
    "addr:street":"Calle De Tercia;Rio Co\u0301Rdoba",
    "iso:country":"ES",
    "sg:address":"Calle de Tercia, 7",
    "sg:city":"Castro Rio",
    "sg:orig_category":"Comerciantes Al Por Mayor De Vinos, Licores Y Alcoholes",
    "sg:phone":"+34 957 37 02 59",
    "sg:postcode":"14840",
    "sg:province":"C\u00f3rdoba",
    "wof:name":"Aranda Gutierrez Jose",
    "wof:placetype":"venue"
},
  "geometry": {"coordinates":[-4.4827332497,37.6888084412],"type":"Point"}
}