{
  "type": "Feature",
  "properties": {
    "iso:country":"ES",
    "sg:address":"Ctra. Belones, S/n",
    "sg:city":"Los Nietos",
    "sg:orig_category":"Producci\u00d3n De Huevos",
    "sg:phone":"+34 968 13 36 37",
    "sg:postcode":"30383",
    "sg:province":"Murcia",
    "wof:name":"Avicola San Isidro S.l.",
    "wof:placetype":"venue"
},
  "geometry": {"coordinates":[-0.8088939786,37.6547164917],"type":"Point"}
}