{
  "type": "Feature",
  "properties": {
    "addr:full":"Aeropuerto, S/n Agoncillo La Rioja 26509",
    "addr:housenumber":"s / n",
    "addr:postcode":"26509",
    "addr:street":"Rioja",
    "iso:country":"ES",
    "sg:address":"Aeropuerto, S/n",
    "sg:city":"Agoncillo",
    "sg:orig_category":"Aeropuertos Y Servicios Aeroportuarios",
    "sg:phone":"+34 941 43 11 39",
    "sg:postcode":"26509",
    "sg:province":"La Rioja",
    "wof:name":"Aireuropa Lineas Aereas S.a.",
    "wof:placetype":"venue"
},
  "geometry": {"coordinates":[-2.3202776909,42.4602775574],"type":"Point"}
}