{
  "type": "Feature",
  "properties": {
    "addr:full":"Avda Lerida (de), 34 Monzon Huesca 22400",
    "addr:housenumber":"34",
    "addr:postcode":"22400",
    "addr:street":"Avda Lerida De",
    "iso:country":"ES",
    "sg:address":"Avda Lerida (de), 34",
    "sg:city":"Monzon",
    "sg:orig_category":"Empresas De Pintura Y Revestimientos",
    "sg:phone":"+34 974 41 50 45",
    "sg:postcode":"22400",
    "sg:province":"Huesca",
    "wof:name":"Sopena Atanasio Nuria",
    "wof:placetype":"venue"
},
  "geometry": {"coordinates":[0.1980150044,41.9093093872],"type":"Point"}
}