{
  "type": "Feature",
  "properties": {
    "iso:country":"ES",
    "sg:address":"Calle de Belgica, 53",
    "sg:city":"Pinto",
    "sg:classifiers":[
        {
            "category":"Autos & Motor Vehicles",
            "subcategory":"Automobile Sales",
            "type":"Retail Goods"
        }
    ],
    "sg:phone":"+34 916 92 49 28",
    "sg:postcode":"28320",
    "sg:province":"Madrid",
    "wof:name":"Centros De Conduccion De Automoviles S.l.",
    "wof:placetype":"venue"
},
  "geometry": {"coordinates":[-3.6959295273,40.251247406],"type":"Point"}
}