{
  "type": "Feature",
  "properties": {
    "addr:full":"Av Magaluf, S/n Magaluf Islas Baleares 07181",
    "addr:housenumber":"s / n",
    "addr:postcode":"07181",
    "addr:street":"Av Magaluf",
    "iso:country":"ES",
    "sg:address":"Av Magaluf, S/n",
    "sg:city":"Magaluf",
    "sg:orig_category":"Bisuter\u00cda, Joyer\u00cda, Relojer\u00cda (al Por Menor)",
    "sg:phone":"+34 971 13 23 47",
    "sg:postcode":"07181",
    "sg:province":"Islas Baleares",
    "wof:name":"Tizon Aceldegui Juan Jose",
    "wof:placetype":"venue"
},
  "geometry": {"coordinates":[2.5323300362,39.5054512024],"type":"Point"}
}