{
  "type": "Feature",
  "properties": {
    "addr:full":"Carrer de Berlines, 31 Barcelona Barcelona 08022",
    "addr:housenumber":"31",
    "addr:postcode":"08022",
    "addr:street":"Carrer De Berlines",
    "iso:country":"ES",
    "sg:address":"Carrer de Berlines, 31",
    "sg:city":"Barcelona",
    "sg:orig_category":"Ingenier\u00cda, Centros De Estudios (diversos)",
    "sg:phone":"+34 932 12 55 58",
    "sg:postcode":"08022",
    "sg:province":"Barcelona",
    "wof:name":"Garcia Bbm S. L",
    "wof:placetype":"venue"
},
  "geometry": {"coordinates":[2.1381959915,41.4042663574],"type":"Point"}
}