{
  "type": "Feature",
  "properties": {
    "addr:full":"Carrer de Rubio I Ors, 144 Cornella Llobregat Barcelona 08940",
    "addr:housenumber":"144",
    "addr:postcode":"08940",
    "addr:street":"Carrer De Rubio;Ors",
    "iso:country":"ES",
    "sg:address":"Carrer de Rubio I Ors, 144",
    "sg:city":"Cornella Llobregat",
    "sg:orig_category":"Ropa Para Se\u00d1oras Y Caballeros (al Por Menor)",
    "sg:phone":"+34 933 77 04 62",
    "sg:postcode":"08940",
    "sg:province":"Barcelona",
    "wof:name":"Pi\u00f1ol Balasch Jordi",
    "wof:placetype":"venue"
},
  "geometry": {"coordinates":[2.0695929527,41.3528404236],"type":"Point"}
}