{
  "type": "Feature",
  "properties": {
    "iso:country":"ES",
    "sg:address":"Calle de Paz, 42",
    "sg:city":"Alcazar S. Juan",
    "sg:orig_category":"Mec\u00c1nico Del Autom\u00d3vil",
    "sg:phone":"+34 926 55 06 24",
    "sg:postcode":"13600",
    "sg:province":"Ciudad Real",
    "wof:name":"Tecnocar C.b.",
    "wof:placetype":"venue"
},
  "geometry": {"coordinates":[-3.2079589367,39.3842735291],"type":"Point"}
}