{
  "type": "Feature",
  "properties": {
    "addr:full":"Ctra Sant Hipolit, Km. 0000,9 Vic Barcelona 08500",
    "addr:postcode":"08500",
    "addr:street":"Ctra Sant Hipolit Km. 0000,9",
    "iso:country":"ES",
    "sg:address":"Ctra Sant Hipolit, Km. 0000,9",
    "sg:city":"Vic",
    "sg:orig_category":"Calefacci\u00d3n Central: Material (fabricaci\u00d3n, Al Por Mayor)",
    "sg:phone":"+34 938 86 11 53",
    "sg:postcode":"08500",
    "sg:province":"Barcelona",
    "wof:name":"Julian Arumi S.l.",
    "wof:placetype":"venue"
},
  "geometry": {"coordinates":[2.2540359497,41.9390411377],"type":"Point"}
}