{
  "type": "Feature",
  "properties": {
    "addr:full":"Calle de Cervantes, 12 Le\u00f3n Le\u00f3n 24003",
    "addr:housenumber":"12",
    "addr:postcode":"24003",
    "addr:street":"Calle De Cervantes;Leo\u0301N",
    "iso:country":"ES",
    "sg:address":"Calle de Cervantes, 12",
    "sg:city":"Le\u00f3n",
    "sg:orig_category":"Institutos De Belleza",
    "sg:phone":"+34 987 24 24 04",
    "sg:postcode":"24003",
    "sg:province":"Le\u00f3n",
    "wof:name":"Carbajal Garcia Monica",
    "wof:placetype":"venue"
},
  "geometry": {"coordinates":[-5.5691537857,42.5993537903],"type":"Point"}
}