{
  "type": "Feature",
  "properties": {
    "addr:full":"Avda Breogan, 63 Ferrol La Coru\u00f1a 15401",
    "addr:housenumber":"63",
    "addr:postcode":"15401",
    "addr:street":"Avda Breogan;La Corun\u0303A",
    "iso:country":"ES",
    "sg:address":"Avda Breogan, 63",
    "sg:city":"Ferrol",
    "sg:orig_category":"Abogados",
    "sg:phone":"+34 981 35 45 66",
    "sg:postcode":"15401",
    "sg:province":"La Coru\u00f1a",
    "wof:name":"Estevan Alberto Mariano",
    "wof:placetype":"venue"
},
  "geometry": {"coordinates":[-8.2273387909,43.4868507385],"type":"Point"}
}