{
  "type": "Feature",
  "properties": {
    "iso:country":"ES",
    "sg:address":"Calle de Rosario, 16",
    "sg:city":"Albacete",
    "sg:orig_category":"Asesor\u00cda Fiscal Y Jur\u00cddica",
    "sg:phone":"+34 967 21 61 12",
    "sg:postcode":"02001",
    "sg:province":"Albacete",
    "wof:name":"Cano Moreno Moises",
    "wof:placetype":"venue"
},
  "geometry": {"coordinates":[-1.8562179804,38.9942359924],"type":"Point"}
}