{
  "type": "Feature",
  "properties": {
    "addr:full":"Avda Pablo Neruda, 98 Madrid Madrid 28018",
    "addr:housenumber":"98",
    "addr:postcode":"madrid;28018",
    "addr:street":"Avda Pablo Neruda",
    "iso:country":"ES",
    "sg:address":"Avda Pablo Neruda, 98",
    "sg:city":"Madrid",
    "sg:orig_category":"Molduras, Junquillos, Listones Y Molduras Perforadas",
    "sg:phone":"+34 913 80 39 41",
    "sg:postcode":"28018",
    "sg:province":"Madrid",
    "wof:name":"Cytasa Comunicaciones S.l.",
    "wof:placetype":"venue"
},
  "geometry": {"coordinates":[-3.653660059,40.3816452026],"type":"Point"}
}