{
  "type": "Feature",
  "properties": {
    "iso:country":"ES",
    "sg:address":"Rua Elduayen, 17",
    "sg:city":"Vigo",
    "sg:orig_category":"Ropa De Hogar (al Por Menor)",
    "sg:phone":"+34 986 43 25 97",
    "sg:postcode":"36202",
    "sg:province":"Pontevedra",
    "wof:name":"Galihogar Sociedad Cooperativa",
    "wof:placetype":"venue"
},
  "geometry": {"coordinates":[-8.7275314331,42.237827301],"type":"Point"}
}