{
  "type": "Feature",
  "properties": {
    "iso:country":"ES",
    "sg:address":"Pase Revellin (del), 30",
    "sg:city":"Ceuta",
    "sg:classifiers":[
        {
            "category":"Professional",
            "subcategory":"Research",
            "type":"Services"
        }
    ],
    "sg:phone":"+34 956 51 00 17",
    "sg:postcode":"51001",
    "sg:province":"Ceuta",
    "sg:tags":[
        "mercado",
        "de",
        "estudios"
    ],
    "wof:name":"Instituto De Estudios Ceuties",
    "wof:placetype":"venue"
},
  "geometry": {"coordinates":[-5.3302302361,35.8947601318],"type":"Point"}
}