{
  "type": "Feature",
  "properties": {
    "iso:country":"ES",
    "sg:address":"Carrer de Sepulveda, 151",
    "sg:city":"Barcelona",
    "sg:orig_category":"Carnicer\u00cdas, Carnicer\u00cdas",
    "sg:phone":"+34 934 54 73 72",
    "sg:postcode":"08011",
    "sg:province":"Barcelona",
    "wof:name":"Cordero Sanchez Serafin",
    "wof:placetype":"venue"
},
  "geometry": {"coordinates":[2.1611618996,41.3823890686],"type":"Point"}
}