{
  "type": "Feature",
  "properties": {
    "iso:country":"ES",
    "sg:address":"Carr Major, 53",
    "sg:city":"Bescano",
    "sg:orig_category":"Ense\u00d1anza: Profesiones Art\u00cdsticas",
    "sg:phone":"+34 972 44 04 26",
    "sg:postcode":"17162",
    "sg:province":"Girona",
    "wof:name":"Joan I Josep Segur S.c.",
    "wof:placetype":"venue"
},
  "geometry": {"coordinates":[2.7389070988,41.9661102295],"type":"Point"}
}