{
  "type": "Feature",
  "properties": {
    "iso:country":"ES",
    "sg:address":"Borrateiros, 9",
    "sg:city":"Borrateiros",
    "sg:orig_category":"Gases Industriales",
    "sg:phone":"+34 986 70 85 31",
    "sg:postcode":"36140",
    "sg:province":"Pontevedra",
    "wof:name":"Suministros Industriales Jumor Cb",
    "wof:placetype":"venue"
},
  "geometry": {"coordinates":[-8.6514892578,42.3227615356],"type":"Point"}
}