{
  "type": "Feature",
  "properties": {
    "addr:full":"Pol Ind Camino Angosto, 18 Mancha Real Ja\u00e9n 23100",
    "addr:housenumber":"18",
    "addr:postcode":"23100",
    "addr:street":"Camino Angosto",
    "iso:country":"ES",
    "sg:address":"Pol Ind Camino Angosto, 18",
    "sg:city":"Mancha Real",
    "sg:orig_category":"Piedra Natural",
    "sg:phone":"+34 953 35 11 03",
    "sg:postcode":"23100",
    "sg:province":"Ja\u00e9n",
    "sg:website":"www.paginasamarillas.es",
    "wof:name":"Artesur Gomez Cobo C.b.",
    "wof:placetype":"venue"
},
  "geometry": {"coordinates":[-3.6217813492,37.813495636],"type":"Point"}
}