{
  "type": "Feature",
  "properties": {
    "iso:country":"ES",
    "sg:address":"Rua Pravia (da), 42",
    "sg:city":"Vilalba",
    "sg:classifiers":[
        {
            "category":"Communications",
            "type":"Services"
        }
    ],
    "sg:phone":"+34 982 51 01 12",
    "sg:postcode":"27800",
    "sg:province":"Lugo",
    "sg:tags":[
        "televisiones",
        "y",
        "radio"
    ],
    "wof:name":"Radio Principal S.a.",
    "wof:placetype":"venue"
},
  "geometry": {"coordinates":[-7.6790909767,43.2989959717],"type":"Point"}
}