{
  "type": "Feature",
  "properties": {
    "iso:country":"ES",
    "sg:address":"Calle de Pedro Laborde, 48",
    "sg:city":"Madrid",
    "sg:orig_category":"Molduras, Junquillos, Listones Y Molduras Perforadas",
    "sg:phone":"+34 913 03 78 99",
    "sg:postcode":"28038",
    "sg:province":"Madrid",
    "wof:name":"Gila Burgos Juan",
    "wof:placetype":"venue"
},
  "geometry": {"coordinates":[-3.648788929,40.3878135681],"type":"Point"}
}