{
  "type": "Feature",
  "properties": {
    "iso:country":"ES",
    "sg:address":"Ctra Rueda, S/n",
    "sg:city":"Seca",
    "sg:orig_category":"Productores Recolectores, Venta Directa De Vinos",
    "sg:phone":"+34 983 81 63 26",
    "sg:postcode":"47491",
    "sg:province":"Valladolid",
    "wof:name":"Predio De Vascarlon S.l.",
    "wof:placetype":"venue"
},
  "geometry": {"coordinates":[-4.9083590508,41.4160308838],"type":"Point"}
}