{
  "type": "Feature",
  "properties": {
    "addr:full":"Avda Inmaculada Concepcion, S/n Sauzal Santa Cruz De Tenerife 38360",
    "addr:housenumber":"s / n",
    "addr:postcode":"38360",
    "addr:street":"Avda Inmaculada Concepcion",
    "iso:country":"ES",
    "sg:address":"Avda Inmaculada Concepcion, S/n",
    "sg:city":"Sauzal",
    "sg:orig_category":"Frutas, Legumbres Frescas Y Tempranas (al Por Menor)",
    "sg:phone":"+34 922 56 43 46",
    "sg:postcode":"38360",
    "sg:province":"Santa Cruz De Tenerife",
    "wof:name":"Perez Perez Ana Maria",
    "wof:placetype":"venue"
},
  "geometry": {"coordinates":[-16.4346046448,28.4799137115],"type":"Point"}
}