{
  "type": "Feature",
  "properties": {
    "addr:full":"Avda Primero De Mayo, 66 Coria Rio Sevilla 41100",
    "addr:housenumber":"66",
    "addr:postcode":"41100",
    "addr:street":"Avda Primero De Mayo;Rio Sevilla",
    "iso:country":"ES",
    "sg:address":"Avda Primero De Mayo, 66",
    "sg:city":"Coria Rio",
    "sg:orig_category":"Ropa De Hogar (al Por Menor)",
    "sg:phone":"+34 954 77 37 61",
    "sg:postcode":"41100",
    "sg:province":"Sevilla",
    "wof:name":"Curiel Garcia Rosa Maria",
    "wof:placetype":"venue"
},
  "geometry": {"coordinates":[-6.0522379875,37.2911148071],"type":"Point"}
}