{
  "type": "Feature",
  "properties": {
    "iso:country":"ES",
    "sg:address":"Avda Barcelona, 2",
    "sg:city":"Jaen",
    "sg:orig_category":"Herramientas Y Suministros Para Plomeros",
    "sg:phone":"+34 953 22 01 43",
    "sg:postcode":"23006",
    "sg:province":"Ja\u00e9n",
    "wof:name":"Diego Santiago Miguel Angel",
    "wof:placetype":"venue"
},
  "geometry": {"coordinates":[-3.7980089188,37.7805480957],"type":"Point"}
}