{
  "type": "Feature",
  "properties": {
    "iso:country":"ES",
    "sg:address":"Calle de Taberna, 3",
    "sg:city":"Marchamalo",
    "sg:orig_category":"Loter\u00cda Y T\u00d3mbola",
    "sg:phone":"+34 949 25 23 61",
    "sg:postcode":"19180",
    "sg:province":"Guadalajara",
    "wof:name":"Pajares Garcia Ana Isabel",
    "wof:placetype":"venue"
},
  "geometry": {"coordinates":[-3.202452898,40.6688537598],"type":"Point"}
}