{
  "type": "Feature",
  "properties": {
    "iso:country":"ES",
    "sg:address":"Avda Vigo, 16",
    "sg:city":"Pontecaldelas",
    "sg:orig_category":"Ense\u00d1anza: Profesiones Art\u00cdsticas",
    "sg:phone":"+34 986 76 72 33",
    "sg:postcode":"36820",
    "sg:province":"Pontevedra",
    "wof:name":"Foto Alameda C.b.",
    "wof:placetype":"venue"
},
  "geometry": {"coordinates":[-8.4997596741,42.3941688538],"type":"Point"}
}