{
  "type": "Feature",
  "properties": {
    "iso:country":"ES",
    "sg:address":"Play Benitez, S/n",
    "sg:city":"Ceuta",
    "sg:orig_category":"Promotores Constructores",
    "sg:phone":"+34 956 50 15 48",
    "sg:postcode":"51004",
    "sg:province":"Ceuta",
    "wof:name":"Robles Velasco Jose",
    "wof:placetype":"venue"
},
  "geometry": {"coordinates":[-5.3568201065,35.9010009766],"type":"Point"}
}