{
  "type": "Feature",
  "properties": {
    "addr:full":"Calle de Padre Francisco Palau Y Quer, 3 Madrid Madrid 28046",
    "addr:housenumber":"3",
    "addr:postcode":"28046",
    "addr:street":"Calle De Padre Francisco Palau Y Quer",
    "iso:country":"ES",
    "sg:address":"Calle de Padre Francisco Palau Y Quer, 3",
    "sg:city":"Madrid",
    "sg:orig_category":"Estancos",
    "sg:phone":"+34 913 15 30 13",
    "sg:postcode":"28046",
    "sg:province":"Madrid",
    "wof:name":"Sanchez Sanchez-mascaraque Francisco Jose",
    "wof:placetype":"venue"
},
  "geometry": {"coordinates":[-3.6856150627,40.4737625122],"type":"Point"}
}