{
  "type": "Feature",
  "properties": {
    "iso:country":"ES",
    "sg:address":"Calle de Alcalde Segalerva Sierra, 14",
    "sg:city":"Malaga",
    "sg:orig_category":"Empresas De Carpinter\u00cda Met\u00c1lica",
    "sg:phone":"+34 952 36 07 55",
    "sg:postcode":"29006",
    "sg:province":"M\u00e1laga",
    "wof:name":"Hermanos Beltran Transformaciones Metalicas S.l.",
    "wof:placetype":"venue"
},
  "geometry": {"coordinates":[-4.4733119011,36.7089538574],"type":"Point"}
}