{
  "type": "Feature",
  "properties": {
    "iso:country":"ES",
    "sg:address":"Carrer de Argentera, 21",
    "sg:city":"Reus",
    "sg:orig_category":"Carnicer\u00cdas, Carnicer\u00cdas",
    "sg:phone":"+34 977 32 19 53",
    "sg:postcode":"43202",
    "sg:province":"Tarragona",
    "wof:name":"Sabate Auque Maria Felicidad",
    "wof:placetype":"venue"
},
  "geometry": {"coordinates":[1.0976829529,41.1553688049],"type":"Point"}
}