{
  "type": "Feature",
  "properties": {
    "iso:country":"ES",
    "sg:address":"Calle de Tristana, 34",
    "sg:city":"Palmas De Gran Canaria",
    "sg:orig_category":"Inmobiliaria (agencias)",
    "sg:phone":"+34 928 25 72 01",
    "sg:postcode":"35012",
    "sg:province":"Las Palmas",
    "wof:name":"Comunidad De Propietarios Edificio Tristana 34",
    "wof:placetype":"venue"
},
  "geometry": {"coordinates":[-15.4345932007,28.110168457],"type":"Point"}
}