{
  "type": "Feature",
  "properties": {
    "iso:country":"ES",
    "sg:address":"Cervantes, 38",
    "sg:city":"La Redondela",
    "sg:orig_category":"Producci\u00d3n, Venta De Productos De Agricultura Biol\u00d3gica",
    "sg:phone":"+34 959 34 10 88",
    "sg:postcode":"21430",
    "sg:province":"Huelva",
    "wof:name":"Martin Alfonseca Jose",
    "wof:placetype":"venue"
},
  "geometry": {"coordinates":[-7.2736940384,37.2221298218],"type":"Point"}
}