{
  "type": "Feature",
  "properties": {
    "iso:country":"ES",
    "sg:address":"Avda San Fermin, 15",
    "sg:city":"Madrid",
    "sg:orig_category":"Plomeros",
    "sg:phone":"+34 914 76 13 74",
    "sg:postcode":"28041",
    "sg:province":"Madrid",
    "wof:name":"O.s.l-punto Y Numero Cero S.l.",
    "wof:placetype":"venue"
},
  "geometry": {"coordinates":[-3.690431118,40.3714447021],"type":"Point"}
}