{
  "type": "Feature",
  "properties": {
    "addr:full":"Carr Barcelona, 39 Balaguer Lleida 25600",
    "addr:housenumber":"39",
    "addr:postcode":"25600",
    "addr:street":"Carr Barcelona",
    "iso:country":"ES",
    "sg:address":"Carr Barcelona, 39",
    "sg:city":"Balaguer",
    "sg:orig_category":"Pintura Y Barniz (al Por Menor)",
    "sg:phone":"+34 973 44 30 41",
    "sg:postcode":"25600",
    "sg:province":"Lleida",
    "wof:name":"Tarros Pintures I Decoracio S.l.",
    "wof:placetype":"venue"
},
  "geometry": {"coordinates":[0.8111900091,41.7886581421],"type":"Point"}
}