{
  "type": "Feature",
  "properties": {
    "iso:country":"ES",
    "sg:address":"Calle de Mayor Principal, 28",
    "sg:city":"Palencia",
    "sg:orig_category":"Heladeros",
    "sg:phone":"+34 979 74 38 60",
    "sg:postcode":"34001",
    "sg:province":"Palencia",
    "sg:website":"www.paginasamarillas.es",
    "wof:name":"Ruiz Gutierrez Paula Flora",
    "wof:placetype":"venue"
},
  "geometry": {"coordinates":[-4.5392618179,42.010433197],"type":"Point"}
}