{
  "type": "Feature",
  "properties": {
    "iso:country":"ES",
    "sg:address":"Cno Ti\u00f1osa(s J De La Vega), 47",
    "sg:city":"Beniajan",
    "sg:orig_category":"Cerrajer\u00cda, Ferrallista",
    "sg:phone":"+34 968 87 42 20",
    "sg:postcode":"30570",
    "sg:province":"Murcia",
    "wof:name":"Cerrajeria Metalica Lopez Y Beltran S.l.",
    "wof:placetype":"venue"
},
  "geometry": {"coordinates":[-1.0715739727,37.9755134583],"type":"Point"}
}