{
  "type": "Feature",
  "properties": {
    "addr:full":"Carrer de Sants, 85 Barcelona Barcelona 08014",
    "addr:housenumber":"85",
    "addr:postcode":"08014",
    "addr:street":"Carrer De Sants",
    "iso:country":"ES",
    "sg:address":"Carrer de Sants, 85",
    "sg:city":"Barcelona",
    "sg:orig_category":"Administradores De Bienes Y Delegados De Comunidades De Propietarios",
    "sg:phone":"+34 934 22 42 11",
    "sg:postcode":"08014",
    "sg:province":"Barcelona",
    "sg:website":"dianafinques.com",
    "wof:name":"Castiger 2002 S. L.",
    "wof:placetype":"venue"
},
  "geometry": {"coordinates":[2.1364700794,41.3753242493],"type":"Point"}
}