{
  "type": "Feature",
  "properties": {
    "addr:full":"Calle de Mayor, 15 Alcantarilla Murcia 30820",
    "addr:housenumber":"15",
    "addr:postcode":"30820",
    "addr:street":"Calle De Mayor",
    "iso:country":"ES",
    "sg:address":"Calle de Mayor, 15",
    "sg:city":"Alcantarilla",
    "sg:orig_category":"Cajas De Ahorro",
    "sg:phone":"+34 968 83 62 45",
    "sg:postcode":"30820",
    "sg:province":"Murcia",
    "wof:name":"Caja De Ahorros De Valencia Castellon Y Alicante",
    "wof:placetype":"venue"
},
  "geometry": {"coordinates":[-1.2086869478,37.972869873],"type":"Point"}
}