{
  "type": "Feature",
  "properties": {
    "iso:country":"ES",
    "sg:address":"Pase Explanada (de La), 31",
    "sg:city":"Petrer",
    "sg:orig_category":"Asociaciones Y Clubs Deportivos",
    "sg:phone":"+34 965 37 50 37",
    "sg:postcode":"03610",
    "sg:province":"Alicante",
    "wof:name":"Club Iron-gyn",
    "wof:placetype":"venue"
},
  "geometry": {"coordinates":[-0.7716709971,38.4817314148],"type":"Point"}
}