{
  "type": "Feature",
  "properties": {
    "addr:full":"Trva San Rafael, 11 Linares Ja\u00e9n 23700",
    "addr:housenumber":"11",
    "addr:postcode":"23700",
    "addr:street":"Trva San Rafael;Jae\u0301N",
    "iso:country":"ES",
    "sg:address":"Trva San Rafael, 11",
    "sg:city":"Linares",
    "sg:orig_category":"Empresas De Carpinter\u00cda Met\u00c1lica",
    "sg:phone":"+34 953 60 28 36",
    "sg:postcode":"23700",
    "sg:province":"Ja\u00e9n",
    "wof:name":"Ruiz Pozas Miguel",
    "wof:placetype":"venue"
},
  "geometry": {"coordinates":[-3.6354179382,38.1045951843],"type":"Point"}
}