{
  "type": "Feature",
  "properties": {
    "iso:country":"ES",
    "sg:address":"Calle de Sagasta, 72",
    "sg:city":"Palmas De Gran Canaria",
    "sg:orig_category":"Fabricaci\u00d3n De Productos Textiles Sin Tejer",
    "sg:phone":"+34 928 27 25 02",
    "sg:postcode":"35008",
    "sg:province":"Las Palmas",
    "wof:name":"Isa Khuory Nicolas",
    "wof:placetype":"venue"
},
  "geometry": {"coordinates":[-15.4301662445,28.1467723846],"type":"Point"}
}