{
  "type": "Feature",
  "properties": {
    "iso:country":"ES",
    "sg:address":"Calle de Platero Pedro De Bares, 37",
    "sg:city":"Cordoba",
    "sg:orig_category":"Inmobiliaria (agencias)",
    "sg:phone":"+34 957 76 48 97",
    "sg:postcode":"14007",
    "sg:province":"C\u00f3rdoba",
    "wof:name":"Estudio Cordoba Fatima 2002 S.l.",
    "wof:placetype":"venue"
},
  "geometry": {"coordinates":[-4.7556729317,37.8948974609],"type":"Point"}
}