{
  "type": "Feature",
  "properties": {
    "iso:country":"ES",
    "sg:address":"M. Redondo (urb Pla Del Castell), 1",
    "sg:city":"Collbato",
    "sg:orig_category":"Piscinas, Accesorios, Suministros (fabricaci\u00d3n, Al Por Mayor)",
    "sg:phone":"+34 937 77 08 65",
    "sg:postcode":"08293",
    "sg:province":"Barcelona",
    "wof:name":"Piscinas Vidazur S.l.",
    "wof:placetype":"venue"
},
  "geometry": {"coordinates":[1.8213499784,41.5657081604],"type":"Point"}
}