{
  "type": "Feature",
  "properties": {
    "iso:country":"ES",
    "sg:address":"Avda Puerto De Santa Maria, Km. 0001,0",
    "sg:city":"Sanlucar De Barrameda",
    "sg:orig_category":"Aparatos E Instalaci\u00d3n De Regad\u00cdos",
    "sg:phone":"+34 956 36 12 71",
    "sg:postcode":"11540",
    "sg:province":"C\u00e1diz",
    "wof:name":"Flores Chisan S.l.",
    "wof:placetype":"venue"
},
  "geometry": {"coordinates":[-6.3467011452,36.7666854858],"type":"Point"}
}