{
  "type": "Feature",
  "properties": {
    "iso:country":"ES",
    "sg:address":"Calle de Rafael Alberti, 8",
    "sg:city":"Garrovilla",
    "sg:orig_category":"Quincaller\u00cda (al Por Menor)",
    "sg:phone":"+34 924 33 51 19",
    "sg:postcode":"06870",
    "sg:province":"Badajoz",
    "wof:name":"Roque Donoso Jose",
    "wof:placetype":"venue"
},
  "geometry": {"coordinates":[-6.4824938774,38.9198150635],"type":"Point"}
}