{
  "type": "Feature",
  "properties": {
    "iso:country":"ES",
    "sg:address":"Calle de Zankoeta, 9",
    "sg:city":"Bilbao",
    "sg:orig_category":"Asociaciones Y Clubs Deportivos",
    "sg:phone":"+34 944 27 41 18",
    "sg:postcode":"48013",
    "sg:province":"Vizcaya",
    "wof:name":"Daniel Pascual Garcia-ignacio Javier Barreiro C.b.",
    "wof:placetype":"venue"
},
  "geometry": {"coordinates":[-2.9461090565,43.2581100464],"type":"Point"}
}