{
  "type": "Feature",
  "properties": {
    "addr:full":"Avda Felipe Ii, 34 Madrid Madrid 28009",
    "addr:housenumber":"34",
    "addr:postcode":"madrid;28009",
    "addr:street":"Avda Felipe Ii",
    "iso:country":"ES",
    "sg:address":"Avda Felipe Ii, 34",
    "sg:city":"Madrid",
    "sg:orig_category":"Abogados",
    "sg:phone":"+34 914 31 82 62",
    "sg:postcode":"28009",
    "sg:province":"Madrid",
    "wof:name":"Cuerda Y De Miguel Antonio",
    "wof:placetype":"venue"
},
  "geometry": {"coordinates":[-3.6730220318,40.4237670898],"type":"Point"}
}