{
  "type": "Feature",
  "properties": {
    "iso:country":"ES",
    "sg:address":"Prol Juan R Jimenez, 2",
    "sg:city":"Bailen",
    "sg:orig_category":"Trabajos De Topograf\u00cda",
    "sg:phone":"+34 953 67 36 10",
    "sg:postcode":"23710",
    "sg:province":"Ja\u00e9n",
    "wof:name":"Medina Garcia Isabel",
    "wof:placetype":"venue"
},
  "geometry": {"coordinates":[-3.7822730541,38.0966796875],"type":"Point"}
}