{
  "type": "Feature",
  "properties": {
    "iso:country":"ES",
    "sg:address":"Avda Alfonso El Sabio, 45",
    "sg:city":"Alacant",
    "sg:orig_category":"Droguer\u00cdas (al Por Menor)",
    "sg:phone":"+34 965 21 40 53",
    "sg:postcode":"03001",
    "sg:province":"Alicante",
    "wof:name":"Lopez Soriano Pedro",
    "wof:placetype":"venue"
},
  "geometry": {"coordinates":[-0.4896799922,38.3462638855],"type":"Point"}
}