{
  "type": "Feature",
  "properties": {
    "addr:full":"Pase Zorrilla, 96 Valladolid Valladolid 47006",
    "addr:housenumber":"96",
    "addr:postcode":"47006",
    "addr:street":"Zorrilla",
    "iso:country":"ES",
    "sg:address":"Pase Zorrilla, 96",
    "sg:city":"Valladolid",
    "sg:orig_category":"M\u00c9dicos: Anestesiolog\u00cda Y Reanimaci\u00d3n Quir\u00dargica",
    "sg:phone":"+34 983 23 62 40",
    "sg:postcode":"47006",
    "sg:province":"Valladolid",
    "wof:name":"De Paz De Paz Juan Felix",
    "wof:placetype":"venue"
},
  "geometry": {"coordinates":[-4.7384538651,41.6395874023],"type":"Point"}
}