{
  "type": "Feature",
  "properties": {
    "iso:country":"ES",
    "sg:address":"Pol Ind Aljoroque, S/n",
    "sg:city":"Antas",
    "sg:orig_category":"Abrasivos Y Superabrasivos (fabricaci\u00d3n, Al Por Mayor)",
    "sg:phone":"+34 950 61 90 30",
    "sg:postcode":"04628",
    "sg:province":"Almer\u00eda",
    "sg:website":"www.abrasivosmanhattan.es",
    "wof:name":"Abrasivos Manhattan S.a.",
    "wof:placetype":"venue"
},
  "geometry": {"coordinates":[-1.958801,37.270367],"type":"Point"}
}