{
  "type": "Feature",
  "properties": {
    "addr:full":"Ctra Ronda, 10 Baza Granada 18800",
    "addr:housenumber":"10",
    "addr:postcode":"18800",
    "addr:street":"Ctra Ronda",
    "iso:country":"ES",
    "sg:address":"Ctra Ronda, 10",
    "sg:city":"Baza",
    "sg:orig_category":"Transportes Por V\u00cdas Navegables",
    "sg:phone":"+34 958 70 12 90",
    "sg:postcode":"18800",
    "sg:province":"Granada",
    "wof:name":"Martinez Domene Juan Jose",
    "wof:placetype":"venue"
},
  "geometry": {"coordinates":[-2.7789080143,37.4911766052],"type":"Point"}
}