{
  "type": "Feature",
  "properties": {
    "addr:full":"Bittiria Kalea, 45 Lesaka Navarra 31770",
    "addr:housenumber":"45",
    "addr:postcode":"31770",
    "addr:street":"Bittiria Kalea",
    "iso:country":"ES",
    "sg:address":"Bittiria Kalea, 45",
    "sg:city":"Lesaka",
    "sg:orig_category":"Contenedores (mercanc\u00cdas)",
    "sg:phone":"+34 948 63 72 46",
    "sg:postcode":"31770",
    "sg:province":"Navarra",
    "wof:name":"Michelena Irazoqui Luciano",
    "wof:placetype":"venue"
},
  "geometry": {"coordinates":[-1.7085609436,43.2470283508],"type":"Point"}
}