{
  "type": "Feature",
  "properties": {
    "iso:country":"ES",
    "sg:address":"Praz Maior, S/n",
    "sg:city":"Baralla",
    "sg:orig_category":"Chapister\u00cda",
    "sg:phone":"+34 982 36 33 78",
    "sg:postcode":"27680",
    "sg:province":"Lugo",
    "wof:name":"Aldegunde Rubinos Jose Antonio",
    "wof:placetype":"venue"
},
  "geometry": {"coordinates":[-7.2503986359,42.8936576843],"type":"Point"}
}