{
  "type": "Feature",
  "properties": {
    "iso:country":"ES",
    "sg:address":"Calle de Lanzarote, 9",
    "sg:city":"Fuengirola",
    "sg:orig_category":"Transportes Por V\u00cdas Navegables",
    "sg:phone":"+34 952 46 53 27",
    "sg:postcode":"29640",
    "sg:province":"M\u00e1laga",
    "wof:name":"Lopez Martin Alfonso",
    "wof:placetype":"venue"
},
  "geometry": {"coordinates":[-4.6330537796,36.5426368713],"type":"Point"}
}