{
  "type": "Feature",
  "properties": {
    "iso:country":"ES",
    "sg:address":"Calle de Lausana, 19",
    "sg:city":"Zaragoza",
    "sg:orig_category":"Inmobiliaria (agencias)",
    "sg:phone":"+34 976 38 34 35",
    "sg:postcode":"50007",
    "sg:province":"Zaragoza",
    "wof:name":"Lausana Viviendas S.l.",
    "wof:placetype":"venue"
},
  "geometry": {"coordinates":[-0.8810008764,41.636882782],"type":"Point"}
}