{
  "type": "Feature",
  "properties": {
    "addr:full":"Carrer de Calvet, 8 Barcelona Barcelona 08021",
    "addr:housenumber":"8",
    "addr:postcode":"08021",
    "addr:street":"Carrer De Calvet",
    "iso:country":"ES",
    "sg:address":"Carrer de Calvet, 8",
    "sg:city":"Barcelona",
    "sg:orig_category":"Asesor\u00cda Fiscal Y Jur\u00cddica",
    "sg:phone":"+34 934 14 21 65",
    "sg:postcode":"08021",
    "sg:province":"Barcelona",
    "wof:name":"Classic D'or S.l.",
    "wof:placetype":"venue"
},
  "geometry": {"coordinates":[2.14508605,41.3936653137],"type":"Point"}
}