{
  "type": "Feature",
  "properties": {
    "addr:full":"Carrer de Rocafort, 240 Barcelona Barcelona 08029",
    "addr:housenumber":"240",
    "addr:postcode":"08029",
    "addr:street":"Carrer De Rocafort",
    "iso:country":"ES",
    "sg:address":"Carrer de Rocafort, 240",
    "sg:city":"Barcelona",
    "sg:orig_category":"Telas (al Por Mayor)",
    "sg:phone":"+34 934 39 96 32",
    "sg:postcode":"08029",
    "sg:province":"Barcelona",
    "wof:name":"Abetex S.l.",
    "wof:placetype":"venue"
},
  "geometry": {"coordinates":[2.144762,41.385754],"type":"Point"}
}