{
  "type": "Feature",
  "properties": {
    "addr:full":"Calle de Braille, 9 Tarifa C\u00e1diz 11380",
    "addr:housenumber":"9",
    "addr:postcode":"11380",
    "addr:street":"Calle De Braille;Ca\u0301Diz",
    "iso:country":"ES",
    "sg:address":"Calle de Braille, 9",
    "sg:city":"Tarifa",
    "sg:orig_category":"Carnicer\u00cdas, Carnicer\u00cdas",
    "sg:phone":"+34 956 68 47 62",
    "sg:postcode":"11380",
    "sg:province":"C\u00e1diz",
    "wof:name":"Fernandez Sede\u00f1o Josefa",
    "wof:placetype":"venue"
},
  "geometry": {"coordinates":[-5.6073431969,36.0175666809],"type":"Point"}
}