{
  "type": "Feature",
  "properties": {
    "addr:full":"Carrer de Berenguer Iii, 86 Mollet Valles Barcelona 08100",
    "addr:housenumber":"86",
    "addr:postcode":"08100",
    "addr:street":"Carrer De Berenguer Iii",
    "iso:country":"ES",
    "sg:address":"Carrer de Berenguer Iii, 86",
    "sg:city":"Mollet Valles",
    "sg:orig_category":"Ropa De Trabajo Y Profesionales (fabricaci\u00d3n, Al Por Mayor)",
    "sg:phone":"+34 935 79 28 85",
    "sg:postcode":"08100",
    "sg:province":"Barcelona",
    "wof:name":"Uniforme Valles S.c.p",
    "wof:placetype":"venue"
},
  "geometry": {"coordinates":[2.2148330212,41.5365600586],"type":"Point"}
}