{
  "type": "Feature",
  "properties": {
    "iso:country":"ES",
    "sg:address":"Calle de Virgen De Los Dolores, 16",
    "sg:city":"Ronda",
    "sg:orig_category":"M\u00c9dicos: Pediatr\u00cda. Enfermedades De Los Ni\u00d1os",
    "sg:phone":"+34 952 87 83 29",
    "sg:postcode":"29400",
    "sg:province":"M\u00e1laga",
    "wof:name":"Gonzalez Serrano Maria Luisa",
    "wof:placetype":"venue"
},
  "geometry": {"coordinates":[-5.1622610092,36.7431793213],"type":"Point"}
}