{
  "type": "Feature",
  "properties": {
    "iso:country":"ES",
    "sg:address":"Ponent, 28",
    "sg:city":"Vilablareix",
    "sg:orig_category":"Fabricaci\u00d3n De Muebles",
    "sg:phone":"+34 972 24 19 34",
    "sg:postcode":"17180",
    "sg:province":"Girona",
    "wof:name":"Fusteria Perello Ebenisteria S.l.",
    "wof:placetype":"venue"
},
  "geometry": {"coordinates":[2.7941510677,41.9537582397],"type":"Point"}
}