{
  "type": "Feature",
  "properties": {
    "iso:country":"ES",
    "sg:address":"Calle de Txuputo, S/n",
    "sg:city":"Arizkun",
    "sg:orig_category":"Iglesia Cat\u00d3lica",
    "sg:phone":"+34 948 45 30 10",
    "sg:postcode":"31713",
    "sg:province":"Navarra",
    "wof:name":"Parroquia De San Juan Bautista",
    "wof:placetype":"venue"
},
  "geometry": {"coordinates":[-1.4713129997,43.1828041077],"type":"Point"}
}