{
  "type": "Feature",
  "properties": {
    "iso:country":"ES",
    "sg:address":"Plaz Houston De, 4",
    "sg:city":"Huelva",
    "sg:orig_category":"Cajas Para Embalar",
    "sg:phone":"+34 959 23 01 51",
    "sg:postcode":"21006",
    "sg:province":"Huelva",
    "wof:name":"Caja Rural Del Sur Sociedad Cooperativa",
    "wof:placetype":"venue"
},
  "geometry": {"coordinates":[-6.9390239716,37.2598304749],"type":"Point"}
}