{
  "type": "Feature",
  "properties": {
    "addr:full":"Carrer de Mare De Deu De Nuria, 21 Granollers Barcelona 08401",
    "addr:housenumber":"21",
    "addr:postcode":"08401",
    "addr:street":"Carrer De Mare De Deu De Nuria",
    "iso:country":"ES",
    "sg:address":"Carrer de Mare De Deu De Nuria, 21",
    "sg:city":"Granollers",
    "sg:orig_category":"Fabricaci\u00d3n, Reparaci\u00d3n Y Mantenimiento De Construcciones Navales Y Fluviales",
    "sg:phone":"+34 938 70 94 00",
    "sg:postcode":"08401",
    "sg:province":"Barcelona",
    "sg:website":"www.mapsal.com",
    "wof:name":"Maquinaria Naval Mapsa S.l.",
    "wof:placetype":"venue"
},
  "geometry": {"coordinates":[2.2838718891,41.6084785461],"type":"Point"}
}