{
  "type": "Feature",
  "properties": {
    "addr:full":"Calle de Montes, 40 Ronda M\u00e1laga 29400",
    "addr:housenumber":"40",
    "addr:postcode":"29400",
    "addr:street":"Calle De Montes;Ronda Ma\u0301Laga",
    "iso:country":"ES",
    "sg:address":"Calle de Montes, 40",
    "sg:city":"Ronda",
    "sg:orig_category":"Asociaciones Y Clubs Deportivos",
    "sg:phone":"+34 952 19 02 17",
    "sg:postcode":"29400",
    "sg:province":"M\u00e1laga",
    "wof:name":"Arundasport S.l.",
    "wof:placetype":"venue"
},
  "geometry": {"coordinates":[-5.16040802,36.7439422607],"type":"Point"}
}