{
  "type": "Feature",
  "properties": {
    "addr:full":"Carrer de Amalia Soler, 83 Vilafranca Penedes Barcelona 08720",
    "addr:housenumber":"83",
    "addr:postcode":"08720",
    "addr:street":"Carrer De Amalia Soler",
    "iso:country":"ES",
    "sg:address":"Carrer de Amalia Soler, 83",
    "sg:city":"Vilafranca Penedes",
    "sg:classifiers":[
        {
            "category":"Taxi",
            "type":"Transportation"
        }
    ],
    "sg:phone":"+34 938 90 21 62",
    "sg:postcode":"08720",
    "sg:province":"Barcelona",
    "wof:name":"Promocions Tivoli 83 Sl",
    "wof:placetype":"venue"
},
  "geometry": {"coordinates":[1.6985349655,41.3420410156],"type":"Point"}
}