{
  "type": "Feature",
  "properties": {
    "iso:country":"ES",
    "sg:address":"Rcial Novo Espartinas, 5",
    "sg:city":"Espartinas",
    "sg:orig_category":"Asesor\u00cda Fiscal Y Jur\u00cddica",
    "sg:phone":"+34 955 71 02 19",
    "sg:postcode":"41807",
    "sg:province":"Sevilla",
    "wof:name":"Ecron Consultores S.a.l.",
    "wof:placetype":"venue"
},
  "geometry": {"coordinates":[-6.1237850189,37.3773117065],"type":"Point"}
}