{
  "type": "Feature",
  "properties": {
    "iso:country":"ES",
    "sg:address":"Calle de Juan De Rihuerga, 16",
    "sg:city":"Malaga",
    "sg:orig_category":"Carnicer\u00cdas, Carnicer\u00cdas",
    "sg:phone":"+34 952 61 66 24",
    "sg:postcode":"29010",
    "sg:province":"M\u00e1laga",
    "wof:name":"Alimentacion Y Carnica Maria Del Rocio S.l.",
    "wof:placetype":"venue"
},
  "geometry": {"coordinates":[-4.4658923149,36.7262916565],"type":"Point"}
}