{
  "type": "Feature",
  "properties": {
    "addr:full":"Rua Nova De Abaixo, 10 Santiago De Compostela La Coru\u00f1a 15706",
    "addr:housenumber":"10",
    "addr:postcode":"15706",
    "addr:street":"Rua Nova De Abaixo;Corun\u0303A",
    "iso:country":"ES",
    "sg:address":"Rua Nova De Abaixo, 10",
    "sg:city":"Santiago De Compostela",
    "sg:orig_category":"Molduras, Junquillos, Listones Y Molduras Perforadas",
    "sg:phone":"+34 981 59 26 06",
    "sg:postcode":"15706",
    "sg:province":"La Coru\u00f1a",
    "wof:name":"Rodriguez Martinez Juan Manuel",
    "wof:placetype":"venue"
},
  "geometry": {"coordinates":[-8.5500621796,42.8752326965],"type":"Point"}
}