{
  "type": "Feature",
  "properties": {
    "iso:country":"ES",
    "sg:address":"Calle de Musico Peydro, 15",
    "sg:city":"Valencia",
    "sg:orig_category":"Art\u00cdculos De Madera (fabricaci\u00d3n Y Al Por Mayor)",
    "sg:phone":"+34 963 51 03 90",
    "sg:postcode":"46001",
    "sg:province":"Valencia",
    "wof:name":"Laborda Tarrega Marina",
    "wof:placetype":"venue"
},
  "geometry": {"coordinates":[-0.3782536983,39.4718589783],"type":"Point"}
}