{
  "type": "Feature",
  "properties": {
    "iso:country":"ES",
    "sg:address":"Plaz Angel, 5",
    "sg:city":"Madrid",
    "sg:orig_category":"Muebles, Minoristas",
    "sg:phone":"+34 915 21 41 88",
    "sg:postcode":"28012",
    "sg:province":"Madrid",
    "wof:name":"Bikarisma S.l.",
    "wof:placetype":"venue"
},
  "geometry": {"coordinates":[-3.7019870281,40.4144058228],"type":"Point"}
}