{
  "type": "Feature",
  "properties": {
    "iso:country":"ES",
    "sg:address":"Carrer de Sant Francesc Xavier, 70",
    "sg:city":"Barcelona",
    "sg:orig_category":"Postigos, Persianas Y Celos\u00cdas",
    "sg:phone":"+34 933 54 90 41",
    "sg:postcode":"08016",
    "sg:province":"Barcelona",
    "wof:name":"Clemente Cacho Santiago",
    "wof:placetype":"venue"
},
  "geometry": {"coordinates":[2.1798779964,41.4396591187],"type":"Point"}
}