{
  "type": "Feature",
  "properties": {
    "addr:full":"Calle de Zaragoza, 31 Sevilla Sevilla 41001",
    "addr:housenumber":"31",
    "addr:postcode":"41001",
    "addr:street":"Calle De Zaragoza",
    "iso:country":"ES",
    "sg:address":"Calle de Zaragoza, 31",
    "sg:city":"Sevilla",
    "sg:orig_category":"Abogados",
    "sg:phone":"+34 954 22 87 15",
    "sg:postcode":"41001",
    "sg:province":"Sevilla",
    "wof:name":"Rivas Gutierrez Antonio",
    "wof:placetype":"venue"
},
  "geometry": {"coordinates":[-5.9968919754,37.3883209229],"type":"Point"}
}