{
  "type": "Feature",
  "properties": {
    "iso:country":"ES",
    "sg:address":"Rua Eduardo Pondal, 82",
    "sg:city":"Pontevedra",
    "sg:orig_category":"Agencias Y Agentes Comerciales, Representantes",
    "sg:phone":"+34 986 85 64 49",
    "sg:postcode":"36003",
    "sg:province":"Pontevedra",
    "wof:name":"Fuentes Sierra Roberto",
    "wof:placetype":"venue"
},
  "geometry": {"coordinates":[-8.6341838837,42.418258667],"type":"Point"}
}