{
  "type": "Feature",
  "properties": {
    "addr:full":"Carrer de Onze De Setembre, 79 Viladecans Barcelona 08840",
    "addr:housenumber":"79",
    "addr:postcode":"08840",
    "addr:street":"Carrer De Onze De Setembre",
    "iso:country":"ES",
    "sg:address":"Carrer de Onze De Setembre, 79",
    "sg:city":"Viladecans",
    "sg:orig_category":"Charcuter\u00cdas (al Por Mayor)",
    "sg:phone":"+34 936 58 27 46",
    "sg:postcode":"08840",
    "sg:province":"Barcelona",
    "wof:name":"Hornos Sanchez Domingo",
    "wof:placetype":"venue"
},
  "geometry": {"coordinates":[2.0110590458,41.3194046021],"type":"Point"}
}