{
  "type": "Feature",
  "properties": {
    "addr:full":"Calle de Jupiter, 2 Valladolid Valladolid 47009",
    "addr:housenumber":"2",
    "addr:postcode":"47009",
    "addr:street":"Calle De Jupiter",
    "iso:country":"ES",
    "sg:address":"Calle de Jupiter, 2",
    "sg:city":"Valladolid",
    "sg:orig_category":"Puertas Y Portales",
    "sg:phone":"+34 983 34 49 41",
    "sg:postcode":"47009",
    "sg:province":"Valladolid",
    "wof:name":"Valverde Marcos Andres",
    "wof:placetype":"venue"
},
  "geometry": {"coordinates":[-4.7369370461,41.661075592],"type":"Point"}
}