{
  "type": "Feature",
  "properties": {
    "addr:full":"Pol Ind Infrexsa, 8 Fregenal Sierra Badajoz 06340",
    "addr:housenumber":"8",
    "addr:postcode":"06340",
    "addr:street":"Infrexsa;Sierra",
    "iso:country":"ES",
    "sg:address":"Pol Ind Infrexsa, 8",
    "sg:city":"Fregenal Sierra",
    "sg:orig_category":"Frutas Y Legumbres Secas (al Por Mayor)",
    "sg:phone":"+34 924 70 12 84",
    "sg:postcode":"06340",
    "sg:province":"Badajoz",
    "wof:name":"Jose Antonio Mayal S. L.",
    "wof:placetype":"venue"
},
  "geometry": {"coordinates":[-6.6505317688,38.1659088135],"type":"Point"}
}