{
  "type": "Feature",
  "properties": {
    "iso:country":"ES",
    "sg:address":"Calle de Doctor Fleming, 14",
    "sg:city":"Entrego",
    "sg:orig_category":"Molduras, Junquillos, Listones Y Molduras Perforadas",
    "sg:phone":"+34 985 66 21 24",
    "sg:postcode":"33940",
    "sg:province":"Asturias",
    "wof:name":"Canga Y Saco C.b.",
    "wof:placetype":"venue"
},
  "geometry": {"coordinates":[-5.6372947693,43.28748703],"type":"Point"}
}