{
  "type": "Feature",
  "properties": {
    "iso:country":"ES",
    "sg:address":"Avda Leon, 19",
    "sg:city":"Tordesillas",
    "sg:orig_category":"Transporte En General",
    "sg:phone":"+34 983 79 69 08",
    "sg:postcode":"47100",
    "sg:province":"Valladolid",
    "wof:name":"Grupo El Arbol Distribucion Y Supermercados S.a. Unipersonal",
    "wof:placetype":"venue"
},
  "geometry": {"coordinates":[-4.9998087883,41.503818512],"type":"Point"}
}