{
  "type": "Feature",
  "properties": {
    "addr:full":"Calle de Catalina De Erauso, 17 Donostia-san Sebastian Guip\u00f9zcoa 20010",
    "addr:housenumber":"17",
    "addr:postcode":"20010",
    "addr:street":"Calle De Catalina De Erauso",
    "iso:country":"ES",
    "sg:address":"Calle de Catalina De Erauso, 17",
    "sg:city":"Donostia-san Sebastian",
    "sg:orig_category":"Abogados",
    "sg:phone":"+34 943 47 02 48",
    "sg:postcode":"20010",
    "sg:province":"Guip\u00f9zcoa",
    "wof:name":"Jose Ramon Osua Gil (abogado)",
    "wof:placetype":"venue"
},
  "geometry": {"coordinates":[-1.9817492962,43.3046836853],"type":"Point"}
}