{
  "type": "Feature",
  "properties": {
    "iso:country":"ES",
    "sg:address":"Calle de Federico Garcia Lorca, 1",
    "sg:city":"Purullena",
    "sg:orig_category":"Materiales De Aislamiento T\u00c9rmico Y Ac\u00dastico",
    "sg:phone":"+34 958 69 06 29",
    "sg:postcode":"18519",
    "sg:province":"Granada",
    "wof:name":"Baena Porcel Ana Maria",
    "wof:placetype":"venue"
},
  "geometry": {"coordinates":[-3.1894490719,37.3155288696],"type":"Point"}
}