{
  "type": "Feature",
  "properties": {
    "addr:full":"Bittiria Kalea, 1 Lesaka Navarra 31770",
    "addr:housenumber":"1",
    "addr:postcode":"31770",
    "addr:street":"Bittiria Kalea",
    "iso:country":"ES",
    "sg:address":"Bittiria Kalea, 1",
    "sg:city":"Lesaka",
    "sg:orig_category":"Peluquer\u00cdas, Peluquer\u00cda Mixta",
    "sg:phone":"+34 948 63 80 04",
    "sg:postcode":"31770",
    "sg:province":"Navarra",
    "wof:name":"Gonzalez Etxepare Ainoa",
    "wof:placetype":"venue"
},
  "geometry": {"coordinates":[-1.7047510147,43.2466812134],"type":"Point"}
}