{
  "type": "Feature",
  "properties": {
    "iso:country":"ES",
    "sg:address":"Calle de Cristo, 28",
    "sg:city":"Talarrubias",
    "sg:orig_category":"Enfermeras: Consultas, Atenci\u00d3n A Domicilio",
    "sg:phone":"+34 924 63 02 32",
    "sg:postcode":"06640",
    "sg:province":"Badajoz",
    "wof:name":"Mu\u00f1iz Sanchez Francisco",
    "wof:placetype":"venue"
},
  "geometry": {"coordinates":[-5.2336235046,39.0398674011],"type":"Point"}
}