{
  "type": "Feature",
  "properties": {
    "iso:country":"ES",
    "sg:address":"Avda Ernestina Otero, 2",
    "sg:city":"Redondela",
    "sg:orig_category":"Bricolaje, Herramientas (al Por Menor)",
    "sg:phone":"+34 986 40 16 29",
    "sg:postcode":"36800",
    "sg:province":"Pontevedra",
    "wof:name":"Toucedo Mu\u00f1oz C.b.",
    "wof:placetype":"venue"
},
  "geometry": {"coordinates":[-8.6097993851,42.2822418213],"type":"Point"}
}