{
  "type": "Feature",
  "properties": {
    "addr:full":"Calle de Felipe Ii, 9 Valladolid Valladolid 47003",
    "addr:housenumber":"9",
    "addr:postcode":"47003",
    "addr:street":"Calle De Felipe Ii",
    "iso:country":"ES",
    "sg:address":"Calle de Felipe Ii, 9",
    "sg:city":"Valladolid",
    "sg:orig_category":"M\u00c9dicos: Medicina Nuclear",
    "sg:phone":"+34 983 37 94 36",
    "sg:postcode":"47003",
    "sg:province":"Valladolid",
    "sg:website":"www.petcal.com",
    "wof:name":"Petcal S.l",
    "wof:placetype":"venue"
},
  "geometry": {"coordinates":[-4.7256269455,41.6552619934],"type":"Point"}
}