{
  "type": "Feature",
  "properties": {
    "iso:country":"ES",
    "sg:address":"Calle de Rulda, 25",
    "sg:city":"Villena",
    "sg:orig_category":"Confecci\u00d3n De Zapatos",
    "sg:phone":"+34 965 34 31 67",
    "sg:postcode":"03400",
    "sg:province":"Alicante",
    "wof:name":"Calzachic S.l.",
    "wof:placetype":"venue"
},
  "geometry": {"coordinates":[-0.868753016,38.6403503418],"type":"Point"}
}