{
  "type": "Feature",
  "properties": {
    "iso:country":"ES",
    "sg:address":"Calle de Ramon Y Cajal, 4",
    "sg:city":"Navalmoral Mata",
    "sg:orig_category":"Agencias Y Agentes Comerciales, Representantes",
    "sg:phone":"+34 927 53 55 46",
    "sg:postcode":"10300",
    "sg:province":"C\u00e1ceres",
    "wof:name":"Ortiz Marcos Cesar",
    "wof:placetype":"venue"
},
  "geometry": {"coordinates":[-5.5404038429,39.8923416138],"type":"Point"}
}