{
  "type": "Feature",
  "properties": {
    "addr:full":"Calle de Agarre, 9 Zaldibar Vizcaya 48250",
    "addr:housenumber":"9",
    "addr:postcode":"48250",
    "addr:street":"Calle De Agarre",
    "iso:country":"ES",
    "sg:address":"Calle de Agarre, 9",
    "sg:city":"Zaldibar",
    "sg:orig_category":"Empresas De Carpinter\u00cda",
    "sg:phone":"+34 946 82 73 52",
    "sg:postcode":"48250",
    "sg:province":"Vizcaya",
    "wof:name":"Carpinteria San Andres",
    "wof:placetype":"venue"
},
  "geometry": {"coordinates":[-2.5446956158,43.1763381958],"type":"Point"}
}