{
  "type": "Feature",
  "properties": {
    "addr:full":"Carrer de Josep Tous Ferrer, 12 Palma Islas Baleares 07002",
    "addr:housenumber":"12",
    "addr:postcode":"07002",
    "addr:street":"Carrer De Josep Tous Ferrer",
    "iso:country":"ES",
    "sg:address":"Carrer de Josep Tous Ferrer, 12",
    "sg:city":"Palma",
    "sg:orig_category":"Zapatos (al Por Menor)",
    "sg:phone":"+34 971 72 24 08",
    "sg:postcode":"07002",
    "sg:province":"Islas Baleares",
    "wof:name":"Llompart Alemany Miguel",
    "wof:placetype":"venue"
},
  "geometry": {"coordinates":[2.6539509296,39.5734786987],"type":"Point"}
}