{
  "type": "Feature",
  "properties": {
    "iso:country":"ES",
    "sg:address":"Carrer de Casp, 89",
    "sg:city":"Barcelona",
    "sg:orig_category":"Abogados",
    "sg:phone":"+34 932 32 49 08",
    "sg:postcode":"08013",
    "sg:province":"Barcelona",
    "wof:name":"Savall Olivella Juan Carlos",
    "wof:placetype":"venue"
},
  "geometry": {"coordinates":[2.1785459518,41.3954467773],"type":"Point"}
}