{
  "type": "Feature",
  "properties": {
    "addr:full":"Avda Ricardo Soriano, 36 Marbella M\u00e1laga 29600",
    "addr:housenumber":"36",
    "addr:postcode":"29600",
    "addr:street":"Avda Ricardo Soriano;Ma\u0301Laga",
    "iso:country":"ES",
    "sg:address":"Avda Ricardo Soriano, 36",
    "sg:city":"Marbella",
    "sg:orig_category":"M\u00c9dicos: Radioterapia (radioterapia Como Opci\u00d3n Oncol\u00d3gica)",
    "sg:phone":"+34 952 77 43 50",
    "sg:postcode":"29600",
    "sg:province":"M\u00e1laga",
    "wof:name":"S. Torres Gonzalez Y Otros C.b.",
    "wof:placetype":"venue"
},
  "geometry": {"coordinates":[-4.8912148476,36.5105857849],"type":"Point"}
}