{
  "type": "Feature",
  "properties": {
    "addr:full":"Calle de Virgen Del Amparo, 49 Guadalajara Guadalajara 19001",
    "addr:housenumber":"49",
    "addr:postcode":"19001",
    "addr:street":"Calle De Virgen Del Amparo",
    "iso:country":"ES",
    "sg:address":"Calle de Virgen Del Amparo, 49",
    "sg:city":"Guadalajara",
    "sg:orig_category":"Armas Y Municiones (fabricaci\u00d3n, Al Por Mayor)",
    "sg:phone":"+34 949 25 32 78",
    "sg:postcode":"19001",
    "sg:province":"Guadalajara",
    "wof:name":"Domingo Garcia Viejo Y Otro Cdad.",
    "wof:placetype":"venue"
},
  "geometry": {"coordinates":[-3.162651062,40.6277313232],"type":"Point"}
}