{
  "type": "Feature",
  "properties": {
    "addr:full":"Pase Santa Maria De La Cabeza, 173 Madrid Madrid 28026",
    "addr:housenumber":"173",
    "addr:postcode":"28026",
    "addr:street":"Cabeza",
    "iso:country":"ES",
    "sg:address":"Pase Santa Maria De La Cabeza, 173",
    "sg:city":"Madrid",
    "sg:orig_category":"Empresas De Pintura Y Revestimientos",
    "sg:phone":"+34 915 65 24 67",
    "sg:postcode":"28026",
    "sg:province":"Madrid",
    "wof:name":"Gallego Pradillo Julio",
    "wof:placetype":"venue"
},
  "geometry": {"coordinates":[-3.7150878906,40.3868904114],"type":"Point"}
}