{
  "type": "Feature",
  "properties": {
    "addr:full":"Calle de La Maso, 25 Madrid Madrid 28034",
    "addr:housenumber":"25",
    "addr:postcode":"madrid;28034",
    "addr:street":"Calle De La Maso",
    "iso:country":"ES",
    "sg:address":"Calle de La Maso, 25",
    "sg:city":"Madrid",
    "sg:orig_category":"Cl\u00cdnicas Dentales",
    "sg:phone":"+34 913 72 19 45",
    "sg:postcode":"28034",
    "sg:province":"Madrid",
    "wof:name":"Centro De Especialidades Odontologicas De Madrid S.l.",
    "wof:placetype":"venue"
},
  "geometry": {"coordinates":[-3.7115020752,40.4928779602],"type":"Point"}
}