{
  "type": "Feature",
  "properties": {
    "addr:full":"Calle de El Rompedizo, 1 Madrid Madrid 28044",
    "addr:housenumber":"1",
    "addr:postcode":"28044",
    "addr:street":"Calle De El Rompedizo",
    "iso:country":"ES",
    "sg:address":"Calle de El Rompedizo, 1",
    "sg:city":"Madrid",
    "sg:orig_category":"Guarder\u00cdas",
    "sg:phone":"+34 917 05 00 37",
    "sg:postcode":"28044",
    "sg:province":"Madrid",
    "wof:name":"Perea Laguna Maria Del Sol",
    "wof:placetype":"venue"
},
  "geometry": {"coordinates":[-3.7652792931,40.3759613037],"type":"Point"}
}