{
  "type": "Feature",
  "properties": {
    "addr:full":"Carr Juli Garreta, 3 Platja D'aro Girona 17250",
    "addr:housenumber":"3",
    "addr:postcode":"17250",
    "addr:street":"Carr Juli Garreta",
    "iso:country":"ES",
    "sg:address":"Carr Juli Garreta, 3",
    "sg:city":"Platja D'aro",
    "sg:orig_category":"Servicios De Telecomunicaciones",
    "sg:phone":"+34 972 81 72 07",
    "sg:postcode":"17250",
    "sg:province":"Girona",
    "wof:name":"Xtra Telecom S.a.",
    "wof:placetype":"venue"
},
  "geometry": {"coordinates":[3.0626885891,41.815700531],"type":"Point"}
}