{
  "type": "Feature",
  "properties": {
    "iso:country":"ES",
    "sg:address":"Plaz Topete, S/n",
    "sg:city":"Cadiz",
    "sg:orig_category":"Sindicatos De Trabajadores",
    "sg:phone":"+34 956 22 11 11",
    "sg:postcode":"11001",
    "sg:province":"C\u00e1diz",
    "wof:name":"Federacion De Servicios Publicos De Ugt",
    "wof:placetype":"venue"
},
  "geometry": {"coordinates":[-6.2971692085,36.5311355591],"type":"Point"}
}