{
  "type": "Feature",
  "properties": {
    "iso:country":"ES",
    "sg:address":"Carrer de Vene\u00c7uela, 87",
    "sg:city":"Barcelona",
    "sg:orig_category":"Artes Gr\u00c1ficas, Artes Pl\u00c1sticas (curso)",
    "sg:phone":"+34 933 03 46 30",
    "sg:postcode":"08019",
    "sg:province":"Barcelona",
    "wof:name":"Talleres Graficos Hostench S. A.",
    "wof:placetype":"venue"
},
  "geometry": {"coordinates":[2.2091341019,41.4116020203],"type":"Point"}
}