{
  "type": "Feature",
  "properties": {
    "addr:full":"Calle de Mayor, 27 Azuqueca Henares Guadalajara 19200",
    "addr:housenumber":"27",
    "addr:postcode":"19200",
    "addr:street":"Calle De Mayor",
    "iso:country":"ES",
    "sg:address":"Calle de Mayor, 27",
    "sg:city":"Azuqueca Henares",
    "sg:orig_category":"Promotores Constructores",
    "sg:phone":"+34 949 26 74 83",
    "sg:postcode":"19200",
    "sg:province":"Guadalajara",
    "sg:website":"www.t.jconstrucciones.com",
    "wof:name":"T.j.construcciones S.l.",
    "wof:placetype":"venue"
},
  "geometry": {"coordinates":[-3.2649490833,40.5674705505],"type":"Point"}
}