{
  "type": "Feature",
  "properties": {
    "addr:full":"Carrer de Sant Pere Martir, 12 Olot Girona 17800",
    "addr:housenumber":"12",
    "addr:postcode":"17800",
    "addr:street":"Carrer De Sant;Martir",
    "iso:country":"ES",
    "sg:address":"Carrer de Sant Pere Martir, 12",
    "sg:city":"Olot",
    "sg:orig_category":"Reposter\u00cdas",
    "sg:phone":"+34 972 26 55 64",
    "sg:postcode":"17800",
    "sg:province":"Girona",
    "wof:name":"Fleca Can Dorca C.b.",
    "wof:placetype":"venue"
},
  "geometry": {"coordinates":[2.4855918884,42.1821098328],"type":"Point"}
}