{
  "type": "Feature",
  "properties": {
    "addr:full":"Plaz Iglesia, 2 Chauchina Granada 18330",
    "addr:housenumber":"2",
    "addr:postcode":"18330",
    "addr:street":"Iglesia",
    "iso:country":"ES",
    "sg:address":"Plaz Iglesia, 2",
    "sg:city":"Chauchina",
    "sg:orig_category":"Comercio, Reparaci\u00d3n De Motocicletas, Bicicletas Y Piezas Sueltas",
    "sg:phone":"+34 958 44 60 23",
    "sg:postcode":"18330",
    "sg:province":"Granada",
    "wof:name":"Ortega Moreno Federico",
    "wof:placetype":"venue"
},
  "geometry": {"coordinates":[-3.7706999779,37.2019462585],"type":"Point"}
}