{
  "type": "Feature",
  "properties": {
    "iso:country":"ES",
    "sg:address":"Carrer de Nou De Porta, 18",
    "sg:city":"Barcelona",
    "sg:orig_category":"Caf\u00c9s, Bares, Cervecer\u00cdas",
    "sg:phone":"+34 933 51 11 14",
    "sg:postcode":"08016",
    "sg:province":"Barcelona",
    "wof:name":"Esber Ruber S.l.",
    "wof:placetype":"venue"
},
  "geometry": {"coordinates":[2.1751990318,41.4322013855],"type":"Point"}
}