{
  "type": "Feature",
  "properties": {
    "addr:full":"Calle de Amaya, 3 Cadiz C\u00e1diz 11005",
    "addr:housenumber":"3",
    "addr:postcode":"11005",
    "addr:street":"Calle De Amaya",
    "iso:country":"ES",
    "sg:address":"Calle de Amaya, 3",
    "sg:city":"Cadiz",
    "sg:classifiers":[
        {
            "category":"Personal",
            "subcategory":"Barber",
            "type":"Services"
        }
    ],
    "sg:phone":"+34 956 28 11 99",
    "sg:postcode":"11005",
    "sg:province":"C\u00e1diz",
    "sg:tags":[
        "caballeros",
        "de",
        "peluqueros"
    ],
    "wof:name":"Garcia Arteaga Maria Auxiliadora",
    "wof:placetype":"venue"
},
  "geometry": {"coordinates":[-6.2919173241,36.5293235779],"type":"Point"}
}