{
  "type": "Feature",
  "properties": {
    "addr:full":"Avda Berganti\u00d1os, 36 Carballo La Coru\u00f1a 15100",
    "addr:housenumber":"36",
    "addr:postcode":"15100",
    "addr:street":"Avda Bergantin\u0303Os;La Corun\u0303A",
    "iso:country":"ES",
    "sg:address":"Avda Berganti\u00d1os, 36",
    "sg:city":"Carballo",
    "sg:orig_category":"Cerrajer\u00cda, Ferrallista",
    "sg:phone":"+34 981 70 39 96",
    "sg:postcode":"15100",
    "sg:province":"La Coru\u00f1a",
    "wof:name":"Manuel Y Perfecto Ba\u00d1a Espasandin S.c",
    "wof:placetype":"venue"
},
  "geometry": {"coordinates":[-8.684469223,43.2198867798],"type":"Point"}
}