{
  "type": "Feature",
  "properties": {
    "iso:country":"ES",
    "sg:address":"Carr Mallorca, 7",
    "sg:city":"Andratx",
    "sg:orig_category":"Estancos",
    "sg:phone":"+34 971 13 63 63",
    "sg:postcode":"07150",
    "sg:province":"Islas Baleares",
    "wof:name":"Alemany Massot Catalina",
    "wof:placetype":"venue"
},
  "geometry": {"coordinates":[2.4193880558,39.5750465393],"type":"Point"}
}