{
  "type": "Feature",
  "properties": {
    "addr:full":"Urb Charcones (los), 17 Sotillo Adrada \u00c1vila 05420",
    "addr:postcode":"05420",
    "addr:street":"Urb;Los;Sotillo;A\u0301Vila",
    "iso:country":"ES",
    "sg:address":"Urb Charcones (los), 17",
    "sg:city":"Sotillo Adrada",
    "sg:orig_category":"Electricidad: Instaladores",
    "sg:phone":"+34 918 66 07 48",
    "sg:postcode":"05420",
    "sg:province":"\u00c1vila",
    "wof:name":"Romo Sanchez Felix",
    "wof:placetype":"venue"
},
  "geometry": {"coordinates":[-4.5896468163,40.2908287048],"type":"Point"}
}