{
  "type": "Feature",
  "properties": {
    "addr:full":"Calle de Victoria, 9 Torredonjimeno Ja\u00e9n 23650",
    "addr:housenumber":"9",
    "addr:postcode":"23650",
    "addr:street":"Calle De Victoria",
    "iso:country":"ES",
    "sg:address":"Calle de Victoria, 9",
    "sg:city":"Torredonjimeno",
    "sg:classifiers":[
        {
            "category":"Manufacturing",
            "subcategory":"Building Materials",
            "type":"Manufacturing & Wholesale Goods"
        }
    ],
    "sg:phone":"+34 953 57 18 59",
    "sg:postcode":"23650",
    "sg:province":"Ja\u00e9n",
    "sg:tags":[
        "cemento",
        "y",
        "de",
        "fabricaci\u00d3n",
        "cal"
    ],
    "wof:name":"Lara Martos Francisco",
    "wof:placetype":"venue"
},
  "geometry": {"coordinates":[-3.9592781067,37.7684669495],"type":"Point"}
}