{
  "type": "Feature",
  "properties": {
    "addr:full":"Carr Carretera De Lliria, 74 Burjassot Valencia 46100",
    "addr:housenumber":"74",
    "addr:postcode":"46100",
    "addr:street":"Carr Carretera De Lliria",
    "iso:country":"ES",
    "sg:address":"Carr Carretera De Lliria, 74",
    "sg:city":"Burjassot",
    "sg:orig_category":"Molduras, Junquillos, Listones Y Molduras Perforadas",
    "sg:phone":"+34 963 64 06 07",
    "sg:postcode":"46100",
    "sg:province":"Valencia",
    "wof:name":"Broton Escribano Mariano",
    "wof:placetype":"venue"
},
  "geometry": {"coordinates":[-0.4105490148,39.5093688965],"type":"Point"}
}