{
  "type": "Feature",
  "properties": {
    "addr:full":"Calle de Australia, 7 Residencial Ontigola Toledo 45340",
    "addr:housenumber":"7",
    "addr:postcode":"45340",
    "addr:street":"Calle De Australia",
    "iso:country":"ES",
    "sg:address":"Calle de Australia, 7",
    "sg:city":"Residencial Ontigola",
    "sg:orig_category":"Cerrajer\u00cda, Ferrallista",
    "sg:phone":"+34 925 12 70 79",
    "sg:postcode":"45340",
    "sg:province":"Toledo",
    "wof:name":"Garcia-osorio Laguna Fabian",
    "wof:placetype":"venue"
},
  "geometry": {"coordinates":[-3.572239399,40.0034637451],"type":"Point"}
}