{
  "type": "Feature",
  "properties": {
    "addr:full":"G.v. Fernando El Catolico, 23 Valencia Valencia 46008",
    "addr:housenumber":"23",
    "addr:postcode":"46008",
    "addr:street":"Fernando El Catolico",
    "iso:country":"ES",
    "sg:address":"G.v. Fernando El Catolico, 23",
    "sg:city":"Valencia",
    "sg:orig_category":"Promotores Constructores",
    "sg:phone":"+34 963 82 03 27",
    "sg:postcode":"46008",
    "sg:province":"Valencia",
    "wof:name":"Ana Eva Juan S.l.",
    "wof:placetype":"venue"
},
  "geometry": {"coordinates":[-0.3859407008,39.4712753296],"type":"Point"}
}