{
  "type": "Feature",
  "properties": {
    "iso:country":"ES",
    "sg:address":"Av Pau (de La), 31",
    "sg:city":"Mollerussa",
    "sg:orig_category":"Laboratorios Y Cl\u00cdnicas Veterinarias",
    "sg:phone":"+34 973 71 19 44",
    "sg:postcode":"25230",
    "sg:province":"Lleida",
    "wof:name":"Centre Veterinari Del Pla S.l.u",
    "wof:placetype":"venue"
},
  "geometry": {"coordinates":[0.899510026,41.6280517578],"type":"Point"}
}