{
  "type": "Feature",
  "properties": {
    "iso:country":"ES",
    "sg:address":"Pg Tarongers, 40",
    "sg:city":"Castelldefels",
    "sg:orig_category":"Asilos De Ancianos. Centros Privados",
    "sg:phone":"+34 936 36 43 93",
    "sg:postcode":"08860",
    "sg:province":"Barcelona",
    "wof:name":"Villalba Perez Enedina",
    "wof:placetype":"venue"
},
  "geometry": {"coordinates":[1.9494179487,41.2672691345],"type":"Point"}
}