{
  "type": "Feature",
  "properties": {
    "addr:full":"Calle de Angeles De Las Heras, 16 Madrid Madrid 28035",
    "addr:housenumber":"16",
    "addr:postcode":"madrid;28035",
    "addr:street":"Calle De Angeles De Las Heras",
    "iso:country":"ES",
    "sg:address":"Calle de Angeles De Las Heras, 16",
    "sg:city":"Madrid",
    "sg:orig_category":"Inversiones",
    "sg:phone":"+34 913 76 85 99",
    "sg:postcode":"28035",
    "sg:province":"Madrid",
    "wof:name":"Norbal Inversiones Sl",
    "wof:placetype":"venue"
},
  "geometry": {"coordinates":[-3.7305428982,40.4814376831],"type":"Point"}
}