{
  "type": "Feature",
  "properties": {
    "addr:full":"Calle de Italia, 2 Haro La Rioja 26200",
    "addr:housenumber":"2",
    "addr:postcode":"26200",
    "addr:street":"Calle De Italia",
    "iso:country":"ES",
    "sg:address":"Calle de Italia, 2",
    "sg:city":"Haro",
    "sg:orig_category":"Arquitectos",
    "sg:phone":"+34 941 30 44 16",
    "sg:postcode":"26200",
    "sg:province":"La Rioja",
    "wof:name":"Piqueras Fisk Gustavo",
    "wof:placetype":"venue"
},
  "geometry": {"coordinates":[-2.8514890671,42.5754776001],"type":"Point"}
}