{
  "type": "Feature",
  "properties": {
    "iso:country":"ES",
    "sg:address":"Pase Martires, 39",
    "sg:city":"Socuellamos",
    "sg:orig_category":"Ropa Para Se\u00d1oras (al Por Menor)",
    "sg:phone":"+34 926 53 10 63",
    "sg:postcode":"13630",
    "sg:province":"Ciudad Real",
    "wof:name":"Alvarez Delgado Maria Del Carmen",
    "wof:placetype":"venue"
},
  "geometry": {"coordinates":[-2.7956140041,39.2889099121],"type":"Point"}
}