{
  "type": "Feature",
  "properties": {
    "iso:country":"ES",
    "sg:address":"Calle de Santos Martires, 14",
    "sg:city":"Talavera Reina",
    "sg:orig_category":"Promotores Constructores",
    "sg:phone":"+34 925 80 14 88",
    "sg:postcode":"45600",
    "sg:province":"Toledo",
    "wof:name":"Pinilla Montealegre Ignacio",
    "wof:placetype":"venue"
},
  "geometry": {"coordinates":[-4.8314080238,39.9640541077],"type":"Point"}
}