{
  "type": "Feature",
  "properties": {
    "addr:full":"Calle de Numancia, 10 Madrid Madrid 28039",
    "addr:housenumber":"10",
    "addr:postcode":"madrid;28039",
    "addr:street":"Calle De Numancia",
    "iso:country":"ES",
    "sg:address":"Calle de Numancia, 10",
    "sg:city":"Madrid",
    "sg:orig_category":"Farmacias",
    "sg:phone":"+34 914 59 32 53",
    "sg:postcode":"28039",
    "sg:province":"Madrid",
    "wof:name":"Liebana Lopez Casilda",
    "wof:placetype":"venue"
},
  "geometry": {"coordinates":[-3.7115819454,40.455078125],"type":"Point"}
}