{
  "type": "Feature",
  "properties": {
    "iso:country":"ES",
    "sg:address":"Calle de Alemania, 19",
    "sg:city":"Torre-pacheco",
    "sg:orig_category":"Agencias Y Agentes Comerciales, Representantes",
    "sg:phone":"+34 968 57 91 22",
    "sg:postcode":"30700",
    "sg:province":"Murcia",
    "wof:name":"Albadalejo Ros Julia",
    "wof:placetype":"venue"
},
  "geometry": {"coordinates":[-0.9379829764,37.7375030518],"type":"Point"}
}