{
  "type": "Feature",
  "properties": {
    "iso:country":"ES",
    "sg:address":"Calle de Pano Y Ruata, 13",
    "sg:city":"Zaragoza",
    "sg:orig_category":"Frutas, Legumbres Frescas Y Tempranas (al Por Menor)",
    "sg:phone":"+34 976 73 42 45",
    "sg:postcode":"50015",
    "sg:province":"Zaragoza",
    "wof:name":"Rivera Ruesca Isabel",
    "wof:placetype":"venue"
},
  "geometry": {"coordinates":[-0.8745440245,41.6612930298],"type":"Point"}
}