{
  "type": "Feature",
  "properties": {
    "addr:full":"Calle de Euskalduna, 9 Bilbao Vizcaya 48008",
    "addr:housenumber":"9",
    "addr:postcode":"48008",
    "addr:street":"Calle De Euskalduna",
    "iso:country":"ES",
    "sg:address":"Calle de Euskalduna, 9",
    "sg:city":"Bilbao",
    "sg:orig_category":"M\u00c9dicos: Estomatolog\u00cda",
    "sg:phone":"+34 944 44 50 72",
    "sg:postcode":"48008",
    "sg:province":"Vizcaya",
    "wof:name":"Borges Marcos Antonio",
    "wof:placetype":"venue"
},
  "geometry": {"coordinates":[-2.9323260784,43.259601593],"type":"Point"}
}