{
  "type": "Feature",
  "properties": {
    "iso:country":"ES",
    "sg:address":"Calle de Calamina, 13",
    "sg:city":"Madrid",
    "sg:orig_category":"Mec\u00c1nico Del Autom\u00d3vil",
    "sg:phone":"+34 917 95 47 28",
    "sg:postcode":"28021",
    "sg:province":"Madrid",
    "wof:name":"Fernandez Lacorte Manuel",
    "wof:placetype":"venue"
},
  "geometry": {"coordinates":[-3.7122387886,40.3464584351],"type":"Point"}
}