{
  "type": "Feature",
  "properties": {
    "addr:full":"Calle de Elizasu, 4 Donostia-san Sebastian Guip\u00f9zcoa 20017",
    "addr:housenumber":"4",
    "addr:postcode":"20017",
    "addr:street":"Calle De Elizasu",
    "iso:country":"ES",
    "sg:address":"Calle de Elizasu, 4",
    "sg:city":"Donostia-san Sebastian",
    "sg:orig_category":"Metalurgia",
    "sg:phone":"+34 943 35 17 80",
    "sg:postcode":"20017",
    "sg:province":"Guip\u00f9zcoa",
    "wof:name":"Alba\u00f1ileria J.pe\u00f1a S.l.",
    "wof:placetype":"venue"
},
  "geometry": {"coordinates":[-1.9329047203,43.3155212402],"type":"Point"}
}