{
  "type": "Feature",
  "properties": {
    "addr:full":"Calle de Justo Rodriguez, 3 Nore\u00f1a Asturias 33180",
    "addr:housenumber":"3",
    "addr:postcode":"33180",
    "addr:street":"Calle De Justo Rodriguez;Asturias",
    "iso:country":"ES",
    "sg:address":"Calle de Justo Rodriguez, 3",
    "sg:city":"Nore\u00f1a",
    "sg:orig_category":"Ense\u00d1anza: Profesiones Art\u00cdsticas",
    "sg:phone":"+34 985 74 18 17",
    "sg:postcode":"33180",
    "sg:province":"Asturias",
    "wof:name":"Ardura Suarez Javier",
    "wof:placetype":"venue"
},
  "geometry": {"coordinates":[-5.7056069374,43.3920440674],"type":"Point"}
}