{
  "type": "Feature",
  "properties": {
    "iso:country":"ES",
    "sg:address":"Calle de Dominicos, 57",
    "sg:city":"Toro",
    "sg:orig_category":"Moda",
    "sg:phone":"+34 980 69 27 24",
    "sg:postcode":"49800",
    "sg:province":"Zamora",
    "wof:name":"El Ajuar Del Bebe De C.a.sl.",
    "wof:placetype":"venue"
},
  "geometry": {"coordinates":[-5.3962640762,41.5252609253],"type":"Point"}
}