{
  "type": "Feature",
  "properties": {
    "iso:country":"ES",
    "sg:address":"Avda Francisco Sobrin, 22",
    "sg:city":"Camponaraya",
    "sg:orig_category":"Quincaller\u00cda (al Por Menor)",
    "sg:phone":"+34 987 45 00 05",
    "sg:postcode":"24410",
    "sg:province":"Le\u00f3n",
    "wof:name":"Garcia Lopez Jose Maria",
    "wof:placetype":"venue"
},
  "geometry": {"coordinates":[-6.6667189598,42.5784492493],"type":"Point"}
}