{
  "type": "Feature",
  "properties": {
    "addr:full":"Calle de Saavedra, 67 Gijon Asturias 33208",
    "addr:housenumber":"67",
    "addr:postcode":"33208",
    "addr:street":"Calle De Saavedra",
    "iso:country":"ES",
    "sg:address":"Calle de Saavedra, 67",
    "sg:city":"Gijon",
    "sg:orig_category":"Empresas De Carpinter\u00cda De Madera",
    "sg:phone":"+34 985 14 10 24",
    "sg:postcode":"33208",
    "sg:province":"Asturias",
    "wof:name":"Garcia Alvarez Manuel Benito",
    "wof:placetype":"venue"
},
  "geometry": {"coordinates":[-5.6645469666,43.5316925049],"type":"Point"}
}