{
  "type": "Feature",
  "properties": {
    "iso:country":"ES",
    "sg:address":"Calle de Doctor Fleming, 15",
    "sg:city":"Zaragoza",
    "sg:orig_category":"Centros De Educaci\u00d3n Especial",
    "sg:phone":"+34 976 40 45 99",
    "sg:postcode":"50004",
    "sg:province":"Zaragoza",
    "wof:name":"Centro De Educacion Infantil El Carmen",
    "wof:placetype":"venue"
},
  "geometry": {"coordinates":[-0.8894246817,41.6518478394],"type":"Point"}
}