{
  "type": "Feature",
  "properties": {
    "addr:full":"Pg En Blai Osanz, 1 Calig Castell\u00f3n 12589",
    "addr:housenumber":"1",
    "addr:postcode":"12589",
    "addr:street":"Pg;Osanz;Castello\u0301N",
    "iso:country":"ES",
    "sg:address":"Pg En Blai Osanz, 1",
    "sg:city":"Calig",
    "sg:orig_category":"Electrodom\u00c9sticos (al Por Menor)",
    "sg:phone":"+34 964 49 20 87",
    "sg:postcode":"12589",
    "sg:province":"Castell\u00f3n",
    "wof:name":"Alberich Calduch Jose Manuel",
    "wof:placetype":"venue"
},
  "geometry": {"coordinates":[0.3465971053,40.4816627502],"type":"Point"}
}