{
  "type": "Feature",
  "properties": {
    "addr:full":"Cmno Paredes, 24 Paredes Asturias 33420",
    "addr:housenumber":"24",
    "addr:postcode":"33420",
    "addr:street":"Cmno Paredes",
    "iso:country":"ES",
    "sg:address":"Cmno Paredes, 24",
    "sg:city":"Paredes",
    "sg:orig_category":"Asociaciones, Organismos Culturales Y Socioeducativos",
    "sg:phone":"+34 985 26 41 79",
    "sg:postcode":"33420",
    "sg:province":"Asturias",
    "wof:name":"Asociacion Cultural Salvadme Reina De Fatima",
    "wof:placetype":"venue"
},
  "geometry": {"coordinates":[-5.9832577705,43.2504386902],"type":"Point"}
}