{
  "type": "Feature",
  "properties": {
    "addr:full":"Avda Alfonso El Sabio, 3 Alacant Alicante 03002",
    "addr:housenumber":"3",
    "addr:postcode":"03002",
    "addr:street":"Avda Alfonso El Sabio",
    "iso:country":"ES",
    "sg:address":"Avda Alfonso El Sabio, 3",
    "sg:city":"Alacant",
    "sg:orig_category":"Reposter\u00cdas",
    "sg:phone":"+34 965 21 08 79",
    "sg:postcode":"03002",
    "sg:province":"Alicante",
    "wof:name":"Jimenez Toledo Manuel",
    "wof:placetype":"venue"
},
  "geometry": {"coordinates":[-0.4850589931,38.3479232788],"type":"Point"}
}