{
  "type": "Feature",
  "properties": {
    "addr:full":"Calle de Rector Lucena, 11 Salamanca Salamanca 37002",
    "addr:housenumber":"11",
    "addr:postcode":"37002",
    "addr:street":"Calle De Rector Lucena",
    "iso:country":"ES",
    "sg:address":"Calle de Rector Lucena, 11",
    "sg:city":"Salamanca",
    "sg:orig_category":"Asesor\u00cda Fiscal Y Jur\u00cddica",
    "sg:phone":"+34 923 21 02 75",
    "sg:postcode":"37002",
    "sg:province":"Salamanca",
    "wof:name":"Carlos Velasco Dominguez Sl",
    "wof:placetype":"venue"
},
  "geometry": {"coordinates":[-5.6632990837,40.9672164917],"type":"Point"}
}