{
  "type": "Feature",
  "properties": {
    "iso:country":"ES",
    "sg:address":"Altzibar Nuc., S/n",
    "sg:city":"Oiartzun",
    "sg:orig_category":"Carnicer\u00cdas, Carnicer\u00cdas",
    "sg:phone":"+34 943 49 14 86",
    "sg:postcode":"20180",
    "sg:province":"Guip\u00f9zcoa",
    "wof:name":"Zalakain Lekuona Jose Antonio",
    "wof:placetype":"venue"
},
  "geometry": {"coordinates":[-1.8559260368,43.2925300598],"type":"Point"}
}