{
  "type": "Feature",
  "properties": {
    "addr:full":"Calle de Fuente (de La), 26 Parla Madrid 28980",
    "addr:housenumber":"26",
    "addr:postcode":"28980",
    "addr:street":"Calle De Fuente De La",
    "iso:country":"ES",
    "sg:address":"Calle de Fuente (de La), 26",
    "sg:city":"Parla",
    "sg:orig_category":"Servicio De Salud",
    "sg:phone":"+34 916 98 22 39",
    "sg:postcode":"28980",
    "sg:province":"Madrid",
    "wof:name":"Lanzat Mu\u00f1oz Antonio",
    "wof:placetype":"venue"
},
  "geometry": {"coordinates":[-3.7763769627,40.2392272949],"type":"Point"}
}