{
  "type": "Feature",
  "properties": {
    "addr:full":"Av Pau, De Sa, 74 Sant Lluis Islas Baleares 07710",
    "addr:housenumber":"74",
    "addr:postcode":"07710",
    "addr:street":"Av Pau De Sa",
    "iso:country":"ES",
    "sg:address":"Av Pau, De Sa, 74",
    "sg:city":"Sant Lluis",
    "sg:orig_category":"Agencias De Viajes",
    "sg:phone":"+34 971 15 68 00",
    "sg:postcode":"07710",
    "sg:province":"Islas Baleares",
    "wof:name":"Viajes Magon S.a.",
    "wof:placetype":"venue"
},
  "geometry": {"coordinates":[4.2691421509,39.8487739563],"type":"Point"}
}