{
  "type": "Feature",
  "properties": {
    "addr:full":"Calle de Ollerias, 14 Ronda M\u00e1laga 29400",
    "addr:housenumber":"14",
    "addr:postcode":"29400",
    "addr:street":"Calle De Ollerias;Ronda Ma\u0301Laga",
    "iso:country":"ES",
    "sg:address":"Calle de Ollerias, 14",
    "sg:city":"Ronda",
    "sg:orig_category":"Promotores Constructores",
    "sg:phone":"+34 952 87 35 73",
    "sg:postcode":"29400",
    "sg:province":"M\u00e1laga",
    "wof:name":"Construcciones Arcoronda S,l.",
    "wof:placetype":"venue"
},
  "geometry": {"coordinates":[-5.1673970222,36.7465705872],"type":"Point"}
}