{
  "type": "Feature",
  "properties": {
    "addr:full":"Cmno Ventillas (las), S/n Motril Granada 18600",
    "addr:postcode":"18600",
    "addr:street":"Cmno Ventillas Las S / N;Granada",
    "iso:country":"ES",
    "sg:address":"Cmno Ventillas (las), S/n",
    "sg:city":"Motril",
    "sg:orig_category":"Negocio De Materiales De Construcci\u00d3n",
    "sg:phone":"+34 958 82 03 18",
    "sg:postcode":"18600",
    "sg:province":"Granada",
    "wof:name":"Rodriguez Y Llanes S.l.",
    "wof:placetype":"venue"
},
  "geometry": {"coordinates":[-3.513053894,36.7437705994],"type":"Point"}
}