{
  "type": "Feature",
  "properties": {
    "iso:country":"ES",
    "sg:address":"Calle de Virgen De La Oliva, 46",
    "sg:city":"Madrid",
    "sg:orig_category":"Fisioterapia",
    "sg:phone":"+34 917 54 12 58",
    "sg:postcode":"28037",
    "sg:province":"Madrid",
    "wof:name":"Mejorado Garcia Maria Dolores",
    "wof:placetype":"venue"
},
  "geometry": {"coordinates":[-3.624407053,40.4325332642],"type":"Point"}
}