{
  "type": "Feature",
  "properties": {
    "iso:country":"ES",
    "sg:address":"Carr Major, 74",
    "sg:city":"Esterri D'aneu",
    "sg:orig_category":"Empresarios",
    "sg:phone":"+34 973 62 60 68",
    "sg:postcode":"25580",
    "sg:province":"Lleida",
    "wof:name":"Farre Rollan Jose",
    "wof:placetype":"venue"
},
  "geometry": {"coordinates":[0.6244090199,41.613407135],"type":"Point"}
}