{
  "type": "Feature",
  "properties": {
    "iso:country":"ES",
    "sg:address":"Plaz Republica Del Ecuador, 8",
    "sg:city":"Madrid",
    "sg:orig_category":"Ropa Para Se\u00d1oras Y Caballeros (al Por Menor)",
    "sg:phone":"+34 914 58 01 04",
    "sg:postcode":"28016",
    "sg:province":"Madrid",
    "wof:name":"Cotton Moon S.l.",
    "wof:placetype":"venue"
},
  "geometry": {"coordinates":[-3.6774890423,40.4554595947],"type":"Point"}
}