{
  "type": "Feature",
  "properties": {
    "addr:full":"Calle de Almudevar, S/n Huesca Huesca 22004",
    "addr:housenumber":"s",
    "addr:postcode":"22004",
    "addr:street":"Calle De Almudevar;/ N",
    "iso:country":"ES",
    "sg:address":"Calle de Almudevar, S/n",
    "sg:city":"Huesca",
    "sg:orig_category":"Asociaciones, Organismos Culturales Y Socioeducativos",
    "sg:phone":"+34 974 21 27 44",
    "sg:postcode":"22004",
    "sg:province":"Huesca",
    "wof:name":"Pe\u00f1a Los Que Faltaban",
    "wof:placetype":"venue"
},
  "geometry": {"coordinates":[-0.4123449922,42.1318435669],"type":"Point"}
}