{
  "type": "Feature",
  "properties": {
    "addr:full":"Calle de Lagasca, 4 Madrid Madrid 28...",
    "addr:housenumber":"4;28 ...",
    "addr:street":"Calle De Lagasca;Madrid",
    "iso:country":"ES",
    "sg:address":"Calle de Lagasca, 4",
    "sg:city":"Madrid",
    "sg:orig_category":"Agencias Y Asesores De Publicidad",
    "sg:phone":"+34 914 32 98 00",
    "sg:postcode":"28...",
    "sg:province":"Madrid",
    "sg:website":"www.tnsofres.es",
    "wof:name":"Taylor Nelson Sofres S.a.",
    "wof:placetype":"venue"
},
  "geometry": {"coordinates":[-3.6857330799,40.4209632874],"type":"Point"}
}