{
  "type": "Feature",
  "properties": {
    "addr:full":"Calle de General Solchaga, 84 Valladolid Valladolid 47008",
    "addr:housenumber":"84",
    "addr:postcode":"47008",
    "addr:street":"Calle De General Solchaga",
    "iso:country":"ES",
    "sg:address":"Calle de General Solchaga, 84",
    "sg:city":"Valladolid",
    "sg:orig_category":"Chapister\u00cda",
    "sg:phone":"+34 983 22 30 64",
    "sg:postcode":"47008",
    "sg:province":"Valladolid",
    "wof:name":"Talleres Solchaga 84",
    "wof:placetype":"venue"
},
  "geometry": {"coordinates":[-4.7344808578,41.6252975464],"type":"Point"}
}