{
  "type": "Feature",
  "properties": {
    "iso:country":"ES",
    "sg:address":"Calle de Paraguay, 2",
    "sg:city":"Alcantarilla",
    "sg:orig_category":"Planchado",
    "sg:phone":"+34 968 89 26 06",
    "sg:postcode":"30820",
    "sg:province":"Murcia",
    "wof:name":"Talleres Alba S.l.u",
    "wof:placetype":"venue"
},
  "geometry": {"coordinates":[-1.1992619038,37.9563026428],"type":"Point"}
}