{
  "type": "Feature",
  "properties": {
    "addr:full":"Ctra Gador Laujar, 41 Alhama De Almeria Almer\u00eda 04400",
    "addr:housenumber":"41",
    "addr:postcode":"04400",
    "addr:street":"Ctra Gador Laujar;Almeri\u0301A",
    "iso:country":"ES",
    "sg:address":"Ctra Gador Laujar, 41",
    "sg:city":"Alhama De Almeria",
    "sg:orig_category":"Cooperativas Agr\u00cdcolas",
    "sg:phone":"+34 950 64 02 32",
    "sg:postcode":"04400",
    "sg:province":"Almer\u00eda",
    "wof:name":"Union De Agricultores Y Ganaderos De Alm",
    "wof:placetype":"venue"
},
  "geometry": {"coordinates":[-2.5686340332,36.9578285217],"type":"Point"}
}