{
  "type": "Feature",
  "properties": {
    "addr:full":"Calle de Lanzarote (de), 42 Humanes De Madrid Madrid 28970",
    "addr:housenumber":"42",
    "addr:postcode":"28970",
    "addr:street":"Calle De Lanzarote De",
    "iso:country":"ES",
    "sg:address":"Calle de Lanzarote (de), 42",
    "sg:city":"Humanes De Madrid",
    "sg:orig_category":"Empresas De Carpinter\u00cda",
    "sg:phone":"+34 914 92 04 22",
    "sg:postcode":"28970",
    "sg:province":"Madrid",
    "wof:name":"Aluminios Elimar S.l.",
    "wof:placetype":"venue"
},
  "geometry": {"coordinates":[-3.8145632744,40.2709236145],"type":"Point"}
}