{
  "type": "Feature",
  "properties": {
    "addr:full":"Finca Dehesa Campoamor, S/n Dehesa Campoamor Alicante 03189",
    "addr:housenumber":"s / n",
    "addr:postcode":"03189",
    "iso:country":"ES",
    "sg:address":"Finca Dehesa Campoamor, S/n",
    "sg:city":"Dehesa Campoamor",
    "sg:orig_category":"Urbanistas",
    "sg:phone":"+34 965 96 65 13",
    "sg:postcode":"03189",
    "sg:province":"Alicante",
    "wof:name":"Montepiedra S. A.",
    "wof:placetype":"venue"
},
  "geometry": {"coordinates":[-0.7677609921,37.9303321838],"type":"Point"}
}