{
  "type": "Feature",
  "properties": {
    "iso:country":"ES",
    "sg:address":"Psaj Virgen Del Rocio, 2",
    "sg:city":"Ecija",
    "sg:orig_category":"Restaurantes",
    "sg:phone":"+34 955 90 43 83",
    "sg:postcode":"41400",
    "sg:province":"Sevilla",
    "wof:name":"Carmona Cortes Manuel",
    "wof:placetype":"venue"
},
  "geometry": {"coordinates":[-5.0780930519,37.5400657654],"type":"Point"}
}