{
  "type": "Feature",
  "properties": {
    "addr:full":"Avda Costa, 149 Gijon Asturias 33203",
    "addr:housenumber":"149",
    "addr:postcode":"33203",
    "addr:street":"Avda Costa",
    "iso:country":"ES",
    "sg:address":"Avda Costa, 149",
    "sg:city":"Gijon",
    "sg:orig_category":"Librer\u00cdas",
    "sg:phone":"+34 985 33 68 80",
    "sg:postcode":"33203",
    "sg:province":"Asturias",
    "wof:name":"Undagoitia Forcelledo Maria Del Carmen",
    "wof:placetype":"venue"
},
  "geometry": {"coordinates":[-5.6465687752,43.5353775024],"type":"Point"}
}