{
  "type": "Feature",
  "properties": {
    "addr:full":"Ctra Terrassa, 94 Rubi Barcelona 08191",
    "addr:housenumber":"94",
    "addr:postcode":"08191",
    "addr:street":"Ctra Terrassa",
    "iso:country":"ES",
    "sg:address":"Ctra Terrassa, 94",
    "sg:city":"Rubi",
    "sg:orig_category":"Molduras, Junquillos, Listones Y Molduras Perforadas",
    "sg:phone":"+34 936 97 99 55",
    "sg:postcode":"08191",
    "sg:province":"Barcelona",
    "wof:name":"Recreativos Centelles S.l.",
    "wof:placetype":"venue"
},
  "geometry": {"coordinates":[2.0330600739,41.5011138916],"type":"Point"}
}