{
  "type": "Feature",
  "properties": {
    "iso:country":"ES",
    "sg:address":"Avda Fernandez Latorre, 1",
    "sg:city":"Coru\u00d1a",
    "sg:orig_category":"Fabricaci\u00d3n, Importaci\u00d3n, Venta De Material De Telefon\u00cda, Peritelefon\u00cda",
    "sg:phone":"+34 981 23 34 32",
    "sg:postcode":"15006",
    "sg:province":"La Coru\u00f1a",
    "wof:name":"Agris S. A.",
    "wof:placetype":"venue"
},
  "geometry": {"coordinates":[-8.4048423767,43.360004425],"type":"Point"}
}