{
  "type": "Feature",
  "properties": {
    "iso:country":"ES",
    "sg:address":"Calle de Jose Maria Pereda, S/n",
    "sg:city":"Alcala Henares",
    "sg:orig_category":"Zapatos (al Por Menor)",
    "sg:phone":"+34 918 02 52 72",
    "sg:postcode":"28806",
    "sg:province":"Madrid",
    "wof:name":"Santano Martin Estibaliz",
    "wof:placetype":"venue"
},
  "geometry": {"coordinates":[-3.366079092,40.5006752014],"type":"Point"}
}