{
  "type": "Feature",
  "properties": {
    "iso:country":"ES",
    "sg:address":"Calle de Ancha, 8",
    "sg:city":"Cadiz",
    "sg:orig_category":"Art\u00cdculos De Decoraci\u00d3n",
    "sg:phone":"+34 956 22 02 08",
    "sg:postcode":"11001",
    "sg:province":"C\u00e1diz",
    "wof:name":"Residencia Chamara S.l.",
    "wof:placetype":"venue"
},
  "geometry": {"coordinates":[-6.2983031273,36.5341682434],"type":"Point"}
}