{
  "type": "Feature",
  "properties": {
    "iso:country":"ES",
    "sg:address":"Bo. Quintanilla Sociguenza, S/n",
    "sg:city":"Villarcayo",
    "sg:orig_category":"Imprenta",
    "sg:phone":"+34 947 13 20 94",
    "sg:postcode":"09550",
    "sg:province":"Burgos",
    "wof:name":"Imprenta Garcia S.a.",
    "wof:placetype":"venue"
},
  "geometry": {"coordinates":[-3.5719640255,42.9387702942],"type":"Point"}
}