{
  "type": "Feature",
  "properties": {
    "addr:full":"Calle de Garcia Paredes, 12 Armunia Le\u00f3n 24009",
    "addr:housenumber":"12",
    "addr:postcode":"24009",
    "addr:street":"Calle De Garcia Paredes;Leo\u0301N",
    "iso:country":"ES",
    "sg:address":"Calle de Garcia Paredes, 12",
    "sg:city":"Armunia",
    "sg:orig_category":"Alimentaci\u00d3n General (al Por Menor)",
    "sg:phone":"+34 987 25 31 16",
    "sg:postcode":"24009",
    "sg:province":"Le\u00f3n",
    "wof:name":"Garcia Diez Mercurino",
    "wof:placetype":"venue"
},
  "geometry": {"coordinates":[-5.5859279633,42.5879554749],"type":"Point"}
}