{
  "type": "Feature",
  "properties": {
    "addr:full":"Calle de Cirilo Amoros, 45 Valencia Valencia 46004",
    "addr:housenumber":"45",
    "addr:postcode":"46004",
    "addr:street":"Calle De Cirilo Amoros",
    "iso:country":"ES",
    "sg:address":"Calle de Cirilo Amoros, 45",
    "sg:city":"Valencia",
    "sg:orig_category":"Marroquiner\u00cda (confecci\u00d3n)",
    "sg:phone":"+34 963 50 94 31",
    "sg:postcode":"46004",
    "sg:province":"Valencia",
    "wof:name":"Luis Bg Sohops S.l.u.",
    "wof:placetype":"venue"
},
  "geometry": {"coordinates":[-0.3706535995,39.4676933289],"type":"Point"}
}