{
  "type": "Feature",
  "properties": {
    "addr:full":"Calle de General Mola, 2 Riaza Segovia 40500",
    "addr:housenumber":"2",
    "addr:postcode":"40500",
    "addr:street":"Calle De General Mola",
    "iso:country":"ES",
    "sg:address":"Calle de General Mola, 2",
    "sg:city":"Riaza",
    "sg:orig_category":"Plomeros",
    "sg:phone":"+34 921 55 03 42",
    "sg:postcode":"40500",
    "sg:province":"Segovia",
    "wof:name":"Arranz Palermo Angel",
    "wof:placetype":"venue"
},
  "geometry": {"coordinates":[-3.4778454304,41.2810630798],"type":"Point"}
}