{
  "type": "Feature",
  "properties": {
    "addr:full":"Calle de Cura, 7 Fuente Cantos Badajoz 06240",
    "addr:housenumber":"7",
    "addr:postcode":"06240",
    "addr:street":"Calle De Cura",
    "iso:country":"ES",
    "sg:address":"Calle de Cura, 7",
    "sg:city":"Fuente Cantos",
    "sg:orig_category":"Promotores Constructores",
    "sg:phone":"+34 924 58 04 87",
    "sg:postcode":"06240",
    "sg:province":"Badajoz",
    "wof:name":"Construcciones Suroeste",
    "wof:placetype":"venue"
},
  "geometry": {"coordinates":[-6.3084793091,38.2435302734],"type":"Point"}
}