{
  "type": "Feature",
  "properties": {
    "iso:country":"ES",
    "sg:address":"Avda Arcadio Pardi\u00d1as, 161",
    "sg:city":"Burela",
    "sg:orig_category":"Agencias Y Agentes Comerciales, Representantes",
    "sg:phone":"+34 982 58 15 82",
    "sg:postcode":"27880",
    "sg:province":"Lugo",
    "wof:name":"Lopez Lopez Javier",
    "wof:placetype":"venue"
},
  "geometry": {"coordinates":[-7.3567471504,43.6543884277],"type":"Point"}
}