{
  "type": "Feature",
  "properties": {
    "iso:country":"ES",
    "sg:address":"Calle de Zamora, 4",
    "sg:city":"Mostoles",
    "sg:orig_category":"Molduras, Junquillos, Listones Y Molduras Perforadas",
    "sg:phone":"+34 916 13 25 61",
    "sg:postcode":"28931",
    "sg:province":"Madrid",
    "wof:name":"Perez Suarez Juan Jose",
    "wof:placetype":"venue"
},
  "geometry": {"coordinates":[-3.8670909405,40.3254203796],"type":"Point"}
}