{
  "type": "Feature",
  "properties": {
    "addr:full":"Calle de Mosen Bosqued, 4 Zaragoza Zaragoza 50011",
    "addr:housenumber":"4",
    "addr:postcode":"50011",
    "addr:street":"Calle De Mosen Bosqued",
    "iso:country":"ES",
    "sg:address":"Calle de Mosen Bosqued, 4",
    "sg:city":"Zaragoza",
    "sg:orig_category":"Farmacias",
    "sg:phone":"+34 976 34 45 86",
    "sg:postcode":"50011",
    "sg:province":"Zaragoza",
    "wof:name":"Garcia Solans Jose Ramon",
    "wof:placetype":"venue"
},
  "geometry": {"coordinates":[-0.9211080074,41.6495246887],"type":"Point"}
}