{
  "type": "Feature",
  "properties": {
    "addr:full":"Avda Maria Auxiliadora, 22 Badajoz Badajoz 06011",
    "addr:housenumber":"22",
    "addr:postcode":"06011",
    "addr:street":"Avda Maria Auxiliadora",
    "iso:country":"ES",
    "sg:address":"Avda Maria Auxiliadora, 22",
    "sg:city":"Badajoz",
    "sg:orig_category":"M\u00c9dicos: Pediatr\u00cda. Enfermedades De Los Ni\u00d1os",
    "sg:phone":"+34 924 25 70 69",
    "sg:postcode":"06011",
    "sg:province":"Badajoz",
    "wof:name":"Cabezas Segurado Fabian Hermenegildo",
    "wof:placetype":"venue"
},
  "geometry": {"coordinates":[-6.9795298576,38.8688545227],"type":"Point"}
}