{
  "type": "Feature",
  "properties": {
    "addr:full":"Calle de San Francisco, 41 Carmona Sevilla 41410",
    "addr:housenumber":"41",
    "addr:postcode":"41410",
    "addr:street":"Calle De San Francisco",
    "iso:country":"ES",
    "sg:address":"Calle de San Francisco, 41",
    "sg:city":"Carmona",
    "sg:orig_category":"Bazares, Art\u00cdculos De Limpieza Y De Cocina (al Por Menor)",
    "sg:phone":"+34 954 14 35 04",
    "sg:postcode":"41410",
    "sg:province":"Sevilla",
    "wof:name":"Lorenzo Macias Francisco",
    "wof:placetype":"venue"
},
  "geometry": {"coordinates":[-5.6483998299,37.4702148438],"type":"Point"}
}