{
  "type": "Feature",
  "properties": {
    "addr:full":"C/ Fra Pere Balaguer, 27 Elche Alicante 03202",
    "addr:housenumber":"27",
    "addr:postcode":"03202",
    "addr:street":"C / Fra Pere Balaguer",
    "iso:country":"ES",
    "sg:address":"C/ Fra Pere Balaguer, 27",
    "sg:city":"Elche",
    "sg:orig_category":"Arreglo, Reparaci\u00d3n, Piezas Sueltas De Televisi\u00d3n, V\u00cddeo, Hi",
    "sg:phone":"+34 965 45 82 90",
    "sg:postcode":"03202",
    "sg:province":"Alicante",
    "wof:name":"Miralles Agullo Diego",
    "wof:placetype":"venue"
},
  "geometry": {"coordinates":[-0.6838700175,38.2698822021],"type":"Point"}
}