{
  "type": "Feature",
  "properties": {
    "addr:full":"Calle de Polvoranca, 40 Alcorcon Madrid 28921",
    "addr:housenumber":"40",
    "addr:postcode":"28921",
    "addr:street":"Calle De Polvoranca",
    "iso:country":"ES",
    "sg:address":"Calle de Polvoranca, 40",
    "sg:city":"Alcorcon",
    "sg:orig_category":"Empresas De Carpinter\u00cda De Madera",
    "sg:phone":"+34 916 44 34 48",
    "sg:postcode":"28921",
    "sg:province":"Madrid",
    "wof:name":"Garcia Redondo Santos",
    "wof:placetype":"venue"
},
  "geometry": {"coordinates":[-3.824559927,40.3462524414],"type":"Point"}
}