{
  "type": "Feature",
  "properties": {
    "iso:country":"ES",
    "sg:address":"Av Estadi, 13",
    "sg:city":"Vic",
    "sg:orig_category":"Molduras, Junquillos, Listones Y Molduras Perforadas",
    "sg:phone":"+34 938 85 46 69",
    "sg:postcode":"08500",
    "sg:province":"Barcelona",
    "wof:name":"Perez Luna Julian",
    "wof:placetype":"venue"
},
  "geometry": {"coordinates":[2.2538559437,41.9218101501],"type":"Point"}
}