{
  "type": "Feature",
  "properties": {
    "addr:full":"Calle de Real, 88 Illescas Toledo 45200",
    "addr:housenumber":"88",
    "addr:postcode":"45200",
    "addr:street":"Calle De Real",
    "iso:country":"ES",
    "sg:address":"Calle de Real, 88",
    "sg:city":"Illescas",
    "sg:orig_category":"Asesor\u00cda Sobre Comunicaci\u00d3n De Empresas",
    "sg:phone":"+34 925 54 02 41",
    "sg:postcode":"45200",
    "sg:province":"Toledo",
    "wof:name":"Martinez-conde Sotomayor Jose",
    "wof:placetype":"venue"
},
  "geometry": {"coordinates":[-3.8504219055,40.1241645813],"type":"Point"}
}