{
  "type": "Feature",
  "properties": {
    "iso:country":"ES",
    "sg:address":"Calle de Corta, 4",
    "sg:city":"Valladolid",
    "sg:classifiers":[
        {
            "category":"Personal",
            "subcategory":"Barber",
            "type":"Services"
        }
    ],
    "sg:phone":"+34 983 47 03 99",
    "sg:postcode":"47008",
    "sg:province":"Valladolid",
    "sg:tags":[
        "caballeros",
        "de",
        "peluqueros"
    ],
    "wof:name":"Fuente Prieto Leonardo De La",
    "wof:placetype":"venue"
},
  "geometry": {"coordinates":[-4.7416782379,41.6250839233],"type":"Point"}
}