{
  "type": "Feature",
  "properties": {
    "iso:country":"ES",
    "sg:address":"Carrer de Francesc Duran I Reynals, 29",
    "sg:city":"Granollers",
    "sg:orig_category":"Fabricaci\u00d3n De Cajas De Cart\u00d3n",
    "sg:phone":"+34 938 46 35 94",
    "sg:postcode":"08403",
    "sg:province":"Barcelona",
    "wof:name":"Crooked Island S.l",
    "wof:placetype":"venue"
},
  "geometry": {"coordinates":[2.279804945,41.6144218445],"type":"Point"}
}