{
  "type": "Feature",
  "properties": {
    "iso:country":"ES",
    "sg:address":"Avda Iparralde, 7",
    "sg:city":"Irun",
    "sg:orig_category":"Carnicer\u00cdas, Carnicer\u00cdas",
    "sg:phone":"+34 943 62 35 81",
    "sg:postcode":"20304",
    "sg:province":"Guip\u00f9zcoa",
    "wof:name":"Corderos Juan Mari Sl",
    "wof:placetype":"venue"
},
  "geometry": {"coordinates":[-1.7885489464,43.3441581726],"type":"Point"}
}