{
  "type": "Feature",
  "properties": {
    "iso:country":"ES",
    "sg:address":"Avda General Ortega, S/n",
    "sg:city":"Tauste",
    "sg:orig_category":"Sanatorios M\u00c9dico",
    "sg:phone":"+34 976 85 90 00",
    "sg:postcode":"50660",
    "sg:province":"Zaragoza",
    "wof:name":"Servicio Aragones De Salud",
    "wof:placetype":"venue"
},
  "geometry": {"coordinates":[-1.2559540272,41.9253997803],"type":"Point"}
}