{
  "type": "Feature",
  "properties": {
    "addr:full":"Muralla, S/n Vinaros Castell\u00f3n 12500",
    "addr:housenumber":"s / n",
    "addr:postcode":"12500",
    "addr:street":"Muralla",
    "iso:country":"ES",
    "sg:address":"Muralla, S/n",
    "sg:city":"Vinaros",
    "sg:orig_category":"Empresarios",
    "sg:phone":"+34 964 45 62 09",
    "sg:postcode":"12500",
    "sg:province":"Castell\u00f3n",
    "wof:name":"Forem P.v.",
    "wof:placetype":"venue"
},
  "geometry": {"coordinates":[0.4710899889,40.4694709778],"type":"Point"}
}