{
  "type": "Feature",
  "properties": {
    "iso:country":"ES",
    "sg:address":"Gazteluondo Kalea, 7",
    "sg:city":"Arrasate",
    "sg:orig_category":"Pod\u00d3logos: Pedicuros",
    "sg:phone":"+34 943 79 67 02",
    "sg:postcode":"20500",
    "sg:province":"Guip\u00f9zcoa",
    "wof:name":"Del Rio Garcia Jose Luis",
    "wof:placetype":"venue"
},
  "geometry": {"coordinates":[-2.4920089245,43.0636558533],"type":"Point"}
}