{
  "type": "Feature",
  "properties": {
    "iso:country":"ES",
    "sg:address":"Calle de Padre Venancio Huarte, 1",
    "sg:city":"Zaragoza",
    "sg:orig_category":"Telas Para Tapizar, Cortinas, Pasamaner\u00cda (fabricaci\u00d3n, Al Por Mayor)",
    "sg:phone":"+34 976 38 06 04",
    "sg:postcode":"50007",
    "sg:province":"Zaragoza",
    "wof:name":"Comercial Fernando Salinero",
    "wof:placetype":"venue"
},
  "geometry": {"coordinates":[-0.8914589882,41.6275062561],"type":"Point"}
}