{
  "type": "Feature",
  "properties": {
    "addr:full":"Avda Taramundi, 5 Vegadeo Asturias 33770",
    "addr:housenumber":"5",
    "addr:postcode":"33770",
    "addr:street":"Avda Taramundi",
    "iso:country":"ES",
    "sg:address":"Avda Taramundi, 5",
    "sg:city":"Vegadeo",
    "sg:orig_category":"Promotores Constructores",
    "sg:phone":"+34 985 63 49 21",
    "sg:postcode":"33770",
    "sg:province":"Asturias",
    "wof:name":"Convei Gestion S.l.u.",
    "wof:placetype":"venue"
},
  "geometry": {"coordinates":[-7.050142765,43.4628944397],"type":"Point"}
}