{
  "type": "Feature",
  "properties": {
    "addr:full":"Avda Catalu\u00d1a, 299 Zaragoza Zaragoza 50...",
    "addr:housenumber":"299;50 ...",
    "addr:street":"Avda Catalun\u0303A;Zaragoza",
    "iso:country":"ES",
    "sg:address":"Avda Catalu\u00d1a, 299",
    "sg:city":"Zaragoza",
    "sg:orig_category":"Material Ferroviario",
    "sg:phone":"+34 976 76 51 00",
    "sg:postcode":"50...",
    "sg:province":"Zaragoza",
    "wof:name":"Construccion Auxiliar De Ferrocarriles S.a.",
    "wof:placetype":"venue"
},
  "geometry": {"coordinates":[-0.8448389769,41.6705703735],"type":"Point"}
}