{
  "type": "Feature",
  "properties": {
    "iso:country":"ES",
    "sg:address":"Pda Sant Cristofol (a), S/n",
    "sg:city":"Cocentaina",
    "sg:orig_category":"Chapister\u00cda",
    "sg:phone":"+34 965 59 16 32",
    "sg:postcode":"03820",
    "sg:province":"Alicante",
    "wof:name":"Roberto Paya S.l.",
    "wof:placetype":"venue"
},
  "geometry": {"coordinates":[-0.4393219948,38.743812561],"type":"Point"}
}