{
  "type": "Feature",
  "properties": {
    "iso:country":"ES",
    "sg:address":"Calle de Mayor De Nazaret, 23",
    "sg:city":"Valencia",
    "sg:orig_category":"Art\u00cdculos De Madera (fabricaci\u00d3n Y Al Por Mayor)",
    "sg:phone":"+34 963 67 00 31",
    "sg:postcode":"46024",
    "sg:province":"Valencia",
    "wof:name":"Plaza Ferrandis Jose",
    "wof:placetype":"venue"
},
  "geometry": {"coordinates":[-0.3328379989,39.4486732483],"type":"Point"}
}