{
  "type": "Feature",
  "properties": {
    "iso:country":"ES",
    "sg:address":"Calle de Concepcion, 6",
    "sg:city":"Huelva",
    "sg:orig_category":"\u00d3ptica: Instrumentos (fabricaci\u00d3n)",
    "sg:phone":"+34 959 24 55 20",
    "sg:postcode":"21001",
    "sg:province":"Huelva",
    "wof:name":"Sanchez-cortes Mancha Manuel Maria",
    "wof:placetype":"venue"
},
  "geometry": {"coordinates":[-6.9527893066,37.257144928],"type":"Point"}
}