{
  "type": "Feature",
  "properties": {
    "addr:full":"Cmno Daimiel (de), 2 Almagro Ciudad Real 13270",
    "addr:housenumber":"2",
    "addr:postcode":"13270",
    "addr:street":"Cmno Daimiel De",
    "iso:country":"ES",
    "sg:address":"Cmno Daimiel (de), 2",
    "sg:city":"Almagro",
    "sg:orig_category":"Empresas De Carpinter\u00cda Met\u00c1lica",
    "sg:phone":"+34 926 86 04 31",
    "sg:postcode":"13270",
    "sg:province":"Ciudad Real",
    "wof:name":"Talleres Valencia Rabadan S.l.",
    "wof:placetype":"venue"
},
  "geometry": {"coordinates":[-3.7093889713,38.8842353821],"type":"Point"}
}