{
  "type": "Feature",
  "properties": {
    "addr:full":"Ctra Palma Del Rio (a), S/n Almodovar Del Rio C\u00f3rdoba 14720",
    "addr:housenumber":"s / n",
    "addr:postcode":"14720",
    "addr:street":"Ctra Palma Del Rio A;Co\u0301Rdoba",
    "iso:country":"ES",
    "sg:address":"Ctra Palma Del Rio (a), S/n",
    "sg:city":"Almodovar Del Rio",
    "sg:orig_category":"Ingeniero",
    "sg:phone":"+34 957 71 32 67",
    "sg:postcode":"14720",
    "sg:province":"C\u00f3rdoba",
    "wof:name":"Aviles Siles Antonio",
    "wof:placetype":"venue"
},
  "geometry": {"coordinates":[-5.0184440613,37.8131217957],"type":"Point"}
}