{
  "type": "Feature",
  "properties": {
    "addr:full":"Calle de San Mariano, 103 Madrid Madrid 28022",
    "addr:housenumber":"103",
    "addr:postcode":"28022",
    "addr:street":"Calle De San Mariano",
    "iso:country":"ES",
    "sg:address":"Calle de San Mariano, 103",
    "sg:city":"Madrid",
    "sg:orig_category":"Agentes, Concesionarios Y Sucursales De Veh\u00cdculos",
    "sg:phone":"+34 917 41 48 92",
    "sg:postcode":"28022",
    "sg:province":"Madrid",
    "wof:name":"Talleres San Mariano S.l.",
    "wof:placetype":"venue"
},
  "geometry": {"coordinates":[-3.6089680195,40.4366188049],"type":"Point"}
}