{
  "type": "Feature",
  "properties": {
    "addr:full":"Plaza Del Concejo, S/n Granja Torrehermosa Badajoz 06910",
    "addr:housenumber":"s / n",
    "addr:postcode":"06910",
    "addr:street":"Del Concejo",
    "iso:country":"ES",
    "sg:address":"Plaza Del Concejo, S/n",
    "sg:city":"Granja Torrehermosa",
    "sg:orig_category":"Forjas Y Altos Hornos",
    "sg:phone":"+34 924 89 51 35",
    "sg:postcode":"06910",
    "sg:province":"Badajoz",
    "wof:name":"Francisco Asensio Duran E Hijo C.b.",
    "wof:placetype":"venue"
},
  "geometry": {"coordinates":[-5.5940070152,38.3081474304],"type":"Point"}
}