{
  "type": "Feature",
  "properties": {
    "addr:full":"Carrer de Rovellat, 36 Esplugues Llobregat Barcelona 08950",
    "addr:housenumber":"36",
    "addr:postcode":"08950",
    "addr:street":"Carrer De Rovellat",
    "iso:country":"ES",
    "sg:address":"Carrer de Rovellat, 36",
    "sg:city":"Esplugues Llobregat",
    "sg:orig_category":"Electricidad: Equipos Industriales, Componentes (fabricaci\u00d3n)",
    "sg:phone":"+34 933 71 01 17",
    "sg:postcode":"08950",
    "sg:province":"Barcelona",
    "wof:name":"Daugar S. L.",
    "wof:placetype":"venue"
},
  "geometry": {"coordinates":[2.0862801075,41.3717346191],"type":"Point"}
}