{
  "type": "Feature",
  "properties": {
    "iso:country":"ES",
    "sg:address":"Rua Santa Margarita, 8",
    "sg:city":"Pontevedra",
    "sg:orig_category":"Fabricaci\u00d3n, Venta De Cuadros, Accesorios Para Enmarcar",
    "sg:phone":"+34 986 85 91 88",
    "sg:postcode":"36162",
    "sg:province":"Pontevedra",
    "sg:website":"www.cristalpontevedresa.com",
    "wof:name":"Cristaleria Pontevedresa S. A.",
    "wof:placetype":"venue"
},
  "geometry": {"coordinates":[-8.5895700455,42.4346237183],"type":"Point"}
}