{
  "type": "Feature",
  "properties": {
    "iso:country":"ES",
    "sg:address":"Calle de Angostillo, 2",
    "sg:city":"Sevilla",
    "sg:orig_category":"Caf\u00c9s, Bares, Cervecer\u00cdas",
    "sg:phone":"+34 954 22 26 55",
    "sg:postcode":"41003",
    "sg:province":"Sevilla",
    "wof:name":"Fernandez Benitez Alfonso",
    "wof:placetype":"venue"
},
  "geometry": {"coordinates":[-5.9937982559,37.3939323425],"type":"Point"}
}