{
  "type": "Feature",
  "properties": {
    "iso:country":"ES",
    "sg:address":"Avda Castilla Y Leon, 6",
    "sg:city":"Cabezon.barrio Nuevo",
    "sg:orig_category":"Peluqueros: De Se\u00d1oras",
    "sg:phone":"+34 983 50 06 52",
    "sg:postcode":"47260",
    "sg:province":"Valladolid",
    "wof:name":"Peluqueria Ana Y Jose",
    "wof:placetype":"venue"
},
  "geometry": {"coordinates":[-4.6449050903,41.7403411865],"type":"Point"}
}