{
  "type": "Feature",
  "properties": {
    "addr:full":"Calle de Sorni, 17 Valencia Valencia 46004",
    "addr:housenumber":"17",
    "addr:postcode":"46004",
    "addr:street":"Calle De Sorni",
    "iso:country":"ES",
    "sg:address":"Calle de Sorni, 17",
    "sg:city":"Valencia",
    "sg:orig_category":"Abogados",
    "sg:phone":"+34 963 94 32 66",
    "sg:postcode":"46004",
    "sg:province":"Valencia",
    "wof:name":"Sans Garcia Francisco Javier",
    "wof:placetype":"venue"
},
  "geometry": {"coordinates":[-0.367655009,39.4703865051],"type":"Point"}
}