{
  "type": "Feature",
  "properties": {
    "addr:full":"Av Jaume I, 55 Reus Tarragona 43205",
    "addr:housenumber":"55",
    "addr:postcode":"43205",
    "addr:street":"Av Jaume I",
    "iso:country":"ES",
    "sg:address":"Av Jaume I, 55",
    "sg:city":"Reus",
    "sg:orig_category":"Cerrajer\u00cda, Ferrallista",
    "sg:phone":"+34 977 77 32 43",
    "sg:postcode":"43205",
    "sg:province":"Tarragona",
    "wof:name":"Construcciones Y Enconfrados Ff C.b.",
    "wof:placetype":"venue"
},
  "geometry": {"coordinates":[1.1086729765,41.1503143311],"type":"Point"}
}