{
  "type": "Feature",
  "properties": {
    "addr:full":"Calle de Grecia, 5 Palencia Palencia 34003",
    "addr:housenumber":"5",
    "addr:postcode":"34003",
    "addr:street":"Calle De Grecia",
    "iso:country":"ES",
    "sg:address":"Calle de Grecia, 5",
    "sg:city":"Palencia",
    "sg:orig_category":"Aparatos E Instalaci\u00d3n De Regad\u00cdos",
    "sg:phone":"+34 979 72 36 49",
    "sg:postcode":"34003",
    "sg:province":"Palencia",
    "wof:name":"Talleres Alejandro E Hijos S.l.",
    "wof:placetype":"venue"
},
  "geometry": {"coordinates":[-4.5150198936,42.0067138672],"type":"Point"}
}