{
  "type": "Feature",
  "properties": {
    "addr:full":"Buztinzuri Kalea, 1 Antzuola Guip\u00f9zcoa 20577",
    "addr:housenumber":"1",
    "addr:postcode":"20577",
    "addr:street":"Buztinzuri Kalea;Guipu\u0300Zcoa",
    "iso:country":"ES",
    "sg:address":"Buztinzuri Kalea, 1",
    "sg:city":"Antzuola",
    "sg:orig_category":"Centros De Educaci\u00d3n Especial",
    "sg:phone":"+34 943 76 62 68",
    "sg:postcode":"20577",
    "sg:province":"Guip\u00f9zcoa",
    "wof:name":"Gobierno Vasco-eusko Jaurlaritza",
    "wof:placetype":"venue"
},
  "geometry": {"coordinates":[-2.3807051182,43.0984153748],"type":"Point"}
}