{
  "type": "Feature",
  "properties": {
    "iso:country":"ES",
    "sg:address":"Hortelanos (p I Antequera), 10",
    "sg:city":"Antequera",
    "sg:orig_category":"Empresas De Carpinter\u00cda Met\u00c1lica",
    "sg:phone":"+34 952 70 00 94",
    "sg:postcode":"29200",
    "sg:province":"M\u00e1laga",
    "wof:name":"Rubio Tortosa Miguel Angel",
    "wof:placetype":"venue"
},
  "geometry": {"coordinates":[-4.5343928337,37.0279846191],"type":"Point"}
}