{
  "type": "Feature",
  "properties": {
    "addr:full":"Calle de Juan Xxiii, 10 Cantillana Sevilla 41320",
    "addr:housenumber":"10",
    "addr:postcode":"41320",
    "addr:street":"Calle De Juan Xxiii",
    "iso:country":"ES",
    "sg:address":"Calle de Juan Xxiii, 10",
    "sg:city":"Cantillana",
    "sg:orig_category":"Reposter\u00cdas",
    "sg:phone":"+34 955 73 18 05",
    "sg:postcode":"41320",
    "sg:province":"Sevilla",
    "wof:name":"Villalon Lozano Jesus",
    "wof:placetype":"venue"
},
  "geometry": {"coordinates":[-5.8253397942,37.6088676453],"type":"Point"}
}