{
  "type": "Feature",
  "properties": {
    "iso:country":"ES",
    "sg:address":"Calle de Comunidad De Murcia, 3",
    "sg:city":"Rozas De Madrid",
    "sg:orig_category":"Alimentaci\u00d3n General (al Por Menor)",
    "sg:phone":"+34 916 39 32 27",
    "sg:postcode":"28230",
    "sg:province":"Madrid",
    "wof:name":"Mari\u00f1o Sanchez Juan Carlos",
    "wof:placetype":"venue"
},
  "geometry": {"coordinates":[-3.8877501488,40.4900016785],"type":"Point"}
}