{
  "type": "Feature",
  "properties": {
    "addr:full":"Calle de Antonio Lorenzo Hurtado, 1 Valladolid Valladolid 47014",
    "addr:housenumber":"1",
    "addr:postcode":"47014",
    "addr:street":"Calle De Antonio Lorenzo Hurtado",
    "iso:country":"ES",
    "sg:address":"Calle de Antonio Lorenzo Hurtado, 1",
    "sg:city":"Valladolid",
    "sg:orig_category":"Ense\u00d1anza: Idiomas",
    "sg:phone":"+34 983 37 09 37",
    "sg:postcode":"47014",
    "sg:province":"Valladolid",
    "wof:name":"Martin Herrero Sonsoles",
    "wof:placetype":"venue"
},
  "geometry": {"coordinates":[-4.7351937294,41.6532592773],"type":"Point"}
}