{
  "type": "Feature",
  "properties": {
    "addr:full":"Ctra San Bartolome, Km. 0001,2 Argana Baja Las Palmas 35500",
    "addr:postcode":"35500",
    "addr:street":"Ctra San Bartolome Km. 0001,2",
    "iso:country":"ES",
    "sg:address":"Ctra San Bartolome, Km. 0001,2",
    "sg:city":"Argana Baja",
    "sg:orig_category":"Chapister\u00cda",
    "sg:phone":"+34 928 80 37 85",
    "sg:postcode":"35500",
    "sg:province":"Las Palmas",
    "wof:name":"Ossorio Torres Modesto",
    "wof:placetype":"venue"
},
  "geometry": {"coordinates":[-13.5490036011,28.9582099915],"type":"Point"}
}