{
  "type": "Feature",
  "properties": {
    "addr:full":"Calle de Arco, 11 Salamanca Salamanca 37002",
    "addr:housenumber":"11",
    "addr:postcode":"37002",
    "addr:street":"Calle De Arco",
    "iso:country":"ES",
    "sg:address":"Calle de Arco, 11",
    "sg:city":"Salamanca",
    "sg:orig_category":"Doctores En Medicina",
    "sg:phone":"+34 923 21 50 66",
    "sg:postcode":"37002",
    "sg:province":"Salamanca",
    "wof:name":"Rubio Gomez Juan Pedro",
    "wof:placetype":"venue"
},
  "geometry": {"coordinates":[-5.6626982689,40.9688949585],"type":"Point"}
}