{
  "type": "Feature",
  "properties": {
    "iso:country":"ES",
    "sg:address":"Bo. Henarejo, S/n",
    "sg:city":"Cuevas Provanco",
    "sg:orig_category":"Agricultores, Agricultores",
    "sg:phone":"+34 921 52 73 71",
    "sg:postcode":"40239",
    "sg:province":"Segovia",
    "wof:name":"Velasco Paul Leuvino",
    "wof:placetype":"venue"
},
  "geometry": {"coordinates":[-3.9649391174,41.5444107056],"type":"Point"}
}