{
  "type": "Feature",
  "properties": {
    "addr:full":"Calle de Herreros, 5 Rota C\u00e1diz 11520",
    "addr:housenumber":"5",
    "addr:postcode":"11520",
    "addr:street":"Calle De Herreros;Ca\u0301Diz",
    "iso:country":"ES",
    "sg:address":"Calle de Herreros, 5",
    "sg:city":"Rota",
    "sg:orig_category":"Empresas De Carpinter\u00cda De Madera",
    "sg:phone":"+34 956 81 00 61",
    "sg:postcode":"11520",
    "sg:province":"C\u00e1diz",
    "wof:name":"Gonzalez Perez Manuel",
    "wof:placetype":"venue"
},
  "geometry": {"coordinates":[-6.3655247688,36.6308364868],"type":"Point"}
}