{
  "type": "Feature",
  "properties": {
    "addr:full":"Calle de Gutierrez De La Gandara, 6 Llanes Asturias 33500",
    "addr:housenumber":"6",
    "addr:postcode":"33500",
    "addr:street":"Calle De Gutierrez De La Gandara",
    "iso:country":"ES",
    "sg:address":"Calle de Gutierrez De La Gandara, 6",
    "sg:city":"Llanes",
    "sg:orig_category":"Molduras, Junquillos, Listones Y Molduras Perforadas",
    "sg:phone":"+34 985 40 21 53",
    "sg:postcode":"33500",
    "sg:province":"Asturias",
    "wof:name":"Hosteleria Arbidel S.l:",
    "wof:placetype":"venue"
},
  "geometry": {"coordinates":[-4.7530908585,43.4189796448],"type":"Point"}
}