{
  "type": "Feature",
  "properties": {
    "addr:full":"Rua Real, 103 Ferrol La Coru\u00f1a 15402",
    "addr:housenumber":"103",
    "addr:postcode":"15402",
    "addr:street":"Rua Real;La Corun\u0303A",
    "iso:country":"ES",
    "sg:address":"Rua Real, 103",
    "sg:city":"Ferrol",
    "sg:orig_category":"Bisuter\u00cda, Joyer\u00cda, Relojer\u00cda (al Por Menor)",
    "sg:phone":"+34 981 35 33 76",
    "sg:postcode":"15402",
    "sg:province":"La Coru\u00f1a",
    "wof:name":"Joya 36 S.a.",
    "wof:placetype":"venue"
},
  "geometry": {"coordinates":[-8.2334032059,43.4837684631],"type":"Point"}
}