{
  "type": "Feature",
  "properties": {
    "iso:country":"ES",
    "sg:address":"Avda Antonio Machado, 47",
    "sg:city":"Roquetas Mar",
    "sg:orig_category":"Molduras, Junquillos, Listones Y Molduras Perforadas",
    "sg:phone":"+34 950 32 80 83",
    "sg:postcode":"04740",
    "sg:province":"Almer\u00eda",
    "wof:name":"Rodriguez Lopez Rafael",
    "wof:placetype":"venue"
},
  "geometry": {"coordinates":[-2.6124989986,36.7638435364],"type":"Point"}
}