{
  "type": "Feature",
  "properties": {
    "iso:country":"ES",
    "sg:address":"Carr Aigueta, 170",
    "sg:city":"Bisbal D'emporda",
    "sg:orig_category":"Colchones (fabricaci\u00d3n, Al Por Mayor, Al Por Menor)",
    "sg:phone":"+34 972 64 20 11",
    "sg:postcode":"17100",
    "sg:province":"Girona",
    "wof:name":"Procomiber S.l.",
    "wof:placetype":"venue"
},
  "geometry": {"coordinates":[2.8187398911,41.9808616638],"type":"Point"}
}