{
  "type": "Feature",
  "properties": {
    "iso:country":"ES",
    "sg:address":"Calle de Anton De Alaminos, 20",
    "sg:city":"Sevilla",
    "sg:orig_category":"Organizaciones Profesionales",
    "sg:phone":"+34 954 25 53 00",
    "sg:postcode":"41007",
    "sg:province":"Sevilla",
    "wof:name":"Sevitrade S.l.",
    "wof:placetype":"venue"
},
  "geometry": {"coordinates":[-5.9498848915,37.3965110779],"type":"Point"}
}