{
  "type": "Feature",
  "properties": {
    "iso:country":"ES",
    "sg:address":"Calle de Santiago, 17",
    "sg:city":"Valladolid",
    "sg:orig_category":"Agentes Generales De Seguros",
    "sg:phone":"+34 983 35 55 92",
    "sg:postcode":"47001",
    "sg:province":"Valladolid",
    "wof:name":"Del Cura Y Miranda S.l.",
    "wof:placetype":"venue"
},
  "geometry": {"coordinates":[-4.7287240028,41.6498336792],"type":"Point"}
}