{
  "type": "Feature",
  "properties": {
    "addr:full":"Plaz Carbayedo Del, 23 Aviles Asturias 33402",
    "addr:postcode":"33402",
    "addr:street":"Plaz;Del",
    "iso:country":"ES",
    "sg:address":"Plaz Carbayedo Del, 23",
    "sg:city":"Aviles",
    "sg:orig_category":"Molduras, Junquillos, Listones Y Molduras Perforadas",
    "sg:phone":"+34 985 54 05 24",
    "sg:postcode":"33402",
    "sg:province":"Asturias",
    "wof:name":"Fernandez Villar Maria Carmen",
    "wof:placetype":"venue"
},
  "geometry": {"coordinates":[-5.9263877869,43.534324646],"type":"Point"}
}