{
  "type": "Feature",
  "properties": {
    "addr:full":"Plaz Encuentro, 5 Madrid Madrid 28030",
    "addr:housenumber":"5",
    "addr:postcode":"28030",
    "addr:street":"Encuentro",
    "iso:country":"ES",
    "sg:address":"Plaz Encuentro, 5",
    "sg:city":"Madrid",
    "sg:orig_category":"Supermercados Y Hipermercados",
    "sg:phone":"+34 914 39 00 50",
    "sg:postcode":"28030",
    "sg:province":"Madrid",
    "wof:name":"Supermercados Champion S.a.",
    "wof:placetype":"venue"
},
  "geometry": {"coordinates":[-3.6515800953,40.4055747986],"type":"Point"}
}