{
  "type": "Feature",
  "properties": {
    "iso:country":"ES",
    "sg:address":"Carr Salvador Giner, 13",
    "sg:city":"Alboraya",
    "sg:orig_category":"Venta, Instalaci\u00d3n De Calefacci\u00d3n",
    "sg:phone":"+34 961 85 50 47",
    "sg:postcode":"46120",
    "sg:province":"Valencia",
    "wof:name":"Vivo-gonzalez S.l.",
    "wof:placetype":"venue"
},
  "geometry": {"coordinates":[-0.3516151011,39.5002326965],"type":"Point"}
}