{
  "type": "Feature",
  "properties": {
    "addr:full":"Calle de Ramon Y Cajal, 15 Santa Pola Alicante 03130",
    "addr:housenumber":"15",
    "addr:postcode":"03130",
    "addr:street":"Calle De Ramon Y Cajal",
    "iso:country":"ES",
    "sg:address":"Calle de Ramon Y Cajal, 15",
    "sg:city":"Santa Pola",
    "sg:orig_category":"Plomeros",
    "sg:phone":"+34 965 41 66 80",
    "sg:postcode":"03130",
    "sg:province":"Alicante",
    "wof:name":"Montes Arroyo Francisco",
    "wof:placetype":"venue"
},
  "geometry": {"coordinates":[-0.5592154264,38.1939888],"type":"Point"}
}