{
  "type": "Feature",
  "properties": {
    "iso:country":"ES",
    "sg:address":"Carrer de Creu Coberta, 120",
    "sg:city":"Barcelona",
    "sg:orig_category":"Laboratorios Y Trabajos De Fotograf\u00cda, V\u00cddeo Y Cine",
    "sg:phone":"+34 934 22 36 14",
    "sg:postcode":"08014",
    "sg:province":"Barcelona",
    "sg:website":"www.fotoprix.es",
    "wof:name":"Fotoprix Sa.",
    "wof:placetype":"venue"
},
  "geometry": {"coordinates":[2.141272068,41.3754272461],"type":"Point"}
}