{
  "type": "Feature",
  "properties": {
    "iso:country":"ES",
    "sg:address":"Carr De Peniscola, 64",
    "sg:city":"Benicarlo",
    "sg:orig_category":"Empresas De Carpinter\u00cda",
    "sg:phone":"+34 964 46 19 42",
    "sg:postcode":"12580",
    "sg:province":"Castell\u00f3n",
    "wof:name":"Martinez Domingo Pedro",
    "wof:placetype":"venue"
},
  "geometry": {"coordinates":[0.4226253927,40.4133262634],"type":"Point"}
}