{
  "type": "Feature",
  "properties": {
    "iso:country":"ES",
    "sg:address":"Calle de Leopoldo Lugones, 14",
    "sg:city":"Lugones",
    "sg:orig_category":"Inmobiliaria (agencias)",
    "sg:phone":"+34 985 26 91 85",
    "sg:postcode":"33420",
    "sg:province":"Asturias",
    "wof:name":"Asesores Inmobiliarios C.b.",
    "wof:placetype":"venue"
},
  "geometry": {"coordinates":[-5.804954052,43.4016036987],"type":"Point"}
}