{
  "type": "Feature",
  "properties": {
    "addr:full":"Avda San Juan El Real, 7 Calatayud Zaragoza 50300",
    "addr:housenumber":"7",
    "addr:postcode":"50300",
    "addr:street":"Avda San Juan El Real",
    "iso:country":"ES",
    "sg:address":"Avda San Juan El Real, 7",
    "sg:city":"Calatayud",
    "sg:orig_category":"Fotograf\u00cda Y Cine: Aparatos, Pel\u00cdculas Y Accesorios (fabricaci\u00d3n, Al Por Mayor)",
    "sg:phone":"+34 976 88 57 58",
    "sg:postcode":"50300",
    "sg:province":"Zaragoza",
    "sg:website":"www.fotoprix.es",
    "wof:name":"El Real Estudio Fotografico S.l.u",
    "wof:placetype":"venue"
},
  "geometry": {"coordinates":[-1.6438640356,41.3526573181],"type":"Point"}
}