{
  "type": "Feature",
  "properties": {
    "addr:full":"Mur, 109 Almenara Castell\u00f3n 12590",
    "addr:housenumber":"109",
    "addr:postcode":"12590",
    "addr:street":"Mur",
    "iso:country":"ES",
    "sg:address":"Mur, 109",
    "sg:city":"Almenara",
    "sg:orig_category":"Promotores Constructores",
    "sg:phone":"+34 962 61 02 97",
    "sg:postcode":"12590",
    "sg:province":"Castell\u00f3n",
    "sg:website":"www.conreuccionestomasyluis.com",
    "wof:name":"Construcciones Tomas Y Luis S.l.",
    "wof:placetype":"venue"
},
  "geometry": {"coordinates":[-0.2260439992,39.7561950684],"type":"Point"}
}