{
  "type": "Feature",
  "properties": {
    "addr:full":"Calle de Laureado Garcia Esteban, 1 Teruel Teruel 44001",
    "addr:housenumber":"1",
    "addr:postcode":"44001",
    "addr:street":"Calle De Laureado Garcia Esteban",
    "iso:country":"ES",
    "sg:address":"Calle de Laureado Garcia Esteban, 1",
    "sg:city":"Teruel",
    "sg:orig_category":"Electrodom\u00c9sticos (al Por Menor)",
    "sg:phone":"+34 978 60 36 79",
    "sg:postcode":"44001",
    "sg:province":"Teruel",
    "wof:name":"Comercial Benajes S. L.",
    "wof:placetype":"venue"
},
  "geometry": {"coordinates":[-1.1071120501,40.3421058655],"type":"Point"}
}