{
  "type": "Feature",
  "properties": {
    "addr:full":"Carrer de Comte Borrell, 68 Barcelona Barcelona 08015",
    "addr:housenumber":"68",
    "addr:postcode":"08015",
    "addr:street":"Carrer De Comte Borrell",
    "iso:country":"ES",
    "sg:address":"Carrer de Comte Borrell, 68",
    "sg:city":"Barcelona",
    "sg:orig_category":"Farmacias",
    "sg:phone":"+34 934 23 58 46",
    "sg:postcode":"08015",
    "sg:province":"Barcelona",
    "wof:name":"Herrero Cerda Jose",
    "wof:placetype":"venue"
},
  "geometry": {"coordinates":[2.16051507,41.3790931702],"type":"Point"}
}