{
  "type": "Feature",
  "properties": {
    "addr:full":"Calle de Cueva De Montesinos, 118 Madrid Madrid 28034",
    "addr:housenumber":"118",
    "addr:postcode":"28034",
    "addr:street":"Calle De Cueva De Montesinos",
    "iso:country":"ES",
    "sg:address":"Calle de Cueva De Montesinos, 118",
    "sg:city":"Madrid",
    "sg:orig_category":"Ingenier\u00cda, Centros De Estudios (diversos)",
    "sg:phone":"+34 917 34 83 62",
    "sg:postcode":"28034",
    "sg:province":"Madrid",
    "wof:name":"Iberica De Estudios E Ingenieria S.a.",
    "wof:placetype":"venue"
},
  "geometry": {"coordinates":[-3.6922163963,40.5002441406],"type":"Point"}
}