{
  "type": "Feature",
  "properties": {
    "iso:country":"ES",
    "sg:address":"Ctra Aznalcazar-bollullos, Km. 0016,0",
    "sg:city":"Aznalcazar",
    "sg:orig_category":"Cr\u00cda De Perros Y De Gatos",
    "sg:phone":"+34 955 75 07 59",
    "sg:postcode":"41849",
    "sg:province":"Sevilla",
    "wof:name":"Reina Ponce Antonio",
    "wof:placetype":"venue"
},
  "geometry": {"coordinates":[-6.2510838509,37.303768158],"type":"Point"}
}