{
  "type": "Feature",
  "properties": {
    "iso:country":"ES",
    "sg:address":"Pase Rosa, 12",
    "sg:city":"Toledo",
    "sg:orig_category":"Locales Y Clases De Danza",
    "sg:phone":"+34 925 25 70 40",
    "sg:postcode":"45006",
    "sg:province":"Toledo",
    "wof:name":"Beinat Espa\u00f1a Jose Luis",
    "wof:placetype":"venue"
},
  "geometry": {"coordinates":[-4.0053992271,39.860748291],"type":"Point"}
}