{
  "type": "Feature",
  "properties": {
    "addr:full":"Rio Altzania, 19 Iru\u00f1a Navarra 31005",
    "addr:housenumber":"19",
    "addr:postcode":"31005",
    "addr:street":"Rio Altzania",
    "iso:country":"ES",
    "sg:address":"Rio Altzania, 19",
    "sg:city":"Iru\u00f1a",
    "sg:orig_category":"Arquitectos",
    "sg:phone":"+34 948 23 51 52",
    "sg:postcode":"31005",
    "sg:province":"Navarra",
    "sg:website":"www.arquitecturayurbanismo.net",
    "wof:name":"Arquitectura Y Urbanismo Alsasua S.l.",
    "wof:placetype":"venue"
},
  "geometry": {"coordinates":[-1.6466133595,42.802192688],"type":"Point"}
}