{
  "type": "Feature",
  "properties": {
    "addr:full":"Calle de Rosuero, S/n Villarejo Segovia 40590",
    "addr:housenumber":"s",
    "addr:postcode":"40590",
    "addr:street":"Calle De Rosuero;/ N Villarejo Segovia",
    "iso:country":"ES",
    "sg:address":"Calle de Rosuero, S/n",
    "sg:city":"Villarejo",
    "sg:orig_category":"Empresas De Carpinter\u00cda Met\u00c1lica",
    "sg:phone":"+34 921 55 73 33",
    "sg:postcode":"40590",
    "sg:province":"Segovia",
    "wof:name":"Talleres Crishe S.l.",
    "wof:placetype":"venue"
},
  "geometry": {"coordinates":[-3.5760219097,41.1955909729],"type":"Point"}
}