{
  "type": "Feature",
  "properties": {
    "iso:country":"ES",
    "sg:address":"Av Francesc Riera, S/n",
    "sg:city":"Martorell",
    "sg:orig_category":"Supermercados Y Hipermercados",
    "sg:phone":"+34 937 76 59 20",
    "sg:postcode":"08760",
    "sg:province":"Barcelona",
    "sg:website":"www.capraboacasa.com",
    "wof:name":"Caprabo S.a.",
    "wof:placetype":"venue"
},
  "geometry": {"coordinates":[1.9135099649,41.480796814],"type":"Point"}
}