{
  "type": "Feature",
  "properties": {
    "addr:full":"Avda Castilla Y Leon, 46 Burgos Burgos 09006",
    "addr:housenumber":"46",
    "addr:postcode":"09006",
    "addr:street":"Avda Castilla Y Leon",
    "iso:country":"ES",
    "sg:address":"Avda Castilla Y Leon, 46",
    "sg:city":"Burgos",
    "sg:orig_category":"Ropa De Trabajo Y Profesionales (fabricaci\u00d3n, Al Por Mayor)",
    "sg:phone":"+34 947 24 40 76",
    "sg:postcode":"09006",
    "sg:province":"Burgos",
    "wof:name":"Mikeneko S.l.",
    "wof:placetype":"venue"
},
  "geometry": {"coordinates":[-3.6791689396,42.3554458618],"type":"Point"}
}