{
  "type": "Feature",
  "properties": {
    "addr:full":"Calle de Lorenzo Pardo, 23 Zaragoza Zaragoza 50008",
    "addr:housenumber":"23",
    "addr:postcode":"50008",
    "addr:street":"Calle De Lorenzo Pardo",
    "iso:country":"ES",
    "sg:address":"Calle de Lorenzo Pardo, 23",
    "sg:city":"Zaragoza",
    "sg:orig_category":"Caf\u00c9s, Bares, Cervecer\u00cdas",
    "sg:phone":"+34 976 59 59 04",
    "sg:postcode":"50008",
    "sg:province":"Zaragoza",
    "wof:name":"Blasco Gimenez S.c.",
    "wof:placetype":"venue"
},
  "geometry": {"coordinates":[-0.8754130006,41.6434516907],"type":"Point"}
}