{
  "type": "Feature",
  "properties": {
    "iso:country":"ES",
    "sg:address":"Cra. Sta. Coloma, 150",
    "sg:city":"Olot",
    "sg:orig_category":"Ebanister\u00cda",
    "sg:phone":"+34 972 26 62 79",
    "sg:postcode":"17800",
    "sg:province":"Girona",
    "wof:name":"Colomer Iglesias Miquel",
    "wof:placetype":"venue"
},
  "geometry": {"coordinates":[2.4893848896,42.1809463501],"type":"Point"}
}