{
  "type": "Feature",
  "properties": {
    "iso:country":"ES",
    "sg:address":"Calle de Arturo Soria, 336",
    "sg:city":"Madrid",
    "sg:orig_category":"Inform\u00c1tica, Ofim\u00c1tica (estudios, Asesor\u00cda, Ingenier\u00cda, Formaci\u00d3n)",
    "sg:phone":"+34 913 02 72 92",
    "sg:postcode":"28033",
    "sg:province":"Madrid",
    "wof:name":"Lsi ( Spain",
    "wof:placetype":"venue"
},
  "geometry": {"coordinates":[-3.665730238,40.4814147949],"type":"Point"}
}