{
  "type": "Feature",
  "properties": {
    "iso:country":"ES",
    "sg:address":"Av. Taio (urb El Taio), 59",
    "sg:city":"Castellvi Rosanes",
    "sg:orig_category":"Empresarios Y Productoras De Espect\u00c1culos",
    "sg:phone":"+34 937 74 22 41",
    "sg:postcode":"08769",
    "sg:province":"Barcelona",
    "sg:website":"www.gestiomusical.com",
    "wof:name":"Carmel Gestio Musical S.l",
    "wof:placetype":"venue"
},
  "geometry": {"coordinates":[1.9062149525,41.4559249878],"type":"Point"}
}