{
  "type": "Feature",
  "properties": {
    "addr:full":"Calle de Tarifa, 42 Jodar Ja\u00e9n 23500",
    "addr:housenumber":"42",
    "addr:postcode":"23500",
    "addr:street":"Calle De Tarifa;Jae\u0301N",
    "iso:country":"ES",
    "sg:address":"Calle de Tarifa, 42",
    "sg:city":"Jodar",
    "sg:orig_category":"Inform\u00c1tica (estudios, Servicios, Asesor\u00cda, Formaci\u00d3n)",
    "sg:phone":"+34 953 78 40 09",
    "sg:postcode":"23500",
    "sg:province":"Ja\u00e9n",
    "wof:name":"Moreno Angulo Fernando",
    "wof:placetype":"venue"
},
  "geometry": {"coordinates":[-3.3522439003,37.8409690857],"type":"Point"}
}