{
  "type": "Feature",
  "properties": {
    "addr:full":"Avgd Balmes, 74 Igualada Barcelona 08700",
    "addr:housenumber":"74",
    "addr:postcode":"08700",
    "addr:street":"Avgd Balmes",
    "iso:country":"ES",
    "sg:address":"Avgd Balmes, 74",
    "sg:city":"Igualada",
    "sg:orig_category":"Pe\u00d1as Y Asociaciones Varias",
    "sg:phone":"+34 938 03 20 99",
    "sg:postcode":"08700",
    "sg:province":"Barcelona",
    "wof:name":"Cooperativa Igualadina De Viviendas",
    "wof:placetype":"venue"
},
  "geometry": {"coordinates":[1.6143900156,41.5867881775],"type":"Point"}
}