{
  "type": "Feature",
  "properties": {
    "iso:country":"ES",
    "sg:address":"Josep M. Llompart, 30",
    "sg:city":"Portol",
    "sg:orig_category":"Inform\u00c1tica (estudios, Servicios, Asesor\u00cda, Formaci\u00d3n)",
    "sg:phone":"+34 971 60 36 34",
    "sg:postcode":"07141",
    "sg:province":"Islas Baleares",
    "wof:name":"Report Soft S.l. Unipersonal",
    "wof:placetype":"venue"
},
  "geometry": {"coordinates":[2.741590023,39.6156005859],"type":"Point"}
}