{
  "type": "Feature",
  "properties": {
    "iso:country":"ES",
    "sg:address":"Calle de Actriz Encarna Ma\u00d1ez, 3",
    "sg:city":"Valencia",
    "sg:orig_category":"Caf\u00c9s, Bares, Cervecer\u00cdas",
    "sg:phone":"+34 963 55 24 44",
    "sg:postcode":"46022",
    "sg:province":"Valencia",
    "wof:name":"Alvarez Joga Maria Rocio",
    "wof:placetype":"venue"
},
  "geometry": {"coordinates":[-0.3462322056,39.472454071],"type":"Point"}
}