{
  "type": "Feature",
  "properties": {
    "addr:full":"Carrer de Florida, 57 Hospitalet Llobregat Barcelona 08905",
    "addr:housenumber":"57",
    "addr:postcode":"08905",
    "addr:street":"Carrer De Florida",
    "iso:country":"ES",
    "sg:address":"Carrer de Florida, 57",
    "sg:city":"Hospitalet Llobregat",
    "sg:orig_category":"Restaurantes",
    "sg:phone":"+34 933 34 20 20",
    "sg:postcode":"08905",
    "sg:province":"Barcelona",
    "wof:name":"Fabregas Garcia Luis",
    "wof:placetype":"venue"
},
  "geometry": {"coordinates":[2.1120510101,41.370174408],"type":"Point"}
}