{
  "type": "Feature",
  "properties": {
    "iso:country":"ES",
    "sg:address":"Carr Sant Josep, 73",
    "sg:city":"Villarreal",
    "sg:orig_category":"Institutos De Belleza",
    "sg:phone":"+34 964 52 34 67",
    "sg:postcode":"12540",
    "sg:province":"Castell\u00f3n",
    "wof:name":"Colas Flores Rosmary",
    "wof:placetype":"venue"
},
  "geometry": {"coordinates":[-0.0952939987,39.9453048706],"type":"Point"}
}