{
  "type": "Feature",
  "properties": {
    "iso:country":"ES",
    "sg:address":"Calle de Granero, 2",
    "sg:city":"San Mateo",
    "sg:orig_category":"Reposter\u00cdas",
    "sg:phone":"+34 968 46 72 63",
    "sg:postcode":"30800",
    "sg:province":"Murcia",
    "wof:name":"Alcaraz Cove\u00f1 Jose",
    "wof:placetype":"venue"
},
  "geometry": {"coordinates":[-1.1298867464,37.9834747314],"type":"Point"}
}