{
  "type": "Feature",
  "properties": {
    "addr:full":"Calle de Santa Comba, 8 Madrid Madrid 28008",
    "addr:housenumber":"8",
    "addr:postcode":"madrid;28008",
    "addr:street":"Calle De Santa Comba",
    "iso:country":"ES",
    "sg:address":"Calle de Santa Comba, 8",
    "sg:city":"Madrid",
    "sg:orig_category":"Promotores Constructores",
    "sg:phone":"+34 915 47 96 85",
    "sg:postcode":"28008",
    "sg:province":"Madrid",
    "wof:name":"Construcciones Y Contratas Zagarron",
    "wof:placetype":"venue"
},
  "geometry": {"coordinates":[-3.7335319519,40.4281768799],"type":"Point"}
}