{
  "type": "Feature",
  "properties": {
    "addr:full":"C/ Velarde, 53 Elche Alicante 03203",
    "addr:housenumber":"53",
    "addr:postcode":"03203",
    "addr:street":"C / Velarde",
    "iso:country":"ES",
    "sg:address":"C/ Velarde, 53",
    "sg:city":"Elche",
    "sg:orig_category":"Abogados",
    "sg:phone":"+34 965 45 45 45",
    "sg:postcode":"03203",
    "sg:province":"Alicante",
    "wof:name":"Ortu\u00f1o Cerda Y Cerda Manuel",
    "wof:placetype":"venue"
},
  "geometry": {"coordinates":[-0.691929996,38.2653617859],"type":"Point"}
}