{
  "type": "Feature",
  "properties": {
    "addr:full":"Alam Sundheim, 30 Huelva Huelva 21003",
    "addr:housenumber":"30",
    "addr:postcode":"21003",
    "addr:street":"Alam Sundheim",
    "iso:country":"ES",
    "sg:address":"Alam Sundheim, 30",
    "sg:city":"Huelva",
    "sg:orig_category":"M\u00c9dicos: Cirug\u00cda Pl\u00c1stica, Reconstructiva Y Est\u00c9tica",
    "sg:phone":"+34 959 54 23 40",
    "sg:postcode":"21003",
    "sg:province":"Huelva",
    "wof:name":"Corporacion Dermoestetica S.a.",
    "wof:placetype":"venue"
},
  "geometry": {"coordinates":[-6.9495940208,37.256313324],"type":"Point"}
}