{
  "type": "Feature",
  "properties": {
    "iso:country":"ES",
    "sg:address":"Avda Emilio Castelar, 37",
    "sg:city":"S. Pedro Pinatar",
    "sg:orig_category":"Molduras, Junquillos, Listones Y Molduras Perforadas",
    "sg:phone":"+34 968 18 57 62",
    "sg:postcode":"30740",
    "sg:province":"Murcia",
    "wof:name":"Sanchez Garcia Jose Joaquin",
    "wof:placetype":"venue"
},
  "geometry": {"coordinates":[-0.7883080244,37.8293991089],"type":"Point"}
}