{
  "type": "Feature",
  "properties": {
    "iso:country":"ES",
    "sg:address":"Ctra Barcelona, 19",
    "sg:city":"Centre Urba",
    "sg:orig_category":"Arquitectos",
    "sg:phone":"+34 972 71 50 14",
    "sg:postcode":"17500",
    "sg:province":"Girona",
    "wof:name":"Arquitectura Del Ambiente S.l.",
    "wof:placetype":"venue"
},
  "geometry": {"coordinates":[2.8236999512,41.9817962646],"type":"Point"}
}