{
  "type": "Feature",
  "properties": {
    "iso:country":"ES",
    "sg:address":"Calle de Domingo Arroquia, 20",
    "sg:city":"Jodar",
    "sg:orig_category":"Organizaciones Profesionales",
    "sg:phone":"+34 953 78 61 19",
    "sg:postcode":"23500",
    "sg:province":"Ja\u00e9n",
    "wof:name":"Pastrana Herrera Diego",
    "wof:placetype":"venue"
},
  "geometry": {"coordinates":[-3.3528285027,37.8378067017],"type":"Point"}
}