{
  "type": "Feature",
  "properties": {
    "addr:full":"Avda Cesareo Alierta, 16 Zaragoza Zaragoza 50008",
    "addr:housenumber":"16",
    "addr:postcode":"50008",
    "addr:street":"Avda Cesareo Alierta",
    "iso:country":"ES",
    "sg:address":"Avda Cesareo Alierta, 16",
    "sg:city":"Zaragoza",
    "sg:orig_category":"Suministros Para Hoteles",
    "sg:phone":"+34 976 30 26 85",
    "sg:postcode":"50008",
    "sg:province":"Zaragoza",
    "wof:name":"Servinagar Sl",
    "wof:placetype":"venue"
},
  "geometry": {"coordinates":[-0.8787479997,41.645816803],"type":"Point"}
}