{
  "type": "Feature",
  "properties": {
    "iso:country":"ES",
    "sg:address":"Carrer de Joanot Martorell, 30",
    "sg:city":"Sabadell",
    "sg:orig_category":"Electricidad, Electr\u00d3nica: Suministros (al Por Menor)",
    "sg:phone":"+34 937 11 34 40",
    "sg:postcode":"08203",
    "sg:province":"Barcelona",
    "wof:name":"Dasa Electricidad Y Electronica Industrial S.l.",
    "wof:placetype":"venue"
},
  "geometry": {"coordinates":[2.1053171158,41.5340194702],"type":"Point"}
}