{
  "type": "Feature",
  "properties": {
    "iso:country":"ES",
    "sg:address":"Calle de San Juan Bautista, 4",
    "sg:city":"Santa Cruz De Tenerife",
    "sg:orig_category":"Cl\u00cdnicas Dentales",
    "sg:phone":"+34 922 24 24 03",
    "sg:postcode":"38002",
    "sg:province":"Santa Cruz De Tenerife",
    "wof:name":"Martos Fragoso Pedro Luis",
    "wof:placetype":"venue"
},
  "geometry": {"coordinates":[-16.2490940094,28.4686717987],"type":"Point"}
}