{
  "type": "Feature",
  "properties": {
    "addr:full":"Calle de Galindos, 52 S. Clemente Cuenca 16600",
    "addr:housenumber":"52",
    "addr:postcode":"16600",
    "addr:street":"Calle De Galindos;S. Clemente Cuenca",
    "iso:country":"ES",
    "sg:address":"Calle de Galindos, 52",
    "sg:city":"S. Clemente",
    "sg:orig_category":"Productos Qu\u00cdmicos (fabricaci\u00d3n, Al Por Mayor)",
    "sg:phone":"+34 969 30 24 47",
    "sg:postcode":"16600",
    "sg:province":"Cuenca",
    "wof:name":"Laboratorios Sepulveda S.l.",
    "wof:placetype":"venue"
},
  "geometry": {"coordinates":[-2.4304618835,39.400604248],"type":"Point"}
}