{
  "type": "Feature",
  "properties": {
    "iso:country":"ES",
    "sg:address":"Carrer de Germans Thos I Codina, 51",
    "sg:city":"Mataro",
    "sg:orig_category":"Moda",
    "sg:phone":"+34 937 57 22 79",
    "sg:postcode":"08302",
    "sg:province":"Barcelona",
    "sg:website":"www.suindocor.com",
    "wof:name":"Docor S.l.",
    "wof:placetype":"venue"
},
  "geometry": {"coordinates":[2.4402151108,41.5317344666],"type":"Point"}
}