{
  "type": "Feature",
  "properties": {
    "addr:full":"C/ Anselm Clave, 3 Ripollet Barcelona 08291",
    "addr:housenumber":"3",
    "addr:postcode":"08291",
    "addr:street":"C / Anselm Clave",
    "iso:country":"ES",
    "sg:address":"C/ Anselm Clave, 3",
    "sg:city":"Ripollet",
    "sg:orig_category":"Concepci\u00d3n Y Realizaci\u00d3n De Maquetas Profesionales Y Prototipos",
    "sg:phone":"+34 935 92 22 00",
    "sg:postcode":"08291",
    "sg:province":"Barcelona",
    "sg:website":"www.portellmaquetes.com",
    "wof:name":"Portell Maquetas S.l.",
    "wof:placetype":"venue"
},
  "geometry": {"coordinates":[2.155600071,41.497718811],"type":"Point"}
}