{
  "type": "Feature",
  "properties": {
    "iso:country":"ES",
    "sg:address":"Calle de Sargento Llagas, 45",
    "sg:city":"Palmas De Gran Canaria",
    "sg:orig_category":"Restaurantes",
    "sg:phone":"+34 928 26 42 42",
    "sg:postcode":"35007",
    "sg:province":"Las Palmas",
    "wof:name":"Alvarez Chacon Manuel",
    "wof:placetype":"venue"
},
  "geometry": {"coordinates":[-15.4356060028,28.1404800415],"type":"Point"}
}