{
  "type": "Feature",
  "properties": {
    "addr:full":"Centeans (pontellas), S/n Centeans Pontevedra 36412",
    "addr:postcode":"36412",
    "addr:street":"Pontellas S / N",
    "iso:country":"ES",
    "sg:address":"Centeans (pontellas), S/n",
    "sg:city":"Centeans",
    "sg:orig_category":"Deportes Y Programas De Aventura",
    "sg:phone":"+34 986 33 03 97",
    "sg:postcode":"36412",
    "sg:province":"Pontevedra",
    "wof:name":"Club Deportivo Pontellas",
    "wof:placetype":"venue"
},
  "geometry": {"coordinates":[-8.6552791595,42.1265144348],"type":"Point"}
}