{
  "type": "Feature",
  "properties": {
    "iso:country":"ES",
    "sg:address":"Calle de Stuart (de), 94",
    "sg:city":"Aranjuez",
    "sg:orig_category":"Complementos De Vestir (al Por Menor)",
    "sg:phone":"+34 918 92 41 61",
    "sg:postcode":"28300",
    "sg:province":"Madrid",
    "wof:name":"Ascension Y Carmen Sanchez Nu\u00f1ez C.b.",
    "wof:placetype":"venue"
},
  "geometry": {"coordinates":[-3.6036336422,40.0326042175],"type":"Point"}
}