{
  "type": "Feature",
  "properties": {
    "addr:full":"Avda Castros (los), 77 Santander Cantabria 39005",
    "addr:housenumber":"77",
    "addr:postcode":"39005",
    "addr:street":"Avda Castros Los",
    "iso:country":"ES",
    "sg:address":"Avda Castros (los), 77",
    "sg:city":"Santander",
    "sg:orig_category":"Venta, Instalaci\u00d3n, Reparaci\u00d3n De Antenas Para Televisi\u00d3n",
    "sg:phone":"+34 942 22 00 59",
    "sg:postcode":"39005",
    "sg:province":"Cantabria",
    "wof:name":"Simal Menendez Antonio",
    "wof:placetype":"venue"
},
  "geometry": {"coordinates":[-3.8097450733,43.4695320129],"type":"Point"}
}