{
  "type": "Feature",
  "properties": {
    "addr:full":"Carr Velazquez, 3 Port D'andratx Islas Baleares 07157",
    "addr:housenumber":"3",
    "addr:postcode":"07157",
    "addr:street":"Carr Velazquez",
    "iso:country":"ES",
    "sg:address":"Carr Velazquez, 3",
    "sg:city":"Port D'andratx",
    "sg:orig_category":"Inmobiliaria (agencias)",
    "sg:phone":"+34 971 67 23 73",
    "sg:postcode":"07157",
    "sg:province":"Islas Baleares",
    "wof:name":"Tusculom Mediterraneo,s.l.",
    "wof:placetype":"venue"
},
  "geometry": {"coordinates":[2.378344059,39.5584831238],"type":"Point"}
}