{
  "type": "Feature",
  "properties": {
    "addr:full":"Carrer de Arquitecte Jujol, 13 Eres Tarragona 43839",
    "addr:housenumber":"13",
    "addr:postcode":"43839",
    "addr:street":"Carrer De Arquitecte Jujol",
    "iso:country":"ES",
    "sg:address":"Carrer de Arquitecte Jujol, 13",
    "sg:city":"Eres",
    "sg:orig_category":"Inmobiliaria (agencias)",
    "sg:phone":"+34 977 80 11 08",
    "sg:postcode":"43839",
    "sg:province":"Tarragona",
    "wof:name":"Creixell Actividades S.l.",
    "wof:placetype":"venue"
},
  "geometry": {"coordinates":[1.4396950006,41.1629600525],"type":"Point"}
}