{
  "type": "Feature",
  "properties": {
    "iso:country":"ES",
    "sg:address":"Calle de Chinarral, 76",
    "sg:city":"Guijuelo",
    "sg:orig_category":"Fabrica De Charcuter\u00cda",
    "sg:phone":"+34 923 58 15 32",
    "sg:postcode":"37770",
    "sg:province":"Salamanca",
    "wof:name":"Juansi S.a.",
    "wof:placetype":"venue"
},
  "geometry": {"coordinates":[-5.6733493805,40.5534210205],"type":"Point"}
}