{
  "type": "Feature",
  "properties": {
    "addr:full":"Calle de Artesania, 2 Ubeda Ja\u00e9n 23400",
    "addr:housenumber":"2",
    "addr:postcode":"23400",
    "addr:street":"Calle De Artesania;Jae\u0301N",
    "iso:country":"ES",
    "sg:address":"Calle de Artesania, 2",
    "sg:city":"Ubeda",
    "sg:orig_category":"Material Y Herramientas Agr\u00cdcolas",
    "sg:phone":"+34 953 79 30 69",
    "sg:postcode":"23400",
    "sg:province":"Ja\u00e9n",
    "wof:name":"Jucamp Motores Y Recambios S.l.",
    "wof:placetype":"venue"
},
  "geometry": {"coordinates":[-3.3683433533,38.0248451233],"type":"Point"}
}