{
  "type": "Feature",
  "properties": {
    "addr:full":"Ctra Villena, Km. 0026,0 Bocairent Valencia 46880",
    "addr:postcode":"46880",
    "addr:street":"Ctra Villena Km. 0026,0",
    "iso:country":"ES",
    "sg:address":"Ctra Villena, Km. 0026,0",
    "sg:city":"Bocairent",
    "sg:orig_category":"Carpinteros",
    "sg:phone":"+34 962 35 03 28",
    "sg:postcode":"46880",
    "sg:province":"Valencia",
    "wof:name":"Carpinteria P.v.c. Bocairent S.a.",
    "wof:placetype":"venue"
},
  "geometry": {"coordinates":[-0.6109189987,38.7625846863],"type":"Point"}
}