{
  "type": "Feature",
  "properties": {
    "addr:full":"C/ Angel Guimera, 12 Calonge Girona 17251",
    "addr:housenumber":"12",
    "addr:postcode":"17251",
    "addr:street":"C / Angel Guimera",
    "iso:country":"ES",
    "sg:address":"C/ Angel Guimera, 12",
    "sg:city":"Calonge",
    "sg:orig_category":"Reposter\u00cdas",
    "sg:phone":"+34 972 66 08 74",
    "sg:postcode":"17251",
    "sg:province":"Girona",
    "wof:name":"El Forn Nou S.l.",
    "wof:placetype":"venue"
},
  "geometry": {"coordinates":[3.0734000206,41.8622703552],"type":"Point"}
}