{
  "type": "Feature",
  "properties": {
    "addr:full":"Calle de Hixen I, S/n Cordoba C\u00f3rdoba 14009",
    "addr:housenumber":"s",
    "addr:postcode":"14009",
    "addr:street":"Calle De Hixen I;/ N;Co\u0301Rdoba",
    "iso:country":"ES",
    "sg:address":"Calle de Hixen I, S/n",
    "sg:city":"Cordoba",
    "sg:orig_category":"Centros De Educaci\u00d3n Especial",
    "sg:phone":"+34 957 29 23 80",
    "sg:postcode":"14009",
    "sg:province":"C\u00f3rdoba",
    "wof:name":"Junta De Andalucia",
    "wof:placetype":"venue"
},
  "geometry": {"coordinates":[-4.7704138756,37.8649406433],"type":"Point"}
}