{
  "type": "Feature",
  "properties": {
    "iso:country":"ES",
    "sg:address":"Calle de Villas De Guadalix, 59",
    "sg:city":"Guadalix De La Sierra",
    "sg:orig_category":"Mayoristas E Intermediarios En Alcoholes",
    "sg:phone":"+34 918 47 02 03",
    "sg:postcode":"28794",
    "sg:province":"Madrid",
    "wof:name":"Lopez Castillo Cesareo",
    "wof:placetype":"venue"
},
  "geometry": {"coordinates":[-3.7051579952,40.7848091125],"type":"Point"}
}