{
  "type": "Feature",
  "properties": {
    "addr:full":"Calle de Pericles, 15 Madrid Madrid 28011",
    "addr:housenumber":"15",
    "addr:postcode":"madrid;28011",
    "addr:street":"Calle De Pericles",
    "iso:country":"ES",
    "sg:address":"Calle de Pericles, 15",
    "sg:city":"Madrid",
    "sg:orig_category":"Peluqueros: De Se\u00d1oras",
    "sg:phone":"+34 914 79 46 05",
    "sg:postcode":"28011",
    "sg:province":"Madrid",
    "wof:name":"Picazo Velazquez Concepcion",
    "wof:placetype":"venue"
},
  "geometry": {"coordinates":[-3.7312810421,40.4090957642],"type":"Point"}
}