{
  "type": "Feature",
  "properties": {
    "addr:full":"Calle de Santiago, 3 Madrid Madrid 28013",
    "addr:housenumber":"3",
    "addr:postcode":"28013",
    "addr:street":"Calle De Santiago",
    "iso:country":"ES",
    "sg:address":"Calle de Santiago, 3",
    "sg:city":"Madrid",
    "sg:orig_category":"Ense\u00d1anza: Idiomas",
    "sg:phone":"+34 915 59 32 61",
    "sg:postcode":"28013",
    "sg:province":"Madrid",
    "wof:name":"Hispania Estudio 2 Cb",
    "wof:placetype":"venue"
},
  "geometry": {"coordinates":[-3.7100610733,40.416179657],"type":"Point"}
}