{
  "type": "Feature",
  "properties": {
    "iso:country":"ES",
    "sg:address":"Calle de Princesa Mercedes, 8",
    "sg:city":"Alacant",
    "sg:orig_category":"Comercio De Piezas De Recambio Y De Accesorios De Veh\u00cdculos, Veh\u00cdculos Industriales",
    "sg:phone":"+34 965 10 78 15",
    "sg:postcode":"03006",
    "sg:province":"Alicante",
    "wof:name":"Motrasa Motor S.l.",
    "wof:placetype":"venue"
},
  "geometry": {"coordinates":[-0.5038847923,38.3454170227],"type":"Point"}
}