{
  "type": "Feature",
  "properties": {
    "addr:full":"Calle de Abdon Bordoy (de), 7 Aranjuez Madrid 28300",
    "addr:housenumber":"7",
    "addr:postcode":"28300",
    "addr:street":"Calle De Abdon Bordoy De",
    "iso:country":"ES",
    "sg:address":"Calle de Abdon Bordoy (de), 7",
    "sg:city":"Aranjuez",
    "sg:orig_category":"Peluquer\u00cdas, Peluquer\u00cda Mixta",
    "sg:phone":"+34 918 92 33 74",
    "sg:postcode":"28300",
    "sg:province":"Madrid",
    "wof:name":"Lara Jimenez Diego Antonio",
    "wof:placetype":"venue"
},
  "geometry": {"coordinates":[-3.5932741165,40.0318374634],"type":"Point"}
}