{
  "type": "Feature",
  "properties": {
    "iso:country":"ES",
    "sg:address":"Calle de Villafranca, 8",
    "sg:city":"Le\u00f3n",
    "sg:orig_category":"Transporte En General",
    "sg:phone":"+34 987 25 25 20",
    "sg:postcode":"24001",
    "sg:province":"Le\u00f3n",
    "wof:name":"Anto\u00f1anzas Arias Manuel",
    "wof:placetype":"venue"
},
  "geometry": {"coordinates":[-5.5756225586,42.5958137512],"type":"Point"}
}