{
  "type": "Feature",
  "properties": {
    "iso:country":"ES",
    "sg:address":"Calle de Miguel Morlan, 22",
    "sg:city":"Villanueva Alcardete",
    "sg:orig_category":"Molduras, Junquillos, Listones Y Molduras Perforadas",
    "sg:phone":"+34 925 16 70 54",
    "sg:postcode":"45810",
    "sg:province":"Toledo",
    "wof:name":"Martinez Quintanar Gabriel",
    "wof:placetype":"venue"
},
  "geometry": {"coordinates":[-3.0135109425,39.6696968079],"type":"Point"}
}