{
  "type": "Feature",
  "properties": {
    "addr:full":"Calle de Jabonerias, 51 Cartagena Murcia 30201",
    "addr:housenumber":"51",
    "addr:postcode":"30201",
    "addr:street":"Calle De Jabonerias",
    "iso:country":"ES",
    "sg:address":"Calle de Jabonerias, 51",
    "sg:city":"Cartagena",
    "sg:orig_category":"Tintes (fabricaci\u00d3n, Al Por Mayor)",
    "sg:phone":"+34 968 50 34 26",
    "sg:postcode":"30201",
    "sg:province":"Murcia",
    "wof:name":"Tintoreria Castilla C.b.",
    "wof:placetype":"venue"
},
  "geometry": {"coordinates":[-0.9900889993,37.6042900085],"type":"Point"}
}