{
  "type": "Feature",
  "properties": {
    "iso:country":"ES",
    "sg:address":"Avda Anaga (de), S/n",
    "sg:city":"Santa Cruz De Tenerife",
    "sg:orig_category":"Informaci\u00d3n Financiera Y Comercial",
    "sg:phone":"+34 922 59 60 36",
    "sg:postcode":"38001",
    "sg:province":"Santa Cruz De Tenerife",
    "wof:name":"Contenerfrut S. A.",
    "wof:placetype":"venue"
},
  "geometry": {"coordinates":[-16.2429141998,28.4789600372],"type":"Point"}
}