{
  "type": "Feature",
  "properties": {
    "iso:country":"ES",
    "sg:address":"Calle de Urruchite, 2",
    "sg:city":"Ribabellosa",
    "sg:orig_category":"Empresarios Y Productoras De Espect\u00c1culos",
    "sg:phone":"+34 945 35 51 97",
    "sg:postcode":"01213",
    "sg:province":"\u00c1lava",
    "wof:name":"Be Magic S.l.",
    "wof:placetype":"venue"
},
  "geometry": {"coordinates":[-2.9184379578,42.7114753723],"type":"Point"}
}