{
  "type": "Feature",
  "properties": {
    "iso:country":"ES",
    "sg:address":"Plaz San Vicente De Paul, 6",
    "sg:city":"Madrid",
    "sg:orig_category":"Centros Empresariales",
    "sg:phone":"+34 914 60 54 99",
    "sg:postcode":"28025",
    "sg:province":"Madrid",
    "wof:name":"Carrilero Hermosin Ricardo",
    "wof:placetype":"venue"
},
  "geometry": {"coordinates":[-3.7261579037,40.3856391907],"type":"Point"}
}