{
  "type": "Feature",
  "properties": {
    "iso:country":"ES",
    "sg:address":"Calle de Sierra De Tonda, 67",
    "sg:city":"Guijuelo",
    "sg:orig_category":"Fabrica De Charcuter\u00cda",
    "sg:phone":"+34 923 15 80 27",
    "sg:postcode":"37770",
    "sg:province":"Salamanca",
    "wof:name":"Anral S.l.",
    "wof:placetype":"venue"
},
  "geometry": {"coordinates":[-5.677772522,40.5375518799],"type":"Point"}
}