{
  "type": "Feature",
  "properties": {
    "iso:country":"ES",
    "sg:address":"Calle de Cabo Touri\u00d1ana, S/n",
    "sg:city":"Algeciras",
    "sg:orig_category":"Ense\u00d1anza, Formaci\u00d3n Profesional: Aprendizaje",
    "sg:phone":"+34 956 65 31 45",
    "sg:postcode":"11205",
    "sg:province":"C\u00e1diz",
    "wof:name":"Empresa Municipal De Aguas De Algeciras",
    "wof:placetype":"venue"
},
  "geometry": {"coordinates":[-5.4403610229,36.1648292542],"type":"Point"}
}