{
  "type": "Feature",
  "properties": {
    "iso:country":"ES",
    "sg:address":"Carr Assumpcio, 2",
    "sg:city":"Villarreal",
    "sg:orig_category":"Art\u00cdculos Funerarios (al Por Menor)",
    "sg:phone":"+34 964 52 15 10",
    "sg:postcode":"12540",
    "sg:province":"Castell\u00f3n",
    "wof:name":"Funeraria La Magdalena S.l.",
    "wof:placetype":"venue"
},
  "geometry": {"coordinates":[-0.0952939987,39.9453048706],"type":"Point"}
}