{
  "type": "Feature",
  "properties": {
    "addr:full":"Carrer de Tenor Josep Foraste (del), 6 Vila-seca Tarragona 43480",
    "addr:housenumber":"6",
    "addr:postcode":"43480",
    "addr:street":"Carrer De Tenor Josep Foraste Del",
    "iso:country":"ES",
    "sg:address":"Carrer de Tenor Josep Foraste (del), 6",
    "sg:city":"Vila-seca",
    "sg:orig_category":"Negocio De Materiales De Construcci\u00d3n",
    "sg:phone":"+34 977 39 19 66",
    "sg:postcode":"43480",
    "sg:province":"Tarragona",
    "wof:name":"Granitos Perez S.l.",
    "wof:placetype":"venue"
},
  "geometry": {"coordinates":[1.14882195,41.1128158569],"type":"Point"}
}