{
  "type": "Feature",
  "properties": {
    "addr:full":"Calle de Julio Caro Baroja, 16 Madrid Madrid 28050",
    "addr:housenumber":"16",
    "addr:postcode":"madrid;28050",
    "addr:street":"Calle De Julio Caro Baroja",
    "iso:country":"ES",
    "sg:address":"Calle de Julio Caro Baroja, 16",
    "sg:city":"Madrid",
    "sg:orig_category":"Asesor\u00cda De Comercio Exterior",
    "sg:phone":"+34 916 50 84 73",
    "sg:postcode":"28050",
    "sg:province":"Madrid",
    "wof:name":"Diaz-galvez Camara Javier",
    "wof:placetype":"venue"
},
  "geometry": {"coordinates":[-3.6458799839,40.5080566406],"type":"Point"}
}