{
  "type": "Feature",
  "properties": {
    "iso:country":"ES",
    "sg:address":"Calle de Escosura, 21",
    "sg:city":"Madrid",
    "sg:orig_category":"Traductores",
    "sg:phone":"+34 914 47 15 77",
    "sg:postcode":"28015",
    "sg:province":"Madrid",
    "wof:name":"Beeson  Diane Kay",
    "wof:placetype":"venue"
},
  "geometry": {"coordinates":[-3.7069621086,40.4357872009],"type":"Point"}
}