{
  "type": "Feature",
  "properties": {
    "iso:country":"ES",
    "sg:address":"Calle de Fernando Mugica, 10",
    "sg:city":"Donostia-san Sebastian",
    "sg:orig_category":"Suministros Y Materiales Industriales",
    "sg:phone":"+34 943 37 68 75",
    "sg:postcode":"20018",
    "sg:province":"Guip\u00f9zcoa",
    "wof:name":"Suministros Aguado S.l.",
    "wof:placetype":"venue"
},
  "geometry": {"coordinates":[-2.0164999962,43.2807617188],"type":"Point"}
}