{
  "type": "Feature",
  "properties": {
    "iso:country":"ES",
    "sg:address":"Pla\u00c7 Josep Pla I Casadevall, 4",
    "sg:city":"Girona",
    "sg:orig_category":"Abogados",
    "sg:phone":"+34 972 48 32 53",
    "sg:postcode":"17001",
    "sg:province":"Girona",
    "wof:name":"Poch Musquera Josep",
    "wof:placetype":"venue"
},
  "geometry": {"coordinates":[2.8187448978,41.9808616638],"type":"Point"}
}