{
  "type": "Feature",
  "properties": {
    "addr:full":"Calle de Figon, 7 Sotogrande C\u00e1diz 11310",
    "addr:housenumber":"7",
    "addr:postcode":"11310",
    "addr:street":"Calle De Figon;Ca\u0301Diz",
    "iso:country":"ES",
    "sg:address":"Calle de Figon, 7",
    "sg:city":"Sotogrande",
    "sg:orig_category":"Perfumer\u00cda Y Cosm\u00c9tica (fabricaci\u00d3n, Al Por Mayor)",
    "sg:phone":"+34 956 69 50 50",
    "sg:postcode":"11310",
    "sg:province":"C\u00e1diz",
    "wof:name":"Isis Food Espa\u00f1a S.l.",
    "wof:placetype":"venue"
},
  "geometry": {"coordinates":[-5.3333239555,36.2772903442],"type":"Point"}
}