{
  "type": "Feature",
  "properties": {
    "addr:full":"Claveles(s Y Zaraiche), 9 Murcia Murcia 30007",
    "addr:housenumber":"9",
    "addr:postcode":"30007",
    "addr:street":"Claveles S Y Zaraiche",
    "iso:country":"ES",
    "sg:address":"Claveles(s Y Zaraiche), 9",
    "sg:city":"Murcia",
    "sg:orig_category":"Mercer\u00cda, Lencer\u00cda (al Por Menor)",
    "sg:phone":"+34 968 20 18 11",
    "sg:postcode":"30007",
    "sg:province":"Murcia",
    "wof:name":"Comercial Zaraiche C.b.",
    "wof:placetype":"venue"
},
  "geometry": {"coordinates":[-1.1255710125,38.0013923645],"type":"Point"}
}