{
  "type": "Feature",
  "properties": {
    "addr:full":"Calle de Carretera General, 6 Unquera Cantabria 39560",
    "addr:housenumber":"6",
    "addr:postcode":"39560",
    "addr:street":"Calle De Carretera General",
    "iso:country":"ES",
    "sg:address":"Calle de Carretera General, 6",
    "sg:city":"Unquera",
    "sg:orig_category":"Mercer\u00cda, Lencer\u00cda (al Por Menor)",
    "sg:phone":"+34 942 71 70 55",
    "sg:postcode":"39560",
    "sg:province":"Cantabria",
    "wof:name":"Soberon Cotera Maria Cristina",
    "wof:placetype":"venue"
},
  "geometry": {"coordinates":[-4.5151238441,43.3745231628],"type":"Point"}
}