{
  "type": "Feature",
  "properties": {
    "addr:full":"Carrer de Jaume Balmes, 58 Palma Islas Baleares 07004",
    "addr:housenumber":"58",
    "addr:postcode":"07004",
    "addr:street":"Carrer De Jaume Balmes",
    "iso:country":"ES",
    "sg:address":"Carrer de Jaume Balmes, 58",
    "sg:city":"Palma",
    "sg:orig_category":"Procuradores",
    "sg:phone":"+34 971 29 61 09",
    "sg:postcode":"07004",
    "sg:province":"Islas Baleares",
    "wof:name":"Bauza Roldan Hector",
    "wof:placetype":"venue"
},
  "geometry": {"coordinates":[2.6566870213,39.5810127258],"type":"Point"}
}