{
  "type": "Feature",
  "properties": {
    "addr:full":"Avda Angel, 45 Getxo Vizcaya 48990",
    "addr:housenumber":"45",
    "addr:postcode":"48990",
    "addr:street":"Avda Angel",
    "iso:country":"ES",
    "sg:address":"Avda Angel, 45",
    "sg:city":"Getxo",
    "sg:orig_category":"Reposter\u00cdas",
    "sg:phone":"+34 944 60 90 79",
    "sg:postcode":"48990",
    "sg:province":"Vizcaya",
    "wof:name":"Igone Ateka Zalbidea",
    "wof:placetype":"venue"
},
  "geometry": {"coordinates":[-3.0162088871,43.3613433838],"type":"Point"}
}