{
  "type": "Feature",
  "properties": {
    "addr:full":"Plaz Espa\u00d1a, S/n Campillos M\u00e1laga 29320",
    "addr:housenumber":"s / n",
    "addr:postcode":"29320",
    "addr:street":"Plaz Espan\u0303A",
    "iso:country":"ES",
    "sg:address":"Plaz Espa\u00d1a, S/n",
    "sg:city":"Campillos",
    "sg:orig_category":"Peluqueros: De Se\u00d1oras",
    "sg:phone":"+34 952 72 31 21",
    "sg:postcode":"29320",
    "sg:province":"M\u00e1laga",
    "wof:name":"Romero Villanueva Isabel",
    "wof:placetype":"venue"
},
  "geometry": {"coordinates":[-4.8618388176,37.0470275879],"type":"Point"}
}