{
  "type": "Feature",
  "properties": {
    "addr:full":"Calle de Escultor Fernandez Marquez, 1 Cordoba C\u00f3rdoba 14012",
    "addr:housenumber":"1",
    "addr:postcode":"14012",
    "addr:street":"Calle De Escultor Fernandez Marquez;Co\u0301Rdoba",
    "iso:country":"ES",
    "sg:address":"Calle de Escultor Fernandez Marquez, 1",
    "sg:city":"Cordoba",
    "sg:orig_category":"Aceites Y Grasas Alimentarias (fabricaci\u00d3n, Al Por Mayor)",
    "sg:phone":"+34 957 27 19 39",
    "sg:postcode":"14012",
    "sg:province":"C\u00f3rdoba",
    "wof:name":"Juan Delgado Carvajal S.l.",
    "wof:placetype":"venue"
},
  "geometry": {"coordinates":[-4.7848992348,37.8982887268],"type":"Point"}
}