{
  "type": "Feature",
  "properties": {
    "addr:full":"Carrer de Diputacio, 308 Barcelona Barcelona 08009",
    "addr:housenumber":"308",
    "addr:postcode":"08009",
    "addr:street":"Carrer De Diputacio",
    "iso:country":"ES",
    "sg:address":"Carrer de Diputacio, 308",
    "sg:city":"Barcelona",
    "sg:orig_category":"Asesor\u00cda Fiscal Y Jur\u00cddica",
    "sg:phone":"+34 934 12 68 69",
    "sg:postcode":"08009",
    "sg:province":"Barcelona",
    "sg:website":"www.vwergara-asesores.com",
    "wof:name":"Bernal Vergara Eduardo",
    "wof:placetype":"venue"
},
  "geometry": {"coordinates":[2.1718220711,41.3937988281],"type":"Point"}
}