{
  "type": "Feature",
  "properties": {
    "iso:country":"ES",
    "sg:address":"Carrer de Sant Roc, 49",
    "sg:city":"Benidorm",
    "sg:orig_category":"Asesor\u00cda Fiscal Y Jur\u00cddica",
    "sg:phone":"+34 966 80 23 23",
    "sg:postcode":"03500",
    "sg:province":"Alicante",
    "wof:name":"Taibe Asesores S.l.",
    "wof:placetype":"venue"
},
  "geometry": {"coordinates":[-0.130200997,38.5385742188],"type":"Point"}
}