{
  "type": "Feature",
  "properties": {
    "addr:full":"Calle de Benisoda, 15 Valencia Valencia 46022",
    "addr:housenumber":"15",
    "addr:postcode":"46022",
    "addr:street":"Calle De Benisoda",
    "iso:country":"ES",
    "sg:address":"Calle de Benisoda, 15",
    "sg:city":"Valencia",
    "sg:orig_category":"Muebles, Minoristas",
    "sg:phone":"+34 963 71 37 71",
    "sg:postcode":"46022",
    "sg:province":"Valencia",
    "wof:name":"Muebles Caba\u00f1al S.l.",
    "wof:placetype":"venue"
},
  "geometry": {"coordinates":[-0.3350330889,39.4720420837],"type":"Point"}
}