{
  "type": "Feature",
  "properties": {
    "iso:country":"ES",
    "sg:address":"Calle de Quevedo, 2",
    "sg:city":"Villanueva Cordoba",
    "sg:orig_category":"Sanatorios M\u00c9dico",
    "sg:phone":"+34 957 12 12 35",
    "sg:postcode":"14440",
    "sg:province":"C\u00f3rdoba",
    "wof:name":"Servicio Andaluz De Salud",
    "wof:placetype":"venue"
},
  "geometry": {"coordinates":[-4.6281270981,38.32371521],"type":"Point"}
}