{
  "type": "Feature",
  "properties": {
    "iso:country":"ES",
    "sg:address":"Calle de Menendez Pidal, 17",
    "sg:city":"Almoradi",
    "sg:orig_category":"Ropa Para Se\u00d1oras Y Caballeros (al Por Menor)",
    "sg:phone":"+34 966 78 11 71",
    "sg:postcode":"03160",
    "sg:province":"Alicante",
    "wof:name":"Berenguer Hernandez Jose Antonio S.l.n.e",
    "wof:placetype":"venue"
},
  "geometry": {"coordinates":[-0.7863209844,38.1085281372],"type":"Point"}
}