{
  "type": "Feature",
  "properties": {
    "addr:full":"Carr Colom, (de), 125 Carlet Valencia 46240",
    "addr:housenumber":"125",
    "addr:postcode":"46240",
    "addr:street":"Carr Colom De",
    "iso:country":"ES",
    "sg:address":"Carr Colom, (de), 125",
    "sg:city":"Carlet",
    "sg:orig_category":"Reposter\u00cdas",
    "sg:phone":"+34 962 53 16 71",
    "sg:postcode":"46240",
    "sg:province":"Valencia",
    "wof:name":"Rosello Machi Vicente",
    "wof:placetype":"venue"
},
  "geometry": {"coordinates":[-0.5209739804,39.2250289917],"type":"Point"}
}