{
  "type": "Feature",
  "properties": {
    "addr:full":"Carrer de Puig Major, 55 Sabadell Barcelona 08207",
    "addr:housenumber":"55",
    "addr:postcode":"08207",
    "addr:street":"Carrer De Puig Major",
    "iso:country":"ES",
    "sg:address":"Carrer de Puig Major, 55",
    "sg:city":"Sabadell",
    "sg:orig_category":"Laboratorios Y Trabajos De Fotograf\u00cda, V\u00cddeo Y Cine",
    "sg:phone":"+34 937 23 98 59",
    "sg:postcode":"08207",
    "sg:province":"Barcelona",
    "wof:name":"Vicente Gomez Luis",
    "wof:placetype":"venue"
},
  "geometry": {"coordinates":[2.0857639313,41.5683898926],"type":"Point"}
}