{
  "type": "Feature",
  "properties": {
    "addr:full":"Trva Juan Francisco, 8 Madrid Madrid 28025",
    "addr:housenumber":"8",
    "addr:postcode":"madrid;28025",
    "addr:street":"Trva Juan Francisco",
    "iso:country":"ES",
    "sg:address":"Trva Juan Francisco, 8",
    "sg:city":"Madrid",
    "sg:orig_category":"Radiocomunicaciones, Telefon\u00cda M\u00d3vil, Radiomensajer\u00cda: Servicios, Comercializaci\u00d3n",
    "sg:phone":"+34 914 66 63 78",
    "sg:postcode":"28025",
    "sg:province":"Madrid",
    "wof:name":"International Calls Gimar S.l.",
    "wof:placetype":"venue"
},
  "geometry": {"coordinates":[-3.7319560051,40.386592865],"type":"Point"}
}