{
  "type": "Feature",
  "properties": {
    "addr:full":"Carrer de Sant Eusebi, 53 Barcelona Barcelona 08006",
    "addr:housenumber":"53",
    "addr:postcode":"08006",
    "addr:street":"Carrer De Sant Eusebi",
    "iso:country":"ES",
    "sg:address":"Carrer de Sant Eusebi, 53",
    "sg:city":"Barcelona",
    "sg:classifiers":[
        {
            "category":"Professional",
            "subcategory":"Management & Consulting",
            "type":"Services"
        }
    ],
    "sg:phone":"+34 932 09 15 88",
    "sg:postcode":"08006",
    "sg:province":"Barcelona",
    "sg:tags":[
        "asesor\u00cda",
        "en",
        "marketing"
    ],
    "wof:name":"Larruy S.l.",
    "wof:placetype":"venue"
},
  "geometry": {"coordinates":[2.1467010975,41.3996505737],"type":"Point"}
}