{
  "type": "Feature",
  "properties": {
    "iso:country":"ES",
    "sg:address":"Avda Fernandez Albor, 4",
    "sg:city":"Guarda",
    "sg:orig_category":"Navegaci\u00d3n (equipos Fluviales)",
    "sg:phone":"+34 986 61 10 95",
    "sg:postcode":"36780",
    "sg:province":"Pontevedra",
    "wof:name":"Alonso Martinez Jose",
    "wof:placetype":"venue"
},
  "geometry": {"coordinates":[-8.8767280579,41.8969688416],"type":"Point"}
}