{
  "type": "Feature",
  "properties": {
    "addr:full":"Carrer de Valero, 10 Barcelona Barcelona 08021",
    "addr:housenumber":"10",
    "addr:postcode":"08021",
    "addr:street":"Carrer De Valero",
    "iso:country":"ES",
    "sg:address":"Carrer de Valero, 10",
    "sg:city":"Barcelona",
    "sg:orig_category":"Agencias De Viajes",
    "sg:phone":"+34 932 01 18 70",
    "sg:postcode":"08021",
    "sg:province":"Barcelona",
    "wof:name":"Bru & Bru Sl",
    "wof:placetype":"venue"
},
  "geometry": {"coordinates":[2.1384050846,41.3961601257],"type":"Point"}
}