{
  "type": "Feature",
  "properties": {
    "addr:full":"Barriguelo, 18 Antig\u00fcedad Palencia 34248",
    "addr:housenumber":"18",
    "addr:postcode":"34248",
    "addr:street":"Barriguelo",
    "iso:country":"ES",
    "sg:address":"Barriguelo, 18",
    "sg:city":"Antig\u00fcedad",
    "sg:orig_category":"Centros Empresariales",
    "sg:phone":"+34 979 79 79 41",
    "sg:postcode":"34248",
    "sg:province":"Palencia",
    "wof:name":"Barcenilla De La Cruz Julita",
    "wof:placetype":"venue"
},
  "geometry": {"coordinates":[-4.1233010292,41.9451560974],"type":"Point"}
}