{
  "type": "Feature",
  "properties": {
    "addr:full":"Calle de Antonio Machado, 1 Palencia Palencia 34004",
    "addr:housenumber":"1",
    "addr:postcode":"34004",
    "addr:street":"Calle De Antonio Machado",
    "iso:country":"ES",
    "sg:address":"Calle de Antonio Machado, 1",
    "sg:city":"Palencia",
    "sg:orig_category":"Transporte En General",
    "sg:phone":"+34 979 73 00 66",
    "sg:postcode":"34004",
    "sg:province":"Palencia",
    "wof:name":"Servicios Inmediatos Del Carrion S.%.",
    "wof:placetype":"venue"
},
  "geometry": {"coordinates":[-4.5219159126,42.0035591125],"type":"Point"}
}