{
  "type": "Feature",
  "properties": {
    "addr:full":"Pg Nadal, 26 Sant Feliu Llobregat Barcelona 08980",
    "addr:housenumber":"26",
    "addr:postcode":"08980",
    "addr:street":"Pg Nadal",
    "iso:country":"ES",
    "sg:address":"Pg Nadal, 26",
    "sg:city":"Sant Feliu Llobregat",
    "sg:orig_category":"Ense\u00d1anza: Comercio, Gesti\u00d3n, Inform\u00c1tica",
    "sg:phone":"+34 936 85 47 27",
    "sg:postcode":"08980",
    "sg:province":"Barcelona",
    "wof:name":"Elison Escola Europea De Formacio",
    "wof:placetype":"venue"
},
  "geometry": {"coordinates":[2.0474379063,41.3825378418],"type":"Point"}
}