{
  "type": "Feature",
  "properties": {
    "addr:full":"Calle de Arabial, 94 Granada Granada 18003",
    "addr:housenumber":"94",
    "addr:postcode":"18003",
    "addr:street":"Calle De Arabial",
    "iso:country":"ES",
    "sg:address":"Calle de Arabial, 94",
    "sg:city":"Granada",
    "sg:orig_category":"Cajas De Ahorro",
    "sg:phone":"+34 958 20 97 01",
    "sg:postcode":"18003",
    "sg:province":"Granada",
    "sg:website":"www.lacaixa.es",
    "wof:name":"Caixa D'estalvis I Pensions De Barcelona",
    "wof:placetype":"venue"
},
  "geometry": {"coordinates":[-3.6120541096,37.1777763367],"type":"Point"}
}