{
  "type": "Feature",
  "properties": {
    "addr:full":"Calle de Plaza (de La), 22 Padiernos \u00c1vila 05520",
    "addr:housenumber":"22",
    "addr:postcode":"05520",
    "addr:street":"Calle De Plaza De La",
    "iso:country":"ES",
    "sg:address":"Calle de Plaza (de La), 22",
    "sg:city":"Padiernos",
    "sg:orig_category":"Farmacias",
    "sg:phone":"+34 920 26 55 11",
    "sg:postcode":"05520",
    "sg:province":"\u00c1vila",
    "wof:name":"Garcia Arroyo Maria Sofia",
    "wof:placetype":"venue"
},
  "geometry": {"coordinates":[-4.8461890221,40.6224098206],"type":"Point"}
}