{
  "type": "Feature",
  "properties": {
    "addr:full":"Yebres, S/n Las Medulas Le\u00f3n 24442",
    "addr:housenumber":"/ n",
    "addr:postcode":"24442",
    "addr:street":"Yebres S;Medulas Leo\u0301N",
    "iso:country":"ES",
    "sg:address":"Yebres, S/n",
    "sg:city":"Las Medulas",
    "sg:orig_category":"Asociaciones, Organismos Culturales Y Socioeducativos",
    "sg:phone":"+34 987 42 28 48",
    "sg:postcode":"24442",
    "sg:province":"Le\u00f3n",
    "wof:name":"Instituto De Estudios Bercianos-aula Arqueologica Las Medulas",
    "wof:placetype":"venue"
},
  "geometry": {"coordinates":[-6.7656288147,42.4908943176],"type":"Point"}
}