{
  "type": "Feature",
  "properties": {
    "iso:country":"ES",
    "sg:address":"Pase Marques De Zafra, 44",
    "sg:city":"Madrid",
    "sg:orig_category":"Molduras, Junquillos, Listones Y Molduras Perforadas",
    "sg:phone":"+34 913 56 85 10",
    "sg:postcode":"28028",
    "sg:province":"Madrid",
    "wof:name":"Gallego Santos Maria Sagrario",
    "wof:placetype":"venue"
},
  "geometry": {"coordinates":[-3.6629059315,40.4251899719],"type":"Point"}
}