{
  "type": "Feature",
  "properties": {
    "addr:full":"Calle de Antonio Lopez, 54 Madrid Madrid 28019",
    "addr:housenumber":"54",
    "addr:postcode":"madrid;28019",
    "addr:street":"Calle De Antonio Lopez",
    "iso:country":"ES",
    "sg:address":"Calle de Antonio Lopez, 54",
    "sg:city":"Madrid",
    "sg:orig_category":"Ropa Para Caballeros (al Por Menor)",
    "sg:phone":"+34 915 65 19 48",
    "sg:postcode":"28019",
    "sg:province":"Madrid",
    "wof:name":"Bricio Perez Gloria",
    "wof:placetype":"venue"
},
  "geometry": {"coordinates":[-3.7103745937,40.3951263428],"type":"Point"}
}