{
  "type": "Feature",
  "properties": {
    "addr:full":"Calle de Alta, S/n Bujaraloz Zaragoza 50177",
    "addr:housenumber":"s / n",
    "addr:postcode":"50177",
    "addr:street":"Calle De Alta",
    "iso:country":"ES",
    "sg:address":"Calle de Alta, S/n",
    "sg:city":"Bujaraloz",
    "sg:orig_category":"Poller\u00cda Y Caza (al Por Menor)",
    "sg:phone":"+34 976 17 31 18",
    "sg:postcode":"50177",
    "sg:province":"Zaragoza",
    "wof:name":"Rozas Berenguer Armando",
    "wof:placetype":"venue"
},
  "geometry": {"coordinates":[-0.1560447067,41.4976119995],"type":"Point"}
}