{
  "type": "Feature",
  "properties": {
    "iso:country":"ES",
    "sg:address":"Calle de Bornos, S/n",
    "sg:city":"Pto Real",
    "sg:classifiers":[
        {
            "category":"Autos & Motor Vehicles",
            "subcategory":"Automobile Sales",
            "type":"Retail Goods"
        }
    ],
    "sg:phone":"+34 956 83 34 11",
    "sg:postcode":"11510",
    "sg:province":"C\u00e1diz",
    "wof:name":"Rodriguez Otero Manuel",
    "wof:placetype":"venue"
},
  "geometry": {"coordinates":[-6.1824045181,36.5274887085],"type":"Point"}
}