{
  "type": "Feature",
  "properties": {
    "addr:full":"Moll Barcelona, S/n Barcelona Barcelona 08039",
    "addr:postcode":"08039",
    "addr:street":"Barcelona S / N",
    "iso:country":"ES",
    "sg:address":"Moll Barcelona, S/n",
    "sg:city":"Barcelona",
    "sg:orig_category":"Servicios De Telecomunicaciones",
    "sg:phone":"+34 933 18 59 95",
    "sg:postcode":"08039",
    "sg:province":"Barcelona",
    "wof:name":"At T Global Network Services Espa\u00d1a S.l.",
    "wof:placetype":"venue"
},
  "geometry": {"coordinates":[2.1779949665,41.3738861084],"type":"Point"}
}