{
  "type": "Feature",
  "properties": {
    "addr:full":"Av Ajuntament, 45 Corro D'avall Barcelona 08520",
    "addr:housenumber":"45",
    "addr:postcode":"08520",
    "addr:street":"Av Ajuntament;D'Avall Barcelona",
    "iso:country":"ES",
    "sg:address":"Av Ajuntament, 45",
    "sg:city":"Corro D'avall",
    "sg:orig_category":"Trabajos De Topograf\u00cda",
    "sg:phone":"+34 938 46 56 56",
    "sg:postcode":"08520",
    "sg:province":"Barcelona",
    "wof:name":"Estudio Topografico Styc S.l.",
    "wof:placetype":"venue"
},
  "geometry": {"coordinates":[2.2989888191,41.6362762451],"type":"Point"}
}