{
  "type": "Feature",
  "properties": {
    "addr:full":"Avda Europa, 25 Benidorm Alicante 03500",
    "addr:housenumber":"25",
    "addr:postcode":"03500",
    "addr:street":"Avda Europa",
    "iso:country":"ES",
    "sg:address":"Avda Europa, 25",
    "sg:city":"Benidorm",
    "sg:orig_category":"Empresarios Y Productoras De Espect\u00c1culos",
    "sg:phone":"+34 965 86 75 86",
    "sg:postcode":"03500",
    "sg:province":"Alicante",
    "wof:name":"Enriquez  Maria Rosa",
    "wof:placetype":"venue"
},
  "geometry": {"coordinates":[-0.1203889996,38.5425415039],"type":"Point"}
}