{
  "type": "Feature",
  "properties": {
    "iso:country":"ES",
    "sg:address":"Calle de Camino Real, 88",
    "sg:city":"Bullas",
    "sg:orig_category":"Cooperativas Agr\u00cdcolas",
    "sg:phone":"+34 968 65 53 03",
    "sg:postcode":"30180",
    "sg:province":"Murcia",
    "wof:name":"Cooperativa Agricola Valdespino S.c.l.",
    "wof:placetype":"venue"
},
  "geometry": {"coordinates":[-1.666893959,38.0503196716],"type":"Point"}
}