{
  "type": "Feature",
  "properties": {
    "addr:full":"Calle de Leopoldo Matos, 20 Palmas De Gran Canaria Las Palmas 35006",
    "addr:housenumber":"20",
    "addr:postcode":"35006",
    "addr:street":"Calle De Leopoldo Matos",
    "iso:country":"ES",
    "sg:address":"Calle de Leopoldo Matos, 20",
    "sg:city":"Palmas De Gran Canaria",
    "sg:orig_category":"Ingeniero",
    "sg:phone":"+34 928 29 30 36",
    "sg:postcode":"35006",
    "sg:province":"Las Palmas",
    "wof:name":"Diaz Garcia Juan Antonio",
    "wof:placetype":"venue"
},
  "geometry": {"coordinates":[-15.4325170517,28.1287899017],"type":"Point"}
}