{
  "type": "Feature",
  "properties": {
    "iso:country":"ES",
    "sg:address":"Calle de Jose M. Salaberria, 7",
    "sg:city":"Donostia-san Sebastian",
    "sg:orig_category":"Fabricaci\u00d3n, Venta De Cuadros, Accesorios Para Enmarcar",
    "sg:phone":"+34 943 45 85 06",
    "sg:postcode":"20010",
    "sg:province":"Guip\u00f9zcoa",
    "wof:name":"Gertrudix Alustiza Jesus Maria",
    "wof:placetype":"venue"
},
  "geometry": {"coordinates":[-1.9811010361,43.3086166382],"type":"Point"}
}