{
  "type": "Feature",
  "properties": {
    "iso:country":"ES",
    "sg:address":"Avda Fuente Nueva (de La), 6",
    "sg:city":"San Sebastian De Los Reyes",
    "sg:orig_category":"Mec\u00c1nico Del Autom\u00d3vil",
    "sg:phone":"+34 916 63 78 13",
    "sg:postcode":"28700",
    "sg:province":"Madrid",
    "wof:name":"Industrial De Vehiculos Sanse S.l.",
    "wof:placetype":"venue"
},
  "geometry": {"coordinates":[-3.6137769222,40.5480499268],"type":"Point"}
}