{
  "type": "Feature",
  "properties": {
    "addr:full":"Calle de Monasterio De Rueda, 4 Zaragoza Zaragoza 50007",
    "addr:housenumber":"4",
    "addr:postcode":"50007",
    "addr:street":"Calle De Monasterio De Rueda",
    "iso:country":"ES",
    "sg:address":"Calle de Monasterio De Rueda, 4",
    "sg:city":"Zaragoza",
    "sg:orig_category":"Fabricaci\u00d3n De Art\u00cdculos Y Equipos Deportivos Y De Ocio",
    "sg:phone":"+34 976 27 48 60",
    "sg:postcode":"50007",
    "sg:province":"Zaragoza",
    "wof:name":"Martin Carrasco Francisco",
    "wof:placetype":"venue"
},
  "geometry": {"coordinates":[-0.8833910227,41.6389541626],"type":"Point"}
}