{
  "type": "Feature",
  "properties": {
    "addr:full":"Calle de Escuelas (las), 60 Carlota C\u00f3rdoba 14100",
    "addr:housenumber":"60",
    "addr:postcode":"14100",
    "addr:street":"Calle De Escuelas Las;Co\u0301Rdoba",
    "iso:country":"ES",
    "sg:address":"Calle de Escuelas (las), 60",
    "sg:city":"Carlota",
    "sg:orig_category":"Molduras, Junquillos, Listones Y Molduras Perforadas",
    "sg:phone":"+34 957 30 06 98",
    "sg:postcode":"14100",
    "sg:province":"C\u00f3rdoba",
    "wof:name":"Miranda Carmona Josefa",
    "wof:placetype":"venue"
},
  "geometry": {"coordinates":[-4.9333605766,37.6687088013],"type":"Point"}
}