{
  "type": "Feature",
  "properties": {
    "iso:country":"ES",
    "sg:address":"Calle de Mallorca, 2",
    "sg:city":"Madrid",
    "sg:orig_category":"Asesor\u00cda Sobre Comunicaci\u00d3n De Empresas",
    "sg:phone":"+34 915 30 55 87",
    "sg:postcode":"28012",
    "sg:province":"Madrid",
    "wof:name":"Mago Asesores S.l",
    "wof:placetype":"venue"
},
  "geometry": {"coordinates":[-3.6978945732,40.4071884155],"type":"Point"}
}