{
  "type": "Feature",
  "properties": {
    "addr:full":"Cmno Corte (de La), S/n Alguazas Murcia 30560",
    "addr:postcode":"30560",
    "addr:street":"Cmno Corte De La S / N",
    "iso:country":"ES",
    "sg:address":"Cmno Corte (de La), S/n",
    "sg:city":"Alguazas",
    "sg:orig_category":"Perfumer\u00cda (al Por Menor)",
    "sg:phone":"+34 968 62 02 02",
    "sg:postcode":"30560",
    "sg:province":"Murcia",
    "wof:name":"Araez Alguazas S.l.",
    "wof:placetype":"venue"
},
  "geometry": {"coordinates":[-1.2746607065,38.0615501404],"type":"Point"}
}