{
  "type": "Feature",
  "properties": {
    "iso:country":"ES",
    "sg:address":"Carrer de Industria, 4",
    "sg:city":"Palma",
    "sg:orig_category":"Molduras, Junquillos, Listones Y Molduras Perforadas",
    "sg:phone":"+34 971 28 35 91",
    "sg:postcode":"07013",
    "sg:province":"Islas Baleares",
    "wof:name":"Francisco Zapata Zapata S.l.",
    "wof:placetype":"venue"
},
  "geometry": {"coordinates":[2.6403639317,39.5734863281],"type":"Point"}
}