{
  "type": "Feature",
  "properties": {
    "addr:full":"Calle de Perez Galdos, 5 Bilbao Vizcaya 48010",
    "addr:housenumber":"5",
    "addr:postcode":"48010",
    "addr:street":"Calle De Perez Galdos",
    "iso:country":"ES",
    "sg:address":"Calle de Perez Galdos, 5",
    "sg:city":"Bilbao",
    "sg:orig_category":"Asilos De Ancianos. Centros Privados",
    "sg:phone":"+34 944 70 20 05",
    "sg:postcode":"48010",
    "sg:province":"Vizcaya",
    "wof:name":"Congregacion Hermanas Angelicas",
    "wof:placetype":"venue"
},
  "geometry": {"coordinates":[-2.9417309761,43.2587661743],"type":"Point"}
}