{
  "type": "Feature",
  "properties": {
    "addr:full":"Pe\u00f1a Careses, 36 Lugo Asturias 33192",
    "addr:housenumber":"36",
    "addr:postcode":"33192",
    "addr:street":"Careses",
    "iso:country":"ES",
    "sg:address":"Pe\u00f1a Careses, 36",
    "sg:city":"Lugo",
    "sg:orig_category":"Bebidas",
    "sg:phone":"+34 985 26 73 74",
    "sg:postcode":"33192",
    "sg:province":"Asturias",
    "wof:name":"Mer Principado S.l.",
    "wof:placetype":"venue"
},
  "geometry": {"coordinates":[-5.9832577705,43.2504386902],"type":"Point"}
}