{
  "type": "Feature",
  "properties": {
    "iso:country":"ES",
    "sg:address":"Carrer de Sant Jaume (de), 4",
    "sg:city":"Vilassar De Mar",
    "sg:orig_category":"Peluqueros: De Se\u00d1oras",
    "sg:phone":"+34 937 59 01 48",
    "sg:postcode":"08340",
    "sg:province":"Barcelona",
    "wof:name":"Martinez Lopez Cristobal",
    "wof:placetype":"venue"
},
  "geometry": {"coordinates":[2.3894739151,41.5005073547],"type":"Point"}
}