{
  "type": "Feature",
  "properties": {
    "iso:country":"ES",
    "sg:address":"Calle de Martin Chamorro, 38",
    "sg:city":"Malpartida Plasencia",
    "sg:orig_category":"Marroquiner\u00cda (confecci\u00d3n)",
    "sg:phone":"+34 927 40 44 68",
    "sg:postcode":"10680",
    "sg:province":"C\u00e1ceres",
    "wof:name":"Vivas Garcia Manuel",
    "wof:placetype":"venue"
},
  "geometry": {"coordinates":[-6.0462641716,39.9780693054],"type":"Point"}
}