{
  "type": "Feature",
  "properties": {
    "addr:full":"Calle de Bajeles, 17 Sevilla Sevilla 41002",
    "addr:housenumber":"17",
    "addr:postcode":"41002",
    "addr:street":"Calle De Bajeles",
    "iso:country":"ES",
    "sg:address":"Calle de Bajeles, 17",
    "sg:city":"Sevilla",
    "sg:orig_category":"Agencias Y Asesores De Publicidad",
    "sg:phone":"+34 954 91 59 80",
    "sg:postcode":"41002",
    "sg:province":"Sevilla",
    "wof:name":"Broker Ideas De Publicidad S.l.",
    "wof:placetype":"venue"
},
  "geometry": {"coordinates":[-6.0021529198,37.394733429],"type":"Point"}
}