{
  "type": "Feature",
  "properties": {
    "addr:full":"Calle de Juan Ramon Jimenez, S/n Cala\u00f1as Huelva 21300",
    "addr:postcode":"21300",
    "addr:street":"Calle De Juan Ramon Jimenez S / N Calan\u0303As",
    "iso:country":"ES",
    "sg:address":"Calle de Juan Ramon Jimenez, S/n",
    "sg:city":"Cala\u00f1as",
    "sg:orig_category":"Mayoristas E Intermediarios En Alcoholes",
    "sg:phone":"+34 959 56 53 57",
    "sg:postcode":"21300",
    "sg:province":"Huelva",
    "wof:name":"Garcia Rivera Rodrigo Jose 000094067c .s.l.n.e",
    "wof:placetype":"venue"
},
  "geometry": {"coordinates":[-6.8806200027,37.6546363831],"type":"Point"}
}