{
  "type": "Feature",
  "properties": {
    "iso:country":"ES",
    "sg:address":"Czad Gandaras (das), 9",
    "sg:city":"Lugo",
    "sg:orig_category":"Vinos Y Licores (venta Al Por Menor)",
    "sg:phone":"+34 982 22 44 97",
    "sg:postcode":"27003",
    "sg:province":"Lugo",
    "wof:name":"Fernandez Fernandez Maria Jose",
    "wof:placetype":"venue"
},
  "geometry": {"coordinates":[-7.5763959885,43.0335426331],"type":"Point"}
}