{
  "type": "Feature",
  "properties": {
    "iso:country":"ES",
    "sg:address":"Calle de Santa Ana, 13",
    "sg:city":"Campillos",
    "sg:orig_category":"Zapatos (al Por Menor)",
    "sg:phone":"+34 952 72 20 88",
    "sg:postcode":"29320",
    "sg:province":"M\u00e1laga",
    "wof:name":"Gambero Galeote S.c.a.",
    "wof:placetype":"venue"
},
  "geometry": {"coordinates":[-4.8632211685,37.0478858948],"type":"Point"}
}