{
  "type": "Feature",
  "properties": {
    "addr:full":"Ctra Moraleja De Enmedio, 10 Fuenlabrada Madrid 28944",
    "addr:housenumber":"10",
    "addr:postcode":"28944",
    "addr:street":"Ctra Moraleja De Enmedio",
    "iso:country":"ES",
    "sg:address":"Ctra Moraleja De Enmedio, 10",
    "sg:city":"Fuenlabrada",
    "sg:orig_category":"Ebanistas Y Talladores De Muebles Y Objetos De Arte",
    "sg:phone":"+34 916 90 26 11",
    "sg:postcode":"28944",
    "sg:province":"Madrid",
    "wof:name":"Mueles Fejo S. L.",
    "wof:placetype":"venue"
},
  "geometry": {"coordinates":[-3.8054120541,40.2770881653],"type":"Point"}
}