{
  "type": "Feature",
  "properties": {
    "iso:country":"ES",
    "sg:address":"Calle de Ferraz, 26",
    "sg:city":"Madrid",
    "sg:orig_category":"Promotores Constructores",
    "sg:phone":"+34 915 59 52 62",
    "sg:postcode":"28008",
    "sg:province":"Madrid",
    "wof:name":"Landene Kalea S.l.",
    "wof:placetype":"venue"
},
  "geometry": {"coordinates":[-3.7161591053,40.4251937866],"type":"Point"}
}