{
  "type": "Feature",
  "properties": {
    "iso:country":"ES",
    "sg:address":"La Huerta, 31",
    "sg:city":"Coca\u00f1in",
    "sg:orig_category":"Vinos Y Licores (venta Al Por Menor)",
    "sg:phone":"+34 985 66 10 76",
    "sg:postcode":"33945",
    "sg:province":"Asturias",
    "wof:name":"Laviana Fernandez Jose",
    "wof:placetype":"venue"
},
  "geometry": {"coordinates":[-5.625480175,43.30128479],"type":"Point"}
}