{
  "type": "Feature",
  "properties": {
    "iso:country":"ES",
    "sg:address":"Avda Manuel Barnuevo, 2",
    "sg:city":"Villarrobledo",
    "sg:orig_category":"Mec\u00c1nico Del Autom\u00d3vil",
    "sg:phone":"+34 967 14 36 45",
    "sg:postcode":"02600",
    "sg:province":"Albacete",
    "wof:name":"Villamovil S.l.",
    "wof:placetype":"venue"
},
  "geometry": {"coordinates":[-2.5984311104,39.261428833],"type":"Point"}
}