{
  "type": "Feature",
  "properties": {
    "iso:country":"ES",
    "sg:address":"Calle de Prim, 13",
    "sg:city":"Donostia-san Sebastian",
    "sg:orig_category":"M\u00c9dicos: Gastroenterolog\u00cda Y Hepatolog\u00cda (aparato Digestivo)",
    "sg:phone":"+34 943 47 35 12",
    "sg:postcode":"20006",
    "sg:province":"Guip\u00f9zcoa",
    "wof:name":"Azpiroz Vidaur Francisco Javier",
    "wof:placetype":"venue"
},
  "geometry": {"coordinates":[-1.9796299934,43.3172035217],"type":"Point"}
}