{
  "type": "Feature",
  "properties": {
    "addr:full":"Avda Francisco Franco, S/n Santiago Ribera Murcia 30720",
    "addr:housenumber":"s / n",
    "addr:postcode":"30720",
    "addr:street":"Avda Francisco Franco",
    "iso:country":"ES",
    "sg:address":"Avda Francisco Franco, S/n",
    "sg:city":"Santiago Ribera",
    "sg:orig_category":"Ense\u00d1anza Variada",
    "sg:phone":"+34 968 57 31 68",
    "sg:postcode":"30720",
    "sg:province":"Murcia",
    "wof:name":"Velasco Granero Manuel",
    "wof:placetype":"venue"
},
  "geometry": {"coordinates":[-0.8098689914,37.8009681702],"type":"Point"}
}