{
  "type": "Feature",
  "properties": {
    "addr:full":"Calle de Milanesa, 2 Motril Granada 18600",
    "addr:housenumber":"2",
    "addr:postcode":"18600",
    "addr:street":"Calle De Milanesa",
    "iso:country":"ES",
    "sg:address":"Calle de Milanesa, 2",
    "sg:city":"Motril",
    "sg:orig_category":"Mercer\u00cda, Lencer\u00cda (al Por Menor)",
    "sg:phone":"+34 958 82 32 94",
    "sg:postcode":"18600",
    "sg:province":"Granada",
    "wof:name":"Vilar Ruiz Alfonso",
    "wof:placetype":"venue"
},
  "geometry": {"coordinates":[-3.5183799267,36.7460174561],"type":"Point"}
}