{
  "type": "Feature",
  "properties": {
    "addr:full":"Carr Ferran D'arago, 88 Algemesi Valencia 46680",
    "addr:housenumber":"88",
    "addr:postcode":"46680",
    "addr:street":"Carr Ferran D'Arago",
    "iso:country":"ES",
    "sg:address":"Carr Ferran D'arago, 88",
    "sg:city":"Algemesi",
    "sg:orig_category":"Frutas Y Legumbres Frescas (al Por Mayor)",
    "sg:phone":"+34 962 42 61 09",
    "sg:postcode":"46680",
    "sg:province":"Valencia",
    "wof:name":"Ferris Vilar Jose Enrique",
    "wof:placetype":"venue"
},
  "geometry": {"coordinates":[-0.4321742952,39.1940841675],"type":"Point"}
}