{
  "type": "Feature",
  "properties": {
    "iso:country":"ES",
    "sg:address":"Calle de Blas Infante, 8",
    "sg:city":"Algarrobo",
    "sg:orig_category":"Molduras, Junquillos, Listones Y Molduras Perforadas",
    "sg:phone":"+34 952 55 26 86",
    "sg:postcode":"29750",
    "sg:province":"M\u00e1laga",
    "wof:name":"Ortega Martin Ana Maria",
    "wof:placetype":"venue"
},
  "geometry": {"coordinates":[-4.0391364098,36.7738723755],"type":"Point"}
}