{
  "type": "Feature",
  "properties": {
    "addr:full":"Bule Buenos Aires (de), 10 Alcala Henares Madrid 28806",
    "addr:postcode":"28806",
    "iso:country":"ES",
    "sg:address":"Bule Buenos Aires (de), 10",
    "sg:city":"Alcala Henares",
    "sg:orig_category":"Fabricaci\u00d3n, Instalaci\u00d3n Y Reparaci\u00d3n De Bombas",
    "sg:phone":"+34 918 02 16 71",
    "sg:postcode":"28806",
    "sg:province":"Madrid",
    "wof:name":"Bombas Y Reparaciones S.l.",
    "wof:placetype":"venue"
},
  "geometry": {"coordinates":[-3.4063129425,40.5129585266],"type":"Point"}
}