{
  "type": "Feature",
  "properties": {
    "addr:full":"Calle de Guindales, 29 Alcorcon Madrid 28921",
    "addr:housenumber":"29",
    "addr:postcode":"28921",
    "addr:street":"Calle De Guindales",
    "iso:country":"ES",
    "sg:address":"Calle de Guindales, 29",
    "sg:city":"Alcorcon",
    "sg:orig_category":"Inform\u00c1tica: Material Y Suministros",
    "sg:phone":"+34 916 11 67 07",
    "sg:postcode":"28921",
    "sg:province":"Madrid",
    "wof:name":"Mantenimiento Y Comercializacion De Informatica Y Sistemas S.l.",
    "wof:placetype":"venue"
},
  "geometry": {"coordinates":[-3.8322963715,40.3476219177],"type":"Point"}
}