{
  "type": "Feature",
  "properties": {
    "iso:country":"ES",
    "sg:address":"Avda Bulevar De El Ejido, 25",
    "sg:city":"Ejido",
    "sg:orig_category":"Asesor\u00cda Para La Organizaci\u00d3n Y Gesti\u00d3n Del Transporte",
    "sg:phone":"+34 950 48 97 97",
    "sg:postcode":"04700",
    "sg:province":"Almer\u00eda",
    "wof:name":"Inter Ca\u00d1abate S.l.",
    "wof:placetype":"venue"
},
  "geometry": {"coordinates":[-2.8176040649,36.7727012634],"type":"Point"}
}