{
  "type": "Feature",
  "properties": {
    "addr:full":"Carrer de Gallecs, 68 Mollet Valles Barcelona 08100",
    "addr:housenumber":"68",
    "addr:postcode":"08100",
    "addr:street":"Carrer De Gallecs",
    "iso:country":"ES",
    "sg:address":"Carrer de Gallecs, 68",
    "sg:city":"Mollet Valles",
    "sg:orig_category":"Promotores Constructores",
    "sg:phone":"+34 935 93 73 28",
    "sg:postcode":"08100",
    "sg:province":"Barcelona",
    "wof:name":"Inversiones S.b.m.t. S. A.",
    "wof:placetype":"venue"
},
  "geometry": {"coordinates":[2.2074599266,41.5487289429],"type":"Point"}
}