{
  "type": "Feature",
  "properties": {
    "iso:country":"ES",
    "sg:address":"Calle de Joaquin Cayon, 8",
    "sg:city":"Santander",
    "sg:orig_category":"Art\u00cdculos De Decoraci\u00d3n (fabricaci\u00d3n Y Al Por Mayor)",
    "sg:phone":"+34 942 28 01 10",
    "sg:postcode":"39005",
    "sg:province":"Cantabria",
    "sg:website":"www.mfdecoracion.com",
    "wof:name":"M.f. Corsini Dise\u00f1o Y Decoracion S.l.",
    "wof:placetype":"venue"
},
  "geometry": {"coordinates":[-3.7879390717,43.4750404358],"type":"Point"}
}