{
  "type": "Feature",
  "properties": {
    "iso:country":"ES",
    "sg:address":"Avda Francia (de), S/n",
    "sg:city":"Playa Del Ingles",
    "sg:orig_category":"Bazares, Art\u00cdculos De Limpieza Y De Cocina (al Por Menor)",
    "sg:phone":"+34 928 77 17 31",
    "sg:postcode":"35100",
    "sg:province":"Las Palmas",
    "wof:name":"Sociedad Khatnani S.a.",
    "wof:placetype":"venue"
},
  "geometry": {"coordinates":[-15.5795240402,27.7507400513],"type":"Point"}
}