{
  "type": "Feature",
  "properties": {
    "addr:full":"Aptos. La Panderola, 4 Benicassim Castell\u00f3n 12560",
    "addr:housenumber":"4",
    "addr:postcode":"12560",
    "addr:street":"Aptos.;Panderola;Castello\u0301N",
    "iso:country":"ES",
    "sg:address":"Aptos. La Panderola, 4",
    "sg:city":"Benicassim",
    "sg:orig_category":"Agencias Y Agentes Comerciales, Representantes",
    "sg:phone":"+34 964 39 30 45",
    "sg:postcode":"12560",
    "sg:province":"Castell\u00f3n",
    "wof:name":"Ramirez Salas Jose Luis",
    "wof:placetype":"venue"
},
  "geometry": {"coordinates":[0.0457400009,40.0510292053],"type":"Point"}
}