{
  "type": "Feature",
  "properties": {
    "addr:full":"Via Lactea(pol Ind Estrella), 34 Molina Segura Murcia 30500",
    "addr:housenumber":"34",
    "addr:postcode":"30500",
    "addr:street":"Via Lactea Pol Ind Estrella",
    "iso:country":"ES",
    "sg:address":"Via Lactea(pol Ind Estrella), 34",
    "sg:city":"Molina Segura",
    "sg:orig_category":"Delegados, Agentes De Tr\u00c1nsito, Auxiliares De Transporte Internacional",
    "sg:phone":"+34 968 64 50 92",
    "sg:postcode":"30500",
    "sg:province":"Murcia",
    "wof:name":"Liza Tortola Sebastian",
    "wof:placetype":"venue"
},
  "geometry": {"coordinates":[-1.2119740248,38.0535736084],"type":"Point"}
}