{
  "type": "Feature",
  "properties": {
    "addr:full":"Pje. Bajondillo, S/n Torremolinos M\u00e1laga 29620",
    "addr:housenumber":"s / n",
    "addr:postcode":"29620",
    "addr:street":"Pje. Bajondillo;Ma\u0301Laga",
    "iso:country":"ES",
    "sg:address":"Pje. Bajondillo, S/n",
    "sg:city":"Torremolinos",
    "sg:orig_category":"Centros De Adelgazamiento Y De Est\u00c9tica",
    "sg:phone":"+34 952 37 13 59",
    "sg:postcode":"29620",
    "sg:province":"M\u00e1laga",
    "wof:name":"Gutierrez Soria Alberto",
    "wof:placetype":"venue"
},
  "geometry": {"coordinates":[-4.4953241348,36.6229934692],"type":"Point"}
}