{
  "type": "Feature",
  "properties": {
    "iso:country":"ES",
    "sg:address":"Carrer de Felip Bertran I Guell, 3",
    "sg:city":"Barcelona",
    "sg:orig_category":"Art\u00cdculos De Decoraci\u00d3n (fabricaci\u00d3n Y Al Por Mayor)",
    "sg:phone":"+34 932 43 08 74",
    "sg:postcode":"08027",
    "sg:province":"Barcelona",
    "wof:name":"Soteras Guasch Armando",
    "wof:placetype":"venue"
},
  "geometry": {"coordinates":[2.1821060181,41.424533844],"type":"Point"}
}