{
  "type": "Feature",
  "properties": {
    "iso:country":"ES",
    "sg:address":"Calle de Flor De Porcelana, S/n",
    "sg:city":"Sevilla",
    "sg:orig_category":"Supermercados Y Hipermercados",
    "sg:phone":"+34 954 40 36 32",
    "sg:postcode":"41020",
    "sg:province":"Sevilla",
    "wof:name":"Gonzalez Vita Mari Angeles",
    "wof:placetype":"venue"
},
  "geometry": {"coordinates":[-5.9171471596,37.3947906494],"type":"Point"}
}