{
  "type": "Feature",
  "properties": {
    "iso:country":"ES",
    "sg:address":"Calle de Rey, 9",
    "sg:city":"Plasencia",
    "sg:orig_category":"Ropa De Hogar (al Por Menor)",
    "sg:phone":"+34 927 41 67 07",
    "sg:postcode":"10600",
    "sg:province":"C\u00e1ceres",
    "wof:name":"Caba C.b.",
    "wof:placetype":"venue"
},
  "geometry": {"coordinates":[-6.0894589424,40.0304603577],"type":"Point"}
}