{
  "type": "Feature",
  "properties": {
    "addr:full":"Calle de Castilla-la Mancha, 13 Barakaldo Vizcaya 48901",
    "addr:housenumber":"13",
    "addr:postcode":"48901",
    "addr:street":"Calle De Castilla-La Mancha",
    "iso:country":"ES",
    "sg:address":"Calle de Castilla-la Mancha, 13",
    "sg:city":"Barakaldo",
    "sg:orig_category":"Fabricaci\u00d3n, Venta, Instalaci\u00d3n De R\u00d3tulos, De R\u00d3tulos Luminosos",
    "sg:phone":"+34 944 37 18 97",
    "sg:postcode":"48901",
    "sg:province":"Vizcaya",
    "wof:name":"Luminosos Barakaldo",
    "wof:placetype":"venue"
},
  "geometry": {"coordinates":[-2.9850170612,43.2956581116],"type":"Point"}
}