{
  "type": "Feature",
  "properties": {
    "iso:country":"ES",
    "sg:address":"Avda Maria Auxiliadora, S/n",
    "sg:city":"Rota",
    "sg:orig_category":"Producci\u00d3n, Distribuci\u00d3n De Electricidad",
    "sg:phone":"+34 956 81 33 37",
    "sg:postcode":"11520",
    "sg:province":"C\u00e1diz",
    "wof:name":"Mateos Santamaria Jose",
    "wof:placetype":"venue"
},
  "geometry": {"coordinates":[-6.3637142181,36.6252441406],"type":"Point"}
}