{
  "type": "Feature",
  "properties": {
    "addr:full":"Calle de Castillo De Alcala De Guadaira, 5 Sevilla Sevilla 41013",
    "addr:housenumber":"5",
    "addr:postcode":"41013",
    "addr:street":"Calle De Castillo De Alcala;Guadaira",
    "iso:country":"ES",
    "sg:address":"Calle de Castillo De Alcala De Guadaira, 5",
    "sg:city":"Sevilla",
    "sg:orig_category":"Lencer\u00cda Femenina, Corseter\u00cda, Trajes De Ba\u00d1o (al Por Menor)",
    "sg:phone":"+34 954 61 58 87",
    "sg:postcode":"41013",
    "sg:province":"Sevilla",
    "wof:name":"Bermejo Martin Agueda",
    "wof:placetype":"venue"
},
  "geometry": {"coordinates":[-5.9771437645,37.36120224],"type":"Point"}
}