{
  "type": "Feature",
  "properties": {
    "addr:full":"Calle de Venerables, 8 Burgos Burgos 09003",
    "addr:housenumber":"8",
    "addr:postcode":"09003",
    "addr:street":"Calle De Venerables",
    "iso:country":"ES",
    "sg:address":"Calle de Venerables, 8",
    "sg:city":"Burgos",
    "sg:orig_category":"Asociaciones Y Clubs Deportivos",
    "sg:phone":"+34 947 20 06 86",
    "sg:postcode":"09003",
    "sg:province":"Burgos",
    "wof:name":"Ampaber S.l.",
    "wof:placetype":"venue"
},
  "geometry": {"coordinates":[-3.7105116844,42.3462677002],"type":"Point"}
}