{
  "type": "Feature",
  "properties": {
    "iso:country":"ES",
    "sg:address":"Avda Antona Garcia, 10",
    "sg:city":"Toro",
    "sg:orig_category":"Panader\u00cdas, Panader\u00cdas",
    "sg:phone":"+34 980 69 11 67",
    "sg:postcode":"49800",
    "sg:province":"Zamora",
    "wof:name":"Fernandez Miguel Javier",
    "wof:placetype":"venue"
},
  "geometry": {"coordinates":[-5.3863949776,41.5203361511],"type":"Point"}
}