{
  "type": "Feature",
  "properties": {
    "addr:full":"Calle de Santa Ana La Vieja, 68 Solana Ciudad Real 13240",
    "addr:housenumber":"68",
    "addr:postcode":"13240",
    "addr:street":"Calle De Santa;La Vieja;Real",
    "iso:country":"ES",
    "sg:address":"Calle de Santa Ana La Vieja, 68",
    "sg:city":"Solana",
    "sg:orig_category":"Alimentaci\u00d3n General (al Por Menor)",
    "sg:phone":"+34 926 63 53 74",
    "sg:postcode":"13240",
    "sg:province":"Ciudad Real",
    "wof:name":"Perez Ruiz Santa Quiteria Miguela",
    "wof:placetype":"venue"
},
  "geometry": {"coordinates":[-3.2429890633,38.9474983215],"type":"Point"}
}