{
  "type": "Feature",
  "properties": {
    "iso:country":"ES",
    "sg:address":"Calle de Guardia Civil, S/n",
    "sg:city":"Santa Maria De Guia",
    "sg:orig_category":"Promotores Constructores",
    "sg:phone":"+34 928 88 17 76",
    "sg:postcode":"35450",
    "sg:province":"Las Palmas",
    "wof:name":"Promotora Marcevega",
    "wof:placetype":"venue"
},
  "geometry": {"coordinates":[-15.6350135803,28.1420059204],"type":"Point"}
}