{
  "type": "Feature",
  "properties": {
    "addr:full":"Planeta (la), S/n Mancha Real Ja\u00e9n 23100",
    "addr:housenumber":"/ n",
    "addr:postcode":"23100",
    "addr:street":"La S",
    "iso:country":"ES",
    "sg:address":"Planeta (la), S/n",
    "sg:city":"Mancha Real",
    "sg:orig_category":"Muebles, Minoristas",
    "sg:phone":"+34 953 35 25 29",
    "sg:postcode":"23100",
    "sg:province":"Ja\u00e9n",
    "wof:name":"Mesa Navas Luis",
    "wof:placetype":"venue"
},
  "geometry": {"coordinates":[-3.6116495132,37.8278694153],"type":"Point"}
}