{
  "type": "Feature",
  "properties": {
    "iso:country":"ES",
    "sg:address":"Carrer de Doctor Esteve, 32",
    "sg:city":"Manresa",
    "sg:orig_category":"Promotores Constructores",
    "sg:phone":"+34 938 73 57 51",
    "sg:postcode":"08242",
    "sg:province":"Barcelona",
    "sg:website":"www.joanperramon.com",
    "wof:name":"Construccions Joan Perramon S.l.",
    "wof:placetype":"venue"
},
  "geometry": {"coordinates":[1.8240790367,41.7330322266],"type":"Point"}
}