{
  "type": "Feature",
  "properties": {
    "addr:full":"Pg Sant Gervasi, 82 Barcelona Barcelona 08022",
    "addr:housenumber":"82",
    "addr:postcode":"08022",
    "addr:street":"Pg Sant Gervasi",
    "iso:country":"ES",
    "sg:address":"Pg Sant Gervasi, 82",
    "sg:city":"Barcelona",
    "sg:orig_category":"Laboratorios Y Trabajos De Fotograf\u00cda, V\u00cddeo Y Cine",
    "sg:phone":"+34 934 18 52 70",
    "sg:postcode":"08022",
    "sg:province":"Barcelona",
    "wof:name":"Montenegro Ruiz Petra",
    "wof:placetype":"venue"
},
  "geometry": {"coordinates":[2.1380579472,41.413105011],"type":"Point"}
}