{
  "type": "Feature",
  "properties": {
    "iso:country":"ES",
    "sg:address":"Calle de Guzman El Bueno, 4",
    "sg:city":"Sevilla",
    "sg:orig_category":"Promotores Constructores",
    "sg:phone":"+34 954 22 69 68",
    "sg:postcode":"41004",
    "sg:province":"Sevilla",
    "wof:name":"Moreno De La Cova Serafina",
    "wof:placetype":"venue"
},
  "geometry": {"coordinates":[-5.9905428886,37.3871498108],"type":"Point"}
}