{
  "type": "Feature",
  "properties": {
    "addr:full":"Calle de Angel Lozano, 13 Alacant Alicante 03001",
    "addr:housenumber":"13",
    "addr:postcode":"03001",
    "addr:street":"Calle De Angel Lozano",
    "iso:country":"ES",
    "sg:address":"Calle de Angel Lozano, 13",
    "sg:city":"Alacant",
    "sg:orig_category":"Abogados",
    "sg:phone":"+34 965 20 13 33",
    "sg:postcode":"03001",
    "sg:province":"Alicante",
    "wof:name":"Grau-pastor-mora-serna&asociados.abogados",
    "wof:placetype":"venue"
},
  "geometry": {"coordinates":[-0.4885837138,38.3464241028],"type":"Point"}
}