{
  "type": "Feature",
  "properties": {
    "iso:country":"ES",
    "sg:address":"Calle de Elortza, 14",
    "sg:city":"Elortza",
    "sg:orig_category":"Mec\u00c1nico Del Autom\u00d3vil",
    "sg:phone":"+34 946 76 07 09",
    "sg:postcode":"48610",
    "sg:province":"Vizcaya",
    "wof:name":"Talleres Mecanicos Otegi S.l.",
    "wof:placetype":"venue"
},
  "geometry": {"coordinates":[-2.9578540325,43.3789749146],"type":"Point"}
}