{
  "type": "Feature",
  "properties": {
    "addr:full":"Calle de Republica Argentina, 13 Valencia Valencia 46021",
    "addr:housenumber":"13",
    "addr:postcode":"46021",
    "addr:street":"Calle De Republica Argentina",
    "iso:country":"ES",
    "sg:address":"Calle de Republica Argentina, 13",
    "sg:city":"Valencia",
    "sg:orig_category":"Panader\u00cdas, Panader\u00cdas",
    "sg:phone":"+34 963 60 90 61",
    "sg:postcode":"46021",
    "sg:province":"Valencia",
    "wof:name":"Panificadora Saguntina S.a.",
    "wof:placetype":"venue"
},
  "geometry": {"coordinates":[-0.3516606092,39.4725456238],"type":"Point"}
}