{
  "type": "Feature",
  "properties": {
    "iso:country":"ES",
    "sg:address":"Avda Pais Valencia, 52",
    "sg:city":"Torrent",
    "sg:orig_category":"Ense\u00d1anza, Formaci\u00d3n Profesional: Aprendizaje",
    "sg:phone":"+34 961 55 94 12",
    "sg:postcode":"46900",
    "sg:province":"Valencia",
    "wof:name":"Agencia Estatal De Administracion Tributaria",
    "wof:placetype":"venue"
},
  "geometry": {"coordinates":[-0.4695807993,39.4341812134],"type":"Point"}
}