{
  "type": "Feature",
  "properties": {
    "addr:full":"Avda Federico Anaya, 124 Salamanca Salamanca 37004",
    "addr:housenumber":"124",
    "addr:postcode":"37004",
    "addr:street":"Avda Federico Anaya",
    "iso:country":"ES",
    "sg:address":"Avda Federico Anaya, 124",
    "sg:city":"Salamanca",
    "sg:orig_category":"Contenedores (mercanc\u00cdas)",
    "sg:phone":"+34 923 23 20 37",
    "sg:postcode":"37004",
    "sg:province":"Salamanca",
    "wof:name":"Borrego Sanchez Pedro",
    "wof:placetype":"venue"
},
  "geometry": {"coordinates":[-5.6515522003,40.9801712036],"type":"Point"}
}