{
  "type": "Feature",
  "properties": {
    "iso:country":"ES",
    "sg:address":"Carrer de Merce, 4",
    "sg:city":"Granollers",
    "sg:orig_category":"Trabajos De Perforaciones, Sondeos, Construcci\u00d3n De Pozos",
    "sg:phone":"+34 938 49 26 91",
    "sg:postcode":"08403",
    "sg:province":"Barcelona",
    "wof:name":"Medina Vega Remedios",
    "wof:placetype":"venue"
},
  "geometry": {"coordinates":[2.2751040459,41.6122741699],"type":"Point"}
}