{
  "type": "Feature",
  "properties": {
    "addr:full":"Avda Felipe Iv De, 8 Donostia-san Sebastian Guip\u00f9zcoa 20011",
    "addr:housenumber":"8",
    "addr:postcode":"20011",
    "addr:street":"Avda Felipe Iv De",
    "iso:country":"ES",
    "sg:address":"Avda Felipe Iv De, 8",
    "sg:city":"Donostia-san Sebastian",
    "sg:orig_category":"Bisuter\u00cda, Joyer\u00cda, Relojer\u00cda (al Por Menor)",
    "sg:phone":"+34 943 45 56 71",
    "sg:postcode":"20011",
    "sg:province":"Guip\u00f9zcoa",
    "wof:name":"Aranaz Aranaz Lucia",
    "wof:placetype":"venue"
},
  "geometry": {"coordinates":[-1.9751962423,43.3054771423],"type":"Point"}
}