{
  "type": "Feature",
  "properties": {
    "addr:full":"Edf Florazar Ii, S/n Cullera Valencia 46400",
    "addr:housenumber":"s / n",
    "addr:postcode":"46400",
    "iso:country":"ES",
    "sg:address":"Edf Florazar Ii, S/n",
    "sg:city":"Cullera",
    "sg:orig_category":"Promotores Constructores",
    "sg:phone":"+34 961 72 11 13",
    "sg:postcode":"46400",
    "sg:province":"Valencia",
    "wof:name":"Lumon S.l.",
    "wof:placetype":"venue"
},
  "geometry": {"coordinates":[-0.2526162863,39.1436882019],"type":"Point"}
}