{
  "type": "Feature",
  "properties": {
    "addr:full":"Calle de Soria, 3 Ajalvir Madrid 28864",
    "addr:housenumber":"3",
    "addr:postcode":"28864",
    "addr:street":"Calle De Soria",
    "iso:country":"ES",
    "sg:address":"Calle de Soria, 3",
    "sg:city":"Ajalvir",
    "sg:orig_category":"Art\u00cdculos De Decoraci\u00d3n",
    "sg:phone":"+34 918 84 38 53",
    "sg:postcode":"28864",
    "sg:province":"Madrid",
    "sg:website":"www.isabelgtapia.com",
    "wof:name":"Isabel G.tapia S.a.",
    "wof:placetype":"venue"
},
  "geometry": {"coordinates":[-3.4829149246,40.531375885],"type":"Point"}
}