{
  "type": "Feature",
  "properties": {
    "addr:full":"Plaz Libertad (de La), S/n Pampaneira Granada 18411",
    "addr:housenumber":"s",
    "addr:postcode":"18411",
    "addr:street":"/ N Pampaneira",
    "iso:country":"ES",
    "sg:address":"Plaz Libertad (de La), S/n",
    "sg:city":"Pampaneira",
    "sg:orig_category":"Organismos De Turismo",
    "sg:phone":"+34 958 76 33 01",
    "sg:postcode":"18411",
    "sg:province":"Granada",
    "sg:website":"www.nevadensis.com",
    "wof:name":"Nevadensis S.l.",
    "wof:placetype":"venue"
},
  "geometry": {"coordinates":[-3.3611690998,36.9402961731],"type":"Point"}
}