{
  "type": "Feature",
  "properties": {
    "iso:country":"ES",
    "sg:address":"Calle de Cercas Bajas, 5",
    "sg:city":"Vitoria-gasteiz",
    "sg:orig_category":"Deportes Diversos",
    "sg:phone":"+34 945 13 40 07",
    "sg:postcode":"01001",
    "sg:province":"\u00c1lava",
    "wof:name":"Federacion Alavesa De Futbol Sala",
    "wof:placetype":"venue"
},
  "geometry": {"coordinates":[-2.6760458946,42.8482818604],"type":"Point"}
}