{
  "type": "Feature",
  "properties": {
    "iso:country":"ES",
    "sg:address":"Calle de Caceres, 20",
    "sg:city":"Alcorcon",
    "sg:orig_category":"Muebles Y Accesorios Para Cocinas Y Cuartos De Ba\u00d1o (al Por Menor)",
    "sg:phone":"+34 916 11 03 62",
    "sg:postcode":"28921",
    "sg:province":"Madrid",
    "wof:name":"Fernandez Morillas Jesus Miguel",
    "wof:placetype":"venue"
},
  "geometry": {"coordinates":[-3.8327233791,40.3475723267],"type":"Point"}
}