{
  "type": "Feature",
  "properties": {
    "addr:full":"Paraje La Jarrina, S/n Lillo Del Bierzo Le\u00f3n 24428",
    "addr:housenumber":"s",
    "addr:postcode":"24428",
    "addr:street":"Paraje La Jarrina;/ N;Leo\u0301N",
    "iso:country":"ES",
    "sg:address":"Paraje La Jarrina, S/n",
    "sg:city":"Lillo Del Bierzo",
    "sg:orig_category":"Explotaci\u00d3n De Minas",
    "sg:phone":"+34 987 68 93 84",
    "sg:postcode":"24428",
    "sg:province":"Le\u00f3n",
    "wof:name":"Maxamcorp S.a.u.",
    "wof:placetype":"venue"
},
  "geometry": {"coordinates":[-6.6138410568,42.7812271118],"type":"Point"}
}