{
  "type": "Feature",
  "properties": {
    "iso:country":"ES",
    "sg:address":"Calle de Afuera, S/n",
    "sg:city":"Trujillo",
    "sg:orig_category":"Cr\u00cda De Bovinos",
    "sg:phone":"+34 927 49 00 19",
    "sg:postcode":"10200",
    "sg:province":"C\u00e1ceres",
    "wof:name":"Cotidiano S.l.",
    "wof:placetype":"venue"
},
  "geometry": {"coordinates":[-5.8804101944,39.4621887207],"type":"Point"}
}