{
  "type": "Feature",
  "properties": {
    "addr:full":"Las Retamas, 7 S. Agustin-playa Ingles Las Palmas 35100",
    "addr:housenumber":"7",
    "addr:postcode":"35100",
    "addr:street":"Las Retamas;S. Agustin-Playa",
    "iso:country":"ES",
    "sg:address":"Las Retamas, 7",
    "sg:city":"S. Agustin-playa Ingles",
    "sg:orig_category":"Molduras, Junquillos, Listones Y Molduras Perforadas",
    "sg:phone":"+34 928 76 24 07",
    "sg:postcode":"35100",
    "sg:province":"Las Palmas",
    "wof:name":"Mateo Rodriguez Ramon",
    "wof:placetype":"venue"
},
  "geometry": {"coordinates":[-15.5472917557,27.7690563202],"type":"Point"}
}