{
  "type": "Feature",
  "properties": {
    "iso:country":"ES",
    "sg:address":"Heliche, 20",
    "sg:city":"Olivares",
    "sg:orig_category":"Empresas De Carpinter\u00cda Met\u00c1lica",
    "sg:phone":"+34 954 11 05 20",
    "sg:postcode":"41804",
    "sg:province":"Sevilla",
    "wof:name":"Vargas Gonzalez Bernardo",
    "wof:placetype":"venue"
},
  "geometry": {"coordinates":[-6.1574239731,37.4188308716],"type":"Point"}
}