{
  "type": "Feature",
  "properties": {
    "addr:full":"Carrer de Taquigraf Garriga, 63 Barcelona Barcelona 08029",
    "addr:housenumber":"63",
    "addr:postcode":"08029",
    "addr:street":"Carrer De Taquigraf Garriga",
    "iso:country":"ES",
    "sg:address":"Carrer de Taquigraf Garriga, 63",
    "sg:city":"Barcelona",
    "sg:orig_category":"Farmacias",
    "sg:phone":"+34 934 30 76 43",
    "sg:postcode":"08029",
    "sg:province":"Barcelona",
    "wof:name":"Fernandez Perez Maria Del Carmen",
    "wof:placetype":"venue"
},
  "geometry": {"coordinates":[2.1353158951,41.3878974915],"type":"Point"}
}