{
  "type": "Feature",
  "properties": {
    "addr:full":"Ptge Maria Lluisa, 10 Cerdanyola Valles Barcelona 08290",
    "addr:housenumber":"10",
    "addr:postcode":"08290",
    "addr:street":"Ptge Maria Lluisa;Valles Barcelona",
    "iso:country":"ES",
    "sg:address":"Ptge Maria Lluisa, 10",
    "sg:city":"Cerdanyola Valles",
    "sg:orig_category":"Fabricaci\u00d3n De Moldes Y Modelos",
    "sg:phone":"+34 936 91 15 82",
    "sg:postcode":"08290",
    "sg:province":"Barcelona",
    "wof:name":"Marcos Hernandez Rufino",
    "wof:placetype":"venue"
},
  "geometry": {"coordinates":[2.1470150948,41.4924812317],"type":"Point"}
}