{
  "type": "Feature",
  "properties": {
    "addr:full":"Calle de Cardenal Vera, 42 Alzira Valencia 46600",
    "addr:housenumber":"42",
    "addr:postcode":"46600",
    "addr:street":"Calle De Cardenal Vera",
    "iso:country":"ES",
    "sg:address":"Calle de Cardenal Vera, 42",
    "sg:city":"Alzira",
    "sg:orig_category":"Cajas Para Embalar",
    "sg:phone":"+34 962 45 52 88",
    "sg:postcode":"46600",
    "sg:province":"Valencia",
    "wof:name":"Caja Rural Del Mediterraneo Ruralcaja S Coop De Credito",
    "wof:placetype":"venue"
},
  "geometry": {"coordinates":[-0.4339385927,39.1473579407],"type":"Point"}
}