{
  "type": "Feature",
  "properties": {
    "addr:full":"Pg Font D'en Fargas, 18 Barcelona Barcelona 08032",
    "addr:housenumber":"18",
    "addr:postcode":"08032",
    "addr:street":"Pg Font D'En Fargas",
    "iso:country":"ES",
    "sg:address":"Pg Font D'en Fargas, 18",
    "sg:city":"Barcelona",
    "sg:orig_category":"Empresas De Desmonte",
    "sg:phone":"+34 934 20 84 08",
    "sg:postcode":"08032",
    "sg:province":"Barcelona",
    "wof:name":"Eduard Garcia S. A.",
    "wof:placetype":"venue"
},
  "geometry": {"coordinates":[2.1643209457,41.4213371277],"type":"Point"}
}