{
  "type": "Feature",
  "properties": {
    "iso:country":"ES",
    "sg:address":"Carrer de Pins De Can Caralleu, 4",
    "sg:city":"Barcelona",
    "sg:orig_category":"Agencias Y Asesores De Publicidad",
    "sg:phone":"+34 932 52 50 10",
    "sg:postcode":"08017",
    "sg:province":"Barcelona",
    "wof:name":"Imat Comunicacion S.l.",
    "wof:placetype":"venue"
},
  "geometry": {"coordinates":[2.1085040569,41.4034919739],"type":"Point"}
}