{
  "type": "Feature",
  "properties": {
    "iso:country":"ES",
    "sg:address":"Urteta Bidea, 7",
    "sg:city":"Zarautz",
    "sg:orig_category":"Mec\u00c1nico Del Autom\u00d3vil",
    "sg:phone":"+34 943 83 51 95",
    "sg:postcode":"20800",
    "sg:province":"Guip\u00f9zcoa",
    "wof:name":"Jose Maria Aguinaga Aliri Y Otro Cdad",
    "wof:placetype":"venue"
},
  "geometry": {"coordinates":[-2.1706039906,43.276512146],"type":"Point"}
}