{
  "type": "Feature",
  "properties": {
    "iso:country":"ES",
    "sg:address":"Avda Santa Marta, 4",
    "sg:city":"Huelva",
    "sg:orig_category":"Formaci\u00d3n Continuada (variada)",
    "sg:phone":"+34 959 25 16 95",
    "sg:postcode":"21005",
    "sg:province":"Huelva",
    "wof:name":"Bourre Dominguez Jose",
    "wof:placetype":"venue"
},
  "geometry": {"coordinates":[-6.9364738464,37.2777481079],"type":"Point"}
}