{
  "type": "Feature",
  "properties": {
    "iso:country":"ES",
    "sg:address":"Calle de Francisco Cano Fontecha, 21",
    "sg:city":"Tobarra",
    "sg:orig_category":"Venta, Colocaci\u00d3n, Reparaci\u00d3n De Parabrisas, Techos Descapotables",
    "sg:phone":"+34 967 32 88 13",
    "sg:postcode":"02500",
    "sg:province":"Albacete",
    "wof:name":"Teleglass Albacete S.l",
    "wof:placetype":"venue"
},
  "geometry": {"coordinates":[-1.6863490343,38.5934295654],"type":"Point"}
}