{
  "type": "Feature",
  "properties": {
    "addr:full":"Calle de Fuente Canonigos, 16 Tudela Navarra 31500",
    "addr:housenumber":"16",
    "addr:postcode":"31500",
    "addr:street":"Calle De Fuente Canonigos",
    "iso:country":"ES",
    "sg:address":"Calle de Fuente Canonigos, 16",
    "sg:city":"Tudela",
    "sg:orig_category":"Farmacias",
    "sg:phone":"+34 948 82 21 30",
    "sg:postcode":"31500",
    "sg:province":"Navarra",
    "wof:name":"Farmacia Izquierdo Zu\u00f1iga S.c.",
    "wof:placetype":"venue"
},
  "geometry": {"coordinates":[-1.5998079777,42.0562400818],"type":"Point"}
}