{
  "type": "Feature",
  "properties": {
    "addr:full":"Rua Alcalde Ramiro Rueda Fernandez, 11 Lugo Lugo 27003",
    "addr:housenumber":"11",
    "addr:postcode":"27003",
    "addr:street":"Rua Alcalde Ramiro Rueda Fernandez",
    "iso:country":"ES",
    "sg:address":"Rua Alcalde Ramiro Rueda Fernandez, 11",
    "sg:city":"Lugo",
    "sg:orig_category":"Empresarios",
    "sg:phone":"+34 982 28 02 84",
    "sg:postcode":"27003",
    "sg:province":"Lugo",
    "wof:name":"Forga",
    "wof:placetype":"venue"
},
  "geometry": {"coordinates":[-7.5602498055,43.0185317993],"type":"Point"}
}