{
  "type": "Feature",
  "properties": {
    "iso:country":"ES",
    "sg:address":"Burgos (poligonos Industriales), Km. 0119,0",
    "sg:city":"Valladolid",
    "sg:orig_category":"Venta, Instalaci\u00d3n De Sistemas De Alarmas Y Vigilancia",
    "sg:phone":"+34 983 34 57 40",
    "sg:postcode":"47009",
    "sg:province":"Valladolid",
    "wof:name":"Blindados Del Norte S.a.",
    "wof:placetype":"venue"
},
  "geometry": {"coordinates":[-4.7070288658,41.6909103394],"type":"Point"}
}