{
  "type": "Feature",
  "properties": {
    "addr:full":"Avda Castilla Leon, 34 Campo Criptana Ciudad Real 13610",
    "addr:housenumber":"34",
    "addr:postcode":"13610",
    "addr:street":"Avda Castilla Leon;Criptana",
    "iso:country":"ES",
    "sg:address":"Avda Castilla Leon, 34",
    "sg:city":"Campo Criptana",
    "sg:orig_category":"Carb\u00d3n, Carb\u00d3n De Madera (al Por Mayor)",
    "sg:phone":"+34 926 56 16 93",
    "sg:postcode":"13610",
    "sg:province":"Ciudad Real",
    "wof:name":"Olivares Peinado Eladio",
    "wof:placetype":"venue"
},
  "geometry": {"coordinates":[-3.1243391037,39.403339386],"type":"Point"}
}