{
  "type": "Feature",
  "properties": {
    "addr:full":"Plaz Espa\u00d1a, S/n Samper Calanda Teruel 44520",
    "addr:housenumber":"s",
    "addr:postcode":"44520",
    "addr:street":"Plaz Espan\u0303A;/ N Samper",
    "iso:country":"ES",
    "sg:address":"Plaz Espa\u00d1a, S/n",
    "sg:city":"Samper Calanda",
    "sg:orig_category":"Cajas De Ahorro",
    "sg:phone":"+34 978 82 24 86",
    "sg:postcode":"44520",
    "sg:province":"Teruel",
    "sg:website":"www.ibercaja.es",
    "wof:name":"Caja De Ahorros Y Monte De Piedad De Zaragoza Aragon Y Rioja",
    "wof:placetype":"venue"
},
  "geometry": {"coordinates":[-0.3876709938,41.1920547485],"type":"Point"}
}