{
  "type": "Feature",
  "properties": {
    "iso:country":"ES",
    "sg:address":"Calle de Naranjo, 6",
    "sg:city":"Arganda",
    "sg:orig_category":"Empresas De Operaciones Portuarias Y Elevaci\u00d3n De Mercanc\u00cdas",
    "sg:phone":"+34 918 72 95 71",
    "sg:postcode":"28500",
    "sg:province":"Madrid",
    "wof:name":"Ausum Manipulados S.l.",
    "wof:placetype":"venue"
},
  "geometry": {"coordinates":[-3.4615273476,40.3125953674],"type":"Point"}
}