{
  "type": "Feature",
  "properties": {
    "addr:full":"Calle de Teresa De Cofrentes, S/n Valencia Valencia 46015",
    "addr:housenumber":"s / n",
    "addr:postcode":"46015",
    "addr:street":"Calle De Teresa;Cofrentes",
    "iso:country":"ES",
    "sg:address":"Calle de Teresa De Cofrentes, S/n",
    "sg:city":"Valencia",
    "sg:orig_category":"Asesor\u00cdas Y Estudios Financieros",
    "sg:phone":"+34 963 40 27 37",
    "sg:postcode":"46015",
    "sg:province":"Valencia",
    "wof:name":"Bautista Felipe Alfonso",
    "wof:placetype":"venue"
},
  "geometry": {"coordinates":[-0.3965539932,39.4837265015],"type":"Point"}
}