{
  "type": "Feature",
  "properties": {
    "addr:full":"Calle de Cristobal Colon, 5 Port D'andratx Islas Baleares 07157",
    "addr:housenumber":"5",
    "addr:postcode":"07157",
    "addr:street":"Calle De Cristobal Colon",
    "iso:country":"ES",
    "sg:address":"Calle de Cristobal Colon, 5",
    "sg:city":"Port D'andratx",
    "sg:orig_category":"Caf\u00c9s, Bares, Cervecer\u00cdas",
    "sg:phone":"+34 971 67 16 02",
    "sg:postcode":"07157",
    "sg:province":"Islas Baleares",
    "wof:name":"Alemany Vera Francisca",
    "wof:placetype":"venue"
},
  "geometry": {"coordinates":[2.389121294,39.5446014404],"type":"Point"}
}