{
  "type": "Feature",
  "properties": {
    "iso:country":"ES",
    "sg:address":"Calle de Santa Maria Magdalena, 68",
    "sg:city":"Dos Hermanas",
    "sg:orig_category":"Telas Y Sedas (al Por Menor)",
    "sg:phone":"+34 954 72 13 80",
    "sg:postcode":"41700",
    "sg:province":"Sevilla",
    "wof:name":"Hidalgo Orellana Manuel",
    "wof:placetype":"venue"
},
  "geometry": {"coordinates":[-5.9271020889,37.2830963135],"type":"Point"}
}