{
  "type": "Feature",
  "properties": {
    "iso:country":"ES",
    "sg:address":"Calle de Camino De Los Toros, S/n",
    "sg:city":"Sevilla",
    "sg:orig_category":"Molduras, Junquillos, Listones Y Molduras Perforadas",
    "sg:phone":"+34 954 96 04 52",
    "sg:postcode":"41008",
    "sg:province":"Sevilla",
    "wof:name":"Rivero Mu\u00f1oz Rosario",
    "wof:placetype":"venue"
},
  "geometry": {"coordinates":[-5.9692893028,37.4209480286],"type":"Point"}
}