{
  "type": "Feature",
  "properties": {
    "addr:full":"Ctra Cantalejo, S/n Cuellar Segovia 40200",
    "addr:housenumber":"s / n",
    "addr:postcode":"40200",
    "addr:street":"Ctra Cantalejo",
    "iso:country":"ES",
    "sg:address":"Ctra Cantalejo, S/n",
    "sg:city":"Cuellar",
    "sg:orig_category":"Insecticidas, Fumigaci\u00d3n",
    "sg:phone":"+34 921 14 24 91",
    "sg:postcode":"40200",
    "sg:province":"Segovia",
    "wof:name":"Abonos Tecnicos Y Agroquimicos S.l.",
    "wof:placetype":"venue"
},
  "geometry": {"coordinates":[-4.300924,41.389465],"type":"Point"}
}