{
  "type": "Feature",
  "properties": {
    "addr:full":"Calle de Bonetero, 4 Madrid Madrid 28016",
    "addr:housenumber":"4",
    "addr:postcode":"28016",
    "addr:street":"Calle De Bonetero",
    "iso:country":"ES",
    "sg:address":"Calle de Bonetero, 4",
    "sg:city":"Madrid",
    "sg:orig_category":"Cine: Pel\u00cdculas Educativas, Industriales Y Publicitarias (producci\u00d3n)",
    "sg:phone":"+34 913 59 11 83",
    "sg:postcode":"28016",
    "sg:province":"Madrid",
    "wof:name":"Equipo Sans S.l.",
    "wof:placetype":"venue"
},
  "geometry": {"coordinates":[-3.6790416241,40.4606704712],"type":"Point"}
}