{
  "type": "Feature",
  "properties": {
    "iso:country":"ES",
    "sg:address":"Calle de Hilados, 20",
    "sg:city":"Torrejon Ardoz",
    "sg:orig_category":"Plomeros",
    "sg:phone":"+34 916 56 14 64",
    "sg:postcode":"28850",
    "sg:province":"Madrid",
    "wof:name":"Tauste Sobrino Fernando",
    "wof:placetype":"venue"
},
  "geometry": {"coordinates":[-3.4594089985,40.4454345703],"type":"Point"}
}