{
  "type": "Feature",
  "properties": {
    "addr:full":"Calle de Jose Zorrilla, 18 Sese\u00f1a Toledo 45223",
    "addr:housenumber":"18",
    "addr:postcode":"45223",
    "addr:street":"Calle De Jose Zorrilla",
    "iso:country":"ES",
    "sg:address":"Calle de Jose Zorrilla, 18",
    "sg:city":"Sese\u00f1a",
    "sg:orig_category":"Promotores Constructores",
    "sg:phone":"+34 918 08 81 26",
    "sg:postcode":"45223",
    "sg:province":"Toledo",
    "wof:name":"Construcciones Serrano Torrejon S.l.",
    "wof:placetype":"venue"
},
  "geometry": {"coordinates":[-3.6901390553,40.1064910889],"type":"Point"}
}