{
  "type": "Feature",
  "properties": {
    "iso:country":"ES",
    "sg:address":"Plaz Coimbra, 5",
    "sg:city":"Madrid",
    "sg:orig_category":"T\u00c9cnicos Veterinarios",
    "sg:phone":"+34 914 60 44 39",
    "sg:postcode":"28025",
    "sg:province":"Madrid",
    "wof:name":"Boto Guzman Jose",
    "wof:placetype":"venue"
},
  "geometry": {"coordinates":[-3.7241210938,40.3831481934],"type":"Point"}
}