{
  "type": "Feature",
  "properties": {
    "iso:country":"ES",
    "sg:address":"Calle de Miguel Angel, 1",
    "sg:city":"Alcala Henares",
    "sg:orig_category":"Peluqueros: De Se\u00d1oras",
    "sg:phone":"+34 918 83 74 76",
    "sg:postcode":"28802",
    "sg:province":"Madrid",
    "wof:name":"Enredos Peluquerias Y Esteticistas S.l.",
    "wof:placetype":"venue"
},
  "geometry": {"coordinates":[-3.3782019615,40.4752082825],"type":"Point"}
}