{
  "type": "Feature",
  "properties": {
    "iso:country":"ES",
    "sg:address":"Carr Agustins, 3",
    "sg:city":"Lleida",
    "sg:orig_category":"Carnicer\u00cdas, Carnicer\u00cdas",
    "sg:phone":"+34 973 20 02 41",
    "sg:postcode":"25001",
    "sg:province":"Lleida",
    "wof:name":"Escarp Eroles Jose",
    "wof:placetype":"venue"
},
  "geometry": {"coordinates":[0.634616971,41.6100654602],"type":"Point"}
}