{
  "type": "Feature",
  "properties": {
    "iso:country":"ES",
    "sg:address":"Pg Dintre (de), 36",
    "sg:city":"Blanes",
    "sg:orig_category":"Ropa Para Se\u00d1oras Y Caballeros (al Por Menor)",
    "sg:phone":"+34 972 33 15 25",
    "sg:postcode":"17300",
    "sg:province":"Girona",
    "wof:name":"Medina Gotarra Elvira",
    "wof:placetype":"venue"
},
  "geometry": {"coordinates":[2.7916040421,41.6736488342],"type":"Point"}
}