{
  "type": "Feature",
  "properties": {
    "iso:country":"ES",
    "sg:address":"Calle de Agustin Lara, 24",
    "sg:city":"Granada",
    "sg:classifiers":[
        {
            "category":"Autos & Motor Vehicles",
            "subcategory":"Automobile Sales",
            "type":"Retail Goods"
        }
    ],
    "sg:phone":"+34 958 13 37 03",
    "sg:postcode":"18008",
    "sg:province":"Granada",
    "wof:name":"Perez Duran Pedro Jose",
    "wof:placetype":"venue"
},
  "geometry": {"coordinates":[-3.593506813,37.1632118225],"type":"Point"}
}