{
  "type": "Feature",
  "properties": {
    "addr:full":"Urb Puerto Paraiso, S/n Estepona M\u00e1laga 29680",
    "addr:postcode":"29680",
    "addr:street":"Urb Puerto Paraiso S / N;Ma\u0301Laga",
    "iso:country":"ES",
    "sg:address":"Urb Puerto Paraiso, S/n",
    "sg:city":"Estepona",
    "sg:orig_category":"Centros Empresariales",
    "sg:phone":"+34 952 89 61 04",
    "sg:postcode":"29680",
    "sg:province":"M\u00e1laga",
    "wof:name":"Alfred Franagan David",
    "wof:placetype":"venue"
},
  "geometry": {"coordinates":[-5.1744904518,36.4435119629],"type":"Point"}
}