{
  "type": "Feature",
  "properties": {
    "iso:country":"ES",
    "sg:address":"Calle de Cabo De Trafalgar, 6",
    "sg:city":"Arganda",
    "sg:orig_category":"Empresas De Carpinter\u00cda",
    "sg:phone":"+34 918 71 90 79",
    "sg:postcode":"28500",
    "sg:province":"Madrid",
    "wof:name":"Carpinteria Metalica Lozano Y Garcia S.l.",
    "wof:placetype":"venue"
},
  "geometry": {"coordinates":[-3.4741046429,40.3109283447],"type":"Point"}
}