{
  "type": "Feature",
  "properties": {
    "iso:country":"ES",
    "sg:address":"Ctra Madrid, Km. 0436,0",
    "sg:city":"Ventorrillos",
    "sg:orig_category":"Empresas De Carpinter\u00cda Met\u00c1lica",
    "sg:phone":"+34 968 16 90 77",
    "sg:postcode":"30319",
    "sg:province":"Murcia",
    "wof:name":"Cerramientos Y Mecanicas S.l.",
    "wof:placetype":"venue"
},
  "geometry": {"coordinates":[-1.0148609877,37.6664352417],"type":"Point"}
}