{
  "type": "Feature",
  "properties": {
    "iso:country":"ES",
    "sg:address":"Carr Doctor Domingo Orozco, 27",
    "sg:city":"Burjassot",
    "sg:orig_category":"Peluquer\u00cdas, Peluquer\u00cda Mixta",
    "sg:phone":"+34 963 90 40 82",
    "sg:postcode":"46100",
    "sg:province":"Valencia",
    "wof:name":"Labrada Perez Maria Teresa",
    "wof:placetype":"venue"
},
  "geometry": {"coordinates":[-0.4162290096,39.5102806091],"type":"Point"}
}