{
  "type": "Feature",
  "properties": {
    "addr:full":"Calle de Margaritas, 2 Madrid Madrid 28039",
    "addr:housenumber":"2",
    "addr:postcode":"28039",
    "addr:street":"Calle De Margaritas",
    "iso:country":"ES",
    "sg:address":"Calle de Margaritas, 2",
    "sg:city":"Madrid",
    "sg:orig_category":"Carnicer\u00cdas, Carnicer\u00cdas",
    "sg:phone":"+34 913 11 19 97",
    "sg:postcode":"28039",
    "sg:province":"Madrid",
    "wof:name":"Perez De La Nuez Amalia",
    "wof:placetype":"venue"
},
  "geometry": {"coordinates":[-3.7063150406,40.4567909241],"type":"Point"}
}