{
  "type": "Feature",
  "properties": {
    "addr:full":"Calle de San Francisco, 4 Guadix Granada 18500",
    "addr:housenumber":"4",
    "addr:postcode":"18500",
    "addr:street":"Calle De San Francisco",
    "iso:country":"ES",
    "sg:address":"Calle de San Francisco, 4",
    "sg:city":"Guadix",
    "sg:orig_category":"Abogados",
    "sg:phone":"+34 958 66 03 45",
    "sg:postcode":"18500",
    "sg:province":"Granada",
    "wof:name":"Salas Ibanez Felipe",
    "wof:placetype":"venue"
},
  "geometry": {"coordinates":[-3.1333670616,37.2999916077],"type":"Point"}
}