{
  "type": "Feature",
  "properties": {
    "iso:country":"ES",
    "sg:address":"Pol Ind Plasencia, 23",
    "sg:city":"Plasencia",
    "sg:orig_category":"Maquinaria Para Industrias Diversas",
    "sg:phone":"+34 927 41 30 33",
    "sg:postcode":"10600",
    "sg:province":"C\u00e1ceres",
    "wof:name":"Jaso Equipos De Obras Y Construcciones S.l.",
    "wof:placetype":"venue"
},
  "geometry": {"coordinates":[-6.1739115715,40.0015525818],"type":"Point"}
}