{
  "type": "Feature",
  "properties": {
    "iso:country":"ES",
    "sg:address":"Calle de Pino, 7",
    "sg:city":"Benidorm",
    "sg:orig_category":"Inmobiliaria (agencias)",
    "sg:phone":"+34 966 80 95 52",
    "sg:postcode":"03500",
    "sg:province":"Alicante",
    "wof:name":"Villas Benidorm C.b.",
    "wof:placetype":"venue"
},
  "geometry": {"coordinates":[-0.1306789964,38.540802002],"type":"Point"}
}