{
  "type": "Feature",
  "properties": {
    "addr:full":"Calle de Felipe Gorriti, S/n Uharte-arakil Navarra 31840",
    "addr:housenumber":"s / n",
    "addr:postcode":"31840",
    "addr:street":"Calle De Felipe Gorriti",
    "iso:country":"ES",
    "sg:address":"Calle de Felipe Gorriti, S/n",
    "sg:city":"Uharte-arakil",
    "sg:orig_category":"Empresarios",
    "sg:phone":"+34 948 46 40 09",
    "sg:postcode":"31840",
    "sg:province":"Navarra",
    "wof:name":"Construcciones Razquin S.l.",
    "wof:placetype":"venue"
},
  "geometry": {"coordinates":[-1.9684239626,42.9211654663],"type":"Point"}
}