{
  "type": "Feature",
  "properties": {
    "iso:country":"ES",
    "sg:address":"Francisco Tomas Y Valiente, 2",
    "sg:city":"Quart Poblet",
    "sg:orig_category":"Promotores Constructores",
    "sg:phone":"+34 961 54 69 29",
    "sg:postcode":"46930",
    "sg:province":"Valencia",
    "wof:name":"Fomas Soluciones Integrales Para La Construccion S.l.",
    "wof:placetype":"venue"
},
  "geometry": {"coordinates":[-0.4419890046,39.482711792],"type":"Point"}
}