{
  "type": "Feature",
  "properties": {
    "addr:full":"Carrer de Alfons Sola, 20 Caldes Montbui Barcelona 08140",
    "addr:housenumber":"20",
    "addr:postcode":"08140",
    "addr:street":"Carrer De Alfons Sola;Montbui Barcelona",
    "iso:country":"ES",
    "sg:address":"Carrer de Alfons Sola, 20",
    "sg:city":"Caldes Montbui",
    "sg:orig_category":"Int\u00c9rpretes",
    "sg:phone":"+34 938 62 64 95",
    "sg:postcode":"08140",
    "sg:province":"Barcelona",
    "wof:name":"Vilanova Flaque Mireia",
    "wof:placetype":"venue"
},
  "geometry": {"coordinates":[2.1676158905,41.6311607361],"type":"Point"}
}