{
  "type": "Feature",
  "properties": {
    "iso:country":"ES",
    "sg:address":"Av Alfonso Puchades, 2",
    "sg:city":"Benidorm",
    "sg:classifiers":[
        {
            "category":"Taxi",
            "type":"Transportation"
        }
    ],
    "sg:phone":"+34 965 86 24 24",
    "sg:postcode":"03500",
    "sg:province":"Alicante",
    "wof:name":"Asociacion Local De Radio Taxis De Benidorm",
    "wof:placetype":"venue"
},
  "geometry": {"coordinates":[-0.1273992956,38.5428657532],"type":"Point"}
}