{
  "type": "Feature",
  "properties": {
    "iso:country":"ES",
    "sg:address":"Calle de Instituto, 8",
    "sg:city":"Gijon",
    "sg:orig_category":"Alimentaci\u00d3n General (al Por Menor)",
    "sg:phone":"+34 985 34 59 96",
    "sg:postcode":"33201",
    "sg:province":"Asturias",
    "wof:name":"Garcia Teijeiro Sabino",
    "wof:placetype":"venue"
},
  "geometry": {"coordinates":[-5.6634402275,43.543964386],"type":"Point"}
}