{
  "type": "Feature",
  "properties": {
    "iso:country":"ES",
    "sg:address":"Avda Arana Sabino, 59",
    "sg:city":"Bilbao",
    "sg:orig_category":"Venta, Instalaci\u00d3n De Calefacci\u00d3n",
    "sg:phone":"+34 944 39 50 55",
    "sg:postcode":"48013",
    "sg:province":"Vizcaya",
    "wof:name":"Revuelta Gorostiza Alfonso",
    "wof:placetype":"venue"
},
  "geometry": {"coordinates":[-2.9476690292,43.2581558228],"type":"Point"}
}