{
  "type": "Feature",
  "properties": {
    "addr:full":"Calle de Molino Velasco, S/n Velez-malaga M\u00e1laga 29700",
    "addr:postcode":"29700",
    "addr:street":"Calle De Molino Velasco S / N Velez-Malaga Ma\u0301Laga",
    "iso:country":"ES",
    "sg:address":"Calle de Molino Velasco, S/n",
    "sg:city":"Velez-malaga",
    "sg:orig_category":"Instalaci\u00d3n, Reparaci\u00d3n De Ascensores Y Montacargas",
    "sg:phone":"+34 952 50 38 91",
    "sg:postcode":"29700",
    "sg:province":"M\u00e1laga",
    "sg:website":"www.otis.com",
    "wof:name":"Zardoya Otis S. A.",
    "wof:placetype":"venue"
},
  "geometry": {"coordinates":[-4.1014227867,36.7747268677],"type":"Point"}
}