{
  "type": "Feature",
  "properties": {
    "addr:full":"Avgd Alameda Jaume I, 36 Xativa Valencia 46800",
    "addr:housenumber":"36",
    "addr:postcode":"46800",
    "addr:street":"Alameda Jaume I",
    "iso:country":"ES",
    "sg:address":"Avgd Alameda Jaume I, 36",
    "sg:city":"Xativa",
    "sg:orig_category":"\u00d3ptica: Instrumentos (fabricaci\u00d3n)",
    "sg:phone":"+34 962 28 09 08",
    "sg:postcode":"46800",
    "sg:province":"Valencia",
    "wof:name":"Folch Cano Alicia",
    "wof:placetype":"venue"
},
  "geometry": {"coordinates":[-0.5237929821,38.9893226624],"type":"Point"}
}