{
  "type": "Feature",
  "properties": {
    "addr:full":"Calle de Nueva, 15 Chiclana De La Frontera C\u00e1diz 11130",
    "addr:housenumber":"15",
    "addr:postcode":"11130",
    "addr:street":"Calle De Nueva",
    "iso:country":"ES",
    "sg:address":"Calle de Nueva, 15",
    "sg:city":"Chiclana De La Frontera",
    "sg:orig_category":"Muebles, Minoristas",
    "sg:phone":"+34 956 40 14 00",
    "sg:postcode":"11130",
    "sg:province":"C\u00e1diz",
    "wof:name":"Herederos De Cristobal Benitez S.l.",
    "wof:placetype":"venue"
},
  "geometry": {"coordinates":[-6.1473708153,36.4198760986],"type":"Point"}
}