{
  "type": "Feature",
  "properties": {
    "addr:full":"Carr Bisbe Ruano, 17 Lleida Lleida 25006",
    "addr:housenumber":"17",
    "addr:postcode":"25006",
    "addr:street":"Carr Bisbe Ruano",
    "iso:country":"ES",
    "sg:address":"Carr Bisbe Ruano, 17",
    "sg:city":"Lleida",
    "sg:orig_category":"Ropa Para Beb\u00c9s Y Ni\u00d1os (confecci\u00d3n, Al Por Mayor)",
    "sg:phone":"+34 973 26 45 87",
    "sg:postcode":"25006",
    "sg:province":"Lleida",
    "wof:name":"Espot Vidal Elvira",
    "wof:placetype":"venue"
},
  "geometry": {"coordinates":[0.6176239848,41.6169586182],"type":"Point"}
}