{
  "type": "Feature",
  "properties": {
    "iso:country":"ES",
    "sg:address":"Carr Sant Cristofol, 9",
    "sg:city":"Figueres",
    "sg:orig_category":"Panader\u00cdas, Panader\u00cdas",
    "sg:phone":"+34 972 67 24 97",
    "sg:postcode":"17600",
    "sg:province":"Girona",
    "wof:name":"Croisanteries Associades S.a.",
    "wof:placetype":"venue"
},
  "geometry": {"coordinates":[2.9641990662,42.2669067383],"type":"Point"}
}