{
  "type": "Feature",
  "properties": {
    "iso:country":"ES",
    "sg:address":"Calle de Puerto De Pajares, 12",
    "sg:city":"Madrid",
    "sg:orig_category":"Pintura Y Barniz (al Por Menor)",
    "sg:phone":"+34 914 77 48 92",
    "sg:postcode":"28053",
    "sg:province":"Madrid",
    "wof:name":"Tamurejo Blazquez Jose",
    "wof:placetype":"venue"
},
  "geometry": {"coordinates":[-3.6647639275,40.39503479],"type":"Point"}
}