{
  "type": "Feature",
  "properties": {
    "iso:country":"ES",
    "sg:address":"Calle de Morillo (del), 11",
    "sg:city":"Segovia",
    "sg:orig_category":"Inform\u00c1tica, Ofim\u00c1tica (estudios, Asesor\u00cda, Ingenier\u00cda, Formaci\u00d3n)",
    "sg:phone":"+34 921 41 20 71",
    "sg:postcode":"40002",
    "sg:province":"Segovia",
    "wof:name":"Miguel Sanz Francisco",
    "wof:placetype":"venue"
},
  "geometry": {"coordinates":[-4.1166830063,40.9424705505],"type":"Point"}
}