{
  "type": "Feature",
  "properties": {
    "iso:country":"ES",
    "sg:address":"Olveira, S/n",
    "sg:city":"Olveira",
    "sg:orig_category":"Agentes, Concesionarios Y Sucursales De Veh\u00cdculos",
    "sg:phone":"+34 981 74 15 08",
    "sg:postcode":"15129",
    "sg:province":"A Coru\u00f1a",
    "wof:name":"Senra Sport S.l.",
    "wof:placetype":"venue"
},
  "geometry": {"coordinates":[-9.0328435898,43.1112251282],"type":"Point"}
}