{
  "type": "Feature",
  "properties": {
    "iso:country":"ES",
    "sg:address":"Pl Jacint Verdaguer (d'en), 3",
    "sg:city":"Tarragona",
    "sg:orig_category":"Carnicer\u00cdas, Carnicer\u00cdas",
    "sg:phone":"+34 977 22 46 63",
    "sg:postcode":"43003",
    "sg:province":"Tarragona",
    "wof:name":"Guivernau Queralt Jose",
    "wof:placetype":"venue"
},
  "geometry": {"coordinates":[1.2559789419,41.1154327393],"type":"Point"}
}