{
  "type": "Feature",
  "properties": {
    "iso:country":"ES",
    "sg:address":"Ctra. Almeria, 24",
    "sg:city":"Malaga",
    "sg:orig_category":"Mercer\u00cda, Lencer\u00cda (al Por Menor)",
    "sg:phone":"+34 952 29 67 53",
    "sg:postcode":"29018",
    "sg:province":"M\u00e1laga",
    "wof:name":"Castillo Montes Rosa Maria",
    "wof:placetype":"venue"
},
  "geometry": {"coordinates":[-4.3254132271,36.7129936218],"type":"Point"}
}