{
  "type": "Feature",
  "properties": {
    "iso:country":"ES",
    "sg:address":"Luga Muelle De La Ribera, S/n",
    "sg:city":"Almeria",
    "sg:orig_category":"Contenedores (mercanc\u00cdas)",
    "sg:phone":"+34 950 27 39 74",
    "sg:postcode":"04002",
    "sg:province":"Almer\u00eda",
    "wof:name":"Transbull Almeria, S.l.",
    "wof:placetype":"venue"
},
  "geometry": {"coordinates":[-2.5000441074,36.8265953064],"type":"Point"}
}