{
  "type": "Feature",
  "properties": {
    "iso:country":"ES",
    "sg:address":"Ctra Canteras, Km. 0003,0",
    "sg:city":"Villanueva Rio Y Minas",
    "sg:orig_category":"Trabajos De Asfalto, De Alquitr\u00c1n Y Asfalto",
    "sg:phone":"+34 955 94 00 45",
    "sg:postcode":"41350",
    "sg:province":"Sevilla",
    "wof:name":"Tranconsa S.l.",
    "wof:placetype":"venue"
},
  "geometry": {"coordinates":[-5.7183542252,37.6519584656],"type":"Point"}
}