{
  "type": "Feature",
  "properties": {
    "iso:country":"ES",
    "sg:address":"Calle de Antonio De Nebrija, 18",
    "sg:city":"Berja",
    "sg:orig_category":"Cl\u00cdnicas Dentales",
    "sg:phone":"+34 950 49 04 96",
    "sg:postcode":"04760",
    "sg:province":"Almer\u00eda",
    "wof:name":"Centro Dental Berja S.l.",
    "wof:placetype":"venue"
},
  "geometry": {"coordinates":[-2.9575607777,36.80991745],"type":"Point"}
}