{
  "type": "Feature",
  "properties": {
    "addr:full":"Vall D'uxo, 28 Elche Alicante 03205",
    "addr:housenumber":"28",
    "addr:postcode":"03205",
    "addr:street":"D'Uxo",
    "iso:country":"ES",
    "sg:address":"Vall D'uxo, 28",
    "sg:city":"Elche",
    "sg:orig_category":"Zapatos: Material, Suministros, Accesorios (fabricaci\u00d3n, Al Por Mayor)",
    "sg:phone":"+34 966 67 08 22",
    "sg:postcode":"03205",
    "sg:province":"Alicante",
    "wof:name":"Adornos Clement S.l.",
    "wof:placetype":"venue"
},
  "geometry": {"coordinates":[-0.7135313749,38.2823181152],"type":"Point"}
}