{
  "type": "Feature",
  "properties": {
    "iso:country":"ES",
    "sg:address":"Carrer de Montserrat, 7",
    "sg:city":"Esparreguera",
    "sg:orig_category":"Edici\u00d3n, Venta De Partituras Musicales",
    "sg:phone":"+34 937 77 60 60",
    "sg:postcode":"08292",
    "sg:province":"Barcelona",
    "wof:name":"Harmonia Catalunya S. L.",
    "wof:placetype":"venue"
},
  "geometry": {"coordinates":[1.8670150042,41.5418968201],"type":"Point"}
}