{
  "type": "Feature",
  "properties": {
    "addr:full":"Pl Rosari, 5 Palma Islas Baleares 07001",
    "addr:housenumber":"5",
    "addr:postcode":"07001",
    "addr:street":"Rosari",
    "iso:country":"ES",
    "sg:address":"Pl Rosari, 5",
    "sg:city":"Palma",
    "sg:orig_category":"Asesor\u00cda Sobre Comunicaci\u00d3n De Empresas",
    "sg:phone":"+34 971 71 89 84",
    "sg:postcode":"07001",
    "sg:province":"Islas Baleares",
    "wof:name":"Explaya S.a.",
    "wof:placetype":"venue"
},
  "geometry": {"coordinates":[2.6480050087,39.5695610046],"type":"Point"}
}