{
  "type": "Feature",
  "properties": {
    "addr:full":"Av Rei Joan Carles I, 8 Pego Alicante 03780",
    "addr:housenumber":"8",
    "addr:postcode":"03780",
    "addr:street":"Av Rei Joan Carles I",
    "iso:country":"ES",
    "sg:address":"Av Rei Joan Carles I, 8",
    "sg:city":"Pego",
    "sg:orig_category":"Empresas De Carpinter\u00cda De Madera",
    "sg:phone":"+34 965 57 22 13",
    "sg:postcode":"03780",
    "sg:province":"Alicante",
    "wof:name":"Cuimport S.l.",
    "wof:placetype":"venue"
},
  "geometry": {"coordinates":[-0.1107930019,38.8456001282],"type":"Point"}
}