{
  "type": "Feature",
  "properties": {
    "addr:full":"Carrer de Antoni Roig (d'), 14 Torredembarra Tarragona 43830",
    "addr:housenumber":"14",
    "addr:postcode":"43830",
    "addr:street":"Carrer De Antoni Roig D '",
    "iso:country":"ES",
    "sg:address":"Carrer de Antoni Roig (d'), 14",
    "sg:city":"Torredembarra",
    "sg:orig_category":"Farmacias",
    "sg:phone":"+34 977 64 00 03",
    "sg:postcode":"43830",
    "sg:province":"Tarragona",
    "wof:name":"Cogul Ardevol Maria Blanca",
    "wof:placetype":"venue"
},
  "geometry": {"coordinates":[1.3979190588,41.1445732117],"type":"Point"}
}