{
  "type": "Feature",
  "properties": {
    "addr:full":"Pol Ind Linaritx, 32 Mercadal Islas Baleares 07740",
    "addr:housenumber":"32",
    "addr:postcode":"07740",
    "addr:street":"Linaritx",
    "iso:country":"ES",
    "sg:address":"Pol Ind Linaritx, 32",
    "sg:city":"Mercadal",
    "sg:orig_category":"Empresas De Carpinter\u00cda De Madera",
    "sg:phone":"+34 971 37 53 69",
    "sg:postcode":"07740",
    "sg:province":"Islas Baleares",
    "wof:name":"Fusteria Es Grop S.l.",
    "wof:placetype":"venue"
},
  "geometry": {"coordinates":[4.0921797752,39.9863700867],"type":"Point"}
}