{
  "type": "Feature",
  "properties": {
    "iso:country":"ES",
    "sg:address":"Calle de Ingeniero Ruiz De Azua, S/n",
    "sg:city":"Cordoba",
    "sg:orig_category":"T\u00c9cnicos Veterinarios",
    "sg:phone":"+34 957 76 73 34",
    "sg:postcode":"14006",
    "sg:province":"C\u00f3rdoba",
    "wof:name":"Cabello Suarez I\u00f1igo",
    "wof:placetype":"venue"
},
  "geometry": {"coordinates":[-4.7798290253,37.9004631042],"type":"Point"}
}