{
  "type": "Feature",
  "properties": {
    "addr:full":"Carre Viento, 9 Benidorm Alicante 03500",
    "addr:housenumber":"9",
    "addr:postcode":"03500",
    "addr:street":"Viento",
    "iso:country":"ES",
    "sg:address":"Carre Viento, 9",
    "sg:city":"Benidorm",
    "sg:orig_category":"Arreglo, Reparaci\u00d3n, Piezas Sueltas De Televisi\u00d3n, V\u00cddeo, Hi",
    "sg:phone":"+34 966 80 62 57",
    "sg:postcode":"03500",
    "sg:province":"Alicante",
    "wof:name":"Telecolor Benidorm S.l.",
    "wof:placetype":"venue"
},
  "geometry": {"coordinates":[-0.1739459932,38.5365180969],"type":"Point"}
}