{
  "type": "Feature",
  "properties": {
    "addr:full":"Ctra Sabadell, Km. 0007,1 Matadepera Barcelona 08230",
    "addr:postcode":"08230",
    "addr:street":"Ctra Sabadell Km. 0007,1",
    "iso:country":"ES",
    "sg:address":"Ctra Sabadell, Km. 0007,1",
    "sg:city":"Matadepera",
    "sg:orig_category":"Semiller\u00cdas",
    "sg:phone":"+34 937 30 04 23",
    "sg:postcode":"08230",
    "sg:province":"Barcelona",
    "wof:name":"Jardineria El Roure S.l.",
    "wof:placetype":"venue"
},
  "geometry": {"coordinates":[2.0206840038,41.6016540527],"type":"Point"}
}