{
  "type": "Feature",
  "properties": {
    "iso:country":"ES",
    "sg:address":"Avda Lieiro (de), S/n",
    "sg:city":"Lieiro",
    "sg:orig_category":"Hormigonados",
    "sg:phone":"+34 982 59 42 88",
    "sg:postcode":"27890",
    "sg:province":"Lugo",
    "wof:name":"Prebetong Lugo Hormigones S.a.",
    "wof:placetype":"venue"
},
  "geometry": {"coordinates":[-7.4518938065,43.694103241],"type":"Point"}
}