{
  "type": "Feature",
  "properties": {
    "iso:country":"ES",
    "sg:address":"Calle de Ramon Y Cajal, 5",
    "sg:city":"Madridejos",
    "sg:orig_category":"Agencias Y Agentes Comerciales, Representantes",
    "sg:phone":"+34 925 46 11 13",
    "sg:postcode":"45710",
    "sg:province":"Toledo",
    "wof:name":"Perez Morcillo Isabel",
    "wof:placetype":"venue"
},
  "geometry": {"coordinates":[-3.5354950428,39.467754364],"type":"Point"}
}