{
  "type": "Feature",
  "properties": {
    "iso:country":"ES",
    "sg:address":"Pase Sancha, 23",
    "sg:city":"Malaga",
    "sg:orig_category":"Abogados",
    "sg:phone":"+34 952 22 14 22",
    "sg:postcode":"29016",
    "sg:province":"M\u00e1laga",
    "wof:name":"Ma\u00f1as Castillo Jose Luis",
    "wof:placetype":"venue"
},
  "geometry": {"coordinates":[-4.4031791687,36.7216796875],"type":"Point"}
}