{
  "type": "Feature",
  "properties": {
    "addr:full":"Ptda Costera Pedres, S/n Crevillente Alicante 03330",
    "addr:housenumber":"s / n",
    "addr:postcode":"03330",
    "addr:street":"Ptda Costera Pedres",
    "iso:country":"ES",
    "sg:address":"Ptda Costera Pedres, S/n",
    "sg:city":"Crevillente",
    "sg:orig_category":"Barnizadores",
    "sg:phone":"+34 966 68 00 05",
    "sg:postcode":"03330",
    "sg:province":"Alicante",
    "wof:name":"Lledo Aznar Salvador",
    "wof:placetype":"venue"
},
  "geometry": {"coordinates":[-0.8142840266,38.2463645935],"type":"Point"}
}