{
  "type": "Feature",
  "properties": {
    "iso:country":"ES",
    "sg:address":"Carrer de Major De Sarria, 133",
    "sg:city":"Barcelona",
    "sg:orig_category":"Plomeros",
    "sg:phone":"+34 932 04 03 93",
    "sg:postcode":"08017",
    "sg:province":"Barcelona",
    "wof:name":"Lampisteria Calvet S.l",
    "wof:placetype":"venue"
},
  "geometry": {"coordinates":[2.1198968887,41.401599884],"type":"Point"}
}