{
  "type": "Feature",
  "properties": {
    "addr:full":"Plaz Alcalde De La Moneda, 5 Baena C\u00f3rdoba 14850",
    "addr:housenumber":"5",
    "addr:postcode":"14850",
    "addr:street":"Plaz Alcalde De La Moneda",
    "iso:country":"ES",
    "sg:address":"Plaz Alcalde De La Moneda, 5",
    "sg:city":"Baena",
    "sg:orig_category":"M\u00c9dicos: Estomatolog\u00cda",
    "sg:phone":"+34 957 67 16 22",
    "sg:postcode":"14850",
    "sg:province":"C\u00f3rdoba",
    "wof:name":"Rico De La Rosa Francisco",
    "wof:placetype":"venue"
},
  "geometry": {"coordinates":[-4.3211760521,37.615650177],"type":"Point"}
}