{
  "type": "Feature",
  "properties": {
    "iso:country":"ES",
    "sg:address":"Plaz Cortes Leonesas, 7",
    "sg:city":"Le\u00f3n",
    "sg:orig_category":"Telas Y Sedas (al Por Menor)",
    "sg:phone":"+34 987 20 85 51",
    "sg:postcode":"24003",
    "sg:province":"Le\u00f3n",
    "sg:website":"www.fernandeztextil.com",
    "wof:name":"Fernandez Calvo Angel",
    "wof:placetype":"venue"
},
  "geometry": {"coordinates":[-5.5726537704,42.5956535339],"type":"Point"}
}