{
  "type": "Feature",
  "properties": {
    "iso:country":"ES",
    "sg:address":"Calle de Doctor Francisco Grande Covian, 2",
    "sg:city":"Oviedo",
    "sg:orig_category":"Escayola Y Productos De Escayola (fabricaci\u00d3n, Al Por Mayor)",
    "sg:phone":"+34 985 29 81 20",
    "sg:postcode":"33011",
    "sg:province":"Asturias",
    "wof:name":"Astesa Asturiana De Techos S.a.",
    "wof:placetype":"venue"
},
  "geometry": {"coordinates":[-5.8331799507,43.3693237305],"type":"Point"}
}