{
  "type": "Feature",
  "properties": {
    "iso:country":"ES",
    "sg:address":"Cmno Andaluces, 21",
    "sg:city":"Burgos",
    "sg:orig_category":"Chapister\u00cda",
    "sg:phone":"+34 947 48 64 08",
    "sg:postcode":"09007",
    "sg:province":"Burgos",
    "wof:name":"Perez Juez Francisco Jose",
    "wof:placetype":"venue"
},
  "geometry": {"coordinates":[-3.6495990753,42.344959259],"type":"Point"}
}