{
  "type": "Feature",
  "properties": {
    "addr:full":"Carrer de Gran De Sant Andreu, 152 Barcelona Barcelona 08030",
    "addr:housenumber":"152",
    "addr:postcode":"08030",
    "addr:street":"Carrer De Gran De Sant Andreu",
    "iso:country":"ES",
    "sg:address":"Carrer de Gran De Sant Andreu, 152",
    "sg:city":"Barcelona",
    "sg:orig_category":"Bancos",
    "sg:phone":"+34 933 45 45 66",
    "sg:postcode":"08030",
    "sg:province":"Barcelona",
    "sg:website":"www.bancopopular.es",
    "wof:name":"Banco Popular Espa\u00f1ol",
    "wof:placetype":"venue"
},
  "geometry": {"coordinates":[2.1893839836,41.432144165],"type":"Point"}
}