{
  "type": "Feature",
  "properties": {
    "addr:full":"Plaz San Gregorio, 1 Zaragoza Zaragoza 50015",
    "addr:housenumber":"1",
    "addr:postcode":"50015",
    "addr:street":"Plaz San Gregorio",
    "iso:country":"ES",
    "sg:address":"Plaz San Gregorio, 1",
    "sg:city":"Zaragoza",
    "sg:classifiers":[
        {
            "category":"Personal",
            "subcategory":"Barber",
            "type":"Services"
        }
    ],
    "sg:phone":"+34 976 52 81 07",
    "sg:postcode":"50015",
    "sg:province":"Zaragoza",
    "sg:tags":[
        "caballeros",
        "de",
        "peluqueros"
    ],
    "wof:name":"Domens Agreda Raul",
    "wof:placetype":"venue"
},
  "geometry": {"coordinates":[-0.8762800097,41.6605758667],"type":"Point"}
}