{
  "type": "Feature",
  "properties": {
    "iso:country":"ES",
    "sg:address":"Calle de Mejico, 23",
    "sg:city":"Chiclana De La Frontera",
    "sg:orig_category":"Relojer\u00cda (al Por Menor, Reparaci\u00d3n)",
    "sg:phone":"+34 956 40 16 61",
    "sg:postcode":"11130",
    "sg:province":"C\u00e1diz",
    "wof:name":"Romero Delgado Juan Antonio",
    "wof:placetype":"venue"
},
  "geometry": {"coordinates":[-6.141409874,36.4249687195],"type":"Point"}
}