{
  "type": "Feature",
  "properties": {
    "iso:country":"ES",
    "sg:address":"Carrer de Girona, 20",
    "sg:city":"Tordera",
    "sg:orig_category":"Empresas De Escayolas",
    "sg:phone":"+34 937 64 00 99",
    "sg:postcode":"08490",
    "sg:province":"Barcelona",
    "wof:name":"Rodriguez Mendoza Juan",
    "wof:placetype":"venue"
},
  "geometry": {"coordinates":[2.7164299488,41.6961746216],"type":"Point"}
}