{
  "type": "Feature",
  "properties": {
    "addr:full":"Carrer de Ramon Y Cajal, 98 Terrassa Barcelona 08222",
    "addr:housenumber":"98",
    "addr:postcode":"08222",
    "addr:street":"Carrer De Ramon Y Cajal",
    "iso:country":"ES",
    "sg:address":"Carrer de Ramon Y Cajal, 98",
    "sg:city":"Terrassa",
    "sg:orig_category":"Promotores Constructores",
    "sg:phone":"+34 937 85 69 31",
    "sg:postcode":"08222",
    "sg:province":"Barcelona",
    "wof:name":"Barrera Villanueva Diego",
    "wof:placetype":"venue"
},
  "geometry": {"coordinates":[2.0249540806,41.560043335],"type":"Point"}
}