{
  "type": "Feature",
  "properties": {
    "iso:country":"ES",
    "sg:address":"Avda De Niebla, 57",
    "sg:city":"Bonares",
    "sg:orig_category":"Mec\u00c1nico Del Autom\u00d3vil",
    "sg:phone":"+34 959 36 60 59",
    "sg:postcode":"21830",
    "sg:province":"Huelva",
    "wof:name":"Talleres Avenida Bonares S.l.",
    "wof:placetype":"venue"
},
  "geometry": {"coordinates":[-6.67831707,37.3273353577],"type":"Point"}
}