{
  "type": "Feature",
  "properties": {
    "addr:full":"Pg Ladrillares, 24 Oliva Valencia 46780",
    "addr:housenumber":"24",
    "addr:postcode":"46780",
    "addr:street":"Pg Ladrillares",
    "iso:country":"ES",
    "sg:address":"Pg Ladrillares, 24",
    "sg:city":"Oliva",
    "sg:orig_category":"F\u00c1bricas De Ladrillo Y Tejas",
    "sg:phone":"+34 962 85 13 98",
    "sg:postcode":"46780",
    "sg:province":"Valencia",
    "wof:name":"Ceramicas Arlandis S. L.",
    "wof:placetype":"venue"
},
  "geometry": {"coordinates":[-0.1179220006,38.9189491272],"type":"Point"}
}