{
  "type": "Feature",
  "properties": {
    "iso:country":"ES",
    "sg:address":"Calle de Cesar Elguezabal, 32",
    "sg:city":"Alacant",
    "sg:orig_category":"Centros Empresariales",
    "sg:phone":"+34 965 20 11 44",
    "sg:postcode":"03001",
    "sg:province":"Alicante",
    "wof:name":"Asociacion De Empresarios De Garajes",
    "wof:placetype":"venue"
},
  "geometry": {"coordinates":[-0.4866107106,38.3457107544],"type":"Point"}
}