{
  "type": "Feature",
  "properties": {
    "iso:country":"ES",
    "sg:address":"Avenida De Benedicto Ruiz, S/n",
    "sg:city":"Ajo",
    "sg:orig_category":"Molduras, Junquillos, Listones Y Molduras Perforadas",
    "sg:phone":"+34 942 62 10 14",
    "sg:postcode":"39170",
    "sg:province":"Cantabria",
    "wof:name":"Sanchez Sisniega Agustin",
    "wof:placetype":"venue"
},
  "geometry": {"coordinates":[-3.6131091118,43.4765663147],"type":"Point"}
}