{
  "type": "Feature",
  "properties": {
    "iso:country":"ES",
    "sg:address":"Ctra Pesquera, Km. 0001,0",
    "sg:city":"Pe\u00f1afiel",
    "sg:orig_category":"Cooperativas Agr\u00cdcolas",
    "sg:phone":"+34 983 87 80 34",
    "sg:postcode":"47300",
    "sg:province":"Valladolid",
    "wof:name":"Cocope S.coop.",
    "wof:placetype":"venue"
},
  "geometry": {"coordinates":[-4.1163568497,41.6057090759],"type":"Point"}
}