{
  "type": "Feature",
  "properties": {
    "addr:full":"Calle de Monteleon, 9 Madrid Madrid 28004",
    "addr:housenumber":"9",
    "addr:postcode":"madrid;28004",
    "addr:street":"Calle De Monteleon",
    "iso:country":"ES",
    "sg:address":"Calle de Monteleon, 9",
    "sg:city":"Madrid",
    "sg:orig_category":"Cerrajer\u00cda, Ferrallista",
    "sg:phone":"+34 914 45 88 90",
    "sg:postcode":"28004",
    "sg:province":"Madrid",
    "wof:name":"Cerrajeria Carlos Rodriguez S.l.",
    "wof:placetype":"venue"
},
  "geometry": {"coordinates":[-3.7050609589,40.4283828735],"type":"Point"}
}