{
  "type": "Feature",
  "properties": {
    "iso:country":"ES",
    "sg:address":"Calle de Eria Del Hospital, 11",
    "sg:city":"Pola De Siero",
    "sg:orig_category":"Inmobiliaria (agencias)",
    "sg:phone":"+34 985 72 30 37",
    "sg:postcode":"33510",
    "sg:province":"Asturias",
    "wof:name":"Inmobiliaria Prosiero S.a.",
    "wof:placetype":"venue"
},
  "geometry": {"coordinates":[-5.6632819176,43.3917999268],"type":"Point"}
}