{
  "type": "Feature",
  "properties": {
    "addr:full":"Libertad, 25 Aljucer Murcia 30152",
    "addr:housenumber":"25",
    "addr:postcode":"30152",
    "addr:street":"Libertad",
    "iso:country":"ES",
    "sg:address":"Libertad, 25",
    "sg:city":"Aljucer",
    "sg:orig_category":"Electrodom\u00c9sticos (fabricaci\u00d3n, Al Por Mayor)",
    "sg:phone":"+34 968 34 76 89",
    "sg:postcode":"30152",
    "sg:province":"Murcia",
    "wof:name":"Barcas Electrodomesticos S.l.",
    "wof:placetype":"venue"
},
  "geometry": {"coordinates":[-1.1547880173,37.9569854736],"type":"Point"}
}