{
  "type": "Feature",
  "properties": {
    "iso:country":"ES",
    "sg:address":"Carr Alemanya, 63",
    "sg:city":"Badalona",
    "sg:orig_category":"Ropa Para Caballeros Y Se\u00d1oras (al Por Mayor)",
    "sg:phone":"+34 934 97 02 51",
    "sg:postcode":"08917",
    "sg:province":"Barcelona",
    "wof:name":"Msg Moda S.l.",
    "wof:placetype":"venue"
},
  "geometry": {"coordinates":[2.2234721184,41.4606056213],"type":"Point"}
}