{
  "type": "Feature",
  "properties": {
    "addr:full":"Csri Cucaracha (la), 1 Florida Santa Cruz De Tenerife 38430",
    "addr:postcode":"38430",
    "addr:street":"La 1",
    "iso:country":"ES",
    "sg:address":"Csri Cucaracha (la), 1",
    "sg:city":"Florida",
    "sg:orig_category":"Iglesia Cat\u00d3lica",
    "sg:phone":"+34 922 82 88 55",
    "sg:postcode":"38430",
    "sg:province":"Santa Cruz De Tenerife",
    "wof:name":"Parroquia De Santa Barbara Martir",
    "wof:placetype":"venue"
},
  "geometry": {"coordinates":[-16.7204761505,28.3677654266],"type":"Point"}
}