{
  "type": "Feature",
  "properties": {
    "addr:full":"Carr Carlos Sarthou, 10 Villarreal Castell\u00f3n 12540",
    "addr:housenumber":"10",
    "addr:postcode":"12540",
    "addr:street":"Carr Carlos Sarthou",
    "iso:country":"ES",
    "sg:address":"Carr Carlos Sarthou, 10",
    "sg:city":"Villarreal",
    "sg:orig_category":"Aguas (distribuci\u00d3n, Servicios)",
    "sg:phone":"+34 964 52 76 80",
    "sg:postcode":"12540",
    "sg:province":"Castell\u00f3n",
    "wof:name":"Sociedad De Fomento Agricola Castellonense S.a.",
    "wof:placetype":"venue"
},
  "geometry": {"coordinates":[-0.0976689979,39.9358024597],"type":"Point"}
}