{
  "type": "Feature",
  "properties": {
    "iso:country":"ES",
    "sg:address":"Av Rei Jaume I, 103",
    "sg:city":"Santa Pon\u00c7a",
    "sg:orig_category":"Supermercados Y Hipermercados",
    "sg:phone":"+34 971 69 36 73",
    "sg:postcode":"07180",
    "sg:province":"Islas Baleares",
    "wof:name":"Mu\u00f1oz Mu\u00f1oz Santiago",
    "wof:placetype":"venue"
},
  "geometry": {"coordinates":[2.4793469906,39.5136604309],"type":"Point"}
}