{
  "type": "Feature",
  "properties": {
    "iso:country":"ES",
    "sg:address":"Avda Andalucia, 17",
    "sg:city":"Ronda",
    "sg:orig_category":"Arreglo, Reparaci\u00d3n, Piezas Sueltas De Televisi\u00d3n, V\u00cddeo, Hi",
    "sg:phone":"+34 952 87 58 35",
    "sg:postcode":"29400",
    "sg:province":"M\u00e1laga",
    "wof:name":"Auvitel S.c.",
    "wof:placetype":"venue"
},
  "geometry": {"coordinates":[-5.1633477211,36.7472114563],"type":"Point"}
}