{
  "type": "Feature",
  "properties": {
    "addr:full":"Calle de Londres, 31 Madrid Madrid 28028",
    "addr:housenumber":"31",
    "addr:postcode":"madrid;28028",
    "addr:street":"Calle De Londres",
    "iso:country":"ES",
    "sg:address":"Calle de Londres, 31",
    "sg:city":"Madrid",
    "sg:orig_category":"Venta, Alquiler De Plataformas Y Barquillas Elevadoras",
    "sg:phone":"+34 913 55 21 23",
    "sg:postcode":"28028",
    "sg:province":"Madrid",
    "sg:website":"www.inelsazener.com",
    "wof:name":"Industrial De Elevacion S.a.",
    "wof:placetype":"venue"
},
  "geometry": {"coordinates":[-3.6678340435,40.4317092896],"type":"Point"}
}