{
  "type": "Feature",
  "properties": {
    "iso:country":"ES",
    "sg:address":"Gta Carlos Pinilla, 2",
    "sg:city":"Le\u00f3n",
    "sg:orig_category":"Tiendas De Grano, Frutas Y Legumbres Secas (al Por Menor)",
    "sg:phone":"+34 987 24 57 71",
    "sg:postcode":"24010",
    "sg:province":"Le\u00f3n",
    "wof:name":"Sanchez Sanchez Rosario",
    "wof:placetype":"venue"
},
  "geometry": {"coordinates":[-5.5886440277,42.6022109985],"type":"Point"}
}