{
  "type": "Feature",
  "properties": {
    "iso:country":"ES",
    "sg:address":"Carr Mas Clara, S/n",
    "sg:city":"Bisbal D'emporda",
    "sg:orig_category":"Polideportivos",
    "sg:phone":"+34 972 64 21 98",
    "sg:postcode":"17100",
    "sg:province":"Girona",
    "wof:name":"Ajuntament De La Bisbal D'emporda",
    "wof:placetype":"venue"
},
  "geometry": {"coordinates":[3.0396478176,41.9651527405],"type":"Point"}
}