{
  "type": "Feature",
  "properties": {
    "iso:country":"ES",
    "sg:address":"Almu\u00f1a, 21",
    "sg:city":"Luarca",
    "sg:orig_category":"Comercio De Hierro",
    "sg:phone":"+34 985 64 03 89",
    "sg:postcode":"33700",
    "sg:province":"Asturias",
    "wof:name":"Garcia Valencia Esteban",
    "wof:placetype":"venue"
},
  "geometry": {"coordinates":[-6.5284996033,43.5388145447],"type":"Point"}
}