{
  "type": "Feature",
  "properties": {
    "iso:country":"ES",
    "sg:address":"Carr D'isaac Albeniz, 37",
    "sg:city":"Benicarlo",
    "sg:orig_category":"Electricidad: Equipos Industriales, Componentes (fabricaci\u00d3n)",
    "sg:phone":"+34 964 47 53 04",
    "sg:postcode":"12580",
    "sg:province":"Castell\u00f3n",
    "wof:name":"Mapensa C.b.",
    "wof:placetype":"venue"
},
  "geometry": {"coordinates":[0.4193499982,40.417766571],"type":"Point"}
}