{
  "type": "Feature",
  "properties": {
    "addr:full":"Rua Quinteiro Da Laxe, 13 Laxe Pontevedra 36613",
    "addr:housenumber":"13",
    "addr:postcode":"36613",
    "addr:street":"Rua Quinteiro Da Laxe",
    "iso:country":"ES",
    "sg:address":"Rua Quinteiro Da Laxe, 13",
    "sg:city":"Laxe",
    "sg:orig_category":"Carpinteros",
    "sg:phone":"+34 986 50 37 12",
    "sg:postcode":"36613",
    "sg:province":"Pontevedra",
    "wof:name":"Construcciones Metalicas Cuevas S.l.",
    "wof:placetype":"venue"
},
  "geometry": {"coordinates":[-8.7695436478,42.6105308533],"type":"Point"}
}