{
  "type": "Feature",
  "properties": {
    "addr:full":"Carr Dels Caputxins, S/n Ontinyent Valencia 46870",
    "addr:housenumber":"s / n",
    "addr:postcode":"46870",
    "addr:street":"Carr Dels Caputxins",
    "iso:country":"ES",
    "sg:address":"Carr Dels Caputxins, S/n",
    "sg:city":"Ontinyent",
    "sg:orig_category":"Empresas De Hormig\u00d3n, Hormig\u00d3n Armado Y Pretensado",
    "sg:phone":"+34 962 91 17 27",
    "sg:postcode":"46870",
    "sg:province":"Valencia",
    "wof:name":"Pretobe S.a.l.",
    "wof:placetype":"venue"
},
  "geometry": {"coordinates":[-0.5999789834,38.8209152222],"type":"Point"}
}