{
  "type": "Feature",
  "properties": {
    "iso:country":"ES",
    "sg:address":"Carrer de Montsia, 31",
    "sg:city":"Poligono Industrial Can Carner",
    "sg:orig_category":"Muebles",
    "sg:phone":"+34 937 47 26 14",
    "sg:postcode":"08211",
    "sg:province":"Barcelona",
    "wof:name":"Seliom S.l.",
    "wof:placetype":"venue"
},
  "geometry": {"coordinates":[2.0824799538,41.6114387512],"type":"Point"}
}