{
  "type": "Feature",
  "properties": {
    "addr:full":"Calle de Orense, 18 Madrid Madrid 28020",
    "addr:housenumber":"18",
    "addr:postcode":"madrid;28020",
    "addr:street":"Calle De Orense",
    "iso:country":"ES",
    "sg:address":"Calle de Orense, 18",
    "sg:city":"Madrid",
    "sg:orig_category":"\u00d3ptica: Instrumentos (fabricaci\u00d3n)",
    "sg:phone":"+34 915 56 91 78",
    "sg:postcode":"28020",
    "sg:province":"Madrid",
    "sg:website":"www.generaloptica.es",
    "wof:name":"General Optica S.a.",
    "wof:placetype":"venue"
},
  "geometry": {"coordinates":[-3.6950469017,40.4500007629],"type":"Point"}
}