{
  "type": "Feature",
  "properties": {
    "addr:full":"Calle de Auriz, S/n Adios Navarra 31153",
    "addr:housenumber":"s",
    "addr:postcode":"31153",
    "addr:street":"Calle De Auriz;/ N Adios Navarra",
    "iso:country":"ES",
    "sg:address":"Calle de Auriz, S/n",
    "sg:city":"Adios",
    "sg:orig_category":"Poller\u00cda Y Caza (al Por Menor)",
    "sg:phone":"+34 948 39 00 69",
    "sg:postcode":"31153",
    "sg:province":"Navarra",
    "wof:name":"Perez Eguilondo Cecilio",
    "wof:placetype":"venue"
},
  "geometry": {"coordinates":[-1.7367870808,42.6873474121],"type":"Point"}
}