{
  "type": "Feature",
  "properties": {
    "iso:country":"ES",
    "sg:address":"Carrer de Francesc Layret, 13",
    "sg:city":"Hospitalet Llobregat",
    "sg:orig_category":"Inmobiliaria (agencias)",
    "sg:phone":"+34 934 49 13 87",
    "sg:postcode":"08903",
    "sg:province":"Barcelona",
    "wof:name":"Guatavita Barcelonesa S.l.",
    "wof:placetype":"venue"
},
  "geometry": {"coordinates":[2.1201379299,41.3762588501],"type":"Point"}
}