{
  "type": "Feature",
  "properties": {
    "addr:full":"Avda Concepcion Arenal, 144 Praia Pontevedra 36950",
    "addr:housenumber":"144",
    "addr:postcode":"36950",
    "addr:street":"Avda Concepcion Arenal",
    "iso:country":"ES",
    "sg:address":"Avda Concepcion Arenal, 144",
    "sg:city":"Praia",
    "sg:orig_category":"Fabricaci\u00d3n De Sobres, Bolsas Y Fundas",
    "sg:phone":"+34 986 31 49 11",
    "sg:postcode":"36950",
    "sg:province":"Pontevedra",
    "wof:name":"Elas C.b.",
    "wof:placetype":"venue"
},
  "geometry": {"coordinates":[-8.738442421,42.2772254944],"type":"Point"}
}