{
  "type": "Feature",
  "properties": {
    "iso:country":"ES",
    "sg:address":"Carrer de Francesc Macia, 20",
    "sg:city":"Granollers",
    "sg:orig_category":"Tintes (fabricaci\u00d3n, Al Por Mayor)",
    "sg:phone":"+34 938 70 54 99",
    "sg:postcode":"08401",
    "sg:province":"Barcelona",
    "wof:name":"Saborit Salvador Montserrat",
    "wof:placetype":"venue"
},
  "geometry": {"coordinates":[2.2875730991,41.6027793884],"type":"Point"}
}