{
  "type": "Feature",
  "properties": {
    "iso:country":"ES",
    "sg:address":"Calle de Rodriguez Fabres, 20",
    "sg:city":"Salamanca",
    "sg:orig_category":"Peluqueros: De Se\u00d1oras",
    "sg:phone":"+34 923 22 82 44",
    "sg:postcode":"37005",
    "sg:province":"Salamanca",
    "wof:name":"Concha Peluqueria-estetica S.l.",
    "wof:placetype":"venue"
},
  "geometry": {"coordinates":[-5.6621670723,40.9713172913],"type":"Point"}
}