{
  "type": "Feature",
  "properties": {
    "iso:country":"ES",
    "sg:address":"Calle de Arquitectura, 125",
    "sg:city":"Pozuelo De Alarcon",
    "sg:orig_category":"Instalaci\u00d3n, Preparaci\u00d3n De Exposiciones, Ferias, Salones",
    "sg:phone":"+34 913 52 46 47",
    "sg:postcode":"28224",
    "sg:province":"Madrid",
    "wof:name":"D. Y P. Dise\u00f1o Y Publicidad S. A.",
    "wof:placetype":"venue"
},
  "geometry": {"coordinates":[-3.8115816116,40.4541969299],"type":"Point"}
}