{
  "type": "Feature",
  "properties": {
    "addr:full":"Calle de Menendez Y Pelayo, 3 Cartagena Murcia 30204",
    "addr:housenumber":"3",
    "addr:postcode":"30204",
    "addr:street":"Calle De Menendez Y Pelayo",
    "iso:country":"ES",
    "sg:address":"Calle de Menendez Y Pelayo, 3",
    "sg:city":"Cartagena",
    "sg:orig_category":"M\u00c9dicos: Pediatr\u00cda. Enfermedades De Los Ni\u00d1os",
    "sg:phone":"+34 968 12 18 95",
    "sg:postcode":"30204",
    "sg:province":"Murcia",
    "wof:name":"Gonzalez Perez Angel Javier",
    "wof:placetype":"venue"
},
  "geometry": {"coordinates":[-0.9920430183,37.6055374146],"type":"Point"}
}