{
  "type": "Feature",
  "properties": {
    "iso:country":"ES",
    "sg:address":"Calle de Cueva De La Mora, 14",
    "sg:city":"Villaviciosa Odon",
    "sg:orig_category":"Molduras, Junquillos, Listones Y Molduras Perforadas",
    "sg:phone":"+34 916 16 17 20",
    "sg:postcode":"28670",
    "sg:province":"Madrid",
    "wof:name":"Gomez Medina Francisca",
    "wof:placetype":"venue"
},
  "geometry": {"coordinates":[-3.921787262,40.346496582],"type":"Point"}
}