{
  "type": "Feature",
  "properties": {
    "addr:full":"Calle de Amalia Alayon, 22 Cristianos Santa Cruz De Tenerife 38650",
    "addr:housenumber":"22",
    "addr:postcode":"38650",
    "addr:street":"Calle De Amalia Alayon",
    "iso:country":"ES",
    "sg:address":"Calle de Amalia Alayon, 22",
    "sg:city":"Cristianos",
    "sg:orig_category":"Muebles, Minoristas",
    "sg:phone":"+34 922 79 39 65",
    "sg:postcode":"38650",
    "sg:province":"Santa Cruz De Tenerife",
    "sg:website":"www.mlcmuebles.com",
    "wof:name":"Muebles Los Cristianos S.l.",
    "wof:placetype":"venue"
},
  "geometry": {"coordinates":[-16.7148685455,28.0531005859],"type":"Point"}
}