{
  "type": "Feature",
  "properties": {
    "addr:full":"C/ Pau Casals, 33 Ripollet Barcelona 08291",
    "addr:housenumber":"33",
    "addr:postcode":"08291",
    "addr:street":"C / Pau Casals",
    "iso:country":"ES",
    "sg:address":"C/ Pau Casals, 33",
    "sg:city":"Ripollet",
    "sg:orig_category":"Fabricaci\u00d3n De Pastas Alimentarias",
    "sg:phone":"+34 936 92 17 21",
    "sg:postcode":"08291",
    "sg:province":"Barcelona",
    "sg:website":"www.fadaic.com",
    "wof:name":"Fabricacion De Alimentos S. A.",
    "wof:placetype":"venue"
},
  "geometry": {"coordinates":[2.1599640846,41.4968681335],"type":"Point"}
}