{
  "type": "Feature",
  "properties": {
    "addr:full":"Carr Doctor Moliner, 24 Sueca Valencia 46410",
    "addr:housenumber":"24",
    "addr:postcode":"46410",
    "addr:street":"Carr Doctor Moliner",
    "iso:country":"ES",
    "sg:address":"Carr Doctor Moliner, 24",
    "sg:city":"Sueca",
    "sg:orig_category":"Ingenier\u00cda, Centros De Estudios (diversos)",
    "sg:phone":"+34 961 77 08 02",
    "sg:postcode":"46410",
    "sg:province":"Valencia",
    "wof:name":"Torregrosa Cebolla Jose",
    "wof:placetype":"venue"
},
  "geometry": {"coordinates":[-0.3142359853,39.2031097412],"type":"Point"}
}