{
  "type": "Feature",
  "properties": {
    "addr:full":"Calle de Major, 13 Burriana Castell\u00f3n 12530",
    "addr:housenumber":"13",
    "addr:postcode":"12530",
    "addr:street":"Calle De Major",
    "iso:country":"ES",
    "sg:address":"Calle de Major, 13",
    "sg:city":"Burriana",
    "sg:orig_category":"Zapatos (al Por Menor)",
    "sg:phone":"+34 964 51 28 25",
    "sg:postcode":"12530",
    "sg:province":"Castell\u00f3n",
    "wof:name":"Pitarch Borja Maria Jose",
    "wof:placetype":"venue"
},
  "geometry": {"coordinates":[-0.0833270028,39.8904151917],"type":"Point"}
}