{
  "type": "Feature",
  "properties": {
    "addr:full":"A Ri\u00f1a, 42 Oia Pontevedra 36794",
    "addr:housenumber":"42",
    "addr:postcode":"36794",
    "addr:street":"Rin\u0303A",
    "iso:country":"ES",
    "sg:address":"A Ri\u00f1a, 42",
    "sg:city":"Oia",
    "sg:classifiers":[
        {
            "category":"Autos & Motor Vehicles",
            "subcategory":"Automobile Sales",
            "type":"Retail Goods"
        }
    ],
    "sg:phone":"+34 986 36 22 51",
    "sg:postcode":"36794",
    "sg:province":"Pontevedra",
    "wof:name":"Soto Trabazos Jesus Manuel",
    "wof:placetype":"venue"
},
  "geometry": {"coordinates":[-8.875213623,42.0058250427],"type":"Point"}
}