{
  "type": "Feature",
  "properties": {
    "addr:full":"Calle de Jesusa Lara, 43 Estacion Madrid 28250",
    "addr:housenumber":"43",
    "addr:postcode":"28250",
    "addr:street":"Calle De Jesusa Lara",
    "iso:country":"ES",
    "sg:address":"Calle de Jesusa Lara, 43",
    "sg:city":"Estacion",
    "sg:orig_category":"Alquiler De V\u00cddeo",
    "sg:phone":"+34 918 59 26 11",
    "sg:postcode":"28250",
    "sg:province":"Madrid",
    "wof:name":"Fernandez Aguado Alfonso",
    "wof:placetype":"venue"
},
  "geometry": {"coordinates":[-3.9552099705,40.5790100098],"type":"Point"}
}