{
  "type": "Feature",
  "properties": {
    "addr:full":"Calle de Salamanca, 10 Granada Granada 18001",
    "addr:housenumber":"10",
    "addr:postcode":"18001",
    "addr:street":"Calle De Salamanca",
    "iso:country":"ES",
    "sg:address":"Calle de Salamanca, 10",
    "sg:city":"Granada",
    "sg:orig_category":"Abogados",
    "sg:phone":"+34 958 52 16 70",
    "sg:postcode":"18001",
    "sg:province":"Granada",
    "wof:name":"Moral Cambil Juan Luis Del",
    "wof:placetype":"venue"
},
  "geometry": {"coordinates":[-3.5996232033,37.1745376587],"type":"Point"}
}