{
  "type": "Feature",
  "properties": {
    "iso:country":"ES",
    "sg:address":"Carrer de Llorens I Barba, 12",
    "sg:city":"Barcelona",
    "sg:orig_category":"Empresarios",
    "sg:phone":"+34 934 56 49 37",
    "sg:postcode":"08025",
    "sg:province":"Barcelona",
    "wof:name":"Saversan 21 S.l.",
    "wof:placetype":"venue"
},
  "geometry": {"coordinates":[2.1691739559,41.4108810425],"type":"Point"}
}