{
  "type": "Feature",
  "properties": {
    "addr:full":"Vrda Del Pozo, 9 Dolores Alicante 03150",
    "addr:housenumber":"9",
    "addr:postcode":"03150",
    "addr:street":"Del Pozo",
    "iso:country":"ES",
    "sg:address":"Vrda Del Pozo, 9",
    "sg:city":"Dolores",
    "sg:orig_category":"Fabricaci\u00d3n De Distribuidores Autom\u00c1ticos",
    "sg:phone":"+34 965 72 66 74",
    "sg:postcode":"03150",
    "sg:province":"Alicante",
    "wof:name":"Hernandez Fernandez Jose",
    "wof:placetype":"venue"
},
  "geometry": {"coordinates":[-0.7697039843,38.1368637085],"type":"Point"}
}