{
  "type": "Feature",
  "properties": {
    "iso:country":"ES",
    "sg:address":"Carrer de Singladura, 23",
    "sg:city":"Can Pastilla",
    "sg:orig_category":"Cl\u00cdnicas M\u00c9dicas",
    "sg:phone":"+34 971 26 68 09",
    "sg:postcode":"07610",
    "sg:province":"Islas Baleares",
    "wof:name":"Centro Medico Salus Mallorca S.l.",
    "wof:placetype":"venue"
},
  "geometry": {"coordinates":[2.7189800739,39.5357513428],"type":"Point"}
}