{
  "type": "Feature",
  "properties": {
    "addr:full":"Rua Maria Berdiales, 11 Vigo Pontevedra 36203",
    "addr:housenumber":"11",
    "addr:postcode":"36203",
    "addr:street":"Rua Maria Berdiales",
    "iso:country":"ES",
    "sg:address":"Rua Maria Berdiales, 11",
    "sg:city":"Vigo",
    "sg:orig_category":"Abogados",
    "sg:phone":"+34 986 22 99 65",
    "sg:postcode":"36203",
    "sg:province":"Pontevedra",
    "wof:name":"Ortiz Fernandez Eva Maria",
    "wof:placetype":"venue"
},
  "geometry": {"coordinates":[-8.7196798325,42.2350006104],"type":"Point"}
}