{
  "type": "Feature",
  "properties": {
    "addr:full":"Carrer de Bartrina, 21 Rubi Barcelona 08191",
    "addr:housenumber":"21",
    "addr:postcode":"08191",
    "addr:street":"Carrer De Bartrina",
    "iso:country":"ES",
    "sg:address":"Carrer de Bartrina, 21",
    "sg:city":"Rubi",
    "sg:orig_category":"Zapatos (al Por Menor)",
    "sg:phone":"+34 935 88 50 25",
    "sg:postcode":"08191",
    "sg:province":"Barcelona",
    "wof:name":"Pierucci S.a.",
    "wof:placetype":"venue"
},
  "geometry": {"coordinates":[2.0380029678,41.4882965088],"type":"Point"}
}