{
  "type": "Feature",
  "properties": {
    "iso:country":"ES",
    "sg:address":"Ctra Taiala, S/n",
    "sg:city":"Girona",
    "sg:orig_category":"Promotores Constructores",
    "sg:phone":"+34 972 22 05 79",
    "sg:postcode":"17007",
    "sg:province":"Girona",
    "wof:name":"Tarres Espigol Pedro",
    "wof:placetype":"venue"
},
  "geometry": {"coordinates":[2.806885004,41.9941711426],"type":"Point"}
}