{
  "type": "Feature",
  "properties": {
    "addr:full":"Calle de Gerona, 19 Alacant Alicante 03001",
    "addr:housenumber":"19",
    "addr:postcode":"03001",
    "addr:street":"Calle De Gerona",
    "iso:country":"ES",
    "sg:address":"Calle de Gerona, 19",
    "sg:city":"Alacant",
    "sg:orig_category":"Abogados",
    "sg:phone":"+34 965 14 41 00",
    "sg:postcode":"03001",
    "sg:province":"Alicante",
    "wof:name":"Abogados Trivium S.c.",
    "wof:placetype":"venue"
},
  "geometry": {"coordinates":[-0.485882,38.344318],"type":"Point"}
}