{
  "type": "Feature",
  "properties": {
    "addr:full":"Calle de Puerto De Canfranc, 3 Madrid Madrid 28038",
    "addr:housenumber":"3",
    "addr:postcode":"28038",
    "addr:street":"Calle De Puerto De Canfranc",
    "iso:country":"ES",
    "sg:address":"Calle de Puerto De Canfranc, 3",
    "sg:city":"Madrid",
    "sg:orig_category":"Cerrajer\u00cda, Ferrallista",
    "sg:phone":"+34 914 77 15 39",
    "sg:postcode":"28038",
    "sg:province":"Madrid",
    "wof:name":"Cooperativa Cerrajera Canfranc",
    "wof:placetype":"venue"
},
  "geometry": {"coordinates":[-3.6640241146,40.3962173462],"type":"Point"}
}