{
  "type": "Feature",
  "properties": {
    "addr:full":"Pg Manuel Girona, 14 Barcelona Barcelona 08034",
    "addr:housenumber":"14",
    "addr:postcode":"08034",
    "addr:street":"Pg Manuel Girona",
    "iso:country":"ES",
    "sg:address":"Pg Manuel Girona, 14",
    "sg:city":"Barcelona",
    "sg:orig_category":"Cajas De Ahorro",
    "sg:phone":"+34 932 05 09 19",
    "sg:postcode":"08034",
    "sg:province":"Barcelona",
    "wof:name":"Caixa D'estalvis I Pensions De Barcelona",
    "wof:placetype":"venue"
},
  "geometry": {"coordinates":[2.1211819649,41.3900527954],"type":"Point"}
}