{
  "type": "Feature",
  "properties": {
    "iso:country":"ES",
    "sg:address":"Calle de Muro, 11",
    "sg:city":"Valladolid",
    "sg:orig_category":"Ropa Para Se\u00d1oras Y Caballeros (al Por Menor)",
    "sg:phone":"+34 983 29 78 67",
    "sg:postcode":"47004",
    "sg:province":"Valladolid",
    "wof:name":"Gonzalez Mayo Angel",
    "wof:placetype":"venue"
},
  "geometry": {"coordinates":[-4.7248859406,41.6460723877],"type":"Point"}
}