{
  "type": "Feature",
  "properties": {
    "addr:full":"Rua Real, 147 Ferrol La Coru\u00f1a 15402",
    "addr:housenumber":"147",
    "addr:postcode":"15402",
    "addr:street":"Rua Real;La Corun\u0303A",
    "iso:country":"ES",
    "sg:address":"Rua Real, 147",
    "sg:city":"Ferrol",
    "sg:orig_category":"Expertos Contables, Revisores De Cuentas",
    "sg:phone":"+34 981 35 50 75",
    "sg:postcode":"15402",
    "sg:province":"La Coru\u00f1a",
    "wof:name":"Mejuto Trasmonte Daniel",
    "wof:placetype":"venue"
},
  "geometry": {"coordinates":[-8.2347402573,43.4830627441],"type":"Point"}
}