{
  "type": "Feature",
  "properties": {
    "iso:country":"ES",
    "sg:address":"Calle de Calvario, S/n",
    "sg:city":"San Miguel Del Valle",
    "sg:orig_category":"Centros De Educaci\u00d3n Especial",
    "sg:phone":"+34 980 66 58 88",
    "sg:postcode":"49680",
    "sg:province":"Zamora",
    "wof:name":"Colegio Rural Agrupado De San Cristobal",
    "wof:placetype":"venue"
},
  "geometry": {"coordinates":[-5.4976911545,42.0300521851],"type":"Point"}
}