{
  "type": "Feature",
  "properties": {
    "addr:full":"Pol. Ind Vidreres, 1 Vidreres Girona 17411",
    "addr:housenumber":"1",
    "addr:postcode":"17411",
    "addr:street":"Vidreres",
    "iso:country":"ES",
    "sg:address":"Pol. Ind Vidreres, 1",
    "sg:city":"Vidreres",
    "sg:orig_category":"Alimentaci\u00d3n General (al Por Menor)",
    "sg:phone":"+34 972 85 04 75",
    "sg:postcode":"17411",
    "sg:province":"Girona",
    "sg:website":"www.hnoscanals.com",
    "wof:name":"Hermanos Canals S. A.",
    "wof:placetype":"venue"
},
  "geometry": {"coordinates":[2.7773220539,41.789768219],"type":"Point"}
}