{
  "type": "Feature",
  "properties": {
    "iso:country":"ES",
    "sg:address":"Ptda Tolls, S/n",
    "sg:city":"Benidorm",
    "sg:orig_category":"Aguas (distribuci\u00d3n, Servicios)",
    "sg:phone":"+34 965 86 27 85",
    "sg:postcode":"03500",
    "sg:province":"Alicante",
    "wof:name":"Aquagest Levante S.a.",
    "wof:placetype":"venue"
},
  "geometry": {"coordinates":[-0.130487293,38.50233078],"type":"Point"}
}