{
  "type": "Feature",
  "properties": {
    "iso:country":"ES",
    "sg:address":"Calle de Tembleque, 144",
    "sg:city":"Madrid",
    "sg:orig_category":"Radiocomunicaciones, Telefon\u00cda M\u00d3vil, Radiomensajer\u00cda: Servicios, Comercializaci\u00d3n",
    "sg:phone":"+34 915 12 00 06",
    "sg:postcode":"28024",
    "sg:province":"Madrid",
    "wof:name":"Santacruz Gavilanez Monica Patricia",
    "wof:placetype":"venue"
},
  "geometry": {"coordinates":[-3.7647259235,40.3915328979],"type":"Point"}
}