{
  "type": "Feature",
  "properties": {
    "iso:country":"ES",
    "sg:address":"Pg Verdaguer, 169",
    "sg:city":"Igualada",
    "sg:orig_category":"Loter\u00cda Y T\u00d3mbola",
    "sg:phone":"+34 938 04 27 01",
    "sg:postcode":"08700",
    "sg:province":"Barcelona",
    "wof:name":"De Ramon Torrellardona Antonio",
    "wof:placetype":"venue"
},
  "geometry": {"coordinates":[1.6292439699,41.5785179138],"type":"Point"}
}