{
  "type": "Feature",
  "properties": {
    "addr:full":"Calle de General Solchaga, 85 Valladolid Valladolid 47008",
    "addr:housenumber":"85",
    "addr:postcode":"47008",
    "addr:street":"Calle De General Solchaga",
    "iso:country":"ES",
    "sg:address":"Calle de General Solchaga, 85",
    "sg:city":"Valladolid",
    "sg:orig_category":"Carros Elevadores, Carros De Operaciones Portuarias",
    "sg:phone":"+34 983 22 01 99",
    "sg:postcode":"47008",
    "sg:province":"Valladolid",
    "wof:name":"Maquinaria Gonzalvo S.l.",
    "wof:placetype":"venue"
},
  "geometry": {"coordinates":[-4.7345108986,41.6252288818],"type":"Point"}
}