{
  "type": "Feature",
  "properties": {
    "iso:country":"ES",
    "sg:address":"Carrer de Gava, 77",
    "sg:city":"Barcelona",
    "sg:orig_category":"Agentes, Concesionarios Y Sucursales De Veh\u00cdculos",
    "sg:phone":"+34 934 31 35 43",
    "sg:postcode":"08014",
    "sg:province":"Barcelona",
    "wof:name":"Autogarvi Hostafranrcs S.l.",
    "wof:placetype":"venue"
},
  "geometry": {"coordinates":[2.1387701035,41.3703231812],"type":"Point"}
}