{
  "type": "Feature",
  "properties": {
    "addr:full":"Calle de Seixo, 2 Cangas Pontevedra 36940",
    "addr:housenumber":"2",
    "addr:postcode":"36940",
    "addr:street":"Calle De Seixo",
    "iso:country":"ES",
    "sg:address":"Calle de Seixo, 2",
    "sg:city":"Cangas",
    "sg:orig_category":"Empresas De Carpinter\u00cda",
    "sg:phone":"+34 986 30 29 11",
    "sg:postcode":"36940",
    "sg:province":"Pontevedra",
    "wof:name":"Aluminios Mallo S.l.",
    "wof:placetype":"venue"
},
  "geometry": {"coordinates":[-8.7875614166,42.2603340149],"type":"Point"}
}