{
  "type": "Feature",
  "properties": {
    "addr:full":"Avda Doctor Palos, 3 Sagunt Valencia 46500",
    "addr:housenumber":"3",
    "addr:postcode":"46500",
    "addr:street":"Avda Doctor Palos",
    "iso:country":"ES",
    "sg:address":"Avda Doctor Palos, 3",
    "sg:city":"Sagunt",
    "sg:orig_category":"Ense\u00d1anza, Formaci\u00d3n Profesional: Aprendizaje",
    "sg:phone":"+34 962 65 00 65",
    "sg:postcode":"46500",
    "sg:province":"Valencia",
    "wof:name":"Generalitat Valenciana",
    "wof:placetype":"venue"
},
  "geometry": {"coordinates":[-0.2792856097,39.6817436218],"type":"Point"}
}