{
  "type": "Feature",
  "properties": {
    "addr:full":"Carrer de Sierra Nevada, 186 Terrassa Barcelona 08227",
    "addr:housenumber":"186",
    "addr:postcode":"08227",
    "addr:street":"Carrer De Sierra Nevada",
    "iso:country":"ES",
    "sg:address":"Carrer de Sierra Nevada, 186",
    "sg:city":"Terrassa",
    "sg:orig_category":"Promotores Constructores",
    "sg:phone":"+34 937 84 24 10",
    "sg:postcode":"08227",
    "sg:province":"Barcelona",
    "wof:name":"Construcciones Y Rehabilitaciones Terrassa S.l.",
    "wof:placetype":"venue"
},
  "geometry": {"coordinates":[2.0411388874,41.5715446472],"type":"Point"}
}