{
  "type": "Feature",
  "properties": {
    "addr:full":"Calle de Alcorisa, 19 Madrid Madrid 28043",
    "addr:housenumber":"19",
    "addr:postcode":"madrid;28043",
    "addr:street":"Calle De Alcorisa",
    "iso:country":"ES",
    "sg:address":"Calle de Alcorisa, 19",
    "sg:city":"Madrid",
    "sg:orig_category":"Farmacias",
    "sg:phone":"+34 913 88 44 90",
    "sg:postcode":"28043",
    "sg:province":"Madrid",
    "wof:name":"Sanz Hernan Paz",
    "wof:placetype":"venue"
},
  "geometry": {"coordinates":[-3.6412739754,40.4629325867],"type":"Point"}
}