{
  "type": "Feature",
  "properties": {
    "iso:country":"ES",
    "sg:address":"Calle de Urquijo-urkijo, 24",
    "sg:city":"Getxo",
    "sg:orig_category":"Ense\u00d1anza: Idiomas",
    "sg:phone":"+34 944 63 93 92",
    "sg:postcode":"48930",
    "sg:province":"Vizcaya",
    "sg:website":"www.kebecidiomas.com",
    "wof:name":"Quebec Idiomas Servicios Ling\u00dcisticos, S.l.",
    "wof:placetype":"venue"
},
  "geometry": {"coordinates":[-3.0139489174,43.3270988464],"type":"Point"}
}