{
  "type": "Feature",
  "properties": {
    "addr:full":"Carrer de Sicilia, 394 Barcelona Barcelona 08025",
    "addr:housenumber":"394",
    "addr:postcode":"08025",
    "addr:street":"Carrer De Sicilia",
    "iso:country":"ES",
    "sg:address":"Carrer de Sicilia, 394",
    "sg:city":"Barcelona",
    "sg:orig_category":"Agentes Generales De Seguros",
    "sg:phone":"+34 934 58 89 94",
    "sg:postcode":"08025",
    "sg:province":"Barcelona",
    "wof:name":"Lopez-miguel Seguros Scp",
    "wof:placetype":"venue"
},
  "geometry": {"coordinates":[2.1679890156,41.4059295654],"type":"Point"}
}