{
  "type": "Feature",
  "properties": {
    "addr:full":"Calle de Tenerias, 75 Castellon Castell\u00f3n 12003",
    "addr:housenumber":"75",
    "addr:postcode":"12003",
    "addr:street":"Calle De Tenerias",
    "iso:country":"ES",
    "sg:address":"Calle de Tenerias, 75",
    "sg:city":"Castellon",
    "sg:orig_category":"Centros Empresariales",
    "sg:phone":"+34 964 22 15 90",
    "sg:postcode":"12003",
    "sg:province":"Castell\u00f3n",
    "wof:name":"The Field Guarantee Group Sl",
    "wof:placetype":"venue"
},
  "geometry": {"coordinates":[-0.0307989996,39.9856681824],"type":"Point"}
}