{
  "type": "Feature",
  "properties": {
    "addr:full":"Trva Hongo, 6 Camu\u00f1as Toledo 45720",
    "addr:housenumber":"6",
    "addr:postcode":"45720",
    "addr:street":"Trva Hongo",
    "iso:country":"ES",
    "sg:address":"Trva Hongo, 6",
    "sg:city":"Camu\u00f1as",
    "sg:orig_category":"Centros De Coordinaci\u00d3n",
    "sg:phone":"+34 925 47 00 23",
    "sg:postcode":"45720",
    "sg:province":"Toledo",
    "wof:name":"Frem Asesores S.l.",
    "wof:placetype":"venue"
},
  "geometry": {"coordinates":[-3.4567580223,39.4286956787],"type":"Point"}
}