{
  "type": "Feature",
  "properties": {
    "addr:full":"Calle de Parrillas, 4 Talavera Reina Toledo 45600",
    "addr:housenumber":"4",
    "addr:postcode":"45600",
    "addr:street":"Calle De Parrillas",
    "iso:country":"ES",
    "sg:address":"Calle de Parrillas, 4",
    "sg:city":"Talavera Reina",
    "sg:orig_category":"Mec\u00c1nico Del Autom\u00d3vil",
    "sg:phone":"+34 925 80 45 25",
    "sg:postcode":"45600",
    "sg:province":"Toledo",
    "wof:name":"Talleres Mecanicos Hermanos Martin Duran S.l.l.",
    "wof:placetype":"venue"
},
  "geometry": {"coordinates":[-4.8442978859,39.9599685669],"type":"Point"}
}