{
  "type": "Feature",
  "properties": {
    "addr:full":"Plaz Ganado, 2 Babilafuente Salamanca 37330",
    "addr:housenumber":"2",
    "addr:postcode":"37330",
    "iso:country":"ES",
    "sg:address":"Plaz Ganado, 2",
    "sg:city":"Babilafuente",
    "sg:orig_category":"Empresarios",
    "sg:phone":"+34 923 36 06 19",
    "sg:postcode":"37330",
    "sg:province":"Salamanca",
    "wof:name":"Construcciones Plaza Del Ganado S.l.",
    "wof:placetype":"venue"
},
  "geometry": {"coordinates":[-5.4271788597,40.9780502319],"type":"Point"}
}