{
  "type": "Feature",
  "properties": {
    "iso:country":"ES",
    "sg:address":"Avda Martinez De Velasco, 8",
    "sg:city":"Huesca",
    "sg:orig_category":"Empresarios",
    "sg:phone":"+34 974 21 22 23",
    "sg:postcode":"22005",
    "sg:province":"Huesca",
    "wof:name":"Fundacion Anselmo Pie Sopena",
    "wof:placetype":"venue"
},
  "geometry": {"coordinates":[-0.411962986,42.1347198486],"type":"Point"}
}