{
  "type": "Feature",
  "properties": {
    "addr:full":"Diecisiete De Noviembre, 47 Toral Vados Le\u00f3n 24560",
    "addr:postcode":"24560",
    "addr:street":"Noviembre 47 Toral;Leo\u0301N",
    "iso:country":"ES",
    "sg:address":"Diecisiete De Noviembre, 47",
    "sg:city":"Toral Vados",
    "sg:orig_category":"Reposter\u00cdas",
    "sg:phone":"+34 987 54 46 73",
    "sg:postcode":"24560",
    "sg:province":"Le\u00f3n",
    "wof:name":"Juarez Garcia Maria Del Carmen",
    "wof:placetype":"venue"
},
  "geometry": {"coordinates":[-6.7778639793,42.5418319702],"type":"Point"}
}