{
  "type": "Feature",
  "properties": {
    "iso:country":"ES",
    "sg:address":"Carrer de Jalec, S/n",
    "sg:city":"Tona",
    "sg:orig_category":"Muebles Y Accesorios Para Cocinas Y Cuartos De Ba\u00d1o (al Por Menor)",
    "sg:phone":"+34 938 87 04 94",
    "sg:postcode":"08551",
    "sg:province":"Barcelona",
    "wof:name":"Talleres Joy S.cv.",
    "wof:placetype":"venue"
},
  "geometry": {"coordinates":[2.2289099693,41.8484954834],"type":"Point"}
}