{
  "type": "Feature",
  "properties": {
    "iso:country":"ES",
    "sg:address":"Carr Marques Del Turia, 84",
    "sg:city":"Benetusser",
    "sg:orig_category":"Molduras, Junquillos, Listones Y Molduras Perforadas",
    "sg:phone":"+34 963 75 02 46",
    "sg:postcode":"46910",
    "sg:province":"Valencia",
    "wof:name":"Jimeno Saez Francisco Jose",
    "wof:placetype":"venue"
},
  "geometry": {"coordinates":[-0.3987750113,39.4199485779],"type":"Point"}
}