{
  "type": "Feature",
  "properties": {
    "iso:country":"ES",
    "sg:address":"Calle de Pantano, 12",
    "sg:city":"Poligono Industrial Salinas De San Jose",
    "sg:orig_category":"Ropa Para Beb\u00c9s Y Ni\u00d1os (confecci\u00d3n, Al Por Mayor)",
    "sg:phone":"+34 956 87 76 38",
    "sg:postcode":"11500",
    "sg:province":"C\u00e1diz",
    "wof:name":"Black Queen S.l.",
    "wof:placetype":"venue"
},
  "geometry": {"coordinates":[-6.2197542191,36.6056632996],"type":"Point"}
}