{
  "type": "Feature",
  "properties": {
    "iso:country":"ES",
    "sg:address":"Calle de Horno (el), 33",
    "sg:city":"Berantevilla",
    "sg:orig_category":"Iglesia Cat\u00d3lica",
    "sg:phone":"+34 945 33 71 31",
    "sg:postcode":"01218",
    "sg:province":"\u00c1lava",
    "wof:name":"Parroquia Nuestra Se\u00f1ora De La Asuncion",
    "wof:placetype":"venue"
},
  "geometry": {"coordinates":[-2.8604989052,42.6825714111],"type":"Point"}
}