{
  "type": "Feature",
  "properties": {
    "addr:full":"Trva Palacio, 1 Ayerbe Huesca 22800",
    "addr:housenumber":"1",
    "addr:postcode":"22800",
    "addr:street":"Trva Palacio",
    "iso:country":"ES",
    "sg:address":"Trva Palacio, 1",
    "sg:city":"Ayerbe",
    "sg:classifiers":[
        {
            "category":"Casinos & Gambling",
            "type":"Entertainment"
        }
    ],
    "sg:phone":"+34 974 38 00 16",
    "sg:postcode":"22800",
    "sg:province":"Huesca",
    "sg:tags":[
        "locale",
        "de",
        "juego"
    ],
    "wof:name":"Casino De Ayerbe",
    "wof:placetype":"venue"
},
  "geometry": {"coordinates":[-0.6893860102,42.2759475708],"type":"Point"}
}