{
  "type": "Feature",
  "properties": {
    "addr:full":"Carr Major, 3 Vilanova D'alcolea Castell\u00f3n 12183",
    "addr:housenumber":"3",
    "addr:postcode":"12183",
    "addr:street":"Carr Major",
    "iso:country":"ES",
    "sg:address":"Carr Major, 3",
    "sg:city":"Vilanova D'alcolea",
    "sg:orig_category":"Hoteles",
    "sg:phone":"+34 964 70 72 30",
    "sg:postcode":"12183",
    "sg:province":"Castell\u00f3n",
    "wof:name":"Borras Vidal Carlos Manuel",
    "wof:placetype":"venue"
},
  "geometry": {"coordinates":[-0.0376270004,39.9843559265],"type":"Point"}
}