{
  "type": "Feature",
  "properties": {
    "iso:country":"ES",
    "sg:address":"Pla\u00c7 Sardana (la), 3",
    "sg:city":"Castellsera",
    "sg:orig_category":"Panader\u00cdas, Panader\u00cdas",
    "sg:phone":"+34 973 61 01 71",
    "sg:postcode":"25334",
    "sg:province":"Lleida",
    "wof:name":"Montserrat Regue Jordi",
    "wof:placetype":"venue"
},
  "geometry": {"coordinates":[0.9866899848,41.7461395264],"type":"Point"}
}