{
  "type": "Feature",
  "properties": {
    "iso:country":"ES",
    "sg:address":"Plaz Planillo, 1",
    "sg:city":"Villamayor",
    "sg:orig_category":"Muebles Y Accesorios Para Cocinas Y Cuartos De Ba\u00d1o (al Por Menor)",
    "sg:phone":"+34 976 58 28 47",
    "sg:postcode":"50162",
    "sg:province":"Zaragoza",
    "wof:name":"Guerrero Monzon Alfredo",
    "wof:placetype":"venue"
},
  "geometry": {"coordinates":[-0.7721989751,41.6848487854],"type":"Point"}
}