{
  "type": "Feature",
  "properties": {
    "iso:country":"ES",
    "sg:address":"Calle de Fundadora De Las Siervas De Jesus, 27",
    "sg:city":"Vitoria-gasteiz",
    "sg:orig_category":"Peluquer\u00cdas, Peluquer\u00cda Mixta",
    "sg:phone":"+34 945 28 87 94",
    "sg:postcode":"01001",
    "sg:province":"\u00c1lava",
    "wof:name":"Bartolome Camara Maria Aranzazu",
    "wof:placetype":"venue"
},
  "geometry": {"coordinates":[-2.6751890182,42.8494338989],"type":"Point"}
}