{
  "type": "Feature",
  "properties": {
    "addr:full":"Londres Benidorm Alicante 03500",
    "addr:postcode":"03500",
    "iso:country":"ES",
    "sg:address":"Londres",
    "sg:city":"Benidorm",
    "sg:orig_category":"Caf\u00c9s, Bares, Cervecer\u00cdas",
    "sg:phone":"+34 965 85 63 39",
    "sg:postcode":"03500",
    "sg:province":"Alicante",
    "wof:name":"Lorente Fajardo Adelino",
    "wof:placetype":"venue"
},
  "geometry": {"coordinates":[-0.1012710035,38.536239624],"type":"Point"}
}