{
  "type": "Feature",
  "properties": {
    "addr:full":"Calle de Juan De Toledo, 4 San Lorenzo De El Escorial Madrid 28200",
    "addr:housenumber":"4",
    "addr:postcode":"28200",
    "addr:street":"Calle De Juan De Toledo",
    "iso:country":"ES",
    "sg:address":"Calle de Juan De Toledo, 4",
    "sg:city":"San Lorenzo De El Escorial",
    "sg:orig_category":"Organizaci\u00d3n De Actos, Seminarios Y Congresos",
    "sg:phone":"+34 918 96 98 90",
    "sg:postcode":"28200",
    "sg:province":"Madrid",
    "sg:website":"www.hotelvictoriapalace.com",
    "wof:name":"Hotel Victoria Palace S.a.",
    "wof:placetype":"venue"
},
  "geometry": {"coordinates":[-4.1442728043,40.5909538269],"type":"Point"}
}