{
  "type": "Feature",
  "properties": {
    "iso:country":"ES",
    "sg:address":"Avda Valladolid, 45",
    "sg:city":"Tudela Duero",
    "sg:orig_category":"Panader\u00cdas, Panader\u00cdas",
    "sg:phone":"+34 983 52 00 62",
    "sg:postcode":"47320",
    "sg:province":"Valladolid",
    "wof:name":"Panificadora Tudelana S. A.",
    "wof:placetype":"venue"
},
  "geometry": {"coordinates":[-4.5843391418,41.5873718262],"type":"Point"}
}