{
  "type": "Feature",
  "properties": {
    "iso:country":"ES",
    "sg:address":"Carrer de Sant Francesc, 22",
    "sg:city":"Campello",
    "sg:orig_category":"Ense\u00d1anza Variada",
    "sg:phone":"+34 965 63 25 00",
    "sg:postcode":"03560",
    "sg:province":"Alicante",
    "wof:name":"Hermanas Gomis Planelles C.b.",
    "wof:placetype":"venue"
},
  "geometry": {"coordinates":[-0.3906340003,38.4271888733],"type":"Point"}
}