{
  "type": "Feature",
  "properties": {
    "addr:full":"Calle de Salamanca, 37 Valencia Valencia 46005",
    "addr:housenumber":"37",
    "addr:postcode":"46005",
    "addr:street":"Calle De Salamanca",
    "iso:country":"ES",
    "sg:address":"Calle de Salamanca, 37",
    "sg:city":"Valencia",
    "sg:orig_category":"Electrodom\u00c9sticos (al Por Menor)",
    "sg:phone":"+34 963 74 02 62",
    "sg:postcode":"46005",
    "sg:province":"Valencia",
    "wof:name":"Amoros Mediavilla Angel",
    "wof:placetype":"venue"
},
  "geometry": {"coordinates":[-0.3636811078,39.4653930664],"type":"Point"}
}