{
  "type": "Feature",
  "properties": {
    "addr:full":"Carrer de Alfred Bonet, 8 Palma Islas Baleares 07003",
    "addr:housenumber":"8",
    "addr:postcode":"07003",
    "addr:street":"Carrer De Alfred Bonet",
    "iso:country":"ES",
    "sg:address":"Carrer de Alfred Bonet, 8",
    "sg:city":"Palma",
    "sg:orig_category":"Fotocopias, Reprograf\u00cda",
    "sg:phone":"+34 971 20 21 96",
    "sg:postcode":"07003",
    "sg:province":"Islas Baleares",
    "wof:name":"Alba Contreras Ana Maria",
    "wof:placetype":"venue"
},
  "geometry": {"coordinates":[2.6464464664,39.578666687],"type":"Point"}
}