{
  "type": "Feature",
  "properties": {
    "addr:full":"Rond Industria, 81 Barbera Valles Barcelona 08210",
    "addr:housenumber":"81",
    "addr:postcode":"08210",
    "addr:street":"Rond Industria",
    "iso:country":"ES",
    "sg:address":"Rond Industria, 81",
    "sg:city":"Barbera Valles",
    "sg:orig_category":"Papeler\u00cdas, Librer\u00cdas",
    "sg:phone":"+34 937 18 37 60",
    "sg:postcode":"08210",
    "sg:province":"Barcelona",
    "wof:name":"Ramallo Silva Domingo",
    "wof:placetype":"venue"
},
  "geometry": {"coordinates":[2.1271760464,41.5150566101],"type":"Point"}
}