{
  "type": "Feature",
  "properties": {
    "addr:full":"Avda Extremadura, 193 Talavera Real Badajoz 06140",
    "addr:housenumber":"193",
    "addr:postcode":"06140",
    "addr:street":"Avda Extremadura",
    "iso:country":"ES",
    "sg:address":"Avda Extremadura, 193",
    "sg:city":"Talavera Real",
    "sg:orig_category":"Arenas, Guijarros Y Granulados",
    "sg:phone":"+34 924 44 03 16",
    "sg:postcode":"06140",
    "sg:province":"Badajoz",
    "wof:name":"Aridos Romero S.l.",
    "wof:placetype":"venue"
},
  "geometry": {"coordinates":[-6.7700128555,38.865814209],"type":"Point"}
}