{
  "type": "Feature",
  "properties": {
    "iso:country":"ES",
    "sg:address":"Plaz Carlos Trias Bertran, 7",
    "sg:city":"Madrid",
    "sg:orig_category":"Ense\u00d1anza: Comercio, Gesti\u00d3n, Inform\u00c1tica",
    "sg:phone":"+34 915 56 92 62",
    "sg:postcode":"28020",
    "sg:province":"Madrid",
    "sg:website":"www.thales-is.com",
    "wof:name":"Thales Information System S.a.",
    "wof:placetype":"venue"
},
  "geometry": {"coordinates":[-3.6946210861,40.4513092041],"type":"Point"}
}