{
  "type": "Feature",
  "properties": {
    "addr:full":"Carrer de Tajo, 45 Barcelona Barcelona 08032",
    "addr:housenumber":"45",
    "addr:postcode":"08032",
    "addr:street":"Carrer De Tajo",
    "iso:country":"ES",
    "sg:address":"Carrer de Tajo, 45",
    "sg:city":"Barcelona",
    "sg:orig_category":"Fabricaci\u00d3n De Sobres, Bolsas Y Fundas",
    "sg:phone":"+34 934 29 64 26",
    "sg:postcode":"08032",
    "sg:province":"Barcelona",
    "wof:name":"Suarez Ortega Jose",
    "wof:placetype":"venue"
},
  "geometry": {"coordinates":[2.1615200043,41.4294090271],"type":"Point"}
}