{
  "type": "Feature",
  "properties": {
    "iso:country":"ES",
    "sg:address":"Calle de Mackay Macdonald, 6",
    "sg:city":"Huelva",
    "sg:orig_category":"Asesor\u00cda De Formaci\u00d3n Y Gesti\u00d3n De Personal",
    "sg:phone":"+34 959 24 76 17",
    "sg:postcode":"21004",
    "sg:province":"Huelva",
    "wof:name":"Gomez Arenas Isabel",
    "wof:placetype":"venue"
},
  "geometry": {"coordinates":[-6.9495940208,37.256313324],"type":"Point"}
}