{
  "type": "Feature",
  "properties": {
    "iso:country":"ES",
    "sg:address":"Calle de Abastos (de), 171",
    "sg:city":"Aranjuez",
    "sg:orig_category":"Perfumer\u00cda (al Por Menor)",
    "sg:phone":"+34 918 91 36 05",
    "sg:postcode":"28300",
    "sg:province":"Madrid",
    "wof:name":"Atienza Diaz Felix",
    "wof:placetype":"venue"
},
  "geometry": {"coordinates":[-3.5939919949,40.0308303833],"type":"Point"}
}