{
  "type": "Feature",
  "properties": {
    "iso:country":"ES",
    "sg:address":"C/ Alfred Nobel, 22",
    "sg:city":"Torrellano",
    "sg:orig_category":"Transporte En General",
    "sg:phone":"+34 965 46 40 10",
    "sg:postcode":"03320",
    "sg:province":"Alicante",
    "wof:name":"Astel Logistic S.l.",
    "wof:placetype":"venue"
},
  "geometry": {"coordinates":[-0.6125760078,38.2913017273],"type":"Point"}
}