{
  "type": "Feature",
  "properties": {
    "iso:country":"ES",
    "sg:address":"Pl Era Del Castell, 3",
    "sg:city":"Morell",
    "sg:orig_category":"Peluquer\u00cdas, Peluquer\u00cda Mixta",
    "sg:phone":"+34 977 84 00 19",
    "sg:postcode":"43760",
    "sg:province":"Tarragona",
    "wof:name":"Pujol Vilamajor Esther",
    "wof:placetype":"venue"
},
  "geometry": {"coordinates":[1.2087600231,41.1919708252],"type":"Point"}
}