{
  "type": "Feature",
  "properties": {
    "addr:full":"Carrer de Schubert, 39 Rubi Barcelona 08191",
    "addr:housenumber":"39",
    "addr:postcode":"08191",
    "addr:street":"Carrer De Schubert",
    "iso:country":"ES",
    "sg:address":"Carrer de Schubert, 39",
    "sg:city":"Rubi",
    "sg:orig_category":"Construcciones Met\u00c1licas",
    "sg:phone":"+34 935 88 58 24",
    "sg:postcode":"08191",
    "sg:province":"Barcelona",
    "wof:name":"Construcciones Metalicas Manuel Maza S.l.",
    "wof:placetype":"venue"
},
  "geometry": {"coordinates":[2.0184099674,41.4732017517],"type":"Point"}
}