{
  "type": "Feature",
  "properties": {
    "addr:full":"Carrer de Oviedo, 19 S. Boi Llobregat Barcelona 08830",
    "addr:housenumber":"19",
    "addr:postcode":"08830",
    "addr:street":"Carrer De Oviedo",
    "iso:country":"ES",
    "sg:address":"Carrer de Oviedo, 19",
    "sg:city":"S. Boi Llobregat",
    "sg:orig_category":"Zapatos (al Por Menor)",
    "sg:phone":"+34 936 30 40 82",
    "sg:postcode":"08830",
    "sg:province":"Barcelona",
    "wof:name":"Brull Fenoy Miriam",
    "wof:placetype":"venue"
},
  "geometry": {"coordinates":[2.0367059708,41.3457641602],"type":"Point"}
}