{
  "type": "Feature",
  "properties": {
    "iso:country":"ES",
    "sg:address":"Calle de Alfonso Xiii, 18",
    "sg:city":"Garrucha",
    "sg:orig_category":"Electricidad: Instaladores",
    "sg:phone":"+34 950 13 35 17",
    "sg:postcode":"04630",
    "sg:province":"Almer\u00eda",
    "wof:name":"Montoya Mendez S.l",
    "wof:placetype":"venue"
},
  "geometry": {"coordinates":[-1.8250149488,37.1807327271],"type":"Point"}
}