{
  "type": "Feature",
  "properties": {
    "addr:full":"Uribeguela Kalea, 1 Abetxuko \u00c1lava 01013",
    "addr:housenumber":"1",
    "addr:postcode":"01013",
    "addr:street":"Uribeguela Kalea;A\u0301Lava",
    "iso:country":"ES",
    "sg:address":"Uribeguela Kalea, 1",
    "sg:city":"Abetxuko",
    "sg:orig_category":"Molduras, Junquillos, Listones Y Molduras Perforadas",
    "sg:phone":"+34 945 26 54 97",
    "sg:postcode":"01013",
    "sg:province":"\u00c1lava",
    "wof:name":"Sanchez Acera Eleuterio",
    "wof:placetype":"venue"
},
  "geometry": {"coordinates":[-2.677656889,42.874874115],"type":"Point"}
}