{
  "type": "Feature",
  "properties": {
    "addr:full":"Avda Juan Garcia Navia Castrillon, 11 Viveiro Lugo 27850",
    "addr:housenumber":"11",
    "addr:postcode":"27850",
    "addr:street":"Avda Juan Garcia;Castrillon",
    "iso:country":"ES",
    "sg:address":"Avda Juan Garcia Navia Castrillon, 11",
    "sg:city":"Viveiro",
    "sg:orig_category":"Papeler\u00cdas, Librer\u00cdas",
    "sg:phone":"+34 982 56 09 86",
    "sg:postcode":"27850",
    "sg:province":"Lugo",
    "wof:name":"Gutierrez Martinez Enriqueta",
    "wof:placetype":"venue"
},
  "geometry": {"coordinates":[-7.5968279839,43.6589202881],"type":"Point"}
}