{
  "type": "Feature",
  "properties": {
    "iso:country":"ES",
    "sg:address":"Calle de Campanas, 3",
    "sg:city":"Jaen",
    "sg:orig_category":"Fabricaci\u00d3n De Juguetes Autom\u00c1ticos",
    "sg:phone":"+34 953 23 41 83",
    "sg:postcode":"23002",
    "sg:province":"Ja\u00e9n",
    "wof:name":"Explotacion De Telefonos Publicos S.l.",
    "wof:placetype":"venue"
},
  "geometry": {"coordinates":[-3.7901275158,37.765499115],"type":"Point"}
}