{
  "type": "Feature",
  "properties": {
    "addr:full":"Calle de San Roque, 21 Vitigudino Salamanca 37210",
    "addr:housenumber":"21",
    "addr:postcode":"37210",
    "addr:street":"Calle De San Roque",
    "iso:country":"ES",
    "sg:address":"Calle de San Roque, 21",
    "sg:city":"Vitigudino",
    "sg:orig_category":"Doctores En Medicina",
    "sg:phone":"+34 923 52 00 43",
    "sg:postcode":"37210",
    "sg:province":"Salamanca",
    "wof:name":"Cuadrado Merchan Luis Francisco",
    "wof:placetype":"venue"
},
  "geometry": {"coordinates":[-6.4334578514,41.0124168396],"type":"Point"}
}