{
  "type": "Feature",
  "properties": {
    "iso:country":"ES",
    "sg:address":"Calle de Las Marismas, 37",
    "sg:city":"Madrid",
    "sg:orig_category":"Guarder\u00cdas",
    "sg:phone":"+34 915 01 75 42",
    "sg:postcode":"28038",
    "sg:province":"Madrid",
    "wof:name":"Benavente Escuder Teresa",
    "wof:placetype":"venue"
},
  "geometry": {"coordinates":[-3.6535251141,40.4026641846],"type":"Point"}
}