{
  "type": "Feature",
  "properties": {
    "iso:country":"ES",
    "sg:address":"Calle de Reig Genoves, 15",
    "sg:city":"Valencia",
    "sg:orig_category":"Cl\u00cdnicas Dentales",
    "sg:phone":"+34 963 66 83 28",
    "sg:postcode":"46019",
    "sg:province":"Valencia",
    "wof:name":"Clinica Dental Orriols S.l.",
    "wof:placetype":"venue"
},
  "geometry": {"coordinates":[-0.3712939918,39.4925689697],"type":"Point"}
}