{
  "type": "Feature",
  "properties": {
    "iso:country":"ES",
    "sg:address":"Calle de Muza, 13",
    "sg:city":"Merida",
    "sg:orig_category":"Arquitectos",
    "sg:phone":"+34 924 31 38 01",
    "sg:postcode":"06800",
    "sg:province":"Badajoz",
    "wof:name":"Garcia Curado Juan Jose",
    "wof:placetype":"venue"
},
  "geometry": {"coordinates":[-6.3491659164,38.9198265076],"type":"Point"}
}