{
  "type": "Feature",
  "properties": {
    "addr:full":"Calle de Virgen De La Vega, 22 Haro La Rioja 26200",
    "addr:housenumber":"22",
    "addr:postcode":"26200",
    "addr:street":"Calle De Virgen De La Vega",
    "iso:country":"ES",
    "sg:address":"Calle de Virgen De La Vega, 22",
    "sg:city":"Haro",
    "sg:orig_category":"Abogados",
    "sg:phone":"+34 941 31 01 72",
    "sg:postcode":"26200",
    "sg:province":"La Rioja",
    "wof:name":"Ojeda Verde Luis",
    "wof:placetype":"venue"
},
  "geometry": {"coordinates":[-2.8496394157,42.5768928528],"type":"Point"}
}