{
  "type": "Feature",
  "properties": {
    "iso:country":"ES",
    "sg:address":"Poligon Industrial Ford, S/n",
    "sg:city":"Almussafes",
    "sg:orig_category":"Maquinaria Para Industrias Diversas",
    "sg:phone":"+34 961 79 76 38",
    "sg:postcode":"46440",
    "sg:province":"Valencia",
    "sg:website":"www.sandviktamrock",
    "wof:name":"Sandvik Espa\u00d1ola S.a.",
    "wof:placetype":"venue"
},
  "geometry": {"coordinates":[-0.4122039974,39.2929763794],"type":"Point"}
}