{
  "type": "Feature",
  "properties": {
    "addr:full":"Calle de Pedrapiquers, Dels, 4 Valencia Valencia 46...",
    "addr:housenumber":"4",
    "addr:street":"Calle De Pedrapiquers Dels;Valencia",
    "iso:country":"ES",
    "sg:address":"Calle de Pedrapiquers, Dels, 4",
    "sg:city":"Valencia",
    "sg:orig_category":"Aguas (distribuci\u00d3n, Servicios)",
    "sg:phone":"+34 963 86 06 38",
    "sg:postcode":"46...",
    "sg:province":"Valencia",
    "wof:name":"Aguas De Valencia S.a.",
    "wof:placetype":"venue"
},
  "geometry": {"coordinates":[-0.407186687,39.4586143494],"type":"Point"}
}