{
  "type": "Feature",
  "properties": {
    "addr:full":"Calle de Palominos 12, 2 Urbanizacion Los Palominos Toledo 45217",
    "addr:housenumber":"12 2",
    "addr:postcode":"45217",
    "addr:street":"Calle De Palominos;Urbanizacion Los Palominos",
    "iso:country":"ES",
    "sg:address":"Calle de Palominos 12, 2",
    "sg:city":"Urbanizacion Los Palominos",
    "sg:orig_category":"Reparaciones Y Remolcado De Veh\u00cdculos",
    "sg:phone":"+34 925 54 41 10",
    "sg:postcode":"45217",
    "sg:province":"Toledo",
    "wof:name":"Nu\u00f1ez Caballero Juan Ramon",
    "wof:placetype":"venue"
},
  "geometry": {"coordinates":[-3.877669096,40.1581344604],"type":"Point"}
}