{
  "type": "Feature",
  "properties": {
    "addr:full":"Calle de Obispo Frias, 9 San Isidro Las Palmas 35460",
    "addr:housenumber":"9",
    "addr:postcode":"35460",
    "addr:street":"Calle De Obispo Frias",
    "iso:country":"ES",
    "sg:address":"Calle de Obispo Frias, 9",
    "sg:city":"San Isidro",
    "sg:orig_category":"Iglesia Cat\u00d3lica",
    "sg:phone":"+34 928 88 03 49",
    "sg:postcode":"35460",
    "sg:province":"Las Palmas",
    "wof:name":"Parroquia De San Isidro",
    "wof:placetype":"venue"
},
  "geometry": {"coordinates":[-15.6599931717,28.1319522858],"type":"Point"}
}