{
  "type": "Feature",
  "properties": {
    "addr:full":"Carrer de Serra, 2 Corro D'avall Barcelona 08520",
    "addr:housenumber":"2",
    "addr:postcode":"08520",
    "addr:street":"Carrer De Serra;D'Avall Barcelona",
    "iso:country":"ES",
    "sg:address":"Carrer de Serra, 2",
    "sg:city":"Corro D'avall",
    "sg:orig_category":"Institutos De Belleza",
    "sg:phone":"+34 938 49 84 89",
    "sg:postcode":"08520",
    "sg:province":"Barcelona",
    "wof:name":"Fernandez Lopez Elisabeth",
    "wof:placetype":"venue"
},
  "geometry": {"coordinates":[2.2932496071,41.6244354248],"type":"Point"}
}