{
  "type": "Feature",
  "properties": {
    "addr:full":"Calle de Japon, 19 Alcorcon Madrid 28923",
    "addr:housenumber":"19",
    "addr:postcode":"28923",
    "addr:street":"Calle De Japon",
    "iso:country":"ES",
    "sg:address":"Calle de Japon, 19",
    "sg:city":"Alcorcon",
    "sg:orig_category":"Complementos De Vestir (al Por Menor)",
    "sg:phone":"+34 916 10 53 11",
    "sg:postcode":"28923",
    "sg:province":"Madrid",
    "wof:name":"Blazquez Perez Maria Dolores",
    "wof:placetype":"venue"
},
  "geometry": {"coordinates":[-3.8178501129,40.3453140259],"type":"Point"}
}