{
  "type": "Feature",
  "properties": {
    "addr:full":"Calle de Campo Real, 9 Alcala Henares Madrid 28806",
    "addr:housenumber":"9",
    "addr:postcode":"28806",
    "addr:street":"Calle De Campo",
    "iso:country":"ES",
    "sg:address":"Calle de Campo Real, 9",
    "sg:city":"Alcala Henares",
    "sg:orig_category":"Laboratorios Y Cl\u00cdnicas Veterinarias",
    "sg:phone":"+34 918 83 42 95",
    "sg:postcode":"28806",
    "sg:province":"Madrid",
    "wof:name":"Clinica Veterinaria Layos C.b.",
    "wof:placetype":"venue"
},
  "geometry": {"coordinates":[-3.3779313564,40.4940757751],"type":"Point"}
}