{
  "type": "Feature",
  "properties": {
    "iso:country":"ES",
    "sg:address":"Rua Manuel Rodriguez Casal, 25",
    "sg:city":"Laredo",
    "sg:orig_category":"Empresas De Carpinter\u00cda",
    "sg:phone":"+34 986 45 10 55",
    "sg:postcode":"36320",
    "sg:province":"Pontevedra",
    "wof:name":"Santos Ferreiros Antonio",
    "wof:placetype":"venue"
},
  "geometry": {"coordinates":[-8.6428003311,42.4304618835],"type":"Point"}
}