{
  "type": "Feature",
  "properties": {
    "addr:full":"Antoni Gaudi(p I Las Saladas), 12 Torrellano Alicante 03320",
    "addr:housenumber":"12",
    "addr:postcode":"03320",
    "addr:street":"Antoni Gaudi P;Las Saladas",
    "iso:country":"ES",
    "sg:address":"Antoni Gaudi(p I Las Saladas), 12",
    "sg:city":"Torrellano",
    "sg:orig_category":"Confecci\u00d3n De Zapatos",
    "sg:phone":"+34 965 68 05 35",
    "sg:postcode":"03320",
    "sg:province":"Alicante",
    "sg:website":"www.hi-tec.com",
    "wof:name":"Hi-tec Sports Espa\u00f1a S.a.",
    "wof:placetype":"venue"
},
  "geometry": {"coordinates":[-0.5883839726,38.2929649353],"type":"Point"}
}