{
  "type": "Feature",
  "properties": {
    "addr:full":"Carrer de Sant Jaume, 106 Granollers Barcelona 08401",
    "addr:housenumber":"106",
    "addr:postcode":"08401",
    "addr:street":"Carrer De Sant Jaume",
    "iso:country":"ES",
    "sg:address":"Carrer de Sant Jaume, 106",
    "sg:city":"Granollers",
    "sg:orig_category":"Agencias Y Asesores De Publicidad",
    "sg:phone":"+34 938 79 12 48",
    "sg:postcode":"08401",
    "sg:province":"Barcelona",
    "wof:name":"Pascual Agudo Miguel",
    "wof:placetype":"venue"
},
  "geometry": {"coordinates":[2.2855329514,41.6045188904],"type":"Point"}
}