{
  "type": "Feature",
  "properties": {
    "iso:country":"ES",
    "sg:address":"Avda Ferrandis Salvador, 160",
    "sg:city":"Mas Dels Frares",
    "sg:orig_category":"Caf\u00c9s, Bares, Cervecer\u00cdas",
    "sg:phone":"+34 964 39 24 68",
    "sg:postcode":"12560",
    "sg:province":"Castell\u00f3n",
    "wof:name":"Gasolinera-injucrisa S.l.",
    "wof:placetype":"venue"
},
  "geometry": {"coordinates":[0.0590550005,40.0523414612],"type":"Point"}
}