{
  "type": "Feature",
  "properties": {
    "iso:country":"ES",
    "sg:address":"Calle de Lagos, 2",
    "sg:city":"Marinas",
    "sg:orig_category":"Transporte En General",
    "sg:phone":"+34 950 33 45 04",
    "sg:postcode":"04740",
    "sg:province":"Almer\u00eda",
    "wof:name":"Praena Palenzuela Pedro",
    "wof:placetype":"venue"
},
  "geometry": {"coordinates":[-2.629983902,36.7314682007],"type":"Point"}
}