{
  "type": "Feature",
  "properties": {
    "addr:full":"Avda Virgen De Argeme, 11 Coria C\u00e1ceres 10800",
    "addr:housenumber":"11",
    "addr:postcode":"10800",
    "addr:street":"Avda Virgen De Argeme;Ca\u0301Ceres",
    "iso:country":"ES",
    "sg:address":"Avda Virgen De Argeme, 11",
    "sg:city":"Coria",
    "sg:orig_category":"Fabricaci\u00d3n, Venta De Cuadros, Accesorios Para Enmarcar",
    "sg:phone":"+34 927 50 03 88",
    "sg:postcode":"10800",
    "sg:province":"C\u00e1ceres",
    "wof:name":"Alcala Garcia Emilio",
    "wof:placetype":"venue"
},
  "geometry": {"coordinates":[-6.5388565063,39.9886360168],"type":"Point"}
}