{
  "type": "Feature",
  "properties": {
    "addr:full":"Calle de Arco Marques, 2 Alagon Zaragoza 50630",
    "addr:housenumber":"2",
    "addr:postcode":"50630",
    "addr:street":"Calle De Arco Marques",
    "iso:country":"ES",
    "sg:address":"Calle de Arco Marques, 2",
    "sg:city":"Alagon",
    "sg:orig_category":"Pescader\u00cdas (al Por Menor)",
    "sg:phone":"+34 976 61 02 73",
    "sg:postcode":"50630",
    "sg:province":"Zaragoza",
    "wof:name":"Urbano Gascon Jose Enrique",
    "wof:placetype":"venue"
},
  "geometry": {"coordinates":[-1.1210750341,41.7707443237],"type":"Point"}
}