{
  "type": "Feature",
  "properties": {
    "addr:full":"Calle de San Mateo, 31 San Fernando Las Palmas 35100",
    "addr:housenumber":"31",
    "addr:postcode":"35100",
    "addr:street":"Calle De San Mateo",
    "iso:country":"ES",
    "sg:address":"Calle de San Mateo, 31",
    "sg:city":"San Fernando",
    "sg:orig_category":"Peluquer\u00cdas, Peluquer\u00cda Mixta",
    "sg:phone":"+34 928 76 45 51",
    "sg:postcode":"35100",
    "sg:province":"Las Palmas",
    "wof:name":"Calixto Santana Yuli",
    "wof:placetype":"venue"
},
  "geometry": {"coordinates":[-15.5842504501,28.0904903412],"type":"Point"}
}