{
  "type": "Feature",
  "properties": {
    "iso:country":"ES",
    "sg:address":"Circunvalacion, 14",
    "sg:city":"Granada",
    "sg:orig_category":"Muebles, Minoristas",
    "sg:phone":"+34 958 12 20 22",
    "sg:postcode":"18006",
    "sg:province":"Granada",
    "wof:name":"Ahorro Hogar Mobiliario S.l.",
    "wof:placetype":"venue"
},
  "geometry": {"coordinates":[-3.6015720367,37.1595001221],"type":"Point"}
}