{
  "type": "Feature",
  "properties": {
    "addr:full":"Avda Infante Don Luis (del), 5 Boadilla Del Monte Madrid 28660",
    "addr:postcode":"28660",
    "addr:street":"Avda Infante Don;Del",
    "iso:country":"ES",
    "sg:address":"Avda Infante Don Luis (del), 5",
    "sg:city":"Boadilla Del Monte",
    "sg:orig_category":"Inmobiliaria (agencias)",
    "sg:phone":"+34 916 33 80 47",
    "sg:postcode":"28660",
    "sg:province":"Madrid",
    "wof:name":"Garcia Y Acebal Servicios Inmobiliarios S.l.",
    "wof:placetype":"venue"
},
  "geometry": {"coordinates":[-3.8952167034,40.4082794189],"type":"Point"}
}