{
  "type": "Feature",
  "properties": {
    "addr:full":"Pg Maritim De Les Botigues, S/n Passeig Maritim Barcelona 08870",
    "addr:housenumber":"s / n",
    "addr:postcode":"08870",
    "addr:street":"Pg Maritim De Les Botigues;Passeig Maritim Barcelona",
    "iso:country":"ES",
    "sg:address":"Pg Maritim De Les Botigues, S/n",
    "sg:city":"Passeig Maritim",
    "sg:orig_category":"Deportes N\u00c1uticos, Acu\u00c1ticos Y Subacu\u00c1ticos: Art\u00cdculos Y Equipo (al Por Menor)",
    "sg:phone":"+34 936 65 36 00",
    "sg:postcode":"08870",
    "sg:province":"Barcelona",
    "sg:website":"www.catamarancenter.com",
    "wof:name":"Catamaran Center S.l.",
    "wof:placetype":"venue"
},
  "geometry": {"coordinates":[1.8054499626,41.2342414856],"type":"Point"}
}