{
  "type": "Feature",
  "properties": {
    "addr:full":"Ctra Utrera-carmona, 26 Utrera Sevilla 41710",
    "addr:housenumber":"26",
    "addr:postcode":"41710",
    "addr:street":"Ctra Utrera-Carmona",
    "iso:country":"ES",
    "sg:address":"Ctra Utrera-carmona, 26",
    "sg:city":"Utrera",
    "sg:orig_category":"Material Y Herramientas Agr\u00cdcolas",
    "sg:phone":"+34 954 86 25 18",
    "sg:postcode":"41710",
    "sg:province":"Sevilla",
    "wof:name":"Talleres Hermanos Tirado S.c.",
    "wof:placetype":"venue"
},
  "geometry": {"coordinates":[-5.7883300781,37.192237854],"type":"Point"}
}