{
  "type": "Feature",
  "properties": {
    "addr:full":"Calle de Jose Del Pino, 70 Madrid Madrid 28021",
    "addr:housenumber":"70",
    "addr:postcode":"madrid;28021",
    "addr:street":"Calle De Jose Del Pino",
    "iso:country":"ES",
    "sg:address":"Calle de Jose Del Pino, 70",
    "sg:city":"Madrid",
    "sg:orig_category":"Fabricaci\u00d3n De Sobres, Bolsas Y Fundas",
    "sg:phone":"+34 917 98 00 01",
    "sg:postcode":"28021",
    "sg:province":"Madrid",
    "wof:name":"Cheng  Sujing",
    "wof:placetype":"venue"
},
  "geometry": {"coordinates":[-3.688188076,40.3508682251],"type":"Point"}
}