{
  "type": "Feature",
  "properties": {
    "addr:full":"Calle de Mateo Llana Diaz-estebanez, 8 Oviedo Asturias 33012",
    "addr:housenumber":"8",
    "addr:postcode":"33012",
    "addr:street":"Calle De Mateo Llana Diaz-Estebanez",
    "iso:country":"ES",
    "sg:address":"Calle de Mateo Llana Diaz-estebanez, 8",
    "sg:city":"Oviedo",
    "sg:orig_category":"Caf\u00c9s, Bares, Cervecer\u00cdas",
    "sg:phone":"+34 985 24 59 26",
    "sg:postcode":"33012",
    "sg:province":"Asturias",
    "wof:name":"Ascomtel",
    "wof:placetype":"venue"
},
  "geometry": {"coordinates":[-5.8685231209,43.3676757812],"type":"Point"}
}