{
  "type": "Feature",
  "properties": {
    "addr:full":"Calle de Jose Maria Haro (magistrat), 14 Valencia Valencia 46022",
    "addr:housenumber":"14",
    "addr:postcode":"46022",
    "addr:street":"Calle De Jose Maria Haro Magistrat",
    "iso:country":"ES",
    "sg:address":"Calle de Jose Maria Haro (magistrat), 14",
    "sg:city":"Valencia",
    "sg:orig_category":"Fabricaci\u00d3n, Instalaci\u00d3n Y Reparaci\u00d3n De Bombas",
    "sg:phone":"+34 963 56 45 27",
    "sg:postcode":"46022",
    "sg:province":"Valencia",
    "sg:website":"www.itur.es",
    "wof:name":"Bombas Itur S. A.",
    "wof:placetype":"venue"
},
  "geometry": {"coordinates":[-0.338259995,39.4691352844],"type":"Point"}
}