{
  "type": "Feature",
  "properties": {
    "iso:country":"ES",
    "sg:address":"Calle de Italia, 4",
    "sg:city":"Don Benito",
    "sg:orig_category":"Producci\u00d3n, Venta De Productos De Agricultura Biol\u00d3gica",
    "sg:phone":"+34 924 81 37 24",
    "sg:postcode":"06400",
    "sg:province":"Badajoz",
    "wof:name":"Sabido Ruiz Juan",
    "wof:placetype":"venue"
},
  "geometry": {"coordinates":[-5.8671269417,38.9585762024],"type":"Point"}
}