{
  "type": "Feature",
  "properties": {
    "addr:full":"Avda Mediterraneo, S/n Gran Alacant Alicante 03130",
    "addr:postcode":"03130",
    "addr:street":"Avda Mediterraneo S / N",
    "iso:country":"ES",
    "sg:address":"Avda Mediterraneo, S/n",
    "sg:city":"Gran Alacant",
    "sg:orig_category":"Cajas De Ahorro",
    "sg:phone":"+34 966 69 93 44",
    "sg:postcode":"03130",
    "sg:province":"Alicante",
    "wof:name":"Caja De Ahorros De Valencia Castellon Y Alicante",
    "wof:placetype":"venue"
},
  "geometry": {"coordinates":[-0.5578309894,38.2048950195],"type":"Point"}
}