{
  "type": "Feature",
  "properties": {
    "addr:full":"Carrer de Lluis Companys, 16 Santa Coloma De Gramenet Barcelona 08921",
    "addr:housenumber":"16",
    "addr:postcode":"08921",
    "addr:street":"Carrer De Lluis Companys",
    "iso:country":"ES",
    "sg:address":"Carrer de Lluis Companys, 16",
    "sg:city":"Santa Coloma De Gramenet",
    "sg:orig_category":"Promotores Constructores",
    "sg:phone":"+34 934 66 46 10",
    "sg:postcode":"08921",
    "sg:province":"Barcelona",
    "wof:name":"Comunidad De Propietarios Lluis Companys,16",
    "wof:placetype":"venue"
},
  "geometry": {"coordinates":[2.2050850391,41.4515075684],"type":"Point"}
}