{
  "type": "Feature",
  "properties": {
    "addr:full":"Calle de Argensola, 8 Madrid Madrid 28004",
    "addr:housenumber":"8",
    "addr:postcode":"madrid;28004",
    "addr:street":"Calle De Argensola",
    "iso:country":"ES",
    "sg:address":"Calle de Argensola, 8",
    "sg:city":"Madrid",
    "sg:orig_category":"Bancos",
    "sg:phone":"+34 913 91 05 91",
    "sg:postcode":"28004",
    "sg:province":"Madrid",
    "wof:name":"Auna Telecomunicaciones S.a.u.",
    "wof:placetype":"venue"
},
  "geometry": {"coordinates":[-3.6950240135,40.4250831604],"type":"Point"}
}