{
  "type": "Feature",
  "properties": {
    "addr:full":"Pol Ind San Jorge, S/n Palos Frontera Huelva 21810",
    "addr:housenumber":"s / n",
    "addr:postcode":"21810",
    "addr:street":"Jorge;Palos Frontera",
    "iso:country":"ES",
    "sg:address":"Pol Ind San Jorge, S/n",
    "sg:city":"Palos Frontera",
    "sg:orig_category":"Transportes En Cisternas",
    "sg:phone":"+34 959 53 07 25",
    "sg:postcode":"21810",
    "sg:province":"Huelva",
    "wof:name":"Betunes Asfalticos S. L.",
    "wof:placetype":"venue"
},
  "geometry": {"coordinates":[-6.8923411369,37.2240829468],"type":"Point"}
}