{
  "type": "Feature",
  "properties": {
    "addr:full":"Calle de Badajoz, 18 Alcorcon Madrid 28921",
    "addr:housenumber":"18",
    "addr:postcode":"28921",
    "addr:street":"Calle De Badajoz",
    "iso:country":"ES",
    "sg:address":"Calle de Badajoz, 18",
    "sg:city":"Alcorcon",
    "sg:orig_category":"Peluqueros: De Se\u00d1oras",
    "sg:phone":"+34 916 43 85 15",
    "sg:postcode":"28921",
    "sg:province":"Madrid",
    "wof:name":"Pozo Lopez Maria De Los Llanos",
    "wof:placetype":"venue"
},
  "geometry": {"coordinates":[-3.8310546875,40.346988678],"type":"Point"}
}