{
  "type": "Feature",
  "properties": {
    "iso:country":"ES",
    "sg:address":"Carrer de Rodes (de Les), S/n",
    "sg:city":"Alcover",
    "sg:classifiers":[
        {
            "category":"Communications",
            "type":"Services"
        }
    ],
    "sg:phone":"+34 977 76 01 66",
    "sg:postcode":"43460",
    "sg:province":"Tarragona",
    "sg:tags":[
        "televisiones",
        "y",
        "radio"
    ],
    "wof:name":"Ajuntament D'alcover",
    "wof:placetype":"venue"
},
  "geometry": {"coordinates":[1.1670507193,41.261554718],"type":"Point"}
}