{
  "type": "Feature",
  "properties": {
    "addr:full":"Pl Fra Bernadi, 20 Manlleu Barcelona 08560",
    "addr:housenumber":"20",
    "addr:postcode":"08560",
    "addr:street":"Pl Fra Bernadi",
    "iso:country":"ES",
    "sg:address":"Pl Fra Bernadi, 20",
    "sg:city":"Manlleu",
    "sg:orig_category":"Relojer\u00cda (al Por Menor, Reparaci\u00d3n)",
    "sg:phone":"+34 938 50 76 82",
    "sg:postcode":"08560",
    "sg:province":"Barcelona",
    "wof:name":"Collelldemont Pujadas Nuria",
    "wof:placetype":"venue"
},
  "geometry": {"coordinates":[2.2844119072,41.9993782043],"type":"Point"}
}