{
  "type": "Feature",
  "properties": {
    "addr:full":"Carr Magi Morera, 13 Lleida Lleida 25006",
    "addr:housenumber":"13",
    "addr:postcode":"25006",
    "addr:street":"Carr Magi Morera",
    "iso:country":"ES",
    "sg:address":"Carr Magi Morera, 13",
    "sg:city":"Lleida",
    "sg:orig_category":"Peluquer\u00cdas, Peluquer\u00cda Mixta",
    "sg:phone":"+34 973 26 10 19",
    "sg:postcode":"25006",
    "sg:province":"Lleida",
    "wof:name":"Busom Esteve Ana Maria",
    "wof:placetype":"venue"
},
  "geometry": {"coordinates":[0.6163210273,41.6170654297],"type":"Point"}
}