{
  "type": "Feature",
  "properties": {
    "addr:full":"Avda Oviedo, 2 Torres Cantabria 39300",
    "addr:housenumber":"2",
    "addr:postcode":"39300",
    "addr:street":"Avda Oviedo",
    "iso:country":"ES",
    "sg:address":"Avda Oviedo, 2",
    "sg:city":"Torres",
    "sg:orig_category":"Ense\u00d1anza Secundaria: Colegios Y Escuelas Privadas",
    "sg:phone":"+34 942 89 04 40",
    "sg:postcode":"39300",
    "sg:province":"Cantabria",
    "wof:name":"Instituto Nacional De Ense\u00f1anza Media Mixto Besaya",
    "wof:placetype":"venue"
},
  "geometry": {"coordinates":[-4.0659527779,43.3548088074],"type":"Point"}
}