{
  "type": "Feature",
  "properties": {
    "iso:country":"ES",
    "sg:address":"Avda Federico Garcia Lorca, 42",
    "sg:city":"Almeria",
    "sg:orig_category":"Aparcamientos (infraestructuras, Accesorios)",
    "sg:phone":"+34 950 25 30 60",
    "sg:postcode":"04004",
    "sg:province":"Almer\u00eda",
    "wof:name":"Garaje Belen, S.c.",
    "wof:placetype":"venue"
},
  "geometry": {"coordinates":[-2.4604578018,36.8377037048],"type":"Point"}
}