{
  "type": "Feature",
  "properties": {
    "iso:country":"ES",
    "sg:address":"Carrer de Sants, 384",
    "sg:city":"Barcelona",
    "sg:orig_category":"M\u00c9dicos: Medicina General",
    "sg:phone":"+34 934 40 33 44",
    "sg:postcode":"08028",
    "sg:province":"Barcelona",
    "wof:name":"Mdagnech Halabi Mohamad",
    "wof:placetype":"venue"
},
  "geometry": {"coordinates":[2.1220300198,41.3758392334],"type":"Point"}
}