{
  "type": "Feature",
  "properties": {
    "addr:full":"Calle de San Blas, 45 Pina De Ebro Zaragoza 50750",
    "addr:housenumber":"45",
    "addr:postcode":"50750",
    "addr:street":"Calle De San Blas",
    "iso:country":"ES",
    "sg:address":"Calle de San Blas, 45",
    "sg:city":"Pina De Ebro",
    "sg:orig_category":"Empresas De Carpinter\u00cda De Madera",
    "sg:phone":"+34 976 16 53 42",
    "sg:postcode":"50750",
    "sg:province":"Zaragoza",
    "wof:name":"Talleres Fanlo S.l.",
    "wof:placetype":"venue"
},
  "geometry": {"coordinates":[-0.5262389779,41.4924087524],"type":"Point"}
}