{
  "type": "Feature",
  "properties": {
    "addr:full":"Calle de Foguerer, 9 Alacant Alicante 03012",
    "addr:housenumber":"9",
    "addr:postcode":"03012",
    "addr:street":"Calle De Foguerer",
    "iso:country":"ES",
    "sg:address":"Calle de Foguerer, 9",
    "sg:city":"Alacant",
    "sg:orig_category":"Alquiler De V\u00cddeo",
    "sg:phone":"+34 965 24 03 49",
    "sg:postcode":"03012",
    "sg:province":"Alicante",
    "wof:name":"Video 84 S. L.",
    "wof:placetype":"venue"
},
  "geometry": {"coordinates":[-0.4796110094,38.3604927063],"type":"Point"}
}