{
  "type": "Feature",
  "properties": {
    "iso:country":"ES",
    "sg:address":"Carrer de Ramon Berenguer Iv (de), 60",
    "sg:city":"Tortosa",
    "sg:orig_category":"Venta, Colocaci\u00d3n, Reparaci\u00d3n De Parabrisas, Techos Descapotables",
    "sg:phone":"+34 977 44 01 14",
    "sg:postcode":"43500",
    "sg:province":"Tarragona",
    "wof:name":"Vidre Racing Tarragona S.l.",
    "wof:placetype":"venue"
},
  "geometry": {"coordinates":[0.5258449912,40.8102722168],"type":"Point"}
}