{
  "type": "Feature",
  "properties": {
    "iso:country":"ES",
    "sg:address":"Pl Joan Xxiii, 4",
    "sg:city":"S. Boi Llobregat",
    "sg:orig_category":"Molduras, Junquillos, Listones Y Molduras Perforadas",
    "sg:phone":"+34 936 30 51 63",
    "sg:postcode":"08830",
    "sg:province":"Barcelona",
    "wof:name":"Rodriguez Torres Natividad",
    "wof:placetype":"venue"
},
  "geometry": {"coordinates":[2.0399401188,41.3345603943],"type":"Point"}
}