{
  "type": "Feature",
  "properties": {
    "addr:full":"Calle de Conde De Vistahermosa, 40 Madrid Madrid 28019",
    "addr:housenumber":"40",
    "addr:postcode":"madrid;28019",
    "addr:street":"Calle De Conde De Vistahermosa",
    "iso:country":"ES",
    "sg:address":"Calle de Conde De Vistahermosa, 40",
    "sg:city":"Madrid",
    "sg:orig_category":"Limpieza Con Chorro De Arena Y Con Granalla, Pulido",
    "sg:phone":"+34 915 25 82 85",
    "sg:postcode":"28019",
    "sg:province":"Madrid",
    "wof:name":"Luengo Reyes Francisco Javier",
    "wof:placetype":"venue"
},
  "geometry": {"coordinates":[-3.7111606598,40.3937530518],"type":"Point"}
}