{
  "type": "Feature",
  "properties": {
    "addr:full":"Carrer de Siguenza, 34 Barcelona Barcelona 08032",
    "addr:housenumber":"34",
    "addr:postcode":"08032",
    "addr:street":"Carrer De Siguenza",
    "iso:country":"ES",
    "sg:address":"Carrer de Siguenza, 34",
    "sg:city":"Barcelona",
    "sg:orig_category":"Centros Empresariales",
    "sg:phone":"+34 933 57 11 59",
    "sg:postcode":"08032",
    "sg:province":"Barcelona",
    "wof:name":"Servicios Industriales Gabesa 22 S.l.",
    "wof:placetype":"venue"
},
  "geometry": {"coordinates":[2.154761076,41.4245185852],"type":"Point"}
}