{
  "type": "Feature",
  "properties": {
    "iso:country":"ES",
    "sg:address":"Urb Gondolas Iv (las), S/n",
    "sg:city":"Sevilla",
    "sg:orig_category":"Asociaciones, Organismos Culturales Y Socioeducativos",
    "sg:phone":"+34 954 90 68 14",
    "sg:postcode":"41020",
    "sg:province":"Sevilla",
    "wof:name":"Centro Cultural Aleman Goethe-zentrum",
    "wof:placetype":"venue"
},
  "geometry": {"coordinates":[-5.9419989586,37.3973846436],"type":"Point"}
}