{
  "type": "Feature",
  "properties": {
    "iso:country":"ES",
    "sg:address":"Calle de Luis Antunez, 32",
    "sg:city":"Palmas De Gran Canaria",
    "sg:orig_category":"Obras Y Organismos Sociales",
    "sg:phone":"+34 928 24 71 43",
    "sg:postcode":"35006",
    "sg:province":"Las Palmas",
    "wof:name":"Comision Espa\u00f1ola De Ayuda Al Refugiado",
    "wof:placetype":"venue"
},
  "geometry": {"coordinates":[-15.4304513931,28.1311378479],"type":"Point"}
}