{
  "type": "Feature",
  "properties": {
    "iso:country":"ES",
    "sg:address":"Calle de Louis Pasteur, 1",
    "sg:city":"Alcala Henares",
    "sg:orig_category":"Hormig\u00d3n (m\u00c1quinas E Instalaci\u00d3n)",
    "sg:phone":"+34 918 83 24 47",
    "sg:postcode":"28800",
    "sg:province":"Madrid",
    "wof:name":"Alkiherramienta S.a.",
    "wof:placetype":"venue"
},
  "geometry": {"coordinates":[-3.3864383698,40.4916038513],"type":"Point"}
}