{
  "type": "Feature",
  "properties": {
    "addr:full":"Calle de Goienkale, 7 Ermua Vizcaya 48260",
    "addr:housenumber":"7",
    "addr:postcode":"48260",
    "addr:street":"Calle De Goienkale",
    "iso:country":"ES",
    "sg:address":"Calle de Goienkale, 7",
    "sg:city":"Ermua",
    "sg:orig_category":"Molduras, Junquillos, Listones Y Molduras Perforadas",
    "sg:phone":"+34 943 17 45 84",
    "sg:postcode":"48260",
    "sg:province":"Vizcaya",
    "wof:name":"Infre\u00f1u Taberna C.b",
    "wof:placetype":"venue"
},
  "geometry": {"coordinates":[-2.5019996166,43.1887207031],"type":"Point"}
}