{
  "type": "Feature",
  "properties": {
    "addr:full":"Avda Colon, 137 Pobla Vallbona Valencia 46185",
    "addr:housenumber":"137",
    "addr:postcode":"46185",
    "addr:street":"Avda Colon",
    "iso:country":"ES",
    "sg:address":"Avda Colon, 137",
    "sg:city":"Pobla Vallbona",
    "sg:orig_category":"Electrodom\u00c9sticos (al Por Menor)",
    "sg:phone":"+34 962 76 10 52",
    "sg:postcode":"46185",
    "sg:province":"Valencia",
    "wof:name":"Estelles Medina Miguel",
    "wof:placetype":"venue"
},
  "geometry": {"coordinates":[-0.5532670021,39.5923614502],"type":"Point"}
}