{
  "type": "Feature",
  "properties": {
    "iso:country":"ES",
    "sg:address":"Carr Francesc Layret, 72",
    "sg:city":"Badalona",
    "sg:orig_category":"Ense\u00d1anza Variada",
    "sg:phone":"+34 933 89 03 40",
    "sg:postcode":"08911",
    "sg:province":"Barcelona",
    "wof:name":"Mas Delblanch Maria Dolors",
    "wof:placetype":"venue"
},
  "geometry": {"coordinates":[2.2483689785,41.4506874084],"type":"Point"}
}