{
  "type": "Feature",
  "properties": {
    "iso:country":"ES",
    "sg:address":"Calle de Marina (la), 2",
    "sg:city":"Abrigos",
    "sg:orig_category":"Centros Empresariales",
    "sg:phone":"+34 922 17 03 05",
    "sg:postcode":"38639",
    "sg:province":"Santa Cruz De Tenerife",
    "wof:name":"Daniel Canarias S.l.",
    "wof:placetype":"venue"
},
  "geometry": {"coordinates":[-16.6115474701,28.0350246429],"type":"Point"}
}