{
  "type": "Feature",
  "properties": {
    "addr:full":"Calle de Rafael Salgado, 27 Sevilla Sevilla 41013",
    "addr:housenumber":"27",
    "addr:postcode":"41013",
    "addr:street":"Calle De Rafael Salgado",
    "iso:country":"ES",
    "sg:address":"Calle de Rafael Salgado, 27",
    "sg:city":"Sevilla",
    "sg:orig_category":"Cl\u00cdnicas M\u00c9dicas",
    "sg:phone":"+34 954 62 78 02",
    "sg:postcode":"41013",
    "sg:province":"Sevilla",
    "wof:name":"Clinica Del Pie Bami S.civ.",
    "wof:placetype":"venue"
},
  "geometry": {"coordinates":[-5.9773697853,37.3605079651],"type":"Point"}
}