{
  "type": "Feature",
  "properties": {
    "addr:full":"Calle de Madre Antonia Paris, 4 Madrid Madrid 28027",
    "addr:housenumber":"4",
    "addr:postcode":"28027",
    "addr:street":"Calle De Madre Antonia Paris",
    "iso:country":"ES",
    "sg:address":"Calle de Madre Antonia Paris, 4",
    "sg:city":"Madrid",
    "sg:orig_category":"M\u00c9dicos: Estomatolog\u00cda",
    "sg:phone":"+34 913 26 47 90",
    "sg:postcode":"28027",
    "sg:province":"Madrid",
    "wof:name":"Ruiz Infante Jose Alfonso",
    "wof:placetype":"venue"
},
  "geometry": {"coordinates":[-3.6515569687,40.4445762634],"type":"Point"}
}