{
  "type": "Feature",
  "properties": {
    "addr:full":"Via Pignatelli, 11 Zaragoza Zaragoza 50007",
    "addr:housenumber":"11",
    "addr:postcode":"50007",
    "addr:street":"Via Pignatelli",
    "iso:country":"ES",
    "sg:address":"Via Pignatelli, 11",
    "sg:city":"Zaragoza",
    "sg:classifiers":[
        {
            "category":"Taxi",
            "type":"Transportation"
        }
    ],
    "sg:phone":"+34 976 37 58 71",
    "sg:postcode":"50007",
    "sg:province":"Zaragoza",
    "wof:name":"Lazaro Fabra Miguel",
    "wof:placetype":"venue"
},
  "geometry": {"coordinates":[-0.8860880136,41.6330223083],"type":"Point"}
}