{
  "type": "Feature",
  "properties": {
    "iso:country":"ES",
    "sg:address":"Calle de Crisanta (do\u00d1a), 9",
    "sg:city":"Tomelloso",
    "sg:orig_category":"Ingeniero",
    "sg:phone":"+34 926 51 34 03",
    "sg:postcode":"13700",
    "sg:province":"Ciudad Real",
    "wof:name":"Sanchez De La Nieta Garcia Fernando",
    "wof:placetype":"venue"
},
  "geometry": {"coordinates":[-3.0200352669,39.1578292847],"type":"Point"}
}