{
  "type": "Feature",
  "properties": {
    "addr:full":"Calle de Capitulares, 16 Cordoba C\u00f3rdoba 14002",
    "addr:housenumber":"16",
    "addr:postcode":"14002",
    "addr:street":"Calle De Capitulares;Co\u0301Rdoba",
    "iso:country":"ES",
    "sg:address":"Calle de Capitulares, 16",
    "sg:city":"Cordoba",
    "sg:orig_category":"Arquitectos",
    "sg:phone":"+34 957 48 82 02",
    "sg:postcode":"14002",
    "sg:province":"C\u00f3rdoba",
    "wof:name":"Moreno Moreno Jose",
    "wof:placetype":"venue"
},
  "geometry": {"coordinates":[-4.775967598,37.8850975037],"type":"Point"}
}