{
  "type": "Feature",
  "properties": {
    "iso:country":"ES",
    "sg:address":"Avda San Pablo (de), 51",
    "sg:city":"Coslada",
    "sg:orig_category":"Bazares, Art\u00cdculos De Limpieza Y De Cocina (al Por Menor)",
    "sg:phone":"+34 916 73 43 47",
    "sg:postcode":"28820",
    "sg:province":"Madrid",
    "wof:name":"Zou  Haifan",
    "wof:placetype":"venue"
},
  "geometry": {"coordinates":[-3.5332920551,40.4314079285],"type":"Point"}
}