{
  "type": "Feature",
  "properties": {
    "iso:country":"ES",
    "sg:address":"Calle de Espalmador, 62",
    "sg:city":"Matas-pinar-monte Rozas",
    "sg:orig_category":"Marketing Directo",
    "sg:phone":"+34 916 03 20 47",
    "sg:postcode":"28290",
    "sg:province":"Madrid",
    "wof:name":"Aplicaciones Y Estudios De Marketing S.l.",
    "wof:placetype":"venue"
},
  "geometry": {"coordinates":[-3.8917694092,40.5363616943],"type":"Point"}
}