{
  "type": "Feature",
  "properties": {
    "iso:country":"ES",
    "sg:address":"Avda Constitucion, 56",
    "sg:city":"Villena",
    "sg:orig_category":"Inmobiliaria (agencias)",
    "sg:phone":"+34 965 80 09 40",
    "sg:postcode":"03400",
    "sg:province":"Alicante",
    "wof:name":"Milan Builders S.l.",
    "wof:placetype":"venue"
},
  "geometry": {"coordinates":[-0.8650599718,38.6344108582],"type":"Point"}
}