{
  "type": "Feature",
  "properties": {
    "iso:country":"ES",
    "sg:address":"Carr Marques Del Turia, 51",
    "sg:city":"Benetusser",
    "sg:orig_category":"Ense\u00d1anza, Formaci\u00d3n Profesional: Aprendizaje",
    "sg:phone":"+34 963 76 28 29",
    "sg:postcode":"46910",
    "sg:province":"Valencia",
    "wof:name":"Ayuntamiento De Benetusser",
    "wof:placetype":"venue"
},
  "geometry": {"coordinates":[-0.3974896967,39.4242286682],"type":"Point"}
}