{
  "type": "Feature",
  "properties": {
    "iso:country":"ES",
    "sg:address":"Calle de Gorrion, 2",
    "sg:city":"Madrid",
    "sg:orig_category":"Empresarios",
    "sg:phone":"+34 914 71 34 63",
    "sg:postcode":"28019",
    "sg:province":"Madrid",
    "wof:name":"Fundacion Tomillo",
    "wof:placetype":"venue"
},
  "geometry": {"coordinates":[-3.7273631096,40.3960113525],"type":"Point"}
}