{
  "type": "Feature",
  "properties": {
    "iso:country":"ES",
    "sg:address":"O Peso, S/n",
    "sg:city":"Peso",
    "sg:orig_category":"Piscinas, Accesorios, Suministros (fabricaci\u00d3n, Al Por Mayor)",
    "sg:phone":"+34 986 64 40 35",
    "sg:postcode":"36869",
    "sg:province":"Pontevedra",
    "wof:name":"Covelo Riegos S.l.",
    "wof:placetype":"venue"
},
  "geometry": {"coordinates":[-8.5002822876,42.1918334961],"type":"Point"}
}