{
  "type": "Feature",
  "properties": {
    "iso:country":"ES",
    "sg:address":"Carrer de Ramon Y Cajal, 48",
    "sg:city":"Alcanar",
    "sg:orig_category":"Caf\u00c9s, Bares, Cervecer\u00cdas",
    "sg:phone":"+34 977 73 03 60",
    "sg:postcode":"43530",
    "sg:province":"Tarragona",
    "wof:name":"Sistelcom-telemensaje S.a.",
    "wof:placetype":"venue"
},
  "geometry": {"coordinates":[0.4815019965,40.5408973694],"type":"Point"}
}