{
  "type": "Feature",
  "properties": {
    "iso:country":"ES",
    "sg:address":"Carrer de Sant Iscle, 12",
    "sg:city":"Barcelona",
    "sg:orig_category":"Ropa Para Ni\u00d1os (al Por Menor)",
    "sg:phone":"+34 933 40 92 25",
    "sg:postcode":"08031",
    "sg:province":"Barcelona",
    "wof:name":"Navarro Diaz Pablo",
    "wof:placetype":"venue"
},
  "geometry": {"coordinates":[2.1739480495,41.4309082031],"type":"Point"}
}