{
  "type": "Feature",
  "properties": {
    "iso:country":"ES",
    "sg:address":"Parrilla, S/n",
    "sg:city":"Herrera De Duero",
    "sg:orig_category":"Internados & Ense\u00d1anza Privada",
    "sg:phone":"+34 983 52 86 21",
    "sg:postcode":"47161",
    "sg:province":"Valladolid",
    "wof:name":"Gonzalez Diez Carmen",
    "wof:placetype":"venue"
},
  "geometry": {"coordinates":[-4.6513175964,41.5638885498],"type":"Point"}
}