{
  "type": "Feature",
  "properties": {
    "addr:full":"Calle de Rafael De La Hoz, 10 Madrid Madrid 28022",
    "addr:housenumber":"10",
    "addr:postcode":"madrid;28022",
    "addr:street":"Calle De Rafael De La Hoz",
    "iso:country":"ES",
    "sg:address":"Calle de Rafael De La Hoz, 10",
    "sg:city":"Madrid",
    "sg:orig_category":"Importaci\u00d3n",
    "sg:phone":"+34 913 20 38 04",
    "sg:postcode":"28022",
    "sg:province":"Madrid",
    "wof:name":"Interlube S.l.",
    "wof:placetype":"venue"
},
  "geometry": {"coordinates":[-3.616740942,40.4451637268],"type":"Point"}
}