{
  "type": "Feature",
  "properties": {
    "addr:full":"Avda Ordo\u00d1o Ii, 21 Le\u00f3n Le\u00f3n 24001",
    "addr:housenumber":"21",
    "addr:postcode":"24001",
    "addr:street":"Avda Ordon\u0303O Ii;Leo\u0301N",
    "iso:country":"ES",
    "sg:address":"Avda Ordo\u00d1o Ii, 21",
    "sg:city":"Le\u00f3n",
    "sg:orig_category":"Cajas De Ahorro",
    "sg:phone":"+34 987 21 84 90",
    "sg:postcode":"24001",
    "sg:province":"Le\u00f3n",
    "sg:website":"www.caixacatalunya.es",
    "wof:name":"Caixa D'estalvis De Catalunya",
    "wof:placetype":"venue"
},
  "geometry": {"coordinates":[-5.5744309425,42.5970344543],"type":"Point"}
}