{
  "type": "Feature",
  "properties": {
    "addr:full":"Pase Duque De Ahumada, 3 Vista Alegre Murcia 30007",
    "addr:housenumber":"3",
    "addr:postcode":"30007",
    "addr:street":"Ahumada",
    "iso:country":"ES",
    "sg:address":"Pase Duque De Ahumada, 3",
    "sg:city":"Vista Alegre",
    "sg:classifiers":[
        {
            "category":"Personal",
            "subcategory":"Barber",
            "type":"Services"
        }
    ],
    "sg:phone":"+34 968 20 49 17",
    "sg:postcode":"30007",
    "sg:province":"Murcia",
    "sg:tags":[
        "caballeros",
        "de",
        "peluqueros"
    ],
    "wof:name":"Belleza Integral Alma Gallego S.l.",
    "wof:placetype":"venue"
},
  "geometry": {"coordinates":[-1.1142389774,37.9970092773],"type":"Point"}
}