{
  "type": "Feature",
  "properties": {
    "addr:full":"Calle de Toledo, 78 Madrid Madrid 28005",
    "addr:housenumber":"78",
    "addr:postcode":"madrid;28005",
    "addr:street":"Calle De Toledo",
    "iso:country":"ES",
    "sg:address":"Calle de Toledo, 78",
    "sg:city":"Madrid",
    "sg:orig_category":"Mercer\u00cda, Lencer\u00cda (al Por Menor)",
    "sg:phone":"+34 913 65 48 41",
    "sg:postcode":"28005",
    "sg:province":"Madrid",
    "wof:name":"Tobes Mendez Jose",
    "wof:placetype":"venue"
},
  "geometry": {"coordinates":[-3.7101280689,40.4092216492],"type":"Point"}
}