{
  "type": "Feature",
  "properties": {
    "iso:country":"ES",
    "sg:address":"Plaz Marques De Aracena, 6",
    "sg:city":"Aracena",
    "sg:orig_category":"Arquitectos",
    "sg:phone":"+34 959 12 87 17",
    "sg:postcode":"21200",
    "sg:province":"Huelva",
    "wof:name":"Vazquez Vazquez Hilario",
    "wof:placetype":"venue"
},
  "geometry": {"coordinates":[-6.560833931,37.893863678],"type":"Point"}
}