{
  "type": "Feature",
  "properties": {
    "addr:full":"Cmno Ca\u00d1ada (de La), 8 Biar Alicante 03410",
    "addr:housenumber":"8",
    "addr:postcode":"03410",
    "addr:street":"Cmno Can\u0303Ada De La",
    "iso:country":"ES",
    "sg:address":"Cmno Ca\u00d1ada (de La), 8",
    "sg:city":"Biar",
    "sg:orig_category":"Fabricaci\u00d3n De Telas Y Sedas",
    "sg:phone":"+34 965 81 03 29",
    "sg:postcode":"03410",
    "sg:province":"Alicante",
    "wof:name":"Textiles Jomi S.l.",
    "wof:placetype":"venue"
},
  "geometry": {"coordinates":[-0.76947999,38.6329879761],"type":"Point"}
}