{
  "type": "Feature",
  "properties": {
    "iso:country":"ES",
    "sg:address":"Carrer de Marti Folguera, 20",
    "sg:city":"Reus",
    "sg:orig_category":"Ropa Para Se\u00d1oras Y Caballeros (al Por Menor)",
    "sg:phone":"+34 977 34 44 20",
    "sg:postcode":"43203",
    "sg:province":"Tarragona",
    "wof:name":"Soriano Sanchez Angeles",
    "wof:placetype":"venue"
},
  "geometry": {"coordinates":[1.1146999598,41.1628303528],"type":"Point"}
}