{
  "type": "Feature",
  "properties": {
    "addr:full":"Calle de Curros Enriquez, 43 Coru\u00d1a La Coru\u00f1a 15002",
    "addr:housenumber":"43",
    "addr:postcode":"15002",
    "addr:street":"Calle De Curros Enriquez;Corun\u0303A",
    "iso:country":"ES",
    "sg:address":"Calle de Curros Enriquez, 43",
    "sg:city":"Coru\u00d1a",
    "sg:orig_category":"Agencias De Trabajo Temporal",
    "sg:phone":"+34 981 21 74 95",
    "sg:postcode":"15002",
    "sg:province":"La Coru\u00f1a",
    "wof:name":"Bampimor S.l.",
    "wof:placetype":"venue"
},
  "geometry": {"coordinates":[-8.4014320374,43.3746261597],"type":"Point"}
}