{
  "type": "Feature",
  "properties": {
    "iso:country":"ES",
    "sg:address":"Carrer de Rossello, 21",
    "sg:city":"S. Cugat Valles",
    "sg:orig_category":"Ingeniero",
    "sg:phone":"+34 936 75 47 54",
    "sg:postcode":"08172",
    "sg:province":"Barcelona",
    "wof:name":"Telecomunicaciones Inter K-ahmed S.l.",
    "wof:placetype":"venue"
},
  "geometry": {"coordinates":[2.0789349079,41.4691772461],"type":"Point"}
}