{
  "type": "Feature",
  "properties": {
    "iso:country":"ES",
    "sg:address":"Calle de Pedro Maria Ric, 23",
    "sg:city":"Zaragoza",
    "sg:orig_category":"Puertas Y Portales",
    "sg:phone":"+34 976 22 81 30",
    "sg:postcode":"50008",
    "sg:province":"Zaragoza",
    "wof:name":"Gines Blasco Antonio",
    "wof:placetype":"venue"
},
  "geometry": {"coordinates":[-0.882445991,41.6446228027],"type":"Point"}
}