{
  "type": "Feature",
  "properties": {
    "addr:full":"Calle de Salvador Tuset, 16 Valencia Valencia 46025",
    "addr:housenumber":"16",
    "addr:postcode":"46025",
    "addr:street":"Calle De Salvador Tuset",
    "iso:country":"ES",
    "sg:address":"Calle de Salvador Tuset, 16",
    "sg:city":"Valencia",
    "sg:orig_category":"Plomeros",
    "sg:phone":"+34 963 48 98 03",
    "sg:postcode":"46025",
    "sg:province":"Valencia",
    "wof:name":"Ribes Lledo Vicente",
    "wof:placetype":"venue"
},
  "geometry": {"coordinates":[-0.3941009939,39.4957008362],"type":"Point"}
}