{
  "type": "Feature",
  "properties": {
    "addr:full":"Calle de Huesca De, 66 Fraga Huesca 22520",
    "addr:housenumber":"66",
    "addr:postcode":"22520",
    "addr:street":"Calle De Huesca De",
    "iso:country":"ES",
    "sg:address":"Calle de Huesca De, 66",
    "sg:city":"Fraga",
    "sg:orig_category":"Energ\u00cda Solar Y Nuevas Energ\u00cdas (equipo, Estudios)",
    "sg:phone":"+34 974 47 13 53",
    "sg:postcode":"22520",
    "sg:province":"Huesca",
    "wof:name":"Provodit Ingenieria S.a.",
    "wof:placetype":"venue"
},
  "geometry": {"coordinates":[0.3287003934,41.5203781128],"type":"Point"}
}