{
  "type": "Feature",
  "properties": {
    "addr:full":"Plaz Campo, S/n Zas La Coru\u00f1a 15850",
    "addr:housenumber":"s / n",
    "addr:postcode":"15850",
    "addr:street":"Campo;La Corun\u0303A",
    "iso:country":"ES",
    "sg:address":"Plaz Campo, S/n",
    "sg:city":"Zas",
    "sg:orig_category":"Abogados",
    "sg:phone":"+34 981 75 11 11",
    "sg:postcode":"15850",
    "sg:province":"La Coru\u00f1a",
    "wof:name":"Administracion De Justicia",
    "wof:placetype":"venue"
},
  "geometry": {"coordinates":[-8.9161491394,43.0997467041],"type":"Point"}
}