{
  "type": "Feature",
  "properties": {
    "iso:country":"ES",
    "sg:address":"Calle de Virgen Del Val, 19",
    "sg:city":"Madrid",
    "sg:orig_category":"Electricidad Veh\u00cdculo",
    "sg:phone":"+34 914 03 98 66",
    "sg:postcode":"28027",
    "sg:province":"Madrid",
    "wof:name":"Zapatero Andres Juan Antonio",
    "wof:placetype":"venue"
},
  "geometry": {"coordinates":[-3.6525170803,40.4388008118],"type":"Point"}
}