{
  "type": "Feature",
  "properties": {
    "addr:full":"Carr Miquel Dol\u00c7, 6 Santa Maria Del Cami Islas Baleares 07320",
    "addr:housenumber":"6",
    "addr:postcode":"07320",
    "addr:street":"Carr Miquel Dolc\u0327;Islas",
    "iso:country":"ES",
    "sg:address":"Carr Miquel Dol\u00c7, 6",
    "sg:city":"Santa Maria Del Cami",
    "sg:orig_category":"Administradores De Bienes Y Delegados De Comunidades De Propietarios",
    "sg:phone":"+34 971 62 15 87",
    "sg:postcode":"07320",
    "sg:province":"Islas Baleares",
    "wof:name":"Mallor-k Managers.s.l",
    "wof:placetype":"venue"
},
  "geometry": {"coordinates":[2.7733559608,39.649772644],"type":"Point"}
}