{
  "type": "Feature",
  "properties": {
    "iso:country":"ES",
    "sg:address":"Fabrica, S/n",
    "sg:city":"Navaconcejo",
    "sg:orig_category":"Iglesia Cat\u00d3lica",
    "sg:phone":"+34 927 17 31 69",
    "sg:postcode":"10613",
    "sg:province":"C\u00e1ceres",
    "wof:name":"Parroquia Nuestra Se\u00f1ora De La Asuncion",
    "wof:placetype":"venue"
},
  "geometry": {"coordinates":[-5.8327112198,40.1775016785],"type":"Point"}
}