{
  "type": "Feature",
  "properties": {
    "addr:full":"Avda Duque De Bivona, 9 Ayerbe Huesca 22800",
    "addr:housenumber":"9",
    "addr:postcode":"22800",
    "addr:street":"Avda Duque De Bivona",
    "iso:country":"ES",
    "sg:address":"Avda Duque De Bivona, 9",
    "sg:city":"Ayerbe",
    "sg:orig_category":"Iglesia Cat\u00d3lica",
    "sg:phone":"+34 974 38 00 48",
    "sg:postcode":"22800",
    "sg:province":"Huesca",
    "wof:name":"Parroquia De San Pedro",
    "wof:placetype":"venue"
},
  "geometry": {"coordinates":[-0.6901360154,42.2784156799],"type":"Point"}
}