{
  "type": "Feature",
  "properties": {
    "iso:country":"ES",
    "sg:address":"Encina, 6",
    "sg:city":"Prado Largo",
    "sg:orig_category":"Asesor\u00cda Sobre Comunicaci\u00d3n De Empresas",
    "sg:phone":"+34 913 51 06 11",
    "sg:postcode":"28223",
    "sg:province":"Madrid",
    "wof:name":"Estudios Economicos Y Estrategicos S.a.",
    "wof:placetype":"venue"
},
  "geometry": {"coordinates":[-3.8146739006,40.4409713745],"type":"Point"}
}