{
  "type": "Feature",
  "properties": {
    "addr:full":"Carrer de Secretari Coloma, 57 Barcelona Barcelona 08024",
    "addr:housenumber":"57",
    "addr:postcode":"08024",
    "addr:street":"Carrer De Secretari Coloma",
    "iso:country":"ES",
    "sg:address":"Carrer de Secretari Coloma, 57",
    "sg:city":"Barcelona",
    "sg:orig_category":"Centros Empresariales",
    "sg:phone":"+34 932 19 19 00",
    "sg:postcode":"08024",
    "sg:province":"Barcelona",
    "wof:name":"Administracion Galerias De Servicio De Las Rondas De Barcelona S.l.",
    "wof:placetype":"venue"
},
  "geometry": {"coordinates":[2.1634893417,41.4089927673],"type":"Point"}
}