{
  "type": "Feature",
  "properties": {
    "addr:full":"Calle de Teniente General Gutierrez Mellado, 9 Fama Murcia 30008",
    "addr:housenumber":"9",
    "addr:postcode":"30008",
    "addr:street":"Calle De Teniente General Gutierrez Mellado",
    "iso:country":"ES",
    "sg:address":"Calle de Teniente General Gutierrez Mellado, 9",
    "sg:city":"Fama",
    "sg:orig_category":"Bisuter\u00cda, Joyer\u00cda, Relojer\u00cda (al Por Menor)",
    "sg:phone":"+34 968 23 47 64",
    "sg:postcode":"30008",
    "sg:province":"Murcia",
    "sg:website":"www.mpjoyeros.com",
    "wof:name":"Mis Peque\u00f1os Joyeros S.l.",
    "wof:placetype":"venue"
},
  "geometry": {"coordinates":[-1.1277829409,37.9899139404],"type":"Point"}
}