{
  "type": "Feature",
  "properties": {
    "addr:full":"Calle de Murcia, 15 Tordesillas Valladolid 47100",
    "addr:housenumber":"15",
    "addr:postcode":"47100",
    "addr:street":"Calle De Murcia",
    "iso:country":"ES",
    "sg:address":"Calle de Murcia, 15",
    "sg:city":"Tordesillas",
    "sg:orig_category":"Promotores Constructores",
    "sg:phone":"+34 983 79 63 05",
    "sg:postcode":"47100",
    "sg:province":"Valladolid",
    "wof:name":"Alonso Bastida Juan Jose",
    "wof:placetype":"venue"
},
  "geometry": {"coordinates":[-5.0049347878,41.5000228882],"type":"Point"}
}