{
  "type": "Feature",
  "properties": {
    "addr:full":"Carrer de Sant Jaume, 428 Calella Barcelona 08370",
    "addr:housenumber":"428",
    "addr:postcode":"08370",
    "addr:street":"Carrer De Sant Jaume",
    "iso:country":"ES",
    "sg:address":"Carrer de Sant Jaume, 428",
    "sg:city":"Calella",
    "sg:orig_category":"Comercio De Piezas De Recambio Y De Accesorios De Veh\u00cdculos, Veh\u00cdculos Industriales",
    "sg:phone":"+34 937 66 42 10",
    "sg:postcode":"08370",
    "sg:province":"Barcelona",
    "wof:name":"Recambios Del Automovil Area Nou S.l.",
    "wof:placetype":"venue"
},
  "geometry": {"coordinates":[2.6648929119,41.6192321777],"type":"Point"}
}