{
  "type": "Feature",
  "properties": {
    "iso:country":"ES",
    "sg:address":"Rua Berlin (de), S/n",
    "sg:city":"Santiago De Compostela",
    "sg:orig_category":"Aparcamientos (infraestructuras, Accesorios)",
    "sg:phone":"+34 981 56 01 49",
    "sg:postcode":"15703",
    "sg:province":"La Coru\u00f1a",
    "wof:name":"Cintra Aparcamientos S.a.",
    "wof:placetype":"venue"
},
  "geometry": {"coordinates":[-8.5332660675,42.8845977783],"type":"Point"}
}