{
  "type": "Feature",
  "properties": {
    "addr:full":"Calle de Nueva, 48 Pto Real C\u00e1diz 11510",
    "addr:housenumber":"48",
    "addr:postcode":"11510",
    "addr:street":"Calle De Nueva;Ca\u0301Diz",
    "iso:country":"ES",
    "sg:address":"Calle de Nueva, 48",
    "sg:city":"Pto Real",
    "sg:orig_category":"Ropa Para Se\u00d1oras Y Caballeros (al Por Menor)",
    "sg:phone":"+34 956 47 49 83",
    "sg:postcode":"11510",
    "sg:province":"C\u00e1diz",
    "wof:name":"Caballero Pedrosa S.c.",
    "wof:placetype":"venue"
},
  "geometry": {"coordinates":[-6.1909937859,36.5287246704],"type":"Point"}
}