{
  "type": "Feature",
  "properties": {
    "addr:full":"Calle de Pe\u00d1a Ubi\u00d1a, 41 Madrid Madrid 28053",
    "addr:housenumber":"41",
    "addr:postcode":"madrid;28053",
    "addr:street":"Calle De Pen\u0303A Ubin\u0303A",
    "iso:country":"ES",
    "sg:address":"Calle de Pe\u00d1a Ubi\u00d1a, 41",
    "sg:city":"Madrid",
    "sg:orig_category":"Fabricaci\u00d3n De Productos Textiles Sin Tejer",
    "sg:phone":"+34 915 51 77 91",
    "sg:postcode":"28053",
    "sg:province":"Madrid",
    "wof:name":"Tejidos Carmena S.l.",
    "wof:placetype":"venue"
},
  "geometry": {"coordinates":[-3.6690831184,40.3952941895],"type":"Point"}
}