{
  "type": "Feature",
  "properties": {
    "iso:country":"ES",
    "sg:address":"Ctra Const-puebla Infantes, S/n",
    "sg:city":"Constantina",
    "sg:orig_category":"Frutas Y Legumbres Frescas (al Por Mayor)",
    "sg:phone":"+34 955 88 06 50",
    "sg:postcode":"41450",
    "sg:province":"Sevilla",
    "wof:name":"Marin Marquez Francisco",
    "wof:placetype":"venue"
},
  "geometry": {"coordinates":[-5.6197562218,37.8712120056],"type":"Point"}
}