{
  "type": "Feature",
  "properties": {
    "iso:country":"ES",
    "sg:address":"Pg Sant Joan, 88",
    "sg:city":"Manlleu",
    "sg:orig_category":"Carnicer\u00cdas, Carnicer\u00cdas",
    "sg:phone":"+34 938 51 42 57",
    "sg:postcode":"08560",
    "sg:province":"Barcelona",
    "wof:name":"Batlle Sanjaume Juan",
    "wof:placetype":"venue"
},
  "geometry": {"coordinates":[2.2857570648,42.0017814636],"type":"Point"}
}