{
  "type": "Feature",
  "properties": {
    "addr:full":"Carrer de Tarragona, 92 Barcelona Barcelona 08015",
    "addr:housenumber":"92",
    "addr:postcode":"08015",
    "addr:street":"Carrer De Tarragona",
    "iso:country":"ES",
    "sg:address":"Carrer de Tarragona, 92",
    "sg:city":"Barcelona",
    "sg:orig_category":"Bancos",
    "sg:phone":"+34 932 26 46 76",
    "sg:postcode":"08015",
    "sg:province":"Barcelona",
    "wof:name":"Bankinter S.a.",
    "wof:placetype":"venue"
},
  "geometry": {"coordinates":[2.1452150345,41.3787727356],"type":"Point"}
}