{
  "type": "Feature",
  "properties": {
    "iso:country":"ES",
    "sg:address":"Calle de Cruz De La, 10",
    "sg:city":"Torremolinos",
    "sg:orig_category":"Centros Comerciales Y Grandes Tiendas",
    "sg:phone":"+34 952 38 51 24",
    "sg:postcode":"29620",
    "sg:province":"M\u00e1laga",
    "wof:name":"Aguado Vidal Maria Angeles",
    "wof:placetype":"venue"
},
  "geometry": {"coordinates":[-4.4988780022,36.6255226135],"type":"Point"}
}