{
  "type": "Feature",
  "properties": {
    "addr:full":"Calle de Corrida, 7 Gijon Asturias 33206",
    "addr:housenumber":"7",
    "addr:postcode":"33206",
    "addr:street":"Calle De Corrida",
    "iso:country":"ES",
    "sg:address":"Calle de Corrida, 7",
    "sg:city":"Gijon",
    "sg:orig_category":"Promotores Constructores",
    "sg:phone":"+34 985 34 35 67",
    "sg:postcode":"33206",
    "sg:province":"Asturias",
    "wof:name":"Ceyd S.a.u.",
    "wof:placetype":"venue"
},
  "geometry": {"coordinates":[-5.6642284393,43.5432929993],"type":"Point"}
}