{
  "type": "Feature",
  "properties": {
    "iso:country":"ES",
    "sg:address":"Calle de Ubeda, 11",
    "sg:city":"Linares",
    "sg:orig_category":"Quincaller\u00cda (al Por Menor)",
    "sg:phone":"+34 953 65 67 87",
    "sg:postcode":"23700",
    "sg:province":"Ja\u00e9n",
    "wof:name":"Hermanos Garcia Culebra S.l.",
    "wof:placetype":"venue"
},
  "geometry": {"coordinates":[-3.6174190044,38.0962905884],"type":"Point"}
}