{
  "type": "Feature",
  "properties": {
    "iso:country":"ES",
    "sg:address":"Carrer de Gabriel Maura, 16",
    "sg:city":"Palma",
    "sg:orig_category":"Sociedades, Compa\u00d1\u00cdas Aseguradoras",
    "sg:phone":"+34 971 24 87 50",
    "sg:postcode":"07005",
    "sg:province":"Islas Baleares",
    "wof:name":"Gabinete De Seguros Alomar S.l.",
    "wof:placetype":"venue"
},
  "geometry": {"coordinates":[2.659291029,39.5780982971],"type":"Point"}
}