{
  "type": "Feature",
  "properties": {
    "addr:full":"Calle de Hermosilla, 85 Madrid Madrid 28001",
    "addr:housenumber":"85",
    "addr:postcode":"madrid;28001",
    "addr:street":"Calle De Hermosilla",
    "iso:country":"ES",
    "sg:address":"Calle de Hermosilla, 85",
    "sg:city":"Madrid",
    "sg:orig_category":"Loter\u00cda Y T\u00d3mbola",
    "sg:phone":"+34 914 31 12 09",
    "sg:postcode":"28001",
    "sg:province":"Madrid",
    "wof:name":"Pe\u00f1as Varela Isabel De La Trinidad",
    "wof:placetype":"venue"
},
  "geometry": {"coordinates":[-3.6768629551,40.4261169434],"type":"Point"}
}