{
  "type": "Feature",
  "properties": {
    "addr:full":"Carr Peralada, 24 Figueres Girona 17600",
    "addr:housenumber":"24",
    "addr:postcode":"17600",
    "addr:street":"Carr Peralada",
    "iso:country":"ES",
    "sg:address":"Carr Peralada, 24",
    "sg:city":"Figueres",
    "sg:orig_category":"Agencias De Viajes",
    "sg:phone":"+34 972 50 91 00",
    "sg:postcode":"17600",
    "sg:province":"Girona",
    "wof:name":"Viatges Figueres S. L.",
    "wof:placetype":"venue"
},
  "geometry": {"coordinates":[2.9620549679,42.2678413391],"type":"Point"}
}