{
  "type": "Feature",
  "properties": {
    "addr:full":"Calle de Pollo (del), 4 Jerez De La Frontera C\u00e1diz 11401",
    "addr:postcode":"11401",
    "addr:street":"Calle De;Del",
    "iso:country":"ES",
    "sg:address":"Calle de Pollo (del), 4",
    "sg:city":"Jerez De La Frontera",
    "sg:orig_category":"M\u00c1rmoles, Granitos Y Piedras Naturales",
    "sg:phone":"+34 956 34 45 57",
    "sg:postcode":"11401",
    "sg:province":"C\u00e1diz",
    "wof:name":"Rey Infante Guillermo",
    "wof:placetype":"venue"
},
  "geometry": {"coordinates":[-6.136138916,36.679233551],"type":"Point"}
}