{
  "type": "Feature",
  "properties": {
    "addr:full":"Carrer de Muralla Del Carme, 17 Manresa Barcelona 08241",
    "addr:housenumber":"17",
    "addr:postcode":"08241",
    "addr:street":"Carrer De Muralla Del Carme",
    "iso:country":"ES",
    "sg:address":"Carrer de Muralla Del Carme, 17",
    "sg:city":"Manresa",
    "sg:orig_category":"Sociedades, Compa\u00d1\u00cdas Aseguradoras",
    "sg:phone":"+34 938 72 62 33",
    "sg:postcode":"08241",
    "sg:province":"Barcelona",
    "wof:name":"Alberti Carrera Corredoria D'assegurances S.a.",
    "wof:placetype":"venue"
},
  "geometry": {"coordinates":[1.8249192238,41.7253303528],"type":"Point"}
}