{
  "type": "Feature",
  "properties": {
    "addr:full":"Calle de Legion, La, 45 Melilla Melilla 52006",
    "addr:housenumber":"45",
    "addr:postcode":"52006",
    "addr:street":"Calle De Legion La",
    "iso:country":"ES",
    "sg:address":"Calle de Legion, La, 45",
    "sg:city":"Melilla",
    "sg:orig_category":"Farmacias",
    "sg:phone":"+34 952 69 60 82",
    "sg:postcode":"52006",
    "sg:province":"Melilla",
    "wof:name":"Rosso Martinez Juan Manuel",
    "wof:placetype":"venue"
},
  "geometry": {"coordinates":[-2.9361999035,35.2828216553],"type":"Point"}
}