{
  "type": "Feature",
  "properties": {
    "addr:full":"Calle de Morronguilleta, 8 Errenteria Guip\u00f9zcoa 20100",
    "addr:housenumber":"8",
    "addr:postcode":"20100",
    "addr:street":"Calle De Morronguilleta;Guipu\u0300Zcoa",
    "iso:country":"ES",
    "sg:address":"Calle de Morronguilleta, 8",
    "sg:city":"Errenteria",
    "sg:orig_category":"Promotores Constructores",
    "sg:phone":"+34 943 51 55 99",
    "sg:postcode":"20100",
    "sg:province":"Guip\u00f9zcoa",
    "wof:name":"Irazu Zumeta Jose Maria",
    "wof:placetype":"venue"
},
  "geometry": {"coordinates":[-1.9017720222,43.3126945496],"type":"Point"}
}