{
  "type": "Feature",
  "properties": {
    "iso:country":"ES",
    "sg:address":"Carrer de Industria, 45",
    "sg:city":"Barcelona",
    "sg:orig_category":"Inmobiliaria (agencias)",
    "sg:phone":"+34 934 58 57 36",
    "sg:postcode":"08025",
    "sg:province":"Barcelona",
    "sg:website":"www.mfcongost.com",
    "wof:name":"Peces Del Valles S.l.",
    "wof:placetype":"venue"
},
  "geometry": {"coordinates":[2.1670200825,41.4041671753],"type":"Point"}
}