{
  "type": "Feature",
  "properties": {
    "iso:country":"ES",
    "sg:address":"Avda Alcala (de), 1",
    "sg:city":"Azuqueca Henares",
    "sg:orig_category":"Cervecer\u00cdas",
    "sg:phone":"+34 949 26 48 75",
    "sg:postcode":"19200",
    "sg:province":"Guadalajara",
    "wof:name":"Sanchez Taravillo Higinio",
    "wof:placetype":"venue"
},
  "geometry": {"coordinates":[-3.2718789577,40.5606918335],"type":"Point"}
}