{
  "type": "Feature",
  "properties": {
    "addr:full":"Calle de Medico Almagro, S/n Almedinilla C\u00f3rdoba 14812",
    "addr:housenumber":"s / n",
    "addr:postcode":"14812",
    "addr:street":"Calle De Medico Almagro",
    "iso:country":"ES",
    "sg:address":"Calle de Medico Almagro, S/n",
    "sg:city":"Almedinilla",
    "sg:orig_category":"Asilos De Ancianos. Centros Privados",
    "sg:phone":"+34 957 70 21 62",
    "sg:postcode":"14812",
    "sg:province":"C\u00f3rdoba",
    "wof:name":"Fundacion Geron",
    "wof:placetype":"venue"
},
  "geometry": {"coordinates":[-4.0904388428,37.4390335083],"type":"Point"}
}