{
  "type": "Feature",
  "properties": {
    "addr:full":"Poligono Industrial Calle de B, 1 Iraizotz Navarra 31797",
    "addr:housenumber":"1",
    "addr:postcode":"31797",
    "addr:street":"Calle De B",
    "iso:country":"ES",
    "sg:address":"Poligono Industrial Calle de B, 1",
    "sg:city":"Iraizotz",
    "sg:orig_category":"Perfumer\u00cda Y Cosm\u00c9tica (fabricaci\u00d3n, Al Por Mayor)",
    "sg:phone":"+34 948 30 92 45",
    "sg:postcode":"31797",
    "sg:province":"Navarra",
    "wof:name":"Aurum Cosmetic S.l.",
    "wof:placetype":"venue"
},
  "geometry": {"coordinates":[-1.6957390308,42.9793548584],"type":"Point"}
}