{
  "type": "Feature",
  "properties": {
    "addr:full":"Barr Barqueria (la), S/n Pedre\u00f1a Cantabria 39130",
    "addr:postcode":"39130",
    "addr:street":"La S / N",
    "iso:country":"ES",
    "sg:address":"Barr Barqueria (la), S/n",
    "sg:city":"Pedre\u00f1a",
    "sg:orig_category":"Estudios, Instalaci\u00d3n De Climatizaci\u00d3n",
    "sg:phone":"+34 942 50 04 78",
    "sg:postcode":"39130",
    "sg:province":"Cantabria",
    "wof:name":"Instalaire S.a.",
    "wof:placetype":"venue"
},
  "geometry": {"coordinates":[-3.7675850391,43.443397522],"type":"Point"}
}