{
  "type": "Feature",
  "properties": {
    "iso:country":"ES",
    "sg:address":"Poligono De Arzua, 8",
    "sg:city":"Arzua",
    "sg:orig_category":"Imprenta",
    "sg:phone":"+34 981 50 04 05",
    "sg:postcode":"15810",
    "sg:province":"La Coru\u00f1a",
    "wof:name":"Lopez Ayude Carlos",
    "wof:placetype":"venue"
},
  "geometry": {"coordinates":[-8.1532869339,42.937625885],"type":"Point"}
}