{
  "type": "Feature",
  "properties": {
    "iso:country":"ES",
    "sg:address":"Av Llibertad, 9",
    "sg:city":"Javea",
    "sg:orig_category":"Agencias De Viajes",
    "sg:phone":"+34 966 46 28 57",
    "sg:postcode":"03730",
    "sg:province":"Alicante",
    "wof:name":"Xabia Travel S.l.",
    "wof:placetype":"venue"
},
  "geometry": {"coordinates":[0.1907353997,38.7717094421],"type":"Point"}
}