{
  "type": "Feature",
  "properties": {
    "iso:country":"ES",
    "sg:address":"Calle de Alvarez, 7",
    "sg:city":"Madrid",
    "sg:orig_category":"Empresas De Carpinter\u00cda De Madera",
    "sg:phone":"+34 913 15 96 66",
    "sg:postcode":"28029",
    "sg:province":"Madrid",
    "wof:name":"De Las Heras Sanz El Clavo S.l.",
    "wof:placetype":"venue"
},
  "geometry": {"coordinates":[-3.6991007328,40.4705162048],"type":"Point"}
}