{
  "type": "Feature",
  "properties": {
    "addr:full":"Av J Ortega Y Gasset (p I El Viso), 333 Malaga M\u00e1laga 29006",
    "addr:housenumber":"333",
    "addr:postcode":"29006",
    "addr:street":"Av J Ortega Y Gasset P;El Viso;Ma\u0301Laga",
    "iso:country":"ES",
    "sg:address":"Av J Ortega Y Gasset (p I El Viso), 333",
    "sg:city":"Malaga",
    "sg:orig_category":"Marketing Telef\u00d3nico",
    "sg:phone":"+34 952 31 34 33",
    "sg:postcode":"29006",
    "sg:province":"M\u00e1laga",
    "wof:name":"Filter Queen Malaga S.c.",
    "wof:placetype":"venue"
},
  "geometry": {"coordinates":[-4.4768719673,36.7074813843],"type":"Point"}
}