{
  "type": "Feature",
  "properties": {
    "addr:full":"Calle de Severo Ochoa, 3 Solana Ciudad Real 13240",
    "addr:housenumber":"3",
    "addr:postcode":"solana;13240",
    "addr:street":"Calle De Severo Ochoa;Real",
    "iso:country":"ES",
    "sg:address":"Calle de Severo Ochoa, 3",
    "sg:city":"Solana",
    "sg:orig_category":"Plomeros",
    "sg:phone":"+34 926 63 40 81",
    "sg:postcode":"13240",
    "sg:province":"Ciudad Real",
    "wof:name":"Hidroman S.l.",
    "wof:placetype":"venue"
},
  "geometry": {"coordinates":[-3.2279450893,38.9436187744],"type":"Point"}
}