{
  "type": "Feature",
  "properties": {
    "iso:country":"ES",
    "sg:address":"Av Europa (d'), 28",
    "sg:city":"Blanes",
    "sg:orig_category":"Materiales De Aislamiento T\u00c9rmico Y Ac\u00dastico",
    "sg:phone":"+34 972 33 76 19",
    "sg:postcode":"17300",
    "sg:province":"Girona",
    "wof:name":"Aillaments Blanes S.l.",
    "wof:placetype":"venue"
},
  "geometry": {"coordinates":[2.7767455578,41.6745147705],"type":"Point"}
}