{
  "type": "Feature",
  "properties": {
    "addr:full":"Calle de Gongora, 10 Cordoba C\u00f3rdoba 14001",
    "addr:housenumber":"10",
    "addr:postcode":"14001",
    "addr:street":"Calle De Gongora;Co\u0301Rdoba",
    "iso:country":"ES",
    "sg:address":"Calle de Gongora, 10",
    "sg:city":"Cordoba",
    "sg:orig_category":"M\u00c9dicos: Cirug\u00cda Pl\u00c1stica, Reconstructiva Y Est\u00c9tica",
    "sg:phone":"+34 957 47 19 89",
    "sg:postcode":"14001",
    "sg:province":"C\u00f3rdoba",
    "wof:name":"Cme.cb",
    "wof:placetype":"venue"
},
  "geometry": {"coordinates":[-4.7817292213,37.8859176636],"type":"Point"}
}