{
  "type": "Feature",
  "properties": {
    "addr:full":"Calle de Angostilla, 1 Sisante Cuenca 16700",
    "addr:housenumber":"1",
    "addr:postcode":"16700",
    "addr:street":"Calle De Angostilla",
    "iso:country":"ES",
    "sg:address":"Calle de Angostilla, 1",
    "sg:city":"Sisante",
    "sg:orig_category":"Ense\u00d1anza, Formaci\u00d3n Profesional: Aprendizaje",
    "sg:phone":"+34 969 38 73 20",
    "sg:postcode":"16700",
    "sg:province":"Cuenca",
    "wof:name":"Servicio De Salud De Castilla La Mancha",
    "wof:placetype":"venue"
},
  "geometry": {"coordinates":[-2.2016220093,39.4081573486],"type":"Point"}
}