{
  "type": "Feature",
  "properties": {
    "addr:full":"Ptda Altabix, 41 Elche Alicante 03291",
    "addr:housenumber":"41",
    "addr:postcode":"03291",
    "addr:street":"Ptda Altabix",
    "iso:country":"ES",
    "sg:address":"Ptda Altabix, 41",
    "sg:city":"Elche",
    "sg:orig_category":"Fabricaci\u00d3n De Telas Y Sedas",
    "sg:phone":"+34 965 42 15 07",
    "sg:postcode":"03291",
    "sg:province":"Alicante",
    "wof:name":"Tocritex S.l.",
    "wof:placetype":"venue"
},
  "geometry": {"coordinates":[-0.6765189767,38.2994346619],"type":"Point"}
}