{
  "type": "Feature",
  "properties": {
    "addr:full":"Cadiz, 19 Cornella Llobregat Barcelona 08940",
    "addr:housenumber":"19",
    "addr:postcode":"08940",
    "addr:street":"Cadiz",
    "iso:country":"ES",
    "sg:address":"Cadiz, 19",
    "sg:city":"Cornella Llobregat",
    "sg:orig_category":"Edici\u00d3n De Diarios, Revistas, Boletines",
    "sg:phone":"+34 934 70 94 99",
    "sg:postcode":"08940",
    "sg:province":"Barcelona",
    "wof:name":"Ediciones Rueda Jm S.l.",
    "wof:placetype":"venue"
},
  "geometry": {"coordinates":[2.0708940029,41.3559417725],"type":"Point"}
}