{
  "type": "Feature",
  "properties": {
    "addr:full":"Avda Rosalia De Castro (de), 57 Santiago De Compostela La Coru\u00f1a 15706",
    "addr:housenumber":"57",
    "addr:postcode":"15706",
    "addr:street":"Avda Rosalia De Castro De;Corun\u0303A",
    "iso:country":"ES",
    "sg:address":"Avda Rosalia De Castro (de), 57",
    "sg:city":"Santiago De Compostela",
    "sg:orig_category":"Psic\u00d3logos",
    "sg:phone":"+34 981 59 23 25",
    "sg:postcode":"15706",
    "sg:province":"La Coru\u00f1a",
    "wof:name":"Fernandez Abeledo Ana Rosa",
    "wof:placetype":"venue"
},
  "geometry": {"coordinates":[-8.5514945984,42.8745307922],"type":"Point"}
}