{
  "type": "Feature",
  "properties": {
    "addr:full":"Calle de Gigantes, 11 Ciudad Rodrigo Salamanca 37500",
    "addr:housenumber":"11",
    "addr:postcode":"37500",
    "addr:street":"Calle De Gigantes",
    "iso:country":"ES",
    "sg:address":"Calle de Gigantes, 11",
    "sg:city":"Ciudad Rodrigo",
    "sg:orig_category":"Papel Pintado (al Por Menor)",
    "sg:phone":"+34 923 46 19 97",
    "sg:postcode":"37500",
    "sg:province":"Salamanca",
    "wof:name":"Montero Manchado Cesareo",
    "wof:placetype":"venue"
},
  "geometry": {"coordinates":[-6.5328989029,40.5967407227],"type":"Point"}
}