{
  "type": "Feature",
  "properties": {
    "addr:full":"Rond Ope (de) (el), 1 Archena Murcia 30600",
    "addr:postcode":"30600",
    "iso:country":"ES",
    "sg:address":"Rond Ope (de) (el), 1",
    "sg:city":"Archena",
    "sg:orig_category":"Quincaller\u00cda (al Por Menor)",
    "sg:phone":"+34 968 67 47 92",
    "sg:postcode":"30600",
    "sg:province":"Murcia",
    "wof:name":"Ferrocano S. L.",
    "wof:placetype":"venue"
},
  "geometry": {"coordinates":[-1.2987289429,38.117401123],"type":"Point"}
}