{
  "type": "Feature",
  "properties": {
    "addr:full":"Calle de Cuenca, 7 Ibi Alicante 03440",
    "addr:housenumber":"7",
    "addr:postcode":"03440",
    "addr:street":"Calle De Cuenca",
    "iso:country":"ES",
    "sg:address":"Calle de Cuenca, 7",
    "sg:city":"Ibi",
    "sg:orig_category":"Quincaller\u00cda (al Por Menor)",
    "sg:phone":"+34 965 55 03 65",
    "sg:postcode":"03440",
    "sg:province":"Alicante",
    "wof:name":"Bru Y Rubio S.l.",
    "wof:placetype":"venue"
},
  "geometry": {"coordinates":[-0.5946205854,38.6123428345],"type":"Point"}
}