{
  "type": "Feature",
  "properties": {
    "addr:full":"Calle de Platino, 37 Madrid Madrid 28021",
    "addr:housenumber":"37",
    "addr:postcode":"madrid;28021",
    "addr:street":"Calle De Platino",
    "iso:country":"ES",
    "sg:address":"Calle de Platino, 37",
    "sg:city":"Madrid",
    "sg:orig_category":"Inmobiliaria (agencias)",
    "sg:phone":"+34 917 98 44 83",
    "sg:postcode":"28021",
    "sg:province":"Madrid",
    "wof:name":"Vamer 99 S.l.",
    "wof:placetype":"venue"
},
  "geometry": {"coordinates":[-3.6883308887,40.3490753174],"type":"Point"}
}