{
  "type": "Feature",
  "properties": {
    "iso:country":"ES",
    "sg:address":"Esglesia, 16",
    "sg:city":"Estartit",
    "sg:orig_category":"Peluquer\u00cdas, Peluquer\u00cda Mixta",
    "sg:phone":"+34 972 75 09 41",
    "sg:postcode":"17258",
    "sg:province":"Girona",
    "wof:name":"Hairbar 2000 S.l.",
    "wof:placetype":"venue"
},
  "geometry": {"coordinates":[3.1986210346,42.0549850464],"type":"Point"}
}