{
  "type": "Feature",
  "properties": {
    "iso:country":"ES",
    "sg:address":"Calle de Lopez De Hoyos, 352",
    "sg:city":"Madrid",
    "sg:orig_category":"Inmobiliaria (agencias)",
    "sg:phone":"+34 914 13 43 19",
    "sg:postcode":"28043",
    "sg:province":"Madrid",
    "wof:name":"Ansatel S.l",
    "wof:placetype":"venue"
},
  "geometry": {"coordinates":[-3.6603546143,40.4580955505],"type":"Point"}
}