{
  "type": "Feature",
  "properties": {
    "addr:full":"Pol Ind El Oliveral, 4 P. I. El Oliveral Valencia 46190",
    "addr:housenumber":"4",
    "addr:postcode":"46190",
    "addr:street":"Oliveral;P. I. El Oliveral",
    "iso:country":"ES",
    "sg:address":"Pol Ind El Oliveral, 4",
    "sg:city":"P. I. El Oliveral",
    "sg:orig_category":"Delegados, Agentes De Tr\u00c1nsito, Auxiliares De Transporte Internacional",
    "sg:phone":"+34 961 66 83 05",
    "sg:postcode":"46190",
    "sg:province":"Valencia",
    "wof:name":"Transportes Salinas S. L.",
    "wof:placetype":"venue"
},
  "geometry": {"coordinates":[-0.5698940158,39.5458450317],"type":"Point"}
}