{
  "type": "Feature",
  "properties": {
    "addr:full":"Plaz Santiago (de), 6 Pinto Madrid 28320",
    "addr:housenumber":"6",
    "addr:postcode":"28320",
    "addr:street":"Plaz Santiago De;Pinto",
    "iso:country":"ES",
    "sg:address":"Plaz Santiago (de), 6",
    "sg:city":"Pinto",
    "sg:orig_category":"Inmobiliaria (agencias)",
    "sg:phone":"+34 916 91 47 52",
    "sg:postcode":"28320",
    "sg:province":"Madrid",
    "wof:name":"Compa\u00d1ia Urbanizadora De Pinto S.a.",
    "wof:placetype":"venue"
},
  "geometry": {"coordinates":[-3.6993589401,40.2411193848],"type":"Point"}
}