{
  "type": "Feature",
  "properties": {
    "addr:full":"Calle de Larga, 75 Jerez De La Frontera C\u00e1diz 11403",
    "addr:housenumber":"75",
    "addr:postcode":"11403",
    "addr:street":"Calle De Larga",
    "iso:country":"ES",
    "sg:address":"Calle de Larga, 75",
    "sg:city":"Jerez De La Frontera",
    "sg:orig_category":"Cajas De Ahorro",
    "sg:phone":"+34 956 34 19 09",
    "sg:postcode":"11403",
    "sg:province":"C\u00e1diz",
    "sg:website":"www.cajasur.es",
    "wof:name":"Caja De Ahorros Y Monte De Piedad De Cordoba",
    "wof:placetype":"venue"
},
  "geometry": {"coordinates":[-6.136742115,36.6855621338],"type":"Point"}
}