{
  "type": "Feature",
  "properties": {
    "addr:full":"Carrer de Diputacio, 154 Barcelona Barcelona 08011",
    "addr:housenumber":"154",
    "addr:postcode":"08011",
    "addr:street":"Carrer De Diputacio",
    "iso:country":"ES",
    "sg:address":"Carrer de Diputacio, 154",
    "sg:city":"Barcelona",
    "sg:orig_category":"Inform\u00c1tica: Consultores",
    "sg:phone":"+34 934 51 40 46",
    "sg:postcode":"08011",
    "sg:province":"Barcelona",
    "wof:name":"Opensystemsconsultings.l.",
    "wof:placetype":"venue"
},
  "geometry": {"coordinates":[2.1578199863,41.383266449],"type":"Point"}
}