{
  "type": "Feature",
  "properties": {
    "addr:full":"Calle de Herman Hesse, 33 Malaga M\u00e1laga 29004",
    "addr:housenumber":"33",
    "addr:postcode":"29004",
    "addr:street":"Calle De Herman Hesse;Ma\u0301Laga",
    "iso:country":"ES",
    "sg:address":"Calle de Herman Hesse, 33",
    "sg:city":"Malaga",
    "sg:orig_category":"Dorados, Plater\u00cda (orfebrer\u00cda)",
    "sg:phone":"+34 952 24 15 92",
    "sg:postcode":"29004",
    "sg:province":"M\u00e1laga",
    "wof:name":"Plata Y Decoracion S.l.",
    "wof:placetype":"venue"
},
  "geometry": {"coordinates":[-4.4655861855,36.6939849854],"type":"Point"}
}