{
  "type": "Feature",
  "properties": {
    "iso:country":"ES",
    "sg:address":"Plaz Constitucion De (la), 2",
    "sg:city":"Calahorra",
    "sg:orig_category":"Carnicer\u00cdas, Carnicer\u00cdas",
    "sg:phone":"+34 941 14 71 93",
    "sg:postcode":"26500",
    "sg:province":"La Rioja",
    "wof:name":"Saenz Munilla Cayo",
    "wof:placetype":"venue"
},
  "geometry": {"coordinates":[-1.9670690298,42.3058128357],"type":"Point"}
}