{
  "type": "Feature",
  "properties": {
    "iso:country":"ES",
    "sg:address":"Trav De Gracia, 341",
    "sg:city":"Barcelona",
    "sg:orig_category":"Panader\u00cdas, Panader\u00cdas",
    "sg:phone":"+34 934 59 25 96",
    "sg:postcode":"08025",
    "sg:province":"Barcelona",
    "wof:name":"L'avi Manel Artesans Desde 1930 S.l.",
    "wof:placetype":"venue"
},
  "geometry": {"coordinates":[2.1672930717,41.4074668884],"type":"Point"}
}