{
  "type": "Feature",
  "properties": {
    "iso:country":"ES",
    "sg:address":"Calle de Doctor Mara\u00d1on, 2",
    "sg:city":"Petrer",
    "sg:orig_category":"Inmobiliaria (agencias)",
    "sg:phone":"+34 965 37 05 30",
    "sg:postcode":"03610",
    "sg:province":"Alicante",
    "wof:name":"Reig Difusion S.l.",
    "wof:placetype":"venue"
},
  "geometry": {"coordinates":[-0.7739015818,38.4816398621],"type":"Point"}
}