{
  "type": "Feature",
  "properties": {
    "iso:country":"ES",
    "sg:address":"Unibertsitate Etorbidea, S/n",
    "sg:city":"O\u00f1ati",
    "sg:orig_category":"Iglesia Cat\u00d3lica",
    "sg:phone":"+34 943 78 18 98",
    "sg:postcode":"20560",
    "sg:province":"Guip\u00f9zcoa",
    "wof:name":"Mikel Aozaraza Ikastetxea",
    "wof:placetype":"venue"
},
  "geometry": {"coordinates":[-2.4161419868,43.034072876],"type":"Point"}
}