{
  "type": "Feature",
  "properties": {
    "addr:full":"Rua Castelao (de), 28 Carballi\u00f1o Ourense 32500",
    "addr:housenumber":"28",
    "addr:postcode":"32500",
    "addr:street":"Rua Castelao De",
    "iso:country":"ES",
    "sg:address":"Rua Castelao (de), 28",
    "sg:city":"Carballi\u00f1o",
    "sg:orig_category":"Mec\u00c1nico Del Autom\u00d3vil",
    "sg:phone":"+34 988 27 05 12",
    "sg:postcode":"32500",
    "sg:province":"Ourense",
    "wof:name":"Albarado Fernandez Alberto",
    "wof:placetype":"venue"
},
  "geometry": {"coordinates":[-8.0741491318,42.4347496033],"type":"Point"}
}