{
  "type": "Feature",
  "properties": {
    "addr:full":"Carrer de Sant Artur (de), 20 Vilassar De Mar Barcelona 08340",
    "addr:housenumber":"20",
    "addr:postcode":"08340",
    "addr:street":"Carrer De Sant Artur De",
    "iso:country":"ES",
    "sg:address":"Carrer de Sant Artur (de), 20",
    "sg:city":"Vilassar De Mar",
    "sg:orig_category":"Ense\u00d1anza Variada",
    "sg:phone":"+34 937 59 81 36",
    "sg:postcode":"08340",
    "sg:province":"Barcelona",
    "wof:name":"Martinez Vallejo Cristina",
    "wof:placetype":"venue"
},
  "geometry": {"coordinates":[2.3866159916,41.5020179749],"type":"Point"}
}