{
  "type": "Feature",
  "properties": {
    "addr:full":"Paraje Isetoki, S/n Lekunberri Navarra 31870",
    "addr:housenumber":"s / n",
    "addr:postcode":"31870",
    "addr:street":"Isetoki",
    "iso:country":"ES",
    "sg:address":"Paraje Isetoki, S/n",
    "sg:city":"Lekunberri",
    "sg:orig_category":"Poller\u00cda Y Caza (al Por Menor)",
    "sg:phone":"+34 948 50 41 09",
    "sg:postcode":"31870",
    "sg:province":"Navarra",
    "wof:name":"Ugartemendia Ochandorena Jose Leandro",
    "wof:placetype":"venue"
},
  "geometry": {"coordinates":[-1.965190053,42.9467697144],"type":"Point"}
}