{
  "type": "Feature",
  "properties": {
    "addr:full":"Calle de Ricardo Ibarreche, 1 Arrigorriaga Vizcaya 48480",
    "addr:housenumber":"1",
    "addr:postcode":"48480",
    "addr:street":"Calle De Ricardo Ibarreche",
    "iso:country":"ES",
    "sg:address":"Calle de Ricardo Ibarreche, 1",
    "sg:city":"Arrigorriaga",
    "sg:orig_category":"Promotores Constructores",
    "sg:phone":"+34 946 71 34 12",
    "sg:postcode":"48480",
    "sg:province":"Vizcaya",
    "wof:name":"Lami\u00f1e Erreketa S.a.",
    "wof:placetype":"venue"
},
  "geometry": {"coordinates":[-2.8875434399,43.20652771],"type":"Point"}
}