{
  "type": "Feature",
  "properties": {
    "iso:country":"ES",
    "sg:address":"Avda Canovas Del Castillo, 23",
    "sg:city":"Marbella",
    "sg:orig_category":"Guarder\u00cdas",
    "sg:phone":"+34 952 77 85 60",
    "sg:postcode":"29600",
    "sg:province":"M\u00e1laga",
    "wof:name":"Gomez Gonzalez Teresa",
    "wof:placetype":"venue"
},
  "geometry": {"coordinates":[-4.8974480629,36.513835907],"type":"Point"}
}