{
  "type": "Feature",
  "properties": {
    "addr:full":"De Lerida Colombia, 16 Lleida Lleida 25005",
    "addr:housenumber":"16",
    "addr:postcode":"25005",
    "addr:street":"Colombia",
    "iso:country":"ES",
    "sg:address":"De Lerida Colombia, 16",
    "sg:city":"Lleida",
    "sg:orig_category":"Centros Comerciales Y Grandes Tiendas",
    "sg:phone":"+34 973 22 82 29",
    "sg:postcode":"25005",
    "sg:province":"Lleida",
    "wof:name":"Morales Barbero Maria Nieves",
    "wof:placetype":"venue"
},
  "geometry": {"coordinates":[0.6264280081,41.6282272339],"type":"Point"}
}