{
  "type": "Feature",
  "properties": {
    "addr:full":"Carr Aurora Bertrana I Salazar, 23 Vila-roja Girona 17004",
    "addr:housenumber":"23",
    "addr:postcode":"17004",
    "addr:street":"Carr Aurora Bertrana I Salazar",
    "iso:country":"ES",
    "sg:address":"Carr Aurora Bertrana I Salazar, 23",
    "sg:city":"Vila-roja",
    "sg:orig_category":"Periodistas Profesionales",
    "sg:phone":"+34 972 20 72 37",
    "sg:postcode":"17004",
    "sg:province":"Girona",
    "wof:name":"Vinyals Gamero Gema",
    "wof:placetype":"venue"
},
  "geometry": {"coordinates":[2.8422400951,41.9735031128],"type":"Point"}
}