{
  "type": "Feature",
  "properties": {
    "addr:full":"Calle de Concha General, 8 Bilbao Vizcaya 48008",
    "addr:housenumber":"8",
    "addr:postcode":"48008",
    "addr:street":"Calle De Concha General",
    "iso:country":"ES",
    "sg:address":"Calle de Concha General, 8",
    "sg:city":"Bilbao",
    "sg:orig_category":"Cajas De Ahorro",
    "sg:phone":"+34 944 21 41 13",
    "sg:postcode":"48008",
    "sg:province":"Vizcaya",
    "wof:name":"Caja Laboral Popular",
    "wof:placetype":"venue"
},
  "geometry": {"coordinates":[-2.9319541454,43.2600097656],"type":"Point"}
}