{
  "type": "Feature",
  "properties": {
    "iso:country":"ES",
    "sg:address":"Cno Los Parrales, 121",
    "sg:city":"Aguadulce",
    "sg:orig_category":"Talleres: Ropa A Medida",
    "sg:phone":"+34 950 34 44 78",
    "sg:postcode":"04720",
    "sg:province":"Almer\u00eda",
    "wof:name":"Seisdedos  Sergio Esteban",
    "wof:placetype":"venue"
},
  "geometry": {"coordinates":[-2.5974500179,36.801410675],"type":"Point"}
}