{
  "type": "Feature",
  "properties": {
    "addr:full":"Calle de Hermano Lujan, 1 Cordoba C\u00f3rdoba 14007",
    "addr:housenumber":"1",
    "addr:postcode":"14007",
    "addr:street":"Calle De Hermano Lujan;Co\u0301Rdoba",
    "iso:country":"ES",
    "sg:address":"Calle de Hermano Lujan, 1",
    "sg:city":"Cordoba",
    "sg:orig_category":"Panader\u00cdas, Panader\u00cdas",
    "sg:phone":"+34 957 25 29 73",
    "sg:postcode":"14007",
    "sg:province":"C\u00f3rdoba",
    "wof:name":"Escot Maqueda Cristobal",
    "wof:placetype":"venue"
},
  "geometry": {"coordinates":[-4.7661142349,37.8936767578],"type":"Point"}
}