{
  "type": "Feature",
  "properties": {
    "addr:full":"Calle de Azacayas, 11 Granada Granada 18010",
    "addr:housenumber":"11",
    "addr:postcode":"18010",
    "addr:street":"Calle De Azacayas",
    "iso:country":"ES",
    "sg:address":"Calle de Azacayas, 11",
    "sg:city":"Granada",
    "sg:orig_category":"Ebanister\u00cda",
    "sg:phone":"+34 958 80 08 27",
    "sg:postcode":"18010",
    "sg:province":"Granada",
    "wof:name":"Aguilar Salazar Rafael",
    "wof:placetype":"venue"
},
  "geometry": {"coordinates":[-3.5994346142,37.1800041199],"type":"Point"}
}