{
  "type": "Feature",
  "properties": {
    "iso:country":"ES",
    "sg:address":"Calle de Augusto, 42",
    "sg:city":"Nerva",
    "sg:orig_category":"Molduras, Junquillos, Listones Y Molduras Perforadas",
    "sg:phone":"+34 959 58 23 60",
    "sg:postcode":"21670",
    "sg:province":"Huelva",
    "wof:name":"Henares Trujillo Juan",
    "wof:placetype":"venue"
},
  "geometry": {"coordinates":[-6.5467953682,37.6964416504],"type":"Point"}
}