{
  "type": "Feature",
  "properties": {
    "iso:country":"ES",
    "sg:address":"Gandara (guillarei), S/n",
    "sg:city":"Gandara",
    "sg:orig_category":"M\u00c1rmoles, Granitos Y Piedras Naturales",
    "sg:phone":"+34 986 60 01 91",
    "sg:postcode":"36720",
    "sg:province":"Pontevedra",
    "wof:name":"Granitos Rosada S.l.",
    "wof:placetype":"venue"
},
  "geometry": {"coordinates":[-8.7686672211,42.3305892944],"type":"Point"}
}