{
  "type": "Feature",
  "properties": {
    "iso:country":"ES",
    "sg:address":"Carr De Josep Melcior Gomis, 1",
    "sg:city":"Ontinyent",
    "sg:orig_category":"\u00d3ptica: Instrumentos (fabricaci\u00d3n)",
    "sg:phone":"+34 962 91 08 91",
    "sg:postcode":"46870",
    "sg:province":"Valencia",
    "wof:name":"Borja Asociados S.l.",
    "wof:placetype":"venue"
},
  "geometry": {"coordinates":[-0.6030989885,38.8258895874],"type":"Point"}
}