{
  "type": "Feature",
  "properties": {
    "addr:full":"El Campo, 1 Robledo De La Valdoncina Le\u00f3n 24391",
    "addr:housenumber":"1",
    "addr:postcode":"24391",
    "addr:street":"El Campo;Leo\u0301N",
    "iso:country":"ES",
    "sg:address":"El Campo, 1",
    "sg:city":"Robledo De La Valdoncina",
    "sg:orig_category":"Piedra Natural",
    "sg:phone":"+34 987 30 36 04",
    "sg:postcode":"24391",
    "sg:province":"Le\u00f3n",
    "wof:name":"Lucena Barros Dorinda",
    "wof:placetype":"venue"
},
  "geometry": {"coordinates":[-5.682929039,42.5689697266],"type":"Point"}
}