{
  "type": "Feature",
  "properties": {
    "addr:full":"Avda Principes De Espa\u00d1a (de Los), 41 Coslada Madrid 28820",
    "addr:housenumber":"41",
    "addr:postcode":"28820",
    "addr:street":"Avda Principes De Espan\u0303A De Los",
    "iso:country":"ES",
    "sg:address":"Avda Principes De Espa\u00d1a (de Los), 41",
    "sg:city":"Coslada",
    "sg:orig_category":"M\u00c9dicos: Foniatr\u00cda Y Logopedia",
    "sg:phone":"+34 916 72 56 82",
    "sg:postcode":"28820",
    "sg:province":"Madrid",
    "wof:name":"Bartolome Garcia Angela",
    "wof:placetype":"venue"
},
  "geometry": {"coordinates":[-3.5451309681,40.4255867004],"type":"Point"}
}