{
  "type": "Feature",
  "properties": {
    "addr:full":"Avda Camelias, 45 Vigo Pontevedra 36211",
    "addr:housenumber":"45",
    "addr:postcode":"36211",
    "addr:street":"Avda Camelias",
    "iso:country":"ES",
    "sg:address":"Avda Camelias, 45",
    "sg:city":"Vigo",
    "sg:orig_category":"Supermercados Y Hipermercados",
    "sg:phone":"+34 986 41 74 67",
    "sg:postcode":"36211",
    "sg:province":"Pontevedra",
    "wof:name":"Distribuciones Froiz S.a.",
    "wof:placetype":"venue"
},
  "geometry": {"coordinates":[-8.7298688889,42.2304077148],"type":"Point"}
}