{
  "type": "Feature",
  "properties": {
    "addr:full":"Poligono Industrial, S/n Ascoy Murcia 30530",
    "addr:postcode":"30530",
    "addr:street":"Industrial S / N",
    "iso:country":"ES",
    "sg:address":"Poligono Industrial, S/n",
    "sg:city":"Ascoy",
    "sg:orig_category":"Empresas De Hormig\u00d3n, Hormig\u00d3n Armado Y Pretensado",
    "sg:phone":"+34 968 76 09 97",
    "sg:postcode":"30530",
    "sg:province":"Murcia",
    "wof:name":"Prefabricados De Cieza S.l.",
    "wof:placetype":"venue"
},
  "geometry": {"coordinates":[-1.4241739511,38.2379302979],"type":"Point"}
}