{
  "type": "Feature",
  "properties": {
    "iso:country":"ES",
    "sg:address":"Calle de Albareda, 5",
    "sg:city":"Palmas De Gran Canaria",
    "sg:orig_category":"Telas Para Tapizar, Cortinas, Pasamaner\u00cda (fabricaci\u00d3n, Al Por Mayor)",
    "sg:phone":"+34 928 22 61 29",
    "sg:postcode":"35007",
    "sg:province":"Las Palmas",
    "wof:name":"Ganwant Tulsi Kishan",
    "wof:placetype":"venue"
},
  "geometry": {"coordinates":[-15.4308128357,28.1416168213],"type":"Point"}
}