{
  "type": "Feature",
  "properties": {
    "addr:full":"Calle de Mayor, 27 Belver De Cinca Huesca 22533",
    "addr:housenumber":"27",
    "addr:postcode":"22533",
    "addr:street":"Calle De Mayor",
    "iso:country":"ES",
    "sg:address":"Calle de Mayor, 27",
    "sg:city":"Belver De Cinca",
    "sg:orig_category":"Reposter\u00cdas",
    "sg:phone":"+34 974 45 63 08",
    "sg:postcode":"22533",
    "sg:province":"Huesca",
    "wof:name":"Callen Lloret Luis",
    "wof:placetype":"venue"
},
  "geometry": {"coordinates":[0.1789209992,41.688747406],"type":"Point"}
}