{
  "type": "Feature",
  "properties": {
    "iso:country":"ES",
    "sg:address":"Calle de Lepanto, 60",
    "sg:city":"Castellon",
    "sg:orig_category":"Peluqueros: De Se\u00d1oras",
    "sg:phone":"+34 964 25 18 65",
    "sg:postcode":"12006",
    "sg:province":"Castell\u00f3n",
    "wof:name":"Garcia Fabra Maria Celia",
    "wof:placetype":"venue"
},
  "geometry": {"coordinates":[-0.1292939931,40.0168533325],"type":"Point"}
}