{
  "type": "Feature",
  "properties": {
    "addr:full":"Ctra Denia, 23 Pego Alicante 03780",
    "addr:housenumber":"23",
    "addr:postcode":"03780",
    "addr:street":"Ctra Denia",
    "iso:country":"ES",
    "sg:address":"Ctra Denia, 23",
    "sg:city":"Pego",
    "sg:orig_category":"Empresas De Carpinter\u00cda Met\u00c1lica",
    "sg:phone":"+34 965 57 11 69",
    "sg:postcode":"03780",
    "sg:province":"Alicante",
    "wof:name":"Oltra Sendra Fernando",
    "wof:placetype":"venue"
},
  "geometry": {"coordinates":[-0.1142570004,38.8430023193],"type":"Point"}
}