{
  "type": "Feature",
  "properties": {
    "iso:country":"ES",
    "sg:address":"Pg Costera (la), 21",
    "sg:city":"Monasterios",
    "sg:orig_category":"Puertas Y Portales",
    "sg:phone":"+34 961 40 55 35",
    "sg:postcode":"46530",
    "sg:province":"Valencia",
    "wof:name":"Borras Cabo Jose",
    "wof:placetype":"venue"
},
  "geometry": {"coordinates":[-0.3008790016,39.6156044006],"type":"Point"}
}