{
  "type": "Feature",
  "properties": {
    "addr:full":"C/ Alvarez De Castro, 126 Banyoles Girona 17820",
    "addr:housenumber":"126",
    "addr:postcode":"17820",
    "addr:street":"C / Alvarez De Castro",
    "iso:country":"ES",
    "sg:address":"C/ Alvarez De Castro, 126",
    "sg:city":"Banyoles",
    "sg:orig_category":"Masajes",
    "sg:phone":"+34 972 57 47 89",
    "sg:postcode":"17820",
    "sg:province":"Girona",
    "wof:name":"Sala Ruvirola Gaspar",
    "wof:placetype":"venue"
},
  "geometry": {"coordinates":[2.768709898,42.1149291992],"type":"Point"}
}