{
  "type": "Feature",
  "properties": {
    "iso:country":"ES",
    "sg:address":"Avgd Marques De Montroig, 80",
    "sg:city":"Badalona",
    "sg:orig_category":"Agentes, Concesionarios Y Sucursales De Veh\u00cdculos",
    "sg:phone":"+34 933 99 35 80",
    "sg:postcode":"08912",
    "sg:province":"Barcelona",
    "wof:name":"Villanueva Moreno Gabriel",
    "wof:placetype":"venue"
},
  "geometry": {"coordinates":[2.2346858978,41.4414558411],"type":"Point"}
}