{
  "type": "Feature",
  "properties": {
    "addr:full":"Calle de Ramon Diaz, 7 Monterroso Lugo 27560",
    "addr:housenumber":"7",
    "addr:postcode":"27560",
    "addr:street":"Calle De Ramon Diaz",
    "iso:country":"ES",
    "sg:address":"Calle de Ramon Diaz, 7",
    "sg:city":"Monterroso",
    "sg:orig_category":"Iglesia Cat\u00d3lica",
    "sg:phone":"+34 982 37 71 81",
    "sg:postcode":"27560",
    "sg:province":"Lugo",
    "wof:name":"Diocesis De Lugo",
    "wof:placetype":"venue"
},
  "geometry": {"coordinates":[-7.8364238739,42.7928886414],"type":"Point"}
}