{
  "type": "Feature",
  "properties": {
    "iso:country":"ES",
    "sg:address":"Calle de Gallo, 9",
    "sg:city":"Valladolid",
    "sg:orig_category":"Limpieza Con Chorro De Arena Y Con Granalla, Pulido",
    "sg:phone":"+34 983 29 83 02",
    "sg:postcode":"47012",
    "sg:province":"Valladolid",
    "wof:name":"Milan Garcia Jose Luis",
    "wof:placetype":"venue"
},
  "geometry": {"coordinates":[-4.7088990211,41.646282196],"type":"Point"}
}