{
  "type": "Feature",
  "properties": {
    "iso:country":"ES",
    "sg:address":"Calle de Agastia, 48",
    "sg:city":"Madrid",
    "sg:orig_category":"Caf\u00c9s, Bares, Cervecer\u00cdas",
    "sg:phone":"+34 913 77 17 47",
    "sg:postcode":"28027",
    "sg:province":"Madrid",
    "wof:name":"31 De Enero S.l.",
    "wof:placetype":"venue"
},
  "geometry": {"coordinates":[-3.651659,40.446083],"type":"Point"}
}