{
  "type": "Feature",
  "properties": {
    "addr:full":"Calle de Cervantes, 6 Rute C\u00f3rdoba 14960",
    "addr:housenumber":"6",
    "addr:postcode":"14960",
    "addr:street":"Calle De Cervantes;Co\u0301Rdoba",
    "iso:country":"ES",
    "sg:address":"Calle de Cervantes, 6",
    "sg:city":"Rute",
    "sg:orig_category":"Aceites Y Grasas Alimentarias (fabricaci\u00d3n, Al Por Mayor)",
    "sg:phone":"+34 957 53 81 72",
    "sg:postcode":"14960",
    "sg:province":"C\u00f3rdoba",
    "wof:name":"Explotaciones Agricolas Aguadulce S.l.",
    "wof:placetype":"venue"
},
  "geometry": {"coordinates":[-4.3690772057,37.3243026733],"type":"Point"}
}