{
  "type": "Feature",
  "properties": {
    "iso:country":"ES",
    "sg:address":"Avda Castilla, 18",
    "sg:city":"Guadalajara",
    "sg:orig_category":"Art\u00cdculos De Regalo (al Por Menor)",
    "sg:phone":"+34 949 22 59 61",
    "sg:postcode":"19002",
    "sg:province":"Guadalajara",
    "wof:name":"Pescador Mesonero Maria Luisa",
    "wof:placetype":"venue"
},
  "geometry": {"coordinates":[-3.1644580364,40.6253471375],"type":"Point"}
}