{
  "type": "Feature",
  "properties": {
    "addr:full":"Calle de San Adrian De Sasabe, 8 Zaragoza Zaragoza 50002",
    "addr:housenumber":"8",
    "addr:postcode":"50002",
    "addr:street":"Calle De San Adrian De Sasabe",
    "iso:country":"ES",
    "sg:address":"Calle de San Adrian De Sasabe, 8",
    "sg:city":"Zaragoza",
    "sg:orig_category":"Carpinteros",
    "sg:phone":"+34 976 49 47 40",
    "sg:postcode":"50002",
    "sg:province":"Zaragoza",
    "wof:name":"Navarro Gonzalez Maria Reyes",
    "wof:placetype":"venue"
},
  "geometry": {"coordinates":[-0.8596889973,41.6420288086],"type":"Point"}
}