{
  "type": "Feature",
  "properties": {
    "iso:country":"ES",
    "sg:address":"Avda Isora, 91",
    "sg:city":"Guia Isora",
    "sg:orig_category":"\u00d3ptica: Instrumentos (fabricaci\u00d3n)",
    "sg:phone":"+34 922 85 12 79",
    "sg:postcode":"38680",
    "sg:province":"Santa Cruz De Tenerife",
    "wof:name":"Fustel Guillen Matias",
    "wof:placetype":"venue"
},
  "geometry": {"coordinates":[-16.7819900513,28.2125034332],"type":"Point"}
}