{
  "type": "Feature",
  "properties": {
    "iso:country":"ES",
    "sg:address":"Calle de Ezequiel Solana, 56",
    "sg:city":"Madrid",
    "sg:orig_category":"Molduras, Junquillos, Listones Y Molduras Perforadas",
    "sg:phone":"+34 913 77 26 93",
    "sg:postcode":"28017",
    "sg:province":"Madrid",
    "wof:name":"Prieto Barriga Mariana",
    "wof:placetype":"venue"
},
  "geometry": {"coordinates":[-3.6446518898,40.4302101135],"type":"Point"}
}