{
  "type": "Feature",
  "properties": {
    "iso:country":"ES",
    "sg:address":"Calle de Untzillatx Kalea, 13",
    "sg:city":"Durango",
    "sg:orig_category":"Alquiler De Veh\u00cdculos: Turismos Y Utilitarios",
    "sg:phone":"+34 946 81 20 62",
    "sg:postcode":"48200",
    "sg:province":"Vizcaya",
    "wof:name":"Durango Carr S.l.",
    "wof:placetype":"venue"
},
  "geometry": {"coordinates":[-2.6117420197,43.194644928],"type":"Point"}
}