{
  "type": "Feature",
  "properties": {
    "iso:country":"ES",
    "sg:address":"Calle de Alberca, 57",
    "sg:city":"Salamanca",
    "sg:orig_category":"Autob\u00das (explotaci\u00d3n Y Servicios De)",
    "sg:phone":"+34 923 23 99 81",
    "sg:postcode":"37007",
    "sg:province":"Salamanca",
    "wof:name":"Huerta Nieto Jose",
    "wof:placetype":"venue"
},
  "geometry": {"coordinates":[-5.6749978065,40.9692878723],"type":"Point"}
}