{
  "type": "Feature",
  "properties": {
    "iso:country":"ES",
    "sg:address":"Rua Peregrina, 13",
    "sg:city":"Estrada",
    "sg:orig_category":"Alquiler De V\u00cddeo",
    "sg:phone":"+34 986 57 52 08",
    "sg:postcode":"36680",
    "sg:province":"Pontevedra",
    "wof:name":"Mouri\u00f1o Couto Elena",
    "wof:placetype":"venue"
},
  "geometry": {"coordinates":[-8.491812706,42.6896972656],"type":"Point"}
}