{
  "type": "Feature",
  "properties": {
    "iso:country":"ES",
    "sg:address":"Carrer de Palomar, 62",
    "sg:city":"Barcelona",
    "sg:orig_category":"Puertas Y Portales",
    "sg:phone":"+34 933 46 42 71",
    "sg:postcode":"08030",
    "sg:province":"Barcelona",
    "wof:name":"Tellez Orobitg Jose",
    "wof:placetype":"venue"
},
  "geometry": {"coordinates":[2.1917068958,41.4421081543],"type":"Point"}
}