{
  "type": "Feature",
  "properties": {
    "addr:full":"Calle de Vicente Aleixandre, 25 Burgos Burgos 09006",
    "addr:housenumber":"25",
    "addr:postcode":"09006",
    "addr:street":"Calle De Vicente Aleixandre",
    "iso:country":"ES",
    "sg:address":"Calle de Vicente Aleixandre, 25",
    "sg:city":"Burgos",
    "sg:orig_category":"Oficinas De Estudios De Dise\u00d1o Industrial",
    "sg:phone":"+34 947 24 52 73",
    "sg:postcode":"09006",
    "sg:province":"Burgos",
    "wof:name":"Cromo Publicidad S.l.",
    "wof:placetype":"venue"
},
  "geometry": {"coordinates":[-3.678123951,42.3556785583],"type":"Point"}
}