{
  "type": "Feature",
  "properties": {
    "addr:full":"Calle de Laureano Salgado, 3 Caldas De Reis Pontevedra 36650",
    "addr:housenumber":"3",
    "addr:postcode":"36650",
    "addr:street":"Calle De Laureano Salgado",
    "iso:country":"ES",
    "sg:address":"Calle de Laureano Salgado, 3",
    "sg:city":"Caldas De Reis",
    "sg:orig_category":"Caf\u00c9s, Bares, Cervecer\u00cdas",
    "sg:phone":"+34 986 54 12 06",
    "sg:postcode":"36650",
    "sg:province":"Pontevedra",
    "wof:name":"Galtelcom",
    "wof:placetype":"venue"
},
  "geometry": {"coordinates":[-8.6424341202,42.6034545898],"type":"Point"}
}