{
  "type": "Feature",
  "properties": {
    "iso:country":"ES",
    "sg:address":"Ctra Sevilla, 1",
    "sg:city":"Badajoz",
    "sg:orig_category":"Negocio De Materiales De Construcci\u00d3n",
    "sg:phone":"+34 924 20 72 72",
    "sg:postcode":"06009",
    "sg:province":"Badajoz",
    "wof:name":"Portero Escobar Exposiciones S.l.",
    "wof:placetype":"venue"
},
  "geometry": {"coordinates":[-6.9603190422,38.8727493286],"type":"Point"}
}