{
  "type": "Feature",
  "properties": {
    "iso:country":"ES",
    "sg:address":"D, 25",
    "sg:city":"Santiago De Compostela",
    "sg:orig_category":"Venta, Localizaci\u00d3n, Reparaci\u00d3n De Material E Instrumental M\u00c9dico",
    "sg:phone":"+34 981 58 07 70",
    "sg:postcode":"15890",
    "sg:province":"La Coru\u00f1a",
    "wof:name":"Gallesteril S.l.",
    "wof:placetype":"venue"
},
  "geometry": {"coordinates":[-8.5497770309,42.8711967468],"type":"Point"}
}