{
  "type": "Feature",
  "properties": {
    "addr:full":"Calle de Tomas Breton, 7 Estacion Madrid 28400",
    "addr:housenumber":"7 estacion",
    "addr:postcode":"28400",
    "addr:street":"Calle De Tomas Breton",
    "iso:country":"ES",
    "sg:address":"Calle de Tomas Breton, 7",
    "sg:city":"Estacion",
    "sg:orig_category":"Peluqueros: De Se\u00d1oras",
    "sg:phone":"+34 918 50 18 07",
    "sg:postcode":"28400",
    "sg:province":"Madrid",
    "wof:name":"Sevillano Castro Dolores",
    "wof:placetype":"venue"
},
  "geometry": {"coordinates":[-4.0188651085,40.6325187683],"type":"Point"}
}