{
  "type": "Feature",
  "properties": {
    "addr:full":"Calle de Reina Fabiola, 12 Zaragoza Zaragoza 50008",
    "addr:housenumber":"12",
    "addr:postcode":"50008",
    "addr:street":"Calle De Reina Fabiola",
    "iso:country":"ES",
    "sg:address":"Calle de Reina Fabiola, 12",
    "sg:city":"Zaragoza",
    "sg:orig_category":"Ropa Para Se\u00d1oras Y Caballeros (al Por Menor)",
    "sg:phone":"+34 976 41 75 97",
    "sg:postcode":"50008",
    "sg:province":"Zaragoza",
    "wof:name":"Muro Y Abad S. C.",
    "wof:placetype":"venue"
},
  "geometry": {"coordinates":[-0.8734430075,41.6458778381],"type":"Point"}
}