{
  "type": "Feature",
  "properties": {
    "iso:country":"ES",
    "sg:address":"Calle de Angel Ganivet, 2",
    "sg:city":"Malaga",
    "sg:orig_category":"Formaci\u00d3n Continuada (variada)",
    "sg:phone":"+34 952 21 19 46",
    "sg:postcode":"29005",
    "sg:province":"M\u00e1laga",
    "wof:name":"Huerga Garcia Juan Carlos De La",
    "wof:placetype":"venue"
},
  "geometry": {"coordinates":[-4.4224267006,36.7191390991],"type":"Point"}
}