{
  "type": "Feature",
  "properties": {
    "addr:full":"Avda Juan Carlos I, S/n Santiago Murcia 30800",
    "addr:housenumber":"s / n",
    "addr:postcode":"30800",
    "addr:street":"Avda Juan Carlos I",
    "iso:country":"ES",
    "sg:address":"Avda Juan Carlos I, S/n",
    "sg:city":"Santiago",
    "sg:orig_category":"Farmacias",
    "sg:phone":"+34 968 46 61 06",
    "sg:postcode":"30800",
    "sg:province":"Murcia",
    "wof:name":"Casti\u00f1eiras Bueno Victoria",
    "wof:placetype":"venue"
},
  "geometry": {"coordinates":[-1.6905640364,37.680557251],"type":"Point"}
}