{
  "type": "Feature",
  "properties": {
    "addr:full":"Los Silos, 10 Campillo Llerena Badajoz 06443",
    "addr:housenumber":"10",
    "addr:postcode":"06443",
    "addr:street":"Los Silos",
    "iso:country":"ES",
    "sg:address":"Los Silos, 10",
    "sg:city":"Campillo Llerena",
    "sg:orig_category":"Discotecas Y Salas De Baile",
    "sg:phone":"+34 924 77 01 92",
    "sg:postcode":"06443",
    "sg:province":"Badajoz",
    "wof:name":"Jimenez Moreno Joaquina",
    "wof:placetype":"venue"
},
  "geometry": {"coordinates":[-5.8318376541,38.4998168945],"type":"Point"}
}