{
  "type": "Feature",
  "properties": {
    "iso:country":"ES",
    "sg:address":"Calle de Don Ramon De La Cruz, 36",
    "sg:city":"Madrid",
    "sg:orig_category":"Arquitectos",
    "sg:phone":"+34 915 75 50 59",
    "sg:postcode":"28001",
    "sg:province":"Madrid",
    "wof:name":"Rio Nison S.l",
    "wof:placetype":"venue"
},
  "geometry": {"coordinates":[-3.681987524,40.4290084839],"type":"Point"}
}