{
  "type": "Feature",
  "properties": {
    "iso:country":"ES",
    "sg:address":"Calle de Parroco Segundo Vega, 203",
    "sg:city":"Palmas De Gran Canaria",
    "sg:orig_category":"Comercio De Piezas De Recambio Y De Accesorios De Veh\u00cdculos, Veh\u00cdculos Industriales",
    "sg:phone":"+34 928 33 54 91",
    "sg:postcode":"35015",
    "sg:province":"Las Palmas",
    "wof:name":"Metaboch S.l.",
    "wof:placetype":"venue"
},
  "geometry": {"coordinates":[-15.4300088882,28.0951595306],"type":"Point"}
}