{
  "type": "Feature",
  "properties": {
    "addr:full":"Calle de Capitan Almeida, 10 Oviedo Asturias 33009",
    "addr:housenumber":"10",
    "addr:postcode":"33009",
    "addr:street":"Calle De Capitan Almeida",
    "iso:country":"ES",
    "sg:address":"Calle de Capitan Almeida, 10",
    "sg:city":"Oviedo",
    "sg:orig_category":"Bisuter\u00cda, Joyer\u00cda, Relojer\u00cda (al Por Menor)",
    "sg:phone":"+34 985 22 25 65",
    "sg:postcode":"33009",
    "sg:province":"Asturias",
    "wof:name":"Martos Joyeros C.b.",
    "wof:placetype":"venue"
},
  "geometry": {"coordinates":[-5.84141922,43.35754776],"type":"Point"}
}