{
  "type": "Feature",
  "properties": {
    "iso:country":"ES",
    "sg:address":"Avda Cadiz (de), 68",
    "sg:city":"Cordoba",
    "sg:orig_category":"Agentes, Concesionarios Y Sucursales De Veh\u00cdculos",
    "sg:phone":"+34 957 29 21 22",
    "sg:postcode":"14013",
    "sg:province":"C\u00f3rdoba",
    "wof:name":"Hispanomocion S.a",
    "wof:placetype":"venue"
},
  "geometry": {"coordinates":[-4.7811179161,37.8673057556],"type":"Point"}
}