{
  "type": "Feature",
  "properties": {
    "iso:country":"ES",
    "sg:address":"Autonomia Kalea, 10",
    "sg:city":"Elgoibar",
    "sg:orig_category":"Electricidad: Instalaciones Industriales",
    "sg:phone":"+34 943 74 42 33",
    "sg:postcode":"20870",
    "sg:province":"Guip\u00f9zcoa",
    "wof:name":"Atxolin S.l.",
    "wof:placetype":"venue"
},
  "geometry": {"coordinates":[-2.4195151329,43.2115478516],"type":"Point"}
}