{
  "type": "Feature",
  "properties": {
    "addr:full":"Calle de Navales, 65 Alcorcon Madrid 28925",
    "addr:housenumber":"65",
    "addr:postcode":"28925",
    "addr:street":"Calle De Navales",
    "iso:country":"ES",
    "sg:address":"Calle de Navales, 65",
    "sg:city":"Alcorcon",
    "sg:orig_category":"Fabricaci\u00d3n De Sobres, Bolsas Y Fundas",
    "sg:phone":"+34 916 44 38 96",
    "sg:postcode":"28925",
    "sg:province":"Madrid",
    "sg:website":"www.arenanova.net",
    "wof:name":"Arena Nova S.l.",
    "wof:placetype":"venue"
},
  "geometry": {"coordinates":[-3.8126847744,40.3365898132],"type":"Point"}
}