{
  "type": "Feature",
  "properties": {
    "iso:country":"ES",
    "sg:address":"Ctra Madrid, 11",
    "sg:city":"Bujaraloz",
    "sg:orig_category":"Refiner\u00cdas De Petr\u00d3leo",
    "sg:phone":"+34 976 17 35 51",
    "sg:postcode":"50177",
    "sg:province":"Zaragoza",
    "wof:name":"Luna Villagrasa Agustin",
    "wof:placetype":"venue"
},
  "geometry": {"coordinates":[-0.1559489965,41.4973945618],"type":"Point"}
}