{
  "type": "Feature",
  "properties": {
    "iso:country":"ES",
    "sg:address":"Calle de Independencia, 11",
    "sg:city":"Salamanca",
    "sg:orig_category":"Empresas De Pintura Y Revestimientos",
    "sg:phone":"+34 923 18 37 35",
    "sg:postcode":"37003",
    "sg:province":"Salamanca",
    "wof:name":"Cobos Delgado Jose",
    "wof:placetype":"venue"
},
  "geometry": {"coordinates":[-5.6525578499,40.9645080566],"type":"Point"}
}