{
  "type": "Feature",
  "properties": {
    "addr:full":"Rua Bedoya, 2 Ourense Ourense 32004",
    "addr:housenumber":"2",
    "addr:postcode":"32004",
    "addr:street":"Rua Bedoya",
    "iso:country":"ES",
    "sg:address":"Rua Bedoya, 2",
    "sg:city":"Ourense",
    "sg:orig_category":"Platos Preparados Refrigerados (fabricaci\u00d3n, Al Por Mayor)",
    "sg:phone":"+34 988 25 46 92",
    "sg:postcode":"32004",
    "sg:province":"Ourense",
    "wof:name":"Cazmipan S.l.",
    "wof:placetype":"venue"
},
  "geometry": {"coordinates":[-7.8628721237,42.3405227661],"type":"Point"}
}