{
  "type": "Feature",
  "properties": {
    "addr:full":"Calle de Tulipan, 8 Aguadulce Almer\u00eda 04720",
    "addr:housenumber":"8",
    "addr:postcode":"04720",
    "addr:street":"Calle De Tulipan;Almeri\u0301A",
    "iso:country":"ES",
    "sg:address":"Calle de Tulipan, 8",
    "sg:city":"Aguadulce",
    "sg:orig_category":"Escuelas De Maternidad P\u00dablicas",
    "sg:phone":"+34 950 34 00 81",
    "sg:postcode":"04720",
    "sg:province":"Almer\u00eda",
    "wof:name":"Matilla Gonzalez Julio",
    "wof:placetype":"venue"
},
  "geometry": {"coordinates":[-2.5744130611,36.8153533936],"type":"Point"}
}