{
  "type": "Feature",
  "properties": {
    "iso:country":"ES",
    "sg:address":"Calle de Concejal Julio Gomez, 9",
    "sg:city":"Madrid",
    "sg:orig_category":"Inmobiliaria (agencias)",
    "sg:phone":"+34 914 05 75 47",
    "sg:postcode":"28027",
    "sg:province":"Madrid",
    "wof:name":"Enlace Ambato Ecuador S.l.",
    "wof:placetype":"venue"
},
  "geometry": {"coordinates":[-3.6505672932,40.4336662292],"type":"Point"}
}