{
  "type": "Feature",
  "properties": {
    "addr:full":"Calle de Atxutegi, 2 Astrabudua Vizcaya 48950",
    "addr:housenumber":"2",
    "addr:postcode":"48950",
    "addr:street":"Calle De Atxutegi",
    "iso:country":"ES",
    "sg:address":"Calle de Atxutegi, 2",
    "sg:city":"Astrabudua",
    "sg:orig_category":"Polideportivos",
    "sg:phone":"+34 944 67 34 61",
    "sg:postcode":"48950",
    "sg:province":"Vizcaya",
    "wof:name":"Ayuntamiento De La Anteiglesia De Erandio",
    "wof:placetype":"venue"
},
  "geometry": {"coordinates":[-2.9815299511,43.3146934509],"type":"Point"}
}