{
  "type": "Feature",
  "properties": {
    "iso:country":"ES",
    "sg:address":"Calle de Cabo Noval, S/n",
    "sg:city":"Valladolid",
    "sg:orig_category":"Librer\u00cdas",
    "sg:phone":"+34 983 22 34 78",
    "sg:postcode":"47013",
    "sg:province":"Valladolid",
    "wof:name":"Garcia Garcia Tomasa",
    "wof:placetype":"venue"
},
  "geometry": {"coordinates":[-4.7240142822,41.6313552856],"type":"Point"}
}