{
  "type": "Feature",
  "properties": {
    "addr:full":"Covadonga, 2 Infiesto Asturias 33530",
    "addr:housenumber":"2",
    "addr:postcode":"33530",
    "addr:street":"Covadonga",
    "iso:country":"ES",
    "sg:address":"Covadonga, 2",
    "sg:city":"Infiesto",
    "sg:orig_category":"Telas Y Sedas (al Por Menor)",
    "sg:phone":"+34 985 71 02 64",
    "sg:postcode":"33530",
    "sg:province":"Asturias",
    "wof:name":"Miguel Cueto Jose",
    "wof:placetype":"venue"
},
  "geometry": {"coordinates":[-5.3589448929,43.3432693481],"type":"Point"}
}