{
  "type": "Feature",
  "properties": {
    "addr:full":"Avda Cervantes, 20 Viveiro Lugo 27850",
    "addr:housenumber":"20",
    "addr:postcode":"27850",
    "addr:street":"Avda Cervantes",
    "iso:country":"ES",
    "sg:address":"Avda Cervantes, 20",
    "sg:city":"Viveiro",
    "sg:orig_category":"Carnicer\u00cdas, Carnicer\u00cdas",
    "sg:phone":"+34 982 56 06 32",
    "sg:postcode":"27850",
    "sg:province":"Lugo",
    "wof:name":"Fustes-pe\u00f1a S.l.",
    "wof:placetype":"venue"
},
  "geometry": {"coordinates":[-7.5931239128,43.6628684998],"type":"Point"}
}