{
  "type": "Feature",
  "properties": {
    "iso:country":"ES",
    "sg:address":"Avda Ferial, 10",
    "sg:city":"Aranda Duero",
    "sg:orig_category":"Material Y Herramientas Agr\u00cdcolas",
    "sg:phone":"+34 947 50 20 10",
    "sg:postcode":"09400",
    "sg:province":"Burgos",
    "wof:name":"Manso Pe\u00f1a Maria Del Pilar",
    "wof:placetype":"venue"
},
  "geometry": {"coordinates":[-3.6848840714,41.6730499268],"type":"Point"}
}