{
  "type": "Feature",
  "properties": {
    "addr:full":"Argenters, 9 Pol. Ind. Santiga Barcelona 08130",
    "addr:housenumber":"9",
    "addr:postcode":"08130",
    "addr:street":"Argenters;Ind.",
    "iso:country":"ES",
    "sg:address":"Argenters, 9",
    "sg:city":"Pol. Ind. Santiga",
    "sg:orig_category":"Reciclaje, Tratamiento De Tejidos",
    "sg:phone":"+34 937 18 35 51",
    "sg:postcode":"08130",
    "sg:province":"Barcelona",
    "sg:website":"j",
    "wof:name":"Stableplastic S.a.",
    "wof:placetype":"venue"
},
  "geometry": {"coordinates":[2.1802799702,41.5371818542],"type":"Point"}
}