{
  "type": "Feature",
  "properties": {
    "iso:country":"ES",
    "sg:address":"Ctra Hidum, 13",
    "sg:city":"Melilla",
    "sg:orig_category":"Supermercados Y Hipermercados",
    "sg:phone":"+34 952 68 27 21",
    "sg:postcode":"52003",
    "sg:province":"Melilla",
    "wof:name":"Mustafa Mizzian Said",
    "wof:placetype":"venue"
},
  "geometry": {"coordinates":[-2.9491930008,35.2934074402],"type":"Point"}
}