{
  "type": "Feature",
  "properties": {
    "addr:full":"Calle de Parra, 1 Arroyo Luz C\u00e1ceres 10900",
    "addr:housenumber":"1",
    "addr:postcode":"10900",
    "addr:street":"Calle De Parra;Ca\u0301Ceres",
    "iso:country":"ES",
    "sg:address":"Calle de Parra, 1",
    "sg:city":"Arroyo Luz",
    "sg:orig_category":"Empresas De Pintura Y Revestimientos",
    "sg:phone":"+34 927 27 22 72",
    "sg:postcode":"10900",
    "sg:province":"C\u00e1ceres",
    "wof:name":"Rodriguez Ramos Miguel Angel",
    "wof:placetype":"venue"
},
  "geometry": {"coordinates":[-6.5839691162,39.4864082336],"type":"Point"}
}