{
  "type": "Feature",
  "properties": {
    "iso:country":"ES",
    "sg:address":"Rond Buenavista, 29",
    "sg:city":"Toledo",
    "sg:orig_category":"Fotocopias, Reprograf\u00cda",
    "sg:phone":"+34 925 22 28 57",
    "sg:postcode":"45005",
    "sg:province":"Toledo",
    "wof:name":"Copisteria Villaver S.l.",
    "wof:placetype":"venue"
},
  "geometry": {"coordinates":[-4.0378351212,39.8771247864],"type":"Point"}
}