{
  "type": "Feature",
  "properties": {
    "addr:full":"C/ Doctor Sapena, 3 Elche Alicante 03204",
    "addr:housenumber":"3",
    "addr:postcode":"03204",
    "addr:street":"C / Doctor Sapena",
    "iso:country":"ES",
    "sg:address":"C/ Doctor Sapena, 3",
    "sg:city":"Elche",
    "sg:orig_category":"Reposter\u00cdas",
    "sg:phone":"+34 966 67 21 44",
    "sg:postcode":"03204",
    "sg:province":"Alicante",
    "wof:name":"Horno Josmi S.l.",
    "wof:placetype":"venue"
},
  "geometry": {"coordinates":[-0.7034879923,38.2617492676],"type":"Point"}
}