{
  "type": "Feature",
  "properties": {
    "addr:full":"Antonio Pildain Kalea, 2 Lezo Guip\u00f9zcoa 20100",
    "addr:housenumber":"2",
    "addr:postcode":"20100",
    "addr:street":"Antonio Pildain Kalea;Guipu\u0300Zcoa",
    "iso:country":"ES",
    "sg:address":"Antonio Pildain Kalea, 2",
    "sg:city":"Lezo",
    "sg:orig_category":"Ropa Para Se\u00d1oras Y Caballeros (al Por Menor)",
    "sg:phone":"+34 943 52 37 89",
    "sg:postcode":"20100",
    "sg:province":"Guip\u00f9zcoa",
    "wof:name":"Jose Maria Iparragirre Zabaleta",
    "wof:placetype":"venue"
},
  "geometry": {"coordinates":[-1.900488019,43.3202323914],"type":"Point"}
}