{
  "type": "Feature",
  "properties": {
    "addr:full":"Carrer de Creus (les), 42 Morell Tarragona 43760",
    "addr:housenumber":"42",
    "addr:postcode":"43760",
    "addr:street":"Carrer De Creus Les",
    "iso:country":"ES",
    "sg:address":"Carrer de Creus (les), 42",
    "sg:city":"Morell",
    "sg:orig_category":"Institutos De Belleza",
    "sg:phone":"+34 977 84 21 15",
    "sg:postcode":"43760",
    "sg:province":"Tarragona",
    "wof:name":"Garcia Marin Francisca",
    "wof:placetype":"venue"
},
  "geometry": {"coordinates":[1.2100399733,41.1916389465],"type":"Point"}
}