{
  "type": "Feature",
  "properties": {
    "iso:country":"ES",
    "sg:address":"Carrer de Federico Garcia Lorca (de), 7",
    "sg:city":"Montornes Nord",
    "sg:orig_category":"Reposter\u00cdas",
    "sg:phone":"+34 935 68 07 79",
    "sg:postcode":"08170",
    "sg:province":"Barcelona",
    "wof:name":"L'espiga Del Nord S. L.",
    "wof:placetype":"venue"
},
  "geometry": {"coordinates":[2.2676711082,41.5543136597],"type":"Point"}
}