{
  "type": "Feature",
  "properties": {
    "iso:country":"ES",
    "sg:address":"Nuevo Milenio, 19",
    "sg:city":"Ciudad Rodrigo",
    "sg:orig_category":"Charcuter\u00cdas (al Por Mayor)",
    "sg:phone":"+34 923 48 09 92",
    "sg:postcode":"37500",
    "sg:province":"Salamanca",
    "wof:name":"Industrias Carnicas Perez Malmierca S.l.",
    "wof:placetype":"venue"
},
  "geometry": {"coordinates":[-6.5625290871,40.5755233765],"type":"Point"}
}