{
  "type": "Feature",
  "properties": {
    "iso:country":"ES",
    "sg:address":"Calle de Reyes Catolicos, 4",
    "sg:city":"Huetor-tajar",
    "sg:orig_category":"Geolog\u00cda Y Geof\u00cdsica",
    "sg:phone":"+34 958 33 20 43",
    "sg:postcode":"18360",
    "sg:province":"Granada",
    "wof:name":"Geotecnia Avanzada De Los Materiales S.l.",
    "wof:placetype":"venue"
},
  "geometry": {"coordinates":[-4.0471930504,37.1975517273],"type":"Point"}
}