{
  "type": "Feature",
  "properties": {
    "addr:full":"Fabrica, 26 Navaconcejo C\u00e1ceres 10613",
    "addr:postcode":"10613",
    "addr:street":"Ca\u0301Ceres",
    "iso:country":"ES",
    "sg:address":"Fabrica, 26",
    "sg:city":"Navaconcejo",
    "sg:classifiers":[
        {
            "category":"Taxi",
            "type":"Transportation"
        }
    ],
    "sg:phone":"+34 927 17 30 80",
    "sg:postcode":"10613",
    "sg:province":"C\u00e1ceres",
    "wof:name":"Calle Barbosa Jose De La",
    "wof:placetype":"venue"
},
  "geometry": {"coordinates":[-5.8323569298,40.1778717041],"type":"Point"}
}