{
  "type": "Feature",
  "properties": {
    "iso:country":"ES",
    "sg:address":"Calle de Carralaverde, 57",
    "sg:city":"Navarrete",
    "sg:orig_category":"Empresas De Empedrado",
    "sg:phone":"+34 941 44 00 49",
    "sg:postcode":"26370",
    "sg:province":"La Rioja",
    "sg:website":"www.murosmsd.com",
    "wof:name":"Muros Sinteticos Decorativos S.l.",
    "wof:placetype":"venue"
},
  "geometry": {"coordinates":[-2.5764095783,42.4403190613],"type":"Point"}
}