{
  "type": "Feature",
  "properties": {
    "iso:country":"ES",
    "sg:address":"Calle de Joaquin Costa, 9",
    "sg:city":"Zaragoza",
    "sg:orig_category":"M\u00c9dicos: Estomatolog\u00cda",
    "sg:phone":"+34 976 22 40 48",
    "sg:postcode":"50001",
    "sg:province":"Zaragoza",
    "wof:name":"Arciniega Bardavio Enrique",
    "wof:placetype":"venue"
},
  "geometry": {"coordinates":[-0.8809586167,41.6486778259],"type":"Point"}
}