{
  "type": "Feature",
  "properties": {
    "iso:country":"ES",
    "sg:address":"Calle de Roger De Flor, S/n",
    "sg:city":"Malaga",
    "sg:orig_category":"Ense\u00d1anza: Comercio, Gesti\u00d3n, Inform\u00c1tica",
    "sg:phone":"+34 952 04 01 20",
    "sg:postcode":"29006",
    "sg:province":"M\u00e1laga",
    "wof:name":"Centro Municipal Informatico De Malaga",
    "wof:placetype":"venue"
},
  "geometry": {"coordinates":[-4.433095932,36.7130470276],"type":"Point"}
}