{
  "type": "Feature",
  "properties": {
    "iso:country":"ES",
    "sg:address":"Carrer de Rubio I Ors, 179",
    "sg:city":"Cornella Llobregat",
    "sg:orig_category":"Ense\u00d1anza Variada",
    "sg:phone":"+34 933 77 83 16",
    "sg:postcode":"08940",
    "sg:province":"Barcelona",
    "wof:name":"Torre Rodriguez Sofia",
    "wof:placetype":"venue"
},
  "geometry": {"coordinates":[2.0729119778,41.3526077271],"type":"Point"}
}