{
  "type": "Feature",
  "properties": {
    "iso:country":"ES",
    "sg:address":"Carrer de Nou, 11",
    "sg:city":"Granollers",
    "sg:orig_category":"Moda",
    "sg:phone":"+34 938 60 65 26",
    "sg:postcode":"08401",
    "sg:province":"Barcelona",
    "wof:name":"Baylach Faja Maria Teresa",
    "wof:placetype":"venue"
},
  "geometry": {"coordinates":[2.2877271175,41.6073074341],"type":"Point"}
}