{
  "type": "Feature",
  "properties": {
    "addr:full":"Calle de Real, 21 Navalucillos Toledo 45130",
    "addr:housenumber":"21",
    "addr:postcode":"45130",
    "addr:street":"Calle De Real",
    "iso:country":"ES",
    "sg:address":"Calle de Real, 21",
    "sg:city":"Navalucillos",
    "sg:orig_category":"Cajas Para Embalar",
    "sg:phone":"+34 925 42 62 58",
    "sg:postcode":"45130",
    "sg:province":"Toledo",
    "wof:name":"Caja Rural Provincial De Toledo",
    "wof:placetype":"venue"
},
  "geometry": {"coordinates":[-4.6427631378,39.671836853],"type":"Point"}
}