{
  "type": "Feature",
  "properties": {
    "iso:country":"ES",
    "sg:address":"Calle de Conde De Vistahermosa, 1",
    "sg:city":"Madrid",
    "sg:orig_category":"Molduras, Junquillos, Listones Y Molduras Perforadas",
    "sg:phone":"+34 914 60 61 56",
    "sg:postcode":"28019",
    "sg:province":"Madrid",
    "wof:name":"Marcos Panader Esther",
    "wof:placetype":"venue"
},
  "geometry": {"coordinates":[-3.7134091854,40.3948287964],"type":"Point"}
}