{
  "type": "Feature",
  "properties": {
    "iso:country":"ES",
    "sg:address":"Carr Mont (dels), 11",
    "sg:city":"Algemesi",
    "sg:orig_category":"Ense\u00d1ante, Direcci\u00d3n",
    "sg:phone":"+34 962 42 08 45",
    "sg:postcode":"46680",
    "sg:province":"Valencia",
    "wof:name":"Vicente Revert C.b.",
    "wof:placetype":"venue"
},
  "geometry": {"coordinates":[-0.4383490086,39.1962852478],"type":"Point"}
}