{
  "type": "Feature",
  "properties": {
    "iso:country":"ES",
    "sg:address":"Calle de Isilla, 3",
    "sg:city":"Aranda Duero",
    "sg:orig_category":"Consultas M\u00c9dicas",
    "sg:phone":"+34 947 51 06 26",
    "sg:postcode":"09400",
    "sg:province":"Burgos",
    "wof:name":"Cura Alvarez Fernando Del",
    "wof:placetype":"venue"
},
  "geometry": {"coordinates":[-3.6868970394,41.6713371277],"type":"Point"}
}