{
  "type": "Feature",
  "properties": {
    "iso:country":"ES",
    "sg:address":"Ctra Puigpelat De, S/n",
    "sg:city":"Valls",
    "sg:orig_category":"Clubes, Asociaciones De Ocio",
    "sg:phone":"+34 977 60 11 34",
    "sg:postcode":"43800",
    "sg:province":"Tarragona",
    "wof:name":"Masia Milan S.l.",
    "wof:placetype":"venue"
},
  "geometry": {"coordinates":[1.2525299788,41.2871513367],"type":"Point"}
}