{
  "type": "Feature",
  "properties": {
    "iso:country":"ES",
    "sg:address":"Calle de Virgen, 64",
    "sg:city":"Valdepe\u00f1as",
    "sg:orig_category":"Ropa Para Se\u00d1oras (al Por Menor)",
    "sg:phone":"+34 926 31 33 47",
    "sg:postcode":"13300",
    "sg:province":"Ciudad Real",
    "wof:name":"Merxi S.a.",
    "wof:placetype":"venue"
},
  "geometry": {"coordinates":[-3.3846290112,38.7596702576],"type":"Point"}
}