{
  "type": "Feature",
  "properties": {
    "iso:country":"ES",
    "sg:address":"Calle de Sarria, 56",
    "sg:city":"Madrid",
    "sg:orig_category":"Ropa Para Se\u00d1oras Y Caballeros (al Por Menor)",
    "sg:phone":"+34 913 73 41 21",
    "sg:postcode":"28029",
    "sg:province":"Madrid",
    "wof:name":"Sanchez Delgado Juan Pablo",
    "wof:placetype":"venue"
},
  "geometry": {"coordinates":[-3.7144401073,40.4755058289],"type":"Point"}
}