{
  "type": "Feature",
  "properties": {
    "addr:full":"Urb El Pilar, 4 Motril Granada 18600",
    "addr:housenumber":"4",
    "addr:postcode":"18600",
    "addr:street":"Urb El Pilar",
    "iso:country":"ES",
    "sg:address":"Urb El Pilar, 4",
    "sg:city":"Motril",
    "sg:orig_category":"Peluquer\u00cdas, Peluquer\u00cda Mixta",
    "sg:phone":"+34 958 60 92 16",
    "sg:postcode":"18600",
    "sg:province":"Granada",
    "wof:name":"Herrera Rodriguez Mercedes",
    "wof:placetype":"venue"
},
  "geometry": {"coordinates":[-3.5248510838,36.7526321411],"type":"Point"}
}