{
  "type": "Feature",
  "properties": {
    "addr:full":"Calle de Iglesia, 8 Villarrubia De Los Ojos Ciudad Real 13670",
    "addr:housenumber":"8",
    "addr:postcode":"13670",
    "addr:street":"Calle De Iglesia",
    "iso:country":"ES",
    "sg:address":"Calle de Iglesia, 8",
    "sg:city":"Villarrubia De Los Ojos",
    "sg:orig_category":"Asesor\u00cda Fiscal Y Jur\u00cddica",
    "sg:phone":"+34 926 89 89 84",
    "sg:postcode":"13670",
    "sg:province":"Ciudad Real",
    "wof:name":"Gr Estudio Fiscal Y Laboral Para Pymes S.l.",
    "wof:placetype":"venue"
},
  "geometry": {"coordinates":[-3.6072859764,39.2189674377],"type":"Point"}
}