{
  "type": "Feature",
  "properties": {
    "iso:country":"ES",
    "sg:address":"Carr Joan Maragall, 16",
    "sg:city":"Figueres",
    "sg:orig_category":"Bisuteros (fabricaci\u00d3n, Al Por Mayor)",
    "sg:phone":"+34 972 51 19 57",
    "sg:postcode":"17600",
    "sg:province":"Girona",
    "wof:name":"Martinez Rodriguez Alejandra Guadalupe",
    "wof:placetype":"venue"
},
  "geometry": {"coordinates":[2.9581100941,42.2656898499],"type":"Point"}
}