{
  "type": "Feature",
  "properties": {
    "iso:country":"ES",
    "sg:address":"Calle de Bilbao, 2",
    "sg:city":"Zaragoza",
    "sg:orig_category":"M\u00c9dicos: Cirug\u00cda Maxilofacial",
    "sg:phone":"+34 976 21 93 66",
    "sg:postcode":"50004",
    "sg:province":"Zaragoza",
    "wof:name":"Dehesa Baque Juan Antonio",
    "wof:placetype":"venue"
},
  "geometry": {"coordinates":[-0.8849167228,41.6501083374],"type":"Point"}
}