{
  "type": "Feature",
  "properties": {
    "iso:country":"ES",
    "sg:address":"Calle de Mayor, 26",
    "sg:city":"Arenas -areeta",
    "sg:orig_category":"Venta, Instalaci\u00d3n De Calefacci\u00d3n",
    "sg:phone":"+34 944 63 57 50",
    "sg:postcode":"48930",
    "sg:province":"Vizcaya",
    "wof:name":"Domingez Olabarria Jose Antonio",
    "wof:placetype":"venue"
},
  "geometry": {"coordinates":[-3.0116980076,43.3265419006],"type":"Point"}
}