{
  "type": "Feature",
  "properties": {
    "addr:full":"Avda Alicante, 9 Biar Alicante 03410",
    "addr:housenumber":"9",
    "addr:postcode":"03410",
    "addr:street":"Avda Alicante",
    "iso:country":"ES",
    "sg:address":"Avda Alicante, 9",
    "sg:city":"Biar",
    "sg:orig_category":"Asesor\u00cda Sobre Comunicaci\u00d3n De Empresas",
    "sg:phone":"+34 965 81 12 30",
    "sg:postcode":"03410",
    "sg:province":"Alicante",
    "wof:name":"Valdes Frances Cristobal",
    "wof:placetype":"venue"
},
  "geometry": {"coordinates":[-0.7632700205,38.6278152466],"type":"Point"}
}