{
  "type": "Feature",
  "properties": {
    "iso:country":"ES",
    "sg:address":"Avda Lugo, 79",
    "sg:city":"Pontevedra",
    "sg:orig_category":"Lavado, Limpieza De Veh\u00cdculos",
    "sg:phone":"+34 986 84 09 90",
    "sg:postcode":"36004",
    "sg:province":"Pontevedra",
    "wof:name":"Servi Auto Mourente S.l.",
    "wof:placetype":"venue"
},
  "geometry": {"coordinates":[-8.6227626801,42.4335327148],"type":"Point"}
}