{
  "type": "Feature",
  "properties": {
    "addr:full":"Calle de Juan Carlos I, 15 Arroba De Los Montes Ciudad Real 13193",
    "addr:housenumber":"15",
    "addr:postcode":"13193",
    "addr:street":"Calle De Juan Carlos I;Montes",
    "iso:country":"ES",
    "sg:address":"Calle de Juan Carlos I, 15",
    "sg:city":"Arroba De Los Montes",
    "sg:orig_category":"Refiner\u00cdas De Petr\u00d3leo",
    "sg:phone":"+34 926 77 15 11",
    "sg:postcode":"13193",
    "sg:province":"Ciudad Real",
    "wof:name":"Camacho Muela Manuel",
    "wof:placetype":"venue"
},
  "geometry": {"coordinates":[-4.542178154,39.1551055908],"type":"Point"}
}