{
  "type": "Feature",
  "properties": {
    "addr:full":"Avda Juan Gomez Juanito, 9 Fuengirola M\u00e1laga 29640",
    "addr:housenumber":"9",
    "addr:postcode":"29640",
    "addr:street":"Avda Juan Gomez Juanito;Ma\u0301Laga",
    "iso:country":"ES",
    "sg:address":"Avda Juan Gomez Juanito, 9",
    "sg:city":"Fuengirola",
    "sg:orig_category":"Organismos De Turismo",
    "sg:phone":"+34 952 46 16 47",
    "sg:postcode":"29640",
    "sg:province":"M\u00e1laga",
    "wof:name":"Resemvac S.l.",
    "wof:placetype":"venue"
},
  "geometry": {"coordinates":[-4.6243481636,36.5411758423],"type":"Point"}
}