{
  "type": "Feature",
  "properties": {
    "iso:country":"ES",
    "sg:address":"Avda Victoria, Km. 0012,8",
    "sg:city":"Madrid",
    "sg:orig_category":"Ropa Para Se\u00d1oras Y Caballeros (al Por Menor)",
    "sg:phone":"+34 913 72 91 81",
    "sg:postcode":"28023",
    "sg:province":"Madrid",
    "wof:name":"Arenile S.l.",
    "wof:placetype":"venue"
},
  "geometry": {"coordinates":[-3.8184049129,40.468132019],"type":"Point"}
}