{
  "type": "Feature",
  "properties": {
    "addr:full":"Calle de Andres Vicente, 3 Zaragoza Zaragoza 50017",
    "addr:housenumber":"3",
    "addr:postcode":"50017",
    "addr:street":"Calle De Andres Vicente",
    "iso:country":"ES",
    "sg:address":"Calle de Andres Vicente, 3",
    "sg:city":"Zaragoza",
    "sg:orig_category":"Loter\u00cda Y T\u00d3mbola",
    "sg:phone":"+34 976 34 80 47",
    "sg:postcode":"50017",
    "sg:province":"Zaragoza",
    "wof:name":"Claver Monzon Ana Maria",
    "wof:placetype":"venue"
},
  "geometry": {"coordinates":[-0.9145326018,41.6507415771],"type":"Point"}
}