{
  "type": "Feature",
  "properties": {
    "iso:country":"ES",
    "sg:address":"Zelaia Auzoa, 23",
    "sg:city":"Zelaia",
    "sg:orig_category":"Audiovisuales (producci\u00d3n, Edici\u00d3n, Realizaci\u00d3n)",
    "sg:phone":"+34 946 31 56 81",
    "sg:postcode":"48140",
    "sg:province":"Vizcaya",
    "wof:name":"Balea Musika Ideiak S.l.",
    "wof:placetype":"venue"
},
  "geometry": {"coordinates":[-2.7913589478,43.1569404602],"type":"Point"}
}