{
  "type": "Feature",
  "properties": {
    "addr:full":"Carrer de Gaia (del) - Torreforta, 11 Torreforta Tarragona 43006",
    "addr:housenumber":"11",
    "addr:postcode":"43006",
    "addr:street":"Carrer De Gaia Del Torreforta",
    "iso:country":"ES",
    "sg:address":"Carrer de Gaia (del) - Torreforta, 11",
    "sg:city":"Torreforta",
    "sg:orig_category":"Empresas De Carpinter\u00cda De Madera",
    "sg:phone":"+34 977 54 64 34",
    "sg:postcode":"43006",
    "sg:province":"Tarragona",
    "wof:name":"Diaz Mahe Jose Luis",
    "wof:placetype":"venue"
},
  "geometry": {"coordinates":[1.2202759981,41.1209449768],"type":"Point"}
}