{
  "type": "Feature",
  "properties": {
    "iso:country":"ES",
    "sg:address":"Ctra Sevilla-huelva, Km. 0537,0",
    "sg:city":"Sanlucar Mayor",
    "sg:orig_category":"Art\u00cdculos De Regalo (al Por Menor)",
    "sg:phone":"+34 955 70 06 20",
    "sg:postcode":"41800",
    "sg:province":"Sevilla",
    "wof:name":"Revuelta Reina Maria Del Rosario",
    "wof:placetype":"venue"
},
  "geometry": {"coordinates":[-6.1956338882,37.3855361938],"type":"Point"}
}