{
  "type": "Feature",
  "properties": {
    "iso:country":"ES",
    "sg:address":"Carrer de Muntaner, 393",
    "sg:city":"Barcelona",
    "sg:orig_category":"Asistencia Domiciliaria",
    "sg:phone":"+34 934 14 63 47",
    "sg:postcode":"08021",
    "sg:province":"Barcelona",
    "wof:name":"Barcelona Assistencia I Serveis A La 3 Edat S.l.",
    "wof:placetype":"venue"
},
  "geometry": {"coordinates":[2.1419739723,41.399684906],"type":"Point"}
}