{
  "type": "Feature",
  "properties": {
    "addr:full":"Plaz San Luis Gonzaga, 7 Donostia-san Sebastian Guip\u00f9zcoa 20017",
    "addr:housenumber":"7",
    "addr:postcode":"20017",
    "addr:street":"Plaz San Luis Gonzaga",
    "iso:country":"ES",
    "sg:address":"Plaz San Luis Gonzaga, 7",
    "sg:city":"Donostia-san Sebastian",
    "sg:orig_category":"Alumbrados",
    "sg:phone":"+34 943 39 88 13",
    "sg:postcode":"20017",
    "sg:province":"Guip\u00f9zcoa",
    "wof:name":"Gimenez Echeverria Oscar",
    "wof:placetype":"venue"
},
  "geometry": {"coordinates":[-1.9388259649,43.3192520142],"type":"Point"}
}