{
  "type": "Feature",
  "properties": {
    "iso:country":"ES",
    "sg:address":"Av Princep D'asturies, 15",
    "sg:city":"Barcelona",
    "sg:orig_category":"Mercer\u00cda, Lencer\u00cda (al Por Menor)",
    "sg:phone":"+34 932 18 48 35",
    "sg:postcode":"08012",
    "sg:province":"Barcelona",
    "wof:name":"Pubill Roca Maria Teresa",
    "wof:placetype":"venue"
},
  "geometry": {"coordinates":[2.1505038738,41.4023323059],"type":"Point"}
}