{
  "type": "Feature",
  "properties": {
    "iso:country":"ES",
    "sg:address":"Calle de Galera, 7",
    "sg:city":"Sevilla",
    "sg:orig_category":"Tapicer\u00cdas",
    "sg:phone":"+34 954 22 26 06",
    "sg:postcode":"41001",
    "sg:province":"Sevilla",
    "wof:name":"Perez Gonzalez Juan Manuel",
    "wof:placetype":"venue"
},
  "geometry": {"coordinates":[-5.9991369247,37.3882331848],"type":"Point"}
}