{
  "type": "Feature",
  "properties": {
    "iso:country":"ES",
    "sg:address":"Comisario, 10",
    "sg:city":"Loja",
    "sg:orig_category":"Carnicer\u00cdas, Carnicer\u00cdas",
    "sg:phone":"+34 958 32 54 97",
    "sg:postcode":"18300",
    "sg:province":"Granada",
    "wof:name":"Funes Moles Antonio",
    "wof:placetype":"venue"
},
  "geometry": {"coordinates":[-4.1513848305,37.1654052734],"type":"Point"}
}