{
  "type": "Feature",
  "properties": {
    "iso:country":"ES",
    "sg:address":"Calle de Camilo Jose Cela, 2",
    "sg:city":"Castilleja Cuesta",
    "sg:orig_category":"Distribuci\u00d3n De Petr\u00d3leo Y Derivados",
    "sg:phone":"+34 954 16 42 48",
    "sg:postcode":"41950",
    "sg:province":"Sevilla",
    "wof:name":"Miangli S.l",
    "wof:placetype":"venue"
},
  "geometry": {"coordinates":[-6.0531368256,37.3851509094],"type":"Point"}
}