{
  "type": "Feature",
  "properties": {
    "iso:country":"ES",
    "sg:address":"Carrer de Ramon Marti, 9",
    "sg:city":"Roda Ter",
    "sg:orig_category":"Albergues",
    "sg:phone":"+34 938 54 05 20",
    "sg:postcode":"08510",
    "sg:province":"Barcelona",
    "wof:name":"Gonzalez Barco Victor",
    "wof:placetype":"venue"
},
  "geometry": {"coordinates":[2.3099009991,41.9813842773],"type":"Point"}
}