{
  "type": "Feature",
  "properties": {
    "iso:country":"ES",
    "sg:address":"Plno. Industrial, 1",
    "sg:city":"Villamuriel",
    "sg:orig_category":"Contenedores (mercanc\u00cdas)",
    "sg:phone":"+34 979 77 00 61",
    "sg:postcode":"34190",
    "sg:province":"Palencia",
    "wof:name":"Transportes 4010 S.l.",
    "wof:placetype":"venue"
},
  "geometry": {"coordinates":[-4.5164442062,41.9515914917],"type":"Point"}
}