{
  "type": "Feature",
  "properties": {
    "iso:country":"ES",
    "sg:address":"Carrer de Arcadi Balaguer, 32",
    "sg:city":"Castelldefels",
    "sg:orig_category":"Molduras, Junquillos, Listones Y Molduras Perforadas",
    "sg:phone":"+34 936 36 60 21",
    "sg:postcode":"08860",
    "sg:province":"Barcelona",
    "wof:name":"Bar Musical Poliedro S.c.p.",
    "wof:placetype":"venue"
},
  "geometry": {"coordinates":[1.9759809971,41.2795448303],"type":"Point"}
}