{
  "type": "Feature",
  "properties": {
    "addr:full":"Calle de Sol, 7 Puebla Calzada Badajoz 06490",
    "addr:housenumber":"7",
    "addr:postcode":"06490",
    "addr:street":"Calle De Sol;Calzada Badajoz",
    "iso:country":"ES",
    "sg:address":"Calle de Sol, 7",
    "sg:city":"Puebla Calzada",
    "sg:orig_category":"Institutos De Belleza",
    "sg:phone":"+34 924 45 04 63",
    "sg:postcode":"06490",
    "sg:province":"Badajoz",
    "wof:name":"Navarro Sanchez Maria Del Carmen",
    "wof:placetype":"venue"
},
  "geometry": {"coordinates":[-6.6302289963,38.890460968],"type":"Point"}
}