{
  "type": "Feature",
  "properties": {
    "addr:full":"Calle de Krutzejada, 42 Landa Vizcaya 48610",
    "addr:housenumber":"42",
    "addr:postcode":"48610",
    "addr:street":"Calle De Krutzejada",
    "iso:country":"ES",
    "sg:address":"Calle de Krutzejada, 42",
    "sg:city":"Landa",
    "sg:orig_category":"Productos Qu\u00cdmicos (fabricaci\u00d3n, Al Por Mayor)",
    "sg:phone":"+34 946 76 15 37",
    "sg:postcode":"48610",
    "sg:province":"Vizcaya",
    "wof:name":"Dupont Asturias S.l.",
    "wof:placetype":"venue"
},
  "geometry": {"coordinates":[-2.9565939903,43.3791046143],"type":"Point"}
}