{
  "type": "Feature",
  "properties": {
    "iso:country":"ES",
    "sg:address":"Carr Rectoria, 17",
    "sg:city":"S. Hilari Sacalm",
    "sg:orig_category":"Ense\u00d1anza, Formaci\u00d3n Profesional: Aprendizaje",
    "sg:phone":"+34 972 86 81 01",
    "sg:postcode":"17403",
    "sg:province":"Girona",
    "wof:name":"Ajuntament De Sant Hilari Sacalm-oficinas",
    "wof:placetype":"venue"
},
  "geometry": {"coordinates":[2.5079042912,41.8785667419],"type":"Point"}
}