{
  "type": "Feature",
  "properties": {
    "addr:full":"Calle de Pedro Alfonso, 1 Zaragoza Zaragoza 50017",
    "addr:housenumber":"1",
    "addr:postcode":"50017",
    "addr:street":"Calle De Pedro Alfonso",
    "iso:country":"ES",
    "sg:address":"Calle de Pedro Alfonso, 1",
    "sg:city":"Zaragoza",
    "sg:orig_category":"Servicios De Telecomunicaciones",
    "sg:phone":"+34 976 32 61 74",
    "sg:postcode":"50017",
    "sg:province":"Zaragoza",
    "wof:name":"Pereira Guerron Yolanda",
    "wof:placetype":"venue"
},
  "geometry": {"coordinates":[-0.9117509723,41.6519508362],"type":"Point"}
}