{
  "type": "Feature",
  "properties": {
    "addr:full":"Calle de Via Complutense, S/n Alcala Henares Madrid 28805",
    "addr:housenumber":"s / n",
    "addr:postcode":"28805",
    "addr:street":"Calle De Via Complutense",
    "iso:country":"ES",
    "sg:address":"Calle de Via Complutense, S/n",
    "sg:city":"Alcala Henares",
    "sg:orig_category":"Cl\u00cdnicas M\u00c9dicas",
    "sg:phone":"+34 918 88 18 85",
    "sg:postcode":"28805",
    "sg:province":"Madrid",
    "sg:website":"www.fremap.es",
    "wof:name":"Fremap-mutua De Accidentes De Trabajo Y Enfermedades Profesionale",
    "wof:placetype":"venue"
},
  "geometry": {"coordinates":[-3.3633339405,40.4854431152],"type":"Point"}
}