{
  "type": "Feature",
  "properties": {
    "addr:full":"Calle de Borde Alegre, 8 Malaga M\u00e1laga 29014",
    "addr:housenumber":"8",
    "addr:postcode":"29014",
    "addr:street":"Calle De Borde Alegre;Ma\u0301Laga",
    "iso:country":"ES",
    "sg:address":"Calle de Borde Alegre, 8",
    "sg:city":"Malaga",
    "sg:orig_category":"M\u00c9dicos: Salud P\u00dablica",
    "sg:phone":"+34 952 65 18 19",
    "sg:postcode":"29014",
    "sg:province":"M\u00e1laga",
    "wof:name":"Carrasco Pecci Carlos",
    "wof:placetype":"venue"
},
  "geometry": {"coordinates":[-4.4211177826,36.7501564026],"type":"Point"}
}