{
  "type": "Feature",
  "properties": {
    "addr:full":"Carrer de Sant Joan, 39 Ametlla Mar Tarragona 43860",
    "addr:housenumber":"39",
    "addr:postcode":"43860",
    "addr:street":"Carrer De Sant Joan",
    "iso:country":"ES",
    "sg:address":"Carrer de Sant Joan, 39",
    "sg:city":"Ametlla Mar",
    "sg:orig_category":"Ropa Para Se\u00d1oras (al Por Menor)",
    "sg:phone":"+34 977 45 61 08",
    "sg:postcode":"43860",
    "sg:province":"Tarragona",
    "wof:name":"Margalef S.c.p.",
    "wof:placetype":"venue"
},
  "geometry": {"coordinates":[0.8029969931,40.8847236633],"type":"Point"}
}