{
  "type": "Feature",
  "properties": {
    "addr:full":"Calle de Murillo, 61 Calamonte Badajoz 06810",
    "addr:housenumber":"61",
    "addr:postcode":"06810",
    "addr:street":"Calle De Murillo",
    "iso:country":"ES",
    "sg:address":"Calle de Murillo, 61",
    "sg:city":"Calamonte",
    "sg:orig_category":"Chapister\u00cda",
    "sg:phone":"+34 924 32 31 03",
    "sg:postcode":"06810",
    "sg:province":"Badajoz",
    "wof:name":"Perez Figueroa Celestino",
    "wof:placetype":"venue"
},
  "geometry": {"coordinates":[-6.3847208023,38.88514328],"type":"Point"}
}