{
  "type": "Feature",
  "properties": {
    "addr:full":"Calle de Asuncion, 68 Sevilla Sevilla 41011",
    "addr:housenumber":"68",
    "addr:postcode":"41011",
    "addr:street":"Calle De Asuncion",
    "iso:country":"ES",
    "sg:address":"Calle de Asuncion, 68",
    "sg:city":"Sevilla",
    "sg:orig_category":"Centros Comerciales Y Grandes Tiendas",
    "sg:phone":"+34 954 28 29 85",
    "sg:postcode":"41011",
    "sg:province":"Sevilla",
    "wof:name":"Erestina Comercial Goma S.l.",
    "wof:placetype":"venue"
},
  "geometry": {"coordinates":[-5.9975037575,37.3738899231],"type":"Point"}
}