{
  "type": "Feature",
  "properties": {
    "iso:country":"ES",
    "sg:address":"Rua Justo Martinez, 21",
    "sg:city":"Estrada",
    "sg:orig_category":"Ropa Para Se\u00d1oras (al Por Menor)",
    "sg:phone":"+34 986 57 52 49",
    "sg:postcode":"36680",
    "sg:province":"Pontevedra",
    "wof:name":"Rodriguez Gonzalez Luisa",
    "wof:placetype":"venue"
},
  "geometry": {"coordinates":[-8.4910736084,42.6887664795],"type":"Point"}
}