{
  "type": "Feature",
  "properties": {
    "iso:country":"ES",
    "sg:address":"Avda Hernan Cortes, 8",
    "sg:city":"Caceres",
    "sg:orig_category":"Electrodom\u00c9sticos (fabricaci\u00d3n, Al Por Mayor)",
    "sg:phone":"+34 927 24 04 87",
    "sg:postcode":"10004",
    "sg:province":"C\u00e1ceres",
    "wof:name":"Electrodomesticos Del Oeste S.a.",
    "wof:placetype":"venue"
},
  "geometry": {"coordinates":[-6.3788089752,39.4735298157],"type":"Point"}
}