{
  "type": "Feature",
  "properties": {
    "iso:country":"ES",
    "sg:address":"Calle de Traperia, 30",
    "sg:city":"Catedral",
    "sg:orig_category":"Relojer\u00cda (al Por Menor, Reparaci\u00d3n)",
    "sg:phone":"+34 968 22 28 19",
    "sg:postcode":"30001",
    "sg:province":"Murcia",
    "wof:name":"Alvaro Olivares Joyero S.l.",
    "wof:placetype":"venue"
},
  "geometry": {"coordinates":[-1.1298867464,37.9834747314],"type":"Point"}
}