{
  "type": "Feature",
  "properties": {
    "addr:full":"Calle de Arquitecto Lazaro, 5 Le\u00f3n Le\u00f3n 24003",
    "addr:housenumber":"5",
    "addr:postcode":"24003",
    "addr:street":"Calle De Arquitecto Lazaro;Leo\u0301N",
    "iso:country":"ES",
    "sg:address":"Calle de Arquitecto Lazaro, 5",
    "sg:city":"Le\u00f3n",
    "sg:orig_category":"Producci\u00d3n De Huevos",
    "sg:phone":"+34 987 20 90 16",
    "sg:postcode":"24003",
    "sg:province":"Le\u00f3n",
    "wof:name":"Lufag S.l.",
    "wof:placetype":"venue"
},
  "geometry": {"coordinates":[-5.5670852661,42.5940361023],"type":"Point"}
}