{
  "type": "Feature",
  "properties": {
    "addr:full":"Avda Euzkadi, 14 Barakaldo Vizcaya 48902",
    "addr:housenumber":"14",
    "addr:postcode":"48902",
    "addr:street":"Avda Euzkadi",
    "iso:country":"ES",
    "sg:address":"Avda Euzkadi, 14",
    "sg:city":"Barakaldo",
    "sg:orig_category":"Agentes, Concesionarios Y Sucursales De Veh\u00cdculos",
    "sg:phone":"+34 944 82 08 81",
    "sg:postcode":"48902",
    "sg:province":"Vizcaya",
    "wof:name":"Landa Motor, C.b.",
    "wof:placetype":"venue"
},
  "geometry": {"coordinates":[-2.9903979301,43.293510437],"type":"Point"}
}