{
  "type": "Feature",
  "properties": {
    "addr:full":"Calle de General Ricardos, 81 Madrid Madrid 28019",
    "addr:housenumber":"81",
    "addr:postcode":"madrid;28019",
    "addr:street":"Calle De General Ricardos",
    "iso:country":"ES",
    "sg:address":"Calle de General Ricardos, 81",
    "sg:city":"Madrid",
    "sg:orig_category":"Organismos Y Centros De Vacaciones Y Esparcimiento Para Ni\u00d1os Y Adolescentes",
    "sg:phone":"+34 914 28 02 05",
    "sg:postcode":"28019",
    "sg:province":"Madrid",
    "wof:name":"Centro Profesional De Oficios S.l.",
    "wof:placetype":"venue"
},
  "geometry": {"coordinates":[-3.7228939533,40.393737793],"type":"Point"}
}