{
  "type": "Feature",
  "properties": {
    "iso:country":"ES",
    "sg:address":"Calle de Tabirakalea, 25",
    "sg:city":"Durango",
    "sg:orig_category":"Institutos De Belleza",
    "sg:phone":"+34 946 20 15 77",
    "sg:postcode":"48200",
    "sg:province":"Vizcaya",
    "wof:name":"Izaskun Camara Ezenarro",
    "wof:placetype":"venue"
},
  "geometry": {"coordinates":[-2.6316440105,43.1625442505],"type":"Point"}
}