{
  "type": "Feature",
  "properties": {
    "addr:full":"Cerrada Del Hospital, S/n Benavente Zamora 49600",
    "addr:housenumber":"s / n",
    "addr:postcode":"49600",
    "addr:street":"Cerrada Del Hospital",
    "iso:country":"ES",
    "sg:address":"Cerrada Del Hospital, S/n",
    "sg:city":"Benavente",
    "sg:orig_category":"Organizaciones Internacionales",
    "sg:phone":"+34 980 63 71 72",
    "sg:postcode":"49600",
    "sg:province":"Zamora",
    "wof:name":"Cruz Roja Espa\u00f1ola Asamblea Local",
    "wof:placetype":"venue"
},
  "geometry": {"coordinates":[-5.6747250557,42.0034065247],"type":"Point"}
}