{
  "type": "Feature",
  "properties": {
    "iso:country":"ES",
    "sg:address":"Av Catalunya, 380",
    "sg:city":"Aldea",
    "sg:orig_category":"Ense\u00d1anza: Profesiones Art\u00cdsticas",
    "sg:phone":"+34 977 45 02 76",
    "sg:postcode":"43896",
    "sg:province":"Tarragona",
    "wof:name":"Andreu Falco Daniel",
    "wof:placetype":"venue"
},
  "geometry": {"coordinates":[0.6175916195,40.7449417114],"type":"Point"}
}