{
  "type": "Feature",
  "properties": {
    "addr:full":"Calle de Redonda De Santiago, 11 Ubeda Ja\u00e9n 23400",
    "addr:housenumber":"11",
    "addr:postcode":"23400",
    "addr:street":"Calle De Redonda De Santiago;Jae\u0301N",
    "iso:country":"ES",
    "sg:address":"Calle de Redonda De Santiago, 11",
    "sg:city":"Ubeda",
    "sg:orig_category":"Caf\u00c9s, Bares, Cervecer\u00cdas",
    "sg:phone":"+34 953 79 27 88",
    "sg:postcode":"23400",
    "sg:province":"Ja\u00e9n",
    "wof:name":"Plaza Olivares Agustin",
    "wof:placetype":"venue"
},
  "geometry": {"coordinates":[-3.3771500587,38.0125350952],"type":"Point"}
}