{
  "type": "Feature",
  "properties": {
    "iso:country":"ES",
    "sg:address":"Rua Pontes De Garcia Rodriguez (as), 21",
    "sg:city":"Vilalba",
    "sg:orig_category":"Marmolistas Funerarios",
    "sg:phone":"+34 982 51 09 78",
    "sg:postcode":"27800",
    "sg:province":"Lugo",
    "wof:name":"Rego Gato Ramiro",
    "wof:placetype":"venue"
},
  "geometry": {"coordinates":[-7.6797471046,43.299823761],"type":"Point"}
}