{
  "type": "Feature",
  "properties": {
    "iso:country":"ES",
    "sg:address":"Calle de Zumalacarregui, 104",
    "sg:city":"Melida",
    "sg:orig_category":"Cooperativas Agr\u00cdcolas",
    "sg:phone":"+34 948 74 66 76",
    "sg:postcode":"31382",
    "sg:province":"Navarra",
    "wof:name":"Agricola San Isidro En Carcastillo S.coop.",
    "wof:placetype":"venue"
},
  "geometry": {"coordinates":[-1.5554661751,42.3567771912],"type":"Point"}
}