{
  "type": "Feature",
  "properties": {
    "iso:country":"ES",
    "sg:address":"Carretera De Cordoba, S/n",
    "sg:city":"Pinos-puente",
    "sg:orig_category":"M\u00c1rmoles, Granitos Y Piedras Naturales",
    "sg:phone":"+34 958 45 05 54",
    "sg:postcode":"18240",
    "sg:province":"Granada",
    "wof:name":"Mar Y Sane Dos S.l.",
    "wof:placetype":"venue"
},
  "geometry": {"coordinates":[-3.7566990852,37.2546691895],"type":"Point"}
}