{
  "type": "Feature",
  "properties": {
    "addr:full":"Calle de Arturo Soria, 105 Madrid Madrid 28043",
    "addr:housenumber":"105",
    "addr:postcode":"28043",
    "addr:street":"Calle De Arturo Soria",
    "iso:country":"ES",
    "sg:address":"Calle de Arturo Soria, 105",
    "sg:city":"Madrid",
    "sg:orig_category":"M\u00c9dicos: Cirug\u00cda Ortop\u00c9dica Y Traumatolog\u00cda",
    "sg:phone":"+34 915 19 60 86",
    "sg:postcode":"28043",
    "sg:province":"Madrid",
    "wof:name":"Instituto De Traumatologia Estevez S.l.",
    "wof:placetype":"venue"
},
  "geometry": {"coordinates":[-3.6519436836,40.4502105713],"type":"Point"}
}