{
  "type": "Feature",
  "properties": {
    "addr:full":"Carrer de Nord, 77 Terrassa Barcelona 08221",
    "addr:housenumber":"77",
    "addr:postcode":"08221",
    "addr:street":"Carrer De Nord",
    "iso:country":"ES",
    "sg:address":"Carrer de Nord, 77",
    "sg:city":"Terrassa",
    "sg:orig_category":"Asilos De Ancianos. Centros Privados",
    "sg:phone":"+34 937 31 32 04",
    "sg:postcode":"08221",
    "sg:province":"Barcelona",
    "wof:name":"Leon Villegas Maria Dolores",
    "wof:placetype":"venue"
},
  "geometry": {"coordinates":[2.0136170387,41.568107605],"type":"Point"}
}