{
  "type": "Feature",
  "properties": {
    "iso:country":"ES",
    "sg:address":"Carrer de Cerdanya, 52",
    "sg:city":"S. Boi Llobregat",
    "sg:orig_category":"Arreglo, Reparaci\u00d3n, Piezas Sueltas De Televisi\u00d3n, V\u00cddeo, Hi",
    "sg:phone":"+34 936 54 06 76",
    "sg:postcode":"08830",
    "sg:province":"Barcelona",
    "wof:name":"Cano Montes Francisco",
    "wof:placetype":"venue"
},
  "geometry": {"coordinates":[2.0408070087,41.3416366577],"type":"Point"}
}