{
  "type": "Feature",
  "properties": {
    "addr:full":"Ctra Moledo, 12 Moledo Pontevedra 36214",
    "addr:housenumber":"12",
    "addr:postcode":"36214",
    "addr:street":"Ctra Moledo",
    "iso:country":"ES",
    "sg:address":"Ctra Moledo, 12",
    "sg:city":"Moledo",
    "sg:orig_category":"Aceros Inoxidables",
    "sg:phone":"+34 986 49 31 08",
    "sg:postcode":"36214",
    "sg:province":"Pontevedra",
    "wof:name":"Inoxidables Del Atlantico S.l.",
    "wof:placetype":"venue"
},
  "geometry": {"coordinates":[-8.7059106827,42.2124443054],"type":"Point"}
}