{
  "type": "Feature",
  "properties": {
    "iso:country":"ES",
    "sg:address":"Rond Outeiro, 269",
    "sg:city":"Coru\u00d1a",
    "sg:orig_category":"Centros Empresariales",
    "sg:phone":"+34 981 14 47 63",
    "sg:postcode":"15011",
    "sg:province":"La Coru\u00f1a",
    "wof:name":"I.g. Documentacion S.l.",
    "wof:placetype":"venue"
},
  "geometry": {"coordinates":[-8.4253797531,43.3729400635],"type":"Point"}
}