{
  "type": "Feature",
  "properties": {
    "addr:full":"Avda Constitucion, 1 Novelda Alicante 03660",
    "addr:housenumber":"1",
    "addr:postcode":"03660",
    "addr:street":"Avda Constitucion",
    "iso:country":"ES",
    "sg:address":"Avda Constitucion, 1",
    "sg:city":"Novelda",
    "sg:orig_category":"Inmobiliaria (agencias)",
    "sg:phone":"+34 965 60 64 56",
    "sg:postcode":"03660",
    "sg:province":"Alicante",
    "wof:name":"Mu\u00f1oz Linares Eloisa",
    "wof:placetype":"venue"
},
  "geometry": {"coordinates":[-0.7678009868,38.3815383911],"type":"Point"}
}