{
  "type": "Feature",
  "properties": {
    "iso:country":"ES",
    "sg:address":"Calle de Deprit Lasa Amadeo, 1",
    "sg:city":"Bilbao",
    "sg:orig_category":"Instalaci\u00d3n, Reparaci\u00d3n De Ascensores Y Montacargas",
    "sg:phone":"+34 944 12 44 11",
    "sg:postcode":"48006",
    "sg:province":"Vizcaya",
    "sg:website":"www.otis.com",
    "wof:name":"Zardoya Otis S. A.",
    "wof:placetype":"venue"
},
  "geometry": {"coordinates":[-2.9165248871,43.2573432922],"type":"Point"}
}