{
  "type": "Feature",
  "properties": {
    "iso:country":"ES",
    "sg:address":"Plaza De Clemente Valverde, 1",
    "sg:city":"Baena",
    "sg:orig_category":"Promotores Constructores",
    "sg:phone":"+34 957 67 06 79",
    "sg:postcode":"14850",
    "sg:province":"C\u00f3rdoba",
    "wof:name":"Torrecilla Pavon Manuel",
    "wof:placetype":"venue"
},
  "geometry": {"coordinates":[-4.3244791031,37.6153717041],"type":"Point"}
}