{
  "type": "Feature",
  "properties": {
    "iso:country":"ES",
    "sg:address":"Calle de Oria, 30",
    "sg:city":"Madrid",
    "sg:orig_category":"Arquitectos",
    "sg:phone":"+34 914 11 34 90",
    "sg:postcode":"28002",
    "sg:province":"Madrid",
    "wof:name":"Mesalles Garcia Gonzalo Santiago",
    "wof:placetype":"venue"
},
  "geometry": {"coordinates":[-3.6811716557,40.4462356567],"type":"Point"}
}