{
  "type": "Feature",
  "properties": {
    "addr:full":"Navas De Tolosa, 21 Iru\u00f1a Navarra 31002",
    "addr:housenumber":"21",
    "addr:postcode":"31002",
    "addr:street":"Navas;Tolosa",
    "iso:country":"ES",
    "sg:address":"Navas De Tolosa, 21",
    "sg:city":"Iru\u00f1a",
    "sg:orig_category":"Doctores En Medicina",
    "sg:phone":"+34 948 22 08 05",
    "sg:postcode":"31002",
    "sg:province":"Navarra",
    "wof:name":"Maravi Poma Elias Enrique",
    "wof:placetype":"venue"
},
  "geometry": {"coordinates":[-1.6493090391,42.8153648376],"type":"Point"}
}