{
  "type": "Feature",
  "properties": {
    "iso:country":"ES",
    "sg:address":"Calle de San Jeronimo Kalea, 20",
    "sg:city":"Erandio",
    "sg:orig_category":"Transporte En General",
    "sg:phone":"+34 944 67 19 21",
    "sg:postcode":"48950",
    "sg:province":"Vizcaya",
    "wof:name":"Puri Gonzalez Crespo",
    "wof:placetype":"venue"
},
  "geometry": {"coordinates":[-2.9747629166,43.3024978638],"type":"Point"}
}