{
  "type": "Feature",
  "properties": {
    "iso:country":"ES",
    "sg:address":"Calle de Fuente El Sol, 2",
    "sg:city":"Valladolid",
    "sg:orig_category":"Asociaciones De Vecinos, Centros De Juventud",
    "sg:phone":"+34 983 37 12 79",
    "sg:postcode":"47009",
    "sg:province":"Valladolid",
    "wof:name":"Confederacion De Centros De Desarrollo Rural",
    "wof:placetype":"venue"
},
  "geometry": {"coordinates":[-4.7335710526,41.66147995],"type":"Point"}
}