{
  "type": "Feature",
  "properties": {
    "iso:country":"ES",
    "sg:address":"Calle de Mayor, 53",
    "sg:city":"Pozoblanco",
    "sg:orig_category":"M\u00c9dicos: Estomatolog\u00cda",
    "sg:phone":"+34 957 77 25 01",
    "sg:postcode":"14400",
    "sg:province":"C\u00f3rdoba",
    "wof:name":"Gallego Aguaron Ramon",
    "wof:placetype":"venue"
},
  "geometry": {"coordinates":[-4.8495440483,38.379989624],"type":"Point"}
}