{
  "type": "Feature",
  "properties": {
    "iso:country":"ES",
    "sg:address":"Calle de Constitucion, 48",
    "sg:city":"Carboneros",
    "sg:orig_category":"Empresas De Desmonte",
    "sg:phone":"+34 953 66 11 91",
    "sg:postcode":"23211",
    "sg:province":"Ja\u00e9n",
    "wof:name":"Maeso Maroto Jose",
    "wof:placetype":"venue"
},
  "geometry": {"coordinates":[-3.6313891411,38.2289848328],"type":"Point"}
}