{
  "type": "Feature",
  "properties": {
    "addr:full":"Avda Roma, 22 Le\u00f3n Le\u00f3n 24001",
    "addr:housenumber":"22",
    "addr:postcode":"24001",
    "addr:street":"Avda Roma;Leo\u0301N",
    "iso:country":"ES",
    "sg:address":"Avda Roma, 22",
    "sg:city":"Le\u00f3n",
    "sg:orig_category":"Ropa Para Se\u00d1oras Y Caballeros (al Por Menor)",
    "sg:phone":"+34 987 27 32 66",
    "sg:postcode":"24001",
    "sg:province":"Le\u00f3n",
    "wof:name":"Martin Berguio Millan",
    "wof:placetype":"venue"
},
  "geometry": {"coordinates":[-5.5774831772,42.5970916748],"type":"Point"}
}