{
  "type": "Feature",
  "properties": {
    "iso:country":"ES",
    "sg:address":"Calle de Gran Via De Colon, 26",
    "sg:city":"Granada",
    "sg:orig_category":"Producci\u00d3n, Distribuci\u00d3n De Gas Butano Y Propano",
    "sg:phone":"+34 958 80 50 42",
    "sg:postcode":"18010",
    "sg:province":"Granada",
    "sg:website":"www.repsolypf.com",
    "wof:name":"Repsol Ypf S.a.",
    "wof:placetype":"venue"
},
  "geometry": {"coordinates":[-3.5988690853,37.1783256531],"type":"Point"}
}