{
  "type": "Feature",
  "properties": {
    "addr:full":"Calle de Alarcon, 27 Valdemoro Madrid 28340",
    "addr:housenumber":"27",
    "addr:postcode":"28340",
    "addr:street":"Calle De Alarcon",
    "iso:country":"ES",
    "sg:address":"Calle de Alarcon, 27",
    "sg:city":"Valdemoro",
    "sg:orig_category":"Restaurantes",
    "sg:phone":"+34 918 95 69 74",
    "sg:postcode":"28340",
    "sg:province":"Madrid",
    "wof:name":"Carianchi S.l.",
    "wof:placetype":"venue"
},
  "geometry": {"coordinates":[-3.6761920452,40.1907539368],"type":"Point"}
}