{
  "type": "Feature",
  "properties": {
    "iso:country":"ES",
    "sg:address":"Avda Zarcilla De La, 64",
    "sg:city":"Palma Condado",
    "sg:orig_category":"Carnicer\u00cdas, Carnicer\u00cdas",
    "sg:phone":"+34 959 40 03 21",
    "sg:postcode":"21700",
    "sg:province":"Huelva",
    "wof:name":"Tenepal Ramos Bolos S.l.",
    "wof:placetype":"venue"
},
  "geometry": {"coordinates":[-6.556842804,37.3890342712],"type":"Point"}
}