{
  "type": "Feature",
  "properties": {
    "addr:full":"Ctra Granada, 20 Purullena Granada 18519",
    "addr:housenumber":"20",
    "addr:postcode":"18519",
    "addr:street":"Ctra Granada",
    "iso:country":"ES",
    "sg:address":"Ctra Granada, 20",
    "sg:city":"Purullena",
    "sg:orig_category":"Art\u00cdculos Funerarios (al Por Menor)",
    "sg:phone":"+34 958 69 06 10",
    "sg:postcode":"18519",
    "sg:province":"Granada",
    "wof:name":"Ferreira Y Rubio S.l.",
    "wof:placetype":"venue"
},
  "geometry": {"coordinates":[-3.1901619434,37.3168792725],"type":"Point"}
}