{
  "type": "Feature",
  "properties": {
    "iso:country":"ES",
    "sg:address":"Carrer de Arago, 655",
    "sg:city":"Barcelona",
    "sg:orig_category":"Muebles, Minoristas",
    "sg:phone":"+34 932 65 90 07",
    "sg:postcode":"08026",
    "sg:province":"Barcelona",
    "wof:name":"Diaz Soler Xavier",
    "wof:placetype":"venue"
},
  "geometry": {"coordinates":[2.1904609203,41.4116287231],"type":"Point"}
}