{
  "type": "Feature",
  "properties": {
    "iso:country":"ES",
    "sg:address":"Calle de Arquitecto Rafael Leoz, 18",
    "sg:city":"Madrid",
    "sg:orig_category":"Asesor\u00cda Sobre Comunicaci\u00d3n De Empresas",
    "sg:phone":"+34 913 57 06 33",
    "sg:postcode":"28023",
    "sg:province":"Madrid",
    "wof:name":"Nieto Jimenez Jose Ramon",
    "wof:placetype":"venue"
},
  "geometry": {"coordinates":[-3.7913322449,40.4504776001],"type":"Point"}
}