{
  "type": "Feature",
  "properties": {
    "addr:full":"Calle de Eras Bajas, 5 Huetor-tajar Granada 18360",
    "addr:housenumber":"5",
    "addr:postcode":"18360",
    "addr:street":"Calle De Eras Bajas",
    "iso:country":"ES",
    "sg:address":"Calle de Eras Bajas, 5",
    "sg:city":"Huetor-tajar",
    "sg:orig_category":"Cajas De Ahorro",
    "sg:phone":"+34 958 33 22 51",
    "sg:postcode":"18360",
    "sg:province":"Granada",
    "sg:website":"www.unicaja.es",
    "wof:name":"Unicaja",
    "wof:placetype":"venue"
},
  "geometry": {"coordinates":[-4.0472230911,37.196105957],"type":"Point"}
}