{
  "type": "Feature",
  "properties": {
    "addr:full":"Calle de Doctor Jesus Quesada Sanz, 5 San Andres Murcia 30005",
    "addr:housenumber":"5",
    "addr:postcode":"30005",
    "addr:street":"Calle De Doctor Jesus Quesada Sanz",
    "iso:country":"ES",
    "sg:address":"Calle de Doctor Jesus Quesada Sanz, 5",
    "sg:city":"San Andres",
    "sg:orig_category":"Cajas De Ahorro",
    "sg:phone":"+34 968 28 01 39",
    "sg:postcode":"30005",
    "sg:province":"Murcia",
    "wof:name":"Caja De Ahorros Del Mediterraneo",
    "wof:placetype":"venue"
},
  "geometry": {"coordinates":[-1.1389089823,37.9867668152],"type":"Point"}
}