{
  "type": "Feature",
  "properties": {
    "addr:full":"Pl. Tren, 7 Sa Pobla Islas Baleares 07420",
    "addr:postcode":"07420",
    "addr:street":"Tren",
    "iso:country":"ES",
    "sg:address":"Pl. Tren, 7",
    "sg:city":"Sa Pobla",
    "sg:orig_category":"Institutos De Belleza",
    "sg:phone":"+34 971 54 22 32",
    "sg:postcode":"07420",
    "sg:province":"Islas Baleares",
    "wof:name":"Ginard Caldes Catalina Maria",
    "wof:placetype":"venue"
},
  "geometry": {"coordinates":[3.0275802612,39.7876853943],"type":"Point"}
}