{
  "type": "Feature",
  "properties": {
    "iso:country":"ES",
    "sg:address":"Major, 68",
    "sg:city":"S. Jaume Enveja",
    "sg:orig_category":"Molduras, Junquillos, Listones Y Molduras Perforadas",
    "sg:phone":"+34 977 46 82 40",
    "sg:postcode":"43877",
    "sg:province":"Tarragona",
    "wof:name":"Llambrich Sanz Mauricio",
    "wof:placetype":"venue"
},
  "geometry": {"coordinates":[0.7169960141,40.7058906555],"type":"Point"}
}