{
  "type": "Feature",
  "properties": {
    "addr:full":"Carrer de Segle Xx, 19 Gava Barcelona 08850",
    "addr:housenumber":"19",
    "addr:postcode":"08850",
    "addr:street":"Carrer De Segle Xx",
    "iso:country":"ES",
    "sg:address":"Carrer de Segle Xx, 19",
    "sg:city":"Gava",
    "sg:orig_category":"Electricidad: Instaladores",
    "sg:phone":"+34 936 62 37 94",
    "sg:postcode":"08850",
    "sg:province":"Barcelona",
    "wof:name":"Tomas Martinez Jose",
    "wof:placetype":"venue"
},
  "geometry": {"coordinates":[1.9972449541,41.3089027405],"type":"Point"}
}