{
  "type": "Feature",
  "properties": {
    "addr:full":"Carr Vilavella, 166 Villarreal Castell\u00f3n 12540",
    "addr:housenumber":"166",
    "addr:postcode":"12540",
    "addr:street":"Carr Vilavella",
    "iso:country":"ES",
    "sg:address":"Carr Vilavella, 166",
    "sg:city":"Villarreal",
    "sg:orig_category":"Fabricaci\u00d3n De Moldes Y Modelos",
    "sg:phone":"+34 964 52 06 72",
    "sg:postcode":"12540",
    "sg:province":"Castell\u00f3n",
    "wof:name":"Rectificados Ceramicos S.l.",
    "wof:placetype":"venue"
},
  "geometry": {"coordinates":[-0.0952939987,39.9453048706],"type":"Point"}
}