{
  "type": "Feature",
  "properties": {
    "iso:country":"ES",
    "sg:address":"Calle de Dean Silverio, 32",
    "sg:city":"Realejo Alto",
    "sg:orig_category":"Empresas De Carpinter\u00cda De Madera",
    "sg:phone":"+34 922 34 50 19",
    "sg:postcode":"38410",
    "sg:province":"Santa Cruz De Tenerife",
    "wof:name":"Vega Garcia Carmelo",
    "wof:placetype":"venue"
},
  "geometry": {"coordinates":[-16.5807914734,28.3678131104],"type":"Point"}
}