{
  "type": "Feature",
  "properties": {
    "iso:country":"ES",
    "sg:address":"Alfonso El Batallador, 14",
    "sg:city":"Iru\u00f1a",
    "sg:orig_category":"Ense\u00d1anza: Comercio, Gesti\u00d3n, Inform\u00c1tica",
    "sg:phone":"+34 948 17 25 15",
    "sg:postcode":"31007",
    "sg:province":"Navarra",
    "sg:website":"www.personalsystem.es",
    "wof:name":"Personal Systen Centro Formacion S.l.",
    "wof:placetype":"venue"
},
  "geometry": {"coordinates":[-1.651154995,42.8035163879],"type":"Point"}
}