{
  "type": "Feature",
  "properties": {
    "iso:country":"ES",
    "sg:address":"Carrer de Barcelona (de), 62",
    "sg:city":"Salou",
    "sg:orig_category":"Colchones (fabricaci\u00d3n, Al Por Mayor, Al Por Menor)",
    "sg:phone":"+34 977 35 28 76",
    "sg:postcode":"43840",
    "sg:province":"Tarragona",
    "wof:name":"Jansa Fortuny Joan Albert",
    "wof:placetype":"venue"
},
  "geometry": {"coordinates":[1.1319390535,41.0825767517],"type":"Point"}
}