{
  "type": "Feature",
  "properties": {
    "addr:full":"Iturrama, 45 Iru\u00f1a Navarra 31007",
    "addr:housenumber":"45",
    "addr:postcode":"31007",
    "addr:street":"Iturrama",
    "iso:country":"ES",
    "sg:address":"Iturrama, 45",
    "sg:city":"Iru\u00f1a",
    "sg:orig_category":"Fabrica, Negocio De Vidrieras, Productos Vidriados Y Espejos",
    "sg:phone":"+34 948 17 56 07",
    "sg:postcode":"31007",
    "sg:province":"Navarra",
    "wof:name":"Saenz Mayayo Fermin",
    "wof:placetype":"venue"
},
  "geometry": {"coordinates":[-1.6568599939,42.806427002],"type":"Point"}
}