{
  "type": "Feature",
  "properties": {
    "addr:full":"Carrer de Cavallers, 10 Pedreguer Alicante 03750",
    "addr:housenumber":"10",
    "addr:postcode":"03750",
    "addr:street":"Carrer De Cavallers",
    "iso:country":"ES",
    "sg:address":"Carrer de Cavallers, 10",
    "sg:city":"Pedreguer",
    "sg:orig_category":"Pescader\u00cdas (al Por Menor)",
    "sg:phone":"+34 965 76 07 21",
    "sg:postcode":"03750",
    "sg:province":"Alicante",
    "wof:name":"Gilabert Noguera Jesusa",
    "wof:placetype":"venue"
},
  "geometry": {"coordinates":[0.0337509997,38.7939605713],"type":"Point"}
}