{
  "type": "Feature",
  "properties": {
    "addr:full":"Calle de San Sebastian, 58 Ubrique C\u00e1diz 11600",
    "addr:housenumber":"58",
    "addr:postcode":"11600",
    "addr:street":"Calle De San Sebastian;Ca\u0301Diz",
    "iso:country":"ES",
    "sg:address":"Calle de San Sebastian, 58",
    "sg:city":"Ubrique",
    "sg:orig_category":"Ropa Para Se\u00d1oras Y Caballeros (al Por Menor)",
    "sg:phone":"+34 956 46 02 78",
    "sg:postcode":"11600",
    "sg:province":"C\u00e1diz",
    "wof:name":"Aivar Olivares Francisco",
    "wof:placetype":"venue"
},
  "geometry": {"coordinates":[-5.4451160431,36.6749191284],"type":"Point"}
}