{
  "type": "Feature",
  "properties": {
    "addr:full":"Rua Pintor Seijo Rubio, S/n Betanzos La Coru\u00f1a 15300",
    "addr:housenumber":"s / n",
    "addr:postcode":"15300",
    "addr:street":"Rua Pintor Seijo Rubio;La",
    "iso:country":"ES",
    "sg:address":"Rua Pintor Seijo Rubio, S/n",
    "sg:city":"Betanzos",
    "sg:orig_category":"Alimentaci\u00d3n General (al Por Menor)",
    "sg:phone":"+34 981 77 40 61",
    "sg:postcode":"15300",
    "sg:province":"La Coru\u00f1a",
    "wof:name":"Manuela Garcia Presedo Y Otra S.c",
    "wof:placetype":"venue"
},
  "geometry": {"coordinates":[-8.2102937698,43.2775993347],"type":"Point"}
}