{
  "type": "Feature",
  "properties": {
    "addr:full":"Carrer de Governador Gonzalez, 21 Tarragona Tarragona 43001",
    "addr:housenumber":"21",
    "addr:postcode":"43001",
    "addr:street":"Carrer De Governador Gonzalez",
    "iso:country":"ES",
    "sg:address":"Carrer de Governador Gonzalez, 21",
    "sg:city":"Tarragona",
    "sg:orig_category":"Concepci\u00d3n Y Realizaci\u00d3n De Maquetas Profesionales Y Prototipos",
    "sg:phone":"+34 977 24 37 11",
    "sg:postcode":"43001",
    "sg:province":"Tarragona",
    "wof:name":"Martinez Palones Concepcion",
    "wof:placetype":"venue"
},
  "geometry": {"coordinates":[1.2504349947,41.1153678894],"type":"Point"}
}