{
  "type": "Feature",
  "properties": {
    "addr:full":"Calle de Corredera, 25 San Mateo Murcia 30800",
    "addr:housenumber":"25",
    "addr:postcode":"30800",
    "addr:street":"Calle De Corredera",
    "iso:country":"ES",
    "sg:address":"Calle de Corredera, 25",
    "sg:city":"San Mateo",
    "sg:orig_category":"M\u00c9dicos: Estomatolog\u00cda",
    "sg:phone":"+34 968 47 74 12",
    "sg:postcode":"30800",
    "sg:province":"Murcia",
    "wof:name":"Alcazar Carrillo Juan Francisco",
    "wof:placetype":"venue"
},
  "geometry": {"coordinates":[-1.1298867464,37.9834747314],"type":"Point"}
}