{
  "type": "Feature",
  "properties": {
    "addr:full":"Calle de Ronda De Poniente, S/n Chiclana De La Frontera C\u00e1diz 11130",
    "addr:housenumber":"s / n",
    "addr:postcode":"11130",
    "addr:street":"Calle De Ronda De Poniente",
    "iso:country":"ES",
    "sg:address":"Calle de Ronda De Poniente, S/n",
    "sg:city":"Chiclana De La Frontera",
    "sg:orig_category":"Art\u00cdculos De Limpieza Y De Cocina (fabricaci\u00d3n, Al Por Mayor)",
    "sg:phone":"+34 956 53 31 10",
    "sg:postcode":"11130",
    "sg:province":"C\u00e1diz",
    "wof:name":"Proyectos Y Formulaciones Md10 S.l",
    "wof:placetype":"venue"
},
  "geometry": {"coordinates":[-6.1447038651,36.4212188721],"type":"Point"}
}