{
  "type": "Feature",
  "properties": {
    "addr:full":"Av Europa(base Dos Mil), S/n Lorqui Murcia 30564",
    "addr:housenumber":"s",
    "addr:postcode":"30564",
    "addr:street":"Av Europa Base Dos Mil;/ N",
    "iso:country":"ES",
    "sg:address":"Av Europa(base Dos Mil), S/n",
    "sg:city":"Lorqui",
    "sg:orig_category":"Fabricaci\u00d3n, Instalaci\u00d3n Y Reparaci\u00d3n De Bombas",
    "sg:phone":"+34 968 67 67 06",
    "sg:postcode":"30564",
    "sg:province":"Murcia",
    "wof:name":"Emuse",
    "wof:placetype":"venue"
},
  "geometry": {"coordinates":[-1.2293390036,38.1026992798],"type":"Point"}
}