{
  "type": "Feature",
  "properties": {
    "addr:full":"Carrer de Barcelona (de), 28 Salou Tarragona 43840",
    "addr:housenumber":"28",
    "addr:postcode":"43840",
    "addr:street":"Carrer De Barcelona De",
    "iso:country":"ES",
    "sg:address":"Carrer de Barcelona (de), 28",
    "sg:city":"Salou",
    "sg:orig_category":"Servicios De Telecomunicaciones",
    "sg:phone":"+34 977 35 04 21",
    "sg:postcode":"43840",
    "sg:province":"Tarragona",
    "wof:name":"Touba-cominications Ii",
    "wof:placetype":"venue"
},
  "geometry": {"coordinates":[1.131180048,41.0789718628],"type":"Point"}
}