{
  "type": "Feature",
  "properties": {
    "addr:full":"Carr Sant Vicent Ferrer, 6 Mas Dels Frares Castell\u00f3n 12560",
    "addr:housenumber":"6",
    "addr:postcode":"12560",
    "addr:street":"Carr Sant Vicent Ferrer;Castello\u0301N",
    "iso:country":"ES",
    "sg:address":"Carr Sant Vicent Ferrer, 6",
    "sg:city":"Mas Dels Frares",
    "sg:orig_category":"Alimentaci\u00d3n General (al Por Menor)",
    "sg:phone":"+34 964 30 28 05",
    "sg:postcode":"12560",
    "sg:province":"Castell\u00f3n",
    "wof:name":"Consum Sociedad Cooperativa Limitada",
    "wof:placetype":"venue"
},
  "geometry": {"coordinates":[0.0590550005,40.0523414612],"type":"Point"}
}