{
  "type": "Feature",
  "properties": {
    "addr:full":"Avda Jose Mesa Y Lopez, 80 Palmas De Gran Canaria Las Palmas 35010",
    "addr:postcode":"35010",
    "addr:street":"Avda Jose Mesa Y Lopez 80",
    "iso:country":"ES",
    "sg:address":"Avda Jose Mesa Y Lopez, 80",
    "sg:city":"Palmas De Gran Canaria",
    "sg:orig_category":"Supermercados Y Hipermercados",
    "sg:phone":"+34 928 22 27 58",
    "sg:postcode":"35010",
    "sg:province":"Las Palmas",
    "wof:name":"Dinosol Supermercados S.l.",
    "wof:placetype":"venue"
},
  "geometry": {"coordinates":[-15.4376249313,28.1326618195],"type":"Point"}
}