{
  "type": "Feature",
  "properties": {
    "iso:country":"ES",
    "sg:address":"Carrer de Pere Iv, 558",
    "sg:city":"Barcelona",
    "sg:orig_category":"Lavado, Limpieza De Veh\u00cdculos",
    "sg:phone":"+34 932 66 20 49",
    "sg:postcode":"08019",
    "sg:province":"Barcelona",
    "wof:name":"Auto Shoping Center S.l.",
    "wof:placetype":"venue"
},
  "geometry": {"coordinates":[2.2095999718,41.4182090759],"type":"Point"}
}