{
  "type": "Feature",
  "properties": {
    "iso:country":"ES",
    "sg:address":"Calle de Luis Sauquillo, Km. 0000,7",
    "sg:city":"Fuenlabrada",
    "sg:orig_category":"Empresas De Carpinter\u00cda",
    "sg:phone":"+34 916 90 91 02",
    "sg:postcode":"28944",
    "sg:province":"Madrid",
    "wof:name":"Aluminios Guzman S.l.",
    "wof:placetype":"venue"
},
  "geometry": {"coordinates":[-3.7954804897,40.2837028503],"type":"Point"}
}