{
  "type": "Feature",
  "properties": {
    "addr:full":"Luga Poligono Navas, S/n Medina Pomar Burgos 09500",
    "addr:housenumber":"s / n",
    "addr:postcode":"09500",
    "addr:street":"Poligono Navas",
    "iso:country":"ES",
    "sg:address":"Luga Poligono Navas, S/n",
    "sg:city":"Medina Pomar",
    "sg:orig_category":"Producci\u00d3n, Comercio De Cereales",
    "sg:phone":"+34 947 19 16 47",
    "sg:postcode":"09500",
    "sg:province":"Burgos",
    "wof:name":"Almacenes Huidobro S. A.",
    "wof:placetype":"venue"
},
  "geometry": {"coordinates":[-3.4775261879,42.94115448],"type":"Point"}
}