{
  "type": "Feature",
  "properties": {
    "iso:country":"ES",
    "sg:address":"Plaz Marron, 2",
    "sg:city":"Toledo",
    "sg:orig_category":"Asesor\u00cdas Y Estudios Financieros",
    "sg:phone":"+34 925 25 43 17",
    "sg:postcode":"45002",
    "sg:province":"Toledo",
    "wof:name":"Izquierdo Perez Carmen",
    "wof:placetype":"venue"
},
  "geometry": {"coordinates":[-4.025138855,39.8618774414],"type":"Point"}
}