{
  "type": "Feature",
  "properties": {
    "addr:full":"C\u00f1o. Pi\u00f1eiro, 26 Aldan Pontevedra 36946",
    "addr:housenumber":"26",
    "addr:postcode":"36946",
    "addr:street":"Pin\u0303Eiro",
    "iso:country":"ES",
    "sg:address":"C\u00f1o. Pi\u00f1eiro, 26",
    "sg:city":"Aldan",
    "sg:orig_category":"Publicidad (soportes Y Gesti\u00d3n)",
    "sg:phone":"+34 986 32 85 02",
    "sg:postcode":"36946",
    "sg:province":"Pontevedra",
    "wof:name":"Promociones E Inversiones Aldan S.l.",
    "wof:placetype":"venue"
},
  "geometry": {"coordinates":[-8.8023338318,42.2950210571],"type":"Point"}
}