{
  "type": "Feature",
  "properties": {
    "iso:country":"ES",
    "sg:address":"Calle de Puente, 11",
    "sg:city":"Fuentepelayo",
    "sg:orig_category":"Delegados, Agentes De Tr\u00c1nsito, Auxiliares De Transporte Internacional",
    "sg:phone":"+34 921 57 40 16",
    "sg:postcode":"40260",
    "sg:province":"Segovia",
    "wof:name":"Cardaba Tejedor Jesus",
    "wof:placetype":"venue"
},
  "geometry": {"coordinates":[-4.1760988235,41.2223205566],"type":"Point"}
}