{
  "type": "Feature",
  "properties": {
    "addr:full":"Calle de Antonio Machado, 22 Zafarraya Granada 18128",
    "addr:housenumber":"22",
    "addr:postcode":"18128",
    "addr:street":"Calle De Antonio Machado",
    "iso:country":"ES",
    "sg:address":"Calle de Antonio Machado, 22",
    "sg:city":"Zafarraya",
    "sg:orig_category":"Frutas Y Legumbres Frescas (al Por Mayor)",
    "sg:phone":"+34 958 36 28 51",
    "sg:postcode":"18128",
    "sg:province":"Granada",
    "wof:name":"Hortalizas Montero Martin S.l",
    "wof:placetype":"venue"
},
  "geometry": {"coordinates":[-4.1442022324,36.9730834961],"type":"Point"}
}