{
  "type": "Feature",
  "properties": {
    "iso:country":"ES",
    "sg:address":"Carr Pau Picasso, 22",
    "sg:city":"Badalona",
    "sg:orig_category":"Ense\u00d1anza: Comercio, Gesti\u00d3n, Inform\u00c1tica",
    "sg:phone":"+34 934 60 02 76",
    "sg:postcode":"08917",
    "sg:province":"Barcelona",
    "wof:name":"Centre Pau Picasso S.cv",
    "wof:placetype":"venue"
},
  "geometry": {"coordinates":[2.2267680168,41.4495697021],"type":"Point"}
}