{
  "type": "Feature",
  "properties": {
    "iso:country":"ES",
    "sg:address":"Calle de Parla, 5",
    "sg:city":"Ventorro Del Cano",
    "sg:orig_category":"Ebanister\u00cda",
    "sg:phone":"+34 916 33 44 26",
    "sg:postcode":"28925",
    "sg:province":"Madrid",
    "wof:name":"Carpinteria-ebanisteria Rafael Rodriguez S.l.",
    "wof:placetype":"venue"
},
  "geometry": {"coordinates":[-3.821844101,40.374168396],"type":"Point"}
}