{
  "type": "Feature",
  "properties": {
    "addr:full":"Calle de Principe De Asturias, S/n Sevilla Sevilla 41016",
    "addr:housenumber":"s / n",
    "addr:postcode":"41016",
    "addr:street":"Calle De Principe De Asturias",
    "iso:country":"ES",
    "sg:address":"Calle de Principe De Asturias, S/n",
    "sg:city":"Sevilla",
    "sg:orig_category":"Centros De Educaci\u00d3n Especial",
    "sg:phone":"+34 954 67 08 08",
    "sg:postcode":"41016",
    "sg:province":"Sevilla",
    "wof:name":"Junta De Andalucia Consejeria De Educacion",
    "wof:placetype":"venue"
},
  "geometry": {"coordinates":[-5.9109339714,37.3837966919],"type":"Point"}
}