{
  "type": "Feature",
  "properties": {
    "iso:country":"ES",
    "sg:address":"A Igrexa, 8",
    "sg:city":"Sta. Maria De Xeve",
    "sg:orig_category":"Centros De Coordinaci\u00d3n",
    "sg:phone":"+34 986 87 95 18",
    "sg:postcode":"36151",
    "sg:province":"Pontevedra",
    "wof:name":"Gasca Gabas Jesus Andres",
    "wof:placetype":"venue"
},
  "geometry": {"coordinates":[-8.6209402084,42.4811553955],"type":"Point"}
}