{
  "type": "Feature",
  "properties": {
    "addr:full":"Carrer de Mas De Macia Vila, 35 Reus Tarragona 43204",
    "addr:housenumber":"35",
    "addr:postcode":"43204",
    "addr:street":"Carrer De Mas De Macia Vila",
    "iso:country":"ES",
    "sg:address":"Carrer de Mas De Macia Vila, 35",
    "sg:city":"Reus",
    "sg:orig_category":"Peluquer\u00cdas, Peluquer\u00cda Mixta",
    "sg:phone":"+34 977 77 40 15",
    "sg:postcode":"43204",
    "sg:province":"Tarragona",
    "wof:name":"Perez Mimbrero Beatriz",
    "wof:placetype":"venue"
},
  "geometry": {"coordinates":[1.1215490103,41.1484146118],"type":"Point"}
}