{
  "type": "Feature",
  "properties": {
    "iso:country":"ES",
    "sg:address":"Carrer de Sant Miquel (de), 12",
    "sg:city":"Tarragona",
    "sg:orig_category":"Panader\u00cdas, Panader\u00cdas",
    "sg:phone":"+34 977 24 15 95",
    "sg:postcode":"43004",
    "sg:province":"Tarragona",
    "wof:name":"Gomez Lopez Maria Araceli",
    "wof:placetype":"venue"
},
  "geometry": {"coordinates":[1.2492359877,41.1118812561],"type":"Point"}
}