{
  "type": "Feature",
  "properties": {
    "addr:full":"Ctra. Puente Sevilla-celanova, S/n Merca Ourense 32830",
    "addr:housenumber":"s / n",
    "addr:postcode":"32830",
    "addr:street":"Ctra. Puente Sevilla-Celanova",
    "iso:country":"ES",
    "sg:address":"Ctra. Puente Sevilla-celanova, S/n",
    "sg:city":"Merca",
    "sg:orig_category":"Centros De Educaci\u00d3n Especial",
    "sg:phone":"+34 988 26 00 52",
    "sg:postcode":"32830",
    "sg:province":"Ourense",
    "wof:name":"Colegio Nacional De Ense\u00f1anza General Basica",
    "wof:placetype":"venue"
},
  "geometry": {"coordinates":[-7.9057488441,42.2220458984],"type":"Point"}
}