{
  "type": "Feature",
  "properties": {
    "addr:full":"Carrer de Cami Campet, 146 Novelda Alicante 03660",
    "addr:housenumber":"146",
    "addr:postcode":"03660",
    "addr:street":"Carrer De;Campet",
    "iso:country":"ES",
    "sg:address":"Carrer de Cami Campet, 146",
    "sg:city":"Novelda",
    "sg:orig_category":"Negocio De Materiales De Construcci\u00d3n",
    "sg:phone":"+34 965 60 41 66",
    "sg:postcode":"03660",
    "sg:province":"Alicante",
    "wof:name":"Tosanto S.l",
    "wof:placetype":"venue"
},
  "geometry": {"coordinates":[-0.7606589794,38.3827018738],"type":"Point"}
}