{
  "type": "Feature",
  "properties": {
    "iso:country":"ES",
    "sg:address":"Carrer de Marques De Sentmenat, 73",
    "sg:city":"Barcelona",
    "sg:orig_category":"Alquiler De Veh\u00cdculos: Turismos Y Utilitarios",
    "sg:phone":"+34 934 19 49 67",
    "sg:postcode":"08029",
    "sg:province":"Barcelona",
    "wof:name":"Over Rent S.a.",
    "wof:placetype":"venue"
},
  "geometry": {"coordinates":[2.1398611069,41.3854980469],"type":"Point"}
}