{
  "type": "Feature",
  "properties": {
    "iso:country":"ES",
    "sg:address":"Calle de Salva, 4",
    "sg:city":"Valencia",
    "sg:orig_category":"Arquitectos",
    "sg:phone":"+34 963 94 20 04",
    "sg:postcode":"46002",
    "sg:province":"Valencia",
    "wof:name":"Follana Galant Adrian",
    "wof:placetype":"venue"
},
  "geometry": {"coordinates":[-0.3734200001,39.4716644287],"type":"Point"}
}