{
  "type": "Feature",
  "properties": {
    "addr:full":"Calle de Mariano Garcia Abril, 6 Valladolid Valladolid 47014",
    "addr:housenumber":"6",
    "addr:postcode":"47014",
    "addr:street":"Calle De Mariano Garcia Abril",
    "iso:country":"ES",
    "sg:address":"Calle de Mariano Garcia Abril, 6",
    "sg:city":"Valladolid",
    "sg:orig_category":"Alimentaci\u00d3n General (al Por Menor)",
    "sg:phone":"+34 983 33 08 39",
    "sg:postcode":"47014",
    "sg:province":"Valladolid",
    "wof:name":"Blanco Casares Santos",
    "wof:placetype":"venue"
},
  "geometry": {"coordinates":[-4.7355360985,41.6559066772],"type":"Point"}
}