{
  "type": "Feature",
  "properties": {
    "iso:country":"ES",
    "sg:address":"Ctra Molins De Rei, 83",
    "sg:city":"Rubi",
    "sg:orig_category":"Pintura, Barniz, Productos Asimilables (fabricaci\u00d3n, Al Por Mayor)",
    "sg:phone":"+34 935 86 05 80",
    "sg:postcode":"08191",
    "sg:province":"Barcelona",
    "wof:name":"Dupont Powder Coatings Iberica S. L.",
    "wof:placetype":"venue"
},
  "geometry": {"coordinates":[2.0311160088,41.4770927429],"type":"Point"}
}