{
  "type": "Feature",
  "properties": {
    "iso:country":"ES",
    "sg:address":"Alam Mazarredo, 17",
    "sg:city":"Bilbao",
    "sg:orig_category":"Centros De Coordinaci\u00d3n",
    "sg:phone":"+34 944 24 74 37",
    "sg:postcode":"48001",
    "sg:province":"Vizcaya",
    "wof:name":"Ramos Gonzalez Aurora",
    "wof:placetype":"venue"
},
  "geometry": {"coordinates":[-2.9294710159,43.2646331787],"type":"Point"}
}