{
  "type": "Feature",
  "properties": {
    "addr:full":"Calle de Magallanes, 7 Pagan Murcia 30740",
    "addr:housenumber":"7",
    "addr:postcode":"30740",
    "addr:street":"Calle De Magallanes",
    "iso:country":"ES",
    "sg:address":"Calle de Magallanes, 7",
    "sg:city":"Pagan",
    "sg:orig_category":"Molduras, Junquillos, Listones Y Molduras Perforadas",
    "sg:phone":"+34 968 18 61 71",
    "sg:postcode":"30740",
    "sg:province":"Murcia",
    "wof:name":"Santa Maria Bar, S.l.",
    "wof:placetype":"venue"
},
  "geometry": {"coordinates":[-0.7932540178,37.8340911865],"type":"Point"}
}