{
  "type": "Feature",
  "properties": {
    "iso:country":"ES",
    "sg:address":"Avda Constitucion (de La), 4",
    "sg:city":"Pto. Rosario",
    "sg:orig_category":"Piscinas, Accesorios, Suministros (fabricaci\u00d3n, Al Por Mayor)",
    "sg:phone":"+34 928 85 89 01",
    "sg:postcode":"35600",
    "sg:province":"Las Palmas",
    "wof:name":"Gundepol S.l.",
    "wof:placetype":"venue"
},
  "geometry": {"coordinates":[-13.8628635406,28.5000667572],"type":"Point"}
}