{
  "type": "Feature",
  "properties": {
    "addr:full":"Calle de Gavilan, 22 Fuenlabrada Madrid 28946",
    "addr:housenumber":"22",
    "addr:postcode":"28946",
    "addr:street":"Calle De Gavilan",
    "iso:country":"ES",
    "sg:address":"Calle de Gavilan, 22",
    "sg:city":"Fuenlabrada",
    "sg:orig_category":"Fabricaci\u00d3n De Muebles",
    "sg:phone":"+34 916 42 19 24",
    "sg:postcode":"28946",
    "sg:province":"Madrid",
    "wof:name":"Ocio Muebles S.l.",
    "wof:placetype":"venue"
},
  "geometry": {"coordinates":[-3.7648689747,40.2583503723],"type":"Point"}
}