{
  "type": "Feature",
  "properties": {
    "iso:country":"ES",
    "sg:address":"Carrer de Mare De Deu Dels Dolors, 18",
    "sg:city":"Gava",
    "sg:orig_category":"Droguer\u00cdas (al Por Menor)",
    "sg:phone":"+34 936 62 01 70",
    "sg:postcode":"08850",
    "sg:province":"Barcelona",
    "wof:name":"Fuentes Gonzalez Raul",
    "wof:placetype":"venue"
},
  "geometry": {"coordinates":[1.9970580339,41.3065567017],"type":"Point"}
}