{
  "type": "Feature",
  "properties": {
    "addr:full":"Barr Goitioltza, 37 Goitioltza Vizcaya 48196",
    "addr:housenumber":"37",
    "addr:postcode":"48196",
    "addr:street":"Goitioltza",
    "iso:country":"ES",
    "sg:address":"Barr Goitioltza, 37",
    "sg:city":"Goitioltza",
    "sg:orig_category":"Material Y Suministros Para Horticultura, Arboricultura",
    "sg:phone":"+34 944 55 60 58",
    "sg:postcode":"48196",
    "sg:province":"Vizcaya",
    "wof:name":"Comunidad Bienes Lekes C.b.",
    "wof:placetype":"venue"
},
  "geometry": {"coordinates":[-2.8333890438,43.2739181519],"type":"Point"}
}