{
  "type": "Feature",
  "properties": {
    "iso:country":"ES",
    "sg:address":"Calle de Ramon Y Cajal, 9",
    "sg:city":"Pola De Siero",
    "sg:orig_category":"Promotores Constructores",
    "sg:phone":"+34 985 72 17 01",
    "sg:postcode":"33510",
    "sg:province":"Asturias",
    "wof:name":"Luis Gonzalez Riestra S.l.",
    "wof:placetype":"venue"
},
  "geometry": {"coordinates":[-5.6640181541,43.3922615051],"type":"Point"}
}