{
  "type": "Feature",
  "properties": {
    "addr:full":"Calle de Estiradores (los), 7 Segovia Segovia 40005",
    "addr:housenumber":"7",
    "addr:postcode":"40005",
    "addr:street":"Calle De Estiradores Los",
    "iso:country":"ES",
    "sg:address":"Calle de Estiradores (los), 7",
    "sg:city":"Segovia",
    "sg:orig_category":"Fabricaci\u00d3n De Enlosados, Soler\u00cdas",
    "sg:phone":"+34 921 43 41 58",
    "sg:postcode":"40005",
    "sg:province":"Segovia",
    "wof:name":"Salinas Perlado Carlos",
    "wof:placetype":"venue"
},
  "geometry": {"coordinates":[-4.1171870232,40.9444503784],"type":"Point"}
}