{
  "type": "Feature",
  "properties": {
    "addr:full":"Calle de Cervantes, 17 Ejea De Los Caballeros Zaragoza 50600",
    "addr:housenumber":"17",
    "addr:postcode":"50600",
    "addr:street":"Calle De Cervantes",
    "iso:country":"ES",
    "sg:address":"Calle de Cervantes, 17",
    "sg:city":"Ejea De Los Caballeros",
    "sg:orig_category":"Empresas De Carpinter\u00cda De Madera",
    "sg:phone":"+34 976 66 25 65",
    "sg:postcode":"50600",
    "sg:province":"Zaragoza",
    "wof:name":"Perez Betore Vicente",
    "wof:placetype":"venue"
},
  "geometry": {"coordinates":[-1.136469245,42.1251716614],"type":"Point"}
}