{
  "type": "Feature",
  "properties": {
    "addr:full":"Calle de Andalucia, 27 Alaquas Valencia 46970",
    "addr:housenumber":"27",
    "addr:postcode":"46970",
    "addr:street":"Calle De Andalucia",
    "iso:country":"ES",
    "sg:address":"Calle de Andalucia, 27",
    "sg:city":"Alaquas",
    "sg:orig_category":"Empresas De Impermeabilizaci\u00d3n",
    "sg:phone":"+34 961 51 48 57",
    "sg:postcode":"46970",
    "sg:province":"Valencia",
    "wof:name":"Cifo Carrascosa Jose Luis",
    "wof:placetype":"venue"
},
  "geometry": {"coordinates":[-0.4192894101,39.4782180786],"type":"Point"}
}