{
  "type": "Feature",
  "properties": {
    "iso:country":"ES",
    "sg:address":"Avda Generalisimo, 12",
    "sg:city":"Almunia De Do\u00e7a Godina",
    "sg:orig_category":"Hosteler\u00cda, Empleados",
    "sg:phone":"+34 976 81 32 36",
    "sg:postcode":"50100",
    "sg:province":"Zaragoza",
    "sg:website":"www.airesdearagon.com",
    "wof:name":"Hostelera Horna Laguna S.l.",
    "wof:placetype":"venue"
},
  "geometry": {"coordinates":[-1.3779189587,41.4772033691],"type":"Point"}
}