{
  "type": "Feature",
  "properties": {
    "addr:full":"Carrer de Santa Maria, 22 S. Cugat Valles Barcelona 08172",
    "addr:housenumber":"22",
    "addr:postcode":"08172",
    "addr:street":"Carrer De Santa Maria;S. Cugat Valles Barcelona",
    "iso:country":"ES",
    "sg:address":"Carrer de Santa Maria, 22",
    "sg:city":"S. Cugat Valles",
    "sg:orig_category":"Molduras, Junquillos, Listones Y Molduras Perforadas",
    "sg:phone":"+34 936 74 08 67",
    "sg:postcode":"08172",
    "sg:province":"Barcelona",
    "wof:name":"Briatore Biarge Guillermo",
    "wof:placetype":"venue"
},
  "geometry": {"coordinates":[2.0815329552,41.471282959],"type":"Point"}
}