{
  "type": "Feature",
  "properties": {
    "iso:country":"ES",
    "sg:address":"Carrer de Carme, 74",
    "sg:city":"Malgrat Mar",
    "sg:orig_category":"Animales (al Por Menor)",
    "sg:phone":"+34 937 61 29 22",
    "sg:postcode":"08380",
    "sg:province":"Barcelona",
    "wof:name":"Bosch Fernandez Francesc Xavier",
    "wof:placetype":"venue"
},
  "geometry": {"coordinates":[2.7396900654,41.6447715759],"type":"Point"}
}