{
  "type": "Feature",
  "properties": {
    "iso:country":"ES",
    "sg:address":"Pl. De La Villa, 17",
    "sg:city":"Torreperogil",
    "sg:orig_category":"Iglesia Cat\u00d3lica",
    "sg:phone":"+34 953 77 60 33",
    "sg:postcode":"23320",
    "sg:province":"Ja\u00e9n",
    "wof:name":"Parroquia Santa Maria La Mayor",
    "wof:placetype":"venue"
},
  "geometry": {"coordinates":[-3.2879889011,38.0344009399],"type":"Point"}
}