{
  "type": "Feature",
  "properties": {
    "iso:country":"ES",
    "sg:address":"Calle de Corredera Baja De San Pablo, 47",
    "sg:city":"Madrid",
    "sg:orig_category":"Transportes Por Carretera: Lotes Completos, Mercanc\u00cdas Diversas",
    "sg:phone":"+34 915 21 96 40",
    "sg:postcode":"28004",
    "sg:province":"Madrid",
    "wof:name":"Lin Cai Xiu-hao",
    "wof:placetype":"venue"
},
  "geometry": {"coordinates":[-3.7027342319,40.4233207703],"type":"Point"}
}