{
  "type": "Feature",
  "properties": {
    "addr:full":"Avda Doctor Arsenio Corral, Km. 0002,0 Cenicero La Rioja 26350",
    "addr:postcode":"26350",
    "addr:street":"Avda Doctor Arsenio Corral Km. 0002,0;Rioja",
    "iso:country":"ES",
    "sg:address":"Avda Doctor Arsenio Corral, Km. 0002,0",
    "sg:city":"Cenicero",
    "sg:orig_category":"Tapones Y Art\u00cdculos De Corcho",
    "sg:phone":"+34 941 45 44 01",
    "sg:postcode":"26350",
    "sg:province":"La Rioja",
    "wof:name":"Corkvino S.l.",
    "wof:placetype":"venue"
},
  "geometry": {"coordinates":[-2.6481490135,42.4817581177],"type":"Point"}
}