{
  "type": "Feature",
  "properties": {
    "addr:full":"Avda Callejas, S/n Villaviciosa Asturias 33300",
    "addr:housenumber":"s / n",
    "addr:postcode":"33300",
    "addr:street":"Callejas",
    "iso:country":"ES",
    "sg:address":"Avda Callejas, S/n",
    "sg:city":"Villaviciosa",
    "sg:orig_category":"Polideportivos",
    "sg:phone":"+34 985 89 12 04",
    "sg:postcode":"33300",
    "sg:province":"Asturias",
    "wof:name":"Ayuntamiento De Villaviciosa Polideportivo Municipal",
    "wof:placetype":"venue"
},
  "geometry": {"coordinates":[-5.4329109192,43.4858283997],"type":"Point"}
}