{
  "type": "Feature",
  "properties": {
    "addr:full":"Calle de Carretas, 19 Madrid Madrid 28012",
    "addr:housenumber":"19",
    "addr:postcode":"madrid;28012",
    "addr:street":"Calle De Carretas",
    "iso:country":"ES",
    "sg:address":"Calle de Carretas, 19",
    "sg:city":"Madrid",
    "sg:orig_category":"Estilistas Y Estudios De Estilo De Corte Y Confecci\u00d3n",
    "sg:phone":"+34 915 21 04 01",
    "sg:postcode":"28012",
    "sg:province":"Madrid",
    "wof:name":"Bandera Verde Iberica S.a.",
    "wof:placetype":"venue"
},
  "geometry": {"coordinates":[-3.7031030655,40.4156951904],"type":"Point"}
}