{
  "type": "Feature",
  "properties": {
    "iso:country":"ES",
    "sg:address":"Calle de Acacio Gutierrez, 61",
    "sg:city":"Suances",
    "sg:orig_category":"Bares, Piano",
    "sg:phone":"+34 942 81 05 33",
    "sg:postcode":"39340",
    "sg:province":"Cantabria",
    "wof:name":"Delgado Arias Emilio",
    "wof:placetype":"venue"
},
  "geometry": {"coordinates":[-4.0444498062,43.4380912781],"type":"Point"}
}