{
  "type": "Feature",
  "properties": {
    "iso:country":"ES",
    "sg:address":"Calle de Jorge Torner, 17",
    "sg:city":"Cuenca",
    "sg:orig_category":"Institutos De Belleza",
    "sg:phone":"+34 969 23 35 60",
    "sg:postcode":"16004",
    "sg:province":"Cuenca",
    "wof:name":"Estetica Esperanza S.l.l.",
    "wof:placetype":"venue"
},
  "geometry": {"coordinates":[-2.1342260838,40.0679359436],"type":"Point"}
}