{
  "type": "Feature",
  "properties": {
    "iso:country":"ES",
    "sg:address":"Rua Xunqueira (a), S/n",
    "sg:city":"Vilagarcia",
    "sg:orig_category":"Trajes Y Adornos De Boda (confecci\u00d3n, Al Por Menor)",
    "sg:phone":"+34 986 50 67 20",
    "sg:postcode":"36600",
    "sg:province":"Pontevedra",
    "wof:name":"Fresco Gonzalez Ana Maria",
    "wof:placetype":"venue"
},
  "geometry": {"coordinates":[-8.7652978897,42.5917396545],"type":"Point"}
}