{
  "type": "Feature",
  "properties": {
    "iso:country":"ES",
    "sg:address":"Calle de Cami Reial, 26",
    "sg:city":"Torrent",
    "sg:orig_category":"Ropa De Trabajo Y Profesionales (al Por Menor)",
    "sg:phone":"+34 961 57 13 93",
    "sg:postcode":"46900",
    "sg:province":"Valencia",
    "wof:name":"Martinez Roberto Eloisa",
    "wof:placetype":"venue"
},
  "geometry": {"coordinates":[-0.5352355838,39.4127235413],"type":"Point"}
}