{
  "type": "Feature",
  "properties": {
    "addr:full":"Calle de Mayor, 15 Cartagena Murcia 30201",
    "addr:housenumber":"15",
    "addr:postcode":"30201",
    "addr:street":"Calle De Mayor",
    "iso:country":"ES",
    "sg:address":"Calle de Mayor, 15",
    "sg:city":"Cartagena",
    "sg:orig_category":"Cajas De Ahorro",
    "sg:phone":"+34 968 32 12 40",
    "sg:postcode":"30201",
    "sg:province":"Murcia",
    "sg:website":"www.cam.es",
    "wof:name":"Caja De Ahorros Del Mediterraneo",
    "wof:placetype":"venue"
},
  "geometry": {"coordinates":[-0.9156429768,37.600566864],"type":"Point"}
}