{
  "type": "Feature",
  "properties": {
    "iso:country":"ES",
    "sg:address":"Barr Espino (el), 103",
    "sg:city":"San Salvador",
    "sg:orig_category":"Muebles",
    "sg:phone":"+34 942 54 07 06",
    "sg:postcode":"39619",
    "sg:province":"Cantabria",
    "wof:name":"Escenacan S.l.",
    "wof:placetype":"venue"
},
  "geometry": {"coordinates":[-3.7909290791,43.390045166],"type":"Point"}
}