{
  "type": "Feature",
  "properties": {
    "iso:country":"ES",
    "sg:address":"Calle de Blasco De Garay, 37",
    "sg:city":"Madrid",
    "sg:orig_category":"Arquitectos",
    "sg:phone":"+34 915 43 51 13",
    "sg:postcode":"28015",
    "sg:province":"Madrid",
    "wof:name":"Artiaga Alvarez David",
    "wof:placetype":"venue"
},
  "geometry": {"coordinates":[-3.7114834785,40.4347953796],"type":"Point"}
}