{
  "type": "Feature",
  "properties": {
    "addr:full":"Rua Progreso (do), 15 Ribadavia Ourense 32400",
    "addr:housenumber":"15",
    "addr:postcode":"32400",
    "addr:street":"Rua Progreso Do",
    "iso:country":"ES",
    "sg:address":"Rua Progreso (do), 15",
    "sg:city":"Ribadavia",
    "sg:orig_category":"Fotograf\u00cda Y Cine: Aparatos, Pel\u00cdculas Y Accesorios (al Por Menor)",
    "sg:phone":"+34 988 47 14 17",
    "sg:postcode":"32400",
    "sg:province":"Ourense",
    "wof:name":"Rodriguez Padron Ramon",
    "wof:placetype":"venue"
},
  "geometry": {"coordinates":[-8.1426792145,42.2901611328],"type":"Point"}
}