{
  "type": "Feature",
  "properties": {
    "iso:country":"ES",
    "sg:address":"Calle de Fernando El Catolico, 14",
    "sg:city":"Barbastro",
    "sg:classifiers":[
        {
            "category":"Taxi",
            "type":"Transportation"
        }
    ],
    "sg:phone":"+34 974 31 16 69",
    "sg:postcode":"22300",
    "sg:province":"Huesca",
    "wof:name":"Dominguez Olivera Joaquin",
    "wof:placetype":"venue"
},
  "geometry": {"coordinates":[0.1349810064,42.0331001282],"type":"Point"}
}