{
  "type": "Feature",
  "properties": {
    "iso:country":"ES",
    "sg:address":"Carrer de Cervantes, 5",
    "sg:city":"Palma",
    "sg:orig_category":"Agencias De Viajes",
    "sg:phone":"+34 971 73 27 51",
    "sg:postcode":"07013",
    "sg:province":"Islas Baleares",
    "wof:name":"Viajes Canals S.a.",
    "wof:placetype":"venue"
},
  "geometry": {"coordinates":[2.6352159977,39.572681427],"type":"Point"}
}