{
  "type": "Feature",
  "properties": {
    "iso:country":"ES",
    "sg:address":"Pol Ind El Moralejo, 1",
    "sg:city":"Cabra Sto Cristo",
    "sg:orig_category":"Preparaci\u00d3n De Fibras Textiles Naturales",
    "sg:phone":"+34 953 39 71 68",
    "sg:postcode":"23550",
    "sg:province":"Ja\u00e9n",
    "wof:name":"Garcia Gonzalez Ramon",
    "wof:placetype":"venue"
},
  "geometry": {"coordinates":[-3.2850489616,37.7046966553],"type":"Point"}
}