{
  "type": "Feature",
  "properties": {
    "addr:full":"Izarraitz Auzoa, 56 Azpeitia Guip\u00f9zcoa 20730",
    "addr:housenumber":"56",
    "addr:postcode":"20730",
    "addr:street":"Izarraitz Auzoa;Guipu\u0300Zcoa",
    "iso:country":"ES",
    "sg:address":"Izarraitz Auzoa, 56",
    "sg:city":"Azpeitia",
    "sg:orig_category":"Empresas De Carpinter\u00cda De Madera",
    "sg:phone":"+34 943 81 15 46",
    "sg:postcode":"20730",
    "sg:province":"Guip\u00f9zcoa",
    "wof:name":"Otaegui Orbegozo Jose Luis",
    "wof:placetype":"venue"
},
  "geometry": {"coordinates":[-2.2638750076,43.1857795715],"type":"Point"}
}