{
  "type": "Feature",
  "properties": {
    "iso:country":"ES",
    "sg:address":"Calle de Balsa (la), 8",
    "sg:city":"Esplus",
    "sg:orig_category":"Iglesia Cat\u00d3lica",
    "sg:phone":"+34 974 43 50 54",
    "sg:postcode":"22535",
    "sg:province":"Huesca",
    "wof:name":"Parroquia De San Vicente",
    "wof:placetype":"venue"
},
  "geometry": {"coordinates":[0.2742167115,41.7980690002],"type":"Point"}
}