{
  "type": "Feature",
  "properties": {
    "iso:country":"ES",
    "sg:address":"Calle de Isaac Peral, 30",
    "sg:city":"Dos Hermanas",
    "sg:orig_category":"Comercio, Reparaci\u00d3n De Motocicletas, Bicicletas Y Piezas Sueltas",
    "sg:phone":"+34 955 66 93 00",
    "sg:postcode":"41700",
    "sg:province":"Sevilla",
    "wof:name":"Rodriguez Caro Manuel",
    "wof:placetype":"venue"
},
  "geometry": {"coordinates":[-5.9290428162,37.2864608765],"type":"Point"}
}