{
  "type": "Feature",
  "properties": {
    "addr:full":"Calle de San Juan, 1 Palma Condado Huelva 21700",
    "addr:housenumber":"1",
    "addr:postcode":"21700",
    "addr:street":"Calle De San Juan",
    "iso:country":"ES",
    "sg:address":"Calle de San Juan, 1",
    "sg:city":"Palma Condado",
    "sg:orig_category":"Iglesia Cat\u00d3lica",
    "sg:phone":"+34 959 40 02 79",
    "sg:postcode":"21700",
    "sg:province":"Huelva",
    "wof:name":"Parroquia De San Juan Bautista-coadjutor",
    "wof:placetype":"venue"
},
  "geometry": {"coordinates":[-6.5521121025,37.3876686096],"type":"Point"}
}