{
  "type": "Feature",
  "properties": {
    "addr:full":"Barr Monegro, S/n Monegro Cantabria 39290",
    "addr:housenumber":"s",
    "addr:postcode":"39290",
    "addr:street":"/ N",
    "iso:country":"ES",
    "sg:address":"Barr Monegro, S/n",
    "sg:city":"Monegro",
    "sg:orig_category":"Transportes De Animales Vivos",
    "sg:phone":"+34 942 77 83 59",
    "sg:postcode":"39290",
    "sg:province":"Cantabria",
    "wof:name":"Lopez Diez Valentin",
    "wof:placetype":"venue"
},
  "geometry": {"coordinates":[-4.0347490311,43.0129814148],"type":"Point"}
}