{
  "type": "Feature",
  "properties": {
    "addr:full":"J. Verdaguer, 12 Callus Barcelona 08262",
    "addr:housenumber":"12",
    "addr:postcode":"08262",
    "addr:street":"J. Verdaguer;Barcelona",
    "iso:country":"ES",
    "sg:address":"J. Verdaguer, 12",
    "sg:city":"Callus",
    "sg:orig_category":"Asilos De Ancianos. Centros Privados",
    "sg:phone":"+34 938 36 02 02",
    "sg:postcode":"08262",
    "sg:province":"Barcelona",
    "wof:name":"Ajuntament De Callus",
    "wof:placetype":"venue"
},
  "geometry": {"coordinates":[1.7844314575,41.783405304],"type":"Point"}
}