{
  "type": "Feature",
  "properties": {
    "addr:full":"Calle de Emilio Pino, 1 Santander Cantabria 39002",
    "addr:housenumber":"1",
    "addr:postcode":"39002",
    "addr:street":"Calle De Emilio Pino",
    "iso:country":"ES",
    "sg:address":"Calle de Emilio Pino, 1",
    "sg:city":"Santander",
    "sg:orig_category":"Arquitectos",
    "sg:phone":"+34 942 36 20 18",
    "sg:postcode":"39002",
    "sg:province":"Cantabria",
    "wof:name":"Vallejo Lobete Esther",
    "wof:placetype":"venue"
},
  "geometry": {"coordinates":[-3.8094038963,43.4606933594],"type":"Point"}
}