{
  "type": "Feature",
  "properties": {
    "addr:full":"Sector Ind. Karrika, 8 Sorabilla Guip\u00f9zcoa 20140",
    "addr:postcode":"20140",
    "addr:street":"Karrika;Sorabilla Guipu\u0300Zcoa",
    "iso:country":"ES",
    "sg:address":"Sector Ind. Karrika, 8",
    "sg:city":"Sorabilla",
    "sg:orig_category":"Delegados, Agentes De Tr\u00c1nsito, Auxiliares De Transporte Internacional",
    "sg:phone":"+34 943 59 05 56",
    "sg:postcode":"20140",
    "sg:province":"Guip\u00f9zcoa",
    "wof:name":"Transportes Gorrochategui S.a.",
    "wof:placetype":"venue"
},
  "geometry": {"coordinates":[-2.0200839043,43.2191047668],"type":"Point"}
}