{
  "type": "Feature",
  "properties": {
    "addr:full":"Calle de Goiarzu, 2 Getxo Vizcaya 48990",
    "addr:housenumber":"2",
    "addr:postcode":"48990",
    "addr:street":"Calle De Goiarzu",
    "iso:country":"ES",
    "sg:address":"Calle de Goiarzu, 2",
    "sg:city":"Getxo",
    "sg:orig_category":"Estancos",
    "sg:phone":"+34 944 60 03 47",
    "sg:postcode":"48990",
    "sg:province":"Vizcaya",
    "wof:name":"Estanco Neguri, Ana De Laca",
    "wof:placetype":"venue"
},
  "geometry": {"coordinates":[-3.0081338882,43.3437995911],"type":"Point"}
}