{
  "type": "Feature",
  "properties": {
    "addr:full":"Calle de Independencia, S/n Alcantarilla Murcia 30820",
    "addr:housenumber":"/ n",
    "addr:postcode":"30820",
    "addr:street":"Calle De Independencia S",
    "iso:country":"ES",
    "sg:address":"Calle de Independencia, S/n",
    "sg:city":"Alcantarilla",
    "sg:orig_category":"Negocio De Materiales De Construcci\u00d3n",
    "sg:phone":"+34 968 89 01 03",
    "sg:postcode":"30820",
    "sg:province":"Murcia",
    "wof:name":"Materiales De Construccion El Tontino S.l.",
    "wof:placetype":"venue"
},
  "geometry": {"coordinates":[-1.214828968,37.9619636536],"type":"Point"}
}