{
  "type": "Feature",
  "properties": {
    "iso:country":"ES",
    "sg:address":"Avda La Loma, S/n",
    "sg:city":"Ibros",
    "sg:orig_category":"Construcciones Met\u00c1licas",
    "sg:phone":"+34 953 76 70 00",
    "sg:postcode":"23450",
    "sg:province":"Ja\u00e9n",
    "wof:name":"Hermanos Garrido Martos S.l.l.",
    "wof:placetype":"venue"
},
  "geometry": {"coordinates":[-3.4963779449,38.0180778503],"type":"Point"}
}