{
  "type": "Feature",
  "properties": {
    "addr:full":"Araba Ibilbidea, S/n Aretxabaleta Guip\u00f9zcoa 20550",
    "addr:housenumber":"s / n",
    "addr:postcode":"20550",
    "addr:street":"Araba Ibilbidea;Guipu\u0300Zcoa",
    "iso:country":"ES",
    "sg:address":"Araba Ibilbidea, S/n",
    "sg:city":"Aretxabaleta",
    "sg:classifiers":[
        {
            "category":"Manufacturing",
            "subcategory":"Metals",
            "type":"Manufacturing & Wholesale Goods"
        }
    ],
    "sg:phone":"+34 943 79 16 74",
    "sg:postcode":"20550",
    "sg:province":"Guip\u00f9zcoa",
    "sg:tags":[
        "en",
        "fundiciones"
    ],
    "wof:name":"Fundiciones Olazabal S.l.",
    "wof:placetype":"venue"
},
  "geometry": {"coordinates":[-2.505188942,43.0314331055],"type":"Point"}
}