{
  "type": "Feature",
  "properties": {
    "addr:full":"Calle de Amaya, 2 Burgos Burgos 09005",
    "addr:housenumber":"2",
    "addr:postcode":"09005",
    "addr:street":"Calle De Amaya",
    "iso:country":"ES",
    "sg:address":"Calle de Amaya, 2",
    "sg:city":"Burgos",
    "sg:orig_category":"Procuradores",
    "sg:phone":"+34 947 24 31 89",
    "sg:postcode":"09005",
    "sg:province":"Burgos",
    "wof:name":"Juarros Gonzalez Belen",
    "wof:placetype":"venue"
},
  "geometry": {"coordinates":[-3.6968421936,42.3473358154],"type":"Point"}
}