{
  "type": "Feature",
  "properties": {
    "iso:country":"ES",
    "sg:address":"Pg Carretera, 54",
    "sg:city":"Benidorm",
    "sg:orig_category":"Oficinas De Cambio",
    "sg:phone":"+34 966 80 44 33",
    "sg:postcode":"03500",
    "sg:province":"Alicante",
    "wof:name":"Change Center S.a.",
    "wof:placetype":"venue"
},
  "geometry": {"coordinates":[-0.1324820071,38.5365753174],"type":"Point"}
}