{
  "type": "Feature",
  "properties": {
    "addr:full":"A. Guimera, 5 Camallera Girona 17465",
    "addr:housenumber":"5",
    "addr:postcode":"17465",
    "addr:street":"Guimera",
    "iso:country":"ES",
    "sg:address":"A. Guimera, 5",
    "sg:city":"Camallera",
    "sg:orig_category":"Fotograf\u00cda Art\u00cdstica Y Retratos",
    "sg:phone":"+34 972 79 43 68",
    "sg:postcode":"17465",
    "sg:province":"Girona",
    "wof:name":"Bertran Giro Pedro",
    "wof:placetype":"venue"
},
  "geometry": {"coordinates":[2.9612560272,42.1239624023],"type":"Point"}
}