{
  "type": "Feature",
  "properties": {
    "iso:country":"ES",
    "sg:address":"Carrer de Cristofor Colom, 10",
    "sg:city":"Tarragona",
    "sg:orig_category":"Ropa Para Ni\u00d1os (al Por Menor)",
    "sg:phone":"+34 977 23 06 45",
    "sg:postcode":"43001",
    "sg:province":"Tarragona",
    "wof:name":"Pinilla Triguero Antonia",
    "wof:placetype":"venue"
},
  "geometry": {"coordinates":[1.2488440275,41.1164627075],"type":"Point"}
}