{
  "type": "Feature",
  "properties": {
    "iso:country":"ES",
    "sg:address":"Avda Juan Diego, 29",
    "sg:city":"Bormujos",
    "sg:orig_category":"Frutas, Legumbres Frescas Y Tempranas (al Por Menor)",
    "sg:phone":"+34 954 78 80 75",
    "sg:postcode":"41930",
    "sg:province":"Sevilla",
    "wof:name":"Moreno Acebedo Loli",
    "wof:placetype":"venue"
},
  "geometry": {"coordinates":[-6.0745191574,37.3755722046],"type":"Point"}
}