{
  "type": "Feature",
  "properties": {
    "addr:full":"Calle de Angel Nieto, 3 Zamora Zamora 49007",
    "addr:housenumber":"3",
    "addr:postcode":"49007",
    "addr:street":"Calle De Angel Nieto",
    "iso:country":"ES",
    "sg:address":"Calle de Angel Nieto, 3",
    "sg:city":"Zamora",
    "sg:orig_category":"Molduras, Junquillos, Listones Y Molduras Perforadas",
    "sg:phone":"+34 980 51 30 07",
    "sg:postcode":"49007",
    "sg:province":"Zamora",
    "wof:name":"Barrios Prieto Isabel",
    "wof:placetype":"venue"
},
  "geometry": {"coordinates":[-5.746078968,41.510799408],"type":"Point"}
}