{
  "type": "Feature",
  "properties": {
    "iso:country":"ES",
    "sg:address":"Calle de Bolivia, 3",
    "sg:city":"Valladolid",
    "sg:orig_category":"Asesor\u00cdas En Comunicaci\u00d3n",
    "sg:phone":"+34 983 27 24 16",
    "sg:postcode":"47014",
    "sg:province":"Valladolid",
    "wof:name":"Aplicaciones Tecnicas Ecologicas S.l.",
    "wof:placetype":"venue"
},
  "geometry": {"coordinates":[-4.750140667,41.632610321],"type":"Point"}
}