{
  "type": "Feature",
  "properties": {
    "addr:full":"Calle de Angel Senra, 27 Coru\u00d1a La Coru\u00f1a 15007",
    "addr:housenumber":"27",
    "addr:postcode":"15007",
    "addr:street":"Calle De Angel Senra;La Corun\u0303A",
    "iso:country":"ES",
    "sg:address":"Calle de Angel Senra, 27",
    "sg:city":"Coru\u00d1a",
    "sg:orig_category":"Farmacias",
    "sg:phone":"+34 981 23 13 04",
    "sg:postcode":"15007",
    "sg:province":"La Coru\u00f1a",
    "wof:name":"Castro-acu\u00f1a Leyte Julio",
    "wof:placetype":"venue"
},
  "geometry": {"coordinates":[-8.4089317322,43.3548278809],"type":"Point"}
}