{
  "type": "Feature",
  "properties": {
    "iso:country":"ES",
    "sg:address":"Calle de Lauria, 16",
    "sg:city":"Ronda",
    "sg:orig_category":"Electrodom\u00c9sticos (fabricaci\u00d3n, Al Por Mayor)",
    "sg:phone":"+34 952 87 93 53",
    "sg:postcode":"29400",
    "sg:province":"M\u00e1laga",
    "wof:name":"Salvador Moreno Jimenez S.l.",
    "wof:placetype":"venue"
},
  "geometry": {"coordinates":[-5.1649560928,36.7452316284],"type":"Point"}
}