{
  "type": "Feature",
  "properties": {
    "iso:country":"ES",
    "sg:address":"Calle de Venezuela, 16",
    "sg:city":"Vitoria-gasteiz",
    "sg:orig_category":"M\u00c1quinas De Coser Y De Hacer Punto (al Por Mayor)",
    "sg:phone":"+34 945 28 31 88",
    "sg:postcode":"01012",
    "sg:province":"\u00c1lava",
    "wof:name":"Velez Bajo Ana Maria",
    "wof:placetype":"venue"
},
  "geometry": {"coordinates":[-2.6785800457,42.8582229614],"type":"Point"}
}