{
  "type": "Feature",
  "properties": {
    "addr:full":"Calle de Gallo, 2 Ubeda Ja\u00e9n 23400",
    "addr:housenumber":"2",
    "addr:postcode":"23400",
    "addr:street":"Calle De Gallo;Jae\u0301N",
    "iso:country":"ES",
    "sg:address":"Calle de Gallo, 2",
    "sg:city":"Ubeda",
    "sg:orig_category":"Empresarios",
    "sg:phone":"+34 953 75 74 50",
    "sg:postcode":"23400",
    "sg:province":"Ja\u00e9n",
    "wof:name":"Fundacion Proyecto Don Bosco",
    "wof:placetype":"venue"
},
  "geometry": {"coordinates":[-3.3675041199,38.0122375488],"type":"Point"}
}