{
  "type": "Feature",
  "properties": {
    "addr:full":"Calle de Jaen, 11 Rincon Victoria M\u00e1laga 29730",
    "addr:housenumber":"11",
    "addr:postcode":"29730",
    "addr:street":"Calle De Jaen;Ma\u0301Laga",
    "iso:country":"ES",
    "sg:address":"Calle de Jaen, 11",
    "sg:city":"Rincon Victoria",
    "sg:orig_category":"Pintura Y Barniz (al Por Menor)",
    "sg:phone":"+34 952 40 27 53",
    "sg:postcode":"29730",
    "sg:province":"M\u00e1laga",
    "wof:name":"Pinturas Altrica S.l.",
    "wof:placetype":"venue"
},
  "geometry": {"coordinates":[-4.2843608856,36.7164001465],"type":"Point"}
}