{
  "type": "Feature",
  "properties": {
    "addr:full":"Trv Reyes Catolicos, S/n Elche Alicante 03201",
    "addr:housenumber":"s / n",
    "addr:postcode":"03201",
    "addr:street":"Trv Reyes Catolicos",
    "iso:country":"ES",
    "sg:address":"Trv Reyes Catolicos, S/n",
    "sg:city":"Elche",
    "sg:orig_category":"Procuradores",
    "sg:phone":"+34 966 66 01 83",
    "sg:postcode":"03201",
    "sg:province":"Alicante",
    "wof:name":"Ilustre Colegio De Procuradores De Los Tribunales",
    "wof:placetype":"venue"
},
  "geometry": {"coordinates":[-0.5391439795,38.2737541199],"type":"Point"}
}