{
  "type": "Feature",
  "properties": {
    "iso:country":"ES",
    "sg:address":"Calle de Pedreguer, 18",
    "sg:city":"Denia",
    "sg:orig_category":"Electricidad: Instaladores",
    "sg:phone":"+34 965 78 39 20",
    "sg:postcode":"03700",
    "sg:province":"Alicante",
    "wof:name":"Rioma Redes S.l.",
    "wof:placetype":"venue"
},
  "geometry": {"coordinates":[0.1069030017,38.8353233337],"type":"Point"}
}