{
  "type": "Feature",
  "properties": {
    "addr:full":"Calle de Isaac Garcia De Quiros, 28 Valencia De Don Juan Le\u00f3n 24200",
    "addr:housenumber":"28",
    "addr:postcode":"24200",
    "addr:street":"Calle De Isaac Garcia De Quiros",
    "iso:country":"ES",
    "sg:address":"Calle de Isaac Garcia De Quiros, 28",
    "sg:city":"Valencia De Don Juan",
    "sg:orig_category":"Caf\u00c9s, Bares, Cervecer\u00cdas",
    "sg:phone":"+34 987 75 26 21",
    "sg:postcode":"24200",
    "sg:province":"Le\u00f3n",
    "wof:name":"Hosteleria Leonesa Samoa S.l.",
    "wof:placetype":"venue"
},
  "geometry": {"coordinates":[-5.5195999146,42.2927093506],"type":"Point"}
}