{
  "type": "Feature",
  "properties": {
    "addr:full":"Calle de Gomez Acebo, 94 Villanueva Gallego Zaragoza 50830",
    "addr:housenumber":"94",
    "addr:postcode":"50830",
    "addr:street":"Calle De Gomez Acebo",
    "iso:country":"ES",
    "sg:address":"Calle de Gomez Acebo, 94",
    "sg:city":"Villanueva Gallego",
    "sg:orig_category":"Cajas De Ahorro",
    "sg:phone":"+34 976 18 50 83",
    "sg:postcode":"50830",
    "sg:province":"Zaragoza",
    "wof:name":"Caja De Ahorros Y Monte De Piedad De Zaragoza Aragon Y Rioja",
    "wof:placetype":"venue"
},
  "geometry": {"coordinates":[-0.8106639981,41.7982940674],"type":"Point"}
}