{
  "type": "Feature",
  "properties": {
    "iso:country":"ES",
    "sg:address":"Calle de Rio Genil, 5",
    "sg:city":"Mostoles",
    "sg:orig_category":"Pescader\u00cdas (al Por Menor)",
    "sg:phone":"+34 916 13 69 05",
    "sg:postcode":"28934",
    "sg:province":"Madrid",
    "wof:name":"Senovilla Martinez Pedro",
    "wof:placetype":"venue"
},
  "geometry": {"coordinates":[-3.8698160648,40.3186187744],"type":"Point"}
}