{
  "type": "Feature",
  "properties": {
    "addr:full":"Bidekurutzeta Kalea, 23 Bergara Guip\u00f9zcoa 20570",
    "addr:housenumber":"23",
    "addr:postcode":"20570",
    "addr:street":"Bidekurutzeta Kalea;Guipu\u0300Zcoa",
    "iso:country":"ES",
    "sg:address":"Bidekurutzeta Kalea, 23",
    "sg:city":"Bergara",
    "sg:orig_category":"Partidos Pol\u00cdticos",
    "sg:phone":"+34 943 76 55 23",
    "sg:postcode":"20570",
    "sg:province":"Guip\u00f9zcoa",
    "wof:name":"Partido Socialista Obrero Espa\u00f1ol",
    "wof:placetype":"venue"
},
  "geometry": {"coordinates":[-2.4138379097,43.1155776978],"type":"Point"}
}