{
  "type": "Feature",
  "properties": {
    "iso:country":"ES",
    "sg:address":"Calle de Bahillo (el), 29",
    "sg:city":"Cubillos Sil",
    "sg:orig_category":"Reposter\u00cdas",
    "sg:phone":"+34 987 45 80 21",
    "sg:postcode":"24492",
    "sg:province":"Le\u00f3n",
    "wof:name":"Garcia Garcia Jose",
    "wof:placetype":"venue"
},
  "geometry": {"coordinates":[-6.5673213005,42.6239547729],"type":"Point"}
}