{
  "type": "Feature",
  "properties": {
    "addr:full":"Avda Virgen Del Carmen, 39 Madrid Madrid 28033",
    "addr:housenumber":"39",
    "addr:postcode":"madrid;28033",
    "addr:street":"Avda Virgen Del Carmen",
    "iso:country":"ES",
    "sg:address":"Avda Virgen Del Carmen, 39",
    "sg:city":"Madrid",
    "sg:classifiers":[
        {
            "category":"Personal",
            "subcategory":"Barber",
            "type":"Services"
        }
    ],
    "sg:phone":"+34 913 81 98 68",
    "sg:postcode":"28033",
    "sg:province":"Madrid",
    "sg:tags":[
        "caballeros",
        "de",
        "peluqueros"
    ],
    "wof:name":"Moraleda Josa Alicia",
    "wof:placetype":"venue"
},
  "geometry": {"coordinates":[-3.6501739025,40.4752311707],"type":"Point"}
}