{
  "type": "Feature",
  "properties": {
    "iso:country":"ES",
    "sg:address":"C/ Gilberto Martinez, 45",
    "sg:city":"Elche",
    "sg:orig_category":"Bancos",
    "sg:phone":"+34 966 63 28 00",
    "sg:postcode":"03204",
    "sg:province":"Alicante",
    "wof:name":"Banco Popular Espa\u00f1ol S.a.",
    "wof:placetype":"venue"
},
  "geometry": {"coordinates":[-0.70697999,38.2573699951],"type":"Point"}
}