{
  "type": "Feature",
  "properties": {
    "addr:full":"Sotres, S/n Sotres Asturias 33554",
    "addr:postcode":"33554",
    "addr:street":"Sotres S / N Sotres Asturias",
    "iso:country":"ES",
    "sg:address":"Sotres, S/n",
    "sg:city":"Sotres",
    "sg:orig_category":"Barbacoas Y Accesorios",
    "sg:phone":"+34 985 94 50 49",
    "sg:postcode":"33554",
    "sg:province":"Asturias",
    "wof:name":"Fernandez Lopez Manuel Angel",
    "wof:placetype":"venue"
},
  "geometry": {"coordinates":[-4.815767765,43.3022613525],"type":"Point"}
}