{
  "type": "Feature",
  "properties": {
    "iso:country":"ES",
    "sg:address":"Carrer de Joan Prim, 83",
    "sg:city":"Granollers",
    "sg:orig_category":"Edici\u00d3n De Diarios, Revistas, Boletines",
    "sg:phone":"+34 938 40 29 56",
    "sg:postcode":"08401",
    "sg:province":"Barcelona",
    "wof:name":"Pere I Fills S.l.",
    "wof:placetype":"venue"
},
  "geometry": {"coordinates":[2.2898249626,41.6119346619],"type":"Point"}
}