{
  "type": "Feature",
  "properties": {
    "addr:full":"Calle de San Marcos, 10 Madrid Madrid 28004",
    "addr:housenumber":"10",
    "addr:postcode":"madrid;28004",
    "addr:street":"Calle De San Marcos",
    "iso:country":"ES",
    "sg:address":"Calle de San Marcos, 10",
    "sg:city":"Madrid",
    "sg:orig_category":"Lencer\u00cda Femenina, Corseter\u00cda, Trajes De Ba\u00d1o (al Por Menor)",
    "sg:phone":"+34 915 22 17 70",
    "sg:postcode":"28004",
    "sg:province":"Madrid",
    "wof:name":"Concordia Discors",
    "wof:placetype":"venue"
},
  "geometry": {"coordinates":[-3.6992070675,40.4215888977],"type":"Point"}
}