{
  "type": "Feature",
  "properties": {
    "addr:full":"Calle de Donoso Cortes, 2 Talayuela C\u00e1ceres 10310",
    "addr:housenumber":"2",
    "addr:postcode":"10310",
    "addr:street":"Calle De Donoso Cortes;Ca\u0301Ceres",
    "iso:country":"ES",
    "sg:address":"Calle de Donoso Cortes, 2",
    "sg:city":"Talayuela",
    "sg:orig_category":"Postigos, Persianas Y Celos\u00cdas",
    "sg:phone":"+34 927 55 13 90",
    "sg:postcode":"10310",
    "sg:province":"C\u00e1ceres",
    "wof:name":"Hernandez Rosas Gregorio",
    "wof:placetype":"venue"
},
  "geometry": {"coordinates":[-5.6114048958,39.9865455627],"type":"Point"}
}