{
  "type": "Feature",
  "properties": {
    "addr:full":"Carrer de Doctor Junyent, 16 Vic Barcelona 08500",
    "addr:housenumber":"16",
    "addr:postcode":"08500",
    "addr:street":"Carrer De Doctor Junyent",
    "iso:country":"ES",
    "sg:address":"Carrer de Doctor Junyent, 16",
    "sg:city":"Vic",
    "sg:orig_category":"Material De Ocasi\u00d3n (compra, Reventa)",
    "sg:phone":"+34 938 85 69 25",
    "sg:postcode":"08500",
    "sg:province":"Barcelona",
    "wof:name":"Joper S.c.p.",
    "wof:placetype":"venue"
},
  "geometry": {"coordinates":[2.2502501011,41.9282417297],"type":"Point"}
}