{
  "type": "Feature",
  "properties": {
    "iso:country":"ES",
    "sg:address":"Calle de Jose Franchy Roca, 13",
    "sg:city":"Palmas De Gran Canaria",
    "sg:orig_category":"Transportes Por Carretera: Lotes Completos, Mercanc\u00cdas Diversas",
    "sg:phone":"+34 928 27 00 76",
    "sg:postcode":"35007",
    "sg:province":"Las Palmas",
    "wof:name":"Dialte S.a.",
    "wof:placetype":"venue"
},
  "geometry": {"coordinates":[-15.4332237244,28.1388988495],"type":"Point"}
}