{
  "type": "Feature",
  "properties": {
    "iso:country":"ES",
    "sg:address":"Rua Castelao, 28",
    "sg:city":"Lugo",
    "sg:orig_category":"Ingeniero",
    "sg:phone":"+34 982 25 08 37",
    "sg:postcode":"27001",
    "sg:province":"Lugo",
    "wof:name":"Velayos Pardo Francisco",
    "wof:placetype":"venue"
},
  "geometry": {"coordinates":[-7.5547318459,43.0140190125],"type":"Point"}
}