{
  "type": "Feature",
  "properties": {
    "addr:full":"Rua Barbeitos, 6 Barbeitos Pontevedra 36619",
    "addr:housenumber":"6",
    "addr:postcode":"36619",
    "addr:street":"Rua Barbeitos",
    "iso:country":"ES",
    "sg:address":"Rua Barbeitos, 6",
    "sg:city":"Barbeitos",
    "sg:orig_category":"Frutas Y Legumbres Frescas (al Por Mayor)",
    "sg:phone":"+34 986 50 18 97",
    "sg:postcode":"36619",
    "sg:province":"Pontevedra",
    "wof:name":"Frutas El Progreso S.l.",
    "wof:placetype":"venue"
},
  "geometry": {"coordinates":[-8.7645044327,42.5797958374],"type":"Point"}
}