{
  "type": "Feature",
  "properties": {
    "iso:country":"ES",
    "sg:address":"Calle de Doctor Clara, 10",
    "sg:city":"Oropesa",
    "sg:orig_category":"Diarios, Revistas Y Boletines (suscripciones)",
    "sg:phone":"+34 964 31 03 61",
    "sg:postcode":"12594",
    "sg:province":"Castell\u00f3n",
    "wof:name":"Allepuz Salom Carmen",
    "wof:placetype":"venue"
},
  "geometry": {"coordinates":[0.1355603039,40.0938262939],"type":"Point"}
}