{
  "type": "Feature",
  "properties": {
    "addr:full":"M. Iba\u00f1ez (urb Els Carsos), 28 Corbera Llobregat Barcelona 08757",
    "addr:housenumber":"28",
    "addr:postcode":"08757",
    "addr:street":"Urb;Carsos",
    "iso:country":"ES",
    "sg:address":"M. Iba\u00f1ez (urb Els Carsos), 28",
    "sg:city":"Corbera Llobregat",
    "sg:orig_category":"Aceros Inoxidables",
    "sg:phone":"+34 936 88 12 12",
    "sg:postcode":"08757",
    "sg:province":"Barcelona",
    "wof:name":"Garaza Aceituno Francisco",
    "wof:placetype":"venue"
},
  "geometry": {"coordinates":[2.1699187756,41.3879165649],"type":"Point"}
}