{
  "type": "Feature",
  "properties": {
    "addr:full":"Calle de Soldados (los), 17 Palencia Palencia 34001",
    "addr:postcode":"34001",
    "addr:street":"Calle De Soldados Los",
    "iso:country":"ES",
    "sg:address":"Calle de Soldados (los), 17",
    "sg:city":"Palencia",
    "sg:orig_category":"Molduras, Junquillos, Listones Y Molduras Perforadas",
    "sg:phone":"+34 979 70 26 60",
    "sg:postcode":"34001",
    "sg:province":"Palencia",
    "wof:name":"Martinez De La Cava Julio",
    "wof:placetype":"venue"
},
  "geometry": {"coordinates":[-4.5322399139,42.013420105],"type":"Point"}
}