{
  "type": "Feature",
  "properties": {
    "addr:full":"Rua Andres Muruais, 10 Pontevedra Pontevedra 36001",
    "addr:housenumber":"10",
    "addr:postcode":"36001",
    "addr:street":"Rua Andres Muruais",
    "iso:country":"ES",
    "sg:address":"Rua Andres Muruais, 10",
    "sg:city":"Pontevedra",
    "sg:orig_category":"Arquitectos",
    "sg:phone":"+34 986 85 69 11",
    "sg:postcode":"36001",
    "sg:province":"Pontevedra",
    "wof:name":"Rodriguez Pagan Jose Vicente",
    "wof:placetype":"venue"
},
  "geometry": {"coordinates":[-8.6437702179,42.429069519],"type":"Point"}
}