{
  "type": "Feature",
  "properties": {
    "iso:country":"ES",
    "sg:address":"Psje Part Porto Colom, 2",
    "sg:city":"Palmanova",
    "sg:orig_category":"Zapatos (al Por Menor)",
    "sg:phone":"+34 971 68 27 99",
    "sg:postcode":"07181",
    "sg:province":"Islas Baleares",
    "wof:name":"Munar Vidal Cristina",
    "wof:placetype":"venue"
},
  "geometry": {"coordinates":[2.5657799244,39.5388221741],"type":"Point"}
}