{
  "type": "Feature",
  "properties": {
    "addr:full":"Avda Ricardo Soriano, S/n Marbella M\u00e1laga 29600",
    "addr:housenumber":"s / n",
    "addr:postcode":"29600",
    "addr:street":"Avda Ricardo Soriano;Ma\u0301Laga",
    "iso:country":"ES",
    "sg:address":"Avda Ricardo Soriano, S/n",
    "sg:city":"Marbella",
    "sg:orig_category":"Empresarios",
    "sg:phone":"+34 952 77 08 73",
    "sg:postcode":"29600",
    "sg:province":"M\u00e1laga",
    "wof:name":"Construcciones Quero S.l.",
    "wof:placetype":"venue"
},
  "geometry": {"coordinates":[-4.8931889534,36.5104293823],"type":"Point"}
}