{
  "type": "Feature",
  "properties": {
    "addr:full":"Calle de Alvarez Garaya, 12 Gijon Asturias 33206",
    "addr:housenumber":"12",
    "addr:postcode":"33206",
    "addr:street":"Calle De Alvarez Garaya",
    "iso:country":"ES",
    "sg:address":"Calle de Alvarez Garaya, 12",
    "sg:city":"Gijon",
    "sg:orig_category":"Inmobiliaria (agencias)",
    "sg:phone":"+34 985 17 17 73",
    "sg:postcode":"33206",
    "sg:province":"Asturias",
    "wof:name":"Necor Servicios Inmobiliarios S.a.l.",
    "wof:placetype":"venue"
},
  "geometry": {"coordinates":[-5.6656141281,43.5410919189],"type":"Point"}
}