{
  "type": "Feature",
  "properties": {
    "addr:full":"Calle de San Jose, 11 Bonares Huelva 21830",
    "addr:housenumber":"11",
    "addr:postcode":"21830",
    "addr:street":"Calle De San",
    "iso:country":"ES",
    "sg:address":"Calle de San Jose, 11",
    "sg:city":"Bonares",
    "sg:orig_category":"Delegados, Agentes De Tr\u00c1nsito, Auxiliares De Transporte Internacional",
    "sg:phone":"+34 959 36 62 81",
    "sg:postcode":"21830",
    "sg:province":"Huelva",
    "wof:name":"Carrasco Vega Leonardo",
    "wof:placetype":"venue"
},
  "geometry": {"coordinates":[-6.682926178,37.3230247498],"type":"Point"}
}