{
  "type": "Feature",
  "properties": {
    "iso:country":"ES",
    "sg:address":"Calle de San Vicente Martir, 213",
    "sg:city":"Valencia",
    "sg:orig_category":"Cine: Pel\u00cdculas Educativas, Industriales Y Publicitarias (producci\u00d3n)",
    "sg:phone":"+34 963 10 71 08",
    "sg:postcode":"46007",
    "sg:province":"Valencia",
    "wof:name":"Proesme S.l.",
    "wof:placetype":"venue"
},
  "geometry": {"coordinates":[-0.3835979998,39.4565315247],"type":"Point"}
}