{
  "type": "Feature",
  "properties": {
    "iso:country":"ES",
    "sg:address":"Avda Juan Carlos I, 1",
    "sg:city":"Puntal",
    "sg:orig_category":"Servicios Gsm",
    "sg:phone":"+34 968 35 40 83",
    "sg:postcode":"30100",
    "sg:province":"Murcia",
    "wof:name":"Artmur S.a.",
    "wof:placetype":"venue"
},
  "geometry": {"coordinates":[-1.1384449005,37.9999694824],"type":"Point"}
}