{
  "type": "Feature",
  "properties": {
    "addr:full":"Calle de El Bachato, 33 Panticosa Huesca 22661",
    "addr:housenumber":"33",
    "addr:postcode":"22661",
    "addr:street":"Calle De El Bachato",
    "iso:country":"ES",
    "sg:address":"Calle de El Bachato, 33",
    "sg:city":"Panticosa",
    "sg:orig_category":"Plomeros",
    "sg:phone":"+34 974 48 76 18",
    "sg:postcode":"22661",
    "sg:province":"Huesca",
    "wof:name":"Zanitan S.l.",
    "wof:placetype":"venue"
},
  "geometry": {"coordinates":[-0.2818197906,42.7224960327],"type":"Point"}
}