{
  "type": "Feature",
  "properties": {
    "iso:country":"ES",
    "sg:address":"Avda Oviedo, 6",
    "sg:city":"Solares",
    "sg:orig_category":"Ebanister\u00cda",
    "sg:phone":"+34 942 52 04 74",
    "sg:postcode":"39710",
    "sg:province":"Cantabria",
    "wof:name":"Muebles Benito E Hijo S.l.",
    "wof:placetype":"venue"
},
  "geometry": {"coordinates":[-3.7406010628,43.3809967041],"type":"Point"}
}