{
  "type": "Feature",
  "properties": {
    "addr:full":"Via Pasteur (de), 8 Boisaca La Coru\u00f1a 15890",
    "addr:postcode":"15890",
    "addr:street":"Via Pasteur De 8 Boisaca La Corun\u0303A",
    "iso:country":"ES",
    "sg:address":"Via Pasteur (de), 8",
    "sg:city":"Boisaca",
    "sg:orig_category":"Laboratorios Farmac\u00c9uticos",
    "sg:phone":"+34 981 95 80 02",
    "sg:postcode":"15890",
    "sg:province":"La Coru\u00f1a",
    "wof:name":"Ricardo Bescansa S. L.",
    "wof:placetype":"venue"
},
  "geometry": {"coordinates":[-8.4769210815,42.8835983276],"type":"Point"}
}