{
  "type": "Feature",
  "properties": {
    "iso:country":"ES",
    "sg:address":"Calle de Segura, 10",
    "sg:city":"Pto. Rosario",
    "sg:orig_category":"Veh\u00cdculos De Ocasi\u00d3n",
    "sg:phone":"+34 928 53 25 53",
    "sg:postcode":"35600",
    "sg:province":"Las Palmas",
    "wof:name":"Motor Eleccion Fuerteventura S.l.",
    "wof:placetype":"venue"
},
  "geometry": {"coordinates":[-13.864991188,28.4928798676],"type":"Point"}
}