{
  "type": "Feature",
  "properties": {
    "addr:full":"Avda Estacion, 1 Laguna Duero Valladolid 47140",
    "addr:housenumber":"1",
    "addr:postcode":"47140",
    "addr:street":"Avda Estacion",
    "iso:country":"ES",
    "sg:address":"Avda Estacion, 1",
    "sg:city":"Laguna Duero",
    "sg:orig_category":"Bazares, Art\u00cdculos De Limpieza Y De Cocina (al Por Menor)",
    "sg:phone":"+34 983 54 27 07",
    "sg:postcode":"47140",
    "sg:province":"Valladolid",
    "wof:name":"Sanchez Parra Maria Teresa",
    "wof:placetype":"venue"
},
  "geometry": {"coordinates":[-4.7202939987,41.5809707642],"type":"Point"}
}