{
  "type": "Feature",
  "properties": {
    "iso:country":"ES",
    "sg:address":"Calle de Pintor Matias Moreno, S/n",
    "sg:city":"Toledo",
    "sg:orig_category":"Industria Qu\u00cdmica",
    "sg:phone":"+34 925 28 23 10",
    "sg:postcode":"45002",
    "sg:province":"Toledo",
    "wof:name":"Empresa De Transformacion Agraria S.a.",
    "wof:placetype":"venue"
},
  "geometry": {"coordinates":[-4.0311307907,39.8585739136],"type":"Point"}
}