{
  "type": "Feature",
  "properties": {
    "iso:country":"ES",
    "sg:address":"Calle de Empecinado (del), 24",
    "sg:city":"Alcobendas",
    "sg:orig_category":"Animales (al Por Menor)",
    "sg:phone":"+34 916 52 14 13",
    "sg:postcode":"28100",
    "sg:province":"Madrid",
    "wof:name":"Raposo Barrera Valentin",
    "wof:placetype":"venue"
},
  "geometry": {"coordinates":[-3.6314558983,40.5406303406],"type":"Point"}
}