{
  "type": "Feature",
  "properties": {
    "addr:full":"Carrer de Fra Francesc Peris, 1 Pego Alicante 03780",
    "addr:housenumber":"1",
    "addr:postcode":"03780",
    "addr:street":"Carrer De Fra Francesc Peris",
    "iso:country":"ES",
    "sg:address":"Carrer de Fra Francesc Peris, 1",
    "sg:city":"Pego",
    "sg:orig_category":"Transportes Por Carretera: Lotes Completos, Mercanc\u00cdas Diversas",
    "sg:phone":"+34 965 57 19 47",
    "sg:postcode":"03780",
    "sg:province":"Alicante",
    "wof:name":"Vicens Lucas Rafael",
    "wof:placetype":"venue"
},
  "geometry": {"coordinates":[-0.1209340021,38.8417243958],"type":"Point"}
}