{
  "type": "Feature",
  "properties": {
    "addr:full":"Ptda Sitjar De Baix, S/n Sitjar De Baix Castell\u00f3n 12200",
    "addr:housenumber":"s",
    "addr:postcode":"12200",
    "addr:street":"Ptda Sitjar De Baix;/ N;Castello\u0301N",
    "iso:country":"ES",
    "sg:address":"Ptda Sitjar De Baix, S/n",
    "sg:city":"Sitjar De Baix",
    "sg:orig_category":"Pirotecnia (espect\u00c1culos)",
    "sg:phone":"+34 964 76 64 30",
    "sg:postcode":"12200",
    "sg:province":"Castell\u00f3n",
    "wof:name":"Pirotecnia Marti S.l.",
    "wof:placetype":"venue"
},
  "geometry": {"coordinates":[-0.2620640099,39.9651794434],"type":"Point"}
}