{
  "type": "Feature",
  "properties": {
    "addr:full":"Calle de Fidel Sahuquillo, 9 Salvaca\u00f1ete Cuenca 16318",
    "addr:housenumber":"9",
    "addr:postcode":"16318",
    "addr:street":"Calle De Fidel Sahuquillo",
    "iso:country":"ES",
    "sg:address":"Calle de Fidel Sahuquillo, 9",
    "sg:city":"Salvaca\u00f1ete",
    "sg:orig_category":"Farmacias",
    "sg:phone":"+34 969 35 71 29",
    "sg:postcode":"16318",
    "sg:province":"Cuenca",
    "wof:name":"Fernandez Moreno Miguel",
    "wof:placetype":"venue"
},
  "geometry": {"coordinates":[-1.5026580095,40.098526001],"type":"Point"}
}