{
  "type": "Feature",
  "properties": {
    "iso:country":"ES",
    "sg:address":"Calle de Taller, 54",
    "sg:city":"Macael",
    "sg:orig_category":"M\u00c1rmoles, Granitos Y Piedras Naturales",
    "sg:phone":"+34 950 44 54 03",
    "sg:postcode":"04867",
    "sg:province":"Almer\u00eda",
    "wof:name":"Muro Ca\u00f1adas Andres",
    "wof:placetype":"venue"
},
  "geometry": {"coordinates":[-2.3032329082,37.3313102722],"type":"Point"}
}