{
  "type": "Feature",
  "properties": {
    "addr:full":"Bra\u00f1a Grande(cabovila\u00f1o), S/n Bra\u00e7a Grande La Coru\u00f1a 15145",
    "addr:housenumber":"s",
    "addr:postcode":"15145",
    "addr:street":"/ N Brac\u0327A Grande La Corun\u0303A",
    "iso:country":"ES",
    "sg:address":"Bra\u00f1a Grande(cabovila\u00f1o), S/n",
    "sg:city":"Bra\u00e7a Grande",
    "sg:orig_category":"Negocio De Madera",
    "sg:phone":"+34 981 61 28 63",
    "sg:postcode":"15145",
    "sg:province":"La Coru\u00f1a",
    "wof:name":"Beypa S.l.",
    "wof:placetype":"venue"
},
  "geometry": {"coordinates":[-8.5813436508,43.2482681274],"type":"Point"}
}