{
  "type": "Feature",
  "properties": {
    "iso:country":"ES",
    "sg:address":"Calle de Pintor Gisbert, 21",
    "sg:city":"Alacant",
    "sg:orig_category":"Mercer\u00cda, Lencer\u00cda (al Por Menor)",
    "sg:phone":"+34 965 12 08 58",
    "sg:postcode":"03005",
    "sg:province":"Alicante",
    "wof:name":"Pastor Monzo Raul",
    "wof:placetype":"venue"
},
  "geometry": {"coordinates":[-0.4958710074,38.347946167],"type":"Point"}
}