{
  "type": "Feature",
  "properties": {
    "addr:full":"Carr Xavier Puig Andreu, 24 Lleida Lleida 25005",
    "addr:housenumber":"24",
    "addr:postcode":"25005",
    "addr:street":"Carr Xavier Puig Andreu",
    "iso:country":"ES",
    "sg:address":"Carr Xavier Puig Andreu, 24",
    "sg:city":"Lleida",
    "sg:orig_category":"Aparatos, Material Y Suministros Para Laboratorios",
    "sg:phone":"+34 973 23 88 79",
    "sg:postcode":"25005",
    "sg:province":"Lleida",
    "wof:name":"Toll Andreu S.l.",
    "wof:placetype":"venue"
},
  "geometry": {"coordinates":[0.6381610036,41.62733078],"type":"Point"}
}