{
  "type": "Feature",
  "properties": {
    "iso:country":"ES",
    "sg:address":"Av Mare Deu De Montserrat, 264",
    "sg:city":"Barcelona",
    "sg:orig_category":"Peluqueros: De Se\u00d1oras",
    "sg:phone":"+34 934 56 95 74",
    "sg:postcode":"08041",
    "sg:province":"Barcelona",
    "wof:name":"Olivares Gimenez Carolina",
    "wof:placetype":"venue"
},
  "geometry": {"coordinates":[2.1755669117,41.4234161377],"type":"Point"}
}