{
  "type": "Feature",
  "properties": {
    "addr:full":"Ptda Seniola, 82 Javea Alicante 03730",
    "addr:housenumber":"82",
    "addr:postcode":"03730",
    "addr:street":"Ptda Seniola",
    "iso:country":"ES",
    "sg:address":"Ptda Seniola, 82",
    "sg:city":"Javea",
    "sg:orig_category":"Laboratorios Y Trabajos De Fotograf\u00cda, V\u00cddeo Y Cine",
    "sg:phone":"+34 966 46 16 62",
    "sg:postcode":"03730",
    "sg:province":"Alicante",
    "sg:website":"www.tvhoffer.homepage.es",
    "wof:name":"Hoffer  Peter",
    "wof:placetype":"venue"
},
  "geometry": {"coordinates":[0.1668650061,38.7890739441],"type":"Point"}
}