{
  "type": "Feature",
  "properties": {
    "iso:country":"ES",
    "sg:address":"Calle de Bachiller Del, 3",
    "sg:city":"Huelva",
    "sg:orig_category":"Peluquer\u00cdas, Peluquer\u00cda Mixta",
    "sg:phone":"+34 959 23 23 68",
    "sg:postcode":"21007",
    "sg:province":"Huelva",
    "wof:name":"Mu\u00f1oz Quintero Esperanza",
    "wof:placetype":"venue"
},
  "geometry": {"coordinates":[-6.9292135239,37.2608451843],"type":"Point"}
}