{
  "type": "Feature",
  "properties": {
    "addr:full":"Calle de Jose Oliva, 1 Huelva Huelva 21003",
    "addr:housenumber":"1",
    "addr:postcode":"21003",
    "addr:street":"Calle De Jose Oliva",
    "iso:country":"ES",
    "sg:address":"Calle de Jose Oliva, 1",
    "sg:city":"Huelva",
    "sg:orig_category":"Promotores Constructores",
    "sg:phone":"+34 959 28 62 29",
    "sg:postcode":"21003",
    "sg:province":"Huelva",
    "wof:name":"Construcciones Maralfa S.l.",
    "wof:placetype":"venue"
},
  "geometry": {"coordinates":[-6.9424080849,37.2542953491],"type":"Point"}
}