{
  "type": "Feature",
  "properties": {
    "iso:country":"ES",
    "sg:address":"Calle de Juan De La Cruz, 1",
    "sg:city":"Irun",
    "sg:orig_category":"Psic\u00d3logos",
    "sg:phone":"+34 943 61 40 41",
    "sg:postcode":"20301",
    "sg:province":"Guip\u00f9zcoa",
    "wof:name":"Moran Sanchez Maria Carmen",
    "wof:placetype":"venue"
},
  "geometry": {"coordinates":[-1.7902339697,43.3395233154],"type":"Point"}
}