{
  "type": "Feature",
  "properties": {
    "iso:country":"ES",
    "sg:address":"Carretera De Pedroche, Km. 0000,7",
    "sg:city":"Pozoblanco",
    "sg:classifiers":[
        {
            "category":"Building & Trades",
            "subcategory":"Construction",
            "type":"Services"
        }
    ],
    "sg:phone":"+34 957 77 30 87",
    "sg:postcode":"14400",
    "sg:province":"C\u00f3rdoba",
    "sg:tags":[
        "para",
        "la",
        "material",
        "suministros",
        "cr\u00cda",
        "y"
    ],
    "wof:name":"Galan Alcaide Bartolome",
    "wof:placetype":"venue"
},
  "geometry": {"coordinates":[-4.8401651382,38.3838500977],"type":"Point"}
}