{
  "type": "Feature",
  "properties": {
    "iso:country":"ES",
    "sg:address":"Calle de Paz, 19",
    "sg:city":"Santa Amalia",
    "sg:orig_category":"Agentes Generales De Seguros",
    "sg:phone":"+34 924 82 01 56",
    "sg:postcode":"06410",
    "sg:province":"Badajoz",
    "wof:name":"Donaire Molano Luis",
    "wof:placetype":"venue"
},
  "geometry": {"coordinates":[-6.0067791939,39.0077896118],"type":"Point"}
}