{
  "type": "Feature",
  "properties": {
    "iso:country":"ES",
    "sg:address":"Riera Bisbe Pol, 26",
    "sg:city":"Arenys Mar",
    "sg:orig_category":"Fabricaci\u00d3n, Distribuci\u00d3n De Discos, V\u00cddeodiscos Y Musicassettes",
    "sg:phone":"+34 937 92 07 86",
    "sg:postcode":"08350",
    "sg:province":"Barcelona",
    "wof:name":"Puig Pidemunt Luis",
    "wof:placetype":"venue"
},
  "geometry": {"coordinates":[2.5509679317,41.5798416138],"type":"Point"}
}