{
  "type": "Feature",
  "properties": {
    "iso:country":"ES",
    "sg:address":"Calle de San Francisco, 4",
    "sg:city":"Trujillo",
    "sg:orig_category":"Frutas, Legumbres Frescas Y Tempranas (al Por Menor)",
    "sg:phone":"+34 927 32 21 61",
    "sg:postcode":"10200",
    "sg:province":"C\u00e1ceres",
    "wof:name":"Rivera Trinidad Luis Miguel",
    "wof:placetype":"venue"
},
  "geometry": {"coordinates":[-5.8873138428,39.4544830322],"type":"Point"}
}