{
  "type": "Feature",
  "properties": {
    "addr:full":"Carrer de Riber, 38 Montblanc Tarragona 43400",
    "addr:housenumber":"38",
    "addr:postcode":"43400",
    "addr:street":"Carrer De Riber",
    "iso:country":"ES",
    "sg:address":"Carrer de Riber, 38",
    "sg:city":"Montblanc",
    "sg:orig_category":"Bancos",
    "sg:phone":"+34 977 87 50 03",
    "sg:postcode":"43400",
    "sg:province":"Tarragona",
    "wof:name":"Banco Espa\u00f1ol De Credito S.a.",
    "wof:placetype":"venue"
},
  "geometry": {"coordinates":[1.163689971,41.3765029907],"type":"Point"}
}