{
  "type": "Feature",
  "properties": {
    "addr:full":"Pol Ind El Ca\u00f1o, S/n Espiel C\u00f3rdoba 14220",
    "addr:housenumber":"/ n",
    "addr:postcode":"14220",
    "addr:street":"Can\u0303O S",
    "iso:country":"ES",
    "sg:address":"Pol Ind El Ca\u00f1o, S/n",
    "sg:city":"Espiel",
    "sg:orig_category":"Goma: Materias Primas (producci\u00d3n, Distribuci\u00d3n)",
    "sg:phone":"+34 957 36 41 37",
    "sg:postcode":"14220",
    "sg:province":"C\u00f3rdoba",
    "wof:name":"Multibarrera S.l.",
    "wof:placetype":"venue"
},
  "geometry": {"coordinates":[-5.0181927681,38.1884384155],"type":"Point"}
}