{
  "type": "Feature",
  "properties": {
    "addr:full":"Plaz Puerta Del Sol, S/n Madrid Madrid 28013",
    "addr:housenumber":"/ n",
    "addr:postcode":"28013",
    "addr:street":"Del Sol S",
    "iso:country":"ES",
    "sg:address":"Plaz Puerta Del Sol, S/n",
    "sg:city":"Madrid",
    "sg:orig_category":"Radiocomunicaciones, Telefon\u00cda M\u00d3vil, Radiomensajer\u00cda: Servicios, Comercializaci\u00d3n",
    "sg:phone":"+34 915 22 53 23",
    "sg:postcode":"28013",
    "sg:province":"Madrid",
    "wof:name":"Locured S.l.",
    "wof:placetype":"venue"
},
  "geometry": {"coordinates":[-3.7033209801,40.4171485901],"type":"Point"}
}