{
  "type": "Feature",
  "properties": {
    "addr:full":"Calle de Santutxu, 34 Bilbao Vizcaya 48004",
    "addr:housenumber":"34",
    "addr:postcode":"48004",
    "addr:street":"Calle De Santutxu",
    "iso:country":"ES",
    "sg:address":"Calle de Santutxu, 34",
    "sg:city":"Bilbao",
    "sg:orig_category":"Complementos De Vestir (al Por Menor)",
    "sg:phone":"+34 944 32 04 75",
    "sg:postcode":"48004",
    "sg:province":"Vizcaya",
    "wof:name":"Carmen Vicario Garcia",
    "wof:placetype":"venue"
},
  "geometry": {"coordinates":[-2.9151360989,43.2522506714],"type":"Point"}
}