{
  "type": "Feature",
  "properties": {
    "addr:full":"Calle de San Fernando, S/n Osso Cinca Huesca 22532",
    "addr:housenumber":"/ n",
    "addr:postcode":"22532",
    "addr:street":"Calle De San Fernando S",
    "iso:country":"ES",
    "sg:address":"Calle de San Fernando, S/n",
    "sg:city":"Osso Cinca",
    "sg:orig_category":"Electricidad: Instaladores",
    "sg:phone":"+34 974 45 60 17",
    "sg:postcode":"22532",
    "sg:province":"Huesca",
    "wof:name":"Beque Castejon Manuel",
    "wof:placetype":"venue"
},
  "geometry": {"coordinates":[0.1898149997,41.6668548584],"type":"Point"}
}