{
  "type": "Feature",
  "properties": {
    "iso:country":"ES",
    "sg:address":"Alam Sundheim, 24",
    "sg:city":"Huelva",
    "sg:orig_category":"Ropa Para Ni\u00d1os (al Por Menor)",
    "sg:phone":"+34 959 26 21 85",
    "sg:postcode":"21003",
    "sg:province":"Huelva",
    "wof:name":"Medina Crespo Maria De Carmen",
    "wof:placetype":"venue"
},
  "geometry": {"coordinates":[-6.9495940208,37.256313324],"type":"Point"}
}