{
  "type": "Feature",
  "properties": {
    "addr:full":"Avda Region Murciana, 1 Carril De La Enera Murcia 30011",
    "addr:housenumber":"1",
    "addr:postcode":"30011",
    "addr:street":"Avda Region Murciana;Carril De La",
    "iso:country":"ES",
    "sg:address":"Avda Region Murciana, 1",
    "sg:city":"Carril De La Enera",
    "sg:orig_category":"Molduras, Junquillos, Listones Y Molduras Perforadas",
    "sg:phone":"+34 968 26 97 75",
    "sg:postcode":"30011",
    "sg:province":"Murcia",
    "wof:name":"Hernandez Lorente Angel",
    "wof:placetype":"venue"
},
  "geometry": {"coordinates":[-1.0969905853,37.9772644043],"type":"Point"}
}