{
  "type": "Feature",
  "properties": {
    "addr:full":"Calle de Alcotanes (de), 17 Pinto Madrid 28320",
    "addr:housenumber":"17",
    "addr:postcode":"28320",
    "addr:street":"Calle De Alcotanes De",
    "iso:country":"ES",
    "sg:address":"Calle de Alcotanes (de), 17",
    "sg:city":"Pinto",
    "sg:orig_category":"Estudios, Instalaci\u00d3n De Climatizaci\u00d3n",
    "sg:phone":"+34 916 92 72 40",
    "sg:postcode":"28320",
    "sg:province":"Madrid",
    "wof:name":"Airsum S. A.",
    "wof:placetype":"venue"
},
  "geometry": {"coordinates":[-3.7115557194,40.2491912842],"type":"Point"}
}