{
  "type": "Feature",
  "properties": {
    "iso:country":"ES",
    "sg:address":"Ctra Tembleque, 2",
    "sg:city":"Villaca\u00f1as",
    "sg:orig_category":"Ropa Y Art\u00cdculos Pre",
    "sg:phone":"+34 925 20 17 55",
    "sg:postcode":"45860",
    "sg:province":"Toledo",
    "wof:name":"Linea Actual C.b.",
    "wof:placetype":"venue"
},
  "geometry": {"coordinates":[-3.3513190746,39.6209716797],"type":"Point"}
}