{
  "type": "Feature",
  "properties": {
    "iso:country":"ES",
    "sg:address":"Ctra Calahorra, S/n",
    "sg:city":"Autol",
    "sg:orig_category":"Suministros Y Materiales Industriales",
    "sg:phone":"+34 941 39 05 72",
    "sg:postcode":"26560",
    "sg:province":"La Rioja",
    "wof:name":"Carsal Suministros Industriales S.l.",
    "wof:placetype":"venue"
},
  "geometry": {"coordinates":[-2.0062398911,42.2181930542],"type":"Point"}
}