{
  "type": "Feature",
  "properties": {
    "addr:full":"Rua Calvo Sotelo, 21 Estrada Pontevedra 36680",
    "addr:housenumber":"21",
    "addr:postcode":"36680",
    "addr:street":"Rua Calvo Sotelo;Estrada Pontevedra",
    "iso:country":"ES",
    "sg:address":"Rua Calvo Sotelo, 21",
    "sg:city":"Estrada",
    "sg:orig_category":"Mercer\u00cda, Lencer\u00cda (al Por Menor)",
    "sg:phone":"+34 986 57 39 57",
    "sg:postcode":"36680",
    "sg:province":"Pontevedra",
    "wof:name":"Novoa Rey Maria Dolores",
    "wof:placetype":"venue"
},
  "geometry": {"coordinates":[-8.4886856079,42.6896934509],"type":"Point"}
}