{
  "type": "Feature",
  "properties": {
    "addr:full":"Calle de Beato Tomas De Zumarraga, 48 Vitoria-gasteiz \u00c1lava 01009",
    "addr:housenumber":"48",
    "addr:postcode":"01009",
    "addr:street":"Calle De Beato Tomas De Zumarraga",
    "iso:country":"ES",
    "sg:address":"Calle de Beato Tomas De Zumarraga, 48",
    "sg:city":"Vitoria-gasteiz",
    "sg:orig_category":"Aparatos, Material Y Suministros Para Laboratorios",
    "sg:phone":"+34 945 20 02 48",
    "sg:postcode":"01009",
    "sg:province":"\u00c1lava",
    "wof:name":"Labomed - Az, S.l.",
    "wof:placetype":"venue"
},
  "geometry": {"coordinates":[-2.6829090118,42.8503417969],"type":"Point"}
}