{
  "type": "Feature",
  "properties": {
    "iso:country":"ES",
    "sg:address":"Torrelarragoiti Parcela 7, 12 B",
    "sg:city":"Zamudio",
    "sg:orig_category":"Maquinaria Para Industrias Diversas",
    "sg:phone":"+34 944 52 05 52",
    "sg:postcode":"48170",
    "sg:province":"Vizcaya",
    "wof:name":"Hidraulica Arlu S.l.",
    "wof:placetype":"venue"
},
  "geometry": {"coordinates":[-2.8633139133,43.280834198],"type":"Point"}
}