{
  "type": "Feature",
  "properties": {
    "iso:country":"ES",
    "sg:address":"Calle de Eustaquio Casado, 24",
    "sg:city":"Nava Asuncion",
    "sg:orig_category":"Fisioterapia",
    "sg:phone":"+34 921 58 02 37",
    "sg:postcode":"40450",
    "sg:province":"Segovia",
    "wof:name":"Virseda Garcia Sara",
    "wof:placetype":"venue"
},
  "geometry": {"coordinates":[-4.4884347916,41.1586456299],"type":"Point"}
}