{
  "type": "Feature",
  "properties": {
    "addr:full":"Calle de Pablo Ruiz Picasso, 52 Zaragoza Zaragoza 50015",
    "addr:housenumber":"52",
    "addr:postcode":"50015",
    "addr:street":"Calle De Pablo Ruiz Picasso",
    "iso:country":"ES",
    "sg:address":"Calle de Pablo Ruiz Picasso, 52",
    "sg:city":"Zaragoza",
    "sg:orig_category":"Delegados, Agentes De Tr\u00c1nsito, Auxiliares De Transporte Internacional",
    "sg:phone":"+34 976 73 02 79",
    "sg:postcode":"50015",
    "sg:province":"Zaragoza",
    "wof:name":"Moreno Melendez Jose Antonio",
    "wof:placetype":"venue"
},
  "geometry": {"coordinates":[-0.8772640228,41.6729812622],"type":"Point"}
}