{
  "type": "Feature",
  "properties": {
    "iso:country":"ES",
    "sg:address":"Carrer de Olot, 2",
    "sg:city":"Vic",
    "sg:orig_category":"Electricidad: Equipos Industriales, Componentes (fabricaci\u00d3n)",
    "sg:phone":"+34 938 86 64 20",
    "sg:postcode":"08500",
    "sg:province":"Barcelona",
    "wof:name":"Alg Sistemas S.l.",
    "wof:placetype":"venue"
},
  "geometry": {"coordinates":[2.2556159496,41.9433708191],"type":"Point"}
}