{
  "type": "Feature",
  "properties": {
    "iso:country":"ES",
    "sg:address":"Rua Jose Franco Montes, 4",
    "sg:city":"Pardavila",
    "sg:orig_category":"Congelados: Productos Alimentarios (fabricaci\u00d3n, Al Por Mayor)",
    "sg:phone":"+34 986 26 55 09",
    "sg:postcode":"36214",
    "sg:province":"Pontevedra",
    "wof:name":"Ymir Bifrost S.l.",
    "wof:placetype":"venue"
},
  "geometry": {"coordinates":[-8.7009363174,42.3666763306],"type":"Point"}
}