{
  "type": "Feature",
  "properties": {
    "iso:country":"ES",
    "sg:address":"Avgd Antonio Almela, 59",
    "sg:city":"Alcudia",
    "sg:orig_category":"Centros Pms (psico",
    "sg:phone":"+34 962 99 72 28",
    "sg:postcode":"46250",
    "sg:province":"Valencia",
    "sg:website":"www.ecorasc.com",
    "wof:name":"Ecora S.l",
    "wof:placetype":"venue"
},
  "geometry": {"coordinates":[-0.5070289969,39.1940689087],"type":"Point"}
}