{
  "type": "Feature",
  "properties": {
    "iso:country":"ES",
    "sg:address":"Calle de Real De Motril, 20",
    "sg:city":"Armilla",
    "sg:classifiers":[
        {
            "category":"Autos & Motor Vehicles",
            "subcategory":"Automobile Sales",
            "type":"Retail Goods"
        }
    ],
    "sg:phone":"+34 958 55 31 23",
    "sg:postcode":"18100",
    "sg:province":"Granada",
    "wof:name":"Cano Pulido Juan Domingo",
    "wof:placetype":"venue"
},
  "geometry": {"coordinates":[-3.6242039204,37.1452941895],"type":"Point"}
}