{
  "type": "Feature",
  "properties": {
    "iso:country":"ES",
    "sg:address":"Avda Maria Auxiliadora, S/n",
    "sg:city":"Rota",
    "sg:orig_category":"Equipo De Refrigeraci\u00d3n Industrial",
    "sg:phone":"+34 956 81 58 79",
    "sg:postcode":"11520",
    "sg:province":"C\u00e1diz",
    "wof:name":"Harana Herrera Carmen",
    "wof:placetype":"venue"
},
  "geometry": {"coordinates":[-6.3637142181,36.6252441406],"type":"Point"}
}