{
  "type": "Feature",
  "properties": {
    "addr:full":"Rio Altzania, 23 Iru\u00f1a Navarra 31005",
    "addr:housenumber":"23",
    "addr:postcode":"31005",
    "addr:street":"Rio Altzania",
    "iso:country":"ES",
    "sg:address":"Rio Altzania, 23",
    "sg:city":"Iru\u00f1a",
    "sg:orig_category":"Inform\u00c1tica (estudios, Servicios, Asesor\u00cda, Formaci\u00d3n)",
    "sg:phone":"+34 948 23 70 83",
    "sg:postcode":"31005",
    "sg:province":"Navarra",
    "wof:name":"Gamboa Gamboa Lourdes",
    "wof:placetype":"venue"
},
  "geometry": {"coordinates":[-1.6456090212,42.8039703369],"type":"Point"}
}