{
  "type": "Feature",
  "properties": {
    "iso:country":"ES",
    "sg:address":"Calle de Palmeras (las), 34",
    "sg:city":"Huercal Almeria",
    "sg:orig_category":"Electricidad: Instaladores",
    "sg:phone":"+34 950 30 15 62",
    "sg:postcode":"04230",
    "sg:province":"Almer\u00eda",
    "wof:name":"Aguilar Pino Francisco Jose",
    "wof:placetype":"venue"
},
  "geometry": {"coordinates":[-2.4356555939,36.8842010498],"type":"Point"}
}