{
  "type": "Feature",
  "properties": {
    "iso:country":"ES",
    "sg:address":"Carr Pep Ventura, 12",
    "sg:city":"Figueres",
    "sg:orig_category":"Frutas Y Legumbres Frescas (al Por Mayor)",
    "sg:phone":"+34 972 51 61 00",
    "sg:postcode":"17600",
    "sg:province":"Girona",
    "wof:name":"Comfruit S.l.",
    "wof:placetype":"venue"
},
  "geometry": {"coordinates":[2.9588000774,42.2669792175],"type":"Point"}
}