{
  "type": "Feature",
  "properties": {
    "iso:country":"ES",
    "sg:address":"Carr Borja Moll, De, 43",
    "sg:city":"Mao",
    "sg:orig_category":"Abogados",
    "sg:phone":"+34 971 36 95 61",
    "sg:postcode":"07702",
    "sg:province":"Islas Baleares",
    "wof:name":"Fernandez Terres Felix",
    "wof:placetype":"venue"
},
  "geometry": {"coordinates":[4.2670102119,39.8828201294],"type":"Point"}
}