{
  "type": "Feature",
  "properties": {
    "iso:country":"ES",
    "sg:address":"Valencia, 6",
    "sg:city":"Pujols",
    "sg:classifiers":[
        {
            "category":"Casinos & Gambling",
            "type":"Entertainment"
        }
    ],
    "sg:phone":"+34 971 32 91 24",
    "sg:postcode":"07871",
    "sg:province":"Islas Baleares",
    "sg:tags":[
        "locale",
        "de",
        "juego"
    ],
    "wof:name":"Arcolandia S.l",
    "wof:placetype":"venue"
},
  "geometry": {"coordinates":[1.4568035603,38.7076530457],"type":"Point"}
}