{
  "type": "Feature",
  "properties": {
    "addr:full":"Carr Tortosa, 29 Badalona Barcelona 08918",
    "addr:housenumber":"29",
    "addr:postcode":"08918",
    "addr:street":"Carr Tortosa",
    "iso:country":"ES",
    "sg:address":"Carr Tortosa, 29",
    "sg:city":"Badalona",
    "sg:orig_category":"Alimentaci\u00d3n General (al Por Menor)",
    "sg:phone":"+34 933 83 59 96",
    "sg:postcode":"08918",
    "sg:province":"Barcelona",
    "wof:name":"Evencares S.l.",
    "wof:placetype":"venue"
},
  "geometry": {"coordinates":[2.2313189507,41.4395561218],"type":"Point"}
}