{
  "type": "Feature",
  "properties": {
    "iso:country":"ES",
    "sg:address":"Calle de Clara Del Rey, 20",
    "sg:city":"Madrid",
    "sg:orig_category":"Abogados",
    "sg:phone":"+34 914 16 11 84",
    "sg:postcode":"28002",
    "sg:province":"Madrid",
    "wof:name":"Chercoles Castillo Pilar",
    "wof:placetype":"venue"
},
  "geometry": {"coordinates":[-3.6705663204,40.4422569275],"type":"Point"}
}