{
  "type": "Feature",
  "properties": {
    "addr:full":"Av Onze De Setembre, 105 Sabadell Barcelona 08208",
    "addr:housenumber":"105",
    "addr:postcode":"08208",
    "addr:street":"Av Onze De Setembre",
    "iso:country":"ES",
    "sg:address":"Av Onze De Setembre, 105",
    "sg:city":"Sabadell",
    "sg:orig_category":"Tintes (fabricaci\u00d3n, Al Por Mayor)",
    "sg:phone":"+34 937 45 04 24",
    "sg:postcode":"08208",
    "sg:province":"Barcelona",
    "wof:name":"Punt-net Valles S.l.",
    "wof:placetype":"venue"
},
  "geometry": {"coordinates":[2.1038870811,41.5536651611],"type":"Point"}
}