{
  "type": "Feature",
  "properties": {
    "iso:country":"ES",
    "sg:address":"Avda Habana (la), 26",
    "sg:city":"Cristianos",
    "sg:orig_category":"Inmobiliaria (agencias)",
    "sg:phone":"+34 922 79 85 27",
    "sg:postcode":"38650",
    "sg:province":"Santa Cruz De Tenerife",
    "wof:name":"Bennett  Julia Maria",
    "wof:placetype":"venue"
},
  "geometry": {"coordinates":[-16.72747612,28.0552997589],"type":"Point"}
}