{
  "type": "Feature",
  "properties": {
    "addr:full":"Pase Habana, 23 Madrid Madrid 28036",
    "addr:housenumber":"23",
    "addr:postcode":"madrid;28036",
    "iso:country":"ES",
    "sg:address":"Pase Habana, 23",
    "sg:city":"Madrid",
    "sg:orig_category":"Zapatos (al Por Menor)",
    "sg:phone":"+34 915 64 63 61",
    "sg:postcode":"28036",
    "sg:province":"Madrid",
    "wof:name":"Ramirez Garrote Carmen",
    "wof:placetype":"venue"
},
  "geometry": {"coordinates":[-3.6867160797,40.4511985779],"type":"Point"}
}