{
  "type": "Feature",
  "properties": {
    "addr:full":"Carr Juan Bautista Gil, 24 Burjassot Valencia 46100",
    "addr:housenumber":"24",
    "addr:postcode":"46100",
    "addr:street":"Carr Juan Bautista Gil",
    "iso:country":"ES",
    "sg:address":"Carr Juan Bautista Gil, 24",
    "sg:city":"Burjassot",
    "sg:orig_category":"Asociaciones, Organismos Culturales Y Socioeducativos",
    "sg:phone":"+34 963 90 29 45",
    "sg:postcode":"46100",
    "sg:province":"Valencia",
    "wof:name":"Caritas Diocesana De Valencia",
    "wof:placetype":"venue"
},
  "geometry": {"coordinates":[-0.4189330041,39.5142173767],"type":"Point"}
}