{
  "type": "Feature",
  "properties": {
    "iso:country":"ES",
    "sg:address":"Av. Generalisimo, S/n",
    "sg:city":"Camari\u00f1as",
    "sg:orig_category":"Fabricaci\u00d3n De Bordados, Encajes Y Tules",
    "sg:phone":"+34 981 73 62 19",
    "sg:postcode":"15123",
    "sg:province":"A Coru\u00f1a",
    "wof:name":"Vigo Rego Amalia Angustias",
    "wof:placetype":"venue"
},
  "geometry": {"coordinates":[-9.1833839417,43.1295585632],"type":"Point"}
}