{
  "type": "Feature",
  "properties": {
    "iso:country":"ES",
    "sg:address":"Ctra General, Km. 0067,5",
    "sg:city":"Cornisa Del Suroeste",
    "sg:orig_category":"Bancos",
    "sg:phone":"+34 928 15 17 88",
    "sg:postcode":"35120",
    "sg:province":"Las Palmas",
    "wof:name":"Banca March S.a.",
    "wof:placetype":"venue"
},
  "geometry": {"coordinates":[-15.6830463409,27.7618026733],"type":"Point"}
}