{
  "type": "Feature",
  "properties": {
    "iso:country":"ES",
    "sg:address":"Pg Zona Franca, 148",
    "sg:city":"Barcelona",
    "sg:orig_category":"Molduras, Junquillos, Listones Y Molduras Perforadas",
    "sg:phone":"+34 934 22 20 34",
    "sg:postcode":"08038",
    "sg:province":"Barcelona",
    "wof:name":"Ren  Weizhu",
    "wof:placetype":"venue"
},
  "geometry": {"coordinates":[2.1401000023,41.3590774536],"type":"Point"}
}