{
  "type": "Feature",
  "properties": {
    "addr:full":"Calle de San Benito, 4 Valladolid Valladolid 47003",
    "addr:housenumber":"4",
    "addr:postcode":"47003",
    "addr:street":"Calle De San Benito",
    "iso:country":"ES",
    "sg:address":"Calle de San Benito, 4",
    "sg:city":"Valladolid",
    "sg:orig_category":"Empresarios",
    "sg:phone":"+34 983 33 00 04",
    "sg:postcode":"47003",
    "sg:province":"Valladolid",
    "wof:name":"Gonzalez Romo Manuel",
    "wof:placetype":"venue"
},
  "geometry": {"coordinates":[-4.7287950516,41.6546707153],"type":"Point"}
}