{
  "type": "Feature",
  "properties": {
    "addr:full":"Avgd Alacant, Km. 0245,3 Silla Valencia 46460",
    "addr:postcode":"46460",
    "addr:street":"Alacant Km. 0245,3",
    "iso:country":"ES",
    "sg:address":"Avgd Alacant, Km. 0245,3",
    "sg:city":"Silla",
    "sg:orig_category":"Paletas",
    "sg:phone":"+34 961 20 06 12",
    "sg:postcode":"46460",
    "sg:province":"Valencia",
    "sg:website":"www.aglolak.com",
    "wof:name":"Aglolak S.l.",
    "wof:placetype":"venue"
},
  "geometry": {"coordinates":[-0.4090684056,39.359161377],"type":"Point"}
}