{
  "type": "Feature",
  "properties": {
    "addr:full":"Calle de Rufa Rosado, 1 Gibraleon Huelva 21500",
    "addr:housenumber":"1",
    "addr:postcode":"21500",
    "addr:street":"Calle De Rufa Rosado",
    "iso:country":"ES",
    "sg:address":"Calle de Rufa Rosado, 1",
    "sg:city":"Gibraleon",
    "sg:orig_category":"Maquinaria Para Industrias Diversas",
    "sg:phone":"+34 959 30 15 00",
    "sg:postcode":"21500",
    "sg:province":"Huelva",
    "wof:name":"Correa Palanco Alonso",
    "wof:placetype":"venue"
},
  "geometry": {"coordinates":[-6.9672980309,37.3759651184],"type":"Point"}
}