{
  "type": "Feature",
  "properties": {
    "iso:country":"ES",
    "sg:address":"Calle de Zabalbide, 64",
    "sg:city":"Bilbao",
    "sg:orig_category":"Quincaller\u00cda (al Por Menor)",
    "sg:phone":"+34 944 12 58 55",
    "sg:postcode":"48006",
    "sg:province":"Vizcaya",
    "wof:name":"Jesus Sadornil Mozo",
    "wof:placetype":"venue"
},
  "geometry": {"coordinates":[-2.9143300056,43.2546386719],"type":"Point"}
}