{
  "type": "Feature",
  "properties": {
    "addr:full":"Calle de Finisterre, 29 Madrid Madrid 28029",
    "addr:housenumber":"29",
    "addr:postcode":"madrid;28029",
    "addr:street":"Calle De Finisterre",
    "iso:country":"ES",
    "sg:address":"Calle de Finisterre, 29",
    "sg:city":"Madrid",
    "sg:orig_category":"Alquiler De V\u00cddeo",
    "sg:phone":"+34 913 78 05 08",
    "sg:postcode":"28029",
    "sg:province":"Madrid",
    "wof:name":"Gayol Raya Elena",
    "wof:placetype":"venue"
},
  "geometry": {"coordinates":[-3.7026441097,40.4795265198],"type":"Point"}
}