{
  "type": "Feature",
  "properties": {
    "iso:country":"ES",
    "sg:address":"Carrer de Pintor Ruano Llopis, 7",
    "sg:city":"Orba",
    "sg:orig_category":"Laboratorios Y Cl\u00cdnicas Veterinarias",
    "sg:phone":"+34 965 58 41 24",
    "sg:postcode":"03790",
    "sg:province":"Alicante",
    "wof:name":"Nuria Esther Morera Mayans Y Luis Javier Alvarez Alvarez Cdad",
    "wof:placetype":"venue"
},
  "geometry": {"coordinates":[-0.0644679964,38.7803459167],"type":"Point"}
}