{
  "type": "Feature",
  "properties": {
    "addr:full":"Calle de Callejon Del Castillo, 126 Callejon Del Castillo Las Palmas 35200",
    "addr:housenumber":"126",
    "addr:postcode":"35200",
    "addr:street":"Calle De Callejon Del Castillo;Callejon Del Castillo Las",
    "iso:country":"ES",
    "sg:address":"Calle de Callejon Del Castillo, 126",
    "sg:city":"Callejon Del Castillo",
    "sg:orig_category":"Maquinaria Para Industrias Diversas",
    "sg:phone":"+34 928 70 20 65",
    "sg:postcode":"35200",
    "sg:province":"Las Palmas",
    "wof:name":"Gonzalez Deniz Daniel Alejandro",
    "wof:placetype":"venue"
},
  "geometry": {"coordinates":[-15.4015445709,27.9974040985],"type":"Point"}
}