{
  "type": "Feature",
  "properties": {
    "iso:country":"ES",
    "sg:address":"Pol Pina De Ebro, S/n",
    "sg:city":"Pina",
    "sg:orig_category":"Empresas De Hormig\u00d3n, Hormig\u00d3n Armado Y Pretensado",
    "sg:phone":"+34 976 16 56 83",
    "sg:postcode":"50750",
    "sg:province":"Zaragoza",
    "wof:name":"Hormiebro S.l.",
    "wof:placetype":"venue"
},
  "geometry": {"coordinates":[-0.5231540203,41.4931335449],"type":"Point"}
}