{
  "type": "Feature",
  "properties": {
    "addr:full":"Carrer de Cristofol Colom, 35 Granollers Barcelona 08402",
    "addr:housenumber":"35",
    "addr:postcode":"08402",
    "addr:street":"Carrer De Cristofol Colom",
    "iso:country":"ES",
    "sg:address":"Carrer de Cristofol Colom, 35",
    "sg:city":"Granollers",
    "sg:orig_category":"Plomeros",
    "sg:phone":"+34 938 70 11 63",
    "sg:postcode":"08402",
    "sg:province":"Barcelona",
    "wof:name":"Gual Prat Miguel",
    "wof:placetype":"venue"
},
  "geometry": {"coordinates":[2.2889099121,41.6079521179],"type":"Point"}
}