{
  "type": "Feature",
  "properties": {
    "addr:full":"Carrer de Raimon D'abadal, 25 Vic Barcelona 08500",
    "addr:housenumber":"25",
    "addr:postcode":"08500",
    "addr:street":"Carrer De Raimon D'Abadal",
    "iso:country":"ES",
    "sg:address":"Carrer de Raimon D'abadal, 25",
    "sg:city":"Vic",
    "sg:orig_category":"Plomeros",
    "sg:phone":"+34 938 89 59 34",
    "sg:postcode":"08500",
    "sg:province":"Barcelona",
    "wof:name":"Parareda Codina Bonaventura",
    "wof:placetype":"venue"
},
  "geometry": {"coordinates":[2.2503902912,41.9219055176],"type":"Point"}
}