{
  "type": "Feature",
  "properties": {
    "iso:country":"ES",
    "sg:address":"Pase Estacion Medico Manuel Samper, 18",
    "sg:city":"Callosa Segura",
    "sg:orig_category":"Peluqueros: De Se\u00d1oras",
    "sg:phone":"+34 965 31 15 82",
    "sg:postcode":"03360",
    "sg:province":"Alicante",
    "wof:name":"Martinez Medina Antonio",
    "wof:placetype":"venue"
},
  "geometry": {"coordinates":[-0.8776689768,38.1256752014],"type":"Point"}
}