{
  "type": "Feature",
  "properties": {
    "iso:country":"ES",
    "sg:address":"Calle de Bilbao, 2",
    "sg:city":"Alacant",
    "sg:orig_category":"M\u00c9dicos: Estomatolog\u00cda",
    "sg:phone":"+34 965 21 04 39",
    "sg:postcode":"03001",
    "sg:province":"Alicante",
    "wof:name":"Barrachina Andres Bego\u00d1a",
    "wof:placetype":"venue"
},
  "geometry": {"coordinates":[-0.4835779965,38.3439826965],"type":"Point"}
}