{
  "type": "Feature",
  "properties": {
    "iso:country":"ES",
    "sg:address":"Boedo, S/n",
    "sg:city":"Culleredo",
    "sg:orig_category":"Alimentaci\u00d3n General (al Por Mayor)",
    "sg:phone":"+34 981 66 80 41",
    "sg:postcode":"15199",
    "sg:province":"La Coru\u00f1a",
    "wof:name":"Iglesias Abeleira Domingo Antonio",
    "wof:placetype":"venue"
},
  "geometry": {"coordinates":[-8.4508943558,43.258266449],"type":"Point"}
}