{
  "type": "Feature",
  "properties": {
    "addr:full":"Pase Sagasta, 17 Zaragoza Zaragoza 50008",
    "addr:housenumber":"17",
    "addr:postcode":"50008",
    "iso:country":"ES",
    "sg:address":"Pase Sagasta, 17",
    "sg:city":"Zaragoza",
    "sg:orig_category":"Ingenier\u00cda, Centros De Estudios (diversos)",
    "sg:phone":"+34 976 30 13 51",
    "sg:postcode":"50008",
    "sg:province":"Zaragoza",
    "wof:name":"Sisener Ingenieros S.l.",
    "wof:placetype":"venue"
},
  "geometry": {"coordinates":[-0.8857899904,41.6429100037],"type":"Point"}
}