{
  "type": "Feature",
  "properties": {
    "iso:country":"ES",
    "sg:address":"Calle de Olivo (del), 30",
    "sg:city":"Arganda",
    "sg:orig_category":"Productos Qu\u00cdmicos (fabricaci\u00d3n, Al Por Mayor)",
    "sg:phone":"+34 918 75 75 03",
    "sg:postcode":"28500",
    "sg:province":"Madrid",
    "wof:name":"Distribucion De Productos Carmona",
    "wof:placetype":"venue"
},
  "geometry": {"coordinates":[-3.4617578983,40.3139038086],"type":"Point"}
}