{
  "type": "Feature",
  "properties": {
    "addr:full":"Pla\u00c7 Esplanada, De S', 1 Mao Islas Baleares 07702",
    "addr:postcode":"07702",
    "addr:street":"Islas",
    "iso:country":"ES",
    "sg:address":"Pla\u00c7 Esplanada, De S', 1",
    "sg:city":"Mao",
    "sg:orig_category":"Parques De Atracciones Y Centros De Esparcimiento",
    "sg:phone":"+34 971 36 16 67",
    "sg:postcode":"07702",
    "sg:province":"Islas Baleares",
    "wof:name":"Comercial Pons Orfila Menorca S.l.",
    "wof:placetype":"venue"
},
  "geometry": {"coordinates":[4.2599329948,39.8884811401],"type":"Point"}
}