{
  "type": "Feature",
  "properties": {
    "iso:country":"ES",
    "sg:address":"Calle de Enrique Granados, 6",
    "sg:city":"Pozuelo De Alarcon",
    "sg:orig_category":"Servicio De Salud",
    "sg:phone":"+34 913 51 76 63",
    "sg:postcode":"28224",
    "sg:province":"Madrid",
    "wof:name":"Tecnocam Sistemas S.l.l.",
    "wof:placetype":"venue"
},
  "geometry": {"coordinates":[-3.8116030693,40.4582138062],"type":"Point"}
}