{
  "type": "Feature",
  "properties": {
    "addr:full":"Calle de Jose Maria Martinez Sanchez Arjona, 43 Sevilla Sevilla 41010",
    "addr:housenumber":"43",
    "addr:postcode":"41010",
    "addr:street":"Calle De Jose Maria Martinez;Arjona",
    "iso:country":"ES",
    "sg:address":"Calle de Jose Maria Martinez Sanchez Arjona, 43",
    "sg:city":"Sevilla",
    "sg:orig_category":"Muebles Y Accesorios Para Cocinas Y Cuartos De Ba\u00d1o (al Por Menor)",
    "sg:phone":"+34 954 27 74 68",
    "sg:postcode":"41010",
    "sg:province":"Sevilla",
    "wof:name":"Ramos Fernandez Manuel Miguel",
    "wof:placetype":"venue"
},
  "geometry": {"coordinates":[-6.0018129349,37.3876953125],"type":"Point"}
}