{
  "type": "Feature",
  "properties": {
    "iso:country":"ES",
    "sg:address":"Calle de Carlos Haya, 15",
    "sg:city":"Santander",
    "sg:orig_category":"Administradores De Bienes Y Delegados De Comunidades De Propietarios",
    "sg:phone":"+34 942 21 00 84",
    "sg:postcode":"39009",
    "sg:province":"Cantabria",
    "wof:name":"Comunidad De Propietarios",
    "wof:placetype":"venue"
},
  "geometry": {"coordinates":[-3.8171682358,43.4544563293],"type":"Point"}
}