{
  "type": "Feature",
  "properties": {
    "addr:full":"Carr Rausell, 18 Gandia Valencia 46700",
    "addr:housenumber":"18",
    "addr:postcode":"46700",
    "addr:street":"Carr Rausell;Valencia",
    "iso:country":"ES",
    "sg:address":"Carr Rausell, 18",
    "sg:city":"Gandia",
    "sg:orig_category":"Carnicer\u00cdas, Carnicer\u00cdas",
    "sg:phone":"+34 962 86 91 06",
    "sg:postcode":"46700",
    "sg:province":"Valencia",
    "wof:name":"Crecente Penalva Patricia",
    "wof:placetype":"venue"
},
  "geometry": {"coordinates":[-0.1913339943,38.960735321],"type":"Point"}
}