{
  "type": "Feature",
  "properties": {
    "iso:country":"ES",
    "sg:address":"Ctra Montoro-puente Genil, S/n",
    "sg:city":"Aguilar De La Frontera",
    "sg:orig_category":"Restaurantes",
    "sg:phone":"+34 957 66 04 39",
    "sg:postcode":"14920",
    "sg:province":"C\u00f3rdoba",
    "wof:name":"Cabezas Galisteo Manuel",
    "wof:placetype":"venue"
},
  "geometry": {"coordinates":[-4.6633291245,37.5056343079],"type":"Point"}
}