{
  "type": "Feature",
  "properties": {
    "addr:full":"Calle de Ni\u00d1o Jesus, 12 Yecla Murcia 30510",
    "addr:housenumber":"12",
    "addr:postcode":"30510",
    "addr:street":"Calle De Nin\u0303O Jesus",
    "iso:country":"ES",
    "sg:address":"Calle de Ni\u00d1o Jesus, 12",
    "sg:city":"Yecla",
    "sg:orig_category":"Zapatos (al Por Menor)",
    "sg:phone":"+34 968 79 23 95",
    "sg:postcode":"30510",
    "sg:province":"Murcia",
    "wof:name":"Tomas Perez Francisco",
    "wof:placetype":"venue"
},
  "geometry": {"coordinates":[-1.1168789864,38.6133041382],"type":"Point"}
}