{
  "type": "Feature",
  "properties": {
    "addr:full":"Rua Benito Corbal, 15 Pontevedra Pontevedra 36001",
    "addr:housenumber":"15",
    "addr:postcode":"36001",
    "addr:street":"Rua Benito Corbal",
    "iso:country":"ES",
    "sg:address":"Rua Benito Corbal, 15",
    "sg:city":"Pontevedra",
    "sg:orig_category":"Inform\u00c1tica (estudios, Servicios, Asesor\u00cda, Formaci\u00d3n)",
    "sg:phone":"+34 986 84 85 20",
    "sg:postcode":"36001",
    "sg:province":"Pontevedra",
    "sg:website":"www.galimarket.com",
    "wof:name":"Nccom Pontevedra S.l.",
    "wof:placetype":"venue"
},
  "geometry": {"coordinates":[-8.641960144,42.4304122925],"type":"Point"}
}