{
  "type": "Feature",
  "properties": {
    "iso:country":"ES",
    "sg:address":"Calle de Mayor, 89",
    "sg:city":"Sang\u00fcesa",
    "sg:orig_category":"Peluqueros: De Se\u00d1oras",
    "sg:phone":"+34 948 43 04 30",
    "sg:postcode":"31400",
    "sg:province":"Navarra",
    "wof:name":"Crespo Carlos Maria Jose",
    "wof:placetype":"venue"
},
  "geometry": {"coordinates":[-1.2816259861,42.5761375427],"type":"Point"}
}