{
  "type": "Feature",
  "properties": {
    "iso:country":"ES",
    "sg:address":"Calle de Sierra De Atapuerca, 45",
    "sg:city":"Madrid",
    "sg:orig_category":"Asesor\u00cda Sobre Comunicaci\u00d3n De Empresas",
    "sg:phone":"+34 917 50 57 12",
    "sg:postcode":"28050",
    "sg:province":"Madrid",
    "wof:name":"Adyfin-fijls S.l.",
    "wof:placetype":"venue"
},
  "geometry": {"coordinates":[-3.6660759449,40.5066680908],"type":"Point"}
}