{
  "type": "Feature",
  "properties": {
    "addr:full":"Carr Antoni Vares I Martinell, S/n Girona Girona 17007",
    "addr:housenumber":"/ n",
    "addr:postcode":"17007",
    "addr:street":"Carr Antoni Vares;Martinell S",
    "iso:country":"ES",
    "sg:address":"Carr Antoni Vares I Martinell, S/n",
    "sg:city":"Girona",
    "sg:orig_category":"Asociaciones, Organismos Culturales Y Socioeducativos",
    "sg:phone":"+34 972 22 49 39",
    "sg:postcode":"17007",
    "sg:province":"Girona",
    "wof:name":"Penya Doble Set",
    "wof:placetype":"venue"
},
  "geometry": {"coordinates":[2.812707901,41.9954910278],"type":"Point"}
}