{
  "type": "Feature",
  "properties": {
    "addr:full":"Calle de Etxaburueta, 2 Soraluze-placencia Armas Guip\u00f9zcoa 20590",
    "addr:housenumber":"2",
    "addr:postcode":"20590",
    "addr:street":"Calle De Etxaburueta;Armas Guipu\u0300Zcoa",
    "iso:country":"ES",
    "sg:address":"Calle de Etxaburueta, 2",
    "sg:city":"Soraluze-placencia Armas",
    "sg:orig_category":"Frutas, Legumbres Frescas Y Tempranas (al Por Menor)",
    "sg:phone":"+34 943 75 20 55",
    "sg:postcode":"20590",
    "sg:province":"Guip\u00f9zcoa",
    "wof:name":"Alvarez Casas Jesus Vidal",
    "wof:placetype":"venue"
},
  "geometry": {"coordinates":[-2.4125730991,43.1748123169],"type":"Point"}
}