{
  "type": "Feature",
  "properties": {
    "addr:full":"Avda Novelda, 125 Alacant Alicante 03009",
    "addr:housenumber":"125",
    "addr:postcode":"03009",
    "addr:street":"Avda Novelda",
    "iso:country":"ES",
    "sg:address":"Avda Novelda, 125",
    "sg:city":"Alacant",
    "sg:orig_category":"Fabricaci\u00d3n, Venta De Cuadros, Accesorios Para Enmarcar",
    "sg:phone":"+34 965 17 17 64",
    "sg:postcode":"03009",
    "sg:province":"Alicante",
    "wof:name":"Acristalamiento Y Manufactura Del Vidrio S.l.",
    "wof:placetype":"venue"
},
  "geometry": {"coordinates":[-0.4958730936,38.3660964966],"type":"Point"}
}