{
  "type": "Feature",
  "properties": {
    "iso:country":"ES",
    "sg:address":"Carrer de Sant Cosme, 65",
    "sg:city":"Terrassa",
    "sg:orig_category":"Molduras, Junquillos, Listones Y Molduras Perforadas",
    "sg:phone":"+34 937 31 24 49",
    "sg:postcode":"08222",
    "sg:province":"Barcelona",
    "wof:name":"Canals Salvi Montserrat",
    "wof:placetype":"venue"
},
  "geometry": {"coordinates":[2.0307159424,41.5603713989],"type":"Point"}
}