{
  "type": "Feature",
  "properties": {
    "addr:full":"Calle de Huelva, 25 S. Juan Puerto Huelva 21610",
    "addr:housenumber":"25",
    "addr:postcode":"21610",
    "addr:street":"Calle De Huelva;S. Juan Puerto",
    "iso:country":"ES",
    "sg:address":"Calle de Huelva, 25",
    "sg:city":"S. Juan Puerto",
    "sg:orig_category":"Material Y Herramientas Agr\u00cdcolas",
    "sg:phone":"+34 959 35 64 85",
    "sg:postcode":"21610",
    "sg:province":"Huelva",
    "wof:name":"Hermanos Villegas Pe\u00f1as S.l.",
    "wof:placetype":"venue"
},
  "geometry": {"coordinates":[-6.8426141739,37.3148765564],"type":"Point"}
}