{
  "type": "Feature",
  "properties": {
    "addr:full":"Calle de Mayor, 31 Azuqueca Henares Guadalajara 19200",
    "addr:housenumber":"31",
    "addr:postcode":"19200",
    "addr:street":"Calle De Mayor",
    "iso:country":"ES",
    "sg:address":"Calle de Mayor, 31",
    "sg:city":"Azuqueca Henares",
    "sg:orig_category":"Contenedores (mercanc\u00cdas)",
    "sg:phone":"+34 949 26 19 40",
    "sg:postcode":"19200",
    "sg:province":"Guadalajara",
    "wof:name":"Paris Sanchez Pedro",
    "wof:placetype":"venue"
},
  "geometry": {"coordinates":[-3.2649490833,40.5674705505],"type":"Point"}
}