{
  "type": "Feature",
  "properties": {
    "addr:full":"Calle de Valdes Pumarino, 30 Candas Asturias 33430",
    "addr:housenumber":"30",
    "addr:postcode":"33430",
    "addr:street":"Calle De Valdes Pumarino",
    "iso:country":"ES",
    "sg:address":"Calle de Valdes Pumarino, 30",
    "sg:city":"Candas",
    "sg:orig_category":"Carnicer\u00cdas, Carnicer\u00cdas",
    "sg:phone":"+34 985 87 18 76",
    "sg:postcode":"33430",
    "sg:province":"Asturias",
    "wof:name":"Menendez Fernandez Maria Fernanda",
    "wof:placetype":"venue"
},
  "geometry": {"coordinates":[-5.7635469437,43.5900993347],"type":"Point"}
}