{
  "type": "Feature",
  "properties": {
    "iso:country":"ES",
    "sg:address":"Juan De La Cierva, 19",
    "sg:city":"Torrellano",
    "sg:orig_category":"Higiene, Belleza: Art\u00cdculos (al Por Menor)",
    "sg:phone":"+34 965 68 38 40",
    "sg:postcode":"03320",
    "sg:province":"Alicante",
    "wof:name":"P&l Systems Limited",
    "wof:placetype":"venue"
},
  "geometry": {"coordinates":[-0.5883839726,38.2929649353],"type":"Point"}
}