{
  "type": "Feature",
  "properties": {
    "iso:country":"ES",
    "sg:address":"Calle de Tridente, 15",
    "sg:city":"Alacant",
    "sg:orig_category":"Ropa Para Ni\u00d1os (al Por Menor)",
    "sg:phone":"+34 965 26 87 83",
    "sg:postcode":"03540",
    "sg:province":"Alicante",
    "wof:name":"Jar Publicidad S.l.",
    "wof:placetype":"venue"
},
  "geometry": {"coordinates":[-0.4234699905,38.3586883545],"type":"Point"}
}