{
  "type": "Feature",
  "properties": {
    "addr:full":"Calle de San Francisco, 23 Almansa Albacete 02640",
    "addr:housenumber":"23",
    "addr:postcode":"02640",
    "addr:street":"Calle De San Francisco",
    "iso:country":"ES",
    "sg:address":"Calle de San Francisco, 23",
    "sg:city":"Almansa",
    "sg:orig_category":"Confecci\u00d3n (fabricaci\u00d3n, Al Por Mayor)",
    "sg:phone":"+34 967 31 17 99",
    "sg:postcode":"02640",
    "sg:province":"Albacete",
    "wof:name":"Nachos Moda S. L.",
    "wof:placetype":"venue"
},
  "geometry": {"coordinates":[-1.0951290131,38.8681907654],"type":"Point"}
}