{
  "type": "Feature",
  "properties": {
    "iso:country":"ES",
    "sg:address":"Trva Ballesteros, 1",
    "sg:city":"Huesca",
    "sg:orig_category":"Art\u00cdculos De Decoraci\u00d3n",
    "sg:phone":"+34 974 24 18 73",
    "sg:postcode":"22001",
    "sg:province":"Huesca",
    "wof:name":"Oscadecor J.s. S.l.",
    "wof:placetype":"venue"
},
  "geometry": {"coordinates":[-0.4039950073,42.1367988586],"type":"Point"}
}