{
  "type": "Feature",
  "properties": {
    "addr:full":"Abanto, 1 Molino Hoz Madrid 28230",
    "addr:housenumber":"1",
    "addr:postcode":"28230",
    "addr:street":"Abanto",
    "iso:country":"ES",
    "sg:address":"Abanto, 1",
    "sg:city":"Molino Hoz",
    "sg:orig_category":"Centros Empresariales",
    "sg:phone":"+34 916 30 28 84",
    "sg:postcode":"28230",
    "sg:province":"Madrid",
    "wof:name":"Albendea Consultores S.l.",
    "wof:placetype":"venue"
},
  "geometry": {"coordinates":[-3.9388914108,40.5385131836],"type":"Point"}
}