{
  "type": "Feature",
  "properties": {
    "iso:country":"ES",
    "sg:address":"Carrer de Llibertat, 31",
    "sg:city":"Castelldefels",
    "sg:orig_category":"Art\u00cdculos De Decoraci\u00d3n",
    "sg:phone":"+34 936 64 58 68",
    "sg:postcode":"08860",
    "sg:province":"Barcelona",
    "wof:name":"Dercorgin S.l.",
    "wof:placetype":"venue"
},
  "geometry": {"coordinates":[1.9758549929,41.2776985168],"type":"Point"}
}