{
  "type": "Feature",
  "properties": {
    "iso:country":"ES",
    "sg:address":"Calle de Mayor, 34",
    "sg:city":"Igea",
    "sg:orig_category":"Farmacias",
    "sg:phone":"+34 941 19 40 59",
    "sg:postcode":"26525",
    "sg:province":"La Rioja",
    "wof:name":"Arnedo Hernandez Amaia",
    "wof:placetype":"venue"
},
  "geometry": {"coordinates":[-2.0100514889,42.070602417],"type":"Point"}
}