{
  "type": "Feature",
  "properties": {
    "iso:country":"ES",
    "sg:address":"Calle de Santo Tomas De Villanueva, 17",
    "sg:city":"Salamanca",
    "sg:orig_category":"Librer\u00cdas",
    "sg:phone":"+34 923 24 02 35",
    "sg:postcode":"37005",
    "sg:province":"Salamanca",
    "wof:name":"Vazquez Rivas Juan Antonio",
    "wof:placetype":"venue"
},
  "geometry": {"coordinates":[-5.6559081078,40.9757537842],"type":"Point"}
}