{
  "type": "Feature",
  "properties": {
    "addr:full":"Calle de Herreros, 12 Castro De Fuentidue\u00e7a Segovia 40315",
    "addr:housenumber":"12",
    "addr:postcode":"40315",
    "addr:street":"Calle De Herreros",
    "iso:country":"ES",
    "sg:address":"Calle de Herreros, 12",
    "sg:city":"Castro De Fuentidue\u00e7a",
    "sg:orig_category":"Frutas, Legumbres Frescas Y Tempranas (al Por Menor)",
    "sg:phone":"+34 921 53 31 61",
    "sg:postcode":"40315",
    "sg:province":"Segovia",
    "wof:name":"Pe\u00f1a Miguel Sigifredo",
    "wof:placetype":"venue"
},
  "geometry": {"coordinates":[-3.8560349941,41.4210624695],"type":"Point"}
}