{
  "type": "Feature",
  "properties": {
    "addr:full":"Calle de Cruz Del Monaguillo, 3 Sanlucar De Barrameda C\u00e1diz 11540",
    "addr:housenumber":"3",
    "addr:postcode":"11540",
    "addr:street":"Calle De Cruz Del Monaguillo;Ca\u0301Diz",
    "iso:country":"ES",
    "sg:address":"Calle de Cruz Del Monaguillo, 3",
    "sg:city":"Sanlucar De Barrameda",
    "sg:orig_category":"Alimentaci\u00d3n General (al Por Mayor)",
    "sg:phone":"+34 956 36 04 17",
    "sg:postcode":"11540",
    "sg:province":"C\u00e1diz",
    "wof:name":"Gonzalez Ramos Carlos",
    "wof:placetype":"venue"
},
  "geometry": {"coordinates":[-6.3497357368,36.7722511292],"type":"Point"}
}