{
  "type": "Feature",
  "properties": {
    "addr:full":"Calle de Pelayo, 6 Zamora Zamora 49014",
    "addr:housenumber":"6",
    "addr:postcode":"49014",
    "addr:street":"Calle De Pelayo",
    "iso:country":"ES",
    "sg:address":"Calle de Pelayo, 6",
    "sg:city":"Zamora",
    "sg:orig_category":"Abogados",
    "sg:phone":"+34 980 53 31 45",
    "sg:postcode":"49014",
    "sg:province":"Zamora",
    "wof:name":"Franco Gutierrez Agustin",
    "wof:placetype":"venue"
},
  "geometry": {"coordinates":[-5.7434620857,41.5065307617],"type":"Point"}
}