{
  "type": "Feature",
  "properties": {
    "iso:country":"ES",
    "sg:address":"Calle de San Joaquin, 9",
    "sg:city":"Javea",
    "sg:orig_category":"Pintura Y Barniz (al Por Menor)",
    "sg:phone":"+34 965 79 38 86",
    "sg:postcode":"03730",
    "sg:province":"Alicante",
    "wof:name":"Pintura La Coma S.l.",
    "wof:placetype":"venue"
},
  "geometry": {"coordinates":[0.1609130055,38.7868499756],"type":"Point"}
}