{
  "type": "Feature",
  "properties": {
    "iso:country":"ES",
    "sg:address":"Calle de Ba\u00d1uetaibar Kalea, 21",
    "sg:city":"Amurrio",
    "sg:orig_category":"Promotores Constructores",
    "sg:phone":"+34 945 89 02 97",
    "sg:postcode":"01470",
    "sg:province":"\u00c1lava",
    "wof:name":"Construcciones Y Escavaciones Amurrio, S.l.",
    "wof:placetype":"venue"
},
  "geometry": {"coordinates":[-2.9957849979,43.0520172119],"type":"Point"}
}