{
  "type": "Feature",
  "properties": {
    "iso:country":"ES",
    "sg:address":"C/ Pascual Garcia Rocamora, 14",
    "sg:city":"Elche",
    "sg:orig_category":"Aguas (distribuci\u00d3n, Servicios)",
    "sg:phone":"+34 965 46 43 35",
    "sg:postcode":"03205",
    "sg:province":"Alicante",
    "wof:name":"Mancomunidad De Los Canales Del Taibilla",
    "wof:placetype":"venue"
},
  "geometry": {"coordinates":[-0.7128679752,38.2715187073],"type":"Point"}
}