{
  "type": "Feature",
  "properties": {
    "iso:country":"ES",
    "sg:address":"Pg Pla\u00c7a Major, 1",
    "sg:city":"Sabadell",
    "sg:orig_category":"Ropa Para Ni\u00d1os (al Por Menor)",
    "sg:phone":"+34 937 27 86 98",
    "sg:postcode":"08201",
    "sg:province":"Barcelona",
    "sg:website":"www.e-stradivarius.com",
    "wof:name":"Stradivarius Espa\u00f1a S.a.",
    "wof:placetype":"venue"
},
  "geometry": {"coordinates":[2.1086521149,41.5481071472],"type":"Point"}
}