{
  "type": "Feature",
  "properties": {
    "addr:full":"Calle de Gumersindo Azcarate, 17 Linares Ja\u00e9n 23700",
    "addr:housenumber":"17",
    "addr:postcode":"23700",
    "addr:street":"Calle De Gumersindo Azcarate;Jae\u0301N",
    "iso:country":"ES",
    "sg:address":"Calle de Gumersindo Azcarate, 17",
    "sg:city":"Linares",
    "sg:classifiers":[
        {
            "category":"Personal",
            "subcategory":"Barber",
            "type":"Services"
        }
    ],
    "sg:phone":"+34 953 69 44 01",
    "sg:postcode":"23700",
    "sg:province":"Ja\u00e9n",
    "sg:tags":[
        "caballeros",
        "de",
        "peluqueros"
    ],
    "wof:name":"Centro De Estetica Mu\u00f1oz S.l.",
    "wof:placetype":"venue"
},
  "geometry": {"coordinates":[-3.6351249218,38.0972137451],"type":"Point"}
}