{
  "type": "Feature",
  "properties": {
    "addr:full":"Carrer de Falset (de), 23 Torreforta Tarragona 43006",
    "addr:housenumber":"23",
    "addr:postcode":"43006",
    "addr:street":"Carrer De Falset De",
    "iso:country":"ES",
    "sg:address":"Carrer de Falset (de), 23",
    "sg:city":"Torreforta",
    "sg:orig_category":"Ropa Para Se\u00d1oras Y Caballeros (al Por Menor)",
    "sg:phone":"+34 977 54 44 90",
    "sg:postcode":"43006",
    "sg:province":"Tarragona",
    "wof:name":"Molins Guell Mercedes",
    "wof:placetype":"venue"
},
  "geometry": {"coordinates":[1.2184449434,41.1209220886],"type":"Point"}
}