{
  "type": "Feature",
  "properties": {
    "addr:full":"Avda Reina Mercedes, 13 Sevilla Sevilla 41012",
    "addr:housenumber":"13",
    "addr:postcode":"41012",
    "addr:street":"Avda Reina Mercedes",
    "iso:country":"ES",
    "sg:address":"Avda Reina Mercedes, 13",
    "sg:city":"Sevilla",
    "sg:orig_category":"Fotograf\u00cda Art\u00cdstica Y Retratos",
    "sg:phone":"+34 954 23 78 67",
    "sg:postcode":"41012",
    "sg:province":"Sevilla",
    "wof:name":"Ayuso Guixot Jaime",
    "wof:placetype":"venue"
},
  "geometry": {"coordinates":[-5.9861831665,37.3623847961],"type":"Point"}
}