{
  "type": "Feature",
  "properties": {
    "iso:country":"ES",
    "sg:address":"Carr Sant Pere Claver, 9",
    "sg:city":"Verdu",
    "sg:orig_category":"Asociaciones, Organismos Culturales Y Socioeducativos",
    "sg:phone":"+34 973 34 81 12",
    "sg:postcode":"25340",
    "sg:province":"Lleida",
    "wof:name":"Associacio Juvenil Bacus De Verdu",
    "wof:placetype":"venue"
},
  "geometry": {"coordinates":[1.1426600218,41.6103401184],"type":"Point"}
}