{
  "type": "Feature",
  "properties": {
    "iso:country":"ES",
    "sg:address":"Calle de Santa Maria Micaela, 2",
    "sg:city":"Valencia",
    "sg:orig_category":"Florister\u00cdas",
    "sg:phone":"+34 963 84 69 13",
    "sg:postcode":"46008",
    "sg:province":"Valencia",
    "sg:website":"www.mandaflor.com",
    "wof:name":"Rosello Tamarit Amparo",
    "wof:placetype":"venue"
},
  "geometry": {"coordinates":[-0.391030997,39.4723587036],"type":"Point"}
}