{
  "type": "Feature",
  "properties": {
    "addr:full":"Calle de Prado, 13 Madrid Madrid 28014",
    "addr:housenumber":"13",
    "addr:postcode":"madrid;28014",
    "addr:street":"Calle De Prado",
    "iso:country":"ES",
    "sg:address":"Calle de Prado, 13",
    "sg:city":"Madrid",
    "sg:orig_category":"Sellos De Goma Y Met\u00c1licos",
    "sg:phone":"+34 914 29 74 59",
    "sg:postcode":"28014",
    "sg:province":"Madrid",
    "wof:name":"Soto Garcia Pablo",
    "wof:placetype":"venue"
},
  "geometry": {"coordinates":[-3.6987671852,40.414855957],"type":"Point"}
}