{
  "type": "Feature",
  "properties": {
    "iso:country":"ES",
    "sg:address":"Calle de Iglesia, 10",
    "sg:city":"Gineta",
    "sg:orig_category":"Cajas Para Embalar",
    "sg:phone":"+34 967 27 51 13",
    "sg:postcode":"02110",
    "sg:province":"Albacete",
    "wof:name":"Caja Rural De Albacete",
    "wof:placetype":"venue"
},
  "geometry": {"coordinates":[-1.9966789484,39.113948822],"type":"Point"}
}