{
  "type": "Feature",
  "properties": {
    "iso:country":"ES",
    "sg:address":"Crt. Puertollano, S/n",
    "sg:city":"Almodovar Campo",
    "sg:orig_category":"Instalaci\u00d3n, Reparaci\u00d3n De Ascensores Y Montacargas",
    "sg:phone":"+34 926 69 83 93",
    "sg:postcode":"13580",
    "sg:province":"Ciudad Real",
    "wof:name":"Maepa Puertollano S.l.",
    "wof:placetype":"venue"
},
  "geometry": {"coordinates":[-4.1715488434,38.7124557495],"type":"Point"}
}