{
  "type": "Feature",
  "properties": {
    "iso:country":"ES",
    "sg:address":"Plaz San Luis Gonzaga, 8",
    "sg:city":"Donostia-san Sebastian",
    "sg:orig_category":"Trabajos De Fotocomposici\u00d3n",
    "sg:phone":"+34 943 39 42 98",
    "sg:postcode":"20017",
    "sg:province":"Guip\u00f9zcoa",
    "wof:name":"Aramburu Martinez Jaime",
    "wof:placetype":"venue"
},
  "geometry": {"coordinates":[-1.9392780066,43.3187904358],"type":"Point"}
}