{
  "type": "Feature",
  "properties": {
    "addr:full":"Plaz Santocildes, 21 Astorga Le\u00f3n 24700",
    "addr:housenumber":"21",
    "addr:postcode":"24700",
    "addr:street":"Plaz Santocildes;Leo\u0301N",
    "iso:country":"ES",
    "sg:address":"Plaz Santocildes, 21",
    "sg:city":"Astorga",
    "sg:orig_category":"Edici\u00d3n De Diarios, Revistas, Boletines",
    "sg:phone":"+34 987 60 40 97",
    "sg:postcode":"24700",
    "sg:province":"Le\u00f3n",
    "wof:name":"El Diario De Leon S.a.",
    "wof:placetype":"venue"
},
  "geometry": {"coordinates":[-6.0532841682,42.4577598572],"type":"Point"}
}