{
  "type": "Feature",
  "properties": {
    "iso:country":"ES",
    "sg:address":"Joanot Martorell, 41",
    "sg:city":"Massanassa",
    "sg:orig_category":"Transportes Por Carretera: Lotes Completos, Mercanc\u00cdas Diversas",
    "sg:phone":"+34 961 25 10 70",
    "sg:postcode":"46470",
    "sg:province":"Valencia",
    "wof:name":"Ruserva S.l.",
    "wof:placetype":"venue"
},
  "geometry": {"coordinates":[-0.3999519944,39.4133300781],"type":"Point"}
}