{
  "type": "Feature",
  "properties": {
    "iso:country":"ES",
    "sg:address":"Lloc Son Cladera, 1",
    "sg:city":"Palma",
    "sg:orig_category":"Peluquer\u00cdas, Peluquer\u00cda Mixta",
    "sg:phone":"+34 971 47 07 73",
    "sg:postcode":"07009",
    "sg:province":"Islas Baleares",
    "wof:name":"Ferrer Ruibal Maria",
    "wof:placetype":"venue"
},
  "geometry": {"coordinates":[2.6802430153,39.5992050171],"type":"Point"}
}