{
  "type": "Feature",
  "properties": {
    "addr:full":"Calle de San Roque, 1 Tobarra Albacete 02500",
    "addr:housenumber":"1",
    "addr:postcode":"02500",
    "addr:street":"Calle De San Roque",
    "iso:country":"ES",
    "sg:address":"Calle de San Roque, 1",
    "sg:city":"Tobarra",
    "sg:orig_category":"Asociaciones Y Clubs Deportivos",
    "sg:phone":"+34 967 32 83 51",
    "sg:postcode":"02500",
    "sg:province":"Albacete",
    "wof:name":"Parras Moya Candelaria",
    "wof:placetype":"venue"
},
  "geometry": {"coordinates":[-1.6895509958,38.591835022],"type":"Point"}
}