{
  "type": "Feature",
  "properties": {
    "iso:country":"ES",
    "sg:address":"Pl Concordia (la), 1",
    "sg:city":"Vall D'alba",
    "sg:orig_category":"Asesor\u00cda Fiscal Y Jur\u00cddica",
    "sg:phone":"+34 964 32 00 04",
    "sg:postcode":"12194",
    "sg:province":"Castell\u00f3n",
    "wof:name":"Cuevas Baticon Carlos",
    "wof:placetype":"venue"
},
  "geometry": {"coordinates":[-0.0579910018,39.987323761],"type":"Point"}
}