{
  "type": "Feature",
  "properties": {
    "addr:full":"Calle de Gabriel Ramos Bejarano, 110 Cordoba C\u00f3rdoba 14014",
    "addr:housenumber":"110",
    "addr:postcode":"14014",
    "addr:street":"Calle De Gabriel Ramos Bejarano;Co\u0301Rdoba",
    "iso:country":"ES",
    "sg:address":"Calle de Gabriel Ramos Bejarano, 110",
    "sg:city":"Cordoba",
    "sg:orig_category":"Muebles Y Accesorios Para Cocinas Y Cuartos De Ba\u00d1o (al Por Menor)",
    "sg:phone":"+34 957 32 66 75",
    "sg:postcode":"14014",
    "sg:province":"C\u00f3rdoba",
    "wof:name":"Perez Corripio Ricardo",
    "wof:placetype":"venue"
},
  "geometry": {"coordinates":[-4.7196440697,37.9004745483],"type":"Point"}
}