{
  "type": "Feature",
  "properties": {
    "addr:full":"Calle de Reyes Catolicos, 39 Utiel Valencia 46300",
    "addr:housenumber":"39",
    "addr:postcode":"46300",
    "addr:street":"Calle De Reyes Catolicos",
    "iso:country":"ES",
    "sg:address":"Calle de Reyes Catolicos, 39",
    "sg:city":"Utiel",
    "sg:orig_category":"Muebles, Minoristas",
    "sg:phone":"+34 962 16 82 39",
    "sg:postcode":"46300",
    "sg:province":"Valencia",
    "wof:name":"Jose Luis Lorente Saez S.l.",
    "wof:placetype":"venue"
},
  "geometry": {"coordinates":[-1.2062929869,39.5687026978],"type":"Point"}
}