{
  "type": "Feature",
  "properties": {
    "addr:full":"Calle de Castillo, 11 Vezdemarban Zamora 49840",
    "addr:housenumber":"11",
    "addr:postcode":"49840",
    "addr:street":"Calle De Castillo;Zamora",
    "iso:country":"ES",
    "sg:address":"Calle de Castillo, 11",
    "sg:city":"Vezdemarban",
    "sg:orig_category":"Estancos",
    "sg:phone":"+34 980 69 55 26",
    "sg:postcode":"49840",
    "sg:province":"Zamora",
    "wof:name":"Alonso Alfageme Vicenta",
    "wof:placetype":"venue"
},
  "geometry": {"coordinates":[-5.3659667969,41.6552391052],"type":"Point"}
}