{
  "type": "Feature",
  "properties": {
    "addr:full":"Calle de Oriente, 7 Quintanar Rey Cuenca 16220",
    "addr:housenumber":"7",
    "addr:postcode":"16220",
    "addr:street":"Calle De Oriente;Rey",
    "iso:country":"ES",
    "sg:address":"Calle de Oriente, 7",
    "sg:city":"Quintanar Rey",
    "sg:orig_category":"Materiales De Aislamiento T\u00c9rmico Y Ac\u00dastico",
    "sg:phone":"+34 967 49 53 39",
    "sg:postcode":"16220",
    "sg:province":"Cuenca",
    "wof:name":"Mu\u00f1oz Mu\u00f1oz Alonso",
    "wof:placetype":"venue"
},
  "geometry": {"coordinates":[-1.926510334,39.3456268311],"type":"Point"}
}