{
  "type": "Feature",
  "properties": {
    "iso:country":"ES",
    "sg:address":"Calle de Valencia, 45",
    "sg:city":"Salamanca",
    "sg:orig_category":"Abogados",
    "sg:phone":"+34 923 23 80 03",
    "sg:postcode":"37005",
    "sg:province":"Salamanca",
    "wof:name":"Ramos Vega Francisco Jose",
    "wof:placetype":"venue"
},
  "geometry": {"coordinates":[-5.662779808,40.971824646],"type":"Point"}
}