{
  "type": "Feature",
  "properties": {
    "iso:country":"ES",
    "sg:address":"Carrer de Mendez Nu\u00d1ez, 1",
    "sg:city":"Barcelona",
    "sg:orig_category":"Trabajos De Fotocomposici\u00d3n",
    "sg:phone":"+34 933 10 72 53",
    "sg:postcode":"08003",
    "sg:province":"Barcelona",
    "wof:name":"Ex Libris Sccl",
    "wof:placetype":"venue"
},
  "geometry": {"coordinates":[2.1781289577,41.3893203735],"type":"Point"}
}