{
  "type": "Feature",
  "properties": {
    "addr:full":"Pl Forti, 4 Palma Islas Baleares 07011",
    "addr:housenumber":"4",
    "addr:postcode":"07011",
    "addr:street":"Pl Forti",
    "iso:country":"ES",
    "sg:address":"Pl Forti, 4",
    "sg:city":"Palma",
    "sg:orig_category":"Asesor\u00cda Fiscal Y Jur\u00cddica",
    "sg:phone":"+34 971 45 26 11",
    "sg:postcode":"07011",
    "sg:province":"Islas Baleares",
    "wof:name":"Asesoria Fiscal Hornabeque 4 S.l.",
    "wof:placetype":"venue"
},
  "geometry": {"coordinates":[2.6433548927,39.5762367249],"type":"Point"}
}