{
  "type": "Feature",
  "properties": {
    "addr:full":"Carrer de Miquel Porcel, 13 Palma Islas Baleares 07014",
    "addr:housenumber":"13",
    "addr:postcode":"07014",
    "addr:street":"Carrer De Miquel Porcel",
    "iso:country":"ES",
    "sg:address":"Carrer de Miquel Porcel, 13",
    "sg:city":"Palma",
    "sg:orig_category":"Guarder\u00cdas",
    "sg:phone":"+34 971 28 36 32",
    "sg:postcode":"07014",
    "sg:province":"Islas Baleares",
    "wof:name":"Aleevic C.b",
    "wof:placetype":"venue"
},
  "geometry": {"coordinates":[2.6339375973,39.5765304565],"type":"Point"}
}