{
  "type": "Feature",
  "properties": {
    "addr:full":"Calle de Fernandez Ruano, 11 Cordoba C\u00f3rdoba 14003",
    "addr:housenumber":"11",
    "addr:postcode":"14003",
    "addr:street":"Calle De Fernandez Ruano;Co\u0301Rdoba",
    "iso:country":"ES",
    "sg:address":"Calle de Fernandez Ruano, 11",
    "sg:city":"Cordoba",
    "sg:orig_category":"Albergues",
    "sg:phone":"+34 957 20 28 54",
    "sg:postcode":"14003",
    "sg:province":"C\u00f3rdoba",
    "wof:name":"Salces Mariscal Maria Dolores",
    "wof:placetype":"venue"
},
  "geometry": {"coordinates":[-4.7831001282,37.8810958862],"type":"Point"}
}