{
  "type": "Feature",
  "properties": {
    "addr:full":"Pol Ind El Rubial, 4 Villena Alicante 03400",
    "addr:housenumber":"4",
    "addr:postcode":"03400",
    "iso:country":"ES",
    "sg:address":"Pol Ind El Rubial, 4",
    "sg:city":"Villena",
    "sg:orig_category":"Zapatos: Material, Suministros, Accesorios (fabricaci\u00d3n, Al Por Mayor)",
    "sg:phone":"+34 965 80 21 38",
    "sg:postcode":"03400",
    "sg:province":"Alicante",
    "wof:name":"Eustaquio Canto Cano S.l.",
    "wof:placetype":"venue"
},
  "geometry": {"coordinates":[-0.8688759804,38.6403198242],"type":"Point"}
}