{
  "type": "Feature",
  "properties": {
    "addr:full":"Avda Doctor Peset Aleixandre, 46 Valencia Valencia 46019",
    "addr:housenumber":"46",
    "addr:postcode":"46019",
    "addr:street":"Avda Doctor Peset Aleixandre",
    "iso:country":"ES",
    "sg:address":"Avda Doctor Peset Aleixandre, 46",
    "sg:city":"Valencia",
    "sg:orig_category":"Arqueolog\u00cda Y Patrimonio Cultural",
    "sg:phone":"+34 963 65 31 81",
    "sg:postcode":"46019",
    "sg:province":"Valencia",
    "wof:name":"Melchor Monserrat Jose Manuel",
    "wof:placetype":"venue"
},
  "geometry": {"coordinates":[-0.377703011,39.4913482666],"type":"Point"}
}