{
  "type": "Feature",
  "properties": {
    "iso:country":"ES",
    "sg:address":"Avda Andalucia, 8",
    "sg:city":"Linares",
    "sg:classifiers":[
        {
            "category":"Communications",
            "type":"Services"
        }
    ],
    "sg:phone":"+34 953 65 78 96",
    "sg:postcode":"23700",
    "sg:province":"Ja\u00e9n",
    "sg:tags":[
        "televisiones",
        "y",
        "radio"
    ],
    "wof:name":"Colado Olmo Luis Enrique",
    "wof:placetype":"venue"
},
  "geometry": {"coordinates":[-3.6404490471,38.092716217],"type":"Point"}
}