{
  "type": "Feature",
  "properties": {
    "addr:full":"Carrer de Rafael De Casanova, 73 Molins Rei Barcelona 08750",
    "addr:housenumber":"73",
    "addr:postcode":"08750",
    "addr:street":"Carrer De Rafael De Casanova;Barcelona",
    "iso:country":"ES",
    "sg:address":"Carrer de Rafael De Casanova, 73",
    "sg:city":"Molins Rei",
    "sg:orig_category":"Arquitectos",
    "sg:phone":"+34 936 68 68 23",
    "sg:postcode":"08750",
    "sg:province":"Barcelona",
    "wof:name":"Rivas Zaragueta Amalio Jaime",
    "wof:placetype":"venue"
},
  "geometry": {"coordinates":[2.0155930519,41.413028717],"type":"Point"}
}