{
  "type": "Feature",
  "properties": {
    "addr:full":"Urb Pacheca (la), S/n Benahavis M\u00e1laga 29679",
    "addr:postcode":"29679",
    "addr:street":"Urb Pacheca La S / N Benahavis Ma\u0301Laga",
    "iso:country":"ES",
    "sg:address":"Urb Pacheca (la), S/n",
    "sg:city":"Benahavis",
    "sg:orig_category":"Administradores De Bienes Y Delegados De Comunidades De Propietarios",
    "sg:phone":"+34 952 85 53 93",
    "sg:postcode":"29679",
    "sg:province":"M\u00e1laga",
    "wof:name":"Administraciones Nozal S.l.",
    "wof:placetype":"venue"
},
  "geometry": {"coordinates":[-5.0390534401,36.5248069763],"type":"Point"}
}