{
  "type": "Feature",
  "properties": {
    "addr:full":"Calle de Echegaray, 11 Marin Pontevedra 36900",
    "addr:housenumber":"11",
    "addr:postcode":"36900",
    "addr:street":"Calle De Echegaray",
    "iso:country":"ES",
    "sg:address":"Calle de Echegaray, 11",
    "sg:city":"Marin",
    "sg:orig_category":"Molduras, Junquillos, Listones Y Molduras Perforadas",
    "sg:phone":"+34 986 88 26 47",
    "sg:postcode":"36900",
    "sg:province":"Pontevedra",
    "wof:name":"Garcia Franco Luis",
    "wof:placetype":"venue"
},
  "geometry": {"coordinates":[-8.7034797668,42.3929023743],"type":"Point"}
}