{
  "type": "Feature",
  "properties": {
    "iso:country":"ES",
    "sg:address":"Calle de Cabeza, 14",
    "sg:city":"Madrid",
    "sg:orig_category":"Agencias Y Agentes Comerciales, Representantes",
    "sg:phone":"+34 914 67 22 24",
    "sg:postcode":"28012",
    "sg:province":"Madrid",
    "wof:name":"Peldepa S.l.l.",
    "wof:placetype":"venue"
},
  "geometry": {"coordinates":[-3.7030029297,40.4118537903],"type":"Point"}
}