{
  "type": "Feature",
  "properties": {
    "iso:country":"ES",
    "sg:address":"Carr Moli De La Vila, 6",
    "sg:city":"Algemesi",
    "sg:orig_category":"Promotores Constructores",
    "sg:phone":"+34 962 48 08 13",
    "sg:postcode":"46680",
    "sg:province":"Valencia",
    "wof:name":"Blue Building S.l",
    "wof:placetype":"venue"
},
  "geometry": {"coordinates":[-0.4372209907,39.1889038086],"type":"Point"}
}