{
  "type": "Feature",
  "properties": {
    "iso:country":"ES",
    "sg:address":"Avda Zamora, 8",
    "sg:city":"Tordesillas",
    "sg:orig_category":"\u00d3pticos Optometristas (al Por Menor)",
    "sg:phone":"+34 983 79 66 35",
    "sg:postcode":"47100",
    "sg:province":"Valladolid",
    "wof:name":"Dea Centro De Optometria S.l.",
    "wof:placetype":"venue"
},
  "geometry": {"coordinates":[-5.0041518211,41.5031700134],"type":"Point"}
}