{
  "type": "Feature",
  "properties": {
    "addr:full":"Avda Paskual Abaroa Etorbidea, 39 Lekeitio Vizcaya 48280",
    "addr:housenumber":"39",
    "addr:postcode":"48280",
    "addr:street":"Avda Paskual Abaroa Etorbidea",
    "iso:country":"ES",
    "sg:address":"Avda Paskual Abaroa Etorbidea, 39",
    "sg:city":"Lekeitio",
    "sg:orig_category":"Empresas De Desmonte",
    "sg:phone":"+34 946 84 30 22",
    "sg:postcode":"48280",
    "sg:province":"Vizcaya",
    "wof:name":"Itxasgas S.l.",
    "wof:placetype":"venue"
},
  "geometry": {"coordinates":[-2.5033740997,43.3652877808],"type":"Point"}
}