{
  "type": "Feature",
  "properties": {
    "iso:country":"ES",
    "sg:address":"Calle de Rembrandt, 5",
    "sg:city":"Tafira Alta",
    "sg:orig_category":"\u00d3ptica: Instrumentos (fabricaci\u00d3n)",
    "sg:phone":"+34 928 35 56 09",
    "sg:postcode":"35017",
    "sg:province":"Las Palmas",
    "sg:website":"www.dilab.net.",
    "wof:name":"Dilab Distribuciones De Laboratorios S.l.",
    "wof:placetype":"venue"
},
  "geometry": {"coordinates":[-15.4688606262,28.0556869507],"type":"Point"}
}