{
  "type": "Feature",
  "properties": {
    "addr:full":"Las Eras, 3 Balazote Albacete 02320",
    "addr:housenumber":"3",
    "addr:postcode":"02320",
    "addr:street":"Las Eras",
    "iso:country":"ES",
    "sg:address":"Las Eras, 3",
    "sg:city":"Balazote",
    "sg:orig_category":"Restaurantes",
    "sg:phone":"+34 967 36 01 21",
    "sg:postcode":"02320",
    "sg:province":"Albacete",
    "wof:name":"Hosteleria Santa Monica",
    "wof:placetype":"venue"
},
  "geometry": {"coordinates":[-2.1482720375,38.8859901428],"type":"Point"}
}