{
  "type": "Feature",
  "properties": {
    "iso:country":"ES",
    "sg:address":"Carrer de Can Fortuny, 3",
    "sg:city":"Palma",
    "sg:orig_category":"Arquitectos",
    "sg:phone":"+34 971 71 73 55",
    "sg:postcode":"07001",
    "sg:province":"Islas Baleares",
    "wof:name":"Bibiloni Cerda Company Arquitectes C.b.",
    "wof:placetype":"venue"
},
  "geometry": {"coordinates":[2.6511790752,39.5685882568],"type":"Point"}
}