{
  "type": "Feature",
  "properties": {
    "addr:full":"Calle de Alfonso Ix, 2 Zamora Zamora 49014",
    "addr:housenumber":"2",
    "addr:postcode":"49014",
    "addr:street":"Calle De Alfonso Ix",
    "iso:country":"ES",
    "sg:address":"Calle de Alfonso Ix, 2",
    "sg:city":"Zamora",
    "sg:orig_category":"Informaci\u00d3n Financiera Y Comercial",
    "sg:phone":"+34 980 51 48 34",
    "sg:postcode":"49014",
    "sg:province":"Zamora",
    "wof:name":"Gonzalez Juan Maria Jesus",
    "wof:placetype":"venue"
},
  "geometry": {"coordinates":[-5.7418675423,41.5073890686],"type":"Point"}
}