{
  "type": "Feature",
  "properties": {
    "iso:country":"ES",
    "sg:address":"Carrer de Cartoixa Vallparadis, 10",
    "sg:city":"Terrassa",
    "sg:orig_category":"Electricidad: Instaladores",
    "sg:phone":"+34 937 86 10 59",
    "sg:postcode":"08222",
    "sg:province":"Barcelona",
    "sg:website":"www.tesla.es",
    "wof:name":"Tesla Industrial S.a.",
    "wof:placetype":"venue"
},
  "geometry": {"coordinates":[2.020252943,41.5643196106],"type":"Point"}
}