{
  "type": "Feature",
  "properties": {
    "addr:full":"Avda America, 9 Madrid Madrid 28002",
    "addr:housenumber":"9",
    "addr:postcode":"madrid;28002",
    "addr:street":"Avda America",
    "iso:country":"ES",
    "sg:address":"Avda America, 9",
    "sg:city":"Madrid",
    "sg:orig_category":"Art\u00cdculos De Regalo (al Por Menor)",
    "sg:phone":"+34 915 64 32 66",
    "sg:postcode":"28002",
    "sg:province":"Madrid",
    "wof:name":"Sotillos Frias Joaquin",
    "wof:placetype":"venue"
},
  "geometry": {"coordinates":[-3.6768479347,40.4382514954],"type":"Point"}
}