{
  "type": "Feature",
  "properties": {
    "addr:full":"Calle de Leo, 7 Madrid Madrid 28007",
    "addr:housenumber":"7",
    "addr:postcode":"madrid;28007",
    "addr:street":"Calle De Leo",
    "iso:country":"ES",
    "sg:address":"Calle de Leo, 7",
    "sg:city":"Madrid",
    "sg:orig_category":"Fabricaci\u00d3n, Distribuci\u00d3n De Material Para La Climatizaci\u00d3n, Aireaci\u00d3n Y Ventilaci\u00d3n",
    "sg:phone":"+34 914 09 65 94",
    "sg:postcode":"28007",
    "sg:province":"Madrid",
    "wof:name":"Tecnivel Industrial S.a.",
    "wof:placetype":"venue"
},
  "geometry": {"coordinates":[-3.6674718857,40.4074249268],"type":"Point"}
}