{
  "type": "Feature",
  "properties": {
    "addr:full":"Carrer de Pare Roldos, 7 Barcelona Barcelona 08041",
    "addr:housenumber":"7",
    "addr:postcode":"08041",
    "addr:street":"Carrer De Pare Roldos",
    "iso:country":"ES",
    "sg:address":"Carrer de Pare Roldos, 7",
    "sg:city":"Barcelona",
    "sg:orig_category":"Ense\u00d1anza: Idiomas",
    "sg:phone":"+34 933 51 49 24",
    "sg:postcode":"08041",
    "sg:province":"Barcelona",
    "wof:name":"Centro De Ense\u00d1anza Maragall S.a.",
    "wof:placetype":"venue"
},
  "geometry": {"coordinates":[2.1796779633,41.4211158752],"type":"Point"}
}