{
  "type": "Feature",
  "properties": {
    "addr:full":"Plaz Espa\u00d1a, 4 Santiba\u00e7ez-zarzaguda Burgos 09150",
    "addr:housenumber":"4",
    "addr:postcode":"09150",
    "addr:street":"Plaz Espan\u0303A",
    "iso:country":"ES",
    "sg:address":"Plaz Espa\u00d1a, 4",
    "sg:city":"Santiba\u00e7ez-zarzaguda",
    "sg:orig_category":"Iglesia Cat\u00d3lica",
    "sg:phone":"+34 947 45 30 63",
    "sg:postcode":"09150",
    "sg:province":"Burgos",
    "wof:name":"Parroquia De San Nicolas De Bari",
    "wof:placetype":"venue"
},
  "geometry": {"coordinates":[-3.8045270443,42.4887580872],"type":"Point"}
}