{
  "type": "Feature",
  "properties": {
    "addr:full":"Av Catalunya, 22 Tarragona Tarragona 43002",
    "addr:housenumber":"22",
    "addr:postcode":"43002",
    "addr:street":"Av Catalunya",
    "iso:country":"ES",
    "sg:address":"Av Catalunya, 22",
    "sg:city":"Tarragona",
    "sg:orig_category":"Mercer\u00cda (fabricaci\u00d3n, Al Por Mayor)",
    "sg:phone":"+34 977 22 52 21",
    "sg:postcode":"43002",
    "sg:province":"Tarragona",
    "wof:name":"Sole Nu\u00f1ez Montserrat",
    "wof:placetype":"venue"
},
  "geometry": {"coordinates":[1.2517830133,41.1205558777],"type":"Point"}
}