{
  "type": "Feature",
  "properties": {
    "iso:country":"ES",
    "sg:address":"Julian Etxeberria Kalea, 10",
    "sg:city":"Eibar",
    "sg:orig_category":"Aparcamientos (infraestructuras, Accesorios)",
    "sg:phone":"+34 943 20 22 05",
    "sg:postcode":"20600",
    "sg:province":"Guip\u00f9zcoa",
    "wof:name":"Lizarralde Aizpiri Miguel Mario",
    "wof:placetype":"venue"
},
  "geometry": {"coordinates":[-2.4698519707,43.1856689453],"type":"Point"}
}