{
  "type": "Feature",
  "properties": {
    "addr:full":"Calle de Cervantes, 6 San Vicente De Barakaldo Vizcaya 48901",
    "addr:housenumber":"6",
    "addr:postcode":"48901",
    "addr:street":"Calle De Cervantes",
    "iso:country":"ES",
    "sg:address":"Calle de Cervantes, 6",
    "sg:city":"San Vicente De Barakaldo",
    "sg:orig_category":"Plomeros",
    "sg:phone":"+34 944 38 54 88",
    "sg:postcode":"48901",
    "sg:province":"Vizcaya",
    "wof:name":"Ausin Nicolas Jose Luis",
    "wof:placetype":"venue"
},
  "geometry": {"coordinates":[-2.9887719154,43.3003692627],"type":"Point"}
}