{
  "type": "Feature",
  "properties": {
    "iso:country":"ES",
    "sg:address":"Carrer de Orient, 38",
    "sg:city":"Hospitalet Llobregat",
    "sg:orig_category":"Cristaler\u00cdas",
    "sg:phone":"+34 933 34 78 27",
    "sg:postcode":"08904",
    "sg:province":"Barcelona",
    "wof:name":"Martinez Martin Alfonso",
    "wof:placetype":"venue"
},
  "geometry": {"coordinates":[2.1193590164,41.3719749451],"type":"Point"}
}