{
  "type": "Feature",
  "properties": {
    "addr:full":"Carretera Mora De Ebro, Km. 0020,2 Tivissa Tarragona 43746",
    "addr:housenumber":"km.",
    "addr:postcode":"43746",
    "addr:street":"Carretera Mora De Ebro;0020,2",
    "iso:country":"ES",
    "sg:address":"Carretera Mora De Ebro, Km. 0020,2",
    "sg:city":"Tivissa",
    "sg:orig_category":"Distribuci\u00d3n De Petr\u00d3leo Y Derivados",
    "sg:phone":"+34 977 41 73 10",
    "sg:postcode":"43746",
    "sg:province":"Tarragona",
    "wof:name":"Les Cuatre Rodes S.l.",
    "wof:placetype":"venue"
},
  "geometry": {"coordinates":[0.7349410057,41.0436477661],"type":"Point"}
}