{
  "type": "Feature",
  "properties": {
    "addr:full":"Rua Conde Torrecedeira, 104 Vigo Pontevedra 36208",
    "addr:housenumber":"104",
    "addr:postcode":"36208",
    "addr:street":"Rua Conde Torrecedeira",
    "iso:country":"ES",
    "sg:address":"Rua Conde Torrecedeira, 104",
    "sg:city":"Vigo",
    "sg:orig_category":"Carnicer\u00cdas, Carnicer\u00cdas",
    "sg:phone":"+34 986 29 00 38",
    "sg:postcode":"36208",
    "sg:province":"Pontevedra",
    "wof:name":"Martinez Costas Francisco",
    "wof:placetype":"venue"
},
  "geometry": {"coordinates":[-8.7356719971,42.2248649597],"type":"Point"}
}