{
  "type": "Feature",
  "properties": {
    "addr:full":"Calle de Carmen Conde, 65 Cartagena Murcia 30204",
    "addr:housenumber":"65",
    "addr:postcode":"30204",
    "addr:street":"Calle De Carmen Conde",
    "iso:country":"ES",
    "sg:address":"Calle de Carmen Conde, 65",
    "sg:city":"Cartagena",
    "sg:orig_category":"Asociaciones Y Clubs Deportivos",
    "sg:phone":"+34 968 31 67 04",
    "sg:postcode":"30204",
    "sg:province":"Murcia",
    "wof:name":"Carthago Sport S.l.",
    "wof:placetype":"venue"
},
  "geometry": {"coordinates":[-0.9918428063,37.6170921326],"type":"Point"}
}