{
  "type": "Feature",
  "properties": {
    "iso:country":"ES",
    "sg:address":"Calle de Arriba, 2",
    "sg:city":"Grazalema",
    "sg:classifiers":[
        {
            "category":"Communications",
            "type":"Services"
        }
    ],
    "sg:phone":"+34 956 13 20 77",
    "sg:postcode":"11610",
    "sg:province":"C\u00e1diz",
    "sg:tags":[
        "televisiones",
        "y",
        "radio"
    ],
    "wof:name":"Ayuntamiento De Grazalema",
    "wof:placetype":"venue"
},
  "geometry": {"coordinates":[-5.3664851189,36.759311676],"type":"Point"}
}