{
  "type": "Feature",
  "properties": {
    "addr:full":"Uparan, 12 Aduna Guip\u00f9zcoa 20150",
    "addr:housenumber":"12",
    "addr:postcode":"20150",
    "addr:street":"Uparan;Guipu\u0300Zcoa",
    "iso:country":"ES",
    "sg:address":"Uparan, 12",
    "sg:city":"Aduna",
    "sg:orig_category":"Calderer\u00cda",
    "sg:phone":"+34 943 69 42 14",
    "sg:postcode":"20150",
    "sg:province":"Guip\u00f9zcoa",
    "wof:name":"Caldereria Aburuza S.l.",
    "wof:placetype":"venue"
},
  "geometry": {"coordinates":[-2.0459470749,43.1975631714],"type":"Point"}
}