{
  "type": "Feature",
  "properties": {
    "iso:country":"ES",
    "sg:address":"Plaz Saraspe Plaza, 3",
    "sg:city":"Gernika-lumo",
    "sg:orig_category":"Tapiceros Y Tapiceros",
    "sg:phone":"+34 946 27 03 15",
    "sg:postcode":"48300",
    "sg:province":"Vizcaya",
    "sg:website":"www.etarte.com",
    "wof:name":"Etarte Interiorismo S.l.l",
    "wof:placetype":"venue"
},
  "geometry": {"coordinates":[-97.78224945069999,45.7040786743],"type":"Point"}
}