{
  "type": "Feature",
  "properties": {
    "iso:country":"ES",
    "sg:address":"Avda Milagrosa, 24",
    "sg:city":"Carballo",
    "sg:classifiers":[
        {
            "category":"Personal",
            "subcategory":"Barber",
            "type":"Services"
        }
    ],
    "sg:phone":"+34 981 75 54 94",
    "sg:postcode":"15100",
    "sg:province":"La Coru\u00f1a",
    "sg:tags":[
        "caballeros",
        "de",
        "peluqueros"
    ],
    "wof:name":"Nieto Varela Dolores",
    "wof:placetype":"venue"
},
  "geometry": {"coordinates":[-8.6873235703,43.2087631226],"type":"Point"}
}