{
  "type": "Feature",
  "properties": {
    "iso:country":"ES",
    "sg:address":"Calle de Conde Vallellano, 38",
    "sg:city":"Requena",
    "sg:orig_category":"Peluqueros: De Se\u00d1oras",
    "sg:phone":"+34 962 30 18 52",
    "sg:postcode":"46340",
    "sg:province":"Valencia",
    "wof:name":"Montes Jara Luisa",
    "wof:placetype":"venue"
},
  "geometry": {"coordinates":[-1.1041631699,39.4871444702],"type":"Point"}
}