{
  "type": "Feature",
  "properties": {
    "addr:full":"Calle de Martianes, 10 Fuente Maestre Badajoz 06360",
    "addr:housenumber":"10",
    "addr:postcode":"06360",
    "addr:street":"Calle De Martianes",
    "iso:country":"ES",
    "sg:address":"Calle de Martianes, 10",
    "sg:city":"Fuente Maestre",
    "sg:orig_category":"Promotores Constructores",
    "sg:phone":"+34 924 53 05 31",
    "sg:postcode":"06360",
    "sg:province":"Badajoz",
    "wof:name":"Arevalo Sanchez Jose",
    "wof:placetype":"venue"
},
  "geometry": {"coordinates":[-6.4475913048,38.5255737305],"type":"Point"}
}