{
  "type": "Feature",
  "properties": {
    "iso:country":"ES",
    "sg:address":"Calle de Gran Capitan, 41",
    "sg:city":"Bola\u00e7os De Calatrava",
    "sg:orig_category":"Venta Al Preg\u00d3n",
    "sg:phone":"+34 926 87 03 89",
    "sg:postcode":"13260",
    "sg:province":"Ciudad Real",
    "wof:name":"Delgado Fernandez Eufemiano",
    "wof:placetype":"venue"
},
  "geometry": {"coordinates":[-3.6622788906,38.9041290283],"type":"Point"}
}