{
  "type": "Feature",
  "properties": {
    "addr:full":"Calle de San Martin De Porres, 22 Madrid Madrid 28035",
    "addr:housenumber":"22",
    "addr:postcode":"madrid;28035",
    "addr:street":"Calle De San Martin De Porres",
    "iso:country":"ES",
    "sg:address":"Calle de San Martin De Porres, 22",
    "sg:city":"Madrid",
    "sg:orig_category":"Centros Empresariales",
    "sg:phone":"+34 913 86 53 18",
    "sg:postcode":"28035",
    "sg:province":"Madrid",
    "wof:name":"Investigacion Cualitativa Y Consulltoria S.c",
    "wof:placetype":"venue"
},
  "geometry": {"coordinates":[-3.7287490368,40.4712524414],"type":"Point"}
}