{
  "type": "Feature",
  "properties": {
    "addr:full":"Mouri\u00f1as, 48 Capela-neves La Coru\u00f1a 15613",
    "addr:housenumber":"48",
    "addr:postcode":"15613",
    "addr:street":"Mourin\u0303As;La Corun\u0303A",
    "iso:country":"ES",
    "sg:address":"Mouri\u00f1as, 48",
    "sg:city":"Capela-neves",
    "sg:orig_category":"Electrodom\u00c9sticos (al Por Menor)",
    "sg:phone":"+34 981 45 90 75",
    "sg:postcode":"15613",
    "sg:province":"La Coru\u00f1a",
    "wof:name":"Perez Feal Manuel",
    "wof:placetype":"venue"
},
  "geometry": {"coordinates":[-8.0707349777,43.4355812073],"type":"Point"}
}