{
  "type": "Feature",
  "properties": {
    "iso:country":"ES",
    "sg:address":"Calle de Doctor Esteban San Mateo, S/n",
    "sg:city":"San Pedro Alcantara",
    "sg:orig_category":"Molduras, Junquillos, Listones Y Molduras Perforadas",
    "sg:phone":"+34 952 78 33 88",
    "sg:postcode":"29670",
    "sg:province":"M\u00e1laga",
    "wof:name":"Cristobal Holgado Garcia Y Humberto Holgado Garcia S.cv.",
    "wof:placetype":"venue"
},
  "geometry": {"coordinates":[-4.9947628975,36.48412323],"type":"Point"}
}