{
  "type": "Feature",
  "properties": {
    "iso:country":"ES",
    "sg:address":"Ptda Roig, 18",
    "sg:city":"Javea",
    "sg:orig_category":"Cerrajer\u00cda, Ferrallista",
    "sg:phone":"+34 965 79 13 10",
    "sg:postcode":"03730",
    "sg:province":"Alicante",
    "wof:name":"Castellanos Garcia Jose Antonio",
    "wof:placetype":"venue"
},
  "geometry": {"coordinates":[0.1668650061,38.7890739441],"type":"Point"}
}