{
  "type": "Feature",
  "properties": {
    "addr:full":"Carrer de Muralla De Santa Tecla, 60 Montblanc Tarragona 43400",
    "addr:housenumber":"60",
    "addr:postcode":"43400",
    "addr:street":"Carrer De Muralla De Santa Tecla",
    "iso:country":"ES",
    "sg:address":"Carrer de Muralla De Santa Tecla, 60",
    "sg:city":"Montblanc",
    "sg:orig_category":"Electricidad Veh\u00cdculo",
    "sg:phone":"+34 977 86 10 28",
    "sg:postcode":"43400",
    "sg:province":"Tarragona",
    "wof:name":"Cabestany Olle Ramon",
    "wof:placetype":"venue"
},
  "geometry": {"coordinates":[1.1643300056,41.3753395081],"type":"Point"}
}