{
  "type": "Feature",
  "properties": {
    "iso:country":"ES",
    "sg:address":"Calle de O'donnell, 20",
    "sg:city":"Sevilla",
    "sg:orig_category":"Agencias Y Asesores De Publicidad",
    "sg:phone":"+34 954 50 00 36",
    "sg:postcode":"41001",
    "sg:province":"Sevilla",
    "wof:name":"Publicidad Logos S.l.",
    "wof:placetype":"venue"
},
  "geometry": {"coordinates":[-5.9959673882,37.3918457031],"type":"Point"}
}