{
  "type": "Feature",
  "properties": {
    "addr:full":"Gajano, S/n Gajano Cantabria 39792",
    "addr:housenumber":"s / n",
    "addr:postcode":"39792",
    "addr:street":"Gajano",
    "iso:country":"ES",
    "sg:address":"Gajano, S/n",
    "sg:city":"Gajano",
    "sg:orig_category":"Cajas De Ahorro",
    "sg:phone":"+34 942 50 20 37",
    "sg:postcode":"39792",
    "sg:province":"Cantabria",
    "sg:website":"www.cajacantabria.es",
    "wof:name":"Cableuropa",
    "wof:placetype":"venue"
},
  "geometry": {"coordinates":[-3.7661499977,43.4118690491],"type":"Point"}
}