{
  "type": "Feature",
  "properties": {
    "addr:full":"Calle de Porto Alegre, 2 Alcorcon Madrid 28925",
    "addr:housenumber":"2",
    "addr:postcode":"28925",
    "addr:street":"Calle De Porto Alegre",
    "iso:country":"ES",
    "sg:address":"Calle de Porto Alegre, 2",
    "sg:city":"Alcorcon",
    "sg:orig_category":"Quincaller\u00cda (al Por Menor)",
    "sg:phone":"+34 916 10 03 67",
    "sg:postcode":"28925",
    "sg:province":"Madrid",
    "wof:name":"Ferreteria Ferrecasa S.l.",
    "wof:placetype":"venue"
},
  "geometry": {"coordinates":[-3.8154640198,40.3541908264],"type":"Point"}
}