{
  "type": "Feature",
  "properties": {
    "addr:full":"Plaz Calvo Sotelo, 1 Aceituna C\u00e1ceres 10666",
    "addr:housenumber":"1",
    "addr:postcode":"10666",
    "addr:street":"Plaz Calvo Sotelo;Ca\u0301Ceres",
    "iso:country":"ES",
    "sg:address":"Plaz Calvo Sotelo, 1",
    "sg:city":"Aceituna",
    "sg:orig_category":"Administraciones Regionales, Departamentales Y Locales",
    "sg:phone":"+34 927 43 10 82",
    "sg:postcode":"10666",
    "sg:province":"C\u00e1ceres",
    "wof:name":"Ayuntamiento De Aceituna",
    "wof:placetype":"venue"
},
  "geometry": {"coordinates":[-6.3324446678,40.1496658325],"type":"Point"}
}