{
  "type": "Feature",
  "properties": {
    "addr:full":"Calle de Espoz Y Mina, 22 Madrid Madrid 28012",
    "addr:housenumber":"22",
    "addr:postcode":"madrid;28012",
    "addr:street":"Calle De Espoz Y Mina",
    "iso:country":"ES",
    "sg:address":"Calle de Espoz Y Mina, 22",
    "sg:city":"Madrid",
    "sg:orig_category":"Tiendas De Grano, Frutas Y Legumbres Secas (al Por Menor)",
    "sg:phone":"+34 915 32 34 71",
    "sg:postcode":"28012",
    "sg:province":"Madrid",
    "wof:name":"Cerrada Somolinos Juan Jose",
    "wof:placetype":"venue"
},
  "geometry": {"coordinates":[-3.7024900913,40.4153327942],"type":"Point"}
}