{
  "type": "Feature",
  "properties": {
    "addr:full":"Calle de Carlos Senti, 45 Denia Alicante 03700",
    "addr:housenumber":"45",
    "addr:postcode":"03700",
    "addr:street":"Calle De Carlos Senti",
    "iso:country":"ES",
    "sg:address":"Calle de Carlos Senti, 45",
    "sg:city":"Denia",
    "sg:orig_category":"M\u00c9dicos: Medicina General Orientada A La Homeopat\u00cda",
    "sg:phone":"+34 965 78 83 95",
    "sg:postcode":"03700",
    "sg:province":"Alicante",
    "wof:name":"Salvador Villalba Ana",
    "wof:placetype":"venue"
},
  "geometry": {"coordinates":[0.1102619022,38.8375205994],"type":"Point"}
}