{
  "type": "Feature",
  "properties": {
    "iso:country":"ES",
    "sg:address":"Calle de Puenteareas, 5",
    "sg:city":"Madrid",
    "sg:orig_category":"Audiovisuales (producci\u00d3n, Edici\u00d3n, Realizaci\u00d3n)",
    "sg:phone":"+34 914 13 03 15",
    "sg:postcode":"28002",
    "sg:province":"Madrid",
    "sg:website":"www.acteonproducciones.com",
    "wof:name":"Acteon Producciones",
    "wof:placetype":"venue"
},
  "geometry": {"coordinates":[-3.6709117889,40.4426116943],"type":"Point"}
}