{
  "type": "Feature",
  "properties": {
    "addr:full":"Poligon Baix Ebre, S/n Camp-redo Tarragona 43897",
    "addr:housenumber":"s / n",
    "addr:postcode":"43897",
    "iso:country":"ES",
    "sg:address":"Poligon Baix Ebre, S/n",
    "sg:city":"Camp-redo",
    "sg:orig_category":"Confecci\u00d3n : Material, Suministros Y Accesorios",
    "sg:phone":"+34 977 45 40 01",
    "sg:postcode":"43897",
    "sg:province":"Tarragona",
    "wof:name":"Ykk Espa\u00f1a S.a.",
    "wof:placetype":"venue"
},
  "geometry": {"coordinates":[1.2454571724,41.11901474],"type":"Point"}
}