{
  "type": "Feature",
  "properties": {
    "iso:country":"ES",
    "sg:address":"Calle de Cortes De Aragon, 7",
    "sg:city":"Erla",
    "sg:orig_category":"Maquinaria Para Industrias Diversas",
    "sg:phone":"+34 976 69 40 45",
    "sg:postcode":"50611",
    "sg:province":"Zaragoza",
    "wof:name":"Tarraguel Liso Saturnino",
    "wof:placetype":"venue"
},
  "geometry": {"coordinates":[-0.9494405985,42.1167259216],"type":"Point"}
}