{
  "type": "Feature",
  "properties": {
    "addr:full":"Calle de San Bartolome Kalea, 23 Gernika-lumo Vizcaya 48300",
    "addr:housenumber":"23",
    "addr:postcode":"48300",
    "addr:street":"Calle De San Bartolome Kalea",
    "iso:country":"ES",
    "sg:address":"Calle de San Bartolome Kalea, 23",
    "sg:city":"Gernika-lumo",
    "sg:orig_category":"Electricidad: Instaladores",
    "sg:phone":"+34 946 25 67 07",
    "sg:postcode":"48300",
    "sg:province":"Vizcaya",
    "wof:name":"Jorge O\u00f1arte Etxebarria Enbeitia",
    "wof:placetype":"venue"
},
  "geometry": {"coordinates":[-2.6739089489,43.3182487488],"type":"Point"}
}