{
  "type": "Feature",
  "properties": {
    "addr:full":"Calle de Reyes Catolicos, 75 Palmas De Gran Canaria Las Palmas 35001",
    "addr:housenumber":"75",
    "addr:postcode":"35001",
    "addr:street":"Calle De Reyes Catolicos",
    "iso:country":"ES",
    "sg:address":"Calle de Reyes Catolicos, 75",
    "sg:city":"Palmas De Gran Canaria",
    "sg:orig_category":"Abogados",
    "sg:phone":"+34 928 33 13 60",
    "sg:postcode":"35001",
    "sg:province":"Las Palmas",
    "wof:name":"Noble Rodriguez Rosa Maria",
    "wof:placetype":"venue"
},
  "geometry": {"coordinates":[-15.4144611359,28.0971641541],"type":"Point"}
}