{
  "type": "Feature",
  "properties": {
    "iso:country":"ES",
    "sg:address":"Calle de Esperanza, 60",
    "sg:city":"Calasparra",
    "sg:orig_category":"Mec\u00c1nico Del Autom\u00d3vil",
    "sg:phone":"+34 968 72 11 01",
    "sg:postcode":"30420",
    "sg:province":"Murcia",
    "wof:name":"Perez Rodriguez Fernando",
    "wof:placetype":"venue"
},
  "geometry": {"coordinates":[-1.698546052,38.2282791138],"type":"Point"}
}