{
  "type": "Feature",
  "properties": {
    "iso:country":"ES",
    "sg:address":"Pl Pau Casals, 7",
    "sg:city":"Canet Mar",
    "sg:orig_category":"Ropa Para Beb\u00c9s Y Ni\u00d1os (confecci\u00d3n, Al Por Mayor)",
    "sg:phone":"+34 937 95 61 84",
    "sg:postcode":"08360",
    "sg:province":"Barcelona",
    "wof:name":"Rosell Del Pozo Jordi",
    "wof:placetype":"venue"
},
  "geometry": {"coordinates":[2.5785698891,41.595954895],"type":"Point"}
}