{
  "type": "Feature",
  "properties": {
    "addr:full":"Prje. Asensao, S/n Cieza Murcia 30530",
    "addr:housenumber":"s / n",
    "addr:postcode":"30530",
    "iso:country":"ES",
    "sg:address":"Prje. Asensao, S/n",
    "sg:city":"Cieza",
    "sg:orig_category":"Distribuci\u00d3n De Petr\u00d3leo Y Derivados",
    "sg:phone":"+34 968 76 10 28",
    "sg:postcode":"30530",
    "sg:province":"Murcia",
    "wof:name":"Repsol Ypf S.a.",
    "wof:placetype":"venue"
},
  "geometry": {"coordinates":[-1.4241739511,38.2379302979],"type":"Point"}
}