{
  "type": "Feature",
  "properties": {
    "addr:full":"Calle de Estanislao Figueras, 4 Madrid Madrid 28008",
    "addr:housenumber":"4",
    "addr:postcode":"28008",
    "addr:street":"Calle De Estanislao Figueras",
    "iso:country":"ES",
    "sg:address":"Calle de Estanislao Figueras, 4",
    "sg:city":"Madrid",
    "sg:orig_category":"Abogados",
    "sg:phone":"+34 915 41 13 36",
    "sg:postcode":"28008",
    "sg:province":"Madrid",
    "wof:name":"Mendoza Tarsitano Juan Carlos",
    "wof:placetype":"venue"
},
  "geometry": {"coordinates":[-3.7175550461,40.4214324951],"type":"Point"}
}