{
  "type": "Feature",
  "properties": {
    "addr:full":"Barr Abajo, S/n Igollo Cantabria 39608",
    "addr:housenumber":"s",
    "addr:postcode":"39608",
    "addr:street":"/ N",
    "iso:country":"ES",
    "sg:address":"Barr Abajo, S/n",
    "sg:city":"Igollo",
    "sg:orig_category":"Deportes Y Ocio: Art\u00cdculos Y Equipos (al Por Mayor)",
    "sg:phone":"+34 942 26 93 33",
    "sg:postcode":"39608",
    "sg:province":"Cantabria",
    "sg:website":"www.mmbc.es",
    "wof:name":"Maria Del Mar Bolado Componentes S.l.",
    "wof:placetype":"venue"
},
  "geometry": {"coordinates":[-3.8830139637,43.4323272705],"type":"Point"}
}