{
  "type": "Feature",
  "properties": {
    "addr:full":"Calle de Arostegi, 17 Bermeo Vizcaya 48370",
    "addr:housenumber":"17",
    "addr:postcode":"48370",
    "addr:street":"Calle De Arostegi",
    "iso:country":"ES",
    "sg:address":"Calle de Arostegi, 17",
    "sg:city":"Bermeo",
    "sg:orig_category":"M\u00c9dicos: Estomatolog\u00cda",
    "sg:phone":"+34 946 88 38 71",
    "sg:postcode":"48370",
    "sg:province":"Vizcaya",
    "wof:name":"Aranaga Salazar Ignacio",
    "wof:placetype":"venue"
},
  "geometry": {"coordinates":[-2.7218015194,43.4199714661],"type":"Point"}
}