{
  "type": "Feature",
  "properties": {
    "iso:country":"ES",
    "sg:address":"Calle de Rosa (la), 12",
    "sg:city":"Tauste",
    "sg:orig_category":"Molduras, Junquillos, Listones Y Molduras Perforadas",
    "sg:phone":"+34 976 85 41 10",
    "sg:postcode":"50660",
    "sg:province":"Zaragoza",
    "wof:name":"Garcia Pellicer Maria Lourdes",
    "wof:placetype":"venue"
},
  "geometry": {"coordinates":[-1.2559800148,41.9202804565],"type":"Point"}
}