{
  "type": "Feature",
  "properties": {
    "iso:country":"ES",
    "sg:address":"Carr Baro De Maials, 86",
    "sg:city":"Lleida",
    "sg:orig_category":"Venta, Alquiler De V\u00cddeo",
    "sg:phone":"+34 973 22 23 21",
    "sg:postcode":"25005",
    "sg:province":"Lleida",
    "wof:name":"Bump Mapping S.l.",
    "wof:placetype":"venue"
},
  "geometry": {"coordinates":[0.6282899976,41.6281318665],"type":"Point"}
}