{
  "type": "Feature",
  "properties": {
    "iso:country":"ES",
    "sg:address":"Calle de Santiago, 24",
    "sg:city":"Aranda Duero",
    "sg:orig_category":"Caf\u00c9s, Bares, Cervecer\u00cdas",
    "sg:phone":"+34 947 51 09 99",
    "sg:postcode":"09400",
    "sg:province":"Burgos",
    "wof:name":"Palomar Minguez Jesus Maria",
    "wof:placetype":"venue"
},
  "geometry": {"coordinates":[-3.6784389019,41.6725082397],"type":"Point"}
}