{
  "type": "Feature",
  "properties": {
    "addr:full":"Carrer de Carme, 31 S. Cugat Valles Barcelona 08172",
    "addr:housenumber":"31",
    "addr:postcode":"08172",
    "addr:street":"Carrer De Carme;S. Cugat Valles Barcelona",
    "iso:country":"ES",
    "sg:address":"Carrer de Carme, 31",
    "sg:city":"S. Cugat Valles",
    "sg:orig_category":"Agentes Generales De Seguros",
    "sg:phone":"+34 936 74 71 42",
    "sg:postcode":"08172",
    "sg:province":"Barcelona",
    "wof:name":"Ayala Zubieta Domingo",
    "wof:placetype":"venue"
},
  "geometry": {"coordinates":[2.083591938,41.4719848633],"type":"Point"}
}