{
  "type": "Feature",
  "properties": {
    "addr:full":"Avda Neguri, 15 Algorta Vizcaya 48992",
    "addr:housenumber":"15",
    "addr:postcode":"48992",
    "addr:street":"Avda Neguri",
    "iso:country":"ES",
    "sg:address":"Avda Neguri, 15",
    "sg:city":"Algorta",
    "sg:orig_category":"Farmacias",
    "sg:phone":"+34 944 91 43 51",
    "sg:postcode":"48992",
    "sg:province":"Vizcaya",
    "wof:name":"Gonzalez Mosquera Maria Del Carmen",
    "wof:placetype":"venue"
},
  "geometry": {"coordinates":[-3.0087149143,43.3412246704],"type":"Point"}
}