{
  "type": "Feature",
  "properties": {
    "addr:full":"Las Casillas, S/n Atochares Almer\u00eda 04113",
    "addr:housenumber":"s",
    "addr:postcode":"04113",
    "addr:street":"Casillas;/ N Atochares Almeri\u0301A",
    "iso:country":"ES",
    "sg:address":"Las Casillas, S/n",
    "sg:city":"Atochares",
    "sg:orig_category":"Producci\u00d3n De Abonos Y De Fertilizantes",
    "sg:phone":"+34 950 36 67 95",
    "sg:postcode":"04113",
    "sg:province":"Almer\u00eda",
    "wof:name":"Union De Atochares Sociedad Cooperativa Andaluza",
    "wof:placetype":"venue"
},
  "geometry": {"coordinates":[-2.2043170929,36.8793067932],"type":"Point"}
}