{
  "type": "Feature",
  "properties": {
    "addr:full":"Calle de Marina, La, 12 Valencia Valencia 46011",
    "addr:housenumber":"12",
    "addr:postcode":"46011",
    "addr:street":"Calle De Marina La",
    "iso:country":"ES",
    "sg:address":"Calle de Marina, La, 12",
    "sg:city":"Valencia",
    "sg:orig_category":"Bisuteros (fabricaci\u00d3n, Al Por Mayor)",
    "sg:phone":"+34 963 55 39 52",
    "sg:postcode":"46011",
    "sg:province":"Valencia",
    "wof:name":"Rodrigo Aparicio Josep",
    "wof:placetype":"venue"
},
  "geometry": {"coordinates":[-0.3304949999,39.4725799561],"type":"Point"}
}