{
  "type": "Feature",
  "properties": {
    "addr:full":"Rua Cristobal Colon, 5 Santa Uxia De Ribeira La Coru\u00f1a 15960",
    "addr:housenumber":"5",
    "addr:postcode":"15960",
    "addr:street":"Rua Cristobal Colon;Corun\u0303A",
    "iso:country":"ES",
    "sg:address":"Rua Cristobal Colon, 5",
    "sg:city":"Santa Uxia De Ribeira",
    "sg:orig_category":"Bricolaje, Herramientas (al Por Menor)",
    "sg:phone":"+34 981 87 26 56",
    "sg:postcode":"15960",
    "sg:province":"La Coru\u00f1a",
    "wof:name":"Galerias Colon S.c.",
    "wof:placetype":"venue"
},
  "geometry": {"coordinates":[-8.9909753799,42.5539169312],"type":"Point"}
}