{
  "type": "Feature",
  "properties": {
    "addr:full":"Calle de Domingo Guerra Del Rio, 123 Palmas De Gran Canaria Las Palmas 35014",
    "addr:housenumber":"123",
    "addr:postcode":"35014",
    "addr:street":"Calle De Domingo Guerra Del Rio",
    "iso:country":"ES",
    "sg:address":"Calle de Domingo Guerra Del Rio, 123",
    "sg:city":"Palmas De Gran Canaria",
    "sg:orig_category":"Alimentaci\u00d3n General (al Por Menor)",
    "sg:phone":"+34 928 36 87 68",
    "sg:postcode":"35014",
    "sg:province":"Las Palmas",
    "wof:name":"Machio Ramirez Francisca",
    "wof:placetype":"venue"
},
  "geometry": {"coordinates":[-15.4199829102,28.1046543121],"type":"Point"}
}