{
  "type": "Feature",
  "properties": {
    "iso:country":"ES",
    "sg:address":"Carr Ramon Turro, 3",
    "sg:city":"Girona",
    "sg:orig_category":"Abogados",
    "sg:phone":"+34 972 21 45 07",
    "sg:postcode":"17005",
    "sg:province":"Girona",
    "wof:name":"Lopez Vegas Francesc Xavier",
    "wof:placetype":"venue"
},
  "geometry": {"coordinates":[2.8174989223,41.9830360413],"type":"Point"}
}