{
  "type": "Feature",
  "properties": {
    "iso:country":"ES",
    "sg:address":"Ctra Pe\u00d1afiel, 1",
    "sg:city":"Cuellar",
    "sg:orig_category":"Paneles Diversos",
    "sg:phone":"+34 921 14 14 47",
    "sg:postcode":"40200",
    "sg:province":"Segovia",
    "wof:name":"Sanz Sanchez Amalia Julia",
    "wof:placetype":"venue"
},
  "geometry": {"coordinates":[-4.3057990074,41.4048194885],"type":"Point"}
}