{
  "type": "Feature",
  "properties": {
    "addr:full":"Calle de Vicente De Paul, 101 Algeciras C\u00e1diz 11203",
    "addr:housenumber":"101;ca\u0301diz",
    "addr:postcode":"11203",
    "addr:street":"Calle De Vicente De Paul",
    "iso:country":"ES",
    "sg:address":"Calle de Vicente De Paul, 101",
    "sg:city":"Algeciras",
    "sg:orig_category":"Parques De Atracciones Y Centros De Esparcimiento",
    "sg:phone":"+34 956 66 23 57",
    "sg:postcode":"11203",
    "sg:province":"C\u00e1diz",
    "wof:name":"Automaticos Barrera S.a.",
    "wof:placetype":"venue"
},
  "geometry": {"coordinates":[-5.4571976662,36.130859375],"type":"Point"}
}