{
  "type": "Feature",
  "properties": {
    "iso:country":"ES",
    "sg:address":"Rua Rio Navia, 36",
    "sg:city":"Lugo",
    "sg:orig_category":"Molduras, Junquillos, Listones Y Molduras Perforadas",
    "sg:phone":"+34 982 21 31 72",
    "sg:postcode":"27004",
    "sg:province":"Lugo",
    "wof:name":"Pena Varela Jesus",
    "wof:placetype":"venue"
},
  "geometry": {"coordinates":[-7.566327095,43.017791748],"type":"Point"}
}