{
  "type": "Feature",
  "properties": {
    "addr:full":"S(boverals), 5 Vinaros Castell\u00f3n 12500",
    "addr:housenumber":"5",
    "addr:postcode":"12500",
    "addr:street":"S Boverals",
    "iso:country":"ES",
    "sg:address":"S(boverals), 5",
    "sg:city":"Vinaros",
    "sg:orig_category":"Trabajos De Perforaciones, Sondeos, Construcci\u00d3n De Pozos",
    "sg:phone":"+34 964 45 44 80",
    "sg:postcode":"12500",
    "sg:province":"Castell\u00f3n",
    "wof:name":"Perforaciones Vinaros S. L.",
    "wof:placetype":"venue"
},
  "geometry": {"coordinates":[0.4878750145,40.4943962097],"type":"Point"}
}