{
  "type": "Feature",
  "properties": {
    "addr:full":"Avda Marianistas (los), 4 Jerez De La Frontera C\u00e1diz 11407",
    "addr:postcode":"11407",
    "addr:street":"Avda Marianistas Los",
    "iso:country":"ES",
    "sg:address":"Avda Marianistas (los), 4",
    "sg:city":"Jerez De La Frontera",
    "sg:orig_category":"Molduras, Junquillos, Listones Y Molduras Perforadas",
    "sg:phone":"+34 956 18 21 88",
    "sg:postcode":"11407",
    "sg:province":"C\u00e1diz",
    "wof:name":"F.pe\u00f1a Sevilla S.l.",
    "wof:placetype":"venue"
},
  "geometry": {"coordinates":[-6.1382350922,36.6964645386],"type":"Point"}
}