{
  "type": "Feature",
  "properties": {
    "iso:country":"ES",
    "sg:address":"Calle de General Manrique De Lara, 6",
    "sg:city":"Alcazar S. Juan",
    "sg:orig_category":"Muebles, Minoristas",
    "sg:phone":"+34 926 54 24 84",
    "sg:postcode":"13600",
    "sg:province":"Ciudad Real",
    "wof:name":"Paton Palomino Antonio Tomas",
    "wof:placetype":"venue"
},
  "geometry": {"coordinates":[-3.2115290165,39.3956108093],"type":"Point"}
}