{
  "type": "Feature",
  "properties": {
    "iso:country":"ES",
    "sg:address":"Calle de Asturias, 21",
    "sg:city":"Oviedo",
    "sg:orig_category":"Abogados",
    "sg:phone":"+34 985 27 17 69",
    "sg:postcode":"33004",
    "sg:province":"Asturias",
    "wof:name":"Bustillo Perez Ramon",
    "wof:placetype":"venue"
},
  "geometry": {"coordinates":[-5.8552289009,43.3633117676],"type":"Point"}
}