{
  "type": "Feature",
  "properties": {
    "addr:full":"Calle de Zapateria De Los Ni\u00d1os, 6 Valencia Valencia 46001",
    "addr:housenumber":"6",
    "addr:postcode":"46001",
    "addr:street":"Calle De;Nin\u0303Os",
    "iso:country":"ES",
    "sg:address":"Calle de Zapateria De Los Ni\u00d1os, 6",
    "sg:city":"Valencia",
    "sg:orig_category":"Dietistas",
    "sg:phone":"+34 963 92 16 51",
    "sg:postcode":"46001",
    "sg:province":"Valencia",
    "wof:name":"Blay Diaz Maria Amparo",
    "wof:placetype":"venue"
},
  "geometry": {"coordinates":[-0.3771010041,39.47448349],"type":"Point"}
}