{
  "type": "Feature",
  "properties": {
    "iso:country":"ES",
    "sg:address":"Carrer de Vimbodi, 2",
    "sg:city":"Montblanc",
    "sg:orig_category":"Empleados",
    "sg:phone":"+34 977 86 31 54",
    "sg:postcode":"43400",
    "sg:province":"Tarragona",
    "wof:name":"2-pa Consultors S.l.",
    "wof:placetype":"venue"
},
  "geometry": {"coordinates":[1.161424,41.372433],"type":"Point"}
}