{
  "type": "Feature",
  "properties": {
    "addr:full":"Calle de Gredos, 1 Avila \u00c1vila 05002",
    "addr:housenumber":"1",
    "addr:postcode":"05002",
    "addr:street":"Calle De Gredos;A\u0301Vila",
    "iso:country":"ES",
    "sg:address":"Calle de Gredos, 1",
    "sg:city":"Avila",
    "sg:orig_category":"Mensajer\u00cda Express, Portes Internacionales",
    "sg:phone":"+34 920 22 54 54",
    "sg:postcode":"05002",
    "sg:province":"\u00c1vila",
    "wof:name":"Edur Envios Y Distribuciones Urgentes S.l.",
    "wof:placetype":"venue"
},
  "geometry": {"coordinates":[-4.7014088631,40.6497344971],"type":"Point"}
}