{
  "type": "Feature",
  "properties": {
    "addr:full":"Pol Ind Collet, 705 Benicarlo Castell\u00f3n 12580",
    "addr:housenumber":"705",
    "addr:postcode":"12580",
    "addr:street":"Ind Collet",
    "iso:country":"ES",
    "sg:address":"Pol Ind Collet, 705",
    "sg:city":"Benicarlo",
    "sg:orig_category":"Fabricaci\u00d3n De Muebles De Cocina",
    "sg:phone":"+34 964 46 20 95",
    "sg:postcode":"12580",
    "sg:province":"Castell\u00f3n",
    "wof:name":"Mobles De Cuina Cuinsa S.l.",
    "wof:placetype":"venue"
},
  "geometry": {"coordinates":[0.4042100012,40.4457893372],"type":"Point"}
}