{
  "type": "Feature",
  "properties": {
    "addr:full":"Calle de Pico Meras, 5 Pravia Asturias 33120",
    "addr:housenumber":"5",
    "addr:postcode":"33120",
    "addr:street":"Calle De Pico Meras",
    "iso:country":"ES",
    "sg:address":"Calle de Pico Meras, 5",
    "sg:city":"Pravia",
    "sg:orig_category":"Pr\u00c9stamos Personales E Hipotecarios",
    "sg:phone":"+34 985 82 06 46",
    "sg:postcode":"33120",
    "sg:province":"Asturias",
    "wof:name":"Cuesta Vizoso Gaspar",
    "wof:placetype":"venue"
},
  "geometry": {"coordinates":[-6.1131720543,43.4883956909],"type":"Point"}
}