{
  "type": "Feature",
  "properties": {
    "iso:country":"ES",
    "sg:address":"Avda Madrid De, 9",
    "sg:city":"Donostia-san Sebastian",
    "sg:orig_category":"Psic\u00d3logos",
    "sg:phone":"+34 943 46 04 12",
    "sg:postcode":"20011",
    "sg:province":"Guip\u00f9zcoa",
    "wof:name":"Ugarte Recarte Javier",
    "wof:placetype":"venue"
},
  "geometry": {"coordinates":[-1.9767420292,43.3047294617],"type":"Point"}
}