{
  "type": "Feature",
  "properties": {
    "iso:country":"ES",
    "sg:address":"Avda Portugal, 167",
    "sg:city":"Madrid",
    "sg:orig_category":"Fabricaci\u00d3n, Venta, Instalaci\u00d3n De R\u00d3tulos, De R\u00d3tulos Luminosos",
    "sg:phone":"+34 914 64 69 04",
    "sg:postcode":"28011",
    "sg:province":"Madrid",
    "sg:website":"www.publimovil.net",
    "wof:name":"Garcia Y Schmah S.l.",
    "wof:placetype":"venue"
},
  "geometry": {"coordinates":[-3.7396407127,40.4102363586],"type":"Point"}
}