{
  "type": "Feature",
  "properties": {
    "addr:full":"Carrer de Garcilaso, 7 Sabadell Barcelona 08201",
    "addr:housenumber":"7",
    "addr:postcode":"08201",
    "addr:street":"Carrer De Garcilaso",
    "iso:country":"ES",
    "sg:address":"Carrer de Garcilaso, 7",
    "sg:city":"Sabadell",
    "sg:orig_category":"Telas Y Sedas (al Por Menor)",
    "sg:phone":"+34 937 25 13 67",
    "sg:postcode":"08201",
    "sg:province":"Barcelona",
    "wof:name":"Prat Corderas Eulalia",
    "wof:placetype":"venue"
},
  "geometry": {"coordinates":[2.1062970161,41.5504837036],"type":"Point"}
}