{
  "type": "Feature",
  "properties": {
    "addr:full":"Calle de Zaragoza, 3 Huesca Huesca 22002",
    "addr:housenumber":"3",
    "addr:postcode":"22002",
    "addr:street":"Calle De Zaragoza",
    "iso:country":"ES",
    "sg:address":"Calle de Zaragoza, 3",
    "sg:city":"Huesca",
    "sg:orig_category":"Bancos",
    "sg:phone":"+34 974 24 47 15",
    "sg:postcode":"22002",
    "sg:province":"Huesca",
    "wof:name":"Banco Popular Espa\u00f1ol",
    "wof:placetype":"venue"
},
  "geometry": {"coordinates":[-0.4084700048,42.1353034973],"type":"Point"}
}