{
  "type": "Feature",
  "properties": {
    "addr:full":"Calle de Feria, 42 Albacete Albacete 02005",
    "addr:housenumber":"42",
    "addr:postcode":"02005",
    "addr:street":"Calle De Feria",
    "iso:country":"ES",
    "sg:address":"Calle de Feria, 42",
    "sg:city":"Albacete",
    "sg:orig_category":"Asesor\u00cda Sobre Comunicaci\u00d3n De Empresas",
    "sg:phone":"+34 967 51 20 09",
    "sg:postcode":"02005",
    "sg:province":"Albacete",
    "wof:name":"Asesoria La Noria S.l.l.",
    "wof:placetype":"venue"
},
  "geometry": {"coordinates":[-1.8619749546,38.996295929],"type":"Point"}
}