{
  "type": "Feature",
  "properties": {
    "addr:full":"Bule Jose Prat, 41 Madrid Madrid 28032",
    "addr:housenumber":"41",
    "addr:postcode":"madrid;28032",
    "addr:street":"Prat",
    "iso:country":"ES",
    "sg:address":"Bule Jose Prat, 41",
    "sg:city":"Madrid",
    "sg:orig_category":"Negocio De Madera",
    "sg:phone":"+34 913 71 26 25",
    "sg:postcode":"28032",
    "sg:province":"Madrid",
    "sg:website":"www.cmbbricolage.com",
    "wof:name":"Centro Del Mueble Y Bricolage S.l.",
    "wof:placetype":"venue"
},
  "geometry": {"coordinates":[-3.7057740688,40.42029953],"type":"Point"}
}