{
  "type": "Feature",
  "properties": {
    "addr:full":"Calle de Mar Negro, 15 Madrid Madrid 28033",
    "addr:housenumber":"15",
    "addr:postcode":"madrid;28033",
    "addr:street":"Calle De Mar Negro",
    "iso:country":"ES",
    "sg:address":"Calle de Mar Negro, 15",
    "sg:city":"Madrid",
    "sg:orig_category":"Fotocopias, Reprograf\u00cda",
    "sg:phone":"+34 913 81 71 40",
    "sg:postcode":"28033",
    "sg:province":"Madrid",
    "wof:name":"Garu Reprografia S.l.",
    "wof:placetype":"venue"
},
  "geometry": {"coordinates":[-3.6446049213,40.4736747742],"type":"Point"}
}