{
  "type": "Feature",
  "properties": {
    "iso:country":"ES",
    "sg:address":"Calle de Jacinto Guerrero (de), 17",
    "sg:city":"Boadilla Del Monte",
    "sg:orig_category":"Inform\u00c1tica: Consultores",
    "sg:phone":"+34 916 32 45 92",
    "sg:postcode":"28660",
    "sg:province":"Madrid",
    "wof:name":"Gestion De Recursos Informaticos Y Soluciones Empresariales",
    "wof:placetype":"venue"
},
  "geometry": {"coordinates":[-3.887980938,40.4039726257],"type":"Point"}
}