{
  "type": "Feature",
  "properties": {
    "iso:country":"ES",
    "sg:address":"Calle de Escritor Almeida Garret, 1",
    "sg:city":"Cordoba",
    "sg:orig_category":"Empresas De Vigilancia, Guardia Y Protecci\u00d3n",
    "sg:phone":"+34 957 25 21 42",
    "sg:postcode":"14014",
    "sg:province":"C\u00f3rdoba",
    "sg:website":"www.garotecnia.com",
    "wof:name":"Garotecnia S.a.",
    "wof:placetype":"venue"
},
  "geometry": {"coordinates":[-4.7519574165,37.8979187012],"type":"Point"}
}