{
  "type": "Feature",
  "properties": {
    "addr:full":"Avda Agua Marina, 1 Algeciras C\u00e1diz 11203",
    "addr:housenumber":"1;ca\u0301diz",
    "addr:postcode":"11203",
    "addr:street":"Avda Agua Marina",
    "iso:country":"ES",
    "sg:address":"Avda Agua Marina, 1",
    "sg:city":"Algeciras",
    "sg:orig_category":"Mantenimiento Y Reparaci\u00d3n De Motores Industriales",
    "sg:phone":"+34 956 65 28 52",
    "sg:postcode":"11203",
    "sg:province":"C\u00e1diz",
    "wof:name":"Repnavalsa S.l.",
    "wof:placetype":"venue"
},
  "geometry": {"coordinates":[-5.4589271545,36.1284713745],"type":"Point"}
}