{
  "type": "Feature",
  "properties": {
    "addr:full":"Avda Septima, 23 Colmenar Viejo Madrid 28770",
    "addr:housenumber":"23",
    "addr:postcode":"28770",
    "addr:street":"Avda Septima",
    "iso:country":"ES",
    "sg:address":"Avda Septima, 23",
    "sg:city":"Colmenar Viejo",
    "sg:orig_category":"Transporte En General",
    "sg:phone":"+34 918 45 41 03",
    "sg:postcode":"28770",
    "sg:province":"Madrid",
    "wof:name":"Inversiones Zeusle S.l.",
    "wof:placetype":"venue"
},
  "geometry": {"coordinates":[-3.7670140266,40.6678886414],"type":"Point"}
}