{
  "type": "Feature",
  "properties": {
    "addr:full":"Calle de Conde De Aranda, 28 Aguilas Murcia 30880",
    "addr:housenumber":"28",
    "addr:postcode":"30880",
    "addr:street":"Calle De Conde De Aranda",
    "iso:country":"ES",
    "sg:address":"Calle de Conde De Aranda, 28",
    "sg:city":"Aguilas",
    "sg:orig_category":"Reposter\u00cdas",
    "sg:phone":"+34 968 41 05 74",
    "sg:postcode":"30880",
    "sg:province":"Murcia",
    "wof:name":"Belmonte Lopez Pedro",
    "wof:placetype":"venue"
},
  "geometry": {"coordinates":[-1.5844190121,37.4045791626],"type":"Point"}
}