{
  "type": "Feature",
  "properties": {
    "iso:country":"ES",
    "sg:address":"Av Vilallonga, 104",
    "sg:city":"Figueres",
    "sg:orig_category":"Negocio De Metales No Ferrosos",
    "sg:phone":"+34 972 50 34 37",
    "sg:postcode":"17600",
    "sg:province":"Girona",
    "wof:name":"Eduardo Puig S.a.",
    "wof:placetype":"venue"
},
  "geometry": {"coordinates":[2.9767889977,42.2666015625],"type":"Point"}
}