{
  "type": "Feature",
  "properties": {
    "iso:country":"ES",
    "sg:address":"Calle de Rosalia De Castro, 10",
    "sg:city":"Castellon De La Plana",
    "sg:orig_category":"Inmobiliaria (agencias)",
    "sg:phone":"+34 964 24 50 65",
    "sg:postcode":"12004",
    "sg:province":"Castell\u00f3n",
    "wof:name":"Exclusivas Mayte Blasco S.l.",
    "wof:placetype":"venue"
},
  "geometry": {"coordinates":[-0.0531889983,40.0177879333],"type":"Point"}
}