{
  "type": "Feature",
  "properties": {
    "iso:country":"ES",
    "sg:address":"Avda Mirador (del), 16",
    "sg:city":"Pelayos Presa",
    "sg:classifiers":[
        {
            "category":"Communications",
            "type":"Services"
        }
    ],
    "sg:phone":"+34 918 64 42 52",
    "sg:postcode":"28696",
    "sg:province":"Madrid",
    "sg:tags":[
        "televisiones",
        "y",
        "radio"
    ],
    "wof:name":"Pelayos Radios S.l.",
    "wof:placetype":"venue"
},
  "geometry": {"coordinates":[-4.3367171288,40.3613700867],"type":"Point"}
}