{
  "type": "Feature",
  "properties": {
    "addr:full":"Calle de Gulfar, S/n Dacon Ourense 32572",
    "addr:housenumber":"s",
    "addr:postcode":"32572",
    "addr:street":"Calle De Gulfar;/ N",
    "iso:country":"ES",
    "sg:address":"Calle de Gulfar, S/n",
    "sg:city":"Dacon",
    "sg:orig_category":"Telas Y Sedas (al Por Menor)",
    "sg:phone":"+34 988 27 18 66",
    "sg:postcode":"32572",
    "sg:province":"Ourense",
    "wof:name":"Calle Gonzalez Modesto De La",
    "wof:placetype":"venue"
},
  "geometry": {"coordinates":[-8.0064659119,42.3980865479],"type":"Point"}
}