{
  "type": "Feature",
  "properties": {
    "addr:full":"Calle de Jose Moreno Torres, 6 Porcuna Ja\u00e9n 23790",
    "addr:housenumber":"6",
    "addr:postcode":"23790",
    "addr:street":"Calle De Jose Moreno Torres",
    "iso:country":"ES",
    "sg:address":"Calle de Jose Moreno Torres, 6",
    "sg:city":"Porcuna",
    "sg:classifiers":[
        {
            "category":"Taxi",
            "type":"Transportation"
        }
    ],
    "sg:phone":"+34 953 54 47 91",
    "sg:postcode":"23790",
    "sg:province":"Ja\u00e9n",
    "wof:name":"Morales Salas Rafael",
    "wof:placetype":"venue"
},
  "geometry": {"coordinates":[-4.1852021217,37.8701782227],"type":"Point"}
}