{
  "type": "Feature",
  "properties": {
    "iso:country":"ES",
    "sg:address":"Calle de Tierra De Campos, 44",
    "sg:city":"Salamanca",
    "sg:orig_category":"Electricidad Veh\u00cdculo",
    "sg:phone":"+34 923 19 10 96",
    "sg:postcode":"37008",
    "sg:province":"Salamanca",
    "wof:name":"Autoelectrico Sanfructuoso Cb",
    "wof:placetype":"venue"
},
  "geometry": {"coordinates":[-5.6669130325,40.9380531311],"type":"Point"}
}