{
  "type": "Feature",
  "properties": {
    "addr:full":"Carrer de Sarasate, 20 Sabadell Barcelona 08206",
    "addr:housenumber":"20",
    "addr:postcode":"08206",
    "addr:street":"Carrer De Sarasate",
    "iso:country":"ES",
    "sg:address":"Carrer de Sarasate, 20",
    "sg:city":"Sabadell",
    "sg:orig_category":"Empresarios",
    "sg:phone":"+34 937 26 90 29",
    "sg:postcode":"08206",
    "sg:province":"Barcelona",
    "wof:name":"Murciano Cortes Manuel",
    "wof:placetype":"venue"
},
  "geometry": {"coordinates":[2.0807459354,41.5513687134],"type":"Point"}
}