{
  "type": "Feature",
  "properties": {
    "addr:full":"Calle de Veintiocho De Septiembre, 28 Bejar Salamanca 37700",
    "addr:housenumber":"28",
    "addr:postcode":"37700",
    "addr:street":"Calle De Veintiocho De Septiembre",
    "iso:country":"ES",
    "sg:address":"Calle de Veintiocho De Septiembre, 28",
    "sg:city":"Bejar",
    "sg:orig_category":"Laboratorios Y Trabajos De Fotograf\u00cda, V\u00cddeo Y Cine",
    "sg:phone":"+34 923 40 37 68",
    "sg:postcode":"37700",
    "sg:province":"Salamanca",
    "wof:name":"Montagut Planas Miguel",
    "wof:placetype":"venue"
},
  "geometry": {"coordinates":[-5.7646341324,40.3881340027],"type":"Point"}
}