{
  "type": "Feature",
  "properties": {
    "iso:country":"ES",
    "sg:address":"Calle de Maria Cristina, 59",
    "sg:city":"Torredonjimeno",
    "sg:orig_category":"Molduras, Junquillos, Listones Y Molduras Perforadas",
    "sg:phone":"+34 953 34 42 67",
    "sg:postcode":"23650",
    "sg:province":"Ja\u00e9n",
    "wof:name":"Calahorro Rodriguez Gloria",
    "wof:placetype":"venue"
},
  "geometry": {"coordinates":[-3.9507689476,37.7615509033],"type":"Point"}
}