{
  "type": "Feature",
  "properties": {
    "addr:full":"Avda Carlos V, 39 Carrizal Las Palmas 35240",
    "addr:housenumber":"39",
    "addr:postcode":"35240",
    "addr:street":"Avda Carlos V",
    "iso:country":"ES",
    "sg:address":"Avda Carlos V, 39",
    "sg:city":"Carrizal",
    "sg:orig_category":"Cajas De Ahorro",
    "sg:phone":"+34 928 78 20 11",
    "sg:postcode":"35240",
    "sg:province":"Las Palmas",
    "sg:website":"www.lacaixa.es",
    "wof:name":"Caixa D'estalvis I Pensions De Barcelona",
    "wof:placetype":"venue"
},
  "geometry": {"coordinates":[-15.4056653976,27.9111289978],"type":"Point"}
}