{
  "type": "Feature",
  "properties": {
    "addr:full":"Calle de Sevilla, 4 Bailen Ja\u00e9n 23710",
    "addr:housenumber":"4",
    "addr:postcode":"23710",
    "addr:street":"Calle De Sevilla;Jae\u0301N",
    "iso:country":"ES",
    "sg:address":"Calle de Sevilla, 4",
    "sg:city":"Bailen",
    "sg:orig_category":"Fabricaci\u00d3n, Importaci\u00d3n, Venta De Material De Telefon\u00cda, Peritelefon\u00cda",
    "sg:phone":"+34 953 67 80 55",
    "sg:postcode":"23710",
    "sg:province":"Ja\u00e9n",
    "wof:name":"Digital Milenium 2008 S.l.",
    "wof:placetype":"venue"
},
  "geometry": {"coordinates":[-3.7729289532,38.0932807922],"type":"Point"}
}