{
  "type": "Feature",
  "properties": {
    "iso:country":"ES",
    "sg:address":"Calle de Alhamar, 15",
    "sg:city":"Granada",
    "sg:orig_category":"M\u00c9dicos: Estomatolog\u00cda",
    "sg:phone":"+34 958 25 11 20",
    "sg:postcode":"18005",
    "sg:province":"Granada",
    "wof:name":"Agredano Martin Enrique Jesus",
    "wof:placetype":"venue"
},
  "geometry": {"coordinates":[-3.6011013985,37.1689872742],"type":"Point"}
}