{
  "type": "Feature",
  "properties": {
    "iso:country":"ES",
    "sg:address":"Carrer de Valencia, 396",
    "sg:city":"Barcelona",
    "sg:orig_category":"Bazares, Art\u00cdculos De Limpieza Y De Cocina (al Por Menor)",
    "sg:phone":"+34 934 58 59 73",
    "sg:postcode":"08013",
    "sg:province":"Barcelona",
    "wof:name":"Alaya Morata Maria Dolores",
    "wof:placetype":"venue"
},
  "geometry": {"coordinates":[2.1744832993,41.4010734558],"type":"Point"}
}