{
  "type": "Feature",
  "properties": {
    "addr:full":"Calle de Doctor Lopez Font, 40 Granada Granada 18004",
    "addr:housenumber":"40",
    "addr:postcode":"18004",
    "addr:street":"Calle De Doctor Lopez Font",
    "iso:country":"ES",
    "sg:address":"Calle de Doctor Lopez Font, 40",
    "sg:city":"Granada",
    "sg:orig_category":"Agencias Y Agentes Comerciales, Representantes",
    "sg:phone":"+34 958 52 36 44",
    "sg:postcode":"18004",
    "sg:province":"Granada",
    "wof:name":"Soriano Garcia Francisco",
    "wof:placetype":"venue"
},
  "geometry": {"coordinates":[-3.6089122295,37.164855957],"type":"Point"}
}