{
  "type": "Feature",
  "properties": {
    "iso:country":"ES",
    "sg:address":"Carr Pallars, 15",
    "sg:city":"Lleida",
    "sg:orig_category":"Asesor\u00cda Fiscal Y Jur\u00cddica",
    "sg:phone":"+34 973 24 41 50",
    "sg:postcode":"25004",
    "sg:province":"Lleida",
    "wof:name":"Gatfi S.l.",
    "wof:placetype":"venue"
},
  "geometry": {"coordinates":[0.6240339875,41.6217079163],"type":"Point"}
}