{
  "type": "Feature",
  "properties": {
    "addr:full":"Avda Guindos De Los, 44 Malaga M\u00e1laga 29004",
    "addr:housenumber":"44",
    "addr:postcode":"29004",
    "addr:street":"Avda Guindos De Los;Ma\u0301Laga",
    "iso:country":"ES",
    "sg:address":"Avda Guindos De Los, 44",
    "sg:city":"Malaga",
    "sg:orig_category":"M\u00c9dicos: Estomatolog\u00cda",
    "sg:phone":"+34 952 24 13 69",
    "sg:postcode":"29004",
    "sg:province":"M\u00e1laga",
    "wof:name":"Gavilan Jimenez Mirian",
    "wof:placetype":"venue"
},
  "geometry": {"coordinates":[-4.4473171234,36.6907234192],"type":"Point"}
}