{
  "type": "Feature",
  "properties": {
    "iso:country":"ES",
    "sg:address":"Avda Buenos Aires, 54",
    "sg:city":"Madrid",
    "sg:orig_category":"Delegados, Agentes De Tr\u00c1nsito, Auxiliares De Transporte Internacional",
    "sg:phone":"+34 917 78 59 44",
    "sg:postcode":"28018",
    "sg:province":"Madrid",
    "wof:name":"Puado Mayo Felipe",
    "wof:placetype":"venue"
},
  "geometry": {"coordinates":[-3.6534190178,40.3889045715],"type":"Point"}
}