{
  "type": "Feature",
  "properties": {
    "iso:country":"ES",
    "sg:address":"Calle de Real, 28",
    "sg:city":"Ceuta",
    "sg:orig_category":"Fabricaci\u00d3n De Juegos Y Juguetes",
    "sg:phone":"+34 956 51 56 56",
    "sg:postcode":"51001",
    "sg:province":"Ceuta",
    "wof:name":"A.morales Modelismo S.l.unipersonal",
    "wof:placetype":"venue"
},
  "geometry": {"coordinates":[-5.3063998222,35.8877601624],"type":"Point"}
}