{
  "type": "Feature",
  "properties": {
    "addr:full":"Avda Constitucion (la), 22 Villablino Le\u00f3n 24100",
    "addr:housenumber":"22",
    "addr:postcode":"24100",
    "addr:street":"Avda Constitucion La",
    "iso:country":"ES",
    "sg:address":"Avda Constitucion (la), 22",
    "sg:city":"Villablino",
    "sg:orig_category":"Ense\u00d1anza, Formaci\u00d3n Profesional: Aprendizaje",
    "sg:phone":"+34 987 47 21 73",
    "sg:postcode":"24100",
    "sg:province":"Le\u00f3n",
    "wof:name":"Union Regional De Comisiones Obreras De Castilla Y Leon De Vall",
    "wof:placetype":"venue"
},
  "geometry": {"coordinates":[-6.3190889359,42.9396781921],"type":"Point"}
}