{
  "type": "Feature",
  "properties": {
    "addr:full":"Calle de Santiago Fernandez Portoles, 38 Tudela Navarra 31500",
    "addr:housenumber":"38",
    "addr:postcode":"31500",
    "addr:street":"Calle De Santiago;Portoles",
    "iso:country":"ES",
    "sg:address":"Calle de Santiago Fernandez Portoles, 38",
    "sg:city":"Tudela",
    "sg:orig_category":"Internados & Ense\u00d1anza Privada",
    "sg:phone":"+34 948 82 16 66",
    "sg:postcode":"31500",
    "sg:province":"Navarra",
    "wof:name":"Colegio La Anunciata",
    "wof:placetype":"venue"
},
  "geometry": {"coordinates":[-1.6030139923,42.0557861328],"type":"Point"}
}