{
  "type": "Feature",
  "properties": {
    "iso:country":"ES",
    "sg:address":"Calle de Saavedra Fajardo, 3",
    "sg:city":"Santa Eulalia",
    "sg:orig_category":"Promotores Constructores",
    "sg:phone":"+34 968 21 42 79",
    "sg:postcode":"30001",
    "sg:province":"Murcia",
    "wof:name":"Construcciones Melgar S.a.",
    "wof:placetype":"venue"
},
  "geometry": {"coordinates":[-1.1270469427,37.9856643677],"type":"Point"}
}