{
  "type": "Feature",
  "properties": {
    "iso:country":"ES",
    "sg:address":"Pousada, 3",
    "sg:city":"Callobre",
    "sg:orig_category":"Empresarios",
    "sg:phone":"+34 986 58 81 99",
    "sg:postcode":"36688",
    "sg:province":"Pontevedra",
    "wof:name":"Fundacion Maria Martinez Otero",
    "wof:placetype":"venue"
},
  "geometry": {"coordinates":[-8.4677591324,42.6931114197],"type":"Point"}
}