{
  "type": "Feature",
  "properties": {
    "iso:country":"ES",
    "sg:address":"Calle de Ingeniero La Cierva, 100",
    "sg:city":"Sevilla",
    "sg:orig_category":"Zapatos (al Por Menor)",
    "sg:phone":"+34 954 63 81 35",
    "sg:postcode":"41006",
    "sg:province":"Sevilla",
    "wof:name":"Diaz Bejarano Leonor",
    "wof:placetype":"venue"
},
  "geometry": {"coordinates":[-5.9483761787,37.3728752136],"type":"Point"}
}