{
  "type": "Feature",
  "properties": {
    "iso:country":"ES",
    "sg:address":"Calle de Dolores Mora, 22",
    "sg:city":"Paterna Campo",
    "sg:orig_category":"Empresas De Carpinter\u00cda Met\u00c1lica",
    "sg:phone":"+34 959 42 82 76",
    "sg:postcode":"21880",
    "sg:province":"Huelva",
    "wof:name":"Albarran Lopez Pedro",
    "wof:placetype":"venue"
},
  "geometry": {"coordinates":[-6.4028358459,37.4176216125],"type":"Point"}
}