{
  "type": "Feature",
  "properties": {
    "iso:country":"ES",
    "sg:address":"Carr 31 De Mar\u00c7, 11",
    "sg:city":"Felanitx",
    "sg:orig_category":"Ropa Para Se\u00d1oras Y Caballeros (al Por Menor)",
    "sg:phone":"+34 971 58 28 01",
    "sg:postcode":"07200",
    "sg:province":"Islas Baleares",
    "wof:name":"Ramis Rog Josefa",
    "wof:placetype":"venue"
},
  "geometry": {"coordinates":[3.1472430229,39.4680671692],"type":"Point"}
}