{
  "type": "Feature",
  "properties": {
    "addr:full":"Avgd Maresme, 96 Badalona Barcelona 08918",
    "addr:housenumber":"96",
    "addr:postcode":"08918",
    "addr:street":"Maresme",
    "iso:country":"ES",
    "sg:address":"Avgd Maresme, 96",
    "sg:city":"Badalona",
    "sg:orig_category":"Venta, Reparaci\u00d3n, Localizaci\u00d3n De Balanzas Y De B\u00c1sculas",
    "sg:phone":"+34 934 60 24 10",
    "sg:postcode":"08918",
    "sg:province":"Barcelona",
    "sg:website":"www.eleve.es",
    "wof:name":"Eleve S.l.",
    "wof:placetype":"venue"
},
  "geometry": {"coordinates":[2.2298181057,41.4326972961],"type":"Point"}
}