{
  "type": "Feature",
  "properties": {
    "iso:country":"ES",
    "sg:address":"Calle de Carretera De Burgos, Km. 0011,0",
    "sg:city":"Navarrete",
    "sg:orig_category":"Empresas De Carpinter\u00cda Met\u00c1lica",
    "sg:phone":"+34 941 44 06 24",
    "sg:postcode":"26370",
    "sg:province":"La Rioja",
    "wof:name":"Bravo Nebreda Pedro",
    "wof:placetype":"venue"
},
  "geometry": {"coordinates":[-2.5653500557,42.4315834045],"type":"Point"}
}