{
  "type": "Feature",
  "properties": {
    "iso:country":"ES",
    "sg:address":"Calle de Iba\u00d1ez De Bilbao, 17",
    "sg:city":"Bilbao",
    "sg:orig_category":"Centros Empresariales",
    "sg:phone":"+34 944 24 66 55",
    "sg:postcode":"48009",
    "sg:province":"Vizcaya",
    "sg:website":"www.avic.es",
    "wof:name":"Asociacion Vasca De Empresas De Ingenieria Y Consultoria",
    "wof:placetype":"venue"
},
  "geometry": {"coordinates":[-2.9304862022,43.2636680603],"type":"Point"}
}