{
  "type": "Feature",
  "properties": {
    "addr:full":"Moldano, S/n Moldano Asturias 33518",
    "addr:postcode":"33518",
    "addr:street":"Moldano S / N Moldano Asturias",
    "iso:country":"ES",
    "sg:address":"Moldano, S/n",
    "sg:city":"Moldano",
    "sg:orig_category":"Carnes De Carnicer\u00cda (al Por Mayor)",
    "sg:phone":"+34 985 73 00 81",
    "sg:postcode":"33518",
    "sg:province":"Asturias",
    "wof:name":"Parricar Sll",
    "wof:placetype":"venue"
},
  "geometry": {"coordinates":[-5.5597882271,43.4101409912],"type":"Point"}
}