{
  "type": "Feature",
  "properties": {
    "addr:full":"Calle de Malaga, 16 Valencia Valencia 46009",
    "addr:housenumber":"16",
    "addr:postcode":"46009",
    "addr:street":"Calle De Malaga",
    "iso:country":"ES",
    "sg:address":"Calle de Malaga, 16",
    "sg:city":"Valencia",
    "sg:orig_category":"Promotores Constructores",
    "sg:phone":"+34 963 48 61 30",
    "sg:postcode":"46009",
    "sg:province":"Valencia",
    "wof:name":"Construcciones Lolimar Valencia S.l.",
    "wof:placetype":"venue"
},
  "geometry": {"coordinates":[-0.3831230104,39.4846038818],"type":"Point"}
}