{
  "type": "Feature",
  "properties": {
    "iso:country":"ES",
    "sg:address":"Carr Burgos, 13",
    "sg:city":"Cervera",
    "sg:orig_category":"Promotores Constructores",
    "sg:phone":"+34 973 53 06 18",
    "sg:postcode":"25200",
    "sg:province":"Lleida",
    "wof:name":"Perella Pons Juan",
    "wof:placetype":"venue"
},
  "geometry": {"coordinates":[1.2731659412,41.6711730957],"type":"Point"}
}