{
  "type": "Feature",
  "properties": {
    "addr:full":"Calle de Mar Rojo, 9 Alcala Guadaira Sevilla 41500",
    "addr:housenumber":"9",
    "addr:postcode":"41500",
    "addr:street":"Calle De Mar Rojo",
    "iso:country":"ES",
    "sg:address":"Calle de Mar Rojo, 9",
    "sg:city":"Alcala Guadaira",
    "sg:orig_category":"Agencias Y Agentes Comerciales, Representantes",
    "sg:phone":"+34 955 61 01 06",
    "sg:postcode":"41500",
    "sg:province":"Sevilla",
    "wof:name":"Navarrete Salle Jorge Mario",
    "wof:placetype":"venue"
},
  "geometry": {"coordinates":[-5.8455920219,37.3486175537],"type":"Point"}
}