{
  "type": "Feature",
  "properties": {
    "addr:full":"Avda Pablo Iglesias, 13 Tarancon Cuenca 16400",
    "addr:housenumber":"13",
    "addr:postcode":"16400",
    "addr:street":"Avda Pablo Iglesias",
    "iso:country":"ES",
    "sg:address":"Avda Pablo Iglesias, 13",
    "sg:city":"Tarancon",
    "sg:orig_category":"Productores Recolectores, Venta Directa De Vinos",
    "sg:phone":"+34 969 32 54 55",
    "sg:postcode":"16400",
    "sg:province":"Cuenca",
    "sg:website":"www.bodecheca.com",
    "wof:name":"Bodecheca S.l.",
    "wof:placetype":"venue"
},
  "geometry": {"coordinates":[-3.0186090469,40.0075416565],"type":"Point"}
}