{
  "type": "Feature",
  "properties": {
    "addr:full":"Calle de Esteban Mora, 53 Madrid Madrid 28027",
    "addr:housenumber":"53",
    "addr:postcode":"madrid;28027",
    "addr:street":"Calle De Esteban Mora",
    "iso:country":"ES",
    "sg:address":"Calle de Esteban Mora, 53",
    "sg:city":"Madrid",
    "sg:orig_category":"Inform\u00c1tica Equipo Y Programas (al Por Mayor)",
    "sg:phone":"+34 914 05 81 26",
    "sg:postcode":"28027",
    "sg:province":"Madrid",
    "wof:name":"Albora Software S.l.",
    "wof:placetype":"venue"
},
  "geometry": {"coordinates":[-3.6527471542,40.4394950867],"type":"Point"}
}