{
  "type": "Feature",
  "properties": {
    "iso:country":"ES",
    "sg:address":"Calle de Arrabal, 12",
    "sg:city":"Santander",
    "sg:orig_category":"Psic\u00d3logos",
    "sg:phone":"+34 942 21 47 57",
    "sg:postcode":"39003",
    "sg:province":"Cantabria",
    "wof:name":"Vega Fernandez Purificacion",
    "wof:placetype":"venue"
},
  "geometry": {"coordinates":[-3.8046839237,43.4628944397],"type":"Point"}
}