{
  "type": "Feature",
  "properties": {
    "iso:country":"ES",
    "sg:address":"Calle de Pintor Aparicio, 26",
    "sg:city":"Alacant",
    "sg:orig_category":"Inmobiliaria (agencias)",
    "sg:phone":"+34 965 22 76 46",
    "sg:postcode":"03003",
    "sg:province":"Alicante",
    "wof:name":"Marco Garcia Carlos",
    "wof:placetype":"venue"
},
  "geometry": {"coordinates":[-0.4913089871,38.3416595459],"type":"Point"}
}