{
  "type": "Feature",
  "properties": {
    "iso:country":"ES",
    "sg:address":"Carrer de Migdia, 26",
    "sg:city":"Amposta",
    "sg:orig_category":"Promotores Constructores",
    "sg:phone":"+34 977 70 20 95",
    "sg:postcode":"43870",
    "sg:province":"Tarragona",
    "wof:name":"Conrasal S.l.",
    "wof:placetype":"venue"
},
  "geometry": {"coordinates":[0.5771290064,40.7137031555],"type":"Point"}
}