{
  "type": "Feature",
  "properties": {
    "addr:full":"Calle de Delicias, 3 Arnedo La Rioja 26580",
    "addr:housenumber":"3",
    "addr:postcode":"26580",
    "addr:street":"Calle De Delicias;Rioja",
    "iso:country":"ES",
    "sg:address":"Calle de Delicias, 3",
    "sg:city":"Arnedo",
    "sg:orig_category":"Transportes Por V\u00cdas Navegables",
    "sg:phone":"+34 941 38 03 36",
    "sg:postcode":"26580",
    "sg:province":"La Rioja",
    "wof:name":"Lavega Palacios Felix",
    "wof:placetype":"venue"
},
  "geometry": {"coordinates":[-2.1008565426,42.2239456177],"type":"Point"}
}