{
  "type": "Feature",
  "properties": {
    "iso:country":"ES",
    "sg:address":"Calle de Txorierri, 41",
    "sg:city":"Txorierri",
    "sg:orig_category":"Maquinaria Para Industrias Diversas",
    "sg:phone":"+34 944 64 58 04",
    "sg:postcode":"48940",
    "sg:province":"Vizcaya",
    "wof:name":"Martin Garcia Martin",
    "wof:placetype":"venue"
},
  "geometry": {"coordinates":[-2.9860789776,43.3275489807],"type":"Point"}
}