{
  "type": "Feature",
  "properties": {
    "addr:full":"Avda Castilla-la Mancha, 27 San Pedro Albacete 02326",
    "addr:housenumber":"27",
    "addr:postcode":"02326",
    "addr:street":"Avda Castilla-La Mancha",
    "iso:country":"ES",
    "sg:address":"Avda Castilla-la Mancha, 27",
    "sg:city":"San Pedro",
    "sg:orig_category":"Importaci\u00d3n",
    "sg:phone":"+34 967 35 80 04",
    "sg:postcode":"02326",
    "sg:province":"Albacete",
    "wof:name":"Allium 94 S.l.",
    "wof:placetype":"venue"
},
  "geometry": {"coordinates":[-2.1903483868,38.8240242004],"type":"Point"}
}