{
  "type": "Feature",
  "properties": {
    "iso:country":"ES",
    "sg:address":"Avda Constitucion, 26",
    "sg:city":"Torrejon Ardoz",
    "sg:orig_category":"Comercio De Piezas De Recambio Y De Accesorios De Veh\u00cdculos, Veh\u00cdculos Industriales",
    "sg:phone":"+34 916 75 31 33",
    "sg:postcode":"28850",
    "sg:province":"Madrid",
    "wof:name":"Autorecambios Manolo S.l.",
    "wof:placetype":"venue"
},
  "geometry": {"coordinates":[-3.4826939106,40.4553108215],"type":"Point"}
}