{
  "type": "Feature",
  "properties": {
    "addr:full":"Calle de Joaquin Rodriguez, S/n Cangas Narcea Asturias 33800",
    "addr:housenumber":"/ n",
    "addr:postcode":"33800",
    "addr:street":"Calle De Joaquin Rodriguez S",
    "iso:country":"ES",
    "sg:address":"Calle de Joaquin Rodriguez, S/n",
    "sg:city":"Cangas Narcea",
    "sg:orig_category":"Alquiler De V\u00cddeo",
    "sg:phone":"+34 985 81 18 84",
    "sg:postcode":"33800",
    "sg:province":"Asturias",
    "wof:name":"Gutierrez Garcia Cesar Manuel",
    "wof:placetype":"venue"
},
  "geometry": {"coordinates":[-6.5492367744,43.1764564514],"type":"Point"}
}