{
  "type": "Feature",
  "properties": {
    "iso:country":"ES",
    "sg:address":"Pl. Victoria, 10",
    "sg:city":"Avila",
    "sg:orig_category":"Promotores Constructores",
    "sg:phone":"+34 920 22 91 34",
    "sg:postcode":"05001",
    "sg:province":"\u00c1vila",
    "wof:name":"Proinjisa S.a.",
    "wof:placetype":"venue"
},
  "geometry": {"coordinates":[-4.7072339058,40.6581344604],"type":"Point"}
}