{
  "type": "Feature",
  "properties": {
    "iso:country":"ES",
    "sg:address":"Calle de Vitoria, 17",
    "sg:city":"Burgos",
    "sg:orig_category":"Asesor\u00cda Fiscal Y Jur\u00cddica",
    "sg:phone":"+34 947 20 95 09",
    "sg:postcode":"09004",
    "sg:province":"Burgos",
    "wof:name":"Centro Asesoramiento Fiscal Y Contable S.l.",
    "wof:placetype":"venue"
},
  "geometry": {"coordinates":[-3.6975159645,42.3416213989],"type":"Point"}
}