{
  "type": "Feature",
  "properties": {
    "addr:full":"Plaz Pepe Zorita, 4 Tordesillas Valladolid 47100",
    "addr:housenumber":"4",
    "addr:postcode":"47100",
    "addr:street":"Zorita",
    "iso:country":"ES",
    "sg:address":"Plaz Pepe Zorita, 4",
    "sg:city":"Tordesillas",
    "sg:orig_category":"Sociedades, Compa\u00d1\u00cdas Aseguradoras",
    "sg:phone":"+34 983 77 16 14",
    "sg:postcode":"47100",
    "sg:province":"Valladolid",
    "wof:name":"Gonzalez Fernandez Rocio",
    "wof:placetype":"venue"
},
  "geometry": {"coordinates":[-4.9989957809,41.5035095215],"type":"Point"}
}