{
  "type": "Feature",
  "properties": {
    "iso:country":"ES",
    "sg:address":"Carrer de Fuerteventura, 46",
    "sg:city":"Sabadell",
    "sg:orig_category":"Laboratorios Y Trabajos De Fotograf\u00cda, V\u00cddeo Y Cine",
    "sg:phone":"+34 937 26 26 49",
    "sg:postcode":"08205",
    "sg:province":"Barcelona",
    "wof:name":"Zamorano Garcia Francisco",
    "wof:placetype":"venue"
},
  "geometry": {"coordinates":[2.0898170471,41.5459480286],"type":"Point"}
}