{
  "type": "Feature",
  "properties": {
    "addr:full":"Calle de General Antequera, 12 Santa Cruz De Tenerife Santa Cruz De Tenerife 38004",
    "addr:housenumber":"12",
    "addr:postcode":"38004",
    "addr:street":"Calle De General Antequera",
    "iso:country":"ES",
    "sg:address":"Calle de General Antequera, 12",
    "sg:city":"Santa Cruz De Tenerife",
    "sg:orig_category":"Asesor\u00cda Fiscal Y Jur\u00cddica",
    "sg:phone":"+34 922 27 70 13",
    "sg:postcode":"38004",
    "sg:province":"Santa Cruz De Tenerife",
    "wof:name":"Rodriguez Amez Carlos",
    "wof:placetype":"venue"
},
  "geometry": {"coordinates":[-16.254863739,28.4702033997],"type":"Point"}
}