{
  "type": "Feature",
  "properties": {
    "iso:country":"ES",
    "sg:address":"Calle de General Zuvillaga, 18",
    "sg:city":"Oviedo",
    "sg:orig_category":"Inmobiliaria (agencias)",
    "sg:phone":"+34 985 96 33 32",
    "sg:postcode":"33005",
    "sg:province":"Asturias",
    "wof:name":"Gomez Perez Rosa Matilde",
    "wof:placetype":"venue"
},
  "geometry": {"coordinates":[-5.8581638336,43.3628692627],"type":"Point"}
}