{
  "type": "Feature",
  "properties": {
    "addr:full":"Carr Theolongo Bacchio, 2 Blanes Girona 17300",
    "addr:housenumber":"2",
    "addr:postcode":"17300",
    "addr:street":"Carr Theolongo Bacchio",
    "iso:country":"ES",
    "sg:address":"Carr Theolongo Bacchio, 2",
    "sg:city":"Blanes",
    "sg:orig_category":"Agencias De Trabajo Temporal",
    "sg:phone":"+34 972 33 47 63",
    "sg:postcode":"17300",
    "sg:province":"Girona",
    "wof:name":"Select Recursos Humanos Ett S.a.",
    "wof:placetype":"venue"
},
  "geometry": {"coordinates":[2.7904579639,41.6741981506],"type":"Point"}
}