{
  "type": "Feature",
  "properties": {
    "addr:full":"Avda Lido Del, 10 Torremolinos M\u00e1laga 29620",
    "addr:housenumber":"10",
    "addr:postcode":"29620",
    "addr:street":"Avda Lido Del;Ma\u0301Laga",
    "iso:country":"ES",
    "sg:address":"Avda Lido Del, 10",
    "sg:city":"Torremolinos",
    "sg:orig_category":"Bazares, Art\u00cdculos De Limpieza Y De Cocina (al Por Menor)",
    "sg:phone":"+34 952 05 14 14",
    "sg:postcode":"29620",
    "sg:province":"M\u00e1laga",
    "wof:name":"Mallorca S.c.",
    "wof:placetype":"venue"
},
  "geometry": {"coordinates":[-4.4937582016,36.6274108887],"type":"Point"}
}