{
  "type": "Feature",
  "properties": {
    "addr:full":"Calle de Elvas, 2 Madrid Madrid 28025",
    "addr:housenumber":"2",
    "addr:postcode":"28025",
    "addr:street":"Calle De Elvas",
    "iso:country":"ES",
    "sg:address":"Calle de Elvas, 2",
    "sg:city":"Madrid",
    "sg:orig_category":"Internados & Ense\u00d1anza Privada",
    "sg:phone":"+34 915 69 61 89",
    "sg:postcode":"28025",
    "sg:province":"Madrid",
    "wof:name":"Colegio San Vicente De Paul S.l.",
    "wof:placetype":"venue"
},
  "geometry": {"coordinates":[-3.7253680229,40.3849945068],"type":"Point"}
}