{
  "type": "Feature",
  "properties": {
    "iso:country":"ES",
    "sg:address":"Avda Andalucia, Km. 0007,1",
    "sg:city":"Madrid",
    "sg:orig_category":"Perfumer\u00cda (al Por Menor)",
    "sg:phone":"+34 913 69 93 93",
    "sg:postcode":"28041",
    "sg:province":"Madrid",
    "sg:website":"www.disperfum.com",
    "wof:name":"Disperfum S.l.",
    "wof:placetype":"venue"
},
  "geometry": {"coordinates":[-3.6948060989,40.3722343445],"type":"Point"}
}