{
  "type": "Feature",
  "properties": {
    "addr:full":"Rua Marques De Valladares, 4 Vigo Pontevedra 36201",
    "addr:housenumber":"4",
    "addr:postcode":"36201",
    "addr:street":"Rua Marques De Valladares",
    "iso:country":"ES",
    "sg:address":"Rua Marques De Valladares, 4",
    "sg:city":"Vigo",
    "sg:orig_category":"Agencias De Viajes",
    "sg:phone":"+34 986 22 17 00",
    "sg:postcode":"36201",
    "sg:province":"Pontevedra",
    "sg:website":"www.barceloviajes.com",
    "wof:name":"Viajes Barcelo S.l.",
    "wof:placetype":"venue"
},
  "geometry": {"coordinates":[-8.7240829468,42.2381515503],"type":"Point"}
}