{
  "type": "Feature",
  "properties": {
    "iso:country":"ES",
    "sg:address":"Calle de Illescas, 145",
    "sg:city":"Madrid",
    "sg:orig_category":"M\u00c9dicos: Estomatolog\u00cda",
    "sg:phone":"+34 917 17 72 22",
    "sg:postcode":"28024",
    "sg:province":"Madrid",
    "wof:name":"Oteo Calatayud Agustin",
    "wof:placetype":"venue"
},
  "geometry": {"coordinates":[-3.762342453,40.3949775696],"type":"Point"}
}