{
  "type": "Feature",
  "properties": {
    "iso:country":"ES",
    "sg:address":"Calle de Escuelas, 3",
    "sg:city":"Santa Cruz De Moya",
    "sg:orig_category":"Carnicer\u00cdas, Carnicer\u00cdas",
    "sg:phone":"+34 969 36 50 79",
    "sg:postcode":"16336",
    "sg:province":"Cuenca",
    "wof:name":"Diaz Soriano Delfina",
    "wof:placetype":"venue"
},
  "geometry": {"coordinates":[-1.2549389601,39.955078125],"type":"Point"}
}