{
  "type": "Feature",
  "properties": {
    "iso:country":"ES",
    "sg:address":"Poligono Industrial Las Horcas, 5",
    "sg:city":"Alca\u00f1iz",
    "sg:orig_category":"Empresas De Impermeabilizaci\u00d3n",
    "sg:phone":"+34 978 83 45 38",
    "sg:postcode":"44600",
    "sg:province":"Teruel",
    "wof:name":"Construcciones Y Servicios Cyssa 44 S.l.l.",
    "wof:placetype":"venue"
},
  "geometry": {"coordinates":[-0.1331740022,41.0522842407],"type":"Point"}
}