{
  "type": "Feature",
  "properties": {
    "iso:country":"ES",
    "sg:address":"Carrer de Esglesia, 52",
    "sg:city":"Calella",
    "sg:orig_category":"Ropa Para Se\u00d1oras (al Por Menor)",
    "sg:phone":"+34 937 69 51 58",
    "sg:postcode":"08370",
    "sg:province":"Barcelona",
    "wof:name":"Sans Feliu Juan",
    "wof:placetype":"venue"
},
  "geometry": {"coordinates":[2.6594090462,41.6137046814],"type":"Point"}
}