{
  "type": "Feature",
  "properties": {
    "iso:country":"ES",
    "sg:address":"Cmno San Anton, S/n",
    "sg:city":"Letur",
    "sg:orig_category":"Sanatorios M\u00c9dico",
    "sg:phone":"+34 967 42 60 27",
    "sg:postcode":"02434",
    "sg:province":"Albacete",
    "wof:name":"Ayuntamiento De Letur",
    "wof:placetype":"venue"
},
  "geometry": {"coordinates":[-2.1027748585,38.3629226685],"type":"Point"}
}