{
  "type": "Feature",
  "properties": {
    "addr:full":"Ctra. Es Canar, S/n Sta. Eularia Riu Islas Baleares 07840",
    "addr:housenumber":"s / n",
    "addr:postcode":"07840",
    "addr:street":"Ctra. Es Canar;Islas Baleares",
    "iso:country":"ES",
    "sg:address":"Ctra. Es Canar, S/n",
    "sg:city":"Sta. Eularia Riu",
    "sg:orig_category":"Empresas De Carpinter\u00cda",
    "sg:phone":"+34 971 33 92 79",
    "sg:postcode":"07840",
    "sg:province":"Islas Baleares",
    "wof:name":"Automatismos Y Pvc Santa Eulalia S.l.",
    "wof:placetype":"venue"
},
  "geometry": {"coordinates":[1.547279954,38.9919815063],"type":"Point"}
}