{
  "type": "Feature",
  "properties": {
    "addr:full":"Pg Mata, 32 Reus Tarragona 43202",
    "addr:housenumber":"32",
    "addr:postcode":"43202",
    "addr:street":"Pg Mata",
    "iso:country":"ES",
    "sg:address":"Pg Mata, 32",
    "sg:city":"Reus",
    "sg:orig_category":"Molduras, Junquillos, Listones Y Molduras Perforadas",
    "sg:phone":"+34 977 33 07 92",
    "sg:postcode":"43202",
    "sg:province":"Tarragona",
    "wof:name":"Reus Passeig S.l.",
    "wof:placetype":"venue"
},
  "geometry": {"coordinates":[1.1013079882,41.1596565247],"type":"Point"}
}