{
  "type": "Feature",
  "properties": {
    "addr:full":"Calle de Hermandad, 6 Madrid Madrid 28025",
    "addr:housenumber":"6",
    "addr:postcode":"28025",
    "addr:street":"Calle De Hermandad",
    "iso:country":"ES",
    "sg:address":"Calle de Hermandad, 6",
    "sg:city":"Madrid",
    "sg:orig_category":"Plomeros",
    "sg:phone":"+34 915 25 20 88",
    "sg:postcode":"28025",
    "sg:province":"Madrid",
    "wof:name":"Hernandez Bautista Miguel",
    "wof:placetype":"venue"
},
  "geometry": {"coordinates":[-3.7279610634,40.3841514587],"type":"Point"}
}