{
  "type": "Feature",
  "properties": {
    "addr:full":"Calle de Calzada, 24 Antequera M\u00e1laga 29200",
    "addr:housenumber":"24",
    "addr:postcode":"29200",
    "addr:street":"Calle De Calzada",
    "iso:country":"ES",
    "sg:address":"Calle de Calzada, 24",
    "sg:city":"Antequera",
    "sg:orig_category":"Caf\u00c9s, Bares, Cervecer\u00cdas",
    "sg:phone":"+34 952 84 10 15",
    "sg:postcode":"29200",
    "sg:province":"M\u00e1laga",
    "wof:name":"Sistelcom-telemensaje S.a.",
    "wof:placetype":"venue"
},
  "geometry": {"coordinates":[-4.5578589439,37.0180244446],"type":"Point"}
}