{
  "type": "Feature",
  "properties": {
    "addr:full":"Calle de Requejo, 9 Fermoselle Zamora 49220",
    "addr:housenumber":"9",
    "addr:postcode":"49220",
    "addr:street":"Calle De Requejo;Zamora",
    "iso:country":"ES",
    "sg:address":"Calle de Requejo, 9",
    "sg:city":"Fermoselle",
    "sg:orig_category":"Molduras, Junquillos, Listones Y Molduras Perforadas",
    "sg:phone":"+34 980 61 34 46",
    "sg:postcode":"49220",
    "sg:province":"Zamora",
    "wof:name":"Veloso Funcia Anibal",
    "wof:placetype":"venue"
},
  "geometry": {"coordinates":[-6.3991789818,41.3190116882],"type":"Point"}
}