{
  "type": "Feature",
  "properties": {
    "iso:country":"ES",
    "sg:address":"Trss Casa De La Vila, 1",
    "sg:city":"Vilobi D'onyar",
    "sg:orig_category":"Ense\u00d1anza, Formaci\u00d3n Profesional: Aprendizaje",
    "sg:phone":"+34 972 47 30 26",
    "sg:postcode":"17185",
    "sg:province":"Girona",
    "wof:name":"Ajuntament De Vilobi D'onyar",
    "wof:placetype":"venue"
},
  "geometry": {"coordinates":[2.7282190323,41.8972663879],"type":"Point"}
}