{
  "type": "Feature",
  "properties": {
    "addr:full":"Plaz La Villa, S/n Adahuesca Huesca 22147",
    "addr:housenumber":"s",
    "addr:postcode":"22147",
    "addr:street":"Plaz;/ N Adahuesca",
    "iso:country":"ES",
    "sg:address":"Plaz La Villa, S/n",
    "sg:city":"Adahuesca",
    "sg:orig_category":"Sanatorios M\u00c9dico",
    "sg:phone":"+34 974 31 82 28",
    "sg:postcode":"22147",
    "sg:province":"Huesca",
    "wof:name":"Ayuntamiento De Adahuesca",
    "wof:placetype":"venue"
},
  "geometry": {"coordinates":[-0.0279866997,42.2066383362],"type":"Point"}
}