{
  "type": "Feature",
  "properties": {
    "addr:full":"Merkatondoa, S/n Estella Navarra 31200",
    "addr:housenumber":"/ n",
    "addr:postcode":"31200",
    "addr:street":"Merkatondoa S",
    "iso:country":"ES",
    "sg:address":"Merkatondoa, S/n",
    "sg:city":"Estella",
    "sg:orig_category":"Art\u00cdculos Funerarios (al Por Menor)",
    "sg:phone":"+34 948 54 68 29",
    "sg:postcode":"31200",
    "sg:province":"Navarra",
    "wof:name":"Gestiones Funebres Vega S.l.",
    "wof:placetype":"venue"
},
  "geometry": {"coordinates":[-2.0291090012,42.6582756042],"type":"Point"}
}