{
  "type": "Feature",
  "properties": {
    "addr:full":"Av Mistral, 15 Barcelona Barcelona 08015",
    "addr:housenumber":"15",
    "addr:postcode":"08015",
    "addr:street":"Av Mistral",
    "iso:country":"ES",
    "sg:address":"Av Mistral, 15",
    "sg:city":"Barcelona",
    "sg:orig_category":"Cer\u00c1micas: Material Y Suministros",
    "sg:phone":"+34 934 25 15 71",
    "sg:postcode":"08015",
    "sg:province":"Barcelona",
    "wof:name":"Instalaciones Y Mantenimientos Berna S.l",
    "wof:placetype":"venue"
},
  "geometry": {"coordinates":[2.1578099728,41.376750946],"type":"Point"}
}