{
  "type": "Feature",
  "properties": {
    "iso:country":"ES",
    "sg:address":"Pla\u00c7 Parc De L'estacio, 2",
    "sg:city":"Gandia",
    "sg:orig_category":"Institutos De Belleza",
    "sg:phone":"+34 962 96 24 15",
    "sg:postcode":"46700",
    "sg:province":"Valencia",
    "wof:name":"Beses Guillen Maria Victoria",
    "wof:placetype":"venue"
},
  "geometry": {"coordinates":[-0.1801339984,38.9696960449],"type":"Point"}
}