{
  "type": "Feature",
  "properties": {
    "addr:full":"Avda San Lucas (as), 22 Mondo\u00f1edo Lugo 27740",
    "addr:housenumber":"22",
    "addr:postcode":"27740",
    "addr:street":"Avda San Lucas As",
    "iso:country":"ES",
    "sg:address":"Avda San Lucas (as), 22",
    "sg:city":"Mondo\u00f1edo",
    "sg:orig_category":"Art\u00cdculos Funerarios (al Por Menor)",
    "sg:phone":"+34 982 52 13 86",
    "sg:postcode":"27740",
    "sg:province":"Lugo",
    "wof:name":"Moran Garcia Angel",
    "wof:placetype":"venue"
},
  "geometry": {"coordinates":[-7.3670091629,43.4286003113],"type":"Point"}
}