{
  "type": "Feature",
  "properties": {
    "iso:country":"ES",
    "sg:address":"Avda Andalucia, 4",
    "sg:city":"Cadiz",
    "sg:orig_category":"Comunidades Religiosas",
    "sg:phone":"+34 956 27 07 18",
    "sg:postcode":"11008",
    "sg:province":"C\u00e1diz",
    "wof:name":"Hijas Del Corazon De Maria",
    "wof:placetype":"venue"
},
  "geometry": {"coordinates":[-6.2873878479,36.5244522095],"type":"Point"}
}