{
  "type": "Feature",
  "properties": {
    "addr:full":"Avda Santiago Ramon Y Cajal, 69 Malaga M\u00e1laga 29014",
    "addr:housenumber":"69",
    "addr:postcode":"29014",
    "addr:street":"Avda Santiago Ramon Y Cajal;Ma\u0301Laga",
    "iso:country":"ES",
    "sg:address":"Avda Santiago Ramon Y Cajal, 69",
    "sg:city":"Malaga",
    "sg:orig_category":"Papeler\u00cdas, Librer\u00cdas",
    "sg:phone":"+34 952 25 98 71",
    "sg:postcode":"29014",
    "sg:province":"M\u00e1laga",
    "wof:name":"Ruiz Torres Eugenio",
    "wof:placetype":"venue"
},
  "geometry": {"coordinates":[-4.4230070114,36.744884491],"type":"Point"}
}