{
  "type": "Feature",
  "properties": {
    "addr:full":"Av Castello, 5 Benidorm Alicante 03500",
    "addr:housenumber":"5",
    "addr:postcode":"03500",
    "addr:street":"Av Castello",
    "iso:country":"ES",
    "sg:address":"Av Castello, 5",
    "sg:city":"Benidorm",
    "sg:orig_category":"Agencias De Viajes",
    "sg:phone":"+34 966 80 81 25",
    "sg:postcode":"03500",
    "sg:province":"Alicante",
    "wof:name":"Sunsea Travel S.l.",
    "wof:placetype":"venue"
},
  "geometry": {"coordinates":[-0.1095710024,38.5362663269],"type":"Point"}
}