{
  "type": "Feature",
  "properties": {
    "iso:country":"ES",
    "sg:address":"Carrer de Flors, 7",
    "sg:city":"Vandellos",
    "sg:orig_category":"Inform\u00c1tica: Consultores",
    "sg:phone":"+34 977 82 42 20",
    "sg:postcode":"43891",
    "sg:province":"Tarragona",
    "wof:name":"Assessoria Informatica Vandellos S.l",
    "wof:placetype":"venue"
},
  "geometry": {"coordinates":[0.8323315978,41.0202026367],"type":"Point"}
}