{
  "type": "Feature",
  "properties": {
    "addr:full":"Calle de Favareta, 19 Alzira Valencia 46600",
    "addr:housenumber":"19",
    "addr:postcode":"46600",
    "addr:street":"Calle De Favareta",
    "iso:country":"ES",
    "sg:address":"Calle de Favareta, 19",
    "sg:city":"Alzira",
    "sg:orig_category":"Asesor\u00cda De Formaci\u00d3n Y Gesti\u00d3n De Personal",
    "sg:phone":"+34 962 41 61 23",
    "sg:postcode":"46600",
    "sg:province":"Valencia",
    "wof:name":"Blay Tomas Enric",
    "wof:placetype":"venue"
},
  "geometry": {"coordinates":[-0.4313110113,39.1538047791],"type":"Point"}
}