{
  "type": "Feature",
  "properties": {
    "addr:full":"Calle de Sierra De Ancares, 13 Soto De Vi\u00e7uelas Madrid 28760",
    "addr:housenumber":"13",
    "addr:postcode":"28760",
    "addr:street":"Calle De Sierra De Ancares",
    "iso:country":"ES",
    "sg:address":"Calle de Sierra De Ancares, 13",
    "sg:city":"Soto De Vi\u00e7uelas",
    "sg:orig_category":"Fotograf\u00cda Publicitaria",
    "sg:phone":"+34 918 03 05 56",
    "sg:postcode":"28760",
    "sg:province":"Madrid",
    "wof:name":"Martin Bautista Juan Carlos",
    "wof:placetype":"venue"
},
  "geometry": {"coordinates":[-3.6826319695,40.6118202209],"type":"Point"}
}