{
  "type": "Feature",
  "properties": {
    "iso:country":"ES",
    "sg:address":"Ctra Manlleu, 7",
    "sg:city":"Vic",
    "sg:orig_category":"Tapicer\u00cdas",
    "sg:phone":"+34 938 89 19 58",
    "sg:postcode":"08500",
    "sg:province":"Barcelona",
    "wof:name":"Garcia Company Carme",
    "wof:placetype":"venue"
},
  "geometry": {"coordinates":[2.2550048828,41.9352684021],"type":"Point"}
}