{
  "type": "Feature",
  "properties": {
    "addr:full":"Pla\u00c7 Carme, 12 Seu D'urgell Lleida 25700",
    "addr:housenumber":"12",
    "addr:postcode":"25700",
    "addr:street":"Carme",
    "iso:country":"ES",
    "sg:address":"Pla\u00c7 Carme, 12",
    "sg:city":"Seu D'urgell",
    "sg:orig_category":"Fabricaci\u00d3n De Art\u00cdculos Y Equipos Deportivos Y De Ocio",
    "sg:phone":"+34 973 36 01 69",
    "sg:postcode":"25700",
    "sg:province":"Lleida",
    "wof:name":"Distribucions Cadi S.l.",
    "wof:placetype":"venue"
},
  "geometry": {"coordinates":[0.6232429743,41.6144561768],"type":"Point"}
}