{
  "type": "Feature",
  "properties": {
    "iso:country":"ES",
    "sg:address":"Carrer de Arago, 184",
    "sg:city":"Barcelona",
    "sg:orig_category":"Arquitectos",
    "sg:phone":"+34 933 23 33 41",
    "sg:postcode":"08011",
    "sg:province":"Barcelona",
    "wof:name":"Ozores Marco-gardoqui Fernando",
    "wof:placetype":"venue"
},
  "geometry": {"coordinates":[2.1580779552,41.3868637085],"type":"Point"}
}