{
  "type": "Feature",
  "properties": {
    "addr:full":"Caminograde(iglesiafeita), S/n Iglesiafeita A Coru\u00f1a 15580",
    "addr:housenumber":"s",
    "addr:postcode":"15580",
    "addr:street":"/ N;Corun\u0303A",
    "iso:country":"ES",
    "sg:address":"Caminograde(iglesiafeita), S/n",
    "sg:city":"Iglesiafeita",
    "sg:orig_category":"Art\u00cdculos Funerarios (al Por Menor)",
    "sg:phone":"+34 981 49 05 88",
    "sg:postcode":"15580",
    "sg:province":"A Coru\u00f1a",
    "wof:name":"Servicios Funerarios De Galicia S.l",
    "wof:placetype":"venue"
},
  "geometry": {"coordinates":[-8.0042333603,43.4975585938],"type":"Point"}
}