{
  "type": "Feature",
  "properties": {
    "iso:country":"ES",
    "sg:address":"Carrer de Clot, 158",
    "sg:city":"Barcelona",
    "sg:orig_category":"Asesor\u00cda Sobre Comunicaci\u00d3n De Empresas",
    "sg:phone":"+34 932 32 98 84",
    "sg:postcode":"08026",
    "sg:province":"Barcelona",
    "wof:name":"Aurum Consulting S.l",
    "wof:placetype":"venue"
},
  "geometry": {"coordinates":[2.1899299622,41.4116859436],"type":"Point"}
}