{
  "type": "Feature",
  "properties": {
    "iso:country":"ES",
    "sg:address":"Pg Zona Franca, 221",
    "sg:city":"Barcelona",
    "sg:orig_category":"Distribuci\u00d3n De Petr\u00d3leo Y Derivados",
    "sg:phone":"+34 933 31 78 45",
    "sg:postcode":"08038",
    "sg:province":"Barcelona",
    "wof:name":"Galpgest Petrogal Estaciones De Servicio S.l.u.",
    "wof:placetype":"venue"
},
  "geometry": {"coordinates":[2.1369690895,41.3625793457],"type":"Point"}
}