{
  "type": "Feature",
  "properties": {
    "addr:full":"Markole Auzoa, 5 Aretxabaleta Guip\u00f9zcoa 20550",
    "addr:housenumber":"5",
    "addr:postcode":"20550",
    "addr:street":"Markole Auzoa;Guipu\u0300Zcoa",
    "iso:country":"ES",
    "sg:address":"Markole Auzoa, 5",
    "sg:city":"Aretxabaleta",
    "sg:orig_category":"Centros De Educaci\u00d3n Especial",
    "sg:phone":"+34 943 79 88 50",
    "sg:postcode":"20550",
    "sg:province":"Guip\u00f9zcoa",
    "wof:name":"Gobierno Vasco-eusko Jaurlaritza",
    "wof:placetype":"venue"
},
  "geometry": {"coordinates":[-2.5087060928,43.0297889709],"type":"Point"}
}