{
  "type": "Feature",
  "properties": {
    "iso:country":"ES",
    "sg:address":"Avda Federico Anaya, 17",
    "sg:city":"Salamanca",
    "sg:orig_category":"Ense\u00d1anza Variada",
    "sg:phone":"+34 923 25 63 48",
    "sg:postcode":"37005",
    "sg:province":"Salamanca",
    "sg:website":"www.acedarwingtelefonica.net",
    "wof:name":"Perez Garcia Juan Vicente",
    "wof:placetype":"venue"
},
  "geometry": {"coordinates":[-5.6574220657,40.9724807739],"type":"Point"}
}