{
  "type": "Feature",
  "properties": {
    "addr:full":"Calle de Real, 60 Valdepe\u00f1as Ciudad Real 13300",
    "addr:housenumber":"60",
    "addr:postcode":"13300",
    "addr:street":"Calle De Real",
    "iso:country":"ES",
    "sg:address":"Calle de Real, 60",
    "sg:city":"Valdepe\u00f1as",
    "sg:orig_category":"Radiocomunicaciones, Telefon\u00cda M\u00d3vil, Radiomensajer\u00cda: Servicios, Comercializaci\u00d3n",
    "sg:phone":"+34 902 31 30 30",
    "sg:postcode":"13300",
    "sg:province":"Ciudad Real",
    "wof:name":"Telyman Telecom S.l.",
    "wof:placetype":"venue"
},
  "geometry": {"coordinates":[-3.3828289509,38.7646484375],"type":"Point"}
}