{
  "type": "Feature",
  "properties": {
    "addr:full":"Calle de San Juan, S/n Badajoz Badajoz 06002",
    "addr:housenumber":"s / n",
    "addr:postcode":"06002",
    "addr:street":"Calle De San Juan",
    "iso:country":"ES",
    "sg:address":"Calle de San Juan, S/n",
    "sg:city":"Badajoz",
    "sg:orig_category":"Asociaciones, Instituciones De Consumidores Y Usuarios",
    "sg:phone":"+34 924 20 74 60",
    "sg:postcode":"06002",
    "sg:province":"Badajoz",
    "wof:name":"Union De Consumidores De Extremadura",
    "wof:placetype":"venue"
},
  "geometry": {"coordinates":[-6.9694237709,38.8794555664],"type":"Point"}
}