{
  "type": "Feature",
  "properties": {
    "addr:full":"Calle de San Miguel, 45 Zaragoza Zaragoza 50001",
    "addr:housenumber":"45",
    "addr:postcode":"50001",
    "addr:street":"Calle De San Miguel",
    "iso:country":"ES",
    "sg:address":"Calle de San Miguel, 45",
    "sg:city":"Zaragoza",
    "sg:orig_category":"Electrodom\u00c9sticos (al Por Menor)",
    "sg:phone":"+34 976 21 23 03",
    "sg:postcode":"50001",
    "sg:province":"Zaragoza",
    "wof:name":"Corvinos Sanz Antonio",
    "wof:placetype":"venue"
},
  "geometry": {"coordinates":[-0.8770030141,41.6498641968],"type":"Point"}
}