{
  "type": "Feature",
  "properties": {
    "iso:country":"ES",
    "sg:address":"Cra Picos (de Los), 25",
    "sg:city":"Almeria",
    "sg:orig_category":"M\u00c1quinas De Jardiner\u00cda",
    "sg:phone":"+34 950 24 49 46",
    "sg:postcode":"04004",
    "sg:province":"Almer\u00eda",
    "wof:name":"El Brillante Oliver S.l.",
    "wof:placetype":"venue"
},
  "geometry": {"coordinates":[-2.4608390331,36.8422698975],"type":"Point"}
}