{
  "type": "Feature",
  "properties": {
    "addr:full":"Rua Vazquez De Parga, 169 Carballo La Coru\u00f1a 15100",
    "addr:postcode":"15100",
    "addr:street":"Rua Vazquez De Parga 169 Carballo La Corun\u0303A",
    "iso:country":"ES",
    "sg:address":"Rua Vazquez De Parga, 169",
    "sg:city":"Carballo",
    "sg:orig_category":"Empresas De Pintura Y Revestimientos",
    "sg:phone":"+34 981 70 13 99",
    "sg:postcode":"15100",
    "sg:province":"La Coru\u00f1a",
    "wof:name":"Rodriguez Garcia Marcelino",
    "wof:placetype":"venue"
},
  "geometry": {"coordinates":[-8.686293602,43.2203025818],"type":"Point"}
}