{
  "type": "Feature",
  "properties": {
    "iso:country":"ES",
    "sg:address":"Ibaiondo, 4",
    "sg:city":"Aduna",
    "sg:orig_category":"Construcci\u00d3n Mec\u00c1nica",
    "sg:phone":"+34 943 69 32 92",
    "sg:postcode":"20150",
    "sg:province":"Guip\u00f9zcoa",
    "wof:name":"Talleres Biyok C.b.",
    "wof:placetype":"venue"
},
  "geometry": {"coordinates":[-2.0525400639,43.1982307434],"type":"Point"}
}