{
  "type": "Feature",
  "properties": {
    "iso:country":"ES",
    "sg:address":"Dr. Mara\u00f1on, 24",
    "sg:city":"Cox",
    "sg:orig_category":"Asociaciones Y Clubs Deportivos",
    "sg:phone":"+34 966 75 00 85",
    "sg:postcode":"03350",
    "sg:province":"Alicante",
    "wof:name":"Manresa Santacruz Elias",
    "wof:placetype":"venue"
},
  "geometry": {"coordinates":[-0.8863859773,38.1425857544],"type":"Point"}
}