{
  "type": "Feature",
  "properties": {
    "iso:country":"ES",
    "sg:address":"Los Cambulloneros, S/n",
    "sg:city":"Las Palmas",
    "sg:orig_category":"Transportes Mar\u00cdtimos",
    "sg:phone":"+34 928 46 20 20",
    "sg:postcode":"35008",
    "sg:province":"Las Palmas",
    "wof:name":"Nenufar Shipping S.a.",
    "wof:placetype":"venue"
},
  "geometry": {"coordinates":[-15.4172363281,28.1411418915],"type":"Point"}
}