{
  "type": "Feature",
  "properties": {
    "addr:full":"Calle de Alvaro Cunqueiro, 4 Coru\u00d1a La Coru\u00f1a 15008",
    "addr:housenumber":"4",
    "addr:postcode":"15008",
    "addr:street":"Calle De Alvaro Cunqueiro;La Corun\u0303A",
    "iso:country":"ES",
    "sg:address":"Calle de Alvaro Cunqueiro, 4",
    "sg:city":"Coru\u00d1a",
    "sg:orig_category":"Promotores Constructores",
    "sg:phone":"+34 981 15 36 91",
    "sg:postcode":"15008",
    "sg:province":"La Coru\u00f1a",
    "wof:name":"Inocor S.l.",
    "wof:placetype":"venue"
},
  "geometry": {"coordinates":[-8.4084243774,43.3477935791],"type":"Point"}
}