{
  "type": "Feature",
  "properties": {
    "addr:full":"Calle de Arcos, 40 Jerez De La Frontera C\u00e1diz 11401",
    "addr:housenumber":"40",
    "addr:postcode":"11401",
    "addr:street":"Calle De Arcos",
    "iso:country":"ES",
    "sg:address":"Calle de Arcos, 40",
    "sg:city":"Jerez De La Frontera",
    "sg:orig_category":"Art\u00cdculos De Decoraci\u00d3n",
    "sg:phone":"+34 956 34 10 03",
    "sg:postcode":"11401",
    "sg:province":"C\u00e1diz",
    "wof:name":"Amaya Garcia Maria Dolores",
    "wof:placetype":"venue"
},
  "geometry": {"coordinates":[-6.1320385933,36.683883667],"type":"Point"}
}