{
  "type": "Feature",
  "properties": {
    "iso:country":"ES",
    "sg:address":"Bosch, 1",
    "sg:city":"Vilamant",
    "sg:orig_category":"Cerrajer\u00cda, Ferrallista",
    "sg:phone":"+34 972 54 60 06",
    "sg:postcode":"17743",
    "sg:province":"Girona",
    "wof:name":"Pujolar Ayats Agustin",
    "wof:placetype":"venue"
},
  "geometry": {"coordinates":[2.8895170689,42.2545967102],"type":"Point"}
}