{
  "type": "Feature",
  "properties": {
    "iso:country":"ES",
    "sg:address":"Calle de Honesto Batalon, 27",
    "sg:city":"Gijon",
    "sg:orig_category":"Fabricaci\u00d3n, Reparaci\u00d3n Y Mantenimiento De Construcciones Navales Y Fluviales",
    "sg:phone":"+34 985 34 06 55",
    "sg:postcode":"33201",
    "sg:province":"Asturias",
    "wof:name":"Euromar S.c.",
    "wof:placetype":"venue"
},
  "geometry": {"coordinates":[-5.6639308929,43.5476303101],"type":"Point"}
}