{
  "type": "Feature",
  "properties": {
    "iso:country":"ES",
    "sg:address":"Rier Matamoros, 20",
    "sg:city":"Badalona",
    "sg:orig_category":"Molduras, Junquillos, Listones Y Molduras Perforadas",
    "sg:phone":"+34 933 89 16 02",
    "sg:postcode":"08911",
    "sg:province":"Barcelona",
    "wof:name":"Garcia Castillejos Lidia",
    "wof:placetype":"venue"
},
  "geometry": {"coordinates":[2.2484369278,41.4543914795],"type":"Point"}
}