{
  "type": "Feature",
  "properties": {
    "addr:full":"Calle de Imagen, 7 Madrid Madrid 28018",
    "addr:housenumber":"7",
    "addr:postcode":"madrid;28018",
    "addr:street":"Calle De Imagen",
    "iso:country":"ES",
    "sg:address":"Calle de Imagen, 7",
    "sg:city":"Madrid",
    "sg:orig_category":"Pescader\u00cdas (al Por Menor)",
    "sg:phone":"+34 914 77 99 98",
    "sg:postcode":"28018",
    "sg:province":"Madrid",
    "wof:name":"Acosta Gonzalez Juan Carlos",
    "wof:placetype":"venue"
},
  "geometry": {"coordinates":[-3.7720558643,40.548412323],"type":"Point"}
}