{
  "type": "Feature",
  "properties": {
    "iso:country":"ES",
    "sg:address":"Rua Garcia Olloqui, 8",
    "sg:city":"Vigo",
    "sg:orig_category":"Seguridad Social",
    "sg:phone":"+34 986 43 07 88",
    "sg:postcode":"36201",
    "sg:province":"Pontevedra",
    "sg:website":"www.fremap.es",
    "wof:name":"Fremap Mutua De Accidentes De Trabajo",
    "wof:placetype":"venue"
},
  "geometry": {"coordinates":[-8.7240076065,42.2400436401],"type":"Point"}
}