{
  "type": "Feature",
  "properties": {
    "iso:country":"ES",
    "sg:address":"Calle de Mayor, 18",
    "sg:city":"Madrid",
    "sg:orig_category":"Librer\u00cdas",
    "sg:phone":"+34 913 66 41 41",
    "sg:postcode":"28013",
    "sg:province":"Madrid",
    "sg:website":"www.narraciones.com",
    "wof:name":"Mendez Vicente Antonio",
    "wof:placetype":"venue"
},
  "geometry": {"coordinates":[-3.7067368031,40.4162979126],"type":"Point"}
}