{
  "type": "Feature",
  "properties": {
    "iso:country":"ES",
    "sg:address":"Calle de Aguirre Maximo, 11",
    "sg:city":"Bilbao",
    "sg:orig_category":"Loter\u00cda Y T\u00d3mbola",
    "sg:phone":"+34 944 15 09 45",
    "sg:postcode":"48011",
    "sg:province":"Vizcaya",
    "wof:name":"Azcarreta Garcia Pedro",
    "wof:placetype":"venue"
},
  "geometry": {"coordinates":[-2.9376244545,43.2637939453],"type":"Point"}
}