{
  "type": "Feature",
  "properties": {
    "iso:country":"ES",
    "sg:address":"Calle de Torneros, 55",
    "sg:city":"Getafe",
    "sg:orig_category":"Pescader\u00cdas (al Por Mayor)",
    "sg:phone":"+34 902 11 42 80",
    "sg:postcode":"28906",
    "sg:province":"Madrid",
    "wof:name":"Tecnosea S.l.",
    "wof:placetype":"venue"
},
  "geometry": {"coordinates":[-3.6957285404,40.3108558655],"type":"Point"}
}