{
  "type": "Feature",
  "properties": {
    "addr:full":"Calle de Oran, 23 Gijon Asturias 33210",
    "addr:housenumber":"23",
    "addr:postcode":"33210",
    "addr:street":"Calle De Oran",
    "iso:country":"ES",
    "sg:address":"Calle de Oran, 23",
    "sg:city":"Gijon",
    "sg:orig_category":"\u00d3ptica: Instrumentos (fabricaci\u00d3n)",
    "sg:phone":"+34 985 16 01 03",
    "sg:postcode":"33210",
    "sg:province":"Asturias",
    "wof:name":"Optica Astur Principado S.l",
    "wof:placetype":"venue"
},
  "geometry": {"coordinates":[-5.6785011292,43.5287284851],"type":"Point"}
}