{
  "type": "Feature",
  "properties": {
    "addr:full":"Av Pi I Margall, 143 Caldes Montbui Barcelona 08140",
    "addr:housenumber":"143",
    "addr:postcode":"08140",
    "addr:street":"Av Pi I Margall;Montbui Barcelona",
    "iso:country":"ES",
    "sg:address":"Av Pi I Margall, 143",
    "sg:city":"Caldes Montbui",
    "sg:orig_category":"Centros Comerciales Y Grandes Tiendas",
    "sg:phone":"+34 938 65 26 31",
    "sg:postcode":"08140",
    "sg:province":"Barcelona",
    "wof:name":"Li  Wei",
    "wof:placetype":"venue"
},
  "geometry": {"coordinates":[2.1677401066,41.6276817322],"type":"Point"}
}