{
  "type": "Feature",
  "properties": {
    "addr:full":"Calle de Leones, 24 Valencia Valencia 46022",
    "addr:housenumber":"24",
    "addr:postcode":"46022",
    "addr:street":"Calle De Leones",
    "iso:country":"ES",
    "sg:address":"Calle de Leones, 24",
    "sg:city":"Valencia",
    "sg:orig_category":"Muebles Y Accesorios Para Cocinas Y Cuartos De Ba\u00d1o (al Por Menor)",
    "sg:phone":"+34 963 30 69 92",
    "sg:postcode":"46022",
    "sg:province":"Valencia",
    "wof:name":"Elena Antunez Olivas Y Otros Cdad",
    "wof:placetype":"venue"
},
  "geometry": {"coordinates":[-0.3480130136,39.466506958],"type":"Point"}
}