{
  "type": "Feature",
  "properties": {
    "iso:country":"ES",
    "sg:address":"Calle de Alarcos, 18",
    "sg:city":"Ciudad Real",
    "sg:orig_category":"M\u00c9dicos: Cardiolog\u00cda Y Afecciones Cardiovasculares",
    "sg:phone":"+34 926 21 29 48",
    "sg:postcode":"13001",
    "sg:province":"Ciudad Real",
    "wof:name":"Arroyo Garcia-cervigon Felix",
    "wof:placetype":"venue"
},
  "geometry": {"coordinates":[-3.9311056137,38.9832382202],"type":"Point"}
}