{
  "type": "Feature",
  "properties": {
    "iso:country":"ES",
    "sg:address":"Carr Nou Cases, 2",
    "sg:city":"Badalona",
    "sg:orig_category":"Caf\u00c9s, Bares, Cervecer\u00cdas",
    "sg:phone":"+34 933 95 42 13",
    "sg:postcode":"08917",
    "sg:province":"Barcelona",
    "wof:name":"Leon Martinez Maria Teresa",
    "wof:placetype":"venue"
},
  "geometry": {"coordinates":[2.2392790318,41.4593811035],"type":"Point"}
}