{
  "type": "Feature",
  "properties": {
    "addr:full":"Avda Llano Castellano, 11 Madrid Madrid 28034",
    "addr:housenumber":"11",
    "addr:postcode":"madrid;28034",
    "addr:street":"Avda Llano Castellano",
    "iso:country":"ES",
    "sg:address":"Avda Llano Castellano, 11",
    "sg:city":"Madrid",
    "sg:orig_category":"Poller\u00cda Y Caza (al Por Menor)",
    "sg:phone":"+34 913 58 42 18",
    "sg:postcode":"28034",
    "sg:province":"Madrid",
    "wof:name":"Fernanz Sancho Pedro",
    "wof:placetype":"venue"
},
  "geometry": {"coordinates":[-3.6843829155,40.4838294983],"type":"Point"}
}