{
  "type": "Feature",
  "properties": {
    "iso:country":"ES",
    "sg:address":"Calle de Cristo, S/n",
    "sg:city":"Honrubia",
    "sg:orig_category":"Contenedores (mercanc\u00cdas)",
    "sg:phone":"+34 969 29 20 04",
    "sg:postcode":"16730",
    "sg:province":"Cuenca",
    "wof:name":"Transportes Lopez Hortelano S.l",
    "wof:placetype":"venue"
},
  "geometry": {"coordinates":[-2.2794690132,39.6158256531],"type":"Point"}
}