{
  "type": "Feature",
  "properties": {
    "iso:country":"ES",
    "sg:address":"Ctra Faro Sabinal, 110",
    "sg:city":"Marinas",
    "sg:orig_category":"Ense\u00d1anza: Idiomas",
    "sg:phone":"+34 950 33 34 15",
    "sg:postcode":"04740",
    "sg:province":"Almer\u00eda",
    "wof:name":"Comunicacion S.c.",
    "wof:placetype":"venue"
},
  "geometry": {"coordinates":[-2.6339890957,36.7305793762],"type":"Point"}
}