{
  "type": "Feature",
  "properties": {
    "iso:country":"ES",
    "sg:address":"Calle de Doctor Esquerdo, 170",
    "sg:city":"Madrid",
    "sg:orig_category":"Arquitectos",
    "sg:phone":"+34 914 33 08 89",
    "sg:postcode":"28007",
    "sg:province":"Madrid",
    "wof:name":"Sancho Roda Jose",
    "wof:placetype":"venue"
},
  "geometry": {"coordinates":[-3.6736249924,40.4027938843],"type":"Point"}
}