{
  "type": "Feature",
  "properties": {
    "iso:country":"ES",
    "sg:address":"Carr Pare Vives, 73",
    "sg:city":"Pollen\u00e7a",
    "sg:orig_category":"Empresas De Carpinter\u00cda De Madera",
    "sg:phone":"+34 971 53 03 57",
    "sg:postcode":"07460",
    "sg:province":"Islas Baleares",
    "wof:name":"Fusteria Aixartell S.l.",
    "wof:placetype":"venue"
},
  "geometry": {"coordinates":[3.0187709332,39.8815879822],"type":"Point"}
}