{
  "type": "Feature",
  "properties": {
    "iso:country":"ES",
    "sg:address":"Calle de Bailen, 11",
    "sg:city":"Bilbao",
    "sg:orig_category":"Reparaci\u00d3n Y Restauraci\u00d3n De Objetos Diversos",
    "sg:phone":"+34 944 15 41 99",
    "sg:postcode":"48003",
    "sg:province":"Vizcaya",
    "sg:website":"www.oraintxebi.com",
    "wof:name":"Bilekomen S.l.l. Oraintxe",
    "wof:placetype":"venue"
},
  "geometry": {"coordinates":[-2.9278850555,43.2583770752],"type":"Point"}
}