{
  "type": "Feature",
  "properties": {
    "addr:full":"Carrer de Roger De Flor, 240 Sabadell Barcelona 08205",
    "addr:housenumber":"240",
    "addr:postcode":"08205",
    "addr:street":"Carrer De Roger De Flor",
    "iso:country":"ES",
    "sg:address":"Carrer de Roger De Flor, 240",
    "sg:city":"Sabadell",
    "sg:orig_category":"Telas (al Por Mayor)",
    "sg:phone":"+34 937 10 20 30",
    "sg:postcode":"08205",
    "sg:province":"Barcelona",
    "wof:name":"Modibiba S.l.",
    "wof:placetype":"venue"
},
  "geometry": {"coordinates":[2.1056909561,41.5379295349],"type":"Point"}
}