{
  "type": "Feature",
  "properties": {
    "iso:country":"ES",
    "sg:address":"Las Eras, S/n",
    "sg:city":"Carrizo Ribera",
    "sg:orig_category":"Molduras, Junquillos, Listones Y Molduras Perforadas",
    "sg:phone":"+34 987 35 71 70",
    "sg:postcode":"24270",
    "sg:province":"Le\u00f3n",
    "wof:name":"Alcoba Perez Bernardo",
    "wof:placetype":"venue"
},
  "geometry": {"coordinates":[-5.8238897324,42.586101532],"type":"Point"}
}