{
  "type": "Feature",
  "properties": {
    "addr:full":"Ctra. Valencia, Km. 0018,4 Rivas Vaciamadrid Madrid 28529",
    "addr:postcode":"28529",
    "addr:street":"Ctra. Valencia Km. 0018,4",
    "iso:country":"ES",
    "sg:address":"Ctra. Valencia, Km. 0018,4",
    "sg:city":"Rivas Vaciamadrid",
    "sg:orig_category":"Aguas (distribuci\u00d3n, Servicios)",
    "sg:phone":"+34 916 70 10 73",
    "sg:postcode":"28529",
    "sg:province":"Madrid",
    "wof:name":"Inima Servicios Europeos De Medio Ambiente S.a.",
    "wof:placetype":"venue"
},
  "geometry": {"coordinates":[-3.5102670193,40.314289093],"type":"Point"}
}