{
  "type": "Feature",
  "properties": {
    "iso:country":"ES",
    "sg:address":"Calle de Puerta De Huerta, 13",
    "sg:city":"Oca\u00f1a",
    "sg:orig_category":"Albergues",
    "sg:phone":"+34 925 12 03 20",
    "sg:postcode":"45300",
    "sg:province":"Toledo",
    "wof:name":"Comercial Mapa Y Monedero S.l.l.",
    "wof:placetype":"venue"
},
  "geometry": {"coordinates":[-3.5040390491,39.9554138184],"type":"Point"}
}