{
  "type": "Feature",
  "properties": {
    "iso:country":"ES",
    "sg:address":"Bule Vicente Blasco Iba\u00d1ez, 17",
    "sg:city":"Castellon",
    "sg:orig_category":"Arquitectos",
    "sg:phone":"+34 964 23 62 07",
    "sg:postcode":"12003",
    "sg:province":"Castell\u00f3n",
    "wof:name":"Agusti Ramos Juan",
    "wof:placetype":"venue"
},
  "geometry": {"coordinates":[-0.0093265995,39.9709663391],"type":"Point"}
}