{
  "type": "Feature",
  "properties": {
    "addr:full":"Avgd Espioca, 78 Silla Valencia 46460",
    "addr:housenumber":"78",
    "addr:postcode":"46460",
    "addr:street":"Espioca",
    "iso:country":"ES",
    "sg:address":"Avgd Espioca, 78",
    "sg:city":"Silla",
    "sg:orig_category":"Materiales De Aislamiento T\u00c9rmico Y Ac\u00dastico",
    "sg:phone":"+34 963 37 20 27",
    "sg:postcode":"46460",
    "sg:province":"Valencia",
    "sg:website":"www.prosinter.es",
    "wof:name":"Prosinter Representaciones Internacionales S.l",
    "wof:placetype":"venue"
},
  "geometry": {"coordinates":[-0.417858988,39.3685531616],"type":"Point"}
}