{
  "type": "Feature",
  "properties": {
    "addr:full":"Calle de Abenda\u00d1o, 24 Vitoria-gasteiz \u00c1lava 01008",
    "addr:housenumber":"24",
    "addr:postcode":"01008",
    "addr:street":"Calle De Abendan\u0303O",
    "iso:country":"ES",
    "sg:address":"Calle de Abenda\u00d1o, 24",
    "sg:city":"Vitoria-gasteiz",
    "sg:orig_category":"Promotores Constructores",
    "sg:phone":"+34 945 13 62 38",
    "sg:postcode":"01008",
    "sg:province":"\u00c1lava",
    "wof:name":"Construcciones Ion Virgala, S.a",
    "wof:placetype":"venue"
},
  "geometry": {"coordinates":[-2.6836614609,42.8445930481],"type":"Point"}
}