{
  "type": "Feature",
  "properties": {
    "addr:full":"Avda Campo De Futbol, S/n Yunclillos Toledo 45591",
    "addr:housenumber":"s / n",
    "addr:postcode":"45591",
    "addr:street":"Avda Campo",
    "iso:country":"ES",
    "sg:address":"Avda Campo De Futbol, S/n",
    "sg:city":"Yunclillos",
    "sg:orig_category":"Ropa Y Accesorios",
    "sg:phone":"+34 925 35 10 00",
    "sg:postcode":"45591",
    "sg:province":"Toledo",
    "wof:name":"Confecciones Jamce S. A.",
    "wof:placetype":"venue"
},
  "geometry": {"coordinates":[-3.9860138893,40.0218658447],"type":"Point"}
}