{
  "type": "Feature",
  "properties": {
    "iso:country":"ES",
    "sg:address":"Avda Andalucia (de), 118",
    "sg:city":"Estepa",
    "sg:orig_category":"Quincaller\u00cda (al Por Menor)",
    "sg:phone":"+34 955 91 42 52",
    "sg:postcode":"41560",
    "sg:province":"Sevilla",
    "wof:name":"Comercial Prados Tenor S.l.",
    "wof:placetype":"venue"
},
  "geometry": {"coordinates":[-4.8765091896,37.2947807312],"type":"Point"}
}