{
  "type": "Feature",
  "properties": {
    "iso:country":"ES",
    "sg:address":"Avda Constitucion, 3",
    "sg:city":"Escalona",
    "sg:orig_category":"Electrodom\u00c9sticos (al Por Menor)",
    "sg:phone":"+34 925 78 03 61",
    "sg:postcode":"45910",
    "sg:province":"Toledo",
    "wof:name":"Gonzalez Esteban Jose Carlos",
    "wof:placetype":"venue"
},
  "geometry": {"coordinates":[-4.4024786949,40.1670379639],"type":"Point"}
}