{
  "type": "Feature",
  "properties": {
    "iso:country":"ES",
    "sg:address":"Trino Uria Kalea, 4",
    "sg:city":"Azkoitia",
    "sg:classifiers":[
        {
            "category":"Taxi",
            "type":"Transportation"
        }
    ],
    "sg:phone":"+34 943 85 29 59",
    "sg:postcode":"20720",
    "sg:province":"Guip\u00f9zcoa",
    "wof:name":"Moreno Piris Severiano",
    "wof:placetype":"venue"
},
  "geometry": {"coordinates":[-2.3082070351,43.1786270142],"type":"Point"}
}