{
  "type": "Feature",
  "properties": {
    "addr:full":"Calle de Mayor, 8 Garrucha Almer\u00eda 04630",
    "addr:housenumber":"8",
    "addr:postcode":"04630",
    "addr:street":"Calle De Mayor;Almeri\u0301A",
    "iso:country":"ES",
    "sg:address":"Calle de Mayor, 8",
    "sg:city":"Garrucha",
    "sg:orig_category":"Agencias Y Agentes Comerciales, Representantes",
    "sg:phone":"+34 950 13 33 33",
    "sg:postcode":"04630",
    "sg:province":"Almer\u00eda",
    "wof:name":"Tev Gestores S.l.",
    "wof:placetype":"venue"
},
  "geometry": {"coordinates":[-1.8200889826,37.1865768433],"type":"Point"}
}