{
  "type": "Feature",
  "properties": {
    "addr:full":"Avda Generalitat Valenciana, 3 Catarroja Valencia 46470",
    "addr:housenumber":"3",
    "addr:postcode":"46470",
    "addr:street":"Avda Generalitat Valenciana",
    "iso:country":"ES",
    "sg:address":"Avda Generalitat Valenciana, 3",
    "sg:city":"Catarroja",
    "sg:orig_category":"Organizaciones Profesionales",
    "sg:phone":"+34 961 22 04 57",
    "sg:postcode":"46470",
    "sg:province":"Valencia",
    "wof:name":"Garces Juanes Susana",
    "wof:placetype":"venue"
},
  "geometry": {"coordinates":[-0.4055680037,39.4097976685],"type":"Point"}
}