{
  "type": "Feature",
  "properties": {
    "addr:full":"Calle de Mayor, 32 Reinosa Cantabria 39200",
    "addr:housenumber":"32",
    "addr:postcode":"39200",
    "addr:street":"Calle De Mayor",
    "iso:country":"ES",
    "sg:address":"Calle de Mayor, 32",
    "sg:city":"Reinosa",
    "sg:orig_category":"Carnicer\u00cdas, Carnicer\u00cdas",
    "sg:phone":"+34 942 75 16 97",
    "sg:postcode":"39200",
    "sg:province":"Cantabria",
    "wof:name":"Conde Gonzalez Jose Luis",
    "wof:placetype":"venue"
},
  "geometry": {"coordinates":[-4.1366062164,43.0013618469],"type":"Point"}
}