{
  "type": "Feature",
  "properties": {
    "iso:country":"ES",
    "sg:address":"Calle de Iglesia, 21",
    "sg:city":"Abades",
    "sg:orig_category":"Mec\u00c1nico Del Autom\u00d3vil",
    "sg:phone":"+34 921 49 50 83",
    "sg:postcode":"40141",
    "sg:province":"Segovia",
    "wof:name":"Frutos Arranz Jose Antonio De",
    "wof:placetype":"venue"
},
  "geometry": {"coordinates":[-4.2678389549,40.9162712097],"type":"Point"}
}