{
  "type": "Feature",
  "properties": {
    "iso:country":"ES",
    "sg:address":"Calle de Fundidores (de), 22",
    "sg:city":"Arroyomolinos",
    "sg:orig_category":"Arenas, Guijarros Y Granulados",
    "sg:phone":"+34 916 17 70 00",
    "sg:postcode":"28939",
    "sg:province":"Madrid",
    "wof:name":"Contenedores Belud S.l",
    "wof:placetype":"venue"
},
  "geometry": {"coordinates":[-3.9058790207,40.3006362915],"type":"Point"}
}