{
  "type": "Feature",
  "properties": {
    "iso:country":"ES",
    "sg:address":"Aoiz-agoitz Kalea, 6",
    "sg:city":"Iru\u00f1a",
    "sg:orig_category":"Abogados",
    "sg:phone":"+34 948 23 28 38",
    "sg:postcode":"31004",
    "sg:province":"Navarra",
    "wof:name":"Iraburu Elizondo Javier",
    "wof:placetype":"venue"
},
  "geometry": {"coordinates":[-1.6322449446,42.8101577759],"type":"Point"}
}