{
  "type": "Feature",
  "properties": {
    "addr:full":"Carrer de Girona, S/n Deltebre Tarragona 43580",
    "addr:housenumber":"s / n",
    "addr:postcode":"43580",
    "addr:street":"Carrer De Girona",
    "iso:country":"ES",
    "sg:address":"Carrer de Girona, S/n",
    "sg:city":"Deltebre",
    "sg:orig_category":"F\u00c1bricas De Ladrillo Y Tejas",
    "sg:phone":"+34 977 48 94 22",
    "sg:postcode":"43580",
    "sg:province":"Tarragona",
    "wof:name":"Ladrillos Deltebro S.l.",
    "wof:placetype":"venue"
},
  "geometry": {"coordinates":[0.721503973,40.7256851196],"type":"Point"}
}