{
  "type": "Feature",
  "properties": {
    "addr:full":"Calle de Francisco De Caceres, 1 Cueto Cantabria 39012",
    "addr:housenumber":"1",
    "addr:postcode":"39012",
    "addr:street":"Calle De Francisco De Caceres",
    "iso:country":"ES",
    "sg:address":"Calle de Francisco De Caceres, 1",
    "sg:city":"Cueto",
    "sg:orig_category":"Inmobiliaria (agencias)",
    "sg:phone":"+34 942 39 80 22",
    "sg:postcode":"39012",
    "sg:province":"Cantabria",
    "wof:name":"Gestioninmobiliaria Costadel Norte S.l.",
    "wof:placetype":"venue"
},
  "geometry": {"coordinates":[-3.7965888977,43.4784431458],"type":"Point"}
}