{
  "type": "Feature",
  "properties": {
    "iso:country":"ES",
    "sg:address":"Calle de Salvador Giner, 13",
    "sg:city":"Alfafar",
    "sg:orig_category":"Escayola Y Productos De Escayola (fabricaci\u00d3n, Al Por Mayor)",
    "sg:phone":"+34 963 75 12 31",
    "sg:postcode":"46910",
    "sg:province":"Valencia",
    "wof:name":"Logar De Yesos Y Escayolas S.l.",
    "wof:placetype":"venue"
},
  "geometry": {"coordinates":[-0.3876860142,39.4197425842],"type":"Point"}
}