{
  "type": "Feature",
  "properties": {
    "iso:country":"ES",
    "sg:address":"Calle de Ramon Y Cajal, 2",
    "sg:city":"Epila",
    "sg:orig_category":"Doctores En Medicina",
    "sg:phone":"+34 976 60 37 72",
    "sg:postcode":"50290",
    "sg:province":"Zaragoza",
    "wof:name":"Gabinete Medico Epila",
    "wof:placetype":"venue"
},
  "geometry": {"coordinates":[-1.2809710503,41.6003646851],"type":"Point"}
}