{
  "type": "Feature",
  "properties": {
    "iso:country":"ES",
    "sg:address":"Avda Sevilla (de), 69",
    "sg:city":"Chipiona",
    "sg:orig_category":"Frutas Y Legumbres Frescas (al Por Mayor)",
    "sg:phone":"+34 956 37 05 15",
    "sg:postcode":"11550",
    "sg:province":"C\u00e1diz",
    "wof:name":"San Jose Del Moral Jose Antonio",
    "wof:placetype":"venue"
},
  "geometry": {"coordinates":[-6.4387087822,36.7336082458],"type":"Point"}
}