{
  "type": "Feature",
  "properties": {
    "iso:country":"ES",
    "sg:address":"C/ Salut, 30",
    "sg:city":"Arenal",
    "sg:orig_category":"Ropa Para Se\u00d1oras (al Por Menor)",
    "sg:phone":"+34 971 44 29 05",
    "sg:postcode":"07600",
    "sg:province":"Islas Baleares",
    "wof:name":"Arrebola Lara Angela",
    "wof:placetype":"venue"
},
  "geometry": {"coordinates":[2.7522513866,39.5010871887],"type":"Point"}
}