{
  "type": "Feature",
  "properties": {
    "addr:full":"Partida Monte Molar, 46 Altea Alicante 03590",
    "addr:housenumber":"46",
    "addr:postcode":"03590",
    "addr:street":"Partida Monte Molar",
    "iso:country":"ES",
    "sg:address":"Partida Monte Molar, 46",
    "sg:city":"Altea",
    "sg:orig_category":"Molduras, Junquillos, Listones Y Molduras Perforadas",
    "sg:phone":"+34 966 88 29 53",
    "sg:postcode":"03590",
    "sg:province":"Alicante",
    "wof:name":"Chapman  Michael Anthony",
    "wof:placetype":"venue"
},
  "geometry": {"coordinates":[-0.0506840013,38.6008338928],"type":"Point"}
}