{
  "type": "Feature",
  "properties": {
    "addr:full":"Ramon Peredeta(pol Ind), 26 Catarroja Valencia 46470",
    "addr:housenumber":"26",
    "addr:postcode":"46470",
    "addr:street":"Ind",
    "iso:country":"ES",
    "sg:address":"Ramon Peredeta(pol Ind), 26",
    "sg:city":"Catarroja",
    "sg:orig_category":"Molduras, Junquillos, Listones Y Molduras Perforadas",
    "sg:phone":"+34 961 27 31 38",
    "sg:postcode":"46470",
    "sg:province":"Valencia",
    "wof:name":"Capricho Knack S.l.",
    "wof:placetype":"venue"
},
  "geometry": {"coordinates":[-0.4010620117,39.3999710083],"type":"Point"}
}