{
  "type": "Feature",
  "properties": {
    "iso:country":"ES",
    "sg:address":"Avda Beiramar, 45",
    "sg:city":"Vigo",
    "sg:orig_category":"Fabricaci\u00d3n, Reparaci\u00d3n Y Mantenimiento De Construcciones Navales Y Fluviales",
    "sg:phone":"+34 986 20 53 83",
    "sg:postcode":"36202",
    "sg:province":"Pontevedra",
    "wof:name":"Renavi Sociedad Cooperativa",
    "wof:placetype":"venue"
},
  "geometry": {"coordinates":[-8.7328033447,42.234539032],"type":"Point"}
}