{
  "type": "Feature",
  "properties": {
    "addr:full":"Avda Madrid, 116 Le\u00f3n Le\u00f3n 24005",
    "addr:housenumber":"116",
    "addr:postcode":"24005",
    "addr:street":"Avda Madrid",
    "iso:country":"ES",
    "sg:address":"Avda Madrid, 116",
    "sg:city":"Le\u00f3n",
    "sg:orig_category":"Asesor\u00cda Sobre Comunicaci\u00d3n De Empresas",
    "sg:phone":"+34 987 34 42 32",
    "sg:postcode":"24005",
    "sg:province":"Le\u00f3n",
    "wof:name":"Proyectos Asesoria Y Servicios, S.a.",
    "wof:placetype":"venue"
},
  "geometry": {"coordinates":[-5.5444822311,42.5770606995],"type":"Point"}
}