{
  "type": "Feature",
  "properties": {
    "iso:country":"ES",
    "sg:address":"Rond Alarcos, 15",
    "sg:city":"Ciudad Real",
    "sg:orig_category":"\u00d3ptica: Instrumentos (fabricaci\u00d3n)",
    "sg:phone":"+34 926 21 48 21",
    "sg:postcode":"13002",
    "sg:province":"Ciudad Real",
    "wof:name":"Sanchez Bastante Amador",
    "wof:placetype":"venue"
},
  "geometry": {"coordinates":[-3.9343121052,38.9830551147],"type":"Point"}
}