{
  "type": "Feature",
  "properties": {
    "addr:full":"Calle de Goya, 1 Estepona M\u00e1laga 29680",
    "addr:housenumber":"1",
    "addr:postcode":"29680",
    "addr:street":"Calle De Goya",
    "iso:country":"ES",
    "sg:address":"Calle de Goya, 1",
    "sg:city":"Estepona",
    "sg:orig_category":"Telas Y Sedas (al Por Menor)",
    "sg:phone":"+34 952 79 43 19",
    "sg:postcode":"29680",
    "sg:province":"M\u00e1laga",
    "wof:name":"Todo Tela S.l.",
    "wof:placetype":"venue"
},
  "geometry": {"coordinates":[-5.1450490952,36.4288101196],"type":"Point"}
}