{
  "type": "Feature",
  "properties": {
    "addr:full":"Calle de Rey Francisco, 3 Madrid Madrid 28008",
    "addr:housenumber":"3",
    "addr:postcode":"28008",
    "addr:street":"Calle De Rey Francisco",
    "iso:country":"ES",
    "sg:address":"Calle de Rey Francisco, 3",
    "sg:city":"Madrid",
    "sg:classifiers":[
        {
            "category":"Cinema",
            "subcategory":"Movie Theater",
            "type":"Entertainment"
        }
    ],
    "sg:phone":"+34 915 41 33 87",
    "sg:postcode":"28008",
    "sg:province":"Madrid",
    "sg:tags":[
        "salas",
        "de",
        "cine"
    ],
    "wof:name":"A Z Taller Digital S.l.",
    "wof:placetype":"venue"
},
  "geometry": {"coordinates":[-3.715045929,40.4278297424],"type":"Point"}
}