{
  "type": "Feature",
  "properties": {
    "iso:country":"ES",
    "sg:address":"Calle de Feijoo, 87",
    "sg:city":"Gijon",
    "sg:orig_category":"Agencias Y Asesores De Publicidad",
    "sg:phone":"+34 985 13 50 18",
    "sg:postcode":"33204",
    "sg:province":"Asturias",
    "wof:name":"Cabal Valdes Ana",
    "wof:placetype":"venue"
},
  "geometry": {"coordinates":[-5.647810936,43.5318145752],"type":"Point"}
}