{
  "type": "Feature",
  "properties": {
    "addr:full":"Poli Talluntxe / Talluntze Industrialdea, 4 Noain Navarra 31110",
    "addr:housenumber":"4",
    "addr:postcode":"31110",
    "addr:street":"Industrialdea",
    "iso:country":"ES",
    "sg:address":"Poli Talluntxe / Talluntze Industrialdea, 4",
    "sg:city":"Noain",
    "sg:orig_category":"Comercio De Piezas De Recambio Y De Accesorios De Veh\u00cdculos, Veh\u00cdculos Industriales",
    "sg:phone":"+34 948 31 65 65",
    "sg:postcode":"31110",
    "sg:province":"Navarra",
    "wof:name":"Zoel Mir S.l.",
    "wof:placetype":"venue"
},
  "geometry": {"coordinates":[-1.5935460329,42.7209968567],"type":"Point"}
}