{
  "type": "Feature",
  "properties": {
    "iso:country":"ES",
    "sg:address":"Calle de Huertas, S/n",
    "sg:city":"Marmolejo",
    "sg:orig_category":"Empresas De Carpinter\u00cda",
    "sg:phone":"+34 953 54 03 89",
    "sg:postcode":"23770",
    "sg:province":"Ja\u00e9n",
    "wof:name":"Arevalo Pastor Adriano",
    "wof:placetype":"venue"
},
  "geometry": {"coordinates":[-4.1725783348,38.0502853394],"type":"Point"}
}