{
  "type": "Feature",
  "properties": {
    "addr:full":"Avda Gaiarre Julian, 54 Bilbao Vizcaya 48004",
    "addr:housenumber":"54",
    "addr:postcode":"48004",
    "addr:street":"Avda Gaiarre Julian",
    "iso:country":"ES",
    "sg:address":"Avda Gaiarre Julian, 54",
    "sg:city":"Bilbao",
    "sg:orig_category":"Tintorer\u00cdas, Limpieza En Seco",
    "sg:phone":"+34 944 05 47 13",
    "sg:postcode":"48004",
    "sg:province":"Vizcaya",
    "wof:name":"Hidalgo Tamayo Jose Manuel (reparacion De Calzado Josema)",
    "wof:placetype":"venue"
},
  "geometry": {"coordinates":[-2.9009590149,43.2552680969],"type":"Point"}
}