{
  "type": "Feature",
  "properties": {
    "iso:country":"ES",
    "sg:address":"Pol. Malpica-alfinden, 9",
    "sg:city":"Puebla Alfinden",
    "sg:orig_category":"Mec\u00c1nico Del Autom\u00d3vil",
    "sg:phone":"+34 976 10 85 59",
    "sg:postcode":"50171",
    "sg:province":"Zaragoza",
    "wof:name":"Masip Del Cacho Miguel Angel",
    "wof:placetype":"venue"
},
  "geometry": {"coordinates":[-0.7531189919,41.6323547363],"type":"Point"}
}