{
  "type": "Feature",
  "properties": {
    "addr:full":"Calle de Camino Viejo De Leganes, 157 Madrid Madrid 28025",
    "addr:housenumber":"157",
    "addr:postcode":"28025",
    "addr:street":"Calle De Camino Viejo De Leganes",
    "iso:country":"ES",
    "sg:address":"Calle de Camino Viejo De Leganes, 157",
    "sg:city":"Madrid",
    "sg:orig_category":"Lencer\u00cda Femenina, Corseter\u00cda, Trajes De Ba\u00d1o (al Por Menor)",
    "sg:phone":"+34 915 25 11 38",
    "sg:postcode":"28025",
    "sg:province":"Madrid",
    "wof:name":"Garcia Alvarez Maria",
    "wof:placetype":"venue"
},
  "geometry": {"coordinates":[-3.7298173904,40.3827629089],"type":"Point"}
}