{
  "type": "Feature",
  "properties": {
    "addr:full":"Carrer de Catalans, 56 Cornella Llobregat Barcelona 08940",
    "addr:housenumber":"56",
    "addr:postcode":"08940",
    "addr:street":"Carrer De Catalans",
    "iso:country":"ES",
    "sg:address":"Carrer de Catalans, 56",
    "sg:city":"Cornella Llobregat",
    "sg:orig_category":"Comit\u00c9s De Organizaci\u00d3n De Exposiciones, Ferias, Salones",
    "sg:phone":"+34 933 75 14 64",
    "sg:postcode":"08940",
    "sg:province":"Barcelona",
    "wof:name":"Expo Arte Y Cultura S.l.",
    "wof:placetype":"venue"
},
  "geometry": {"coordinates":[2.0789270401,41.3629226685],"type":"Point"}
}