{
  "type": "Feature",
  "properties": {
    "addr:full":"Calle de Cervantes, 17 Altorricon Huesca 22540",
    "addr:housenumber":"17",
    "addr:postcode":"22540",
    "addr:street":"Calle De Cervantes",
    "iso:country":"ES",
    "sg:address":"Calle de Cervantes, 17",
    "sg:city":"Altorricon",
    "sg:orig_category":"Promotores Constructores",
    "sg:phone":"+34 974 42 53 94",
    "sg:postcode":"22540",
    "sg:province":"Huesca",
    "wof:name":"Construcciones Gabas Blanc S.l.",
    "wof:placetype":"venue"
},
  "geometry": {"coordinates":[0.4141278863,41.8027954102],"type":"Point"}
}