{
  "type": "Feature",
  "properties": {
    "iso:country":"ES",
    "sg:address":"Calle de Casimiro, 12",
    "sg:city":"Almeria",
    "sg:orig_category":"Empresas De Carpinter\u00cda De Madera",
    "sg:phone":"+34 950 14 30 85",
    "sg:postcode":"04009",
    "sg:province":"Almer\u00eda",
    "wof:name":"Asensio Camacho Manuel",
    "wof:placetype":"venue"
},
  "geometry": {"coordinates":[-2.4355537891,36.8488731384],"type":"Point"}
}