{
  "type": "Feature",
  "properties": {
    "addr:full":"Pg Alacant (d'), 43 Gata Gorgos Alicante 03740",
    "addr:housenumber":"43",
    "addr:postcode":"03740",
    "addr:street":"Alacant;'",
    "iso:country":"ES",
    "sg:address":"Pg Alacant (d'), 43",
    "sg:city":"Gata Gorgos",
    "sg:orig_category":"Animales (al Por Menor)",
    "sg:phone":"+34 965 75 70 75",
    "sg:postcode":"03740",
    "sg:province":"Alicante",
    "wof:name":"Ninfa S.c",
    "wof:placetype":"venue"
},
  "geometry": {"coordinates":[0.0851679966,38.7773132324],"type":"Point"}
}