{
  "type": "Feature",
  "properties": {
    "iso:country":"ES",
    "sg:address":"Calle de Tomas Heredia, 19",
    "sg:city":"Malaga",
    "sg:orig_category":"Alumbrados",
    "sg:phone":"+34 952 22 44 57",
    "sg:postcode":"29001",
    "sg:province":"M\u00e1laga",
    "wof:name":"Maybe Iluminacion S.l.",
    "wof:placetype":"venue"
},
  "geometry": {"coordinates":[-4.4227638245,36.7157173157],"type":"Point"}
}