{
  "type": "Feature",
  "properties": {
    "iso:country":"ES",
    "sg:address":"Calle de Determinacion, 2",
    "sg:city":"Malaga",
    "sg:orig_category":"Art\u00cdculos De Decoraci\u00d3n",
    "sg:phone":"+34 952 43 90 00",
    "sg:postcode":"29190",
    "sg:province":"M\u00e1laga",
    "wof:name":"Infantes Cortes Antonia",
    "wof:placetype":"venue"
},
  "geometry": {"coordinates":[-4.482729435,36.7444915771],"type":"Point"}
}