{
  "type": "Feature",
  "properties": {
    "addr:full":"Pase Costa De La Luz, 59 Chipiona C\u00e1diz 11550",
    "addr:housenumber":"59",
    "addr:postcode":"11550",
    "addr:street":"Costa;La Luz",
    "iso:country":"ES",
    "sg:address":"Pase Costa De La Luz, 59",
    "sg:city":"Chipiona",
    "sg:orig_category":"Laboratorios Farmac\u00c9uticos",
    "sg:phone":"+34 956 37 08 77",
    "sg:postcode":"11550",
    "sg:province":"C\u00e1diz",
    "wof:name":"Fernandez Rodriguez Eduardo",
    "wof:placetype":"venue"
},
  "geometry": {"coordinates":[-6.43998909,36.7334709167],"type":"Point"}
}