{
  "type": "Feature",
  "properties": {
    "iso:country":"ES",
    "sg:address":"Carrer de Llibertat, 64",
    "sg:city":"Ametlla Mar",
    "sg:orig_category":"Imprenta",
    "sg:phone":"+34 977 45 67 93",
    "sg:postcode":"43860",
    "sg:province":"Tarragona",
    "wof:name":"Grafica Daurada S.l.",
    "wof:placetype":"venue"
},
  "geometry": {"coordinates":[0.8028810024,40.8855476379],"type":"Point"}
}