{
  "type": "Feature",
  "properties": {
    "iso:country":"ES",
    "sg:address":"Calle de Mejico, 33",
    "sg:city":"Guadalajara",
    "sg:orig_category":"Empresas De Carpinter\u00cda Met\u00c1lica",
    "sg:phone":"+34 949 20 73 00",
    "sg:postcode":"19004",
    "sg:province":"Guadalajara",
    "wof:name":"Carpinteria De Aluminio Villaverde C.b.",
    "wof:placetype":"venue"
},
  "geometry": {"coordinates":[-3.1888930798,40.6283302307],"type":"Point"}
}