{
  "type": "Feature",
  "properties": {
    "addr:full":"C/ Luis Llorente, 5 Elche Alicante 03201",
    "addr:housenumber":"5",
    "addr:postcode":"03201",
    "addr:street":"C / Luis Llorente",
    "iso:country":"ES",
    "sg:address":"C/ Luis Llorente, 5",
    "sg:city":"Elche",
    "sg:orig_category":"Peluqueros: De Se\u00d1oras",
    "sg:phone":"+34 965 43 27 93",
    "sg:postcode":"03201",
    "sg:province":"Alicante",
    "wof:name":"Martinez Beltran Manuela",
    "wof:placetype":"venue"
},
  "geometry": {"coordinates":[-0.7056620121,38.2681694031],"type":"Point"}
}