{
  "type": "Feature",
  "properties": {
    "iso:country":"ES",
    "sg:address":"Calle de Sancho El Sabio, 21",
    "sg:city":"Vitoria-gasteiz",
    "sg:orig_category":"Quincaller\u00cda (al Por Menor)",
    "sg:phone":"+34 945 22 37 43",
    "sg:postcode":"01008",
    "sg:province":"\u00c1lava",
    "wof:name":"Ferreteria Aguirre, S.l",
    "wof:placetype":"venue"
},
  "geometry": {"coordinates":[-2.6804609299,42.8485908508],"type":"Point"}
}