{
  "type": "Feature",
  "properties": {
    "addr:full":"Calle de Rio Taju\u00d1a, 8 Arganda Madrid 28500",
    "addr:housenumber":"8",
    "addr:postcode":"28500",
    "addr:street":"Calle De Rio Tajun\u0303A",
    "iso:country":"ES",
    "sg:address":"Calle de Rio Taju\u00d1a, 8",
    "sg:city":"Arganda",
    "sg:orig_category":"Imprenta",
    "sg:phone":"+34 918 71 78 38",
    "sg:postcode":"28500",
    "sg:province":"Madrid",
    "wof:name":"Guerra Tizon Jose Fernando",
    "wof:placetype":"venue"
},
  "geometry": {"coordinates":[-3.457627058,40.3006362915],"type":"Point"}
}