{
  "type": "Feature",
  "properties": {
    "addr:full":"Calle de Antonio Machado, 20 Alcolea Del Rio Sevilla 41449",
    "addr:housenumber":"20",
    "addr:postcode":"41449",
    "addr:street":"Calle De Antonio Machado",
    "iso:country":"ES",
    "sg:address":"Calle de Antonio Machado, 20",
    "sg:city":"Alcolea Del Rio",
    "sg:orig_category":"Agricultura: Abastecimiento Y Cosechado (negocio)",
    "sg:phone":"+34 955 64 42 64",
    "sg:postcode":"41449",
    "sg:province":"Sevilla",
    "wof:name":"Cruz Barrera Manuel De La",
    "wof:placetype":"venue"
},
  "geometry": {"coordinates":[-5.6676692963,37.6145629883],"type":"Point"}
}