{
  "type": "Feature",
  "properties": {
    "iso:country":"ES",
    "sg:address":"A Igrexa, 68",
    "sg:city":"Chapela",
    "sg:orig_category":"Molduras, Junquillos, Listones Y Molduras Perforadas",
    "sg:phone":"+34 986 45 16 34",
    "sg:postcode":"36320",
    "sg:province":"Pontevedra",
    "wof:name":"Moure Vazquez Aurelio",
    "wof:placetype":"venue"
},
  "geometry": {"coordinates":[-8.6428003311,42.4304618835],"type":"Point"}
}