{
  "type": "Feature",
  "properties": {
    "addr:full":"Calle de Ganado, S/n Puerto De Santa Maria C\u00e1diz 11500",
    "addr:housenumber":"s / n",
    "addr:postcode":"11500",
    "addr:street":"Calle De Ganado;Ca\u0301Diz",
    "iso:country":"ES",
    "sg:address":"Calle de Ganado, S/n",
    "sg:city":"Puerto De Santa Maria",
    "sg:orig_category":"Carnicer\u00cdas, Carnicer\u00cdas",
    "sg:phone":"+34 956 87 39 46",
    "sg:postcode":"11500",
    "sg:province":"C\u00e1diz",
    "wof:name":"Gonzalez Ortega Juan Diego",
    "wof:placetype":"venue"
},
  "geometry": {"coordinates":[-6.2273111343,36.6012573242],"type":"Point"}
}