{
  "type": "Feature",
  "properties": {
    "iso:country":"ES",
    "sg:address":"Calle de Doctor Fleming, 31",
    "sg:city":"Carrion De Los Cespedes",
    "sg:orig_category":"Cristaler\u00cdas",
    "sg:phone":"+34 954 75 51 34",
    "sg:postcode":"41820",
    "sg:province":"Sevilla",
    "wof:name":"Rodriguez Garcia Jose",
    "wof:placetype":"venue"
},
  "geometry": {"coordinates":[-6.328209877,37.3656692505],"type":"Point"}
}