{
  "type": "Feature",
  "properties": {
    "addr:full":"Calle de Sol, 12 Fontellas Navarra 31512",
    "addr:housenumber":"12",
    "addr:postcode":"31512",
    "addr:street":"Calle De Sol",
    "iso:country":"ES",
    "sg:address":"Calle de Sol, 12",
    "sg:city":"Fontellas",
    "sg:orig_category":"Granos Y Semillas (producci\u00d3n, Al Por Mayor)",
    "sg:phone":"+34 948 82 52 59",
    "sg:postcode":"31512",
    "sg:province":"Navarra",
    "sg:website":"www.zulueta.com",
    "wof:name":"Zulueta Corporacion Para La Naturaleza S.a.",
    "wof:placetype":"venue"
},
  "geometry": {"coordinates":[-1.5760840178,42.0264816284],"type":"Point"}
}