{
  "type": "Feature",
  "properties": {
    "iso:country":"ES",
    "sg:address":"Canyes, 1",
    "sg:city":"Beniparrell",
    "sg:orig_category":"Fabricaci\u00d3n, Venta, Instalaci\u00d3n De R\u00d3tulos, De R\u00d3tulos Luminosos",
    "sg:phone":"+34 961 21 09 14",
    "sg:postcode":"46469",
    "sg:province":"Valencia",
    "wof:name":"Roura & Cevasa S.a.",
    "wof:placetype":"venue"
},
  "geometry": {"coordinates":[-0.4015760124,39.3840637207],"type":"Point"}
}