{
  "type": "Feature",
  "properties": {
    "iso:country":"ES",
    "sg:address":"Carrer de Josep Torras I Bages, 1",
    "sg:city":"Granollers",
    "sg:orig_category":"Buzones De Correos",
    "sg:phone":"+34 938 60 65 33",
    "sg:postcode":"08401",
    "sg:province":"Barcelona",
    "sg:website":"www.arfe.com",
    "wof:name":"Articulos De Ferreteria S.a.",
    "wof:placetype":"venue"
},
  "geometry": {"coordinates":[2.2802755833,41.5911216736],"type":"Point"}
}