{
  "type": "Feature",
  "properties": {
    "iso:country":"ES",
    "sg:address":"Ctra Jerez-cartagena, Km. 0076,0",
    "sg:city":"Algodonales",
    "sg:orig_category":"Mec\u00c1nico Del Autom\u00d3vil",
    "sg:phone":"+34 956 23 40 37",
    "sg:postcode":"11680",
    "sg:province":"C\u00e1diz",
    "wof:name":"Taller Mecanico Sierra De Lijar",
    "wof:placetype":"venue"
},
  "geometry": {"coordinates":[-5.405064106,36.8808784485],"type":"Point"}
}