{
  "type": "Feature",
  "properties": {
    "iso:country":"ES",
    "sg:address":"Calle de Puerto De Balbaran, 21",
    "sg:city":"Madrid",
    "sg:orig_category":"Empresas De Carpinter\u00cda De Madera",
    "sg:phone":"+34 914 78 50 02",
    "sg:postcode":"28053",
    "sg:province":"Madrid",
    "wof:name":"Rodriguez Delgado Jose",
    "wof:placetype":"venue"
},
  "geometry": {"coordinates":[-3.6692450047,40.3839874268],"type":"Point"}
}