{
  "type": "Feature",
  "properties": {
    "iso:country":"ES",
    "sg:address":"Calle de Nuestra Se\u00d1ora De Guadalupe, 66",
    "sg:city":"Oliva Frontera",
    "sg:orig_category":"Molduras, Junquillos, Listones Y Molduras Perforadas",
    "sg:phone":"+34 924 74 03 10",
    "sg:postcode":"06120",
    "sg:province":"Badajoz",
    "wof:name":"Cuecas Gamero Rufino",
    "wof:placetype":"venue"
},
  "geometry": {"coordinates":[-6.9170789719,38.273853302],"type":"Point"}
}