{
  "type": "Feature",
  "properties": {
    "iso:country":"ES",
    "sg:address":"Rond Torneros (de Los), 13",
    "sg:city":"Utrera",
    "sg:orig_category":"Aluminio Y Aleaciones (producci\u00d3n, Transformaci\u00d3n, Negocio)",
    "sg:phone":"+34 954 87 30 09",
    "sg:postcode":"41710",
    "sg:province":"Sevilla",
    "wof:name":"Aluminios De Jaen S. A.",
    "wof:placetype":"venue"
},
  "geometry": {"coordinates":[-5.7932009697,37.0917663574],"type":"Point"}
}