{
  "type": "Feature",
  "properties": {
    "iso:country":"ES",
    "sg:address":"Calle de Puig De Santa Maria, 10",
    "sg:city":"Sagunt",
    "sg:orig_category":"Bebidas",
    "sg:phone":"+34 962 65 06 67",
    "sg:postcode":"46500",
    "sg:province":"Valencia",
    "wof:name":"Distribucion De Bebidas S.l.",
    "wof:placetype":"venue"
},
  "geometry": {"coordinates":[-0.2685739994,39.6762924194],"type":"Point"}
}