{
  "type": "Feature",
  "properties": {
    "iso:country":"ES",
    "sg:address":"Avda Madrid, 212",
    "sg:city":"Zaragoza",
    "sg:orig_category":"Pintura, Barniz, Productos Asimilables (fabricaci\u00d3n, Al Por Mayor)",
    "sg:phone":"+34 976 32 15 82",
    "sg:postcode":"50017",
    "sg:province":"Zaragoza",
    "wof:name":"Hipopotamo Europa S.l.",
    "wof:placetype":"venue"
},
  "geometry": {"coordinates":[-0.9165877104,41.6507606506],"type":"Point"}
}