{
  "type": "Feature",
  "properties": {
    "addr:full":"Calle de Serrablo (de), 21 Sabi\u00f1anigo Huesca 22600",
    "addr:housenumber":"21",
    "addr:postcode":"22600",
    "addr:street":"Calle De Serrablo De",
    "iso:country":"ES",
    "sg:address":"Calle de Serrablo (de), 21",
    "sg:city":"Sabi\u00f1anigo",
    "sg:orig_category":"Albergues",
    "sg:phone":"+34 974 48 00 04",
    "sg:postcode":"22600",
    "sg:province":"Huesca",
    "wof:name":"Laguarta Rapun Jose Alfredo",
    "wof:placetype":"venue"
},
  "geometry": {"coordinates":[-0.370133996,42.5191650391],"type":"Point"}
}