{
  "type": "Feature",
  "properties": {
    "iso:country":"ES",
    "sg:address":"Av Port De Caro (del), 26",
    "sg:city":"Roquetes",
    "sg:orig_category":"Peluqueros: De Se\u00d1oras",
    "sg:phone":"+34 977 50 19 57",
    "sg:postcode":"43520",
    "sg:province":"Tarragona",
    "wof:name":"Ginobart Morales Maria Teresa",
    "wof:placetype":"venue"
},
  "geometry": {"coordinates":[0.5066800117,40.8186416626],"type":"Point"}
}