{
  "type": "Feature",
  "properties": {
    "iso:country":"ES",
    "sg:address":"Poli Poligon 06, S/n",
    "sg:city":"Picassent",
    "sg:orig_category":"Mudanzas",
    "sg:phone":"+34 961 24 27 55",
    "sg:postcode":"46220",
    "sg:province":"Valencia",
    "wof:name":"Transportes Y Mudanzas La Albufera Sociedad Cooperativa Valenciana",
    "wof:placetype":"venue"
},
  "geometry": {"coordinates":[-0.4595290124,39.3631401062],"type":"Point"}
}