{
  "type": "Feature",
  "properties": {
    "iso:country":"ES",
    "sg:address":"Calle de Vital Aza, 45",
    "sg:city":"Madrid",
    "sg:orig_category":"Molduras, Junquillos, Listones Y Molduras Perforadas",
    "sg:phone":"+34 914 08 66 96",
    "sg:postcode":"28017",
    "sg:province":"Madrid",
    "wof:name":"Rosado Ramirez Andres Maria",
    "wof:placetype":"venue"
},
  "geometry": {"coordinates":[-3.6411850452,40.4324874878],"type":"Point"}
}