{
  "type": "Feature",
  "properties": {
    "addr:full":"Calle de Real De Gandia, 1 Valencia Valencia 46020",
    "addr:housenumber":"1",
    "addr:postcode":"46020",
    "addr:street":"Calle De Real De Gandia",
    "iso:country":"ES",
    "sg:address":"Calle de Real De Gandia, 1",
    "sg:city":"Valencia",
    "sg:orig_category":"Asesor\u00cda Fiscal Y Jur\u00cddica",
    "sg:phone":"+34 963 93 50 47",
    "sg:postcode":"46020",
    "sg:province":"Valencia",
    "wof:name":"Servicios Interempresariales S.l.",
    "wof:placetype":"venue"
},
  "geometry": {"coordinates":[-0.3549169898,39.4847145081],"type":"Point"}
}