{
  "type": "Feature",
  "properties": {
    "addr:full":"Cmno Zubiberri De, 31 Donostia-san Sebastian Guip\u00f9zcoa 20018",
    "addr:housenumber":"31",
    "addr:postcode":"20018",
    "addr:street":"Cmno Zubiberri De",
    "iso:country":"ES",
    "sg:address":"Cmno Zubiberri De, 31",
    "sg:city":"Donostia-san Sebastian",
    "sg:orig_category":"Ense\u00d1anza, Formaci\u00d3n Profesional: Aprendizaje",
    "sg:phone":"+34 943 42 66 10",
    "sg:postcode":"20018",
    "sg:province":"Guip\u00f9zcoa",
    "wof:name":"Instituto Vasco De Estudios Investigacion S.a.",
    "wof:placetype":"venue"
},
  "geometry": {"coordinates":[-2.0022208691,43.2977905273],"type":"Point"}
}