{
  "type": "Feature",
  "properties": {
    "iso:country":"ES",
    "sg:address":"Carrer de Mas De L'abat (del), 38",
    "sg:city":"Vila-seca",
    "sg:orig_category":"Vinos (agentes)",
    "sg:phone":"+34 977 39 58 19",
    "sg:postcode":"43480",
    "sg:province":"Tarragona",
    "wof:name":"Diene Tarragona S.l.",
    "wof:placetype":"venue"
},
  "geometry": {"coordinates":[1.1487300396,41.1160316467],"type":"Point"}
}