{
  "type": "Feature",
  "properties": {
    "iso:country":"ES",
    "sg:address":"Pase Delicias, 31",
    "sg:city":"Madrid",
    "sg:orig_category":"Asesor\u00cda Sobre Comunicaci\u00d3n De Empresas",
    "sg:phone":"+34 914 68 40 05",
    "sg:postcode":"28045",
    "sg:province":"Madrid",
    "wof:name":"7 Gg Consultoria S.l.",
    "wof:placetype":"venue"
},
  "geometry": {"coordinates":[-3.693542,40.404213],"type":"Point"}
}