{
  "type": "Feature",
  "properties": {
    "iso:country":"ES",
    "sg:address":"Carr Costera (de La), 26",
    "sg:city":"Alaquas",
    "sg:orig_category":"Instalaci\u00d3n De Calefacci\u00d3n Industrial",
    "sg:phone":"+34 961 50 93 11",
    "sg:postcode":"46970",
    "sg:province":"Valencia",
    "sg:website":"www.gilabertmiro.com",
    "wof:name":"Gilabert Miro S.a.",
    "wof:placetype":"venue"
},
  "geometry": {"coordinates":[-0.4578439891,39.4546356201],"type":"Point"}
}