{
  "type": "Feature",
  "properties": {
    "iso:country":"ES",
    "sg:address":"Rbla Catalunya, 14",
    "sg:city":"Barcelona",
    "sg:orig_category":"Creaci\u00d3n De Sitios, Hosting Internet",
    "sg:phone":"+34 933 17 22 61",
    "sg:postcode":"08007",
    "sg:province":"Barcelona",
    "sg:website":"www.comunicaciodigital.com",
    "wof:name":"Comunicacio Digital Equip De Profesionals S.l.",
    "wof:placetype":"venue"
},
  "geometry": {"coordinates":[2.1675560474,41.3881721497],"type":"Point"}
}