{
  "type": "Feature",
  "properties": {
    "addr:full":"Calle de Ribera De Las Almadrabillas, 1 Almeria Almer\u00eda 04004",
    "addr:housenumber":"1",
    "addr:postcode":"04004",
    "addr:street":"Calle De Ribera De Las Almadrabillas",
    "iso:country":"ES",
    "sg:address":"Calle de Ribera De Las Almadrabillas, 1",
    "sg:city":"Almeria",
    "sg:orig_category":"Cl\u00cdnicas Dentales",
    "sg:phone":"+34 950 26 45 13",
    "sg:postcode":"04004",
    "sg:province":"Almer\u00eda",
    "wof:name":"Velasco Vivancos Nisa",
    "wof:placetype":"venue"
},
  "geometry": {"coordinates":[-2.46302104,36.8335266113],"type":"Point"}
}