{
  "type": "Feature",
  "properties": {
    "addr:full":"Carrer de Pare Palau (del), 6 Tarragona Tarragona 43001",
    "addr:housenumber":"6",
    "addr:postcode":"43001",
    "addr:street":"Carrer De Pare Palau Del",
    "iso:country":"ES",
    "sg:address":"Carrer de Pare Palau (del), 6",
    "sg:city":"Tarragona",
    "sg:orig_category":"Agencias Y Asesores De Publicidad",
    "sg:phone":"+34 977 24 07 46",
    "sg:postcode":"43001",
    "sg:province":"Tarragona",
    "wof:name":"Pastor Publicitat S.l.",
    "wof:placetype":"venue"
},
  "geometry": {"coordinates":[1.2470020056,41.1175613403],"type":"Point"}
}