{
  "type": "Feature",
  "properties": {
    "addr:full":"Rua Carlos Iii, 52 Becerrea Lugo 27640",
    "addr:housenumber":"52",
    "addr:postcode":"27640",
    "addr:street":"Rua Carlos Iii",
    "iso:country":"ES",
    "sg:address":"Rua Carlos Iii, 52",
    "sg:city":"Becerrea",
    "sg:orig_category":"Alquiler De V\u00cddeo",
    "sg:phone":"+34 982 36 00 66",
    "sg:postcode":"27640",
    "sg:province":"Lugo",
    "wof:name":"Videociber El Recreo S.l.",
    "wof:placetype":"venue"
},
  "geometry": {"coordinates":[-7.1613059044,42.8526229858],"type":"Point"}
}