{
  "type": "Feature",
  "properties": {
    "iso:country":"ES",
    "sg:address":"Apto Residencia Campus Riu Sec (uji), 5",
    "sg:city":"Castellon De La Plana",
    "sg:orig_category":"Bancos",
    "sg:phone":"+34 964 73 08 37",
    "sg:postcode":"12004",
    "sg:province":"Castell\u00f3n",
    "wof:name":"Auna Telecomunicaciones S.a.u.",
    "wof:placetype":"venue"
},
  "geometry": {"coordinates":[0.0330299996,40.0113639832],"type":"Point"}
}