{
  "type": "Feature",
  "properties": {
    "iso:country":"ES",
    "sg:address":"Calle de Ramon Y Cajal, 40",
    "sg:city":"Coru\u00d1a",
    "sg:orig_category":"M\u00c9dicos: Ortopedia Dento",
    "sg:phone":"+34 981 13 63 55",
    "sg:postcode":"15006",
    "sg:province":"La Coru\u00f1a",
    "sg:website":"www.audifon.es",
    "wof:name":"Audifon S.a.",
    "wof:placetype":"venue"
},
  "geometry": {"coordinates":[-8.403465271,43.354927063],"type":"Point"}
}