{
  "type": "Feature",
  "properties": {
    "iso:country":"ES",
    "sg:address":"Carr Gabriel Roca, S/n",
    "sg:city":"Colonia S. Jordi",
    "sg:orig_category":"Distribuci\u00d3n De Petr\u00d3leo Y Derivados",
    "sg:phone":"+34 971 65 50 66",
    "sg:postcode":"07638",
    "sg:province":"Islas Baleares",
    "wof:name":"Colonia De San Jordi Estacion De Servicio S.l.",
    "wof:placetype":"venue"
},
  "geometry": {"coordinates":[2.9928250313,39.3186759949],"type":"Point"}
}