{
  "type": "Feature",
  "properties": {
    "addr:full":"Unica, S/n Parzan Huesca 22365",
    "addr:postcode":"22365",
    "addr:street":"S / N Parzan",
    "iso:country":"ES",
    "sg:address":"Unica, S/n",
    "sg:city":"Parzan",
    "sg:orig_category":"Refiner\u00cdas De Petr\u00d3leo",
    "sg:phone":"+34 974 50 10 83",
    "sg:postcode":"22365",
    "sg:province":"Huesca",
    "wof:name":"Jose Luis Vidalle Y Cia S.r.c.",
    "wof:placetype":"venue"
},
  "geometry": {"coordinates":[0.1910520047,42.6644706726],"type":"Point"}
}