{
  "type": "Feature",
  "properties": {
    "addr:full":"Calle de Santiago, 2 Castellar Ja\u00e9n 23260",
    "addr:housenumber":"2",
    "addr:postcode":"23260",
    "addr:street":"Calle De Santiago",
    "iso:country":"ES",
    "sg:address":"Calle de Santiago, 2",
    "sg:city":"Castellar",
    "sg:orig_category":"Fotograf\u00cda Art\u00cdstica Y Retratos",
    "sg:phone":"+34 953 46 02 50",
    "sg:postcode":"23260",
    "sg:province":"Ja\u00e9n",
    "wof:name":"Lumbreras Gilabert Anabel",
    "wof:placetype":"venue"
},
  "geometry": {"coordinates":[-3.1324319839,38.2551879883],"type":"Point"}
}