{
  "type": "Feature",
  "properties": {
    "addr:full":"Ctra Dolores, 65 Almoradi Alicante 03160",
    "addr:housenumber":"65",
    "addr:postcode":"03160",
    "addr:street":"Ctra Dolores",
    "iso:country":"ES",
    "sg:address":"Ctra Dolores, 65",
    "sg:city":"Almoradi",
    "sg:orig_category":"Electrodom\u00c9sticos (fabricaci\u00d3n, Al Por Mayor)",
    "sg:phone":"+34 965 70 24 30",
    "sg:postcode":"03160",
    "sg:province":"Alicante",
    "wof:name":"Megahogar S.l.",
    "wof:placetype":"venue"
},
  "geometry": {"coordinates":[-0.7921590209,38.1102905273],"type":"Point"}
}