{
  "type": "Feature",
  "properties": {
    "iso:country":"ES",
    "sg:address":"Calle de Madrid, S/n",
    "sg:city":"Puente-genil",
    "sg:orig_category":"Mec\u00c1nico Del Autom\u00d3vil",
    "sg:phone":"+34 957 60 56 16",
    "sg:postcode":"14500",
    "sg:province":"C\u00f3rdoba",
    "wof:name":"Aviles Moreno Francisco",
    "wof:placetype":"venue"
},
  "geometry": {"coordinates":[-4.7570018768,37.3959197998],"type":"Point"}
}