{
  "type": "Feature",
  "properties": {
    "addr:full":"Ctra. Andratx, 24 Palmanova Islas Baleares 07181",
    "addr:housenumber":"24",
    "addr:postcode":"07181",
    "addr:street":"Ctra. Andratx",
    "iso:country":"ES",
    "sg:address":"Ctra. Andratx, 24",
    "sg:city":"Palmanova",
    "sg:orig_category":"Agencias De Viajes",
    "sg:phone":"+34 971 68 22 54",
    "sg:postcode":"07181",
    "sg:province":"Islas Baleares",
    "wof:name":"Viajes Costa Calvia S.l.",
    "wof:placetype":"venue"
},
  "geometry": {"coordinates":[2.5458359718,39.5282707214],"type":"Point"}
}