{
  "type": "Feature",
  "properties": {
    "iso:country":"ES",
    "sg:address":"Ctra Ezcaray, S/n",
    "sg:city":"Santo Domingo De La Calzada",
    "sg:orig_category":"Ba\u00d1os Y Duchas P\u00dablicos",
    "sg:phone":"+34 941 34 29 73",
    "sg:postcode":"26250",
    "sg:province":"La Rioja",
    "wof:name":"Ayuntamiento De Santo Domingo De La Calzada",
    "wof:placetype":"venue"
},
  "geometry": {"coordinates":[-2.9541339874,42.4394760132],"type":"Point"}
}