{
  "type": "Feature",
  "properties": {
    "addr:full":"Calle de Gamazo, 26 Medina Campo Valladolid 47400",
    "addr:housenumber":"26",
    "addr:postcode":"47400",
    "addr:street":"Calle De Gamazo",
    "iso:country":"ES",
    "sg:address":"Calle de Gamazo, 26",
    "sg:city":"Medina Campo",
    "sg:orig_category":"Agencias De Viajes",
    "sg:phone":"+34 983 80 07 65",
    "sg:postcode":"47400",
    "sg:province":"Valladolid",
    "wof:name":"Martin Rochas Natalia",
    "wof:placetype":"venue"
},
  "geometry": {"coordinates":[-4.9168539047,41.306930542],"type":"Point"}
}