{
  "type": "Feature",
  "properties": {
    "addr:full":"Ctra Paradas-arahal, Km. 0000,4 Paradas Sevilla 41610",
    "addr:postcode":"41610",
    "addr:street":"Ctra Paradas-Arahal Km. 0000,4",
    "iso:country":"ES",
    "sg:address":"Ctra Paradas-arahal, Km. 0000,4",
    "sg:city":"Paradas",
    "sg:orig_category":"Bares, Piano",
    "sg:phone":"+34 954 84 91 96",
    "sg:postcode":"41610",
    "sg:province":"Sevilla",
    "wof:name":"Hermanos Carrion Vargas C.b.",
    "wof:placetype":"venue"
},
  "geometry": {"coordinates":[-5.4962830544,37.290561676],"type":"Point"}
}