{
  "type": "Feature",
  "properties": {
    "addr:full":"Praz Maior, 20 Lugo Lugo 27001",
    "addr:housenumber":"20",
    "addr:postcode":"27001",
    "addr:street":"Praz Maior",
    "iso:country":"ES",
    "sg:address":"Praz Maior, 20",
    "sg:city":"Lugo",
    "sg:orig_category":"Panader\u00cdas, Panader\u00cdas",
    "sg:phone":"+34 982 23 15 16",
    "sg:postcode":"27001",
    "sg:province":"Lugo",
    "wof:name":"Lopez Fernandez Manuel",
    "wof:placetype":"venue"
},
  "geometry": {"coordinates":[-7.5570030212,43.0092086792],"type":"Point"}
}