{
  "type": "Feature",
  "properties": {
    "iso:country":"ES",
    "sg:address":"Carr Sant Lluc, 51",
    "sg:city":"Badalona",
    "sg:orig_category":"Rectificaci\u00d3n, Mecanizado, Fresado",
    "sg:phone":"+34 934 60 74 07",
    "sg:postcode":"08918",
    "sg:province":"Barcelona",
    "wof:name":"Mecanizados Kaikor S.l.",
    "wof:placetype":"venue"
},
  "geometry": {"coordinates":[2.234787941,41.4354553223],"type":"Point"}
}