{
  "type": "Feature",
  "properties": {
    "iso:country":"ES",
    "sg:address":"Calle de Fernandez De La Hoz, 80",
    "sg:city":"Madrid",
    "sg:orig_category":"Abogados",
    "sg:phone":"+34 915 54 00 84",
    "sg:postcode":"28003",
    "sg:province":"Madrid",
    "wof:name":"Herreros Carles Cecilio Antonio",
    "wof:placetype":"venue"
},
  "geometry": {"coordinates":[-3.6941699982,40.4406547546],"type":"Point"}
}