{
  "type": "Feature",
  "properties": {
    "iso:country":"ES",
    "sg:address":"Calle de San Pablo, 9",
    "sg:city":"Rozas De Madrid",
    "sg:orig_category":"Arquitectos",
    "sg:phone":"+34 916 37 28 67",
    "sg:postcode":"28230",
    "sg:province":"Madrid",
    "wof:name":"Baleztena Abarrategui Carlos",
    "wof:placetype":"venue"
},
  "geometry": {"coordinates":[-3.8608791828,40.4928817749],"type":"Point"}
}