{
  "type": "Feature",
  "properties": {
    "addr:full":"Trva San Mateo, 10 Madrid Madrid 28004",
    "addr:housenumber":"10",
    "addr:postcode":"madrid;28004",
    "addr:street":"Trva San Mateo",
    "iso:country":"ES",
    "sg:address":"Trva San Mateo, 10",
    "sg:city":"Madrid",
    "sg:orig_category":"Centros Empresariales",
    "sg:phone":"+34 913 19 51 15",
    "sg:postcode":"28004",
    "sg:province":"Madrid",
    "wof:name":"Marnosus S.l.",
    "wof:placetype":"venue"
},
  "geometry": {"coordinates":[-3.6982889175,40.4252548218],"type":"Point"}
}