{
  "type": "Feature",
  "properties": {
    "iso:country":"ES",
    "sg:address":"Ctra Campana-ftes Andalucia, Km. 0013,0",
    "sg:city":"Fuentes De Andalucia",
    "sg:orig_category":"Maquinaria Para Industrias Diversas",
    "sg:phone":"+34 954 83 80 32",
    "sg:postcode":"41420",
    "sg:province":"Sevilla",
    "wof:name":"Maquinaria Agricola Barcia S.l.",
    "wof:placetype":"venue"
},
  "geometry": {"coordinates":[-5.3430690765,37.4635467529],"type":"Point"}
}