{
  "type": "Feature",
  "properties": {
    "addr:full":"Carrer de Sant Lloren\u00c7, 80 Sabadell Barcelona 08202",
    "addr:housenumber":"80",
    "addr:postcode":"08202",
    "addr:street":"Carrer De Sant Llorenc\u0327",
    "iso:country":"ES",
    "sg:address":"Carrer de Sant Lloren\u00c7, 80",
    "sg:city":"Sabadell",
    "sg:orig_category":"Asesor\u00cda Sobre Comunicaci\u00d3n De Empresas",
    "sg:phone":"+34 937 26 59 66",
    "sg:postcode":"08202",
    "sg:province":"Barcelona",
    "wof:name":"Asinco Asesores S.l.",
    "wof:placetype":"venue"
},
  "geometry": {"coordinates":[2.1119816303,41.5465164185],"type":"Point"}
}