{
  "type": "Feature",
  "properties": {
    "addr:full":"Calle de Jose De Bethencourt Y Castro Molina, 4 Orotava Santa Cruz De Tenerife 38300",
    "addr:housenumber":"4",
    "addr:postcode":"38300",
    "addr:street":"Calle De Jose De Bethencourt Y Castro Molina",
    "iso:country":"ES",
    "sg:address":"Calle de Jose De Bethencourt Y Castro Molina, 4",
    "sg:city":"Orotava",
    "sg:orig_category":"Asesor\u00cda Fiscal Y Jur\u00cddica",
    "sg:phone":"+34 922 33 52 05",
    "sg:postcode":"38300",
    "sg:province":"Santa Cruz De Tenerife",
    "wof:name":"Cedaco Norte S.l.",
    "wof:placetype":"venue"
},
  "geometry": {"coordinates":[-16.5265331268,28.3938789368],"type":"Point"}
}