{
  "type": "Feature",
  "properties": {
    "iso:country":"ES",
    "sg:address":"Urdaburu Kalea, 2",
    "sg:city":"Lezo",
    "sg:orig_category":"Partidos Pol\u00cdticos",
    "sg:phone":"+34 943 52 64 10",
    "sg:postcode":"20100",
    "sg:province":"Guip\u00f9zcoa",
    "wof:name":"Partido Socialista Obrero Espa\u00f1ol",
    "wof:placetype":"venue"
},
  "geometry": {"coordinates":[-1.8977160454,43.3222160339],"type":"Point"}
}