{
  "type": "Feature",
  "properties": {
    "iso:country":"ES",
    "sg:address":"Carrer de Raurell, 1",
    "sg:city":"Castelldefels",
    "sg:orig_category":"Controles De Edificaci\u00d3n (construcci\u00d3n, Seguridad)",
    "sg:phone":"+34 936 36 42 43",
    "sg:postcode":"08860",
    "sg:province":"Barcelona",
    "sg:website":"www.aneclau.com",
    "wof:name":"Igipt Spain One S.l.",
    "wof:placetype":"venue"
},
  "geometry": {"coordinates":[1.9870599508,41.2837944031],"type":"Point"}
}