{
  "type": "Feature",
  "properties": {
    "iso:country":"ES",
    "sg:address":"Calle de Portal De Legutiano, 36",
    "sg:city":"Vitoria-gasteiz",
    "sg:classifiers":[
        {
            "category":"Autos & Motor Vehicles",
            "subcategory":"Automobile Sales",
            "type":"Retail Goods"
        }
    ],
    "sg:phone":"+34 945 28 45 85",
    "sg:postcode":"01002",
    "sg:province":"\u00c1lava",
    "wof:name":"Aua Ajuria Jose Luis",
    "wof:placetype":"venue"
},
  "geometry": {"coordinates":[-2.666131258,42.8550682068],"type":"Point"}
}