{
  "type": "Feature",
  "properties": {
    "iso:country":"ES",
    "sg:address":"Avda Alcala (de), 2",
    "sg:city":"Azuqueca Henares",
    "sg:orig_category":"Farmacias",
    "sg:phone":"+34 949 26 74 37",
    "sg:postcode":"19200",
    "sg:province":"Guadalajara",
    "wof:name":"Rodenas Bleda Elena",
    "wof:placetype":"venue"
},
  "geometry": {"coordinates":[-3.2742099762,40.5585365295],"type":"Point"}
}