{
  "type": "Feature",
  "properties": {
    "iso:country":"ES",
    "sg:address":"Maritima, S/n",
    "sg:city":"Puerto Santiago",
    "sg:orig_category":"Bazares, Art\u00cdculos De Limpieza Y De Cocina (al Por Menor)",
    "sg:phone":"+34 922 86 73 29",
    "sg:postcode":"38683",
    "sg:province":"Santa Cruz De Tenerife",
    "wof:name":"Rodriguez Gonzalez Juan Zacarias",
    "wof:placetype":"venue"
},
  "geometry": {"coordinates":[-16.839723587,28.243019104],"type":"Point"}
}