{
  "type": "Feature",
  "properties": {
    "addr:full":"Calle de Almeria, 22 Pozo Alcon Ja\u00e9n 23485",
    "addr:housenumber":"22",
    "addr:postcode":"23485",
    "addr:street":"Calle De Almeria;Alcon Jae\u0301N",
    "iso:country":"ES",
    "sg:address":"Calle de Almeria, 22",
    "sg:city":"Pozo Alcon",
    "sg:orig_category":"M\u00c1rmoles, Granitos Y Piedras Naturales",
    "sg:phone":"+34 953 71 80 69",
    "sg:postcode":"23485",
    "sg:province":"Ja\u00e9n",
    "wof:name":"Gamez Gamez Santiago",
    "wof:placetype":"venue"
},
  "geometry": {"coordinates":[-2.9362661839,37.6985816956],"type":"Point"}
}