{
  "type": "Feature",
  "properties": {
    "iso:country":"ES",
    "sg:address":"Elkano Kalea, 33",
    "sg:city":"Hernani",
    "sg:orig_category":"Fabricaci\u00d3n De Motores El\u00c9ctricos",
    "sg:phone":"+34 943 33 04 46",
    "sg:postcode":"20120",
    "sg:province":"Guip\u00f9zcoa",
    "wof:name":"Garin Echenique Jose Maria",
    "wof:placetype":"venue"
},
  "geometry": {"coordinates":[-1.9753215313,43.2693710327],"type":"Point"}
}