{
  "type": "Feature",
  "properties": {
    "iso:country":"ES",
    "sg:address":"Carrer de Pons I Gallarza, 92",
    "sg:city":"Barcelona",
    "sg:orig_category":"Farmacias",
    "sg:phone":"+34 933 45 06 67",
    "sg:postcode":"08030",
    "sg:province":"Barcelona",
    "wof:name":"Busquet Masip Carles",
    "wof:placetype":"venue"
},
  "geometry": {"coordinates":[2.1850349903,41.4356956482],"type":"Point"}
}