{
  "type": "Feature",
  "properties": {
    "addr:full":"Calle de Leon Y Castillo, 89 Pto. Rosario Las Palmas 35600",
    "addr:housenumber":"89",
    "addr:postcode":"35600",
    "addr:street":"Calle De Leon Y Castillo;Pto. Rosario Las",
    "iso:country":"ES",
    "sg:address":"Calle de Leon Y Castillo, 89",
    "sg:city":"Pto. Rosario",
    "sg:orig_category":"Audiovisuales (producci\u00d3n, Edici\u00d3n, Realizaci\u00d3n)",
    "sg:phone":"+34 928 85 82 14",
    "sg:postcode":"35600",
    "sg:province":"Las Palmas",
    "wof:name":"Alamo Alvarez Victor Manuel",
    "wof:placetype":"venue"
},
  "geometry": {"coordinates":[-13.8685216904,28.5015029907],"type":"Point"}
}