{
  "type": "Feature",
  "properties": {
    "addr:full":"Banarta, 3 Alkaiaga Navarra 31789",
    "addr:housenumber":"3",
    "addr:postcode":"31789",
    "addr:street":"Banarta",
    "iso:country":"ES",
    "sg:address":"Banarta, 3",
    "sg:city":"Alkaiaga",
    "sg:orig_category":"Construcciones Met\u00c1licas",
    "sg:phone":"+34 948 62 54 19",
    "sg:postcode":"31789",
    "sg:province":"Navarra",
    "wof:name":"Espincer S.l.",
    "wof:placetype":"venue"
},
  "geometry": {"coordinates":[-1.6493040323,43.2943649292],"type":"Point"}
}