{
  "type": "Feature",
  "properties": {
    "iso:country":"ES",
    "sg:address":"Calle de Aguacate, 45",
    "sg:city":"Madrid",
    "sg:orig_category":"Agentes, Concesionarios Y Sucursales De Veh\u00cdculos",
    "sg:phone":"+34 915 08 68 42",
    "sg:postcode":"28044",
    "sg:province":"Madrid",
    "sg:website":"www.audi.es",
    "wof:name":"M. Conde S.a.",
    "wof:placetype":"venue"
},
  "geometry": {"coordinates":[-3.7416596413,40.3680343628],"type":"Point"}
}