{
  "type": "Feature",
  "properties": {
    "iso:country":"ES",
    "sg:address":"Calle de Consuelo, 14",
    "sg:city":"Valencia",
    "sg:orig_category":"Delegados, Agentes De Tr\u00c1nsito, Auxiliares De Transporte Internacional",
    "sg:phone":"+34 963 24 56 58",
    "sg:postcode":"46...",
    "sg:province":"Valencia",
    "wof:name":"Juan Roig S.l.",
    "wof:placetype":"venue"
},
  "geometry": {"coordinates":[-0.8427612185,38.4393844604],"type":"Point"}
}