{
  "type": "Feature",
  "properties": {
    "addr:full":"Calle de Zurbano, 94 Madrid Madrid 28003",
    "addr:housenumber":"94",
    "addr:postcode":"madrid;28003",
    "addr:street":"Calle De Zurbano",
    "iso:country":"ES",
    "sg:address":"Calle de Zurbano, 94",
    "sg:city":"Madrid",
    "sg:orig_category":"Asociaciones, Organismos Culturales Y Socioeducativos",
    "sg:phone":"+34 914 42 95 82",
    "sg:postcode":"28003",
    "sg:province":"Madrid",
    "wof:name":"Asociacion Cultural Belarcazar",
    "wof:placetype":"venue"
},
  "geometry": {"coordinates":[-3.6928222179,40.4386749268],"type":"Point"}
}