{
  "type": "Feature",
  "properties": {
    "iso:country":"ES",
    "sg:address":"Calle de Isabel La Catolica, 3",
    "sg:city":"Medina Campo",
    "sg:orig_category":"Asilos De Ancianos. Centros Privados",
    "sg:phone":"+34 983 80 44 68",
    "sg:postcode":"47400",
    "sg:province":"Valladolid",
    "wof:name":"Residencia De Medina S.l.",
    "wof:placetype":"venue"
},
  "geometry": {"coordinates":[-4.9123091698,41.3108901978],"type":"Point"}
}