{
  "type": "Feature",
  "properties": {
    "addr:full":"Avda Agirre Lehendakaria, 72 Urbi Vizcaya 48970",
    "addr:housenumber":"72",
    "addr:postcode":"48970",
    "addr:street":"Avda Agirre Lehendakaria",
    "iso:country":"ES",
    "sg:address":"Avda Agirre Lehendakaria, 72",
    "sg:city":"Urbi",
    "sg:orig_category":"Marroquiner\u00cda (confecci\u00d3n)",
    "sg:phone":"+34 944 49 15 22",
    "sg:postcode":"48970",
    "sg:province":"Vizcaya",
    "wof:name":"Lacalle Arnedillo Francisco Javier",
    "wof:placetype":"venue"
},
  "geometry": {"coordinates":[-2.8794789314,43.2355804443],"type":"Point"}
}