{
  "type": "Feature",
  "properties": {
    "addr:full":"Avda Puerto, 218 Valencia Valencia 46023",
    "addr:housenumber":"218",
    "addr:postcode":"46023",
    "addr:street":"Avda Puerto",
    "iso:country":"ES",
    "sg:address":"Avda Puerto, 218",
    "sg:city":"Valencia",
    "sg:orig_category":"Cajas De Ahorro",
    "sg:phone":"+34 963 30 64 57",
    "sg:postcode":"46023",
    "sg:province":"Valencia",
    "sg:website":"www.cam.es",
    "wof:name":"Caja De Ahorros Del Mediterraneo",
    "wof:placetype":"venue"
},
  "geometry": {"coordinates":[-0.3769130111,39.4687919617],"type":"Point"}
}