{
  "type": "Feature",
  "properties": {
    "addr:full":"Calle de General Davila, 31 Alcorcon Madrid 28924",
    "addr:housenumber":"31",
    "addr:postcode":"28924",
    "addr:street":"Calle De General Davila",
    "iso:country":"ES",
    "sg:address":"Calle de General Davila, 31",
    "sg:city":"Alcorcon",
    "sg:orig_category":"Frutas, Legumbres Frescas Y Tempranas (al Por Menor)",
    "sg:phone":"+34 916 12 18 01",
    "sg:postcode":"28924",
    "sg:province":"Madrid",
    "wof:name":"Martin Sanchez Patricia",
    "wof:placetype":"venue"
},
  "geometry": {"coordinates":[-3.8133199215,40.3487548828],"type":"Point"}
}