{
  "type": "Feature",
  "properties": {
    "iso:country":"ES",
    "sg:address":"Rbla Catalunya, 31",
    "sg:city":"Barcelona",
    "sg:orig_category":"Abogados",
    "sg:phone":"+34 932 15 62 98",
    "sg:postcode":"08007",
    "sg:province":"Barcelona",
    "wof:name":"Vives Biel Juan",
    "wof:placetype":"venue"
},
  "geometry": {"coordinates":[2.1655623913,41.3894271851],"type":"Point"}
}