{
  "type": "Feature",
  "properties": {
    "iso:country":"ES",
    "sg:address":"Calle de Lavaderos (de Los), 7",
    "sg:city":"Arevalo",
    "sg:orig_category":"Molduras, Junquillos, Listones Y Molduras Perforadas",
    "sg:phone":"+34 920 30 17 74",
    "sg:postcode":"05200",
    "sg:province":"\u00c1vila",
    "wof:name":"Garcia Del Dedo Jose",
    "wof:placetype":"venue"
},
  "geometry": {"coordinates":[-4.7177028656,41.0480766296],"type":"Point"}
}