{
  "type": "Feature",
  "properties": {
    "iso:country":"ES",
    "sg:address":"Calle de Jazmin, 18",
    "sg:city":"Periana",
    "sg:orig_category":"Pescader\u00cdas (al Por Menor)",
    "sg:phone":"+34 952 53 60 98",
    "sg:postcode":"29710",
    "sg:province":"M\u00e1laga",
    "wof:name":"Trujillo Molina Antonio",
    "wof:placetype":"venue"
},
  "geometry": {"coordinates":[-4.1918888092,36.9280281067],"type":"Point"}
}