{
  "type": "Feature",
  "properties": {
    "iso:country":"ES",
    "sg:address":"Plaz Encarnacion, 12",
    "sg:city":"Sevilla",
    "sg:orig_category":"Carnicer\u00cdas, Carnicer\u00cdas",
    "sg:phone":"+34 954 21 61 86",
    "sg:postcode":"41003",
    "sg:province":"Sevilla",
    "wof:name":"Chang Bogallo Rafael",
    "wof:placetype":"venue"
},
  "geometry": {"coordinates":[-5.9919681549,37.3939399719],"type":"Point"}
}