{
  "type": "Feature",
  "properties": {
    "iso:country":"ES",
    "sg:address":"Carr Pau Casals, 16",
    "sg:city":"Girona",
    "sg:orig_category":"Ense\u00d1anza Variada",
    "sg:phone":"+34 972 41 01 00",
    "sg:postcode":"17001",
    "sg:province":"Girona",
    "wof:name":"Opcio Formativa S.l.",
    "wof:placetype":"venue"
},
  "geometry": {"coordinates":[2.8142840862,41.9836044312],"type":"Point"}
}