{
  "type": "Feature",
  "properties": {
    "addr:full":"Carrer de Montserrat, 11 Mataro Barcelona 08302",
    "addr:housenumber":"11",
    "addr:postcode":"08302",
    "addr:street":"Carrer De Montserrat",
    "iso:country":"ES",
    "sg:address":"Carrer de Montserrat, 11",
    "sg:city":"Mataro",
    "sg:orig_category":"Art\u00cdculos De Decoraci\u00d3n",
    "sg:phone":"+34 937 90 60 86",
    "sg:postcode":"08302",
    "sg:province":"Barcelona",
    "sg:website":"www.ka-international.com",
    "wof:name":"Labor Invicta S.l.",
    "wof:placetype":"venue"
},
  "geometry": {"coordinates":[2.4424610138,41.5377845764],"type":"Point"}
}