{
  "type": "Feature",
  "properties": {
    "addr:full":"Carrer de Sevilla, S/n Hospitalet Llobregat Barcelona 08905",
    "addr:housenumber":"s",
    "addr:postcode":"08905",
    "addr:street":"Carrer De Sevilla;/ N",
    "iso:country":"ES",
    "sg:address":"Carrer de Sevilla, S/n",
    "sg:city":"Hospitalet Llobregat",
    "sg:orig_category":"Carnicer\u00cdas, Carnicer\u00cdas",
    "sg:phone":"+34 934 48 34 80",
    "sg:postcode":"08905",
    "sg:province":"Barcelona",
    "wof:name":"Albesa Ala\u00f1a Miguel Juan",
    "wof:placetype":"venue"
},
  "geometry": {"coordinates":[2.1077032089,41.3702163696],"type":"Point"}
}