{
  "type": "Feature",
  "properties": {
    "addr:full":"Calle de Jorge Juan, 35 Madrid Madrid 28001",
    "addr:housenumber":"35",
    "addr:postcode":"madrid;28001",
    "addr:street":"Calle De Jorge Juan",
    "iso:country":"ES",
    "sg:address":"Calle de Jorge Juan, 35",
    "sg:city":"Madrid",
    "sg:orig_category":"Ropa Para Se\u00d1oras (al Por Menor)",
    "sg:phone":"+34 915 75 66 05",
    "sg:postcode":"28001",
    "sg:province":"Madrid",
    "sg:website":"www.hannibal-laguna.com",
    "wof:name":"Halaguna Costura S.l.",
    "wof:placetype":"venue"
},
  "geometry": {"coordinates":[-3.6831119061,40.423866272],"type":"Point"}
}