{
  "type": "Feature",
  "properties": {
    "iso:country":"ES",
    "sg:address":"Avda Granada, 15",
    "sg:city":"Jaen",
    "sg:orig_category":"Muebles, Minoristas",
    "sg:phone":"+34 953 24 16 16",
    "sg:postcode":"23001",
    "sg:province":"Ja\u00e9n",
    "wof:name":"Hurtado Bonoso Juan",
    "wof:placetype":"venue"
},
  "geometry": {"coordinates":[-3.7850410938,37.76902771],"type":"Point"}
}