{
  "type": "Feature",
  "properties": {
    "iso:country":"ES",
    "sg:address":"Calle de Cruz Verde, 23",
    "sg:city":"Ronda",
    "sg:orig_category":"Droguer\u00cdas (al Por Menor)",
    "sg:phone":"+34 952 87 68 48",
    "sg:postcode":"29400",
    "sg:province":"M\u00e1laga",
    "wof:name":"Perez Hidalgo Rafael",
    "wof:placetype":"venue"
},
  "geometry": {"coordinates":[-5.0806918144,36.7813644409],"type":"Point"}
}