{
  "type": "Feature",
  "properties": {
    "iso:country":"ES",
    "sg:address":"Calle de Acacias (las), 2",
    "sg:city":"Palencia",
    "sg:orig_category":"Frutas, Legumbres Frescas Y Tempranas (al Por Menor)",
    "sg:phone":"+34 979 74 68 30",
    "sg:postcode":"34003",
    "sg:province":"Palencia",
    "wof:name":"Andres Sendino Esther",
    "wof:placetype":"venue"
},
  "geometry": {"coordinates":[-4.5304756165,42.0139694214],"type":"Point"}
}