{
  "type": "Feature",
  "properties": {
    "iso:country":"ES",
    "sg:address":"Carr Pare Huguet, 2",
    "sg:city":"Ciutadella Menorca",
    "sg:orig_category":"Electricidad: Instaladores",
    "sg:phone":"+34 971 38 42 95",
    "sg:postcode":"07760",
    "sg:province":"Islas Baleares",
    "wof:name":"Instelec S.c.",
    "wof:placetype":"venue"
},
  "geometry": {"coordinates":[3.8426589966,39.9988937378],"type":"Point"}
}