{
  "type": "Feature",
  "properties": {
    "addr:full":"Calle de Real De Motril, 7 Armilla Granada 18100",
    "addr:housenumber":"7",
    "addr:postcode":"18100",
    "addr:street":"Calle De Real De Motril",
    "iso:country":"ES",
    "sg:address":"Calle de Real De Motril, 7",
    "sg:city":"Armilla",
    "sg:orig_category":"Construcci\u00d3n De Edificios Residenciales Y No Residenciales",
    "sg:phone":"+34 958 57 02 37",
    "sg:postcode":"18100",
    "sg:province":"Granada",
    "wof:name":"Construcciones Edirali S.l.",
    "wof:placetype":"venue"
},
  "geometry": {"coordinates":[-3.6254599094,37.1434822083],"type":"Point"}
}