{
  "type": "Feature",
  "properties": {
    "addr:full":"Carrer de Andrade, 224 Barcelona Barcelona 08020",
    "addr:housenumber":"224",
    "addr:postcode":"08020",
    "addr:street":"Carrer De Andrade",
    "iso:country":"ES",
    "sg:address":"Carrer de Andrade, 224",
    "sg:city":"Barcelona",
    "sg:orig_category":"Droguer\u00cdas (al Por Menor)",
    "sg:phone":"+34 933 14 95 54",
    "sg:postcode":"08020",
    "sg:province":"Barcelona",
    "wof:name":"Plumed Melendez Manuel",
    "wof:placetype":"venue"
},
  "geometry": {"coordinates":[2.2052218914,41.4188728333],"type":"Point"}
}