{
  "type": "Feature",
  "properties": {
    "iso:country":"ES",
    "sg:address":"Carrer de Vico, 29",
    "sg:city":"Barcelona",
    "sg:orig_category":"Confecci\u00d3n De Corbatas",
    "sg:phone":"+34 932 01 20 00",
    "sg:postcode":"08021",
    "sg:province":"Barcelona",
    "wof:name":"Anthime Mouley Espa\u00f1a S. A.",
    "wof:placetype":"venue"
},
  "geometry": {"coordinates":[2.1360354424,41.4002151489],"type":"Point"}
}