{
  "type": "Feature",
  "properties": {
    "iso:country":"ES",
    "sg:address":"Calle de San Andres, 3",
    "sg:city":"Arrigorriaga",
    "sg:orig_category":"Forjas Y Altos Hornos",
    "sg:phone":"+34 944 02 06 97",
    "sg:postcode":"48480",
    "sg:province":"Vizcaya",
    "wof:name":"Talleres Ibarrondo, S.l.",
    "wof:placetype":"venue"
},
  "geometry": {"coordinates":[-2.8882789612,43.2067642212],"type":"Point"}
}