{
  "type": "Feature",
  "properties": {
    "addr:full":"C/ Canal, 30 Banyoles Girona 17820",
    "addr:housenumber":"30",
    "addr:postcode":"17820",
    "addr:street":"C / Canal",
    "iso:country":"ES",
    "sg:address":"C/ Canal, 30",
    "sg:city":"Banyoles",
    "sg:orig_category":"Asesor\u00cdas Y Estudios Financieros",
    "sg:phone":"+34 972 57 33 01",
    "sg:postcode":"17820",
    "sg:province":"Girona",
    "wof:name":"Ros Planas Jose",
    "wof:placetype":"venue"
},
  "geometry": {"coordinates":[2.764786005,42.1186027527],"type":"Point"}
}