{
  "type": "Feature",
  "properties": {
    "iso:country":"ES",
    "sg:address":"Avda Betanzos, 17",
    "sg:city":"Madrid",
    "sg:orig_category":"Molduras, Junquillos, Listones Y Molduras Perforadas",
    "sg:phone":"+34 917 31 91 29",
    "sg:postcode":"28029",
    "sg:province":"Madrid",
    "wof:name":"Bar Madrid Es La Corte D.b.",
    "wof:placetype":"venue"
},
  "geometry": {"coordinates":[-3.7113230228,40.4748649597],"type":"Point"}
}