{
  "type": "Feature",
  "properties": {
    "addr:full":"Carrer de Tarragones, 6 Olesa Montserrat Barcelona 08640",
    "addr:housenumber":"6",
    "addr:postcode":"08640",
    "addr:street":"Carrer De Tarragones;Barcelona",
    "iso:country":"ES",
    "sg:address":"Carrer de Tarragones, 6",
    "sg:city":"Olesa Montserrat",
    "sg:orig_category":"Agencias Y Agentes Comerciales, Representantes",
    "sg:phone":"+34 937 78 58 19",
    "sg:postcode":"08640",
    "sg:province":"Barcelona",
    "wof:name":"Sicre Diaz Fernando",
    "wof:placetype":"venue"
},
  "geometry": {"coordinates":[1.891505003,41.5489616394],"type":"Point"}
}