{
  "type": "Feature",
  "properties": {
    "iso:country":"ES",
    "sg:address":"Carrer de Conreria, 10",
    "sg:city":"Barcelona",
    "sg:orig_category":"Centros De Salud",
    "sg:phone":"+34 932 21 78 61",
    "sg:postcode":"08003",
    "sg:province":"Barcelona",
    "wof:name":"Taller Escola Barcelona S.c.c.l.",
    "wof:placetype":"venue"
},
  "geometry": {"coordinates":[2.1920759678,41.3802375793],"type":"Point"}
}