{
  "type": "Feature",
  "properties": {
    "addr:full":"Calle de Marjalillo Bajo, 12 Motril Granada 18600",
    "addr:housenumber":"12",
    "addr:postcode":"18600",
    "addr:street":"Calle De Marjalillo Bajo",
    "iso:country":"ES",
    "sg:address":"Calle de Marjalillo Bajo, 12",
    "sg:city":"Motril",
    "sg:orig_category":"Procuradores",
    "sg:phone":"+34 958 60 37 27",
    "sg:postcode":"18600",
    "sg:province":"Granada",
    "wof:name":"Aguado Hernandez Jesus",
    "wof:placetype":"venue"
},
  "geometry": {"coordinates":[-3.5171325207,36.7446250916],"type":"Point"}
}