{
  "type": "Feature",
  "properties": {
    "addr:full":"Monasterio Belate, 1 Iru\u00f1a Navarra 31011",
    "addr:housenumber":"1",
    "addr:postcode":"31011",
    "addr:street":"Belate",
    "iso:country":"ES",
    "sg:address":"Monasterio Belate, 1",
    "sg:city":"Iru\u00f1a",
    "sg:orig_category":"M\u00c9dicos: Salud P\u00dablica",
    "sg:phone":"+34 948 26 29 77",
    "sg:postcode":"31011",
    "sg:province":"Navarra",
    "wof:name":"Layana Burguete Ramiro",
    "wof:placetype":"venue"
},
  "geometry": {"coordinates":[-1.6603629589,42.8147201538],"type":"Point"}
}