{
  "type": "Feature",
  "properties": {
    "iso:country":"ES",
    "sg:address":"Barqueros, 4",
    "sg:city":"Cordoba",
    "sg:orig_category":"Librer\u00cdas",
    "sg:phone":"+34 957 47 82 30",
    "sg:postcode":"14002",
    "sg:province":"C\u00f3rdoba",
    "wof:name":"Cabello Alfaro Dulce Nombre",
    "wof:placetype":"venue"
},
  "geometry": {"coordinates":[-4.7791371346,37.8856391907],"type":"Point"}
}