{
  "type": "Feature",
  "properties": {
    "addr:full":"Carrer de Riu Llobregat, 38 Deltebre Tarragona 43580",
    "addr:housenumber":"38",
    "addr:postcode":"43580",
    "addr:street":"Carrer De Riu Llobregat",
    "iso:country":"ES",
    "sg:address":"Carrer de Riu Llobregat, 38",
    "sg:city":"Deltebre",
    "sg:orig_category":"Negocio De Materiales De Construcci\u00d3n",
    "sg:phone":"+34 977 48 01 07",
    "sg:postcode":"43580",
    "sg:province":"Tarragona",
    "wof:name":"Subministres Delta 98 C.b",
    "wof:placetype":"venue"
},
  "geometry": {"coordinates":[0.7339199781,40.7188682556],"type":"Point"}
}