{
  "type": "Feature",
  "properties": {
    "iso:country":"ES",
    "sg:address":"Av Diagonal, 648",
    "sg:city":"Barcelona",
    "sg:orig_category":"Sociedades, Compa\u00d1\u00cdas Aseguradoras",
    "sg:phone":"+34 932 05 22 13",
    "sg:postcode":"08017",
    "sg:province":"Barcelona",
    "sg:website":"www.fiatc.es",
    "wof:name":"Fiatc Mutua De Seguros Generales",
    "wof:placetype":"venue"
},
  "geometry": {"coordinates":[2.1340389252,41.3905448914],"type":"Point"}
}