{
  "type": "Feature",
  "properties": {
    "iso:country":"ES",
    "sg:address":"Calle de Camarena, 110",
    "sg:city":"Madrid",
    "sg:orig_category":"Electricidad: Instaladores",
    "sg:phone":"+34 917 19 03 39",
    "sg:postcode":"28047",
    "sg:province":"Madrid",
    "wof:name":"Sanz Martin Juan Carlos",
    "wof:placetype":"venue"
},
  "geometry": {"coordinates":[-3.7557930946,40.3949241638],"type":"Point"}
}