{
  "type": "Feature",
  "properties": {
    "addr:full":"Avda Daroca, 44 Madrid Madrid 28017",
    "addr:housenumber":"44",
    "addr:postcode":"madrid;28017",
    "addr:street":"Avda Daroca",
    "iso:country":"ES",
    "sg:address":"Avda Daroca, 44",
    "sg:city":"Madrid",
    "sg:orig_category":"Muebles, Minoristas",
    "sg:phone":"+34 913 56 17 02",
    "sg:postcode":"28017",
    "sg:province":"Madrid",
    "wof:name":"Mainre S.l.",
    "wof:placetype":"venue"
},
  "geometry": {"coordinates":[-3.6551859379,40.4295310974],"type":"Point"}
}