{
  "type": "Feature",
  "properties": {
    "iso:country":"ES",
    "sg:address":"Av Principe Felipe De Borbon, Km. 0157,2",
    "sg:city":"Las Pedro\u00f1eras",
    "sg:orig_category":"Reparaciones Y Remolcado De Veh\u00cdculos",
    "sg:phone":"+34 967 16 08 09",
    "sg:postcode":"16660",
    "sg:province":"Cuenca",
    "wof:name":"Auto-comercial Pedro\u00f1eras Sociedad Limitada",
    "wof:placetype":"venue"
},
  "geometry": {"coordinates":[-2.6387794018,39.4773025513],"type":"Point"}
}