{
  "type": "Feature",
  "properties": {
    "addr:full":"Ctra Matadepera, 110 Terrassa Barcelona 08226",
    "addr:housenumber":"110",
    "addr:postcode":"08226",
    "addr:street":"Ctra Matadepera",
    "iso:country":"ES",
    "sg:address":"Ctra Matadepera, 110",
    "sg:city":"Terrassa",
    "sg:orig_category":"Arreglo, Reparaci\u00d3n, Piezas Sueltas De Televisi\u00d3n, V\u00cddeo, Hi",
    "sg:phone":"+34 937 35 16 78",
    "sg:postcode":"08226",
    "sg:province":"Barcelona",
    "sg:website":"www.barrinet.net/televide",
    "wof:name":"Televideo Terrassa S.l.",
    "wof:placetype":"venue"
},
  "geometry": {"coordinates":[2.0179789066,41.5781326294],"type":"Point"}
}