{
  "type": "Feature",
  "properties": {
    "iso:country":"ES",
    "sg:address":"Avda Aguirre Lehendakari, 131",
    "sg:city":"Bilbao",
    "sg:orig_category":"Ense\u00d1anza Secundaria: Colegios Y Escuelas Privadas",
    "sg:phone":"+34 944 76 17 81",
    "sg:postcode":"48015",
    "sg:province":"Vizcaya",
    "wof:name":"Centro De Estudios Juan Xxiii Sl",
    "wof:placetype":"venue"
},
  "geometry": {"coordinates":[-2.9594860077,43.2752723694],"type":"Point"}
}