{
  "type": "Feature",
  "properties": {
    "addr:full":"Avda Juan Pablo Ii, 1 Olivares Sevilla 41804",
    "addr:housenumber":"1",
    "addr:postcode":"41804",
    "addr:street":"Avda Juan Pablo Ii;Sevilla",
    "iso:country":"ES",
    "sg:address":"Avda Juan Pablo Ii, 1",
    "sg:city":"Olivares",
    "sg:orig_category":"Imprenta",
    "sg:phone":"+34 955 71 94 48",
    "sg:postcode":"41804",
    "sg:province":"Sevilla",
    "wof:name":"Cotan Pe\u00f1a Francisco Javier",
    "wof:placetype":"venue"
},
  "geometry": {"coordinates":[-6.151843071,37.4181404114],"type":"Point"}
}