{
  "type": "Feature",
  "properties": {
    "iso:country":"ES",
    "sg:address":"Calle de Bailen, 72",
    "sg:city":"Alcala Guadaira",
    "sg:orig_category":"Agencias Y Agentes Comerciales, Representantes",
    "sg:phone":"+34 955 68 25 65",
    "sg:postcode":"41500",
    "sg:province":"Sevilla",
    "wof:name":"Redysur S.l.",
    "wof:placetype":"venue"
},
  "geometry": {"coordinates":[-5.8440699577,37.3352584839],"type":"Point"}
}