{
  "type": "Feature",
  "properties": {
    "addr:full":"Avda Primero De Mayo, 107 Don Benito Badajoz 06400",
    "addr:housenumber":"107",
    "addr:postcode":"06400",
    "addr:street":"Avda Primero De Mayo",
    "iso:country":"ES",
    "sg:address":"Avda Primero De Mayo, 107",
    "sg:city":"Don Benito",
    "sg:orig_category":"Transportes Por V\u00cdas Navegables",
    "sg:phone":"+34 924 80 16 41",
    "sg:postcode":"06400",
    "sg:province":"Badajoz",
    "wof:name":"Ruiz Mu\u00f1oz Adolfo",
    "wof:placetype":"venue"
},
  "geometry": {"coordinates":[-5.8575692177,38.9614486694],"type":"Point"}
}