{
  "type": "Feature",
  "properties": {
    "addr:full":"Ctra Cabra, S/n Lucena C\u00f3rdoba 14900",
    "addr:postcode":"14900",
    "addr:street":"Ctra Cabra S / N",
    "iso:country":"ES",
    "sg:address":"Ctra Cabra, S/n",
    "sg:city":"Lucena",
    "sg:orig_category":"Porcelanas, Azulejos (fabricaci\u00d3n, Al Por Mayor)",
    "sg:phone":"+34 957 50 93 06",
    "sg:postcode":"14900",
    "sg:province":"C\u00f3rdoba",
    "sg:website":"www.arance.com",
    "wof:name":"Arance Cordoba S.l.",
    "wof:placetype":"venue"
},
  "geometry": {"coordinates":[-4.4828619957,37.4187164307],"type":"Point"}
}