{
  "type": "Feature",
  "properties": {
    "iso:country":"ES",
    "sg:address":"Ctra Alicante Madrid, Km. 0044,1",
    "sg:city":"Sax",
    "sg:orig_category":"Postigos, Persianas Y Celos\u00cdas",
    "sg:phone":"+34 966 96 81 23",
    "sg:postcode":"03630",
    "sg:province":"Alicante",
    "wof:name":"Persianas Gilper S.l.",
    "wof:placetype":"venue"
},
  "geometry": {"coordinates":[-0.8193240166,38.5343437195],"type":"Point"}
}