{
  "type": "Feature",
  "properties": {
    "iso:country":"ES",
    "sg:address":"Carrer de Fenolleda (la), 22",
    "sg:city":"Terrassa",
    "sg:orig_category":"Material Y Equipo Para Vinificaci\u00d3n",
    "sg:phone":"+34 937 34 94 40",
    "sg:postcode":"08226",
    "sg:province":"Barcelona",
    "wof:name":"Vins I Olis Puig S. A.",
    "wof:placetype":"venue"
},
  "geometry": {"coordinates":[2.0259990692,41.5822715759],"type":"Point"}
}