{
  "type": "Feature",
  "properties": {
    "iso:country":"ES",
    "sg:address":"Avda Sancho El Sabio, 19",
    "sg:city":"Donostia-san Sebastian",
    "sg:orig_category":"Ense\u00d1anza: Profesiones Art\u00cdsticas",
    "sg:phone":"+34 943 45 49 98",
    "sg:postcode":"20010",
    "sg:province":"Guip\u00f9zcoa",
    "wof:name":"Rezola Vicondo Jose Maria",
    "wof:placetype":"venue"
},
  "geometry": {"coordinates":[-1.9796910286,43.3097038269],"type":"Point"}
}