{
  "type": "Feature",
  "properties": {
    "addr:full":"Calle de Padre Benito, 14 Almagro Ciudad Real 13270",
    "addr:housenumber":"14",
    "addr:postcode":"13270",
    "addr:street":"Calle De Padre Benito",
    "iso:country":"ES",
    "sg:address":"Calle de Padre Benito, 14",
    "sg:city":"Almagro",
    "sg:orig_category":"Alimentaci\u00d3n General (al Por Menor)",
    "sg:phone":"+34 926 88 25 90",
    "sg:postcode":"13270",
    "sg:province":"Ciudad Real",
    "wof:name":"Diaz Cruz Santos",
    "wof:placetype":"venue"
},
  "geometry": {"coordinates":[-3.7127330303,38.8935813904],"type":"Point"}
}