{
  "type": "Feature",
  "properties": {
    "iso:country":"ES",
    "sg:address":"Calle de Londres, S/n",
    "sg:city":"Huecas",
    "sg:orig_category":"Serigraf\u00cda (material Y Suministros)",
    "sg:phone":"+34 925 78 52 28",
    "sg:postcode":"45511",
    "sg:province":"Toledo",
    "wof:name":"Escalten S.l.",
    "wof:placetype":"venue"
},
  "geometry": {"coordinates":[-4.1959791183,40.0118255615],"type":"Point"}
}