{
  "type": "Feature",
  "properties": {
    "iso:country":"ES",
    "sg:address":"Calle de Monte Carmelo, 6",
    "sg:city":"Zaragoza",
    "sg:orig_category":"Cultos Diversos",
    "sg:phone":"+34 976 33 47 14",
    "sg:postcode":"50010",
    "sg:province":"Zaragoza",
    "wof:name":"Asamblea Espiritual Nacional De Los Baha'is De Espa\u00f1a",
    "wof:placetype":"venue"
},
  "geometry": {"coordinates":[-0.9000681043,41.6557998657],"type":"Point"}
}