{
  "type": "Feature",
  "properties": {
    "addr:full":"Calle de Martianes, 7 Fuente Maestre Badajoz 06360",
    "addr:housenumber":"7",
    "addr:postcode":"06360",
    "addr:street":"Calle De Martianes",
    "iso:country":"ES",
    "sg:address":"Calle de Martianes, 7",
    "sg:city":"Fuente Maestre",
    "sg:orig_category":"Notarios",
    "sg:phone":"+34 924 53 04 35",
    "sg:postcode":"06360",
    "sg:province":"Badajoz",
    "wof:name":"Garcia Morlesin Maria De Los Angeles",
    "wof:placetype":"venue"
},
  "geometry": {"coordinates":[-6.4474477768,38.5219039917],"type":"Point"}
}