{
  "type": "Feature",
  "properties": {
    "iso:country":"ES",
    "sg:address":"Calle de Mostoles (de), 101",
    "sg:city":"Fuenlabrada",
    "sg:orig_category":"Muebles, Minoristas",
    "sg:phone":"+34 916 08 38 31",
    "sg:postcode":"28942",
    "sg:province":"Madrid",
    "wof:name":"Gonzalez Martinez Antonio",
    "wof:placetype":"venue"
},
  "geometry": {"coordinates":[-3.8157908916,40.2964706421],"type":"Point"}
}