{
  "type": "Feature",
  "properties": {
    "iso:country":"ES",
    "sg:address":"Plaz Viudas, 38",
    "sg:city":"Cadiz",
    "sg:orig_category":"Serigraf\u00cda (material Y Suministros)",
    "sg:phone":"+34 956 22 66 31",
    "sg:postcode":"11003",
    "sg:province":"C\u00e1diz",
    "wof:name":"Galvan Benitez Maria Dolores",
    "wof:placetype":"venue"
},
  "geometry": {"coordinates":[-6.3010492325,36.533203125],"type":"Point"}
}