{
  "type": "Feature",
  "properties": {
    "iso:country":"ES",
    "sg:address":"Calle de Cuna, 11",
    "sg:city":"Sevilla",
    "sg:orig_category":"Comercio De Cuadros, L\u00c1minas Y Reproducciones De Obras De Arte",
    "sg:phone":"+34 954 21 14 15",
    "sg:postcode":"41004",
    "sg:province":"Sevilla",
    "wof:name":"Galeria El Marco S.l.",
    "wof:placetype":"venue"
},
  "geometry": {"coordinates":[-5.9935560226,37.3919563293],"type":"Point"}
}