{
  "type": "Feature",
  "properties": {
    "iso:country":"ES",
    "sg:address":"Calle de Velazquez, 3",
    "sg:city":"Oviedo",
    "sg:orig_category":"Agencias De Viajes",
    "sg:phone":"+34 985 11 88 48",
    "sg:postcode":"33011",
    "sg:province":"Asturias",
    "sg:website":"www.iberojet.es",
    "wof:name":"Viajes Iberojet",
    "wof:placetype":"venue"
},
  "geometry": {"coordinates":[-5.8376870155,43.3690490723],"type":"Point"}
}