{
  "type": "Feature",
  "properties": {
    "addr:full":"Calle de Carballal, S/n San Pedro De Trones Le\u00f3n 24385",
    "addr:housenumber":"s / n",
    "addr:postcode":"24385",
    "addr:street":"Calle De Carballal;Leo\u0301N",
    "iso:country":"ES",
    "sg:address":"Calle de Carballal, S/n",
    "sg:city":"San Pedro De Trones",
    "sg:orig_category":"Centros De Educaci\u00d3n Especial",
    "sg:phone":"+34 987 46 03 69",
    "sg:postcode":"24385",
    "sg:province":"Le\u00f3n",
    "wof:name":"Colegio Rural Agrupado Puente De Domingo Florez",
    "wof:placetype":"venue"
},
  "geometry": {"coordinates":[-6.8012709618,42.4002227783],"type":"Point"}
}