{
  "type": "Feature",
  "properties": {
    "iso:country":"ES",
    "sg:address":"Co Algarrada, 19",
    "sg:city":"Calahorra",
    "sg:orig_category":"Confecci\u00d3n De Zapatos",
    "sg:phone":"+34 941 14 61 15",
    "sg:postcode":"26500",
    "sg:province":"La Rioja",
    "wof:name":"Calzados Tripodi S.l.",
    "wof:placetype":"venue"
},
  "geometry": {"coordinates":[-1.9533619881,42.3119087219],"type":"Point"}
}