{
  "type": "Feature",
  "properties": {
    "addr:full":"Avda Constitucion, S/n Mansilla Mulas Le\u00f3n 24210",
    "addr:postcode":"24210",
    "addr:street":"Avda Constitucion S / N Mansilla;Leo\u0301N",
    "iso:country":"ES",
    "sg:address":"Avda Constitucion, S/n",
    "sg:city":"Mansilla Mulas",
    "sg:orig_category":"Alimentaci\u00d3n General (al Por Menor)",
    "sg:phone":"+34 987 31 09 11",
    "sg:postcode":"24210",
    "sg:province":"Le\u00f3n",
    "wof:name":"Hernandez Garcia Pedro",
    "wof:placetype":"venue"
},
  "geometry": {"coordinates":[-5.4154491425,42.4973907471],"type":"Point"}
}