{
  "type": "Feature",
  "properties": {
    "iso:country":"ES",
    "sg:address":"Av General Luque, 238",
    "sg:city":"Inca",
    "sg:classifiers":[
        {
            "category":"Personal",
            "subcategory":"Barber",
            "type":"Services"
        }
    ],
    "sg:phone":"+34 971 50 35 37",
    "sg:postcode":"07300",
    "sg:province":"Islas Baleares",
    "sg:tags":[
        "caballeros",
        "de",
        "peluqueros"
    ],
    "wof:name":"Aulet Ferrer Gabriel",
    "wof:placetype":"venue"
},
  "geometry": {"coordinates":[2.9067800045,39.7166366577],"type":"Point"}
}