{
  "type": "Feature",
  "properties": {
    "addr:full":"Avda Huelva De, 1 Palma Condado Huelva 21700",
    "addr:housenumber":"1",
    "addr:postcode":"21700",
    "addr:street":"Avda Huelva De",
    "iso:country":"ES",
    "sg:address":"Avda Huelva De, 1",
    "sg:city":"Palma Condado",
    "sg:orig_category":"Procuradores",
    "sg:phone":"+34 959 40 03 61",
    "sg:postcode":"21700",
    "sg:province":"Huelva",
    "wof:name":"Jimenez Mateos Jose Antonio",
    "wof:placetype":"venue"
},
  "geometry": {"coordinates":[-6.556842804,37.3890342712],"type":"Point"}
}