{
  "type": "Feature",
  "properties": {
    "iso:country":"ES",
    "sg:address":"Rua Cervantes, 7",
    "sg:city":"Foz",
    "sg:orig_category":"Albergues",
    "sg:phone":"+34 982 14 00 35",
    "sg:postcode":"27780",
    "sg:province":"Lugo",
    "wof:name":"Moreda Marful Eliseo",
    "wof:placetype":"venue"
},
  "geometry": {"coordinates":[-7.2613739967,43.5743751526],"type":"Point"}
}