{
  "type": "Feature",
  "properties": {
    "addr:full":"Avda Valencia, 105 Castellon Castell\u00f3n 12005",
    "addr:housenumber":"105",
    "addr:postcode":"12005",
    "addr:street":"Avda Valencia",
    "iso:country":"ES",
    "sg:address":"Avda Valencia, 105",
    "sg:city":"Castellon",
    "sg:orig_category":"Centros Empresariales",
    "sg:phone":"+34 964 20 53 75",
    "sg:postcode":"12005",
    "sg:province":"Castell\u00f3n",
    "wof:name":"Castello Gourmet S.l.",
    "wof:placetype":"venue"
},
  "geometry": {"coordinates":[-0.0512389988,39.9737892151],"type":"Point"}
}