{
  "type": "Feature",
  "properties": {
    "addr:full":"Calle de Tordesillas, 34 Campillo Del Moro Almer\u00eda 04720",
    "addr:housenumber":"34",
    "addr:postcode":"04720",
    "addr:street":"Calle De Tordesillas",
    "iso:country":"ES",
    "sg:address":"Calle de Tordesillas, 34",
    "sg:city":"Campillo Del Moro",
    "sg:orig_category":"Inversiones",
    "sg:phone":"+34 950 34 29 04",
    "sg:postcode":"04720",
    "sg:province":"Almer\u00eda",
    "wof:name":"Gestion Y Promociones Darom S.l.",
    "wof:placetype":"venue"
},
  "geometry": {"coordinates":[-2.5974500179,36.801410675],"type":"Point"}
}