{
  "type": "Feature",
  "properties": {
    "addr:full":"Calle de General Arrando, 5 Madrid Madrid 28010",
    "addr:housenumber":"5",
    "addr:postcode":"28010",
    "addr:street":"Calle De General Arrando",
    "iso:country":"ES",
    "sg:address":"Calle de General Arrando, 5",
    "sg:city":"Madrid",
    "sg:orig_category":"Ropa Para Ni\u00d1os (al Por Menor)",
    "sg:phone":"+34 914 47 21 89",
    "sg:postcode":"28010",
    "sg:province":"Madrid",
    "sg:website":"www.e-nicolino.com",
    "wof:name":"E Nicolino S.l.",
    "wof:placetype":"venue"
},
  "geometry": {"coordinates":[-3.6964540482,40.431842804],"type":"Point"}
}