{
  "type": "Feature",
  "properties": {
    "iso:country":"ES",
    "sg:address":"Carrer de Pilar, 24",
    "sg:city":"Premia Mar",
    "sg:orig_category":"Importaci\u00d3n",
    "sg:phone":"+34 937 52 45 87",
    "sg:postcode":"08330",
    "sg:province":"Barcelona",
    "wof:name":"Nurundur Studio S.l.",
    "wof:placetype":"venue"
},
  "geometry": {"coordinates":[2.355547905,41.4933280945],"type":"Point"}
}