{
  "type": "Feature",
  "properties": {
    "addr:full":"Calle de Jaen, 27 Pozo Alcon Ja\u00e9n 23485",
    "addr:housenumber":"27",
    "addr:postcode":"23485",
    "addr:street":"Calle De Jaen;Alcon Jae\u0301N",
    "iso:country":"ES",
    "sg:address":"Calle de Jaen, 27",
    "sg:city":"Pozo Alcon",
    "sg:orig_category":"Delegados, Agentes De Tr\u00c1nsito, Auxiliares De Transporte Internacional",
    "sg:phone":"+34 953 73 82 42",
    "sg:postcode":"23485",
    "sg:province":"Ja\u00e9n",
    "wof:name":"Transportes Eliseo E Hijos S.l.",
    "wof:placetype":"venue"
},
  "geometry": {"coordinates":[-2.9342908859,37.7026977539],"type":"Point"}
}