{
  "type": "Feature",
  "properties": {
    "iso:country":"ES",
    "sg:address":"Ciutat Cooperativa, S/n",
    "sg:city":"S. Boi Llobregat",
    "sg:orig_category":"Venta, Instalaci\u00d3n De Calefacci\u00d3n",
    "sg:phone":"+34 936 30 26 80",
    "sg:postcode":"08830",
    "sg:province":"Barcelona",
    "wof:name":"Lampisteria A.mora S.l.",
    "wof:placetype":"venue"
},
  "geometry": {"coordinates":[2.0449779034,41.3480606079],"type":"Point"}
}