{
  "type": "Feature",
  "properties": {
    "iso:country":"ES",
    "sg:address":"Avda Carlos Vii, 14",
    "sg:city":"Portugalete",
    "sg:orig_category":"Agentes, Concesionarios Y Sucursales De Veh\u00cdculos",
    "sg:phone":"+34 944 83 66 72",
    "sg:postcode":"48920",
    "sg:province":"Vizcaya",
    "wof:name":"Antonio Argudo Espada ( Ford San Roque)",
    "wof:placetype":"venue"
},
  "geometry": {"coordinates":[-3.0218951702,43.3186569214],"type":"Point"}
}