{
  "type": "Feature",
  "properties": {
    "iso:country":"ES",
    "sg:address":"Carrer de Ricardo Calvo, 4",
    "sg:city":"Barcelona",
    "sg:orig_category":"M\u00c9dicos: Psiquiatr\u00cda",
    "sg:phone":"+34 932 11 26 72",
    "sg:postcode":"08022",
    "sg:province":"Barcelona",
    "wof:name":"Perez Sanchez Manuel",
    "wof:placetype":"venue"
},
  "geometry": {"coordinates":[2.1333870888,41.4031867981],"type":"Point"}
}