{
  "type": "Feature",
  "properties": {
    "iso:country":"ES",
    "sg:address":"Rio Tenorio, 5",
    "sg:city":"Rio Tenorio",
    "sg:orig_category":"Pintura, Barniz, Productos Asimilables (fabricaci\u00d3n, Al Por Mayor)",
    "sg:phone":"+34 986 76 41 65",
    "sg:postcode":"36120",
    "sg:province":"Pontevedra",
    "wof:name":"Chano Pinturas Sl",
    "wof:placetype":"venue"
},
  "geometry": {"coordinates":[-8.5576162338,42.4647750854],"type":"Point"}
}