{
  "type": "Feature",
  "properties": {
    "addr:full":"Av President Macia, 7 Fondarella Lleida 25244",
    "addr:housenumber":"7",
    "addr:postcode":"25244",
    "addr:street":"Av President Macia",
    "iso:country":"ES",
    "sg:address":"Av President Macia, 7",
    "sg:city":"Fondarella",
    "sg:orig_category":"Agentes, Concesionarios Y Sucursales De Veh\u00cdculos",
    "sg:phone":"+34 973 60 11 84",
    "sg:postcode":"25244",
    "sg:province":"Lleida",
    "wof:name":"Auto Camions Morera S.l.",
    "wof:placetype":"venue"
},
  "geometry": {"coordinates":[0.8707395792,41.629322052],"type":"Point"}
}