{
  "type": "Feature",
  "properties": {
    "iso:country":"ES",
    "sg:address":"Calle de Alcalde Suarez Llanos, 7",
    "sg:city":"Alacant",
    "sg:orig_category":"Plomeros",
    "sg:phone":"+34 965 21 23 30",
    "sg:postcode":"03012",
    "sg:province":"Alicante",
    "wof:name":"Fontaneria Marco Oliver S.l",
    "wof:placetype":"venue"
},
  "geometry": {"coordinates":[-0.4813627899,38.3539543152],"type":"Point"}
}