{
  "type": "Feature",
  "properties": {
    "iso:country":"ES",
    "sg:address":"Calle de Platanos (de Los), 2",
    "sg:city":"Arevalo",
    "sg:orig_category":"Alquiler De V\u00cddeo",
    "sg:phone":"+34 920 30 34 72",
    "sg:postcode":"05200",
    "sg:province":"\u00c1vila",
    "wof:name":"Esteban Carrascal Maria Belen",
    "wof:placetype":"venue"
},
  "geometry": {"coordinates":[-4.7212557793,41.0558815002],"type":"Point"}
}