{
  "type": "Feature",
  "properties": {
    "iso:country":"ES",
    "sg:address":"Calle de Mequinenza (cha), 3",
    "sg:city":"Madrid",
    "sg:orig_category":"Alquiler De Material Y De Programas Audiovisuales",
    "sg:phone":"+34 914 45 19 98",
    "sg:postcode":"28004",
    "sg:province":"Madrid",
    "wof:name":"Llorente Arrebola Jose Luis",
    "wof:placetype":"venue"
},
  "geometry": {"coordinates":[-3.6990947723,40.42445755],"type":"Point"}
}