{
  "type": "Feature",
  "properties": {
    "addr:full":"Av Generalitat (de La), 102 Vila-seca Tarragona 43480",
    "addr:housenumber":"102",
    "addr:postcode":"43480",
    "addr:street":"Av Generalitat De La",
    "iso:country":"ES",
    "sg:address":"Av Generalitat (de La), 102",
    "sg:city":"Vila-seca",
    "sg:orig_category":"Promotores Constructores",
    "sg:phone":"+34 977 39 41 72",
    "sg:postcode":"43480",
    "sg:province":"Tarragona",
    "wof:name":"Francesc Salvado S.l.",
    "wof:placetype":"venue"
},
  "geometry": {"coordinates":[1.1415400505,41.1120491028],"type":"Point"}
}