{
  "type": "Feature",
  "properties": {
    "addr:full":"Calle de Buenavista, 4 Majadahonda Madrid 28220",
    "addr:housenumber":"4",
    "addr:postcode":"28220",
    "addr:street":"Calle De Buenavista",
    "iso:country":"ES",
    "sg:address":"Calle de Buenavista, 4",
    "sg:city":"Majadahonda",
    "sg:orig_category":"Zapatos (al Por Menor)",
    "sg:phone":"+34 916 38 93 71",
    "sg:postcode":"28220",
    "sg:province":"Madrid",
    "wof:name":"Moreno Segura Jose Maria",
    "wof:placetype":"venue"
},
  "geometry": {"coordinates":[-3.8712983131,40.4717292786],"type":"Point"}
}