{
  "type": "Feature",
  "properties": {
    "addr:full":"Carrer de Progres, 76 Hospitalet Llobregat Barcelona 08904",
    "addr:housenumber":"76",
    "addr:postcode":"08904",
    "addr:street":"Carrer De Progres",
    "iso:country":"ES",
    "sg:address":"Carrer de Progres, 76",
    "sg:city":"Hospitalet Llobregat",
    "sg:orig_category":"Zapatos (al Por Menor)",
    "sg:phone":"+34 934 48 26 27",
    "sg:postcode":"08904",
    "sg:province":"Barcelona",
    "wof:name":"Comercial Internacional De Calzado S. A.",
    "wof:placetype":"venue"
},
  "geometry": {"coordinates":[2.1202208996,41.3730163574],"type":"Point"}
}