{
  "type": "Feature",
  "properties": {
    "addr:full":"Avda Nueve De Octubre, 12 Puerto Valencia 46520",
    "addr:housenumber":"12",
    "addr:postcode":"46520",
    "addr:street":"Avda Nueve De Octubre",
    "iso:country":"ES",
    "sg:address":"Avda Nueve De Octubre, 12",
    "sg:city":"Puerto",
    "sg:orig_category":"Librer\u00cdas",
    "sg:phone":"+34 962 67 23 33",
    "sg:postcode":"46520",
    "sg:province":"Valencia",
    "wof:name":"Gil Valles Luisa Maria",
    "wof:placetype":"venue"
},
  "geometry": {"coordinates":[-0.2201009989,39.6584396362],"type":"Point"}
}