{
  "type": "Feature",
  "properties": {
    "addr:full":"Calle de Adolfo Suarez De Figueroa, 16 Estepona M\u00e1laga 29680",
    "addr:housenumber":"16",
    "addr:postcode":"29680",
    "addr:street":"Calle De Adolfo Suarez De Figueroa",
    "iso:country":"ES",
    "sg:address":"Calle de Adolfo Suarez De Figueroa, 16",
    "sg:city":"Estepona",
    "sg:orig_category":"Agentes Generales De Seguros",
    "sg:phone":"+34 952 79 45 00",
    "sg:postcode":"29680",
    "sg:province":"M\u00e1laga",
    "sg:website":"www.ajroldan.com",
    "wof:name":"Agencia J. Roldan Estepona S.l.",
    "wof:placetype":"venue"
},
  "geometry": {"coordinates":[-5.145178318,36.426109314],"type":"Point"}
}