{
  "type": "Feature",
  "properties": {
    "iso:country":"ES",
    "sg:address":"Calle de Ezpondoa, 14",
    "sg:city":"Burlada",
    "sg:orig_category":"Lencer\u00cda Femenina, Corseter\u00cda, Trajes De Ba\u00d1o (al Por Menor)",
    "sg:phone":"+34 948 24 97 65",
    "sg:postcode":"31600",
    "sg:province":"Navarra",
    "wof:name":"Garcia Garcia Araceli",
    "wof:placetype":"venue"
},
  "geometry": {"coordinates":[-1.6183040142,42.8231468201],"type":"Point"}
}