{
  "type": "Feature",
  "properties": {
    "iso:country":"ES",
    "sg:address":"Avda Langraiz, 23",
    "sg:city":"Nanclares De La Oca",
    "sg:orig_category":"Pescader\u00cdas (al Por Menor)",
    "sg:phone":"+34 945 36 16 98",
    "sg:postcode":"01230",
    "sg:province":"\u00c1lava",
    "wof:name":"Carpintero Atienza Rosa Maria",
    "wof:placetype":"venue"
},
  "geometry": {"coordinates":[-2.8150889874,42.8163604736],"type":"Point"}
}