{
  "type": "Feature",
  "properties": {
    "addr:full":"Carrer de Alvarez De Castro, 51 Mollet Valles Barcelona 08100",
    "addr:housenumber":"51",
    "addr:postcode":"08100",
    "addr:street":"Carrer De Alvarez De Castro",
    "iso:country":"ES",
    "sg:address":"Carrer de Alvarez De Castro, 51",
    "sg:city":"Mollet Valles",
    "sg:orig_category":"Ingenier\u00cda, Centros De Estudios (diversos)",
    "sg:phone":"+34 935 70 04 74",
    "sg:postcode":"08100",
    "sg:province":"Barcelona",
    "wof:name":"Proyectos Y Aplicaciones Montajes Tecnico Industriales S.l.",
    "wof:placetype":"venue"
},
  "geometry": {"coordinates":[2.203001976,41.5415153503],"type":"Point"}
}