{
  "type": "Feature",
  "properties": {
    "iso:country":"ES",
    "sg:address":"Calle de Mayor, 79",
    "sg:city":"Madrid",
    "sg:orig_category":"Ense\u00d1anza, Formaci\u00d3n Profesional: Aprendizaje",
    "sg:phone":"+34 915 16 62 62",
    "sg:postcode":"28...",
    "sg:province":"Madrid",
    "sg:website":"www.consejo-estado.es",
    "wof:name":"Consejo De Estado",
    "wof:placetype":"venue"
},
  "geometry": {"coordinates":[-3.7139210701,40.4149475098],"type":"Point"}
}