{
  "type": "Feature",
  "properties": {
    "addr:full":"Av Constitucio, 190 Castelldefels Barcelona 08860",
    "addr:housenumber":"190",
    "addr:postcode":"08860",
    "addr:street":"Av Constitucio",
    "iso:country":"ES",
    "sg:address":"Av Constitucio, 190",
    "sg:city":"Castelldefels",
    "sg:orig_category":"Electricidad: Instaladores",
    "sg:phone":"+34 936 65 20 96",
    "sg:postcode":"08860",
    "sg:province":"Barcelona",
    "wof:name":"Martinez Vilardell Jose",
    "wof:placetype":"venue"
},
  "geometry": {"coordinates":[1.9764009714,41.2775650024],"type":"Point"}
}