{
  "type": "Feature",
  "properties": {
    "addr:full":"C/ Sant Maure, 43 Alcoi Alicante 03801",
    "addr:housenumber":"43",
    "addr:postcode":"03801",
    "addr:street":"C / Sant Maure",
    "iso:country":"ES",
    "sg:address":"C/ Sant Maure, 43",
    "sg:city":"Alcoi",
    "sg:orig_category":"Inmobiliaria (agencias)",
    "sg:phone":"+34 965 54 19 77",
    "sg:postcode":"03801",
    "sg:province":"Alicante",
    "wof:name":"Afrie S.l.",
    "wof:placetype":"venue"
},
  "geometry": {"coordinates":[-0.4749118984,38.6969261169],"type":"Point"}
}