{
  "type": "Feature",
  "properties": {
    "addr:full":"Pg Granja, 4 Caldes Malavella Girona 17455",
    "addr:housenumber":"4",
    "addr:postcode":"17455",
    "addr:street":"Pg Granja",
    "iso:country":"ES",
    "sg:address":"Pg Granja, 4",
    "sg:city":"Caldes Malavella",
    "sg:orig_category":"Empresarios",
    "sg:phone":"+34 972 47 02 24",
    "sg:postcode":"17455",
    "sg:province":"Girona",
    "wof:name":"Construccions Ramon Badenas S.l.",
    "wof:placetype":"venue"
},
  "geometry": {"coordinates":[2.8070120811,41.8343658447],"type":"Point"}
}