{
  "type": "Feature",
  "properties": {
    "iso:country":"ES",
    "sg:address":"Carrer de Ca N Oliva, 91",
    "sg:city":"Barcelona",
    "sg:orig_category":"Mec\u00c1nico Del Autom\u00d3vil",
    "sg:phone":"+34 933 13 52 32",
    "sg:postcode":"08020",
    "sg:province":"Barcelona",
    "wof:name":"Dieste Pe\u00f1a Jose",
    "wof:placetype":"venue"
},
  "geometry": {"coordinates":[2.2061600685,41.4229812622],"type":"Point"}
}