{
  "type": "Feature",
  "properties": {
    "iso:country":"ES",
    "sg:address":"Carrer de Menendez Pelayo, 30",
    "sg:city":"Molins Rei",
    "sg:orig_category":"Transportes Por Carretera: Lotes Completos, Mercanc\u00cdas Diversas",
    "sg:phone":"+34 936 80 09 53",
    "sg:postcode":"08750",
    "sg:province":"Barcelona",
    "wof:name":"Soler Diaz S.c.p.",
    "wof:placetype":"venue"
},
  "geometry": {"coordinates":[2.0164849758,41.414604187],"type":"Point"}
}