{
  "type": "Feature",
  "properties": {
    "addr:full":"Calle de Fuensanta, 79 Espinardo Murcia 30012",
    "addr:housenumber":"79",
    "addr:postcode":"30012",
    "addr:street":"Calle De Fuensanta",
    "iso:country":"ES",
    "sg:address":"Calle de Fuensanta, 79",
    "sg:city":"Espinardo",
    "sg:orig_category":"Plomeros",
    "sg:phone":"+34 968 25 71 72",
    "sg:postcode":"30012",
    "sg:province":"Murcia",
    "wof:name":"Lopez Cortes Ramon",
    "wof:placetype":"venue"
},
  "geometry": {"coordinates":[-1.1272289753,37.9738464355],"type":"Point"}
}