{
  "type": "Feature",
  "properties": {
    "iso:country":"ES",
    "sg:address":"Calle de Santa Maria, 15",
    "sg:city":"Ejea De Los Caballeros",
    "sg:orig_category":"Centros Empresariales",
    "sg:phone":"+34 976 66 39 62",
    "sg:postcode":"50600",
    "sg:province":"Zaragoza",
    "wof:name":"Otc Rial Consulting End & Ovtsurcing.s.l",
    "wof:placetype":"venue"
},
  "geometry": {"coordinates":[-1.1375039816,42.128112793],"type":"Point"}
}