{
  "type": "Feature",
  "properties": {
    "addr:full":"Calle de Via Lactea, 3 Madrid Madrid 28023",
    "addr:housenumber":"3",
    "addr:postcode":"28023",
    "addr:street":"Calle De Via Lactea",
    "iso:country":"ES",
    "sg:address":"Calle de Via Lactea, 3",
    "sg:city":"Madrid",
    "sg:orig_category":"Administradores De Bienes Y Delegados De Comunidades De Propietarios",
    "sg:phone":"+34 913 57 49 55",
    "sg:postcode":"28023",
    "sg:province":"Madrid",
    "wof:name":"Perez Yllan Manuel",
    "wof:placetype":"venue"
},
  "geometry": {"coordinates":[-3.7839338779,40.4494934082],"type":"Point"}
}