{
  "type": "Feature",
  "properties": {
    "addr:full":"Rua Severo Ochoa, 6 Vigo Pontevedra 36202",
    "addr:housenumber":"6",
    "addr:postcode":"36202",
    "addr:street":"Rua Severo Ochoa",
    "iso:country":"ES",
    "sg:address":"Rua Severo Ochoa, 6",
    "sg:city":"Vigo",
    "sg:orig_category":"Importaci\u00d3n, Exportaci\u00d3n Y Comercios De Productos Textiles",
    "sg:phone":"+34 986 23 34 95",
    "sg:postcode":"36202",
    "sg:province":"Pontevedra",
    "wof:name":"Dominguez Lorenzo Salud",
    "wof:placetype":"venue"
},
  "geometry": {"coordinates":[-8.7337837219,42.229019165],"type":"Point"}
}