{
  "type": "Feature",
  "properties": {
    "addr:full":"Via Massague, 40 Sabadell Barcelona 08202",
    "addr:housenumber":"40",
    "addr:postcode":"08202",
    "addr:street":"Via Massague",
    "iso:country":"ES",
    "sg:address":"Via Massague, 40",
    "sg:city":"Sabadell",
    "sg:orig_category":"Farmacias",
    "sg:phone":"+34 937 25 21 76",
    "sg:postcode":"08202",
    "sg:province":"Barcelona",
    "wof:name":"Blanchart Capdet Miguel",
    "wof:placetype":"venue"
},
  "geometry": {"coordinates":[2.1072320938,41.5509986877],"type":"Point"}
}