{
  "type": "Feature",
  "properties": {
    "addr:full":"Calle de Padilla, 18 Madrid Madrid 28006",
    "addr:housenumber":"18",
    "addr:postcode":"madrid;28006",
    "addr:street":"Calle De Padilla",
    "iso:country":"ES",
    "sg:address":"Calle de Padilla, 18",
    "sg:city":"Madrid",
    "sg:orig_category":"Porcelana Decorativa",
    "sg:phone":"+34 914 31 16 37",
    "sg:postcode":"28006",
    "sg:province":"Madrid",
    "sg:website":"www.piarubio.es",
    "wof:name":"Pia Rubio S.l.",
    "wof:placetype":"venue"
},
  "geometry": {"coordinates":[-3.684442997,40.4314651489],"type":"Point"}
}