{
  "type": "Feature",
  "properties": {
    "addr:full":"Calle de Ibaizabal, 25 Kurtzea Vizcaya 48960",
    "addr:housenumber":"25",
    "addr:postcode":"48960",
    "addr:street":"Calle De Ibaizabal",
    "iso:country":"ES",
    "sg:address":"Calle de Ibaizabal, 25",
    "sg:city":"Kurtzea",
    "sg:orig_category":"Muebles, Minoristas",
    "sg:phone":"+34 944 56 73 16",
    "sg:postcode":"48960",
    "sg:province":"Vizcaya",
    "wof:name":"Querejeta Brazal Igor",
    "wof:placetype":"venue"
},
  "geometry": {"coordinates":[-2.8511369228,43.2317047119],"type":"Point"}
}