{
  "type": "Feature",
  "properties": {
    "iso:country":"ES",
    "sg:address":"Calle de Gimenez Soler, 5",
    "sg:city":"Zaragoza",
    "sg:orig_category":"Alimentaci\u00d3n General (al Por Menor)",
    "sg:phone":"+34 976 55 07 25",
    "sg:postcode":"50009",
    "sg:province":"Zaragoza",
    "wof:name":"Fuentes Lopez Domingo",
    "wof:placetype":"venue"
},
  "geometry": {"coordinates":[-0.8964537978,41.6403236389],"type":"Point"}
}