{
  "type": "Feature",
  "properties": {
    "addr:full":"Calle de Vi\u00d1as (las), 22 Santurtzi Vizcaya 48980",
    "addr:housenumber":"22",
    "addr:postcode":"48980",
    "addr:street":"Calle De Vin\u0303As Las",
    "iso:country":"ES",
    "sg:address":"Calle de Vi\u00d1as (las), 22",
    "sg:city":"Santurtzi",
    "sg:orig_category":"Cooperativas Agr\u00cdcolas",
    "sg:phone":"+34 944 83 42 68",
    "sg:postcode":"48980",
    "sg:province":"Vizcaya",
    "wof:name":"Eroski Sociedad Cooperativa",
    "wof:placetype":"venue"
},
  "geometry": {"coordinates":[-3.0363249779,43.3289070129],"type":"Point"}
}