{
  "type": "Feature",
  "properties": {
    "addr:full":"C/ Sax, 30 Elche Alicante 03205",
    "addr:housenumber":"30",
    "addr:postcode":"03205",
    "addr:street":"C / Sax",
    "iso:country":"ES",
    "sg:address":"C/ Sax, 30",
    "sg:city":"Elche",
    "sg:orig_category":"Producci\u00d3n, Distribuci\u00d3n De Electricidad",
    "sg:phone":"+34 965 46 05 64",
    "sg:postcode":"03205",
    "sg:province":"Alicante",
    "wof:name":"Electricidad Gines S.l.",
    "wof:placetype":"venue"
},
  "geometry": {"coordinates":[-0.6995239854,38.2634811401],"type":"Point"}
}