{
  "type": "Feature",
  "properties": {
    "addr:full":"Calle de Llerena, 13 Sevilla Sevilla 41008",
    "addr:housenumber":"13",
    "addr:postcode":"41008",
    "addr:street":"Calle De Llerena",
    "iso:country":"ES",
    "sg:address":"Calle de Llerena, 13",
    "sg:city":"Sevilla",
    "sg:orig_category":"Material Y Suministros Para Peluquer\u00cda",
    "sg:phone":"+34 954 36 13 31",
    "sg:postcode":"41008",
    "sg:province":"Sevilla",
    "wof:name":"Estetica Profesional S.l.",
    "wof:placetype":"venue"
},
  "geometry": {"coordinates":[-5.9797801971,37.4037857056],"type":"Point"}
}