{
  "type": "Feature",
  "properties": {
    "addr:full":"Calle de Pablo Iglesias, 28 Zaragoza Zaragoza 50018",
    "addr:housenumber":"28",
    "addr:postcode":"50018",
    "addr:street":"Calle De Pablo Iglesias",
    "iso:country":"ES",
    "sg:address":"Calle de Pablo Iglesias, 28",
    "sg:city":"Zaragoza",
    "sg:orig_category":"Cer\u00c1micas: Material Y Suministros",
    "sg:phone":"+34 976 10 65 20",
    "sg:postcode":"50018",
    "sg:province":"Zaragoza",
    "sg:website":"www.bitmed.com",
    "wof:name":"Meditel Ingenieria Medica S.l.",
    "wof:placetype":"venue"
},
  "geometry": {"coordinates":[-0.8835759759,41.6772460938],"type":"Point"}
}