{
  "type": "Feature",
  "properties": {
    "iso:country":"ES",
    "sg:address":"Ptge Dormitori De Sant Francesc, 2",
    "sg:city":"Barcelona",
    "sg:orig_category":"Edici\u00d3n De Diarios, Revistas, Boletines",
    "sg:phone":"+34 933 17 51 41",
    "sg:postcode":"08002",
    "sg:province":"Barcelona",
    "sg:website":"www.men-car.com",
    "wof:name":"Publicaciones Men-car S.a.",
    "wof:placetype":"venue"
},
  "geometry": {"coordinates":[2.178426981,41.3776817322],"type":"Point"}
}