{
  "type": "Feature",
  "properties": {
    "addr:full":"Calle de Herradura, 32 Rodeo M\u00e1laga 29100",
    "addr:housenumber":"32",
    "addr:postcode":"29100",
    "addr:street":"Calle De Herradura;Ma\u0301Laga",
    "iso:country":"ES",
    "sg:address":"Calle de Herradura, 32",
    "sg:city":"Rodeo",
    "sg:orig_category":"Agencias Y Agentes Comerciales, Representantes",
    "sg:phone":"+34 952 45 01 99",
    "sg:postcode":"29100",
    "sg:province":"M\u00e1laga",
    "wof:name":"Representaciones Francisco Melendez S.l",
    "wof:placetype":"venue"
},
  "geometry": {"coordinates":[-4.7576842308,36.659740448],"type":"Point"}
}