{
  "type": "Feature",
  "properties": {
    "iso:country":"ES",
    "sg:address":"Avda Juan Carlos I, 15",
    "sg:city":"Aguilas",
    "sg:orig_category":"Venta, Alquiler Y Mantenimiento De Juegos De Sal\u00d3n O Casinos",
    "sg:phone":"+34 968 41 22 99",
    "sg:postcode":"30880",
    "sg:province":"Murcia",
    "wof:name":"Video Juegos Murcia S.l.",
    "wof:placetype":"venue"
},
  "geometry": {"coordinates":[-1.5843900442,37.4054069519],"type":"Point"}
}