{
  "type": "Feature",
  "properties": {
    "iso:country":"ES",
    "sg:address":"Calle de Ardemans, 68",
    "sg:city":"Madrid",
    "sg:orig_category":"M\u00c9dicos: Cardiolog\u00cda Y Afecciones Cardiovasculares",
    "sg:phone":"+34 913 56 76 26",
    "sg:postcode":"28028",
    "sg:province":"Madrid",
    "wof:name":"Cardiogide S.l.",
    "wof:placetype":"venue"
},
  "geometry": {"coordinates":[-3.6756334305,40.4369087219],"type":"Point"}
}