{
  "type": "Feature",
  "properties": {
    "addr:full":"Calle de Francisco Silvela, 112 Madrid Madrid 28002",
    "addr:housenumber":"112",
    "addr:postcode":"28002",
    "addr:street":"Calle De Francisco Silvela",
    "iso:country":"ES",
    "sg:address":"Calle de Francisco Silvela, 112",
    "sg:city":"Madrid",
    "sg:orig_category":"Abogados",
    "sg:phone":"+34 915 63 60 57",
    "sg:postcode":"28002",
    "sg:province":"Madrid",
    "sg:website":"www.fijetespana.org",
    "wof:name":"Garcia Brera Miguel Angel",
    "wof:placetype":"venue"
},
  "geometry": {"coordinates":[-3.6794295311,40.439491272],"type":"Point"}
}