{
  "type": "Feature",
  "properties": {
    "addr:full":"Calle de Euskalduna, 6 Barakaldo Vizcaya 48903",
    "addr:housenumber":"6",
    "addr:postcode":"48903",
    "addr:street":"Calle De Euskalduna",
    "iso:country":"ES",
    "sg:address":"Calle de Euskalduna, 6",
    "sg:city":"Barakaldo",
    "sg:orig_category":"Ortopedia General",
    "sg:phone":"+34 944 85 18 01",
    "sg:postcode":"48903",
    "sg:province":"Vizcaya",
    "wof:name":"Jose Javier Guerediaga Madariaga",
    "wof:placetype":"venue"
},
  "geometry": {"coordinates":[-2.9814679623,43.2825698853],"type":"Point"}
}