{
  "type": "Feature",
  "properties": {
    "iso:country":"ES",
    "sg:address":"Carrer de Sant Pere, 34",
    "sg:city":"Cambrils",
    "sg:orig_category":"Peluquer\u00cdas, Peluquer\u00cda Mixta",
    "sg:phone":"+34 977 36 23 54",
    "sg:postcode":"43850",
    "sg:province":"Tarragona",
    "wof:name":"Gibert Ras Maria Carmen",
    "wof:placetype":"venue"
},
  "geometry": {"coordinates":[1.0622099638,41.0661506653],"type":"Point"}
}