{
  "type": "Feature",
  "properties": {
    "addr:full":"Araba Kalea, 41 Zarautz Guip\u00f9zcoa 20800",
    "addr:housenumber":"41",
    "addr:postcode":"20800",
    "addr:street":"Araba Kalea;Guipu\u0300Zcoa",
    "iso:country":"ES",
    "sg:address":"Araba Kalea, 41",
    "sg:city":"Zarautz",
    "sg:orig_category":"Supermercados Y Hipermercados",
    "sg:phone":"+34 943 83 11 94",
    "sg:postcode":"20800",
    "sg:province":"Guip\u00f9zcoa",
    "sg:website":"www.grupoeroski.es",
    "wof:name":"Eroski Sociedad Cooperativa",
    "wof:placetype":"venue"
},
  "geometry": {"coordinates":[-2.1644120216,43.2810745239],"type":"Point"}
}