{
  "type": "Feature",
  "properties": {
    "addr:full":"Ptge Boada Vell, S/n Poligon Industrial Riera De Caldes Barcelona 08184",
    "addr:housenumber":"s / n",
    "addr:postcode":"08184",
    "addr:street":"Ptge Boada Vell;Industrial",
    "iso:country":"ES",
    "sg:address":"Ptge Boada Vell, S/n",
    "sg:city":"Poligon Industrial Riera De Caldes",
    "sg:orig_category":"Maquinaria Para Industrias Diversas",
    "sg:phone":"+34 938 64 82 96",
    "sg:postcode":"08184",
    "sg:province":"Barcelona",
    "wof:name":"Tecnologia Mecanica De La Extrusion E Inyeccion S.l.",
    "wof:placetype":"venue"
},
  "geometry": {"coordinates":[2.1748299599,41.5814590454],"type":"Point"}
}