{
  "type": "Feature",
  "properties": {
    "iso:country":"ES",
    "sg:address":"Concejo De Sarriguren, 22",
    "sg:city":"Iru\u00f1a",
    "sg:orig_category":"Profesiones M\u00c9dicas, Param\u00c9dicas",
    "sg:phone":"+34 948 26 88 05",
    "sg:postcode":"31016",
    "sg:province":"Navarra",
    "wof:name":"Jimenez Lasanta Ana",
    "wof:placetype":"venue"
},
  "geometry": {"coordinates":[-1.6187534332,42.8084068298],"type":"Point"}
}