{
  "type": "Feature",
  "properties": {
    "iso:country":"ES",
    "sg:address":"Calle de Cruz, 7",
    "sg:city":"Ciudad Real",
    "sg:orig_category":"Zapatos (al Por Menor)",
    "sg:phone":"+34 926 22 18 12",
    "sg:postcode":"13001",
    "sg:province":"Ciudad Real",
    "wof:name":"Jota Eva S. A",
    "wof:placetype":"venue"
},
  "geometry": {"coordinates":[-3.9273221493,38.9860954285],"type":"Point"}
}