{
  "type": "Feature",
  "properties": {
    "iso:country":"ES",
    "sg:address":"Calle de San Anton, 48",
    "sg:city":"Jaraba",
    "sg:classifiers":[
        {
            "category":"Taxi",
            "type":"Transportation"
        }
    ],
    "sg:phone":"+34 976 84 81 28",
    "sg:postcode":"50237",
    "sg:province":"Zaragoza",
    "wof:name":"Bueno Gonzalez Pablo",
    "wof:placetype":"venue"
},
  "geometry": {"coordinates":[-1.8826500177,41.189163208],"type":"Point"}
}