{
  "type": "Feature",
  "properties": {
    "iso:country":"ES",
    "sg:address":"Ctra Madrid, Km. 0328,3",
    "sg:city":"Jaen",
    "sg:orig_category":"Distribuci\u00d3n De Petr\u00d3leo Y Derivados",
    "sg:phone":"+34 953 28 14 22",
    "sg:postcode":"23009",
    "sg:province":"Ja\u00e9n",
    "wof:name":"Tartesia, S.l.",
    "wof:placetype":"venue"
},
  "geometry": {"coordinates":[-3.7830190659,37.7865905762],"type":"Point"}
}