{
  "type": "Feature",
  "properties": {
    "iso:country":"ES",
    "sg:address":"Pantalan, S/n",
    "sg:city":"Barri Maritim Coma-ruga",
    "sg:orig_category":"Asociaciones Y Clubs Deportivos",
    "sg:phone":"+34 977 68 01 75",
    "sg:postcode":"43880",
    "sg:province":"Tarragona",
    "wof:name":"Club Nautico De Comarruga",
    "wof:placetype":"venue"
},
  "geometry": {"coordinates":[1.5386699438,41.1833496094],"type":"Point"}
}