{
  "type": "Feature",
  "properties": {
    "addr:full":"Lanza(tiobre), 3 Lanza La Coru\u00f1a 15319",
    "addr:housenumber":"3",
    "addr:postcode":"15319",
    "addr:street":"Tiobre;Lanza La Corun\u0303A",
    "iso:country":"ES",
    "sg:address":"Lanza(tiobre), 3",
    "sg:city":"Lanza",
    "sg:orig_category":"Empresas De Carpinter\u00cda De Madera",
    "sg:phone":"+34 981 77 01 36",
    "sg:postcode":"15319",
    "sg:province":"La Coru\u00f1a",
    "wof:name":"Casanova Gonzalez Jose Luis",
    "wof:placetype":"venue"
},
  "geometry": {"coordinates":[-8.0784473419,43.3035011292],"type":"Point"}
}