{
  "type": "Feature",
  "properties": {
    "addr:full":"Calle de Fuente (la), 13 Burlada Navarra 31600",
    "addr:housenumber":"13",
    "addr:postcode":"31600",
    "addr:street":"Calle De Fuente La",
    "iso:country":"ES",
    "sg:address":"Calle de Fuente (la), 13",
    "sg:city":"Burlada",
    "sg:orig_category":"Inform\u00c1tica: Material Y Suministros",
    "sg:phone":"+34 948 13 67 65",
    "sg:postcode":"31600",
    "sg:province":"Navarra",
    "wof:name":"N-link Automatizacion Y Sistemas S.l.",
    "wof:placetype":"venue"
},
  "geometry": {"coordinates":[-1.6180069447,42.8266563416],"type":"Point"}
}