{
  "type": "Feature",
  "properties": {
    "iso:country":"ES",
    "sg:address":"Colonia Vidal, S/n",
    "sg:city":"Puig-reig",
    "sg:orig_category":"Hilaturas, Hilos Y Actividades Relacionadas",
    "sg:phone":"+34 938 38 04 01",
    "sg:postcode":"08692",
    "sg:province":"Barcelona",
    "wof:name":"Unic Inox S.l.i.",
    "wof:placetype":"venue"
},
  "geometry": {"coordinates":[1.8822699785,41.9447784424],"type":"Point"}
}