{
  "type": "Feature",
  "properties": {
    "iso:country":"ES",
    "sg:address":"Avda Oporto, 108",
    "sg:city":"Madrid",
    "sg:orig_category":"Fabricaci\u00d3n, Venta, Instalaci\u00d3n De R\u00d3tulos, De R\u00d3tulos Luminosos",
    "sg:phone":"+34 914 71 57 20",
    "sg:postcode":"28019",
    "sg:province":"Madrid",
    "wof:name":"Otero Rio Maria Angeles",
    "wof:placetype":"venue"
},
  "geometry": {"coordinates":[-3.7310190201,40.3878250122],"type":"Point"}
}