{
  "type": "Feature",
  "properties": {
    "iso:country":"ES",
    "sg:address":"Calle de Tierra, S/n",
    "sg:city":"Algeciras",
    "sg:orig_category":"Deportes Diversos",
    "sg:phone":"+34 956 57 03 02",
    "sg:postcode":"11207",
    "sg:province":"C\u00e1diz",
    "wof:name":"Club De Buceo Cies",
    "wof:placetype":"venue"
},
  "geometry": {"coordinates":[-5.4438891411,36.1126251221],"type":"Point"}
}