{
  "type": "Feature",
  "properties": {
    "iso:country":"ES",
    "sg:address":"Avda Ciudad De Barcelona, 53",
    "sg:city":"Madrid",
    "sg:orig_category":"Bazares, Art\u00cdculos De Limpieza Y De Cocina (al Por Menor)",
    "sg:phone":"+34 915 51 16 68",
    "sg:postcode":"28007",
    "sg:province":"Madrid",
    "wof:name":"Huang  Xuyong",
    "wof:placetype":"venue"
},
  "geometry": {"coordinates":[-3.677562952,40.4028434753],"type":"Point"}
}