{
  "type": "Feature",
  "properties": {
    "addr:full":"Avda Constitucion, 170 Mazarron Murcia 30870",
    "addr:housenumber":"170",
    "addr:postcode":"30870",
    "addr:street":"Avda Constitucion",
    "iso:country":"ES",
    "sg:address":"Avda Constitucion, 170",
    "sg:city":"Mazarron",
    "sg:orig_category":"Chapister\u00cda",
    "sg:phone":"+34 968 59 21 59",
    "sg:postcode":"30870",
    "sg:province":"Murcia",
    "wof:name":"Gomez Cervantes Juan Antonio",
    "wof:placetype":"venue"
},
  "geometry": {"coordinates":[-1.3098779917,37.5944366455],"type":"Point"}
}