{
  "type": "Feature",
  "properties": {
    "addr:full":"Calle de Oriental, 7 Gijon Asturias 33213",
    "addr:housenumber":"7",
    "addr:postcode":"33213",
    "addr:street":"Calle De Oriental",
    "iso:country":"ES",
    "sg:address":"Calle de Oriental, 7",
    "sg:city":"Gijon",
    "sg:orig_category":"Bazares, Art\u00cdculos De Limpieza Y De Cocina (al Por Menor)",
    "sg:phone":"+34 985 30 11 03",
    "sg:postcode":"33213",
    "sg:province":"Asturias",
    "wof:name":"Bazar Buena Suerte S.l.",
    "wof:placetype":"venue"
},
  "geometry": {"coordinates":[-5.6968002319,43.539352417],"type":"Point"}
}