{
  "type": "Feature",
  "properties": {
    "addr:full":"Polig. Ind. Bertola, S/n Jerez C\u00e1diz 11408",
    "addr:housenumber":"s / n",
    "addr:postcode":"11408",
    "addr:street":"Polig. Ind. Bertola",
    "iso:country":"ES",
    "sg:address":"Polig. Ind. Bertola, S/n",
    "sg:city":"Jerez",
    "sg:orig_category":"Veh\u00cdculos De Ocasi\u00d3n",
    "sg:phone":"+34 956 14 35 45",
    "sg:postcode":"11408",
    "sg:province":"C\u00e1diz",
    "wof:name":"Moreno Mayor Maria Jose",
    "wof:placetype":"venue"
},
  "geometry": {"coordinates":[-6.1592831612,36.6686592102],"type":"Point"}
}