{
  "type": "Feature",
  "properties": {
    "iso:country":"ES",
    "sg:address":"Calle de Benidorm, 11",
    "sg:city":"Valencia",
    "sg:orig_category":"Asesor\u00cda De Formaci\u00d3n Y Gesti\u00d3n De Personal",
    "sg:phone":"+34 963 47 00 78",
    "sg:postcode":"46015",
    "sg:province":"Valencia",
    "wof:name":"Veadecamp S.l.",
    "wof:placetype":"venue"
},
  "geometry": {"coordinates":[-0.3980920017,39.4825363159],"type":"Point"}
}