{
  "type": "Feature",
  "properties": {
    "iso:country":"ES",
    "sg:address":"Calle de Paz, La, 11",
    "sg:city":"Puig De'n Valls",
    "sg:orig_category":"Centros Empresariales",
    "sg:phone":"+34 971 31 40 96",
    "sg:postcode":"07819",
    "sg:province":"Islas Baleares",
    "wof:name":"Riera Cardona Jaime",
    "wof:placetype":"venue"
},
  "geometry": {"coordinates":[2.9117100239,39.6136398315],"type":"Point"}
}