{
  "type": "Feature",
  "properties": {
    "addr:full":"Calle de Orden (la), 6 Yeste Albacete 02480",
    "addr:housenumber":"6",
    "addr:postcode":"02480",
    "addr:street":"Calle De Orden La",
    "iso:country":"ES",
    "sg:address":"Calle de Orden (la), 6",
    "sg:city":"Yeste",
    "sg:orig_category":"Caf\u00c9s, Bares, Cervecer\u00cdas",
    "sg:phone":"+34 967 43 12 16",
    "sg:postcode":"02480",
    "sg:province":"Albacete",
    "wof:name":"Ruiz Lozano Adoracion",
    "wof:placetype":"venue"
},
  "geometry": {"coordinates":[-2.3183150291,38.368183136],"type":"Point"}
}