{
  "type": "Feature",
  "properties": {
    "addr:full":"Calle de Pages Del Corro, 145 Sevilla Sevilla 41010",
    "addr:housenumber":"145",
    "addr:postcode":"41010",
    "addr:street":"Calle De Pages Del Corro",
    "iso:country":"ES",
    "sg:address":"Calle de Pages Del Corro, 145",
    "sg:city":"Sevilla",
    "sg:orig_category":"Colchones (fabricaci\u00d3n, Al Por Mayor, Al Por Menor)",
    "sg:phone":"+34 954 45 40 54",
    "sg:postcode":"41010",
    "sg:province":"Sevilla",
    "wof:name":"Colchones Rupe S.l.",
    "wof:placetype":"venue"
},
  "geometry": {"coordinates":[-6.0007128716,37.3815536499],"type":"Point"}
}