{
  "type": "Feature",
  "properties": {
    "addr:full":"Carrer de Bergara, 5 S. Cugat Valles Barcelona 08172",
    "addr:housenumber":"5",
    "addr:postcode":"08172",
    "addr:street":"Carrer De Bergara;Barcelona",
    "iso:country":"ES",
    "sg:address":"Carrer de Bergara, 5",
    "sg:city":"S. Cugat Valles",
    "sg:orig_category":"Productos Qu\u00cdmicos (fabricaci\u00d3n, Al Por Mayor)",
    "sg:phone":"+34 935 89 20 98",
    "sg:postcode":"08172",
    "sg:province":"Barcelona",
    "wof:name":"Mirtha Pharm S. A.",
    "wof:placetype":"venue"
},
  "geometry": {"coordinates":[2.0809729099,41.4654312134],"type":"Point"}
}