{
  "type": "Feature",
  "properties": {
    "addr:full":"Avda Valdecilla, S/n Santander Cantabria 39009",
    "addr:housenumber":"s / n",
    "addr:postcode":"39009",
    "addr:street":"Avda Valdecilla",
    "iso:country":"ES",
    "sg:address":"Avda Valdecilla, S/n",
    "sg:city":"Santander",
    "sg:orig_category":"Aparcamientos (infraestructuras, Accesorios)",
    "sg:phone":"+34 942 32 26 47",
    "sg:postcode":"39009",
    "sg:province":"Cantabria",
    "wof:name":"Estacionamientos Controlados S.a.",
    "wof:placetype":"venue"
},
  "geometry": {"coordinates":[-3.8332140446,43.4551239014],"type":"Point"}
}