{
  "type": "Feature",
  "properties": {
    "iso:country":"ES",
    "sg:address":"Calle de Mariano Foronda, 34",
    "sg:city":"Cazorla",
    "sg:orig_category":"Peluqueros: De Se\u00d1oras",
    "sg:phone":"+34 953 72 03 28",
    "sg:postcode":"23470",
    "sg:province":"Ja\u00e9n",
    "wof:name":"Alcala Martinez Aurora",
    "wof:placetype":"venue"
},
  "geometry": {"coordinates":[-3.0026888847,37.9127235413],"type":"Point"}
}