{
  "type": "Feature",
  "properties": {
    "iso:country":"ES",
    "sg:address":"Urb La Regia, 39",
    "sg:city":"Dehesa Campoamor",
    "sg:orig_category":"Peluqueros: De Se\u00d1oras",
    "sg:phone":"+34 965 32 24 55",
    "sg:postcode":"03189",
    "sg:province":"Alicante",
    "wof:name":"Ventura Da Rosa Rosiclea",
    "wof:placetype":"venue"
},
  "geometry": {"coordinates":[-0.7374460101,37.948802948],"type":"Point"}
}