{
  "type": "Feature",
  "properties": {
    "iso:country":"ES",
    "sg:address":"Carrer de Sant Joan, S/n",
    "sg:city":"Rubi",
    "sg:orig_category":"Aparcamientos (infraestructuras, Accesorios)",
    "sg:phone":"+34 936 97 49 99",
    "sg:postcode":"08191",
    "sg:province":"Barcelona",
    "wof:name":"Estacionamientos Y Servicios S.a.",
    "wof:placetype":"venue"
},
  "geometry": {"coordinates":[2.0305099487,41.4905166626],"type":"Point"}
}