{
  "type": "Feature",
  "properties": {
    "iso:country":"ES",
    "sg:address":"Cobos(capela), 1",
    "sg:city":"Covos",
    "sg:orig_category":"Flores Y Plantas Naturales (al Por Mayor)",
    "sg:phone":"+34 981 45 91 81",
    "sg:postcode":"15613",
    "sg:province":"La Coru\u00f1a",
    "wof:name":"Puentes Calvo Juan",
    "wof:placetype":"venue"
},
  "geometry": {"coordinates":[-8.0707349777,43.4355812073],"type":"Point"}
}