{
  "type": "Feature",
  "properties": {
    "iso:country":"ES",
    "sg:address":"Albinoni (p I Trevenez), 2",
    "sg:city":"Malaga",
    "sg:orig_category":"Chapister\u00cda",
    "sg:phone":"+34 952 17 81 59",
    "sg:postcode":"29006",
    "sg:province":"M\u00e1laga",
    "wof:name":"Talleres Dobucar S.l.",
    "wof:placetype":"venue"
},
  "geometry": {"coordinates":[-4.5172200203,36.7170295715],"type":"Point"}
}