{
  "type": "Feature",
  "properties": {
    "addr:full":"Carr Bauza, De, 5 Soller Islas Baleares 07100",
    "addr:housenumber":"5",
    "addr:postcode":"07100",
    "addr:street":"Carr Bauza De",
    "iso:country":"ES",
    "sg:address":"Carr Bauza, De, 5",
    "sg:city":"Soller",
    "sg:orig_category":"Fabricaci\u00d3n, Importaci\u00d3n, Venta De Material De Telefon\u00cda, Peritelefon\u00cda",
    "sg:phone":"+34 971 63 81 33",
    "sg:postcode":"07100",
    "sg:province":"Islas Baleares",
    "wof:name":"Telecom Balear S.l.",
    "wof:placetype":"venue"
},
  "geometry": {"coordinates":[2.7147779465,39.7659072876],"type":"Point"}
}