{
  "type": "Feature",
  "properties": {
    "iso:country":"ES",
    "sg:address":"Calle de Canalejas, 24",
    "sg:city":"Linares",
    "sg:orig_category":"Agencias De Viajes",
    "sg:phone":"+34 953 60 19 48",
    "sg:postcode":"23700",
    "sg:province":"Ja\u00e9n",
    "sg:website":"www.linares.zafirtours.es",
    "wof:name":"Molina Martinez Manuel Jesus",
    "wof:placetype":"venue"
},
  "geometry": {"coordinates":[-3.6368398666,38.0964241028],"type":"Point"}
}