{
  "type": "Feature",
  "properties": {
    "addr:full":"Calle de Nafarroa, 3 Amorebieta Vizcaya 48340",
    "addr:housenumber":"3",
    "addr:postcode":"48340",
    "addr:street":"Calle De Nafarroa",
    "iso:country":"ES",
    "sg:address":"Calle de Nafarroa, 3",
    "sg:city":"Amorebieta",
    "sg:orig_category":"Peluquer\u00cdas, Peluquer\u00cda Mixta",
    "sg:phone":"+34 946 30 89 04",
    "sg:postcode":"48340",
    "sg:province":"Vizcaya",
    "wof:name":"Gorro\u00f1o Azueta Maria Gloria",
    "wof:placetype":"venue"
},
  "geometry": {"coordinates":[-2.7338790894,43.2192611694],"type":"Point"}
}