{
  "type": "Feature",
  "properties": {
    "iso:country":"ES",
    "sg:address":"Avda Alfonso Onceno, 29",
    "sg:city":"Guadalupe",
    "sg:orig_category":"Laboratorios Y Trabajos De Fotograf\u00cda, V\u00cddeo Y Cine",
    "sg:phone":"+34 927 15 41 93",
    "sg:postcode":"10140",
    "sg:province":"C\u00e1ceres",
    "wof:name":"Bravo Redondo Jose Luis",
    "wof:placetype":"venue"
},
  "geometry": {"coordinates":[-5.3286771774,39.4527702332],"type":"Point"}
}