{
  "type": "Feature",
  "properties": {
    "iso:country":"ES",
    "sg:address":"Rua Galicia, 7",
    "sg:city":"Ourense",
    "sg:orig_category":"Carnicer\u00cdas, Carnicer\u00cdas",
    "sg:phone":"+34 988 22 01 85",
    "sg:postcode":"32005",
    "sg:province":"Ourense",
    "wof:name":"Parente Ferreiro Jose",
    "wof:placetype":"venue"
},
  "geometry": {"coordinates":[-7.8629212379,42.330165863],"type":"Point"}
}