{
  "type": "Feature",
  "properties": {
    "iso:country":"ES",
    "sg:address":"Calle de Molino, S/n",
    "sg:city":"Hernansancho",
    "sg:orig_category":"Empresas De Carpinter\u00cda",
    "sg:phone":"+34 920 26 10 85",
    "sg:postcode":"05164",
    "sg:province":"\u00c1vila",
    "wof:name":"Gil Aldea Jose Luis",
    "wof:placetype":"venue"
},
  "geometry": {"coordinates":[-4.7292342186,40.8582763672],"type":"Point"}
}