{
  "type": "Feature",
  "properties": {
    "iso:country":"ES",
    "sg:address":"Cargadero Del Mineral, 33",
    "sg:city":"Melilla",
    "sg:orig_category":"Molduras, Junquillos, Listones Y Molduras Perforadas",
    "sg:phone":"+34 952 67 34 58",
    "sg:postcode":"52004",
    "sg:province":"Melilla",
    "wof:name":"Akodad Laarbi Mimont",
    "wof:placetype":"venue"
},
  "geometry": {"coordinates":[-2.939447403,35.2897834778],"type":"Point"}
}