{
  "type": "Feature",
  "properties": {
    "addr:full":"Avda Republica Argentina, 9 Logro\u00f1o La Rioja 26002",
    "addr:housenumber":"9",
    "addr:postcode":"26002",
    "addr:street":"Avda Republica Argentina;Rioja",
    "iso:country":"ES",
    "sg:address":"Avda Republica Argentina, 9",
    "sg:city":"Logro\u00f1o",
    "sg:orig_category":"Abogados",
    "sg:phone":"+34 941 25 83 20",
    "sg:postcode":"26002",
    "sg:province":"La Rioja",
    "wof:name":"Alda Lumbreras Angel",
    "wof:placetype":"venue"
},
  "geometry": {"coordinates":[-2.4484255314,42.4627418518],"type":"Point"}
}