{
  "type": "Feature",
  "properties": {
    "addr:full":"Plaz Barrio Vidal, 10 Salamanca Salamanca 37006",
    "addr:housenumber":"10",
    "addr:postcode":"37006",
    "addr:street":"Barrio Vidal",
    "iso:country":"ES",
    "sg:address":"Plaz Barrio Vidal, 10",
    "sg:city":"Salamanca",
    "sg:orig_category":"Bancos",
    "sg:phone":"+34 923 24 51 73",
    "sg:postcode":"37006",
    "sg:province":"Salamanca",
    "wof:name":"Caixa D'estalvis I Pensions De Barcelona",
    "wof:placetype":"venue"
},
  "geometry": {"coordinates":[-5.6670651436,40.9740638733],"type":"Point"}
}