{
  "type": "Feature",
  "properties": {
    "iso:country":"ES",
    "sg:address":"Carrer de Escorpio, 1",
    "sg:city":"Almaixada",
    "sg:orig_category":"Cr\u00cda De Animales",
    "sg:phone":"+34 965 95 63 67",
    "sg:postcode":"03110",
    "sg:province":"Alicante",
    "wof:name":"Clinica Veterinaria La Almajada",
    "wof:placetype":"venue"
},
  "geometry": {"coordinates":[-0.4602490067,38.4031295776],"type":"Point"}
}