{
  "type": "Feature",
  "properties": {
    "addr:full":"Calle de Aviles (de), 2 Fuenlabrada Madrid 28942",
    "addr:housenumber":"2",
    "addr:postcode":"28942",
    "addr:street":"Calle De Aviles De",
    "iso:country":"ES",
    "sg:address":"Calle de Aviles (de), 2",
    "sg:city":"Fuenlabrada",
    "sg:orig_category":"Sanatorios M\u00c9dico",
    "sg:phone":"+34 916 07 31 11",
    "sg:postcode":"28942",
    "sg:province":"Madrid",
    "wof:name":"Organismo Autonomo De Informatica Y Comunicaciones De La Comunidad De Madrid",
    "wof:placetype":"venue"
},
  "geometry": {"coordinates":[-3.8088469505,40.2950057983],"type":"Point"}
}