{
  "type": "Feature",
  "properties": {
    "addr:full":"Esglesia De Santa Fe, 2 Palma Islas Baleares 07001",
    "addr:postcode":"07001",
    "addr:street":"Fe",
    "iso:country":"ES",
    "sg:address":"Esglesia De Santa Fe, 2",
    "sg:city":"Palma",
    "sg:orig_category":"Molduras, Junquillos, Listones Y Molduras Perforadas",
    "sg:phone":"+34 971 71 15 62",
    "sg:postcode":"07001",
    "sg:province":"Islas Baleares",
    "wof:name":"Acosta Rodriguez Carmen",
    "wof:placetype":"venue"
},
  "geometry": {"coordinates":[2.654791832,39.5662918091],"type":"Point"}
}