{
  "type": "Feature",
  "properties": {
    "addr:full":"Plaz Ayuntamiento, 11 Valencia Valencia 46002",
    "addr:housenumber":"11",
    "addr:postcode":"46002",
    "addr:street":"Valencia",
    "iso:country":"ES",
    "sg:address":"Plaz Ayuntamiento, 11",
    "sg:city":"Valencia",
    "sg:orig_category":"Abogados",
    "sg:phone":"+34 963 50 93 80",
    "sg:postcode":"46002",
    "sg:province":"Valencia",
    "wof:name":"Iuris Abogados Coop V",
    "wof:placetype":"venue"
},
  "geometry": {"coordinates":[-0.3766379952,39.4719009399],"type":"Point"}
}