{
  "type": "Feature",
  "properties": {
    "iso:country":"ES",
    "sg:address":"Plaz Maria Agustina, 5",
    "sg:city":"Castellon",
    "sg:orig_category":"Librer\u00cdas",
    "sg:phone":"+34 964 23 40 56",
    "sg:postcode":"12003",
    "sg:province":"Castell\u00f3n",
    "wof:name":"Sanahuja Prades Enrique",
    "wof:placetype":"venue"
},
  "geometry": {"coordinates":[-0.034483999,39.9888496399],"type":"Point"}
}