{
  "type": "Feature",
  "properties": {
    "iso:country":"ES",
    "sg:address":"Calle de Asensi, 6",
    "sg:city":"Castellon",
    "sg:orig_category":"M\u00c9dicos: Neumolog\u00cda",
    "sg:phone":"+34 964 22 07 76",
    "sg:postcode":"12002",
    "sg:province":"Castell\u00f3n",
    "wof:name":"Bernat Gomez Fernando",
    "wof:placetype":"venue"
},
  "geometry": {"coordinates":[-0.0374919996,39.9831428528],"type":"Point"}
}