{
  "type": "Feature",
  "properties": {
    "iso:country":"ES",
    "sg:address":"Calle de Nueve De Mayo, 2",
    "sg:city":"Oviedo",
    "sg:orig_category":"Asesor\u00cda De Formaci\u00d3n Y Gesti\u00d3n De Personal",
    "sg:phone":"+34 985 21 69 67",
    "sg:postcode":"33002",
    "sg:province":"Asturias",
    "wof:name":"Florez Menendez Ignacio Joaquin",
    "wof:placetype":"venue"
},
  "geometry": {"coordinates":[-5.8502011299,43.3656921387],"type":"Point"}
}