{
  "type": "Feature",
  "properties": {
    "addr:full":"Calle de Cardenal Torquemada, 47 Valladolid Valladolid 47010",
    "addr:housenumber":"47",
    "addr:postcode":"47010",
    "addr:street":"Calle De Cardenal Torquemada",
    "iso:country":"ES",
    "sg:address":"Calle de Cardenal Torquemada, 47",
    "sg:city":"Valladolid",
    "sg:orig_category":"Reposter\u00cdas",
    "sg:phone":"+34 983 26 02 64",
    "sg:postcode":"47010",
    "sg:province":"Valladolid",
    "wof:name":"Sanmite S. L.",
    "wof:placetype":"venue"
},
  "geometry": {"coordinates":[-4.7217321396,41.6633872986],"type":"Point"}
}