{
  "type": "Feature",
  "properties": {
    "addr:full":"Calle de Ciudad Dolores Hidalgo, 20 Mostoles Madrid 28934",
    "addr:postcode":"28934",
    "addr:street":"Calle De Ciudad;Hidalgo 20 Mostoles",
    "iso:country":"ES",
    "sg:address":"Calle de Ciudad Dolores Hidalgo, 20",
    "sg:city":"Mostoles",
    "sg:orig_category":"Ense\u00d1anza: Profesiones Art\u00cdsticas",
    "sg:phone":"+34 916 13 12 61",
    "sg:postcode":"28934",
    "sg:province":"Madrid",
    "sg:website":"www.intermoda.net/empresa/cdmo",
    "wof:name":"Soledad Barahona Villaverde C.b.",
    "wof:placetype":"venue"
},
  "geometry": {"coordinates":[-3.8655529022,40.3205566406],"type":"Point"}
}