{
  "type": "Feature",
  "properties": {
    "iso:country":"ES",
    "sg:address":"Pg Prim, 39",
    "sg:city":"Reus",
    "sg:orig_category":"Tintes (fabricaci\u00d3n, Al Por Mayor)",
    "sg:phone":"+34 977 32 13 51",
    "sg:postcode":"43205",
    "sg:province":"Tarragona",
    "sg:website":"www.pressto.com",
    "wof:name":"Prim 39 S.l.",
    "wof:placetype":"venue"
},
  "geometry": {"coordinates":[1.1041580439,41.1500968933],"type":"Point"}
}