{
  "type": "Feature",
  "properties": {
    "iso:country":"ES",
    "sg:address":"Vall Boi, Km. 0000,5",
    "sg:city":"Pont Suert",
    "sg:orig_category":"Zonas De Acampada, Aparcamiento Para Caravanas",
    "sg:phone":"+34 973 69 05 02",
    "sg:postcode":"25520",
    "sg:province":"Lleida",
    "wof:name":"Roig Llanes Ramon",
    "wof:placetype":"venue"
},
  "geometry": {"coordinates":[0.7424060106,42.4047966003],"type":"Point"}
}