{
  "type": "Feature",
  "properties": {
    "iso:country":"ES",
    "sg:address":"Calle de Portal De Gamarra, 58",
    "sg:city":"Vitoria-gasteiz",
    "sg:orig_category":"Armer\u00cdas",
    "sg:phone":"+34 945 28 90 45",
    "sg:postcode":"01013",
    "sg:province":"\u00c1lava",
    "wof:name":"Ballestas Gasteiz S.a.",
    "wof:placetype":"venue"
},
  "geometry": {"coordinates":[-2.6639900208,42.8566169739],"type":"Point"}
}