{
  "type": "Feature",
  "properties": {
    "iso:country":"ES",
    "sg:address":"Ronda Coru\u00f1a, 50",
    "sg:city":"Melide",
    "sg:orig_category":"Notarios",
    "sg:phone":"+34 981 50 52 80",
    "sg:postcode":"15800",
    "sg:province":"La Coru\u00f1a",
    "wof:name":"Carreira Simon Maria Carmen",
    "wof:placetype":"venue"
},
  "geometry": {"coordinates":[-8.015838623,42.9156684875],"type":"Point"}
}