{
  "type": "Feature",
  "properties": {
    "iso:country":"ES",
    "sg:address":"Calle de Aguardenteros, 14",
    "sg:city":"Antequera",
    "sg:orig_category":"Ingenier\u00cda, Centros De Estudios (diversos)",
    "sg:phone":"+34 952 84 19 72",
    "sg:postcode":"29200",
    "sg:province":"M\u00e1laga",
    "wof:name":"Vidaurreta Schoendorff Francisco Javier",
    "wof:placetype":"venue"
},
  "geometry": {"coordinates":[-4.5626001358,37.0180358887],"type":"Point"}
}