{
  "type": "Feature",
  "properties": {
    "addr:full":"Carrer de Colon, 33 Valls Tarragona 43800",
    "addr:housenumber":"33",
    "addr:postcode":"43800",
    "addr:street":"Carrer De Colon",
    "iso:country":"ES",
    "sg:address":"Carrer de Colon, 33",
    "sg:city":"Valls",
    "sg:orig_category":"Masajistas Kinesiterapeutas",
    "sg:phone":"+34 977 60 67 52",
    "sg:postcode":"43800",
    "sg:province":"Tarragona",
    "wof:name":"Pasalagua Esteve Nuria",
    "wof:placetype":"venue"
},
  "geometry": {"coordinates":[1.2544549704,41.2871818542],"type":"Point"}
}