{
  "type": "Feature",
  "properties": {
    "addr:full":"Carrer de Gravina, 1 S. Adria Besos Barcelona 08930",
    "addr:housenumber":"1",
    "addr:postcode":"08930",
    "addr:street":"Carrer De Gravina;Barcelona",
    "iso:country":"ES",
    "sg:address":"Carrer de Gravina, 1",
    "sg:city":"S. Adria Besos",
    "sg:orig_category":"Perfumer\u00cda Y Cosm\u00c9tica (fabricaci\u00d3n, Al Por Mayor)",
    "sg:phone":"+34 934 62 03 66",
    "sg:postcode":"08930",
    "sg:province":"Barcelona",
    "wof:name":"Marcas Y Servicios De Cosmetica S.a.",
    "wof:placetype":"venue"
},
  "geometry": {"coordinates":[2.2288100719,41.4301986694],"type":"Point"}
}