{
  "type": "Feature",
  "properties": {
    "iso:country":"ES",
    "sg:address":"Avda Gran Via Tarrega Monteblanco, 17",
    "sg:city":"Castellon",
    "sg:classifiers":[
        {
            "category":"Banks & Credit Unions",
            "subcategory":"Bureau De Change",
            "type":"Services"
        }
    ],
    "sg:phone":"+34 964 26 14 15",
    "sg:postcode":"12006",
    "sg:province":"Castell\u00f3n",
    "sg:tags":[
        "organismos",
        "control"
    ],
    "wof:name":"3 Sercal S.l.l.",
    "wof:placetype":"venue"
},
  "geometry": {"coordinates":[-0.050488,39.981567],"type":"Point"}
}