{
  "type": "Feature",
  "properties": {
    "addr:full":"Calle de Santo Tomas, 5 Vinaros Castell\u00f3n 12500",
    "addr:housenumber":"5",
    "addr:postcode":"12500",
    "addr:street":"Calle De Santo Tomas",
    "iso:country":"ES",
    "sg:address":"Calle de Santo Tomas, 5",
    "sg:city":"Vinaros",
    "sg:orig_category":"Confecci\u00d3n De Trajes Para Se\u00d1oras",
    "sg:phone":"+34 964 40 76 14",
    "sg:postcode":"12500",
    "sg:province":"Castell\u00f3n",
    "wof:name":"Itarte Sanchez Estefania",
    "wof:placetype":"venue"
},
  "geometry": {"coordinates":[0.4749450088,40.4711990356],"type":"Point"}
}