{
  "type": "Feature",
  "properties": {
    "iso:country":"ES",
    "sg:address":"Pagesos, S/n",
    "sg:city":"Ciutadella Menorca",
    "sg:orig_category":"Marroquiner\u00cda (confecci\u00d3n)",
    "sg:phone":"+34 971 48 27 42",
    "sg:postcode":"07760",
    "sg:province":"Islas Baleares",
    "wof:name":"Pell Grup Menorca S.l.",
    "wof:placetype":"venue"
},
  "geometry": {"coordinates":[3.8606600761,40.0080833435],"type":"Point"}
}