{
  "type": "Feature",
  "properties": {
    "iso:country":"ES",
    "sg:address":"Calle de Alfredo Atienza, 182",
    "sg:city":"Roda",
    "sg:orig_category":"Aceites Y Grasas Alimentarias (fabricaci\u00d3n, Al Por Mayor)",
    "sg:phone":"+34 967 44 53 86",
    "sg:postcode":"02630",
    "sg:province":"Albacete",
    "wof:name":"Suministros Ceramicas La Roda S L",
    "wof:placetype":"venue"
},
  "geometry": {"coordinates":[-2.1379652023,39.1948280334],"type":"Point"}
}