{
  "type": "Feature",
  "properties": {
    "addr:full":"Ba\u00f1il O, 19 Lians A Coru\u00f1a 15179",
    "addr:housenumber":"19",
    "addr:postcode":"15179",
    "addr:street":"O;Corun\u0303A",
    "iso:country":"ES",
    "sg:address":"Ba\u00f1il O, 19",
    "sg:city":"Lians",
    "sg:orig_category":"Empresarios",
    "sg:phone":"+34 981 61 49 27",
    "sg:postcode":"15179",
    "sg:province":"A Coru\u00f1a",
    "wof:name":"Vazquez Garcia Francisco",
    "wof:placetype":"venue"
},
  "geometry": {"coordinates":[-8.3459596634,43.3464698792],"type":"Point"}
}