{
  "type": "Feature",
  "properties": {
    "addr:full":"Carrer de Fontrodona, 1 Barcelona Barcelona 08004",
    "addr:housenumber":"1",
    "addr:postcode":"08004",
    "addr:street":"Carrer De Fontrodona",
    "iso:country":"ES",
    "sg:address":"Carrer de Fontrodona, 1",
    "sg:city":"Barcelona",
    "sg:orig_category":"Cajas De Ahorro",
    "sg:phone":"+34 933 29 49 05",
    "sg:postcode":"08004",
    "sg:province":"Barcelona",
    "sg:website":"www.lacaixa.es",
    "wof:name":"Caixa D'estalvis I Pensions De Barcelona",
    "wof:placetype":"venue"
},
  "geometry": {"coordinates":[2.1678938866,41.3747215271],"type":"Point"}
}