{
  "type": "Feature",
  "properties": {
    "addr:full":"Calle de Escuelas, 21 Valdepe\u00f1as Ciudad Real 13300",
    "addr:housenumber":"21",
    "addr:postcode":"13300",
    "addr:street":"Calle De Escuelas",
    "iso:country":"ES",
    "sg:address":"Calle de Escuelas, 21",
    "sg:city":"Valdepe\u00f1as",
    "sg:orig_category":"Electricidad, Electr\u00d3nica: Suministros (al Por Menor)",
    "sg:phone":"+34 926 34 78 05",
    "sg:postcode":"13300",
    "sg:province":"Ciudad Real",
    "wof:name":"Casa Luz S.a.",
    "wof:placetype":"venue"
},
  "geometry": {"coordinates":[-3.3864760399,38.760635376],"type":"Point"}
}