{
  "type": "Feature",
  "properties": {
    "addr:full":"Calle de Manteo, 3 Donostia-san Sebastian Guip\u00f9zcoa 20013",
    "addr:housenumber":"3",
    "addr:postcode":"20013",
    "addr:street":"Calle De Manteo",
    "iso:country":"ES",
    "sg:address":"Calle de Manteo, 3",
    "sg:city":"Donostia-san Sebastian",
    "sg:orig_category":"Peluqueros: De Se\u00d1oras",
    "sg:phone":"+34 943 29 27 50",
    "sg:postcode":"20013",
    "sg:province":"Guip\u00f9zcoa",
    "wof:name":"Ruiz Vadillo Jose Luis",
    "wof:placetype":"venue"
},
  "geometry": {"coordinates":[-1.9679479599,43.3260002136],"type":"Point"}
}