{
  "type": "Feature",
  "properties": {
    "addr:full":"Calle de El Arroyo, 8 Balmaseda Vizcaya 48800",
    "addr:housenumber":"8",
    "addr:postcode":"48800",
    "addr:street":"Calle De El Arroyo",
    "iso:country":"ES",
    "sg:address":"Calle de El Arroyo, 8",
    "sg:city":"Balmaseda",
    "sg:orig_category":"Empresas De Limpieza",
    "sg:phone":"+34 946 80 17 79",
    "sg:postcode":"48800",
    "sg:province":"Vizcaya",
    "wof:name":"Servicio Enkarterri S.l.",
    "wof:placetype":"venue"
},
  "geometry": {"coordinates":[-3.1949388981,43.1978416443],"type":"Point"}
}