{
  "type": "Feature",
  "properties": {
    "addr:full":"Calle de Santa Margarita, S/n Torre Mar M\u00e1laga 29740",
    "addr:housenumber":"s / n",
    "addr:postcode":"29740",
    "addr:street":"Calle De Santa Margarita;Ma\u0301Laga",
    "iso:country":"ES",
    "sg:address":"Calle de Santa Margarita, S/n",
    "sg:city":"Torre Mar",
    "sg:orig_category":"Agencias Y Agentes Comerciales, Representantes",
    "sg:phone":"+34 952 54 12 59",
    "sg:postcode":"29740",
    "sg:province":"M\u00e1laga",
    "wof:name":"Pormociones Y Construcciones Araguez S.l.",
    "wof:placetype":"venue"
},
  "geometry": {"coordinates":[-4.0942540169,36.7418861389],"type":"Point"}
}