{
  "type": "Feature",
  "properties": {
    "addr:full":"Calle de Buenavista, 23 Zujaira Granada 18291",
    "addr:housenumber":"23",
    "addr:postcode":"18291",
    "addr:street":"Calle De Buenavista",
    "iso:country":"ES",
    "sg:address":"Calle de Buenavista, 23",
    "sg:city":"Zujaira",
    "sg:orig_category":"Trabajos De Aislamiento T\u00c9rmico Y Ac\u00dastico",
    "sg:phone":"+34 958 46 19 40",
    "sg:postcode":"18291",
    "sg:province":"Granada",
    "wof:name":"Refuja S.l",
    "wof:placetype":"venue"
},
  "geometry": {"coordinates":[-3.8054015636,37.2564086914],"type":"Point"}
}