{
  "type": "Feature",
  "properties": {
    "iso:country":"ES",
    "sg:address":"Calle de San Antonio, 73",
    "sg:city":"Mislata",
    "sg:orig_category":"Centros De Coordinaci\u00d3n",
    "sg:phone":"+34 963 83 75 15",
    "sg:postcode":"46920",
    "sg:province":"Valencia",
    "wof:name":"Olmos Navarro Ana Maria",
    "wof:placetype":"venue"
},
  "geometry": {"coordinates":[-0.4180339873,39.4759864807],"type":"Point"}
}