{
  "type": "Feature",
  "properties": {
    "addr:full":"Calle de Francisco De Medina Y Mendoza, 16 Cabanillas Campo Guadalajara 19171",
    "addr:housenumber":"16",
    "addr:postcode":"19171",
    "addr:street":"Calle De Francisco De Medina Y Mendoza",
    "iso:country":"ES",
    "sg:address":"Calle de Francisco De Medina Y Mendoza, 16",
    "sg:city":"Cabanillas Campo",
    "sg:orig_category":"Escayola Y Productos De Escayola (fabricaci\u00d3n, Al Por Mayor)",
    "sg:phone":"+34 949 20 15 25",
    "sg:postcode":"19171",
    "sg:province":"Guadalajara",
    "wof:name":"Decoracion Escayolas Guadalajara S.a.",
    "wof:placetype":"venue"
},
  "geometry": {"coordinates":[-3.2065179348,40.617603302],"type":"Point"}
}