{
  "type": "Feature",
  "properties": {
    "addr:full":"Calle de Alicante, 43 Mairena Aljarafe Sevilla 41927",
    "addr:housenumber":"43",
    "addr:postcode":"41927",
    "addr:street":"Calle De Alicante",
    "iso:country":"ES",
    "sg:address":"Calle de Alicante, 43",
    "sg:city":"Mairena Aljarafe",
    "sg:orig_category":"Venta, Localizaci\u00d3n, Reparaci\u00d3n De Material E Instrumental M\u00c9dico",
    "sg:phone":"+34 954 76 36 47",
    "sg:postcode":"41927",
    "sg:province":"Sevilla",
    "wof:name":"Ingenieria Medica S.l.",
    "wof:placetype":"venue"
},
  "geometry": {"coordinates":[-6.03891325,37.3546066284],"type":"Point"}
}