{
  "type": "Feature",
  "properties": {
    "addr:full":"Avda Puntarron, S/n Puntarron Murcia 30835",
    "addr:housenumber":"s",
    "addr:postcode":"30835",
    "addr:street":"Avda Puntarron;/ N",
    "iso:country":"ES",
    "sg:address":"Avda Puntarron, S/n",
    "sg:city":"Puntarron",
    "sg:orig_category":"Maquinaria Para Industrias Diversas",
    "sg:phone":"+34 968 80 45 16",
    "sg:postcode":"30835",
    "sg:province":"Murcia",
    "wof:name":"Jesus Valverde Marin Y Otros Cdad.",
    "wof:placetype":"venue"
},
  "geometry": {"coordinates":[-1.2273789644,37.9609642029],"type":"Point"}
}