{
  "type": "Feature",
  "properties": {
    "addr:full":"Calle de Obispo Huarte, 8 Leitza Navarra 31880",
    "addr:housenumber":"8",
    "addr:postcode":"31880",
    "addr:street":"Calle De Obispo Huarte",
    "iso:country":"ES",
    "sg:address":"Calle de Obispo Huarte, 8",
    "sg:city":"Leitza",
    "sg:classifiers":[
        {
            "category":"Autos & Motor Vehicles",
            "subcategory":"Automobile Sales",
            "type":"Retail Goods"
        }
    ],
    "sg:phone":"+34 948 51 03 38",
    "sg:postcode":"31880",
    "sg:province":"Navarra",
    "wof:name":"Auto-escuela Plaza S. L.",
    "wof:placetype":"venue"
},
  "geometry": {"coordinates":[-1.9162960052,43.0793151855],"type":"Point"}
}