{
  "type": "Feature",
  "properties": {
    "addr:full":"Rua Rafael Alberti, 1 Fonteculler La Coru\u00f1a 15174",
    "addr:housenumber":"1",
    "addr:postcode":"15174",
    "addr:street":"Rua Rafael Alberti;La Corun\u0303A",
    "iso:country":"ES",
    "sg:address":"Rua Rafael Alberti, 1",
    "sg:city":"Fonteculler",
    "sg:orig_category":"Promotores Constructores",
    "sg:phone":"+34 981 66 15 56",
    "sg:postcode":"15174",
    "sg:province":"La Coru\u00f1a",
    "wof:name":"Garango Construcciones S.l.",
    "wof:placetype":"venue"
},
  "geometry": {"coordinates":[-8.3959693909,43.3714904785],"type":"Point"}
}