{
  "type": "Feature",
  "properties": {
    "iso:country":"ES",
    "sg:address":"Av Salle (la), 39",
    "sg:city":"Reus",
    "sg:orig_category":"Bazares, Art\u00cdculos De Limpieza Y De Cocina (al Por Menor)",
    "sg:phone":"+34 977 75 49 76",
    "sg:postcode":"43205",
    "sg:province":"Tarragona",
    "wof:name":"Bazar Micronesia S.l.",
    "wof:placetype":"venue"
},
  "geometry": {"coordinates":[1.107763052,41.1482696533],"type":"Point"}
}