{
  "type": "Feature",
  "properties": {
    "iso:country":"ES",
    "sg:address":"Calle de San Julian, 2",
    "sg:city":"Olmedo",
    "sg:orig_category":"Ingenier\u00cda, Centros De Estudios (diversos)",
    "sg:phone":"+34 983 60 01 49",
    "sg:postcode":"47410",
    "sg:province":"Valladolid",
    "wof:name":"Araque Cuenca Jose Luis",
    "wof:placetype":"venue"
},
  "geometry": {"coordinates":[-4.6854524612,41.2875595093],"type":"Point"}
}