{
  "type": "Feature",
  "properties": {
    "iso:country":"ES",
    "sg:address":"Calle de Tenerife, S/n",
    "sg:city":"Casas Nuevas",
    "sg:orig_category":"Quincaller\u00cda (al Por Menor)",
    "sg:phone":"+34 928 13 01 10",
    "sg:postcode":"35214",
    "sg:province":"Las Palmas",
    "wof:name":"Ferrocosta Melenara S.l.",
    "wof:placetype":"venue"
},
  "geometry": {"coordinates":[-15.390089035,27.9938850403],"type":"Point"}
}