{
  "type": "Feature",
  "properties": {
    "iso:country":"ES",
    "sg:address":"Avd. Bellavista, 28",
    "sg:city":"Urbanizacion Las Jaras",
    "sg:orig_category":"Ense\u00d1anza: Comercio, Gesti\u00d3n, Inform\u00c1tica",
    "sg:phone":"+34 957 73 90 36",
    "sg:postcode":"14029",
    "sg:province":"C\u00f3rdoba",
    "wof:name":"Minguez Correas Ignacio",
    "wof:placetype":"venue"
},
  "geometry": {"coordinates":[-4.849366188,37.9660682678],"type":"Point"}
}