{
  "type": "Feature",
  "properties": {
    "iso:country":"ES",
    "sg:address":"P. Industrial, 3",
    "sg:city":"Melilla",
    "sg:orig_category":"Electricidad Veh\u00cdculo",
    "sg:phone":"+34 952 67 37 11",
    "sg:postcode":"52006",
    "sg:province":"Melilla",
    "wof:name":"Perez Castro Antonio",
    "wof:placetype":"venue"
},
  "geometry": {"coordinates":[-2.9383699894,35.2764587402],"type":"Point"}
}