{
  "type": "Feature",
  "properties": {
    "iso:country":"ES",
    "sg:address":"Calle de Doctor Esquerdo, 12",
    "sg:city":"Valladolid",
    "sg:orig_category":"Mercer\u00cda, Lencer\u00cda (al Por Menor)",
    "sg:phone":"+34 983 26 42 34",
    "sg:postcode":"47011",
    "sg:province":"Valladolid",
    "wof:name":"Martinez Martinez Milagros",
    "wof:placetype":"venue"
},
  "geometry": {"coordinates":[-4.7166156769,41.6594467163],"type":"Point"}
}