{
  "type": "Feature",
  "properties": {
    "iso:country":"ES",
    "sg:address":"Plaz Gibaxa (de), 2",
    "sg:city":"Utrera",
    "sg:orig_category":"Centros De Educaci\u00d3n Especial",
    "sg:phone":"+34 955 86 32 80",
    "sg:postcode":"41710",
    "sg:province":"Sevilla",
    "wof:name":"Asociacion Protectora Utrerana De Subnormales",
    "wof:placetype":"venue"
},
  "geometry": {"coordinates":[-5.7816224098,37.1834068298],"type":"Point"}
}