{
  "type": "Feature",
  "properties": {
    "iso:country":"ES",
    "sg:address":"Barr Intzuntza, 22",
    "sg:city":"Intzuntza",
    "sg:orig_category":"Pescader\u00cdas (al Por Menor)",
    "sg:phone":"+34 946 31 35 95",
    "sg:postcode":"48330",
    "sg:province":"Vizcaya",
    "wof:name":"Ortuzar Tabernilla A. Y Otro C.b.",
    "wof:placetype":"venue"
},
  "geometry": {"coordinates":[-2.7691090107,43.2078361511],"type":"Point"}
}