{
  "type": "Feature",
  "properties": {
    "addr:full":"Pol Montfulla, 2 Bescano Girona 17162",
    "addr:housenumber":"2",
    "addr:postcode":"17162",
    "addr:street":"Montfulla",
    "iso:country":"ES",
    "sg:address":"Pol Montfulla, 2",
    "sg:city":"Bescano",
    "sg:orig_category":"Art\u00cdculos De Madera (fabricaci\u00d3n Y Al Por Mayor)",
    "sg:phone":"+34 972 23 49 47",
    "sg:postcode":"17162",
    "sg:province":"Girona",
    "wof:name":"Interiorisme Europeu S.l.",
    "wof:placetype":"venue"
},
  "geometry": {"coordinates":[2.7389600277,41.9652786255],"type":"Point"}
}