{
  "type": "Feature",
  "properties": {
    "iso:country":"ES",
    "sg:address":"Calle de Cuevas (las), S/n",
    "sg:city":"Guaza",
    "sg:orig_category":"Masajistas Kinesiterapeutas",
    "sg:phone":"+34 922 16 92 12",
    "sg:postcode":"38627",
    "sg:province":"Santa Cruz De Tenerife",
    "wof:name":"Gutierrez Rodriguez Maria De La Antigua",
    "wof:placetype":"venue"
},
  "geometry": {"coordinates":[-16.6762466431,28.0509147644],"type":"Point"}
}