{
  "type": "Feature",
  "properties": {
    "addr:full":"Carr Major, 14 Sort Lleida 25560",
    "addr:housenumber":"14",
    "addr:postcode":"25560",
    "addr:street":"Carr Major",
    "iso:country":"ES",
    "sg:address":"Carr Major, 14",
    "sg:city":"Sort",
    "sg:orig_category":"Estancos",
    "sg:phone":"+34 973 62 00 45",
    "sg:postcode":"25560",
    "sg:province":"Lleida",
    "wof:name":"Gabriel Lliset Robert",
    "wof:placetype":"venue"
},
  "geometry": {"coordinates":[1.1305099726,42.4115371704],"type":"Point"}
}