{
  "type": "Feature",
  "properties": {
    "addr:full":"Paseo Bombe, 3 Muros La Coru\u00f1a 15250",
    "addr:housenumber":"3",
    "addr:postcode":"15250",
    "addr:street":"Paseo Bombe;La Corun\u0303A",
    "iso:country":"ES",
    "sg:address":"Paseo Bombe, 3",
    "sg:city":"Muros",
    "sg:orig_category":"M\u00c9dicos: Estomatolog\u00cda",
    "sg:phone":"+34 981 76 22 48",
    "sg:postcode":"15250",
    "sg:province":"La Coru\u00f1a",
    "wof:name":"Castro Varela Andres Calixto",
    "wof:placetype":"venue"
},
  "geometry": {"coordinates":[-9.0576505661,42.7748222351],"type":"Point"}
}