{
  "type": "Feature",
  "properties": {
    "iso:country":"ES",
    "sg:address":"Calle de Rodriguez Vega, 12",
    "sg:city":"Madrid",
    "sg:orig_category":"Prot\u00c9sicos Dentales",
    "sg:phone":"+34 914 61 99 50",
    "sg:postcode":"28025",
    "sg:province":"Madrid",
    "wof:name":"Mardones San Jose Victor",
    "wof:placetype":"venue"
},
  "geometry": {"coordinates":[-3.7273440361,40.3839302063],"type":"Point"}
}