{
  "type": "Feature",
  "properties": {
    "addr:full":"Avda Ordo\u00d1o Ii, 12 Le\u00f3n Le\u00f3n 24001",
    "addr:housenumber":"12",
    "addr:postcode":"24001",
    "addr:street":"Avda Ordon\u0303O Ii;Leo\u0301N",
    "iso:country":"ES",
    "sg:address":"Avda Ordo\u00d1o Ii, 12",
    "sg:city":"Le\u00f3n",
    "sg:orig_category":"Abogados",
    "sg:phone":"+34 987 22 51 11",
    "sg:postcode":"24001",
    "sg:province":"Le\u00f3n",
    "wof:name":"Martinez Fariza Carlos",
    "wof:placetype":"venue"
},
  "geometry": {"coordinates":[-5.5744028091,42.597278595],"type":"Point"}
}