{
  "type": "Feature",
  "properties": {
    "iso:country":"ES",
    "sg:address":"Avgd Pais Valencia, 49",
    "sg:city":"Betera",
    "sg:orig_category":"Librer\u00cdas",
    "sg:phone":"+34 961 60 14 88",
    "sg:postcode":"46117",
    "sg:province":"Valencia",
    "wof:name":"Bolea Pontevedra Maria Teresa",
    "wof:placetype":"venue"
},
  "geometry": {"coordinates":[-0.4638009965,39.589805603],"type":"Point"}
}