{
  "type": "Feature",
  "properties": {
    "addr:full":"Carrer de Castell, 2 Reus Tarragona 43201",
    "addr:housenumber":"2",
    "addr:postcode":"43201",
    "addr:street":"Carrer De Castell",
    "iso:country":"ES",
    "sg:address":"Carrer de Castell, 2",
    "sg:city":"Reus",
    "sg:orig_category":"Administradores De Bienes Y Delegados De Comunidades De Propietarios",
    "sg:phone":"+34 977 34 35 81",
    "sg:postcode":"43201",
    "sg:province":"Tarragona",
    "wof:name":"Torres Carrion Jordi",
    "wof:placetype":"venue"
},
  "geometry": {"coordinates":[1.1092040539,41.1550292969],"type":"Point"}
}