{
  "type": "Feature",
  "properties": {
    "iso:country":"ES",
    "sg:address":"Calle de Maria Parodi, 2",
    "sg:city":"Torrevieja",
    "sg:orig_category":"Bisuter\u00cda, Joyer\u00cda, Relojer\u00cda (al Por Menor)",
    "sg:phone":"+34 965 71 12 65",
    "sg:postcode":"03180",
    "sg:province":"Alicante",
    "wof:name":"Hernandez Mijares Trinidad",
    "wof:placetype":"venue"
},
  "geometry": {"coordinates":[-0.6802020073,37.9765548706],"type":"Point"}
}