{
  "type": "Feature",
  "properties": {
    "iso:country":"ES",
    "sg:address":"Ctra. Quero, S/n",
    "sg:city":"Villafranca Caballeros",
    "sg:orig_category":"M\u00c9dicos: Termomedicina (hidrolog\u00cda Y Climatolog\u00cda M\u00c9dicas)",
    "sg:phone":"+34 926 57 83 01",
    "sg:postcode":"45730",
    "sg:province":"Toledo",
    "wof:name":"Balneario Las Palmeras S.l",
    "wof:placetype":"venue"
},
  "geometry": {"coordinates":[-3.3565769196,39.4263534546],"type":"Point"}
}