{
  "type": "Feature",
  "properties": {
    "iso:country":"ES",
    "sg:address":"Calle de Reina Fabiola, 3",
    "sg:city":"Aguadulce",
    "sg:orig_category":"Doctores En Medicina",
    "sg:phone":"+34 950 34 62 95",
    "sg:postcode":"04720",
    "sg:province":"Almer\u00eda",
    "wof:name":"Apellaniz Garcia Jose Miguel",
    "wof:placetype":"venue"
},
  "geometry": {"coordinates":[-2.5789012909,36.806968689],"type":"Point"}
}