{
  "type": "Feature",
  "properties": {
    "addr:full":"Calle de Laguna, 14 Ciudad Rodrigo Salamanca 37500",
    "addr:housenumber":"14",
    "addr:postcode":"37500",
    "addr:street":"Calle De Laguna",
    "iso:country":"ES",
    "sg:address":"Calle de Laguna, 14",
    "sg:city":"Ciudad Rodrigo",
    "sg:orig_category":"Arquitectos",
    "sg:phone":"+34 923 46 24 93",
    "sg:postcode":"37500",
    "sg:province":"Salamanca",
    "wof:name":"Oficina Tecnica Mirobriga C.b.",
    "wof:placetype":"venue"
},
  "geometry": {"coordinates":[-6.5278811455,40.599155426],"type":"Point"}
}