{
  "type": "Feature",
  "properties": {
    "iso:country":"ES",
    "sg:address":"Carrer de Castell D'en Planes, 6",
    "sg:city":"Vic",
    "sg:orig_category":"Inform\u00c1tica: Soportes De Informaci\u00d3n, Suministros & Accesorios",
    "sg:phone":"+34 938 86 01 95",
    "sg:postcode":"08500",
    "sg:province":"Barcelona",
    "wof:name":"Enbagri S.l.",
    "wof:placetype":"venue"
},
  "geometry": {"coordinates":[2.2473978996,41.9356575012],"type":"Point"}
}