{
  "type": "Feature",
  "properties": {
    "iso:country":"ES",
    "sg:address":"Calle de Vallehermoso, 48",
    "sg:city":"Madrid",
    "sg:orig_category":"Contenedores (mercanc\u00cdas)",
    "sg:phone":"+34 914 48 33 19",
    "sg:postcode":"28015",
    "sg:province":"Madrid",
    "wof:name":"Garcia Rodriguez Candido",
    "wof:placetype":"venue"
},
  "geometry": {"coordinates":[-3.7083780766,40.435508728],"type":"Point"}
}