{
  "type": "Feature",
  "properties": {
    "addr:full":"Calle de Barones De Alcahali, 34 Foios Valencia 46134",
    "addr:housenumber":"34",
    "addr:postcode":"46134",
    "addr:street":"Calle De Barones De Alcahali",
    "iso:country":"ES",
    "sg:address":"Calle de Barones De Alcahali, 34",
    "sg:city":"Foios",
    "sg:orig_category":"Transportes Internacionales",
    "sg:phone":"+34 961 49 61 43",
    "sg:postcode":"46134",
    "sg:province":"Valencia",
    "wof:name":"Trans Dimegui S.l.",
    "wof:placetype":"venue"
},
  "geometry": {"coordinates":[-0.3542413116,39.539516449],"type":"Point"}
}