{
  "type": "Feature",
  "properties": {
    "addr:full":"Calle de Eugenio Gross, 5 Malaga M\u00e1laga 29010",
    "addr:housenumber":"5",
    "addr:postcode":"29010",
    "addr:street":"Calle De Eugenio Gross;Ma\u0301Laga",
    "iso:country":"ES",
    "sg:address":"Calle de Eugenio Gross, 5",
    "sg:city":"Malaga",
    "sg:orig_category":"Zapatos (al Por Menor)",
    "sg:phone":"+34 952 27 54 43",
    "sg:postcode":"29010",
    "sg:province":"M\u00e1laga",
    "wof:name":"Caro Guzman Adelaida",
    "wof:placetype":"venue"
},
  "geometry": {"coordinates":[-4.435904026,36.722530365],"type":"Point"}
}