{
  "type": "Feature",
  "properties": {
    "addr:full":"Pg Fabra I Puig, 266 Barcelona Barcelona 08031",
    "addr:housenumber":"266",
    "addr:postcode":"08031",
    "addr:street":"Pg Fabra I Puig",
    "iso:country":"ES",
    "sg:address":"Pg Fabra I Puig, 266",
    "sg:city":"Barcelona",
    "sg:orig_category":"Carnicer\u00cdas, Carnicer\u00cdas",
    "sg:phone":"+34 934 08 13 90",
    "sg:postcode":"08031",
    "sg:province":"Barcelona",
    "wof:name":"Tiendas Especializadas Lopez Torrecillas S.l.",
    "wof:placetype":"venue"
},
  "geometry": {"coordinates":[2.1742649078,41.430519104],"type":"Point"}
}