{
  "type": "Feature",
  "properties": {
    "addr:full":"Calle de Chopo (del), 5 Puebla Alfinden Zaragoza 50171",
    "addr:housenumber":"5",
    "addr:postcode":"50171",
    "addr:street":"Calle De Chopo Del;Alfinden",
    "iso:country":"ES",
    "sg:address":"Calle de Chopo (del), 5",
    "sg:city":"Puebla Alfinden",
    "sg:orig_category":"Motores Diessel",
    "sg:phone":"+34 976 10 81 28",
    "sg:postcode":"50171",
    "sg:province":"Zaragoza",
    "wof:name":"Motores Hatz Espa\u00f1a S.r.l.",
    "wof:placetype":"venue"
},
  "geometry": {"coordinates":[-0.7553533912,41.6396369934],"type":"Point"}
}