{
  "type": "Feature",
  "properties": {
    "iso:country":"ES",
    "sg:address":"Chapistas (p I Huerto Ordo\u00f1ez), 21",
    "sg:city":"Arahal",
    "sg:orig_category":"Transportes Por Carretera: Lotes Completos, Mercanc\u00cdas Diversas",
    "sg:phone":"+34 954 84 15 42",
    "sg:postcode":"41600",
    "sg:province":"Sevilla",
    "wof:name":"Distarajal S.l.",
    "wof:placetype":"venue"
},
  "geometry": {"coordinates":[-5.5460991859,37.246711731],"type":"Point"}
}