{
  "type": "Feature",
  "properties": {
    "iso:country":"ES",
    "sg:address":"Avda San Francisco Javier, 13",
    "sg:city":"Sevilla",
    "sg:orig_category":"Financiaci\u00d3n Y Cr\u00c9ditos",
    "sg:phone":"+34 954 93 47 47",
    "sg:postcode":"41005",
    "sg:province":"Sevilla",
    "wof:name":"Consultoria Financiera Global S.l.",
    "wof:placetype":"venue"
},
  "geometry": {"coordinates":[-5.9740519524,37.3792152405],"type":"Point"}
}