{
  "type": "Feature",
  "properties": {
    "iso:country":"ES",
    "sg:address":"Carr Ramon Castejon, 8",
    "sg:city":"Lleida",
    "sg:orig_category":"Inmobiliaria (agencias)",
    "sg:phone":"+34 973 23 25 24",
    "sg:postcode":"25007",
    "sg:province":"Lleida",
    "wof:name":"Noguerolo S.l.",
    "wof:placetype":"venue"
},
  "geometry": {"coordinates":[0.6321790218,41.618473053],"type":"Point"}
}