{
  "type": "Feature",
  "properties": {
    "iso:country":"ES",
    "sg:address":"Cra. Ta\u00fcll, S/n",
    "sg:city":"Boi",
    "sg:orig_category":"Delegados, Agentes De Tr\u00c1nsito, Auxiliares De Transporte Internacional",
    "sg:phone":"+34 973 69 61 24",
    "sg:postcode":"25528",
    "sg:province":"Lleida",
    "wof:name":"Bardaji Guillen Joaquin",
    "wof:placetype":"venue"
},
  "geometry": {"coordinates":[0.8340499997,42.5233917236],"type":"Point"}
}