{
  "type": "Feature",
  "properties": {
    "addr:full":"Carrer de Cantabria, 78 Barcelona Barcelona 08020",
    "addr:housenumber":"78",
    "addr:postcode":"08020",
    "addr:street":"Carrer De Cantabria",
    "iso:country":"ES",
    "sg:address":"Carrer de Cantabria, 78",
    "sg:city":"Barcelona",
    "sg:orig_category":"Alquiler De V\u00cddeo",
    "sg:phone":"+34 933 13 54 49",
    "sg:postcode":"08020",
    "sg:province":"Barcelona",
    "wof:name":"Martin Rodriguez Manuel",
    "wof:placetype":"venue"
},
  "geometry": {"coordinates":[2.199105978,41.4242172241],"type":"Point"}
}