{
  "type": "Feature",
  "properties": {
    "addr:full":"Rua Martin Echegaray, 28 Vigo Pontevedra 36209",
    "addr:housenumber":"28",
    "addr:postcode":"36209",
    "addr:street":"Rua Martin Echegaray",
    "iso:country":"ES",
    "sg:address":"Rua Martin Echegaray, 28",
    "sg:city":"Vigo",
    "sg:orig_category":"Farmacias",
    "sg:phone":"+34 986 29 26 46",
    "sg:postcode":"36209",
    "sg:province":"Pontevedra",
    "wof:name":"Millan Otero Maria Luisa",
    "wof:placetype":"venue"
},
  "geometry": {"coordinates":[-8.7437562943,42.2175788879],"type":"Point"}
}