{
  "type": "Feature",
  "properties": {
    "addr:full":"Calle de Romo, 59 Pozoblanco C\u00f3rdoba 14400",
    "addr:housenumber":"59",
    "addr:postcode":"14400",
    "addr:street":"Calle De Romo",
    "iso:country":"ES",
    "sg:address":"Calle de Romo, 59",
    "sg:city":"Pozoblanco",
    "sg:orig_category":"Cr\u00cda De Bovinos",
    "sg:phone":"+34 957 77 05 50",
    "sg:postcode":"14400",
    "sg:province":"C\u00f3rdoba",
    "wof:name":"Juan Moreno Y Ramirez C.b.",
    "wof:placetype":"venue"
},
  "geometry": {"coordinates":[-4.8469147682,38.374382019],"type":"Point"}
}