{
  "type": "Feature",
  "properties": {
    "addr:full":"Cno. Polan, S/n Galvez Toledo 45164",
    "addr:housenumber":"s / n",
    "addr:postcode":"45164",
    "addr:street":"Cno. Polan",
    "iso:country":"ES",
    "sg:address":"Cno. Polan, S/n",
    "sg:city":"Galvez",
    "sg:orig_category":"Barnizadores",
    "sg:phone":"+34 925 40 01 58",
    "sg:postcode":"45164",
    "sg:province":"Toledo",
    "wof:name":"Sobrino Bermudez Justino",
    "wof:placetype":"venue"
},
  "geometry": {"coordinates":[-4.2685542107,39.7027282715],"type":"Point"}
}