{
  "type": "Feature",
  "properties": {
    "iso:country":"ES",
    "sg:address":"Plaz Easo De, 6",
    "sg:city":"Donostia-san Sebastian",
    "sg:orig_category":"Supermercados Y Hipermercados",
    "sg:phone":"+34 943 46 44 09",
    "sg:postcode":"20006",
    "sg:province":"Guip\u00f9zcoa",
    "wof:name":"Alimentacion Fonseca S.l",
    "wof:placetype":"venue"
},
  "geometry": {"coordinates":[-1.9793989658,43.3173866272],"type":"Point"}
}