{
  "type": "Feature",
  "properties": {
    "addr:full":"Rond Doctor Ferran, 30 Mataro Barcelona 08304",
    "addr:housenumber":"30",
    "addr:postcode":"08304",
    "addr:street":"Doctor Ferran",
    "iso:country":"ES",
    "sg:address":"Rond Doctor Ferran, 30",
    "sg:city":"Mataro",
    "sg:orig_category":"Fabricaci\u00d3n, Importaci\u00d3n De L\u00c1mparas Y Bombillas",
    "sg:phone":"+34 937 98 74 66",
    "sg:postcode":"08304",
    "sg:province":"Barcelona",
    "wof:name":"Casta\u00f1e Vila Jaime",
    "wof:placetype":"venue"
},
  "geometry": {"coordinates":[2.4365100861,41.5483779907],"type":"Point"}
}