{
  "type": "Feature",
  "properties": {
    "iso:country":"ES",
    "sg:address":"Carr Princep De Viana, 28",
    "sg:city":"Lleida",
    "sg:orig_category":"Transportes Por V\u00cdas Navegables",
    "sg:phone":"+34 973 23 14 03",
    "sg:postcode":"25004",
    "sg:province":"Lleida",
    "wof:name":"Farre Franquet Josep Maria",
    "wof:placetype":"venue"
},
  "geometry": {"coordinates":[0.6275190115,41.6231651306],"type":"Point"}
}