{
  "type": "Feature",
  "properties": {
    "iso:country":"ES",
    "sg:address":"Calle de Maria Auxiliadora, 8",
    "sg:city":"Salamanca",
    "sg:orig_category":"Farmacias",
    "sg:phone":"+34 923 22 03 94",
    "sg:postcode":"37004",
    "sg:province":"Salamanca",
    "wof:name":"Yague Gomez Eugenio Benito",
    "wof:placetype":"venue"
},
  "geometry": {"coordinates":[-5.6590800285,40.9693336487],"type":"Point"}
}