{
  "type": "Feature",
  "properties": {
    "addr:full":"Avda Conquistadores, S/n Mazagon Huelva 21130",
    "addr:housenumber":"s / n",
    "addr:postcode":"21130",
    "addr:street":"Avda Conquistadores",
    "iso:country":"ES",
    "sg:address":"Avda Conquistadores, S/n",
    "sg:city":"Mazagon",
    "sg:classifiers":[
        {
            "category":"Retail",
            "subcategory":"Event Space",
            "type":"Services"
        }
    ],
    "sg:phone":"+34 959 37 68 67",
    "sg:postcode":"21130",
    "sg:province":"Huelva",
    "sg:tags":[
        "planchas",
        "surf",
        "alquiler",
        "de",
        "vela",
        "kayak",
        "barcos",
        "canoes",
        "y"
    ],
    "wof:name":"Arcangel Valerio Isabel",
    "wof:placetype":"venue"
},
  "geometry": {"coordinates":[-6.8283948898,37.1360778809],"type":"Point"}
}