{
  "type": "Feature",
  "properties": {
    "iso:country":"ES",
    "sg:address":"Avgd Mar (del), 11",
    "sg:city":"Albuixech",
    "sg:orig_category":"Arboricultura Y Producci\u00d3n De Frutas",
    "sg:phone":"+34 961 40 25 08",
    "sg:postcode":"46550",
    "sg:province":"Valencia",
    "wof:name":"Meneu Distribucion S.a.",
    "wof:placetype":"venue"
},
  "geometry": {"coordinates":[-0.3256070018,39.5474662781],"type":"Point"}
}