{
  "type": "Feature",
  "properties": {
    "addr:full":"Ctra Tortosa, Km. 0050,0 Rasquera Tarragona 43513",
    "addr:postcode":"43513",
    "addr:street":"Ctra Tortosa Km. 0050,0",
    "iso:country":"ES",
    "sg:address":"Ctra Tortosa, Km. 0050,0",
    "sg:city":"Rasquera",
    "sg:orig_category":"Distribuci\u00d3n De Petr\u00d3leo Y Derivados",
    "sg:phone":"+34 977 40 47 38",
    "sg:postcode":"43513",
    "sg:province":"Tarragona",
    "wof:name":"E.s. Les Sorts S.l.",
    "wof:placetype":"venue"
},
  "geometry": {"coordinates":[0.6007710099,41.0045928955],"type":"Point"}
}