{
  "type": "Feature",
  "properties": {
    "iso:country":"ES",
    "sg:address":"Kale Nagusia-calle Mayor, 3",
    "sg:city":"Lasarte",
    "sg:orig_category":"Agentes Generales De Seguros",
    "sg:phone":"+34 943 37 02 02",
    "sg:postcode":"20160",
    "sg:province":"Guip\u00f9zcoa",
    "wof:name":"Blanco Ferreira Mercedes",
    "wof:placetype":"venue"
},
  "geometry": {"coordinates":[-2.020414114,43.2698173523],"type":"Point"}
}