{
  "type": "Feature",
  "properties": {
    "iso:country":"ES",
    "sg:address":"Casa Campo, S/n",
    "sg:city":"Murla",
    "sg:orig_category":"Autob\u00das (explotaci\u00d3n Y Servicios De)",
    "sg:phone":"+34 965 58 10 36",
    "sg:postcode":"03792",
    "sg:province":"Alicante",
    "wof:name":"Autocares Carrio S.l",
    "wof:placetype":"venue"
},
  "geometry": {"coordinates":[-0.0829430968,38.7603111267],"type":"Point"}
}