{
  "type": "Feature",
  "properties": {
    "addr:full":"Calle de Porvenir, 15 Alcazar S. Juan Ciudad Real 13600",
    "addr:housenumber":"15",
    "addr:postcode":"13600",
    "addr:street":"Calle De Porvenir;Alcazar S. Juan Ciudad Real",
    "iso:country":"ES",
    "sg:address":"Calle de Porvenir, 15",
    "sg:city":"Alcazar S. Juan",
    "sg:orig_category":"Fabricaci\u00d3n De Productos Textiles Sin Tejer",
    "sg:phone":"+34 926 55 13 22",
    "sg:postcode":"13600",
    "sg:province":"Ciudad Real",
    "wof:name":"Radim Sociedad Cooperativa",
    "wof:placetype":"venue"
},
  "geometry": {"coordinates":[-3.2074389458,39.3851242065],"type":"Point"}
}