{
  "type": "Feature",
  "properties": {
    "iso:country":"ES",
    "sg:address":"Calle de San Torcuato, 25",
    "sg:city":"Zamora",
    "sg:orig_category":"Abogados",
    "sg:phone":"+34 980 53 25 05",
    "sg:postcode":"49014",
    "sg:province":"Zamora",
    "wof:name":"Rominguera Salazar Maria Del Mar",
    "wof:placetype":"venue"
},
  "geometry": {"coordinates":[-5.7443199158,41.5063438416],"type":"Point"}
}