{
  "type": "Feature",
  "properties": {
    "iso:country":"ES",
    "sg:address":"Avda Chopos (los), 35",
    "sg:city":"Algorta",
    "sg:orig_category":"Reposter\u00cdas",
    "sg:phone":"+34 944 30 01 23",
    "sg:postcode":"48992",
    "sg:province":"Vizcaya",
    "wof:name":"Panaderia La Moderna Viuda E Hijos De J.beldarrain S.l.",
    "wof:placetype":"venue"
},
  "geometry": {"coordinates":[-3.002022028,43.3404006958],"type":"Point"}
}