{
  "type": "Feature",
  "properties": {
    "addr:full":"A (p I Aeropuerto), 1 Sevilla Sevilla 41020",
    "addr:housenumber":"1",
    "addr:postcode":"41020",
    "addr:street":"Aeropuerto",
    "iso:country":"ES",
    "sg:address":"A (p I Aeropuerto), 1",
    "sg:city":"Sevilla",
    "sg:orig_category":"Poller\u00cda Y Caza (al Por Menor)",
    "sg:phone":"+34 954 25 34 02",
    "sg:postcode":"41020",
    "sg:province":"Sevilla",
    "wof:name":"Juan Jose Sola Ricca S.a.",
    "wof:placetype":"venue"
},
  "geometry": {"coordinates":[-5.9439787865,37.4068450928],"type":"Point"}
}