{
  "type": "Feature",
  "properties": {
    "addr:full":"Calle de Luis Mari Tolosa, 22 Irun Guip\u00f9zcoa 20305",
    "addr:housenumber":"22",
    "addr:postcode":"20305",
    "addr:street":"Calle De Luis Mari Tolosa;Guipu\u0300Zcoa",
    "iso:country":"ES",
    "sg:address":"Calle de Luis Mari Tolosa, 22",
    "sg:city":"Irun",
    "sg:orig_category":"Contenedores (mercanc\u00cdas)",
    "sg:phone":"+34 943 61 65 61",
    "sg:postcode":"20305",
    "sg:province":"Guip\u00f9zcoa",
    "wof:name":"Fernandez Gonzalez Jesus",
    "wof:placetype":"venue"
},
  "geometry": {"coordinates":[-1.8088949919,43.337890625],"type":"Point"}
}