{
  "type": "Feature",
  "properties": {
    "iso:country":"ES",
    "sg:address":"Calle de Canal De Suez, 58",
    "sg:city":"Madrid",
    "sg:orig_category":"Producci\u00d3n, Comercio De Cereales",
    "sg:phone":"+34 917 47 78 75",
    "sg:postcode":"28042",
    "sg:province":"Madrid",
    "wof:name":"Ranz Herrero Jose",
    "wof:placetype":"venue"
},
  "geometry": {"coordinates":[-3.5788943768,40.4743080139],"type":"Point"}
}