{
  "type": "Feature",
  "properties": {
    "iso:country":"ES",
    "sg:address":"Carrer de Guilleries, 10",
    "sg:city":"Barcelona",
    "sg:orig_category":"Peluqueros: De Se\u00d1oras",
    "sg:phone":"+34 934 15 29 96",
    "sg:postcode":"08012",
    "sg:province":"Barcelona",
    "wof:name":"Nakoh  Mostafa",
    "wof:placetype":"venue"
},
  "geometry": {"coordinates":[2.1568000317,41.4033584595],"type":"Point"}
}