{
  "type": "Feature",
  "properties": {
    "addr:full":"Plaz General Casta\u00d1os, 11 Bailen Ja\u00e9n 23710",
    "addr:housenumber":"11",
    "addr:postcode":"23710",
    "addr:street":"Castan\u0303Os;Jae\u0301N",
    "iso:country":"ES",
    "sg:address":"Plaz General Casta\u00d1os, 11",
    "sg:city":"Bailen",
    "sg:orig_category":"Ropa Para Ni\u00d1os (al Por Menor)",
    "sg:phone":"+34 953 67 60 65",
    "sg:postcode":"23710",
    "sg:province":"Ja\u00e9n",
    "wof:name":"Ubetienda S.l.",
    "wof:placetype":"venue"
},
  "geometry": {"coordinates":[-3.7784240246,38.0956954956],"type":"Point"}
}