{
  "type": "Feature",
  "properties": {
    "iso:country":"ES",
    "sg:address":"Trv. Saragossa, S/n",
    "sg:city":"S. Feliu Guixols",
    "sg:orig_category":"Empresarios",
    "sg:phone":"+34 972 32 16 78",
    "sg:postcode":"17220",
    "sg:province":"Girona",
    "wof:name":"Albiol Sola Narciso",
    "wof:placetype":"venue"
},
  "geometry": {"coordinates":[3.0276582241,41.7922859192],"type":"Point"}
}