{
  "type": "Feature",
  "properties": {
    "addr:full":"Calle de Montanchez - Aldea Moret, 8 Caceres C\u00e1ceres 10195",
    "addr:housenumber":"8",
    "addr:postcode":"10195",
    "addr:street":"Calle De Montanchez Aldea Moret;Ca\u0301Ceres",
    "iso:country":"ES",
    "sg:address":"Calle de Montanchez - Aldea Moret, 8",
    "sg:city":"Caceres",
    "sg:orig_category":"Artes Gr\u00c1ficas, Artes Pl\u00c1sticas (curso)",
    "sg:phone":"+34 927 23 35 57",
    "sg:postcode":"10195",
    "sg:province":"C\u00e1ceres",
    "wof:name":"Sarro Casares Antonio",
    "wof:placetype":"venue"
},
  "geometry": {"coordinates":[-6.38920784,39.4477577209],"type":"Point"}
}