{
  "type": "Feature",
  "properties": {
    "iso:country":"ES",
    "sg:address":"Calle de Santa Eulalia, S/n",
    "sg:city":"Berriosuso",
    "sg:orig_category":"Artes Gr\u00c1ficas, Artes Pl\u00c1sticas (curso)",
    "sg:phone":"+34 948 30 27 91",
    "sg:postcode":"31195",
    "sg:province":"Navarra",
    "wof:name":"Arrondo Amigot Emilio",
    "wof:placetype":"venue"
},
  "geometry": {"coordinates":[-1.6874951124,42.8607444763],"type":"Point"}
}