{
  "type": "Feature",
  "properties": {
    "addr:full":"Calle de Azagador De La Torre, 91 Horno De Alcedo Valencia 46026",
    "addr:housenumber":"91",
    "addr:postcode":"46026",
    "addr:street":"Calle De Azagador De La Torre;De Alcedo",
    "iso:country":"ES",
    "sg:address":"Calle de Azagador De La Torre, 91",
    "sg:city":"Horno De Alcedo",
    "sg:orig_category":"Ferreter\u00cda (diversos)",
    "sg:phone":"+34 963 76 57 12",
    "sg:postcode":"46026",
    "sg:province":"Valencia",
    "wof:name":"Uniserral S.a.sociedad Unipersonal",
    "wof:placetype":"venue"
},
  "geometry": {"coordinates":[-0.3637839854,39.4265289307],"type":"Point"}
}