{
  "type": "Feature",
  "properties": {
    "iso:country":"ES",
    "sg:address":"Fca. V. Buenamadre, S/n",
    "sg:city":"Fuente S. Esteban",
    "sg:orig_category":"Cr\u00cda De Animales",
    "sg:phone":"+34 923 44 00 15",
    "sg:postcode":"37200",
    "sg:province":"Salamanca",
    "wof:name":"Angoso Catalina Adrian",
    "wof:placetype":"venue"
},
  "geometry": {"coordinates":[-5.6630473137,40.9649734497],"type":"Point"}
}