{
  "type": "Feature",
  "properties": {
    "addr:full":"Calle de Obispo Frutos, 1 Santa Eulalia Murcia 30003",
    "addr:housenumber":"1",
    "addr:postcode":"30003",
    "addr:street":"Calle De Obispo Frutos",
    "iso:country":"ES",
    "sg:address":"Calle de Obispo Frutos, 1",
    "sg:city":"Santa Eulalia",
    "sg:orig_category":"Propiedad Industrial: Patentes De Inventos, Marcas, Modelos, Dise\u00d1os",
    "sg:phone":"+34 968 20 17 74",
    "sg:postcode":"30003",
    "sg:province":"Murcia",
    "sg:website":"www.lidermark.com",
    "wof:name":"Intermark Patentes Y Marcas S.l.",
    "wof:placetype":"venue"
},
  "geometry": {"coordinates":[-1.1233459711,37.9856834412],"type":"Point"}
}