{
  "type": "Feature",
  "properties": {
    "addr:full":"Calle de Fray Luis De Leon, 7 Valladolid Valladolid 47002",
    "addr:housenumber":"7",
    "addr:postcode":"47002",
    "addr:street":"Calle De Fray Luis De Leon",
    "iso:country":"ES",
    "sg:address":"Calle de Fray Luis De Leon, 7",
    "sg:city":"Valladolid",
    "sg:orig_category":"Ense\u00d1anza, Formaci\u00d3n Profesional: Aprendizaje",
    "sg:phone":"+34 983 30 12 55",
    "sg:postcode":"47002",
    "sg:province":"Valladolid",
    "wof:name":"Delegacion De Defensa De Valladolid",
    "wof:placetype":"venue"
},
  "geometry": {"coordinates":[-4.7235751152,41.6511497498],"type":"Point"}
}