{
  "type": "Feature",
  "properties": {
    "iso:country":"ES",
    "sg:address":"Calle de Ingleses, 31",
    "sg:city":"Santovenia Pisuerga",
    "sg:orig_category":"Vulcanizado",
    "sg:phone":"+34 983 31 02 27",
    "sg:postcode":"47155",
    "sg:province":"Valladolid",
    "wof:name":"Vulsan S.l.",
    "wof:placetype":"venue"
},
  "geometry": {"coordinates":[-4.6801185608,41.6906242371],"type":"Point"}
}