{
  "type": "Feature",
  "properties": {
    "addr:full":"Calle de Vizcaya, 4 Villaviciosa Odon Madrid 28670",
    "addr:housenumber":"4",
    "addr:postcode":"28670",
    "addr:street":"Calle De Vizcaya;Odon",
    "iso:country":"ES",
    "sg:address":"Calle de Vizcaya, 4",
    "sg:city":"Villaviciosa Odon",
    "sg:orig_category":"Arquitectos",
    "sg:phone":"+34 916 16 64 44",
    "sg:postcode":"28670",
    "sg:province":"Madrid",
    "wof:name":"Sanz Morillas Juan Carlos",
    "wof:placetype":"venue"
},
  "geometry": {"coordinates":[-3.8757269382,40.3594932556],"type":"Point"}
}