{
  "type": "Feature",
  "properties": {
    "addr:full":"Rua Estacion (da), S/n Burela Lugo 27880",
    "addr:postcode":"27880",
    "addr:street":"Rua Estacion Da S / N",
    "iso:country":"ES",
    "sg:address":"Rua Estacion (da), S/n",
    "sg:city":"Burela",
    "sg:orig_category":"Autob\u00das (explotaci\u00d3n Y Servicios De)",
    "sg:phone":"+34 982 58 58 86",
    "sg:postcode":"27880",
    "sg:province":"Lugo",
    "wof:name":"Arriva Noroeste S.l.",
    "wof:placetype":"venue"
},
  "geometry": {"coordinates":[-7.3611736298,43.660320282],"type":"Point"}
}