{
  "type": "Feature",
  "properties": {
    "addr:full":"Carrer de Calabria, 142 Barcelona Barcelona 08015",
    "addr:housenumber":"142",
    "addr:postcode":"08015",
    "addr:street":"Carrer De Calabria",
    "iso:country":"ES",
    "sg:address":"Carrer de Calabria, 142",
    "sg:city":"Barcelona",
    "sg:orig_category":"Arquitectos",
    "sg:phone":"+34 934 24 13 92",
    "sg:postcode":"08015",
    "sg:province":"Barcelona",
    "wof:name":"Herce Asociados S.l.",
    "wof:placetype":"venue"
},
  "geometry": {"coordinates":[2.1526238918,41.3817176819],"type":"Point"}
}