{
  "type": "Feature",
  "properties": {
    "addr:full":"Carrer de Sant Isidre, 4 Gava Barcelona 08850",
    "addr:housenumber":"4",
    "addr:postcode":"08850",
    "addr:street":"Carrer De Sant Isidre",
    "iso:country":"ES",
    "sg:address":"Carrer de Sant Isidre, 4",
    "sg:city":"Gava",
    "sg:orig_category":"Institutos De Belleza",
    "sg:phone":"+34 936 38 40 06",
    "sg:postcode":"08850",
    "sg:province":"Barcelona",
    "wof:name":"Tus Manos Hablan S.l.",
    "wof:placetype":"venue"
},
  "geometry": {"coordinates":[2.0043120384,41.3049316406],"type":"Point"}
}