{
  "type": "Feature",
  "properties": {
    "iso:country":"ES",
    "sg:address":"Calle de Moreras (de Las), 43",
    "sg:city":"Aranjuez",
    "sg:orig_category":"Alimentaci\u00d3n General (al Por Menor)",
    "sg:phone":"+34 918 91 85 46",
    "sg:postcode":"28300",
    "sg:province":"Madrid",
    "wof:name":"Palacio Del Pollo S.l.",
    "wof:placetype":"venue"
},
  "geometry": {"coordinates":[-3.5949640274,40.0354690552],"type":"Point"}
}