{
  "type": "Feature",
  "properties": {
    "iso:country":"ES",
    "sg:address":"Elkano Kalea, 18",
    "sg:city":"Hernani",
    "sg:orig_category":"Frutas, Legumbres Frescas Y Tempranas (al Por Menor)",
    "sg:phone":"+34 943 33 07 90",
    "sg:postcode":"20120",
    "sg:province":"Guip\u00f9zcoa",
    "wof:name":"Perez Garcia Luis Ramon",
    "wof:placetype":"venue"
},
  "geometry": {"coordinates":[-1.9760299921,43.2684822083],"type":"Point"}
}