{
  "type": "Feature",
  "properties": {
    "iso:country":"ES",
    "sg:address":"Itzea Karrika, 1",
    "sg:city":"Bera",
    "sg:orig_category":"M\u00c9dicos: Estomatolog\u00cda",
    "sg:phone":"+34 948 63 06 47",
    "sg:postcode":"31780",
    "sg:province":"Navarra",
    "wof:name":"Sope\u00f1a Colombera Jorge Alberto",
    "wof:placetype":"venue"
},
  "geometry": {"coordinates":[-1.6784160137,43.2820358276],"type":"Point"}
}