{
  "type": "Feature",
  "properties": {
    "iso:country":"ES",
    "sg:address":"Bartolome Benitez (finca Espa\u00f1a), 15",
    "sg:city":"La Cuesta",
    "sg:orig_category":"Dietistas",
    "sg:phone":"+34 922 64 83 63",
    "sg:postcode":"38320",
    "sg:province":"Santa Cruz De Tenerife",
    "wof:name":"Distribuidoras Farma Tenerife S.l.",
    "wof:placetype":"venue"
},
  "geometry": {"coordinates":[-16.2880134583,28.468454361],"type":"Point"}
}