{
  "type": "Feature",
  "properties": {
    "addr:full":"Avda Cascante, 5 Ablitas Navarra 31523",
    "addr:housenumber":"5",
    "addr:postcode":"31523",
    "addr:street":"Avda Cascante",
    "iso:country":"ES",
    "sg:address":"Avda Cascante, 5",
    "sg:city":"Ablitas",
    "sg:orig_category":"Reposter\u00cdas",
    "sg:phone":"+34 948 81 31 53",
    "sg:postcode":"31523",
    "sg:province":"Navarra",
    "wof:name":"Panaderia Ablitense S.l.",
    "wof:placetype":"venue"
},
  "geometry": {"coordinates":[-1.6424330473,41.9764328003],"type":"Point"}
}