{
  "type": "Feature",
  "properties": {
    "addr:full":"Calle de Eduardo Aunos, 24 Madrid Madrid 28028",
    "addr:housenumber":"24",
    "addr:postcode":"madrid;28028",
    "addr:street":"Calle De Eduardo Aunos",
    "iso:country":"ES",
    "sg:address":"Calle de Eduardo Aunos, 24",
    "sg:city":"Madrid",
    "sg:orig_category":"Fotocopias, Reprograf\u00cda",
    "sg:phone":"+34 915 73 13 71",
    "sg:postcode":"28028",
    "sg:province":"Madrid",
    "wof:name":"Santiago De Santiago Estudio De Arte S.l.",
    "wof:placetype":"venue"
},
  "geometry": {"coordinates":[-3.6655349731,40.4218788147],"type":"Point"}
}