{
  "type": "Feature",
  "properties": {
    "iso:country":"ES",
    "sg:address":"Bda. Encina, 19",
    "sg:city":"Granada",
    "sg:orig_category":"Panader\u00cdas, Panader\u00cdas",
    "sg:phone":"+34 958 20 20 23",
    "sg:postcode":"18015",
    "sg:province":"Granada",
    "wof:name":"Asociacion Provincial De Fabricantes De Pan De Granada Y Provincia",
    "wof:placetype":"venue"
},
  "geometry": {"coordinates":[-3.6572542191,37.1927947998],"type":"Point"}
}