{
  "type": "Feature",
  "properties": {
    "addr:full":"Carrer de Carolines, 25 Barcelona Barcelona 08012",
    "addr:housenumber":"25",
    "addr:postcode":"08012",
    "addr:street":"Carrer De Carolines",
    "iso:country":"ES",
    "sg:address":"Carrer de Carolines, 25",
    "sg:city":"Barcelona",
    "sg:orig_category":"Institutos De Belleza",
    "sg:phone":"+34 932 17 45 48",
    "sg:postcode":"08012",
    "sg:province":"Barcelona",
    "wof:name":"Calpe Ramon Ana",
    "wof:placetype":"venue"
},
  "geometry": {"coordinates":[2.150190115,41.4030380249],"type":"Point"}
}