{
  "type": "Feature",
  "properties": {
    "iso:country":"ES",
    "sg:address":"Poli Poligono Louzaneta, S/n",
    "sg:city":"Lugo",
    "sg:orig_category":"Alimentaci\u00d3n Para Ganado",
    "sg:phone":"+34 982 25 55 13",
    "sg:postcode":"27297",
    "sg:province":"Lugo",
    "wof:name":"Agricola Del Mi\u00f1o S.l.",
    "wof:placetype":"venue"
},
  "geometry": {"coordinates":[-7.5951576233,43.0050773621],"type":"Point"}
}