{
  "type": "Feature",
  "properties": {
    "addr:full":"Avda Cardenal Francisco Alvarez, 12 Alacant Alicante 03009",
    "addr:housenumber":"12",
    "addr:postcode":"03009",
    "addr:street":"Avda Cardenal Francisco Alvarez",
    "iso:country":"ES",
    "sg:address":"Avda Cardenal Francisco Alvarez, 12",
    "sg:city":"Alacant",
    "sg:orig_category":"Farmacias",
    "sg:phone":"+34 965 12 72 83",
    "sg:postcode":"03009",
    "sg:province":"Alicante",
    "wof:name":"Casares Rodriguez Tomas",
    "wof:placetype":"venue"
},
  "geometry": {"coordinates":[-0.5031419992,38.3717079163],"type":"Point"}
}