{
  "type": "Feature",
  "properties": {
    "addr:full":"Cami Mig, S/n Cabrera Mar Barcelona 08349",
    "addr:postcode":"08349",
    "addr:street":"Mig S / N Cabrera Mar Barcelona",
    "iso:country":"ES",
    "sg:address":"Cami Mig, S/n",
    "sg:city":"Cabrera Mar",
    "sg:orig_category":"Materias Pl\u00c1sticas: Art\u00cdculos Para La Industria",
    "sg:phone":"+34 937 59 21 96",
    "sg:postcode":"08349",
    "sg:province":"Barcelona",
    "wof:name":"Alberplas S.l.",
    "wof:placetype":"venue"
},
  "geometry": {"coordinates":[2.4158155918,41.527797699],"type":"Point"}
}