{
  "type": "Feature",
  "properties": {
    "addr:full":"Carrer de Joan Maragall, 28 Hospitalet Llobregat Barcelona 08901",
    "addr:housenumber":"28",
    "addr:postcode":"08901",
    "addr:street":"Carrer De Joan Maragall",
    "iso:country":"ES",
    "sg:address":"Carrer de Joan Maragall, 28",
    "sg:city":"Hospitalet Llobregat",
    "sg:orig_category":"Marroquiner\u00cda (confecci\u00d3n)",
    "sg:phone":"+34 933 37 99 91",
    "sg:postcode":"08901",
    "sg:province":"Barcelona",
    "wof:name":"Bolsos Tonini S.l.",
    "wof:placetype":"venue"
},
  "geometry": {"coordinates":[2.1083590984,41.3634567261],"type":"Point"}
}