{
  "type": "Feature",
  "properties": {
    "iso:country":"ES",
    "sg:address":"Calle de Aitzbitarte, Pasaje De, 3",
    "sg:city":"Errenteria",
    "sg:orig_category":"Albergues",
    "sg:phone":"+34 943 51 19 78",
    "sg:postcode":"20100",
    "sg:province":"Guip\u00f9zcoa",
    "wof:name":"Carrera Miguelez Timoteo",
    "wof:placetype":"venue"
},
  "geometry": {"coordinates":[-1.8907879591,43.3099708557],"type":"Point"}
}