{
  "type": "Feature",
  "properties": {
    "addr:full":"Calle de Pirineos, 31 Madrid Madrid 28040",
    "addr:housenumber":"31",
    "addr:postcode":"madrid;28040",
    "addr:street":"Calle De Pirineos",
    "iso:country":"ES",
    "sg:address":"Calle de Pirineos, 31",
    "sg:city":"Madrid",
    "sg:orig_category":"Extinci\u00d3n De Incendios: Material Y Suministros (fabricaci\u00d3n, Al Por Mayor)",
    "sg:phone":"+34 914 59 19 02",
    "sg:postcode":"28040",
    "sg:province":"Madrid",
    "wof:name":"Confaire S.a.",
    "wof:placetype":"venue"
},
  "geometry": {"coordinates":[-3.7171809673,40.4554519653],"type":"Point"}
}