{
  "type": "Feature",
  "properties": {
    "addr:full":"Calle de Artekalea, 6 Gernika-lumo Vizcaya 48300",
    "addr:housenumber":"6",
    "addr:postcode":"48300",
    "addr:street":"Calle De Artekalea",
    "iso:country":"ES",
    "sg:address":"Calle de Artekalea, 6",
    "sg:city":"Gernika-lumo",
    "sg:orig_category":"Ropa Para Se\u00d1oras Y Caballeros (al Por Menor)",
    "sg:phone":"+34 946 25 02 30",
    "sg:postcode":"48300",
    "sg:province":"Vizcaya",
    "wof:name":"Alberto Arejita Barinaga",
    "wof:placetype":"venue"
},
  "geometry": {"coordinates":[-2.6780586243,43.3150901794],"type":"Point"}
}