{
  "type": "Feature",
  "properties": {
    "iso:country":"ES",
    "sg:address":"Rua Real, S/n",
    "sg:city":"Fisterra",
    "sg:orig_category":"Supermercados Y Hipermercados",
    "sg:phone":"+34 981 74 07 77",
    "sg:postcode":"15155",
    "sg:province":"A Coru\u00f1a",
    "wof:name":"Vego Supermercados S.a.",
    "wof:placetype":"venue"
},
  "geometry": {"coordinates":[-9.2632684708,42.9090614319],"type":"Point"}
}