{
  "type": "Feature",
  "properties": {
    "addr:full":"Av. Portugal, 24 Valverde Fresno C\u00e1ceres 10890",
    "addr:housenumber":"24",
    "addr:postcode":"10890",
    "addr:street":"Av. Portugal",
    "iso:country":"ES",
    "sg:address":"Av. Portugal, 24",
    "sg:city":"Valverde Fresno",
    "sg:orig_category":"Agencias Y Agentes Comerciales, Representantes",
    "sg:phone":"+34 927 51 04 06",
    "sg:postcode":"10890",
    "sg:province":"C\u00e1ceres",
    "wof:name":"Andrade Asencio Maria Angeles",
    "wof:placetype":"venue"
},
  "geometry": {"coordinates":[-6.8836054802,40.2173347473],"type":"Point"}
}