{
  "type": "Feature",
  "properties": {
    "iso:country":"ES",
    "sg:address":"Carrer de Vista Alegre, 27",
    "sg:city":"Sant Agusti",
    "sg:classifiers":[
        {
            "category":"Retail",
            "subcategory":"Event Space",
            "type":"Services"
        }
    ],
    "sg:phone":"+34 971 70 32 97",
    "sg:postcode":"07015",
    "sg:province":"Islas Baleares",
    "sg:tags":[
        "planchas",
        "surf",
        "alquiler",
        "de",
        "vela",
        "kayak",
        "barcos",
        "canoes",
        "y"
    ],
    "sg:website":"www.anclazul.com",
    "wof:name":"Anclazul,s.l.",
    "wof:placetype":"venue"
},
  "geometry": {"coordinates":[2.6197500229,39.5526542664],"type":"Point"}
}