{
  "type": "Feature",
  "properties": {
    "addr:full":"Avgd Lloreda, 66 Badalona Barcelona 08917",
    "addr:housenumber":"66",
    "addr:postcode":"08917",
    "addr:street":"Lloreda",
    "iso:country":"ES",
    "sg:address":"Avgd Lloreda, 66",
    "sg:city":"Badalona",
    "sg:orig_category":"Cajas De Ahorro",
    "sg:phone":"+34 933 97 27 63",
    "sg:postcode":"08917",
    "sg:province":"Barcelona",
    "wof:name":"Caixa D'estalvis Del Penedes",
    "wof:placetype":"venue"
},
  "geometry": {"coordinates":[2.2317650318,41.4493255615],"type":"Point"}
}