{
  "type": "Feature",
  "properties": {
    "iso:country":"ES",
    "sg:address":"Carpinteros (pi Villa Rota P P Tres), 4",
    "sg:city":"Rota",
    "sg:orig_category":"Mec\u00c1nico Del Autom\u00d3vil",
    "sg:phone":"+34 956 84 13 84",
    "sg:postcode":"11520",
    "sg:province":"C\u00e1diz",
    "wof:name":"Autos Gallego S.l.",
    "wof:placetype":"venue"
},
  "geometry": {"coordinates":[-6.3438782692,36.677822113],"type":"Point"}
}