{
  "type": "Feature",
  "properties": {
    "iso:country":"ES",
    "sg:address":"Calle de San Pedro, 10",
    "sg:city":"Oliva Frontera",
    "sg:orig_category":"Autob\u00das (explotaci\u00d3n Y Servicios De)",
    "sg:phone":"+34 924 74 01 60",
    "sg:postcode":"06120",
    "sg:province":"Badajoz",
    "wof:name":"Perez Rangel Francisco",
    "wof:placetype":"venue"
},
  "geometry": {"coordinates":[-6.9167737961,38.2765388489],"type":"Point"}
}