{
  "type": "Feature",
  "properties": {
    "addr:full":"Calle de Pozo Del Rey, 4 Manilva M\u00e1laga 29691",
    "addr:housenumber":"4",
    "addr:postcode":"29691",
    "addr:street":"Calle De Pozo Del Rey",
    "iso:country":"ES",
    "sg:address":"Calle de Pozo Del Rey, 4",
    "sg:city":"Manilva",
    "sg:orig_category":"Promotores Constructores",
    "sg:phone":"+34 952 89 13 28",
    "sg:postcode":"29691",
    "sg:province":"M\u00e1laga",
    "wof:name":"Qui\u00f1ones Benitez Diego",
    "wof:placetype":"venue"
},
  "geometry": {"coordinates":[-5.252603054,36.376411438],"type":"Point"}
}