{
  "type": "Feature",
  "properties": {
    "addr:full":"Calle de Puerto De Santa Maria, 112 Madrid Madrid 28043",
    "addr:housenumber":"112",
    "addr:postcode":"28043",
    "addr:street":"Calle De Puerto De Santa Maria",
    "iso:country":"ES",
    "sg:address":"Calle de Puerto De Santa Maria, 112",
    "sg:city":"Madrid",
    "sg:orig_category":"Organismos De Desarrollo",
    "sg:phone":"+34 917 16 00 10",
    "sg:postcode":"28043",
    "sg:province":"Madrid",
    "wof:name":"Tracer Tecnologias Analiticas Sl",
    "wof:placetype":"venue"
},
  "geometry": {"coordinates":[-4.1466302872,40.5977287292],"type":"Point"}
}