{
  "type": "Feature",
  "properties": {
    "addr:full":"Avda Barcelona, 26 Malaga M\u00e1laga 29009",
    "addr:housenumber":"26",
    "addr:postcode":"29009",
    "addr:street":"Avda Barcelona;Ma\u0301Laga",
    "iso:country":"ES",
    "sg:address":"Avda Barcelona, 26",
    "sg:city":"Malaga",
    "sg:orig_category":"Telefon\u00cda: Instaladores Varios",
    "sg:phone":"+34 952 10 22 58",
    "sg:postcode":"29009",
    "sg:province":"M\u00e1laga",
    "wof:name":"Neotel 2000 S.l.",
    "wof:placetype":"venue"
},
  "geometry": {"coordinates":[-4.4315071106,36.7235336304],"type":"Point"}
}