{
  "type": "Feature",
  "properties": {
    "iso:country":"ES",
    "sg:address":"Pl Santa Pon\u00c7a, 3",
    "sg:city":"Santa Pon\u00c7a",
    "sg:orig_category":"Art\u00cdculos De Regalo (al Por Menor)",
    "sg:phone":"+34 971 69 06 18",
    "sg:postcode":"07180",
    "sg:province":"Islas Baleares",
    "wof:name":"Cozar Martinez Andres",
    "wof:placetype":"venue"
},
  "geometry": {"coordinates":[2.4985899925,39.5253143311],"type":"Point"}
}