{
  "type": "Feature",
  "properties": {
    "addr:full":"Calle de Libertad, 84 Pola De Laviana Asturias 33980",
    "addr:housenumber":"84",
    "addr:postcode":"33980",
    "addr:street":"Calle De Libertad",
    "iso:country":"ES",
    "sg:address":"Calle de Libertad, 84",
    "sg:city":"Pola De Laviana",
    "sg:orig_category":"Fabricaci\u00d3n, Instalaci\u00d3n De Armarios",
    "sg:phone":"+34 985 60 20 00",
    "sg:postcode":"33980",
    "sg:province":"Asturias",
    "wof:name":"Gutierrez Orviz Adenso",
    "wof:placetype":"venue"
},
  "geometry": {"coordinates":[-5.5608987808,43.243221283],"type":"Point"}
}