{
  "type": "Feature",
  "properties": {
    "iso:country":"ES",
    "sg:address":"Carrer de Mossen Mole, 30",
    "sg:city":"Mataro",
    "sg:orig_category":"Ropa Para Se\u00d1oras Y Caballeros (al Por Menor)",
    "sg:phone":"+34 937 90 73 84",
    "sg:postcode":"08304",
    "sg:province":"Barcelona",
    "wof:name":"Sac Sac S.l.",
    "wof:placetype":"venue"
},
  "geometry": {"coordinates":[2.4464440346,41.5474243164],"type":"Point"}
}