{
  "type": "Feature",
  "properties": {
    "iso:country":"ES",
    "sg:address":"Paredilla, 5",
    "sg:city":"Alhaurin Torre",
    "sg:orig_category":"Material Y Herramientas Agr\u00cdcolas",
    "sg:phone":"+34 952 41 11 00",
    "sg:postcode":"29130",
    "sg:province":"M\u00e1laga",
    "wof:name":"Moreno Sanchez Rafael",
    "wof:placetype":"venue"
},
  "geometry": {"coordinates":[-4.5667190552,36.6618614197],"type":"Point"}
}