{
  "type": "Feature",
  "properties": {
    "iso:country":"ES",
    "sg:address":"Calle de Magallanes, 12",
    "sg:city":"Velez-malaga",
    "sg:orig_category":"Electricidad: Instaladores",
    "sg:phone":"+34 952 50 71 09",
    "sg:postcode":"29700",
    "sg:province":"M\u00e1laga",
    "wof:name":"Instalaciones Mercado Y Diaz S.c.",
    "wof:placetype":"venue"
},
  "geometry": {"coordinates":[-4.1040258408,36.7751579285],"type":"Point"}
}