{
  "type": "Feature",
  "properties": {
    "addr:full":"Calle de Pedro Laborde, 25 Madrid Madrid 28038",
    "addr:housenumber":"25",
    "addr:postcode":"madrid;28038",
    "addr:street":"Calle De Pedro Laborde",
    "iso:country":"ES",
    "sg:address":"Calle de Pedro Laborde, 25",
    "sg:city":"Madrid",
    "sg:orig_category":"Bisuter\u00cda, Joyer\u00cda, Relojer\u00cda (al Por Menor)",
    "sg:phone":"+34 913 03 37 33",
    "sg:postcode":"28038",
    "sg:province":"Madrid",
    "wof:name":"Arribas Duque Miguel",
    "wof:placetype":"venue"
},
  "geometry": {"coordinates":[-3.6477100849,40.3889503479],"type":"Point"}
}