{
  "type": "Feature",
  "properties": {
    "iso:country":"ES",
    "sg:address":"Calle de Rio Alberche (del), 19",
    "sg:city":"Humanes De Madrid",
    "sg:orig_category":"Fabricaci\u00d3n, Instalaci\u00d3n De Escaleras",
    "sg:phone":"+34 916 04 91 92",
    "sg:postcode":"28970",
    "sg:province":"Madrid",
    "wof:name":"Fermin Garcia Maria Jose",
    "wof:placetype":"venue"
},
  "geometry": {"coordinates":[-3.8115301132,40.2648391724],"type":"Point"}
}