{
  "type": "Feature",
  "properties": {
    "iso:country":"ES",
    "sg:address":"Pase San Jose, 96",
    "sg:city":"Palmas De Gran Canaria",
    "sg:orig_category":"Caf\u00c9s, Bares, Cervecer\u00cdas",
    "sg:phone":"+34 928 33 76 32",
    "sg:postcode":"35015",
    "sg:province":"Las Palmas",
    "wof:name":"Artiles Vega Carmen",
    "wof:placetype":"venue"
},
  "geometry": {"coordinates":[-15.4331674576,28.0846118927],"type":"Point"}
}