{
  "type": "Feature",
  "properties": {
    "addr:full":"Calle de Aranzadi Telesforo, 8 Bilbao Vizcaya 48008",
    "addr:housenumber":"8",
    "addr:postcode":"48008",
    "addr:street":"Calle De Aranzadi Telesforo",
    "iso:country":"ES",
    "sg:address":"Calle de Aranzadi Telesforo, 8",
    "sg:city":"Bilbao",
    "sg:orig_category":"Herboristas (al Por Menor)",
    "sg:phone":"+34 944 43 52 48",
    "sg:postcode":"48008",
    "sg:province":"Vizcaya",
    "wof:name":"Fernandez Fernandez Obdulia",
    "wof:placetype":"venue"
},
  "geometry": {"coordinates":[-2.9350402355,43.2609138489],"type":"Point"}
}