{
  "type": "Feature",
  "properties": {
    "addr:full":"Calle de Perez De Ayala, 3 Oviedo Asturias 33007",
    "addr:housenumber":"3",
    "addr:postcode":"33007",
    "addr:street":"Calle De Perez De Ayala",
    "iso:country":"ES",
    "sg:address":"Calle de Perez De Ayala, 3",
    "sg:city":"Oviedo",
    "sg:orig_category":"M\u00c9dicos: Estomatolog\u00cda",
    "sg:phone":"+34 985 25 63 06",
    "sg:postcode":"33007",
    "sg:province":"Asturias",
    "wof:name":"Bouso\u00f1o Garcia Juan Luis",
    "wof:placetype":"venue"
},
  "geometry": {"coordinates":[-5.8499908447,43.3568687439],"type":"Point"}
}