{
  "type": "Feature",
  "properties": {
    "iso:country":"ES",
    "sg:address":"Calle de Gonzalo Bilbao, 4",
    "sg:city":"Sevilla",
    "sg:orig_category":"Abogados",
    "sg:phone":"+34 954 54 18 58",
    "sg:postcode":"41003",
    "sg:province":"Sevilla",
    "wof:name":"Martinez Lopez Julio",
    "wof:placetype":"venue"
},
  "geometry": {"coordinates":[-5.9833378792,37.3930702209],"type":"Point"}
}