{
  "type": "Feature",
  "properties": {
    "addr:full":"Calle de Mayor Sevilla, 8 Totana Murcia 30850",
    "addr:housenumber":"8",
    "addr:postcode":"30850",
    "addr:street":"Calle De Mayor Sevilla",
    "iso:country":"ES",
    "sg:address":"Calle de Mayor Sevilla, 8",
    "sg:city":"Totana",
    "sg:orig_category":"Peluqueros: De Se\u00d1oras",
    "sg:phone":"+34 968 42 44 54",
    "sg:postcode":"30850",
    "sg:province":"Murcia",
    "wof:name":"Lopez Jara Enrique",
    "wof:placetype":"venue"
},
  "geometry": {"coordinates":[-1.5032260418,37.7700996399],"type":"Point"}
}