{
  "type": "Feature",
  "properties": {
    "addr:full":"Av Sarria, 28 Barcelona Barcelona 08029",
    "addr:housenumber":"28",
    "addr:postcode":"08029",
    "addr:street":"Av Sarria",
    "iso:country":"ES",
    "sg:address":"Av Sarria, 28",
    "sg:city":"Barcelona",
    "sg:orig_category":"Ense\u00d1anza Variada",
    "sg:phone":"+34 933 21 15 39",
    "sg:postcode":"08029",
    "sg:province":"Barcelona",
    "wof:name":"Centre D'estudis Economics I Socials",
    "wof:placetype":"venue"
},
  "geometry": {"coordinates":[2.1432039738,41.3906974792],"type":"Point"}
}