{
  "type": "Feature",
  "properties": {
    "iso:country":"ES",
    "sg:address":"Zubiondo Poligonoa, S/n",
    "sg:city":"Hernani",
    "sg:orig_category":"Ferreter\u00cda (diversos)",
    "sg:phone":"+34 943 33 26 54",
    "sg:postcode":"20120",
    "sg:province":"Guip\u00f9zcoa",
    "wof:name":"Chatarreria Cuesta S. L",
    "wof:placetype":"venue"
},
  "geometry": {"coordinates":[-1.9798289537,43.2647514343],"type":"Point"}
}