{
  "type": "Feature",
  "properties": {
    "iso:country":"ES",
    "sg:address":"Carrer de Ausias Marc, 67",
    "sg:city":"Barcelona",
    "sg:orig_category":"Agencias Y Agentes Comerciales, Representantes",
    "sg:phone":"+34 932 32 87 07",
    "sg:postcode":"08010",
    "sg:province":"Barcelona",
    "wof:name":"Garces Coll Orencio",
    "wof:placetype":"venue"
},
  "geometry": {"coordinates":[2.1785581112,41.3937454224],"type":"Point"}
}