{
  "type": "Feature",
  "properties": {
    "iso:country":"ES",
    "sg:address":"Calle de Jacinto Verdaguer, 2",
    "sg:city":"Madrid",
    "sg:orig_category":"Cl\u00cdnicas Dentales",
    "sg:phone":"+34 915 60 90 25",
    "sg:postcode":"28019",
    "sg:province":"Madrid",
    "wof:name":"Clinica Dental Arroyo S.l.",
    "wof:placetype":"venue"
},
  "geometry": {"coordinates":[-3.7139639854,40.39635849],"type":"Point"}
}