{
  "type": "Feature",
  "properties": {
    "iso:country":"ES",
    "sg:address":"Calle de Martin Aldehuela, 3",
    "sg:city":"Malaga",
    "sg:orig_category":"Imprenta",
    "sg:phone":"+34 952 26 54 82",
    "sg:postcode":"29014",
    "sg:province":"M\u00e1laga",
    "wof:name":"Gascon Gallardo Eduardo Alfonso",
    "wof:placetype":"venue"
},
  "geometry": {"coordinates":[-4.4213762283,36.745223999],"type":"Point"}
}