{
  "type": "Feature",
  "properties": {
    "addr:full":"Calle de General Jauregi, 7 Donostia-san Sebastian Guip\u00f9zcoa 20003",
    "addr:housenumber":"7",
    "addr:postcode":"20003",
    "addr:street":"Calle De General Jauregi",
    "iso:country":"ES",
    "sg:address":"Calle de General Jauregi, 7",
    "sg:city":"Donostia-san Sebastian",
    "sg:orig_category":"Mec\u00c1nico Del Autom\u00d3vil",
    "sg:phone":"+34 943 42 23 41",
    "sg:postcode":"20003",
    "sg:province":"Guip\u00f9zcoa",
    "wof:name":"Faustino Solis Gonzalez Y Saturnino Solis Gonzalez Cdad.",
    "wof:placetype":"venue"
},
  "geometry": {"coordinates":[-1.9825229645,43.3246803284],"type":"Point"}
}