{
  "type": "Feature",
  "properties": {
    "iso:country":"ES",
    "sg:address":"Carr Guell, 49",
    "sg:city":"Girona",
    "sg:orig_category":"Promotores Constructores",
    "sg:phone":"+34 972 22 84 38",
    "sg:postcode":"17005",
    "sg:province":"Girona",
    "wof:name":"Cala Blanca Promocions Gironimes S.l.",
    "wof:placetype":"venue"
},
  "geometry": {"coordinates":[2.8141438961,41.9821281433],"type":"Point"}
}