{
  "type": "Feature",
  "properties": {
    "iso:country":"ES",
    "sg:address":"Carrer de Roine, 21",
    "sg:city":"Segur Calafell",
    "sg:orig_category":"Promotores Constructores",
    "sg:phone":"+34 977 15 90 17",
    "sg:postcode":"43882",
    "sg:province":"Tarragona",
    "wof:name":"Inmopen S.l.",
    "wof:placetype":"venue"
},
  "geometry": {"coordinates":[1.6030399799,41.1915588379],"type":"Point"}
}