{
  "type": "Feature",
  "properties": {
    "addr:full":"Calle de Islas Aleutianas, 3 Madrid Madrid 28035",
    "addr:housenumber":"3",
    "addr:postcode":"28035",
    "addr:street":"Calle De Islas Aleutianas",
    "iso:country":"ES",
    "sg:address":"Calle de Islas Aleutianas, 3",
    "sg:city":"Madrid",
    "sg:orig_category":"Centros Empresariales",
    "sg:phone":"+34 913 76 80 87",
    "sg:postcode":"28035",
    "sg:province":"Madrid",
    "wof:name":"Nuevo Grial S.l.",
    "wof:placetype":"venue"
},
  "geometry": {"coordinates":[-3.7294280529,40.4747886658],"type":"Point"}
}