{
  "type": "Feature",
  "properties": {
    "addr:full":"Ptda Cachapet, 32 Crevillente Alicante 03330",
    "addr:housenumber":"32",
    "addr:postcode":"03330",
    "addr:street":"Ptda Cachapet",
    "iso:country":"ES",
    "sg:address":"Ptda Cachapet, 32",
    "sg:city":"Crevillente",
    "sg:orig_category":"Veh\u00cdculos De Ocasi\u00d3n",
    "sg:phone":"+34 965 97 02 36",
    "sg:postcode":"03330",
    "sg:province":"Alicante",
    "wof:name":"Tani Todo En Automoviles S.l.",
    "wof:placetype":"venue"
},
  "geometry": {"coordinates":[-0.8163840175,38.2342567444],"type":"Point"}
}