{
  "type": "Feature",
  "properties": {
    "iso:country":"ES",
    "sg:address":"Cmno Camino De Casablanca, S/n",
    "sg:city":"Melilla",
    "sg:orig_category":"Dibujantes (diversos)",
    "sg:phone":"+34 956 49 54 23",
    "sg:postcode":"11130",
    "sg:province":"C\u00e1diz",
    "wof:name":"Garcia Polanco Antonio Manuel",
    "wof:placetype":"venue"
},
  "geometry": {"coordinates":[-6.1438241005,36.3590583801],"type":"Point"}
}