{
  "type": "Feature",
  "properties": {
    "iso:country":"ES",
    "sg:address":"Calle de Invierno, 53",
    "sg:city":"Hoya Andrea",
    "sg:orig_category":"Empresas De Carpinter\u00cda Met\u00c1lica",
    "sg:phone":"+34 928 67 10 93",
    "sg:postcode":"35018",
    "sg:province":"Las Palmas",
    "wof:name":"Hosterinox S.l.",
    "wof:placetype":"venue"
},
  "geometry": {"coordinates":[-15.4613294601,28.0902805328],"type":"Point"}
}