{
  "type": "Feature",
  "properties": {
    "addr:full":"Avenida Florentino Agustin Diez, S/n Canales-magdalena Le\u00f3n 24120",
    "addr:postcode":"24120",
    "addr:street":"Avenida Florentino Agustin Diez S / N Canales-Magdalena Leo\u0301N",
    "iso:country":"ES",
    "sg:address":"Avenida Florentino Agustin Diez, S/n",
    "sg:city":"Canales-magdalena",
    "sg:orig_category":"Electrodom\u00c9sticos (al Por Menor)",
    "sg:phone":"+34 987 58 11 66",
    "sg:postcode":"24120",
    "sg:province":"Le\u00f3n",
    "wof:name":"Garcia-lorenza Lorenzana Yolanda",
    "wof:placetype":"venue"
},
  "geometry": {"coordinates":[-5.8100237846,42.7811889648],"type":"Point"}
}