{
  "type": "Feature",
  "properties": {
    "addr:full":"Calle de Francos Rodriguez, 53 Madrid Madrid 28039",
    "addr:housenumber":"53",
    "addr:postcode":"madrid;28039",
    "addr:street":"Calle De Francos Rodriguez",
    "iso:country":"ES",
    "sg:address":"Calle de Francos Rodriguez, 53",
    "sg:city":"Madrid",
    "sg:orig_category":"Cine (distribuci\u00d3n)",
    "sg:phone":"+34 914 59 54 33",
    "sg:postcode":"28039",
    "sg:province":"Madrid",
    "wof:name":"Marte Films Internacional S.a.",
    "wof:placetype":"venue"
},
  "geometry": {"coordinates":[-3.7083220482,40.4565811157],"type":"Point"}
}