{
  "type": "Feature",
  "properties": {
    "iso:country":"ES",
    "sg:address":"Avda Doctor Gregorio Mara\u00d1on, 35",
    "sg:city":"Torrevieja",
    "sg:orig_category":"Confecci\u00d3n De Zapatos",
    "sg:phone":"+34 965 71 89 67",
    "sg:postcode":"03180",
    "sg:province":"Alicante",
    "wof:name":"Calzados Cubaelx S.l",
    "wof:placetype":"venue"
},
  "geometry": {"coordinates":[-0.684607029,37.9756202698],"type":"Point"}
}