{
  "type": "Feature",
  "properties": {
    "iso:country":"ES",
    "sg:address":"Ctra. Madrid-cadiz, Km. 0267,3",
    "sg:city":"La Carolina",
    "sg:orig_category":"Empresas De Portes Y Mensajer\u00cda",
    "sg:phone":"+34 953 68 23 50",
    "sg:postcode":"23200",
    "sg:province":"Ja\u00e9n",
    "wof:name":"Servicio Directo Urgente S.l.",
    "wof:placetype":"venue"
},
  "geometry": {"coordinates":[-3.6041269302,38.2787742615],"type":"Point"}
}