{
  "type": "Feature",
  "properties": {
    "iso:country":"ES",
    "sg:address":"Barr Estacion (la), 1",
    "sg:city":"Saron",
    "sg:orig_category":"Peluquer\u00cdas",
    "sg:phone":"+34 942 56 36 33",
    "sg:postcode":"39620",
    "sg:province":"Cantabria",
    "wof:name":"Media Saro Elena",
    "wof:placetype":"venue"
},
  "geometry": {"coordinates":[-3.8524339199,43.3249206543],"type":"Point"}
}