{
  "type": "Feature",
  "properties": {
    "iso:country":"ES",
    "sg:address":"Carrer de Colon, 81",
    "sg:city":"Olesa Montserrat",
    "sg:orig_category":"Alimentaci\u00d3n General (al Por Menor)",
    "sg:phone":"+34 937 78 26 03",
    "sg:postcode":"08640",
    "sg:province":"Barcelona",
    "wof:name":"Torrabadell Basaga\u00f1a Maria Rosa",
    "wof:placetype":"venue"
},
  "geometry": {"coordinates":[1.8949999809,41.541179657],"type":"Point"}
}