{
  "type": "Feature",
  "properties": {
    "iso:country":"ES",
    "sg:address":"Carr Nou, 29",
    "sg:city":"Mao",
    "sg:orig_category":"Bisuter\u00cda, Joyer\u00cda, Relojer\u00cda (al Por Menor)",
    "sg:phone":"+34 971 36 28 46",
    "sg:postcode":"07701",
    "sg:province":"Islas Baleares",
    "wof:name":"Vives Campomar Juan",
    "wof:placetype":"venue"
},
  "geometry": {"coordinates":[4.2646436691,39.8884010315],"type":"Point"}
}