{
  "type": "Feature",
  "properties": {
    "iso:country":"ES",
    "sg:address":"Calle de Cuellar, 4",
    "sg:city":"Gomezserracin",
    "sg:orig_category":"Cajas De Ahorro",
    "sg:phone":"+34 921 16 82 39",
    "sg:postcode":"40240",
    "sg:province":"Segovia",
    "wof:name":"Caja De Ahorros Y Monte De Piedad De Segovia",
    "wof:placetype":"venue"
},
  "geometry": {"coordinates":[-4.3254985809,41.2906608582],"type":"Point"}
}