{
  "type": "Feature",
  "properties": {
    "addr:full":"Cmno Cementerio, 9 Fuentes Ebro Zaragoza 50740",
    "addr:housenumber":"9",
    "addr:postcode":"50740",
    "addr:street":"Cmno Cementerio",
    "iso:country":"ES",
    "sg:address":"Cmno Cementerio, 9",
    "sg:city":"Fuentes Ebro",
    "sg:orig_category":"Piedra, Vidrio, Cer\u00c1mica Y Porcelana",
    "sg:phone":"+34 976 16 10 38",
    "sg:postcode":"50740",
    "sg:province":"Zaragoza",
    "wof:name":"Soro Gayan Alfonso",
    "wof:placetype":"venue"
},
  "geometry": {"coordinates":[-0.6268740296,41.5112380981],"type":"Point"}
}