{
  "type": "Feature",
  "properties": {
    "addr:full":"Calle de Cuevas De San Marcos, 14 Malaga M\u00e1laga 29006",
    "addr:housenumber":"14",
    "addr:postcode":"29006",
    "addr:street":"Calle De Cuevas De San Marcos;Ma\u0301Laga",
    "iso:country":"ES",
    "sg:address":"Calle de Cuevas De San Marcos, 14",
    "sg:city":"Malaga",
    "sg:orig_category":"Chapister\u00cda",
    "sg:phone":"+34 952 32 76 04",
    "sg:postcode":"29006",
    "sg:province":"M\u00e1laga",
    "wof:name":"Chapisalas Malaga S.l.",
    "wof:placetype":"venue"
},
  "geometry": {"coordinates":[-4.4664530754,36.7008552551],"type":"Point"}
}