{
  "type": "Feature",
  "properties": {
    "addr:full":"Carrer de Manuel Aza\u00d1a, 1 Palma Islas Baleares 07006",
    "addr:housenumber":"1",
    "addr:postcode":"07006",
    "addr:street":"Carrer De Manuel Azan\u0303A",
    "iso:country":"ES",
    "sg:address":"Carrer de Manuel Aza\u00d1a, 1",
    "sg:city":"Palma",
    "sg:orig_category":"Centros M\u00c9dicos Y Sociales, Dispensarios",
    "sg:phone":"+34 971 46 50 56",
    "sg:postcode":"07006",
    "sg:province":"Islas Baleares",
    "wof:name":"Caballero Cabalgante Maria Isabel",
    "wof:placetype":"venue"
},
  "geometry": {"coordinates":[2.6634120941,39.5658607483],"type":"Point"}
}