{
  "type": "Feature",
  "properties": {
    "iso:country":"ES",
    "sg:address":"Calle de Real De Arriba, 13",
    "sg:city":"Valverde Camino",
    "sg:orig_category":"Farmacias",
    "sg:phone":"+34 959 55 00 55",
    "sg:postcode":"21600",
    "sg:province":"Huelva",
    "wof:name":"Vizcaino Vizcaino Javier",
    "wof:placetype":"venue"
},
  "geometry": {"coordinates":[-6.7535729408,37.5729408264],"type":"Point"}
}