{
  "type": "Feature",
  "properties": {
    "addr:full":"Av. Pio Xii, 29 Iru\u00f1a Navarra 31008",
    "addr:housenumber":"29",
    "addr:postcode":"31008",
    "addr:street":"Av. Pio Xii",
    "iso:country":"ES",
    "sg:address":"Av. Pio Xii, 29",
    "sg:city":"Iru\u00f1a",
    "sg:orig_category":"Librer\u00cdas",
    "sg:phone":"+34 948 25 96 31",
    "sg:postcode":"31008",
    "sg:province":"Navarra",
    "wof:name":"Joven Tejero Herminia",
    "wof:placetype":"venue"
},
  "geometry": {"coordinates":[-1.6584839821,42.8089637756],"type":"Point"}
}