{
  "type": "Feature",
  "properties": {
    "iso:country":"ES",
    "sg:address":"Calle de Pedroche, 23",
    "sg:city":"Adamuz",
    "sg:orig_category":"Persianas Interiores, Exteriores",
    "sg:phone":"+34 957 16 62 43",
    "sg:postcode":"14430",
    "sg:province":"C\u00f3rdoba",
    "wof:name":"Garcia Moreno Manuel",
    "wof:placetype":"venue"
},
  "geometry": {"coordinates":[-4.5228438377,38.0284805298],"type":"Point"}
}