{
  "type": "Feature",
  "properties": {
    "iso:country":"ES",
    "sg:address":"Calle de Alameda Las Llanas, 15",
    "sg:city":"Sestao",
    "sg:orig_category":"Panader\u00cdas, Panader\u00cdas",
    "sg:phone":"+34 944 95 13 21",
    "sg:postcode":"48910",
    "sg:province":"Vizcaya",
    "wof:name":"Perez Cano Bego\u00f1a",
    "wof:placetype":"venue"
},
  "geometry": {"coordinates":[-3.0082771778,43.3093185425],"type":"Point"}
}