{
  "type": "Feature",
  "properties": {
    "addr:full":"Ctra Prat, 36 Almeda Mercader Barcelona 08940",
    "addr:housenumber":"36",
    "addr:postcode":"08940",
    "addr:street":"Ctra Prat;Mercader Barcelona",
    "iso:country":"ES",
    "sg:address":"Ctra Prat, 36",
    "sg:city":"Almeda Mercader",
    "sg:classifiers":[
        {
            "category":"Manufacturing",
            "subcategory":"Metals",
            "type":"Manufacturing & Wholesale Goods"
        }
    ],
    "sg:phone":"+34 933 77 20 46",
    "sg:postcode":"08940",
    "sg:province":"Barcelona",
    "sg:tags":[
        "en",
        "fundiciones"
    ],
    "wof:name":"Fosa Prats S.l.",
    "wof:placetype":"venue"
},
  "geometry": {"coordinates":[2.0708940029,41.3559417725],"type":"Point"}
}