{
  "type": "Feature",
  "properties": {
    "addr:full":"Cmno Ronda (de), 188 Granada Granada 18003",
    "addr:housenumber":"188",
    "addr:postcode":"18003",
    "addr:street":"Cmno Ronda De",
    "iso:country":"ES",
    "sg:address":"Cmno Ronda (de), 188",
    "sg:city":"Granada",
    "sg:orig_category":"Chapister\u00cda",
    "sg:phone":"+34 958 29 37 50",
    "sg:postcode":"18003",
    "sg:province":"Granada",
    "wof:name":"Carrocerias Neptuno S.l.",
    "wof:placetype":"venue"
},
  "geometry": {"coordinates":[-3.6134150028,37.1832542419],"type":"Point"}
}