{
  "type": "Feature",
  "properties": {
    "addr:full":"Pl. El Se\u00f1orio, S/n Rincon Victoria M\u00e1laga 29730",
    "addr:housenumber":"s / n",
    "addr:postcode":"29730",
    "addr:street":"Ma\u0301Laga",
    "iso:country":"ES",
    "sg:address":"Pl. El Se\u00f1orio, S/n",
    "sg:city":"Rincon Victoria",
    "sg:orig_category":"Agencias Y Agentes Comerciales, Representantes",
    "sg:phone":"+34 952 97 26 55",
    "sg:postcode":"29730",
    "sg:province":"M\u00e1laga",
    "wof:name":"Rinvic Malaga S.l..",
    "wof:placetype":"venue"
},
  "geometry": {"coordinates":[-4.2807641029,36.714641571],"type":"Point"}
}