{
  "type": "Feature",
  "properties": {
    "addr:full":"Constitucion, 9 O Temple La Coru\u00f1a 15679",
    "addr:housenumber":"9 o",
    "addr:postcode":"15679",
    "addr:street":"Constitucion;La Corun\u0303A",
    "iso:country":"ES",
    "sg:address":"Constitucion, 9",
    "sg:city":"O Temple",
    "sg:orig_category":"Supermercados Y Hipermercados",
    "sg:phone":"+34 981 66 48 57",
    "sg:postcode":"15679",
    "sg:province":"La Coru\u00f1a",
    "wof:name":"Dubra Suarez Albino",
    "wof:placetype":"venue"
},
  "geometry": {"coordinates":[-8.3578081131,43.3183479309],"type":"Point"}
}