{
  "type": "Feature",
  "properties": {
    "iso:country":"ES",
    "sg:address":"Calle de Carde\u00d1osa, 34",
    "sg:city":"Madrid",
    "sg:orig_category":"Peluquer\u00cdas, Peluquer\u00cda Mixta",
    "sg:phone":"+34 915 07 47 60",
    "sg:postcode":"28053",
    "sg:province":"Madrid",
    "wof:name":"Cides Artesero Abel",
    "wof:placetype":"venue"
},
  "geometry": {"coordinates":[-3.67228508,40.383102417],"type":"Point"}
}