{
  "type": "Feature",
  "properties": {
    "addr:full":"Calle de Tirso De Molina, S/n Nueva Andalucia M\u00e1laga 29660",
    "addr:housenumber":"s / n",
    "addr:postcode":"29660",
    "addr:street":"Calle De Tirso De Molina;Ma\u0301Laga",
    "iso:country":"ES",
    "sg:address":"Calle de Tirso De Molina, S/n",
    "sg:city":"Nueva Andalucia",
    "sg:orig_category":"Asilos De Ancianos. Centros Privados",
    "sg:phone":"+34 952 81 67 92",
    "sg:postcode":"29660",
    "sg:province":"M\u00e1laga",
    "wof:name":"Ayuntamiento De Marbella",
    "wof:placetype":"venue"
},
  "geometry": {"coordinates":[-4.9778571129,36.4971427917],"type":"Point"}
}