{
  "type": "Feature",
  "properties": {
    "iso:country":"ES",
    "sg:address":"Ctra Castillo De Locubin, 3",
    "sg:city":"Fuensanta Martos",
    "sg:orig_category":"Empresas De Carpinter\u00cda Met\u00c1lica",
    "sg:phone":"+34 953 56 41 22",
    "sg:postcode":"23610",
    "sg:province":"Ja\u00e9n",
    "wof:name":"Pe\u00f1a Planelles Jose Antonio",
    "wof:placetype":"venue"
},
  "geometry": {"coordinates":[-3.9120569229,37.6458854675],"type":"Point"}
}