{
  "type": "Feature",
  "properties": {
    "iso:country":"ES",
    "sg:address":"Calle de Inmaculada Concepcion, 45",
    "sg:city":"Madrid",
    "sg:orig_category":"Veh\u00cdculos, Transporte",
    "sg:phone":"+34 915 60 02 22",
    "sg:postcode":"28019",
    "sg:province":"Madrid",
    "sg:website":"www.infonegocio.com/askwinch",
    "wof:name":"Askrom Iberica S.l",
    "wof:placetype":"venue"
},
  "geometry": {"coordinates":[-3.7125389576,40.3909721375],"type":"Point"}
}