{
  "type": "Feature",
  "properties": {
    "iso:country":"ES",
    "sg:address":"Calle de Ingeniero Iribarren, S/n",
    "sg:city":"Cordoba",
    "sg:classifiers":[
        {
            "category":"Manufacturing",
            "subcategory":"Building Materials",
            "type":"Manufacturing & Wholesale Goods"
        }
    ],
    "sg:phone":"+34 957 29 96 91",
    "sg:postcode":"14013",
    "sg:province":"C\u00f3rdoba",
    "sg:tags":[
        "cemento",
        "y",
        "de",
        "fabricaci\u00d3n",
        "cal"
    ],
    "wof:name":"Gecol Cordoba S.a.",
    "wof:placetype":"venue"
},
  "geometry": {"coordinates":[-4.7946858406,37.8482818604],"type":"Point"}
}