{
  "type": "Feature",
  "properties": {
    "iso:country":"ES",
    "sg:address":"Carrer de Escoles, 4",
    "sg:city":"S. Adria Besos",
    "sg:orig_category":"Venta, Instalaci\u00d3n, Mantenimiento De Chimeneas De Interior Y Accesorios",
    "sg:phone":"+34 933 81 92 75",
    "sg:postcode":"08930",
    "sg:province":"Barcelona",
    "wof:name":"Cosremo S.l.",
    "wof:placetype":"venue"
},
  "geometry": {"coordinates":[2.2207269669,41.4298210144],"type":"Point"}
}