{
  "type": "Feature",
  "properties": {
    "addr:full":"Calle de Gasset, S/n Sari\u00f1ena Huesca 22200",
    "addr:housenumber":"s / n",
    "addr:postcode":"22200",
    "addr:street":"Calle De Gasset",
    "iso:country":"ES",
    "sg:address":"Calle de Gasset, S/n",
    "sg:city":"Sari\u00f1ena",
    "sg:orig_category":"Centros Empresariales",
    "sg:phone":"+34 974 57 10 12",
    "sg:postcode":"22200",
    "sg:province":"Huesca",
    "wof:name":"Millera Marin Manuel",
    "wof:placetype":"venue"
},
  "geometry": {"coordinates":[-0.1600486934,41.7914466858],"type":"Point"}
}