{
  "type": "Feature",
  "properties": {
    "addr:full":"Pl Espanya, 59 Llucmajor Islas Baleares 07620",
    "addr:housenumber":"59",
    "addr:postcode":"07620",
    "addr:street":"Pl Espanya",
    "iso:country":"ES",
    "sg:address":"Pl Espanya, 59",
    "sg:city":"Llucmajor",
    "sg:orig_category":"Promotores Constructores",
    "sg:phone":"+34 971 12 07 24",
    "sg:postcode":"07620",
    "sg:province":"Islas Baleares",
    "wof:name":"Prats Garcia Antonia Maria",
    "wof:placetype":"venue"
},
  "geometry": {"coordinates":[2.8909249306,39.4906997681],"type":"Point"}
}