{
  "type": "Feature",
  "properties": {
    "iso:country":"ES",
    "sg:address":"Rio Genil, 20",
    "sg:city":"Mijas Costa",
    "sg:orig_category":"Ingeniero",
    "sg:phone":"+34 952 46 36 09",
    "sg:postcode":"29649",
    "sg:province":"M\u00e1laga",
    "wof:name":"Garcia-carpintero Laza Antonio",
    "wof:placetype":"venue"
},
  "geometry": {"coordinates":[-4.7157039642,36.4931945801],"type":"Point"}
}