{
  "type": "Feature",
  "properties": {
    "iso:country":"ES",
    "sg:address":"Avda Blasco Iba\u00d1ez, 82",
    "sg:city":"Valencia",
    "sg:orig_category":"Comercio, Reparaci\u00d3n De Bicicletas, De Motocicletas, De Accesorios",
    "sg:phone":"+34 963 69 07 75",
    "sg:postcode":"46021",
    "sg:province":"Valencia",
    "wof:name":"Top Bici S.l.",
    "wof:placetype":"venue"
},
  "geometry": {"coordinates":[-0.3518460095,39.4746246338],"type":"Point"}
}