{
  "type": "Feature",
  "properties": {
    "addr:full":"Carr Ferran Rambla, 24 Lleida Lleida 25007",
    "addr:housenumber":"24",
    "addr:postcode":"25007",
    "addr:street":"Carr Ferran Rambla",
    "iso:country":"ES",
    "sg:address":"Carr Ferran Rambla, 24",
    "sg:city":"Lleida",
    "sg:orig_category":"Complementos De Vestir (al Por Menor)",
    "sg:phone":"+34 973 23 98 79",
    "sg:postcode":"25007",
    "sg:province":"Lleida",
    "wof:name":"Comunidad De Propietarios Rambla Ferran",
    "wof:placetype":"venue"
},
  "geometry": {"coordinates":[0.627129972,41.6145210266],"type":"Point"}
}