{
  "type": "Feature",
  "properties": {
    "iso:country":"ES",
    "sg:address":"Carr Doctor Vicente Navarro Soler, 10",
    "sg:city":"Benetusser",
    "sg:orig_category":"Comercio De Cuadros, L\u00c1minas Y Reproducciones De Obras De Arte",
    "sg:phone":"+34 963 75 41 22",
    "sg:postcode":"46910",
    "sg:province":"Valencia",
    "wof:name":"Iniesta Garcia Isabel",
    "wof:placetype":"venue"
},
  "geometry": {"coordinates":[-0.3992600143,39.4200210571],"type":"Point"}
}