{
  "type": "Feature",
  "properties": {
    "addr:full":"Calle de Fray Luis De Granada, 64 Badajoz Badajoz 06008",
    "addr:housenumber":"64",
    "addr:postcode":"06008",
    "addr:street":"Calle De Fray Luis De Granada",
    "iso:country":"ES",
    "sg:address":"Calle de Fray Luis De Granada, 64",
    "sg:city":"Badajoz",
    "sg:orig_category":"Reparto A Domicilio De Productos Perecederos Y No Perecederos",
    "sg:phone":"+34 924 25 06 20",
    "sg:postcode":"06008",
    "sg:province":"Badajoz",
    "wof:name":"Distribuciones Alimenticias Vallesol S.l.",
    "wof:placetype":"venue"
},
  "geometry": {"coordinates":[-6.9562897682,38.8783607483],"type":"Point"}
}