{
  "type": "Feature",
  "properties": {
    "iso:country":"ES",
    "sg:address":"Calle de Historiador Beti, 3",
    "sg:city":"Sant Mateu",
    "sg:orig_category":"\u00d3ptica: Instrumentos (fabricaci\u00d3n)",
    "sg:phone":"+34 964 41 64 64",
    "sg:postcode":"12170",
    "sg:province":"Castell\u00f3n",
    "sg:website":"www.opticanueva.es.",
    "wof:name":"Optica Nueva Sant Mateu S.l.",
    "wof:placetype":"venue"
},
  "geometry": {"coordinates":[0.1785899997,40.4668502808],"type":"Point"}
}