{
  "type": "Feature",
  "properties": {
    "addr:full":"Ptge Oliveras, 18 Hospitalet Llobregat Barcelona 08904",
    "addr:housenumber":"18",
    "addr:postcode":"08904",
    "addr:street":"Ptge Oliveras",
    "iso:country":"ES",
    "sg:address":"Ptge Oliveras, 18",
    "sg:city":"Hospitalet Llobregat",
    "sg:classifiers":[
        {
            "category":"Taxi",
            "type":"Transportation"
        }
    ],
    "sg:phone":"+34 933 33 33 95",
    "sg:postcode":"08904",
    "sg:province":"Barcelona",
    "wof:name":"Garcia Garcia Agapito",
    "wof:placetype":"venue"
},
  "geometry": {"coordinates":[2.1174519062,41.3695831299],"type":"Point"}
}