{
  "type": "Feature",
  "properties": {
    "iso:country":"ES",
    "sg:address":"Calle de Nueva, 47",
    "sg:city":"Feria",
    "sg:orig_category":"Agencias Y Agentes Comerciales, Representantes",
    "sg:phone":"+34 924 69 42 78",
    "sg:postcode":"06390",
    "sg:province":"Badajoz",
    "wof:name":"Veira Boquete Jose Ignacio",
    "wof:placetype":"venue"
},
  "geometry": {"coordinates":[-6.5613059998,38.5123748779],"type":"Point"}
}