{
  "type": "Feature",
  "properties": {
    "iso:country":"ES",
    "sg:address":"Calle de Pedro Perez Fernandez, 6",
    "sg:city":"Sevilla",
    "sg:classifiers":[
        {
            "category":"Professional",
            "subcategory":"Management & Consulting",
            "type":"Services"
        }
    ],
    "sg:phone":"+34 954 28 55 65",
    "sg:postcode":"41011",
    "sg:province":"Sevilla",
    "sg:tags":[
        "asesor\u00cda",
        "en",
        "marketing"
    ],
    "wof:name":"En Clave Promocional I S.a.",
    "wof:placetype":"venue"
},
  "geometry": {"coordinates":[-6.0011501312,37.3751945496],"type":"Point"}
}