{
  "type": "Feature",
  "properties": {
    "addr:full":"Calle de Puente Del Cura, 3 Arganda Madrid 28500",
    "addr:housenumber":"3",
    "addr:postcode":"28500",
    "addr:street":"Calle De Puente Del Cura",
    "iso:country":"ES",
    "sg:address":"Calle de Puente Del Cura, 3",
    "sg:city":"Arganda",
    "sg:orig_category":"Bancos",
    "sg:phone":"+34 918 71 13 04",
    "sg:postcode":"28500",
    "sg:province":"Madrid",
    "sg:website":"www.deutsche-bank.es",
    "wof:name":"Deutsche Bank S.a.e.",
    "wof:placetype":"venue"
},
  "geometry": {"coordinates":[-3.4393460751,40.3009376526],"type":"Point"}
}