{
  "type": "Feature",
  "properties": {
    "addr:full":"Ocho Mil Catorce, 16 Las Palmas Las Palmas 35018",
    "addr:housenumber":"16",
    "addr:postcode":"35018",
    "addr:street":"Catorce",
    "iso:country":"ES",
    "sg:address":"Ocho Mil Catorce, 16",
    "sg:city":"Las Palmas",
    "sg:orig_category":"Venta, Localizaci\u00d3n, Reparaci\u00d3n De Material E Instrumental M\u00c9dico",
    "sg:phone":"+34 928 67 48 77",
    "sg:postcode":"35018",
    "sg:province":"Las Palmas",
    "sg:website":"www.emergencia.com",
    "wof:name":"Emergencia 2000 S. A.",
    "wof:placetype":"venue"
},
  "geometry": {"coordinates":[-15.5378570557,28.0759296417],"type":"Point"}
}