{
  "type": "Feature",
  "properties": {
    "iso:country":"ES",
    "sg:address":"A Valenza, 97",
    "sg:city":"Valenza",
    "sg:orig_category":"Rectificaci\u00d3n, Mecanizado, Fresado",
    "sg:phone":"+34 988 24 34 04",
    "sg:postcode":"32002",
    "sg:province":"Ourense",
    "wof:name":"Alvarez Dominguez Ricardo",
    "wof:placetype":"venue"
},
  "geometry": {"coordinates":[-7.8853440285,42.3171424866],"type":"Point"}
}