{
  "type": "Feature",
  "properties": {
    "iso:country":"ES",
    "sg:address":"Carrer de Cantabria, 73",
    "sg:city":"Barcelona",
    "sg:orig_category":"Iglesia Cat\u00d3lica",
    "sg:phone":"+34 933 13 52 62",
    "sg:postcode":"08020",
    "sg:province":"Barcelona",
    "wof:name":"Parroquia Santisimo Sacramento",
    "wof:placetype":"venue"
},
  "geometry": {"coordinates":[2.1987810135,41.4238586426],"type":"Point"}
}