{
  "type": "Feature",
  "properties": {
    "iso:country":"ES",
    "sg:address":"Pda Sant Feliu, 29",
    "sg:city":"Girona",
    "sg:orig_category":"Iglesia Cat\u00d3lica",
    "sg:phone":"+34 972 20 14 07",
    "sg:postcode":"17004",
    "sg:province":"Girona",
    "wof:name":"Bisbat De Girona",
    "wof:placetype":"venue"
},
  "geometry": {"coordinates":[2.8248329163,41.9878082275],"type":"Point"}
}