{
  "type": "Feature",
  "properties": {
    "iso:country":"ES",
    "sg:address":"Fentina(pol Ind Xara), 3",
    "sg:city":"Carrascalet",
    "sg:orig_category":"Mec\u00c1nico Del Autom\u00d3vil",
    "sg:phone":"+34 962 48 00 95",
    "sg:postcode":"46680",
    "sg:province":"Valencia",
    "wof:name":"Talleres Plancha Y Pintura Xara S.l.",
    "wof:placetype":"venue"
},
  "geometry": {"coordinates":[-0.4383490086,39.1962852478],"type":"Point"}
}