{
  "type": "Feature",
  "properties": {
    "addr:full":"Calle de Colon, 2 Benaguasil Valencia 46180",
    "addr:housenumber":"2",
    "addr:postcode":"46180",
    "addr:street":"Calle De Colon",
    "iso:country":"ES",
    "sg:address":"Calle de Colon, 2",
    "sg:city":"Benaguasil",
    "sg:orig_category":"Plomeros",
    "sg:phone":"+34 962 73 00 38",
    "sg:postcode":"46180",
    "sg:province":"Valencia",
    "wof:name":"Mullor Garrido Ramon",
    "wof:placetype":"venue"
},
  "geometry": {"coordinates":[-0.5851669908,39.5979499817],"type":"Point"}
}