{
  "type": "Feature",
  "properties": {
    "addr:full":"Trva Doctor Jose Fari\u00d1a, 2 Betanzos La Coru\u00f1a 15300",
    "addr:housenumber":"2",
    "addr:postcode":"15300",
    "addr:street":"Trva Doctor Jose Farin\u0303A;La",
    "iso:country":"ES",
    "sg:address":"Trva Doctor Jose Fari\u00d1a, 2",
    "sg:city":"Betanzos",
    "sg:orig_category":"Material Y Suministros Para Veterinarios",
    "sg:phone":"+34 981 77 50 96",
    "sg:postcode":"15300",
    "sg:province":"La Coru\u00f1a",
    "wof:name":"Agropecuaria Betanzos S.l.l.",
    "wof:placetype":"venue"
},
  "geometry": {"coordinates":[-8.226767,43.269627],"type":"Point"}
}