{
  "type": "Feature",
  "properties": {
    "addr:full":"Calle de Domingo Beltran De Otazu, 56 Vitoria-gasteiz \u00c1lava 01012",
    "addr:housenumber":"56",
    "addr:postcode":"01012",
    "addr:street":"Calle De Domingo Beltran De Otazu",
    "iso:country":"ES",
    "sg:address":"Calle de Domingo Beltran De Otazu, 56",
    "sg:city":"Vitoria-gasteiz",
    "sg:orig_category":"Contables",
    "sg:phone":"+34 945 24 71 54",
    "sg:postcode":"01012",
    "sg:province":"\u00c1lava",
    "wof:name":"Acc Asesores S.c.",
    "wof:placetype":"venue"
},
  "geometry": {"coordinates":[-2.6762549877,42.8552055359],"type":"Point"}
}