{
  "type": "Feature",
  "properties": {
    "addr:full":"Calle de Ramon Gallud, 70 Torrevieja Alicante 03180",
    "addr:housenumber":"70",
    "addr:postcode":"03180",
    "addr:street":"Calle De Ramon Gallud",
    "iso:country":"ES",
    "sg:address":"Calle de Ramon Gallud, 70",
    "sg:city":"Torrevieja",
    "sg:orig_category":"Inform\u00c1tica (estudios, Servicios, Asesor\u00cda, Formaci\u00d3n)",
    "sg:phone":"+34 965 71 09 99",
    "sg:postcode":"03180",
    "sg:province":"Alicante",
    "wof:name":"Informatica Torrevieja Perez Martinez S.l.",
    "wof:placetype":"venue"
},
  "geometry": {"coordinates":[-0.6802250147,37.9771842957],"type":"Point"}
}