{
  "type": "Feature",
  "properties": {
    "iso:country":"ES",
    "sg:address":"Calle de Manuel De Vera, S/n",
    "sg:city":"Valle De Guerra",
    "sg:classifiers":[
        {
            "category":"Taxi",
            "type":"Transportation"
        }
    ],
    "sg:phone":"+34 922 54 35 21",
    "sg:postcode":"38270",
    "sg:province":"Santa Cruz De Tenerife",
    "wof:name":"Perez Perez Domingo",
    "wof:placetype":"venue"
},
  "geometry": {"coordinates":[-16.3963832855,28.5111694336],"type":"Point"}
}