{
  "type": "Feature",
  "properties": {
    "iso:country":"ES",
    "sg:address":"Calle de Alfonso Rodriguez Castelao, 9",
    "sg:city":"Madrid",
    "sg:orig_category":"Agencias De Viajes",
    "sg:phone":"+34 913 16 74 25",
    "sg:postcode":"28035",
    "sg:province":"Madrid",
    "wof:name":"Aramendi Fernandez De La Cruz Maite",
    "wof:placetype":"venue"
},
  "geometry": {"coordinates":[-3.7347891331,40.4821929932],"type":"Point"}
}