{
  "type": "Feature",
  "properties": {
    "addr:full":"Calle de Badajoz, 5 Flores Del Sil Le\u00f3n 24400",
    "addr:housenumber":"5",
    "addr:postcode":"24400",
    "addr:street":"Calle De Badajoz",
    "iso:country":"ES",
    "sg:address":"Calle de Badajoz, 5",
    "sg:city":"Flores Del Sil",
    "sg:orig_category":"Empresas De Carpinter\u00cda Met\u00c1lica",
    "sg:phone":"+34 987 40 52 72",
    "sg:postcode":"24400",
    "sg:province":"Le\u00f3n",
    "wof:name":"Accesorios Noroeste S.l.",
    "wof:placetype":"venue"
},
  "geometry": {"coordinates":[-6.6125044823,42.5461769104],"type":"Point"}
}