{
  "type": "Feature",
  "properties": {
    "addr:full":"Calle de Hernan Cortes, S/n Alguazas Murcia 30560",
    "addr:housenumber":"s / n",
    "addr:postcode":"30560",
    "addr:street":"Calle De Hernan Cortes",
    "iso:country":"ES",
    "sg:address":"Calle de Hernan Cortes, S/n",
    "sg:city":"Alguazas",
    "sg:orig_category":"Centros De Educaci\u00d3n Especial",
    "sg:phone":"+34 968 62 02 04",
    "sg:postcode":"30560",
    "sg:province":"Murcia",
    "wof:name":"Colegio Publico Nuestra Se\u00f1ora Del Carmen",
    "wof:placetype":"venue"
},
  "geometry": {"coordinates":[-1.2499409914,38.0558204651],"type":"Point"}
}