{
  "type": "Feature",
  "properties": {
    "iso:country":"ES",
    "sg:address":"Calle de Blanqueadores, 16",
    "sg:city":"Merida",
    "sg:orig_category":"Venta, Colocaci\u00d3n, Reparaci\u00d3n De Radiadores Para Veh\u00cdculos",
    "sg:phone":"+34 924 30 13 65",
    "sg:postcode":"06800",
    "sg:province":"Badajoz",
    "wof:name":"Vidal Serrano Manuel",
    "wof:placetype":"venue"
},
  "geometry": {"coordinates":[-6.3302159309,38.9256858826],"type":"Point"}
}