{
  "type": "Feature",
  "properties": {
    "iso:country":"ES",
    "sg:address":"Calle de Sebastian De Benalcazar, 12",
    "sg:city":"Cordoba",
    "sg:orig_category":"Negocio De Materiales De Construcci\u00d3n",
    "sg:phone":"+34 957 40 00 65",
    "sg:postcode":"14006",
    "sg:province":"C\u00f3rdoba",
    "wof:name":"Material Construccion Jr. Garcia Fernandez S.l.",
    "wof:placetype":"venue"
},
  "geometry": {"coordinates":[-4.7863321304,37.8945426941],"type":"Point"}
}