{
  "type": "Feature",
  "properties": {
    "iso:country":"ES",
    "sg:address":"Calle de Tiermas, 11",
    "sg:city":"Zaragoza",
    "sg:orig_category":"Confecci\u00d3n (fabricaci\u00d3n, Al Por Mayor)",
    "sg:phone":"+34 976 20 01 83",
    "sg:postcode":"50002",
    "sg:province":"Zaragoza",
    "wof:name":"Vaillant Corbacho Lucia",
    "wof:placetype":"venue"
},
  "geometry": {"coordinates":[-0.8625584245,41.6502876282],"type":"Point"}
}