{
  "type": "Feature",
  "properties": {
    "addr:full":"Calle de Padre Damian, 9 Montesinos Alicante 03187",
    "addr:housenumber":"9",
    "addr:postcode":"03187",
    "addr:street":"Calle De Padre Damian",
    "iso:country":"ES",
    "sg:address":"Calle de Padre Damian, 9",
    "sg:city":"Montesinos",
    "sg:orig_category":"Insecticidas, Fumigaci\u00d3n",
    "sg:phone":"+34 966 72 10 14",
    "sg:postcode":"03187",
    "sg:province":"Alicante",
    "wof:name":"Saez Aniorte Jose Manuel",
    "wof:placetype":"venue"
},
  "geometry": {"coordinates":[-0.7478150129,38.0282936096],"type":"Point"}
}