{
  "type": "Feature",
  "properties": {
    "addr:full":"Calle de Doctor Castelo, 48 Madrid Madrid 28009",
    "addr:housenumber":"48",
    "addr:postcode":"madrid;28009",
    "addr:street":"Calle De Doctor Castelo",
    "iso:country":"ES",
    "sg:address":"Calle de Doctor Castelo, 48",
    "sg:city":"Madrid",
    "sg:orig_category":"Ingenier\u00cda, Centros De Estudios (diversos)",
    "sg:phone":"+34 915 74 77 96",
    "sg:postcode":"28009",
    "sg:province":"Madrid",
    "wof:name":"Fajardo Castro Juan",
    "wof:placetype":"venue"
},
  "geometry": {"coordinates":[-3.6733736992,40.4202156067],"type":"Point"}
}