{
  "type": "Feature",
  "properties": {
    "iso:country":"ES",
    "sg:address":"Calle de Rio Sorbe, S/n",
    "sg:city":"Alcala Henares",
    "sg:orig_category":"Peluqueros: De Se\u00d1oras",
    "sg:phone":"+34 918 82 44 53",
    "sg:postcode":"28803",
    "sg:province":"Madrid",
    "sg:website":"www.rizos.es",
    "wof:name":"Gonzalez De Miguel Sonia",
    "wof:placetype":"venue"
},
  "geometry": {"coordinates":[-3.3636910915,40.4744491577],"type":"Point"}
}