{
  "type": "Feature",
  "properties": {
    "iso:country":"ES",
    "sg:address":"Nueve De Agosto, 24",
    "sg:city":"Ribeira-santa Uxia",
    "sg:orig_category":"Inform\u00c1tica: Mini Y Grandes Sistemas (venta, Instalaci\u00d3n, Mantenimiento)",
    "sg:phone":"+34 981 84 30 15",
    "sg:postcode":"15960",
    "sg:province":"La Coru\u00f1a",
    "wof:name":"Aldera Networks S.l.u.",
    "wof:placetype":"venue"
},
  "geometry": {"coordinates":[-8.9965953827,42.5522918701],"type":"Point"}
}