{
  "type": "Feature",
  "properties": {
    "addr:full":"Luga Carrus Poligono Industrial, S/n Elche Alicante 03291",
    "addr:postcode":"03291",
    "addr:street":"Poligono Industrial S / N",
    "iso:country":"ES",
    "sg:address":"Luga Carrus Poligono Industrial, S/n",
    "sg:city":"Elche",
    "sg:orig_category":"Complementos Para Pasteler\u00cdas, Confiter\u00cdas Y Chocolater\u00cdas",
    "sg:phone":"+34 965 46 12 01",
    "sg:postcode":"03291",
    "sg:province":"Alicante",
    "wof:name":"Codipan S.l.",
    "wof:placetype":"venue"
},
  "geometry": {"coordinates":[-0.6765189767,38.2994346619],"type":"Point"}
}