{
  "type": "Feature",
  "properties": {
    "iso:country":"ES",
    "sg:address":"Carrer de Colom, 329",
    "sg:city":"Terrassa",
    "sg:orig_category":"Frutas, Legumbres Frescas Y Tempranas (al Por Menor)",
    "sg:phone":"+34 937 31 29 79",
    "sg:postcode":"08223",
    "sg:province":"Barcelona",
    "wof:name":"Sanchez Lopez Guadalupe",
    "wof:placetype":"venue"
},
  "geometry": {"coordinates":[2.0254640579,41.5545883179],"type":"Point"}
}