{
  "type": "Feature",
  "properties": {
    "addr:full":"Calle de Cervantes, 28 Saceruela Ciudad Real 13414",
    "addr:housenumber":"28",
    "addr:postcode":"saceruela;13414",
    "addr:street":"Calle De Cervantes",
    "iso:country":"ES",
    "sg:address":"Calle de Cervantes, 28",
    "sg:city":"Saceruela",
    "sg:orig_category":"Cajas De Ahorro",
    "sg:phone":"+34 926 77 99 02",
    "sg:postcode":"13414",
    "sg:province":"Ciudad Real",
    "wof:name":"Unicaja",
    "wof:placetype":"venue"
},
  "geometry": {"coordinates":[-4.6081233025,38.9431915283],"type":"Point"}
}