{
  "type": "Feature",
  "properties": {
    "addr:full":"Calle de Ave Maria, 44 Madrid Madrid 28012",
    "addr:housenumber":"44",
    "addr:postcode":"madrid;28012",
    "addr:street":"Calle De Ave Maria",
    "iso:country":"ES",
    "sg:address":"Calle de Ave Maria, 44",
    "sg:city":"Madrid",
    "sg:orig_category":"Radiocomunicaciones, Telefon\u00cda M\u00d3vil, Radiomensajer\u00cda: Servicios, Comercializaci\u00d3n",
    "sg:phone":"+34 914 68 73 43",
    "sg:postcode":"28012",
    "sg:province":"Madrid",
    "wof:name":"Lucky 786 Madrid S.l.",
    "wof:placetype":"venue"
},
  "geometry": {"coordinates":[-3.7010211945,40.4096984863],"type":"Point"}
}