{
  "type": "Feature",
  "properties": {
    "iso:country":"ES",
    "sg:address":"Avda Angel Guimera, 49",
    "sg:city":"Santa Cruz De Tenerife",
    "sg:orig_category":"Doctores En Medicina",
    "sg:phone":"+34 922 27 15 97",
    "sg:postcode":"38003",
    "sg:province":"Santa Cruz De Tenerife",
    "wof:name":"Montes De Oca Arias Leoncio",
    "wof:placetype":"venue"
},
  "geometry": {"coordinates":[-16.3326644897,28.4846744537],"type":"Point"}
}