{
  "type": "Feature",
  "properties": {
    "iso:country":"ES",
    "sg:address":"Calle de Berenisa, 3",
    "sg:city":"Madrid",
    "sg:orig_category":"Agentes, Concesionarios Y Sucursales De Veh\u00cdculos",
    "sg:phone":"+34 913 07 17 27",
    "sg:postcode":"28023",
    "sg:province":"Madrid",
    "wof:name":"Talleres Pescador S.l.",
    "wof:placetype":"venue"
},
  "geometry": {"coordinates":[-3.7792429924,40.4584274292],"type":"Point"}
}