{
  "type": "Feature",
  "properties": {
    "addr:full":"Puig I Cadafalch, 13 Cunit Tarragona 43881",
    "addr:housenumber":"13",
    "addr:postcode":"43881",
    "addr:street":"Cadafalch",
    "iso:country":"ES",
    "sg:address":"Puig I Cadafalch, 13",
    "sg:city":"Cunit",
    "sg:orig_category":"\u00d3ptica: Instrumentos (fabricaci\u00d3n)",
    "sg:phone":"+34 977 67 63 53",
    "sg:postcode":"43881",
    "sg:province":"Tarragona",
    "wof:name":"Ruiz Garcia Yolanda",
    "wof:placetype":"venue"
},
  "geometry": {"coordinates":[1.6356970072,41.1967391968],"type":"Point"}
}