{
  "type": "Feature",
  "properties": {
    "iso:country":"ES",
    "sg:address":"Calle de Paules, 16",
    "sg:city":"Monzon",
    "sg:orig_category":"Empresas De Pintura Y Revestimientos",
    "sg:phone":"+34 974 41 55 15",
    "sg:postcode":"22400",
    "sg:province":"Huesca",
    "wof:name":"Alriols Causada Jose Antonio",
    "wof:placetype":"venue"
},
  "geometry": {"coordinates":[0.1912259012,41.9141921997],"type":"Point"}
}