{
  "type": "Feature",
  "properties": {
    "addr:full":"Calle de Guadalajara, 20 Salamanca Salamanca 37003",
    "addr:housenumber":"20",
    "addr:postcode":"37003",
    "addr:street":"Calle De Guadalajara",
    "iso:country":"ES",
    "sg:address":"Calle de Guadalajara, 20",
    "sg:city":"Salamanca",
    "sg:orig_category":"Promotores Constructores",
    "sg:phone":"+34 923 18 79 53",
    "sg:postcode":"37003",
    "sg:province":"Salamanca",
    "wof:name":"Compa\u00f1ia Castellana De Edificaciones Y Obras S.a.",
    "wof:placetype":"venue"
},
  "geometry": {"coordinates":[-5.6500358582,40.9677734375],"type":"Point"}
}