{
  "type": "Feature",
  "properties": {
    "addr:full":"Rua Travesia De Vigo, 207 Roris Pontevedra 36207",
    "addr:housenumber":"207",
    "addr:postcode":"36207",
    "addr:street":"Rua Travesia De Vigo",
    "iso:country":"ES",
    "sg:address":"Rua Travesia De Vigo, 207",
    "sg:city":"Roris",
    "sg:orig_category":"Empresas De Limpieza",
    "sg:phone":"+34 986 27 27 55",
    "sg:postcode":"36207",
    "sg:province":"Pontevedra",
    "wof:name":"Garcia Rodriguez Dolores",
    "wof:placetype":"venue"
},
  "geometry": {"coordinates":[-8.6667003632,42.25],"type":"Point"}
}