{
  "type": "Feature",
  "properties": {
    "addr:full":"Rua Poeta Uxio Novoneyra (do), S/n Pontevedra Pontevedra 36004",
    "addr:housenumber":"s / n",
    "addr:postcode":"36004",
    "addr:street":"Rua Poeta Uxio",
    "iso:country":"ES",
    "sg:address":"Rua Poeta Uxio Novoneyra (do), S/n",
    "sg:city":"Pontevedra",
    "sg:orig_category":"Empresarios",
    "sg:phone":"+34 986 85 19 19",
    "sg:postcode":"36004",
    "sg:province":"Pontevedra",
    "wof:name":"Sociedad Crespo Sandoval S.l.",
    "wof:placetype":"venue"
},
  "geometry": {"coordinates":[-8.6387691498,42.4276542664],"type":"Point"}
}