{
  "type": "Feature",
  "properties": {
    "iso:country":"ES",
    "sg:address":"Calle de Ponce, 6",
    "sg:city":"Jerez De La Frontera",
    "sg:orig_category":"Locales Y Clases De Danza",
    "sg:phone":"+34 956 33 29 14",
    "sg:postcode":"11403",
    "sg:province":"C\u00e1diz",
    "wof:name":"Rios Fernandez Antonio",
    "wof:placetype":"venue"
},
  "geometry": {"coordinates":[-6.1400141716,36.6888084412],"type":"Point"}
}