{
  "type": "Feature",
  "properties": {
    "iso:country":"ES",
    "sg:address":"Calle de Santa Maria De La Cabeza, 20",
    "sg:city":"Majadahonda",
    "sg:orig_category":"Electromec\u00c1nica",
    "sg:phone":"+34 916 34 57 57",
    "sg:postcode":"28220",
    "sg:province":"Madrid",
    "wof:name":"Jupamauto S.l.",
    "wof:placetype":"venue"
},
  "geometry": {"coordinates":[-3.8708364964,40.4723548889],"type":"Point"}
}