{
  "type": "Feature",
  "properties": {
    "iso:country":"ES",
    "sg:address":"Calle de San Quirce, 3",
    "sg:city":"Valladolid",
    "sg:orig_category":"Carnicer\u00cdas, Carnicer\u00cdas",
    "sg:phone":"+34 983 35 01 09",
    "sg:postcode":"47003",
    "sg:province":"Valladolid",
    "wof:name":"Heras Cimas Julio De Las",
    "wof:placetype":"venue"
},
  "geometry": {"coordinates":[-4.7294502258,41.6568222046],"type":"Point"}
}