{
  "type": "Feature",
  "properties": {
    "addr:full":"Calle de Martinez Marina, 2 Gijon Asturias 33201",
    "addr:housenumber":"2",
    "addr:postcode":"33201",
    "addr:street":"Calle De Martinez Marina",
    "iso:country":"ES",
    "sg:address":"Calle de Martinez Marina, 2",
    "sg:city":"Gijon",
    "sg:orig_category":"Compraventa De Antig\u00dcedades",
    "sg:phone":"+34 985 35 63 07",
    "sg:postcode":"33201",
    "sg:province":"Asturias",
    "wof:name":"Caballin Mu\u00f1iz David Armando",
    "wof:placetype":"venue"
},
  "geometry": {"coordinates":[-5.662498951,43.5428352356],"type":"Point"}
}