{
  "type": "Feature",
  "properties": {
    "iso:country":"ES",
    "sg:address":"Calle de Madre Soledad Torres Acosta, 10",
    "sg:city":"Jaen",
    "sg:orig_category":"Asesor\u00cda De Formaci\u00d3n Y Gesti\u00d3n De Personal",
    "sg:phone":"+34 953 26 05 64",
    "sg:postcode":"23001",
    "sg:province":"Ja\u00e9n",
    "wof:name":"Alvarez Begara Adolfo",
    "wof:placetype":"venue"
},
  "geometry": {"coordinates":[-3.7895202637,37.7691078186],"type":"Point"}
}