{
  "type": "Feature",
  "properties": {
    "addr:full":"Rua Sar (de), 49 Santiago De Compostela La Coru\u00f1a 15702",
    "addr:housenumber":"49",
    "addr:postcode":"15702",
    "addr:street":"Rua Sar De;Corun\u0303A",
    "iso:country":"ES",
    "sg:address":"Rua Sar (de), 49",
    "sg:city":"Santiago De Compostela",
    "sg:orig_category":"Asesor\u00cda Fiscal Y Jur\u00cddica",
    "sg:phone":"+34 981 58 44 50",
    "sg:postcode":"15702",
    "sg:province":"La Coru\u00f1a",
    "wof:name":"Asesoria Estradense S.l.",
    "wof:placetype":"venue"
},
  "geometry": {"coordinates":[-8.5368671417,42.8733100891],"type":"Point"}
}