{
  "type": "Feature",
  "properties": {
    "iso:country":"ES",
    "sg:address":"Calle de Benjumeda, 37",
    "sg:city":"Cadiz",
    "sg:orig_category":"Librer\u00cdas",
    "sg:phone":"+34 956 21 13 50",
    "sg:postcode":"11003",
    "sg:province":"C\u00e1diz",
    "sg:website":"www.jet.es/lib",
    "wof:name":"Libreria Universitaria Tecnico Empresarial S.l.",
    "wof:placetype":"venue"
},
  "geometry": {"coordinates":[-6.3012061119,36.5339736938],"type":"Point"}
}