{
  "type": "Feature",
  "properties": {
    "addr:full":"Calle de Motril, 12 Almeria Almer\u00eda 04007",
    "addr:housenumber":"12",
    "addr:postcode":"04007",
    "addr:street":"Calle De Motril",
    "iso:country":"ES",
    "sg:address":"Calle de Motril, 12",
    "sg:city":"Almeria",
    "sg:orig_category":"Ropa Para Se\u00d1oras Y Caballeros (al Por Menor)",
    "sg:phone":"+34 950 26 37 81",
    "sg:postcode":"04007",
    "sg:province":"Almer\u00eda",
    "wof:name":"Blanco Gomez Ana",
    "wof:placetype":"venue"
},
  "geometry": {"coordinates":[-2.4501109123,36.8289031982],"type":"Point"}
}