{
  "type": "Feature",
  "properties": {
    "addr:full":"Calle de Eulogio Serdan, 18 Vitoria-gasteiz \u00c1lava 01012",
    "addr:housenumber":"18",
    "addr:postcode":"01012",
    "addr:street":"Calle De Eulogio Serdan",
    "iso:country":"ES",
    "sg:address":"Calle de Eulogio Serdan, 18",
    "sg:city":"Vitoria-gasteiz",
    "sg:orig_category":"Suministros Para Carrocer\u00cdas",
    "sg:phone":"+34 945 22 52 62",
    "sg:postcode":"01012",
    "sg:province":"\u00c1lava",
    "wof:name":"Carrocerias Ceballos Hermanos S. L.",
    "wof:placetype":"venue"
},
  "geometry": {"coordinates":[-2.6758389473,42.8531303406],"type":"Point"}
}