{
  "type": "Feature",
  "properties": {
    "iso:country":"ES",
    "sg:address":"Rua Urzaiz, 18",
    "sg:city":"Vigo",
    "sg:orig_category":"Parques De Atracciones Y Centros De Esparcimiento",
    "sg:phone":"+34 986 43 78 28",
    "sg:postcode":"36201",
    "sg:province":"Pontevedra",
    "wof:name":"Union De Operadores Reunidos S.a.",
    "wof:placetype":"venue"
},
  "geometry": {"coordinates":[-8.7192077637,42.2354278564],"type":"Point"}
}