{
  "type": "Feature",
  "properties": {
    "iso:country":"ES",
    "sg:address":"Calle de Real, 41",
    "sg:city":"Lachar",
    "sg:orig_category":"Iglesia Cat\u00d3lica",
    "sg:phone":"+34 958 45 70 30",
    "sg:postcode":"18327",
    "sg:province":"Granada",
    "wof:name":"Parroquia Nuestra Se\u00f1ora Del Rosario",
    "wof:placetype":"venue"
},
  "geometry": {"coordinates":[-3.832901001,37.1963806152],"type":"Point"}
}