{
  "type": "Feature",
  "properties": {
    "addr:full":"Carr Barcelona, 9 S. Hilari Sacalm Girona 17403",
    "addr:housenumber":"9",
    "addr:postcode":"17403",
    "addr:street":"Carr Barcelona",
    "iso:country":"ES",
    "sg:address":"Carr Barcelona, 9",
    "sg:city":"S. Hilari Sacalm",
    "sg:orig_category":"Controles De Edificaci\u00d3n (construcci\u00d3n, Seguridad)",
    "sg:phone":"+34 972 86 92 43",
    "sg:postcode":"17403",
    "sg:province":"Girona",
    "wof:name":"Toro Luque Angel",
    "wof:placetype":"venue"
},
  "geometry": {"coordinates":[2.5119540691,41.8778266907],"type":"Point"}
}