{
  "type": "Feature",
  "properties": {
    "addr:full":"C/ Concepcion Arenal, 77 Elche Alicante 03201",
    "addr:housenumber":"77",
    "addr:postcode":"03201",
    "addr:street":"C / Concepcion Arenal",
    "iso:country":"ES",
    "sg:address":"C/ Concepcion Arenal, 77",
    "sg:city":"Elche",
    "sg:orig_category":"Pod\u00d3logos: Pedicuros",
    "sg:phone":"+34 966 22 53 77",
    "sg:postcode":"03201",
    "sg:province":"Alicante",
    "wof:name":"Perez Rico Javier",
    "wof:placetype":"venue"
},
  "geometry": {"coordinates":[-0.7072489858,38.2639732361],"type":"Point"}
}