{
  "type": "Feature",
  "properties": {
    "iso:country":"ES",
    "sg:address":"Calle de Infantas, 6",
    "sg:city":"Alcorcon",
    "sg:orig_category":"Persianas Interiores, Exteriores",
    "sg:phone":"+34 916 43 63 19",
    "sg:postcode":"28922",
    "sg:province":"Madrid",
    "wof:name":"Landa Aldape Francisco Javier",
    "wof:placetype":"venue"
},
  "geometry": {"coordinates":[-3.8320252895,40.3466720581],"type":"Point"}
}