{
  "type": "Feature",
  "properties": {
    "iso:country":"ES",
    "sg:address":"Calle de San Felipe Neri, 1",
    "sg:city":"Alcala Henares",
    "sg:orig_category":"Ropa Y Accesorios",
    "sg:phone":"+34 918 83 37 44",
    "sg:postcode":"28801",
    "sg:province":"Madrid",
    "wof:name":"Tradin S.l.",
    "wof:placetype":"venue"
},
  "geometry": {"coordinates":[-3.3688857555,40.481212616],"type":"Point"}
}