{
  "type": "Feature",
  "properties": {
    "iso:country":"ES",
    "sg:address":"Calle de Ruperto Chapi, 1",
    "sg:city":"Palmas De Gran Canaria",
    "sg:orig_category":"Zapatos (al Por Menor)",
    "sg:phone":"+34 928 41 39 52",
    "sg:postcode":"35013",
    "sg:province":"Las Palmas",
    "wof:name":"Monzon Santana Carmelo",
    "wof:placetype":"venue"
},
  "geometry": {"coordinates":[-15.4467782974,28.0940475464],"type":"Point"}
}