{
  "type": "Feature",
  "properties": {
    "addr:full":"Calle de Fuerzas Armadas, S/n Estepona M\u00e1laga 29680",
    "addr:housenumber":"s / n",
    "addr:postcode":"29680",
    "addr:street":"Calle De Fuerzas Armadas",
    "iso:country":"ES",
    "sg:address":"Calle de Fuerzas Armadas, S/n",
    "sg:city":"Estepona",
    "sg:orig_category":"Electrodom\u00c9sticos (al Por Menor)",
    "sg:phone":"+34 952 80 03 82",
    "sg:postcode":"29680",
    "sg:province":"M\u00e1laga",
    "wof:name":"Mena Quintero Juan Jose",
    "wof:placetype":"venue"
},
  "geometry": {"coordinates":[-5.1507139206,36.4274711609],"type":"Point"}
}