{
  "type": "Feature",
  "properties": {
    "addr:full":"Prol. S. Miguel, 2 Guadix Granada 18500",
    "addr:housenumber":"2",
    "addr:postcode":"18500",
    "addr:street":"Prol. S. Miguel",
    "iso:country":"ES",
    "sg:address":"Prol. S. Miguel, 2",
    "sg:city":"Guadix",
    "sg:orig_category":"Confecci\u00d3n (fabricaci\u00d3n, Al Por Mayor)",
    "sg:phone":"+34 958 66 18 06",
    "sg:postcode":"18500",
    "sg:province":"Granada",
    "wof:name":"Manuel Ruiz Ruiz Y Otros C.b.",
    "wof:placetype":"venue"
},
  "geometry": {"coordinates":[-3.1385910511,37.3029594421],"type":"Point"}
}