{
  "type": "Feature",
  "properties": {
    "iso:country":"ES",
    "sg:address":"Calle de Antonio Lopez Torres, 20",
    "sg:city":"Madrid",
    "sg:orig_category":"Alquiler De Bicicletas Y Motocicletas",
    "sg:phone":"+34 913 81 51 24",
    "sg:postcode":"28050",
    "sg:province":"Madrid",
    "wof:name":"Ruiz Adame Jose Luis",
    "wof:placetype":"venue"
},
  "geometry": {"coordinates":[-3.6278862953,40.4765968323],"type":"Point"}
}