{
  "type": "Feature",
  "properties": {
    "iso:country":"ES",
    "sg:address":"Pso. Maritimo, S/n",
    "sg:city":"Torrox-costa",
    "sg:orig_category":"Molduras, Junquillos, Listones Y Molduras Perforadas",
    "sg:phone":"+34 952 53 13 22",
    "sg:postcode":"29793",
    "sg:province":"M\u00e1laga",
    "wof:name":"Montilla Martin Francisco",
    "wof:placetype":"venue"
},
  "geometry": {"coordinates":[-3.9646790028,36.729309082],"type":"Point"}
}