{
  "type": "Feature",
  "properties": {
    "addr:full":"Calle de Luis Bu\u00d1uel, 21 Almoradi Alicante 03160",
    "addr:housenumber":"21",
    "addr:postcode":"03160",
    "addr:street":"Calle De Luis Bun\u0303Uel",
    "iso:country":"ES",
    "sg:address":"Calle de Luis Bu\u00d1uel, 21",
    "sg:city":"Almoradi",
    "sg:orig_category":"Talleres: Ropa A Medida",
    "sg:phone":"+34 966 78 06 21",
    "sg:postcode":"03160",
    "sg:province":"Alicante",
    "wof:name":"Quiles Lucas Francisco Javier",
    "wof:placetype":"venue"
},
  "geometry": {"coordinates":[-0.7916759849,38.1109848022],"type":"Point"}
}