{
  "type": "Feature",
  "properties": {
    "iso:country":"ES",
    "sg:address":"Pedro Migel Urruzuno Kalea, 27",
    "sg:city":"Elgoibar",
    "sg:orig_category":"Construcciones Navales Y Fluviales",
    "sg:phone":"+34 943 74 10 78",
    "sg:postcode":"20870",
    "sg:province":"Guip\u00f9zcoa",
    "wof:name":"Raquel Dos Santos Augusto Y Otra, C.b.",
    "wof:placetype":"venue"
},
  "geometry": {"coordinates":[-2.4084939957,43.218044281],"type":"Point"}
}