{
  "type": "Feature",
  "properties": {
    "iso:country":"ES",
    "sg:address":"Avda Rambleta, 25",
    "sg:city":"Catarroja",
    "sg:orig_category":"Empresas De Portes Y Mensajer\u00cda",
    "sg:phone":"+34 961 22 06 76",
    "sg:postcode":"46470",
    "sg:province":"Valencia",
    "wof:name":"Ospina  Claudia Patricia",
    "wof:placetype":"venue"
},
  "geometry": {"coordinates":[-0.4065470099,39.404006958],"type":"Point"}
}