{
  "type": "Feature",
  "properties": {
    "addr:full":"Calle de Julio Saez De La Hoya, 9 Burgos Burgos 09005",
    "addr:housenumber":"9",
    "addr:postcode":"09005",
    "addr:street":"Calle De Julio Saez De La Hoya",
    "iso:country":"ES",
    "sg:address":"Calle de Julio Saez De La Hoya, 9",
    "sg:city":"Burgos",
    "sg:orig_category":"Muebles Y Accesorios Para Cocinas Y Cuartos De Ba\u00d1o (al Por Menor)",
    "sg:phone":"+34 947 21 80 54",
    "sg:postcode":"09005",
    "sg:province":"Burgos",
    "wof:name":"Siro Vazquez S.l.",
    "wof:placetype":"venue"
},
  "geometry": {"coordinates":[-3.6969308853,42.3451423645],"type":"Point"}
}