{
  "type": "Feature",
  "properties": {
    "addr:full":"Calle de Jaen, 12 Cordoba C\u00f3rdoba 14013",
    "addr:housenumber":"12",
    "addr:postcode":"14013",
    "addr:street":"Calle De Jaen;Co\u0301Rdoba",
    "iso:country":"ES",
    "sg:address":"Calle de Jaen, 12",
    "sg:city":"Cordoba",
    "sg:orig_category":"Ropa Para Se\u00d1oras Y Caballeros (al Por Menor)",
    "sg:phone":"+34 957 20 07 73",
    "sg:postcode":"14013",
    "sg:province":"C\u00f3rdoba",
    "wof:name":"Jimenez Medina Manuela",
    "wof:placetype":"venue"
},
  "geometry": {"coordinates":[-4.7760081291,37.8677177429],"type":"Point"}
}