{
  "type": "Feature",
  "properties": {
    "addr:full":"Calle de O'donnell, 46 Madrid Madrid 28009",
    "addr:housenumber":"46",
    "addr:postcode":"madrid;28009",
    "addr:street":"Calle De O'Donnell",
    "iso:country":"ES",
    "sg:address":"Calle de O'donnell, 46",
    "sg:city":"Madrid",
    "sg:orig_category":"M\u00c9dicos: Cardiolog\u00cda Y Afecciones Cardiovasculares",
    "sg:phone":"+34 915 74 69 74",
    "sg:postcode":"28009",
    "sg:province":"Madrid",
    "wof:name":"Palomino Fernandez Antonio",
    "wof:placetype":"venue"
},
  "geometry": {"coordinates":[-3.6768717766,40.4215507507],"type":"Point"}
}