{
  "type": "Feature",
  "properties": {
    "addr:full":"Avda Ferrandis Salvador, 312 Mas Dels Frares Castell\u00f3n 12560",
    "addr:housenumber":"312",
    "addr:postcode":"12560",
    "addr:street":"Avda Ferrandis Salvador;Castello\u0301N",
    "iso:country":"ES",
    "sg:address":"Avda Ferrandis Salvador, 312",
    "sg:city":"Mas Dels Frares",
    "sg:orig_category":"Aguas (distribuci\u00d3n, Servicios)",
    "sg:phone":"+34 964 39 50 38",
    "sg:postcode":"12560",
    "sg:province":"Castell\u00f3n",
    "wof:name":"Ramos Tirado Antonio",
    "wof:placetype":"venue"
},
  "geometry": {"coordinates":[0.0590550005,40.0523414612],"type":"Point"}
}