{
  "type": "Feature",
  "properties": {
    "iso:country":"ES",
    "sg:address":"Carrer de Vilaseca, 11",
    "sg:city":"S. Cugat Valles",
    "sg:orig_category":"Molduras, Junquillos, Listones Y Molduras Perforadas",
    "sg:phone":"+34 936 74 85 83",
    "sg:postcode":"08172",
    "sg:province":"Barcelona",
    "wof:name":"Sole Pla Magin",
    "wof:placetype":"venue"
},
  "geometry": {"coordinates":[2.0834970474,41.467048645],"type":"Point"}
}