{
  "type": "Feature",
  "properties": {
    "iso:country":"ES",
    "sg:address":"Ctra. Daganzo, Km. 0003,5",
    "sg:city":"Alcala Henares",
    "sg:orig_category":"Panader\u00cdas, Panader\u00cdas",
    "sg:phone":"+34 918 88 04 27",
    "sg:postcode":"28806",
    "sg:province":"Madrid",
    "wof:name":"Fabrica De Pan Jabardo S. A.",
    "wof:placetype":"venue"
},
  "geometry": {"coordinates":[-3.422385931,40.5286216736],"type":"Point"}
}