{
  "type": "Feature",
  "properties": {
    "addr:full":"Carrer de Sant Roc, 5 Flix Tarragona 43750",
    "addr:housenumber":"5",
    "addr:postcode":"43750",
    "addr:street":"Carrer De Sant Roc",
    "iso:country":"ES",
    "sg:address":"Carrer de Sant Roc, 5",
    "sg:city":"Flix",
    "sg:orig_category":"Librer\u00cdas",
    "sg:phone":"+34 977 41 05 91",
    "sg:postcode":"43750",
    "sg:province":"Tarragona",
    "wof:name":"Bages Zamora Jaume",
    "wof:placetype":"venue"
},
  "geometry": {"coordinates":[0.5508553982,41.2317428589],"type":"Point"}
}