{
  "type": "Feature",
  "properties": {
    "addr:full":"Rua Barbate, 1 San Roque Do Monte Pontevedra 36940",
    "addr:housenumber":"1",
    "addr:postcode":"36940",
    "addr:street":"Barbate",
    "iso:country":"ES",
    "sg:address":"Rua Barbate, 1",
    "sg:city":"San Roque Do Monte",
    "sg:orig_category":"Farmacias",
    "sg:phone":"+34 986 30 52 59",
    "sg:postcode":"36940",
    "sg:province":"Pontevedra",
    "wof:name":"Garcia Gayo Julio",
    "wof:placetype":"venue"
},
  "geometry": {"coordinates":[-8.8184690475,42.2741928101],"type":"Point"}
}