{
  "type": "Feature",
  "properties": {
    "iso:country":"ES",
    "sg:address":"Ctra Basurtu-kastrexana, 57",
    "sg:city":"Bilbao",
    "sg:orig_category":"Plomeros",
    "sg:phone":"+34 944 41 87 80",
    "sg:postcode":"48002",
    "sg:province":"Vizcaya",
    "wof:name":"Servicios Integrados En Procesos Del Agua S.l.",
    "wof:placetype":"venue"
},
  "geometry": {"coordinates":[-2.9532189369,43.2595214844],"type":"Point"}
}