{
  "type": "Feature",
  "properties": {
    "iso:country":"ES",
    "sg:address":"Calle de Bencomo, 1",
    "sg:city":"Sardina",
    "sg:orig_category":"Transportes Por V\u00cdas Navegables",
    "sg:phone":"+34 928 75 90 05",
    "sg:postcode":"35110",
    "sg:province":"Las Palmas",
    "wof:name":"Perez Martel Felipe",
    "wof:placetype":"venue"
},
  "geometry": {"coordinates":[-15.4676675797,27.8530025482],"type":"Point"}
}