{
  "type": "Feature",
  "properties": {
    "addr:full":"Carrer de Francesc Layret, 4 Cornella Llobregat Barcelona 08940",
    "addr:housenumber":"4",
    "addr:postcode":"08940",
    "addr:street":"Carrer De Francesc Layret",
    "iso:country":"ES",
    "sg:address":"Carrer de Francesc Layret, 4",
    "sg:city":"Cornella Llobregat",
    "sg:orig_category":"Mec\u00c1nico Del Autom\u00d3vil",
    "sg:phone":"+34 933 77 08 61",
    "sg:postcode":"08940",
    "sg:province":"Barcelona",
    "wof:name":"Romero Trancoso Benjamin",
    "wof:placetype":"venue"
},
  "geometry": {"coordinates":[2.0717439651,41.3501014709],"type":"Point"}
}