{
  "type": "Feature",
  "properties": {
    "addr:full":"Lestedo, 21 Lestedo A Coru\u00f1a 15881",
    "addr:housenumber":"21",
    "addr:postcode":"15881",
    "addr:street":"Lestedo;Corun\u0303A",
    "iso:country":"ES",
    "sg:address":"Lestedo, 21",
    "sg:city":"Lestedo",
    "sg:orig_category":"Carnicer\u00cdas, Carnicer\u00cdas",
    "sg:phone":"+34 981 50 32 77",
    "sg:postcode":"15881",
    "sg:province":"A Coru\u00f1a",
    "wof:name":"Troiti\u00f1o Lorenzo Manuel",
    "wof:placetype":"venue"
},
  "geometry": {"coordinates":[-8.4128170013,42.8135566711],"type":"Point"}
}