{
  "type": "Feature",
  "properties": {
    "addr:full":"Artica, 9 Iru\u00f1a Navarra 31014",
    "addr:housenumber":"9",
    "addr:postcode":"31014",
    "addr:street":"Artica",
    "iso:country":"ES",
    "sg:address":"Artica, 9",
    "sg:city":"Iru\u00f1a",
    "sg:orig_category":"Tapicer\u00cdas",
    "sg:phone":"+34 948 12 63 97",
    "sg:postcode":"31014",
    "sg:province":"Navarra",
    "wof:name":"Hernandez Flores Luis",
    "wof:placetype":"venue"
},
  "geometry": {"coordinates":[-1.6472300291,42.8270530701],"type":"Point"}
}