{
  "type": "Feature",
  "properties": {
    "iso:country":"ES",
    "sg:address":"Calle de Campo (del), 2",
    "sg:city":"Almansa",
    "sg:orig_category":"Cl\u00cdnicas Dentales",
    "sg:phone":"+34 967 31 04 89",
    "sg:postcode":"02640",
    "sg:province":"Albacete",
    "wof:name":"Clinica Dental Dr.calvarro",
    "wof:placetype":"venue"
},
  "geometry": {"coordinates":[-1.0991517305,38.8715515137],"type":"Point"}
}