{
  "type": "Feature",
  "properties": {
    "addr:full":"Carrer de Bartrina, 241 Terrassa Barcelona 08226",
    "addr:housenumber":"241",
    "addr:postcode":"08226",
    "addr:street":"Carrer De Bartrina",
    "iso:country":"ES",
    "sg:address":"Carrer de Bartrina, 241",
    "sg:city":"Terrassa",
    "sg:orig_category":"Empresas De Carpinter\u00cda",
    "sg:phone":"+34 937 31 34 46",
    "sg:postcode":"08226",
    "sg:province":"Barcelona",
    "wof:name":"Persi Alumini Molina S.l.",
    "wof:placetype":"venue"
},
  "geometry": {"coordinates":[2.025949955,41.5733528137],"type":"Point"}
}