{
  "type": "Feature",
  "properties": {
    "iso:country":"ES",
    "sg:address":"Plaz Lovaina, 1",
    "sg:city":"Vitoria-gasteiz",
    "sg:orig_category":"Muebles, Minoristas",
    "sg:phone":"+34 945 13 37 50",
    "sg:postcode":"01008",
    "sg:province":"\u00c1lava",
    "wof:name":"Eikos Proyectos, S.l.",
    "wof:placetype":"venue"
},
  "geometry": {"coordinates":[-2.6826090813,42.8435783386],"type":"Point"}
}