{
  "type": "Feature",
  "properties": {
    "iso:country":"ES",
    "sg:address":"Calle de Ronda De Santa Ana, 2",
    "sg:city":"Medina Campo",
    "sg:orig_category":"Asociaciones Y Clubs Deportivos",
    "sg:phone":"+34 983 81 20 73",
    "sg:postcode":"47400",
    "sg:province":"Valladolid",
    "wof:name":"Toresano Alvarez Laura",
    "wof:placetype":"venue"
},
  "geometry": {"coordinates":[-4.913184166,41.3120155334],"type":"Point"}
}