{
  "type": "Feature",
  "properties": {
    "iso:country":"ES",
    "sg:address":"Calle de Rio Guadiana, 13",
    "sg:city":"Parla",
    "sg:orig_category":"Fabricaci\u00d3n De Sobres, Bolsas Y Fundas",
    "sg:phone":"+34 916 99 87 55",
    "sg:postcode":"28980",
    "sg:province":"Madrid",
    "wof:name":"Qiye Bolsos S.l.",
    "wof:placetype":"venue"
},
  "geometry": {"coordinates":[-3.770911932,40.2436408997],"type":"Point"}
}