{
  "type": "Feature",
  "properties": {
    "iso:country":"ES",
    "sg:address":"Calle de Doctor Policarpo Lizcano, 6",
    "sg:city":"Alcazar S. Juan",
    "sg:orig_category":"Reposter\u00cdas",
    "sg:phone":"+34 926 54 54 38",
    "sg:postcode":"13600",
    "sg:province":"Ciudad Real",
    "wof:name":"Rodriguez Olivares Petronilo",
    "wof:placetype":"venue"
},
  "geometry": {"coordinates":[-3.2068665028,39.389667511],"type":"Point"}
}