{
  "type": "Feature",
  "properties": {
    "iso:country":"ES",
    "sg:address":"Avda Constitucion La, 12",
    "sg:city":"Arriondas",
    "sg:orig_category":"Ense\u00d1anza: Idiomas",
    "sg:phone":"+34 985 84 10 51",
    "sg:postcode":"33540",
    "sg:province":"Asturias",
    "wof:name":"Lara Tresguerres Natalia",
    "wof:placetype":"venue"
},
  "geometry": {"coordinates":[-5.1852741241,43.3902168274],"type":"Point"}
}