{
  "type": "Feature",
  "properties": {
    "iso:country":"ES",
    "sg:address":"Calle de Concepcion, 13",
    "sg:city":"Borja",
    "sg:orig_category":"Ense\u00d1anza Variada",
    "sg:phone":"+34 976 86 60 24",
    "sg:postcode":"50540",
    "sg:province":"Zaragoza",
    "wof:name":"Teixeira Torralba Maria Del Mar",
    "wof:placetype":"venue"
},
  "geometry": {"coordinates":[-1.5321029425,41.8342552185],"type":"Point"}
}