{
  "type": "Feature",
  "properties": {
    "addr:full":"Ctra. Andalucia, Km. 0094,0 Tembleque Toledo 45780",
    "addr:postcode":"45780",
    "addr:street":"Ctra. Andalucia Km. 0094,0",
    "iso:country":"ES",
    "sg:address":"Ctra. Andalucia, Km. 0094,0",
    "sg:city":"Tembleque",
    "sg:orig_category":"Negocio De Madera",
    "sg:phone":"+34 925 14 51 30",
    "sg:postcode":"45780",
    "sg:province":"Toledo",
    "wof:name":"Eurochapas Y Maderas S.l.",
    "wof:placetype":"venue"
},
  "geometry": {"coordinates":[-3.5035789013,39.6947860718],"type":"Point"}
}