{
  "type": "Feature",
  "properties": {
    "addr:full":"Calle de San Neviano, 5 Madrid Madrid 28021",
    "addr:housenumber":"5",
    "addr:postcode":"28021",
    "addr:street":"Calle De San Neviano",
    "iso:country":"ES",
    "sg:address":"Calle de San Neviano, 5",
    "sg:city":"Madrid",
    "sg:orig_category":"Peluqueros: De Se\u00d1oras",
    "sg:phone":"+34 917 98 66 18",
    "sg:postcode":"28021",
    "sg:province":"Madrid",
    "wof:name":"Rodriguez Gomez Rosa Maria",
    "wof:placetype":"venue"
},
  "geometry": {"coordinates":[-3.7043480873,40.3465270996],"type":"Point"}
}