{
  "type": "Feature",
  "properties": {
    "iso:country":"ES",
    "sg:address":"Carr Cardenal Cisneros, 20",
    "sg:city":"Lleida",
    "sg:orig_category":"Mantenimiento Y Reparaci\u00d3n De Motores Industriales",
    "sg:phone":"+34 973 26 95 02",
    "sg:postcode":"25003",
    "sg:province":"Lleida",
    "wof:name":"Modol Cuit Antonio",
    "wof:placetype":"venue"
},
  "geometry": {"coordinates":[0.6141819954,41.6101264954],"type":"Point"}
}