{
  "type": "Feature",
  "properties": {
    "addr:full":"Calle de Munguia, 3 Palmas De Gran Canaria Las Palmas 35002",
    "addr:housenumber":"3",
    "addr:postcode":"35002",
    "addr:street":"Calle De Munguia",
    "iso:country":"ES",
    "sg:address":"Calle de Munguia, 3",
    "sg:city":"Palmas De Gran Canaria",
    "sg:orig_category":"Agencias Y Asesores De Publicidad",
    "sg:phone":"+34 928 38 41 38",
    "sg:postcode":"35002",
    "sg:province":"Las Palmas",
    "wof:name":"As De Publicidad Exterior S.l.",
    "wof:placetype":"venue"
},
  "geometry": {"coordinates":[-15.4160881042,28.1061248779],"type":"Point"}
}