{
  "type": "Feature",
  "properties": {
    "addr:full":"Cno. Coma Freda, 10 Andratx Islas Baleares 07150",
    "addr:housenumber":"10",
    "addr:postcode":"07150",
    "addr:street":"Cno. Coma Freda",
    "iso:country":"ES",
    "sg:address":"Cno. Coma Freda, 10",
    "sg:city":"Andratx",
    "sg:orig_category":"Inmobiliaria (agencias)",
    "sg:phone":"+34 971 23 64 09",
    "sg:postcode":"07150",
    "sg:province":"Islas Baleares",
    "wof:name":"Feld Conect S.l",
    "wof:placetype":"venue"
},
  "geometry": {"coordinates":[2.4228799343,39.5626411438],"type":"Point"}
}