{
  "type": "Feature",
  "properties": {
    "addr:full":"Calle de Casta Alvarez, 83 Zaragoza Zaragoza 50003",
    "addr:housenumber":"83",
    "addr:postcode":"50003",
    "addr:street":"Calle De Casta Alvarez",
    "iso:country":"ES",
    "sg:address":"Calle de Casta Alvarez, 83",
    "sg:city":"Zaragoza",
    "sg:orig_category":"Asilos De Ancianos. Centros Privados",
    "sg:phone":"+34 976 44 00 00",
    "sg:postcode":"50003",
    "sg:province":"Zaragoza",
    "wof:name":"Comunidad Jesus Te Ama",
    "wof:placetype":"venue"
},
  "geometry": {"coordinates":[-0.8856825829,41.6571960449],"type":"Point"}
}