{
  "type": "Feature",
  "properties": {
    "iso:country":"ES",
    "sg:address":"Calle de Aragon, 12",
    "sg:city":"Andorra",
    "sg:orig_category":"Asociaciones, Organismos Culturales Y Socioeducativos",
    "sg:phone":"+34 978 88 05 06",
    "sg:postcode":"44500",
    "sg:province":"Teruel",
    "wof:name":"Asociacion Cultural Interpe\u00f1as",
    "wof:placetype":"venue"
},
  "geometry": {"coordinates":[-0.4434336126,40.9762039185],"type":"Point"}
}