{
  "type": "Feature",
  "properties": {
    "addr:full":"Emilio Luque, 16 La Orotava Santa Cruz De Tenerife 38300",
    "addr:housenumber":"16",
    "addr:postcode":"38300",
    "addr:street":"Luque",
    "iso:country":"ES",
    "sg:address":"Emilio Luque, 16",
    "sg:city":"La Orotava",
    "sg:orig_category":"Ropa Para Se\u00d1oras (al Por Menor)",
    "sg:phone":"+34 922 33 19 32",
    "sg:postcode":"38300",
    "sg:province":"Santa Cruz De Tenerife",
    "wof:name":"Margarita Rodriguez E Hijos C.b.",
    "wof:placetype":"venue"
},
  "geometry": {"coordinates":[-16.5216712952,28.3919963837],"type":"Point"}
}