{
  "type": "Feature",
  "properties": {
    "iso:country":"ES",
    "sg:address":"Calle de Coso, 120",
    "sg:city":"Zaragoza",
    "sg:orig_category":"Fabricaci\u00d3n De Art\u00cdculos Y Ornamentos Religiosos",
    "sg:phone":"+34 976 29 57 84",
    "sg:postcode":"50001",
    "sg:province":"Zaragoza",
    "wof:name":"Siervas Seglares De Jesucristo Sacerdote",
    "wof:placetype":"venue"
},
  "geometry": {"coordinates":[-0.8762689829,41.650680542],"type":"Point"}
}