{
  "type": "Feature",
  "properties": {
    "addr:full":"Calle de Cura Jimenez, 5 Alquerias Murcia 30580",
    "addr:housenumber":"5",
    "addr:postcode":"30580",
    "addr:street":"Calle De Cura Jimenez",
    "iso:country":"ES",
    "sg:address":"Calle de Cura Jimenez, 5",
    "sg:city":"Alquerias",
    "sg:orig_category":"Florister\u00cdas",
    "sg:phone":"+34 968 81 21 34",
    "sg:postcode":"30580",
    "sg:province":"Murcia",
    "wof:name":"Perez Ruiz Jose Angel",
    "wof:placetype":"venue"
},
  "geometry": {"coordinates":[-1.0363560915,38.015422821],"type":"Point"}
}