{
  "type": "Feature",
  "properties": {
    "iso:country":"ES",
    "sg:address":"Calle de Donoso Cortes, 9",
    "sg:city":"Malaga",
    "sg:orig_category":"Lavado, Limpieza De Veh\u00cdculos",
    "sg:phone":"+34 952 35 87 27",
    "sg:postcode":"29002",
    "sg:province":"M\u00e1laga",
    "wof:name":"Frias Alarcon Francisco",
    "wof:placetype":"venue"
},
  "geometry": {"coordinates":[-4.4292297363,36.709564209],"type":"Point"}
}