{
  "type": "Feature",
  "properties": {
    "iso:country":"ES",
    "sg:address":"Calle de Juan Alvarez Delgado, 16",
    "sg:city":"Santa Cruz De Tenerife",
    "sg:orig_category":"Alimentaci\u00d3n General (al Por Menor)",
    "sg:phone":"+34 922 22 10 04",
    "sg:postcode":"38007",
    "sg:province":"Santa Cruz De Tenerife",
    "wof:name":"Vicente San Juan S.l.",
    "wof:placetype":"venue"
},
  "geometry": {"coordinates":[-16.2714633942,28.4659805298],"type":"Point"}
}