{
  "type": "Feature",
  "properties": {
    "iso:country":"ES",
    "sg:address":"Carretera Calonge-la Bisbal, S/n",
    "sg:city":"Calonge",
    "sg:orig_category":"Supermercados Y Hipermercados",
    "sg:phone":"+34 972 66 01 35",
    "sg:postcode":"17251",
    "sg:province":"Girona",
    "wof:name":"Valvi Alimentacio I Serveis S.l.",
    "wof:placetype":"venue"
},
  "geometry": {"coordinates":[3.0666899681,41.8805236816],"type":"Point"}
}