{
  "type": "Feature",
  "properties": {
    "iso:country":"ES",
    "sg:address":"Carrer de Sant Joan, 39",
    "sg:city":"S. Celoni",
    "sg:orig_category":"Molduras, Junquillos, Listones Y Molduras Perforadas",
    "sg:phone":"+34 938 67 51 60",
    "sg:postcode":"08470",
    "sg:province":"Barcelona",
    "wof:name":"Aldama Lopez Oscar",
    "wof:placetype":"venue"
},
  "geometry": {"coordinates":[2.4940350056,41.689655304],"type":"Point"}
}