{
  "type": "Feature",
  "properties": {
    "addr:full":"Pl Sol, 3 Martorell Barcelona 08760",
    "addr:housenumber":"3",
    "addr:postcode":"08760",
    "addr:street":"Pl Sol",
    "iso:country":"ES",
    "sg:address":"Pl Sol, 3",
    "sg:city":"Martorell",
    "sg:orig_category":"Empresas De Portes Y Mensajer\u00cda",
    "sg:phone":"+34 937 74 02 29",
    "sg:postcode":"08760",
    "sg:province":"Barcelona",
    "wof:name":"Isigolf 97 S.l.",
    "wof:placetype":"venue"
},
  "geometry": {"coordinates":[1.913967967,41.4812507629],"type":"Point"}
}