{
  "type": "Feature",
  "properties": {
    "iso:country":"ES",
    "sg:address":"Itsasbegi Kalea, 6",
    "sg:city":"Deba",
    "sg:orig_category":"Industria Qu\u00cdmica",
    "sg:phone":"+34 943 19 22 07",
    "sg:postcode":"20820",
    "sg:province":"Guip\u00f9zcoa",
    "wof:name":"Castro Montoya Francisco Javier",
    "wof:placetype":"venue"
},
  "geometry": {"coordinates":[-2.3514909744,43.2956123352],"type":"Point"}
}