{
  "type": "Feature",
  "properties": {
    "addr:full":"Calle de Trinquete, 4 Alginet Valencia 46230",
    "addr:housenumber":"4",
    "addr:postcode":"46230",
    "addr:street":"Calle De Trinquete",
    "iso:country":"ES",
    "sg:address":"Calle de Trinquete, 4",
    "sg:city":"Alginet",
    "sg:orig_category":"Asesor\u00cda De Formaci\u00d3n Y Gesti\u00d3n De Personal",
    "sg:phone":"+34 961 75 30 86",
    "sg:postcode":"46230",
    "sg:province":"Valencia",
    "wof:name":"Asesoria De Empresas Oficem S.l.",
    "wof:placetype":"venue"
},
  "geometry": {"coordinates":[-0.4679920971,39.2643814087],"type":"Point"}
}