{
  "type": "Feature",
  "properties": {
    "iso:country":"ES",
    "sg:address":"Calle de Rio De Monelos, 2",
    "sg:city":"Coru\u00d1a",
    "sg:orig_category":"M\u00c9dicos: Cirug\u00cda Urol\u00d3gica",
    "sg:phone":"+34 981 28 08 39",
    "sg:postcode":"15006",
    "sg:province":"La Coru\u00f1a",
    "wof:name":"Chantada Abal Venancio",
    "wof:placetype":"venue"
},
  "geometry": {"coordinates":[-8.3985290527,43.3560829163],"type":"Point"}
}