{
  "type": "Feature",
  "properties": {
    "iso:country":"ES",
    "sg:address":"Calle de Marques Don Gonzalo, 29",
    "sg:city":"Granada",
    "sg:orig_category":"Empresas De Limpieza",
    "sg:phone":"+34 958 52 32 01",
    "sg:postcode":"18004",
    "sg:province":"Granada",
    "wof:name":"Limpiezas Y Arreglos Ferregal S.l.",
    "wof:placetype":"venue"
},
  "geometry": {"coordinates":[-3.6062788963,37.1719284058],"type":"Point"}
}