{
  "type": "Feature",
  "properties": {
    "addr:full":"Avda Andalucia (de), 23 Rus Ja\u00e9n 23430",
    "addr:housenumber":"23",
    "addr:postcode":"23430",
    "addr:street":"Avda Andalucia De;Jae\u0301N",
    "iso:country":"ES",
    "sg:address":"Avda Andalucia (de), 23",
    "sg:city":"Rus",
    "sg:orig_category":"Fabricaci\u00d3n De Su\u00c9ters Y Chalecos De Punto",
    "sg:phone":"+34 953 77 01 07",
    "sg:postcode":"23430",
    "sg:province":"Ja\u00e9n",
    "wof:name":"Lopez Moreno Gabriel",
    "wof:placetype":"venue"
},
  "geometry": {"coordinates":[-3.4633131027,38.0471725464],"type":"Point"}
}