{
  "type": "Feature",
  "properties": {
    "addr:full":"Calle de Juan Bautista Maury, 22 Malaga M\u00e1laga 29010",
    "addr:housenumber":"22",
    "addr:postcode":"29010",
    "addr:street":"Calle De Juan Bautista Maury;Ma\u0301Laga",
    "iso:country":"ES",
    "sg:address":"Calle de Juan Bautista Maury, 22",
    "sg:city":"Malaga",
    "sg:classifiers":[
        {
            "category":"Professional",
            "subcategory":"Business Services",
            "type":"Services"
        }
    ],
    "sg:phone":"+34 952 27 20 30",
    "sg:postcode":"29010",
    "sg:province":"M\u00e1laga",
    "sg:tags":[
        "control",
        "asesor\u00cda",
        "organizaci\u00d3n",
        "la",
        "de",
        "gesti\u00d3n",
        "y"
    ],
    "wof:name":"Villa Cuenca S.l.",
    "wof:placetype":"venue"
},
  "geometry": {"coordinates":[-4.4560580254,36.7206497192],"type":"Point"}
}