{
  "type": "Feature",
  "properties": {
    "addr:full":"Calle de Aladino, 12 Torremolinos M\u00e1laga 29620",
    "addr:housenumber":"12",
    "addr:postcode":"29620",
    "addr:street":"Calle De Aladino;Ma\u0301Laga",
    "iso:country":"ES",
    "sg:address":"Calle de Aladino, 12",
    "sg:city":"Torremolinos",
    "sg:orig_category":"Molduras, Junquillos, Listones Y Molduras Perforadas",
    "sg:phone":"+34 952 38 24 35",
    "sg:postcode":"29620",
    "sg:province":"M\u00e1laga",
    "wof:name":"Appleyard  Richard Michael",
    "wof:placetype":"venue"
},
  "geometry": {"coordinates":[-4.5050706863,36.6098861694],"type":"Point"}
}