{
  "type": "Feature",
  "properties": {
    "addr:full":"Calle de Civiles (los), 1 Andujar Ja\u00e9n 23740",
    "addr:housenumber":"1",
    "addr:postcode":"23740",
    "addr:street":"Calle De Civiles Los",
    "iso:country":"ES",
    "sg:address":"Calle de Civiles (los), 1",
    "sg:city":"Andujar",
    "sg:orig_category":"Arquitectos",
    "sg:phone":"+34 953 51 16 55",
    "sg:postcode":"23740",
    "sg:province":"Ja\u00e9n",
    "wof:name":"Garcia Gonzalez Antonio",
    "wof:placetype":"venue"
},
  "geometry": {"coordinates":[-4.052611351,38.0399208069],"type":"Point"}
}