{
  "type": "Feature",
  "properties": {
    "iso:country":"ES",
    "sg:address":"Pque Nicolas Salmeron (de), 10",
    "sg:city":"Almeria",
    "sg:orig_category":"Caf\u00c9s, Bares, Cervecer\u00cdas",
    "sg:phone":"+34 950 25 35 20",
    "sg:postcode":"04002",
    "sg:province":"Almer\u00eda",
    "wof:name":"Puerto Parque Bribones S.l.",
    "wof:placetype":"venue"
},
  "geometry": {"coordinates":[-2.4655170441,36.8350944519],"type":"Point"}
}