{
  "type": "Feature",
  "properties": {
    "addr:full":"Correlos, 2 A Seara Lugo 27775",
    "addr:housenumber":"2 a",
    "addr:postcode":"27775",
    "addr:street":"Correlos",
    "iso:country":"ES",
    "sg:address":"Correlos, 2",
    "sg:city":"A Seara",
    "sg:orig_category":"Empresas De Carpinter\u00cda De Madera",
    "sg:phone":"+34 982 55 83 57",
    "sg:postcode":"27775",
    "sg:province":"Lugo",
    "wof:name":"Maseda Gonzalez Laureano",
    "wof:placetype":"venue"
},
  "geometry": {"coordinates":[-7.4476804733,43.4607467651],"type":"Point"}
}