{
  "type": "Feature",
  "properties": {
    "iso:country":"ES",
    "sg:address":"Calle de Iglesia (la), 18",
    "sg:city":"Alcorcon",
    "sg:orig_category":"Peluquer\u00cdas, Peluquer\u00cda Mixta",
    "sg:phone":"+34 916 11 13 53",
    "sg:postcode":"28921",
    "sg:province":"Madrid",
    "wof:name":"Manrique Fernandez Sara",
    "wof:placetype":"venue"
},
  "geometry": {"coordinates":[-3.8280730247,40.3502082825],"type":"Point"}
}