{
  "type": "Feature",
  "properties": {
    "addr:full":"Calle de Fernando Lopez, 17 San Pedro Albacete 02326",
    "addr:postcode":"02326",
    "addr:street":"Calle De Fernando Lopez 17",
    "iso:country":"ES",
    "sg:address":"Calle de Fernando Lopez, 17",
    "sg:city":"San Pedro",
    "sg:orig_category":"Electrodom\u00c9sticos (fabricaci\u00d3n, Al Por Mayor)",
    "sg:phone":"+34 967 35 80 67",
    "sg:postcode":"02326",
    "sg:province":"Albacete",
    "wof:name":"Electrodomesticos Hermanos Moreno Sanchez S.l.",
    "wof:placetype":"venue"
},
  "geometry": {"coordinates":[-2.1862130165,38.8275413513],"type":"Point"}
}