{
  "type": "Feature",
  "properties": {
    "addr:full":"Av Onze De Setembre, 24 Cubelles Barcelona 08880",
    "addr:housenumber":"24",
    "addr:postcode":"08880",
    "addr:street":"Av Onze De Setembre",
    "iso:country":"ES",
    "sg:address":"Av Onze De Setembre, 24",
    "sg:city":"Cubelles",
    "sg:orig_category":"Revestimiento De Suelos Industriales",
    "sg:phone":"+34 938 95 31 52",
    "sg:postcode":"08880",
    "sg:province":"Barcelona",
    "sg:website":"www.3bpavimentos.com",
    "wof:name":"3b Pavimentos S.l.",
    "wof:placetype":"venue"
},
  "geometry": {"coordinates":[1.669447,41.202484],"type":"Point"}
}