{
  "type": "Feature",
  "properties": {
    "iso:country":"ES",
    "sg:address":"Pase Dos De Mayo, 1",
    "sg:city":"Villa Don Fadrique",
    "sg:orig_category":"Centros Empresariales",
    "sg:phone":"+34 925 19 50 30",
    "sg:postcode":"45850",
    "sg:province":"Toledo",
    "wof:name":"Diaz Maroto Organero Maria Jesus",
    "wof:placetype":"venue"
},
  "geometry": {"coordinates":[-3.2231938839,39.6154937744],"type":"Point"}
}