{
  "type": "Feature",
  "properties": {
    "iso:country":"ES",
    "sg:address":"Calle de Goya, 19",
    "sg:city":"San Rafael",
    "sg:orig_category":"Albergues",
    "sg:phone":"+34 921 17 15 57",
    "sg:postcode":"40410",
    "sg:province":"Segovia",
    "wof:name":"La Vi\u00f1a De Santamaria E Hijos S.l.",
    "wof:placetype":"venue"
},
  "geometry": {"coordinates":[-4.1907720566,40.7151794434],"type":"Point"}
}