{
  "type": "Feature",
  "properties": {
    "addr:full":"Calle de Paloma (de La), 26 Brunete Madrid 28690",
    "addr:housenumber":"26",
    "addr:postcode":"28690",
    "addr:street":"Calle De Paloma De La",
    "iso:country":"ES",
    "sg:address":"Calle de Paloma (de La), 26",
    "sg:city":"Brunete",
    "sg:orig_category":"Electricidad: Instaladores",
    "sg:phone":"+34 918 15 80 25",
    "sg:postcode":"28690",
    "sg:province":"Madrid",
    "wof:name":"Electro Ac S.a.",
    "wof:placetype":"venue"
},
  "geometry": {"coordinates":[-3.9949939251,40.3984718323],"type":"Point"}
}