{
  "type": "Feature",
  "properties": {
    "iso:country":"ES",
    "sg:address":"Avgd Vicent Mortes Alfonso, 34",
    "sg:city":"Paterna",
    "sg:orig_category":"Farmacias",
    "sg:phone":"+34 961 38 24 96",
    "sg:postcode":"46980",
    "sg:province":"Valencia",
    "wof:name":"Salvador Verdu Gloria",
    "wof:placetype":"venue"
},
  "geometry": {"coordinates":[-0.4465540051,39.5057411194],"type":"Point"}
}