{
  "type": "Feature",
  "properties": {
    "iso:country":"ES",
    "sg:address":"Av. Progres (pol Ind La Drecera), S/n",
    "sg:city":"Selva Del Camp",
    "sg:orig_category":"Material Y Herramientas Agr\u00cdcolas",
    "sg:phone":"+34 977 84 51 39",
    "sg:postcode":"43470",
    "sg:province":"Tarragona",
    "wof:name":"Agrotrac S.l.",
    "wof:placetype":"venue"
},
  "geometry": {"coordinates":[1.1257082224,41.2050590515],"type":"Point"}
}