{
  "type": "Feature",
  "properties": {
    "addr:full":"Pase Colon, 29 Irun Guip\u00f9zcoa 20301",
    "addr:housenumber":"29",
    "addr:postcode":"20301",
    "addr:street":"Colon;Guipu\u0300Zcoa",
    "iso:country":"ES",
    "sg:address":"Pase Colon, 29",
    "sg:city":"Irun",
    "sg:orig_category":"Peluqueros: De Se\u00d1oras",
    "sg:phone":"+34 943 61 87 93",
    "sg:postcode":"20301",
    "sg:province":"Guip\u00f9zcoa",
    "wof:name":"Berges Aranguren Jose Joaquin",
    "wof:placetype":"venue"
},
  "geometry": {"coordinates":[-1.7902339697,43.3395233154],"type":"Point"}
}