{
  "type": "Feature",
  "properties": {
    "addr:full":"Ctra. S. Jose, Km. 0005,1 S Jose Almer\u00eda 04118",
    "addr:postcode":"04118",
    "addr:street":"Ctra. S. Jose Km. 0005,1 S Jose Almeri\u0301A",
    "iso:country":"ES",
    "sg:address":"Ctra. S. Jose, Km. 0005,1",
    "sg:city":"S Jose",
    "sg:orig_category":"Invernaderos Y Semilleros",
    "sg:phone":"+34 950 38 06 95",
    "sg:postcode":"04118",
    "sg:province":"Almer\u00eda",
    "wof:name":"Semilleros Europlan S.l.",
    "wof:placetype":"venue"
},
  "geometry": {"coordinates":[-2.1109490395,36.763130188],"type":"Point"}
}