{
  "type": "Feature",
  "properties": {
    "addr:full":"Carrer de Sant Roc, 3 Prades Tarragona 43364",
    "addr:housenumber":"3",
    "addr:postcode":"43364",
    "addr:street":"Carrer De Sant Roc",
    "iso:country":"ES",
    "sg:address":"Carrer de Sant Roc, 3",
    "sg:city":"Prades",
    "sg:orig_category":"Zonas De Acampada, Aparcamiento Para Caravanas",
    "sg:phone":"+34 977 86 83 89",
    "sg:postcode":"43364",
    "sg:province":"Tarragona",
    "wof:name":"Verd Natura De Prades C.b.",
    "wof:placetype":"venue"
},
  "geometry": {"coordinates":[0.9888210297,41.3091659546],"type":"Point"}
}