{
  "type": "Feature",
  "properties": {
    "addr:full":"Calle de Niza, 2 Caceres C\u00e1ceres 10001",
    "addr:housenumber":"2",
    "addr:postcode":"10001",
    "addr:street":"Calle De Niza;Ca\u0301Ceres",
    "iso:country":"ES",
    "sg:address":"Calle de Niza, 2",
    "sg:city":"Caceres",
    "sg:orig_category":"Peluqueros: De Se\u00d1oras",
    "sg:phone":"+34 927 22 24 48",
    "sg:postcode":"10001",
    "sg:province":"C\u00e1ceres",
    "wof:name":"Macias Alonso Francisca",
    "wof:placetype":"venue"
},
  "geometry": {"coordinates":[-6.3806400299,39.4730224609],"type":"Point"}
}