{
  "type": "Feature",
  "properties": {
    "addr:full":"Dr Rio Ortega(p I Las Teresas), S/n Yecla Murcia 30510",
    "addr:housenumber":"s / n",
    "addr:postcode":"30510",
    "addr:street":"Dr;Ortega P I Las Teresas",
    "iso:country":"ES",
    "sg:address":"Dr Rio Ortega(p I Las Teresas), S/n",
    "sg:city":"Yecla",
    "sg:orig_category":"Empresas De Carpinter\u00cda De Madera",
    "sg:phone":"+34 968 71 82 51",
    "sg:postcode":"30510",
    "sg:province":"Murcia",
    "wof:name":"Armazones Navarro Rico S.l.",
    "wof:placetype":"venue"
},
  "geometry": {"coordinates":[-1.173699379,38.6051635742],"type":"Point"}
}