{
  "type": "Feature",
  "properties": {
    "iso:country":"ES",
    "sg:address":"Avda Antonio Machado, 33",
    "sg:city":"Roquetas Mar",
    "sg:orig_category":"Asilos De Ancianos. Centros Privados",
    "sg:phone":"+34 950 32 40 73",
    "sg:postcode":"04740",
    "sg:province":"Almer\u00eda",
    "wof:name":"Asociacion Cultural Verdemar",
    "wof:placetype":"venue"
},
  "geometry": {"coordinates":[-2.6067910194,36.7575149536],"type":"Point"}
}