{
  "type": "Feature",
  "properties": {
    "addr:full":"Avda Constitucion, 5 Escalona Toledo 45910",
    "addr:housenumber":"5",
    "addr:postcode":"45910",
    "addr:street":"Avda Constitucion",
    "iso:country":"ES",
    "sg:address":"Avda Constitucion, 5",
    "sg:city":"Escalona",
    "sg:orig_category":"Inmobiliaria (agencias)",
    "sg:phone":"+34 925 78 00 98",
    "sg:postcode":"45910",
    "sg:province":"Toledo",
    "wof:name":"Sanchez Rodriguez Juan Manuel",
    "wof:placetype":"venue"
},
  "geometry": {"coordinates":[-4.4021492004,40.1649398804],"type":"Point"}
}