{
  "type": "Feature",
  "properties": {
    "addr:full":"La Carretona, S/n Piedramuelle Asturias 33193",
    "addr:housenumber":"s",
    "addr:postcode":"33193",
    "addr:street":"/ N Piedramuelle Asturias",
    "iso:country":"ES",
    "sg:address":"La Carretona, S/n",
    "sg:city":"Piedramuelle",
    "sg:orig_category":"Arenas, Guijarros Y Granulados",
    "sg:phone":"+34 985 78 10 40",
    "sg:postcode":"33193",
    "sg:province":"Asturias",
    "wof:name":"Canteras Mecanicas Carcaba S. A.",
    "wof:placetype":"venue"
},
  "geometry": {"coordinates":[-5.894742012,43.3435211182],"type":"Point"}
}