{
  "type": "Feature",
  "properties": {
    "addr:full":"Calle de Federico Balart, 1 San Antolin Murcia 30004",
    "addr:housenumber":"1",
    "addr:postcode":"30004",
    "addr:street":"Calle De Federico Balart;San Antolin",
    "iso:country":"ES",
    "sg:address":"Calle de Federico Balart, 1",
    "sg:city":"San Antolin",
    "sg:orig_category":"Carnicer\u00cdas, Carnicer\u00cdas",
    "sg:phone":"+34 968 29 05 31",
    "sg:postcode":"30004",
    "sg:province":"Murcia",
    "wof:name":"Nicolas Buitrago Francisco",
    "wof:placetype":"venue"
},
  "geometry": {"coordinates":[-1.1357970238,37.9839248657],"type":"Point"}
}