{
  "type": "Feature",
  "properties": {
    "iso:country":"ES",
    "sg:address":"Plaz Angel Urzaiz, 2",
    "sg:city":"Gondomar",
    "sg:orig_category":"Telas Y Sedas (al Por Menor)",
    "sg:phone":"+34 986 38 91 19",
    "sg:postcode":"36380",
    "sg:province":"Pontevedra",
    "wof:name":"Perez Gonzalez Jose Luis",
    "wof:placetype":"venue"
},
  "geometry": {"coordinates":[-8.7610292435,42.1107025146],"type":"Point"}
}