{
  "type": "Feature",
  "properties": {
    "iso:country":"ES",
    "sg:address":"Calle de Acera Recoletos, 27",
    "sg:city":"Valladolid",
    "sg:orig_category":"Fisioterapia",
    "sg:phone":"+34 983 20 80 15",
    "sg:postcode":"47004",
    "sg:province":"Valladolid",
    "wof:name":"Centro De Fisioterapia Gamazo Sl",
    "wof:placetype":"venue"
},
  "geometry": {"coordinates":[-4.7269172668,41.644493103],"type":"Point"}
}