{
  "type": "Feature",
  "properties": {
    "iso:country":"ES",
    "sg:address":"Calle de Hernan Cortes, 11",
    "sg:city":"Motilla Palancar",
    "sg:orig_category":"Fabricaci\u00d3n De Juegos Y Juguetes",
    "sg:phone":"+34 969 33 15 42",
    "sg:postcode":"16200",
    "sg:province":"Cuenca",
    "wof:name":"Moises Herreros S.l.",
    "wof:placetype":"venue"
},
  "geometry": {"coordinates":[-1.9082189798,39.5625190735],"type":"Point"}
}