{
  "type": "Feature",
  "properties": {
    "addr:full":"Calle de Velazquez, 8 Madrid Madrid 28001",
    "addr:housenumber":"8",
    "addr:postcode":"madrid;28001",
    "addr:street":"Calle De Velazquez",
    "iso:country":"ES",
    "sg:address":"Calle de Velazquez, 8",
    "sg:city":"Madrid",
    "sg:orig_category":"Televisi\u00d3n, V\u00cddeo: Aparatos Y Accesorios (venta)",
    "sg:phone":"+34 915 78 36 17",
    "sg:postcode":"28001",
    "sg:province":"Madrid",
    "sg:website":"www.quadriga.com",
    "wof:name":"Quadriga Espa\u00f1a S.a.",
    "wof:placetype":"venue"
},
  "geometry": {"coordinates":[-3.6842041016,40.42212677],"type":"Point"}
}