{
  "type": "Feature",
  "properties": {
    "iso:country":"ES",
    "sg:address":"Cami Gabarres (de Les), S/n",
    "sg:city":"Floresta",
    "sg:orig_category":"Cajas De Ahorro",
    "sg:phone":"+34 977 55 23 80",
    "sg:postcode":"43006",
    "sg:province":"Tarragona",
    "sg:website":"www.lacaixa.es",
    "wof:name":"Caixa D'estalvis I Pensions De Barcelona",
    "wof:placetype":"venue"
},
  "geometry": {"coordinates":[1.2209249735,41.1154441833],"type":"Point"}
}