{
  "type": "Feature",
  "properties": {
    "addr:full":"Calle de Cueva De La Mora, 6 Villaviciosa Odon Madrid 28670",
    "addr:housenumber":"6",
    "addr:postcode":"28670",
    "addr:street":"Calle De Cueva De La Mora;Odon",
    "iso:country":"ES",
    "sg:address":"Calle de Cueva De La Mora, 6",
    "sg:city":"Villaviciosa Odon",
    "sg:orig_category":"Carnicer\u00cdas, Carnicer\u00cdas",
    "sg:phone":"+34 916 16 15 51",
    "sg:postcode":"28670",
    "sg:province":"Madrid",
    "wof:name":"Mesa Baena Manuel",
    "wof:placetype":"venue"
},
  "geometry": {"coordinates":[-3.921787262,40.346496582],"type":"Point"}
}