{
  "type": "Feature",
  "properties": {
    "addr:full":"Ermita Baja, 24 Huetor-tajar Granada 18360",
    "addr:housenumber":"24",
    "addr:postcode":"18360",
    "addr:street":"Baja",
    "iso:country":"ES",
    "sg:address":"Ermita Baja, 24",
    "sg:city":"Huetor-tajar",
    "sg:orig_category":"Centros De Educaci\u00d3n Especial",
    "sg:phone":"+34 958 33 22 03",
    "sg:postcode":"18360",
    "sg:province":"Granada",
    "wof:name":"Soriano Galvez Francisco Manuel",
    "wof:placetype":"venue"
},
  "geometry": {"coordinates":[-4.0483179092,37.1954994202],"type":"Point"}
}