{
  "type": "Feature",
  "properties": {
    "iso:country":"ES",
    "sg:address":"Calle de Albert Einstein, 48",
    "sg:city":"Palmas De Gran Canaria",
    "sg:orig_category":"Comercio, Reparaci\u00d3n De Motocicletas, Bicicletas Y Piezas Sueltas",
    "sg:phone":"+34 928 42 20 81",
    "sg:postcode":"35013",
    "sg:province":"Las Palmas",
    "wof:name":"Radical Custom Performance",
    "wof:placetype":"venue"
},
  "geometry": {"coordinates":[-15.4506893158,28.0931987762],"type":"Point"}
}