{
  "type": "Feature",
  "properties": {
    "iso:country":"ES",
    "sg:address":"Rua Conde Torrecedeira, 68",
    "sg:city":"Vigo",
    "sg:orig_category":"Supermercados Y Hipermercados",
    "sg:phone":"+34 986 21 13 60",
    "sg:postcode":"36202",
    "sg:province":"Pontevedra",
    "wof:name":"Vego Supermercados S.a.",
    "wof:placetype":"venue"
},
  "geometry": {"coordinates":[-8.7329730988,42.229511261],"type":"Point"}
}