{
  "type": "Feature",
  "properties": {
    "iso:country":"ES",
    "sg:address":"Calle de General Sanjurjo, 7",
    "sg:city":"Coca",
    "sg:orig_category":"Bancos",
    "sg:phone":"+34 921 58 61 11",
    "sg:postcode":"40480",
    "sg:province":"Segovia",
    "sg:website":"www.banesto.es",
    "wof:name":"Banco Espa\u00d1ol De Credito S.a.",
    "wof:placetype":"venue"
},
  "geometry": {"coordinates":[-4.5227208138,41.2187156677],"type":"Point"}
}