{
  "type": "Feature",
  "properties": {
    "addr:full":"Czad Toro, S/n Poligono Industrial Los Villares Salamanca 37184",
    "addr:housenumber":"/ n",
    "addr:postcode":"37184",
    "addr:street":"Toro S;Industrial",
    "iso:country":"ES",
    "sg:address":"Czad Toro, S/n",
    "sg:city":"Poligono Industrial Los Villares",
    "sg:orig_category":"Molduras, Junquillos, Listones Y Molduras Perforadas",
    "sg:phone":"+34 923 25 02 44",
    "sg:postcode":"37184",
    "sg:province":"Salamanca",
    "wof:name":"Bajo Garcia Jose",
    "wof:placetype":"venue"
},
  "geometry": {"coordinates":[-5.6476120949,41.0065116882],"type":"Point"}
}