{
  "type": "Feature",
  "properties": {
    "iso:country":"ES",
    "sg:address":"Calle de Qui\u00d1ones, 15",
    "sg:city":"Madrid",
    "sg:orig_category":"Ebanistas Y Talladores De Muebles Y Objetos De Arte",
    "sg:phone":"+34 915 22 59 39",
    "sg:postcode":"28015",
    "sg:province":"Madrid",
    "wof:name":"Rozas Terras Jose Ernesto",
    "wof:placetype":"venue"
},
  "geometry": {"coordinates":[-3.7079179287,40.4272918701],"type":"Point"}
}