{
  "type": "Feature",
  "properties": {
    "addr:full":"Cra Caldes, S/n Papiol Barcelona 08754",
    "addr:housenumber":"s / n",
    "addr:postcode":"08754",
    "addr:street":"Caldes",
    "iso:country":"ES",
    "sg:address":"Cra Caldes, S/n",
    "sg:city":"Papiol",
    "sg:orig_category":"Semiller\u00cdas",
    "sg:phone":"+34 936 73 05 49",
    "sg:postcode":"08754",
    "sg:province":"Barcelona",
    "wof:name":"Faura Busquet Miguel",
    "wof:placetype":"venue"
},
  "geometry": {"coordinates":[2.0120489597,41.4390106201],"type":"Point"}
}