{
  "type": "Feature",
  "properties": {
    "addr:full":"Calle de Calzada, 2 Antequera M\u00e1laga 29200",
    "addr:housenumber":"2",
    "addr:postcode":"29200",
    "addr:street":"Calle De Calzada",
    "iso:country":"ES",
    "sg:address":"Calle de Calzada, 2",
    "sg:city":"Antequera",
    "sg:orig_category":"Electricidad: Instaladores",
    "sg:phone":"+34 952 84 14 38",
    "sg:postcode":"29200",
    "sg:province":"M\u00e1laga",
    "wof:name":"Electricidad Perez Alvarez S.c.",
    "wof:placetype":"venue"
},
  "geometry": {"coordinates":[-4.5570650101,37.0172805786],"type":"Point"}
}