{
  "type": "Feature",
  "properties": {
    "addr:full":"Ptda La Cometa, S/n Llutxent Valencia 46838",
    "addr:housenumber":"s / n",
    "addr:postcode":"46838",
    "addr:street":"Ptda La Cometa",
    "iso:country":"ES",
    "sg:address":"Ptda La Cometa, S/n",
    "sg:city":"Llutxent",
    "sg:orig_category":"Poller\u00cda Y Caza (al Por Menor)",
    "sg:phone":"+34 962 13 24 07",
    "sg:postcode":"46838",
    "sg:province":"Valencia",
    "wof:name":"Franco Canet Jose Renato",
    "wof:placetype":"venue"
},
  "geometry": {"coordinates":[-0.3564560115,38.9408912659],"type":"Point"}
}