{
  "type": "Feature",
  "properties": {
    "iso:country":"ES",
    "sg:address":"Real, 1",
    "sg:city":"Puerta",
    "sg:orig_category":"Molduras, Junquillos, Listones Y Molduras Perforadas",
    "sg:phone":"+34 949 81 86 14",
    "sg:postcode":"19492",
    "sg:province":"Guadalajara",
    "wof:name":"Begibe S.l.",
    "wof:placetype":"venue"
},
  "geometry": {"coordinates":[-2.5897688866,40.6363830566],"type":"Point"}
}