{
  "type": "Feature",
  "properties": {
    "addr:full":"Cm\u00d1o Espedrigada, 9 Vigo Pontevedra 36210",
    "addr:housenumber":"9",
    "addr:postcode":"36210",
    "addr:street":"Espedrigada",
    "iso:country":"ES",
    "sg:address":"Cm\u00d1o Espedrigada, 9",
    "sg:city":"Vigo",
    "sg:orig_category":"Agencias Y Agentes Comerciales, Representantes",
    "sg:phone":"+34 986 20 12 15",
    "sg:postcode":"36210",
    "sg:province":"Pontevedra",
    "wof:name":"Alvarez Santamaria Melchor",
    "wof:placetype":"venue"
},
  "geometry": {"coordinates":[-8.734837532,42.215675354],"type":"Point"}
}