{
  "type": "Feature",
  "properties": {
    "addr:full":"C/ Calderon, 1 Alcoi Alicante 03804",
    "addr:housenumber":"1",
    "addr:postcode":"03804",
    "addr:street":"C / Calderon",
    "iso:country":"ES",
    "sg:address":"C/ Calderon, 1",
    "sg:city":"Alcoi",
    "sg:orig_category":"Maquinaria Para Industrias Diversas",
    "sg:phone":"+34 966 52 15 53",
    "sg:postcode":"03804",
    "sg:province":"Alicante",
    "wof:name":"Gisbert Sanchis Antonio Jorge",
    "wof:placetype":"venue"
},
  "geometry": {"coordinates":[-0.4730490148,38.7038192749],"type":"Point"}
}