{
  "type": "Feature",
  "properties": {
    "addr:full":"Cmno San Martin De La Vega, 67 Arganda Madrid 28500",
    "addr:housenumber":"67",
    "addr:postcode":"28500",
    "addr:street":"Cmno San Martin De La Vega",
    "iso:country":"ES",
    "sg:address":"Cmno San Martin De La Vega, 67",
    "sg:city":"Arganda",
    "sg:orig_category":"Fabricaci\u00d3n De Moldes Y Modelos",
    "sg:phone":"+34 918 71 82 30",
    "sg:postcode":"28500",
    "sg:province":"Madrid",
    "wof:name":"Garcia Chamorro Vicenta",
    "wof:placetype":"venue"
},
  "geometry": {"coordinates":[-3.4662709236,40.2998313904],"type":"Point"}
}