{
  "type": "Feature",
  "properties": {
    "addr:full":"Calle de Julian Romea, 9 Madrid Madrid 28003",
    "addr:housenumber":"9",
    "addr:postcode":"madrid;28003",
    "addr:street":"Calle De Julian Romea",
    "iso:country":"ES",
    "sg:address":"Calle de Julian Romea, 9",
    "sg:city":"Madrid",
    "sg:orig_category":"M\u00c9dicos: Cardiolog\u00cda Y Afecciones Cardiovasculares",
    "sg:phone":"+34 915 53 93 25",
    "sg:postcode":"28003",
    "sg:province":"Madrid",
    "wof:name":"Llovet Verdugo Alfredo",
    "wof:placetype":"venue"
},
  "geometry": {"coordinates":[-3.7147479057,40.442565918],"type":"Point"}
}