{
  "type": "Feature",
  "properties": {
    "addr:full":"Carrer de Narcis Monturiol, 10 Manresa Barcelona 08243",
    "addr:housenumber":"10",
    "addr:postcode":"08243",
    "addr:street":"Carrer De Narcis Monturiol",
    "iso:country":"ES",
    "sg:address":"Carrer de Narcis Monturiol, 10",
    "sg:city":"Manresa",
    "sg:orig_category":"Material Hidr\u00c1ulico",
    "sg:phone":"+34 938 77 07 73",
    "sg:postcode":"08243",
    "sg:province":"Barcelona",
    "wof:name":"Recanvis Codina S. L.",
    "wof:placetype":"venue"
},
  "geometry": {"coordinates":[1.8474980593,41.717628479],"type":"Point"}
}