{
  "type": "Feature",
  "properties": {
    "addr:full":"Luga Finca Los Alamos, S/n Playa San Juan Santa Cruz De Tenerife 38687",
    "addr:housenumber":"/ n",
    "addr:postcode":"38687",
    "addr:street":"Los Alamos S",
    "iso:country":"ES",
    "sg:address":"Luga Finca Los Alamos, S/n",
    "sg:city":"Playa San Juan",
    "sg:orig_category":"Frutas Y Legumbres Frescas (al Por Mayor)",
    "sg:phone":"+34 922 86 51 67",
    "sg:postcode":"38687",
    "sg:province":"Santa Cruz De Tenerife",
    "wof:name":"Iniciativas Empresariales Canarias S.l.",
    "wof:placetype":"venue"
},
  "geometry": {"coordinates":[-16.7886390686,28.1805458069],"type":"Point"}
}