{
  "type": "Feature",
  "properties": {
    "addr:full":"Calle de Celestino Cabeza, 16 Langreo Asturias 33900",
    "addr:housenumber":"16",
    "addr:postcode":"33900",
    "addr:street":"Calle De Celestino Cabeza",
    "iso:country":"ES",
    "sg:address":"Calle de Celestino Cabeza, 16",
    "sg:city":"Langreo",
    "sg:orig_category":"M\u00c9dicos: Estomatolog\u00cda",
    "sg:phone":"+34 985 67 48 71",
    "sg:postcode":"33900",
    "sg:province":"Asturias",
    "wof:name":"Junquera Gonzalez Jose Vicente",
    "wof:placetype":"venue"
},
  "geometry": {"coordinates":[-5.6928339005,43.3093338013],"type":"Point"}
}