{
  "type": "Feature",
  "properties": {
    "iso:country":"ES",
    "sg:address":"Calle de Limon, 20",
    "sg:city":"Madrid",
    "sg:orig_category":"Edici\u00d3n De Diarios, Revistas, Boletines",
    "sg:phone":"+34 915 59 00 91",
    "sg:postcode":"28015",
    "sg:province":"Madrid",
    "wof:name":"Fundacion Viento Sur",
    "wof:placetype":"venue"
},
  "geometry": {"coordinates":[-3.7102539539,40.4266433716],"type":"Point"}
}