{
  "type": "Feature",
  "properties": {
    "iso:country":"ES",
    "sg:address":"Calle de Mesena, 33",
    "sg:city":"Madrid",
    "sg:orig_category":"Inform\u00c1tica Equipo Y Programas (al Por Mayor)",
    "sg:phone":"+34 913 00 45 66",
    "sg:postcode":"28033",
    "sg:province":"Madrid",
    "sg:website":"www.gruphotel.com",
    "wof:name":"Aplicaciones Informaticas De Hoteles S.l.",
    "wof:placetype":"venue"
},
  "geometry": {"coordinates":[-3.6625943184,40.464427948],"type":"Point"}
}