{
  "type": "Feature",
  "properties": {
    "addr:full":"Avda Reyes Catolicos, 17 Melilla Melilla 52003",
    "addr:housenumber":"17",
    "addr:postcode":"52003",
    "addr:street":"Avda Reyes Catolicos",
    "iso:country":"ES",
    "sg:address":"Avda Reyes Catolicos, 17",
    "sg:city":"Melilla",
    "sg:orig_category":"Audiovisuales: Material Y Accesorios (al Por Menor)",
    "sg:phone":"+34 952 68 55 57",
    "sg:postcode":"52003",
    "sg:province":"Melilla",
    "wof:name":"Soriano Carvajal Luis",
    "wof:placetype":"venue"
},
  "geometry": {"coordinates":[-2.9443769455,35.2915611267],"type":"Point"}
}