{
  "type": "Feature",
  "properties": {
    "iso:country":"ES",
    "sg:address":"Prag Puig Rumi, S/n",
    "sg:city":"Bruguerol",
    "sg:orig_category":"Inmobiliaria (agencias)",
    "sg:phone":"+34 972 19 61 92",
    "sg:postcode":"17200",
    "sg:province":"Girona",
    "wof:name":"Gramar Dos S.l.",
    "wof:placetype":"venue"
},
  "geometry": {"coordinates":[3.1597599983,41.9181594849],"type":"Point"}
}