{
  "type": "Feature",
  "properties": {
    "iso:country":"ES",
    "sg:address":"Avda Tilo (del), 7",
    "sg:city":"Toledo",
    "sg:orig_category":"Agencias Y Asesores De Publicidad",
    "sg:phone":"+34 925 28 16 14",
    "sg:postcode":"45005",
    "sg:province":"Toledo",
    "sg:website":"www.elsacacorcho.com",
    "wof:name":"Comunicacion Morales S.l.",
    "wof:placetype":"venue"
},
  "geometry": {"coordinates":[-4.0524578094,39.9003448486],"type":"Point"}
}