{
  "type": "Feature",
  "properties": {
    "iso:country":"ES",
    "sg:address":"Calle de Emilio Parra, 5",
    "sg:city":"S. Asensio",
    "sg:orig_category":"Supermercados Y Hipermercados",
    "sg:phone":"+34 941 45 75 10",
    "sg:postcode":"26340",
    "sg:province":"La Rioja",
    "wof:name":"Autoservicio Ortem S.l.",
    "wof:placetype":"venue"
},
  "geometry": {"coordinates":[-2.7487716675,42.497013092],"type":"Point"}
}