{
  "type": "Feature",
  "properties": {
    "iso:country":"ES",
    "sg:address":"Calle de Jose Antonio (de), 19",
    "sg:city":"Boadilla Del Monte",
    "sg:orig_category":"Peluquer\u00cdas, Peluquer\u00cda Mixta",
    "sg:phone":"+34 916 32 68 60",
    "sg:postcode":"28660",
    "sg:province":"Madrid",
    "wof:name":"Aubena C.b.",
    "wof:placetype":"venue"
},
  "geometry": {"coordinates":[-3.8772931099,40.4053268433],"type":"Point"}
}