{
  "type": "Feature",
  "properties": {
    "iso:country":"ES",
    "sg:address":"Calle de Laguna Negra, 13",
    "sg:city":"Madrid",
    "sg:orig_category":"Centros Empresariales",
    "sg:phone":"+34 913 01 60 23",
    "sg:postcode":"28030",
    "sg:province":"Madrid",
    "wof:name":"Lucas Mateos Ana",
    "wof:placetype":"venue"
},
  "geometry": {"coordinates":[-3.6294898987,40.4047584534],"type":"Point"}
}