{
  "type": "Feature",
  "properties": {
    "iso:country":"ES",
    "sg:address":"Avda Pianista Martinez Carrasco, 2",
    "sg:city":"Valencia",
    "sg:orig_category":"Servidores Y Editores De Bases De Datos",
    "sg:phone":"+34 963 73 85 07",
    "sg:postcode":"46026",
    "sg:province":"Valencia",
    "sg:website":"www.digitalvalue.es",
    "wof:name":"Digital Value S.l.",
    "wof:placetype":"venue"
},
  "geometry": {"coordinates":[-0.3698990047,39.4477119446],"type":"Point"}
}