{
  "type": "Feature",
  "properties": {
    "iso:country":"ES",
    "sg:address":"Plaz Mayor, 32",
    "sg:city":"Forcall",
    "sg:orig_category":"Cajas Para Embalar",
    "sg:phone":"+34 964 17 10 55",
    "sg:postcode":"12310",
    "sg:province":"Castell\u00f3n",
    "wof:name":"Caja Rural Del Mediterraneo Ruralcaja S Coop De Credito",
    "wof:placetype":"venue"
},
  "geometry": {"coordinates":[-0.1997240037,40.6456031799],"type":"Point"}
}