{
  "type": "Feature",
  "properties": {
    "addr:full":"Avda Jerez, 51 Sevilla Sevilla 41013",
    "addr:housenumber":"51",
    "addr:postcode":"41013",
    "addr:street":"Avda Jerez",
    "iso:country":"ES",
    "sg:address":"Avda Jerez, 51",
    "sg:city":"Sevilla",
    "sg:orig_category":"Internados & Ense\u00d1anza Privada",
    "sg:phone":"+34 954 69 00 72",
    "sg:postcode":"41013",
    "sg:province":"Sevilla",
    "wof:name":"Colegio Santa Maria De Bellavista S.a.",
    "wof:placetype":"venue"
},
  "geometry": {"coordinates":[-5.9772291183,37.351688385],"type":"Point"}
}