{
  "type": "Feature",
  "properties": {
    "iso:country":"ES",
    "sg:address":"Calle de Leon Y Castillo, 29",
    "sg:city":"Ingenio",
    "sg:orig_category":"M\u00c9dicos: Pediatr\u00cda. Enfermedades De Los Ni\u00d1os",
    "sg:phone":"+34 928 78 00 81",
    "sg:postcode":"35250",
    "sg:province":"Las Palmas",
    "wof:name":"Gil Ramirez Juan",
    "wof:placetype":"venue"
},
  "geometry": {"coordinates":[-15.4385004044,27.9193077087],"type":"Point"}
}