{
  "type": "Feature",
  "properties": {
    "iso:country":"ES",
    "sg:address":"Talleres, 29",
    "sg:city":"Puerto Sagunto",
    "sg:orig_category":"Material Hidr\u00c1ulico",
    "sg:phone":"+34 962 67 10 88",
    "sg:postcode":"46520",
    "sg:province":"Valencia",
    "wof:name":"Sanchez Y Marin Hidraulic S.l.",
    "wof:placetype":"venue"
},
  "geometry": {"coordinates":[-0.2025949955,39.7040786743],"type":"Point"}
}