{
  "type": "Feature",
  "properties": {
    "iso:country":"ES",
    "sg:address":"Carr Rutlla, 22",
    "sg:city":"Girona",
    "sg:orig_category":"Peluqueros: De Se\u00d1oras",
    "sg:phone":"+34 972 20 88 82",
    "sg:postcode":"17002",
    "sg:province":"Girona",
    "wof:name":"Rufi Vilalta Joaquina",
    "wof:placetype":"venue"
},
  "geometry": {"coordinates":[2.8232069016,41.9782714844],"type":"Point"}
}