{
  "type": "Feature",
  "properties": {
    "addr:full":"Ctra Canillas, 138 Madrid Madrid 28043",
    "addr:housenumber":"138",
    "addr:postcode":"28043",
    "addr:street":"Ctra Canillas",
    "iso:country":"ES",
    "sg:address":"Ctra Canillas, 138",
    "sg:city":"Madrid",
    "sg:orig_category":"Inform\u00c1tica (estudios, Servicios, Asesor\u00cda, Formaci\u00d3n)",
    "sg:phone":"+34 913 88 47 17",
    "sg:postcode":"28043",
    "sg:province":"Madrid",
    "wof:name":"Nivania Investigacion Y Desarrollo S.l.l",
    "wof:placetype":"venue"
},
  "geometry": {"coordinates":[-3.6399900913,40.4651451111],"type":"Point"}
}