{
  "type": "Feature",
  "properties": {
    "addr:full":"Calle de Valencia, Km. 0100,0 Yecla Murcia 30510",
    "addr:postcode":"30510",
    "addr:street":"Calle De Valencia Km. 0100,0",
    "iso:country":"ES",
    "sg:address":"Calle de Valencia, Km. 0100,0",
    "sg:city":"Yecla",
    "sg:orig_category":"Contenedores (mercanc\u00cdas)",
    "sg:phone":"+34 968 71 80 13",
    "sg:postcode":"30510",
    "sg:province":"Murcia",
    "wof:name":"Transportes Y Transitos Navarro Y Garcia S.l.",
    "wof:placetype":"venue"
},
  "geometry": {"coordinates":[-1.1103210449,38.6174201965],"type":"Point"}
}