{
  "type": "Feature",
  "properties": {
    "iso:country":"ES",
    "sg:address":"Poli Poligono Industrial Pedroches, S/n",
    "sg:city":"Cordoba",
    "sg:orig_category":"Discotecas Y Salas De Baile",
    "sg:phone":"+34 957 43 15 40",
    "sg:postcode":"14014",
    "sg:province":"C\u00f3rdoba",
    "wof:name":"Baena Ca\u00f1ero Miguel",
    "wof:placetype":"venue"
},
  "geometry": {"coordinates":[-4.6243748665,37.9513511658],"type":"Point"}
}