{
  "type": "Feature",
  "properties": {
    "iso:country":"ES",
    "sg:address":"Calle de San Francisco, 2",
    "sg:city":"Burgos",
    "sg:orig_category":"Molduras, Junquillos, Listones Y Molduras Perforadas",
    "sg:phone":"+34 947 20 49 35",
    "sg:postcode":"09003",
    "sg:province":"Burgos",
    "wof:name":"Gonzalez Velazco Jose Luis",
    "wof:placetype":"venue"
},
  "geometry": {"coordinates":[-3.7032470703,42.3450202942],"type":"Point"}
}