{
  "type": "Feature",
  "properties": {
    "addr:full":"Avda Colon, 29 Logro\u00f1o La Rioja 26003",
    "addr:housenumber":"29",
    "addr:postcode":"26003",
    "addr:street":"Avda Colon;Rioja",
    "iso:country":"ES",
    "sg:address":"Avda Colon, 29",
    "sg:city":"Logro\u00f1o",
    "sg:orig_category":"Promotores Constructores",
    "sg:phone":"+34 941 25 06 99",
    "sg:postcode":"26003",
    "sg:province":"La Rioja",
    "wof:name":"Ramos Fernandez Juan Nicolas",
    "wof:placetype":"venue"
},
  "geometry": {"coordinates":[-2.4397270679,42.4626922607],"type":"Point"}
}