{
  "type": "Feature",
  "properties": {
    "iso:country":"ES",
    "sg:address":"Avda San Pedro De Alcantara, 4",
    "sg:city":"Caceres",
    "sg:orig_category":"Bisuter\u00cda, Joyer\u00cda, Relojer\u00cda (al Por Menor)",
    "sg:phone":"+34 927 22 23 70",
    "sg:postcode":"10001",
    "sg:province":"C\u00e1ceres",
    "wof:name":"Morales Vinagre Juan",
    "wof:placetype":"venue"
},
  "geometry": {"coordinates":[-6.378431797,39.4706802368],"type":"Point"}
}