{
  "type": "Feature",
  "properties": {
    "iso:country":"ES",
    "sg:address":"Calle de San Bernardo, 15",
    "sg:city":"Gijon",
    "sg:orig_category":"Suministros Para Hoteles",
    "sg:phone":"+34 985 34 53 23",
    "sg:postcode":"33201",
    "sg:province":"Asturias",
    "sg:website":"www.jesuspastor.com",
    "wof:name":"Jesus Pastor Hosteleria S.l.",
    "wof:placetype":"venue"
},
  "geometry": {"coordinates":[-5.662217617,43.543636322],"type":"Point"}
}