{
  "type": "Feature",
  "properties": {
    "addr:full":"Calle de Eras, 11 Alcantarilla Murcia 30820",
    "addr:housenumber":"11",
    "addr:postcode":"30820",
    "addr:street":"Calle De Eras",
    "iso:country":"ES",
    "sg:address":"Calle de Eras, 11",
    "sg:city":"Alcantarilla",
    "sg:orig_category":"Ense\u00d1anza, Formaci\u00d3n Profesional: Aprendizaje",
    "sg:phone":"+34 968 80 11 00",
    "sg:postcode":"30820",
    "sg:province":"Murcia",
    "wof:name":"Direccion General De La Policia",
    "wof:placetype":"venue"
},
  "geometry": {"coordinates":[-1.2119669914,37.9697952271],"type":"Point"}
}