{
  "type": "Feature",
  "properties": {
    "iso:country":"ES",
    "sg:address":"Urb. Mare N., 24",
    "sg:city":"Salobre\u00f1a",
    "sg:orig_category":"Moda",
    "sg:phone":"+34 958 61 25 77",
    "sg:postcode":"18680",
    "sg:province":"Granada",
    "wof:name":"Garcia Calatayud Estefania",
    "wof:placetype":"venue"
},
  "geometry": {"coordinates":[-3.5913939476,36.7602424622],"type":"Point"}
}