{
  "type": "Feature",
  "properties": {
    "addr:full":"Pl. Jaime I, 3 Alfas Pi Alicante 03580",
    "addr:housenumber":"3",
    "addr:postcode":"03580",
    "addr:street":"Pl. Jaime I",
    "iso:country":"ES",
    "sg:address":"Pl. Jaime I, 3",
    "sg:city":"Alfas Pi",
    "sg:orig_category":"Edici\u00d3n De Diarios, Revistas, Boletines",
    "sg:phone":"+34 965 88 99 05",
    "sg:postcode":"03580",
    "sg:province":"Alicante",
    "sg:website":"www.aktueltspania.com",
    "wof:name":"Artuelt Magasin Sl",
    "wof:placetype":"venue"
},
  "geometry": {"coordinates":[-0.1030813009,38.5804176331],"type":"Point"}
}