{
  "type": "Feature",
  "properties": {
    "iso:country":"ES",
    "sg:address":"Avda Menendez Y Pelayo, 20",
    "sg:city":"Valencia",
    "sg:orig_category":"Institutos De Belleza",
    "sg:phone":"+34 963 60 36 14",
    "sg:postcode":"46010",
    "sg:province":"Valencia",
    "wof:name":"Leonor Frijanes Bachiller Y Concha Frijanes Bachiller Cdad",
    "wof:placetype":"venue"
},
  "geometry": {"coordinates":[-0.3566539884,39.4780845642],"type":"Point"}
}