{
  "type": "Feature",
  "properties": {
    "addr:full":"Trva Cedro (del), 5 Huesca Huesca 22001",
    "addr:housenumber":"5",
    "addr:postcode":"22001",
    "addr:street":"Trva Cedro Del",
    "iso:country":"ES",
    "sg:address":"Trva Cedro (del), 5",
    "sg:city":"Huesca",
    "sg:orig_category":"Electricidad: Instaladores",
    "sg:phone":"+34 974 24 21 01",
    "sg:postcode":"22001",
    "sg:province":"Huesca",
    "wof:name":"Huescaluz S.cv.",
    "wof:placetype":"venue"
},
  "geometry": {"coordinates":[-0.4067389965,42.1384391785],"type":"Point"}
}