{
  "type": "Feature",
  "properties": {
    "addr:full":"Calle de Camino Del Norte, S/n Alcora Castell\u00f3n 12110",
    "addr:housenumber":"s / n",
    "addr:postcode":"12110",
    "addr:street":"Calle De Camino Del Norte;Alcora Castello\u0301N",
    "iso:country":"ES",
    "sg:address":"Calle de Camino Del Norte, S/n",
    "sg:city":"Alcora",
    "sg:orig_category":"Supermercados Y Hipermercados",
    "sg:phone":"+34 964 36 30 84",
    "sg:postcode":"12110",
    "sg:province":"Castell\u00f3n",
    "sg:website":"www.mercadona.es",
    "wof:name":"Mercadona S.a.",
    "wof:placetype":"venue"
},
  "geometry": {"coordinates":[-0.215545997,40.0709190369],"type":"Point"}
}