{
  "type": "Feature",
  "properties": {
    "addr:full":"Calle de Villaamil, 39 Madrid Madrid 28039",
    "addr:housenumber":"39",
    "addr:postcode":"madrid;28039",
    "addr:street":"Calle De Villaamil",
    "iso:country":"ES",
    "sg:address":"Calle de Villaamil, 39",
    "sg:city":"Madrid",
    "sg:orig_category":"Afiladoras, Pulidoras Y Bru\u00d1idoras",
    "sg:phone":"+34 913 11 31 50",
    "sg:postcode":"28039",
    "sg:province":"Madrid",
    "wof:name":"Alfredo Blanco S.l.",
    "wof:placetype":"venue"
},
  "geometry": {"coordinates":[-3.7074158192,40.4592437744],"type":"Point"}
}