{
  "type": "Feature",
  "properties": {
    "iso:country":"ES",
    "sg:address":"Avda Buenos Aires, 86",
    "sg:city":"Lalin",
    "sg:orig_category":"Molduras, Junquillos, Listones Y Molduras Perforadas",
    "sg:phone":"+34 986 78 06 18",
    "sg:postcode":"36500",
    "sg:province":"Pontevedra",
    "wof:name":"Fernandez Garcia Francisco Javier",
    "wof:placetype":"venue"
},
  "geometry": {"coordinates":[-8.1126489639,42.6599311829],"type":"Point"}
}