{
  "type": "Feature",
  "properties": {
    "iso:country":"ES",
    "sg:address":"Rond Torrassa, 44",
    "sg:city":"Hospitalet Llobregat",
    "sg:orig_category":"Carnicer\u00cdas, Carnicer\u00cdas",
    "sg:phone":"+34 934 22 75 82",
    "sg:postcode":"08903",
    "sg:province":"Barcelona",
    "wof:name":"Catasus Perez Gloria",
    "wof:placetype":"venue"
},
  "geometry": {"coordinates":[2.1276259422,41.3696937561],"type":"Point"}
}