{
  "type": "Feature",
  "properties": {
    "addr:full":"Avda Granada, Km. 0337,0 Jaen Ja\u00e9n 23001",
    "addr:postcode":"23001",
    "addr:street":"Avda Granada Km. 0337,0 Jaen Jae\u0301N",
    "iso:country":"ES",
    "sg:address":"Avda Granada, Km. 0337,0",
    "sg:city":"Jaen",
    "sg:orig_category":"Distribuci\u00d3n De Petr\u00d3leo Y Derivados",
    "sg:phone":"+34 953 24 36 57",
    "sg:postcode":"23001",
    "sg:province":"Ja\u00e9n",
    "wof:name":"Cedipsa Compa\u00d1ia Espa\u00d1ola Distribuidora De Petroleos S.a.",
    "wof:placetype":"venue"
},
  "geometry": {"coordinates":[-3.7841889858,37.768699646],"type":"Point"}
}