{
  "type": "Feature",
  "properties": {
    "iso:country":"ES",
    "sg:address":"Ctra. Nacional T. Cuarenta, Km. 0187,0",
    "sg:city":"Marbella",
    "sg:orig_category":"Hospitales",
    "sg:phone":"+34 952 86 27 48",
    "sg:postcode":"29600",
    "sg:province":"M\u00e1laga",
    "wof:name":"Empresa Publica Hospital Costa Del Sol",
    "wof:placetype":"venue"
},
  "geometry": {"coordinates":[-4.8833007812,36.5079956055],"type":"Point"}
}