{
  "type": "Feature",
  "properties": {
    "iso:country":"ES",
    "sg:address":"Carrer de Girona, 31",
    "sg:city":"Granollers",
    "sg:orig_category":"Muebles, Minoristas",
    "sg:phone":"+34 938 70 42 37",
    "sg:postcode":"08402",
    "sg:province":"Barcelona",
    "sg:website":"www.treku.es",
    "wof:name":"Albi Mobles Decoracio I Disseny De Barcelona 2004 S.l.",
    "wof:placetype":"venue"
},
  "geometry": {"coordinates":[2.2909605503,41.6107177734],"type":"Point"}
}