{
  "type": "Feature",
  "properties": {
    "iso:country":"ES",
    "sg:address":"Pase San Francisco De Sales, 35",
    "sg:city":"Madrid",
    "sg:orig_category":"Ingenier\u00cda, Centros De Estudios (diversos)",
    "sg:phone":"+34 915 53 19 28",
    "sg:postcode":"28003",
    "sg:province":"Madrid",
    "wof:name":"Rodriguez Francos Javier",
    "wof:placetype":"venue"
},
  "geometry": {"coordinates":[-3.7126510143,40.4425926208],"type":"Point"}
}