{
  "type": "Feature",
  "properties": {
    "addr:full":"Trav De Gracia, 207 Barcelona Barcelona 08012",
    "addr:housenumber":"207",
    "addr:postcode":"08012",
    "addr:street":"Trav De Gracia",
    "iso:country":"ES",
    "sg:address":"Trav De Gracia, 207",
    "sg:city":"Barcelona",
    "sg:orig_category":"Centros Comerciales Y Grandes Tiendas",
    "sg:phone":"+34 932 85 66 70",
    "sg:postcode":"08012",
    "sg:province":"Barcelona",
    "wof:name":"Liu  Yun Wen",
    "wof:placetype":"venue"
},
  "geometry": {"coordinates":[2.1602458954,41.4029350281],"type":"Point"}
}