{
  "type": "Feature",
  "properties": {
    "addr:full":"Calle de L'horta, 6 Torrent Valencia 46900",
    "addr:housenumber":"6",
    "addr:postcode":"46900",
    "addr:street":"Calle De L'Horta;Valencia",
    "iso:country":"ES",
    "sg:address":"Calle de L'horta, 6",
    "sg:city":"Torrent",
    "sg:orig_category":"Mec\u00c1nico Del Autom\u00d3vil",
    "sg:phone":"+34 961 57 11 34",
    "sg:postcode":"46900",
    "sg:province":"Valencia",
    "wof:name":"Tomas Reparauto S.l.",
    "wof:placetype":"venue"
},
  "geometry": {"coordinates":[-0.4729574919,39.4338874817],"type":"Point"}
}