{
  "type": "Feature",
  "properties": {
    "iso:country":"ES",
    "sg:address":"Calle de Verdaguer Y Garcia, 57",
    "sg:city":"Madrid",
    "sg:orig_category":"Arreglo, Reparaci\u00d3n, Piezas Sueltas De Televisi\u00d3n, V\u00cddeo, Hi",
    "sg:phone":"+34 914 04 33 44",
    "sg:postcode":"28027",
    "sg:province":"Madrid",
    "sg:website":"www.francoservicios.es",
    "wof:name":"Franco Servicio Hi-fi Tv S.l.",
    "wof:placetype":"venue"
},
  "geometry": {"coordinates":[-3.6529910564,40.4412574768],"type":"Point"}
}