{
  "type": "Feature",
  "properties": {
    "addr:full":"Calle de Senda Mitjana, S/n Nules Castell\u00f3n 12520",
    "addr:housenumber":"s / n",
    "addr:postcode":"12520",
    "addr:street":"Calle De Senda Mitjana",
    "iso:country":"ES",
    "sg:address":"Calle de Senda Mitjana, S/n",
    "sg:city":"Nules",
    "sg:orig_category":"Alimentaci\u00d3n General (al Por Mayor)",
    "sg:phone":"+34 964 67 35 62",
    "sg:postcode":"12520",
    "sg:province":"Castell\u00f3n",
    "wof:name":"Coaliment Valencia S. A.",
    "wof:placetype":"venue"
},
  "geometry": {"coordinates":[-0.1493750066,39.8548622131],"type":"Point"}
}