{
  "type": "Feature",
  "properties": {
    "addr:full":"Calle de Sanchez Pacheco, 85 Madrid Madrid 28002",
    "addr:housenumber":"85",
    "addr:postcode":"madrid;28002",
    "addr:street":"Calle De Sanchez Pacheco",
    "iso:country":"ES",
    "sg:address":"Calle de Sanchez Pacheco, 85",
    "sg:city":"Madrid",
    "sg:orig_category":"Agencias Y Asesores De Publicidad",
    "sg:phone":"+34 914 13 41 59",
    "sg:postcode":"28002",
    "sg:province":"Madrid",
    "sg:website":"www.soleroysolero.com",
    "wof:name":"Solero Y Solero Y Partners S.a.",
    "wof:placetype":"venue"
},
  "geometry": {"coordinates":[-3.6688816547,40.4487342834],"type":"Point"}
}