{
  "type": "Feature",
  "properties": {
    "addr:full":"Calle de San Filiberto, 4 Madrid Madrid 28026",
    "addr:housenumber":"4",
    "addr:postcode":"28026",
    "addr:street":"Calle De San Filiberto",
    "iso:country":"ES",
    "sg:address":"Calle de San Filiberto, 4",
    "sg:city":"Madrid",
    "sg:orig_category":"Comerciantes Al Por Mayor De Vinos, Licores Y Alcoholes",
    "sg:phone":"+34 915 69 30 58",
    "sg:postcode":"28026",
    "sg:province":"Madrid",
    "wof:name":"Martinez Vazquez Jose Luis",
    "wof:placetype":"venue"
},
  "geometry": {"coordinates":[-3.715182066,40.3855285645],"type":"Point"}
}