{
  "type": "Feature",
  "properties": {
    "addr:full":"Akezko Auzoa, 1 Elbarrena Guip\u00f9zcoa 20159",
    "addr:housenumber":"1",
    "addr:postcode":"20159",
    "addr:street":"Akezko Auzoa;Guipu\u0300Zcoa",
    "iso:country":"ES",
    "sg:address":"Akezko Auzoa, 1",
    "sg:city":"Elbarrena",
    "sg:orig_category":"Tubos De Cart\u00d3n Y Papel",
    "sg:phone":"+34 943 69 34 88",
    "sg:postcode":"20159",
    "sg:province":"Guip\u00f9zcoa",
    "wof:name":"Vi\u00f1aras Echeverria Francisco Javier",
    "wof:placetype":"venue"
},
  "geometry": {"coordinates":[-2.0742990971,43.1991958618],"type":"Point"}
}