{
  "type": "Feature",
  "properties": {
    "addr:full":"Calle de Berenguer, 8 Huesca Huesca 22002",
    "addr:housenumber":"8",
    "addr:postcode":"22002",
    "addr:street":"Calle De Berenguer",
    "iso:country":"ES",
    "sg:address":"Calle de Berenguer, 8",
    "sg:city":"Huesca",
    "sg:orig_category":"Agricultura: Abastecimiento Y Cosechado (negocio)",
    "sg:phone":"+34 974 21 82 62",
    "sg:postcode":"22002",
    "sg:province":"Huesca",
    "wof:name":"Usata Sociedad Cooperativa Limitada",
    "wof:placetype":"venue"
},
  "geometry": {"coordinates":[-0.4075700045,42.1364555359],"type":"Point"}
}