{
  "type": "Feature",
  "properties": {
    "iso:country":"ES",
    "sg:address":"Carrer de L'equador, 39",
    "sg:city":"Barcelona",
    "sg:orig_category":"Inform\u00c1tica (estudios, Servicios, Asesor\u00cda, Formaci\u00d3n)",
    "sg:phone":"+34 933 66 69 00",
    "sg:postcode":"08...",
    "sg:province":"Barcelona",
    "wof:name":"Abast Systems S.a.",
    "wof:placetype":"venue"
},
  "geometry": {"coordinates":[2.140136,41.385853],"type":"Point"}
}