{
  "type": "Feature",
  "properties": {
    "addr:full":"Pase Maria Agustin, 80 Zaragoza Zaragoza 50003",
    "addr:housenumber":"80",
    "addr:postcode":"50003",
    "addr:street":"Agustin",
    "iso:country":"ES",
    "sg:address":"Pase Maria Agustin, 80",
    "sg:city":"Zaragoza",
    "sg:orig_category":"Promotores Constructores",
    "sg:phone":"+34 976 43 06 10",
    "sg:postcode":"50003",
    "sg:province":"Zaragoza",
    "wof:name":"Promociones Inmobiliarias Servet 2000 S.l.",
    "wof:placetype":"venue"
},
  "geometry": {"coordinates":[-0.8928340077,41.6578865051],"type":"Point"}
}