{
  "type": "Feature",
  "properties": {
    "iso:country":"ES",
    "sg:address":"Plaz Jose Antonio, S/n",
    "sg:city":"Villasante",
    "sg:orig_category":"Farmacias",
    "sg:phone":"+34 947 14 01 00",
    "sg:postcode":"09569",
    "sg:province":"Burgos",
    "wof:name":"Paredes Astarloa Maria Pilar",
    "wof:placetype":"venue"
},
  "geometry": {"coordinates":[-3.4740591049,43.0654754639],"type":"Point"}
}