{
  "type": "Feature",
  "properties": {
    "iso:country":"ES",
    "sg:address":"Avda Monforte De Lemos, S/n",
    "sg:city":"Madrid",
    "sg:orig_category":"Fabricaci\u00d3n De Productos Textiles Sin Tejer",
    "sg:phone":"+34 917 30 19 97",
    "sg:postcode":"28029",
    "sg:province":"Madrid",
    "sg:website":"www.hogarmodatres.com",
    "wof:name":"Almacenes Glofer S.a.",
    "wof:placetype":"venue"
},
  "geometry": {"coordinates":[-3.70332551,40.4793395996],"type":"Point"}
}