{
  "type": "Feature",
  "properties": {
    "addr:full":"Carrer de Major, 23 S. Boi Llobregat Barcelona 08830",
    "addr:housenumber":"23",
    "addr:postcode":"08830",
    "addr:street":"Carrer De Major",
    "iso:country":"ES",
    "sg:address":"Carrer de Major, 23",
    "sg:city":"S. Boi Llobregat",
    "sg:orig_category":"Farmacias",
    "sg:phone":"+34 936 40 00 06",
    "sg:postcode":"08830",
    "sg:province":"Barcelona",
    "wof:name":"Vaquer Fontanet Anna",
    "wof:placetype":"venue"
},
  "geometry": {"coordinates":[2.0423159599,41.3467216492],"type":"Point"}
}