{
  "type": "Feature",
  "properties": {
    "iso:country":"ES",
    "sg:address":"Calle de Florentino Cueto Felgueroso, 5",
    "sg:city":"Langreo",
    "sg:orig_category":"Fabricaci\u00d3n, Importaci\u00d3n De L\u00c1mparas Y Bombillas",
    "sg:phone":"+34 985 67 70 88",
    "sg:postcode":"33930",
    "sg:province":"Asturias",
    "wof:name":"Instelan Digital S.l.",
    "wof:placetype":"venue"
},
  "geometry": {"coordinates":[-5.692440033,43.3076629639],"type":"Point"}
}