{
  "type": "Feature",
  "properties": {
    "iso:country":"ES",
    "sg:address":"Carrer de Gavines (peguera), 14",
    "sg:city":"Peguera",
    "sg:orig_category":"Caf\u00c9s, Bares, Cervecer\u00cdas",
    "sg:phone":"+34 971 68 66 53",
    "sg:postcode":"07160",
    "sg:province":"Islas Baleares",
    "wof:name":"Sans Alema\u00f1y Francisco",
    "wof:placetype":"venue"
},
  "geometry": {"coordinates":[2.4581298828,39.5372200012],"type":"Point"}
}