{
  "type": "Feature",
  "properties": {
    "iso:country":"ES",
    "sg:address":"Carrer de Casanova, 228",
    "sg:city":"Barcelona",
    "sg:orig_category":"Librer\u00cdas",
    "sg:phone":"+34 933 22 04 71",
    "sg:postcode":"08036",
    "sg:province":"Barcelona",
    "wof:name":"Labra\u00f1a Galceran Maria Rosa",
    "wof:placetype":"venue"
},
  "geometry": {"coordinates":[2.1494300365,41.3924789429],"type":"Point"}
}