{
  "type": "Feature",
  "properties": {
    "iso:country":"ES",
    "sg:address":"Carrer de Consell De Cent, 322",
    "sg:city":"Barcelona",
    "sg:orig_category":"Abogados",
    "sg:phone":"+34 934 87 68 06",
    "sg:postcode":"08007",
    "sg:province":"Barcelona",
    "wof:name":"Oromi Badia Alberto",
    "wof:placetype":"venue"
},
  "geometry": {"coordinates":[2.1671249866,41.3919868469],"type":"Point"}
}