{
  "type": "Feature",
  "properties": {
    "addr:full":"Avda Toledo, 1 Calypo Fado Toledo 45950",
    "addr:housenumber":"1",
    "addr:postcode":"45950",
    "addr:street":"Avda Toledo",
    "iso:country":"ES",
    "sg:address":"Avda Toledo, 1",
    "sg:city":"Calypo Fado",
    "sg:orig_category":"Reposter\u00cdas",
    "sg:phone":"+34 918 13 90 64",
    "sg:postcode":"45950",
    "sg:province":"Toledo",
    "wof:name":"Calipopan S.l..",
    "wof:placetype":"venue"
},
  "geometry": {"coordinates":[-4.0632991791,40.2422904968],"type":"Point"}
}