{
  "type": "Feature",
  "properties": {
    "addr:full":"Barr Sant Antoni, 37 Sant Antoni Lleida 25700",
    "addr:housenumber":"37",
    "addr:postcode":"25700",
    "addr:street":"Sant Antoni",
    "iso:country":"ES",
    "sg:address":"Barr Sant Antoni, 37",
    "sg:city":"Sant Antoni",
    "sg:orig_category":"Empresas De Carpinter\u00cda De Madera",
    "sg:phone":"+34 973 35 03 56",
    "sg:postcode":"25700",
    "sg:province":"Lleida",
    "wof:name":"Segon Grau Esteban",
    "wof:placetype":"venue"
},
  "geometry": {"coordinates":[1.4592299461,42.3578453064],"type":"Point"}
}