{
  "type": "Feature",
  "properties": {
    "addr:full":"Ctra Moron-marchena, Km. 0007,0 Moron Frontera Sevilla 41530",
    "addr:postcode":"41530",
    "addr:street":"Ctra Moron-Marchena Km. 0007,0 Moron",
    "iso:country":"ES",
    "sg:address":"Ctra Moron-marchena, Km. 0007,0",
    "sg:city":"Moron Frontera",
    "sg:orig_category":"Agricultores, Agricultores",
    "sg:phone":"+34 955 95 71 79",
    "sg:postcode":"41530",
    "sg:province":"Sevilla",
    "wof:name":"La Amarguilla S.l.",
    "wof:placetype":"venue"
},
  "geometry": {"coordinates":[-5.4528231621,37.1294212341],"type":"Point"}
}