{
  "type": "Feature",
  "properties": {
    "addr:full":"Carr Jacint Verdaguer, 13 Blanes Girona 17300",
    "addr:housenumber":"13",
    "addr:postcode":"17300",
    "addr:street":"Carr Jacint Verdaguer",
    "iso:country":"ES",
    "sg:address":"Carr Jacint Verdaguer, 13",
    "sg:city":"Blanes",
    "sg:orig_category":"Panader\u00cdas, Panader\u00cdas",
    "sg:phone":"+34 972 35 55 34",
    "sg:postcode":"17300",
    "sg:province":"Girona",
    "wof:name":"Mora 33 S.l.",
    "wof:placetype":"venue"
},
  "geometry": {"coordinates":[2.7805609703,41.6825675964],"type":"Point"}
}