{
  "type": "Feature",
  "properties": {
    "iso:country":"ES",
    "sg:address":"Calle de Joan Miro, 2",
    "sg:city":"Zubia",
    "sg:orig_category":"Notarios",
    "sg:phone":"+34 958 59 29 17",
    "sg:postcode":"18140",
    "sg:province":"Granada",
    "wof:name":"Gonzalez Laa Enrique Emilio",
    "wof:placetype":"venue"
},
  "geometry": {"coordinates":[-3.5853440762,37.1218338013],"type":"Point"}
}