{
  "type": "Feature",
  "properties": {
    "iso:country":"ES",
    "sg:address":"Carrer de Luarca, 4",
    "sg:city":"Hospitalet Llobregat",
    "sg:orig_category":"Peluquer\u00cdas, Peluquer\u00cda Mixta",
    "sg:phone":"+34 934 38 71 92",
    "sg:postcode":"08906",
    "sg:province":"Barcelona",
    "wof:name":"Peluqueria Formas-1 S.c.p.",
    "wof:placetype":"venue"
},
  "geometry": {"coordinates":[2.1030609608,41.3714065552],"type":"Point"}
}