{
  "type": "Feature",
  "properties": {
    "iso:country":"ES",
    "sg:address":"Calle de Primo De Rivera, 14",
    "sg:city":"Caspe",
    "sg:orig_category":"Electricidad: Instaladores",
    "sg:phone":"+34 976 63 02 10",
    "sg:postcode":"50700",
    "sg:province":"Zaragoza",
    "sg:website":"www.insbar.es.org",
    "wof:name":"Insbar S.l.",
    "wof:placetype":"venue"
},
  "geometry": {"coordinates":[-0.0425189994,41.2394981384],"type":"Point"}
}