{
  "type": "Feature",
  "properties": {
    "iso:country":"ES",
    "sg:address":"Ctra Palamos, 53",
    "sg:city":"S. Feliu Guixols",
    "sg:orig_category":"Reposter\u00cdas",
    "sg:phone":"+34 972 32 82 68",
    "sg:postcode":"17220",
    "sg:province":"Girona",
    "wof:name":"Barderi Heras Valeri",
    "wof:placetype":"venue"
},
  "geometry": {"coordinates":[3.0359969139,41.782989502],"type":"Point"}
}