{
  "type": "Feature",
  "properties": {
    "iso:country":"ES",
    "sg:address":"Carr Alfons Xii, 653",
    "sg:city":"Badalona",
    "sg:orig_category":"Materias Pl\u00c1sticas: Productos De Consumo Masivo (fabricaci\u00d3n, Al Por Mayor)",
    "sg:phone":"+34 933 83 28 05",
    "sg:postcode":"08918",
    "sg:province":"Barcelona",
    "wof:name":"Merino Requena Francisco",
    "wof:placetype":"venue"
},
  "geometry": {"coordinates":[2.2280399799,41.4340209961],"type":"Point"}
}