{
  "type": "Feature",
  "properties": {
    "addr:full":"Plaz Calvario, 11 Calvario Pontevedra 36770",
    "addr:housenumber":"11",
    "addr:postcode":"36770",
    "addr:street":"Calvario",
    "iso:country":"ES",
    "sg:address":"Plaz Calvario, 11",
    "sg:city":"Calvario",
    "sg:orig_category":"Cajas De Ahorro",
    "sg:phone":"+34 986 62 62 72",
    "sg:postcode":"36770",
    "sg:province":"Pontevedra",
    "sg:website":"www.lacaixa.es",
    "wof:name":"Caixa D'estalvis I Pensions De Barcelona",
    "wof:placetype":"venue"
},
  "geometry": {"coordinates":[-8.8362493515,41.9370346069],"type":"Point"}
}