{
  "type": "Feature",
  "properties": {
    "addr:full":"Plaz Universidad, 2 Fama Murcia 30001",
    "addr:housenumber":"2",
    "addr:postcode":"30001",
    "addr:street":"Universidad",
    "iso:country":"ES",
    "sg:address":"Plaz Universidad, 2",
    "sg:city":"Fama",
    "sg:classifiers":[
        {
            "category":"Autos & Motor Vehicles",
            "subcategory":"Automobile Sales",
            "type":"Retail Goods"
        }
    ],
    "sg:phone":"+34 968 23 78 49",
    "sg:postcode":"30001",
    "sg:province":"Murcia",
    "wof:name":"Benavente Y Reche S.l",
    "wof:placetype":"venue"
},
  "geometry": {"coordinates":[-1.1302490234,37.9829597473],"type":"Point"}
}