{
  "type": "Feature",
  "properties": {
    "addr:full":"Calle de Progreso, S/n Valencia Alcantara C\u00e1ceres 10500",
    "addr:postcode":"10500",
    "addr:street":"Calle De Progreso S / N;Alcantara Ca\u0301Ceres",
    "iso:country":"ES",
    "sg:address":"Calle de Progreso, S/n",
    "sg:city":"Valencia Alcantara",
    "sg:orig_category":"Polideportivos",
    "sg:phone":"+34 927 58 01 84",
    "sg:postcode":"10500",
    "sg:province":"C\u00e1ceres",
    "wof:name":"Ayuntamiento De Valencia De Alcantara",
    "wof:placetype":"venue"
},
  "geometry": {"coordinates":[-7.247616291,39.4118804932],"type":"Point"}
}