{
  "type": "Feature",
  "properties": {
    "addr:full":"San Pelayo, S/n Coristanco La Coru\u00f1a 15147",
    "addr:housenumber":"s / n",
    "addr:postcode":"15147",
    "addr:street":"La Corun\u0303A",
    "iso:country":"ES",
    "sg:address":"San Pelayo, S/n",
    "sg:city":"Coristanco",
    "sg:orig_category":"Ense\u00d1anza, Formaci\u00d3n Profesional: Aprendizaje",
    "sg:phone":"+34 981 73 30 63",
    "sg:postcode":"15147",
    "sg:province":"La Coru\u00f1a",
    "wof:name":"Parroquia De Santa Eulalia De Castro Y San Pelayo De Coristanco",
    "wof:placetype":"venue"
},
  "geometry": {"coordinates":[-8.7573442459,43.1895332336],"type":"Point"}
}