{
  "type": "Feature",
  "properties": {
    "addr:full":"Bda. San Cristobal, S/n Pinos-puente Granada 18240",
    "addr:postcode":"18240",
    "addr:street":"San Cristobal S / N",
    "iso:country":"ES",
    "sg:address":"Bda. San Cristobal, S/n",
    "sg:city":"Pinos-puente",
    "sg:orig_category":"Cerrajer\u00cda, Ferrallista",
    "sg:phone":"+34 958 45 08 01",
    "sg:postcode":"18240",
    "sg:province":"Granada",
    "wof:name":"Pemilja C.b.",
    "wof:placetype":"venue"
},
  "geometry": {"coordinates":[-3.7557189465,37.2533912659],"type":"Point"}
}