{
  "type": "Feature",
  "properties": {
    "iso:country":"ES",
    "sg:address":"Avda Alemania De, 13",
    "sg:city":"Aviles",
    "sg:orig_category":"Peluqueros: De Se\u00d1oras",
    "sg:phone":"+34 985 56 33 07",
    "sg:postcode":"33401",
    "sg:province":"Asturias",
    "wof:name":"Mieres Fernandez Maria Soledad",
    "wof:placetype":"venue"
},
  "geometry": {"coordinates":[-5.9258170128,43.5601615906],"type":"Point"}
}