{
  "type": "Feature",
  "properties": {
    "addr:full":"Carrer de Marina, 69 Barcelona Barcelona 08005",
    "addr:housenumber":"69",
    "addr:postcode":"08005",
    "addr:street":"Carrer De Marina",
    "iso:country":"ES",
    "sg:address":"Carrer de Marina, 69",
    "sg:city":"Barcelona",
    "sg:orig_category":"Pod\u00d3logos: Pedicuros",
    "sg:phone":"+34 933 00 82 22",
    "sg:postcode":"08005",
    "sg:province":"Barcelona",
    "wof:name":"Martinez Mujal Maria Victoria",
    "wof:placetype":"venue"
},
  "geometry": {"coordinates":[2.1900041103,41.3922920227],"type":"Point"}
}