{
  "type": "Feature",
  "properties": {
    "addr:full":"Carrer de Vila I Vila, 57 Barcelona Barcelona 08004",
    "addr:housenumber":"57",
    "addr:postcode":"08004",
    "addr:street":"Carrer De Vila I Vila",
    "iso:country":"ES",
    "sg:address":"Carrer de Vila I Vila, 57",
    "sg:city":"Barcelona",
    "sg:orig_category":"Peluquer\u00cdas, Peluquer\u00cda Mixta",
    "sg:phone":"+34 934 41 17 08",
    "sg:postcode":"08004",
    "sg:province":"Barcelona",
    "wof:name":"Aragon Garro Juan Jose",
    "wof:placetype":"venue"
},
  "geometry": {"coordinates":[2.170265913,41.3737602234],"type":"Point"}
}