{
  "type": "Feature",
  "properties": {
    "iso:country":"ES",
    "sg:address":"Avgd Blasco Iba\u00d1ez, 34",
    "sg:city":"Canals",
    "sg:orig_category":"Plomeros",
    "sg:phone":"+34 962 24 40 83",
    "sg:postcode":"46650",
    "sg:province":"Valencia",
    "wof:name":"Suministros Fontaneria J.o.s. S.l.",
    "wof:placetype":"venue"
},
  "geometry": {"coordinates":[-0.5873789787,38.9627761841],"type":"Point"}
}