{
  "type": "Feature",
  "properties": {
    "iso:country":"ES",
    "sg:address":"Calle de Principe De Vergara, 91",
    "sg:city":"Madrid",
    "sg:orig_category":"Quiropr\u00c1cticos",
    "sg:phone":"+34 915 62 41 29",
    "sg:postcode":"28006",
    "sg:province":"Madrid",
    "wof:name":"Sunyer Sendra Belen",
    "wof:placetype":"venue"
},
  "geometry": {"coordinates":[-3.679325819,40.4364814758],"type":"Point"}
}