{
  "type": "Feature",
  "properties": {
    "iso:country":"ES",
    "sg:address":"Carrer de Banyeres, 26",
    "sg:city":"Castalla",
    "sg:orig_category":"Centros Empresariales",
    "sg:phone":"+34 965 56 18 33",
    "sg:postcode":"03420",
    "sg:province":"Alicante",
    "wof:name":"Edelplast S.l.",
    "wof:placetype":"venue"
},
  "geometry": {"coordinates":[-0.6657389998,38.5993118286],"type":"Point"}
}