{
  "type": "Feature",
  "properties": {
    "addr:full":"Avda America (de), 18 Teruel Teruel 44002",
    "addr:housenumber":"18",
    "addr:postcode":"44002",
    "addr:street":"Avda America De",
    "iso:country":"ES",
    "sg:address":"Avda America (de), 18",
    "sg:city":"Teruel",
    "sg:orig_category":"Periodistas Profesionales",
    "sg:phone":"+34 978 62 14 96",
    "sg:postcode":"44002",
    "sg:province":"Teruel",
    "wof:name":"Garcia Rubio Jose Antonio",
    "wof:placetype":"venue"
},
  "geometry": {"coordinates":[-1.1098849773,40.330783844],"type":"Point"}
}