{
  "type": "Feature",
  "properties": {
    "addr:full":"Carrer de Amigo, 70 Barcelona Barcelona 08021",
    "addr:housenumber":"70",
    "addr:postcode":"08021",
    "addr:street":"Carrer De Amigo",
    "iso:country":"ES",
    "sg:address":"Carrer de Amigo, 70",
    "sg:city":"Barcelona",
    "sg:orig_category":"M\u00c9dicos: Medicina General Orientada A La Homeopat\u00cda",
    "sg:phone":"+34 934 14 04 91",
    "sg:postcode":"08021",
    "sg:province":"Barcelona",
    "wof:name":"Gutierrez Albala Montserrat",
    "wof:placetype":"venue"
},
  "geometry": {"coordinates":[2.1423780918,41.3970985413],"type":"Point"}
}