{
  "type": "Feature",
  "properties": {
    "addr:full":"Calle de Capitan Almeida, 9 Oviedo Asturias 33009",
    "addr:housenumber":"9",
    "addr:postcode":"33009",
    "addr:street":"Calle De Capitan Almeida",
    "iso:country":"ES",
    "sg:address":"Calle de Capitan Almeida, 9",
    "sg:city":"Oviedo",
    "sg:orig_category":"Bancos",
    "sg:phone":"+34 985 22 48 40",
    "sg:postcode":"33009",
    "sg:province":"Asturias",
    "wof:name":"Banc Sabadell S.a.",
    "wof:placetype":"venue"
},
  "geometry": {"coordinates":[-5.8410630226,43.3579444885],"type":"Point"}
}