{
  "type": "Feature",
  "properties": {
    "iso:country":"ES",
    "sg:address":"Calle de Batan, 61",
    "sg:city":"Pinos-puente",
    "sg:orig_category":"Reposter\u00cdas",
    "sg:phone":"+34 958 45 03 76",
    "sg:postcode":"18240",
    "sg:province":"Granada",
    "wof:name":"Panificadora Pinospan S.l.",
    "wof:placetype":"venue"
},
  "geometry": {"coordinates":[-3.7436964512,37.2480201721],"type":"Point"}
}