{
  "type": "Feature",
  "properties": {
    "iso:country":"ES",
    "sg:address":"Calle de Almeria (de), 16",
    "sg:city":"Humanes De Madrid",
    "sg:orig_category":"Cerrajer\u00cda, Ferrallista",
    "sg:phone":"+34 916 06 63 75",
    "sg:postcode":"28970",
    "sg:province":"Madrid",
    "wof:name":"Maria Brasero Valentin",
    "wof:placetype":"venue"
},
  "geometry": {"coordinates":[-3.8240880966,40.2759437561],"type":"Point"}
}