{
  "type": "Feature",
  "properties": {
    "iso:country":"ES",
    "sg:address":"Calle de Altamira, 2",
    "sg:city":"Almeria",
    "sg:orig_category":"Inmobiliaria (agencias)",
    "sg:phone":"+34 950 62 23 45",
    "sg:postcode":"04005",
    "sg:province":"Almer\u00eda",
    "sg:website":"www.almer-invest.es",
    "wof:name":"Almer-invest S.l.",
    "wof:placetype":"venue"
},
  "geometry": {"coordinates":[-2.4587845802,36.8376579285],"type":"Point"}
}