{
  "type": "Feature",
  "properties": {
    "iso:country":"ES",
    "sg:address":"Calle de Mu\u00d1oz Degrain, 12",
    "sg:city":"Oviedo",
    "sg:orig_category":"Zapatos (al Por Menor)",
    "sg:phone":"+34 985 25 62 99",
    "sg:postcode":"33007",
    "sg:province":"Asturias",
    "wof:name":"Velazquez Calzon Bernardino",
    "wof:placetype":"venue"
},
  "geometry": {"coordinates":[-5.84938097,43.3554153442],"type":"Point"}
}