{
  "type": "Feature",
  "properties": {
    "addr:full":"Calle de Tolosa Latour, 4 Cartagena Murcia 30201",
    "addr:housenumber":"4",
    "addr:postcode":"30201",
    "addr:street":"Calle De Tolosa Latour",
    "iso:country":"ES",
    "sg:address":"Calle de Tolosa Latour, 4",
    "sg:city":"Cartagena",
    "sg:orig_category":"M\u00c9dicos: Pediatr\u00cda. Enfermedades De Los Ni\u00d1os",
    "sg:phone":"+34 968 50 85 82",
    "sg:postcode":"30201",
    "sg:province":"Murcia",
    "wof:name":"Arance De Prada Jose Ignacio",
    "wof:placetype":"venue"
},
  "geometry": {"coordinates":[-0.9913911819,37.604473114],"type":"Point"}
}