{
  "type": "Feature",
  "properties": {
    "addr:full":"Calle de Jaen, 8 Bilbao Vizcaya 48012",
    "addr:housenumber":"8",
    "addr:postcode":"48012",
    "addr:street":"Calle De Jaen",
    "iso:country":"ES",
    "sg:address":"Calle de Jaen, 8",
    "sg:city":"Bilbao",
    "sg:orig_category":"Venta, Instalaci\u00d3n De Calefacci\u00d3n",
    "sg:phone":"+34 944 21 28 54",
    "sg:postcode":"48012",
    "sg:province":"Vizcaya",
    "wof:name":"Vaillant S. L.",
    "wof:placetype":"venue"
},
  "geometry": {"coordinates":[-2.9438350201,43.253578186],"type":"Point"}
}