{
  "type": "Feature",
  "properties": {
    "addr:full":"Avda Alicante, 75 Villena Alicante 03400",
    "addr:housenumber":"75",
    "addr:postcode":"03400",
    "addr:street":"Avda Alicante",
    "iso:country":"ES",
    "sg:address":"Avda Alicante, 75",
    "sg:city":"Villena",
    "sg:orig_category":"Caf\u00c9s, Bares, Cervecer\u00cdas",
    "sg:phone":"+34 965 81 80 19",
    "sg:postcode":"03400",
    "sg:province":"Alicante",
    "wof:name":"Iba\u00f1ez Y Molina Cb",
    "wof:placetype":"venue"
},
  "geometry": {"coordinates":[-0.8549200296,38.6298332214],"type":"Point"}
}