{
  "type": "Feature",
  "properties": {
    "addr:full":"Calle de Jose Lopez Rodriguez, S/n S. Fernando C\u00e1diz 11100",
    "addr:postcode":"11100",
    "addr:street":"Calle De Jose Lopez Rodriguez S / N S. Fernando Ca\u0301Diz",
    "iso:country":"ES",
    "sg:address":"Calle de Jose Lopez Rodriguez, S/n",
    "sg:city":"S. Fernando",
    "sg:orig_category":"Carnicer\u00cdas, Carnicer\u00cdas",
    "sg:phone":"+34 956 88 58 68",
    "sg:postcode":"11100",
    "sg:province":"C\u00e1diz",
    "wof:name":"Usero Galvez Jose Maria",
    "wof:placetype":"venue"
},
  "geometry": {"coordinates":[-6.198964119,36.4651908875],"type":"Point"}
}