{
  "type": "Feature",
  "properties": {
    "addr:full":"Calle de Gran Avenida, 1 Coria Rio Sevilla 41100",
    "addr:postcode":"41100",
    "addr:street":"Calle De Gran Avenida 1",
    "iso:country":"ES",
    "sg:address":"Calle de Gran Avenida, 1",
    "sg:city":"Coria Rio",
    "sg:orig_category":"Organismos De Investigaciones Cient\u00cdficas Y T\u00c9cnicas",
    "sg:phone":"+34 954 77 90 21",
    "sg:postcode":"41100",
    "sg:province":"Sevilla",
    "wof:name":"Cabeza Gomez Juan Antonio",
    "wof:placetype":"venue"
},
  "geometry": {"coordinates":[-6.0458350182,37.2945785522],"type":"Point"}
}