{
  "type": "Feature",
  "properties": {
    "iso:country":"ES",
    "sg:address":"Dos, 24",
    "sg:city":"Alcazar S. Juan",
    "sg:orig_category":"Distribuci\u00d3n De Petr\u00d3leo Y Derivados",
    "sg:phone":"+34 926 55 20 77",
    "sg:postcode":"13600",
    "sg:province":"Ciudad Real",
    "wof:name":"Comino Gasoleos S.l",
    "wof:placetype":"venue"
},
  "geometry": {"coordinates":[-3.2275290489,39.3936195374],"type":"Point"}
}