{
  "type": "Feature",
  "properties": {
    "iso:country":"ES",
    "sg:address":"Calle de Rua Mayor, 21",
    "sg:city":"Salamanca",
    "sg:orig_category":"V\u00cddeo (producci\u00d3n Y Realizaci\u00d3n)",
    "sg:phone":"+34 923 26 09 38",
    "sg:postcode":"37002",
    "sg:province":"Salamanca",
    "wof:name":"Dominguez De Prado Gaspar",
    "wof:placetype":"venue"
},
  "geometry": {"coordinates":[-5.6650600433,40.9631156921],"type":"Point"}
}