{
  "type": "Feature",
  "properties": {
    "iso:country":"ES",
    "sg:address":"Rua Cristo, 14",
    "sg:city":"Vigo",
    "sg:orig_category":"Peluqueros: De Se\u00d1oras",
    "sg:phone":"+34 986 27 31 86",
    "sg:postcode":"36205",
    "sg:province":"Pontevedra",
    "wof:name":"Perez De Los Angeles Lucia",
    "wof:placetype":"venue"
},
  "geometry": {"coordinates":[-8.7032842636,42.2302703857],"type":"Point"}
}