{
  "type": "Feature",
  "properties": {
    "addr:full":"Rua Eduardo Pondal, 5 Foz Lugo 27780",
    "addr:housenumber":"5",
    "addr:postcode":"27780",
    "addr:street":"Rua Eduardo Pondal",
    "iso:country":"ES",
    "sg:address":"Rua Eduardo Pondal, 5",
    "sg:city":"Foz",
    "sg:orig_category":"Panader\u00cdas, Panader\u00cdas",
    "sg:phone":"+34 982 14 17 08",
    "sg:postcode":"27780",
    "sg:province":"Lugo",
    "wof:name":"Gumiel Lafuente Jose Antonio",
    "wof:placetype":"venue"
},
  "geometry": {"coordinates":[-7.2555861473,43.5687599182],"type":"Point"}
}