{
  "type": "Feature",
  "properties": {
    "iso:country":"ES",
    "sg:address":"Calle de Sevilla, 30",
    "sg:city":"Hornachuelos",
    "sg:orig_category":"Promotores Constructores",
    "sg:phone":"+34 957 64 05 93",
    "sg:postcode":"14740",
    "sg:province":"C\u00f3rdoba",
    "wof:name":"Murillo Hidalgo Francisco",
    "wof:placetype":"venue"
},
  "geometry": {"coordinates":[-5.2468791008,37.8367805481],"type":"Point"}
}