{
  "type": "Feature",
  "properties": {
    "addr:full":"Calle de Reina Cristina, 1 Campo Criptana Ciudad Real 13610",
    "addr:housenumber":"1",
    "addr:postcode":"13610",
    "addr:street":"Calle De Reina Cristina;Criptana",
    "iso:country":"ES",
    "sg:address":"Calle de Reina Cristina, 1",
    "sg:city":"Campo Criptana",
    "sg:orig_category":"Cl\u00cdnicas Dentales",
    "sg:phone":"+34 926 56 33 48",
    "sg:postcode":"13610",
    "sg:province":"Ciudad Real",
    "wof:name":"Criptana Dental S.l.",
    "wof:placetype":"venue"
},
  "geometry": {"coordinates":[-3.125289917,39.4043388367],"type":"Point"}
}