{
  "type": "Feature",
  "properties": {
    "iso:country":"ES",
    "sg:address":"Avda Pedriza (de La), 36",
    "sg:city":"Manzanares El Real",
    "sg:orig_category":"Polideportivos",
    "sg:phone":"+34 918 53 00 00",
    "sg:postcode":"28410",
    "sg:province":"Madrid",
    "wof:name":"Ayuntamiento De Manzanares El Real",
    "wof:placetype":"venue"
},
  "geometry": {"coordinates":[-3.8692305088,40.7271499634],"type":"Point"}
}