{
  "type": "Feature",
  "properties": {
    "iso:country":"ES",
    "sg:address":"Calle de San Antonio, 32",
    "sg:city":"Pozoblanco",
    "sg:orig_category":"Electricidad: Instaladores",
    "sg:phone":"+34 957 77 09 19",
    "sg:postcode":"14400",
    "sg:province":"C\u00f3rdoba",
    "wof:name":"Navarro Cardador Antonio",
    "wof:placetype":"venue"
},
  "geometry": {"coordinates":[-4.8460488319,38.3806304932],"type":"Point"}
}