{
  "type": "Feature",
  "properties": {
    "iso:country":"ES",
    "sg:address":"Calle de Pio Del Rio Hortega, 4",
    "sg:city":"Valladolid",
    "sg:orig_category":"Frutas, Legumbres Frescas Y Tempranas (al Por Menor)",
    "sg:phone":"+34 983 37 01 00",
    "sg:postcode":"47014",
    "sg:province":"Valladolid",
    "wof:name":"Muelledes Martin Carlos",
    "wof:placetype":"venue"
},
  "geometry": {"coordinates":[-4.7393698692,41.6535682678],"type":"Point"}
}