{
  "type": "Feature",
  "properties": {
    "iso:country":"ES",
    "sg:address":"Calle de Corredera De San Marcos, 38",
    "sg:city":"Linares",
    "sg:orig_category":"Zapater\u00cdas",
    "sg:phone":"+34 953 69 22 07",
    "sg:postcode":"23700",
    "sg:province":"Ja\u00e9n",
    "wof:name":"Francisco Y Andres Mas Moreno C.b.",
    "wof:placetype":"venue"
},
  "geometry": {"coordinates":[-3.6342756748,38.0965805054],"type":"Point"}
}