{
  "type": "Feature",
  "properties": {
    "iso:country":"ES",
    "sg:address":"Carrer de Riera Alta, 20",
    "sg:city":"Barcelona",
    "sg:orig_category":"Fabricaci\u00d3n, Venta De Cuadros, Accesorios Para Enmarcar",
    "sg:phone":"+34 934 42 24 57",
    "sg:postcode":"08001",
    "sg:province":"Barcelona",
    "wof:name":"Sultana  Nasrin",
    "wof:placetype":"venue"
},
  "geometry": {"coordinates":[2.1659419537,41.3805885315],"type":"Point"}
}