{
  "type": "Feature",
  "properties": {
    "iso:country":"ES",
    "sg:address":"Iturrama, 70",
    "sg:city":"Iru\u00f1a",
    "sg:orig_category":"Inform\u00c1tica: Soportes De Informaci\u00d3n, Suministros & Accesorios",
    "sg:phone":"+34 948 17 02 76",
    "sg:postcode":"31008",
    "sg:province":"Navarra",
    "wof:name":"Jump Ordenadores S.l.",
    "wof:placetype":"venue"
},
  "geometry": {"coordinates":[-1.658446908,42.8077888489],"type":"Point"}
}