{
  "type": "Feature",
  "properties": {
    "iso:country":"ES",
    "sg:address":"Cortijo El Huerto, S/n",
    "sg:city":"Antequera",
    "sg:orig_category":"Frutas Y Legumbres Frescas (al Por Mayor)",
    "sg:phone":"+34 952 11 14 63",
    "sg:postcode":"29200",
    "sg:province":"M\u00e1laga",
    "wof:name":"Canovas Y Mu\u00f1oz S.l.",
    "wof:placetype":"venue"
},
  "geometry": {"coordinates":[-4.5636138916,37.0203018188],"type":"Point"}
}