{
  "type": "Feature",
  "properties": {
    "addr:full":"Carrer de Eduard Blasco I Ejarque, 7 Prat Llobregat Barcelona 08820",
    "addr:housenumber":"7",
    "addr:postcode":"08820",
    "addr:street":"Carrer De Eduard Blasco I Ejarque;Llobregat",
    "iso:country":"ES",
    "sg:address":"Carrer de Eduard Blasco I Ejarque, 7",
    "sg:city":"Prat Llobregat",
    "sg:orig_category":"Guarder\u00cdas",
    "sg:phone":"+34 933 70 03 54",
    "sg:postcode":"08820",
    "sg:province":"Barcelona",
    "wof:name":"Guarderia El Cargolet S.c.p.",
    "wof:placetype":"venue"
},
  "geometry": {"coordinates":[2.09770298,41.323513031],"type":"Point"}
}