{
  "type": "Feature",
  "properties": {
    "iso:country":"ES",
    "sg:address":"Calle de Dos De Mayo, 34",
    "sg:city":"Sevilla",
    "sg:orig_category":"Arquitectos",
    "sg:phone":"+34 954 22 74 08",
    "sg:postcode":"41001",
    "sg:province":"Sevilla",
    "wof:name":"Arquiestudio Sevilla S.l.",
    "wof:placetype":"venue"
},
  "geometry": {"coordinates":[-5.9967803955,37.3844718933],"type":"Point"}
}