{
  "type": "Feature",
  "properties": {
    "addr:full":"Ctra. Malaga, 91 Venta Gutierrez-caba\u00f1uelas Almer\u00eda 04738",
    "addr:housenumber":"91",
    "addr:postcode":"04738",
    "addr:street":"Ctra. Malaga;Almeri\u0301A",
    "iso:country":"ES",
    "sg:address":"Ctra. Malaga, 91",
    "sg:city":"Venta Gutierrez-caba\u00f1uelas",
    "sg:orig_category":"Bisuter\u00cda, Joyer\u00cda, Relojer\u00cda (al Por Menor)",
    "sg:phone":"+34 950 55 44 09",
    "sg:postcode":"04738",
    "sg:province":"Almer\u00eda",
    "wof:name":"Zapata Gutierrez Jose",
    "wof:placetype":"venue"
},
  "geometry": {"coordinates":[-2.4679217339,36.8401641846],"type":"Point"}
}