{
  "type": "Feature",
  "properties": {
    "iso:country":"ES",
    "sg:address":"Carrer de Lleialtat, 13",
    "sg:city":"Esplugues Llobregat",
    "sg:orig_category":"Empresas De Operaciones Portuarias Y Elevaci\u00d3n De Mercanc\u00cdas",
    "sg:phone":"+34 933 71 23 41",
    "sg:postcode":"08950",
    "sg:province":"Barcelona",
    "wof:name":"H2 Sol Enginyeria Mediambiental S.l",
    "wof:placetype":"venue"
},
  "geometry": {"coordinates":[2.0924789906,41.3760490417],"type":"Point"}
}