{
  "type": "Feature",
  "properties": {
    "addr:full":"Calle de Sor Valentina Miron, 1 Plasencia C\u00e1ceres 10600",
    "addr:housenumber":"1",
    "addr:postcode":"10600",
    "addr:street":"Calle De Sor Valentina Miron;Ca\u0301Ceres",
    "iso:country":"ES",
    "sg:address":"Calle de Sor Valentina Miron, 1",
    "sg:city":"Plasencia",
    "sg:orig_category":"Panader\u00cdas, Panader\u00cdas",
    "sg:phone":"+34 927 41 20 55",
    "sg:postcode":"10600",
    "sg:province":"C\u00e1ceres",
    "wof:name":"Mas Sanchez-collado Maria Del Sagrario",
    "wof:placetype":"venue"
},
  "geometry": {"coordinates":[-6.092361927,40.0313873291],"type":"Point"}
}