{
  "type": "Feature",
  "properties": {
    "addr:full":"Calle de Juan Sebastian Elcano, 59 Albacete Albacete 02005",
    "addr:housenumber":"59",
    "addr:postcode":"02005",
    "addr:street":"Calle De Juan Sebastian Elcano",
    "iso:country":"ES",
    "sg:address":"Calle de Juan Sebastian Elcano, 59",
    "sg:city":"Albacete",
    "sg:orig_category":"Mec\u00c1nico Del Autom\u00d3vil",
    "sg:phone":"+34 967 22 06 39",
    "sg:postcode":"02005",
    "sg:province":"Albacete",
    "wof:name":"Hijos De Diego Martinez Nieto S.l.",
    "wof:placetype":"venue"
},
  "geometry": {"coordinates":[-1.8652590513,38.9982032776],"type":"Point"}
}