{
  "type": "Feature",
  "properties": {
    "addr:full":"Calle de Aguilon, 17 Madrid Madrid 28045",
    "addr:housenumber":"17",
    "addr:postcode":"madrid;28045",
    "addr:street":"Calle De Aguilon",
    "iso:country":"ES",
    "sg:address":"Calle de Aguilon, 17",
    "sg:city":"Madrid",
    "sg:orig_category":"M\u00dasicos Int\u00c9rpretes",
    "sg:phone":"+34 914 73 87 52",
    "sg:postcode":"28045",
    "sg:province":"Madrid",
    "wof:name":"Lopez Perez Jose Rafael",
    "wof:placetype":"venue"
},
  "geometry": {"coordinates":[-3.700773716,40.3971977234],"type":"Point"}
}