{
  "type": "Feature",
  "properties": {
    "iso:country":"ES",
    "sg:address":"C/ Vara De Rey, De, S/n",
    "sg:city":"S. Antoni Portmany",
    "sg:orig_category":"Cajas De Ahorro",
    "sg:phone":"+34 971 80 30 60",
    "sg:postcode":"07820",
    "sg:province":"Islas Baleares",
    "sg:website":"www.bancaja.es",
    "wof:name":"Caja De Ahorros De Valencia Castellon Y Alicante",
    "wof:placetype":"venue"
},
  "geometry": {"coordinates":[1.5188339949,39.1094055176],"type":"Point"}
}