{
  "type": "Feature",
  "properties": {
    "addr:full":"Avda Alicante, 15 Javea Alicante 03730",
    "addr:housenumber":"15",
    "addr:postcode":"03730",
    "addr:street":"Avda Alicante",
    "iso:country":"ES",
    "sg:address":"Avda Alicante, 15",
    "sg:city":"Javea",
    "sg:orig_category":"Centros De Coordinaci\u00d3n",
    "sg:phone":"+34 965 79 03 54",
    "sg:postcode":"03730",
    "sg:province":"Alicante",
    "wof:name":"Font Gestors Administratius",
    "wof:placetype":"venue"
},
  "geometry": {"coordinates":[0.1649619937,38.7906494141],"type":"Point"}
}