{
  "type": "Feature",
  "properties": {
    "iso:country":"ES",
    "sg:address":"Calle de Gumersindo Azcarate, 1",
    "sg:city":"Linares",
    "sg:orig_category":"Procuradores",
    "sg:phone":"+34 953 65 02 65",
    "sg:postcode":"23700",
    "sg:province":"Ja\u00e9n",
    "wof:name":"Torres Hidalgo Julia",
    "wof:placetype":"venue"
},
  "geometry": {"coordinates":[-3.6344358921,38.0967292786],"type":"Point"}
}