{
  "type": "Feature",
  "properties": {
    "addr:full":"Avda Estacion (da), 1 Barco Ourense 32300",
    "addr:housenumber":"1",
    "addr:postcode":"32300",
    "addr:street":"Avda Estacion Da",
    "iso:country":"ES",
    "sg:address":"Avda Estacion (da), 1",
    "sg:city":"Barco",
    "sg:orig_category":"Peluquer\u00cdas, Peluquer\u00cda Mixta",
    "sg:phone":"+34 988 32 06 51",
    "sg:postcode":"32300",
    "sg:province":"Ourense",
    "wof:name":"Peluquerias Sagra S.l.",
    "wof:placetype":"venue"
},
  "geometry": {"coordinates":[-6.9858579636,42.4154129028],"type":"Point"}
}