{
  "type": "Feature",
  "properties": {
    "addr:full":"Crt Avila-toledo, Km. 0055,0 Escalona Toledo 45910",
    "addr:postcode":"45910",
    "addr:street":"Avila-Toledo Km. 0055,0",
    "iso:country":"ES",
    "sg:address":"Crt Avila-toledo, Km. 0055,0",
    "sg:city":"Escalona",
    "sg:orig_category":"Doctores En Medicina",
    "sg:phone":"+34 925 78 09 46",
    "sg:postcode":"45910",
    "sg:province":"Toledo",
    "wof:name":"Rodriguez Rodriguez Vicente",
    "wof:placetype":"venue"
},
  "geometry": {"coordinates":[-4.4054641724,40.1705665588],"type":"Point"}
}