{
  "type": "Feature",
  "properties": {
    "iso:country":"ES",
    "sg:address":"Calle de Boteros, 8",
    "sg:city":"Pinto",
    "sg:orig_category":"Institutos De Belleza",
    "sg:phone":"+34 916 92 56 11",
    "sg:postcode":"28320",
    "sg:province":"Madrid",
    "sg:website":"www.vitalterapias.com",
    "wof:name":"Estetica Maroc S.l.",
    "wof:placetype":"venue"
},
  "geometry": {"coordinates":[-3.7001867294,40.2422599792],"type":"Point"}
}