{
  "type": "Feature",
  "properties": {
    "addr:full":"Calle de Iparragirre, 4 Arizgoiti Vizcaya 48970",
    "addr:housenumber":"4",
    "addr:postcode":"48970",
    "addr:street":"Calle De Iparragirre",
    "iso:country":"ES",
    "sg:address":"Calle de Iparragirre, 4",
    "sg:city":"Arizgoiti",
    "sg:orig_category":"Congelados: Productos Alimentarios (al Por Menor)",
    "sg:phone":"+34 944 49 93 08",
    "sg:postcode":"48970",
    "sg:province":"Vizcaya",
    "wof:name":"Ace\u00f1a Gayubo Jose Miguel",
    "wof:placetype":"venue"
},
  "geometry": {"coordinates":[-2.8932373524,43.2371330261],"type":"Point"}
}