{
  "type": "Feature",
  "properties": {
    "addr:full":"Avda America (de), 3 Cordoba C\u00f3rdoba 14008",
    "addr:housenumber":"3",
    "addr:postcode":"14008",
    "addr:street":"Avda America De;Co\u0301Rdoba",
    "iso:country":"ES",
    "sg:address":"Avda America (de), 3",
    "sg:city":"Cordoba",
    "sg:orig_category":"M\u00c9dicos: Naturistas",
    "sg:phone":"+34 957 48 60 00",
    "sg:postcode":"14008",
    "sg:province":"C\u00f3rdoba",
    "wof:name":"Gonzalez Peran Concepcion",
    "wof:placetype":"venue"
},
  "geometry": {"coordinates":[-4.7817072868,37.8910827637],"type":"Point"}
}