{
  "type": "Feature",
  "properties": {
    "iso:country":"ES",
    "sg:address":"Calle de Garcia De Paredes, 17",
    "sg:city":"Badajoz",
    "sg:orig_category":"Ense\u00d1anza, Formaci\u00d3n Profesional: Aprendizaje",
    "sg:phone":"+34 924 27 07 16",
    "sg:postcode":"06006",
    "sg:province":"Badajoz",
    "wof:name":"Hermanas De La Providencia",
    "wof:placetype":"venue"
},
  "geometry": {"coordinates":[-6.9819779396,38.8862495422],"type":"Point"}
}