{
  "type": "Feature",
  "properties": {
    "addr:full":"Pg Font Pudenta, 102 Montcada Centre Barcelona 08110",
    "addr:housenumber":"102",
    "addr:postcode":"08110",
    "addr:street":"Pg;Pudenta",
    "iso:country":"ES",
    "sg:address":"Pg Font Pudenta, 102",
    "sg:city":"Montcada Centre",
    "sg:orig_category":"Restaurantes",
    "sg:phone":"+34 935 64 00 34",
    "sg:postcode":"08110",
    "sg:province":"Barcelona",
    "wof:name":"Carrasco Bertran Lluis",
    "wof:placetype":"venue"
},
  "geometry": {"coordinates":[2.1777799129,41.4834709167],"type":"Point"}
}