{
  "type": "Feature",
  "properties": {
    "iso:country":"ES",
    "sg:address":"Plaz Diputacion, 5",
    "sg:city":"Morales Vino",
    "sg:orig_category":"Pescader\u00cdas (al Por Menor)",
    "sg:phone":"+34 980 57 43 29",
    "sg:postcode":"49190",
    "sg:province":"Zamora",
    "wof:name":"Hernandez Gonzalez Julian",
    "wof:placetype":"venue"
},
  "geometry": {"coordinates":[-5.7349591255,41.445602417],"type":"Point"}
}