{
  "type": "Feature",
  "properties": {
    "addr:full":"Calle de Canovas Del Castillo, 10 Santa Eulalia Murcia 30003",
    "addr:housenumber":"10",
    "addr:postcode":"30003",
    "addr:street":"Calle De Canovas Del Castillo",
    "iso:country":"ES",
    "sg:address":"Calle de Canovas Del Castillo, 10",
    "sg:city":"Santa Eulalia",
    "sg:orig_category":"Centro De Estudios",
    "sg:phone":"+34 968 21 98 49",
    "sg:postcode":"30003",
    "sg:province":"Murcia",
    "wof:name":"Cachafeiro Vi\u00f1ambres Angel",
    "wof:placetype":"venue"
},
  "geometry": {"coordinates":[-1.1258397102,37.9841690063],"type":"Point"}
}