{
  "type": "Feature",
  "properties": {
    "iso:country":"ES",
    "sg:address":"Carrer de Guatlla, 1",
    "sg:city":"Rubi",
    "sg:orig_category":"Promotores Constructores",
    "sg:phone":"+34 935 87 50 61",
    "sg:postcode":"08191",
    "sg:province":"Barcelona",
    "wof:name":"Construcciones Ruiamo",
    "wof:placetype":"venue"
},
  "geometry": {"coordinates":[2.0190908909,41.4836502075],"type":"Point"}
}