{
  "type": "Feature",
  "properties": {
    "addr:full":"Calle de Santa Maria, 26 Gijon Asturias 33208",
    "addr:housenumber":"26",
    "addr:postcode":"33208",
    "addr:street":"Calle De Santa Maria",
    "iso:country":"ES",
    "sg:address":"Calle de Santa Maria, 26",
    "sg:city":"Gijon",
    "sg:orig_category":"Laboratorios Y Trabajos De Fotograf\u00cda, V\u00cddeo Y Cine",
    "sg:phone":"+34 985 38 54 58",
    "sg:postcode":"33208",
    "sg:province":"Asturias",
    "wof:name":"Norfilm S.l.",
    "wof:placetype":"venue"
},
  "geometry": {"coordinates":[-5.6651029587,43.5324172974],"type":"Point"}
}