{
  "type": "Feature",
  "properties": {
    "addr:full":"Avgd Doctor Fleming, 47 Lleida Lleida 25006",
    "addr:housenumber":"47",
    "addr:postcode":"25006",
    "addr:street":"Doctor Fleming",
    "iso:country":"ES",
    "sg:address":"Avgd Doctor Fleming, 47",
    "sg:city":"Lleida",
    "sg:orig_category":"Venta, Colocaci\u00d3n De Autoradios",
    "sg:phone":"+34 973 26 74 47",
    "sg:postcode":"25006",
    "sg:province":"Lleida",
    "wof:name":"Posino Flix Ramon",
    "wof:placetype":"venue"
},
  "geometry": {"coordinates":[0.6130650043,41.6206283569],"type":"Point"}
}