{
  "type": "Feature",
  "properties": {
    "iso:country":"ES",
    "sg:address":"Carrer de Doctor Codina, 35",
    "sg:city":"Sabadell",
    "sg:orig_category":"Fabricaci\u00d3n, Venta, Instalaci\u00d3n De R\u00d3tulos, De R\u00d3tulos Luminosos",
    "sg:phone":"+34 937 16 20 39",
    "sg:postcode":"08208",
    "sg:province":"Barcelona",
    "wof:name":"Lopez Marques Moises",
    "wof:placetype":"venue"
},
  "geometry": {"coordinates":[2.0985050201,41.5601959229],"type":"Point"}
}