{
  "type": "Feature",
  "properties": {
    "addr:full":"Calle de Ricardo Buesa, 8 Vitoria-gasteiz \u00c1lava 01008",
    "addr:housenumber":"8",
    "addr:postcode":"01008",
    "addr:street":"Calle De Ricardo Buesa",
    "iso:country":"ES",
    "sg:address":"Calle de Ricardo Buesa, 8",
    "sg:city":"Vitoria-gasteiz",
    "sg:orig_category":"Caf\u00c9s, Bares, Cervecer\u00cdas",
    "sg:phone":"+34 945 24 88 87",
    "sg:postcode":"01008",
    "sg:province":"\u00c1lava",
    "wof:name":"Union 84 S. A.",
    "wof:placetype":"venue"
},
  "geometry": {"coordinates":[-2.6798789501,42.8484649658],"type":"Point"}
}