{
  "type": "Feature",
  "properties": {
    "iso:country":"ES",
    "sg:address":"Carrer de Europa, 3",
    "sg:city":"Terrassa",
    "sg:orig_category":"Radiocomunicaciones, Telefon\u00cda M\u00d3vil, Radiomensajer\u00cda: Servicios, Comercializaci\u00d3n",
    "sg:phone":"+34 937 85 10 07",
    "sg:postcode":"08228",
    "sg:province":"Barcelona",
    "wof:name":"Kahil  Abderrazzak",
    "wof:placetype":"venue"
},
  "geometry": {"coordinates":[2.0432488918,41.5393714905],"type":"Point"}
}