{
  "type": "Feature",
  "properties": {
    "addr:full":"Calle de Almendros (los), 1 Segovia Segovia 40002",
    "addr:housenumber":"1",
    "addr:postcode":"40002",
    "addr:street":"Calle De Almendros Los",
    "iso:country":"ES",
    "sg:address":"Calle de Almendros (los), 1",
    "sg:city":"Segovia",
    "sg:orig_category":"Calzados Ortop\u00c9dicos",
    "sg:phone":"+34 921 46 17 77",
    "sg:postcode":"40002",
    "sg:province":"Segovia",
    "wof:name":"Moreno Isabel Juan Antonio",
    "wof:placetype":"venue"
},
  "geometry": {"coordinates":[-4.1192789078,40.9424476624],"type":"Point"}
}