{
  "type": "Feature",
  "properties": {
    "addr:full":"Avda Mediterraneo, S/n Bahia De Javea Alicante 03730",
    "addr:postcode":"03730",
    "addr:street":"Avda Mediterraneo S / N Bahia De Javea Alicante",
    "iso:country":"ES",
    "sg:address":"Avda Mediterraneo, S/n",
    "sg:city":"Bahia De Javea",
    "sg:orig_category":"Inversiones",
    "sg:phone":"+34 965 79 54 83",
    "sg:postcode":"03730",
    "sg:province":"Alicante",
    "wof:name":"Inversiones S. A.",
    "wof:placetype":"venue"
},
  "geometry": {"coordinates":[0.1668650061,38.7890739441],"type":"Point"}
}