{
  "type": "Feature",
  "properties": {
    "addr:full":"Pase Maritimo, 7 Coru\u00d1a La Coru\u00f1a 15002",
    "addr:housenumber":"7",
    "addr:postcode":"15002",
    "addr:street":"Maritimo;La Corun\u0303A",
    "iso:country":"ES",
    "sg:address":"Pase Maritimo, 7",
    "sg:city":"Coru\u00d1a",
    "sg:orig_category":"Agencias Y Agentes Comerciales, Representantes",
    "sg:phone":"+34 981 20 51 09",
    "sg:postcode":"15002",
    "sg:province":"La Coru\u00f1a",
    "wof:name":"Rivas Pradanos Santiago",
    "wof:placetype":"venue"
},
  "geometry": {"coordinates":[-8.5979213715,42.8414230347],"type":"Point"}
}