{
  "type": "Feature",
  "properties": {
    "iso:country":"ES",
    "sg:address":"Calle de Matahacas, 5",
    "sg:city":"Sevilla",
    "sg:orig_category":"Empresas De Portes Y Mensajer\u00cda",
    "sg:phone":"+34 954 21 28 58",
    "sg:postcode":"41003",
    "sg:province":"Sevilla",
    "wof:name":"Martin Ruiz Dolores",
    "wof:placetype":"venue"
},
  "geometry": {"coordinates":[-5.9862589836,37.3947792053],"type":"Point"}
}