{
  "type": "Feature",
  "properties": {
    "iso:country":"ES",
    "sg:address":"Calle de Iberia, 50",
    "sg:city":"Aguilas",
    "sg:orig_category":"Restaurantes",
    "sg:phone":"+34 968 44 88 61",
    "sg:postcode":"30880",
    "sg:province":"Murcia",
    "wof:name":"Jordan Cotes Pedro",
    "wof:placetype":"venue"
},
  "geometry": {"coordinates":[-1.5948879719,37.4008560181],"type":"Point"}
}