{
  "type": "Feature",
  "properties": {
    "iso:country":"ES",
    "sg:address":"Carrer de Sardenya, 68",
    "sg:city":"Barcelona",
    "sg:orig_category":"Geolog\u00cda Y Geof\u00cdsica",
    "sg:phone":"+34 933 00 47 00",
    "sg:postcode":"08005",
    "sg:province":"Barcelona",
    "wof:name":"Tanner Intermediaria S.l.",
    "wof:placetype":"venue"
},
  "geometry": {"coordinates":[2.1890859604,41.3916664124],"type":"Point"}
}