{
  "type": "Feature",
  "properties": {
    "iso:country":"ES",
    "sg:address":"C/ Jose Belso Casta\u00d1o, 7",
    "sg:city":"Elche",
    "sg:orig_category":"Ciencias Ocultas",
    "sg:phone":"+34 965 46 16 02",
    "sg:postcode":"03206",
    "sg:province":"Alicante",
    "wof:name":"Ruiz Paredes Josefa",
    "wof:placetype":"venue"
},
  "geometry": {"coordinates":[-0.7036269903,38.2711029053],"type":"Point"}
}