{
  "type": "Feature",
  "properties": {
    "addr:full":"Rbla Pulido, 35 Santa Cruz De Tenerife Santa Cruz De Tenerife 38004",
    "addr:housenumber":"35",
    "addr:postcode":"38004",
    "addr:street":"Rbla Pulido",
    "iso:country":"ES",
    "sg:address":"Rbla Pulido, 35",
    "sg:city":"Santa Cruz De Tenerife",
    "sg:orig_category":"Ropa Para Se\u00d1oras (al Por Menor)",
    "sg:phone":"+34 922 53 31 02",
    "sg:postcode":"38004",
    "sg:province":"Santa Cruz De Tenerife",
    "wof:name":"Rodriguez Ponce Alipio",
    "wof:placetype":"venue"
},
  "geometry": {"coordinates":[-16.2582950592,28.4674606323],"type":"Point"}
}