{
  "type": "Feature",
  "properties": {
    "addr:full":"Calle de Abadia (la), 14 Iglesia Cantabria 39527",
    "addr:housenumber":"14",
    "addr:postcode":"39527",
    "addr:street":"Calle De Abadia La",
    "iso:country":"ES",
    "sg:address":"Calle de Abadia (la), 14",
    "sg:city":"Iglesia",
    "sg:orig_category":"Centros Empresariales",
    "sg:phone":"+34 942 72 25 57",
    "sg:postcode":"39527",
    "sg:province":"Cantabria",
    "wof:name":"Rozas Incera Vicente",
    "wof:placetype":"venue"
},
  "geometry": {"coordinates":[-3.9878427982,43.1828384399],"type":"Point"}
}