{
  "type": "Feature",
  "properties": {
    "iso:country":"ES",
    "sg:address":"Avda Manoteras, 30",
    "sg:city":"Madrid",
    "sg:orig_category":"Promotores Constructores",
    "sg:phone":"+34 917 68 00 71",
    "sg:postcode":"28050",
    "sg:province":"Madrid",
    "wof:name":"Sareton Construcciones S.l.",
    "wof:placetype":"venue"
},
  "geometry": {"coordinates":[-3.6662039757,40.4879798889],"type":"Point"}
}