{
  "type": "Feature",
  "properties": {
    "addr:full":"Calle de Salvador (el), S/n Roda Albacete 02630",
    "addr:postcode":"02630",
    "addr:street":"Calle De Salvador El S / N Roda",
    "iso:country":"ES",
    "sg:address":"Calle de Salvador (el), S/n",
    "sg:city":"Roda",
    "sg:orig_category":"Delegados, Agentes De Tr\u00c1nsito, Auxiliares De Transporte Internacional",
    "sg:phone":"+34 967 54 80 17",
    "sg:postcode":"02630",
    "sg:province":"Albacete",
    "wof:name":"Transportes Joaquin Cortijo S.l.",
    "wof:placetype":"venue"
},
  "geometry": {"coordinates":[-2.1600987911,39.2042655945],"type":"Point"}
}