{
  "type": "Feature",
  "properties": {
    "addr:full":"Carrer de Santa Anna, 24 Barcelona Barcelona 08002",
    "addr:housenumber":"24",
    "addr:postcode":"08002",
    "addr:street":"Carrer De Santa Anna",
    "iso:country":"ES",
    "sg:address":"Carrer de Santa Anna, 24",
    "sg:city":"Barcelona",
    "sg:orig_category":"Hoteles",
    "sg:phone":"+34 933 01 91 50",
    "sg:postcode":"08002",
    "sg:province":"Barcelona",
    "wof:name":"Intertur S.l.",
    "wof:placetype":"venue"
},
  "geometry": {"coordinates":[2.1717710495,41.3854675293],"type":"Point"}
}