{
  "type": "Feature",
  "properties": {
    "addr:full":"Calle de Marques De Hinojares (del), S/n Mejorada Campo Madrid 28840",
    "addr:housenumber":"/ n",
    "addr:postcode":"28840",
    "addr:street":"Calle De Marques De Hinojares Del S",
    "iso:country":"ES",
    "sg:address":"Calle de Marques De Hinojares (del), S/n",
    "sg:city":"Mejorada Campo",
    "sg:orig_category":"Prensas Industriales",
    "sg:phone":"+34 916 68 22 64",
    "sg:postcode":"28840",
    "sg:province":"Madrid",
    "wof:name":"Soto Galan Francisco",
    "wof:placetype":"venue"
},
  "geometry": {"coordinates":[-3.4876258373,40.3984298706],"type":"Point"}
}