{
  "type": "Feature",
  "properties": {
    "iso:country":"ES",
    "sg:address":"Carrer de Calabria, 31",
    "sg:city":"Barcelona",
    "sg:orig_category":"Centros Y Asociaciones De Gesti\u00d3n Homologados",
    "sg:phone":"+34 933 25 44 48",
    "sg:postcode":"08015",
    "sg:province":"Barcelona",
    "wof:name":"Chumilla Cabeza Francisco",
    "wof:placetype":"venue"
},
  "geometry": {"coordinates":[2.1589779854,41.3765220642],"type":"Point"}
}