{
  "type": "Feature",
  "properties": {
    "iso:country":"ES",
    "sg:address":"Calle de Mayor, 9",
    "sg:city":"Cartagena",
    "sg:orig_category":"Ropa Para Se\u00d1oras (al Por Menor)",
    "sg:phone":"+34 968 12 01 49",
    "sg:postcode":"30201",
    "sg:province":"Murcia",
    "sg:website":"www.torero.com",
    "wof:name":"Confecciones Liwe S.a.e.",
    "wof:placetype":"venue"
},
  "geometry": {"coordinates":[-0.9156429768,37.600566864],"type":"Point"}
}