{
  "type": "Feature",
  "properties": {
    "addr:full":"Avda Virgen De Gracia, 12 Fresneda Teruel 44596",
    "addr:housenumber":"12",
    "addr:postcode":"44596",
    "addr:street":"Avda Virgen De Gracia",
    "iso:country":"ES",
    "sg:address":"Avda Virgen De Gracia, 12",
    "sg:city":"Fresneda",
    "sg:orig_category":"Farmacias",
    "sg:phone":"+34 978 85 41 80",
    "sg:postcode":"44596",
    "sg:province":"Teruel",
    "wof:name":"Merchante Garcia Constancio",
    "wof:placetype":"venue"
},
  "geometry": {"coordinates":[0.0760819986,40.9298744202],"type":"Point"}
}