{
  "type": "Feature",
  "properties": {
    "iso:country":"ES",
    "sg:address":"Carrer de Quinze, 7",
    "sg:city":"Bonavista",
    "sg:orig_category":"Promotores Constructores",
    "sg:phone":"+34 977 54 06 27",
    "sg:postcode":"43100",
    "sg:province":"Tarragona",
    "sg:website":"www.construccionesubeda.com",
    "wof:name":"Construcciones Y Reformas Hermanos Ubeda",
    "wof:placetype":"venue"
},
  "geometry": {"coordinates":[1.1932469606,41.1209220886],"type":"Point"}
}