{
  "type": "Feature",
  "properties": {
    "iso:country":"ES",
    "sg:address":"Calle de Villavaliente, S/n",
    "sg:city":"Madrid",
    "sg:orig_category":"Librer\u00cdas",
    "sg:phone":"+34 914 70 01 15",
    "sg:postcode":"28011",
    "sg:province":"Madrid",
    "wof:name":"Blasco Rodriguez Luis",
    "wof:placetype":"venue"
},
  "geometry": {"coordinates":[-3.749532938,40.4075965881],"type":"Point"}
}