{
  "type": "Feature",
  "properties": {
    "addr:full":"Calle de Ingenios, 1 Torrijos Toledo 45500",
    "addr:housenumber":"1",
    "addr:postcode":"45500",
    "addr:street":"Calle De Ingenios",
    "iso:country":"ES",
    "sg:address":"Calle de Ingenios, 1",
    "sg:city":"Torrijos",
    "sg:orig_category":"Guarder\u00cdas",
    "sg:phone":"+34 925 76 15 67",
    "sg:postcode":"45500",
    "sg:province":"Toledo",
    "wof:name":"Guarderia Cardenas S.c.p.",
    "wof:placetype":"venue"
},
  "geometry": {"coordinates":[-4.2850580215,39.9820747375],"type":"Point"}
}