{
  "type": "Feature",
  "properties": {
    "addr:full":"Calle de Severo Ochoa, S/n Poligono Industrial Los Villares Salamanca 37184",
    "addr:housenumber":"s / n",
    "addr:postcode":"37184",
    "addr:street":"Calle De Severo Ochoa;Industrial",
    "iso:country":"ES",
    "sg:address":"Calle de Severo Ochoa, S/n",
    "sg:city":"Poligono Industrial Los Villares",
    "sg:orig_category":"Molduras, Junquillos, Listones Y Molduras Perforadas",
    "sg:phone":"+34 923 22 25 70",
    "sg:postcode":"37184",
    "sg:province":"Salamanca",
    "wof:name":"Rodriguez Valiente Fructuoso",
    "wof:placetype":"venue"
},
  "geometry": {"coordinates":[-5.6367840767,40.9904441833],"type":"Point"}
}