{
  "type": "Feature",
  "properties": {
    "addr:full":"Nta Sra Mercedes, 26 Moral Calatrava Ciudad Real 13350",
    "addr:housenumber":"26",
    "addr:postcode":"13350",
    "addr:street":"Sra;Moral Calatrava",
    "iso:country":"ES",
    "sg:address":"Nta Sra Mercedes, 26",
    "sg:city":"Moral Calatrava",
    "sg:orig_category":"Producci\u00d3n, Venta De Productos De Agricultura Biol\u00d3gica",
    "sg:phone":"+34 926 33 02 21",
    "sg:postcode":"13350",
    "sg:province":"Ciudad Real",
    "wof:name":"Perez Fernandez Roque Antonio",
    "wof:placetype":"venue"
},
  "geometry": {"coordinates":[-3.5793139935,38.8292617798],"type":"Point"}
}