{
  "type": "Feature",
  "properties": {
    "iso:country":"ES",
    "sg:address":"Calle de Luchana, 4",
    "sg:city":"Alzira",
    "sg:orig_category":"Alimentaci\u00d3n General (al Por Menor)",
    "sg:phone":"+34 962 40 41 77",
    "sg:postcode":"46600",
    "sg:province":"Valencia",
    "wof:name":"Martinez Belda Presentacion Carmen",
    "wof:placetype":"venue"
},
  "geometry": {"coordinates":[-0.427850008,39.1584358215],"type":"Point"}
}