{
  "type": "Feature",
  "properties": {
    "addr:full":"Calle de Fontanares, 36 Valencia Valencia 46007",
    "addr:housenumber":"36",
    "addr:postcode":"46007",
    "addr:street":"Calle De Fontanares",
    "iso:country":"ES",
    "sg:address":"Calle de Fontanares, 36",
    "sg:city":"Valencia",
    "sg:orig_category":"Torrefactado De Caf\u00c9",
    "sg:phone":"+34 963 78 06 11",
    "sg:postcode":"46007",
    "sg:province":"Valencia",
    "wof:name":"Productos Del Cafe S.a.",
    "wof:placetype":"venue"
},
  "geometry": {"coordinates":[-0.3925470114,39.458732605],"type":"Point"}
}