{
  "type": "Feature",
  "properties": {
    "addr:full":"Pl Catalunya, S/n Roda De Bara Tarragona 43883",
    "addr:housenumber":"s / n",
    "addr:postcode":"43883",
    "addr:street":"Pl Catalunya",
    "iso:country":"ES",
    "sg:address":"Pl Catalunya, S/n",
    "sg:city":"Roda De Bara",
    "sg:orig_category":"Inform\u00c1tica, Ofim\u00c1tica (estudios, Asesor\u00cda, Ingenier\u00cda, Formaci\u00d3n)",
    "sg:phone":"+34 977 65 77 08",
    "sg:postcode":"43883",
    "sg:province":"Tarragona",
    "wof:name":"Moreno Lopez Yolanda",
    "wof:placetype":"venue"
},
  "geometry": {"coordinates":[1.4569209814,41.1829490662],"type":"Point"}
}