{
  "type": "Feature",
  "properties": {
    "iso:country":"ES",
    "sg:address":"Calle de Capitan Dema, 3",
    "sg:city":"Alacant",
    "sg:orig_category":"Asesor\u00cda Fiscal Y Jur\u00cddica",
    "sg:phone":"+34 965 10 69 84",
    "sg:postcode":"03007",
    "sg:province":"Alicante",
    "sg:website":"www.apynegestion.com",
    "wof:name":"Apyme Gestion,asesoramiento Integral De Empresas S.l.",
    "wof:placetype":"venue"
},
  "geometry": {"coordinates":[-0.5004913211,38.342540741],"type":"Point"}
}