{
  "type": "Feature",
  "properties": {
    "iso:country":"ES",
    "sg:address":"Calle de Baiona, 33",
    "sg:city":"Vitoria-gasteiz",
    "sg:orig_category":"Centros Empresariales",
    "sg:phone":"+34 945 17 70 79",
    "sg:postcode":"01013",
    "sg:province":"\u00c1lava",
    "wof:name":"Joaquin Zamora Sanchez",
    "wof:placetype":"venue"
},
  "geometry": {"coordinates":[-2.6938467026,42.8642425537],"type":"Point"}
}