{
  "type": "Feature",
  "properties": {
    "addr:full":"Calle de Alfonso El Sabio, 12 Sotogrande C\u00e1diz 11310",
    "addr:housenumber":"12",
    "addr:postcode":"11310",
    "addr:street":"Calle De Alfonso El Sabio;Ca\u0301Diz",
    "iso:country":"ES",
    "sg:address":"Calle de Alfonso El Sabio, 12",
    "sg:city":"Sotogrande",
    "sg:orig_category":"Centros Empresariales",
    "sg:phone":"+34 956 79 47 78",
    "sg:postcode":"11310",
    "sg:province":"C\u00e1diz",
    "wof:name":"Inversiones Rio Grande S.l.",
    "wof:placetype":"venue"
},
  "geometry": {"coordinates":[-5.2979450226,36.284236908],"type":"Point"}
}