{
  "type": "Feature",
  "properties": {
    "addr:full":"Calle de Azafranal, 18 Salamanca Salamanca 37001",
    "addr:housenumber":"18",
    "addr:postcode":"37001",
    "addr:street":"Calle De Azafranal",
    "iso:country":"ES",
    "sg:address":"Calle de Azafranal, 18",
    "sg:city":"Salamanca",
    "sg:orig_category":"\u00d3ptica: Instrumentos (fabricaci\u00d3n)",
    "sg:phone":"+34 923 21 14 44",
    "sg:postcode":"37001",
    "sg:province":"Salamanca",
    "wof:name":"Luengo Sanchez Mariano",
    "wof:placetype":"venue"
},
  "geometry": {"coordinates":[-5.6610074043,40.9671401978],"type":"Point"}
}