{
  "type": "Feature",
  "properties": {
    "iso:country":"ES",
    "sg:address":"Carrer de Maignon, 50",
    "sg:city":"Barcelona",
    "sg:orig_category":"Alumbrados",
    "sg:phone":"+34 932 10 89 50",
    "sg:postcode":"08024",
    "sg:province":"Barcelona",
    "sg:website":"www.blachere.fti.com",
    "wof:name":"Ingenieria Construccion Tecnicas De Iluminacion S.l.",
    "wof:placetype":"venue"
},
  "geometry": {"coordinates":[2.1525290012,41.4094467163],"type":"Point"}
}