{
  "type": "Feature",
  "properties": {
    "addr:full":"Carr Caceres, 34 Badalona Barcelona 08918",
    "addr:housenumber":"34",
    "addr:postcode":"08918",
    "addr:street":"Carr Caceres",
    "iso:country":"ES",
    "sg:address":"Carr Caceres, 34",
    "sg:city":"Badalona",
    "sg:orig_category":"Asociaciones, Organismos Culturales Y Socioeducativos",
    "sg:phone":"+34 933 99 39 51",
    "sg:postcode":"08918",
    "sg:province":"Barcelona",
    "wof:name":"Fundacio Privada Ateneum Sant Roc",
    "wof:placetype":"venue"
},
  "geometry": {"coordinates":[2.2234799862,41.4352912903],"type":"Point"}
}