{
  "type": "Feature",
  "properties": {
    "iso:country":"ES",
    "sg:address":"Pla\u00c7 Pais Valencia, 12",
    "sg:city":"Alcudia",
    "sg:orig_category":"\u00d3ptica: Instrumentos (fabricaci\u00d3n)",
    "sg:phone":"+34 962 99 61 89",
    "sg:postcode":"46250",
    "sg:province":"Valencia",
    "wof:name":"Optica Maseres, S.l.",
    "wof:placetype":"venue"
},
  "geometry": {"coordinates":[-0.5070289969,39.1940689087],"type":"Point"}
}