{
  "type": "Feature",
  "properties": {
    "iso:country":"ES",
    "sg:address":"Carrer de Josep Anselm Clave, 18",
    "sg:city":"Santa Coloma De Gramenet",
    "sg:orig_category":"M\u00c9dicos: Neurolog\u00cda",
    "sg:phone":"+34 934 66 26 64",
    "sg:postcode":"08921",
    "sg:province":"Barcelona",
    "wof:name":"Molins Girbau Miguel",
    "wof:placetype":"venue"
},
  "geometry": {"coordinates":[2.2088730335,41.4528694153],"type":"Point"}
}