{
  "type": "Feature",
  "properties": {
    "iso:country":"ES",
    "sg:address":"Cmno Garrapinillos, S/n",
    "sg:city":"Utebo",
    "sg:orig_category":"Asilos De Ancianos. Centros Privados",
    "sg:phone":"+34 976 77 10 04",
    "sg:postcode":"50180",
    "sg:province":"Zaragoza",
    "wof:name":"Asim-hogar Residencia S.l.",
    "wof:placetype":"venue"
},
  "geometry": {"coordinates":[-1.0074396133,41.7026748657],"type":"Point"}
}