{
  "type": "Feature",
  "properties": {
    "addr:full":"Calle de Riaza, 2 Madrid Madrid 28023",
    "addr:housenumber":"2",
    "addr:postcode":"28023",
    "addr:street":"Calle De Riaza",
    "iso:country":"ES",
    "sg:address":"Calle de Riaza, 2",
    "sg:city":"Madrid",
    "sg:orig_category":"Centros Empresariales",
    "sg:phone":"+34 917 29 90 16",
    "sg:postcode":"28023",
    "sg:province":"Madrid",
    "wof:name":"Continental Tres Mil Servicios",
    "wof:placetype":"venue"
},
  "geometry": {"coordinates":[-3.7803330421,40.4566879272],"type":"Point"}
}