{
  "type": "Feature",
  "properties": {
    "addr:full":"Calle de Gabino Amaya, 18 Puebla Sancho Perez Badajoz 06310",
    "addr:housenumber":"18",
    "addr:postcode":"06310",
    "addr:street":"Calle De Gabino Amaya;Sancho",
    "iso:country":"ES",
    "sg:address":"Calle de Gabino Amaya, 18",
    "sg:city":"Puebla Sancho Perez",
    "sg:orig_category":"Productores Recolectores, Venta Directa De Vinos",
    "sg:phone":"+34 924 55 14 31",
    "sg:postcode":"06310",
    "sg:province":"Badajoz",
    "wof:name":"Matamoros Toribio Miguel Angel",
    "wof:placetype":"venue"
},
  "geometry": {"coordinates":[-6.3998661041,38.395160675],"type":"Point"}
}