{
  "type": "Feature",
  "properties": {
    "addr:full":"Calle de Caidos De La Division Azul, 20 Madrid Madrid 28016",
    "addr:housenumber":"20",
    "addr:postcode":"madrid;28016",
    "addr:street":"Calle De Caidos De La Division Azul",
    "iso:country":"ES",
    "sg:address":"Calle de Caidos De La Division Azul, 20",
    "sg:city":"Madrid",
    "sg:orig_category":"Cl\u00cdnicas M\u00c9dicas",
    "sg:phone":"+34 913 43 03 07",
    "sg:postcode":"28016",
    "sg:province":"Madrid",
    "wof:name":"Clinica Interplastica S.l",
    "wof:placetype":"venue"
},
  "geometry": {"coordinates":[-3.6733076572,40.4667167664],"type":"Point"}
}