{
  "type": "Feature",
  "properties": {
    "addr:full":"Praz Alfonso Alcaraz, 3 Ourense Ourense 32002",
    "addr:housenumber":"3",
    "addr:postcode":"32002",
    "addr:street":"Praz Alfonso Alcaraz",
    "iso:country":"ES",
    "sg:address":"Praz Alfonso Alcaraz, 3",
    "sg:city":"Ourense",
    "sg:orig_category":"Alimentaci\u00d3n General (al Por Menor)",
    "sg:phone":"+34 988 22 52 06",
    "sg:postcode":"32002",
    "sg:province":"Ourense",
    "wof:name":"Bola\u00f1o Carrasco Candido",
    "wof:placetype":"venue"
},
  "geometry": {"coordinates":[-7.8813591003,42.3439445496],"type":"Point"}
}