{
  "type": "Feature",
  "properties": {
    "addr:full":"Calle de Andres Vives, 2 Alca\u00f1iz Teruel 44600",
    "addr:housenumber":"2",
    "addr:postcode":"44600",
    "addr:street":"Calle De Andres Vives",
    "iso:country":"ES",
    "sg:address":"Calle de Andres Vives, 2",
    "sg:city":"Alca\u00f1iz",
    "sg:orig_category":"Profesiones M\u00c9dicas, Param\u00c9dicas",
    "sg:phone":"+34 978 87 06 47",
    "sg:postcode":"44600",
    "sg:province":"Teruel",
    "wof:name":"Aqa Ba\u00f1os De Alqannis S.l.",
    "wof:placetype":"venue"
},
  "geometry": {"coordinates":[-0.1286507994,41.0461769104],"type":"Point"}
}