{
  "type": "Feature",
  "properties": {
    "iso:country":"ES",
    "sg:address":"Carrer de Feliu I Codina, 74",
    "sg:city":"Barcelona",
    "sg:orig_category":"Carnicer\u00cdas, Carnicer\u00cdas",
    "sg:phone":"+34 934 27 84 52",
    "sg:postcode":"08031",
    "sg:province":"Barcelona",
    "wof:name":"Bescos Marco Pedro",
    "wof:placetype":"venue"
},
  "geometry": {"coordinates":[2.1630239487,41.436000824],"type":"Point"}
}