{
  "type": "Feature",
  "properties": {
    "addr:full":"Avda Concordia, 6 Muriedas Cantabria 39600",
    "addr:housenumber":"6",
    "addr:postcode":"39600",
    "addr:street":"Avda Concordia",
    "iso:country":"ES",
    "sg:address":"Avda Concordia, 6",
    "sg:city":"Muriedas",
    "sg:orig_category":"Cajas De Ahorro",
    "sg:phone":"+34 942 26 98 52",
    "sg:postcode":"39600",
    "sg:province":"Cantabria",
    "sg:website":"www.bbk.es",
    "wof:name":"Bilbao Bizkaia Kutxa",
    "wof:placetype":"venue"
},
  "geometry": {"coordinates":[-3.8458189964,43.4184341431],"type":"Point"}
}