{
  "type": "Feature",
  "properties": {
    "addr:full":"Carrer de Missio, 4 Palma Islas Baleares 07003",
    "addr:housenumber":"4",
    "addr:postcode":"07003",
    "addr:street":"Carrer De Missio",
    "iso:country":"ES",
    "sg:address":"Carrer de Missio, 4",
    "sg:city":"Palma",
    "sg:orig_category":"Artes Gr\u00c1ficas, Artes Pl\u00c1sticas (curso)",
    "sg:phone":"+34 971 71 96 52",
    "sg:postcode":"07003",
    "sg:province":"Islas Baleares",
    "wof:name":"Vich Tugores Juan",
    "wof:placetype":"venue"
},
  "geometry": {"coordinates":[2.6516399384,39.5734939575],"type":"Point"}
}