{
  "type": "Feature",
  "properties": {
    "iso:country":"ES",
    "sg:address":"Avda Antonio Machado, 62",
    "sg:city":"Arroyo De La Miel-benalmadena Costa",
    "sg:orig_category":"Molduras, Junquillos, Listones Y Molduras Perforadas",
    "sg:phone":"+34 952 56 75 91",
    "sg:postcode":"29630",
    "sg:province":"M\u00e1laga",
    "wof:name":"Astur Phone S.l.",
    "wof:placetype":"venue"
},
  "geometry": {"coordinates":[-4.5221476555,36.5946960449],"type":"Point"}
}