{
  "type": "Feature",
  "properties": {
    "addr:full":"Calle de Real, S/n Alcolea Del Pinar Guadalajara 19260",
    "addr:housenumber":"s / n",
    "addr:postcode":"19260",
    "addr:street":"Calle De Real",
    "iso:country":"ES",
    "sg:address":"Calle de Real, S/n",
    "sg:city":"Alcolea Del Pinar",
    "sg:orig_category":"Empresas De Carpinter\u00cda",
    "sg:phone":"+34 949 30 01 14",
    "sg:postcode":"19260",
    "sg:province":"Guadalajara",
    "wof:name":"Emilio Garcia E Hijos S.l.",
    "wof:placetype":"venue"
},
  "geometry": {"coordinates":[-2.4668529034,41.0365791321],"type":"Point"}
}