{
  "type": "Feature",
  "properties": {
    "addr:full":"Calle de Poeta Viana, 3 Medano Santa Cruz De Tenerife 38612",
    "addr:housenumber":"3",
    "addr:postcode":"38612",
    "addr:street":"Calle De Poeta Viana",
    "iso:country":"ES",
    "sg:address":"Calle de Poeta Viana, 3",
    "sg:city":"Medano",
    "sg:orig_category":"Alquiler De Veh\u00cdculos: Turismos Y Utilitarios",
    "sg:phone":"+34 922 17 68 51",
    "sg:postcode":"38612",
    "sg:province":"Santa Cruz De Tenerife",
    "wof:name":"Rent A Car Sancho Tenerife S.l.",
    "wof:placetype":"venue"
},
  "geometry": {"coordinates":[-16.5262241364,28.0532035828],"type":"Point"}
}