{
  "type": "Feature",
  "properties": {
    "addr:full":"Carrer de Conca, 4 Barcelona Barcelona 08026",
    "addr:housenumber":"4",
    "addr:postcode":"08026",
    "addr:street":"Carrer De Conca",
    "iso:country":"ES",
    "sg:address":"Carrer de Conca, 4",
    "sg:city":"Barcelona",
    "sg:orig_category":"Peluquer\u00cdas, Peluquer\u00cda Mixta",
    "sg:phone":"+34 934 36 91 24",
    "sg:postcode":"08026",
    "sg:province":"Barcelona",
    "wof:name":"Ortega Perez Maria Lourdes",
    "wof:placetype":"venue"
},
  "geometry": {"coordinates":[2.1809511185,41.4132347107],"type":"Point"}
}