{
  "type": "Feature",
  "properties": {
    "addr:full":"Carrer de Sol, 1 Viladecans Barcelona 08840",
    "addr:housenumber":"1",
    "addr:postcode":"08840",
    "addr:street":"Carrer De Sol",
    "iso:country":"ES",
    "sg:address":"Carrer de Sol, 1",
    "sg:city":"Viladecans",
    "sg:orig_category":"Fabricaci\u00d3n, Distribuci\u00d3n De Discos, V\u00cddeodiscos Y Musicassettes",
    "sg:phone":"+34 936 58 51 42",
    "sg:postcode":"08840",
    "sg:province":"Barcelona",
    "wof:name":"Leou Negre S.l.",
    "wof:placetype":"venue"
},
  "geometry": {"coordinates":[2.0188789368,41.3159484863],"type":"Point"}
}