{
  "type": "Feature",
  "properties": {
    "addr:full":"Rua Wenceslao Fernandez Florez, 18 Cambre La Coru\u00f1a 15660",
    "addr:housenumber":"18",
    "addr:postcode":"15660",
    "addr:street":"Rua Wenceslao Fernandez Florez;La Corun\u0303A",
    "iso:country":"ES",
    "sg:address":"Rua Wenceslao Fernandez Florez, 18",
    "sg:city":"Cambre",
    "sg:orig_category":"Pompas F\u00danebres, Inhumaciones Y Cremaciones",
    "sg:phone":"+34 981 67 56 02",
    "sg:postcode":"15660",
    "sg:province":"La Coru\u00f1a",
    "wof:name":"Eiroa Dovao Luis",
    "wof:placetype":"venue"
},
  "geometry": {"coordinates":[-8.3439779282,43.2928543091],"type":"Point"}
}