{
  "type": "Feature",
  "properties": {
    "iso:country":"ES",
    "sg:address":"Carrer de Ter, S/n",
    "sg:city":"Torello",
    "sg:orig_category":"Metales (labores, Pulido)",
    "sg:phone":"+34 938 59 10 73",
    "sg:postcode":"08570",
    "sg:province":"Barcelona",
    "wof:name":"Tecniques D'estampacio I Emboticio De Me",
    "wof:placetype":"venue"
},
  "geometry": {"coordinates":[2.2575950623,42.0476264954],"type":"Point"}
}