{
  "type": "Feature",
  "properties": {
    "addr:full":"Calle de Libertad, 59 Pola De Laviana Asturias 33980",
    "addr:housenumber":"59",
    "addr:postcode":"33980",
    "addr:street":"Calle De Libertad",
    "iso:country":"ES",
    "sg:address":"Calle de Libertad, 59",
    "sg:city":"Pola De Laviana",
    "sg:orig_category":"Peluquer\u00cdas, Peluquer\u00cda Mixta",
    "sg:phone":"+34 985 60 03 63",
    "sg:postcode":"33980",
    "sg:province":"Asturias",
    "wof:name":"Blanco Alonso Celestino",
    "wof:placetype":"venue"
},
  "geometry": {"coordinates":[-5.5601511002,43.2422218323],"type":"Point"}
}