{
  "type": "Feature",
  "properties": {
    "addr:full":"Carrer de Rufo, 43 S. Feliu Guixols Girona 17220",
    "addr:housenumber":"43",
    "addr:postcode":"17220",
    "addr:street":"Carrer De Rufo;S. Feliu Guixols",
    "iso:country":"ES",
    "sg:address":"Carrer de Rufo, 43",
    "sg:city":"S. Feliu Guixols",
    "sg:orig_category":"Mec\u00c1nico Del Autom\u00d3vil",
    "sg:phone":"+34 972 82 16 29",
    "sg:postcode":"17220",
    "sg:province":"Girona",
    "wof:name":"Pajares Martinez Manuel",
    "wof:placetype":"venue"
},
  "geometry": {"coordinates":[3.0319600105,41.7881317139],"type":"Point"}
}