{
  "type": "Feature",
  "properties": {
    "iso:country":"ES",
    "sg:address":"Av Verge Montserrat, 180",
    "sg:city":"Prat Llobregat",
    "sg:orig_category":"Inmobiliaria (agencias)",
    "sg:phone":"+34 934 78 82 13",
    "sg:postcode":"08820",
    "sg:province":"Barcelona",
    "wof:name":"Prat 96 S.l.",
    "wof:placetype":"venue"
},
  "geometry": {"coordinates":[2.0904080868,41.324420929],"type":"Point"}
}