{
  "type": "Feature",
  "properties": {
    "addr:full":"Calle de General Arrando, 10 Madrid Madrid 28010",
    "addr:housenumber":"10",
    "addr:postcode":"madrid;28010",
    "addr:street":"Calle De General Arrando",
    "iso:country":"ES",
    "sg:address":"Calle de General Arrando, 10",
    "sg:city":"Madrid",
    "sg:orig_category":"Inmobiliaria (agencias)",
    "sg:phone":"+34 914 45 01 00",
    "sg:postcode":"28010",
    "sg:province":"Madrid",
    "wof:name":"Exclusivas Viali S.l.",
    "wof:placetype":"venue"
},
  "geometry": {"coordinates":[-3.6963331699,40.4316902161],"type":"Point"}
}