{
  "type": "Feature",
  "properties": {
    "addr:full":"Calle de Padre Huesca, 14 Huesca Huesca 22002",
    "addr:housenumber":"14",
    "addr:postcode":"22002",
    "addr:street":"Calle De Padre Huesca",
    "iso:country":"ES",
    "sg:address":"Calle de Padre Huesca, 14",
    "sg:city":"Huesca",
    "sg:orig_category":"Molduras, Junquillos, Listones Y Molduras Perforadas",
    "sg:phone":"+34 974 22 77 65",
    "sg:postcode":"22002",
    "sg:province":"Huesca",
    "wof:name":"Arasanz Arasanz Angel",
    "wof:placetype":"venue"
},
  "geometry": {"coordinates":[-0.4069708884,42.136341095],"type":"Point"}
}