{
  "type": "Feature",
  "properties": {
    "addr:full":"Calle de Fernando Vela, 13 Oviedo Asturias 33001",
    "addr:housenumber":"13",
    "addr:postcode":"33001",
    "addr:street":"Calle De Fernando Vela",
    "iso:country":"ES",
    "sg:address":"Calle de Fernando Vela, 13",
    "sg:city":"Oviedo",
    "sg:orig_category":"Bancos",
    "sg:phone":"+34 985 29 40 00",
    "sg:postcode":"33001",
    "sg:province":"Asturias",
    "wof:name":"Banc Sabadell S.a.",
    "wof:placetype":"venue"
},
  "geometry": {"coordinates":[-5.8414888382,43.3664741516],"type":"Point"}
}