{
  "type": "Feature",
  "properties": {
    "addr:full":"Avda Asturias, 20 Santa Maria Del Paramo Le\u00f3n 24240",
    "addr:housenumber":"20",
    "addr:postcode":"24240",
    "addr:street":"Avda Asturias",
    "iso:country":"ES",
    "sg:address":"Avda Asturias, 20",
    "sg:city":"Santa Maria Del Paramo",
    "sg:orig_category":"Agentes, Concesionarios Y Sucursales De Veh\u00cdculos",
    "sg:phone":"+34 987 35 01 82",
    "sg:postcode":"24240",
    "sg:province":"Le\u00f3n",
    "wof:name":"Talleres Fernandez Trisac.s.l.",
    "wof:placetype":"venue"
},
  "geometry": {"coordinates":[-5.7452120781,42.3560905457],"type":"Point"}
}