{
  "type": "Feature",
  "properties": {
    "iso:country":"ES",
    "sg:address":"Avda El Minero, 7",
    "sg:city":"Gallarta",
    "sg:orig_category":"Relojer\u00cda (al Por Menor, Reparaci\u00d3n)",
    "sg:phone":"+34 946 36 22 27",
    "sg:postcode":"48500",
    "sg:province":"Vizcaya",
    "wof:name":"Lahuerta Del Rio Jose Manuel",
    "wof:placetype":"venue"
},
  "geometry": {"coordinates":[-3.0733940601,43.3148536682],"type":"Point"}
}