{
  "type": "Feature",
  "properties": {
    "iso:country":"ES",
    "sg:address":"Av Meridiana, 168",
    "sg:city":"Barcelona",
    "sg:classifiers":[
        {
            "category":"Autos & Motor Vehicles",
            "subcategory":"Automobile Sales",
            "type":"Retail Goods"
        }
    ],
    "sg:phone":"+34 932 46 23 96",
    "sg:postcode":"08026",
    "sg:province":"Barcelona",
    "wof:name":"Conduccion Record06 S.c.c.l.",
    "wof:placetype":"venue"
},
  "geometry": {"coordinates":[2.1871049404,41.4114646912],"type":"Point"}
}