{
  "type": "Feature",
  "properties": {
    "addr:full":"Carrer de Piferrer, S/n Barcelona Barcelona 08016",
    "addr:housenumber":"s / n",
    "addr:postcode":"08016",
    "addr:street":"Carrer De Piferrer",
    "iso:country":"ES",
    "sg:address":"Carrer de Piferrer, S/n",
    "sg:city":"Barcelona",
    "sg:orig_category":"Centros De Educaci\u00d3n Especial",
    "sg:phone":"+34 933 50 72 82",
    "sg:postcode":"08016",
    "sg:province":"Barcelona",
    "wof:name":"Ajuntament De Barcelona",
    "wof:placetype":"venue"
},
  "geometry": {"coordinates":[2.1783232689,41.4330177307],"type":"Point"}
}