{
  "type": "Feature",
  "properties": {
    "addr:full":"Calle de Aduana, 27 Irun Guip\u00f9zcoa 20303",
    "addr:housenumber":"27",
    "addr:postcode":"20303",
    "addr:street":"Calle De Aduana;Guipu\u0300Zcoa",
    "iso:country":"ES",
    "sg:address":"Calle de Aduana, 27",
    "sg:city":"Irun",
    "sg:orig_category":"Asociaciones Humanitarias, De Cooperaci\u00d3n, De Acci\u00d3n Social",
    "sg:phone":"+34 943 61 70 49",
    "sg:postcode":"20303",
    "sg:province":"Guip\u00f9zcoa",
    "wof:name":"Asociacion Guipuzcoana De Familiares Y Enfermos Psiquicos",
    "wof:placetype":"venue"
},
  "geometry": {"coordinates":[-1.798361659,43.3381462097],"type":"Point"}
}