{
  "type": "Feature",
  "properties": {
    "iso:country":"ES",
    "sg:address":"Avda Cuba (de), 10",
    "sg:city":"Mairena Aljarafe",
    "sg:orig_category":"Florister\u00cdas",
    "sg:phone":"+34 954 76 25 82",
    "sg:postcode":"41927",
    "sg:province":"Sevilla",
    "wof:name":"Black Bacca",
    "wof:placetype":"venue"
},
  "geometry": {"coordinates":[-6.0626192093,37.3473587036],"type":"Point"}
}