{
  "type": "Feature",
  "properties": {
    "addr:full":"Calle de Nu\u00d1ez De Balboa, 1 Malagon Ciudad Real 13420",
    "addr:housenumber":"1",
    "addr:postcode":"13420",
    "addr:street":"Calle De Nun\u0303Ez De Balboa",
    "iso:country":"ES",
    "sg:address":"Calle de Nu\u00d1ez De Balboa, 1",
    "sg:city":"Malagon",
    "sg:orig_category":"Delegados, Agentes De Tr\u00c1nsito, Auxiliares De Transporte Internacional",
    "sg:phone":"+34 926 80 24 03",
    "sg:postcode":"13420",
    "sg:province":"Ciudad Real",
    "wof:name":"Transportes Santos Cruz S.l.",
    "wof:placetype":"venue"
},
  "geometry": {"coordinates":[-3.8570849895,39.1615943909],"type":"Point"}
}