{
  "type": "Feature",
  "properties": {
    "iso:country":"ES",
    "sg:address":"Calle de Pintor Balaca, 62",
    "sg:city":"Cartagena",
    "sg:orig_category":"Prot\u00c9sicos Dentales",
    "sg:phone":"+34 968 50 23 25",
    "sg:postcode":"30203",
    "sg:province":"Murcia",
    "wof:name":"Urios Sanchez Carmelo",
    "wof:placetype":"venue"
},
  "geometry": {"coordinates":[-0.9833499789,37.6091499329],"type":"Point"}
}