{
  "type": "Feature",
  "properties": {
    "addr:full":"Rond Calvari (del), 26 Algemesi Valencia 46680",
    "addr:postcode":"46680",
    "iso:country":"ES",
    "sg:address":"Rond Calvari (del), 26",
    "sg:city":"Algemesi",
    "sg:orig_category":"Cajas Y Embalajes De Madera",
    "sg:phone":"+34 962 48 41 10",
    "sg:postcode":"46680",
    "sg:province":"Valencia",
    "wof:name":"Romero Garcia Jose Maria",
    "wof:placetype":"venue"
},
  "geometry": {"coordinates":[-0.4386000037,39.195892334],"type":"Point"}
}