{
  "type": "Feature",
  "properties": {
    "iso:country":"ES",
    "sg:address":"Carrer de Sant Nicasi, 2",
    "sg:city":"Gava",
    "sg:orig_category":"Ropa Para Se\u00d1oras Y Caballeros (al Por Menor)",
    "sg:phone":"+34 936 38 48 14",
    "sg:postcode":"08850",
    "sg:province":"Barcelona",
    "wof:name":"Osma Y Gala S.l.",
    "wof:placetype":"venue"
},
  "geometry": {"coordinates":[2.0027210712,41.3054656982],"type":"Point"}
}