{
  "type": "Feature",
  "properties": {
    "iso:country":"ES",
    "sg:address":"Carrer de Romani, 1",
    "sg:city":"Barcelona",
    "sg:orig_category":"Fabricaci\u00d3n De Su\u00c9ters Y Chalecos De Punto",
    "sg:phone":"+34 933 50 58 16",
    "sg:postcode":"08042",
    "sg:province":"Barcelona",
    "wof:name":"Importaciones Mclenn S.l.",
    "wof:placetype":"venue"
},
  "geometry": {"coordinates":[2.1747300625,41.4464416504],"type":"Point"}
}