{
  "type": "Feature",
  "properties": {
    "iso:country":"ES",
    "sg:address":"Carrer de Ismael Candela, 8",
    "sg:city":"Crevillent",
    "sg:orig_category":"Cooperativas Agr\u00cdcolas",
    "sg:phone":"+34 966 68 14 68",
    "sg:postcode":"03330",
    "sg:province":"Alicante",
    "wof:name":"Cooperativa Electrica Benefica San Francisco De Asis",
    "wof:placetype":"venue"
},
  "geometry": {"coordinates":[-0.8058720231,38.2491912842],"type":"Point"}
}