{
  "type": "Feature",
  "properties": {
    "iso:country":"ES",
    "sg:address":"Rond Sindic Antoni Albuixech, 23",
    "sg:city":"Almussafes",
    "sg:orig_category":"Promotores Constructores",
    "sg:phone":"+34 961 78 46 57",
    "sg:postcode":"46440",
    "sg:province":"Valencia",
    "wof:name":"Construcciones Mari Aleixos S.l.",
    "wof:placetype":"venue"
},
  "geometry": {"coordinates":[-0.4110909998,39.2889404297],"type":"Point"}
}