{
  "type": "Feature",
  "properties": {
    "addr:full":"Pl Rius I Taulet, 12 Barcelona Barcelona 08012",
    "addr:housenumber":"12",
    "addr:postcode":"08012",
    "addr:street":"Pl Rius I Taulet",
    "iso:country":"ES",
    "sg:address":"Pl Rius I Taulet, 12",
    "sg:city":"Barcelona",
    "sg:orig_category":"Bisuter\u00cda, Joyer\u00cda, Relojer\u00cda (al Por Menor)",
    "sg:phone":"+34 934 15 97 54",
    "sg:postcode":"08012",
    "sg:province":"Barcelona",
    "sg:website":"www.locuracotidiana.com",
    "wof:name":"Martinez Cortes Omar Hernan",
    "wof:placetype":"venue"
},
  "geometry": {"coordinates":[2.1572959423,41.4005241394],"type":"Point"}
}