{
  "type": "Feature",
  "properties": {
    "iso:country":"ES",
    "sg:address":"Pl Jaume I, 7",
    "sg:city":"Vendrell",
    "sg:orig_category":"Juegos Y Juguetes (al Por Menor)",
    "sg:phone":"+34 977 66 87 50",
    "sg:postcode":"43700",
    "sg:province":"Tarragona",
    "wof:name":"Basar Llorens S. A.",
    "wof:placetype":"venue"
},
  "geometry": {"coordinates":[1.5355260372,41.2205505371],"type":"Point"}
}