{
  "type": "Feature",
  "properties": {
    "addr:full":"Rua Ramon Puga, 43 Ourense Ourense 32005",
    "addr:housenumber":"43",
    "addr:postcode":"32005",
    "addr:street":"Rua Ramon Puga",
    "iso:country":"ES",
    "sg:address":"Rua Ramon Puga, 43",
    "sg:city":"Ourense",
    "sg:orig_category":"Caf\u00c9s, Bares, Cervecer\u00cdas",
    "sg:phone":"+34 988 25 27 17",
    "sg:postcode":"32005",
    "sg:province":"Ourense",
    "wof:name":"Galtelcom",
    "wof:placetype":"venue"
},
  "geometry": {"coordinates":[-7.8593759537,42.3278236389],"type":"Point"}
}