{
  "type": "Feature",
  "properties": {
    "addr:full":"Calle de Lucios, 61 Puente Tocinos Murcia 30006",
    "addr:housenumber":"61",
    "addr:postcode":"30006",
    "addr:street":"Calle De Lucios",
    "iso:country":"ES",
    "sg:address":"Calle de Lucios, 61",
    "sg:city":"Puente Tocinos",
    "sg:orig_category":"Centros De Educaci\u00d3n Especial",
    "sg:phone":"+34 968 23 69 08",
    "sg:postcode":"30006",
    "sg:province":"Murcia",
    "wof:name":"Colegio Publico Infanta Cristina",
    "wof:placetype":"venue"
},
  "geometry": {"coordinates":[-1.1047290564,37.9914512634],"type":"Point"}
}