{
  "type": "Feature",
  "properties": {
    "iso:country":"ES",
    "sg:address":"Calle de Gil De Onta\u00d1on, 1",
    "sg:city":"Salamanca",
    "sg:orig_category":"Librer\u00cdas",
    "sg:phone":"+34 923 22 36 67",
    "sg:postcode":"37005",
    "sg:province":"Salamanca",
    "wof:name":"Melgar Jimenez Francisco Javier",
    "wof:placetype":"venue"
},
  "geometry": {"coordinates":[-5.6618947983,40.9712600708],"type":"Point"}
}