{
  "type": "Feature",
  "properties": {
    "addr:full":"Plaz Mayor, 7 Tarazona Mancha Albacete 02100",
    "addr:housenumber":"7",
    "addr:postcode":"02100",
    "addr:street":"Plaz Mayor",
    "iso:country":"ES",
    "sg:address":"Plaz Mayor, 7",
    "sg:city":"Tarazona Mancha",
    "sg:orig_category":"Cajas De Ahorro",
    "sg:phone":"+34 967 48 00 32",
    "sg:postcode":"02100",
    "sg:province":"Albacete",
    "wof:name":"Caja De Ahorros De Castilla La Mancha",
    "wof:placetype":"venue"
},
  "geometry": {"coordinates":[-1.9125390053,39.2651023865],"type":"Point"}
}