{
  "type": "Feature",
  "properties": {
    "addr:full":"Calle de Flor La, 14 Grado Asturias 33820",
    "addr:housenumber":"14",
    "addr:postcode":"33820",
    "addr:street":"Calle De Flor La",
    "iso:country":"ES",
    "sg:address":"Calle de Flor La, 14",
    "sg:city":"Grado",
    "sg:orig_category":"Procuradores",
    "sg:phone":"+34 985 75 27 39",
    "sg:postcode":"33820",
    "sg:province":"Asturias",
    "wof:name":"Fernandez Fernandez Jose Ramon",
    "wof:placetype":"venue"
},
  "geometry": {"coordinates":[-6.0750794411,43.3849563599],"type":"Point"}
}