{
  "type": "Feature",
  "properties": {
    "addr:full":"C/ Ciutat De Lliria, 43 Paterna Valencia 46988",
    "addr:housenumber":"43",
    "addr:postcode":"46988",
    "addr:street":"C / Ciutat De Lliria",
    "iso:country":"ES",
    "sg:address":"C/ Ciutat De Lliria, 43",
    "sg:city":"Paterna",
    "sg:orig_category":"Cromado Y Niquelado",
    "sg:phone":"+34 961 32 43 34",
    "sg:postcode":"46988",
    "sg:province":"Valencia",
    "wof:name":"Cromados Lafuente S.l.",
    "wof:placetype":"venue"
},
  "geometry": {"coordinates":[-0.4661760032,39.5240783691],"type":"Point"}
}