{
  "type": "Feature",
  "properties": {
    "addr:full":"Poli Industrial Corbones, 126 Puebla Cazalla Sevilla 41540",
    "addr:housenumber":"126",
    "addr:postcode":"41540",
    "iso:country":"ES",
    "sg:address":"Poli Industrial Corbones, 126",
    "sg:city":"Puebla Cazalla",
    "sg:orig_category":"Empresas De Carpinter\u00cda De Madera",
    "sg:phone":"+34 954 84 78 97",
    "sg:postcode":"41540",
    "sg:province":"Sevilla",
    "wof:name":"Bejarano Navarro Manuel",
    "wof:placetype":"venue"
},
  "geometry": {"coordinates":[-5.3132190704,37.2229957581],"type":"Point"}
}