{
  "type": "Feature",
  "properties": {
    "iso:country":"ES",
    "sg:address":"Urkizu Pasealekua, 18",
    "sg:city":"Eibar",
    "sg:orig_category":"Carnicer\u00cdas, Carnicer\u00cdas",
    "sg:phone":"+34 943 12 01 94",
    "sg:postcode":"20600",
    "sg:province":"Guip\u00f9zcoa",
    "wof:name":"Oregi Guisasola Aitor",
    "wof:placetype":"venue"
},
  "geometry": {"coordinates":[-2.4632430077,43.1861877441],"type":"Point"}
}