{
  "type": "Feature",
  "properties": {
    "iso:country":"ES",
    "sg:address":"Calle de Gran Capitan, 75",
    "sg:city":"Bola\u00e7os De Calatrava",
    "sg:orig_category":"Empresas De Carpinter\u00cda Met\u00c1lica",
    "sg:phone":"+34 926 87 08 43",
    "sg:postcode":"13260",
    "sg:province":"Ciudad Real",
    "wof:name":"De Toro Moraga Miguel",
    "wof:placetype":"venue"
},
  "geometry": {"coordinates":[-3.6622788906,38.9041290283],"type":"Point"}
}