{
  "type": "Feature",
  "properties": {
    "addr:full":"Carr Constitucio (la), 8 Petrer Alicante 03610",
    "addr:housenumber":"8",
    "addr:postcode":"03610",
    "addr:street":"Carr Constitucio La",
    "iso:country":"ES",
    "sg:address":"Carr Constitucio (la), 8",
    "sg:city":"Petrer",
    "sg:orig_category":"Cl\u00cdnicas M\u00c9dicas",
    "sg:phone":"+34 965 37 44 98",
    "sg:postcode":"03610",
    "sg:province":"Alicante",
    "wof:name":"Llorente Segura Francisco Jose",
    "wof:placetype":"venue"
},
  "geometry": {"coordinates":[-0.771156013,38.4852600098],"type":"Point"}
}