{
  "type": "Feature",
  "properties": {
    "iso:country":"ES",
    "sg:address":"Avda San Isidro, 1",
    "sg:city":"Caba\u00d1aquinta",
    "sg:orig_category":"Venta, Instalaci\u00d3n De Calefacci\u00d3n",
    "sg:phone":"+34 985 49 45 32",
    "sg:postcode":"33686",
    "sg:province":"Asturias",
    "wof:name":"Instalaciones De Frio Y Calor Hermanos Fernandez S.l.",
    "wof:placetype":"venue"
},
  "geometry": {"coordinates":[-5.6216692924,43.1606178284],"type":"Point"}
}