{
  "type": "Feature",
  "properties": {
    "addr:full":"Calle de Juan Xxiii, 43 Aviles Asturias 33401",
    "addr:housenumber":"43",
    "addr:postcode":"33401",
    "addr:street":"Calle De Juan Xxiii",
    "iso:country":"ES",
    "sg:address":"Calle de Juan Xxiii, 43",
    "sg:city":"Aviles",
    "sg:orig_category":"Polideportivos",
    "sg:phone":"+34 985 56 78 31",
    "sg:postcode":"33401",
    "sg:province":"Asturias",
    "wof:name":"Fundacion Deportiva Municipal De Aviles",
    "wof:placetype":"venue"
},
  "geometry": {"coordinates":[-5.9324588776,43.5560913086],"type":"Point"}
}