{
  "type": "Feature",
  "properties": {
    "iso:country":"ES",
    "sg:address":"Calle de Evangelista, 26",
    "sg:city":"Sevilla",
    "sg:orig_category":"Agencias Y Agentes Comerciales, Representantes",
    "sg:phone":"+34 954 33 96 69",
    "sg:postcode":"41010",
    "sg:province":"Sevilla",
    "wof:name":"Fraile Pereira E Hijos S.l.",
    "wof:placetype":"venue"
},
  "geometry": {"coordinates":[-6.0042376518,37.3817672729],"type":"Point"}
}