{
  "type": "Feature",
  "properties": {
    "addr:full":"Carr Terri, 1 Girona Girona 17003",
    "addr:housenumber":"1",
    "addr:postcode":"17003",
    "addr:street":"Carr Terri",
    "iso:country":"ES",
    "sg:address":"Carr Terri, 1",
    "sg:city":"Girona",
    "sg:orig_category":"Ropa Para Ni\u00d1os (al Por Menor)",
    "sg:phone":"+34 972 20 62 06",
    "sg:postcode":"17003",
    "sg:province":"Girona",
    "wof:name":"Martin Bosser Rosa",
    "wof:placetype":"venue"
},
  "geometry": {"coordinates":[2.8169000149,41.9693145752],"type":"Point"}
}