{
  "type": "Feature",
  "properties": {
    "iso:country":"ES",
    "sg:address":"Calle de Salado, 39",
    "sg:city":"Sevilla",
    "sg:orig_category":"Papeler\u00cdas, Librer\u00cdas",
    "sg:phone":"+34 954 99 04 51",
    "sg:postcode":"41010",
    "sg:province":"Sevilla",
    "wof:name":"Copiador S.c.a.",
    "wof:placetype":"venue"
},
  "geometry": {"coordinates":[-6.0045552254,37.376991272],"type":"Point"}
}