{
  "type": "Feature",
  "properties": {
    "addr:full":"Carrer de Sant Josep, 97 Sant Vicen\u00c7 Dels Horts Barcelona 08620",
    "addr:housenumber":"97",
    "addr:postcode":"08620",
    "addr:street":"Carrer De Sant Josep",
    "iso:country":"ES",
    "sg:address":"Carrer de Sant Josep, 97",
    "sg:city":"Sant Vicen\u00c7 Dels Horts",
    "sg:orig_category":"Cajas De Ahorro",
    "sg:phone":"+34 936 56 09 49",
    "sg:postcode":"08620",
    "sg:province":"Barcelona",
    "wof:name":"Caixa D'estalvis Del Penedes",
    "wof:placetype":"venue"
},
  "geometry": {"coordinates":[2.010819912,41.3902206421],"type":"Point"}
}