{
  "type": "Feature",
  "properties": {
    "iso:country":"ES",
    "sg:address":"Arzua(priorada-sancibrao), 5",
    "sg:city":"Melide",
    "sg:orig_category":"Estancos",
    "sg:phone":"+34 981 50 52 58",
    "sg:postcode":"15800",
    "sg:province":"La Coru\u00f1a",
    "wof:name":"Lopez Rodriguez Mercedes",
    "wof:placetype":"venue"
},
  "geometry": {"coordinates":[-8.1010923386,42.9557991028],"type":"Point"}
}