{
  "type": "Feature",
  "properties": {
    "addr:full":"Calle de Colombia, 41 Salamanca Salamanca 37003",
    "addr:housenumber":"41",
    "addr:postcode":"37003",
    "addr:street":"Calle De Colombia",
    "iso:country":"ES",
    "sg:address":"Calle de Colombia, 41",
    "sg:city":"Salamanca",
    "sg:orig_category":"Plomeros",
    "sg:phone":"+34 923 18 25 04",
    "sg:postcode":"37003",
    "sg:province":"Salamanca",
    "wof:name":"Nava Gomez Juan",
    "wof:placetype":"venue"
},
  "geometry": {"coordinates":[-5.6462731361,40.9686965942],"type":"Point"}
}