{
  "type": "Feature",
  "properties": {
    "addr:full":"Rua Venezuela, 70 Ferrol La Coru\u00f1a 15404",
    "addr:housenumber":"70",
    "addr:postcode":"15404",
    "addr:street":"Rua Venezuela;La Corun\u0303A",
    "iso:country":"ES",
    "sg:address":"Rua Venezuela, 70",
    "sg:city":"Ferrol",
    "sg:orig_category":"Iglesia Cat\u00d3lica",
    "sg:phone":"+34 981 32 16 04",
    "sg:postcode":"15404",
    "sg:province":"La Coru\u00f1a",
    "wof:name":"Parroquia De Santo Domingo",
    "wof:placetype":"venue"
},
  "geometry": {"coordinates":[-8.2175483704,43.4897003174],"type":"Point"}
}