{
  "type": "Feature",
  "properties": {
    "addr:full":"Calle de Mayoral, 2 Malaga M\u00e1laga 29016",
    "addr:housenumber":"2",
    "addr:postcode":"29016",
    "addr:street":"Calle De Mayoral;Ma\u0301Laga",
    "iso:country":"ES",
    "sg:address":"Calle de Mayoral, 2",
    "sg:city":"Malaga",
    "sg:orig_category":"Arquitectos",
    "sg:phone":"+34 952 21 94 24",
    "sg:postcode":"29016",
    "sg:province":"M\u00e1laga",
    "wof:name":"Hellin Armengol Carlos Ignacio",
    "wof:placetype":"venue"
},
  "geometry": {"coordinates":[-4.3965902328,36.7319908142],"type":"Point"}
}