{
  "type": "Feature",
  "properties": {
    "addr:full":"Bobila, S/n Camos Girona 17834",
    "addr:postcode":"17834",
    "addr:street":"Bobila S / N Camos",
    "iso:country":"ES",
    "sg:address":"Bobila, S/n",
    "sg:city":"Camos",
    "sg:orig_category":"Empresarios",
    "sg:phone":"+34 972 57 43 02",
    "sg:postcode":"17834",
    "sg:province":"Girona",
    "wof:name":"Planas De Palol Juan",
    "wof:placetype":"venue"
},
  "geometry": {"coordinates":[2.764480114,42.0982017517],"type":"Point"}
}