{
  "type": "Feature",
  "properties": {
    "addr:full":"Carrer de Jovellanos, 46 Sabadell Barcelona 08201",
    "addr:housenumber":"46",
    "addr:postcode":"08201",
    "addr:street":"Carrer De Jovellanos",
    "iso:country":"ES",
    "sg:address":"Carrer de Jovellanos, 46",
    "sg:city":"Sabadell",
    "sg:orig_category":"Promotores Constructores",
    "sg:phone":"+34 937 45 94 75",
    "sg:postcode":"08201",
    "sg:province":"Barcelona",
    "wof:name":"Edinfe S.l.",
    "wof:placetype":"venue"
},
  "geometry": {"coordinates":[2.1051669121,41.5487747192],"type":"Point"}
}