{
  "type": "Feature",
  "properties": {
    "iso:country":"ES",
    "sg:address":"Ctra. Chapineria-valdemorillo, 32",
    "sg:city":"Colmenar Arroyo",
    "sg:orig_category":"Semiller\u00cdas",
    "sg:phone":"+34 918 65 13 26",
    "sg:postcode":"28213",
    "sg:province":"Madrid",
    "wof:name":"Ventura Herrero Antonio",
    "wof:placetype":"venue"
},
  "geometry": {"coordinates":[-4.1977062225,40.4207878113],"type":"Point"}
}