{
  "type": "Feature",
  "properties": {
    "iso:country":"ES",
    "sg:address":"Plaz Puerta Del Sol, 7",
    "sg:city":"Madrid",
    "sg:orig_category":"Impresiones Sobre Tela",
    "sg:phone":"+34 915 22 65 25",
    "sg:postcode":"28013",
    "sg:province":"Madrid",
    "wof:name":"Sincro Digital S.l.",
    "wof:placetype":"venue"
},
  "geometry": {"coordinates":[-3.7040090561,40.4165267944],"type":"Point"}
}