{
  "type": "Feature",
  "properties": {
    "addr:full":"Alam Boulevard Del, 19 Donostia-san Sebastian Guip\u00f9zcoa 20003",
    "addr:housenumber":"19",
    "addr:postcode":"20003",
    "addr:street":"Alam Boulevard Del",
    "iso:country":"ES",
    "sg:address":"Alam Boulevard Del, 19",
    "sg:city":"Donostia-san Sebastian",
    "sg:orig_category":"Transporte En General",
    "sg:phone":"+34 943 42 07 83",
    "sg:postcode":"20003",
    "sg:province":"Guip\u00f9zcoa",
    "wof:name":"Aznar Orge Alfonso",
    "wof:placetype":"venue"
},
  "geometry": {"coordinates":[-1.9838399887,43.3218383789],"type":"Point"}
}