{
  "type": "Feature",
  "properties": {
    "iso:country":"ES",
    "sg:address":"Pl Prim, 2",
    "sg:city":"Reus",
    "sg:orig_category":"M\u00c9dicos: Otorrinolaringolog\u00cda",
    "sg:phone":"+34 977 32 37 96",
    "sg:postcode":"43201",
    "sg:province":"Tarragona",
    "wof:name":"Figuerola Masana Enrique",
    "wof:placetype":"venue"
},
  "geometry": {"coordinates":[1.1068040133,41.1563491821],"type":"Point"}
}