{
  "type": "Feature",
  "properties": {
    "addr:full":"Avda Libertad (de La), 32 Puerto De Santa Maria C\u00e1diz 11500",
    "addr:housenumber":"32",
    "addr:postcode":"11500",
    "addr:street":"Avda Libertad De La;Ca\u0301Diz",
    "iso:country":"ES",
    "sg:address":"Avda Libertad (de La), 32",
    "sg:city":"Puerto De Santa Maria",
    "sg:orig_category":"Fabricaci\u00d3n De Mobiliario Met\u00c1lico",
    "sg:phone":"+34 956 54 11 95",
    "sg:postcode":"11500",
    "sg:province":"C\u00e1diz",
    "wof:name":"La Vieja Buhardilla S.l.",
    "wof:placetype":"venue"
},
  "geometry": {"coordinates":[-6.2428689003,36.5958786011],"type":"Point"}
}