{
  "type": "Feature",
  "properties": {
    "addr:full":"Via Trajana, 48 Barcelona Barcelona 08020",
    "addr:housenumber":"48",
    "addr:postcode":"08020",
    "addr:street":"Via Trajana",
    "iso:country":"ES",
    "sg:address":"Via Trajana, 48",
    "sg:city":"Barcelona",
    "sg:orig_category":"Art\u00cdculos De Pvc (fabricaci\u00d3n Y Al Por Mayor)",
    "sg:phone":"+34 933 13 75 97",
    "sg:postcode":"08020",
    "sg:province":"Barcelona",
    "wof:name":"Plasti-frec S.l.",
    "wof:placetype":"venue"
},
  "geometry": {"coordinates":[2.2003509998,41.4287109375],"type":"Point"}
}