{
  "type": "Feature",
  "properties": {
    "addr:full":"Ctra. Nnal. Seiscientos Uno, 20 Cuellar Segovia 40200",
    "addr:housenumber":"20",
    "addr:postcode":"40200",
    "addr:street":"Ctra. Nnal.;Uno",
    "iso:country":"ES",
    "sg:address":"Ctra. Nnal. Seiscientos Uno, 20",
    "sg:city":"Cuellar",
    "sg:orig_category":"Material Y Herramientas Agr\u00cdcolas",
    "sg:phone":"+34 921 14 09 41",
    "sg:postcode":"40200",
    "sg:province":"Segovia",
    "wof:name":"Solver Agroindustrial S.l.",
    "wof:placetype":"venue"
},
  "geometry": {"coordinates":[-4.3119688034,41.4013137817],"type":"Point"}
}