{
  "type": "Feature",
  "properties": {
    "addr:full":"Calle de Fondos De Segura, 7 Palmas De Gran Canaria Las Palmas 35019",
    "addr:housenumber":"7",
    "addr:postcode":"35019",
    "addr:street":"Calle De Fondos De Segura",
    "iso:country":"ES",
    "sg:address":"Calle de Fondos De Segura, 7",
    "sg:city":"Palmas De Gran Canaria",
    "sg:orig_category":"Pintura Y Barniz (al Por Menor)",
    "sg:phone":"+34 928 41 96 13",
    "sg:postcode":"35019",
    "sg:province":"Las Palmas",
    "wof:name":"Color Y Pintura Atlantico S. L.",
    "wof:placetype":"venue"
},
  "geometry": {"coordinates":[-15.4533042908,28.1070899963],"type":"Point"}
}