{
  "type": "Feature",
  "properties": {
    "addr:full":"Plaz Ayuntamiento, 4 Linares Ja\u00e9n 23700",
    "addr:housenumber":"4",
    "addr:postcode":"23700",
    "addr:street":"Ayuntamiento;Jae\u0301N",
    "iso:country":"ES",
    "sg:address":"Plaz Ayuntamiento, 4",
    "sg:city":"Linares",
    "sg:orig_category":"Oficinas Y Gesti\u00d3n De Inmuebles",
    "sg:phone":"+34 953 65 60 83",
    "sg:postcode":"23700",
    "sg:province":"Ja\u00e9n",
    "wof:name":"Geaco C.b.",
    "wof:placetype":"venue"
},
  "geometry": {"coordinates":[-3.6354629993,38.0937347412],"type":"Point"}
}