{
  "type": "Feature",
  "properties": {
    "addr:full":"C/ Leonardo Da Vinci, S/n Cala Anguila-cala Mendia Islas Baleares 07689",
    "addr:housenumber":"s / n",
    "addr:postcode":"07689",
    "addr:street":"C / Leonardo Da Vinci;Anguila-Cala;Islas",
    "iso:country":"ES",
    "sg:address":"C/ Leonardo Da Vinci, S/n",
    "sg:city":"Cala Anguila-cala Mendia",
    "sg:orig_category":"Alquiler De Oficinas Equipadas",
    "sg:phone":"+34 971 55 83 63",
    "sg:postcode":"07689",
    "sg:province":"Islas Baleares",
    "wof:name":"Proyectos Schall Iberica S.l.",
    "wof:placetype":"venue"
},
  "geometry": {"coordinates":[3.2705500126,39.4597702026],"type":"Point"}
}