{
  "type": "Feature",
  "properties": {
    "addr:full":"Carr Napols, 33 Palamos Girona 17230",
    "addr:housenumber":"33",
    "addr:postcode":"17230",
    "addr:street":"Carr Napols",
    "iso:country":"ES",
    "sg:address":"Carr Napols, 33",
    "sg:city":"Palamos",
    "sg:orig_category":"Mec\u00c1nico Del Autom\u00d3vil",
    "sg:phone":"+34 972 31 42 91",
    "sg:postcode":"17230",
    "sg:province":"Girona",
    "wof:name":"Taller Unio Perez I Fills S.l.",
    "wof:placetype":"venue"
},
  "geometry": {"coordinates":[3.119148016,41.8519935608],"type":"Point"}
}