{
  "type": "Feature",
  "properties": {
    "addr:full":"Rai\u00f1a Dona Urraca, S/n Salvaterra Mi\u00f1o Pontevedra 36450",
    "addr:housenumber":"s / n",
    "addr:postcode":"36450",
    "iso:country":"ES",
    "sg:address":"Rai\u00f1a Dona Urraca, S/n",
    "sg:city":"Salvaterra Mi\u00f1o",
    "sg:orig_category":"Centros Empresariales",
    "sg:phone":"+34 986 65 93 70",
    "sg:postcode":"36450",
    "sg:province":"Pontevedra",
    "wof:name":"Asociacion De Comerciantes Y Empresarios De Salvaterra De Mi\u00f1o",
    "wof:placetype":"venue"
},
  "geometry": {"coordinates":[-8.497751236,42.0826721191],"type":"Point"}
}