{
  "type": "Feature",
  "properties": {
    "iso:country":"ES",
    "sg:address":"Avda Madrid (de), 10",
    "sg:city":"Jaen",
    "sg:orig_category":"Fabricaci\u00d3n, Venta, Instalaci\u00d3n De R\u00d3tulos, De R\u00d3tulos Luminosos",
    "sg:phone":"+34 953 26 46 62",
    "sg:postcode":"23003",
    "sg:province":"Ja\u00e9n",
    "wof:name":"Rotulos Ramirez S.l.",
    "wof:placetype":"venue"
},
  "geometry": {"coordinates":[-3.7862980366,37.7708282471],"type":"Point"}
}