{
  "type": "Feature",
  "properties": {
    "iso:country":"ES",
    "sg:address":"Calle de Chile, 10",
    "sg:city":"Valdemoro",
    "sg:orig_category":"Centros Empresariales",
    "sg:phone":"+34 918 08 28 53",
    "sg:postcode":"28340",
    "sg:province":"Madrid",
    "wof:name":"Pe\u00f1a&carazo S.l.",
    "wof:placetype":"venue"
},
  "geometry": {"coordinates":[-3.6871302128,40.1863594055],"type":"Point"}
}