{
  "type": "Feature",
  "properties": {
    "iso:country":"ES",
    "sg:address":"V. Del Penedes, 23",
    "sg:city":"Pla Del Bon Aire",
    "sg:orig_category":"Grafistas",
    "sg:phone":"+34 937 35 96 11",
    "sg:postcode":"08225",
    "sg:province":"Barcelona",
    "sg:website":"www.utopiag.com",
    "wof:name":"Utopia.g Disseny I Publicitat S.l.",
    "wof:placetype":"venue"
},
  "geometry": {"coordinates":[1.9797079563,41.5738563538],"type":"Point"}
}