{
  "type": "Feature",
  "properties": {
    "iso:country":"ES",
    "sg:address":"Pque Virgen Del Manzano, 24",
    "sg:city":"Burgos",
    "sg:orig_category":"Arquitectos",
    "sg:phone":"+34 947 24 30 73",
    "sg:postcode":"09004",
    "sg:province":"Burgos",
    "wof:name":"Arquitectura E Inversiones 2002 S.l.",
    "wof:placetype":"venue"
},
  "geometry": {"coordinates":[-3.6914846897,42.3431930542],"type":"Point"}
}