{
  "type": "Feature",
  "properties": {
    "addr:full":"Urb Cales Piques, S/n Cales Piques Islas Baleares 07760",
    "addr:housenumber":"s",
    "addr:postcode":"07760",
    "addr:street":"Urb Cales Piques;/ N Cales Piques",
    "iso:country":"ES",
    "sg:address":"Urb Cales Piques, S/n",
    "sg:city":"Cales Piques",
    "sg:orig_category":"Supermercados Y Hipermercados",
    "sg:phone":"+34 971 38 87 42",
    "sg:postcode":"07760",
    "sg:province":"Islas Baleares",
    "wof:name":"Hiper Centro Menorca S.l.",
    "wof:placetype":"venue"
},
  "geometry": {"coordinates":[3.7996919155,40.0072402954],"type":"Point"}
}