{
  "type": "Feature",
  "properties": {
    "iso:country":"ES",
    "sg:address":"Carrer de Diputacio, 42",
    "sg:city":"S. Celoni",
    "sg:orig_category":"Formaci\u00d3n Continuada (variada)",
    "sg:phone":"+34 938 67 15 02",
    "sg:postcode":"08470",
    "sg:province":"Barcelona",
    "wof:name":"Rocha Renau Abel",
    "wof:placetype":"venue"
},
  "geometry": {"coordinates":[2.4864499569,41.6884117126],"type":"Point"}
}