{
  "type": "Feature",
  "properties": {
    "iso:country":"ES",
    "sg:address":"Calle de Atienza, 24",
    "sg:city":"Sevilla",
    "sg:orig_category":"Empresarios",
    "sg:phone":"+34 954 38 68 13",
    "sg:postcode":"41003",
    "sg:province":"Sevilla",
    "wof:name":"Pepe Bernal S.l.",
    "wof:placetype":"venue"
},
  "geometry": {"coordinates":[-5.9934082031,37.3944396973],"type":"Point"}
}