{
  "type": "Feature",
  "properties": {
    "iso:country":"ES",
    "sg:address":"Plaz Jesus, 18",
    "sg:city":"Montijo",
    "sg:orig_category":"Comercio De Mobiliario De Oficina",
    "sg:phone":"+34 924 45 47 01",
    "sg:postcode":"06480",
    "sg:province":"Badajoz",
    "wof:name":"Muebles Y Complementos Lopez Sosa",
    "wof:placetype":"venue"
},
  "geometry": {"coordinates":[-6.6062841415,38.9077644348],"type":"Point"}
}