{
  "type": "Feature",
  "properties": {
    "iso:country":"ES",
    "sg:address":"C\u00aa Sant Feliu, 85",
    "sg:city":"Quart",
    "sg:orig_category":"Frutas, Legumbres Frescas Y Tempranas (al Por Menor)",
    "sg:phone":"+34 972 46 97 96",
    "sg:postcode":"17242",
    "sg:province":"Girona",
    "wof:name":"Fabrega Canalias Maria Dolores",
    "wof:placetype":"venue"
},
  "geometry": {"coordinates":[2.8420550823,41.9365539551],"type":"Point"}
}