{
  "type": "Feature",
  "properties": {
    "iso:country":"ES",
    "sg:address":"Calle de Santa Brigida, 5",
    "sg:city":"Salamanca",
    "sg:orig_category":"Molduras, Junquillos, Listones Y Molduras Perforadas",
    "sg:phone":"+34 923 26 63 87",
    "sg:postcode":"37008",
    "sg:province":"Salamanca",
    "wof:name":"Romero Ramos Bonifacio",
    "wof:placetype":"venue"
},
  "geometry": {"coordinates":[-5.66558218,40.9581069946],"type":"Point"}
}