{
  "type": "Feature",
  "properties": {
    "iso:country":"ES",
    "sg:address":"Avda Madrid, 84",
    "sg:city":"Le\u00f3n",
    "sg:orig_category":"Construcci\u00d3n, Importaci\u00d3n De Veh\u00cdculos",
    "sg:phone":"+34 987 34 41 23",
    "sg:postcode":"24005",
    "sg:province":"Le\u00f3n",
    "wof:name":"Wagens Sanher S.l.",
    "wof:placetype":"venue"
},
  "geometry": {"coordinates":[-5.5488409996,42.579246521],"type":"Point"}
}