{
  "type": "Feature",
  "properties": {
    "addr:full":"Carrer de M. Aurelia Capmany, 20 Castelldefels Barcelona 08860",
    "addr:housenumber":"20",
    "addr:postcode":"08860",
    "addr:street":"Carrer De M. Aurelia Capmany",
    "iso:country":"ES",
    "sg:address":"Carrer de M. Aurelia Capmany, 20",
    "sg:city":"Castelldefels",
    "sg:orig_category":"Molduras, Junquillos, Listones Y Molduras Perforadas",
    "sg:phone":"+34 936 36 08 55",
    "sg:postcode":"08860",
    "sg:province":"Barcelona",
    "wof:name":"Galisteo Ballesteros Maria",
    "wof:placetype":"venue"
},
  "geometry": {"coordinates":[1.9766249657,41.2876014709],"type":"Point"}
}