{
  "type": "Feature",
  "properties": {
    "addr:full":"Pol Carravacas, S/n Laguardia-biasteri \u00c1lava 01300",
    "addr:housenumber":"s",
    "addr:postcode":"01300",
    "addr:street":"/ N Laguardia-Biasteri A\u0301Lava",
    "iso:country":"ES",
    "sg:address":"Pol Carravacas, S/n",
    "sg:city":"Laguardia-biasteri",
    "sg:orig_category":"Panader\u00cdas, Panader\u00cdas",
    "sg:phone":"+34 945 60 08 89",
    "sg:postcode":"01300",
    "sg:province":"\u00c1lava",
    "wof:name":"Panaderia Jovi S.l.",
    "wof:placetype":"venue"
},
  "geometry": {"coordinates":[-2.5707108974,42.5471076965],"type":"Point"}
}