{
  "type": "Feature",
  "properties": {
    "addr:full":"Avda Aragon, 5 Montalban Teruel 44700",
    "addr:housenumber":"5",
    "addr:postcode":"44700",
    "addr:street":"Avda Aragon",
    "iso:country":"ES",
    "sg:address":"Avda Aragon, 5",
    "sg:city":"Montalban",
    "sg:orig_category":"Calderer\u00cda",
    "sg:phone":"+34 978 75 02 01",
    "sg:postcode":"44700",
    "sg:province":"Teruel",
    "wof:name":"Mecanicas Valero S. L.",
    "wof:placetype":"venue"
},
  "geometry": {"coordinates":[-0.7979450226,40.8311920166],"type":"Point"}
}