{
  "type": "Feature",
  "properties": {
    "iso:country":"ES",
    "sg:address":"Calle de Arca Real, 21",
    "sg:city":"Valladolid",
    "sg:orig_category":"Ense\u00d1anza, Formaci\u00d3n Profesional: Aprendizaje",
    "sg:phone":"+34 983 23 07 48",
    "sg:postcode":"47013",
    "sg:province":"Valladolid",
    "wof:name":"Hermanas De La Compa\u00f1ia De La Cruz",
    "wof:placetype":"venue"
},
  "geometry": {"coordinates":[-4.7230195999,41.6385040283],"type":"Point"}
}