{
  "type": "Feature",
  "properties": {
    "iso:country":"ES",
    "sg:address":"Calle de Carlos Hernandez, 14",
    "sg:city":"Madrid",
    "sg:orig_category":"Mensajer\u00cda Express, Portes Internacionales",
    "sg:phone":"+34 914 07 11 12",
    "sg:postcode":"28017",
    "sg:province":"Madrid",
    "wof:name":"Euroser Pack S.l.",
    "wof:placetype":"venue"
},
  "geometry": {"coordinates":[-3.6496851444,40.4304580688],"type":"Point"}
}