{
  "type": "Feature",
  "properties": {
    "addr:full":"Pasaje Las Jacarandas, 8 Pto Sta Maria C\u00e1diz 11500",
    "addr:housenumber":"8",
    "addr:postcode":"11500",
    "addr:street":"Pasaje Las Jacarandas;Ca\u0301Diz",
    "iso:country":"ES",
    "sg:address":"Pasaje Las Jacarandas, 8",
    "sg:city":"Pto Sta Maria",
    "sg:orig_category":"Plomeros",
    "sg:phone":"+34 956 85 28 37",
    "sg:postcode":"11500",
    "sg:province":"C\u00e1diz",
    "wof:name":"Lojo Lopez Daniel",
    "wof:placetype":"venue"
},
  "geometry": {"coordinates":[-6.2811789513,36.6079368591],"type":"Point"}
}