{
  "type": "Feature",
  "properties": {
    "addr:full":"Carr Codonyat, 12 Vilanova I La Geltru Barcelona 08800",
    "addr:housenumber":"12",
    "addr:postcode":"08800",
    "addr:street":"Carr Codonyat",
    "iso:country":"ES",
    "sg:address":"Carr Codonyat, 12",
    "sg:city":"Vilanova I La Geltru",
    "sg:orig_category":"Asesor\u00cdas Y Estudios Financieros",
    "sg:phone":"+34 938 16 62 62",
    "sg:postcode":"08800",
    "sg:province":"Barcelona",
    "wof:name":"Assessoria Financredit S.l.l.",
    "wof:placetype":"venue"
},
  "geometry": {"coordinates":[1.728141427,41.2224769592],"type":"Point"}
}