{
  "type": "Feature",
  "properties": {
    "addr:full":"Calle de Marques De Valdeflores, 1 Malaga M\u00e1laga 29003",
    "addr:housenumber":"1",
    "addr:postcode":"29003",
    "addr:street":"Calle De Marques De Valdeflores;Ma\u0301Laga",
    "iso:country":"ES",
    "sg:address":"Calle de Marques De Valdeflores, 1",
    "sg:city":"Malaga",
    "sg:orig_category":"Mercer\u00cda, Lencer\u00cda (al Por Menor)",
    "sg:phone":"+34 952 34 68 21",
    "sg:postcode":"29003",
    "sg:province":"M\u00e1laga",
    "wof:name":"Robles Galacho Maria Rosa",
    "wof:placetype":"venue"
},
  "geometry": {"coordinates":[-4.4403238297,36.7044067383],"type":"Point"}
}