{
  "type": "Feature",
  "properties": {
    "iso:country":"ES",
    "sg:address":"Avda Jose Rodriguez Ruano, 53",
    "sg:city":"Almansa",
    "sg:orig_category":"Electricidad: Instaladores",
    "sg:phone":"+34 967 34 24 41",
    "sg:postcode":"02640",
    "sg:province":"Albacete",
    "wof:name":"Electricidad Geva S.l.",
    "wof:placetype":"venue"
},
  "geometry": {"coordinates":[-1.0930160284,38.8698005676],"type":"Point"}
}