{
  "type": "Feature",
  "properties": {
    "iso:country":"ES",
    "sg:address":"Calle de Molinazo, 21",
    "sg:city":"Cella",
    "sg:orig_category":"Promotores Constructores",
    "sg:phone":"+34 978 65 03 61",
    "sg:postcode":"44370",
    "sg:province":"Teruel",
    "wof:name":"Elena Lorente Juan",
    "wof:placetype":"venue"
},
  "geometry": {"coordinates":[-1.283239007,40.4487686157],"type":"Point"}
}