{
  "type": "Feature",
  "properties": {
    "iso:country":"ES",
    "sg:address":"Carrer de Eduard Brossa, 6",
    "sg:city":"Sabadell",
    "sg:orig_category":"Restaurantes",
    "sg:phone":"+34 937 12 39 34",
    "sg:postcode":"08204",
    "sg:province":"Barcelona",
    "wof:name":"Gutierrez Manzano Maria Del Carmen",
    "wof:placetype":"venue"
},
  "geometry": {"coordinates":[2.1154069901,41.52684021],"type":"Point"}
}