{
  "type": "Feature",
  "properties": {
    "addr:full":"Calle de Naves, 15 Madrid Madrid 28005",
    "addr:housenumber":"15",
    "addr:postcode":"madrid;28005",
    "addr:street":"Calle De Naves",
    "iso:country":"ES",
    "sg:address":"Calle de Naves, 15",
    "sg:city":"Madrid",
    "sg:orig_category":"Asesor\u00cda Fiscal Y Jur\u00cddica",
    "sg:phone":"+34 915 17 83 71",
    "sg:postcode":"28005",
    "sg:province":"Madrid",
    "wof:name":"Felylay S.l.",
    "wof:placetype":"venue"
},
  "geometry": {"coordinates":[-3.706897974,40.3981666565],"type":"Point"}
}