{
  "type": "Feature",
  "properties": {
    "iso:country":"ES",
    "sg:address":"Calle de Virgen De La Soledad, 9",
    "sg:city":"Guadalajara",
    "sg:orig_category":"Farmacias",
    "sg:phone":"+34 949 22 81 48",
    "sg:postcode":"19003",
    "sg:province":"Guadalajara",
    "wof:name":"Farmacia Luis Y Mercedes Navarro C.b.",
    "wof:placetype":"venue"
},
  "geometry": {"coordinates":[-3.1657021046,40.628276825],"type":"Point"}
}