{
  "type": "Feature",
  "properties": {
    "addr:full":"Carrer de Manila, 51 Barcelona Barcelona 08034",
    "addr:housenumber":"51",
    "addr:postcode":"08034",
    "addr:street":"Carrer De Manila",
    "iso:country":"ES",
    "sg:address":"Carrer de Manila, 51",
    "sg:city":"Barcelona",
    "sg:orig_category":"Panader\u00cdas, Panader\u00cdas",
    "sg:phone":"+34 932 03 67 63",
    "sg:postcode":"08034",
    "sg:province":"Barcelona",
    "wof:name":"Torremade Font Jose",
    "wof:placetype":"venue"
},
  "geometry": {"coordinates":[2.1258890629,41.390083313],"type":"Point"}
}