{
  "type": "Feature",
  "properties": {
    "iso:country":"ES",
    "sg:address":"Carrer de Cigne, 2",
    "sg:city":"Barcelona",
    "sg:orig_category":"Bisuter\u00cda, Joyer\u00cda, Relojer\u00cda (al Por Menor)",
    "sg:phone":"+34 932 18 70 13",
    "sg:postcode":"08012",
    "sg:province":"Barcelona",
    "wof:name":"Cantarell Farres Dolors",
    "wof:placetype":"venue"
},
  "geometry": {"coordinates":[2.1541030407,41.4008293152],"type":"Point"}
}