{
  "type": "Feature",
  "properties": {
    "addr:full":"Rua Xunqueira (a), S/n Vilagarcia Pontevedra 36600",
    "addr:housenumber":"s / n",
    "addr:postcode":"36600",
    "addr:street":"Rua Xunqueira A",
    "iso:country":"ES",
    "sg:address":"Rua Xunqueira (a), S/n",
    "sg:city":"Vilagarcia",
    "sg:orig_category":"Librer\u00cdas",
    "sg:phone":"+34 986 50 69 96",
    "sg:postcode":"36600",
    "sg:province":"Pontevedra",
    "wof:name":"Marilo Galicia S.l.",
    "wof:placetype":"venue"
},
  "geometry": {"coordinates":[-8.7652978897,42.5917396545],"type":"Point"}
}