{
  "type": "Feature",
  "properties": {
    "addr:full":"Calle de Vasco Nu\u00d1ez, 10 Badajoz Badajoz 06001",
    "addr:housenumber":"10",
    "addr:postcode":"06001",
    "addr:street":"Calle De Vasco Nun\u0303Ez",
    "iso:country":"ES",
    "sg:address":"Calle de Vasco Nu\u00d1ez, 10",
    "sg:city":"Badajoz",
    "sg:orig_category":"Estancos",
    "sg:phone":"+34 924 22 05 57",
    "sg:postcode":"06001",
    "sg:province":"Badajoz",
    "wof:name":"Fernandez Almazan Alejandro",
    "wof:placetype":"venue"
},
  "geometry": {"coordinates":[-6.9738359451,38.8778762817],"type":"Point"}
}