{
  "type": "Feature",
  "properties": {
    "iso:country":"ES",
    "sg:address":"Avda Alcalde Gines De La Hoz, S/n",
    "sg:city":"Arrecife",
    "sg:orig_category":"Zapatos (al Por Menor)",
    "sg:phone":"+34 928 80 11 24",
    "sg:postcode":"35500",
    "sg:province":"Las Palmas",
    "wof:name":"T-shirt Lanzarote S.cv",
    "wof:placetype":"venue"
},
  "geometry": {"coordinates":[-13.5564041138,28.9679450989],"type":"Point"}
}