{
  "type": "Feature",
  "properties": {
    "addr:full":"Avda Malvarrosa, 71 Valencia Valencia 46011",
    "addr:housenumber":"71",
    "addr:postcode":"46011",
    "addr:street":"Avda Malvarrosa",
    "iso:country":"ES",
    "sg:address":"Avda Malvarrosa, 71",
    "sg:city":"Valencia",
    "sg:orig_category":"Confecci\u00d3n (fabricaci\u00d3n, Al Por Mayor)",
    "sg:phone":"+34 963 55 60 11",
    "sg:postcode":"46011",
    "sg:province":"Valencia",
    "wof:name":"Garcia Encuentra Jesus",
    "wof:placetype":"venue"
},
  "geometry": {"coordinates":[-0.3281680048,39.4801445007],"type":"Point"}
}