{
  "type": "Feature",
  "properties": {
    "addr:full":"Calle de Doctor Lopez Pe\u00d1a, 10 Huetor-tajar Granada 18360",
    "addr:housenumber":"10",
    "addr:postcode":"18360",
    "addr:street":"Calle De Doctor Lopez Pen\u0303A",
    "iso:country":"ES",
    "sg:address":"Calle de Doctor Lopez Pe\u00d1a, 10",
    "sg:city":"Huetor-tajar",
    "sg:orig_category":"Fabricaci\u00d3n De Muebles",
    "sg:phone":"+34 958 33 41 47",
    "sg:postcode":"18360",
    "sg:province":"Granada",
    "wof:name":"Decoracion Santa Maria 2000 S.l.",
    "wof:placetype":"venue"
},
  "geometry": {"coordinates":[-4.0461788177,37.1940841675],"type":"Point"}
}