{
  "type": "Feature",
  "properties": {
    "iso:country":"ES",
    "sg:address":"Calle de Doctor Antonio Manzanares, S/n",
    "sg:city":"Cordoba",
    "sg:orig_category":"Armas Y Municiones (fabricaci\u00d3n, Al Por Mayor)",
    "sg:phone":"+34 957 25 60 78",
    "sg:postcode":"14014",
    "sg:province":"C\u00f3rdoba",
    "wof:name":"Armeria Millan",
    "wof:placetype":"venue"
},
  "geometry": {"coordinates":[-4.7641339302,37.8987007141],"type":"Point"}
}