{
  "type": "Feature",
  "properties": {
    "iso:country":"ES",
    "sg:address":"Calle de Lagasca, 27",
    "sg:city":"Madrid",
    "sg:orig_category":"Importaci\u00d3n",
    "sg:phone":"+34 914 35 44 65",
    "sg:postcode":"28001",
    "sg:province":"Madrid",
    "wof:name":"Fundacion Para La Juventud",
    "wof:placetype":"venue"
},
  "geometry": {"coordinates":[-3.6856451035,40.424571991],"type":"Point"}
}