{
  "type": "Feature",
  "properties": {
    "addr:full":"Carrer de Fusina, 13 Vic Barcelona 08500",
    "addr:housenumber":"13",
    "addr:postcode":"08500",
    "addr:street":"Carrer De Fusina",
    "iso:country":"ES",
    "sg:address":"Carrer de Fusina, 13",
    "sg:city":"Vic",
    "sg:orig_category":"Zapatos (al Por Menor)",
    "sg:phone":"+34 938 86 14 60",
    "sg:postcode":"08500",
    "sg:province":"Barcelona",
    "wof:name":"Miralles Grau Joan",
    "wof:placetype":"venue"
},
  "geometry": {"coordinates":[2.2575139999,41.9307746887],"type":"Point"}
}