{
  "type": "Feature",
  "properties": {
    "addr:full":"Calle de Cruzada, 3 Madrid Madrid 28013",
    "addr:housenumber":"3",
    "addr:postcode":"28013",
    "addr:street":"Calle De Cruzada",
    "iso:country":"ES",
    "sg:address":"Calle de Cruzada, 3",
    "sg:city":"Madrid",
    "sg:orig_category":"Venta, Alquiler De Instrumentos Y Accesorios De M\u00dasica",
    "sg:phone":"+34 915 41 42 03",
    "sg:postcode":"28013",
    "sg:province":"Madrid",
    "wof:name":"Mundimusica S.l.",
    "wof:placetype":"venue"
},
  "geometry": {"coordinates":[-3.7114868164,40.4164161682],"type":"Point"}
}