{
  "type": "Feature",
  "properties": {
    "addr:full":"Calle de Grama, 24 Madrid Madrid 28050",
    "addr:housenumber":"24",
    "addr:postcode":"madrid;28050",
    "addr:street":"Calle De Grama",
    "iso:country":"ES",
    "sg:address":"Calle de Grama, 24",
    "sg:city":"Madrid",
    "sg:orig_category":"Promotores Constructores",
    "sg:phone":"+34 913 82 05 68",
    "sg:postcode":"28050",
    "sg:province":"Madrid",
    "wof:name":"Promociones Grama 24 S.l.",
    "wof:placetype":"venue"
},
  "geometry": {"coordinates":[-3.6281039715,40.4771766663],"type":"Point"}
}