{
  "type": "Feature",
  "properties": {
    "addr:full":"Calle de Presa (de La), 38 San Fernando De Henares Madrid 28830",
    "addr:housenumber":"38",
    "addr:postcode":"28830",
    "addr:street":"Calle De Presa De La",
    "iso:country":"ES",
    "sg:address":"Calle de Presa (de La), 38",
    "sg:city":"San Fernando De Henares",
    "sg:orig_category":"Farmacias",
    "sg:phone":"+34 916 71 24 22",
    "sg:postcode":"28830",
    "sg:province":"Madrid",
    "wof:name":"Lopez Esteban Maria Aranzazu",
    "wof:placetype":"venue"
},
  "geometry": {"coordinates":[-3.5288119316,40.428527832],"type":"Point"}
}