{
  "type": "Feature",
  "properties": {
    "iso:country":"ES",
    "sg:address":"Carrer de Espronceda, 180",
    "sg:city":"Barcelona",
    "sg:orig_category":"Aparatos De Medida, Control, Regulaci\u00d3n Y Detecci\u00d3n",
    "sg:phone":"+34 933 08 69 93",
    "sg:postcode":"08018",
    "sg:province":"Barcelona",
    "wof:name":"Utiltall S. A.",
    "wof:placetype":"venue"
},
  "geometry": {"coordinates":[2.1991360188,41.4097175598],"type":"Point"}
}