{
  "type": "Feature",
  "properties": {
    "addr:full":"Calle de Jose Antonio Noguera Gil, 13 Aguilas Murcia 30880",
    "addr:housenumber":"13",
    "addr:postcode":"30880",
    "addr:street":"Calle De Jose Antonio Noguera Gil",
    "iso:country":"ES",
    "sg:address":"Calle de Jose Antonio Noguera Gil, 13",
    "sg:city":"Aguilas",
    "sg:classifiers":[
        {
            "category":"Autos & Motor Vehicles",
            "subcategory":"Automobile Sales",
            "type":"Retail Goods"
        }
    ],
    "sg:phone":"+34 968 44 79 18",
    "sg:postcode":"30880",
    "sg:province":"Murcia",
    "wof:name":"Belmonte Garcia Bartolome",
    "wof:placetype":"venue"
},
  "geometry": {"coordinates":[-1.5849649906,37.4075546265],"type":"Point"}
}