{
  "type": "Feature",
  "properties": {
    "addr:full":"Avda Virgen De Lidon, 4 Castellon Castell\u00f3n 12003",
    "addr:housenumber":"4",
    "addr:postcode":"12003",
    "addr:street":"Avda Virgen De Lidon;Castello\u0301N",
    "iso:country":"ES",
    "sg:address":"Avda Virgen De Lidon, 4",
    "sg:city":"Castellon",
    "sg:orig_category":"Lencer\u00cda Femenina, Corseter\u00cda, Trajes De Ba\u00d1o (al Por Menor)",
    "sg:phone":"+34 964 23 78 55",
    "sg:postcode":"12003",
    "sg:province":"Castell\u00f3n",
    "wof:name":"Alfredo Monfort S.a.",
    "wof:placetype":"venue"
},
  "geometry": {"coordinates":[-0.0340038985,39.9890632629],"type":"Point"}
}