{
  "type": "Feature",
  "properties": {
    "addr:full":"Calle de Fuentelarreina, 22 Zamora Zamora 49023",
    "addr:housenumber":"22",
    "addr:postcode":"49023",
    "addr:street":"Calle De Fuentelarreina",
    "iso:country":"ES",
    "sg:address":"Calle de Fuentelarreina, 22",
    "sg:city":"Zamora",
    "sg:orig_category":"Chapister\u00cda",
    "sg:phone":"+34 980 52 97 62",
    "sg:postcode":"49023",
    "sg:province":"Zamora",
    "wof:name":"Calvo Nu\u00f1ez Ramon",
    "wof:placetype":"venue"
},
  "geometry": {"coordinates":[-5.7624387741,41.539440155],"type":"Point"}
}