{
  "type": "Feature",
  "properties": {
    "addr:full":"Plaz Juan Xxiii, 69 Oliva Frontera Badajoz 06120",
    "addr:housenumber":"69",
    "addr:postcode":"06120",
    "addr:street":"Plaz Juan Xxiii",
    "iso:country":"ES",
    "sg:address":"Plaz Juan Xxiii, 69",
    "sg:city":"Oliva Frontera",
    "sg:orig_category":"Herramientas Y Suministros Para Plomeros",
    "sg:phone":"+34 924 75 42 56",
    "sg:postcode":"06120",
    "sg:province":"Badajoz",
    "wof:name":"Vellarino Rastrojo Jose Luis",
    "wof:placetype":"venue"
},
  "geometry": {"coordinates":[-6.9155139923,38.2829017639],"type":"Point"}
}