{
  "type": "Feature",
  "properties": {
    "iso:country":"ES",
    "sg:address":"Berlin(p I Mas De Tous), 19",
    "sg:city":"Pobla Vallbona",
    "sg:orig_category":"Negocio De Materiales De Construcci\u00d3n",
    "sg:phone":"+34 962 76 31 42",
    "sg:postcode":"46185",
    "sg:province":"Valencia",
    "wof:name":"Garcopanel S.l.",
    "wof:placetype":"venue"
},
  "geometry": {"coordinates":[-0.5386559963,39.5909614563],"type":"Point"}
}