{
  "type": "Feature",
  "properties": {
    "iso:country":"ES",
    "sg:address":"Rua Peregrina (da), 14",
    "sg:city":"Pontevedra",
    "sg:orig_category":"Zapatos (al Por Menor)",
    "sg:phone":"+34 986 85 30 52",
    "sg:postcode":"36001",
    "sg:province":"Pontevedra",
    "wof:name":"Fernandez Otero Jose Joaquin",
    "wof:placetype":"venue"
},
  "geometry": {"coordinates":[-8.6437768936,42.4301986694],"type":"Point"}
}