{
  "type": "Feature",
  "properties": {
    "iso:country":"ES",
    "sg:address":"Cllo Bouza, 2",
    "sg:city":"Santa Cruz De Tenerife",
    "sg:orig_category":"Ingenier\u00cda, Centros De Estudios (diversos)",
    "sg:phone":"+34 922 27 67 10",
    "sg:postcode":"38002",
    "sg:province":"Santa Cruz De Tenerife",
    "sg:website":"www.irciterra.com",
    "wof:name":"Irciterra Ingenieria Y Recursos De La Tierra S.l.",
    "wof:placetype":"venue"
},
  "geometry": {"coordinates":[-17.2191944122,28.1820106506],"type":"Point"}
}