{
  "type": "Feature",
  "properties": {
    "addr:full":"C/ Violeta, 6 Torrellano Alicante 03320",
    "addr:housenumber":"6",
    "addr:postcode":"03320",
    "addr:street":"C / Violeta",
    "iso:country":"ES",
    "sg:address":"C/ Violeta, 6",
    "sg:city":"Torrellano",
    "sg:orig_category":"Empresas De Carpinter\u00cda",
    "sg:phone":"+34 965 68 07 27",
    "sg:postcode":"03320",
    "sg:province":"Alicante",
    "wof:name":"Aluminios Torrealum S.l.",
    "wof:placetype":"venue"
},
  "geometry": {"coordinates":[-0.5880457759,38.2924957275],"type":"Point"}
}