{
  "type": "Feature",
  "properties": {
    "addr:full":"Calle de Nardo (del), 17 Alcobendas Madrid 28109",
    "addr:postcode":"28109",
    "addr:street":"Calle De Nardo Del;Alcobendas",
    "iso:country":"ES",
    "sg:address":"Calle de Nardo (del), 17",
    "sg:city":"Alcobendas",
    "sg:orig_category":"Sociedades, Compa\u00d1\u00cdas Aseguradoras",
    "sg:phone":"+34 916 50 16 79",
    "sg:postcode":"28109",
    "sg:province":"Madrid",
    "wof:name":"Salus Agrupadas S.l.",
    "wof:placetype":"venue"
},
  "geometry": {"coordinates":[-3.6372671127,40.5288238525],"type":"Point"}
}