{
  "type": "Feature",
  "properties": {
    "addr:full":"Calle de San Pedro Martir, 34 Granada Granada 18009",
    "addr:housenumber":"34",
    "addr:postcode":"18009",
    "addr:street":"Calle De San Pedro Martir",
    "iso:country":"ES",
    "sg:address":"Calle de San Pedro Martir, 34",
    "sg:city":"Granada",
    "sg:orig_category":"Albergues",
    "sg:phone":"+34 958 22 87 93",
    "sg:postcode":"18009",
    "sg:province":"Granada",
    "wof:name":"Alvarez Martin Juan",
    "wof:placetype":"venue"
},
  "geometry": {"coordinates":[-3.5959796906,37.1702346802],"type":"Point"}
}