{
  "type": "Feature",
  "properties": {
    "addr:full":"Calle de Arapiles, 22 Almeria Almer\u00eda 04001",
    "addr:housenumber":"22",
    "addr:postcode":"04001",
    "addr:street":"Calle De Arapiles",
    "iso:country":"ES",
    "sg:address":"Calle de Arapiles, 22",
    "sg:city":"Almeria",
    "sg:orig_category":"Procuradores",
    "sg:phone":"+34 950 23 07 74",
    "sg:postcode":"04001",
    "sg:province":"Almer\u00eda",
    "wof:name":"Soler Pareja Carmen",
    "wof:placetype":"venue"
},
  "geometry": {"coordinates":[-2.4642059803,36.8353996277],"type":"Point"}
}