{
  "type": "Feature",
  "properties": {
    "addr:full":"Calle de Guillermo Mesa (de), Km. 0003,3 El Cruce Madrid 28860",
    "addr:postcode":"28860",
    "addr:street":"Calle De Guillermo Mesa De Km. 0003,3",
    "iso:country":"ES",
    "sg:address":"Calle de Guillermo Mesa (de), Km. 0003,3",
    "sg:city":"El Cruce",
    "sg:orig_category":"Alquiler De Muebles",
    "sg:phone":"+34 916 58 04 01",
    "sg:postcode":"28860",
    "sg:province":"Madrid",
    "sg:website":"www.strasserstand.com",
    "wof:name":"Estructuras Strasser S.l.",
    "wof:placetype":"venue"
},
  "geometry": {"coordinates":[-3.5296940804,40.5049209595],"type":"Point"}
}