{
  "type": "Feature",
  "properties": {
    "iso:country":"ES",
    "sg:address":"Carrer de Pau Casals, 34",
    "sg:city":"Cambrils",
    "sg:orig_category":"Ropa Para Se\u00d1oras (al Por Menor)",
    "sg:phone":"+34 977 36 19 88",
    "sg:postcode":"43850",
    "sg:province":"Tarragona",
    "wof:name":"Hardouin  Robert",
    "wof:placetype":"venue"
},
  "geometry": {"coordinates":[1.0622260571,41.0666885376],"type":"Point"}
}