{
  "type": "Feature",
  "properties": {
    "addr:full":"Os Mui\u00f1os, 2 Mui\u00d1os Pontevedra 36157",
    "addr:housenumber":"2",
    "addr:postcode":"36157",
    "addr:street":"Muin\u0303Os",
    "iso:country":"ES",
    "sg:address":"Os Mui\u00f1os, 2",
    "sg:city":"Mui\u00d1os",
    "sg:orig_category":"Empresas De Carpinter\u00cda De Madera",
    "sg:phone":"+34 986 87 01 92",
    "sg:postcode":"36157",
    "sg:province":"Pontevedra",
    "wof:name":"Corredoira Villaverde Jose Ramon",
    "wof:placetype":"venue"
},
  "geometry": {"coordinates":[-8.6582126617,42.4889144897],"type":"Point"}
}