{
  "type": "Feature",
  "properties": {
    "addr:full":"Kale Nagusia, 25 Astigarraga Guip\u00f9zcoa 20115",
    "addr:housenumber":"25",
    "addr:postcode":"20115",
    "addr:street":"Kale Nagusia;Guipu\u0300Zcoa",
    "iso:country":"ES",
    "sg:address":"Kale Nagusia, 25",
    "sg:city":"Astigarraga",
    "sg:orig_category":"Cajas De Ahorro",
    "sg:phone":"+34 943 33 14 72",
    "sg:postcode":"20115",
    "sg:province":"Guip\u00f9zcoa",
    "wof:name":"Caja Laboral Popular",
    "wof:placetype":"venue"
},
  "geometry": {"coordinates":[-1.9507540464,43.2802085876],"type":"Point"}
}