{
  "type": "Feature",
  "properties": {
    "addr:full":"Calle de Cordoba, 1 Castro Rio C\u00f3rdoba 14840",
    "addr:housenumber":"1",
    "addr:postcode":"14840",
    "addr:street":"Calle De Cordoba;Rio Co\u0301Rdoba",
    "iso:country":"ES",
    "sg:address":"Calle de Cordoba, 1",
    "sg:city":"Castro Rio",
    "sg:orig_category":"Cajas De Ahorro",
    "sg:phone":"+34 957 37 02 26",
    "sg:postcode":"14840",
    "sg:province":"C\u00f3rdoba",
    "sg:website":"www.cajasur.es",
    "wof:name":"Caja De Ahorros Y Monte De Piedad De Cordoba",
    "wof:placetype":"venue"
},
  "geometry": {"coordinates":[-4.4836587906,37.68983078],"type":"Point"}
}