{
  "type": "Feature",
  "properties": {
    "iso:country":"ES",
    "sg:address":"Calle de Virgen De La Pe\u00d1a, 13",
    "sg:city":"Pto. Rosario",
    "sg:orig_category":"Ropa Para Se\u00d1oras (al Por Menor)",
    "sg:phone":"+34 928 85 22 80",
    "sg:postcode":"35600",
    "sg:province":"Las Palmas",
    "wof:name":"Sandalo S.c.p",
    "wof:placetype":"venue"
},
  "geometry": {"coordinates":[-13.8658781052,28.5000324249],"type":"Point"}
}