{
  "type": "Feature",
  "properties": {
    "addr:full":"Plaz Carlos Castel, 26 Teruel Teruel 44001",
    "addr:postcode":"26;44001",
    "addr:street":"Castel",
    "iso:country":"ES",
    "sg:address":"Plaz Carlos Castel, 26",
    "sg:city":"Teruel",
    "sg:orig_category":"Bancos",
    "sg:phone":"+34 978 61 73 33",
    "sg:postcode":"44001",
    "sg:province":"Teruel",
    "sg:website":"www.bancozaragozano.es",
    "wof:name":"Barclays Bank S.a.e.",
    "wof:placetype":"venue"
},
  "geometry": {"coordinates":[-1.1045490503,40.3420944214],"type":"Point"}
}