{
  "type": "Feature",
  "properties": {
    "iso:country":"ES",
    "sg:address":"Plaz Jose Bermudez De La Rubia, S/n",
    "sg:city":"Coin",
    "sg:orig_category":"\u00d3ptica: Instrumentos (fabricaci\u00d3n)",
    "sg:phone":"+34 952 45 14 05",
    "sg:postcode":"29100",
    "sg:province":"M\u00e1laga",
    "wof:name":"Enriquez Llagas Salvador",
    "wof:placetype":"venue"
},
  "geometry": {"coordinates":[-4.7590789795,36.659576416],"type":"Point"}
}