{
  "type": "Feature",
  "properties": {
    "addr:full":"Pg Estacio De L', 30 Valls Tarragona 43800",
    "addr:housenumber":"30",
    "addr:postcode":"43800",
    "addr:street":"Pg Estacio De L '",
    "iso:country":"ES",
    "sg:address":"Pg Estacio De L', 30",
    "sg:city":"Valls",
    "sg:orig_category":"Frutas, Legumbres Frescas Y Tempranas (al Por Menor)",
    "sg:phone":"+34 977 61 38 78",
    "sg:postcode":"43800",
    "sg:province":"Tarragona",
    "wof:name":"Barrios Manso Dolors",
    "wof:placetype":"venue"
},
  "geometry": {"coordinates":[1.2525299788,41.2871513367],"type":"Point"}
}