{
  "type": "Feature",
  "properties": {
    "iso:country":"ES",
    "sg:address":"Ctra Logro\u00d1o, 1",
    "sg:city":"Briones",
    "sg:orig_category":"Ense\u00d1anza, Formaci\u00d3n Profesional: Aprendizaje",
    "sg:phone":"+34 941 32 21 92",
    "sg:postcode":"26330",
    "sg:province":"La Rioja",
    "wof:name":"Ayuntamiento De Briones",
    "wof:placetype":"venue"
},
  "geometry": {"coordinates":[-2.7864160538,42.5427017212],"type":"Point"}
}