{
  "type": "Feature",
  "properties": {
    "addr:full":"Cra. Lleida, Km. 0128,1 Seu Urgell Lleida 25700",
    "addr:postcode":"25700",
    "addr:street":"Lleida Km. 0128,1",
    "iso:country":"ES",
    "sg:address":"Cra. Lleida, Km. 0128,1",
    "sg:city":"Seu Urgell",
    "sg:orig_category":"Cer\u00c1micas: Material Y Suministros",
    "sg:phone":"+34 973 35 08 66",
    "sg:postcode":"25700",
    "sg:province":"Lleida",
    "wof:name":"Materials Alt Urgell S.l.",
    "wof:placetype":"venue"
},
  "geometry": {"coordinates":[1.4592299461,42.3578453064],"type":"Point"}
}