{
  "type": "Feature",
  "properties": {
    "iso:country":"ES",
    "sg:address":"Avda Richard Yeoward, 9",
    "sg:city":"Botanico",
    "sg:orig_category":"Asesor\u00cda De Formaci\u00d3n Y Gesti\u00d3n De Personal",
    "sg:phone":"+34 922 37 50 30",
    "sg:postcode":"38400",
    "sg:province":"Santa Cruz De Tenerife",
    "wof:name":"Aslanorte S.l.",
    "wof:placetype":"venue"
},
  "geometry": {"coordinates":[-16.2548561096,28.4698104858],"type":"Point"}
}