{
  "type": "Feature",
  "properties": {
    "addr:full":"Avda Cesar Augusto, 35 Zaragoza Zaragoza 50004",
    "addr:housenumber":"35",
    "addr:postcode":"50004",
    "addr:street":"Avda Cesar Augusto",
    "iso:country":"ES",
    "sg:address":"Avda Cesar Augusto, 35",
    "sg:city":"Zaragoza",
    "sg:orig_category":"Internados & Ense\u00d1anza Privada",
    "sg:phone":"+34 976 44 51 54",
    "sg:postcode":"50004",
    "sg:province":"Zaragoza",
    "wof:name":"Escolapios Escuelas Pias De Aragon Curia Provincial",
    "wof:placetype":"venue"
},
  "geometry": {"coordinates":[-0.8843140006,41.6539039612],"type":"Point"}
}