{
  "type": "Feature",
  "properties": {
    "iso:country":"ES",
    "sg:address":"Calle de Dendari Kalea, 1",
    "sg:city":"Lekeitio",
    "sg:orig_category":"Carnicer\u00cdas, Carnicer\u00cdas",
    "sg:phone":"+34 946 84 04 06",
    "sg:postcode":"48280",
    "sg:province":"Vizcaya",
    "wof:name":"Juan Tomas Goikoetxea Leniz",
    "wof:placetype":"venue"
},
  "geometry": {"coordinates":[-2.5040855408,43.3634300232],"type":"Point"}
}