{
  "type": "Feature",
  "properties": {
    "addr:full":"Calle de Calvario, 14 Madrid Madrid 28012",
    "addr:housenumber":"14",
    "addr:postcode":"madrid;28012",
    "addr:street":"Calle De Calvario",
    "iso:country":"ES",
    "sg:address":"Calle de Calvario, 14",
    "sg:city":"Madrid",
    "sg:orig_category":"Ense\u00d1anza Industrial Y T\u00c9cnica",
    "sg:phone":"+34 915 28 30 24",
    "sg:postcode":"28012",
    "sg:province":"Madrid",
    "wof:name":"Cincomas Music S.l.",
    "wof:placetype":"venue"
},
  "geometry": {"coordinates":[-3.7021028996,40.4114875793],"type":"Point"}
}