{
  "type": "Feature",
  "properties": {
    "iso:country":"ES",
    "sg:address":"Avda Ejercito Espa\u00d1ol, 10",
    "sg:city":"Ceuta",
    "sg:orig_category":"Farmacias",
    "sg:phone":"+34 956 50 30 54",
    "sg:postcode":"51002",
    "sg:province":"Ceuta",
    "wof:name":"Farmacion Lobato C.b.",
    "wof:placetype":"venue"
},
  "geometry": {"coordinates":[-5.330095768,35.8897972107],"type":"Point"}
}