{
  "type": "Feature",
  "properties": {
    "addr:full":"Pg Pins, 47 Sant Feliu Llobregat Barcelona 08980",
    "addr:housenumber":"47",
    "addr:postcode":"08980",
    "addr:street":"Pg Pins",
    "iso:country":"ES",
    "sg:address":"Pg Pins, 47",
    "sg:city":"Sant Feliu Llobregat",
    "sg:orig_category":"Alquiler De V\u00cddeo",
    "sg:phone":"+34 936 66 45 67",
    "sg:postcode":"08980",
    "sg:province":"Barcelona",
    "wof:name":"Sant Feliu Video Digital, S.l.",
    "wof:placetype":"venue"
},
  "geometry": {"coordinates":[2.0422708988,41.3840141296],"type":"Point"}
}