{
  "type": "Feature",
  "properties": {
    "iso:country":"ES",
    "sg:address":"Avda Nuestra Se\u00d1ora De Las Guias, 3",
    "sg:city":"Malaga",
    "sg:orig_category":"Agencias Y Agentes Comerciales, Representantes",
    "sg:phone":"+34 952 25 70 37",
    "sg:postcode":"29014",
    "sg:province":"M\u00e1laga",
    "wof:name":"Laplana Fajula Jorge",
    "wof:placetype":"venue"
},
  "geometry": {"coordinates":[-4.4215011597,36.73853302],"type":"Point"}
}