{
  "type": "Feature",
  "properties": {
    "iso:country":"ES",
    "sg:address":"Calle de Segundo Izpizua, 14",
    "sg:city":"Donostia-san Sebastian",
    "sg:orig_category":"Agentes, Concesionarios Y Sucursales De Veh\u00cdculos",
    "sg:phone":"+34 943 32 72 56",
    "sg:postcode":"20001",
    "sg:province":"Guip\u00f9zcoa",
    "wof:name":"Automotor Bikar S.a.",
    "wof:placetype":"venue"
},
  "geometry": {"coordinates":[-1.9713225365,43.3248901367],"type":"Point"}
}