{
  "type": "Feature",
  "properties": {
    "addr:full":"Plaz Maestro Quislant, 6 Santa Pola Alicante 03130",
    "addr:housenumber":"6",
    "addr:postcode":"03130",
    "addr:street":"Plaz;Quislant",
    "iso:country":"ES",
    "sg:address":"Plaz Maestro Quislant, 6",
    "sg:city":"Santa Pola",
    "sg:orig_category":"Laboratorios Y Trabajos De Fotograf\u00cda, V\u00cddeo Y Cine",
    "sg:phone":"+34 965 41 41 08",
    "sg:postcode":"03130",
    "sg:province":"Alicante",
    "wof:name":"Uglietta Catalano Philippe",
    "wof:placetype":"venue"
},
  "geometry": {"coordinates":[-0.555685997,38.1934432983],"type":"Point"}
}