{
  "type": "Feature",
  "properties": {
    "addr:full":"Calle de Pedro Requena, 25 Petrer Alicante 03610",
    "addr:housenumber":"25",
    "addr:postcode":"03610",
    "addr:street":"Calle De Pedro Requena",
    "iso:country":"ES",
    "sg:address":"Calle de Pedro Requena, 25",
    "sg:city":"Petrer",
    "sg:orig_category":"Art\u00cdculos De Regalo (al Por Menor)",
    "sg:phone":"+34 965 37 12 46",
    "sg:postcode":"03610",
    "sg:province":"Alicante",
    "wof:name":"Tortosa Poveda Julia",
    "wof:placetype":"venue"
},
  "geometry": {"coordinates":[-0.7712159753,38.4832839966],"type":"Point"}
}