{
  "type": "Feature",
  "properties": {
    "iso:country":"ES",
    "sg:address":"Calle de Irala, 11",
    "sg:city":"Bilbao",
    "sg:orig_category":"Cristaler\u00cdas",
    "sg:phone":"+34 944 10 29 69",
    "sg:postcode":"48012",
    "sg:province":"Vizcaya",
    "wof:name":"Blanco Olabarrieta Francisco Javier",
    "wof:placetype":"venue"
},
  "geometry": {"coordinates":[-2.9358689785,43.2553977966],"type":"Point"}
}