{
  "type": "Feature",
  "properties": {
    "iso:country":"ES",
    "sg:address":"Calle de Hermana Matilde, 37",
    "sg:city":"Cari\u00f1ena",
    "sg:orig_category":"Electricidad: Instalaciones Industriales",
    "sg:phone":"+34 976 62 20 64",
    "sg:postcode":"50400",
    "sg:province":"Zaragoza",
    "wof:name":"Electricidad Lorente Y Serrano S.l.",
    "wof:placetype":"venue"
},
  "geometry": {"coordinates":[-1.2264490128,41.3375205994],"type":"Point"}
}