{
  "type": "Feature",
  "properties": {
    "addr:full":"Calle de Viriato, 114 Pto. Rosario Las Palmas 35600",
    "addr:housenumber":"114",
    "addr:postcode":"35600",
    "addr:street":"Calle De Viriato;Pto. Rosario Las",
    "iso:country":"ES",
    "sg:address":"Calle de Viriato, 114",
    "sg:city":"Pto. Rosario",
    "sg:orig_category":"Promotores Constructores",
    "sg:phone":"+34 928 53 20 51",
    "sg:postcode":"35600",
    "sg:province":"Las Palmas",
    "wof:name":"Obras Y Construcciones Del Archipielago S.l.",
    "wof:placetype":"venue"
},
  "geometry": {"coordinates":[-13.8476848602,28.5040836334],"type":"Point"}
}