{
  "type": "Feature",
  "properties": {
    "addr:full":"Calle de Gondola, 15 Palmones C\u00e1diz 11379",
    "addr:housenumber":"15",
    "addr:postcode":"11379",
    "addr:street":"Calle De Gondola;Ca\u0301Diz",
    "iso:country":"ES",
    "sg:address":"Calle de Gondola, 15",
    "sg:city":"Palmones",
    "sg:orig_category":"Molduras, Junquillos, Listones Y Molduras Perforadas",
    "sg:phone":"+34 956 67 66 37",
    "sg:postcode":"11379",
    "sg:province":"C\u00e1diz",
    "wof:name":"Sistelcom-telemensaje S.a.",
    "wof:placetype":"venue"
},
  "geometry": {"coordinates":[-5.437579155,36.1809005737],"type":"Point"}
}