{
  "type": "Feature",
  "properties": {
    "iso:country":"ES",
    "sg:address":"Carr Palleter (el), 13",
    "sg:city":"Benetusser",
    "sg:orig_category":"Imprenta",
    "sg:phone":"+34 963 75 59 19",
    "sg:postcode":"46910",
    "sg:province":"Valencia",
    "wof:name":"Imprenta Aitana S.l",
    "wof:placetype":"venue"
},
  "geometry": {"coordinates":[-0.3985640109,39.4212265015],"type":"Point"}
}