{
  "type": "Feature",
  "properties": {
    "iso:country":"ES",
    "sg:address":"Avda Constitucion, 29",
    "sg:city":"Aljucer",
    "sg:orig_category":"Guarder\u00cdas",
    "sg:phone":"+34 968 34 61 05",
    "sg:postcode":"30152",
    "sg:province":"Murcia",
    "wof:name":"Pujante Barqueros Soledad",
    "wof:placetype":"venue"
},
  "geometry": {"coordinates":[-1.1546000242,37.9594535828],"type":"Point"}
}