{
  "type": "Feature",
  "properties": {
    "iso:country":"ES",
    "sg:address":"Avda Costa, 6",
    "sg:city":"Gijon",
    "sg:orig_category":"Abogados",
    "sg:phone":"+34 985 35 14 08",
    "sg:postcode":"33207",
    "sg:province":"Asturias",
    "wof:name":"Gonzalez Fernandez Ricardo",
    "wof:placetype":"venue"
},
  "geometry": {"coordinates":[-5.6649727821,43.5378341675],"type":"Point"}
}