{
  "type": "Feature",
  "properties": {
    "addr:full":"Ptge Vicent Martin, 13 Barcelona Barcelona 08028",
    "addr:housenumber":"13",
    "addr:postcode":"08028",
    "addr:street":"Ptge Vicent Martin",
    "iso:country":"ES",
    "sg:address":"Ptge Vicent Martin, 13",
    "sg:city":"Barcelona",
    "sg:orig_category":"Centros Empresariales",
    "sg:phone":"+34 934 47 04 64",
    "sg:postcode":"08028",
    "sg:province":"Barcelona",
    "wof:name":"Serlima S.a.",
    "wof:placetype":"venue"
},
  "geometry": {"coordinates":[2.1152598858,41.3769798279],"type":"Point"}
}