{
  "type": "Feature",
  "properties": {
    "iso:country":"ES",
    "sg:address":"Calle de Suecia (de), 3",
    "sg:city":"Fuenlabrada",
    "sg:orig_category":"Molduras, Junquillos, Listones Y Molduras Perforadas",
    "sg:phone":"+34 916 08 41 02",
    "sg:postcode":"28942",
    "sg:province":"Madrid",
    "wof:name":"Diez Cha\u00f1ez Jesus",
    "wof:placetype":"venue"
},
  "geometry": {"coordinates":[-3.8082959652,40.2899398804],"type":"Point"}
}