{
  "type": "Feature",
  "properties": {
    "iso:country":"ES",
    "sg:address":"Rbla Don Diego, 4",
    "sg:city":"Alhama Murcia",
    "sg:orig_category":"Empresas De Portes Y Mensajer\u00cda",
    "sg:phone":"+34 968 63 30 48",
    "sg:postcode":"30840",
    "sg:province":"Murcia",
    "wof:name":"Lapt Courrier S.l.",
    "wof:placetype":"venue"
},
  "geometry": {"coordinates":[-1.4241490364,37.8507995605],"type":"Point"}
}