{
  "type": "Feature",
  "properties": {
    "iso:country":"ES",
    "sg:address":"Av Rei Jaume I, 84",
    "sg:city":"Santa Pon\u00c7a",
    "sg:orig_category":"Restaurantes",
    "sg:phone":"+34 971 69 02 66",
    "sg:postcode":"07180",
    "sg:province":"Islas Baleares",
    "wof:name":"Lambry  Daniel",
    "wof:placetype":"venue"
},
  "geometry": {"coordinates":[2.4792010784,39.513343811],"type":"Point"}
}