{
  "type": "Feature",
  "properties": {
    "addr:full":"Pla\u00c7 Rafael Atard, 24 Manises Valencia 46940",
    "addr:housenumber":"24",
    "addr:postcode":"46940",
    "addr:street":"Rafael Atard",
    "iso:country":"ES",
    "sg:address":"Pla\u00c7 Rafael Atard, 24",
    "sg:city":"Manises",
    "sg:orig_category":"Notarios",
    "sg:phone":"+34 961 52 36 90",
    "sg:postcode":"46940",
    "sg:province":"Valencia",
    "wof:name":"Moreno Betoret Salvador",
    "wof:placetype":"venue"
},
  "geometry": {"coordinates":[-0.4662519991,39.4951286316],"type":"Point"}
}