{
  "type": "Feature",
  "properties": {
    "iso:country":"ES",
    "sg:address":"Calle de Constitucion, 16",
    "sg:city":"Paiporta",
    "sg:orig_category":"Loter\u00cda Y T\u00d3mbola",
    "sg:phone":"+34 963 97 07 01",
    "sg:postcode":"46200",
    "sg:province":"Valencia",
    "wof:name":"Martinez Buen Jose Maria",
    "wof:placetype":"venue"
},
  "geometry": {"coordinates":[-0.4177354872,39.4277687073],"type":"Point"}
}