{
  "type": "Feature",
  "properties": {
    "addr:full":"Carrer de Pius Xii, 5 Granollers Barcelona 08401",
    "addr:housenumber":"5",
    "addr:postcode":"08401",
    "addr:street":"Carrer De Pius Xii",
    "iso:country":"ES",
    "sg:address":"Carrer de Pius Xii, 5",
    "sg:city":"Granollers",
    "sg:orig_category":"Sindicatos De Trabajadores",
    "sg:phone":"+34 938 60 19 40",
    "sg:postcode":"08401",
    "sg:province":"Barcelona",
    "wof:name":"Comision Obrera De Catalunya",
    "wof:placetype":"venue"
},
  "geometry": {"coordinates":[2.2817349434,41.6062011719],"type":"Point"}
}