{
  "type": "Feature",
  "properties": {
    "iso:country":"ES",
    "sg:address":"Carrer de Camp, 34",
    "sg:city":"Barcelona",
    "sg:orig_category":"Multimedia: Servicios En L\u00cdnea, Acceso En L\u00cdnea, Cd",
    "sg:phone":"+34 934 18 02 07",
    "sg:postcode":"08022",
    "sg:province":"Barcelona",
    "sg:website":"www.workbtec.com",
    "wof:name":"Workbtec Multimedia Projects S.l.",
    "wof:placetype":"venue"
},
  "geometry": {"coordinates":[2.1371090412,41.4026489258],"type":"Point"}
}