{
  "type": "Feature",
  "properties": {
    "iso:country":"ES",
    "sg:address":"Huerto Del Marques, S/n",
    "sg:city":"Cox",
    "sg:orig_category":"Frutas Y Legumbres Secas (al Por Mayor)",
    "sg:phone":"+34 965 36 06 38",
    "sg:postcode":"03350",
    "sg:province":"Alicante",
    "wof:name":"Fulleda Mo\u00f1ino Rafael",
    "wof:placetype":"venue"
},
  "geometry": {"coordinates":[-0.8880140185,38.1392059326],"type":"Point"}
}