{
  "type": "Feature",
  "properties": {
    "addr:full":"Calle de Leon Xiii, 36 Hinojosa Del Duque C\u00f3rdoba 14270",
    "addr:housenumber":"36",
    "addr:postcode":"14270",
    "addr:street":"Calle De Leon Xiii;Co\u0301Rdoba",
    "iso:country":"ES",
    "sg:address":"Calle de Leon Xiii, 36",
    "sg:city":"Hinojosa Del Duque",
    "sg:orig_category":"Reposter\u00cdas",
    "sg:phone":"+34 957 14 00 19",
    "sg:postcode":"14270",
    "sg:province":"C\u00f3rdoba",
    "wof:name":"Almansa Mu\u00f1oz Juan",
    "wof:placetype":"venue"
},
  "geometry": {"coordinates":[-5.151968956,38.5038452148],"type":"Point"}
}