{
  "type": "Feature",
  "properties": {
    "iso:country":"ES",
    "sg:address":"Carrer de Arago, 187",
    "sg:city":"Palma",
    "sg:orig_category":"Agencias De Viajes",
    "sg:phone":"+34 971 44 42 44",
    "sg:postcode":"07005",
    "sg:province":"Islas Baleares",
    "wof:name":"Viajes Sirius Tours S.a.",
    "wof:placetype":"venue"
},
  "geometry": {"coordinates":[2.6688899994,39.5828094482],"type":"Point"}
}