{
  "type": "Feature",
  "properties": {
    "addr:full":"Carrer de Crom, 57 Femades Barcelona 08940",
    "addr:housenumber":"57",
    "addr:postcode":"08940",
    "addr:street":"Carrer De Crom;Barcelona",
    "iso:country":"ES",
    "sg:address":"Carrer de Crom, 57",
    "sg:city":"Femades",
    "sg:orig_category":"Farmacias",
    "sg:phone":"+34 933 77 09 79",
    "sg:postcode":"08940",
    "sg:province":"Barcelona",
    "wof:name":"Pares Lucini Juan",
    "wof:placetype":"venue"
},
  "geometry": {"coordinates":[2.0740599632,41.356880188],"type":"Point"}
}