{
  "type": "Feature",
  "properties": {
    "iso:country":"ES",
    "sg:address":"Ctra. Granada-dilar, S/n",
    "sg:city":"Ogijares",
    "sg:orig_category":"Charcuter\u00cdas (al Por Mayor)",
    "sg:phone":"+34 958 50 83 87",
    "sg:postcode":"18151",
    "sg:province":"Granada",
    "wof:name":"Arnes Alonso Manuel",
    "wof:placetype":"venue"
},
  "geometry": {"coordinates":[-3.6305556297,37.1118125916],"type":"Point"}
}