{
  "type": "Feature",
  "properties": {
    "addr:full":"Calle de Camino Isla, 5 Gibraleon Huelva 21500",
    "addr:housenumber":"5",
    "addr:postcode":"21500",
    "addr:street":"Calle De Camino Isla",
    "iso:country":"ES",
    "sg:address":"Calle de Camino Isla, 5",
    "sg:city":"Gibraleon",
    "sg:orig_category":"Contenedores (mercanc\u00cdas)",
    "sg:phone":"+34 959 30 14 89",
    "sg:postcode":"21500",
    "sg:province":"Huelva",
    "wof:name":"Peancar S L",
    "wof:placetype":"venue"
},
  "geometry": {"coordinates":[-6.9714975357,37.374130249],"type":"Point"}
}