{
  "type": "Feature",
  "properties": {
    "iso:country":"ES",
    "sg:address":"Calle de Don Jaime I, 11",
    "sg:city":"Zaragoza",
    "sg:orig_category":"Loter\u00cda Y T\u00d3mbola",
    "sg:phone":"+34 976 39 54 87",
    "sg:postcode":"50003",
    "sg:province":"Zaragoza",
    "sg:website":"www.elgordo.com",
    "wof:name":"Aznar Villagrasa Alejandro",
    "wof:placetype":"venue"
},
  "geometry": {"coordinates":[-0.8793461919,41.6525268555],"type":"Point"}
}