{
  "type": "Feature",
  "properties": {
    "iso:country":"ES",
    "sg:address":"Calle de Mayor, 46",
    "sg:city":"Alumbres",
    "sg:orig_category":"Comerciantes Al Por Mayor De Vinos, Licores Y Alcoholes",
    "sg:phone":"+34 968 55 23 26",
    "sg:postcode":"30351",
    "sg:province":"Murcia",
    "wof:name":"Bodega Bar Hermanos Velasco S.l.",
    "wof:placetype":"venue"
},
  "geometry": {"coordinates":[-0.9150329828,37.6038551331],"type":"Point"}
}