{
  "type": "Feature",
  "properties": {
    "addr:full":"Avda Oporto, 21 Madrid Madrid 28019",
    "addr:housenumber":"21",
    "addr:postcode":"madrid;28019",
    "addr:street":"Avda Oporto",
    "iso:country":"ES",
    "sg:address":"Avda Oporto, 21",
    "sg:city":"Madrid",
    "sg:orig_category":"Agencias De Viajes",
    "sg:phone":"+34 914 69 55 43",
    "sg:postcode":"28019",
    "sg:province":"Madrid",
    "wof:name":"Lope Becerra Blanca",
    "wof:placetype":"venue"
},
  "geometry": {"coordinates":[-3.7229549885,40.3851852417],"type":"Point"}
}