{
  "type": "Feature",
  "properties": {
    "iso:country":"ES",
    "sg:address":"Uztarroz, 13",
    "sg:city":"Iru\u00f1a",
    "sg:orig_category":"Agencias Y Agentes Comerciales, Representantes",
    "sg:phone":"+34 948 14 07 74",
    "sg:postcode":"31014",
    "sg:province":"Navarra",
    "wof:name":"Diarte Corcin Jose Maria",
    "wof:placetype":"venue"
},
  "geometry": {"coordinates":[-1.6496039629,42.8261566162],"type":"Point"}
}