{
  "type": "Feature",
  "properties": {
    "addr:full":"Avda Sierra Nevada, 2 Cenes Vega Granada 18190",
    "addr:housenumber":"2",
    "addr:postcode":"18190",
    "addr:street":"Avda Sierra Nevada",
    "iso:country":"ES",
    "sg:address":"Avda Sierra Nevada, 2",
    "sg:city":"Cenes Vega",
    "sg:orig_category":"Gu\u00cdas De Monta\u00d1a, Monitores De Esqu\u00cd, Acompa\u00d1antes En Monta\u00d1a",
    "sg:phone":"+34 958 48 95 07",
    "sg:postcode":"18190",
    "sg:province":"Granada",
    "wof:name":"Escuela Granadina De Esqui Y Snow S.l.",
    "wof:placetype":"venue"
},
  "geometry": {"coordinates":[-3.5423738956,37.1603355408],"type":"Point"}
}