{
  "type": "Feature",
  "properties": {
    "iso:country":"ES",
    "sg:address":"Calle de San Marcos, 62",
    "sg:city":"Guadix",
    "sg:orig_category":"Reposter\u00cdas",
    "sg:phone":"+34 958 66 02 42",
    "sg:postcode":"18500",
    "sg:province":"Granada",
    "wof:name":"Perez Gonzalez Antonio",
    "wof:placetype":"venue"
},
  "geometry": {"coordinates":[-3.1353490353,37.2952003479],"type":"Point"}
}