{
  "type": "Feature",
  "properties": {
    "iso:country":"ES",
    "sg:address":"Calle de Nueva, 9",
    "sg:city":"San Pablo De Los Montes",
    "sg:orig_category":"Peluquer\u00cdas, Peluquer\u00cda Mixta",
    "sg:phone":"+34 925 41 54 69",
    "sg:postcode":"45120",
    "sg:province":"Toledo",
    "wof:name":"Lancha Herrera Maria De Gracia",
    "wof:placetype":"venue"
},
  "geometry": {"coordinates":[-4.3302650452,39.5398902893],"type":"Point"}
}