{
  "type": "Feature",
  "properties": {
    "iso:country":"ES",
    "sg:address":"Calle de Bocangel, 4",
    "sg:city":"Madrid",
    "sg:orig_category":"M\u00c9dicos: Medicina General Orientada A La Acupuntura",
    "sg:phone":"+34 913 61 38 29",
    "sg:postcode":"28028",
    "sg:province":"Madrid",
    "wof:name":"Martin Gutierrez Marino",
    "wof:placetype":"venue"
},
  "geometry": {"coordinates":[-3.6641905308,40.4298171997],"type":"Point"}
}