{
  "type": "Feature",
  "properties": {
    "addr:full":"Calle de Uranio, S/n Aimayr Madrid 28320",
    "addr:housenumber":"s / n",
    "addr:postcode":"28320",
    "addr:street":"Calle De Uranio",
    "iso:country":"ES",
    "sg:address":"Calle de Uranio, S/n",
    "sg:city":"Aimayr",
    "sg:orig_category":"Fabricaci\u00d3n De Moldes Y Modelos",
    "sg:phone":"+34 916 91 76 40",
    "sg:postcode":"28320",
    "sg:province":"Madrid",
    "wof:name":"Desarrollos Y Fabricacion D Y F S.a.",
    "wof:placetype":"venue"
},
  "geometry": {"coordinates":[-3.640805006,40.2337989807],"type":"Point"}
}