{
  "type": "Feature",
  "properties": {
    "addr:full":"Oasis San Antonio, 3 Los Cancajos Santa Cruz De Tenerife 38712",
    "addr:housenumber":"3",
    "addr:postcode":"38712",
    "addr:street":"San Antonio;Los Cancajos",
    "iso:country":"ES",
    "sg:address":"Oasis San Antonio, 3",
    "sg:city":"Los Cancajos",
    "sg:orig_category":"Asociaciones Y Clubs Deportivos",
    "sg:phone":"+34 922 43 47 54",
    "sg:postcode":"38712",
    "sg:province":"Santa Cruz De Tenerife",
    "wof:name":"Hernandez Cabrera Pedro",
    "wof:placetype":"venue"
},
  "geometry": {"coordinates":[-17.7672138214,28.6476554871],"type":"Point"}
}