{
  "type": "Feature",
  "properties": {
    "iso:country":"ES",
    "sg:address":"Calle de San Pantaleon, 52",
    "sg:city":"Porzuna",
    "sg:orig_category":"Promotores Constructores",
    "sg:phone":"+34 926 78 11 40",
    "sg:postcode":"13120",
    "sg:province":"Ciudad Real",
    "wof:name":"Rodriguez Mendoza Martin",
    "wof:placetype":"venue"
},
  "geometry": {"coordinates":[-4.1585302353,39.1507377625],"type":"Point"}
}