{
  "type": "Feature",
  "properties": {
    "addr:full":"Calle de Magdalena, 18 Madrid Madrid 28012",
    "addr:housenumber":"18",
    "addr:postcode":"madrid;28012",
    "addr:street":"Calle De Magdalena",
    "iso:country":"ES",
    "sg:address":"Calle de Magdalena, 18",
    "sg:city":"Madrid",
    "sg:orig_category":"Bazares, Art\u00cdculos De Limpieza Y De Cocina (al Por Menor)",
    "sg:phone":"+34 914 20 38 94",
    "sg:postcode":"28012",
    "sg:province":"Madrid",
    "wof:name":"Orient Star",
    "wof:placetype":"venue"
},
  "geometry": {"coordinates":[-3.7013440132,40.4122200012],"type":"Point"}
}