{
  "type": "Feature",
  "properties": {
    "iso:country":"ES",
    "sg:address":"Nafarroa Kalea, 21",
    "sg:city":"Zarautz",
    "sg:orig_category":"Plomeros",
    "sg:phone":"+34 943 83 34 97",
    "sg:postcode":"20800",
    "sg:province":"Guip\u00f9zcoa",
    "wof:name":"Larra\u00f1aga Berraondo German",
    "wof:placetype":"venue"
},
  "geometry": {"coordinates":[-2.1700510979,43.2861785889],"type":"Point"}
}