{
  "type": "Feature",
  "properties": {
    "iso:country":"ES",
    "sg:address":"Rua San Pedro, 4",
    "sg:city":"Monforte De Lemos",
    "sg:orig_category":"Ense\u00d1anza, Formaci\u00d3n Profesional: Aprendizaje",
    "sg:phone":"+34 982 41 13 00",
    "sg:postcode":"27400",
    "sg:province":"Lugo",
    "wof:name":"Instituto Nacional De La Seguridad Social-direccion Provincial De Lugo",
    "wof:placetype":"venue"
},
  "geometry": {"coordinates":[-7.5082798004,42.526714325],"type":"Point"}
}