{
  "type": "Feature",
  "properties": {
    "iso:country":"ES",
    "sg:address":"Carr Anselm Clave, 27",
    "sg:city":"Santa Margarida De Montbui A-antiguo",
    "sg:orig_category":"Jardiner\u00cdas, Vegetales, Art\u00cdculos De Jardiner\u00cda (al Por Menor)",
    "sg:phone":"+34 938 05 49 81",
    "sg:postcode":"08710",
    "sg:province":"Barcelona",
    "wof:name":"Moix Vilanova Jose",
    "wof:placetype":"venue"
},
  "geometry": {"coordinates":[1.605404973,41.5578384399],"type":"Point"}
}