{
  "type": "Feature",
  "properties": {
    "iso:country":"ES",
    "sg:address":"C/ Sant Mateu, 1",
    "sg:city":"Alcoi",
    "sg:orig_category":"Iglesia Cat\u00d3lica",
    "sg:phone":"+34 965 54 31 08",
    "sg:postcode":"03801",
    "sg:province":"Alicante",
    "wof:name":"Parroquia De San Mauro Y San Francisco",
    "wof:placetype":"venue"
},
  "geometry": {"coordinates":[-0.4744189978,38.6951141357],"type":"Point"}
}