{
  "type": "Feature",
  "properties": {
    "iso:country":"ES",
    "sg:address":"Calle de Tucidides, S/n",
    "sg:city":"Malaga",
    "sg:orig_category":"Electrodom\u00c9sticos (fabricaci\u00d3n, Al Por Mayor)",
    "sg:phone":"+34 952 10 55 77",
    "sg:postcode":"29004",
    "sg:province":"M\u00e1laga",
    "sg:website":"www.urende.es",
    "wof:name":"Urende S.a.",
    "wof:placetype":"venue"
},
  "geometry": {"coordinates":[-4.460914135,36.6940078735],"type":"Point"}
}