{
  "type": "Feature",
  "properties": {
    "addr:full":"Calle de Pe\u00d1a Gorbea, 2 Madrid Madrid 28053",
    "addr:housenumber":"2",
    "addr:postcode":"28053",
    "addr:street":"Calle De Pen\u0303A Gorbea",
    "iso:country":"ES",
    "sg:address":"Calle de Pe\u00d1a Gorbea, 2",
    "sg:city":"Madrid",
    "sg:orig_category":"Grafistas",
    "sg:phone":"+34 914 78 58 67",
    "sg:postcode":"28053",
    "sg:province":"Madrid",
    "sg:website":"www.aci.es",
    "wof:name":"Arte Comunicacion E Ideas",
    "wof:placetype":"venue"
},
  "geometry": {"coordinates":[-3.6681408882,40.3957862854],"type":"Point"}
}