{
  "type": "Feature",
  "properties": {
    "iso:country":"ES",
    "sg:address":"Av Isidor Macabich, S/n",
    "sg:city":"S. Antoni Portmany",
    "sg:orig_category":"Estancos",
    "sg:phone":"+34 971 34 42 62",
    "sg:postcode":"07820",
    "sg:province":"Islas Baleares",
    "wof:name":"Planells Ripoll Francisco",
    "wof:placetype":"venue"
},
  "geometry": {"coordinates":[1.2984650135,38.9825286865],"type":"Point"}
}