{
  "type": "Feature",
  "properties": {
    "iso:country":"ES",
    "sg:address":"Avda Torres Bellas, S/n",
    "sg:city":"Alcorcon",
    "sg:orig_category":"Farmacias",
    "sg:phone":"+34 916 19 30 91",
    "sg:postcode":"28923",
    "sg:province":"Madrid",
    "wof:name":"Vidal Alvarez Maria Teresa",
    "wof:placetype":"venue"
},
  "geometry": {"coordinates":[-3.8208398819,40.3465843201],"type":"Point"}
}