{
  "type": "Feature",
  "properties": {
    "iso:country":"ES",
    "sg:address":"Av Rei Jaume I, 22",
    "sg:city":"Benidorm",
    "sg:orig_category":"Inmobiliaria (agencias)",
    "sg:phone":"+34 965 85 63 21",
    "sg:postcode":"03500",
    "sg:province":"Alicante",
    "sg:website":"www.benidormweb.com",
    "wof:name":"Fincas Lainen S.l.",
    "wof:placetype":"venue"
},
  "geometry": {"coordinates":[-0.1358889937,38.5389671326],"type":"Point"}
}