{
  "type": "Feature",
  "properties": {
    "addr:full":"Calle de Chimidas, 38 Playa Honda Las Palmas 35509",
    "addr:housenumber":"38",
    "addr:postcode":"35509",
    "addr:street":"Calle De Chimidas",
    "iso:country":"ES",
    "sg:address":"Calle de Chimidas, 38",
    "sg:city":"Playa Honda",
    "sg:orig_category":"Peluquer\u00cdas, Peluquer\u00cda Mixta",
    "sg:phone":"+34 928 82 30 71",
    "sg:postcode":"35509",
    "sg:province":"Las Palmas",
    "wof:name":"Gonzalez Espinosa Maria Esmeralda",
    "wof:placetype":"venue"
},
  "geometry": {"coordinates":[-13.5917158127,28.9558792114],"type":"Point"}
}