{
  "type": "Feature",
  "properties": {
    "iso:country":"ES",
    "sg:address":"Calle de Tomas Nougues, 4",
    "sg:city":"Teruel",
    "sg:orig_category":"Abogados",
    "sg:phone":"+34 978 60 09 93",
    "sg:postcode":"44001",
    "sg:province":"Teruel",
    "wof:name":"Consultoria Integral De Teruel S.l.",
    "wof:placetype":"venue"
},
  "geometry": {"coordinates":[-1.1068470478,40.3419036865],"type":"Point"}
}