{
  "type": "Feature",
  "properties": {
    "addr:full":"P. Garcia De Najera, 2 Iru\u00f1a Navarra 31008",
    "addr:housenumber":"2",
    "addr:postcode":"31008",
    "addr:street":"P. Garcia De Najera",
    "iso:country":"ES",
    "sg:address":"P. Garcia De Najera, 2",
    "sg:city":"Iru\u00f1a",
    "sg:classifiers":[
        {
            "category":"Banks & Credit Unions",
            "subcategory":"Bureau De Change",
            "type":"Services"
        }
    ],
    "sg:phone":"+34 948 19 71 62",
    "sg:postcode":"31008",
    "sg:province":"Navarra",
    "sg:tags":[
        "organismos",
        "control"
    ],
    "sg:website":"www.sgs.es",
    "wof:name":"Sgs Tecnos S.a.",
    "wof:placetype":"venue"
},
  "geometry": {"coordinates":[-1.6601779461,42.8098068237],"type":"Point"}
}