{
  "type": "Feature",
  "properties": {
    "addr:full":"Calle de Americas (de Las), 7 Coslada Madrid 28820",
    "addr:housenumber":"7",
    "addr:postcode":"28820",
    "addr:street":"Calle De Americas De Las",
    "iso:country":"ES",
    "sg:address":"Calle de Americas (de Las), 7",
    "sg:city":"Coslada",
    "sg:orig_category":"Material Y Suministros Para Imprenta E Industrias Gr\u00c1ficas",
    "sg:phone":"+34 916 73 33 58",
    "sg:postcode":"28820",
    "sg:province":"Madrid",
    "wof:name":"Imprenta Raga S.l.",
    "wof:placetype":"venue"
},
  "geometry": {"coordinates":[-3.5301504135,40.433681488],"type":"Point"}
}