{
  "type": "Feature",
  "properties": {
    "addr:full":"Carr Roi\u00c7 De Corella, 8 Gandia Valencia 46700",
    "addr:housenumber":"8",
    "addr:postcode":"46700",
    "addr:street":"Carr Roic\u0327 De Corella;Valencia",
    "iso:country":"ES",
    "sg:address":"Carr Roi\u00c7 De Corella, 8",
    "sg:city":"Gandia",
    "sg:orig_category":"Asociaciones Y Clubs Deportivos",
    "sg:phone":"+34 962 96 15 95",
    "sg:postcode":"46700",
    "sg:province":"Valencia",
    "wof:name":"Sabater Santonja Luis Miguel",
    "wof:placetype":"venue"
},
  "geometry": {"coordinates":[-0.1913339943,38.960735321],"type":"Point"}
}