{
  "type": "Feature",
  "properties": {
    "addr:full":"Avda Padre Huidobro, Km. 0014,0 Madrid Madrid 28023",
    "addr:postcode":"28023",
    "addr:street":"Avda Padre Huidobro Km. 0014,0",
    "iso:country":"ES",
    "sg:address":"Avda Padre Huidobro, Km. 0014,0",
    "sg:city":"Madrid",
    "sg:orig_category":"Asociaciones Y Clubs Deportivos",
    "sg:phone":"+34 913 72 88 58",
    "sg:postcode":"28023",
    "sg:province":"Madrid",
    "wof:name":"Club K-2",
    "wof:placetype":"venue"
},
  "geometry": {"coordinates":[-3.7598800659,40.4611663818],"type":"Point"}
}