{
  "type": "Feature",
  "properties": {
    "iso:country":"ES",
    "sg:address":"Pol. Sta. Rita-casta\u00f1era, S/n",
    "sg:city":"Cuadrove\u00f1a",
    "sg:orig_category":"Cerrajer\u00cda, Ferrallista",
    "sg:phone":"+34 985 84 11 23",
    "sg:postcode":"33540",
    "sg:province":"Asturias",
    "wof:name":"Perez Freije Luis",
    "wof:placetype":"venue"
},
  "geometry": {"coordinates":[-5.1852741241,43.3902168274],"type":"Point"}
}