{
  "type": "Feature",
  "properties": {
    "iso:country":"ES",
    "sg:address":"Rbla Hospital, 3",
    "sg:city":"Vic",
    "sg:orig_category":"Cl\u00cdnicas Dentales",
    "sg:phone":"+34 938 81 43 50",
    "sg:postcode":"08500",
    "sg:province":"Barcelona",
    "wof:name":"Dentalmar Vic S.l.",
    "wof:placetype":"venue"
},
  "geometry": {"coordinates":[2.2530150414,41.9298973083],"type":"Point"}
}