{
  "type": "Feature",
  "properties": {
    "addr:full":"Calle de Zaragoza, 11 Maella Zaragoza 50710",
    "addr:housenumber":"11",
    "addr:postcode":"50710",
    "addr:street":"Calle De Zaragoza",
    "iso:country":"ES",
    "sg:address":"Calle de Zaragoza, 11",
    "sg:city":"Maella",
    "sg:orig_category":"Supermercados Y Hipermercados",
    "sg:phone":"+34 976 63 82 23",
    "sg:postcode":"50710",
    "sg:province":"Zaragoza",
    "wof:name":"Falgas La Cueva.s:l",
    "wof:placetype":"venue"
},
  "geometry": {"coordinates":[0.1375569999,41.1232261658],"type":"Point"}
}