{
  "type": "Feature",
  "properties": {
    "iso:country":"ES",
    "sg:address":"Avda Jose Quintana, 2",
    "sg:city":"Salda\u00f1a",
    "sg:orig_category":"Cajas Para Embalar",
    "sg:phone":"+34 979 89 12 00",
    "sg:postcode":"34100",
    "sg:province":"Palencia",
    "wof:name":"Caja Rural Del Duero",
    "wof:placetype":"venue"
},
  "geometry": {"coordinates":[-4.73726511,42.5221366882],"type":"Point"}
}