{
  "type": "Feature",
  "properties": {
    "iso:country":"ES",
    "sg:address":"Calle de Bonifacio Obispo, 1",
    "sg:city":"Osuna",
    "sg:orig_category":"Material Y Herramientas Agr\u00cdcolas",
    "sg:phone":"+34 954 81 11 81",
    "sg:postcode":"41640",
    "sg:province":"Sevilla",
    "wof:name":"Mecanizacion Agricola Del Sur S. L.",
    "wof:placetype":"venue"
},
  "geometry": {"coordinates":[-5.1109986305,37.2382049561],"type":"Point"}
}