{
  "type": "Feature",
  "properties": {
    "iso:country":"ES",
    "sg:address":"Plaz Victorio Macho, 1",
    "sg:city":"Toledo",
    "sg:orig_category":"Ense\u00d1anza, Formaci\u00d3n Profesional: Aprendizaje",
    "sg:phone":"+34 925 21 63 55",
    "sg:postcode":"45002",
    "sg:province":"Toledo",
    "wof:name":"Diputacion Provincial De Toledo-deportes",
    "wof:placetype":"venue"
},
  "geometry": {"coordinates":[-4.0298237801,39.8555717468],"type":"Point"}
}