{
  "type": "Feature",
  "properties": {
    "iso:country":"ES",
    "sg:address":"Calle de Azahar, 2",
    "sg:city":"Alcala Henares",
    "sg:orig_category":"Centros Empresariales",
    "sg:phone":"+34 918 83 15 96",
    "sg:postcode":"28803",
    "sg:province":"Madrid",
    "wof:name":"Servicios Fupesa S.l.",
    "wof:placetype":"venue"
},
  "geometry": {"coordinates":[-3.3706519604,40.4734458923],"type":"Point"}
}