{
  "type": "Feature",
  "properties": {
    "addr:full":"Calle de Mariano Jose De Larra, 18 Merida Badajoz 06800",
    "addr:housenumber":"18",
    "addr:postcode":"06800",
    "addr:street":"Calle De Mariano Jose De Larra",
    "iso:country":"ES",
    "sg:address":"Calle de Mariano Jose De Larra, 18",
    "sg:city":"Merida",
    "sg:classifiers":[
        {
            "category":"Taxi",
            "type":"Transportation"
        }
    ],
    "sg:phone":"+34 924 31 09 84",
    "sg:postcode":"06800",
    "sg:province":"Badajoz",
    "wof:name":"Ugalde Cordero Jose Francisco",
    "wof:placetype":"venue"
},
  "geometry": {"coordinates":[-6.3394365311,38.9178314209],"type":"Point"}
}