{
  "type": "Feature",
  "properties": {
    "addr:full":"Calle de Altozano, 5 Sanlucar Mayor Sevilla 41800",
    "addr:housenumber":"5",
    "addr:postcode":"41800",
    "addr:street":"Calle De Altozano",
    "iso:country":"ES",
    "sg:address":"Calle de Altozano, 5",
    "sg:city":"Sanlucar Mayor",
    "sg:orig_category":"Pintura Y Barniz (al Por Menor)",
    "sg:phone":"+34 955 70 13 14",
    "sg:postcode":"41800",
    "sg:province":"Sevilla",
    "wof:name":"Antonio Mu\u00f1oz Camero S. A.",
    "wof:placetype":"venue"
},
  "geometry": {"coordinates":[-6.203751564,37.3866767883],"type":"Point"}
}