{
  "type": "Feature",
  "properties": {
    "addr:full":"Rua Cami\u00d1o Real (do), S/n Lugo Lugo 27004",
    "addr:housenumber":"s / n",
    "addr:postcode":"27004",
    "addr:street":"Rua Camin\u0303O",
    "iso:country":"ES",
    "sg:address":"Rua Cami\u00d1o Real (do), S/n",
    "sg:city":"Lugo",
    "sg:orig_category":"Librer\u00cdas",
    "sg:phone":"+34 982 21 31 90",
    "sg:postcode":"27004",
    "sg:province":"Lugo",
    "wof:name":"Nu\u00f1ez Astariz Carmen",
    "wof:placetype":"venue"
},
  "geometry": {"coordinates":[-7.562953949,43.0167503357],"type":"Point"}
}