{
  "type": "Feature",
  "properties": {
    "iso:country":"ES",
    "sg:address":"Avda Ciudad De Barcelona, 53",
    "sg:city":"Madrid",
    "sg:orig_category":"Publicidad (soportes Y Gesti\u00d3n)",
    "sg:phone":"+34 914 34 09 39",
    "sg:postcode":"28007",
    "sg:province":"Madrid",
    "wof:name":"Gesdomo - Gestora Iberica Sl",
    "wof:placetype":"venue"
},
  "geometry": {"coordinates":[-3.677562952,40.4028434753],"type":"Point"}
}