{
  "type": "Feature",
  "properties": {
    "addr:full":"Calle de Francisco Franco, 5 Tapia Casariego Asturias 33740",
    "addr:housenumber":"5",
    "addr:postcode":"33740",
    "addr:street":"Calle De Francisco Franco;Casariego",
    "iso:country":"ES",
    "sg:address":"Calle de Francisco Franco, 5",
    "sg:city":"Tapia Casariego",
    "sg:orig_category":"Fotograf\u00cda Publicitaria E Industrial",
    "sg:phone":"+34 985 62 80 41",
    "sg:postcode":"33740",
    "sg:province":"Asturias",
    "wof:name":"Fernandez Pola Jaime",
    "wof:placetype":"venue"
},
  "geometry": {"coordinates":[-6.946141243,43.5698318481],"type":"Point"}
}