{
  "type": "Feature",
  "properties": {
    "addr:full":"Calle de Isabel La Catolica, 18 Cadiz C\u00e1diz 11004",
    "addr:housenumber":"18",
    "addr:postcode":"11004",
    "addr:street":"Calle De Isabel La Catolica",
    "iso:country":"ES",
    "sg:address":"Calle de Isabel La Catolica, 18",
    "sg:city":"Cadiz",
    "sg:orig_category":"M\u00c9dicos: Estomatolog\u00cda",
    "sg:phone":"+34 956 22 59 83",
    "sg:postcode":"11004",
    "sg:province":"C\u00e1diz",
    "wof:name":"Pe\u00f1as Alonso Ricardo De Las",
    "wof:placetype":"venue"
},
  "geometry": {"coordinates":[-6.2949571609,36.5357971191],"type":"Point"}
}