{
  "type": "Feature",
  "properties": {
    "addr:full":"Arroyo Del Moro, 25 Cordoba C\u00f3rdoba 14011",
    "addr:housenumber":"25",
    "addr:postcode":"14011",
    "addr:street":"Arroyo Del Moro;Co\u0301Rdoba",
    "iso:country":"ES",
    "sg:address":"Arroyo Del Moro, 25",
    "sg:city":"Cordoba",
    "sg:orig_category":"Maquinaria Para Industrias Diversas",
    "sg:phone":"+34 957 46 17 47",
    "sg:postcode":"14011",
    "sg:province":"C\u00f3rdoba",
    "wof:name":"Lope Rodrigo Francisco Javier",
    "wof:placetype":"venue"
},
  "geometry": {"coordinates":[-4.7990608215,37.8930969238],"type":"Point"}
}