{
  "type": "Feature",
  "properties": {
    "addr:full":"P. Moret, 1 Porqueres Girona 17834",
    "addr:housenumber":"1",
    "addr:postcode":"17834",
    "addr:street":"P. Moret",
    "iso:country":"ES",
    "sg:address":"P. Moret, 1",
    "sg:city":"Porqueres",
    "sg:orig_category":"Arquitectos",
    "sg:phone":"+34 972 57 60 90",
    "sg:postcode":"17834",
    "sg:province":"Girona",
    "wof:name":"Costa Mayoles Miquel",
    "wof:placetype":"venue"
},
  "geometry": {"coordinates":[2.764480114,42.0982017517],"type":"Point"}
}