{
  "type": "Feature",
  "properties": {
    "iso:country":"ES",
    "sg:address":"Carrer de Sagrament, 15",
    "sg:city":"Sant Feliu Llobregat",
    "sg:orig_category":"Iglesia Cat\u00d3lica",
    "sg:phone":"+34 936 85 31 71",
    "sg:postcode":"08980",
    "sg:province":"Barcelona",
    "wof:name":"Parroquia San Juan Bautista",
    "wof:placetype":"venue"
},
  "geometry": {"coordinates":[2.0449299812,41.3884506226],"type":"Point"}
}