{
  "type": "Feature",
  "properties": {
    "iso:country":"ES",
    "sg:address":"Plaz Espa\u00d1a, 15",
    "sg:city":"Bejar",
    "sg:orig_category":"Agentes, Concesionarios Y Sucursales De Veh\u00cdculos",
    "sg:phone":"+34 923 40 05 20",
    "sg:postcode":"37700",
    "sg:province":"Salamanca",
    "wof:name":"Honorio S.l.",
    "wof:placetype":"venue"
},
  "geometry": {"coordinates":[-5.7728161812,40.3881263733],"type":"Point"}
}