{
  "type": "Feature",
  "properties": {
    "addr:full":"Calle de San Sebastian, 10 Alcantarilla Murcia 30820",
    "addr:housenumber":"10",
    "addr:postcode":"30820",
    "addr:street":"Calle De San Sebastian",
    "iso:country":"ES",
    "sg:address":"Calle de San Sebastian, 10",
    "sg:city":"Alcantarilla",
    "sg:orig_category":"Ropa De Hogar (al Por Menor)",
    "sg:phone":"+34 968 89 31 26",
    "sg:postcode":"30820",
    "sg:province":"Murcia",
    "wof:name":"Martinez Marin Antonia",
    "wof:placetype":"venue"
},
  "geometry": {"coordinates":[-1.2116789818,37.9670791626],"type":"Point"}
}