{
  "type": "Feature",
  "properties": {
    "addr:full":"Carr Romaguera, 9 Garriguella Girona 17780",
    "addr:housenumber":"9",
    "addr:postcode":"17780",
    "addr:street":"Carr Romaguera",
    "iso:country":"ES",
    "sg:address":"Carr Romaguera, 9",
    "sg:city":"Garriguella",
    "sg:orig_category":"Empresas De Limpieza",
    "sg:phone":"+34 972 53 09 27",
    "sg:postcode":"17780",
    "sg:province":"Girona",
    "wof:name":"Rustic Net S.l.",
    "wof:placetype":"venue"
},
  "geometry": {"coordinates":[3.0652480125,42.3445053101],"type":"Point"}
}