{
  "type": "Feature",
  "properties": {
    "iso:country":"ES",
    "sg:address":"Carrer de Retir, 15",
    "sg:city":"Castellar Valles",
    "sg:orig_category":"Dibujantes (diversos)",
    "sg:phone":"+34 937 14 80 41",
    "sg:postcode":"08211",
    "sg:province":"Barcelona",
    "wof:name":"Rocavert Homet Laia",
    "wof:placetype":"venue"
},
  "geometry": {"coordinates":[2.0858390331,41.6172485352],"type":"Point"}
}