{
  "type": "Feature",
  "properties": {
    "iso:country":"ES",
    "sg:address":"Calle de Santos Justo Y Pastor, 43",
    "sg:city":"Valencia",
    "sg:orig_category":"\u00d3ptica: Instrumentos (fabricaci\u00d3n)",
    "sg:phone":"+34 963 56 49 69",
    "sg:postcode":"46022",
    "sg:province":"Valencia",
    "wof:name":"Grau Ballesta Alejandro",
    "wof:placetype":"venue"
},
  "geometry": {"coordinates":[-0.3488979936,39.4700202942],"type":"Point"}
}