{
  "type": "Feature",
  "properties": {
    "addr:full":"Calle de Rafael Alberti, 1 Montilla C\u00f3rdoba 14550",
    "addr:housenumber":"1",
    "addr:postcode":"14550",
    "addr:street":"Calle De Rafael Alberti;Co\u0301Rdoba",
    "iso:country":"ES",
    "sg:address":"Calle de Rafael Alberti, 1",
    "sg:city":"Montilla",
    "sg:orig_category":"Ropa Para Se\u00d1oras (al Por Menor)",
    "sg:phone":"+34 957 65 27 15",
    "sg:postcode":"14550",
    "sg:province":"C\u00f3rdoba",
    "wof:name":"Ambar C.b.",
    "wof:placetype":"venue"
},
  "geometry": {"coordinates":[-4.6330313683,37.5890083313],"type":"Point"}
}