{
  "type": "Feature",
  "properties": {
    "iso:country":"ES",
    "sg:address":"Pg Ramon Berenguer Iii, 97",
    "sg:city":"Mataro",
    "sg:orig_category":"Peluquer\u00cdas, Peluquer\u00cda Mixta",
    "sg:phone":"+34 937 98 78 90",
    "sg:postcode":"08303",
    "sg:province":"Barcelona",
    "wof:name":"Lebron Vargas Julissa",
    "wof:placetype":"venue"
},
  "geometry": {"coordinates":[2.425385952,41.5375289917],"type":"Point"}
}