{
  "type": "Feature",
  "properties": {
    "addr:full":"Calle de Padre Anton Martin, 3 Valencia Valencia 46011",
    "addr:housenumber":"3",
    "addr:postcode":"46011",
    "addr:street":"Calle De Padre Anton Martin",
    "iso:country":"ES",
    "sg:address":"Calle de Padre Anton Martin, 3",
    "sg:city":"Valencia",
    "sg:orig_category":"Servicio De Salud",
    "sg:phone":"+34 963 71 87 31",
    "sg:postcode":"46011",
    "sg:province":"Valencia",
    "wof:name":"Soler Gil Jose",
    "wof:placetype":"venue"
},
  "geometry": {"coordinates":[-0.3286957145,39.4757232666],"type":"Point"}
}