{
  "type": "Feature",
  "properties": {
    "addr:full":"Calle de Mayor, 2 Santo Domingo De La Calzada La Rioja 26250",
    "addr:housenumber":"2",
    "addr:postcode":"26250",
    "addr:street":"Calle De Mayor;Calzada;Rioja",
    "iso:country":"ES",
    "sg:address":"Calle de Mayor, 2",
    "sg:city":"Santo Domingo De La Calzada",
    "sg:orig_category":"Insecticidas, Fumigaci\u00d3n",
    "sg:phone":"+34 941 34 07 65",
    "sg:postcode":"26250",
    "sg:province":"La Rioja",
    "wof:name":"Janda Servicios Agricolas Y Comercio S.l",
    "wof:placetype":"venue"
},
  "geometry": {"coordinates":[-2.9511458874,42.4404830933],"type":"Point"}
}