{
  "type": "Feature",
  "properties": {
    "addr:full":"Cmno Caritat, 7 Tudela Navarra 31500",
    "addr:housenumber":"7",
    "addr:postcode":"31500",
    "addr:street":"Cmno Caritat",
    "iso:country":"ES",
    "sg:address":"Cmno Caritat, 7",
    "sg:city":"Tudela",
    "sg:orig_category":"Alimentaci\u00d3n General (al Por Menor)",
    "sg:phone":"+34 948 82 10 14",
    "sg:postcode":"31500",
    "sg:province":"Navarra",
    "wof:name":"Diez Apastegui Jesus",
    "wof:placetype":"venue"
},
  "geometry": {"coordinates":[-1.5988630056,42.0580215454],"type":"Point"}
}