{
  "type": "Feature",
  "properties": {
    "iso:country":"ES",
    "sg:address":"Calle de Santo Domingo, 3",
    "sg:city":"Jerez De La Frontera",
    "sg:orig_category":"Molduras, Junquillos, Listones Y Molduras Perforadas",
    "sg:phone":"+34 956 32 33 03",
    "sg:postcode":"11402",
    "sg:province":"C\u00e1diz",
    "wof:name":"Bar Restaurante Aladro S.c.a.",
    "wof:placetype":"venue"
},
  "geometry": {"coordinates":[-6.1356167793,36.6884002686],"type":"Point"}
}