{
  "type": "Feature",
  "properties": {
    "iso:country":"ES",
    "sg:address":"Calle de Encarnacion, 4",
    "sg:city":"Madrid",
    "sg:orig_category":"Marketing Directo",
    "sg:phone":"+34 915 59 42 52",
    "sg:postcode":"28013",
    "sg:province":"Madrid",
    "wof:name":"Vision Global Comunicacion S.l.",
    "wof:placetype":"venue"
},
  "geometry": {"coordinates":[-3.7111876011,40.4199790955],"type":"Point"}
}