{
  "type": "Feature",
  "properties": {
    "addr:full":"El Pozo, S/n Adeje Santa Cruz De Tenerife 38670",
    "addr:housenumber":"s / n",
    "addr:postcode":"38670",
    "addr:street":"El Pozo",
    "iso:country":"ES",
    "sg:address":"El Pozo, S/n",
    "sg:city":"Adeje",
    "sg:orig_category":"Frutas Y Legumbres Frescas (al Por Mayor)",
    "sg:phone":"+34 922 74 00 31",
    "sg:postcode":"38670",
    "sg:province":"Santa Cruz De Tenerife",
    "wof:name":"Fraga Afonso Enrique",
    "wof:placetype":"venue"
},
  "geometry": {"coordinates":[-16.724899292,28.1215400696],"type":"Point"}
}