{
  "type": "Feature",
  "properties": {
    "iso:country":"ES",
    "sg:address":"Calle de Elorri, 1",
    "sg:city":"Algorta",
    "sg:orig_category":"Molduras, Junquillos, Listones Y Molduras Perforadas",
    "sg:phone":"+34 944 30 80 17",
    "sg:postcode":"48991",
    "sg:province":"Vizcaya",
    "wof:name":"Dulce Ansoleaga Julia",
    "wof:placetype":"venue"
},
  "geometry": {"coordinates":[-3.0089728832,43.3544692993],"type":"Point"}
}