{
  "type": "Feature",
  "properties": {
    "addr:full":"Plaz Mayor, 6 San Nicolas Murcia 30005",
    "addr:housenumber":"6",
    "addr:postcode":"30005",
    "addr:street":"Plaz Mayor",
    "iso:country":"ES",
    "sg:address":"Plaz Mayor, 6",
    "sg:city":"San Nicolas",
    "sg:orig_category":"Abogados",
    "sg:phone":"+34 968 21 00 14",
    "sg:postcode":"30005",
    "sg:province":"Murcia",
    "wof:name":"Teruel Mu\u00f1oz Manuel Jose",
    "wof:placetype":"venue"
},
  "geometry": {"coordinates":[-1.1349109411,37.9865913391],"type":"Point"}
}