{
  "type": "Feature",
  "properties": {
    "iso:country":"ES",
    "sg:address":"Av Cami De L'angel, 8",
    "sg:city":"Lloret Mar",
    "sg:orig_category":"Comercio, Reparaci\u00d3n De Motocicletas, Bicicletas Y Piezas Sueltas",
    "sg:phone":"+34 972 37 07 15",
    "sg:postcode":"17310",
    "sg:province":"Girona",
    "wof:name":"Carmona Carmona Gregorio",
    "wof:placetype":"venue"
},
  "geometry": {"coordinates":[2.8187398911,41.9808616638],"type":"Point"}
}