{
  "type": "Feature",
  "properties": {
    "addr:full":"Calle de San Sebastian, 58 Marchena Sevilla 41620",
    "addr:housenumber":"58",
    "addr:postcode":"41620",
    "addr:street":"Calle De San Sebastian",
    "iso:country":"ES",
    "sg:address":"Calle de San Sebastian, 58",
    "sg:city":"Marchena",
    "sg:orig_category":"Empresas De Portes Y Mensajer\u00cda",
    "sg:phone":"+34 955 96 08 34",
    "sg:postcode":"41620",
    "sg:province":"Sevilla",
    "wof:name":"Nu\u00f1ez Aguilar Inmaculada",
    "wof:placetype":"venue"
},
  "geometry": {"coordinates":[-5.4131350517,37.3268127441],"type":"Point"}
}