{
  "type": "Feature",
  "properties": {
    "addr:full":"Avda Jose Antonio, 32 Lalin Pontevedra 36500",
    "addr:housenumber":"32",
    "addr:postcode":"36500",
    "addr:street":"Avda Jose Antonio",
    "iso:country":"ES",
    "sg:address":"Avda Jose Antonio, 32",
    "sg:city":"Lalin",
    "sg:orig_category":"Partidos Pol\u00cdticos",
    "sg:phone":"+34 986 78 05 56",
    "sg:postcode":"36500",
    "sg:province":"Pontevedra",
    "wof:name":"Alianza Popular",
    "wof:placetype":"venue"
},
  "geometry": {"coordinates":[-8.1092424393,42.6615142822],"type":"Point"}
}