{
  "type": "Feature",
  "properties": {
    "addr:full":"Avda Santa Cruz, 2 San Isidro Santa Cruz De Tenerife 38611",
    "addr:housenumber":"2",
    "addr:postcode":"38611",
    "addr:street":"Avda Santa Cruz",
    "iso:country":"ES",
    "sg:address":"Avda Santa Cruz, 2",
    "sg:city":"San Isidro",
    "sg:orig_category":"Comercio De Piezas De Recambio Y De Accesorios De Veh\u00cdculos, Veh\u00cdculos Industriales",
    "sg:phone":"+34 922 39 14 11",
    "sg:postcode":"38611",
    "sg:province":"Santa Cruz De Tenerife",
    "wof:name":"Rodriguez Gazpar Feliciano",
    "wof:placetype":"venue"
},
  "geometry": {"coordinates":[-16.5606594086,28.0817394257],"type":"Point"}
}