{
  "type": "Feature",
  "properties": {
    "iso:country":"ES",
    "sg:address":"Avda Fuenlabrada (de), 63",
    "sg:city":"Humanes De Madrid",
    "sg:orig_category":"Panader\u00cdas, Panader\u00cdas",
    "sg:phone":"+34 916 04 96 93",
    "sg:postcode":"28970",
    "sg:province":"Madrid",
    "wof:name":"Pastin Hermanos Carrasco S. L.",
    "wof:placetype":"venue"
},
  "geometry": {"coordinates":[-3.8123459816,40.2681121826],"type":"Point"}
}