{
  "type": "Feature",
  "properties": {
    "addr:full":"Carrer de Corsega, 508 Barcelona Barcelona 08025",
    "addr:housenumber":"508",
    "addr:postcode":"08025",
    "addr:street":"Carrer De Corsega",
    "iso:country":"ES",
    "sg:address":"Carrer de Corsega, 508",
    "sg:city":"Barcelona",
    "sg:orig_category":"Carnicer\u00cdas, Carnicer\u00cdas",
    "sg:phone":"+34 932 07 39 18",
    "sg:postcode":"08025",
    "sg:province":"Barcelona",
    "wof:name":"Nebot Bayot Juan",
    "wof:placetype":"venue"
},
  "geometry": {"coordinates":[2.1706840992,41.4048957825],"type":"Point"}
}