{
  "type": "Feature",
  "properties": {
    "addr:full":"Pol Ind El Portal, 33 Jerez C\u00e1diz 11408",
    "addr:housenumber":"33",
    "addr:postcode":"11408",
    "addr:street":"El Portal",
    "iso:country":"ES",
    "sg:address":"Pol Ind El Portal, 33",
    "sg:city":"Jerez",
    "sg:orig_category":"Material Y Herramientas Agr\u00cdcolas",
    "sg:phone":"+34 956 14 47 31",
    "sg:postcode":"11408",
    "sg:province":"C\u00e1diz",
    "wof:name":"Marquez Aguilar Antonio",
    "wof:placetype":"venue"
},
  "geometry": {"coordinates":[-6.1592831612,36.6686592102],"type":"Point"}
}