{
  "type": "Feature",
  "properties": {
    "iso:country":"ES",
    "sg:address":"Av Parc, 28",
    "sg:city":"Cornella Llobregat",
    "sg:orig_category":"Ropa Para Caballeros (al Por Menor)",
    "sg:phone":"+34 933 75 31 01",
    "sg:postcode":"08940",
    "sg:province":"Barcelona",
    "wof:name":"Amat Oller Dalmau",
    "wof:placetype":"venue"
},
  "geometry": {"coordinates":[2.0803360939,41.3571052551],"type":"Point"}
}