{
  "type": "Feature",
  "properties": {
    "iso:country":"ES",
    "sg:address":"Calle de Santiago Ramon Y Cajal (de), 5",
    "sg:city":"Humanes De Madrid",
    "sg:orig_category":"Droguer\u00cdas (al Por Menor)",
    "sg:phone":"+34 916 04 12 26",
    "sg:postcode":"28970",
    "sg:province":"Madrid",
    "wof:name":"Jimenez Ribero Juan Antonio",
    "wof:placetype":"venue"
},
  "geometry": {"coordinates":[-3.8222539425,40.2586669922],"type":"Point"}
}