{
  "type": "Feature",
  "properties": {
    "iso:country":"ES",
    "sg:address":"Pl Alexander Fleming, 4",
    "sg:city":"Palma",
    "sg:orig_category":"Cajas De Ahorro",
    "sg:phone":"+34 971 75 29 07",
    "sg:postcode":"07004",
    "sg:province":"Islas Baleares",
    "sg:website":"www.lacaixa.es",
    "wof:name":"Caixa D'estalvis I Pensions De Barcelona",
    "wof:placetype":"venue"
},
  "geometry": {"coordinates":[2.6554179192,39.5810508728],"type":"Point"}
}