{
  "type": "Feature",
  "properties": {
    "addr:full":"Calle de Ramon Y Cajal, S/n Arquillos Ja\u00e9n 23230",
    "addr:housenumber":"s / n",
    "addr:postcode":"23230",
    "addr:street":"Calle De Ramon Y Cajal",
    "iso:country":"ES",
    "sg:address":"Calle de Ramon Y Cajal, S/n",
    "sg:city":"Arquillos",
    "sg:orig_category":"Trabajos De Perforaciones, Sondeos, Construcci\u00d3n De Pozos",
    "sg:phone":"+34 953 63 33 97",
    "sg:postcode":"23230",
    "sg:province":"Ja\u00e9n",
    "wof:name":"Perez Valero Serafin",
    "wof:placetype":"venue"
},
  "geometry": {"coordinates":[-3.4314439297,38.1804466248],"type":"Point"}
}