{
  "type": "Feature",
  "properties": {
    "iso:country":"ES",
    "sg:address":"Calle de Arroyo, 8",
    "sg:city":"Quintanar Rey",
    "sg:orig_category":"Quincaller\u00cda (al Por Menor)",
    "sg:phone":"+34 967 49 68 55",
    "sg:postcode":"16220",
    "sg:province":"Cuenca",
    "wof:name":"Ferreteria Y Decoracion Cabila S.l.",
    "wof:placetype":"venue"
},
  "geometry": {"coordinates":[-1.9301995039,39.3434410095],"type":"Point"}
}