{
  "type": "Feature",
  "properties": {
    "addr:full":"Partida La Carbonera, S/n Altea Alicante 03590",
    "addr:housenumber":"s / n",
    "addr:postcode":"03590",
    "addr:street":"Partida La Carbonera",
    "iso:country":"ES",
    "sg:address":"Partida La Carbonera, S/n",
    "sg:city":"Altea",
    "sg:orig_category":"Piscinas, Accesorios, Suministros (fabricaci\u00d3n, Al Por Mayor)",
    "sg:phone":"+34 966 88 25 43",
    "sg:postcode":"03590",
    "sg:province":"Alicante",
    "wof:name":"Niemann  Katja",
    "wof:placetype":"venue"
},
  "geometry": {"coordinates":[-0.0411509983,38.6206245422],"type":"Point"}
}