{
  "type": "Feature",
  "properties": {
    "iso:country":"ES",
    "sg:address":"Calle de Herencia, 23",
    "sg:city":"Valdemoro",
    "sg:orig_category":"Ropa Y Art\u00cdculos Pre",
    "sg:phone":"+34 918 95 04 53",
    "sg:postcode":"28340",
    "sg:province":"Madrid",
    "wof:name":"De Oro Granados Maria Del Carmen",
    "wof:placetype":"venue"
},
  "geometry": {"coordinates":[-3.6831469536,40.1906013489],"type":"Point"}
}