{
  "type": "Feature",
  "properties": {
    "addr:full":"Carr Santa Maria, 16 Caldes Malavella Girona 17455",
    "addr:housenumber":"16",
    "addr:postcode":"17455",
    "addr:street":"Carr Santa Maria",
    "iso:country":"ES",
    "sg:address":"Carr Santa Maria, 16",
    "sg:city":"Caldes Malavella",
    "sg:orig_category":"Panader\u00cdas, Panader\u00cdas",
    "sg:phone":"+34 972 47 03 28",
    "sg:postcode":"17455",
    "sg:province":"Girona",
    "wof:name":"Andreu Ros S.l.",
    "wof:placetype":"venue"
},
  "geometry": {"coordinates":[2.8089909554,41.8367958069],"type":"Point"}
}