{
  "type": "Feature",
  "properties": {
    "iso:country":"ES",
    "sg:address":"Calle de Leitariegos, 19",
    "sg:city":"Villablino",
    "sg:orig_category":"Librer\u00cdas",
    "sg:phone":"+34 987 48 03 19",
    "sg:postcode":"24100",
    "sg:province":"Le\u00f3n",
    "wof:name":"Fernandez Garcia Fidel",
    "wof:placetype":"venue"
},
  "geometry": {"coordinates":[-6.321117878,42.9387702942],"type":"Point"}
}