{
  "type": "Feature",
  "properties": {
    "addr:full":"C/ Casa La Bassa, 2 Alcoi Alicante 03804",
    "addr:housenumber":"2",
    "addr:postcode":"03804",
    "addr:street":"C / Casa La",
    "iso:country":"ES",
    "sg:address":"C/ Casa La Bassa, 2",
    "sg:city":"Alcoi",
    "sg:orig_category":"Institutos De Belleza",
    "sg:phone":"+34 965 33 54 15",
    "sg:postcode":"03804",
    "sg:province":"Alicante",
    "wof:name":"Cerrillo Fabian Ana Belen",
    "wof:placetype":"venue"
},
  "geometry": {"coordinates":[-0.4694330096,38.7071838379],"type":"Point"}
}