{
  "type": "Feature",
  "properties": {
    "addr:full":"Avda Rectores, 4 Conjunto Residencial Murcia 30100",
    "addr:housenumber":"4",
    "addr:postcode":"30100",
    "addr:street":"Avda Rectores;Conjunto",
    "iso:country":"ES",
    "sg:address":"Avda Rectores, 4",
    "sg:city":"Conjunto Residencial",
    "sg:orig_category":"Inform\u00c1tica, Ofim\u00c1tica (estudios, Asesor\u00cda, Ingenier\u00cda, Formaci\u00d3n)",
    "sg:phone":"+34 968 85 84 20",
    "sg:postcode":"30100",
    "sg:province":"Murcia",
    "sg:website":"www.starmicrosistem.com",
    "wof:name":"Gimenez Cordente Maria Luisa",
    "wof:placetype":"venue"
},
  "geometry": {"coordinates":[-1.161962986,38.0152282715],"type":"Point"}
}