{
  "type": "Feature",
  "properties": {
    "addr:full":"Calle de Pago De Troya, S/n Pto Real C\u00e1diz 11510",
    "addr:housenumber":"s / n",
    "addr:postcode":"11510",
    "addr:street":"Calle De Pago De Troya;Pto;Ca\u0301Diz",
    "iso:country":"ES",
    "sg:address":"Calle de Pago De Troya, S/n",
    "sg:city":"Pto Real",
    "sg:orig_category":"Confecci\u00d3n (fabricaci\u00d3n, Al Por Mayor)",
    "sg:phone":"+34 956 83 77 03",
    "sg:postcode":"11510",
    "sg:province":"C\u00e1diz",
    "wof:name":"Jimenez Moya Victoria",
    "wof:placetype":"venue"
},
  "geometry": {"coordinates":[-6.1940288544,36.5306015015],"type":"Point"}
}