{
  "type": "Feature",
  "properties": {
    "addr:full":"Calle de Oro, S/n Valladolid Valladolid 47012",
    "addr:housenumber":"/ n",
    "addr:postcode":"47012",
    "addr:street":"Calle De Oro S",
    "iso:country":"ES",
    "sg:address":"Calle de Oro, S/n",
    "sg:city":"Valladolid",
    "sg:orig_category":"Comercio De Hierro",
    "sg:phone":"+34 983 20 92 33",
    "sg:postcode":"47012",
    "sg:province":"Valladolid",
    "sg:website":"www.lizalde.com",
    "wof:name":"Comercial Lizalde S. A.",
    "wof:placetype":"venue"
},
  "geometry": {"coordinates":[-4.7059688568,41.6159591675],"type":"Point"}
}