{
  "type": "Feature",
  "properties": {
    "addr:full":"Calle de Sinai, 17 Sevilla Sevilla 41007",
    "addr:housenumber":"17",
    "addr:postcode":"41007",
    "addr:street":"Calle De Sinai",
    "iso:country":"ES",
    "sg:address":"Calle de Sinai, 17",
    "sg:city":"Sevilla",
    "sg:orig_category":"Muebles Y Accesorios Para Cocinas Y Cuartos De Ba\u00d1o (al Por Menor)",
    "sg:phone":"+34 954 57 02 66",
    "sg:postcode":"41007",
    "sg:province":"Sevilla",
    "sg:website":"www.di-como.com",
    "wof:name":"Di'como Dise\u00f1o S.l.",
    "wof:placetype":"venue"
},
  "geometry": {"coordinates":[-5.9704737663,37.3898963928],"type":"Point"}
}