{
  "type": "Feature",
  "properties": {
    "addr:full":"Pg Pere Iii, 30 Manresa Barcelona 08242",
    "addr:housenumber":"30",
    "addr:postcode":"08242",
    "addr:street":"Pg Pere Iii",
    "iso:country":"ES",
    "sg:address":"Pg Pere Iii, 30",
    "sg:city":"Manresa",
    "sg:orig_category":"Agentes Generales De Seguros",
    "sg:phone":"+34 938 72 34 95",
    "sg:postcode":"08242",
    "sg:province":"Barcelona",
    "wof:name":"Terre Pons Josep",
    "wof:placetype":"venue"
},
  "geometry": {"coordinates":[1.8239350319,41.7275733948],"type":"Point"}
}