{
  "type": "Feature",
  "properties": {
    "addr:full":"Calle de Canto, 7 Jerez De La Frontera C\u00e1diz 11403",
    "addr:housenumber":"7",
    "addr:postcode":"11403",
    "addr:street":"Calle De Canto",
    "iso:country":"ES",
    "sg:address":"Calle de Canto, 7",
    "sg:city":"Jerez De La Frontera",
    "sg:orig_category":"Iglesias Evang\u00c9licas",
    "sg:phone":"+34 956 33 27 26",
    "sg:postcode":"11403",
    "sg:province":"C\u00e1diz",
    "wof:name":"Asamblea Cristiana",
    "wof:placetype":"venue"
},
  "geometry": {"coordinates":[-6.1414604187,36.6856079102],"type":"Point"}
}