{
  "type": "Feature",
  "properties": {
    "iso:country":"ES",
    "sg:address":"Ctra Sevilla-malaga-granada, Km. 0005,9",
    "sg:city":"Alcala Guadaira",
    "sg:orig_category":"Agentes, Concesionarios Y Sucursales De Veh\u00cdculos",
    "sg:phone":"+34 955 63 12 85",
    "sg:postcode":"41500",
    "sg:province":"Sevilla",
    "sg:website":"www.monesterio.com/myl",
    "wof:name":"Automoviles Mu\u00f1oz Y Lancharro S.l.",
    "wof:placetype":"venue"
},
  "geometry": {"coordinates":[-5.8740124702,37.3626556396],"type":"Point"}
}