{
  "type": "Feature",
  "properties": {
    "addr:full":"Calle de Licenciado Madrid, 20 Alcala Henares Madrid 28802",
    "addr:housenumber":"20",
    "addr:postcode":"28802",
    "addr:street":"Calle De Licenciado Madrid",
    "iso:country":"ES",
    "sg:address":"Calle de Licenciado Madrid, 20",
    "sg:city":"Alcala Henares",
    "sg:orig_category":"Frutas, Legumbres Frescas Y Tempranas (al Por Menor)",
    "sg:phone":"+34 918 81 61 01",
    "sg:postcode":"28802",
    "sg:province":"Madrid",
    "wof:name":"Frutas Mari Luz S.l.",
    "wof:placetype":"venue"
},
  "geometry": {"coordinates":[-3.3766689301,40.4770011902],"type":"Point"}
}