{
  "type": "Feature",
  "properties": {
    "addr:full":"Calle de Castillo De Constantina, 11 Sevilla Sevilla 41013",
    "addr:housenumber":"11",
    "addr:postcode":"41013",
    "addr:street":"Calle De Castillo",
    "iso:country":"ES",
    "sg:address":"Calle de Castillo De Constantina, 11",
    "sg:city":"Sevilla",
    "sg:orig_category":"Explotaci\u00d3n De Minas",
    "sg:phone":"+34 954 62 30 34",
    "sg:postcode":"41013",
    "sg:province":"Sevilla",
    "wof:name":"Moreno Ca\u00f1as Manuel",
    "wof:placetype":"venue"
},
  "geometry": {"coordinates":[-5.9782261848,37.3604316711],"type":"Point"}
}