{
  "type": "Feature",
  "properties": {
    "iso:country":"ES",
    "sg:address":"Alfonso El Batallador, 3",
    "sg:city":"Iru\u00f1a",
    "sg:orig_category":"Frutas, Legumbres Frescas Y Tempranas (al Por Menor)",
    "sg:phone":"+34 948 27 68 98",
    "sg:postcode":"31007",
    "sg:province":"Navarra",
    "wof:name":"Esteban Goicoechea Jose Miguel",
    "wof:placetype":"venue"
},
  "geometry": {"coordinates":[-1.6498080492,42.8027954102],"type":"Point"}
}