{
  "type": "Feature",
  "properties": {
    "addr:full":"Calle de Alba (del), 7 Marbella M\u00e1laga 29600",
    "addr:housenumber":"7",
    "addr:postcode":"29600",
    "addr:street":"Calle De Alba Del;Ma\u0301Laga",
    "iso:country":"ES",
    "sg:address":"Calle de Alba (del), 7",
    "sg:city":"Marbella",
    "sg:orig_category":"Retoques De Vestidos",
    "sg:phone":"+34 952 86 29 33",
    "sg:postcode":"29600",
    "sg:province":"M\u00e1laga",
    "wof:name":"Las Modistas Sociedad Cooperativa Andaluza",
    "wof:placetype":"venue"
},
  "geometry": {"coordinates":[-4.8810691833,36.5120849609],"type":"Point"}
}