{
  "type": "Feature",
  "properties": {
    "iso:country":"ES",
    "sg:address":"Trva Mari\u00d1a (da), 7",
    "sg:city":"Vilanova",
    "sg:orig_category":"Cajas De Ahorro",
    "sg:phone":"+34 982 12 11 77",
    "sg:postcode":"27760",
    "sg:province":"Lugo",
    "wof:name":"Bt Espa\u00d1a Compa\u00d1ia De Servicios Globales De Telecomunicaciones S.a.u.",
    "wof:placetype":"venue"
},
  "geometry": {"coordinates":[-7.2977337837,43.4696350098],"type":"Point"}
}