{
  "type": "Feature",
  "properties": {
    "iso:country":"ES",
    "sg:address":"Rbla Joaquim Ruyra, 38",
    "sg:city":"Blanes",
    "sg:orig_category":"Fisioterapia",
    "sg:phone":"+34 972 33 72 05",
    "sg:postcode":"17300",
    "sg:province":"Girona",
    "wof:name":"Molina Fuente Marta",
    "wof:placetype":"venue"
},
  "geometry": {"coordinates":[2.7899839878,41.6735916138],"type":"Point"}
}