{
  "type": "Feature",
  "properties": {
    "iso:country":"ES",
    "sg:address":"Calle de Olavarri Jose Maria, 1",
    "sg:city":"Bilbao",
    "sg:classifiers":[
        {
            "category":"Casinos & Gambling",
            "type":"Entertainment"
        }
    ],
    "sg:phone":"+34 944 24 85 80",
    "sg:postcode":"48001",
    "sg:province":"Vizcaya",
    "sg:tags":[
        "locale",
        "de",
        "juego"
    ],
    "wof:name":"Binberri S.a.",
    "wof:placetype":"venue"
},
  "geometry": {"coordinates":[-2.926609993,43.2603645325],"type":"Point"}
}