{
  "type": "Feature",
  "properties": {
    "iso:country":"ES",
    "sg:address":"Avda Jose Maria Monforte, S/n",
    "sg:city":"Vilecha",
    "sg:orig_category":"Empresas De Carpinter\u00cda Met\u00c1lica",
    "sg:phone":"+34 987 28 95 22",
    "sg:postcode":"24192",
    "sg:province":"Le\u00f3n",
    "wof:name":"Gutierrez Fernandez Francisco",
    "wof:placetype":"venue"
},
  "geometry": {"coordinates":[-5.5686221123,42.543182373],"type":"Point"}
}