{
  "type": "Feature",
  "properties": {
    "addr:full":"Plaz Constitucion, 3 Noez Toledo 45162",
    "addr:housenumber":"3",
    "addr:postcode":"45162",
    "addr:street":"Constitucion",
    "iso:country":"ES",
    "sg:address":"Plaz Constitucion, 3",
    "sg:city":"Noez",
    "sg:orig_category":"Papeler\u00cdas, Librer\u00cdas",
    "sg:phone":"+34 925 37 43 08",
    "sg:postcode":"45162",
    "sg:province":"Toledo",
    "wof:name":"Medina Esperanza Jose Luis",
    "wof:placetype":"venue"
},
  "geometry": {"coordinates":[-4.184073925,39.742515564],"type":"Point"}
}