{
  "type": "Feature",
  "properties": {
    "iso:country":"ES",
    "sg:address":"Rava Coma(del), 37",
    "sg:city":"Guissona",
    "sg:orig_category":"Peluqueros: De Se\u00d1oras",
    "sg:phone":"+34 973 55 06 88",
    "sg:postcode":"25210",
    "sg:province":"Lleida",
    "wof:name":"Tomas Bertran Juan",
    "wof:placetype":"venue"
},
  "geometry": {"coordinates":[1.2887649536,41.7873535156],"type":"Point"}
}