{
  "type": "Feature",
  "properties": {
    "iso:country":"ES",
    "sg:address":"Carrer de Amadeu, 82",
    "sg:city":"Calella",
    "sg:orig_category":"Agentes Generales De Seguros",
    "sg:phone":"+34 937 69 03 60",
    "sg:postcode":"08370",
    "sg:province":"Barcelona",
    "wof:name":"Massuet Casamitjana Jose",
    "wof:placetype":"venue"
},
  "geometry": {"coordinates":[2.6642770767,41.6165618896],"type":"Point"}
}