{
  "type": "Feature",
  "properties": {
    "addr:full":"Calle de Pintor Aparicio, 18 Alacant Alicante 03003",
    "addr:housenumber":"18",
    "addr:postcode":"03003",
    "addr:street":"Calle De Pintor Aparicio",
    "iso:country":"ES",
    "sg:address":"Calle de Pintor Aparicio, 18",
    "sg:city":"Alacant",
    "sg:orig_category":"Asesor\u00cda Fiscal Y Jur\u00cddica",
    "sg:phone":"+34 965 22 71 94",
    "sg:postcode":"03003",
    "sg:province":"Alicante",
    "wof:name":"Gefisco S.l.",
    "wof:placetype":"venue"
},
  "geometry": {"coordinates":[-0.4905099869,38.3405609131],"type":"Point"}
}