{
  "type": "Feature",
  "properties": {
    "addr:full":"Calle de Jose Arana, 14 Donostia-san Sebastian Guip\u00f9zcoa 20001",
    "addr:housenumber":"14",
    "addr:postcode":"20001",
    "addr:street":"Calle De Jose Arana",
    "iso:country":"ES",
    "sg:address":"Calle de Jose Arana, 14",
    "sg:city":"Donostia-san Sebastian",
    "sg:orig_category":"Relojer\u00cda Industrial",
    "sg:phone":"+34 943 32 32 32",
    "sg:postcode":"20001",
    "sg:province":"Guip\u00f9zcoa",
    "wof:name":"Gutierrez Aparicio Juan",
    "wof:placetype":"venue"
},
  "geometry": {"coordinates":[-1.9694360495,43.3238067627],"type":"Point"}
}