{
  "type": "Feature",
  "properties": {
    "addr:full":"Avda Andalucia, 26 Cadiz C\u00e1diz 11008",
    "addr:housenumber":"26",
    "addr:postcode":"11008",
    "addr:street":"Avda Andalucia",
    "iso:country":"ES",
    "sg:address":"Avda Andalucia, 26",
    "sg:city":"Cadiz",
    "sg:orig_category":"Cine (producci\u00d3n, Realizaci\u00d3n)",
    "sg:phone":"+34 956 25 53 49",
    "sg:postcode":"11008",
    "sg:province":"C\u00e1diz",
    "wof:name":"Medina Tamayo Andres Pablo",
    "wof:placetype":"venue"
},
  "geometry": {"coordinates":[-6.2857952118,36.5216331482],"type":"Point"}
}