{
  "type": "Feature",
  "properties": {
    "addr:full":"Calle de Agustina De Aragon, 10 Altorricon Huesca 22540",
    "addr:housenumber":"10",
    "addr:postcode":"22540",
    "addr:street":"Calle De Agustina De Aragon",
    "iso:country":"ES",
    "sg:address":"Calle de Agustina De Aragon, 10",
    "sg:city":"Altorricon",
    "sg:orig_category":"Agricultores, Agricultores",
    "sg:phone":"+34 974 42 51 52",
    "sg:postcode":"22540",
    "sg:province":"Huesca",
    "wof:name":"Morancho Sese Amado",
    "wof:placetype":"venue"
},
  "geometry": {"coordinates":[0.4150558114,41.8028869629],"type":"Point"}
}