{
  "type": "Feature",
  "properties": {
    "addr:full":"Calle de Federico Garcia Lorca, 4 Miajadas C\u00e1ceres 10100",
    "addr:housenumber":"4",
    "addr:postcode":"10100",
    "addr:street":"Calle De Federico Garcia Lorca;Ca\u0301Ceres",
    "iso:country":"ES",
    "sg:address":"Calle de Federico Garcia Lorca, 4",
    "sg:city":"Miajadas",
    "sg:orig_category":"Sociedades, Compa\u00d1\u00cdas Aseguradoras",
    "sg:phone":"+34 927 16 12 87",
    "sg:postcode":"10100",
    "sg:province":"C\u00e1ceres",
    "wof:name":"Cento Inmobiliario Y Empresarial Miajade\u00f1o C.b.",
    "wof:placetype":"venue"
},
  "geometry": {"coordinates":[-5.907324791,39.1501159668],"type":"Point"}
}