{
  "type": "Feature",
  "properties": {
    "addr:full":"Calle de Miguel De Unamuno, 20 Fuenlabrada Madrid 28944",
    "addr:housenumber":"20",
    "addr:postcode":"28944",
    "addr:street":"Calle De Miguel De Unamuno",
    "iso:country":"ES",
    "sg:address":"Calle de Miguel De Unamuno, 20",
    "sg:city":"Fuenlabrada",
    "sg:orig_category":"Asociaciones Humanitarias, De Cooperaci\u00d3n, De Acci\u00d3n Social",
    "sg:phone":"+34 916 06 78 11",
    "sg:postcode":"28944",
    "sg:province":"Madrid",
    "wof:name":"Organizacion Nacional De Ciegos",
    "wof:placetype":"venue"
},
  "geometry": {"coordinates":[-3.7911400795,40.2841262817],"type":"Point"}
}