{
  "type": "Feature",
  "properties": {
    "addr:full":"Fray Diego De Estella, 5 Estella Navarra 31200",
    "addr:housenumber":"5",
    "addr:postcode":"31200",
    "addr:street":"Fray Diego De Estella",
    "iso:country":"ES",
    "sg:address":"Fray Diego De Estella, 5",
    "sg:city":"Estella",
    "sg:orig_category":"Muebles, Minoristas",
    "sg:phone":"+34 948 55 52 36",
    "sg:postcode":"31200",
    "sg:province":"Navarra",
    "wof:name":"Muebles Minguez Mauleon S.l.",
    "wof:placetype":"venue"
},
  "geometry": {"coordinates":[-2.0297648907,42.6694984436],"type":"Point"}
}