{
  "type": "Feature",
  "properties": {
    "iso:country":"ES",
    "sg:address":"Avda Fray Albino, S/n",
    "sg:city":"Cordoba",
    "sg:orig_category":"Delegados, Agentes De Tr\u00c1nsito, Auxiliares De Transporte Internacional",
    "sg:phone":"+34 957 42 11 45",
    "sg:postcode":"14009",
    "sg:province":"C\u00f3rdoba",
    "wof:name":"Morales Guerrero Angel Jose",
    "wof:placetype":"venue"
},
  "geometry": {"coordinates":[-4.7787342072,37.8732719421],"type":"Point"}
}