{
  "type": "Feature",
  "properties": {
    "addr:full":"Calle de Martinez Cubells, 10 Valencia Valencia 46002",
    "addr:housenumber":"10",
    "addr:postcode":"46002",
    "addr:street":"Calle De Martinez Cubells",
    "iso:country":"ES",
    "sg:address":"Calle de Martinez Cubells, 10",
    "sg:city":"Valencia",
    "sg:orig_category":"Inmobiliaria (agencias)",
    "sg:phone":"+34 963 52 57 57",
    "sg:postcode":"46002",
    "sg:province":"Valencia",
    "wof:name":"Jose Luis Alarcon S.l.",
    "wof:placetype":"venue"
},
  "geometry": {"coordinates":[-0.3740876019,39.4682312012],"type":"Point"}
}