{
  "type": "Feature",
  "properties": {
    "iso:country":"ES",
    "sg:address":"Calle de Venezuela, 6",
    "sg:city":"Coru\u00d1a",
    "sg:orig_category":"Sociedades De Franquicias",
    "sg:phone":"+34 981 27 87 32",
    "sg:postcode":"15011",
    "sg:province":"La Coru\u00f1a",
    "wof:name":"Conectel Plus S.l.",
    "wof:placetype":"venue"
},
  "geometry": {"coordinates":[-8.4216918945,43.3715286255],"type":"Point"}
}