{
  "type": "Feature",
  "properties": {
    "iso:country":"ES",
    "sg:address":"Calle de Azor (del), 22",
    "sg:city":"Galapagar",
    "sg:orig_category":"Arquitectos",
    "sg:phone":"+34 918 58 01 02",
    "sg:postcode":"28420",
    "sg:province":"Madrid",
    "wof:name":"Montoya Batiz Roberto",
    "wof:placetype":"venue"
},
  "geometry": {"coordinates":[-3.981746912,40.5934753418],"type":"Point"}
}