{
  "type": "Feature",
  "properties": {
    "iso:country":"ES",
    "sg:address":"Carrer de Sant Just, 2",
    "sg:city":"Vic",
    "sg:orig_category":"Partidos Pol\u00cdticos",
    "sg:phone":"+34 938 89 43 83",
    "sg:postcode":"08500",
    "sg:province":"Barcelona",
    "wof:name":"Unio Democratica De Catalunya-osona",
    "wof:placetype":"venue"
},
  "geometry": {"coordinates":[2.2541620731,41.9292602539],"type":"Point"}
}