{
  "type": "Feature",
  "properties": {
    "iso:country":"ES",
    "sg:address":"Ctra. Ventorros, 6",
    "sg:city":"Zagra",
    "sg:orig_category":"Confecci\u00d3n (fabricaci\u00d3n, Al Por Mayor)",
    "sg:phone":"+34 958 31 50 02",
    "sg:postcode":"18311",
    "sg:province":"Granada",
    "wof:name":"Zagra Textil S.a.",
    "wof:placetype":"venue"
},
  "geometry": {"coordinates":[-4.141140461,37.2570877075],"type":"Point"}
}