{
  "type": "Feature",
  "properties": {
    "iso:country":"ES",
    "sg:address":"Calle de Coronel Fernandez Golfin, 67",
    "sg:city":"Almendralejo",
    "sg:orig_category":"Promotores Constructores",
    "sg:phone":"+34 924 66 48 36",
    "sg:postcode":"06200",
    "sg:province":"Badajoz",
    "wof:name":"Construcciones Izigon C.b.",
    "wof:placetype":"venue"
},
  "geometry": {"coordinates":[-6.4056563377,38.6748847961],"type":"Point"}
}