{
  "type": "Feature",
  "properties": {
    "addr:full":"Calle de Cedaceros, 9 Madrid Madrid 28014",
    "addr:housenumber":"9",
    "addr:postcode":"madrid;28014",
    "addr:street":"Calle De Cedaceros",
    "iso:country":"ES",
    "sg:address":"Calle de Cedaceros, 9",
    "sg:city":"Madrid",
    "sg:orig_category":"M\u00c9dicos: Oftalmolog\u00cda",
    "sg:phone":"+34 914 29 76 98",
    "sg:postcode":"28014",
    "sg:province":"Madrid",
    "wof:name":"Leoz Macias Gustavo",
    "wof:placetype":"venue"
},
  "geometry": {"coordinates":[-3.6983997822,40.4169998169],"type":"Point"}
}