{
  "type": "Feature",
  "properties": {
    "addr:full":"Avda Constitucion, 37 Mazarron Murcia 30870",
    "addr:housenumber":"37",
    "addr:postcode":"30870",
    "addr:street":"Avda Constitucion",
    "iso:country":"ES",
    "sg:address":"Avda Constitucion, 37",
    "sg:city":"Mazarron",
    "sg:orig_category":"Agentes, Concesionarios Y Sucursales De Veh\u00cdculos",
    "sg:phone":"+34 968 59 01 27",
    "sg:postcode":"30870",
    "sg:province":"Murcia",
    "wof:name":"Antonio Robles Sanchez Y Otros C.b.",
    "wof:placetype":"venue"
},
  "geometry": {"coordinates":[-1.3156065941,37.6007919312],"type":"Point"}
}