{
  "type": "Feature",
  "properties": {
    "iso:country":"ES",
    "sg:address":"Calle de Padre Huesca, 4",
    "sg:city":"Huesca",
    "sg:orig_category":"Zapater\u00cdas",
    "sg:phone":"+34 974 22 63 75",
    "sg:postcode":"22002",
    "sg:province":"Huesca",
    "wof:name":"Calzados Risu S.a.",
    "wof:placetype":"venue"
},
  "geometry": {"coordinates":[-0.4073599875,42.1368865967],"type":"Point"}
}