{
  "type": "Feature",
  "properties": {
    "iso:country":"ES",
    "sg:address":"Calle de San Isidro, 51",
    "sg:city":"Losar Vera",
    "sg:orig_category":"Reposter\u00cdas",
    "sg:phone":"+34 927 57 07 67",
    "sg:postcode":"10460",
    "sg:province":"C\u00e1ceres",
    "wof:name":"Anton Martin Modesta",
    "wof:placetype":"venue"
},
  "geometry": {"coordinates":[-5.6064419746,40.1206474304],"type":"Point"}
}