{
  "type": "Feature",
  "properties": {
    "addr:full":"Calle de San Adrian, 6 Bilbao Vizcaya 48003",
    "addr:housenumber":"6",
    "addr:postcode":"48003",
    "addr:street":"Calle De San Adrian",
    "iso:country":"ES",
    "sg:address":"Calle de San Adrian, 6",
    "sg:city":"Bilbao",
    "sg:orig_category":"Frutas, Legumbres Frescas Y Tempranas (al Por Menor)",
    "sg:phone":"+34 944 10 15 91",
    "sg:postcode":"48003",
    "sg:province":"Vizcaya",
    "wof:name":"Kareaga Goikoa 30 S.l.",
    "wof:placetype":"venue"
},
  "geometry": {"coordinates":[-2.9340004921,43.250202179],"type":"Point"}
}