{
  "type": "Feature",
  "properties": {
    "iso:country":"ES",
    "sg:address":"Calle de Otero Blas De, 53",
    "sg:city":"Bilbao",
    "sg:orig_category":"Cl\u00cdnicas Dentales",
    "sg:phone":"+34 944 76 33 78",
    "sg:postcode":"48014",
    "sg:province":"Vizcaya",
    "wof:name":"Pedraz Ya\u00f1ez Paloma",
    "wof:placetype":"venue"
},
  "geometry": {"coordinates":[-2.9515199661,43.2697067261],"type":"Point"}
}