{
  "type": "Feature",
  "properties": {
    "addr:full":"Calle de Belostikale, 16 Bilbao Vizcaya 48005",
    "addr:housenumber":"16",
    "addr:postcode":"48005",
    "addr:street":"Calle De Belostikale",
    "iso:country":"ES",
    "sg:address":"Calle de Belostikale, 16",
    "sg:city":"Bilbao",
    "sg:orig_category":"Zapatos (al Por Menor)",
    "sg:phone":"+34 944 15 62 02",
    "sg:postcode":"48005",
    "sg:province":"Vizcaya",
    "wof:name":"Gomez Merino Jose Manuel",
    "wof:placetype":"venue"
},
  "geometry": {"coordinates":[-2.9242255688,43.2564849854],"type":"Point"}
}