{
  "type": "Feature",
  "properties": {
    "addr:full":"Carrer de Sant Jordi, 35 S. Cugat Valles Barcelona 08172",
    "addr:housenumber":"35",
    "addr:postcode":"08172",
    "addr:street":"Carrer De Sant Jordi;S. Cugat Valles Barcelona",
    "iso:country":"ES",
    "sg:address":"Carrer de Sant Jordi, 35",
    "sg:city":"S. Cugat Valles",
    "sg:orig_category":"Confiter\u00cdas, Chocolater\u00cdas (al Por Menor)",
    "sg:phone":"+34 936 74 25 71",
    "sg:postcode":"08172",
    "sg:province":"Barcelona",
    "sg:website":".",
    "wof:name":"De Ochoa Martinez Ana",
    "wof:placetype":"venue"
},
  "geometry": {"coordinates":[2.0817248821,41.4680252075],"type":"Point"}
}