{
  "type": "Feature",
  "properties": {
    "iso:country":"ES",
    "sg:address":"Calle de Masustegi, 5",
    "sg:city":"Bilbao",
    "sg:orig_category":"Asesor\u00cda Sobre Comunicaci\u00d3n De Empresas",
    "sg:phone":"+34 944 33 91 05",
    "sg:postcode":"48006",
    "sg:province":"Vizcaya",
    "wof:name":"Asesoria Financiera Bilbaina S.a.",
    "wof:placetype":"venue"
},
  "geometry": {"coordinates":[-2.9132020473,43.2560539246],"type":"Point"}
}