{
  "type": "Feature",
  "properties": {
    "addr:full":"Ctra Icod A Buenavista La Caleta, Km. 0008,9 Caleta De Interian Santa Cruz De Tenerife 38460",
    "addr:postcode":"38460",
    "addr:street":"Ctra Icod A Buenavista La Caleta Km. 0008,9 Caleta De Interian",
    "iso:country":"ES",
    "sg:address":"Ctra Icod A Buenavista La Caleta, Km. 0008,9",
    "sg:city":"Caleta De Interian",
    "sg:orig_category":"Distribuci\u00d3n De Petr\u00d3leo Y Derivados",
    "sg:phone":"+34 922 83 12 25",
    "sg:postcode":"38460",
    "sg:province":"Santa Cruz De Tenerife",
    "wof:name":"Guerra Martin Maria Lourdes",
    "wof:placetype":"venue"
},
  "geometry": {"coordinates":[-16.7948741913,28.3742008209],"type":"Point"}
}