{
  "type": "Feature",
  "properties": {
    "addr:full":"Avda Libertador Simon Bolivar, 5 Portugalete Vizcaya 48920",
    "addr:housenumber":"5",
    "addr:postcode":"48920",
    "addr:street":"Avda Libertador Simon Bolivar",
    "iso:country":"ES",
    "sg:address":"Avda Libertador Simon Bolivar, 5",
    "sg:city":"Portugalete",
    "sg:orig_category":"Psic\u00d3logos",
    "sg:phone":"+34 944 62 96 66",
    "sg:postcode":"48920",
    "sg:province":"Vizcaya",
    "wof:name":"Psikobide Psicologos",
    "wof:placetype":"venue"
},
  "geometry": {"coordinates":[-3.0224049091,43.3188438416],"type":"Point"}
}