{
  "type": "Feature",
  "properties": {
    "addr:full":"Calle de Carretera De Fuenterrabia, Km. 0001,0 Poblado Naval C\u00e1diz 11500",
    "addr:postcode":"11500",
    "addr:street":"Calle De Carretera De Fuenterrabia Km. 0001,0 Poblado Naval Ca\u0301Diz",
    "iso:country":"ES",
    "sg:address":"Calle de Carretera De Fuenterrabia, Km. 0001,0",
    "sg:city":"Poblado Naval",
    "sg:orig_category":"Ense\u00d1anza: Idiomas",
    "sg:phone":"+34 956 85 30 00",
    "sg:postcode":"11500",
    "sg:province":"C\u00e1diz",
    "wof:name":"El Centro Ingles S.l.",
    "wof:placetype":"venue"
},
  "geometry": {"coordinates":[-6.2197542191,36.6056632996],"type":"Point"}
}