{
  "type": "Feature",
  "properties": {
    "addr:full":"Calle de Arteta Aurelio Pintor, 1 Bilbao Vizcaya 48004",
    "addr:housenumber":"1",
    "addr:postcode":"48004",
    "addr:street":"Calle De Arteta Aurelio Pintor",
    "iso:country":"ES",
    "sg:address":"Calle de Arteta Aurelio Pintor, 1",
    "sg:city":"Bilbao",
    "sg:orig_category":"Fotocopias, Reprograf\u00cda",
    "sg:phone":"+34 944 12 82 45",
    "sg:postcode":"48004",
    "sg:province":"Vizcaya",
    "wof:name":"Amaia Gorrochategui Azanza",
    "wof:placetype":"venue"
},
  "geometry": {"coordinates":[-2.900121212,43.2565917969],"type":"Point"}
}