{
  "type": "Feature",
  "properties": {
    "iso:country":"ES",
    "sg:address":"Urb Eixample Llevant Casc Urba, S/n",
    "sg:city":"Pobla De Montornes",
    "sg:orig_category":"Delegados, Agentes De Tr\u00c1nsito, Auxiliares De Transporte Internacional",
    "sg:phone":"+34 977 64 80 48",
    "sg:postcode":"43761",
    "sg:province":"Tarragona",
    "wof:name":"Herrera Garcia Juan",
    "wof:placetype":"venue"
},
  "geometry": {"coordinates":[1.4154100418,41.1786766052],"type":"Point"}
}