{
  "type": "Feature",
  "properties": {
    "iso:country":"ES",
    "sg:address":"Calle de Truchas, 2",
    "sg:city":"Valdelagua",
    "sg:orig_category":"Productores Recolectores, Venta Directa De Vinos",
    "sg:phone":"+34 923 13 81 87",
    "sg:postcode":"37194",
    "sg:province":"Salamanca",
    "wof:name":"Sovisur S.a.",
    "wof:placetype":"venue"
},
  "geometry": {"coordinates":[-5.6189584732,40.940574646],"type":"Point"}
}