{
  "type": "Feature",
  "properties": {
    "addr:full":"Alam Mazarredo, 20 Bilbao Vizcaya 48009",
    "addr:housenumber":"20",
    "addr:postcode":"48009",
    "addr:street":"Mazarredo",
    "iso:country":"ES",
    "sg:address":"Alam Mazarredo, 20",
    "sg:city":"Bilbao",
    "sg:orig_category":"Abogados",
    "sg:phone":"+34 944 24 19 66",
    "sg:postcode":"48009",
    "sg:province":"Vizcaya",
    "wof:name":"Ruiz Visaira Jose Ramon",
    "wof:placetype":"venue"
},
  "geometry": {"coordinates":[-2.9309151173,43.2676696777],"type":"Point"}
}