{
  "type": "Feature",
  "properties": {
    "addr:full":"Calle de Pintada, 22 Nerja M\u00e1laga 29780",
    "addr:housenumber":"22",
    "addr:postcode":"29780",
    "addr:street":"Calle De Pintada;Ma\u0301Laga",
    "iso:country":"ES",
    "sg:address":"Calle de Pintada, 22",
    "sg:city":"Nerja",
    "sg:orig_category":"Art\u00cdculos De Decoraci\u00d3n",
    "sg:phone":"+34 952 52 27 93",
    "sg:postcode":"29780",
    "sg:province":"M\u00e1laga",
    "wof:name":"Gomez Navas Miguel",
    "wof:placetype":"venue"
},
  "geometry": {"coordinates":[-3.8759579659,36.7465591431],"type":"Point"}
}