{
  "type": "Feature",
  "properties": {
    "iso:country":"ES",
    "sg:address":"Calle de Estrella, 24",
    "sg:city":"Coru\u00d1a",
    "sg:orig_category":"Dorados, Plater\u00cda (orfebrer\u00cda)",
    "sg:phone":"+34 981 20 88 81",
    "sg:postcode":"15003",
    "sg:province":"La Coru\u00f1a",
    "wof:name":"Camiplat S.l.",
    "wof:placetype":"venue"
},
  "geometry": {"coordinates":[-8.4037151337,43.3687019348],"type":"Point"}
}