{
  "type": "Feature",
  "properties": {
    "addr:full":"Avda Rafael Cabrera, 24 Palmas De Gran Canaria Las Palmas 35002",
    "addr:postcode":"35002",
    "addr:street":"Avda Rafael Cabrera 24",
    "iso:country":"ES",
    "sg:address":"Avda Rafael Cabrera, 24",
    "sg:city":"Palmas De Gran Canaria",
    "sg:orig_category":"Abogados",
    "sg:phone":"+34 928 37 06 66",
    "sg:postcode":"35002",
    "sg:province":"Las Palmas",
    "wof:name":"Avila Cava Jose",
    "wof:placetype":"venue"
},
  "geometry": {"coordinates":[-15.415184021,28.1070041656],"type":"Point"}
}