{
  "type": "Feature",
  "properties": {
    "iso:country":"ES",
    "sg:address":"Calle de Explanada De Camellos, 3",
    "sg:city":"Melilla",
    "sg:orig_category":"Transportes Por Carretera: Lotes Completos, Mercanc\u00cdas Diversas",
    "sg:phone":"+34 952 67 69 46",
    "sg:postcode":"52005",
    "sg:province":"Melilla",
    "wof:name":"Navas Salas Antonio",
    "wof:placetype":"venue"
},
  "geometry": {"coordinates":[-2.9556701183,35.2835693359],"type":"Point"}
}