{
  "type": "Feature",
  "properties": {
    "iso:country":"ES",
    "sg:address":"Calle de Elcano, 9",
    "sg:city":"San Vicente De Barakaldo",
    "sg:orig_category":"Zapatos (al Por Menor)",
    "sg:phone":"+34 944 37 13 21",
    "sg:postcode":"48901",
    "sg:province":"Vizcaya",
    "wof:name":"Martinez Palacio Andres",
    "wof:placetype":"venue"
},
  "geometry": {"coordinates":[-2.9879961014,43.2964515686],"type":"Point"}
}