{
  "type": "Feature",
  "properties": {
    "iso:country":"ES",
    "sg:address":"Av Onze De Setembre, 26",
    "sg:city":"Olot",
    "sg:orig_category":"Sociedades, Compa\u00d1\u00cdas Aseguradoras",
    "sg:phone":"+34 972 27 60 31",
    "sg:postcode":"17800",
    "sg:province":"Girona",
    "wof:name":"Aulinas Cargol S.l.",
    "wof:placetype":"venue"
},
  "geometry": {"coordinates":[2.4934000969,42.182800293],"type":"Point"}
}