{
  "type": "Feature",
  "properties": {
    "iso:country":"ES",
    "sg:address":"Calle de Obispo Ballester, 35",
    "sg:city":"Vitoria-gasteiz",
    "sg:orig_category":"Tapiceros Y Tapiceros",
    "sg:phone":"+34 945 27 09 95",
    "sg:postcode":"01002",
    "sg:province":"\u00c1lava",
    "wof:name":"Moreno Sanchez Rafael",
    "wof:placetype":"venue"
},
  "geometry": {"coordinates":[-2.6628079414,42.8538246155],"type":"Point"}
}