{
  "type": "Feature",
  "properties": {
    "addr:full":"Av Albir (l'), 111 Albir Alicante 03580",
    "addr:housenumber":"111",
    "addr:postcode":"03580",
    "addr:street":"Av Albir L ';Alicante",
    "iso:country":"ES",
    "sg:address":"Av Albir (l'), 111",
    "sg:city":"Albir",
    "sg:orig_category":"Asesor\u00cda Fiscal Y Jur\u00cddica",
    "sg:phone":"+34 966 86 66 40",
    "sg:postcode":"03580",
    "sg:province":"Alicante",
    "sg:website":"www.interbureau.es}}",
    "wof:name":"Alcaraz Benavent Francisco",
    "wof:placetype":"venue"
},
  "geometry": {"coordinates":[-0.0715261996,38.5720710754],"type":"Point"}
}