{
  "type": "Feature",
  "properties": {
    "iso:country":"ES",
    "sg:address":"Calle de Felipe Solano Antelo, 17",
    "sg:city":"Guadalajara",
    "sg:orig_category":"Bisuter\u00cda, Joyer\u00cda, Relojer\u00cda (al Por Menor)",
    "sg:phone":"+34 949 22 46 28",
    "sg:postcode":"19002",
    "sg:province":"Guadalajara",
    "wof:name":"Galvez Tarabillo Angel",
    "wof:placetype":"venue"
},
  "geometry": {"coordinates":[-3.161960125,40.6229286194],"type":"Point"}
}