{
  "type": "Feature",
  "properties": {
    "iso:country":"ES",
    "sg:address":"Calle de Fuente Grande (de), 5",
    "sg:city":"Bustarviejo",
    "sg:orig_category":"Cr\u00cda De Animales",
    "sg:phone":"+34 918 48 21 06",
    "sg:postcode":"28720",
    "sg:province":"Madrid",
    "wof:name":"Lara Anguas Fernando",
    "wof:placetype":"venue"
},
  "geometry": {"coordinates":[-3.7109901905,40.8574447632],"type":"Point"}
}