{
  "type": "Feature",
  "properties": {
    "addr:full":"Avda Sancho El Sabio, 23 Donostia-san Sebastian Guip\u00f9zcoa 20010",
    "addr:housenumber":"23",
    "addr:postcode":"20010",
    "addr:street":"Avda Sancho El Sabio",
    "iso:country":"ES",
    "sg:address":"Avda Sancho El Sabio, 23",
    "sg:city":"Donostia-san Sebastian",
    "sg:orig_category":"Equipo De Refrigeraci\u00d3n Industrial",
    "sg:phone":"+34 943 46 32 22",
    "sg:postcode":"20010",
    "sg:province":"Guip\u00f9zcoa",
    "wof:name":"Foster Refrigerator U K Limited",
    "wof:placetype":"venue"
},
  "geometry": {"coordinates":[-1.9796110392,43.3093185425],"type":"Point"}
}