{
  "type": "Feature",
  "properties": {
    "iso:country":"ES",
    "sg:address":"Calle de Nuestra Se\u00d1ora Del Rocio, 49",
    "sg:city":"Pilas",
    "sg:orig_category":"Promotores Constructores",
    "sg:phone":"+34 955 75 27 34",
    "sg:postcode":"41840",
    "sg:province":"Sevilla",
    "wof:name":"Construcciones Cuesta Rubio S.l",
    "wof:placetype":"venue"
},
  "geometry": {"coordinates":[-6.29708004,37.3057785034],"type":"Point"}
}