{
  "type": "Feature",
  "properties": {
    "addr:full":"Calle de Vitoria, 34 Miranda Ebro Burgos 09200",
    "addr:housenumber":"34",
    "addr:postcode":"09200",
    "addr:street":"Calle De Vitoria",
    "iso:country":"ES",
    "sg:address":"Calle de Vitoria, 34",
    "sg:city":"Miranda Ebro",
    "sg:orig_category":"Dietistas",
    "sg:phone":"+34 947 31 42 61",
    "sg:postcode":"09200",
    "sg:province":"Burgos",
    "sg:website":"www.naturhouse.com",
    "wof:name":"Kiluva Diet S.l.",
    "wof:placetype":"venue"
},
  "geometry": {"coordinates":[-2.9497330189,42.686958313],"type":"Point"}
}