{
  "type": "Feature",
  "properties": {
    "iso:country":"ES",
    "sg:address":"Calle de Barriada Eusebio Rebolleda, 43",
    "sg:city":"Toro",
    "sg:orig_category":"Contenedores (mercanc\u00cdas)",
    "sg:phone":"+34 980 69 11 68",
    "sg:postcode":"49800",
    "sg:province":"Zamora",
    "wof:name":"Garcia De La Calle Ernesto",
    "wof:placetype":"venue"
},
  "geometry": {"coordinates":[-5.3951888084,41.5273017883],"type":"Point"}
}