{
  "type": "Feature",
  "properties": {
    "iso:country":"ES",
    "sg:address":"Cesar, S/n",
    "sg:city":"La Union",
    "sg:orig_category":"Internados & Ense\u00d1anza Privada",
    "sg:phone":"+34 968 56 00 48",
    "sg:postcode":"30360",
    "sg:province":"Murcia",
    "wof:name":"Colegio Nuestra Se\u00f1ora Del Carmen",
    "wof:placetype":"venue"
},
  "geometry": {"coordinates":[-0.8793339729,37.6173553467],"type":"Point"}
}