{
  "type": "Feature",
  "properties": {
    "addr:full":"Barr Elizondo, 8 Ermitabarri-ibarra Vizcaya 48499",
    "addr:housenumber":"8",
    "addr:postcode":"48499",
    "addr:street":"Elizondo",
    "iso:country":"ES",
    "sg:address":"Barr Elizondo, 8",
    "sg:city":"Ermitabarri-ibarra",
    "sg:orig_category":"Asilos De Ancianos. Centros Privados",
    "sg:phone":"+34 946 48 16 32",
    "sg:postcode":"48499",
    "sg:province":"Vizcaya",
    "wof:name":"Residencia Eusebio Aldekoa",
    "wof:placetype":"venue"
},
  "geometry": {"coordinates":[-2.8493540287,43.1476364136],"type":"Point"}
}