{
  "type": "Feature",
  "properties": {
    "addr:full":"Avgd Catalunya, 48 Badalona Barcelona 08917",
    "addr:housenumber":"48",
    "addr:postcode":"08917",
    "iso:country":"ES",
    "sg:address":"Avgd Catalunya, 48",
    "sg:city":"Badalona",
    "sg:orig_category":"Asociaciones, Organismos Culturales Y Socioeducativos",
    "sg:phone":"+34 933 99 64 72",
    "sg:postcode":"08917",
    "sg:province":"Barcelona",
    "wof:name":"K-liu Badalona Associacio Infantil I Juvenil",
    "wof:placetype":"venue"
},
  "geometry": {"coordinates":[2.2297270298,41.449798584],"type":"Point"}
}