{
  "type": "Feature",
  "properties": {
    "iso:country":"ES",
    "sg:address":"Calle de Arevalo Lara, 84",
    "sg:city":"Madrid",
    "sg:orig_category":"Droguer\u00cdas (al Por Menor)",
    "sg:phone":"+34 913 93 28 10",
    "sg:postcode":"28027",
    "sg:province":"Madrid",
    "wof:name":"Garcia Hernandez Francisca",
    "wof:placetype":"venue"
},
  "geometry": {"coordinates":[-3.6313223839,40.4428863525],"type":"Point"}
}