{
  "type": "Feature",
  "properties": {
    "iso:country":"ES",
    "sg:address":"Calle de Cuarteles, 17",
    "sg:city":"Malaga",
    "sg:orig_category":"Inmobiliaria (agencias)",
    "sg:phone":"+34 952 31 16 44",
    "sg:postcode":"29002",
    "sg:province":"M\u00e1laga",
    "sg:website":"www.unicasa.es",
    "wof:name":"Estudio Unico Asociados S.l.",
    "wof:placetype":"venue"
},
  "geometry": {"coordinates":[-4.4272708893,36.7143745422],"type":"Point"}
}