{
  "type": "Feature",
  "properties": {
    "addr:full":"Pase San Illan, 33 Madrid Madrid 28019",
    "addr:housenumber":"33",
    "addr:postcode":"madrid;28019",
    "addr:street":"Illan",
    "iso:country":"ES",
    "sg:address":"Pase San Illan, 33",
    "sg:city":"Madrid",
    "sg:orig_category":"Maquinaria Para Industrias Diversas",
    "sg:phone":"+34 914 69 83 51",
    "sg:postcode":"28019",
    "sg:province":"Madrid",
    "wof:name":"Tecnologia Y Aparcamientos S.l.",
    "wof:placetype":"venue"
},
  "geometry": {"coordinates":[-3.7225739956,40.4000549316],"type":"Point"}
}