{
  "type": "Feature",
  "properties": {
    "addr:full":"Calle de Reina Fabiola, 3 Zaragoza Zaragoza 50008",
    "addr:housenumber":"3",
    "addr:postcode":"50008",
    "addr:street":"Calle De Reina Fabiola",
    "iso:country":"ES",
    "sg:address":"Calle de Reina Fabiola, 3",
    "sg:city":"Zaragoza",
    "sg:orig_category":"Productores Recolectores, Venta Directa De Vinos",
    "sg:phone":"+34 976 41 77 82",
    "sg:postcode":"50008",
    "sg:province":"Zaragoza",
    "sg:website":"www.lagarnacha.com",
    "wof:name":"La Ganacha Club De Vinos S.l.",
    "wof:placetype":"venue"
},
  "geometry": {"coordinates":[-0.8725535274,41.6460952759],"type":"Point"}
}