{
  "type": "Feature",
  "properties": {
    "addr:full":"Rua Alvarellos Berrocal, 7 Cee La Coru\u00f1a 15270",
    "addr:postcode":"15270",
    "addr:street":"Rua Alvarellos",
    "iso:country":"ES",
    "sg:address":"Rua Alvarellos Berrocal, 7",
    "sg:city":"Cee",
    "sg:orig_category":"Bisuter\u00cda, Joyer\u00cda, Relojer\u00cda (al Por Menor)",
    "sg:phone":"+34 981 74 55 27",
    "sg:postcode":"15270",
    "sg:province":"La Coru\u00f1a",
    "wof:name":"Joyeria Nicolas S.l.",
    "wof:placetype":"venue"
},
  "geometry": {"coordinates":[-9.1885595322,42.9557914734],"type":"Point"}
}