{
  "type": "Feature",
  "properties": {
    "iso:country":"ES",
    "sg:address":"Urb Parque (el), 12",
    "sg:city":"Cabez\u00f3n Sal",
    "sg:orig_category":"Material Y Herramientas Agr\u00cdcolas",
    "sg:phone":"+34 942 70 17 46",
    "sg:postcode":"39500",
    "sg:province":"Cantabria",
    "wof:name":"Fernandez Gonzalez Jose Antonio",
    "wof:placetype":"venue"
},
  "geometry": {"coordinates":[-4.2374691963,43.3085784912],"type":"Point"}
}