{
  "type": "Feature",
  "properties": {
    "addr:full":"La Rosa, 33 Sta Cruz Tenerife Santa Cruz De Tenerife 38001",
    "addr:housenumber":"33",
    "addr:postcode":"38001",
    "addr:street":"Rosa;Cruz",
    "iso:country":"ES",
    "sg:address":"La Rosa, 33",
    "sg:city":"Sta Cruz Tenerife",
    "sg:orig_category":"Farmacias",
    "sg:phone":"+34 922 28 34 59",
    "sg:postcode":"38001",
    "sg:province":"Santa Cruz De Tenerife",
    "wof:name":"Suarez Perez Carlos",
    "wof:placetype":"venue"
},
  "geometry": {"coordinates":[-16.2496566772,28.4714202881],"type":"Point"}
}