{
  "type": "Feature",
  "properties": {
    "iso:country":"ES",
    "sg:address":"Rua San Marti\u00d1o, 42",
    "sg:city":"Ribadavia",
    "sg:orig_category":"Panader\u00cdas, Panader\u00cdas",
    "sg:phone":"+34 988 47 02 88",
    "sg:postcode":"32400",
    "sg:province":"Ourense",
    "wof:name":"Gonzalez Blanco Juan Carlos",
    "wof:placetype":"venue"
},
  "geometry": {"coordinates":[-8.1429443359,42.2893943787],"type":"Point"}
}