{
  "type": "Feature",
  "properties": {
    "iso:country":"ES",
    "sg:address":"Calle de Vista Alegre, S/n",
    "sg:city":"Chimeneas",
    "sg:orig_category":"Empresas De Desmonte",
    "sg:phone":"+34 958 55 72 18",
    "sg:postcode":"18329",
    "sg:province":"Granada",
    "wof:name":"Agricola Y Excavaciones Vicente S.l.",
    "wof:placetype":"venue"
},
  "geometry": {"coordinates":[-3.8239688873,37.1311454773],"type":"Point"}
}