{
  "type": "Feature",
  "properties": {
    "iso:country":"ES",
    "sg:address":"Av Catalunya, 85",
    "sg:city":"Tarrega",
    "sg:orig_category":"Neum\u00c1ticos (fabricaci\u00d3n, Al Por Mayor)",
    "sg:phone":"+34 973 31 01 63",
    "sg:postcode":"25300",
    "sg:province":"Lleida",
    "wof:name":"Neumaticos Roca Esteve S.l.",
    "wof:placetype":"venue"
},
  "geometry": {"coordinates":[1.1314450502,41.6473121643],"type":"Point"}
}