{
  "type": "Feature",
  "properties": {
    "addr:full":"Calle de Juan Ramon Jimenez, 15 Massamagrell Valencia 46130",
    "addr:housenumber":"15",
    "addr:postcode":"46130",
    "addr:street":"Calle De Juan Ramon Jimenez",
    "iso:country":"ES",
    "sg:address":"Calle de Juan Ramon Jimenez, 15",
    "sg:city":"Massamagrell",
    "sg:orig_category":"Peluquer\u00cdas, Peluquer\u00cda Mixta",
    "sg:phone":"+34 961 44 14 76",
    "sg:postcode":"46130",
    "sg:province":"Valencia",
    "wof:name":"Aznar Peluqueros S.l",
    "wof:placetype":"venue"
},
  "geometry": {"coordinates":[-0.3298349977,39.5709915161],"type":"Point"}
}