{
  "type": "Feature",
  "properties": {
    "addr:full":"Calle de Duque De Mandas, 21 Valencia Valencia 46019",
    "addr:housenumber":"21",
    "addr:postcode":"46019",
    "addr:street":"Calle De Duque De Mandas",
    "iso:country":"ES",
    "sg:address":"Calle de Duque De Mandas, 21",
    "sg:city":"Valencia",
    "sg:orig_category":"Cajas De Ahorro",
    "sg:phone":"+34 963 68 09 26",
    "sg:postcode":"46019",
    "sg:province":"Valencia",
    "wof:name":"Caixa D'estalvis I Pensions De Barcelona",
    "wof:placetype":"venue"
},
  "geometry": {"coordinates":[-0.3700517118,39.4940605164],"type":"Point"}
}