{
  "type": "Feature",
  "properties": {
    "iso:country":"ES",
    "sg:address":"Ptda Alzabares Alto, 63",
    "sg:city":"Elche",
    "sg:orig_category":"Cristaler\u00cdas",
    "sg:phone":"+34 965 45 50 45",
    "sg:postcode":"03290",
    "sg:province":"Alicante",
    "wof:name":"Agullo Y Selva Cristaleros S.l.",
    "wof:placetype":"venue"
},
  "geometry": {"coordinates":[-0.6915392876,38.2354507446],"type":"Point"}
}