{
  "type": "Feature",
  "properties": {
    "iso:country":"ES",
    "sg:address":"Rua Rio Mao, 16",
    "sg:city":"Ourense",
    "sg:orig_category":"Electricidad: Instaladores",
    "sg:phone":"+34 988 21 24 40",
    "sg:postcode":"32001",
    "sg:province":"Ourense",
    "wof:name":"Segade Saelco S.a.",
    "wof:placetype":"venue"
},
  "geometry": {"coordinates":[-7.8642477989,42.3518295288],"type":"Point"}
}