{
  "type": "Feature",
  "properties": {
    "iso:country":"ES",
    "sg:address":"Calle de Herradura, 7",
    "sg:city":"Santa Eulalia",
    "sg:orig_category":"Deportes Y Programas De Aventura",
    "sg:phone":"+34 968 22 24 99",
    "sg:postcode":"30003",
    "sg:province":"Murcia",
    "wof:name":"Alegria Cantabella David",
    "wof:placetype":"venue"
},
  "geometry": {"coordinates":[-1.5573451519,37.8003540039],"type":"Point"}
}