{
  "type": "Feature",
  "properties": {
    "iso:country":"ES",
    "sg:address":"Calle de Angel, 29",
    "sg:city":"Granada",
    "sg:orig_category":"Mec\u00c1nico Del Autom\u00d3vil",
    "sg:phone":"+34 958 81 81 51",
    "sg:postcode":"18006",
    "sg:province":"Granada",
    "wof:name":"Ruiz Martin Antonio",
    "wof:placetype":"venue"
},
  "geometry": {"coordinates":[-3.6490426064,37.1433792114],"type":"Point"}
}