{
  "type": "Feature",
  "properties": {
    "addr:full":"Rua Carlos Iii, 14 Becerrea Lugo 27640",
    "addr:housenumber":"14",
    "addr:postcode":"27640",
    "addr:street":"Rua Carlos Iii",
    "iso:country":"ES",
    "sg:address":"Rua Carlos Iii, 14",
    "sg:city":"Becerrea",
    "sg:orig_category":"Bazares, Art\u00cdculos De Limpieza Y De Cocina (al Por Menor)",
    "sg:phone":"+34 982 36 02 25",
    "sg:postcode":"27640",
    "sg:province":"Lugo",
    "wof:name":"Nu\u00f1ez Rodriguez Maria",
    "wof:placetype":"venue"
},
  "geometry": {"coordinates":[-7.1613059044,42.8526229858],"type":"Point"}
}