{
  "type": "Feature",
  "properties": {
    "addr:full":"Calle de Einstein (de), 6 Alcobendas Madrid 28108",
    "addr:postcode":"28108",
    "addr:street":"Calle De Einstein De 6",
    "iso:country":"ES",
    "sg:address":"Calle de Einstein (de), 6",
    "sg:city":"Alcobendas",
    "sg:orig_category":"Alimentaci\u00d3n General (al Por Mayor)",
    "sg:phone":"+34 916 61 39 52",
    "sg:postcode":"28108",
    "sg:province":"Madrid",
    "wof:name":"Essen Gourmet S.l.",
    "wof:placetype":"venue"
},
  "geometry": {"coordinates":[-3.6536729336,40.5345687866],"type":"Point"}
}