{
  "type": "Feature",
  "properties": {
    "iso:country":"ES",
    "sg:address":"Calle de Bravo Murillo, 18",
    "sg:city":"Palmas De Gran Canaria",
    "sg:orig_category":"Farmacias",
    "sg:phone":"+34 928 36 83 68",
    "sg:postcode":"35003",
    "sg:province":"Las Palmas",
    "wof:name":"Alvarez Rodriguez Sonia",
    "wof:placetype":"venue"
},
  "geometry": {"coordinates":[-15.4192390442,28.1083602905],"type":"Point"}
}