{
  "type": "Feature",
  "properties": {
    "iso:country":"ES",
    "sg:address":"Calle de Infanta Do\u00d1a Maria, 80",
    "sg:city":"Cordoba",
    "sg:orig_category":"Peluqueros: De Se\u00d1oras",
    "sg:phone":"+34 957 41 45 49",
    "sg:postcode":"14004",
    "sg:province":"C\u00f3rdoba",
    "wof:name":"Carrion Mu\u00f1oz Maria",
    "wof:placetype":"venue"
},
  "geometry": {"coordinates":[-4.7907972336,37.8785057068],"type":"Point"}
}