{
  "type": "Feature",
  "properties": {
    "addr:full":"Avda Laba\u00d1ou, 2 Coru\u00d1a La Coru\u00f1a 15011",
    "addr:housenumber":"2",
    "addr:postcode":"15011",
    "addr:street":"Avda Laban\u0303Ou;La Corun\u0303A",
    "iso:country":"ES",
    "sg:address":"Avda Laba\u00d1ou, 2",
    "sg:city":"Coru\u00d1a",
    "sg:orig_category":"Cervecer\u00cdas",
    "sg:phone":"+34 981 25 18 52",
    "sg:postcode":"15011",
    "sg:province":"La Coru\u00f1a",
    "wof:name":"Incotel S.l.",
    "wof:placetype":"venue"
},
  "geometry": {"coordinates":[-8.4205598831,43.3735847473],"type":"Point"}
}