{
  "type": "Feature",
  "properties": {
    "iso:country":"ES",
    "sg:address":"Plaz Santa Isabel, 3",
    "sg:city":"Santa Catalina",
    "sg:orig_category":"Asociaciones Humanitarias, De Cooperaci\u00d3n, De Acci\u00d3n Social",
    "sg:phone":"+34 968 21 32 33",
    "sg:postcode":"30004",
    "sg:province":"Murcia",
    "wof:name":"Asociacion Para La Defensa De La Atencion A La Anorexia Nerviosa",
    "wof:placetype":"venue"
},
  "geometry": {"coordinates":[-1.1298867464,37.9834747314],"type":"Point"}
}