{
  "type": "Feature",
  "properties": {
    "iso:country":"ES",
    "sg:address":"Plaz Cedro Del, 2",
    "sg:city":"Donostia-san Sebastian",
    "sg:orig_category":"Caf\u00c9s, Bares, Cervecer\u00cdas",
    "sg:phone":"+34 943 39 99 52",
    "sg:postcode":"20016",
    "sg:province":"Guip\u00f9zcoa",
    "wof:name":"Cafeteria Bikote Cb",
    "wof:placetype":"venue"
},
  "geometry": {"coordinates":[-1.9414600134,43.323551178],"type":"Point"}
}