{
  "type": "Feature",
  "properties": {
    "iso:country":"ES",
    "sg:address":"Carrer de Arago, 63",
    "sg:city":"Barcelona",
    "sg:orig_category":"Carnicer\u00cdas, Carnicer\u00cdas",
    "sg:phone":"+34 932 26 59 22",
    "sg:postcode":"08015",
    "sg:province":"Barcelona",
    "wof:name":"Garcia Guirado Manel",
    "wof:placetype":"venue"
},
  "geometry": {"coordinates":[2.1496219635,41.3808784485],"type":"Point"}
}