{
  "type": "Feature",
  "properties": {
    "addr:full":"Zalain Auzoa, 2 Bera Navarra 31780",
    "addr:housenumber":"2",
    "addr:postcode":"31780",
    "addr:street":"Zalain Auzoa",
    "iso:country":"ES",
    "sg:address":"Zalain Auzoa, 2",
    "sg:city":"Bera",
    "sg:orig_category":"Conservas De Legumbres (fabricaci\u00d3n, Al Por Mayor)",
    "sg:phone":"+34 948 63 05 18",
    "sg:postcode":"31780",
    "sg:province":"Navarra",
    "sg:website":"www.envasadosubidea.com",
    "wof:name":"Exclusivas Ubidea S.l",
    "wof:placetype":"venue"
},
  "geometry": {"coordinates":[-1.6813839674,43.2808914185],"type":"Point"}
}