{
  "type": "Feature",
  "properties": {
    "iso:country":"ES",
    "sg:address":"Rua Areal, 58",
    "sg:city":"Vigo",
    "sg:orig_category":"Servicio De Salud",
    "sg:phone":"+34 986 22 51 81",
    "sg:postcode":"36201",
    "sg:province":"Pontevedra",
    "sg:website":"www.fonca.es",
    "wof:name":"Suministros Para La Fontaneria Y Calefac",
    "wof:placetype":"venue"
},
  "geometry": {"coordinates":[-8.7155714035,42.2388114929],"type":"Point"}
}