{
  "type": "Feature",
  "properties": {
    "iso:country":"ES",
    "sg:address":"Avda Duque De Tamames, 4",
    "sg:city":"Orihuela",
    "sg:orig_category":"Asilos De Ancianos. Centros Privados",
    "sg:phone":"+34 965 30 02 51",
    "sg:postcode":"03300",
    "sg:province":"Alicante",
    "wof:name":"Hogar De Ancianos En Orihuela Hermanitas Ancianos Desamparados Provincia Sagrado Corazon",
    "wof:placetype":"venue"
},
  "geometry": {"coordinates":[-0.94184798,38.0821914673],"type":"Point"}
}