{
  "type": "Feature",
  "properties": {
    "addr:full":"Luna Y Sol, S/n Le\u00f3n Le\u00f3n 24005",
    "addr:postcode":"24005",
    "addr:street":"S / N Leo\u0301N Leo\u0301N",
    "iso:country":"ES",
    "sg:address":"Luna Y Sol, S/n",
    "sg:city":"Le\u00f3n",
    "sg:orig_category":"Comercio De Hierro",
    "sg:phone":"+34 987 21 02 08",
    "sg:postcode":"24005",
    "sg:province":"Le\u00f3n",
    "wof:name":"Hierros Del Cantabrico Sa",
    "wof:placetype":"venue"
},
  "geometry": {"coordinates":[-5.554669857,42.5806999207],"type":"Point"}
}