{
  "type": "Feature",
  "properties": {
    "addr:full":"Afores, S/n Calders Barcelona 08275",
    "addr:housenumber":"s / n",
    "addr:postcode":"08275",
    "addr:street":"Afores",
    "iso:country":"ES",
    "sg:address":"Afores, S/n",
    "sg:city":"Calders",
    "sg:orig_category":"Cr\u00cda De Poller\u00cda Y De Conejos",
    "sg:phone":"+34 938 30 92 59",
    "sg:postcode":"08275",
    "sg:province":"Barcelona",
    "wof:name":"Sanchez Rodriguez Jose Ramon",
    "wof:placetype":"venue"
},
  "geometry": {"coordinates":[1.99150002,41.7876701355],"type":"Point"}
}