{
  "type": "Feature",
  "properties": {
    "addr:full":"Ctra Ronda (de), 76 Almeria Almer\u00eda 04004",
    "addr:housenumber":"76",
    "addr:postcode":"04004",
    "addr:street":"Ctra Ronda De",
    "iso:country":"ES",
    "sg:address":"Ctra Ronda (de), 76",
    "sg:city":"Almeria",
    "sg:orig_category":"Materiales De Construcci\u00d3n (en General)",
    "sg:phone":"+34 950 27 73 82",
    "sg:postcode":"04004",
    "sg:province":"Almer\u00eda",
    "wof:name":"Urciplast S.l.",
    "wof:placetype":"venue"
},
  "geometry": {"coordinates":[-2.455835104,36.8370780945],"type":"Point"}
}