{
  "type": "Feature",
  "properties": {
    "iso:country":"ES",
    "sg:address":"Calle de San Francisco, 10",
    "sg:city":"Segovia",
    "sg:orig_category":"Abogados",
    "sg:phone":"+34 921 41 27 92",
    "sg:postcode":"40001",
    "sg:province":"Segovia",
    "wof:name":"Ruiz Garcia Gonzalo",
    "wof:placetype":"venue"
},
  "geometry": {"coordinates":[-4.1180810928,40.9474411011],"type":"Point"}
}