{
  "type": "Feature",
  "properties": {
    "iso:country":"ES",
    "sg:address":"Ctra Bajada De Las Guayarminas, 9",
    "sg:city":"Galdar",
    "sg:orig_category":"M\u00c9dicos: Estomatolog\u00cda",
    "sg:phone":"+34 928 55 30 30",
    "sg:postcode":"35460",
    "sg:province":"Las Palmas",
    "wof:name":"Holcer Sutler Carlos",
    "wof:placetype":"venue"
},
  "geometry": {"coordinates":[-15.6528720856,28.1450138092],"type":"Point"}
}