{
  "type": "Feature",
  "properties": {
    "addr:full":"Calle de Doctor Fleming, 24 Valdemoro Madrid 28340",
    "addr:housenumber":"24",
    "addr:postcode":"28340",
    "addr:street":"Calle De Doctor Fleming",
    "iso:country":"ES",
    "sg:address":"Calle de Doctor Fleming, 24",
    "sg:city":"Valdemoro",
    "sg:orig_category":"Asociaciones Y Clubs Deportivos",
    "sg:phone":"+34 918 95 26 01",
    "sg:postcode":"28340",
    "sg:province":"Madrid",
    "wof:name":"Valdemoro New Fietness",
    "wof:placetype":"venue"
},
  "geometry": {"coordinates":[-3.6755549908,40.1941871643],"type":"Point"}
}