{
  "type": "Feature",
  "properties": {
    "addr:full":"Calle de Melquiades Alvarez, 19 Oviedo Asturias 33003",
    "addr:housenumber":"19",
    "addr:postcode":"33003",
    "addr:street":"Calle De Melquiades Alvarez",
    "iso:country":"ES",
    "sg:address":"Calle de Melquiades Alvarez, 19",
    "sg:city":"Oviedo",
    "sg:orig_category":"M\u00c9dicos: Oftalmolog\u00cda",
    "sg:phone":"+34 985 21 29 57",
    "sg:postcode":"33003",
    "sg:province":"Asturias",
    "wof:name":"Bajo Fernandez Antonio",
    "wof:placetype":"venue"
},
  "geometry": {"coordinates":[-5.8517131805,43.3649635315],"type":"Point"}
}