{
  "type": "Feature",
  "properties": {
    "iso:country":"ES",
    "sg:address":"Calle de Villalba Hervas, 12",
    "sg:city":"Santa Cruz De Tenerife",
    "sg:orig_category":"Asesor\u00cda Sobre Comunicaci\u00d3n De Empresas",
    "sg:phone":"+34 922 15 17 80",
    "sg:postcode":"38002",
    "sg:province":"Santa Cruz De Tenerife",
    "wof:name":"S.s. Consultores Tributarios Legales S.l.",
    "wof:placetype":"venue"
},
  "geometry": {"coordinates":[-16.2488899231,28.467792511],"type":"Point"}
}