{
  "type": "Feature",
  "properties": {
    "addr:full":"Carr Doctor Trueta, 38 Santa Coloma De Farners Girona 17430",
    "addr:housenumber":"38",
    "addr:postcode":"17430",
    "addr:street":"Carr Doctor Trueta",
    "iso:country":"ES",
    "sg:address":"Carr Doctor Trueta, 38",
    "sg:city":"Santa Coloma De Farners",
    "sg:orig_category":"Paletas",
    "sg:phone":"+34 972 84 29 31",
    "sg:postcode":"17430",
    "sg:province":"Girona",
    "wof:name":"Palets Farners S.l.",
    "wof:placetype":"venue"
},
  "geometry": {"coordinates":[2.660533905,41.8647956848],"type":"Point"}
}