{
  "type": "Feature",
  "properties": {
    "addr:full":"Calle de Domingo Fernandez, 5 Madrid Madrid 28036",
    "addr:housenumber":"5",
    "addr:postcode":"28036",
    "addr:street":"Calle De Domingo Fernandez",
    "iso:country":"ES",
    "sg:address":"Calle de Domingo Fernandez, 5",
    "sg:city":"Madrid",
    "sg:orig_category":"Cables Y Hilos El\u00c9ctricos (fabricaci\u00d3n, Al Por Mayor)",
    "sg:phone":"+34 913 59 45 09",
    "sg:postcode":"28036",
    "sg:province":"Madrid",
    "sg:website":"www.optral.com",
    "wof:name":"Optral S.a.",
    "wof:placetype":"venue"
},
  "geometry": {"coordinates":[-3.6824634075,40.4592819214],"type":"Point"}
}