{
  "type": "Feature",
  "properties": {
    "addr:full":"Calle de Magistrado Salvador Barbera, 3 Malaga M\u00e1laga 29010",
    "addr:housenumber":"3",
    "addr:postcode":"29010",
    "addr:street":"Calle De Magistrado;Barbera;Ma\u0301Laga",
    "iso:country":"ES",
    "sg:address":"Calle de Magistrado Salvador Barbera, 3",
    "sg:city":"Malaga",
    "sg:orig_category":"Bisuter\u00cda, Joyer\u00cda, Relojer\u00cda (al Por Menor)",
    "sg:phone":"+34 952 30 67 38",
    "sg:postcode":"29010",
    "sg:province":"M\u00e1laga",
    "wof:name":"Racabardi S.l",
    "wof:placetype":"venue"
},
  "geometry": {"coordinates":[-4.4433040619,36.7233657837],"type":"Point"}
}