{
  "type": "Feature",
  "properties": {
    "iso:country":"ES",
    "sg:address":"Calle de Lepanto, 21",
    "sg:city":"Villena",
    "sg:orig_category":"Electricidad: Instaladores",
    "sg:phone":"+34 965 80 70 39",
    "sg:postcode":"03400",
    "sg:province":"Alicante",
    "wof:name":"Teyma C.b.",
    "wof:placetype":"venue"
},
  "geometry": {"coordinates":[-0.868991375,38.6382980347],"type":"Point"}
}