{
  "type": "Feature",
  "properties": {
    "addr:full":"Carr Bisbe Abad I Lasierra, 54 Eivissa Islas Baleares 07800",
    "addr:housenumber":"54",
    "addr:postcode":"07800",
    "addr:street":"Carr Bisbe Abad I Lasierra",
    "iso:country":"ES",
    "sg:address":"Carr Bisbe Abad I Lasierra, 54",
    "sg:city":"Eivissa",
    "sg:orig_category":"M\u00c9dicos: Estomatolog\u00cda",
    "sg:phone":"+34 971 31 35 86",
    "sg:postcode":"07800",
    "sg:province":"Islas Baleares",
    "wof:name":"Rosello Mayans Elena",
    "wof:placetype":"venue"
},
  "geometry": {"coordinates":[1.4274139404,38.9125938416],"type":"Point"}
}