{
  "type": "Feature",
  "properties": {
    "addr:full":"Ctra. Cordoba-p. Rio, S/n Hornachuelos C\u00f3rdoba 14740",
    "addr:housenumber":"/ n",
    "addr:postcode":"14740",
    "addr:street":"Ctra. Cordoba-P. Rio S",
    "iso:country":"ES",
    "sg:address":"Ctra. Cordoba-p. Rio, S/n",
    "sg:city":"Hornachuelos",
    "sg:orig_category":"Aceites Y Grasas Alimentarias (fabricaci\u00d3n, Al Por Mayor)",
    "sg:phone":"+34 957 33 83 24",
    "sg:postcode":"14740",
    "sg:province":"C\u00f3rdoba",
    "wof:name":"Oleoguadalora S.l.",
    "wof:placetype":"venue"
},
  "geometry": {"coordinates":[-5.2428050041,37.8309288025],"type":"Point"}
}