{
  "type": "Feature",
  "properties": {
    "iso:country":"ES",
    "sg:address":"Avda De La Libertad, 47",
    "sg:city":"Vinaros",
    "sg:orig_category":"Empresarios",
    "sg:phone":"+34 964 45 10 47",
    "sg:postcode":"12500",
    "sg:province":"Castell\u00f3n",
    "wof:name":"Guijarro Roig Josefina",
    "wof:placetype":"venue"
},
  "geometry": {"coordinates":[0.4742591977,40.4751625061],"type":"Point"}
}