{
  "type": "Feature",
  "properties": {
    "iso:country":"ES",
    "sg:address":"Villafranca, 7",
    "sg:city":"Iru\u00f1a",
    "sg:orig_category":"Iglesia Cat\u00d3lica",
    "sg:phone":"+34 948 12 53 79",
    "sg:postcode":"31015",
    "sg:province":"Navarra",
    "wof:name":"Parroquia Santa Teresa",
    "wof:placetype":"venue"
},
  "geometry": {"coordinates":[-1.6303119659,42.8317909241],"type":"Point"}
}