{
  "type": "Feature",
  "properties": {
    "addr:full":"Pol Ind Martiartu Ii, 44 Arrigorriaga Vizcaya 48480",
    "addr:housenumber":"44",
    "addr:postcode":"48480",
    "iso:country":"ES",
    "sg:address":"Pol Ind Martiartu Ii, 44",
    "sg:city":"Arrigorriaga",
    "sg:orig_category":"Tapiceros Y Tapiceros",
    "sg:phone":"+34 944 44 82 78",
    "sg:postcode":"48480",
    "sg:province":"Vizcaya",
    "sg:website":"www.gaztenet.com/flozano",
    "wof:name":"Lozano Luengo Felipe Javier",
    "wof:placetype":"venue"
},
  "geometry": {"coordinates":[-2.8916389942,43.2028694153],"type":"Point"}
}