{
  "type": "Feature",
  "properties": {
    "addr:full":"Calle de Olmos (los), 3 Ribabellosa \u00c1lava 01213",
    "addr:housenumber":"3",
    "addr:postcode":"01213",
    "addr:street":"Calle De Olmos Los;A\u0301Lava",
    "iso:country":"ES",
    "sg:address":"Calle de Olmos (los), 3",
    "sg:city":"Ribabellosa",
    "sg:orig_category":"Mudanzas",
    "sg:phone":"+34 945 35 53 17",
    "sg:postcode":"01213",
    "sg:province":"\u00c1lava",
    "wof:name":"De La Dehesa Parra Alfredo",
    "wof:placetype":"venue"
},
  "geometry": {"coordinates":[-2.9200739861,42.7085838318],"type":"Point"}
}