{
  "type": "Feature",
  "properties": {
    "iso:country":"ES",
    "sg:address":"Carrer de Muralla Del Carme, S/n",
    "sg:city":"Manresa",
    "sg:orig_category":"Carnicer\u00cdas, Carnicer\u00cdas",
    "sg:phone":"+34 938 75 16 83",
    "sg:postcode":"08241",
    "sg:province":"Barcelona",
    "wof:name":"Camero Frias Rafael",
    "wof:placetype":"venue"
},
  "geometry": {"coordinates":[1.8249139786,41.7253265381],"type":"Point"}
}