{
  "type": "Feature",
  "properties": {
    "addr:full":"Carrer de Navas De Tolosa, 358 Barcelona Barcelona 08027",
    "addr:housenumber":"358",
    "addr:postcode":"08027",
    "addr:street":"Carrer De Navas De Tolosa",
    "iso:country":"ES",
    "sg:address":"Carrer de Navas De Tolosa, 358",
    "sg:city":"Barcelona",
    "sg:orig_category":"Promotores Constructores",
    "sg:phone":"+34 933 52 57 34",
    "sg:postcode":"08027",
    "sg:province":"Barcelona",
    "wof:name":"Carulla Cutiller Promocions Sl",
    "wof:placetype":"venue"
},
  "geometry": {"coordinates":[2.1818099022,41.4193344116],"type":"Point"}
}