{
  "type": "Feature",
  "properties": {
    "iso:country":"ES",
    "sg:address":"Muel Ca\u00d1onero Dato, S/n",
    "sg:city":"Ceuta",
    "sg:orig_category":"Fabricaci\u00d3n De Productos L\u00c1cteos Y Derivados",
    "sg:phone":"+34 956 50 84 88",
    "sg:postcode":"51001",
    "sg:province":"Ceuta",
    "wof:name":"Danone S.a.",
    "wof:placetype":"venue"
},
  "geometry": {"coordinates":[-5.3302302361,35.8947601318],"type":"Point"}
}