{
  "type": "Feature",
  "properties": {
    "addr:full":"Grandarrasa, 14 Anes Asturias 33189",
    "addr:housenumber":"14",
    "addr:postcode":"33189",
    "addr:street":"Grandarrasa",
    "iso:country":"ES",
    "sg:address":"Grandarrasa, 14",
    "sg:city":"Anes",
    "sg:orig_category":"Cr\u00cda De Poller\u00cda Y De Conejos",
    "sg:phone":"+34 985 92 08 70",
    "sg:postcode":"33189",
    "sg:province":"Asturias",
    "wof:name":"Granja La Faeda S.l.",
    "wof:placetype":"venue"
},
  "geometry": {"coordinates":[-5.697245121,43.4521560669],"type":"Point"}
}