{
  "type": "Feature",
  "properties": {
    "addr:full":"Bard Pilar, S/n Burgos Burgos 09001",
    "addr:housenumber":"s / n",
    "addr:postcode":"09001",
    "addr:street":"Pilar",
    "iso:country":"ES",
    "sg:address":"Bard Pilar, S/n",
    "sg:city":"Burgos",
    "sg:orig_category":"Frutas Y Legumbres Frescas (al Por Mayor)",
    "sg:phone":"+34 947 48 36 33",
    "sg:postcode":"09001",
    "sg:province":"Burgos",
    "wof:name":"Miranda Alonso Rafael",
    "wof:placetype":"venue"
},
  "geometry": {"coordinates":[-3.7410039902,42.3424758911],"type":"Point"}
}