{
  "type": "Feature",
  "properties": {
    "addr:full":"Calle de Escultor Ramirez, 23 Zaragoza Zaragoza 50007",
    "addr:housenumber":"23",
    "addr:postcode":"50007",
    "addr:street":"Calle De Escultor Ramirez",
    "iso:country":"ES",
    "sg:address":"Calle de Escultor Ramirez, 23",
    "sg:city":"Zaragoza",
    "sg:orig_category":"Molduras, Junquillos, Listones Y Molduras Perforadas",
    "sg:phone":"+34 976 37 76 91",
    "sg:postcode":"50007",
    "sg:province":"Zaragoza",
    "wof:name":"Sainz-aja Fernandez Cosme",
    "wof:placetype":"venue"
},
  "geometry": {"coordinates":[-0.8755490184,41.6331291199],"type":"Point"}
}