{
  "type": "Feature",
  "properties": {
    "addr:full":"Calle de Toneleros, 4 S. Juan Puerto Huelva 21610",
    "addr:housenumber":"4",
    "addr:postcode":"21610",
    "addr:street":"Calle De Toneleros;S. Juan Puerto",
    "iso:country":"ES",
    "sg:address":"Calle de Toneleros, 4",
    "sg:city":"S. Juan Puerto",
    "sg:orig_category":"Agentes Generales De Seguros",
    "sg:phone":"+34 959 36 73 78",
    "sg:postcode":"21610",
    "sg:province":"Huelva",
    "wof:name":"Sanchez Toscano Antonio",
    "wof:placetype":"venue"
},
  "geometry": {"coordinates":[-6.8425750732,37.3138809204],"type":"Point"}
}