{
  "type": "Feature",
  "properties": {
    "addr:full":"Ctra Ilanes, S/n Puente Zamora 49350",
    "addr:housenumber":"s / n",
    "addr:postcode":"49350",
    "addr:street":"Ctra Ilanes",
    "iso:country":"ES",
    "sg:address":"Ctra Ilanes, S/n",
    "sg:city":"Puente",
    "sg:orig_category":"Reposter\u00cdas",
    "sg:phone":"+34 980 62 02 71",
    "sg:postcode":"49350",
    "sg:province":"Zamora",
    "wof:name":"Alvarez Anta Daniel",
    "wof:placetype":"venue"
},
  "geometry": {"coordinates":[-6.6440472603,42.0839881897],"type":"Point"}
}