{
  "type": "Feature",
  "properties": {
    "addr:full":"Carr Pere Ferro, S/n Eivissa Islas Baleares 07800",
    "addr:housenumber":"s / n",
    "addr:postcode":"07800",
    "addr:street":"Carr Pere Ferro",
    "iso:country":"ES",
    "sg:address":"Carr Pere Ferro, S/n",
    "sg:city":"Eivissa",
    "sg:orig_category":"Transportes Por V\u00cdas Navegables",
    "sg:phone":"+34 971 19 30 30",
    "sg:postcode":"07800",
    "sg:province":"Islas Baleares",
    "wof:name":"Argibay Gato Manuel Alfonso",
    "wof:placetype":"venue"
},
  "geometry": {"coordinates":[1.4241404533,38.922454834],"type":"Point"}
}