{
  "type": "Feature",
  "properties": {
    "iso:country":"ES",
    "sg:address":"Calle de Juan Pedro Vidal, 9",
    "sg:city":"Lebrija",
    "sg:orig_category":"Asesor\u00cda Sobre Comunicaci\u00d3n De Empresas",
    "sg:phone":"+34 955 97 05 37",
    "sg:postcode":"41740",
    "sg:province":"Sevilla",
    "wof:name":"Asociacion Lebrijana De Minusvalidos Fisicos Almif",
    "wof:placetype":"venue"
},
  "geometry": {"coordinates":[-6.0795922279,36.91954422],"type":"Point"}
}