{
  "type": "Feature",
  "properties": {
    "iso:country":"ES",
    "sg:address":"Calle de Estibaliz, 5",
    "sg:city":"Oyon-oion",
    "sg:orig_category":"Reposter\u00cdas",
    "sg:phone":"+34 945 60 12 70",
    "sg:postcode":"01320",
    "sg:province":"\u00c1lava",
    "wof:name":"Mazariegos Ferrer Alejandro",
    "wof:placetype":"venue"
},
  "geometry": {"coordinates":[-2.4364089966,42.5043525696],"type":"Point"}
}