{
  "type": "Feature",
  "properties": {
    "addr:full":"Calle de Pascual Amat, 22 Yecla Murcia 30510",
    "addr:housenumber":"22",
    "addr:postcode":"30510",
    "addr:street":"Calle De Pascual Amat",
    "iso:country":"ES",
    "sg:address":"Calle de Pascual Amat, 22",
    "sg:city":"Yecla",
    "sg:orig_category":"Dibujantes (diversos)",
    "sg:phone":"+34 968 79 08 69",
    "sg:postcode":"30510",
    "sg:province":"Murcia",
    "wof:name":"Puche Ferriz Andres",
    "wof:placetype":"venue"
},
  "geometry": {"coordinates":[-1.1164770126,38.6148948669],"type":"Point"}
}