{
  "type": "Feature",
  "properties": {
    "iso:country":"ES",
    "sg:address":"Pl Glories Catalanes, 26",
    "sg:city":"Barcelona",
    "sg:orig_category":"Fabricaci\u00d3n De Moldes Y Modelos",
    "sg:phone":"+34 933 09 59 90",
    "sg:postcode":"08018",
    "sg:province":"Barcelona",
    "wof:name":"Hernando Martin Alejandro",
    "wof:placetype":"venue"
},
  "geometry": {"coordinates":[2.1882739067,41.4030303955],"type":"Point"}
}