{
  "type": "Feature",
  "properties": {
    "iso:country":"ES",
    "sg:address":"Calle de Leonardo Rodriguez, 15",
    "sg:city":"Chantada",
    "sg:orig_category":"Ropa Para Se\u00d1oras Y Caballeros (al Por Menor)",
    "sg:phone":"+34 982 44 05 26",
    "sg:postcode":"27500",
    "sg:province":"Lugo",
    "wof:name":"Lopez Guerra Sara",
    "wof:placetype":"venue"
},
  "geometry": {"coordinates":[-7.7714090347,42.6098518372],"type":"Point"}
}