{
  "type": "Feature",
  "properties": {
    "iso:country":"ES",
    "sg:address":"Calle de Mayor, 6",
    "sg:city":"Madrid",
    "sg:orig_category":"Sindicatos Y Colegios Profesionales",
    "sg:phone":"+34 915 22 51 97",
    "sg:postcode":"28013",
    "sg:province":"Madrid",
    "wof:name":"Asociacion Espa\u00f1ola De Tecnicos De Laboratorio",
    "wof:placetype":"venue"
},
  "geometry": {"coordinates":[-3.7054429054,40.4164619446],"type":"Point"}
}