{
  "type": "Feature",
  "properties": {
    "iso:country":"ES",
    "sg:address":"Kale Zaharra, 34",
    "sg:city":"O\u00f1ati",
    "sg:orig_category":"Molduras, Junquillos, Listones Y Molduras Perforadas",
    "sg:phone":"+34 943 78 35 43",
    "sg:postcode":"20560",
    "sg:province":"Guip\u00f9zcoa",
    "wof:name":"Gorostiaga Urrutia Iker (bar Harripe)",
    "wof:placetype":"venue"
},
  "geometry": {"coordinates":[-2.4143586159,43.0347976685],"type":"Point"}
}