{
  "type": "Feature",
  "properties": {
    "iso:country":"ES",
    "sg:address":"Ctra Madrid, Km. 0351,0",
    "sg:city":"Cieza",
    "sg:orig_category":"Chapister\u00cda",
    "sg:phone":"+34 968 76 06 26",
    "sg:postcode":"30530",
    "sg:province":"Murcia",
    "wof:name":"Comercial Ascoy S.c.l.",
    "wof:placetype":"venue"
},
  "geometry": {"coordinates":[-1.4274940491,38.2550163269],"type":"Point"}
}