{
  "type": "Feature",
  "properties": {
    "iso:country":"ES",
    "sg:address":"Bard Guadajoz, 4",
    "sg:city":"Guadajoz",
    "sg:orig_category":"Droguer\u00cdas (al Por Menor)",
    "sg:phone":"+34 955 64 51 31",
    "sg:postcode":"41339",
    "sg:province":"Sevilla",
    "wof:name":"Cruz Mesa Manuel",
    "wof:placetype":"venue"
},
  "geometry": {"coordinates":[-5.6687679291,37.5800437927],"type":"Point"}
}