{
  "type": "Feature",
  "properties": {
    "iso:country":"ES",
    "sg:address":"Rda. N. Monturiol, 31",
    "sg:city":"Cabrera Mar",
    "sg:orig_category":"Empresas De Carpinter\u00cda De Madera",
    "sg:phone":"+34 937 50 64 62",
    "sg:postcode":"08349",
    "sg:province":"Barcelona",
    "sg:website":"www.aparicio.com",
    "wof:name":"V Aparicio S.a.",
    "wof:placetype":"venue"
},
  "geometry": {"coordinates":[2.4156870842,41.530292511],"type":"Point"}
}