{
  "type": "Feature",
  "properties": {
    "addr:full":"Ctra Plasencia, Km. 0080,0 Adrada \u00c1vila 05430",
    "addr:postcode":"05430",
    "addr:street":"Ctra Plasencia Km. 0080,0;A\u0301Vila",
    "iso:country":"ES",
    "sg:address":"Ctra Plasencia, Km. 0080,0",
    "sg:city":"Adrada",
    "sg:orig_category":"Asociaciones Y Clubs Deportivos",
    "sg:phone":"+34 918 67 08 00",
    "sg:postcode":"05430",
    "sg:province":"\u00c1vila",
    "wof:name":"Natur Alimentos D,agostino S.l",
    "wof:placetype":"venue"
},
  "geometry": {"coordinates":[-4.638753891,40.3024139404],"type":"Point"}
}