{
  "type": "Feature",
  "properties": {
    "addr:full":"Carrer de Frares, 11 S. Joan Despi Barcelona 08970",
    "addr:housenumber":"11",
    "addr:postcode":"08970",
    "addr:street":"Carrer De Frares;S. Joan Despi",
    "iso:country":"ES",
    "sg:address":"Carrer de Frares, 11",
    "sg:city":"S. Joan Despi",
    "sg:orig_category":"Chapister\u00cda",
    "sg:phone":"+34 933 73 13 04",
    "sg:postcode":"08970",
    "sg:province":"Barcelona",
    "wof:name":"Conchillo Del Arco Diego",
    "wof:placetype":"venue"
},
  "geometry": {"coordinates":[2.0770580769,41.3691291809],"type":"Point"}
}