{
  "type": "Feature",
  "properties": {
    "addr:full":"Calle de Republica Argentina, 24 Malaga M\u00e1laga 29016",
    "addr:housenumber":"24",
    "addr:postcode":"29016",
    "addr:street":"Calle De Republica Argentina;Ma\u0301Laga",
    "iso:country":"ES",
    "sg:address":"Calle de Republica Argentina, 24",
    "sg:city":"Malaga",
    "sg:orig_category":"Industria Qu\u00cdmica",
    "sg:phone":"+34 952 22 33 57",
    "sg:postcode":"29016",
    "sg:province":"M\u00e1laga",
    "wof:name":"Lopez Tapia Maria Inmaculada",
    "wof:placetype":"venue"
},
  "geometry": {"coordinates":[-4.398583889,36.728603363],"type":"Point"}
}