{
  "type": "Feature",
  "properties": {
    "iso:country":"ES",
    "sg:address":"Calle de Concejal Julio Gomez, 2",
    "sg:city":"Madrid",
    "sg:orig_category":"Molduras, Junquillos, Listones Y Molduras Perforadas",
    "sg:phone":"+34 914 05 47 76",
    "sg:postcode":"28027",
    "sg:province":"Madrid",
    "wof:name":"Jose Luis Paul De La Fuente S.l.",
    "wof:placetype":"venue"
},
  "geometry": {"coordinates":[-3.6503608227,40.4329566956],"type":"Point"}
}