{
  "type": "Feature",
  "properties": {
    "addr:full":"Carrer de Doctor Ulles, 2 Terrassa Barcelona 08224",
    "addr:housenumber":"2",
    "addr:postcode":"08224",
    "addr:street":"Carrer De Doctor Ulles",
    "iso:country":"ES",
    "sg:address":"Carrer de Doctor Ulles, 2",
    "sg:city":"Terrassa",
    "sg:orig_category":"Asesor\u00cda Fiscal Y Jur\u00cddica",
    "sg:phone":"+34 937 88 55 08",
    "sg:postcode":"08224",
    "sg:province":"Barcelona",
    "wof:name":"Bonastre & Palau Assessors S.l.",
    "wof:placetype":"venue"
},
  "geometry": {"coordinates":[2.0075099468,41.561920166],"type":"Point"}
}