{
  "type": "Feature",
  "properties": {
    "addr:full":"Carr Cadi, 7 Alp Girona 17538",
    "addr:housenumber":"7",
    "addr:postcode":"17538",
    "addr:street":"Carr Cadi",
    "iso:country":"ES",
    "sg:address":"Carr Cadi, 7",
    "sg:city":"Alp",
    "sg:orig_category":"Asociaciones Y Clubs Deportivos",
    "sg:phone":"+34 972 89 17 28",
    "sg:postcode":"17538",
    "sg:province":"Girona",
    "wof:name":"Hernandez Morales Jose Antonio",
    "wof:placetype":"venue"
},
  "geometry": {"coordinates":[1.8867280483,42.3738555908],"type":"Point"}
}