{
  "type": "Feature",
  "properties": {
    "iso:country":"ES",
    "sg:address":"Carrer de Major, 19",
    "sg:city":"Terrassa",
    "sg:orig_category":"M\u00c9dicos: Oftalmolog\u00cda",
    "sg:phone":"+34 937 88 57 82",
    "sg:postcode":"08221",
    "sg:province":"Barcelona",
    "wof:name":"Gonzalez San Juan Maria Elena",
    "wof:placetype":"venue"
},
  "geometry": {"coordinates":[2.0095369816,41.5611038208],"type":"Point"}
}