{
  "type": "Feature",
  "properties": {
    "iso:country":"ES",
    "sg:address":"Salgosa, 7",
    "sg:city":"Salgosa",
    "sg:orig_category":"Poller\u00cda Y Caza (al Por Menor)",
    "sg:phone":"+34 986 62 21 93",
    "sg:postcode":"36740",
    "sg:province":"Pontevedra",
    "wof:name":"Alvarez De Santiago Manuel",
    "wof:placetype":"venue"
},
  "geometry": {"coordinates":[-8.6480531693,42.4336204529],"type":"Point"}
}