{
  "type": "Feature",
  "properties": {
    "addr:full":"Carrer de Barcelona, 56 Palleja Barcelona 08780",
    "addr:housenumber":"56",
    "addr:postcode":"08780",
    "addr:street":"Carrer De Barcelona",
    "iso:country":"ES",
    "sg:address":"Carrer de Barcelona, 56",
    "sg:city":"Palleja",
    "sg:orig_category":"Promotores Constructores",
    "sg:phone":"+34 936 63 41 09",
    "sg:postcode":"08780",
    "sg:province":"Barcelona",
    "wof:name":"Obres I Reparacions Yherla S.l.",
    "wof:placetype":"venue"
},
  "geometry": {"coordinates":[1.9973299503,41.4173469543],"type":"Point"}
}