{
  "type": "Feature",
  "properties": {
    "addr:full":"Rua Irida, S/n Estrada Pontevedra 36680",
    "addr:housenumber":"s / n",
    "addr:postcode":"36680",
    "addr:street":"Rua Irida;Estrada Pontevedra",
    "iso:country":"ES",
    "sg:address":"Rua Irida, S/n",
    "sg:city":"Estrada",
    "sg:orig_category":"Transportes Por Carretera: Lotes Completos, Mercanc\u00cdas Diversas",
    "sg:phone":"+34 986 57 50 06",
    "sg:postcode":"36680",
    "sg:province":"Pontevedra",
    "wof:name":"Vego Supermercados S.a.",
    "wof:placetype":"venue"
},
  "geometry": {"coordinates":[-8.4910736084,42.6887664795],"type":"Point"}
}