{
  "type": "Feature",
  "properties": {
    "iso:country":"ES",
    "sg:address":"Avda Andalucia, 52",
    "sg:city":"Palma Rio",
    "sg:orig_category":"Producci\u00d3n, Distribuci\u00d3n De Electricidad",
    "sg:phone":"+34 957 64 48 11",
    "sg:postcode":"14700",
    "sg:province":"C\u00f3rdoba",
    "wof:name":"Barcena Onieva Jose Miguel",
    "wof:placetype":"venue"
},
  "geometry": {"coordinates":[-5.2783927917,37.693523407],"type":"Point"}
}