{
  "type": "Feature",
  "properties": {
    "iso:country":"ES",
    "sg:address":"Crri Parragas, 23",
    "sg:city":"Nonduermas",
    "sg:orig_category":"Edici\u00d3n De Diarios, Revistas, Boletines",
    "sg:phone":"+34 968 26 60 58",
    "sg:postcode":"30166",
    "sg:province":"Murcia",
    "wof:name":"Hermes Editora General S.a.",
    "wof:placetype":"venue"
},
  "geometry": {"coordinates":[-1.175778985,37.9699516296],"type":"Point"}
}