{
  "type": "Feature",
  "properties": {
    "addr:full":"Rua Urzaiz, 96 Vigo Pontevedra 36204",
    "addr:housenumber":"96",
    "addr:postcode":"36204",
    "addr:street":"Rua Urzaiz",
    "iso:country":"ES",
    "sg:address":"Rua Urzaiz, 96",
    "sg:city":"Vigo",
    "sg:orig_category":"Perfumer\u00cda (al Por Menor)",
    "sg:phone":"+34 986 41 40 28",
    "sg:postcode":"36204",
    "sg:province":"Pontevedra",
    "wof:name":"Perfumeria Lar S.l.",
    "wof:placetype":"venue"
},
  "geometry": {"coordinates":[-8.7122879028,42.2327270508],"type":"Point"}
}