{
  "type": "Feature",
  "properties": {
    "iso:country":"ES",
    "sg:address":"Carrer de Ravaleta (de), 13",
    "sg:city":"Canonja",
    "sg:orig_category":"Carnicer\u00cdas, Carnicer\u00cdas",
    "sg:phone":"+34 977 54 48 98",
    "sg:postcode":"43110",
    "sg:province":"Tarragona",
    "wof:name":"Porta Rialp Jose",
    "wof:placetype":"venue"
},
  "geometry": {"coordinates":[1.1796230078,41.1233215332],"type":"Point"}
}