{
  "type": "Feature",
  "properties": {
    "addr:full":"Av Montserrat, 17 Lli\u00e7a Vall Barcelona 08185",
    "addr:housenumber":"17",
    "addr:postcode":"08185",
    "addr:street":"Av Montserrat;Vall Barcelona",
    "iso:country":"ES",
    "sg:address":"Av Montserrat, 17",
    "sg:city":"Lli\u00e7a Vall",
    "sg:orig_category":"Molduras, Junquillos, Listones Y Molduras Perforadas",
    "sg:phone":"+34 938 43 93 85",
    "sg:postcode":"08185",
    "sg:province":"Barcelona",
    "wof:name":"Puig Parera Jaume",
    "wof:placetype":"venue"
},
  "geometry": {"coordinates":[2.2429740429,41.5922737122],"type":"Point"}
}