{
  "type": "Feature",
  "properties": {
    "iso:country":"ES",
    "sg:address":"Calle de M, 11",
    "sg:city":"Mutiloabeiti",
    "sg:orig_category":"Estudios, Instalaci\u00d3n De Climatizaci\u00d3n",
    "sg:phone":"+34 948 23 65 91",
    "sg:postcode":"31192",
    "sg:province":"Navarra",
    "wof:name":"Zortziok S.coop.l.",
    "wof:placetype":"venue"
},
  "geometry": {"coordinates":[-1.634578824,42.8070755005],"type":"Point"}
}