{
  "type": "Feature",
  "properties": {
    "addr:full":"Camino Viejo De Cehegin, 7 Caravaca Cruz Murcia 30400",
    "addr:housenumber":"7",
    "addr:postcode":"30400",
    "addr:street":"Camino Viejo De Cehegin",
    "iso:country":"ES",
    "sg:address":"Camino Viejo De Cehegin, 7",
    "sg:city":"Caravaca Cruz",
    "sg:orig_category":"Confecci\u00d3n De Zapatos",
    "sg:phone":"+34 968 70 35 16",
    "sg:postcode":"30400",
    "sg:province":"Murcia",
    "wof:name":"Calzados Dalson S.l.",
    "wof:placetype":"venue"
},
  "geometry": {"coordinates":[-1.8645700216,38.104763031],"type":"Point"}
}