{
  "type": "Feature",
  "properties": {
    "addr:full":"Carretera De Badajoz-huelva, Km. 0006,9 Almendral Badajoz 06171",
    "addr:postcode":"06171",
    "addr:street":"Carretera De Badajoz-Huelva Km. 0006,9",
    "iso:country":"ES",
    "sg:address":"Carretera De Badajoz-huelva, Km. 0006,9",
    "sg:city":"Almendral",
    "sg:orig_category":"Agricultores, Agricultores",
    "sg:phone":"+34 924 14 06 56",
    "sg:postcode":"06171",
    "sg:province":"Badajoz",
    "wof:name":"Sanchez Ayuso Elvira",
    "wof:placetype":"venue"
},
  "geometry": {"coordinates":[-6.8223757744,38.6122398376],"type":"Point"}
}