{
  "type": "Feature",
  "properties": {
    "iso:country":"ES",
    "sg:address":"Zelaia Auzoa, 1",
    "sg:city":"Zelaia",
    "sg:orig_category":"Administraciones Regionales, Departamentales Y Locales",
    "sg:phone":"+34 946 31 56 89",
    "sg:postcode":"48140",
    "sg:province":"Vizcaya",
    "wof:name":"Ayuntamiento De Aranzazu",
    "wof:placetype":"venue"
},
  "geometry": {"coordinates":[-2.7914814949,43.1569023132],"type":"Point"}
}