{
  "type": "Feature",
  "properties": {
    "addr:full":"Calle de Virgen Del Pilar, 11 Almodovar Campo Ciudad Real 13580",
    "addr:housenumber":"11",
    "addr:postcode":"13580",
    "addr:street":"Calle De Virgen Del Pilar",
    "iso:country":"ES",
    "sg:address":"Calle de Virgen Del Pilar, 11",
    "sg:city":"Almodovar Campo",
    "sg:orig_category":"Chapister\u00cda",
    "sg:phone":"+34 926 48 36 45",
    "sg:postcode":"13580",
    "sg:province":"Ciudad Real",
    "wof:name":"Talleres Candeluis S.l.l.",
    "wof:placetype":"venue"
},
  "geometry": {"coordinates":[-4.176504612,38.7051734924],"type":"Point"}
}