{
  "type": "Feature",
  "properties": {
    "iso:country":"ES",
    "sg:address":"Ctra Villaviciosa, S/n",
    "sg:city":"Gijon",
    "sg:orig_category":"Venta, Instalaci\u00d3n De Cocinas",
    "sg:phone":"+34 985 13 08 01",
    "sg:postcode":"33203",
    "sg:province":"Asturias",
    "wof:name":"Hosteleria La Llorea S.l.",
    "wof:placetype":"venue"
},
  "geometry": {"coordinates":[-5.6453800201,43.5347251892],"type":"Point"}
}