{
  "type": "Feature",
  "properties": {
    "iso:country":"ES",
    "sg:address":"Ctra Matola, S/n",
    "sg:city":"Elche",
    "sg:orig_category":"Agricultores, Agricultores",
    "sg:phone":"+34 966 64 01 90",
    "sg:postcode":"03204",
    "sg:province":"Alicante",
    "wof:name":"Restaurante Matola S.l.",
    "wof:placetype":"venue"
},
  "geometry": {"coordinates":[-0.7038729787,38.2519683838],"type":"Point"}
}