{
  "type": "Feature",
  "properties": {
    "iso:country":"ES",
    "sg:address":"Inmaculada, 5",
    "sg:city":"Pontedeume",
    "sg:orig_category":"Electrodom\u00c9sticos (al Por Menor)",
    "sg:phone":"+34 981 43 00 45",
    "sg:postcode":"15600",
    "sg:province":"La Coru\u00f1a",
    "wof:name":"Eumegas S.l.",
    "wof:placetype":"venue"
},
  "geometry": {"coordinates":[-8.1705942154,43.4071388245],"type":"Point"}
}