{
  "type": "Feature",
  "properties": {
    "addr:full":"Avda Encartaciones, 26 Balmaseda Vizcaya 48800",
    "addr:housenumber":"26",
    "addr:postcode":"48800",
    "addr:street":"Avda Encartaciones",
    "iso:country":"ES",
    "sg:address":"Avda Encartaciones, 26",
    "sg:city":"Balmaseda",
    "sg:orig_category":"Caf\u00c9s, Bares, Cervecer\u00cdas",
    "sg:phone":"+34 946 10 30 82",
    "sg:postcode":"48800",
    "sg:province":"Vizcaya",
    "wof:name":"Lopez Ventades Francisco De Borja",
    "wof:placetype":"venue"
},
  "geometry": {"coordinates":[-3.2004749775,43.1899490356],"type":"Point"}
}