{
  "type": "Feature",
  "properties": {
    "iso:country":"ES",
    "sg:address":"Calle de De Gabriel, 3",
    "sg:city":"Badajoz",
    "sg:orig_category":"Alimentaci\u00d3n General (al Por Menor)",
    "sg:phone":"+34 924 22 40 01",
    "sg:postcode":"06001",
    "sg:province":"Badajoz",
    "wof:name":"Mendez Martin Jose Antonio",
    "wof:placetype":"venue"
},
  "geometry": {"coordinates":[-6.9727520943,38.8789405823],"type":"Point"}
}