{
  "type": "Feature",
  "properties": {
    "addr:full":"Calle de Sevilla, 17 Zafra Badajoz 06300",
    "addr:housenumber":"17",
    "addr:postcode":"06300",
    "addr:street":"Calle De Sevilla",
    "iso:country":"ES",
    "sg:address":"Calle de Sevilla, 17",
    "sg:city":"Zafra",
    "sg:orig_category":"Bisuter\u00cda, Joyer\u00cda, Relojer\u00cda (al Por Menor)",
    "sg:phone":"+34 924 55 15 77",
    "sg:postcode":"06300",
    "sg:province":"Badajoz",
    "wof:name":"Toro Garrido Maria Teresa",
    "wof:placetype":"venue"
},
  "geometry": {"coordinates":[-6.4185562134,38.4242858887],"type":"Point"}
}