{
  "type": "Feature",
  "properties": {
    "iso:country":"ES",
    "sg:address":"Rbla Sant Andreu (de), 4",
    "sg:city":"Ripollet",
    "sg:orig_category":"Empresas De Pintura Y Revestimientos",
    "sg:phone":"+34 936 92 67 38",
    "sg:postcode":"08291",
    "sg:province":"Barcelona",
    "wof:name":"Firart S.l.",
    "wof:placetype":"venue"
},
  "geometry": {"coordinates":[2.1600370407,41.5010414124],"type":"Point"}
}