{
  "type": "Feature",
  "properties": {
    "addr:full":"Rua Mexico, 24 Vigo Pontevedra 36204",
    "addr:housenumber":"24",
    "addr:postcode":"36204",
    "addr:street":"Rua Mexico",
    "iso:country":"ES",
    "sg:address":"Rua Mexico, 24",
    "sg:city":"Vigo",
    "sg:orig_category":"Arquitectos",
    "sg:phone":"+34 986 41 38 00",
    "sg:postcode":"36204",
    "sg:province":"Pontevedra",
    "wof:name":"Garrido Rodriguez Jaime",
    "wof:placetype":"venue"
},
  "geometry": {"coordinates":[-8.7155256271,42.2329559326],"type":"Point"}
}