{
  "type": "Feature",
  "properties": {
    "addr:full":"Avda. Alpujarra, 12 Pampaneira Granada 18411",
    "addr:housenumber":"12",
    "addr:postcode":"18411",
    "addr:street":"Avda. Alpujarra",
    "iso:country":"ES",
    "sg:address":"Avda. Alpujarra, 12",
    "sg:city":"Pampaneira",
    "sg:orig_category":"Artesan\u00cda",
    "sg:phone":"+34 958 76 33 94",
    "sg:postcode":"18411",
    "sg:province":"Granada",
    "wof:name":"Martin Martin Francisco Daniel",
    "wof:placetype":"venue"
},
  "geometry": {"coordinates":[-3.36124897,36.9397773743],"type":"Point"}
}