{
  "type": "Feature",
  "properties": {
    "addr:full":"Calle de Mateo Errota, 3 Donostia-san Sebastian Guip\u00f9zcoa 20014",
    "addr:housenumber":"3",
    "addr:postcode":"20014",
    "addr:street":"Calle De Mateo Errota",
    "iso:country":"ES",
    "sg:address":"Calle de Mateo Errota, 3",
    "sg:city":"Donostia-san Sebastian",
    "sg:orig_category":"Muebles",
    "sg:phone":"+34 943 44 59 91",
    "sg:postcode":"20014",
    "sg:province":"Guip\u00f9zcoa",
    "wof:name":"Coop Cocinas S.l.",
    "wof:placetype":"venue"
},
  "geometry": {"coordinates":[-1.9457269907,43.3015060425],"type":"Point"}
}