{
  "type": "Feature",
  "properties": {
    "iso:country":"ES",
    "sg:address":"Calle de Cristo Del, 5",
    "sg:city":"Bilbao",
    "sg:orig_category":"Fabricaci\u00d3n, Distribuci\u00d3n De Discos, V\u00cddeodiscos Y Musicassettes",
    "sg:phone":"+34 944 46 54 75",
    "sg:postcode":"48007",
    "sg:province":"Vizcaya",
    "wof:name":"Saez De La Fuente Gonzalez Jaime",
    "wof:placetype":"venue"
},
  "geometry": {"coordinates":[-2.9224734306,43.2650871277],"type":"Point"}
}