{
  "type": "Feature",
  "properties": {
    "iso:country":"ES",
    "sg:address":"Calle de Oscurilla, 10",
    "sg:city":"Villamayor De Calatrava",
    "sg:orig_category":"Empresarios",
    "sg:phone":"+34 926 46 61 75",
    "sg:postcode":"13595",
    "sg:province":"Ciudad Real",
    "wof:name":"Espinosa Ure\u00f1a Jose",
    "wof:placetype":"venue"
},
  "geometry": {"coordinates":[-4.1385450363,38.7886505127],"type":"Point"}
}