{
  "type": "Feature",
  "properties": {
    "iso:country":"ES",
    "sg:address":"Ctra. Nueva Carteya, Km. 0000,5",
    "sg:city":"Montilla",
    "sg:orig_category":"Empresas De Carpinter\u00cda De Madera",
    "sg:phone":"+34 957 65 13 17",
    "sg:postcode":"14550",
    "sg:province":"C\u00f3rdoba",
    "wof:name":"Carpinteria Moyano S.l.",
    "wof:placetype":"venue"
},
  "geometry": {"coordinates":[-4.6205668449,37.5800590515],"type":"Point"}
}