{
  "type": "Feature",
  "properties": {
    "iso:country":"ES",
    "sg:address":"Calle de Palma De Mallorca, 11",
    "sg:city":"Palmas De Gran Canaria",
    "sg:orig_category":"Reposter\u00cdas",
    "sg:phone":"+34 928 33 22 98",
    "sg:postcode":"35016",
    "sg:province":"Las Palmas",
    "wof:name":"Panificadora San Cristobal S.l.",
    "wof:placetype":"venue"
},
  "geometry": {"coordinates":[-15.4177284241,28.0934963226],"type":"Point"}
}