{
  "type": "Feature",
  "properties": {
    "addr:full":"Pla\u00c7 De La Concepci\u00e9, 8 Ontinyent Valencia 46870",
    "addr:housenumber":"8",
    "addr:postcode":"46870",
    "iso:country":"ES",
    "sg:address":"Pla\u00c7 De La Concepci\u00e9, 8",
    "sg:city":"Ontinyent",
    "sg:orig_category":"Cajas De Ahorro",
    "sg:phone":"+34 962 91 53 31",
    "sg:postcode":"46870",
    "sg:province":"Valencia",
    "wof:name":"Caja De Ahorros De Onteniente",
    "wof:placetype":"venue"
},
  "geometry": {"coordinates":[-0.6030989885,38.8258895874],"type":"Point"}
}