{
  "type": "Feature",
  "properties": {
    "addr:full":"Calle de San Isidro, 6 Alcorcon Madrid 28921",
    "addr:housenumber":"6",
    "addr:postcode":"28921",
    "addr:street":"Calle De San Isidro",
    "iso:country":"ES",
    "sg:address":"Calle de San Isidro, 6",
    "sg:city":"Alcorcon",
    "sg:orig_category":"Maquinaria Para Industrias Diversas",
    "sg:phone":"+34 916 19 26 49",
    "sg:postcode":"28921",
    "sg:province":"Madrid",
    "sg:website":"www.divenal.com",
    "wof:name":"Divenal Sl",
    "wof:placetype":"venue"
},
  "geometry": {"coordinates":[-3.8288099766,40.3501586914],"type":"Point"}
}