{
  "type": "Feature",
  "properties": {
    "addr:full":"Calle de Fabrica Nueva, 32 Salobre\u00f1a Granada 18680",
    "addr:housenumber":"32 salobren\u0303a",
    "addr:postcode":"18680",
    "addr:street":"Calle De;Nueva",
    "iso:country":"ES",
    "sg:address":"Calle de Fabrica Nueva, 32",
    "sg:city":"Salobre\u00f1a",
    "sg:orig_category":"Cer\u00c1micas: Material Y Suministros",
    "sg:phone":"+34 958 61 02 52",
    "sg:postcode":"18680",
    "sg:province":"Granada",
    "wof:name":"Merino Garcia Jose",
    "wof:placetype":"venue"
},
  "geometry": {"coordinates":[-3.5850589275,36.743976593],"type":"Point"}
}