{
  "type": "Feature",
  "properties": {
    "addr:full":"Avda Enrique Mederos, 49 Llanos De Aridane Santa Cruz De Tenerife 38760",
    "addr:housenumber":"49",
    "addr:postcode":"38760",
    "addr:street":"Avda Enrique Mederos",
    "iso:country":"ES",
    "sg:address":"Avda Enrique Mederos, 49",
    "sg:city":"Llanos De Aridane",
    "sg:orig_category":"Ropa Para Se\u00d1oras Y Caballeros (al Por Menor)",
    "sg:phone":"+34 922 46 03 00",
    "sg:postcode":"38760",
    "sg:province":"Santa Cruz De Tenerife",
    "wof:name":"Lorenzo Lorenzo Maria Nela",
    "wof:placetype":"venue"
},
  "geometry": {"coordinates":[-17.9085597992,28.6563796997],"type":"Point"}
}