{
  "type": "Feature",
  "properties": {
    "iso:country":"ES",
    "sg:address":"Avda Principal, 72",
    "sg:city":"Navas Del Marques",
    "sg:orig_category":"Supermercados Y Hipermercados",
    "sg:phone":"+34 918 97 00 12",
    "sg:postcode":"05230",
    "sg:province":"\u00c1vila",
    "wof:name":"Cermol 79 S.a.",
    "wof:placetype":"venue"
},
  "geometry": {"coordinates":[-4.3341851234,40.6024551392],"type":"Point"}
}