{
  "type": "Feature",
  "properties": {
    "iso:country":"ES",
    "sg:address":"Lavacerido(meiras), S/n",
    "sg:city":"Meiras",
    "sg:orig_category":"Centros Empresariales",
    "sg:phone":"+34 981 48 51 51",
    "sg:postcode":"15550",
    "sg:province":"A Coru\u00f1a",
    "wof:name":"Villa De Cedeira S.l.",
    "wof:placetype":"venue"
},
  "geometry": {"coordinates":[-8.1737756729,43.5668754578],"type":"Point"}
}