{
  "type": "Feature",
  "properties": {
    "addr:full":"Matsaria Kalea, 12 Eibar Guip\u00f9zcoa 20600",
    "addr:housenumber":"12",
    "addr:postcode":"20600",
    "addr:street":"Matsaria Kalea;Guipu\u0300Zcoa",
    "iso:country":"ES",
    "sg:address":"Matsaria Kalea, 12",
    "sg:city":"Eibar",
    "sg:orig_category":"Limpieza Con Chorro De Arena Y Con Granalla, Pulido",
    "sg:phone":"+34 943 20 64 35",
    "sg:postcode":"20600",
    "sg:province":"Guip\u00f9zcoa",
    "wof:name":"Pulimentos Arga S.l.",
    "wof:placetype":"venue"
},
  "geometry": {"coordinates":[-2.4673190117,43.1915397644],"type":"Point"}
}