{
  "type": "Feature",
  "properties": {
    "addr:full":"Calle de Resina, 27 Pinar De Antequera Valladolid 47153",
    "addr:housenumber":"27",
    "addr:postcode":"47153",
    "addr:street":"Calle De Resina",
    "iso:country":"ES",
    "sg:address":"Calle de Resina, 27",
    "sg:city":"Pinar De Antequera",
    "sg:orig_category":"Asilos De Ancianos. Centros Privados",
    "sg:phone":"+34 983 24 66 42",
    "sg:postcode":"47153",
    "sg:province":"Valladolid",
    "wof:name":"Resinas 27 S.l",
    "wof:placetype":"venue"
},
  "geometry": {"coordinates":[-4.7533807755,41.5858268738],"type":"Point"}
}