{
  "type": "Feature",
  "properties": {
    "addr:full":"Cmno Fojanes (somio), 435 Gijon Asturias 33203",
    "addr:housenumber":"435",
    "addr:postcode":"33203",
    "addr:street":"Cmno Fojanes Somio",
    "iso:country":"ES",
    "sg:address":"Cmno Fojanes (somio), 435",
    "sg:city":"Gijon",
    "sg:orig_category":"Ingenier\u00cda, Centros De Estudios (diversos)",
    "sg:phone":"+34 985 37 31 50",
    "sg:postcode":"33203",
    "sg:province":"Asturias",
    "wof:name":"Servicios Energeticos S.l.",
    "wof:placetype":"venue"
},
  "geometry": {"coordinates":[-5.5962839127,43.5261116028],"type":"Point"}
}