{
  "type": "Feature",
  "properties": {
    "addr:full":"Ctra Aracena, Km. 0045,5 Castillo Guardas Sevilla 41890",
    "addr:postcode":"41890",
    "addr:street":"Ctra Aracena Km. 0045,5;Guardas",
    "iso:country":"ES",
    "sg:address":"Ctra Aracena, Km. 0045,5",
    "sg:city":"Castillo Guardas",
    "sg:orig_category":"Cr\u00cda De Bovinos",
    "sg:phone":"+34 955 95 22 66",
    "sg:postcode":"41890",
    "sg:province":"Sevilla",
    "wof:name":"Los Olivos De Buena Vista S.l.",
    "wof:placetype":"venue"
},
  "geometry": {"coordinates":[-6.3137922287,37.6944007874],"type":"Point"}
}