{
  "type": "Feature",
  "properties": {
    "addr:full":"Avda Alcalde Don Juan Rodriguez, 36 Barrios C\u00e1diz 11370",
    "addr:housenumber":"36",
    "addr:postcode":"11370",
    "addr:street":"Avda Alcalde Don Juan Rodriguez;Ca\u0301Diz",
    "iso:country":"ES",
    "sg:address":"Avda Alcalde Don Juan Rodriguez, 36",
    "sg:city":"Barrios",
    "sg:orig_category":"T\u00c9cnicos Veterinarios",
    "sg:phone":"+34 956 62 15 18",
    "sg:postcode":"11370",
    "sg:province":"C\u00e1diz",
    "wof:name":"Garcia Gonzalez Fernando",
    "wof:placetype":"venue"
},
  "geometry": {"coordinates":[-5.4902529716,36.1868896484],"type":"Point"}
}