{
  "type": "Feature",
  "properties": {
    "addr:full":"Avda Comuneros, S/n Salamanca Salamanca 37003",
    "addr:housenumber":"s / n",
    "addr:postcode":"37003",
    "addr:street":"Avda Comuneros",
    "iso:country":"ES",
    "sg:address":"Avda Comuneros, S/n",
    "sg:city":"Salamanca",
    "sg:orig_category":"Molduras, Junquillos, Listones Y Molduras Perforadas",
    "sg:phone":"+34 923 26 68 49",
    "sg:postcode":"37003",
    "sg:province":"Salamanca",
    "wof:name":"Servicios Monleon C.b.",
    "wof:placetype":"venue"
},
  "geometry": {"coordinates":[-5.6557588577,40.9686546326],"type":"Point"}
}