{
  "type": "Feature",
  "properties": {
    "iso:country":"ES",
    "sg:address":"Ctra Obispo, 42",
    "sg:city":"Gijon",
    "sg:orig_category":"Promotores Constructores",
    "sg:phone":"+34 985 16 10 19",
    "sg:postcode":"33210",
    "sg:province":"Asturias",
    "wof:name":"Josefina Cienfuegos Gonzales",
    "wof:placetype":"venue"
},
  "geometry": {"coordinates":[-5.6656889915,43.5222015381],"type":"Point"}
}