{
  "type": "Feature",
  "properties": {
    "addr:full":"Avda Rey Juan Carlos I, S/n Roquetas Mar Almer\u00eda 04740",
    "addr:housenumber":"s",
    "addr:postcode":"04740",
    "addr:street":"Avda Rey Juan Carlos I;/ N Roquetas Mar Almeri\u0301A",
    "iso:country":"ES",
    "sg:address":"Avda Rey Juan Carlos I, S/n",
    "sg:city":"Roquetas Mar",
    "sg:orig_category":"Cajas Para Embalar",
    "sg:phone":"+34 950 32 30 07",
    "sg:postcode":"04740",
    "sg:province":"Almer\u00eda",
    "wof:name":"Cajamar",
    "wof:placetype":"venue"
},
  "geometry": {"coordinates":[-2.6132490635,36.7652740479],"type":"Point"}
}