{
  "type": "Feature",
  "properties": {
    "iso:country":"ES",
    "sg:address":"Calle de Aguzanieves, 4",
    "sg:city":"Miranda Ebro",
    "sg:orig_category":"Laboratorios",
    "sg:phone":"+34 947 33 63 03",
    "sg:postcode":"09200",
    "sg:province":"Burgos",
    "wof:name":"Asistencia Tecnica Industrial S.a.e.",
    "wof:placetype":"venue"
},
  "geometry": {"coordinates":[-2.9702689648,42.6807365417],"type":"Point"}
}