{
  "type": "Feature",
  "properties": {
    "addr:full":"Calle de Vinader, 6 Santa Catalina Murcia 30004",
    "addr:housenumber":"6",
    "addr:postcode":"30004",
    "addr:street":"Calle De Vinader",
    "iso:country":"ES",
    "sg:address":"Calle de Vinader, 6",
    "sg:city":"Santa Catalina",
    "sg:orig_category":"Promotores Constructores",
    "sg:phone":"+34 968 22 56 46",
    "sg:postcode":"30004",
    "sg:province":"Murcia",
    "wof:name":"Sociedad Anonima De Riegos Caminos Y Obras S.a.",
    "wof:placetype":"venue"
},
  "geometry": {"coordinates":[-1.1334539652,37.9863891602],"type":"Point"}
}