{
  "type": "Feature",
  "properties": {
    "iso:country":"ES",
    "sg:address":"Calle de Arturo Soria, 189",
    "sg:city":"Madrid",
    "sg:orig_category":"Ense\u00d1anza: Profesiones Art\u00cdsticas",
    "sg:phone":"+34 915 19 17 51",
    "sg:postcode":"28043",
    "sg:province":"Madrid",
    "wof:name":"Garcia Nguyen Jose",
    "wof:placetype":"venue"
},
  "geometry": {"coordinates":[-3.6593511105,40.4585914612],"type":"Point"}
}