{
  "type": "Feature",
  "properties": {
    "iso:country":"ES",
    "sg:address":"Carrer de Amadeu I, 23",
    "sg:city":"Masnou",
    "sg:orig_category":"Madera Para Construcci\u00d3n E Industria",
    "sg:phone":"+34 935 55 29 37",
    "sg:postcode":"08320",
    "sg:province":"Barcelona",
    "wof:name":"Calvo Callejon Carlos",
    "wof:placetype":"venue"
},
  "geometry": {"coordinates":[2.307363987,41.4768981934],"type":"Point"}
}