{
  "type": "Feature",
  "properties": {
    "addr:full":"Avda Ernestina Otero, 21 Redondela Pontevedra 36800",
    "addr:housenumber":"21",
    "addr:postcode":"36800",
    "addr:street":"Avda Ernestina Otero",
    "iso:country":"ES",
    "sg:address":"Avda Ernestina Otero, 21",
    "sg:city":"Redondela",
    "sg:orig_category":"Artes Gr\u00c1ficas, Artes Pl\u00c1sticas (curso)",
    "sg:phone":"+34 986 40 23 48",
    "sg:postcode":"36800",
    "sg:province":"Pontevedra",
    "wof:name":"Otero Castro Tania",
    "wof:placetype":"venue"
},
  "geometry": {"coordinates":[-8.6100082397,42.2835464478],"type":"Point"}
}