{
  "type": "Feature",
  "properties": {
    "iso:country":"ES",
    "sg:address":"Calle de Trafalgar (de), 2",
    "sg:city":"Coslada",
    "sg:orig_category":"Molduras, Junquillos, Listones Y Molduras Perforadas",
    "sg:phone":"+34 916 73 52 35",
    "sg:postcode":"28820",
    "sg:province":"Madrid",
    "wof:name":"Polanco Redondo Julio",
    "wof:placetype":"venue"
},
  "geometry": {"coordinates":[-3.5642170906,40.4243507385],"type":"Point"}
}