{
  "type": "Feature",
  "properties": {
    "addr:full":"Finca El Tesoro, S/n Villarrobledo Albacete 02600",
    "addr:housenumber":"/ n",
    "addr:postcode":"02600",
    "addr:street":"S",
    "iso:country":"ES",
    "sg:address":"Finca El Tesoro, S/n",
    "sg:city":"Villarrobledo",
    "sg:orig_category":"Asociaciones Y Clubs Deportivos",
    "sg:phone":"+34 967 57 31 39",
    "sg:postcode":"02600",
    "sg:province":"Albacete",
    "wof:name":"Sociedad Agraria De Transformacion Num 8175 Terrabona",
    "wof:placetype":"venue"
},
  "geometry": {"coordinates":[-0.6567689776,38.0584983826],"type":"Point"}
}