{
  "type": "Feature",
  "properties": {
    "iso:country":"ES",
    "sg:address":"Calle de San Juan, 31",
    "sg:city":"Sanlucar De Barrameda",
    "sg:orig_category":"Iglesia Cat\u00d3lica",
    "sg:phone":"+34 956 36 05 40",
    "sg:postcode":"11540",
    "sg:province":"C\u00e1diz",
    "wof:name":"Parroquia Del Carmen",
    "wof:placetype":"venue"
},
  "geometry": {"coordinates":[-6.3547120094,36.778137207],"type":"Point"}
}