{
  "type": "Feature",
  "properties": {
    "iso:country":"ES",
    "sg:address":"Calle de Cordoba, 7",
    "sg:city":"Malaga",
    "sg:orig_category":"Hoteles",
    "sg:phone":"+34 952 22 73 00",
    "sg:postcode":"29001",
    "sg:province":"M\u00e1laga",
    "wof:name":"Hotel Lis S.l.",
    "wof:placetype":"venue"
},
  "geometry": {"coordinates":[-4.422191143,36.716796875],"type":"Point"}
}