{
  "type": "Feature",
  "properties": {
    "iso:country":"ES",
    "sg:address":"Avda Santiago (de), 7",
    "sg:city":"Rubian",
    "sg:orig_category":"Alimentaci\u00d3n General (al Por Menor)",
    "sg:phone":"+34 982 42 40 16",
    "sg:postcode":"27350",
    "sg:province":"Lugo",
    "wof:name":"Vali\u00f1a Arias Pilar",
    "wof:placetype":"venue"
},
  "geometry": {"coordinates":[-7.4779639244,42.6528358459],"type":"Point"}
}