{
  "type": "Feature",
  "properties": {
    "addr:full":"Ctra. Portocolom, 1 Felanitx Islas Baleares 07200",
    "addr:housenumber":"1",
    "addr:postcode":"07200",
    "addr:street":"Ctra. Portocolom",
    "iso:country":"ES",
    "sg:address":"Ctra. Portocolom, 1",
    "sg:city":"Felanitx",
    "sg:orig_category":"Distribuci\u00d3n De Petr\u00d3leo Y Derivados",
    "sg:phone":"+34 971 58 31 61",
    "sg:postcode":"07200",
    "sg:province":"Islas Baleares",
    "wof:name":"Gasolinera Canto D'en Masana S.l.",
    "wof:placetype":"venue"
},
  "geometry": {"coordinates":[3.1542959213,39.4742164612],"type":"Point"}
}