{
  "type": "Feature",
  "properties": {
    "iso:country":"ES",
    "sg:address":"Calle de Altozano, 6",
    "sg:city":"Montiel",
    "sg:orig_category":"Iglesia Cat\u00d3lica",
    "sg:phone":"+34 926 35 30 80",
    "sg:postcode":"13326",
    "sg:province":"Ciudad Real",
    "wof:name":"Parroquia San Sebastian",
    "wof:placetype":"venue"
},
  "geometry": {"coordinates":[-2.8621504307,38.6968688965],"type":"Point"}
}