{
  "type": "Feature",
  "properties": {
    "iso:country":"ES",
    "sg:address":"Calle de Don Ricardo, 2",
    "sg:city":"Malaga",
    "sg:orig_category":"Muebles Y Accesorios Para Cocinas Y Cuartos De Ba\u00d1o (al Por Menor)",
    "sg:phone":"+34 952 28 92 99",
    "sg:postcode":"29007",
    "sg:province":"M\u00e1laga",
    "wof:name":"Delgado Labrador Diego",
    "wof:placetype":"venue"
},
  "geometry": {"coordinates":[-4.4302158356,36.7193565369],"type":"Point"}
}