{
  "type": "Feature",
  "properties": {
    "addr:full":"Calle de Nieremberg, 29 Madrid Madrid 28002",
    "addr:housenumber":"29",
    "addr:postcode":"madrid;28002",
    "addr:street":"Calle De Nieremberg",
    "iso:country":"ES",
    "sg:address":"Calle de Nieremberg, 29",
    "sg:city":"Madrid",
    "sg:orig_category":"Asesor\u00cda Fiscal Y Jur\u00cddica",
    "sg:phone":"+34 914 16 23 43",
    "sg:postcode":"28002",
    "sg:province":"Madrid",
    "wof:name":"Gabinete Asesor De Empresas Mg 97 S.l.",
    "wof:placetype":"venue"
},
  "geometry": {"coordinates":[-3.6728770733,40.4483337402],"type":"Point"}
}