{
  "type": "Feature",
  "properties": {
    "addr:full":"Calle de Txinboak Kalea, 9 Erandio Vizcaya 48950",
    "addr:housenumber":"9",
    "addr:postcode":"48950",
    "addr:street":"Calle De Txinboak Kalea",
    "iso:country":"ES",
    "sg:address":"Calle de Txinboak Kalea, 9",
    "sg:city":"Erandio",
    "sg:orig_category":"Electricidad Veh\u00cdculo",
    "sg:phone":"+34 944 67 45 06",
    "sg:postcode":"48950",
    "sg:province":"Vizcaya",
    "wof:name":"Javier Moldes Polancos",
    "wof:placetype":"venue"
},
  "geometry": {"coordinates":[-2.9715061188,43.3034515381],"type":"Point"}
}