{
  "type": "Feature",
  "properties": {
    "addr:full":"Calle de Juan Lorenzo Segura, 9 Le\u00f3n Le\u00f3n 24001",
    "addr:housenumber":"9",
    "addr:postcode":"24001",
    "addr:street":"Calle De Juan;Segura;Leo\u0301N",
    "iso:country":"ES",
    "sg:address":"Calle de Juan Lorenzo Segura, 9",
    "sg:city":"Le\u00f3n",
    "sg:orig_category":"Bazares, Art\u00cdculos De Limpieza Y De Cocina (al Por Menor)",
    "sg:phone":"+34 987 23 51 34",
    "sg:postcode":"24001",
    "sg:province":"Le\u00f3n",
    "wof:name":"Ortega Fernandez Patricia",
    "wof:placetype":"venue"
},
  "geometry": {"coordinates":[-5.5763258934,42.5973854065],"type":"Point"}
}