{
  "type": "Feature",
  "properties": {
    "addr:full":"Calle de San Agustin, 13 Casas-iba\u00e7ez Albacete 02200",
    "addr:housenumber":"13",
    "addr:postcode":"02200",
    "addr:street":"Calle De San Agustin",
    "iso:country":"ES",
    "sg:address":"Calle de San Agustin, 13",
    "sg:city":"Casas-iba\u00e7ez",
    "sg:orig_category":"Carnicer\u00cdas, Carnicer\u00cdas",
    "sg:phone":"+34 967 46 06 34",
    "sg:postcode":"02200",
    "sg:province":"Albacete",
    "wof:name":"Tolosa Jimenez Juan",
    "wof:placetype":"venue"
},
  "geometry": {"coordinates":[-1.4741410017,39.2847290039],"type":"Point"}
}