{
  "type": "Feature",
  "properties": {
    "addr:full":"Luga Campons, 5 Campons La Coru\u00f1a 15181",
    "addr:housenumber":"5",
    "addr:postcode":"15181",
    "addr:street":"Campons;La Corun\u0303A",
    "iso:country":"ES",
    "sg:address":"Luga Campons, 5",
    "sg:city":"Campons",
    "sg:orig_category":"Promotores Constructores",
    "sg:phone":"+34 981 67 49 10",
    "sg:postcode":"15181",
    "sg:province":"La Coru\u00f1a",
    "wof:name":"Galaica De Construcciones S.l.",
    "wof:placetype":"venue"
},
  "geometry": {"coordinates":[-8.3443889618,43.291721344],"type":"Point"}
}