{
  "type": "Feature",
  "properties": {
    "addr:full":"Plaz Iglesia, 1 Fuentes Ebro Zaragoza 50740",
    "addr:housenumber":"1",
    "addr:postcode":"50740",
    "addr:street":"Iglesia",
    "iso:country":"ES",
    "sg:address":"Plaz Iglesia, 1",
    "sg:city":"Fuentes Ebro",
    "sg:orig_category":"Reposter\u00cdas",
    "sg:phone":"+34 976 16 00 21",
    "sg:postcode":"50740",
    "sg:province":"Zaragoza",
    "wof:name":"Panaderia Hermanos Carot Parroche S.c.",
    "wof:placetype":"venue"
},
  "geometry": {"coordinates":[-0.6268740296,41.5112380981],"type":"Point"}
}