{
  "type": "Feature",
  "properties": {
    "iso:country":"ES",
    "sg:address":"Calle de Nicolas Sanchez, 50",
    "sg:city":"Madrid",
    "sg:orig_category":"Peluquer\u00cdas, Peluquer\u00cda Mixta",
    "sg:phone":"+34 914 75 10 27",
    "sg:postcode":"28026",
    "sg:province":"Madrid",
    "wof:name":"Vecino Rubio Javier",
    "wof:placetype":"venue"
},
  "geometry": {"coordinates":[-3.7061800957,40.3840332031],"type":"Point"}
}