{
  "type": "Feature",
  "properties": {
    "iso:country":"ES",
    "sg:address":"Rua Praza (da), 31",
    "sg:city":"Grove",
    "sg:orig_category":"Librer\u00cdas",
    "sg:phone":"+34 986 73 07 69",
    "sg:postcode":"36980",
    "sg:province":"Pontevedra",
    "wof:name":"Alvarez Mascato Rogelio",
    "wof:placetype":"venue"
},
  "geometry": {"coordinates":[-8.8650312424,42.4948158264],"type":"Point"}
}