{
  "type": "Feature",
  "properties": {
    "iso:country":"ES",
    "sg:address":"Calle de Pelicana, 5",
    "sg:city":"Rozas De Madrid",
    "sg:orig_category":"\u00d3ptica: Instrumentos (fabricaci\u00d3n)",
    "sg:phone":"+34 916 40 71 22",
    "sg:postcode":"28230",
    "sg:province":"Madrid",
    "wof:name":"Iniciativas Opticas Todo Vision",
    "wof:placetype":"venue"
},
  "geometry": {"coordinates":[-3.8725690842,40.4925079346],"type":"Point"}
}