{
  "type": "Feature",
  "properties": {
    "iso:country":"ES",
    "sg:address":"Avda Doctor Corachan, 9",
    "sg:city":"Chiva",
    "sg:orig_category":"Empleado Administrativo",
    "sg:phone":"+34 962 52 07 17",
    "sg:postcode":"46370",
    "sg:province":"Valencia",
    "wof:name":"Gestoria Fontestad S.a.",
    "wof:placetype":"venue"
},
  "geometry": {"coordinates":[-0.715027988,39.471912384],"type":"Point"}
}