{
  "type": "Feature",
  "properties": {
    "addr:full":"Candas, 1 Candas Lugo 27246",
    "addr:housenumber":"1",
    "addr:postcode":"27246",
    "addr:street":"Candas",
    "iso:country":"ES",
    "sg:address":"Candas, 1",
    "sg:city":"Candas",
    "sg:orig_category":"Agricultores, Agricultores",
    "sg:phone":"+34 982 33 00 07",
    "sg:postcode":"27246",
    "sg:province":"Lugo",
    "wof:name":"Mendez Acevedo Benito",
    "wof:placetype":"venue"
},
  "geometry": {"coordinates":[-7.3576340675,43.2669296265],"type":"Point"}
}