{
  "type": "Feature",
  "properties": {
    "iso:country":"ES",
    "sg:address":"Calle de Roberto Martin Holgado (de), 12",
    "sg:city":"Pozuelo De Alarcon",
    "sg:orig_category":"Comercio De Piezas De Recambio Y De Accesorios De Veh\u00cdculos, Veh\u00cdculos Industriales",
    "sg:phone":"+34 913 52 18 33",
    "sg:postcode":"28223",
    "sg:province":"Madrid",
    "wof:name":"Motor Diper S.l.",
    "wof:placetype":"venue"
},
  "geometry": {"coordinates":[-3.812787056,40.4340896606],"type":"Point"}
}