{
  "type": "Feature",
  "properties": {
    "addr:full":"Calle de Horno De San Torcuato, S/n Zamora Zamora 49014",
    "addr:housenumber":"s",
    "addr:postcode":"49014",
    "addr:street":"Calle De Horno De San Torcuato;/ N",
    "iso:country":"ES",
    "sg:address":"Calle de Horno De San Torcuato, S/n",
    "sg:city":"Zamora",
    "sg:orig_category":"Molduras, Junquillos, Listones Y Molduras Perforadas",
    "sg:phone":"+34 980 51 79 17",
    "sg:postcode":"49014",
    "sg:province":"Zamora",
    "wof:name":"Tupinamba C.b.",
    "wof:placetype":"venue"
},
  "geometry": {"coordinates":[-5.7428588867,41.5070419312],"type":"Point"}
}