{
  "type": "Feature",
  "properties": {
    "addr:full":"Calle de Acacia, 30 Arges Toledo 45122",
    "addr:housenumber":"30",
    "addr:postcode":"45122",
    "addr:street":"Calle De Acacia",
    "iso:country":"ES",
    "sg:address":"Calle de Acacia, 30",
    "sg:city":"Arges",
    "sg:orig_category":"Producci\u00d3n, Distribuci\u00d3n De Electricidad",
    "sg:phone":"+34 925 37 61 73",
    "sg:postcode":"45122",
    "sg:province":"Toledo",
    "sg:website":"www.niessen.es",
    "wof:name":"Asea Brown Boveri S.a.",
    "wof:placetype":"venue"
},
  "geometry": {"coordinates":[-4.0660862923,39.8111877441],"type":"Point"}
}