{
  "type": "Feature",
  "properties": {
    "addr:full":"Carrer de Francesc Tarrega, 23 Barcelona Barcelona 08027",
    "addr:housenumber":"23",
    "addr:postcode":"08027",
    "addr:street":"Carrer De Francesc Tarrega",
    "iso:country":"ES",
    "sg:address":"Carrer de Francesc Tarrega, 23",
    "sg:city":"Barcelona",
    "sg:orig_category":"Mec\u00c1nico Del Autom\u00d3vil",
    "sg:phone":"+34 933 40 56 54",
    "sg:postcode":"08027",
    "sg:province":"Barcelona",
    "wof:name":"Aguilera Mateo Benito",
    "wof:placetype":"venue"
},
  "geometry": {"coordinates":[2.1803500652,41.4231758118],"type":"Point"}
}