{
  "type": "Feature",
  "properties": {
    "iso:country":"ES",
    "sg:address":"Plaz Pilar (del), 4",
    "sg:city":"Zubia",
    "sg:orig_category":"Supermercados Y Hipermercados",
    "sg:phone":"+34 958 59 00 08",
    "sg:postcode":"18140",
    "sg:province":"Granada",
    "wof:name":"Supermercado David Quesada S.l.",
    "wof:placetype":"venue"
},
  "geometry": {"coordinates":[-3.5853440762,37.1218338013],"type":"Point"}
}