{
  "type": "Feature",
  "properties": {
    "iso:country":"ES",
    "sg:address":"Avda Ronda De Pio Xii, 15",
    "sg:city":"Sevilla",
    "sg:orig_category":"Agencias Y Agentes Comerciales, Representantes",
    "sg:phone":"+34 954 36 06 89",
    "sg:postcode":"41008",
    "sg:province":"Sevilla",
    "wof:name":"Suarez Mu\u00f1oz Armando",
    "wof:placetype":"venue"
},
  "geometry": {"coordinates":[-5.9777531624,37.4067382812],"type":"Point"}
}