{
  "type": "Feature",
  "properties": {
    "iso:country":"ES",
    "sg:address":"Calle de Camino Nuevo, 45",
    "sg:city":"Alora",
    "sg:orig_category":"Negocio De Materiales De Construcci\u00d3n",
    "sg:phone":"+34 952 49 62 43",
    "sg:postcode":"29500",
    "sg:province":"M\u00e1laga",
    "wof:name":"Martin-prieto Guerrero Jose",
    "wof:placetype":"venue"
},
  "geometry": {"coordinates":[-4.7044835091,36.825138092],"type":"Point"}
}