{
  "type": "Feature",
  "properties": {
    "addr:full":"Calle de Escribanos, 26 Madrid Madrid 28021",
    "addr:housenumber":"26",
    "addr:postcode":"madrid;28021",
    "addr:street":"Calle De Escribanos",
    "iso:country":"ES",
    "sg:address":"Calle de Escribanos, 26",
    "sg:city":"Madrid",
    "sg:orig_category":"Empresas De Carpinter\u00cda De Madera",
    "sg:phone":"+34 917 97 19 99",
    "sg:postcode":"28021",
    "sg:province":"Madrid",
    "wof:name":"Hernandez Blanco Miguel",
    "wof:placetype":"venue"
},
  "geometry": {"coordinates":[-3.7126142979,40.3429489136],"type":"Point"}
}