{
  "type": "Feature",
  "properties": {
    "iso:country":"ES",
    "sg:address":"Avda Doctor Perez Gil, 11",
    "sg:city":"Fuente-alamo",
    "sg:orig_category":"Molduras, Junquillos, Listones Y Molduras Perforadas",
    "sg:phone":"+34 967 32 11 08",
    "sg:postcode":"02651",
    "sg:province":"Albacete",
    "wof:name":"Rodriguez Bautista Gregorio",
    "wof:placetype":"venue"
},
  "geometry": {"coordinates":[-1.4341189861,38.6888885498],"type":"Point"}
}