{
  "type": "Feature",
  "properties": {
    "iso:country":"ES",
    "sg:address":"Benifayo, 9",
    "sg:city":"Beniparrell",
    "sg:orig_category":"Metalurgia",
    "sg:phone":"+34 961 21 03 18",
    "sg:postcode":"46469",
    "sg:province":"Valencia",
    "wof:name":"Vicente Balaguer Lopez S.l.",
    "wof:placetype":"venue"
},
  "geometry": {"coordinates":[-0.4060690105,39.3871498108],"type":"Point"}
}