{
  "type": "Feature",
  "properties": {
    "iso:country":"ES",
    "sg:address":"Tv. Junquera, 15",
    "sg:city":"Cedeira",
    "sg:orig_category":"Construcci\u00d3n Mec\u00c1nica",
    "sg:phone":"+34 981 48 22 90",
    "sg:postcode":"15350",
    "sg:province":"La Coru\u00f1a",
    "wof:name":"Perblago S.l.",
    "wof:placetype":"venue"
},
  "geometry": {"coordinates":[-8.052989006,43.6609916687],"type":"Point"}
}