{
  "type": "Feature",
  "properties": {
    "addr:full":"Pg Germanies (de Les), 70 Gandia Valencia 46700",
    "addr:housenumber":"70",
    "addr:postcode":"46700",
    "addr:street":"Pg Germanies De Les;Valencia",
    "iso:country":"ES",
    "sg:address":"Pg Germanies (de Les), 70",
    "sg:city":"Gandia",
    "sg:orig_category":"Telas Y Sedas (al Por Menor)",
    "sg:phone":"+34 962 86 72 18",
    "sg:postcode":"46700",
    "sg:province":"Valencia",
    "wof:name":"Perez Albi\u00f1ana Rosario",
    "wof:placetype":"venue"
},
  "geometry": {"coordinates":[-0.187579006,38.9665336609],"type":"Point"}
}