{
  "type": "Feature",
  "properties": {
    "iso:country":"ES",
    "sg:address":"Calle de San Salvador, 9",
    "sg:city":"Huelva",
    "sg:orig_category":"Prot\u00c9sicos Dentales",
    "sg:phone":"+34 959 24 57 13",
    "sg:postcode":"21003",
    "sg:province":"Huelva",
    "wof:name":"Andres Cardenas Francisco Javier De",
    "wof:placetype":"venue"
},
  "geometry": {"coordinates":[-6.9480419159,37.2563476562],"type":"Point"}
}