{
  "type": "Feature",
  "properties": {
    "addr:full":"Carrer de Marti I Julia, 37 Manresa Barcelona 08242",
    "addr:housenumber":"37",
    "addr:postcode":"08242",
    "addr:street":"Carrer De Marti I Julia",
    "iso:country":"ES",
    "sg:address":"Carrer de Marti I Julia, 37",
    "sg:city":"Manresa",
    "sg:orig_category":"Organizaciones Profesionales",
    "sg:phone":"+34 938 72 81 80",
    "sg:postcode":"08242",
    "sg:province":"Barcelona",
    "wof:name":"Llado Sobrevals Enrique",
    "wof:placetype":"venue"
},
  "geometry": {"coordinates":[1.8191850185,41.7282714844],"type":"Point"}
}