{
  "type": "Feature",
  "properties": {
    "addr:full":"Aralar, 39 Iru\u00f1a Navarra 31004",
    "addr:housenumber":"39",
    "addr:postcode":"31004",
    "addr:street":"Aralar",
    "iso:country":"ES",
    "sg:address":"Aralar, 39",
    "sg:city":"Iru\u00f1a",
    "sg:orig_category":"Molduras, Junquillos, Listones Y Molduras Perforadas",
    "sg:phone":"+34 948 23 90 11",
    "sg:postcode":"31004",
    "sg:province":"Navarra",
    "wof:name":"Gorria Soteras Jose Oscar",
    "wof:placetype":"venue"
},
  "geometry": {"coordinates":[-1.6332490444,42.8116111755],"type":"Point"}
}