{
  "type": "Feature",
  "properties": {
    "iso:country":"ES",
    "sg:address":"Carrer de Bellfort, 19",
    "sg:city":"Manlleu",
    "sg:orig_category":"Ropa Para Ni\u00d1os (al Por Menor)",
    "sg:phone":"+34 938 51 35 00",
    "sg:postcode":"08560",
    "sg:province":"Barcelona",
    "wof:name":"Bermudez Leiva Dulcenombre",
    "wof:placetype":"venue"
},
  "geometry": {"coordinates":[2.2840769291,42.0055809021],"type":"Point"}
}