{
  "type": "Feature",
  "properties": {
    "addr:full":"Erville, S/n Herville Pontevedra 36419",
    "addr:postcode":"36419",
    "addr:street":"Erville S / N",
    "iso:country":"ES",
    "sg:address":"Erville, S/n",
    "sg:city":"Herville",
    "sg:orig_category":"Asociaciones Y Clubs Deportivos",
    "sg:phone":"+34 986 33 75 40",
    "sg:postcode":"36419",
    "sg:province":"Pontevedra",
    "wof:name":"Comunidad De Propietarios Club Hipico Alazan",
    "wof:placetype":"venue"
},
  "geometry": {"coordinates":[-8.6284589767,42.1718101501],"type":"Point"}
}