{
  "type": "Feature",
  "properties": {
    "addr:full":"Calle de Moises De Leon, 51 Le\u00f3n Le\u00f3n 24006",
    "addr:housenumber":"51",
    "addr:postcode":"24006",
    "addr:street":"Calle De Moises De Leon;Leo\u0301N",
    "iso:country":"ES",
    "sg:address":"Calle de Moises De Leon, 51",
    "sg:city":"Le\u00f3n",
    "sg:classifiers":[
        {
            "category":"Banks & Credit Unions",
            "subcategory":"Bureau De Change",
            "type":"Services"
        }
    ],
    "sg:phone":"+34 987 26 09 09",
    "sg:postcode":"24006",
    "sg:province":"Le\u00f3n",
    "sg:tags":[
        "organismos",
        "control"
    ],
    "wof:name":"Asistencia Tecnica Indusrial S.a.e.",
    "wof:placetype":"venue"
},
  "geometry": {"coordinates":[-5.5607318878,42.590385437],"type":"Point"}
}