{
  "type": "Feature",
  "properties": {
    "iso:country":"ES",
    "sg:address":"Calle de Velazquez, 5",
    "sg:city":"Le\u00f3n",
    "sg:orig_category":"Complementos De Vestir (al Por Menor)",
    "sg:phone":"+34 987 25 59 08",
    "sg:postcode":"24004",
    "sg:province":"Le\u00f3n",
    "wof:name":"Rodriguez Calvo Teresa",
    "wof:placetype":"venue"
},
  "geometry": {"coordinates":[-5.5677652359,42.5903396606],"type":"Point"}
}