{
  "type": "Feature",
  "properties": {
    "addr:full":"Calle de Padre Anchieta, 10 Santa Cruz De Tenerife Santa Cruz De Tenerife 38005",
    "addr:housenumber":"10",
    "addr:postcode":"38005",
    "addr:street":"Calle De Padre Anchieta",
    "iso:country":"ES",
    "sg:address":"Calle de Padre Anchieta, 10",
    "sg:city":"Santa Cruz De Tenerife",
    "sg:orig_category":"Diet\u00c9tica: Productos Biol\u00d3gicos, Naturales Y Diet\u00c9ticos (fabricaci\u00d3n, Al Por Mayor)",
    "sg:phone":"+34 922 20 66 30",
    "sg:postcode":"38005",
    "sg:province":"Santa Cruz De Tenerife",
    "wof:name":"Discanapro S.l.",
    "wof:placetype":"venue"
},
  "geometry": {"coordinates":[-16.2540054321,28.4640216827],"type":"Point"}
}