{
  "type": "Feature",
  "properties": {
    "addr:full":"Av Baix Camp, 22 Cambrils Tarragona 43850",
    "addr:housenumber":"22",
    "addr:postcode":"43850",
    "addr:street":"Av Baix Camp",
    "iso:country":"ES",
    "sg:address":"Av Baix Camp, 22",
    "sg:city":"Cambrils",
    "sg:orig_category":"Piscinas, Accesorios, Suministros (fabricaci\u00d3n, Al Por Mayor)",
    "sg:phone":"+34 977 36 45 60",
    "sg:postcode":"43850",
    "sg:province":"Tarragona",
    "wof:name":"Piscinas Y Gunitados S.l.",
    "wof:placetype":"venue"
},
  "geometry": {"coordinates":[1.0524400473,41.071521759],"type":"Point"}
}