{
  "type": "Feature",
  "properties": {
    "addr:full":"Celeiros, S/n Chandrexa Ourense 32786",
    "addr:housenumber":"/ n",
    "addr:postcode":"32786",
    "addr:street":"Celeiros S",
    "iso:country":"ES",
    "sg:address":"Celeiros, S/n",
    "sg:city":"Chandrexa",
    "sg:orig_category":"Cajas De Ahorro",
    "sg:phone":"+34 988 33 40 24",
    "sg:postcode":"32786",
    "sg:province":"Ourense",
    "wof:name":"Bt Espa\u00d1a Compa\u00d1ia De Servicios Globales De Telecomunicaciones S.a.u.",
    "wof:placetype":"venue"
},
  "geometry": {"coordinates":[-7.3319191933,42.3153266907],"type":"Point"}
}