{
  "type": "Feature",
  "properties": {
    "iso:country":"ES",
    "sg:address":"Calle de Oriente, 19",
    "sg:city":"Valencia",
    "sg:orig_category":"Alimentaci\u00d3n General (al Por Menor)",
    "sg:phone":"+34 963 33 40 94",
    "sg:postcode":"46006",
    "sg:province":"Valencia",
    "wof:name":"Danvila Gomez Josefina",
    "wof:placetype":"venue"
},
  "geometry": {"coordinates":[-0.3622710109,39.4581718445],"type":"Point"}
}