{
  "type": "Feature",
  "properties": {
    "addr:full":"Carrer de Sant Josep, 2 Llagosta Barcelona 08120",
    "addr:housenumber":"2",
    "addr:postcode":"08120",
    "addr:street":"Carrer De Sant Josep",
    "iso:country":"ES",
    "sg:address":"Carrer de Sant Josep, 2",
    "sg:city":"Llagosta",
    "sg:orig_category":"Cajas De Ahorro",
    "sg:phone":"+34 935 60 63 89",
    "sg:postcode":"08120",
    "sg:province":"Barcelona",
    "wof:name":"Caixa D'estalvis Del Penedes",
    "wof:placetype":"venue"
},
  "geometry": {"coordinates":[2.1931340694,41.5124702454],"type":"Point"}
}