{
  "type": "Feature",
  "properties": {
    "addr:full":"Calle de Fuente Del Rey, 31 Madrid Madrid 28023",
    "addr:housenumber":"31",
    "addr:postcode":"madrid;28023",
    "addr:street":"Calle De Fuente Del Rey",
    "iso:country":"ES",
    "sg:address":"Calle de Fuente Del Rey, 31",
    "sg:city":"Madrid",
    "sg:orig_category":"Arquitectos",
    "sg:phone":"+34 917 40 04 06",
    "sg:postcode":"28023",
    "sg:province":"Madrid",
    "wof:name":"Galow Gestion Integral De Proyectos Y Obras S.l.",
    "wof:placetype":"venue"
},
  "geometry": {"coordinates":[-3.7766709328,40.4576797485],"type":"Point"}
}