{
  "type": "Feature",
  "properties": {
    "iso:country":"ES",
    "sg:address":"Afores, Km. 0009,9",
    "sg:city":"Pontils",
    "sg:orig_category":"Producci\u00d3n, Venta De Productos De Agricultura Biol\u00d3gica",
    "sg:phone":"+34 977 26 60 21",
    "sg:postcode":"43421",
    "sg:province":"Tarragona",
    "wof:name":"Lehtinen  Helka",
    "wof:placetype":"venue"
},
  "geometry": {"coordinates":[1.3882710934,41.4772415161],"type":"Point"}
}