{
  "type": "Feature",
  "properties": {
    "iso:country":"ES",
    "sg:address":"Av Matadepera, 9",
    "sg:city":"Sabadell",
    "sg:orig_category":"Institutos De Belleza",
    "sg:phone":"+34 937 16 32 92",
    "sg:postcode":"08207",
    "sg:province":"Barcelona",
    "wof:name":"Instituto Belleza Integral Tamaya S.l.",
    "wof:placetype":"venue"
},
  "geometry": {"coordinates":[2.0904901028,41.5637016296],"type":"Point"}
}