{
  "type": "Feature",
  "properties": {
    "addr:full":"Calle de Miguel Angel, 18 Madrid Madrid 28010",
    "addr:housenumber":"18",
    "addr:postcode":"madrid;28010",
    "addr:street":"Calle De Miguel Angel",
    "iso:country":"ES",
    "sg:address":"Calle de Miguel Angel, 18",
    "sg:city":"Madrid",
    "sg:orig_category":"M\u00c9dicos: Naturistas",
    "sg:phone":"+34 913 19 87 83",
    "sg:postcode":"28010",
    "sg:province":"Madrid",
    "wof:name":"Fernandez Garcia Joaquina",
    "wof:placetype":"venue"
},
  "geometry": {"coordinates":[-3.6910889149,40.4355697632],"type":"Point"}
}