{
  "type": "Feature",
  "properties": {
    "iso:country":"ES",
    "sg:address":"Avda Paz La, S/n",
    "sg:city":"Llanes",
    "sg:orig_category":"Equipos De Marcado, Etiquetado",
    "sg:phone":"+34 985 40 08 92",
    "sg:postcode":"33500",
    "sg:province":"Asturias",
    "wof:name":"R.c. Dise\u00d1o Y Rotulacion C.b.",
    "wof:placetype":"venue"
},
  "geometry": {"coordinates":[-4.7588191032,43.4216041565],"type":"Point"}
}