{
  "type": "Feature",
  "properties": {
    "addr:full":"Carr Minerva, 5 Igualada Barcelona 08700",
    "addr:housenumber":"5",
    "addr:postcode":"08700",
    "addr:street":"Carr Minerva",
    "iso:country":"ES",
    "sg:address":"Carr Minerva, 5",
    "sg:city":"Igualada",
    "sg:orig_category":"Electricidad: Instaladores",
    "sg:phone":"+34 938 04 90 26",
    "sg:postcode":"08700",
    "sg:province":"Barcelona",
    "wof:name":"Guitar Perez Isidro",
    "wof:placetype":"venue"
},
  "geometry": {"coordinates":[1.6245770454,41.5836029053],"type":"Point"}
}