{
  "type": "Feature",
  "properties": {
    "iso:country":"ES",
    "sg:address":"Ctra Taoro (del), 34",
    "sg:city":"Taoro-malpais",
    "sg:orig_category":"Inmobiliaria (agencias)",
    "sg:phone":"+34 922 38 19 87",
    "sg:postcode":"38400",
    "sg:province":"Santa Cruz De Tenerife",
    "wof:name":"Sitio Rosales S.a.",
    "wof:placetype":"venue"
},
  "geometry": {"coordinates":[-16.5485649109,28.4088039398],"type":"Point"}
}