{
  "type": "Feature",
  "properties": {
    "iso:country":"ES",
    "sg:address":"Calle de Reus, 3",
    "sg:city":"Madrid",
    "sg:orig_category":"Delegados, Agentes De Tr\u00c1nsito, Auxiliares De Transporte Internacional",
    "sg:phone":"+34 915 08 29 99",
    "sg:postcode":"28044",
    "sg:province":"Madrid",
    "wof:name":"Montraser S.l.",
    "wof:placetype":"venue"
},
  "geometry": {"coordinates":[-3.74593997,40.3718185425],"type":"Point"}
}