{
  "type": "Feature",
  "properties": {
    "iso:country":"ES",
    "sg:address":"Calle de General Ceballos, 1",
    "sg:city":"Torrelavega",
    "sg:orig_category":"Pescader\u00cdas (al Por Menor)",
    "sg:phone":"+34 942 89 15 73",
    "sg:postcode":"39300",
    "sg:province":"Cantabria",
    "wof:name":"Corrales Ruiz Felipe",
    "wof:placetype":"venue"
},
  "geometry": {"coordinates":[-4.0465788841,43.3522186279],"type":"Point"}
}