{
  "type": "Feature",
  "properties": {
    "iso:country":"ES",
    "sg:address":"Pg Dintre (de), 17",
    "sg:city":"Blanes",
    "sg:orig_category":"Estancos",
    "sg:phone":"+34 972 33 02 33",
    "sg:postcode":"17300",
    "sg:province":"Girona",
    "wof:name":"Pla Alberti Nuria",
    "wof:placetype":"venue"
},
  "geometry": {"coordinates":[2.7919549942,41.6741409302],"type":"Point"}
}