{
  "type": "Feature",
  "properties": {
    "iso:country":"ES",
    "sg:address":"Elkano Kalea, 1",
    "sg:city":"Hernani",
    "sg:orig_category":"Contenedores (mercanc\u00cdas)",
    "sg:phone":"+34 943 55 20 88",
    "sg:postcode":"20120",
    "sg:province":"Guip\u00f9zcoa",
    "wof:name":"Go\u00f1i Alzaga Maria Teresa",
    "wof:placetype":"venue"
},
  "geometry": {"coordinates":[-1.9764387608,43.2675971985],"type":"Point"}
}