{
  "type": "Feature",
  "properties": {
    "addr:full":"La Iglesia, 2 Mosqueruela Teruel 44410",
    "addr:housenumber":"2",
    "addr:postcode":"44410",
    "addr:street":"Iglesia",
    "iso:country":"ES",
    "sg:address":"La Iglesia, 2",
    "sg:city":"Mosqueruela",
    "sg:orig_category":"Cajas De Ahorro",
    "sg:phone":"+34 978 80 51 83",
    "sg:postcode":"44410",
    "sg:province":"Teruel",
    "wof:name":"Caja De Ahorros Y Monte De Piedad De Zaragoza Aragon Y Rioja",
    "wof:placetype":"venue"
},
  "geometry": {"coordinates":[-0.4494769871,40.3613777161],"type":"Point"}
}