{
  "type": "Feature",
  "properties": {
    "iso:country":"ES",
    "sg:address":"Calle de Juan Bravo, 9",
    "sg:city":"Madrid",
    "sg:orig_category":"Art\u00cdculos De Decoraci\u00d3n (fabricaci\u00d3n Y Al Por Mayor)",
    "sg:phone":"+34 915 76 12 01",
    "sg:postcode":"28006",
    "sg:province":"Madrid",
    "wof:name":"Valenti S. A.",
    "wof:placetype":"venue"
},
  "geometry": {"coordinates":[-3.6837399006,40.4330558777],"type":"Point"}
}