{
  "type": "Feature",
  "properties": {
    "addr:full":"M. Escombreras, 3 Escombreras Murcia 30350",
    "addr:housenumber":"3",
    "addr:postcode":"30350",
    "addr:street":"Escombreras",
    "iso:country":"ES",
    "sg:address":"M. Escombreras, 3",
    "sg:city":"Escombreras",
    "sg:orig_category":"Metales (labores, Pulido)",
    "sg:phone":"+34 968 16 70 07",
    "sg:postcode":"30350",
    "sg:province":"Murcia",
    "wof:name":"Nervion Montajes Y Mantenimientos S.l.",
    "wof:placetype":"venue"
},
  "geometry": {"coordinates":[-0.915988028,37.5820579529],"type":"Point"}
}