{
  "type": "Feature",
  "properties": {
    "addr:full":"Avda Antones (los), S/n Pulpi Almer\u00eda 04640",
    "addr:postcode":"04640",
    "addr:street":"Avda Antones Los S / N Pulpi Almeri\u0301A",
    "iso:country":"ES",
    "sg:address":"Avda Antones (los), S/n",
    "sg:city":"Pulpi",
    "sg:orig_category":"Ropa Para Ni\u00d1os (al Por Menor)",
    "sg:phone":"+34 950 46 54 47",
    "sg:postcode":"04640",
    "sg:province":"Almer\u00eda",
    "wof:name":"Ghirardini  Andrea",
    "wof:placetype":"venue"
},
  "geometry": {"coordinates":[-1.7490290403,37.4060440063],"type":"Point"}
}