{
  "type": "Feature",
  "properties": {
    "iso:country":"ES",
    "sg:address":"Ctra Toledo, S/n",
    "sg:city":"Navahermosa",
    "sg:orig_category":"Art\u00cdculos De Madera (fabricaci\u00d3n Y Al Por Mayor)",
    "sg:phone":"+34 925 41 06 37",
    "sg:postcode":"45150",
    "sg:province":"Toledo",
    "sg:website":"www.manchamobel.com",
    "wof:name":"Manchamobel S.a.",
    "wof:placetype":"venue"
},
  "geometry": {"coordinates":[-4.4650430679,39.6381950378],"type":"Point"}
}