{
  "type": "Feature",
  "properties": {
    "iso:country":"ES",
    "sg:address":"Avda Buhaira (la), 10",
    "sg:city":"Sevilla",
    "sg:orig_category":"Farmacias",
    "sg:phone":"+34 954 41 27 32",
    "sg:postcode":"41018",
    "sg:province":"Sevilla",
    "wof:name":"Algora Castro Maria",
    "wof:placetype":"venue"
},
  "geometry": {"coordinates":[-5.9794511795,37.3837623596],"type":"Point"}
}