{
  "type": "Feature",
  "properties": {
    "iso:country":"ES",
    "sg:address":"Avda Chopos (los), 14",
    "sg:city":"Algorta",
    "sg:orig_category":"Asilos De Ancianos. Centros Privados",
    "sg:phone":"+34 944 91 01 01",
    "sg:postcode":"48992",
    "sg:province":"Vizcaya",
    "wof:name":"Geriatrico San Esteban S.a.",
    "wof:placetype":"venue"
},
  "geometry": {"coordinates":[-3.0025150776,43.337638855],"type":"Point"}
}