{
  "type": "Feature",
  "properties": {
    "iso:country":"ES",
    "sg:address":"Ptge Bruc, 3",
    "sg:city":"Premia Mar",
    "sg:orig_category":"Ebanister\u00cda",
    "sg:phone":"+34 937 51 15 23",
    "sg:postcode":"08330",
    "sg:province":"Barcelona",
    "wof:name":"Moreno Redondo Manuel",
    "wof:placetype":"venue"
},
  "geometry": {"coordinates":[2.3485269547,41.4906654358],"type":"Point"}
}