{
  "type": "Feature",
  "properties": {
    "iso:country":"ES",
    "sg:address":"Calle de Tolu, 4",
    "sg:city":"Madrid",
    "sg:orig_category":"Talleres: Ropa A Medida",
    "sg:phone":"+34 917 64 39 84",
    "sg:postcode":"28033",
    "sg:province":"Madrid",
    "wof:name":"Gonzalez Deus Jose Luis",
    "wof:placetype":"venue"
},
  "geometry": {"coordinates":[-3.6362199783,40.4734687805],"type":"Point"}
}