{
  "type": "Feature",
  "properties": {
    "addr:full":"Rua Progreso, 35 Sanxenxo Pontevedra 36960",
    "addr:housenumber":"35",
    "addr:postcode":"36960",
    "addr:street":"Rua Progreso",
    "iso:country":"ES",
    "sg:address":"Rua Progreso, 35",
    "sg:city":"Sanxenxo",
    "sg:classifiers":[
        {
            "category":"Autos & Motor Vehicles",
            "subcategory":"Automobile Sales",
            "type":"Retail Goods"
        }
    ],
    "sg:phone":"+34 986 69 13 91",
    "sg:postcode":"36960",
    "sg:province":"Pontevedra",
    "wof:name":"Veiga Fontan Manuel",
    "wof:placetype":"venue"
},
  "geometry": {"coordinates":[-8.799908638,42.4011306763],"type":"Point"}
}