{
  "type": "Feature",
  "properties": {
    "iso:country":"ES",
    "sg:address":"Calle de General Franco, 29",
    "sg:city":"San Miguel",
    "sg:orig_category":"Fabricaci\u00d3n De Telas Y Sedas",
    "sg:phone":"+34 922 70 01 04",
    "sg:postcode":"38620",
    "sg:province":"Santa Cruz De Tenerife",
    "wof:name":"Bello Diaz Candida Teresa",
    "wof:placetype":"venue"
},
  "geometry": {"coordinates":[-16.6205711365,28.0961017609],"type":"Point"}
}