{
  "type": "Feature",
  "properties": {
    "iso:country":"ES",
    "sg:address":"Calle de Alcala, 127",
    "sg:city":"Madrid",
    "sg:orig_category":"Abogados",
    "sg:phone":"+34 915 77 77 27",
    "sg:postcode":"28009",
    "sg:province":"Madrid",
    "wof:name":"Sanjuan Juan Rafael",
    "wof:placetype":"venue"
},
  "geometry": {"coordinates":[-3.6795632839,40.4231109619],"type":"Point"}
}