{
  "type": "Feature",
  "properties": {
    "iso:country":"ES",
    "sg:address":"Rond Peius Pascual I Carbo, 27",
    "sg:city":"Girona",
    "sg:orig_category":"Formaci\u00d3n Continuada (variada)",
    "sg:phone":"+34 972 22 13 20",
    "sg:postcode":"17006",
    "sg:province":"Girona",
    "wof:name":"Garcia Gomez Manuel",
    "wof:placetype":"venue"
},
  "geometry": {"coordinates":[2.8281669617,41.9957122803],"type":"Point"}
}