{
  "type": "Feature",
  "properties": {
    "addr:full":"O Vilar De Calo, S/n Vilar De Calo La Coru\u00f1a 15895",
    "addr:housenumber":"s / n",
    "addr:postcode":"15895",
    "addr:street":"O Vilar De Calo;Calo;Corun\u0303A",
    "iso:country":"ES",
    "sg:address":"O Vilar De Calo, S/n",
    "sg:city":"Vilar De Calo",
    "sg:orig_category":"Chapa Y Pintura Veh\u00cdculos",
    "sg:phone":"+34 981 52 40 45",
    "sg:postcode":"15895",
    "sg:province":"La Coru\u00f1a",
    "wof:name":"Meimije De La Iglesia Alicia",
    "wof:placetype":"venue"
},
  "geometry": {"coordinates":[-8.5794343948,42.8416137695],"type":"Point"}
}