{
  "type": "Feature",
  "properties": {
    "iso:country":"ES",
    "sg:address":"Calle de Aramis, 5",
    "sg:city":"Madrid",
    "sg:orig_category":"Imprenta",
    "sg:phone":"+34 914 79 10 44",
    "sg:postcode":"28011",
    "sg:province":"Madrid",
    "wof:name":"Lopez Mu\u00f1oz Eduardo",
    "wof:placetype":"venue"
},
  "geometry": {"coordinates":[-3.7301192284,40.408744812],"type":"Point"}
}