{
  "type": "Feature",
  "properties": {
    "addr:full":"Pla\u00c7 Catalunya, 15 Llagostera Girona 17240",
    "addr:postcode":"17240",
    "iso:country":"ES",
    "sg:address":"Pla\u00c7 Catalunya, 15",
    "sg:city":"Llagostera",
    "sg:orig_category":"Librer\u00cdas",
    "sg:phone":"+34 972 83 00 97",
    "sg:postcode":"17240",
    "sg:province":"Girona",
    "wof:name":"Sureda Torrent Pilar",
    "wof:placetype":"venue"
},
  "geometry": {"coordinates":[2.8711810112,41.8295783997],"type":"Point"}
}