{
  "type": "Feature",
  "properties": {
    "iso:country":"ES",
    "sg:address":"Carr Margarida Xirgu, 17",
    "sg:city":"Badalona",
    "sg:orig_category":"Carnicer\u00cdas, Carnicer\u00cdas",
    "sg:phone":"+34 933 89 61 89",
    "sg:postcode":"08911",
    "sg:province":"Barcelona",
    "wof:name":"El Monte S.l.",
    "wof:placetype":"venue"
},
  "geometry": {"coordinates":[2.2493610382,41.4547653198],"type":"Point"}
}