{
  "type": "Feature",
  "properties": {
    "iso:country":"ES",
    "sg:address":"Polg. Abesadas, S/n",
    "sg:city":"Ribeira-santa Uxia",
    "sg:orig_category":"Promotores Constructores",
    "sg:phone":"+34 981 87 60 34",
    "sg:postcode":"15960",
    "sg:province":"La Coru\u00f1a",
    "wof:name":"Rin Dominguez S.l",
    "wof:placetype":"venue"
},
  "geometry": {"coordinates":[-8.9956893921,42.5540351868],"type":"Point"}
}