{
  "type": "Feature",
  "properties": {
    "addr:full":"Avda Jaen (de), 5 Castro Rio C\u00f3rdoba 14840",
    "addr:housenumber":"5",
    "addr:postcode":"14840",
    "addr:street":"Avda Jaen De;Rio Co\u0301Rdoba",
    "iso:country":"ES",
    "sg:address":"Avda Jaen (de), 5",
    "sg:city":"Castro Rio",
    "sg:orig_category":"Empresas De Carpinter\u00cda De Madera",
    "sg:phone":"+34 957 37 07 37",
    "sg:postcode":"14840",
    "sg:province":"C\u00f3rdoba",
    "wof:name":"Armeria Gurullana S.l.",
    "wof:placetype":"venue"
},
  "geometry": {"coordinates":[-4.4763250351,37.6915969849],"type":"Point"}
}