{
  "type": "Feature",
  "properties": {
    "iso:country":"ES",
    "sg:address":"Luga Carrus Poligono Industrial, 32",
    "sg:city":"Elche",
    "sg:orig_category":"Medias Y Calcetines (al Por Menor)",
    "sg:phone":"+34 966 67 52 32",
    "sg:postcode":"03291",
    "sg:province":"Alicante",
    "wof:name":"Calzados Toli S.l.",
    "wof:placetype":"venue"
},
  "geometry": {"coordinates":[-0.6765189767,38.2994346619],"type":"Point"}
}