{
  "type": "Feature",
  "properties": {
    "iso:country":"ES",
    "sg:address":"Primera Trav, 3",
    "sg:city":"Castello Plana",
    "sg:orig_category":"Piedra, Vidrio, Cer\u00c1mica Y Porcelana",
    "sg:phone":"+34 964 28 60 07",
    "sg:postcode":"12100",
    "sg:province":"Castell\u00f3n",
    "wof:name":"Alquds S.l",
    "wof:placetype":"venue"
},
  "geometry": {"coordinates":[-0.0696737021,40.0423431396],"type":"Point"}
}