{
  "type": "Feature",
  "properties": {
    "iso:country":"ES",
    "sg:address":"Carrer de Subirats, 6",
    "sg:city":"Barcelona",
    "sg:orig_category":"Mec\u00c1nico Del Autom\u00d3vil",
    "sg:phone":"+34 933 52 15 10",
    "sg:postcode":"08031",
    "sg:province":"Barcelona",
    "wof:name":"Vazquez Lopez Ricardo",
    "wof:placetype":"venue"
},
  "geometry": {"coordinates":[2.1745409966,41.4264144897],"type":"Point"}
}