{
  "type": "Feature",
  "properties": {
    "addr:full":"Calle de Duquesa Villahermosa, 38 Zaragoza Zaragoza 50010",
    "addr:housenumber":"38",
    "addr:postcode":"50010",
    "addr:street":"Calle De Duquesa Villahermosa",
    "iso:country":"ES",
    "sg:address":"Calle de Duquesa Villahermosa, 38",
    "sg:city":"Zaragoza",
    "sg:orig_category":"Zapatos (al Por Menor)",
    "sg:phone":"+34 976 34 11 71",
    "sg:postcode":"50010",
    "sg:province":"Zaragoza",
    "wof:name":"Mu\u00f1oz Lasheras Flora",
    "wof:placetype":"venue"
},
  "geometry": {"coordinates":[-0.9029334188,41.6480484009],"type":"Point"}
}