{
  "type": "Feature",
  "properties": {
    "iso:country":"ES",
    "sg:address":"Calle de Higinio Valero Sanchez, 19",
    "sg:city":"Lagartera",
    "sg:orig_category":"Molduras, Junquillos, Listones Y Molduras Perforadas",
    "sg:phone":"+34 925 45 02 13",
    "sg:postcode":"45567",
    "sg:province":"Toledo",
    "wof:name":"Iglesias Arroyo Jeronimo",
    "wof:placetype":"venue"
},
  "geometry": {"coordinates":[-5.2000408173,39.9055862427],"type":"Point"}
}