{
  "type": "Feature",
  "properties": {
    "addr:full":"Calle de Vergel (el), S/n Robles De Laciana Le\u00f3n 24139",
    "addr:housenumber":"/ n",
    "addr:postcode":"24139",
    "addr:street":"Calle De Vergel El S",
    "iso:country":"ES",
    "sg:address":"Calle de Vergel (el), S/n",
    "sg:city":"Robles De Laciana",
    "sg:orig_category":"Artes: Servicios En General",
    "sg:phone":"+34 987 48 33 95",
    "sg:postcode":"24139",
    "sg:province":"Le\u00f3n",
    "wof:name":"Canguro Arte S.l.",
    "wof:placetype":"venue"
},
  "geometry": {"coordinates":[-6.2770409584,42.9410896301],"type":"Point"}
}