{
  "type": "Feature",
  "properties": {
    "addr:full":"Avda Martires, 22 Mula Murcia 30170",
    "addr:housenumber":"22",
    "addr:postcode":"30170",
    "addr:street":"Avda Martires",
    "iso:country":"ES",
    "sg:address":"Avda Martires, 22",
    "sg:city":"Mula",
    "sg:orig_category":"Tintes (fabricaci\u00d3n, Al Por Mayor)",
    "sg:phone":"+34 968 66 44 13",
    "sg:postcode":"30170",
    "sg:province":"Murcia",
    "wof:name":"Perez Sanchez Encarnacion",
    "wof:placetype":"venue"
},
  "geometry": {"coordinates":[-1.4953659773,38.0399208069],"type":"Point"}
}