{
  "type": "Feature",
  "properties": {
    "iso:country":"ES",
    "sg:address":"Ctra Mas Del Jutge, Km. 0002,3",
    "sg:city":"P.i. Masia Del Juez",
    "sg:orig_category":"Paneles De Madera: Contrachapados, Fibras, Particulados, Estratificados (fabricaci\u00d3n, Venta)",
    "sg:phone":"+34 961 55 20 71",
    "sg:postcode":"46900",
    "sg:province":"Valencia",
    "wof:name":"Lopez Godoy Domingo",
    "wof:placetype":"venue"
},
  "geometry": {"coordinates":[-0.4623290002,39.441619873],"type":"Point"}
}