{
  "type": "Feature",
  "properties": {
    "addr:full":"Avda Gregorio Gea, 21 Mislata Valencia 46920",
    "addr:housenumber":"21",
    "addr:postcode":"46920",
    "addr:street":"Avda Gregorio Gea",
    "iso:country":"ES",
    "sg:address":"Avda Gregorio Gea, 21",
    "sg:city":"Mislata",
    "sg:orig_category":"Arquitectos",
    "sg:phone":"+34 963 50 33 83",
    "sg:postcode":"46920",
    "sg:province":"Valencia",
    "wof:name":"Torregrosa Soler Vicente",
    "wof:placetype":"venue"
},
  "geometry": {"coordinates":[-0.4157480001,39.4730567932],"type":"Point"}
}