{
  "type": "Feature",
  "properties": {
    "addr:full":"Avgd Gregorio Molina, 4 Xativa Valencia 46800",
    "addr:housenumber":"4",
    "addr:postcode":"46800",
    "addr:street":"Gregorio Molina",
    "iso:country":"ES",
    "sg:address":"Avgd Gregorio Molina, 4",
    "sg:city":"Xativa",
    "sg:orig_category":"Ropa Para Se\u00d1oras (al Por Menor)",
    "sg:phone":"+34 962 27 74 31",
    "sg:postcode":"46800",
    "sg:province":"Valencia",
    "wof:name":"Modas Aplicate Siglo Xxi S.l.",
    "wof:placetype":"venue"
},
  "geometry": {"coordinates":[-0.5234310031,38.9911270142],"type":"Point"}
}