{
  "type": "Feature",
  "properties": {
    "iso:country":"ES",
    "sg:address":"Calle de San Pablo, 38",
    "sg:city":"Baeza",
    "sg:orig_category":"\u00d3ptica: Instrumentos (fabricaci\u00d3n)",
    "sg:phone":"+34 953 74 82 04",
    "sg:postcode":"23440",
    "sg:province":"Ja\u00e9n",
    "wof:name":"Centro Optico Guadalimar S.l.",
    "wof:placetype":"venue"
},
  "geometry": {"coordinates":[-3.4654319286,37.9942207336],"type":"Point"}
}