{
  "type": "Feature",
  "properties": {
    "addr:full":"Calle de Esparteros, 1 A\u00e7over De Tajo Toledo 45250",
    "addr:housenumber":"1",
    "addr:postcode":"45250",
    "addr:street":"Calle De Esparteros",
    "iso:country":"ES",
    "sg:address":"Calle de Esparteros, 1",
    "sg:city":"A\u00e7over De Tajo",
    "sg:orig_category":"Alimentaci\u00d3n General (al Por Menor)",
    "sg:phone":"+34 925 50 63 87",
    "sg:postcode":"45250",
    "sg:province":"Toledo",
    "wof:name":"Estevez Martin Daniel",
    "wof:placetype":"venue"
},
  "geometry": {"coordinates":[-3.7624680996,39.98670578],"type":"Point"}
}