{
  "type": "Feature",
  "properties": {
    "addr:full":"Calle de Real Del Mediodia, 47 Torrecilla Pinar Segovia 40359",
    "addr:housenumber":"47",
    "addr:postcode":"40359",
    "addr:street":"Calle De Real Del Mediodia",
    "iso:country":"ES",
    "sg:address":"Calle de Real Del Mediodia, 47",
    "sg:city":"Torrecilla Pinar",
    "sg:orig_category":"Empresas De Carpinter\u00cda",
    "sg:phone":"+34 921 15 41 17",
    "sg:postcode":"40359",
    "sg:province":"Segovia",
    "wof:name":"Metalicas Arranz S.l.",
    "wof:placetype":"venue"
},
  "geometry": {"coordinates":[-4.0389070511,41.3716926575],"type":"Point"}
}