{
  "type": "Feature",
  "properties": {
    "iso:country":"ES",
    "sg:address":"Plaz Reyes Magos, 9",
    "sg:city":"Madrid",
    "sg:orig_category":"Asociaciones, Instituciones De Consumidores Y Usuarios",
    "sg:phone":"+34 915 52 48 09",
    "sg:postcode":"28007",
    "sg:province":"Madrid",
    "wof:name":"Asociacion Espa\u00f1ola Para La Defensa Del Peque\u00f1o Accionista",
    "wof:placetype":"venue"
},
  "geometry": {"coordinates":[-3.676823616,40.4084701538],"type":"Point"}
}