{
  "type": "Feature",
  "properties": {
    "addr:full":"Carr Hospital, 16 Tremp Lleida 25620",
    "addr:housenumber":"16",
    "addr:postcode":"25620",
    "addr:street":"Carr Hospital",
    "iso:country":"ES",
    "sg:address":"Carr Hospital, 16",
    "sg:city":"Tremp",
    "sg:orig_category":"Internados & Ense\u00d1anza Privada",
    "sg:phone":"+34 973 65 02 35",
    "sg:postcode":"25620",
    "sg:province":"Lleida",
    "wof:name":"Religiosas De Maria Inmaculada-misioneras Claretianas",
    "wof:placetype":"venue"
},
  "geometry": {"coordinates":[0.8948950171,42.1686935425],"type":"Point"}
}