{
  "type": "Feature",
  "properties": {
    "iso:country":"ES",
    "sg:address":"Carr Sant Joan Baptista La Salle, 31",
    "sg:city":"Girona",
    "sg:classifiers":[
        {
            "category":"Utilities",
            "subcategory":"Natural Gas",
            "type":"Services"
        }
    ],
    "sg:phone":"+34 872 08 02 01",
    "sg:postcode":"17002",
    "sg:province":"Girona",
    "sg:tags":[
        "te",
        "de",
        "salones"
    ],
    "wof:name":"Elixir Bigeon And Fare",
    "wof:placetype":"venue"
},
  "geometry": {"coordinates":[2.8193809986,41.9776611328],"type":"Point"}
}