{
  "type": "Feature",
  "properties": {
    "addr:full":"Carrer de Josep Tous Ferrer, 3 Palma Islas Baleares 07002",
    "addr:housenumber":"3",
    "addr:postcode":"07002",
    "addr:street":"Carrer De Josep Tous Ferrer",
    "iso:country":"ES",
    "sg:address":"Carrer de Josep Tous Ferrer, 3",
    "sg:city":"Palma",
    "sg:orig_category":"Telas Y Sedas (al Por Menor)",
    "sg:phone":"+34 971 72 23 92",
    "sg:postcode":"07002",
    "sg:province":"Islas Baleares",
    "wof:name":"Pomar Miro Rafael",
    "wof:placetype":"venue"
},
  "geometry": {"coordinates":[2.6524779797,39.5731544495],"type":"Point"}
}