{
  "type": "Feature",
  "properties": {
    "iso:country":"ES",
    "sg:address":"Calle de Infanta Mercedes, 61",
    "sg:city":"Madrid",
    "sg:classifiers":[
        {
            "category":"Personal",
            "subcategory":"Barber",
            "type":"Services"
        }
    ],
    "sg:phone":"+34 915 70 04 85",
    "sg:postcode":"28020",
    "sg:province":"Madrid",
    "sg:tags":[
        "caballeros",
        "de",
        "peluqueros"
    ],
    "wof:name":"Siverio & Zabalegui S.l.",
    "wof:placetype":"venue"
},
  "geometry": {"coordinates":[-3.696821928,40.4599151611],"type":"Point"}
}