{
  "type": "Feature",
  "properties": {
    "iso:country":"ES",
    "sg:address":"Calle de Merida, 15",
    "sg:city":"Santos De Maimona",
    "sg:orig_category":"Quincaller\u00cda (al Por Menor)",
    "sg:phone":"+34 924 54 43 35",
    "sg:postcode":"06230",
    "sg:province":"Badajoz",
    "wof:name":"Ferreteria Vista Hermosa S.l.",
    "wof:placetype":"venue"
},
  "geometry": {"coordinates":[-6.3758449554,38.4483833313],"type":"Point"}
}