{
  "type": "Feature",
  "properties": {
    "addr:full":"Escultor Ferreiro, 4 Noia La Coru\u00f1a 15200",
    "addr:housenumber":"4",
    "addr:postcode":"15200",
    "addr:street":"Escultor Ferreiro;La Corun\u0303A",
    "iso:country":"ES",
    "sg:address":"Escultor Ferreiro, 4",
    "sg:city":"Noia",
    "sg:orig_category":"Peluqueros: De Se\u00d1oras",
    "sg:phone":"+34 981 82 02 16",
    "sg:postcode":"15200",
    "sg:province":"La Coru\u00f1a",
    "wof:name":"Romero Martinez Josefa",
    "wof:placetype":"venue"
},
  "geometry": {"coordinates":[-8.8861103058,42.7826461792],"type":"Point"}
}