{
  "type": "Feature",
  "properties": {
    "addr:full":"Rbla Independencia, 64 Silla Valencia 46460",
    "addr:housenumber":"64",
    "addr:postcode":"46460",
    "addr:street":"Rbla Independencia",
    "iso:country":"ES",
    "sg:address":"Rbla Independencia, 64",
    "sg:city":"Silla",
    "sg:orig_category":"Poller\u00cda Y Caza (al Por Menor)",
    "sg:phone":"+34 961 20 30 00",
    "sg:postcode":"46460",
    "sg:province":"Valencia",
    "wof:name":"Selles Iba\u00f1ez Maria Del Carmen",
    "wof:placetype":"venue"
},
  "geometry": {"coordinates":[-0.4108220041,39.3592262268],"type":"Point"}
}