{
  "type": "Feature",
  "properties": {
    "iso:country":"ES",
    "sg:address":"Pg Creu, 26",
    "sg:city":"Castelldefels",
    "sg:orig_category":"Aparatos De Medida, Control, Regulaci\u00d3n Y Detecci\u00d3n",
    "sg:phone":"+34 936 64 48 52",
    "sg:postcode":"08860",
    "sg:province":"Barcelona",
    "wof:name":"Woehrle S.l.",
    "wof:placetype":"venue"
},
  "geometry": {"coordinates":[1.9524672031,41.2724456787],"type":"Point"}
}