{
  "type": "Feature",
  "properties": {
    "iso:country":"ES",
    "sg:address":"Avda Castilleja De La Cuesta, 286",
    "sg:city":"Bollullos Mitacion",
    "sg:orig_category":"Electricidad: Instaladores",
    "sg:phone":"+34 954 71 76 72",
    "sg:postcode":"41110",
    "sg:province":"Sevilla",
    "wof:name":"H.m. Insman Instalaciones Y Montajes S.l.",
    "wof:placetype":"venue"
},
  "geometry": {"coordinates":[-6.1373138428,37.3355293274],"type":"Point"}
}