{
  "type": "Feature",
  "properties": {
    "iso:country":"ES",
    "sg:address":"Polig. De Xaras, S/n",
    "sg:city":"Xaras",
    "sg:orig_category":"Comercio De Piezas De Recambio Y De Accesorios De Veh\u00cdculos, Veh\u00cdculos Industriales",
    "sg:phone":"+34 981 87 44 66",
    "sg:postcode":"15960",
    "sg:province":"La Coru\u00f1a",
    "wof:name":"Motores Y Vehiculos Santiago S.l.",
    "wof:placetype":"venue"
},
  "geometry": {"coordinates":[-8.9908485413,42.5553665161],"type":"Point"}
}