{
  "type": "Feature",
  "properties": {
    "addr:full":"Calle de Golondrina, 90 Madrid Madrid 28023",
    "addr:housenumber":"90",
    "addr:postcode":"madrid;28023",
    "addr:street":"Calle De Golondrina",
    "iso:country":"ES",
    "sg:address":"Calle de Golondrina, 90",
    "sg:city":"Madrid",
    "sg:orig_category":"Administraci\u00d3n En Agricultura",
    "sg:phone":"+34 913 57 46 48",
    "sg:postcode":"28023",
    "sg:province":"Madrid",
    "wof:name":"Agrotae S.l.",
    "wof:placetype":"venue"
},
  "geometry": {"coordinates":[-3.7851042747,40.4493904114],"type":"Point"}
}