{
  "type": "Feature",
  "properties": {
    "addr:full":"Calle de Breton De Los Herreros, 2 Calahorra La Rioja 26500",
    "addr:housenumber":"2",
    "addr:postcode":"26500",
    "addr:street":"Calle De Breton De Los Herreros",
    "iso:country":"ES",
    "sg:address":"Calle de Breton De Los Herreros, 2",
    "sg:city":"Calahorra",
    "sg:orig_category":"Administraciones De Trabajo Y Empleo",
    "sg:phone":"+34 941 13 18 54",
    "sg:postcode":"26500",
    "sg:province":"La Rioja",
    "wof:name":"Servicio Riojano De Empleo",
    "wof:placetype":"venue"
},
  "geometry": {"coordinates":[-1.9688169956,42.3046035767],"type":"Point"}
}