{
  "type": "Feature",
  "properties": {
    "addr:full":"Calle de Pintor Balaca, 36 Cartagena Murcia 30204",
    "addr:housenumber":"36",
    "addr:postcode":"30204",
    "addr:street":"Calle De Pintor Balaca",
    "iso:country":"ES",
    "sg:address":"Calle de Pintor Balaca, 36",
    "sg:city":"Cartagena",
    "sg:orig_category":"Bisuter\u00cda, Joyer\u00cda, Relojer\u00cda (al Por Menor)",
    "sg:phone":"+34 968 52 23 18",
    "sg:postcode":"30204",
    "sg:province":"Murcia",
    "wof:name":"Ortu\u00f1o Garcia Juan Francisco",
    "wof:placetype":"venue"
},
  "geometry": {"coordinates":[-0.9876090288,37.6088218689],"type":"Point"}
}