{
  "type": "Feature",
  "properties": {
    "iso:country":"ES",
    "sg:address":"Calle de Federico Sanchez Bedoya, 7",
    "sg:city":"Sevilla",
    "sg:orig_category":"Producci\u00d3n, Comercio De Cereales",
    "sg:phone":"+34 954 22 40 26",
    "sg:postcode":"41001",
    "sg:province":"Sevilla",
    "wof:name":"Cereales Matamoros S. A.",
    "wof:placetype":"venue"
},
  "geometry": {"coordinates":[-5.9948310852,37.3859863281],"type":"Point"}
}