{
  "type": "Feature",
  "properties": {
    "addr:full":"Calle de Cascajar, 21 Aranda Duero Burgos 09400",
    "addr:housenumber":"21",
    "addr:postcode":"09400",
    "addr:street":"Calle De Cascajar",
    "iso:country":"ES",
    "sg:address":"Calle de Cascajar, 21",
    "sg:city":"Aranda Duero",
    "sg:orig_category":"Arquitectos",
    "sg:phone":"+34 947 50 23 62",
    "sg:postcode":"09400",
    "sg:province":"Burgos",
    "wof:name":"Gonzalez Calvo Jose Maria",
    "wof:placetype":"venue"
},
  "geometry": {"coordinates":[-3.6881504059,41.6724624634],"type":"Point"}
}