{
  "type": "Feature",
  "properties": {
    "iso:country":"ES",
    "sg:address":"Calle de Virgen De Aranzazu, 31",
    "sg:city":"Madrid",
    "sg:orig_category":"Molduras, Junquillos, Listones Y Molduras Perforadas",
    "sg:phone":"+34 917 29 24 54",
    "sg:postcode":"28034",
    "sg:province":"Madrid",
    "wof:name":"Martin Garcia Pedro",
    "wof:placetype":"venue"
},
  "geometry": {"coordinates":[-3.6883072853,40.4867095947],"type":"Point"}
}