{
  "type": "Feature",
  "properties": {
    "iso:country":"ES",
    "sg:address":"Avda Tres Cruces, 25",
    "sg:city":"Zamora",
    "sg:orig_category":"Farmacias",
    "sg:phone":"+34 980 52 00 60",
    "sg:postcode":"49008",
    "sg:province":"Zamora",
    "wof:name":"Tejedor Siguenza Isabel",
    "wof:placetype":"venue"
},
  "geometry": {"coordinates":[-5.7411789894,41.5112342834],"type":"Point"}
}