{
  "type": "Feature",
  "properties": {
    "addr:full":"Calle de Teodoro Calvache, 2 Jaen Ja\u00e9n 23001",
    "addr:housenumber":"2;jae\u0301n",
    "addr:postcode":"23001",
    "addr:street":"Calle De Teodoro Calvache",
    "iso:country":"ES",
    "sg:address":"Calle de Teodoro Calvache, 2",
    "sg:city":"Jaen",
    "sg:orig_category":"Inmobiliaria (agencias)",
    "sg:phone":"+34 953 24 18 00",
    "sg:postcode":"23001",
    "sg:province":"Ja\u00e9n",
    "wof:name":"Grupo 2 Consulting Inmobiliario De Jaen S.l.l",
    "wof:placetype":"venue"
},
  "geometry": {"coordinates":[-3.7863121033,37.767074585],"type":"Point"}
}