{
  "type": "Feature",
  "properties": {
    "addr:full":"Rbla Jaume I, 36 Cambrils Tarragona 43850",
    "addr:housenumber":"36",
    "addr:postcode":"43850",
    "addr:street":"Rbla Jaume I",
    "iso:country":"ES",
    "sg:address":"Rbla Jaume I, 36",
    "sg:city":"Cambrils",
    "sg:orig_category":"Fabricaci\u00d3n, Importaci\u00d3n, Venta De Material De Telefon\u00cda, Peritelefon\u00cda",
    "sg:phone":"+34 977 36 96 26",
    "sg:postcode":"43850",
    "sg:province":"Tarragona",
    "wof:name":"B.t. Cel.lular Audio Catalunya S.l.",
    "wof:placetype":"venue"
},
  "geometry": {"coordinates":[1.0641599894,41.0671195984],"type":"Point"}
}