{
  "type": "Feature",
  "properties": {
    "iso:country":"ES",
    "sg:address":"Ctra Arta, 6",
    "sg:city":"Port D'alcudia",
    "sg:orig_category":"Juegos Y Juguetes (al Por Menor)",
    "sg:phone":"+34 971 54 88 58",
    "sg:postcode":"07410",
    "sg:province":"Islas Baleares",
    "wof:name":"Toys Palace S.l.",
    "wof:placetype":"venue"
},
  "geometry": {"coordinates":[3.120937109,39.8396034241],"type":"Point"}
}