{
  "type": "Feature",
  "properties": {
    "iso:country":"ES",
    "sg:address":"Calle de Antonio Machado, 2",
    "sg:city":"San Juan De Aznalfarache",
    "sg:orig_category":"Agentes Generales De Seguros",
    "sg:phone":"+34 954 76 03 75",
    "sg:postcode":"41920",
    "sg:province":"Sevilla",
    "wof:name":"Jardi Reyes S.l.",
    "wof:placetype":"venue"
},
  "geometry": {"coordinates":[-6.0252447128,37.3633270264],"type":"Point"}
}