{
  "type": "Feature",
  "properties": {
    "iso:country":"ES",
    "sg:address":"Avda Constitucion (de La), 40",
    "sg:city":"Torre Juan Abad",
    "sg:orig_category":"Bares, Piano",
    "sg:phone":"+34 926 38 30 63",
    "sg:postcode":"13344",
    "sg:province":"Ciudad Real",
    "wof:name":"Gines Santos Sandalio",
    "wof:placetype":"venue"
},
  "geometry": {"coordinates":[-3.9301741123,38.9844093323],"type":"Point"}
}