{
  "type": "Feature",
  "properties": {
    "iso:country":"ES",
    "sg:address":"Avda Castelao, 23",
    "sg:city":"Vigo",
    "sg:orig_category":"Complementos De Vestir (al Por Menor)",
    "sg:phone":"+34 986 20 09 74",
    "sg:postcode":"36209",
    "sg:province":"Pontevedra",
    "wof:name":"Carpena Guillem Modesto",
    "wof:placetype":"venue"
},
  "geometry": {"coordinates":[-8.7382564545,42.2192802429],"type":"Point"}
}