{
  "type": "Feature",
  "properties": {
    "iso:country":"ES",
    "sg:address":"Salgueiros, S/n",
    "sg:city":"Salgueiros",
    "sg:orig_category":"Frutas Y Legumbres Frescas (al Por Mayor)",
    "sg:phone":"+34 981 74 80 56",
    "sg:postcode":"15152",
    "sg:province":"La Coru\u00f1a",
    "wof:name":"Frutvila S.l.",
    "wof:placetype":"venue"
},
  "geometry": {"coordinates":[-9.150809288,43.009929657],"type":"Point"}
}