{
  "type": "Feature",
  "properties": {
    "iso:country":"ES",
    "sg:address":"Pg Maritim, 106",
    "sg:city":"Vilanova I La Geltru",
    "sg:orig_category":"Pr\u00c1ctica De Vela, Navegaci\u00d3n Y Deportes N\u00c1uticos Y Acu\u00c1ticos",
    "sg:phone":"+34 938 15 04 02",
    "sg:postcode":"08800",
    "sg:province":"Barcelona",
    "wof:name":"Escola Nautica Vilanova S.l.",
    "wof:placetype":"venue"
},
  "geometry": {"coordinates":[1.7350349426,41.2173690796],"type":"Point"}
}