{
  "type": "Feature",
  "properties": {
    "addr:full":"Calle de Baja, 35 Vinaceite Teruel 44591",
    "addr:housenumber":"35",
    "addr:postcode":"44591",
    "addr:street":"Calle De Baja",
    "iso:country":"ES",
    "sg:address":"Calle de Baja, 35",
    "sg:city":"Vinaceite",
    "sg:orig_category":"Cajas Para Embalar",
    "sg:phone":"+34 978 82 30 98",
    "sg:postcode":"44591",
    "sg:province":"Teruel",
    "wof:name":"Caja Rural De Teruel",
    "wof:placetype":"venue"
},
  "geometry": {"coordinates":[-0.5778440833,41.2659797668],"type":"Point"}
}