{
  "type": "Feature",
  "properties": {
    "iso:country":"ES",
    "sg:address":"Pase Acacias, 61",
    "sg:city":"Madrid",
    "sg:orig_category":"Muebles, Minoristas",
    "sg:phone":"+34 914 73 51 54",
    "sg:postcode":"28005",
    "sg:province":"Madrid",
    "wof:name":"Hurtado Nieto Juan",
    "wof:placetype":"venue"
},
  "geometry": {"coordinates":[-3.7127840519,40.4013404846],"type":"Point"}
}