{
  "type": "Feature",
  "properties": {
    "iso:country":"ES",
    "sg:address":"Calle de Zapateros, 12",
    "sg:city":"Casas Bajas",
    "sg:orig_category":"Frutas Y Legumbres Secas (al Por Mayor)",
    "sg:phone":"+34 978 78 22 80",
    "sg:postcode":"46146",
    "sg:province":"Valencia",
    "wof:name":"Lozano Tortajada Herminio",
    "wof:placetype":"venue"
},
  "geometry": {"coordinates":[-1.2609989643,40.0232543945],"type":"Point"}
}