{
  "type": "Feature",
  "properties": {
    "addr:full":"Carrer de Bailen, 9 Barcelona Barcelona 08010",
    "addr:housenumber":"9",
    "addr:postcode":"08010",
    "addr:street":"Carrer De Bailen",
    "iso:country":"ES",
    "sg:address":"Carrer de Bailen, 9",
    "sg:city":"Barcelona",
    "sg:orig_category":"Abogados",
    "sg:phone":"+34 932 65 45 24",
    "sg:postcode":"08010",
    "sg:province":"Barcelona",
    "wof:name":"Garcia Quinteiro Leopoldo",
    "wof:placetype":"venue"
},
  "geometry": {"coordinates":[2.1772370338,41.3917198181],"type":"Point"}
}