{
  "type": "Feature",
  "properties": {
    "addr:full":"Rond Industria, S/n Barbera Valles Barcelona 08210",
    "addr:housenumber":"/ n",
    "addr:postcode":"08210",
    "addr:street":"Rond Industria S",
    "iso:country":"ES",
    "sg:address":"Rond Industria, S/n",
    "sg:city":"Barbera Valles",
    "sg:orig_category":"Cajas De Ahorro",
    "sg:phone":"+34 937 29 06 30",
    "sg:postcode":"08210",
    "sg:province":"Barcelona",
    "wof:name":"Caixa D'estalvis I Pensions De Barcelona",
    "wof:placetype":"venue"
},
  "geometry": {"coordinates":[2.1271760464,41.5150566101],"type":"Point"}
}