{
  "type": "Feature",
  "properties": {
    "iso:country":"ES",
    "sg:address":"Calle de Ruperto Escobar, 1",
    "sg:city":"Umbrete",
    "sg:classifiers":[
        {
            "category":"Manufacturing",
            "subcategory":"Building Materials",
            "type":"Manufacturing & Wholesale Goods"
        }
    ],
    "sg:phone":"+34 955 71 55 88",
    "sg:postcode":"41806",
    "sg:province":"Sevilla",
    "sg:tags":[
        "bebidas",
        "para",
        "la",
        "de",
        "y",
        "equipo",
        "industria"
    ],
    "sg:website":"www.bodegasfsalado.com",
    "wof:name":"Salado Pichardo Francisco",
    "wof:placetype":"venue"
},
  "geometry": {"coordinates":[-6.1562981606,37.369884491],"type":"Point"}
}