{
  "type": "Feature",
  "properties": {
    "addr:full":"Calle de Orden De Calatrava, 36 Manzanares Ciudad Real 13200",
    "addr:housenumber":"36",
    "addr:postcode":"13200",
    "addr:street":"Calle De Orden De Calatrava",
    "iso:country":"ES",
    "sg:address":"Calle de Orden De Calatrava, 36",
    "sg:city":"Manzanares",
    "sg:orig_category":"Ebanister\u00cda",
    "sg:phone":"+34 926 61 08 55",
    "sg:postcode":"13200",
    "sg:province":"Ciudad Real",
    "wof:name":"Nieto-sandoval Carrion Isidro",
    "wof:placetype":"venue"
},
  "geometry": {"coordinates":[-3.3739690781,38.9979400635],"type":"Point"}
}