{
  "type": "Feature",
  "properties": {
    "addr:full":"Rond Segovia, 40 Madrid Madrid 28005",
    "addr:housenumber":"40",
    "addr:postcode":"madrid;28005",
    "addr:street":"Segovia",
    "iso:country":"ES",
    "sg:address":"Rond Segovia, 40",
    "sg:city":"Madrid",
    "sg:orig_category":"Equipo De Refrigeraci\u00d3n Industrial",
    "sg:phone":"+34 913 66 76 05",
    "sg:postcode":"28005",
    "sg:province":"Madrid",
    "sg:website":"www.itv.es",
    "wof:name":"Industria Tecnica Valenciana S.a.",
    "wof:placetype":"venue"
},
  "geometry": {"coordinates":[-3.7148189545,40.4078216553],"type":"Point"}
}