{
  "type": "Feature",
  "properties": {
    "addr:full":"Antezana De Foronda, 4 Antezana \u00c1lava 01196",
    "addr:housenumber":"4",
    "addr:postcode":"01196",
    "addr:street":"Antezana;Foronda;A\u0301Lava",
    "iso:country":"ES",
    "sg:address":"Antezana De Foronda, 4",
    "sg:city":"Antezana",
    "sg:orig_category":"Empresas De Carpinter\u00cda De Madera",
    "sg:phone":"+34 945 28 56 56",
    "sg:postcode":"01196",
    "sg:province":"\u00c1lava",
    "wof:name":"Carpinteria Ebanisteria Antezana S.l.",
    "wof:placetype":"venue"
},
  "geometry": {"coordinates":[-2.7102339268,42.9176445007],"type":"Point"}
}