{
  "type": "Feature",
  "properties": {
    "iso:country":"ES",
    "sg:address":"Avda Alberto Alcocer, 10",
    "sg:city":"Madrid",
    "sg:orig_category":"Agencias Y Asesores De Publicidad",
    "sg:phone":"+34 913 44 04 71",
    "sg:postcode":"28036",
    "sg:province":"Madrid",
    "wof:name":"Emilio Javier Publicidad S.l.",
    "wof:placetype":"venue"
},
  "geometry": {"coordinates":[-3.68689394,40.4587745667],"type":"Point"}
}