{
  "type": "Feature",
  "properties": {
    "iso:country":"ES",
    "sg:address":"Carr Cervantes, 172",
    "sg:city":"Badalona",
    "sg:orig_category":"Venta, Reparaci\u00d3n, Localizaci\u00d3n De Balanzas Y De B\u00c1sculas",
    "sg:phone":"+34 933 99 12 11",
    "sg:postcode":"08912",
    "sg:province":"Barcelona",
    "wof:name":"Comercial Aya S.l.",
    "wof:placetype":"venue"
},
  "geometry": {"coordinates":[2.2374711037,41.441860199],"type":"Point"}
}