{
  "type": "Feature",
  "properties": {
    "addr:full":"Calle de Alemania, 9 Alacant Alicante 03003",
    "addr:housenumber":"9",
    "addr:postcode":"03003",
    "addr:street":"Calle De Alemania",
    "iso:country":"ES",
    "sg:address":"Calle de Alemania, 9",
    "sg:city":"Alacant",
    "sg:orig_category":"Asesor\u00cda Fiscal Y Jur\u00cddica",
    "sg:phone":"+34 965 92 45 12",
    "sg:postcode":"03003",
    "sg:province":"Alicante",
    "wof:name":"Moreno Jimenez Victoriano",
    "wof:placetype":"venue"
},
  "geometry": {"coordinates":[-0.4887053072,38.341381073],"type":"Point"}
}