{
  "type": "Feature",
  "properties": {
    "iso:country":"ES",
    "sg:address":"Carrer de Clavell, 45",
    "sg:city":"Montcada Centre",
    "sg:orig_category":"Fabricaci\u00d3n De Moldes Y Modelos",
    "sg:phone":"+34 935 64 19 48",
    "sg:postcode":"08110",
    "sg:province":"Barcelona",
    "wof:name":"Tallers Format S.a.",
    "wof:placetype":"venue"
},
  "geometry": {"coordinates":[2.1892640591,41.4831390381],"type":"Point"}
}