{
  "type": "Feature",
  "properties": {
    "iso:country":"ES",
    "sg:address":"Avda Republica Argentina, 36",
    "sg:city":"Le\u00f3n",
    "sg:orig_category":"Art\u00cdculos De Regalo (al Por Menor)",
    "sg:phone":"+34 987 25 16 16",
    "sg:postcode":"24004",
    "sg:province":"Le\u00f3n",
    "wof:name":"Perez Castro Maria Del Pilar Gloria",
    "wof:placetype":"venue"
},
  "geometry": {"coordinates":[-5.5771660805,42.5963020325],"type":"Point"}
}