{
  "type": "Feature",
  "properties": {
    "addr:full":"Calle de Gran Via, 78 Madrid Madrid 28013",
    "addr:housenumber":"78",
    "addr:postcode":"madrid;28013",
    "addr:street":"Calle De Gran Via",
    "iso:country":"ES",
    "sg:address":"Calle de Gran Via, 78",
    "sg:city":"Madrid",
    "sg:orig_category":"Procuradores",
    "sg:phone":"+34 915 78 06 10",
    "sg:postcode":"28013",
    "sg:province":"Madrid",
    "wof:name":"Alvarez-buylla Ballesteros Manuel",
    "wof:placetype":"venue"
},
  "geometry": {"coordinates":[-3.7104620934,40.4231071472],"type":"Point"}
}