{
  "type": "Feature",
  "properties": {
    "iso:country":"ES",
    "sg:address":"Carrer de Mestral, 5",
    "sg:city":"Altafulla",
    "sg:orig_category":"Organismos De Turismo",
    "sg:phone":"+34 977 65 62 68",
    "sg:postcode":"43893",
    "sg:province":"Tarragona",
    "wof:name":"Iberica Hotel Y Turismo Consulting S.l.",
    "wof:placetype":"venue"
},
  "geometry": {"coordinates":[1.3769849539,41.1349334717],"type":"Point"}
}