{
  "type": "Feature",
  "properties": {
    "addr:full":"Calle de Mariano Santos, 4 Pradoluengo Burgos 09260",
    "addr:housenumber":"4",
    "addr:postcode":"09260",
    "addr:street":"Calle De Mariano Santos",
    "iso:country":"ES",
    "sg:address":"Calle de Mariano Santos, 4",
    "sg:city":"Pradoluengo",
    "sg:orig_category":"Medias Y Calcetines (fabricaci\u00d3n, Al Por Mayor)",
    "sg:phone":"+34 947 58 60 96",
    "sg:postcode":"09260",
    "sg:province":"Burgos",
    "wof:name":"Calcetines Urga\u00f1a S.l",
    "wof:placetype":"venue"
},
  "geometry": {"coordinates":[-3.1976540089,42.3231544495],"type":"Point"}
}