{
  "type": "Feature",
  "properties": {
    "addr:full":"Tercera Trav Comandante Villar, 3 Laredo Cantabria 39770",
    "addr:housenumber":"3",
    "addr:postcode":"39770",
    "addr:street":"Tercera Trav Comandante Villar",
    "iso:country":"ES",
    "sg:address":"Tercera Trav Comandante Villar, 3",
    "sg:city":"Laredo",
    "sg:orig_category":"Ropa Para Se\u00d1oras Y Caballeros (al Por Menor)",
    "sg:phone":"+34 942 60 55 64",
    "sg:postcode":"39770",
    "sg:province":"Cantabria",
    "wof:name":"Pellon Araujo Jose Manuel",
    "wof:placetype":"venue"
},
  "geometry": {"coordinates":[-3.4082789421,43.4121055603],"type":"Point"}
}