{
  "type": "Feature",
  "properties": {
    "addr:full":"Pase Regino Sainz De La Maza, 3 Burgos Burgos 09004",
    "addr:housenumber":"3",
    "addr:postcode":"09004",
    "addr:street":"Regino;De La Maza",
    "iso:country":"ES",
    "sg:address":"Pase Regino Sainz De La Maza, 3",
    "sg:city":"Burgos",
    "sg:orig_category":"Expertos Contables, Revisores De Cuentas",
    "sg:phone":"+34 947 27 11 99",
    "sg:postcode":"09004",
    "sg:province":"Burgos",
    "wof:name":"Val Murga Elias Del",
    "wof:placetype":"venue"
},
  "geometry": {"coordinates":[-3.693475008,42.3430671692],"type":"Point"}
}