{
  "type": "Feature",
  "properties": {
    "addr:full":"Avda Constitucion, 20 Nava Asuncion Segovia 40450",
    "addr:housenumber":"20",
    "addr:postcode":"40450",
    "addr:street":"Avda Constitucion",
    "iso:country":"ES",
    "sg:address":"Avda Constitucion, 20",
    "sg:city":"Nava Asuncion",
    "sg:orig_category":"Producci\u00d3n, Distribuci\u00d3n De Electricidad",
    "sg:phone":"+34 921 58 02 31",
    "sg:postcode":"40450",
    "sg:province":"Segovia",
    "wof:name":"Conde Padin Miguel Angel",
    "wof:placetype":"venue"
},
  "geometry": {"coordinates":[-4.4882631302,41.1547355652],"type":"Point"}
}