{
  "type": "Feature",
  "properties": {
    "iso:country":"ES",
    "sg:address":"Calle de Juan Ramon Jimenez, S/n",
    "sg:city":"Hellin",
    "sg:orig_category":"Hospitales",
    "sg:phone":"+34 967 30 95 00",
    "sg:postcode":"02400",
    "sg:province":"Albacete",
    "wof:name":"Servicio De Salud De Castilla La Mancha",
    "wof:placetype":"venue"
},
  "geometry": {"coordinates":[-1.6908890009,38.5066413879],"type":"Point"}
}