{
  "type": "Feature",
  "properties": {
    "addr:full":"Ctra Albacete, 8 Madrigueras Albacete 02230",
    "addr:housenumber":"8",
    "addr:postcode":"02230",
    "addr:street":"Ctra Albacete",
    "iso:country":"ES",
    "sg:address":"Ctra Albacete, 8",
    "sg:city":"Madrigueras",
    "sg:orig_category":"Promotores Constructores",
    "sg:phone":"+34 967 48 43 28",
    "sg:postcode":"02230",
    "sg:province":"Albacete",
    "wof:name":"Cebrian Utiel Ulpiano",
    "wof:placetype":"venue"
},
  "geometry": {"coordinates":[-1.801486969,39.2316665649],"type":"Point"}
}