{
  "type": "Feature",
  "properties": {
    "addr:full":"Carr Arqueoleg Ballester (de L'), 22 Albaida Valencia 46860",
    "addr:housenumber":"22",
    "addr:postcode":"46860",
    "addr:street":"Carr Arqueoleg;De L '",
    "iso:country":"ES",
    "sg:address":"Carr Arqueoleg Ballester (de L'), 22",
    "sg:city":"Albaida",
    "sg:orig_category":"Transportes Por Carretera: Lotes Completos, Mercanc\u00cdas Diversas",
    "sg:phone":"+34 962 90 01 90",
    "sg:postcode":"46860",
    "sg:province":"Valencia",
    "wof:name":"Blanquer Y Cortes S.l.",
    "wof:placetype":"venue"
},
  "geometry": {"coordinates":[-0.5156700015,38.8376426697],"type":"Point"}
}