{
  "type": "Feature",
  "properties": {
    "iso:country":"ES",
    "sg:address":"Carr Corregidor Escofet, 44",
    "sg:city":"Lleida",
    "sg:orig_category":"Ingeniero",
    "sg:phone":"+34 973 19 21 07",
    "sg:postcode":"25005",
    "sg:province":"Lleida",
    "wof:name":"Condal Gou Jose",
    "wof:placetype":"venue"
},
  "geometry": {"coordinates":[0.6348680258,41.6255302429],"type":"Point"}
}