{
  "type": "Feature",
  "properties": {
    "addr:full":"Ctra. Alcala, Km. 0017,0 Benalua Villas Granada 18564",
    "addr:postcode":"18564",
    "addr:street":"Ctra. Alcala Km. 0017,0 Benalua Villas Granada",
    "iso:country":"ES",
    "sg:address":"Ctra. Alcala, Km. 0017,0",
    "sg:city":"Benalua Villas",
    "sg:orig_category":"Distribuci\u00d3n De Petr\u00d3leo Y Derivados",
    "sg:phone":"+34 958 38 60 27",
    "sg:postcode":"18564",
    "sg:province":"Granada",
    "wof:name":"Antonio Romero Bolivar S.l.",
    "wof:placetype":"venue"
},
  "geometry": {"coordinates":[-3.6853423119,37.4298362732],"type":"Point"}
}