{
  "type": "Feature",
  "properties": {
    "addr:full":"Plaz San Francisco, 7 Cartagena Murcia 30201",
    "addr:housenumber":"7",
    "addr:postcode":"30201",
    "addr:street":"Plaz San Francisco",
    "iso:country":"ES",
    "sg:address":"Plaz San Francisco, 7",
    "sg:city":"Cartagena",
    "sg:orig_category":"Bancos",
    "sg:phone":"+34 968 50 88 00",
    "sg:postcode":"30201",
    "sg:province":"Murcia",
    "wof:name":"Deutsche Bank S.a.e.",
    "wof:placetype":"venue"
},
  "geometry": {"coordinates":[-0.8610739708,37.719329834],"type":"Point"}
}