{
  "type": "Feature",
  "properties": {
    "iso:country":"ES",
    "sg:address":"Pase Ermita Del Santo, 16",
    "sg:city":"Madrid",
    "sg:orig_category":"Iluminaci\u00d3n Industrial, Alumbrado P\u00dablico: Material (fabricaci\u00d3n, Importaci\u00d3n)",
    "sg:phone":"+34 914 79 60 05",
    "sg:postcode":"28011",
    "sg:province":"Madrid",
    "sg:website":"www.atpiluminacion.com",
    "wof:name":"Atp Alumbrado Tecnico Publico S.a.",
    "wof:placetype":"venue"
},
  "geometry": {"coordinates":[-3.7234396935,40.4117355347],"type":"Point"}
}