{
  "type": "Feature",
  "properties": {
    "iso:country":"ES",
    "sg:address":"Calle de Sebastian Perez, S/n",
    "sg:city":"Gergal",
    "sg:orig_category":"Institutos M\u00c9dicos",
    "sg:phone":"+34 950 35 37 00",
    "sg:postcode":"04550",
    "sg:province":"Almer\u00eda",
    "wof:name":"Servicio Andaluz De Salud",
    "wof:placetype":"venue"
},
  "geometry": {"coordinates":[-2.5393540859,37.1198997498],"type":"Point"}
}