{
  "type": "Feature",
  "properties": {
    "addr:full":"Rua Castelao, 50 Grove Pontevedra 36980",
    "addr:housenumber":"50",
    "addr:postcode":"36980",
    "addr:street":"Rua Castelao;Grove Pontevedra",
    "iso:country":"ES",
    "sg:address":"Rua Castelao, 50",
    "sg:city":"Grove",
    "sg:orig_category":"Radiocomunicaciones, Telefon\u00cda M\u00d3vil, Radiomensajer\u00cda: Servicios, Comercializaci\u00d3n",
    "sg:phone":"+34 986 73 04 53",
    "sg:postcode":"36980",
    "sg:province":"Pontevedra",
    "wof:name":"Electromecanica Fresco S.l.",
    "wof:placetype":"venue"
},
  "geometry": {"coordinates":[-8.8577260971,42.4897003174],"type":"Point"}
}