{
  "type": "Feature",
  "properties": {
    "addr:full":"Calle de Carmen (la), 54 Arrecife Las Palmas 35500",
    "addr:housenumber":"54",
    "addr:postcode":"35500",
    "addr:street":"Calle De Carmen La",
    "iso:country":"ES",
    "sg:address":"Calle de Carmen (la), 54",
    "sg:city":"Arrecife",
    "sg:orig_category":"Electromec\u00c1nica",
    "sg:phone":"+34 928 81 27 82",
    "sg:postcode":"35500",
    "sg:province":"Las Palmas",
    "wof:name":"Lemes Umpierrez Leandro",
    "wof:placetype":"venue"
},
  "geometry": {"coordinates":[-13.5605916977,28.9689426422],"type":"Point"}
}