{
  "type": "Feature",
  "properties": {
    "iso:country":"ES",
    "sg:address":"Velazquez, 1",
    "sg:city":"Benahadux",
    "sg:orig_category":"Material Y Suministros Para Perforaciones, Sondeos",
    "sg:phone":"+34 950 31 11 21",
    "sg:postcode":"04410",
    "sg:province":"Almer\u00eda",
    "wof:name":"Movimientos De Tierras Iruela S.l.",
    "wof:placetype":"venue"
},
  "geometry": {"coordinates":[-2.46352005,36.9250488281],"type":"Point"}
}