{
  "type": "Feature",
  "properties": {
    "addr:full":"Avda Mar (el), S/n Costa Teguise Las Palmas 35509",
    "addr:housenumber":"/ n",
    "addr:postcode":"35509",
    "addr:street":"Avda Mar El S",
    "iso:country":"ES",
    "sg:address":"Avda Mar (el), S/n",
    "sg:city":"Costa Teguise",
    "sg:orig_category":"Alquiler De Veh\u00cdculos: Turismos Y Utilitarios",
    "sg:phone":"+34 928 59 11 97",
    "sg:postcode":"35509",
    "sg:province":"Las Palmas",
    "wof:name":"Rocio Rent A Car S.l.",
    "wof:placetype":"venue"
},
  "geometry": {"coordinates":[-13.4981241226,28.9952640533],"type":"Point"}
}