{
  "type": "Feature",
  "properties": {
    "iso:country":"ES",
    "sg:address":"Calle de Salazar General, 2",
    "sg:city":"Bilbao",
    "sg:orig_category":"Publicidad (soportes Y Gesti\u00d3n)",
    "sg:phone":"+34 944 44 92 33",
    "sg:postcode":"48012",
    "sg:province":"Vizcaya",
    "wof:name":"Igartua Imaz Ignacio De",
    "wof:placetype":"venue"
},
  "geometry": {"coordinates":[-2.9390349388,43.2560043335],"type":"Point"}
}