{
  "type": "Feature",
  "properties": {
    "addr:full":"Carrer de Llacuna, 142 Barcelona Barcelona 08018",
    "addr:housenumber":"142",
    "addr:postcode":"08018",
    "addr:street":"Carrer De Llacuna",
    "iso:country":"ES",
    "sg:address":"Carrer de Llacuna, 142",
    "sg:city":"Barcelona",
    "sg:orig_category":"Escritores",
    "sg:phone":"+34 933 00 05 86",
    "sg:postcode":"08018",
    "sg:province":"Barcelona",
    "wof:name":"Adell Pitarch Joan Elies",
    "wof:placetype":"venue"
},
  "geometry": {"coordinates":[2.193603754,41.4051818848],"type":"Point"}
}