{
  "type": "Feature",
  "properties": {
    "iso:country":"ES",
    "sg:address":"Pase Bachilleres, 2",
    "sg:city":"Toledo",
    "sg:orig_category":"Vinos Y Licores (venta Al Por Menor)",
    "sg:phone":"+34 925 22 03 80",
    "sg:postcode":"45003",
    "sg:province":"Toledo",
    "wof:name":"Promotores Ramirez S.a.",
    "wof:placetype":"venue"
},
  "geometry": {"coordinates":[-4.0256662369,39.8692092896],"type":"Point"}
}