{
  "type": "Feature",
  "properties": {
    "addr:full":"Elduainalde, 13 Berastegi Guip\u00f9zcoa 20492",
    "addr:housenumber":"13",
    "addr:postcode":"20492",
    "addr:street":"Elduainalde;Guipu\u0300Zcoa",
    "iso:country":"ES",
    "sg:address":"Elduainalde, 13",
    "sg:city":"Berastegi",
    "sg:classifiers":[
        {
            "category":"Taxi",
            "type":"Transportation"
        }
    ],
    "sg:phone":"+34 943 68 31 20",
    "sg:postcode":"20492",
    "sg:province":"Guip\u00f9zcoa",
    "wof:name":"Achucarro Zubeldia Juan",
    "wof:placetype":"venue"
},
  "geometry": {"coordinates":[-1.9852077961,43.1308937073],"type":"Point"}
}