{
  "type": "Feature",
  "properties": {
    "addr:full":"Calle de Meson, 3 Escacena Campo Huelva 21870",
    "addr:housenumber":"3",
    "addr:postcode":"21870",
    "addr:street":"Calle De Meson",
    "iso:country":"ES",
    "sg:address":"Calle de Meson, 3",
    "sg:city":"Escacena Campo",
    "sg:orig_category":"Administraciones Regionales, Departamentales Y Locales",
    "sg:phone":"+34 959 42 30 38",
    "sg:postcode":"21870",
    "sg:province":"Huelva",
    "wof:name":"Ayuntamiento De Escacena Del Campo",
    "wof:placetype":"venue"
},
  "geometry": {"coordinates":[-6.3892273903,37.4098854065],"type":"Point"}
}