{
  "type": "Feature",
  "properties": {
    "addr:full":"Calle de Jorge Guillen, 4 Valladolid Valladolid 47003",
    "addr:housenumber":"4",
    "addr:postcode":"47003",
    "addr:street":"Calle De Jorge Guillen",
    "iso:country":"ES",
    "sg:address":"Calle de Jorge Guillen, 4",
    "sg:city":"Valladolid",
    "sg:orig_category":"Molduras, Junquillos, Listones Y Molduras Perforadas",
    "sg:phone":"+34 983 33 61 92",
    "sg:postcode":"47003",
    "sg:province":"Valladolid",
    "wof:name":"Martin Santos Rosa Maria",
    "wof:placetype":"venue"
},
  "geometry": {"coordinates":[-4.7308087349,41.6546669006],"type":"Point"}
}