{
  "type": "Feature",
  "properties": {
    "addr:full":"Calle de Alta, 35 Villa Rio C\u00f3rdoba 14640",
    "addr:housenumber":"35",
    "addr:postcode":"14640",
    "addr:street":"Calle De Alta;Rio Co\u0301Rdoba",
    "iso:country":"ES",
    "sg:address":"Calle de Alta, 35",
    "sg:city":"Villa Rio",
    "sg:orig_category":"Panader\u00cdas, Panader\u00cdas",
    "sg:phone":"+34 957 17 62 33",
    "sg:postcode":"14640",
    "sg:province":"C\u00f3rdoba",
    "wof:name":"Enriquez Silva Urbano",
    "wof:placetype":"venue"
},
  "geometry": {"coordinates":[-4.291662693,37.9811134338],"type":"Point"}
}