{
  "type": "Feature",
  "properties": {
    "iso:country":"ES",
    "sg:address":"Ctra. Arenal, 13",
    "sg:city":"Les Meravelles",
    "sg:orig_category":"Bisuter\u00cda, Joyer\u00cda, Relojer\u00cda (al Por Menor)",
    "sg:phone":"+34 971 26 32 59",
    "sg:postcode":"07610",
    "sg:province":"Islas Baleares",
    "wof:name":"Corrales Pacheco Rafael",
    "wof:placetype":"venue"
},
  "geometry": {"coordinates":[2.7243249416,39.5336914062],"type":"Point"}
}