{
  "type": "Feature",
  "properties": {
    "addr:full":"Pase Zumaquera, 84 Vitoria-gasteiz \u00c1lava 01006",
    "addr:housenumber":"84",
    "addr:postcode":"01006",
    "addr:street":"Zumaquera",
    "iso:country":"ES",
    "sg:address":"Pase Zumaquera, 84",
    "sg:city":"Vitoria-gasteiz",
    "sg:orig_category":"Escayola Y Productos De Escayola (fabricaci\u00d3n, Al Por Mayor)",
    "sg:phone":"+34 945 13 66 79",
    "sg:postcode":"01006",
    "sg:province":"\u00c1lava",
    "wof:name":"Jose Luis Reyes Forero S.l.",
    "wof:placetype":"venue"
},
  "geometry": {"coordinates":[-2.6621439457,42.8353118896],"type":"Point"}
}