{
  "type": "Feature",
  "properties": {
    "addr:full":"Crta. La Jana, S/n Canet Roig Castell\u00f3n 12350",
    "addr:housenumber":"s / n",
    "addr:postcode":"12350",
    "addr:street":"Crta. La Jana",
    "iso:country":"ES",
    "sg:address":"Crta. La Jana, S/n",
    "sg:city":"Canet Roig",
    "sg:orig_category":"Negocio De Madera",
    "sg:phone":"+34 964 49 40 61",
    "sg:postcode":"12350",
    "sg:province":"Castell\u00f3n",
    "wof:name":"Salvador Jaime Vicente",
    "wof:placetype":"venue"
},
  "geometry": {"coordinates":[0.2444549948,40.5492744446],"type":"Point"}
}