{
  "type": "Feature",
  "properties": {
    "addr:full":"Calle de Galdo, 18 Carmen Murcia 30002",
    "addr:housenumber":"18",
    "addr:postcode":"30002",
    "addr:street":"Calle De Galdo",
    "iso:country":"ES",
    "sg:address":"Calle de Galdo, 18",
    "sg:city":"Carmen",
    "sg:classifiers":[
        {
            "category":"Personal",
            "subcategory":"Barber",
            "type":"Services"
        }
    ],
    "sg:phone":"+34 968 25 90 51",
    "sg:postcode":"30002",
    "sg:province":"Murcia",
    "sg:tags":[
        "caballeros",
        "de",
        "peluqueros"
    ],
    "wof:name":"Lahmidi Hamzi El Mostafa",
    "wof:placetype":"venue"
},
  "geometry": {"coordinates":[-1.1302499771,37.9829597473],"type":"Point"}
}