{
  "type": "Feature",
  "properties": {
    "iso:country":"ES",
    "sg:address":"Carr Capitan Cortes, 20",
    "sg:city":"Oliva",
    "sg:orig_category":"Asesor\u00cda Fiscal Y Jur\u00cddica",
    "sg:phone":"+34 962 96 35 19",
    "sg:postcode":"46780",
    "sg:province":"Valencia",
    "wof:name":"Castello Navarro Vicente",
    "wof:placetype":"venue"
},
  "geometry": {"coordinates":[-0.1193189994,38.9222946167],"type":"Point"}
}