{
  "type": "Feature",
  "properties": {
    "iso:country":"ES",
    "sg:address":"Plaz Generalisimo, 1",
    "sg:city":"Villaviciosa",
    "sg:orig_category":"Caf\u00c9s, Bares, Cervecer\u00cdas",
    "sg:phone":"+34 985 89 17 39",
    "sg:postcode":"33300",
    "sg:province":"Asturias",
    "wof:name":"Solares Alonso Rafael",
    "wof:placetype":"venue"
},
  "geometry": {"coordinates":[-5.4310541153,43.4800834656],"type":"Point"}
}