{
  "type": "Feature",
  "properties": {
    "addr:full":"Ctra. Logro\u00f1o-vitoria, Km. 0047,0 S. Vicente Sonsierra La Rioja 26338",
    "addr:postcode":"26338",
    "addr:street":"Ctra. Logron\u0303O-Vitoria Km. 0047,0 S. Vicente Sonsierra;Rioja",
    "iso:country":"ES",
    "sg:address":"Ctra. Logro\u00f1o-vitoria, Km. 0047,0",
    "sg:city":"S. Vicente Sonsierra",
    "sg:orig_category":"Distribuci\u00d3n De Petr\u00d3leo Y Derivados",
    "sg:phone":"+34 941 33 43 06",
    "sg:postcode":"26338",
    "sg:province":"La Rioja",
    "wof:name":"Viuda E Hijos De Luis Fernandez S.l.",
    "wof:placetype":"venue"
},
  "geometry": {"coordinates":[-2.7544562817,42.5712928772],"type":"Point"}
}