{
  "type": "Feature",
  "properties": {
    "addr:full":"Calle de Marques De Altamira, 7 Madrid Madrid 28033",
    "addr:housenumber":"7",
    "addr:postcode":"madrid;28033",
    "addr:street":"Calle De Marques De Altamira",
    "iso:country":"ES",
    "sg:address":"Calle de Marques De Altamira, 7",
    "sg:city":"Madrid",
    "sg:classifiers":[
        {
            "category":"Professional",
            "subcategory":"Management & Consulting",
            "type":"Services"
        }
    ],
    "sg:phone":"+34 917 66 48 95",
    "sg:postcode":"28033",
    "sg:province":"Madrid",
    "sg:tags":[
        "asesor\u00cda",
        "en",
        "marketing"
    ],
    "wof:name":"Premier Marketing Development S.l.",
    "wof:placetype":"venue"
},
  "geometry": {"coordinates":[-3.6664071083,40.4747467041],"type":"Point"}
}