{
  "type": "Feature",
  "properties": {
    "addr:full":"Calle de Blasco Iba\u00d1ez, 25 Almeria Almer\u00eda 04006",
    "addr:housenumber":"25",
    "addr:postcode":"04006",
    "addr:street":"Calle De Blasco Iban\u0303Ez",
    "iso:country":"ES",
    "sg:address":"Calle de Blasco Iba\u00d1ez, 25",
    "sg:city":"Almeria",
    "sg:orig_category":"Contenedores (mercanc\u00cdas)",
    "sg:phone":"+34 950 22 07 00",
    "sg:postcode":"04006",
    "sg:province":"Almer\u00eda",
    "wof:name":"Gonzalez Salvador Juan",
    "wof:placetype":"venue"
},
  "geometry": {"coordinates":[-2.4487142563,36.8423233032],"type":"Point"}
}