{
  "type": "Feature",
  "properties": {
    "iso:country":"ES",
    "sg:address":"C/ Alvarez De Castro, 41",
    "sg:city":"Banyoles",
    "sg:orig_category":"Florister\u00cdas",
    "sg:phone":"+34 972 57 12 07",
    "sg:postcode":"17820",
    "sg:province":"Girona",
    "wof:name":"Marti Sallo Fidel",
    "wof:placetype":"venue"
},
  "geometry": {"coordinates":[2.7650160789,42.1167678833],"type":"Point"}
}