{
  "type": "Feature",
  "properties": {
    "addr:full":"Calle de Infantas, 4 Madrid Madrid 28004",
    "addr:housenumber":"4",
    "addr:postcode":"28004",
    "addr:street":"Calle De Infantas",
    "iso:country":"ES",
    "sg:address":"Calle de Infantas, 4",
    "sg:city":"Madrid",
    "sg:orig_category":"Centros Empresariales",
    "sg:phone":"+34 915 21 51 12",
    "sg:postcode":"28004",
    "sg:province":"Madrid",
    "wof:name":"Derechos Civiles",
    "wof:placetype":"venue"
},
  "geometry": {"coordinates":[-3.7008390427,40.4209213257],"type":"Point"}
}