{
  "type": "Feature",
  "properties": {
    "addr:full":"Calle de Juan Ramon Jimenez, S/n Algeciras C\u00e1diz 11207",
    "addr:postcode":"11207",
    "addr:street":"Calle De Juan Ramon Jimenez S / N;Ca\u0301Diz",
    "iso:country":"ES",
    "sg:address":"Calle de Juan Ramon Jimenez, S/n",
    "sg:city":"Algeciras",
    "sg:orig_category":"Confiter\u00cdas, Chocolater\u00cdas (al Por Menor)",
    "sg:phone":"+34 956 57 03 95",
    "sg:postcode":"11207",
    "sg:province":"C\u00e1diz",
    "wof:name":"Lopez Gavira Manuel",
    "wof:placetype":"venue"
},
  "geometry": {"coordinates":[-5.4491319656,36.1151885986],"type":"Point"}
}