{
  "type": "Feature",
  "properties": {
    "iso:country":"ES",
    "sg:address":"Avda Esteiro, 30",
    "sg:city":"Ferrol",
    "sg:orig_category":"Radiocomunicaciones, Telefon\u00cda M\u00d3vil, Radiomensajer\u00cda: Servicios, Comercializaci\u00d3n",
    "sg:phone":"+34 981 36 90 58",
    "sg:postcode":"15403",
    "sg:province":"A Coru\u00f1a",
    "wof:name":"Telemovil Ferrol S.l.",
    "wof:placetype":"venue"
},
  "geometry": {"coordinates":[-8.2249717712,43.483417511],"type":"Point"}
}