{
  "type": "Feature",
  "properties": {
    "addr:full":"Calle de Julio Burell, 76 Linares Ja\u00e9n 23700",
    "addr:housenumber":"76",
    "addr:postcode":"23700",
    "addr:street":"Calle De Julio Burell;Jae\u0301N",
    "iso:country":"ES",
    "sg:address":"Calle de Julio Burell, 76",
    "sg:city":"Linares",
    "sg:orig_category":"Peluqueros: De Se\u00d1oras",
    "sg:phone":"+34 953 60 19 80",
    "sg:postcode":"23700",
    "sg:province":"Ja\u00e9n",
    "wof:name":"Garcia Garcia Maria Aurora",
    "wof:placetype":"venue"
},
  "geometry": {"coordinates":[-3.6272859573,38.0926399231],"type":"Point"}
}