{
  "type": "Feature",
  "properties": {
    "addr:full":"Avda Miguel De Unamuno, 19 Alcala Henares Madrid 28806",
    "addr:housenumber":"19",
    "addr:postcode":"28806",
    "addr:street":"Avda Miguel De Unamuno",
    "iso:country":"ES",
    "sg:address":"Avda Miguel De Unamuno, 19",
    "sg:city":"Alcala Henares",
    "sg:orig_category":"Bisuter\u00cda, Joyer\u00cda, Relojer\u00cda (al Por Menor)",
    "sg:phone":"+34 918 78 40 90",
    "sg:postcode":"28806",
    "sg:province":"Madrid",
    "wof:name":"Italian Bijoux S.l.",
    "wof:placetype":"venue"
},
  "geometry": {"coordinates":[-3.368005991,40.495174408],"type":"Point"}
}