{
  "type": "Feature",
  "properties": {
    "iso:country":"ES",
    "sg:address":"Carrer de Artesans, S/n",
    "sg:city":"Valls",
    "sg:orig_category":"Contenedores (mercanc\u00cdas)",
    "sg:phone":"+34 977 61 36 51",
    "sg:postcode":"43800",
    "sg:province":"Tarragona",
    "wof:name":"Felagram S.l.",
    "wof:placetype":"venue"
},
  "geometry": {"coordinates":[1.2628949881,41.3012657166],"type":"Point"}
}