{
  "type": "Feature",
  "properties": {
    "iso:country":"ES",
    "sg:address":"Avgd Naquera, 2",
    "sg:city":"Massamagrell",
    "sg:orig_category":"Servicios Gsm",
    "sg:phone":"+34 961 45 23 98",
    "sg:postcode":"46130",
    "sg:province":"Valencia",
    "wof:name":"Telecomunicaciones Massamagrell, S.l.",
    "wof:placetype":"venue"
},
  "geometry": {"coordinates":[-0.3329139948,39.5671310425],"type":"Point"}
}