{
  "type": "Feature",
  "properties": {
    "iso:country":"ES",
    "sg:address":"Pase Platanos (cartuja Baja), S/n",
    "sg:city":"Cartuja Baja",
    "sg:orig_category":"Asociaciones, Organismos Culturales Y Socioeducativos",
    "sg:phone":"+34 976 50 03 02",
    "sg:postcode":"50720",
    "sg:province":"Zaragoza",
    "wof:name":"Ayuntamiento-club Municipal Jubilados",
    "wof:placetype":"venue"
},
  "geometry": {"coordinates":[-0.8234379888,41.6062088013],"type":"Point"}
}