{
  "type": "Feature",
  "properties": {
    "addr:full":"Calle de Jose Maria Haro (magistrat), 13 Valencia Valencia 46022",
    "addr:housenumber":"13",
    "addr:postcode":"46022",
    "addr:street":"Calle De Jose Maria Haro Magistrat",
    "iso:country":"ES",
    "sg:address":"Calle de Jose Maria Haro (magistrat), 13",
    "sg:city":"Valencia",
    "sg:orig_category":"Panader\u00cdas, Panader\u00cdas",
    "sg:phone":"+34 963 72 45 60",
    "sg:postcode":"46022",
    "sg:province":"Valencia",
    "wof:name":"Piquer Pomer Juan Bautista",
    "wof:placetype":"venue"
},
  "geometry": {"coordinates":[-0.3387520015,39.4687232971],"type":"Point"}
}