{
  "type": "Feature",
  "properties": {
    "addr:full":"Carrer de Cierva, S/n Zona Industrial Barcelona 08397",
    "addr:housenumber":"s / n",
    "addr:postcode":"08397",
    "addr:street":"Carrer De Cierva",
    "iso:country":"ES",
    "sg:address":"Carrer de Cierva, S/n",
    "sg:city":"Zona Industrial",
    "sg:orig_category":"Telas (al Por Mayor)",
    "sg:phone":"+34 937 67 22 17",
    "sg:postcode":"08397",
    "sg:province":"Barcelona",
    "wof:name":"Gloor S.l.",
    "wof:placetype":"venue"
},
  "geometry": {"coordinates":[2.6827499866,41.6266441345],"type":"Point"}
}