{
  "type": "Feature",
  "properties": {
    "iso:country":"ES",
    "sg:address":"Carrer de Salvador Espriu, 32",
    "sg:city":"Sabadell",
    "sg:orig_category":"Contables",
    "sg:phone":"+34 937 17 68 46",
    "sg:postcode":"08207",
    "sg:province":"Barcelona",
    "wof:name":"Vilas Martinez Cristina",
    "wof:placetype":"venue"
},
  "geometry": {"coordinates":[2.0834610462,41.5744819641],"type":"Point"}
}