{
  "type": "Feature",
  "properties": {
    "iso:country":"ES",
    "sg:address":"Avda Ejercito, 15",
    "sg:city":"Guadalajara",
    "sg:orig_category":"C\u00c1maras De Comercio E Industria, Oficios, Agricultura",
    "sg:phone":"+34 949 22 29 58",
    "sg:postcode":"19003",
    "sg:province":"Guadalajara",
    "wof:name":"Camara Agraria Provincial",
    "wof:placetype":"venue"
},
  "geometry": {"coordinates":[-3.1801519394,40.6287956238],"type":"Point"}
}