{
  "type": "Feature",
  "properties": {
    "addr:full":"Avda Bruselas (de), 6 Alcobendas Madrid 28108",
    "addr:postcode":"28108",
    "addr:street":"Avda Bruselas De 6",
    "iso:country":"ES",
    "sg:address":"Avda Bruselas (de), 6",
    "sg:city":"Alcobendas",
    "sg:orig_category":"Ingenier\u00cda, Centros De Estudios (diversos)",
    "sg:phone":"+34 916 61 45 15",
    "sg:postcode":"28108",
    "sg:province":"Madrid",
    "wof:name":"Ifara Tecnologias S.l.",
    "wof:placetype":"venue"
},
  "geometry": {"coordinates":[-3.6323750019,40.5311164856],"type":"Point"}
}