{
  "type": "Feature",
  "properties": {
    "addr:full":"Calle de Portugal (de), 5 Mejorada Campo Madrid 28840",
    "addr:housenumber":"5",
    "addr:postcode":"28840",
    "addr:street":"Calle De Portugal De",
    "iso:country":"ES",
    "sg:address":"Calle de Portugal (de), 5",
    "sg:city":"Mejorada Campo",
    "sg:orig_category":"Paletas",
    "sg:phone":"+34 916 68 29 20",
    "sg:postcode":"28840",
    "sg:province":"Madrid",
    "wof:name":"Alejano Via Soraya",
    "wof:placetype":"venue"
},
  "geometry": {"coordinates":[-3.4885659218,40.3870811462],"type":"Point"}
}