{
  "type": "Feature",
  "properties": {
    "addr:full":"Carrer de Espanya, 13 Mollet Valles Barcelona 08100",
    "addr:housenumber":"13",
    "addr:postcode":"08100",
    "addr:street":"Carrer De Espanya",
    "iso:country":"ES",
    "sg:address":"Carrer de Espanya, 13",
    "sg:city":"Mollet Valles",
    "sg:orig_category":"Comercio, Reparaci\u00d3n De Motocicletas, Bicicletas Y Piezas Sueltas",
    "sg:phone":"+34 935 93 00 82",
    "sg:postcode":"08100",
    "sg:province":"Barcelona",
    "wof:name":"Industria Ciclista Sola S.a.",
    "wof:placetype":"venue"
},
  "geometry": {"coordinates":[2.2135820389,41.5394859314],"type":"Point"}
}