{
  "type": "Feature",
  "properties": {
    "addr:full":"Casa Camp, 56 Vilassar Barcelona 08340",
    "addr:postcode":"08340",
    "addr:street":"Barcelona",
    "iso:country":"ES",
    "sg:address":"Casa Camp, 56",
    "sg:city":"Vilassar",
    "sg:orig_category":"Agricultores, Agricultores",
    "sg:phone":"+34 937 50 19 03",
    "sg:postcode":"08340",
    "sg:province":"Barcelona",
    "sg:website":"www.rosassabatesroca.com",
    "wof:name":"Sabates-roca S.l.",
    "wof:placetype":"venue"
},
  "geometry": {"coordinates":[2.3907299042,41.5019264221],"type":"Point"}
}