{
  "type": "Feature",
  "properties": {
    "addr:full":"Calle de Andres Torrejon, 18 Madrid Madrid 28014",
    "addr:housenumber":"18",
    "addr:postcode":"madrid;28014",
    "addr:street":"Calle De Andres Torrejon",
    "iso:country":"ES",
    "sg:address":"Calle de Andres Torrejon, 18",
    "sg:city":"Madrid",
    "sg:orig_category":"Confecci\u00d3n (fabricaci\u00d3n, Al Por Mayor)",
    "sg:phone":"+34 914 34 04 55",
    "sg:postcode":"28014",
    "sg:province":"Madrid",
    "wof:name":"Piris Pinilla S.l.",
    "wof:placetype":"venue"
},
  "geometry": {"coordinates":[-3.6822547913,40.4077339172],"type":"Point"}
}