{
  "type": "Feature",
  "properties": {
    "iso:country":"ES",
    "sg:address":"Carrer de Joiers, 11",
    "sg:city":"Poligon Industrial Riera De Caldes",
    "sg:orig_category":"Fabricaci\u00d3n De Capiteles",
    "sg:phone":"+34 938 66 77 92",
    "sg:postcode":"08184",
    "sg:province":"Barcelona",
    "wof:name":"Alquicarp S.l.",
    "wof:placetype":"venue"
},
  "geometry": {"coordinates":[2.1659221649,41.6297569275],"type":"Point"}
}