{
  "type": "Feature",
  "properties": {
    "addr:full":"Plaz Maestro Quislant, S/n Santa Pola Alicante 03130",
    "addr:housenumber":"/ n",
    "addr:postcode":"03130",
    "addr:street":"Plaz;Quislant S",
    "iso:country":"ES",
    "sg:address":"Plaz Maestro Quislant, S/n",
    "sg:city":"Santa Pola",
    "sg:orig_category":"Pescader\u00cdas (al Por Menor)",
    "sg:phone":"+34 965 41 67 34",
    "sg:postcode":"03130",
    "sg:province":"Alicante",
    "wof:name":"Molina Sempere Josefa",
    "wof:placetype":"venue"
},
  "geometry": {"coordinates":[-0.5551989079,38.1935272217],"type":"Point"}
}