{
  "type": "Feature",
  "properties": {
    "addr:full":"Plaz Oriente, 8 Madrid Madrid 28013",
    "addr:housenumber":"8",
    "addr:postcode":"madrid;28013",
    "addr:street":"Plaz Oriente",
    "iso:country":"ES",
    "sg:address":"Plaz Oriente, 8",
    "sg:city":"Madrid",
    "sg:orig_category":"Agencias De Viajes",
    "sg:phone":"+34 915 41 18 07",
    "sg:postcode":"28013",
    "sg:province":"Madrid",
    "sg:website":"www.pullmantur.es",
    "wof:name":"Pullmantur S. A.",
    "wof:placetype":"venue"
},
  "geometry": {"coordinates":[-3.7113790512,40.4188270569],"type":"Point"}
}