{
  "type": "Feature",
  "properties": {
    "addr:full":"Plaz Longoria Carbajal, 3 Oviedo Asturias 33002",
    "addr:housenumber":"3",
    "addr:postcode":"33002",
    "addr:street":"Plaz;Carbajal",
    "iso:country":"ES",
    "sg:address":"Plaz Longoria Carbajal, 3",
    "sg:city":"Oviedo",
    "sg:orig_category":"Reparaci\u00d3n Y Restauraci\u00d3n De Objetos Diversos",
    "sg:phone":"+34 985 21 13 36",
    "sg:postcode":"33002",
    "sg:province":"Asturias",
    "wof:name":"Blanco Del Bustio Bego\u00f1a",
    "wof:placetype":"venue"
},
  "geometry": {"coordinates":[-5.8484492302,43.364238739],"type":"Point"}
}