{
  "type": "Feature",
  "properties": {
    "addr:full":"Calle de Aljibe, 21 Pulianas Granada 18197",
    "addr:housenumber":"21",
    "addr:postcode":"18197",
    "addr:street":"Calle De Aljibe",
    "iso:country":"ES",
    "sg:address":"Calle de Aljibe, 21",
    "sg:city":"Pulianas",
    "sg:orig_category":"Institutos De Belleza",
    "sg:phone":"+34 958 42 40 28",
    "sg:postcode":"18197",
    "sg:province":"Granada",
    "wof:name":"Mu\u00f1oz Huertas Elisa",
    "wof:placetype":"venue"
},
  "geometry": {"coordinates":[-3.6065759659,37.222820282],"type":"Point"}
}