{
  "type": "Feature",
  "properties": {
    "addr:full":"Rbla Passeig, 36 Vic Barcelona 08500",
    "addr:housenumber":"36",
    "addr:postcode":"08500",
    "addr:street":"Passeig",
    "iso:country":"ES",
    "sg:address":"Rbla Passeig, 36",
    "sg:city":"Vic",
    "sg:orig_category":"Granos Y Semillas (producci\u00d3n, Al Por Mayor)",
    "sg:phone":"+34 938 86 05 72",
    "sg:postcode":"08500",
    "sg:province":"Barcelona",
    "wof:name":"Llavors I Cereals Caralt S.l.",
    "wof:placetype":"venue"
},
  "geometry": {"coordinates":[2.256841898,41.929813385],"type":"Point"}
}