{
  "type": "Feature",
  "properties": {
    "iso:country":"ES",
    "sg:address":"Calle de General Mola, 29",
    "sg:city":"Alacon",
    "sg:orig_category":"Empresas De Pintura Y Revestimientos",
    "sg:phone":"+34 978 81 85 29",
    "sg:postcode":"44549",
    "sg:province":"Teruel",
    "wof:name":"Alquezar Alquezar Vicente",
    "wof:placetype":"venue"
},
  "geometry": {"coordinates":[-0.6981058121,41.0220298767],"type":"Point"}
}