{
  "type": "Feature",
  "properties": {
    "iso:country":"ES",
    "sg:address":"Pl Arquebisbe Modrego, 2",
    "sg:city":"Viladecans",
    "sg:orig_category":"Promotores Constructores",
    "sg:phone":"+34 936 37 07 17",
    "sg:postcode":"08840",
    "sg:province":"Barcelona",
    "wof:name":"Construcciones Espingol S.l.",
    "wof:placetype":"venue"
},
  "geometry": {"coordinates":[2.021805048,41.3167800903],"type":"Point"}
}