{
  "type": "Feature",
  "properties": {
    "iso:country":"ES",
    "sg:address":"Ctra Jarandilla, 58",
    "sg:city":"Navalmoral Mata",
    "sg:orig_category":"Carpinteros",
    "sg:phone":"+34 927 53 49 33",
    "sg:postcode":"10300",
    "sg:province":"C\u00e1ceres",
    "wof:name":"Alian Comercial Ara\u00f1uelo S.l.",
    "wof:placetype":"venue"
},
  "geometry": {"coordinates":[-5.5743112564,39.9308395386],"type":"Point"}
}