{
  "type": "Feature",
  "properties": {
    "addr:full":"Ferreiros, 3 Santa Cruz Lugo 27305",
    "addr:housenumber":"3",
    "addr:postcode":"27305",
    "addr:street":"Ferreiros",
    "iso:country":"ES",
    "sg:address":"Ferreiros, 3",
    "sg:city":"Santa Cruz",
    "sg:orig_category":"Bosques (trabajos, Asesor\u00cda, Gesti\u00d3n)",
    "sg:phone":"+34 982 16 36 96",
    "sg:postcode":"27305",
    "sg:province":"Lugo",
    "wof:name":"Freire Rodriguez Jose Celso",
    "wof:placetype":"venue"
},
  "geometry": {"coordinates":[-7.8772788048,43.2302932739],"type":"Point"}
}