{
  "type": "Feature",
  "properties": {
    "iso:country":"ES",
    "sg:address":"Calle de Laderas Barrio Del Carmen, 13",
    "sg:city":"Teruel",
    "sg:orig_category":"Cr\u00cda De Animales",
    "sg:phone":"+34 978 60 63 14",
    "sg:postcode":"44001",
    "sg:province":"Teruel",
    "wof:name":"Sebastian Izquierdo Luis",
    "wof:placetype":"venue"
},
  "geometry": {"coordinates":[-1.114503026,40.3477401733],"type":"Point"}
}