{
  "type": "Feature",
  "properties": {
    "addr:full":"Calle de Orense, 2 Madrid Madrid 28020",
    "addr:housenumber":"2",
    "addr:postcode":"28020",
    "addr:street":"Calle De Orense",
    "iso:country":"ES",
    "sg:address":"Calle de Orense, 2",
    "sg:city":"Madrid",
    "sg:orig_category":"Caf\u00c9s, Bares, Cervecer\u00cdas",
    "sg:phone":"+34 915 56 28 43",
    "sg:postcode":"28020",
    "sg:province":"Madrid",
    "sg:website":"www.rodilla.com",
    "wof:name":"Rodilla Sanchez S. L.",
    "wof:placetype":"venue"
},
  "geometry": {"coordinates":[-3.695374012,40.4468383789],"type":"Point"}
}