{
  "type": "Feature",
  "properties": {
    "iso:country":"ES",
    "sg:address":"Caminos Varios, 25",
    "sg:city":"Alhama Aragon",
    "sg:orig_category":"Maquinaria Para Industrias Diversas",
    "sg:phone":"+34 976 84 04 49",
    "sg:postcode":"50230",
    "sg:province":"Zaragoza",
    "wof:name":"Excavaciones Esteban Marco S.l.",
    "wof:placetype":"venue"
},
  "geometry": {"coordinates":[-1.9006040096,41.2966537476],"type":"Point"}
}