{
  "type": "Feature",
  "properties": {
    "addr:full":"Calle de Alcala, 441 Madrid Madrid 28027",
    "addr:housenumber":"441",
    "addr:postcode":"28027",
    "addr:street":"Calle De Alcala",
    "iso:country":"ES",
    "sg:address":"Calle de Alcala, 441",
    "sg:city":"Madrid",
    "sg:orig_category":"Tapicer\u00cdas",
    "sg:phone":"+34 917 42 32 64",
    "sg:postcode":"28027",
    "sg:province":"Madrid",
    "wof:name":"Rabadan Y Asociados S.a.",
    "wof:placetype":"venue"
},
  "geometry": {"coordinates":[-3.6357426643,40.4385070801],"type":"Point"}
}