{
  "type": "Feature",
  "properties": {
    "iso:country":"ES",
    "sg:address":"Carr Joaquim Escriva I Peiro (retor), 17",
    "sg:city":"Catarroja",
    "sg:orig_category":"Chapister\u00cda",
    "sg:phone":"+34 961 26 90 75",
    "sg:postcode":"46470",
    "sg:province":"Valencia",
    "wof:name":"Servei D'automocio S.l.l.",
    "wof:placetype":"venue"
},
  "geometry": {"coordinates":[-0.4087530077,39.403793335],"type":"Point"}
}