{
  "type": "Feature",
  "properties": {
    "addr:full":"Calle de Manuel Salda\u00d1a, 45 Badajoz Badajoz 06010",
    "addr:housenumber":"45",
    "addr:postcode":"06010",
    "addr:street":"Calle De Manuel Saldan\u0303A",
    "iso:country":"ES",
    "sg:address":"Calle de Manuel Salda\u00d1a, 45",
    "sg:city":"Badajoz",
    "sg:orig_category":"Peluquer\u00cdas, Peluquer\u00cda Mixta",
    "sg:phone":"+34 924 23 01 13",
    "sg:postcode":"06010",
    "sg:province":"Badajoz",
    "wof:name":"Lopez Garcia Maria Josefa",
    "wof:placetype":"venue"
},
  "geometry": {"coordinates":[-6.9797358513,38.8675346375],"type":"Point"}
}