{
  "type": "Feature",
  "properties": {
    "addr:full":"Carrer de Sant Joan Salle, 13 Palma Islas Baleares 07003",
    "addr:housenumber":"13",
    "addr:postcode":"07003",
    "addr:street":"Carrer De Sant;Salle",
    "iso:country":"ES",
    "sg:address":"Carrer de Sant Joan Salle, 13",
    "sg:city":"Palma",
    "sg:orig_category":"Doctores En Medicina",
    "sg:phone":"+34 971 75 81 83",
    "sg:postcode":"07003",
    "sg:province":"Islas Baleares",
    "wof:name":"Estrades Gomez Joaquin",
    "wof:placetype":"venue"
},
  "geometry": {"coordinates":[2.6468939781,39.5796470642],"type":"Point"}
}