{
  "type": "Feature",
  "properties": {
    "iso:country":"ES",
    "sg:address":"Poli Las Capellanias, S/n",
    "sg:city":"Caceres",
    "sg:orig_category":"Electrodom\u00c9sticos (fabricaci\u00d3n, Al Por Mayor)",
    "sg:phone":"+34 927 23 08 54",
    "sg:postcode":"10005",
    "sg:province":"C\u00e1ceres",
    "wof:name":"Lorenzo Roman S.a.",
    "wof:placetype":"venue"
},
  "geometry": {"coordinates":[-6.5356450081,39.3445549011],"type":"Point"}
}