{
  "type": "Feature",
  "properties": {
    "addr:full":"Calle de Cervantes, 1 Villamalea Albacete 02270",
    "addr:housenumber":"1",
    "addr:postcode":"02270",
    "addr:street":"Calle De Cervantes",
    "iso:country":"ES",
    "sg:address":"Calle de Cervantes, 1",
    "sg:city":"Villamalea",
    "sg:orig_category":"Negocio De Materiales De Construcci\u00d3n",
    "sg:phone":"+34 967 48 30 61",
    "sg:postcode":"02270",
    "sg:province":"Albacete",
    "wof:name":"Gomez Tarancon Pedro",
    "wof:placetype":"venue"
},
  "geometry": {"coordinates":[-1.5986332893,39.3576011658],"type":"Point"}
}