{
  "type": "Feature",
  "properties": {
    "addr:full":"Rua Ramon Gonzalez, 11 Porri\u00f1o Pontevedra 36400",
    "addr:housenumber":"11",
    "addr:postcode":"36400",
    "addr:street":"Rua Ramon Gonzalez",
    "iso:country":"ES",
    "sg:address":"Rua Ramon Gonzalez, 11",
    "sg:city":"Porri\u00f1o",
    "sg:orig_category":"Librer\u00cdas",
    "sg:phone":"+34 986 33 13 14",
    "sg:postcode":"36400",
    "sg:province":"Pontevedra",
    "wof:name":"Fernandez Vazquez Ana Lucia",
    "wof:placetype":"venue"
},
  "geometry": {"coordinates":[-8.6213569641,42.1620101929],"type":"Point"}
}