{
  "type": "Feature",
  "properties": {
    "iso:country":"ES",
    "sg:address":"Carrer de Angel Guimera, 16",
    "sg:city":"Masnou",
    "sg:orig_category":"Comercio, Reparaci\u00d3n De Motocicletas, Bicicletas Y Piezas Sueltas",
    "sg:phone":"+34 935 40 88 52",
    "sg:postcode":"08320",
    "sg:province":"Barcelona",
    "wof:name":"Torralba Castellano Pedro",
    "wof:placetype":"venue"
},
  "geometry": {"coordinates":[2.3291599751,41.4814491272],"type":"Point"}
}