{
  "type": "Feature",
  "properties": {
    "addr:full":"Ctra. Jerez-cartagena, Km. 0124,0 Almargen M\u00e1laga 29330",
    "addr:housenumber":"almargen",
    "addr:postcode":"29330",
    "addr:street":"Ctra. Jerez-Cartagena Km. 0124,0",
    "iso:country":"ES",
    "sg:address":"Ctra. Jerez-cartagena, Km. 0124,0",
    "sg:city":"Almargen",
    "sg:orig_category":"Reciclaje, Desguace De Veh\u00cdculos",
    "sg:phone":"+34 952 11 45 07",
    "sg:postcode":"29330",
    "sg:province":"M\u00e1laga",
    "wof:name":"Roman Sanchez Juan",
    "wof:placetype":"venue"
},
  "geometry": {"coordinates":[-5.022714138,37.0001945496],"type":"Point"}
}