{
  "type": "Feature",
  "properties": {
    "addr:full":"Calle de Francisco Javier De Moya, 70 Albacete Albacete 02002",
    "addr:housenumber":"70",
    "addr:postcode":"02002",
    "addr:street":"Calle De Francisco Javier De Moya",
    "iso:country":"ES",
    "sg:address":"Calle de Francisco Javier De Moya, 70",
    "sg:city":"Albacete",
    "sg:orig_category":"Peluquer\u00cdas, Peluquer\u00cda Mixta",
    "sg:phone":"+34 967 50 39 79",
    "sg:postcode":"02002",
    "sg:province":"Albacete",
    "wof:name":"Crisa C.b.",
    "wof:placetype":"venue"
},
  "geometry": {"coordinates":[-1.8525619507,38.9855079651],"type":"Point"}
}