{
  "type": "Feature",
  "properties": {
    "addr:full":"Carrer de Torras I Bages, 13 Sabadell Barcelona 08201",
    "addr:housenumber":"13",
    "addr:postcode":"08201",
    "addr:street":"Carrer De Torras I Bages",
    "iso:country":"ES",
    "sg:address":"Carrer de Torras I Bages, 13",
    "sg:city":"Sabadell",
    "sg:orig_category":"Fabricaci\u00d3n, Venta De Cuadros, Accesorios Para Enmarcar",
    "sg:phone":"+34 937 26 49 55",
    "sg:postcode":"08201",
    "sg:province":"Barcelona",
    "wof:name":"Juanico Lopez Margarita",
    "wof:placetype":"venue"
},
  "geometry": {"coordinates":[2.1047620773,41.5457954407],"type":"Point"}
}