{
  "type": "Feature",
  "properties": {
    "iso:country":"ES",
    "sg:address":"Calle de Honduras, 2",
    "sg:city":"Salamanca",
    "sg:orig_category":"Arquitectos",
    "sg:phone":"+34 923 12 01 22",
    "sg:postcode":"37003",
    "sg:province":"Salamanca",
    "wof:name":"Perez Cornejo Pablo",
    "wof:placetype":"venue"
},
  "geometry": {"coordinates":[-5.6551790237,40.9647102356],"type":"Point"}
}