{
  "type": "Feature",
  "properties": {
    "iso:country":"ES",
    "sg:address":"Calle de Virgen De Guadalupe, 33",
    "sg:city":"Ubeda",
    "sg:orig_category":"Promotores Constructores",
    "sg:phone":"+34 953 75 13 58",
    "sg:postcode":"23400",
    "sg:province":"Ja\u00e9n",
    "wof:name":"Empresa De Transformacion Agraria S A",
    "wof:placetype":"venue"
},
  "geometry": {"coordinates":[-3.3726360798,38.0161209106],"type":"Point"}
}