{
  "type": "Feature",
  "properties": {
    "addr:full":"Calle de Duquesa, 5 Granada Granada 18001",
    "addr:housenumber":"5",
    "addr:postcode":"18001",
    "addr:street":"Calle De Duquesa",
    "iso:country":"ES",
    "sg:address":"Calle de Duquesa, 5",
    "sg:city":"Granada",
    "sg:orig_category":"Fabricaci\u00d3n, Distribuci\u00d3n De Discos, V\u00cddeodiscos Y Musicassettes",
    "sg:phone":"+34 958 28 32 56",
    "sg:postcode":"18001",
    "sg:province":"Granada",
    "wof:name":"Marmol Ortega Jose",
    "wof:placetype":"venue"
},
  "geometry": {"coordinates":[-3.601834774,37.1767730713],"type":"Point"}
}