{
  "type": "Feature",
  "properties": {
    "iso:country":"ES",
    "sg:address":"Avda Xose Solla, 11",
    "sg:city":"Calle",
    "sg:orig_category":"Panader\u00cdas, Panader\u00cdas",
    "sg:phone":"+34 986 70 08 54",
    "sg:postcode":"36690",
    "sg:province":"Pontevedra",
    "wof:name":"Lopez Taboas Maria Del Pilar",
    "wof:placetype":"venue"
},
  "geometry": {"coordinates":[-8.6063833237,42.3409309387],"type":"Point"}
}