{
  "type": "Feature",
  "properties": {
    "iso:country":"ES",
    "sg:address":"Calle de Poeta Miguel Hernandez, 8",
    "sg:city":"Santa Pola",
    "sg:orig_category":"M\u00c9dicos: Estomatolog\u00cda",
    "sg:phone":"+34 965 41 26 77",
    "sg:postcode":"03130",
    "sg:province":"Alicante",
    "wof:name":"Juan Garcia Nelson",
    "wof:placetype":"venue"
},
  "geometry": {"coordinates":[-0.5565180182,38.192035675],"type":"Point"}
}