{
  "type": "Feature",
  "properties": {
    "addr:full":"Calle de Poeta Miguel Hernandez, 22 Santa Pola Alicante 03130",
    "addr:housenumber":"22",
    "addr:postcode":"03130",
    "addr:street":"Calle De Poeta Miguel Hernandez",
    "iso:country":"ES",
    "sg:address":"Calle de Poeta Miguel Hernandez, 22",
    "sg:city":"Santa Pola",
    "sg:orig_category":"Inform\u00c1tica, Ofim\u00c1tica (estudios, Asesor\u00cda, Ingenier\u00cda, Formaci\u00d3n)",
    "sg:phone":"+34 966 69 46 24",
    "sg:postcode":"03130",
    "sg:province":"Alicante",
    "wof:name":"Pina Gosalbez Francisco Javier",
    "wof:placetype":"venue"
},
  "geometry": {"coordinates":[-0.5569999814,38.1914901733],"type":"Point"}
}