{
  "type": "Feature",
  "properties": {
    "addr:full":"Calle de Hermanos Lopez Francos, 2 Palencia Palencia 34003",
    "addr:housenumber":"2",
    "addr:postcode":"34003",
    "addr:street":"Calle De Hermanos Lopez Francos",
    "iso:country":"ES",
    "sg:address":"Calle de Hermanos Lopez Francos, 2",
    "sg:city":"Palencia",
    "sg:orig_category":"Molduras, Junquillos, Listones Y Molduras Perforadas",
    "sg:phone":"+34 979 75 23 72",
    "sg:postcode":"34003",
    "sg:province":"Palencia",
    "wof:name":"Calderon Diez Oscar",
    "wof:placetype":"venue"
},
  "geometry": {"coordinates":[-4.5313749313,42.0169448853],"type":"Point"}
}