{
  "type": "Feature",
  "properties": {
    "addr:full":"Calle de Horacio Lengo, 19 Malaga M\u00e1laga 29006",
    "addr:housenumber":"19",
    "addr:postcode":"29006",
    "addr:street":"Calle De Horacio Lengo;Ma\u0301Laga",
    "iso:country":"ES",
    "sg:address":"Calle de Horacio Lengo, 19",
    "sg:city":"Malaga",
    "sg:orig_category":"Muebles, Minoristas",
    "sg:phone":"+34 952 33 19 04",
    "sg:postcode":"29006",
    "sg:province":"M\u00e1laga",
    "sg:website":"www.qummuebles.com",
    "wof:name":"Alcora Muebles Dise\u00f1o S.l.",
    "wof:placetype":"venue"
},
  "geometry": {"coordinates":[-4.439725399,36.7142601013],"type":"Point"}
}