{
  "type": "Feature",
  "properties": {
    "iso:country":"ES",
    "sg:address":"Urb. Pline, 12",
    "sg:city":"Loja",
    "sg:orig_category":"Aparcamientos (infraestructuras, Accesorios)",
    "sg:phone":"+34 958 32 30 50",
    "sg:postcode":"18300",
    "sg:province":"Granada",
    "wof:name":"Estacionamientos Y Servicios S.a.",
    "wof:placetype":"venue"
},
  "geometry": {"coordinates":[-4.1416559219,37.1755256653],"type":"Point"}
}