{
  "type": "Feature",
  "properties": {
    "iso:country":"ES",
    "sg:address":"Avda Cardenal Vicente Enrique Y Tarancon, 24",
    "sg:city":"Burriana",
    "sg:orig_category":"Art\u00cdculos De Decoraci\u00d3n",
    "sg:phone":"+34 964 57 16 97",
    "sg:postcode":"12530",
    "sg:province":"Castell\u00f3n",
    "wof:name":"Bucaro Decoracio S.l.",
    "wof:placetype":"venue"
},
  "geometry": {"coordinates":[-0.0760790035,39.8851013184],"type":"Point"}
}