{
  "type": "Feature",
  "properties": {
    "addr:full":"Calle de Doctor Carmena Villarta, S/n A\u00e7over De Tajo Toledo 45250",
    "addr:housenumber":"s / n",
    "addr:postcode":"45250",
    "addr:street":"Calle De Doctor Carmena Villarta",
    "iso:country":"ES",
    "sg:address":"Calle de Doctor Carmena Villarta, S/n",
    "sg:city":"A\u00e7over De Tajo",
    "sg:orig_category":"Centros De Educaci\u00d3n Especial",
    "sg:phone":"+34 925 50 61 53",
    "sg:postcode":"45250",
    "sg:province":"Toledo",
    "wof:name":"Colegio Nacional Conde Mayalde",
    "wof:placetype":"venue"
},
  "geometry": {"coordinates":[-3.7720139027,39.988658905],"type":"Point"}
}