{
  "type": "Feature",
  "properties": {
    "addr:full":"Calle de Granada, 266 Almeria Almer\u00eda 04008",
    "addr:housenumber":"266",
    "addr:postcode":"04008",
    "addr:street":"Calle De Granada",
    "iso:country":"ES",
    "sg:address":"Calle de Granada, 266",
    "sg:city":"Almeria",
    "sg:orig_category":"Cajas De Ahorro",
    "sg:phone":"+34 950 23 08 08",
    "sg:postcode":"04008",
    "sg:province":"Almer\u00eda",
    "sg:website":"www.cajasur.es",
    "wof:name":"Caja De Ahorros Y Monte De Piedad De Cordoba",
    "wof:placetype":"venue"
},
  "geometry": {"coordinates":[-2.4553101063,36.8493309021],"type":"Point"}
}