{
  "type": "Feature",
  "properties": {
    "iso:country":"ES",
    "sg:address":"Av. Puxeiros, 89",
    "sg:city":"Mos",
    "sg:orig_category":"Suministros Para Hoteles",
    "sg:phone":"+34 986 48 65 51",
    "sg:postcode":"36416",
    "sg:province":"Pontevedra",
    "wof:name":"Mercantil Espa\u00f1ola De Refrigeracion S.l.",
    "wof:placetype":"venue"
},
  "geometry": {"coordinates":[-8.6066894531,42.2026252747],"type":"Point"}
}