{
  "type": "Feature",
  "properties": {
    "iso:country":"ES",
    "sg:address":"Torrent, 11",
    "sg:city":"Cervia Ter",
    "sg:orig_category":"M\u00c9dicos: Estomatolog\u00cda",
    "sg:phone":"+34 972 49 60 10",
    "sg:postcode":"17464",
    "sg:province":"Girona",
    "wof:name":"Clinica Dental Dentsana S.c.",
    "wof:placetype":"venue"
},
  "geometry": {"coordinates":[2.9534270763,42.0719909668],"type":"Point"}
}