{
  "type": "Feature",
  "properties": {
    "iso:country":"ES",
    "sg:address":"Av Remolar, 58",
    "sg:city":"Prat Llobregat",
    "sg:orig_category":"Mec\u00c1nico Del Autom\u00d3vil",
    "sg:phone":"+34 933 79 40 16",
    "sg:postcode":"08820",
    "sg:province":"Barcelona",
    "wof:name":"Molina Rejon Justo",
    "wof:placetype":"venue"
},
  "geometry": {"coordinates":[2.0878961086,41.3241004944],"type":"Point"}
}