{
  "type": "Feature",
  "properties": {
    "addr:full":"Calle de Inmaculada Concepcion, 44 Madrid Madrid 28019",
    "addr:housenumber":"44",
    "addr:postcode":"madrid;28019",
    "addr:street":"Calle De Inmaculada Concepcion",
    "iso:country":"ES",
    "sg:address":"Calle de Inmaculada Concepcion, 44",
    "sg:city":"Madrid",
    "sg:orig_category":"Carnicer\u00cdas, Carnicer\u00cdas",
    "sg:phone":"+34 914 69 36 97",
    "sg:postcode":"28019",
    "sg:province":"Madrid",
    "wof:name":"Arribas Andres Juan",
    "wof:placetype":"venue"
},
  "geometry": {"coordinates":[-3.7124626637,40.3916816711],"type":"Point"}
}