{
  "type": "Feature",
  "properties": {
    "iso:country":"ES",
    "sg:address":"La Ba\u00f1eza, 16",
    "sg:city":"Villoria De Orbigo",
    "sg:orig_category":"Semiller\u00cdas",
    "sg:phone":"+34 987 37 54 25",
    "sg:postcode":"24358",
    "sg:province":"Le\u00f3n",
    "wof:name":"Cuevas Lombas Jose",
    "wof:placetype":"venue"
},
  "geometry": {"coordinates":[-5.886619091,42.4169464111],"type":"Point"}
}