{
  "type": "Feature",
  "properties": {
    "addr:full":"Av Catalunya, 58 Cerdanyola Valles Barcelona 08290",
    "addr:housenumber":"58",
    "addr:postcode":"08290",
    "addr:street":"Av Catalunya;Valles Barcelona",
    "iso:country":"ES",
    "sg:address":"Av Catalunya, 58",
    "sg:city":"Cerdanyola Valles",
    "sg:orig_category":"Arquitectos",
    "sg:phone":"+34 935 80 97 44",
    "sg:postcode":"08290",
    "sg:province":"Barcelona",
    "wof:name":"Gonzalez Gonzalez Alfredo",
    "wof:placetype":"venue"
},
  "geometry": {"coordinates":[2.1445236206,41.4930534363],"type":"Point"}
}