{
  "type": "Feature",
  "properties": {
    "iso:country":"ES",
    "sg:address":"Carrer de Collserola, 68",
    "sg:city":"Hospitalet Llobregat",
    "sg:orig_category":"Asociaciones, Organismos Culturales Y Socioeducativos",
    "sg:phone":"+34 934 49 48 23",
    "sg:postcode":"08905",
    "sg:province":"Barcelona",
    "wof:name":"Pe\u00f1a Flamenca Y Recreativa Antonio Mairena De Hospitalet",
    "wof:placetype":"venue"
},
  "geometry": {"coordinates":[2.1103889942,41.3739700317],"type":"Point"}
}