{
  "type": "Feature",
  "properties": {
    "iso:country":"ES",
    "sg:address":"Calle de Rector Martin Villa, 16",
    "sg:city":"Almonte",
    "sg:orig_category":"Aparcamientos (infraestructuras, Accesorios)",
    "sg:phone":"+34 959 45 05 18",
    "sg:postcode":"21730",
    "sg:province":"Huelva",
    "wof:name":"Focus Aparcamientos Urbanos S.l.",
    "wof:placetype":"venue"
},
  "geometry": {"coordinates":[-6.5186100006,37.2632102966],"type":"Point"}
}