{
  "type": "Feature",
  "properties": {
    "iso:country":"ES",
    "sg:address":"Av Mare De Deu De Bellvitge, 20",
    "sg:city":"Hospitalet Llobregat",
    "sg:orig_category":"Asilos De Ancianos. Centros Privados",
    "sg:phone":"+34 932 63 20 34",
    "sg:postcode":"08907",
    "sg:province":"Barcelona",
    "wof:name":"Residencia Y Atencion Social S.l.",
    "wof:placetype":"venue"
},
  "geometry": {"coordinates":[2.1075479984,41.3477783203],"type":"Point"}
}