{
  "type": "Feature",
  "properties": {
    "addr:full":"Fortuna-murcia, S/n Fortuna Murcia 30620",
    "addr:housenumber":"/ n",
    "addr:postcode":"30620",
    "addr:street":"Fortuna-Murcia S",
    "iso:country":"ES",
    "sg:address":"Fortuna-murcia, S/n",
    "sg:city":"Fortuna",
    "sg:orig_category":"Centros Empresariales",
    "sg:phone":"+34 968 68 58 72",
    "sg:postcode":"30620",
    "sg:province":"Murcia",
    "wof:name":"Ramirez  Santi Francois",
    "wof:placetype":"venue"
},
  "geometry": {"coordinates":[-1.1266340017,38.1826553345],"type":"Point"}
}