{
  "type": "Feature",
  "properties": {
    "addr:full":"Ctra. Granada, Km. 0394,0 Alcala Real Ja\u00e9n 23680",
    "addr:postcode":"23680",
    "addr:street":"Ctra. Granada Km. 0394,0;Jae\u0301N",
    "iso:country":"ES",
    "sg:address":"Ctra. Granada, Km. 0394,0",
    "sg:city":"Alcala Real",
    "sg:orig_category":"Mec\u00c1nico Del Autom\u00d3vil",
    "sg:phone":"+34 953 58 04 12",
    "sg:postcode":"23680",
    "sg:province":"Ja\u00e9n",
    "wof:name":"Auto Diesel Hermanos Navarro S.l.",
    "wof:placetype":"venue"
},
  "geometry": {"coordinates":[-3.919318676,37.4495582581],"type":"Point"}
}