{
  "type": "Feature",
  "properties": {
    "iso:country":"ES",
    "sg:address":"Carrer de Rafael Capdevila, 7",
    "sg:city":"Barcelona",
    "sg:orig_category":"Inmobiliaria (agencias)",
    "sg:phone":"+34 932 89 06 48",
    "sg:postcode":"08018",
    "sg:province":"Barcelona",
    "wof:name":"General De Aduanas Transitos Y Transportes S.l.",
    "wof:placetype":"venue"
},
  "geometry": {"coordinates":[2.1880750656,41.4090614319],"type":"Point"}
}