{
  "type": "Feature",
  "properties": {
    "iso:country":"ES",
    "sg:address":"Calle de Arevalo, 8",
    "sg:city":"Ti\u00d1osillos",
    "sg:orig_category":"Reposter\u00cdas",
    "sg:phone":"+34 920 26 70 28",
    "sg:postcode":"05165",
    "sg:province":"\u00c1vila",
    "wof:name":"Garcinu\u00f1o Gonzalez Jose Benigno",
    "wof:placetype":"venue"
},
  "geometry": {"coordinates":[-4.7284631729,40.9331550598],"type":"Point"}
}