{
  "type": "Feature",
  "properties": {
    "addr:full":"Cmno Arebeta Bidea, 5 Berango Vizcaya 48640",
    "addr:housenumber":"5",
    "addr:postcode":"48640",
    "addr:street":"Cmno Arebeta Bidea",
    "iso:country":"ES",
    "sg:address":"Cmno Arebeta Bidea, 5",
    "sg:city":"Berango",
    "sg:orig_category":"Barnizadores",
    "sg:phone":"+34 946 68 10 67",
    "sg:postcode":"48640",
    "sg:province":"Vizcaya",
    "wof:name":"Garcia Herreros Pablo",
    "wof:placetype":"venue"
},
  "geometry": {"coordinates":[-2.9955940247,43.3641815186],"type":"Point"}
}