{
  "type": "Feature",
  "properties": {
    "iso:country":"ES",
    "sg:address":"Ctra Fuengirola Mijas, S/n",
    "sg:city":"Mijas",
    "sg:orig_category":"Alquiler De Veh\u00cdculos: Turismos Y Utilitarios",
    "sg:phone":"+34 952 48 64 07",
    "sg:postcode":"29650",
    "sg:province":"M\u00e1laga",
    "wof:name":"Dragon Car Hire S.l.",
    "wof:placetype":"venue"
},
  "geometry": {"coordinates":[-4.6816139221,36.5521850586],"type":"Point"}
}