{
  "type": "Feature",
  "properties": {
    "iso:country":"ES",
    "sg:address":"Calle de Capulino Jauregui, 7",
    "sg:city":"Malaga",
    "sg:orig_category":"Ingenier\u00cda, Centros De Estudios (diversos)",
    "sg:phone":"+34 952 32 51 56",
    "sg:postcode":"29002",
    "sg:province":"M\u00e1laga",
    "wof:name":"Aufer Ingenieria Y Gestion S.l.",
    "wof:placetype":"venue"
},
  "geometry": {"coordinates":[-4.4349632263,36.7052612305],"type":"Point"}
}