{
  "type": "Feature",
  "properties": {
    "iso:country":"ES",
    "sg:address":"Plaza Yamaguchi, 11",
    "sg:city":"Iru\u00f1a",
    "sg:orig_category":"Arquitectos",
    "sg:phone":"+34 948 17 23 49",
    "sg:postcode":"31008",
    "sg:province":"Navarra",
    "wof:name":"Arribas Echeveste Jose Ignacio",
    "wof:placetype":"venue"
},
  "geometry": {"coordinates":[-1.6624530554,42.8103675842],"type":"Point"}
}