{
  "type": "Feature",
  "properties": {
    "addr:full":"Calle de Trinidad, 16 Toledo Toledo 45002",
    "addr:housenumber":"16",
    "addr:postcode":"45002",
    "addr:street":"Calle De Trinidad",
    "iso:country":"ES",
    "sg:address":"Calle de Trinidad, 16",
    "sg:city":"Toledo",
    "sg:orig_category":"Empresas De Pintura Y Revestimientos",
    "sg:phone":"+34 925 22 70 16",
    "sg:postcode":"45002",
    "sg:province":"Toledo",
    "wof:name":"Gomez Fernandez Juan Jose",
    "wof:placetype":"venue"
},
  "geometry": {"coordinates":[-4.0260381699,39.857208252],"type":"Point"}
}