{
  "type": "Feature",
  "properties": {
    "iso:country":"ES",
    "sg:address":"Carrer de Lluc, 11",
    "sg:city":"Barcelona",
    "sg:orig_category":"Carnicer\u00cdas, Carnicer\u00cdas",
    "sg:phone":"+34 933 50 82 97",
    "sg:postcode":"08016",
    "sg:province":"Barcelona",
    "wof:name":"Matas Merchan Diego",
    "wof:placetype":"venue"
},
  "geometry": {"coordinates":[2.177355051,41.4384422302],"type":"Point"}
}