{
  "type": "Feature",
  "properties": {
    "addr:full":"Calle de Cristobal Gracia, 15 Santomera Murcia 30140",
    "addr:housenumber":"15",
    "addr:postcode":"30140",
    "addr:street":"Calle De Cristobal Gracia",
    "iso:country":"ES",
    "sg:address":"Calle de Cristobal Gracia, 15",
    "sg:city":"Santomera",
    "sg:orig_category":"Promotores Constructores",
    "sg:phone":"+34 968 86 32 12",
    "sg:postcode":"30140",
    "sg:province":"Murcia",
    "wof:name":"Somgas Levante S.l.",
    "wof:placetype":"venue"
},
  "geometry": {"coordinates":[-1.0458282232,38.061706543],"type":"Point"}
}