{
  "type": "Feature",
  "properties": {
    "iso:country":"ES",
    "sg:address":"Calle de Manuel Escribano, 11",
    "sg:city":"A\u00e7over De Tajo",
    "sg:orig_category":"Papeler\u00cdas, Librer\u00cdas",
    "sg:phone":"+34 925 55 51 65",
    "sg:postcode":"45250",
    "sg:province":"Toledo",
    "wof:name":"Garcia Diaz Gregoria",
    "wof:placetype":"venue"
},
  "geometry": {"coordinates":[-3.769215107,39.9885787964],"type":"Point"}
}