{
  "type": "Feature",
  "properties": {
    "addr:full":"Calle de Campo, 140 Tomelloso Ciudad Real 13700",
    "addr:housenumber":"140",
    "addr:postcode":"13700",
    "addr:street":"Calle De Campo",
    "iso:country":"ES",
    "sg:address":"Calle de Campo, 140",
    "sg:city":"Tomelloso",
    "sg:orig_category":"Mec\u00c1nico Del Autom\u00d3vil",
    "sg:phone":"+34 926 51 05 07",
    "sg:postcode":"13700",
    "sg:province":"Ciudad Real",
    "wof:name":"Ortiz Y Cabrera S.a",
    "wof:placetype":"venue"
},
  "geometry": {"coordinates":[-3.0224099159,39.1695404053],"type":"Point"}
}