{
  "type": "Feature",
  "properties": {
    "iso:country":"ES",
    "sg:address":"Calle de Cardenal Cisneros, 26",
    "sg:city":"Alcala Henares",
    "sg:orig_category":"Asociaciones, Organismos Culturales Y Socioeducativos",
    "sg:phone":"+34 918 82 31 93",
    "sg:postcode":"28802",
    "sg:province":"Madrid",
    "wof:name":"Asociacion Cultural Pe\u00f1alen",
    "wof:placetype":"venue"
},
  "geometry": {"coordinates":[-3.3713593483,40.4807014465],"type":"Point"}
}