{
  "type": "Feature",
  "properties": {
    "addr:full":"Calle de Serrano, 1 Villarrubia Santiago Toledo 45360",
    "addr:housenumber":"1",
    "addr:postcode":"45360",
    "addr:street":"Calle De Serrano",
    "iso:country":"ES",
    "sg:address":"Calle de Serrano, 1",
    "sg:city":"Villarrubia Santiago",
    "sg:orig_category":"Molduras, Junquillos, Listones Y Molduras Perforadas",
    "sg:phone":"+34 925 15 02 79",
    "sg:postcode":"45360",
    "sg:province":"Toledo",
    "wof:name":"Escobar Garro Cecilio",
    "wof:placetype":"venue"
},
  "geometry": {"coordinates":[-3.3684620857,39.9871520996],"type":"Point"}
}