{
  "type": "Feature",
  "properties": {
    "iso:country":"ES",
    "sg:address":"Avda Industria (de La), 22",
    "sg:city":"Coslada",
    "sg:orig_category":"Agencias De Aduana",
    "sg:phone":"+34 916 72 72 14",
    "sg:postcode":"28820",
    "sg:province":"Madrid",
    "wof:name":"Doman S. A.",
    "wof:placetype":"venue"
},
  "geometry": {"coordinates":[-3.5515499115,40.4348106384],"type":"Point"}
}