{
  "type": "Feature",
  "properties": {
    "addr:full":"Calle de Vicente Mu\u00d1oz, 5 Pozuelo De Alarcon Madrid 28223",
    "addr:housenumber":"5",
    "addr:postcode":"28223",
    "addr:street":"Calle De Vicente Mun\u0303Oz",
    "iso:country":"ES",
    "sg:address":"Calle de Vicente Mu\u00d1oz, 5",
    "sg:city":"Pozuelo De Alarcon",
    "sg:orig_category":"Producci\u00d3n, Distribuci\u00d3n De Electricidad",
    "sg:phone":"+34 917 15 34 12",
    "sg:postcode":"28223",
    "sg:province":"Madrid",
    "wof:name":"Sanchez Coto Juan",
    "wof:placetype":"venue"
},
  "geometry": {"coordinates":[-3.8144218922,40.4401741028],"type":"Point"}
}