{
  "type": "Feature",
  "properties": {
    "addr:full":"G.v. Lopez De Haro D. Diego, 81 Bilbao Vizcaya 48011",
    "addr:housenumber":"81",
    "addr:postcode":"48011",
    "addr:street":"Lopez De Haro D. Diego",
    "iso:country":"ES",
    "sg:address":"G.v. Lopez De Haro D. Diego, 81",
    "sg:city":"Bilbao",
    "sg:orig_category":"M\u00c9dicos: Ginecolog\u00cda Y Obstetricia",
    "sg:phone":"+34 944 05 13 78",
    "sg:postcode":"48011",
    "sg:province":"Vizcaya",
    "wof:name":"Bilbomedi, S.l.",
    "wof:placetype":"venue"
},
  "geometry": {"coordinates":[-2.9434769154,43.2647438049],"type":"Point"}
}