{
  "type": "Feature",
  "properties": {
    "iso:country":"ES",
    "sg:address":"Zona Portuaria, S/n",
    "sg:city":"Palamos",
    "sg:orig_category":"Fabricaci\u00d3n, Reparaci\u00d3n Y Mantenimiento De Construcciones Navales Y Fluviales",
    "sg:phone":"+34 972 31 50 14",
    "sg:postcode":"17230",
    "sg:province":"Girona",
    "wof:name":"Taller Del Port S.l.",
    "wof:placetype":"venue"
},
  "geometry": {"coordinates":[3.1279499531,41.8473548889],"type":"Point"}
}