{
  "type": "Feature",
  "properties": {
    "addr:full":"Avda Rosalia De Castro, 2 Santa Uxia De Ribeira La Coru\u00f1a 15960",
    "addr:housenumber":"2",
    "addr:postcode":"15960",
    "addr:street":"Avda Rosalia De Castro;Corun\u0303A",
    "iso:country":"ES",
    "sg:address":"Avda Rosalia De Castro, 2",
    "sg:city":"Santa Uxia De Ribeira",
    "sg:orig_category":"Art\u00cdculos De Regalo (al Por Menor)",
    "sg:phone":"+34 981 87 08 29",
    "sg:postcode":"15960",
    "sg:province":"La Coru\u00f1a",
    "wof:name":"Hermanas Pego Paz S.c.",
    "wof:placetype":"venue"
},
  "geometry": {"coordinates":[-8.990811348,42.5552635193],"type":"Point"}
}