{
  "type": "Feature",
  "properties": {
    "iso:country":"ES",
    "sg:address":"Calle de Postiguillo, 1",
    "sg:city":"Torredonjimeno",
    "sg:orig_category":"Inform\u00c1tica, Ofim\u00c1tica (estudios, Asesor\u00cda, Ingenier\u00cda, Formaci\u00d3n)",
    "sg:phone":"+34 953 34 13 09",
    "sg:postcode":"23650",
    "sg:province":"Ja\u00e9n",
    "wof:name":"Top System 2006 S.l.",
    "wof:placetype":"venue"
},
  "geometry": {"coordinates":[-3.9577488899,37.7663803101],"type":"Point"}
}