{
  "type": "Feature",
  "properties": {
    "iso:country":"ES",
    "sg:address":"Calle de Capitan Oca\u00d1a, 1",
    "sg:city":"Navas De Estena",
    "sg:orig_category":"Molduras, Junquillos, Listones Y Molduras Perforadas",
    "sg:phone":"+34 925 40 90 20",
    "sg:postcode":"13194",
    "sg:province":"Ciudad Real",
    "wof:name":"Martin Delgado Sebastian",
    "wof:placetype":"venue"
},
  "geometry": {"coordinates":[-4.52140522,39.4951553345],"type":"Point"}
}