{
  "type": "Feature",
  "properties": {
    "iso:country":"ES",
    "sg:address":"Calle de Cruz De Conchas, 11",
    "sg:city":"Motril",
    "sg:orig_category":"M\u00c9dicos: Dermatolog\u00cda Y Venereolog\u00cda",
    "sg:phone":"+34 958 60 18 43",
    "sg:postcode":"18600",
    "sg:province":"Granada",
    "wof:name":"Abdul-rahim Rashid Rashio",
    "wof:placetype":"venue"
},
  "geometry": {"coordinates":[-3.519478,36.746658],"type":"Point"}
}