{
  "type": "Feature",
  "properties": {
    "iso:country":"ES",
    "sg:address":"Calle de San Francisco, 19",
    "sg:city":"Algeciras",
    "sg:orig_category":"Carnicer\u00cdas, Carnicer\u00cdas",
    "sg:phone":"+34 956 66 43 16",
    "sg:postcode":"11203",
    "sg:province":"C\u00e1diz",
    "wof:name":"Gomez Caballero David",
    "wof:placetype":"venue"
},
  "geometry": {"coordinates":[-5.4548311234,36.1318664551],"type":"Point"}
}