{
  "type": "Feature",
  "properties": {
    "iso:country":"ES",
    "sg:address":"Calle de San Vicente Martir, 306",
    "sg:city":"Valencia",
    "sg:orig_category":"Aparatos, Sistemas De Tele",
    "sg:phone":"+34 963 78 06 56",
    "sg:postcode":"46017",
    "sg:province":"Valencia",
    "wof:name":"Proyectos E Ingenieria Contra Incendios S.l.",
    "wof:placetype":"venue"
},
  "geometry": {"coordinates":[-0.3851000071,39.450920105],"type":"Point"}
}