{
  "type": "Feature",
  "properties": {
    "addr:full":"Calle de Virgen De La Oliva, 3 Recas Toledo 45211",
    "addr:housenumber":"3",
    "addr:postcode":"45211",
    "addr:street":"Calle De Virgen De La Oliva",
    "iso:country":"ES",
    "sg:address":"Calle de Virgen De La Oliva, 3",
    "sg:city":"Recas",
    "sg:orig_category":"M\u00c1quinas De Coser Y De Hacer Punto (al Por Mayor)",
    "sg:phone":"+34 925 54 70 16",
    "sg:postcode":"45211",
    "sg:province":"Toledo",
    "wof:name":"Nieto S.l.",
    "wof:placetype":"venue"
},
  "geometry": {"coordinates":[-3.9877951145,40.0484199524],"type":"Point"}
}