{
  "type": "Feature",
  "properties": {
    "addr:full":"Calle de San Eugenio, 2 Zaragoza Zaragoza 50007",
    "addr:housenumber":"2",
    "addr:postcode":"50007",
    "addr:street":"Calle De San Eugenio",
    "iso:country":"ES",
    "sg:address":"Calle de San Eugenio, 2",
    "sg:city":"Zaragoza",
    "sg:orig_category":"Asilos De Ancianos. Centros Privados",
    "sg:phone":"+34 976 37 98 00",
    "sg:postcode":"50007",
    "sg:province":"Zaragoza",
    "wof:name":"Patronato De San Eugenio",
    "wof:placetype":"venue"
},
  "geometry": {"coordinates":[-0.8801559806,41.6258049011],"type":"Point"}
}