{
  "type": "Feature",
  "properties": {
    "iso:country":"ES",
    "sg:address":"Calle de Blas Simon, 3",
    "sg:city":"Santa Cruz Palma",
    "sg:orig_category":"Zapatos (al Por Menor)",
    "sg:phone":"+34 922 41 74 64",
    "sg:postcode":"38700",
    "sg:province":"Santa Cruz De Tenerife",
    "wof:name":"La Base Resort S.l.",
    "wof:placetype":"venue"
},
  "geometry": {"coordinates":[-17.7658805847,28.681804657],"type":"Point"}
}