{
  "type": "Feature",
  "properties": {
    "addr:full":"Calle de De Carreteros, 14 Medina Campo Valladolid 47400",
    "addr:housenumber":"14",
    "addr:postcode":"47400",
    "addr:street":"Calle De De Carreteros",
    "iso:country":"ES",
    "sg:address":"Calle de De Carreteros, 14",
    "sg:city":"Medina Campo",
    "sg:orig_category":"Fabricaci\u00d3n Y Distribuci\u00d3n De Colas, Masillas Y Encoladoras",
    "sg:phone":"+34 983 81 25 55",
    "sg:postcode":"47400",
    "sg:province":"Valladolid",
    "wof:name":"Industrias Quimicas Lo-gar S.a.",
    "wof:placetype":"venue"
},
  "geometry": {"coordinates":[-4.7283878326,41.6529464722],"type":"Point"}
}