{
  "type": "Feature",
  "properties": {
    "iso:country":"ES",
    "sg:address":"Rguez. De La Fuente, S/n",
    "sg:city":"Prado Del Rey",
    "sg:orig_category":"Distribuci\u00d3n De Petr\u00d3leo Y Derivados",
    "sg:phone":"+34 956 72 31 52",
    "sg:postcode":"11660",
    "sg:province":"C\u00e1diz",
    "wof:name":"Antonio Mateos Beltran C.b.",
    "wof:placetype":"venue"
},
  "geometry": {"coordinates":[-5.5512280464,36.7711105347],"type":"Point"}
}