{
  "type": "Feature",
  "properties": {
    "addr:full":"Carr Castello, 36 Figueres Girona 17600",
    "addr:housenumber":"36",
    "addr:postcode":"17600",
    "addr:street":"Carr Castello",
    "iso:country":"ES",
    "sg:address":"Carr Castello, 36",
    "sg:city":"Figueres",
    "sg:orig_category":"Molduras, Junquillos, Listones Y Molduras Perforadas",
    "sg:phone":"+34 972 50 09 83",
    "sg:postcode":"17600",
    "sg:province":"Girona",
    "wof:name":"Planas Cerras Catalina",
    "wof:placetype":"venue"
},
  "geometry": {"coordinates":[2.9648919106,42.2658233643],"type":"Point"}
}