{
  "type": "Feature",
  "properties": {
    "addr:full":"Carr Nuria, 3 Badalona Barcelona 08917",
    "addr:housenumber":"3",
    "addr:postcode":"08917",
    "addr:street":"Carr Nuria",
    "iso:country":"ES",
    "sg:address":"Carr Nuria, 3",
    "sg:city":"Badalona",
    "sg:orig_category":"Limpieza Industrial",
    "sg:phone":"+34 933 98 40 00",
    "sg:postcode":"08917",
    "sg:province":"Barcelona",
    "wof:name":"Perez Herrero Florencio",
    "wof:placetype":"venue"
},
  "geometry": {"coordinates":[2.2249100208,41.4526405334],"type":"Point"}
}