{
  "type": "Feature",
  "properties": {
    "addr:full":"Avda Betanzos, 89 Madrid Madrid 28034",
    "addr:housenumber":"89",
    "addr:postcode":"madrid;28034",
    "addr:street":"Avda Betanzos",
    "iso:country":"ES",
    "sg:address":"Avda Betanzos, 89",
    "sg:city":"Madrid",
    "sg:orig_category":"Asesor\u00cda Sobre Comunicaci\u00d3n De Empresas",
    "sg:phone":"+34 917 39 58 60",
    "sg:postcode":"28034",
    "sg:province":"Madrid",
    "wof:name":"Solitax S.l.",
    "wof:placetype":"venue"
},
  "geometry": {"coordinates":[-3.7129099369,40.4795227051],"type":"Point"}
}