{
  "type": "Feature",
  "properties": {
    "addr:full":"Carr Teulada, 11 Benissa Alicante 03720",
    "addr:housenumber":"11",
    "addr:postcode":"03720",
    "addr:street":"Carr Teulada",
    "iso:country":"ES",
    "sg:address":"Carr Teulada, 11",
    "sg:city":"Benissa",
    "sg:orig_category":"Inmobiliaria (agencias)",
    "sg:phone":"+34 965 73 37 42",
    "sg:postcode":"03720",
    "sg:province":"Alicante",
    "wof:name":"Westland Developmenps Espa\u00f1a S.l",
    "wof:placetype":"venue"
},
  "geometry": {"coordinates":[0.0899650007,38.7131652832],"type":"Point"}
}