{
  "type": "Feature",
  "properties": {
    "addr:full":"Calle de Joaquin Ibarra, 6 Madrid Madrid 28042",
    "addr:housenumber":"6",
    "addr:postcode":"28042",
    "addr:street":"Calle De Joaquin Ibarra",
    "iso:country":"ES",
    "sg:address":"Calle de Joaquin Ibarra, 6",
    "sg:city":"Madrid",
    "sg:orig_category":"Fabricaci\u00d3n, Distribuci\u00d3n De Discos, V\u00cddeodiscos Y Musicassettes",
    "sg:phone":"+34 917 42 55 37",
    "sg:postcode":"28042",
    "sg:province":"Madrid",
    "wof:name":"Letras Y Musas S.c.",
    "wof:placetype":"venue"
},
  "geometry": {"coordinates":[-3.593818903,40.4584197998],"type":"Point"}
}