{
  "type": "Feature",
  "properties": {
    "iso:country":"ES",
    "sg:address":"Calle de Almas, 34",
    "sg:city":"Benaguasil",
    "sg:orig_category":"Carnicer\u00cdas, Carnicer\u00cdas",
    "sg:phone":"+34 962 73 11 78",
    "sg:postcode":"46180",
    "sg:province":"Valencia",
    "wof:name":"Peris Llosa Dolores",
    "wof:placetype":"venue"
},
  "geometry": {"coordinates":[-0.6156793833,39.5933952332],"type":"Point"}
}