{
  "type": "Feature",
  "properties": {
    "iso:country":"ES",
    "sg:address":"Calle de Pinar De Inagua, S/n",
    "sg:city":"Mesas",
    "sg:orig_category":"Art\u00cdculos De Regalo (al Por Menor)",
    "sg:phone":"+34 928 43 69 53",
    "sg:postcode":"35018",
    "sg:province":"Las Palmas",
    "wof:name":"Oyasin S.l.",
    "wof:placetype":"venue"
},
  "geometry": {"coordinates":[-15.4947786331,28.1029491425],"type":"Point"}
}