{
  "type": "Feature",
  "properties": {
    "iso:country":"ES",
    "sg:address":"Calle de San Martin, 12",
    "sg:city":"Briviesca",
    "sg:orig_category":"Panader\u00cdas, Panader\u00cdas",
    "sg:phone":"+34 947 59 02 49",
    "sg:postcode":"09240",
    "sg:province":"Burgos",
    "wof:name":"Santaolalla Garcia Mariano",
    "wof:placetype":"venue"
},
  "geometry": {"coordinates":[-3.3239889145,42.5518417358],"type":"Point"}
}