{
  "type": "Feature",
  "properties": {
    "iso:country":"ES",
    "sg:address":"Calle de Gobernador Fernandez Jimenez (del), 5",
    "sg:city":"Segovia",
    "sg:orig_category":"Loter\u00cda Y T\u00d3mbola",
    "sg:phone":"+34 921 42 63 13",
    "sg:postcode":"40001",
    "sg:province":"Segovia",
    "wof:name":"Pajon Blanco Guzman",
    "wof:placetype":"venue"
},
  "geometry": {"coordinates":[-4.1187062263,40.9458847046],"type":"Point"}
}