{
  "type": "Feature",
  "properties": {
    "iso:country":"ES",
    "sg:address":"Calle de Villa Valencia De Alcantara, 18",
    "sg:city":"Alfacar",
    "sg:orig_category":"Estancos",
    "sg:phone":"+34 958 54 32 30",
    "sg:postcode":"18170",
    "sg:province":"Granada",
    "wof:name":"Iba\u00f1ez Martin Daniel",
    "wof:placetype":"venue"
},
  "geometry": {"coordinates":[-3.5660591125,37.2369918823],"type":"Point"}
}