{
  "type": "Feature",
  "properties": {
    "iso:country":"ES",
    "sg:address":"Calle de Alfacar, S/n",
    "sg:city":"Madrid",
    "sg:orig_category":"Alimentaci\u00d3n General (al Por Menor)",
    "sg:phone":"+34 917 63 76 10",
    "sg:postcode":"28033",
    "sg:province":"Madrid",
    "wof:name":"Lozano Sobrino Maxima",
    "wof:placetype":"venue"
},
  "geometry": {"coordinates":[-3.6478557587,40.4770927429],"type":"Point"}
}