{
  "type": "Feature",
  "properties": {
    "iso:country":"ES",
    "sg:address":"Plaz Capitan Colinas, S/n",
    "sg:city":"Villafer",
    "sg:orig_category":"Centros De Educaci\u00d3n Especial",
    "sg:phone":"+34 987 77 40 50",
    "sg:postcode":"24236",
    "sg:province":"Le\u00f3n",
    "wof:name":"C.r.a. De Villaquejida",
    "wof:placetype":"venue"
},
  "geometry": {"coordinates":[-5.5683689117,42.1217651367],"type":"Point"}
}