{
  "type": "Feature",
  "properties": {
    "iso:country":"ES",
    "sg:address":"Av Pau Casals, 104",
    "sg:city":"Hospitalet Llobregat",
    "sg:orig_category":"Barnizadores",
    "sg:phone":"+34 933 38 79 62",
    "sg:postcode":"08907",
    "sg:province":"Barcelona",
    "wof:name":"Barnizados Tumar S.c.p.",
    "wof:placetype":"venue"
},
  "geometry": {"coordinates":[2.1048998833,41.3587303162],"type":"Point"}
}