{
  "type": "Feature",
  "properties": {
    "iso:country":"ES",
    "sg:address":"Calle de Instituto, 10",
    "sg:city":"Beniajan",
    "sg:orig_category":"Promotores Constructores",
    "sg:phone":"+34 968 82 13 18",
    "sg:postcode":"30570",
    "sg:province":"Murcia",
    "wof:name":"Belando Sanchez Concepcion",
    "wof:placetype":"venue"
},
  "geometry": {"coordinates":[-1.0722420216,37.9724121094],"type":"Point"}
}