{
  "type": "Feature",
  "properties": {
    "addr:full":"Calle de Antonio Maura, 24 Hinojosa Del Duque C\u00f3rdoba 14270",
    "addr:housenumber":"24",
    "addr:postcode":"14270",
    "addr:street":"Calle De Antonio Maura;Co\u0301Rdoba",
    "iso:country":"ES",
    "sg:address":"Calle de Antonio Maura, 24",
    "sg:city":"Hinojosa Del Duque",
    "sg:orig_category":"Alimentaci\u00d3n General (al Por Menor)",
    "sg:phone":"+34 957 14 00 94",
    "sg:postcode":"14270",
    "sg:province":"C\u00f3rdoba",
    "wof:name":"Ayuso Ramos Francisco",
    "wof:placetype":"venue"
},
  "geometry": {"coordinates":[-5.1486406326,38.4990501404],"type":"Point"}
}