{
  "type": "Feature",
  "properties": {
    "addr:full":"Rua Jose Maria Gonzalez Rio, 10 Burela Lugo 27880",
    "addr:housenumber":"10",
    "addr:postcode":"27880",
    "addr:street":"Rua Jose Maria Gonzalez Rio",
    "iso:country":"ES",
    "sg:address":"Rua Jose Maria Gonzalez Rio, 10",
    "sg:city":"Burela",
    "sg:orig_category":"Venta, Instalaci\u00d3n De Calefacci\u00d3n",
    "sg:phone":"+34 982 58 00 63",
    "sg:postcode":"27880",
    "sg:province":"Lugo",
    "wof:name":"Instalaciones A.trobo S.l.",
    "wof:placetype":"venue"
},
  "geometry": {"coordinates":[-7.3604969978,43.658657074],"type":"Point"}
}