{
  "type": "Feature",
  "properties": {
    "addr:full":"Carrer de Manxa, 15 Barcelona Barcelona 08032",
    "addr:housenumber":"15",
    "addr:postcode":"08032",
    "addr:street":"Carrer De Manxa",
    "iso:country":"ES",
    "sg:address":"Carrer de Manxa, 15",
    "sg:city":"Barcelona",
    "sg:orig_category":"Bisuteros (fabricaci\u00d3n, Al Por Mayor)",
    "sg:phone":"+34 933 57 95 29",
    "sg:postcode":"08032",
    "sg:province":"Barcelona",
    "wof:name":"Martinez Carmona Bonifacio",
    "wof:placetype":"venue"
},
  "geometry": {"coordinates":[2.1529569626,41.4215965271],"type":"Point"}
}