{
  "type": "Feature",
  "properties": {
    "addr:full":"Calle de Margarita Xirgu, 2 Getafe Madrid 28903",
    "addr:housenumber":"2",
    "addr:postcode":"28903",
    "addr:street":"Calle De Margarita Xirgu",
    "iso:country":"ES",
    "sg:address":"Calle de Margarita Xirgu, 2",
    "sg:city":"Getafe",
    "sg:orig_category":"Fabricaci\u00d3n De Cortinas Y Visillos",
    "sg:phone":"+34 916 83 08 11",
    "sg:postcode":"28903",
    "sg:province":"Madrid",
    "wof:name":"Aranzana Rico Severiano",
    "wof:placetype":"venue"
},
  "geometry": {"coordinates":[-3.7181246281,40.3156242371],"type":"Point"}
}