{
  "type": "Feature",
  "properties": {
    "iso:country":"ES",
    "sg:address":"Pol Ind La Mora, S/n",
    "sg:city":"La Cisterniga",
    "sg:orig_category":"Revestimiento De Suelos Industriales",
    "sg:phone":"+34 983 40 32 43",
    "sg:postcode":"47193",
    "sg:province":"Valladolid",
    "sg:website":"www.pavinca.com",
    "wof:name":"Dhl Express Iberia S.l.",
    "wof:placetype":"venue"
},
  "geometry": {"coordinates":[-4.6859240532,41.6106681824],"type":"Point"}
}