{
  "type": "Feature",
  "properties": {
    "addr:full":"Calle de Canalejas, 12 Palmas De Gran Canaria Las Palmas 35003",
    "addr:housenumber":"12",
    "addr:postcode":"35003",
    "addr:street":"Calle De Canalejas",
    "iso:country":"ES",
    "sg:address":"Calle de Canalejas, 12",
    "sg:city":"Palmas De Gran Canaria",
    "sg:orig_category":"Guarder\u00cdas",
    "sg:phone":"+34 928 43 12 75",
    "sg:postcode":"35003",
    "sg:province":"Las Palmas",
    "wof:name":"Paulina  Bermingham",
    "wof:placetype":"venue"
},
  "geometry": {"coordinates":[-15.4196720123,28.1089725494],"type":"Point"}
}