{
  "type": "Feature",
  "properties": {
    "iso:country":"ES",
    "sg:address":"Calle de Manuel Fernandez Arriola, 19",
    "sg:city":"Ejido",
    "sg:orig_category":"Alquiler De Apartamentos",
    "sg:phone":"+34 950 48 64 25",
    "sg:postcode":"04700",
    "sg:province":"Almer\u00eda",
    "wof:name":"Pesaindalo S.l.",
    "wof:placetype":"venue"
},
  "geometry": {"coordinates":[-2.8151609898,36.7722396851],"type":"Point"}
}