{
  "type": "Feature",
  "properties": {
    "addr:full":"Avda Blas Infante (de), 44 Almeria Almer\u00eda 04006",
    "addr:housenumber":"44",
    "addr:postcode":"04006",
    "addr:street":"Avda Blas Infante De",
    "iso:country":"ES",
    "sg:address":"Avda Blas Infante (de), 44",
    "sg:city":"Almeria",
    "sg:orig_category":"Farmacias",
    "sg:phone":"+34 950 22 62 57",
    "sg:postcode":"04006",
    "sg:province":"Almer\u00eda",
    "wof:name":"Cuadrado Gomez Fernanda",
    "wof:placetype":"venue"
},
  "geometry": {"coordinates":[-2.4517879486,36.8411254883],"type":"Point"}
}