{
  "type": "Feature",
  "properties": {
    "addr:full":"Avda Arquitecto Jesus Valverde, S/n Baiona Pontevedra 36300",
    "addr:housenumber":"s / n",
    "addr:postcode":"36300",
    "addr:street":"Avda Arquitecto Jesus Valverde",
    "iso:country":"ES",
    "sg:address":"Avda Arquitecto Jesus Valverde, S/n",
    "sg:city":"Baiona",
    "sg:orig_category":"Oficinas De Turismo, Asociaciones De Iniciativa",
    "sg:phone":"+34 986 68 70 67",
    "sg:postcode":"36300",
    "sg:province":"Pontevedra",
    "wof:name":"Concello De Baiona",
    "wof:placetype":"venue"
},
  "geometry": {"coordinates":[-97.78224945069999,45.7040786743],"type":"Point"}
}