{
  "type": "Feature",
  "properties": {
    "addr:full":"Calle de Ipar, 22 Ondarroa Vizcaya 48700",
    "addr:housenumber":"22",
    "addr:postcode":"48700",
    "addr:street":"Calle De Ipar",
    "iso:country":"ES",
    "sg:address":"Calle de Ipar, 22",
    "sg:city":"Ondarroa",
    "sg:classifiers":[
        {
            "category":"Taxi",
            "type":"Transportation"
        }
    ],
    "sg:phone":"+34 946 13 41 64",
    "sg:postcode":"48700",
    "sg:province":"Vizcaya",
    "wof:name":"Eizaguirre Aranguena Jose Maria",
    "wof:placetype":"venue"
},
  "geometry": {"coordinates":[-2.4218170643,43.3210525513],"type":"Point"}
}