{
  "type": "Feature",
  "properties": {
    "addr:full":"Calle de Don Pio Coronado, 74 Palmas De Gran Canaria Las Palmas 35012",
    "addr:housenumber":"74",
    "addr:postcode":"35012",
    "addr:street":"Calle De Don Pio Coronado",
    "iso:country":"ES",
    "sg:address":"Calle de Don Pio Coronado, 74",
    "sg:city":"Palmas De Gran Canaria",
    "sg:orig_category":"Peluqueros: De Se\u00d1oras",
    "sg:phone":"+34 928 25 31 86",
    "sg:postcode":"35012",
    "sg:province":"Las Palmas",
    "wof:name":"Vega Rodriguez America",
    "wof:placetype":"venue"
},
  "geometry": {"coordinates":[-15.4339952469,28.109336853],"type":"Point"}
}