{
  "type": "Feature",
  "properties": {
    "iso:country":"ES",
    "sg:address":"Carrer de L'avenir, 35",
    "sg:city":"Barcelona",
    "sg:orig_category":"Arquitectos",
    "sg:phone":"+34 932 00 02 45",
    "sg:postcode":"08021",
    "sg:province":"Barcelona",
    "wof:name":"Roura Goicoechea Ricard",
    "wof:placetype":"venue"
},
  "geometry": {"coordinates":[2.1469709873,41.395904541],"type":"Point"}
}