{
  "type": "Feature",
  "properties": {
    "addr:full":"C/ Maximilia Thous, 101 Elche Alicante 03204",
    "addr:housenumber":"101",
    "addr:postcode":"03204",
    "addr:street":"C / Maximilia Thous",
    "iso:country":"ES",
    "sg:address":"C/ Maximilia Thous, 101",
    "sg:city":"Elche",
    "sg:classifiers":[
        {
            "category":"Autos & Motor Vehicles",
            "subcategory":"Automobile Sales",
            "type":"Retail Goods"
        }
    ],
    "sg:phone":"+34 966 64 15 34",
    "sg:postcode":"03204",
    "sg:province":"Alicante",
    "wof:name":"Elenrober Elche S.l.",
    "wof:placetype":"venue"
},
  "geometry": {"coordinates":[-0.7058759928,38.2564697266],"type":"Point"}
}