{
  "type": "Feature",
  "properties": {
    "addr:full":"Carrer de Enric Granados, 7 Barcelona Barcelona 08007",
    "addr:housenumber":"7",
    "addr:postcode":"08007",
    "addr:street":"Carrer De Enric Granados",
    "iso:country":"ES",
    "sg:address":"Carrer de Enric Granados, 7",
    "sg:city":"Barcelona",
    "sg:orig_category":"Confecci\u00d3n (fabricaci\u00d3n, Al Por Mayor)",
    "sg:phone":"+34 933 23 21 58",
    "sg:postcode":"08007",
    "sg:province":"Barcelona",
    "wof:name":"Adana S.a.",
    "wof:placetype":"venue"
},
  "geometry": {"coordinates":[2.1625328064,41.3876686096],"type":"Point"}
}