{
  "type": "Feature",
  "properties": {
    "iso:country":"ES",
    "sg:address":"Carrer de Mulleras, S/n",
    "sg:city":"Olot",
    "sg:orig_category":"Frutas, Legumbres Frescas Y Tempranas (al Por Menor)",
    "sg:phone":"+34 972 26 47 44",
    "sg:postcode":"17800",
    "sg:province":"Girona",
    "wof:name":"Picart Rius Esteban",
    "wof:placetype":"venue"
},
  "geometry": {"coordinates":[2.4888100624,42.1808586121],"type":"Point"}
}