{
  "type": "Feature",
  "properties": {
    "iso:country":"ES",
    "sg:address":"Plaz Aljarafe (el), 12",
    "sg:city":"Sevilla",
    "sg:orig_category":"Ropa Y Accesorios",
    "sg:phone":"+34 954 64 24 24",
    "sg:postcode":"41005",
    "sg:province":"Sevilla",
    "wof:name":"Confecciones Roney S. L.",
    "wof:placetype":"venue"
},
  "geometry": {"coordinates":[-5.9736380577,37.3757972717],"type":"Point"}
}