{
  "type": "Feature",
  "properties": {
    "iso:country":"ES",
    "sg:address":"Av Novelda, 51",
    "sg:city":"Elche",
    "sg:orig_category":"Caf\u00c9s, Bares, Cervecer\u00cdas",
    "sg:phone":"+34 965 46 10 72",
    "sg:postcode":"03205",
    "sg:province":"Alicante",
    "wof:name":"Rada Business S.l.",
    "wof:placetype":"venue"
},
  "geometry": {"coordinates":[-0.7107719779,38.2723426819],"type":"Point"}
}