{
  "type": "Feature",
  "properties": {
    "iso:country":"ES",
    "sg:address":"Calle de Pintor Francisco Carretero, 20",
    "sg:city":"Tomelloso",
    "sg:orig_category":"Agencias Y Agentes Comerciales, Representantes",
    "sg:phone":"+34 926 50 44 62",
    "sg:postcode":"13700",
    "sg:province":"Ciudad Real",
    "wof:name":"Diaz Sanchez Jose Miguel",
    "wof:placetype":"venue"
},
  "geometry": {"coordinates":[-3.0186829567,39.1560058594],"type":"Point"}
}