{
  "type": "Feature",
  "properties": {
    "addr:full":"Carr Enginyer Balaguer, (de L'), 124 Carlet Valencia 46240",
    "addr:housenumber":"124",
    "addr:postcode":"46240",
    "addr:street":"Carr Enginyer;De L '",
    "iso:country":"ES",
    "sg:address":"Carr Enginyer Balaguer, (de L'), 124",
    "sg:city":"Carlet",
    "sg:orig_category":"Laboratorios Y Cl\u00cdnicas Veterinarias",
    "sg:phone":"+34 962 99 45 00",
    "sg:postcode":"46240",
    "sg:province":"Valencia",
    "wof:name":"A\u00f1o Casp Gracia Maria",
    "wof:placetype":"venue"
},
  "geometry": {"coordinates":[-0.554148972,39.2258453369],"type":"Point"}
}