{
  "type": "Feature",
  "properties": {
    "addr:full":"Calle de San Fructuoso, 1 Ponferrada Le\u00f3n 24400",
    "addr:housenumber":"1",
    "addr:postcode":"24400",
    "addr:street":"Calle De San Fructuoso",
    "iso:country":"ES",
    "sg:address":"Calle de San Fructuoso, 1",
    "sg:city":"Ponferrada",
    "sg:orig_category":"Inmobiliaria (agencias)",
    "sg:phone":"+34 987 42 46 68",
    "sg:postcode":"24400",
    "sg:province":"Le\u00f3n",
    "wof:name":"Frangollo S.l.",
    "wof:placetype":"venue"
},
  "geometry": {"coordinates":[-6.584900856,42.5487823486],"type":"Point"}
}