{
  "type": "Feature",
  "properties": {
    "addr:full":"Carrer de Mestres Casals I Martorell, 24 Barcelona Barcelona 08003",
    "addr:housenumber":"24",
    "addr:postcode":"08003",
    "addr:street":"Carrer De Mestres Casals I Martorell",
    "iso:country":"ES",
    "sg:address":"Carrer de Mestres Casals I Martorell, 24",
    "sg:city":"Barcelona",
    "sg:orig_category":"Molduras, Junquillos, Listones Y Molduras Perforadas",
    "sg:phone":"+34 933 19 10 18",
    "sg:postcode":"08003",
    "sg:province":"Barcelona",
    "wof:name":"Asorey Camino Fernando",
    "wof:placetype":"venue"
},
  "geometry": {"coordinates":[2.1779761314,41.3875732422],"type":"Point"}
}