{
  "type": "Feature",
  "properties": {
    "addr:full":"Av Gil Atrocillo, S/n Vinaros Castell\u00f3n 12500",
    "addr:housenumber":"s / n",
    "addr:postcode":"12500",
    "addr:street":"Av Gil Atrocillo",
    "iso:country":"ES",
    "sg:address":"Av Gil Atrocillo, S/n",
    "sg:city":"Vinaros",
    "sg:orig_category":"Hospitales",
    "sg:phone":"+34 964 40 15 85",
    "sg:postcode":"12500",
    "sg:province":"Castell\u00f3n",
    "wof:name":"Tanaki Espa\u00d1a S.a.",
    "wof:placetype":"venue"
},
  "geometry": {"coordinates":[0.4562149942,40.4696578979],"type":"Point"}
}