{
  "type": "Feature",
  "properties": {
    "addr:full":"Estd Ouzande (a), 11 Estrada Pontevedra 36680",
    "addr:housenumber":"11",
    "addr:postcode":"36680",
    "addr:street":"Estrada Pontevedra",
    "iso:country":"ES",
    "sg:address":"Estd Ouzande (a), 11",
    "sg:city":"Estrada",
    "sg:orig_category":"Material Y Herramientas Agr\u00cdcolas",
    "sg:phone":"+34 986 57 09 40",
    "sg:postcode":"36680",
    "sg:province":"Pontevedra",
    "wof:name":"Cabanas Magari\u00f1os Jose",
    "wof:placetype":"venue"
},
  "geometry": {"coordinates":[-8.4910736084,42.6887664795],"type":"Point"}
}