{
  "type": "Feature",
  "properties": {
    "addr:full":"Calle de Venta De Antepardo, S/n Caicedo De Yuso \u00c1lava 01213",
    "addr:housenumber":"s",
    "addr:postcode":"01213",
    "addr:street":"Calle De Venta De Antepardo;/ N Caicedo De Yuso A\u0301Lava",
    "iso:country":"ES",
    "sg:address":"Calle de Venta De Antepardo, S/n",
    "sg:city":"Caicedo De Yuso",
    "sg:orig_category":"Material Y Suministros Para Dentistas, Cirujanos",
    "sg:phone":"+34 945 33 21 00",
    "sg:postcode":"01213",
    "sg:province":"\u00c1lava",
    "sg:website":"www.trlentz.es",
    "wof:name":"Depositos Tubos Reunidos Lentz Tr-lentz S.a.",
    "wof:placetype":"venue"
},
  "geometry": {"coordinates":[-2.9184379578,42.7114753723],"type":"Point"}
}