{
  "type": "Feature",
  "properties": {
    "addr:full":"Calle de Miguel De Cervantes, 8 Palmas De Gran Canaria Las Palmas 35002",
    "addr:housenumber":"8",
    "addr:postcode":"35002",
    "addr:street":"Calle De Miguel De Cervantes",
    "iso:country":"ES",
    "sg:address":"Calle de Miguel De Cervantes, 8",
    "sg:city":"Palmas De Gran Canaria",
    "sg:orig_category":"Peluquer\u00cdas, Peluquer\u00cda Mixta",
    "sg:phone":"+34 928 36 22 57",
    "sg:postcode":"35002",
    "sg:province":"Las Palmas",
    "wof:name":"Rivero Naranjo Socorro",
    "wof:placetype":"venue"
},
  "geometry": {"coordinates":[-15.4144477844,28.1044654846],"type":"Point"}
}