{
  "type": "Feature",
  "properties": {
    "iso:country":"ES",
    "sg:address":"Pol Ind Munic Vial C, 13",
    "sg:city":"Tudela",
    "sg:orig_category":"Asociaciones Humanitarias, De Cooperaci\u00d3n, De Acci\u00d3n Social",
    "sg:phone":"+34 948 41 01 00",
    "sg:postcode":"31500",
    "sg:province":"Navarra",
    "wof:name":"Asociacion De Disminuidos Fisicos De La Ribera De Navarra",
    "wof:placetype":"venue"
},
  "geometry": {"coordinates":[-1.6235691309,42.0642585754],"type":"Point"}
}