{
  "type": "Feature",
  "properties": {
    "addr:full":"Montortal, 132 Alcudia Valencia 46250",
    "addr:housenumber":"132",
    "addr:postcode":"46250",
    "addr:street":"Montortal",
    "iso:country":"ES",
    "sg:address":"Montortal, 132",
    "sg:city":"Alcudia",
    "sg:orig_category":"Barnizadores",
    "sg:phone":"+34 962 99 67 03",
    "sg:postcode":"46250",
    "sg:province":"Valencia",
    "wof:name":"Lacados Lalcudia S.l",
    "wof:placetype":"venue"
},
  "geometry": {"coordinates":[-0.5177590251,39.171257019],"type":"Point"}
}