{
  "type": "Feature",
  "properties": {
    "addr:full":"Carrer de Bailen, 39 Barcelona Barcelona 08010",
    "addr:housenumber":"39",
    "addr:postcode":"08010",
    "addr:street":"Carrer De Bailen",
    "iso:country":"ES",
    "sg:address":"Carrer de Bailen, 39",
    "sg:city":"Barcelona",
    "sg:orig_category":"Agencias Y Agentes Comerciales, Representantes",
    "sg:phone":"+34 932 31 36 46",
    "sg:postcode":"08010",
    "sg:province":"Barcelona",
    "sg:website":"www.canatallops1897.com",
    "wof:name":"Cantallops 1897 S.l.",
    "wof:placetype":"venue"
},
  "geometry": {"coordinates":[2.1749010086,41.3934860229],"type":"Point"}
}