{
  "type": "Feature",
  "properties": {
    "addr:full":"Plza. Tartessos, 3 Maracena Granada 18200",
    "addr:housenumber":"3",
    "addr:postcode":"18200",
    "addr:street":"Plza. Tartessos",
    "iso:country":"ES",
    "sg:address":"Plza. Tartessos, 3",
    "sg:city":"Maracena",
    "sg:classifiers":[
        {
            "category":"Personal",
            "subcategory":"Barber",
            "type":"Services"
        }
    ],
    "sg:phone":"+34 958 41 12 50",
    "sg:postcode":"18200",
    "sg:province":"Granada",
    "sg:tags":[
        "caballeros",
        "de",
        "peluqueros"
    ],
    "wof:name":"Bertos Espinola Simon",
    "wof:placetype":"venue"
},
  "geometry": {"coordinates":[-3.6371719837,37.2051467896],"type":"Point"}
}