{
  "type": "Feature",
  "properties": {
    "iso:country":"ES",
    "sg:address":"Calle de Bilbao La Vieja, 6",
    "sg:city":"Bilbao",
    "sg:orig_category":"Plomeros",
    "sg:phone":"+34 944 15 73 96",
    "sg:postcode":"48003",
    "sg:province":"Vizcaya",
    "wof:name":"Fer-san Instalaciones Sanitarias S.l.",
    "wof:placetype":"venue"
},
  "geometry": {"coordinates":[-2.9240365028,43.2544593811],"type":"Point"}
}