{
  "type": "Feature",
  "properties": {
    "addr:full":"Calle de Doctor Modesto Cogollos, 4 Valencia Valencia 46021",
    "addr:housenumber":"4",
    "addr:postcode":"46021",
    "addr:street":"Calle De Doctor Modesto Cogollos",
    "iso:country":"ES",
    "sg:address":"Calle de Doctor Modesto Cogollos, 4",
    "sg:city":"Valencia",
    "sg:orig_category":"Agencias Y Agentes Comerciales, Representantes",
    "sg:phone":"+34 963 93 19 20",
    "sg:postcode":"46021",
    "sg:province":"Valencia",
    "wof:name":"Villanueva Pla Pascual",
    "wof:placetype":"venue"
},
  "geometry": {"coordinates":[-0.3517929912,39.4739875793],"type":"Point"}
}