{
  "type": "Feature",
  "properties": {
    "addr:full":"Calle de Parany, 3 Vall D'uixo Castell\u00f3n 12600",
    "addr:housenumber":"3",
    "addr:postcode":"12600",
    "addr:street":"Calle De Parany",
    "iso:country":"ES",
    "sg:address":"Calle de Parany, 3",
    "sg:city":"Vall D'uixo",
    "sg:orig_category":"Mec\u00c1nico Del Autom\u00d3vil",
    "sg:phone":"+34 964 69 11 37",
    "sg:postcode":"12600",
    "sg:province":"Castell\u00f3n",
    "wof:name":"Turbo-gaspar S.l.",
    "wof:placetype":"venue"
},
  "geometry": {"coordinates":[-0.0355090015,39.9793128967],"type":"Point"}
}