{
  "type": "Feature",
  "properties": {
    "iso:country":"ES",
    "sg:address":"Av Costa Brava, 23",
    "sg:city":"Platja D'aro",
    "sg:orig_category":"Promotores Constructores",
    "sg:phone":"+34 972 82 90 11",
    "sg:postcode":"17250",
    "sg:province":"Girona",
    "wof:name":"Firina S.l.",
    "wof:placetype":"venue"
},
  "geometry": {"coordinates":[2.8088560104,41.9703140259],"type":"Point"}
}