{
  "type": "Feature",
  "properties": {
    "iso:country":"ES",
    "sg:address":"Calle de Progreso, 41",
    "sg:city":"Puerto",
    "sg:orig_category":"Molduras, Junquillos, Listones Y Molduras Perforadas",
    "sg:phone":"+34 962 67 97 04",
    "sg:postcode":"46520",
    "sg:province":"Valencia",
    "wof:name":"Casta\u00f1eda Lopez Anselmo",
    "wof:placetype":"venue"
},
  "geometry": {"coordinates":[-0.2173299938,39.6608734131],"type":"Point"}
}