{
  "type": "Feature",
  "properties": {
    "addr:full":"Calle de Avila, 21 San Juan De Aznalfarache Sevilla 41920",
    "addr:housenumber":"21",
    "addr:postcode":"41920",
    "addr:street":"Calle De Avila",
    "iso:country":"ES",
    "sg:address":"Calle de Avila, 21",
    "sg:city":"San Juan De Aznalfarache",
    "sg:orig_category":"Asesor\u00cda Fiscal Y Jur\u00cddica",
    "sg:phone":"+34 954 17 17 25",
    "sg:postcode":"41920",
    "sg:province":"Sevilla",
    "wof:name":"Cesar Caceres S.l.",
    "wof:placetype":"venue"
},
  "geometry": {"coordinates":[-6.0360784531,37.3554344177],"type":"Point"}
}