{
  "type": "Feature",
  "properties": {
    "iso:country":"ES",
    "sg:address":"Calle de La Vi\u00d1a, 35",
    "sg:city":"Almonte",
    "sg:orig_category":"Reposter\u00cdas",
    "sg:phone":"+34 959 45 14 01",
    "sg:postcode":"21730",
    "sg:province":"Huelva",
    "wof:name":"Jimenez Faraco Pilar",
    "wof:placetype":"venue"
},
  "geometry": {"coordinates":[-6.5155620575,37.2587623596],"type":"Point"}
}