{
  "type": "Feature",
  "properties": {
    "iso:country":"ES",
    "sg:address":"Rua Carboeiros (dos), S/n",
    "sg:city":"Carballi\u00f1o",
    "sg:orig_category":"Mec\u00c1nico Del Autom\u00d3vil",
    "sg:phone":"+34 988 27 19 49",
    "sg:postcode":"32500",
    "sg:province":"Ourense",
    "wof:name":"Gayoso Fernandez Francisco",
    "wof:placetype":"venue"
},
  "geometry": {"coordinates":[-8.079829216,42.4342918396],"type":"Point"}
}