{
  "type": "Feature",
  "properties": {
    "addr:full":"Rua Union (de La), 15 Ourense Ourense 32005",
    "addr:housenumber":"15",
    "addr:postcode":"32005",
    "addr:street":"Rua Union De La",
    "iso:country":"ES",
    "sg:address":"Rua Union (de La), 15",
    "sg:city":"Ourense",
    "sg:orig_category":"Molduras, Junquillos, Listones Y Molduras Perforadas",
    "sg:phone":"+34 988 24 72 72",
    "sg:postcode":"32005",
    "sg:province":"Ourense",
    "wof:name":"Vazquez Perez Indalecio",
    "wof:placetype":"venue"
},
  "geometry": {"coordinates":[-7.8622970581,42.3364906311],"type":"Point"}
}