{
  "type": "Feature",
  "properties": {
    "addr:full":"G.v. Ramon Y Cajal, 27 Valencia Valencia 46007",
    "addr:housenumber":"27",
    "addr:postcode":"46007",
    "addr:street":"Ramon Y Cajal",
    "iso:country":"ES",
    "sg:address":"G.v. Ramon Y Cajal, 27",
    "sg:city":"Valencia",
    "sg:classifiers":[
        {
            "category":"Banks & Credit Unions",
            "subcategory":"Bureau De Change",
            "type":"Services"
        }
    ],
    "sg:phone":"+34 963 10 72 39",
    "sg:postcode":"46007",
    "sg:province":"Valencia",
    "sg:tags":[
        "organismos",
        "control"
    ],
    "wof:name":"Aja Registrars Espa\u00d1a S.l.",
    "wof:placetype":"venue"
},
  "geometry": {"coordinates":[-0.3821390867,39.4660873413],"type":"Point"}
}