{
  "type": "Feature",
  "properties": {
    "iso:country":"ES",
    "sg:address":"Tomas Carranza, 1",
    "sg:city":"Villasequilla",
    "sg:orig_category":"Asesor\u00cda Sobre Comunicaci\u00d3n De Empresas",
    "sg:phone":"+34 925 31 05 53",
    "sg:postcode":"45740",
    "sg:province":"Toledo",
    "wof:name":"Gestion Toledo S.l.",
    "wof:placetype":"venue"
},
  "geometry": {"coordinates":[-3.7290990353,39.8743133545],"type":"Point"}
}