{
  "type": "Feature",
  "properties": {
    "iso:country":"ES",
    "sg:address":"Cra. Sta. Coloma, 35",
    "sg:city":"Olot",
    "sg:orig_category":"Grafistas",
    "sg:phone":"+34 972 26 57 58",
    "sg:postcode":"17800",
    "sg:province":"Girona",
    "wof:name":"Gelis Dissenyadors S.l.",
    "wof:placetype":"venue"
},
  "geometry": {"coordinates":[2.4893848896,42.1809463501],"type":"Point"}
}