{
  "type": "Feature",
  "properties": {
    "iso:country":"ES",
    "sg:address":"Calle de Tenderina, 6",
    "sg:city":"Oviedo",
    "sg:orig_category":"Electrodom\u00c9sticos (fabricaci\u00d3n, Al Por Mayor)",
    "sg:phone":"+34 985 22 87 00",
    "sg:postcode":"33010",
    "sg:province":"Asturias",
    "wof:name":"Soto Proyectos E Inversiones S.l.",
    "wof:placetype":"venue"
},
  "geometry": {"coordinates":[-5.8386569023,43.3640594482],"type":"Point"}
}