{
  "type": "Feature",
  "properties": {
    "addr:full":"Carrer de Sepulveda, 46 Barcelona Barcelona 08015",
    "addr:housenumber":"46",
    "addr:postcode":"08015",
    "addr:street":"Carrer De Sepulveda",
    "iso:country":"ES",
    "sg:address":"Carrer de Sepulveda, 46",
    "sg:city":"Barcelona",
    "sg:orig_category":"Negocio De Materiales De Construcci\u00d3n",
    "sg:phone":"+34 934 26 27 31",
    "sg:postcode":"08015",
    "sg:province":"Barcelona",
    "wof:name":"Pallares Camarasa Jordi",
    "wof:placetype":"venue"
},
  "geometry": {"coordinates":[2.1546390057,41.3771018982],"type":"Point"}
}