{
  "type": "Feature",
  "properties": {
    "iso:country":"ES",
    "sg:address":"Calle de Lugo, 51",
    "sg:city":"Arzua",
    "sg:orig_category":"Ingeniero",
    "sg:phone":"+34 981 50 10 86",
    "sg:postcode":"15810",
    "sg:province":"La Coru\u00f1a",
    "wof:name":"Lopez Louzao Jose Maria",
    "wof:placetype":"venue"
},
  "geometry": {"coordinates":[-8.1590147018,42.9278831482],"type":"Point"}
}