{
  "type": "Feature",
  "properties": {
    "addr:full":"Calle de Almirante Martin De Vallecilla, 2 Portugalete Vizcaya 48920",
    "addr:housenumber":"2",
    "addr:postcode":"48920",
    "addr:street":"Calle De Almirante Martin De Vallecilla",
    "iso:country":"ES",
    "sg:address":"Calle de Almirante Martin De Vallecilla, 2",
    "sg:city":"Portugalete",
    "sg:orig_category":"Molduras, Junquillos, Listones Y Molduras Perforadas",
    "sg:phone":"+34 944 62 98 90",
    "sg:postcode":"48920",
    "sg:province":"Vizcaya",
    "wof:name":"Anbuhl Diaz Jorge",
    "wof:placetype":"venue"
},
  "geometry": {"coordinates":[-3.0220050812,43.3180465698],"type":"Point"}
}