{
  "type": "Feature",
  "properties": {
    "iso:country":"ES",
    "sg:address":"Carretera De Campillos, Km. 0097,0",
    "sg:city":"Gaucin",
    "sg:orig_category":"Distribuci\u00d3n De Petr\u00d3leo Y Derivados",
    "sg:phone":"+34 952 15 13 24",
    "sg:postcode":"29480",
    "sg:province":"M\u00e1laga",
    "wof:name":"Moncada Oil 2003 S.l.",
    "wof:placetype":"venue"
},
  "geometry": {"coordinates":[-5.3247990608,36.5199356079],"type":"Point"}
}