{
  "type": "Feature",
  "properties": {
    "addr:full":"Calle de Mariano Vela, 38 Madrid Madrid 28026",
    "addr:housenumber":"38",
    "addr:postcode":"madrid;28026",
    "addr:street":"Calle De Mariano Vela",
    "iso:country":"ES",
    "sg:address":"Calle de Mariano Vela, 38",
    "sg:city":"Madrid",
    "sg:orig_category":"Aparatos, Sistemas De Tele",
    "sg:phone":"+34 915 69 56 57",
    "sg:postcode":"28026",
    "sg:province":"Madrid",
    "wof:name":"Velez Ganuza Antonio",
    "wof:placetype":"venue"
},
  "geometry": {"coordinates":[-3.7106420994,40.3842773438],"type":"Point"}
}