{
  "type": "Feature",
  "properties": {
    "iso:country":"ES",
    "sg:address":"Calle de Perales (de Los), 26",
    "sg:city":"San Sebastian De Los Reyes",
    "sg:orig_category":"Cerrajer\u00cda, Ferrallista",
    "sg:phone":"+34 916 53 56 84",
    "sg:postcode":"28700",
    "sg:province":"Madrid",
    "wof:name":"Cerrajeria Industrial Y Construccion S. A.",
    "wof:placetype":"venue"
},
  "geometry": {"coordinates":[-3.6183109283,40.54637146],"type":"Point"}
}