{
  "type": "Feature",
  "properties": {
    "addr:full":"Aldea De Arriba, S/n Calvos Ourense 32849",
    "addr:housenumber":"s / n",
    "addr:postcode":"32849",
    "addr:street":"Aldea;Arriba",
    "iso:country":"ES",
    "sg:address":"Aldea De Arriba, S/n",
    "sg:city":"Calvos",
    "sg:orig_category":"Delegados, Agentes De Tr\u00c1nsito, Auxiliares De Transporte Internacional",
    "sg:phone":"+34 988 30 20 73",
    "sg:postcode":"32849",
    "sg:province":"Ourense",
    "wof:name":"Lopez Rodriguez Benito",
    "wof:placetype":"venue"
},
  "geometry": {"coordinates":[-7.9543991089,41.9970817566],"type":"Point"}
}