{
  "type": "Feature",
  "properties": {
    "iso:country":"ES",
    "sg:address":"Doctor Labayen, 14",
    "sg:city":"Iru\u00f1a",
    "sg:orig_category":"Mec\u00c1nico Del Autom\u00d3vil",
    "sg:phone":"+34 948 27 75 89",
    "sg:postcode":"31012",
    "sg:province":"Navarra",
    "wof:name":"Uriz Sala Jesus",
    "wof:placetype":"venue"
},
  "geometry": {"coordinates":[-1.6672420502,42.8197097778],"type":"Point"}
}