{
  "type": "Feature",
  "properties": {
    "addr:full":"Calle de Paraguay, 3 Moguer Huelva 21800",
    "addr:housenumber":"3",
    "addr:postcode":"21800",
    "addr:street":"Calle De Paraguay",
    "iso:country":"ES",
    "sg:address":"Calle de Paraguay, 3",
    "sg:city":"Moguer",
    "sg:orig_category":"Ropa Para Caballeros (al Por Menor)",
    "sg:phone":"+34 959 37 01 88",
    "sg:postcode":"21800",
    "sg:province":"Huelva",
    "wof:name":"Conde Rasco Juan Antonio",
    "wof:placetype":"venue"
},
  "geometry": {"coordinates":[-6.8346748352,37.2787742615],"type":"Point"}
}