{
  "type": "Feature",
  "properties": {
    "iso:country":"ES",
    "sg:address":"Calle de Alberto Gomez Arroyo, 32",
    "sg:city":"Villamuriel De Cerrato",
    "sg:orig_category":"Carnicer\u00cdas, Carnicer\u00cdas",
    "sg:phone":"+34 979 77 66 99",
    "sg:postcode":"34190",
    "sg:province":"Palencia",
    "wof:name":"Matia Meneses Agustin",
    "wof:placetype":"venue"
},
  "geometry": {"coordinates":[-4.515566349,41.9496765137],"type":"Point"}
}