{
  "type": "Feature",
  "properties": {
    "iso:country":"ES",
    "sg:address":"Plaz Gascones, 2",
    "sg:city":"Salamanca",
    "sg:orig_category":"Ingeniero",
    "sg:phone":"+34 923 26 73 01",
    "sg:postcode":"37002",
    "sg:province":"Salamanca",
    "wof:name":"Hernandez Zaballos Jose",
    "wof:placetype":"venue"
},
  "geometry": {"coordinates":[-5.6692008972,40.9650535583],"type":"Point"}
}