{
  "type": "Feature",
  "properties": {
    "addr:full":"Carr Major, 124 Alcarras Lleida 25180",
    "addr:housenumber":"124",
    "addr:postcode":"25180",
    "addr:street":"Carr Major",
    "iso:country":"ES",
    "sg:address":"Carr Major, 124",
    "sg:city":"Alcarras",
    "sg:orig_category":"Cajas Para Embalar",
    "sg:phone":"+34 973 79 01 52",
    "sg:postcode":"25180",
    "sg:province":"Lleida",
    "wof:name":"Caja Rural Aragonesa Y De Los Pirineos",
    "wof:placetype":"venue"
},
  "geometry": {"coordinates":[0.5248169899,41.5631752014],"type":"Point"}
}