{
  "type": "Feature",
  "properties": {
    "iso:country":"ES",
    "sg:address":"Av Diagonal, 287",
    "sg:city":"Barcelona",
    "sg:orig_category":"M\u00c9dicos: Pediatr\u00cda. Enfermedades De Los Ni\u00d1os",
    "sg:phone":"+34 932 07 04 98",
    "sg:postcode":"08013",
    "sg:province":"Barcelona",
    "wof:name":"Mauri Aledo Jorge",
    "wof:placetype":"venue"
},
  "geometry": {"coordinates":[2.1750519276,41.4002532959],"type":"Point"}
}