{
  "type": "Feature",
  "properties": {
    "addr:full":"Avda Independencia, 24 Zaragoza Zaragoza 50004",
    "addr:housenumber":"24",
    "addr:postcode":"50004",
    "addr:street":"Avda Independencia",
    "iso:country":"ES",
    "sg:address":"Avda Independencia, 24",
    "sg:city":"Zaragoza",
    "sg:orig_category":"Agencias De Trabajo Temporal",
    "sg:phone":"+34 976 22 44 88",
    "sg:postcode":"50004",
    "sg:province":"Zaragoza",
    "wof:name":"Zarbeit S.l.u.",
    "wof:placetype":"venue"
},
  "geometry": {"coordinates":[-0.8811250925,41.6517829895],"type":"Point"}
}