{
  "type": "Feature",
  "properties": {
    "addr:full":"Calle de Tudela, 2 Azagra Navarra 31560",
    "addr:housenumber":"2",
    "addr:postcode":"31560",
    "addr:street":"Calle De Tudela",
    "iso:country":"ES",
    "sg:address":"Calle de Tudela, 2",
    "sg:city":"Azagra",
    "sg:orig_category":"Panader\u00cdas, Panader\u00cdas",
    "sg:phone":"+34 948 69 21 72",
    "sg:postcode":"31560",
    "sg:province":"Navarra",
    "wof:name":"Ega Pan S. A.",
    "wof:placetype":"venue"
},
  "geometry": {"coordinates":[-1.8956049681,42.3067131042],"type":"Point"}
}