{
  "type": "Feature",
  "properties": {
    "addr:full":"Carrer de Frederic Soler, 98 Prat Llobregat Barcelona 08820",
    "addr:housenumber":"98",
    "addr:postcode":"08820",
    "addr:street":"Carrer De Frederic Soler;Llobregat",
    "iso:country":"ES",
    "sg:address":"Carrer de Frederic Soler, 98",
    "sg:city":"Prat Llobregat",
    "sg:orig_category":"Mercer\u00cda, Lencer\u00cda (al Por Menor)",
    "sg:phone":"+34 934 78 33 27",
    "sg:postcode":"08820",
    "sg:province":"Barcelona",
    "wof:name":"Martinez Martinez Maria",
    "wof:placetype":"venue"
},
  "geometry": {"coordinates":[2.0976419449,41.3244514465],"type":"Point"}
}