{
  "type": "Feature",
  "properties": {
    "iso:country":"ES",
    "sg:address":"Calle de Atxuri, 25",
    "sg:city":"Bilbao",
    "sg:orig_category":"Peluqueros: De Se\u00d1oras",
    "sg:phone":"+34 944 33 20 92",
    "sg:postcode":"48006",
    "sg:province":"Vizcaya",
    "wof:name":"Laiseca Rodriguez Elvira",
    "wof:placetype":"venue"
},
  "geometry": {"coordinates":[-2.9216947556,43.2528762817],"type":"Point"}
}