{
  "type": "Feature",
  "properties": {
    "addr:full":"Calle de Francisco Quero, 19 Porcuna Ja\u00e9n 23790",
    "addr:housenumber":"19",
    "addr:postcode":"23790",
    "addr:street":"Calle De Francisco Quero",
    "iso:country":"ES",
    "sg:address":"Calle de Francisco Quero, 19",
    "sg:city":"Porcuna",
    "sg:orig_category":"Autob\u00das (explotaci\u00d3n Y Servicios De)",
    "sg:phone":"+34 953 54 42 84",
    "sg:postcode":"23790",
    "sg:province":"Ja\u00e9n",
    "wof:name":"Millan Fernandez Benito",
    "wof:placetype":"venue"
},
  "geometry": {"coordinates":[-4.1836228371,37.8713035583],"type":"Point"}
}