{
  "type": "Feature",
  "properties": {
    "addr:full":"Plaz Anzaran, 2 Irun Guip\u00f9zcoa 20301",
    "addr:housenumber":"2",
    "addr:postcode":"20301",
    "addr:street":"Plaz Anzaran;Guipu\u0300Zcoa",
    "iso:country":"ES",
    "sg:address":"Plaz Anzaran, 2",
    "sg:city":"Irun",
    "sg:orig_category":"Delegados, Agentes De Tr\u00c1nsito, Auxiliares De Transporte Internacional",
    "sg:phone":"+34 943 61 90 64",
    "sg:postcode":"20301",
    "sg:province":"Guip\u00f9zcoa",
    "wof:name":"Guretrans S.l.",
    "wof:placetype":"venue"
},
  "geometry": {"coordinates":[-1.7983510494,43.3426856995],"type":"Point"}
}