{
  "type": "Feature",
  "properties": {
    "iso:country":"ES",
    "sg:address":"Calle de Extramuros, S/n",
    "sg:city":"Belinchon",
    "sg:orig_category":"Farmacias",
    "sg:phone":"+34 969 32 41 22",
    "sg:postcode":"16471",
    "sg:province":"Cuenca",
    "wof:name":"Cuellar Garcia Enrique",
    "wof:placetype":"venue"
},
  "geometry": {"coordinates":[-3.0578160286,40.0484924316],"type":"Point"}
}