{
  "type": "Feature",
  "properties": {
    "addr:full":"Avda Guadiana, 1 Badajoz Badajoz 06011",
    "addr:housenumber":"1",
    "addr:postcode":"06011",
    "addr:street":"Avda Guadiana",
    "iso:country":"ES",
    "sg:address":"Avda Guadiana, 1",
    "sg:city":"Badajoz",
    "sg:orig_category":"Farmacias",
    "sg:phone":"+34 924 23 36 07",
    "sg:postcode":"06011",
    "sg:province":"Badajoz",
    "wof:name":"Rodrigo Cobos Maria Del Pilar",
    "wof:placetype":"venue"
},
  "geometry": {"coordinates":[-6.9753270149,38.8926925659],"type":"Point"}
}