{
  "type": "Feature",
  "properties": {
    "addr:full":"Pl Alls (dels), 9 Valls Tarragona 43800",
    "addr:housenumber":"9",
    "addr:postcode":"43800",
    "addr:street":"Pl Alls Dels",
    "iso:country":"ES",
    "sg:address":"Pl Alls (dels), 9",
    "sg:city":"Valls",
    "sg:orig_category":"Ropa Para Se\u00d1oras (al Por Menor)",
    "sg:phone":"+34 977 61 47 07",
    "sg:postcode":"43800",
    "sg:province":"Tarragona",
    "wof:name":"Escude Jimenez Palmira",
    "wof:placetype":"venue"
},
  "geometry": {"coordinates":[1.2500809431,41.284954071],"type":"Point"}
}