{
  "type": "Feature",
  "properties": {
    "iso:country":"ES",
    "sg:address":"Calle de San Jorge, 21",
    "sg:city":"Zaragoza",
    "sg:orig_category":"Estancos",
    "sg:phone":"+34 976 39 68 31",
    "sg:postcode":"50001",
    "sg:province":"Zaragoza",
    "wof:name":"Siurana Moragrega Juan",
    "wof:placetype":"venue"
},
  "geometry": {"coordinates":[-0.8757240176,41.6520118713],"type":"Point"}
}