{
  "type": "Feature",
  "properties": {
    "iso:country":"ES",
    "sg:address":"Pl Catalunya, 8",
    "sg:city":"Olesa Montserrat",
    "sg:orig_category":"Reposter\u00cdas",
    "sg:phone":"+34 937 78 06 43",
    "sg:postcode":"08640",
    "sg:province":"Barcelona",
    "wof:name":"Montserrat Esplugas Isidro",
    "wof:placetype":"venue"
},
  "geometry": {"coordinates":[1.8935270309,41.5429420471],"type":"Point"}
}