{
  "type": "Feature",
  "properties": {
    "iso:country":"ES",
    "sg:address":"Carrer de Angel Guimera, 1",
    "sg:city":"Molins Rei",
    "sg:orig_category":"Empresas De Labores Complejas De Carga Y Descarga, Montaje Con Elevadores",
    "sg:phone":"+34 936 68 97 79",
    "sg:postcode":"08750",
    "sg:province":"Barcelona",
    "wof:name":"Buron Cabrera Antonio",
    "wof:placetype":"venue"
},
  "geometry": {"coordinates":[2.0192849636,41.4119567871],"type":"Point"}
}