{
  "type": "Feature",
  "properties": {
    "addr:full":"Carrer de Cop, 1 Denia Alicante 03700",
    "addr:housenumber":"1",
    "addr:postcode":"03700",
    "addr:street":"Carrer De Cop",
    "iso:country":"ES",
    "sg:address":"Carrer de Cop, 1",
    "sg:city":"Denia",
    "sg:orig_category":"Ropa Para Se\u00d1oras (al Por Menor)",
    "sg:phone":"+34 966 43 01 98",
    "sg:postcode":"03700",
    "sg:province":"Alicante",
    "sg:website":"www.donalgodon.com",
    "wof:name":"Dianum 2000 S.l.",
    "wof:placetype":"venue"
},
  "geometry": {"coordinates":[0.1063520014,38.8407516479],"type":"Point"}
}