{
  "type": "Feature",
  "properties": {
    "addr:full":"Calle de Torre De Romo, 38 Carmen Murcia 30011",
    "addr:housenumber":"38",
    "addr:postcode":"30011",
    "addr:street":"Calle De Torre De Romo",
    "iso:country":"ES",
    "sg:address":"Calle de Torre De Romo, 38",
    "sg:city":"Carmen",
    "sg:orig_category":"Cajas De Ahorro",
    "sg:phone":"+34 968 26 42 00",
    "sg:postcode":"30011",
    "sg:province":"Murcia",
    "wof:name":"Caja De Ahorros De Murcia",
    "wof:placetype":"venue"
},
  "geometry": {"coordinates":[-1.1055790186,37.9783668518],"type":"Point"}
}