{
  "type": "Feature",
  "properties": {
    "addr:full":"Calle de Alemania, 8 Alacant Alicante 03003",
    "addr:housenumber":"8",
    "addr:postcode":"03003",
    "addr:street":"Calle De Alemania",
    "iso:country":"ES",
    "sg:address":"Calle de Alemania, 8",
    "sg:city":"Alacant",
    "sg:orig_category":"Caf\u00c9s, Bares, Cervecer\u00cdas",
    "sg:phone":"+34 965 12 33 75",
    "sg:postcode":"03003",
    "sg:province":"Alicante",
    "wof:name":"Mengaes S.a.",
    "wof:placetype":"venue"
},
  "geometry": {"coordinates":[-0.4883205891,38.3409194946],"type":"Point"}
}