{
  "type": "Feature",
  "properties": {
    "addr:full":"Rua Subcampo, S/n Rianxo La Coru\u00f1a 15920",
    "addr:housenumber":"s",
    "addr:postcode":"15920",
    "addr:street":"Rua Subcampo;/ N;La Corun\u0303A",
    "iso:country":"ES",
    "sg:address":"Rua Subcampo, S/n",
    "sg:city":"Rianxo",
    "sg:orig_category":"Cajas De Ahorro",
    "sg:phone":"+34 981 86 03 93",
    "sg:postcode":"15920",
    "sg:province":"La Coru\u00f1a",
    "sg:website":"www.caixanova.es",
    "wof:name":"Caixa De Aforros De Vigo Ourense E Pontevedra",
    "wof:placetype":"venue"
},
  "geometry": {"coordinates":[-8.8172187805,42.6528091431],"type":"Point"}
}