{
  "type": "Feature",
  "properties": {
    "iso:country":"ES",
    "sg:address":"Avda Castilla, 8",
    "sg:city":"Reinosa",
    "sg:orig_category":"Alimentaci\u00d3n General (al Por Mayor)",
    "sg:phone":"+34 942 75 30 61",
    "sg:postcode":"39200",
    "sg:province":"Cantabria",
    "wof:name":"Cooperativa Campoo Los Valles",
    "wof:placetype":"venue"
},
  "geometry": {"coordinates":[-4.1454691887,42.9896583557],"type":"Point"}
}