{
  "type": "Feature",
  "properties": {
    "iso:country":"ES",
    "sg:address":"Avda Xose Solla, 38",
    "sg:city":"Calle",
    "sg:orig_category":"Art\u00cdculos De Decoraci\u00d3n",
    "sg:phone":"+34 986 70 12 00",
    "sg:postcode":"36690",
    "sg:province":"Pontevedra",
    "wof:name":"Parras Sanz Antonia",
    "wof:placetype":"venue"
},
  "geometry": {"coordinates":[-8.6055440903,42.3392410278],"type":"Point"}
}