{
  "type": "Feature",
  "properties": {
    "iso:country":"ES",
    "sg:address":"Calle de Prado, 9",
    "sg:city":"Valladolid",
    "sg:orig_category":"Lanas (al Por Menor)",
    "sg:phone":"+34 983 26 78 30",
    "sg:postcode":"47003",
    "sg:province":"Valladolid",
    "wof:name":"Orlandi Morales Marta",
    "wof:placetype":"venue"
},
  "geometry": {"coordinates":[-4.7210259438,41.6557540894],"type":"Point"}
}