{
  "type": "Feature",
  "properties": {
    "addr:full":"Calle de Canovas, 26 Zaragoza Zaragoza 50004",
    "addr:housenumber":"26",
    "addr:postcode":"50004",
    "addr:street":"Calle De Canovas",
    "iso:country":"ES",
    "sg:address":"Calle de Canovas, 26",
    "sg:city":"Zaragoza",
    "sg:orig_category":"Mec\u00c1nico Del Autom\u00d3vil",
    "sg:phone":"+34 976 21 19 22",
    "sg:postcode":"50004",
    "sg:province":"Zaragoza",
    "wof:name":"Neumaticos J.m.martinez S.a.",
    "wof:placetype":"venue"
},
  "geometry": {"coordinates":[-0.8925157785,41.6474647522],"type":"Point"}
}