{
  "type": "Feature",
  "properties": {
    "addr:full":"Calle de Real, 12 Porzuna Ciudad Real 13120",
    "addr:housenumber":"12",
    "addr:postcode":"13120",
    "addr:street":"Calle De Real",
    "iso:country":"ES",
    "sg:address":"Calle de Real, 12",
    "sg:city":"Porzuna",
    "sg:orig_category":"Molduras, Junquillos, Listones Y Molduras Perforadas",
    "sg:phone":"+34 926 78 03 47",
    "sg:postcode":"13120",
    "sg:province":"Ciudad Real",
    "wof:name":"Carpintero Gomez Candelario",
    "wof:placetype":"venue"
},
  "geometry": {"coordinates":[-4.1552891731,39.1469154358],"type":"Point"}
}