{
  "type": "Feature",
  "properties": {
    "addr:full":"Armagin Kalea, 3 Eibar Guip\u00f9zcoa 20600",
    "addr:housenumber":"3",
    "addr:postcode":"20600",
    "addr:street":"Armagin Kalea;Guipu\u0300Zcoa",
    "iso:country":"ES",
    "sg:address":"Armagin Kalea, 3",
    "sg:city":"Eibar",
    "sg:orig_category":"Pescader\u00cdas (al Por Menor)",
    "sg:phone":"+34 943 12 70 26",
    "sg:postcode":"20600",
    "sg:province":"Guip\u00f9zcoa",
    "wof:name":"Ana Teresa Izagirre Mendiola",
    "wof:placetype":"venue"
},
  "geometry": {"coordinates":[-2.4698777199,43.1836929321],"type":"Point"}
}