{
  "type": "Feature",
  "properties": {
    "addr:full":"Calle de Fernando El Catolico, 88 Madrid Madrid 28015",
    "addr:housenumber":"88",
    "addr:postcode":"madrid;28015",
    "addr:street":"Calle De Fernando El Catolico",
    "iso:country":"ES",
    "sg:address":"Calle de Fernando El Catolico, 88",
    "sg:city":"Madrid",
    "sg:orig_category":"Cooperativas Agr\u00cdcolas",
    "sg:phone":"+34 915 49 59 79",
    "sg:postcode":"28015",
    "sg:province":"Madrid",
    "wof:name":"Cooperativa Universitaria Cisneros",
    "wof:placetype":"venue"
},
  "geometry": {"coordinates":[-3.7180390358,40.4342803955],"type":"Point"}
}