{
  "type": "Feature",
  "properties": {
    "addr:full":"Calle de Martina Garcia, 11 Pozuelo De Alarcon Madrid 28224",
    "addr:housenumber":"11",
    "addr:postcode":"28224",
    "addr:street":"Calle De Martina Garcia",
    "iso:country":"ES",
    "sg:address":"Calle de Martina Garcia, 11",
    "sg:city":"Pozuelo De Alarcon",
    "sg:orig_category":"Muebles Y Accesorios Para Cocinas Y Cuartos De Ba\u00d1o (al Por Menor)",
    "sg:phone":"+34 913 52 51 76",
    "sg:postcode":"28224",
    "sg:province":"Madrid",
    "wof:name":"Soto Exposito Antonia",
    "wof:placetype":"venue"
},
  "geometry": {"coordinates":[-3.8020801544,40.4482536316],"type":"Point"}
}