{
  "type": "Feature",
  "properties": {
    "iso:country":"ES",
    "sg:address":"Ctra Canya, La, 155",
    "sg:city":"Olot",
    "sg:orig_category":"Lavado, Limpieza De Veh\u00cdculos",
    "sg:phone":"+34 972 27 30 73",
    "sg:postcode":"17800",
    "sg:province":"Girona",
    "wof:name":"Rentat La Canya S.l.",
    "wof:placetype":"venue"
},
  "geometry": {"coordinates":[2.4987990856,42.1983337402],"type":"Point"}
}