{
  "type": "Feature",
  "properties": {
    "iso:country":"ES",
    "sg:address":"Avgda Textil, 37",
    "sg:city":"Ontinyent",
    "sg:orig_category":"Delegados, Agentes De Tr\u00c1nsito, Auxiliares De Transporte Internacional",
    "sg:phone":"+34 962 91 44 40",
    "sg:postcode":"46870",
    "sg:province":"Valencia",
    "wof:name":"Transportes Alfonso Zamorano S.l.",
    "wof:placetype":"venue"
},
  "geometry": {"coordinates":[-0.599247992,38.825958252],"type":"Point"}
}