{
  "type": "Feature",
  "properties": {
    "iso:country":"ES",
    "sg:address":"Avda Santiago Ramon Y Cajal, 7",
    "sg:city":"Badajoz",
    "sg:orig_category":"Agencias De Viajes",
    "sg:phone":"+34 924 22 17 72",
    "sg:postcode":"06001",
    "sg:province":"Badajoz",
    "sg:website":"www.viajestraventure.com",
    "wof:name":"Traventuretours S.l.",
    "wof:placetype":"venue"
},
  "geometry": {"coordinates":[-6.9758481979,38.8799629211],"type":"Point"}
}