{
  "type": "Feature",
  "properties": {
    "addr:full":"Carrer de Nicolau De Pacs, 31 Palma Islas Baleares 07006",
    "addr:housenumber":"31",
    "addr:postcode":"07006",
    "addr:street":"Carrer De Nicolau De Pacs",
    "iso:country":"ES",
    "sg:address":"Carrer de Nicolau De Pacs, 31",
    "sg:city":"Palma",
    "sg:orig_category":"Muebles, Minoristas",
    "sg:phone":"+34 971 46 68 31",
    "sg:postcode":"07006",
    "sg:province":"Islas Baleares",
    "sg:website":"www.sumueble.es",
    "wof:name":"Su Mueble 2000 S.l.",
    "wof:placetype":"venue"
},
  "geometry": {"coordinates":[2.6600000858,39.5756225586],"type":"Point"}
}