{
  "type": "Feature",
  "properties": {
    "addr:full":"Avda Fuente Nueva (de La), 8 San Sebastian De Los Reyes Madrid 28700",
    "addr:postcode":"28700",
    "addr:street":"Avda Fuente Nueva De La 8",
    "iso:country":"ES",
    "sg:address":"Avda Fuente Nueva (de La), 8",
    "sg:city":"San Sebastian De Los Reyes",
    "sg:orig_category":"Artes Gr\u00c1ficas, Artes Pl\u00c1sticas (curso)",
    "sg:phone":"+34 916 53 43 68",
    "sg:postcode":"28700",
    "sg:province":"Madrid",
    "wof:name":"Artes Graficas Geminis C.b.",
    "wof:placetype":"venue"
},
  "geometry": {"coordinates":[-3.6142530441,40.5484771729],"type":"Point"}
}