{
  "type": "Feature",
  "properties": {
    "addr:full":"Carrer de Jesus, 12 Sitges Barcelona 08870",
    "addr:housenumber":"12",
    "addr:postcode":"08870",
    "addr:street":"Carrer De Jesus",
    "iso:country":"ES",
    "sg:address":"Carrer de Jesus, 12",
    "sg:city":"Sitges",
    "sg:orig_category":"\u00d3ptica: Instrumentos (fabricaci\u00d3n)",
    "sg:phone":"+34 938 94 21 96",
    "sg:postcode":"08870",
    "sg:province":"Barcelona",
    "wof:name":"Sol-gun I Associats S.l.",
    "wof:placetype":"venue"
},
  "geometry": {"coordinates":[1.8101819754,41.2368888855],"type":"Point"}
}