{
  "type": "Feature",
  "properties": {
    "iso:country":"ES",
    "sg:address":"Grup Omega, 7",
    "sg:city":"Otxandio",
    "sg:orig_category":"Electrodom\u00c9sticos (al Por Menor)",
    "sg:phone":"+34 945 45 00 67",
    "sg:postcode":"48210",
    "sg:province":"Vizcaya",
    "wof:name":"Beitia Ajuria Josefa",
    "wof:placetype":"venue"
},
  "geometry": {"coordinates":[-2.6528980732,43.0418739319],"type":"Point"}
}