{
  "type": "Feature",
  "properties": {
    "addr:full":"Calle de Maria Cristina, 1 Nerva Huelva 21670",
    "addr:housenumber":"1",
    "addr:postcode":"21670",
    "addr:street":"Calle De Maria Cristina",
    "iso:country":"ES",
    "sg:address":"Calle de Maria Cristina, 1",
    "sg:city":"Nerva",
    "sg:orig_category":"Carnicer\u00cdas, Carnicer\u00cdas",
    "sg:phone":"+34 959 58 08 59",
    "sg:postcode":"21670",
    "sg:province":"Huelva",
    "wof:name":"Oliva Prieto Antonio",
    "wof:placetype":"venue"
},
  "geometry": {"coordinates":[-6.5508890152,37.6937713623],"type":"Point"}
}