{
  "type": "Feature",
  "properties": {
    "iso:country":"ES",
    "sg:address":"Gta. Arroyo, 2",
    "sg:city":"Arroyo De La Encomienda",
    "sg:orig_category":"Ingenier\u00cda, Centros De Estudios (diversos)",
    "sg:phone":"+34 983 40 94 33",
    "sg:postcode":"47195",
    "sg:province":"Valladolid",
    "wof:name":"Vega Ingenieria Sl",
    "wof:placetype":"venue"
},
  "geometry": {"coordinates":[-4.782602787,41.6173286438],"type":"Point"}
}