{
  "type": "Feature",
  "properties": {
    "iso:country":"ES",
    "sg:address":"Av Montserrat, 18",
    "sg:city":"S. Esteve Sesrovires",
    "sg:orig_category":"Bazares, Art\u00cdculos De Limpieza Y De Cocina (al Por Menor)",
    "sg:phone":"+34 937 71 46 08",
    "sg:postcode":"08635",
    "sg:province":"Barcelona",
    "wof:name":"Cruz Guerrero Dolores",
    "wof:placetype":"venue"
},
  "geometry": {"coordinates":[1.8720029593,41.4954032898],"type":"Point"}
}