{
  "type": "Feature",
  "properties": {
    "iso:country":"ES",
    "sg:address":"Pl Mercat, 4",
    "sg:city":"Vendrell",
    "sg:orig_category":"Inmobiliaria (agencias)",
    "sg:phone":"+34 977 15 53 29",
    "sg:postcode":"43700",
    "sg:province":"Tarragona",
    "wof:name":"Palacin Sanchez Isabel",
    "wof:placetype":"venue"
},
  "geometry": {"coordinates":[1.5359489918,41.2197341919],"type":"Point"}
}