{
  "type": "Feature",
  "properties": {
    "iso:country":"ES",
    "sg:address":"Calle de Santa Ana, 22",
    "sg:city":"Soraluze-placencia Armas",
    "sg:orig_category":"Quincaller\u00cda (al Por Menor)",
    "sg:phone":"+34 943 75 25 22",
    "sg:postcode":"20590",
    "sg:province":"Guip\u00f9zcoa",
    "wof:name":"Arpla C.b.",
    "wof:placetype":"venue"
},
  "geometry": {"coordinates":[-2.4129185677,43.1735572815],"type":"Point"}
}