{
  "type": "Feature",
  "properties": {
    "addr:full":"Calle de San Camilo, S/n Boo Cantabria 39673",
    "addr:housenumber":"s / n",
    "addr:postcode":"39673",
    "addr:street":"Calle De San Camilo",
    "iso:country":"ES",
    "sg:address":"Calle de San Camilo, S/n",
    "sg:city":"Boo",
    "sg:orig_category":"Electricidad Veh\u00cdculo",
    "sg:phone":"+34 942 54 04 24",
    "sg:postcode":"39673",
    "sg:province":"Cantabria",
    "wof:name":"Talleres Del Automovil Ricardo Diego S. L.",
    "wof:placetype":"venue"
},
  "geometry": {"coordinates":[-3.8394269943,43.4058532715],"type":"Point"}
}