{
  "type": "Feature",
  "properties": {
    "iso:country":"ES",
    "sg:address":"Calle de Plaza (de La), 12",
    "sg:city":"Chiclana De La Frontera",
    "sg:orig_category":"M\u00c9dicos: Estomatolog\u00cda",
    "sg:phone":"+34 956 40 35 07",
    "sg:postcode":"11130",
    "sg:province":"C\u00e1diz",
    "wof:name":"Martin Corriente Domingo",
    "wof:placetype":"venue"
},
  "geometry": {"coordinates":[-6.1479649544,36.4212799072],"type":"Point"}
}