{
  "type": "Feature",
  "properties": {
    "addr:full":"Plaz Alcolea, 8 Cartagena Murcia 30201",
    "addr:housenumber":"8",
    "addr:postcode":"30201",
    "addr:street":"Alcolea",
    "iso:country":"ES",
    "sg:address":"Plaz Alcolea, 8",
    "sg:city":"Cartagena",
    "sg:orig_category":"Sindicatos De Trabajadores",
    "sg:phone":"+34 968 52 87 45",
    "sg:postcode":"30201",
    "sg:province":"Murcia",
    "wof:name":"Federacion De Sindicatos Independientes De La Ense\u00f1anza De La Comunidad De Murcia",
    "wof:placetype":"venue"
},
  "geometry": {"coordinates":[-0.8610739708,37.719329834],"type":"Point"}
}