{
  "type": "Feature",
  "properties": {
    "iso:country":"ES",
    "sg:address":"Calle de Castillo De Simancas, 29",
    "sg:city":"Madrid",
    "sg:orig_category":"Limpieza Con Chorro De Arena Y Con Granalla, Pulido",
    "sg:phone":"+34 913 27 20 20",
    "sg:postcode":"28037",
    "sg:province":"Madrid",
    "wof:name":"Limpiezas Colima Sociedad Cooperativa Limitada",
    "wof:placetype":"venue"
},
  "geometry": {"coordinates":[-3.6249604225,40.4307518005],"type":"Point"}
}