{
  "type": "Feature",
  "properties": {
    "iso:country":"ES",
    "sg:address":"Calle de Valle Inclan, 2",
    "sg:city":"Alacant",
    "sg:orig_category":"Laboratorios Y Trabajos De Fotograf\u00cda, V\u00cddeo Y Cine",
    "sg:phone":"+34 965 17 54 38",
    "sg:postcode":"03011",
    "sg:province":"Alicante",
    "wof:name":"I\u00f1esta Perez Rafael",
    "wof:placetype":"venue"
},
  "geometry": {"coordinates":[-0.4895389974,38.3742103577],"type":"Point"}
}