{
  "type": "Feature",
  "properties": {
    "addr:full":"Carrer de Sant Vicent Ferrer, 1 Crevillent Alicante 03330",
    "addr:housenumber":"1",
    "addr:postcode":"03330",
    "addr:street":"Carrer De Sant Vicent Ferrer",
    "iso:country":"ES",
    "sg:address":"Carrer de Sant Vicent Ferrer, 1",
    "sg:city":"Crevillent",
    "sg:orig_category":"Asociaciones Y Clubs Deportivos",
    "sg:phone":"+34 965 40 33 31",
    "sg:postcode":"03330",
    "sg:province":"Alicante",
    "wof:name":"Sanchez Perez Antonio Jesus",
    "wof:placetype":"venue"
},
  "geometry": {"coordinates":[-0.8084390163,38.2455596924],"type":"Point"}
}