{
  "type": "Feature",
  "properties": {
    "iso:country":"ES",
    "sg:address":"Ctra Valle Tabares, 51",
    "sg:city":"Cuesta",
    "sg:orig_category":"Industria Qu\u00cdmica",
    "sg:phone":"+34 922 64 60 02",
    "sg:postcode":"38320",
    "sg:province":"Santa Cruz De Tenerife",
    "wof:name":"Picardo Franquis Jose Luis",
    "wof:placetype":"venue"
},
  "geometry": {"coordinates":[-16.2896747589,28.4723854065],"type":"Point"}
}