{
  "type": "Feature",
  "properties": {
    "iso:country":"ES",
    "sg:address":"Rava Santa Anna, 52",
    "sg:city":"Reus",
    "sg:orig_category":"Mercer\u00cda, Lencer\u00cda (al Por Menor)",
    "sg:phone":"+34 977 34 43 43",
    "sg:postcode":"43201",
    "sg:province":"Tarragona",
    "wof:name":"La Gallineta S.l.",
    "wof:placetype":"venue"
},
  "geometry": {"coordinates":[1.1096819639,41.156791687],"type":"Point"}
}