{
  "type": "Feature",
  "properties": {
    "iso:country":"ES",
    "sg:address":"Calle de Aragon (de), 3",
    "sg:city":"Arroyomolinos",
    "sg:orig_category":"Flores Y Plantas Naturales (al Por Mayor)",
    "sg:phone":"+34 916 09 11 23",
    "sg:postcode":"28939",
    "sg:province":"Madrid",
    "sg:website":"www.cultiusroig.com",
    "wof:name":"Vivers Del Tordera S.a.t. 1343 Cat",
    "wof:placetype":"venue"
},
  "geometry": {"coordinates":[-3.9203090668,40.2691116333],"type":"Point"}
}