{
  "type": "Feature",
  "properties": {
    "iso:country":"ES",
    "sg:address":"Calle de Cervantes, 16",
    "sg:city":"Segovia",
    "sg:orig_category":"Estilistas Y Estudios De Estilo De Corte Y Confecci\u00d3n",
    "sg:phone":"+34 921 46 16 49",
    "sg:postcode":"40001",
    "sg:province":"Segovia",
    "wof:name":"Nesho Balcan S.l.",
    "wof:placetype":"venue"
},
  "geometry": {"coordinates":[-4.1192464828,40.9478492737],"type":"Point"}
}