{
  "type": "Feature",
  "properties": {
    "addr:full":"Avda Paz De (la), 19 Logro\u00f1o La Rioja 26004",
    "addr:housenumber":"19",
    "addr:postcode":"26004",
    "addr:street":"Avda Paz De La;Rioja",
    "iso:country":"ES",
    "sg:address":"Avda Paz De (la), 19",
    "sg:city":"Logro\u00f1o",
    "sg:orig_category":"Material Y Suministros Para Peluquer\u00cda",
    "sg:phone":"+34 941 23 35 44",
    "sg:postcode":"26004",
    "sg:province":"La Rioja",
    "wof:name":"Exclusivas Crish S.l.",
    "wof:placetype":"venue"
},
  "geometry": {"coordinates":[-2.437951088,42.4653930664],"type":"Point"}
}