{
  "type": "Feature",
  "properties": {
    "iso:country":"ES",
    "sg:address":"Calle de Nacimiento, S/n",
    "sg:city":"Jodar",
    "sg:orig_category":"Aceites Y Grasas Alimentarias (fabricaci\u00d3n, Al Por Mayor)",
    "sg:phone":"+34 953 78 74 90",
    "sg:postcode":"23500",
    "sg:province":"Ja\u00e9n",
    "wof:name":"Aceites La Dehesa S.l.",
    "wof:placetype":"venue"
},
  "geometry": {"coordinates":[-3.3507215977,37.83776474],"type":"Point"}
}