{
  "type": "Feature",
  "properties": {
    "addr:full":"Calle de Maqueda, 138 Madrid Madrid 28024",
    "addr:housenumber":"138",
    "addr:postcode":"28024",
    "addr:street":"Calle De Maqueda",
    "iso:country":"ES",
    "sg:address":"Calle de Maqueda, 138",
    "sg:city":"Madrid",
    "sg:orig_category":"Lavado, Limpieza De Veh\u00cdculos",
    "sg:phone":"+34 917 19 24 90",
    "sg:postcode":"28024",
    "sg:province":"Madrid",
    "wof:name":"Sanz Fernandez Feliciano",
    "wof:placetype":"venue"
},
  "geometry": {"coordinates":[-3.7609820366,40.3867416382],"type":"Point"}
}