{
  "type": "Feature",
  "properties": {
    "iso:country":"ES",
    "sg:address":"Calle de Manila, 15",
    "sg:city":"Marpeque\u00d1a",
    "sg:orig_category":"Transporte En General",
    "sg:phone":"+34 928 70 67 96",
    "sg:postcode":"35214",
    "sg:province":"Las Palmas",
    "wof:name":"Distribuidora Ersa S.l.",
    "wof:placetype":"venue"
},
  "geometry": {"coordinates":[-15.3887634277,27.9937648773],"type":"Point"}
}