{
  "type": "Feature",
  "properties": {
    "addr:full":"Calle de Fuengirola, S/n Madrid Madrid 28018",
    "addr:housenumber":"s / n",
    "addr:postcode":"28018",
    "addr:street":"Calle De Fuengirola",
    "iso:country":"ES",
    "sg:address":"Calle de Fuengirola, S/n",
    "sg:city":"Madrid",
    "sg:orig_category":"Poller\u00cda Y Caza (al Por Menor)",
    "sg:phone":"+34 917 78 25 41",
    "sg:postcode":"28018",
    "sg:province":"Madrid",
    "wof:name":"Esteban Hernando Pedro",
    "wof:placetype":"venue"
},
  "geometry": {"coordinates":[-3.6397390366,40.3851356506],"type":"Point"}
}