{
  "type": "Feature",
  "properties": {
    "iso:country":"ES",
    "sg:address":"Calle de Doctor Encinas, 11",
    "sg:city":"Potes",
    "sg:orig_category":"Bancos",
    "sg:phone":"+34 942 73 02 24",
    "sg:postcode":"39570",
    "sg:province":"Cantabria",
    "sg:website":"www.gruposantander.es",
    "wof:name":"Bulnes Ruiz Manuel",
    "wof:placetype":"venue"
},
  "geometry": {"coordinates":[-4.6220693588,43.1539382935],"type":"Point"}
}