{
  "type": "Feature",
  "properties": {
    "iso:country":"ES",
    "sg:address":"Pdis Lluis Muncunill, De, 10",
    "sg:city":"Terrassa",
    "sg:orig_category":"Quincaller\u00cda (al Por Menor)",
    "sg:phone":"+34 937 35 88 76",
    "sg:postcode":"08225",
    "sg:province":"Barcelona",
    "wof:name":"Fernandez Sansa Xavier",
    "wof:placetype":"venue"
},
  "geometry": {"coordinates":[2.0128519535,41.5781173706],"type":"Point"}
}