{
  "type": "Feature",
  "properties": {
    "addr:full":"Bard Residencial Las Palmeras, S/n Sevilla Sevilla 41013",
    "addr:housenumber":"s / n",
    "addr:postcode":"41013",
    "addr:street":"Residencial Las",
    "iso:country":"ES",
    "sg:address":"Bard Residencial Las Palmeras, S/n",
    "sg:city":"Sevilla",
    "sg:orig_category":"Tapicer\u00cdas",
    "sg:phone":"+34 954 61 36 22",
    "sg:postcode":"41013",
    "sg:province":"Sevilla",
    "wof:name":"Rojas Molina Juan",
    "wof:placetype":"venue"
},
  "geometry": {"coordinates":[-6.0018129349,37.3876953125],"type":"Point"}
}