{
  "type": "Feature",
  "properties": {
    "addr:full":"Calle de Antonio Y Manuel Martinez, 7 Santiago El Mayor Murcia 30012",
    "addr:housenumber":"7",
    "addr:postcode":"30012",
    "addr:street":"Calle De Antonio Y Manuel Martinez",
    "iso:country":"ES",
    "sg:address":"Calle de Antonio Y Manuel Martinez, 7",
    "sg:city":"Santiago El Mayor",
    "sg:orig_category":"Equipo De Refrigeraci\u00d3n Industrial",
    "sg:phone":"+34 968 26 00 32",
    "sg:postcode":"30012",
    "sg:province":"Murcia",
    "wof:name":"Levantina De Suministros Frigorificos S.a.l.",
    "wof:placetype":"venue"
},
  "geometry": {"coordinates":[-1.1265063286,37.9737319946],"type":"Point"}
}