{
  "type": "Feature",
  "properties": {
    "addr:full":"T Palomino Lodares, S/n Hontanaya Cuenca 16416",
    "addr:postcode":"16416",
    "addr:street":"T;Lodares S / N Hontanaya",
    "iso:country":"ES",
    "sg:address":"T Palomino Lodares, S/n",
    "sg:city":"Hontanaya",
    "sg:orig_category":"Cr\u00cda De Animales",
    "sg:phone":"+34 969 12 90 62",
    "sg:postcode":"16416",
    "sg:province":"Cuenca",
    "wof:name":"Valentin Pastor Tomas",
    "wof:placetype":"venue"
},
  "geometry": {"coordinates":[-2.8342339993,39.7178497314],"type":"Point"}
}