{
  "type": "Feature",
  "properties": {
    "iso:country":"ES",
    "sg:address":"Avda El Ferial, 95",
    "sg:city":"Benavente",
    "sg:orig_category":"Empresas De Desmonte",
    "sg:phone":"+34 980 63 75 35",
    "sg:postcode":"49600",
    "sg:province":"Zamora",
    "wof:name":"Dominguez Gonzalez Natalio",
    "wof:placetype":"venue"
},
  "geometry": {"coordinates":[-5.6773190498,41.9971694946],"type":"Point"}
}