{
  "type": "Feature",
  "properties": {
    "iso:country":"ES",
    "sg:address":"Calle de Navas (las), 39",
    "sg:city":"Alacant",
    "sg:orig_category":"Electrodom\u00c9sticos (al Por Menor)",
    "sg:phone":"+34 965 14 09 84",
    "sg:postcode":"03001",
    "sg:province":"Alicante",
    "wof:name":"Rovifran S.l.",
    "wof:placetype":"venue"
},
  "geometry": {"coordinates":[-0.4872789979,38.3461914062],"type":"Point"}
}