{
  "type": "Feature",
  "properties": {
    "addr:full":"Calle de Ramon Y Cajal, 8 Alcala Henares Madrid 28801",
    "addr:housenumber":"8",
    "addr:postcode":"28801",
    "addr:street":"Calle De Ramon Y Cajal",
    "iso:country":"ES",
    "sg:address":"Calle de Ramon Y Cajal, 8",
    "sg:city":"Alcala Henares",
    "sg:orig_category":"Centros Empresariales",
    "sg:phone":"+34 918 89 51 11",
    "sg:postcode":"28801",
    "sg:province":"Madrid",
    "wof:name":"Redondo Cebrian Ines",
    "wof:placetype":"venue"
},
  "geometry": {"coordinates":[-3.365334034,40.4823570251],"type":"Point"}
}