{
  "type": "Feature",
  "properties": {
    "iso:country":"ES",
    "sg:address":"Calle de Perez Galdos, 41",
    "sg:city":"Bilbao",
    "sg:orig_category":"Art\u00cdculos De Regalo (al Por Menor)",
    "sg:phone":"+34 944 27 33 46",
    "sg:postcode":"48010",
    "sg:province":"Vizcaya",
    "wof:name":"Marisol Saez Del Rio",
    "wof:placetype":"venue"
},
  "geometry": {"coordinates":[-2.946158886,43.2598800659],"type":"Point"}
}