{
  "type": "Feature",
  "properties": {
    "iso:country":"ES",
    "sg:address":"Calle de Hierro, 20",
    "sg:city":"Torrejon Ardoz",
    "sg:orig_category":"Garajes De Veh\u00cdculos",
    "sg:phone":"+34 916 75 80 43",
    "sg:postcode":"28850",
    "sg:province":"Madrid",
    "sg:website":"www.valverauto.es",
    "wof:name":"Valberauto S.a.",
    "wof:placetype":"venue"
},
  "geometry": {"coordinates":[-3.4618198872,40.4549751282],"type":"Point"}
}