{
  "type": "Feature",
  "properties": {
    "iso:country":"ES",
    "sg:address":"Otaola Hiribidea, 13",
    "sg:city":"Eibar",
    "sg:orig_category":"Muebles, Minoristas",
    "sg:phone":"+34 943 20 78 44",
    "sg:postcode":"20600",
    "sg:province":"Guip\u00f9zcoa",
    "wof:name":"Conde Quintas Victor",
    "wof:placetype":"venue"
},
  "geometry": {"coordinates":[-2.485188961,43.1806716919],"type":"Point"}
}