{
  "type": "Feature",
  "properties": {
    "iso:country":"ES",
    "sg:address":"Carrer de Joaquim Valls, 87",
    "sg:city":"Barcelona",
    "sg:orig_category":"Centros Comerciales Y Grandes Tiendas",
    "sg:phone":"+34 932 76 22 75",
    "sg:postcode":"08016",
    "sg:province":"Barcelona",
    "wof:name":"Yan  Zheng",
    "wof:placetype":"venue"
},
  "geometry": {"coordinates":[2.179461956,41.4440383911],"type":"Point"}
}