{
  "type": "Feature",
  "properties": {
    "addr:full":"Ctra. Zaidin, S/n Altorricon Huesca 22540",
    "addr:housenumber":"s / n",
    "addr:postcode":"22540",
    "addr:street":"Ctra. Zaidin",
    "iso:country":"ES",
    "sg:address":"Ctra. Zaidin, S/n",
    "sg:city":"Altorricon",
    "sg:orig_category":"Cr\u00cda De Cerdos",
    "sg:phone":"+34 974 33 90 42",
    "sg:postcode":"22540",
    "sg:province":"Huesca",
    "wof:name":"Ventafarinas S.l.",
    "wof:placetype":"venue"
},
  "geometry": {"coordinates":[0.4147399962,41.8023605347],"type":"Point"}
}