{
  "type": "Feature",
  "properties": {
    "iso:country":"ES",
    "sg:address":"Calle de Rufas, 21",
    "sg:city":"Zaragoza",
    "sg:orig_category":"Fabricaci\u00d3n, Distribuci\u00d3n De Discos, V\u00cddeodiscos Y Musicassettes",
    "sg:phone":"+34 976 23 05 26",
    "sg:postcode":"50001",
    "sg:province":"Zaragoza",
    "sg:website":"www.tipo.es",
    "wof:name":"Promointegrator S.l.",
    "wof:placetype":"venue"
},
  "geometry": {"coordinates":[-0.8777629733,41.6501579285],"type":"Point"}
}