{
  "type": "Feature",
  "properties": {
    "addr:full":"Calle de Baltasar, 3 Madrid Madrid 28033",
    "addr:housenumber":"3",
    "addr:postcode":"28033",
    "addr:street":"Calle De Baltasar",
    "iso:country":"ES",
    "sg:address":"Calle de Baltasar, 3",
    "sg:city":"Madrid",
    "sg:orig_category":"Centros Empresariales",
    "sg:phone":"+34 913 88 76 86",
    "sg:postcode":"28033",
    "sg:province":"Madrid",
    "wof:name":"Barrio Del Pilar Servicios Hosteleros",
    "wof:placetype":"venue"
},
  "geometry": {"coordinates":[-3.6534800529,40.4663696289],"type":"Point"}
}