{
  "type": "Feature",
  "properties": {
    "addr:full":"C/ Governador Padules, 13 Tarrega Lleida 25300",
    "addr:housenumber":"13",
    "addr:postcode":"25300",
    "addr:street":"C / Governador Padules",
    "iso:country":"ES",
    "sg:address":"C/ Governador Padules, 13",
    "sg:city":"Tarrega",
    "sg:orig_category":"Producci\u00d3n, Comercio De Cereales",
    "sg:phone":"+34 973 31 09 53",
    "sg:postcode":"25300",
    "sg:province":"Lleida",
    "wof:name":"Vila Climent Emilia",
    "wof:placetype":"venue"
},
  "geometry": {"coordinates":[1.1410850286,41.6482696533],"type":"Point"}
}