{
  "type": "Feature",
  "properties": {
    "addr:full":"Nafarroa Etorbidea, 5 Beasain Guip\u00f9zcoa 20200",
    "addr:housenumber":"5",
    "addr:postcode":"20200",
    "addr:street":"Nafarroa Etorbidea;Guipu\u0300Zcoa",
    "iso:country":"ES",
    "sg:address":"Nafarroa Etorbidea, 5",
    "sg:city":"Beasain",
    "sg:orig_category":"Tapicer\u00cdas",
    "sg:phone":"+34 943 08 65 65",
    "sg:postcode":"20200",
    "sg:province":"Guip\u00f9zcoa",
    "wof:name":"Tapicerias Biok, C.b.",
    "wof:placetype":"venue"
},
  "geometry": {"coordinates":[-2.2002909184,43.0467071533],"type":"Point"}
}