{
  "type": "Feature",
  "properties": {
    "iso:country":"ES",
    "sg:address":"Carrer de Ricard Cirera (de), 6",
    "sg:city":"Tortosa",
    "sg:orig_category":"Arquitectos",
    "sg:phone":"+34 977 44 51 66",
    "sg:postcode":"43500",
    "sg:province":"Tarragona",
    "wof:name":"Roig Montagut Enric",
    "wof:placetype":"venue"
},
  "geometry": {"coordinates":[0.5213339925,40.8100242615],"type":"Point"}
}