{
  "type": "Feature",
  "properties": {
    "addr:full":"Monte, S/n Montroy Valencia 46193",
    "addr:housenumber":"s",
    "addr:postcode":"46193",
    "addr:street":"Monte;/ N",
    "iso:country":"ES",
    "sg:address":"Monte, S/n",
    "sg:city":"Montroy",
    "sg:orig_category":"Polideportivos",
    "sg:phone":"+34 962 55 61 82",
    "sg:postcode":"46193",
    "sg:province":"Valencia",
    "wof:name":"Ayuntamiento De Montroy",
    "wof:placetype":"venue"
},
  "geometry": {"coordinates":[-0.6143140197,39.3403549194],"type":"Point"}
}