{
  "type": "Feature",
  "properties": {
    "iso:country":"ES",
    "sg:address":"Calle de Jose Antonio, 2",
    "sg:city":"Huecas",
    "sg:orig_category":"Molduras, Junquillos, Listones Y Molduras Perforadas",
    "sg:phone":"+34 925 78 47 88",
    "sg:postcode":"45511",
    "sg:province":"Toledo",
    "wof:name":"Sanchez Garcia Martin",
    "wof:placetype":"venue"
},
  "geometry": {"coordinates":[-4.1962389946,40.0121994019],"type":"Point"}
}