{
  "type": "Feature",
  "properties": {
    "addr:full":"Plaza Kuwait, 7 Almu\u00f1ecar Granada 18690",
    "addr:housenumber":"7",
    "addr:postcode":"18690",
    "iso:country":"ES",
    "sg:address":"Plaza Kuwait, 7",
    "sg:city":"Almu\u00f1ecar",
    "sg:orig_category":"Instalaci\u00d3n, Reparaci\u00d3n De Ascensores Y Montacargas",
    "sg:phone":"+34 958 88 14 50",
    "sg:postcode":"18690",
    "sg:province":"Granada",
    "wof:name":"A Embarba S.a.",
    "wof:placetype":"venue"
},
  "geometry": {"coordinates":[-3.6926088333,36.7355308533],"type":"Point"}
}