{
  "type": "Feature",
  "properties": {
    "addr:full":"Calle de Uria, 25 Gijon Asturias 33202",
    "addr:housenumber":"25",
    "addr:postcode":"33202",
    "addr:street":"Calle De Uria",
    "iso:country":"ES",
    "sg:address":"Calle de Uria, 25",
    "sg:city":"Gijon",
    "sg:orig_category":"M\u00c9dicos: Cirug\u00cda General",
    "sg:phone":"+34 985 37 45 61",
    "sg:postcode":"33202",
    "sg:province":"Asturias",
    "wof:name":"Alvarez Obregon Raul",
    "wof:placetype":"venue"
},
  "geometry": {"coordinates":[-5.6556010246,43.5386619568],"type":"Point"}
}