{
  "type": "Feature",
  "properties": {
    "addr:full":"Carr Sant Ramon, De, 13 Soller Islas Baleares 07100",
    "addr:housenumber":"13",
    "addr:postcode":"07100",
    "addr:street":"Carr Sant Ramon De",
    "iso:country":"ES",
    "sg:address":"Carr Sant Ramon, De, 13",
    "sg:city":"Soller",
    "sg:orig_category":"Maquinaria Para Industrias Diversas",
    "sg:phone":"+34 971 63 07 69",
    "sg:postcode":"07100",
    "sg:province":"Islas Baleares",
    "wof:name":"Talleres Andreu C.b.",
    "wof:placetype":"venue"
},
  "geometry": {"coordinates":[2.7199959755,39.7663421631],"type":"Point"}
}