{
  "type": "Feature",
  "properties": {
    "iso:country":"ES",
    "sg:address":"Pase Olof Palme, S/n",
    "sg:city":"Badalona",
    "sg:orig_category":"Ropa Para Se\u00d1oras (al Por Menor)",
    "sg:phone":"+34 934 65 83 40",
    "sg:postcode":"08917",
    "sg:province":"Barcelona",
    "sg:website":"www.etxartpanno.com",
    "wof:name":"Garrido Galvez Marta",
    "wof:placetype":"venue"
},
  "geometry": {"coordinates":[2.2269508839,41.4548301697],"type":"Point"}
}