{
  "type": "Feature",
  "properties": {
    "iso:country":"ES",
    "sg:address":"Av Furs (dels), 64",
    "sg:city":"Lliria",
    "sg:orig_category":"Agencias Y Agentes Comerciales, Representantes",
    "sg:phone":"+34 962 78 04 24",
    "sg:postcode":"46160",
    "sg:province":"Valencia",
    "wof:name":"Ma\u00f1ez Movejarque Miguel",
    "wof:placetype":"venue"
},
  "geometry": {"coordinates":[-0.5932790041,39.6327972412],"type":"Point"}
}