{
  "type": "Feature",
  "properties": {
    "addr:full":"Avda Diego Moron De, 31 Huelva Huelva 21005",
    "addr:postcode":"21005",
    "addr:street":"Avda Diego",
    "iso:country":"ES",
    "sg:address":"Avda Diego Moron De, 31",
    "sg:city":"Huelva",
    "sg:orig_category":"Distribuci\u00d3n De Petr\u00d3leo Y Derivados",
    "sg:phone":"+34 959 15 24 23",
    "sg:postcode":"21005",
    "sg:province":"Huelva",
    "wof:name":"Expromar S.a.",
    "wof:placetype":"venue"
},
  "geometry": {"coordinates":[-6.9416952133,37.2786941528],"type":"Point"}
}