{
  "type": "Feature",
  "properties": {
    "iso:country":"ES",
    "sg:address":"Avda Playa Serena, 135",
    "sg:city":"Urbanizacion Roquetas De Mar",
    "sg:orig_category":"Abogados",
    "sg:phone":"+34 950 33 38 88",
    "sg:postcode":"04740",
    "sg:province":"Almer\u00eda",
    "wof:name":"Salvador Herrada Antonio",
    "wof:placetype":"venue"
},
  "geometry": {"coordinates":[-2.6137111187,36.7678031921],"type":"Point"}
}