{
  "type": "Feature",
  "properties": {
    "iso:country":"ES",
    "sg:address":"Calle de E, 4",
    "sg:city":"Mutiloabeiti",
    "sg:orig_category":"Maquinaria Para Industrias Diversas",
    "sg:phone":"+34 948 24 07 44",
    "sg:postcode":"31192",
    "sg:province":"Navarra",
    "wof:name":"Abicet S.l.",
    "wof:placetype":"venue"
},
  "geometry": {"coordinates":[-1.634595,42.807041],"type":"Point"}
}