{
  "type": "Feature",
  "properties": {
    "addr:full":"Rua Evaristo Correa Calderon, 54 Baralla Lugo 27680",
    "addr:housenumber":"54",
    "addr:postcode":"27680",
    "addr:street":"Rua Evaristo Correa Calderon",
    "iso:country":"ES",
    "sg:address":"Rua Evaristo Correa Calderon, 54",
    "sg:city":"Baralla",
    "sg:orig_category":"Agentes Generales De Seguros",
    "sg:phone":"+34 982 36 32 56",
    "sg:postcode":"27680",
    "sg:province":"Lugo",
    "wof:name":"Silva Mediacion S.l.",
    "wof:placetype":"venue"
},
  "geometry": {"coordinates":[-7.2502617836,42.8940124512],"type":"Point"}
}