{
  "type": "Feature",
  "properties": {
    "iso:country":"ES",
    "sg:address":"Las Chafiras, S/n",
    "sg:city":"Las Chafiras",
    "sg:orig_category":"Muebles",
    "sg:phone":"+34 922 73 52 28",
    "sg:postcode":"38639",
    "sg:province":"Santa Cruz De Tenerife",
    "wof:name":"Hernandez Guerra Maria Angelica",
    "wof:placetype":"venue"
},
  "geometry": {"coordinates":[-16.2548561096,28.4698104858],"type":"Point"}
}