{
  "type": "Feature",
  "properties": {
    "iso:country":"ES",
    "sg:address":"Pase Isabel La Catolica, 8",
    "sg:city":"Valladolid",
    "sg:orig_category":"Alimentaci\u00d3n General (al Por Menor)",
    "sg:phone":"+34 983 33 10 05",
    "sg:postcode":"47001",
    "sg:province":"Valladolid",
    "wof:name":"Garcia Pascual Concepcion",
    "wof:placetype":"venue"
},
  "geometry": {"coordinates":[-4.7323784828,41.6519050598],"type":"Point"}
}