{
  "type": "Feature",
  "properties": {
    "addr:full":"Calle de Muralla, 35 Albolote Granada 18220",
    "addr:housenumber":"35",
    "addr:postcode":"18220",
    "addr:street":"Calle De Muralla",
    "iso:country":"ES",
    "sg:address":"Calle de Muralla, 35",
    "sg:city":"Albolote",
    "sg:orig_category":"Inform\u00c1tica Equipo Y Programas (al Por Mayor)",
    "sg:phone":"+34 958 43 07 59",
    "sg:postcode":"18220",
    "sg:province":"Granada",
    "wof:name":"Ruiz Aznar Diego",
    "wof:placetype":"venue"
},
  "geometry": {"coordinates":[-3.6539189816,37.2314796448],"type":"Point"}
}