{
  "type": "Feature",
  "properties": {
    "iso:country":"ES",
    "sg:address":"Calle de Viveros, 6",
    "sg:city":"Logro\u00f1o",
    "sg:orig_category":"Electricidad: Instaladores",
    "sg:phone":"+34 941 20 91 99",
    "sg:postcode":"26005",
    "sg:province":"La Rioja",
    "wof:name":"Fuentes Molia Jose Vicente",
    "wof:placetype":"venue"
},
  "geometry": {"coordinates":[-2.4588930607,42.4628181458],"type":"Point"}
}