{
  "type": "Feature",
  "properties": {
    "iso:country":"ES",
    "sg:address":"Calle de Imagen, 8",
    "sg:city":"Sevilla",
    "sg:orig_category":"Ingeniero",
    "sg:phone":"+34 954 22 65 42",
    "sg:postcode":"41003",
    "sg:province":"Sevilla",
    "wof:name":"Medina Encina Fernando",
    "wof:placetype":"venue"
},
  "geometry": {"coordinates":[-5.9900012016,37.3926086426],"type":"Point"}
}