{
  "type": "Feature",
  "properties": {
    "addr:full":"Afueras, S/n Genova Islas Baleares 07015",
    "addr:postcode":"07015",
    "addr:street":"Afueras S / N",
    "iso:country":"ES",
    "sg:address":"Afueras, S/n",
    "sg:city":"Genova",
    "sg:orig_category":"Iglesia Cat\u00d3lica",
    "sg:phone":"+34 971 40 23 75",
    "sg:postcode":"07015",
    "sg:province":"Islas Baleares",
    "wof:name":"Obispado De Mallorca",
    "wof:placetype":"venue"
},
  "geometry": {"coordinates":[2.606345892,39.5533103943],"type":"Point"}
}