{
  "type": "Feature",
  "properties": {
    "addr:full":"Avda Juventud (de La), S/n Avila \u00c1vila 05003",
    "addr:postcode":"05003",
    "addr:street":"Avda Juventud De La S / N;A\u0301Vila",
    "iso:country":"ES",
    "sg:address":"Avda Juventud (de La), S/n",
    "sg:city":"Avila",
    "sg:orig_category":"Agricultores, Agricultores",
    "sg:phone":"+34 920 21 12 35",
    "sg:postcode":"05003",
    "sg:province":"\u00c1vila",
    "wof:name":"Jose Tomas Rodriguez S.l.",
    "wof:placetype":"venue"
},
  "geometry": {"coordinates":[-4.6881380081,40.6489562988],"type":"Point"}
}