{
  "type": "Feature",
  "properties": {
    "iso:country":"ES",
    "sg:address":"Cmno Mitxine, 1",
    "sg:city":"Basozabal",
    "sg:orig_category":"Reparaciones Y Remolcado De Veh\u00cdculos",
    "sg:phone":"+34 944 53 18 68",
    "sg:postcode":"48150",
    "sg:province":"Vizcaya",
    "wof:name":"Ibarrondo Mendizabal Sabino",
    "wof:placetype":"venue"
},
  "geometry": {"coordinates":[-2.9280378819,43.2989196777],"type":"Point"}
}