{
  "type": "Feature",
  "properties": {
    "addr:full":"Carrer de Biada, 15 Barcelona Barcelona 08012",
    "addr:housenumber":"15",
    "addr:postcode":"08012",
    "addr:street":"Carrer De Biada",
    "iso:country":"ES",
    "sg:address":"Carrer de Biada, 15",
    "sg:city":"Barcelona",
    "sg:orig_category":"Fabricaci\u00d3n De Telas Y Sedas",
    "sg:phone":"+34 934 15 14 38",
    "sg:postcode":"08012",
    "sg:province":"Barcelona",
    "wof:name":"Obradors S. A.",
    "wof:placetype":"venue"
},
  "geometry": {"coordinates":[2.154966116,41.4054527283],"type":"Point"}
}