{
  "type": "Feature",
  "properties": {
    "addr:full":"Carrer de Francesc Vila, S/n S. Cugat Valles Barcelona 08173",
    "addr:housenumber":"s",
    "addr:postcode":"08173",
    "addr:street":"Carrer De Francesc Vila;/ N S. Cugat Valles Barcelona",
    "iso:country":"ES",
    "sg:address":"Carrer de Francesc Vila, S/n",
    "sg:city":"S. Cugat Valles",
    "sg:orig_category":"Fabricaci\u00d3n, Importaci\u00d3n De Material Y Sistemas De Telecomunicaciones",
    "sg:phone":"+34 935 89 38 58",
    "sg:postcode":"08173",
    "sg:province":"Barcelona",
    "sg:website":"www.arpsl.com",
    "wof:name":"Auto Radio Provenza S.l.",
    "wof:placetype":"venue"
},
  "geometry": {"coordinates":[2.0914769173,41.4793968201],"type":"Point"}
}