{
  "type": "Feature",
  "properties": {
    "addr:full":"Avda Menendez Pidal, 15 Valencia Valencia 46009",
    "addr:housenumber":"15",
    "addr:postcode":"46009",
    "addr:street":"Avda Menendez Pidal",
    "iso:country":"ES",
    "sg:address":"Avda Menendez Pidal, 15",
    "sg:city":"Valencia",
    "sg:orig_category":"Higiene, Belleza: Art\u00cdculos (al Por Menor)",
    "sg:phone":"+34 963 49 60 27",
    "sg:postcode":"46009",
    "sg:province":"Valencia",
    "wof:name":"Telecor S.a.",
    "wof:placetype":"venue"
},
  "geometry": {"coordinates":[-0.3908750117,39.4791374207],"type":"Point"}
}