{
  "type": "Feature",
  "properties": {
    "iso:country":"ES",
    "sg:address":"Cra. Sanson, 31",
    "sg:city":"Sant Feliu Llobregat",
    "sg:orig_category":"Bisuter\u00cda, Joyer\u00cda, Relojer\u00cda (al Por Menor)",
    "sg:phone":"+34 936 66 16 59",
    "sg:postcode":"08980",
    "sg:province":"Barcelona",
    "wof:name":"Ramirez Nieto Cristobal",
    "wof:placetype":"venue"
},
  "geometry": {"coordinates":[2.0435750484,41.3816261292],"type":"Point"}
}