{
  "type": "Feature",
  "properties": {
    "iso:country":"ES",
    "sg:address":"Avda Torrelavega De, 23",
    "sg:city":"Oviedo",
    "sg:orig_category":"Peluqueros: De Se\u00d1oras",
    "sg:phone":"+34 985 21 09 14",
    "sg:postcode":"33010",
    "sg:province":"Asturias",
    "wof:name":"Rodrigo Sienra Raquel",
    "wof:placetype":"venue"
},
  "geometry": {"coordinates":[-5.8366241455,43.3639564514],"type":"Point"}
}