{
  "type": "Feature",
  "properties": {
    "iso:country":"ES",
    "sg:address":"Calle de Celia Vi\u00d1as, 7",
    "sg:city":"Roquetas Mar",
    "sg:orig_category":"Asilos De Ancianos. Centros Privados",
    "sg:phone":"+34 950 32 59 70",
    "sg:postcode":"04740",
    "sg:province":"Almer\u00eda",
    "wof:name":"Club Tercera Edad Jose Maria Cara",
    "wof:placetype":"venue"
},
  "geometry": {"coordinates":[-2.6149809361,36.7662200928],"type":"Point"}
}