{
  "type": "Feature",
  "properties": {
    "addr:full":"Calle de Tarragona, 4 Binefar Huesca 22500",
    "addr:housenumber":"4",
    "addr:postcode":"22500",
    "addr:street":"Calle De Tarragona",
    "iso:country":"ES",
    "sg:address":"Calle de Tarragona, 4",
    "sg:city":"Binefar",
    "sg:orig_category":"Peluqueros: De Se\u00d1oras",
    "sg:phone":"+34 974 43 08 71",
    "sg:postcode":"22500",
    "sg:province":"Huesca",
    "wof:name":"Peluqueria Lidia S.l.",
    "wof:placetype":"venue"
},
  "geometry": {"coordinates":[0.2919409871,41.8514900208],"type":"Point"}
}