{
  "type": "Feature",
  "properties": {
    "iso:country":"ES",
    "sg:address":"Calle de Casalilla, 3",
    "sg:city":"Priego Cordoba",
    "sg:orig_category":"Arquitectos",
    "sg:phone":"+34 957 70 00 15",
    "sg:postcode":"14800",
    "sg:province":"C\u00f3rdoba",
    "wof:name":"Arutce Arquitectura Y Servicios S.l.",
    "wof:placetype":"venue"
},
  "geometry": {"coordinates":[-4.1952180862,37.4389610291],"type":"Point"}
}