{
  "type": "Feature",
  "properties": {
    "iso:country":"ES",
    "sg:address":"Calle de Eugenio Cavia, 2",
    "sg:city":"Bo\u00f1ar",
    "sg:orig_category":"Asilos De Ancianos. Centros Privados",
    "sg:phone":"+34 987 73 51 14",
    "sg:postcode":"24850",
    "sg:province":"Le\u00f3n",
    "wof:name":"Asociacion De Jubilados Y Pensionistas Porma Mayor",
    "wof:placetype":"venue"
},
  "geometry": {"coordinates":[-5.3225460052,42.8665542603],"type":"Point"}
}