{
  "type": "Feature",
  "properties": {
    "addr:full":"C/ Sant Francesc Xavier, 7 Elche Alicante 03202",
    "addr:housenumber":"7",
    "addr:postcode":"03202",
    "addr:street":"C / Sant Francesc Xavier",
    "iso:country":"ES",
    "sg:address":"C/ Sant Francesc Xavier, 7",
    "sg:city":"Elche",
    "sg:orig_category":"Asesor\u00cda Sobre Comunicaci\u00d3n De Empresas",
    "sg:phone":"+34 965 45 34 43",
    "sg:postcode":"03202",
    "sg:province":"Alicante",
    "wof:name":"Asesoria Falco S.l.",
    "wof:placetype":"venue"
},
  "geometry": {"coordinates":[-0.6958817244,38.2682800293],"type":"Point"}
}