{
  "type": "Feature",
  "properties": {
    "addr:full":"Diseminado El Molino, S/n Salamon Le\u00f3n 24991",
    "addr:housenumber":"s / n",
    "addr:postcode":"24991",
    "addr:street":"Diseminado El Molino;Salamon Leo\u0301N",
    "iso:country":"ES",
    "sg:address":"Diseminado El Molino, S/n",
    "sg:city":"Salamon",
    "sg:orig_category":"Producci\u00d3n, Venta De Productos De Agricultura Biol\u00d3gica",
    "sg:phone":"+34 987 71 08 49",
    "sg:postcode":"24991",
    "sg:province":"Le\u00f3n",
    "wof:name":"El Enebro S.a.",
    "wof:placetype":"venue"
},
  "geometry": {"coordinates":[-5.1487240791,42.9390449524],"type":"Point"}
}