{
  "type": "Feature",
  "properties": {
    "addr:full":"Rua Rosalia De Castro, 82 Burela Lugo 27880",
    "addr:housenumber":"82",
    "addr:postcode":"27880",
    "addr:street":"Rua Rosalia De Castro",
    "iso:country":"ES",
    "sg:address":"Rua Rosalia De Castro, 82",
    "sg:city":"Burela",
    "sg:orig_category":"Caf\u00c9s, Bares, Cervecer\u00cdas",
    "sg:phone":"+34 982 58 15 51",
    "sg:postcode":"27880",
    "sg:province":"Lugo",
    "wof:name":"Veiga Fraga Feliciano",
    "wof:placetype":"venue"
},
  "geometry": {"coordinates":[-7.3616390228,43.6646614075],"type":"Point"}
}