{
  "type": "Feature",
  "properties": {
    "addr:full":"C/ Torre (la), 35 Elche Alicante 03204",
    "addr:housenumber":"35",
    "addr:postcode":"03204",
    "addr:street":"C / Torre La",
    "iso:country":"ES",
    "sg:address":"C/ Torre (la), 35",
    "sg:city":"Elche",
    "sg:orig_category":"Plomeros",
    "sg:phone":"+34 965 46 95 28",
    "sg:postcode":"03204",
    "sg:province":"Alicante",
    "wof:name":"Ferrandez Fullera Jose Ramon",
    "wof:placetype":"venue"
},
  "geometry": {"coordinates":[-0.6698589921,38.2585983276],"type":"Point"}
}