{
  "type": "Feature",
  "properties": {
    "addr:full":"Pg Sant Joan, 51 Barcelona Barcelona 08009",
    "addr:housenumber":"51",
    "addr:postcode":"08009",
    "addr:street":"Pg Sant Joan",
    "iso:country":"ES",
    "sg:address":"Pg Sant Joan, 51",
    "sg:city":"Barcelona",
    "sg:classifiers":[
        {
            "category":"Personal",
            "subcategory":"Barber",
            "type":"Services"
        }
    ],
    "sg:phone":"+34 932 65 43 26",
    "sg:postcode":"08009",
    "sg:province":"Barcelona",
    "sg:tags":[
        "caballeros",
        "de",
        "peluqueros"
    ],
    "wof:name":"Perez Suarez Jorge",
    "wof:placetype":"venue"
},
  "geometry": {"coordinates":[2.1728889942,41.3967399597],"type":"Point"}
}