{
  "type": "Feature",
  "properties": {
    "iso:country":"ES",
    "sg:address":"Calle de Villa De Muro, 10",
    "sg:city":"Valencia",
    "sg:orig_category":"M\u00c1quinas De Escribir, M\u00c1quinas Calculadoras, Maquinaria De Oficina (al Por Menor Y Alquiler)",
    "sg:phone":"+34 963 29 46 70",
    "sg:postcode":"46020",
    "sg:province":"Valencia",
    "wof:name":"Peac Suministros De Ofimatica S.l.",
    "wof:placetype":"venue"
},
  "geometry": {"coordinates":[-0.3616339862,39.4836959839],"type":"Point"}
}