{
  "type": "Feature",
  "properties": {
    "iso:country":"ES",
    "sg:address":"Avda Gudarien Etorbidea, S/n",
    "sg:city":"Andoain",
    "sg:orig_category":"Soldadura, Equipo Y Herramental",
    "sg:phone":"+34 943 59 31 30",
    "sg:postcode":"20140",
    "sg:province":"Guip\u00f9zcoa",
    "wof:name":"Construcciones Metalicas Adarra S.a.l.",
    "wof:placetype":"venue"
},
  "geometry": {"coordinates":[-2.0118739605,43.2246284485],"type":"Point"}
}