{
  "type": "Feature",
  "properties": {
    "addr:full":"Pase Estacion, 2 Torredelcampo Ja\u00e9n 23640",
    "addr:housenumber":"2",
    "addr:postcode":"23640",
    "addr:street":"Estacion;Jae\u0301N",
    "iso:country":"ES",
    "sg:address":"Pase Estacion, 2",
    "sg:city":"Torredelcampo",
    "sg:orig_category":"Bazares, Art\u00cdculos De Limpieza Y De Cocina (al Por Menor)",
    "sg:phone":"+34 953 41 11 87",
    "sg:postcode":"23640",
    "sg:province":"Ja\u00e9n",
    "wof:name":"Martos Rubio Manuel",
    "wof:placetype":"venue"
},
  "geometry": {"coordinates":[-3.897382021,37.7712173462],"type":"Point"}
}