{
  "type": "Feature",
  "properties": {
    "iso:country":"ES",
    "sg:address":"Calle de Almendros, 25",
    "sg:city":"Majadahonda",
    "sg:orig_category":"Inmobiliaria (agencias)",
    "sg:phone":"+34 916 38 52 98",
    "sg:postcode":"28220",
    "sg:province":"Madrid",
    "wof:name":"Inmuebles Patrimoniales S.l.",
    "wof:placetype":"venue"
},
  "geometry": {"coordinates":[-3.8558101654,40.477432251],"type":"Point"}
}