{
  "type": "Feature",
  "properties": {
    "iso:country":"ES",
    "sg:address":"Pda. Eres, S/n",
    "sg:city":"Torres Segre",
    "sg:orig_category":"Agricultores, Agricultores",
    "sg:phone":"+34 973 79 63 48",
    "sg:postcode":"25170",
    "sg:province":"Lleida",
    "wof:name":"Aldavert Marselles Gaspar",
    "wof:placetype":"venue"
},
  "geometry": {"coordinates":[0.6257824898,41.614151001],"type":"Point"}
}