{
  "type": "Feature",
  "properties": {
    "iso:country":"ES",
    "sg:address":"Alagon, 3",
    "sg:city":"Bejar",
    "sg:orig_category":"Arreglo, Reparaci\u00d3n, Piezas Sueltas De Televisi\u00d3n, V\u00cddeo, Hi",
    "sg:phone":"+34 923 40 25 19",
    "sg:postcode":"37700",
    "sg:province":"Salamanca",
    "wof:name":"Belloso Elices Gumersindo",
    "wof:placetype":"venue"
},
  "geometry": {"coordinates":[-5.7558398247,40.3867797852],"type":"Point"}
}