{
  "type": "Feature",
  "properties": {
    "addr:full":"Avda Valladolid, S/n S. Esteban Gormaz Soria 42330",
    "addr:postcode":"42330",
    "addr:street":"Avda Valladolid S / N S. Esteban Gormaz",
    "iso:country":"ES",
    "sg:address":"Avda Valladolid, S/n",
    "sg:city":"S. Esteban Gormaz",
    "sg:orig_category":"Organizaciones Internacionales",
    "sg:phone":"+34 975 35 01 26",
    "sg:postcode":"42330",
    "sg:province":"Soria",
    "wof:name":"Cruz Roja Espa\u00f1ola",
    "wof:placetype":"venue"
},
  "geometry": {"coordinates":[-3.2036440372,41.5728988647],"type":"Point"}
}