{
  "type": "Feature",
  "properties": {
    "addr:full":"Calle de Doctor J.j. Domine, 7 Valencia Valencia 46011",
    "addr:housenumber":"7",
    "addr:postcode":"46011",
    "addr:street":"Calle De Doctor J.J. Domine",
    "iso:country":"ES",
    "sg:address":"Calle de Doctor J.j. Domine, 7",
    "sg:city":"Valencia",
    "sg:orig_category":"Promotores Constructores",
    "sg:phone":"+34 963 67 11 94",
    "sg:postcode":"46011",
    "sg:province":"Valencia",
    "wof:name":"Construcciones Y Estudios S.a.",
    "wof:placetype":"venue"
},
  "geometry": {"coordinates":[-0.3324263096,39.4611473083],"type":"Point"}
}