{
  "type": "Feature",
  "properties": {
    "addr:full":"Calle de Buen Pastor, 4 Bilbao Vizcaya 48007",
    "addr:housenumber":"4",
    "addr:postcode":"48007",
    "addr:street":"Calle De Buen Pastor",
    "iso:country":"ES",
    "sg:address":"Calle de Buen Pastor, 4",
    "sg:city":"Bilbao",
    "sg:orig_category":"Metalurgia",
    "sg:phone":"+34 944 45 61 44",
    "sg:postcode":"48007",
    "sg:province":"Vizcaya",
    "wof:name":"Muelles Y Aceros Bilbainos S. A.",
    "wof:placetype":"venue"
},
  "geometry": {"coordinates":[-2.9766151905,43.2902412415],"type":"Point"}
}