{
  "type": "Feature",
  "properties": {
    "addr:full":"Calle de Eugenio Ubeda, 3 Santiago Murcia 30800",
    "addr:housenumber":"3",
    "addr:postcode":"30800",
    "addr:street":"Calle De Eugenio Ubeda",
    "iso:country":"ES",
    "sg:address":"Calle de Eugenio Ubeda, 3",
    "sg:city":"Santiago",
    "sg:orig_category":"Peluquer\u00cdas, Peluquer\u00cda Mixta",
    "sg:phone":"+34 968 47 04 82",
    "sg:postcode":"30800",
    "sg:province":"Murcia",
    "wof:name":"Jimenez Romera Maria Del Carmen",
    "wof:placetype":"venue"
},
  "geometry": {"coordinates":[-1.6905640364,37.680557251],"type":"Point"}
}