{
  "type": "Feature",
  "properties": {
    "addr:full":"Carr Maestro Serrano, 14 Manises Valencia 46940",
    "addr:housenumber":"14",
    "addr:postcode":"46940",
    "addr:street":"Carr Maestro Serrano",
    "iso:country":"ES",
    "sg:address":"Carr Maestro Serrano, 14",
    "sg:city":"Manises",
    "sg:orig_category":"Art\u00cdculos De Decoraci\u00d3n (fabricaci\u00d3n Y Al Por Mayor)",
    "sg:phone":"+34 961 54 24 27",
    "sg:postcode":"46940",
    "sg:province":"Valencia",
    "wof:name":"Josecer S.l.",
    "wof:placetype":"venue"
},
  "geometry": {"coordinates":[-0.4653765857,39.4903335571],"type":"Point"}
}