{
  "type": "Feature",
  "properties": {
    "iso:country":"ES",
    "sg:address":"Calle de Garcia De Paredes, 66",
    "sg:city":"Madrid",
    "sg:orig_category":"Administradores De Bienes Y Delegados De Comunidades De Propietarios",
    "sg:phone":"+34 914 45 50 03",
    "sg:postcode":"28010",
    "sg:province":"Madrid",
    "wof:name":"Muro Velaz Jose",
    "wof:placetype":"venue"
},
  "geometry": {"coordinates":[-3.6955471039,40.4366455078],"type":"Point"}
}