{
  "type": "Feature",
  "properties": {
    "iso:country":"ES",
    "sg:address":"Avda Menceyes (los), 24",
    "sg:city":"Gracia",
    "sg:orig_category":"Congelados: Productos Alimentarios (fabricaci\u00d3n, Al Por Mayor)",
    "sg:phone":"+34 922 82 50 10",
    "sg:postcode":"38295",
    "sg:province":"Santa Cruz De Tenerife",
    "wof:name":"Distribuciones Frionorte S.a.",
    "wof:placetype":"venue"
},
  "geometry": {"coordinates":[-16.3025226593,28.4732723236],"type":"Point"}
}