{
  "type": "Feature",
  "properties": {
    "addr:full":"Carrer de Valencia, 392 Barcelona Barcelona 08013",
    "addr:housenumber":"392",
    "addr:postcode":"08013",
    "addr:street":"Carrer De Valencia",
    "iso:country":"ES",
    "sg:address":"Carrer de Valencia, 392",
    "sg:city":"Barcelona",
    "sg:orig_category":"Peluquer\u00cdas, Peluquer\u00cda Mixta",
    "sg:phone":"+34 934 57 63 67",
    "sg:postcode":"08013",
    "sg:province":"Barcelona",
    "wof:name":"Lara Lasalvia Ana Maria",
    "wof:placetype":"venue"
},
  "geometry": {"coordinates":[2.1742589474,41.4007301331],"type":"Point"}
}