{
  "type": "Feature",
  "properties": {
    "addr:full":"Rua Lagoa, 45 Carballo La Coru\u00f1a 15100",
    "addr:housenumber":"45",
    "addr:postcode":"15100",
    "addr:street":"Rua Lagoa;La Corun\u0303A",
    "iso:country":"ES",
    "sg:address":"Rua Lagoa, 45",
    "sg:city":"Carballo",
    "sg:orig_category":"Reposter\u00cdas",
    "sg:phone":"+34 981 70 07 12",
    "sg:postcode":"15100",
    "sg:province":"La Coru\u00f1a",
    "wof:name":"Pazos Mesejo Ana Maria",
    "wof:placetype":"venue"
},
  "geometry": {"coordinates":[-8.6882839203,43.2114448547],"type":"Point"}
}