{
  "type": "Feature",
  "properties": {
    "iso:country":"ES",
    "sg:address":"Rua Gerona, 8",
    "sg:city":"Vigo",
    "sg:orig_category":"Promotores Constructores",
    "sg:phone":"+34 986 29 83 65",
    "sg:postcode":"36211",
    "sg:province":"Pontevedra",
    "sg:website":"www.vialmar.es",
    "wof:name":"Vialmar S.a.",
    "wof:placetype":"venue"
},
  "geometry": {"coordinates":[-8.7299690247,42.2223892212],"type":"Point"}
}