{
  "type": "Feature",
  "properties": {
    "iso:country":"ES",
    "sg:address":"Rua Amado Carballo, S/n",
    "sg:city":"Pontevedra",
    "sg:orig_category":"Iglesia Cat\u00d3lica",
    "sg:phone":"+34 986 85 24 98",
    "sg:postcode":"36002",
    "sg:province":"Pontevedra",
    "wof:name":"Parroquia Virgen Del Camino",
    "wof:placetype":"venue"
},
  "geometry": {"coordinates":[-8.6345081329,42.4293479919],"type":"Point"}
}