{
  "type": "Feature",
  "properties": {
    "addr:full":"Calle de Cordon, 6 Castrojeriz Burgos 09110",
    "addr:housenumber":"6",
    "addr:postcode":"09110",
    "addr:street":"Calle De Cordon",
    "iso:country":"ES",
    "sg:address":"Calle de Cordon, 6",
    "sg:city":"Castrojeriz",
    "sg:orig_category":"Asesor\u00cda Fiscal Y Jur\u00cddica",
    "sg:phone":"+34 947 37 85 45",
    "sg:postcode":"09110",
    "sg:province":"Burgos",
    "wof:name":"Bermejo Cavia Jorge Alfredo",
    "wof:placetype":"venue"
},
  "geometry": {"coordinates":[-4.1414780617,42.2887077332],"type":"Point"}
}