{
  "type": "Feature",
  "properties": {
    "iso:country":"ES",
    "sg:address":"Calle de Mendez Nu\u00d1ez, 14",
    "sg:city":"Almeria",
    "sg:orig_category":"Ropa Para Se\u00d1oras Y Caballeros (al Por Menor)",
    "sg:phone":"+34 950 23 27 57",
    "sg:postcode":"04001",
    "sg:province":"Almer\u00eda",
    "wof:name":"Perez Ruiz Gines",
    "wof:placetype":"venue"
},
  "geometry": {"coordinates":[-2.4621219635,36.8387832642],"type":"Point"}
}