{
  "type": "Feature",
  "properties": {
    "iso:country":"ES",
    "sg:address":"Calle de Pe\u00d1uelas, S/n",
    "sg:city":"Villalba Rey",
    "sg:orig_category":"Alimentaci\u00d3n General (al Por Menor)",
    "sg:phone":"+34 969 37 00 24",
    "sg:postcode":"16535",
    "sg:province":"Cuenca",
    "wof:name":"Bello Falcon Alfredo",
    "wof:placetype":"venue"
},
  "geometry": {"coordinates":[-2.6399059296,40.3442726135],"type":"Point"}
}