{
  "type": "Feature",
  "properties": {
    "iso:country":"ES",
    "sg:address":"Calle de Urrestieta, 8",
    "sg:city":"Sodupe",
    "sg:orig_category":"Perfumer\u00cda Y Cosm\u00c9tica (fabricaci\u00d3n, Al Por Mayor)",
    "sg:phone":"+34 946 69 21 77",
    "sg:postcode":"48830",
    "sg:province":"Vizcaya",
    "wof:name":"Albizu Moreno Jose Angel",
    "wof:placetype":"venue"
},
  "geometry": {"coordinates":[-3.0513532162,43.2015914917],"type":"Point"}
}