{
  "type": "Feature",
  "properties": {
    "iso:country":"ES",
    "sg:address":"Calle de San Pedro De Mestallon, 8",
    "sg:city":"Oviedo",
    "sg:orig_category":"Guarder\u00cdas",
    "sg:phone":"+34 985 20 22 65",
    "sg:postcode":"33009",
    "sg:province":"Asturias",
    "wof:name":"Martinez Diaz Covadonga",
    "wof:placetype":"venue"
},
  "geometry": {"coordinates":[-5.8405351639,43.3582229614],"type":"Point"}
}