{
  "type": "Feature",
  "properties": {
    "addr:full":"Carrer de Luxemburg, 11 Rubi Barcelona 08191",
    "addr:housenumber":"11",
    "addr:postcode":"08191",
    "addr:street":"Carrer De Luxemburg",
    "iso:country":"ES",
    "sg:address":"Carrer de Luxemburg, 11",
    "sg:city":"Rubi",
    "sg:orig_category":"Garajes De Veh\u00cdculos",
    "sg:phone":"+34 935 86 27 27",
    "sg:postcode":"08191",
    "sg:province":"Barcelona",
    "sg:website":"www.rema-tiptop.es",
    "wof:name":"Rema Tip Top Iberica S.a.",
    "wof:placetype":"venue"
},
  "geometry": {"coordinates":[2.0274920464,41.4815216064],"type":"Point"}
}