{
  "type": "Feature",
  "properties": {
    "addr:full":"Calle de Jose Luis Borau, 15 Zaragoza Zaragoza 50018",
    "addr:housenumber":"15",
    "addr:postcode":"50018",
    "addr:street":"Calle De Jose Luis Borau",
    "iso:country":"ES",
    "sg:address":"Calle de Jose Luis Borau, 15",
    "sg:city":"Zaragoza",
    "sg:orig_category":"Fabricaci\u00d3n, Instalaci\u00d3n Y Reparaci\u00d3n De Bombas",
    "sg:phone":"+34 976 51 54 40",
    "sg:postcode":"50018",
    "sg:province":"Zaragoza",
    "wof:name":"Aracom S. A.",
    "wof:placetype":"venue"
},
  "geometry": {"coordinates":[-0.8851745129,41.6751899719],"type":"Point"}
}