{
  "type": "Feature",
  "properties": {
    "addr:full":"Carrer de Madrazo, 129 Barcelona Barcelona 08021",
    "addr:housenumber":"129",
    "addr:postcode":"08021",
    "addr:street":"Carrer De Madrazo",
    "iso:country":"ES",
    "sg:address":"Carrer de Madrazo, 129",
    "sg:city":"Barcelona",
    "sg:orig_category":"Centros M\u00c9dicos Y Sociales, Dispensarios",
    "sg:phone":"+34 934 14 69 07",
    "sg:postcode":"08021",
    "sg:province":"Barcelona",
    "wof:name":"Roldan Bornez Ana Maria",
    "wof:placetype":"venue"
},
  "geometry": {"coordinates":[2.1447789669,41.3968544006],"type":"Point"}
}