{
  "type": "Feature",
  "properties": {
    "addr:full":"Carrer de Vallet, S/n Pego Alicante 03780",
    "addr:housenumber":"s / n",
    "addr:postcode":"03780",
    "addr:street":"Carrer De Vallet",
    "iso:country":"ES",
    "sg:address":"Carrer de Vallet, S/n",
    "sg:city":"Pego",
    "sg:orig_category":"Pistas Y Clases De Tenis",
    "sg:phone":"+34 965 57 03 65",
    "sg:postcode":"03780",
    "sg:province":"Alicante",
    "wof:name":"Sala Vilanova Jose Manuel",
    "wof:placetype":"venue"
},
  "geometry": {"coordinates":[-0.1172289997,38.842010498],"type":"Point"}
}