{
  "type": "Feature",
  "properties": {
    "addr:full":"Carrer de Arago, 273 Barcelona Barcelona 08...",
    "addr:housenumber":"273",
    "addr:street":"Carrer De Arago",
    "iso:country":"ES",
    "sg:address":"Carrer de Arago, 273",
    "sg:city":"Barcelona",
    "sg:orig_category":"Ense\u00d1anza, Formaci\u00d3n Profesional: Aprendizaje",
    "sg:phone":"+34 932 16 59 00",
    "sg:postcode":"08...",
    "sg:province":"Barcelona",
    "sg:website":"www.seg-social.es",
    "wof:name":"Tesoreria General De La Seguridad Social-servicios Centrales",
    "wof:placetype":"venue"
},
  "geometry": {"coordinates":[2.1655631065,41.3928794861],"type":"Point"}
}