{
  "type": "Feature",
  "properties": {
    "addr:full":"Av Baro D'esponella, 13 Almacelles Lleida 25100",
    "addr:housenumber":"13",
    "addr:postcode":"25100",
    "addr:street":"Av Baro D'Esponella",
    "iso:country":"ES",
    "sg:address":"Av Baro D'esponella, 13",
    "sg:city":"Almacelles",
    "sg:orig_category":"Supermercados Y Hipermercados",
    "sg:phone":"+34 973 74 15 68",
    "sg:postcode":"25100",
    "sg:province":"Lleida",
    "wof:name":"Supermercados Pujol S.a.",
    "wof:placetype":"venue"
},
  "geometry": {"coordinates":[0.4409739971,41.7298355103],"type":"Point"}
}