{
  "type": "Feature",
  "properties": {
    "addr:full":"Urb Coblanca, 37 Coblanca Alicante 03500",
    "addr:housenumber":"37",
    "addr:postcode":"03500",
    "addr:street":"Urb Coblanca;Alicante",
    "iso:country":"ES",
    "sg:address":"Urb Coblanca, 37",
    "sg:city":"Coblanca",
    "sg:orig_category":"Inmobiliaria (agencias)",
    "sg:phone":"+34 966 80 77 87",
    "sg:postcode":"03500",
    "sg:province":"Alicante",
    "wof:name":"Wendy And Roy S.l.",
    "wof:placetype":"venue"
},
  "geometry": {"coordinates":[-0.4810059965,38.3452033997],"type":"Point"}
}