{
  "type": "Feature",
  "properties": {
    "addr:full":"Paiosaco, S/n Laracha La Coru\u00f1a 15145",
    "addr:housenumber":"s / n",
    "addr:postcode":"15145",
    "addr:street":"Paiosaco;La Corun\u0303A",
    "iso:country":"ES",
    "sg:address":"Paiosaco, S/n",
    "sg:city":"Laracha",
    "sg:orig_category":"Quincaller\u00cda (al Por Menor)",
    "sg:phone":"+34 981 60 51 78",
    "sg:postcode":"15145",
    "sg:province":"La Coru\u00f1a",
    "wof:name":"Angeriz Suarez Mercedes",
    "wof:placetype":"venue"
},
  "geometry": {"coordinates":[-8.5502700806,43.2565727234],"type":"Point"}
}