{
  "type": "Feature",
  "properties": {
    "addr:full":"Ctra. Alcorcon-plasencia, S/n Sotillo Adrada \u00c1vila 05420",
    "addr:housenumber":"s",
    "addr:postcode":"05420",
    "addr:street":"Ctra. Alcorcon-Plasencia;/ N Sotillo;A\u0301Vila",
    "iso:country":"ES",
    "sg:address":"Ctra. Alcorcon-plasencia, S/n",
    "sg:city":"Sotillo Adrada",
    "sg:orig_category":"Mec\u00c1nico Del Autom\u00d3vil",
    "sg:phone":"+34 918 66 02 14",
    "sg:postcode":"05420",
    "sg:province":"\u00c1vila",
    "wof:name":"Jaimari Sotillo S. L.",
    "wof:placetype":"venue"
},
  "geometry": {"coordinates":[-4.5898241997,40.2908287048],"type":"Point"}
}