{
  "type": "Feature",
  "properties": {
    "iso:country":"ES",
    "sg:address":"Calle de Doctor Gamero, 84",
    "sg:city":"Arahal",
    "sg:orig_category":"Alimentaci\u00d3n General (al Por Menor)",
    "sg:phone":"+34 954 84 09 68",
    "sg:postcode":"41600",
    "sg:province":"Sevilla",
    "wof:name":"Oliva Blanco Jose Manuel",
    "wof:placetype":"venue"
},
  "geometry": {"coordinates":[-5.5493984222,37.2613487244],"type":"Point"}
}