{
  "type": "Feature",
  "properties": {
    "addr:full":"Calle de Casi\u00d1as, 3 Sobrado A Coru\u00f1a 15813",
    "addr:housenumber":"3",
    "addr:postcode":"15813",
    "addr:street":"Calle De Casin\u0303As;Corun\u0303A",
    "iso:country":"ES",
    "sg:address":"Calle de Casi\u00d1as, 3",
    "sg:city":"Sobrado",
    "sg:orig_category":"Material Y Suministros Para Veterinarios",
    "sg:phone":"+34 981 78 77 91",
    "sg:postcode":"15813",
    "sg:province":"A Coru\u00f1a",
    "wof:name":"Veterinaria Coru\u00f1esa S.l.",
    "wof:placetype":"venue"
},
  "geometry": {"coordinates":[-8.0220422745,43.0429534912],"type":"Point"}
}