{
  "type": "Feature",
  "properties": {
    "iso:country":"ES",
    "sg:address":"Calle de Calvario, 13",
    "sg:city":"Ajalvir",
    "sg:orig_category":"Perfumer\u00cda Y Cosm\u00c9tica (fabricaci\u00d3n, Al Por Mayor)",
    "sg:phone":"+34 918 84 30 85",
    "sg:postcode":"28864",
    "sg:province":"Madrid",
    "wof:name":"Verniglass Espa\u00f1a S.l",
    "wof:placetype":"venue"
},
  "geometry": {"coordinates":[-3.4860069752,40.5331077576],"type":"Point"}
}