{
  "type": "Feature",
  "properties": {
    "iso:country":"ES",
    "sg:address":"Urb Canyera, S/n",
    "sg:city":"Canyera",
    "sg:orig_category":"Cojinetes De Bolas, Agujas Y Rodillos (fabricaci\u00d3n, Al Por Mayor)",
    "sg:phone":"+34 972 83 07 04",
    "sg:postcode":"17240",
    "sg:province":"Girona",
    "wof:name":"Soler Sanchez Sergio",
    "wof:placetype":"venue"
},
  "geometry": {"coordinates":[2.892385006,41.8299255371],"type":"Point"}
}