{
  "type": "Feature",
  "properties": {
    "addr:full":"Plaz Saralegi, 2 Bilbao Vizcaya 48003",
    "addr:housenumber":"2",
    "addr:postcode":"48003",
    "addr:street":"Plaz Saralegi",
    "iso:country":"ES",
    "sg:address":"Plaz Saralegi, 2",
    "sg:city":"Bilbao",
    "sg:orig_category":"Ense\u00d1anza, Formaci\u00d3n Profesional: Aprendizaje",
    "sg:phone":"+34 944 15 08 41",
    "sg:postcode":"48003",
    "sg:province":"Vizcaya",
    "wof:name":"Gobierno Vasco-eusko Jaurlaritza",
    "wof:placetype":"venue"
},
  "geometry": {"coordinates":[-2.9250490665,43.2430305481],"type":"Point"}
}