{
  "type": "Feature",
  "properties": {
    "addr:full":"Calle de Pamplona, 12 Roquetas Mar Almer\u00eda 04740",
    "addr:housenumber":"12",
    "addr:postcode":"04740",
    "addr:street":"Calle De Pamplona",
    "iso:country":"ES",
    "sg:address":"Calle de Pamplona, 12",
    "sg:city":"Roquetas Mar",
    "sg:orig_category":"Supermercados Y Hipermercados",
    "sg:phone":"+34 950 32 17 78",
    "sg:postcode":"04740",
    "sg:province":"Almer\u00eda",
    "wof:name":"Marin Garcia Andres",
    "wof:placetype":"venue"
},
  "geometry": {"coordinates":[-2.6130890846,36.7608184814],"type":"Point"}
}