{
  "type": "Feature",
  "properties": {
    "addr:full":"Calle de Santo Domingo, 3 Aranda Duero Burgos 09400",
    "addr:housenumber":"3",
    "addr:postcode":"09400",
    "addr:street":"Calle De Santo Domingo",
    "iso:country":"ES",
    "sg:address":"Calle de Santo Domingo, 3",
    "sg:city":"Aranda Duero",
    "sg:orig_category":"Extinci\u00d3n De Incendios: Material Y Suministros (fabricaci\u00d3n, Al Por Mayor)",
    "sg:phone":"+34 947 51 04 61",
    "sg:postcode":"09400",
    "sg:province":"Burgos",
    "wof:name":"Pizarro Ramos Comercial De Seguridad S.l.",
    "wof:placetype":"venue"
},
  "geometry": {"coordinates":[-3.6915380955,41.6686553955],"type":"Point"}
}