{
  "type": "Feature",
  "properties": {
    "addr:full":"Monasterio Irache, 34 Iru\u00f1a Navarra 31011",
    "addr:housenumber":"34",
    "addr:postcode":"31011",
    "addr:street":"Irache",
    "iso:country":"ES",
    "sg:address":"Monasterio Irache, 34",
    "sg:city":"Iru\u00f1a",
    "sg:orig_category":"Fabricaci\u00d3n De Muebles De Cocina",
    "sg:phone":"+34 948 27 53 54",
    "sg:postcode":"31011",
    "sg:province":"Navarra",
    "wof:name":"Biltoki S. A.",
    "wof:placetype":"venue"
},
  "geometry": {"coordinates":[-1.6621700525,42.8165779114],"type":"Point"}
}