{
  "type": "Feature",
  "properties": {
    "iso:country":"ES",
    "sg:address":"Los Cercados, 129",
    "sg:city":"Victoria Acentejo",
    "sg:orig_category":"Empresas De Carpinter\u00cda De Madera",
    "sg:phone":"+34 922 58 03 14",
    "sg:postcode":"38380",
    "sg:province":"Santa Cruz De Tenerife",
    "wof:name":"Ramos Gonzalez Juan",
    "wof:placetype":"venue"
},
  "geometry": {"coordinates":[-16.4657344818,28.4353294373],"type":"Point"}
}