{
  "type": "Feature",
  "properties": {
    "addr:full":"Casti\u00f1eiras(pol Ind Milladoiro), 110 Milladoiro La Coru\u00f1a 15895",
    "addr:housenumber":"110",
    "addr:postcode":"15895",
    "addr:street":"Milladoiro La Corun\u0303A",
    "iso:country":"ES",
    "sg:address":"Casti\u00f1eiras(pol Ind Milladoiro), 110",
    "sg:city":"Milladoiro",
    "sg:orig_category":"Asesor\u00cda Sobre Comunicaci\u00d3n De Empresas",
    "sg:phone":"+34 981 53 84 65",
    "sg:postcode":"15895",
    "sg:province":"La Coru\u00f1a",
    "wof:name":"Eurocontrol S.a.",
    "wof:placetype":"venue"
},
  "geometry": {"coordinates":[-8.5848693848,42.8517913818],"type":"Point"}
}