{
  "type": "Feature",
  "properties": {
    "addr:full":"Calle de Prevision (la), S/n Cordoba C\u00f3rdoba 14004",
    "addr:postcode":"14004",
    "addr:street":"Calle De Prevision La S / N;Co\u0301Rdoba",
    "iso:country":"ES",
    "sg:address":"Calle de Prevision (la), S/n",
    "sg:city":"Cordoba",
    "sg:orig_category":"Zapatos (al Por Menor)",
    "sg:phone":"+34 957 45 23 29",
    "sg:postcode":"14004",
    "sg:province":"C\u00f3rdoba",
    "wof:name":"Gutierrez Noguerol Alfonso",
    "wof:placetype":"venue"
},
  "geometry": {"coordinates":[-4.7918639183,37.8787651062],"type":"Point"}
}