{
  "type": "Feature",
  "properties": {
    "addr:full":"Afores, S/n Palamos Girona 17230",
    "addr:housenumber":"s / n",
    "addr:postcode":"17230",
    "addr:street":"Afores",
    "iso:country":"ES",
    "sg:address":"Afores, S/n",
    "sg:city":"Palamos",
    "sg:orig_category":"Supermercados Y Hipermercados",
    "sg:phone":"+34 972 60 24 11",
    "sg:postcode":"17230",
    "sg:province":"Girona",
    "wof:name":"Pal Beach Gestio S.a.",
    "wof:placetype":"venue"
},
  "geometry": {"coordinates":[3.1279499531,41.8473548889],"type":"Point"}
}