{
  "type": "Feature",
  "properties": {
    "iso:country":"ES",
    "sg:address":"Estd Nacional 525, Km. 0530,0",
    "sg:city":"San Cibrao Das Vi\u00e7as",
    "sg:orig_category":"Delegados, Agentes De Tr\u00c1nsito, Auxiliares De Transporte Internacional",
    "sg:phone":"+34 988 24 10 24",
    "sg:postcode":"32911",
    "sg:province":"Ourense",
    "wof:name":"Transdrako S.l",
    "wof:placetype":"venue"
},
  "geometry": {"coordinates":[-7.872358799,42.2972106934],"type":"Point"}
}