{
  "type": "Feature",
  "properties": {
    "iso:country":"ES",
    "sg:address":"La Pesquera, S/n",
    "sg:city":"Laredo",
    "sg:orig_category":"Rectificaci\u00d3n, Mecanizado, Fresado",
    "sg:phone":"+34 942 61 07 75",
    "sg:postcode":"39770",
    "sg:province":"Cantabria",
    "wof:name":"Sucesores De A.g.c. S.l.",
    "wof:placetype":"venue"
},
  "geometry": {"coordinates":[-3.4341549873,43.4056358337],"type":"Point"}
}