{
  "type": "Feature",
  "properties": {
    "iso:country":"ES",
    "sg:address":"Plaz Andalucia, 1",
    "sg:city":"Montellano",
    "sg:orig_category":"Cajas Para Embalar",
    "sg:phone":"+34 954 87 52 97",
    "sg:postcode":"41770",
    "sg:province":"Sevilla",
    "wof:name":"Caja Rural Del Sur Sociedad Cooperativa",
    "wof:placetype":"venue"
},
  "geometry": {"coordinates":[-5.5730772018,36.994846344],"type":"Point"}
}