{
  "type": "Feature",
  "properties": {
    "addr:full":"Pg Paisos Catalans, 230 Salt Girona 17190",
    "addr:housenumber":"230",
    "addr:postcode":"17190",
    "addr:street":"Pg Paisos Catalans",
    "iso:country":"ES",
    "sg:address":"Pg Paisos Catalans, 230",
    "sg:city":"Salt",
    "sg:orig_category":"Promotores Constructores",
    "sg:phone":"+34 972 24 39 11",
    "sg:postcode":"17190",
    "sg:province":"Girona",
    "wof:name":"Construccions El Girones S. A.",
    "wof:placetype":"venue"
},
  "geometry": {"coordinates":[2.7968149185,41.9733505249],"type":"Point"}
}