{
  "type": "Feature",
  "properties": {
    "addr:full":"Carr Josep Zulueta, 22 Seu D'urgell Lleida 25700",
    "addr:housenumber":"22",
    "addr:postcode":"25700",
    "addr:street":"Carr Josep Zulueta",
    "iso:country":"ES",
    "sg:address":"Carr Josep Zulueta, 22",
    "sg:city":"Seu D'urgell",
    "sg:classifiers":[
        {
            "category":"Taxi",
            "type":"Transportation"
        }
    ],
    "sg:phone":"+34 973 35 07 11",
    "sg:postcode":"25700",
    "sg:province":"Lleida",
    "wof:name":"Ramos Peque\u00f1o Carlos",
    "wof:placetype":"venue"
},
  "geometry": {"coordinates":[0.6457189918,41.6027946472],"type":"Point"}
}