{
  "type": "Feature",
  "properties": {
    "addr:full":"Avda Alcarria (de La), 13 Azuqueca Henares Guadalajara 19200",
    "addr:housenumber":"13",
    "addr:postcode":"19200",
    "addr:street":"Avda Alcarria De La",
    "iso:country":"ES",
    "sg:address":"Avda Alcarria (de La), 13",
    "sg:city":"Azuqueca Henares",
    "sg:orig_category":"Servicios De Telecomunicaciones",
    "sg:phone":"+34 949 88 30 37",
    "sg:postcode":"19200",
    "sg:province":"Guadalajara",
    "wof:name":"Ericcson Espa\u00d1a S.a.",
    "wof:placetype":"venue"
},
  "geometry": {"coordinates":[-3.2627639771,40.5669708252],"type":"Point"}
}