{
  "type": "Feature",
  "properties": {
    "iso:country":"ES",
    "sg:address":"Carr Coll I Pujol, 198",
    "sg:city":"Badalona",
    "sg:orig_category":"Ropa Para Se\u00d1oras Y Caballeros (al Por Menor)",
    "sg:phone":"+34 933 87 24 90",
    "sg:postcode":"08917",
    "sg:province":"Barcelona",
    "wof:name":"Mora\u00f1a Reyes Daniel",
    "wof:placetype":"venue"
},
  "geometry": {"coordinates":[2.2369730473,41.4534835815],"type":"Point"}
}