{
  "type": "Feature",
  "properties": {
    "iso:country":"ES",
    "sg:address":"Plaz San Vicente Ferrer, 16",
    "sg:city":"Valencia",
    "sg:classifiers":[
        {
            "category":"Banks & Credit Unions",
            "subcategory":"Bureau De Change",
            "type":"Services"
        }
    ],
    "sg:phone":"+34 963 15 20 46",
    "sg:postcode":"46003",
    "sg:province":"Valencia",
    "sg:tags":[
        "organismos",
        "control"
    ],
    "sg:website":"www.inteinco.es",
    "wof:name":"Inteinco S.a.",
    "wof:placetype":"venue"
},
  "geometry": {"coordinates":[-0.3723990023,39.4738197327],"type":"Point"}
}