{
  "type": "Feature",
  "properties": {
    "iso:country":"ES",
    "sg:address":"Jose Mu\u00f1oz (p I Dos Octubre), 5",
    "sg:city":"Santa Fe",
    "sg:orig_category":"Rectificaci\u00d3n, Mecanizado, Fresado",
    "sg:phone":"+34 958 51 07 65",
    "sg:postcode":"18320",
    "sg:province":"Granada",
    "wof:name":"Ingenieria Maquinaria Y Produccion Cloner S.l.",
    "wof:placetype":"venue"
},
  "geometry": {"coordinates":[-3.7299690247,37.1925697327],"type":"Point"}
}