{
  "type": "Feature",
  "properties": {
    "addr:full":"Av Catalunya, 82 Alcanar Tarragona 43530",
    "addr:housenumber":"82",
    "addr:postcode":"43530",
    "addr:street":"Av Catalunya",
    "iso:country":"ES",
    "sg:address":"Av Catalunya, 82",
    "sg:city":"Alcanar",
    "sg:orig_category":"Maquinaria Para Industrias Diversas",
    "sg:phone":"+34 977 73 01 33",
    "sg:postcode":"43530",
    "sg:province":"Tarragona",
    "wof:name":"Royo Agustin Victor",
    "wof:placetype":"venue"
},
  "geometry": {"coordinates":[0.482565999,40.5417633057],"type":"Point"}
}