{
  "type": "Feature",
  "properties": {
    "iso:country":"ES",
    "sg:address":"Ctra. Estacion, 46",
    "sg:city":"Sarracin Aliste",
    "sg:orig_category":"Asociaciones, Organismos Culturales Y Socioeducativos",
    "sg:phone":"+34 980 59 47 83",
    "sg:postcode":"49591",
    "sg:province":"Zamora",
    "wof:name":"Moran Blanco Juan",
    "wof:placetype":"venue"
},
  "geometry": {"coordinates":[-6.189016819,41.8408737183],"type":"Point"}
}