{
  "type": "Feature",
  "properties": {
    "addr:full":"Carr Goya, (de), 14 Carlet Valencia 46240",
    "addr:housenumber":"14",
    "addr:postcode":"46240",
    "addr:street":"Carr Goya De",
    "iso:country":"ES",
    "sg:address":"Carr Goya, (de), 14",
    "sg:city":"Carlet",
    "sg:orig_category":"Peluquer\u00cdas, Peluquer\u00cda Mixta",
    "sg:phone":"+34 962 53 30 39",
    "sg:postcode":"46240",
    "sg:province":"Valencia",
    "wof:name":"Martinez Javier Ana Maria",
    "wof:placetype":"venue"
},
  "geometry": {"coordinates":[-0.5209739804,39.2250289917],"type":"Point"}
}