{
  "type": "Feature",
  "properties": {
    "addr:full":"Carrer de Sogorb, S/n Manlleu Barcelona 08560",
    "addr:housenumber":"s / n",
    "addr:postcode":"08560",
    "addr:street":"Carrer De Sogorb",
    "iso:country":"ES",
    "sg:address":"Carrer de Sogorb, S/n",
    "sg:city":"Manlleu",
    "sg:orig_category":"Fabricaci\u00d3n De Moldes Y Modelos",
    "sg:phone":"+34 938 51 26 85",
    "sg:postcode":"08560",
    "sg:province":"Barcelona",
    "wof:name":"Fontarnau Prat Jaime",
    "wof:placetype":"venue"
},
  "geometry": {"coordinates":[2.2885000706,42.0061950684],"type":"Point"}
}