{
  "type": "Feature",
  "properties": {
    "addr:full":"Seber Altube Plaza, 7 Arrasate Guip\u00f9zcoa 20500",
    "addr:housenumber":"7",
    "addr:postcode":"20500",
    "addr:street":"Seber Altube Plaza;Guipu\u0300Zcoa",
    "iso:country":"ES",
    "sg:address":"Seber Altube Plaza, 7",
    "sg:city":"Arrasate",
    "sg:orig_category":"Alquiler De V\u00cddeo",
    "sg:phone":"+34 943 71 27 37",
    "sg:postcode":"20500",
    "sg:province":"Guip\u00f9zcoa",
    "wof:name":"Video Club Musakola S.l.u.",
    "wof:placetype":"venue"
},
  "geometry": {"coordinates":[-2.4884469509,43.0665969849],"type":"Point"}
}