{
  "type": "Feature",
  "properties": {
    "addr:full":"Carrer de Clave, 7 Ulldecona Tarragona 43550",
    "addr:postcode":"43550",
    "addr:street":"Carrer De Clave 7",
    "iso:country":"ES",
    "sg:address":"Carrer de Clave, 7",
    "sg:city":"Ulldecona",
    "sg:orig_category":"Productores Recolectores, Venta Directa De Vinos",
    "sg:phone":"+34 977 72 03 34",
    "sg:postcode":"43550",
    "sg:province":"Tarragona",
    "wof:name":"Pomada Domenech Javier",
    "wof:placetype":"venue"
},
  "geometry": {"coordinates":[0.44511801,40.597694397],"type":"Point"}
}