{
  "type": "Feature",
  "properties": {
    "iso:country":"ES",
    "sg:address":"Rua Arcebispo Lago, 12",
    "sg:city":"Vilagarcia",
    "sg:orig_category":"Parafarmacias",
    "sg:phone":"+34 986 50 84 95",
    "sg:postcode":"36600",
    "sg:province":"Pontevedra",
    "wof:name":"Farmatres Parafarmacia S.l.",
    "wof:placetype":"venue"
},
  "geometry": {"coordinates":[-8.7667617798,42.5948677063],"type":"Point"}
}