{
  "type": "Feature",
  "properties": {
    "addr:full":"Calle de Alcalde Parrondo, 7 Pola De Siero Asturias 33510",
    "addr:housenumber":"7",
    "addr:postcode":"33510",
    "addr:street":"Calle De Alcalde Parrondo",
    "iso:country":"ES",
    "sg:address":"Calle de Alcalde Parrondo, 7",
    "sg:city":"Pola De Siero",
    "sg:orig_category":"Procuradores",
    "sg:phone":"+34 985 72 07 94",
    "sg:postcode":"33510",
    "sg:province":"Asturias",
    "wof:name":"Roces Arbesu Antonio Rafael",
    "wof:placetype":"venue"
},
  "geometry": {"coordinates":[-5.6541419029,43.3924331665],"type":"Point"}
}