{
  "type": "Feature",
  "properties": {
    "addr:full":"Calle de Antonio Machado, 77 Albacete Albacete 02004",
    "addr:housenumber":"77",
    "addr:postcode":"02004",
    "addr:street":"Calle De Antonio Machado",
    "iso:country":"ES",
    "sg:address":"Calle de Antonio Machado, 77",
    "sg:city":"Albacete",
    "sg:orig_category":"Pintura Y Barniz (al Por Menor)",
    "sg:phone":"+34 967 22 80 20",
    "sg:postcode":"02004",
    "sg:province":"Albacete",
    "sg:website":"www.jafep.com",
    "wof:name":"Carrilero Clemente Delfina",
    "wof:placetype":"venue"
},
  "geometry": {"coordinates":[-1.8644666672,38.9916305542],"type":"Point"}
}