{
  "type": "Feature",
  "properties": {
    "addr:full":"J. Pe\u00f1a Lebrij., S/n Lebrija Sevilla 41740",
    "addr:postcode":"41740",
    "addr:street":"J.;Lebrij. S / N",
    "iso:country":"ES",
    "sg:address":"J. Pe\u00f1a Lebrij., S/n",
    "sg:city":"Lebrija",
    "sg:orig_category":"Adaptaciones, Acondicionamientos Especiales Para Veh\u00cdculos, Veh\u00cdculos Industriales",
    "sg:phone":"+34 955 97 53 17",
    "sg:postcode":"41740",
    "sg:province":"Sevilla",
    "wof:name":"Velazquez Serrano Julio Jose",
    "wof:placetype":"venue"
},
  "geometry": {"coordinates":[-6.0639038086,36.9178314209],"type":"Point"}
}