{
  "type": "Feature",
  "properties": {
    "iso:country":"ES",
    "sg:address":"Poli Escopar, 1",
    "sg:city":"Peralta",
    "sg:orig_category":"Aparatos De Iluminaci\u00d3n (al Por Menor)",
    "sg:phone":"+34 948 75 14 62",
    "sg:postcode":"31350",
    "sg:province":"Navarra",
    "wof:name":"Electricidad Ignacio Busto S.l.",
    "wof:placetype":"venue"
},
  "geometry": {"coordinates":[-1.8050489426,42.3389167786],"type":"Point"}
}