{
  "type": "Feature",
  "properties": {
    "iso:country":"ES",
    "sg:address":"Calle de Manuel Cortina, 7",
    "sg:city":"Villaviciosa",
    "sg:orig_category":"Mercer\u00cda, Lencer\u00cda (al Por Menor)",
    "sg:phone":"+34 985 89 30 33",
    "sg:postcode":"33300",
    "sg:province":"Asturias",
    "wof:name":"Batalla Noval Claudia",
    "wof:placetype":"venue"
},
  "geometry": {"coordinates":[-5.4333868027,43.4796829224],"type":"Point"}
}