{
  "type": "Feature",
  "properties": {
    "iso:country":"ES",
    "sg:address":"Carrer de Arago, 52",
    "sg:city":"Mas Rampinyo",
    "sg:orig_category":"Mec\u00c1nico Del Autom\u00d3vil",
    "sg:phone":"+34 935 75 34 75",
    "sg:postcode":"08110",
    "sg:province":"Barcelona",
    "wof:name":"Buendia Bermejo Isaac",
    "wof:placetype":"venue"
},
  "geometry": {"coordinates":[2.182019949,41.4957962036],"type":"Point"}
}