{
  "type": "Feature",
  "properties": {
    "iso:country":"ES",
    "sg:address":"Ptda Granyena, 14",
    "sg:city":"Lleida",
    "sg:orig_category":"Frutas, Legumbres Frescas Y Tempranas (al Por Menor)",
    "sg:phone":"+34 973 20 28 24",
    "sg:postcode":"25191",
    "sg:province":"Lleida",
    "wof:name":"Ros Ausas Angel",
    "wof:placetype":"venue"
},
  "geometry": {"coordinates":[0.6831650138,41.5832138062],"type":"Point"}
}