{
  "type": "Feature",
  "properties": {
    "addr:full":"Benjamin Franklin, 6 Zaragoza Zaragoza 50014",
    "addr:housenumber":"6",
    "addr:postcode":"50014",
    "addr:street":"Benjamin Franklin",
    "iso:country":"ES",
    "sg:address":"Benjamin Franklin, 6",
    "sg:city":"Zaragoza",
    "sg:orig_category":"Trabajos De Soldaduras",
    "sg:phone":"+34 976 47 08 46",
    "sg:postcode":"50014",
    "sg:province":"Zaragoza",
    "sg:website":"www.solgar.net",
    "wof:name":"Galagar S.l.",
    "wof:placetype":"venue"
},
  "geometry": {"coordinates":[-0.8644310236,41.6646156311],"type":"Point"}
}