{
  "type": "Feature",
  "properties": {
    "iso:country":"ES",
    "sg:address":"Cmno Bermejo, 28",
    "sg:city":"Alcaudete",
    "sg:orig_category":"Trabajos De Perforaciones, Sondeos, Construcci\u00d3n De Pozos",
    "sg:phone":"+34 953 70 81 56",
    "sg:postcode":"23660",
    "sg:province":"Ja\u00e9n",
    "wof:name":"Gonzalez Exposito Manuel Segundo",
    "wof:placetype":"venue"
},
  "geometry": {"coordinates":[-4.0815138817,37.5928001404],"type":"Point"}
}