{
  "type": "Feature",
  "properties": {
    "addr:full":"Calle de General Yag\u00fce, 26 Madrid Madrid 28020",
    "addr:housenumber":"26",
    "addr:postcode":"madrid;28020",
    "addr:street":"Calle De General Yaguee",
    "iso:country":"ES",
    "sg:address":"Calle de General Yag\u00fce, 26",
    "sg:city":"Madrid",
    "sg:orig_category":"Iglesia Cat\u00d3lica",
    "sg:phone":"+34 915 55 46 56",
    "sg:postcode":"28020",
    "sg:province":"Madrid",
    "wof:name":"Parroquia San German",
    "wof:placetype":"venue"
},
  "geometry": {"coordinates":[-3.6949267387,40.4564323425],"type":"Point"}
}