{
  "type": "Feature",
  "properties": {
    "iso:country":"ES",
    "sg:address":"Calle de Torrevieja, 10",
    "sg:city":"Valencia",
    "sg:orig_category":"Electricidad: Equipos Industriales, Componentes (fabricaci\u00d3n)",
    "sg:phone":"+34 963 78 40 86",
    "sg:postcode":"46007",
    "sg:province":"Valencia",
    "sg:website":"www.weidmuller.com",
    "wof:name":"Weidmuller S.a.",
    "wof:placetype":"venue"
},
  "geometry": {"coordinates":[-0.3877567947,39.4555587769],"type":"Point"}
}