{
  "type": "Feature",
  "properties": {
    "iso:country":"ES",
    "sg:address":"Carrer de Mallorca, 636",
    "sg:city":"Barcelona",
    "sg:orig_category":"Peluqueros: De Se\u00d1oras",
    "sg:phone":"+34 934 08 63 07",
    "sg:postcode":"08026",
    "sg:province":"Barcelona",
    "wof:name":"Rafols Villar Montserrat",
    "wof:placetype":"venue"
},
  "geometry": {"coordinates":[2.1878669262,41.4126968384],"type":"Point"}
}