{
  "type": "Feature",
  "properties": {
    "addr:full":"Edifici Campalias, S/n Baqueira Lleida 25598",
    "addr:housenumber":"s",
    "addr:postcode":"25598",
    "addr:street":"/ N Baqueira",
    "iso:country":"ES",
    "sg:address":"Edifici Campalias, S/n",
    "sg:city":"Baqueira",
    "sg:orig_category":"Farmacias",
    "sg:phone":"+34 973 64 44 62",
    "sg:postcode":"25598",
    "sg:province":"Lleida",
    "wof:name":"Pala Ari\u00f1o Maria Eugenia",
    "wof:placetype":"venue"
},
  "geometry": {"coordinates":[0.9334179759,42.6994895935],"type":"Point"}
}