{
  "type": "Feature",
  "properties": {
    "iso:country":"ES",
    "sg:address":"Plaza Herriko Plaza, 3",
    "sg:city":"Derio",
    "sg:orig_category":"Ense\u00d1anza, Formaci\u00d3n Profesional: Aprendizaje",
    "sg:phone":"+34 944 04 58 81",
    "sg:postcode":"48160",
    "sg:province":"Vizcaya",
    "wof:name":"Derioko Udala",
    "wof:placetype":"venue"
},
  "geometry": {"coordinates":[-2.8858649731,43.2909011841],"type":"Point"}
}