{
  "type": "Feature",
  "properties": {
    "addr:full":"Calle de Ronda Magdalena, 115 Castellon Castell\u00f3n 12004",
    "addr:housenumber":"115",
    "addr:postcode":"12004",
    "addr:street":"Calle De Ronda Magdalena;Castello\u0301N",
    "iso:country":"ES",
    "sg:address":"Calle de Ronda Magdalena, 115",
    "sg:city":"Castellon",
    "sg:orig_category":"Caf\u00c9s, Bares, Cervecer\u00cdas",
    "sg:phone":"+34 964 24 22 05",
    "sg:postcode":"12004",
    "sg:province":"Castell\u00f3n",
    "wof:name":"Allepuz Pitarch Juan Carlos",
    "wof:placetype":"venue"
},
  "geometry": {"coordinates":[-0.0279866997,40.0120239258],"type":"Point"}
}