{
  "type": "Feature",
  "properties": {
    "iso:country":"ES",
    "sg:address":"Carr Extremadura, 27",
    "sg:city":"Eivissa",
    "sg:orig_category":"Servicios De Telecomunicaciones",
    "sg:phone":"+34 971 19 34 72",
    "sg:postcode":"07800",
    "sg:province":"Islas Baleares",
    "wof:name":"World Sistem Pitiuso S.l.",
    "wof:placetype":"venue"
},
  "geometry": {"coordinates":[1.4267524481,38.9103279114],"type":"Point"}
}