{
  "type": "Feature",
  "properties": {
    "iso:country":"ES",
    "sg:address":"Avda Primado Reig, 42",
    "sg:city":"Valencia",
    "sg:orig_category":"Muebles, Minoristas",
    "sg:phone":"+34 963 66 43 30",
    "sg:postcode":"46009",
    "sg:province":"Valencia",
    "sg:website":"www.azcue.com",
    "wof:name":"Muebles El Filero S. A.",
    "wof:placetype":"venue"
},
  "geometry": {"coordinates":[-0.3687939942,39.4882354736],"type":"Point"}
}