{
  "type": "Feature",
  "properties": {
    "iso:country":"ES",
    "sg:address":"Calle de Palleter, 1",
    "sg:city":"Paiporta",
    "sg:orig_category":"Aguas (distribuci\u00d3n, Servicios)",
    "sg:phone":"+34 963 97 14 85",
    "sg:postcode":"46200",
    "sg:province":"Valencia",
    "wof:name":"Omnium Iberico S. A.",
    "wof:placetype":"venue"
},
  "geometry": {"coordinates":[-0.4202989936,39.4241294861],"type":"Point"}
}