{
  "type": "Feature",
  "properties": {
    "addr:full":"Avda Peinador, 43 Mos Pontevedra 36416",
    "addr:housenumber":"43",
    "addr:postcode":"36416",
    "addr:street":"Avda Peinador",
    "iso:country":"ES",
    "sg:address":"Avda Peinador, 43",
    "sg:city":"Mos",
    "sg:orig_category":"Asociaciones Humanitarias, De Cooperaci\u00d3n, De Acci\u00d3n Social",
    "sg:phone":"+34 986 48 75 57",
    "sg:postcode":"36416",
    "sg:province":"Pontevedra",
    "wof:name":"Asociacion Disminuidos Fisicos Y Psiquicos De Mos",
    "wof:placetype":"venue"
},
  "geometry": {"coordinates":[-8.6341075897,42.2228813171],"type":"Point"}
}