{
  "type": "Feature",
  "properties": {
    "iso:country":"ES",
    "sg:address":"Calle de Redonda De San Fernando, S/n",
    "sg:city":"Bujalance",
    "sg:orig_category":"Delegados, Agentes De Tr\u00c1nsito, Auxiliares De Transporte Internacional",
    "sg:phone":"+34 957 17 16 80",
    "sg:postcode":"14650",
    "sg:province":"C\u00f3rdoba",
    "wof:name":"Semar C.b.",
    "wof:placetype":"venue"
},
  "geometry": {"coordinates":[-4.3766641617,37.8974914551],"type":"Point"}
}