{
  "type": "Feature",
  "properties": {
    "addr:full":"Benjamin Franklin, S/n Gijon Asturias 33211",
    "addr:housenumber":"s / n",
    "addr:postcode":"33211",
    "addr:street":"Benjamin Franklin",
    "iso:country":"ES",
    "sg:address":"Benjamin Franklin, S/n",
    "sg:city":"Gijon",
    "sg:orig_category":"Impermeabilizantes",
    "sg:phone":"+34 985 16 74 42",
    "sg:postcode":"33211",
    "sg:province":"Asturias",
    "sg:website":"www.composan.com",
    "wof:name":"Composan Construccion S.a.",
    "wof:placetype":"venue"
},
  "geometry": {"coordinates":[-5.692512989,43.5058479309],"type":"Point"}
}