{
  "type": "Feature",
  "properties": {
    "addr:full":"Calle de Vi\u00d1as, S/n Villanueva Jara Cuenca 16230",
    "addr:housenumber":"s",
    "addr:postcode":"16230",
    "addr:street":"Calle De Vin\u0303As;/ N;Jara",
    "iso:country":"ES",
    "sg:address":"Calle de Vi\u00d1as, S/n",
    "sg:city":"Villanueva Jara",
    "sg:orig_category":"Supermercados Y Hipermercados",
    "sg:phone":"+34 967 49 86 25",
    "sg:postcode":"16230",
    "sg:province":"Cuenca",
    "wof:name":"Leal Y Zamora Alimentacion S.l.",
    "wof:placetype":"venue"
},
  "geometry": {"coordinates":[-1.9562939405,39.4415893555],"type":"Point"}
}