{
  "type": "Feature",
  "properties": {
    "addr:full":"Plaz Centenario Del, 1 Donostia-san Sebastian Guip\u00f9zcoa 20006",
    "addr:housenumber":"1",
    "addr:postcode":"20006",
    "iso:country":"ES",
    "sg:address":"Plaz Centenario Del, 1",
    "sg:city":"Donostia-san Sebastian",
    "sg:orig_category":"Ingeniero",
    "sg:phone":"+34 943 46 04 75",
    "sg:postcode":"20006",
    "sg:province":"Guip\u00f9zcoa",
    "wof:name":"Luzuriaga Telleria Jose Ramon",
    "wof:placetype":"venue"
},
  "geometry": {"coordinates":[-1.9793989658,43.3173866272],"type":"Point"}
}