{
  "type": "Feature",
  "properties": {
    "iso:country":"ES",
    "sg:address":"Rbla San Pedro (de), 28",
    "sg:city":"Biescas",
    "sg:orig_category":"Carnicer\u00cdas, Carnicer\u00cdas",
    "sg:phone":"+34 974 48 50 75",
    "sg:postcode":"22630",
    "sg:province":"Huesca",
    "wof:name":"Perez Acin Jose Miguel",
    "wof:placetype":"venue"
},
  "geometry": {"coordinates":[-0.3262380064,42.6301383972],"type":"Point"}
}