{
  "type": "Feature",
  "properties": {
    "addr:full":"Avda Compromiso De Caspe, 107 Zaragoza Zaragoza 50002",
    "addr:housenumber":"107",
    "addr:postcode":"50002",
    "addr:street":"Avda Compromiso De Caspe",
    "iso:country":"ES",
    "sg:address":"Avda Compromiso De Caspe, 107",
    "sg:city":"Zaragoza",
    "sg:orig_category":"Alumbrados",
    "sg:phone":"+34 976 59 76 77",
    "sg:postcode":"50002",
    "sg:province":"Zaragoza",
    "wof:name":"Mas Luz Regalos S.cv.",
    "wof:placetype":"venue"
},
  "geometry": {"coordinates":[-0.8608070016,41.6451721191],"type":"Point"}
}