{
  "type": "Feature",
  "properties": {
    "addr:full":"Lamansian, S/n Mabegondo La Coru\u00f1a 15318",
    "addr:postcode":"15318",
    "addr:street":"Lamansian S / N Mabegondo La Corun\u0303A",
    "iso:country":"ES",
    "sg:address":"Lamansian, S/n",
    "sg:city":"Mabegondo",
    "sg:orig_category":"Quincaller\u00cda (al Por Menor)",
    "sg:phone":"+34 981 67 30 36",
    "sg:postcode":"15318",
    "sg:province":"La Coru\u00f1a",
    "wof:name":"Fernandez Rodriguez Manuel",
    "wof:placetype":"venue"
},
  "geometry": {"coordinates":[-8.2870817184,43.2287101746],"type":"Point"}
}