{
  "type": "Feature",
  "properties": {
    "addr:full":"Calle de San Felipe, 5 Cordoba C\u00f3rdoba 14003",
    "addr:housenumber":"5",
    "addr:postcode":"14003",
    "addr:street":"Calle De San Felipe;Co\u0301Rdoba",
    "iso:country":"ES",
    "sg:address":"Calle de San Felipe, 5",
    "sg:city":"Cordoba",
    "sg:orig_category":"Inform\u00c1tica Equipo Y Programas (al Por Mayor)",
    "sg:phone":"+34 957 49 61 94",
    "sg:postcode":"14003",
    "sg:province":"C\u00f3rdoba",
    "sg:website":"www.indra.es",
    "wof:name":"Indra Sistemas S.a.",
    "wof:placetype":"venue"
},
  "geometry": {"coordinates":[-4.7818689346,37.8843917847],"type":"Point"}
}