{
  "type": "Feature",
  "properties": {
    "addr:full":"Calle de Jose Maria Hernansaez, 4 Coru\u00d1a La Coru\u00f1a 15009",
    "addr:housenumber":"4",
    "addr:postcode":"15009",
    "addr:street":"Calle De Jose Maria Hernansaez;La Corun\u0303A",
    "iso:country":"ES",
    "sg:address":"Calle de Jose Maria Hernansaez, 4",
    "sg:city":"Coru\u00d1a",
    "sg:orig_category":"Ingeniero",
    "sg:phone":"+34 981 13 95 32",
    "sg:postcode":"15009",
    "sg:province":"La Coru\u00f1a",
    "sg:website":"www.inaltel.es",
    "wof:name":"Inaltel S.a.",
    "wof:placetype":"venue"
},
  "geometry": {"coordinates":[-8.3926439285,43.3515701294],"type":"Point"}
}