{
  "type": "Feature",
  "properties": {
    "addr:full":"Carrer de Massenet, 33 Santa Coloma De Gramenet Barcelona 08922",
    "addr:housenumber":"33",
    "addr:postcode":"08922",
    "addr:street":"Carrer De Massenet",
    "iso:country":"ES",
    "sg:address":"Carrer de Massenet, 33",
    "sg:city":"Santa Coloma De Gramenet",
    "sg:orig_category":"Electrodom\u00c9sticos (al Por Menor)",
    "sg:phone":"+34 933 92 09 01",
    "sg:postcode":"08922",
    "sg:province":"Barcelona",
    "wof:name":"Comercial Bello S.a.",
    "wof:placetype":"venue"
},
  "geometry": {"coordinates":[2.2186150551,41.4504089355],"type":"Point"}
}