{
  "type": "Feature",
  "properties": {
    "iso:country":"ES",
    "sg:address":"Calle de Naumaquia, 36",
    "sg:city":"Merida",
    "sg:orig_category":"Dorados, Plater\u00cda (orfebrer\u00cda)",
    "sg:phone":"+34 924 30 08 52",
    "sg:postcode":"06800",
    "sg:province":"Badajoz",
    "sg:website":"www.paginasamarillas.es",
    "wof:name":"Vivas Casares Andres",
    "wof:placetype":"venue"
},
  "geometry": {"coordinates":[-6.3320045471,38.9171218872],"type":"Point"}
}