{
  "type": "Feature",
  "properties": {
    "iso:country":"ES",
    "sg:address":"Mcdo Azoque, S/n",
    "sg:city":"Zaragoza",
    "sg:orig_category":"Frutas, Legumbres Frescas Y Tempranas (al Por Menor)",
    "sg:phone":"+34 976 21 93 58",
    "sg:postcode":"50004",
    "sg:province":"Zaragoza",
    "wof:name":"Bartolome Bartolome Luis",
    "wof:placetype":"venue"
},
  "geometry": {"coordinates":[-0.8842989802,41.6517410278],"type":"Point"}
}