{
  "type": "Feature",
  "properties": {
    "addr:full":"Avda Torcuato Fernandez Miranda, 12 00ab Gijon Asturias 33203",
    "addr:housenumber":"12 00ab",
    "addr:postcode":"33203",
    "addr:street":"Avda Torcuato Fernandez Miranda",
    "iso:country":"ES",
    "sg:address":"Avda Torcuato Fernandez Miranda, 12 00ab",
    "sg:city":"Gijon",
    "sg:orig_category":"Estancos",
    "sg:phone":"+34 985 36 54 72",
    "sg:postcode":"33203",
    "sg:province":"Asturias",
    "wof:name":"Fernando Mendiz Vidal",
    "wof:placetype":"venue"
},
  "geometry": {"coordinates":[-5.6452240944,43.5370674133],"type":"Point"}
}