{
  "type": "Feature",
  "properties": {
    "addr:full":"Calle de Narvaez, 52 Madrid Madrid 28009",
    "addr:housenumber":"52",
    "addr:postcode":"madrid;28009",
    "addr:street":"Calle De Narvaez",
    "iso:country":"ES",
    "sg:address":"Calle de Narvaez, 52",
    "sg:city":"Madrid",
    "sg:orig_category":"Carnicer\u00cdas, Carnicer\u00cdas",
    "sg:phone":"+34 915 74 30 20",
    "sg:postcode":"28009",
    "sg:province":"Madrid",
    "wof:name":"Vicario Vicario Leon",
    "wof:placetype":"venue"
},
  "geometry": {"coordinates":[-3.676347971,40.4192657471],"type":"Point"}
}