{
  "type": "Feature",
  "properties": {
    "addr:full":"Calle de Asarau, 3 Castellon Castell\u00f3n 12001",
    "addr:housenumber":"3",
    "addr:postcode":"12001",
    "addr:street":"Calle De Asarau;Castello\u0301N",
    "iso:country":"ES",
    "sg:address":"Calle de Asarau, 3",
    "sg:city":"Castellon",
    "sg:orig_category":"Freidur\u00cdas: Equipos Y Suministros",
    "sg:phone":"+34 964 23 95 46",
    "sg:postcode":"12001",
    "sg:province":"Castell\u00f3n",
    "wof:name":"Garcia Peris Javier",
    "wof:placetype":"venue"
},
  "geometry": {"coordinates":[-0.0347821005,39.9863510132],"type":"Point"}
}