{
  "type": "Feature",
  "properties": {
    "iso:country":"ES",
    "sg:address":"Carrer de Priorat, 60",
    "sg:city":"Poligono Industrial Can Carner",
    "sg:orig_category":"Fabricaci\u00d3n De Telas Y Sedas",
    "sg:phone":"+34 937 14 37 57",
    "sg:postcode":"08211",
    "sg:province":"Barcelona",
    "wof:name":"Tissatge, Scp",
    "wof:placetype":"venue"
},
  "geometry": {"coordinates":[2.0824799538,41.6114387512],"type":"Point"}
}