{
  "type": "Feature",
  "properties": {
    "iso:country":"ES",
    "sg:address":"Rua Velazquez Moreno, 9",
    "sg:city":"Vigo",
    "sg:classifiers":[
        {
            "category":"Banks & Credit Unions",
            "subcategory":"Bureau De Change",
            "type":"Services"
        }
    ],
    "sg:phone":"+34 986 22 33 98",
    "sg:postcode":"36201",
    "sg:province":"Pontevedra",
    "sg:tags":[
        "organismos",
        "control"
    ],
    "wof:name":"S G S Espa\u00f1ola De Control S. A.",
    "wof:placetype":"venue"
},
  "geometry": {"coordinates":[-8.7216243744,42.2380371094],"type":"Point"}
}