{
  "type": "Feature",
  "properties": {
    "addr:full":"Avda Felipe Ii, 17 Madrid Madrid 28009",
    "addr:housenumber":"17",
    "addr:postcode":"madrid;28009",
    "addr:street":"Avda Felipe Ii",
    "iso:country":"ES",
    "sg:address":"Avda Felipe Ii, 17",
    "sg:city":"Madrid",
    "sg:orig_category":"M\u00c9dicos: Estomatolog\u00cda",
    "sg:phone":"+34 915 75 27 89",
    "sg:postcode":"28009",
    "sg:province":"Madrid",
    "wof:name":"Ortiz Ortiz Fernando",
    "wof:placetype":"venue"
},
  "geometry": {"coordinates":[-3.6731441021,40.424041748],"type":"Point"}
}