{
  "type": "Feature",
  "properties": {
    "iso:country":"ES",
    "sg:address":"Ctra Cadiz-barcelona Cn-340, S/n",
    "sg:city":"Sagunt",
    "sg:orig_category":"Negocio De Enlosados, Soler\u00cdas",
    "sg:phone":"+34 962 66 02 04",
    "sg:postcode":"46500",
    "sg:province":"Valencia",
    "wof:name":"Ramon Gimeno S.l.",
    "wof:placetype":"venue"
},
  "geometry": {"coordinates":[-0.2783089876,39.6799659729],"type":"Point"}
}