{
  "type": "Feature",
  "properties": {
    "addr:full":"Pase Extremadura, 150 Madrid Madrid 28011",
    "addr:housenumber":"150",
    "addr:postcode":"28011",
    "addr:street":"Extremadura",
    "iso:country":"ES",
    "sg:address":"Pase Extremadura, 150",
    "sg:city":"Madrid",
    "sg:orig_category":"Centros Empresariales",
    "sg:phone":"+34 914 63 06 76",
    "sg:postcode":"28011",
    "sg:province":"Madrid",
    "wof:name":"Control Y Geologia S.a.",
    "wof:placetype":"venue"
},
  "geometry": {"coordinates":[-3.7398540974,40.4095191956],"type":"Point"}
}