{
  "type": "Feature",
  "properties": {
    "iso:country":"ES",
    "sg:address":"Ctra. Sanchidrian, Km. 0021,2",
    "sg:city":"Riocabado",
    "sg:orig_category":"Distribuci\u00d3n De Petr\u00d3leo Y Derivados",
    "sg:phone":"+34 920 24 01 36",
    "sg:postcode":"05164",
    "sg:province":"\u00c1vila",
    "wof:name":"Nieto Y Ramos S.l.",
    "wof:placetype":"venue"
},
  "geometry": {"coordinates":[-4.7377557755,40.8698730469],"type":"Point"}
}