{
  "type": "Feature",
  "properties": {
    "addr:full":"Calle de San Nicolas, 13 Ubeda Ja\u00e9n 23400",
    "addr:housenumber":"13",
    "addr:postcode":"23400",
    "addr:street":"Calle De San;Ubeda Jae\u0301N",
    "iso:country":"ES",
    "sg:address":"Calle de San Nicolas, 13",
    "sg:city":"Ubeda",
    "sg:orig_category":"Charcuter\u00cdas (al Por Mayor)",
    "sg:phone":"+34 953 75 07 26",
    "sg:postcode":"23400",
    "sg:province":"Ja\u00e9n",
    "wof:name":"Gomez Moyar Antonio",
    "wof:placetype":"venue"
},
  "geometry": {"coordinates":[-3.3696520329,38.0140266418],"type":"Point"}
}