{
  "type": "Feature",
  "properties": {
    "iso:country":"ES",
    "sg:address":"Carrer de Jacint Verdaguer, 7",
    "sg:city":"Martorell",
    "sg:orig_category":"Ropa Para Se\u00d1oras (al Por Menor)",
    "sg:phone":"+34 937 74 83 91",
    "sg:postcode":"08760",
    "sg:province":"Barcelona",
    "wof:name":"Alba Montero Juana",
    "wof:placetype":"venue"
},
  "geometry": {"coordinates":[1.9147769213,41.4767990112],"type":"Point"}
}