{
  "type": "Feature",
  "properties": {
    "iso:country":"ES",
    "sg:address":"Calle de Araba, 4",
    "sg:city":"Legizamon",
    "sg:orig_category":"Calderer\u00cda",
    "sg:phone":"+34 944 49 28 49",
    "sg:postcode":"48450",
    "sg:province":"Vizcaya",
    "wof:name":"Caldereria Thb S.l.",
    "wof:placetype":"venue"
},
  "geometry": {"coordinates":[-2.8958415985,43.2496795654],"type":"Point"}
}