{
  "type": "Feature",
  "properties": {
    "iso:country":"ES",
    "sg:address":"Avda Portugal (de), 52",
    "sg:city":"Verin",
    "sg:orig_category":"Maquinaria Para Industrias Diversas",
    "sg:phone":"+34 988 41 32 87",
    "sg:postcode":"32600",
    "sg:province":"Ourense",
    "wof:name":"Fernandez Diaz Rosa Maria",
    "wof:placetype":"venue"
},
  "geometry": {"coordinates":[-7.4374990463,41.9401817322],"type":"Point"}
}