{
  "type": "Feature",
  "properties": {
    "iso:country":"ES",
    "sg:address":"Pe\u00f1a Santa, S/n",
    "sg:city":"Lugo",
    "sg:orig_category":"Electricidad: Equipos Industriales, Componentes (fabricaci\u00d3n)",
    "sg:phone":"+34 985 98 07 69",
    "sg:postcode":"33192",
    "sg:province":"Asturias",
    "wof:name":"Dimelsa S.a.",
    "wof:placetype":"venue"
},
  "geometry": {"coordinates":[-5.7745718956,43.4596939087],"type":"Point"}
}