{
  "type": "Feature",
  "properties": {
    "addr:full":"Calle de San Juan, 55 Alquerias Murcia 30580",
    "addr:housenumber":"55",
    "addr:postcode":"30580",
    "addr:street":"Calle De San Juan",
    "iso:country":"ES",
    "sg:address":"Calle de San Juan, 55",
    "sg:city":"Alquerias",
    "sg:orig_category":"Frutas Y Legumbres Frescas (al Por Mayor)",
    "sg:phone":"+34 968 81 04 17",
    "sg:postcode":"30580",
    "sg:province":"Murcia",
    "wof:name":"Alfrecisco S.l.",
    "wof:placetype":"venue"
},
  "geometry": {"coordinates":[-1.0365827084,38.0129890442],"type":"Point"}
}