{
  "type": "Feature",
  "properties": {
    "iso:country":"ES",
    "sg:address":"Carrer de Prat De La Riba, 40",
    "sg:city":"Martorell",
    "sg:orig_category":"Ingenier\u00cda, Centros De Estudios (diversos)",
    "sg:phone":"+34 937 76 68 43",
    "sg:postcode":"08760",
    "sg:province":"Barcelona",
    "wof:name":"Martecni Mantenimiento S.l.",
    "wof:placetype":"venue"
},
  "geometry": {"coordinates":[1.9118310213,41.4824523926],"type":"Point"}
}