{
  "type": "Feature",
  "properties": {
    "addr:full":"Av Cister, 25 Secar De La Real Islas Baleares 07010",
    "addr:housenumber":"25",
    "addr:postcode":"07010",
    "addr:street":"Av Cister",
    "iso:country":"ES",
    "sg:address":"Av Cister, 25",
    "sg:city":"Secar De La Real",
    "sg:orig_category":"Agentes Generales De Seguros",
    "sg:phone":"+34 971 76 97 14",
    "sg:postcode":"07010",
    "sg:province":"Islas Baleares",
    "wof:name":"Company Mora Monserrat",
    "wof:placetype":"venue"
},
  "geometry": {"coordinates":[2.6361160278,39.6080322266],"type":"Point"}
}