{
  "type": "Feature",
  "properties": {
    "iso:country":"ES",
    "sg:address":"Carrer de Doctor Dou, 11",
    "sg:city":"Barcelona",
    "sg:orig_category":"Ropa Para Se\u00d1oras Y Caballeros (al Por Menor)",
    "sg:phone":"+34 933 02 40 05",
    "sg:postcode":"08001",
    "sg:province":"Barcelona",
    "wof:name":"Guillaumin Soto Paula Andrea",
    "wof:placetype":"venue"
},
  "geometry": {"coordinates":[2.1687240601,41.382484436],"type":"Point"}
}