{
  "type": "Feature",
  "properties": {
    "iso:country":"ES",
    "sg:address":"Carrer de Sales I Ferre, 1",
    "sg:city":"Barcelona",
    "sg:orig_category":"Papeler\u00cdas, Librer\u00cdas",
    "sg:phone":"+34 934 55 06 79",
    "sg:postcode":"08041",
    "sg:province":"Barcelona",
    "wof:name":"Pulido Carbonell Antonio",
    "wof:placetype":"venue"
},
  "geometry": {"coordinates":[2.1745040417,41.4190711975],"type":"Point"}
}