{
  "type": "Feature",
  "properties": {
    "iso:country":"ES",
    "sg:address":"Rua Tomas A Alonso, 224",
    "sg:city":"Vigo",
    "sg:orig_category":"Fabricaci\u00d3n, Importaci\u00d3n, Venta De Material De Telefon\u00cda, Peritelefon\u00cda",
    "sg:phone":"+34 986 24 77 69",
    "sg:postcode":"36208",
    "sg:province":"Pontevedra",
    "wof:name":"Erictega S.l.l.",
    "wof:placetype":"venue"
},
  "geometry": {"coordinates":[-8.7513952255,42.2241516113],"type":"Point"}
}