{
  "type": "Feature",
  "properties": {
    "addr:full":"Calle de Francisco Verdu, 46 Alacant Alicante 03010",
    "addr:housenumber":"46",
    "addr:postcode":"03010",
    "addr:street":"Calle De Francisco Verdu",
    "iso:country":"ES",
    "sg:address":"Calle de Francisco Verdu, 46",
    "sg:city":"Alacant",
    "sg:orig_category":"Molduras, Junquillos, Listones Y Molduras Perforadas",
    "sg:phone":"+34 965 24 74 29",
    "sg:postcode":"03010",
    "sg:province":"Alicante",
    "wof:name":"Balsalobre Guillamon Ignacio",
    "wof:placetype":"venue"
},
  "geometry": {"coordinates":[-0.4846189916,38.3621406555],"type":"Point"}
}