{
  "type": "Feature",
  "properties": {
    "addr:full":"Calle de Jorge Guillen, 14 Arrabal De Portillo Valladolid 47160",
    "addr:housenumber":"14",
    "addr:postcode":"47160",
    "addr:street":"Calle De Jorge Guillen",
    "iso:country":"ES",
    "sg:address":"Calle de Jorge Guillen, 14",
    "sg:city":"Arrabal De Portillo",
    "sg:orig_category":"Inform\u00c1tica (estudios, Servicios, Asesor\u00cda, Formaci\u00d3n)",
    "sg:phone":"+34 983 55 71 15",
    "sg:postcode":"47160",
    "sg:province":"Valladolid",
    "wof:name":"Villalba Callejo Jesus",
    "wof:placetype":"venue"
},
  "geometry": {"coordinates":[-4.5952019691,41.4729614258],"type":"Point"}
}