{
  "type": "Feature",
  "properties": {
    "addr:full":"Rua Curros Enriquez, 53 Carballi\u00f1o Ourense 32500",
    "addr:housenumber":"53",
    "addr:postcode":"32500",
    "addr:street":"Rua Curros Enriquez",
    "iso:country":"ES",
    "sg:address":"Rua Curros Enriquez, 53",
    "sg:city":"Carballi\u00f1o",
    "sg:orig_category":"Psic\u00d3logos",
    "sg:phone":"+34 988 27 13 38",
    "sg:postcode":"32500",
    "sg:province":"Ourense",
    "wof:name":"Alberte Iglesias Purificacion",
    "wof:placetype":"venue"
},
  "geometry": {"coordinates":[-8.0756244659,42.4331550598],"type":"Point"}
}