{
  "type": "Feature",
  "properties": {
    "addr:full":"Carrer de Valencia, 85 Barcelona Barcelona 08029",
    "addr:housenumber":"85",
    "addr:postcode":"08029",
    "addr:street":"Carrer De Valencia",
    "iso:country":"ES",
    "sg:address":"Carrer de Valencia, 85",
    "sg:city":"Barcelona",
    "sg:orig_category":"Artes Gr\u00c1ficas, Artes Pl\u00c1sticas (curso)",
    "sg:phone":"+34 933 23 83 11",
    "sg:postcode":"08029",
    "sg:province":"Barcelona",
    "wof:name":"Cevagraf S. Coop. C. Ltda.",
    "wof:placetype":"venue"
},
  "geometry": {"coordinates":[2.1530950069,41.3851890564],"type":"Point"}
}