{
  "type": "Feature",
  "properties": {
    "iso:country":"ES",
    "sg:address":"Carr Sant Pau, 15",
    "sg:city":"Figueres",
    "sg:orig_category":"Reposter\u00cdas",
    "sg:phone":"+34 972 50 22 73",
    "sg:postcode":"17600",
    "sg:province":"Girona",
    "wof:name":"Boutique Del Pa S.l.",
    "wof:placetype":"venue"
},
  "geometry": {"coordinates":[2.9581100941,42.2656898499],"type":"Point"}
}