{
  "type": "Feature",
  "properties": {
    "iso:country":"ES",
    "sg:address":"Carrer de Cantallops, 1",
    "sg:city":"Llagostera",
    "sg:orig_category":"Asociaciones Y Clubs Deportivos",
    "sg:phone":"+34 972 83 16 94",
    "sg:postcode":"17240",
    "sg:province":"Girona",
    "wof:name":"Pe\u00f1a Madridista Llagostera",
    "wof:placetype":"venue"
},
  "geometry": {"coordinates":[2.894299984,41.8292198181],"type":"Point"}
}