{
  "type": "Feature",
  "properties": {
    "addr:full":"Via Europa, 50 Mataro Barcelona 08303",
    "addr:housenumber":"50",
    "addr:postcode":"08303",
    "addr:street":"Via Europa",
    "iso:country":"ES",
    "sg:address":"Via Europa, 50",
    "sg:city":"Mataro",
    "sg:orig_category":"Arquitectos",
    "sg:phone":"+34 937 57 65 96",
    "sg:postcode":"08303",
    "sg:province":"Barcelona",
    "wof:name":"Ciscar Ribes Vicente",
    "wof:placetype":"venue"
},
  "geometry": {"coordinates":[2.4338181019,41.5425720215],"type":"Point"}
}