{
  "type": "Feature",
  "properties": {
    "iso:country":"ES",
    "sg:address":"Calle de Cervantes, 22",
    "sg:city":"Ejido",
    "sg:orig_category":"Psic\u00d3logos",
    "sg:phone":"+34 950 48 41 90",
    "sg:postcode":"04700",
    "sg:province":"Almer\u00eda",
    "wof:name":"Carpe Diem C.b.",
    "wof:placetype":"venue"
},
  "geometry": {"coordinates":[-2.8184700012,36.7736053467],"type":"Point"}
}