{
  "type": "Feature",
  "properties": {
    "iso:country":"ES",
    "sg:address":"Calle de Aldapa, 23",
    "sg:city":"Donostia-san Sebastian",
    "sg:orig_category":"Arquitectos",
    "sg:phone":"+34 943 32 03 54",
    "sg:postcode":"20012",
    "sg:province":"Guip\u00f9zcoa",
    "wof:name":"Sese Madrazo Luis",
    "wof:placetype":"venue"
},
  "geometry": {"coordinates":[-1.9696960449,43.3158302307],"type":"Point"}
}