{
  "type": "Feature",
  "properties": {
    "addr:full":"Rivera, 3 La Pola Asturias 33630",
    "addr:housenumber":"3",
    "addr:postcode":"33630",
    "addr:street":"Rivera",
    "iso:country":"ES",
    "sg:address":"Rivera, 3",
    "sg:city":"La Pola",
    "sg:orig_category":"Supermercados Y Hipermercados",
    "sg:phone":"+34 985 49 76 15",
    "sg:postcode":"33630",
    "sg:province":"Asturias",
    "wof:name":"Merkaprecio S.a.",
    "wof:placetype":"venue"
},
  "geometry": {"coordinates":[-5.8276748657,43.1602592468],"type":"Point"}
}