{
  "type": "Feature",
  "properties": {
    "addr:full":"Ctra. Alzira, S/n Xativa Valencia 46800",
    "addr:housenumber":"s",
    "addr:postcode":"46800",
    "addr:street":"Ctra. Alzira;/ N",
    "iso:country":"ES",
    "sg:address":"Ctra. Alzira, S/n",
    "sg:city":"Xativa",
    "sg:orig_category":"Agentes, Concesionarios Y Sucursales De Veh\u00cdculos",
    "sg:phone":"+34 962 27 09 00",
    "sg:postcode":"46800",
    "sg:province":"Valencia",
    "wof:name":"Autointer S. A.",
    "wof:placetype":"venue"
},
  "geometry": {"coordinates":[-0.5141375065,38.9954566956],"type":"Point"}
}