{
  "type": "Feature",
  "properties": {
    "iso:country":"ES",
    "sg:address":"Moll Barcelona, S/n",
    "sg:city":"Barcelona",
    "sg:orig_category":"Ingeniero",
    "sg:phone":"+34 933 43 40 00",
    "sg:postcode":"08...",
    "sg:province":"Barcelona",
    "sg:website":"www.agilet.com",
    "wof:name":"Agilent Technologies Spain S.l.",
    "wof:placetype":"venue"
},
  "geometry": {"coordinates":[2.1807153225,41.3718147278],"type":"Point"}
}