{
  "type": "Feature",
  "properties": {
    "iso:country":"ES",
    "sg:address":"Calle de Lopez De Hoyos, 148",
    "sg:city":"Madrid",
    "sg:orig_category":"Ropa Para Se\u00d1oras (al Por Menor)",
    "sg:phone":"+34 914 13 05 46",
    "sg:postcode":"28002",
    "sg:province":"Madrid",
    "wof:name":"Machin S. A.",
    "wof:placetype":"venue"
},
  "geometry": {"coordinates":[-3.6718571186,40.4454956055],"type":"Point"}
}