{
  "type": "Feature",
  "properties": {
    "addr:full":"Calle de Cuna, 46 Sevilla Sevilla 41004",
    "addr:housenumber":"46",
    "addr:postcode":"41004",
    "addr:street":"Calle De Cuna",
    "iso:country":"ES",
    "sg:address":"Calle de Cuna, 46",
    "sg:city":"Sevilla",
    "sg:orig_category":"Zapatos (al Por Menor)",
    "sg:phone":"+34 954 56 21 87",
    "sg:postcode":"41004",
    "sg:province":"Sevilla",
    "wof:name":"Osorno Rubio Jose",
    "wof:placetype":"venue"
},
  "geometry": {"coordinates":[-5.9934067726,37.3909187317],"type":"Point"}
}