{
  "type": "Feature",
  "properties": {
    "iso:country":"ES",
    "sg:address":"Romeo, 7",
    "sg:city":"Barbastro",
    "sg:orig_category":"Supermercados Y Hipermercados",
    "sg:phone":"+34 974 31 05 96",
    "sg:postcode":"22300",
    "sg:province":"Huesca",
    "wof:name":"Autoservicio Y Charcuteria Hermanos Pueyo S.c.",
    "wof:placetype":"venue"
},
  "geometry": {"coordinates":[0.1307796985,42.0187110901],"type":"Point"}
}