{
  "type": "Feature",
  "properties": {
    "addr:full":"Calle de Cervantes, 74 Alginet Valencia 46230",
    "addr:housenumber":"74",
    "addr:postcode":"46230",
    "addr:street":"Calle De Cervantes",
    "iso:country":"ES",
    "sg:address":"Calle de Cervantes, 74",
    "sg:city":"Alginet",
    "sg:orig_category":"Comercio, Reparaci\u00d3n De Motocicletas, Bicicletas Y Piezas Sueltas",
    "sg:phone":"+34 961 75 33 59",
    "sg:postcode":"46230",
    "sg:province":"Valencia",
    "wof:name":"Novamoto Racing S.l",
    "wof:placetype":"venue"
},
  "geometry": {"coordinates":[-0.4678333104,39.2588653564],"type":"Point"}
}