{
  "type": "Feature",
  "properties": {
    "iso:country":"ES",
    "sg:address":"Barr Centulle, S/n",
    "sg:city":"Centulle",
    "sg:orig_category":"Ferreter\u00cda (diversos)",
    "sg:phone":"+34 982 44 02 51",
    "sg:postcode":"27518",
    "sg:province":"Lugo",
    "wof:name":"Prefabricados Chantada S.l.",
    "wof:placetype":"venue"
},
  "geometry": {"coordinates":[-7.8486537933,42.6254386902],"type":"Point"}
}