{
  "type": "Feature",
  "properties": {
    "addr:full":"Avda Martin Descalzo, 47 Madridejos Toledo 45710",
    "addr:housenumber":"47",
    "addr:postcode":"45710",
    "addr:street":"Avda Martin Descalzo",
    "iso:country":"ES",
    "sg:address":"Avda Martin Descalzo, 47",
    "sg:city":"Madridejos",
    "sg:orig_category":"Venta, Instalaci\u00d3n De Calefacci\u00d3n",
    "sg:phone":"+34 925 46 34 90",
    "sg:postcode":"45710",
    "sg:province":"Toledo",
    "wof:name":"Hergofont S.l",
    "wof:placetype":"venue"
},
  "geometry": {"coordinates":[-3.5293490887,39.4792251587],"type":"Point"}
}