{
  "type": "Feature",
  "properties": {
    "addr:full":"Calle de Villalba, 13 Poligono Industrial Los Villares Salamanca 37184",
    "addr:housenumber":"13",
    "addr:postcode":"37184",
    "addr:street":"Calle De Villalba;Industrial",
    "iso:country":"ES",
    "sg:address":"Calle de Villalba, 13",
    "sg:city":"Poligono Industrial Los Villares",
    "sg:orig_category":"Piscinas, Accesorios, Suministros (fabricaci\u00d3n, Al Por Mayor)",
    "sg:phone":"+34 923 20 43 82",
    "sg:postcode":"37184",
    "sg:province":"Salamanca",
    "wof:name":"Cuposol S.l.",
    "wof:placetype":"venue"
},
  "geometry": {"coordinates":[-5.6396541595,40.9895515442],"type":"Point"}
}