{
  "type": "Feature",
  "properties": {
    "addr:full":"Calle de Solana Alta, 3 Tudela Duero Valladolid 47320",
    "addr:housenumber":"3;duero",
    "addr:postcode":"47320",
    "addr:street":"Calle De Solana Alta",
    "iso:country":"ES",
    "sg:address":"Calle de Solana Alta, 3",
    "sg:city":"Tudela Duero",
    "sg:orig_category":"Centros Empresariales",
    "sg:phone":"+34 983 52 22 60",
    "sg:postcode":"47320",
    "sg:province":"Valladolid",
    "wof:name":"Construcciones Fraile Cu\u00f1ado S.l.",
    "wof:placetype":"venue"
},
  "geometry": {"coordinates":[-4.5819039345,41.5847167969],"type":"Point"}
}