{
  "type": "Feature",
  "properties": {
    "addr:full":"Calle de Blasco De Garay, 36 Madrid Madrid 28015",
    "addr:housenumber":"36",
    "addr:postcode":"madrid;28015",
    "addr:street":"Calle De Blasco De Garay",
    "iso:country":"ES",
    "sg:address":"Calle de Blasco De Garay, 36",
    "sg:city":"Madrid",
    "sg:orig_category":"Lencer\u00cda Femenina, Corseter\u00cda, Trajes De Ba\u00d1o (al Por Menor)",
    "sg:phone":"+34 915 93 37 77",
    "sg:postcode":"28015",
    "sg:province":"Madrid",
    "sg:website":"www.noredredon.com",
    "wof:name":"Nor Edredon Textil Espa\u00f1a S.l.",
    "wof:placetype":"venue"
},
  "geometry": {"coordinates":[-3.7116265297,40.4328689575],"type":"Point"}
}