{
  "type": "Feature",
  "properties": {
    "iso:country":"ES",
    "sg:address":"Calle de Adolfo Suarez, 13",
    "sg:city":"Cebreros",
    "sg:orig_category":"Carnicer\u00cdas, Carnicer\u00cdas",
    "sg:phone":"+34 918 63 01 13",
    "sg:postcode":"05260",
    "sg:province":"\u00c1vila",
    "wof:name":"Carnicas Malena S.l.",
    "wof:placetype":"venue"
},
  "geometry": {"coordinates":[-4.4657654762,40.4554595947],"type":"Point"}
}