{
  "type": "Feature",
  "properties": {
    "addr:full":"Crta De Martos, S/n Higuera Calatrava Ja\u00e9n 23611",
    "addr:housenumber":"/ n",
    "addr:postcode":"23611",
    "addr:street":"Crta De Martos S",
    "iso:country":"ES",
    "sg:address":"Crta De Martos, S/n",
    "sg:city":"Higuera Calatrava",
    "sg:orig_category":"Distribuci\u00d3n De Petr\u00d3leo Y Derivados",
    "sg:phone":"+34 953 52 91 82",
    "sg:postcode":"23611",
    "sg:province":"Ja\u00e9n",
    "wof:name":"Vepaos S.l.",
    "wof:placetype":"venue"
},
  "geometry": {"coordinates":[-4.1551990509,37.7966156006],"type":"Point"}
}