{
  "type": "Feature",
  "properties": {
    "addr:full":"Carrer de Pere Alvarez, 5 Sant Feliu Llobregat Barcelona 08980",
    "addr:housenumber":"5",
    "addr:postcode":"08980",
    "addr:street":"Carrer De Pere Alvarez",
    "iso:country":"ES",
    "sg:address":"Carrer de Pere Alvarez, 5",
    "sg:city":"Sant Feliu Llobregat",
    "sg:orig_category":"Artes Gr\u00c1ficas, Artes Pl\u00c1sticas (curso)",
    "sg:phone":"+34 936 85 58 19",
    "sg:postcode":"08980",
    "sg:province":"Barcelona",
    "wof:name":"Litografia Ochoa S.l.",
    "wof:placetype":"venue"
},
  "geometry": {"coordinates":[2.0437009335,41.3827209473],"type":"Point"}
}