{
  "type": "Feature",
  "properties": {
    "addr:full":"Avda Valladolid, 24 Tordesillas Valladolid 47100",
    "addr:housenumber":"24",
    "addr:postcode":"47100",
    "addr:street":"Avda Valladolid",
    "iso:country":"ES",
    "sg:address":"Avda Valladolid, 24",
    "sg:city":"Tordesillas",
    "sg:orig_category":"Quincaller\u00cda (al Por Menor)",
    "sg:phone":"+34 983 77 11 32",
    "sg:postcode":"47100",
    "sg:province":"Valladolid",
    "wof:name":"Mielgo Merillas Jose Luis",
    "wof:placetype":"venue"
},
  "geometry": {"coordinates":[-4.9884839058,41.5042915344],"type":"Point"}
}