{
  "type": "Feature",
  "properties": {
    "addr:full":"Calle de Julian Camarillo, 28 Madrid Madrid 28037",
    "addr:housenumber":"28",
    "addr:postcode":"madrid;28037",
    "addr:street":"Calle De Julian Camarillo",
    "iso:country":"ES",
    "sg:address":"Calle de Julian Camarillo, 28",
    "sg:city":"Madrid",
    "sg:orig_category":"Laboratorios Y Cl\u00cdnicas Veterinarias",
    "sg:phone":"+34 913 04 94 81",
    "sg:postcode":"28037",
    "sg:province":"Madrid",
    "sg:website":"www.azasa.es",
    "wof:name":"Instrumental Quirurgico Y Material Ganadero S.a.",
    "wof:placetype":"venue"
},
  "geometry": {"coordinates":[-3.6268150806,40.4350204468],"type":"Point"}
}