{
  "type": "Feature",
  "properties": {
    "addr:full":"San Miguel De Geneto, 233 San Cristobal De La Laguna Santa Cruz De Tenerife 38296",
    "addr:housenumber":"233",
    "addr:postcode":"38296",
    "addr:street":"Geneto",
    "iso:country":"ES",
    "sg:address":"San Miguel De Geneto, 233",
    "sg:city":"San Cristobal De La Laguna",
    "sg:orig_category":"Imprenta",
    "sg:phone":"+34 922 31 55 42",
    "sg:postcode":"38296",
    "sg:province":"Santa Cruz De Tenerife",
    "wof:name":"Graficas Joisan S.l.l.",
    "wof:placetype":"venue"
},
  "geometry": {"coordinates":[-16.3192081451,28.453540802],"type":"Point"}
}