{
  "type": "Feature",
  "properties": {
    "iso:country":"ES",
    "sg:address":"Ctra Vilallobent, 3",
    "sg:city":"Sant Marc",
    "sg:orig_category":"Molduras, Junquillos, Listones Y Molduras Perforadas",
    "sg:phone":"+34 972 14 13 72",
    "sg:postcode":"17520",
    "sg:province":"Girona",
    "wof:name":"Garcia Martin Concepcion",
    "wof:placetype":"venue"
},
  "geometry": {"coordinates":[1.9278999567,42.4336547852],"type":"Point"}
}