{
  "type": "Feature",
  "properties": {
    "addr:full":"Calle de Bravo Murillo, 213 Madrid Madrid 28020",
    "addr:housenumber":"213",
    "addr:postcode":"28020",
    "addr:street":"Calle De Bravo Murillo",
    "iso:country":"ES",
    "sg:address":"Calle de Bravo Murillo, 213",
    "sg:city":"Madrid",
    "sg:orig_category":"Art\u00cdculos De Decoraci\u00d3n",
    "sg:phone":"+34 915 71 43 39",
    "sg:postcode":"28020",
    "sg:province":"Madrid",
    "sg:website":"www.nuevalinea.es",
    "wof:name":"Deslan Decoracion S.l.",
    "wof:placetype":"venue"
},
  "geometry": {"coordinates":[-3.7022812366,40.4562149048],"type":"Point"}
}