{
  "type": "Feature",
  "properties": {
    "addr:full":"Calle de Portal De Bergara, 27 Vitoria-gasteiz \u00c1lava 01013",
    "addr:housenumber":"27",
    "addr:postcode":"01013",
    "addr:street":"Calle De Portal De Bergara",
    "iso:country":"ES",
    "sg:address":"Calle de Portal De Bergara, 27",
    "sg:city":"Vitoria-gasteiz",
    "sg:orig_category":"Suministros Y Materiales Industriales",
    "sg:phone":"+34 945 27 90 91",
    "sg:postcode":"01013",
    "sg:province":"\u00c1lava",
    "wof:name":"Jean S.l.",
    "wof:placetype":"venue"
},
  "geometry": {"coordinates":[-2.6453709602,42.8751602173],"type":"Point"}
}