{
  "type": "Feature",
  "properties": {
    "addr:full":"Calle de Miguel Servet, 1 Zaragoza Zaragoza 50002",
    "addr:housenumber":"1",
    "addr:postcode":"50002",
    "addr:street":"Calle De Miguel Servet",
    "iso:country":"ES",
    "sg:address":"Calle de Miguel Servet, 1",
    "sg:city":"Zaragoza",
    "sg:orig_category":"Negocio De Madera",
    "sg:phone":"+34 976 42 75 47",
    "sg:postcode":"50002",
    "sg:province":"Zaragoza",
    "wof:name":"Gines Falcon Jesus",
    "wof:placetype":"venue"
},
  "geometry": {"coordinates":[-0.8753319979,41.648475647],"type":"Point"}
}