{
  "type": "Feature",
  "properties": {
    "iso:country":"ES",
    "sg:address":"Calle de Fray Bartolome De Las Casas, S/n",
    "sg:city":"Albolote",
    "sg:orig_category":"Centros De Educaci\u00d3n Especial",
    "sg:phone":"+34 958 43 06 84",
    "sg:postcode":"18220",
    "sg:province":"Granada",
    "wof:name":"Abad Moles Francisca",
    "wof:placetype":"venue"
},
  "geometry": {"coordinates":[-3.656486,37.225269],"type":"Point"}
}