{
  "type": "Feature",
  "properties": {
    "iso:country":"ES",
    "sg:address":"Calle de Matias Montero, 18",
    "sg:city":"Plasencia",
    "sg:orig_category":"Alimentaci\u00d3n General (al Por Menor)",
    "sg:phone":"+34 927 41 53 94",
    "sg:postcode":"10600",
    "sg:province":"C\u00e1ceres",
    "wof:name":"Pablos Granado Valeriano",
    "wof:placetype":"venue"
},
  "geometry": {"coordinates":[-6.0940289497,40.0303382874],"type":"Point"}
}