{
  "type": "Feature",
  "properties": {
    "addr:full":"Cmno Parras (las), 36 Villafranqueza - Palamo Alicante 03112",
    "addr:housenumber":"36",
    "addr:postcode":"03112",
    "addr:street":"Cmno Parras Las",
    "iso:country":"ES",
    "sg:address":"Cmno Parras (las), 36",
    "sg:city":"Villafranqueza - Palamo",
    "sg:orig_category":"Contenedores (mercanc\u00cdas)",
    "sg:phone":"+34 965 17 95 79",
    "sg:postcode":"03112",
    "sg:province":"Alicante",
    "wof:name":"Transportes Y Pescado Los Alegres S.l.",
    "wof:placetype":"venue"
},
  "geometry": {"coordinates":[-0.4732680023,38.4022827148],"type":"Point"}
}