{
  "type": "Feature",
  "properties": {
    "iso:country":"ES",
    "sg:address":"Pl Doctor Galtes, 6",
    "sg:city":"S. Cugat Valles",
    "sg:orig_category":"Agencias De Viajes",
    "sg:phone":"+34 935 89 74 64",
    "sg:postcode":"08172",
    "sg:province":"Barcelona",
    "wof:name":"Herver-9 S.l.",
    "wof:placetype":"venue"
},
  "geometry": {"coordinates":[2.0806701183,41.47082901],"type":"Point"}
}