{
  "type": "Feature",
  "properties": {
    "iso:country":"ES",
    "sg:address":"Carrer de Irlanda, 89",
    "sg:city":"Santa Coloma De Gramenet",
    "sg:orig_category":"Institutos De Belleza (productos Y Aparatos)",
    "sg:phone":"+34 933 91 80 02",
    "sg:postcode":"08922",
    "sg:province":"Barcelona",
    "wof:name":"Martinez Llorente Imma",
    "wof:placetype":"venue"
},
  "geometry": {"coordinates":[2.215679884,41.4482917786],"type":"Point"}
}