{
  "type": "Feature",
  "properties": {
    "addr:full":"Rond Guinardo, 8 Barcelona Barcelona 08024",
    "addr:housenumber":"8",
    "addr:postcode":"08024",
    "addr:street":"Guinardo",
    "iso:country":"ES",
    "sg:address":"Rond Guinardo, 8",
    "sg:city":"Barcelona",
    "sg:orig_category":"Ense\u00d1anza Variada",
    "sg:phone":"+34 932 10 15 68",
    "sg:postcode":"08024",
    "sg:province":"Barcelona",
    "sg:website":"www.fengshuinatural.com",
    "wof:name":"Escuela Feng Shui Natural S.c.p.",
    "wof:placetype":"venue"
},
  "geometry": {"coordinates":[2.1614758968,41.4123535156],"type":"Point"}
}