{
  "type": "Feature",
  "properties": {
    "addr:full":"Avda Pulianas (de), 42 Granada Granada 18011",
    "addr:housenumber":"42",
    "addr:postcode":"18011",
    "addr:street":"Avda Pulianas De",
    "iso:country":"ES",
    "sg:address":"Avda Pulianas (de), 42",
    "sg:city":"Granada",
    "sg:orig_category":"Internados & Ense\u00d1anza Privada",
    "sg:phone":"+34 958 15 40 05",
    "sg:postcode":"18011",
    "sg:province":"Granada",
    "wof:name":"Asociacion Obra Social Padre Manjon",
    "wof:placetype":"venue"
},
  "geometry": {"coordinates":[-3.6043946743,37.1939125061],"type":"Point"}
}