{
  "type": "Feature",
  "properties": {
    "iso:country":"ES",
    "sg:address":"Avda Alcalde Miguel Casta\u00d1o, 58",
    "sg:city":"Le\u00f3n",
    "sg:orig_category":"Motocicletas (agentes, Concesionarios)",
    "sg:phone":"+34 987 26 04 40",
    "sg:postcode":"24005",
    "sg:province":"Le\u00f3n",
    "wof:name":"Casteflor Motocasion S.l.",
    "wof:placetype":"venue"
},
  "geometry": {"coordinates":[-5.5636439323,42.5906295776],"type":"Point"}
}