{
  "type": "Feature",
  "properties": {
    "addr:full":"Calle de Extremadura (de), S/n Fuenlabrada Madrid 28944",
    "addr:postcode":"28944",
    "addr:street":"Calle De Extremadura De S / N",
    "iso:country":"ES",
    "sg:address":"Calle de Extremadura (de), S/n",
    "sg:city":"Fuenlabrada",
    "sg:orig_category":"Centros De Educaci\u00d3n Especial",
    "sg:phone":"+34 916 15 62 62",
    "sg:postcode":"28944",
    "sg:province":"Madrid",
    "wof:name":"Comunidad Autonoma De Madrid-centros De Educacion",
    "wof:placetype":"venue"
},
  "geometry": {"coordinates":[-3.7958340645,40.2801246643],"type":"Point"}
}