{
  "type": "Feature",
  "properties": {
    "iso:country":"ES",
    "sg:address":"Plaz Mayor, S/n",
    "sg:city":"Rincon Beniscornia",
    "sg:orig_category":"Asociaciones, Organismos Culturales Y Socioeducativos",
    "sg:phone":"+34 968 29 80 10",
    "sg:postcode":"30108",
    "sg:province":"Murcia",
    "wof:name":"Rodriguez Mantilla Juan",
    "wof:placetype":"venue"
},
  "geometry": {"coordinates":[-1.176273942,37.9847564697],"type":"Point"}
}