{
  "type": "Feature",
  "properties": {
    "iso:country":"ES",
    "sg:address":"Carr Tramuntana, 29",
    "sg:city":"Sineu",
    "sg:orig_category":"Prot\u00c9sicos Dentales",
    "sg:phone":"+34 971 52 10 85",
    "sg:postcode":"07510",
    "sg:province":"Islas Baleares",
    "wof:name":"Busquets Monserrat Antonio",
    "wof:placetype":"venue"
},
  "geometry": {"coordinates":[3.009139061,39.6458740234],"type":"Point"}
}