{
  "type": "Feature",
  "properties": {
    "iso:country":"ES",
    "sg:address":"Calle de Venerable Juan De Santiago, 1",
    "sg:city":"Cordoba",
    "sg:orig_category":"Pescader\u00cdas (al Por Menor)",
    "sg:phone":"+34 957 75 20 07",
    "sg:postcode":"14010",
    "sg:province":"C\u00f3rdoba",
    "wof:name":"Carre\u00f1o Valle Juan Manuel",
    "wof:placetype":"venue"
},
  "geometry": {"coordinates":[-4.7667679787,37.879863739],"type":"Point"}
}