{
  "type": "Feature",
  "properties": {
    "addr:full":"Calle de Batuecas, 5 Valladolid Valladolid 47010",
    "addr:housenumber":"5",
    "addr:postcode":"47010",
    "addr:street":"Calle De Batuecas",
    "iso:country":"ES",
    "sg:address":"Calle de Batuecas, 5",
    "sg:city":"Valladolid",
    "sg:orig_category":"Equipo De Refrigeraci\u00d3n Industrial",
    "sg:phone":"+34 983 25 84 53",
    "sg:postcode":"47010",
    "sg:province":"Valladolid",
    "wof:name":"Refrigeracion Movall S.l.",
    "wof:placetype":"venue"
},
  "geometry": {"coordinates":[-4.7153878212,41.6653366089],"type":"Point"}
}