{
  "type": "Feature",
  "properties": {
    "iso:country":"ES",
    "sg:address":"Plaz Arguelles, 46",
    "sg:city":"Pola De Siero",
    "sg:orig_category":"Asesor\u00cda Sobre Comunicaci\u00d3n De Empresas",
    "sg:phone":"+34 985 72 18 88",
    "sg:postcode":"33510",
    "sg:province":"Asturias",
    "wof:name":"Asesoria Angeles Valdes-isabel Fernandez S.l.",
    "wof:placetype":"venue"
},
  "geometry": {"coordinates":[-5.6614813805,43.3932533264],"type":"Point"}
}