{
  "type": "Feature",
  "properties": {
    "addr:full":"Pase Condes De Barcelona, S/n Badajoz Badajoz 06010",
    "addr:postcode":"06010",
    "addr:street":"S / N",
    "iso:country":"ES",
    "sg:address":"Pase Condes De Barcelona, S/n",
    "sg:city":"Badajoz",
    "sg:orig_category":"Cajas Para Embalar",
    "sg:phone":"+34 924 22 25 06",
    "sg:postcode":"06010",
    "sg:province":"Badajoz",
    "wof:name":"Caja Rural De Extremadura",
    "wof:placetype":"venue"
},
  "geometry": {"coordinates":[-6.9803590775,38.8667831421],"type":"Point"}
}