{
  "type": "Feature",
  "properties": {
    "iso:country":"ES",
    "sg:address":"Calle de Rio Cares, 7",
    "sg:city":"Pola De Laviana",
    "sg:orig_category":"Invernaderos Y Semilleros",
    "sg:phone":"+34 985 60 10 12",
    "sg:postcode":"33980",
    "sg:province":"Asturias",
    "wof:name":"Rodriguez Abella Alfonso",
    "wof:placetype":"venue"
},
  "geometry": {"coordinates":[-5.5629911423,43.2405433655],"type":"Point"}
}