{
  "type": "Feature",
  "properties": {
    "iso:country":"ES",
    "sg:address":"Calle de Cervantes, 6",
    "sg:city":"Solana",
    "sg:orig_category":"Cajas De Ahorro",
    "sg:phone":"+34 926 63 52 64",
    "sg:postcode":"13240",
    "sg:province":"Ciudad Real",
    "sg:website":"www.lacaixa.es",
    "wof:name":"Caixa D'estalvis I Pensions De Barcelona",
    "wof:placetype":"venue"
},
  "geometry": {"coordinates":[-3.2386822701,38.9425392151],"type":"Point"}
}