{
  "type": "Feature",
  "properties": {
    "addr:full":"Pl Espanya (d'), 26 Gata Gorgos Alicante 03740",
    "addr:postcode":"03740",
    "addr:street":"Pl",
    "iso:country":"ES",
    "sg:address":"Pl Espanya (d'), 26",
    "sg:city":"Gata Gorgos",
    "sg:orig_category":"Art\u00cdculos De Regalo (al Por Menor)",
    "sg:phone":"+34 966 45 42 35",
    "sg:postcode":"03740",
    "sg:province":"Alicante",
    "wof:name":"Mulet Borrel Rosa Alicia",
    "wof:placetype":"venue"
},
  "geometry": {"coordinates":[0.0839079991,38.7759056091],"type":"Point"}
}