{
  "type": "Feature",
  "properties": {
    "addr:full":"Cmno Valderribas, 70 Madrid Madrid 28038",
    "addr:housenumber":"70",
    "addr:postcode":"madrid;28038",
    "addr:street":"Cmno Valderribas",
    "iso:country":"ES",
    "sg:address":"Cmno Valderribas, 70",
    "sg:city":"Madrid",
    "sg:orig_category":"Grafistas",
    "sg:phone":"+34 914 34 87 44",
    "sg:postcode":"28038",
    "sg:province":"Madrid",
    "wof:name":"Grupo Separacionline S.l.",
    "wof:placetype":"venue"
},
  "geometry": {"coordinates":[-3.6624839306,40.3995361328],"type":"Point"}
}