{
  "type": "Feature",
  "properties": {
    "iso:country":"ES",
    "sg:address":"Plaz Laurel Del, S/n",
    "sg:city":"Huelva",
    "sg:orig_category":"Bisuter\u00cda, Joyer\u00cda, Relojer\u00cda (al Por Menor)",
    "sg:phone":"+34 959 15 51 71",
    "sg:postcode":"21005",
    "sg:province":"Huelva",
    "wof:name":"Borrego Huertas Fernando",
    "wof:placetype":"venue"
},
  "geometry": {"coordinates":[-6.9067587852,37.3151283264],"type":"Point"}
}