{
  "type": "Feature",
  "properties": {
    "addr:full":"Calle de Torres Quevedo, 13 Salamanca Salamanca 37004",
    "addr:housenumber":"13",
    "addr:postcode":"37004",
    "addr:street":"Calle De Torres Quevedo",
    "iso:country":"ES",
    "sg:address":"Calle de Torres Quevedo, 13",
    "sg:city":"Salamanca",
    "sg:orig_category":"Inmobiliaria (agencias)",
    "sg:phone":"+34 923 12 42 51",
    "sg:postcode":"37004",
    "sg:province":"Salamanca",
    "wof:name":"Rufer Inversiones S.a.",
    "wof:placetype":"venue"
},
  "geometry": {"coordinates":[-5.6535711288,40.971157074],"type":"Point"}
}