{
  "type": "Feature",
  "properties": {
    "iso:country":"ES",
    "sg:address":"Avda Escaleritas, 64",
    "sg:city":"Palmas De Gran Canaria",
    "sg:orig_category":"Empresas De Portes Y Mensajer\u00cda",
    "sg:phone":"+34 928 25 04 24",
    "sg:postcode":"35011",
    "sg:province":"Las Palmas",
    "wof:name":"Mapocan S.l.",
    "wof:placetype":"venue"
},
  "geometry": {"coordinates":[-15.4455966949,28.1020584106],"type":"Point"}
}