{
  "type": "Feature",
  "properties": {
    "addr:full":"Pl. Iglesia, S/n Alarba Zaragoza 50345",
    "addr:housenumber":"s / n",
    "addr:postcode":"50345",
    "addr:street":"Pl. Iglesia",
    "iso:country":"ES",
    "sg:address":"Pl. Iglesia, S/n",
    "sg:city":"Alarba",
    "sg:orig_category":"Cajas Para Embalar",
    "sg:phone":"+34 976 89 42 81",
    "sg:postcode":"50345",
    "sg:province":"Zaragoza",
    "wof:name":"Caja Rural De Aragon S.coop Credito",
    "wof:placetype":"venue"
},
  "geometry": {"coordinates":[-1.6145160198,41.2063446045],"type":"Point"}
}