{
  "type": "Feature",
  "properties": {
    "iso:country":"ES",
    "sg:address":"Avda Aeroporto, 447",
    "sg:city":"Vigo",
    "sg:orig_category":"Producci\u00d3n, Comercio De Cereales",
    "sg:phone":"+34 986 48 69 06",
    "sg:postcode":"36215",
    "sg:province":"Pontevedra",
    "wof:name":"Agro Rinxela S.l",
    "wof:placetype":"venue"
},
  "geometry": {"coordinates":[-8.6619148254,42.2353935242],"type":"Point"}
}