{
  "type": "Feature",
  "properties": {
    "addr:full":"Otadui Zuhaiztia, 10 O\u00f1ati Guip\u00f9zcoa 20560",
    "addr:housenumber":"10",
    "addr:postcode":"20560",
    "addr:street":"Otadui Zuhaiztia;Guipu\u0300Zcoa",
    "iso:country":"ES",
    "sg:address":"Otadui Zuhaiztia, 10",
    "sg:city":"O\u00f1ati",
    "sg:orig_category":"Cajas De Ahorro",
    "sg:phone":"+34 943 78 23 11",
    "sg:postcode":"20560",
    "sg:province":"Guip\u00f9zcoa",
    "wof:name":"Caja Laboral Popular",
    "wof:placetype":"venue"
},
  "geometry": {"coordinates":[-2.4079990387,43.0313835144],"type":"Point"}
}