{
  "type": "Feature",
  "properties": {
    "addr:full":"Calle de Rio De Monelos, 18 Coru\u00d1a La Coru\u00f1a 15006",
    "addr:housenumber":"18",
    "addr:postcode":"15006",
    "addr:street":"Calle De Rio De Monelos;La Corun\u0303A",
    "iso:country":"ES",
    "sg:address":"Calle de Rio De Monelos, 18",
    "sg:city":"Coru\u00d1a",
    "sg:orig_category":"Sindicatos De Trabajadores",
    "sg:phone":"+34 981 13 20 54",
    "sg:postcode":"15006",
    "sg:province":"La Coru\u00f1a",
    "wof:name":"Fetico",
    "wof:placetype":"venue"
},
  "geometry": {"coordinates":[-8.3985290527,43.3560829163],"type":"Point"}
}