{
  "type": "Feature",
  "properties": {
    "iso:country":"ES",
    "sg:address":"Avda Gasteiz, 64",
    "sg:city":"Vitoria-gasteiz",
    "sg:orig_category":"Iglesia Cat\u00d3lica",
    "sg:phone":"+34 945 21 32 34",
    "sg:postcode":"01012",
    "sg:province":"\u00c1lava",
    "wof:name":"Parroquia San Mateo",
    "wof:placetype":"venue"
},
  "geometry": {"coordinates":[-2.6802721024,42.8510665894],"type":"Point"}
}