{
  "type": "Feature",
  "properties": {
    "iso:country":"ES",
    "sg:address":"Avda Aeronautica (la), 16",
    "sg:city":"Sevilla",
    "sg:orig_category":"Bazares, Art\u00cdculos De Limpieza Y De Cocina (al Por Menor)",
    "sg:phone":"+34 954 44 30 96",
    "sg:postcode":"41020",
    "sg:province":"Sevilla",
    "wof:name":"Merpali S.l.",
    "wof:placetype":"venue"
},
  "geometry": {"coordinates":[-5.9197177887,37.3893203735],"type":"Point"}
}