{
  "type": "Feature",
  "properties": {
    "iso:country":"ES",
    "sg:address":"Pl. Mayor, 13",
    "sg:city":"Viver",
    "sg:orig_category":"Ingeniero",
    "sg:phone":"+34 964 14 00 07",
    "sg:postcode":"12460",
    "sg:province":"Castell\u00f3n",
    "wof:name":"Euroestudios S.l.",
    "wof:placetype":"venue"
},
  "geometry": {"coordinates":[-0.5947989821,39.9213256836],"type":"Point"}
}