{
  "type": "Feature",
  "properties": {
    "iso:country":"ES",
    "sg:address":"Ctra Tias-macher, S/n",
    "sg:city":"Macher",
    "sg:orig_category":"Molduras, Junquillos, Listones Y Molduras Perforadas",
    "sg:phone":"+34 928 51 59 86",
    "sg:postcode":"35572",
    "sg:province":"Las Palmas",
    "wof:name":"Lazaro Momblona Jose Luis",
    "wof:placetype":"venue"
},
  "geometry": {"coordinates":[-13.6521291733,28.9543895721],"type":"Point"}
}