{
  "type": "Feature",
  "properties": {
    "iso:country":"ES",
    "sg:address":"Pol. Ind. La Drecera, 13",
    "sg:city":"Selva Del Camp",
    "sg:orig_category":"Discotecas Y Salas De Baile",
    "sg:phone":"+34 977 76 62 37",
    "sg:postcode":"43470",
    "sg:province":"Tarragona",
    "sg:website":"www.laterraclub.com",
    "wof:name":"Pedrojona S.l.",
    "wof:placetype":"venue"
},
  "geometry": {"coordinates":[1.1409749985,41.2144813538],"type":"Point"}
}