{
  "type": "Feature",
  "properties": {
    "iso:country":"ES",
    "sg:address":"Carrer de Castillejos, 385",
    "sg:city":"Barcelona",
    "sg:orig_category":"Ense\u00d1anza, Formaci\u00d3n Profesional: Aprendizaje",
    "sg:phone":"+34 934 46 44 50",
    "sg:postcode":"08025",
    "sg:province":"Barcelona",
    "wof:name":"Direccion General De La Policia",
    "wof:placetype":"venue"
},
  "geometry": {"coordinates":[2.1713330746,41.4116821289],"type":"Point"}
}