{
  "type": "Feature",
  "properties": {
    "iso:country":"ES",
    "sg:address":"Avda Linares Rivas, 43",
    "sg:city":"Coru\u00d1a",
    "sg:orig_category":"Quincaller\u00cda (al Por Menor)",
    "sg:phone":"+34 981 23 39 44",
    "sg:postcode":"15005",
    "sg:province":"La Coru\u00f1a",
    "wof:name":"Almacenes Torres Y Saez S. A.",
    "wof:placetype":"venue"
},
  "geometry": {"coordinates":[-8.4055299759,43.3621253967],"type":"Point"}
}