{
  "type": "Feature",
  "properties": {
    "iso:country":"ES",
    "sg:address":"Calle de Peru, 4",
    "sg:city":"Malaga",
    "sg:orig_category":"Abogados",
    "sg:phone":"+34 952 29 14 57",
    "sg:postcode":"29017",
    "sg:province":"M\u00e1laga",
    "wof:name":"Reyes Gallur Abogados S.l.",
    "wof:placetype":"venue"
},
  "geometry": {"coordinates":[-4.3728508949,36.7226867676],"type":"Point"}
}