{
  "type": "Feature",
  "properties": {
    "iso:country":"ES",
    "sg:address":"Cra. Nal. Tres-cents Quaranta, Km. 0282,0",
    "sg:city":"Bellvei",
    "sg:orig_category":"Licores (fabricaci\u00d3n, Al Por Mayor)",
    "sg:phone":"+34 977 16 87 01",
    "sg:postcode":"43719",
    "sg:province":"Tarragona",
    "wof:name":"Teichenne S.a.",
    "wof:placetype":"venue"
},
  "geometry": {"coordinates":[1.5798250437,41.2386817932],"type":"Point"}
}