{
  "type": "Feature",
  "properties": {
    "addr:full":"Calle de Ramon Y Cajal, 42 Miranda Ebro Burgos 09200",
    "addr:housenumber":"42",
    "addr:postcode":"09200",
    "addr:street":"Calle De Ramon Y Cajal",
    "iso:country":"ES",
    "sg:address":"Calle de Ramon Y Cajal, 42",
    "sg:city":"Miranda Ebro",
    "sg:orig_category":"Molduras, Junquillos, Listones Y Molduras Perforadas",
    "sg:phone":"+34 947 31 10 86",
    "sg:postcode":"09200",
    "sg:province":"Burgos",
    "wof:name":"Perez Arteaga Elias",
    "wof:placetype":"venue"
},
  "geometry": {"coordinates":[-2.9426140785,42.6877632141],"type":"Point"}
}