{
  "type": "Feature",
  "properties": {
    "addr:full":"Calle de Montevideo, 65 Palmas De Gran Canaria Las Palmas 35007",
    "addr:housenumber":"65",
    "addr:postcode":"35007",
    "addr:street":"Calle De Montevideo",
    "iso:country":"ES",
    "sg:address":"Calle de Montevideo, 65",
    "sg:city":"Palmas De Gran Canaria",
    "sg:orig_category":"Televisi\u00d3n, V\u00cddeo: Aparatos Y Accesorios (venta)",
    "sg:phone":"+34 928 22 73 34",
    "sg:postcode":"35007",
    "sg:province":"Las Palmas",
    "wof:name":"M.a. Master Audio S.l.",
    "wof:placetype":"venue"
},
  "geometry": {"coordinates":[-15.4329319,28.1360721588],"type":"Point"}
}