{
  "type": "Feature",
  "properties": {
    "addr:full":"Union Artistica El Cabo, 5 Sta Cruz Tenerife Santa Cruz De Tenerife 38003",
    "addr:housenumber":"5",
    "addr:postcode":"38003",
    "addr:street":"El Cabo;Sta Cruz Tenerife",
    "iso:country":"ES",
    "sg:address":"Union Artistica El Cabo, 5",
    "sg:city":"Sta Cruz Tenerife",
    "sg:orig_category":"Instalaci\u00d3n De Sanitarios",
    "sg:phone":"+34 922 28 88 61",
    "sg:postcode":"38003",
    "sg:province":"Santa Cruz De Tenerife",
    "wof:name":"Martinez-barona Zerolo Jorge",
    "wof:placetype":"venue"
},
  "geometry": {"coordinates":[-16.3326644897,28.4846744537],"type":"Point"}
}