{
  "type": "Feature",
  "properties": {
    "iso:country":"ES",
    "sg:address":"Calle de Mascaraque, 20",
    "sg:city":"Madrid",
    "sg:orig_category":"Postigos, Persianas Y Celos\u00cdas",
    "sg:phone":"+34 915 09 26 55",
    "sg:postcode":"28044",
    "sg:province":"Madrid",
    "wof:name":"Martinez Cattoni Ramon",
    "wof:placetype":"venue"
},
  "geometry": {"coordinates":[-3.7580559254,40.374332428],"type":"Point"}
}