{
  "type": "Feature",
  "properties": {
    "addr:full":"Carrer de Pintor Mir, 19 Barcelona Barcelona 08031",
    "addr:housenumber":"19",
    "addr:postcode":"08031",
    "addr:street":"Carrer De Pintor Mir",
    "iso:country":"ES",
    "sg:address":"Carrer de Pintor Mir, 19",
    "sg:city":"Barcelona",
    "sg:orig_category":"Empresas De Carpinter\u00cda Met\u00c1lica",
    "sg:phone":"+34 934 27 10 44",
    "sg:postcode":"08031",
    "sg:province":"Barcelona",
    "wof:name":"Rosell Del Pino Andres",
    "wof:placetype":"venue"
},
  "geometry": {"coordinates":[2.1661720276,41.4283714294],"type":"Point"}
}