{
  "type": "Feature",
  "properties": {
    "iso:country":"ES",
    "sg:address":"Calle de Gabino Tejado, 60",
    "sg:city":"Badajoz",
    "sg:orig_category":"Reparaciones Y Remolcado De Veh\u00cdculos",
    "sg:phone":"+34 924 22 43 83",
    "sg:postcode":"06008",
    "sg:province":"Badajoz",
    "wof:name":"Carlain S.l.",
    "wof:placetype":"venue"
},
  "geometry": {"coordinates":[-6.9571938515,38.8779335022],"type":"Point"}
}