{
  "type": "Feature",
  "properties": {
    "addr:full":"Calle de Guindalera, 6 Najera La Rioja 26300",
    "addr:housenumber":"6",
    "addr:postcode":"26300",
    "addr:street":"Calle De Guindalera;Rioja",
    "iso:country":"ES",
    "sg:address":"Calle de Guindalera, 6",
    "sg:city":"Najera",
    "sg:orig_category":"Material Y Equipo Para Panader\u00cdas Y Pasteler\u00cdas",
    "sg:phone":"+34 941 36 02 13",
    "sg:postcode":"26300",
    "sg:province":"La Rioja",
    "wof:name":"Sanz Mainez Alejandro",
    "wof:placetype":"venue"
},
  "geometry": {"coordinates":[-2.7273440361,42.4163665771],"type":"Point"}
}