{
  "type": "Feature",
  "properties": {
    "iso:country":"ES",
    "sg:address":"Paraje Illarra, S/n",
    "sg:city":"Etxarri-aranatz",
    "sg:orig_category":"Poller\u00cda Y Caza (al Por Menor)",
    "sg:phone":"+34 948 39 60 44",
    "sg:postcode":"31820",
    "sg:province":"Navarra",
    "wof:name":"Lopez Azpilicueta Jesus Ignacio",
    "wof:placetype":"venue"
},
  "geometry": {"coordinates":[-2.0638840199,42.9061965942],"type":"Point"}
}