{
  "type": "Feature",
  "properties": {
    "iso:country":"ES",
    "sg:address":"Carrer de Sant Antoni Maria Claret, 424",
    "sg:city":"Barcelona",
    "sg:orig_category":"Porcelanas, Azulejos (fabricaci\u00d3n, Al Por Mayor)",
    "sg:phone":"+34 933 51 11 13",
    "sg:postcode":"08027",
    "sg:province":"Barcelona",
    "wof:name":"Malo De La Torre Jose Antonio",
    "wof:placetype":"venue"
},
  "geometry": {"coordinates":[2.1842579842,41.4184341431],"type":"Point"}
}