{
  "type": "Feature",
  "properties": {
    "addr:full":"Calle de Blasco Vichares, 6 Castellon Castell\u00f3n 12005",
    "addr:housenumber":"6",
    "addr:postcode":"12005",
    "addr:street":"Calle De Blasco Vichares;Castello\u0301N",
    "iso:country":"ES",
    "sg:address":"Calle de Blasco Vichares, 6",
    "sg:city":"Castellon",
    "sg:orig_category":"Electricidad: Instaladores",
    "sg:phone":"+34 964 34 06 66",
    "sg:postcode":"12005",
    "sg:province":"Castell\u00f3n",
    "wof:name":"Montajes Electricos Juan Vinuesa S.l.",
    "wof:placetype":"venue"
},
  "geometry": {"coordinates":[-0.0430652015,39.9774665833],"type":"Point"}
}