{
  "type": "Feature",
  "properties": {
    "addr:full":"Calle de Minas, 13 Alcorcon Madrid 28925",
    "addr:housenumber":"13",
    "addr:postcode":"28925",
    "addr:street":"Calle De Minas",
    "iso:country":"ES",
    "sg:address":"Calle de Minas, 13",
    "sg:city":"Alcorcon",
    "sg:orig_category":"Comercio De Piezas De Recambio Y De Accesorios De Veh\u00cdculos, Veh\u00cdculos Industriales",
    "sg:phone":"+34 916 43 19 08",
    "sg:postcode":"28925",
    "sg:province":"Madrid",
    "wof:name":"Std Del Motor S.l.",
    "wof:placetype":"venue"
},
  "geometry": {"coordinates":[-3.8157110214,40.3375320435],"type":"Point"}
}