{
  "type": "Feature",
  "properties": {
    "iso:country":"ES",
    "sg:address":"Carr General Guell, 12",
    "sg:city":"Cervera",
    "sg:orig_category":"Transportes Por Carretera: Lotes Completos, Mercanc\u00cdas Diversas",
    "sg:phone":"+34 973 53 02 09",
    "sg:postcode":"25200",
    "sg:province":"Lleida",
    "wof:name":"Pedros Puig Ramon",
    "wof:placetype":"venue"
},
  "geometry": {"coordinates":[1.2743010521,41.6716499329],"type":"Point"}
}