{
  "type": "Feature",
  "properties": {
    "iso:country":"ES",
    "sg:address":"Carrer de Corsega, 594",
    "sg:city":"Barcelona",
    "sg:orig_category":"Muebles Y Accesorios Para Cocinas Y Cuartos De Ba\u00d1o (al Por Menor)",
    "sg:phone":"+34 934 33 52 87",
    "sg:postcode":"08025",
    "sg:province":"Barcelona",
    "sg:website":"www.maipol.com",
    "wof:name":"Oyarzun Y Vargas Group Serveices Sl",
    "wof:placetype":"venue"
},
  "geometry": {"coordinates":[2.1757400036,41.4086952209],"type":"Point"}
}