{
  "type": "Feature",
  "properties": {
    "iso:country":"ES",
    "sg:address":"Calle de Villafranca Del Bierzo, 36",
    "sg:city":"Fuenlabrada",
    "sg:orig_category":"Pintura, Barniz, Productos Asimilables (fabricaci\u00d3n, Al Por Mayor)",
    "sg:phone":"+34 916 42 12 14",
    "sg:postcode":"28947",
    "sg:province":"Madrid",
    "wof:name":"Orita S. A.",
    "wof:placetype":"venue"
},
  "geometry": {"coordinates":[-3.7476181984,40.2635879517],"type":"Point"}
}