{
  "type": "Feature",
  "properties": {
    "addr:full":"Calle de Angosta, 22 Castellar Ja\u00e9n 23260",
    "addr:housenumber":"22",
    "addr:postcode":"23260",
    "addr:street":"Calle De Angosta",
    "iso:country":"ES",
    "sg:address":"Calle de Angosta, 22",
    "sg:city":"Castellar",
    "sg:orig_category":"Guarder\u00cdas",
    "sg:phone":"+34 953 46 04 01",
    "sg:postcode":"23260",
    "sg:province":"Ja\u00e9n",
    "wof:name":"Comercial Acazar S.l.",
    "wof:placetype":"venue"
},
  "geometry": {"coordinates":[-3.129226923,38.257270813],"type":"Point"}
}