{
  "type": "Feature",
  "properties": {
    "iso:country":"ES",
    "sg:address":"Carr Palma, De, 67",
    "sg:city":"Consell",
    "sg:orig_category":"Alimentaci\u00d3n General (al Por Menor)",
    "sg:phone":"+34 971 62 21 57",
    "sg:postcode":"07330",
    "sg:province":"Islas Baleares",
    "wof:name":"Busquets Isern Jorge",
    "wof:placetype":"venue"
},
  "geometry": {"coordinates":[2.8105449677,39.6676445007],"type":"Point"}
}