{
  "type": "Feature",
  "properties": {
    "addr:full":"Avda Galicia, S/n Muros Asturias 33138",
    "addr:housenumber":"s / n",
    "addr:postcode":"33138",
    "addr:street":"Avda Galicia",
    "iso:country":"ES",
    "sg:address":"Avda Galicia, S/n",
    "sg:city":"Muros",
    "sg:orig_category":"Quincaller\u00cda (al Por Menor)",
    "sg:phone":"+34 985 58 31 00",
    "sg:postcode":"33138",
    "sg:province":"Asturias",
    "wof:name":"Lopez Rodriguez Juan Jose",
    "wof:placetype":"venue"
},
  "geometry": {"coordinates":[-6.1026439667,43.539024353],"type":"Point"}
}