{
  "type": "Feature",
  "properties": {
    "addr:full":"Calle de Mediodia, 2 Algezares Murcia 30157",
    "addr:housenumber":"2",
    "addr:postcode":"30157",
    "addr:street":"Calle De Mediodia",
    "iso:country":"ES",
    "sg:address":"Calle de Mediodia, 2",
    "sg:city":"Algezares",
    "sg:orig_category":"Teatro, Ballet, Danza (agrupaciones, Compa\u00d1\u00cdas)",
    "sg:phone":"+34 968 84 00 99",
    "sg:postcode":"30157",
    "sg:province":"Murcia",
    "wof:name":"Dado Producciones Teatrales S.l.",
    "wof:placetype":"venue"
},
  "geometry": {"coordinates":[-1.1152039766,37.9410934448],"type":"Point"}
}