{
  "type": "Feature",
  "properties": {
    "iso:country":"ES",
    "sg:address":"Calle de Jorge Manrique, S/n",
    "sg:city":"Palencia",
    "sg:orig_category":"Molduras, Junquillos, Listones Y Molduras Perforadas",
    "sg:phone":"+34 979 74 20 14",
    "sg:postcode":"34001",
    "sg:province":"Palencia",
    "wof:name":"Remiro Sobreviela Agustin",
    "wof:placetype":"venue"
},
  "geometry": {"coordinates":[-4.5358991623,42.0113182068],"type":"Point"}
}