{
  "type": "Feature",
  "properties": {
    "iso:country":"ES",
    "sg:address":"Carrer de Doctor Valls, 25",
    "sg:city":"Barcelona",
    "sg:orig_category":"Audiovisuales: Material Y Accesorios (al Por Menor)",
    "sg:phone":"+34 934 36 60 82",
    "sg:postcode":"08041",
    "sg:province":"Barcelona",
    "wof:name":"Trayson S. A. L.",
    "wof:placetype":"venue"
},
  "geometry": {"coordinates":[2.1789851189,41.4198722839],"type":"Point"}
}