{
  "type": "Feature",
  "properties": {
    "addr:full":"Avgd Alfons Xiii, 14 Badalona Barcelona 08912",
    "addr:housenumber":"14",
    "addr:postcode":"08912",
    "addr:street":"Alfons Xiii",
    "iso:country":"ES",
    "sg:address":"Avgd Alfons Xiii, 14",
    "sg:city":"Badalona",
    "sg:orig_category":"Abogados",
    "sg:phone":"+34 933 97 32 15",
    "sg:postcode":"08912",
    "sg:province":"Barcelona",
    "wof:name":"Cavaller Idiarte Antonio Ramon",
    "wof:placetype":"venue"
},
  "geometry": {"coordinates":[2.2385859489,41.4450721741],"type":"Point"}
}