{
  "type": "Feature",
  "properties": {
    "iso:country":"ES",
    "sg:address":"Calle de Corredera, 25",
    "sg:city":"Almansa",
    "sg:orig_category":"Promotores Constructores",
    "sg:phone":"+34 967 31 21 44",
    "sg:postcode":"02640",
    "sg:province":"Albacete",
    "wof:name":"Davisto Promociones S.l.",
    "wof:placetype":"venue"
},
  "geometry": {"coordinates":[-1.0957125425,38.8672790527],"type":"Point"}
}