{
  "type": "Feature",
  "properties": {
    "addr:full":"Calle de Camino Del Hoyo, 2 Valencina Concepcion Sevilla 41907",
    "addr:housenumber":"2",
    "addr:postcode":"41907",
    "addr:street":"Calle De Camino Del Hoyo",
    "iso:country":"ES",
    "sg:address":"Calle de Camino Del Hoyo, 2",
    "sg:city":"Valencina Concepcion",
    "sg:orig_category":"Empresas De Carpinter\u00cda Met\u00c1lica",
    "sg:phone":"+34 955 72 00 60",
    "sg:postcode":"41907",
    "sg:province":"Sevilla",
    "wof:name":"Gelo Vicente Manuel",
    "wof:placetype":"venue"
},
  "geometry": {"coordinates":[-6.0792546272,37.4140472412],"type":"Point"}
}