{
  "type": "Feature",
  "properties": {
    "iso:country":"ES",
    "sg:address":"Calle de Casta\u00d1o (el), 5",
    "sg:city":"Cordoba",
    "sg:orig_category":"Alimentaci\u00d3n General (al Por Menor)",
    "sg:phone":"+34 957 28 19 00",
    "sg:postcode":"14006",
    "sg:province":"C\u00f3rdoba",
    "wof:name":"Barbarroja Vacas Angel Luis",
    "wof:placetype":"venue"
},
  "geometry": {"coordinates":[-4.7811732292,37.8993110657],"type":"Point"}
}