{
  "type": "Feature",
  "properties": {
    "iso:country":"ES",
    "sg:address":"Calle de San Roque, 16",
    "sg:city":"Coru\u00d1a",
    "sg:orig_category":"Transporte En General",
    "sg:phone":"+34 981 20 44 91",
    "sg:postcode":"15002",
    "sg:province":"La Coru\u00f1a",
    "wof:name":"Juan Vazquez Y Sobrinos S.l.",
    "wof:placetype":"venue"
},
  "geometry": {"coordinates":[-8.3977518082,43.3737411499],"type":"Point"}
}