{
  "type": "Feature",
  "properties": {
    "iso:country":"ES",
    "sg:address":"Carrer de Trinitat, 1",
    "sg:city":"Sitges",
    "sg:orig_category":"Fabricaci\u00d3n, Reparaci\u00d3n Y Mantenimiento De Construcciones Navales Y Fluviales",
    "sg:phone":"+34 938 94 60 85",
    "sg:postcode":"08870",
    "sg:province":"Barcelona",
    "wof:name":"Navas Perez Emilio",
    "wof:placetype":"venue"
},
  "geometry": {"coordinates":[1.8249030113,41.2431716919],"type":"Point"}
}