{
  "type": "Feature",
  "properties": {
    "addr:full":"Carr Nelson Mandela, 16 Badalona Barcelona 08915",
    "addr:housenumber":"16",
    "addr:postcode":"08915",
    "addr:street":"Carr Nelson Mandela",
    "iso:country":"ES",
    "sg:address":"Carr Nelson Mandela, 16",
    "sg:city":"Badalona",
    "sg:orig_category":"Lencer\u00cda Femenina, Corseter\u00cda, Trajes De Ba\u00d1o (al Por Menor)",
    "sg:phone":"+34 933 95 66 92",
    "sg:postcode":"08915",
    "sg:province":"Barcelona",
    "wof:name":"Torres Viedma Alicia Maria",
    "wof:placetype":"venue"
},
  "geometry": {"coordinates":[2.2470281124,41.4633140564],"type":"Point"}
}