{
  "type": "Feature",
  "properties": {
    "addr:full":"Calle de Juan Esplandiu, S/n Madrid Madrid 28007",
    "addr:housenumber":"s / n",
    "addr:postcode":"28007",
    "addr:street":"Calle De Juan Esplandiu",
    "iso:country":"ES",
    "sg:address":"Calle de Juan Esplandiu, S/n",
    "sg:city":"Madrid",
    "sg:orig_category":"Empresarios",
    "sg:phone":"+34 915 73 75 08",
    "sg:postcode":"28007",
    "sg:province":"Madrid",
    "sg:website":"www.fuhem.es",
    "wof:name":"Fundacion Benefico Social Hogar Del Empl",
    "wof:placetype":"venue"
},
  "geometry": {"coordinates":[-3.6645689011,40.4187431335],"type":"Point"}
}