{
  "type": "Feature",
  "properties": {
    "addr:full":"Rua Orfas (das), 34 Santiago De Compostela La Coru\u00f1a 15703",
    "addr:housenumber":"34",
    "addr:postcode":"15703",
    "addr:street":"Rua Orfas Das;Corun\u0303A",
    "iso:country":"ES",
    "sg:address":"Rua Orfas (das), 34",
    "sg:city":"Santiago De Compostela",
    "sg:orig_category":"Agencias Y Agentes Comerciales, Representantes",
    "sg:phone":"+34 981 57 63 54",
    "sg:postcode":"15703",
    "sg:province":"La Coru\u00f1a",
    "wof:name":"Mjcb Santiago",
    "wof:placetype":"venue"
},
  "geometry": {"coordinates":[-8.5443334579,42.8771972656],"type":"Point"}
}