{
  "type": "Feature",
  "properties": {
    "iso:country":"ES",
    "sg:address":"Carr Magallanes, 5",
    "sg:city":"Puerto De Pollen\u00c7a",
    "sg:orig_category":"Organizaciones Profesionales",
    "sg:phone":"+34 971 86 59 96",
    "sg:postcode":"07470",
    "sg:province":"Islas Baleares",
    "wof:name":"Ordo\u00f1ez Mu\u00f1oz Antonio",
    "wof:placetype":"venue"
},
  "geometry": {"coordinates":[3.0821900368,39.9063034058],"type":"Point"}
}