{
  "type": "Feature",
  "properties": {
    "addr:full":"Av Bartomeu De Rosello, 3 Eivissa Islas Baleares 07800",
    "addr:housenumber":"3",
    "addr:postcode":"07800",
    "addr:street":"Av Bartomeu De Rosello",
    "iso:country":"ES",
    "sg:address":"Av Bartomeu De Rosello, 3",
    "sg:city":"Eivissa",
    "sg:orig_category":"Ropa Para Se\u00d1oras Y Caballeros (al Por Menor)",
    "sg:phone":"+34 971 31 41 23",
    "sg:postcode":"07800",
    "sg:province":"Islas Baleares",
    "wof:name":"Bibas Y Renner S.cv.",
    "wof:placetype":"venue"
},
  "geometry": {"coordinates":[1.4343810081,38.9104003906],"type":"Point"}
}