{
  "type": "Feature",
  "properties": {
    "addr:full":"Calle de Alicante, 19 Novelda Alicante 03660",
    "addr:housenumber":"19",
    "addr:postcode":"03660",
    "addr:street":"Calle De Alicante",
    "iso:country":"ES",
    "sg:address":"Calle de Alicante, 19",
    "sg:city":"Novelda",
    "sg:orig_category":"Muebles, Minoristas",
    "sg:phone":"+34 965 60 51 54",
    "sg:postcode":"03660",
    "sg:province":"Alicante",
    "sg:website":"info@niwalamobiliaria.com",
    "wof:name":"Niwala Mobiliario Cdad",
    "wof:placetype":"venue"
},
  "geometry": {"coordinates":[-0.7684834003,38.387298584],"type":"Point"}
}