{
  "type": "Feature",
  "properties": {
    "addr:full":"Calle de San Miguel, 8 Pi\u00e7a De Campos Palencia 34430",
    "addr:housenumber":"8",
    "addr:postcode":"34430",
    "addr:street":"Calle De San Miguel",
    "iso:country":"ES",
    "sg:address":"Calle de San Miguel, 8",
    "sg:city":"Pi\u00e7a De Campos",
    "sg:orig_category":"Reparaciones Y Remolcado De Veh\u00cdculos",
    "sg:phone":"+34 979 15 30 32",
    "sg:postcode":"34430",
    "sg:province":"Palencia",
    "wof:name":"Salda\u00f1a Rojas Isidro",
    "wof:placetype":"venue"
},
  "geometry": {"coordinates":[-4.436478138,42.2138214111],"type":"Point"}
}