{
  "type": "Feature",
  "properties": {
    "addr:full":"Avda Berlin (de), 4 Coslada Madrid 28820",
    "addr:housenumber":"4",
    "addr:postcode":"28820",
    "addr:street":"Avda Berlin De",
    "iso:country":"ES",
    "sg:address":"Avda Berlin (de), 4",
    "sg:city":"Coslada",
    "sg:orig_category":"Centros De Educaci\u00d3n Especial",
    "sg:phone":"+34 916 71 25 81",
    "sg:postcode":"28820",
    "sg:province":"Madrid",
    "wof:name":"Comunidad Autonoma De Madrid-centros De Educacion",
    "wof:placetype":"venue"
},
  "geometry": {"coordinates":[-3.5387310982,40.4205970764],"type":"Point"}
}