{
  "type": "Feature",
  "properties": {
    "iso:country":"ES",
    "sg:address":"Pase Canalejas, 57",
    "sg:city":"Santander",
    "sg:orig_category":"Papeler\u00cdas: Art\u00cdculos (al Por Mayor)",
    "sg:phone":"+34 942 27 42 28",
    "sg:postcode":"39004",
    "sg:province":"Cantabria",
    "wof:name":"Hernandez Bedia Eduardo",
    "wof:placetype":"venue"
},
  "geometry": {"coordinates":[-3.7901399136,43.4651145935],"type":"Point"}
}