{
  "type": "Feature",
  "properties": {
    "addr:full":"Calle de Daroca, 79 Zaragoza Zaragoza 50017",
    "addr:housenumber":"79",
    "addr:postcode":"50017",
    "addr:street":"Calle De Daroca",
    "iso:country":"ES",
    "sg:address":"Calle de Daroca, 79",
    "sg:city":"Zaragoza",
    "sg:orig_category":"Cajas De Ahorro",
    "sg:phone":"+34 976 53 33 24",
    "sg:postcode":"50017",
    "sg:province":"Zaragoza",
    "sg:website":"www.ibercaja.es",
    "wof:name":"Caja De Ahorros Y Monte De Piedad De Zaragoza Aragon Y Rioja",
    "wof:placetype":"venue"
},
  "geometry": {"coordinates":[-0.9093589783,41.6498985291],"type":"Point"}
}