{
  "type": "Feature",
  "properties": {
    "addr:full":"Rua Areal (do), 63 Lalin Pontevedra 36500",
    "addr:housenumber":"63",
    "addr:postcode":"36500",
    "addr:street":"Rua Areal Do",
    "iso:country":"ES",
    "sg:address":"Rua Areal (do), 63",
    "sg:city":"Lalin",
    "sg:orig_category":"Centros Empresariales",
    "sg:phone":"+34 986 78 22 78",
    "sg:postcode":"36500",
    "sg:province":"Pontevedra",
    "wof:name":"Agrobotica Lalin S.l.",
    "wof:placetype":"venue"
},
  "geometry": {"coordinates":[-8.1039390564,42.6687088013],"type":"Point"}
}