{
  "type": "Feature",
  "properties": {
    "addr:full":"Calle de Palmera, 5 Bornos C\u00e1diz 11640",
    "addr:housenumber":"5",
    "addr:postcode":"11640",
    "addr:street":"Calle De Palmera;Ca\u0301Diz",
    "iso:country":"ES",
    "sg:address":"Calle de Palmera, 5",
    "sg:city":"Bornos",
    "sg:orig_category":"Fabricaci\u00d3n Y Venta De Volquetes Y Remolques",
    "sg:phone":"+34 956 71 22 27",
    "sg:postcode":"11640",
    "sg:province":"C\u00e1diz",
    "wof:name":"Gonzalez Rodriguez Rafael",
    "wof:placetype":"venue"
},
  "geometry": {"coordinates":[-5.7438669205,36.8206214905],"type":"Point"}
}