{
  "type": "Feature",
  "properties": {
    "iso:country":"ES",
    "sg:address":"Rua Colon, 32",
    "sg:city":"Ourense",
    "sg:orig_category":"Bisuter\u00cda, Joyer\u00cda, Relojer\u00cda (al Por Menor)",
    "sg:phone":"+34 988 22 30 78",
    "sg:postcode":"32005",
    "sg:province":"Ourense",
    "wof:name":"Alvarez Alvarez Juan",
    "wof:placetype":"venue"
},
  "geometry": {"coordinates":[-7.8636617661,42.3337593079],"type":"Point"}
}