{
  "type": "Feature",
  "properties": {
    "iso:country":"ES",
    "sg:address":"Praz Galicia (de), 9",
    "sg:city":"Vilagarcia",
    "sg:orig_category":"Agencias Y Asesores De Publicidad",
    "sg:phone":"+34 986 56 51 52",
    "sg:postcode":"36600",
    "sg:province":"Pontevedra",
    "sg:website":"www.elidealgallego.com",
    "wof:name":"Editorial La Capital S.l.",
    "wof:placetype":"venue"
},
  "geometry": {"coordinates":[-8.7652978897,42.5917396545],"type":"Point"}
}