{
  "type": "Feature",
  "properties": {
    "iso:country":"ES",
    "sg:address":"Calle de Gordoniz, 27",
    "sg:city":"Bilbao",
    "sg:orig_category":"Servicios De Telecomunicaciones",
    "sg:phone":"+34 944 43 96 14",
    "sg:postcode":"48010",
    "sg:province":"Vizcaya",
    "wof:name":"Arata Logyst S.l.",
    "wof:placetype":"venue"
},
  "geometry": {"coordinates":[-2.9409842491,43.2579727173],"type":"Point"}
}