{
  "type": "Feature",
  "properties": {
    "addr:full":"Barr Nuevo, 2 Santalecina Huesca 22411",
    "addr:housenumber":"2",
    "addr:postcode":"22411",
    "addr:street":"Nuevo",
    "iso:country":"ES",
    "sg:address":"Barr Nuevo, 2",
    "sg:city":"Santalecina",
    "sg:orig_category":"Agencias Y Agentes Comerciales, Representantes",
    "sg:phone":"+34 974 41 30 46",
    "sg:postcode":"22411",
    "sg:province":"Huesca",
    "wof:name":"Lacosta Avilla Miguel Angel",
    "wof:placetype":"venue"
},
  "geometry": {"coordinates":[0.1125029996,41.7797851562],"type":"Point"}
}