{
  "type": "Feature",
  "properties": {
    "iso:country":"ES",
    "sg:address":"Plaz San Miguel, 4",
    "sg:city":"Valsequillo",
    "sg:orig_category":"Molduras, Junquillos, Listones Y Molduras Perforadas",
    "sg:phone":"+34 928 57 02 22",
    "sg:postcode":"35217",
    "sg:province":"Las Palmas",
    "wof:name":"Liria Ramirez Bartolome",
    "wof:placetype":"venue"
},
  "geometry": {"coordinates":[-15.4914102554,27.991230011],"type":"Point"}
}