{
  "type": "Feature",
  "properties": {
    "addr:full":"Carrer de Montseny, 8 Santa Perpetua De Mogoda Barcelona 08130",
    "addr:housenumber":"8",
    "addr:postcode":"08130",
    "addr:street":"Carrer De Montseny",
    "iso:country":"ES",
    "sg:address":"Carrer de Montseny, 8",
    "sg:city":"Santa Perpetua De Mogoda",
    "sg:orig_category":"Asesor\u00cda Sobre Comunicaci\u00d3n De Empresas",
    "sg:phone":"+34 935 44 61 51",
    "sg:postcode":"08130",
    "sg:province":"Barcelona",
    "wof:name":"Gestem Assesors 2004 S.l.",
    "wof:placetype":"venue"
},
  "geometry": {"coordinates":[2.1815869808,41.5343742371],"type":"Point"}
}