{
  "type": "Feature",
  "properties": {
    "addr:full":"Plaz Jimenez Diaz, 8 Getafe Madrid 28903",
    "addr:housenumber":"8",
    "addr:postcode":"28903",
    "addr:street":"Diaz",
    "iso:country":"ES",
    "sg:address":"Plaz Jimenez Diaz, 8",
    "sg:city":"Getafe",
    "sg:orig_category":"Electricidad: Instaladores",
    "sg:phone":"+34 916 96 07 17",
    "sg:postcode":"28903",
    "sg:province":"Madrid",
    "wof:name":"Loga Electricidad-iluminacion C.b.",
    "wof:placetype":"venue"
},
  "geometry": {"coordinates":[-3.7212650776,40.314868927],"type":"Point"}
}