{
  "type": "Feature",
  "properties": {
    "addr:full":"Rua Marques De Valladares, 3 Vigo Pontevedra 36201",
    "addr:housenumber":"3",
    "addr:postcode":"36201",
    "addr:street":"Rua Marques De Valladares",
    "iso:country":"ES",
    "sg:address":"Rua Marques De Valladares, 3",
    "sg:city":"Vigo",
    "sg:orig_category":"Agencias De Viajes",
    "sg:phone":"+34 986 43 50 00",
    "sg:postcode":"36201",
    "sg:province":"Pontevedra",
    "wof:name":"Viajes Venezuela S. A.",
    "wof:placetype":"venue"
},
  "geometry": {"coordinates":[-8.7241973877,42.2384223938],"type":"Point"}
}