{
  "type": "Feature",
  "properties": {
    "addr:full":"Pase Maritimo Aguadulce, 10 Aguadulce Almer\u00eda 04720",
    "addr:housenumber":"10",
    "addr:postcode":"04720",
    "addr:street":"Aguadulce;Almeri\u0301A",
    "iso:country":"ES",
    "sg:address":"Pase Maritimo Aguadulce, 10",
    "sg:city":"Aguadulce",
    "sg:orig_category":"Caf\u00c9s, Bares, Cervecer\u00cdas",
    "sg:phone":"+34 950 55 05 30",
    "sg:postcode":"04720",
    "sg:province":"Almer\u00eda",
    "wof:name":"Lara Aranda Jose Manuel",
    "wof:placetype":"venue"
},
  "geometry": {"coordinates":[-2.5711190701,36.8077964783],"type":"Point"}
}