{
  "type": "Feature",
  "properties": {
    "addr:full":"Calle de Domingo Juliana, 14 Gijon Asturias 33212",
    "addr:housenumber":"14",
    "addr:postcode":"33212",
    "addr:street":"Calle De Domingo Juliana",
    "iso:country":"ES",
    "sg:address":"Calle de Domingo Juliana, 14",
    "sg:city":"Gijon",
    "sg:orig_category":"Farmacias",
    "sg:phone":"+34 985 32 19 23",
    "sg:postcode":"33212",
    "sg:province":"Asturias",
    "wof:name":"Bascones Martinez Magdalena",
    "wof:placetype":"venue"
},
  "geometry": {"coordinates":[-5.6958470345,43.5394744873],"type":"Point"}
}