{
  "type": "Feature",
  "properties": {
    "addr:full":"Avda Ancha De Castelar, 88 San Vicente Del Raspeig-sant Vicent Del Raspeig Alicante 03690",
    "addr:housenumber":"88",
    "addr:postcode":"03690",
    "addr:street":"Avda Ancha De Castelar",
    "iso:country":"ES",
    "sg:address":"Avda Ancha De Castelar, 88",
    "sg:city":"San Vicente Del Raspeig-sant Vicent Del Raspeig",
    "sg:orig_category":"Fisioterapia",
    "sg:phone":"+34 965 66 98 30",
    "sg:postcode":"03690",
    "sg:province":"Alicante",
    "wof:name":"Kinesan C.b.",
    "wof:placetype":"venue"
},
  "geometry": {"coordinates":[-0.5232909918,38.3985061646],"type":"Point"}
}