{
  "type": "Feature",
  "properties": {
    "iso:country":"ES",
    "sg:address":"Calle de Cobalto, S/n",
    "sg:city":"Valladolid",
    "sg:orig_category":"Venta, Montaje De Neum\u00c1ticos",
    "sg:phone":"+34 983 30 72 55",
    "sg:postcode":"47012",
    "sg:province":"Valladolid",
    "wof:name":"Omnia Motor S.a.",
    "wof:placetype":"venue"
},
  "geometry": {"coordinates":[-4.7044382095,41.6211166382],"type":"Point"}
}