{
  "type": "Feature",
  "properties": {
    "iso:country":"ES",
    "sg:address":"Cargadero, S/n",
    "sg:city":"Cargadoiro",
    "sg:orig_category":"Mec\u00c1nico Del Autom\u00d3vil",
    "sg:phone":"+34 982 12 84 98",
    "sg:postcode":"27700",
    "sg:province":"Lugo",
    "wof:name":"Cartoy Gonzalez Pablo",
    "wof:placetype":"venue"
},
  "geometry": {"coordinates":[-7.0403847694,43.5336265564],"type":"Point"}
}