{
  "type": "Feature",
  "properties": {
    "addr:full":"Luga Vista De Yaiza, S/n Yaiza Las Palmas 35570",
    "addr:housenumber":"s / n",
    "addr:postcode":"35570",
    "addr:street":"Luga Vista De Yaiza",
    "iso:country":"ES",
    "sg:address":"Luga Vista De Yaiza, S/n",
    "sg:city":"Yaiza",
    "sg:orig_category":"Molduras, Junquillos, Listones Y Molduras Perforadas",
    "sg:phone":"+34 928 83 00 97",
    "sg:postcode":"35570",
    "sg:province":"Las Palmas",
    "wof:name":"Eugenio Camacho Angel",
    "wof:placetype":"venue"
},
  "geometry": {"coordinates":[-13.772354126,28.9544143677],"type":"Point"}
}