{
  "type": "Feature",
  "properties": {
    "addr:full":"Calle de Zurreros, S/n Noblejas Toledo 45350",
    "addr:housenumber":"s / n",
    "addr:postcode":"45350",
    "addr:street":"Calle De Zurreros",
    "iso:country":"ES",
    "sg:address":"Calle de Zurreros, S/n",
    "sg:city":"Noblejas",
    "sg:orig_category":"Productores Recolectores, Venta Directa De Vinos",
    "sg:phone":"+34 925 14 09 10",
    "sg:postcode":"45350",
    "sg:province":"Toledo",
    "wof:name":"D.o.5 Hispanobodegas, S.l.",
    "wof:placetype":"venue"
},
  "geometry": {"coordinates":[-3.4526689053,39.9769210815],"type":"Point"}
}