{
  "type": "Feature",
  "properties": {
    "iso:country":"ES",
    "sg:address":"Calle de Leales De Aljubarrota, 14",
    "sg:city":"Soria",
    "sg:orig_category":"Alimentaci\u00d3n General (al Por Menor)",
    "sg:phone":"+34 975 22 60 50",
    "sg:postcode":"42004",
    "sg:province":"Soria",
    "wof:name":"Eurojimal S. L.",
    "wof:placetype":"venue"
},
  "geometry": {"coordinates":[-2.4777081013,41.768321991],"type":"Point"}
}