{
  "type": "Feature",
  "properties": {
    "addr:full":"Ctra Las Navas-san Calixto, S/n Navas De La Concepcion Sevilla 41460",
    "addr:housenumber":"s / n",
    "addr:postcode":"41460",
    "addr:street":"Ctra Las Navas-San Calixto",
    "iso:country":"ES",
    "sg:address":"Ctra Las Navas-san Calixto, S/n",
    "sg:city":"Navas De La Concepcion",
    "sg:orig_category":"Charcuter\u00cdas (al Por Mayor)",
    "sg:phone":"+34 955 88 50 46",
    "sg:postcode":"41460",
    "sg:province":"Sevilla",
    "wof:name":"Dehesa Madera S.l.l.",
    "wof:placetype":"venue"
},
  "geometry": {"coordinates":[-5.4644980431,37.9328231812],"type":"Point"}
}