{
  "type": "Feature",
  "properties": {
    "iso:country":"ES",
    "sg:address":"Castellar, 56",
    "sg:city":"Murcia",
    "sg:orig_category":"Fabricaci\u00d3n, Venta, Instalaci\u00d3n De R\u00d3tulos, De R\u00d3tulos Luminosos",
    "sg:phone":"+34 902 10 05 97",
    "sg:postcode":"30110",
    "sg:province":"Murcia",
    "wof:name":"Internacional De Rotulos Publicos S.l.",
    "wof:placetype":"venue"
},
  "geometry": {"coordinates":[-1.1360189915,38.0214653015],"type":"Point"}
}