{
  "type": "Feature",
  "properties": {
    "iso:country":"ES",
    "sg:address":"Ctra Soria-plasencia, Km. 0021,7",
    "sg:city":"Barco De Avila",
    "sg:orig_category":"Mec\u00c1nico Del Autom\u00d3vil",
    "sg:phone":"+34 920 34 02 34",
    "sg:postcode":"05600",
    "sg:province":"\u00c1vila",
    "wof:name":"Talleres Calzada Motor S.l",
    "wof:placetype":"venue"
},
  "geometry": {"coordinates":[-5.5109491348,40.3599700928],"type":"Point"}
}