{
  "type": "Feature",
  "properties": {
    "addr:full":"Avda Pablo Picasso, 16 Venta De Ba\u00e7os Palencia 34200",
    "addr:housenumber":"16",
    "addr:postcode":"34200",
    "addr:street":"Avda Pablo Picasso",
    "iso:country":"ES",
    "sg:address":"Avda Pablo Picasso, 16",
    "sg:city":"Venta De Ba\u00e7os",
    "sg:orig_category":"Peluquer\u00cdas, Peluquer\u00cda Mixta",
    "sg:phone":"+34 979 77 28 12",
    "sg:postcode":"34200",
    "sg:province":"Palencia",
    "wof:name":"Yuguero Ortega Jesus Angel",
    "wof:placetype":"venue"
},
  "geometry": {"coordinates":[-4.5311746597,42.0124588013],"type":"Point"}
}