{
  "type": "Feature",
  "properties": {
    "iso:country":"ES",
    "sg:address":"Avda Covibar (de), S/n",
    "sg:city":"Partija-santa Monica",
    "sg:orig_category":"Centros De Educaci\u00d3n Especial",
    "sg:phone":"+34 916 66 60 78",
    "sg:postcode":"28529",
    "sg:province":"Madrid",
    "wof:name":"Colegio Publico El Parque",
    "wof:placetype":"venue"
},
  "geometry": {"coordinates":[-3.5102670193,40.314289093],"type":"Point"}
}