{
  "type": "Feature",
  "properties": {
    "iso:country":"ES",
    "sg:address":"Calle de Isabela, 1",
    "sg:city":"Sevilla",
    "sg:orig_category":"Ense\u00d1anza, Formaci\u00d3n Profesional: Aprendizaje",
    "sg:phone":"+34 954 21 68 18",
    "sg:postcode":"41013",
    "sg:province":"Sevilla",
    "wof:name":"Nuevas Profesiones S.a.",
    "wof:placetype":"venue"
},
  "geometry": {"coordinates":[-5.9808220863,37.3755226135],"type":"Point"}
}