{
  "type": "Feature",
  "properties": {
    "addr:full":"Carrer de Providencia, 18 Manresa Barcelona 08241",
    "addr:housenumber":"18",
    "addr:postcode":"08241",
    "addr:street":"Carrer De Providencia",
    "iso:country":"ES",
    "sg:address":"Carrer de Providencia, 18",
    "sg:city":"Manresa",
    "sg:orig_category":"Cajas De Ahorro",
    "sg:phone":"+34 938 74 80 30",
    "sg:postcode":"08241",
    "sg:province":"Barcelona",
    "sg:website":"www.caixapenedes.es",
    "wof:name":"Caixa D'estalvis Del Penedes",
    "wof:placetype":"venue"
},
  "geometry": {"coordinates":[1.836204052,41.7254753113],"type":"Point"}
}