{
  "type": "Feature",
  "properties": {
    "addr:full":"Calle de Teruel, 1 Getafe Madrid 28903",
    "addr:housenumber":"1",
    "addr:postcode":"28903",
    "addr:street":"Calle De Teruel",
    "iso:country":"ES",
    "sg:address":"Calle de Teruel, 1",
    "sg:city":"Getafe",
    "sg:orig_category":"Inform\u00c1tica (estudios, Servicios, Asesor\u00cda, Formaci\u00d3n)",
    "sg:phone":"+34 916 83 06 14",
    "sg:postcode":"28903",
    "sg:province":"Madrid",
    "wof:name":"Apinfor S.l.",
    "wof:placetype":"venue"
},
  "geometry": {"coordinates":[-3.7171196938,40.3104286194],"type":"Point"}
}