{
  "type": "Feature",
  "properties": {
    "addr:full":"Calle de Colmenares, 4 Palmas De Gran Canaria Las Palmas 35003",
    "addr:housenumber":"4",
    "addr:postcode":"35003",
    "addr:street":"Calle De Colmenares",
    "iso:country":"ES",
    "sg:address":"Calle de Colmenares, 4",
    "sg:city":"Palmas De Gran Canaria",
    "sg:orig_category":"Institutos De Belleza",
    "sg:phone":"+34 928 37 19 32",
    "sg:postcode":"35003",
    "sg:province":"Las Palmas",
    "wof:name":"Gil Curbelo Josefa",
    "wof:placetype":"venue"
},
  "geometry": {"coordinates":[-15.4172115326,28.1096248627],"type":"Point"}
}