{
  "type": "Feature",
  "properties": {
    "iso:country":"ES",
    "sg:address":"Carrer de Vint-i-un, 6",
    "sg:city":"Bonavista",
    "sg:orig_category":"Ropa De Hogar (al Por Menor)",
    "sg:phone":"+34 977 54 68 98",
    "sg:postcode":"43100",
    "sg:province":"Tarragona",
    "wof:name":"Mu\u00f1oz Juarez Adrian",
    "wof:placetype":"venue"
},
  "geometry": {"coordinates":[1.1947499514,41.1214942932],"type":"Point"}
}