{
  "type": "Feature",
  "properties": {
    "addr:full":"Carrer de Valencia, 245 Barcelona Barcelona 08007",
    "addr:housenumber":"245",
    "addr:postcode":"08007",
    "addr:street":"Carrer De Valencia",
    "iso:country":"ES",
    "sg:address":"Carrer de Valencia, 245",
    "sg:city":"Barcelona",
    "sg:orig_category":"Abogados",
    "sg:phone":"+34 934 87 25 41",
    "sg:postcode":"08007",
    "sg:province":"Barcelona",
    "wof:name":"Bufete Cadena Abogados Asociados S.l.",
    "wof:placetype":"venue"
},
  "geometry": {"coordinates":[2.1627459526,41.392414093],"type":"Point"}
}