{
  "type": "Feature",
  "properties": {
    "iso:country":"ES",
    "sg:address":"Carrer de Marques De Campo Sagrado, 21",
    "sg:city":"Barcelona",
    "sg:orig_category":"Mudanzas",
    "sg:phone":"+34 934 41 23 26",
    "sg:postcode":"08015",
    "sg:province":"Barcelona",
    "sg:website":"www.mudanzasrojals.com",
    "wof:name":"Mudanzas Casa Rojals S. A.",
    "wof:placetype":"venue"
},
  "geometry": {"coordinates":[2.1645460129,41.3764266968],"type":"Point"}
}