{
  "type": "Feature",
  "properties": {
    "iso:country":"ES",
    "sg:address":"Ctra Canillas, 108",
    "sg:city":"Madrid",
    "sg:orig_category":"Farmacias",
    "sg:phone":"+34 913 88 09 40",
    "sg:postcode":"28043",
    "sg:province":"Madrid",
    "wof:name":"Alamo Lopez Maria Isabel",
    "wof:placetype":"venue"
},
  "geometry": {"coordinates":[-3.6430675983,40.4645118713],"type":"Point"}
}