{
  "type": "Feature",
  "properties": {
    "addr:full":"Calle de Fontanillas, 7 Santa Cruz De Los Ca\u00e7amos Ciudad Real 13327",
    "addr:housenumber":"7",
    "addr:postcode":"13327",
    "addr:street":"Calle De Fontanillas;Cruz;Los",
    "iso:country":"ES",
    "sg:address":"Calle de Fontanillas, 7",
    "sg:city":"Santa Cruz De Los Ca\u00e7amos",
    "sg:orig_category":"Centro De Estudios",
    "sg:phone":"+34 926 38 70 02",
    "sg:postcode":"13327",
    "sg:province":"Ciudad Real",
    "wof:name":"Sat La Herren",
    "wof:placetype":"venue"
},
  "geometry": {"coordinates":[-2.8656439781,38.6380233765],"type":"Point"}
}