{
  "type": "Feature",
  "properties": {
    "iso:country":"ES",
    "sg:address":"Calle de Iglesia, S/n",
    "sg:city":"Esguevillas Esgueva",
    "sg:orig_category":"Delegados, Agentes De Tr\u00c1nsito, Auxiliares De Transporte Internacional",
    "sg:phone":"+34 983 68 61 76",
    "sg:postcode":"47176",
    "sg:province":"Valladolid",
    "wof:name":"Garcia Moro Jose",
    "wof:placetype":"venue"
},
  "geometry": {"coordinates":[-4.3799891472,41.7513694763],"type":"Point"}
}