{
  "type": "Feature",
  "properties": {
    "iso:country":"ES",
    "sg:address":"Carrer de Balmes, 2",
    "sg:city":"Esparreguera",
    "sg:orig_category":"Cristaler\u00cda: Suministros",
    "sg:phone":"+34 937 77 36 02",
    "sg:postcode":"08292",
    "sg:province":"Barcelona",
    "wof:name":"Moya Pedrol Guillermo",
    "wof:placetype":"venue"
},
  "geometry": {"coordinates":[1.8672549725,41.5403862],"type":"Point"}
}