{
  "type": "Feature",
  "properties": {
    "addr:full":"Avda Generalisimo, 47 Meira Lugo 27240",
    "addr:housenumber":"47",
    "addr:postcode":"27240",
    "addr:street":"Avda Generalisimo",
    "iso:country":"ES",
    "sg:address":"Avda Generalisimo, 47",
    "sg:city":"Meira",
    "sg:orig_category":"Transporte En General",
    "sg:phone":"+34 982 33 06 33",
    "sg:postcode":"27240",
    "sg:province":"Lugo",
    "wof:name":"Cemar Alimemtacion S.l.",
    "wof:placetype":"venue"
},
  "geometry": {"coordinates":[-7.2952880859,43.213180542],"type":"Point"}
}