{
  "type": "Feature",
  "properties": {
    "addr:full":"Avda Galicia, 19 Cambados Pontevedra 36630",
    "addr:housenumber":"19",
    "addr:postcode":"36630",
    "addr:street":"Avda Galicia",
    "iso:country":"ES",
    "sg:address":"Avda Galicia, 19",
    "sg:city":"Cambados",
    "sg:orig_category":"Bancos",
    "sg:phone":"+34 986 54 29 60",
    "sg:postcode":"36630",
    "sg:province":"Pontevedra",
    "wof:name":"Banco Bilbao Vizcaya Argentaria S.a.",
    "wof:placetype":"venue"
},
  "geometry": {"coordinates":[-8.8156642914,42.5111503601],"type":"Point"}
}