{
  "type": "Feature",
  "properties": {
    "iso:country":"ES",
    "sg:address":"Calle de Juan Xxiii, 6",
    "sg:city":"Gra\u00f1en",
    "sg:orig_category":"Centros De Educaci\u00d3n Especial",
    "sg:phone":"+34 974 39 02 52",
    "sg:postcode":"22260",
    "sg:province":"Huesca",
    "wof:name":"Ayuntamiento De Gra\u00d1en",
    "wof:placetype":"venue"
},
  "geometry": {"coordinates":[-0.3672800064,41.9447669983],"type":"Point"}
}