{
  "type": "Feature",
  "properties": {
    "addr:full":"Plaz Barranco De La Ballena, S/n Palmas De Gran Canaria Las Palmas 35012",
    "addr:housenumber":"s",
    "addr:postcode":"35012",
    "addr:street":"/ N",
    "iso:country":"ES",
    "sg:address":"Plaz Barranco De La Ballena, S/n",
    "sg:city":"Palmas De Gran Canaria",
    "sg:orig_category":"Transporte En General",
    "sg:phone":"+34 928 42 16 55",
    "sg:postcode":"35012",
    "sg:province":"Las Palmas",
    "sg:website":"www.philips.es",
    "wof:name":"Philips Iberica S.a.",
    "wof:placetype":"venue"
},
  "geometry": {"coordinates":[-15.4471635818,28.1134300232],"type":"Point"}
}