{
  "type": "Feature",
  "properties": {
    "iso:country":"ES",
    "sg:address":"Las Farolas, S/n",
    "sg:city":"Mijas Costa",
    "sg:orig_category":"Artes Gr\u00c1ficas, Artes Pl\u00c1sticas: Material Y Suministros (al Por Menor)",
    "sg:phone":"+34 952 58 76 40",
    "sg:postcode":"29649",
    "sg:province":"M\u00e1laga",
    "wof:name":"Plank  Peter",
    "wof:placetype":"venue"
},
  "geometry": {"coordinates":[-4.7157039642,36.4931945801],"type":"Point"}
}