{
  "type": "Feature",
  "properties": {
    "iso:country":"ES",
    "sg:address":"Comedias, 4",
    "sg:city":"Iru\u00f1a",
    "sg:orig_category":"Relojer\u00cda (al Por Menor, Reparaci\u00d3n)",
    "sg:phone":"+34 948 22 71 81",
    "sg:postcode":"31001",
    "sg:province":"Navarra",
    "wof:name":"Zarag\u00fceta Sanchez Juan",
    "wof:placetype":"venue"
},
  "geometry": {"coordinates":[-1.6438548565,42.8165588379],"type":"Point"}
}