{
  "type": "Feature",
  "properties": {
    "addr:full":"Plaz Mayor, 1 Pomar Cinca Huesca 22413",
    "addr:housenumber":"1",
    "addr:postcode":"22413",
    "addr:street":"Plaz Mayor",
    "iso:country":"ES",
    "sg:address":"Plaz Mayor, 1",
    "sg:city":"Pomar Cinca",
    "sg:orig_category":"Iglesia Cat\u00d3lica",
    "sg:phone":"+34 974 41 30 65",
    "sg:postcode":"22413",
    "sg:province":"Huesca",
    "wof:name":"Obispado De Barbastro",
    "wof:placetype":"venue"
},
  "geometry": {"coordinates":[0.1284050047,41.8516349792],"type":"Point"}
}