{
  "type": "Feature",
  "properties": {
    "iso:country":"ES",
    "sg:address":"Ctra. De Caniles, Km. 0110,8",
    "sg:city":"Caniles",
    "sg:orig_category":"Empresas De Carpinter\u00cda Met\u00c1lica",
    "sg:phone":"+34 958 71 05 84",
    "sg:postcode":"18810",
    "sg:province":"Granada",
    "wof:name":"Bleisa Fernandez Jose Francisco",
    "wof:placetype":"venue"
},
  "geometry": {"coordinates":[-2.7215490341,37.4435958862],"type":"Point"}
}