{
  "type": "Feature",
  "properties": {
    "addr:full":"Carr Costa Verda, 17 Calella Girona 17210",
    "addr:housenumber":"17",
    "addr:postcode":"17210",
    "addr:street":"Carr Costa Verda",
    "iso:country":"ES",
    "sg:address":"Carr Costa Verda, 17",
    "sg:city":"Calella",
    "sg:orig_category":"Televisi\u00d3n, V\u00cddeo: Aparatos Y Accesorios (venta)",
    "sg:phone":"+34 972 61 70 22",
    "sg:postcode":"17210",
    "sg:province":"Girona",
    "wof:name":"Vectacion S.l.",
    "wof:placetype":"venue"
},
  "geometry": {"coordinates":[3.1871829033,41.8926353455],"type":"Point"}
}