{
  "type": "Feature",
  "properties": {
    "iso:country":"ES",
    "sg:address":"Luga Cano Cartamon, S/n",
    "sg:city":"Estacion",
    "sg:orig_category":"Centros De Educaci\u00d3n Especial",
    "sg:phone":"+34 952 42 05 83",
    "sg:postcode":"29580",
    "sg:province":"M\u00e1laga",
    "wof:name":"Junta De Andalucia - C.e.i.p. Cano-cartamon",
    "wof:placetype":"venue"
},
  "geometry": {"coordinates":[-4.6088900566,36.7374916077],"type":"Point"}
}