{
  "type": "Feature",
  "properties": {
    "addr:full":"Av. Gral. Franco, 17 Mezquita Ourense 32549",
    "addr:housenumber":"17",
    "addr:postcode":"32549",
    "addr:street":"Av. Gral. Franco",
    "iso:country":"ES",
    "sg:address":"Av. Gral. Franco, 17",
    "sg:city":"Mezquita",
    "sg:orig_category":"Farmacias",
    "sg:phone":"+34 988 42 55 25",
    "sg:postcode":"32549",
    "sg:province":"Ourense",
    "wof:name":"Gonzalez Gonzalez Cleto",
    "wof:placetype":"venue"
},
  "geometry": {"coordinates":[-7.0450391769,42.010925293],"type":"Point"}
}