{
  "type": "Feature",
  "properties": {
    "addr:full":"Pol Industrial Heras, 310 Heras Cantabria 39792",
    "addr:housenumber":"310",
    "addr:postcode":"39792",
    "addr:street":"Industrial Heras",
    "iso:country":"ES",
    "sg:address":"Pol Industrial Heras, 310",
    "sg:city":"Heras",
    "sg:orig_category":"Vinos (agentes)",
    "sg:phone":"+34 942 54 42 45",
    "sg:postcode":"39792",
    "sg:province":"Cantabria",
    "wof:name":"Hijos De Alfonso Obregon S.l",
    "wof:placetype":"venue"
},
  "geometry": {"coordinates":[-3.7661499977,43.4118690491],"type":"Point"}
}