{
  "type": "Feature",
  "properties": {
    "iso:country":"ES",
    "sg:address":"Calle de Antonio Blazquez, 20",
    "sg:city":"Ciudad Real",
    "sg:orig_category":"C\u00c1maras De Comercio E Industria, Oficios, Agricultura",
    "sg:phone":"+34 926 21 20 86",
    "sg:postcode":"13002",
    "sg:province":"Ciudad Real",
    "wof:name":"Camara Agraria Provincial",
    "wof:placetype":"venue"
},
  "geometry": {"coordinates":[-3.934220314,38.9845695496],"type":"Point"}
}