{
  "type": "Feature",
  "properties": {
    "iso:country":"ES",
    "sg:address":"Plaz Vasco Nu\u00d1ez De Balboa, 14",
    "sg:city":"Jerez De Los Caballeros",
    "sg:orig_category":"Estancos",
    "sg:phone":"+34 924 73 01 30",
    "sg:postcode":"06380",
    "sg:province":"Badajoz",
    "wof:name":"Rodriguez Cordobes Ildefonso",
    "wof:placetype":"venue"
},
  "geometry": {"coordinates":[-6.7698688507,38.3207168579],"type":"Point"}
}