{
  "type": "Feature",
  "properties": {
    "iso:country":"ES",
    "sg:address":"Carrer de Vinaros, 30",
    "sg:city":"Hospitalet Llobregat",
    "sg:orig_category":"Molduras, Junquillos, Listones Y Molduras Perforadas",
    "sg:phone":"+34 934 37 58 71",
    "sg:postcode":"08906",
    "sg:province":"Barcelona",
    "wof:name":"Tirado Aviles Josefa",
    "wof:placetype":"venue"
},
  "geometry": {"coordinates":[2.1022379398,41.3727264404],"type":"Point"}
}