{
  "type": "Feature",
  "properties": {
    "iso:country":"ES",
    "sg:address":"Urb. J. Del Eden, S/n",
    "sg:city":"Ogijares",
    "sg:orig_category":"Venta, Localizaci\u00d3n, Reparaci\u00d3n De Material E Instrumental M\u00c9dico",
    "sg:phone":"+34 958 59 75 36",
    "sg:postcode":"18151",
    "sg:province":"Granada",
    "wof:name":"Biomet Spain Orthopaedics S.l.",
    "wof:placetype":"venue"
},
  "geometry": {"coordinates":[-3.6051189899,37.1205368042],"type":"Point"}
}