{
  "type": "Feature",
  "properties": {
    "addr:full":"Condado De Trevi\u00f1o, 53 Villalonquejar Burgos 09001",
    "addr:housenumber":"53",
    "addr:postcode":"09001",
    "addr:street":"Trevin\u0303O",
    "iso:country":"ES",
    "sg:address":"Condado De Trevi\u00f1o, 53",
    "sg:city":"Villalonquejar",
    "sg:orig_category":"Maquinaria Para Industrias Diversas",
    "sg:phone":"+34 947 29 84 35",
    "sg:postcode":"09001",
    "sg:province":"Burgos",
    "wof:name":"Nc Hyperbaric S.a.",
    "wof:placetype":"venue"
},
  "geometry": {"coordinates":[-3.7250521183,42.3698387146],"type":"Point"}
}