{
  "type": "Feature",
  "properties": {
    "iso:country":"ES",
    "sg:address":"Carrer de Riu Segre, S/n",
    "sg:city":"Campclar",
    "sg:orig_category":"Promotores Constructores",
    "sg:phone":"+34 977 55 05 11",
    "sg:postcode":"43006",
    "sg:province":"Tarragona",
    "wof:name":"Vallve Marti Domingo",
    "wof:placetype":"venue"
},
  "geometry": {"coordinates":[1.2209249735,41.1154441833],"type":"Point"}
}