{
  "type": "Feature",
  "properties": {
    "addr:full":"Tv. A. Gorricho, S/n Iru\u00f1a Navarra 31015",
    "addr:housenumber":"s",
    "addr:postcode":"31015",
    "addr:street":"/ N Irun\u0303A Navarra",
    "iso:country":"ES",
    "sg:address":"Tv. A. Gorricho, S/n",
    "sg:city":"Iru\u00f1a",
    "sg:orig_category":"Molduras, Junquillos, Listones Y Molduras Perforadas",
    "sg:phone":"+34 948 13 58 23",
    "sg:postcode":"31015",
    "sg:province":"Navarra",
    "wof:name":"Gonzalez Herce Jose Luis",
    "wof:placetype":"venue"
},
  "geometry": {"coordinates":[-1.6437540054,42.81275177],"type":"Point"}
}