{
  "type": "Feature",
  "properties": {
    "addr:full":"Calle de Blas Infante, 4 Roda Andalucia Sevilla 41590",
    "addr:housenumber":"4",
    "addr:postcode":"41590",
    "addr:street":"Calle De Blas Infante",
    "iso:country":"ES",
    "sg:address":"Calle de Blas Infante, 4",
    "sg:city":"Roda Andalucia",
    "sg:orig_category":"Droguer\u00cdas (al Por Menor)",
    "sg:phone":"+34 954 01 53 19",
    "sg:postcode":"41590",
    "sg:province":"Sevilla",
    "wof:name":"Drosolu S.l.",
    "wof:placetype":"venue"
},
  "geometry": {"coordinates":[-4.7795147896,37.2011108398],"type":"Point"}
}