{
  "type": "Feature",
  "properties": {
    "addr:full":"Calle de General Mas De Gaminde, 47 Palmas De Gran Canaria Las Palmas 35006",
    "addr:housenumber":"47",
    "addr:postcode":"35006",
    "addr:street":"Calle De General Mas De Gaminde",
    "iso:country":"ES",
    "sg:address":"Calle de General Mas De Gaminde, 47",
    "sg:city":"Palmas De Gran Canaria",
    "sg:orig_category":"Centros Comerciales Y Grandes Tiendas",
    "sg:phone":"+34 928 24 46 26",
    "sg:postcode":"35006",
    "sg:province":"Las Palmas",
    "wof:name":"Gestiones Noche Y Dia S.l.",
    "wof:placetype":"venue"
},
  "geometry": {"coordinates":[-15.4339981079,28.1337566376],"type":"Point"}
}