{
  "type": "Feature",
  "properties": {
    "addr:full":"Calle de Joaquin Costa, 2 Ballobar Huesca 22234",
    "addr:housenumber":"2",
    "addr:postcode":"22234",
    "addr:street":"Calle De Joaquin Costa",
    "iso:country":"ES",
    "sg:address":"Calle de Joaquin Costa, 2",
    "sg:city":"Ballobar",
    "sg:orig_category":"Cajas Para Embalar",
    "sg:phone":"+34 974 46 10 52",
    "sg:postcode":"22234",
    "sg:province":"Huesca",
    "wof:name":"Caja Rural Aragonesa Y De Los Pirineos",
    "wof:placetype":"venue"
},
  "geometry": {"coordinates":[0.1924400032,41.621471405],"type":"Point"}
}