{
  "type": "Feature",
  "properties": {
    "iso:country":"ES",
    "sg:address":"Calle de Ca\u00d1adilla, 8",
    "sg:city":"Torredonjimeno",
    "sg:orig_category":"Fabricaci\u00d3n De Cortinas Y Visillos",
    "sg:phone":"+34 953 34 41 30",
    "sg:postcode":"23650",
    "sg:province":"Ja\u00e9n",
    "wof:name":"Torres Lopez Dolores",
    "wof:placetype":"venue"
},
  "geometry": {"coordinates":[-3.9562339783,37.7647323608],"type":"Point"}
}