{
  "type": "Feature",
  "properties": {
    "addr:full":"Errota Poligonoa, 2 Anoeta Guip\u00f9zcoa 20270",
    "addr:housenumber":"2",
    "addr:postcode":"20270",
    "addr:street":"Errota Poligonoa;Guipu\u0300Zcoa",
    "iso:country":"ES",
    "sg:address":"Errota Poligonoa, 2",
    "sg:city":"Anoeta",
    "sg:orig_category":"Promotores Constructores",
    "sg:phone":"+34 943 65 03 34",
    "sg:postcode":"20270",
    "sg:province":"Guip\u00f9zcoa",
    "wof:name":"Promociones Euskalduna 2005 S.l.",
    "wof:placetype":"venue"
},
  "geometry": {"coordinates":[-2.069963932,43.1619186401],"type":"Point"}
}