{
  "type": "Feature",
  "properties": {
    "addr:full":"Calle de Turia, 18 Valencia Valencia 46008",
    "addr:housenumber":"18",
    "addr:postcode":"46008",
    "addr:street":"Calle De Turia",
    "iso:country":"ES",
    "sg:address":"Calle de Turia, 18",
    "sg:city":"Valencia",
    "sg:orig_category":"Marroquiner\u00cda (confecci\u00d3n)",
    "sg:phone":"+34 963 91 45 59",
    "sg:postcode":"46008",
    "sg:province":"Valencia",
    "wof:name":"Livori Mantovani Pierino",
    "wof:placetype":"venue"
},
  "geometry": {"coordinates":[-0.385096997,39.4749679565],"type":"Point"}
}