{
  "type": "Feature",
  "properties": {
    "addr:full":"Calle de Praderas, 1 Majadahonda Madrid 28220",
    "addr:housenumber":"1",
    "addr:postcode":"28220",
    "addr:street":"Calle De Praderas",
    "iso:country":"ES",
    "sg:address":"Calle de Praderas, 1",
    "sg:city":"Majadahonda",
    "sg:orig_category":"Guarder\u00cdas",
    "sg:phone":"+34 916 38 00 69",
    "sg:postcode":"28220",
    "sg:province":"Madrid",
    "wof:name":"Kinder Godwin",
    "wof:placetype":"venue"
},
  "geometry": {"coordinates":[-3.8567149639,40.474609375],"type":"Point"}
}