{
  "type": "Feature",
  "properties": {
    "addr:full":"Avda Pontejos, 3 Santander Cantabria 39005",
    "addr:housenumber":"3",
    "addr:postcode":"39005",
    "addr:street":"Avda Pontejos",
    "iso:country":"ES",
    "sg:address":"Avda Pontejos, 3",
    "sg:city":"Santander",
    "sg:orig_category":"T\u00c9cnicos Veterinarios",
    "sg:phone":"+34 942 27 69 53",
    "sg:postcode":"39005",
    "sg:province":"Cantabria",
    "wof:name":"Escalada Miyares Mercedes",
    "wof:placetype":"venue"
},
  "geometry": {"coordinates":[-3.7882020473,43.4727096558],"type":"Point"}
}