{
  "type": "Feature",
  "properties": {
    "addr:full":"Plaz San Miguel Arcangel, 10 Abaran Murcia 30550",
    "addr:housenumber":"10",
    "addr:postcode":"30550",
    "addr:street":"Plaz",
    "iso:country":"ES",
    "sg:address":"Plaz San Miguel Arcangel, 10",
    "sg:city":"Abaran",
    "sg:orig_category":"Alquiler De V\u00cddeo",
    "sg:phone":"+34 968 45 10 30",
    "sg:postcode":"30550",
    "sg:province":"Murcia",
    "wof:name":"Gomez Carrasco Nefertari",
    "wof:placetype":"venue"
},
  "geometry": {"coordinates":[-1.3944859505,38.2074737549],"type":"Point"}
}