{
  "type": "Feature",
  "properties": {
    "addr:full":"Calle de Viteri, 16 Errenteria Guip\u00f9zcoa 20100",
    "addr:housenumber":"16",
    "addr:postcode":"20100",
    "addr:street":"Calle De Viteri;Guipu\u0300Zcoa",
    "iso:country":"ES",
    "sg:address":"Calle de Viteri, 16",
    "sg:city":"Errenteria",
    "sg:orig_category":"Ropa Para Ni\u00d1os (al Por Menor)",
    "sg:phone":"+34 943 51 21 98",
    "sg:postcode":"20100",
    "sg:province":"Guip\u00f9zcoa",
    "wof:name":"Olatz Erauskin S.l.",
    "wof:placetype":"venue"
},
  "geometry": {"coordinates":[-1.9005420208,43.3133125305],"type":"Point"}
}