{
  "type": "Feature",
  "properties": {
    "addr:full":"Tarambana, 178 Tarambana Almer\u00eda 04713",
    "addr:housenumber":"178",
    "addr:postcode":"04713",
    "addr:street":"Tarambana;Almeri\u0301A",
    "iso:country":"ES",
    "sg:address":"Tarambana, 178",
    "sg:city":"Tarambana",
    "sg:orig_category":"Distribuci\u00d3n De Petr\u00d3leo Y Derivados",
    "sg:phone":"+34 950 40 67 76",
    "sg:postcode":"04713",
    "sg:province":"Almer\u00eda",
    "wof:name":"Maldonado Y Mendez S.l.",
    "wof:placetype":"venue"
},
  "geometry": {"coordinates":[-2.9129910469,36.7498703003],"type":"Point"}
}