{
  "type": "Feature",
  "properties": {
    "iso:country":"ES",
    "sg:address":"Carrer de Loreto, 36",
    "sg:city":"Barcelona",
    "sg:orig_category":"Pod\u00d3logos: Pedicuros",
    "sg:phone":"+34 933 21 70 28",
    "sg:postcode":"08029",
    "sg:province":"Barcelona",
    "wof:name":"Gili Farres Inmaculada",
    "wof:placetype":"venue"
},
  "geometry": {"coordinates":[2.1423449516,41.3906211853],"type":"Point"}
}