{
  "type": "Feature",
  "properties": {
    "addr:full":"Calle de San Teodomiro, 10 Carmona Sevilla 41410",
    "addr:housenumber":"10",
    "addr:postcode":"41410",
    "addr:street":"Calle De San Teodomiro",
    "iso:country":"ES",
    "sg:address":"Calle de San Teodomiro, 10",
    "sg:city":"Carmona",
    "sg:orig_category":"Reposter\u00cdas",
    "sg:phone":"+34 954 14 16 88",
    "sg:postcode":"41410",
    "sg:province":"Sevilla",
    "wof:name":"Horno San Teodomiro S.c.",
    "wof:placetype":"venue"
},
  "geometry": {"coordinates":[-5.6399149895,37.4747962952],"type":"Point"}
}