{
  "type": "Feature",
  "properties": {
    "iso:country":"ES",
    "sg:address":"Avda Jesus Garcia Naveira, 6",
    "sg:city":"Betanzos",
    "sg:orig_category":"Plomeros",
    "sg:phone":"+34 981 77 31 47",
    "sg:postcode":"15300",
    "sg:province":"A Coru\u00f1a",
    "wof:name":"Velo Cabanas Antonio",
    "wof:placetype":"venue"
},
  "geometry": {"coordinates":[-8.2119092941,43.279914856],"type":"Point"}
}