{
  "type": "Feature",
  "properties": {
    "iso:country":"ES",
    "sg:address":"Av Osona, 18",
    "sg:city":"Torello",
    "sg:orig_category":"Productos Alimentarios",
    "sg:phone":"+34 938 59 07 31",
    "sg:postcode":"08570",
    "sg:province":"Barcelona",
    "wof:name":"Agraria De Torello S.c.c.l.",
    "wof:placetype":"venue"
},
  "geometry": {"coordinates":[2.2713797092,42.0414505005],"type":"Point"}
}