{
  "type": "Feature",
  "properties": {
    "addr:full":"Ctra Madrid-alican., S/n Quintanar Orden Toledo 45800",
    "addr:housenumber":"s / n",
    "addr:postcode":"45800",
    "addr:street":"Ctra Madrid-Alican.",
    "iso:country":"ES",
    "sg:address":"Ctra Madrid-alican., S/n",
    "sg:city":"Quintanar Orden",
    "sg:orig_category":"Cooperativas Agr\u00cdcolas",
    "sg:phone":"+34 925 18 02 37",
    "sg:postcode":"45800",
    "sg:province":"Toledo",
    "wof:name":"Sociedad Cooperativa Agricola Nuestra Se\u00f1ora De La Piedad",
    "wof:placetype":"venue"
},
  "geometry": {"coordinates":[-3.0198190212,39.5781135559],"type":"Point"}
}