{
  "type": "Feature",
  "properties": {
    "iso:country":"ES",
    "sg:address":"Calle de Pamplona-iru\u00d1ea, 3",
    "sg:city":"Vitoria-gasteiz",
    "sg:classifiers":[
        {
            "category":"Autos & Motor Vehicles",
            "subcategory":"Automobile Sales",
            "type":"Retail Goods"
        }
    ],
    "sg:phone":"+34 945 17 74 41",
    "sg:postcode":"01010",
    "sg:province":"\u00c1lava",
    "wof:name":"Auto Escuela Salazar S.l.",
    "wof:placetype":"venue"
},
  "geometry": {"coordinates":[-2.696644783,42.8607940674],"type":"Point"}
}