{
  "type": "Feature",
  "properties": {
    "iso:country":"ES",
    "sg:address":"Calle de Molino De Viento, 1",
    "sg:city":"Fuente Maestre",
    "sg:orig_category":"Sociedades, Compa\u00d1\u00cdas Aseguradoras",
    "sg:phone":"+34 924 53 08 72",
    "sg:postcode":"06360",
    "sg:province":"Badajoz",
    "wof:name":"Leal S.l. Asesoria Laboral Fiscal Y Contable",
    "wof:placetype":"venue"
},
  "geometry": {"coordinates":[-6.4434289932,38.5266189575],"type":"Point"}
}