{
  "type": "Feature",
  "properties": {
    "addr:full":"Carr Dolors, 10 Ma\u00e7anet Selva Girona 17412",
    "addr:housenumber":"10",
    "addr:postcode":"17412",
    "addr:street":"Carr Dolors",
    "iso:country":"ES",
    "sg:address":"Carr Dolors, 10",
    "sg:city":"Ma\u00e7anet Selva",
    "sg:orig_category":"Empresas De Carpinter\u00cda",
    "sg:phone":"+34 972 16 50 40",
    "sg:postcode":"17412",
    "sg:province":"Girona",
    "wof:name":"Nova Fusta S.c.",
    "wof:placetype":"venue"
},
  "geometry": {"coordinates":[2.7342700958,41.7778396606],"type":"Point"}
}