{
  "type": "Feature",
  "properties": {
    "iso:country":"ES",
    "sg:address":"Rua Ramon Puga, 75",
    "sg:city":"Ourense",
    "sg:orig_category":"Suministros Y Colocaci\u00d3n De Canalones Para Aguas Pluviales",
    "sg:phone":"+34 988 39 11 70",
    "sg:postcode":"32005",
    "sg:province":"Ourense",
    "wof:name":"Salgado Carrasco Domingo",
    "wof:placetype":"venue"
},
  "geometry": {"coordinates":[-7.8561191559,42.3268241882],"type":"Point"}
}