{
  "type": "Feature",
  "properties": {
    "addr:full":"Luga Poligono Industrial Del Bierzo, 11 Toral De Los Vados Le\u00f3n 24560",
    "addr:housenumber":"11",
    "addr:postcode":"24560",
    "addr:street":"Poligono Industrial Del Bierzo",
    "iso:country":"ES",
    "sg:address":"Luga Poligono Industrial Del Bierzo, 11",
    "sg:city":"Toral De Los Vados",
    "sg:orig_category":"Muebles, Minoristas",
    "sg:phone":"+34 987 54 51 56",
    "sg:postcode":"24560",
    "sg:province":"Le\u00f3n",
    "wof:name":"Castro Tovar S.a.l.",
    "wof:placetype":"venue"
},
  "geometry": {"coordinates":[-6.7822341919,42.5436286926],"type":"Point"}
}