{
  "type": "Feature",
  "properties": {
    "addr:full":"Calle de Ingeniero Martin Gil, 8 Cantalejo Segovia 40320",
    "addr:housenumber":"8",
    "addr:postcode":"40320",
    "addr:street":"Calle De Ingeniero Martin Gil",
    "iso:country":"ES",
    "sg:address":"Calle de Ingeniero Martin Gil, 8",
    "sg:city":"Cantalejo",
    "sg:orig_category":"Farmacias",
    "sg:phone":"+34 921 52 00 05",
    "sg:postcode":"40320",
    "sg:province":"Segovia",
    "wof:name":"Salcedo Madero Maria Rosa",
    "wof:placetype":"venue"
},
  "geometry": {"coordinates":[-3.9279720783,41.2588996887],"type":"Point"}
}