{
  "type": "Feature",
  "properties": {
    "addr:full":"Calle de Doctor Sixto Perera Gonzalez, 10 Orotava Santa Cruz De Tenerife 38300",
    "addr:housenumber":"10",
    "addr:postcode":"38300",
    "addr:street":"Calle De Doctor Sixto Perera Gonzalez",
    "iso:country":"ES",
    "sg:address":"Calle de Doctor Sixto Perera Gonzalez, 10",
    "sg:city":"Orotava",
    "sg:orig_category":"Herramientas Y Suministros Para Plomeros",
    "sg:phone":"+34 922 32 65 45",
    "sg:postcode":"38300",
    "sg:province":"Santa Cruz De Tenerife",
    "wof:name":"Tubos Y Hierros Industriales S.a.",
    "wof:placetype":"venue"
},
  "geometry": {"coordinates":[-16.5269069672,28.3928184509],"type":"Point"}
}