{
  "type": "Feature",
  "properties": {
    "iso:country":"ES",
    "sg:address":"Carr Sant Antoni, 63",
    "sg:city":"Figueres",
    "sg:orig_category":"Contenedores (mercanc\u00cdas)",
    "sg:phone":"+34 972 50 63 24",
    "sg:postcode":"17600",
    "sg:province":"Girona",
    "wof:name":"Transampurdan S.l.",
    "wof:placetype":"venue"
},
  "geometry": {"coordinates":[2.9657649994,42.2629203796],"type":"Point"}
}