{
  "type": "Feature",
  "properties": {
    "iso:country":"ES",
    "sg:address":"Ctra. Ubrique-benaocaz, S/n",
    "sg:city":"Ubrique",
    "sg:orig_category":"Reciclaje Y Tratamiento De Desechos Varios",
    "sg:phone":"+34 956 23 42 44",
    "sg:postcode":"11600",
    "sg:province":"C\u00e1diz",
    "wof:name":"Bioreciclaje De Cadiz S.a.",
    "wof:placetype":"venue"
},
  "geometry": {"coordinates":[-5.4494590759,36.6789398193],"type":"Point"}
}