{
  "type": "Feature",
  "properties": {
    "addr:full":"Calle de Milan, 23 Arenal Islas Baleares 07600",
    "addr:housenumber":"23",
    "addr:postcode":"07600",
    "addr:street":"Calle De Milan",
    "iso:country":"ES",
    "sg:address":"Calle de Milan, 23",
    "sg:city":"Arenal",
    "sg:orig_category":"Ropa Para Ni\u00d1os (al Por Menor)",
    "sg:phone":"+34 971 74 39 79",
    "sg:postcode":"07600",
    "sg:province":"Islas Baleares",
    "wof:name":"Azabache Carbajal Carla",
    "wof:placetype":"venue"
},
  "geometry": {"coordinates":[2.7533962727,39.5042800903],"type":"Point"}
}