{
  "type": "Feature",
  "properties": {
    "addr:full":"Calle de Teatro, 18 Alacant Alicante 03001",
    "addr:housenumber":"18",
    "addr:postcode":"03001",
    "addr:street":"Calle De Teatro",
    "iso:country":"ES",
    "sg:address":"Calle de Teatro, 18",
    "sg:city":"Alacant",
    "sg:orig_category":"Asesor\u00cda Fiscal Y Jur\u00cddica",
    "sg:phone":"+34 965 21 34 65",
    "sg:postcode":"03001",
    "sg:province":"Alicante",
    "wof:name":"Lorente Lorente Ricardo",
    "wof:placetype":"venue"
},
  "geometry": {"coordinates":[-0.4866069853,38.3457679749],"type":"Point"}
}