{
  "type": "Feature",
  "properties": {
    "addr:full":"Calle de Martin De Luque, 2 Antequera M\u00e1laga 29200",
    "addr:housenumber":"2",
    "addr:postcode":"29200",
    "addr:street":"Calle De Martin De Luque",
    "iso:country":"ES",
    "sg:address":"Calle de Martin De Luque, 2",
    "sg:city":"Antequera",
    "sg:orig_category":"Agencias Y Agentes Comerciales, Representantes",
    "sg:phone":"+34 952 84 12 81",
    "sg:postcode":"29200",
    "sg:province":"M\u00e1laga",
    "wof:name":"Perez Campos Antonio",
    "wof:placetype":"venue"
},
  "geometry": {"coordinates":[-4.5575451851,37.0198707581],"type":"Point"}
}