{
  "type": "Feature",
  "properties": {
    "addr:full":"Ctra Malaga, 37 Alhaurin El Grande M\u00e1laga 29120",
    "addr:housenumber":"37",
    "addr:postcode":"29120",
    "addr:street":"Ctra Malaga",
    "iso:country":"ES",
    "sg:address":"Ctra Malaga, 37",
    "sg:city":"Alhaurin El Grande",
    "sg:orig_category":"Asesor\u00cda Fiscal Y Jur\u00cddica",
    "sg:phone":"+34 952 59 42 79",
    "sg:postcode":"29120",
    "sg:province":"M\u00e1laga",
    "wof:name":"Manzanares Abogados S.l.",
    "wof:placetype":"venue"
},
  "geometry": {"coordinates":[-4.6911292076,36.6420783997],"type":"Point"}
}