{
  "type": "Feature",
  "properties": {
    "iso:country":"ES",
    "sg:address":"Ctra La Roda-pedrera, 1",
    "sg:city":"Roda Andalucia",
    "sg:orig_category":"Aceites Y Grasas Alimentarias (fabricaci\u00d3n, Al Por Mayor)",
    "sg:phone":"+34 954 01 61 13",
    "sg:postcode":"41590",
    "sg:province":"Sevilla",
    "wof:name":"Inmaculada Concepcion De La Roda S.c.a.",
    "wof:placetype":"venue"
},
  "geometry": {"coordinates":[-4.7789430618,37.2011032104],"type":"Point"}
}