{
  "type": "Feature",
  "properties": {
    "addr:full":"Calle de Alvarez Quintero, 7 Sevilla Sevilla 41004",
    "addr:housenumber":"7",
    "addr:postcode":"41004",
    "addr:street":"Calle De Alvarez Quintero",
    "iso:country":"ES",
    "sg:address":"Calle de Alvarez Quintero, 7",
    "sg:city":"Sevilla",
    "sg:orig_category":"Dibujantes (diversos)",
    "sg:phone":"+34 954 22 64 61",
    "sg:postcode":"41004",
    "sg:province":"Sevilla",
    "wof:name":"Aq 7 Modulo 2 S.cv",
    "wof:placetype":"venue"
},
  "geometry": {"coordinates":[-5.9933018684,37.3892478943],"type":"Point"}
}