{
  "type": "Feature",
  "properties": {
    "addr:full":"Avda Juan Xxiii, 1 Huesca Huesca 22003",
    "addr:housenumber":"1",
    "addr:postcode":"22003",
    "addr:street":"Avda Juan Xxiii",
    "iso:country":"ES",
    "sg:address":"Avda Juan Xxiii, 1",
    "sg:city":"Huesca",
    "sg:orig_category":"Farmacias",
    "sg:phone":"+34 974 21 57 15",
    "sg:postcode":"22003",
    "sg:province":"Huesca",
    "wof:name":"Liarte Pastor Pedro Eloy",
    "wof:placetype":"venue"
},
  "geometry": {"coordinates":[-0.4083139896,42.1365661621],"type":"Point"}
}