{
  "type": "Feature",
  "properties": {
    "addr:full":"Carr Lauri Volpi, 26 Burjassot Valencia 46100",
    "addr:housenumber":"26",
    "addr:postcode":"46100",
    "addr:street":"Carr Lauri Volpi",
    "iso:country":"ES",
    "sg:address":"Carr Lauri Volpi, 26",
    "sg:city":"Burjassot",
    "sg:orig_category":"Comit\u00c9s De Organizaci\u00d3n De Exposiciones, Ferias, Salones",
    "sg:phone":"+34 963 63 39 71",
    "sg:postcode":"46100",
    "sg:province":"Valencia",
    "wof:name":"Decma",
    "wof:placetype":"venue"
},
  "geometry": {"coordinates":[-0.4126240015,39.5172615051],"type":"Point"}
}