{
  "type": "Feature",
  "properties": {
    "addr:full":"Benigno Quiroga, 10 Pobra De San Xiao Lugo 27360",
    "addr:housenumber":"10",
    "addr:postcode":"27360",
    "addr:street":"Benigno Quiroga",
    "iso:country":"ES",
    "sg:address":"Benigno Quiroga, 10",
    "sg:city":"Pobra De San Xiao",
    "sg:orig_category":"Negocio De Materiales De Construcci\u00d3n",
    "sg:phone":"+34 982 54 30 53",
    "sg:postcode":"27360",
    "sg:province":"Lugo",
    "wof:name":"Comercial Franco S. A.",
    "wof:placetype":"venue"
},
  "geometry": {"coordinates":[-7.4470348358,42.8677558899],"type":"Point"}
}