{
  "type": "Feature",
  "properties": {
    "addr:full":"Alcalde Leon De La Riva, 5 Simancas Valladolid 47130",
    "addr:housenumber":"5",
    "addr:postcode":"47130",
    "addr:street":"Alcalde Leon De La Riva",
    "iso:country":"ES",
    "sg:address":"Alcalde Leon De La Riva, 5",
    "sg:city":"Simancas",
    "sg:orig_category":"Inform\u00c1tica, Ofim\u00c1tica (estudios, Asesor\u00cda, Ingenier\u00cda, Formaci\u00d3n)",
    "sg:phone":"+34 983 59 19 37",
    "sg:postcode":"47130",
    "sg:province":"Valladolid",
    "wof:name":"At 7 Dise\u00f1o Informatico S.l.",
    "wof:placetype":"venue"
},
  "geometry": {"coordinates":[-4.8416934013,41.5892333984],"type":"Point"}
}