{
  "type": "Feature",
  "properties": {
    "addr:full":"Calle de Trespaderne, 5 Madrid Madrid 28042",
    "addr:housenumber":"5",
    "addr:postcode":"28042",
    "addr:street":"Calle De Trespaderne",
    "iso:country":"ES",
    "sg:address":"Calle de Trespaderne, 5",
    "sg:city":"Madrid",
    "sg:orig_category":"Molduras, Junquillos, Listones Y Molduras Perforadas",
    "sg:phone":"+34 917 47 56 90",
    "sg:postcode":"28042",
    "sg:province":"Madrid",
    "wof:name":"Velazquez Jimenez Laudelino",
    "wof:placetype":"venue"
},
  "geometry": {"coordinates":[-3.5813610554,40.4511070251],"type":"Point"}
}