{
  "type": "Feature",
  "properties": {
    "iso:country":"ES",
    "sg:address":"Carr Alemanya, 30",
    "sg:city":"Igualada",
    "sg:orig_category":"Distribuci\u00d3n De Petr\u00d3leo Y Derivados",
    "sg:phone":"+34 938 05 03 87",
    "sg:postcode":"08700",
    "sg:province":"Barcelona",
    "wof:name":"Soto Ballesteros S.l.",
    "wof:placetype":"venue"
},
  "geometry": {"coordinates":[1.6342730522,41.5847091675],"type":"Point"}
}