{
  "type": "Feature",
  "properties": {
    "iso:country":"ES",
    "sg:address":"Avda Hellin, 99996",
    "sg:city":"Madrid",
    "sg:orig_category":"Laboratorios Y Trabajos De Fotograf\u00cda, V\u00cddeo Y Cine",
    "sg:phone":"+34 913 06 73 97",
    "sg:postcode":"28037",
    "sg:province":"Madrid",
    "wof:name":"Iris Europea S.a.",
    "wof:placetype":"venue"
},
  "geometry": {"coordinates":[-3.6161189079,40.43227005],"type":"Point"}
}