{
  "type": "Feature",
  "properties": {
    "addr:full":"Carrer de Gabriel Miro, 2 Pedreguer Alicante 03750",
    "addr:housenumber":"2",
    "addr:postcode":"03750",
    "addr:street":"Carrer De Gabriel Miro",
    "iso:country":"ES",
    "sg:address":"Carrer de Gabriel Miro, 2",
    "sg:city":"Pedreguer",
    "sg:orig_category":"Caf\u00c9s, Bares, Cervecer\u00cdas",
    "sg:phone":"+34 966 45 62 73",
    "sg:postcode":"03750",
    "sg:province":"Alicante",
    "wof:name":"Ramis Fornes Teresa",
    "wof:placetype":"venue"
},
  "geometry": {"coordinates":[0.0332939997,38.7952957153],"type":"Point"}
}