{
  "type": "Feature",
  "properties": {
    "addr:full":"Extremo, 17 Pobra Carami\u00f1al La Coru\u00f1a 15940",
    "addr:housenumber":"17",
    "addr:postcode":"15940",
    "addr:street":"Extremo;Corun\u0303A",
    "iso:country":"ES",
    "sg:address":"Extremo, 17",
    "sg:city":"Pobra Carami\u00f1al",
    "sg:orig_category":"Molduras, Junquillos, Listones Y Molduras Perforadas",
    "sg:phone":"+34 981 83 22 52",
    "sg:postcode":"15940",
    "sg:province":"La Coru\u00f1a",
    "wof:name":"Rivas Rego Jose Francisco",
    "wof:placetype":"venue"
},
  "geometry": {"coordinates":[-8.938164711,42.6049346924],"type":"Point"}
}