{
  "type": "Feature",
  "properties": {
    "iso:country":"ES",
    "sg:address":"Carr Calderon De La Barca, 139",
    "sg:city":"Badalona",
    "sg:orig_category":"Confecci\u00d3n : Material, Suministros Y Accesorios",
    "sg:phone":"+34 933 83 10 03",
    "sg:postcode":"08914",
    "sg:province":"Barcelona",
    "wof:name":"Accesorios Jordan S.l.",
    "wof:placetype":"venue"
},
  "geometry": {"coordinates":[2.2226018906,41.4483757019],"type":"Point"}
}