{
  "type": "Feature",
  "properties": {
    "iso:country":"ES",
    "sg:address":"C/ Ciutat De Cartagena, 42",
    "sg:city":"Paterna",
    "sg:orig_category":"Electricidad: Equipos Industriales, Componentes (fabricaci\u00d3n)",
    "sg:phone":"+34 961 34 30 55",
    "sg:postcode":"46988",
    "sg:province":"Valencia",
    "sg:website":"w.w.w.viudafginer.com",
    "wof:name":"Viuda De Federico Giner S.a.",
    "wof:placetype":"venue"
},
  "geometry": {"coordinates":[-0.4736742973,39.5140266418],"type":"Point"}
}