{
  "type": "Feature",
  "properties": {
    "addr:full":"Avda Burjasot, 222 Valencia Valencia 46025",
    "addr:housenumber":"222",
    "addr:postcode":"46025",
    "addr:street":"Avda Burjasot",
    "iso:country":"ES",
    "sg:address":"Avda Burjasot, 222",
    "sg:city":"Valencia",
    "sg:orig_category":"Inmobiliaria (agencias)",
    "sg:phone":"+34 963 45 50 15",
    "sg:postcode":"46025",
    "sg:province":"Valencia",
    "wof:name":"Delcoso Roman S.l.",
    "wof:placetype":"venue"
},
  "geometry": {"coordinates":[-0.393768996,39.4928398132],"type":"Point"}
}