{
  "type": "Feature",
  "properties": {
    "addr:full":"Calle de Pareja, General, 14 Melilla Melilla 52001",
    "addr:housenumber":"14",
    "addr:postcode":"52001",
    "addr:street":"Calle De Pareja General",
    "iso:country":"ES",
    "sg:address":"Calle de Pareja, General, 14",
    "sg:city":"Melilla",
    "sg:orig_category":"Peluqueros: De Se\u00d1oras",
    "sg:phone":"+34 952 68 41 82",
    "sg:postcode":"52001",
    "sg:province":"Melilla",
    "wof:name":"Garcia Mesa Isabel",
    "wof:placetype":"venue"
},
  "geometry": {"coordinates":[-2.9411659241,35.2941246033],"type":"Point"}
}