{
  "type": "Feature",
  "properties": {
    "iso:country":"ES",
    "sg:address":"Pol Ind Ctra Amarilla, S/n",
    "sg:city":"Utrera",
    "sg:orig_category":"Confecci\u00d3n De Zapatos",
    "sg:phone":"+34 955 86 12 64",
    "sg:postcode":"41710",
    "sg:province":"Sevilla",
    "wof:name":"Iturri S.a.",
    "wof:placetype":"venue"
},
  "geometry": {"coordinates":[-5.7932009697,37.0917663574],"type":"Point"}
}