{
  "type": "Feature",
  "properties": {
    "iso:country":"ES",
    "sg:address":"Calle de Federico Sanchez Bedoya, 20",
    "sg:city":"Sevilla",
    "sg:orig_category":"Asesor\u00cda De Formaci\u00d3n Y Gesti\u00d3n De Personal",
    "sg:phone":"+34 954 22 99 82",
    "sg:postcode":"41001",
    "sg:province":"Sevilla",
    "wof:name":"Aneas Guillen Antonio",
    "wof:placetype":"venue"
},
  "geometry": {"coordinates":[-5.9957938194,37.3861312866],"type":"Point"}
}