{
  "type": "Feature",
  "properties": {
    "addr:full":"Pla\u00c7 Maestro Palau, 9 Moncada Valencia 46113",
    "addr:housenumber":"9",
    "addr:postcode":"46113",
    "addr:street":"Maestro Palau",
    "iso:country":"ES",
    "sg:address":"Pla\u00c7 Maestro Palau, 9",
    "sg:city":"Moncada",
    "sg:orig_category":"Carnicer\u00cdas, Carnicer\u00cdas",
    "sg:phone":"+34 961 39 02 13",
    "sg:postcode":"46113",
    "sg:province":"Valencia",
    "wof:name":"Fort Trenco Ramon Desiderio",
    "wof:placetype":"venue"
},
  "geometry": {"coordinates":[-0.3917999864,39.5449790955],"type":"Point"}
}