{
  "type": "Feature",
  "properties": {
    "iso:country":"ES",
    "sg:address":"Calle de Jaboneria, 65",
    "sg:city":"Alcorcon",
    "sg:orig_category":"Administraciones Regionales, Departamentales Y Locales",
    "sg:phone":"+34 916 64 81 00",
    "sg:postcode":"28...",
    "sg:province":"Madrid",
    "sg:website":"www.ayto-alcorcon.es",
    "wof:name":"Ayuntamiento De Alcorcon",
    "wof:placetype":"venue"
},
  "geometry": {"coordinates":[-3.8228850365,40.3496818542],"type":"Point"}
}