{
  "type": "Feature",
  "properties": {
    "addr:full":"Urb. Rancho Hotel, 3 Elviria M\u00e1laga 29604",
    "addr:housenumber":"3",
    "addr:postcode":"29604",
    "addr:street":"Urb.;Elviria Ma\u0301Laga",
    "iso:country":"ES",
    "sg:address":"Urb. Rancho Hotel, 3",
    "sg:city":"Elviria",
    "sg:orig_category":"Lavado, Limpieza De Veh\u00cdculos",
    "sg:phone":"+34 952 83 61 27",
    "sg:postcode":"29604",
    "sg:province":"M\u00e1laga",
    "wof:name":"Indifon S.a.",
    "wof:placetype":"venue"
},
  "geometry": {"coordinates":[-4.7747840881,36.4966812134],"type":"Point"}
}