{
  "type": "Feature",
  "properties": {
    "iso:country":"ES",
    "sg:address":"Rua Bautizados (dos), 1",
    "sg:city":"Santiago De Compostela",
    "sg:orig_category":"Inmobiliaria (agencias)",
    "sg:phone":"+34 981 55 31 15",
    "sg:postcode":"15702",
    "sg:province":"La Coru\u00f1a",
    "wof:name":"Gecur S.l.",
    "wof:placetype":"venue"
},
  "geometry": {"coordinates":[-8.5453195572,42.8773422241],"type":"Point"}
}