{
  "type": "Feature",
  "properties": {
    "addr:full":"Aingeru Kalea, 4 Azkoitia Guip\u00f9zcoa 20720",
    "addr:housenumber":"4",
    "addr:postcode":"20720",
    "addr:street":"Aingeru Kalea;Guipu\u0300Zcoa",
    "iso:country":"ES",
    "sg:address":"Aingeru Kalea, 4",
    "sg:city":"Azkoitia",
    "sg:orig_category":"Electricidad: Instaladores",
    "sg:phone":"+34 943 85 00 90",
    "sg:postcode":"20720",
    "sg:province":"Guip\u00f9zcoa",
    "wof:name":"Bigen Argi Lanak S.l.",
    "wof:placetype":"venue"
},
  "geometry": {"coordinates":[-2.3145179749,43.1772918701],"type":"Point"}
}