{
  "type": "Feature",
  "properties": {
    "iso:country":"ES",
    "sg:address":"Avda Del Mediterrani, 3",
    "sg:city":"Onda",
    "sg:orig_category":"Agentes, Concesionarios Y Sucursales De Veh\u00cdculos",
    "sg:phone":"+34 964 60 10 24",
    "sg:postcode":"12200",
    "sg:province":"Castell\u00f3n",
    "wof:name":"Talleres Elios Sanchez S.l.",
    "wof:placetype":"venue"
},
  "geometry": {"coordinates":[-0.2524180114,39.9652938843],"type":"Point"}
}