{
  "type": "Feature",
  "properties": {
    "iso:country":"ES",
    "sg:address":"Calle de Templarios (los), 3",
    "sg:city":"Fabero",
    "sg:orig_category":"Farmacias",
    "sg:phone":"+34 987 55 04 32",
    "sg:postcode":"24420",
    "sg:province":"Le\u00f3n",
    "wof:name":"Orallo Cambeiro Placida Maria",
    "wof:placetype":"venue"
},
  "geometry": {"coordinates":[-6.627863884,42.7677383423],"type":"Point"}
}