{
  "type": "Feature",
  "properties": {
    "iso:country":"ES",
    "sg:address":"Calle de Olvera, 9",
    "sg:city":"Valdelagrana",
    "sg:orig_category":"Caf\u00c9s, Bares, Cervecer\u00cdas",
    "sg:phone":"+34 956 56 02 67",
    "sg:postcode":"11500",
    "sg:province":"C\u00e1diz",
    "wof:name":"Chacon Fernandez Ana Maria",
    "wof:placetype":"venue"
},
  "geometry": {"coordinates":[-6.2166838646,36.5751228333],"type":"Point"}
}