{
  "type": "Feature",
  "properties": {
    "iso:country":"ES",
    "sg:address":"Avda Reino De Leon, 9",
    "sg:city":"Le\u00f3n",
    "sg:orig_category":"Frutas, Legumbres Frescas Y Tempranas (al Por Menor)",
    "sg:phone":"+34 987 20 25 81",
    "sg:postcode":"24006",
    "sg:province":"Le\u00f3n",
    "wof:name":"Chamorro Alvarez Jose Luis",
    "wof:placetype":"venue"
},
  "geometry": {"coordinates":[-5.5643191338,42.5925140381],"type":"Point"}
}