{
  "type": "Feature",
  "properties": {
    "iso:country":"ES",
    "sg:address":"Ctra Marinaleda, 3",
    "sg:city":"Estepa",
    "sg:orig_category":"Arquitectos",
    "sg:phone":"+34 955 91 23 33",
    "sg:postcode":"41560",
    "sg:province":"Sevilla",
    "sg:website":"www.ajrobles.c.telefonica.net",
    "wof:name":"A Robles S.c.p.",
    "wof:placetype":"venue"
},
  "geometry": {"coordinates":[-4.8607959747,37.3641204834],"type":"Point"}
}