{
  "type": "Feature",
  "properties": {
    "addr:full":"Ptda Tollos, S/n Tous Valencia 46269",
    "addr:housenumber":"s / n",
    "addr:postcode":"46269",
    "addr:street":"Ptda Tollos",
    "iso:country":"ES",
    "sg:address":"Ptda Tollos, S/n",
    "sg:city":"Tous",
    "sg:orig_category":"Pirotecnia (espect\u00c1culos)",
    "sg:phone":"+34 962 12 00 01",
    "sg:postcode":"46269",
    "sg:province":"Valencia",
    "wof:name":"Pirotecnia Zamorano Caballer S.a.",
    "wof:placetype":"venue"
},
  "geometry": {"coordinates":[-0.5896350145,39.1404190063],"type":"Point"}
}