{
  "type": "Feature",
  "properties": {
    "addr:full":"Calle de Mayor, 98 Alberca De Las Torres Murcia 30150",
    "addr:housenumber":"98",
    "addr:postcode":"30150",
    "addr:street":"Calle De Mayor",
    "iso:country":"ES",
    "sg:address":"Calle de Mayor, 98",
    "sg:city":"Alberca De Las Torres",
    "sg:orig_category":"Bancos",
    "sg:phone":"+34 968 84 59 05",
    "sg:postcode":"30150",
    "sg:province":"Murcia",
    "sg:website":"www.bancodevalencia.es",
    "wof:name":"Banco De Valencia S.a.",
    "wof:placetype":"venue"
},
  "geometry": {"coordinates":[-1.1438070536,37.9413108826],"type":"Point"}
}