{
  "type": "Feature",
  "properties": {
    "iso:country":"ES",
    "sg:address":"Vallehermoso, 24",
    "sg:city":"Madrid",
    "sg:orig_category":"Veh\u00cdculos De Ocasi\u00d3n",
    "sg:phone":"+34 914 47 08 81",
    "sg:postcode":"28015",
    "sg:province":"Madrid",
    "sg:website":"www.garagejj.com",
    "wof:name":"Garaje J-j S.a.",
    "wof:placetype":"venue"
},
  "geometry": {"coordinates":[-3.7088108063,40.4324798584],"type":"Point"}
}