{
  "type": "Feature",
  "properties": {
    "addr:full":"Cm\u00d1o Con Do Gato, 52 Grove Pontevedra 36980",
    "addr:housenumber":"52",
    "addr:postcode":"36980",
    "addr:street":"Grove Pontevedra",
    "iso:country":"ES",
    "sg:address":"Cm\u00d1o Con Do Gato, 52",
    "sg:city":"Grove",
    "sg:orig_category":"Fabricaci\u00d3n, Reparaci\u00d3n Y Mantenimiento De Construcciones Navales Y Fluviales",
    "sg:phone":"+34 986 73 02 12",
    "sg:postcode":"36980",
    "sg:province":"Pontevedra",
    "wof:name":"Gondar Perez Jose Carlos",
    "wof:placetype":"venue"
},
  "geometry": {"coordinates":[-8.86282444,42.4956588745],"type":"Point"}
}