{
  "type": "Feature",
  "properties": {
    "addr:full":"Plaz Ayuntamiento, S/n Boal Asturias 33720",
    "addr:housenumber":"/ n",
    "addr:postcode":"33720",
    "addr:street":"S",
    "iso:country":"ES",
    "sg:address":"Plaz Ayuntamiento, S/n",
    "sg:city":"Boal",
    "sg:classifiers":[
        {
            "category":"Taxi",
            "type":"Transportation"
        }
    ],
    "sg:phone":"+34 985 62 02 50",
    "sg:postcode":"33720",
    "sg:province":"Asturias",
    "wof:name":"Ayuntamiento De Boal",
    "wof:placetype":"venue"
},
  "geometry": {"coordinates":[-6.8185386658,43.428478241],"type":"Point"}
}