{
  "type": "Feature",
  "properties": {
    "addr:full":"Carrer de Riera Blanca, 46 Hospitalet Llobregat Barcelona 08903",
    "addr:housenumber":"46",
    "addr:postcode":"08903",
    "addr:street":"Carrer De Riera Blanca",
    "iso:country":"ES",
    "sg:address":"Carrer de Riera Blanca, 46",
    "sg:city":"Hospitalet Llobregat",
    "sg:orig_category":"Institutos De Belleza",
    "sg:phone":"+34 934 48 54 81",
    "sg:postcode":"08903",
    "sg:province":"Barcelona",
    "wof:name":"Jara Y Marta S.l.l.",
    "wof:placetype":"venue"
},
  "geometry": {"coordinates":[2.1235349178,41.374370575],"type":"Point"}
}