{
  "type": "Feature",
  "properties": {
    "iso:country":"ES",
    "sg:address":"Carrer de Canuda, 6",
    "sg:city":"Barcelona",
    "sg:orig_category":"Sindicatos Y Colegios Profesionales",
    "sg:phone":"+34 933 18 87 48",
    "sg:postcode":"08002",
    "sg:province":"Barcelona",
    "wof:name":"Associacio Colegial D'escriptors De Catalunya",
    "wof:placetype":"venue"
},
  "geometry": {"coordinates":[2.1716122627,41.3846740723],"type":"Point"}
}