{
  "type": "Feature",
  "properties": {
    "addr:full":"Av Santa Coloma, 38 Santa Coloma De Gramenet Barcelona 08922",
    "addr:housenumber":"38",
    "addr:postcode":"08922",
    "addr:street":"Av Santa Coloma",
    "iso:country":"ES",
    "sg:address":"Av Santa Coloma, 38",
    "sg:city":"Santa Coloma De Gramenet",
    "sg:orig_category":"Panader\u00cdas, Panader\u00cdas",
    "sg:phone":"+34 934 66 07 34",
    "sg:postcode":"08922",
    "sg:province":"Barcelona",
    "wof:name":"Panificadora San Carlos S.a.",
    "wof:placetype":"venue"
},
  "geometry": {"coordinates":[2.207447052,41.4489517212],"type":"Point"}
}