{
  "type": "Feature",
  "properties": {
    "iso:country":"ES",
    "sg:address":"Calle de Embajadores, 117",
    "sg:city":"Madrid",
    "sg:orig_category":"Cojinetes De Bolas, Agujas Y Rodillos (fabricaci\u00d3n, Al Por Mayor)",
    "sg:phone":"+34 914 68 41 71",
    "sg:postcode":"28045",
    "sg:province":"Madrid",
    "wof:name":"Rodacars S.a.",
    "wof:placetype":"venue"
},
  "geometry": {"coordinates":[-3.6973359585,40.3982810974],"type":"Point"}
}