{
  "type": "Feature",
  "properties": {
    "iso:country":"ES",
    "sg:address":"Calle de Gamazo, 12",
    "sg:city":"Valladolid",
    "sg:classifiers":[
        {
            "category":"Autos & Motor Vehicles",
            "subcategory":"Automobile Sales",
            "type":"Retail Goods"
        }
    ],
    "sg:phone":"+34 983 30 55 69",
    "sg:postcode":"47004",
    "sg:province":"Valladolid",
    "wof:name":"Arroyo Tovar Jose Maria",
    "wof:placetype":"venue"
},
  "geometry": {"coordinates":[-4.7261371613,41.6465911865],"type":"Point"}
}