{
  "type": "Feature",
  "properties": {
    "iso:country":"ES",
    "sg:address":"Carr Pica D'estats, 21",
    "sg:city":"Lleida",
    "sg:orig_category":"Comercio, Reparaci\u00d3n De Bicicletas, De Motocicletas, De Accesorios",
    "sg:phone":"+34 973 28 20 12",
    "sg:postcode":"25006",
    "sg:province":"Lleida",
    "wof:name":"Antonio Solsona E Hijos S.l.",
    "wof:placetype":"venue"
},
  "geometry": {"coordinates":[0.6151934266,41.617980957],"type":"Point"}
}