{
  "type": "Feature",
  "properties": {
    "iso:country":"ES",
    "sg:address":"Velazquez, 71",
    "sg:city":"Madrid",
    "sg:orig_category":"Ropa Para Se\u00d1oras (al Por Menor)",
    "sg:phone":"+34 915 78 14 27",
    "sg:postcode":"28006",
    "sg:province":"Madrid",
    "sg:website":"www.jorgegomez.es",
    "wof:name":"Jorge Gomez Manuel Agustin",
    "wof:placetype":"venue"
},
  "geometry": {"coordinates":[-3.6838200092,40.4309425354],"type":"Point"}
}