{
  "type": "Feature",
  "properties": {
    "iso:country":"ES",
    "sg:address":"Iturriotz Kalea, 7",
    "sg:city":"Arrasate",
    "sg:orig_category":"Cl\u00cdnicas Dentales",
    "sg:phone":"+34 943 79 73 88",
    "sg:postcode":"20500",
    "sg:province":"Guip\u00f9zcoa",
    "wof:name":"Caviglia Rey Silvana",
    "wof:placetype":"venue"
},
  "geometry": {"coordinates":[-2.4891240597,43.0659675598],"type":"Point"}
}