{
  "type": "Feature",
  "properties": {
    "iso:country":"ES",
    "sg:address":"Carr Nou, 4",
    "sg:city":"Girona",
    "sg:orig_category":"Zapatos (al Por Menor)",
    "sg:phone":"+34 972 20 44 70",
    "sg:postcode":"17001",
    "sg:province":"Girona",
    "wof:name":"Baro Puig Antonio",
    "wof:placetype":"venue"
},
  "geometry": {"coordinates":[2.8187448978,41.9808616638],"type":"Point"}
}