{
  "type": "Feature",
  "properties": {
    "addr:full":"Carrer de Pere De Fices, 49 Terrassa Barcelona 08225",
    "addr:housenumber":"49",
    "addr:postcode":"08225",
    "addr:street":"Carrer De Pere De Fices",
    "iso:country":"ES",
    "sg:address":"Carrer de Pere De Fices, 49",
    "sg:city":"Terrassa",
    "sg:orig_category":"Trabajos De Perforaciones, Sondeos, Construcci\u00d3n De Pozos",
    "sg:phone":"+34 937 33 61 78",
    "sg:postcode":"08225",
    "sg:province":"Barcelona",
    "sg:website":"www.trepanos.com",
    "wof:name":"Matarin Ayala Jose",
    "wof:placetype":"venue"
},
  "geometry": {"coordinates":[2.0091760159,41.5737266541],"type":"Point"}
}