{
  "type": "Feature",
  "properties": {
    "addr:full":"Avda Canillejas A Vicalvaro, 129 Madrid Madrid 28022",
    "addr:housenumber":"129",
    "addr:postcode":"28022",
    "addr:street":"Avda Canillejas A Vicalvaro",
    "iso:country":"ES",
    "sg:address":"Avda Canillejas A Vicalvaro, 129",
    "sg:city":"Madrid",
    "sg:orig_category":"Masajistas Kinesiterapeutas",
    "sg:phone":"+34 913 06 38 58",
    "sg:postcode":"28022",
    "sg:province":"Madrid",
    "wof:name":"Carmona Avalo Francisca",
    "wof:placetype":"venue"
},
  "geometry": {"coordinates":[-3.6110970974,40.4272422791],"type":"Point"}
}