{
  "type": "Feature",
  "properties": {
    "addr:full":"Calle de Misericordia, 14 Zamora Zamora 49001",
    "addr:housenumber":"14",
    "addr:postcode":"49001",
    "addr:street":"Calle De Misericordia",
    "iso:country":"ES",
    "sg:address":"Calle de Misericordia, 14",
    "sg:city":"Zamora",
    "sg:orig_category":"Molduras, Junquillos, Listones Y Molduras Perforadas",
    "sg:phone":"+34 980 53 15 58",
    "sg:postcode":"49001",
    "sg:province":"Zamora",
    "wof:name":"Arroyo Garcia Santiago",
    "wof:placetype":"venue"
},
  "geometry": {"coordinates":[-5.7502770424,41.501914978],"type":"Point"}
}