{
  "type": "Feature",
  "properties": {
    "iso:country":"ES",
    "sg:address":"Carr Senda Del Moli, 34",
    "sg:city":"Blanes",
    "sg:orig_category":"Alquiler De V\u00cddeo",
    "sg:phone":"+34 972 33 06 48",
    "sg:postcode":"17300",
    "sg:province":"Girona",
    "wof:name":"Cruz Fernandez Antonio Jose",
    "wof:placetype":"venue"
},
  "geometry": {"coordinates":[2.784473896,41.6693305969],"type":"Point"}
}