{
  "type": "Feature",
  "properties": {
    "iso:country":"ES",
    "sg:address":"Pase Universidad, 15",
    "sg:city":"Vitoria-gasteiz",
    "sg:orig_category":"Ense\u00d1anza Variada",
    "sg:phone":"+34 945 13 19 06",
    "sg:postcode":"01006",
    "sg:province":"\u00c1lava",
    "wof:name":"Escuela Superior De Negocios Y Tecnologia S.l.",
    "wof:placetype":"venue"
},
  "geometry": {"coordinates":[-2.6764519215,42.8412437439],"type":"Point"}
}