{
  "type": "Feature",
  "properties": {
    "iso:country":"ES",
    "sg:address":"Calle de Mayor, 2",
    "sg:city":"Garrucha",
    "sg:orig_category":"Albergues",
    "sg:phone":"+34 950 46 02 29",
    "sg:postcode":"04630",
    "sg:province":"Almer\u00eda",
    "wof:name":"Martinez Molina Francisco Juan",
    "wof:placetype":"venue"
},
  "geometry": {"coordinates":[-1.8200069666,37.1870002747],"type":"Point"}
}