{
  "type": "Feature",
  "properties": {
    "iso:country":"ES",
    "sg:address":"Avda Herencia, S/n",
    "sg:city":"Alcazar S. Juan",
    "sg:orig_category":"Fabricaci\u00d3n De Muebles",
    "sg:phone":"+34 926 54 41 64",
    "sg:postcode":"13600",
    "sg:province":"Ciudad Real",
    "wof:name":"Muebles Ramirez C.b.",
    "wof:placetype":"venue"
},
  "geometry": {"coordinates":[-3.2183539867,39.3883552551],"type":"Point"}
}