{
  "type": "Feature",
  "properties": {
    "iso:country":"ES",
    "sg:address":"Calle de Erreka Bazterrak, 20",
    "sg:city":"Urbi",
    "sg:orig_category":"Adaptaciones, Acondicionamientos Especiales Para Veh\u00cdculos, Veh\u00cdculos Industriales",
    "sg:phone":"+34 944 26 26 29",
    "sg:postcode":"48970",
    "sg:province":"Vizcaya",
    "sg:website":"www.wrccompeticion.com",
    "wof:name":"W R C Tuning Competicion Sl",
    "wof:placetype":"venue"
},
  "geometry": {"coordinates":[-2.881862402,43.2284431458],"type":"Point"}
}