{
  "type": "Feature",
  "properties": {
    "addr:full":"Tiburzio Anitua Kalea, 12 Eibar Guip\u00f9zcoa 20600",
    "addr:housenumber":"12",
    "addr:postcode":"20600",
    "addr:street":"Tiburzio Anitua Kalea;Guipu\u0300Zcoa",
    "iso:country":"ES",
    "sg:address":"Tiburzio Anitua Kalea, 12",
    "sg:city":"Eibar",
    "sg:orig_category":"Molduras, Junquillos, Listones Y Molduras Perforadas",
    "sg:phone":"+34 943 20 35 01",
    "sg:postcode":"20600",
    "sg:province":"Guip\u00f9zcoa",
    "wof:name":"Suarez Diaz Maria Del Carmen",
    "wof:placetype":"venue"
},
  "geometry": {"coordinates":[-2.4830789566,43.1828308105],"type":"Point"}
}