{
  "type": "Feature",
  "properties": {
    "iso:country":"ES",
    "sg:address":"Bard Nuestro Padre Jesus, S/n",
    "sg:city":"Lora Rio",
    "sg:orig_category":"Carnicer\u00cdas, Carnicer\u00cdas",
    "sg:phone":"+34 955 80 34 17",
    "sg:postcode":"41440",
    "sg:province":"Sevilla",
    "wof:name":"Martin Galvez Antonia",
    "wof:placetype":"venue"
},
  "geometry": {"coordinates":[-5.5281839371,37.659828186],"type":"Point"}
}