{
  "type": "Feature",
  "properties": {
    "iso:country":"ES",
    "sg:address":"Ctra Sabadell, Km. 0013,0",
    "sg:city":"Rubi",
    "sg:orig_category":"Cerrajer\u00cda, Ferrallista",
    "sg:phone":"+34 936 99 69 30",
    "sg:postcode":"08191",
    "sg:province":"Barcelona",
    "wof:name":"Enjo S.l.",
    "wof:placetype":"venue"
},
  "geometry": {"coordinates":[2.0354149342,41.5032501221],"type":"Point"}
}