{
  "type": "Feature",
  "properties": {
    "addr:full":"Pl Vila, 3 S. Pol Mar Barcelona 08395",
    "addr:housenumber":"3",
    "addr:postcode":"08395",
    "addr:street":"Pl Vila;Pol;Barcelona",
    "iso:country":"ES",
    "sg:address":"Pl Vila, 3",
    "sg:city":"S. Pol Mar",
    "sg:orig_category":"Museos",
    "sg:phone":"+34 937 60 08 46",
    "sg:postcode":"08395",
    "sg:province":"Barcelona",
    "wof:name":"Ajuntament De Sant Pol De Mar",
    "wof:placetype":"venue"
},
  "geometry": {"coordinates":[2.6626732349,41.6215782166],"type":"Point"}
}