{
  "type": "Feature",
  "properties": {
    "addr:full":"Grup Arrizar, 12 Donostia-san Sebastian Guip\u00f9zcoa 20017",
    "addr:housenumber":"12",
    "addr:postcode":"20017",
    "addr:street":"Arrizar",
    "iso:country":"ES",
    "sg:address":"Grup Arrizar, 12",
    "sg:city":"Donostia-san Sebastian",
    "sg:orig_category":"Peluquer\u00cdas",
    "sg:phone":"+34 943 35 12 75",
    "sg:postcode":"20017",
    "sg:province":"Guip\u00f9zcoa",
    "wof:name":"Barbe Alcorta David",
    "wof:placetype":"venue"
},
  "geometry": {"coordinates":[-1.9297319651,43.3184700012],"type":"Point"}
}