{
  "type": "Feature",
  "properties": {
    "addr:full":"Partida Vilaperdich, S/n Benicarlo Castell\u00f3n 12580",
    "addr:housenumber":"s",
    "addr:postcode":"12580",
    "addr:street":"Partida Vilaperdich;/ N;Castello\u0301N",
    "iso:country":"ES",
    "sg:address":"Partida Vilaperdich, S/n",
    "sg:city":"Benicarlo",
    "sg:orig_category":"Poller\u00cda Y Caza (al Por Menor)",
    "sg:phone":"+34 964 47 34 33",
    "sg:postcode":"12580",
    "sg:province":"Castell\u00f3n",
    "wof:name":"Granja Vicent S. L.",
    "wof:placetype":"venue"
},
  "geometry": {"coordinates":[0.4042100012,40.4457893372],"type":"Point"}
}