{
  "type": "Feature",
  "properties": {
    "iso:country":"ES",
    "sg:address":"Plaz Generalisimo, 12",
    "sg:city":"Suances",
    "sg:orig_category":"Fisioterapia",
    "sg:phone":"+34 942 84 40 04",
    "sg:postcode":"39340",
    "sg:province":"Cantabria",
    "wof:name":"Garcia Rio Pablo",
    "wof:placetype":"venue"
},
  "geometry": {"coordinates":[-4.0416297913,43.4257621765],"type":"Point"}
}