{
  "type": "Feature",
  "properties": {
    "iso:country":"ES",
    "sg:address":"Calle de Teresa Gil, 15",
    "sg:city":"Valladolid",
    "sg:orig_category":"Telas Y Sedas (al Por Menor)",
    "sg:phone":"+34 983 30 27 10",
    "sg:postcode":"47002",
    "sg:province":"Valladolid",
    "wof:name":"Garcia Sanz Leopoldo Jose",
    "wof:placetype":"venue"
},
  "geometry": {"coordinates":[-4.7255740166,41.650806427],"type":"Point"}
}