{
  "type": "Feature",
  "properties": {
    "addr:full":"Av Torrent, D'es, 24 Manacor Islas Baleares 07500",
    "addr:housenumber":"24",
    "addr:postcode":"07500",
    "addr:street":"Av Torrent D'Es",
    "iso:country":"ES",
    "sg:address":"Av Torrent, D'es, 24",
    "sg:city":"Manacor",
    "sg:orig_category":"Inmobiliaria (agencias)",
    "sg:phone":"+34 971 55 92 81",
    "sg:postcode":"07500",
    "sg:province":"Islas Baleares",
    "wof:name":"Massot Segura Antonio",
    "wof:placetype":"venue"
},
  "geometry": {"coordinates":[3.2087171078,39.5662155151],"type":"Point"}
}