{
  "type": "Feature",
  "properties": {
    "addr:full":"Rua Rio Arnoia, 14 Xinzo De Limia Ourense 32630",
    "addr:housenumber":"14",
    "addr:postcode":"32630",
    "addr:street":"Rua;Arnoia",
    "iso:country":"ES",
    "sg:address":"Rua Rio Arnoia, 14",
    "sg:city":"Xinzo De Limia",
    "sg:orig_category":"Centros De Coordinaci\u00d3n",
    "sg:phone":"+34 988 46 14 68",
    "sg:postcode":"32630",
    "sg:province":"Ourense",
    "wof:name":"Celta Xestions S.l.",
    "wof:placetype":"venue"
},
  "geometry": {"coordinates":[-7.7236161232,42.0579910278],"type":"Point"}
}