{
  "type": "Feature",
  "properties": {
    "iso:country":"ES",
    "sg:address":"Carrer de Barcelona, 18",
    "sg:city":"Manresa",
    "sg:orig_category":"Locales Y Clases De Danza",
    "sg:phone":"+34 938 73 20 24",
    "sg:postcode":"08242",
    "sg:province":"Barcelona",
    "wof:name":"Balaguer Bonvehi Mari Angels",
    "wof:placetype":"venue"
},
  "geometry": {"coordinates":[1.8228499889,41.7310829163],"type":"Point"}
}