{
  "type": "Feature",
  "properties": {
    "addr:full":"Pla\u00c7 Major, 4 Camarasa Lleida 25613",
    "addr:postcode":"25613",
    "iso:country":"ES",
    "sg:address":"Pla\u00c7 Major, 4",
    "sg:city":"Camarasa",
    "sg:orig_category":"Pensiones Familiares",
    "sg:phone":"+34 973 42 00 29",
    "sg:postcode":"25613",
    "sg:province":"Lleida",
    "wof:name":"Garde\u00f1es Llorens Casiano",
    "wof:placetype":"venue"
},
  "geometry": {"coordinates":[0.8484523892,41.8569526672],"type":"Point"}
}