{
  "type": "Feature",
  "properties": {
    "iso:country":"ES",
    "sg:address":"Plaz Anteiglesia De Zaldua, 8",
    "sg:city":"Zaldibar",
    "sg:orig_category":"Molduras, Junquillos, Listones Y Molduras Perforadas",
    "sg:phone":"+34 946 82 70 03",
    "sg:postcode":"48250",
    "sg:province":"Vizcaya",
    "wof:name":"Alberdi Gaztelurrutia Maria Angeles",
    "wof:placetype":"venue"
},
  "geometry": {"coordinates":[-2.5247449875,43.1711616516],"type":"Point"}
}