{
  "type": "Feature",
  "properties": {
    "addr:full":"Crt Almansa, S/n Fuente-alamo Albacete 02651",
    "addr:housenumber":"s / n",
    "addr:postcode":"02651",
    "iso:country":"ES",
    "sg:address":"Crt Almansa, S/n",
    "sg:city":"Fuente-alamo",
    "sg:orig_category":"Mec\u00c1nico Del Autom\u00d3vil",
    "sg:phone":"+34 967 32 11 28",
    "sg:postcode":"02651",
    "sg:province":"Albacete",
    "wof:name":"Cerdan Felipe Ildefonso",
    "wof:placetype":"venue"
},
  "geometry": {"coordinates":[-1.4325129986,38.6947288513],"type":"Point"}
}