{
  "type": "Feature",
  "properties": {
    "addr:full":"Avda Andalucia, 51 Arjonilla Ja\u00e9n 23750",
    "addr:housenumber":"51",
    "addr:postcode":"23750",
    "addr:street":"Avda Andalucia",
    "iso:country":"ES",
    "sg:address":"Avda Andalucia, 51",
    "sg:city":"Arjonilla",
    "sg:orig_category":"Fabricaci\u00d3n De Muebles",
    "sg:phone":"+34 953 52 04 01",
    "sg:postcode":"23750",
    "sg:province":"Ja\u00e9n",
    "wof:name":"Garcia Lara Bartolome",
    "wof:placetype":"venue"
},
  "geometry": {"coordinates":[-4.108976841,37.9744033813],"type":"Point"}
}