{
  "type": "Feature",
  "properties": {
    "addr:full":"Carrer de Nou De La Rambla, 48 Barcelona Barcelona 08001",
    "addr:housenumber":"48",
    "addr:postcode":"08001",
    "addr:street":"Carrer De Nou De La Rambla",
    "iso:country":"ES",
    "sg:address":"Carrer de Nou De La Rambla, 48",
    "sg:city":"Barcelona",
    "sg:orig_category":"Quincaller\u00cda (al Por Menor)",
    "sg:phone":"+34 933 29 91 36",
    "sg:postcode":"08001",
    "sg:province":"Barcelona",
    "wof:name":"Navarro Bueno Antonio",
    "wof:placetype":"venue"
},
  "geometry": {"coordinates":[2.1725161076,41.3776130676],"type":"Point"}
}