{
  "type": "Feature",
  "properties": {
    "addr:full":"Carr Barcelona, 47 Breda Girona 17400",
    "addr:housenumber":"47",
    "addr:postcode":"17400",
    "addr:street":"Carr Barcelona",
    "iso:country":"ES",
    "sg:address":"Carr Barcelona, 47",
    "sg:city":"Breda",
    "sg:orig_category":"Promotores Constructores",
    "sg:phone":"+34 972 87 11 09",
    "sg:postcode":"17400",
    "sg:province":"Girona",
    "wof:name":"Diaz Gonzalez Antonio",
    "wof:placetype":"venue"
},
  "geometry": {"coordinates":[2.5579440594,41.7450752258],"type":"Point"}
}