{
  "type": "Feature",
  "properties": {
    "iso:country":"ES",
    "sg:address":"Calle de Carmen, 1",
    "sg:city":"Tarancon",
    "sg:orig_category":"Molduras, Junquillos, Listones Y Molduras Perforadas",
    "sg:phone":"+34 969 32 12 43",
    "sg:postcode":"16400",
    "sg:province":"Cuenca",
    "wof:name":"Catalan Sanchez Antonio",
    "wof:placetype":"venue"
},
  "geometry": {"coordinates":[-3.0099527836,40.0101165771],"type":"Point"}
}