{
  "type": "Feature",
  "properties": {
    "iso:country":"ES",
    "sg:address":"Avgd Jaume I, 54",
    "sg:city":"Olleria",
    "sg:orig_category":"Agencias Y Agentes Comerciales, Representantes",
    "sg:phone":"+34 962 20 02 79",
    "sg:postcode":"46850",
    "sg:province":"Valencia",
    "wof:name":"Albi\u00f1ana Garcia Vicente",
    "wof:placetype":"venue"
},
  "geometry": {"coordinates":[-0.5538514256,38.9147148132],"type":"Point"}
}