{
  "type": "Feature",
  "properties": {
    "iso:country":"ES",
    "sg:address":"Capitan (la Vera), 8",
    "sg:city":"Sta.ursula",
    "sg:orig_category":"Supermercados Y Hipermercados",
    "sg:phone":"+34 922 30 11 86",
    "sg:postcode":"38390",
    "sg:province":"Santa Cruz De Tenerife",
    "wof:name":"Calzadilla Gutierrez Juan",
    "wof:placetype":"venue"
},
  "geometry": {"coordinates":[-16.4837837219,28.4287948608],"type":"Point"}
}