{
  "type": "Feature",
  "properties": {
    "addr:full":"Av Novelda, 160 Elche Alicante 03206",
    "addr:housenumber":"160",
    "addr:postcode":"03206",
    "addr:street":"Av Novelda",
    "iso:country":"ES",
    "sg:address":"Av Novelda, 160",
    "sg:city":"Elche",
    "sg:orig_category":"Zapatos (al Por Menor)",
    "sg:phone":"+34 966 67 31 47",
    "sg:postcode":"03206",
    "sg:province":"Alicante",
    "wof:name":"Comodidad Sl",
    "wof:placetype":"venue"
},
  "geometry": {"coordinates":[-0.7208619714,38.2819328308],"type":"Point"}
}