{
  "type": "Feature",
  "properties": {
    "iso:country":"ES",
    "sg:address":"Barrio Santa Cruz, S/n",
    "sg:city":"Sepulveda",
    "sg:orig_category":"Ba\u00d1os Y Duchas P\u00dablicos",
    "sg:phone":"+34 921 54 01 43",
    "sg:postcode":"40300",
    "sg:province":"Segovia",
    "wof:name":"Ayuntamiento De Sepulveda",
    "wof:placetype":"venue"
},
  "geometry": {"coordinates":[-3.7763793468,41.3514328003],"type":"Point"}
}