{
  "type": "Feature",
  "properties": {
    "addr:full":"Avda Trapiche, S/n Marbella M\u00e1laga 29600",
    "addr:postcode":"29600",
    "addr:street":"Avda Trapiche S / N;Ma\u0301Laga",
    "iso:country":"ES",
    "sg:address":"Avda Trapiche, S/n",
    "sg:city":"Marbella",
    "sg:orig_category":"Instalaci\u00d3n, Reparaci\u00d3n De Ascensores Y Montacargas",
    "sg:phone":"+34 952 77 02 82",
    "sg:postcode":"29600",
    "sg:province":"M\u00e1laga",
    "sg:website":"www.otis.com",
    "wof:name":"Zardoya Otis S. A.",
    "wof:placetype":"venue"
},
  "geometry": {"coordinates":[-4.8898596764,36.5178565979],"type":"Point"}
}