{
  "type": "Feature",
  "properties": {
    "iso:country":"ES",
    "sg:address":"O Salgueiral, S/n",
    "sg:city":"Salgueiral",
    "sg:orig_category":"Maquinaria Para Industrias Diversas",
    "sg:phone":"+34 986 66 14 17",
    "sg:postcode":"36869",
    "sg:province":"Pontevedra",
    "wof:name":"Comercial Laredo C.b.",
    "wof:placetype":"venue"
},
  "geometry": {"coordinates":[-8.5002822876,42.1918334961],"type":"Point"}
}