{
  "type": "Feature",
  "properties": {
    "iso:country":"ES",
    "sg:address":"Rio Jucar(gabatos), 31",
    "sg:city":"Los Dolores",
    "sg:orig_category":"Empresas De Carpinter\u00cda De Madera",
    "sg:phone":"+34 968 51 08 66",
    "sg:postcode":"30310",
    "sg:province":"Murcia",
    "wof:name":"Sanchez Conesa Sebastian",
    "wof:placetype":"venue"
},
  "geometry": {"coordinates":[-1.0081410408,37.6362533569],"type":"Point"}
}