{
  "type": "Feature",
  "properties": {
    "addr:full":"Pla\u00c7 Enric Cristofol Ricart, 23 Vilanova I La Geltru Barcelona 08800",
    "addr:housenumber":"23",
    "addr:postcode":"08800",
    "addr:street":"Cristofol Ricart",
    "iso:country":"ES",
    "sg:address":"Pla\u00c7 Enric Cristofol Ricart, 23",
    "sg:city":"Vilanova I La Geltru",
    "sg:orig_category":"Papeler\u00cdas, Librer\u00cdas",
    "sg:phone":"+34 938 15 31 84",
    "sg:postcode":"08800",
    "sg:province":"Barcelona",
    "wof:name":"Lopez Luque Elena",
    "wof:placetype":"venue"
},
  "geometry": {"coordinates":[1.7240040302,41.221534729],"type":"Point"}
}