{
  "type": "Feature",
  "properties": {
    "iso:country":"ES",
    "sg:address":"Av Sant Jordi, 33",
    "sg:city":"Reus",
    "sg:orig_category":"Farmacias",
    "sg:phone":"+34 977 34 59 37",
    "sg:postcode":"43201",
    "sg:province":"Tarragona",
    "wof:name":"Farmacia Urgelles S.c.p.",
    "wof:placetype":"venue"
},
  "geometry": {"coordinates":[1.1109319925,41.1614837646],"type":"Point"}
}