{
  "type": "Feature",
  "properties": {
    "addr:full":"Calle de Doctor Domingo Gallego, 2 Cabezas S. Juan Sevilla 41730",
    "addr:housenumber":"2",
    "addr:postcode":"41730",
    "addr:street":"Calle De Doctor Domingo Gallego;S.",
    "iso:country":"ES",
    "sg:address":"Calle de Doctor Domingo Gallego, 2",
    "sg:city":"Cabezas S. Juan",
    "sg:orig_category":"Notarios",
    "sg:phone":"+34 955 87 22 57",
    "sg:postcode":"41730",
    "sg:province":"Sevilla",
    "wof:name":"Cortina Mallol Rosa Maria",
    "wof:placetype":"venue"
},
  "geometry": {"coordinates":[-5.9402589798,36.9874687195],"type":"Point"}
}