{
  "type": "Feature",
  "properties": {
    "iso:country":"ES",
    "sg:address":"Barrena Kalea, 6",
    "sg:city":"Eibar",
    "sg:orig_category":"Asesor\u00cda Sobre Comunicaci\u00d3n De Empresas",
    "sg:phone":"+34 943 12 02 50",
    "sg:postcode":"20600",
    "sg:province":"Guip\u00f9zcoa",
    "wof:name":"Carlos Javier Perez Lopez",
    "wof:placetype":"venue"
},
  "geometry": {"coordinates":[-2.459831953,43.1884307861],"type":"Point"}
}