{
  "type": "Feature",
  "properties": {
    "addr:full":"Calle de Gonzalo De Berceo, 21 Logro\u00f1o La Rioja 26005",
    "addr:housenumber":"21",
    "addr:postcode":"26005",
    "addr:street":"Calle De Gonzalo De Berceo;Rioja",
    "iso:country":"ES",
    "sg:address":"Calle de Gonzalo De Berceo, 21",
    "sg:city":"Logro\u00f1o",
    "sg:orig_category":"Electrodom\u00c9sticos (al Por Menor)",
    "sg:phone":"+34 941 25 83 42",
    "sg:postcode":"26005",
    "sg:province":"La Rioja",
    "wof:name":"Borge Velasco Jose Antonio",
    "wof:placetype":"venue"
},
  "geometry": {"coordinates":[-2.4576690197,42.4659729004],"type":"Point"}
}