{
  "type": "Feature",
  "properties": {
    "addr:full":"Calle de Babel, 5 Malaga M\u00e1laga 29006",
    "addr:housenumber":"5",
    "addr:postcode":"29006",
    "addr:street":"Calle De Babel;Ma\u0301Laga",
    "iso:country":"ES",
    "sg:address":"Calle de Babel, 5",
    "sg:city":"Malaga",
    "sg:orig_category":"Agencias De Trabajo Temporal",
    "sg:phone":"+34 952 31 25 95",
    "sg:postcode":"29006",
    "sg:province":"M\u00e1laga",
    "sg:website":"www.flexiplan.es",
    "wof:name":"Flexiplan S.a.",
    "wof:placetype":"venue"
},
  "geometry": {"coordinates":[-4.4380865097,36.7151489258],"type":"Point"}
}