{
  "type": "Feature",
  "properties": {
    "iso:country":"ES",
    "sg:address":"Carrer de Mateu Enric Llado, 34",
    "sg:city":"Palma",
    "sg:orig_category":"Buzones De Correos",
    "sg:phone":"+34 971 71 82 96",
    "sg:postcode":"07002",
    "sg:province":"Islas Baleares",
    "wof:name":"Coll Pons Antonio",
    "wof:placetype":"venue"
},
  "geometry": {"coordinates":[2.655944109,39.5681991577],"type":"Point"}
}