{
  "type": "Feature",
  "properties": {
    "iso:country":"ES",
    "sg:address":"Calle de Isla De Salvora, 6",
    "sg:city":"Estacion",
    "sg:orig_category":"Alimentaci\u00d3n General (al Por Menor)",
    "sg:phone":"+34 918 50 77 50",
    "sg:postcode":"28400",
    "sg:province":"Madrid",
    "wof:name":"Zhang  Shixin",
    "wof:placetype":"venue"
},
  "geometry": {"coordinates":[-4.0122599602,40.6183509827],"type":"Point"}
}