{
  "type": "Feature",
  "properties": {
    "iso:country":"ES",
    "sg:address":"Zirkuitu Ibilbidea - Camino Del Circuito, 2",
    "sg:city":"Oztaran",
    "sg:orig_category":"Ingeniero",
    "sg:phone":"+34 943 37 13 52",
    "sg:postcode":"20160",
    "sg:province":"Guip\u00f9zcoa",
    "wof:name":"Einco S.a.",
    "wof:placetype":"venue"
},
  "geometry": {"coordinates":[-2.020414114,43.2698173523],"type":"Point"}
}