{
  "type": "Feature",
  "properties": {
    "addr:full":"Carrer de Llavador, 4 Pego Alicante 03780",
    "addr:housenumber":"4",
    "addr:postcode":"03780",
    "addr:street":"Carrer De Llavador",
    "iso:country":"ES",
    "sg:address":"Carrer de Llavador, 4",
    "sg:city":"Pego",
    "sg:orig_category":"Muebles, Minoristas",
    "sg:phone":"+34 965 57 09 33",
    "sg:postcode":"03780",
    "sg:province":"Alicante",
    "wof:name":"Alemany Vicens Daniel",
    "wof:placetype":"venue"
},
  "geometry": {"coordinates":[-0.1192717031,38.8415489197],"type":"Point"}
}