{
  "type": "Feature",
  "properties": {
    "iso:country":"ES",
    "sg:address":"Calle de Brasa, 4",
    "sg:city":"Zamora",
    "sg:orig_category":"Bisuter\u00cda, Joyer\u00cda, Relojer\u00cda (al Por Menor)",
    "sg:phone":"+34 980 53 29 74",
    "sg:postcode":"49003",
    "sg:province":"Zamora",
    "wof:name":"Garcia Sacristan Manuel",
    "wof:placetype":"venue"
},
  "geometry": {"coordinates":[-5.7427196503,41.5052947998],"type":"Point"}
}