{
  "type": "Feature",
  "properties": {
    "iso:country":"ES",
    "sg:address":"Calle de Cisne, 18",
    "sg:city":"Granada",
    "sg:orig_category":"Mec\u00c1nico Del Autom\u00d3vil",
    "sg:phone":"+34 958 20 36 13",
    "sg:postcode":"18014",
    "sg:province":"Granada",
    "wof:name":"Gomez Molina Jose",
    "wof:placetype":"venue"
},
  "geometry": {"coordinates":[-3.6105589867,37.1851234436],"type":"Point"}
}