{
  "type": "Feature",
  "properties": {
    "addr:full":"Avda Galicia De, 29 Oviedo Asturias 33005",
    "addr:housenumber":"29",
    "addr:postcode":"33005",
    "addr:street":"Avda Galicia De",
    "iso:country":"ES",
    "sg:address":"Avda Galicia De, 29",
    "sg:city":"Oviedo",
    "sg:orig_category":"Caf\u00c9s, Bares, Cervecer\u00cdas",
    "sg:phone":"+34 985 23 10 74",
    "sg:postcode":"33005",
    "sg:province":"Asturias",
    "wof:name":"Sistelcom-telemensaje S.a.",
    "wof:placetype":"venue"
},
  "geometry": {"coordinates":[-5.8605399132,43.3604240417],"type":"Point"}
}