{
  "type": "Feature",
  "properties": {
    "addr:full":"Calle de Amorebieta, 6 S. Vicente Sonsierra La Rioja 26338",
    "addr:housenumber":"6",
    "addr:postcode":"26338",
    "addr:street":"Calle De Amorebieta;S. Vicente Sonsierra;Rioja",
    "iso:country":"ES",
    "sg:address":"Calle de Amorebieta, 6",
    "sg:city":"S. Vicente Sonsierra",
    "sg:orig_category":"Bebidas",
    "sg:phone":"+34 941 33 42 28",
    "sg:postcode":"26338",
    "sg:province":"La Rioja",
    "wof:name":"Vinos De Benjamin Romeo S.l",
    "wof:placetype":"venue"
},
  "geometry": {"coordinates":[-2.7606709003,42.5640525818],"type":"Point"}
}