{
  "type": "Feature",
  "properties": {
    "iso:country":"ES",
    "sg:address":"Jaume Carner, 30",
    "sg:city":"El Vendrell",
    "sg:orig_category":"Mec\u00c1nico Del Autom\u00d3vil",
    "sg:phone":"+34 977 66 01 57",
    "sg:postcode":"43700",
    "sg:province":"Tarragona",
    "wof:name":"Morgades Vidal Jaime",
    "wof:placetype":"venue"
},
  "geometry": {"coordinates":[1.5367679596,41.2190284729],"type":"Point"}
}