{
  "type": "Feature",
  "properties": {
    "addr:full":"Carr Mas Palau, S/n Vilanova I La Geltru Barcelona 08800",
    "addr:housenumber":"s / n",
    "addr:postcode":"08800",
    "addr:street":"Carr Mas Palau",
    "iso:country":"ES",
    "sg:address":"Carr Mas Palau, S/n",
    "sg:city":"Vilanova I La Geltru",
    "sg:orig_category":"Producci\u00d3n, Venta De Productos De Agricultura Biol\u00d3gica",
    "sg:phone":"+34 938 15 52 28",
    "sg:postcode":"08800",
    "sg:province":"Barcelona",
    "wof:name":"Anguela Rosell Juan",
    "wof:placetype":"venue"
},
  "geometry": {"coordinates":[1.6934887171,41.225605011],"type":"Point"}
}