{
  "type": "Feature",
  "properties": {
    "iso:country":"ES",
    "sg:address":"Rua Republica Arxentina (da), 9",
    "sg:city":"Santiago De Compostela",
    "sg:orig_category":"Ropa Para Ni\u00d1os (al Por Menor)",
    "sg:phone":"+34 981 59 29 96",
    "sg:postcode":"15701",
    "sg:province":"La Coru\u00f1a",
    "wof:name":"Garcia Cambon Alvaro",
    "wof:placetype":"venue"
},
  "geometry": {"coordinates":[-8.5467777252,42.8730621338],"type":"Point"}
}