{
  "type": "Feature",
  "properties": {
    "addr:full":"Calle de San Bernardo, 97 Madrid Madrid 28015",
    "addr:housenumber":"97",
    "addr:postcode":"madrid;28015",
    "addr:street":"Calle De San Bernardo",
    "iso:country":"ES",
    "sg:address":"Calle de San Bernardo, 97",
    "sg:city":"Madrid",
    "sg:orig_category":"Alumbrados",
    "sg:phone":"+34 914 46 39 78",
    "sg:postcode":"28015",
    "sg:province":"Madrid",
    "wof:name":"Ayuso De Dios Nicolas",
    "wof:placetype":"venue"
},
  "geometry": {"coordinates":[-3.7055151463,40.4304351807],"type":"Point"}
}