{
  "type": "Feature",
  "properties": {
    "addr:full":"Carrer de Cardenal Vives I Tuto, 46 Barcelona Barcelona 08034",
    "addr:housenumber":"46",
    "addr:postcode":"08034",
    "addr:street":"Carrer De Cardenal Vives;Tuto",
    "iso:country":"ES",
    "sg:address":"Carrer de Cardenal Vives I Tuto, 46",
    "sg:city":"Barcelona",
    "sg:orig_category":"M\u00c9dicos: Medicina General",
    "sg:phone":"+34 932 03 37 72",
    "sg:postcode":"08034",
    "sg:province":"Barcelona",
    "wof:name":"Sastre Vilarrasa Genoveva",
    "wof:placetype":"venue"
},
  "geometry": {"coordinates":[2.1224899292,41.3949775696],"type":"Point"}
}