{
  "type": "Feature",
  "properties": {
    "iso:country":"ES",
    "sg:address":"Bard Majaneque, 1",
    "sg:city":"Majaneque",
    "sg:orig_category":"Tapiceros Y Tapiceros",
    "sg:phone":"+34 957 32 82 06",
    "sg:postcode":"14193",
    "sg:province":"C\u00f3rdoba",
    "wof:name":"Montalban Plaza Juan",
    "wof:placetype":"venue"
},
  "geometry": {"coordinates":[-4.8512039185,37.8670501709],"type":"Point"}
}