{
  "type": "Feature",
  "properties": {
    "iso:country":"ES",
    "sg:address":"Diseminados, S/n",
    "sg:city":"Gomezserracin",
    "sg:orig_category":"Centros De Educaci\u00d3n Especial",
    "sg:phone":"+34 921 16 82 50",
    "sg:postcode":"40240",
    "sg:province":"Segovia",
    "wof:name":"Colegio Rural Agrupado El Carracillo",
    "wof:placetype":"venue"
},
  "geometry": {"coordinates":[-4.3238329887,41.2902030945],"type":"Point"}
}