{
  "type": "Feature",
  "properties": {
    "addr:full":"Polig. Cantorral, S/n Cuenca Cuenca 16004",
    "addr:housenumber":"s / n",
    "addr:postcode":"16004",
    "addr:street":"Polig. Cantorral",
    "iso:country":"ES",
    "sg:address":"Polig. Cantorral, S/n",
    "sg:city":"Cuenca",
    "sg:orig_category":"Contenedores (mercanc\u00cdas)",
    "sg:phone":"+34 969 22 97 75",
    "sg:postcode":"16004",
    "sg:province":"Cuenca",
    "wof:name":"Verdu Garcia Luis",
    "wof:placetype":"venue"
},
  "geometry": {"coordinates":[-2.1262440681,40.0541381836],"type":"Point"}
}