{
  "type": "Feature",
  "properties": {
    "iso:country":"ES",
    "sg:address":"Carrer de Independencia, 321",
    "sg:city":"Barcelona",
    "sg:orig_category":"Institutos De Belleza",
    "sg:phone":"+34 934 56 88 14",
    "sg:postcode":"08026",
    "sg:province":"Barcelona",
    "wof:name":"Ramos Ingelmo Maria Teresa",
    "wof:placetype":"venue"
},
  "geometry": {"coordinates":[2.1812469959,41.4092330933],"type":"Point"}
}