{
  "type": "Feature",
  "properties": {
    "iso:country":"ES",
    "sg:address":"Calle de Guzman El Bueno, 22",
    "sg:city":"Madrid",
    "sg:orig_category":"Cajas De Ahorro",
    "sg:phone":"+34 914 55 04 02",
    "sg:postcode":"28015",
    "sg:province":"Madrid",
    "sg:website":"www.caixadelpenedes.com",
    "wof:name":"Caixa D'estalvis Del Penedes",
    "wof:placetype":"venue"
},
  "geometry": {"coordinates":[-3.7132089138,40.4326858521],"type":"Point"}
}