{
  "type": "Feature",
  "properties": {
    "addr:full":"Calle de Ramon Y Cajal, 45 Ossa Montiel Albacete 02611",
    "addr:housenumber":"45",
    "addr:postcode":"02611",
    "addr:street":"Calle De Ramon Y Cajal;Montiel",
    "iso:country":"ES",
    "sg:address":"Calle de Ramon Y Cajal, 45",
    "sg:city":"Ossa Montiel",
    "sg:orig_category":"Perfumer\u00cda: Materias Primas Y Esencias",
    "sg:phone":"+34 967 37 71 31",
    "sg:postcode":"02611",
    "sg:province":"Albacete",
    "wof:name":"Nieto Gomez Basilio",
    "wof:placetype":"venue"
},
  "geometry": {"coordinates":[-2.7425370216,38.9654579163],"type":"Point"}
}