{
  "type": "Feature",
  "properties": {
    "iso:country":"ES",
    "sg:address":"Rua Xoan Montes, 3",
    "sg:city":"Lugo",
    "sg:orig_category":"Asesor\u00cda Sobre Comunicaci\u00d3n De Empresas",
    "sg:phone":"+34 982 28 41 31",
    "sg:postcode":"27001",
    "sg:province":"Lugo",
    "wof:name":"Oficina Contable Tributaria S.l.",
    "wof:placetype":"venue"
},
  "geometry": {"coordinates":[-7.555685997,43.0110282898],"type":"Point"}
}