{
  "type": "Feature",
  "properties": {
    "addr:full":"Calle de Basilon, 15 Quintanilla Onesimo Valladolid 47350",
    "addr:housenumber":"15",
    "addr:postcode":"47350",
    "addr:street":"Calle De Basilon",
    "iso:country":"ES",
    "sg:address":"Calle de Basilon, 15",
    "sg:city":"Quintanilla Onesimo",
    "sg:orig_category":"Productores Recolectores, Venta Directa De Vinos",
    "sg:phone":"+34 983 68 00 15",
    "sg:postcode":"47350",
    "sg:province":"Valladolid",
    "wof:name":"Vi\u00f1edos Y Bodegas Ribon S.l.",
    "wof:placetype":"venue"
},
  "geometry": {"coordinates":[-4.3630409241,41.6251564026],"type":"Point"}
}