{
  "type": "Feature",
  "properties": {
    "addr:full":"Calle de Constitucion, 1 Palacios Y Villafranca Sevilla 41720",
    "addr:housenumber":"1",
    "addr:postcode":"41720",
    "addr:street":"Calle De Constitucion",
    "iso:country":"ES",
    "sg:address":"Calle de Constitucion, 1",
    "sg:city":"Palacios Y Villafranca",
    "sg:orig_category":"Cr\u00cda De Animales",
    "sg:phone":"+34 955 81 49 79",
    "sg:postcode":"41720",
    "sg:province":"Sevilla",
    "wof:name":"Clavijo Castro Antonio",
    "wof:placetype":"venue"
},
  "geometry": {"coordinates":[-5.9237451553,37.1656799316],"type":"Point"}
}