{
  "type": "Feature",
  "properties": {
    "addr:full":"Calle de Gran Via De San Marcos, 30 Le\u00f3n Le\u00f3n 24002",
    "addr:housenumber":"30",
    "addr:postcode":"24002",
    "addr:street":"Calle De Gran Via De San Marcos;Leo\u0301N",
    "iso:country":"ES",
    "sg:address":"Calle de Gran Via De San Marcos, 30",
    "sg:city":"Le\u00f3n",
    "sg:orig_category":"Art\u00cdculos De Decoraci\u00d3n",
    "sg:phone":"+34 987 08 26 41",
    "sg:postcode":"24002",
    "sg:province":"Le\u00f3n",
    "wof:name":"Leyendas Del Sur S.l.i.",
    "wof:placetype":"venue"
},
  "geometry": {"coordinates":[-5.5787553787,42.6005210876],"type":"Point"}
}