{
  "type": "Feature",
  "properties": {
    "addr:full":"Calle de Badajoz, 1 San Pedro Alcantara M\u00e1laga 29670",
    "addr:housenumber":"1",
    "addr:postcode":"29670",
    "addr:street":"Calle De Badajoz",
    "iso:country":"ES",
    "sg:address":"Calle de Badajoz, 1",
    "sg:city":"San Pedro Alcantara",
    "sg:orig_category":"Promotores Constructores",
    "sg:phone":"+34 952 78 78 59",
    "sg:postcode":"29670",
    "sg:province":"M\u00e1laga",
    "wof:name":"A.t.e. Consulting Financiero Inmobiliario S.l.",
    "wof:placetype":"venue"
},
  "geometry": {"coordinates":[-4.99066782,36.4851150513],"type":"Point"}
}