{
  "type": "Feature",
  "properties": {
    "iso:country":"ES",
    "sg:address":"Calle de Santo Reino, 4",
    "sg:city":"Jaen",
    "sg:orig_category":"M\u00c9dicos: Salud P\u00dablica",
    "sg:phone":"+34 953 27 15 92",
    "sg:postcode":"23001",
    "sg:province":"Ja\u00e9n",
    "wof:name":"Francisco Jose Lopez Mu\u00f1oz Y Dos Mas C.b.",
    "wof:placetype":"venue"
},
  "geometry": {"coordinates":[-3.7880289555,37.7716560364],"type":"Point"}
}