{
  "type": "Feature",
  "properties": {
    "iso:country":"ES",
    "sg:address":"Bloc Miramar-i, 6",
    "sg:city":"Sant Pere I Sant Pau",
    "sg:orig_category":"Asesor\u00cdas En Comunicaci\u00d3n",
    "sg:phone":"+34 977 20 40 26",
    "sg:postcode":"43007",
    "sg:province":"Tarragona",
    "wof:name":"Gestion Cuatro Estudios S.l.",
    "wof:placetype":"venue"
},
  "geometry": {"coordinates":[1.2959779501,41.1377334595],"type":"Point"}
}