{
  "type": "Feature",
  "properties": {
    "addr:full":"Calle de Isla De Alboran, 15 Pozuelo De Alarcon Madrid 28223",
    "addr:housenumber":"15",
    "addr:postcode":"28223",
    "addr:street":"Calle De Isla De Alboran",
    "iso:country":"ES",
    "sg:address":"Calle de Isla De Alboran, 15",
    "sg:city":"Pozuelo De Alarcon",
    "sg:orig_category":"Inmobiliaria (agencias)",
    "sg:phone":"+34 913 51 23 60",
    "sg:postcode":"28223",
    "sg:province":"Madrid",
    "wof:name":"Sociedad Gestora Alboran S.l.",
    "wof:placetype":"venue"
},
  "geometry": {"coordinates":[-3.8173060417,40.4431648254],"type":"Point"}
}