{
  "type": "Feature",
  "properties": {
    "addr:full":"Av Generalitat, 58 Deltebre Tarragona 43580",
    "addr:housenumber":"58",
    "addr:postcode":"43580",
    "addr:street":"Av Generalitat",
    "iso:country":"ES",
    "sg:address":"Av Generalitat, 58",
    "sg:city":"Deltebre",
    "sg:orig_category":"Empresas De Carpinter\u00cda De Madera",
    "sg:phone":"+34 977 48 75 34",
    "sg:postcode":"43580",
    "sg:province":"Tarragona",
    "wof:name":"Marin Castells Carlos",
    "wof:placetype":"venue"
},
  "geometry": {"coordinates":[0.7266560197,40.7177581787],"type":"Point"}
}