{
  "type": "Feature",
  "properties": {
    "addr:full":"Calle de Fika, 9 Bilbao Vizcaya 48006",
    "addr:housenumber":"9",
    "addr:postcode":"48006",
    "addr:street":"Calle De Fika",
    "iso:country":"ES",
    "sg:address":"Calle de Fika, 9",
    "sg:city":"Bilbao",
    "sg:orig_category":"Peluqueros: De Se\u00d1oras",
    "sg:phone":"+34 944 33 56 19",
    "sg:postcode":"48006",
    "sg:province":"Vizcaya",
    "wof:name":"Cosgaya Gutierrez Maria Rosario",
    "wof:placetype":"venue"
},
  "geometry": {"coordinates":[-2.9186959267,43.2573204041],"type":"Point"}
}