{
  "type": "Feature",
  "properties": {
    "iso:country":"ES",
    "sg:address":"Calle de Eras, 4",
    "sg:city":"Blascomillan",
    "sg:orig_category":"Ense\u00d1anza, Formaci\u00d3n Profesional: Aprendizaje",
    "sg:phone":"+34 923 56 31 78",
    "sg:postcode":"05146",
    "sg:province":"\u00c1vila",
    "wof:name":"Ayuntamiento De Blascomillan",
    "wof:placetype":"venue"
},
  "geometry": {"coordinates":[-5.0883097649,40.7997894287],"type":"Point"}
}