{
  "type": "Feature",
  "properties": {
    "iso:country":"ES",
    "sg:address":"Calle de Rambla De La Mancha, 31",
    "sg:city":"Almansa",
    "sg:orig_category":"Centros Empresariales",
    "sg:phone":"+34 967 31 07 32",
    "sg:postcode":"02640",
    "sg:province":"Albacete",
    "wof:name":"Papeleria Ramblas C.b.",
    "wof:placetype":"venue"
},
  "geometry": {"coordinates":[-1.0954389572,38.8619995117],"type":"Point"}
}