{
  "type": "Feature",
  "properties": {
    "addr:full":"Calle de Calvo Sotelo, 36 Lanciego Lantziego \u00c1lava 01308",
    "addr:housenumber":"36",
    "addr:postcode":"01308",
    "addr:street":"Calle De Calvo Sotelo",
    "iso:country":"ES",
    "sg:address":"Calle de Calvo Sotelo, 36",
    "sg:city":"Lanciego Lantziego",
    "sg:orig_category":"Productores Recolectores, Venta Directa De Vinos",
    "sg:phone":"+34 945 60 81 27",
    "sg:postcode":"01308",
    "sg:province":"\u00c1lava",
    "wof:name":"Bodegas Garcia Crespo S.c.",
    "wof:placetype":"venue"
},
  "geometry": {"coordinates":[-2.5110290051,42.5624504089],"type":"Point"}
}