{
  "type": "Feature",
  "properties": {
    "iso:country":"ES",
    "sg:address":"Karmen Kalea, 4",
    "sg:city":"Eibar",
    "sg:orig_category":"Peluqueros: De Se\u00d1oras",
    "sg:phone":"+34 943 12 02 18",
    "sg:postcode":"20600",
    "sg:province":"Guip\u00f9zcoa",
    "wof:name":"Mari Angeles Perez Y Nieves Perosanz C.b.",
    "wof:placetype":"venue"
},
  "geometry": {"coordinates":[-2.4604730606,43.1879997253],"type":"Point"}
}