{
  "type": "Feature",
  "properties": {
    "iso:country":"ES",
    "sg:address":"Ctra Estacion, 1",
    "sg:city":"Villalon Campos",
    "sg:orig_category":"Autob\u00das (explotaci\u00d3n Y Servicios De)",
    "sg:phone":"+34 983 76 10 79",
    "sg:postcode":"47600",
    "sg:province":"Valladolid",
    "wof:name":"Ayuntamiento De Villalon De Campos",
    "wof:placetype":"venue"
},
  "geometry": {"coordinates":[-5.0365691185,42.0953712463],"type":"Point"}
}