{
  "type": "Feature",
  "properties": {
    "addr:full":"Calle de Benavente, 18 Quiruelas Vidriales Zamora 49622",
    "addr:housenumber":"18",
    "addr:postcode":"49622",
    "addr:street":"Calle De Benavente;Zamora",
    "iso:country":"ES",
    "sg:address":"Calle de Benavente, 18",
    "sg:city":"Quiruelas Vidriales",
    "sg:orig_category":"Farmacias",
    "sg:phone":"+34 980 64 30 87",
    "sg:postcode":"49622",
    "sg:province":"Zamora",
    "wof:name":"Valderrey Villalibre Maria Teresa",
    "wof:placetype":"venue"
},
  "geometry": {"coordinates":[-5.8254880905,42.0193061829],"type":"Point"}
}