{
  "type": "Feature",
  "properties": {
    "iso:country":"ES",
    "sg:address":"Carrer de Joan Maragall, 38",
    "sg:city":"Cornella Llobregat",
    "sg:orig_category":"Molduras, Junquillos, Listones Y Molduras Perforadas",
    "sg:phone":"+34 933 77 19 64",
    "sg:postcode":"08940",
    "sg:province":"Barcelona",
    "wof:name":"Rodriguez Gonzalez Enrique",
    "wof:placetype":"venue"
},
  "geometry": {"coordinates":[2.0708489418,41.3572616577],"type":"Point"}
}