{
  "type": "Feature",
  "properties": {
    "addr:full":"Isaac Peral, 7 Valdemoro Madrid 28340",
    "addr:housenumber":"7",
    "addr:postcode":"28340",
    "addr:street":"Isaac Peral",
    "iso:country":"ES",
    "sg:address":"Isaac Peral, 7",
    "sg:city":"Valdemoro",
    "sg:orig_category":"Empresas De Carpinter\u00cda",
    "sg:phone":"+34 918 08 53 72",
    "sg:postcode":"28340",
    "sg:province":"Madrid",
    "wof:name":"Aluper C.b.",
    "wof:placetype":"venue"
},
  "geometry": {"coordinates":[-3.6666436195,40.1626472473],"type":"Point"}
}