{
  "type": "Feature",
  "properties": {
    "iso:country":"ES",
    "sg:address":"Calle de Manuel De Falla (de), 48",
    "sg:city":"Alcobendas",
    "sg:orig_category":"Caf\u00c9s, Bares, Cervecer\u00cdas",
    "sg:phone":"+34 916 53 75 97",
    "sg:postcode":"28100",
    "sg:province":"Madrid",
    "wof:name":"Lazaro Garcia Antonio",
    "wof:placetype":"venue"
},
  "geometry": {"coordinates":[-3.6436131001,40.5520782471],"type":"Point"}
}