{
  "type": "Feature",
  "properties": {
    "addr:full":"Trva Santa Catalina, 1 Avila \u00c1vila 05001",
    "addr:housenumber":"1",
    "addr:postcode":"05001",
    "addr:street":"Trva Santa Catalina;A\u0301Vila",
    "iso:country":"ES",
    "sg:address":"Trva Santa Catalina, 1",
    "sg:city":"Avila",
    "sg:orig_category":"M\u00c9dicos: Anatom\u00cda Patol\u00d3gica Y Citolog\u00cda",
    "sg:phone":"+34 920 22 14 32",
    "sg:postcode":"05001",
    "sg:province":"\u00c1vila",
    "wof:name":"Cerme\u00f1o De Giles Faustino Arturo",
    "wof:placetype":"venue"
},
  "geometry": {"coordinates":[-4.6947040558,40.656375885],"type":"Point"}
}