{
  "type": "Feature",
  "properties": {
    "iso:country":"ES",
    "sg:address":"Calle de Mayor, 47",
    "sg:city":"Zaragoza",
    "sg:orig_category":"Caf\u00c9s, Bares, Cervecer\u00cdas",
    "sg:phone":"+34 976 39 09 35",
    "sg:postcode":"50001",
    "sg:province":"Zaragoza",
    "wof:name":"Tercerol S.l",
    "wof:placetype":"venue"
},
  "geometry": {"coordinates":[-0.875352025,41.6530609131],"type":"Point"}
}