{
  "type": "Feature",
  "properties": {
    "addr:full":"Av Diagonal, 490 Barcelona Barcelona 08006",
    "addr:housenumber":"490",
    "addr:postcode":"08006",
    "addr:street":"Av Diagonal",
    "iso:country":"ES",
    "sg:address":"Av Diagonal, 490",
    "sg:city":"Barcelona",
    "sg:orig_category":"Laboratorios Farmac\u00c9uticos",
    "sg:phone":"+34 934 15 48 22",
    "sg:postcode":"08006",
    "sg:province":"Barcelona",
    "wof:name":"Bama-geve S.l.",
    "wof:placetype":"venue"
},
  "geometry": {"coordinates":[2.1550540924,41.3957366943],"type":"Point"}
}