{
  "type": "Feature",
  "properties": {
    "addr:full":"Carrer de Sitges, 85 S. Pere Ribes Barcelona 08810",
    "addr:housenumber":"85",
    "addr:postcode":"08810",
    "addr:street":"Carrer De Sitges;S. Pere Ribes Barcelona",
    "iso:country":"ES",
    "sg:address":"Carrer de Sitges, 85",
    "sg:city":"S. Pere Ribes",
    "sg:orig_category":"Herboristas (al Por Menor)",
    "sg:phone":"+34 938 96 11 03",
    "sg:postcode":"08810",
    "sg:province":"Barcelona",
    "wof:name":"Satnam S.c.p.",
    "wof:placetype":"venue"
},
  "geometry": {"coordinates":[1.7765699625,41.2583999634],"type":"Point"}
}