{
  "type": "Feature",
  "properties": {
    "iso:country":"ES",
    "sg:address":"Calle de Luis Rosales, 4",
    "sg:city":"Alcala Henares",
    "sg:orig_category":"Prot\u00c9sicos Dentales",
    "sg:phone":"+34 918 78 43 48",
    "sg:postcode":"28806",
    "sg:province":"Madrid",
    "wof:name":"Martin-cid Gutierrez Cristina",
    "wof:placetype":"venue"
},
  "geometry": {"coordinates":[-3.3770189285,40.4949035645],"type":"Point"}
}