{
  "type": "Feature",
  "properties": {
    "iso:country":"ES",
    "sg:address":"Calle de Huertos (los), S/n",
    "sg:city":"Herencia",
    "sg:orig_category":"Producci\u00d3n De Huevos",
    "sg:phone":"+34 926 57 14 32",
    "sg:postcode":"13640",
    "sg:province":"Ciudad Real",
    "wof:name":"Canales Porras S.l.",
    "wof:placetype":"venue"
},
  "geometry": {"coordinates":[-3.3516089916,39.3683052063],"type":"Point"}
}