{
  "type": "Feature",
  "properties": {
    "addr:full":"Calle de Recogidas, 12 Granada Granada 18002",
    "addr:housenumber":"12",
    "addr:postcode":"18002",
    "addr:street":"Calle De Recogidas",
    "iso:country":"ES",
    "sg:address":"Calle de Recogidas, 12",
    "sg:city":"Granada",
    "sg:orig_category":"Asesor\u00cda De Formaci\u00d3n Y Gesti\u00d3n De Personal",
    "sg:phone":"+34 958 53 60 87",
    "sg:postcode":"18002",
    "sg:province":"Granada",
    "sg:website":"www.asesoriampm.com",
    "wof:name":"Miguel Angel Perez Merida S.l.",
    "wof:placetype":"venue"
},
  "geometry": {"coordinates":[-3.6011459827,37.1729011536],"type":"Point"}
}