{
  "type": "Feature",
  "properties": {
    "addr:full":"Calle de Navarra, 1 Calahorra La Rioja 26500",
    "addr:housenumber":"1",
    "addr:postcode":"26500",
    "addr:street":"Calle De Navarra",
    "iso:country":"ES",
    "sg:address":"Calle de Navarra, 1",
    "sg:city":"Calahorra",
    "sg:orig_category":"Cristaler\u00cdas",
    "sg:phone":"+34 941 13 29 40",
    "sg:postcode":"26500",
    "sg:province":"La Rioja",
    "wof:name":"Martinez Martinez Jose",
    "wof:placetype":"venue"
},
  "geometry": {"coordinates":[-1.9722579718,42.3082542419],"type":"Point"}
}