{
  "type": "Feature",
  "properties": {
    "iso:country":"ES",
    "sg:address":"Avda Eduardo Dato, 55",
    "sg:city":"Sevilla",
    "sg:orig_category":"Abogados",
    "sg:phone":"+34 954 53 04 62",
    "sg:postcode":"41018",
    "sg:province":"Sevilla",
    "wof:name":"Romero Y Forero Abogadas Sc",
    "wof:placetype":"venue"
},
  "geometry": {"coordinates":[-5.9742598534,37.383228302],"type":"Point"}
}