{
  "type": "Feature",
  "properties": {
    "addr:full":"Calle de Hipocrates, 17 Goro Las Palmas 35215",
    "addr:housenumber":"17",
    "addr:postcode":"35215",
    "addr:street":"Calle De Hipocrates",
    "iso:country":"ES",
    "sg:address":"Calle de Hipocrates, 17",
    "sg:city":"Goro",
    "sg:orig_category":"Supermercados Y Hipermercados",
    "sg:phone":"+34 928 57 47 61",
    "sg:postcode":"35215",
    "sg:province":"Las Palmas",
    "wof:name":"Martel Martel Adelina",
    "wof:placetype":"venue"
},
  "geometry": {"coordinates":[-15.398223877,27.9939899445],"type":"Point"}
}