{
  "type": "Feature",
  "properties": {
    "iso:country":"ES",
    "sg:address":"Cami Llor, 13",
    "sg:city":"S. Boi Llobregat",
    "sg:orig_category":"Inmobiliaria (agencias)",
    "sg:phone":"+34 936 40 06 14",
    "sg:postcode":"08830",
    "sg:province":"Barcelona",
    "wof:name":"Port Marinas 2004.s.l",
    "wof:placetype":"venue"
},
  "geometry": {"coordinates":[2.0229399204,41.355556488],"type":"Point"}
}