{
  "type": "Feature",
  "properties": {
    "iso:country":"ES",
    "sg:address":"Calle de Real, 141",
    "sg:city":"Yuncos",
    "sg:orig_category":"Empresarios",
    "sg:phone":"+34 925 55 33 30",
    "sg:postcode":"45210",
    "sg:province":"Toledo",
    "wof:name":"Huloma S.a.",
    "wof:placetype":"venue"
},
  "geometry": {"coordinates":[-3.8733189106,40.0875511169],"type":"Point"}
}