{
  "type": "Feature",
  "properties": {
    "addr:full":"Calle de Puenteareas, 13 Madrid Madrid 28002",
    "addr:housenumber":"13",
    "addr:postcode":"madrid;28002",
    "addr:street":"Calle De Puenteareas",
    "iso:country":"ES",
    "sg:address":"Calle de Puenteareas, 13",
    "sg:city":"Madrid",
    "sg:orig_category":"Mensajer\u00cda Express, Portes Internacionales",
    "sg:phone":"+34 914 15 87 75",
    "sg:postcode":"28002",
    "sg:province":"Madrid",
    "sg:website":"www.interpuertos.com",
    "wof:name":"Interpuertos Express S.l.",
    "wof:placetype":"venue"
},
  "geometry": {"coordinates":[-3.6697258949,40.44348526],"type":"Point"}
}