{
  "type": "Feature",
  "properties": {
    "addr:full":"Calle de San Quirce, 11 Valladolid Valladolid 47003",
    "addr:housenumber":"11",
    "addr:postcode":"47003",
    "addr:street":"Calle De San Quirce",
    "iso:country":"ES",
    "sg:address":"Calle de San Quirce, 11",
    "sg:city":"Valladolid",
    "sg:orig_category":"Alquiler De Veh\u00cdculos: Turismos Y Utilitarios",
    "sg:phone":"+34 983 35 83 83",
    "sg:postcode":"47003",
    "sg:province":"Valladolid",
    "wof:name":"Valbuena Salan Jose Benito",
    "wof:placetype":"venue"
},
  "geometry": {"coordinates":[-4.7287969589,41.6568908691],"type":"Point"}
}