{
  "type": "Feature",
  "properties": {
    "iso:country":"ES",
    "sg:address":"Calle de Cefiro, S/n",
    "sg:city":"Sevilla",
    "sg:orig_category":"Aparcamientos (infraestructuras, Accesorios)",
    "sg:phone":"+34 954 57 56 35",
    "sg:postcode":"41018",
    "sg:province":"Sevilla",
    "wof:name":"Las Canteruelas S.l.",
    "wof:placetype":"venue"
},
  "geometry": {"coordinates":[-5.9748744965,37.3882827759],"type":"Point"}
}