{
  "type": "Feature",
  "properties": {
    "iso:country":"ES",
    "sg:address":"Av Robert Graupera, 210",
    "sg:city":"Deltebre",
    "sg:orig_category":"Pescader\u00cdas (al Por Menor)",
    "sg:phone":"+34 977 48 95 80",
    "sg:postcode":"43580",
    "sg:province":"Tarragona",
    "wof:name":"Agripesca Maria Jesus S.l.",
    "wof:placetype":"venue"
},
  "geometry": {"coordinates":[0.715893805,40.7190513611],"type":"Point"}
}