{
  "type": "Feature",
  "properties": {
    "addr:full":"Calle de Doctor Eduardo Garcia-trivi\u00d1o Lopez, 1 Jaen Ja\u00e9n 23007",
    "addr:housenumber":"1;jae\u0301n",
    "addr:postcode":"23007",
    "addr:street":"Calle De Doctor Eduardo Garcia-Trivin\u0303O Lopez",
    "iso:country":"ES",
    "sg:address":"Calle de Doctor Eduardo Garcia-trivi\u00d1o Lopez, 1",
    "sg:city":"Jaen",
    "sg:orig_category":"Grafistas",
    "sg:phone":"+34 953 26 61 94",
    "sg:postcode":"23007",
    "sg:province":"Ja\u00e9n",
    "wof:name":"Lopez Simon Susana",
    "wof:placetype":"venue"
},
  "geometry": {"coordinates":[-3.7885758877,37.7796630859],"type":"Point"}
}