{
  "type": "Feature",
  "properties": {
    "iso:country":"ES",
    "sg:address":"Plaz Puerta De Alarcos, 4",
    "sg:city":"Ciudad Real",
    "sg:orig_category":"Asesor\u00cda Fiscal Y Jur\u00cddica",
    "sg:phone":"+34 926 21 56 52",
    "sg:postcode":"13002",
    "sg:province":"Ciudad Real",
    "wof:name":"Segura Bravo Jose Juan",
    "wof:placetype":"venue"
},
  "geometry": {"coordinates":[-3.9374189377,38.981426239],"type":"Point"}
}