{
  "type": "Feature",
  "properties": {
    "addr:full":"Carr Vint-i-cinc D'abril, 72 Olleria Valencia 46850",
    "addr:housenumber":"72",
    "addr:postcode":"46850",
    "addr:street":"Carr Vint-I-Cinc D'Abril",
    "iso:country":"ES",
    "sg:address":"Carr Vint-i-cinc D'abril, 72",
    "sg:city":"Olleria",
    "sg:orig_category":"Electricidad: Instaladores",
    "sg:phone":"+34 962 20 04 15",
    "sg:postcode":"46850",
    "sg:province":"Valencia",
    "wof:name":"Montages Electricos Climent S.l.",
    "wof:placetype":"venue"
},
  "geometry": {"coordinates":[-0.554148972,38.9132995605],"type":"Point"}
}