{
  "type": "Feature",
  "properties": {
    "addr:full":"Calle de Costanillas, 38 Cordoba C\u00f3rdoba 14001",
    "addr:housenumber":"38",
    "addr:postcode":"14001",
    "addr:street":"Calle De Costanillas;Co\u0301Rdoba",
    "iso:country":"ES",
    "sg:address":"Calle de Costanillas, 38",
    "sg:city":"Cordoba",
    "sg:orig_category":"Bisuter\u00cda, Joyer\u00cda, Relojer\u00cda (al Por Menor)",
    "sg:phone":"+34 957 49 22 55",
    "sg:postcode":"14001",
    "sg:province":"C\u00f3rdoba",
    "wof:name":"Marquez Siles Jose",
    "wof:placetype":"venue"
},
  "geometry": {"coordinates":[-4.7685618401,37.8912391663],"type":"Point"}
}