{
  "type": "Feature",
  "properties": {
    "addr:full":"Muniello, 7 Prevera Asturias 33492",
    "addr:housenumber":"7",
    "addr:postcode":"33492",
    "addr:street":"Muniello;Asturias",
    "iso:country":"ES",
    "sg:address":"Muniello, 7",
    "sg:city":"Prevera",
    "sg:orig_category":"Distribuci\u00d3n De Petr\u00d3leo Y Derivados",
    "sg:phone":"+34 985 16 91 08",
    "sg:postcode":"33492",
    "sg:province":"Asturias",
    "wof:name":"Rodriguez Fernandez Jose Armando",
    "wof:placetype":"venue"
},
  "geometry": {"coordinates":[-5.7282118797,43.5552406311],"type":"Point"}
}