{
  "type": "Feature",
  "properties": {
    "addr:full":"Calle de Real, 14 Almendralejo Badajoz 06200",
    "addr:housenumber":"14",
    "addr:postcode":"06200",
    "addr:street":"Calle De Real",
    "iso:country":"ES",
    "sg:address":"Calle de Real, 14",
    "sg:city":"Almendralejo",
    "sg:orig_category":"Fabricaci\u00d3n, Venta De Productos Base Farmac\u00c9uticos",
    "sg:phone":"+34 924 66 20 38",
    "sg:postcode":"06200",
    "sg:province":"Badajoz",
    "wof:name":"Pacheco Rodriguez-malo Matilde",
    "wof:placetype":"venue"
},
  "geometry": {"coordinates":[-6.4080810547,38.6833572388],"type":"Point"}
}