{
  "type": "Feature",
  "properties": {
    "addr:full":"Calle de Artolategi, 9 Donostia-san Sebastian Guip\u00f9zcoa 20014",
    "addr:housenumber":"9",
    "addr:postcode":"20014",
    "addr:street":"Calle De Artolategi",
    "iso:country":"ES",
    "sg:address":"Calle de Artolategi, 9",
    "sg:city":"Donostia-san Sebastian",
    "sg:orig_category":"Geolog\u00cda Y Geof\u00cdsica",
    "sg:phone":"+34 943 46 88 73",
    "sg:postcode":"20014",
    "sg:province":"Guip\u00f9zcoa",
    "wof:name":"Leizaran Geologia Y Geotecnia S.l.",
    "wof:placetype":"venue"
},
  "geometry": {"coordinates":[-1.9553565979,43.295879364],"type":"Point"}
}