{
  "type": "Feature",
  "properties": {
    "iso:country":"ES",
    "sg:address":"Calle de Fuente, 5",
    "sg:city":"Adalia",
    "sg:orig_category":"Librer\u00cdas",
    "sg:phone":"+34 983 78 02 19",
    "sg:postcode":"47129",
    "sg:province":"Valladolid",
    "wof:name":"Elas 95 S.l.",
    "wof:placetype":"venue"
},
  "geometry": {"coordinates":[-5.1219549179,41.6478309631],"type":"Point"}
}