{
  "type": "Feature",
  "properties": {
    "iso:country":"ES",
    "sg:address":"Calle de Azorin, 8",
    "sg:city":"Gijon",
    "sg:orig_category":"Librer\u00cdas",
    "sg:phone":"+34 985 38 44 89",
    "sg:postcode":"33210",
    "sg:province":"Asturias",
    "wof:name":"Garcia Del Toro Aida",
    "wof:placetype":"venue"
},
  "geometry": {"coordinates":[-5.6701865196,43.5185966492],"type":"Point"}
}