{
  "type": "Feature",
  "properties": {
    "addr:full":"Plaz Santo Domingo El Sabio, 1 Zaragoza Zaragoza 50009",
    "addr:housenumber":"1",
    "addr:postcode":"50009",
    "addr:street":"El Sabio",
    "iso:country":"ES",
    "sg:address":"Plaz Santo Domingo El Sabio, 1",
    "sg:city":"Zaragoza",
    "sg:orig_category":"Equipo Y Material Deportivo Y De Actividades Invernales Y De Monta\u00d1a",
    "sg:phone":"+34 976 35 90 63",
    "sg:postcode":"50009",
    "sg:province":"Zaragoza",
    "wof:name":"Ayuntamiento De Zaragoza",
    "wof:placetype":"venue"
},
  "geometry": {"coordinates":[-0.9017390013,41.6468391418],"type":"Point"}
}