{
  "type": "Feature",
  "properties": {
    "iso:country":"ES",
    "sg:address":"Calle de Serapio Mugica, 26",
    "sg:city":"Irun",
    "sg:orig_category":"Cristaler\u00cdas",
    "sg:phone":"+34 943 61 23 53",
    "sg:postcode":"20302",
    "sg:province":"Guip\u00f9zcoa",
    "wof:name":"Tellexea Larreta Joseba",
    "wof:placetype":"venue"
},
  "geometry": {"coordinates":[-1.7966730595,43.3372612],"type":"Point"}
}