{
  "type": "Feature",
  "properties": {
    "iso:country":"ES",
    "sg:address":"Carr Masia De La Cova, 18",
    "sg:city":"Manises",
    "sg:orig_category":"Goma: Productos De Uso Industrial (fabricaci\u00d3n, Al Por Mayor)",
    "sg:phone":"+34 961 54 38 74",
    "sg:postcode":"46940",
    "sg:province":"Valencia",
    "sg:website":"www.webs.ono.com/xeyt/inicio.html",
    "wof:name":"Xerri Espumas Y Transformados S.l.",
    "wof:placetype":"venue"
},
  "geometry": {"coordinates":[-0.4617952108,39.4937934875],"type":"Point"}
}