{
  "type": "Feature",
  "properties": {
    "iso:country":"ES",
    "sg:address":"Ramon De Canagot, 20",
    "sg:city":"Alforja",
    "sg:orig_category":"Agricultores, Agricultores",
    "sg:phone":"+34 977 81 64 72",
    "sg:postcode":"43365",
    "sg:province":"Tarragona",
    "wof:name":"Granja Saludes Llopis C.b.",
    "wof:placetype":"venue"
},
  "geometry": {"coordinates":[0.9744119048,41.2105636597],"type":"Point"}
}