{
  "type": "Feature",
  "properties": {
    "iso:country":"ES",
    "sg:address":"Carrer de Doctor Gimbernat, 2",
    "sg:city":"Reus",
    "sg:orig_category":"\u00d3ptica: Instrumentos (fabricaci\u00d3n)",
    "sg:phone":"+34 977 33 25 75",
    "sg:postcode":"43205",
    "sg:province":"Tarragona",
    "sg:website":"www.opticamassull.com",
    "wof:name":"Optica Massull S.l.",
    "wof:placetype":"venue"
},
  "geometry": {"coordinates":[1.1053119898,41.1525535583],"type":"Point"}
}