{
  "type": "Feature",
  "properties": {
    "addr:full":"Av General Luque, 50 Inca Islas Baleares 07300",
    "addr:housenumber":"50",
    "addr:postcode":"07300",
    "addr:street":"Av General Luque",
    "iso:country":"ES",
    "sg:address":"Av General Luque, 50",
    "sg:city":"Inca",
    "sg:orig_category":"Arreglo, Reparaci\u00d3n, Piezas Sueltas De Televisi\u00d3n, V\u00cddeo, Hi",
    "sg:phone":"+34 971 50 43 14",
    "sg:postcode":"07300",
    "sg:province":"Islas Baleares",
    "wof:name":"Llompart Bergas Lucas",
    "wof:placetype":"venue"
},
  "geometry": {"coordinates":[2.9088139534,39.7195892334],"type":"Point"}
}