{
  "type": "Feature",
  "properties": {
    "addr:full":"Carrer de Rossello, 40 Hospitalet Llobregat Barcelona 08903",
    "addr:housenumber":"40",
    "addr:postcode":"08903",
    "addr:street":"Carrer De Rossello",
    "iso:country":"ES",
    "sg:address":"Carrer de Rossello, 40",
    "sg:city":"Hospitalet Llobregat",
    "sg:orig_category":"Mec\u00c1nico Del Autom\u00d3vil",
    "sg:phone":"+34 933 34 26 48",
    "sg:postcode":"08903",
    "sg:province":"Barcelona",
    "wof:name":"Escribano Millan Juan",
    "wof:placetype":"venue"
},
  "geometry": {"coordinates":[2.1255090237,41.3717041016],"type":"Point"}
}