{
  "type": "Feature",
  "properties": {
    "addr:full":"Calle de Postigo, 26 Caceres C\u00e1ceres 10003",
    "addr:housenumber":"26",
    "addr:postcode":"10003",
    "addr:street":"Calle De Postigo;Ca\u0301Ceres",
    "iso:country":"ES",
    "sg:address":"Calle de Postigo, 26",
    "sg:city":"Caceres",
    "sg:orig_category":"Empresarios Y Productoras De Espect\u00c1culos",
    "sg:phone":"+34 927 21 53 68",
    "sg:postcode":"10003",
    "sg:province":"C\u00e1ceres",
    "wof:name":"Paco Martin Producciones Artisticas S.l.",
    "wof:placetype":"venue"
},
  "geometry": {"coordinates":[-6.3721089363,39.4735794067],"type":"Point"}
}