{
  "type": "Feature",
  "properties": {
    "addr:full":"Pl. Abastos, S/n Cee La Coru\u00f1a 15270",
    "addr:housenumber":"s / n",
    "addr:postcode":"15270",
    "addr:street":"Abastos;La",
    "iso:country":"ES",
    "sg:address":"Pl. Abastos, S/n",
    "sg:city":"Cee",
    "sg:orig_category":"Carnicer\u00cdas, Carnicer\u00cdas",
    "sg:phone":"+34 981 74 59 26",
    "sg:postcode":"15270",
    "sg:province":"La Coru\u00f1a",
    "wof:name":"Lago Fandi\u00f1o Benigno",
    "wof:placetype":"venue"
},
  "geometry": {"coordinates":[-9.187494278,42.9554710388],"type":"Point"}
}