{
  "type": "Feature",
  "properties": {
    "iso:country":"ES",
    "sg:address":"Calle de Nieremberg, 21",
    "sg:city":"Madrid",
    "sg:orig_category":"Inform\u00c1tica (estudios, Servicios, Asesor\u00cda, Formaci\u00d3n)",
    "sg:phone":"+34 917 24 01 70",
    "sg:postcode":"28002",
    "sg:province":"Madrid",
    "wof:name":"Omega 2001 Servicios Informaticos S.l.",
    "wof:placetype":"venue"
},
  "geometry": {"coordinates":[-3.6723649502,40.4478645325],"type":"Point"}
}