{
  "type": "Feature",
  "properties": {
    "iso:country":"ES",
    "sg:address":"Trva Ciudad Jardin, 12",
    "sg:city":"Reinosa",
    "sg:orig_category":"Transportes Por V\u00cdas Navegables",
    "sg:phone":"+34 942 75 44 71",
    "sg:postcode":"39200",
    "sg:province":"Cantabria",
    "wof:name":"Ruiz Gutierrez Ubaldo",
    "wof:placetype":"venue"
},
  "geometry": {"coordinates":[-4.1444478035,42.9961395264],"type":"Point"}
}