{
  "type": "Feature",
  "properties": {
    "iso:country":"ES",
    "sg:address":"Avgd Francesc Macia, 35",
    "sg:city":"Lleida",
    "sg:orig_category":"Notarios",
    "sg:phone":"+34 973 23 67 97",
    "sg:postcode":"25007",
    "sg:province":"Lleida",
    "wof:name":"Chaves-prados Notarios Scp",
    "wof:placetype":"venue"
},
  "geometry": {"coordinates":[0.6286659837,41.6165504456],"type":"Point"}
}