{
  "type": "Feature",
  "properties": {
    "addr:full":"Calle de Pino Apolinario, 89 Palmas De Gran Canaria Las Palmas 35014",
    "addr:housenumber":"89",
    "addr:postcode":"35014",
    "addr:street":"Calle De Pino Apolinario",
    "iso:country":"ES",
    "sg:address":"Calle de Pino Apolinario, 89",
    "sg:city":"Palmas De Gran Canaria",
    "sg:orig_category":"Molduras, Junquillos, Listones Y Molduras Perforadas",
    "sg:phone":"+34 928 20 69 46",
    "sg:postcode":"35014",
    "sg:province":"Las Palmas",
    "wof:name":"Navarro Navarro Jose",
    "wof:placetype":"venue"
},
  "geometry": {"coordinates":[-15.4389286041,28.09491539],"type":"Point"}
}