{
  "type": "Feature",
  "properties": {
    "addr:full":"Rua Cabeza De Manzaneda, 6 Ourense Ourense 32005",
    "addr:housenumber":"6",
    "addr:postcode":"32005",
    "addr:street":"Rua Cabeza De Manzaneda",
    "iso:country":"ES",
    "sg:address":"Rua Cabeza De Manzaneda, 6",
    "sg:city":"Ourense",
    "sg:orig_category":"Caf\u00c9s, Bares, Cervecer\u00cdas",
    "sg:phone":"+34 988 25 03 16",
    "sg:postcode":"32005",
    "sg:province":"Ourense",
    "wof:name":"Juan Carlos Sampayo Boan Y Otra S.cv.",
    "wof:placetype":"venue"
},
  "geometry": {"coordinates":[-7.8620100021,42.3353500366],"type":"Point"}
}