{
  "type": "Feature",
  "properties": {
    "addr:full":"Calle de Monteverde, 31 Madrid Madrid 28042",
    "addr:housenumber":"31",
    "addr:postcode":"madrid;28042",
    "addr:street":"Calle De Monteverde",
    "iso:country":"ES",
    "sg:address":"Calle de Monteverde, 31",
    "sg:city":"Madrid",
    "sg:orig_category":"Arquitectos",
    "sg:phone":"+34 913 71 70 17",
    "sg:postcode":"28042",
    "sg:province":"Madrid",
    "wof:name":"Arkias Arquitectura S.l",
    "wof:placetype":"venue"
},
  "geometry": {"coordinates":[-3.5955405235,40.4588127136],"type":"Point"}
}