{
  "type": "Feature",
  "properties": {
    "addr:full":"Las Margaritas, S/n S. Agustin-playa Ingles Las Palmas 35100",
    "addr:postcode":"35100",
    "addr:street":"Las Margaritas S / N S. Agustin-Playa",
    "iso:country":"ES",
    "sg:address":"Las Margaritas, S/n",
    "sg:city":"S. Agustin-playa Ingles",
    "sg:orig_category":"Internados & Ense\u00d1anza Privada",
    "sg:phone":"+34 928 76 13 38",
    "sg:postcode":"35100",
    "sg:province":"Las Palmas",
    "wof:name":"Arenas School S.l.",
    "wof:placetype":"venue"
},
  "geometry": {"coordinates":[-15.549870491,27.7691860199],"type":"Point"}
}