{
  "type": "Feature",
  "properties": {
    "addr:full":"Av Joan Xxiii, 14 Gava Barcelona 08850",
    "addr:housenumber":"14",
    "addr:postcode":"08850",
    "addr:street":"Av Joan Xxiii",
    "iso:country":"ES",
    "sg:address":"Av Joan Xxiii, 14",
    "sg:city":"Gava",
    "sg:orig_category":"Molduras, Junquillos, Listones Y Molduras Perforadas",
    "sg:phone":"+34 936 62 45 02",
    "sg:postcode":"08850",
    "sg:province":"Barcelona",
    "wof:name":"Sepulveda Valencia Maria Victoria",
    "wof:placetype":"venue"
},
  "geometry": {"coordinates":[2.0025680065,41.3094291687],"type":"Point"}
}