{
  "type": "Feature",
  "properties": {
    "iso:country":"ES",
    "sg:address":"Carr Ensenyan\u00c7a, 3",
    "sg:city":"Borges Blanques",
    "sg:orig_category":"Laboratorios Y Trabajos De Fotograf\u00cda, V\u00cddeo Y Cine",
    "sg:phone":"+34 973 14 23 39",
    "sg:postcode":"25400",
    "sg:province":"Lleida",
    "wof:name":"Pedrol Segarra Guillen",
    "wof:placetype":"venue"
},
  "geometry": {"coordinates":[0.8711360097,41.5198669434],"type":"Point"}
}