{
  "type": "Feature",
  "properties": {
    "iso:country":"ES",
    "sg:address":"Carrer de Cala Blanca, 2",
    "sg:city":"Palma",
    "sg:orig_category":"Seguridad En El Trabajo Y Prevenci\u00d3n De Riesgos Laborales",
    "sg:phone":"+34 971 44 44 14",
    "sg:postcode":"07009",
    "sg:province":"Islas Baleares",
    "wof:name":"Mapema Mir-serra S.l.",
    "wof:placetype":"venue"
},
  "geometry": {"coordinates":[2.6770529747,39.5969390869],"type":"Point"}
}