{
  "type": "Feature",
  "properties": {
    "addr:full":"Calle de Procion, 47 Alacant Alicante 03006",
    "addr:housenumber":"47",
    "addr:postcode":"03006",
    "addr:street":"Calle De Procion",
    "iso:country":"ES",
    "sg:address":"Calle de Procion, 47",
    "sg:city":"Alacant",
    "sg:orig_category":"Servicios De Telecomunicaciones",
    "sg:phone":"+34 965 10 67 03",
    "sg:postcode":"03006",
    "sg:province":"Alicante",
    "wof:name":"Telecal S.a.",
    "wof:placetype":"venue"
},
  "geometry": {"coordinates":[-0.513974905,38.3457946777],"type":"Point"}
}