{
  "type": "Feature",
  "properties": {
    "iso:country":"ES",
    "sg:address":"Carrer de Manuel Arnus, S/n",
    "sg:city":"Barcelona",
    "sg:orig_category":"Obras Y Organismos Sociales",
    "sg:phone":"+34 934 18 35 06",
    "sg:postcode":"08035",
    "sg:province":"Barcelona",
    "wof:name":"Fundacion Antoni Serra Santamans",
    "wof:placetype":"venue"
},
  "geometry": {"coordinates":[2.1324260235,41.4165916443],"type":"Point"}
}