{
  "type": "Feature",
  "properties": {
    "addr:full":"Poli Merinals, 69 Sabadell Barcelona 08205",
    "addr:housenumber":"69",
    "addr:postcode":"08205",
    "addr:street":"Merinals",
    "iso:country":"ES",
    "sg:address":"Poli Merinals, 69",
    "sg:city":"Sabadell",
    "sg:orig_category":"Inform\u00c1tica: Mantenimiento Y Reparaci\u00d3n De Ordenadores",
    "sg:phone":"+34 937 25 01 30",
    "sg:postcode":"08205",
    "sg:province":"Barcelona",
    "sg:website":"www.inforsab.com",
    "wof:name":"Hernandez Rodriguez Jose Luis",
    "wof:placetype":"venue"
},
  "geometry": {"coordinates":[2.0880498886,41.5456695557],"type":"Point"}
}