{
  "type": "Feature",
  "properties": {
    "addr:full":"Calle de Viriato, 31 Villanueva Serena Badajoz 06700",
    "addr:housenumber":"31",
    "addr:postcode":"06700",
    "addr:street":"Calle De Viriato",
    "iso:country":"ES",
    "sg:address":"Calle de Viriato, 31",
    "sg:city":"Villanueva Serena",
    "sg:orig_category":"Doctores En Medicina",
    "sg:phone":"+34 924 84 57 12",
    "sg:postcode":"06700",
    "sg:province":"Badajoz",
    "wof:name":"Garcia Barcelo Maria Victoria",
    "wof:placetype":"venue"
},
  "geometry": {"coordinates":[-5.7964191437,38.9737014771],"type":"Point"}
}