{
  "type": "Feature",
  "properties": {
    "addr:full":"Carrer de Marques De Campo, 40 Denia Alicante 03700",
    "addr:housenumber":"40",
    "addr:postcode":"03700",
    "addr:street":"Carrer De Marques De Campo",
    "iso:country":"ES",
    "sg:address":"Carrer de Marques De Campo, 40",
    "sg:city":"Denia",
    "sg:orig_category":"M\u00c9dicos: Oftalmolog\u00cda",
    "sg:phone":"+34 965 78 75 05",
    "sg:postcode":"03700",
    "sg:province":"Alicante",
    "wof:name":"Didovic  Olga",
    "wof:placetype":"venue"
},
  "geometry": {"coordinates":[0.1092789993,38.8404541016],"type":"Point"}
}