{
  "type": "Feature",
  "properties": {
    "addr:full":"Eras De Abajo, 19 Trobajo Camino Le\u00f3n 24010",
    "addr:housenumber":"19",
    "addr:postcode":"24010",
    "addr:street":"Abajo;Camino Leo\u0301N",
    "iso:country":"ES",
    "sg:address":"Eras De Abajo, 19",
    "sg:city":"Trobajo Camino",
    "sg:orig_category":"Ebanister\u00cda",
    "sg:phone":"+34 987 80 11 60",
    "sg:postcode":"24010",
    "sg:province":"Le\u00f3n",
    "wof:name":"Muebles Urdiales, C.b.",
    "wof:placetype":"venue"
},
  "geometry": {"coordinates":[-5.5716600418,42.5981292725],"type":"Point"}
}