{
  "type": "Feature",
  "properties": {
    "iso:country":"ES",
    "sg:address":"Calle de Brasil, 7",
    "sg:city":"Vitoria-gasteiz",
    "sg:orig_category":"Empresas De Pintura Y Revestimientos",
    "sg:phone":"+34 945 27 45 20",
    "sg:postcode":"01012",
    "sg:province":"\u00c1lava",
    "wof:name":"Garcia Martin Miguel",
    "wof:placetype":"venue"
},
  "geometry": {"coordinates":[-2.6788129807,42.8586463928],"type":"Point"}
}