{
  "type": "Feature",
  "properties": {
    "addr:full":"Azeri Kalea, 7 Arrasate Guip\u00f9zcoa 20500",
    "addr:housenumber":"7",
    "addr:postcode":"20500",
    "addr:street":"Azeri Kalea;Guipu\u0300Zcoa",
    "iso:country":"ES",
    "sg:address":"Azeri Kalea, 7",
    "sg:city":"Arrasate",
    "sg:orig_category":"Empresas De Portes Y Mensajer\u00cda",
    "sg:phone":"+34 943 79 92 77",
    "sg:postcode":"20500",
    "sg:province":"Guip\u00f9zcoa",
    "wof:name":"Euskonacex S.a.",
    "wof:placetype":"venue"
},
  "geometry": {"coordinates":[-2.494328022,43.0583953857],"type":"Point"}
}