{
  "type": "Feature",
  "properties": {
    "addr:full":"Carrer de Paisos Catalans, 4 S. Just Desvern Barcelona 08960",
    "addr:housenumber":"4",
    "addr:postcode":"08960",
    "addr:street":"Carrer De Paisos Catalans",
    "iso:country":"ES",
    "sg:address":"Carrer de Paisos Catalans, 4",
    "sg:city":"S. Just Desvern",
    "sg:orig_category":"Restaurantes",
    "sg:phone":"+34 933 71 55 49",
    "sg:postcode":"08960",
    "sg:province":"Barcelona",
    "wof:name":"Europea Restauracio I Alimentacio S.l.",
    "wof:placetype":"venue"
},
  "geometry": {"coordinates":[2.0791859627,41.3777389526],"type":"Point"}
}