{
  "type": "Feature",
  "properties": {
    "iso:country":"ES",
    "sg:address":"Urb Torre Moya, S/n",
    "sg:city":"Benajarafe",
    "sg:orig_category":"Negocio De Enlosados, Soler\u00cdas",
    "sg:phone":"+34 952 51 41 40",
    "sg:postcode":"29790",
    "sg:province":"M\u00e1laga",
    "wof:name":"Ramirez Llanos Jose Manuel",
    "wof:placetype":"venue"
},
  "geometry": {"coordinates":[-4.2237138748,36.7277183533],"type":"Point"}
}