{
  "type": "Feature",
  "properties": {
    "addr:full":"Carrer de Sant Francesc Xavier, 34 Barcelona Barcelona 08016",
    "addr:housenumber":"34",
    "addr:postcode":"08016",
    "addr:street":"Carrer De Sant Francesc Xavier",
    "iso:country":"ES",
    "sg:address":"Carrer de Sant Francesc Xavier, 34",
    "sg:city":"Barcelona",
    "sg:orig_category":"Peluquer\u00cdas, Peluquer\u00cda Mixta",
    "sg:phone":"+34 933 53 87 83",
    "sg:postcode":"08016",
    "sg:province":"Barcelona",
    "wof:name":"Pamair S.c.p.",
    "wof:placetype":"venue"
},
  "geometry": {"coordinates":[2.1790521145,41.4409332275],"type":"Point"}
}