{
  "type": "Feature",
  "properties": {
    "addr:full":"Calle de Paris, 4 Sonseca Toledo 45100",
    "addr:housenumber":"4",
    "addr:postcode":"45100",
    "addr:street":"Calle De Paris",
    "iso:country":"ES",
    "sg:address":"Calle de Paris, 4",
    "sg:city":"Sonseca",
    "sg:orig_category":"Lencer\u00cda Femenina, Corseter\u00cda, Trajes De Ba\u00d1o (al Por Menor)",
    "sg:phone":"+34 925 38 17 20",
    "sg:postcode":"45100",
    "sg:province":"Toledo",
    "wof:name":"Pereira Alfonso Maria Fatima",
    "wof:placetype":"venue"
},
  "geometry": {"coordinates":[-3.9829540253,39.6811599731],"type":"Point"}
}