{
  "type": "Feature",
  "properties": {
    "addr:full":"C/ Jaime Pomares Javaloyes, 12 Elche Alicante 03202",
    "addr:housenumber":"12",
    "addr:postcode":"03202",
    "addr:street":"C / Jaime Pomares Javaloyes",
    "iso:country":"ES",
    "sg:address":"C/ Jaime Pomares Javaloyes, 12",
    "sg:city":"Elche",
    "sg:orig_category":"Iglesia Cat\u00d3lica",
    "sg:phone":"+34 965 45 80 17",
    "sg:postcode":"03202",
    "sg:province":"Alicante",
    "wof:name":"Parroquia San Vicente Ferrer",
    "wof:placetype":"venue"
},
  "geometry": {"coordinates":[-0.6827579737,38.2721290588],"type":"Point"}
}