{
  "type": "Feature",
  "properties": {
    "iso:country":"ES",
    "sg:address":"Avda Federico Silva, 1",
    "sg:city":"Benavente",
    "sg:orig_category":"Alimentaci\u00d3n General (al Por Menor)",
    "sg:phone":"+34 980 63 27 54",
    "sg:postcode":"49600",
    "sg:province":"Zamora",
    "wof:name":"Fernandez Gelado Juan Francisco",
    "wof:placetype":"venue"
},
  "geometry": {"coordinates":[-5.6582942009,41.9968681335],"type":"Point"}
}