{
  "type": "Feature",
  "properties": {
    "iso:country":"ES",
    "sg:address":"Calle de Ponjalucho, S/n",
    "sg:city":"Villabalter",
    "sg:orig_category":"Empresas De Carpinter\u00cda Met\u00c1lica",
    "sg:phone":"+34 987 84 67 15",
    "sg:postcode":"24010",
    "sg:province":"Le\u00f3n",
    "wof:name":"H.costales E Hijo S.l.",
    "wof:placetype":"venue"
},
  "geometry": {"coordinates":[-5.6172580719,42.6228561401],"type":"Point"}
}