{
  "type": "Feature",
  "properties": {
    "addr:full":"Calle de Castilla Perez, 3 Nerja M\u00e1laga 29780",
    "addr:housenumber":"3",
    "addr:postcode":"29780",
    "addr:street":"Calle De Castilla Perez",
    "iso:country":"ES",
    "sg:address":"Calle de Castilla Perez, 3",
    "sg:city":"Nerja",
    "sg:orig_category":"Sociedades, Compa\u00d1\u00cdas Aseguradoras",
    "sg:phone":"+34 952 52 31 50",
    "sg:postcode":"29780",
    "sg:province":"M\u00e1laga",
    "wof:name":"Mapfre Servicios De Informatica",
    "wof:placetype":"venue"
},
  "geometry": {"coordinates":[-3.8799479008,36.7452430725],"type":"Point"}
}