{
  "type": "Feature",
  "properties": {
    "addr:full":"Calle de San Buenaventura, 21 Medina Rioseco Valladolid 47800",
    "addr:housenumber":"21",
    "addr:postcode":"47800",
    "addr:street":"Calle De San Buenaventura",
    "iso:country":"ES",
    "sg:address":"Calle de San Buenaventura, 21",
    "sg:city":"Medina Rioseco",
    "sg:orig_category":"Reposter\u00cdas",
    "sg:phone":"+34 983 70 04 93",
    "sg:postcode":"47800",
    "sg:province":"Valladolid",
    "wof:name":"La Flor De Castilla-medina De Rioseco S.l.",
    "wof:placetype":"venue"
},
  "geometry": {"coordinates":[-5.0400414467,41.8818016052],"type":"Point"}
}