{
  "type": "Feature",
  "properties": {
    "addr:full":"Calle de Orbigo, 24 Barrio De Pinilla Le\u00f3n 24010",
    "addr:housenumber":"24",
    "addr:postcode":"24010",
    "addr:street":"Calle De Orbigo",
    "iso:country":"ES",
    "sg:address":"Calle de Orbigo, 24",
    "sg:city":"Barrio De Pinilla",
    "sg:orig_category":"Centros Comerciales Y Grandes Tiendas",
    "sg:phone":"+34 987 27 10 05",
    "sg:postcode":"24010",
    "sg:province":"Le\u00f3n",
    "wof:name":"Garcia Rubial Monica",
    "wof:placetype":"venue"
},
  "geometry": {"coordinates":[-5.5918388367,42.6046295166],"type":"Point"}
}