{
  "type": "Feature",
  "properties": {
    "iso:country":"ES",
    "sg:address":"Pg Catalunya, 79",
    "sg:city":"Torroella Montgri",
    "sg:orig_category":"Florister\u00cdas",
    "sg:phone":"+34 972 76 15 69",
    "sg:postcode":"17257",
    "sg:province":"Girona",
    "wof:name":"Floristeria Vivaldi S.c.",
    "wof:placetype":"venue"
},
  "geometry": {"coordinates":[3.1277420521,42.042766571],"type":"Point"}
}