{
  "type": "Feature",
  "properties": {
    "iso:country":"ES",
    "sg:address":"Calle de Monasterio De Samos, 8",
    "sg:city":"Zaragoza",
    "sg:orig_category":"Asociaciones Humanitarias, De Cooperaci\u00d3n, De Acci\u00d3n Social",
    "sg:phone":"+34 976 41 29 11",
    "sg:postcode":"50013",
    "sg:province":"Zaragoza",
    "wof:name":"Asociacion Familiares Enfermos De Alzheimer",
    "wof:placetype":"venue"
},
  "geometry": {"coordinates":[-0.8723704219,41.6416740417],"type":"Point"}
}