{
  "type": "Feature",
  "properties": {
    "addr:full":"Carrer de Sant Vicen\u00c7, 46 Santa Coloma De Queralt Tarragona 43420",
    "addr:housenumber":"46",
    "addr:postcode":"43420",
    "addr:street":"Carrer De Sant Vicenc\u0327",
    "iso:country":"ES",
    "sg:address":"Carrer de Sant Vicen\u00c7, 46",
    "sg:city":"Santa Coloma De Queralt",
    "sg:orig_category":"Agentes Generales De Seguros",
    "sg:phone":"+34 977 88 10 16",
    "sg:postcode":"43420",
    "sg:province":"Tarragona",
    "wof:name":"Ballabriga Palau Joaquin",
    "wof:placetype":"venue"
},
  "geometry": {"coordinates":[1.3821057081,41.5325737],"type":"Point"}
}