{
  "type": "Feature",
  "properties": {
    "addr:full":"Calle de Henry Dunant, 23 Palmas De Gran Canaria Las Palmas 35011",
    "addr:housenumber":"23",
    "addr:postcode":"35011",
    "addr:street":"Calle De Henry Dunant",
    "iso:country":"ES",
    "sg:address":"Calle de Henry Dunant, 23",
    "sg:city":"Palmas De Gran Canaria",
    "sg:orig_category":"Farmacias",
    "sg:phone":"+34 928 25 58 20",
    "sg:postcode":"35011",
    "sg:province":"Las Palmas",
    "wof:name":"Abelda Mora Concepcion Amparo",
    "wof:placetype":"venue"
},
  "geometry": {"coordinates":[-15.439025,28.12388],"type":"Point"}
}