{
  "type": "Feature",
  "properties": {
    "addr:full":"Av Generalitat (de La), 112 Tortosa Tarragona 43500",
    "addr:housenumber":"112",
    "addr:postcode":"43500",
    "addr:street":"Av Generalitat De La",
    "iso:country":"ES",
    "sg:address":"Av Generalitat (de La), 112",
    "sg:city":"Tortosa",
    "sg:orig_category":"Prot\u00c9sicos Dentales",
    "sg:phone":"+34 977 44 32 89",
    "sg:postcode":"43500",
    "sg:province":"Tarragona",
    "wof:name":"Riba Crespo Mariana",
    "wof:placetype":"venue"
},
  "geometry": {"coordinates":[0.5202980042,40.803653717],"type":"Point"}
}