{
  "type": "Feature",
  "properties": {
    "addr:full":"Calle de Carcel, 11 Fregenal Sierra Badajoz 06340",
    "addr:housenumber":"11",
    "addr:postcode":"06340",
    "addr:street":"Calle De Carcel",
    "iso:country":"ES",
    "sg:address":"Calle de Carcel, 11",
    "sg:city":"Fregenal Sierra",
    "sg:orig_category":"Procuradores",
    "sg:phone":"+34 924 70 03 51",
    "sg:postcode":"06340",
    "sg:province":"Badajoz",
    "wof:name":"Cuesta Martin Ana Maria Dolores",
    "wof:placetype":"venue"
},
  "geometry": {"coordinates":[-6.6534733772,38.169178009],"type":"Point"}
}