{
  "type": "Feature",
  "properties": {
    "addr:full":"Calle de Pedro Alonso Ni\u00d1o, 1 Huelva Huelva 21006",
    "addr:housenumber":"1",
    "addr:postcode":"21006",
    "addr:street":"Calle De Pedro Alonso Nin\u0303O",
    "iso:country":"ES",
    "sg:address":"Calle de Pedro Alonso Ni\u00d1o, 1",
    "sg:city":"Huelva",
    "sg:orig_category":"Organizaciones Internacionales",
    "sg:phone":"+34 959 23 66 66",
    "sg:postcode":"21006",
    "sg:province":"Huelva",
    "wof:name":"Federacion De Mujeres Progresistas Por La Igualdad De Andalucia",
    "wof:placetype":"venue"
},
  "geometry": {"coordinates":[-6.9364008904,37.2573928833],"type":"Point"}
}