{
  "type": "Feature",
  "properties": {
    "addr:full":"Calle de Magacela, 33 Villanueva Serena Badajoz 06700",
    "addr:housenumber":"33",
    "addr:postcode":"06700",
    "addr:street":"Calle De Magacela",
    "iso:country":"ES",
    "sg:address":"Calle de Magacela, 33",
    "sg:city":"Villanueva Serena",
    "sg:orig_category":"Peluqueros: De Se\u00d1oras",
    "sg:phone":"+34 924 84 48 32",
    "sg:postcode":"06700",
    "sg:province":"Badajoz",
    "wof:name":"Mera Rejas Elvira",
    "wof:placetype":"venue"
},
  "geometry": {"coordinates":[-5.7980179787,38.9716758728],"type":"Point"}
}