{
  "type": "Feature",
  "properties": {
    "addr:full":"Calle de Tomas Lopez Torregrosa, 1 Alacant Alicante 03002",
    "addr:housenumber":"1",
    "addr:postcode":"03002",
    "addr:street":"Calle De Tomas Lopez Torregrosa",
    "iso:country":"ES",
    "sg:address":"Calle de Tomas Lopez Torregrosa, 1",
    "sg:city":"Alacant",
    "sg:orig_category":"Bares, Piano",
    "sg:phone":"+34 965 21 33 34",
    "sg:postcode":"03002",
    "sg:province":"Alicante",
    "wof:name":"John Mulligan's S.l.",
    "wof:placetype":"venue"
},
  "geometry": {"coordinates":[-0.4848920107,38.3469352722],"type":"Point"}
}