{
  "type": "Feature",
  "properties": {
    "iso:country":"ES",
    "sg:address":"Calle de Pozo, 8",
    "sg:city":"Puebla De Los Infantes",
    "sg:orig_category":"Empresas De Desmonte",
    "sg:phone":"+34 954 80 84 36",
    "sg:postcode":"41479",
    "sg:province":"Sevilla",
    "wof:name":"Martinico Movimientos De Tierra S.c.",
    "wof:placetype":"venue"
},
  "geometry": {"coordinates":[-5.3888697624,37.7781639099],"type":"Point"}
}