{
  "type": "Feature",
  "properties": {
    "iso:country":"ES",
    "sg:address":"Calle de Narvaez, 6",
    "sg:city":"Madrid",
    "sg:orig_category":"Bisuter\u00cda, Joyer\u00cda, Relojer\u00cda (al Por Menor)",
    "sg:phone":"+34 915 76 44 50",
    "sg:postcode":"28009",
    "sg:province":"Madrid",
    "wof:name":"Sanchez De Las Matas Sanchez Juan",
    "wof:placetype":"venue"
},
  "geometry": {"coordinates":[-3.6760098934,40.4235458374],"type":"Point"}
}