{
  "type": "Feature",
  "properties": {
    "iso:country":"ES",
    "sg:address":"Centeno, 34",
    "sg:city":"Ferreras Arriba",
    "sg:orig_category":"Molduras, Junquillos, Listones Y Molduras Perforadas",
    "sg:phone":"+34 980 59 31 34",
    "sg:postcode":"49335",
    "sg:province":"Zamora",
    "wof:name":"Andres Fernandez Tomas",
    "wof:placetype":"venue"
},
  "geometry": {"coordinates":[-5.7462787628,41.5033454895],"type":"Point"}
}